{
  "type": "Feature",
  "properties": {
    "iso:country":"IT",
    "sg:address":"24, Via G. Carducci 05023 Baschi",
    "sg:city":"Baschi",
    "sg:classifiers":[
        {
            "category":"Manufacturing",
            "subcategory":"Lumber",
            "type":"Manufacturing & Wholesale Goods"
        }
    ],
    "sg:phone":"+39 0744 952016",
    "sg:postcode":"05023",
    "sg:province":"Terni",
    "sg:tags":[
        "wood"
    ],
    "wof:name":"3 Erre B Snc Di Buia Manlio E C.",
    "wof:placetype":"venue"
},
  "geometry": {"coordinates":[12.646781,42.560219],"type":"Point"}
}