{
  "type": "Feature",
  "properties": {
    "iso:country":"IT",
    "sg:address":"35012 Camposampiero",
    "sg:city":"Camposampiero",
    "sg:orig_category":"Bagno - Accessori E Mobili",
    "sg:phone":"+39 049 930 0161",
    "sg:postcode":"35012",
    "sg:province":"Padova",
    "sg:website":"http://www.kristallux.it",
    "wof:name":"Kristallux Spa",
    "wof:placetype":"venue"
},
  "geometry": {"coordinates":[11.935573,45.399872],"type":"Point"}
}