{
  "type": "Feature",
  "properties": {
    "addr:full":"Via Ca Bianca 1 21052 Busto Arsizio Busto Arsizio Varese 21052",
    "addr:housenumber":"1",
    "addr:postcode":"21052;21052",
    "addr:street":"Via Ca Bianca",
    "iso:country":"IT",
    "sg:address":"Via Ca Bianca 1 21052 Busto Arsizio",
    "sg:city":"Busto Arsizio",
    "sg:classifiers":[
        {
            "category":"Banks & Credit Unions",
            "subcategory":"Investment Brokerage",
            "type":"Services"
        }
    ],
    "sg:phone":"+39 0331 631949",
    "sg:postcode":"21052",
    "sg:province":"Varese",
    "sg:tags":[
        "textile",
        "machine"
    ],
    "sg:website":"www.guarneri.it",
    "wof:name":"Officina Meccanica Guarneri Snc Di Tullio Guarneri E C.",
    "wof:placetype":"venue"
},
  "geometry": {"coordinates":[8.871796,45.611641],"type":"Point"}
}