{
  "type": "Feature",
  "properties": {
    "iso:country":"IT",
    "sg:address":"28845 Domodossola",
    "sg:city":"Domodossola",
    "sg:orig_category":"Servizi Per Lo Sport E Il Tempo Libero. Servizi Al Turismo",
    "sg:phone":"+39 0324 242722",
    "sg:postcode":"28845",
    "sg:province":"Verbano-Cusio-Ossola",
    "wof:name":"Domobianca",
    "wof:placetype":"venue"
},
  "geometry": {"coordinates":[8.30128,46.110435],"type":"Point"}
}