{
  "type": "Feature",
  "properties": {
    "addr:full":"80011 Acerra Acerra Napoli 80011",
    "addr:postcode":"80011;80011",
    "iso:country":"IT",
    "sg:address":"80011 Acerra",
    "sg:city":"Acerra",
    "sg:orig_category":"Zootecnia E Pesca, Allevamento Piccoli Animali. Animali Domestici",
    "sg:phone":"+39 081 520 8288",
    "sg:postcode":"80011",
    "sg:province":"Napoli",
    "wof:name":"La Fauna Sas Di De Sena",
    "wof:placetype":"venue"
},
  "geometry": {"coordinates":[14.369511,40.943405],"type":"Point"}
}