{
  "type": "Feature",
  "properties": {
    "addr:full":"1, Via Carnia 33078 San Vito Al Tagliamento San Vito al Tagliamento Pordenone 33078",
    "addr:postcode":"33078;33078",
    "addr:street":"Via Carnia",
    "iso:country":"IT",
    "sg:address":"1, Via Carnia 33078 San Vito Al Tagliamento",
    "sg:city":"San Vito al Tagliamento",
    "sg:classifiers":[
        {
            "category":"Manufacturing",
            "subcategory":"Food",
            "type":"Manufacturing & Wholesale Goods"
        }
    ],
    "sg:phone":"+39 0434 857000",
    "sg:postcode":"33078",
    "sg:province":"Pordenone",
    "sg:tags":[
        "equipment",
        "processing",
        "-",
        "machinery"
    ],
    "wof:name":"Pizza Group S.r.l.",
    "wof:placetype":"venue"
},
  "geometry": {"coordinates":[12.655043602,45.9626502991],"type":"Point"}
}