{
  "type": "Feature",
  "properties": {
    "iso:country":"IT",
    "sg:address":"98, Via Madonna Del Ponte 90041 Balestrate",
    "sg:city":"Balestrate",
    "sg:classifiers":[
        {
            "category":"Building & Trades",
            "subcategory":"Construction",
            "type":"Services"
        }
    ],
    "sg:phone":"+39 091 898 7282",
    "sg:postcode":"90041",
    "sg:province":"Palermo",
    "sg:tags":[
        "work",
        "public"
    ],
    "wof:name":"Cataldo Costruzioni S.r.l.",
    "wof:placetype":"venue"
},
  "geometry": {"coordinates":[13.00185,38.049908],"type":"Point"}
}