{
  "type": "Feature",
  "properties": {
    "addr:full":"23018 Talamona Talamona Sondrio 23018",
    "addr:postcode":"23018;23018",
    "iso:country":"IT",
    "sg:address":"23018 Talamona",
    "sg:city":"Talamona",
    "sg:orig_category":"Prodotti Alimentari",
    "sg:phone":"+39 0342 670304",
    "sg:postcode":"23018",
    "sg:province":"Sondrio",
    "wof:name":"Demetra Srl",
    "wof:placetype":"venue"
},
  "geometry": {"coordinates":[9.602186203,46.1390151978],"type":"Point"}
}