{
  "type": "Feature",
  "properties": {
    "iso:country":"IT",
    "sg:address":"74100 Taranto",
    "sg:city":"Taranto",
    "sg:orig_category":"Servizi E Lavori Per Agricoltura E Zootecnia",
    "sg:phone":"+39 099 459 5847",
    "sg:postcode":"74100",
    "sg:province":"Taranto",
    "wof:name":"Associazione Provinciale Allevatori Taranto",
    "wof:placetype":"venue"
},
  "geometry": {"coordinates":[17.2380409241,40.474319458],"type":"Point"}
}