{
  "type": "Feature",
  "properties": {
    "iso:country":"IT",
    "sg:address":"83, Via Alessandro Volta 20090 Cusago",
    "sg:city":"Cusago",
    "sg:orig_category":"Miscellaneous Products",
    "sg:phone":"+39 390 290 2561",
    "sg:postcode":"20090",
    "sg:province":"Milano",
    "wof:name":"Itw Elettro Gibi Divisione Itw Industrial Components Srl",
    "wof:placetype":"venue"
},
  "geometry": {"coordinates":[9.0471324921,45.4417610168],"type":"Point"}
}