{
  "type": "Feature",
  "properties": {
    "addr:full":"Ctr. Fiastra 27/h 62014 Petriolo Petriolo Macerata 62014",
    "addr:housenumber":"27 / h",
    "addr:postcode":"62014;62014",
    "addr:street":"Fiastra",
    "iso:country":"IT",
    "sg:address":"Ctr. Fiastra 27/h 62014 Petriolo",
    "sg:city":"Petriolo",
    "sg:classifiers":[
        {
            "category":"Shopping",
            "subcategory":"Used Merchandise",
            "type":"Retail Goods"
        }
    ],
    "sg:phone":"+39 0733 550226",
    "sg:postcode":"62014",
    "sg:province":"Macerata",
    "sg:tags":[
        "ribbon"
    ],
    "wof:name":"M.c.i. Spa - Metallurgica Centro Italia",
    "wof:placetype":"venue"
},
  "geometry": {"coordinates":[13.456262,43.300747],"type":"Point"}
}