{
  "type": "Feature",
  "properties": {
    "iso:country":"IT",
    "sg:address":"50019 Sesto Fiorentino",
    "sg:city":"Sesto Fiorentino",
    "sg:orig_category":"Pompe. Macchine, Strumenti Ed Apparecchi Per Attivita' Industriali",
    "sg:phone":"+39 055 316130",
    "sg:postcode":"50019",
    "sg:province":"Firenze",
    "wof:name":"Italthermo Spa",
    "wof:placetype":"venue"
},
  "geometry": {"coordinates":[11.1749010086,43.8048248291],"type":"Point"}
}