{
  "type": "Feature",
  "properties": {
    "iso:country":"IT",
    "sg:address":"Via Fabrega 36033 Isola Vicentina",
    "sg:city":"Isola Vicentina",
    "sg:classifiers":[
        {
            "category":"Manufacturing",
            "subcategory":"Rubber & Plastics",
            "type":"Manufacturing & Wholesale Goods"
        }
    ],
    "sg:phone":"+39 0444 975766",
    "sg:postcode":"36033",
    "sg:province":"Vicenza",
    "wof:name":"Sirte S.p.a.",
    "wof:placetype":"venue"
},
  "geometry": {"coordinates":[11.4820346832,45.6089248657],"type":"Point"}
}