{
  "type": "Feature",
  "properties": {
    "iso:country":"IT",
    "sg:address":"44011 Argenta",
    "sg:city":"Argenta",
    "sg:orig_category":"Materiali Edili",
    "sg:phone":"+39 0532 318222",
    "sg:postcode":"44011",
    "sg:province":"Ferrara",
    "wof:name":"Tecnoform Srl",
    "wof:placetype":"venue"
},
  "geometry": {"coordinates":[11.825068,44.63097],"type":"Point"}
}