{
  "type": "Feature",
  "properties": {
    "iso:country":"IT",
    "sg:address":"96019 Rosolini",
    "sg:city":"Rosolini",
    "sg:classifiers":[
        {
            "category":"Health Services",
            "subcategory":"Nursing And Care Facility",
            "type":"Services"
        }
    ],
    "sg:phone":"+39 0931 855059",
    "sg:postcode":"96019",
    "sg:province":"Siracusa",
    "sg:tags":[
        "case",
        "cura",
        "private",
        "di"
    ],
    "wof:name":"Casa Protetta Villa Rosa Sas",
    "wof:placetype":"venue"
},
  "geometry": {"coordinates":[15.297523,37.084827],"type":"Point"}
}