{
  "type": "Feature",
  "properties": {
    "iso:country":"IT",
    "sg:address":"19, Via Giovanni Ventitreesimo 23873 Missaglia",
    "sg:city":"Missaglia",
    "sg:classifiers":[
        {
            "category":"Professional",
            "subcategory":"Printing & Photocopies",
            "type":"Services"
        }
    ],
    "sg:phone":"+39 039 924 1621",
    "sg:postcode":"23873",
    "sg:province":"Lecco",
    "wof:name":"Grafica Bierre (s.r.l.)",
    "wof:placetype":"venue"
},
  "geometry": {"coordinates":[9.3900709152,45.8529815674],"type":"Point"}
}