{
  "type": "Feature",
  "properties": {
    "addr:full":"186, Via Nazionale Dei Giovi 20030 Lentate Sul Seveso Lentate sul Seveso Milano 20030",
    "addr:housenumber":"186",
    "addr:postcode":"20030;20030",
    "addr:street":"Via Nazionale Dei Giovi",
    "iso:country":"IT",
    "sg:address":"186, Via Nazionale Dei Giovi 20030 Lentate Sul Seveso",
    "sg:city":"Lentate sul Seveso",
    "sg:classifiers":[
        {
            "category":"Food & Beverages",
            "subcategory":"Groceries & Convenience Stores",
            "type":"Retail Goods"
        }
    ],
    "sg:phone":"+39 036 256 5691",
    "sg:postcode":"20030",
    "sg:province":"Milano",
    "sg:tags":[
        "product",
        "related"
    ],
    "wof:name":"Alta Salumeria Spa",
    "wof:placetype":"venue"
},
  "geometry": {"coordinates":[9.1200847626,45.6708259583],"type":"Point"}
}