{
  "type": "Feature",
  "properties": {
    "iso:country":"IT",
    "sg:address":"20099 Sesto San Giovanni",
    "sg:city":"Sesto San Giovanni",
    "sg:orig_category":"Servizi E Lavori Per Ecologia E Smaltimento Rifiuti. Servizi Ausiliari Di Sorveglianza, Manutenzione E Pulizia",
    "sg:phone":"+39 02 262 0851",
    "sg:postcode":"20099",
    "sg:province":"Milano",
    "sg:website":"http://www.ecoltecnica.com",
    "wof:name":"Ecoltecnica Italiana Spa",
    "wof:placetype":"venue"
},
  "geometry": {"coordinates":[9.242583,45.538628],"type":"Point"}
}