{
  "type": "Feature",
  "properties": {
    "addr:full":"Via Case Nuove Russo 98066 Patti Case nuove russo Messina 98066",
    "addr:postcode":"98066;98066",
    "addr:street":"Via Case Nuove Russo",
    "iso:country":"IT",
    "sg:address":"Via Case Nuove Russo 98066 Patti",
    "sg:city":"Case nuove russo",
    "sg:classifiers":[
        {
            "category":"Home & Garden",
            "subcategory":"Building Materials",
            "type":"Retail Goods"
        }
    ],
    "sg:phone":"+39 0941 317708",
    "sg:postcode":"98066",
    "sg:province":"Messina",
    "sg:tags":[
        "slab",
        "marble"
    ],
    "wof:name":"Furnari Antonino",
    "wof:placetype":"venue"
},
  "geometry": {"coordinates":[14.986814,38.145641],"type":"Point"}
}