{
  "type": "Feature",
  "properties": {
    "iso:country":"IT",
    "sg:address":"35129 Padova",
    "sg:city":"Padova",
    "sg:orig_category":"Articoli Medico-sanitari Ed Ortopedici. Impianti, Attrezzature E Forniture Sanitarie Ed Ospedaliere",
    "sg:phone":"+39 049 807 3888",
    "sg:postcode":"35129",
    "sg:province":"Padova",
    "wof:name":"Salandin Enrico Srl",
    "wof:placetype":"venue"
},
  "geometry": {"coordinates":[11.925999,45.426647],"type":"Point"}
}