{
  "type": "Feature",
  "properties": {
    "iso:country":"IT",
    "sg:address":"2/a, Reg. Dota 14053 Canelli",
    "sg:city":"Canelli",
    "sg:classifiers":[
        {
            "category":"Manufacturing",
            "subcategory":"Food",
            "type":"Manufacturing & Wholesale Goods"
        }
    ],
    "sg:phone":"+39 0141 824882",
    "sg:postcode":"14053",
    "sg:province":"Asti",
    "sg:tags":[
        "equipment",
        "processing",
        "-",
        "machinery"
    ],
    "wof:name":"Ferrero Di Ugo & Fabrizio",
    "wof:placetype":"venue"
},
  "geometry": {"coordinates":[8.2068128586,44.9008636475],"type":"Point"}
}