{
  "type": "Feature",
  "properties": {
    "addr:full":"7, Via Bossa 24021 Albino Albino Bergamo 24021",
    "addr:postcode":"24021;24021",
    "addr:street":"Via Bossa",
    "iso:country":"IT",
    "sg:address":"7, Via Bossa 24021 Albino",
    "sg:city":"Albino",
    "sg:classifiers":[
        {
            "category":"Manufacturing",
            "subcategory":"Rubber & Plastics",
            "type":"Manufacturing & Wholesale Goods"
        }
    ],
    "sg:phone":"+39 39035752350",
    "sg:postcode":"24021",
    "sg:province":"Bergamo",
    "wof:name":"Colatex (s.r.l.)",
    "wof:placetype":"venue"
},
  "geometry": {"coordinates":[9.806603,45.766441],"type":"Point"}
}