{
  "type": "Feature",
  "properties": {
    "addr:full":"57122 Livorno Livorno Livorno 57122",
    "addr:postcode":"57122;57122",
    "iso:country":"IT",
    "sg:address":"57122 Livorno",
    "sg:city":"Livorno",
    "sg:orig_category":"Ricambi E Componenti Dei Mezzi Di Trasporto",
    "sg:phone":"+39 0586 404006",
    "sg:postcode":"57122",
    "sg:province":"Livorno",
    "wof:name":"L.g.m.",
    "wof:placetype":"venue"
},
  "geometry": {"coordinates":[10.319797,43.561794],"type":"Point"}
}