{
  "type": "Feature",
  "properties": {
    "iso:country":"IT",
    "sg:address":"02100 Rieti",
    "sg:city":"Rieti",
    "sg:orig_category":"Studi E Consulenze Amministrative, Commerciali E Aziendali. Consulenze Tecniche, Amministrative E Perizie",
    "sg:phone":"+39 0746 491331",
    "sg:postcode":"02100",
    "sg:province":"Rieti",
    "wof:name":"Rag. Pitoni Marco",
    "wof:placetype":"venue"
},
  "geometry": {"coordinates":[12.86069,42.399174],"type":"Point"}
}