{
  "type": "Feature",
  "properties": {
    "addr:full":"95030 Sant'agata Li Battiati Catania 95030",
    "addr:postcode":"95030;95030",
    "iso:country":"IT",
    "sg:address":"95030 Sant'agata Li Battiati",
    "sg:orig_category":"Forniture Alle Strutture Ricettive. Macchine E Impianti Per Attivita' Commerciali Ed Artigianali",
    "sg:phone":"+39 095 213956",
    "sg:postcode":"95030",
    "sg:province":"Catania",
    "wof:name":"Stima Srl",
    "wof:placetype":"venue"
},
  "geometry": {"coordinates":[15.0769252777,37.558380127],"type":"Point"}
}