{
  "type": "Feature",
  "properties": {
    "addr:full":"00046 Grottaferrata Grottaferrata Roma 00046",
    "addr:postcode":"00046;roma 00046",
    "iso:country":"IT",
    "sg:address":"00046 Grottaferrata",
    "sg:city":"Grottaferrata",
    "sg:orig_category":"Macchine E Forniture Per Arredamento E Industria Del Legno. Forniture Per Edilizia E Lavori Pubblici",
    "sg:phone":"+39 06 9454 6114",
    "sg:postcode":"00046",
    "sg:province":"Roma",
    "wof:name":"Ascot Srl",
    "wof:placetype":"venue"
},
  "geometry": {"coordinates":[12.669788,41.792992],"type":"Point"}
}