{
  "type": "Feature",
  "properties": {
    "iso:country":"IT",
    "sg:address":"Via Mentana 40 20035 Lissone",
    "sg:city":"Lissone",
    "sg:orig_category":"Inner Spring Mattresses",
    "sg:phone":"+39 039 483241",
    "sg:postcode":"20035",
    "sg:province":"Milano",
    "wof:name":"La Continentale S.n.c.",
    "wof:placetype":"venue"
},
  "geometry": {"coordinates":[9.245279,45.604965],"type":"Point"}
}