{
  "type": "Feature",
  "properties": {
    "iso:country":"IT",
    "sg:address":"20093 Cologno Monzese",
    "sg:city":"Cologno Monzese",
    "sg:orig_category":"Carni, Salumi E Pesci",
    "sg:phone":"+39 02 254 4690",
    "sg:postcode":"20093",
    "sg:province":"Milano",
    "wof:name":"Di Bartolomeo Francesco",
    "wof:placetype":"venue"
},
  "geometry": {"coordinates":[9.26609,45.521049],"type":"Point"}
}