{
  "type": "Feature",
  "properties": {
    "addr:full":"Via Bosena 7/b 16035 Rapallo Rapallo Genova 16035",
    "addr:housenumber":"7 / b",
    "addr:postcode":"16035;16035",
    "addr:street":"Via Bosena",
    "iso:country":"IT",
    "sg:address":"Via Bosena 7/b 16035 Rapallo",
    "sg:city":"Rapallo",
    "sg:classifiers":[
        {
            "category":"Autos & Motor Vehicles",
            "subcategory":"Boat Sales",
            "type":"Retail Goods"
        }
    ],
    "sg:phone":"+39 0185 263004",
    "sg:postcode":"16035",
    "sg:province":"Genova",
    "sg:tags":[
        "yacht",
        "accessory"
    ],
    "sg:website":"www.versaridelmonte.com",
    "wof:name":"Versari & Delmonte Srl",
    "wof:placetype":"venue"
},
  "geometry": {"coordinates":[8.933989,44.407063],"type":"Point"}
}