{
  "type": "Feature",
  "properties": {
    "iso:country":"IT",
    "sg:address":"95030 Gravina Di Catania",
    "sg:city":"Gravina di Catania",
    "sg:orig_category":"Abbigliamento Esterno, Maglierie E Pelliccerie. Forniture Per Il Settore Dello Spettacolo",
    "sg:phone":"+39 095 394887",
    "sg:postcode":"95030",
    "sg:province":"Catania",
    "wof:name":"R.c. Di Curto Arturo",
    "wof:placetype":"venue"
},
  "geometry": {"coordinates":[15.060348,37.562775],"type":"Point"}
}