{
  "type": "Feature",
  "properties": {
    "iso:country":"IT",
    "sg:address":"57023 Cecina",
    "sg:city":"Cecina",
    "sg:orig_category":"Prodotti Alimentari",
    "sg:phone":"+39 0586 620555",
    "sg:postcode":"57023",
    "sg:province":"Livorno",
    "wof:name":"Mediterranea Belfiore Srl",
    "wof:placetype":"venue"
},
  "geometry": {"coordinates":[10.4945373535,43.3160324097],"type":"Point"}
}