{
  "type": "Feature",
  "properties": {
    "iso:country":"IT",
    "sg:address":"25032 Chiari",
    "sg:city":"Chiari",
    "sg:orig_category":"Tessuti Arredamento, Tende E Tappeti. Forniture Per Edilizia E Lavori Pubblici",
    "sg:phone":"+39 030 712022",
    "sg:postcode":"25032",
    "sg:province":"Brescia",
    "wof:name":"Casa Del Tendaggio Tappezzeria Di Morsia P. E D. Snc",
    "wof:placetype":"venue"
},
  "geometry": {"coordinates":[9.925162,45.538723],"type":"Point"}
}