{
  "type": "Feature",
  "properties": {
    "addr:full":"Via S. Andrea 18 20020 Lazzate Lazzate Milano 20020",
    "addr:housenumber":"18",
    "addr:postcode":"20020;20020",
    "addr:street":"Via S. Andrea",
    "iso:country":"IT",
    "sg:address":"Via S. Andrea 18 20020 Lazzate",
    "sg:city":"Lazzate",
    "sg:classifiers":[
        {
            "category":"Manufacturing",
            "subcategory":"Metals",
            "type":"Manufacturing & Wholesale Goods"
        }
    ],
    "sg:phone":"+39 02 9632 0231",
    "sg:postcode":"20020",
    "sg:province":"Milano",
    "sg:tags":[
        "sheet",
        "miscellaneous",
        "working",
        "machines"
    ],
    "sg:website":"www.indumac.com",
    "wof:name":"Caimi, E C., Snc",
    "wof:placetype":"venue"
},
  "geometry": {"coordinates":[9.188141,45.463688],"type":"Point"}
}