{
  "type": "Feature",
  "properties": {
    "iso:country":"IT",
    "sg:address":"65126 Pescara",
    "sg:city":"Pescara",
    "sg:orig_category":"Spedizionieri Doganali",
    "sg:phone":"+39 085 60240",
    "sg:postcode":"65126",
    "sg:province":"Pescara",
    "wof:name":"Delmar Snc",
    "wof:placetype":"venue"
},
  "geometry": {"coordinates":[14.217222,42.462345],"type":"Point"}
}