{
  "type": "Feature",
  "properties": {
    "iso:country":"IT",
    "sg:address":"23875 Osnago",
    "sg:city":"Osnago",
    "sg:orig_category":"Arte Ed Artigianato Artistico",
    "sg:phone":"+39 039 58570",
    "sg:postcode":"23875",
    "sg:province":"Lecco",
    "wof:name":"Freddi Bruno",
    "wof:placetype":"venue"
},
  "geometry": {"coordinates":[9.385139,45.677601],"type":"Point"}
}