{
  "type": "Feature",
  "properties": {
    "iso:country":"IT",
    "sg:address":"185, Via Quarantadue Martiri 28924 Verbania",
    "sg:city":"Verbania",
    "sg:classifiers":[
        {
            "category":"Shopping",
            "type":"Retail Goods"
        }
    ],
    "sg:phone":"+39 0323 586820",
    "sg:postcode":"28924",
    "sg:province":"Verbano-Cusio-Ossola",
    "sg:tags":[
        "finished",
        "-",
        "metallic"
    ],
    "wof:name":"Inoxia S.r.l.",
    "wof:placetype":"venue"
},
  "geometry": {"coordinates":[8.4759473801,45.9435005188],"type":"Point"}
}