{
  "type": "Feature",
  "properties": {
    "iso:country":"IT",
    "sg:address":"10071 Borgaro Torinese",
    "sg:city":"Borgaro Torinese",
    "sg:orig_category":"Apparecchiature E Sistemi Per Magazzinaggio E Movimentazione",
    "sg:phone":"+39 011 224 6827",
    "sg:postcode":"10071",
    "sg:province":"Torino",
    "wof:name":"Tecnonastri Di De Faveri Roberto & C. Snc",
    "wof:placetype":"venue"
},
  "geometry": {"coordinates":[7.691592,45.134594],"type":"Point"}
}