{
  "type": "Feature",
  "properties": {
    "iso:country":"IT",
    "sg:address":"Via Torino 366 10042 Nichelino",
    "sg:city":"Nichelino",
    "sg:classifiers":[
        {
            "category":"Wholesale",
            "subcategory":"Auto Parts",
            "type":"Manufacturing & Wholesale Goods"
        }
    ],
    "sg:phone":"+39 011 647 4429",
    "sg:postcode":"10042",
    "sg:province":"Torino",
    "sg:tags":[
        "brake"
    ],
    "wof:name":"Coinfo Srl",
    "wof:placetype":"venue"
},
  "geometry": {"coordinates":[7.629053,44.980583],"type":"Point"}
}