{
  "type": "Feature",
  "properties": {
    "iso:country":"IT",
    "sg:address":"30175 Venezia",
    "sg:city":"Venezia",
    "sg:orig_category":"Scuole E Servizi Scolastici. Servizi Per Lo Sport E Il Tempo Libero",
    "sg:phone":"+39 041 930525",
    "sg:postcode":"30175",
    "sg:province":"Venezia",
    "wof:name":"Sportest",
    "wof:placetype":"venue"
},
  "geometry": {"coordinates":[12.283298,45.440845],"type":"Point"}
}