{
  "type": "Feature",
  "properties": {
    "iso:country":"IT",
    "sg:address":"Via Francesco Gallina 51 20010 Bareggio",
    "sg:city":"Bareggio",
    "sg:classifiers":[
        {
            "category":"Government",
            "subcategory":"Fire Station",
            "type":"Public Place"
        }
    ],
    "sg:phone":"+39 02 903131",
    "sg:postcode":"20010",
    "sg:province":"Milano",
    "sg:tags":[
        "equipment",
        "heat",
        "tempering",
        "recovery",
        "air"
    ],
    "sg:website":"www.atisa.it",
    "wof:name":"Atisa Aero-termica Italiana Spa",
    "wof:placetype":"venue"
},
  "geometry": {"coordinates":[9.000663,45.480095],"type":"Point"}
}