{
  "type": "Feature",
  "properties": {
    "iso:country":"IT",
    "sg:address":"95024 Acireale",
    "sg:city":"Acireale",
    "sg:orig_category":"Prodotti Di Base E Forniture Per Industria Alimentare E Bevande. Carta, Cartone E Prodotti Primari. Forniture Per Attivita' Commerciali Ed Artigianali",
    "sg:phone":"+39 095 763 3391",
    "sg:postcode":"95024",
    "sg:province":"Catania",
    "wof:name":"Della Corte Sabatino",
    "wof:placetype":"venue"
},
  "geometry": {"coordinates":[15.1609840393,37.6357650757],"type":"Point"}
}