{
  "type": "Feature",
  "properties": {
    "addr:full":"Via Respighi 15 47841 Cattolica Cattolica Rimini 47841",
    "addr:housenumber":"15",
    "addr:postcode":"47841;47841",
    "addr:street":"Via Respighi",
    "iso:country":"IT",
    "sg:address":"Via Respighi 15 47841 Cattolica",
    "sg:city":"Cattolica",
    "sg:classifiers":[
        {
            "category":"Home & Garden",
            "subcategory":"Kitchen Supply",
            "type":"Retail Goods"
        }
    ],
    "sg:phone":"+39 0541 833166",
    "sg:postcode":"47841",
    "sg:province":"Rimini",
    "sg:tags":[
        "current",
        "direct",
        "power"
    ],
    "sg:website":"www.umpi.it",
    "wof:name":"Umpi Elettronica Srl",
    "wof:placetype":"venue"
},
  "geometry": {"coordinates":[12.736642,43.949718],"type":"Point"}
}