{
  "type": "Feature",
  "properties": {
    "iso:country":"IT",
    "sg:address":"10, Viale Europa 26855 Lodi Vecchio",
    "sg:city":"Lodi Vecchio",
    "sg:classifiers":[
        {
            "category":"Wholesale",
            "subcategory":"Drugs",
            "type":"Manufacturing & Wholesale Goods"
        }
    ],
    "sg:phone":"+39 390 371 4621",
    "sg:postcode":"26855",
    "sg:province":"Lodi",
    "sg:tags":[
        "chemical",
        "pharmaceutical"
    ],
    "wof:name":"Conter Spa",
    "wof:placetype":"venue"
},
  "geometry": {"coordinates":[9.419626,45.306839],"type":"Point"}
}