{
  "type": "Feature",
  "properties": {
    "iso:country":"IT",
    "sg:address":"274, Via Milano 21017 Samarate",
    "sg:city":"Samarate",
    "sg:classifiers":[
        {
            "category":"Professional",
            "subcategory":"Engineering",
            "type":"Services"
        }
    ],
    "sg:phone":"+39 0331 223288",
    "sg:postcode":"21017",
    "sg:province":"Varese",
    "sg:tags":[
        "machine",
        "-",
        "mechanical"
    ],
    "wof:name":"Italsystem Snc",
    "wof:placetype":"venue"
},
  "geometry": {"coordinates":[8.803754,45.620937],"type":"Point"}
}