{
  "type": "Feature",
  "properties": {
    "iso:country":"IT",
    "sg:address":"20018 Sedriano",
    "sg:city":"Sedriano",
    "sg:classifiers":[
        {
            "category":"Health Services",
            "subcategory":"Health Practitioner",
            "type":"Services"
        }
    ],
    "sg:phone":"+39 02 9026 0551",
    "sg:postcode":"20018",
    "sg:province":"Milano",
    "sg:tags":[
        "medici"
    ],
    "wof:name":"Carcano Maria Maura",
    "wof:placetype":"venue"
},
  "geometry": {"coordinates":[9.00762,45.496479],"type":"Point"}
}