{
  "type": "Feature",
  "properties": {
    "iso:country":"IT",
    "sg:address":"32040 Dosoledo",
    "sg:city":"Dosoledo",
    "sg:orig_category":"Non-classified Establishments",
    "sg:phone":"+39 0435 68145",
    "sg:postcode":"32040",
    "sg:province":"Belluno",
    "wof:name":"Zandonella Luciano",
    "wof:placetype":"venue"
},
  "geometry": {"coordinates":[12.492347,46.599564],"type":"Point"}
}