{
  "type": "Feature",
  "properties": {
    "addr:full":"9, Via Buccari 16153 Genova Genova Genova 16153",
    "addr:postcode":"16153;16153",
    "addr:street":"Via Buccari",
    "iso:country":"IT",
    "sg:address":"9, Via Buccari 16153 Genova",
    "sg:city":"Genova",
    "sg:classifiers":[
        {
            "category":"Manufacturing",
            "subcategory":"Metals",
            "type":"Manufacturing & Wholesale Goods"
        }
    ],
    "sg:phone":"+39 010 614 1980",
    "sg:postcode":"16153",
    "sg:province":"Genova",
    "sg:tags":[
        "processing"
    ],
    "wof:name":"Apv Ratto S.p.a.",
    "wof:placetype":"venue"
},
  "geometry": {"coordinates":[8.8565654755,44.4203948975],"type":"Point"}
}