{
  "type": "Feature",
  "properties": {
    "addr:full":"63018 Porto S. Elpidio Ascoli Piceno 63018",
    "addr:housenumber":"63018",
    "addr:postcode":"63018",
    "addr:street":"Porto S. Elpidio;Piceno",
    "iso:country":"IT",
    "sg:address":"63018 Porto S. Elpidio",
    "sg:classifiers":[
        {
            "category":"Manufacturing",
            "subcategory":"Leather Goods",
            "type":"Manufacturing & Wholesale Goods"
        }
    ],
    "sg:phone":"+39 0734 991269",
    "sg:postcode":"63018",
    "sg:province":"Ascoli Piceno",
    "sg:tags":[
        "footwear",
        "skin"
    ],
    "wof:name":"Calzaturificio Mr",
    "wof:placetype":"venue"
},
  "geometry": {"coordinates":[13.5749769211,42.8554000854],"type":"Point"}
}