{
  "type": "Feature",
  "properties": {
    "iso:country":"IT",
    "sg:address":"218, Via Sempione 21052 Busto Arsizio",
    "sg:city":"Busto Arsizio",
    "sg:classifiers":[
        {
            "category":"Shopping",
            "subcategory":"Clothing, Apparel, & Fashions",
            "type":"Retail Goods"
        }
    ],
    "sg:phone":"+39 0331 382100",
    "sg:postcode":"21052",
    "sg:province":"Varese",
    "sg:tags":[
        "clothes"
    ],
    "wof:name":"Bottigelli Mario (s.p.a.)",
    "wof:placetype":"venue"
},
  "geometry": {"coordinates":[8.827798,45.636883],"type":"Point"}
}