{
  "type": "Feature",
  "properties": {
    "addr:full":"25049 Iseo Iseo Brescia 25049",
    "addr:postcode":"25049;25049",
    "iso:country":"IT",
    "sg:address":"25049 Iseo",
    "sg:city":"Iseo",
    "sg:orig_category":"Riparazione Dei Mezzi Di Trasporto. Servizi Ausiliari Dei Mezzi Di Trasporto",
    "sg:phone":"+39 030 980486",
    "sg:postcode":"25049",
    "sg:province":"Brescia",
    "wof:name":"Cantiere Nautico Cadei",
    "wof:placetype":"venue"
},
  "geometry": {"coordinates":[10.213829,45.582371],"type":"Point"}
}