{
  "type": "Feature",
  "properties": {
    "iso:country":"IT",
    "sg:address":"11/13, Zona Industriale Piana 36078 Valdagno",
    "sg:city":"Piana",
    "sg:classifiers":[
        {
            "category":"Professional",
            "subcategory":"Engineering",
            "type":"Services"
        }
    ],
    "sg:phone":"+39 0445 431144",
    "sg:postcode":"36078",
    "sg:province":"Vicenza",
    "sg:tags":[
        "machine",
        "-",
        "mechanical"
    ],
    "wof:name":"Costruzioni Meccaniche Eugenio Fiori (s.r.l.)",
    "wof:placetype":"venue"
},
  "geometry": {"coordinates":[11.314177,45.620365],"type":"Point"}
}