{
  "type": "Feature",
  "properties": {
    "addr:full":"50144 Firenze Firenze Firenze 50144",
    "addr:postcode":"50144;50144",
    "iso:country":"IT",
    "sg:address":"50144 Firenze",
    "sg:city":"Firenze",
    "sg:classifiers":[
        {
            "category":"Insurance",
            "subcategory":"Life Insurance",
            "type":"Services"
        }
    ],
    "sg:phone":"+39 055 321 5397",
    "sg:postcode":"50144",
    "sg:province":"Firenze",
    "sg:website":"http://www.excelsiorent.it",
    "wof:name":"Excelsior Autonoleggio Srl",
    "wof:placetype":"venue"
},
  "geometry": {"coordinates":[11.235638,43.787418],"type":"Point"}
}