{
  "type": "Feature",
  "properties": {
    "iso:country":"IT",
    "sg:address":"58033 Castel Del Piano",
    "sg:city":"Castel del Piano",
    "sg:orig_category":"Elettrotecnica Industriale, Prodotti E Apparecchiature. Ricambi E Componenti Dei Mezzi Di Trasporto",
    "sg:phone":"+39 0564 955409",
    "sg:postcode":"58033",
    "sg:province":"Grosseto",
    "wof:name":"Maior Accumulatori F.lli Pelosi & Pieri Snc",
    "wof:placetype":"venue"
},
  "geometry": {"coordinates":[11.531773,42.88554],"type":"Point"}
}