{
  "type": "Feature",
  "properties": {
    "iso:country":"IT",
    "sg:address":"19/bis, Strada Redentore 10024 Moncalieri",
    "sg:city":"Moncalieri",
    "sg:classifiers":[
        {
            "category":"Utilities",
            "subcategory":"Electric",
            "type":"Services"
        }
    ],
    "sg:phone":"+39 011 813 1184",
    "sg:postcode":"10024",
    "sg:province":"Torino",
    "sg:tags":[
        "energy"
    ],
    "wof:name":"Valdenassi Emanuele Maria D.i.",
    "wof:placetype":"venue"
},
  "geometry": {"coordinates":[7.736661,45.022194],"type":"Point"}
}