{
  "type": "Feature",
  "properties": {
    "iso:country":"IT",
    "sg:address":"73055 Racale",
    "sg:city":"Racale",
    "sg:orig_category":"Articoli Da Regalo. Arte Ed Artigianato Artistico. Shopping. Regalistica Aziendale",
    "sg:phone":"+39 0833 584854",
    "sg:postcode":"73055",
    "sg:province":"Lecce",
    "wof:name":"Fascino Antico Sas",
    "wof:placetype":"venue"
},
  "geometry": {"coordinates":[18.022305,39.967709],"type":"Point"}
}