{
  "type": "Feature",
  "properties": {
    "iso:country":"IT",
    "sg:address":"68, Via Luigi Einaudi 35030 Saccolongo",
    "sg:city":"Saccolongo",
    "sg:classifiers":[
        {
            "category":"Professional",
            "subcategory":"Engineering",
            "type":"Services"
        }
    ],
    "sg:phone":"+39 049 801 5422",
    "sg:postcode":"35030",
    "sg:province":"Padova",
    "sg:tags":[
        "machine",
        "-",
        "mechanical"
    ],
    "wof:name":"Lamapla M.g. (s.r.l.)",
    "wof:placetype":"venue"
},
  "geometry": {"coordinates":[11.761293,45.39209],"type":"Point"}
}