{
  "type": "Feature",
  "properties": {
    "iso:country":"IT",
    "sg:address":"Via Teocrito 52 20128 Milano",
    "sg:city":"Milano",
    "sg:orig_category":"Oil Transportation Buckets For Car Repair Shops",
    "sg:phone":"+39 02 255 1340",
    "sg:postcode":"20128",
    "sg:province":"Milano",
    "sg:website":"www.lamaplast.com",
    "wof:name":"Lamaplast Srl",
    "wof:placetype":"venue"
},
  "geometry": {"coordinates":[9.229612,45.508251],"type":"Point"}
}