{
  "type": "Feature",
  "properties": {
    "iso:country":"IT",
    "sg:address":"41012 Carpi",
    "sg:city":"Carpi",
    "sg:orig_category":"Tessuti E Stoffe. Filati E Materie Prime Tessili",
    "sg:phone":"+39 059 652455",
    "sg:postcode":"41012",
    "sg:province":"Modena",
    "wof:name":"Emilcotoni Spa",
    "wof:placetype":"venue"
},
  "geometry": {"coordinates":[10.883916,44.810295],"type":"Point"}
}