{
  "type": "Feature",
  "properties": {
    "addr:full":"Via Tario 12 10020 Andezeno Andezeno Torino 10020",
    "addr:housenumber":"12",
    "addr:postcode":"10020;10020",
    "addr:street":"Via Tario",
    "iso:country":"IT",
    "sg:address":"Via Tario 12 10020 Andezeno",
    "sg:city":"Andezeno",
    "sg:classifiers":[
        {
            "category":"Shopping",
            "subcategory":"Gifts & Souvenirs",
            "type":"Retail Goods"
        }
    ],
    "sg:phone":"+39 011 943 4272",
    "sg:postcode":"10020",
    "sg:province":"Torino",
    "sg:tags":[
        "wrap",
        "paper"
    ],
    "wof:name":"Adp Carta Snc Di De Pari A. & C",
    "wof:placetype":"venue"
},
  "geometry": {"coordinates":[7.854409,45.027618],"type":"Point"}
}