{
  "type": "Feature",
  "properties": {
    "iso:country":"IT",
    "sg:address":"Via Cascina Crivella 18 20090 Vimodrone",
    "sg:city":"Vimodrone",
    "sg:classifiers":[
        {
            "category":"Bars & Pubs",
            "subcategory":"Biergarten",
            "type":"Food & Drink"
        }
    ],
    "sg:phone":"+39 02 2730 1324",
    "sg:postcode":"20090",
    "sg:province":"Milano",
    "sg:tags":[
        "dosing",
        "pump"
    ],
    "sg:website":"www.doseuro.com",
    "wof:name":"Doseuro S.r.l.",
    "wof:placetype":"venue"
},
  "geometry": {"coordinates":[9.188141,45.463688],"type":"Point"}
}