{
  "type": "Feature",
  "properties": {
    "addr:full":"98124 Messina Messina Messina 98124",
    "addr:postcode":"98124;98124",
    "iso:country":"IT",
    "sg:address":"98124 Messina",
    "sg:city":"Messina",
    "sg:orig_category":"Termotecnica E Riscaldamento, Apparecchiature E Servizi",
    "sg:phone":"+39 090 715811",
    "sg:postcode":"98124",
    "sg:province":"Messina",
    "wof:name":"Giuliano Rappresentanze Sas",
    "wof:placetype":"venue"
},
  "geometry": {"coordinates":[15.5483474731,38.1868438721],"type":"Point"}
}