{
  "type": "Feature",
  "properties": {
    "iso:country":"IT",
    "sg:address":"16157 Genova",
    "sg:city":"Genova",
    "sg:orig_category":"Materiali Semilavorati Metallici",
    "sg:phone":"+39 010 698 0747",
    "sg:postcode":"16157",
    "sg:province":"Genova",
    "wof:name":"Tasso Franco",
    "wof:placetype":"venue"
},
  "geometry": {"coordinates":[8.795491,44.426132],"type":"Point"}
}