{
  "type": "Feature",
  "properties": {
    "iso:country":"IT",
    "sg:address":"Via Della Pace 43 31041 Cornuda",
    "sg:city":"Cornuda",
    "sg:classifiers":[
        {
            "category":"Shopping",
            "subcategory":"Clothing, Apparel, & Fashions",
            "type":"Retail Goods"
        }
    ],
    "sg:phone":"+39 0423 639730",
    "sg:postcode":"31041",
    "sg:province":"Treviso",
    "sg:tags":[
        "work",
        "clothes"
    ],
    "sg:website":"www.ravazzolosrl.com",
    "wof:name":"Ravazzolo Srl",
    "wof:placetype":"venue"
},
  "geometry": {"coordinates":[12.014328,45.836468],"type":"Point"}
}