{
  "type": "Feature",
  "properties": {
    "iso:country":"IT",
    "sg:address":"70125 Bari",
    "sg:city":"Bari",
    "sg:orig_category":"Materiali E Componenti Elettronici",
    "sg:phone":"+39 080 542 2577",
    "sg:postcode":"70125",
    "sg:province":"Bari",
    "wof:name":"Sud Suono S.r.l.",
    "wof:placetype":"venue"
},
  "geometry": {"coordinates":[16.873657,41.102005],"type":"Point"}
}