{
  "type": "Feature",
  "properties": {
    "iso:country":"IT",
    "sg:address":"Corso Unione Sovietica 153 10134 Torino",
    "sg:city":"Torino",
    "sg:classifiers":[
        {
            "category":"Retail",
            "subcategory":"Event Space",
            "type":"Services"
        }
    ],
    "sg:phone":"+39 011 319 4880",
    "sg:postcode":"10134",
    "sg:province":"Torino",
    "sg:tags":[
        "steel",
        "special"
    ],
    "sg:website":"www.sideria.com",
    "wof:name":"Sideria Srl",
    "wof:placetype":"venue"
},
  "geometry": {"coordinates":[7.644395,45.030575],"type":"Point"}
}