{
  "type": "Feature",
  "properties": {
    "iso:country":"IT",
    "sg:address":"23899 Robbiate",
    "sg:city":"Robbiate",
    "sg:orig_category":"Abbigliamento - Produzione E Ingrosso",
    "sg:phone":"+39 039 510048",
    "sg:postcode":"23899",
    "sg:province":"Lecco",
    "sg:website":"http://www.maglierie-effegi.it",
    "wof:name":"Maglierie Effegi",
    "wof:placetype":"venue"
},
  "geometry": {"coordinates":[9.435592,45.687737],"type":"Point"}
}