{
  "type": "Feature",
  "properties": {
    "addr:full":"23870 Cernusco Lombardone Cernusco Lombardone Lecco 23870",
    "addr:postcode":"23870;23870",
    "iso:country":"IT",
    "sg:address":"23870 Cernusco Lombardone",
    "sg:city":"Cernusco Lombardone",
    "sg:orig_category":"Servizi E Lavori Per Edilizia E Lavori Pubblici. Consulenze Tecniche, Amministrative E Perizie",
    "sg:phone":"+39 039 927 0198",
    "sg:postcode":"23870",
    "sg:province":"Lecco",
    "sg:website":"http://www.sb3.it",
    "wof:name":"Sb3 Snc Di Bonfanti Massimiliano & C.",
    "wof:placetype":"venue"
},
  "geometry": {"coordinates":[9.393299,45.687046],"type":"Point"}
}