{
  "type": "Feature",
  "properties": {
    "iso:country":"IT",
    "sg:address":"70124 Bari",
    "sg:city":"Bari",
    "sg:orig_category":"Servizi E Lavori Per Edilizia E Lavori Pubblici. Servizi E Lavori Per Ecologia E Smaltimento Rifiuti",
    "sg:phone":"+39 080 504 6513",
    "sg:postcode":"70124",
    "sg:province":"Bari",
    "sg:website":"http://www.geasrl.com",
    "wof:name":"Gea Srl",
    "wof:placetype":"venue"
},
  "geometry": {"coordinates":[16.854572,41.094208],"type":"Point"}
}