{
  "type": "Feature",
  "properties": {
    "iso:country":"IT",
    "sg:address":"115, Corso Lodi 20139 Milano",
    "sg:city":"Milano",
    "sg:classifiers":[
        {
            "category":"Professional",
            "subcategory":"Engineering",
            "type":"Services"
        }
    ],
    "sg:phone":"+39 02 5521 3464",
    "sg:postcode":"20139",
    "sg:province":"Milano",
    "sg:tags":[
        "machine",
        "-",
        "mechanical"
    ],
    "wof:name":"P.a. Process Analyzers (s.r.l.)",
    "wof:placetype":"venue"
},
  "geometry": {"coordinates":[9.202935,45.451721],"type":"Point"}
}