{
  "type": "Feature",
  "properties": {
    "addr:full":"88842 Cutro Cutro Crotone 88842",
    "addr:postcode":"88842;88842",
    "iso:country":"IT",
    "sg:address":"88842 Cutro",
    "sg:city":"Cutro",
    "sg:orig_category":"Petroli, Gas E Combustibili",
    "sg:phone":"+39 0962 771004",
    "sg:postcode":"88842",
    "sg:province":"Crotone",
    "wof:name":"Lucente Rosa",
    "wof:placetype":"venue"
},
  "geometry": {"coordinates":[16.9830856323,38.9927711487],"type":"Point"}
}