{
  "type": "Feature",
  "properties": {
    "iso:country":"IT",
    "sg:address":"25065 Lumezzane",
    "sg:city":"Lumezzane",
    "sg:classifiers":[
        {
            "category":"Manufacturing",
            "subcategory":"Tools & Machinery",
            "type":"Manufacturing & Wholesale Goods"
        }
    ],
    "sg:phone":"+39 030 892 5563",
    "sg:postcode":"25065",
    "sg:province":"Brescia",
    "sg:tags":[
        "machine",
        "system"
    ],
    "sg:website":"http://www.autind.com",
    "wof:name":"I.a. Automazioni Industriali",
    "wof:placetype":"venue"
},
  "geometry": {"coordinates":[10.271223,45.641441],"type":"Point"}
}