{
  "type": "Feature",
  "properties": {
    "iso:country":"IT",
    "sg:address":"19126 La Spezia",
    "sg:orig_category":"Abbigliamento Esterno, Maglierie E Pelliccerie. Forniture Industriali Per Prevenzione, Controllo E Sicurezza",
    "sg:phone":"+39 0187 515291",
    "sg:province":"SP",
    "wof:name":"Me-gears & Service Srl",
    "wof:placetype":"venue"
},
  "geometry": {"coordinates":[9.840796,44.111759],"type":"Point"}
}