{
  "type": "Feature",
  "properties": {
    "iso:country":"IT",
    "sg:address":"10156 Torino",
    "sg:city":"Torino",
    "sg:orig_category":"Macchine E Forniture Per Arredamento E Industria Del Legno. Macchine Utensili E Impianti",
    "sg:phone":"+39 011 223 7946",
    "sg:postcode":"10156",
    "sg:province":"Torino",
    "wof:name":"Martin (s.r.l.)",
    "wof:placetype":"venue"
},
  "geometry": {"coordinates":[7.744346,45.102108],"type":"Point"}
}