{
  "type": "Feature",
  "properties": {
    "addr:full":"181, Via Cossa Pietro 10146 Torino Torino Torino 10146",
    "addr:housenumber":"181",
    "addr:postcode":"10146;10146",
    "addr:street":"Via Cossa Pietro",
    "iso:country":"IT",
    "sg:address":"181, Via Cossa Pietro 10146 Torino",
    "sg:city":"Torino",
    "sg:classifiers":[
        {
            "category":"Wholesale",
            "subcategory":"Machinery & Supplies",
            "type":"Manufacturing & Wholesale Goods"
        }
    ],
    "sg:phone":"+39 011 779 5454",
    "sg:postcode":"10146",
    "sg:province":"Torino",
    "sg:tags":[
        "equipment",
        "precision"
    ],
    "wof:name":"Security Ca' Service S.n.c.",
    "wof:placetype":"venue"
},
  "geometry": {"coordinates":[7.6258296967,45.086681366],"type":"Point"}
}