{
  "type": "Feature",
  "properties": {
    "iso:country":"IT",
    "sg:address":"20145 Milano",
    "sg:city":"Milano",
    "sg:orig_category":"Macchine, Impianti Ed Attrezzature Industria Chimica",
    "sg:phone":"+39 02 4801 4137",
    "sg:postcode":"20145",
    "sg:province":"Milano",
    "wof:name":"Promochem S.r.l.",
    "wof:placetype":"venue"
},
  "geometry": {"coordinates":[9.1562,45.470871],"type":"Point"}
}