{
  "type": "Feature",
  "properties": {
    "addr:full":"10072 Caselle Mappano Torino 10072",
    "addr:postcode":"10072;10072",
    "addr:street":"Mappano",
    "iso:country":"IT",
    "sg:address":"10072 Caselle",
    "sg:city":"Mappano",
    "sg:orig_category":"Gioiellerie E Oreficerie - Vendita Al Dettaglio",
    "sg:phone":"+39 011 996 8279",
    "sg:postcode":"10072",
    "sg:province":"Torino",
    "wof:name":"Gioielli Baudino Sas Di Paola Baudino & C.",
    "wof:placetype":"venue"
},
  "geometry": {"coordinates":[7.7078,45.148254],"type":"Point"}
}