{
  "type": "Feature",
  "properties": {
    "iso:country":"IT",
    "sg:address":"95127 Catania",
    "sg:city":"Catania",
    "sg:orig_category":"Dolciumi E Gelati",
    "sg:phone":"+39 095 386221",
    "sg:postcode":"95127",
    "sg:province":"Catania",
    "wof:name":"Pasticceria Pistorio Srl",
    "wof:placetype":"venue"
},
  "geometry": {"coordinates":[15.101407,37.518398],"type":"Point"}
}