{
  "type": "Feature",
  "properties": {
    "iso:country":"IT",
    "sg:address":"00199 Roma",
    "sg:city":"Roma",
    "sg:orig_category":"Arredamenti - Vendita Al Dettaglio",
    "sg:phone":"+39 06 884 5253",
    "sg:postcode":"00199",
    "sg:province":"Roma",
    "sg:website":"http://www.riva.it",
    "wof:name":"Riva Giuseppe E C. Snc",
    "wof:placetype":"venue"
},
  "geometry": {"coordinates":[12.508389,41.924763],"type":"Point"}
}