{
  "type": "Feature",
  "properties": {
    "iso:country":"IT",
    "sg:address":"Vle Delle Industrie 1 20060 Ornago",
    "sg:city":"Ornago",
    "sg:orig_category":"Espresso",
    "sg:phone":"+39 039 601 0232",
    "sg:postcode":"20060",
    "sg:province":"Milano",
    "sg:website":"www.mokalba.it",
    "wof:name":"Caffe' Mokalba Di Stucchi Carlo",
    "wof:placetype":"venue"
},
  "geometry": {"coordinates":[9.188141,45.463688],"type":"Point"}
}