{
  "type": "Feature",
  "properties": {
    "iso:country":"IT",
    "sg:address":"51036 Larciano",
    "sg:city":"Larciano",
    "sg:orig_category":"Servizi E Lavori Per Edilizia E Lavori Pubblici. Servizi E Lavori Per Ecologia E Smaltimento Rifiuti. Macchine E Forniture Per Ecologia E Smaltimento Rifiuti. Acqua, Luce, Gas E Societa' Di Esercizio ",
    "sg:phone":"+39 0573 838339",
    "sg:postcode":"51036",
    "sg:province":"Pistoia",
    "wof:name":"V.a.b. Vigilanza Anticendi Boschivi",
    "wof:placetype":"venue"
},
  "geometry": {"coordinates":[10.913737,43.930965],"type":"Point"}
}