{
  "type": "Feature",
  "properties": {
    "addr:full":"80129 Napoli Napoli Napoli 80129",
    "addr:housenumber":"80129",
    "addr:postcode":"80129",
    "iso:country":"IT",
    "sg:address":"80129 Napoli",
    "sg:city":"Napoli",
    "sg:orig_category":"Zootecnia E Pesca, Allevamento Piccoli Animali. Animali Domestici",
    "sg:phone":"+39 081 578 2002",
    "sg:postcode":"80129",
    "sg:province":"Napoli",
    "wof:name":"Busiello Michelangelo",
    "wof:placetype":"venue"
},
  "geometry": {"coordinates":[14.234825,40.843956],"type":"Point"}
}