{
  "type": "Feature",
  "properties": {
    "addr:full":"70121 Bari Bari Bari 70121",
    "addr:postcode":"70121;70121",
    "iso:country":"IT",
    "sg:address":"70121 Bari",
    "sg:city":"Bari",
    "sg:orig_category":"Telecomunicazioni E Telefonia, Impianti, Apparecchi E Servizi. Automazione E Macchine Per Ufficio",
    "sg:phone":"+39 080 524 0935",
    "sg:postcode":"70121",
    "sg:province":"Bari",
    "wof:name":"Palmarini Fabrizio",
    "wof:placetype":"venue"
},
  "geometry": {"coordinates":[16.875366,41.12019],"type":"Point"}
}