{
  "type": "Feature",
  "properties": {
    "iso:country":"IT",
    "sg:address":"22078 Turate",
    "sg:city":"Turate",
    "sg:orig_category":"Macchine, Impianti Ed Attrezzature Industria Chimica. Impiantistica E Prodotti Tecnologici Per Edilizia. Impianti, Attrezzature E Forniture Sanitarie Ed Ospedaliere",
    "sg:phone":"+39 02 9648 0838",
    "sg:postcode":"22078",
    "sg:province":"Como",
    "wof:name":"Getinge Spa",
    "wof:placetype":"venue"
},
  "geometry": {"coordinates":[9.001402,45.655991],"type":"Point"}
}