{
  "type": "Feature",
  "properties": {
    "iso:country":"IT",
    "sg:address":"95013 Fiumefreddo Sicilia",
    "sg:orig_category":"Serramenti Ed Infissi",
    "sg:phone":"+39 095 776 2106",
    "sg:postcode":"95013",
    "sg:province":"Catania",
    "wof:name":"Imaf Dei F.lli Belfiore Snc",
    "wof:placetype":"venue"
},
  "geometry": {"coordinates":[15.214951,37.793011],"type":"Point"}
}