{
  "type": "Feature",
  "properties": {
    "addr:full":"20155 Milano Milano Milano 20155",
    "addr:postcode":"20155;20155",
    "iso:country":"IT",
    "sg:address":"20155 Milano",
    "sg:city":"Milano",
    "sg:classifiers":[
        {
            "category":"Health Services",
            "subcategory":"Health Practitioner",
            "type":"Services"
        }
    ],
    "sg:phone":"+39 02 3921 1408",
    "sg:postcode":"20155",
    "sg:province":"Milano",
    "sg:tags":[
        "medici"
    ],
    "wof:name":"Brondolo Walter",
    "wof:placetype":"venue"
},
  "geometry": {"coordinates":[9.153943,45.489376],"type":"Point"}
}