{
  "type": "Feature",
  "properties": {
    "iso:country":"IT",
    "sg:address":"07026 Olbia",
    "sg:city":"Olbia",
    "sg:orig_category":"Prodotti Chimici Secondari. Macchine E Forniture Per Ecologia E Smaltimento Rifiuti. Forniture Per Attivita' Industriali",
    "sg:phone":"+39 0789 58585",
    "sg:postcode":"07026",
    "sg:province":"Olbia-Tempio",
    "sg:website":"http://www.sardegnaffiti.it/",
    "wof:name":"Pulisarda Di Burrai Arcangelo E C. Snc",
    "wof:placetype":"venue"
},
  "geometry": {"coordinates":[9.2785587311,40.826839447],"type":"Point"}
}