{
  "type": "Feature",
  "properties": {
    "addr:full":"Via Calatafimi 52; Castelfranco Di Sotto",
    "addr:housenumber":"52",
    "addr:street":"Via Calatafimi",
    "iso:country":"IT",
    "sg:address":"Via Calatafimi 52; Castelfranco Di Sotto",
    "sg:classifiers":[
        {
            "category":"Banks & Credit Unions",
            "subcategory":"Bank",
            "type":"Services"
        }
    ],
    "sg:phone":"+39 0571 489971",
    "wof:name":"Cassa Di Risparmio Di San Miniato",
    "wof:placetype":"venue"
},
  "geometry": {"coordinates":[10.744034,43.698723],"type":"Point"}
}