{
  "type": "Feature",
  "properties": {
    "iso:country":"IT",
    "sg:address":"30038 Spinea",
    "sg:city":"Spinea",
    "sg:orig_category":"Cartotecnica E Servizi. Composizione, Stampa E Confezione. Forniture E Prodotti Informatici. Forniture Per Congressi, Fiere E Manifestazioni",
    "sg:phone":"+39 041 508 9711",
    "sg:postcode":"30038",
    "sg:province":"Venezia",
    "wof:name":"Comuniko Snc Di Capogrosso E. & Rolfini B.",
    "wof:placetype":"venue"
},
  "geometry": {"coordinates":[12.167568,45.49152],"type":"Point"}
}