{
  "type": "Feature",
  "properties": {
    "iso:country":"IT",
    "sg:address":"00040 Rocca Di Papa",
    "sg:city":"Rocca di Papa",
    "sg:orig_category":"Servizi E Lavori Per Arredamento E Industria Del Legno",
    "sg:phone":"+39 06 949 5064",
    "sg:postcode":"00040",
    "sg:province":"Roma",
    "wof:name":"De Luca Alfio & Luigi Snc",
    "wof:placetype":"venue"
},
  "geometry": {"coordinates":[12.699036,41.74218],"type":"Point"}
}