{
  "type": "Feature",
  "properties": {
    "iso:country":"IT",
    "sg:address":"84018 Scafati",
    "sg:city":"Scafati",
    "sg:orig_category":"Accessori Dei Mezzi Di Trasporto",
    "sg:phone":"+39 081 863 2529",
    "sg:postcode":"84018",
    "sg:province":"Salerno",
    "wof:name":"Ambruoso Nicola",
    "wof:placetype":"venue"
},
  "geometry": {"coordinates":[14.523524,40.752949],"type":"Point"}
}