{
  "type": "Feature",
  "properties": {
    "iso:country":"IT",
    "sg:address":"Via Canaletto 139/a 41030 San Prospero Sulla Secchia",
    "sg:city":"San Prospero",
    "sg:classifiers":[
        {
            "category":"Wholesale",
            "subcategory":"Chemicals & Plastics",
            "type":"Manufacturing & Wholesale Goods"
        }
    ],
    "sg:phone":"+39 059 808 0811",
    "sg:postcode":"41030",
    "sg:province":"Modena",
    "sg:tags":[
        "dry",
        "plant",
        "granulates",
        "powders",
        "flake",
        "dosing",
        "device",
        "machines"
    ],
    "sg:website":"www.wam.it",
    "wof:name":"Torex Srl",
    "wof:placetype":"venue"
},
  "geometry": {"coordinates":[10.92522,44.647079],"type":"Point"}
}