{
  "type": "Feature",
  "properties": {
    "addr:full":"12, Via Perosi 70022 Altamura Altamura Bari 70022",
    "addr:postcode":"70022;70022",
    "addr:street":"Via Perosi",
    "iso:country":"IT",
    "sg:address":"12, Via Perosi 70022 Altamura",
    "sg:city":"Altamura",
    "sg:classifiers":[
        {
            "category":"Home & Garden",
            "subcategory":"Home Furnishings",
            "type":"Retail Goods"
        }
    ],
    "sg:phone":"+39 080 310 2991",
    "sg:postcode":"70022",
    "sg:province":"Bari",
    "sg:tags":[
        "household"
    ],
    "wof:name":"Pass Di Baldassarra & Nicoletti (s.n.c.)",
    "wof:placetype":"venue"
},
  "geometry": {"coordinates":[16.544531,40.8293],"type":"Point"}
}