{
  "type": "Feature",
  "properties": {
    "iso:country":"IT",
    "sg:address":"80122 Napoli",
    "sg:city":"Napoli",
    "sg:orig_category":"Artigianato Tipico",
    "sg:phone":"+39 081 761 2359",
    "sg:postcode":"80122",
    "sg:province":"Napoli",
    "wof:name":"Landolfi Franco",
    "wof:placetype":"venue"
},
  "geometry": {"coordinates":[14.213019,40.91338],"type":"Point"}
}