{
  "type": "Feature",
  "properties": {
    "addr:full":"193, Via Giusti Giuseppe 50041 Calenzano Calenzano Firenze 50041",
    "addr:housenumber":"193",
    "addr:postcode":"50041;50041",
    "addr:street":"Via Giusti Giuseppe",
    "iso:country":"IT",
    "sg:address":"193, Via Giusti Giuseppe 50041 Calenzano",
    "sg:city":"Calenzano",
    "sg:classifiers":[
        {
            "category":"Manufacturing",
            "subcategory":"Glass & Minerals",
            "type":"Manufacturing & Wholesale Goods"
        }
    ],
    "sg:phone":"+39 39055882356",
    "sg:postcode":"50041",
    "sg:province":"Firenze",
    "wof:name":"Pack Line S.r.l.",
    "wof:placetype":"venue"
},
  "geometry": {"coordinates":[11.204296,43.829369],"type":"Point"}
}