{
  "type": "Feature",
  "properties": {
    "iso:country":"IT",
    "sg:address":"42035 Castelnovo Ne' Monti",
    "sg:orig_category":"Legno E Semilavorati. Materiali Edili",
    "sg:phone":"+39 0522 812620",
    "sg:postcode":"42035",
    "sg:province":"Reggio Nell'Emilia",
    "wof:name":"G.r. Rosati Snc",
    "wof:placetype":"venue"
},
  "geometry": {"coordinates":[10.417181,44.430557],"type":"Point"}
}