{
  "type": "Feature",
  "properties": {
    "iso:country":"IT",
    "sg:address":"62027 San Severino Marche",
    "sg:city":"San Severino Marche",
    "sg:orig_category":"Prodotti E Manufatti In Materie Plastiche. Articoli Per Imballaggio E Confezionamento",
    "sg:phone":"+39 0733 638670",
    "sg:postcode":"62027",
    "sg:province":"Macerata",
    "wof:name":"Saccoplast Srl",
    "wof:placetype":"venue"
},
  "geometry": {"coordinates":[13.1971063614,43.2730751038],"type":"Point"}
}