{
  "type": "Feature",
  "properties": {
    "iso:country":"IT",
    "sg:address":"06100 Perugia",
    "sg:orig_category":"Collegi, Convitti E Pensionati",
    "sg:phone":"+39 075 528 7441",
    "sg:province":"PG",
    "sg:website":"http://www.fermi.it",
    "wof:name":"Istituto Enrico Fermi Perugia Srl",
    "wof:placetype":"venue"
},
  "geometry": {"coordinates":[12.346151,43.084835],"type":"Point"}
}