{
  "type": "Feature",
  "properties": {
    "addr:full":"20094 Corsico Corsico Milano 20094",
    "addr:postcode":"20094;20094",
    "iso:country":"IT",
    "sg:address":"20094 Corsico",
    "sg:city":"Corsico",
    "sg:orig_category":"Materiali Semilavorati Metallici",
    "sg:phone":"+39 02 450 0671",
    "sg:postcode":"20094",
    "sg:province":"Milano",
    "wof:name":"Marcegaglia S.p.a.",
    "wof:placetype":"venue"
},
  "geometry": {"coordinates":[9.090293,45.435665],"type":"Point"}
}