{
  "type": "Feature",
  "properties": {
    "iso:country":"IT",
    "sg:address":"24054 Calcio",
    "sg:city":"Calcio",
    "sg:classifiers":[
        {
            "category":"Wholesale",
            "subcategory":"Stationery",
            "type":"Manufacturing & Wholesale Goods"
        }
    ],
    "sg:phone":"+39 036 396 9503",
    "sg:postcode":"24054",
    "sg:province":"Bergamo",
    "sg:tags":[
        "pistole",
        "spruzzo"
    ],
    "sg:website":"http://www.aircatinternational.com",
    "wof:name":"Air Cat International Srl",
    "wof:placetype":"venue"
},
  "geometry": {"coordinates":[9.8546819687,45.5108642578],"type":"Point"}
}