{
  "type": "Feature",
  "properties": {
    "iso:country":"IT",
    "sg:address":"73100 Lecce",
    "sg:city":"Lecce",
    "sg:orig_category":"Ospedali E Servizi Sanitari",
    "sg:phone":"+39 0832 352102",
    "sg:postcode":"73100",
    "sg:province":"Lecce",
    "wof:name":"Calabrese Studio Radiologico Associato",
    "wof:placetype":"venue"
},
  "geometry": {"coordinates":[18.165499,40.348087],"type":"Point"}
}