{
  "type": "Feature",
  "properties": {
    "addr:full":"00191 Roma Roma Roma 00191",
    "addr:postcode":"00191;00191",
    "iso:country":"IT",
    "sg:address":"00191 Roma",
    "sg:city":"Roma",
    "sg:orig_category":"Petroli, Gas E Combustibili",
    "sg:phone":"+39 06 333 0756",
    "sg:postcode":"00191",
    "sg:province":"Roma",
    "wof:name":"F.lli Palazzo Di Enzo Palazzo Sas",
    "wof:placetype":"venue"
},
  "geometry": {"coordinates":[12.4691133499,41.8008003235],"type":"Point"}
}