{
  "type": "Feature",
  "properties": {
    "addr:full":"20123 Milano Milano Milano 20123",
    "addr:postcode":"20123;20123",
    "iso:country":"IT",
    "sg:address":"20123 Milano",
    "sg:city":"Milano",
    "sg:orig_category":"Tessuti E Stoffe. Tessuti Arredamento, Tende E Tappeti",
    "sg:phone":"+39 02 8645 2691",
    "sg:postcode":"20123",
    "sg:province":"Milano",
    "wof:name":"D & D - De Architectura Meeting Point Srl",
    "wof:placetype":"venue"
},
  "geometry": {"coordinates":[9.182878,45.459827],"type":"Point"}
}