{
  "type": "Feature",
  "properties": {
    "iso:country":"IT",
    "sg:address":"177, Via Pianezza 10151 Torino",
    "sg:city":"Torino",
    "sg:classifiers":[
        {
            "category":"Shopping",
            "type":"Retail Goods"
        }
    ],
    "sg:phone":"+39 011 455 3662",
    "sg:postcode":"10151",
    "sg:province":"Torino",
    "sg:tags":[
        "finished",
        "-",
        "metallic"
    ],
    "wof:name":"Tecnobajardi Di Innocente Enzo & C. Snc",
    "wof:placetype":"venue"
},
  "geometry": {"coordinates":[7.5734267235,45.0668830872],"type":"Point"}
}