{
  "type": "Feature",
  "properties": {
    "addr:full":"20092 Cinisello Balsamo Cinisello Balsamo Milano 20092",
    "addr:postcode":"20092;20092",
    "iso:country":"IT",
    "sg:address":"20092 Cinisello Balsamo",
    "sg:city":"Cinisello Balsamo",
    "sg:orig_category":"Professionisti - Studi E Servizi Ed Associazioni Di Interesse Aziendale. Associazioni Ed Organismi Di Interesse Pubblico",
    "sg:phone":"+39 02 6601 3711",
    "sg:postcode":"20092",
    "sg:province":"Milano",
    "wof:name":"Lega Nord",
    "wof:placetype":"venue"
},
  "geometry": {"coordinates":[9.2133169174,45.5663871765],"type":"Point"}
}