{
  "type": "Feature",
  "properties": {
    "addr:full":"20090 Segrate Segrate Milano 20090",
    "addr:postcode":"20090;20090",
    "iso:country":"IT",
    "sg:address":"20090 Segrate",
    "sg:city":"Segrate",
    "sg:orig_category":"Agenzie D'affari E Servizi Commerciali",
    "sg:phone":"+39 02 213 5577",
    "sg:postcode":"20090",
    "sg:province":"Milano",
    "wof:name":"Pronto Service Di Gina Cosco",
    "wof:placetype":"venue"
},
  "geometry": {"coordinates":[9.287485,45.499279],"type":"Point"}
}