{
  "type": "Feature",
  "properties": {
    "iso:country":"IT",
    "sg:address":"40013 Castel Maggiore",
    "sg:city":"Castel Maggiore",
    "sg:orig_category":"Lamiere - Lavorazione",
    "sg:phone":"+39 051 700577",
    "sg:postcode":"40013",
    "sg:province":"Bologna",
    "wof:name":"Nuova C.t.r. Di Persici Mileo Arena & C. Snc",
    "wof:placetype":"venue"
},
  "geometry": {"coordinates":[11.374831,44.557121],"type":"Point"}
}