{
  "type": "Feature",
  "properties": {
    "iso:country":"IT",
    "sg:address":"18, V. G. Bossi 13044 Crescentino",
    "sg:city":"Crescentino",
    "sg:classifiers":[
        {
            "category":"Shopping",
            "type":"Retail Goods"
        }
    ],
    "sg:phone":"+39 0161 831150",
    "sg:postcode":"13044",
    "sg:province":"Vercelli",
    "sg:tags":[
        "finished",
        "-",
        "metallic"
    ],
    "sg:website":"http://www.paginegialle.it/fraba",
    "wof:name":"Fraba",
    "wof:placetype":"venue"
},
  "geometry": {"coordinates":[8.4263935089,45.3210601807],"type":"Point"}
}