{
  "type": "Feature",
  "properties": {
    "addr:full":"87050 Figline Vegliaturo Figline Vegliaturo Cosenza 87050",
    "addr:postcode":"87050;vegliaturo;87050",
    "iso:country":"IT",
    "sg:address":"87050 Figline Vegliaturo",
    "sg:city":"Figline Vegliaturo",
    "sg:orig_category":"Cartotecnica E Servizi. Articoli Per Imballaggio E Confezionamento",
    "sg:phone":"+39 0984 969173",
    "sg:postcode":"87050",
    "sg:province":"Cosenza",
    "wof:name":"Interplast Srl",
    "wof:placetype":"venue"
},
  "geometry": {"coordinates":[16.304396,39.213398],"type":"Point"}
}