{
  "type": "Feature",
  "properties": {
    "addr:full":"10121 Torino Torino Torino 10121",
    "addr:postcode":"10121;10121",
    "iso:country":"IT",
    "sg:address":"10121 Torino",
    "sg:city":"Torino",
    "sg:orig_category":"Agenzie Immobiliari",
    "sg:phone":"+39 011 562 6242",
    "sg:postcode":"10121",
    "sg:province":"Torino",
    "wof:name":"Immoconsult Sas",
    "wof:placetype":"venue"
},
  "geometry": {"coordinates":[7.568362,45.066238],"type":"Point"}
}