{
  "type": "Feature",
  "properties": {
    "addr:full":"9, Via Degli Artigiani 22040 Lurago D'erba Como 22040",
    "addr:postcode":"22040;22040",
    "addr:street":"Via Degli Artigiani",
    "iso:country":"IT",
    "sg:address":"9, Via Degli Artigiani 22040 Lurago D'erba",
    "sg:classifiers":[
        {
            "category":"Home & Garden",
            "subcategory":"Home Furnishings",
            "type":"Retail Goods"
        }
    ],
    "sg:phone":"+39 031 359 9008",
    "sg:postcode":"22040",
    "sg:province":"Como",
    "sg:tags":[
        "household"
    ],
    "wof:name":"Baxter S.r.l.",
    "wof:placetype":"venue"
},
  "geometry": {"coordinates":[9.208639,45.740589],"type":"Point"}
}