{
  "type": "Feature",
  "properties": {
    "addr:full":"Km. 36.300, Via Cassia 01036 Nepi Nepi Viterbo 01036",
    "addr:postcode":"01036;01036",
    "addr:street":"Km. 36.300 Via Cassia",
    "iso:country":"IT",
    "sg:address":"Km. 36.300, Via Cassia 01036 Nepi",
    "sg:city":"Nepi",
    "sg:classifiers":[
        {
            "category":"Manufacturing",
            "subcategory":"Glass & Minerals",
            "type":"Manufacturing & Wholesale Goods"
        }
    ],
    "sg:phone":"+39 390 761 5291",
    "sg:postcode":"01036",
    "sg:province":"Viterbo",
    "sg:tags":[
        "building",
        "material"
    ],
    "wof:name":"Ceramica Vallelunga S R L",
    "wof:placetype":"venue"
},
  "geometry": {"coordinates":[12.104854,42.417381],"type":"Point"}
}