{
  "type": "Feature",
  "properties": {
    "iso:country":"IT",
    "sg:address":"100, Via Mandolossa 25064 Gussago",
    "sg:city":"Gussago",
    "sg:classifiers":[
        {
            "category":"Shopping",
            "subcategory":"Stationery & Office Supplies",
            "type":"Retail Goods"
        }
    ],
    "sg:phone":"+39 030 252 6511",
    "sg:postcode":"25064",
    "sg:province":"Brescia",
    "sg:tags":[
        "professional"
    ],
    "wof:name":"Sidac Spa",
    "wof:placetype":"venue"
},
  "geometry": {"coordinates":[10.1553268433,45.5591087341],"type":"Point"}
}