{
  "type": "Feature",
  "properties": {
    "iso:country":"IT",
    "sg:address":"12078 Ormea",
    "sg:city":"Ormea",
    "sg:orig_category":"Servizi Per Lo Sport E Il Tempo Libero. Alberghi E Strutture Extra Alberghiere",
    "sg:phone":"+39 0174 390196",
    "sg:postcode":"12078",
    "sg:province":"Cuneo",
    "wof:name":"Club Alpino Italiano",
    "wof:placetype":"venue"
},
  "geometry": {"coordinates":[7.782352,44.144894],"type":"Point"}
}