{
  "type": "Feature",
  "properties": {
    "addr:full":"22, V. Matteotti 22012 Cernobbio Cernobbio Como 22012",
    "addr:housenumber":"22",
    "addr:postcode":"22012;22012",
    "addr:street":"V. Matteotti",
    "iso:country":"IT",
    "sg:address":"22, V. Matteotti 22012 Cernobbio",
    "sg:city":"Cernobbio",
    "sg:classifiers":[
        {
            "category":"Shopping",
            "subcategory":"Clothing, Apparel, & Fashions",
            "type":"Retail Goods"
        }
    ],
    "sg:phone":"+39 031 334 7038",
    "sg:postcode":"22012",
    "sg:province":"Como",
    "sg:tags":[
        "clothing",
        "accessory"
    ],
    "sg:website":"http://www.paginegialle.it/sirioties",
    "wof:name":"Sirio Di Bistoletti L.",
    "wof:placetype":"venue"
},
  "geometry": {"coordinates":[9.061996,45.838638],"type":"Point"}
}