{
  "type": "Feature",
  "properties": {
    "iso:country":"IT",
    "sg:address":"Via Archimede 19 37010 Affi",
    "sg:city":"Affi",
    "sg:classifiers":[
        {
            "category":"Manufacturing",
            "subcategory":"Building Materials",
            "type":"Manufacturing & Wholesale Goods"
        }
    ],
    "sg:phone":"+39 045 626 9016",
    "sg:postcode":"37010",
    "sg:province":"Verona",
    "sg:tags":[
        "cement"
    ],
    "sg:website":"www.odem.it",
    "wof:name":"Odem Srl",
    "wof:placetype":"venue"
},
  "geometry": {"coordinates":[10.799122,45.549381],"type":"Point"}
}