{
  "type": "Feature",
  "properties": {
    "addr:full":"00193 Roma Roma Roma 00193",
    "addr:postcode":"00193;00193",
    "iso:country":"IT",
    "sg:address":"00193 Roma",
    "sg:city":"Roma",
    "sg:orig_category":"Prodotti Alimentari. Bevande, Vini E Liquori. Medicinali E Prodotti Parafarmaceutici",
    "sg:phone":"+39 06 6880 5566",
    "sg:postcode":"00193",
    "sg:province":"Roma",
    "wof:name":"Settespighe Sas Di Maffei Aldo",
    "wof:placetype":"venue"
},
  "geometry": {"coordinates":[12.4634084702,41.9057273865],"type":"Point"}
}