{
  "type": "Feature",
  "properties": {
    "iso:country":"IT",
    "sg:address":"19, V. Trevisago 25080 Manerba Del Garda",
    "sg:city":"Manerba del Garda",
    "sg:classifiers":[
        {
            "category":"Food & Beverages",
            "subcategory":"Groceries & Convenience Stores",
            "type":"Retail Goods"
        }
    ],
    "sg:phone":"+39 036 555 1013",
    "sg:postcode":"25080",
    "sg:province":"Brescia",
    "sg:tags":[
        "drink"
    ],
    "sg:website":"http://www.avanzi.net",
    "wof:name":"Avanzi F.lli Cantine Frantoio",
    "wof:placetype":"venue"
},
  "geometry": {"coordinates":[10.531329,45.542706],"type":"Point"}
}