{
  "type": "Feature",
  "properties": {
    "iso:country":"IT",
    "sg:address":"1/8, Via Pila 40037 Sasso Marconi",
    "sg:city":"Sasso Marconi",
    "sg:classifiers":[
        {
            "category":"Wholesale",
            "subcategory":"Machinery & Supplies",
            "type":"Manufacturing & Wholesale Goods"
        }
    ],
    "sg:phone":"+39 39051846851",
    "sg:postcode":"40037",
    "sg:province":"Bologna",
    "sg:tags":[
        "equipment",
        "-",
        "instrument",
        "measurement"
    ],
    "wof:name":"I.m.s. Internazionale Medico Scientifica (s.r.l.)",
    "wof:placetype":"venue"
},
  "geometry": {"coordinates":[11.28271,44.432178],"type":"Point"}
}