{
  "type": "Feature",
  "properties": {
    "addr:full":"52100 Arezzo Arezzo Arezzo 52100",
    "addr:postcode":"52100;52100",
    "iso:country":"IT",
    "sg:address":"52100 Arezzo",
    "sg:city":"Arezzo",
    "sg:orig_category":"Articoli Da Regalo. Regalistica Aziendale",
    "sg:phone":"+39 0575 908486",
    "sg:postcode":"52100",
    "sg:province":"Arezzo",
    "wof:name":"Hollow Gold Srl",
    "wof:placetype":"venue"
},
  "geometry": {"coordinates":[11.871062,43.453606],"type":"Point"}
}