{
  "type": "Feature",
  "properties": {
    "iso:country":"IT",
    "sg:address":"36015 Schio",
    "sg:city":"Schio",
    "sg:orig_category":"Cartotecnica E Servizi. Prodotti E Manufatti In Materie Plastiche. Articoli Per Imballaggio E Confezionamento",
    "sg:phone":"+39 0445 575190",
    "sg:postcode":"36015",
    "sg:province":"Vicenza",
    "wof:name":"Saf F.lli Bianco Srl",
    "wof:placetype":"venue"
},
  "geometry": {"coordinates":[11.54653,45.572327],"type":"Point"}
}