{
  "type": "Feature",
  "properties": {
    "iso:country":"IT",
    "sg:address":"3, Via F.lli Cervi 46023 Gonzaga",
    "sg:city":"Gonzaga",
    "sg:classifiers":[
        {
            "category":"Shopping",
            "subcategory":"Clothing, Apparel, & Fashions",
            "type":"Retail Goods"
        }
    ],
    "sg:phone":"+39 0376 512411",
    "sg:postcode":"46023",
    "sg:province":"Mantova",
    "sg:tags":[
        "clothes"
    ],
    "wof:name":"Luemme S.p.a.",
    "wof:placetype":"venue"
},
  "geometry": {"coordinates":[10.797698,45.160366],"type":"Point"}
}