{
  "type": "Feature",
  "properties": {
    "iso:country":"IT",
    "sg:address":"Via Delle Industrie 148 30020 Marcon",
    "sg:city":"Marcon",
    "sg:classifiers":[
        {
            "category":"Shopping",
            "subcategory":"Clothing, Apparel, & Fashions",
            "type":"Retail Goods"
        }
    ],
    "sg:phone":"+39 041 595 1260",
    "sg:postcode":"30020",
    "sg:province":"Venezia",
    "sg:tags":[
        "sportswear"
    ],
    "sg:website":"www.silverlinesport.com",
    "wof:name":"Ceolin Cristian Silver Line",
    "wof:placetype":"venue"
},
  "geometry": {"coordinates":[12.29197,45.546219],"type":"Point"}
}