{
  "type": "Feature",
  "properties": {
    "iso:country":"IT",
    "sg:address":"26041 Casalmaggiore",
    "sg:city":"Casalmaggiore",
    "sg:orig_category":"Automobili E Mezzi Di Trasporto",
    "sg:phone":"+39 0375 42414",
    "sg:postcode":"26041",
    "sg:province":"Cremona",
    "wof:name":"Capelli Automobili Srl",
    "wof:placetype":"venue"
},
  "geometry": {"coordinates":[10.422895,44.981167],"type":"Point"}
}