{
  "type": "Feature",
  "properties": {
    "addr:full":"95030 Mascalucia Mascalucia Catania 95030",
    "addr:postcode":"95030;95030",
    "iso:country":"IT",
    "sg:address":"95030 Mascalucia",
    "sg:city":"Mascalucia",
    "sg:orig_category":"Prodotti Alimentari. Agricoltura, Orticoltura E Floricoltura",
    "sg:phone":"+39 095 727 3480",
    "sg:postcode":"95030",
    "sg:province":"Catania",
    "wof:name":"Riso Scotti S.p.a.",
    "wof:placetype":"venue"
},
  "geometry": {"coordinates":[15.0533428192,37.5781440735],"type":"Point"}
}