{
  "type": "Feature",
  "properties": {
    "iso:country":"IT",
    "sg:address":"88063 Catanzaro Lido",
    "sg:orig_category":"Servizi Per Lo Sport E Il Tempo Libero. Servizi Al Turismo",
    "sg:phone":"+39 0961 735973",
    "sg:province":"CZ",
    "wof:name":"Disneyland Di Pitingolo Sas",
    "wof:placetype":"venue"
},
  "geometry": {"coordinates":[-106.576088,31.793894],"type":"Point"}
}