{
  "type": "Feature",
  "properties": {
    "iso:country":"IT",
    "sg:address":"25011 Calcinato",
    "sg:city":"Calcinato",
    "sg:orig_category":"Lavorazioni Metalli, Stampaggio E Saldatura",
    "sg:phone":"+39 030 963092",
    "sg:postcode":"25011",
    "sg:province":"Brescia",
    "wof:name":"Podavini Fratelli Snc",
    "wof:placetype":"venue"
},
  "geometry": {"coordinates":[10.227371,45.548283],"type":"Point"}
}