{
  "type": "Feature",
  "properties": {
    "iso:country":"IT",
    "sg:address":"22063 Cantu'",
    "sg:orig_category":"Servizi E Lavori Per Agricoltura E Zootecnia. Servizi E Lavori Per Ecologia E Smaltimento Rifiuti",
    "sg:phone":"+39 031 700527",
    "sg:postcode":"22063",
    "sg:province":"Como",
    "wof:name":"Consorzio Risanamento Idraulico Bacino Sud Seveso",
    "wof:placetype":"venue"
},
  "geometry": {"coordinates":[9.126978,45.737896],"type":"Point"}
}