{
  "type": "Feature",
  "properties": {
    "addr:full":"7, Via I Maggio 46030 San Giorgio Di Mantova San Giorgio di Mantova Mantova 46030",
    "addr:postcode":"46030;46030",
    "addr:street":"Via I Maggio",
    "iso:country":"IT",
    "sg:address":"7, Via I Maggio 46030 San Giorgio Di Mantova",
    "sg:city":"San Giorgio di Mantova",
    "sg:classifiers":[
        {
            "category":"Shopping",
            "type":"Retail Goods"
        }
    ],
    "sg:phone":"+39 0376 371541",
    "sg:postcode":"46030",
    "sg:province":"Mantova",
    "sg:tags":[
        "finished",
        "-",
        "metallic"
    ],
    "wof:name":"Volponi Massimiliano E Figlio (s.n.c.)",
    "wof:placetype":"venue"
},
  "geometry": {"coordinates":[10.8717050552,45.1731262207],"type":"Point"}
}