{
  "type": "Feature",
  "properties": {
    "addr:full":"95124 Catania Catania Catania 95124",
    "addr:postcode":"95124;95124",
    "iso:country":"IT",
    "sg:address":"95124 Catania",
    "sg:city":"Catania",
    "sg:orig_category":"Servizi E Lavori Per Agricoltura E Zootecnia. Servizi E Lavori Industria Chimica. Servizi Ausiliari Di Analisi, Controllo E Ricerca",
    "sg:phone":"+39 095 715 9995",
    "sg:postcode":"95124",
    "sg:province":"Catania",
    "wof:name":"Caponnetto Maria",
    "wof:placetype":"venue"
},
  "geometry": {"coordinates":[15.0809736252,37.5049552917],"type":"Point"}
}