{
  "type": "Feature",
  "properties": {
    "iso:country":"IT",
    "sg:address":"Via Gradara 61100 Pesaro",
    "sg:city":"Pesaro",
    "sg:classifiers":[
        {
            "category":"Home & Garden",
            "subcategory":"Home Furnishings",
            "type":"Retail Goods"
        }
    ],
    "sg:phone":"+39 39072123690",
    "sg:postcode":"61100",
    "sg:province":"Pesaro E Urbino",
    "sg:tags":[
        "household"
    ],
    "wof:name":"Vitali Di Vitali Valentino E Marco S.n.c.",
    "wof:placetype":"venue"
},
  "geometry": {"coordinates":[12.893961,43.905964],"type":"Point"}
}