{
  "type": "Feature",
  "properties": {
    "iso:country":"IT",
    "sg:address":"Cso Cuneo 3 10078 Venaria",
    "sg:classifiers":[
        {
            "category":"Manufacturing",
            "subcategory":"Glass & Minerals",
            "type":"Manufacturing & Wholesale Goods"
        }
    ],
    "sg:phone":"+39 011 424 2133",
    "sg:postcode":"10078",
    "sg:province":"Torino",
    "sg:tags":[
        "crystal",
        "mirror"
    ],
    "wof:name":"Picco & Martini S.r.l.",
    "wof:placetype":"venue"
},
  "geometry": {"coordinates":[7.633593,45.116699],"type":"Point"}
}