{
  "type": "Feature",
  "properties": {
    "iso:country":"IT",
    "sg:address":"25019 Sirmione",
    "sg:city":"Sirmione",
    "sg:orig_category":"Filati E Materie Prime Tessili",
    "sg:phone":"+39 030 919 6506",
    "sg:postcode":"25019",
    "sg:province":"Brescia",
    "wof:name":"Al Capriccio",
    "wof:placetype":"venue"
},
  "geometry": {"coordinates":[10.6173210144,45.476020813],"type":"Point"}
}