{
  "type": "Feature",
  "properties": {
    "addr:full":"Via Dei Pescatori 16128 Genova Genova Genova 16128",
    "addr:postcode":"16128;16128",
    "addr:street":"Via Dei Pescatori",
    "iso:country":"IT",
    "sg:address":"Via Dei Pescatori 16128 Genova",
    "sg:city":"Genova",
    "sg:classifiers":[
        {
            "category":"Autos & Motor Vehicles",
            "subcategory":"Boat Sales",
            "type":"Retail Goods"
        }
    ],
    "sg:phone":"+39 010 595 5040",
    "sg:postcode":"16128",
    "sg:province":"Genova",
    "wof:name":"G.m.g. General Montaggi Genovesi S.r.l.",
    "wof:placetype":"venue"
},
  "geometry": {"coordinates":[8.938192,44.397606],"type":"Point"}
}