{
  "type": "Feature",
  "properties": {
    "iso:country":"IT",
    "sg:address":"10, Via San Francesco D'assisi 22079 Villa Guardia",
    "sg:city":"Villa Guardia",
    "sg:classifiers":[
        {
            "category":"Shopping",
            "subcategory":"Crafts & Fabrics",
            "type":"Retail Goods"
        }
    ],
    "sg:phone":"+39 39031563569",
    "sg:postcode":"22079",
    "sg:province":"Como",
    "wof:name":"Gruppocinque Linea Tessile S.r.l.",
    "wof:placetype":"venue"
},
  "geometry": {"coordinates":[9.080450058,45.7868919373],"type":"Point"}
}