{
  "type": "Feature",
  "properties": {
    "addr:full":"265, V. Umberto I 27053 Lungavilla Lungavilla Pavia 27053",
    "addr:housenumber":"265",
    "addr:postcode":"27053;27053",
    "addr:street":"V. Umberto I",
    "iso:country":"IT",
    "sg:address":"265, V. Umberto I 27053 Lungavilla",
    "sg:city":"Lungavilla",
    "sg:classifiers":[
        {
            "category":"Food & Beverages",
            "subcategory":"Bakery",
            "type":"Retail Goods"
        }
    ],
    "sg:phone":"+39 0383 371900",
    "sg:postcode":"27053",
    "sg:province":"Pavia",
    "sg:tags":[
        "grain",
        "cereal"
    ],
    "sg:website":"http://www.biobove.com",
    "wof:name":"Bio' Sas Di Viola Gianmario & C.",
    "wof:placetype":"venue"
},
  "geometry": {"coordinates":[9.081466,45.042557],"type":"Point"}
}