{
  "type": "Feature",
  "properties": {
    "iso:country":"IT",
    "sg:address":"62, Via Buozzi Bruno 40062 Molinella",
    "sg:city":"Molinella",
    "sg:classifiers":[
        {
            "category":"Professional",
            "subcategory":"Engineering",
            "type":"Services"
        }
    ],
    "sg:phone":"+39 051 690 5105",
    "sg:postcode":"40062",
    "sg:province":"Bologna",
    "sg:tags":[
        "machine",
        "-",
        "mechanical"
    ],
    "wof:name":"United Klima Technologies Italia S.r.l.",
    "wof:placetype":"venue"
},
  "geometry": {"coordinates":[11.346481,44.494221],"type":"Point"}
}