{
  "type": "Feature",
  "properties": {
    "iso:country":"IT",
    "sg:address":"24124 Bergamo",
    "sg:city":"Bergamo",
    "sg:orig_category":"Impiantistica E Prodotti Tecnologici Per Edilizia. Forniture Industriali Per Prevenzione, Controllo E Sicurezza",
    "sg:phone":"+39 035 243094",
    "sg:postcode":"24124",
    "sg:province":"Bergamo",
    "wof:name":"Lanzagomma Snc",
    "wof:placetype":"venue"
},
  "geometry": {"coordinates":[9.692514,45.713848],"type":"Point"}
}