{
  "type": "Feature",
  "properties": {
    "iso:country":"IT",
    "sg:address":"Via Trani 41\\\\47 70051 Barletta",
    "sg:city":"Barletta",
    "sg:orig_category":"Ladies' Shoes",
    "sg:phone":"+39 0883 536112",
    "sg:postcode":"70051",
    "sg:province":"Bari",
    "sg:website":"www.stillwinning.it",
    "wof:name":"Still Winning Srl",
    "wof:placetype":"venue"
},
  "geometry": {"coordinates":[16.298702,41.315903],"type":"Point"}
}