{
  "type": "Feature",
  "properties": {
    "addr:full":"23854 Olginate Olginate Lecco 23854",
    "addr:postcode":"23854;23854",
    "iso:country":"IT",
    "sg:address":"23854 Olginate",
    "sg:city":"Olginate",
    "sg:orig_category":"Macchine Utensili E Impianti",
    "sg:phone":"+39 0341 682285",
    "sg:postcode":"23854",
    "sg:province":"Lecco",
    "wof:name":"Fiu-mu Di Brini G. Sas",
    "wof:placetype":"venue"
},
  "geometry": {"coordinates":[9.424914,45.78965],"type":"Point"}
}