{
  "type": "Feature",
  "properties": {
    "addr:full":"60019 Brugnetto Ancona 60019",
    "addr:postcode":"60019;60019",
    "iso:country":"IT",
    "sg:address":"60019 Brugnetto",
    "sg:orig_category":"Accessori Dei Mezzi Di Trasporto",
    "sg:phone":"+39 071 662 0010",
    "sg:postcode":"60019",
    "sg:province":"Ancona",
    "wof:name":"Paolini S.n.c. Di Manna Maria Giuseppina & C.",
    "wof:placetype":"venue"
},
  "geometry": {"coordinates":[13.162938,43.674606],"type":"Point"}
}