{
  "type": "Feature",
  "properties": {
    "iso:country":"IT",
    "sg:address":"20146 Milano",
    "sg:city":"Milano",
    "sg:orig_category":"Professionisti - Studi E Servizi Ed Associazioni Di Interesse Aziendale. Servizi Sociali. Associazioni Ed Organismi Di Interesse Pubblico",
    "sg:phone":"+39 02 415 8653",
    "sg:postcode":"20146",
    "sg:province":"Milano",
    "wof:name":"Oasi S. Francesco",
    "wof:placetype":"venue"
},
  "geometry": {"coordinates":[9.1370506287,45.4563789368],"type":"Point"}
}