{
  "type": "Feature",
  "properties": {
    "iso:country":"IT",
    "sg:address":"23, Via Crosera 33082 Azzano Decimo",
    "sg:city":"Azzano Decimo",
    "sg:classifiers":[
        {
            "category":"Home & Garden",
            "subcategory":"Home Furnishings",
            "type":"Retail Goods"
        }
    ],
    "sg:phone":"+39 0434 640871",
    "sg:postcode":"33082",
    "sg:province":"Pordenone",
    "sg:tags":[
        "household"
    ],
    "wof:name":"Diim S.r.l.",
    "wof:placetype":"venue"
},
  "geometry": {"coordinates":[12.688641,45.892895],"type":"Point"}
}