{
  "type": "Feature",
  "properties": {
    "addr:full":"00040 Monte Porzio Catone Monte Porzio Catone Roma 00040",
    "addr:housenumber":"00040",
    "addr:postcode":"00040",
    "addr:street":"Monte",
    "iso:country":"IT",
    "sg:address":"00040 Monte Porzio Catone",
    "sg:city":"Monte Porzio Catone",
    "sg:orig_category":"Bevande, Vini E Liquori. Agricoltura, Orticoltura E Floricoltura",
    "sg:phone":"+39 06 941 9863",
    "sg:postcode":"00040",
    "sg:province":"Roma",
    "wof:name":"Gruppo Italiano Vini S.c. A R.l.",
    "wof:placetype":"venue"
},
  "geometry": {"coordinates":[12.707801,41.823215],"type":"Point"}
}