{
  "type": "Feature",
  "properties": {
    "addr:full":"2, Via Cattaneo Carlo 48012 Bagnacavallo Bagnacavallo Ravenna 48012",
    "addr:postcode":"48012;48012",
    "addr:street":"Via Cattaneo",
    "iso:country":"IT",
    "sg:address":"2, Via Cattaneo Carlo 48012 Bagnacavallo",
    "sg:city":"Bagnacavallo",
    "sg:classifiers":[
        {
            "category":"Personal",
            "subcategory":"Shoe Repair & Shine",
            "type":"Services"
        }
    ],
    "sg:phone":"+39 39054561949",
    "sg:postcode":"48012",
    "sg:province":"Ravenna",
    "sg:tags":[
        "leather"
    ],
    "wof:name":"Calzaturificio Marco Botti Srl",
    "wof:placetype":"venue"
},
  "geometry": {"coordinates":[11.972003,44.419476],"type":"Point"}
}