{
  "type": "Feature",
  "properties": {
    "iso:country":"IT",
    "sg:address":"Localita' Le Prese 05014 Castel Viscardo",
    "sg:city":"Castel Viscardo",
    "sg:classifiers":[
        {
            "category":"Shopping",
            "subcategory":"Clothing, Apparel, & Fashions",
            "type":"Retail Goods"
        }
    ],
    "sg:phone":"+39 0763 626279",
    "sg:postcode":"05014",
    "sg:province":"Terni",
    "sg:tags":[
        "clothes"
    ],
    "wof:name":"Arcangeletti Ernesto",
    "wof:placetype":"venue"
},
  "geometry": {"coordinates":[12.041715,42.766159],"type":"Point"}
}