{
  "type": "Feature",
  "properties": {
    "iso:country":"IT",
    "sg:address":"20121 Milano",
    "sg:city":"Milano",
    "sg:classifiers":[
        {
            "category":"Health Services",
            "subcategory":"Health Practitioner",
            "type":"Services"
        }
    ],
    "sg:phone":"+39 02 805 6978",
    "sg:postcode":"20121",
    "sg:province":"Milano",
    "sg:tags":[
        "medici"
    ],
    "wof:name":"Miraglia Matteo",
    "wof:placetype":"venue"
},
  "geometry": {"coordinates":[9.186655,45.469738],"type":"Point"}
}