{
  "type": "Feature",
  "properties": {
    "iso:country":"IT",
    "sg:address":"20144 Milano",
    "sg:city":"Milano",
    "sg:classifiers":[
        {
            "category":"Shopping",
            "subcategory":"Stationery & Office Supplies",
            "type":"Retail Goods"
        }
    ],
    "sg:phone":"+39 02 8940 3792",
    "sg:postcode":"20144",
    "sg:province":"Milano",
    "sg:tags":[
        "sector",
        "knitwear",
        "furs",
        "clothing",
        "entertainment"
    ],
    "wof:name":"Brancato Srl Costumi Teatrali",
    "wof:placetype":"venue"
},
  "geometry": {"coordinates":[9.166855,45.45652],"type":"Point"}
}