{
  "type": "Feature",
  "properties": {
    "addr:full":"17030 Castelbianco Castelbianco Savona 17030",
    "addr:housenumber":"17030",
    "addr:postcode":"17030",
    "addr:street":"Castelbianco Castelbianco",
    "iso:country":"IT",
    "sg:address":"17030 Castelbianco",
    "sg:city":"Castelbianco",
    "sg:orig_category":"Termotecnica E Riscaldamento, Apparecchiature E Servizi",
    "sg:phone":"+39 0182 77088",
    "sg:postcode":"17030",
    "sg:province":"Savona",
    "wof:name":"Ingauna Vapore Snc",
    "wof:placetype":"venue"
},
  "geometry": {"coordinates":[8.104395,44.096962],"type":"Point"}
}