{
  "type": "Feature",
  "properties": {
    "addr:full":"55041 Camaiore Camaiore Lucca 55041",
    "addr:postcode":"55041;55041",
    "iso:country":"IT",
    "sg:address":"55041 Camaiore",
    "sg:city":"Camaiore",
    "sg:orig_category":"Agenzie D'affari E Servizi Commerciali",
    "sg:phone":"+39 0584 956322",
    "sg:postcode":"55041",
    "sg:province":"Lucca",
    "wof:name":"Matilda Srl",
    "wof:placetype":"venue"
},
  "geometry": {"coordinates":[10.409048,43.901691],"type":"Point"}
}