{
  "type": "Feature",
  "properties": {
    "iso:country":"IT",
    "sg:address":"27012 Certosa Di Pavia",
    "sg:city":"Certosa di Pavia",
    "sg:orig_category":"Prodotti Finiti Stampati. Servizi Editoriali. Tempo Libero - Articoli E Forniture",
    "sg:phone":"+39 0382 933840",
    "sg:postcode":"27012",
    "sg:province":"Pavia",
    "wof:name":"Zanella Marco",
    "wof:placetype":"venue"
},
  "geometry": {"coordinates":[9.1573171616,45.1850013733],"type":"Point"}
}