{
  "type": "Feature",
  "properties": {
    "iso:country":"IT",
    "sg:address":"42030 Vezzano Sul Crostolo",
    "sg:orig_category":"Alberghi",
    "sg:phone":"+39 0522 600157",
    "sg:postcode":"42030",
    "sg:province":"Reggio Nell'Emilia",
    "wof:name":"Hostaria Venturi",
    "wof:placetype":"venue"
},
  "geometry": {"coordinates":[10.555877,44.55035],"type":"Point"}
}