{
  "type": "Feature",
  "properties": {
    "iso:country":"IT",
    "sg:address":"50041 Calenzano",
    "sg:city":"Calenzano",
    "sg:orig_category":"Lavorazioni Meccaniche E Servizi",
    "sg:phone":"+39 055 887 4550",
    "sg:postcode":"50041",
    "sg:province":"Firenze",
    "wof:name":"Centromeccanica Srl",
    "wof:placetype":"venue"
},
  "geometry": {"coordinates":[11.141737,43.824493],"type":"Point"}
}