{
  "type": "Feature",
  "properties": {
    "iso:country":"IT",
    "sg:address":"80012 Calvizzano",
    "sg:city":"Calvizzano",
    "sg:orig_category":"Armadi Guardaroba",
    "sg:phone":"+39 081 713 0784",
    "sg:postcode":"80012",
    "sg:province":"Napoli",
    "wof:name":"Ciat Snc Dimensione Casa",
    "wof:placetype":"venue"
},
  "geometry": {"coordinates":[14.173304,40.908192],"type":"Point"}
}