{
  "type": "Feature",
  "properties": {
    "iso:country":"IT",
    "sg:address":"4, V. Novella 21046 Malnate",
    "sg:city":"Malnate",
    "sg:classifiers":[
        {
            "category":"Shopping",
            "subcategory":"Computers & Home Electronics",
            "type":"Retail Goods"
        }
    ],
    "sg:phone":"+39 0332 427406",
    "sg:postcode":"21046",
    "sg:province":"Varese",
    "sg:tags":[
        "electronic",
        "electrical",
        "equipment"
    ],
    "sg:website":"http://www.paginegialle.it/fpeffepi",
    "wof:name":"Effepi Srl",
    "wof:placetype":"venue"
},
  "geometry": {"coordinates":[8.890051,45.788284],"type":"Point"}
}