{
  "type": "Feature",
  "properties": {
    "iso:country":"IT",
    "sg:address":"24043 Caravaggio",
    "sg:city":"Caravaggio",
    "sg:orig_category":"Ristorazione E Locali Pubblici Affini. Ristoranti Ed Esercizi Affini. Servizi Ausiliari Di Ristorazione E Di Intrattenimento",
    "sg:phone":"+39 036 330 1930",
    "sg:postcode":"24043",
    "sg:province":"Bergamo",
    "sg:website":"http://www.cascinasancarlo.it",
    "wof:name":"Cascina S. Carlo",
    "wof:placetype":"venue"
},
  "geometry": {"coordinates":[9.641889,45.524223],"type":"Point"}
}