{
  "type": "Feature",
  "properties": {
    "iso:country":"IT",
    "sg:address":"55100 Lucca",
    "sg:city":"Lucca",
    "sg:orig_category":"Prodotti Alimentari",
    "sg:phone":"+39 0583 40521",
    "sg:postcode":"55100",
    "sg:province":"Lucca",
    "wof:name":"Pastificio Mennucci Spa",
    "wof:placetype":"venue"
},
  "geometry": {"coordinates":[10.532740593,43.9138336182],"type":"Point"}
}