{
  "type": "Feature",
  "properties": {
    "addr:full":"33170 Pordenone La comina Pordenone 33170",
    "addr:postcode":"33170;33170",
    "iso:country":"IT",
    "sg:address":"33170 Pordenone",
    "sg:city":"La comina",
    "sg:orig_category":"Scuole Di Orientamento, Formazione E Addestramento Professionale",
    "sg:phone":"+39 0434 361470",
    "sg:postcode":"33170",
    "sg:province":"Pordenone",
    "sg:website":"http://www.formazionepn.org",
    "wof:name":"Opera Sacra Famiglia C.f.p. Villaggio Del Fanciullo",
    "wof:placetype":"venue"
},
  "geometry": {"coordinates":[12.644071,45.992275],"type":"Point"}
}