{
  "type": "Feature",
  "properties": {
    "addr:full":"25, Viale Costa Smeralda 07021 Arzachena Arzachena Olbia-Tempio 07021",
    "addr:housenumber":"25",
    "addr:postcode":"07021;07021",
    "addr:street":"Viale Costa Smeralda",
    "iso:country":"IT",
    "sg:address":"25, Viale Costa Smeralda 07021 Arzachena",
    "sg:city":"Arzachena",
    "sg:classifiers":[
        {
            "category":"Farming",
            "subcategory":"Livestock Farm",
            "type":"Manufacturing & Wholesale Goods"
        }
    ],
    "sg:phone":"+39 39078982405",
    "sg:postcode":"07021",
    "sg:province":"Olbia-Tempio",
    "sg:tags":[
        "agriculture"
    ],
    "wof:name":"Ittico Sarda Srl",
    "wof:placetype":"venue"
},
  "geometry": {"coordinates":[9.390853,41.077518],"type":"Point"}
}