{
  "type": "Feature",
  "properties": {
    "iso:country":"IT",
    "sg:address":"98, V. Romentino 28069 Trecate",
    "sg:city":"Trecate",
    "sg:classifiers":[
        {
            "category":"Food & Beverages",
            "subcategory":"Dairy",
            "type":"Retail Goods"
        }
    ],
    "sg:phone":"+39 0321 770614",
    "sg:postcode":"28069",
    "sg:province":"Novara",
    "sg:tags":[
        "product"
    ],
    "sg:website":"http://www.paginegialle.it/invernizzi-06",
    "wof:name":"Invernizzi Gisberto Francesco & Figlia Srl",
    "wof:placetype":"venue"
},
  "geometry": {"coordinates":[8.730727,45.444557],"type":"Point"}
}