{
  "type": "Feature",
  "properties": {
    "iso:country":"IT",
    "sg:address":"39, Via Chiantigiana 52025 Montevarchi",
    "sg:city":"Montevarchi",
    "sg:classifiers":[
        {
            "category":"Professional",
            "subcategory":"Engineering",
            "type":"Services"
        }
    ],
    "sg:phone":"+39 055 910 2726",
    "sg:postcode":"52025",
    "sg:province":"Arezzo",
    "sg:tags":[
        "machine",
        "-",
        "mechanical"
    ],
    "wof:name":"C.o.m.e.v. (s.p.a.)",
    "wof:placetype":"venue"
},
  "geometry": {"coordinates":[11.558905,43.526127],"type":"Point"}
}