{
  "type": "Feature",
  "properties": {
    "iso:country":"IT",
    "sg:address":"13, Via Del Chisso 21052 Busto Arsizio",
    "sg:city":"Busto Arsizio",
    "sg:classifiers":[
        {
            "category":"Utilities",
            "subcategory":"Electric",
            "type":"Services"
        }
    ],
    "sg:phone":"+39 0331 678052",
    "sg:postcode":"21052",
    "sg:province":"Varese",
    "sg:tags":[
        "component",
        "electronic"
    ],
    "wof:name":"Mar - Ita (s.n.c.)",
    "wof:placetype":"venue"
},
  "geometry": {"coordinates":[8.83253,45.605076],"type":"Point"}
}