{
  "type": "Feature",
  "properties": {
    "iso:country":"IT",
    "sg:address":"Via S. Antonio, 19; La Spezia; 19100",
    "sg:classifiers":[
        {
            "category":"Banks & Credit Unions",
            "subcategory":"Bank",
            "type":"Services"
        }
    ],
    "sg:phone":"+39 0187 34427",
    "wof:name":"Banca D'italia",
    "wof:placetype":"venue"
},
  "geometry": {"coordinates":[9.80953,44.097664],"type":"Point"}
}