{
  "type": "Feature",
  "properties": {
    "addr:full":"16162 Genova Genova Genova 16162",
    "addr:postcode":"16162;16162",
    "iso:country":"IT",
    "sg:address":"16162 Genova",
    "sg:city":"Genova",
    "sg:classifiers":[
        {
            "category":"Manufacturing",
            "subcategory":"Motor Vehicles & Parts",
            "type":"Manufacturing & Wholesale Goods"
        }
    ],
    "sg:phone":"+39 010 711583",
    "sg:postcode":"16162",
    "sg:province":"Genova",
    "sg:tags":[
        "spare",
        "vehicles",
        "component",
        "drives"
    ],
    "wof:name":"Ranieri Tonissi Srl",
    "wof:placetype":"venue"
},
  "geometry": {"coordinates":[8.8954296112,44.4696311951],"type":"Point"}
}