{
  "type": "Feature",
  "properties": {
    "iso:country":"IT",
    "sg:address":"31047 Ponte Di Piave",
    "sg:city":"Ponte di Piave",
    "sg:orig_category":"Macchine E Forniture Per Arredamento E Industria Del Legno",
    "sg:phone":"+39 0422 853300",
    "sg:postcode":"31047",
    "sg:province":"Treviso",
    "wof:name":"Legnotranciati Dall'olio Viscardo & Figlio Snc",
    "wof:placetype":"venue"
},
  "geometry": {"coordinates":[12.510603,45.70229],"type":"Point"}
}