{
  "type": "Feature",
  "properties": {
    "iso:country":"IT",
    "sg:address":"Vle Stelvio 57 21052 Busto Arsizio",
    "sg:city":"Busto Arsizio",
    "sg:classifiers":[
        {
            "category":"Insurance",
            "subcategory":"Title Insurance",
            "type":"Services"
        }
    ],
    "sg:phone":"+39 0331 680200",
    "sg:postcode":"21052",
    "sg:province":"Varese",
    "sg:tags":[
        "slipper"
    ],
    "wof:name":"Skintop Srl",
    "wof:placetype":"venue"
},
  "geometry": {"coordinates":[8.826385,45.817604],"type":"Point"}
}