{
  "type": "Feature",
  "properties": {
    "iso:country":"IT",
    "sg:address":"Viale Della Repubblica 1; Misano; 47046",
    "sg:classifiers":[
        {
            "category":"Banks & Credit Unions",
            "subcategory":"Bank",
            "type":"Services"
        }
    ],
    "sg:phone":"+39 0541 610846",
    "wof:name":"Banca Popolare Valconca Scarl",
    "wof:placetype":"venue"
},
  "geometry": {"coordinates":[12.618029,43.970791],"type":"Point"}
}