{
  "type": "Feature",
  "properties": {
    "iso:country":"IT",
    "sg:address":"35020 Ponte San Nicolo'",
    "sg:orig_category":"Servizi E Lavori Per Ecologia E Smaltimento Rifiuti. Forniture Industriali Per Prevenzione, Controllo E Sicurezza",
    "sg:phone":"+39 049 717461",
    "sg:postcode":"35020",
    "sg:province":"Padova",
    "wof:name":"Ceola Danilo & C. Snc",
    "wof:placetype":"venue"
},
  "geometry": {"coordinates":[11.943635,45.367046],"type":"Point"}
}