{
  "type": "Feature",
  "properties": {
    "iso:country":"IT",
    "sg:address":"10098 Rivoli",
    "sg:city":"Rivoli",
    "sg:orig_category":"Birra - Produzione E Commercio",
    "sg:phone":"+39 011 957 4822",
    "sg:postcode":"10098",
    "sg:province":"Torino",
    "wof:name":"Vendetti Distribuzione Srl",
    "wof:placetype":"venue"
},
  "geometry": {"coordinates":[7.558302,45.057827],"type":"Point"}
}