{
  "type": "Feature",
  "properties": {
    "iso:country":"IT",
    "sg:address":"52100 Arezzo",
    "sg:city":"Arezzo",
    "sg:orig_category":"Agenzie D'affari E Servizi Commerciali",
    "sg:phone":"+39 800 117 766",
    "sg:postcode":"52100",
    "sg:province":"Arezzo",
    "wof:name":"Pec - Pronto Emergenza Casa Srl",
    "wof:placetype":"venue"
},
  "geometry": {"coordinates":[11.871904,43.454571],"type":"Point"}
}