{
  "type": "Feature",
  "properties": {
    "iso:country":"IT",
    "sg:address":"41013 Castelfranco Emilia",
    "sg:city":"Castelfranco Emilia",
    "sg:orig_category":"Detergenti Industriali",
    "sg:phone":"+39 059 937313",
    "sg:postcode":"41013",
    "sg:province":"Modena",
    "wof:name":"Greenwood Di De Feo Daniela E C. Snc",
    "wof:placetype":"venue"
},
  "geometry": {"coordinates":[11.117111,44.631409],"type":"Point"}
}