{
  "type": "Feature",
  "properties": {
    "iso:country":"IT",
    "sg:address":"Via Portogaleo 04020 Santi Cosma E Damiano",
    "sg:city":"Santi Cosma e Damiano",
    "sg:classifiers":[
        {
            "category":"Wholesale",
            "subcategory":"Drugs",
            "type":"Manufacturing & Wholesale Goods"
        }
    ],
    "sg:phone":"+39 390 771 6211",
    "sg:postcode":"04020",
    "sg:province":"Latina",
    "sg:tags":[
        "chemical",
        "pharmaceutical"
    ],
    "wof:name":"Manuli Autoadesivi S.p.a.",
    "wof:placetype":"venue"
},
  "geometry": {"coordinates":[12.9037,41.467598],"type":"Point"}
}