{
  "type": "Feature",
  "properties": {
    "iso:country":"IT",
    "sg:address":"20089 Rozzano",
    "sg:city":"Rozzano",
    "sg:orig_category":"Prodotti E Manufatti In Materie Plastiche",
    "sg:phone":"+39 02 5751 0233",
    "sg:postcode":"20089",
    "sg:province":"Milano",
    "wof:name":"Grafoplast (s.p.a.)",
    "wof:placetype":"venue"
},
  "geometry": {"coordinates":[9.1528587341,45.3934020996],"type":"Point"}
}