{
  "type": "Feature",
  "properties": {
    "iso:country":"IT",
    "sg:address":"35010 Saletto Di Vigodarzere",
    "sg:city":"Saletto di Vigodarzere",
    "sg:orig_category":"Minuterie Di Precisione",
    "sg:phone":"+39 049 768645",
    "sg:postcode":"35010",
    "sg:province":"Padova",
    "wof:name":"Minustar Di Zanatta A. E C. Snc",
    "wof:placetype":"venue"
},
  "geometry": {"coordinates":[11.8765888214,45.4095687866],"type":"Point"}
}