{
  "type": "Feature",
  "properties": {
    "addr:full":"5, Via Locatelli Antonio 20124 Milano Milano Milano 20124",
    "addr:postcode":"20124;20124",
    "addr:street":"Via Locatelli Antonio",
    "iso:country":"IT",
    "sg:address":"5, Via Locatelli Antonio 20124 Milano",
    "sg:city":"Milano",
    "sg:classifiers":[
        {
            "category":"Shopping",
            "type":"Retail Goods"
        }
    ],
    "sg:phone":"+39 39026738341",
    "sg:postcode":"20124",
    "sg:province":"Milano",
    "sg:tags":[
        "finished",
        "-",
        "metallic"
    ],
    "wof:name":"Petrolvalves Srl",
    "wof:placetype":"venue"
},
  "geometry": {"coordinates":[9.1983270645,45.4811515808],"type":"Point"}
}