{
  "type": "Feature",
  "properties": {
    "iso:country":"IT",
    "sg:address":"41053 Maranello",
    "sg:city":"Maranello",
    "sg:orig_category":"Ceramiche E Refrattari - Impianti, Macchine E Materiali",
    "sg:phone":"+39 0536 943339",
    "sg:postcode":"41053",
    "sg:province":"Modena",
    "wof:name":"C.d.s. Di Manfredini Sante & C. Snc",
    "wof:placetype":"venue"
},
  "geometry": {"coordinates":[10.877775,44.530617],"type":"Point"}
}