{
  "type": "Feature",
  "properties": {
    "iso:country":"IT",
    "sg:address":"16129 Genova",
    "sg:city":"Genova",
    "sg:orig_category":"Informatica - Consulenza E Servizi. Automazione E Macchine Per Ufficio. Servizi Ausiliari Di Analisi, Controllo E Ricerca. Servizi Per Aziende, Manifestazioni E Supporto Agli Scambi Commerciali",
    "sg:phone":"+39 010 310 6925",
    "sg:postcode":"16129",
    "sg:province":"Genova",
    "sg:website":"http://www.tin.it/comsis",
    "wof:name":"Comunicazione & Sistemi",
    "wof:placetype":"venue"
},
  "geometry": {"coordinates":[8.9526,44.403099],"type":"Point"}
}