{
  "type": "Feature",
  "properties": {
    "iso:country":"IT",
    "sg:address":"22071 Cadorago",
    "sg:city":"Cadorago",
    "sg:orig_category":"Tessuti E Stoffe. Filati E Materie Prime Tessili",
    "sg:phone":"+39 031 903144",
    "sg:postcode":"22071",
    "sg:province":"Como",
    "wof:name":"Sama Tessile (s.n.c.)",
    "wof:placetype":"venue"
},
  "geometry": {"coordinates":[9.080233,45.810627],"type":"Point"}
}