{
  "type": "Feature",
  "properties": {
    "iso:country":"IT",
    "sg:address":"15/b, Viale Delle Industrie 33085 Maniago",
    "sg:city":"Maniago",
    "sg:classifiers":[
        {
            "category":"Shopping",
            "type":"Retail Goods"
        }
    ],
    "sg:phone":"+39 39042772376",
    "sg:postcode":"33085",
    "sg:province":"Pordenone",
    "sg:tags":[
        "finished",
        "-",
        "metallic"
    ],
    "wof:name":"Sta-for Di Gaspardo Luigino & C. Snc",
    "wof:placetype":"venue"
},
  "geometry": {"coordinates":[12.655043602,45.9626502991],"type":"Point"}
}