{
  "type": "Feature",
  "properties": {
    "iso:country":"IT",
    "sg:address":"22100 Como",
    "sg:city":"Como",
    "sg:orig_category":"Accessori Moda D'abbigliamento",
    "sg:phone":"+39 031 308346",
    "sg:postcode":"22100",
    "sg:province":"Como",
    "sg:website":"http://www.paginegialle.it/nouveaute",
    "wof:name":"Noveaute Snc",
    "wof:placetype":"venue"
},
  "geometry": {"coordinates":[9.097794,45.792786],"type":"Point"}
}