{
  "type": "Feature",
  "properties": {
    "addr:full":"20025 Legnano Legnano Milano 20025",
    "addr:postcode":"20025;20025",
    "iso:country":"IT",
    "sg:address":"20025 Legnano",
    "sg:city":"Legnano",
    "sg:orig_category":"Metalli E Leghe",
    "sg:phone":"+39 0331 428611",
    "sg:postcode":"20025",
    "sg:province":"Milano",
    "wof:name":"Loterios S.p.a.",
    "wof:placetype":"venue"
},
  "geometry": {"coordinates":[9.3089780807,45.434841156],"type":"Point"}
}