{
  "type": "Feature",
  "properties": {
    "addr:full":"20122 Milano Milano Milano 20122",
    "addr:postcode":"20122;20122",
    "iso:country":"IT",
    "sg:address":"20122 Milano",
    "sg:city":"Milano",
    "sg:orig_category":"Ospedali E Servizi Sanitari. Servizi Sociali. Associazioni Ed Organismi Di Interesse Pubblico",
    "sg:phone":"+39 02 5843 0313",
    "sg:postcode":"20122",
    "sg:province":"Milano",
    "wof:name":"Asm Associazione Italiana Studio Malformazioni Onlus",
    "wof:placetype":"venue"
},
  "geometry": {"coordinates":[9.186964,45.453487],"type":"Point"}
}