{
  "type": "Feature",
  "properties": {
    "addr:full":"1, Viale Richard Giulio 20143 Milano Milano Milano 20143",
    "addr:postcode":"20143;20143",
    "addr:street":"Viale Richard Giulio",
    "iso:country":"IT",
    "sg:address":"1, Viale Richard Giulio 20143 Milano",
    "sg:city":"Milano",
    "sg:classifiers":[
        {
            "category":"Professional",
            "subcategory":"Computer Services",
            "type":"Services"
        }
    ],
    "sg:phone":"+39 390 289 1741",
    "sg:postcode":"20143",
    "sg:province":"Milano",
    "sg:tags":[
        "information",
        "technology"
    ],
    "wof:name":"Harpaceas Srl",
    "wof:placetype":"venue"
},
  "geometry": {"coordinates":[9.146602,45.445164],"type":"Point"}
}