{
  "type": "Feature",
  "properties": {
    "iso:country":"IT",
    "sg:address":"00141 Roma",
    "sg:city":"Roma",
    "sg:orig_category":"Automazione E Macchine Per Ufficio. Arredi Ed Attrezzature Per Attivita' Commerciali Ed Artigianali",
    "sg:phone":"+39 06 817 1151",
    "sg:postcode":"00141",
    "sg:province":"Roma",
    "wof:name":"Penta Electronic Srl",
    "wof:placetype":"venue"
},
  "geometry": {"coordinates":[12.526622,41.935543],"type":"Point"}
}