{
  "type": "Feature",
  "properties": {
    "addr:full":"51, Via Gonin Francesco 10137 Torino Torino Torino 10137",
    "addr:postcode":"10137;10137",
    "addr:street":"Via Gonin Francesco",
    "iso:country":"IT",
    "sg:address":"51, Via Gonin Francesco 10137 Torino",
    "sg:city":"Torino",
    "sg:classifiers":[
        {
            "category":"Shopping",
            "subcategory":"Computers & Home Electronics",
            "type":"Retail Goods"
        }
    ],
    "sg:phone":"+39 011 309 9259",
    "sg:postcode":"10137",
    "sg:province":"Torino",
    "sg:tags":[
        "electronic",
        "electrical",
        "equipment"
    ],
    "wof:name":"Milone Impianti Elettrici S.r.l.",
    "wof:placetype":"venue"
},
  "geometry": {"coordinates":[7.686619,45.07056],"type":"Point"}
}