{
  "type": "Feature",
  "properties": {
    "addr:full":"3, Via Vittorio Dal Bello 35040 Vighizzolo D'este Padova 35040",
    "addr:postcode":"35040;35040",
    "addr:street":"Via Vittorio Dal Bello",
    "iso:country":"IT",
    "sg:address":"3, Via Vittorio Dal Bello 35040 Vighizzolo D'este",
    "sg:classifiers":[
        {
            "category":"Manufacturing",
            "subcategory":"Metals",
            "type":"Manufacturing & Wholesale Goods"
        }
    ],
    "sg:phone":"+39 39042999266",
    "sg:postcode":"35040",
    "sg:province":"Padova",
    "sg:tags":[
        "processing"
    ],
    "wof:name":"Brogin Giordano",
    "wof:placetype":"venue"
},
  "geometry": {"coordinates":[11.8765888214,45.4095687866],"type":"Point"}
}