{
  "type": "Feature",
  "properties": {
    "iso:country":"IT",
    "sg:address":"Via Ariosto ,149/157 20099 Sesto San Giovanni",
    "sg:city":"Sesto San Giovanni",
    "sg:classifiers":[
        {
            "category":"Mining & Drilling",
            "type":"Manufacturing & Wholesale Goods"
        }
    ],
    "sg:phone":"+39 02 2626 2144",
    "sg:postcode":"20099",
    "sg:province":"Milano",
    "sg:tags":[
        "machine",
        "auger",
        "underground"
    ],
    "sg:website":"www.tecniplant.it",
    "wof:name":"Tecniplant Spa",
    "wof:placetype":"venue"
},
  "geometry": {"coordinates":[9.237611,45.541988],"type":"Point"}
}