{
  "type": "Feature",
  "properties": {
    "iso:country":"IT",
    "sg:address":"60121 Ancona",
    "sg:city":"Ancona",
    "sg:orig_category":"Scuole Pubbliche",
    "sg:phone":"+39 0712201",
    "sg:postcode":"60121",
    "sg:province":"Ancona",
    "sg:website":"http://www.unian.it",
    "wof:name":"Universit\u00c0 Degli Studi Di Ancona",
    "wof:placetype":"venue"
},
  "geometry": {"coordinates":[13.51321,43.617382],"type":"Point"}
}