{
  "type": "Feature",
  "properties": {
    "addr:full":"40050 Monte San Pietro Monte San Pietro Bologna 40050",
    "addr:housenumber":"40050",
    "addr:postcode":"40050",
    "addr:street":"Monte",
    "iso:country":"IT",
    "sg:address":"40050 Monte San Pietro",
    "sg:city":"Monte San Pietro",
    "sg:orig_category":"Accessori Moda D'abbigliamento. Forniture Per Abbigliamento E Pelletterie. Shopping",
    "sg:phone":"+39 051 675 9410",
    "sg:postcode":"40050",
    "sg:province":"Bologna",
    "wof:name":"Roxana Tricot S.n.c Di Giovanetti R. & C.",
    "wof:placetype":"venue"
},
  "geometry": {"coordinates":[11.169447,44.413826],"type":"Point"}
}