{
  "type": "Feature",
  "properties": {
    "addr:full":"35012 Camposampiero Camposampiero Padova 35012",
    "addr:postcode":"35012;35012",
    "iso:country":"IT",
    "sg:address":"35012 Camposampiero",
    "sg:city":"Camposampiero",
    "sg:orig_category":"Servizi E Lavori Per Arredamento E Industria Del Legno",
    "sg:phone":"+39 049 579 1777",
    "sg:postcode":"35012",
    "sg:province":"Padova",
    "wof:name":"Vecchiato & C. (s.n.c.)",
    "wof:placetype":"venue"
},
  "geometry": {"coordinates":[11.928808,45.556675],"type":"Point"}
}