{
  "type": "Feature",
  "properties": {
    "addr:full":"09028 Sestu Sestu Cagliari 09028",
    "addr:postcode":"09028;09028",
    "iso:country":"IT",
    "sg:address":"09028 Sestu",
    "sg:city":"Sestu",
    "sg:orig_category":"Manufacturers: Prefabbricati. Servizi E Lavori Per Ecologia E Smaltimento Rifiuti",
    "sg:phone":"+39 070 262163",
    "sg:postcode":"09028",
    "sg:province":"Cagliari",
    "wof:name":"Agus Rosa",
    "wof:placetype":"venue"
},
  "geometry": {"coordinates":[9.088761,39.305717],"type":"Point"}
}