{
  "type": "Feature",
  "properties": {
    "iso:country":"IT",
    "sg:address":"14, Via Allende 41051 Castelnuovo Rangone",
    "sg:city":"Castelnuovo Rangone",
    "sg:classifiers":[
        {
            "category":"Wholesale",
            "subcategory":"Drugs",
            "type":"Manufacturing & Wholesale Goods"
        }
    ],
    "sg:phone":"+39 39059536502",
    "sg:postcode":"41051",
    "sg:province":"Modena",
    "sg:tags":[
        "chemical",
        "pharmaceutical"
    ],
    "wof:name":"Barchemicals (s.r.l.)",
    "wof:placetype":"venue"
},
  "geometry": {"coordinates":[10.924488,44.547882],"type":"Point"}
}