{
  "type": "Feature",
  "properties": {
    "iso:country":"IT",
    "sg:address":"20154 Milano",
    "sg:city":"Milano",
    "sg:orig_category":"Apparecchiature Ed Attrezzature Meccaniche. Elettronica Industriale, Prodotti E Apparecchiature. Impianti, Attrezzature E Forniture Sanitarie Ed Ospedaliere. Apparecchi, Attrezzature E Forniture Per C",
    "sg:phone":"+39 02 345 0880",
    "sg:postcode":"20154",
    "sg:province":"Milano",
    "wof:name":"Coherent Italia",
    "wof:placetype":"venue"
},
  "geometry": {"coordinates":[9.169493,45.489258],"type":"Point"}
}