{
  "type": "Feature",
  "properties": {
    "iso:country":"IT",
    "sg:address":"12, Via Stelvio 23032 Bormio",
    "sg:city":"Bormio",
    "sg:classifiers":[
        {
            "category":"Travel",
            "subcategory":"Travel Agent",
            "type":"Entertainment"
        }
    ],
    "sg:phone":"+39 0342 903447",
    "sg:postcode":"23032",
    "sg:province":"Sondrio",
    "sg:tags":[
        "business"
    ],
    "wof:name":"Terme Bormiesi (s.p.a.)",
    "wof:placetype":"venue"
},
  "geometry": {"coordinates":[10.367694,46.473026],"type":"Point"}
}