{
  "type": "Feature",
  "properties": {
    "iso:country":"IT",
    "sg:address":"15100 Alessandria",
    "sg:city":"Alessandria",
    "sg:orig_category":"Servizi E Lavori Per Agricoltura E Zootecnia",
    "sg:phone":"+39 0131 225281",
    "sg:postcode":"15100",
    "sg:province":"Alessandria",
    "wof:name":"Istituto Zooprofilattico Piemonte E Liguria",
    "wof:placetype":"venue"
},
  "geometry": {"coordinates":[8.627371,44.920555],"type":"Point"}
}