{
  "type": "Feature",
  "properties": {
    "addr:full":"24030 Medolago Medolago Bergamo 24030",
    "addr:postcode":"24030;24030",
    "iso:country":"IT",
    "sg:address":"24030 Medolago",
    "sg:city":"Medolago",
    "sg:orig_category":"Servizi E Lavori Per Industria Alimentare E Bevande",
    "sg:phone":"+39 035 494 8813",
    "sg:postcode":"24030",
    "sg:province":"Bergamo",
    "wof:name":"Pennati Giuseppe",
    "wof:placetype":"venue"
},
  "geometry": {"coordinates":[9.493223,45.673588],"type":"Point"}
}