{
  "type": "Feature",
  "properties": {
    "iso:country":"IT",
    "sg:address":"61020 Tavoleto",
    "sg:city":"Tavoleto",
    "sg:orig_category":"Arredo Camera Letto E Complementi. Servizi E Lavori Per Arredamento E Industria Del Legno",
    "sg:phone":"+39 0722 629422",
    "sg:postcode":"61020",
    "sg:province":"Pesaro E Urbino",
    "sg:website":"http://www.mofeus.it",
    "wof:name":"Morfeus Spa",
    "wof:placetype":"venue"
},
  "geometry": {"coordinates":[12.592044,43.848232],"type":"Point"}
}