{
  "type": "Feature",
  "properties": {
    "addr:full":"25068 Sarezzo Sarezzo Brescia 25068",
    "addr:postcode":"25068;25068",
    "iso:country":"IT",
    "sg:address":"25068 Sarezzo",
    "sg:city":"Sarezzo",
    "sg:orig_category":"Apparecchiature Ed Attrezzature Meccaniche",
    "sg:phone":"+39 030 890 0607",
    "sg:postcode":"25068",
    "sg:province":"Brescia",
    "wof:name":"Pmz Morstek Snc Dei Fratelli Zambelli",
    "wof:placetype":"venue"
},
  "geometry": {"coordinates":[10.197412,45.663994],"type":"Point"}
}