{
  "type": "Feature",
  "properties": {
    "addr:full":"20017 Rho Rho Milano 20017",
    "addr:postcode":"20017;20017",
    "iso:country":"IT",
    "sg:address":"20017 Rho",
    "sg:city":"Rho",
    "sg:orig_category":"Ospedali E Servizi Sanitari. Servizi Sociali. Associazioni Ed Organismi Di Interesse Pubblico",
    "sg:phone":"+39 02 930 6523",
    "sg:postcode":"20017",
    "sg:province":"Milano",
    "wof:name":"Centro Di Consulenza Per La Famiglia",
    "wof:placetype":"venue"
},
  "geometry": {"coordinates":[9.041754,45.529324],"type":"Point"}
}