{
  "type": "Feature",
  "properties": {
    "iso:country":"IT",
    "sg:address":"58, Via Garibaldi Giuseppe 25065 Lumezzane",
    "sg:city":"Lumezzane",
    "sg:classifiers":[
        {
            "category":"Professional",
            "subcategory":"Engineering",
            "type":"Services"
        }
    ],
    "sg:phone":"+39 39030871200",
    "sg:postcode":"25065",
    "sg:province":"Brescia",
    "sg:tags":[
        "machine",
        "-",
        "mechanical"
    ],
    "wof:name":"Gnutti S.n.c. Di Gnutti Gianfranco & C.",
    "wof:placetype":"venue"
},
  "geometry": {"coordinates":[10.222958,45.539829],"type":"Point"}
}