{
  "type": "Feature",
  "properties": {
    "addr:full":"48022 Lugo Lugo Ravenna 48022",
    "addr:postcode":"48022;48022",
    "iso:country":"IT",
    "sg:address":"48022 Lugo",
    "sg:city":"Lugo",
    "sg:orig_category":"Servizi Ausiliari Di Certificati, Riproduzioni, Disegni E Foto",
    "sg:phone":"+39 0545 22288",
    "sg:postcode":"48022",
    "sg:province":"Ravenna",
    "wof:name":"Elios Centro Copie Dei F.lli Collini & C. Snc",
    "wof:placetype":"venue"
},
  "geometry": {"coordinates":[11.914608,44.418667],"type":"Point"}
}