{
  "type": "Feature",
  "properties": {
    "iso:country":"IT",
    "sg:address":"10, Via Marconi 56043 Fauglia",
    "sg:city":"Fauglia",
    "sg:classifiers":[
        {
            "category":"Food & Beverages",
            "subcategory":"Dairy",
            "type":"Retail Goods"
        }
    ],
    "sg:phone":"+39 39050650565",
    "sg:postcode":"56043",
    "sg:province":"Pisa",
    "sg:tags":[
        "product"
    ],
    "wof:name":"Caseificio Busti S.n.c. Di Busti Remo & C.",
    "wof:placetype":"venue"
},
  "geometry": {"coordinates":[10.461408,43.610355],"type":"Point"}
}