{
  "type": "Feature",
  "properties": {
    "addr:full":"Sda Farone 4 42045 Luzzara Reggio Nell'Emilia 42045",
    "addr:housenumber":"4",
    "addr:postcode":"42045;42045",
    "addr:street":"Farone",
    "iso:country":"IT",
    "sg:address":"Sda Farone 4 42045 Luzzara",
    "sg:classifiers":[
        {
            "category":"Banks & Credit Unions",
            "subcategory":"Investment Brokerage",
            "type":"Services"
        }
    ],
    "sg:phone":"+39 0522 977052",
    "sg:postcode":"42045",
    "sg:province":"Reggio Nell'Emilia",
    "sg:tags":[
        "door",
        "panel"
    ],
    "sg:website":"www.bertarelli.savino.it",
    "wof:name":"Bertarelli Savino E C. Snc",
    "wof:placetype":"venue"
},
  "geometry": {"coordinates":[10.627794,44.696228],"type":"Point"}
}