{
  "type": "Feature",
  "properties": {
    "addr:full":"Via Valdentro 125/b 45026 Lendinara Lendinara Rovigo 45026",
    "addr:housenumber":"125 / b",
    "addr:postcode":"45026;45026",
    "addr:street":"Via Valdentro",
    "iso:country":"IT",
    "sg:address":"Via Valdentro 125/b 45026 Lendinara",
    "sg:city":"Lendinara",
    "sg:orig_category":"Ladies' Shoes",
    "sg:phone":"+39 0425 669034",
    "sg:postcode":"45026",
    "sg:province":"Rovigo",
    "wof:name":"Calzature F.lli Baccaro Di Baccaro Amedeo & C. Sas",
    "wof:placetype":"venue"
},
  "geometry": {"coordinates":[11.645009,45.053143],"type":"Point"}
}