{
  "type": "Feature",
  "properties": {
    "iso:country":"IT",
    "sg:address":"40138 Bologna",
    "sg:city":"Bologna",
    "sg:orig_category":"Filati E Materie Prime Tessili",
    "sg:phone":"+39 051 300136",
    "sg:postcode":"40138",
    "sg:province":"Bologna",
    "wof:name":"Zini Francesca",
    "wof:placetype":"venue"
},
  "geometry": {"coordinates":[11.3703613281,44.4928970337],"type":"Point"}
}