{
  "type": "Feature",
  "properties": {
    "addr:full":"84014 Nocera Inferiore Nocera Inferiore Salerno 84014",
    "addr:postcode":"84014;84014",
    "iso:country":"IT",
    "sg:address":"84014 Nocera Inferiore",
    "sg:city":"Nocera Inferiore",
    "sg:classifiers":[
        {
            "category":"Health Services",
            "subcategory":"Health Practitioner",
            "type":"Services"
        }
    ],
    "sg:phone":"+39 081 517 6487",
    "sg:postcode":"84014",
    "sg:province":"Salerno",
    "sg:tags":[
        "medici"
    ],
    "wof:name":"Della Porta Vincenzo & C S.a.s.",
    "wof:placetype":"venue"
},
  "geometry": {"coordinates":[14.64114,40.744003],"type":"Point"}
}