{
  "type": "Feature",
  "properties": {
    "iso:country":"IT",
    "sg:address":"3, V. L. Pavoni20159 Milano",
    "sg:city":"Milano",
    "sg:classifiers":[
        {
            "category":"Parking",
            "subcategory":"Lot",
            "type":"Transportation"
        }
    ],
    "sg:phone":"+39 02 9673 4146",
    "sg:postcode":"20159",
    "sg:province":"Milano",
    "sg:tags":[
        "transport",
        "road"
    ],
    "sg:website":"http://www.paginegialle.it/larosa-mi",
    "wof:name":"Fratelli La Rosa",
    "wof:placetype":"venue"
},
  "geometry": {"coordinates":[9.187343,45.501511],"type":"Point"}
}