{
  "type": "Feature",
  "properties": {
    "addr:full":"88046 Lamezia Terme Lamezia Terme Catanzaro 88046",
    "addr:postcode":"88046;88046",
    "iso:country":"IT",
    "sg:address":"88046 Lamezia Terme",
    "sg:city":"Lamezia Terme",
    "sg:orig_category":"Arredamenti - Vendita Al Dettaglio",
    "sg:phone":"+39 0968 26488",
    "sg:postcode":"88046",
    "sg:province":"Catanzaro",
    "wof:name":"Cugnetto Angela",
    "wof:placetype":"venue"
},
  "geometry": {"coordinates":[16.318193,38.974281],"type":"Point"}
}