{
  "type": "Feature",
  "properties": {
    "addr:full":"20010 Bareggio Bareggio Milano 20010",
    "addr:postcode":"20010;20010",
    "iso:country":"IT",
    "sg:address":"20010 Bareggio",
    "sg:city":"Bareggio",
    "sg:classifiers":[
        {
            "category":"Health Services",
            "subcategory":"Health Practitioner",
            "type":"Services"
        }
    ],
    "sg:phone":"+39 02 9036 1647",
    "sg:postcode":"20010",
    "sg:province":"Milano",
    "sg:tags":[
        "medici"
    ],
    "wof:name":"Viola Emilia",
    "wof:placetype":"venue"
},
  "geometry": {"coordinates":[9.004860878,45.4863624573],"type":"Point"}
}