{
  "type": "Feature",
  "properties": {
    "addr:full":"Via Lecco 58 20059 Vimercate Vimercate Milano 20059",
    "addr:housenumber":"58",
    "addr:postcode":"20059;20059",
    "addr:street":"Via Lecco",
    "iso:country":"IT",
    "sg:address":"Via Lecco 58 20059 Vimercate",
    "sg:city":"Vimercate",
    "sg:classifiers":[
        {
            "category":"Food & Beverages",
            "subcategory":"Fruits & Vegetables",
            "type":"Retail Goods"
        }
    ],
    "sg:phone":"+39 039 669644",
    "sg:postcode":"20059",
    "sg:province":"Milano",
    "sg:tags":[
        "flower",
        "seed"
    ],
    "wof:name":"Magnani Sementi Spa",
    "wof:placetype":"venue"
},
  "geometry": {"coordinates":[9.3603715897,45.6191902161],"type":"Point"}
}