{
  "type": "Feature",
  "properties": {
    "iso:country":"IT",
    "sg:address":"41100 Modena",
    "sg:city":"Baggiovara",
    "sg:orig_category":"Apparecchiature E Sistemi Per Magazzinaggio E Movimentazione",
    "sg:phone":"+39 059 511686",
    "sg:postcode":"41100",
    "sg:province":"Modena",
    "wof:name":"Euromont Srl",
    "wof:placetype":"venue"
},
  "geometry": {"coordinates":[10.86446,44.610073],"type":"Point"}
}