{
  "type": "Feature",
  "properties": {
    "addr:full":"50041 Calenzano Calenzano Firenze 50041",
    "addr:postcode":"50041;50041",
    "iso:country":"IT",
    "sg:address":"50041 Calenzano",
    "sg:city":"Calenzano",
    "sg:orig_category":"Agriturismo",
    "sg:phone":"+39 055 400317",
    "sg:postcode":"50041",
    "sg:province":"Firenze",
    "wof:name":"Fattoria Di Sommaia",
    "wof:placetype":"venue"
},
  "geometry": {"coordinates":[10.747925,43.67762],"type":"Point"}
}