{
  "type": "Feature",
  "properties": {
    "iso:country":"IT",
    "sg:address":"Via Maniago 33080 San Quirino",
    "sg:city":"San Quirino",
    "sg:classifiers":[
        {
            "category":"Food & Beverages",
            "subcategory":"Groceries & Convenience Stores",
            "type":"Retail Goods"
        }
    ],
    "sg:phone":"+39 0434 919138",
    "sg:postcode":"33080",
    "sg:province":"Pordenone",
    "sg:tags":[
        "drink"
    ],
    "wof:name":"F.lli Piazza (s.r.l.)",
    "wof:placetype":"venue"
},
  "geometry": {"coordinates":[12.652166,46.023624],"type":"Point"}
}