{
  "type": "Feature",
  "properties": {
    "iso:country":"IT",
    "sg:address":"Piazza Del Popolo 18 00187 Roma",
    "sg:city":"Roma",
    "sg:classifiers":[
        {
            "category":"Professional",
            "subcategory":"Advertising",
            "type":"Services"
        }
    ],
    "sg:phone":"+39 06 362201",
    "sg:postcode":"00187",
    "sg:province":"Roma",
    "sg:tags":[
        "screen",
        "photo-advertising",
        "film"
    ],
    "sg:website":"www.saatchi-saatchi.com",
    "wof:name":"Saatchi & Saatchi Spa",
    "wof:placetype":"venue"
},
  "geometry": {"coordinates":[12.47692,41.91029],"type":"Point"}
}