{
  "type": "Feature",
  "properties": {
    "iso:country":"IT",
    "sg:address":"80070 Barano D'ischia",
    "sg:orig_category":"Carni, Salumi E Pesci. Zootecnia E Pesca, Allevamento Piccoli Animali",
    "sg:phone":"+39 081 906003",
    "sg:postcode":"80070",
    "sg:province":"Napoli",
    "wof:name":"Agricola S. Luciano Srl",
    "wof:placetype":"venue"
},
  "geometry": {"coordinates":[13.923481,40.708546],"type":"Point"}
}