{
  "type": "Feature",
  "properties": {
    "addr:full":"91, Via Roma 42049 Sant'ilario D'enza Reggio Nell'Emilia 42049",
    "addr:postcode":"42049;42049",
    "addr:street":"Via Roma",
    "iso:country":"IT",
    "sg:address":"91, Via Roma 42049 Sant'ilario D'enza",
    "sg:classifiers":[
        {
            "category":"Manufacturing",
            "subcategory":"Rubber & Plastics",
            "type":"Manufacturing & Wholesale Goods"
        }
    ],
    "sg:phone":"+39 0522 672220",
    "sg:postcode":"42049",
    "sg:province":"Reggio Nell'Emilia",
    "wof:name":"Molino Maioli S.r.l.",
    "wof:placetype":"venue"
},
  "geometry": {"coordinates":[10.4518966675,44.7605476379],"type":"Point"}
}