{
  "type": "Feature",
  "properties": {
    "iso:country":"IT",
    "sg:address":"Viale Ungheria 20; Milano; 20138",
    "sg:city":"Milano",
    "sg:classifiers":[
        {
            "category":"Banks & Credit Unions",
            "subcategory":"Bank",
            "type":"Services"
        }
    ],
    "sg:phone":"+39 02 5540 0181",
    "sg:postcode":"20138",
    "sg:province":"Milano",
    "wof:name":"Banca Mercantile Italiana",
    "wof:placetype":"venue"
},
  "geometry": {"coordinates":[9.245615,45.445724],"type":"Point"}
}