{
  "type": "Feature",
  "properties": {
    "iso:country":"IT",
    "sg:address":"28100 Novara",
    "sg:city":"Novara",
    "sg:orig_category":"Autolinee",
    "sg:phone":"+39 0321 472647",
    "sg:postcode":"28100",
    "sg:province":"Novara",
    "wof:name":"Stn Societ\u00c0 Trasporti Novaresi Srl",
    "wof:placetype":"venue"
},
  "geometry": {"coordinates":[8.630118,45.460281],"type":"Point"}
}