{
  "type": "Feature",
  "properties": {
    "iso:country":"IT",
    "sg:address":"97100 Ragusa",
    "sg:city":"Ragusa",
    "sg:orig_category":"Servizi Per Lo Sport E Il Tempo Libero. Servizi Al Turismo. Servizi Ausiliari Dei Mezzi Di Trasporto. Servizi Ausiliari Per Il Trasporto",
    "sg:phone":"+39 0932 655449",
    "sg:postcode":"97100",
    "sg:province":"Ragusa",
    "sg:website":"http://www.pluchino.com",
    "wof:name":"Pluchino Servizi Srl",
    "wof:placetype":"venue"
},
  "geometry": {"coordinates":[14.72329,36.912281],"type":"Point"}
}