{
  "type": "Feature",
  "properties": {
    "iso:country":"IT",
    "sg:address":"03040 Pignataro Interamna",
    "sg:city":"Pignataro Interamna",
    "sg:orig_category":"Abbigliamento Esterno, Maglierie E Pelliccerie. Servizi E Lavori Per Abbigliamento E Pelletterie",
    "sg:phone":"+39 0776 949518",
    "sg:postcode":"03040",
    "sg:province":"Frosinone",
    "wof:name":"Labo Tex Srl",
    "wof:placetype":"venue"
},
  "geometry": {"coordinates":[13.781568,41.447769],"type":"Point"}
}