{
  "type": "Feature",
  "properties": {
    "addr:full":"60021 Camerano Camerano Ancona 60021",
    "addr:postcode":"60021;60021",
    "iso:country":"IT",
    "sg:address":"60021 Camerano",
    "sg:city":"Camerano",
    "sg:orig_category":"Acciaierie E Fonderie",
    "sg:phone":"+39 071 731033",
    "sg:postcode":"60021",
    "sg:province":"Ancona",
    "sg:website":"http://www.defendi.com",
    "wof:name":"Officine Meccaniche Defendi Srl",
    "wof:placetype":"venue"
},
  "geometry": {"coordinates":[13.55864,43.502674],"type":"Point"}
}