{
  "type": "Feature",
  "properties": {
    "addr:full":"33032 Bertiolo Bertiolo Udine 33032",
    "addr:postcode":"33032;33032",
    "iso:country":"IT",
    "sg:address":"33032 Bertiolo",
    "sg:city":"Bertiolo",
    "sg:orig_category":"Materiali Edili",
    "sg:phone":"+39 0432 914026",
    "sg:postcode":"33032",
    "sg:province":"Udine",
    "wof:name":"Fabello Vittorio Di Fabello Paolo & C. Snc",
    "wof:placetype":"venue"
},
  "geometry": {"coordinates":[13.055747,45.94339],"type":"Point"}
}