{
  "type": "Feature",
  "properties": {
    "addr:full":"20142 Milano Milano Milano 20142",
    "addr:postcode":"20142;20142",
    "iso:country":"IT",
    "sg:address":"20142 Milano",
    "sg:city":"Milano",
    "sg:orig_category":"Carta, Cartone E Prodotti Primari. Forniture Per Uffici",
    "sg:phone":"+39 02 8912 5557",
    "sg:postcode":"20142",
    "sg:province":"Milano",
    "wof:name":"Carella Sas",
    "wof:placetype":"venue"
},
  "geometry": {"coordinates":[9.169571,45.453266],"type":"Point"}
}