{
  "type": "Feature",
  "properties": {
    "addr:full":"12, V. Cesare Battisti 23894 Cremella Cremella Lecco 23894",
    "addr:housenumber":"12",
    "addr:postcode":"23894;23894",
    "addr:street":"V. Cesare Battisti",
    "iso:country":"IT",
    "sg:address":"12, V. Cesare Battisti 23894 Cremella",
    "sg:city":"Cremella",
    "sg:classifiers":[
        {
            "category":"Manufacturing",
            "subcategory":"Metals",
            "type":"Manufacturing & Wholesale Goods"
        }
    ],
    "sg:phone":"+39 39039955622",
    "sg:postcode":"23894",
    "sg:province":"Lecco",
    "sg:tags":[
        "processing"
    ],
    "sg:website":"http://www.paginegialle.it/spiralflex",
    "wof:name":"Spiralflex Srl",
    "wof:placetype":"venue"
},
  "geometry": {"coordinates":[9.3005084991,45.7408485413],"type":"Point"}
}