{
  "type": "Feature",
  "properties": {
    "iso:country":"IT",
    "sg:address":"00165 Roma",
    "sg:city":"Roma",
    "sg:orig_category":"Prodotti E Manufatti In Materie Plastiche",
    "sg:phone":"+39 06 6641 6345",
    "sg:postcode":"00165",
    "sg:province":"Roma",
    "wof:name":"Evangelisti Francesco",
    "wof:placetype":"venue"
},
  "geometry": {"coordinates":[12.4139165878,41.8939208984],"type":"Point"}
}