{
  "type": "Feature",
  "properties": {
    "iso:country":"IT",
    "sg:address":"Via Fossone 8 19034 Ortonovo",
    "sg:city":"Ortonovo",
    "sg:classifiers":[
        {
            "category":"Home & Garden",
            "subcategory":"Building Materials",
            "type":"Retail Goods"
        }
    ],
    "sg:phone":"+39 0187 661680",
    "sg:postcode":"19034",
    "sg:province":"La Spezia",
    "sg:tags":[
        "granite",
        "syenite"
    ],
    "sg:website":"www.gmcspa.com",
    "wof:name":"G.m.c. Spa",
    "wof:placetype":"venue"
},
  "geometry": {"coordinates":[10.038636,44.070213],"type":"Point"}
}