{
  "type": "Feature",
  "properties": {
    "addr:full":"10126 Torino Torino Torino 10126",
    "addr:postcode":"10126;10126",
    "iso:country":"IT",
    "sg:address":"10126 Torino",
    "sg:city":"Torino",
    "sg:orig_category":"Banche E Servizi Finanziari. Acqua, Luce, Gas E Societa' Di Esercizio Pubblico",
    "sg:phone":"+39 011 631 3224",
    "sg:postcode":"10126",
    "sg:province":"Torino",
    "wof:name":"Uniriscossioni S.p.a.",
    "wof:placetype":"venue"
},
  "geometry": {"coordinates":[7.670169,45.039875],"type":"Point"}
}