{
  "type": "Feature",
  "properties": {
    "iso:country":"IT",
    "sg:address":"Via Cottin Ang; Leini; 10040",
    "sg:classifiers":[
        {
            "category":"Banks & Credit Unions",
            "subcategory":"Bank",
            "type":"Services"
        }
    ],
    "sg:phone":"+39 011 997 4007",
    "sg:postcode":"10040",
    "sg:province":"Torino",
    "wof:name":"Istituto Bancario, San Paolo Di Torino Spa",
    "wof:placetype":"venue"
},
  "geometry": {"coordinates":[7.715315,45.183758],"type":"Point"}
}