{
  "type": "Feature",
  "properties": {
    "addr:full":"72017 Ostuni Ostuni Brindisi 72017",
    "addr:postcode":"72017;72017",
    "iso:country":"IT",
    "sg:address":"72017 Ostuni",
    "sg:city":"Ostuni",
    "sg:orig_category":"Alberghi",
    "sg:phone":"+39 0831 304000",
    "sg:postcode":"72017",
    "sg:province":"Brindisi",
    "wof:name":"Cavallo Ges Tur Srl",
    "wof:placetype":"venue"
},
  "geometry": {"coordinates":[17.644037,40.775959],"type":"Point"}
}