{
  "type": "Feature",
  "properties": {
    "iso:country":"IT",
    "sg:address":"Via Brenno 21 20046 Biassono",
    "sg:city":"Biassono",
    "sg:orig_category":"Dishwashers, Commercial",
    "sg:phone":"+39 039 470113",
    "sg:postcode":"20046",
    "sg:province":"Milano",
    "sg:website":"www.cemb.it/ime/",
    "wof:name":"Ime Industrie Meccaniche Elettromeccaniche S.r.l.",
    "wof:placetype":"venue"
},
  "geometry": {"coordinates":[9.291553,45.631645],"type":"Point"}
}