{
  "type": "Feature",
  "properties": {
    "addr:full":"Vle Stazione 5 15025 Morano Po Alessandria 15025",
    "addr:housenumber":"5",
    "addr:postcode":"15025;15025",
    "addr:street":"Vle Stazione;Po",
    "iso:country":"IT",
    "sg:address":"Vle Stazione 5 15025 Morano Po",
    "sg:classifiers":[
        {
            "category":"Wholesale",
            "subcategory":"Fruits & Vegetables",
            "type":"Manufacturing & Wholesale Goods"
        }
    ],
    "sg:phone":"+39 0142 85132",
    "sg:postcode":"15025",
    "sg:province":"Alessandria",
    "sg:tags":[
        "product",
        "cereal"
    ],
    "sg:website":"www.molinoboccardi.it",
    "wof:name":"Molino Boccardi Di Sauro Boccardi D Itta Individuale",
    "wof:placetype":"venue"
},
  "geometry": {"coordinates":[8.366145,45.168884],"type":"Point"}
}