{
  "type": "Feature",
  "properties": {
    "addr:full":"20090 Trezzano Sul Naviglio Trezzano sul Naviglio Milano 20090",
    "addr:postcode":"20090;20090",
    "iso:country":"IT",
    "sg:address":"20090 Trezzano Sul Naviglio",
    "sg:city":"Trezzano sul Naviglio",
    "sg:orig_category":"Motori Ed Organi Di Trasmissione",
    "sg:phone":"+39 02 4840 2572",
    "sg:postcode":"20090",
    "sg:province":"Milano",
    "wof:name":"Effe A. Bovio Srl",
    "wof:placetype":"venue"
},
  "geometry": {"coordinates":[9.0571603775,45.4275970459],"type":"Point"}
}