{
  "type": "Feature",
  "properties": {
    "iso:country":"IT",
    "sg:address":"Via San Giovanni 3; S. Gimigniano; 53037",
    "sg:classifiers":[
        {
            "category":"Banks & Credit Unions",
            "subcategory":"Bank",
            "type":"Services"
        }
    ],
    "sg:phone":"+39 0577 942235",
    "sg:postcode":"53037",
    "sg:province":"Siena",
    "wof:name":"Banca Di Credito Cooperativo, Di Cambiano",
    "wof:placetype":"venue"
},
  "geometry": {"coordinates":[11.04296,43.466785],"type":"Point"}
}