{
  "type": "Feature",
  "properties": {
    "iso:country":"IT",
    "sg:address":"20031 Cesano Maderno",
    "sg:city":"Cesano Maderno",
    "sg:orig_category":"Prodotti Di Base E Forniture Per Industria Alimentare E Bevande. Prodotti Chimici Di Base",
    "sg:phone":"+39 036 250 6843",
    "sg:postcode":"20031",
    "sg:province":"Milano",
    "wof:name":"Big Aliment Sas",
    "wof:placetype":"venue"
},
  "geometry": {"coordinates":[9.1843004227,45.4666671753],"type":"Point"}
}