{
  "type": "Feature",
  "properties": {
    "addr:full":"62014 Corridonia Corridonia Macerata 62014",
    "addr:postcode":"62014;62014",
    "iso:country":"IT",
    "sg:address":"62014 Corridonia",
    "sg:city":"Corridonia",
    "sg:orig_category":"Calzaturifici E Calzolai - Forniture",
    "sg:phone":"+39 0733 281047",
    "sg:postcode":"62014",
    "sg:province":"Macerata",
    "wof:name":"Suolificio Coniplast Di Luconi Nazzareno",
    "wof:placetype":"venue"
},
  "geometry": {"coordinates":[13.493004,43.264717],"type":"Point"}
}