{
  "type": "Feature",
  "properties": {
    "iso:country":"IT",
    "sg:address":"22075 Lurate Caccivio",
    "sg:city":"Lurate Caccivio",
    "sg:orig_category":"Zootecnia E Pesca, Allevamento Piccoli Animali",
    "sg:phone":"+39 031 490084",
    "sg:postcode":"22075",
    "sg:province":"Como",
    "wof:name":"Maino Enrico Di Maino Enrico-adriano E C. (s.n.c.)",
    "wof:placetype":"venue"
},
  "geometry": {"coordinates":[9.03105,45.81292],"type":"Point"}
}