{
  "type": "Feature",
  "properties": {
    "iso:country":"IT",
    "sg:address":"16033 Lavagna",
    "sg:city":"Lavagna",
    "sg:orig_category":"Forniture Per Edilizia E Lavori Pubblici",
    "sg:phone":"+39 0185 323275",
    "sg:postcode":"16033",
    "sg:province":"Genova",
    "sg:website":"http://www.lamaiolica.it",
    "wof:name":"La Maiolica Di Casagrande Giorgio",
    "wof:placetype":"venue"
},
  "geometry": {"coordinates":[8.9555912018,44.3997192383],"type":"Point"}
}