{
  "type": "Feature",
  "properties": {
    "addr:full":"13040 Alice Castello Alice Castello Vercelli 13040",
    "addr:housenumber":"13040",
    "addr:postcode":"13040",
    "addr:street":"Alice Castello",
    "iso:country":"IT",
    "sg:address":"13040 Alice Castello",
    "sg:city":"Alice Castello",
    "sg:orig_category":"Accessori Dei Mezzi Di Trasporto",
    "sg:phone":"+39 0161 909228",
    "sg:postcode":"13040",
    "sg:province":"Vercelli",
    "wof:name":"A.b.c. Moto Di Consolandi Roberto",
    "wof:placetype":"venue"
},
  "geometry": {"coordinates":[8.031776,45.396214],"type":"Point"}
}