{
  "type": "Feature",
  "properties": {
    "iso:country":"IT",
    "sg:address":"90141 Palermo",
    "sg:city":"Palermo",
    "sg:orig_category":"Arredi Ed Attrezzature Per Uffici",
    "sg:phone":"+39 091 307834",
    "sg:postcode":"90141",
    "sg:province":"Palermo",
    "wof:name":"De Magistris Successore V. Bellotti (s.p.a.)",
    "wof:placetype":"venue"
},
  "geometry": {"coordinates":[13.345044,38.128727],"type":"Point"}
}