{
  "type": "Feature",
  "properties": {
    "iso:country":"IT",
    "sg:address":"19, Via Como 22030 Montorfano",
    "sg:city":"Montorfano",
    "sg:classifiers":[
        {
            "category":"Travel",
            "subcategory":"Travel Agent",
            "type":"Entertainment"
        }
    ],
    "sg:phone":"+39 39031200220",
    "sg:postcode":"22030",
    "sg:province":"Como",
    "sg:tags":[
        "business"
    ],
    "wof:name":"Albergo Ristorante Sant'andrea Golf - Hotel",
    "wof:placetype":"venue"
},
  "geometry": {"coordinates":[9.135273,45.786198],"type":"Point"}
}