{
  "type": "Feature",
  "properties": {
    "iso:country":"IT",
    "sg:address":"44100 Ferrara",
    "sg:city":"Ferrara",
    "sg:orig_category":"Dolciumi E Gelati. Condimenti, Spezie, Infusi E Caffe'",
    "sg:phone":"+39 0532 590111",
    "sg:postcode":"44100",
    "sg:province":"Ferrara",
    "sg:website":"http://www.eridania-beghin-say.com",
    "wof:name":"Eridania Spa",
    "wof:placetype":"venue"
},
  "geometry": {"coordinates":[11.641193,44.816753],"type":"Point"}
}