{
  "type": "Feature",
  "properties": {
    "addr:full":"13900 Biella Biella Biella 13900",
    "addr:postcode":"13900;13900",
    "iso:country":"IT",
    "sg:address":"13900 Biella",
    "sg:city":"Biella",
    "sg:orig_category":"Servizi E Lavori Per Abbigliamento E Pelletterie",
    "sg:phone":"+39 015 849 1674",
    "sg:postcode":"13900",
    "sg:province":"Biella",
    "wof:name":"Rammendatura Di Biella",
    "wof:placetype":"venue"
},
  "geometry": {"coordinates":[8.036505,45.57856],"type":"Point"}
}