{
  "type": "Feature",
  "properties": {
    "addr:full":"252 Via Gaiato, 41026 Pavullo Nel Frignano Gaiato Modena 41026",
    "addr:housenumber":"252",
    "addr:postcode":"41026;41026",
    "addr:street":"Via Gaiato;Nel Frignano Gaiato Modena",
    "iso:country":"IT",
    "sg:address":"252 Via Gaiato, 41026 Pavullo Nel Frignano",
    "sg:city":"Gaiato",
    "sg:classifiers":[
        {
            "category":"Banks & Credit Unions",
            "subcategory":"Financial Services",
            "type":"Services"
        }
    ],
    "sg:phone":"+39 39053642039",
    "sg:postcode":"41026",
    "sg:province":"Modena",
    "sg:tags":[
        "banking",
        "finance",
        "insurance"
    ],
    "wof:name":"Villa Pineta Srl",
    "wof:placetype":"venue"
},
  "geometry": {"coordinates":[10.8477954865,44.2922363281],"type":"Point"}
}