{
  "type": "Feature",
  "properties": {
    "addr:full":"66, Via Kennedy Fratelli 07041 Alghero Alghero Sassari 07041",
    "addr:postcode":"07041;07041",
    "addr:street":"Via Kennedy",
    "iso:country":"IT",
    "sg:address":"66, Via Kennedy Fratelli 07041 Alghero",
    "sg:city":"Alghero",
    "sg:classifiers":[
        {
            "category":"Professional",
            "subcategory":"Business Services",
            "type":"Services"
        }
    ],
    "sg:phone":"+39 39079974238",
    "sg:postcode":"07041",
    "sg:province":"Sassari",
    "sg:tags":[
        "advice"
    ],
    "wof:name":"Istituto Professionale Alberghiero",
    "wof:placetype":"venue"
},
  "geometry": {"coordinates":[8.558469,40.727165],"type":"Point"}
}