{
  "type": "Feature",
  "properties": {
    "iso:country":"IT",
    "sg:address":"00173 Roma",
    "sg:city":"Roma",
    "sg:orig_category":"Cinematografia E Radiotelevisione. Pubblicita', Marketing E Comunicazione. Acqua, Luce, Gas E Societa' Di Esercizio Pubblico",
    "sg:phone":"+39 06 723 1273",
    "sg:postcode":"00173",
    "sg:province":"Roma",
    "wof:name":"Teleradio Tuscolo Srl",
    "wof:placetype":"venue"
},
  "geometry": {"coordinates":[12.60018,41.833324],"type":"Point"}
}