{
  "type": "Feature",
  "properties": {
    "addr:full":"Via Vittorio Veneto 60/r; Busalla; 16012 Busalla Genova 16012",
    "addr:housenumber":"60 / r",
    "addr:postcode":"16012;16012",
    "addr:street":"Via Vittorio Veneto",
    "iso:country":"IT",
    "sg:address":"Via Vittorio Veneto 60/r; Busalla; 16012",
    "sg:city":"Busalla",
    "sg:classifiers":[
        {
            "category":"Banks & Credit Unions",
            "subcategory":"Bank",
            "type":"Services"
        }
    ],
    "sg:phone":"+39 010 964 2490",
    "sg:postcode":"16012",
    "sg:province":"Genova",
    "wof:name":"Istituto Bancario, San Paolo Di Torino Spa",
    "wof:placetype":"venue"
},
  "geometry": {"coordinates":[8.944668,44.572556],"type":"Point"}
}