{
  "type": "Feature",
  "properties": {
    "iso:country":"IT",
    "sg:address":"20027 Rescaldina",
    "sg:city":"Rescaldina",
    "sg:orig_category":"Valvole - Produzione E Commercio",
    "sg:phone":"+39 0331 465124",
    "sg:postcode":"20027",
    "sg:province":"Milano",
    "wof:name":"Valvocomponenti Sas",
    "wof:placetype":"venue"
},
  "geometry": {"coordinates":[8.957996,45.614365],"type":"Point"}
}