{
  "type": "Feature",
  "properties": {
    "iso:country":"IT",
    "sg:address":"34071 Cormons",
    "sg:city":"Cormons",
    "sg:orig_category":"Macchine, Impianti Ed Attrezzature Per Agricoltura E Zootecnia",
    "sg:phone":"+39 0481 60387",
    "sg:postcode":"34071",
    "sg:province":"Gorizia",
    "wof:name":"Nicita Franco",
    "wof:placetype":"venue"
},
  "geometry": {"coordinates":[13.477687,45.958439],"type":"Point"}
}