{
  "type": "Feature",
  "properties": {
    "iso:country":"IT",
    "sg:address":"Via Arduino Casale 10010 Lessolo",
    "sg:city":"Lessolo",
    "sg:classifiers":[
        {
            "category":"Sports & Exercise",
            "subcategory":"Playing Field",
            "type":"Entertainment"
        }
    ],
    "sg:phone":"+39 39012558848",
    "sg:postcode":"10010",
    "sg:province":"Torino",
    "sg:tags":[
        "game"
    ],
    "wof:name":"Roberto Sport (s.r.l.)",
    "wof:placetype":"venue"
},
  "geometry": {"coordinates":[7.827972,45.480156],"type":"Point"}
}