{
  "type": "Feature",
  "properties": {
    "addr:full":"38, Stazione Marittima 80142 Napoli Napoli Napoli 80142",
    "addr:housenumber":"38",
    "addr:postcode":"80142;80142",
    "addr:street":"Stazione",
    "iso:country":"IT",
    "sg:address":"38, Stazione Marittima 80142 Napoli",
    "sg:city":"Napoli",
    "sg:classifiers":[
        {
            "category":"Marine",
            "type":"Transportation"
        }
    ],
    "sg:phone":"+39 081 552 0683",
    "sg:postcode":"80142",
    "sg:province":"Napoli",
    "sg:tags":[
        "transport",
        "sea"
    ],
    "wof:name":"General Shipchandler",
    "wof:placetype":"venue"
},
  "geometry": {"coordinates":[14.251636,40.840096],"type":"Point"}
}