{
  "type": "Feature",
  "properties": {
    "addr:full":"Via Reggio 28/b 10153 Torino Torino Torino 10153",
    "addr:housenumber":"28 / b",
    "addr:postcode":"10153;10153",
    "addr:street":"Via Reggio",
    "iso:country":"IT",
    "sg:address":"Via Reggio 28/b 10153 Torino",
    "sg:city":"Torino",
    "sg:classifiers":[
        {
            "category":"Manufacturing",
            "subcategory":"Textiles",
            "type":"Manufacturing & Wholesale Goods"
        }
    ],
    "sg:phone":"+39 011 248 1495",
    "sg:postcode":"10153",
    "sg:province":"Torino",
    "sg:tags":[
        "label"
    ],
    "wof:name":"Frassinelli Decalcomanie Autoadesivi Srl",
    "wof:placetype":"venue"
},
  "geometry": {"coordinates":[7.555273,45.060833],"type":"Point"}
}