{
  "type": "Feature",
  "properties": {
    "addr:full":"20141 Milano Milano Milano 20141",
    "addr:postcode":"20141;20141",
    "iso:country":"IT",
    "sg:address":"20141 Milano",
    "sg:city":"Milano",
    "sg:orig_category":"Alimenti Dietetici, Macrobiotici E Biologici - Produzione E Ingrosso",
    "sg:phone":"+39 0252561",
    "sg:postcode":"20141",
    "sg:province":"Milano",
    "sg:website":"http://www.plasmon.it",
    "wof:name":"Plasmon Dietetici Alimentari Srl",
    "wof:placetype":"venue"
},
  "geometry": {"coordinates":[9.199751,45.423962],"type":"Point"}
}