{
  "type": "Feature",
  "properties": {
    "iso:country":"IT",
    "sg:address":"51, Vl. Italia 20030 Camnago Di Lentate S/seveso",
    "sg:city":"Camnago",
    "sg:classifiers":[
        {
            "category":"Professional",
            "subcategory":"Engineering",
            "type":"Services"
        }
    ],
    "sg:phone":"+39 036 255 7722",
    "sg:postcode":"20030",
    "sg:province":"Milano",
    "sg:tags":[
        "machine",
        "-",
        "mechanical"
    ],
    "sg:website":"http://www.lombardafiltri.it",
    "wof:name":"Lombarda Filtri Srl",
    "wof:placetype":"venue"
},
  "geometry": {"coordinates":[9.129246,45.672527],"type":"Point"}
}