{
  "type": "Feature",
  "properties": {
    "iso:country":"IT",
    "sg:address":"25010 Borgosatollo",
    "sg:city":"Borgosatollo",
    "sg:orig_category":"Gioielleria, Oreficeria E Argenteria. Articoli Da Regalo. Shopping",
    "sg:phone":"+39 030 250 1580",
    "sg:postcode":"25010",
    "sg:province":"Brescia",
    "wof:name":"Sa.vi.v Di Veronesi Giuliano & C. S.n.c.",
    "wof:placetype":"venue"
},
  "geometry": {"coordinates":[10.25547,45.474922],"type":"Point"}
}