{
  "type": "Feature",
  "properties": {
    "addr:full":"20098 S. Giuliano Milanese Milano 20098",
    "addr:housenumber":"20098",
    "addr:postcode":"20098",
    "addr:street":"S. Giuliano Milanese",
    "iso:country":"IT",
    "sg:address":"20098 S. Giuliano Milanese",
    "sg:orig_category":"Macchine, Impianti Ed Attrezzature Industria Chimica. Pompe",
    "sg:phone":"+39 02 988 1024",
    "sg:postcode":"20098",
    "sg:province":"Milano",
    "wof:name":"Galvano F.p. Srl",
    "wof:placetype":"venue"
},
  "geometry": {"coordinates":[9.267515,45.398632],"type":"Point"}
}