{
  "type": "Feature",
  "properties": {
    "iso:country":"IT",
    "sg:address":"Via Charta 15 50018 Scandicci",
    "sg:city":"Scandicci",
    "sg:classifiers":[
        {
            "category":"Shopping",
            "subcategory":"Luggage & Leather Goods",
            "type":"Retail Goods"
        }
    ],
    "sg:phone":"+39 055 735751",
    "sg:postcode":"50018",
    "sg:province":"Firenze",
    "sg:tags":[
        "bag"
    ],
    "sg:website":"www.limberti.it",
    "wof:name":"Limberti Srl",
    "wof:placetype":"venue"
},
  "geometry": {"coordinates":[11.16015,43.763515],"type":"Point"}
}