{
  "type": "Feature",
  "properties": {
    "addr:full":"44100 Ferrara Ferrara Ferrara 44100",
    "addr:postcode":"44100;44100",
    "iso:country":"IT",
    "sg:address":"44100 Ferrara",
    "sg:city":"Ferrara",
    "sg:orig_category":"Metalli E Leghe",
    "sg:phone":"+39 0532 417076",
    "sg:postcode":"44100",
    "sg:province":"Ferrara",
    "wof:name":"Roversi Franco Snc",
    "wof:placetype":"venue"
},
  "geometry": {"coordinates":[11.6960220337,44.7316207886],"type":"Point"}
}