{
  "type": "Feature",
  "properties": {
    "iso:country":"IT",
    "sg:address":"50, Str. Maratta Bassa 05100 Terni",
    "sg:city":"Terni",
    "sg:classifiers":[
        {
            "category":"Wholesale",
            "subcategory":"Drugs",
            "type":"Manufacturing & Wholesale Goods"
        }
    ],
    "sg:phone":"+39 0744 300174",
    "sg:postcode":"05100",
    "sg:province":"Terni",
    "sg:tags":[
        "chemical",
        "pharmaceutical"
    ],
    "sg:website":"http://www.colorificiocat.com",
    "wof:name":"Colorificio C.a.t.",
    "wof:placetype":"venue"
},
  "geometry": {"coordinates":[12.594704,42.565525],"type":"Point"}
}