{
  "type": "Feature",
  "properties": {
    "iso:country":"IT",
    "sg:address":"47900 Rimini",
    "sg:city":"Rimini",
    "sg:orig_category":"Campeggio. Alberghi E Strutture Extra Alberghiere",
    "sg:phone":"+39 0541 732882",
    "sg:postcode":"47900",
    "sg:province":"Rimini",
    "sg:website":"http://www.zucchetti.it/camping.it",
    "wof:name":"Riva E Mare Srl Camping Italia International",
    "wof:placetype":"venue"
},
  "geometry": {"coordinates":[12.548799,44.081059],"type":"Point"}
}