{
  "type": "Feature",
  "properties": {
    "iso:country":"IT",
    "sg:address":"Via Arciprete Figura 24020 Vilminore Di Scalve",
    "sg:city":"Vilminore",
    "sg:classifiers":[
        {
            "category":"Professional",
            "subcategory":"Engineering",
            "type":"Services"
        }
    ],
    "sg:phone":"+39 39034651485",
    "sg:postcode":"24020",
    "sg:province":"Bergamo",
    "sg:tags":[
        "machine",
        "-",
        "mechanical"
    ],
    "wof:name":"Duci Elio & Gian Domenico (s.n.c.)",
    "wof:placetype":"venue"
},
  "geometry": {"coordinates":[10.094595,45.996593],"type":"Point"}
}