{
  "type": "Feature",
  "properties": {
    "iso:country":"IT",
    "sg:address":"20135 Milano",
    "sg:city":"Milano",
    "sg:orig_category":"Chiese Ed Associazioni Religiose",
    "sg:phone":"+39 02 545 5615",
    "sg:postcode":"20135",
    "sg:province":"Milano",
    "wof:name":"Parrocchia Ss Silvestro E Martino",
    "wof:placetype":"venue"
},
  "geometry": {"coordinates":[9.201735,45.469372],"type":"Point"}
}