{
  "type": "Feature",
  "properties": {
    "addr:full":"37060 Castel D'azzano Azzano Verona 37060",
    "addr:postcode":"37060;37060",
    "iso:country":"IT",
    "sg:address":"37060 Castel D'azzano",
    "sg:city":"Azzano",
    "sg:orig_category":"Servizi E Lavori Per Arredamento E Industria Del Legno. Servizi Di Magazzinaggio E Movimentazione",
    "sg:phone":"+39 045 519496",
    "sg:postcode":"37060",
    "sg:province":"Verona",
    "wof:name":"Bertolani Traslochi Snc Di Bertolani Daniele & C.",
    "wof:placetype":"venue"
},
  "geometry": {"coordinates":[10.96176,45.442505],"type":"Point"}
}