{
  "type": "Feature",
  "properties": {
    "addr:full":"Via Alpignano, 142; Caselette; 10040 Caselette Torino 10040",
    "addr:housenumber":"142",
    "addr:postcode":"10040;10040",
    "addr:street":"Via Alpignano;Caselette",
    "iso:country":"IT",
    "sg:address":"Via Alpignano, 142; Caselette; 10040",
    "sg:city":"Caselette",
    "sg:classifiers":[
        {
            "category":"Banks & Credit Unions",
            "subcategory":"Bank",
            "type":"Services"
        }
    ],
    "sg:phone":"+39 011 968 8310",
    "sg:postcode":"10040",
    "sg:province":"Torino",
    "wof:name":"Banca Popolare Di Novara",
    "wof:placetype":"venue"
},
  "geometry": {"coordinates":[7.49303,45.106812],"type":"Point"}
}