{
  "type": "Feature",
  "properties": {
    "iso:country":"IT",
    "sg:address":"Via Torre D'agera 70032 Bitonto",
    "sg:city":"Bitonto",
    "sg:classifiers":[
        {
            "category":"Real Estate",
            "subcategory":"Architect",
            "type":"Services"
        }
    ],
    "sg:phone":"+39 080 374 5269",
    "sg:postcode":"70032",
    "sg:province":"Bari",
    "sg:tags":[
        "textile",
        "clothing"
    ],
    "wof:name":"Sa.ma. S.r.l.",
    "wof:placetype":"venue"
},
  "geometry": {"coordinates":[16.679188,41.132793],"type":"Point"}
}