{
  "type": "Feature",
  "properties": {
    "addr:full":"Via Roma 81 14040 Castel Boglione Castel Boglione Asti 14040",
    "addr:housenumber":"81",
    "addr:postcode":"14040;14040",
    "addr:street":"Via Roma",
    "iso:country":"IT",
    "sg:address":"Via Roma 81 14040 Castel Boglione",
    "sg:city":"Castel Boglione",
    "sg:classifiers":[
        {
            "category":"Manufacturing",
            "subcategory":"Printing",
            "type":"Manufacturing & Wholesale Goods"
        }
    ],
    "sg:phone":"+39 0141 766811",
    "sg:postcode":"14040",
    "sg:province":"Asti",
    "sg:tags":[
        "plastic"
    ],
    "sg:website":"www.stampla.it",
    "wof:name":"Stampla Srl",
    "wof:placetype":"venue"
},
  "geometry": {"coordinates":[8.3362121582,44.7367095947],"type":"Point"}
}