{
  "type": "Feature",
  "properties": {
    "iso:country":"IT",
    "sg:address":"70126 Bari",
    "sg:city":"Bari",
    "sg:orig_category":"Climatizzazione E Condizionamento, Apparecchiature E Servizi. Elettrodomestici",
    "sg:phone":"+39 080 555 9834",
    "sg:postcode":"70126",
    "sg:province":"Bari",
    "sg:website":"http://www.climatrade.it",
    "wof:name":"Climatrade Di Tiani",
    "wof:placetype":"venue"
},
  "geometry": {"coordinates":[16.876682,41.117439],"type":"Point"}
}