{
  "type": "Feature",
  "properties": {
    "iso:country":"IT",
    "sg:address":"00161 Roma",
    "sg:city":"Roma",
    "sg:orig_category":"Servizi Al Turismo. Trasporto Pubblico E Privato. Acqua, Luce, Gas E Societa' Di Esercizio Pubblico. Pubblica Amministrazione",
    "sg:phone":"+39 06 4424 1593",
    "sg:postcode":"00161",
    "sg:province":"Roma",
    "wof:name":"Ente Ferrovie Dello Stato",
    "wof:placetype":"venue"
},
  "geometry": {"coordinates":[12.515463,41.911732],"type":"Point"}
}