{
  "type": "Feature",
  "properties": {
    "iso:country":"IT",
    "sg:address":"20037 Paderno Dugnano",
    "sg:city":"Paderno Dugnano",
    "sg:orig_category":"Lavorazioni Meccaniche E Servizi",
    "sg:phone":"+39 02 990 0141",
    "sg:postcode":"20037",
    "sg:province":"Milano",
    "wof:name":"Cabo Srl",
    "wof:placetype":"venue"
},
  "geometry": {"coordinates":[9.171721,45.590855],"type":"Point"}
}