{
  "type": "Feature",
  "properties": {
    "iso:country":"IT",
    "sg:address":"10126 Torino",
    "sg:city":"Torino",
    "sg:orig_category":"Articoli Medico-sanitari Ed Ortopedici",
    "sg:phone":"+39 011 664 7428",
    "sg:postcode":"10126",
    "sg:province":"Torino",
    "wof:name":"S.t.o. Srl",
    "wof:placetype":"venue"
},
  "geometry": {"coordinates":[7.776793,45.141403],"type":"Point"}
}