{
  "type": "Feature",
  "properties": {
    "iso:country":"IT",
    "sg:address":"80143 Napoli",
    "sg:city":"Napoli",
    "sg:orig_category":"Aziende Agricole",
    "sg:phone":"+39 081 206114",
    "sg:postcode":"80143",
    "sg:province":"Napoli",
    "wof:name":"Calviati Srl",
    "wof:placetype":"venue"
},
  "geometry": {"coordinates":[14.307055,40.919708],"type":"Point"}
}