{
  "type": "Feature",
  "properties": {
    "iso:country":"IT",
    "sg:address":"20131 Milano",
    "sg:city":"Milano",
    "sg:orig_category":"Articoli Da Regalo. Arte Ed Artigianato Artistico. Shopping",
    "sg:phone":"+39 02 236 7776",
    "sg:postcode":"20131",
    "sg:province":"Milano",
    "wof:name":"Blu Cina Di Massimo Mondini E C. Sas",
    "wof:placetype":"venue"
},
  "geometry": {"coordinates":[9.223652,45.481754],"type":"Point"}
}