{
  "type": "Feature",
  "properties": {
    "addr:full":"31046 Oderzo Oderzo Treviso 31046",
    "addr:postcode":"31046;31046",
    "iso:country":"IT",
    "sg:address":"31046 Oderzo",
    "sg:city":"Oderzo",
    "sg:orig_category":"Utensili Meccanici E Materiali",
    "sg:phone":"+39 0422 712107",
    "sg:postcode":"31046",
    "sg:province":"Treviso",
    "wof:name":"Orlando Bruno",
    "wof:placetype":"venue"
},
  "geometry": {"coordinates":[12.489751,45.779156],"type":"Point"}
}