{
  "type": "Feature",
  "properties": {
    "iso:country":"IT",
    "sg:address":"20052 Monza",
    "sg:city":"Monza",
    "sg:orig_category":"Accessori Moda D'abbigliamento. Shopping",
    "sg:phone":"+39 039 322339",
    "sg:postcode":"20052",
    "sg:province":"Milano",
    "wof:name":"Pirola A. Di Lazzari E C.",
    "wof:placetype":"venue"
},
  "geometry": {"coordinates":[9.27788,45.574421],"type":"Point"}
}