{
  "type": "Feature",
  "properties": {
    "iso:country":"IT",
    "sg:address":"00036 Palestrina",
    "sg:city":"Palestrina",
    "sg:orig_category":"Servizi Culturali E Per Lo Spettacolo. Servizi Al Turismo. Acqua, Luce, Gas E Societa' Di Esercizio Pubblico",
    "sg:phone":"+39 06 953 8100",
    "sg:postcode":"00036",
    "sg:province":"Roma",
    "wof:name":"Museo Nazionale Prenestino",
    "wof:placetype":"venue"
},
  "geometry": {"coordinates":[12.491537,41.904552],"type":"Point"}
}