{
  "type": "Feature",
  "properties": {
    "addr:full":"14, Viale Iii Venezie 35043 Monselice Monselice Padova 35043",
    "addr:housenumber":"14",
    "addr:postcode":"35043;35043",
    "addr:street":"Viale Iii Venezie",
    "iso:country":"IT",
    "sg:address":"14, Viale Iii Venezie 35043 Monselice",
    "sg:city":"Monselice",
    "sg:classifiers":[
        {
            "category":"Professional",
            "subcategory":"Printing & Photocopies",
            "type":"Services"
        }
    ],
    "sg:phone":"+39 0429 781133",
    "sg:postcode":"35043",
    "sg:province":"Padova",
    "wof:name":"Litografia Silsab (s.n.c.)",
    "wof:placetype":"venue"
},
  "geometry": {"coordinates":[11.8765888214,45.4095687866],"type":"Point"}
}