{
  "type": "Feature",
  "properties": {
    "iso:country":"IT",
    "sg:address":"2, Via Gino Cappannini Box 21/a 00054 Fiumicino",
    "sg:city":"Fiumicino",
    "sg:classifiers":[
        {
            "category":"Airport",
            "subcategory":"General Aviation",
            "type":"Transportation"
        }
    ],
    "sg:phone":"+39 39066529017",
    "sg:postcode":"00054",
    "sg:province":"Roma",
    "sg:tags":[
        "transport",
        "air"
    ],
    "wof:name":"S.i.t.e.s. S.r.l.",
    "wof:placetype":"venue"
},
  "geometry": {"coordinates":[12.482325,41.895466],"type":"Point"}
}