{
  "type": "Feature",
  "properties": {
    "addr:full":"15077 Predosa Predosa Alessandria 15077",
    "addr:postcode":"15077;15077",
    "iso:country":"IT",
    "sg:address":"15077 Predosa",
    "sg:city":"Predosa",
    "sg:orig_category":"Prodotti Vari In Metallo. Articoli Per Imballaggio E Confezionamento",
    "sg:phone":"+39 0131 71495",
    "sg:postcode":"15077",
    "sg:province":"Alessandria",
    "wof:name":"Baratta Industrie (s.r.l.)",
    "wof:placetype":"venue"
},
  "geometry": {"coordinates":[8.6352043152,44.8052825928],"type":"Point"}
}