{
  "type": "Feature",
  "properties": {
    "addr:full":"20128 Milano Milano Milano 20128",
    "addr:postcode":"20128;20128",
    "iso:country":"IT",
    "sg:address":"20128 Milano",
    "sg:city":"Milano",
    "sg:orig_category":"Motori Ed Organi Di Trasmissione",
    "sg:phone":"+39 02 255 0221",
    "sg:postcode":"20128",
    "sg:province":"Milano",
    "wof:name":"Automec Srl",
    "wof:placetype":"venue"
},
  "geometry": {"coordinates":[9.2269468307,45.5079841614],"type":"Point"}
}