{
  "type": "Feature",
  "properties": {
    "iso:country":"IT",
    "sg:address":"80146 Napoli",
    "sg:city":"Napoli",
    "sg:orig_category":"Prodotti Finiti Stampati. Forniture E Prodotti Informatici. Forniture Per Uffici",
    "sg:phone":"+39 081 572 3413",
    "sg:postcode":"80146",
    "sg:province":"Napoli",
    "wof:name":"Tipolito Modernografica",
    "wof:placetype":"venue"
},
  "geometry": {"coordinates":[14.2901544571,40.9243583679],"type":"Point"}
}