{
  "type": "Feature",
  "properties": {
    "iso:country":"IT",
    "sg:address":"17/a, Via Garibaldi 40069 Zola Predosa",
    "sg:city":"Zola",
    "sg:classifiers":[
        {
            "category":"Shopping",
            "subcategory":"Clothing, Apparel, & Fashions",
            "type":"Retail Goods"
        }
    ],
    "sg:phone":"+39 39051758941",
    "sg:postcode":"40069",
    "sg:province":"Bologna",
    "sg:tags":[
        "clothes"
    ],
    "wof:name":"Viesse S.r.l.",
    "wof:placetype":"venue"
},
  "geometry": {"coordinates":[11.224467,44.482155],"type":"Point"}
}