{
  "type": "Feature",
  "properties": {
    "addr:full":"98124 Messina Messina Messina 98124",
    "addr:postcode":"98124;98124",
    "iso:country":"IT",
    "sg:address":"98124 Messina",
    "sg:city":"Messina",
    "sg:orig_category":"Forniture Per Edilizia E Lavori Pubblici",
    "sg:phone":"+39 090 293 5315",
    "sg:postcode":"98124",
    "sg:province":"Messina",
    "wof:name":"I-pla Srl",
    "wof:placetype":"venue"
},
  "geometry": {"coordinates":[15.5485639572,38.1732597351],"type":"Point"}
}