{
  "type": "Feature",
  "properties": {
    "iso:country":"IT",
    "sg:address":"Largo Amigazzi 4 20027 Rescaldina",
    "sg:city":"Rescaldina",
    "sg:classifiers":[
        {
            "category":"Banks & Credit Unions",
            "subcategory":"Investment Brokerage",
            "type":"Services"
        }
    ],
    "sg:phone":"+39 0331 520615",
    "sg:postcode":"20027",
    "sg:province":"Milano",
    "sg:tags":[
        "machine",
        "blasting",
        "centrifugal",
        "system"
    ],
    "sg:website":"www.carlobanfi.it",
    "wof:name":"Banfi Engineering Srl",
    "wof:placetype":"venue"
},
  "geometry": {"coordinates":[8.942589,45.622578],"type":"Point"}
}