{
  "type": "Feature",
  "properties": {
    "iso:country":"IT",
    "sg:address":"70026 Modugno",
    "sg:city":"Modugno",
    "sg:orig_category":"Prodotti E Manufatti In Materie Plastiche",
    "sg:phone":"+39 080 532 5192",
    "sg:postcode":"70026",
    "sg:province":"Bari",
    "wof:name":"Centro Servizi Metalli Srl",
    "wof:placetype":"venue"
},
  "geometry": {"coordinates":[16.7824420929,41.0863647461],"type":"Point"}
}