{
  "type": "Feature",
  "properties": {
    "addr:full":"278, Via Roma 16036 Recco Recco Genova 16036",
    "addr:housenumber":"278",
    "addr:postcode":"16036;16036",
    "addr:street":"Via Roma",
    "iso:country":"IT",
    "sg:address":"278, Via Roma 16036 Recco",
    "sg:city":"Recco",
    "sg:classifiers":[
        {
            "category":"Travel",
            "subcategory":"Travel Agent",
            "type":"Entertainment"
        }
    ],
    "sg:phone":"+39 39018574128",
    "sg:postcode":"16036",
    "sg:province":"Genova",
    "sg:tags":[
        "business"
    ],
    "wof:name":"Ristorante Tipico Manuelina",
    "wof:placetype":"venue"
},
  "geometry": {"coordinates":[9.088326,44.375553],"type":"Point"}
}