{
  "type": "Feature",
  "properties": {
    "addr:full":"Via Ribes 10010 Colleretto Giacosa Colleretto Giacosa Torino 10010",
    "addr:postcode":"10010;10010",
    "addr:street":"Via Ribes;Giacosa",
    "iso:country":"IT",
    "sg:address":"Via Ribes 10010 Colleretto Giacosa",
    "sg:city":"Colleretto Giacosa",
    "sg:classifiers":[
        {
            "category":"Shopping",
            "type":"Retail Goods"
        }
    ],
    "sg:phone":"+39 0125 538091",
    "sg:postcode":"10010",
    "sg:province":"Torino",
    "sg:tags":[
        "finished",
        "-",
        "metallic"
    ],
    "wof:name":"Ats S.p.a.",
    "wof:placetype":"venue"
},
  "geometry": {"coordinates":[7.824242115,45.4412536621],"type":"Point"}
}