{
  "type": "Feature",
  "properties": {
    "iso:country":"IT",
    "sg:address":"23, Via Caboto Giovanni E Sebastiano 34147 Trieste",
    "sg:city":"Trieste",
    "sg:classifiers":[
        {
            "category":"Shopping",
            "subcategory":"Computers & Home Electronics",
            "type":"Retail Goods"
        }
    ],
    "sg:phone":"+39 39040826440",
    "sg:postcode":"34147",
    "sg:province":"Trieste",
    "sg:tags":[
        "electronic",
        "electrical",
        "equipment"
    ],
    "wof:name":"Automatic Service S.r.l.",
    "wof:placetype":"venue"
},
  "geometry": {"coordinates":[13.778407,45.653629],"type":"Point"}
}