{
  "type": "Feature",
  "properties": {
    "iso:country":"IT",
    "sg:address":"70054 Giovinazzo",
    "sg:city":"Giovinazzo",
    "sg:orig_category":"Cartotecnica E Servizi. Forniture Per Uffici",
    "sg:phone":"+39 080 394 8805",
    "sg:postcode":"70054",
    "sg:province":"Bari",
    "wof:name":"Dettagli Srl",
    "wof:placetype":"venue"
},
  "geometry": {"coordinates":[16.766304,41.157131],"type":"Point"}
}