{
  "type": "Feature",
  "properties": {
    "iso:country":"IT",
    "sg:address":"Via Sacca, 60/1 43052 Colorno",
    "sg:city":"Colorno",
    "sg:classifiers":[
        {
            "category":"Home & Garden",
            "subcategory":"Carpets & Floor Coverings",
            "type":"Retail Goods"
        }
    ],
    "sg:phone":"+39 0521 312593",
    "sg:postcode":"43052",
    "sg:province":"Parma",
    "sg:tags":[
        "synthetic",
        "resin"
    ],
    "sg:website":"www.sirec.it",
    "wof:name":"S.i.r.e.c. S.r.l. Societa' Italiana Resine E Calcestruzzi Spa",
    "wof:placetype":"venue"
},
  "geometry": {"coordinates":[10.402735,44.937416],"type":"Point"}
}