{
  "type": "Feature",
  "properties": {
    "iso:country":"IT",
    "sg:address":"36056 Tezze Sul Brenta",
    "sg:city":"Tezze sul Brenta",
    "sg:orig_category":"Macchine Utensili E Impianti",
    "sg:phone":"+39 0424 560727",
    "sg:postcode":"36056",
    "sg:province":"Vicenza",
    "wof:name":"Infotec Di Parise Lino & C. (s.n.c.)",
    "wof:placetype":"venue"
},
  "geometry": {"coordinates":[11.779221,45.698364],"type":"Point"}
}