{
  "type": "Feature",
  "properties": {
    "iso:country":"IT",
    "sg:address":"26030 Gadesco Pieve Delmona",
    "sg:city":"Gadesco Pieve Delmona",
    "sg:orig_category":"Automazione E Macchine Per Ufficio. Servizi Ausiliari Di Certificati, Riproduzioni, Disegni E Foto",
    "sg:phone":"+39 0372 838707",
    "sg:postcode":"26030",
    "sg:province":"Cremona",
    "wof:name":"Microdata Service Snc Di Alfredo Lupi & C.",
    "wof:placetype":"venue"
},
  "geometry": {"coordinates":[10.103663,45.151791],"type":"Point"}
}