{
  "type": "Feature",
  "properties": {
    "iso:country":"IT",
    "sg:address":"20146 Milano",
    "sg:city":"Milano",
    "sg:orig_category":"Servizi Ausiliari Di Analisi, Controllo E Ricerca",
    "sg:phone":"+39 02 413151",
    "sg:postcode":"20146",
    "sg:province":"Milano",
    "wof:name":"Istituto Geriatrico P. Redaelli",
    "wof:placetype":"venue"
},
  "geometry": {"coordinates":[9.137708,45.460152],"type":"Point"}
}