{
  "type": "Feature",
  "properties": {
    "addr:full":"20010 Vittuone Vittuone Milano 20010",
    "addr:postcode":"20010;20010",
    "iso:country":"IT",
    "sg:address":"20010 Vittuone",
    "sg:city":"Vittuone",
    "sg:orig_category":"Pubblica Amministrazione",
    "sg:phone":"+39 02 9011 0258",
    "sg:postcode":"20010",
    "sg:province":"Milano",
    "wof:name":"Provincia Di Milano Itis Vittuone",
    "wof:placetype":"venue"
},
  "geometry": {"coordinates":[8.9569883347,45.4895782471],"type":"Point"}
}