{
  "type": "Feature",
  "properties": {
    "addr:full":"28011 Armeno Armeno Novara 28011",
    "addr:postcode":"28011;28011",
    "iso:country":"IT",
    "sg:address":"28011 Armeno",
    "sg:city":"Armeno",
    "sg:classifiers":[
        {
            "category":"Home & Garden",
            "subcategory":"Home Furnishings",
            "type":"Retail Goods"
        }
    ],
    "sg:phone":"+39 0322 900257",
    "sg:postcode":"28011",
    "sg:province":"Novara",
    "sg:tags":[
        "hardware",
        "plumbing",
        "bathroom",
        "accessories",
        "fitting"
    ],
    "sg:website":"http://www.righi.it",
    "wof:name":"Righi Spa",
    "wof:placetype":"venue"
},
  "geometry": {"coordinates":[8.453373909,45.8273162842],"type":"Point"}
}