{
  "type": "Feature",
  "properties": {
    "iso:country":"IT",
    "sg:address":"68, Via P. Zorutti 33030 Campoformido",
    "sg:city":"Campoformido",
    "sg:classifiers":[
        {
            "category":"Manufacturing",
            "subcategory":"Tools & Machinery",
            "type":"Manufacturing & Wholesale Goods"
        }
    ],
    "sg:phone":"+39 0432 663305",
    "sg:postcode":"33030",
    "sg:province":"Udine",
    "sg:tags":[
        "environment",
        "equipment",
        "-"
    ],
    "wof:name":"Aereco Di Bulfon Franco",
    "wof:placetype":"venue"
},
  "geometry": {"coordinates":[13.229218,46.06638],"type":"Point"}
}