{
  "type": "Feature",
  "properties": {
    "iso:country":"IT",
    "sg:address":"Via Mazzini Giuseppe 65 26013 Crema",
    "sg:city":"Crema",
    "sg:classifiers":[
        {
            "category":"Manufacturing",
            "subcategory":"Rubber & Plastics",
            "type":"Manufacturing & Wholesale Goods"
        }
    ],
    "sg:phone":"+39 0373 86891",
    "sg:postcode":"26013",
    "sg:province":"Cremona",
    "sg:tags":[
        "technical",
        "item",
        "us"
    ],
    "sg:website":"www.chizzoli.it",
    "wof:name":"Chizzoli Gomma Snc",
    "wof:placetype":"venue"
},
  "geometry": {"coordinates":[10.026135,45.133499],"type":"Point"}
}