{
  "type": "Feature",
  "properties": {
    "iso:country":"IT",
    "sg:address":"1, Piazza Manin Daniele 16122 Genova",
    "sg:city":"Genova",
    "sg:classifiers":[
        {
            "category":"Communications",
            "subcategory":"Newspaper",
            "type":"Services"
        }
    ],
    "sg:phone":"+39 39010873286",
    "sg:postcode":"16122",
    "sg:province":"Genova",
    "sg:tags":[
        "advertising"
    ],
    "wof:name":"Geggi Tagliafico Italia (s.r.l.)",
    "wof:placetype":"venue"
},
  "geometry": {"coordinates":[8.933989,44.407063],"type":"Point"}
}