{
  "type": "Feature",
  "properties": {
    "iso:country":"IT",
    "sg:address":"10141 Torino",
    "sg:city":"Torino",
    "sg:orig_category":"Ricambi E Componenti Dei Mezzi Di Trasporto",
    "sg:phone":"+39 011 332403",
    "sg:postcode":"10141",
    "sg:province":"Torino",
    "wof:name":"Batti Gervasio",
    "wof:placetype":"venue"
},
  "geometry": {"coordinates":[7.642105,45.063015],"type":"Point"}
}