{
  "type": "Feature",
  "properties": {
    "iso:country":"IT",
    "sg:address":"50, Ctr. Giuliano 85100 Potenza",
    "sg:city":"Giuliano",
    "sg:classifiers":[
        {
            "category":"Shopping",
            "subcategory":"Crafts & Fabrics",
            "type":"Retail Goods"
        }
    ],
    "sg:phone":"+39 0971 480236",
    "sg:postcode":"85100",
    "sg:province":"Potenza",
    "sg:website":"http://www.paginegialle.it/rikamsud",
    "wof:name":"Rikam Sud Di Summa Rocchina",
    "wof:placetype":"venue"
},
  "geometry": {"coordinates":[15.7724952698,40.6840896606],"type":"Point"}
}