{
  "type": "Feature",
  "properties": {
    "iso:country":"IT",
    "sg:address":"24121 Bergamo",
    "sg:city":"Bergamo",
    "sg:orig_category":"Brevetti D'invenzione - Consulenza Tecnica E Legale",
    "sg:phone":"+39 035 220116",
    "sg:postcode":"24121",
    "sg:province":"Bergamo",
    "wof:name":"Studio First Srl",
    "wof:placetype":"venue"
},
  "geometry": {"coordinates":[9.676953,45.694138],"type":"Point"}
}