{
  "type": "Feature",
  "properties": {
    "iso:country":"IT",
    "sg:address":"Via Del Lavoro 4 40023 Castel Guelfo Di Bologna",
    "sg:city":"Castel Guelfo di Bologna",
    "sg:classifiers":[
        {
            "category":"Shopping",
            "subcategory":"Hobbies, Toys, & Games",
            "type":"Retail Goods"
        }
    ],
    "sg:phone":"+39 0542 670160",
    "sg:postcode":"40023",
    "sg:province":"Bologna",
    "sg:tags":[
        "machine",
        "cross-cut"
    ],
    "sg:website":"www.femi.it",
    "wof:name":"Femi Spa",
    "wof:placetype":"venue"
},
  "geometry": {"coordinates":[11.61594,44.438091],"type":"Point"}
}