{
  "type": "Feature",
  "properties": {
    "addr:full":"32014 Ponte Nelle Alpi Ponte nelle Alpi Belluno 32014",
    "addr:postcode":"32014;32014",
    "iso:country":"IT",
    "sg:address":"32014 Ponte Nelle Alpi",
    "sg:city":"Ponte nelle Alpi",
    "sg:orig_category":"Frigotecnica, Apparecchiature E Servizi. Climatizzazione E Condizionamento, Apparecchiature E Servizi",
    "sg:phone":"+39 0437 981674",
    "sg:postcode":"32014",
    "sg:province":"Belluno",
    "wof:name":"De Barba Giovanni",
    "wof:placetype":"venue"
},
  "geometry": {"coordinates":[12.2827653885,46.1716880798],"type":"Point"}
}