{
  "type": "Feature",
  "properties": {
    "addr:full":"Via Fornace Vecchia 61100 Pesaro Pesaro Pesaro E Urbino 61100",
    "addr:postcode":"61100;61100",
    "addr:street":"Via Fornace Vecchia",
    "iso:country":"IT",
    "sg:address":"Via Fornace Vecchia 61100 Pesaro",
    "sg:city":"Pesaro",
    "sg:classifiers":[
        {
            "category":"Autos & Motor Vehicles",
            "subcategory":"Automobile Sales",
            "type":"Retail Goods"
        }
    ],
    "sg:phone":"+39 39072141871",
    "sg:postcode":"61100",
    "sg:province":"Pesaro E Urbino",
    "sg:tags":[
        "equipment",
        "transport"
    ],
    "wof:name":"Benelli S.p.a.",
    "wof:placetype":"venue"
},
  "geometry": {"coordinates":[12.845058,43.89542],"type":"Point"}
}