{
  "type": "Feature",
  "properties": {
    "iso:country":"IT",
    "sg:address":"21013 Gallarate",
    "sg:city":"Gallarate",
    "sg:classifiers":[
        {
            "category":"Conference Center",
            "type":"Public Place"
        }
    ],
    "sg:phone":"+39 0331 714 9011",
    "sg:postcode":"21013",
    "sg:province":"Varese",
    "sg:tags":[
        "call",
        "e",
        "telemarketing"
    ],
    "wof:name":"Full Data Center Srl",
    "wof:placetype":"venue"
},
  "geometry": {"coordinates":[8.793321,45.764267],"type":"Point"}
}