{
  "type": "Feature",
  "properties": {
    "iso:country":"IT",
    "sg:address":"55042 Forte Dei Marmi",
    "sg:city":"Forte dei Marmi",
    "sg:classifiers":[
        {
            "category":"Health Services",
            "subcategory":"Health Practitioner",
            "type":"Services"
        }
    ],
    "sg:phone":"+39 0584 752595",
    "sg:postcode":"55042",
    "sg:province":"Lucca",
    "sg:tags":[
        "medici"
    ],
    "wof:name":"Torsoli Dr.maria Angela Studio",
    "wof:placetype":"venue"
},
  "geometry": {"coordinates":[10.1600780487,43.9715118408],"type":"Point"}
}