{
  "type": "Feature",
  "properties": {
    "addr:full":"4, Via Provinciale 22030 Lasnigo Lasnigo Como 22030",
    "addr:postcode":"22030;22030",
    "addr:street":"Via Provinciale",
    "iso:country":"IT",
    "sg:address":"4, Via Provinciale 22030 Lasnigo",
    "sg:city":"Lasnigo",
    "sg:classifiers":[
        {
            "category":"Food & Beverages",
            "subcategory":"Dairy",
            "type":"Retail Goods"
        }
    ],
    "sg:phone":"+39 39031670922",
    "sg:postcode":"22030",
    "sg:province":"Como",
    "sg:tags":[
        "product"
    ],
    "wof:name":"Premium S.r.l.",
    "wof:placetype":"venue"
},
  "geometry": {"coordinates":[9.263146,45.881748],"type":"Point"}
}