{
  "type": "Feature",
  "properties": {
    "addr:full":"10098 Rivoli Cascine vica Torino 10098",
    "addr:postcode":"10098;10098",
    "iso:country":"IT",
    "sg:address":"10098 Rivoli",
    "sg:city":"Cascine vica",
    "sg:orig_category":"Lavorazioni Metalli, Stampaggio E Saldatura",
    "sg:phone":"+39 011 957 2364",
    "sg:postcode":"10098",
    "sg:province":"Torino",
    "wof:name":"Oscam Di C. Mus",
    "wof:placetype":"venue"
},
  "geometry": {"coordinates":[7.561288,45.063171],"type":"Point"}
}