{
  "type": "Feature",
  "properties": {
    "addr:full":"Via Martiri Della Liberta' 6-8 35010 Grantorto Grantorto Padova 35010",
    "addr:housenumber":"6-8",
    "addr:postcode":"35010;35010",
    "addr:street":"Via Martiri Della Liberta '",
    "iso:country":"IT",
    "sg:address":"Via Martiri Della Liberta' 6-8 35010 Grantorto",
    "sg:city":"Grantorto",
    "sg:classifiers":[
        {
            "category":"Structure",
            "subcategory":"Office Building",
            "type":"Public Place"
        }
    ],
    "sg:phone":"+39 049 949 0289",
    "sg:postcode":"35010",
    "sg:province":"Padova",
    "sg:tags":[
        "chair",
        "backrest"
    ],
    "sg:website":"www.geoplast.it",
    "wof:name":"Geoplast S.r.l.",
    "wof:placetype":"venue"
},
  "geometry": {"coordinates":[11.732004,45.606544],"type":"Point"}
}