{
  "type": "Feature",
  "properties": {
    "addr:full":"95030 Tremestieri Etneo Tremestieri Etneo Catania 95030",
    "addr:postcode":"95030;95030",
    "iso:country":"IT",
    "sg:address":"95030 Tremestieri Etneo",
    "sg:city":"Tremestieri Etneo",
    "sg:orig_category":"Prodotti Alimentari",
    "sg:phone":"+39 095 338466",
    "sg:postcode":"95030",
    "sg:province":"Catania",
    "wof:name":"Alifar Di Garozzo Mario & C. (s.a.s.)",
    "wof:placetype":"venue"
},
  "geometry": {"coordinates":[15.0907611847,37.5399093628],"type":"Point"}
}