{
  "type": "Feature",
  "properties": {
    "iso:country":"IT",
    "sg:address":"25020 Seniga",
    "sg:city":"Seniga",
    "sg:orig_category":"Servizi E Lavori Industria Chimica",
    "sg:phone":"+39 030 995 5434",
    "sg:postcode":"25020",
    "sg:province":"Brescia",
    "wof:name":"Plastic Center S.r.l.",
    "wof:placetype":"venue"
},
  "geometry": {"coordinates":[10.194702,45.555218],"type":"Point"}
}