{
  "type": "Feature",
  "properties": {
    "addr:full":"90143 Palermo Palermo Palermo 90143",
    "addr:postcode":"90143;90143",
    "iso:country":"IT",
    "sg:address":"90143 Palermo",
    "sg:city":"Palermo",
    "sg:orig_category":"Servizi Per Aziende, Manifestazioni E Supporto Agli Scambi Commerciali",
    "sg:phone":"+39 091 7309 0880",
    "sg:postcode":"90143",
    "sg:province":"Palermo",
    "wof:name":"Or Mediterranea Srl",
    "wof:placetype":"venue"
},
  "geometry": {"coordinates":[13.350065,38.141975],"type":"Point"}
}