{
  "type": "Feature",
  "properties": {
    "iso:country":"IT",
    "sg:address":"12066 Monticello D'alba",
    "sg:orig_category":"Acciai Inossidabili - Lavorazione",
    "sg:phone":"+39 0173 441375",
    "sg:postcode":"12066",
    "sg:province":"Cuneo",
    "wof:name":"Euromec Srl",
    "wof:placetype":"venue"
},
  "geometry": {"coordinates":[7.882618,44.697872],"type":"Point"}
}