{
  "type": "Feature",
  "properties": {
    "addr:full":"09122 Cagliari Cagliari Cagliari 09122",
    "addr:postcode":"09122;09122",
    "iso:country":"IT",
    "sg:address":"09122 Cagliari",
    "sg:city":"Cagliari",
    "sg:orig_category":"Motori Ed Organi Di Trasmissione",
    "sg:phone":"+39 070 280741",
    "sg:postcode":"09122",
    "sg:province":"Cagliari",
    "wof:name":"Giochi Di Abilita' S.n.c. Di S.petrulli & C.",
    "wof:placetype":"venue"
},
  "geometry": {"coordinates":[9.0997571945,39.2276992798],"type":"Point"}
}