{
  "type": "Feature",
  "properties": {
    "iso:country":"IT",
    "sg:address":"Corso Italia 24/26; Saluzzo; 12037",
    "sg:city":"Saluzzo",
    "sg:classifiers":[
        {
            "category":"Banks & Credit Unions",
            "subcategory":"Bank",
            "type":"Services"
        }
    ],
    "sg:phone":"+39 0175 47009",
    "sg:postcode":"12037",
    "sg:province":"Cuneo",
    "wof:name":"Cariverona Banca Spa",
    "wof:placetype":"venue"
},
  "geometry": {"coordinates":[7.492062,44.645081],"type":"Point"}
}