{
  "type": "Feature",
  "properties": {
    "iso:country":"IT",
    "sg:address":"20146 Milano",
    "sg:city":"Milano",
    "sg:orig_category":"Abbigliamento Esterno, Maglierie E Pelliccerie. Servizi E Lavori Per Abbigliamento E Pelletterie",
    "sg:phone":"+39 02 475546",
    "sg:postcode":"20146",
    "sg:province":"Milano",
    "wof:name":"Goretti Silvio",
    "wof:placetype":"venue"
},
  "geometry": {"coordinates":[9.141409,45.451447],"type":"Point"}
}