{
  "type": "Feature",
  "properties": {
    "addr:full":"Via C. Betteloni 4 37023 Grezzana Grezzana Verona 37023",
    "addr:housenumber":"4",
    "addr:postcode":"37023;37023",
    "addr:street":"Via C. Betteloni",
    "iso:country":"IT",
    "sg:address":"Via C. Betteloni 4 37023 Grezzana",
    "sg:city":"Grezzana",
    "sg:classifiers":[
        {
            "category":"Banks & Credit Unions",
            "subcategory":"Investment Brokerage",
            "type":"Services"
        }
    ],
    "sg:phone":"+39 045 865 0355",
    "sg:postcode":"37023",
    "sg:province":"Verona",
    "sg:tags":[
        "work",
        "marble"
    ],
    "sg:website":"www.bellamoli.it",
    "wof:name":"Bellamoli Sas",
    "wof:placetype":"venue"
},
  "geometry": {"coordinates":[10.997061,45.544086],"type":"Point"}
}