{
  "type": "Feature",
  "properties": {
    "addr:full":"56126 Pisa Pisa Pisa 56126",
    "addr:postcode":"56126;56126",
    "iso:country":"IT",
    "sg:address":"56126 Pisa",
    "sg:city":"Pisa",
    "sg:classifiers":[
        {
            "category":"Restaurant",
            "type":"Food & Drink"
        }
    ],
    "sg:phone":"+39 050 561881",
    "sg:postcode":"56126",
    "sg:province":"Pisa",
    "sg:tags":[
        "auxiliary",
        "entertainment",
        "premises",
        "related",
        "catering",
        "similar",
        "public",
        "restaurants"
    ],
    "wof:name":"Ristorante Santa Maria",
    "wof:placetype":"venue"
},
  "geometry": {"coordinates":[10.747925,43.67762],"type":"Point"}
}