{
  "type": "Feature",
  "properties": {
    "iso:country":"IT",
    "sg:address":"56, Viale Della Repubblica 33080 Fiume Veneto",
    "sg:city":"Fiume Veneto",
    "sg:classifiers":[
        {
            "category":"Manufacturing",
            "subcategory":"Paper Products",
            "type":"Manufacturing & Wholesale Goods"
        }
    ],
    "sg:phone":"+39 0434 958101",
    "sg:postcode":"33080",
    "sg:province":"Pordenone",
    "sg:tags":[
        "cardboard"
    ],
    "wof:name":"Fantuz",
    "wof:placetype":"venue"
},
  "geometry": {"coordinates":[12.7283821106,45.9316673279],"type":"Point"}
}