{
  "type": "Feature",
  "properties": {
    "iso:country":"IT",
    "sg:address":"Via Lambrakis 1/a 42100 Reggio Emilia",
    "sg:classifiers":[
        {
            "category":"Shopping",
            "subcategory":"Mobile Phones",
            "type":"Retail Goods"
        }
    ],
    "sg:phone":"+39 0522 334002",
    "sg:postcode":"42100",
    "sg:province":"Reggio Nell'Emilia",
    "sg:tags":[
        "telephone",
        "accessory"
    ],
    "sg:website":"www.cellularline.com",
    "wof:name":"Cellular Italia S.p.a.",
    "wof:placetype":"venue"
},
  "geometry": {"coordinates":[10.654239,44.677891],"type":"Point"}
}