{
  "type": "Feature",
  "properties": {
    "addr:full":"20010 Arluno Arluno Milano 20010",
    "addr:postcode":"20010;20010",
    "iso:country":"IT",
    "sg:address":"20010 Arluno",
    "sg:city":"Arluno",
    "sg:orig_category":"Forniture Industriali Per Prevenzione, Controllo E Sicurezza",
    "sg:phone":"+39 02 9037 6774",
    "sg:postcode":"20010",
    "sg:province":"Milano",
    "wof:name":"Il Gabbiano Di Veronese Franco (s.n.c.)",
    "wof:placetype":"venue"
},
  "geometry": {"coordinates":[8.9388694763,45.5052223206],"type":"Point"}
}