{
  "type": "Feature",
  "properties": {
    "addr:full":"89819 Monterosso Calabro Monterosso Calabro Vibo Valentia 89819",
    "addr:postcode":"89819;89819",
    "addr:street":"Calabro Vibo Valentia",
    "iso:country":"IT",
    "sg:address":"89819 Monterosso Calabro",
    "sg:city":"Monterosso Calabro",
    "sg:orig_category":"Alimentare E Conserviera Industria - Macchine",
    "sg:phone":"+39 0963 327809",
    "sg:postcode":"89819",
    "sg:province":"Vibo Valentia",
    "wof:name":"Bep Di Pittella Antonio",
    "wof:placetype":"venue"
},
  "geometry": {"coordinates":[16.293406,38.722298],"type":"Point"}
}