{
  "type": "Feature",
  "properties": {
    "iso:country":"IT",
    "sg:address":"20091 Bresso",
    "sg:city":"Bresso",
    "sg:orig_category":"Materiali E Componenti Elettrotecnici",
    "sg:phone":"+39 02 610 0055",
    "sg:postcode":"20091",
    "sg:province":"Milano",
    "wof:name":"Elettromeccanica Di Dario Ghidini & C. Snc",
    "wof:placetype":"venue"
},
  "geometry": {"coordinates":[9.192056,45.544827],"type":"Point"}
}