{
  "type": "Feature",
  "properties": {
    "iso:country":"IT",
    "sg:address":"35035 Mestrino",
    "sg:city":"Mestrino",
    "sg:orig_category":"Servizi E Lavori Per Arredamento E Industria Del Legno. Servizi E Lavori Per Edilizia E Lavori Pubblici",
    "sg:phone":"+39 049 900 4271",
    "sg:postcode":"35035",
    "sg:province":"Padova",
    "wof:name":"Dona' Roberto",
    "wof:placetype":"venue"
},
  "geometry": {"coordinates":[11.765571,45.445873],"type":"Point"}
}