{
  "type": "Feature",
  "properties": {
    "addr:full":"5, Via Siani 41049 Sassuolo Sassuolo Modena 41049",
    "addr:postcode":"41049;41049",
    "addr:street":"Via Siani",
    "iso:country":"IT",
    "sg:address":"5, Via Siani 41049 Sassuolo",
    "sg:city":"Sassuolo",
    "sg:classifiers":[
        {
            "category":"Shopping",
            "type":"Retail Goods"
        }
    ],
    "sg:phone":"+39 0536 803800",
    "sg:postcode":"41049",
    "sg:province":"Modena",
    "sg:tags":[
        "finished",
        "-",
        "metallic"
    ],
    "wof:name":"Casa Del Cuscinetto Di Sassuolo (s.r.l.)",
    "wof:placetype":"venue"
},
  "geometry": {"coordinates":[10.786895752,44.5506858826],"type":"Point"}
}