{
  "type": "Feature",
  "properties": {
    "addr:full":"45021 Badia Polesine Badia Polesine Rovigo 45021",
    "addr:postcode":"45021;45021",
    "iso:country":"IT",
    "sg:address":"45021 Badia Polesine",
    "sg:city":"Badia Polesine",
    "sg:orig_category":"Ceramiche: Prodotti E Lavorazioni",
    "sg:phone":"+39 0425 590909",
    "sg:postcode":"45021",
    "sg:province":"Rovigo",
    "sg:website":"http://www.ghirotto.it",
    "wof:name":"Ghirotto Edilizia Sas",
    "wof:placetype":"venue"
},
  "geometry": {"coordinates":[11.485913,45.089298],"type":"Point"}
}