{
  "type": "Feature",
  "properties": {
    "addr:full":"36010 Zan\u00e8 Vicenza 36010",
    "addr:postcode":"36010;36010",
    "iso:country":"IT",
    "sg:address":"36010 Zan\u00e8",
    "sg:orig_category":"Arredamento Alberghi",
    "sg:phone":"+39 0445 314046",
    "sg:postcode":"36010",
    "sg:province":"Vicenza",
    "wof:name":"Gruppo 5 Srl",
    "wof:placetype":"venue"
},
  "geometry": {"coordinates":[11.484218,45.712337],"type":"Point"}
}