{
  "type": "Feature",
  "properties": {
    "addr:full":"00122 Lido Di Ostia Roma 00122",
    "addr:postcode":"00122;00122",
    "addr:street":"Di Ostia Roma",
    "iso:country":"IT",
    "sg:address":"00122 Lido Di Ostia",
    "sg:orig_category":"Abbigliamento Intimo, Calze E Costumi Da Bagno. Sport - Articoli E Forniture. Shopping",
    "sg:phone":"+39 06 568 4600",
    "sg:postcode":"00122",
    "sg:province":"Roma",
    "wof:name":"Rensink Johanna Hendrika",
    "wof:placetype":"venue"
},
  "geometry": {"coordinates":[12.292165,41.733757],"type":"Point"}
}