{
  "type": "Feature",
  "properties": {
    "addr:full":"13, Via Trofarello 10127 Torino Torino Torino 10127",
    "addr:postcode":"10127;10127",
    "addr:street":"Via Trofarello",
    "iso:country":"IT",
    "sg:address":"13, Via Trofarello 10127 Torino",
    "sg:city":"Torino",
    "sg:classifiers":[
        {
            "category":"Wholesale",
            "subcategory":"Medical Equipment & Supplies",
            "type":"Manufacturing & Wholesale Goods"
        }
    ],
    "sg:phone":"+39 011 663 8063",
    "sg:postcode":"10127",
    "sg:province":"Torino",
    "sg:tags":[
        "-",
        "health",
        "instrument"
    ],
    "wof:name":"D.a.s. (s.r.l.)",
    "wof:placetype":"venue"
},
  "geometry": {"coordinates":[7.659927,45.022007],"type":"Point"}
}