{
  "type": "Feature",
  "properties": {
    "iso:country":"IT",
    "sg:address":"Corso Savona 16; Moncalieri; 10024",
    "sg:city":"Moncalieri",
    "sg:classifiers":[
        {
            "category":"Banks & Credit Unions",
            "subcategory":"Bank",
            "type":"Services"
        }
    ],
    "sg:phone":"+39 011 682 8100",
    "sg:postcode":"10024",
    "sg:province":"Torino",
    "wof:name":"Banca Fideuram Spa",
    "wof:placetype":"venue"
},
  "geometry": {"coordinates":[7.684772,44.99633],"type":"Point"}
}