{
  "type": "Feature",
  "properties": {
    "addr:full":"Sda Provinciale Donnalucata Scicli 97018 Scicli Donnalucata Ragusa 97018",
    "addr:postcode":"97018;97018",
    "addr:street":"Scicli",
    "iso:country":"IT",
    "sg:address":"Sda Provinciale Donnalucata Scicli 97018 Scicli",
    "sg:city":"Donnalucata",
    "sg:classifiers":[
        {
            "category":"Manufacturing",
            "subcategory":"Food",
            "type":"Manufacturing & Wholesale Goods"
        }
    ],
    "sg:phone":"+39 0932 937451",
    "sg:postcode":"97018",
    "sg:province":"Ragusa",
    "sg:tags":[
        "processing"
    ],
    "sg:website":"www.cooprisorgimento.it",
    "wof:name":"Coop. A.r.l. Risorgimento",
    "wof:placetype":"venue"
},
  "geometry": {"coordinates":[14.7285032272,36.9259109497],"type":"Point"}
}