{
  "type": "Feature",
  "properties": {
    "iso:country":"IT",
    "sg:address":"95128 Catania",
    "sg:city":"Catania",
    "sg:orig_category":"Impiantistica E Prodotti Tecnologici Per Edilizia. Elettrotecnica Industriale, Prodotti E Apparecchiature. Elettrotecnica Professionale E Di Consumo",
    "sg:phone":"+39 095 432264",
    "sg:postcode":"95128",
    "sg:province":"Catania",
    "sg:website":"http://www.mgimpiantisrl.it",
    "wof:name":"M.g. Impianti Srl",
    "wof:placetype":"venue"
},
  "geometry": {"coordinates":[15.088848,37.525185],"type":"Point"}
}