{
  "type": "Feature",
  "properties": {
    "addr:full":"29, V. Fedolfi 43038 Sala Baganza Sala Baganza Parma 43038",
    "addr:housenumber":"29;baganza",
    "addr:postcode":"43038;43038",
    "addr:street":"V. Fedolfi;Parma",
    "iso:country":"IT",
    "sg:address":"29, V. Fedolfi 43038 Sala Baganza",
    "sg:city":"Sala Baganza",
    "sg:classifiers":[
        {
            "category":"Professional",
            "subcategory":"Engineering",
            "type":"Services"
        }
    ],
    "sg:phone":"+39 0521 839411",
    "sg:postcode":"43038",
    "sg:province":"Parma",
    "sg:tags":[
        "machine",
        "-",
        "mechanical"
    ],
    "sg:website":"http://www.procomac.it",
    "wof:name":"Procomac Spa",
    "wof:placetype":"venue"
},
  "geometry": {"coordinates":[10.23097,44.725117],"type":"Point"}
}