{
  "type": "Feature",
  "properties": {
    "addr:full":"42020 Quattro Castella Reggio Nell'Emilia 42020",
    "addr:postcode":"42020;42020",
    "iso:country":"IT",
    "sg:address":"42020 Quattro Castella",
    "sg:orig_category":"Forniture Per Agricoltura E Zootecnia. Animali Domestici",
    "sg:phone":"+39 0522 887323",
    "sg:postcode":"42020",
    "sg:province":"Reggio Nell'Emilia",
    "wof:name":"Racof Di Gambarelli E C. (s.n.c.)",
    "wof:placetype":"venue"
},
  "geometry": {"coordinates":[10.5101156235,44.6428985596],"type":"Point"}
}