{
  "type": "Feature",
  "properties": {
    "iso:country":"IT",
    "sg:address":"21040 Gornate Olona",
    "sg:orig_category":"Apparecchi, Attrezzature E Forniture Per Centri Estetici. Forniture Per Attivita' Commerciali Ed Artigianali",
    "sg:phone":"+39 0331 820254",
    "sg:postcode":"21040",
    "sg:province":"Varese",
    "wof:name":"Castiglioni Giuseppe & C. Snc",
    "wof:placetype":"venue"
},
  "geometry": {"coordinates":[8.826413,45.767384],"type":"Point"}
}