{
  "type": "Feature",
  "properties": {
    "iso:country":"IT",
    "sg:address":"24126 Bergamo",
    "sg:city":"Bergamo",
    "sg:orig_category":"Macchine, Strumenti Ed Apparecchi Per Attivita' Industriali",
    "sg:phone":"+39 035 311040",
    "sg:postcode":"24126",
    "sg:province":"Bergamo",
    "sg:website":"http://www.forlabitalia.it",
    "wof:name":"For Lab Italia Srl",
    "wof:placetype":"venue"
},
  "geometry": {"coordinates":[9.657347,45.671482],"type":"Point"}
}