{
  "type": "Feature",
  "properties": {
    "iso:country":"IT",
    "sg:address":"25080 Vallio Terme",
    "sg:city":"Vallio Terme",
    "sg:orig_category":"Carni, Salumi E Pesci. Zootecnia E Pesca, Allevamento Piccoli Animali",
    "sg:phone":"+39 036 537 0173",
    "sg:postcode":"25080",
    "sg:province":"Brescia",
    "sg:website":"http://www.garofolini.com",
    "wof:name":"Garofolini Giancarlo",
    "wof:placetype":"venue"
},
  "geometry": {"coordinates":[10.395984,45.610363],"type":"Point"}
}