{
  "type": "Feature",
  "properties": {
    "addr:full":"Viale Carducci 137a; Cattolica; 47033",
    "addr:housenumber":"137a",
    "addr:postcode":"47033",
    "addr:street":"Viale Carducci",
    "iso:country":"IT",
    "sg:address":"Viale Carducci 137a; Cattolica; 47033",
    "sg:classifiers":[
        {
            "category":"Banks & Credit Unions",
            "subcategory":"Bank",
            "type":"Services"
        }
    ],
    "sg:phone":"+39 0541 967764",
    "wof:name":"Banca Popolare Valconca Scarl",
    "wof:placetype":"venue"
},
  "geometry": {"coordinates":[12.728549,43.968712],"type":"Point"}
}