{
  "type": "Feature",
  "properties": {
    "iso:country":"IT",
    "sg:address":"10078 Venaria",
    "sg:orig_category":"Servizi Culturali E Per Lo Spettacolo. Servizi Al Turismo. Acqua, Luce, Gas E Societa' Di Esercizio Pubblico",
    "sg:phone":"+39 011 495780",
    "sg:postcode":"10078",
    "sg:province":"Torino",
    "wof:name":"Municipio",
    "wof:placetype":"venue"
},
  "geometry": {"coordinates":[7.626093,45.135071],"type":"Point"}
}