{
  "type": "Feature",
  "properties": {
    "addr:full":"11100 Aosta Aosta Aosta 11100",
    "addr:postcode":"11100;11100",
    "iso:country":"IT",
    "sg:address":"11100 Aosta",
    "sg:city":"Aosta",
    "sg:orig_category":"Pubblica Amministrazione",
    "sg:phone":"+39 0165 3001",
    "sg:postcode":"11100",
    "sg:province":"Aosta",
    "sg:website":"http://www.comune.aosta.it",
    "wof:name":"Comune Di Aosta",
    "wof:placetype":"venue"
},
  "geometry": {"coordinates":[7.320166111,45.7373123169],"type":"Point"}
}