{
  "type": "Feature",
  "properties": {
    "iso:country":"IT",
    "sg:address":"25050 Pisogne",
    "sg:orig_category":"Macchine Utensili E Impianti",
    "sg:phone":"+39 036 489030",
    "sg:postcode":"25050",
    "sg:province":"Brescia",
    "wof:name":"Trafileria Camuna Srl",
    "wof:placetype":"venue"
},
  "geometry": {"coordinates":[10.130432,45.831421],"type":"Point"}
}