{
  "type": "Feature",
  "properties": {
    "iso:country":"IT",
    "sg:address":"58022 Follonica",
    "sg:city":"Follonica",
    "sg:orig_category":"Ottica, Lenti A Contatto Ed Occhiali - Vendita Al Dettaglio",
    "sg:phone":"+39 0566 43770",
    "sg:postcode":"58022",
    "sg:province":"Grosseto",
    "wof:name":"Centro Ottico Tonarelli",
    "wof:placetype":"venue"
},
  "geometry": {"coordinates":[10.756507,42.925278],"type":"Point"}
}