{
  "type": "Feature",
  "properties": {
    "addr:full":"12, Via Galileo Galilei 27052 Godiasco Godiasco Pavia 27052",
    "addr:postcode":"27052;27052",
    "addr:street":"Via Galileo Galilei",
    "iso:country":"IT",
    "sg:address":"12, Via Galileo Galilei 27052 Godiasco",
    "sg:city":"Godiasco",
    "sg:classifiers":[
        {
            "category":"Travel",
            "subcategory":"Travel Agent",
            "type":"Entertainment"
        }
    ],
    "sg:phone":"+39 0383 944520",
    "sg:postcode":"27052",
    "sg:province":"Pavia",
    "sg:tags":[
        "business"
    ],
    "wof:name":"Nuovo Hotel Terme",
    "wof:placetype":"venue"
},
  "geometry": {"coordinates":[9.156563,45.185886],"type":"Point"}
}