{
  "type": "Feature",
  "properties": {
    "iso:country":"IT",
    "sg:address":"06012 Citta'dicastello",
    "sg:orig_category":"Cartotecnica E Servizi. Prodotti E Manufatti In Materie Plastiche. Articoli Per Imballaggio E Confezionamento",
    "sg:phone":"+39 075 851 1256",
    "sg:postcode":"06012",
    "sg:province":"Perugia",
    "sg:website":"http://www.litop.com",
    "wof:name":"Litop Sas",
    "wof:placetype":"venue"
},
  "geometry": {"coordinates":[12.231905,43.457787],"type":"Point"}
}