{
  "type": "Feature",
  "properties": {
    "iso:country":"IT",
    "sg:address":"63023 Fermo",
    "sg:city":"Fermo",
    "sg:orig_category":"Scuole E Servizi Scolastici",
    "sg:phone":"+39 0734 223333",
    "sg:postcode":"63023",
    "sg:province":"Ascoli Piceno",
    "wof:name":"Sobrini Demis",
    "wof:placetype":"venue"
},
  "geometry": {"coordinates":[13.794646,43.183071],"type":"Point"}
}