{
  "type": "Feature",
  "properties": {
    "iso:country":"IT",
    "sg:address":"50026 S. Casciano Val Di Pesa",
    "sg:orig_category":"Ricevimenti E Banchetti - Sale E Servizi",
    "sg:phone":"+39 055 820977",
    "sg:postcode":"50026",
    "sg:province":"Firenze",
    "wof:name":"Ristorante Il Mulinaccio Sas",
    "wof:placetype":"venue"
},
  "geometry": {"coordinates":[11.214704,43.678295],"type":"Point"}
}