{
  "type": "Feature",
  "properties": {
    "iso:country":"IT",
    "sg:address":"Via Delle Primule 5 20020 Cogliate",
    "sg:city":"Cogliate",
    "sg:classifiers":[
        {
            "category":"Shopping",
            "subcategory":"Hobbies, Toys, & Games",
            "type":"Retail Goods"
        }
    ],
    "sg:phone":"+39 02 964751",
    "sg:postcode":"20020",
    "sg:province":"Milano",
    "sg:tags":[
        "baby",
        "infant",
        "toy",
        "toys"
    ],
    "sg:website":"www.giochipreziosi.it",
    "wof:name":"Giochi Preziosi S.p.a.",
    "wof:placetype":"venue"
},
  "geometry": {"coordinates":[9.104408,45.64312],"type":"Point"}
}