{
  "type": "Feature",
  "properties": {
    "iso:country":"IT",
    "sg:address":"Via Gide 33 00143 Roma",
    "sg:city":"Roma",
    "sg:orig_category":"Satellite And Aerospace Systems",
    "sg:phone":"+39 06 502 0321",
    "sg:postcode":"00143",
    "sg:province":"Roma",
    "wof:name":"Ips International Promotion Service Srl",
    "wof:placetype":"venue"
},
  "geometry": {"coordinates":[12.464149,41.809784],"type":"Point"}
}