{
  "type": "Feature",
  "properties": {
    "addr:full":"10156 Torino Torino Torino 10156",
    "addr:postcode":"10156;10156",
    "iso:country":"IT",
    "sg:address":"10156 Torino",
    "sg:city":"Torino",
    "sg:classifiers":[
        {
            "category":"Manufacturing",
            "subcategory":"Metals",
            "type":"Manufacturing & Wholesale Goods"
        }
    ],
    "sg:phone":"+39 011 470 1687",
    "sg:postcode":"10156",
    "sg:province":"Torino",
    "sg:tags":[
        "packaging",
        "article",
        "packing",
        "various",
        "products"
    ],
    "sg:website":"http://www.fiorecontenitori.com",
    "wof:name":"Fiore Srl",
    "wof:placetype":"venue"
},
  "geometry": {"coordinates":[7.70615,45.119347],"type":"Point"}
}