{
  "type": "Feature",
  "properties": {
    "iso:country":"IT",
    "sg:address":"30030 Martellago",
    "sg:city":"Martellago",
    "sg:orig_category":"Manufacturers: Prefabbricati",
    "sg:phone":"+39 041 503 0374",
    "sg:postcode":"30030",
    "sg:province":"Venezia",
    "wof:name":"Berta Marino",
    "wof:placetype":"venue"
},
  "geometry": {"coordinates":[12.154462,45.52282],"type":"Point"}
}