{
  "type": "Feature",
  "properties": {
    "iso:country":"IT",
    "sg:address":"90143 Palermo",
    "sg:city":"Palermo",
    "sg:orig_category":"Associazioni Ed Organismi Di Interesse Pubblico",
    "sg:phone":"+39 091 307761",
    "sg:postcode":"90143",
    "sg:province":"Palermo",
    "wof:name":"Associazione Adiconsum Difesa Consumatori",
    "wof:placetype":"venue"
},
  "geometry": {"coordinates":[13.347238,38.137875],"type":"Point"}
}