{
  "type": "Feature",
  "properties": {
    "iso:country":"IT",
    "sg:address":"C.so Italia 169; Villammare; 84070",
    "sg:classifiers":[
        {
            "category":"Banks & Credit Unions",
            "subcategory":"Bank",
            "type":"Services"
        }
    ],
    "sg:phone":"+39 0973 365026",
    "sg:postcode":"84070",
    "sg:province":"Salerno",
    "wof:name":"Banca Di Lucania",
    "wof:placetype":"venue"
},
  "geometry": {"coordinates":[15.591993,40.074753],"type":"Point"}
}