{
  "type": "Feature",
  "properties": {
    "iso:country":"IT",
    "sg:address":"10088 Volpiano",
    "sg:city":"Volpiano",
    "sg:orig_category":"Macchine, Impianti Ed Attrezzature Industria Chimica. Attrezzature E Forniture Per Officine Riparazione E Servizi Ausiliari",
    "sg:phone":"+39 011 995 3810",
    "sg:postcode":"10088",
    "sg:province":"Torino",
    "wof:name":"P.c.m. Srl",
    "wof:placetype":"venue"
},
  "geometry": {"coordinates":[7.766539,45.178349],"type":"Point"}
}