{
  "type": "Feature",
  "properties": {
    "addr:full":"20063 Cernusco Sul Naviglio Cernusco sul Naviglio Milano 20063",
    "addr:postcode":"20063;20063",
    "iso:country":"IT",
    "sg:address":"20063 Cernusco Sul Naviglio",
    "sg:city":"Cernusco sul Naviglio",
    "sg:orig_category":"Motori Ed Organi Di Trasmissione",
    "sg:phone":"+39 02 9210 6954",
    "sg:postcode":"20063",
    "sg:province":"Milano",
    "wof:name":"A.t.t.i. (s.r.l.)",
    "wof:placetype":"venue"
},
  "geometry": {"coordinates":[9.3268976212,45.5275878906],"type":"Point"}
}