{
  "type": "Feature",
  "properties": {
    "iso:country":"IT",
    "sg:address":"00152 Roma",
    "sg:city":"Roma",
    "sg:orig_category":"Arredo Camera Letto E Complementi. Servizi E Lavori Per Arredamento E Industria Del Legno",
    "sg:phone":"+39 06 557 6898",
    "sg:postcode":"00152",
    "sg:province":"Roma",
    "wof:name":"A. & F. (s.r.l.)",
    "wof:placetype":"venue"
},
  "geometry": {"coordinates":[12.462209,41.868271],"type":"Point"}
}