{
  "type": "Feature",
  "properties": {
    "addr:full":"04012 Cisterna Di Latina Cisterna di Latina Latina 04012",
    "addr:postcode":"04012;04012",
    "iso:country":"IT",
    "sg:address":"04012 Cisterna Di Latina",
    "sg:city":"Cisterna di Latina",
    "sg:orig_category":"Motori Ed Organi Di Trasmissione. Ricambi E Componenti Dei Mezzi Di Trasporto",
    "sg:phone":"+39 06 968 0344",
    "sg:postcode":"04012",
    "sg:province":"Latina",
    "wof:name":"La Nuova Rettifica Ricambi S.a.s.",
    "wof:placetype":"venue"
},
  "geometry": {"coordinates":[12.8075532913,41.6127052307],"type":"Point"}
}