{
  "type": "Feature",
  "properties": {
    "addr:full":"9, Via Della Stanga 23801 Calolziocorte Calolziocorte Lecco 23801",
    "addr:postcode":"23801;23801",
    "addr:street":"Via Della Stanga",
    "iso:country":"IT",
    "sg:address":"9, Via Della Stanga 23801 Calolziocorte",
    "sg:city":"Calolziocorte",
    "sg:classifiers":[
        {
            "category":"Real Estate",
            "subcategory":"Surveying",
            "type":"Services"
        }
    ],
    "sg:phone":"+39 39800341251",
    "sg:postcode":"23801",
    "sg:province":"Lecco",
    "sg:tags":[
        "equipment",
        "material",
        "good",
        "-",
        "handling"
    ],
    "wof:name":"Prim S.p.a.",
    "wof:placetype":"venue"
},
  "geometry": {"coordinates":[9.438786,45.78231],"type":"Point"}
}