{
  "type": "Feature",
  "properties": {
    "iso:country":"IT",
    "sg:address":"25126 Brescia",
    "sg:city":"Brescia",
    "sg:orig_category":"Montacarichi Ed Elevatori",
    "sg:phone":"+39 030 240 0656",
    "sg:postcode":"25126",
    "sg:province":"Brescia",
    "wof:name":"Stam Sil",
    "wof:placetype":"venue"
},
  "geometry": {"coordinates":[10.205406189,45.5364494324],"type":"Point"}
}