{
  "type": "Feature",
  "properties": {
    "iso:country":"IT",
    "sg:address":"31057 Silea",
    "sg:city":"Silea",
    "sg:orig_category":"Prodotti Di Base E Forniture Per Industria Alimentare E Bevande. Forniture Per Attivita' Commerciali Ed Artigianali",
    "sg:phone":"+39 0422 360282",
    "sg:postcode":"31057",
    "sg:province":"Treviso",
    "wof:name":"La Cialcon Di Vanin Luigi E Roberto & C.(s.n.c.)",
    "wof:placetype":"venue"
},
  "geometry": {"coordinates":[12.3068437576,45.6480751038],"type":"Point"}
}