{
  "type": "Feature",
  "properties": {
    "iso:country":"IT",
    "sg:address":"1, Via Giacomo Manzu' 24035 Curno",
    "sg:city":"Curno",
    "sg:classifiers":[
        {
            "category":"Professional",
            "subcategory":"Engineering",
            "type":"Services"
        }
    ],
    "sg:phone":"+39 39035615279",
    "sg:postcode":"24035",
    "sg:province":"Bergamo",
    "sg:tags":[
        "machine",
        "-",
        "mechanical"
    ],
    "wof:name":"Tecnomacchine (s.a.s.)",
    "wof:placetype":"venue"
},
  "geometry": {"coordinates":[9.612977,45.692352],"type":"Point"}
}