{
  "type": "Feature",
  "properties": {
    "addr:full":"10029 Villastellone Villastellone Torino 10029",
    "addr:housenumber":"10029",
    "addr:postcode":"10029",
    "addr:street":"Villastellone Villastellone",
    "iso:country":"IT",
    "sg:address":"10029 Villastellone",
    "sg:city":"Villastellone",
    "sg:classifiers":[
        {
            "category":"Health Services",
            "subcategory":"Health Practitioner",
            "type":"Services"
        }
    ],
    "sg:phone":"+39 011 961 9484",
    "sg:postcode":"10029",
    "sg:province":"Torino",
    "sg:tags":[
        "medici"
    ],
    "wof:name":"Istituto Medico Morgagni",
    "wof:placetype":"venue"
},
  "geometry": {"coordinates":[7.746083,44.921539],"type":"Point"}
}