{
  "type": "Feature",
  "properties": {
    "iso:country":"IT",
    "sg:address":"00138 Roma",
    "sg:city":"Roma",
    "sg:orig_category":"Macchine E Forniture Per Industria Orafa E Per Orologeria",
    "sg:phone":"+39 06 881 0879",
    "sg:postcode":"00138",
    "sg:province":"Roma",
    "wof:name":"Centro Commerciale Giubileo",
    "wof:placetype":"venue"
},
  "geometry": {"coordinates":[12.515914,41.985905],"type":"Point"}
}