{
  "type": "Feature",
  "properties": {
    "addr:full":"90124 Palermo Palermo Palermo 90124",
    "addr:postcode":"90124;90124",
    "iso:country":"IT",
    "sg:address":"90124 Palermo",
    "sg:city":"Palermo",
    "sg:classifiers":[
        {
            "category":"Sports & Exercise",
            "subcategory":"Tennis Court",
            "type":"Entertainment"
        }
    ],
    "sg:phone":"+39 091 616 5556",
    "sg:postcode":"90124",
    "sg:province":"Palermo",
    "sg:tags":[
        "e",
        "lo",
        "tempo",
        "libero",
        "per",
        "impianti",
        "il",
        "attrezzature"
    ],
    "wof:name":"Olimpia Raffineria Salgemma Srl",
    "wof:placetype":"venue"
},
  "geometry": {"coordinates":[13.371387,38.105011],"type":"Point"}
}