{
  "type": "Feature",
  "properties": {
    "addr:full":"4, Via Grado 21052 Busto Arsizio Busto Arsizio Varese 21052",
    "addr:postcode":"21052;21052",
    "addr:street":"Via Grado",
    "iso:country":"IT",
    "sg:address":"4, Via Grado 21052 Busto Arsizio",
    "sg:city":"Busto Arsizio",
    "sg:classifiers":[
        {
            "category":"Shopping",
            "subcategory":"Crafts & Fabrics",
            "type":"Retail Goods"
        }
    ],
    "sg:phone":"+39 0331 631064",
    "sg:postcode":"21052",
    "sg:province":"Varese",
    "wof:name":"Magugliani Fratelli Di Carlo (s.r.l.)",
    "wof:placetype":"venue"
},
  "geometry": {"coordinates":[8.8394117355,45.5990447998],"type":"Point"}
}