{
  "type": "Feature",
  "properties": {
    "iso:country":"IT",
    "sg:address":"20126 Milano",
    "sg:city":"Milano",
    "sg:orig_category":"Professionisti - Studi E Servizi Ed Associazioni Di Interesse Aziendale. Associazioni Ed Organismi Di Interesse Pubblico",
    "sg:phone":"+39 02 2611 3512",
    "sg:postcode":"20126",
    "sg:province":"Milano",
    "wof:name":"Forza Italia",
    "wof:placetype":"venue"
},
  "geometry": {"coordinates":[9.2207994461,45.5001144409],"type":"Point"}
}