{
  "type": "Feature",
  "properties": {
    "addr:full":"Via Roma 45 21057 Olgiate Olona Olgiate Olona Varese 21057",
    "addr:housenumber":"45",
    "addr:postcode":"21057;21057",
    "addr:street":"Via Roma",
    "iso:country":"IT",
    "sg:address":"Via Roma 45 21057 Olgiate Olona",
    "sg:city":"Olgiate Olona",
    "sg:classifiers":[
        {
            "category":"Health Services",
            "subcategory":"Dentist",
            "type":"Services"
        }
    ],
    "sg:phone":"+39 0331 376760",
    "sg:postcode":"21057",
    "sg:province":"Varese",
    "sg:tags":[
        "dental",
        "implant"
    ],
    "wof:name":"De G\u00d6tzen Srl",
    "wof:placetype":"venue"
},
  "geometry": {"coordinates":[8.903342,45.753658],"type":"Point"}
}