{
  "type": "Feature",
  "properties": {
    "addr:full":"Via Dell'industria 6 21040 Origgio Origgio Varese 21040",
    "addr:housenumber":"6",
    "addr:postcode":"21040;21040",
    "addr:street":"Via Dell'Industria",
    "iso:country":"IT",
    "sg:address":"Via Dell'industria 6 21040 Origgio",
    "sg:city":"Origgio",
    "sg:classifiers":[
        {
            "category":"Home & Garden",
            "subcategory":"Home Furnishings",
            "type":"Retail Goods"
        }
    ],
    "sg:phone":"+39 02 969501",
    "sg:postcode":"21040",
    "sg:province":"Varese",
    "sg:tags":[
        "bathroom",
        "wc",
        "fitting"
    ],
    "sg:website":"www.gedy.com",
    "wof:name":"Gedy Spa",
    "wof:placetype":"venue"
},
  "geometry": {"coordinates":[8.826385,45.817604],"type":"Point"}
}