{
  "type": "Feature",
  "properties": {
    "iso:country":"IT",
    "sg:address":"90127 Palermo",
    "sg:city":"Palermo",
    "sg:classifiers":[
        {
            "category":"Health Services",
            "subcategory":"Health Practitioner",
            "type":"Services"
        }
    ],
    "sg:phone":"+39 091 651 6139",
    "sg:postcode":"90127",
    "sg:province":"Palermo",
    "sg:tags":[
        "medici"
    ],
    "wof:name":"Idt Istituto Diagnostico Toscano",
    "wof:placetype":"venue"
},
  "geometry": {"coordinates":[13.360769,38.107502],"type":"Point"}
}