{
  "type": "Feature",
  "properties": {
    "iso:country":"IT",
    "sg:address":"42100 Reggio Emilia",
    "sg:orig_category":"Servizi Per Aziende, Manifestazioni E Supporto Agli Scambi Commerciali",
    "sg:phone":"+39 0522 232354",
    "sg:postcode":"42100",
    "sg:province":"Reggio Nell'Emilia",
    "sg:website":"http://www.eurods.it",
    "wof:name":"Eurodesign Allestimenti",
    "wof:placetype":"venue"
},
  "geometry": {"coordinates":[10.611506,44.728703],"type":"Point"}
}