{
  "type": "Feature",
  "properties": {
    "addr:full":"54031 Carrara MS",
    "addr:postcode":"54031",
    "iso:country":"IT",
    "sg:address":"54031 Carrara",
    "sg:orig_category":"Marmo, Granito E Pietre Lavorazione - Macchine",
    "sg:phone":"+39 0585 857342",
    "sg:province":"MS",
    "sg:website":"http://www.micheletti-macchine.com",
    "wof:name":"Micheletti Macchine Srl",
    "wof:placetype":"venue"
},
  "geometry": {"coordinates":[10.068837,44.051357],"type":"Point"}
}