{
  "type": "Feature",
  "properties": {
    "iso:country":"IT",
    "sg:address":"09045 Quartu S. Elena",
    "sg:orig_category":"Ospedali E Servizi Sanitari",
    "sg:phone":"+39 070 883886",
    "sg:postcode":"09045",
    "sg:province":"Cagliari",
    "wof:name":"Laboratorio Analisi Patologia Chimico Clinica",
    "wof:placetype":"venue"
},
  "geometry": {"coordinates":[9.186585,39.232925],"type":"Point"}
}