{
  "type": "Feature",
  "properties": {
    "addr:full":"00171 Roma Roma Roma 00171",
    "addr:postcode":"00171;00171",
    "iso:country":"IT",
    "sg:address":"00171 Roma",
    "sg:city":"Roma",
    "sg:orig_category":"Arredamenti - Vendita Al Dettaglio",
    "sg:phone":"+39 06 259 8947",
    "sg:postcode":"00171",
    "sg:province":"Roma",
    "wof:name":"Civitavecchia Pietro - Piero Mobili",
    "wof:placetype":"venue"
},
  "geometry": {"coordinates":[12.566254,41.891651],"type":"Point"}
}