{
  "type": "Feature",
  "properties": {
    "iso:country":"IT",
    "sg:address":"55, Via S. Michele 31032 Casale Sul Sile",
    "sg:city":"Casale sul Sile",
    "sg:classifiers":[
        {
            "category":"Autos & Motor Vehicles",
            "subcategory":"Boat Sales",
            "type":"Retail Goods"
        }
    ],
    "sg:phone":"+39 0422 821000",
    "sg:postcode":"31032",
    "sg:province":"Treviso",
    "wof:name":"Cantiere Nautico Vz (s.r.l.)",
    "wof:placetype":"venue"
},
  "geometry": {"coordinates":[12.242072,45.666286],"type":"Point"}
}