{
  "type": "Feature",
  "properties": {
    "addr:full":"Loc. Larzano 29029 Rivergaro Rivergaro Piacenza 29029",
    "addr:postcode":"29029;29029",
    "addr:street":"Loc. Larzano",
    "iso:country":"IT",
    "sg:address":"Loc. Larzano 29029 Rivergaro",
    "sg:city":"Rivergaro",
    "sg:classifiers":[
        {
            "category":"Manufacturing",
            "subcategory":"Paper Products",
            "type":"Manufacturing & Wholesale Goods"
        }
    ],
    "sg:phone":"+39 0523 956301",
    "sg:postcode":"29029",
    "sg:province":"Piacenza",
    "sg:tags":[
        "cardboard"
    ],
    "sg:website":"http://www.paginegialle.it/etik90pc",
    "wof:name":"Etik 90 Srl",
    "wof:placetype":"venue"
},
  "geometry": {"coordinates":[9.6951417923,45.0537719727],"type":"Point"}
}