{
  "type": "Feature",
  "properties": {
    "iso:country":"IT",
    "sg:address":"97016 Pozzallo",
    "sg:city":"Pozzallo",
    "sg:orig_category":"Trasporto Pubblico E Privato",
    "sg:phone":"+39 0932 797140",
    "sg:postcode":"97016",
    "sg:province":"Ragusa",
    "wof:name":"Siciltour Di Ricca & C. Sas",
    "wof:placetype":"venue"
},
  "geometry": {"coordinates":[14.862974,36.736912],"type":"Point"}
}