{
  "type": "Feature",
  "properties": {
    "iso:country":"IT",
    "sg:address":"38079 Tione Di Trento",
    "sg:city":"Tione di Trento",
    "sg:orig_category":"Abbigliamento Esterno, Maglierie E Pelliccerie",
    "sg:phone":"+39 0465 339311",
    "sg:postcode":"38079",
    "sg:province":"Trento",
    "wof:name":"Novurania S P A",
    "wof:placetype":"venue"
},
  "geometry": {"coordinates":[10.728194,46.034348],"type":"Point"}
}