{
  "type": "Feature",
  "properties": {
    "iso:country":"IT",
    "sg:address":"25122 Brescia",
    "sg:city":"Brescia",
    "sg:orig_category":"Bilance, Bilici E Bascule",
    "sg:phone":"+39 030 294809",
    "sg:postcode":"25122",
    "sg:province":"Brescia",
    "sg:website":"http://www.lenzinibilance.it",
    "wof:name":"Lenzini Di Lenzini Mauro & C. Snc",
    "wof:placetype":"venue"
},
  "geometry": {"coordinates":[10.215284,45.540356],"type":"Point"}
}