{
  "type": "Feature",
  "properties": {
    "iso:country":"IT",
    "sg:address":"Via Paolo Da Cannobio 10 20122 Milano",
    "sg:city":"Milano",
    "sg:classifiers":[
        {
            "category":"Wholesale",
            "subcategory":"Auto Parts",
            "type":"Manufacturing & Wholesale Goods"
        }
    ],
    "sg:phone":"+39 02 809926",
    "sg:postcode":"20122",
    "sg:province":"Milano",
    "sg:tags":[
        "machine",
        "precision",
        "special"
    ],
    "sg:website":"www.mariodimaio.com",
    "wof:name":"Mario Di Maio Spa",
    "wof:placetype":"venue"
},
  "geometry": {"coordinates":[9.190247,45.461346],"type":"Point"}
}