{
  "type": "Feature",
  "properties": {
    "addr:full":"77, Corso Volta Alessandro 80040 Terzigno Terzigno Napoli 80040",
    "addr:postcode":"80040;80040",
    "addr:street":"Corso Volta Alessandro",
    "iso:country":"IT",
    "sg:address":"77, Corso Volta Alessandro 80040 Terzigno",
    "sg:city":"Terzigno",
    "sg:classifiers":[
        {
            "category":"Shopping",
            "subcategory":"Clothing, Apparel, & Fashions",
            "type":"Retail Goods"
        }
    ],
    "sg:phone":"+39 081 529 2573",
    "sg:postcode":"80040",
    "sg:province":"Napoli",
    "sg:tags":[
        "clothes"
    ],
    "wof:name":"Dago Sas",
    "wof:placetype":"venue"
},
  "geometry": {"coordinates":[14.251636,40.840096],"type":"Point"}
}