{
  "type": "Feature",
  "properties": {
    "addr:full":"36071 Arzignano Arzignano Vicenza 36071",
    "addr:postcode":"36071;36071",
    "iso:country":"IT",
    "sg:address":"36071 Arzignano",
    "sg:city":"Arzignano",
    "sg:classifiers":[
        {
            "category":"Retail",
            "subcategory":"Event Space",
            "type":"Services"
        }
    ],
    "sg:phone":"+39 0444 473911",
    "sg:postcode":"36071",
    "sg:province":"Vicenza",
    "sg:tags":[
        "leather",
        "clothing",
        "goods",
        "work"
    ],
    "sg:website":"http://www.gruppoconciarioveneto.com",
    "wof:name":"Gruppo Conciario Veneto",
    "wof:placetype":"venue"
},
  "geometry": {"coordinates":[11.512953,45.5261],"type":"Point"}
}