{
  "type": "Feature",
  "properties": {
    "iso:country":"IT",
    "sg:address":"46/50 V. Fratelli Buschetto - Zona Industriale 84014 Nocera Inferiore",
    "sg:city":"Nocera Inferiore",
    "sg:classifiers":[
        {
            "category":"Food & Beverages",
            "subcategory":"Groceries & Convenience Stores",
            "type":"Retail Goods"
        }
    ],
    "sg:phone":"+39 39081924445",
    "sg:postcode":"84014",
    "sg:province":"Salerno",
    "sg:tags":[
        "product",
        "related"
    ],
    "sg:website":"http://www.aromi.it:ws_end: :mark:ws:http://www.paginegialle.it/aromimediterranei",
    "wof:name":"Aromi Mediterranei Visa Srl",
    "wof:placetype":"venue"
},
  "geometry": {"coordinates":[14.765912056,40.6779556274],"type":"Point"}
}