{
  "type": "Feature",
  "properties": {
    "iso:country":"IT",
    "sg:address":"40064 Ozzano Dell'emilia",
    "sg:orig_category":"Macchine Utensili E Impianti. Apparecchiature Ed Attrezzature Meccaniche",
    "sg:phone":"+39 051 796737",
    "sg:postcode":"40064",
    "sg:province":"Bologna",
    "wof:name":"F.s.g. Di Gasperini G.battista & C. (s.n.c.)",
    "wof:placetype":"venue"
},
  "geometry": {"coordinates":[11.503451,44.465221],"type":"Point"}
}