{
  "type": "Feature",
  "properties": {
    "iso:country":"IT",
    "sg:address":"20017 Rho",
    "sg:city":"Rho",
    "sg:orig_category":"Serramenti Ed Infissi",
    "sg:phone":"+39 02 9316 2157",
    "sg:postcode":"20017",
    "sg:province":"Milano",
    "wof:name":"Nuovo Centro Serramenti Snc",
    "wof:placetype":"venue"
},
  "geometry": {"coordinates":[9.04293,45.524986],"type":"Point"}
}