{
  "type": "Feature",
  "properties": {
    "iso:country":"IT",
    "sg:address":"52, Via Pastrengo 37012 Bussolengo",
    "sg:city":"Bussolengo",
    "sg:classifiers":[
        {
            "category":"Shopping",
            "subcategory":"Clothing, Apparel, & Fashions",
            "type":"Retail Goods"
        }
    ],
    "sg:phone":"+39 045 715 2976",
    "sg:postcode":"37012",
    "sg:province":"Verona",
    "sg:tags":[
        "clothes"
    ],
    "wof:name":"Walmode (s.r.l.)",
    "wof:placetype":"venue"
},
  "geometry": {"coordinates":[10.845164,45.474045],"type":"Point"}
}