{
  "type": "Feature",
  "properties": {
    "addr:full":"20083 Gaggiano Gaggiano Milano 20083",
    "addr:postcode":"20083;20083",
    "iso:country":"IT",
    "sg:address":"20083 Gaggiano",
    "sg:city":"Gaggiano",
    "sg:orig_category":"Macchine, Impianti Ed Attrezzature Per Abbigliamento E Pelletterie",
    "sg:phone":"+39 02 908 6965",
    "sg:postcode":"20083",
    "sg:province":"Milano",
    "wof:name":"Paggi S.r.l.",
    "wof:placetype":"venue"
},
  "geometry": {"coordinates":[9.13515,45.527634],"type":"Point"}
}