{
  "type": "Feature",
  "properties": {
    "iso:country":"IT",
    "sg:address":"16145 Genova",
    "sg:city":"Genova",
    "sg:orig_category":"Riparazione Dei Mezzi Di Trasporto. Servizi Ausiliari Dei Mezzi Di Trasporto",
    "sg:phone":"+39 010 374 1193",
    "sg:postcode":"16145",
    "sg:province":"Genova",
    "wof:name":"Impresa Tank Coating Srl",
    "wof:placetype":"venue"
},
  "geometry": {"coordinates":[8.949424,44.395012],"type":"Point"}
}