{
  "type": "Feature",
  "properties": {
    "iso:country":"IT",
    "sg:address":"12100 Cuneo",
    "sg:city":"Cuneo",
    "sg:orig_category":"Servizi E Lavori Per Edilizia E Lavori Pubblici. Professionisti - Studi E Servizi Ed Associazioni Di Interesse Aziendale",
    "sg:phone":"+39 0171 699935",
    "sg:postcode":"12100",
    "sg:province":"Cuneo",
    "wof:name":"Fino Geom. Corrado Rilievi Topografici",
    "wof:placetype":"venue"
},
  "geometry": {"coordinates":[7.820601,44.389576],"type":"Point"}
}