{
  "type": "Feature",
  "properties": {
    "iso:country":"IT",
    "sg:address":"00040 Monte Porzio Catone",
    "sg:city":"Monte Porzio Catone",
    "sg:orig_category":"Ospedali E Servizi Sanitari. Servizi Ausiliari Di Analisi, Controllo E Ricerca",
    "sg:phone":"+39 06 944 7304",
    "sg:postcode":"00040",
    "sg:province":"Roma",
    "wof:name":"Gagliardi Ezio",
    "wof:placetype":"venue"
},
  "geometry": {"coordinates":[12.716998,41.813942],"type":"Point"}
}