{
  "type": "Feature",
  "properties": {
    "addr:full":"09025 Sanluri Sanluri Medio Campidano 09025",
    "addr:postcode":"09025;09025",
    "iso:country":"IT",
    "sg:address":"09025 Sanluri",
    "sg:city":"Sanluri",
    "sg:orig_category":"Prodotti Alimentari",
    "sg:phone":"+39 070 937 1216",
    "sg:postcode":"09025",
    "sg:province":"Medio Campidano",
    "wof:name":"Molinor Srl",
    "wof:placetype":"venue"
},
  "geometry": {"coordinates":[8.7040748596,39.5317382812],"type":"Point"}
}