{
  "type": "Feature",
  "properties": {
    "addr:full":"Via Della Rupe 35 38017 Mezzolombardo Mezzolombardo Trento 38017",
    "addr:housenumber":"35",
    "addr:postcode":"38017;38017",
    "addr:street":"Via Della Rupe",
    "iso:country":"IT",
    "sg:address":"Via Della Rupe 35 38017 Mezzolombardo",
    "sg:city":"Mezzolombardo",
    "sg:classifiers":[
        {
            "category":"Bars & Pubs",
            "subcategory":"Nightclub",
            "type":"Food & Drink"
        }
    ],
    "sg:phone":"+39 0461 602376",
    "sg:postcode":"38017",
    "sg:province":"Trento",
    "sg:tags":[
        "lamp",
        "halogen",
        "illuminant"
    ],
    "sg:website":"www.rotaliana.it",
    "wof:name":"Elettrica Rotaliana Srl",
    "wof:placetype":"venue"
},
  "geometry": {"coordinates":[11.097796,46.192043],"type":"Point"}
}