{
  "type": "Feature",
  "properties": {
    "addr:full":"35010 Campo San Martino Campo San Martino Padova 35010",
    "addr:housenumber":"35010",
    "addr:postcode":"35010",
    "addr:street":"Campo;San",
    "iso:country":"IT",
    "sg:address":"35010 Campo San Martino",
    "sg:city":"Campo San Martino",
    "sg:orig_category":"Sport - Articoli E Forniture",
    "sg:phone":"+39 049 552009",
    "sg:postcode":"35010",
    "sg:province":"Padova",
    "wof:name":"Finco Munizioni Di Finco Giorgio & C. (s.n.c.)",
    "wof:placetype":"venue"
},
  "geometry": {"coordinates":[11.115941,45.418343],"type":"Point"}
}