{
  "type": "Feature",
  "properties": {
    "addr:full":"Viale C Battisti; Atessa; 66041 Atessa Chieti 66041",
    "addr:postcode":"66041;66041",
    "addr:street":"Viale C Battisti",
    "iso:country":"IT",
    "sg:address":"Viale C Battisti; Atessa; 66041",
    "sg:city":"Atessa",
    "sg:classifiers":[
        {
            "category":"Banks & Credit Unions",
            "subcategory":"Bank",
            "type":"Services"
        }
    ],
    "sg:phone":"+39 0872 866239",
    "sg:postcode":"66041",
    "sg:province":"Chieti",
    "wof:name":"Banco Di Napoli Spa",
    "wof:placetype":"venue"
},
  "geometry": {"coordinates":[14.445889,42.067734],"type":"Point"}
}