{
  "type": "Feature",
  "properties": {
    "iso:country":"IT",
    "sg:address":"24048 Treviolo",
    "sg:city":"Treviolo",
    "sg:orig_category":"Arredi Ed Attrezzature Per Attivita' Commerciali Ed Artigianali",
    "sg:phone":"+39 035 200733",
    "sg:postcode":"24048",
    "sg:province":"Bergamo",
    "sg:website":"http://www.novideastand.it",
    "wof:name":"Novidea Stand Srl",
    "wof:placetype":"venue"
},
  "geometry": {"coordinates":[9.593619,45.665691],"type":"Point"}
}