{
  "type": "Feature",
  "properties": {
    "addr:full":"Via Portuense 95/h 00153 Roma Roma Roma 00153",
    "addr:housenumber":"95 / h",
    "addr:postcode":"00153;00153",
    "addr:street":"Via Portuense",
    "iso:country":"IT",
    "sg:address":"Via Portuense 95/h 00153 Roma",
    "sg:city":"Roma",
    "sg:classifiers":[
        {
            "category":"Shopping",
            "subcategory":"Luggage & Leather Goods",
            "type":"Retail Goods"
        }
    ],
    "sg:phone":"+39 06 589 6638",
    "sg:postcode":"00153",
    "sg:province":"Roma",
    "sg:tags":[
        "clothing"
    ],
    "sg:website":"www.pietrocorsi.com",
    "wof:name":"Pietro Corsi & C Srl",
    "wof:placetype":"venue"
},
  "geometry": {"coordinates":[12.45293,41.862167],"type":"Point"}
}