{
  "type": "Feature",
  "properties": {
    "iso:country":"IT",
    "sg:address":"80067 Sorrento",
    "sg:city":"Sorrento",
    "sg:orig_category":"Prodotti Alimentari",
    "sg:phone":"+39 081 877 3724",
    "sg:postcode":"80067",
    "sg:province":"Napoli",
    "sg:website":"http://www.saporietradizioni.com",
    "wof:name":"Sapori E Tradizioni Snc",
    "wof:placetype":"venue"
},
  "geometry": {"coordinates":[14.3835687637,40.6240997314],"type":"Point"}
}