{
  "type": "Feature",
  "properties": {
    "addr:full":"47, Via Costituzione 42015 Correggio Reggio Nell'Emilia 42015",
    "addr:postcode":"42015;42015",
    "addr:street":"Via Costituzione",
    "iso:country":"IT",
    "sg:address":"47, Via Costituzione 42015 Correggio",
    "sg:classifiers":[
        {
            "category":"Manufacturing",
            "subcategory":"Rubber & Plastics",
            "type":"Manufacturing & Wholesale Goods"
        }
    ],
    "sg:phone":"+39 0522 637722",
    "sg:postcode":"42015",
    "sg:province":"Reggio Nell'Emilia",
    "wof:name":"Nosi Plast S.r.l",
    "wof:placetype":"venue"
},
  "geometry": {"coordinates":[10.826426506,44.7717933655],"type":"Point"}
}