{
  "type": "Feature",
  "properties": {
    "addr:full":"02100 Rieti Rieti Rieti 02100",
    "addr:postcode":"02100;02100",
    "iso:country":"IT",
    "sg:address":"02100 Rieti",
    "sg:city":"Rieti",
    "sg:orig_category":"Forniture Per Agricoltura E Zootecnia. Animali Domestici",
    "sg:phone":"+39 0746 496603",
    "sg:postcode":"02100",
    "sg:province":"Rieti",
    "wof:name":"Samperna Nello",
    "wof:placetype":"venue"
},
  "geometry": {"coordinates":[12.8284769058,42.3946495056],"type":"Point"}
}