{
  "type": "Feature",
  "properties": {
    "iso:country":"IT",
    "sg:address":"8, Via Dell' Industria 60031 Castelplanio",
    "sg:city":"Castelplanio",
    "sg:classifiers":[
        {
            "category":"Professional",
            "subcategory":"Engineering",
            "type":"Services"
        }
    ],
    "sg:phone":"+39 0731 814418",
    "sg:postcode":"60031",
    "sg:province":"Ancona",
    "sg:tags":[
        "machine",
        "-",
        "mechanical"
    ],
    "wof:name":"Air Condott S.n.c.",
    "wof:placetype":"venue"
},
  "geometry": {"coordinates":[13.115051,43.50119],"type":"Point"}
}