{
  "type": "Feature",
  "properties": {
    "iso:country":"IT",
    "sg:address":"17100 Savona",
    "sg:city":"Savona",
    "sg:orig_category":"Informatica - Consulenza E Software",
    "sg:phone":"+39 019 826955",
    "sg:postcode":"17100",
    "sg:province":"Savona",
    "sg:website":"http://www.scuolaipi.it",
    "wof:name":"I.p.i.",
    "wof:placetype":"venue"
},
  "geometry": {"coordinates":[8.478672,44.310852],"type":"Point"}
}