{
  "type": "Feature",
  "properties": {
    "iso:country":"IT",
    "sg:address":"20127 Milano",
    "sg:city":"Milano",
    "sg:orig_category":"Ricambi E Componenti Dei Mezzi Di Trasporto",
    "sg:phone":"+39 02 2614 5252",
    "sg:postcode":"20127",
    "sg:province":"Milano",
    "wof:name":"Silenziatori Ascari Di Bertoli Maurizio E C. S.a.s.",
    "wof:placetype":"venue"
},
  "geometry": {"coordinates":[9.219065,45.499847],"type":"Point"}
}