{
  "type": "Feature",
  "properties": {
    "iso:country":"IT",
    "sg:address":"130, V. Perticara 47023 Cesena",
    "sg:city":"Cesena",
    "sg:classifiers":[
        {
            "category":"Manufacturing",
            "subcategory":"Motor Vehicles & Parts",
            "type":"Manufacturing & Wholesale Goods"
        }
    ],
    "sg:phone":"+39 0547 632233",
    "sg:postcode":"47023",
    "sg:province":"Forl\u00ec-Cesena",
    "sg:tags":[
        "engine"
    ],
    "sg:website":"http://www.motoriseven.com",
    "wof:name":"Motori Seven",
    "wof:placetype":"venue"
},
  "geometry": {"coordinates":[12.247049,44.147755],"type":"Point"}
}