{
  "type": "Feature",
  "properties": {
    "addr:full":"Via Ca' Ferrario 14 24030 Caprino Bergamasco Caprino Bergamo 24030",
    "addr:housenumber":"14",
    "addr:postcode":"24030;24030",
    "addr:street":"Via Ca ' Ferrario",
    "iso:country":"IT",
    "sg:address":"Via Ca' Ferrario 14 24030 Caprino Bergamasco",
    "sg:city":"Caprino",
    "sg:orig_category":"Pre-press Services",
    "sg:phone":"+39 035 781298",
    "sg:postcode":"24030",
    "sg:province":"Bergamo",
    "wof:name":"Colour Separation Trust Srl",
    "wof:placetype":"venue"
},
  "geometry": {"coordinates":[9.6699523926,45.6949043274],"type":"Point"}
}