{
  "type": "Feature",
  "properties": {
    "iso:country":"IT",
    "sg:address":"4, V. A. Moro 25030 Roncadelle",
    "sg:city":"Roncadelle",
    "sg:classifiers":[
        {
            "category":"Manufacturing",
            "subcategory":"Tools & Machinery",
            "type":"Manufacturing & Wholesale Goods"
        }
    ],
    "sg:phone":"+39 030 258 4975",
    "sg:postcode":"25030",
    "sg:province":"Brescia",
    "sg:tags":[
        "environment",
        "equipment",
        "-"
    ],
    "sg:website":"http://www.por-srl.it",
    "wof:name":"Ecomec Srl - P.o.r.",
    "wof:placetype":"venue"
},
  "geometry": {"coordinates":[10.141216,45.520557],"type":"Point"}
}