{
  "type": "Feature",
  "properties": {
    "iso:country":"IT",
    "sg:address":"45, Strada I Zona Industriale 35129 Padova",
    "sg:city":"Padova",
    "sg:classifiers":[
        {
            "category":"Autos & Motor Vehicles",
            "subcategory":"Automobile Sales",
            "type":"Retail Goods"
        }
    ],
    "sg:phone":"+39 049 807 4020",
    "sg:postcode":"35129",
    "sg:province":"Padova",
    "sg:tags":[
        "motor-cars"
    ],
    "wof:name":"Emporio Dell'auto (s.p.a.)",
    "wof:placetype":"venue"
},
  "geometry": {"coordinates":[11.1159410477,45.4183425903],"type":"Point"}
}