{
  "type": "Feature",
  "properties": {
    "iso:country":"IT",
    "sg:address":"20132 Milano",
    "sg:city":"Milano",
    "sg:orig_category":"Architetti - Studi",
    "sg:phone":"+39 02 215 4803",
    "sg:postcode":"20132",
    "sg:province":"Milano",
    "wof:name":"Studio Original Designers 6r5 Network",
    "wof:placetype":"venue"
},
  "geometry": {"coordinates":[9.235041,45.489952],"type":"Point"}
}