{
  "type": "Feature",
  "properties": {
    "iso:country":"IT",
    "sg:address":"Via Al Ponte Caprazucca 4, 43100 Parma, Pr",
    "sg:city":"Parma",
    "sg:classifiers":[
        {
            "category":"Banks & Credit Unions",
            "subcategory":"Bank",
            "type":"Services"
        }
    ],
    "sg:postcode":"43100",
    "sg:province":"Parma",
    "wof:name":"Fondazione Cariparma Spa",
    "wof:placetype":"venue"
},
  "geometry": {"coordinates":[10.29492,44.823208],"type":"Point"}
}