{
  "type": "Feature",
  "properties": {
    "addr:full":"58022 Follonica Follonica Grosseto 58022",
    "addr:postcode":"58022;58022",
    "iso:country":"IT",
    "sg:address":"58022 Follonica",
    "sg:city":"Follonica",
    "sg:orig_category":"Apparecchiature Ed Attrezzature Meccaniche. Ricambi E Componenti Dei Mezzi Di Trasporto",
    "sg:phone":"+39 0566 58455",
    "sg:postcode":"58022",
    "sg:province":"Grosseto",
    "wof:name":"Race Factory Di Bardini Simona",
    "wof:placetype":"venue"
},
  "geometry": {"coordinates":[10.766163,42.966339],"type":"Point"}
}