{
  "type": "Feature",
  "properties": {
    "addr:full":"57023 Cecina Cecina Livorno 57023",
    "addr:postcode":"57023;57023",
    "iso:country":"IT",
    "sg:address":"57023 Cecina",
    "sg:city":"Cecina",
    "sg:orig_category":"Insegne Luminose",
    "sg:phone":"+39 0586 632198",
    "sg:postcode":"57023",
    "sg:province":"Livorno",
    "wof:name":"Neon Universal",
    "wof:placetype":"venue"
},
  "geometry": {"coordinates":[10.52931,43.288616],"type":"Point"}
}