{
  "type": "Feature",
  "properties": {
    "iso:country":"IT",
    "sg:address":"37034 Verona",
    "sg:orig_category":"Cantine Sociali",
    "sg:phone":"+39 045 550032",
    "sg:province":"VR",
    "sg:website":"http://www.cantinavalpantena.it",
    "wof:name":"Cantina Sociale Della Valpantena",
    "wof:placetype":"venue"
},
  "geometry": {"coordinates":[-86.681252,35.629597],"type":"Point"}
}