{
  "type": "Feature",
  "properties": {
    "iso:country":"IT",
    "sg:address":"Via Del Padule, 78/80 50018 Scandicci",
    "sg:city":"Scandicci",
    "sg:classifiers":[
        {
            "category":"Shopping",
            "subcategory":"Gifts & Souvenirs",
            "type":"Retail Goods"
        }
    ],
    "sg:phone":"+39 055 721115",
    "sg:postcode":"50018",
    "sg:province":"Firenze",
    "sg:tags":[
        "item"
    ],
    "sg:website":"www.soldiart.com",
    "wof:name":"Soldi Snc",
    "wof:placetype":"venue"
},
  "geometry": {"coordinates":[11.158251,43.760761],"type":"Point"}
}