{
  "type": "Feature",
  "properties": {
    "addr:full":"92015 Raffadali Raffadali Agrigento 92015",
    "addr:postcode":"92015;92015",
    "iso:country":"IT",
    "sg:address":"92015 Raffadali",
    "sg:city":"Raffadali",
    "sg:orig_category":"Ambulanze Private - Servizio",
    "sg:phone":"+39 0922 473340",
    "sg:postcode":"92015",
    "sg:province":"Agrigento",
    "wof:name":"Agenzia Funebre S. Maria Snc",
    "wof:placetype":"venue"
},
  "geometry": {"coordinates":[13.53188,37.400314],"type":"Point"}
}