{
  "type": "Feature",
  "properties": {
    "addr:full":"00176 Roma Roma Roma 00176",
    "addr:postcode":"00176;00176",
    "iso:country":"IT",
    "sg:address":"00176 Roma",
    "sg:city":"Roma",
    "sg:orig_category":"Forniture Per Abbigliamento E Pelletterie",
    "sg:phone":"+39 06 290193",
    "sg:postcode":"00176",
    "sg:province":"Roma",
    "wof:name":"Falasca Doriana",
    "wof:placetype":"venue"
},
  "geometry": {"coordinates":[12.5345697403,41.8902702332],"type":"Point"}
}