{
  "type": "Feature",
  "properties": {
    "addr:full":"05100 Terni Terni Terni 05100",
    "addr:postcode":"05100;05100",
    "iso:country":"IT",
    "sg:address":"05100 Terni",
    "sg:city":"Terni",
    "sg:orig_category":"Autolinee",
    "sg:phone":"+39 0744 406057",
    "sg:postcode":"05100",
    "sg:province":"Terni",
    "sg:website":"http://www.cosed.com",
    "wof:name":"Co.se.a. Soc.coop.r.l.",
    "wof:placetype":"venue"
},
  "geometry": {"coordinates":[12.644587,42.569992],"type":"Point"}
}