{
  "type": "Feature",
  "properties": {
    "addr:full":"00192 Roma Roma Roma 00192",
    "addr:postcode":"00192;00192",
    "iso:country":"IT",
    "sg:address":"00192 Roma",
    "sg:city":"Roma",
    "sg:orig_category":"Case Editrici",
    "sg:phone":"+39 06 321 4150",
    "sg:postcode":"00192",
    "sg:province":"Roma",
    "wof:name":"Palombi Fratelli Srl",
    "wof:placetype":"venue"
},
  "geometry": {"coordinates":[12.465161,41.908649],"type":"Point"}
}