{
  "type": "Feature",
  "properties": {
    "addr:full":"33095 San Giorgio Della Richinvelda Rauscedo Pordenone 33095",
    "addr:housenumber":"33095",
    "addr:postcode":"rauscedo;33095",
    "iso:country":"IT",
    "sg:address":"33095 San Giorgio Della Richinvelda",
    "sg:city":"Rauscedo",
    "sg:orig_category":"Forniture Per Agricoltura E Zootecnia",
    "sg:phone":"+39 0427 948811",
    "sg:postcode":"33095",
    "sg:province":"Pordenone",
    "wof:name":"Vivai Cooperativi Rauscedo Soc.coop.r.l.",
    "wof:placetype":"venue"
},
  "geometry": {"coordinates":[12.8330745697,46.0405693054],"type":"Point"}
}