{
  "type": "Feature",
  "properties": {
    "iso:country":"IT",
    "sg:address":"21/s, Via Valcamonica 25132 Brescia",
    "sg:city":"Brescia",
    "sg:classifiers":[
        {
            "category":"Manufacturing",
            "subcategory":"Metals",
            "type":"Manufacturing & Wholesale Goods"
        }
    ],
    "sg:phone":"+39 39030322221",
    "sg:postcode":"25132",
    "sg:province":"Brescia",
    "sg:tags":[
        "metallurgy",
        "metalworking"
    ],
    "wof:name":"Officine Fonderie Cervati (s.p.a.)",
    "wof:placetype":"venue"
},
  "geometry": {"coordinates":[10.1632585526,45.5475120544],"type":"Point"}
}