{
  "type": "Feature",
  "properties": {
    "addr:full":"35, Via Montecuccoli Raimondo 20147 Milano Milano Milano 20147",
    "addr:postcode":"20147;20147",
    "addr:street":"Via Montecuccoli Raimondo",
    "iso:country":"IT",
    "sg:address":"35, Via Montecuccoli Raimondo 20147 Milano",
    "sg:city":"Milano",
    "sg:classifiers":[
        {
            "category":"Wholesale",
            "subcategory":"Drugs",
            "type":"Manufacturing & Wholesale Goods"
        }
    ],
    "sg:phone":"+39 39024832961",
    "sg:postcode":"20147",
    "sg:province":"Milano",
    "sg:tags":[
        "chemical",
        "pharmaceutical"
    ],
    "wof:name":"B.m.a. Brusati Manifattura Abrasivi Spa",
    "wof:placetype":"venue"
},
  "geometry": {"coordinates":[9.135056,45.459583],"type":"Point"}
}