{
  "type": "Feature",
  "properties": {
    "addr:full":"36075 Montecchio Maggiore Montecchio Maggiore Vicenza 36075",
    "addr:postcode":"36075;36075",
    "iso:country":"IT",
    "sg:address":"36075 Montecchio Maggiore",
    "sg:city":"Montecchio Maggiore",
    "sg:orig_category":"Articoli Sportivi - Produzione E Ingrosso",
    "sg:phone":"+39 0444 499234",
    "sg:postcode":"36075",
    "sg:province":"Vicenza",
    "sg:website":"http://www.rancan.com",
    "wof:name":"Rancan Srl",
    "wof:placetype":"venue"
},
  "geometry": {"coordinates":[11.451921,45.523937],"type":"Point"}
}