{
  "type": "Feature",
  "properties": {
    "iso:country":"IT",
    "sg:address":"Via Valsolda 15 20142 Milano",
    "sg:city":"Milano",
    "sg:classifiers":[
        {
            "category":"Shopping",
            "subcategory":"Computers & Home Electronics",
            "type":"Retail Goods"
        }
    ],
    "sg:phone":"+39 02 895901",
    "sg:postcode":"20142",
    "sg:province":"Milano",
    "sg:tags":[
        "telephone"
    ],
    "sg:website":"www.fitre.it",
    "wof:name":"Fitre Spa",
    "wof:placetype":"venue"
},
  "geometry": {"coordinates":[9.169755,45.442955],"type":"Point"}
}