{
  "type": "Feature",
  "properties": {
    "iso:country":"IT",
    "sg:address":"15, Via Colombo 16121 Genova",
    "sg:city":"Genova",
    "sg:classifiers":[
        {
            "category":"Communications",
            "subcategory":"Newspaper",
            "type":"Services"
        }
    ],
    "sg:phone":"+39 39010583357",
    "sg:postcode":"16121",
    "sg:province":"Genova",
    "sg:tags":[
        "advertising"
    ],
    "wof:name":"B. & G. Comunicazione S.r.l.",
    "wof:placetype":"venue"
},
  "geometry": {"coordinates":[8.914777,44.410175],"type":"Point"}
}