{
  "type": "Feature",
  "properties": {
    "iso:country":"IT",
    "sg:address":"98057 Milazzo",
    "sg:city":"Milazzo",
    "sg:orig_category":"Servizi E Lavori Per Edilizia E Lavori Pubblici. Servizi E Lavori Per Ecologia E Smaltimento Rifiuti",
    "sg:phone":"+39 090 928 6226",
    "sg:postcode":"98057",
    "sg:province":"Messina",
    "wof:name":"Milae Medical Di La Rosa F. & C. Snc",
    "wof:placetype":"venue"
},
  "geometry": {"coordinates":[15.237034,38.200718],"type":"Point"}
}