{
  "type": "Feature",
  "properties": {
    "iso:country":"IT",
    "sg:address":"56017 San Giuliano Terme",
    "sg:city":"San Giuliano Terme",
    "sg:orig_category":"Elettrodomestici - Riparazione E Vendita Al Dettaglio Di Accessori",
    "sg:phone":"+39 050 877151",
    "sg:postcode":"56017",
    "sg:province":"Pisa",
    "wof:name":"Ghignoli Di Ghignoli Piero & C. Sas",
    "wof:placetype":"venue"
},
  "geometry": {"coordinates":[10.405946,43.763622],"type":"Point"}
}