{
  "type": "Feature",
  "properties": {
    "iso:country":"IT",
    "sg:address":"03039 Sora",
    "sg:city":"Sora",
    "sg:orig_category":"Animali Domestici - Allevamento E Addestramento",
    "sg:phone":"+39 0776 822086",
    "sg:postcode":"03039",
    "sg:province":"Frosinone",
    "wof:name":"Esotica Di Sarra Fabio",
    "wof:placetype":"venue"
},
  "geometry": {"coordinates":[13.618526,41.718792],"type":"Point"}
}