{
  "type": "Feature",
  "properties": {
    "iso:country":"IT",
    "sg:address":"Km 22,300, V. Palombarese 00012 Guidonia Montecelio",
    "sg:city":"Guidonia",
    "sg:classifiers":[
        {
            "category":"Shopping",
            "subcategory":"Computers & Home Electronics",
            "type":"Retail Goods"
        }
    ],
    "sg:phone":"+39 0774 346967",
    "sg:postcode":"00012",
    "sg:province":"Roma",
    "sg:tags":[
        "electronic",
        "electrical",
        "equipment"
    ],
    "sg:website":"http://www.lampadarifratocchi.com",
    "wof:name":"G.f. Fabbrica Lampadari",
    "wof:placetype":"venue"
},
  "geometry": {"coordinates":[12.482325,41.895466],"type":"Point"}
}