{
  "type": "Feature",
  "properties": {
    "iso:country":"IT",
    "sg:address":"560, Via Del Trullo 00148 Roma",
    "sg:city":"Roma",
    "sg:classifiers":[
        {
            "category":"Professional",
            "subcategory":"Printing & Photocopies",
            "type":"Services"
        }
    ],
    "sg:phone":"+39 39066572966",
    "sg:postcode":"00148",
    "sg:province":"Roma",
    "wof:name":"Rotopress S.r.l.",
    "wof:placetype":"venue"
},
  "geometry": {"coordinates":[12.4365539551,41.8352928162],"type":"Point"}
}