{
  "type": "Feature",
  "properties": {
    "iso:country":"IT",
    "sg:address":"13866 Masserano",
    "sg:city":"Masserano",
    "sg:orig_category":"Macchine E Forniture Per Ecologia E Smaltimento Rifiuti",
    "sg:phone":"+39 015 99240",
    "sg:postcode":"13866",
    "sg:province":"Biella",
    "wof:name":"Servizi Tecnologie Ambientali Spa",
    "wof:placetype":"venue"
},
  "geometry": {"coordinates":[8.217814,45.59798],"type":"Point"}
}