{
  "type": "Feature",
  "properties": {
    "addr:full":"80017 Melito Di Napoli Melito di Napoli Napoli 80017",
    "addr:postcode":"80017;80017",
    "iso:country":"IT",
    "sg:address":"80017 Melito Di Napoli",
    "sg:city":"Melito di Napoli",
    "sg:orig_category":"Forniture Per Abbigliamento E Pelletterie",
    "sg:phone":"+39 081 702 0172",
    "sg:postcode":"80017",
    "sg:province":"Napoli",
    "wof:name":"Na.tex. Sas Di Napolitano Giuseppe",
    "wof:placetype":"venue"
},
  "geometry": {"coordinates":[14.2355957031,40.9068336487],"type":"Point"}
}