{
  "type": "Feature",
  "properties": {
    "iso:country":"IT",
    "sg:address":"70017 Putignano",
    "sg:city":"Putignano",
    "sg:orig_category":"Ospedali E Servizi Sanitari. Centri Di Estetica E Cosmesi E Servizi",
    "sg:phone":"+39 080 405 9207",
    "sg:postcode":"70017",
    "sg:province":"Bari",
    "wof:name":"Soave Alessandra",
    "wof:placetype":"venue"
},
  "geometry": {"coordinates":[17.121401,40.796101],"type":"Point"}
}