{
  "type": "Feature",
  "properties": {
    "addr:full":"35030 Galzignano Galzignano Padova 35030",
    "addr:postcode":"35030;35030",
    "iso:country":"IT",
    "sg:address":"35030 Galzignano",
    "sg:city":"Galzignano",
    "sg:orig_category":"Alberghi",
    "sg:phone":"+39 049 919 5555",
    "sg:postcode":"35030",
    "sg:province":"Padova",
    "sg:website":"http://www.galzignano.it",
    "wof:name":"Terme Di Galzignano Spa - Revital Resort Per Il Corpo E Lo Spirito",
    "wof:placetype":"venue"
},
  "geometry": {"coordinates":[11.782875,45.34021],"type":"Point"}
}