{
  "type": "Feature",
  "properties": {
    "addr:full":"10093 Collegno Collegno Torino 10093",
    "addr:postcode":"10093;10093",
    "iso:country":"IT",
    "sg:address":"10093 Collegno",
    "sg:city":"Collegno",
    "sg:orig_category":"Arredamenti E Mobili Professionali. Arredi Ed Attrezzature Per Uffici",
    "sg:phone":"+39 011 405 1481",
    "sg:postcode":"10093",
    "sg:province":"Torino",
    "wof:name":"Simag (s.r.l.)",
    "wof:placetype":"venue"
},
  "geometry": {"coordinates":[7.610179,45.074329],"type":"Point"}
}