{
  "type": "Feature",
  "properties": {
    "addr:full":"70032 Bitonto Bitonto Bari 70032",
    "addr:postcode":"70032;70032",
    "iso:country":"IT",
    "sg:address":"70032 Bitonto",
    "sg:city":"Bitonto",
    "sg:orig_category":"Abbigliamento Esterno, Maglierie E Pelliccerie. Calzature, Pelletterie E Pelli. Shopping",
    "sg:phone":"+39 080 371 7290",
    "sg:postcode":"70032",
    "sg:province":"Bari",
    "wof:name":"Labianca Carmela Boutique Sposa",
    "wof:placetype":"venue"
},
  "geometry": {"coordinates":[16.785139,41.081779],"type":"Point"}
}