{
  "type": "Feature",
  "properties": {
    "iso:country":"IT",
    "sg:address":"20017 Rho",
    "sg:city":"Rho",
    "sg:orig_category":"Materie Plastiche - Commercio",
    "sg:phone":"+39 02 9390 1538",
    "sg:postcode":"20017",
    "sg:province":"Milano",
    "wof:name":"Veglas Srl",
    "wof:placetype":"venue"
},
  "geometry": {"coordinates":[9.084438,45.525776],"type":"Point"}
}