{
  "type": "Feature",
  "properties": {
    "addr:full":"20131 Milano Milano Milano 20131",
    "addr:postcode":"20131;20131",
    "iso:country":"IT",
    "sg:address":"20131 Milano",
    "sg:city":"Milano",
    "sg:orig_category":"Cartotecnica E Servizi. Forniture Per Uffici",
    "sg:phone":"+39 02 284 1504",
    "sg:postcode":"20131",
    "sg:province":"Milano",
    "wof:name":"G.e.m.m.a. (s.n.c.)",
    "wof:placetype":"venue"
},
  "geometry": {"coordinates":[9.224836,45.491417],"type":"Point"}
}