{
  "type": "Feature",
  "properties": {
    "iso:country":"IT",
    "sg:address":"Via Tribolina 30 24064 Grumello Del Monte",
    "sg:city":"Grumello del Monte",
    "sg:classifiers":[
        {
            "category":"Shopping",
            "subcategory":"Jewelry",
            "type":"Retail Goods"
        }
    ],
    "sg:phone":"+39 035 832555",
    "sg:postcode":"24064",
    "sg:province":"Bergamo",
    "sg:tags":[
        "fashion",
        "jewellery"
    ],
    "sg:website":"www.ctpspa.it",
    "wof:name":"C.t.p. Spa",
    "wof:placetype":"venue"
},
  "geometry": {"coordinates":[9.8834285736,45.6285743713],"type":"Point"}
}