{
  "type": "Feature",
  "properties": {
    "iso:country":"IT",
    "sg:address":"00185 Roma",
    "sg:city":"Roma",
    "sg:orig_category":"Congressi E Conferenze - Organizzazione E Servizi",
    "sg:phone":"+39 06 4470 3796",
    "sg:postcode":"00185",
    "sg:province":"Roma",
    "sg:website":"http://www.ilcerimoniere.it",
    "wof:name":"Il Cerimoniere Srl",
    "wof:placetype":"venue"
},
  "geometry": {"coordinates":[12.504697,41.903393],"type":"Point"}
}