{
  "type": "Feature",
  "properties": {
    "iso:country":"IT",
    "sg:address":"1, Viale Dell' Industria 35023 Bagnoli Di Sopra",
    "sg:city":"Bagnoli di Sopra",
    "sg:classifiers":[
        {
            "category":"Professional",
            "subcategory":"Engineering",
            "type":"Services"
        }
    ],
    "sg:phone":"+39 049 953 5044",
    "sg:postcode":"35023",
    "sg:province":"Padova",
    "sg:tags":[
        "machine",
        "-",
        "mechanical"
    ],
    "wof:name":"A.p.v. (s.r.l.)",
    "wof:placetype":"venue"
},
  "geometry": {"coordinates":[11.889931,45.201099],"type":"Point"}
}