{
  "type": "Feature",
  "properties": {
    "iso:country":"IT",
    "sg:address":"20093 Cologno Monzese",
    "sg:city":"Cologno Monzese",
    "sg:orig_category":"Prodotti E Manufatti In Materie Plastiche. Forniture Per Edilizia E Lavori Pubblici. Forniture E Materiali Per Imballaggio E Confezionamento",
    "sg:phone":"+39 02 2539 1207",
    "sg:postcode":"20093",
    "sg:province":"Milano",
    "wof:name":"Adria Polistirolo Srl",
    "wof:placetype":"venue"
},
  "geometry": {"coordinates":[9.2661504745,45.5352210999],"type":"Point"}
}