{
  "type": "Feature",
  "properties": {
    "iso:country":"IT",
    "sg:address":"44043 Mirabello",
    "sg:city":"Mirabello",
    "sg:orig_category":"Tappezzerie In Stoffa, Plastica E Pelle",
    "sg:phone":"+39 0532 847460",
    "sg:postcode":"44043",
    "sg:province":"Ferrara",
    "wof:name":"Gr Tappezzeria Di Gulmini Rodolfo",
    "wof:placetype":"venue"
},
  "geometry": {"coordinates":[11.463463,44.827972],"type":"Point"}
}