{
  "type": "Feature",
  "properties": {
    "iso:country":"IT",
    "sg:address":"20090 Cesano Boscone",
    "sg:city":"Cesano Boscone",
    "sg:orig_category":"Impiantistica E Prodotti Tecnologici Per Edilizia. Forniture Industriali Per Prevenzione, Controllo E Sicurezza",
    "sg:phone":"+39 02 450 0833",
    "sg:postcode":"20090",
    "sg:province":"Milano",
    "wof:name":"Sigma Estintori Snc",
    "wof:placetype":"venue"
},
  "geometry": {"coordinates":[9.079421,45.441601],"type":"Point"}
}