{
  "type": "Feature",
  "properties": {
    "iso:country":"IT",
    "sg:address":"0/2, Viale Torino 10042 Nichelino",
    "sg:city":"Nichelino",
    "sg:classifiers":[
        {
            "category":"Professional",
            "subcategory":"Engineering",
            "type":"Services"
        }
    ],
    "sg:phone":"+39 011 358 2736",
    "sg:postcode":"10042",
    "sg:province":"Torino",
    "sg:tags":[
        "machine",
        "-",
        "mechanical"
    ],
    "wof:name":"F.a.s.e. (s.p.a.)",
    "wof:placetype":"venue"
},
  "geometry": {"coordinates":[7.609621,45.000233],"type":"Point"}
}