{
  "type": "Feature",
  "properties": {
    "addr:full":"27, Via Ospitaletto 25046 Cazzago San Martino Cazzago San Martino Brescia 25046",
    "addr:postcode":"25046;25046",
    "addr:street":"Via Ospitaletto",
    "iso:country":"IT",
    "sg:address":"27, Via Ospitaletto 25046 Cazzago San Martino",
    "sg:city":"Cazzago San Martino",
    "sg:classifiers":[
        {
            "category":"Manufacturing",
            "subcategory":"Metals",
            "type":"Manufacturing & Wholesale Goods"
        }
    ],
    "sg:phone":"+39 030 775 9928",
    "sg:postcode":"25046",
    "sg:province":"Brescia",
    "sg:tags":[
        "processing"
    ],
    "wof:name":"Zincature Industriali (s.r.l.)",
    "wof:placetype":"venue"
},
  "geometry": {"coordinates":[10.0700206757,45.5653076172],"type":"Point"}
}