{
  "type": "Feature",
  "properties": {
    "iso:country":"IT",
    "sg:address":"00197 Roma",
    "sg:city":"Roma",
    "sg:orig_category":"Arte Ed Artigianato Artistico. Scuole E Servizi Scolastici. Servizi Ausiliari Di Analisi, Controllo E Ricerca",
    "sg:phone":"+39 06 320 1596",
    "sg:postcode":"00197",
    "sg:province":"Roma",
    "wof:name":"Istituto Svedese Di Studi Classici A Roma",
    "wof:placetype":"venue"
},
  "geometry": {"coordinates":[12.478827,41.916813],"type":"Point"}
}