{
  "type": "Feature",
  "properties": {
    "iso:country":"IT",
    "sg:address":"91026 Mazara Del Vallo",
    "sg:city":"Mazara del Vallo",
    "sg:orig_category":"Servizi Ausiliari Per Il Trasporto",
    "sg:phone":"+39 0923 932828",
    "sg:postcode":"91026",
    "sg:province":"Trapani",
    "wof:name":"Campo Giuseppe & F.lli",
    "wof:placetype":"venue"
},
  "geometry": {"coordinates":[12.581088,37.654484],"type":"Point"}
}