{
  "type": "Feature",
  "properties": {
    "iso:country":"IT",
    "sg:address":"Via Iv Novembre 29 24038 Sant'omobono Imagna",
    "sg:classifiers":[
        {
            "category":"Manufacturing",
            "subcategory":"Wood Products",
            "type":"Manufacturing & Wholesale Goods"
        }
    ],
    "sg:phone":"+39 035 851176",
    "sg:postcode":"24038",
    "sg:province":"Bergamo",
    "sg:tags":[
        "cnc",
        "working"
    ],
    "wof:name":"Frm Di Frosio Ruggero & Mirco Snc",
    "wof:placetype":"venue"
},
  "geometry": {"coordinates":[9.669952,45.694904],"type":"Point"}
}