{
  "type": "Feature",
  "properties": {
    "iso:country":"IT",
    "sg:address":"21040 Origgio",
    "sg:city":"Origgio",
    "sg:orig_category":"Arredi Ed Attrezzature Per Uffici",
    "sg:phone":"+39 02 9673 4184",
    "sg:postcode":"21040",
    "sg:province":"Varese",
    "wof:name":"Tuttoespresso Spa",
    "wof:placetype":"venue"
},
  "geometry": {"coordinates":[9.026745,45.599529],"type":"Point"}
}