{
  "type": "Feature",
  "properties": {
    "addr:full":"16159 Genova Genova Genova 16159",
    "addr:postcode":"16159;16159",
    "iso:country":"IT",
    "sg:address":"16159 Genova",
    "sg:city":"Genova",
    "sg:orig_category":"Ospedali E Servizi Sanitari",
    "sg:phone":"+39 010 740 7083",
    "sg:postcode":"16159",
    "sg:province":"Genova",
    "wof:name":"Istituto Colombo Srl",
    "wof:placetype":"venue"
},
  "geometry": {"coordinates":[8.900854,44.440651],"type":"Point"}
}