{
  "type": "Feature",
  "properties": {
    "addr:full":"41058 Vignola Vignola Modena 41058",
    "addr:postcode":"41058;41058",
    "iso:country":"IT",
    "sg:address":"41058 Vignola",
    "sg:city":"Vignola",
    "sg:classifiers":[
        {
            "category":"Restaurant",
            "type":"Food & Drink"
        }
    ],
    "sg:phone":"+39 059 774610",
    "sg:postcode":"41058",
    "sg:province":"Modena",
    "sg:tags":[
        "equipment",
        "industry",
        "machinery"
    ],
    "sg:website":"http://www.macaut.it",
    "wof:name":"Mac Aut Impianti Srl",
    "wof:placetype":"venue"
},
  "geometry": {"coordinates":[11.0002985001,44.4959144592],"type":"Point"}
}