{
  "type": "Feature",
  "properties": {
    "iso:country":"IT",
    "sg:address":"38085 Pieve Di Modolena",
    "sg:orig_category":"Lavorazioni Meccaniche E Servizi. Riparazione Dei Mezzi Di Trasporto",
    "sg:phone":"+39 0522 303570",
    "sg:postcode":"38085",
    "sg:province":"Trento",
    "wof:name":"Autorettifica M.f. Di Morini Ermanno & C. Snc",
    "wof:placetype":"venue"
},
  "geometry": {"coordinates":[10.640933,45.942936],"type":"Point"}
}