{
  "type": "Feature",
  "properties": {
    "iso:country":"IT",
    "sg:address":"22, Via Monte Grappa 84018 Scafati",
    "sg:city":"Scafati",
    "sg:classifiers":[
        {
            "category":"Shopping",
            "subcategory":"Crafts & Fabrics",
            "type":"Retail Goods"
        }
    ],
    "sg:phone":"+39 081 863 1616",
    "sg:postcode":"84018",
    "sg:province":"Salerno",
    "wof:name":"Tessil Sud (s.p.a.)",
    "wof:placetype":"venue"
},
  "geometry": {"coordinates":[14.525177002,40.749786377],"type":"Point"}
}