{
  "type": "Feature",
  "properties": {
    "iso:country":"IT",
    "sg:address":"10048 Vinovo",
    "sg:city":"Vinovo",
    "sg:orig_category":"Gasolio, Kerosene E Nafta",
    "sg:phone":"+39 011 965 1443",
    "sg:postcode":"10048",
    "sg:province":"Torino",
    "wof:name":"Ferrero Chiaffredo",
    "wof:placetype":"venue"
},
  "geometry": {"coordinates":[7.623423,44.975182],"type":"Point"}
}