{
  "type": "Feature",
  "properties": {
    "iso:country":"IT",
    "sg:address":"26, Via Friuli 20135 Milano",
    "sg:city":"Milano",
    "sg:classifiers":[
        {
            "category":"Shopping",
            "subcategory":"Clothing, Apparel, & Fashions",
            "type":"Retail Goods"
        }
    ],
    "sg:phone":"+39 02 5410 1961",
    "sg:postcode":"20135",
    "sg:province":"Milano",
    "sg:tags":[
        "clothes"
    ],
    "wof:name":"Tre S.r.l.",
    "wof:placetype":"venue"
},
  "geometry": {"coordinates":[9.274355,45.523937],"type":"Point"}
}