{
  "type": "Feature",
  "properties": {
    "iso:country":"IT",
    "sg:address":"Via Delle Industrie, 90/92 30020 Marcon",
    "sg:city":"Marcon",
    "sg:classifiers":[
        {
            "category":"Home & Garden",
            "subcategory":"Home Furnishings",
            "type":"Retail Goods"
        }
    ],
    "sg:phone":"+39 041 595 1199",
    "sg:postcode":"30020",
    "sg:province":"Venezia",
    "sg:tags":[
        "decorative",
        "lighting",
        "system"
    ],
    "sg:website":"www.foscarini.com",
    "wof:name":"Foscarini Murano Srl",
    "wof:placetype":"venue"
},
  "geometry": {"coordinates":[12.291401,45.544109],"type":"Point"}
}