{
  "type": "Feature",
  "properties": {
    "addr:full":"25032 Chiari Chiari Brescia 25032",
    "addr:postcode":"25032;25032",
    "iso:country":"IT",
    "sg:address":"25032 Chiari",
    "sg:city":"Chiari",
    "sg:orig_category":"Forniture Per Agricoltura E Zootecnia. Prodotti Chimici Secondari",
    "sg:phone":"+39 030 710 0860",
    "sg:postcode":"25032",
    "sg:province":"Brescia",
    "wof:name":"Baglioni Elena",
    "wof:placetype":"venue"
},
  "geometry": {"coordinates":[9.8894739151,45.5422019958],"type":"Point"}
}