{
  "type": "Feature",
  "properties": {
    "iso:country":"IT",
    "sg:address":"8, Viale Lombardia 24050 Orio Al Serio",
    "sg:city":"Orio al Serio",
    "sg:classifiers":[
        {
            "category":"Food & Beverages",
            "subcategory":"Groceries & Convenience Stores",
            "type":"Retail Goods"
        }
    ],
    "sg:phone":"+39 39035532089",
    "sg:postcode":"24050",
    "sg:province":"Bergamo",
    "sg:tags":[
        "product",
        "related"
    ],
    "wof:name":"Dolber (s.p.a.)",
    "wof:placetype":"venue"
},
  "geometry": {"coordinates":[9.6887378693,45.6639022827],"type":"Point"}
}