{
  "type": "Feature",
  "properties": {
    "addr:full":"20093 Cologno Monzese Cologno Monzese Milano 20093",
    "addr:postcode":"20093;20093",
    "iso:country":"IT",
    "sg:address":"20093 Cologno Monzese",
    "sg:city":"Cologno Monzese",
    "sg:orig_category":"Utensili Meccanici E Materiali. Elettrotecnica Industriale, Prodotti E Apparecchiature",
    "sg:phone":"+39 02 253 2436",
    "sg:postcode":"20093",
    "sg:province":"Milano",
    "wof:name":"Rock - Flex",
    "wof:placetype":"venue"
},
  "geometry": {"coordinates":[9.264235,45.521358],"type":"Point"}
}