{
  "type": "Feature",
  "properties": {
    "iso:country":"IT",
    "sg:address":"36075 Montecchio Maggiore",
    "sg:city":"Montecchio Maggiore",
    "sg:orig_category":"Macchine Edili E Stradali - Produzione",
    "sg:phone":"+39 0444 491805",
    "sg:postcode":"36075",
    "sg:province":"Vicenza",
    "wof:name":"Gelai & Castegnaro Srl",
    "wof:placetype":"venue"
},
  "geometry": {"coordinates":[11.405453,45.513783],"type":"Point"}
}