{
  "type": "Feature",
  "properties": {
    "addr:full":"47016 Fiumana Fiumana Forl\u00ec-Cesena 47016",
    "addr:postcode":"47016;47016",
    "iso:country":"IT",
    "sg:address":"47016 Fiumana",
    "sg:city":"Fiumana",
    "sg:orig_category":"Zootecnia E Pesca, Allevamento Piccoli Animali. Servizi Per Lo Sport E Il Tempo Libero",
    "sg:phone":"+39 0543 940325",
    "sg:postcode":"47016",
    "sg:province":"Forl\u00ec-Cesena",
    "wof:name":"Maneggio Moffa Di Moffa Giovanni",
    "wof:placetype":"venue"
},
  "geometry": {"coordinates":[11.987379,44.138599],"type":"Point"}
}