{
  "type": "Feature",
  "properties": {
    "iso:country":"IT",
    "sg:address":"13900 Biella",
    "sg:city":"Biella",
    "sg:orig_category":"Cartotecnica E Servizi. Forniture Per Attivita' Commerciali Ed Artigianali",
    "sg:phone":"+39 015 27192",
    "sg:postcode":"13900",
    "sg:province":"Biella",
    "wof:name":"Leomar Di Croce Paola & C. (s.a.s.)",
    "wof:placetype":"venue"
},
  "geometry": {"coordinates":[8.048603,45.56097],"type":"Point"}
}