{
  "type": "Feature",
  "properties": {
    "iso:country":"IT",
    "sg:address":"12011 Borgo San Dalmazzo",
    "sg:city":"Borgo San Dalmazzo",
    "sg:orig_category":"Cancelli, Porte E Portoni Automatici E Telecomandati",
    "sg:phone":"+39 0171 262728",
    "sg:postcode":"12011",
    "sg:province":"Cuneo",
    "wof:name":"Lombardo Dei Cancelli Sas",
    "wof:placetype":"venue"
},
  "geometry": {"coordinates":[7.476005,44.329208],"type":"Point"}
}