{
  "type": "Feature",
  "properties": {
    "iso:country":"IT",
    "sg:address":"21040 Gornate Olona Fraz. Torba",
    "sg:orig_category":"Materiali Edili",
    "sg:phone":"+39 0331 820240",
    "sg:postcode":"21040",
    "sg:province":"Varese",
    "wof:name":"Fabio Premazzi Eredi Srl",
    "wof:placetype":"venue"
},
  "geometry": {"coordinates":[8.861111,45.7425],"type":"Point"}
}