{
  "type": "Feature",
  "properties": {
    "iso:country":"IT",
    "sg:address":"Via Roma 16; Auronzo Di Cadore; 32041",
    "sg:city":"Auronzo di Cadore",
    "sg:classifiers":[
        {
            "category":"Banks & Credit Unions",
            "subcategory":"Bank",
            "type":"Services"
        }
    ],
    "sg:phone":"+39 0435 400660",
    "sg:postcode":"32041",
    "sg:province":"Belluno",
    "wof:name":"Rolo Banca 1473 Spa",
    "wof:placetype":"venue"
},
  "geometry": {"coordinates":[12.444623,46.550339],"type":"Point"}
}