{
  "type": "Feature",
  "properties": {
    "addr:full":"35133 Padova Padova Padova 35133",
    "addr:postcode":"35133;35133",
    "iso:country":"IT",
    "sg:address":"35133 Padova",
    "sg:city":"Padova",
    "sg:orig_category":"Macchine, Impianti Ed Attrezzature Industria Chimica. Pompe",
    "sg:phone":"+39 049 701076",
    "sg:postcode":"35133",
    "sg:province":"Padova",
    "wof:name":"Emac S.a.s.",
    "wof:placetype":"venue"
},
  "geometry": {"coordinates":[11.440072,45.438366],"type":"Point"}
}