{
  "type": "Feature",
  "properties": {
    "addr:full":"70121 Bari Bari Bari 70121",
    "addr:postcode":"70121;70121",
    "iso:country":"IT",
    "sg:address":"70121 Bari",
    "sg:city":"Bari",
    "sg:orig_category":"Impianti, Attrezzature E Forniture Sanitarie Ed Ospedaliere",
    "sg:phone":"+39 080 523 7646",
    "sg:postcode":"70121",
    "sg:province":"Bari",
    "wof:name":"Medicamen Sas",
    "wof:placetype":"venue"
},
  "geometry": {"coordinates":[16.871469,41.122128],"type":"Point"}
}