{
  "type": "Feature",
  "properties": {
    "iso:country":"IT",
    "sg:address":"12036 Revello",
    "sg:city":"Revello",
    "sg:orig_category":"Servizi Di Magazzinaggio E Movimentazione",
    "sg:phone":"+39 0175 257632",
    "sg:postcode":"12036",
    "sg:province":"Cuneo",
    "wof:name":"Comecar S.r.l.",
    "wof:placetype":"venue"
},
  "geometry": {"coordinates":[7.422388,44.733845],"type":"Point"}
}