{
  "type": "Feature",
  "properties": {
    "addr:full":"45030 Calto Calto Rovigo 45030",
    "addr:postcode":"45030;45030",
    "iso:country":"IT",
    "sg:address":"45030 Calto",
    "sg:city":"Calto",
    "sg:orig_category":"Manufacturers: Prefabbricati. Impianti E Attrezzature Per Lo Sport E Il Tempo Libero",
    "sg:phone":"+39 0425 804020",
    "sg:postcode":"45030",
    "sg:province":"Rovigo",
    "wof:name":"Fc Fabbri Park (s.r.l.)",
    "wof:placetype":"venue"
},
  "geometry": {"coordinates":[11.75433,44.948196],"type":"Point"}
}