{
  "type": "Feature",
  "properties": {
    "iso:country":"IT",
    "sg:address":"Via Provinciale 36 24040 Lallio",
    "sg:city":"Lallio",
    "sg:classifiers":[
        {
            "category":"Shopping",
            "subcategory":"Clothing, Apparel, & Fashions",
            "type":"Retail Goods"
        }
    ],
    "sg:phone":"+39 035 209111",
    "sg:postcode":"24040",
    "sg:province":"Bergamo",
    "sg:tags":[
        "clothing",
        "fabric"
    ],
    "sg:website":"www.radicitessuti.it",
    "wof:name":"Radici Tessuti Spa",
    "wof:placetype":"venue"
},
  "geometry": {"coordinates":[9.614531,45.643604],"type":"Point"}
}