{
  "type": "Feature",
  "properties": {
    "addr:full":"62, Via Cumiana 10141 Torino Torino Torino 10141",
    "addr:postcode":"10141;10141",
    "addr:street":"Via Cumiana",
    "iso:country":"IT",
    "sg:address":"62, Via Cumiana 10141 Torino",
    "sg:city":"Torino",
    "sg:classifiers":[
        {
            "category":"Professional",
            "subcategory":"Printing & Photocopies",
            "type":"Services"
        }
    ],
    "sg:phone":"+39 011 385 4337",
    "sg:postcode":"10141",
    "sg:province":"Torino",
    "wof:name":"Litho-nova S.r.l.",
    "wof:placetype":"venue"
},
  "geometry": {"coordinates":[7.5860710144,45.0490951538],"type":"Point"}
}