{
  "type": "Feature",
  "properties": {
    "iso:country":"IT",
    "sg:address":"27, V. Recanati 80046 S. Giorgio A Cremano",
    "sg:classifiers":[
        {
            "category":"Shopping",
            "subcategory":"Clothing, Apparel, & Fashions",
            "type":"Retail Goods"
        }
    ],
    "sg:phone":"+39 39081482279",
    "sg:postcode":"80046",
    "sg:province":"Napoli",
    "sg:tags":[
        "clothes"
    ],
    "sg:website":"http://www.finamore.it:ws_end: :mark:ws:http://www.paginegialle.it/finamore",
    "wof:name":"Camicie Finamore Dal 1925 Napoli",
    "wof:placetype":"venue"
},
  "geometry": {"coordinates":[14.336607,40.832829],"type":"Point"}
}