{
  "type": "Feature",
  "properties": {
    "addr:full":"12060 Grinzane Cavour Grinzane Cavour Cuneo 12060",
    "addr:housenumber":"12060",
    "addr:postcode":"12060",
    "addr:street":"Grinzane Cavour",
    "iso:country":"IT",
    "sg:address":"12060 Grinzane Cavour",
    "sg:city":"Grinzane Cavour",
    "sg:orig_category":"Prodotti Di Base E Forniture Per Industria Alimentare E Bevande. Vetro: Prodotti E Lavorazioni. Articoli Per Imballaggio E Confezionamento",
    "sg:phone":"+39 0173 262262",
    "sg:postcode":"12060",
    "sg:province":"Cuneo",
    "wof:name":"Vetreria Veglio (s.a.s.)",
    "wof:placetype":"venue"
},
  "geometry": {"coordinates":[7.9817271233,44.6566314697],"type":"Point"}
}