{
  "type": "Feature",
  "properties": {
    "iso:country":"IT",
    "sg:address":"S.da Dordone 41 43040 Felegara",
    "sg:city":"Felegara",
    "sg:classifiers":[
        {
            "category":"Structure",
            "subcategory":"Warehouse",
            "type":"Public Place"
        }
    ],
    "sg:phone":"+39 0525 431660",
    "sg:postcode":"43040",
    "sg:province":"Parma",
    "sg:tags":[
        "prefabricated"
    ],
    "sg:website":"www.newhouse.it",
    "wof:name":"New House Spa",
    "wof:placetype":"venue"
},
  "geometry": {"coordinates":[10.3295478821,44.8078651428],"type":"Point"}
}