{
  "type": "Feature",
  "properties": {
    "iso:country":"IT",
    "sg:address":"Via Rossa Guido 45 51037 Montale",
    "sg:city":"Montale",
    "sg:classifiers":[
        {
            "category":"Manufacturing",
            "subcategory":"Textiles",
            "type":"Manufacturing & Wholesale Goods"
        }
    ],
    "sg:phone":"+39 0573 55499",
    "sg:postcode":"51037",
    "sg:province":"Pistoia",
    "sg:tags":[
        "knitted"
    ],
    "wof:name":"Aico Srl",
    "wof:placetype":"venue"
},
  "geometry": {"coordinates":[11.018413,43.911659],"type":"Point"}
}