{
  "type": "Feature",
  "properties": {
    "addr:full":"31030 Altivole Altivole Treviso 31030",
    "addr:postcode":"31030;31030",
    "iso:country":"IT",
    "sg:address":"31030 Altivole",
    "sg:city":"Altivole",
    "sg:orig_category":"Forniture Ospedaliere",
    "sg:phone":"+39 0423 940050",
    "sg:postcode":"31030",
    "sg:province":"Treviso",
    "wof:name":"Deltasan Di Formentin Claudio",
    "wof:placetype":"venue"
},
  "geometry": {"coordinates":[11.9104042053,45.7633209229],"type":"Point"}
}