{
  "type": "Feature",
  "properties": {
    "iso:country":"IT",
    "sg:address":"59100 Prato",
    "sg:city":"Prato",
    "sg:orig_category":"Arredamenti - Vendita Al Dettaglio",
    "sg:phone":"+39 0574 692229",
    "sg:postcode":"59100",
    "sg:province":"Prato",
    "wof:name":"Falegnameria Chianca E Imbrenda",
    "wof:placetype":"venue"
},
  "geometry": {"coordinates":[11.086455,43.898243],"type":"Point"}
}