{
  "type": "Feature",
  "properties": {
    "addr:full":"37014 Castelnuovo Del Garda Castelnuovo del Garda Verona 37014",
    "addr:postcode":"37014;37014",
    "iso:country":"IT",
    "sg:address":"37014 Castelnuovo Del Garda",
    "sg:city":"Castelnuovo del Garda",
    "sg:orig_category":"Cartotecnica E Servizi. Forniture Per Attivita' Commerciali Ed Artigianali",
    "sg:phone":"+39 045 645 0478",
    "sg:postcode":"37014",
    "sg:province":"Verona",
    "wof:name":"Cacca By Marco Turri",
    "wof:placetype":"venue"
},
  "geometry": {"coordinates":[10.761494,45.438393],"type":"Point"}
}