{
  "type": "Feature",
  "properties": {
    "addr:full":"29010 Cadeo Cadeo Piacenza 29010",
    "addr:postcode":"29010;29010",
    "iso:country":"IT",
    "sg:address":"29010 Cadeo",
    "sg:city":"Cadeo",
    "sg:orig_category":"Giocattoli E Giochi - Produzione E Ingrosso",
    "sg:phone":"+39 0523 509947",
    "sg:postcode":"29010",
    "sg:province":"Piacenza",
    "wof:name":"Clienti Giancarlo (miniplast)",
    "wof:placetype":"venue"
},
  "geometry": {"coordinates":[9.777415,45.005993],"type":"Point"}
}