{
  "type": "Feature",
  "properties": {
    "iso:country":"IT",
    "sg:address":"C Da Ciavolo 156; Ciavolo; 91025",
    "sg:city":"Ciavolo",
    "sg:classifiers":[
        {
            "category":"Banks & Credit Unions",
            "subcategory":"Bank",
            "type":"Services"
        }
    ],
    "sg:phone":"+39 0923 984533",
    "sg:postcode":"91025",
    "sg:province":"Trapani",
    "wof:name":"Credito Emiliano Spa",
    "wof:placetype":"venue"
},
  "geometry": {"coordinates":[12.53893,37.777779],"type":"Point"}
}