{
  "type": "Feature",
  "properties": {
    "addr:full":"00173 Roma Roma Roma 00173",
    "addr:postcode":"00173;00173",
    "iso:country":"IT",
    "sg:address":"00173 Roma",
    "sg:city":"Roma",
    "sg:orig_category":"Servizi E Lavori Industria Chimica. Riparazione Dei Mezzi Di Trasporto",
    "sg:phone":"+39 06 723 0379",
    "sg:postcode":"00173",
    "sg:province":"Roma",
    "wof:name":"Trinca Vittorio",
    "wof:placetype":"venue"
},
  "geometry": {"coordinates":[12.599027,41.83794],"type":"Point"}
}