{
  "type": "Feature",
  "properties": {
    "iso:country":"IT",
    "sg:address":"80121 Napoli",
    "sg:city":"Napoli",
    "sg:orig_category":"Articoli Da Regalo. Arte Ed Artigianato Artistico. Shopping. Regalistica Aziendale",
    "sg:phone":"+39 081 403413",
    "sg:postcode":"80121",
    "sg:province":"Napoli",
    "wof:name":"Buonocore Mario",
    "wof:placetype":"venue"
},
  "geometry": {"coordinates":[14.234624,40.834465],"type":"Point"}
}