{
  "type": "Feature",
  "properties": {
    "iso:country":"IT",
    "sg:address":"47841 Cattolica",
    "sg:city":"Cattolica",
    "sg:orig_category":"Gioielleria, Oreficeria E Argenteria. Shopping",
    "sg:phone":"+39 0541 954916",
    "sg:postcode":"47841",
    "sg:province":"Rimini",
    "wof:name":"Apogeo Pietre",
    "wof:placetype":"venue"
},
  "geometry": {"coordinates":[12.459558,44.087669],"type":"Point"}
}