{
  "type": "Feature",
  "properties": {
    "addr:full":"40121 Bologna Bologna Bologna 40121",
    "addr:postcode":"40121;40121",
    "iso:country":"IT",
    "sg:address":"40121 Bologna",
    "sg:city":"Bologna",
    "sg:orig_category":"Trasporti E Spedizioni Merci",
    "sg:phone":"+39 051 255610",
    "sg:postcode":"40121",
    "sg:province":"Bologna",
    "sg:website":"http://www.cfpbo.it",
    "wof:name":"Cooperativa Facchini Portabagagli Srl",
    "wof:placetype":"venue"
},
  "geometry": {"coordinates":[11.341376,44.505623],"type":"Point"}
}