{
  "type": "Feature",
  "properties": {
    "iso:country":"IT",
    "sg:address":"12038 Savigliano",
    "sg:city":"Savigliano",
    "sg:orig_category":"Forniture Alle Strutture Ricettive. Forniture Per Attivita' Commerciali Ed Artigianali",
    "sg:phone":"+39 0172 714111",
    "sg:postcode":"12038",
    "sg:province":"Cuneo",
    "sg:website":"http://www.origlia.it",
    "wof:name":"Origlia Spa",
    "wof:placetype":"venue"
},
  "geometry": {"coordinates":[7.6588516235,44.6391143799],"type":"Point"}
}