{
  "type": "Feature",
  "properties": {
    "addr:full":"45030 Occhiobello Occhiobello Rovigo 45030",
    "addr:postcode":"45030;45030",
    "iso:country":"IT",
    "sg:address":"45030 Occhiobello",
    "sg:city":"Occhiobello",
    "sg:orig_category":"Acquari Ornamentali Ed Accessori",
    "sg:phone":"+39 0425 756158",
    "sg:postcode":"45030",
    "sg:province":"Rovigo",
    "wof:name":"Chimica Polesana Srl",
    "wof:placetype":"venue"
},
  "geometry": {"coordinates":[11.581259,44.921741],"type":"Point"}
}