{
  "type": "Feature",
  "properties": {
    "iso:country":"IT",
    "sg:address":"Via Dei Greci 144/e 84135 Salerno",
    "sg:city":"Salerno",
    "sg:classifiers":[
        {
            "category":"Transit Center",
            "subcategory":"Freight",
            "type":"Transportation"
        }
    ],
    "sg:phone":"+39 089 271144",
    "sg:postcode":"84135",
    "sg:province":"Salerno",
    "sg:tags":[
        "ready",
        "castings",
        "installation"
    ],
    "wof:name":"Fonderie Di Foggia S.r.l.",
    "wof:placetype":"venue"
},
  "geometry": {"coordinates":[14.765912,40.677956],"type":"Point"}
}