{
  "type": "Feature",
  "properties": {
    "iso:country":"IT",
    "sg:address":"27100 Pavia",
    "sg:city":"Pavia",
    "sg:classifiers":[
        {
            "category":"Health Services",
            "subcategory":"Health Practitioner",
            "type":"Services"
        }
    ],
    "sg:phone":"+39 0382 302535",
    "sg:postcode":"27100",
    "sg:province":"Pavia",
    "sg:tags":[
        "medici"
    ],
    "wof:name":"Mosca Marisa",
    "wof:placetype":"venue"
},
  "geometry": {"coordinates":[9.1454238892,45.1844100952],"type":"Point"}
}