{
  "type": "Feature",
  "properties": {
    "iso:country":"IT",
    "sg:address":"Via Pergolesi 24; Cagliari; 09128",
    "sg:city":"Cagliari",
    "sg:classifiers":[
        {
            "category":"Banks & Credit Unions",
            "subcategory":"Bank",
            "type":"Services"
        }
    ],
    "sg:phone":"+39 070 400138",
    "sg:postcode":"09128",
    "sg:province":"Cagliari",
    "wof:name":"Istituto Bancario, San Paolo Di Torino Spa",
    "wof:placetype":"venue"
},
  "geometry": {"coordinates":[9.128219,39.222244],"type":"Point"}
}