{
  "type": "Feature",
  "properties": {
    "iso:country":"IT",
    "sg:address":"15, V. Delle Mele 47023 Cesena",
    "sg:city":"Cesena",
    "sg:orig_category":"Miscellaneous Products",
    "sg:phone":"+39 0547 416811",
    "sg:postcode":"47023",
    "sg:province":"Forl\u00ec-Cesena",
    "sg:website":"http://www.airmachine.it",
    "wof:name":"Airmachine Srl",
    "wof:placetype":"venue"
},
  "geometry": {"coordinates":[11.9804611206,43.9947662354],"type":"Point"}
}