{
  "type": "Feature",
  "properties": {
    "iso:country":"IT",
    "sg:address":"80139 Napoli",
    "sg:city":"Napoli",
    "sg:orig_category":"Banche E Servizi Finanziari",
    "sg:phone":"+39 081 445517",
    "sg:postcode":"80139",
    "sg:province":"Napoli",
    "wof:name":"Pio Monte Della Misericordia",
    "wof:placetype":"venue"
},
  "geometry": {"coordinates":[14.26041,40.851997],"type":"Point"}
}