{
  "type": "Feature",
  "properties": {
    "addr:full":"Via Anselmo Panfi 17 50025 Montespertoli Montespertoli Firenze 50025",
    "addr:housenumber":"17",
    "addr:postcode":"50025;50025",
    "addr:street":"Via Anselmo Panfi",
    "iso:country":"IT",
    "sg:address":"Via Anselmo Panfi 17 50025 Montespertoli",
    "sg:city":"Montespertoli",
    "sg:classifiers":[
        {
            "category":"Social Services",
            "subcategory":"Job Training",
            "type":"Services"
        }
    ],
    "sg:phone":"+39 0571 671907",
    "sg:postcode":"50025",
    "sg:province":"Firenze",
    "sg:tags":[
        "pottery"
    ],
    "wof:name":"Ceramiche Il Pino Srl",
    "wof:placetype":"venue"
},
  "geometry": {"coordinates":[11.0591068268,43.6848564148],"type":"Point"}
}