{
  "type": "Feature",
  "properties": {
    "iso:country":"IT",
    "sg:address":"91100 Trapani",
    "sg:city":"Trapani",
    "sg:orig_category":"Aspirapolvere E Lucidatrici Uso Domestico",
    "sg:phone":"+39 0923 533920",
    "sg:postcode":"91100",
    "sg:province":"Trapani",
    "wof:name":"Castiglione Francesco",
    "wof:placetype":"venue"
},
  "geometry": {"coordinates":[12.560025,38.007652],"type":"Point"}
}