{
  "type": "Feature",
  "properties": {
    "addr:full":"75012 Bernalda Bernalda Matera 75012",
    "addr:postcode":"75012;75012",
    "iso:country":"IT",
    "sg:address":"75012 Bernalda",
    "sg:city":"Bernalda",
    "sg:orig_category":"Abbigliamento Esterno, Maglierie E Pelliccerie",
    "sg:phone":"+39 0835 542790",
    "sg:postcode":"75012",
    "sg:province":"Matera",
    "wof:name":"Cointa Trading",
    "wof:placetype":"venue"
},
  "geometry": {"coordinates":[16.75885,40.39986],"type":"Point"}
}