{
  "type": "Feature",
  "properties": {
    "iso:country":"IT",
    "sg:address":"50058 Signa",
    "sg:city":"Signa",
    "sg:orig_category":"Accessori Moda D'abbigliamento. Forniture Per Abbigliamento E Pelletterie. Shopping",
    "sg:phone":"+39 055 876067",
    "sg:postcode":"50058",
    "sg:province":"Firenze",
    "wof:name":"Ricamificio - Bitossi Di Bitossi Antonella Antonella",
    "wof:placetype":"venue"
},
  "geometry": {"coordinates":[11.082252,43.783676],"type":"Point"}
}