{
  "type": "Feature",
  "properties": {
    "iso:country":"IT",
    "sg:address":"; Piovega; 33013",
    "sg:classifiers":[
        {
            "category":"Banks & Credit Unions",
            "subcategory":"Bank",
            "type":"Services"
        }
    ],
    "sg:phone":"+39 0432 981253",
    "sg:postcode":"33013",
    "sg:province":"Udine",
    "wof:name":"Banca Popolare Di Gemona",
    "wof:placetype":"venue"
},
  "geometry": {"coordinates":[13.133679,46.272507],"type":"Point"}
}