{
  "type": "Feature",
  "properties": {
    "iso:country":"IT",
    "sg:address":"40057 Granarolo Dell'emilia",
    "sg:orig_category":"Motori Ed Organi Di Trasmissione",
    "sg:phone":"+39 051 766531",
    "sg:postcode":"40057",
    "sg:province":"Bologna",
    "wof:name":"Casa Della Catena Di Malaguti G. E Iorio E. S.n.c.",
    "wof:placetype":"venue"
},
  "geometry": {"coordinates":[11.3953361511,44.5473899841],"type":"Point"}
}