{
  "type": "Feature",
  "properties": {
    "iso:country":"IT",
    "sg:address":"33, Via Case Sparse 27040 Verrua Po",
    "sg:city":"Verrua Po",
    "sg:classifiers":[
        {
            "category":"Manufacturing",
            "subcategory":"Metals",
            "type":"Manufacturing & Wholesale Goods"
        }
    ],
    "sg:phone":"+39 39038596136",
    "sg:postcode":"27040",
    "sg:province":"Pavia",
    "sg:tags":[
        "metallurgy",
        "metalworking"
    ],
    "wof:name":"F.i.a.r. (s.p.a.)",
    "wof:placetype":"venue"
},
  "geometry": {"coordinates":[9.1718044281,45.1146965027],"type":"Point"}
}