{
  "type": "Feature",
  "properties": {
    "iso:country":"IT",
    "sg:address":"34133 Trieste",
    "sg:city":"Trieste",
    "sg:orig_category":"Biblioteche Pubbliche E Private",
    "sg:phone":"+39 040 635764",
    "sg:postcode":"34133",
    "sg:province":"Trieste",
    "wof:name":"Centro Culturale Italo - Tedesco Di Trieste",
    "wof:placetype":"venue"
},
  "geometry": {"coordinates":[13.776536,45.653091],"type":"Point"}
}