{
  "type": "Feature",
  "properties": {
    "addr:full":"15057 Tortona Tortona Alessandria 15057",
    "addr:postcode":"15057;15057",
    "iso:country":"IT",
    "sg:address":"15057 Tortona",
    "sg:city":"Tortona",
    "sg:orig_category":"Imprese Di Costruzioni Civili Ed Industriali. Servizi Ausiliari Di Sorveglianza, Manutenzione E Pulizia",
    "sg:phone":"+39 0131 870270",
    "sg:postcode":"15057",
    "sg:province":"Alessandria",
    "sg:website":"http://www.minorservices.it",
    "wof:name":"Minor Services Di Simonetta Silvano",
    "wof:placetype":"venue"
},
  "geometry": {"coordinates":[8.863519,44.89402],"type":"Point"}
}