{
  "type": "Feature",
  "properties": {
    "iso:country":"IT",
    "sg:address":"37029 S.pietro In Cariano",
    "sg:city":"Negarine",
    "sg:orig_category":"Editoria",
    "sg:phone":"+39 045 772 5543",
    "sg:postcode":"37029",
    "sg:province":"Verona",
    "sg:website":"http://www.gabriellieditori.it",
    "wof:name":"Il Segno Dei Gabrielli Editori",
    "wof:placetype":"venue"
},
  "geometry": {"coordinates":[10.906543,45.498611],"type":"Point"}
}