{
  "type": "Feature",
  "properties": {
    "addr:full":"21100 Varese Varese Varese 21100",
    "addr:postcode":"21100;21100",
    "iso:country":"IT",
    "sg:address":"21100 Varese",
    "sg:city":"Varese",
    "sg:orig_category":"Bevande, Vini E Liquori. Ristorazione E Locali Pubblici Affini. Ristoranti Ed Esercizi Affini. Servizi Ausiliari Di Ristorazione E Di Intrattenimento",
    "sg:phone":"+39 0332 831814",
    "sg:postcode":"21100",
    "sg:province":"Varese",
    "sg:website":"http://www.inpreparazione",
    "wof:name":"Harley Music Caf\u00c8",
    "wof:placetype":"venue"
},
  "geometry": {"coordinates":[8.7894067764,45.7645683289],"type":"Point"}
}