{
  "type": "Feature",
  "properties": {
    "iso:country":"IT",
    "sg:address":"21013 Gallarate",
    "sg:city":"Gallarate",
    "sg:orig_category":"Valigerie Ed Articoli Da Viaggio - Produzione E Ingrosso",
    "sg:phone":"+39 0331 792473",
    "sg:postcode":"21013",
    "sg:province":"Varese",
    "sg:website":"http://www.twssrl.net",
    "wof:name":"Tws Srl",
    "wof:placetype":"venue"
},
  "geometry": {"coordinates":[8.797383,45.674732],"type":"Point"}
}