{
  "type": "Feature",
  "properties": {
    "iso:country":"IT",
    "sg:address":"00136 Roma",
    "sg:city":"Roma",
    "sg:orig_category":"Agenzie Di Spettacolo E Di Animazione",
    "sg:phone":"+39 339 228 0061",
    "sg:postcode":"00136",
    "sg:province":"Roma",
    "sg:website":"http://www.bollicineonline.org",
    "wof:name":"Bollicine",
    "wof:placetype":"venue"
},
  "geometry": {"coordinates":[12.449008,41.913357],"type":"Point"}
}