{
  "type": "Feature",
  "properties": {
    "iso:country":"IT",
    "sg:address":"40013 Castel Maggiore",
    "sg:city":"Castel Maggiore",
    "sg:orig_category":"Impiantistica E Prodotti Tecnologici Per Edilizia. Elettronica Professionale E Di Consumo. Accessori Dei Mezzi Di Trasporto. Forniture Industriali Per Prevenzione, Controllo E Sicurezza",
    "sg:phone":"+39 051 712295",
    "sg:postcode":"40013",
    "sg:province":"Bologna",
    "sg:website":"http://www.alinet.it/bm",
    "wof:name":"B.m. Elettronica Srl",
    "wof:placetype":"venue"
},
  "geometry": {"coordinates":[11.34029,44.575275],"type":"Point"}
}