{
  "type": "Feature",
  "properties": {
    "addr:full":"Via Ciro Menotti, 90; Modena; 41100 Modena Modena 41100",
    "addr:housenumber":"90",
    "addr:postcode":"41100;41100",
    "addr:street":"Via Ciro Menotti",
    "iso:country":"IT",
    "sg:address":"Via Ciro Menotti, 90; Modena; 41100",
    "sg:city":"Modena",
    "sg:classifiers":[
        {
            "category":"Banks & Credit Unions",
            "subcategory":"Bank",
            "type":"Services"
        }
    ],
    "sg:phone":"+39 059 220928",
    "sg:postcode":"41100",
    "sg:province":"Modena",
    "wof:name":"Cariplo",
    "wof:placetype":"venue"
},
  "geometry": {"coordinates":[10.935433,44.645119],"type":"Point"}
}