{
  "type": "Feature",
  "properties": {
    "iso:country":"IT",
    "sg:address":"Sda Provinciale Colligiana 27 53035 Monteriggioni",
    "sg:city":"Monteriggioni",
    "sg:classifiers":[
        {
            "category":"Restaurant",
            "type":"Food & Drink"
        }
    ],
    "sg:phone":"+39 0577 306018",
    "sg:postcode":"53035",
    "sg:province":"Siena",
    "sg:tags":[
        "pasta"
    ],
    "wof:name":"A.p.s Srl",
    "wof:placetype":"venue"
},
  "geometry": {"coordinates":[11.3305139542,43.3186607361],"type":"Point"}
}