{
  "type": "Feature",
  "properties": {
    "iso:country":"IT",
    "sg:address":"Via Pandino 2; Crema; 26010",
    "sg:classifiers":[
        {
            "category":"Banks & Credit Unions",
            "subcategory":"Bank",
            "type":"Services"
        }
    ],
    "sg:phone":"+39 0373 230286",
    "sg:postcode":"26010",
    "sg:province":"Cremona",
    "wof:name":"Istituto Bancario, San Paolo Di Torino Spa",
    "wof:placetype":"venue"
},
  "geometry": {"coordinates":[9.651738,45.35606],"type":"Point"}
}