{
  "type": "Feature",
  "properties": {
    "iso:country":"IT",
    "sg:address":"Corso Trieste 95, 85050 Satriano Di Lucania, Pz",
    "sg:city":"Satriano di Lucania",
    "sg:classifiers":[
        {
            "category":"Banks & Credit Unions",
            "subcategory":"Bank",
            "type":"Services"
        }
    ],
    "sg:postcode":"85050",
    "sg:province":"Potenza",
    "wof:name":"Banca Di Credito Cooperativo Della Valle Del Melandro Scrl",
    "wof:placetype":"venue"
},
  "geometry": {"coordinates":[15.640251,40.54393],"type":"Point"}
}