{
  "type": "Feature",
  "properties": {
    "iso:country":"IT",
    "sg:address":"Via Moro Aldo 46019 Viadana",
    "sg:city":"Viadana",
    "sg:orig_category":"Miscellaneous Products",
    "sg:phone":"+39 0375 790200",
    "sg:postcode":"46019",
    "sg:province":"Mantova",
    "wof:name":"Rosa Giuseppe & Figli (s.n.c.)",
    "wof:placetype":"venue"
},
  "geometry": {"coordinates":[10.7976980209,45.1603660583],"type":"Point"}
}