{
  "type": "Feature",
  "properties": {
    "iso:country":"IT",
    "sg:address":"Via Bisone 21 24034 Cisano Bergamasco",
    "sg:city":"Cisano Bergamasco",
    "sg:classifiers":[
        {
            "category":"Metro Station",
            "type":"Transportation"
        }
    ],
    "sg:phone":"+39 035 782342",
    "sg:postcode":"24034",
    "sg:province":"Bergamo",
    "sg:tags":[
        "tube",
        "nipple"
    ],
    "sg:website":"www.oteraccordi.it",
    "wof:name":"Oteraccordi Spa",
    "wof:placetype":"venue"
},
  "geometry": {"coordinates":[9.452351,45.75914],"type":"Point"}
}