{
  "type": "Feature",
  "properties": {
    "iso:country":"IT",
    "sg:address":"80049 Somma Vesuviana",
    "sg:city":"Somma Vesuviana",
    "sg:classifiers":[
        {
            "category":"Shopping",
            "subcategory":"Stationery & Office Supplies",
            "type":"Retail Goods"
        }
    ],
    "sg:phone":"+39 081 899 5511",
    "sg:postcode":"80049",
    "sg:province":"Napoli",
    "sg:tags":[
        "information",
        "product",
        "technology",
        "supplies"
    ],
    "sg:website":"http://www.moremax.it",
    "wof:name":"Moremax Sas Di Diaco Alberto & C.",
    "wof:placetype":"venue"
},
  "geometry": {"coordinates":[14.461899,40.869476],"type":"Point"}
}