{
  "type": "Feature",
  "properties": {
    "addr:full":"10023 Chieri Chieri Torino 10023",
    "addr:postcode":"10023;10023",
    "iso:country":"IT",
    "sg:address":"10023 Chieri",
    "sg:city":"Chieri",
    "sg:orig_category":"Campeggio, Tende, Attrezzature Ed Articoli - Vendita Al Dettaglio",
    "sg:phone":"+39 011 947 1812",
    "sg:postcode":"10023",
    "sg:province":"Torino",
    "wof:name":"Cavaliere Antonio & C. Snc",
    "wof:placetype":"venue"
},
  "geometry": {"coordinates":[7.862912,44.992847],"type":"Point"}
}