{
  "type": "Feature",
  "properties": {
    "iso:country":"IT",
    "sg:address":"48010 Fusignano",
    "sg:city":"Fusignano",
    "sg:orig_category":"Pompe",
    "sg:phone":"+39 0545 58308",
    "sg:postcode":"48010",
    "sg:province":"Ravenna",
    "wof:name":"A.r. Sas Di Antoniello Annunziata E C.",
    "wof:placetype":"venue"
},
  "geometry": {"coordinates":[11.9767866135,44.4823112488],"type":"Point"}
}