{
  "type": "Feature",
  "properties": {
    "iso:country":"IT",
    "sg:address":"00179 Roma",
    "sg:city":"Roma",
    "sg:orig_category":"Legno E Semilavorati",
    "sg:phone":"+39 06 784 7025",
    "sg:postcode":"00179",
    "sg:province":"Roma",
    "wof:name":"Supermercato Del Legno (s.r.l.)",
    "wof:placetype":"venue"
},
  "geometry": {"coordinates":[12.511471,41.874435],"type":"Point"}
}