{
  "type": "Feature",
  "properties": {
    "iso:country":"IT",
    "sg:address":"13, Via Pellico Silvio 59013 Montemurlo",
    "sg:city":"Montemurlo",
    "sg:classifiers":[
        {
            "category":"Shopping",
            "subcategory":"Crafts & Fabrics",
            "type":"Retail Goods"
        }
    ],
    "sg:phone":"+39 0574 791151",
    "sg:postcode":"59013",
    "sg:province":"Prato",
    "wof:name":"Comex (s.r.l.)",
    "wof:placetype":"venue"
},
  "geometry": {"coordinates":[11.0275745392,43.9077186584],"type":"Point"}
}