{
  "type": "Feature",
  "properties": {
    "addr:full":"Via Dell' Artigianato 10 35020 Due Carrare Due Carrare Padova 35020",
    "addr:housenumber":"10",
    "addr:postcode":"35020;35020",
    "addr:street":"Via Dell ' Artigianato",
    "iso:country":"IT",
    "sg:address":"Via Dell' Artigianato 10 35020 Due Carrare",
    "sg:city":"Due Carrare",
    "sg:classifiers":[
        {
            "category":"Banks & Credit Unions",
            "subcategory":"Investment Brokerage",
            "type":"Services"
        }
    ],
    "sg:phone":"+39 049 912 5266",
    "sg:postcode":"35020",
    "sg:province":"Padova",
    "sg:tags":[
        "lift",
        "truck"
    ],
    "wof:name":"Adriatica Industriale Macchine Srl",
    "wof:placetype":"venue"
},
  "geometry": {"coordinates":[11.822065,45.330223],"type":"Point"}
}