{
  "type": "Feature",
  "properties": {
    "iso:country":"IT",
    "sg:address":"100, Via Sansotta Domenico 00144 Roma",
    "sg:city":"Roma",
    "sg:classifiers":[
        {
            "category":"Professional",
            "subcategory":"Computer Services",
            "type":"Services"
        }
    ],
    "sg:phone":"+39 06 5227 9826",
    "sg:postcode":"00144",
    "sg:province":"Roma",
    "sg:tags":[
        "information",
        "technology"
    ],
    "wof:name":"Safo Sistemi S.r.l.",
    "wof:placetype":"venue"
},
  "geometry": {"coordinates":[12.436876,41.817505],"type":"Point"}
}