{
  "type": "Feature",
  "properties": {
    "iso:country":"IT",
    "sg:address":"00193 Roma",
    "sg:city":"Roma",
    "sg:orig_category":"Servizi Culturali E Per Lo Spettacolo. Servizi Al Turismo. Acqua, Luce, Gas E Societa' Di Esercizio Pubblico",
    "sg:phone":"+39 06 681 9111",
    "sg:postcode":"00193",
    "sg:province":"Roma",
    "wof:name":"Museo Nazionale Di Castel S.angelo",
    "wof:placetype":"venue"
},
  "geometry": {"coordinates":[12.46242,41.904129],"type":"Point"}
}