{
  "type": "Feature",
  "properties": {
    "iso:country":"IT",
    "sg:address":"Via Bafile 310; Jesolo",
    "sg:classifiers":[
        {
            "category":"Banks & Credit Unions",
            "subcategory":"Bank",
            "type":"Services"
        }
    ],
    "sg:phone":"+39 0421 93361",
    "wof:name":"Cassa Di Risparmio Di Venezia Spa",
    "wof:placetype":"venue"
},
  "geometry": {"coordinates":[12.632699,45.501446],"type":"Point"}
}