{
  "type": "Feature",
  "properties": {
    "iso:country":"IT",
    "sg:address":"Fondamenta Manin Daniele 5 30141 Venezia",
    "sg:city":"Venezia",
    "sg:classifiers":[
        {
            "category":"Ice Cream",
            "type":"Food & Drink"
        }
    ],
    "sg:phone":"+39 041 736788",
    "sg:postcode":"30141",
    "sg:province":"Venezia",
    "sg:tags":[
        "article",
        "gift",
        "glass"
    ],
    "sg:website":"www.ferromurano.it",
    "wof:name":"Ferro Murano Srl",
    "wof:placetype":"venue"
},
  "geometry": {"coordinates":[12.350761,45.452396],"type":"Point"}
}