{
  "type": "Feature",
  "properties": {
    "iso:country":"IT",
    "sg:address":"65019 Pianella",
    "sg:city":"Pianella",
    "sg:orig_category":"Alimentari - Produzione E Ingrosso",
    "sg:phone":"+39 085 973247",
    "sg:postcode":"65019",
    "sg:province":"Pescara",
    "sg:website":"http://www.dileonardo.it",
    "wof:name":"Salumificio Di Leonardo Spa",
    "wof:placetype":"venue"
},
  "geometry": {"coordinates":[14.065289,42.392345],"type":"Point"}
}