{
  "type": "Feature",
  "properties": {
    "addr:full":"20132 Milano Milano Milano 20132",
    "addr:postcode":"20132;20132",
    "iso:country":"IT",
    "sg:address":"20132 Milano",
    "sg:city":"Milano",
    "sg:orig_category":"Bevande, Vini E Liquori",
    "sg:phone":"+39 02 259 1271",
    "sg:postcode":"20132",
    "sg:province":"Milano",
    "wof:name":"Lobello Damiano",
    "wof:placetype":"venue"
},
  "geometry": {"coordinates":[9.242936,45.49958],"type":"Point"}
}