{
  "type": "Feature",
  "properties": {
    "iso:country":"IT",
    "sg:address":"24011 Alme'",
    "sg:orig_category":"Servizi E Lavori Per Arredamento E Industria Del Legno",
    "sg:phone":"+39 035 542157",
    "sg:postcode":"24011",
    "sg:province":"Bergamo",
    "wof:name":"Salvi Paola",
    "wof:placetype":"venue"
},
  "geometry": {"coordinates":[9.610068,45.739445],"type":"Point"}
}