{
  "type": "Feature",
  "properties": {
    "iso:country":"IT",
    "sg:address":"51, Via Del Gavardello 52100 Arezzo",
    "sg:city":"Arezzo",
    "sg:classifiers":[
        {
            "category":"Shopping",
            "subcategory":"Jewelry",
            "type":"Retail Goods"
        }
    ],
    "sg:phone":"+39 0575 383134",
    "sg:postcode":"52100",
    "sg:province":"Arezzo",
    "sg:tags":[
        "jewellery"
    ],
    "wof:name":"Manu' Italia (s.r.l.)",
    "wof:placetype":"venue"
},
  "geometry": {"coordinates":[11.86221,43.478271],"type":"Point"}
}