{
  "type": "Feature",
  "properties": {
    "iso:country":"IT",
    "sg:address":"70, Strada Del Francese 10156 Torino",
    "sg:city":"Torino",
    "sg:classifiers":[
        {
            "category":"Autos & Motor Vehicles",
            "subcategory":"Automobile Sales",
            "type":"Retail Goods"
        }
    ],
    "sg:phone":"+39 011 470 1516",
    "sg:postcode":"10156",
    "sg:province":"Torino",
    "sg:tags":[
        "industrial"
    ],
    "wof:name":"F.o.r.m.a. (s.r.l.)",
    "wof:placetype":"venue"
},
  "geometry": {"coordinates":[7.672542,45.134933],"type":"Point"}
}