{
  "type": "Feature",
  "properties": {
    "iso:country":"IT",
    "sg:address":"51017 Pescia",
    "sg:city":"Pescia",
    "sg:orig_category":"Fiori E Piante - Ingrosso",
    "sg:phone":"+39 0572 429358",
    "sg:postcode":"51017",
    "sg:province":"Pistoia",
    "wof:name":"Checchi Roi",
    "wof:placetype":"venue"
},
  "geometry": {"coordinates":[10.6737947464,43.8848800659],"type":"Point"}
}