{
  "type": "Feature",
  "properties": {
    "iso:country":"IT",
    "sg:address":"Piazza Archimede, 7; Siracusa; 96100",
    "sg:city":"Siracusa",
    "sg:classifiers":[
        {
            "category":"Banks & Credit Unions",
            "subcategory":"Bank",
            "type":"Services"
        }
    ],
    "sg:phone":"+39 0931 68203",
    "sg:postcode":"96100",
    "sg:province":"Siracusa",
    "wof:name":"Banca D'italia",
    "wof:placetype":"venue"
},
  "geometry": {"coordinates":[15.293708,37.061398],"type":"Point"}
}