{
  "type": "Feature",
  "properties": {
    "addr:full":"3, Viale Martiri Xxviii Giugno 38066 Riva Del Garda Riva del Garda Trento 38066",
    "addr:postcode":"38066;38066",
    "addr:street":"Viale Martiri Xxviii Giugno",
    "iso:country":"IT",
    "sg:address":"3, Viale Martiri Xxviii Giugno 38066 Riva Del Garda",
    "sg:city":"Riva del Garda",
    "sg:classifiers":[
        {
            "category":"Parking",
            "subcategory":"Lot",
            "type":"Transportation"
        }
    ],
    "sg:phone":"+39 0464 552325",
    "sg:postcode":"38066",
    "sg:province":"Trento",
    "sg:tags":[
        "transport",
        "road"
    ],
    "wof:name":"Betta Enzo Autotrasporti (s.r.l.)",
    "wof:placetype":"venue"
},
  "geometry": {"coordinates":[11.119053,46.066738],"type":"Point"}
}