{
  "type": "Feature",
  "properties": {
    "iso:country":"IT",
    "sg:address":"2, Via Del Trifoglio 30100 Venezia",
    "sg:classifiers":[
        {
            "category":"Utilities",
            "subcategory":"Electric",
            "type":"Services"
        }
    ],
    "sg:phone":"+39 39041932442",
    "sg:province":"VE",
    "sg:tags":[
        "component",
        "electronic"
    ],
    "wof:name":"Maccatrozzo Bruno",
    "wof:placetype":"venue"
},
  "geometry": {"coordinates":[12.214753,45.460426],"type":"Point"}
}