{
  "type": "Feature",
  "properties": {
    "iso:country":"IT",
    "sg:address":"40134 Bologna",
    "sg:city":"Bologna",
    "sg:orig_category":"Tappezzieri In Stoffa E Pelle",
    "sg:phone":"+39 051 614 2334",
    "sg:postcode":"40134",
    "sg:province":"Bologna",
    "wof:name":"Tappezzeria Artigiana Di Stuppazzoni Sergio",
    "wof:placetype":"venue"
},
  "geometry": {"coordinates":[11.318541,44.495804],"type":"Point"}
}