{
  "type": "Feature",
  "properties": {
    "iso:country":"IT",
    "sg:address":"53049 Torrita Di Siena",
    "sg:city":"Torrita di Siena",
    "sg:orig_category":"Termotecnica E Riscaldamento, Apparecchiature E Servizi",
    "sg:phone":"+39 0577 686000",
    "sg:postcode":"53049",
    "sg:province":"Siena",
    "wof:name":"D.m.t. S.r.l.",
    "wof:placetype":"venue"
},
  "geometry": {"coordinates":[11.763778,43.154911],"type":"Point"}
}