{
  "type": "Feature",
  "properties": {
    "iso:country":"IT",
    "sg:address":"20146 Milano",
    "sg:city":"Milano",
    "sg:orig_category":"Abbigliamento Esterno, Maglierie E Pelliccerie. Servizi E Lavori Per Abbigliamento E Pelletterie",
    "sg:phone":"+39 02 427772",
    "sg:postcode":"20146",
    "sg:province":"Milano",
    "wof:name":"Strummiello C. & Cislaghi V. Sdf Di Strummiello Cosimo & C.",
    "wof:placetype":"venue"
},
  "geometry": {"coordinates":[9.154417,45.454514],"type":"Point"}
}