{
  "type": "Feature",
  "properties": {
    "addr:full":"23868 Valmadrera Valmadrera Lecco 23868",
    "addr:postcode":"23868;23868",
    "iso:country":"IT",
    "sg:address":"23868 Valmadrera",
    "sg:city":"Valmadrera",
    "sg:orig_category":"Minuterie Metalliche E Ferramenta",
    "sg:phone":"+39 0341 580184",
    "sg:postcode":"23868",
    "sg:province":"Lecco",
    "wof:name":"Punteria Bartesaghi Di Bartesaghi Alfredo E C.(s.n.c.)",
    "wof:placetype":"venue"
},
  "geometry": {"coordinates":[9.3669748306,45.8464851379],"type":"Point"}
}