{
  "type": "Feature",
  "properties": {
    "iso:country":"IT",
    "sg:address":"Via Po N\u00b0 1 53036 Poggibonsi",
    "sg:city":"Poggibonsi",
    "sg:classifiers":[
        {
            "category":"Structure",
            "subcategory":"Tunnel",
            "type":"Public Place"
        }
    ],
    "sg:phone":"+39 0577 936722",
    "sg:postcode":"53036",
    "sg:province":"Siena",
    "sg:tags":[
        "extrusion",
        "system",
        "extruders"
    ],
    "sg:website":"www.leoplast.it",
    "wof:name":"Leoplast Industrie Srl",
    "wof:placetype":"venue"
},
  "geometry": {"coordinates":[11.144483,43.481857],"type":"Point"}
}