{
  "type": "Feature",
  "properties": {
    "addr:full":"43010 Fontevivo Bianconese Parma 43010",
    "addr:postcode":"43010;43010",
    "iso:country":"IT",
    "sg:address":"43010 Fontevivo",
    "sg:city":"Bianconese",
    "sg:orig_category":"Trasporti",
    "sg:phone":"+39 0521 619070",
    "sg:postcode":"43010",
    "sg:province":"Parma",
    "sg:website":"http://www.transystem.it",
    "wof:name":"Transystem Srl",
    "wof:placetype":"venue"
},
  "geometry": {"coordinates":[10.237073,44.856709],"type":"Point"}
}