{
  "type": "Feature",
  "properties": {
    "iso:country":"IT",
    "sg:address":"10032 Brandizzo",
    "sg:city":"Brandizzo",
    "sg:orig_category":"Macchine Utensili E Impianti",
    "sg:phone":"+39 011 913 9173",
    "sg:postcode":"10032",
    "sg:province":"Torino",
    "wof:name":"Ditta Dassetto Paolo Di Dassetto Geom. Luigi",
    "wof:placetype":"venue"
},
  "geometry": {"coordinates":[7.757177,45.146152],"type":"Point"}
}