{
  "type": "Feature",
  "properties": {
    "iso:country":"IT",
    "sg:address":"20122 Milano",
    "sg:city":"Milano",
    "sg:orig_category":"Prodotti E Manufatti In Materie Plastiche. Articoli Per Imballaggio E Confezionamento",
    "sg:postcode":"20122",
    "sg:province":"Milano",
    "wof:name":"Polifill Srl",
    "wof:placetype":"venue"
},
  "geometry": {"coordinates":[9.1959218979,45.4655685425],"type":"Point"}
}