{
  "type": "Feature",
  "properties": {
    "addr:full":"40122 Bologna Bologna Bologna 40122",
    "addr:postcode":"40122;40122",
    "iso:country":"IT",
    "sg:address":"40122 Bologna",
    "sg:city":"Bologna",
    "sg:orig_category":"Studi E Consulenze Legali E Notarili. Avvocati, Notai E Servizi Legali. Professionisti - Studi E Servizi Ed Associazioni Di Interesse Aziendale",
    "sg:phone":"+39 051 551040",
    "sg:postcode":"40122",
    "sg:province":"Bologna",
    "wof:name":"Avv. Rita Rossi",
    "wof:placetype":"venue"
},
  "geometry": {"coordinates":[11.334181,44.498508],"type":"Point"}
}