{
  "type": "Feature",
  "properties": {
    "iso:country":"IT",
    "sg:address":"64024 Notaresco",
    "sg:city":"Notaresco",
    "sg:orig_category":"Ricambi E Componenti Dei Mezzi Di Trasporto",
    "sg:phone":"+39 085 895 8666",
    "sg:postcode":"64024",
    "sg:province":"Teramo",
    "wof:name":"Fedele M Dei F.lli Leo & Luigi Fedele",
    "wof:placetype":"venue"
},
  "geometry": {"coordinates":[13.864812,42.72942],"type":"Point"}
}