{
  "type": "Feature",
  "properties": {
    "iso:country":"IT",
    "sg:address":"00141 Roma",
    "sg:city":"Roma",
    "sg:orig_category":"Servizi E Lavori Per Agricoltura E Zootecnia. Consulenze Tecniche, Amministrative E Perizie",
    "sg:phone":"+39 06 8719 3996",
    "sg:postcode":"00141",
    "sg:province":"Roma",
    "wof:name":"Rizzo Concetto",
    "wof:placetype":"venue"
},
  "geometry": {"coordinates":[12.528147,41.933769],"type":"Point"}
}