{
  "type": "Feature",
  "properties": {
    "iso:country":"IT",
    "sg:address":"00187 Roma",
    "sg:city":"Roma",
    "sg:orig_category":"Articoli Da Regalo. Arte Ed Artigianato Artistico. Shopping",
    "sg:phone":"+39 06 679 7540",
    "sg:postcode":"00187",
    "sg:province":"Roma",
    "wof:name":"Lovecchio Ettore Raoul",
    "wof:placetype":"venue"
},
  "geometry": {"coordinates":[12.488222,41.906181],"type":"Point"}
}