{
  "type": "Feature",
  "properties": {
    "iso:country":"IT",
    "sg:address":"48/e, Via Leonardo Da Vinci 20062 Cassano D'adda",
    "sg:classifiers":[
        {
            "category":"Utilities",
            "subcategory":"Electric",
            "type":"Services"
        }
    ],
    "sg:phone":"+39 39036363375",
    "sg:postcode":"20062",
    "sg:province":"Milano",
    "sg:tags":[
        "component",
        "electronic"
    ],
    "wof:name":"Telcavi (s.r.l.)",
    "wof:placetype":"venue"
},
  "geometry": {"coordinates":[9.562763,45.567478],"type":"Point"}
}