{
  "type": "Feature",
  "properties": {
    "iso:country":"IT",
    "sg:address":"6, Via Nazionale 43043 Borgo Val Di Taro",
    "sg:city":"Borgo Val di Taro",
    "sg:classifiers":[
        {
            "category":"Professional",
            "subcategory":"Computer Services",
            "type":"Services"
        }
    ],
    "sg:phone":"+39 0525 920008",
    "sg:postcode":"43043",
    "sg:province":"Parma",
    "sg:tags":[
        "information",
        "technology"
    ],
    "wof:name":"Info. Mont. (s.r.l.)",
    "wof:placetype":"venue"
},
  "geometry": {"coordinates":[9.765472,44.487152],"type":"Point"}
}