{
  "type": "Feature",
  "properties": {
    "iso:country":"IT",
    "sg:address":"20097 San Donato Milanese",
    "sg:city":"San Donato Milanese",
    "sg:orig_category":"Telecomunicazioni E Telefonia, Impianti, Apparecchi E Servizi. Acqua, Luce, Gas E Societa' Di Esercizio Pubblico. Servizi Vari Di Interesse Pubblico",
    "sg:phone":"+39 0255621",
    "sg:postcode":"20097",
    "sg:province":"Milano",
    "wof:name":"Finpromonet Srl",
    "wof:placetype":"venue"
},
  "geometry": {"coordinates":[9.276134,45.409676],"type":"Point"}
}