{
  "type": "Feature",
  "properties": {
    "addr:full":"Via Cavour 21, 67059 Trasacco, Aq L'Aquila 67059",
    "addr:housenumber":"21",
    "addr:postcode":"67059;67059",
    "addr:street":"Via Cavour",
    "iso:country":"IT",
    "sg:address":"Via Cavour 21, 67059 Trasacco, Aq",
    "sg:classifiers":[
        {
            "category":"Banks & Credit Unions",
            "subcategory":"Bank",
            "type":"Services"
        }
    ],
    "sg:postcode":"67059",
    "sg:province":"L'Aquila",
    "wof:name":"Banca Di Credito Cooperativo Di Trasacco Scrl",
    "wof:placetype":"venue"
},
  "geometry": {"coordinates":[13.537631,41.962063],"type":"Point"}
}