{
  "type": "Feature",
  "properties": {
    "iso:country":"IT",
    "sg:address":"33010 Osoppo",
    "sg:city":"Osoppo",
    "sg:orig_category":"Automobili E Mezzi Di Trasporto",
    "sg:phone":"+39 0432 986040",
    "sg:postcode":"33010",
    "sg:province":"Udine",
    "wof:name":"Carrozzeria Sora (s.r.l.)",
    "wof:placetype":"venue"
},
  "geometry": {"coordinates":[13.102862,46.304192],"type":"Point"}
}