{
  "type": "Feature",
  "properties": {
    "iso:country":"IT",
    "sg:address":"Via Roma, 54; Gazzo Veronese; 37060",
    "sg:city":"Gazzo Veronese",
    "sg:classifiers":[
        {
            "category":"Banks & Credit Unions",
            "subcategory":"Bank",
            "type":"Services"
        }
    ],
    "sg:phone":"+39 0442 58166",
    "sg:postcode":"37060",
    "sg:province":"Verona",
    "wof:name":"Banca Agricola Popolare Di Cerea",
    "wof:placetype":"venue"
},
  "geometry": {"coordinates":[11.107494,45.138966],"type":"Point"}
}