{
  "type": "Feature",
  "properties": {
    "iso:country":"IT",
    "sg:address":"54033 Carrara",
    "sg:city":"Carrara",
    "sg:orig_category":"Servizi Ausiliari Di Sorveglianza, Manutenzione E Pulizia",
    "sg:phone":"+39 0585 70093",
    "sg:postcode":"54033",
    "sg:province":"Massa-Carrara",
    "sg:website":"http://la.polizia.privata.it",
    "wof:name":"La Polizia Privata Srl",
    "wof:placetype":"venue"
},
  "geometry": {"coordinates":[10.035966,44.221401],"type":"Point"}
}