{
  "type": "Feature",
  "properties": {
    "iso:country":"IT",
    "sg:address":"30123 Venezia",
    "sg:city":"Dorsoduro",
    "sg:orig_category":"Prodotti Alimentari",
    "sg:phone":"+39 041 522 2251",
    "sg:postcode":"30123",
    "sg:province":"Venezia",
    "wof:name":"Frison Eliseo (s.n.c.)",
    "wof:placetype":"venue"
},
  "geometry": {"coordinates":[12.3260002136,45.4309997559],"type":"Point"}
}