{
  "type": "Feature",
  "properties": {
    "iso:country":"IT",
    "sg:address":"Via Lovara 40g 36075 Montecchio Maggiore",
    "sg:city":"Montecchio Maggiore",
    "sg:orig_category":"Ladies' Trousers Suits, Suits, Jackets, Skirts, And Trousers",
    "sg:phone":"+39 0444 482978",
    "sg:postcode":"36075",
    "sg:province":"Vicenza",
    "wof:name":"Protea Srl",
    "wof:placetype":"venue"
},
  "geometry": {"coordinates":[11.540307,45.545906],"type":"Point"}
}