{
  "type": "Feature",
  "properties": {
    "addr:full":"Via Giotto 2, 46042 Castelgoffredo, Mn Mantova 46042",
    "addr:housenumber":"2",
    "addr:postcode":"46042;46042",
    "addr:street":"Via Giotto",
    "iso:country":"IT",
    "sg:address":"Via Giotto 2, 46042 Castelgoffredo, Mn",
    "sg:classifiers":[
        {
            "category":"Banks & Credit Unions",
            "subcategory":"Bank",
            "type":"Services"
        }
    ],
    "sg:postcode":"46042",
    "sg:province":"Mantova",
    "wof:name":"Banca Di Credito Cooperativo Di Castel Goffredo Scrl",
    "wof:placetype":"venue"
},
  "geometry": {"coordinates":[10.797698,45.160366],"type":"Point"}
}