{
  "type": "Feature",
  "properties": {
    "addr:full":"12043 Canale Canale Cuneo 12043",
    "addr:postcode":"12043;12043",
    "iso:country":"IT",
    "sg:address":"12043 Canale",
    "sg:city":"Canale",
    "sg:orig_category":"Arredo Cucina Ed Elettrodomestici",
    "sg:phone":"+39 0173 979251",
    "sg:postcode":"12043",
    "sg:province":"Cuneo",
    "wof:name":"M.i.m. Masoero & Icardi Snc",
    "wof:placetype":"venue"
},
  "geometry": {"coordinates":[7.996784,44.76437],"type":"Point"}
}