{
  "type": "Feature",
  "properties": {
    "iso:country":"IT",
    "sg:address":"Via Xxv Aprile, 3/9 51035 Lamporecchio",
    "sg:city":"Lamporecchio",
    "sg:classifiers":[
        {
            "category":"Personal",
            "subcategory":"Shoe Repair & Shine",
            "type":"Services"
        }
    ],
    "sg:phone":"+39 0573 803430",
    "sg:postcode":"51035",
    "sg:province":"Pistoia",
    "sg:tags":[
        "fitting",
        "ferrule"
    ],
    "sg:website":"www.anteosrl.com",
    "wof:name":"Anteo Srl",
    "wof:placetype":"venue"
},
  "geometry": {"coordinates":[10.918524,43.932156],"type":"Point"}
}