{
  "type": "Feature",
  "properties": {
    "iso:country":"IT",
    "sg:address":"2, V. Pascoli 50129 Firenze",
    "sg:city":"Firenze",
    "sg:classifiers":[
        {
            "category":"Communications",
            "subcategory":"Newspaper",
            "type":"Services"
        }
    ],
    "sg:phone":"+39 055 552 0827",
    "sg:postcode":"50129",
    "sg:province":"Firenze",
    "sg:tags":[
        "advertising"
    ],
    "sg:website":"http://www.creativeimage.com",
    "wof:name":"Creative Image Entertainment",
    "wof:placetype":"venue"
},
  "geometry": {"coordinates":[11.2661,43.78558],"type":"Point"}
}