{
  "type": "Feature",
  "properties": {
    "iso:country":"IT",
    "sg:address":"Via Biella 71bis 10098 Rivoli",
    "sg:city":"Rivoli",
    "sg:classifiers":[
        {
            "category":"Banks & Credit Unions",
            "subcategory":"Investment Brokerage",
            "type":"Services"
        }
    ],
    "sg:phone":"+39 011 957 2527",
    "sg:postcode":"10098",
    "sg:province":"Torino",
    "sg:tags":[
        "lift",
        "truck"
    ],
    "wof:name":"Adl Costruzioni Elettromeccaniche S.n.c.",
    "wof:placetype":"venue"
},
  "geometry": {"coordinates":[7.545512,45.065598],"type":"Point"}
}