{
  "type": "Feature",
  "properties": {
    "iso:country":"IT",
    "sg:address":"60022 Castelfidardo",
    "sg:city":"Castelfidardo",
    "sg:orig_category":"Metalli E Leghe",
    "sg:phone":"+39 071 782 5300",
    "sg:postcode":"60022",
    "sg:province":"Ancona",
    "wof:name":"Asset Trade Srl",
    "wof:placetype":"venue"
},
  "geometry": {"coordinates":[13.4969549179,43.5098304749],"type":"Point"}
}