{
  "type": "Feature",
  "properties": {
    "addr:full":"40033 Casalecchio Di Reno Casalecchio di Reno Bologna 40033",
    "addr:postcode":"40033;40033",
    "addr:street":"Di Reno",
    "iso:country":"IT",
    "sg:address":"40033 Casalecchio Di Reno",
    "sg:city":"Casalecchio di Reno",
    "sg:orig_category":"Studi E Consulenze Amministrative, Commerciali E Aziendali. Consulenze Tecniche, Amministrative E Perizie. Professionisti - Studi E Servizi Ed Associazioni Di Interesse Aziendale",
    "sg:phone":"+39 051 572311",
    "sg:postcode":"40033",
    "sg:province":"Bologna",
    "sg:website":"http://www.studiodavalli.com",
    "wof:name":"Davalli Michele",
    "wof:placetype":"venue"
},
  "geometry": {"coordinates":[11.274617,44.474384],"type":"Point"}
}