{
  "type": "Feature",
  "properties": {
    "addr:full":"94, V. Delle Industrie 31030 Dosson Di Casier Casier Treviso 31030",
    "addr:housenumber":"94",
    "addr:postcode":"31030;31030",
    "addr:street":"V. Delle Industrie",
    "iso:country":"IT",
    "sg:address":"94, V. Delle Industrie 31030 Dosson Di Casier",
    "sg:city":"Casier",
    "sg:classifiers":[
        {
            "category":"Shopping",
            "subcategory":"Stationery & Office Supplies",
            "type":"Retail Goods"
        }
    ],
    "sg:phone":"+39 0422 636100",
    "sg:postcode":"31030",
    "sg:province":"Treviso",
    "sg:tags":[
        "professional"
    ],
    "sg:website":"http://www.fidiainc.com",
    "wof:name":"Fidia Spa",
    "wof:placetype":"venue"
},
  "geometry": {"coordinates":[12.262799263,45.6161422729],"type":"Point"}
}