{
  "type": "Feature",
  "properties": {
    "addr:full":"47023 Cesena Cesena Forl\u00ec-Cesena 47023",
    "addr:postcode":"47023;47023",
    "iso:country":"IT",
    "sg:address":"47023 Cesena",
    "sg:city":"Cesena",
    "sg:orig_category":"Motori Ed Organi Di Trasmissione",
    "sg:phone":"+39 0547 646163",
    "sg:postcode":"47023",
    "sg:province":"Forl\u00ec-Cesena",
    "wof:name":"Fratelli Pagliarani Srl",
    "wof:placetype":"venue"
},
  "geometry": {"coordinates":[12.2958669662,44.1188697815],"type":"Point"}
}