{
  "type": "Feature",
  "properties": {
    "addr:full":"20145 Milano Milano Milano 20145",
    "addr:postcode":"20145;20145",
    "iso:country":"IT",
    "sg:address":"20145 Milano",
    "sg:city":"Milano",
    "sg:orig_category":"Servizi Ausiliari Di Certificati, Riproduzioni, Disegni E Foto",
    "sg:phone":"+39 02 469 0680",
    "sg:postcode":"20145",
    "sg:province":"Milano",
    "sg:website":"http://www.dedit.it/natali",
    "wof:name":"Natali Technology Srl",
    "wof:placetype":"venue"
},
  "geometry": {"coordinates":[9.162676,45.467731],"type":"Point"}
}