{
  "type": "Feature",
  "properties": {
    "addr:full":"30, Via Oberdan Guglielmo 33078 San Vito Al Tagliamento San Vito al Tagliamento Pordenone 33078",
    "addr:postcode":"33078;33078",
    "addr:street":"Via Oberdan Guglielmo",
    "iso:country":"IT",
    "sg:address":"30, Via Oberdan Guglielmo 33078 San Vito Al Tagliamento",
    "sg:city":"San Vito al Tagliamento",
    "sg:classifiers":[
        {
            "category":"Manufacturing",
            "subcategory":"Metals",
            "type":"Manufacturing & Wholesale Goods"
        }
    ],
    "sg:phone":"+39 0434 875580",
    "sg:postcode":"33078",
    "sg:province":"Pordenone",
    "sg:tags":[
        "metallurgy",
        "metalworking"
    ],
    "wof:name":"Metalferramenta (s.p.a.)",
    "wof:placetype":"venue"
},
  "geometry": {"coordinates":[12.655043602,45.9626502991],"type":"Point"}
}