{
  "type": "Feature",
  "properties": {
    "addr:full":"27049 Stradella Stradella Pavia 27049",
    "addr:postcode":"27049;27049",
    "iso:country":"IT",
    "sg:address":"27049 Stradella",
    "sg:city":"Stradella",
    "sg:orig_category":"Apparecchiature E Sistemi Per Magazzinaggio E Movimentazione",
    "sg:phone":"+39 0385 240833",
    "sg:postcode":"27049",
    "sg:province":"Pavia",
    "wof:name":"Nuova Carrozzauto Sas Di Giorgi & C.",
    "wof:placetype":"venue"
},
  "geometry": {"coordinates":[9.301888,45.074074],"type":"Point"}
}