{
  "type": "Feature",
  "properties": {
    "iso:country":"IT",
    "sg:address":"81100 Caserta",
    "sg:city":"Caserta",
    "sg:orig_category":"Ospedali E Servizi Sanitari",
    "sg:phone":"+39 0823 279616",
    "sg:postcode":"81100",
    "sg:province":"Caserta",
    "wof:name":"Garozzo Gaudenzio",
    "wof:placetype":"venue"
},
  "geometry": {"coordinates":[14.33624,41.067032],"type":"Point"}
}