{
  "type": "Feature",
  "properties": {
    "addr:full":"Via Miraglia Nicola 47 80143 Napoli Napoli Napoli 80143",
    "addr:housenumber":"47",
    "addr:postcode":"80143;80143",
    "addr:street":"Via Miraglia Nicola",
    "iso:country":"IT",
    "sg:address":"Via Miraglia Nicola 47 80143 Napoli",
    "sg:city":"Napoli",
    "sg:classifiers":[
        {
            "category":"Manufacturing",
            "subcategory":"Glass & Minerals",
            "type":"Manufacturing & Wholesale Goods"
        }
    ],
    "sg:phone":"+39 081 759 7545",
    "sg:postcode":"80143",
    "sg:province":"Napoli",
    "sg:tags":[
        "industrial",
        "working"
    ],
    "wof:name":"Eredi Di Pasquale Varriale Snc Di Pasquale Varriale E C.",
    "wof:placetype":"venue"
},
  "geometry": {"coordinates":[14.295545,40.867672],"type":"Point"}
}