{
  "type": "Feature",
  "properties": {
    "iso:country":"IT",
    "sg:address":"13/b, Via Tassinara 40017 San Giovanni In Persiceto",
    "sg:city":"San Giovanni in Persiceto",
    "sg:classifiers":[
        {
            "category":"Shopping",
            "type":"Retail Goods"
        }
    ],
    "sg:phone":"+39 39051822735",
    "sg:postcode":"40017",
    "sg:province":"Bologna",
    "sg:tags":[
        "finished",
        "-",
        "metallic"
    ],
    "wof:name":"B.i.e. Di Baldazzi Emilio & C. (s.n.c.)",
    "wof:placetype":"venue"
},
  "geometry": {"coordinates":[11.2003545761,44.6216812134],"type":"Point"}
}