{
  "type": "Feature",
  "properties": {
    "addr:full":"20010 Cornaredo Cornaredo Milano 20010",
    "addr:postcode":"20010;20010",
    "iso:country":"IT",
    "sg:address":"20010 Cornaredo",
    "sg:city":"Cornaredo",
    "sg:orig_category":"Marmo Ed Affini - Commercio",
    "sg:phone":"+39 02 936 2160",
    "sg:postcode":"20010",
    "sg:province":"Milano",
    "wof:name":"Borchia Leonello",
    "wof:placetype":"venue"
},
  "geometry": {"coordinates":[9.052553,45.534931],"type":"Point"}
}