{
  "type": "Feature",
  "properties": {
    "addr:full":"88046 Lamezia Terme Lamezia Terme Catanzaro 88046",
    "addr:postcode":"88046;88046",
    "iso:country":"IT",
    "sg:address":"88046 Lamezia Terme",
    "sg:city":"Lamezia Terme",
    "sg:orig_category":"Acque Minerali E Bevande, Naturali E Gassate - Commercio",
    "sg:phone":"+39 0968 21947",
    "sg:postcode":"88046",
    "sg:province":"Catanzaro",
    "sg:website":"http://www.bibicaffe.it",
    "wof:name":"Desarro & Torchia Srl",
    "wof:placetype":"venue"
},
  "geometry": {"coordinates":[16.275751,38.93362],"type":"Point"}
}