{
  "type": "Feature",
  "properties": {
    "iso:country":"IT",
    "sg:address":"20010 Pregnana Milanese",
    "sg:city":"Pregnana Milanese",
    "sg:orig_category":"Servizi E Lavori Per Industria Alimentare E Bevande",
    "sg:phone":"+39 02 930 1762",
    "sg:postcode":"20010",
    "sg:province":"Milano",
    "wof:name":"Rossi Giovanni",
    "wof:placetype":"venue"
},
  "geometry": {"coordinates":[9.009096,45.515209],"type":"Point"}
}