{
  "type": "Feature",
  "properties": {
    "iso:country":"IT",
    "sg:address":"87100 Cosenza",
    "sg:city":"Cosenza",
    "sg:orig_category":"Alberghi",
    "sg:phone":"+39 0984 27440",
    "sg:postcode":"87100",
    "sg:province":"Cosenza",
    "wof:name":"Terme Luigiane",
    "wof:placetype":"venue"
},
  "geometry": {"coordinates":[16.250834,39.299026],"type":"Point"}
}