{
  "type": "Feature",
  "properties": {
    "addr:full":"40, V. Mossa 63020 Montappone Montappone Ascoli Piceno 63020",
    "addr:housenumber":"40",
    "addr:postcode":"63020;63020",
    "addr:street":"V. Mossa",
    "iso:country":"IT",
    "sg:address":"40, V. Mossa 63020 Montappone",
    "sg:city":"Montappone",
    "sg:classifiers":[
        {
            "category":"Shopping",
            "subcategory":"Clothing, Apparel, & Fashions",
            "type":"Retail Goods"
        }
    ],
    "sg:phone":"+39 0734 760669",
    "sg:postcode":"63020",
    "sg:province":"Ascoli Piceno",
    "sg:tags":[
        "clothing",
        "accessory"
    ],
    "wof:name":"Cappellificio Fagiani Vincenzo",
    "wof:placetype":"venue"
},
  "geometry": {"coordinates":[13.471622,43.126865],"type":"Point"}
}