{
  "type": "Feature",
  "properties": {
    "iso:country":"IT",
    "sg:address":"235, Via Di Salone 00131 Roma",
    "sg:city":"Roma",
    "sg:classifiers":[
        {
            "category":"Home & Garden",
            "subcategory":"Home Furnishings",
            "type":"Retail Goods"
        }
    ],
    "sg:phone":"+39 39064190340",
    "sg:postcode":"00131",
    "sg:province":"Roma",
    "sg:tags":[
        "household"
    ],
    "wof:name":"Lolli Fratelli (s.p.a.)",
    "wof:placetype":"venue"
},
  "geometry": {"coordinates":[12.627867,41.929649],"type":"Point"}
}