{
  "type": "Feature",
  "properties": {
    "iso:country":"IT",
    "sg:address":"20149 Milano",
    "sg:city":"Milano",
    "sg:orig_category":"Autolavaggio",
    "sg:phone":"+39 02 463727",
    "sg:postcode":"20149",
    "sg:province":"Milano",
    "wof:name":"Silva Assistauto Srl",
    "wof:placetype":"venue"
},
  "geometry": {"coordinates":[9.150843,45.480858],"type":"Point"}
}