{
  "type": "Feature",
  "properties": {
    "addr:full":"23842 Bosisio Parini Bosisio Parini Lecco 23842",
    "addr:postcode":"23842;23842",
    "iso:country":"IT",
    "sg:address":"23842 Bosisio Parini",
    "sg:city":"Bosisio Parini",
    "sg:orig_category":"Prodotti Vari In Metallo. Articoli Per Imballaggio E Confezionamento",
    "sg:phone":"+39 031 866031",
    "sg:postcode":"23842",
    "sg:province":"Lecco",
    "wof:name":"Beccalli Maria Rita",
    "wof:placetype":"venue"
},
  "geometry": {"coordinates":[9.2688083649,45.8152656555],"type":"Point"}
}