{
  "type": "Feature",
  "properties": {
    "iso:country":"IT",
    "sg:address":"10, Via Pascolo 24044 Dalmine",
    "sg:city":"Dalmine",
    "sg:classifiers":[
        {
            "category":"Parking",
            "subcategory":"Lot",
            "type":"Transportation"
        }
    ],
    "sg:phone":"+39 39035502312",
    "sg:postcode":"24044",
    "sg:province":"Bergamo",
    "sg:tags":[
        "transport",
        "road"
    ],
    "wof:name":"Comco (s.p.a.)",
    "wof:placetype":"venue"
},
  "geometry": {"coordinates":[9.582582,45.661057],"type":"Point"}
}