{
  "type": "Feature",
  "properties": {
    "iso:country":"IT",
    "sg:address":"Via Dei Prati 20 10020 Cambiano",
    "sg:city":"Cambiano",
    "sg:classifiers":[
        {
            "category":"Shopping Center",
            "type":"Public Place"
        }
    ],
    "sg:phone":"+39 011 945 7170",
    "sg:postcode":"10020",
    "sg:province":"Torino",
    "sg:tags":[
        "spotlight"
    ],
    "wof:name":"Tri.o.m. Spa",
    "wof:placetype":"venue"
},
  "geometry": {"coordinates":[7.767499,44.962044],"type":"Point"}
}