{
  "type": "Feature",
  "properties": {
    "iso:country":"IT",
    "sg:address":"20019 Settimo Milanese",
    "sg:city":"Settimo Milanese",
    "sg:orig_category":"Prodotti Alimentari",
    "sg:phone":"+39 02 328 3060",
    "sg:postcode":"20019",
    "sg:province":"Milano",
    "wof:name":"Corrado Elviro",
    "wof:placetype":"venue"
},
  "geometry": {"coordinates":[9.0626010895,45.4727363586],"type":"Point"}
}