{
  "type": "Feature",
  "properties": {
    "addr:full":"93, Via Postumia 31050 Ponzano Veneto Ponzano Veneto Treviso 31050",
    "addr:postcode":"31050;31050",
    "addr:street":"Via Postumia",
    "iso:country":"IT",
    "sg:address":"93, Via Postumia 31050 Ponzano Veneto",
    "sg:city":"Ponzano Veneto",
    "sg:classifiers":[
        {
            "category":"Shopping",
            "type":"Retail Goods"
        }
    ],
    "sg:phone":"+39 0422 969127",
    "sg:postcode":"31050",
    "sg:province":"Treviso",
    "sg:tags":[
        "finished",
        "-",
        "metallic"
    ],
    "wof:name":"O.m.p. Paronetto S.r.l.",
    "wof:placetype":"venue"
},
  "geometry": {"coordinates":[12.2037496567,45.7289466858],"type":"Point"}
}