{
  "type": "Feature",
  "properties": {
    "iso:country":"IT",
    "sg:address":"102, Via Granarolo 48018 Faenza",
    "sg:city":"Faenza",
    "sg:classifiers":[
        {
            "category":"Food & Beverages",
            "subcategory":"Groceries & Convenience Stores",
            "type":"Retail Goods"
        }
    ],
    "sg:phone":"+39 39054646034",
    "sg:postcode":"48018",
    "sg:province":"Ravenna",
    "sg:tags":[
        "product",
        "related"
    ],
    "wof:name":"Tampieri Financial Group Spa",
    "wof:placetype":"venue"
},
  "geometry": {"coordinates":[11.912112236,44.3306884766],"type":"Point"}
}