{
  "type": "Feature",
  "properties": {
    "iso:country":"IT",
    "sg:address":"09126 Cagliari",
    "sg:city":"Cagliari",
    "sg:classifiers":[
        {
            "category":"Health Services",
            "subcategory":"Health Practitioner",
            "type":"Services"
        }
    ],
    "sg:phone":"+39 070 307889",
    "sg:postcode":"09126",
    "sg:province":"Cagliari",
    "sg:tags":[
        "medici"
    ],
    "wof:name":"Lorrai Silvio",
    "wof:placetype":"venue"
},
  "geometry": {"coordinates":[9.134759,39.205662],"type":"Point"}
}