{
  "type": "Feature",
  "properties": {
    "iso:country":"IT",
    "sg:address":"7, Via Delle Scuole 42019 Scandiano",
    "sg:classifiers":[
        {
            "category":"Food & Beverages",
            "subcategory":"Groceries & Convenience Stores",
            "type":"Retail Goods"
        }
    ],
    "sg:phone":"+39 0522 855441",
    "sg:postcode":"42019",
    "sg:province":"Reggio Nell'Emilia",
    "sg:tags":[
        "drink"
    ],
    "wof:name":"Casali Viticultori S.r.l.",
    "wof:placetype":"venue"
},
  "geometry": {"coordinates":[10.6751384735,44.6025772095],"type":"Point"}
}