{
  "type": "Feature",
  "properties": {
    "iso:country":"IT",
    "sg:address":"13863 Coggiola",
    "sg:city":"Coggiola",
    "sg:orig_category":"Lana Tessuti",
    "sg:phone":"+39 015 78541",
    "sg:postcode":"13863",
    "sg:province":"Biella",
    "wof:name":"Lanificio Fratelli Fila",
    "wof:placetype":"venue"
},
  "geometry": {"coordinates":[8.15489,45.712872],"type":"Point"}
}