{
  "type": "Feature",
  "properties": {
    "iso:country":"IT",
    "sg:address":"56034 Casciana Alta",
    "sg:orig_category":"Alberghi E Strutture Extra Alberghiere",
    "sg:phone":"+39 0587 689171",
    "sg:postcode":"56034",
    "sg:province":"Pisa",
    "sg:website":"http://villaorsini.com",
    "wof:name":"Villa Orsini",
    "wof:placetype":"venue"
},
  "geometry": {"coordinates":[10.5987596512,43.5392417908],"type":"Point"}
}