{
  "type": "Feature",
  "properties": {
    "iso:country":"IT",
    "sg:address":"37057 S.giovanni Lupatoto",
    "sg:orig_category":"Impiantistica E Prodotti Tecnologici Per Edilizia. Climatizzazione E Condizionamento, Apparecchiature E Servizi",
    "sg:phone":"+39 045 875 0394",
    "sg:postcode":"37057",
    "sg:province":"Verona",
    "sg:website":"http://www.galvani.com",
    "wof:name":"Galvani Srl",
    "wof:placetype":"venue"
},
  "geometry": {"coordinates":[11.08102,45.373146],"type":"Point"}
}