{
  "type": "Feature",
  "properties": {
    "iso:country":"IT",
    "sg:address":"Strada Pedagnolo 3b 46042 Castel Goffredo",
    "sg:city":"Castel Goffredo",
    "sg:classifiers":[
        {
            "category":"Shopping",
            "subcategory":"Baby Store",
            "type":"Retail Goods"
        }
    ],
    "sg:phone":"+39 0376 770369",
    "sg:postcode":"46042",
    "sg:province":"Mantova",
    "sg:tags":[
        "children's",
        "tights"
    ],
    "sg:website":"www.bellafonte.com",
    "wof:name":"Calzificio Bellafonte S.r.l.",
    "wof:placetype":"venue"
},
  "geometry": {"coordinates":[10.494456,45.294365],"type":"Point"}
}