{
  "type": "Feature",
  "properties": {
    "addr:full":"95121 Catania Catania Catania 95121",
    "addr:postcode":"95121;95121",
    "iso:country":"IT",
    "sg:address":"95121 Catania",
    "sg:city":"Catania",
    "sg:orig_category":"Servizi Ausiliari Dei Mezzi Di Trasporto",
    "sg:phone":"+39 095 577618",
    "sg:postcode":"95121",
    "sg:province":"Catania",
    "wof:name":"Erbasecca Giuseppe",
    "wof:placetype":"venue"
},
  "geometry": {"coordinates":[15.061591,37.479515],"type":"Point"}
}