{
  "type": "Feature",
  "properties": {
    "iso:country":"IT",
    "sg:address":"48022 Lugo",
    "sg:city":"Lugo",
    "sg:orig_category":"Macchine, Impianti Ed Attrezzature Per Industria Alimentare E Bevande",
    "sg:phone":"+39 0545 72608",
    "sg:postcode":"48022",
    "sg:province":"Ravenna",
    "wof:name":"I.c.m. Impianti Srl",
    "wof:placetype":"venue"
},
  "geometry": {"coordinates":[11.932364,44.540428],"type":"Point"}
}