{
  "type": "Feature",
  "properties": {
    "addr:full":"41019 Soliera Soliera Modena 41019",
    "addr:postcode":"41019;41019",
    "iso:country":"IT",
    "sg:address":"41019 Soliera",
    "sg:city":"Soliera",
    "sg:orig_category":"Pavimenti - Lamatura, Levigatura E Verniciatura",
    "sg:phone":"+39 059 567283",
    "sg:postcode":"41019",
    "sg:province":"Modena",
    "wof:name":"Annovi Verter",
    "wof:placetype":"venue"
},
  "geometry": {"coordinates":[10.9155664444,44.7358398438],"type":"Point"}
}