{
  "type": "Feature",
  "properties": {
    "iso:country":"IT",
    "sg:address":"10142 Torino",
    "sg:city":"Torino",
    "sg:orig_category":"Televisori, Videoregistratori E Radio - Riparazione",
    "sg:phone":"+39 011 411 3279",
    "sg:postcode":"10142",
    "sg:province":"Torino",
    "wof:name":"Tecno-test Di Antonio Lucia & Lo Camp",
    "wof:placetype":"venue"
},
  "geometry": {"coordinates":[7.120077,45.126019],"type":"Point"}
}