{
  "type": "Feature",
  "properties": {
    "iso:country":"IT",
    "sg:address":"28886 Pieve Vergonte",
    "sg:city":"Pieve Vergonte",
    "sg:orig_category":"Musica",
    "sg:phone":"+39 0324 83189",
    "sg:postcode":"28886",
    "sg:province":"Verbano-Cusio-Ossola",
    "wof:name":"Silvestri Orlando",
    "wof:placetype":"venue"
},
  "geometry": {"coordinates":[8.2591686249,46.0194892883],"type":"Point"}
}