{
  "type": "Feature",
  "properties": {
    "iso:country":"IT",
    "sg:address":"70020 Bitritto",
    "sg:city":"Bitritto",
    "sg:orig_category":"Arredamento Bar E Ristoranti",
    "sg:phone":"+39 080 634038",
    "sg:postcode":"70020",
    "sg:province":"Bari",
    "wof:name":"Colazzo Roberto",
    "wof:placetype":"venue"
},
  "geometry": {"coordinates":[16.826164,41.04343],"type":"Point"}
}