{
  "type": "Feature",
  "properties": {
    "addr:full":"Via Sicilia 35; Perugia; 06100",
    "addr:housenumber":"35",
    "addr:postcode":"06100",
    "addr:street":"Via Sicilia",
    "iso:country":"IT",
    "sg:address":"Via Sicilia 35; Perugia; 06100",
    "sg:classifiers":[
        {
            "category":"Banks & Credit Unions",
            "subcategory":"Bank",
            "type":"Services"
        }
    ],
    "sg:phone":"+39 075 505 1541",
    "wof:name":"Banco Di Sicilia Spa",
    "wof:placetype":"venue"
},
  "geometry": {"coordinates":[12.376274,43.10257],"type":"Point"}
}