{
  "type": "Feature",
  "properties": {
    "iso:country":"IT",
    "sg:address":"14012 Ferrere",
    "sg:city":"Ferrere",
    "sg:orig_category":"Capannoni, Tensostrutture E Tendoni",
    "sg:phone":"+39 0141 934209",
    "sg:postcode":"14012",
    "sg:province":"Asti",
    "wof:name":"Viglione Fratelli",
    "wof:placetype":"venue"
},
  "geometry": {"coordinates":[7.993,44.880032],"type":"Point"}
}