{
  "type": "Feature",
  "properties": {
    "iso:country":"IT",
    "sg:address":"40064 Ozzano Dell'emilia",
    "sg:orig_category":"Sementi E Bulbi",
    "sg:phone":"+39 051 790176",
    "sg:postcode":"40064",
    "sg:province":"Bologna",
    "wof:name":"Arborea Piccola Soc. Coop. R.l.",
    "wof:placetype":"venue"
},
  "geometry": {"coordinates":[11.502067,44.453754],"type":"Point"}
}