{
  "type": "Feature",
  "properties": {
    "addr:full":"24069 Cenate Sotto Cenate Sotto Bergamo 24069",
    "addr:postcode":"24069;24069",
    "iso:country":"IT",
    "sg:address":"24069 Cenate Sotto",
    "sg:city":"Cenate Sotto",
    "sg:orig_category":"Frutta E Verdura - Ingrosso",
    "sg:phone":"+39 035 425 0732",
    "sg:postcode":"24069",
    "sg:province":"Bergamo",
    "wof:name":"Salvi Frutta Srl",
    "wof:placetype":"venue"
},
  "geometry": {"coordinates":[9.6723003387,45.6986961365],"type":"Point"}
}