{
  "type": "Feature",
  "properties": {
    "iso:country":"IT",
    "sg:address":"37060 Nogarole Rocca",
    "sg:city":"Nogarole Rocca",
    "sg:orig_category":"Abbigliamento Esterno, Maglierie E Pelliccerie. Shopping",
    "sg:phone":"+39 045 792 5610",
    "sg:postcode":"37060",
    "sg:province":"Verona",
    "wof:name":"Emil Conf Moda Srl",
    "wof:placetype":"venue"
},
  "geometry": {"coordinates":[10.877878,45.281769],"type":"Point"}
}