{
  "type": "Feature",
  "properties": {
    "addr:full":"42/d, V. Nazionale 33010 Tavagnacco Tavagnacco Udine 33010",
    "addr:housenumber":"42 / d",
    "addr:postcode":"33010;33010",
    "addr:street":"V. Nazionale",
    "iso:country":"IT",
    "sg:address":"42/d, V. Nazionale 33010 Tavagnacco",
    "sg:city":"Tavagnacco",
    "sg:classifiers":[
        {
            "category":"Shopping",
            "subcategory":"Stationery & Office Supplies",
            "type":"Retail Goods"
        }
    ],
    "sg:phone":"+39 0432 548844",
    "sg:postcode":"33010",
    "sg:province":"Udine",
    "sg:tags":[
        "professional"
    ],
    "sg:website":"http://www.centroemmedi.it",
    "wof:name":"Centro Emmedi",
    "wof:placetype":"venue"
},
  "geometry": {"coordinates":[13.2291841507,46.1047134399],"type":"Point"}
}