{
  "type": "Feature",
  "properties": {
    "iso:country":"IT",
    "sg:address":"31049 Valdobbiadene",
    "sg:city":"Valdobbiadene",
    "sg:orig_category":"Arredamenti Ed Architettura D'interni",
    "sg:phone":"+39 0423 982180",
    "sg:postcode":"31049",
    "sg:province":"Treviso",
    "wof:name":"Euroluce Di Palermiti E Prosdocimo Snc",
    "wof:placetype":"venue"
},
  "geometry": {"coordinates":[12.019026,45.879452],"type":"Point"}
}