{
  "type": "Feature",
  "properties": {
    "addr:full":"36078 Valdagno Valdagno Vicenza 36078",
    "addr:postcode":"36078;36078",
    "iso:country":"IT",
    "sg:address":"36078 Valdagno",
    "sg:city":"Valdagno",
    "sg:orig_category":"Medicinali E Prodotti Parafarmaceutici",
    "sg:phone":"+39 0445 413665",
    "sg:postcode":"36078",
    "sg:province":"Vicenza",
    "wof:name":"Farmacia Cooperativa Arl",
    "wof:placetype":"venue"
},
  "geometry": {"coordinates":[11.289765358,45.6647262573],"type":"Point"}
}