{
  "type": "Feature",
  "properties": {
    "iso:country":"IT",
    "sg:address":"50068 Rufina",
    "sg:city":"Rufina",
    "sg:orig_category":"Bevande, Vini E Liquori",
    "sg:phone":"+39 055 839 6025",
    "sg:postcode":"50068",
    "sg:province":"Firenze",
    "sg:website":"http://www.cantinebellini.it",
    "wof:name":"Cantine Fratelli Bellini Sas",
    "wof:placetype":"venue"
},
  "geometry": {"coordinates":[11.268443,43.766602],"type":"Point"}
}