{
  "type": "Feature",
  "properties": {
    "addr:full":"07020 Golfo Aranci Golfo Aranci Olbia-Tempio 07020",
    "addr:postcode":"07020;07020",
    "iso:country":"IT",
    "sg:address":"07020 Golfo Aranci",
    "sg:city":"Golfo Aranci",
    "sg:classifiers":[
        {
            "category":"Restaurant",
            "type":"Food & Drink"
        }
    ],
    "sg:phone":"+39 0789 46929",
    "sg:postcode":"07020",
    "sg:province":"Olbia-Tempio",
    "sg:tags":[
        "auxiliary",
        "entertainment",
        "premises",
        "related",
        "catering",
        "similar",
        "public",
        "restaurants"
    ],
    "wof:name":"Hotel Gabbiano Azzurro",
    "wof:placetype":"venue"
},
  "geometry": {"coordinates":[9.616757,41.003803],"type":"Point"}
}