{
  "type": "Feature",
  "properties": {
    "iso:country":"IT",
    "sg:address":"91, Via Udine 33017 Tarcento",
    "sg:city":"Tarcento",
    "sg:classifiers":[
        {
            "category":"Professional",
            "subcategory":"Engineering",
            "type":"Services"
        }
    ],
    "sg:phone":"+39 0432 799001",
    "sg:postcode":"33017",
    "sg:province":"Udine",
    "sg:tags":[
        "machine",
        "-",
        "mechanical"
    ],
    "wof:name":"S.i.m.a.c. S.p.a.",
    "wof:placetype":"venue"
},
  "geometry": {"coordinates":[13.199004,46.194164],"type":"Point"}
}