{
  "type": "Feature",
  "properties": {
    "iso:country":"IT",
    "sg:address":"62012 Civitanova Marche",
    "sg:city":"Civitanova Marche",
    "sg:orig_category":"Arredamenti - Produzione E Ingrosso",
    "sg:phone":"+39 0733 812824",
    "sg:postcode":"62012",
    "sg:province":"Macerata",
    "sg:website":"http://www.puntorelaxonline.it",
    "wof:name":"Punto Relax Di Antonino Valenti",
    "wof:placetype":"venue"
},
  "geometry": {"coordinates":[13.728143,43.301533],"type":"Point"}
}