{
  "type": "Feature",
  "properties": {
    "addr:full":"88100 Catanzaro Catanzaro Catanzaro 88100",
    "addr:postcode":"88100;88100",
    "iso:country":"IT",
    "sg:address":"88100 Catanzaro",
    "sg:city":"Catanzaro",
    "sg:orig_category":"Nautica. Ricambi E Componenti Dei Mezzi Di Trasporto",
    "sg:phone":"+39 0961 744034",
    "sg:postcode":"88100",
    "sg:province":"Catanzaro",
    "wof:name":"Duomotori Di Bitonti Giuseppe",
    "wof:placetype":"venue"
},
  "geometry": {"coordinates":[16.591541,38.905209],"type":"Point"}
}