{
  "type": "Feature",
  "properties": {
    "iso:country":"IT",
    "sg:address":"Viale Repubblica, 4 /b; Bondeno; 44012",
    "sg:city":"Bondeno",
    "sg:classifiers":[
        {
            "category":"Banks & Credit Unions",
            "subcategory":"Bank",
            "type":"Services"
        }
    ],
    "sg:phone":"+39 0532 892206",
    "sg:postcode":"44012",
    "sg:province":"Ferrara",
    "wof:name":"Banca Agricola Mantovana",
    "wof:placetype":"venue"
},
  "geometry": {"coordinates":[11.416078,44.885918],"type":"Point"}
}