{
  "type": "Feature",
  "properties": {
    "addr:full":"42043 Taneto Di Gattatico Reggio Nell'Emilia 42043",
    "addr:postcode":"42043;42043",
    "iso:country":"IT",
    "sg:address":"42043 Taneto Di Gattatico",
    "sg:classifiers":[
        {
            "category":"Building & Trades",
            "subcategory":"Construction",
            "type":"Services"
        }
    ],
    "sg:phone":"+39 0522 674121",
    "sg:postcode":"42043",
    "sg:province":"Reggio Nell'Emilia",
    "sg:tags":[
        "rubber",
        "industry",
        "work"
    ],
    "wof:name":"Multicom Srl",
    "wof:placetype":"venue"
},
  "geometry": {"coordinates":[10.627794,44.696228],"type":"Point"}
}