{
  "type": "Feature",
  "properties": {
    "iso:country":"IT",
    "sg:address":"33044 Manzano",
    "sg:city":"Manzano",
    "sg:orig_category":"Arredamento Alberghi",
    "sg:phone":"+39 0432 740071",
    "sg:postcode":"33044",
    "sg:province":"Udine",
    "wof:name":"S-tre Di Sfiligoi Gianni & C. Snc",
    "wof:placetype":"venue"
},
  "geometry": {"coordinates":[13.362219,45.983948],"type":"Point"}
}