{
  "type": "Feature",
  "properties": {
    "iso:country":"IT",
    "sg:address":"Via Censisio 30; Milano; 20154",
    "sg:city":"Milano",
    "sg:classifiers":[
        {
            "category":"Banks & Credit Unions",
            "subcategory":"Bank",
            "type":"Services"
        }
    ],
    "sg:phone":"+39 02 3178 5134",
    "sg:postcode":"20154",
    "sg:province":"Milano",
    "wof:name":"Credito Artigiano",
    "wof:placetype":"venue"
},
  "geometry": {"coordinates":[9.168399,45.487686],"type":"Point"}
}