{
  "type": "Feature",
  "properties": {
    "addr:full":"8, Piazza Sempione 20154 Milano Milano Milano 20154",
    "addr:postcode":"20154;20154",
    "addr:street":"Piazza Sempione",
    "iso:country":"IT",
    "sg:address":"8, Piazza Sempione 20154 Milano",
    "sg:city":"Milano",
    "sg:classifiers":[
        {
            "category":"Banks & Credit Unions",
            "subcategory":"Financial Services",
            "type":"Services"
        }
    ],
    "sg:phone":"+39 02 3310 5312",
    "sg:postcode":"20154",
    "sg:province":"Milano",
    "sg:tags":[
        "banking",
        "finance",
        "insurance"
    ],
    "wof:name":"Soluzioni Assicurative Snc",
    "wof:placetype":"venue"
},
  "geometry": {"coordinates":[9.171993,45.476254],"type":"Point"}
}