{
  "type": "Feature",
  "properties": {
    "addr:full":"10092 Beinasco Beinasco Torino 10092",
    "addr:postcode":"10092;10092",
    "iso:country":"IT",
    "sg:address":"10092 Beinasco",
    "sg:city":"Beinasco",
    "sg:orig_category":"Ricambi E Componenti Dei Mezzi Di Trasporto",
    "sg:phone":"+39 011 349 9205",
    "sg:postcode":"10092",
    "sg:province":"Torino",
    "wof:name":"Amper - Auto (s.r.l.)",
    "wof:placetype":"venue"
},
  "geometry": {"coordinates":[7.600805,45.02882],"type":"Point"}
}