{
  "type": "Feature",
  "properties": {
    "iso:country":"IT",
    "sg:address":"43100 Parma",
    "sg:city":"Parma",
    "sg:orig_category":"Trasporti E Spedizioni Merci",
    "sg:phone":"+39 0521 270470",
    "sg:postcode":"43100",
    "sg:province":"Parma",
    "wof:name":"St 2000 Global Logistic Srl",
    "wof:placetype":"venue"
},
  "geometry": {"coordinates":[10.32296,44.7756],"type":"Point"}
}