{
  "type": "Feature",
  "properties": {
    "iso:country":"IT",
    "sg:address":"39, Via Quattro Novembre 38030 Rovere' Della Luna",
    "sg:classifiers":[
        {
            "category":"Home & Garden",
            "subcategory":"Home Furnishings",
            "type":"Retail Goods"
        }
    ],
    "sg:phone":"+39 0461 658613",
    "sg:postcode":"38030",
    "sg:province":"Trento",
    "sg:tags":[
        "household"
    ],
    "wof:name":"Walter Meinrad (s.a.s.)",
    "wof:placetype":"venue"
},
  "geometry": {"coordinates":[11.119053,46.066738],"type":"Point"}
}