{
  "type": "Feature",
  "properties": {
    "iso:country":"IT",
    "sg:address":"Via Quarto Negroni 10 00040 Cecchina Stazione",
    "sg:classifiers":[
        {
            "category":"Building & Trades",
            "subcategory":"Electrical",
            "type":"Services"
        }
    ],
    "sg:phone":"+39 06 930251",
    "sg:postcode":"00040",
    "sg:province":"Roma",
    "sg:tags":[
        "component",
        "elevator",
        "accessory"
    ],
    "sg:website":"www.dmg.it",
    "wof:name":"D.m.g. Spa",
    "wof:placetype":"venue"
},
  "geometry": {"coordinates":[12.509796,41.892555],"type":"Point"}
}