{
  "type": "Feature",
  "properties": {
    "addr:full":"32, Via Casalmaggiore Case Sparse 26041 Casalmaggiore Casalmaggiore Cremona 26041",
    "addr:postcode":"26041;26041",
    "addr:street":"Via Casalmaggiore",
    "iso:country":"IT",
    "sg:address":"32, Via Casalmaggiore Case Sparse 26041 Casalmaggiore",
    "sg:city":"Casalmaggiore",
    "sg:classifiers":[
        {
            "category":"Professional",
            "subcategory":"Engineering",
            "type":"Services"
        }
    ],
    "sg:phone":"+39 0375 200616",
    "sg:postcode":"26041",
    "sg:province":"Cremona",
    "sg:tags":[
        "machine",
        "-",
        "mechanical"
    ],
    "wof:name":"Laminart Sas Di Minardi Mirko & C.",
    "wof:placetype":"venue"
},
  "geometry": {"coordinates":[10.026135,45.133499],"type":"Point"}
}