{
  "type": "Feature",
  "properties": {
    "iso:country":"IT",
    "sg:address":"15, Piazza Rizzone Corrado 97015 Modica",
    "sg:city":"Modica",
    "sg:classifiers":[
        {
            "category":"Manufacturing",
            "subcategory":"Lumber",
            "type":"Manufacturing & Wholesale Goods"
        }
    ],
    "sg:phone":"+39 0932 942384",
    "sg:postcode":"97015",
    "sg:province":"Ragusa",
    "sg:tags":[
        "wood"
    ],
    "wof:name":"Cicero Francesco S.a.s. Di Cicero Santalena Giuseppe & C.",
    "wof:placetype":"venue"
},
  "geometry": {"coordinates":[14.760893,36.85561],"type":"Point"}
}