{
  "type": "Feature",
  "properties": {
    "iso:country":"IT",
    "sg:address":"51, Via Trieste 35035 Mestrino",
    "sg:city":"Mestrino",
    "sg:classifiers":[
        {
            "category":"Manufacturing",
            "subcategory":"Rubber & Plastics",
            "type":"Manufacturing & Wholesale Goods"
        }
    ],
    "sg:phone":"+39 049 900 0252",
    "sg:postcode":"35035",
    "sg:province":"Padova",
    "wof:name":"Imar (s.p.a.)",
    "wof:placetype":"venue"
},
  "geometry": {"coordinates":[11.7855997086,45.4302215576],"type":"Point"}
}