{
  "type": "Feature",
  "properties": {
    "addr:full":"Via Dell' Acero 16 56022 Castelfranco Di Sotto Castelfranco di Sotto Pisa 56022",
    "addr:housenumber":"16",
    "addr:postcode":"56022;56022",
    "addr:street":"Via Dell ' Acero;Di Sotto Pisa",
    "iso:country":"IT",
    "sg:address":"Via Dell' Acero 16 56022 Castelfranco Di Sotto",
    "sg:city":"Castelfranco di Sotto",
    "sg:classifiers":[
        {
            "category":"Manufacturing",
            "subcategory":"Chemicals & Compounds",
            "type":"Manufacturing & Wholesale Goods"
        }
    ],
    "sg:phone":"+39 0571 471205",
    "sg:postcode":"56022",
    "sg:province":"Pisa",
    "sg:tags":[
        "base"
    ],
    "sg:website":"www.alanchim.it",
    "wof:name":"Alanchim Srl",
    "wof:placetype":"venue"
},
  "geometry": {"coordinates":[10.755135,43.706436],"type":"Point"}
}