{
  "type": "Feature",
  "properties": {
    "iso:country":"IT",
    "sg:address":"Via Dello Spuntone 27 53034 Colle Di Val D'elsa",
    "sg:classifiers":[
        {
            "category":"Manufacturing",
            "subcategory":"Glass & Minerals",
            "type":"Manufacturing & Wholesale Goods"
        }
    ],
    "sg:phone":"+39 0577 929486",
    "sg:postcode":"53034",
    "sg:province":"Siena",
    "sg:tags":[
        "mould",
        "industry"
    ],
    "wof:name":"O.m.v. Snc",
    "wof:placetype":"venue"
},
  "geometry": {"coordinates":[11.1328878403,43.4164085388],"type":"Point"}
}