{
  "type": "Feature",
  "properties": {
    "iso:country":"IT",
    "sg:address":"9, Regione Cravero 10088 Volpiano",
    "sg:city":"Volpiano",
    "sg:classifiers":[
        {
            "category":"Shopping",
            "type":"Retail Goods"
        }
    ],
    "sg:phone":"+39 011 995 2890",
    "sg:postcode":"10088",
    "sg:province":"Torino",
    "sg:tags":[
        "finished",
        "-",
        "metallic"
    ],
    "wof:name":"Guardini S.p.a.",
    "wof:placetype":"venue"
},
  "geometry": {"coordinates":[7.7913131714,45.174407959],"type":"Point"}
}