{
  "type": "Feature",
  "properties": {
    "addr:full":"50134 Firenze Firenze Firenze 50134",
    "addr:postcode":"50134;50134",
    "iso:country":"IT",
    "sg:address":"50134 Firenze",
    "sg:city":"Firenze",
    "sg:orig_category":"Apparecchiature Ed Attrezzature Meccaniche. Ricambi E Componenti Dei Mezzi Di Trasporto",
    "sg:phone":"+39 055 496460",
    "sg:postcode":"50134",
    "sg:province":"Firenze",
    "wof:name":"O.m.c.r.a.",
    "wof:placetype":"venue"
},
  "geometry": {"coordinates":[11.243234,43.791416],"type":"Point"}
}