{
  "type": "Feature",
  "properties": {
    "addr:full":"2, Via Terza Strada 35026 Conselve Conselve Padova 35026",
    "addr:postcode":"35026;35026",
    "addr:street":"Via Terza Strada",
    "iso:country":"IT",
    "sg:address":"2, Via Terza Strada 35026 Conselve",
    "sg:city":"Conselve",
    "sg:classifiers":[
        {
            "category":"Shopping",
            "subcategory":"Stationery & Office Supplies",
            "type":"Retail Goods"
        }
    ],
    "sg:phone":"+39 049 950 0971",
    "sg:postcode":"35026",
    "sg:province":"Padova",
    "sg:tags":[
        "professional"
    ],
    "wof:name":"Gfg S.r.l",
    "wof:placetype":"venue"
},
  "geometry": {"coordinates":[11.8955583572,45.2045516968],"type":"Point"}
}