{
  "type": "Feature",
  "properties": {
    "addr:full":"Centro Commerciale Verdena 1 29010 Castelvetro Piacentino Castelvetro Piacentino Piacenza 29010",
    "addr:housenumber":"1",
    "addr:postcode":"29010;29010",
    "addr:street":"Piacentino",
    "iso:country":"IT",
    "sg:address":"Centro Commerciale Verdena 1 29010 Castelvetro Piacentino",
    "sg:city":"Castelvetro Piacentino",
    "sg:classifiers":[
        {
            "category":"Communications",
            "subcategory":"Film & Video Production",
            "type":"Services"
        }
    ],
    "sg:phone":"+39 0523 823207",
    "sg:postcode":"29010",
    "sg:province":"Piacenza",
    "sg:tags":[
        "ceramic",
        "processing"
    ],
    "wof:name":"Porcellane Franchi Di Alessi Marta",
    "wof:placetype":"venue"
},
  "geometry": {"coordinates":[9.695142,45.053772],"type":"Point"}
}