{
  "type": "Feature",
  "properties": {
    "addr:full":"30174 Venezia Venezia Venezia 30174",
    "addr:postcode":"30174;30174",
    "iso:country":"IT",
    "sg:address":"30174 Venezia",
    "sg:city":"Venezia",
    "sg:orig_category":"Articoli Da Regalo. Arte Ed Artigianato Artistico",
    "sg:phone":"+39 041 984388",
    "sg:postcode":"30174",
    "sg:province":"Venezia",
    "wof:name":"De Martino Srl",
    "wof:placetype":"venue"
},
  "geometry": {"coordinates":[12.21824,45.506252],"type":"Point"}
}