{
  "type": "Feature",
  "properties": {
    "iso:country":"IT",
    "sg:address":"20, Via Lombardi Giovanni 80141 Napoli",
    "sg:city":"Napoli",
    "sg:classifiers":[
        {
            "category":"Manufacturing",
            "subcategory":"Metals",
            "type":"Manufacturing & Wholesale Goods"
        }
    ],
    "sg:phone":"+39 081 599 0979",
    "sg:postcode":"80141",
    "sg:province":"Napoli",
    "sg:tags":[
        "metallurgy",
        "metalworking"
    ],
    "wof:name":"Telese S.r.l.",
    "wof:placetype":"venue"
},
  "geometry": {"coordinates":[14.2662162781,40.8762130737],"type":"Point"}
}