{
  "type": "Feature",
  "properties": {
    "addr:full":"61015 Novafeltria Novafeltria Pesaro E Urbino 61015",
    "addr:postcode":"61015;61015",
    "iso:country":"IT",
    "sg:address":"61015 Novafeltria",
    "sg:city":"Novafeltria",
    "sg:orig_category":"Pubblica Amministrazione",
    "sg:phone":"+39 0541 921897",
    "sg:postcode":"61015",
    "sg:province":"Pesaro E Urbino",
    "wof:name":"Comunita' Montana Alta Valmarecchia Zona A",
    "wof:placetype":"venue"
},
  "geometry": {"coordinates":[12.5298032761,43.633556366],"type":"Point"}
}