{
  "type": "Feature",
  "properties": {
    "addr:full":"10154 Torino Torino Torino 10154",
    "addr:postcode":"10154;10154",
    "iso:country":"IT",
    "sg:address":"10154 Torino",
    "sg:city":"Torino",
    "sg:orig_category":"Cinematografia E Radiotelevisione",
    "sg:phone":"+39 011 246 2074",
    "sg:postcode":"10154",
    "sg:province":"Torino",
    "wof:name":"Multimedia S.r.l.",
    "wof:placetype":"venue"
},
  "geometry": {"coordinates":[7.585036,45.063278],"type":"Point"}
}