{
  "type": "Feature",
  "properties": {
    "iso:country":"IT",
    "sg:address":"4, Via Arzari 35011 Campodarsego",
    "sg:city":"Campodarsego",
    "sg:classifiers":[
        {
            "category":"Shopping",
            "type":"Retail Goods"
        }
    ],
    "sg:phone":"+39 049 556 4483",
    "sg:postcode":"35011",
    "sg:province":"Padova",
    "sg:tags":[
        "finished",
        "-",
        "metallic"
    ],
    "wof:name":"Mollificio Zandarin Snc Di Zandarin Oscar Giampaolo & C.",
    "wof:placetype":"venue"
},
  "geometry": {"coordinates":[11.9525375366,45.5116729736],"type":"Point"}
}