{
  "type": "Feature",
  "properties": {
    "iso:country":"IT",
    "sg:address":"64100 Teramo",
    "sg:city":"Teramo",
    "sg:orig_category":"Ospedali E Servizi Sanitari",
    "sg:phone":"+39 0861 3321",
    "sg:postcode":"64100",
    "sg:province":"Teramo",
    "sg:website":"http://www.izs.it",
    "wof:name":"Istituto Zooprofilattico Sperimentale Dell'abruzzo E Del Molise 'g. Caporale'",
    "wof:placetype":"venue"
},
  "geometry": {"coordinates":[13.709796,42.656151],"type":"Point"}
}