{
  "type": "Feature",
  "properties": {
    "addr:full":"Localita' Bisone 24034 Cisano Bergamasco Cisano Bergamasco Bergamo 24034",
    "addr:postcode":"24034;24034",
    "addr:street":"Localita ' Bisone",
    "iso:country":"IT",
    "sg:address":"Localita' Bisone 24034 Cisano Bergamasco",
    "sg:city":"Cisano Bergamasco",
    "sg:classifiers":[
        {
            "category":"Shopping",
            "type":"Retail Goods"
        }
    ],
    "sg:phone":"+39 39035781769",
    "sg:postcode":"24034",
    "sg:province":"Bergamo",
    "sg:tags":[
        "finished",
        "-",
        "metallic"
    ],
    "wof:name":"Elettrosaldati Bisone (s.n.c.)",
    "wof:placetype":"venue"
},
  "geometry": {"coordinates":[9.4848670959,45.7374191284],"type":"Point"}
}