{
  "type": "Feature",
  "properties": {
    "iso:country":"IT",
    "sg:address":"24, Traversa I Spiana' 37138 Verona",
    "sg:city":"Verona",
    "sg:classifiers":[
        {
            "category":"Manufacturing",
            "subcategory":"Rubber & Plastics",
            "type":"Manufacturing & Wholesale Goods"
        }
    ],
    "sg:phone":"+39 39045567785",
    "sg:postcode":"37138",
    "sg:province":"Verona",
    "wof:name":"Fm Magalini (s.r.l.)",
    "wof:placetype":"venue"
},
  "geometry": {"coordinates":[10.9641838074,45.4271430969],"type":"Point"}
}