{
  "type": "Feature",
  "properties": {
    "iso:country":"IT",
    "sg:address":"10127 Torino",
    "sg:city":"Torino",
    "sg:orig_category":"Arredamenti E Mobili Professionali. Arredi Ed Attrezzature Per Uffici",
    "sg:phone":"+39 011 674532",
    "sg:postcode":"10127",
    "sg:province":"Torino",
    "wof:name":"Samar (s.r.l.)",
    "wof:placetype":"venue"
},
  "geometry": {"coordinates":[7.660998,45.02087],"type":"Point"}
}