{
  "type": "Feature",
  "properties": {
    "iso:country":"IT",
    "sg:address":"48100 Ravenna",
    "sg:city":"Piangipane",
    "sg:classifiers":[
        {
            "category":"Retail",
            "subcategory":"Storage",
            "type":"Services"
        }
    ],
    "sg:phone":"+39 0544 415013",
    "sg:postcode":"48100",
    "sg:province":"Ravenna",
    "sg:tags":[
        "services",
        "equipment",
        "handling",
        "refrigeration"
    ],
    "wof:name":"Eurofreddo Soc.coop.r.l.",
    "wof:placetype":"venue"
},
  "geometry": {"coordinates":[12.082213,44.416805],"type":"Point"}
}