{
  "type": "Feature",
  "properties": {
    "iso:country":"IT",
    "sg:address":"40133 Bologna",
    "sg:city":"Bologna",
    "sg:orig_category":"Utensili Meccanici E Materiali",
    "sg:phone":"+39 051 619 0121",
    "sg:postcode":"40133",
    "sg:province":"Bologna",
    "wof:name":"U.t.a.m. (s.n.c.)",
    "wof:placetype":"venue"
},
  "geometry": {"coordinates":[11.293683,44.503895],"type":"Point"}
}