{
  "type": "Feature",
  "properties": {
    "iso:country":"IT",
    "sg:address":"41100 Modena",
    "sg:city":"Modena",
    "sg:orig_category":"Etichette",
    "sg:phone":"+39 059 251386",
    "sg:postcode":"41100",
    "sg:province":"Modena",
    "wof:name":"Etichettificio Tiesse Snc",
    "wof:placetype":"venue"
},
  "geometry": {"coordinates":[10.940104,44.549126],"type":"Point"}
}