{
  "type": "Feature",
  "properties": {
    "iso:country":"IT",
    "sg:address":"9, V. V. Giardina 97016 Pozzallo",
    "sg:city":"Pozzallo",
    "sg:classifiers":[
        {
            "category":"Food & Beverages",
            "subcategory":"Groceries & Convenience Stores",
            "type":"Retail Goods"
        }
    ],
    "sg:phone":"+39 0932 798676",
    "sg:postcode":"97016",
    "sg:province":"Ragusa",
    "sg:tags":[
        "drink"
    ],
    "sg:website":"http://www.tastesicily.com",
    "wof:name":"Taste Sicily Srl",
    "wof:placetype":"venue"
},
  "geometry": {"coordinates":[14.728503,36.925911],"type":"Point"}
}