{
  "type": "Feature",
  "properties": {
    "addr:full":"25100 Brescia BS",
    "addr:postcode":"25100",
    "iso:country":"IT",
    "sg:address":"25100 Brescia",
    "sg:orig_category":"Prodotti Alimentari",
    "sg:phone":"+39 030 354 3857",
    "sg:province":"BS",
    "wof:name":"Ortofrutta Charlie",
    "wof:placetype":"venue"
},
  "geometry": {"coordinates":[10.1853752136,45.5127029419],"type":"Point"}
}