{
  "type": "Feature",
  "properties": {
    "addr:full":"25021 Bagnolo Mella Bagnolo Mella Brescia 25021",
    "addr:postcode":"25021;25021",
    "iso:country":"IT",
    "sg:address":"25021 Bagnolo Mella",
    "sg:city":"Bagnolo Mella",
    "sg:orig_category":"Automobili E Mezzi Di Trasporto. Riparazione Dei Mezzi Di Trasporto",
    "sg:phone":"+39 030 682 9311",
    "sg:postcode":"25021",
    "sg:province":"Brescia",
    "wof:name":"Bai Antincendi International",
    "wof:placetype":"venue"
},
  "geometry": {"coordinates":[10.182368,45.390373],"type":"Point"}
}