{
  "type": "Feature",
  "properties": {
    "iso:country":"IT",
    "sg:address":"80143 Napoli",
    "sg:city":"Napoli",
    "sg:orig_category":"Manufacturers: Prefabbricati. Servizi E Lavori Per Ecologia E Smaltimento Rifiuti",
    "sg:phone":"+39 081 759 3526",
    "sg:postcode":"80143",
    "sg:province":"Napoli",
    "wof:name":"Agizza Antonio",
    "wof:placetype":"venue"
},
  "geometry": {"coordinates":[14.300841,40.871803],"type":"Point"}
}