{
  "type": "Feature",
  "properties": {
    "iso:country":"IT",
    "sg:address":"20142 Milano",
    "sg:city":"Milano",
    "sg:orig_category":"Medici. Assicurazioni E Servizi Assicurativi. Avvocati, Notai E Servizi Legali. Professionisti - Studi E Servizi Ed Associazioni Di Interesse Aziendale",
    "sg:phone":"+39 02 8950 1206",
    "sg:postcode":"20142",
    "sg:province":"Milano",
    "wof:name":"Corsini Marco",
    "wof:placetype":"venue"
},
  "geometry": {"coordinates":[9.1627616882,45.4174613953],"type":"Point"}
}