{
  "type": "Feature",
  "properties": {
    "iso:country":"IT",
    "sg:address":"Via Artigiani 24060 Brusaporto",
    "sg:city":"Brusaporto",
    "sg:classifiers":[
        {
            "category":"Professional",
            "subcategory":"Engineering",
            "type":"Services"
        }
    ],
    "sg:phone":"+39 39035682645",
    "sg:postcode":"24060",
    "sg:province":"Bergamo",
    "sg:tags":[
        "machine",
        "-",
        "mechanical"
    ],
    "wof:name":"Abv S.r.l.",
    "wof:placetype":"venue"
},
  "geometry": {"coordinates":[9.745475,45.667049],"type":"Point"}
}