{
  "type": "Feature",
  "properties": {
    "iso:country":"IT",
    "sg:address":"50018 Scandicci",
    "sg:city":"Scandicci",
    "sg:orig_category":"Cine-foto-ottica. Articoli Medico-sanitari Ed Ortopedici. Impianti, Attrezzature E Forniture Sanitarie Ed Ospedaliere",
    "sg:phone":"+39 055 755746",
    "sg:postcode":"50018",
    "sg:province":"Firenze",
    "wof:name":"Idealottica E C. Snc",
    "wof:placetype":"venue"
},
  "geometry": {"coordinates":[11.172002,43.764496],"type":"Point"}
}