{
  "type": "Feature",
  "properties": {
    "iso:country":"IT",
    "sg:address":"66034 Lanciano",
    "sg:city":"Lanciano",
    "sg:classifiers":[
        {
            "category":"Professional",
            "subcategory":"Advertising",
            "type":"Services"
        }
    ],
    "sg:phone":"+39 0872 724000",
    "sg:postcode":"66034",
    "sg:province":"Chieti",
    "sg:tags":[
        "marketing",
        "communication"
    ],
    "wof:name":"Open Service Di Martelli Stefania",
    "wof:placetype":"venue"
},
  "geometry": {"coordinates":[14.39514,42.224926],"type":"Point"}
}