{
  "type": "Feature",
  "properties": {
    "addr:full":"45030 Crespino Crespino Rovigo 45030",
    "addr:postcode":"45030;45030",
    "addr:street":"Crespino",
    "iso:country":"IT",
    "sg:address":"45030 Crespino",
    "sg:city":"Crespino",
    "sg:orig_category":"Automobili E Mezzi Di Trasporto",
    "sg:phone":"+39 0425 780489",
    "sg:postcode":"45030",
    "sg:province":"Rovigo",
    "wof:name":"Fratelli Ongaro S.n.c. Di Ongaro Davide & C.",
    "wof:placetype":"venue"
},
  "geometry": {"coordinates":[11.889239,44.987431],"type":"Point"}
}