{
  "type": "Feature",
  "properties": {
    "iso:country":"IT",
    "sg:address":"00167 Roma",
    "sg:city":"Roma",
    "sg:orig_category":"Fotoriproduttori E Fotocopiatrici",
    "sg:phone":"+39 06 3938 8757",
    "sg:postcode":"00167",
    "sg:province":"Roma",
    "sg:website":"http://www.romaprocess.it",
    "wof:name":"Romaprocess Srl",
    "wof:placetype":"venue"
},
  "geometry": {"coordinates":[12.4363327026,41.8998756409],"type":"Point"}
}