{
  "type": "Feature",
  "properties": {
    "iso:country":"IT",
    "sg:address":"107, Via Mure 31030 Altivole",
    "sg:city":"Altivole",
    "sg:classifiers":[
        {
            "category":"Shopping",
            "subcategory":"Clothing, Apparel, & Fashions",
            "type":"Retail Goods"
        }
    ],
    "sg:phone":"+39 0423 915279",
    "sg:postcode":"31030",
    "sg:province":"Treviso",
    "sg:tags":[
        "clothes"
    ],
    "wof:name":"Linea 5 S.r.l.",
    "wof:placetype":"venue"
},
  "geometry": {"coordinates":[11.975228,45.757065],"type":"Point"}
}