{
  "type": "Feature",
  "properties": {
    "addr:full":"34123 Trieste Trieste Trieste 34123",
    "addr:postcode":"34123;34123",
    "iso:country":"IT",
    "sg:address":"34123 Trieste",
    "sg:city":"Trieste",
    "sg:orig_category":"Impiantistica E Prodotti Tecnologici Per Edilizia. Forniture Industriali Per Prevenzione, Controllo E Sicurezza",
    "sg:phone":"+39 040 311439",
    "sg:postcode":"34123",
    "sg:province":"Trieste",
    "wof:name":"Firest Srl",
    "wof:placetype":"venue"
},
  "geometry": {"coordinates":[13.760844,45.645683],"type":"Point"}
}