{
  "type": "Feature",
  "properties": {
    "addr:full":"19, V. Pacinotti 00015 Monterotondo Scalo Monterotondo Roma 00015",
    "addr:housenumber":"19",
    "addr:postcode":"00015;roma 00015",
    "addr:street":"V. Pacinotti",
    "iso:country":"IT",
    "sg:address":"19, V. Pacinotti 00015 Monterotondo Scalo",
    "sg:city":"Monterotondo",
    "sg:classifiers":[
        {
            "category":"Banks & Credit Unions",
            "subcategory":"Investment Brokerage",
            "type":"Services"
        }
    ],
    "sg:phone":"+39 39069060935",
    "sg:postcode":"00015",
    "sg:province":"Roma",
    "sg:tags":[
        "-",
        "transport",
        "related"
    ],
    "sg:website":"http://www.intersped.it:ws_end: :mark:ws:http://www.paginegialle.it/intersped-",
    "wof:name":"Intersped Srl",
    "wof:placetype":"venue"
},
  "geometry": {"coordinates":[12.591003,42.075809],"type":"Point"}
}