{
  "type": "Feature",
  "properties": {
    "iso:country":"IT",
    "sg:address":"Via Del Commercio 16 37066 Sommacampagna",
    "sg:city":"Sommacampagna",
    "sg:classifiers":[
        {
            "category":"Shopping",
            "subcategory":"Shoes",
            "type":"Retail Goods"
        }
    ],
    "sg:phone":"+39 045 515534",
    "sg:postcode":"37066",
    "sg:province":"Verona",
    "sg:tags":[
        "men's",
        "boot"
    ],
    "sg:website":"www.dariododoni.com",
    "wof:name":"Calzaturificio Catullo S.r.l.",
    "wof:placetype":"venue"
},
  "geometry": {"coordinates":[10.8466796875,45.4047431946],"type":"Point"}
}