{
  "type": "Feature",
  "properties": {
    "iso:country":"IT",
    "sg:address":"36100 Vicenza",
    "sg:city":"Vicenza",
    "sg:orig_category":"Informatica - Consulenza E Servizi. Editoria",
    "sg:phone":"+39 0444 288288",
    "sg:postcode":"36100",
    "sg:province":"Vicenza",
    "sg:website":"http://www.edaco.it",
    "wof:name":"Edaco Consulting Srl",
    "wof:placetype":"venue"
},
  "geometry": {"coordinates":[11.5346832275,45.3215026855],"type":"Point"}
}