{
  "type": "Feature",
  "properties": {
    "iso:country":"IT",
    "sg:address":"9, Via Giolitti Colombe' 10070 Robassomero",
    "sg:city":"Robassomero",
    "sg:classifiers":[
        {
            "category":"Manufacturing",
            "subcategory":"Metals",
            "type":"Manufacturing & Wholesale Goods"
        }
    ],
    "sg:phone":"+39 011 923 5153",
    "sg:postcode":"10070",
    "sg:province":"Torino",
    "sg:tags":[
        "metallurgy",
        "metalworking"
    ],
    "wof:name":"F.i.m. S.a.s.",
    "wof:placetype":"venue"
},
  "geometry": {"coordinates":[7.5923423767,45.1773071289],"type":"Point"}
}