{
  "type": "Feature",
  "properties": {
    "addr:full":"24010 Ubiale Clanezzo Clanezzo Bergamo 24010",
    "addr:postcode":"24010;24010",
    "addr:street":"Clanezzo Clanezzo",
    "iso:country":"IT",
    "sg:address":"24010 Ubiale Clanezzo",
    "sg:city":"Clanezzo",
    "sg:orig_category":"Alberghi",
    "sg:phone":"+39 035 641567",
    "sg:postcode":"24010",
    "sg:province":"Bergamo",
    "wof:name":"Il Castello Di Clanezzo Srl",
    "wof:placetype":"venue"
},
  "geometry": {"coordinates":[9.606172,45.734219],"type":"Point"}
}