{
  "type": "Feature",
  "properties": {
    "iso:country":"IT",
    "sg:address":"Via F.lli Bandi4era; Rende; 87036",
    "sg:city":"Rende",
    "sg:classifiers":[
        {
            "category":"Banks & Credit Unions",
            "subcategory":"Bank",
            "type":"Services"
        }
    ],
    "sg:phone":"+39 0984 466300",
    "sg:postcode":"87036",
    "sg:province":"Cosenza",
    "wof:name":"Credito Italiano Spa",
    "wof:placetype":"venue"
},
  "geometry": {"coordinates":[16.216913,39.357628],"type":"Point"}
}