{
  "type": "Feature",
  "properties": {
    "iso:country":"IT",
    "sg:address":"Via C. Cugnod, 7; Brusson; 11022",
    "sg:city":"Brusson",
    "sg:classifiers":[
        {
            "category":"Banks & Credit Unions",
            "subcategory":"Bank",
            "type":"Services"
        }
    ],
    "sg:phone":"+39 0125 300130",
    "sg:postcode":"11022",
    "sg:province":"Aosta",
    "wof:name":"Cassa Di Risparmio Di Torino",
    "wof:placetype":"venue"
},
  "geometry": {"coordinates":[7.733191,45.758228],"type":"Point"}
}