{
  "type": "Feature",
  "properties": {
    "iso:country":"IT",
    "sg:address":"25046 Cazzago S. Martino",
    "sg:orig_category":"Gru - Costruzione E Commercio",
    "sg:phone":"+39 030 775 1509",
    "sg:postcode":"25046",
    "sg:province":"Brescia",
    "wof:name":"Minelli Srl",
    "wof:placetype":"venue"
},
  "geometry": {"coordinates":[10.033444,45.572075],"type":"Point"}
}