{
  "type": "Feature",
  "properties": {
    "iso:country":"IT",
    "sg:address":"1/3, Via Guido Volpato 30020 Quarto D'altino",
    "sg:classifiers":[
        {
            "category":"Manufacturing",
            "subcategory":"Motor Vehicles & Parts",
            "type":"Manufacturing & Wholesale Goods"
        }
    ],
    "sg:phone":"+39 0422 824143",
    "sg:postcode":"30020",
    "sg:province":"Venezia",
    "sg:tags":[
        "engine"
    ],
    "wof:name":"Officina C.c.c. Di Ferrarese Carlo & Chiara (s.n.c.)",
    "wof:placetype":"venue"
},
  "geometry": {"coordinates":[12.352821,45.580597],"type":"Point"}
}