{
  "type": "Feature",
  "properties": {
    "iso:country":"IT",
    "sg:address":"Via Vivaio 60030 Maiolati Spontini",
    "sg:city":"Maiolati Spontini",
    "sg:classifiers":[
        {
            "category":"Food & Beverages",
            "subcategory":"Liquor & Beverages",
            "type":"Retail Goods"
        }
    ],
    "sg:phone":"+39 0731 700297",
    "sg:postcode":"60030",
    "sg:province":"Ancona",
    "sg:tags":[
        "wine",
        "italian"
    ],
    "sg:website":"www.monteschiavo.it",
    "wof:name":"La Vite Spa",
    "wof:placetype":"venue"
},
  "geometry": {"coordinates":[13.170453,43.50885],"type":"Point"}
}