{
  "type": "Feature",
  "properties": {
    "iso:country":"IT",
    "sg:address":"62, V. Cascina Pontevica 25010 Brescia",
    "sg:classifiers":[
        {
            "category":"Shopping",
            "type":"Retail Goods"
        }
    ],
    "sg:phone":"+39 030 216 0868",
    "sg:postcode":"25010",
    "sg:province":"Brescia",
    "sg:tags":[
        "finished",
        "-",
        "metallic"
    ],
    "sg:website":"http://www.parafancar.it:ws_end: :mark:ws:http://www.paginegialle.it/parafancar",
    "wof:name":"Parafancar Snc",
    "wof:placetype":"venue"
},
  "geometry": {"coordinates":[10.2371492386,45.4925842285],"type":"Point"}
}