{
  "type": "Feature",
  "properties": {
    "addr:full":"00152 Roma Roma Roma 00152",
    "addr:postcode":"00152;00152",
    "iso:country":"IT",
    "sg:address":"00152 Roma",
    "sg:city":"Roma",
    "sg:classifiers":[
        {
            "category":"Health Services",
            "subcategory":"Health Practitioner",
            "type":"Services"
        }
    ],
    "sg:phone":"+39 06 588 0861",
    "sg:postcode":"00152",
    "sg:province":"Roma",
    "sg:tags":[
        "medici"
    ],
    "wof:name":"Valenti Gabriele",
    "wof:placetype":"venue"
},
  "geometry": {"coordinates":[12.4629974365,41.8774261475],"type":"Point"}
}