{
  "type": "Feature",
  "properties": {
    "iso:country":"IT",
    "sg:address":"30010 Campagna Lupia",
    "sg:city":"Campagna Lupia",
    "sg:orig_category":"Imprese Di Costruzioni Civili Ed Industriali",
    "sg:phone":"+39 041 518 5061",
    "sg:postcode":"30010",
    "sg:province":"Venezia",
    "wof:name":"Locapal Srl",
    "wof:placetype":"venue"
},
  "geometry": {"coordinates":[12.1317100525,45.388507843],"type":"Point"}
}