{
  "type": "Feature",
  "properties": {
    "addr:full":"16043 Chiavari Chiavari Genova 16043",
    "addr:postcode":"16043;16043",
    "iso:country":"IT",
    "sg:address":"16043 Chiavari",
    "sg:city":"Chiavari",
    "sg:orig_category":"Scuole E Servizi Scolastici",
    "sg:phone":"+39 0185 300645",
    "sg:postcode":"16043",
    "sg:province":"Genova",
    "wof:name":"Istituto Suore Santa Marta",
    "wof:placetype":"venue"
},
  "geometry": {"coordinates":[9.0394,44.381145],"type":"Point"}
}