{
  "type": "Feature",
  "properties": {
    "addr:full":"36, V. Galvani 41037 Mirandola Mirandola Modena 41037",
    "addr:housenumber":"36",
    "addr:postcode":"41037;41037",
    "addr:street":"V. Galvani",
    "iso:country":"IT",
    "sg:address":"36, V. Galvani 41037 Mirandola",
    "sg:city":"Mirandola",
    "sg:classifiers":[
        {
            "category":"Manufacturing",
            "subcategory":"Rubber & Plastics",
            "type":"Manufacturing & Wholesale Goods"
        }
    ],
    "sg:phone":"+39 39053521979",
    "sg:postcode":"41037",
    "sg:province":"Modena",
    "sg:website":"http://www.nichelcromo.com:ws_end: :mark:ws:http://www.paginegialle.it/nichelcrom",
    "wof:name":"Nichel Cromo",
    "wof:placetype":"venue"
},
  "geometry": {"coordinates":[10.9252195358,44.6470794678],"type":"Point"}
}