{
  "type": "Feature",
  "properties": {
    "addr:full":"13, Via Mario Vitalini 25032 Chiari Chiari Brescia 25032",
    "addr:postcode":"25032;25032",
    "addr:street":"Via Mario Vitalini",
    "iso:country":"IT",
    "sg:address":"13, Via Mario Vitalini 25032 Chiari",
    "sg:city":"Chiari",
    "sg:classifiers":[
        {
            "category":"Manufacturing",
            "subcategory":"Lumber",
            "type":"Manufacturing & Wholesale Goods"
        }
    ],
    "sg:phone":"+39 39030713026",
    "sg:postcode":"25032",
    "sg:province":"Brescia",
    "sg:tags":[
        "wood"
    ],
    "wof:name":"Italserramenti S.r.l.",
    "wof:placetype":"venue"
},
  "geometry": {"coordinates":[10.222958,45.539829],"type":"Point"}
}