{
  "type": "Feature",
  "properties": {
    "addr:full":"Via San Gerolamo 6 95024 Acireale Acireale Catania 95024",
    "addr:housenumber":"6",
    "addr:postcode":"95024;95024",
    "addr:street":"Via San Gerolamo",
    "iso:country":"IT",
    "sg:address":"Via San Gerolamo 6 95024 Acireale",
    "sg:city":"Acireale",
    "sg:classifiers":[
        {
            "category":"Food & Beverages",
            "subcategory":"Fruits & Vegetables",
            "type":"Retail Goods"
        }
    ],
    "sg:phone":"+39 095 608388",
    "sg:postcode":"95024",
    "sg:province":"Catania",
    "wof:name":"G. Privitera Di Venera Pennisi",
    "wof:placetype":"venue"
},
  "geometry": {"coordinates":[15.1664934158,37.586353302],"type":"Point"}
}