{
  "type": "Feature",
  "properties": {
    "addr:full":"74013 Ginosa Ginosa Taranto 74013",
    "addr:postcode":"74013;74013",
    "addr:street":"Ginosa Taranto",
    "iso:country":"IT",
    "sg:address":"74013 Ginosa",
    "sg:city":"Ginosa",
    "sg:orig_category":"Ospedali E Servizi Sanitari",
    "sg:phone":"+39 099 829 1871",
    "sg:postcode":"74013",
    "sg:province":"Taranto",
    "wof:name":"Laboratorio Di Analisi Ginosino Srl",
    "wof:placetype":"venue"
},
  "geometry": {"coordinates":[16.753798,40.576965],"type":"Point"}
}