{
  "type": "Feature",
  "properties": {
    "iso:country":"IT",
    "sg:address":"20069 Vaprio D'adda",
    "sg:orig_category":"Arredi Ed Attrezzature Per Attivita' Commerciali Ed Artigianali",
    "sg:phone":"+39 02 9096 5067",
    "sg:postcode":"20069",
    "sg:province":"Milano",
    "wof:name":"Lotti Mauro",
    "wof:placetype":"venue"
},
  "geometry": {"coordinates":[9.579993,45.599545],"type":"Point"}
}