{
  "type": "Feature",
  "properties": {
    "iso:country":"IT",
    "sg:address":"20122 Milano",
    "sg:city":"Milano",
    "sg:orig_category":"Librerie",
    "sg:phone":"+39 02 5519 2134",
    "sg:postcode":"20122",
    "sg:province":"Milano",
    "sg:website":"http://www.lagiuridica.it",
    "wof:name":"La Giuridica Di Porta Vittoria",
    "wof:placetype":"venue"
},
  "geometry": {"coordinates":[9.2053,45.462521],"type":"Point"}
}