{
  "type": "Feature",
  "properties": {
    "iso:country":"IT",
    "sg:address":"40, V. Giusti 20033 Desio",
    "sg:city":"Desio",
    "sg:classifiers":[
        {
            "category":"Home & Garden",
            "subcategory":"Home Furnishings",
            "type":"Retail Goods"
        }
    ],
    "sg:phone":"+39 036 230 8333",
    "sg:postcode":"20033",
    "sg:province":"Milano",
    "sg:tags":[
        "household"
    ],
    "sg:website":"http://www.gagliazzodino.com:ws_end: :mark:ws:http://www.paginegialle.it/gagliazzo",
    "wof:name":"Gagliazzo Dino Snc",
    "wof:placetype":"venue"
},
  "geometry": {"coordinates":[9.188141,45.463688],"type":"Point"}
}