{
  "type": "Feature",
  "properties": {
    "iso:country":"IT",
    "sg:address":"20123 Milano",
    "sg:city":"Milano",
    "sg:orig_category":"Ospedali E Servizi Sanitari. Servizi Sociali",
    "sg:phone":"+39 02 7201 0348",
    "sg:postcode":"20123",
    "sg:province":"Milano",
    "wof:name":"E.t.i.c.a.",
    "wof:placetype":"venue"
},
  "geometry": {"coordinates":[9.186164,45.46368],"type":"Point"}
}