{
  "type": "Feature",
  "properties": {
    "addr:full":"39, Via Trento 20017 Rho Rho Milano 20017",
    "addr:postcode":"20017;20017",
    "addr:street":"Via Trento",
    "iso:country":"IT",
    "sg:address":"39, Via Trento 20017 Rho",
    "sg:city":"Rho",
    "sg:classifiers":[
        {
            "category":"Manufacturing",
            "subcategory":"Rubber & Plastics",
            "type":"Manufacturing & Wholesale Goods"
        }
    ],
    "sg:phone":"+39 39029326131",
    "sg:postcode":"20017",
    "sg:province":"Milano",
    "wof:name":"Quadrant Epp Italia S.r.l.",
    "wof:placetype":"venue"
},
  "geometry": {"coordinates":[9.0993337631,45.5430450439],"type":"Point"}
}