{
  "type": "Feature",
  "properties": {
    "iso:country":"IT",
    "sg:address":"Piazza Marconi 11; Zevio; 37059",
    "sg:city":"Zevio",
    "sg:classifiers":[
        {
            "category":"Banks & Credit Unions",
            "subcategory":"Bank",
            "type":"Services"
        }
    ],
    "sg:phone":"+39 045 605 0477",
    "sg:postcode":"37059",
    "sg:province":"Verona",
    "wof:name":"Credito Bergamasco Spa",
    "wof:placetype":"venue"
},
  "geometry": {"coordinates":[11.134319,45.372272],"type":"Point"}
}