{
  "type": "Feature",
  "properties": {
    "iso:country":"IT",
    "sg:address":"47042 Cesenatico",
    "sg:city":"Cesenatico",
    "sg:orig_category":"Materassi - Vendita Al Dettaglio",
    "sg:phone":"+39 0547 82039",
    "sg:postcode":"47042",
    "sg:province":"Forl\u00ec-Cesena",
    "wof:name":"Casa Del Materasso",
    "wof:placetype":"venue"
},
  "geometry": {"coordinates":[12.236576,44.135292],"type":"Point"}
}