{
  "type": "Feature",
  "properties": {
    "iso:country":"IT",
    "sg:address":"20032 Cormano",
    "sg:city":"Cormano",
    "sg:orig_category":"Macchine, Impianti E Forniture Per Industria Grafica, Cartaria E Cartotecnica",
    "sg:phone":"+39 02 6630 1914",
    "sg:postcode":"20032",
    "sg:province":"Milano",
    "wof:name":"R.m. Di Vignati Rita Valentina",
    "wof:placetype":"venue"
},
  "geometry": {"coordinates":[9.175701,45.538383],"type":"Point"}
}