{
  "type": "Feature",
  "properties": {
    "iso:country":"IT",
    "sg:address":"00186 Roma",
    "sg:city":"Roma",
    "sg:orig_category":"Trattamenti Termici E Superficiali Metalli, Galvanotecnica",
    "sg:phone":"+39 06 322 7098",
    "sg:postcode":"00186",
    "sg:province":"Roma",
    "wof:name":"Zagarola Ubaldo",
    "wof:placetype":"venue"
},
  "geometry": {"coordinates":[12.476534,41.906956],"type":"Point"}
}