{
  "type": "Feature",
  "properties": {
    "iso:country":"IT",
    "sg:address":"16121 Genova",
    "sg:city":"Genova",
    "sg:orig_category":"Scuole E Servizi Scolastici. Ospedali E Servizi Sanitari",
    "sg:phone":"+39 010 595 4276",
    "sg:postcode":"16121",
    "sg:province":"Genova",
    "wof:name":"Azienda Usl 3 Genovese",
    "wof:placetype":"venue"
},
  "geometry": {"coordinates":[8.935081,44.406364],"type":"Point"}
}