{
  "type": "Feature",
  "properties": {
    "iso:country":"IT",
    "sg:address":"17, Via Prove 44021 Codigoro",
    "sg:city":"Codigoro",
    "sg:classifiers":[
        {
            "category":"Real Estate",
            "subcategory":"Architect",
            "type":"Services"
        }
    ],
    "sg:phone":"+39 0533 712218",
    "sg:postcode":"44021",
    "sg:province":"Ferrara",
    "sg:tags":[
        "textile",
        "clothing"
    ],
    "wof:name":"E. & E.",
    "wof:placetype":"venue"
},
  "geometry": {"coordinates":[12.12016,44.816086],"type":"Point"}
}