{
  "type": "Feature",
  "properties": {
    "addr:full":"Corso Roma 5; Alessandria; 15100 Alessandria Alessandria 15100",
    "addr:housenumber":"5",
    "addr:postcode":"15100;15100",
    "addr:street":"Corso Roma",
    "iso:country":"IT",
    "sg:address":"Corso Roma 5; Alessandria; 15100",
    "sg:city":"Alessandria",
    "sg:classifiers":[
        {
            "category":"Banks & Credit Unions",
            "subcategory":"Bank",
            "type":"Services"
        }
    ],
    "sg:phone":"+39 0131 201111",
    "sg:postcode":"15100",
    "sg:province":"Alessandria",
    "wof:name":"Banca Commerciale Italiana Spa",
    "wof:placetype":"venue"
},
  "geometry": {"coordinates":[8.612722,44.911572],"type":"Point"}
}