{
  "type": "Feature",
  "properties": {
    "iso:country":"IT",
    "sg:address":"Piazza Concordia 14; Cartigliano; 36050",
    "sg:city":"Cartigliano",
    "sg:classifiers":[
        {
            "category":"Banks & Credit Unions",
            "subcategory":"Bank",
            "type":"Services"
        }
    ],
    "sg:phone":"+39 0424 828541",
    "sg:postcode":"36050",
    "sg:province":"Vicenza",
    "wof:name":"Banca Popolare Vicentina Scarl",
    "wof:placetype":"venue"
},
  "geometry": {"coordinates":[11.694149,45.713264],"type":"Point"}
}