{
  "type": "Feature",
  "properties": {
    "addr:full":"36100 Vicenza Vicenza Vicenza 36100",
    "addr:postcode":"36100;36100",
    "iso:country":"IT",
    "sg:address":"36100 Vicenza",
    "sg:city":"Vicenza",
    "sg:orig_category":"Servizi E Lavori Per Abbigliamento E Pelletterie",
    "sg:phone":"+39 0444 502158",
    "sg:postcode":"36100",
    "sg:province":"Vicenza",
    "wof:name":"Ago E Filo",
    "wof:placetype":"venue"
},
  "geometry": {"coordinates":[11.862636,45.411674],"type":"Point"}
}