{
  "type": "Feature",
  "properties": {
    "iso:country":"IT",
    "sg:address":"Piazza Garibaldi 4; Vico Canavese; 10080",
    "sg:city":"Vico Canavese",
    "sg:classifiers":[
        {
            "category":"Banks & Credit Unions",
            "subcategory":"Bank",
            "type":"Services"
        }
    ],
    "sg:phone":"+39 0125 74326",
    "sg:postcode":"10080",
    "sg:province":"Torino",
    "wof:name":"Istituto Bancario, San Paolo Di Torino Spa",
    "wof:placetype":"venue"
},
  "geometry": {"coordinates":[7.778546,45.494205],"type":"Point"}
}