{
  "type": "Feature",
  "properties": {
    "iso:country":"IT",
    "sg:address":"37010 Costermano",
    "sg:city":"Costermano",
    "sg:orig_category":"Gelateria E Pasticceria Fresca - Macchine E Forniture",
    "sg:phone":"+39 045 720 0211",
    "sg:postcode":"37010",
    "sg:province":"Verona",
    "wof:name":"Frigo Nord Srl",
    "wof:placetype":"venue"
},
  "geometry": {"coordinates":[10.766797,45.567219],"type":"Point"}
}