{
  "type": "Feature",
  "properties": {
    "iso:country":"IT",
    "sg:address":"30126 Lido",
    "sg:city":"Lido",
    "sg:orig_category":"Associazioni Ed Organismi Di Interesse Pubblico",
    "sg:phone":"+39 041 731429",
    "sg:postcode":"30126",
    "sg:province":"Venezia",
    "wof:name":"Anbba",
    "wof:placetype":"venue"
},
  "geometry": {"coordinates":[12.372045,45.411076],"type":"Point"}
}