{
  "type": "Feature",
  "properties": {
    "iso:country":"IT",
    "sg:address":"Via Rotondi 14; Paderno Dugnano; 20037",
    "sg:city":"Paderno Dugnano",
    "sg:classifiers":[
        {
            "category":"Banks & Credit Unions",
            "subcategory":"Bank",
            "type":"Services"
        }
    ],
    "sg:phone":"+39 02 9904 2254",
    "sg:postcode":"20037",
    "sg:province":"Milano",
    "wof:name":"Credito Italiano Spa",
    "wof:placetype":"venue"
},
  "geometry": {"coordinates":[9.1641,45.568008],"type":"Point"}
}