{
  "type": "Feature",
  "properties": {
    "iso:country":"IT",
    "sg:address":"06083 Bastia",
    "sg:city":"Bastia",
    "sg:classifiers":[
        {
            "category":"Banks & Credit Unions",
            "subcategory":"Investment Brokerage",
            "type":"Services"
        }
    ],
    "sg:phone":"+39 075 800 1164",
    "sg:postcode":"06083",
    "sg:province":"Perugia",
    "sg:tags":[
        "control",
        "climate",
        "vehicles",
        "accessory",
        "equipment",
        "conditioning",
        "motor",
        "services"
    ],
    "wof:name":"Nuova Autoservice Di Rosignoli Lanfranco",
    "wof:placetype":"venue"
},
  "geometry": {"coordinates":[12.550793,43.061871],"type":"Point"}
}