{
  "type": "Feature",
  "properties": {
    "iso:country":"IT",
    "sg:address":"Via Cefalonia 4 20156 Milano",
    "sg:city":"Milano",
    "sg:classifiers":[
        {
            "category":"Manufacturing",
            "subcategory":"Rubber & Plastics",
            "type":"Manufacturing & Wholesale Goods"
        }
    ],
    "sg:phone":"+39 02 3340 7123",
    "sg:postcode":"20156",
    "sg:province":"Milano",
    "sg:tags":[
        "mould",
        "industry"
    ],
    "wof:name":"Loran Srl",
    "wof:placetype":"venue"
},
  "geometry": {"coordinates":[9.2880859375,45.4330329895],"type":"Point"}
}