{
  "type": "Feature",
  "properties": {
    "iso:country":"IT",
    "sg:address":"11/2, Via Beniamino Franklin 41012 Carpi",
    "sg:city":"Carpi",
    "sg:classifiers":[
        {
            "category":"Shopping",
            "subcategory":"Clothing, Apparel, & Fashions",
            "type":"Retail Goods"
        }
    ],
    "sg:phone":"+39 39059696340",
    "sg:postcode":"41012",
    "sg:province":"Modena",
    "sg:tags":[
        "clothing",
        "accessory"
    ],
    "wof:name":"G.a.t. (s.r.l.)",
    "wof:placetype":"venue"
},
  "geometry": {"coordinates":[10.854417,44.780758],"type":"Point"}
}