{
  "type": "Feature",
  "properties": {
    "iso:country":"IT",
    "sg:address":"116, Via Caravaggio Michelangelo 80126 Napoli",
    "sg:city":"Napoli",
    "sg:classifiers":[
        {
            "category":"Parking",
            "subcategory":"Lot",
            "type":"Transportation"
        }
    ],
    "sg:phone":"+39 39081649006",
    "sg:postcode":"80126",
    "sg:province":"Napoli",
    "sg:tags":[
        "transport",
        "road"
    ],
    "wof:name":"Lida Srl",
    "wof:placetype":"venue"
},
  "geometry": {"coordinates":[14.228622,40.919174],"type":"Point"}
}