{
  "type": "Feature",
  "properties": {
    "iso:country":"IT",
    "sg:address":"50142 Firenze",
    "sg:city":"Firenze",
    "sg:classifiers":[
        {
            "category":"Banks & Credit Unions",
            "subcategory":"Investment Brokerage",
            "type":"Services"
        }
    ],
    "sg:phone":"+39 055 780986",
    "sg:postcode":"50142",
    "sg:province":"Firenze",
    "sg:tags":[
        "services",
        "various",
        "auxiliary",
        "transport",
        "public"
    ],
    "wof:name":"Pubblica Assistenza Humanitas Firenze Sms",
    "wof:placetype":"venue"
},
  "geometry": {"coordinates":[11.213337,43.773327],"type":"Point"}
}