{
  "type": "Feature",
  "properties": {
    "addr:full":"83020 Quadrelle Quadrelle Avellino 83020",
    "addr:postcode":"83020;83020",
    "iso:country":"IT",
    "sg:address":"83020 Quadrelle",
    "sg:city":"Quadrelle",
    "sg:orig_category":"Pubblica Amministrazione",
    "sg:phone":"+39 081 511 1446",
    "sg:postcode":"83020",
    "sg:province":"Avellino",
    "wof:name":"Comunita' Montana Vallo Di Lauro E Baianese",
    "wof:placetype":"venue"
},
  "geometry": {"coordinates":[14.6048164368,40.9514389038],"type":"Point"}
}