{
  "type": "Feature",
  "properties": {
    "addr:full":"39, Via Alcide De Gasperi 25030 Erbusco Erbusco Brescia 25030",
    "addr:postcode":"25030;25030",
    "addr:street":"Via Alcide De Gasperi",
    "iso:country":"IT",
    "sg:address":"39, Via Alcide De Gasperi 25030 Erbusco",
    "sg:city":"Erbusco",
    "sg:classifiers":[
        {
            "category":"Manufacturing",
            "subcategory":"Metals",
            "type":"Manufacturing & Wholesale Goods"
        }
    ],
    "sg:phone":"+39 030 726 8153",
    "sg:postcode":"25030",
    "sg:province":"Brescia",
    "sg:tags":[
        "processing"
    ],
    "wof:name":"Megamek S.r.l.",
    "wof:placetype":"venue"
},
  "geometry": {"coordinates":[10.2135133743,45.5792388916],"type":"Point"}
}