{
  "type": "Feature",
  "properties": {
    "iso:country":"IT",
    "sg:address":"84012 Angri",
    "sg:city":"Angri",
    "sg:orig_category":"Climatizzazione E Condizionamento, Apparecchiature E Servizi. Accessori Dei Mezzi Di Trasporto",
    "sg:phone":"+39 081 513 2626",
    "sg:postcode":"84012",
    "sg:province":"Salerno",
    "wof:name":"Catania Francesco",
    "wof:placetype":"venue"
},
  "geometry": {"coordinates":[14.572877,40.743446],"type":"Point"}
}