{
  "type": "Feature",
  "properties": {
    "addr:full":"31050 Ponzano Veneto Ponzano Veneto Treviso 31050",
    "addr:postcode":"31050;31050",
    "iso:country":"IT",
    "sg:address":"31050 Ponzano Veneto",
    "sg:city":"Ponzano Veneto",
    "sg:classifiers":[
        {
            "category":"Wholesale",
            "subcategory":"Machinery & Supplies",
            "type":"Manufacturing & Wholesale Goods"
        }
    ],
    "sg:phone":"+39 0422 968709",
    "sg:postcode":"31050",
    "sg:province":"Treviso",
    "sg:tags":[
        "product",
        "industrial",
        "equipment",
        "engineering",
        "mechanical",
        "electronic"
    ],
    "wof:name":"Meccanica Dima Snc",
    "wof:placetype":"venue"
},
  "geometry": {"coordinates":[12.219675,45.704216],"type":"Point"}
}