{
  "type": "Feature",
  "properties": {
    "iso:country":"IT",
    "sg:address":"20093 Cologno Monzese",
    "sg:city":"Cologno Monzese",
    "sg:orig_category":"Non-classified Establishments",
    "sg:phone":"+39 02 254 2021",
    "sg:postcode":"20093",
    "sg:province":"Milano",
    "wof:name":"Boutique Arredo Sas",
    "wof:placetype":"venue"
},
  "geometry": {"coordinates":[9.276417,45.531597],"type":"Point"}
}