{
  "type": "Feature",
  "properties": {
    "iso:country":"IT",
    "sg:address":"15, Via S. Giovanni Alla Paglia 20124 Milano",
    "sg:city":"Milano",
    "sg:classifiers":[
        {
            "category":"Shopping",
            "subcategory":"Clothing, Apparel, & Fashions",
            "type":"Retail Goods"
        }
    ],
    "sg:phone":"+39 02 6698 8115",
    "sg:postcode":"20124",
    "sg:province":"Milano",
    "sg:tags":[
        "clothes"
    ],
    "wof:name":"Events Di Zanzuri Silvio",
    "wof:placetype":"venue"
},
  "geometry": {"coordinates":[9.203344,45.480003],"type":"Point"}
}