{
  "type": "Feature",
  "properties": {
    "addr:full":"40056 Crespellano Crespellano Bologna 40056",
    "addr:postcode":"40056;40056",
    "iso:country":"IT",
    "sg:address":"40056 Crespellano",
    "sg:city":"Crespellano",
    "sg:orig_category":"Articoli Pulizia",
    "sg:phone":"+39 051 672 0039",
    "sg:postcode":"40056",
    "sg:province":"Bologna",
    "wof:name":"Pelloni Detersivi Industriali Di Pelloni Emanuela & C. Snc",
    "wof:placetype":"venue"
},
  "geometry": {"coordinates":[11.129846,44.521412],"type":"Point"}
}