{
  "type": "Feature",
  "properties": {
    "addr:full":"20154 Milano Milano Milano 20154",
    "addr:postcode":"20154;20154",
    "iso:country":"IT",
    "sg:address":"20154 Milano",
    "sg:city":"Milano",
    "sg:orig_category":"Prodotti Alimentari",
    "sg:phone":"+39 02 3361 4063",
    "sg:postcode":"20154",
    "sg:province":"Milano",
    "wof:name":"Vgm Consulting Di Dott. Vittorio Giovanni Meazza E C. Sas",
    "wof:placetype":"venue"
},
  "geometry": {"coordinates":[9.173913002,45.479133606],"type":"Point"}
}