{
  "type": "Feature",
  "properties": {
    "addr:full":"73/75, Via Prati Giovanni 25086 Rezzato Rezzato Brescia 25086",
    "addr:housenumber":"73 / 75",
    "addr:postcode":"25086;25086",
    "addr:street":"Via Prati Giovanni",
    "iso:country":"IT",
    "sg:address":"73/75, Via Prati Giovanni 25086 Rezzato",
    "sg:city":"Rezzato",
    "sg:classifiers":[
        {
            "category":"Manufacturing",
            "subcategory":"Metals",
            "type":"Manufacturing & Wholesale Goods"
        }
    ],
    "sg:phone":"+39 030 259 3383",
    "sg:postcode":"25086",
    "sg:province":"Brescia",
    "sg:tags":[
        "metallurgy",
        "metalworking"
    ],
    "wof:name":"Remog S.p.a.",
    "wof:placetype":"venue"
},
  "geometry": {"coordinates":[10.3022766113,45.5114479065],"type":"Point"}
}