{
  "type": "Feature",
  "properties": {
    "addr:full":"72, V. Della Tecnica 41100 Modena Modena Modena 41100",
    "addr:housenumber":"72",
    "addr:postcode":"41100;41100",
    "addr:street":"V. Della Tecnica",
    "iso:country":"IT",
    "sg:address":"72, V. Della Tecnica 41100 Modena",
    "sg:city":"Modena",
    "sg:classifiers":[
        {
            "category":"Manufacturing",
            "subcategory":"Metals",
            "type":"Manufacturing & Wholesale Goods"
        }
    ],
    "sg:phone":"+39 39059281535",
    "sg:postcode":"41100",
    "sg:province":"Modena",
    "sg:tags":[
        "metallurgy",
        "metalworking"
    ],
    "sg:website":"http://www.fonderiaghirlandina.com",
    "wof:name":"Fonderia Ghirlandina",
    "wof:placetype":"venue"
},
  "geometry": {"coordinates":[10.9806699753,44.6374511719],"type":"Point"}
}