{
  "type": "Feature",
  "properties": {
    "addr:full":"Via Galilei 9/c 20090 Assago Assago Milano 20090",
    "addr:housenumber":"9 / c",
    "addr:postcode":"20090;20090",
    "addr:street":"Via Galilei;Assago",
    "iso:country":"IT",
    "sg:address":"Via Galilei 9/c 20090 Assago",
    "sg:city":"Assago",
    "sg:classifiers":[
        {
            "category":"Manufacturing",
            "subcategory":"Paper Products",
            "type":"Manufacturing & Wholesale Goods"
        }
    ],
    "sg:phone":"+39 02 457771",
    "sg:postcode":"20090",
    "sg:province":"Milano",
    "sg:tags":[
        "cardboard",
        "package"
    ],
    "sg:website":"www.mead.com",
    "wof:name":"Mead Westvaco Aviocart S.r.l.",
    "wof:placetype":"venue"
},
  "geometry": {"coordinates":[9.121249,45.406055],"type":"Point"}
}