{
  "type": "Feature",
  "properties": {
    "addr:full":"33070 Brugnera Brugnera Pordenone 33070",
    "addr:postcode":"33070;33070",
    "iso:country":"IT",
    "sg:address":"33070 Brugnera",
    "sg:city":"Brugnera",
    "sg:orig_category":"Prodotti E Manufatti In Materie Plastiche. Articoli Per Imballaggio E Confezionamento",
    "sg:phone":"+39 0434 623504",
    "sg:postcode":"33070",
    "sg:province":"Pordenone",
    "wof:name":"Forniture Industriali Srl",
    "wof:placetype":"venue"
},
  "geometry": {"coordinates":[12.5271425247,45.9087142944],"type":"Point"}
}