{
  "type": "Feature",
  "properties": {
    "iso:country":"IT",
    "sg:address":"24035 Curno",
    "sg:city":"Curno",
    "sg:classifiers":[
        {
            "category":"Home & Garden",
            "subcategory":"Building Materials",
            "type":"Retail Goods"
        }
    ],
    "sg:phone":"+39 035 461859",
    "sg:postcode":"24035",
    "sg:province":"Bergamo",
    "sg:tags":[
        "gas",
        "caldaie"
    ],
    "wof:name":"A.c.m. Di Angeloni Maurilio & C. Snc",
    "wof:placetype":"venue"
},
  "geometry": {"coordinates":[9.610684,45.683796],"type":"Point"}
}