{
  "type": "Feature",
  "properties": {
    "addr:full":"58100 Grosseto Grosseto Grosseto 58100",
    "addr:postcode":"58100;58100",
    "iso:country":"IT",
    "sg:address":"58100 Grosseto",
    "sg:city":"Grosseto",
    "sg:orig_category":"Pompe. Macchine, Strumenti Ed Apparecchi Per Attivita' Industriali",
    "sg:phone":"+39 0564 451272",
    "sg:postcode":"58100",
    "sg:province":"Grosseto",
    "wof:name":"Fluxinos Italia Srl",
    "wof:placetype":"venue"
},
  "geometry": {"coordinates":[11.1316480637,42.7858924866],"type":"Point"}
}