{
  "type": "Feature",
  "properties": {
    "iso:country":"IT",
    "sg:address":"Via Maremmana, Km. 3.500 00033 San Cesareo",
    "sg:classifiers":[
        {
            "category":"Building & Trades",
            "subcategory":"Plumbing",
            "type":"Services"
        }
    ],
    "sg:phone":"+39 06 958 7710",
    "sg:postcode":"00033",
    "sg:province":"Roma",
    "sg:tags":[
        "tub",
        "bath"
    ],
    "sg:website":"www.orlandiroma.it",
    "wof:name":"Orlandi Roma Srl",
    "wof:placetype":"venue"
},
  "geometry": {"coordinates":[12.482325,41.895466],"type":"Point"}
}