{
  "type": "Feature",
  "properties": {
    "iso:country":"IT",
    "sg:address":"24021 Albino",
    "sg:city":"Albino",
    "sg:orig_category":"Macchine, Impianti Ed Attrezzature Per Abbigliamento E Pelletterie",
    "sg:phone":"+39 800 993 001",
    "sg:postcode":"24021",
    "sg:province":"Bergamo",
    "sg:website":"http://www.birolinigiorgio.it",
    "wof:name":"Birolini Giorgio & C. Snc",
    "wof:placetype":"venue"
},
  "geometry": {"coordinates":[9.825229,45.781319],"type":"Point"}
}