{
  "type": "Feature",
  "properties": {
    "iso:country":"IT",
    "sg:address":"10125 Torino",
    "sg:city":"Torino",
    "sg:orig_category":"Dolciumi E Gelati",
    "sg:phone":"+39 011 650 5498",
    "sg:postcode":"10125",
    "sg:province":"Torino",
    "sg:website":"http://www.ilmelogranoblu.com",
    "wof:name":"Il Melograno Blu",
    "wof:placetype":"venue"
},
  "geometry": {"coordinates":[7.547031,45.005409],"type":"Point"}
}