{
  "type": "Feature",
  "properties": {
    "addr:full":"00154 Roma Roma Roma 00154",
    "addr:postcode":"00154;00154",
    "iso:country":"IT",
    "sg:address":"00154 Roma",
    "sg:city":"Roma",
    "sg:orig_category":"Fotoriproduttori E Fotocopiatrici",
    "sg:phone":"+39 06 5713 8578",
    "sg:postcode":"00154",
    "sg:province":"Roma",
    "wof:name":"Ram Service Srl",
    "wof:placetype":"venue"
},
  "geometry": {"coordinates":[12.4934463501,41.8684616089],"type":"Point"}
}