{
  "type": "Feature",
  "properties": {
    "iso:country":"IT",
    "sg:address":"20123 Milano",
    "sg:city":"Milano",
    "sg:orig_category":"Ceramiche Per Pavimenti E Rivestimenti - Produzione E Ingrosso",
    "sg:phone":"+39 02 837 3925",
    "sg:postcode":"20123",
    "sg:province":"Milano",
    "wof:name":"Superskin Srl",
    "wof:placetype":"venue"
},
  "geometry": {"coordinates":[9.176047,45.456844],"type":"Point"}
}