{
  "type": "Feature",
  "properties": {
    "addr:full":"35010 Villafranca Padovana Villafranca Padovana Padova 35010",
    "addr:postcode":"35010;35010",
    "iso:country":"IT",
    "sg:address":"35010 Villafranca Padovana",
    "sg:city":"Villafranca Padovana",
    "sg:orig_category":"Vetrate Isolanti",
    "sg:phone":"+39 049 907 5066",
    "sg:postcode":"35010",
    "sg:province":"Padova",
    "sg:website":"http://www.hardglass.com",
    "wof:name":"Hard Glass Spa",
    "wof:placetype":"venue"
},
  "geometry": {"coordinates":[11.804461,45.456581],"type":"Point"}
}