{
  "type": "Feature",
  "properties": {
    "iso:country":"IT",
    "sg:address":"12037 Saluzzo",
    "sg:city":"Saluzzo",
    "sg:orig_category":"Materiali E Componenti Elettrotecnici",
    "sg:phone":"+39 0175 43761",
    "sg:postcode":"12037",
    "sg:province":"Cuneo",
    "wof:name":"Roberto Riccardo",
    "wof:placetype":"venue"
},
  "geometry": {"coordinates":[7.503067,44.660316],"type":"Point"}
}