{
  "type": "Feature",
  "properties": {
    "iso:country":"IT",
    "sg:address":"26041 Casalmaggiore",
    "sg:city":"Casalmaggiore",
    "sg:orig_category":"Campeggio",
    "sg:phone":"+39 0375 200052",
    "sg:postcode":"26041",
    "sg:province":"Cremona",
    "wof:name":"Stiliac Spa",
    "wof:placetype":"venue"
},
  "geometry": {"coordinates":[10.437128,44.985302],"type":"Point"}
}