{
  "type": "Feature",
  "properties": {
    "addr:full":"60044 Fabriano Fabriano Ancona 60044",
    "addr:postcode":"60044;60044",
    "iso:country":"IT",
    "sg:address":"60044 Fabriano",
    "sg:city":"Fabriano",
    "sg:orig_category":"Arredo Cucina Ed Elettrodomestici. Climatizzazione E Condizionamento, Apparecchiature E Servizi",
    "sg:postcode":"60044",
    "sg:province":"Ancona",
    "wof:name":"Dueffe S.r.l.",
    "wof:placetype":"venue"
},
  "geometry": {"coordinates":[12.870448,43.339912],"type":"Point"}
}