{
  "type": "Feature",
  "properties": {
    "addr:full":"Piazza Xxiii Aprile, 14; Poponesco; 46030 Mantova 46030",
    "addr:housenumber":"14",
    "addr:postcode":"46030;46030",
    "addr:street":"Piazza Xxiii Aprile",
    "iso:country":"IT",
    "sg:address":"Piazza Xxiii Aprile, 14; Poponesco; 46030",
    "sg:classifiers":[
        {
            "category":"Banks & Credit Unions",
            "subcategory":"Bank",
            "type":"Services"
        }
    ],
    "sg:phone":"+39 0375 86012",
    "sg:postcode":"46030",
    "sg:province":"Mantova",
    "wof:name":"Banca Agricola Mantovana",
    "wof:placetype":"venue"
},
  "geometry": {"coordinates":[10.794552,45.060955],"type":"Point"}
}