{
  "type": "Feature",
  "properties": {
    "iso:country":"IT",
    "sg:address":"142/a, Via Costa Andrea 40065 Pianoro",
    "sg:city":"Pianoro",
    "sg:classifiers":[
        {
            "category":"Personal",
            "subcategory":"Shoe Repair & Shine",
            "type":"Services"
        }
    ],
    "sg:phone":"+39 39051742354",
    "sg:postcode":"40065",
    "sg:province":"Bologna",
    "sg:tags":[
        "leather"
    ],
    "wof:name":"Covizzi Giuseppe - Impresa Artigiana Pelletteria",
    "wof:placetype":"venue"
},
  "geometry": {"coordinates":[11.354621,44.434586],"type":"Point"}
}