{
  "type": "Feature",
  "properties": {
    "addr:full":"98050 Caldera' Messina 98050",
    "addr:postcode":"98050;98050",
    "addr:street":"Caldera ' Messina",
    "iso:country":"IT",
    "sg:address":"98050 Caldera'",
    "sg:orig_category":"Motori Ed Organi Di Trasmissione. Ricambi E Componenti Dei Mezzi Di Trasporto",
    "sg:phone":"+39 090 970 1532",
    "sg:postcode":"98050",
    "sg:province":"Messina",
    "wof:name":"Ciaccio & Imbesi",
    "wof:placetype":"venue"
},
  "geometry": {"coordinates":[15.5555229187,38.1923332214],"type":"Point"}
}