{
  "type": "Feature",
  "properties": {
    "iso:country":"IT",
    "sg:address":"62, Via Fermi Enrico 37136 Verona",
    "sg:city":"Verona",
    "sg:classifiers":[
        {
            "category":"Banks & Credit Unions",
            "subcategory":"Investment Brokerage",
            "type":"Services"
        }
    ],
    "sg:phone":"+39 045 862 2955",
    "sg:postcode":"37136",
    "sg:province":"Verona",
    "sg:tags":[
        "-",
        "transport",
        "related"
    ],
    "wof:name":"Itx Cargo Veneto Srl",
    "wof:placetype":"venue"
},
  "geometry": {"coordinates":[10.963692,45.40517],"type":"Point"}
}