{
  "type": "Feature",
  "properties": {
    "addr:full":"40057 Cadriano Di Granarolo Bologna 40057",
    "addr:postcode":"40057;granarolo bologna 40057",
    "iso:country":"IT",
    "sg:address":"40057 Cadriano Di Granarolo",
    "sg:orig_category":"Arredi Ed Attrezzature Per Uffici",
    "sg:phone":"+39 051 763654",
    "sg:postcode":"40057",
    "sg:province":"Bologna",
    "sg:website":"http://www.venturicaffe.it/info.html",
    "wof:name":"Venturi Caff\u00c8 Snc",
    "wof:placetype":"venue"
},
  "geometry": {"coordinates":[11.390834,44.550911],"type":"Point"}
}