{
  "type": "Feature",
  "properties": {
    "iso:country":"IT",
    "sg:address":"33052 Cervignano Del Friuli",
    "sg:city":"Cervignano del Friuli",
    "sg:orig_category":"Impiantistica E Prodotti Tecnologici Per Edilizia. Forniture Industriali Per Prevenzione, Controllo E Sicurezza",
    "sg:phone":"+39 0431 30545",
    "sg:postcode":"33052",
    "sg:province":"Udine",
    "wof:name":"Friuli Estintori Srl",
    "wof:placetype":"venue"
},
  "geometry": {"coordinates":[13.357357,45.809872],"type":"Point"}
}