{
  "type": "Feature",
  "properties": {
    "iso:country":"IT",
    "sg:address":"31013 Codogne'",
    "sg:classifiers":[
        {
            "category":"Manufacturing",
            "subcategory":"Tools & Machinery",
            "type":"Manufacturing & Wholesale Goods"
        }
    ],
    "sg:phone":"+39 0438 7706",
    "sg:postcode":"31013",
    "sg:province":"Treviso",
    "sg:tags":[
        "leather",
        "equipment",
        "goods",
        "clothing"
    ],
    "sg:website":"http://www.vinilveneta.com",
    "wof:name":"Vinil Veneta Group Srl",
    "wof:placetype":"venue"
},
  "geometry": {"coordinates":[12.377282,45.865807],"type":"Point"}
}