{
  "type": "Feature",
  "properties": {
    "iso:country":"IT",
    "sg:address":"04019 Terracina",
    "sg:city":"Terracina",
    "sg:orig_category":"Imprese Edili",
    "sg:phone":"+39 0773 720091",
    "sg:postcode":"04019",
    "sg:province":"Latina",
    "wof:name":"Edil House Srl",
    "wof:placetype":"venue"
},
  "geometry": {"coordinates":[13.242488,41.289352],"type":"Point"}
}