{
  "type": "Feature",
  "properties": {
    "iso:country":"IT",
    "sg:address":"Via Cappannini 12 60035 Jesi",
    "sg:city":"Jesi",
    "sg:orig_category":"Sealing Systems",
    "sg:phone":"+39 0731 214978",
    "sg:postcode":"60035",
    "sg:province":"Ancona",
    "sg:website":"www.eurotenute.com",
    "wof:name":"Eurotenute Srl",
    "wof:placetype":"venue"
},
  "geometry": {"coordinates":[13.268971,43.531937],"type":"Point"}
}