{
  "type": "Feature",
  "properties": {
    "addr:full":"V. Tommaso Lauri 7; Macerata; 62100 Macerata Macerata 62100",
    "addr:housenumber":"7",
    "addr:postcode":"62100;62100",
    "addr:street":"V. Tommaso Lauri",
    "iso:country":"IT",
    "sg:address":"V. Tommaso Lauri 7; Macerata; 62100",
    "sg:city":"Macerata",
    "sg:classifiers":[
        {
            "category":"Shopping",
            "subcategory":"Computers & Home Electronics",
            "type":"Retail Goods"
        }
    ],
    "sg:phone":"+39 0733 2511",
    "sg:postcode":"62100",
    "sg:province":"Macerata",
    "sg:tags":[
        "chamber",
        "commerce"
    ],
    "wof:name":"Macerata Cci",
    "wof:placetype":"venue"
},
  "geometry": {"coordinates":[13.45021,43.300541],"type":"Point"}
}