{
  "type": "Feature",
  "properties": {
    "iso:country":"IT",
    "sg:address":"35043 Monselice",
    "sg:city":"Monselice",
    "sg:orig_category":"Impiantistica E Prodotti Tecnologici Per Edilizia. Elettrotecnica Industriale, Prodotti E Apparecchiature. Elettrotecnica Professionale E Di Consumo",
    "sg:phone":"+39 0429 783255",
    "sg:postcode":"35043",
    "sg:province":"Padova",
    "sg:website":"http://www.termoidraulicafavaro.it",
    "wof:name":"Termoidraulica Favaro Massimo Snc",
    "wof:placetype":"venue"
},
  "geometry": {"coordinates":[11.747677,45.22274],"type":"Point"}
}