{
  "type": "Feature",
  "properties": {
    "addr:full":"97014 Ispica Ispica Ragusa 97014",
    "addr:postcode":"97014;97014",
    "iso:country":"IT",
    "sg:address":"97014 Ispica",
    "sg:city":"Ispica",
    "sg:orig_category":"Macchine, Impianti Ed Attrezzature Per Agricoltura E Zootecnia",
    "sg:phone":"+39 0932 791024",
    "sg:postcode":"97014",
    "sg:province":"Ragusa",
    "wof:name":"Cannata Antonino",
    "wof:placetype":"venue"
},
  "geometry": {"coordinates":[14.927204,36.765606],"type":"Point"}
}