{
  "type": "Feature",
  "properties": {
    "iso:country":"IT",
    "sg:address":"93100 Caltanissetta",
    "sg:city":"Caltanissetta",
    "sg:orig_category":"Carta Da Parati - Vendita Al Dettaglio",
    "sg:phone":"+39 0934 29441",
    "sg:postcode":"93100",
    "sg:province":"Caltanissetta",
    "wof:name":"Lipani Carmela",
    "wof:placetype":"venue"
},
  "geometry": {"coordinates":[14.060139,37.497684],"type":"Point"}
}