{
  "type": "Feature",
  "properties": {
    "iso:country":"IT",
    "sg:address":"Via Francia 4 37135 Verona",
    "sg:city":"Verona",
    "sg:classifiers":[
        {
            "category":"Transit Center",
            "subcategory":"Freight",
            "type":"Transportation"
        }
    ],
    "sg:phone":"+39 045 829 0600",
    "sg:postcode":"37135",
    "sg:province":"Verona",
    "sg:tags":[
        "machining",
        "marble"
    ],
    "sg:website":"www.quarellaspa.com",
    "wof:name":"Quarella Spa",
    "wof:placetype":"venue"
},
  "geometry": {"coordinates":[10.975141,45.40976],"type":"Point"}
}