{
  "type": "Feature",
  "properties": {
    "addr:full":"6, Via Giovanni Ventitreesimo 47020 Longiano Longiano Forl\u00ec-Cesena 47020",
    "addr:postcode":"47020;47020",
    "addr:street":"Via Giovanni Ventitreesimo",
    "iso:country":"IT",
    "sg:address":"6, Via Giovanni Ventitreesimo 47020 Longiano",
    "sg:city":"Longiano",
    "sg:classifiers":[
        {
            "category":"Food & Beverages",
            "subcategory":"Groceries & Convenience Stores",
            "type":"Retail Goods"
        }
    ],
    "sg:phone":"+39 0547 666090",
    "sg:postcode":"47020",
    "sg:province":"Forl\u00ec-Cesena",
    "sg:tags":[
        "product",
        "related"
    ],
    "wof:name":"La Teggia Snc Di Latino Marco & C.",
    "wof:placetype":"venue"
},
  "geometry": {"coordinates":[11.9804611206,43.9947662354],"type":"Point"}
}