{
  "type": "Feature",
  "properties": {
    "iso:country":"IT",
    "sg:address":"Via Michelangelo Buonarroti 34 20090 Trezzano Sul Naviglio",
    "sg:city":"Trezzano sul Naviglio",
    "sg:classifiers":[
        {
            "category":"Exhibition Hall",
            "type":"Public Place"
        }
    ],
    "sg:phone":"+39 02 4840 1744",
    "sg:postcode":"20090",
    "sg:province":"Milano",
    "sg:tags":[
        "screen",
        "printing",
        "precision"
    ],
    "sg:website":"www.fpeitalia.it",
    "wof:name":"Fpe Ferrari Pubblicita' Esterna Srl",
    "wof:placetype":"venue"
},
  "geometry": {"coordinates":[9.05651474,45.4221496582],"type":"Point"}
}