{
  "type": "Feature",
  "properties": {
    "addr:full":"Via Lucchese 39 50019 Sesto Fiorentino Sesto Fiorentino Firenze 50019",
    "addr:housenumber":"39",
    "addr:postcode":"50019;50019",
    "addr:street":"Via Lucchese",
    "iso:country":"IT",
    "sg:address":"Via Lucchese 39 50019 Sesto Fiorentino",
    "sg:city":"Sesto Fiorentino",
    "sg:classifiers":[
        {
            "category":"Train Station",
            "subcategory":"Light Rail",
            "type":"Transportation"
        }
    ],
    "sg:phone":"+39 055 310607",
    "sg:postcode":"50019",
    "sg:province":"Firenze",
    "sg:tags":[
        "lighting"
    ],
    "sg:website":"www.baga.it",
    "wof:name":"Baga Srl",
    "wof:placetype":"venue"
},
  "geometry": {"coordinates":[11.171207,43.809132],"type":"Point"}
}