{
  "type": "Feature",
  "properties": {
    "iso:country":"IT",
    "sg:address":"00146 Roma",
    "sg:city":"Roma",
    "sg:orig_category":"Bigiotteria - Produzione E Ingrosso",
    "sg:phone":"+39 06 557 8073",
    "sg:postcode":"00146",
    "sg:province":"Roma",
    "wof:name":"Gherardi Collection Di Valeria Colacchio",
    "wof:placetype":"venue"
},
  "geometry": {"coordinates":[12.470099,41.862347],"type":"Point"}
}