{
  "type": "Feature",
  "properties": {
    "iso:country":"IT",
    "sg:address":"23868 Valmadrera",
    "sg:city":"Valmadrera",
    "sg:orig_category":"Prodotti Chimici Secondari. Macchine, Impianti Ed Attrezzature Industria Chimica. Servizi E Lavori Industria Chimica",
    "sg:phone":"+39 0341 580493",
    "sg:postcode":"23868",
    "sg:province":"Lecco",
    "wof:name":"Siri (s.r.l.)",
    "wof:placetype":"venue"
},
  "geometry": {"coordinates":[9.3651161194,45.8471221924],"type":"Point"}
}