{
  "type": "Feature",
  "properties": {
    "iso:country":"IT",
    "sg:address":"12044 Centallo",
    "sg:city":"Centallo",
    "sg:orig_category":"Edilizia - Materiali",
    "sg:phone":"+39 0171 211709",
    "sg:postcode":"12044",
    "sg:province":"Cuneo",
    "wof:name":"Retifer Snc",
    "wof:placetype":"venue"
},
  "geometry": {"coordinates":[7.600579,44.494736],"type":"Point"}
}