{
  "type": "Feature",
  "properties": {
    "addr:full":"Via Brancilione 2 24030 Corna Imagna Corna Imagna Bergamo 24030",
    "addr:housenumber":"2;imagna",
    "addr:postcode":"24030;24030",
    "addr:street":"Via Brancilione;Imagna",
    "iso:country":"IT",
    "sg:address":"Via Brancilione 2 24030 Corna Imagna",
    "sg:city":"Corna Imagna",
    "sg:classifiers":[
        {
            "category":"Manufacturing",
            "subcategory":"Textiles",
            "type":"Manufacturing & Wholesale Goods"
        }
    ],
    "sg:phone":"+39 035 853007",
    "sg:postcode":"24030",
    "sg:province":"Bergamo",
    "sg:tags":[
        "blended",
        "yarn"
    ],
    "wof:name":"Filotecnica Bergamasca Di Brumana L. & C. Sas",
    "wof:placetype":"venue"
},
  "geometry": {"coordinates":[9.532948,45.822586],"type":"Point"}
}