{
  "type": "Feature",
  "properties": {
    "addr:full":"90011 Aspra Aspra Palermo 90011",
    "addr:postcode":"90011;90011",
    "addr:street":"Aspra",
    "iso:country":"IT",
    "sg:address":"90011 Aspra",
    "sg:city":"Aspra",
    "sg:orig_category":"Carni, Salumi E Pesci",
    "sg:phone":"+39 091 928006",
    "sg:postcode":"90011",
    "sg:province":"Palermo",
    "wof:name":"Sud Pesca S R L",
    "wof:placetype":"venue"
},
  "geometry": {"coordinates":[13.499785,38.101643],"type":"Point"}
}