{
  "type": "Feature",
  "properties": {
    "addr:full":"3, Via Dell' Artigianato 40026 Imola Imola Bologna 40026",
    "addr:postcode":"40026;40026",
    "addr:street":"Via Dell ' Artigianato",
    "iso:country":"IT",
    "sg:address":"3, Via Dell' Artigianato 40026 Imola",
    "sg:city":"Imola",
    "sg:classifiers":[
        {
            "category":"Shopping",
            "subcategory":"Stationery & Office Supplies",
            "type":"Retail Goods"
        }
    ],
    "sg:phone":"+39 0542 640009",
    "sg:postcode":"40026",
    "sg:province":"Bologna",
    "sg:tags":[
        "professional"
    ],
    "wof:name":"L'arca - Societa' Cooperativa Di' Solidarieta' Soc",
    "wof:placetype":"venue"
},
  "geometry": {"coordinates":[11.7159080505,44.3698425293],"type":"Point"}
}