{
  "type": "Feature",
  "properties": {
    "iso:country":"IT",
    "sg:address":"20, Via Vicenza 21040 Oggiona Con Santo Stefano",
    "sg:city":"Oggiona",
    "sg:classifiers":[
        {
            "category":"Shopping",
            "type":"Retail Goods"
        }
    ],
    "sg:phone":"+39 0331 215224",
    "sg:postcode":"21040",
    "sg:province":"Varese",
    "sg:tags":[
        "finished",
        "-",
        "metallic"
    ],
    "wof:name":"De Tomi Srl",
    "wof:placetype":"venue"
},
  "geometry": {"coordinates":[8.8225259781,45.7077827454],"type":"Point"}
}