{
  "type": "Feature",
  "properties": {
    "addr:full":"Strada Statale 35 Giovi N. 11 20031 Cesano Maderno Cesano Maderno Milano 20031",
    "addr:housenumber":"35;11",
    "addr:postcode":"20031;20031",
    "addr:street":"Strada Statale;Giovi N.",
    "iso:country":"IT",
    "sg:address":"Strada Statale 35 Giovi N. 11 20031 Cesano Maderno",
    "sg:city":"Cesano Maderno",
    "sg:classifiers":[
        {
            "category":"Building & Trades",
            "subcategory":"Construction",
            "type":"Services"
        }
    ],
    "sg:phone":"+39 036 264 1343",
    "sg:postcode":"20031",
    "sg:province":"Milano",
    "sg:tags":[
        "installation",
        "heating"
    ],
    "wof:name":"Igeit Spa",
    "wof:placetype":"venue"
},
  "geometry": {"coordinates":[9.188141,45.463688],"type":"Point"}
}