{
  "type": "Feature",
  "properties": {
    "iso:country":"IT",
    "sg:address":"12, Via Curie 20019 Settimo Milanese",
    "sg:city":"Settimo Milanese",
    "sg:classifiers":[
        {
            "category":"Shopping",
            "type":"Retail Goods"
        }
    ],
    "sg:phone":"+39 02 4892 0188",
    "sg:postcode":"20019",
    "sg:province":"Milano",
    "sg:tags":[
        "finished",
        "-",
        "metallic"
    ],
    "wof:name":"Rolax S.r.l. Guide Per Mobili",
    "wof:placetype":"venue"
},
  "geometry": {"coordinates":[9.0665941238,45.4652671814],"type":"Point"}
}