{
  "type": "Feature",
  "properties": {
    "addr:full":"52045 Foiano Della Chiana Foiano della Chiana Arezzo 52045",
    "addr:housenumber":"della chiana",
    "addr:postcode":"52045;52045",
    "iso:country":"IT",
    "sg:address":"52045 Foiano Della Chiana",
    "sg:city":"Foiano della Chiana",
    "sg:orig_category":"Pavimenti Industriali",
    "sg:phone":"+39 0575 640010",
    "sg:postcode":"52045",
    "sg:province":"Arezzo",
    "wof:name":"Martone Antonio",
    "wof:placetype":"venue"
},
  "geometry": {"coordinates":[11.8093585968,43.2647781372],"type":"Point"}
}