{
  "type": "Feature",
  "properties": {
    "iso:country":"IT",
    "sg:address":"53037 San Gimignano",
    "sg:city":"San Gimignano",
    "sg:orig_category":"Restaurants And Related Public Premises. Sport And Leisure, Services. Hotels And Hotel Facilities. Restaurants And Similar",
    "sg:phone":"+39 0577 940225",
    "sg:postcode":"53037",
    "sg:province":"Siena",
    "wof:name":"Immobiliare 2p",
    "wof:placetype":"venue"
},
  "geometry": {"coordinates":[11.048549,43.465431],"type":"Point"}
}