{
  "type": "Feature",
  "properties": {
    "iso:country":"IT",
    "sg:address":"24010 Sorisole",
    "sg:city":"Sorisole",
    "sg:orig_category":"Dolciumi E Gelati",
    "sg:phone":"+39 035 577431",
    "sg:postcode":"24010",
    "sg:province":"Bergamo",
    "wof:name":"M.g.m. - S.a.s.- Di Mussetti Michela & C.",
    "wof:placetype":"venue"
},
  "geometry": {"coordinates":[9.659214,45.742161],"type":"Point"}
}