{
  "type": "Feature",
  "properties": {
    "iso:country":"IT",
    "sg:address":"Crosaron Di Villabella 18; Villabella Di S. Bonifacio; 37047",
    "sg:city":"Villabella",
    "sg:classifiers":[
        {
            "category":"Banks & Credit Unions",
            "subcategory":"Bank",
            "type":"Services"
        }
    ],
    "sg:phone":"+39 045 761 3822",
    "sg:postcode":"37047",
    "sg:province":"Verona",
    "wof:name":"Banca Popolare Vicentina Scparl",
    "wof:placetype":"venue"
},
  "geometry": {"coordinates":[11.247124,45.405922],"type":"Point"}
}