{
  "type": "Feature",
  "properties": {
    "addr:full":"Via Masseria Catrini 73040 Alliste Alliste Lecce 73040",
    "addr:postcode":"73040;73040",
    "addr:street":"Via Masseria Catrini",
    "iso:country":"IT",
    "sg:address":"Via Masseria Catrini 73040 Alliste",
    "sg:city":"Alliste",
    "sg:classifiers":[
        {
            "category":"Food & Beverages",
            "subcategory":"Groceries & Convenience Stores",
            "type":"Retail Goods"
        }
    ],
    "sg:phone":"+39 0833 585873",
    "sg:postcode":"73040",
    "sg:province":"Lecce",
    "sg:tags":[
        "product",
        "related"
    ],
    "wof:name":"Mirelli S.a.s. Di Manco Gianluca & C.",
    "wof:placetype":"venue"
},
  "geometry": {"coordinates":[18.1740150452,40.3532905579],"type":"Point"}
}