{
  "type": "Feature",
  "properties": {
    "iso:country":"IT",
    "sg:address":"10146 Torino",
    "sg:city":"Torino",
    "sg:orig_category":"Materiali E Componenti Elettrotecnici",
    "sg:phone":"+39 011 728872",
    "sg:postcode":"10146",
    "sg:province":"Torino",
    "wof:name":"Acet (s.r.l.)",
    "wof:placetype":"venue"
},
  "geometry": {"coordinates":[7.619183,45.076698],"type":"Point"}
}