{
  "type": "Feature",
  "properties": {
    "iso:country":"IT",
    "sg:address":"Via Pagane 25060 Marmentino",
    "sg:city":"Marmentino",
    "sg:classifiers":[
        {
            "category":"Shopping",
            "type":"Retail Goods"
        }
    ],
    "sg:phone":"+39 030 922 8261",
    "sg:postcode":"25060",
    "sg:province":"Brescia",
    "sg:tags":[
        "finished",
        "-",
        "metallic"
    ],
    "wof:name":"Fro - Mac Rubinetteria Di Frola A. E C. (s.n.c.)",
    "wof:placetype":"venue"
},
  "geometry": {"coordinates":[10.2684860229,45.7520027161],"type":"Point"}
}