{
  "type": "Feature",
  "properties": {
    "iso:country":"IT",
    "sg:address":"41019 Modena",
    "sg:city":"Appalto",
    "sg:orig_category":"Servizi E Lavori Per Arredamento E Industria Del Legno",
    "sg:phone":"+39 059 857 0169",
    "sg:postcode":"41019",
    "sg:province":"Modena",
    "wof:name":"Cucinarte Snc",
    "wof:placetype":"venue"
},
  "geometry": {"coordinates":[10.927352,44.738907],"type":"Point"}
}