{
  "type": "Feature",
  "properties": {
    "iso:country":"IT",
    "sg:address":"25045 Castegnato",
    "sg:city":"Castegnato",
    "sg:orig_category":"Macchine, Strumenti Ed Apparecchi Per Attivita' Industriali",
    "sg:phone":"+39 030 21491",
    "sg:postcode":"25045",
    "sg:province":"Brescia",
    "wof:name":"Mg Spa",
    "wof:placetype":"venue"
},
  "geometry": {"coordinates":[10.110429,45.553822],"type":"Point"}
}