{
  "type": "Feature",
  "properties": {
    "iso:country":"IT",
    "sg:address":"53017 Radda In Chianti",
    "sg:city":"Radda in Chianti",
    "sg:orig_category":"Edilizia - Materiali",
    "sg:phone":"+39 0577 738040",
    "sg:postcode":"53017",
    "sg:province":"Siena",
    "wof:name":"Ru-fa Srl",
    "wof:placetype":"venue"
},
  "geometry": {"coordinates":[11.354452,43.501762],"type":"Point"}
}