{
  "type": "Feature",
  "properties": {
    "addr:full":"20037 Incirano Milano 20037",
    "addr:postcode":"20037;20037",
    "addr:street":"Incirano",
    "iso:country":"IT",
    "sg:address":"20037 Incirano",
    "sg:orig_category":"Servizi E Lavori Per Industria Alimentare E Bevande",
    "sg:postcode":"20037",
    "sg:province":"Milano",
    "wof:name":"Cooperativa L'economia",
    "wof:placetype":"venue"
},
  "geometry": {"coordinates":[9.163766,45.572632],"type":"Point"}
}