{
  "type": "Feature",
  "properties": {
    "iso:country":"IT",
    "sg:address":"811/813, V. Messina95100 Catania",
    "sg:classifiers":[
        {
            "category":"Parking",
            "subcategory":"Lot",
            "type":"Transportation"
        }
    ],
    "sg:phone":"+39 39095498283",
    "sg:tags":[
        "transport",
        "road"
    ],
    "sg:website":"http://www.sanmauroct.it",
    "wof:name":"Cappadonna San Mauro",
    "wof:placetype":"venue"
},
  "geometry": {"coordinates":[15.120348,37.540134],"type":"Point"}
}