{
  "type": "Feature",
  "properties": {
    "addr:full":"50126 Firenze Firenze Firenze 50126",
    "addr:postcode":"50126;50126",
    "iso:country":"IT",
    "sg:address":"50126 Firenze",
    "sg:city":"Firenze",
    "sg:orig_category":"Acqua Potabile - Societa' Di Esercizio",
    "sg:phone":"+39 055 653 1977",
    "sg:postcode":"50126",
    "sg:province":"Firenze",
    "wof:name":"Torricini Anna & C.",
    "wof:placetype":"venue"
},
  "geometry": {"coordinates":[11.296544075,43.7578315735],"type":"Point"}
}