{
  "type": "Feature",
  "properties": {
    "iso:country":"IT",
    "sg:address":"V. Don Abbo Ii Santo, 8; Imperia; 18100",
    "sg:city":"Imperia",
    "sg:classifiers":[
        {
            "category":"Banks & Credit Unions",
            "subcategory":"Bank",
            "type":"Services"
        }
    ],
    "sg:phone":"+39 0183 24922",
    "sg:postcode":"18100",
    "sg:province":"Imperia",
    "wof:name":"Banca Popolare Di Novara",
    "wof:placetype":"venue"
},
  "geometry": {"coordinates":[8.031564,43.887894],"type":"Point"}
}