{
  "type": "Feature",
  "properties": {
    "iso:country":"IT",
    "sg:address":"70124 Bari",
    "sg:city":"Bari",
    "sg:orig_category":"Automazione E Macchine Per Ufficio",
    "sg:phone":"+39 080 509 3496",
    "sg:postcode":"70124",
    "sg:province":"Bari",
    "wof:name":"Cronotime Srl",
    "wof:placetype":"venue"
},
  "geometry": {"coordinates":[16.847338,41.091347],"type":"Point"}
}