{
  "type": "Feature",
  "properties": {
    "iso:country":"IT",
    "sg:address":"07100 Sassari",
    "sg:city":"Sassari",
    "sg:classifiers":[
        {
            "category":"Health Services",
            "subcategory":"Health Practitioner",
            "type":"Services"
        }
    ],
    "sg:phone":"+39 079 232532",
    "sg:postcode":"07100",
    "sg:province":"Sassari",
    "sg:tags":[
        "medici"
    ],
    "wof:name":"Piccinini Dr. Renato",
    "wof:placetype":"venue"
},
  "geometry": {"coordinates":[8.5538892746,40.7294425964],"type":"Point"}
}