{
  "type": "Feature",
  "properties": {
    "addr:full":"Via Di Meleto 1 50027 Strada In Chianti Strada in Chianti Firenze 50027",
    "addr:housenumber":"1",
    "addr:postcode":"50027;50027",
    "addr:street":"Via Di Meleto;Strada;Strada In Chianti",
    "iso:country":"IT",
    "sg:address":"Via Di Meleto 1 50027 Strada In Chianti",
    "sg:city":"Strada in Chianti",
    "sg:classifiers":[
        {
            "category":"Retail",
            "subcategory":"Event Space",
            "type":"Services"
        }
    ],
    "sg:phone":"+39 055 859241",
    "sg:postcode":"50027",
    "sg:province":"Firenze",
    "sg:tags":[
        "small",
        "leather",
        "good"
    ],
    "wof:name":"Celine Production S.r.l.",
    "wof:placetype":"venue"
},
  "geometry": {"coordinates":[11.32204,43.665817],"type":"Point"}
}