{
  "type": "Feature",
  "properties": {
    "iso:country":"IT",
    "sg:address":"Via Vecchia Roma 82100 Benevento",
    "sg:city":"Benevento",
    "sg:classifiers":[
        {
            "category":"Organizations",
            "subcategory":"Labor Organization",
            "type":"Services"
        }
    ],
    "sg:phone":"+39 0824 776035",
    "sg:postcode":"82100",
    "sg:province":"Benevento",
    "sg:tags":[
        "match"
    ],
    "wof:name":"S.i.r.f.a. Srl",
    "wof:placetype":"venue"
},
  "geometry": {"coordinates":[14.735418,41.180943],"type":"Point"}
}