{
  "type": "Feature",
  "properties": {
    "iso:country":"IT",
    "sg:address":"46048 Roverbella",
    "sg:city":"Roverbella",
    "sg:orig_category":"Prodotti E Manufatti In Materie Plastiche. Forniture Per Edilizia E Lavori Pubblici. Forniture E Materiali Per Imballaggio E Confezionamento",
    "sg:phone":"+39 0376 693639",
    "sg:postcode":"46048",
    "sg:province":"Mantova",
    "wof:name":"Erregi Due Snc",
    "wof:placetype":"venue"
},
  "geometry": {"coordinates":[10.7960681915,45.2175559998],"type":"Point"}
}