{
  "type": "Feature",
  "properties": {
    "iso:country":"IT",
    "sg:address":"26015 Soresina",
    "sg:city":"Soresina",
    "sg:orig_category":"Arredo Camera Letto E Complementi",
    "sg:phone":"+39 0374 340643",
    "sg:postcode":"26015",
    "sg:province":"Cremona",
    "wof:name":"Arredamenti Bonizzoni Mobilificio",
    "wof:placetype":"venue"
},
  "geometry": {"coordinates":[9.864432,45.29705],"type":"Point"}
}