{
  "type": "Feature",
  "properties": {
    "addr:full":"17, V. Rosselli - Fizzonasco 20090 Pieve Emanuele Fizzonasco Milano 20090",
    "addr:housenumber":"17",
    "addr:postcode":"20090;20090",
    "addr:street":"V. Rosselli",
    "iso:country":"IT",
    "sg:address":"17, V. Rosselli - Fizzonasco 20090 Pieve Emanuele",
    "sg:city":"Fizzonasco",
    "sg:classifiers":[
        {
            "category":"Wholesale",
            "subcategory":"Drugs",
            "type":"Manufacturing & Wholesale Goods"
        }
    ],
    "sg:phone":"+39 02 9078 1875",
    "sg:postcode":"20090",
    "sg:province":"Milano",
    "sg:tags":[
        "chemical",
        "pharmaceutical"
    ],
    "sg:website":"http://www.m5biadesivi.it",
    "wof:name":"M5 Biadesivi Srl",
    "wof:placetype":"venue"
},
  "geometry": {"coordinates":[9.181771,45.371605],"type":"Point"}
}