{
  "type": "Feature",
  "properties": {
    "iso:country":"IT",
    "sg:address":"63017 Porto San Giorgio",
    "sg:city":"Porto San Giorgio",
    "sg:orig_category":"Articoli Regalo - Produzione E Ingrosso",
    "sg:phone":"+39 0734 671800",
    "sg:postcode":"63017",
    "sg:province":"Ascoli Piceno",
    "wof:name":"Ceral Snc",
    "wof:placetype":"venue"
},
  "geometry": {"coordinates":[13.794389,43.183777],"type":"Point"}
}