{
  "type": "Feature",
  "properties": {
    "addr:full":"50144 Firenze Firenze Firenze 50144",
    "addr:postcode":"50144;50144",
    "iso:country":"IT",
    "sg:address":"50144 Firenze",
    "sg:city":"Firenze",
    "sg:orig_category":"Impianti, Attrezzature E Forniture Sanitarie Ed Ospedaliere",
    "sg:phone":"+39 055 331412",
    "sg:postcode":"50144",
    "sg:province":"Firenze",
    "wof:name":"E.p.e.m. Srl",
    "wof:placetype":"venue"
},
  "geometry": {"coordinates":[11.236046,43.78352],"type":"Point"}
}