{
  "type": "Feature",
  "properties": {
    "addr:full":"18, Viale Dei Pini 88049 Soveria Mannelli Soveria Mannelli Catanzaro 88049",
    "addr:housenumber":"18",
    "addr:postcode":"88049;88049",
    "addr:street":"Viale Dei Pini;Mannelli;Mannelli",
    "iso:country":"IT",
    "sg:address":"18, Viale Dei Pini 88049 Soveria Mannelli",
    "sg:city":"Soveria Mannelli",
    "sg:classifiers":[
        {
            "category":"Professional",
            "subcategory":"Printing & Photocopies",
            "type":"Services"
        }
    ],
    "sg:phone":"+39 0968 662034",
    "sg:postcode":"88049",
    "sg:province":"Catanzaro",
    "wof:name":"Rubbettino Editore S.r.l.",
    "wof:placetype":"venue"
},
  "geometry": {"coordinates":[16.5876789093,38.9105987549],"type":"Point"}
}