{
  "type": "Feature",
  "properties": {
    "addr:full":"41056 Savignano Sul Panaro Savignano sul Panaro Modena 41056",
    "addr:postcode":"41056;41056",
    "iso:country":"IT",
    "sg:address":"41056 Savignano Sul Panaro",
    "sg:city":"Savignano sul Panaro",
    "sg:orig_category":"Ceramiche: Prodotti E Lavorazioni",
    "sg:phone":"+39 059 739111",
    "sg:postcode":"41056",
    "sg:province":"Modena",
    "sg:website":"http://pastorellitiles.com",
    "wof:name":"Pastorelli Ceramiche Spa",
    "wof:placetype":"venue"
},
  "geometry": {"coordinates":[11.0333337784,44.4702110291],"type":"Point"}
}