{
  "type": "Feature",
  "properties": {
    "iso:country":"IT",
    "sg:address":"10010 Chiaverano",
    "sg:city":"Chiaverano",
    "sg:orig_category":"Distillerie",
    "sg:phone":"+39 0125 54808",
    "sg:postcode":"10010",
    "sg:province":"Torino",
    "wof:name":"Distilleria Revel Chion",
    "wof:placetype":"venue"
},
  "geometry": {"coordinates":[7.901605,45.494656],"type":"Point"}
}