{
  "type": "Feature",
  "properties": {
    "iso:country":"IT",
    "sg:address":"33078 San Vito Al Tagliamento",
    "sg:city":"San Vito al Tagliamento",
    "sg:orig_category":"Servizi Al Turismo. Trasporto Pubblico E Privato",
    "sg:phone":"+39 0434 875300",
    "sg:postcode":"33078",
    "sg:province":"Pordenone",
    "wof:name":"Viaggiare Insieme Srl",
    "wof:placetype":"venue"
},
  "geometry": {"coordinates":[12.869829,45.913448],"type":"Point"}
}