{
  "type": "Feature",
  "properties": {
    "iso:country":"IT",
    "sg:address":"36010 Velo D'astico",
    "sg:city":"Velo",
    "sg:orig_category":"Macchine, Impianti Ed Attrezzature Per Industria Alimentare E Bevande",
    "sg:phone":"+39 0445 742036",
    "sg:postcode":"36010",
    "sg:province":"Vicenza",
    "wof:name":"Caretta Alfredo",
    "wof:placetype":"venue"
},
  "geometry": {"coordinates":[11.366323,45.790051],"type":"Point"}
}