{
  "type": "Feature",
  "properties": {
    "iso:country":"IT",
    "sg:address":"Via Geola, 29 - Maggiate Superiore 28013 Gattico",
    "sg:city":"Gattico",
    "sg:classifiers":[
        {
            "category":"Shopping",
            "subcategory":"Clothing, Apparel, & Fashions",
            "type":"Retail Goods"
        }
    ],
    "sg:phone":"+39 0322 846591",
    "sg:postcode":"28013",
    "sg:province":"Novara",
    "sg:tags":[
        "image",
        "clothing",
        "basic"
    ],
    "wof:name":"Job Spa",
    "wof:placetype":"venue"
},
  "geometry": {"coordinates":[8.490787,45.714649],"type":"Point"}
}