{
  "type": "Feature",
  "properties": {
    "iso:country":"IT",
    "sg:address":"Via Quarto Negroni 32 00040 Ariccia",
    "sg:city":"Ariccia",
    "sg:classifiers":[
        {
            "category":"Communications",
            "subcategory":"Radio Station",
            "type":"Services"
        }
    ],
    "sg:phone":"+39 06 934 2244",
    "sg:postcode":"00040",
    "sg:province":"Roma",
    "sg:tags":[
        "glass",
        "breakage",
        "detector"
    ],
    "wof:name":"3i Security International Srl",
    "wof:placetype":"venue"
},
  "geometry": {"coordinates":[12.626868,41.709408],"type":"Point"}
}