{
  "type": "Feature",
  "properties": {
    "iso:country":"IT",
    "sg:address":"55012 Capannori",
    "sg:city":"Capannori",
    "sg:classifiers":[
        {
            "category":"Military Area",
            "subcategory":"Air Force Base",
            "type":"Public Place"
        }
    ],
    "sg:phone":"+39 0583 403594",
    "sg:postcode":"55012",
    "sg:province":"Lucca",
    "sg:tags":[
        "cave",
        "e",
        "miniere"
    ],
    "sg:website":"http://www.cavediguamo.it",
    "wof:name":"Frediani Moreno & C. Snc",
    "wof:placetype":"venue"
},
  "geometry": {"coordinates":[10.4986000061,43.8092002869],"type":"Point"}
}