{
  "type": "Feature",
  "properties": {
    "iso:country":"IT",
    "sg:address":"31038 Paese",
    "sg:city":"Paese",
    "sg:orig_category":"Apparecchiature Ed Attrezzature Meccaniche. Elettrotecnica Industriale, Prodotti E Apparecchiature",
    "sg:phone":"+39 0422 452266",
    "sg:postcode":"31038",
    "sg:province":"Treviso",
    "wof:name":"Sp & S S.r.l.",
    "wof:placetype":"venue"
},
  "geometry": {"coordinates":[12.165113,45.67667],"type":"Point"}
}