{
  "type": "Feature",
  "properties": {
    "iso:country":"IT",
    "sg:address":"07046 Porto Torres",
    "sg:city":"Porto Torres",
    "sg:orig_category":"Servizi Al Turismo. Servizi Ausiliari Per Il Trasporto",
    "sg:phone":"+39 079 514613",
    "sg:postcode":"07046",
    "sg:province":"Sassari",
    "wof:name":"G.m.s. Mar Srl",
    "wof:placetype":"venue"
},
  "geometry": {"coordinates":[8.401317,40.833702],"type":"Point"}
}