{
  "type": "Feature",
  "properties": {
    "iso:country":"IT",
    "sg:address":"48018 Faenza",
    "sg:city":"Faenza",
    "sg:orig_category":"Agricoltura - Attrezzi, Prodotti E Forniture",
    "sg:phone":"+39 0546 620743",
    "sg:postcode":"48018",
    "sg:province":"Ravenna",
    "wof:name":"Tanesini Technology Srl",
    "wof:placetype":"venue"
},
  "geometry": {"coordinates":[11.86823,44.298306],"type":"Point"}
}