{
  "type": "Feature",
  "properties": {
    "addr:full":"20030 Bovisio Masciago Bovisio Milano 20030",
    "addr:postcode":"20030;20030",
    "iso:country":"IT",
    "sg:address":"20030 Bovisio Masciago",
    "sg:city":"Bovisio",
    "sg:classifiers":[
        {
            "category":"Home & Garden",
            "subcategory":"Home Furnishings",
            "type":"Retail Goods"
        }
    ],
    "sg:phone":"+39 036 259 0718",
    "sg:postcode":"20030",
    "sg:province":"Milano",
    "sg:tags":[
        "bathroom",
        "accessories"
    ],
    "sg:website":"http://www.porro.it",
    "wof:name":"Fratelli Porro Snc Di Porro Artemio E Luigi",
    "wof:placetype":"venue"
},
  "geometry": {"coordinates":[9.1492538452,45.6066169739],"type":"Point"}
}