{
  "type": "Feature",
  "properties": {
    "iso:country":"IT",
    "sg:address":"36063 Marostica",
    "sg:city":"Marostica",
    "sg:classifiers":[
        {
            "category":"Sports & Exercise",
            "subcategory":"Tennis Court",
            "type":"Entertainment"
        }
    ],
    "sg:phone":"+39 0424 73063",
    "sg:postcode":"36063",
    "sg:province":"Vicenza",
    "sg:tags":[
        "e",
        "lo",
        "tempo",
        "libero",
        "per",
        "impianti",
        "il",
        "attrezzature"
    ],
    "wof:name":"Ekolwasser Italiana Srl",
    "wof:placetype":"venue"
},
  "geometry": {"coordinates":[11.65254,45.774448],"type":"Point"}
}