{
  "type": "Feature",
  "properties": {
    "iso:country":"IT",
    "sg:address":"00046 Grottaferrata",
    "sg:city":"Grottaferrata",
    "sg:orig_category":"Servizi Culturali E Per Lo Spettacolo. Servizi Al Turismo. Acqua, Luce, Gas E Societa' Di Esercizio Pubblico",
    "sg:phone":"+39 06 941 5122",
    "sg:postcode":"00046",
    "sg:province":"Roma",
    "wof:name":"Abbazia Greca",
    "wof:placetype":"venue"
},
  "geometry": {"coordinates":[12.666492,41.786644],"type":"Point"}
}