{
  "type": "Feature",
  "properties": {
    "addr:full":"5, Via Vadisi 03010 Patrica Patrica Frosinone 03010",
    "addr:postcode":"03010;03010",
    "addr:street":"Via Vadisi",
    "iso:country":"IT",
    "sg:address":"5, Via Vadisi 03010 Patrica",
    "sg:city":"Patrica",
    "sg:classifiers":[
        {
            "category":"Wholesale",
            "subcategory":"Drugs",
            "type":"Manufacturing & Wholesale Goods"
        }
    ],
    "sg:phone":"+39 390 775 2581",
    "sg:postcode":"03010",
    "sg:province":"Frosinone",
    "sg:tags":[
        "chemical",
        "pharmaceutical"
    ],
    "wof:name":"Chemi S.p.a.",
    "wof:placetype":"venue"
},
  "geometry": {"coordinates":[13.264143,41.60955],"type":"Point"}
}