{
  "type": "Feature",
  "properties": {
    "addr:full":"10155 Torino Torino Torino 10155",
    "addr:postcode":"10155;10155",
    "iso:country":"IT",
    "sg:address":"10155 Torino",
    "sg:city":"Torino",
    "sg:orig_category":"Forniture Alle Strutture Ricettive. Macchine E Impianti Per Attivita' Commerciali Ed Artigianali",
    "sg:phone":"+39 011 248 9620",
    "sg:postcode":"10155",
    "sg:province":"Torino",
    "wof:name":"F.a.b. Italia Di Montagna Ivo & C. Sas",
    "wof:placetype":"venue"
},
  "geometry": {"coordinates":[7.6878209114,45.0907058716],"type":"Point"}
}