{
  "type": "Feature",
  "properties": {
    "iso:country":"IT",
    "sg:address":"20099 Sesto San Giovanni",
    "sg:city":"Sesto San Giovanni",
    "sg:orig_category":"Automobili E Mezzi Di Trasporto",
    "sg:phone":"+39 02 2622 2523",
    "sg:postcode":"20099",
    "sg:province":"Milano",
    "wof:name":"Farem (s.p.a.)",
    "wof:placetype":"venue"
},
  "geometry": {"coordinates":[9.261349,45.527428],"type":"Point"}
}