{
  "type": "Feature",
  "properties": {
    "iso:country":"IT",
    "sg:address":"10147 Torino",
    "sg:city":"Torino",
    "sg:orig_category":"Servizi Per Lo Sport E Il Tempo Libero. Servizi Al Turismo",
    "sg:phone":"+39 011 216 6855",
    "sg:postcode":"10147",
    "sg:province":"Torino",
    "wof:name":"Racing Sport Line Di Sussio Maria Pia E C. S.a.s.",
    "wof:placetype":"venue"
},
  "geometry": {"coordinates":[7.674358,45.100121],"type":"Point"}
}