{
  "type": "Feature",
  "properties": {
    "iso:country":"IT",
    "sg:address":"Via Code 81 30027 San Dona' Di Piave",
    "sg:classifiers":[
        {
            "category":"Transit Center",
            "subcategory":"Freight",
            "type":"Transportation"
        }
    ],
    "sg:phone":"+39 0421 221329",
    "sg:postcode":"30027",
    "sg:province":"Venezia",
    "sg:tags":[
        "machining",
        "marble"
    ],
    "sg:website":"www.marmoglass.it",
    "wof:name":"Marmoglass Srl",
    "wof:placetype":"venue"
},
  "geometry": {"coordinates":[12.587285,45.617573],"type":"Point"}
}