{
  "type": "Feature",
  "properties": {
    "addr:full":"Corso Sempione 15; Gallarate; 21013 Gallarate Varese 21013",
    "addr:housenumber":"15",
    "addr:postcode":"21013;21013",
    "addr:street":"Corso Sempione",
    "iso:country":"IT",
    "sg:address":"Corso Sempione 15; Gallarate; 21013",
    "sg:city":"Gallarate",
    "sg:classifiers":[
        {
            "category":"Banks & Credit Unions",
            "subcategory":"Bank",
            "type":"Services"
        }
    ],
    "sg:phone":"+39 0331 714111",
    "sg:postcode":"21013",
    "sg:province":"Varese",
    "wof:name":"Banca Commerciale Italiana Spa",
    "wof:placetype":"venue"
},
  "geometry": {"coordinates":[8.785708,45.66246],"type":"Point"}
}