{
  "type": "Feature",
  "properties": {
    "iso:country":"IT",
    "sg:address":"20051 Limbiate",
    "sg:city":"Limbiate",
    "sg:orig_category":"Arredo Bagno Ed Idrosanitari. Idrosanitari E Accessori",
    "sg:phone":"+39 02 9905 5861",
    "sg:postcode":"20051",
    "sg:province":"Milano",
    "wof:name":"R & C Di Rupolo M. Snc",
    "wof:placetype":"venue"
},
  "geometry": {"coordinates":[9.117207,45.601707],"type":"Point"}
}