{
  "type": "Feature",
  "properties": {
    "addr:full":"80126 Napoli Napoli Napoli 80126",
    "addr:housenumber":"80126",
    "addr:postcode":"80126",
    "iso:country":"IT",
    "sg:address":"80126 Napoli",
    "sg:city":"Napoli",
    "sg:orig_category":"Motori Ed Organi Di Trasmissione",
    "sg:phone":"+39 081 767 8181",
    "sg:postcode":"80126",
    "sg:province":"Napoli",
    "wof:name":"Geat Di Barbara Gallo",
    "wof:placetype":"venue"
},
  "geometry": {"coordinates":[14.2044677734,40.8439674377],"type":"Point"}
}