{
  "type": "Feature",
  "properties": {
    "iso:country":"IT",
    "sg:address":"47900 Viserba",
    "sg:city":"Viserba",
    "sg:orig_category":"Pompe. Elettrotecnica Industriale, Prodotti E Apparecchiature",
    "sg:phone":"+39 0541 733950",
    "sg:postcode":"47900",
    "sg:province":"Rimini",
    "wof:name":"Itt Flygt (s.p.a.)",
    "wof:placetype":"venue"
},
  "geometry": {"coordinates":[12.5307817459,44.076675415],"type":"Point"}
}