{
  "type": "Feature",
  "properties": {
    "addr:full":"16133 Genova Genova Genova 16133",
    "addr:postcode":"16133;16133",
    "iso:country":"IT",
    "sg:address":"16133 Genova",
    "sg:city":"Genova",
    "sg:orig_category":"Filati E Materie Prime Tessili",
    "sg:phone":"+39 010 373 2147",
    "sg:postcode":"16133",
    "sg:province":"Genova",
    "wof:name":"Rosano' Maria",
    "wof:placetype":"venue"
},
  "geometry": {"coordinates":[8.9900922775,44.4082145691],"type":"Point"}
}