{
  "type": "Feature",
  "properties": {
    "iso:country":"IT",
    "sg:address":"90143 Palermo",
    "sg:city":"Palermo",
    "sg:orig_category":"Apparecchiature E Sistemi Per Magazzinaggio E Movimentazione",
    "sg:phone":"+39 091 625 5916",
    "sg:postcode":"90143",
    "sg:province":"Palermo",
    "sg:website":"http://www.bertolinolift.it",
    "wof:name":"Bertolino Ascensori",
    "wof:placetype":"venue"
},
  "geometry": {"coordinates":[13.350546,38.139099],"type":"Point"}
}