{
  "type": "Feature",
  "properties": {
    "iso:country":"IT",
    "sg:address":"Via Sant'andrea 24 36061 Bassano Del Grappa",
    "sg:city":"Bassano del Grappa",
    "sg:classifiers":[
        {
            "category":"Home & Garden",
            "subcategory":"Garden Supply",
            "type":"Retail Goods"
        }
    ],
    "sg:phone":"+39 0424 884911",
    "sg:postcode":"36061",
    "sg:province":"Vicenza",
    "sg:website":"www.epocaspa.com",
    "wof:name":"Epoca Spa",
    "wof:placetype":"venue"
},
  "geometry": {"coordinates":[11.704075,45.745487],"type":"Point"}
}