{
  "type": "Feature",
  "properties": {
    "addr:full":"20043 Arcore Arcore Milano 20043",
    "addr:postcode":"20043;20043",
    "iso:country":"IT",
    "sg:address":"20043 Arcore",
    "sg:city":"Arcore",
    "sg:orig_category":"Climatizzazione E Condizionamento, Apparecchiature E Servizi",
    "sg:phone":"+39 039 615684",
    "sg:postcode":"20043",
    "sg:province":"Milano",
    "wof:name":"Boldrocchi S.r.l.",
    "wof:placetype":"venue"
},
  "geometry": {"coordinates":[9.326173,45.632385],"type":"Point"}
}