{
  "type": "Feature",
  "properties": {
    "addr:full":"80141 Napoli Napoli Napoli 80141",
    "addr:housenumber":"80141",
    "addr:postcode":"80141",
    "iso:country":"IT",
    "sg:address":"80141 Napoli",
    "sg:city":"Napoli",
    "sg:orig_category":"Arredi Sacri",
    "sg:phone":"+39 081 445403",
    "sg:postcode":"80141",
    "sg:province":"Napoli",
    "sg:website":"http://www.dittarobertorusso.it",
    "wof:name":"Russo Roberto Snc",
    "wof:placetype":"venue"
},
  "geometry": {"coordinates":[14.270812,40.916912],"type":"Point"}
}