{
  "type": "Feature",
  "properties": {
    "iso:country":"IT",
    "sg:address":"277, V. Valdellatorre 10091 Alpignano",
    "sg:city":"Alpignano",
    "sg:classifiers":[
        {
            "category":"Autos & Motor Vehicles",
            "subcategory":"Automobile Sales",
            "type":"Retail Goods"
        }
    ],
    "sg:phone":"+39 011 966 4314",
    "sg:postcode":"10091",
    "sg:province":"Torino",
    "sg:tags":[
        "industrial"
    ],
    "sg:website":"http://www.bcesrl.it",
    "wof:name":"B.c.e. Srl Di Bonetto & C.",
    "wof:placetype":"venue"
},
  "geometry": {"coordinates":[7.52488,45.094254],"type":"Point"}
}