{
  "type": "Feature",
  "properties": {
    "iso:country":"IT",
    "sg:address":"19, Via Dell' Industria 40064 Ozzano Dell'emilia",
    "sg:classifiers":[
        {
            "category":"Manufacturing",
            "subcategory":"Metals",
            "type":"Manufacturing & Wholesale Goods"
        }
    ],
    "sg:phone":"+39 39051799966",
    "sg:postcode":"40064",
    "sg:province":"Bologna",
    "sg:tags":[
        "metallurgy",
        "metalworking"
    ],
    "wof:name":"Fg Devab (s.r.l.)",
    "wof:placetype":"venue"
},
  "geometry": {"coordinates":[11.4257497787,44.4620628357],"type":"Point"}
}