{
  "type": "Feature",
  "properties": {
    "iso:country":"IT",
    "sg:address":"Vle Simoncini 36 51016 Montecatini Terme E Tettuccio",
    "sg:classifiers":[
        {
            "category":"Home & Garden",
            "subcategory":"Carpets & Floor Coverings",
            "type":"Retail Goods"
        }
    ],
    "sg:phone":"+39 0572 73768",
    "sg:postcode":"51016",
    "sg:province":"Pistoia",
    "sg:tags":[
        "animal",
        "skin"
    ],
    "wof:name":"Nolusnova Srl",
    "wof:placetype":"venue"
},
  "geometry": {"coordinates":[10.918524,43.932156],"type":"Point"}
}