{
  "type": "Feature",
  "properties": {
    "iso:country":"IT",
    "sg:address":"20092 Cinisello Balsamo",
    "sg:city":"Cinisello Balsamo",
    "sg:orig_category":"Servizi E Lavori Per Industria Alimentare E Bevande",
    "sg:phone":"+39 02 612 0197",
    "sg:postcode":"20092",
    "sg:province":"Milano",
    "wof:name":"Cooperativa Cieffeti A R.l.",
    "wof:placetype":"venue"
},
  "geometry": {"coordinates":[9.214459,45.550907],"type":"Point"}
}