{
  "type": "Feature",
  "properties": {
    "iso:country":"IT",
    "sg:address":"Via Delle Industrie 20d 35020 Brugine",
    "sg:city":"Brugine",
    "sg:classifiers":[
        {
            "category":"Bars & Pubs",
            "subcategory":"Sports Bar",
            "type":"Food & Drink"
        }
    ],
    "sg:phone":"+39 049 580 6829",
    "sg:postcode":"35020",
    "sg:province":"Padova",
    "sg:tags":[
        "dy",
        "forging"
    ],
    "wof:name":"Generalmec S.r.l.",
    "wof:placetype":"venue"
},
  "geometry": {"coordinates":[11.8765888214,45.4095687866],"type":"Point"}
}