{
  "type": "Feature",
  "properties": {
    "addr:full":"Via Brava 38 33046 San Giovanni Al Natisone Udine 33046",
    "addr:housenumber":"38",
    "addr:postcode":"33046;33046",
    "addr:street":"Via Brava",
    "iso:country":"IT",
    "sg:address":"Via Brava 38 33046 San Giovanni Al Natisone",
    "sg:classifiers":[
        {
            "category":"Manufacturing",
            "subcategory":"Tools & Machinery",
            "type":"Manufacturing & Wholesale Goods"
        }
    ],
    "sg:phone":"+39 0432 746577",
    "sg:postcode":"33046",
    "sg:province":"Udine",
    "sg:tags":[
        "abrasive"
    ],
    "wof:name":"Karim Snc",
    "wof:placetype":"venue"
},
  "geometry": {"coordinates":[13.230724,46.064941],"type":"Point"}
}