{
  "type": "Feature",
  "properties": {
    "addr:full":"35020 Albignasego Albignasego Padova 35020",
    "addr:postcode":"35020;35020",
    "iso:country":"IT",
    "sg:address":"35020 Albignasego",
    "sg:city":"Albignasego",
    "sg:orig_category":"Termotecnica E Riscaldamento, Apparecchiature E Servizi",
    "sg:postcode":"35020",
    "sg:province":"Padova",
    "wof:name":"Rolle (s.p.a.)",
    "wof:placetype":"venue"
},
  "geometry": {"coordinates":[11.845734,45.356014],"type":"Point"}
}