{
  "type": "Feature",
  "properties": {
    "iso:country":"IT",
    "sg:address":"104, Via Sindacale 30023 Concordia Sagittaria",
    "sg:city":"Concordia Sagittaria",
    "sg:classifiers":[
        {
            "category":"Farming",
            "subcategory":"Livestock Farm",
            "type":"Manufacturing & Wholesale Goods"
        }
    ],
    "sg:phone":"+39 0421 769212",
    "sg:postcode":"30023",
    "sg:province":"Venezia",
    "sg:tags":[
        "agriculture"
    ],
    "wof:name":"Valle Zignago (s.p.a.)",
    "wof:placetype":"venue"
},
  "geometry": {"coordinates":[12.338784,45.434338],"type":"Point"}
}