{
  "type": "Feature",
  "properties": {
    "addr:full":"16121 Genova Genova Genova 16121",
    "addr:postcode":"16121;16121",
    "iso:country":"IT",
    "sg:address":"16121 Genova",
    "sg:city":"Genova",
    "sg:classifiers":[
        {
            "category":"Professional",
            "subcategory":"Management & Consulting",
            "type":"Services"
        }
    ],
    "sg:phone":"+39 010 540073",
    "sg:postcode":"16121",
    "sg:province":"Genova",
    "sg:tags":[
        "business",
        "technical",
        "consultant",
        "-",
        "worker",
        "consultancies",
        "administration",
        "appraisers",
        "administrative"
    ],
    "wof:name":"Studio Rovida Commercialisti Associati",
    "wof:placetype":"venue"
},
  "geometry": {"coordinates":[8.939713,44.405628],"type":"Point"}
}