{
  "type": "Feature",
  "properties": {
    "iso:country":"IT",
    "sg:address":"19123 La Spezia",
    "sg:orig_category":"Imprese Di Costruzioni Civili Ed Industriali",
    "sg:phone":"+39 0187 713833",
    "sg:province":"SP",
    "wof:name":"M.f. Domus",
    "wof:placetype":"venue"
},
  "geometry": {"coordinates":[9.8039979935,44.1137084961],"type":"Point"}
}