{
  "type": "Feature",
  "properties": {
    "iso:country":"IT",
    "sg:address":"46100 Mantova",
    "sg:city":"Mantova",
    "sg:orig_category":"Banche E Servizi Finanziari",
    "sg:phone":"+39 0376 319011",
    "sg:postcode":"46100",
    "sg:province":"Mantova",
    "wof:name":"Banca Fideuram Spa",
    "wof:placetype":"venue"
},
  "geometry": {"coordinates":[10.795613,45.158459],"type":"Point"}
}