{
  "type": "Feature",
  "properties": {
    "iso:country":"IT",
    "sg:address":"40037 Sasso Marconi",
    "sg:city":"Sasso Marconi",
    "sg:orig_category":"Forniture Per Abbigliamento E Pelletterie",
    "sg:phone":"+39 051 675 1371",
    "sg:postcode":"40037",
    "sg:province":"Bologna",
    "wof:name":"Martini Maurizia - Morselli Rosanna S.n.c.",
    "wof:placetype":"venue"
},
  "geometry": {"coordinates":[11.2451477051,44.3951301575],"type":"Point"}
}