{
  "type": "Feature",
  "properties": {
    "iso:country":"IT",
    "sg:address":"60016 Marina Di Montemarciano",
    "sg:orig_category":"Apparecchiature E Sistemi Per Magazzinaggio E Movimentazione. Macchine E Impianti Per Attivita' Commerciali Ed Artigianali. Macchine, Strumenti Ed Apparecchi Per Attivita' Industriali",
    "sg:phone":"+39 071 919 8351",
    "sg:province":"AN",
    "wof:name":"Serrani Luciano",
    "wof:placetype":"venue"
},
  "geometry": {"coordinates":[-87.90406,42.049213],"type":"Point"}
}