{
  "type": "Feature",
  "properties": {
    "addr:full":"20159 Milano Milano Milano 20159",
    "addr:postcode":"20159;20159",
    "iso:country":"IT",
    "sg:address":"20159 Milano",
    "sg:city":"Milano",
    "sg:orig_category":"Servizi E Lavori Per Edilizia E Lavori Pubblici. Banche E Servizi Finanziari",
    "sg:phone":"+39 02 6680 9609",
    "sg:postcode":"20159",
    "sg:province":"Milano",
    "wof:name":"Alpa Immobiliare Srl",
    "wof:placetype":"venue"
},
  "geometry": {"coordinates":[9.191761,45.498196],"type":"Point"}
}