{
  "type": "Feature",
  "properties": {
    "iso:country":"IT",
    "sg:address":"20052 Monza",
    "sg:city":"Monza",
    "sg:orig_category":"Accessori Moda D'abbigliamento",
    "sg:phone":"+39 039 323775",
    "sg:postcode":"20052",
    "sg:province":"Milano",
    "wof:name":"Fossati Alberto & C. (s.a.s.)",
    "wof:placetype":"venue"
},
  "geometry": {"coordinates":[9.273499,45.52874],"type":"Point"}
}