{
  "type": "Feature",
  "properties": {
    "iso:country":"IT",
    "sg:address":"Corso Giannone 78; Caserta; 81100",
    "sg:city":"Caserta",
    "sg:classifiers":[
        {
            "category":"Banks & Credit Unions",
            "subcategory":"Bank",
            "type":"Services"
        }
    ],
    "sg:phone":"+39 0823 355101",
    "sg:postcode":"81100",
    "sg:province":"Caserta",
    "wof:name":"Banca Popolare Dell'irpinia Scarl",
    "wof:placetype":"venue"
},
  "geometry": {"coordinates":[14.331285,41.078194],"type":"Point"}
}