{
  "type": "Feature",
  "properties": {
    "iso:country":"IT",
    "sg:address":"20123 Milano",
    "sg:city":"Milano",
    "sg:orig_category":"Pubblicita', Marketing E Comunicazione",
    "sg:phone":"+39 02 8645 5490",
    "sg:postcode":"20123",
    "sg:province":"Milano",
    "wof:name":"Business Press Srl",
    "wof:placetype":"venue"
},
  "geometry": {"coordinates":[9.1752223969,45.465259552],"type":"Point"}
}