{
  "type": "Feature",
  "properties": {
    "iso:country":"IT",
    "sg:address":"66030 Santa Maria Imbaro",
    "sg:city":"Santa Maria Imbaro",
    "sg:orig_category":"Certificazione Qualita', Sicurezza Ed Ambiente",
    "sg:phone":"+39 0872 578377",
    "sg:postcode":"66030",
    "sg:province":"Chieti",
    "wof:name":"Sistema 2000 Srl Servizi Ecologici",
    "wof:placetype":"venue"
},
  "geometry": {"coordinates":[14.449548,42.221863],"type":"Point"}
}