{
  "type": "Feature",
  "properties": {
    "iso:country":"IT",
    "sg:address":"00153 Roma",
    "sg:city":"Roma",
    "sg:orig_category":"Arredo Bagno Ed Idrosanitari. Complementi Di Arredamento. Vetro: Prodotti E Lavorazioni",
    "sg:phone":"+39 06 581 0700",
    "sg:postcode":"00153",
    "sg:province":"Roma",
    "wof:name":"Vetreria R. Rubei & C.",
    "wof:placetype":"venue"
},
  "geometry": {"coordinates":[12.471945,41.885506],"type":"Point"}
}