{
  "type": "Feature",
  "properties": {
    "iso:country":"IT",
    "sg:address":"00054 Fiumicino",
    "sg:city":"Fiumicino",
    "sg:orig_category":"Nautica. Automobili E Mezzi Di Trasporto",
    "sg:phone":"+39 06 6502 4008",
    "sg:postcode":"00054",
    "sg:province":"Roma",
    "wof:name":"Alimar Srl",
    "wof:placetype":"venue"
},
  "geometry": {"coordinates":[12.23161,41.758213],"type":"Point"}
}