{
  "type": "Feature",
  "properties": {
    "addr:full":"00146 Roma Roma Roma 00146",
    "addr:postcode":"00146;00146",
    "iso:country":"IT",
    "sg:address":"00146 Roma",
    "sg:city":"Roma",
    "sg:orig_category":"Apparecchi, Attrezzature E Forniture Per Centri Estetici. Forniture Per Attivita' Commerciali Ed Artigianali",
    "sg:phone":"+39 06 559 5141",
    "sg:postcode":"00146",
    "sg:province":"Roma",
    "wof:name":"Dabor Srl",
    "wof:placetype":"venue"
},
  "geometry": {"coordinates":[12.46855,41.861187],"type":"Point"}
}