{
  "type": "Feature",
  "properties": {
    "iso:country":"IT",
    "sg:address":"Via Del Lavoro 5 22100 Como",
    "sg:city":"Como",
    "sg:classifiers":[
        {
            "category":"Building & Trades",
            "subcategory":"Plumbing",
            "type":"Services"
        }
    ],
    "sg:phone":"+39 031 507008",
    "sg:postcode":"22100",
    "sg:province":"Como",
    "sg:tags":[
        "steel",
        "pipe"
    ],
    "sg:website":"www.mussari.com",
    "wof:name":"Mussari Srl",
    "wof:placetype":"venue"
},
  "geometry": {"coordinates":[9.078023,45.782715],"type":"Point"}
}