{
  "type": "Feature",
  "properties": {
    "addr:full":"00166 Roma Roma Roma 00166",
    "addr:postcode":"00166;00166",
    "iso:country":"IT",
    "sg:address":"00166 Roma",
    "sg:city":"Roma",
    "sg:orig_category":"Lavorazioni Meccaniche E Servizi",
    "sg:phone":"+39 06 6152 1127",
    "sg:postcode":"00166",
    "sg:province":"Roma",
    "wof:name":"Vama Srl",
    "wof:placetype":"venue"
},
  "geometry": {"coordinates":[12.388314,41.898499],"type":"Point"}
}