{
  "type": "Feature",
  "properties": {
    "addr:full":"130, Via Viole 47035 Gambettola Gambettola Forl\u00ec-Cesena 47035",
    "addr:housenumber":"130",
    "addr:postcode":"47035;47035",
    "addr:street":"Via Viole",
    "iso:country":"IT",
    "sg:address":"130, Via Viole 47035 Gambettola",
    "sg:city":"Gambettola",
    "sg:classifiers":[
        {
            "category":"Food & Beverages",
            "subcategory":"Groceries & Convenience Stores",
            "type":"Retail Goods"
        }
    ],
    "sg:phone":"+39 39054757079",
    "sg:postcode":"47035",
    "sg:province":"Forl\u00ec-Cesena",
    "sg:tags":[
        "product",
        "related"
    ],
    "wof:name":"Ellecarni (s.r.l.)",
    "wof:placetype":"venue"
},
  "geometry": {"coordinates":[12.3507356644,44.1209144592],"type":"Point"}
}