{
  "type": "Feature",
  "properties": {
    "addr:full":"07010 Benetutti Benetutti Sassari 07010",
    "addr:postcode":"07010;07010",
    "iso:country":"IT",
    "sg:address":"07010 Benetutti",
    "sg:city":"Benetutti",
    "sg:orig_category":"Prodotti Finiti Stampati. Forniture Per Uffici",
    "sg:phone":"+39 079 796327",
    "sg:postcode":"07010",
    "sg:province":"Sassari",
    "wof:name":"La Stampa Snc Di Soddu Piras & C.",
    "wof:placetype":"venue"
},
  "geometry": {"coordinates":[8.568230629,40.7350082397],"type":"Point"}
}