{
  "type": "Feature",
  "properties": {
    "addr:full":"33170 Pordenone Pordenone Pordenone 33170",
    "addr:postcode":"33170;33170",
    "iso:country":"IT",
    "sg:address":"33170 Pordenone",
    "sg:city":"Pordenone",
    "sg:orig_category":"Automobili E Mezzi Di Trasporto",
    "sg:phone":"+39 0434 572211",
    "sg:postcode":"33170",
    "sg:province":"Pordenone",
    "wof:name":"Rimorchi Bertoja Spa",
    "wof:placetype":"venue"
},
  "geometry": {"coordinates":[12.650542,45.926983],"type":"Point"}
}