{
  "type": "Feature",
  "properties": {
    "addr:full":"2, Strada Marziana 27020 Parona Parona Pavia 27020",
    "addr:postcode":"27020;27020",
    "addr:street":"Strada Marziana",
    "iso:country":"IT",
    "sg:address":"2, Strada Marziana 27020 Parona",
    "sg:city":"Parona",
    "sg:classifiers":[
        {
            "category":"Manufacturing",
            "subcategory":"Textiles",
            "type":"Manufacturing & Wholesale Goods"
        }
    ],
    "sg:phone":"+39 0384 253460",
    "sg:postcode":"27020",
    "sg:province":"Pavia",
    "sg:tags":[
        "leather",
        "raw",
        "material",
        "-"
    ],
    "wof:name":"O.m.p.a. (s.r.l.)",
    "wof:placetype":"venue"
},
  "geometry": {"coordinates":[8.779153,45.278313],"type":"Point"}
}