{
  "type": "Feature",
  "properties": {
    "iso:country":"IT",
    "sg:address":"Via Vittorio Emanuele 450, 95033 Biancavilla, Ct",
    "sg:city":"Biancavilla",
    "sg:classifiers":[
        {
            "category":"Banks & Credit Unions",
            "subcategory":"Bank",
            "type":"Services"
        }
    ],
    "sg:postcode":"95033",
    "sg:province":"Catania",
    "wof:name":"Banca Di Credito Biancavilla",
    "wof:placetype":"venue"
},
  "geometry": {"coordinates":[14.863753,37.644726],"type":"Point"}
}