{
  "type": "Feature",
  "properties": {
    "iso:country":"IT",
    "sg:address":"12100 Cuneo",
    "sg:city":"Cuneo",
    "sg:orig_category":"Ponteggi Metallici E Palchi Per Manifestazioni",
    "sg:phone":"+39 338 129 2222",
    "sg:postcode":"12100",
    "sg:province":"Cuneo",
    "wof:name":"Edilcantieri Srl",
    "wof:placetype":"venue"
},
  "geometry": {"coordinates":[7.4946475029,44.3356971741],"type":"Point"}
}