{
  "type": "Feature",
  "properties": {
    "iso:country":"IT",
    "sg:address":"70052 Bisceglie",
    "sg:city":"Bisceglie",
    "sg:orig_category":"Macchine E Forniture Per Arredamento E Industria Del Legno",
    "sg:phone":"+39 080 392 4469",
    "sg:postcode":"70052",
    "sg:province":"Bari",
    "wof:name":"Ventura Giuseppe",
    "wof:placetype":"venue"
},
  "geometry": {"coordinates":[16.873985,41.12228],"type":"Point"}
}