{
  "type": "Feature",
  "properties": {
    "iso:country":"IT",
    "sg:address":"20145 Milano",
    "sg:city":"Milano",
    "sg:orig_category":"Strumenti Musicali Ed Accessori - Vendita Al Dettaglio",
    "sg:phone":"+39 02 3360 0955",
    "sg:postcode":"20145",
    "sg:province":"Milano",
    "wof:name":"Fantova De Lucca Liutai Snc",
    "wof:placetype":"venue"
},
  "geometry": {"coordinates":[9.169994,45.475849],"type":"Point"}
}