{
  "type": "Feature",
  "properties": {
    "addr:full":"00186 Roma Roma Roma 00186",
    "addr:postcode":"00186;00186",
    "iso:country":"IT",
    "sg:address":"00186 Roma",
    "sg:city":"Roma",
    "sg:orig_category":"Articoli Da Regalo. Shopping. Regalistica Aziendale",
    "sg:phone":"+39 06 678 9844",
    "sg:postcode":"00186",
    "sg:province":"Roma",
    "wof:name":"Magini Athos",
    "wof:placetype":"venue"
},
  "geometry": {"coordinates":[12.616367,41.723404],"type":"Point"}
}