{
  "type": "Feature",
  "properties": {
    "iso:country":"IT",
    "sg:address":"33100 Udine",
    "sg:city":"Udine",
    "sg:orig_category":"Frigotecnica, Apparecchiature E Servizi",
    "sg:phone":"+39 0432 506051",
    "sg:postcode":"33100",
    "sg:province":"Udine",
    "wof:name":"Edil Friuli Spa",
    "wof:placetype":"venue"
},
  "geometry": {"coordinates":[13.2342920303,46.056098938],"type":"Point"}
}