{
  "type": "Feature",
  "properties": {
    "iso:country":"IT",
    "sg:address":"S.s. 16 Per Barletta, Km 756,200 70059 Trani",
    "sg:city":"Trani",
    "sg:classifiers":[
        {
            "category":"Building & Trades",
            "subcategory":"Construction",
            "type":"Services"
        }
    ],
    "sg:phone":"+39 0883 500285",
    "sg:postcode":"70059",
    "sg:province":"Bari",
    "sg:tags":[
        "granite",
        "working"
    ],
    "sg:website":"www.mundialgraniti.it",
    "wof:name":"Mundial Graniti Sas",
    "wof:placetype":"venue"
},
  "geometry": {"coordinates":[16.869291,41.126053],"type":"Point"}
}