{
  "type": "Feature",
  "properties": {
    "addr:full":"Via Ciambellana, 18/20 50059 Vinci Vinci Firenze 50059",
    "addr:housenumber":"18 / 20",
    "addr:postcode":"50059;50059",
    "addr:street":"Via Ciambellana",
    "iso:country":"IT",
    "sg:address":"Via Ciambellana, 18/20 50059 Vinci",
    "sg:city":"Vinci",
    "sg:classifiers":[
        {
            "category":"Shopping",
            "subcategory":"Clothing, Apparel, & Fashions",
            "type":"Retail Goods"
        }
    ],
    "sg:phone":"+39 0571 584571",
    "sg:postcode":"50059",
    "sg:province":"Firenze",
    "sg:tags":[
        "leather",
        "clothing"
    ],
    "sg:website":"www.shasa-confezioni.com",
    "wof:name":"Shasa S.r.l.",
    "wof:placetype":"venue"
},
  "geometry": {"coordinates":[10.944158,43.758057],"type":"Point"}
}