{
  "type": "Feature",
  "properties": {
    "iso:country":"IT",
    "sg:address":"8, Via Mortini 24060 San Paolo D'argon",
    "sg:classifiers":[
        {
            "category":"Shopping",
            "type":"Retail Goods"
        }
    ],
    "sg:phone":"+39 39035959711",
    "sg:postcode":"24060",
    "sg:province":"Bergamo",
    "sg:tags":[
        "finished",
        "-",
        "metallic"
    ],
    "wof:name":"Friulco S.r.l.",
    "wof:placetype":"venue"
},
  "geometry": {"coordinates":[9.7969655991,45.6798286438],"type":"Point"}
}