{
  "type": "Feature",
  "properties": {
    "iso:country":"IT",
    "sg:address":"37, Via San Bernardino 24040 Lallio",
    "sg:city":"Lallio",
    "sg:classifiers":[
        {
            "category":"Manufacturing",
            "subcategory":"Metals",
            "type":"Manufacturing & Wholesale Goods"
        }
    ],
    "sg:phone":"+39 39035691127",
    "sg:postcode":"24040",
    "sg:province":"Bergamo",
    "sg:tags":[
        "metallurgy",
        "metalworking"
    ],
    "wof:name":"Metalma (s.p.a.)",
    "wof:placetype":"venue"
},
  "geometry": {"coordinates":[9.6260185242,45.670337677],"type":"Point"}
}