{
  "type": "Feature",
  "properties": {
    "iso:country":"IT",
    "sg:address":"87032 Amantea",
    "sg:city":"Amantea",
    "sg:orig_category":"Lavanderie",
    "sg:phone":"+39 0982 46022",
    "sg:postcode":"87032",
    "sg:province":"Cosenza",
    "wof:name":"Lavanderia Mister Bianco Di Magnone A. & C. Snc",
    "wof:placetype":"venue"
},
  "geometry": {"coordinates":[16.093412,39.08651],"type":"Point"}
}