{
  "type": "Feature",
  "properties": {
    "iso:country":"IT",
    "sg:address":"31046 Oderzo",
    "sg:city":"Oderzo",
    "sg:orig_category":"Studi E Consulenze Amministrative, Commerciali E Aziendali. Consulenze Tecniche, Amministrative E Perizie. Professionisti - Studi E Servizi Ed Associazioni Di Interesse Aziendale",
    "sg:phone":"+39 0422 814181",
    "sg:postcode":"31046",
    "sg:province":"Treviso",
    "wof:name":"Filipozzi Dr. Gabriele",
    "wof:placetype":"venue"
},
  "geometry": {"coordinates":[12.492871,45.784386],"type":"Point"}
}