{
  "type": "Feature",
  "properties": {
    "addr:full":"106, Via Oberdan 22060 Arosio Arosio Como 22060",
    "addr:housenumber":"106",
    "addr:postcode":"22060;22060",
    "addr:street":"Via Oberdan",
    "iso:country":"IT",
    "sg:address":"106, Via Oberdan 22060 Arosio",
    "sg:city":"Arosio",
    "sg:classifiers":[
        {
            "category":"Shopping",
            "subcategory":"Crafts & Fabrics",
            "type":"Retail Goods"
        }
    ],
    "sg:phone":"+39 39031761024",
    "sg:postcode":"22060",
    "sg:province":"Como",
    "wof:name":"Tessitura Alberto Albertazzi (s.p.a.)",
    "wof:placetype":"venue"
},
  "geometry": {"coordinates":[9.0854558945,45.8119659424],"type":"Point"}
}