{
  "type": "Feature",
  "properties": {
    "iso:country":"IT",
    "sg:address":"84, Corso Marx Carlo 95045 Misterbianco",
    "sg:city":"Misterbianco",
    "sg:classifiers":[
        {
            "category":"Manufacturing",
            "subcategory":"Rubber & Plastics",
            "type":"Manufacturing & Wholesale Goods"
        }
    ],
    "sg:phone":"+39 39095471533",
    "sg:postcode":"95045",
    "sg:province":"Catania",
    "wof:name":"La Superior Di Palmeri Giuseppe S.a.s.",
    "wof:placetype":"venue"
},
  "geometry": {"coordinates":[15.026661,37.513203],"type":"Point"}
}