{
  "type": "Feature",
  "properties": {
    "addr:full":"35122 Padova Padova Padova 35122",
    "addr:postcode":"35122;35122",
    "iso:country":"IT",
    "sg:address":"35122 Padova",
    "sg:city":"Padova",
    "sg:orig_category":"Agenzie D'affari E Servizi Commerciali. Servizi Per Aziende, Manifestazioni E Supporto Agli Scambi Commerciali. Acqua, Luce, Gas E Societa' Di Esercizio Pubblico",
    "sg:phone":"+39 049 876 2530",
    "sg:postcode":"35122",
    "sg:province":"Padova",
    "wof:name":"Delegazione Commerciale D'austria",
    "wof:placetype":"venue"
},
  "geometry": {"coordinates":[11.870431,45.400311],"type":"Point"}
}