{
  "type": "Feature",
  "properties": {
    "iso:country":"IT",
    "sg:address":"125, Via Di Francia Canonico Annibale Maria 70059 Trani",
    "sg:city":"Trani",
    "sg:classifiers":[
        {
            "category":"Home & Garden",
            "subcategory":"Home Furnishings",
            "type":"Retail Goods"
        }
    ],
    "sg:phone":"+39 0883 509796",
    "sg:postcode":"70059",
    "sg:province":"Bari",
    "sg:tags":[
        "household"
    ],
    "wof:name":"Gusmai F.lli A. F. (s.r.l.)",
    "wof:placetype":"venue"
},
  "geometry": {"coordinates":[16.869291,41.126053],"type":"Point"}
}