{
  "type": "Feature",
  "properties": {
    "iso:country":"IT",
    "sg:address":"109, Via Delle Repubbliche Marinare 80146 Napoli",
    "sg:city":"Napoli",
    "sg:classifiers":[
        {
            "category":"Manufacturing",
            "subcategory":"Paper Products",
            "type":"Manufacturing & Wholesale Goods"
        }
    ],
    "sg:phone":"+39 081 752 4897",
    "sg:postcode":"80146",
    "sg:province":"Napoli",
    "sg:tags":[
        "cardboard"
    ],
    "wof:name":"Fintissue S.r.l.",
    "wof:placetype":"venue"
},
  "geometry": {"coordinates":[14.2901544571,40.9243583679],"type":"Point"}
}