{
  "type": "Feature",
  "properties": {
    "iso:country":"IT",
    "sg:address":"97013 Comiso",
    "sg:city":"Comiso",
    "sg:orig_category":"Termotecnica E Riscaldamento, Apparecchiature E Servizi",
    "sg:phone":"+39 0932 721111",
    "sg:postcode":"97013",
    "sg:province":"Ragusa",
    "wof:name":"Tauclima Srl",
    "wof:placetype":"venue"
},
  "geometry": {"coordinates":[14.602847,36.949608],"type":"Point"}
}