{
  "type": "Feature",
  "properties": {
    "addr:full":"63037 S. Benedetto Del Tronto AP",
    "addr:housenumber":"63037",
    "addr:street":"S. Benedetto Del Tronto Ap",
    "iso:country":"IT",
    "sg:address":"63037 S. Benedetto Del Tronto",
    "sg:orig_category":"Automobili E Mezzi Di Trasporto",
    "sg:phone":"+39 0735 753350",
    "sg:province":"AP",
    "wof:name":"Maxi Car Srl",
    "wof:placetype":"venue"
},
  "geometry": {"coordinates":[13.893513,42.905338],"type":"Point"}
}