{
  "type": "Feature",
  "properties": {
    "addr:full":"66100 Chieti Chieti Chieti 66100",
    "addr:postcode":"66100;66100",
    "iso:country":"IT",
    "sg:address":"66100 Chieti",
    "sg:city":"Chieti",
    "sg:orig_category":"Musica",
    "sg:phone":"+39 0871 561282",
    "sg:postcode":"66100",
    "sg:province":"Chieti",
    "wof:name":"Tosoni Pasquale",
    "wof:placetype":"venue"
},
  "geometry": {"coordinates":[14.1412906647,42.3649406433],"type":"Point"}
}