{
  "type": "Feature",
  "properties": {
    "iso:country":"IT",
    "sg:address":"08100 Nuoro",
    "sg:city":"Nuoro",
    "sg:orig_category":"Ricambi E Componenti Dei Mezzi Di Trasporto",
    "sg:phone":"+39 0784 39000",
    "sg:postcode":"08100",
    "sg:province":"Nuoro",
    "sg:website":"http://www.achilleflore.it",
    "wof:name":"Achille Flore Srl",
    "wof:placetype":"venue"
},
  "geometry": {"coordinates":[9.331828,40.318092],"type":"Point"}
}