{
  "type": "Feature",
  "properties": {
    "addr:full":"15, Lungo Mare Spalato 64021 Giulianova Giulianova Teramo 64021",
    "addr:housenumber":"15",
    "addr:postcode":"64021;64021",
    "addr:street":"Lungo Mare Spalato",
    "iso:country":"IT",
    "sg:address":"15, Lungo Mare Spalato 64021 Giulianova",
    "sg:city":"Giulianova",
    "sg:classifiers":[
        {
            "category":"Autos & Motor Vehicles",
            "subcategory":"Boat Sales",
            "type":"Retail Goods"
        }
    ],
    "sg:phone":"+39 085 800 0371",
    "sg:postcode":"64021",
    "sg:province":"Teramo",
    "wof:name":"Naval Comm S.r.l.",
    "wof:placetype":"venue"
},
  "geometry": {"coordinates":[13.698531,42.66127],"type":"Point"}
}