{
  "type": "Feature",
  "properties": {
    "addr:full":"24060 San Paolo D'argon Bergamo 24060",
    "addr:housenumber":"24060",
    "addr:postcode":"24060",
    "addr:street":"San",
    "iso:country":"IT",
    "sg:address":"24060 San Paolo D'argon",
    "sg:orig_category":"Alimentari - Produzione E Ingrosso",
    "sg:phone":"+39 035 959484",
    "sg:postcode":"24060",
    "sg:province":"Bergamo",
    "wof:name":"Orto Piu' Srl",
    "wof:placetype":"venue"
},
  "geometry": {"coordinates":[9.803463,45.689388],"type":"Point"}
}