{
  "type": "Feature",
  "properties": {
    "iso:country":"IT",
    "sg:address":"Via Cordusio 2, I-20123 Milan, Mi",
    "sg:classifiers":[
        {
            "category":"Banks & Credit Unions",
            "subcategory":"Bank",
            "type":"Services"
        }
    ],
    "sg:phone":"+39 02 723231",
    "sg:postcode":"20123",
    "sg:province":"Milano",
    "wof:name":"Creditanstalt Finanziaria Spa",
    "wof:placetype":"venue"
},
  "geometry": {"coordinates":[9.185772,45.464947],"type":"Point"}
}