{
  "type": "Feature",
  "properties": {
    "addr:full":"Via Cordusio 2, I-20123 Milan, Mi Milano 20123",
    "addr:housenumber":"2",
    "addr:postcode":"i-20123;20123",
    "addr:street":"Via Cordusio",
    "iso:country":"IT",
    "sg:address":"Via Cordusio 2, I-20123 Milan, Mi",
    "sg:classifiers":[
        {
            "category":"Banks & Credit Unions",
            "subcategory":"Bank",
            "type":"Services"
        }
    ],
    "sg:phone":"+39 02 723231",
    "sg:postcode":"20123",
    "sg:province":"Milano",
    "wof:name":"Creditanstalt Finanziaria Spa",
    "wof:placetype":"venue"
},
  "geometry": {"coordinates":[9.185772,45.464947],"type":"Point"}
}