{
  "type": "Feature",
  "properties": {
    "addr:full":"37010 Rivoli Veronese Rivoli Veronese Verona 37010",
    "addr:postcode":"37010;37010",
    "iso:country":"IT",
    "sg:address":"37010 Rivoli Veronese",
    "sg:city":"Rivoli Veronese",
    "sg:orig_category":"Forniture Per Edilizia E Lavori Pubblici",
    "sg:phone":"+39 045 626 9148",
    "sg:postcode":"37010",
    "sg:province":"Verona",
    "wof:name":"Marmi Furia Di Furia Felice & Alberto Snc",
    "wof:placetype":"venue"
},
  "geometry": {"coordinates":[10.8119287491,45.571559906],"type":"Point"}
}