{
  "type": "Feature",
  "properties": {
    "iso:country":"IT",
    "sg:address":"128/a, Via Callalta 31057 Silea",
    "sg:city":"Silea",
    "sg:classifiers":[
        {
            "category":"Utilities",
            "subcategory":"Electric",
            "type":"Services"
        }
    ],
    "sg:phone":"+39 0422 347107",
    "sg:postcode":"31057",
    "sg:province":"Treviso",
    "sg:tags":[
        "component",
        "electronic"
    ],
    "wof:name":"Siet Societa' Italiana Elettronica Trasformatori (s.r.l.)",
    "wof:placetype":"venue"
},
  "geometry": {"coordinates":[12.304931,45.664536],"type":"Point"}
}