{
  "type": "Feature",
  "properties": {
    "iso:country":"IT",
    "sg:address":"05100 Terni",
    "sg:city":"Terni",
    "sg:orig_category":"Ristorazione E Locali Pubblici Affini. Ristoranti Ed Esercizi Affini. Servizi Ausiliari Di Ristorazione E Di Intrattenimento",
    "sg:phone":"+39 0744 248060",
    "sg:postcode":"05100",
    "sg:province":"Terni",
    "sg:website":"http://www.lagiara.interfree.it",
    "wof:name":"La Giara Di Listante Lanfranco & C. Sas",
    "wof:placetype":"venue"
},
  "geometry": {"coordinates":[12.575104,42.590889],"type":"Point"}
}