{
  "type": "Feature",
  "properties": {
    "iso:country":"IT",
    "sg:address":"80014 Lago Patria",
    "sg:city":"Lago Patria",
    "sg:orig_category":"Zootecnia E Pesca, Allevamento Piccoli Animali",
    "sg:phone":"+39 081 509 1008",
    "sg:postcode":"80014",
    "sg:province":"Napoli",
    "wof:name":"Gallo Pasquale",
    "wof:placetype":"venue"
},
  "geometry": {"coordinates":[14.028258,40.916405],"type":"Point"}
}