{
  "type": "Feature",
  "properties": {
    "addr:full":"95129 Catania Catania Catania 95129",
    "addr:postcode":"95129;95129",
    "iso:country":"IT",
    "sg:address":"95129 Catania",
    "sg:city":"Catania",
    "sg:orig_category":"Forniture Per Agricoltura E Zootecnia. Animali Domestici",
    "sg:phone":"+39 0333 260 3831",
    "sg:postcode":"95129",
    "sg:province":"Catania",
    "wof:name":"Allevamento Amatoriale 'del Parco'",
    "wof:placetype":"venue"
},
  "geometry": {"coordinates":[15.1026906967,37.5135955811],"type":"Point"}
}