{
  "type": "Feature",
  "properties": {
    "iso:country":"IT",
    "sg:address":"00136 Roma",
    "sg:city":"Roma",
    "sg:orig_category":"Pubblica Amministrazione",
    "sg:phone":"+39 06 390 8011",
    "sg:postcode":"00136",
    "sg:province":"Roma",
    "wof:name":"Maritele Marina Militare",
    "wof:placetype":"venue"
},
  "geometry": {"coordinates":[12.4504146576,41.9166412354],"type":"Point"}
}