{
  "type": "Feature",
  "properties": {
    "iso:country":"IT",
    "sg:address":"37122 Verona",
    "sg:city":"Verona",
    "sg:orig_category":"Servizi Editoriali. Shopping",
    "sg:phone":"+39 045 803 0073",
    "sg:postcode":"37122",
    "sg:province":"Verona",
    "wof:name":"Libreria Antiquaria Perini S.a.s.",
    "wof:placetype":"venue"
},
  "geometry": {"coordinates":[10.98892,45.436337],"type":"Point"}
}