{
  "type": "Feature",
  "properties": {
    "iso:country":"IT",
    "sg:address":"00040 Roma",
    "sg:classifiers":[
        {
            "category":"Farming",
            "subcategory":"Fish & Marine Products",
            "type":"Manufacturing & Wholesale Goods"
        }
    ],
    "sg:phone":"+39 06 718 2712",
    "sg:postcode":"00040",
    "sg:province":"Roma",
    "sg:tags":[
        "equipment",
        "engineering",
        "industrial",
        "electrical",
        "electronic"
    ],
    "wof:name":"Leur Trasporti Sas",
    "wof:placetype":"venue"
},
  "geometry": {"coordinates":[12.62756,41.80888],"type":"Point"}
}