{
  "type": "Feature",
  "properties": {
    "iso:country":"IT",
    "sg:address":"20035 Lissone",
    "sg:city":"Lissone",
    "sg:orig_category":"Servizi E Lavori Per Abbigliamento E Pelletterie. Arte Ed Artigianato Artistico. Shopping",
    "sg:phone":"+39 039 245 7052",
    "sg:postcode":"20035",
    "sg:province":"Milano",
    "wof:name":"Uni Cuoio (s.r.l.)",
    "wof:placetype":"venue"
},
  "geometry": {"coordinates":[9.241096,45.60265],"type":"Point"}
}