{
  "type": "Feature",
  "properties": {
    "addr:full":"2, V. Granella 27058 Voghera Voghera Pavia 27058",
    "addr:housenumber":"2",
    "addr:postcode":"27058;27058",
    "addr:street":"Granella",
    "iso:country":"IT",
    "sg:address":"2, V. Granella 27058 Voghera",
    "sg:city":"Voghera",
    "sg:classifiers":[
        {
            "category":"Farming",
            "subcategory":"Livestock Farm",
            "type":"Manufacturing & Wholesale Goods"
        }
    ],
    "sg:phone":"+39 0383 369839",
    "sg:postcode":"27058",
    "sg:province":"Pavia",
    "sg:tags":[
        "agriculture"
    ],
    "sg:website":"http://www.paginegialle.it/naresegabri",
    "wof:name":"Narese Gabriele",
    "wof:placetype":"venue"
},
  "geometry": {"coordinates":[9.020678,45.009159],"type":"Point"}
}