{
  "type": "Feature",
  "properties": {
    "iso:country":"IT",
    "sg:address":"84091 Battipaglia",
    "sg:city":"Battipaglia",
    "sg:orig_category":"Prodotti Di Base E Forniture Per Industria Alimentare E Bevande. Carta, Cartone E Prodotti Primari. Forniture Per Attivita' Commerciali Ed Artigianali",
    "sg:phone":"+39 0828 304455",
    "sg:postcode":"84091",
    "sg:province":"Salerno",
    "wof:name":"De.cal.plast. Di Della Calce Sergio",
    "wof:placetype":"venue"
},
  "geometry": {"coordinates":[14.993555069,40.6045532227],"type":"Point"}
}