{
  "type": "Feature",
  "properties": {
    "iso:country":"IT",
    "sg:address":"16129 Genova",
    "sg:city":"Genova",
    "sg:orig_category":"Serramenti Ed Infissi",
    "sg:phone":"+39 010 312473",
    "sg:postcode":"16129",
    "sg:province":"Genova",
    "wof:name":"Centrocasa Di Mancini Luigi",
    "wof:placetype":"venue"
},
  "geometry": {"coordinates":[8.950916,44.399509],"type":"Point"}
}