{
  "type": "Feature",
  "properties": {
    "addr:full":"36030 Montecchio Precalcino Montecchio Precalcino Vicenza 36030",
    "addr:postcode":"36030;36030",
    "iso:country":"IT",
    "sg:address":"36030 Montecchio Precalcino",
    "sg:city":"Montecchio Precalcino",
    "sg:orig_category":"Arredo Cucina Ed Elettrodomestici. Elettrodomestici",
    "sg:phone":"+39 0445 334111",
    "sg:postcode":"36030",
    "sg:province":"Vicenza",
    "wof:name":"Officine Dal Zotto Comm. Giorgio",
    "wof:placetype":"venue"
},
  "geometry": {"coordinates":[11.533187,45.68383],"type":"Point"}
}