{
  "type": "Feature",
  "properties": {
    "iso:country":"IT",
    "sg:address":"10153 Torino",
    "sg:city":"Torino",
    "sg:orig_category":"Forniture Per Edilizia E Lavori Pubblici",
    "sg:phone":"+39 011 899 0676",
    "sg:postcode":"10153",
    "sg:province":"Torino",
    "wof:name":"Leo J.",
    "wof:placetype":"venue"
},
  "geometry": {"coordinates":[7.7153511047,45.0732841492],"type":"Point"}
}