{
  "type": "Feature",
  "properties": {
    "addr:full":"50068 Rufina Rufina Firenze 50068",
    "addr:postcode":"50068;50068",
    "iso:country":"IT",
    "sg:address":"50068 Rufina",
    "sg:city":"Rufina",
    "sg:orig_category":"Agricoltura, Orticoltura E Floricoltura",
    "sg:phone":"+39 055 839 6002",
    "sg:postcode":"50068",
    "sg:province":"Firenze",
    "wof:name":"Ingrosso Fiorentino Srl",
    "wof:placetype":"venue"
},
  "geometry": {"coordinates":[11.485083,43.82579],"type":"Point"}
}