{
  "type": "Feature",
  "properties": {
    "addr:full":"56017 San Giuliano Terme San Giuliano Terme Pisa 56017",
    "addr:postcode":"56017;56017",
    "iso:country":"IT",
    "sg:address":"56017 San Giuliano Terme",
    "sg:city":"San Giuliano Terme",
    "sg:orig_category":"Ristorazione E Locali Pubblici Affini. Ristoranti Ed Esercizi Affini",
    "sg:phone":"+39 050 878795",
    "sg:postcode":"56017",
    "sg:province":"Pisa",
    "wof:name":"Cooperativa Alba Nuova Srl",
    "wof:placetype":"venue"
},
  "geometry": {"coordinates":[10.42067,43.725044],"type":"Point"}
}