{
  "type": "Feature",
  "properties": {
    "iso:country":"IT",
    "sg:address":"41042 Fiorano Modenese",
    "sg:city":"Fiorano Modenese",
    "sg:orig_category":"Ceramiche: Prodotti E Lavorazioni",
    "sg:phone":"+39 0536 927611",
    "sg:postcode":"41042",
    "sg:province":"Modena",
    "wof:name":"Ceramiche Provenza Srl",
    "wof:placetype":"venue"
},
  "geometry": {"coordinates":[10.85959,44.538795],"type":"Point"}
}