{
  "type": "Feature",
  "properties": {
    "iso:country":"IT",
    "sg:address":"4, Via El Alamein 31100 Treviso",
    "sg:city":"Treviso",
    "sg:classifiers":[
        {
            "category":"Manufacturing",
            "subcategory":"Food",
            "type":"Manufacturing & Wholesale Goods"
        }
    ],
    "sg:phone":"+39 0422 431153",
    "sg:postcode":"31100",
    "sg:province":"Treviso",
    "sg:tags":[
        "equipment",
        "processing",
        "-",
        "machinery"
    ],
    "wof:name":"Garbuio S.p.a.",
    "wof:placetype":"venue"
},
  "geometry": {"coordinates":[12.1943645477,45.689781189],"type":"Point"}
}