{
  "type": "Feature",
  "properties": {
    "iso:country":"IT",
    "sg:address":"22063 Cant\u00f9",
    "sg:orig_category":"Prodotti E Manufatti In Materie Plastiche",
    "sg:phone":"+39 031 735136",
    "sg:postcode":"22063",
    "sg:province":"Como",
    "wof:name":"Gaiotto C.r.b. Di Claudio, Renzo, Benedetto & C. Snc",
    "wof:placetype":"venue"
},
  "geometry": {"coordinates":[9.1556005478,45.7309265137],"type":"Point"}
}