{
  "type": "Feature",
  "properties": {
    "addr:full":"68, Via Palazzetto 33080 Prata Di Pordenone Prata di Pordenone Pordenone 33080",
    "addr:postcode":"33080;33080",
    "addr:street":"Via Palazzetto",
    "iso:country":"IT",
    "sg:address":"68, Via Palazzetto 33080 Prata Di Pordenone",
    "sg:city":"Prata di Pordenone",
    "sg:classifiers":[
        {
            "category":"Food & Beverages",
            "subcategory":"Groceries & Convenience Stores",
            "type":"Retail Goods"
        }
    ],
    "sg:phone":"+39 0434 605911",
    "sg:postcode":"33080",
    "sg:province":"Pordenone",
    "sg:tags":[
        "drink"
    ],
    "wof:name":"Villa Frattina S.p.a.",
    "wof:placetype":"venue"
},
  "geometry": {"coordinates":[12.559342,45.848175],"type":"Point"}
}