{
  "type": "Feature",
  "properties": {
    "iso:country":"IT",
    "sg:address":"33057 Palmanova",
    "sg:city":"Palmanova",
    "sg:orig_category":"Arredamenti E Mobili Professionali. Forniture Alle Strutture Ricettive",
    "sg:phone":"+39 0432 928894",
    "sg:postcode":"33057",
    "sg:province":"Udine",
    "wof:name":"Arredamenti Generali Angelini",
    "wof:placetype":"venue"
},
  "geometry": {"coordinates":[13.345739,45.912533],"type":"Point"}
}