{
  "type": "Feature",
  "properties": {
    "addr:full":"Via Leonardo Da Vinci 20 25064 Gussago Gussago Brescia 25064",
    "addr:housenumber":"20",
    "addr:postcode":"25064;25064",
    "addr:street":"Via Leonardo Da Vinci",
    "iso:country":"IT",
    "sg:address":"Via Leonardo Da Vinci 20 25064 Gussago",
    "sg:city":"Gussago",
    "sg:classifiers":[
        {
            "category":"Structure",
            "subcategory":"Bridge",
            "type":"Public Place"
        }
    ],
    "sg:phone":"+39 030 373 1180",
    "sg:postcode":"25064",
    "sg:province":"Brescia",
    "sg:tags":[
        "cemented",
        "powder",
        "carbide"
    ],
    "sg:website":"www.metalpolveri.it",
    "wof:name":"Metalpolveri Srl",
    "wof:placetype":"venue"
},
  "geometry": {"coordinates":[10.160076,45.555771],"type":"Point"}
}