{
  "type": "Feature",
  "properties": {
    "iso:country":"IT",
    "sg:address":"61030 Cartoceto",
    "sg:city":"Cartoceto",
    "sg:orig_category":"Arredo Cucina Ed Elettrodomestici",
    "sg:phone":"+39 0721 899988",
    "sg:postcode":"61030",
    "sg:province":"Pesaro E Urbino",
    "sg:website":"http://www.www.pedini.it",
    "wof:name":"Pedini Srl",
    "wof:placetype":"venue"
},
  "geometry": {"coordinates":[12.937982,43.775963],"type":"Point"}
}