{
  "type": "Feature",
  "properties": {
    "addr:full":"77/79, Via Lombardia 23888 Rovagnate Rovagnate Lecco 23888",
    "addr:housenumber":"77 / 79",
    "addr:postcode":"23888;23888",
    "addr:street":"Via Lombardia",
    "iso:country":"IT",
    "sg:address":"77/79, Via Lombardia 23888 Rovagnate",
    "sg:city":"Rovagnate",
    "sg:classifiers":[
        {
            "category":"Shopping",
            "type":"Retail Goods"
        }
    ],
    "sg:phone":"+39 39039570597",
    "sg:postcode":"23888",
    "sg:province":"Lecco",
    "sg:tags":[
        "finished",
        "-",
        "metallic"
    ],
    "wof:name":"New Bed (s.p.a..)",
    "wof:placetype":"venue"
},
  "geometry": {"coordinates":[9.3812389374,45.729549408],"type":"Point"}
}