{
  "type": "Feature",
  "properties": {
    "iso:country":"IT",
    "sg:address":"05039 Stroncone",
    "sg:city":"Stroncone",
    "sg:orig_category":"Trattamenti Termici E Superficiali Metalli, Galvanotecnica",
    "sg:phone":"+39 0744 609100",
    "sg:postcode":"05039",
    "sg:province":"Terni",
    "wof:name":"Sider Zinco S.r.l.",
    "wof:placetype":"venue"
},
  "geometry": {"coordinates":[12.656072,42.481777],"type":"Point"}
}