{
  "type": "Feature",
  "properties": {
    "addr:full":"Via Garibaldi 37; Comerio; 21025 Comerio Varese 21025",
    "addr:housenumber":"37",
    "addr:postcode":"21025;21025",
    "addr:street":"Via Garibaldi",
    "iso:country":"IT",
    "sg:address":"Via Garibaldi 37; Comerio; 21025",
    "sg:city":"Comerio",
    "sg:classifiers":[
        {
            "category":"Banks & Credit Unions",
            "subcategory":"Bank",
            "type":"Services"
        }
    ],
    "sg:phone":"+39 0332 737179",
    "sg:postcode":"21025",
    "sg:province":"Varese",
    "wof:name":"Istituto Bancario, San Paolo Di Torino Spa",
    "wof:placetype":"venue"
},
  "geometry": {"coordinates":[8.744475,45.840382],"type":"Point"}
}