{
  "type": "Feature",
  "properties": {
    "iso:country":"IT",
    "sg:address":"20127 Milano",
    "sg:city":"Milano",
    "sg:orig_category":"Cinematografia E Radiotelevisione",
    "sg:phone":"+39 02 282 2732",
    "sg:postcode":"20127",
    "sg:province":"Milano",
    "wof:name":"Cooperativa A.d.c. Attori Doppiatori Cinematografici A R.l.",
    "wof:placetype":"venue"
},
  "geometry": {"coordinates":[9.217348,45.48806],"type":"Point"}
}