{
  "type": "Feature",
  "properties": {
    "addr:full":"68/a, Via Per Sassuolo 41043 Formigine Formigine Modena 41043",
    "addr:housenumber":"68 / a",
    "addr:postcode":"41043;41043",
    "addr:street":"Via Per Sassuolo",
    "iso:country":"IT",
    "sg:address":"68/a, Via Per Sassuolo 41043 Formigine",
    "sg:city":"Formigine",
    "sg:classifiers":[
        {
            "category":"Manufacturing",
            "subcategory":"Metals",
            "type":"Manufacturing & Wholesale Goods"
        }
    ],
    "sg:phone":"+39 39059557210",
    "sg:postcode":"41043",
    "sg:province":"Modena",
    "sg:tags":[
        "processing"
    ],
    "wof:name":"Officine Lala (s.r.l.)",
    "wof:placetype":"venue"
},
  "geometry": {"coordinates":[10.7518672943,44.6062698364],"type":"Point"}
}