{
  "type": "Feature",
  "properties": {
    "iso:country":"IT",
    "sg:address":"64016 Sant'egidio Alla Vibrata",
    "sg:orig_category":"Automobili E Mezzi Di Trasporto",
    "sg:phone":"+39 0861 841171",
    "sg:postcode":"64016",
    "sg:province":"Teramo",
    "sg:website":"http://www.calvaresetrucks.com",
    "wof:name":"Calvarese Autocarri",
    "wof:placetype":"venue"
},
  "geometry": {"coordinates":[13.722977,42.816788],"type":"Point"}
}