{
  "type": "Feature",
  "properties": {
    "iso:country":"IT",
    "sg:address":"62019 Recanati",
    "sg:city":"Recanati",
    "sg:orig_category":"Forniture Per Abbigliamento E Pelletterie",
    "sg:phone":"+39 071 757 4296",
    "sg:postcode":"62019",
    "sg:province":"Macerata",
    "wof:name":"Arbotto Pepanella Fa.bo.re",
    "wof:placetype":"venue"
},
  "geometry": {"coordinates":[13.5347356796,43.4012489319],"type":"Point"}
}