{
  "type": "Feature",
  "properties": {
    "iso:country":"IT",
    "sg:address":"Via Evangelista Torricelli 15 25080 Mazzano",
    "sg:city":"Mazzano",
    "sg:orig_category":"Blanking, Punching, Stamping, Embossing And Drawing Dies, Progressive Dies",
    "sg:phone":"+39 030 212 1015",
    "sg:postcode":"25080",
    "sg:province":"Brescia",
    "sg:website":"www.bellegrandi.it",
    "wof:name":"Officina Meccanica F.lli Bellegrandi Di Cottini & Rovizzi Snc",
    "wof:placetype":"venue"
},
  "geometry": {"coordinates":[10.358829,45.495457],"type":"Point"}
}