{
  "type": "Feature",
  "properties": {
    "iso:country":"IT",
    "sg:address":"V.le Della Resistenza 21 87040 Castrolibero",
    "sg:city":"Castrolibero",
    "sg:classifiers":[
        {
            "category":"Wholesale",
            "subcategory":"Office Equipment",
            "type":"Manufacturing & Wholesale Goods"
        }
    ],
    "sg:phone":"+39 0984 454000",
    "sg:postcode":"87040",
    "sg:province":"Cosenza",
    "sg:tags":[
        "agency",
        "internet"
    ],
    "sg:website":"www.bottegainfo.it",
    "wof:name":"La Bottega Dell'informatica",
    "wof:placetype":"venue"
},
  "geometry": {"coordinates":[16.222227,39.306229],"type":"Point"}
}