{
  "type": "Feature",
  "properties": {
    "addr:full":"30030 Fosso' Venezia 30030",
    "addr:postcode":"30030;30030",
    "addr:street":"Fosso ' Venezia",
    "iso:country":"IT",
    "sg:address":"30030 Fosso'",
    "sg:orig_category":"Servizi E Lavori Per Ecologia E Smaltimento Rifiuti. Servizi Ausiliari Di Sorveglianza, Manutenzione E Pulizia",
    "sg:phone":"+39 041 466338",
    "sg:postcode":"30030",
    "sg:province":"Venezia",
    "wof:name":"Cal Di Candian Loris & C. Snc",
    "wof:placetype":"venue"
},
  "geometry": {"coordinates":[12.050482,45.386276],"type":"Point"}
}