{
  "type": "Feature",
  "properties": {
    "iso:country":"IT",
    "sg:address":"22, Via Del Tornitore 40138 Bologna",
    "sg:city":"Bologna",
    "sg:classifiers":[
        {
            "category":"Wholesale",
            "subcategory":"Medical Equipment & Supplies",
            "type":"Manufacturing & Wholesale Goods"
        }
    ],
    "sg:phone":"+39 39051535290",
    "sg:postcode":"40138",
    "sg:province":"Bologna",
    "sg:tags":[
        "-",
        "health",
        "instrument"
    ],
    "wof:name":"Seasonic Srl",
    "wof:placetype":"venue"
},
  "geometry": {"coordinates":[11.417488,44.50108],"type":"Point"}
}