{
  "type": "Feature",
  "properties": {
    "addr:full":"3, Viale Veneto 35020 Saonara Saonara Padova 35020",
    "addr:postcode":"35020;35020",
    "addr:street":"Viale Veneto",
    "iso:country":"IT",
    "sg:address":"3, Viale Veneto 35020 Saonara",
    "sg:city":"Saonara",
    "sg:classifiers":[
        {
            "category":"Manufacturing",
            "subcategory":"Motor Vehicles & Parts",
            "type":"Manufacturing & Wholesale Goods"
        }
    ],
    "sg:phone":"+39 049 879 1020",
    "sg:postcode":"35020",
    "sg:province":"Padova",
    "sg:tags":[
        "engine"
    ],
    "wof:name":"Mayr Italia (s.r.l.)",
    "wof:placetype":"venue"
},
  "geometry": {"coordinates":[11.959017,45.383492],"type":"Point"}
}