{
  "type": "Feature",
  "properties": {
    "iso:country":"IT",
    "sg:address":"20091 Bresso",
    "sg:city":"Bresso",
    "sg:orig_category":"Termotecnica E Riscaldamento, Apparecchiature E Servizi",
    "sg:phone":"+39 02 610 2389",
    "sg:postcode":"20091",
    "sg:province":"Milano",
    "wof:name":"Adami Giorgio & C. Snc",
    "wof:placetype":"venue"
},
  "geometry": {"coordinates":[9.185952,45.541008],"type":"Point"}
}