{
  "type": "Feature",
  "properties": {
    "iso:country":"IT",
    "sg:address":"Via Matteotti 117 24069 Trescore Balneario",
    "sg:city":"Trescore Balneario",
    "sg:classifiers":[
        {
            "category":"Parking",
            "subcategory":"Bicycle",
            "type":"Transportation"
        }
    ],
    "sg:phone":"+39 035 943636",
    "sg:postcode":"24069",
    "sg:province":"Bergamo",
    "sg:tags":[
        "wheel",
        "dull",
        "grinding"
    ],
    "sg:website":"www.gloxi.it",
    "wof:name":"Gloxi Italia S.r.l.",
    "wof:placetype":"venue"
},
  "geometry": {"coordinates":[9.822755,45.687763],"type":"Point"}
}