{
  "type": "Feature",
  "properties": {
    "iso:country":"IT",
    "sg:address":"4, Via Per Borriana 13876 Sandigliano",
    "sg:city":"Sandigliano",
    "sg:classifiers":[
        {
            "category":"Shopping",
            "subcategory":"Crafts & Fabrics",
            "type":"Retail Goods"
        }
    ],
    "sg:phone":"+39 015 249 3280",
    "sg:postcode":"13876",
    "sg:province":"Biella",
    "wof:name":"Evergreen (s.r.l.)",
    "wof:placetype":"venue"
},
  "geometry": {"coordinates":[8.0449428558,45.5302085876],"type":"Point"}
}