{
  "type": "Feature",
  "properties": {
    "addr:full":"00186 Roma Roma Roma 00186",
    "addr:postcode":"00186;00186",
    "iso:country":"IT",
    "sg:address":"00186 Roma",
    "sg:city":"Roma",
    "sg:orig_category":"Campeggio. Accessori Dei Mezzi Di Trasporto",
    "sg:phone":"+39 06 678 4885",
    "sg:postcode":"00186",
    "sg:province":"Roma",
    "wof:name":"Calo' Anselmo",
    "wof:placetype":"venue"
},
  "geometry": {"coordinates":[12.483891,41.887825],"type":"Point"}
}