{
  "type": "Feature",
  "properties": {
    "iso:country":"IT",
    "sg:address":"10017 Montanaro",
    "sg:city":"Montanaro",
    "sg:orig_category":"Forniture Per Abbigliamento E Pelletterie. Complementi Di Arredamento",
    "sg:phone":"+39 011 919 3574",
    "sg:postcode":"10017",
    "sg:province":"Torino",
    "wof:name":"Passamaneria Piemontese Snc Di Shamku Zamira E C.",
    "wof:placetype":"venue"
},
  "geometry": {"coordinates":[8.3989200592,45.4623451233],"type":"Point"}
}