{
  "type": "Feature",
  "properties": {
    "iso:country":"IT",
    "sg:address":"13018 Valduggia",
    "sg:city":"Valduggia",
    "sg:orig_category":"Valvole E Apparecchiature Di Misura. Minuterie Metalliche E Ferramenta. Forniture Per Attivita' Industriali",
    "sg:phone":"+39 0163 47276",
    "sg:postcode":"13018",
    "sg:province":"Vercelli",
    "wof:name":"A.m.c.o. Snc",
    "wof:placetype":"venue"
},
  "geometry": {"coordinates":[8.345448,45.736012],"type":"Point"}
}