{
  "type": "Feature",
  "properties": {
    "addr:full":"90100 Palermo PA",
    "addr:postcode":"90100",
    "iso:country":"IT",
    "sg:address":"90100 Palermo",
    "sg:orig_category":"Forniture Per Abbigliamento E Pelletterie. Forniture Per Attivita' Commerciali Ed Artigianali",
    "sg:phone":"+39 091 688 2504",
    "sg:province":"PA",
    "wof:name":"Centro Vetrinistico Lo Conte S.r.l.",
    "wof:placetype":"venue"
},
  "geometry": {"coordinates":[13.3584499359,38.1213111877],"type":"Point"}
}