{
  "type": "Feature",
  "properties": {
    "iso:country":"IT",
    "sg:address":"80143 Napoli",
    "sg:city":"Napoli",
    "sg:orig_category":"Salotti, Poltrone, Sedie E Tavoli",
    "sg:phone":"+39 081 562 8498",
    "sg:postcode":"80143",
    "sg:province":"Napoli",
    "sg:website":"http://www.alfredoguerri.it",
    "wof:name":"Alfredo Guerri Arredamenti Sas",
    "wof:placetype":"venue"
},
  "geometry": {"coordinates":[14.282045,40.856991],"type":"Point"}
}