{
  "type": "Feature",
  "properties": {
    "iso:country":"IT",
    "sg:address":"40013 Castel Maggiore",
    "sg:city":"Castel Maggiore",
    "sg:orig_category":"Cartotecnica E Servizi. Composizione, Stampa E Confezione. Forniture E Prodotti Informatici. Forniture Per Congressi, Fiere E Manifestazioni",
    "sg:phone":"+39 051 417 8311",
    "sg:postcode":"40013",
    "sg:province":"Bologna",
    "wof:name":"Kaba Srl",
    "wof:placetype":"venue"
},
  "geometry": {"coordinates":[11.366593,44.558693],"type":"Point"}
}