{
  "type": "Feature",
  "properties": {
    "iso:country":"IT",
    "sg:address":"81025 Marcianise",
    "sg:city":"Marcianise",
    "sg:classifiers":[
        {
            "category":"Manufacturing",
            "subcategory":"Tobacco Products",
            "type":"Manufacturing & Wholesale Goods"
        }
    ],
    "sg:phone":"+39 0823 821210",
    "sg:postcode":"81025",
    "sg:province":"Caserta",
    "sg:tags":[
        "activities",
        "refuse",
        "industrial",
        "supply",
        "disposal",
        "environmental",
        "chemicals",
        "protection",
        "products",
        "machinery",
        "supplies",
        "secondary"
    ],
    "sg:website":"http://www.rea.it",
    "wof:name":"Rea Srl Industria Chimica",
    "wof:placetype":"venue"
},
  "geometry": {"coordinates":[14.297743,41.015236],"type":"Point"}
}