{
  "type": "Feature",
  "properties": {
    "iso:country":"IT",
    "sg:address":"Via Monte S. Pietro 25/c 61049 Urbania",
    "sg:city":"Urbania",
    "sg:classifiers":[
        {
            "category":"Ferry Terminal",
            "type":"Transportation"
        }
    ],
    "sg:phone":"+39 0722 318644",
    "sg:postcode":"61049",
    "sg:province":"Pesaro E Urbino",
    "sg:tags":[
        "casual",
        "shirt"
    ],
    "wof:name":"Ideal Blue Manifatture Spa",
    "wof:placetype":"venue"
},
  "geometry": {"coordinates":[12.529803,43.633556],"type":"Point"}
}