{
  "type": "Feature",
  "properties": {
    "iso:country":"IT",
    "sg:address":"80026 Casoria",
    "sg:city":"Casoria",
    "sg:orig_category":"Elettronica Professionale E Di Consumo. Automazione E Macchine Per Ufficio",
    "sg:phone":"+39 081 540 2840",
    "sg:postcode":"80026",
    "sg:province":"Napoli",
    "wof:name":"Idea Ufficio Snc",
    "wof:placetype":"venue"
},
  "geometry": {"coordinates":[14.30167,40.915234],"type":"Point"}
}