{
  "type": "Feature",
  "properties": {
    "iso:country":"IT",
    "sg:address":"31050 Vedelago",
    "sg:city":"Vedelago",
    "sg:orig_category":"Lavorazioni Metalli, Stampaggio E Saldatura",
    "sg:phone":"+39 0423 478172",
    "sg:postcode":"31050",
    "sg:province":"Treviso",
    "wof:name":"F.a.m. Srl",
    "wof:placetype":"venue"
},
  "geometry": {"coordinates":[12.124266,45.677055],"type":"Point"}
}