{
  "type": "Feature",
  "properties": {
    "iso:country":"IT",
    "sg:address":"50144 Firenze",
    "sg:city":"Firenze",
    "sg:classifiers":[
        {
            "category":"Shopping",
            "subcategory":"Clothing, Apparel, & Fashions",
            "type":"Retail Goods"
        }
    ],
    "sg:phone":"+39 055 354655",
    "sg:postcode":"50144",
    "sg:province":"Firenze",
    "sg:tags":[
        "activities",
        "goods",
        "supply",
        "leather",
        "commercial",
        "artisan",
        "supplies",
        "clothing"
    ],
    "wof:name":"Fratelli Reali E C. Spa",
    "wof:placetype":"venue"
},
  "geometry": {"coordinates":[11.226877,43.782269],"type":"Point"}
}