{
  "type": "Feature",
  "properties": {
    "iso:country":"IT",
    "sg:address":"9, Via Delle Ancone 38060 Volano",
    "sg:city":"Volano",
    "sg:classifiers":[
        {
            "category":"Shopping",
            "type":"Retail Goods"
        }
    ],
    "sg:phone":"+39 0464 411141",
    "sg:postcode":"38060",
    "sg:province":"Trento",
    "sg:tags":[
        "finished",
        "-",
        "metallic"
    ],
    "wof:name":"La Segnaletica Di Stiz A. (s.n.c.)",
    "wof:placetype":"venue"
},
  "geometry": {"coordinates":[11.076048851,45.9170608521],"type":"Point"}
}