{
  "type": "Feature",
  "properties": {
    "iso:country":"IT",
    "sg:address":"Zona Industriale Sn 64046 Montorio Al Vomano",
    "sg:city":"Montorio al Vomano",
    "sg:classifiers":[
        {
            "category":"Shopping",
            "subcategory":"Stationery & Office Supplies",
            "type":"Retail Goods"
        }
    ],
    "sg:phone":"+39 0861 592646",
    "sg:postcode":"64046",
    "sg:province":"Teramo",
    "sg:tags":[
        "furniture"
    ],
    "sg:website":"www.pragma-srl.com",
    "wof:name":"Pragma Srl",
    "wof:placetype":"venue"
},
  "geometry": {"coordinates":[13.698531,42.66127],"type":"Point"}
}