{
  "type": "Feature",
  "properties": {
    "iso:country":"IT",
    "sg:address":"Via Lesina ,63/65 24030 Brembate Di Sopra",
    "sg:city":"Brembate di Sopra",
    "sg:classifiers":[
        {
            "category":"Banks & Credit Unions",
            "subcategory":"Bureau De Change",
            "type":"Services"
        }
    ],
    "sg:phone":"+39 035 621759",
    "sg:postcode":"24030",
    "sg:province":"Bergamo",
    "sg:tags":[
        "punching",
        "series",
        "press"
    ],
    "sg:website":"www.ma-el.it",
    "wof:name":"Ma.el Srl",
    "wof:placetype":"venue"
},
  "geometry": {"coordinates":[9.575651,45.710808],"type":"Point"}
}