{
  "type": "Feature",
  "properties": {
    "iso:country":"IT",
    "sg:address":"20017 Rho",
    "sg:city":"Rho",
    "sg:classifiers":[
        {
            "category":"Professional",
            "subcategory":"Engineering",
            "type":"Services"
        }
    ],
    "sg:phone":"+39 02 9350 2875",
    "sg:postcode":"20017",
    "sg:province":"Milano",
    "sg:tags":[
        "component",
        "material",
        "electronic"
    ],
    "wof:name":"Itaca Srl",
    "wof:placetype":"venue"
},
  "geometry": {"coordinates":[9.05262,45.525738],"type":"Point"}
}