{
  "type": "Feature",
  "properties": {
    "addr:full":"22073 Fino Mornasco Fino Mornasco Como 22073",
    "addr:postcode":"22073;22073",
    "iso:country":"IT",
    "sg:address":"22073 Fino Mornasco",
    "sg:city":"Fino Mornasco",
    "sg:orig_category":"Pastifici - Impianti E Macchine",
    "sg:phone":"+39 031 921876",
    "sg:postcode":"22073",
    "sg:province":"Como",
    "wof:name":"Capitani Snc",
    "wof:placetype":"venue"
},
  "geometry": {"coordinates":[9.0575180054,45.7357177734],"type":"Point"}
}