{
  "type": "Feature",
  "properties": {
    "addr:full":"09098 Terralba Terralba Oristano 09098",
    "addr:postcode":"09098;09098",
    "iso:country":"IT",
    "sg:address":"09098 Terralba",
    "sg:city":"Terralba",
    "sg:orig_category":"Arredo Cucina Ed Elettrodomestici. Elettrodomestici",
    "sg:phone":"+39 0783 81872",
    "sg:postcode":"09098",
    "sg:province":"Oristano",
    "wof:name":"Pistis Maria Snc",
    "wof:placetype":"venue"
},
  "geometry": {"coordinates":[8.64362,39.719063],"type":"Point"}
}