{
  "type": "Feature",
  "properties": {
    "iso:country":"IT",
    "sg:address":"1, Via Francia 37069 Villafranca Di Verona",
    "sg:city":"Villafranca di Verona",
    "sg:classifiers":[
        {
            "category":"Personal",
            "subcategory":"Shoe Repair & Shine",
            "type":"Services"
        }
    ],
    "sg:phone":"+39 045 630 3412",
    "sg:postcode":"37069",
    "sg:province":"Verona",
    "sg:tags":[
        "leather"
    ],
    "wof:name":"Bontex Italia (s.r.l.)",
    "wof:placetype":"venue"
},
  "geometry": {"coordinates":[10.975283,45.409538],"type":"Point"}
}