{
  "type": "Feature",
  "properties": {
    "iso:country":"IT",
    "sg:address":"18038 Sanremo",
    "sg:orig_category":"Prodotti Finiti Stampati. Shopping. Regalistica Aziendale",
    "sg:phone":"+39 0184 572475",
    "sg:postcode":"18038",
    "sg:province":"Imperia",
    "wof:name":"Il Nuovo Atelier Snc",
    "wof:placetype":"venue"
},
  "geometry": {"coordinates":[7.7741298676,43.8163299561],"type":"Point"}
}