{
  "type": "Feature",
  "properties": {
    "addr:full":"5, Via Delle Colonie 19020 Brugnato Brugnato La Spezia 19020",
    "addr:postcode":"19020;19020",
    "addr:street":"Via Delle Colonie",
    "iso:country":"IT",
    "sg:address":"5, Via Delle Colonie 19020 Brugnato",
    "sg:city":"Brugnato",
    "sg:classifiers":[
        {
            "category":"Real Estate",
            "subcategory":"Architect",
            "type":"Services"
        }
    ],
    "sg:phone":"+39 0187 897282",
    "sg:postcode":"19020",
    "sg:province":"La Spezia",
    "sg:tags":[
        "textile",
        "clothing"
    ],
    "wof:name":"Consorzio Liguria",
    "wof:placetype":"venue"
},
  "geometry": {"coordinates":[9.829219,44.106735],"type":"Point"}
}