{
  "type": "Feature",
  "properties": {
    "iso:country":"IT",
    "sg:address":"10023 Chieri",
    "sg:city":"Chieri",
    "sg:orig_category":"Non-classified Establishments",
    "sg:phone":"+39 011 941 4446",
    "sg:postcode":"10023",
    "sg:province":"Torino",
    "wof:name":"Mammaorsa Di Bona Pier Paola",
    "wof:placetype":"venue"
},
  "geometry": {"coordinates":[7.825376,45.003212],"type":"Point"}
}