{
  "type": "Feature",
  "properties": {
    "iso:country":"IT",
    "sg:address":"43022 Montechiarugolo",
    "sg:city":"Montechiarugolo",
    "sg:classifiers":[
        {
            "category":"Restaurant",
            "type":"Food & Drink"
        }
    ],
    "sg:phone":"+39 0521 681754",
    "sg:postcode":"43022",
    "sg:province":"Parma",
    "sg:tags":[
        "equipment",
        "industry",
        "machinery"
    ],
    "wof:name":"Rovom Snc",
    "wof:placetype":"venue"
},
  "geometry": {"coordinates":[10.3722496033,44.7008056641],"type":"Point"}
}