{
  "type": "Feature",
  "properties": {
    "addr:full":"20094 Corsico Corsico Milano 20094",
    "addr:postcode":"20094;20094",
    "iso:country":"IT",
    "sg:address":"20094 Corsico",
    "sg:city":"Corsico",
    "sg:orig_category":"Elettrotecnica Industriale, Prodotti E Apparecchiature. Elettronica Industriale, Prodotti E Apparecchiature. Macchine, Strumenti Ed Apparecchi Per Attivita' Industriali",
    "sg:phone":"+39 02 448781",
    "sg:postcode":"20094",
    "sg:province":"Milano",
    "wof:name":"I.m.e. Spa",
    "wof:placetype":"venue"
},
  "geometry": {"coordinates":[9.112024,45.445877],"type":"Point"}
}