{
  "type": "Feature",
  "properties": {
    "iso:country":"IT",
    "sg:address":"06127 Perugia",
    "sg:city":"Perugia",
    "sg:orig_category":"Ospedali E Servizi Sanitari. Pubblica Amministrazione. Servizi Sociali",
    "sg:phone":"+39 0755411",
    "sg:postcode":"06127",
    "sg:province":"Perugia",
    "sg:website":"http://www.ausl2.umbria.it",
    "wof:name":"Unit\u00c0 Sanitaria Locale N. 2",
    "wof:placetype":"venue"
},
  "geometry": {"coordinates":[12.365883,43.105137],"type":"Point"}
}