{
  "type": "Feature",
  "properties": {
    "iso:country":"IT",
    "sg:address":"Via Astalonga 80047 San Giuseppe Vesuviano",
    "sg:city":"San Giuseppe Vesuviano",
    "sg:classifiers":[
        {
            "category":"Shopping",
            "subcategory":"Clothing, Apparel, & Fashions",
            "type":"Retail Goods"
        }
    ],
    "sg:phone":"+39 081 529 4928",
    "sg:postcode":"80047",
    "sg:province":"Napoli",
    "sg:tags":[
        "clothes"
    ],
    "wof:name":"B. D. G. Srl",
    "wof:placetype":"venue"
},
  "geometry": {"coordinates":[14.493877,40.838512],"type":"Point"}
}