{
  "type": "Feature",
  "properties": {
    "iso:country":"IT",
    "sg:address":"25128 Brescia",
    "sg:city":"Brescia",
    "sg:classifiers":[
        {
            "category":"Building & Trades",
            "subcategory":"Construction",
            "type":"Services"
        }
    ],
    "sg:phone":"+39 030 390854",
    "sg:postcode":"25128",
    "sg:province":"Brescia",
    "sg:tags":[
        "equipment",
        "heat",
        "heating",
        "engineering"
    ],
    "wof:name":"Berlini Francesco E Zanferrari G. Carlo Snc",
    "wof:placetype":"venue"
},
  "geometry": {"coordinates":[10.220082,45.557796],"type":"Point"}
}