{
  "type": "Feature",
  "properties": {
    "iso:country":"IT",
    "sg:address":"22, Via Madonna Delle Grazie 80017 Melito Di Napoli",
    "sg:city":"Melito di Napoli",
    "sg:classifiers":[
        {
            "category":"Manufacturing",
            "subcategory":"Glass & Minerals",
            "type":"Manufacturing & Wholesale Goods"
        }
    ],
    "sg:phone":"+39 081 711 4256",
    "sg:postcode":"80017",
    "sg:province":"Napoli",
    "wof:name":"Creazioni Silvestri Di Silvestri R. & C. Sas",
    "wof:placetype":"venue"
},
  "geometry": {"coordinates":[14.22241,40.918274],"type":"Point"}
}