{
  "type": "Feature",
  "properties": {
    "iso:country":"IT",
    "sg:address":"81100 Caserta",
    "sg:city":"Caserta",
    "sg:orig_category":"Prodotti E Manufatti In Materie Plastiche. Articoli Per Imballaggio E Confezionamento",
    "sg:phone":"+39 0823 344319",
    "sg:postcode":"81100",
    "sg:province":"Caserta",
    "wof:name":"Leardi Daniele",
    "wof:placetype":"venue"
},
  "geometry": {"coordinates":[14.3288393021,41.0673065186],"type":"Point"}
}