{
  "type": "Feature",
  "properties": {
    "iso:country":"IT",
    "sg:address":"80142 Napoli",
    "sg:city":"Napoli",
    "sg:orig_category":"Accessori Moda D'abbigliamento",
    "sg:phone":"+39 081 287437",
    "sg:postcode":"80142",
    "sg:province":"Napoli",
    "wof:name":"Framar Ingrosso S.r.l.",
    "wof:placetype":"venue"
},
  "geometry": {"coordinates":[14.267687,40.850822],"type":"Point"}
}