{
  "type": "Feature",
  "properties": {
    "iso:country":"IT",
    "sg:address":"97100 Ragusa",
    "sg:city":"Ragusa",
    "sg:classifiers":[
        {
            "category":"Bars & Pubs",
            "subcategory":"Champagne Bar",
            "type":"Food & Drink"
        }
    ],
    "sg:phone":"+39 0932 651403",
    "sg:postcode":"97100",
    "sg:province":"Ragusa",
    "sg:tags":[
        "caffe'",
        "e"
    ],
    "wof:name":"Ristorante Mediterraneo - Ristor House Sas",
    "wof:placetype":"venue"
},
  "geometry": {"coordinates":[14.524183,36.826019],"type":"Point"}
}