{
  "type": "Feature",
  "properties": {
    "addr:full":"37036 San Martino Buon Albergo San Martino Buon Albergo Verona 37036",
    "addr:housenumber":"37036",
    "addr:postcode":"buon albergo;37036",
    "iso:country":"IT",
    "sg:address":"37036 San Martino Buon Albergo",
    "sg:city":"San Martino Buon Albergo",
    "sg:orig_category":"Alberghi",
    "sg:phone":"+39 045 878 0222",
    "sg:postcode":"37036",
    "sg:province":"Verona",
    "wof:name":"Hotel Turismo Di Boscolo Giovanni E C. Snc",
    "wof:placetype":"venue"
},
  "geometry": {"coordinates":[11.109552,45.421322],"type":"Point"}
}