{
  "type": "Feature",
  "properties": {
    "iso:country":"IT",
    "sg:address":"36021 Villaga",
    "sg:city":"Villaga",
    "sg:orig_category":"Bevande, Vini E Liquori. Servizi E Lavori Per Industria Alimentare E Bevande",
    "sg:phone":"+39 0444 885074",
    "sg:postcode":"36021",
    "sg:province":"Vicenza",
    "wof:name":"Distilleria Li.di.a.",
    "wof:placetype":"venue"
},
  "geometry": {"coordinates":[11.536315,45.37775],"type":"Point"}
}