{
  "type": "Feature",
  "properties": {
    "iso:country":"IT",
    "sg:address":"61033 Fermignano",
    "sg:city":"Fermignano",
    "sg:orig_category":"Macchine Ed Impianti Per Edilizia E Lavori Pubblici",
    "sg:phone":"+39 0722 333013",
    "sg:postcode":"61033",
    "sg:province":"Pesaro E Urbino",
    "wof:name":"Techno-in Srl",
    "wof:placetype":"venue"
},
  "geometry": {"coordinates":[12.529803,43.633556],"type":"Point"}
}