{
  "type": "Feature",
  "properties": {
    "addr:full":"9, Via Vivaldi Antonio 00199 Roma Roma Roma 00199",
    "addr:postcode":"00199;00199",
    "addr:street":"Via Vivaldi Antonio",
    "iso:country":"IT",
    "sg:address":"9, Via Vivaldi Antonio 00199 Roma",
    "sg:city":"Roma",
    "sg:classifiers":[
        {
            "category":"Wholesale",
            "subcategory":"Drugs",
            "type":"Manufacturing & Wholesale Goods"
        }
    ],
    "sg:phone":"+39 06 8620 3006",
    "sg:postcode":"00199",
    "sg:province":"Roma",
    "sg:tags":[
        "chemical",
        "pharmaceutical"
    ],
    "wof:name":"U.ra.g.me. (s.a.s.)",
    "wof:placetype":"venue"
},
  "geometry": {"coordinates":[12.482325,41.895466],"type":"Point"}
}