{
  "type": "Feature",
  "properties": {
    "addr:full":"Zona Industriale 85020 Atella Atella Potenza 85020",
    "addr:postcode":"85020;85020",
    "addr:street":"Zona Industriale",
    "iso:country":"IT",
    "sg:address":"Zona Industriale 85020 Atella",
    "sg:city":"Atella",
    "sg:classifiers":[
        {
            "category":"Professional",
            "subcategory":"Engineering",
            "type":"Services"
        }
    ],
    "sg:phone":"+39 0972 715696",
    "sg:postcode":"85020",
    "sg:province":"Potenza",
    "sg:tags":[
        "machine",
        "-",
        "mechanical"
    ],
    "wof:name":"C.m.d. Costruzioni Motori Diesel Srl",
    "wof:placetype":"venue"
},
  "geometry": {"coordinates":[15.802221,40.637241],"type":"Point"}
}