{
  "type": "Feature",
  "properties": {
    "iso:country":"IT",
    "sg:address":"43100 Parma",
    "sg:city":"Parma",
    "sg:orig_category":"Forniture Per Attivita' Commerciali Ed Artigianali. Arredi Ed Attrezzature Per Attivita' Commerciali Ed Artigianali",
    "sg:phone":"+39 0521 291340",
    "sg:postcode":"43100",
    "sg:province":"Parma",
    "sg:website":"http://www.tamagnini.com",
    "wof:name":"Tamagnini Snc Di Tamagnini Sergio & C.",
    "wof:placetype":"venue"
},
  "geometry": {"coordinates":[10.3229598999,44.7756004333],"type":"Point"}
}