{
  "type": "Feature",
  "properties": {
    "iso:country":"IT",
    "sg:address":"20145 Milano",
    "sg:city":"Milano",
    "sg:orig_category":"Assicurazioni E Servizi Assicurativi",
    "sg:phone":"+39 02 4800 1050",
    "sg:postcode":"20145",
    "sg:province":"Milano",
    "wof:name":"Eurostudio Srl",
    "wof:placetype":"venue"
},
  "geometry": {"coordinates":[9.161902,45.476368],"type":"Point"}
}