{
  "type": "Feature",
  "properties": {
    "addr:full":"15/17, Via Cere' 38061 Ala Ala Trento 38061",
    "addr:housenumber":"15 / 17",
    "addr:postcode":"38061;38061",
    "addr:street":"Via Cere '",
    "iso:country":"IT",
    "sg:address":"15/17, Via Cere' 38061 Ala",
    "sg:city":"Ala",
    "sg:classifiers":[
        {
            "category":"Food & Beverages",
            "subcategory":"Groceries & Convenience Stores",
            "type":"Retail Goods"
        }
    ],
    "sg:phone":"+39 0464 670603",
    "sg:postcode":"38061",
    "sg:province":"Trento",
    "sg:tags":[
        "product",
        "related"
    ],
    "wof:name":"Ala Carni (s.r.l.)",
    "wof:placetype":"venue"
},
  "geometry": {"coordinates":[11.0045633316,45.7649459839],"type":"Point"}
}