{
  "type": "Feature",
  "properties": {
    "addr:full":"55100 Lucca Lucca Lucca 55100",
    "addr:postcode":"55100;55100",
    "iso:country":"IT",
    "sg:address":"55100 Lucca",
    "sg:city":"Lucca",
    "sg:orig_category":"Abbigliamento In Pelle - Vendita Al Dettaglio",
    "sg:phone":"+39 0583 955359",
    "sg:postcode":"55100",
    "sg:province":"Lucca",
    "sg:website":"http://www.la-pelle.it",
    "wof:name":"La Pelle",
    "wof:placetype":"venue"
},
  "geometry": {"coordinates":[10.527906,43.854897],"type":"Point"}
}