{
  "type": "Feature",
  "properties": {
    "iso:country":"IT",
    "sg:address":"80078 Pozzuoli",
    "sg:city":"Pozzuoli",
    "sg:classifiers":[
        {
            "category":"Sports & Exercise",
            "subcategory":"Tennis Court",
            "type":"Entertainment"
        }
    ],
    "sg:phone":"+39 081 524 6884",
    "sg:postcode":"80078",
    "sg:province":"Napoli",
    "sg:tags":[
        "e",
        "lo",
        "tempo",
        "libero",
        "per",
        "impianti",
        "il",
        "attrezzature"
    ],
    "wof:name":"Pim Piscine Srl",
    "wof:placetype":"venue"
},
  "geometry": {"coordinates":[14.088517,40.843346],"type":"Point"}
}