{
  "type": "Feature",
  "properties": {
    "iso:country":"IT",
    "sg:address":"1 Piazza Armando Diaz, 58052 Magliano In Toscana",
    "sg:classifiers":[
        {
            "category":"Banks & Credit Unions",
            "subcategory":"Financial Services",
            "type":"Services"
        }
    ],
    "sg:phone":"+39 0564 589808",
    "sg:province":"GR",
    "sg:tags":[
        "banking",
        "finance",
        "insurance"
    ],
    "wof:name":"Banca Di Credito Cooperativo Della Maremma Greossetana Soc Coop A Rl",
    "wof:placetype":"venue"
},
  "geometry": {"coordinates":[11.0729999542,42.7452011108],"type":"Point"}
}