{
  "type": "Feature",
  "properties": {
    "addr:full":"04024 Gaeta Gaeta Latina 04024",
    "addr:postcode":"04024;04024",
    "iso:country":"IT",
    "sg:address":"04024 Gaeta",
    "sg:city":"Gaeta",
    "sg:orig_category":"Prodotti Cosmetici E Da Toeletta",
    "sg:phone":"+39 0771 460239",
    "sg:postcode":"04024",
    "sg:province":"Latina",
    "wof:name":"Buttaro Rocco",
    "wof:placetype":"venue"
},
  "geometry": {"coordinates":[13.5661964417,41.2125434875],"type":"Point"}
}