{
  "type": "Feature",
  "properties": {
    "iso:country":"IT",
    "sg:address":"37129 Verona",
    "sg:city":"Verona",
    "sg:classifiers":[
        {
            "category":"Health Services",
            "subcategory":"Health Practitioner",
            "type":"Services"
        }
    ],
    "sg:phone":"+39 045 800 9405",
    "sg:postcode":"37129",
    "sg:province":"Verona",
    "sg:tags":[
        "medici"
    ],
    "wof:name":"Di Spigno Franco",
    "wof:placetype":"venue"
},
  "geometry": {"coordinates":[11.003195,45.444656],"type":"Point"}
}