{
  "type": "Feature",
  "properties": {
    "iso:country":"IT",
    "sg:address":"20080 Basiglio",
    "sg:city":"Basiglio",
    "sg:orig_category":"Sport - Articoli E Forniture",
    "sg:phone":"+39 02 9075 3759",
    "sg:postcode":"20080",
    "sg:province":"Milano",
    "wof:name":"Palgolf Srl",
    "wof:placetype":"venue"
},
  "geometry": {"coordinates":[9.175797,45.385601],"type":"Point"}
}