{
  "type": "Feature",
  "properties": {
    "addr:full":"22070 Solbiate Solbiate Como 22070",
    "addr:postcode":"22070;22070",
    "iso:country":"IT",
    "sg:address":"22070 Solbiate",
    "sg:city":"Solbiate",
    "sg:orig_category":"Servizi Al Turismo. Trasporto Pubblico E Privato. Acqua, Luce, Gas E Societa' Di Esercizio Pubblico",
    "sg:postcode":"22070",
    "sg:province":"Como",
    "wof:name":"Ferrovie Nord Milano Autoservizi (s.p.a.)",
    "wof:placetype":"venue"
},
  "geometry": {"coordinates":[8.987272,45.801643],"type":"Point"}
}