{
  "type": "Feature",
  "properties": {
    "iso:country":"IT",
    "sg:address":"16012 Busalla",
    "sg:city":"Busalla",
    "sg:orig_category":"Articoli Pulizia. Carta, Cartone E Prodotti Primari. Prodotti Cosmetici E Da Toeletta",
    "sg:phone":"+39 010 964 1840",
    "sg:postcode":"16012",
    "sg:province":"Genova",
    "wof:name":"Cabona Pietro Di Cabona Renato & C. Sas",
    "wof:placetype":"venue"
},
  "geometry": {"coordinates":[8.961462,44.572945],"type":"Point"}
}