{
  "type": "Feature",
  "properties": {
    "iso:country":"IT",
    "sg:address":"25085 Gavardo",
    "sg:city":"Gavardo",
    "sg:orig_category":"Servizi E Lavori Industria Chimica. Trattamenti Termici E Superficiali Metalli, Galvanotecnica",
    "sg:phone":"+39 036 537 4453",
    "sg:postcode":"25085",
    "sg:province":"Brescia",
    "wof:name":"F.m. Verniciature Di F. Marocchi",
    "wof:placetype":"venue"
},
  "geometry": {"coordinates":[10.419898,45.589684],"type":"Point"}
}