{
  "type": "Feature",
  "properties": {
    "iso:country":"IT",
    "sg:address":"09123 Cagliari",
    "sg:city":"Cagliari",
    "sg:orig_category":"Servizi Ausiliari Per Il Trasporto. Agenzie D'affari E Servizi Commerciali",
    "sg:phone":"+39 070 655395",
    "sg:postcode":"09123",
    "sg:province":"Cagliari",
    "wof:name":"Cincotta Feederferry Srl",
    "wof:placetype":"venue"
},
  "geometry": {"coordinates":[9.101801,39.213474],"type":"Point"}
}