{
  "type": "Feature",
  "properties": {
    "iso:country":"IT",
    "sg:address":"20011 Corbetta",
    "sg:city":"Corbetta",
    "sg:orig_category":"Tempo Libero - Articoli E Forniture. Automobili E Mezzi Di Trasporto",
    "sg:phone":"+39 02 977 1550",
    "sg:postcode":"20011",
    "sg:province":"Milano",
    "wof:name":"Cesare Rizzato & C. Spa",
    "wof:placetype":"venue"
},
  "geometry": {"coordinates":[8.933924,45.464149],"type":"Point"}
}