{
  "type": "Feature",
  "properties": {
    "addr:full":"20063 Cernusco Sul Naviglio Cernusco sul Naviglio Milano 20063",
    "addr:postcode":"20063;20063",
    "iso:country":"IT",
    "sg:address":"20063 Cernusco Sul Naviglio",
    "sg:city":"Cernusco sul Naviglio",
    "sg:orig_category":"Forniture Per Attivita' Commerciali Ed Artigianali. Arredi Ed Attrezzature Per Attivita' Commerciali Ed Artigianali",
    "sg:phone":"+39 02 9214 0064",
    "sg:postcode":"20063",
    "sg:province":"Milano",
    "wof:name":"Arredoshop (s.r.l.)",
    "wof:placetype":"venue"
},
  "geometry": {"coordinates":[9.2827157974,45.5322875977],"type":"Point"}
}