{
  "type": "Feature",
  "properties": {
    "iso:country":"IT",
    "sg:address":"158, Via Marino Parenti 46041 Asola",
    "sg:city":"Asola",
    "sg:classifiers":[
        {
            "category":"Shopping",
            "subcategory":"Clothing, Apparel, & Fashions",
            "type":"Retail Goods"
        }
    ],
    "sg:phone":"+39 0376 720018",
    "sg:postcode":"46041",
    "sg:province":"Mantova",
    "sg:tags":[
        "clothes"
    ],
    "wof:name":"Tintoria Elisa (s.n.c.)",
    "wof:placetype":"venue"
},
  "geometry": {"coordinates":[10.425656,45.22049],"type":"Point"}
}