{
  "type": "Feature",
  "properties": {
    "addr:full":"28, Via Michelangelo Buonarroti 22070 Carbonate Carbonate Como 22070",
    "addr:postcode":"22070;22070",
    "addr:street":"Via Michelangelo Buonarroti",
    "iso:country":"IT",
    "sg:address":"28, Via Michelangelo Buonarroti 22070 Carbonate",
    "sg:city":"Carbonate",
    "sg:classifiers":[
        {
            "category":"Manufacturing",
            "subcategory":"Metals",
            "type":"Manufacturing & Wholesale Goods"
        }
    ],
    "sg:phone":"+39 0331 832200",
    "sg:postcode":"22070",
    "sg:province":"Como",
    "sg:tags":[
        "processing"
    ],
    "wof:name":"Famit (s.r.l.)",
    "wof:placetype":"venue"
},
  "geometry": {"coordinates":[8.9257955551,45.6749382019],"type":"Point"}
}