{
  "type": "Feature",
  "properties": {
    "addr:full":"00153 Roma Roma Roma 00153",
    "addr:postcode":"00153;00153",
    "iso:country":"IT",
    "sg:address":"00153 Roma",
    "sg:city":"Roma",
    "sg:orig_category":"Pubblicita', Marketing E Comunicazione",
    "sg:phone":"+39 06 5833 3134",
    "sg:postcode":"00153",
    "sg:province":"Roma",
    "sg:website":"http://www.vivagroup.it",
    "wof:name":"Viva Group Srl",
    "wof:placetype":"venue"
},
  "geometry": {"coordinates":[12.4656934738,41.8760452271],"type":"Point"}
}