{
  "type": "Feature",
  "properties": {
    "iso:country":"IT",
    "sg:address":"8, Via Raffaello 23861 Cesana Brianza",
    "sg:city":"Cesana Brianza",
    "sg:classifiers":[
        {
            "category":"Food & Beverages",
            "subcategory":"Groceries & Convenience Stores",
            "type":"Retail Goods"
        }
    ],
    "sg:phone":"+39 39031655998",
    "sg:postcode":"23861",
    "sg:province":"Lecco",
    "sg:tags":[
        "product",
        "related"
    ],
    "wof:name":"Lem Market (s.p.a.)",
    "wof:placetype":"venue"
},
  "geometry": {"coordinates":[9.30859375,45.8143539429],"type":"Point"}
}