{
  "type": "Feature",
  "properties": {
    "iso:country":"IT",
    "sg:address":"36050 Sovizzo",
    "sg:city":"Sovizzo",
    "sg:orig_category":"Utensili Meccanici E Materiali",
    "sg:phone":"+39 0444 536389",
    "sg:postcode":"36050",
    "sg:province":"Vicenza",
    "wof:name":"Cerato Stampi Srl",
    "wof:placetype":"venue"
},
  "geometry": {"coordinates":[11.449955,45.527977],"type":"Point"}
}