{
  "type": "Feature",
  "properties": {
    "iso:country":"IT",
    "sg:address":"Via A. Grandi 35 47811 Viserba",
    "sg:classifiers":[
        {
            "category":"Shopping",
            "subcategory":"Crafts & Fabrics",
            "type":"Retail Goods"
        }
    ],
    "sg:phone":"+39 0541 732522",
    "sg:tags":[
        "industry",
        "shoe"
    ],
    "wof:name":"Conceria Tarricone Armando Sas",
    "wof:placetype":"venue"
},
  "geometry": {"coordinates":[12.5265645981,44.0744514465],"type":"Point"}
}