{
  "type": "Feature",
  "properties": {
    "addr:full":"43010 Vigatto Parma 43010",
    "addr:postcode":"43010;43010",
    "iso:country":"IT",
    "sg:address":"43010 Vigatto",
    "sg:orig_category":"Motori Ed Organi Di Trasmissione",
    "sg:phone":"+39 0521 648124",
    "sg:postcode":"43010",
    "sg:province":"Parma",
    "wof:name":"Cometa Pulegge S.r.l.",
    "wof:placetype":"venue"
},
  "geometry": {"coordinates":[10.3334102631,44.7520103455],"type":"Point"}
}