{
  "type": "Feature",
  "properties": {
    "iso:country":"IT",
    "sg:address":"95127 Catania",
    "sg:city":"Catania",
    "sg:orig_category":"Abbigliamento Esterno, Maglierie E Pelliccerie. Shopping",
    "sg:phone":"+39 095 374498",
    "sg:postcode":"95127",
    "sg:province":"Catania",
    "wof:name":"Colletta Anna Anteo",
    "wof:placetype":"venue"
},
  "geometry": {"coordinates":[15.101588,37.517502],"type":"Point"}
}