{
  "type": "Feature",
  "properties": {
    "addr:full":"69, Via Dell' Albereto 50041 Calenzano Calenzano Firenze 50041",
    "addr:postcode":"50041;50041",
    "addr:street":"Via Dell ' Albereto",
    "iso:country":"IT",
    "sg:address":"69, Via Dell' Albereto 50041 Calenzano",
    "sg:city":"Calenzano",
    "sg:classifiers":[
        {
            "category":"Shopping",
            "subcategory":"Computers & Home Electronics",
            "type":"Retail Goods"
        }
    ],
    "sg:phone":"+39 055 883 9863",
    "sg:postcode":"50041",
    "sg:province":"Firenze",
    "sg:tags":[
        "electronic",
        "electrical",
        "equipment"
    ],
    "wof:name":"Victoria Srl",
    "wof:placetype":"venue"
},
  "geometry": {"coordinates":[11.182713,43.858788],"type":"Point"}
}