{
  "type": "Feature",
  "properties": {
    "addr:full":"36061 Bassano Del Grappa Bassano del Grappa Vicenza 36061",
    "addr:postcode":"36061;36061",
    "iso:country":"IT",
    "sg:address":"36061 Bassano Del Grappa",
    "sg:city":"Bassano del Grappa",
    "sg:classifiers":[
        {
            "category":"Shopping",
            "subcategory":"Crafts & Fabrics",
            "type":"Retail Goods"
        }
    ],
    "sg:phone":"+39 0424 828033",
    "sg:postcode":"36061",
    "sg:province":"Vicenza",
    "sg:tags":[
        "product",
        "art",
        "processing",
        "gifts",
        "artistic",
        "crafts",
        "ceramics"
    ],
    "wof:name":"Ceramiche La Gardenia Snc",
    "wof:placetype":"venue"
},
  "geometry": {"coordinates":[11.701485,45.759373],"type":"Point"}
}