{
  "type": "Feature",
  "properties": {
    "addr:full":"47838 Riccione Riccione Rimini 47838",
    "addr:postcode":"47838;47838",
    "iso:country":"IT",
    "sg:address":"47838 Riccione",
    "sg:city":"Riccione",
    "sg:orig_category":"Forniture Per Agricoltura E Zootecnia. Forniture Per Attivita' Industriali",
    "sg:phone":"+39 0541 640252",
    "sg:postcode":"47838",
    "sg:province":"Rimini",
    "wof:name":"Nanni Ivo",
    "wof:placetype":"venue"
},
  "geometry": {"coordinates":[12.61622715,43.9942321777],"type":"Point"}
}