{
  "type": "Feature",
  "properties": {
    "iso:country":"IT",
    "sg:address":"Via Rosellini Ippolito 1 20124 Milano",
    "sg:city":"Milano",
    "sg:classifiers":[
        {
            "category":"Autos & Motor Vehicles",
            "subcategory":"Fuel & Gas Station",
            "type":"Retail Goods"
        }
    ],
    "sg:phone":"+39 02 696 1421",
    "sg:postcode":"20124",
    "sg:province":"Milano",
    "sg:tags":[
        "valve"
    ],
    "sg:website":"www.fiorentini.com",
    "wof:name":"Pietro Fiorentini Spa",
    "wof:placetype":"venue"
},
  "geometry": {"coordinates":[9.193634,45.488129],"type":"Point"}
}