{
  "type": "Feature",
  "properties": {
    "addr:full":"10094 Giaveno Giaveno Torino 10094",
    "addr:postcode":"10094;10094",
    "iso:country":"IT",
    "sg:address":"10094 Giaveno",
    "sg:city":"Giaveno",
    "sg:orig_category":"Vetro: Prodotti E Lavorazioni",
    "sg:phone":"+39 011 937 6472",
    "sg:postcode":"10094",
    "sg:province":"Torino",
    "wof:name":"Bivetro Snc Di Giacone & C.",
    "wof:placetype":"venue"
},
  "geometry": {"coordinates":[7.355765,45.044907],"type":"Point"}
}