{
  "type": "Feature",
  "properties": {
    "iso:country":"IT",
    "sg:address":"Via Tunisi 25 10134 Torino",
    "sg:city":"Torino",
    "sg:classifiers":[
        {
            "category":"Shopping",
            "subcategory":"Computers & Home Electronics",
            "type":"Retail Goods"
        }
    ],
    "sg:phone":"+39 011 319 6460",
    "sg:postcode":"10134",
    "sg:province":"Torino",
    "sg:tags":[
        "instrument",
        "electronic",
        "measurement"
    ],
    "wof:name":"Vectra Misure Srl",
    "wof:placetype":"venue"
},
  "geometry": {"coordinates":[7.659551,45.043148],"type":"Point"}
}