{
  "type": "Feature",
  "properties": {
    "iso:country":"IT",
    "sg:address":"Via M. Emilio Lepido 66/7; Bologna",
    "sg:classifiers":[
        {
            "category":"Banks & Credit Unions",
            "subcategory":"Bank",
            "type":"Services"
        }
    ],
    "sg:phone":"+39 051 401031",
    "wof:name":"Cassa Di Risparmio In Bologna Spa",
    "wof:placetype":"venue"
},
  "geometry": {"coordinates":[11.273746,44.517052],"type":"Point"}
}