{
  "type": "Feature",
  "properties": {
    "iso:country":"IT",
    "sg:address":"20035 Lissone",
    "sg:city":"Lissone",
    "sg:orig_category":"Arredamenti - Produzione E Ingrosso",
    "sg:phone":"+39 039 483585",
    "sg:postcode":"20035",
    "sg:province":"Milano",
    "wof:name":"Mobilificio Fratelli Meroni Snc",
    "wof:placetype":"venue"
},
  "geometry": {"coordinates":[9.20271,45.489349],"type":"Point"}
}