{
  "type": "Feature",
  "properties": {
    "iso:country":"IT",
    "sg:address":"86/88, Via De Amicis Edmondo 62012 Civitanova Marche",
    "sg:city":"Civitanova Marche",
    "sg:classifiers":[
        {
            "category":"Autos & Motor Vehicles",
            "subcategory":"Automobile Sales",
            "type":"Retail Goods"
        }
    ],
    "sg:phone":"+39 0733 770588",
    "sg:postcode":"62012",
    "sg:province":"Macerata",
    "sg:tags":[
        "motor-cars"
    ],
    "wof:name":"Viavai (s.p.a.)",
    "wof:placetype":"venue"
},
  "geometry": {"coordinates":[13.4562616348,43.3007469177],"type":"Point"}
}