{
  "type": "Feature",
  "properties": {
    "iso:country":"IT",
    "sg:address":"Contrada Carra' 88046 Lamezia Terme",
    "sg:city":"Lamezia Terme",
    "sg:classifiers":[
        {
            "category":"Wholesale",
            "subcategory":"Machinery & Supplies",
            "type":"Manufacturing & Wholesale Goods"
        }
    ],
    "sg:phone":"+39 0968 463200",
    "sg:postcode":"88046",
    "sg:province":"Catanzaro",
    "sg:tags":[
        "-",
        "agriculture",
        "equipment"
    ],
    "wof:name":"Lamezia Trucks S.r.l",
    "wof:placetype":"venue"
},
  "geometry": {"coordinates":[16.587679,38.910599],"type":"Point"}
}