{
  "type": "Feature",
  "properties": {
    "addr:full":"Via Alessandro Volta 23 24060 San Paolo D'argon Bergamo 24060",
    "addr:housenumber":"23",
    "addr:postcode":"24060;24060",
    "addr:street":"Via Alessandro Volta",
    "iso:country":"IT",
    "sg:address":"Via Alessandro Volta 23 24060 San Paolo D'argon",
    "sg:orig_category":"Granite Pavers",
    "sg:phone":"+39 035 958004",
    "sg:postcode":"24060",
    "sg:province":"Bergamo",
    "sg:website":"www.rota.it",
    "wof:name":"Rota Srl",
    "wof:placetype":"venue"
},
  "geometry": {"coordinates":[9.756733,45.702053],"type":"Point"}
}