{
  "type": "Feature",
  "properties": {
    "iso:country":"IT",
    "sg:address":"32043 Cortina D'ampezzo",
    "sg:classifiers":[
        {
            "category":"Professional",
            "subcategory":"Engineering",
            "type":"Services"
        }
    ],
    "sg:phone":"+39 0436 860696",
    "sg:postcode":"32043",
    "sg:province":"Belluno",
    "sg:tags":[
        "equipment",
        "product",
        "industrial",
        "electrical"
    ],
    "wof:name":"Majoni Osvaldo",
    "wof:placetype":"venue"
},
  "geometry": {"coordinates":[12.099303,46.552547],"type":"Point"}
}