{
  "type": "Feature",
  "properties": {
    "addr:full":"11, Via Beretta Andina 23845 Costa Masnaga Costa Masnaga Lecco 23845",
    "addr:postcode":"23845;masnaga;23845",
    "addr:street":"Via Beretta Andina",
    "iso:country":"IT",
    "sg:address":"11, Via Beretta Andina 23845 Costa Masnaga",
    "sg:city":"Costa Masnaga",
    "sg:classifiers":[
        {
            "category":"Shopping",
            "subcategory":"Crafts & Fabrics",
            "type":"Retail Goods"
        }
    ],
    "sg:phone":"+39 39031855025",
    "sg:postcode":"23845",
    "sg:province":"Lecco",
    "wof:name":"Gitalia Jacquard (s.r.l.)",
    "wof:placetype":"venue"
},
  "geometry": {"coordinates":[9.2761106491,45.7692832947],"type":"Point"}
}