{
  "type": "Feature",
  "properties": {
    "iso:country":"IT",
    "sg:address":"13854 Quaregna",
    "sg:city":"Quaregna",
    "sg:orig_category":"Filati E Materie Prime Tessili",
    "sg:phone":"+39 015 94607",
    "sg:postcode":"13854",
    "sg:province":"Biella",
    "wof:name":"Millefili (s.p.a.)",
    "wof:placetype":"venue"
},
  "geometry": {"coordinates":[8.1094684601,45.5587501526],"type":"Point"}
}