{
  "type": "Feature",
  "properties": {
    "addr:full":"20, Via Sacco E Vanzetti 42021 Bibbiano Reggio Nell'Emilia 42021",
    "addr:postcode":"42021;42021",
    "addr:street":"Via Sacco E Vanzetti",
    "iso:country":"IT",
    "sg:address":"20, Via Sacco E Vanzetti 42021 Bibbiano",
    "sg:classifiers":[
        {
            "category":"Shopping",
            "type":"Retail Goods"
        }
    ],
    "sg:phone":"+39 0522 882701",
    "sg:postcode":"42021",
    "sg:province":"Reggio Nell'Emilia",
    "sg:tags":[
        "finished",
        "-",
        "metallic"
    ],
    "wof:name":"B & B Saldatura Sas Di Borghi P. E C.",
    "wof:placetype":"venue"
},
  "geometry": {"coordinates":[10.5078620911,44.6651725769],"type":"Point"}
}