{
  "type": "Feature",
  "properties": {
    "addr:full":"Via Roma 28; Palazzo San Gervasio; 85026 Palazzo San Gervasio Potenza 85026",
    "addr:housenumber":"28",
    "addr:postcode":"85026;85026",
    "addr:street":"Via Roma",
    "iso:country":"IT",
    "sg:address":"Via Roma 28; Palazzo San Gervasio; 85026",
    "sg:city":"Palazzo San Gervasio",
    "sg:classifiers":[
        {
            "category":"Banks & Credit Unions",
            "subcategory":"Bank",
            "type":"Services"
        }
    ],
    "sg:phone":"+39 0972 44106",
    "sg:postcode":"85026",
    "sg:province":"Potenza",
    "wof:name":"Banco Di Napoli Spa",
    "wof:placetype":"venue"
},
  "geometry": {"coordinates":[15.980627,40.930527],"type":"Point"}
}