{
  "type": "Feature",
  "properties": {
    "iso:country":"IT",
    "sg:address":"20122 Milano",
    "sg:city":"Milano",
    "sg:orig_category":"Abbigliamento Esterno, Maglierie E Pelliccerie. Servizi E Lavori Per Abbigliamento E Pelletterie",
    "sg:phone":"+39 02 782293",
    "sg:postcode":"20122",
    "sg:province":"Milano",
    "wof:name":"Jaqueline Pizzati Rachele",
    "wof:placetype":"venue"
},
  "geometry": {"coordinates":[9.201193,45.462742],"type":"Point"}
}