{
  "type": "Feature",
  "properties": {
    "addr:full":"Sda Statale 98 Km 76110 70032 Bitonto Bitonto Bari 70032",
    "addr:housenumber":"km 76110",
    "addr:postcode":"70032;70032",
    "iso:country":"IT",
    "sg:address":"Sda Statale 98 Km 76110 70032 Bitonto",
    "sg:city":"Bitonto",
    "sg:classifiers":[
        {
            "category":"Social Services",
            "subcategory":"Retirement Home",
            "type":"Services"
        }
    ],
    "sg:phone":"+39 080 371 8195",
    "sg:postcode":"70032",
    "sg:province":"Bari",
    "sg:tags":[
        "slipper",
        "house"
    ],
    "sg:website":"www.game.it/tatarella-distribuzione",
    "wof:name":"Tatarella Distribuzione Srl",
    "wof:placetype":"venue"
},
  "geometry": {"coordinates":[16.869291,41.126053],"type":"Point"}
}