{
  "type": "Feature",
  "properties": {
    "addr:full":"87036 Rende Rende Cosenza 87036",
    "addr:postcode":"87036;87036",
    "iso:country":"IT",
    "sg:address":"87036 Rende",
    "sg:city":"Rende",
    "sg:orig_category":"Agenzie Viaggi E Turismo",
    "sg:phone":"+39 0984 846192",
    "sg:postcode":"87036",
    "sg:province":"Cosenza",
    "wof:name":"Top Class Srl",
    "wof:placetype":"venue"
},
  "geometry": {"coordinates":[16.245386,39.326096],"type":"Point"}
}