{
  "type": "Feature",
  "properties": {
    "addr:full":"Strada Statale 468 No. 9 42015 Correggio Reggio Nell'Emilia 42015",
    "addr:housenumber":"468",
    "addr:postcode":"42015;42015",
    "addr:street":"Strada Statale;No. 9",
    "iso:country":"IT",
    "sg:address":"Strada Statale 468 No. 9 42015 Correggio",
    "sg:classifiers":[
        {
            "category":"Retail",
            "subcategory":"Repair Shop",
            "type":"Services"
        }
    ],
    "sg:phone":"+39 0522 639111",
    "sg:postcode":"42015",
    "sg:province":"Reggio Nell'Emilia",
    "sg:tags":[
        "car",
        "equipment"
    ],
    "sg:website":"www.corghi.com",
    "wof:name":"Corghi Spa",
    "wof:placetype":"venue"
},
  "geometry": {"coordinates":[10.744089,44.753517],"type":"Point"}
}