{
  "type": "Feature",
  "properties": {
    "iso:country":"IT",
    "sg:address":"55100 Lucca",
    "sg:city":"Lucca",
    "sg:classifiers":[
        {
            "category":"Travel",
            "subcategory":"Hotels & Motels",
            "type":"Entertainment"
        }
    ],
    "sg:phone":"+39 0583 953356",
    "sg:postcode":"55100",
    "sg:province":"Lucca",
    "sg:tags":[
        "hotels",
        "facility"
    ],
    "wof:name":"Albergo Bernardino",
    "wof:placetype":"venue"
},
  "geometry": {"coordinates":[10.518538,43.842278],"type":"Point"}
}