{
  "type": "Feature",
  "properties": {
    "addr:full":"98100 Messina ME",
    "addr:postcode":"98100",
    "iso:country":"IT",
    "sg:address":"98100 Messina",
    "sg:orig_category":"Servizi Per Lo Sport E Il Tempo Libero. Alberghi E Strutture Extra Alberghiere",
    "sg:phone":"+39 090 321017",
    "sg:province":"ME",
    "wof:name":"Grand Hotel Lido Di Mortelle - Giardino Delle Palme",
    "wof:placetype":"venue"
},
  "geometry": {"coordinates":[15.615418,38.271606],"type":"Point"}
}