{
  "type": "Feature",
  "properties": {
    "addr:full":"20090 Vimodrone Vimodrone Milano 20090",
    "addr:postcode":"20090;20090",
    "iso:country":"IT",
    "sg:address":"20090 Vimodrone",
    "sg:city":"Vimodrone",
    "sg:classifiers":[
        {
            "category":"Shopping",
            "subcategory":"Computers & Home Electronics",
            "type":"Retail Goods"
        }
    ],
    "sg:phone":"+39 02 285831",
    "sg:postcode":"20090",
    "sg:province":"Milano",
    "sg:tags":[
        "personal",
        "ed",
        "accessori"
    ],
    "sg:website":"http://www.fujitsu-siemens.it",
    "wof:name":"Fujitsu Siemens Computers Spa",
    "wof:placetype":"venue"
},
  "geometry": {"coordinates":[9.2852230072,45.5134925842],"type":"Point"}
}