{
  "type": "Feature",
  "properties": {
    "addr:full":"20050 Lesmo Lesmo Milano 20050",
    "addr:postcode":"20050;20050",
    "iso:country":"IT",
    "sg:address":"20050 Lesmo",
    "sg:city":"Lesmo",
    "sg:orig_category":"Mobili Giardini E Terrazzi",
    "sg:phone":"+39 039 628481",
    "sg:postcode":"20050",
    "sg:province":"Milano",
    "sg:website":"http://www.brianzatende.it",
    "wof:name":"Brianzatende Srl",
    "wof:placetype":"venue"
},
  "geometry": {"coordinates":[9.3066282272,45.6500015259],"type":"Point"}
}