{
  "type": "Feature",
  "properties": {
    "addr:full":"28802 Mergozzo Mergozzo Verbano-Cusio-Ossola 28802",
    "addr:postcode":"28802;28802",
    "iso:country":"IT",
    "sg:address":"28802 Mergozzo",
    "sg:city":"Mergozzo",
    "sg:orig_category":"Marmo, Pietre Ed Affini",
    "sg:phone":"+39 0323 80183",
    "sg:postcode":"28802",
    "sg:province":"Verbano-Cusio-Ossola",
    "wof:name":"Scur Diego",
    "wof:placetype":"venue"
},
  "geometry": {"coordinates":[8.441749,45.958256],"type":"Point"}
}