{
  "type": "Feature",
  "properties": {
    "iso:country":"IT",
    "sg:address":"Via Morpurgo 4; Udine; 33100",
    "sg:city":"Udine",
    "sg:classifiers":[
        {
            "category":"Shopping",
            "subcategory":"Computers & Home Electronics",
            "type":"Retail Goods"
        }
    ],
    "sg:phone":"+39 0432 2731",
    "sg:postcode":"33100",
    "sg:province":"Udine",
    "sg:tags":[
        "chamber",
        "commerce"
    ],
    "wof:name":"Udine Cci",
    "wof:placetype":"venue"
},
  "geometry": {"coordinates":[13.236403,46.060722],"type":"Point"}
}