{
  "type": "Feature",
  "properties": {
    "iso:country":"IT",
    "sg:address":"00167 Roma",
    "sg:city":"Roma",
    "sg:orig_category":"Zootecnia E Pesca, Allevamento Piccoli Animali. Animali Domestici",
    "sg:phone":"+39 06 663 4640",
    "sg:postcode":"00167",
    "sg:province":"Roma",
    "wof:name":"Giglio Francesco Paolo",
    "wof:placetype":"venue"
},
  "geometry": {"coordinates":[12.422523,41.906582],"type":"Point"}
}