{
  "type": "Feature",
  "properties": {
    "iso:country":"IT",
    "sg:address":"78, Viale Italia 14053 Canelli",
    "sg:city":"Canelli",
    "sg:classifiers":[
        {
            "category":"Shopping",
            "type":"Retail Goods"
        }
    ],
    "sg:phone":"+39 0141 832515",
    "sg:postcode":"14053",
    "sg:province":"Asti",
    "sg:tags":[
        "finished",
        "-",
        "metallic"
    ],
    "wof:name":"Robino E Galandrino (s.p.a.)",
    "wof:placetype":"venue"
},
  "geometry": {"coordinates":[8.2998695374,44.7224884033],"type":"Point"}
}