{
  "type": "Feature",
  "properties": {
    "addr:full":"92024 Canicatt\u00ec Agrigento 92024",
    "addr:postcode":"92024;92024",
    "iso:country":"IT",
    "sg:address":"92024 Canicatt\u00ec",
    "sg:orig_category":"Servizi E Lavori Per Edilizia E Lavori Pubblici. Consulenze Tecniche, Amministrative E Perizie",
    "sg:phone":"+39 0922 855849",
    "sg:postcode":"92024",
    "sg:province":"Agrigento",
    "wof:name":"Aet Srl",
    "wof:placetype":"venue"
},
  "geometry": {"coordinates":[13.667566,37.324963],"type":"Point"}
}