{
  "type": "Feature",
  "properties": {
    "addr:full":"Via Mascagni 8 20050 Sulbiate Sulbiate Milano 20050",
    "addr:housenumber":"8",
    "addr:postcode":"20050;20050",
    "addr:street":"Via Mascagni",
    "iso:country":"IT",
    "sg:address":"Via Mascagni 8 20050 Sulbiate",
    "sg:city":"Sulbiate",
    "sg:classifiers":[
        {
            "category":"Autos & Motor Vehicles",
            "subcategory":"Auto Supplies",
            "type":"Retail Goods"
        }
    ],
    "sg:phone":"+39 039 623992",
    "sg:postcode":"20050",
    "sg:province":"Milano",
    "sg:tags":[
        "punched",
        "gasket"
    ],
    "wof:name":"Mecondor Spa",
    "wof:placetype":"venue"
},
  "geometry": {"coordinates":[9.4287633896,45.6431312561],"type":"Point"}
}