{
  "type": "Feature",
  "properties": {
    "iso:country":"IT",
    "sg:address":"35010 Grantorto",
    "sg:city":"Grantorto",
    "sg:orig_category":"Autotrasporti",
    "sg:phone":"+39 049 949 0210",
    "sg:postcode":"35010",
    "sg:province":"Padova",
    "wof:name":"Levio Loris",
    "wof:placetype":"venue"
},
  "geometry": {"coordinates":[11.72675,45.609867],"type":"Point"}
}