{
  "type": "Feature",
  "properties": {
    "iso:country":"IT",
    "sg:address":"20142 Milano",
    "sg:city":"Milano",
    "sg:orig_category":"Musica",
    "sg:phone":"+39 02 8480 0489",
    "sg:postcode":"20142",
    "sg:province":"Milano",
    "wof:name":"Rnd Promotion Di Stefano Landi",
    "wof:placetype":"venue"
},
  "geometry": {"coordinates":[9.1532030106,45.4571304321],"type":"Point"}
}