{
  "type": "Feature",
  "properties": {
    "iso:country":"IT",
    "sg:address":"37050 Angiari",
    "sg:city":"Angiari",
    "sg:orig_category":"Manufacturers: Prefabbricati",
    "sg:phone":"+39 0442 98454",
    "sg:postcode":"37050",
    "sg:province":"Verona",
    "wof:name":"Vipp S.p.a.",
    "wof:placetype":"venue"
},
  "geometry": {"coordinates":[11.280369,45.259644],"type":"Point"}
}