{
  "type": "Feature",
  "properties": {
    "iso:country":"IT",
    "sg:address":"Ss Belchiaro 135/a 47012 Civitella Di Romagna",
    "sg:city":"Civitella di Romagna",
    "sg:orig_category":"Press Working Machinery",
    "sg:phone":"+39 0543 983400",
    "sg:postcode":"47012",
    "sg:province":"Forl\u00ec-Cesena",
    "wof:name":"Babbini Srl",
    "wof:placetype":"venue"
},
  "geometry": {"coordinates":[11.9804611206,43.9947662354],"type":"Point"}
}