{
  "type": "Feature",
  "properties": {
    "iso:country":"IT",
    "sg:address":"234, Via Monti Lepini 03100 Frosinone",
    "sg:city":"Frosinone",
    "sg:classifiers":[
        {
            "category":"Manufacturing",
            "subcategory":"Rubber & Plastics",
            "type":"Manufacturing & Wholesale Goods"
        }
    ],
    "sg:phone":"+39 0775 290708",
    "sg:postcode":"03100",
    "sg:province":"Frosinone",
    "wof:name":"Carloni Pneumatici Srl",
    "wof:placetype":"venue"
},
  "geometry": {"coordinates":[13.326509,41.632992],"type":"Point"}
}