{
  "type": "Feature",
  "properties": {
    "addr:full":"26022 Castelverde Castelverde Cremona 26022",
    "addr:housenumber":"26022",
    "addr:postcode":"26022",
    "addr:street":"Castelverde",
    "iso:country":"IT",
    "sg:address":"26022 Castelverde",
    "sg:city":"Castelverde",
    "sg:orig_category":"Depurazione E Trattamento Delle Acque - Impianti Ed Apparecchi",
    "sg:phone":"+39 0372 471140",
    "sg:postcode":"26022",
    "sg:province":"Cremona",
    "sg:website":"http://www.gamma3ecologia.com",
    "wof:name":"Gamma 3",
    "wof:placetype":"venue"
},
  "geometry": {"coordinates":[9.963522,45.171246],"type":"Point"}
}