{
  "type": "Feature",
  "properties": {
    "iso:country":"IT",
    "sg:address":"22070 Vertemate Con Minoprio",
    "sg:city":"Minoprio",
    "sg:orig_category":"Cartotecnica E Servizi. Composizione, Stampa E Confezione. Forniture E Prodotti Informatici. Forniture Per Congressi, Fiere E Manifestazioni",
    "sg:phone":"+39 031 901562",
    "sg:postcode":"22070",
    "sg:province":"Como",
    "wof:name":"Supercard Snc",
    "wof:placetype":"venue"
},
  "geometry": {"coordinates":[9.069239,45.842396],"type":"Point"}
}