{
  "type": "Feature",
  "properties": {
    "addr:full":"19031 Ameglia Ameglia La Spezia 19031",
    "addr:postcode":"19031;19031",
    "addr:street":"Ameglia Ameglia",
    "iso:country":"IT",
    "sg:address":"19031 Ameglia",
    "sg:city":"Ameglia",
    "sg:classifiers":[
        {
            "category":"Banks & Credit Unions",
            "subcategory":"Investment Brokerage",
            "type":"Services"
        }
    ],
    "sg:phone":"+39 0187 609042",
    "sg:postcode":"19031",
    "sg:province":"La Spezia",
    "sg:tags":[
        "article",
        "sport",
        "leisure",
        "supplies"
    ],
    "sg:website":"http://www.ossodiseppiadiving.com",
    "wof:name":"Osso Di Seppia",
    "wof:placetype":"venue"
},
  "geometry": {"coordinates":[9.973181,44.058395],"type":"Point"}
}