{
  "type": "Feature",
  "properties": {
    "addr:full":"10121 Torino Torino Torino 10121",
    "addr:postcode":"10121;10121",
    "iso:country":"IT",
    "sg:address":"10121 Torino",
    "sg:city":"Torino",
    "sg:orig_category":"Cartotecnica E Servizi. Composizione, Stampa E Confezione. Servizi E Lavori Industria Delle Materie Plastiche. Servizi Per Imballaggio E Confezionamento",
    "sg:phone":"+39 011 541294",
    "sg:postcode":"10121",
    "sg:province":"Torino",
    "wof:name":"Weren Di Roberto Majo",
    "wof:placetype":"venue"
},
  "geometry": {"coordinates":[7.668364,45.067791],"type":"Point"}
}