{
  "type": "Feature",
  "properties": {
    "addr:full":"37014 Castelnuovo Del Garda Castelnuovo del Garda Verona 37014",
    "addr:postcode":"37014;37014",
    "iso:country":"IT",
    "sg:address":"37014 Castelnuovo Del Garda",
    "sg:city":"Castelnuovo del Garda",
    "sg:orig_category":"Prodotti E Manufatti In Materie Plastiche",
    "sg:phone":"+39 045 757 0866",
    "sg:postcode":"37014",
    "sg:province":"Verona",
    "wof:name":"Zenari Claudio",
    "wof:placetype":"venue"
},
  "geometry": {"coordinates":[10.7588558197,45.4304733276],"type":"Point"}
}