{
  "type": "Feature",
  "properties": {
    "addr:full":"Via Della Cartieri 21; Collodi; 51014",
    "addr:housenumber":"21",
    "addr:postcode":"51014",
    "addr:street":"Via Della Cartieri;Collodi",
    "iso:country":"IT",
    "sg:address":"Via Della Cartieri 21; Collodi; 51014",
    "sg:classifiers":[
        {
            "category":"Banks & Credit Unions",
            "subcategory":"Bank",
            "type":"Services"
        }
    ],
    "sg:phone":"+39 0572 429336",
    "wof:name":"Cassa Di Risparmio Di, Pistoia E Pescia",
    "wof:placetype":"venue"
},
  "geometry": {"coordinates":[10.69615,43.885132],"type":"Point"}
}