{
  "type": "Feature",
  "properties": {
    "addr:full":"57, Via Per Venegono 21040 Vedano Olona Vedano Olona Varese 21040",
    "addr:postcode":"21040;21040",
    "addr:street":"Via Per Venegono",
    "iso:country":"IT",
    "sg:address":"57, Via Per Venegono 21040 Vedano Olona",
    "sg:city":"Vedano Olona",
    "sg:classifiers":[
        {
            "category":"Manufacturing",
            "subcategory":"Rubber & Plastics",
            "type":"Manufacturing & Wholesale Goods"
        }
    ],
    "sg:phone":"+39 0332 400497",
    "sg:postcode":"21040",
    "sg:province":"Varese",
    "sg:tags":[
        "packaging",
        "material",
        "-"
    ],
    "wof:name":"Verve (s.p.a.)",
    "wof:placetype":"venue"
},
  "geometry": {"coordinates":[8.8263845444,45.8176040649],"type":"Point"}
}