{
  "type": "Feature",
  "properties": {
    "addr:full":"65027 Scafa Scafa Pescara 65027",
    "addr:postcode":"65027;65027",
    "iso:country":"IT",
    "sg:address":"65027 Scafa",
    "sg:city":"Scafa",
    "sg:orig_category":"Marmo, Granito E Pietre Lavorazione - Macchine",
    "sg:phone":"+39 085 854 1325",
    "sg:postcode":"65027",
    "sg:province":"Pescara",
    "wof:name":"Morsella Marmi Snc",
    "wof:placetype":"venue"
},
  "geometry": {"coordinates":[14.006531,42.253876],"type":"Point"}
}