{
  "type": "Feature",
  "properties": {
    "iso:country":"IT",
    "sg:address":"20054 Nova Milanese",
    "sg:city":"Nova Milanese",
    "sg:orig_category":"Motori Ed Organi Di Trasmissione. Ricambi E Componenti Dei Mezzi Di Trasporto",
    "sg:phone":"+39 036 236 5077",
    "sg:postcode":"20054",
    "sg:province":"Milano",
    "wof:name":"C.p.m. Spa",
    "wof:placetype":"venue"
},
  "geometry": {"coordinates":[9.1939220428,45.5860061646],"type":"Point"}
}