{
  "type": "Feature",
  "properties": {
    "addr:full":"66100 Chieti Chieti Chieti 66100",
    "addr:postcode":"66100;66100",
    "iso:country":"IT",
    "sg:address":"66100 Chieti",
    "sg:city":"Chieti",
    "sg:classifiers":[
        {
            "category":"Health Services",
            "subcategory":"Health Practitioner",
            "type":"Services"
        }
    ],
    "sg:phone":"+39 0871 560642",
    "sg:postcode":"66100",
    "sg:province":"Chieti",
    "sg:tags":[
        "medici"
    ],
    "wof:name":"Di Fonzo Rosa Maria",
    "wof:placetype":"venue"
},
  "geometry": {"coordinates":[14.141291,42.364941],"type":"Point"}
}