{
  "type": "Feature",
  "properties": {
    "addr:full":"10147 Torino Torino Torino 10147",
    "addr:postcode":"10147;10147",
    "iso:country":"IT",
    "sg:address":"10147 Torino",
    "sg:city":"Torino",
    "sg:orig_category":"Petroli, Gas E Combustibili",
    "sg:phone":"+39 011 290259",
    "sg:postcode":"10147",
    "sg:province":"Torino",
    "wof:name":"Borgo Emanuele (s.a.s.)",
    "wof:placetype":"venue"
},
  "geometry": {"coordinates":[7.6672120094,45.1025123596],"type":"Point"}
}