{
  "type": "Feature",
  "properties": {
    "addr:full":"35030 Caselle Caselle Padova 35030",
    "addr:postcode":"35030;35030",
    "iso:country":"IT",
    "sg:address":"35030 Caselle",
    "sg:city":"Caselle",
    "sg:orig_category":"Gioielleria, Oreficeria E Argenteria. Shopping",
    "sg:phone":"+39 049 630537",
    "sg:postcode":"35030",
    "sg:province":"Padova",
    "wof:name":"Miola (s.r.l.)",
    "wof:placetype":"venue"
},
  "geometry": {"coordinates":[11.809112,45.415031],"type":"Point"}
}