{
  "type": "Feature",
  "properties": {
    "iso:country":"IT",
    "sg:address":"91025 Marsala",
    "sg:city":"Marsala",
    "sg:orig_category":"Servizi Vari Di Interesse Pubblico",
    "sg:phone":"+39 0923 953030",
    "sg:postcode":"91025",
    "sg:province":"Trapani",
    "wof:name":"Orchidea Laguna Blu Sas",
    "wof:placetype":"venue"
},
  "geometry": {"coordinates":[12.526578,38.02066],"type":"Point"}
}