{
  "type": "Feature",
  "properties": {
    "iso:country":"IT",
    "sg:address":"60019 Senigallia",
    "sg:city":"Senigallia",
    "sg:orig_category":"Materiali Edili",
    "sg:phone":"+39 071 792 6026",
    "sg:postcode":"60019",
    "sg:province":"Ancona",
    "sg:website":"http://www.bigellimarmi.it",
    "wof:name":"Bigelli Marmi Srl",
    "wof:placetype":"venue"
},
  "geometry": {"coordinates":[13.209116,43.705177],"type":"Point"}
}