{
  "type": "Feature",
  "properties": {
    "addr:full":"8/a, V. G. Galilei 42027 Montecchio Emilia Reggio Nell'Emilia 42027",
    "addr:housenumber":"8 / a",
    "addr:postcode":"42027;42027",
    "addr:street":"V. G. Galilei",
    "iso:country":"IT",
    "sg:address":"8/a, V. G. Galilei 42027 Montecchio Emilia",
    "sg:classifiers":[
        {
            "category":"Food & Beverages",
            "subcategory":"Groceries & Convenience Stores",
            "type":"Retail Goods"
        }
    ],
    "sg:phone":"+39 0522 864745",
    "sg:postcode":"42027",
    "sg:province":"Reggio Nell'Emilia",
    "sg:tags":[
        "product",
        "related"
    ],
    "sg:website":"http://www.paginegialle.it/gianbon",
    "wof:name":"Gianbon Srl",
    "wof:placetype":"venue"
},
  "geometry": {"coordinates":[10.4785604477,44.667388916],"type":"Point"}
}