{
  "type": "Feature",
  "properties": {
    "addr:full":"62019 Recanati Recanati Macerata 62019",
    "addr:postcode":"62019;62019",
    "iso:country":"IT",
    "sg:address":"62019 Recanati",
    "sg:city":"Recanati",
    "sg:orig_category":"Arti Grafiche - Accessori E Forniture",
    "sg:phone":"+39 0733 750 6046",
    "sg:postcode":"62019",
    "sg:province":"Macerata",
    "wof:name":"Co.ma.graf Cocchi & C. Snc",
    "wof:placetype":"venue"
},
  "geometry": {"coordinates":[13.58174,43.439075],"type":"Point"}
}