{
  "type": "Feature",
  "properties": {
    "iso:country":"IT",
    "sg:address":"91100 Trapani",
    "sg:city":"Trapani",
    "sg:classifiers":[
        {
            "category":"Restaurant",
            "type":"Food & Drink"
        }
    ],
    "sg:phone":"+39 0923 542222",
    "sg:postcode":"91100",
    "sg:province":"Trapani",
    "sg:tags":[
        "equipment",
        "industry",
        "machinery"
    ],
    "wof:name":"Caruso Francesco",
    "wof:placetype":"venue"
},
  "geometry": {"coordinates":[12.5527505875,37.9160804749],"type":"Point"}
}