{
  "type": "Feature",
  "properties": {
    "iso:country":"IT",
    "sg:address":"56037 Peccioli",
    "sg:city":"Peccioli",
    "sg:orig_category":"Servizi Per Lo Sport E Il Tempo Libero. Servizi Al Turismo",
    "sg:phone":"+39 0587 636030",
    "sg:postcode":"56037",
    "sg:province":"Pisa",
    "wof:name":"Ghironi Parco Preistorico",
    "wof:placetype":"venue"
},
  "geometry": {"coordinates":[10.398363,43.706024],"type":"Point"}
}