{
  "type": "Feature",
  "properties": {
    "iso:country":"IT",
    "sg:address":"96100 Siracusa",
    "sg:city":"Siracusa",
    "sg:orig_category":"Agricoltura, Orticoltura E Floricoltura. Articoli Da Regalo. Shopping",
    "sg:phone":"+39 0931 480135",
    "sg:postcode":"96100",
    "sg:province":"Siracusa",
    "wof:name":"La Mesa Alessandro",
    "wof:placetype":"venue"
},
  "geometry": {"coordinates":[15.159276,37.089405],"type":"Point"}
}