{
  "type": "Feature",
  "properties": {
    "iso:country":"IT",
    "sg:address":"20089 Rozzano",
    "sg:city":"Rozzano",
    "sg:orig_category":"Attrezzature E Forniture Per Officine Riparazione E Servizi Ausiliari",
    "sg:phone":"+39 02 8920 2080",
    "sg:postcode":"20089",
    "sg:province":"Milano",
    "wof:name":"Aleant S.r.l.",
    "wof:placetype":"venue"
},
  "geometry": {"coordinates":[9.166812,45.39447],"type":"Point"}
}