{
  "type": "Feature",
  "properties": {
    "addr:full":"25034 Orzinuovi Orzinuovi Brescia 25034",
    "addr:postcode":"25034;25034",
    "iso:country":"IT",
    "sg:address":"25034 Orzinuovi",
    "sg:city":"Orzinuovi",
    "sg:orig_category":"Oli Alimentari E Frantoi Oleari",
    "sg:phone":"+39 030 941761",
    "sg:postcode":"25034",
    "sg:province":"Brescia",
    "wof:name":"I.g.o.r. Spa",
    "wof:placetype":"venue"
},
  "geometry": {"coordinates":[10.209558,45.54216],"type":"Point"}
}