{
  "type": "Feature",
  "properties": {
    "iso:country":"IT",
    "sg:address":"27030 Mezzana Rabattone",
    "sg:city":"Mezzana Rabattone",
    "sg:orig_category":"Macchine E Forniture Per Ecologia E Smaltimento Rifiuti. Elettrodomestici. Forniture Alle Strutture Ricettive. Macchine, Strumenti Ed Apparecchi Per Attivita' Industriali",
    "sg:phone":"+39 0382 914116",
    "sg:postcode":"27030",
    "sg:province":"Pavia",
    "wof:name":"Fa-de Snc",
    "wof:placetype":"venue"
},
  "geometry": {"coordinates":[9.032162,45.095669],"type":"Point"}
}