{
  "type": "Feature",
  "properties": {
    "iso:country":"IT",
    "sg:address":"Corso Palermo 11 10152 Torino",
    "sg:city":"Torino",
    "sg:classifiers":[
        {
            "category":"Real Estate",
            "subcategory":"Real Estate Agent",
            "type":"Services"
        }
    ],
    "sg:phone":"+39 011 853826",
    "sg:postcode":"10152",
    "sg:province":"Torino",
    "sg:tags":[
        "lacquer"
    ],
    "sg:website":"www.nicolavernici.com",
    "wof:name":"Nicola Sas",
    "wof:placetype":"venue"
},
  "geometry": {"coordinates":[7.692554,45.077637],"type":"Point"}
}