{
  "type": "Feature",
  "properties": {
    "addr:full":"Viale Delle Rimembranze 5/a; Sorbolo",
    "addr:housenumber":"5 / a",
    "addr:street":"Viale Delle Rimembranze;Sorbolo",
    "iso:country":"IT",
    "sg:address":"Viale Delle Rimembranze 5/a; Sorbolo",
    "sg:classifiers":[
        {
            "category":"Banks & Credit Unions",
            "subcategory":"Bank",
            "type":"Services"
        }
    ],
    "sg:phone":"+39 0521 690345",
    "wof:name":"Cassa Di Risparmio Di Parma, E Piacenza Spa",
    "wof:placetype":"venue"
},
  "geometry": {"coordinates":[10.448946,44.844921],"type":"Point"}
}