{
  "type": "Feature",
  "properties": {
    "iso:country":"IT",
    "sg:address":"64018 Tortoreto",
    "sg:city":"Tortoreto",
    "sg:orig_category":"Prodotti Chimici Secondari. Materiali Edili",
    "sg:phone":"+39 0861 781005",
    "sg:postcode":"64018",
    "sg:province":"Teramo",
    "sg:website":"http://www.bigmat.it/euroedil",
    "wof:name":"Euroedil Srl",
    "wof:placetype":"venue"
},
  "geometry": {"coordinates":[13.9198760986,42.7913398743],"type":"Point"}
}