{
  "type": "Feature",
  "properties": {
    "addr:full":"Sda Provinciale 202/4 26836 Montanaso Lombardo Montanaso Lombardo Lodi 26836",
    "addr:housenumber":"4",
    "addr:postcode":"26836;26836",
    "addr:street":"Provinciale 202 /;Lombardo",
    "iso:country":"IT",
    "sg:address":"Sda Provinciale 202/4 26836 Montanaso Lombardo",
    "sg:city":"Montanaso Lombardo",
    "sg:classifiers":[
        {
            "category":"Wholesale",
            "subcategory":"Chemicals & Plastics",
            "type":"Manufacturing & Wholesale Goods"
        }
    ],
    "sg:phone":"+39 0371 68043",
    "sg:postcode":"26836",
    "sg:province":"Lodi",
    "sg:tags":[
        "articles",
        "sterile",
        "disposable"
    ],
    "wof:name":"Anelli Srl",
    "wof:placetype":"venue"
},
  "geometry": {"coordinates":[9.4609727859,45.3334465027],"type":"Point"}
}