{
  "type": "Feature",
  "properties": {
    "addr:full":"20121 Milano Milano Milano 20121",
    "addr:postcode":"20121;20121",
    "iso:country":"IT",
    "sg:address":"20121 Milano",
    "sg:city":"Milano",
    "sg:orig_category":"Gioielleria, Oreficeria E Argenteria. Shopping",
    "sg:phone":"+39 02 7601 7271",
    "sg:postcode":"20121",
    "sg:province":"Milano",
    "wof:name":"Gioielli Di Via Della Spiga",
    "wof:placetype":"venue"
},
  "geometry": {"coordinates":[9.19876,45.468491],"type":"Point"}
}