{
  "type": "Feature",
  "properties": {
    "addr:full":"884/a, Via Appia Nuova 00178 Roma Roma Roma 00178",
    "addr:housenumber":"884 / a",
    "addr:postcode":"00178;00178",
    "addr:street":"Via Appia Nuova",
    "iso:country":"IT",
    "sg:address":"884/a, Via Appia Nuova 00178 Roma",
    "sg:city":"Roma",
    "sg:classifiers":[
        {
            "category":"Food & Beverages",
            "subcategory":"Groceries & Convenience Stores",
            "type":"Retail Goods"
        }
    ],
    "sg:phone":"+39 39067188504",
    "sg:postcode":"00178",
    "sg:province":"Roma",
    "sg:tags":[
        "product",
        "related"
    ],
    "wof:name":"Bongustaia Srl",
    "wof:placetype":"venue"
},
  "geometry": {"coordinates":[12.5780220032,41.8090896606],"type":"Point"}
}