{
  "type": "Feature",
  "properties": {
    "addr:full":"60124 Ancona Ancona Ancona 60124",
    "addr:postcode":"60124;60124",
    "iso:country":"IT",
    "sg:address":"60124 Ancona",
    "sg:city":"Ancona",
    "sg:orig_category":"Abbigliamento Intimo, Calze E Costumi Da Bagno. Articoli Medico-sanitari Ed Ortopedici",
    "sg:phone":"+39 071 203324",
    "sg:postcode":"60124",
    "sg:province":"Ancona",
    "wof:name":"Fogliardi Raffaele",
    "wof:placetype":"venue"
},
  "geometry": {"coordinates":[13.518557,43.614883],"type":"Point"}
}