{
  "type": "Feature",
  "properties": {
    "addr:full":"20015 Parabiago Parabiago Milano 20015",
    "addr:postcode":"20015;20015",
    "iso:country":"IT",
    "sg:address":"20015 Parabiago",
    "sg:city":"Parabiago",
    "sg:orig_category":"Forniture Per Abbigliamento E Pelletterie",
    "sg:phone":"+39 0331 559480",
    "sg:postcode":"20015",
    "sg:province":"Milano",
    "wof:name":"Tucs (s.r.l.)",
    "wof:placetype":"venue"
},
  "geometry": {"coordinates":[8.9188137054,45.5746955872],"type":"Point"}
}