{
  "type": "Feature",
  "properties": {
    "iso:country":"IT",
    "sg:address":"20068 Peschiera Borromeo",
    "sg:city":"Peschiera Borromeo",
    "sg:orig_category":"Macchine E Forniture Per Arredamento E Industria Del Legno. Utensili Meccanici E Materiali",
    "sg:phone":"+39 02 5530 3631",
    "sg:postcode":"20068",
    "sg:province":"Milano",
    "wof:name":"Galli Carlo",
    "wof:placetype":"venue"
},
  "geometry": {"coordinates":[9.294644,45.441841],"type":"Point"}
}