{
  "type": "Feature",
  "properties": {
    "iso:country":"IT",
    "sg:address":"98051 Barcellona Pozzo Di Gotto",
    "sg:city":"Barcellona Pozzo di Gotto",
    "sg:orig_category":"Prodotti Di Base E Forniture Per Industria Alimentare E Bevande",
    "sg:phone":"+39 090 979 9167",
    "sg:postcode":"98051",
    "sg:province":"Messina",
    "wof:name":"Caruso Placido",
    "wof:placetype":"venue"
},
  "geometry": {"coordinates":[15.2560653687,38.1834907532],"type":"Point"}
}