{
  "type": "Feature",
  "properties": {
    "addr:full":"50025 Montespertoli Montespertoli Firenze 50025",
    "addr:postcode":"50025;50025",
    "iso:country":"IT",
    "sg:address":"50025 Montespertoli",
    "sg:city":"Montespertoli",
    "sg:orig_category":"Forniture Per Agricoltura E Zootecnia. Animali Domestici",
    "sg:phone":"+39 0571 608018",
    "sg:postcode":"50025",
    "sg:province":"Firenze",
    "wof:name":"Agri Chianti Srl",
    "wof:placetype":"venue"
},
  "geometry": {"coordinates":[11.0485486984,43.6554260254],"type":"Point"}
}