{
  "type": "Feature",
  "properties": {
    "iso:country":"IT",
    "sg:address":"46, Viale Lombardia 20093 Cologno Monzese",
    "sg:city":"Cologno Monzese",
    "sg:classifiers":[
        {
            "category":"Professional",
            "subcategory":"Engineering",
            "type":"Services"
        }
    ],
    "sg:phone":"+39 39022547977",
    "sg:postcode":"20093",
    "sg:province":"Milano",
    "sg:tags":[
        "machine",
        "-",
        "mechanical"
    ],
    "wof:name":"Miotto Este (s.p.a.)",
    "wof:placetype":"venue"
},
  "geometry": {"coordinates":[9.275017,45.540081],"type":"Point"}
}