{
  "type": "Feature",
  "properties": {
    "iso:country":"IT",
    "sg:address":"92027 Licata",
    "sg:city":"Licata",
    "sg:classifiers":[
        {
            "category":"Home & Garden",
            "subcategory":"Building Materials",
            "type":"Retail Goods"
        }
    ],
    "sg:phone":"+39 0922 894761",
    "sg:postcode":"92027",
    "sg:province":"Agrigento",
    "sg:tags":[
        "window",
        "door",
        "frame"
    ],
    "wof:name":"F.a.l.i.s. Di D'andrea Giacomo & C. Snc",
    "wof:placetype":"venue"
},
  "geometry": {"coordinates":[13.937602,37.130039],"type":"Point"}
}