{
  "type": "Feature",
  "properties": {
    "iso:country":"IT",
    "sg:address":"20123 Milano",
    "sg:city":"Milano",
    "sg:orig_category":"Servizi E Lavori Per Edilizia E Lavori Pubblici. Banche E Servizi Finanziari",
    "sg:phone":"+39 02 498 3512",
    "sg:postcode":"20123",
    "sg:province":"Milano",
    "wof:name":"Immobiliare Simplicitas Srl",
    "wof:placetype":"venue"
},
  "geometry": {"coordinates":[9.165349,45.464905],"type":"Point"}
}