{
  "type": "Feature",
  "properties": {
    "addr:full":"40057 Quarto Inferiore - Granarolo E Quarto Inferiore Bologna 40057",
    "addr:postcode":"40057;40057",
    "iso:country":"IT",
    "sg:address":"40057 Quarto Inferiore - Granarolo E",
    "sg:city":"Quarto Inferiore",
    "sg:orig_category":"Pompe. Macchine, Strumenti Ed Apparecchi Per Attivita' Industriali",
    "sg:phone":"+39 051 767857",
    "sg:postcode":"40057",
    "sg:province":"Bologna",
    "wof:name":"P.e.p. Tecnoattrezzature",
    "wof:placetype":"venue"
},
  "geometry": {"coordinates":[11.4146318436,44.532043457],"type":"Point"}
}