{
  "type": "Feature",
  "properties": {
    "iso:country":"IT",
    "sg:address":"87036 Rende",
    "sg:city":"Rende",
    "sg:orig_category":"Macchine, Impianti E Forniture Per Industria Grafica, Cartaria E Cartotecnica. Automazione E Macchine Per Ufficio",
    "sg:phone":"+39 0984 3081",
    "sg:postcode":"87036",
    "sg:province":"Cosenza",
    "wof:name":"Cali\u00d2 Informatica Srl",
    "wof:placetype":"venue"
},
  "geometry": {"coordinates":[16.239141,39.319473],"type":"Point"}
}