{
  "type": "Feature",
  "properties": {
    "iso:country":"IT",
    "sg:address":"39052 Caldaro Strada Vino",
    "sg:orig_category":"Servizi E Lavori Per Edilizia E Lavori Pubblici",
    "sg:phone":"+39 0471 964281",
    "sg:postcode":"39052",
    "sg:province":"Bolzano/Bozen",
    "wof:name":"Softclean Srl",
    "wof:placetype":"venue"
},
  "geometry": {"coordinates":[11.250582,46.423523],"type":"Point"}
}