{
  "type": "Feature",
  "properties": {
    "iso:country":"IT",
    "sg:address":"98122 Messina",
    "sg:city":"Messina",
    "sg:orig_category":"Fotografia - Servizi, Studi, Sviluppo E Stampa",
    "sg:phone":"+39 090 710448",
    "sg:postcode":"98122",
    "sg:province":"Messina",
    "wof:name":"La Cinetecnica Di Saya Francesco",
    "wof:placetype":"venue"
},
  "geometry": {"coordinates":[15.5529384613,38.1886558533],"type":"Point"}
}