{
  "type": "Feature",
  "properties": {
    "addr:full":"46, Via Borgo Mattina 26029 Soncino Soncino Cremona 26029",
    "addr:postcode":"26029;26029",
    "addr:street":"Via Borgo Mattina",
    "iso:country":"IT",
    "sg:address":"46, Via Borgo Mattina 26029 Soncino",
    "sg:city":"Soncino",
    "sg:classifiers":[
        {
            "category":"Shopping",
            "type":"Retail Goods"
        }
    ],
    "sg:phone":"+39 39037483518",
    "sg:postcode":"26029",
    "sg:province":"Cremona",
    "sg:tags":[
        "finished",
        "-",
        "metallic"
    ],
    "wof:name":"Il Segnale Di Merlo Pietro & C. (s.n.c.)",
    "wof:placetype":"venue"
},
  "geometry": {"coordinates":[9.8775224686,45.4019241333],"type":"Point"}
}