{
  "type": "Feature",
  "properties": {
    "iso:country":"IT",
    "sg:address":"Via Diotti Benedetto 43 20153 Milano",
    "sg:city":"Milano",
    "sg:orig_category":"Turned Parts Of Various Materials",
    "sg:phone":"+39 02 4891 1191",
    "sg:postcode":"20153",
    "sg:province":"Milano",
    "wof:name":"D.b.r. Roberto Dal Brun",
    "wof:placetype":"venue"
},
  "geometry": {"coordinates":[9.203226,45.482468],"type":"Point"}
}