{
  "type": "Feature",
  "properties": {
    "iso:country":"IT",
    "sg:address":"Via Averolda 31 25039 Travagliato",
    "sg:city":"Travagliato",
    "sg:classifiers":[
        {
            "category":"Personal",
            "subcategory":"Skin Care",
            "type":"Services"
        }
    ],
    "sg:phone":"+39 030 686 3629",
    "sg:postcode":"25039",
    "sg:province":"Brescia",
    "sg:tags":[
        "rifles",
        "closed-season",
        "hunting",
        "rifle"
    ],
    "sg:website":"www.fabarm.com",
    "wof:name":"Fabarm Spa",
    "wof:placetype":"venue"
},
  "geometry": {"coordinates":[10.101091,45.536377],"type":"Point"}
}