{
  "type": "Feature",
  "properties": {
    "iso:country":"IT",
    "sg:address":"Via Collegno 84 10091 Alpignano",
    "sg:city":"Alpignano",
    "sg:orig_category":"Deep-drawing, Hydromechanical",
    "sg:phone":"+39 011 967 8198",
    "sg:postcode":"10091",
    "sg:province":"Torino",
    "sg:website":"www.gruppoisil.com",
    "wof:name":"Isil S.r.l.",
    "wof:placetype":"venue"
},
  "geometry": {"coordinates":[7.573233,45.069592],"type":"Point"}
}