{
  "type": "Feature",
  "properties": {
    "addr:full":"28014 Maggiora Maggiora Novara 28014",
    "addr:postcode":"28014;28014",
    "iso:country":"IT",
    "sg:address":"28014 Maggiora",
    "sg:city":"Maggiora",
    "sg:orig_category":"Petroli, Gas E Combustibili",
    "sg:phone":"+39 0322 866504",
    "sg:postcode":"28014",
    "sg:province":"Novara",
    "wof:name":"Fasolo Adriano & C. S.n.c.",
    "wof:placetype":"venue"
},
  "geometry": {"coordinates":[8.4121284485,45.6965332031],"type":"Point"}
}