{
  "type": "Feature",
  "properties": {
    "iso:country":"IT",
    "sg:address":"95030 Tremestieri Etneo",
    "sg:city":"Tremestieri Etneo",
    "sg:orig_category":"Impianti, Attrezzature E Forniture Sanitarie Ed Ospedaliere",
    "sg:phone":"+39 095 496497",
    "sg:postcode":"95030",
    "sg:province":"Catania",
    "wof:name":"Forel Srl",
    "wof:placetype":"venue"
},
  "geometry": {"coordinates":[15.097744,37.541313],"type":"Point"}
}