{
  "type": "Feature",
  "properties": {
    "iso:country":"IT",
    "sg:address":"25055 Pisogne",
    "sg:city":"Pisogne",
    "sg:orig_category":"Valvole E Apparecchiature Di Misura. Forniture Per Attivita' Industriali",
    "sg:phone":"+39 036 488 0088",
    "sg:postcode":"25055",
    "sg:province":"Brescia",
    "sg:website":"http://www.mpgasvalves.com",
    "wof:name":"Mp Fabbrica Rubinetti Srl",
    "wof:placetype":"venue"
},
  "geometry": {"coordinates":[10.139048,45.8064],"type":"Point"}
}