{
  "type": "Feature",
  "properties": {
    "iso:country":"IT",
    "sg:address":"4, Via Maestri Del Lavoro 22070 Carbonate",
    "sg:city":"Carbonate",
    "sg:classifiers":[
        {
            "category":"Shopping",
            "type":"Retail Goods"
        }
    ],
    "sg:phone":"+39 0331 821070",
    "sg:postcode":"22070",
    "sg:province":"Como",
    "sg:tags":[
        "finished",
        "-",
        "metallic"
    ],
    "wof:name":"Victor (s.r.l.)",
    "wof:placetype":"venue"
},
  "geometry": {"coordinates":[8.9253988266,45.6748847961],"type":"Point"}
}