{
  "type": "Feature",
  "properties": {
    "iso:country":"IT",
    "sg:address":"00184 Roma",
    "sg:city":"Roma",
    "sg:orig_category":"Elettrotecnica Industriale, Prodotti E Apparecchiature. Forniture Per Attivita' Commerciali Ed Artigianali",
    "sg:phone":"+39 06 481 9638",
    "sg:postcode":"00184",
    "sg:province":"Roma",
    "wof:name":"Neon Kromos Insegne Luminose",
    "wof:placetype":"venue"
},
  "geometry": {"coordinates":[12.498258,41.889187],"type":"Point"}
}