{
  "type": "Feature",
  "properties": {
    "iso:country":"IT",
    "sg:address":"Via Roma; S. Vito Di Leguzzano; 36030",
    "sg:classifiers":[
        {
            "category":"Banks & Credit Unions",
            "subcategory":"Bank",
            "type":"Services"
        }
    ],
    "sg:phone":"+39 0445 519655",
    "sg:postcode":"36030",
    "sg:province":"Vicenza",
    "wof:name":"Banca Popolare Vicentina Scparl",
    "wof:placetype":"venue"
},
  "geometry": {"coordinates":[11.378622,45.679314],"type":"Point"}
}