{
  "type": "Feature",
  "properties": {
    "iso:country":"IT",
    "sg:address":"Via Avello 40 23892 Bulciago",
    "sg:city":"Bulciago",
    "sg:classifiers":[
        {
            "category":"Home & Garden",
            "subcategory":"Home Furnishings",
            "type":"Retail Goods"
        }
    ],
    "sg:phone":"+39 031 860332",
    "sg:postcode":"23892",
    "sg:province":"Lecco",
    "sg:tags":[
        "textile"
    ],
    "wof:name":"Carboni Snc",
    "wof:placetype":"venue"
},
  "geometry": {"coordinates":[9.390071,45.852982],"type":"Point"}
}