{
  "type": "Feature",
  "properties": {
    "addr:full":"60035 Jesi Jesi Ancona 60035",
    "addr:postcode":"60035;60035",
    "iso:country":"IT",
    "sg:address":"60035 Jesi",
    "sg:city":"Jesi",
    "sg:orig_category":"Abbigliamento Esterno, Maglierie E Pelliccerie",
    "sg:phone":"+39 0731 201478",
    "sg:postcode":"60035",
    "sg:province":"Ancona",
    "wof:name":"Giorgio Chiari Agency",
    "wof:placetype":"venue"
},
  "geometry": {"coordinates":[13.514808,43.536625],"type":"Point"}
}