{
  "type": "Feature",
  "properties": {
    "iso:country":"IT",
    "sg:address":"20035 Lissone",
    "sg:city":"Lissone",
    "sg:orig_category":"Motori Ed Organi Di Trasmissione",
    "sg:phone":"+39 039 214 5363",
    "sg:postcode":"20035",
    "sg:province":"Milano",
    "wof:name":"Siti S.p.a.",
    "wof:placetype":"venue"
},
  "geometry": {"coordinates":[9.2080945969,45.6946525574],"type":"Point"}
}