{
  "type": "Feature",
  "properties": {
    "iso:country":"IT",
    "sg:address":"44011 Argenta",
    "sg:city":"Argenta",
    "sg:orig_category":"Autodemolizioni",
    "sg:phone":"+39 0532 803043",
    "sg:postcode":"44011",
    "sg:province":"Ferrara",
    "wof:name":"Sarasini Celso",
    "wof:placetype":"venue"
},
  "geometry": {"coordinates":[11.708464,44.710972],"type":"Point"}
}