{
  "type": "Feature",
  "properties": {
    "addr:full":"20094 Corsico Corsico Milano 20094",
    "addr:postcode":"20094;20094",
    "iso:country":"IT",
    "sg:address":"20094 Corsico",
    "sg:city":"Corsico",
    "sg:orig_category":"Servizi Vari Di Interesse Pubblico",
    "sg:phone":"+39 02 4510 1076",
    "sg:postcode":"20094",
    "sg:province":"Milano",
    "wof:name":"Monni Paolo",
    "wof:placetype":"venue"
},
  "geometry": {"coordinates":[9.108964,45.431469],"type":"Point"}
}