{
  "type": "Feature",
  "properties": {
    "iso:country":"IT",
    "sg:address":"50041 Calenzano",
    "sg:city":"Calenzano",
    "sg:orig_category":"Forniture Per Abbigliamento E Pelletterie",
    "sg:phone":"+39 055 886721",
    "sg:postcode":"50041",
    "sg:province":"Firenze",
    "sg:website":"http://www.3mc.it",
    "wof:name":"3mc Srl",
    "wof:placetype":"venue"
},
  "geometry": {"coordinates":[10.7479085922,43.8607368469],"type":"Point"}
}