{
  "type": "Feature",
  "properties": {
    "iso:country":"IT",
    "sg:address":"90039 Villabate",
    "sg:city":"Villabate",
    "sg:orig_category":"Vetrerie Artistiche - Vendita Al Dettaglio",
    "sg:phone":"+39 091 492643",
    "sg:postcode":"90039",
    "sg:province":"Palermo",
    "wof:name":"Vetreria Artistica Lucy Collection",
    "wof:placetype":"venue"
},
  "geometry": {"coordinates":[13.442204,38.07716],"type":"Point"}
}