{
  "type": "Feature",
  "properties": {
    "addr:full":"20123 Milano Milano Milano 20123",
    "addr:postcode":"20123;20123",
    "iso:country":"IT",
    "sg:address":"20123 Milano",
    "sg:city":"Milano",
    "sg:orig_category":"Scuole E Servizi Scolastici. Servizi Per Lo Sport E Il Tempo Libero",
    "sg:phone":"+39 02 8646 0394",
    "sg:postcode":"20123",
    "sg:province":"Milano",
    "wof:name":"Circolo Culturale E Ricr. Della Danza Di Pulcini T.",
    "wof:placetype":"venue"
},
  "geometry": {"coordinates":[9.188689,45.463291],"type":"Point"}
}