{
  "type": "Feature",
  "properties": {
    "iso:country":"IT",
    "sg:address":"80053 Castellammare Di Stabia",
    "sg:city":"Castellammare di Stabia",
    "sg:orig_category":"Banche E Servizi Finanziari",
    "sg:phone":"+39 338 422 0885",
    "sg:postcode":"80053",
    "sg:province":"Napoli",
    "wof:name":"Agenzia Immobiliare Dicasaincasa",
    "wof:placetype":"venue"
},
  "geometry": {"coordinates":[14.484421,40.700462],"type":"Point"}
}