{
  "type": "Feature",
  "properties": {
    "iso:country":"IT",
    "sg:address":"22100 Como",
    "sg:city":"Como",
    "sg:orig_category":"Ricambi E Componenti Dei Mezzi Di Trasporto",
    "sg:phone":"+39 031 273100",
    "sg:postcode":"22100",
    "sg:province":"Como",
    "wof:name":"La Carburatecnica",
    "wof:placetype":"venue"
},
  "geometry": {"coordinates":[9.077852,45.806911],"type":"Point"}
}