{
  "type": "Feature",
  "properties": {
    "addr:full":"1, Contrada Morghella 96018 Pachino Pachino Siracusa 96018",
    "addr:postcode":"96018;96018",
    "addr:street":"Contrada Morghella",
    "iso:country":"IT",
    "sg:address":"1, Contrada Morghella 96018 Pachino",
    "sg:city":"Pachino",
    "sg:classifiers":[
        {
            "category":"Farming",
            "subcategory":"Livestock Farm",
            "type":"Manufacturing & Wholesale Goods"
        }
    ],
    "sg:phone":"+39 0931 804111",
    "sg:postcode":"96018",
    "sg:province":"Siracusa",
    "sg:tags":[
        "agriculture"
    ],
    "wof:name":"Acqua Azzurra Srl",
    "wof:placetype":"venue"
},
  "geometry": {"coordinates":[15.28444,37.066483],"type":"Point"}
}