{
  "type": "Feature",
  "properties": {
    "iso:country":"IT",
    "sg:address":"21057 Olgiate Olona",
    "sg:city":"Olgiate Olona",
    "sg:orig_category":"Prodotti E Manufatti In Materie Plastiche",
    "sg:phone":"+39 0331 649665",
    "sg:postcode":"21057",
    "sg:province":"Varese",
    "wof:name":"Garbarini (s.r.l.)",
    "wof:placetype":"venue"
},
  "geometry": {"coordinates":[8.8809213638,45.62449646],"type":"Point"}
}