{
  "type": "Feature",
  "properties": {
    "iso:country":"IT",
    "sg:address":"84126 Salerno",
    "sg:city":"Salerno",
    "sg:orig_category":"Metalli E Leghe",
    "sg:phone":"+39 089 795185",
    "sg:postcode":"84126",
    "sg:province":"Salerno",
    "wof:name":"Del Gizzo Rosalba",
    "wof:placetype":"venue"
},
  "geometry": {"coordinates":[14.7666788101,40.6900634766],"type":"Point"}
}