{
  "type": "Feature",
  "properties": {
    "addr:full":"33074 Fontanafredda Fontanafredda Pordenone 33074",
    "addr:postcode":"33074;33074",
    "iso:country":"IT",
    "sg:address":"33074 Fontanafredda",
    "sg:city":"Fontanafredda",
    "sg:orig_category":"Servizi E Lavori Per Ecologia E Smaltimento Rifiuti",
    "sg:phone":"+39 0434 997219",
    "sg:postcode":"33074",
    "sg:province":"Pordenone",
    "wof:name":"Ideal Water Snc",
    "wof:placetype":"venue"
},
  "geometry": {"coordinates":[12.522894,46.007538],"type":"Point"}
}