{
  "type": "Feature",
  "properties": {
    "iso:country":"IT",
    "sg:address":"16042 Carasco",
    "sg:city":"Carasco",
    "sg:orig_category":"Sport - Articoli E Forniture",
    "sg:phone":"+39 0185 350405",
    "sg:postcode":"16042",
    "sg:province":"Genova",
    "wof:name":"Devoto Sub Di Devoto Albino",
    "wof:placetype":"venue"
},
  "geometry": {"coordinates":[9.361758,44.358757],"type":"Point"}
}