{
  "type": "Feature",
  "properties": {
    "addr:full":"12, Via Betty Ambiveri 24060 Villongo Villongo Bergamo 24060",
    "addr:postcode":"24060;24060",
    "addr:street":"Via Betty Ambiveri",
    "iso:country":"IT",
    "sg:address":"12, Via Betty Ambiveri 24060 Villongo",
    "sg:city":"Villongo",
    "sg:classifiers":[
        {
            "category":"Professional",
            "subcategory":"Engineering",
            "type":"Services"
        }
    ],
    "sg:phone":"+39 39035927337",
    "sg:postcode":"24060",
    "sg:province":"Bergamo",
    "sg:tags":[
        "machine",
        "-",
        "mechanical"
    ],
    "wof:name":"S.a.c.i. (s.r.l.)",
    "wof:placetype":"venue"
},
  "geometry": {"coordinates":[9.928039,45.666103],"type":"Point"}
}