{
  "type": "Feature",
  "properties": {
    "iso:country":"IT",
    "sg:address":"20122 Milano",
    "sg:city":"Milano",
    "sg:orig_category":"Professionisti - Studi E Servizi Ed Associazioni Di Interesse Aziendale. Associazioni Ed Organismi Di Interesse Pubblico",
    "sg:phone":"+39 02 551 0510",
    "sg:postcode":"20122",
    "sg:province":"Milano",
    "wof:name":"Fondazione Pierfranco E Luisa Mariani",
    "wof:placetype":"venue"
},
  "geometry": {"coordinates":[9.1988859177,45.458732605],"type":"Point"}
}