{
  "type": "Feature",
  "properties": {
    "iso:country":"IT",
    "sg:address":"29, Via Belleguardo 25010 Montirone",
    "sg:city":"Montirone",
    "sg:classifiers":[
        {
            "category":"Shopping",
            "subcategory":"Clothing, Apparel, & Fashions",
            "type":"Retail Goods"
        }
    ],
    "sg:phone":"+39 39030267108",
    "sg:postcode":"25010",
    "sg:province":"Brescia",
    "sg:tags":[
        "clothes"
    ],
    "wof:name":"Confezioni Tea Di Soncina Fulvio & C. S.a.s.",
    "wof:placetype":"venue"
},
  "geometry": {"coordinates":[10.230328,45.453182],"type":"Point"}
}