{
  "type": "Feature",
  "properties": {
    "iso:country":"IT",
    "sg:address":"5, Via Vercelli 13030 Caresanablot",
    "sg:city":"Caresanablot",
    "sg:classifiers":[
        {
            "category":"Home & Garden",
            "subcategory":"Home Furnishings",
            "type":"Retail Goods"
        }
    ],
    "sg:phone":"+39 39800806002",
    "sg:postcode":"13030",
    "sg:province":"Vercelli",
    "sg:tags":[
        "household"
    ],
    "wof:name":"Grosfillex (s.p.a.)",
    "wof:placetype":"venue"
},
  "geometry": {"coordinates":[8.388285,45.357548],"type":"Point"}
}