{
  "type": "Feature",
  "properties": {
    "iso:country":"IT",
    "sg:address":"24020 Torre Boldone",
    "sg:city":"Torre Boldone",
    "sg:orig_category":"Prodotti Finiti Stampati. Forniture E Materiali Per Imballaggio E Confezionamento. Forniture Per Attivita' Commerciali Ed Artigianali",
    "sg:phone":"+39 035 343432",
    "sg:postcode":"24020",
    "sg:province":"Bergamo",
    "wof:name":"Millerighe",
    "wof:placetype":"venue"
},
  "geometry": {"coordinates":[9.7028007507,45.7248077393],"type":"Point"}
}