{
  "type": "Feature",
  "properties": {
    "addr:full":"22069 Rovellasca Rovellasca Como 22069",
    "addr:postcode":"22069;22069",
    "iso:country":"IT",
    "sg:address":"22069 Rovellasca",
    "sg:city":"Rovellasca",
    "sg:orig_category":"Forniture Per Agricoltura E Zootecnia. Prodotti Chimici Secondari. Macchine E Forniture Per Ecologia E Smaltimento Rifiuti",
    "sg:phone":"+39 02 9634 2413",
    "sg:postcode":"22069",
    "sg:province":"Como",
    "wof:name":"S.i.a.p.i. (s.a.s.)",
    "wof:placetype":"venue"
},
  "geometry": {"coordinates":[9.0186986923,45.7501220703],"type":"Point"}
}