{
  "type": "Feature",
  "properties": {
    "addr:full":"Via Mazzini 147 73055 Racale Racale Lecce 73055",
    "addr:housenumber":"147",
    "addr:postcode":"73055;73055",
    "addr:street":"Via Mazzini",
    "iso:country":"IT",
    "sg:address":"Via Mazzini 147 73055 Racale",
    "sg:city":"Racale",
    "sg:classifiers":[
        {
            "category":"Personal",
            "subcategory":"Shoe Repair & Shine",
            "type":"Services"
        }
    ],
    "sg:phone":"+39 0833 585110",
    "sg:postcode":"73055",
    "sg:province":"Lecce",
    "sg:tags":[
        "men's",
        "sock"
    ],
    "sg:website":"www.arealevante.com",
    "wof:name":"Calzificio Ala Di Marte Anna Maria",
    "wof:placetype":"venue"
},
  "geometry": {"coordinates":[18.1033000946,39.96276474],"type":"Point"}
}