{
  "type": "Feature",
  "properties": {
    "iso:country":"IT",
    "sg:address":"15, Via Dei Mulini 20080 Albairate",
    "sg:city":"Albairate",
    "sg:classifiers":[
        {
            "category":"Wholesale",
            "subcategory":"Medical Equipment & Supplies",
            "type":"Manufacturing & Wholesale Goods"
        }
    ],
    "sg:phone":"+39 39029406426",
    "sg:postcode":"20080",
    "sg:province":"Milano",
    "sg:tags":[
        "-",
        "health",
        "instrument"
    ],
    "wof:name":"Darbo Engineering S.r.l.",
    "wof:placetype":"venue"
},
  "geometry": {"coordinates":[8.931077,45.421822],"type":"Point"}
}