{
  "type": "Feature",
  "properties": {
    "addr:full":"Via Nuova Provinciale, Snc 23034 Grosotto Grosotto Sondrio 23034",
    "addr:postcode":"23034;23034",
    "addr:street":"Via Nuova Provinciale Snc",
    "iso:country":"IT",
    "sg:address":"Via Nuova Provinciale, Snc 23034 Grosotto",
    "sg:city":"Grosotto",
    "sg:classifiers":[
        {
            "category":"Shopping",
            "subcategory":"Pharmacy",
            "type":"Retail Goods"
        }
    ],
    "sg:phone":"+39 0342 887191",
    "sg:postcode":"23034",
    "sg:province":"Sondrio",
    "sg:tags":[
        "pharmaceutical"
    ],
    "sg:website":"www.baxter.com",
    "wof:name":"Bieffe Medital Spa",
    "wof:placetype":"venue"
},
  "geometry": {"coordinates":[9.8693332672,46.1712608337],"type":"Point"}
}