{
  "type": "Feature",
  "properties": {
    "addr:full":"09134 Cagliari Cagliari Cagliari 09134",
    "addr:postcode":"09134;09134",
    "iso:country":"IT",
    "sg:address":"09134 Cagliari",
    "sg:city":"Cagliari",
    "sg:orig_category":"Macchine, Impianti E Forniture Per Industria Grafica, Cartaria E Cartotecnica. Automazione E Macchine Per Ufficio",
    "sg:phone":"+39 070 551837",
    "sg:postcode":"09134",
    "sg:province":"Cagliari",
    "wof:name":"Emme Office Srl",
    "wof:placetype":"venue"
},
  "geometry": {"coordinates":[9.131346,39.242382],"type":"Point"}
}