{
  "type": "Feature",
  "properties": {
    "iso:country":"IT",
    "sg:address":"8, Via Vedelleria 36040 Torri Di Quartesolo",
    "sg:city":"Torri di Quartesolo",
    "sg:classifiers":[
        {
            "category":"Home & Garden",
            "subcategory":"Home Furnishings",
            "type":"Retail Goods"
        }
    ],
    "sg:phone":"+39 0444 583622",
    "sg:postcode":"36040",
    "sg:province":"Vicenza",
    "sg:tags":[
        "household"
    ],
    "wof:name":"Mobili D'arte Bassanesi S.r.l.",
    "wof:placetype":"venue"
},
  "geometry": {"coordinates":[11.630132,45.507839],"type":"Point"}
}