{
  "type": "Feature",
  "properties": {
    "iso:country":"IT",
    "sg:address":"103, Via S. Stefano 28047 Oleggio",
    "sg:city":"Oleggio",
    "sg:classifiers":[
        {
            "category":"Real Estate",
            "subcategory":"Surveying",
            "type":"Services"
        }
    ],
    "sg:phone":"+39 39032194734",
    "sg:postcode":"28047",
    "sg:province":"Novara",
    "sg:tags":[
        "equipment",
        "material",
        "good",
        "-",
        "handling"
    ],
    "wof:name":"Benazzato Gru (s.p.a.)",
    "wof:placetype":"venue"
},
  "geometry": {"coordinates":[8.64253,45.579842],"type":"Point"}
}