{
  "type": "Feature",
  "properties": {
    "iso:country":"IT",
    "sg:address":"60027 Osimo",
    "sg:city":"Osimo",
    "sg:orig_category":"Servizi E Lavori Per Arredamento E Industria Del Legno. Servizi E Lavori Per Edilizia E Lavori Pubblici",
    "sg:phone":"+39 071 781405",
    "sg:postcode":"60027",
    "sg:province":"Ancona",
    "wof:name":"Gioacchini Adriano",
    "wof:placetype":"venue"
},
  "geometry": {"coordinates":[13.510612,43.523193],"type":"Point"}
}