{
  "type": "Feature",
  "properties": {
    "iso:country":"IT",
    "sg:address":"71010 Peschici",
    "sg:city":"Peschici",
    "sg:orig_category":"Agenzie Marittime",
    "sg:phone":"+39 0884 964234",
    "sg:postcode":"71010",
    "sg:province":"Foggia",
    "wof:name":"Ctm Navigazioni Srl",
    "wof:placetype":"venue"
},
  "geometry": {"coordinates":[16.013638,41.946926],"type":"Point"}
}