{
  "type": "Feature",
  "properties": {
    "iso:country":"IT",
    "sg:address":"9, Via Cervi Fratelli 20017 Rho",
    "sg:city":"Rho",
    "sg:classifiers":[
        {
            "category":"Professional",
            "subcategory":"Engineering",
            "type":"Services"
        }
    ],
    "sg:phone":"+39 02 9390 1153",
    "sg:postcode":"20017",
    "sg:province":"Milano",
    "sg:tags":[
        "machine",
        "-",
        "mechanical"
    ],
    "wof:name":"Meccanica Rhodense",
    "wof:placetype":"venue"
},
  "geometry": {"coordinates":[9.076497,45.528187],"type":"Point"}
}