{
  "type": "Feature",
  "properties": {
    "addr:full":"Zona Industriale Commerciale Artigianale 85016 Piano San Nicola Di Pietragalla Pietragalla Potenza 85016",
    "addr:postcode":"85016;85016",
    "addr:street":"Zona Industriale Commerciale Artigianale;Pietragalla",
    "iso:country":"IT",
    "sg:address":"Zona Industriale Commerciale Artigianale 85016 Piano San Nicola Di Pietragalla",
    "sg:city":"Pietragalla",
    "sg:classifiers":[
        {
            "category":"Communications",
            "subcategory":"Newspaper",
            "type":"Services"
        }
    ],
    "sg:phone":"+39 39097168429",
    "sg:postcode":"85016",
    "sg:province":"Potenza",
    "sg:tags":[
        "advertising"
    ],
    "sg:website":"http://www.effegpubblicitaria.com",
    "wof:name":"Effeg Pubblicitaria",
    "wof:placetype":"venue"
},
  "geometry": {"coordinates":[15.802221,40.637241],"type":"Point"}
}