{
  "type": "Feature",
  "properties": {
    "iso:country":"IT",
    "sg:address":"20121 Milano",
    "sg:city":"Milano",
    "sg:orig_category":"Abbigliamento Esterno, Maglierie E Pelliccerie. Forniture Per Il Settore Dello Spettacolo",
    "sg:phone":"+39 02 8646 1744",
    "sg:postcode":"20121",
    "sg:province":"Milano",
    "wof:name":"Wannabe Srl",
    "wof:placetype":"venue"
},
  "geometry": {"coordinates":[9.185172,45.469559],"type":"Point"}
}