{
  "type": "Feature",
  "properties": {
    "iso:country":"IT",
    "sg:address":"20090 Buccinasco",
    "sg:city":"Buccinasco",
    "sg:orig_category":"Minuterie Metalliche E Ferramenta",
    "sg:phone":"+39 02 4884 2094",
    "sg:postcode":"20090",
    "sg:province":"Milano",
    "wof:name":"Derk (s.p.a.)",
    "wof:placetype":"venue"
},
  "geometry": {"coordinates":[9.1215257645,45.4264450073],"type":"Point"}
}