{
  "type": "Feature",
  "properties": {
    "addr:full":"2583, S. Polo 30125 Venezia Venezia Venezia 30125",
    "addr:housenumber":"2583",
    "addr:postcode":"30125;30125",
    "addr:street":"S. Polo",
    "iso:country":"IT",
    "sg:address":"2583, S. Polo 30125 Venezia",
    "sg:city":"Venezia",
    "sg:classifiers":[
        {
            "category":"Manufacturing",
            "subcategory":"Printing",
            "type":"Manufacturing & Wholesale Goods"
        }
    ],
    "sg:phone":"+39 39041714035",
    "sg:postcode":"30125",
    "sg:province":"Venezia",
    "sg:tags":[
        "publishing"
    ],
    "wof:name":"Einaudi - Electa Rateale",
    "wof:placetype":"venue"
},
  "geometry": {"coordinates":[12.3240594864,45.4381980896],"type":"Point"}
}