{
  "type": "Feature",
  "properties": {
    "iso:country":"IT",
    "sg:address":"80012 Calvizzano",
    "sg:city":"Calvizzano",
    "sg:orig_category":"Scuole E Servizi Scolastici",
    "sg:phone":"+39 081 713 0978",
    "sg:postcode":"80012",
    "sg:province":"Napoli",
    "wof:name":"Istituto Parificato S.botticelli",
    "wof:placetype":"venue"
},
  "geometry": {"coordinates":[14.178563,40.908966],"type":"Point"}
}