{
  "type": "Feature",
  "properties": {
    "addr:full":"80138 Napoli Napoli Napoli 80138",
    "addr:housenumber":"80138",
    "addr:postcode":"80138",
    "iso:country":"IT",
    "sg:address":"80138 Napoli",
    "sg:city":"Napoli",
    "sg:orig_category":"Impianti, Attrezzature E Forniture Sanitarie Ed Ospedaliere",
    "sg:phone":"+39 081 554 1260",
    "sg:postcode":"80138",
    "sg:province":"Napoli",
    "wof:name":"Antica Farmacia Cozzolino & Vecchione Di Giovanni Calcagno",
    "wof:placetype":"venue"
},
  "geometry": {"coordinates":[14.180674,40.860336],"type":"Point"}
}