{
  "type": "Feature",
  "properties": {
    "iso:country":"IT",
    "sg:address":"98027 Roccalumera",
    "sg:city":"Roccalumera",
    "sg:orig_category":"Scuole E Servizi Scolastici. Ricerca, Selezione E Formazione Del Personale",
    "sg:phone":"+39 0942 747144",
    "sg:postcode":"98027",
    "sg:province":"Messina",
    "wof:name":"Istituto Dattilografico Italiano Srl",
    "wof:placetype":"venue"
},
  "geometry": {"coordinates":[15.426314,38.234119],"type":"Point"}
}