{
  "type": "Feature",
  "properties": {
    "addr:full":"21047 Saronno Saronno Varese 21047",
    "addr:postcode":"21047;21047",
    "iso:country":"IT",
    "sg:address":"21047 Saronno",
    "sg:city":"Saronno",
    "sg:orig_category":"Non-classified Establishments",
    "sg:phone":"+39 02 9670 8158",
    "sg:postcode":"21047",
    "sg:province":"Varese",
    "wof:name":"Masi Alessandro Piero",
    "wof:placetype":"venue"
},
  "geometry": {"coordinates":[9.034451,45.633488],"type":"Point"}
}