{
  "type": "Feature",
  "properties": {
    "iso:country":"IT",
    "sg:address":"20124 Milano",
    "sg:city":"Milano",
    "sg:orig_category":"Banche E Servizi Finanziari",
    "sg:phone":"+39 02 669 4609",
    "sg:postcode":"20124",
    "sg:province":"Milano",
    "wof:name":"Fidelconsult Compagnia Fiduciaria E Di Revisione S.p.a.",
    "wof:placetype":"venue"
},
  "geometry": {"coordinates":[9.200013,45.479797],"type":"Point"}
}