{
  "type": "Feature",
  "properties": {
    "addr:full":"48, Via Cuneo 12045 Fossano Fossano Cuneo 12045",
    "addr:postcode":"12045;12045",
    "addr:street":"Via Cuneo",
    "iso:country":"IT",
    "sg:address":"48, Via Cuneo 12045 Fossano",
    "sg:city":"Fossano",
    "sg:orig_category":"Miscellaneous Products",
    "sg:phone":"+39 39017260216",
    "sg:postcode":"12045",
    "sg:province":"Cuneo",
    "wof:name":"Oberto",
    "wof:placetype":"venue"
},
  "geometry": {"coordinates":[7.545586586,44.5265693665],"type":"Point"}
}