{
  "type": "Feature",
  "properties": {
    "addr:full":"09010 Decimoputzu Decimoputzu Cagliari 09010",
    "addr:postcode":"09010;09010",
    "iso:country":"IT",
    "sg:address":"09010 Decimoputzu",
    "sg:city":"Decimoputzu",
    "sg:orig_category":"Vivai Piante E Fiori",
    "sg:phone":"+39 070 963 3161",
    "sg:postcode":"09010",
    "sg:province":"Cagliari",
    "wof:name":"Canale Del Leccio Vivai Sas",
    "wof:placetype":"venue"
},
  "geometry": {"coordinates":[8.916259,39.336426],"type":"Point"}
}