{
  "type": "Feature",
  "properties": {
    "iso:country":"IT",
    "sg:address":"43, Traversa Criscuolo 84016 Pagani",
    "sg:city":"Pagani",
    "sg:classifiers":[
        {
            "category":"Real Estate",
            "subcategory":"Surveying",
            "type":"Services"
        }
    ],
    "sg:phone":"+39 39081916197",
    "sg:postcode":"84016",
    "sg:province":"Salerno",
    "sg:tags":[
        "equipment",
        "material",
        "good",
        "-",
        "handling"
    ],
    "wof:name":"Stoia Giuseppe",
    "wof:placetype":"venue"
},
  "geometry": {"coordinates":[14.598064,40.757301],"type":"Point"}
}