{
  "type": "Feature",
  "properties": {
    "addr:full":"Via V Emanuele 153; Bordighera; 18012 Bordighera Imperia 18012",
    "addr:housenumber":"153",
    "addr:postcode":"18012;18012",
    "addr:street":"Via V Emanuele",
    "iso:country":"IT",
    "sg:address":"Via V Emanuele 153; Bordighera; 18012",
    "sg:city":"Bordighera",
    "sg:classifiers":[
        {
            "category":"Banks & Credit Unions",
            "subcategory":"Bank",
            "type":"Services"
        }
    ],
    "sg:phone":"+39 0184 266777",
    "sg:postcode":"18012",
    "sg:province":"Imperia",
    "wof:name":"Banca Carige Spa",
    "wof:placetype":"venue"
},
  "geometry": {"coordinates":[7.664283,43.778965],"type":"Point"}
}