{
  "type": "Feature",
  "properties": {
    "iso:country":"IT",
    "sg:address":"40037 Sasso Marconi",
    "sg:city":"Sasso Marconi",
    "sg:orig_category":"Stampi Pressofusione",
    "sg:phone":"+39 051 842312",
    "sg:postcode":"40037",
    "sg:province":"Bologna",
    "wof:name":"Bucciol Fratelli Snc",
    "wof:placetype":"venue"
},
  "geometry": {"coordinates":[11.229711,44.427582],"type":"Point"}
}