{
  "type": "Feature",
  "properties": {
    "iso:country":"IT",
    "sg:address":"Via L. Allegro 1 16016 Cogoleto",
    "sg:city":"Cogoleto",
    "sg:classifiers":[
        {
            "category":"Utilities",
            "subcategory":"Water",
            "type":"Services"
        }
    ],
    "sg:phone":"+39 010 91711",
    "sg:postcode":"16016",
    "sg:province":"Genova",
    "sg:tags":[
        "construction",
        "piping",
        "drinking",
        "supply"
    ],
    "sg:website":"www.sgcondotte.com",
    "wof:name":"Saint-gobain Condotte Spa",
    "wof:placetype":"venue"
},
  "geometry": {"coordinates":[8.9339885712,44.4070625305],"type":"Point"}
}