{
  "type": "Feature",
  "properties": {
    "addr:full":"15020 Villa Del Foro Villa del Foro Alessandria 15020",
    "addr:housenumber":"15020",
    "addr:postcode":"15020",
    "addr:street":"Villa;Foro;Foro",
    "iso:country":"IT",
    "sg:address":"15020 Villa Del Foro",
    "sg:city":"Villa del Foro",
    "sg:orig_category":"Articoli Per Imballaggio E Confezionamento",
    "sg:phone":"+39 0131 259885",
    "sg:postcode":"15020",
    "sg:province":"Alessandria",
    "wof:name":"Rapetti Luigi",
    "wof:placetype":"venue"
},
  "geometry": {"coordinates":[8.526966,44.887878],"type":"Point"}
}