{
  "type": "Feature",
  "properties": {
    "iso:country":"IT",
    "sg:address":"06121 Perugia",
    "sg:city":"Perugia",
    "sg:orig_category":"Apparecchi Acustici Per Sordita'",
    "sg:phone":"+39 075 573 6866",
    "sg:postcode":"06121",
    "sg:province":"Perugia",
    "wof:name":"Service Import Maxico Srl",
    "wof:placetype":"venue"
},
  "geometry": {"coordinates":[12.389246,43.109695],"type":"Point"}
}