{
  "type": "Feature",
  "properties": {
    "addr:full":"00167 Roma Roma Roma 00167",
    "addr:postcode":"00167;00167",
    "iso:country":"IT",
    "sg:address":"00167 Roma",
    "sg:city":"Roma",
    "sg:orig_category":"Barche, Canotti Pneumatici E Motoscafi - Vendita Al Dettaglio",
    "sg:phone":"+39 06 614 6953",
    "sg:postcode":"00167",
    "sg:province":"Roma",
    "wof:name":"'il Gommone' Di Massimo Agostinelli & C. Sas",
    "wof:placetype":"venue"
},
  "geometry": {"coordinates":[12.422555,41.914413],"type":"Point"}
}