{
  "type": "Feature",
  "properties": {
    "iso:country":"IT",
    "sg:address":"12060 Magliano Alpi",
    "sg:city":"Magliano Alpi",
    "sg:classifiers":[
        {
            "category":"Personal",
            "subcategory":"Nail Salon",
            "type":"Services"
        }
    ],
    "sg:phone":"+39 0174 66675",
    "sg:postcode":"12060",
    "sg:province":"Cuneo",
    "sg:tags":[
        "scale"
    ],
    "wof:name":"Massimino Piervincenzo Massimino Scale",
    "wof:placetype":"venue"
},
  "geometry": {"coordinates":[7.806407,44.460629],"type":"Point"}
}