{
  "type": "Feature",
  "properties": {
    "addr:full":"52031 Anghiari Anghiari Arezzo 52031",
    "addr:postcode":"52031;52031",
    "iso:country":"IT",
    "sg:address":"52031 Anghiari",
    "sg:city":"Anghiari",
    "sg:orig_category":"Musica",
    "sg:phone":"+39 0575 749313",
    "sg:postcode":"52031",
    "sg:province":"Arezzo",
    "wof:name":"Ramo Legno E Musica Di Neumann R.",
    "wof:placetype":"venue"
},
  "geometry": {"coordinates":[12.3306293488,43.7224998474],"type":"Point"}
}