{
  "type": "Feature",
  "properties": {
    "addr:full":"56017 San Giuliano Terme San Giuliano Terme Pisa 56017",
    "addr:postcode":"56017;56017",
    "iso:country":"IT",
    "sg:address":"56017 San Giuliano Terme",
    "sg:city":"San Giuliano Terme",
    "sg:orig_category":"Prodotti Alimentari",
    "sg:phone":"+39 050 870293",
    "sg:postcode":"56017",
    "sg:province":"Pisa",
    "wof:name":"Cnc Di Nencioni Marcello & C. Snc",
    "wof:placetype":"venue"
},
  "geometry": {"coordinates":[10.4833984375,43.7099838257],"type":"Point"}
}