{
  "type": "Feature",
  "properties": {
    "iso:country":"IT",
    "sg:address":"22060 Cucciago",
    "sg:city":"Cucciago",
    "sg:orig_category":"Ospedali E Servizi Sanitari. Servizi Ausiliari Di Analisi, Controllo E Ricerca",
    "sg:phone":"+39 031 787809",
    "sg:postcode":"22060",
    "sg:province":"Como",
    "wof:name":"M.p. Srl",
    "wof:placetype":"venue"
},
  "geometry": {"coordinates":[9.094074,45.740334],"type":"Point"}
}