{
  "type": "Feature",
  "properties": {
    "iso:country":"IT",
    "sg:address":"20040 Usmate Velate",
    "sg:city":"Usmate Velate",
    "sg:orig_category":"Servizi Per Aziende, Manifestazioni E Supporto Agli Scambi Commerciali",
    "sg:phone":"+39 039 682 9153",
    "sg:postcode":"20040",
    "sg:province":"Milano",
    "wof:name":"Mapelli Gianpiero",
    "wof:placetype":"venue"
},
  "geometry": {"coordinates":[9.363587,45.65144],"type":"Point"}
}