{
  "type": "Feature",
  "properties": {
    "addr:full":"13, Viale Magellano 42046 Reggiolo Reggio Nell'Emilia 42046",
    "addr:housenumber":"13",
    "addr:postcode":"42046;42046",
    "addr:street":"Viale Magellano",
    "iso:country":"IT",
    "sg:address":"13, Viale Magellano 42046 Reggiolo",
    "sg:classifiers":[
        {
            "category":"Shopping",
            "type":"Retail Goods"
        }
    ],
    "sg:phone":"+39 0522 973030",
    "sg:postcode":"42046",
    "sg:province":"Reggio Nell'Emilia",
    "sg:tags":[
        "finished",
        "-",
        "metallic"
    ],
    "wof:name":"Falavigna Officine S.p.a.",
    "wof:placetype":"venue"
},
  "geometry": {"coordinates":[10.8438529968,44.9079856873],"type":"Point"}
}