{
  "type": "Feature",
  "properties": {
    "iso:country":"IT",
    "sg:address":"1, Localita' S.scolastica 06046 Norcia",
    "sg:city":"Norcia",
    "sg:classifiers":[
        {
            "category":"Food & Beverages",
            "subcategory":"Groceries & Convenience Stores",
            "type":"Retail Goods"
        }
    ],
    "sg:phone":"+39 0743 816119",
    "sg:postcode":"06046",
    "sg:province":"Perugia",
    "sg:tags":[
        "product",
        "related"
    ],
    "wof:name":"Lanzi S.r.l.",
    "wof:placetype":"venue"
},
  "geometry": {"coordinates":[12.3891716003,43.1107025146],"type":"Point"}
}