{
  "type": "Feature",
  "properties": {
    "addr:full":"84, Piazza Municipio 80133 Napoli Napoli Napoli 80133",
    "addr:postcode":"80133;80133",
    "addr:street":"Piazza Municipio",
    "iso:country":"IT",
    "sg:address":"84, Piazza Municipio 80133 Napoli",
    "sg:city":"Napoli",
    "sg:classifiers":[
        {
            "category":"Manufacturing",
            "subcategory":"Metals",
            "type":"Manufacturing & Wholesale Goods"
        }
    ],
    "sg:phone":"+39 081 552 2283",
    "sg:postcode":"80133",
    "sg:province":"Napoli",
    "sg:tags":[
        "processing"
    ],
    "wof:name":"Mp. Pagliuca S.r.l.",
    "wof:placetype":"venue"
},
  "geometry": {"coordinates":[14.2505283356,40.8402709961],"type":"Point"}
}