{
  "type": "Feature",
  "properties": {
    "addr:full":"65122 Pescara Pescara Pescara 65122",
    "addr:postcode":"65122;65122",
    "iso:country":"IT",
    "sg:address":"65122 Pescara",
    "sg:city":"Pescara",
    "sg:orig_category":"Istituti Di Bellezza",
    "sg:phone":"+39 085 421 1224",
    "sg:postcode":"65122",
    "sg:province":"Pescara",
    "sg:website":"http://www.paginegialle.it/scuolasem",
    "wof:name":"Scuola Sem Sas",
    "wof:placetype":"venue"
},
  "geometry": {"coordinates":[14.210313,42.467079],"type":"Point"}
}