{
  "type": "Feature",
  "properties": {
    "iso:country":"IT",
    "sg:address":"30020 Marcon",
    "sg:city":"Marcon",
    "sg:orig_category":"Trasporti E Spedizioni Merci",
    "sg:phone":"+39 041 596 9025",
    "sg:postcode":"30020",
    "sg:province":"Venezia",
    "wof:name":"Dolce Mare S.a.s.",
    "wof:placetype":"venue"
},
  "geometry": {"coordinates":[12.307994,45.549164],"type":"Point"}
}