{
  "type": "Feature",
  "properties": {
    "iso:country":"IT",
    "sg:address":"74020 Maruggio",
    "sg:city":"Maruggio",
    "sg:orig_category":"Serramenti Ed Infissi",
    "sg:phone":"+39 099 675292",
    "sg:postcode":"74020",
    "sg:province":"Taranto",
    "wof:name":"Fam Srl",
    "wof:placetype":"venue"
},
  "geometry": {"coordinates":[17.448774,40.390179],"type":"Point"}
}