{
  "type": "Feature",
  "properties": {
    "iso:country":"IT",
    "sg:address":"00151 Roma",
    "sg:city":"Roma",
    "sg:orig_category":"Servizi Al Turismo. Ambasciate Ed Enti Internazionali",
    "sg:phone":"+39 06 653 5856",
    "sg:postcode":"00151",
    "sg:province":"Roma",
    "wof:name":"Ambasciata Presso Lo Stato Italiano Angola",
    "wof:placetype":"venue"
},
  "geometry": {"coordinates":[12.441254,41.863708],"type":"Point"}
}