{
  "type": "Feature",
  "properties": {
    "iso:country":"IT",
    "sg:address":"Via Frejus 8 10092 Beinasco",
    "sg:city":"Beinasco",
    "sg:classifiers":[
        {
            "category":"Manufacturing",
            "subcategory":"Motor Vehicles & Parts",
            "type":"Manufacturing & Wholesale Goods"
        }
    ],
    "sg:phone":"+39 011 397 1143",
    "sg:postcode":"10092",
    "sg:province":"Torino",
    "sg:tags":[
        "aluminium",
        "processing",
        "sheet"
    ],
    "sg:website":"www.furlan.it",
    "wof:name":"G.furlan Srl",
    "wof:placetype":"venue"
},
  "geometry": {"coordinates":[7.584508,45.027153],"type":"Point"}
}