{
  "type": "Feature",
  "properties": {
    "addr:full":"20144 Milano Milano Milano 20144",
    "addr:postcode":"20144;20144",
    "iso:country":"IT",
    "sg:address":"20144 Milano",
    "sg:city":"Milano",
    "sg:orig_category":"Forniture Per Attivita' Industriali",
    "sg:phone":"+39 02 4895 0008",
    "sg:postcode":"20144",
    "sg:province":"Milano",
    "sg:website":"http://www.vibrostop.it",
    "wof:name":"Vibrostop Srl",
    "wof:placetype":"venue"
},
  "geometry": {"coordinates":[9.1464605331,45.448474884],"type":"Point"}
}