{
  "type": "Feature",
  "properties": {
    "iso:country":"IT",
    "sg:address":"57122 Livorno",
    "sg:city":"Livorno",
    "sg:orig_category":"Caffe' Crudo E Torrefatto",
    "sg:phone":"+39 0586 829275",
    "sg:postcode":"57122",
    "sg:province":"Livorno",
    "wof:name":"Torrefazione S. Paulo Di Colonnacchi Marisa",
    "wof:placetype":"venue"
},
  "geometry": {"coordinates":[10.312834,43.556107],"type":"Point"}
}