{
  "type": "Feature",
  "properties": {
    "iso:country":"IT",
    "sg:address":"25085 Gavardo",
    "sg:city":"Gavardo",
    "sg:orig_category":"Materiali Edili",
    "sg:phone":"+39 036 532100",
    "sg:postcode":"25085",
    "sg:province":"Brescia",
    "wof:name":"Ferretti Fratelli (s.r.l.)",
    "wof:placetype":"venue"
},
  "geometry": {"coordinates":[10.380643,45.644794],"type":"Point"}
}