{
  "type": "Feature",
  "properties": {
    "iso:country":"IT",
    "sg:address":"22070 Bregnano",
    "sg:city":"Bregnano",
    "sg:orig_category":"Accessori Moda D'abbigliamento. Forniture Per Abbigliamento E Pelletterie",
    "sg:phone":"+39 031 778853",
    "sg:postcode":"22070",
    "sg:province":"Como",
    "wof:name":"Desseilles Italia Srl",
    "wof:placetype":"venue"
},
  "geometry": {"coordinates":[9.062572,45.706463],"type":"Point"}
}