{
  "type": "Feature",
  "properties": {
    "iso:country":"IT",
    "sg:address":"Via Lein\u00ec 150 10036 Settimo Torinese",
    "sg:city":"Settimo Torinese",
    "sg:classifiers":[
        {
            "category":"Banks & Credit Unions",
            "subcategory":"Investment Brokerage",
            "type":"Services"
        }
    ],
    "sg:phone":"+39 011 802 3411",
    "sg:postcode":"10036",
    "sg:province":"Torino",
    "sg:tags":[
        "product",
        "hair-care"
    ],
    "sg:website":"www.farmenspa.com",
    "wof:name":"Farmen Spa",
    "wof:placetype":"venue"
},
  "geometry": {"coordinates":[7.729383,45.148468],"type":"Point"}
}