{
  "type": "Feature",
  "properties": {
    "addr:full":"87064 Corigliano Calabro Corigliano Calabro Cosenza 87064",
    "addr:postcode":"87064;87064",
    "iso:country":"IT",
    "sg:address":"87064 Corigliano Calabro",
    "sg:city":"Corigliano Calabro",
    "sg:orig_category":"Accessori Dei Mezzi Di Trasporto",
    "sg:phone":"+39 0983 884268",
    "sg:postcode":"87064",
    "sg:province":"Cosenza",
    "wof:name":"B.r.t. Motors Srl",
    "wof:placetype":"venue"
},
  "geometry": {"coordinates":[16.513344,39.628185],"type":"Point"}
}