{
  "type": "Feature",
  "properties": {
    "addr:full":"5, Via Genova 20039 Varedo Varedo Milano 20039",
    "addr:postcode":"20039;20039",
    "addr:street":"Via Genova",
    "iso:country":"IT",
    "sg:address":"5, Via Genova 20039 Varedo",
    "sg:city":"Varedo",
    "sg:classifiers":[
        {
            "category":"Manufacturing",
            "subcategory":"Rubber & Plastics",
            "type":"Manufacturing & Wholesale Goods"
        }
    ],
    "sg:phone":"+39 036 254 4335",
    "sg:postcode":"20039",
    "sg:province":"Milano",
    "wof:name":"Esta Spa",
    "wof:placetype":"venue"
},
  "geometry": {"coordinates":[9.1955137253,45.5994186401],"type":"Point"}
}