{
  "type": "Feature",
  "properties": {
    "addr:full":"24125 Bergamo Bergamo Bergamo 24125",
    "addr:postcode":"24125;24125",
    "iso:country":"IT",
    "sg:address":"24125 Bergamo",
    "sg:city":"Bergamo",
    "sg:orig_category":"Pubblica Amministrazione",
    "sg:phone":"+39 035 294423",
    "sg:postcode":"24125",
    "sg:province":"Bergamo",
    "wof:name":"Casa Circondariale",
    "wof:placetype":"venue"
},
  "geometry": {"coordinates":[9.7060594559,45.6952552795],"type":"Point"}
}