{
  "type": "Feature",
  "properties": {
    "iso:country":"IT",
    "sg:address":"Viale Dell' Industria 22 20040 Cambiago",
    "sg:city":"Cambiago",
    "sg:classifiers":[
        {
            "category":"Banks & Credit Unions",
            "subcategory":"Atm",
            "type":"Services"
        }
    ],
    "sg:phone":"+39 02 9530 8400",
    "sg:postcode":"20040",
    "sg:province":"Milano",
    "sg:tags":[
        "field"
    ],
    "sg:website":"www.cbi-service.com",
    "wof:name":"Cbi Service Srl",
    "wof:placetype":"venue"
},
  "geometry": {"coordinates":[9.1881408691,45.4636878967],"type":"Point"}
}