{
  "type": "Feature",
  "properties": {
    "iso:country":"IT",
    "sg:address":"34147 Trieste",
    "sg:city":"Trieste",
    "sg:orig_category":"Manufacturers: Prefabbricati. Arredi Ed Attrezzature Per Attivita' Commerciali Ed Artigianali",
    "sg:phone":"+39 040 281149",
    "sg:postcode":"34147",
    "sg:province":"Trieste",
    "wof:name":"Plastifilo Snc Di Fanelli Sergio E C.",
    "wof:placetype":"venue"
},
  "geometry": {"coordinates":[13.809273,45.615253],"type":"Point"}
}