{
  "type": "Feature",
  "properties": {
    "iso:country":"IT",
    "sg:address":"57023 Cecina",
    "sg:city":"Cecina",
    "sg:orig_category":"Impiantistica E Prodotti Tecnologici Per Edilizia. Termotecnica E Riscaldamento, Apparecchiature E Servizi",
    "sg:phone":"+39 347 706 0870",
    "sg:postcode":"57023",
    "sg:province":"Livorno",
    "wof:name":"Novoclima Di Castellini A.",
    "wof:placetype":"venue"
},
  "geometry": {"coordinates":[10.495868,43.317638],"type":"Point"}
}