{
  "type": "Feature",
  "properties": {
    "iso:country":"IT",
    "sg:address":"1, Via Milano 20020 Lainate",
    "sg:city":"Lainate",
    "sg:classifiers":[
        {
            "category":"Professional",
            "subcategory":"Engineering",
            "type":"Services"
        }
    ],
    "sg:phone":"+39 39029376071",
    "sg:postcode":"20020",
    "sg:province":"Milano",
    "sg:tags":[
        "machine",
        "-",
        "mechanical"
    ],
    "wof:name":"Savio Macchine S.p.a.",
    "wof:placetype":"venue"
},
  "geometry": {"coordinates":[9.043819,45.525215],"type":"Point"}
}