{
  "type": "Feature",
  "properties": {
    "addr:full":"Via Campagna, 15 - Cognento 41100 Modena Cognento Modena 41100",
    "addr:housenumber":"15",
    "addr:postcode":"41100;41100",
    "addr:street":"Via Campagna",
    "iso:country":"IT",
    "sg:address":"Via Campagna, 15 - Cognento 41100 Modena",
    "sg:city":"Cognento",
    "sg:classifiers":[
        {
            "category":"Shopping",
            "subcategory":"Clothing, Apparel, & Fashions",
            "type":"Retail Goods"
        }
    ],
    "sg:phone":"+39 059 421511",
    "sg:postcode":"41100",
    "sg:province":"Modena",
    "sg:tags":[
        "image",
        "clothing",
        "basic"
    ],
    "wof:name":"Rotondi Evolution Spa - Divisione Abbigliamento",
    "wof:placetype":"venue"
},
  "geometry": {"coordinates":[10.877438,44.639328],"type":"Point"}
}