{
  "type": "Feature",
  "properties": {
    "iso:country":"IT",
    "sg:address":"18016 Villa Faraldi",
    "sg:orig_category":"Pubblica Amministrazione",
    "sg:phone":"+39 0183 41025",
    "sg:postcode":"18016",
    "sg:province":"Imperia",
    "wof:name":"Comune Villa Faraldi",
    "wof:placetype":"venue"
},
  "geometry": {"coordinates":[8.0761032104,43.9314918518],"type":"Point"}
}