{
  "type": "Feature",
  "properties": {
    "iso:country":"IT",
    "sg:address":"00060 Sacrofano",
    "sg:city":"Sacrofano",
    "sg:orig_category":"Autoscuole",
    "sg:phone":"+39 06 908 6621",
    "sg:postcode":"00060",
    "sg:province":"Roma",
    "wof:name":"Capuani Elvira",
    "wof:placetype":"venue"
},
  "geometry": {"coordinates":[12.448756,42.104149],"type":"Point"}
}