{
  "type": "Feature",
  "properties": {
    "iso:country":"IT",
    "sg:address":"36034 Malo",
    "sg:city":"Malo",
    "sg:orig_category":"Materiali Semilavorati Metallici. Materiali E Componenti Elettrotecnici",
    "sg:phone":"+39 0445 637355",
    "sg:postcode":"36034",
    "sg:province":"Vicenza",
    "sg:website":"http://www.metraspa.it",
    "wof:name":"Metra Spa",
    "wof:placetype":"venue"
},
  "geometry": {"coordinates":[11.459337,45.679569],"type":"Point"}
}