{
  "type": "Feature",
  "properties": {
    "iso:country":"IT",
    "sg:address":"20064 Gorgonzola",
    "sg:city":"Gorgonzola",
    "sg:orig_category":"Ospedali E Servizi Sanitari. Pubblica Amministrazione. Servizi Sociali",
    "sg:phone":"+39 02 9530 0061",
    "sg:postcode":"20064",
    "sg:province":"Milano",
    "wof:name":"Azienda Ospedaliera Di Melegnano",
    "wof:placetype":"venue"
},
  "geometry": {"coordinates":[9.06901,45.538532],"type":"Point"}
}