{
  "type": "Feature",
  "properties": {
    "iso:country":"IT",
    "sg:address":"24060 Villongo",
    "sg:city":"Villongo",
    "sg:orig_category":"Forniture Per Attivita' Industriali",
    "sg:phone":"+39 035 426 0111",
    "sg:postcode":"24060",
    "sg:province":"Bergamo",
    "sg:website":"http://www.argomm.com",
    "wof:name":"Argomm Spa",
    "wof:placetype":"venue"
},
  "geometry": {"coordinates":[9.6718006134,45.6947059631],"type":"Point"}
}