{
  "type": "Feature",
  "properties": {
    "iso:country":"IT",
    "sg:address":"19020 Follo",
    "sg:city":"Ceparana",
    "sg:orig_category":"Carni, Salumi E Pesci",
    "sg:phone":"+39 0187 933871",
    "sg:postcode":"19020",
    "sg:province":"La Spezia",
    "wof:name":"Golfomar Srl",
    "wof:placetype":"venue"
},
  "geometry": {"coordinates":[9.862982,44.164871],"type":"Point"}
}