{
  "type": "Feature",
  "properties": {
    "addr:full":"Via Travazzoi 47 32100 Belluno Belluno Belluno 32100",
    "addr:housenumber":"47",
    "addr:postcode":"32100;32100",
    "addr:street":"Via Travazzoi",
    "iso:country":"IT",
    "sg:address":"Via Travazzoi 47 32100 Belluno",
    "sg:city":"Belluno",
    "sg:classifiers":[
        {
            "category":"Manufacturing",
            "subcategory":"Glass & Minerals",
            "type":"Manufacturing & Wholesale Goods"
        }
    ],
    "sg:phone":"+39 0437 26876",
    "sg:postcode":"32100",
    "sg:province":"Belluno",
    "sg:tags":[
        "frame"
    ],
    "wof:name":"Optical & Service Di Giotto Alfredo & C. S.a.s.",
    "wof:placetype":"venue"
},
  "geometry": {"coordinates":[12.203369,46.145374],"type":"Point"}
}