{
  "type": "Feature",
  "properties": {
    "addr:full":"90, Via Marzabotto 40050 Argelato Argelato Bologna 40050",
    "addr:postcode":"40050;40050",
    "addr:street":"Via Marzabotto",
    "iso:country":"IT",
    "sg:address":"90, Via Marzabotto 40050 Argelato",
    "sg:city":"Argelato",
    "sg:classifiers":[
        {
            "category":"Manufacturing",
            "subcategory":"Rubber & Plastics",
            "type":"Manufacturing & Wholesale Goods"
        }
    ],
    "sg:phone":"+39 051 664 6394",
    "sg:postcode":"40050",
    "sg:province":"Bologna",
    "wof:name":"La.ma. Srl",
    "wof:placetype":"venue"
},
  "geometry": {"coordinates":[11.3205394745,44.5553321838],"type":"Point"}
}