{
  "type": "Feature",
  "properties": {
    "addr:full":"24020 Scanzorosciate Rosciate Bergamo 24020",
    "addr:postcode":"24020;24020",
    "iso:country":"IT",
    "sg:address":"24020 Scanzorosciate",
    "sg:city":"Rosciate",
    "sg:classifiers":[
        {
            "category":"Professional",
            "subcategory":"Employment Agencies",
            "type":"Services"
        }
    ],
    "sg:phone":"+39 035 662722",
    "sg:postcode":"24020",
    "sg:province":"Bergamo",
    "sg:tags":[
        "activities",
        "commercial",
        "equipment",
        "artisan",
        "supplies",
        "furniture",
        "accommodation",
        "furnishing"
    ],
    "sg:website":"http://www.lineart-arredamenti.it",
    "wof:name":"Lineart Srl",
    "wof:placetype":"venue"
},
  "geometry": {"coordinates":[9.7362775803,45.7117233276],"type":"Point"}
}