{
  "type": "Feature",
  "properties": {
    "iso:country":"IT",
    "sg:address":"Via Iv Novembre 114 13853 Lessona",
    "sg:city":"Lessona",
    "sg:classifiers":[
        {
            "category":"Wholesale",
            "subcategory":"Plants",
            "type":"Manufacturing & Wholesale Goods"
        }
    ],
    "sg:phone":"+39 015 93139",
    "sg:postcode":"13853",
    "sg:province":"Biella",
    "sg:tags":[
        "synthetic",
        "fibre",
        "spinning",
        "yarn"
    ],
    "wof:name":"Miranda Trasformazioni Tessili Srl",
    "wof:placetype":"venue"
},
  "geometry": {"coordinates":[8.05827,45.562836],"type":"Point"}
}