{
  "type": "Feature",
  "properties": {
    "addr:full":"03011 Alatri Alatri Frosinone 03011",
    "addr:postcode":"03011;03011",
    "iso:country":"IT",
    "sg:address":"03011 Alatri",
    "sg:city":"Alatri",
    "sg:orig_category":"Forniture Alberghi, Bar, Ristoranti E Comunita'",
    "sg:phone":"+39 0775 459650",
    "sg:postcode":"03011",
    "sg:province":"Frosinone",
    "wof:name":"Deymont Sas Di D. Montori & Co.",
    "wof:placetype":"venue"
},
  "geometry": {"coordinates":[13.3409566879,41.6657142639],"type":"Point"}
}