{
  "type": "Feature",
  "properties": {
    "addr:full":"13048 Santhi\u00e0 Vercelli 13048",
    "addr:postcode":"13048;13048",
    "iso:country":"IT",
    "sg:address":"13048 Santhi\u00e0",
    "sg:orig_category":"Servizi E Lavori Per Arredamento E Industria Del Legno",
    "sg:phone":"+39 0161 931015",
    "sg:postcode":"13048",
    "sg:province":"Vercelli",
    "wof:name":"Mod Sas",
    "wof:placetype":"venue"
},
  "geometry": {"coordinates":[8.200011,45.372536],"type":"Point"}
}