{
  "type": "Feature",
  "properties": {
    "iso:country":"IT",
    "sg:address":"Pza Spallanzani 12 42019 Scandiano",
    "sg:classifiers":[
        {
            "category":"Professional",
            "subcategory":"Business Services",
            "type":"Services"
        }
    ],
    "sg:phone":"+39 0522 851151",
    "sg:postcode":"42019",
    "sg:province":"Reggio Nell'Emilia",
    "sg:tags":[
        "agency",
        "export"
    ],
    "sg:website":"www.italfarm.com",
    "wof:name":"Italfarm Srl",
    "wof:placetype":"venue"
},
  "geometry": {"coordinates":[10.686519,44.600239],"type":"Point"}
}