{
  "type": "Feature",
  "properties": {
    "addr:full":"16016 Cogoleto Cogoleto Genova 16016",
    "addr:postcode":"16016;16016",
    "iso:country":"IT",
    "sg:address":"16016 Cogoleto",
    "sg:city":"Cogoleto",
    "sg:classifiers":[
        {
            "category":"Health Services",
            "subcategory":"Hospital",
            "type":"Services"
        }
    ],
    "sg:phone":"+39 010 918 8702",
    "sg:postcode":"16016",
    "sg:province":"Genova",
    "sg:tags":[
        "equipment",
        "systems",
        "supply"
    ],
    "wof:name":"Gi Esse Technology Srl",
    "wof:placetype":"venue"
},
  "geometry": {"coordinates":[8.626456,44.4007],"type":"Point"}
}