{
  "type": "Feature",
  "properties": {
    "iso:country":"IT",
    "sg:address":"50121 Firenze",
    "sg:city":"Firenze",
    "sg:orig_category":"Lavorazioni Metalli, Stampaggio E Saldatura",
    "sg:phone":"+39 055 667356",
    "sg:postcode":"50121",
    "sg:province":"Firenze",
    "wof:name":"Capanni Massimo",
    "wof:placetype":"venue"
},
  "geometry": {"coordinates":[11.274709,43.76796],"type":"Point"}
}