{
  "type": "Feature",
  "properties": {
    "iso:country":"IT",
    "sg:address":"11, Via Sondrio 20053 Muggio'",
    "sg:classifiers":[
        {
            "category":"Farming",
            "subcategory":"Livestock Farm",
            "type":"Manufacturing & Wholesale Goods"
        }
    ],
    "sg:phone":"+39 39039743111",
    "sg:postcode":"20053",
    "sg:province":"Milano",
    "sg:tags":[
        "agriculture"
    ],
    "wof:name":"Massironi Carni S.r.l.",
    "wof:placetype":"venue"
},
  "geometry": {"coordinates":[9.193697,45.570457],"type":"Point"}
}