{
  "type": "Feature",
  "properties": {
    "addr:full":"49, V. Maggior Piovesana 31015 Conegliano Conegliano Treviso 31015",
    "addr:housenumber":"49",
    "addr:postcode":"31015;31015",
    "addr:street":"V. Maggior Piovesana",
    "iso:country":"IT",
    "sg:address":"49, V. Maggior Piovesana 31015 Conegliano",
    "sg:city":"Conegliano",
    "sg:classifiers":[
        {
            "category":"Autos & Motor Vehicles",
            "subcategory":"Boat Sales",
            "type":"Retail Goods"
        }
    ],
    "sg:phone":"+39 0438 410786",
    "sg:postcode":"31015",
    "sg:province":"Treviso",
    "sg:website":"http://www.inoxking.it",
    "wof:name":"Inoxking Srl",
    "wof:placetype":"venue"
},
  "geometry": {"coordinates":[12.242072,45.666286],"type":"Point"}
}