{
  "type": "Feature",
  "properties": {
    "iso:country":"IT",
    "sg:address":"35, Via Di Pescaiola-badia Al Pino 52040 Civitella In Val Di Chiana",
    "sg:classifiers":[
        {
            "category":"Manufacturing",
            "subcategory":"Metals",
            "type":"Manufacturing & Wholesale Goods"
        }
    ],
    "sg:phone":"+39 0575 410202",
    "sg:province":"AR",
    "sg:tags":[
        "metallurgy",
        "metalworking"
    ],
    "wof:name":"I.g.a.r S.r.l",
    "wof:placetype":"venue"
},
  "geometry": {"coordinates":[11.7692098618,43.4140281677],"type":"Point"}
}