{
  "type": "Feature",
  "properties": {
    "iso:country":"IT",
    "sg:address":"Via Gugl.marconi 22; Viterbo; 01100",
    "sg:city":"Viterbo",
    "sg:classifiers":[
        {
            "category":"Banks & Credit Unions",
            "subcategory":"Bank",
            "type":"Services"
        }
    ],
    "sg:phone":"+39 0761 225356",
    "sg:postcode":"01100",
    "sg:province":"Viterbo",
    "wof:name":"Banco Di Santo Spirito",
    "wof:placetype":"venue"
},
  "geometry": {"coordinates":[12.048979,42.441536],"type":"Point"}
}