{
  "type": "Feature",
  "properties": {
    "iso:country":"IT",
    "sg:address":"25128 Brescia",
    "sg:city":"Brescia",
    "sg:classifiers":[
        {
            "category":"Structure",
            "subcategory":"Factory",
            "type":"Public Place"
        }
    ],
    "sg:phone":"+39 030 39921",
    "sg:postcode":"25128",
    "sg:province":"Brescia",
    "sg:tags":[
        "steelworks",
        "foundry"
    ],
    "sg:website":"http://www.lucchini.it",
    "wof:name":"Lucchini Spa",
    "wof:placetype":"venue"
},
  "geometry": {"coordinates":[10.220082,45.557796],"type":"Point"}
}