{
  "type": "Feature",
  "properties": {
    "iso:country":"IT",
    "sg:address":"48018 Faenza",
    "sg:city":"Faenza",
    "sg:orig_category":"Forniture Per Agricoltura E Zootecnia. Animali Domestici",
    "sg:phone":"+39 0546 661552",
    "sg:postcode":"48018",
    "sg:province":"Ravenna",
    "wof:name":"Briciole Di Natura Di Lusa Ivonne E C. Snc",
    "wof:placetype":"venue"
},
  "geometry": {"coordinates":[12.0344762802,44.3705558777],"type":"Point"}
}