{
  "type": "Feature",
  "properties": {
    "iso:country":"IT",
    "sg:address":"21017 Samarate",
    "sg:city":"Samarate",
    "sg:orig_category":"Prodotti E Manufatti In Materie Plastiche",
    "sg:phone":"+39 0331 234365",
    "sg:postcode":"21017",
    "sg:province":"Varese",
    "wof:name":"Team Plast (s.r.l.)",
    "wof:placetype":"venue"
},
  "geometry": {"coordinates":[8.7786455154,45.619884491],"type":"Point"}
}