{
  "type": "Feature",
  "properties": {
    "iso:country":"IT",
    "sg:address":"14035 Grazzano Badoglio",
    "sg:city":"Grazzano Badoglio",
    "sg:classifiers":[
        {
            "category":"Education",
            "subcategory":"School",
            "type":"Public Place"
        }
    ],
    "sg:phone":"+39 0141 925498",
    "sg:postcode":"14035",
    "sg:province":"Asti",
    "sg:tags":[
        "small",
        "breeding",
        "livestock",
        "animal",
        "fishing"
    ],
    "wof:name":"Circolo Ippico 'santa Vittoria'",
    "wof:placetype":"venue"
},
  "geometry": {"coordinates":[8.313027,45.039055],"type":"Point"}
}