{
  "type": "Feature",
  "properties": {
    "iso:country":"IT",
    "sg:address":"24, Via Del Roseto 50012 Bagno A Ripoli",
    "sg:city":"Bagno a Ripoli",
    "sg:classifiers":[
        {
            "category":"Manufacturing",
            "subcategory":"Wood Products",
            "type":"Manufacturing & Wholesale Goods"
        }
    ],
    "sg:phone":"+39 39055696126",
    "sg:postcode":"50012",
    "sg:province":"Firenze",
    "sg:tags":[
        "furniture"
    ],
    "wof:name":"Gmg S.r.l",
    "wof:placetype":"venue"
},
  "geometry": {"coordinates":[11.363304,43.775845],"type":"Point"}
}