{
  "type": "Feature",
  "properties": {
    "addr:full":"84015 Nocera Superiore Nocera Superiore Salerno 84015",
    "addr:postcode":"84015;84015",
    "iso:country":"IT",
    "sg:address":"84015 Nocera Superiore",
    "sg:city":"Nocera Superiore",
    "sg:orig_category":"Elettrotecnica Industriale, Prodotti E Apparecchiature",
    "sg:phone":"+39 081 514 5452",
    "sg:postcode":"84015",
    "sg:province":"Salerno",
    "sg:website":"http://www.coindel.it",
    "wof:name":"Coindel Srl",
    "wof:placetype":"venue"
},
  "geometry": {"coordinates":[14.676273,40.73407],"type":"Point"}
}