{
  "type": "Feature",
  "properties": {
    "iso:country":"IT",
    "sg:address":"Via Orfanotrofio 26 13900 Biella",
    "sg:city":"Biella",
    "sg:classifiers":[
        {
            "category":"Manufacturing",
            "subcategory":"Tools & Machinery",
            "type":"Manufacturing & Wholesale Goods"
        }
    ],
    "sg:phone":"+39 015 28667",
    "sg:postcode":"13900",
    "sg:province":"Biella",
    "sg:tags":[
        "tannery"
    ],
    "sg:website":"www.soraco.it",
    "wof:name":"Soraco S.r.l.",
    "wof:placetype":"venue"
},
  "geometry": {"coordinates":[8.057653,45.568775],"type":"Point"}
}