{
  "type": "Feature",
  "properties": {
    "iso:country":"IT",
    "sg:address":"80125 Napoli",
    "sg:city":"Napoli",
    "sg:classifiers":[
        {
            "category":"Sports & Exercise",
            "subcategory":"Tennis Court",
            "type":"Entertainment"
        }
    ],
    "sg:phone":"+39 081 239 7579",
    "sg:postcode":"80125",
    "sg:province":"Napoli",
    "sg:tags":[
        "e",
        "lo",
        "tempo",
        "libero",
        "per",
        "impianti",
        "il",
        "attrezzature"
    ],
    "wof:name":"O.s.a.i. Organizzazioni Spettacoli Attrazioni Internazionali",
    "wof:placetype":"venue"
},
  "geometry": {"coordinates":[14.143929,40.88699],"type":"Point"}
}