{
  "type": "Feature",
  "properties": {
    "iso:country":"IT",
    "sg:address":"Via Papa Giovanni Xxiii 47 20090 Rodano",
    "sg:city":"Rodano",
    "sg:classifiers":[
        {
            "category":"Manufacturing",
            "subcategory":"Tools & Machinery",
            "type":"Manufacturing & Wholesale Goods"
        }
    ],
    "sg:phone":"+39 02 9532 1326",
    "sg:postcode":"20090",
    "sg:province":"Milano",
    "sg:tags":[
        "hydraulic"
    ],
    "sg:website":"www.ridgid.com",
    "wof:name":"Ridgid Italia Srl",
    "wof:placetype":"venue"
},
  "geometry": {"coordinates":[9.311447,45.429554],"type":"Point"}
}