{
  "type": "Feature",
  "properties": {
    "iso:country":"IT",
    "sg:address":"00013 Mentana",
    "sg:city":"Mentana",
    "sg:orig_category":"Tessuti E Stoffe - Produzione E Ingrosso",
    "sg:phone":"+39 06 905 1055",
    "sg:postcode":"00013",
    "sg:province":"Roma",
    "wof:name":"Fabel Piu' Srl",
    "wof:placetype":"venue"
},
  "geometry": {"coordinates":[12.643934,42.016117],"type":"Point"}
}