{
  "type": "Feature",
  "properties": {
    "iso:country":"IT",
    "sg:address":"Via Verdi 10; Basiliano; 33031",
    "sg:city":"Basiliano",
    "sg:classifiers":[
        {
            "category":"Banks & Credit Unions",
            "subcategory":"Bank",
            "type":"Services"
        }
    ],
    "sg:phone":"+39 0432 830482",
    "sg:postcode":"33031",
    "sg:province":"Udine",
    "wof:name":"Rolo Banca 1473 Spa",
    "wof:placetype":"venue"
},
  "geometry": {"coordinates":[13.103724,46.014145],"type":"Point"}
}