{
  "type": "Feature",
  "properties": {
    "addr:full":"Via Forum Julii 46/48; Corno Di Rosazzo; 33040 Corno di Rosazzo Udine 33040",
    "addr:housenumber":"46 / 48",
    "addr:postcode":"33040;33040",
    "addr:street":"Via Forum Julii",
    "iso:country":"IT",
    "sg:address":"Via Forum Julii 46/48; Corno Di Rosazzo; 33040",
    "sg:city":"Corno di Rosazzo",
    "sg:classifiers":[
        {
            "category":"Banks & Credit Unions",
            "subcategory":"Bank",
            "type":"Services"
        }
    ],
    "sg:phone":"+39 0432 775 9924",
    "sg:postcode":"33040",
    "sg:province":"Udine",
    "wof:name":"Cassa Rurale Ed Artigiano, Di Manzano",
    "wof:placetype":"venue"
},
  "geometry": {"coordinates":[13.440575,45.998833],"type":"Point"}
}