{
  "type": "Feature",
  "properties": {
    "iso:country":"IT",
    "sg:address":"40138 Bologna",
    "sg:city":"Bologna",
    "sg:orig_category":"Imprese Pulizia",
    "sg:phone":"+39 051 601 6111",
    "sg:postcode":"40138",
    "sg:province":"Bologna",
    "sg:website":"http://www.gambaservice.com",
    "wof:name":"Gamba Service Spa",
    "wof:placetype":"venue"
},
  "geometry": {"coordinates":[11.399348,44.496525],"type":"Point"}
}