{
  "type": "Feature",
  "properties": {
    "addr:full":"64023 Mosciano Sant'angelo Teramo 64023",
    "addr:postcode":"64023;64023",
    "iso:country":"IT",
    "sg:address":"64023 Mosciano Sant'angelo",
    "sg:orig_category":"Prodotti Chimici Secondari. Macchine E Forniture Per Ecologia E Smaltimento Rifiuti. Forniture Per Attivita' Industriali",
    "sg:phone":"+39 085 807 1395",
    "sg:postcode":"64023",
    "sg:province":"Teramo",
    "wof:name":"Battestini Pietro Snc Di Battestini Marco & C.",
    "wof:placetype":"venue"
},
  "geometry": {"coordinates":[13.9063262939,42.7257995605],"type":"Point"}
}