{
  "type": "Feature",
  "properties": {
    "addr:full":"00183 Roma Roma Roma 00183",
    "addr:postcode":"00183;00183",
    "iso:country":"IT",
    "sg:address":"00183 Roma",
    "sg:city":"Roma",
    "sg:orig_category":"Imprese Di Costruzioni Civili Ed Industriali. Servizi Ausiliari Di Sorveglianza, Manutenzione E Pulizia",
    "sg:phone":"+39 06 7045 4779",
    "sg:postcode":"00183",
    "sg:province":"Roma",
    "sg:website":"http://artigiana3.d.com",
    "wof:name":"D'antonio Enzo",
    "wof:placetype":"venue"
},
  "geometry": {"coordinates":[12.233334,41.799999],"type":"Point"}
}