{
  "type": "Feature",
  "properties": {
    "iso:country":"IT",
    "sg:address":"10144 Torino",
    "sg:city":"Torino",
    "sg:orig_category":"Lavorazioni Meccaniche E Servizi. Riparazione Dei Mezzi Di Trasporto",
    "sg:phone":"+39 011 480194",
    "sg:postcode":"10144",
    "sg:province":"Torino",
    "wof:name":"Bucci F.lli Di Bucci Vincenzo & C. S.n.c.",
    "wof:placetype":"venue"
},
  "geometry": {"coordinates":[7.653499,45.38932],"type":"Point"}
}