{
  "type": "Feature",
  "properties": {
    "addr:full":"24066 Pedrengo Pedrengo Bergamo 24066",
    "addr:postcode":"24066;24066",
    "iso:country":"IT",
    "sg:address":"24066 Pedrengo",
    "sg:city":"Pedrengo",
    "sg:orig_category":"Non-classified Establishments",
    "sg:phone":"+39 035 655271",
    "sg:postcode":"24066",
    "sg:province":"Bergamo",
    "wof:name":"Carta Orobica Poloni Srl",
    "wof:placetype":"venue"
},
  "geometry": {"coordinates":[9.740199,45.699924],"type":"Point"}
}