{
  "type": "Feature",
  "properties": {
    "iso:country":"IT",
    "sg:address":"Km. 6, V. Provinciale - Loc. Botriolo 52020 Castelfranco Di Sopra",
    "sg:city":"Castelfranco di Sopra",
    "sg:classifiers":[
        {
            "category":"Real Estate",
            "subcategory":"Surveying",
            "type":"Services"
        }
    ],
    "sg:phone":"+39 055 914 9357",
    "sg:postcode":"52020",
    "sg:province":"Arezzo",
    "sg:tags":[
        "equipment",
        "material",
        "good",
        "-",
        "handling"
    ],
    "sg:website":"http://www.zetolink.com:ws_end: :mark:ws:http://www.paginegialle.it/thermindus",
    "wof:name":"Zetolink Srl",
    "wof:placetype":"venue"
},
  "geometry": {"coordinates":[11.863062,43.471203],"type":"Point"}
}