{
  "type": "Feature",
  "properties": {
    "iso:country":"IT",
    "sg:address":"10/a, Viale Milano Fiori 20090 Assago",
    "sg:city":"Assago",
    "sg:classifiers":[
        {
            "category":"Communications",
            "subcategory":"Television Station",
            "type":"Services"
        }
    ],
    "sg:phone":"+39 39025778951",
    "sg:postcode":"20090",
    "sg:province":"Milano",
    "sg:tags":[
        "electronic",
        "publishing"
    ],
    "wof:name":"Opera Multimedia Spa",
    "wof:placetype":"venue"
},
  "geometry": {"coordinates":[9.148091,45.403061],"type":"Point"}
}