{
  "type": "Feature",
  "properties": {
    "addr:full":"20146 Milano Milano Milano 20146",
    "addr:postcode":"20146;20146",
    "iso:country":"IT",
    "sg:address":"20146 Milano",
    "sg:city":"Milano",
    "sg:classifiers":[
        {
            "category":"Professional",
            "subcategory":"Advertising",
            "type":"Services"
        }
    ],
    "sg:phone":"+39 02 403 5943",
    "sg:postcode":"20146",
    "sg:province":"Milano",
    "sg:tags":[
        "marketing",
        "communication"
    ],
    "wof:name":"Interstand Service Srl",
    "wof:placetype":"venue"
},
  "geometry": {"coordinates":[9.142751,45.462116],"type":"Point"}
}