{
  "type": "Feature",
  "properties": {
    "addr:full":"20, Via Alessandro Volta 33080 Prata Di Pordenone Prata di Pordenone Pordenone 33080",
    "addr:postcode":"33080;33080",
    "addr:street":"Via Alessandro Volta",
    "iso:country":"IT",
    "sg:address":"20, Via Alessandro Volta 33080 Prata Di Pordenone",
    "sg:city":"Prata di Pordenone",
    "sg:classifiers":[
        {
            "category":"Home & Garden",
            "subcategory":"Home Furnishings",
            "type":"Retail Goods"
        }
    ],
    "sg:phone":"+39 0434 601411",
    "sg:postcode":"33080",
    "sg:province":"Pordenone",
    "sg:tags":[
        "household"
    ],
    "wof:name":"Armobil S.p.a.",
    "wof:placetype":"venue"
},
  "geometry": {"coordinates":[12.584301,45.883583],"type":"Point"}
}