{
  "type": "Feature",
  "properties": {
    "iso:country":"IT",
    "sg:address":"78, Viale Della Liberta' 33170 Pordenone",
    "sg:city":"Pordenone",
    "sg:classifiers":[
        {
            "category":"Professional",
            "subcategory":"Engineering",
            "type":"Services"
        }
    ],
    "sg:phone":"+39 0434 541117",
    "sg:postcode":"33170",
    "sg:province":"Pordenone",
    "sg:tags":[
        "machine",
        "-",
        "mechanical"
    ],
    "wof:name":"L'assistente (s.r.l.)",
    "wof:placetype":"venue"
},
  "geometry": {"coordinates":[12.596484,45.891243],"type":"Point"}
}