{
  "type": "Feature",
  "properties": {
    "addr:full":"30021 Caorle Caorle Venezia 30021",
    "addr:postcode":"30021;30021",
    "iso:country":"IT",
    "sg:address":"30021 Caorle",
    "sg:city":"Caorle",
    "sg:orig_category":"Servizi Ausiliari Dei Mezzi Di Trasporto. Servizi Ausiliari Per Il Trasporto. Acqua, Luce, Gas E Societa' Di Esercizio Pubblico",
    "sg:phone":"+39 0421 260469",
    "sg:postcode":"30021",
    "sg:province":"Venezia",
    "sg:website":"http://www.marina4.com",
    "wof:name":"Marina 4 Spa",
    "wof:placetype":"venue"
},
  "geometry": {"coordinates":[12.853712,45.587742],"type":"Point"}
}