{
  "type": "Feature",
  "properties": {
    "iso:country":"IT",
    "sg:address":"92010 Siculiana",
    "sg:city":"Siculiana",
    "sg:orig_category":"Guarnizioni Industriali",
    "sg:phone":"+39 0922 815660",
    "sg:postcode":"92010",
    "sg:province":"Agrigento",
    "wof:name":"Manzella Maurizio",
    "wof:placetype":"venue"
},
  "geometry": {"coordinates":[13.426701,37.3354],"type":"Point"}
}