{
  "type": "Feature",
  "properties": {
    "addr:full":"101, Via Como 23883 Brivio Brivio Lecco 23883",
    "addr:housenumber":"101",
    "addr:postcode":"23883;23883",
    "addr:street":"Via Como",
    "iso:country":"IT",
    "sg:address":"101, Via Como 23883 Brivio",
    "sg:city":"Brivio",
    "sg:classifiers":[
        {
            "category":"Parking",
            "subcategory":"Lot",
            "type":"Transportation"
        }
    ],
    "sg:phone":"+39 039 532 0380",
    "sg:postcode":"23883",
    "sg:province":"Lecco",
    "sg:tags":[
        "transport",
        "road"
    ],
    "wof:name":"Blue Eagle Srl",
    "wof:placetype":"venue"
},
  "geometry": {"coordinates":[9.419081,45.73476],"type":"Point"}
}