{
  "type": "Feature",
  "properties": {
    "iso:country":"IT",
    "sg:address":"37010 Cavaion Veronese",
    "sg:city":"Cavaion Veronese",
    "sg:orig_category":"Marmo Ed Affini - Commercio",
    "sg:phone":"+39 045 626 9433",
    "sg:postcode":"37010",
    "sg:province":"Verona",
    "sg:website":"http://www.marmidolomiti.it",
    "wof:name":"Marmi Dolomiti Sas Di Gastaldelli Guerrino & C.",
    "wof:placetype":"venue"
},
  "geometry": {"coordinates":[10.769303,45.539875],"type":"Point"}
}