{
  "type": "Feature",
  "properties": {
    "addr:full":"6, Via Edolo 20125 Milano Milano Milano 20125",
    "addr:postcode":"20125;20125",
    "addr:street":"Via Edolo",
    "iso:country":"IT",
    "sg:address":"6, Via Edolo 20125 Milano",
    "sg:city":"Milano",
    "sg:classifiers":[
        {
            "category":"Personal",
            "subcategory":"Shoe Repair & Shine",
            "type":"Services"
        }
    ],
    "sg:phone":"+39 39026709432",
    "sg:postcode":"20125",
    "sg:province":"Milano",
    "sg:tags":[
        "leather"
    ],
    "wof:name":"Caribbean Art Promotion Sas",
    "wof:placetype":"venue"
},
  "geometry": {"coordinates":[9.206056,45.491531],"type":"Point"}
}