{
  "type": "Feature",
  "properties": {
    "iso:country":"IT",
    "sg:address":"Via Adamoli Gelasio 241/e 16138 Genova",
    "sg:city":"Genova",
    "sg:classifiers":[
        {
            "category":"Coffee & Tea",
            "type":"Food & Drink"
        }
    ],
    "sg:phone":"+39 010 835 6944",
    "sg:postcode":"16138",
    "sg:province":"Genova",
    "sg:tags":[
        "roasted"
    ],
    "sg:website":"www.covimcaffe.it",
    "wof:name":"Covim Spa",
    "wof:placetype":"venue"
},
  "geometry": {"coordinates":[8.933989,44.407063],"type":"Point"}
}