{
  "type": "Feature",
  "properties": {
    "iso:country":"IT",
    "sg:address":"50034 Marradi",
    "sg:city":"Marradi",
    "sg:orig_category":"Macchine, Impianti E Forniture Per Industria Grafica, Cartaria E Cartotecnica. Automazione E Macchine Per Ufficio",
    "sg:phone":"+39 055 804 4323",
    "sg:postcode":"50034",
    "sg:province":"Firenze",
    "sg:website":"http://www.praticompany.it",
    "wof:name":"Prati",
    "wof:placetype":"venue"
},
  "geometry": {"coordinates":[11.638533,44.049282],"type":"Point"}
}