{
  "type": "Feature",
  "properties": {
    "addr:full":"12, Via Verrazzano 43010 Roccabianca Roccabianca Parma 43010",
    "addr:postcode":"43010;43010",
    "addr:street":"Via Verrazzano",
    "iso:country":"IT",
    "sg:address":"12, Via Verrazzano 43010 Roccabianca",
    "sg:city":"Roccabianca",
    "sg:classifiers":[
        {
            "category":"Manufacturing",
            "subcategory":"Rubber & Plastics",
            "type":"Manufacturing & Wholesale Goods"
        }
    ],
    "sg:phone":"+39 0521 876430",
    "sg:postcode":"43010",
    "sg:province":"Parma",
    "wof:name":"Plafond Plast (s.n.c.)",
    "wof:placetype":"venue"
},
  "geometry": {"coordinates":[10.2254362106,45.0072135925],"type":"Point"}
}