{
  "type": "Feature",
  "properties": {
    "iso:country":"IT",
    "sg:address":"1120, Via Stanzano 40024 Castel San Pietro Terme",
    "sg:city":"Castel San Pietro Terme",
    "sg:classifiers":[
        {
            "category":"Food & Beverages",
            "subcategory":"Groceries & Convenience Stores",
            "type":"Retail Goods"
        }
    ],
    "sg:phone":"+39 39051941001",
    "sg:postcode":"40024",
    "sg:province":"Bologna",
    "sg:tags":[
        "drink"
    ],
    "wof:name":"Cesari (s.r.l.)",
    "wof:placetype":"venue"
},
  "geometry": {"coordinates":[11.556021,44.404667],"type":"Point"}
}