{
  "type": "Feature",
  "properties": {
    "addr:full":"00040 Rocca Di Papa Rocca di Papa Roma 00040",
    "addr:postcode":"00040;00040",
    "iso:country":"IT",
    "sg:address":"00040 Rocca Di Papa",
    "sg:city":"Rocca di Papa",
    "sg:orig_category":"Servizi Ausiliari Di Analisi, Controllo E Ricerca. Acqua, Luce, Gas E Societa' Di Esercizio Pubblico",
    "sg:phone":"+39 06 9443 6469",
    "sg:postcode":"00040",
    "sg:province":"Roma",
    "wof:name":"Associazione Tuscolana Di Astronomia",
    "wof:placetype":"venue"
},
  "geometry": {"coordinates":[12.50686,41.650593],"type":"Point"}
}