{
  "type": "Feature",
  "properties": {
    "addr:full":"20020 Lainate Lainate Milano 20020",
    "addr:postcode":"20020;20020",
    "iso:country":"IT",
    "sg:address":"20020 Lainate",
    "sg:city":"Lainate",
    "sg:orig_category":"Servizi E Lavori Per Edilizia E Lavori Pubblici. Acqua, Luce, Gas E Societa' Di Esercizio Pubblico",
    "sg:phone":"+39 02 9379 6627",
    "sg:postcode":"20020",
    "sg:province":"Milano",
    "wof:name":"Euroenergy Group Srl - Gia' Marcegaglia Consulting Srl-",
    "wof:placetype":"venue"
},
  "geometry": {"coordinates":[9.17673,45.456135],"type":"Point"}
}