{
  "type": "Feature",
  "properties": {
    "iso:country":"IT",
    "sg:address":"40121 Bologna",
    "sg:city":"Bologna",
    "sg:orig_category":"Ospedali E Servizi Sanitari. Servizi Sociali",
    "sg:phone":"+39 051 296 0437",
    "sg:postcode":"40121",
    "sg:province":"Bologna",
    "wof:name":"Auxilia",
    "wof:placetype":"venue"
},
  "geometry": {"coordinates":[11.339943,44.495316],"type":"Point"}
}