{
  "type": "Feature",
  "properties": {
    "iso:country":"IT",
    "sg:address":"83, Via Rosa Gabriele 25121 Brescia",
    "sg:city":"Brescia",
    "sg:classifiers":[
        {
            "category":"Real Estate",
            "subcategory":"Architect",
            "type":"Services"
        }
    ],
    "sg:phone":"+39 390 304 7407",
    "sg:postcode":"25121",
    "sg:province":"Brescia",
    "sg:tags":[
        "textile",
        "clothing"
    ],
    "wof:name":"Dimensione (s.r.l.)",
    "wof:placetype":"venue"
},
  "geometry": {"coordinates":[10.222958,45.539829],"type":"Point"}
}