{
  "type": "Feature",
  "properties": {
    "iso:country":"IT",
    "sg:address":"50065 Pontassieve",
    "sg:city":"Pontassieve",
    "sg:classifiers":[
        {
            "category":"Home & Garden",
            "subcategory":"Building Materials",
            "type":"Retail Goods"
        }
    ],
    "sg:phone":"+39 347 612 9075",
    "sg:postcode":"50065",
    "sg:province":"Firenze",
    "sg:tags":[
        "gas",
        "caldaie"
    ],
    "wof:name":"Ditta Edile C & G Di Palmieri Giovanni",
    "wof:placetype":"venue"
},
  "geometry": {"coordinates":[11.411205,43.846481],"type":"Point"}
}