{
  "type": "Feature",
  "properties": {
    "iso:country":"IT",
    "sg:address":"56017 S. Giuliano Terme",
    "sg:orig_category":"Musei E Pinacoteche",
    "sg:phone":"+39 050 850028",
    "sg:postcode":"56017",
    "sg:province":"Pisa",
    "wof:name":"Camici Roncioni Francesco",
    "wof:placetype":"venue"
},
  "geometry": {"coordinates":[10.4358310699,43.7701148987],"type":"Point"}
}