{
  "type": "Feature",
  "properties": {
    "iso:country":"IT",
    "sg:address":"3, Via F.lli Rosselli 28014 Maggiora",
    "sg:city":"Maggiora",
    "sg:classifiers":[
        {
            "category":"Manufacturing",
            "subcategory":"Metals",
            "type":"Manufacturing & Wholesale Goods"
        }
    ],
    "sg:phone":"+39 39032287190",
    "sg:postcode":"28014",
    "sg:province":"Novara",
    "sg:tags":[
        "metallurgy",
        "metalworking"
    ],
    "wof:name":"Zanetta Cav. Giovanni (s.r.l.)",
    "wof:placetype":"venue"
},
  "geometry": {"coordinates":[8.6186714172,45.4450836182],"type":"Point"}
}