{
  "type": "Feature",
  "properties": {
    "iso:country":"IT",
    "sg:address":"7, Viale A. Moro 26017 Trescore Cremasco",
    "sg:city":"Trescore Cremasco",
    "sg:classifiers":[
        {
            "category":"Food & Beverages",
            "subcategory":"Groceries & Convenience Stores",
            "type":"Retail Goods"
        }
    ],
    "sg:phone":"+39 0373 273052",
    "sg:postcode":"26017",
    "sg:province":"Cremona",
    "sg:tags":[
        "product",
        "related"
    ],
    "wof:name":"Salumificio Cagnana (s.p.a.)",
    "wof:placetype":"venue"
},
  "geometry": {"coordinates":[10.0261354446,45.1334991455],"type":"Point"}
}