{
  "type": "Feature",
  "properties": {
    "iso:country":"IT",
    "sg:address":"43036 Fidenza",
    "sg:city":"Fidenza",
    "sg:orig_category":"Macchine, Impianti Ed Attrezzature Per Industria Alimentare E Bevande",
    "sg:phone":"+39 0524 528688",
    "sg:postcode":"43036",
    "sg:province":"Parma",
    "sg:website":"http://www.laparmigiana.com",
    "wof:name":"La Parmigiana Srl",
    "wof:placetype":"venue"
},
  "geometry": {"coordinates":[10.410019,44.950798],"type":"Point"}
}