{
  "type": "Feature",
  "properties": {
    "iso:country":"IT",
    "sg:address":"Via Papa Giovanni Xxiii; Leffe",
    "sg:classifiers":[
        {
            "category":"Banks & Credit Unions",
            "subcategory":"Bank",
            "type":"Services"
        }
    ],
    "sg:phone":"+39 035 733343",
    "wof:name":"Banca Popolare Di Cremona Scarl",
    "wof:placetype":"venue"
},
  "geometry": {"coordinates":[9.885415,45.798935],"type":"Point"}
}