{
  "type": "Feature",
  "properties": {
    "addr:full":"Via Del Mosso 13894 Gaglianico Gaglianico Biella 13894",
    "addr:postcode":"13894;13894",
    "addr:street":"Via Del Mosso",
    "iso:country":"IT",
    "sg:address":"Via Del Mosso 13894 Gaglianico",
    "sg:city":"Gaglianico",
    "sg:classifiers":[
        {
            "category":"Shopping",
            "subcategory":"Crafts & Fabrics",
            "type":"Retail Goods"
        }
    ],
    "sg:phone":"+39 015 254 3920",
    "sg:postcode":"13894",
    "sg:province":"Biella",
    "wof:name":"Pelle Elisabetta & C. (s.n.c.)",
    "wof:placetype":"venue"
},
  "geometry": {"coordinates":[8.0879220963,45.5340881348],"type":"Point"}
}