{
  "type": "Feature",
  "properties": {
    "addr:full":"24, Via Dell'orto Ferruccio 24126 Bergamo Bergamo Bergamo 24126",
    "addr:postcode":"24126;24126",
    "addr:street":"Via Dell'Orto Ferruccio",
    "iso:country":"IT",
    "sg:address":"24, Via Dell'orto Ferruccio 24126 Bergamo",
    "sg:city":"Bergamo",
    "sg:classifiers":[
        {
            "category":"Shopping",
            "subcategory":"Computers & Home Electronics",
            "type":"Retail Goods"
        }
    ],
    "sg:phone":"+39 39035316418",
    "sg:postcode":"24126",
    "sg:province":"Bergamo",
    "sg:tags":[
        "electronic",
        "electrical",
        "equipment"
    ],
    "wof:name":"Euro - Cab Italia (s.a.s.)",
    "wof:placetype":"venue"
},
  "geometry": {"coordinates":[9.669952,45.694904],"type":"Point"}
}