{
  "type": "Feature",
  "properties": {
    "iso:country":"IT",
    "sg:address":"Via Vittorio Alfieri 7 35013 Cittadella",
    "sg:city":"Cittadella",
    "sg:classifiers":[
        {
            "category":"Professional",
            "subcategory":"Advertising",
            "type":"Services"
        }
    ],
    "sg:phone":"+39 049 940 1020",
    "sg:postcode":"35013",
    "sg:province":"Padova",
    "sg:tags":[
        "article",
        "paper"
    ],
    "wof:name":"Artegrafica Sociale Snc",
    "wof:placetype":"venue"
},
  "geometry": {"coordinates":[11.778072,45.647842],"type":"Point"}
}