{
  "type": "Feature",
  "properties": {
    "iso:country":"IT",
    "sg:address":"50142 Firenze",
    "sg:city":"Firenze",
    "sg:orig_category":"Trasporti E Spedizioni Merci",
    "sg:phone":"+39 055 716841",
    "sg:postcode":"50142",
    "sg:province":"Firenze",
    "sg:website":"http://www.transvogue.it",
    "wof:name":"Transvogue Service Srl",
    "wof:placetype":"venue"
},
  "geometry": {"coordinates":[11.190053,43.778824],"type":"Point"}
}