{
  "type": "Feature",
  "properties": {
    "addr:full":"Via Gaggia Pietro 1/a 20139 Milano Milano Milano 20139",
    "addr:housenumber":"1 / a",
    "addr:postcode":"20139;20139",
    "addr:street":"Via Gaggia Pietro",
    "iso:country":"IT",
    "sg:address":"Via Gaggia Pietro 1/a 20139 Milano",
    "sg:city":"Milano",
    "sg:classifiers":[
        {
            "category":"Shopping",
            "subcategory":"Jewelry",
            "type":"Retail Goods"
        }
    ],
    "sg:phone":"+39 02 5740 4089",
    "sg:postcode":"20139",
    "sg:province":"Milano",
    "sg:tags":[
        "fashion",
        "jewellery"
    ],
    "wof:name":"Newdel Snc Di Giovanni De Liguoro & C.",
    "wof:placetype":"venue"
},
  "geometry": {"coordinates":[9.2032260895,45.4824676514],"type":"Point"}
}