{
  "type": "Feature",
  "properties": {
    "iso:country":"IT",
    "sg:address":"Piazza Della Cisterna 26; S. Gimigniano; 53037",
    "sg:classifiers":[
        {
            "category":"Banks & Credit Unions",
            "subcategory":"Bank",
            "type":"Services"
        }
    ],
    "sg:phone":"+39 0577 941300",
    "sg:postcode":"53037",
    "sg:province":"Siena",
    "wof:name":"Banca Toscana Spa",
    "wof:placetype":"venue"
},
  "geometry": {"coordinates":[11.043764,43.467316],"type":"Point"}
}