{
  "type": "Feature",
  "properties": {
    "addr:full":"50013 S. Donnino, Campi Bisenzio Campi Bisenzio Firenze 50013",
    "addr:housenumber":"50013",
    "addr:postcode":"50013",
    "addr:street":"S. Donnino;Bisenzio",
    "iso:country":"IT",
    "sg:address":"50013 S. Donnino, Campi Bisenzio",
    "sg:city":"Campi Bisenzio",
    "sg:orig_category":"Arti Grafiche - Impianti E Macchine",
    "sg:phone":"+39 055 896 4097",
    "sg:postcode":"50013",
    "sg:province":"Firenze",
    "sg:website":"http://www.puntoflorence.it",
    "wof:name":"Punto Florence",
    "wof:placetype":"venue"
},
  "geometry": {"coordinates":[11.150303,43.796623],"type":"Point"}
}