{
  "type": "Feature",
  "properties": {
    "addr:full":"59100 Prato Prato Prato 59100",
    "addr:postcode":"59100;59100",
    "iso:country":"IT",
    "sg:address":"59100 Prato",
    "sg:city":"Prato",
    "sg:orig_category":"Musica",
    "sg:phone":"+39 0574 23077",
    "sg:postcode":"59100",
    "sg:province":"Prato",
    "wof:name":"Automat Spiel (s.r.l.)",
    "wof:placetype":"venue"
},
  "geometry": {"coordinates":[11.0917329788,43.8687553406],"type":"Point"}
}