{
  "type": "Feature",
  "properties": {
    "iso:country":"IT",
    "sg:address":"55, Via Miola Cesare 21047 Saronno",
    "sg:city":"Saronno",
    "sg:classifiers":[
        {
            "category":"Professional",
            "subcategory":"Computer Services",
            "type":"Services"
        }
    ],
    "sg:phone":"+39 39800828167",
    "sg:postcode":"21047",
    "sg:province":"Varese",
    "sg:tags":[
        "information",
        "technology"
    ],
    "wof:name":"Eco S.r.l.",
    "wof:placetype":"venue"
},
  "geometry": {"coordinates":[8.826385,45.817604],"type":"Point"}
}