{
  "type": "Feature",
  "properties": {
    "addr:full":"Via Marconi 370; Calusco D'adda; 24033 Bergamo 24033",
    "addr:housenumber":"370",
    "addr:postcode":"24033;24033",
    "addr:street":"Via Marconi",
    "iso:country":"IT",
    "sg:address":"Via Marconi 370; Calusco D'adda; 24033",
    "sg:classifiers":[
        {
            "category":"Banks & Credit Unions",
            "subcategory":"Bank",
            "type":"Services"
        }
    ],
    "sg:phone":"+39 035 791237",
    "sg:postcode":"24033",
    "sg:province":"Bergamo",
    "wof:name":"Istituto Bancario, San Paolo Di Torino Spa",
    "wof:placetype":"venue"
},
  "geometry": {"coordinates":[9.473883,45.690094],"type":"Point"}
}