{
  "type": "Feature",
  "properties": {
    "addr:full":"6, Via Cecconi 50050 Cerreto Guidi Cerreto Guidi Firenze 50050",
    "addr:postcode":"50050;50050",
    "addr:street":"Via Cecconi",
    "iso:country":"IT",
    "sg:address":"6, Via Cecconi 50050 Cerreto Guidi",
    "sg:city":"Cerreto Guidi",
    "sg:classifiers":[
        {
            "category":"Manufacturing",
            "subcategory":"Glass & Minerals",
            "type":"Manufacturing & Wholesale Goods"
        }
    ],
    "sg:phone":"+39 0571 902067",
    "sg:postcode":"50050",
    "sg:province":"Firenze",
    "wof:name":"Nuova Stilvetro Di Riccardo Olivari & F.lli S.n.c.",
    "wof:placetype":"venue"
},
  "geometry": {"coordinates":[11.256902,43.768734],"type":"Point"}
}