{
  "type": "Feature",
  "properties": {
    "addr:full":"10093 Collegno Collegno Torino 10093",
    "addr:postcode":"10093;10093",
    "iso:country":"IT",
    "sg:address":"10093 Collegno",
    "sg:city":"Collegno",
    "sg:orig_category":"Apparecchiature Ed Attrezzature Meccaniche",
    "sg:phone":"+39 011 411 5593",
    "sg:postcode":"10093",
    "sg:province":"Torino",
    "wof:name":"Piscazzi Lavorazioni Meccaniche Srl",
    "wof:placetype":"venue"
},
  "geometry": {"coordinates":[7.591805,45.07375],"type":"Point"}
}