{
  "type": "Feature",
  "properties": {
    "iso:country":"IT",
    "sg:address":"05035 Narni",
    "sg:city":"Narni",
    "sg:orig_category":"Arredamenti - Vendita Al Dettaglio",
    "sg:phone":"+39 0744 744554",
    "sg:postcode":"05035",
    "sg:province":"Terni",
    "wof:name":"Mercatone Dei Fallimenti Di Zanconato Giuseppe",
    "wof:placetype":"venue"
},
  "geometry": {"coordinates":[12.561653,42.534653],"type":"Point"}
}