{
  "type": "Feature",
  "properties": {
    "addr:full":"18035 Isolabona Isolabona Imperia 18035",
    "addr:housenumber":"18035",
    "addr:postcode":"18035",
    "addr:street":"Isolabona Isolabona",
    "iso:country":"IT",
    "sg:address":"18035 Isolabona",
    "sg:city":"Isolabona",
    "sg:classifiers":[
        {
            "category":"Health Services",
            "subcategory":"Health Practitioner",
            "type":"Services"
        }
    ],
    "sg:phone":"+39 0184 208454",
    "sg:postcode":"18035",
    "sg:province":"Imperia",
    "sg:tags":[
        "medici"
    ],
    "wof:name":"Veziano Danilo",
    "wof:placetype":"venue"
},
  "geometry": {"coordinates":[7.9806542397,43.8725852966],"type":"Point"}
}