{
  "type": "Feature",
  "properties": {
    "addr:full":"22078 Turate Turate Como 22078",
    "addr:postcode":"22078;22078",
    "iso:country":"IT",
    "sg:address":"22078 Turate",
    "sg:city":"Turate",
    "sg:orig_category":"Macchine Utensili E Impianti",
    "sg:phone":"+39 02 9648 9012",
    "sg:postcode":"22078",
    "sg:province":"Como",
    "wof:name":"Lovent Italia (s.r.l.)",
    "wof:placetype":"venue"
},
  "geometry": {"coordinates":[9.012857,45.649971],"type":"Point"}
}