{
  "type": "Feature",
  "properties": {
    "iso:country":"IT",
    "sg:address":"23900 Lecco",
    "sg:city":"Lecco",
    "sg:orig_category":"Cromatura E Nichelatura",
    "sg:phone":"+39 0341 363664",
    "sg:postcode":"23900",
    "sg:province":"Lecco",
    "sg:website":"http://web.tiscalinet.it/guarnaroli",
    "wof:name":"Guarnaroli Francesco Di Guarnaroli Renato & C. Snc",
    "wof:placetype":"venue"
},
  "geometry": {"coordinates":[9.404939,45.853374],"type":"Point"}
}