{
  "type": "Feature",
  "properties": {
    "iso:country":"IT",
    "sg:address":"25128 Brescia",
    "sg:city":"Brescia",
    "sg:orig_category":"Apparecchi, Attrezzature E Forniture Per Centri Estetici",
    "sg:phone":"+39 030 293047",
    "sg:postcode":"25128",
    "sg:province":"Brescia",
    "sg:website":"http://www.nuovaeuroestetica.com",
    "wof:name":"Nuova Euroestetica Di Marcello Forgiano & C. Sas",
    "wof:placetype":"venue"
},
  "geometry": {"coordinates":[10.22578,45.544846],"type":"Point"}
}