{
  "type": "Feature",
  "properties": {
    "iso:country":"IT",
    "sg:address":"16, Via Vittorio Veneto 24060 Rogno",
    "sg:city":"Rogno",
    "sg:classifiers":[
        {
            "category":"Shopping",
            "subcategory":"Clothing, Apparel, & Fashions",
            "type":"Retail Goods"
        }
    ],
    "sg:phone":"+39 39035967104",
    "sg:postcode":"24060",
    "sg:province":"Bergamo",
    "sg:tags":[
        "clothes"
    ],
    "wof:name":"Daritex Sport Wear (s.r.l.)",
    "wof:placetype":"venue"
},
  "geometry": {"coordinates":[10.143399,45.862873],"type":"Point"}
}