{
  "type": "Feature",
  "properties": {
    "addr:full":"4, Via Stelvio Regoledo 23013 Cosio Valtellino Cosio Valtellino Sondrio 23013",
    "addr:postcode":"23013;23013",
    "addr:street":"Via Stelvio Regoledo",
    "iso:country":"IT",
    "sg:address":"4, Via Stelvio Regoledo 23013 Cosio Valtellino",
    "sg:city":"Cosio Valtellino",
    "sg:classifiers":[
        {
            "category":"Shopping",
            "subcategory":"Crafts & Fabrics",
            "type":"Retail Goods"
        }
    ],
    "sg:phone":"+39 0342 637066",
    "sg:postcode":"23013",
    "sg:province":"Sondrio",
    "sg:tags":[
        "linen"
    ],
    "wof:name":"Persianfarsh Di Shahroozi Keyvan E Ponti Roberta S.a.s.",
    "wof:placetype":"venue"
},
  "geometry": {"coordinates":[9.5425653458,46.1333618164],"type":"Point"}
}