{
  "type": "Feature",
  "properties": {
    "addr:full":"74100 Taranto Taranto Taranto 74100",
    "addr:postcode":"74100;74100",
    "iso:country":"IT",
    "sg:address":"74100 Taranto",
    "sg:city":"Taranto",
    "sg:orig_category":"Editoria Elettronica E Multimediale",
    "sg:phone":"+39 099 779 2834",
    "sg:postcode":"74100",
    "sg:province":"Taranto",
    "sg:website":"http://www.planio.it",
    "wof:name":"Planetario Srl",
    "wof:placetype":"venue"
},
  "geometry": {"coordinates":[17.279715,40.464523],"type":"Point"}
}