{
  "type": "Feature",
  "properties": {
    "addr:full":"47100 Forli' Forl\u00ec-Cesena 47100",
    "addr:postcode":"47100;47100",
    "addr:street":"Forli ' Forli\u0300-Cesena",
    "iso:country":"IT",
    "sg:address":"47100 Forli'",
    "sg:orig_category":"Alluminio E Leghe",
    "sg:phone":"+39 0543 781081",
    "sg:postcode":"47100",
    "sg:province":"Forl\u00ec-Cesena",
    "wof:name":"Anofor Srl",
    "wof:placetype":"venue"
},
  "geometry": {"coordinates":[12.103204,44.212139],"type":"Point"}
}