{
  "type": "Feature",
  "properties": {
    "iso:country":"IT",
    "sg:address":"36071 Arzignano",
    "sg:city":"Arzignano",
    "sg:orig_category":"Prodotti Chimici",
    "sg:phone":"+39 0444 673770",
    "sg:postcode":"36071",
    "sg:province":"Vicenza",
    "wof:name":"Neotens Italia Srl",
    "wof:placetype":"venue"
},
  "geometry": {"coordinates":[11.3472499847,45.5170211792],"type":"Point"}
}