{
  "type": "Feature",
  "properties": {
    "iso:country":"IT",
    "sg:address":"53017 Radda In Chianti",
    "sg:city":"Radda in Chianti",
    "sg:orig_category":"Ristorazione E Locali Pubblici Affini. Ristoranti Ed Esercizi Affini. Servizi Ausiliari Di Ristorazione E Di Intrattenimento",
    "sg:phone":"+39 0577 738300",
    "sg:postcode":"53017",
    "sg:province":"Siena",
    "wof:name":"Relais Fattoria Vignale",
    "wof:placetype":"venue"
},
  "geometry": {"coordinates":[11.372744,43.48629],"type":"Point"}
}