{
  "type": "Feature",
  "properties": {
    "iso:country":"IT",
    "sg:address":"10098 Rivoli",
    "sg:city":"Rivoli",
    "sg:orig_category":"Fiorai - Accessori E Forniture",
    "sg:phone":"+39 011 959 1136",
    "sg:postcode":"10098",
    "sg:province":"Torino",
    "wof:name":"Il Trifoglio Snc",
    "wof:placetype":"venue"
},
  "geometry": {"coordinates":[7.5387296677,45.0659713745],"type":"Point"}
}