{
  "type": "Feature",
  "properties": {
    "iso:country":"IT",
    "sg:address":"Via S. Gemiliano 08048 Tortoli'",
    "sg:classifiers":[
        {
            "category":"Travel",
            "subcategory":"Travel Agent",
            "type":"Entertainment"
        }
    ],
    "sg:phone":"+39 0782 667318",
    "sg:postcode":"08048",
    "sg:province":"Ogliastra",
    "sg:tags":[
        "business"
    ],
    "wof:name":"Villaggio Turistico Saraceno",
    "wof:placetype":"venue"
},
  "geometry": {"coordinates":[9.456155,39.841053],"type":"Point"}
}