{
  "type": "Feature",
  "properties": {
    "addr:full":"35133 Padova Padova Padova 35133",
    "addr:postcode":"35133;35133",
    "iso:country":"IT",
    "sg:address":"35133 Padova",
    "sg:city":"Padova",
    "sg:orig_category":"Adesivi",
    "sg:phone":"+39 049 864 3700",
    "sg:postcode":"35133",
    "sg:province":"Padova",
    "wof:name":"T&t Srl",
    "wof:placetype":"venue"
},
  "geometry": {"coordinates":[11.440072,45.438366],"type":"Point"}
}