{
  "type": "Feature",
  "properties": {
    "iso:country":"IT",
    "sg:address":"20019 Settimo Milanese",
    "sg:city":"Settimo Milanese",
    "sg:orig_category":"Elettronica Professionale E Di Consumo. Tempo Libero - Articoli E Forniture",
    "sg:phone":"+39 02 328 2958",
    "sg:postcode":"20019",
    "sg:province":"Milano",
    "wof:name":"Cd Express Srl",
    "wof:placetype":"venue"
},
  "geometry": {"coordinates":[9.058027,45.488319],"type":"Point"}
}