{
  "type": "Feature",
  "properties": {
    "iso:country":"IT",
    "sg:address":"20090 Trezzano Sul Naviglio",
    "sg:city":"Trezzano sul Naviglio",
    "sg:orig_category":"Macchine, Impianti Ed Attrezzature Per Abbigliamento E Pelletterie",
    "sg:phone":"+39 02 445 5697",
    "sg:postcode":"20090",
    "sg:province":"Milano",
    "wof:name":"Anichini Bruno S.r.l.",
    "wof:placetype":"venue"
},
  "geometry": {"coordinates":[9.049536,45.426693],"type":"Point"}
}