{
  "type": "Feature",
  "properties": {
    "iso:country":"IT",
    "sg:address":"35020 Albignasego",
    "sg:city":"Albignasego",
    "sg:classifiers":[
        {
            "category":"Farming",
            "subcategory":"Livestock Farm",
            "type":"Manufacturing & Wholesale Goods"
        }
    ],
    "sg:phone":"+39 049 862 9099",
    "sg:postcode":"35020",
    "sg:province":"Padova",
    "sg:tags":[
        "equipment",
        "breeding",
        "agriculture",
        "machinery"
    ],
    "sg:website":"http://www.cuoghi-luigi.it",
    "wof:name":"Cuoghi Luigi Snc",
    "wof:placetype":"venue"
},
  "geometry": {"coordinates":[11.831532,45.344246],"type":"Point"}
}