{
  "type": "Feature",
  "properties": {
    "iso:country":"IT",
    "sg:address":"90133 Palermo",
    "sg:city":"Palermo",
    "sg:orig_category":"Orologeria",
    "sg:phone":"+39 091 584496",
    "sg:postcode":"90133",
    "sg:province":"Palermo",
    "wof:name":"Foresta Filippo",
    "wof:placetype":"venue"
},
  "geometry": {"coordinates":[13.36203,38.122314],"type":"Point"}
}