{
  "type": "Feature",
  "properties": {
    "iso:country":"IT",
    "sg:address":"20099 Sesto San Giovanni",
    "sg:city":"Sesto San Giovanni",
    "sg:orig_category":"Servizi E Lavori Per Arredamento E Industria Del Legno. Servizi E Lavori Per Edilizia E Lavori Pubblici",
    "sg:phone":"+39 02 240 2540",
    "sg:postcode":"20099",
    "sg:province":"Milano",
    "wof:name":"Marra Antonio",
    "wof:placetype":"venue"
},
  "geometry": {"coordinates":[9.241683,45.535503],"type":"Point"}
}