{
  "type": "Feature",
  "properties": {
    "iso:country":"IT",
    "sg:address":"20094 Corsico",
    "sg:city":"Corsico",
    "sg:orig_category":"Carta, Cartone E Prodotti Primari. Forniture Per Uffici",
    "sg:phone":"+39 02 449 1043",
    "sg:postcode":"20094",
    "sg:province":"Milano",
    "wof:name":"Sodalco Spa",
    "wof:placetype":"venue"
},
  "geometry": {"coordinates":[9.114703,45.442738],"type":"Point"}
}