{
  "type": "Feature",
  "properties": {
    "iso:country":"IT",
    "sg:address":"00194 Roma",
    "sg:city":"Roma",
    "sg:orig_category":"Ambasciate Ed Enti Internazionali",
    "sg:phone":"+39 06 3630 0260",
    "sg:postcode":"00194",
    "sg:province":"Roma",
    "wof:name":"Ambasciata Presso La S. Sede Paraguay",
    "wof:placetype":"venue"
},
  "geometry": {"coordinates":[12.461871,41.9459],"type":"Point"}
}