{
  "type": "Feature",
  "properties": {
    "iso:country":"IT",
    "sg:address":"50145 Firenze",
    "sg:city":"Firenze",
    "sg:classifiers":[
        {
            "category":"Home & Garden",
            "subcategory":"Hardware",
            "type":"Retail Goods"
        }
    ],
    "sg:phone":"+39 055 316104",
    "sg:postcode":"50145",
    "sg:province":"Firenze",
    "wof:name":"Daniele & Adami Sas",
    "wof:placetype":"venue"
},
  "geometry": {"coordinates":[11.191649,43.798168],"type":"Point"}
}