{
  "type": "Feature",
  "properties": {
    "iso:country":"IT",
    "sg:address":"00141 Roma",
    "sg:city":"Roma",
    "sg:orig_category":"Arredo Cucina Ed Elettrodomestici. Elettrodomestici",
    "sg:phone":"+39 06 812 3113",
    "sg:postcode":"00141",
    "sg:province":"Roma",
    "wof:name":"Simat Srl",
    "wof:placetype":"venue"
},
  "geometry": {"coordinates":[12.528551,41.942818],"type":"Point"}
}