{
  "type": "Feature",
  "properties": {
    "iso:country":"IT",
    "sg:address":"Via Marconi Ang; Grottaglie; 74023",
    "sg:city":"Grottaglie",
    "sg:classifiers":[
        {
            "category":"Banks & Credit Unions",
            "subcategory":"Bank",
            "type":"Services"
        }
    ],
    "sg:phone":"+39 099 562 8200",
    "sg:postcode":"74023",
    "sg:province":"Taranto",
    "wof:name":"Credito Italiano Spa",
    "wof:placetype":"venue"
},
  "geometry": {"coordinates":[17.420366,40.536877],"type":"Point"}
}