{
  "type": "Feature",
  "properties": {
    "addr:full":"8, Via Norvegia 64026 Roseto Degli Abruzzi Roseto degli Abruzzi Teramo 64026",
    "addr:postcode":"64026;64026",
    "addr:street":"Via Norvegia",
    "iso:country":"IT",
    "sg:address":"8, Via Norvegia 64026 Roseto Degli Abruzzi",
    "sg:city":"Roseto degli Abruzzi",
    "sg:classifiers":[
        {
            "category":"Shopping",
            "subcategory":"Clothing, Apparel, & Fashions",
            "type":"Retail Goods"
        }
    ],
    "sg:phone":"+39 085 894 4370",
    "sg:postcode":"64026",
    "sg:province":"Teramo",
    "sg:tags":[
        "clothes"
    ],
    "wof:name":"Luvistile S.r.l.",
    "wof:placetype":"venue"
},
  "geometry": {"coordinates":[14.003226,42.651398],"type":"Point"}
}