{
  "type": "Feature",
  "properties": {
    "iso:country":"IT",
    "sg:address":"Via G. Giusti, 30/32 71016 San Severo",
    "sg:city":"San Severo",
    "sg:classifiers":[
        {
            "category":"Shopping",
            "subcategory":"Bicycles & Sporting Goods",
            "type":"Retail Goods"
        }
    ],
    "sg:phone":"+39 0882 335195",
    "sg:postcode":"71016",
    "sg:province":"Foggia",
    "wof:name":"G.i.b.i.m. S.r.l. Grande Industria Biciclette Italiana Meridionale",
    "wof:placetype":"venue"
},
  "geometry": {"coordinates":[15.5447,41.462334],"type":"Point"}
}