{
  "type": "Feature",
  "properties": {
    "iso:country":"IT",
    "sg:address":"42019 Scandiano",
    "sg:orig_category":"Ceramiche Artistiche",
    "sg:phone":"+39 0522 763411",
    "sg:postcode":"42019",
    "sg:province":"Reggio Nell'Emilia",
    "sg:website":"http://www.runway.it",
    "wof:name":"Runway Srl",
    "wof:placetype":"venue"
},
  "geometry": {"coordinates":[10.698287,44.602356],"type":"Point"}
}