{
  "type": "Feature",
  "properties": {
    "iso:country":"IT",
    "sg:address":"00153 Roma",
    "sg:city":"Roma",
    "sg:orig_category":"Arte Ed Artigianato Artistico. Scuole E Servizi Scolastici. Servizi Ausiliari Di Analisi, Controllo E Ricerca",
    "sg:phone":"+39 06 580 9474",
    "sg:postcode":"00153",
    "sg:province":"Roma",
    "wof:name":"American Academy In Rome",
    "wof:placetype":"venue"
},
  "geometry": {"coordinates":[12.463059,41.888004],"type":"Point"}
}