{
  "type": "Feature",
  "properties": {
    "iso:country":"IT",
    "sg:address":"6, Zona Industriale Sambuceto",
    "sg:city":"Recanati",
    "sg:classifiers":[
        {
            "category":"Home & Garden",
            "subcategory":"Home Furnishings",
            "type":"Retail Goods"
        }
    ],
    "sg:phone":"+39 071 757 8025",
    "sg:postcode":"62019",
    "sg:province":"Macerata",
    "sg:tags":[
        "household"
    ],
    "sg:website":"http://www.ebansrl.com",
    "wof:name":"Eban Srl",
    "wof:placetype":"venue"
},
  "geometry": {"coordinates":[13.456262,43.300747],"type":"Point"}
}