{
  "type": "Feature",
  "properties": {
    "addr:full":"Frazione S. Grato 26900 Lodi Lodi Lodi 26900",
    "addr:postcode":"26900;26900",
    "addr:street":"Frazione S.",
    "iso:country":"IT",
    "sg:address":"Frazione S. Grato 26900 Lodi",
    "sg:city":"Lodi",
    "sg:classifiers":[
        {
            "category":"Shopping",
            "type":"Retail Goods"
        }
    ],
    "sg:phone":"+39 0371 417224",
    "sg:postcode":"26900",
    "sg:province":"Lodi",
    "sg:tags":[
        "finished",
        "-",
        "metallic"
    ],
    "wof:name":"Meccarts Di Faccini Luca E C. Sas",
    "wof:placetype":"venue"
},
  "geometry": {"coordinates":[9.4978504181,45.312877655],"type":"Point"}
}