{
  "type": "Feature",
  "properties": {
    "iso:country":"IT",
    "sg:address":"12, Via Monte Grappa 35019 Tombolo",
    "sg:city":"Tombolo",
    "sg:classifiers":[
        {
            "category":"Farming",
            "subcategory":"Livestock Farm",
            "type":"Manufacturing & Wholesale Goods"
        }
    ],
    "sg:phone":"+39 049 947 0694",
    "sg:postcode":"35019",
    "sg:province":"Padova",
    "sg:tags":[
        "agriculture"
    ],
    "wof:name":"Frigo",
    "wof:placetype":"venue"
},
  "geometry": {"coordinates":[11.827323,45.65147],"type":"Point"}
}