{
  "type": "Feature",
  "properties": {
    "iso:country":"IT",
    "sg:address":"1, Via Fornaci 23884 Castello Di Brianza",
    "sg:city":"Castello di Brianza",
    "sg:classifiers":[
        {
            "category":"Manufacturing",
            "subcategory":"Rubber & Plastics",
            "type":"Manufacturing & Wholesale Goods"
        }
    ],
    "sg:phone":"+39 390 399 9861",
    "sg:postcode":"23884",
    "sg:province":"Lecco",
    "wof:name":"Textron Automotive Company Italia S.r.l.",
    "wof:placetype":"venue"
},
  "geometry": {"coordinates":[9.349937439,45.7505569458],"type":"Point"}
}