{
  "type": "Feature",
  "properties": {
    "addr:full":"00195 Roma Roma Roma 00195",
    "addr:postcode":"00195;00195",
    "iso:country":"IT",
    "sg:address":"00195 Roma",
    "sg:city":"Roma",
    "sg:orig_category":"Alimentari - Vendita Al Dettaglio",
    "sg:phone":"+39 06 372 4050",
    "sg:postcode":"00195",
    "sg:province":"Roma",
    "wof:name":"De.car.f. Snc",
    "wof:placetype":"venue"
},
  "geometry": {"coordinates":[12.461246,41.916412],"type":"Point"}
}