{
  "type": "Feature",
  "properties": {
    "iso:country":"IT",
    "sg:address":"91016 Erice",
    "sg:city":"Erice",
    "sg:orig_category":"Dolciumi - Produzione",
    "sg:phone":"+39 0923 562690",
    "sg:postcode":"91016",
    "sg:province":"Trapani",
    "wof:name":"Sala Bonheur Di Stabile Nicolo'",
    "wof:placetype":"venue"
},
  "geometry": {"coordinates":[12.564226,38.029552],"type":"Point"}
}