{
  "type": "Feature",
  "properties": {
    "iso:country":"IT",
    "sg:address":"80146 Napoli",
    "sg:city":"Napoli",
    "sg:orig_category":"Forniture Per Edilizia E Lavori Pubblici",
    "sg:phone":"+39 081 752 7846",
    "sg:postcode":"80146",
    "sg:province":"Napoli",
    "wof:name":"Posatori Riuniti Linoleum Sas Di Cetrangolo Carmine & C",
    "wof:placetype":"venue"
},
  "geometry": {"coordinates":[14.3116044998,40.839630127],"type":"Point"}
}