{
  "type": "Feature",
  "properties": {
    "addr:full":"28, Via Principe Amedeo 10092 Beinasco Beinasco Torino 10092",
    "addr:postcode":"10092;10092",
    "addr:street":"Via Principe Amedeo",
    "iso:country":"IT",
    "sg:address":"28, Via Principe Amedeo 10092 Beinasco",
    "sg:city":"Beinasco",
    "sg:classifiers":[
        {
            "category":"Autos & Motor Vehicles",
            "subcategory":"Automobile Sales",
            "type":"Retail Goods"
        }
    ],
    "sg:phone":"+39 011 349 9722",
    "sg:postcode":"10092",
    "sg:province":"Torino",
    "sg:tags":[
        "motor-cars"
    ],
    "wof:name":"Sirrexport (s.r.l.)",
    "wof:placetype":"venue"
},
  "geometry": {"coordinates":[7.5841817856,45.0222740173],"type":"Point"}
}