{
  "type": "Feature",
  "properties": {
    "iso:country":"IT",
    "sg:address":"62024 Matelica",
    "sg:city":"Matelica",
    "sg:orig_category":"Servizi Ausiliari Dei Mezzi Di Trasporto",
    "sg:phone":"+39 0737 85526",
    "sg:postcode":"62024",
    "sg:province":"Macerata",
    "wof:name":"Antonelli Auto Snc Di Antonelli A. & C.",
    "wof:placetype":"venue"
},
  "geometry": {"coordinates":[13.007103,43.268383],"type":"Point"}
}