{
  "type": "Feature",
  "properties": {
    "iso:country":"IT",
    "sg:address":"1, Via Parco Degli Angeli 92100 Agrigento",
    "sg:city":"Agrigento",
    "sg:classifiers":[
        {
            "category":"Travel",
            "subcategory":"Travel Agent",
            "type":"Entertainment"
        }
    ],
    "sg:phone":"+39 0922 606144",
    "sg:postcode":"92100",
    "sg:province":"Agrigento",
    "sg:tags":[
        "business"
    ],
    "wof:name":"Grand Hotel Dei Templi",
    "wof:placetype":"venue"
},
  "geometry": {"coordinates":[13.616069,37.273628],"type":"Point"}
}