{
  "type": "Feature",
  "properties": {
    "addr:full":"06034 Foligno Foligno Perugia 06034",
    "addr:postcode":"06034;06034",
    "iso:country":"IT",
    "sg:address":"06034 Foligno",
    "sg:city":"Foligno",
    "sg:orig_category":"Bagno - Accessori E Mobili",
    "sg:phone":"+39 0742 670440",
    "sg:postcode":"06034",
    "sg:province":"Perugia",
    "wof:name":"Ediltermica Foligno Srl",
    "wof:placetype":"venue"
},
  "geometry": {"coordinates":[12.420604,43.071075],"type":"Point"}
}