{
  "type": "Feature",
  "properties": {
    "addr:full":"13836 Cossato Castellengo Biella 13836",
    "addr:postcode":"13836;13836",
    "iso:country":"IT",
    "sg:address":"13836 Cossato",
    "sg:city":"Castellengo",
    "sg:orig_category":"Filati E Materie Prime Tessili",
    "sg:phone":"+39 015 983784",
    "sg:postcode":"13836",
    "sg:province":"Biella",
    "wof:name":"Pettinatura Paola Di Bada' R. & C. (s.n.c.)",
    "wof:placetype":"venue"
},
  "geometry": {"coordinates":[8.1883392334,45.5320854187],"type":"Point"}
}