{
  "type": "Feature",
  "properties": {
    "addr:full":"38, Via Gallarata 20019 Settimo Milanese Settimo Milanese Milano 20019",
    "addr:postcode":"20019;20019",
    "addr:street":"Via Gallarata",
    "iso:country":"IT",
    "sg:address":"38, Via Gallarata 20019 Settimo Milanese",
    "sg:city":"Settimo Milanese",
    "sg:classifiers":[
        {
            "category":"Home & Garden",
            "subcategory":"Home Furnishings",
            "type":"Retail Goods"
        }
    ],
    "sg:phone":"+39 02 3350 1216",
    "sg:postcode":"20019",
    "sg:province":"Milano",
    "sg:tags":[
        "household"
    ],
    "wof:name":"Mobil Crab S.r.l.",
    "wof:placetype":"venue"
},
  "geometry": {"coordinates":[9.0667495728,45.4683685303],"type":"Point"}
}