{
  "type": "Feature",
  "properties": {
    "iso:country":"IT",
    "sg:address":"8, Lung'adige Galtarossa 37133 Verona",
    "sg:city":"Verona",
    "sg:classifiers":[
        {
            "category":"Utilities",
            "subcategory":"Electric",
            "type":"Services"
        }
    ],
    "sg:phone":"+39 045 867 7111",
    "sg:postcode":"37133",
    "sg:province":"Verona",
    "sg:tags":[
        "electricity"
    ],
    "wof:name":"Azienda Generale Servizi Municipali Verona Spa",
    "wof:placetype":"venue"
},
  "geometry": {"coordinates":[10.991748,45.438366],"type":"Point"}
}