{
  "type": "Feature",
  "properties": {
    "addr:full":"20132 Milano Milano Milano 20132",
    "addr:postcode":"20132;20132",
    "iso:country":"IT",
    "sg:address":"20132 Milano",
    "sg:city":"Milano",
    "sg:orig_category":"Forniture Per Abbigliamento E Pelletterie",
    "sg:phone":"+39 02 256 4685",
    "sg:postcode":"20132",
    "sg:province":"Milano",
    "wof:name":"Scorti Loredana",
    "wof:placetype":"venue"
},
  "geometry": {"coordinates":[9.2409982681,45.5041999817],"type":"Point"}
}