{
  "type": "Feature",
  "properties": {
    "addr:full":"00185 Roma Roma Roma 00185",
    "addr:postcode":"00185;00185",
    "iso:country":"IT",
    "sg:address":"00185 Roma",
    "sg:city":"Roma",
    "sg:orig_category":"Ospedali E Servizi Sanitari. Servizi Ausiliari Di Analisi, Controllo E Ricerca",
    "sg:phone":"+39 06 486698",
    "sg:postcode":"00185",
    "sg:province":"Roma",
    "wof:name":"Argenti Letizia",
    "wof:placetype":"venue"
},
  "geometry": {"coordinates":[12.500722,41.906887],"type":"Point"}
}