{
  "type": "Feature",
  "properties": {
    "addr:full":"75013 Ferrandina Ferrandina Matera 75013",
    "addr:postcode":"75013;75013",
    "iso:country":"IT",
    "sg:address":"75013 Ferrandina",
    "sg:city":"Ferrandina",
    "sg:orig_category":"Utensili Meccanici E Materiali",
    "sg:phone":"+39 0835 757075",
    "sg:postcode":"75013",
    "sg:province":"Matera",
    "wof:name":"Sapio Idrogeno Spa",
    "wof:placetype":"venue"
},
  "geometry": {"coordinates":[16.5027427673,40.470905304],"type":"Point"}
}