{
  "type": "Feature",
  "properties": {
    "addr:full":"4, Via Val Di Stava 37060 Sona Sona Verona 37060",
    "addr:postcode":"37060;37060",
    "addr:street":"Via Val Di Stava",
    "iso:country":"IT",
    "sg:address":"4, Via Val Di Stava 37060 Sona",
    "sg:city":"Sona",
    "sg:classifiers":[
        {
            "category":"Communications",
            "subcategory":"Television Station",
            "type":"Services"
        }
    ],
    "sg:phone":"+39 045 608 1167",
    "sg:postcode":"37060",
    "sg:province":"Verona",
    "sg:tags":[
        "audio-visual"
    ],
    "wof:name":"Musical Box Rent S.r.l.",
    "wof:placetype":"venue"
},
  "geometry": {"coordinates":[10.846976,45.43026],"type":"Point"}
}