{
  "type": "Feature",
  "properties": {
    "addr:full":"47030 S. Mauro Pascoli Forl\u00ec-Cesena 47030",
    "addr:housenumber":"47030",
    "addr:postcode":"47030",
    "addr:street":"S. Mauro Pascoli",
    "iso:country":"IT",
    "sg:address":"47030 S. Mauro Pascoli",
    "sg:classifiers":[
        {
            "category":"Health Services",
            "subcategory":"Health Practitioner",
            "type":"Services"
        }
    ],
    "sg:phone":"+39 0541 931119",
    "sg:postcode":"47030",
    "sg:province":"Forl\u00ec-Cesena",
    "sg:tags":[
        "medici"
    ],
    "wof:name":"Bianchini Dr. Stefano",
    "wof:placetype":"venue"
},
  "geometry": {"coordinates":[11.980461,43.994766],"type":"Point"}
}