{
  "type": "Feature",
  "properties": {
    "iso:country":"IT",
    "sg:address":"Via G. Marconi 4 - Ponticelli 56020 Santa Maria A Monte",
    "sg:city":"Santa Maria a Monte",
    "sg:orig_category":"Ladies' Shoes",
    "sg:phone":"+39 0587 706730",
    "sg:postcode":"56020",
    "sg:province":"Pisa",
    "sg:website":"www.calzaturificiojaguar.it",
    "wof:name":"Calzaturificio Jaguar Snc",
    "wof:placetype":"venue"
},
  "geometry": {"coordinates":[10.396585,43.716137],"type":"Point"}
}