{
  "type": "Feature",
  "properties": {
    "addr:full":"16159 Genova Genova Genova 16159",
    "addr:postcode":"16159;16159",
    "iso:country":"IT",
    "sg:address":"16159 Genova",
    "sg:city":"Genova",
    "sg:orig_category":"Scuole E Servizi Scolastici. Servizi Ausiliari Dei Mezzi Di Trasporto. Ricerca, Selezione E Formazione Del Personale",
    "sg:phone":"+39 010 642 3417",
    "sg:postcode":"16159",
    "sg:province":"Genova",
    "wof:name":"Autoscuola Rivarolo",
    "wof:placetype":"venue"
},
  "geometry": {"coordinates":[8.893147,44.431725],"type":"Point"}
}