{
  "type": "Feature",
  "properties": {
    "addr:full":"80143 Napoli Napoli Napoli 80143",
    "addr:housenumber":"80143",
    "addr:postcode":"80143",
    "iso:country":"IT",
    "sg:address":"80143 Napoli",
    "sg:city":"Napoli",
    "sg:orig_category":"Impiantistica E Prodotti Tecnologici Per Edilizia. Forniture Industriali Per Prevenzione, Controllo E Sicurezza",
    "sg:phone":"+39 081 787 1793",
    "sg:postcode":"80143",
    "sg:province":"Napoli",
    "wof:name":"Protezione Incendi Di Lombardi & C. S.a.s. Antonio",
    "wof:placetype":"venue"
},
  "geometry": {"coordinates":[14.28902,40.860413],"type":"Point"}
}