{
  "type": "Feature",
  "properties": {
    "iso:country":"IT",
    "sg:address":"22070 Capiago Intimiano",
    "sg:city":"Capiago",
    "sg:orig_category":"Macchine, Impianti Ed Attrezzature Per Abbigliamento E Pelletterie",
    "sg:phone":"+39 031 460182",
    "sg:postcode":"22070",
    "sg:province":"Como",
    "sg:website":"http://www.marelliluciano.com",
    "wof:name":"Marelli Luciano Sas Di Marelli Sergio & C.",
    "wof:placetype":"venue"
},
  "geometry": {"coordinates":[9.116843,45.764935],"type":"Point"}
}