{
  "type": "Feature",
  "properties": {
    "addr:full":"10, Via Dell' Artigianato 60015 Falconara Marittima Falconara Marittima Ancona 60015",
    "addr:postcode":"60015;60015",
    "addr:street":"Via Dell ' Artigianato",
    "iso:country":"IT",
    "sg:address":"10, Via Dell' Artigianato 60015 Falconara Marittima",
    "sg:city":"Falconara Marittima",
    "sg:classifiers":[
        {
            "category":"Manufacturing",
            "subcategory":"Food",
            "type":"Manufacturing & Wholesale Goods"
        }
    ],
    "sg:phone":"+39 39071918000",
    "sg:postcode":"60015",
    "sg:province":"Ancona",
    "sg:tags":[
        "equipment",
        "processing",
        "-",
        "machinery"
    ],
    "wof:name":"Sergio Pianelli S.r.l.",
    "wof:placetype":"venue"
},
  "geometry": {"coordinates":[13.3728561401,43.613571167],"type":"Point"}
}