{
  "type": "Feature",
  "properties": {
    "iso:country":"IT",
    "sg:address":"36016 Thiene",
    "sg:city":"Thiene",
    "sg:orig_category":"Accessori Dei Mezzi Di Trasporto",
    "sg:phone":"+39 0445 361441",
    "sg:postcode":"36016",
    "sg:province":"Vicenza",
    "wof:name":"Cavedon Moto Snc Di Cavedon E. F. L.",
    "wof:placetype":"venue"
},
  "geometry": {"coordinates":[11.494468,45.708652],"type":"Point"}
}