{
  "type": "Feature",
  "properties": {
    "iso:country":"IT",
    "sg:address":"00040 Pomezia",
    "sg:city":"Pomezia",
    "sg:orig_category":"Campeggio, Tende, Attrezzature Ed Articoli - Vendita Al Dettaglio",
    "sg:phone":"+39 06 9196 9036",
    "sg:postcode":"00040",
    "sg:province":"Roma",
    "wof:name":"S.g.r. Srl",
    "wof:placetype":"venue"
},
  "geometry": {"coordinates":[12.444936,41.776138],"type":"Point"}
}