{
  "type": "Feature",
  "properties": {
    "addr:full":"06010 Citerna Citerna Perugia 06010",
    "addr:postcode":"06010;06010",
    "iso:country":"IT",
    "sg:address":"06010 Citerna",
    "sg:city":"Citerna",
    "sg:orig_category":"Non-classified Establishments",
    "sg:phone":"+39 075 859 2298",
    "sg:postcode":"06010",
    "sg:province":"Perugia",
    "wof:name":"Due Erre Di Rossi Paola & C. Snc",
    "wof:placetype":"venue"
},
  "geometry": {"coordinates":[12.143296,43.511406],"type":"Point"}
}