{
  "type": "Feature",
  "properties": {
    "addr:full":"Viale Elmas 206 09122 Cagliari Cagliari Cagliari 09122",
    "addr:housenumber":"206",
    "addr:postcode":"09122;09122",
    "addr:street":"Viale Elmas",
    "iso:country":"IT",
    "sg:address":"Viale Elmas 206 09122 Cagliari",
    "sg:city":"Cagliari",
    "sg:classifiers":[
        {
            "category":"Shopping",
            "subcategory":"Books",
            "type":"Retail Goods"
        }
    ],
    "sg:phone":"+39 0702003",
    "sg:postcode":"09122",
    "sg:province":"Cagliari",
    "sg:tags":[
        "text",
        "school",
        "books",
        "material",
        "learning"
    ],
    "wof:name":"Editar Spa Editrice Italo Araba",
    "wof:placetype":"venue"
},
  "geometry": {"coordinates":[9.089971,39.243458],"type":"Point"}
}