{
  "type": "Feature",
  "properties": {
    "addr:full":"41031 Camposanto Camposanto Modena 41031",
    "addr:postcode":"41031;41031",
    "iso:country":"IT",
    "sg:address":"41031 Camposanto",
    "sg:city":"Camposanto",
    "sg:orig_category":"Contenitori - Produzione E Commercio",
    "sg:phone":"+39 0535 87422",
    "sg:postcode":"41031",
    "sg:province":"Modena",
    "sg:website":"http://www.bombonette.it",
    "wof:name":"Bombonette Srl",
    "wof:placetype":"venue"
},
  "geometry": {"coordinates":[11.14932,44.787933],"type":"Point"}
}