{
  "type": "Feature",
  "properties": {
    "addr:full":"24020 Ranica Ranica Bergamo 24020",
    "addr:postcode":"24020;24020",
    "iso:country":"IT",
    "sg:address":"24020 Ranica",
    "sg:city":"Ranica",
    "sg:orig_category":"Apparecchiature E Sistemi Per Magazzinaggio E Movimentazione",
    "sg:phone":"+39 035 511441",
    "sg:postcode":"24020",
    "sg:province":"Bergamo",
    "wof:name":"Tomasoni Srl",
    "wof:placetype":"venue"
},
  "geometry": {"coordinates":[9.714556,45.724224],"type":"Point"}
}