{
  "type": "Feature",
  "properties": {
    "iso:country":"IT",
    "sg:address":"50041 Calenzano",
    "sg:city":"Calenzano",
    "sg:orig_category":"Arredamento Negozi E Supermercati",
    "sg:phone":"+39 055 887 9465",
    "sg:postcode":"50041",
    "sg:province":"Firenze",
    "sg:website":"http://www.arpaarreda.it",
    "wof:name":"Arpa Arreda Srl",
    "wof:placetype":"venue"
},
  "geometry": {"coordinates":[11.16265,43.849236],"type":"Point"}
}