{
  "type": "Feature",
  "properties": {
    "iso:country":"IT",
    "sg:address":"Via Dell' Industria, 27/29 36063 Marostica",
    "sg:city":"Marostica",
    "sg:classifiers":[
        {
            "category":"Utilities",
            "subcategory":"Natural Gas",
            "type":"Services"
        }
    ],
    "sg:phone":"+39 0424 475800",
    "sg:postcode":"36063",
    "sg:province":"Vicenza",
    "sg:tags":[
        "pulley",
        "motors",
        "drum",
        "motor",
        "electric"
    ],
    "sg:website":"www.valco.net",
    "wof:name":"Valco Srlu",
    "wof:placetype":"venue"
},
  "geometry": {"coordinates":[11.656526,45.731007],"type":"Point"}
}