{
  "type": "Feature",
  "properties": {
    "addr:full":"35020 Albignasego Albignasego Padova 35020",
    "addr:postcode":"35020;35020",
    "iso:country":"IT",
    "sg:address":"35020 Albignasego",
    "sg:city":"Albignasego",
    "sg:orig_category":"Petroli, Gas E Combustibili. Termotecnica E Riscaldamento, Apparecchiature E Servizi",
    "sg:phone":"+39 049 862 5355",
    "sg:postcode":"35020",
    "sg:province":"Padova",
    "wof:name":"Babetto Giancarlo Srl",
    "wof:placetype":"venue"
},
  "geometry": {"coordinates":[11.8682966232,45.3484458923],"type":"Point"}
}