{
  "type": "Feature",
  "properties": {
    "iso:country":"IT",
    "sg:address":"8, Via Falzarego 20021 Bollate",
    "sg:city":"Bollate",
    "sg:classifiers":[
        {
            "category":"Communications",
            "subcategory":"Television Station",
            "type":"Services"
        }
    ],
    "sg:phone":"+39 39023834151",
    "sg:postcode":"20021",
    "sg:province":"Milano",
    "sg:tags":[
        "audio-visual"
    ],
    "wof:name":"L.p.e. Spa",
    "wof:placetype":"venue"
},
  "geometry": {"coordinates":[9.103408,45.532925],"type":"Point"}
}