{
  "type": "Feature",
  "properties": {
    "iso:country":"IT",
    "sg:address":"36063 Marostica",
    "sg:city":"Marostica",
    "sg:orig_category":"Non-classified Establishments",
    "sg:phone":"+39 0424 77217",
    "sg:postcode":"36063",
    "sg:province":"Vicenza",
    "wof:name":"Lisciotto Domenico",
    "wof:placetype":"venue"
},
  "geometry": {"coordinates":[11.685527,45.757294],"type":"Point"}
}