{
  "type": "Feature",
  "properties": {
    "iso:country":"IT",
    "sg:address":"10137 Torino",
    "sg:city":"Torino",
    "sg:orig_category":"Automobili - Commercio",
    "sg:phone":"+39 011 329 9322",
    "sg:postcode":"10137",
    "sg:province":"Torino",
    "wof:name":"Pastorino Srl",
    "wof:placetype":"venue"
},
  "geometry": {"coordinates":[7.65269,45.04224],"type":"Point"}
}