{
  "type": "Feature",
  "properties": {
    "iso:country":"IT",
    "sg:address":"07100 Sassari",
    "sg:city":"Sassari",
    "sg:orig_category":"Pubblica Amministrazione",
    "sg:phone":"+39 079 259 9000",
    "sg:postcode":"07100",
    "sg:province":"Sassari",
    "wof:name":"Comune Di Sassari",
    "wof:placetype":"venue"
},
  "geometry": {"coordinates":[8.3745718002,40.7555809021],"type":"Point"}
}