{
  "type": "Feature",
  "properties": {
    "addr:full":"Via Bibiana 76 12031 Bagnolo Piemonte Bagnolo Piemonte Cuneo 12031",
    "addr:housenumber":"76",
    "addr:postcode":"12031;12031",
    "addr:street":"Via Bibiana",
    "iso:country":"IT",
    "sg:address":"Via Bibiana 76 12031 Bagnolo Piemonte",
    "sg:city":"Bagnolo Piemonte",
    "sg:classifiers":[
        {
            "category":"Landmark",
            "subcategory":"City Walls",
            "type":"Public Place"
        }
    ],
    "sg:phone":"+39 0175 391901",
    "sg:postcode":"12031",
    "sg:province":"Cuneo",
    "sg:tags":[
        "stone",
        "working"
    ],
    "sg:website":"www.manavella.com",
    "wof:name":"Manavella F.lli R. E R. Snc",
    "wof:placetype":"venue"
},
  "geometry": {"coordinates":[7.304039,44.773346],"type":"Point"}
}