{
  "type": "Feature",
  "properties": {
    "iso:country":"IT",
    "sg:address":"37014 Castelnuovo Del Garda",
    "sg:city":"Castelnuovo del Garda",
    "sg:orig_category":"Servizi E Lavori Per Arredamento E Industria Del Legno. Servizi E Lavori Per Edilizia E Lavori Pubblici",
    "sg:phone":"+39 045 757 0227",
    "sg:postcode":"37014",
    "sg:province":"Verona",
    "wof:name":"Vall Eros",
    "wof:placetype":"venue"
},
  "geometry": {"coordinates":[10.756612,45.429455],"type":"Point"}
}