{
  "type": "Feature",
  "properties": {
    "addr:full":"00186 Roma Roma Roma 00186",
    "addr:postcode":"00186;00186",
    "iso:country":"IT",
    "sg:address":"00186 Roma",
    "sg:city":"Roma",
    "sg:orig_category":"Abbigliamento Donna",
    "sg:phone":"+39 06 686 7670",
    "sg:postcode":"00186",
    "sg:province":"Roma",
    "wof:name":"Baulla' Di Gerbasio Teresa",
    "wof:placetype":"venue"
},
  "geometry": {"coordinates":[12.4715805054,41.8954353333],"type":"Point"}
}