{
  "type": "Feature",
  "properties": {
    "iso:country":"IT",
    "sg:address":"40131 Bologna",
    "sg:city":"Bologna",
    "sg:orig_category":"Servizi Per Aziende, Manifestazioni E Supporto Agli Scambi Commerciali",
    "sg:phone":"+39 051 528 1901",
    "sg:postcode":"40131",
    "sg:province":"Bologna",
    "wof:name":"Executive Service",
    "wof:placetype":"venue"
},
  "geometry": {"coordinates":[11.321144,44.501293],"type":"Point"}
}