{
  "type": "Feature",
  "properties": {
    "iso:country":"IT",
    "sg:address":"80128 Napoli",
    "sg:city":"Napoli",
    "sg:orig_category":"Non-classified Establishments",
    "sg:phone":"+39 081 579 8590",
    "sg:postcode":"80128",
    "sg:province":"Napoli",
    "wof:name":"Lombardi Maria Di Peduto Paola Sas",
    "wof:placetype":"venue"
},
  "geometry": {"coordinates":[14.219248,40.849354],"type":"Point"}
}