{
  "type": "Feature",
  "properties": {
    "addr:full":"Ctr Baruso 83048 Montella Montella Avellino 83048",
    "addr:postcode":"83048;83048",
    "addr:street":"Baruso",
    "iso:country":"IT",
    "sg:address":"Ctr Baruso 83048 Montella",
    "sg:city":"Montella",
    "sg:classifiers":[
        {
            "category":"Military Area",
            "subcategory":"Air Force Base",
            "type":"Public Place"
        }
    ],
    "sg:phone":"+39 0827 61491",
    "sg:postcode":"83048",
    "sg:province":"Avellino",
    "sg:tags":[
        "test",
        "stand",
        "automation"
    ],
    "wof:name":"Co.mec. Costruzioni Meccaniche Di Clemente Antonio & C. Snc",
    "wof:placetype":"venue"
},
  "geometry": {"coordinates":[14.792723,40.914749],"type":"Point"}
}