{
  "type": "Feature",
  "properties": {
    "addr:full":"26837 Mulazzano Mulazzano Lodi 26837",
    "addr:postcode":"26837;26837",
    "iso:country":"IT",
    "sg:address":"26837 Mulazzano",
    "sg:city":"Mulazzano",
    "sg:classifiers":[
        {
            "category":"Bars & Pubs",
            "subcategory":"Lounge",
            "type":"Food & Drink"
        }
    ],
    "sg:phone":"+39 02 989112",
    "sg:postcode":"26837",
    "sg:province":"Lodi",
    "sg:tags":[
        "e",
        "-",
        "spray",
        "aerosol",
        "prodotti",
        "confezionamenti"
    ],
    "sg:website":"http://www.cosmosol.com",
    "wof:name":"Cosmosol Srl",
    "wof:placetype":"venue"
},
  "geometry": {"coordinates":[9.418612,45.358147],"type":"Point"}
}