{
  "type": "Feature",
  "properties": {
    "addr:full":"10128 Torino Torino Torino 10128",
    "addr:postcode":"10128;10128",
    "iso:country":"IT",
    "sg:address":"10128 Torino",
    "sg:city":"Torino",
    "sg:orig_category":"Facchinaggio, Carico E Scarico Merci, Portabagagli - Servizio",
    "sg:phone":"+39 011 562 8740",
    "sg:postcode":"10128",
    "sg:province":"Torino",
    "wof:name":"Consorzio Piemontese Coop. Portabagagli C.p.c.p.",
    "wof:placetype":"venue"
},
  "geometry": {"coordinates":[7.6752362251,45.06224823],"type":"Point"}
}