{
  "type": "Feature",
  "properties": {
    "iso:country":"IT",
    "sg:address":"89900 Vibo Valentia",
    "sg:city":"Porto Salvo",
    "sg:orig_category":"Tubi E Tubazioni - Produzione E Commercio",
    "sg:phone":"+39 0963 561257",
    "sg:postcode":"89900",
    "sg:province":"Vibo Valentia",
    "wof:name":"Racal Sas",
    "wof:placetype":"venue"
},
  "geometry": {"coordinates":[16.105164,38.67366],"type":"Point"}
}