{
  "type": "Feature",
  "properties": {
    "iso:country":"IT",
    "sg:address":"71019 Vieste",
    "sg:city":"Vieste",
    "sg:orig_category":"Campeggio. Alberghi E Strutture Extra Alberghiere",
    "sg:phone":"+39 0884 709011",
    "sg:postcode":"71019",
    "sg:province":"Foggia",
    "sg:website":"http://www.pugnochiuso.com",
    "wof:name":"Pugnochiuso - Gruppo Marcegaglia",
    "wof:placetype":"venue"
},
  "geometry": {"coordinates":[16.188774,41.783867],"type":"Point"}
}