{
  "type": "Feature",
  "properties": {
    "iso:country":"IT",
    "sg:address":"31039 Poggiana Di Riese Pio X",
    "sg:city":"Poggiana",
    "sg:orig_category":"Macchine Ed Impianti Per Edilizia E Lavori Pubblici",
    "sg:phone":"+39 0423 456374",
    "sg:postcode":"31039",
    "sg:province":"Treviso",
    "wof:name":"Pavi Center Srl",
    "wof:placetype":"venue"
},
  "geometry": {"coordinates":[12.242072,45.666286],"type":"Point"}
}