{
  "type": "Feature",
  "properties": {
    "addr:full":"64011 Alba Adriatica Alba Adriatica Teramo 64011",
    "addr:postcode":"64011;64011",
    "iso:country":"IT",
    "sg:address":"64011 Alba Adriatica",
    "sg:city":"Alba Adriatica",
    "sg:orig_category":"Abbigliamento Esterno, Maglierie E Pelliccerie. Shopping",
    "sg:phone":"+39 0861 752158",
    "sg:postcode":"64011",
    "sg:province":"Teramo",
    "wof:name":"Studio Pietro Celli",
    "wof:placetype":"venue"
},
  "geometry": {"coordinates":[13.925491,42.831905],"type":"Point"}
}