{
  "type": "Feature",
  "properties": {
    "iso:country":"IT",
    "sg:address":"20090 Assago",
    "sg:city":"Assago",
    "sg:orig_category":"Agenzie D'affari E Servizi Commerciali",
    "sg:phone":"+39 02 488531",
    "sg:postcode":"20090",
    "sg:province":"Milano",
    "wof:name":"Saim Spa",
    "wof:placetype":"venue"
},
  "geometry": {"coordinates":[9.116024,45.407162],"type":"Point"}
}