{
  "type": "Feature",
  "properties": {
    "iso:country":"IT",
    "sg:address":"70024 Gravina In Puglia",
    "sg:city":"Gravina in Puglia",
    "sg:orig_category":"Salotti, Poltrone, Sedie E Tavoli",
    "sg:phone":"+39 080 325 2246",
    "sg:postcode":"70024",
    "sg:province":"Bari",
    "wof:name":"Eurolegno Snc",
    "wof:placetype":"venue"
},
  "geometry": {"coordinates":[16.369926,40.842537],"type":"Point"}
}