{
  "type": "Feature",
  "properties": {
    "iso:country":"IT",
    "sg:address":"Contrada Valle Molino 65010 Moscufo",
    "sg:city":"Moscufo",
    "sg:classifiers":[
        {
            "category":"Coffee & Tea",
            "type":"Food & Drink"
        }
    ],
    "sg:phone":"+39 085 975556",
    "sg:postcode":"65010",
    "sg:province":"Pescara",
    "sg:tags":[
        "raw"
    ],
    "sg:website":"www.universalcaffe.com",
    "wof:name":"Compagnia Del Caffe' Srl",
    "wof:placetype":"venue"
},
  "geometry": {"coordinates":[14.076019,42.449669],"type":"Point"}
}