{
  "type": "Feature",
  "properties": {
    "iso:country":"IT",
    "sg:address":"Parco Raffaele; S. Giovanni In Persiceto; 40017",
    "sg:classifiers":[
        {
            "category":"Banks & Credit Unions",
            "subcategory":"Bank",
            "type":"Services"
        }
    ],
    "sg:phone":"+39 051 825132",
    "sg:postcode":"40017",
    "sg:province":"Bologna",
    "wof:name":"Banca Nazionale Del Lavoro Spa",
    "wof:placetype":"venue"
},
  "geometry": {"coordinates":[11.209474,44.6632],"type":"Point"}
}