{
  "type": "Feature",
  "properties": {
    "iso:country":"IT",
    "sg:address":"20161 Milano",
    "sg:city":"Milano",
    "sg:orig_category":"Cancelleria",
    "sg:phone":"+39 02 6620 3404",
    "sg:postcode":"20161",
    "sg:province":"Milano",
    "wof:name":"Tigra Service Snc Di Montserrat Granados E Marina Tricarico",
    "wof:placetype":"venue"
},
  "geometry": {"coordinates":[9.17084,45.523651],"type":"Point"}
}