{
  "type": "Feature",
  "properties": {
    "iso:country":"IT",
    "sg:address":"Via Piave 39 20049 Concorezzo",
    "sg:city":"Concorezzo",
    "sg:classifiers":[
        {
            "category":"Autos & Motor Vehicles",
            "subcategory":"Boat Sales",
            "type":"Retail Goods"
        }
    ],
    "sg:phone":"+39 039 688 6119",
    "sg:postcode":"20049",
    "sg:province":"Milano",
    "sg:tags":[
        "varnish"
    ],
    "sg:website":"www.arasnai.it",
    "wof:name":"S.n.a.i. S.r.l. Servizi Nautici Aeronavali Ed Industriali",
    "wof:placetype":"venue"
},
  "geometry": {"coordinates":[9.329883,45.601093],"type":"Point"}
}