{
  "type": "Feature",
  "properties": {
    "addr:full":"20099 Sesto San Giovanni Sesto San Giovanni Milano 20099",
    "addr:postcode":"20099;20099",
    "iso:country":"IT",
    "sg:address":"20099 Sesto San Giovanni",
    "sg:city":"Sesto San Giovanni",
    "sg:orig_category":"Non-classified Establishments",
    "sg:phone":"+39 02 248 3031",
    "sg:postcode":"20099",
    "sg:province":"Milano",
    "wof:name":"Pelucchi Roberto",
    "wof:placetype":"venue"
},
  "geometry": {"coordinates":[9.235241,45.534424],"type":"Point"}
}