{
  "type": "Feature",
  "properties": {
    "iso:country":"IT",
    "sg:address":"00146 Roma",
    "sg:city":"Roma",
    "sg:orig_category":"Zootecnia E Pesca, Allevamento Piccoli Animali. Animali Domestici",
    "sg:phone":"+39 06 556 2929",
    "sg:postcode":"00146",
    "sg:province":"Roma",
    "wof:name":"Zoo 2000 Di Vitali Paola",
    "wof:placetype":"venue"
},
  "geometry": {"coordinates":[12.465664,41.867393],"type":"Point"}
}