{
  "type": "Feature",
  "properties": {
    "iso:country":"IT",
    "sg:address":"3, Via Mazzini 20060 Gessate",
    "sg:city":"Gessate",
    "sg:orig_category":"Miscellaneous Products",
    "sg:phone":"+39 02 9578 0422",
    "sg:postcode":"20060",
    "sg:province":"Milano",
    "wof:name":"Dell'aquila",
    "wof:placetype":"venue"
},
  "geometry": {"coordinates":[9.4429893494,45.5457038879],"type":"Point"}
}