{
  "type": "Feature",
  "properties": {
    "iso:country":"IT",
    "sg:address":"Via Benozzo Gozzoli, 5/8 50018 Scandicci",
    "sg:city":"Scandicci",
    "sg:classifiers":[
        {
            "category":"Shopping",
            "subcategory":"Event Tickets",
            "type":"Retail Goods"
        }
    ],
    "sg:phone":"+39 055 731 0373",
    "sg:postcode":"50018",
    "sg:province":"Firenze",
    "sg:tags":[
        "billfold"
    ],
    "wof:name":"P.l.g. Di Passariello A. E C. Snc",
    "wof:placetype":"venue"
},
  "geometry": {"coordinates":[11.132414,43.768848],"type":"Point"}
}