{
  "type": "Feature",
  "properties": {
    "iso:country":"IT",
    "sg:address":"41034 Finale Emilia",
    "sg:city":"Finale Emilia",
    "sg:orig_category":"Ceramiche Per Pavimenti E Rivestimenti - Produzione E Ingrosso",
    "sg:phone":"+39 0535 90401",
    "sg:postcode":"41034",
    "sg:province":"Modena",
    "sg:website":"http://www.cermoma.com",
    "wof:name":"Ceramiche Moma Spa",
    "wof:placetype":"venue"
},
  "geometry": {"coordinates":[11.281302,44.843826],"type":"Point"}
}