{
  "type": "Feature",
  "properties": {
    "iso:country":"IT",
    "sg:address":"25036 Palazzolo Sull'oglio",
    "sg:orig_category":"Abbigliamento Esterno, Maglierie E Pelliccerie",
    "sg:phone":"+39 030 740 2470",
    "sg:postcode":"25036",
    "sg:province":"Brescia",
    "sg:website":"http://www.raccagni.it",
    "wof:name":"Raccagni Snc Di Raccagni Italo Snc",
    "wof:placetype":"venue"
},
  "geometry": {"coordinates":[9.891188,45.594101],"type":"Point"}
}