{
  "type": "Feature",
  "properties": {
    "addr:full":"55049 Viareggio Viareggio Lucca 55049",
    "addr:postcode":"55049;55049",
    "iso:country":"IT",
    "sg:address":"55049 Viareggio",
    "sg:city":"Viareggio",
    "sg:orig_category":"Materiali E Componenti Elettrotecnici",
    "sg:phone":"+39 0584 49344",
    "sg:postcode":"55049",
    "sg:province":"Lucca",
    "wof:name":"Bienne Snc",
    "wof:placetype":"venue"
},
  "geometry": {"coordinates":[10.491113,43.84304],"type":"Point"}
}