{
  "type": "Feature",
  "properties": {
    "iso:country":"IT",
    "sg:address":"48010 Fusignano",
    "sg:city":"Fusignano",
    "sg:orig_category":"Motocicli E Motocarri Accessori E Parti - Vendita Al Dettaglio",
    "sg:phone":"+39 0545 53292",
    "sg:postcode":"48010",
    "sg:province":"Ravenna",
    "wof:name":"Zack Suspension",
    "wof:placetype":"venue"
},
  "geometry": {"coordinates":[11.9589996338,44.4659233093],"type":"Point"}
}