{
  "type": "Feature",
  "properties": {
    "iso:country":"IT",
    "sg:address":"20136 Milano",
    "sg:city":"Milano",
    "sg:classifiers":[
        {
            "category":"Health Services",
            "subcategory":"Health Practitioner",
            "type":"Services"
        }
    ],
    "sg:phone":"+39 02 837 3133",
    "sg:postcode":"20136",
    "sg:province":"Milano",
    "sg:tags":[
        "medici"
    ],
    "wof:name":"La Falce Giovanni",
    "wof:placetype":"venue"
},
  "geometry": {"coordinates":[9.179997,45.447365],"type":"Point"}
}