{
  "type": "Feature",
  "properties": {
    "iso:country":"IT",
    "sg:address":"10154 Torino",
    "sg:city":"Torino",
    "sg:orig_category":"Climatizzazione E Condizionamento, Apparecchiature E Servizi. Accessori Dei Mezzi Di Trasporto",
    "sg:phone":"+39 011 205 8038",
    "sg:postcode":"10154",
    "sg:province":"Torino",
    "wof:name":"Climasystem Sas",
    "wof:placetype":"venue"
},
  "geometry": {"coordinates":[7.701769,45.102024],"type":"Point"}
}