{
  "type": "Feature",
  "properties": {
    "iso:country":"IT",
    "sg:address":"20134 Milano",
    "sg:city":"Milano",
    "sg:orig_category":"Scuole E Servizi Scolastici. Ricerca, Selezione E Formazione Del Personale. Pubblica Amministrazione",
    "sg:phone":"+39 02 210 1181",
    "sg:postcode":"20134",
    "sg:province":"Milano",
    "wof:name":"Universita' Degli Studi",
    "wof:placetype":"venue"
},
  "geometry": {"coordinates":[9.24206,45.472778],"type":"Point"}
}