{
  "type": "Feature",
  "properties": {
    "iso:country":"IT",
    "sg:address":"33170 Pordenone",
    "sg:city":"Pordenone",
    "sg:classifiers":[
        {
            "category":"Health Services",
            "subcategory":"Hospital",
            "type":"Services"
        }
    ],
    "sg:phone":"+39 0434 572600",
    "sg:postcode":"33170",
    "sg:province":"Pordenone",
    "sg:tags":[
        "equipment",
        "systems",
        "supply"
    ],
    "sg:website":"http://www.saratoga-on-line.com",
    "wof:name":"Saratoga Spa",
    "wof:placetype":"venue"
},
  "geometry": {"coordinates":[12.650542,45.926983],"type":"Point"}
}