{
  "type": "Feature",
  "properties": {
    "iso:country":"IT",
    "sg:address":"25, Via Galileo Galilei 37030 Lavagno",
    "sg:city":"Lavagno",
    "sg:classifiers":[
        {
            "category":"Manufacturing",
            "subcategory":"Food",
            "type":"Manufacturing & Wholesale Goods"
        }
    ],
    "sg:phone":"+39 39045982008",
    "sg:postcode":"37030",
    "sg:province":"Verona",
    "sg:tags":[
        "equipment",
        "processing",
        "-",
        "machinery"
    ],
    "wof:name":"Trezzaforni Srl",
    "wof:placetype":"venue"
},
  "geometry": {"coordinates":[11.0975427628,45.4209861755],"type":"Point"}
}