{
  "type": "Feature",
  "properties": {
    "addr:full":"13, Via Dell' Artigianato 20034 Giussano Giussano Milano 20034",
    "addr:postcode":"20034;20034",
    "addr:street":"Via Dell ' Artigianato",
    "iso:country":"IT",
    "sg:address":"13, Via Dell' Artigianato 20034 Giussano",
    "sg:city":"Giussano",
    "sg:classifiers":[
        {
            "category":"Home & Garden",
            "subcategory":"Home Furnishings",
            "type":"Retail Goods"
        }
    ],
    "sg:phone":"+39 036 286 2384",
    "sg:postcode":"20034",
    "sg:province":"Milano",
    "sg:tags":[
        "household"
    ],
    "wof:name":"C.s. Di Cappellini G. & C. (s.n.c.)",
    "wof:placetype":"venue"
},
  "geometry": {"coordinates":[9.196162,45.681831],"type":"Point"}
}