{
  "type": "Feature",
  "properties": {
    "iso:country":"IT",
    "sg:address":"20052 Monza",
    "sg:city":"Monza",
    "sg:orig_category":"Cinematografia E Radiotelevisione. Forniture Per Il Settore Dello Spettacolo",
    "sg:phone":"+39 039 214 1369",
    "sg:postcode":"20052",
    "sg:province":"Milano",
    "wof:name":"Cine Project Italia Srl",
    "wof:placetype":"venue"
},
  "geometry": {"coordinates":[9.251822,45.578678],"type":"Point"}
}