{
  "type": "Feature",
  "properties": {
    "addr:full":"20131 Milano Milano Milano 20131",
    "addr:postcode":"20131;20131",
    "iso:country":"IT",
    "sg:address":"20131 Milano",
    "sg:city":"Milano",
    "sg:orig_category":"Prodotti Alimentari",
    "sg:phone":"+39 02 266 6427",
    "sg:postcode":"20131",
    "sg:province":"Milano",
    "wof:name":"Zuccolin Agostino",
    "wof:placetype":"venue"
},
  "geometry": {"coordinates":[9.2342691422,45.481628418],"type":"Point"}
}