{
  "type": "Feature",
  "properties": {
    "addr:full":"15/b, Via Maniago Fabio 33085 Maniago Maniago Pordenone 33085",
    "addr:housenumber":"15 / b",
    "addr:postcode":"33085;33085",
    "addr:street":"Via Maniago Fabio",
    "iso:country":"IT",
    "sg:address":"15/b, Via Maniago Fabio 33085 Maniago",
    "sg:city":"Maniago",
    "sg:classifiers":[
        {
            "category":"Real Estate",
            "subcategory":"Surveying",
            "type":"Services"
        }
    ],
    "sg:phone":"+39 0427 709084",
    "sg:postcode":"33085",
    "sg:province":"Pordenone",
    "sg:tags":[
        "equipment",
        "material",
        "good",
        "-",
        "handling"
    ],
    "wof:name":"Logimag S.r.l.",
    "wof:placetype":"venue"
},
  "geometry": {"coordinates":[12.655044,45.96265],"type":"Point"}
}