{
  "type": "Feature",
  "properties": {
    "iso:country":"IT",
    "sg:address":"10022 Carmagnola",
    "sg:city":"Carmagnola",
    "sg:orig_category":"Prodotti E Manufatti In Gomma",
    "sg:phone":"+39 011 972 3760",
    "sg:postcode":"10022",
    "sg:province":"Torino",
    "wof:name":"Rpm Srl",
    "wof:placetype":"venue"
},
  "geometry": {"coordinates":[7.7116222382,44.8374900818],"type":"Point"}
}