{
  "type": "Feature",
  "properties": {
    "addr:full":"32036 Sedico Sedico Belluno 32036",
    "addr:postcode":"32036;32036",
    "iso:country":"IT",
    "sg:address":"32036 Sedico",
    "sg:city":"Sedico",
    "sg:orig_category":"Carpenterie Ferro",
    "sg:phone":"+39 0437 852146",
    "sg:postcode":"32036",
    "sg:province":"Belluno",
    "wof:name":"Dal Pont Augusto & C. Snc",
    "wof:placetype":"venue"
},
  "geometry": {"coordinates":[12.118439,46.136456],"type":"Point"}
}