{
  "type": "Feature",
  "properties": {
    "addr:full":"Via Celentane Zona Industriale 83029 Solofra Solofra Avellino 83029",
    "addr:postcode":"83029;83029",
    "addr:street":"Via Celentane Zona Industriale",
    "iso:country":"IT",
    "sg:address":"Via Celentane Zona Industriale 83029 Solofra",
    "sg:city":"Solofra",
    "sg:classifiers":[
        {
            "category":"Shopping",
            "subcategory":"Luggage & Leather Goods",
            "type":"Retail Goods"
        }
    ],
    "sg:phone":"+39 0825 582772",
    "sg:postcode":"83029",
    "sg:province":"Avellino",
    "sg:tags":[
        "glove"
    ],
    "sg:website":"www.spp.it",
    "wof:name":"Societa' Partenopea Pellami Di Siciliano Antonio E C. Snc",
    "wof:placetype":"venue"
},
  "geometry": {"coordinates":[14.792723,40.914749],"type":"Point"}
}