{
  "type": "Feature",
  "properties": {
    "iso:country":"IT",
    "sg:address":"Via Ruca 346 25065 Lumezzane",
    "sg:city":"Lumezzane",
    "sg:classifiers":[
        {
            "category":"Autos & Motor Vehicles",
            "subcategory":"Auto Supplies",
            "type":"Retail Goods"
        }
    ],
    "sg:phone":"+39 030 892 2633",
    "sg:postcode":"25065",
    "sg:province":"Brescia",
    "sg:tags":[
        "window",
        "handle"
    ],
    "sg:website":"www.sifral.com",
    "wof:name":"Sifral Srl",
    "wof:placetype":"venue"
},
  "geometry": {"coordinates":[10.271279,45.641235],"type":"Point"}
}