{
  "type": "Feature",
  "properties": {
    "addr:full":"20146 Milano Milano Milano 20146",
    "addr:postcode":"20146;20146",
    "iso:country":"IT",
    "sg:address":"20146 Milano",
    "sg:city":"Milano",
    "sg:orig_category":"Metalli E Leghe",
    "sg:phone":"+39 02 422 4484",
    "sg:postcode":"20146",
    "sg:province":"Milano",
    "wof:name":"Metal - U S.r.l.",
    "wof:placetype":"venue"
},
  "geometry": {"coordinates":[9.1385068893,45.458366394],"type":"Point"}
}