{
  "type": "Feature",
  "properties": {
    "iso:country":"IT",
    "sg:address":"10154 Torino",
    "sg:city":"Torino",
    "sg:orig_category":"Minuterie Metalliche E Ferramenta. Forniture Per Attivita' Industriali",
    "sg:phone":"+39 011 247 2535",
    "sg:postcode":"10154",
    "sg:province":"Torino",
    "wof:name":"Merlo Fabio",
    "wof:placetype":"venue"
},
  "geometry": {"coordinates":[7.7096309662,45.0909118652],"type":"Point"}
}