{
  "type": "Feature",
  "properties": {
    "addr:full":"Via Castellanza 47 20027 Rescaldina Rescaldina Milano 20027",
    "addr:housenumber":"47",
    "addr:postcode":"20027;20027",
    "addr:street":"Via Castellanza",
    "iso:country":"IT",
    "sg:address":"Via Castellanza 47 20027 Rescaldina",
    "sg:city":"Rescaldina",
    "sg:classifiers":[
        {
            "category":"Wholesale",
            "subcategory":"Metals & Minerals",
            "type":"Manufacturing & Wholesale Goods"
        }
    ],
    "sg:phone":"+39 0331 575111",
    "sg:postcode":"20027",
    "sg:province":"Milano",
    "sg:tags":[
        "articles",
        "industrial"
    ],
    "wof:name":"Taico Valves & Controls Italia Srl",
    "wof:placetype":"venue"
},
  "geometry": {"coordinates":[8.9408302307,45.6251335144],"type":"Point"}
}