{
  "type": "Feature",
  "properties": {
    "iso:country":"IT",
    "sg:address":"10127 Torino",
    "sg:city":"Torino",
    "sg:orig_category":"Utensili Meccanici E Materiali",
    "sg:phone":"+39 011 619 9622",
    "sg:postcode":"10127",
    "sg:province":"Torino",
    "wof:name":"Nicolis Sergio",
    "wof:placetype":"venue"
},
  "geometry": {"coordinates":[7.655202,45.025414],"type":"Point"}
}