{
  "type": "Feature",
  "properties": {
    "iso:country":"IT",
    "sg:address":"10042 Nichelino",
    "sg:city":"Nichelino",
    "sg:orig_category":"Minuterie Metalliche E Ferramenta. Ricambi E Componenti Dei Mezzi Di Trasporto",
    "sg:phone":"+39 011 627 1023",
    "sg:postcode":"10042",
    "sg:province":"Torino",
    "wof:name":"Toni Balestre Di Pivesso Antonio & Figlio (s.n.c.)",
    "wof:placetype":"venue"
},
  "geometry": {"coordinates":[7.6236915588,44.9877967834],"type":"Point"}
}