{
  "type": "Feature",
  "properties": {
    "iso:country":"IT",
    "sg:address":"85050 Balvano",
    "sg:city":"Balvano",
    "sg:orig_category":"Legno E Semilavorati. Articoli Per Imballaggio E Confezionamento",
    "sg:phone":"+39 0971 992085",
    "sg:postcode":"85050",
    "sg:province":"Potenza",
    "wof:name":"F. Lli Santagata Snc",
    "wof:placetype":"venue"
},
  "geometry": {"coordinates":[15.515,40.651424],"type":"Point"}
}