{
  "type": "Feature",
  "properties": {
    "iso:country":"IT",
    "sg:address":"Via F. Casorati 7 42100 Reggio Emilia",
    "sg:classifiers":[
        {
            "category":"Professional",
            "subcategory":"Art Services",
            "type":"Services"
        }
    ],
    "sg:phone":"+39 0522 511300",
    "sg:postcode":"42100",
    "sg:province":"Reggio Nell'Emilia",
    "sg:tags":[
        "development",
        "transmission",
        "designing"
    ],
    "wof:name":"B.i.m.a. S.r.l.",
    "wof:placetype":"venue"
},
  "geometry": {"coordinates":[10.648163,44.735077],"type":"Point"}
}