{
  "type": "Feature",
  "properties": {
    "iso:country":"IT",
    "sg:address":"10121 Torino",
    "sg:city":"Torino",
    "sg:orig_category":"Elettrotecnica Professionale E Di Consumo",
    "sg:phone":"+39 011 562 7636",
    "sg:postcode":"10121",
    "sg:province":"Torino",
    "wof:name":"Eclissi Di Mazza Pietro",
    "wof:placetype":"venue"
},
  "geometry": {"coordinates":[7.67281,45.066181],"type":"Point"}
}