{
  "type": "Feature",
  "properties": {
    "iso:country":"IT",
    "sg:address":"20077 Melegnano",
    "sg:city":"Melegnano",
    "sg:orig_category":"Materiali E Componenti Elettronici",
    "sg:postcode":"20077",
    "sg:province":"Milano",
    "wof:name":"Tecnomaster (s.a.s.)",
    "wof:placetype":"venue"
},
  "geometry": {"coordinates":[9.325457,45.35445],"type":"Point"}
}