{
  "type": "Feature",
  "properties": {
    "addr:full":"2, Piazza Cesare Battisti 38087 Roncone Roncone Trento 38087",
    "addr:postcode":"38087;38087",
    "addr:street":"Piazza Cesare Battisti",
    "iso:country":"IT",
    "sg:address":"2, Piazza Cesare Battisti 38087 Roncone",
    "sg:city":"Roncone",
    "sg:classifiers":[
        {
            "category":"Banks & Credit Unions",
            "subcategory":"Bank",
            "type":"Services"
        }
    ],
    "sg:phone":"+39 0465 901074",
    "sg:postcode":"38087",
    "sg:province":"Trento",
    "sg:tags":[
        "banking",
        "institution"
    ],
    "wof:name":"Cassa Rurale Alto Chiese B.c.c. S.c.p.a.a.r.l.",
    "wof:placetype":"venue"
},
  "geometry": {"coordinates":[10.669538,45.98391],"type":"Point"}
}