{
  "type": "Feature",
  "properties": {
    "addr:full":"3, Via Callalta 31037 Loria Loria Treviso 31037",
    "addr:postcode":"31037;31037",
    "addr:street":"Via Callalta",
    "iso:country":"IT",
    "sg:address":"3, Via Callalta 31037 Loria",
    "sg:city":"Loria",
    "sg:classifiers":[
        {
            "category":"Autos & Motor Vehicles",
            "subcategory":"Automobile Sales",
            "type":"Retail Goods"
        }
    ],
    "sg:phone":"+39 0423 758101",
    "sg:postcode":"31037",
    "sg:province":"Treviso",
    "sg:tags":[
        "equipment",
        "transport"
    ],
    "wof:name":"Italmanubri S.p.a.",
    "wof:placetype":"venue"
},
  "geometry": {"coordinates":[11.86697,45.732944],"type":"Point"}
}