{
  "type": "Feature",
  "properties": {
    "iso:country":"IT",
    "sg:address":"00198 Roma",
    "sg:city":"Roma",
    "sg:orig_category":"Tessuti E Stoffe",
    "sg:phone":"+39 06 841 1520",
    "sg:postcode":"00198",
    "sg:province":"Roma",
    "wof:name":"Modasystem Srl",
    "wof:placetype":"venue"
},
  "geometry": {"coordinates":[12.510056,41.919609],"type":"Point"}
}