{
  "type": "Feature",
  "properties": {
    "iso:country":"IT",
    "sg:address":"58022 Follonica",
    "sg:city":"Follonica",
    "sg:orig_category":"Servizi Per Lo Sport E Il Tempo Libero. Servizi Ausiliari Dei Mezzi Di Trasporto",
    "sg:phone":"+39 0566 57355",
    "sg:postcode":"58022",
    "sg:province":"Grosseto",
    "wof:name":"Gaggioli Arnaldo",
    "wof:placetype":"venue"
},
  "geometry": {"coordinates":[10.758295,42.91951],"type":"Point"}
}