{
  "type": "Feature",
  "properties": {
    "iso:country":"IT",
    "sg:address":"50053 Empoli",
    "sg:city":"Empoli",
    "sg:orig_category":"Arredo Cucina Ed Elettrodomestici. Elettrodomestici",
    "sg:phone":"+39 0571 931591",
    "sg:postcode":"50053",
    "sg:province":"Firenze",
    "wof:name":"Gruppo Ninci Srl",
    "wof:placetype":"venue"
},
  "geometry": {"coordinates":[10.946794,43.693741],"type":"Point"}
}