{
  "type": "Feature",
  "properties": {
    "addr:full":"Sda Statale 16, 3008 45038 Polesella Polesella Rovigo 45038",
    "addr:housenumber":"3008",
    "addr:postcode":"45038;45038",
    "iso:country":"IT",
    "sg:address":"Sda Statale 16, 3008 45038 Polesella",
    "sg:city":"Polesella",
    "sg:classifiers":[
        {
            "category":"Professional",
            "subcategory":"Engineering",
            "type":"Services"
        }
    ],
    "sg:phone":"+39 0425 444102",
    "sg:postcode":"45038",
    "sg:province":"Rovigo",
    "sg:tags":[
        "crane"
    ],
    "sg:website":"www.opmacchine.com",
    "wof:name":"Oleodinamica Polesana Di Coltro Giovanni & C. Snc",
    "wof:placetype":"venue"
},
  "geometry": {"coordinates":[11.740569,44.959801],"type":"Point"}
}