{
  "type": "Feature",
  "properties": {
    "addr:full":"55, V. Monte Asolon 36022 Cassola Cassola Vicenza 36022",
    "addr:housenumber":"55",
    "addr:postcode":"36022;36022",
    "addr:street":"V. Monte Asolon",
    "iso:country":"IT",
    "sg:address":"55, V. Monte Asolon 36022 Cassola",
    "sg:city":"Cassola",
    "sg:classifiers":[
        {
            "category":"Manufacturing",
            "subcategory":"Metals",
            "type":"Manufacturing & Wholesale Goods"
        }
    ],
    "sg:phone":"+39 0424 570696",
    "sg:postcode":"36022",
    "sg:province":"Vicenza",
    "sg:tags":[
        "processing"
    ],
    "sg:website":"http://www.fioresegiovanni.it:ws_end: :mark:ws:http://www.paginegialle.it/fiorese",
    "wof:name":"Fiorese Giovanni Srl",
    "wof:placetype":"venue"
},
  "geometry": {"coordinates":[11.7649402618,45.7506942749],"type":"Point"}
}