{
  "type": "Feature",
  "properties": {
    "addr:full":"3/11, Via Cesare Correnti 20028 San Vittore Olona San Vittore Olona Milano 20028",
    "addr:housenumber":"3 / 11",
    "addr:postcode":"20028;vittore olona;20028",
    "addr:street":"Via Cesare Correnti",
    "iso:country":"IT",
    "sg:address":"3/11, Via Cesare Correnti 20028 San Vittore Olona",
    "sg:city":"San Vittore Olona",
    "sg:classifiers":[
        {
            "category":"Manufacturing",
            "subcategory":"Rubber & Plastics",
            "type":"Manufacturing & Wholesale Goods"
        }
    ],
    "sg:phone":"+39 0331 517386",
    "sg:postcode":"20028",
    "sg:province":"Milano",
    "wof:name":"Lavorazioni Plastiche Sas Di Dell'acqua Angelo & C.",
    "wof:placetype":"venue"
},
  "geometry": {"coordinates":[8.9478492737,45.5837898254],"type":"Point"}
}