{
  "type": "Feature",
  "properties": {
    "addr:full":"Via Favorita 36040 Sarego Sarego Vicenza 36040",
    "addr:postcode":"36040;36040",
    "addr:street":"Via Favorita",
    "iso:country":"IT",
    "sg:address":"Via Favorita 36040 Sarego",
    "sg:city":"Sarego",
    "sg:classifiers":[
        {
            "category":"Manufacturing",
            "subcategory":"Printing",
            "type":"Manufacturing & Wholesale Goods"
        }
    ],
    "sg:phone":"+39 0444 436444",
    "sg:postcode":"36040",
    "sg:province":"Vicenza",
    "sg:tags":[
        "publishing"
    ],
    "wof:name":"Cartotecnica Montebello S.p.a.",
    "wof:placetype":"venue"
},
  "geometry": {"coordinates":[11.3910388947,45.4319076538],"type":"Point"}
}