{
  "type": "Feature",
  "properties": {
    "iso:country":"IT",
    "sg:address":"41100 Modena",
    "sg:city":"Modena",
    "sg:orig_category":"Termotecnica E Riscaldamento, Apparecchiature E Servizi",
    "sg:phone":"+39 059 334375",
    "sg:postcode":"41100",
    "sg:province":"Modena",
    "sg:website":"http://www.amatipietro.it",
    "wof:name":"Amati Pietro",
    "wof:placetype":"venue"
},
  "geometry": {"coordinates":[10.89959,44.653702],"type":"Point"}
}