{
  "type": "Feature",
  "properties": {
    "addr:full":"28, V. Matera 70022 Altamura Altamura Bari 70022",
    "addr:housenumber":"28",
    "addr:postcode":"70022;70022",
    "addr:street":"V. Matera",
    "iso:country":"IT",
    "sg:address":"28, V. Matera 70022 Altamura",
    "sg:city":"Altamura",
    "sg:classifiers":[
        {
            "category":"Bars & Pubs",
            "subcategory":"Nightclub",
            "type":"Food & Drink"
        }
    ],
    "sg:phone":"+39 080 311 2888",
    "sg:postcode":"70022",
    "sg:province":"Bari",
    "sg:tags":[
        "cake",
        "bread"
    ],
    "sg:website":"http://www.panificiodellago.it",
    "wof:name":"Panificio Del Lago",
    "wof:placetype":"venue"
},
  "geometry": {"coordinates":[16.553595,40.821293],"type":"Point"}
}