{
  "type": "Feature",
  "properties": {
    "iso:country":"IT",
    "sg:address":"00193 Roma",
    "sg:city":"Roma",
    "sg:orig_category":"Non-classified Establishments",
    "sg:phone":"+39 06 6880 6402",
    "sg:postcode":"00193",
    "sg:province":"Roma",
    "wof:name":"Baby Pace",
    "wof:placetype":"venue"
},
  "geometry": {"coordinates":[12.462474,41.904377],"type":"Point"}
}