{
  "type": "Feature",
  "properties": {
    "addr:full":"27058 Voghera Oriolo Pavia 27058",
    "addr:postcode":"27058;27058",
    "iso:country":"IT",
    "sg:address":"27058 Voghera",
    "sg:city":"Oriolo",
    "sg:orig_category":"Petroli, Gas E Combustibili. Termotecnica E Riscaldamento, Apparecchiature E Servizi",
    "sg:phone":"+39 0383 49227",
    "sg:postcode":"27058",
    "sg:province":"Pavia",
    "wof:name":"Cooperativa Di Consumo Fra Ferrovieri Scrl",
    "wof:placetype":"venue"
},
  "geometry": {"coordinates":[9.013882637,45.0133972168],"type":"Point"}
}