{
  "type": "Feature",
  "properties": {
    "iso:country":"IT",
    "sg:address":"Via Alberazzo 870 47039 Savignano Sul Rubicone",
    "sg:city":"Savignano sul Rubicone",
    "sg:orig_category":"Soles, Heels",
    "sg:phone":"+39 0541 932886",
    "sg:postcode":"47039",
    "sg:province":"Forl\u00ec-Cesena",
    "wof:name":"Tacchificio Zanzani Srl",
    "wof:placetype":"venue"
},
  "geometry": {"coordinates":[12.415275,44.092087],"type":"Point"}
}