{
  "type": "Feature",
  "properties": {
    "iso:country":"IT",
    "sg:address":"36010 Carr\u00e8",
    "sg:classifiers":[
        {
            "category":"Building & Trades",
            "subcategory":"Construction",
            "type":"Services"
        }
    ],
    "sg:phone":"+39 0445 315149",
    "sg:postcode":"36010",
    "sg:province":"Vicenza",
    "sg:tags":[
        "industry",
        "work",
        "plastic"
    ],
    "sg:website":"http://www.dbmengineering.it",
    "wof:name":"Dbm Engineering Snc",
    "wof:placetype":"venue"
},
  "geometry": {"coordinates":[11.5301580429,45.7341117859],"type":"Point"}
}