{
  "type": "Feature",
  "properties": {
    "addr:full":"40126 Bologna Bologna Bologna 40126",
    "addr:postcode":"40126;40126",
    "iso:country":"IT",
    "sg:address":"40126 Bologna",
    "sg:city":"Bologna",
    "sg:orig_category":"Centri Di Estetica E Cosmesi E Servizi",
    "sg:phone":"+39 051 233951",
    "sg:postcode":"40126",
    "sg:province":"Bologna",
    "wof:name":"Body Bag",
    "wof:placetype":"venue"
},
  "geometry": {"coordinates":[11.348095,44.49781],"type":"Point"}
}