{
  "type": "Feature",
  "properties": {
    "iso:country":"IT",
    "sg:address":"Via Padana Superiore 1 25046 Cazzago San Martino",
    "sg:city":"Cazzago San Martino",
    "sg:classifiers":[
        {
            "category":"Retail",
            "subcategory":"Storage",
            "type":"Services"
        }
    ],
    "sg:phone":"+39 030 725012",
    "sg:postcode":"25046",
    "sg:province":"Brescia",
    "sg:tags":[
        "equipment",
        "conveying",
        "automation",
        "system",
        "storehouse"
    ],
    "sg:website":"www.officineminelli.it",
    "wof:name":"Minelli Officine Srl",
    "wof:placetype":"venue"
},
  "geometry": {"coordinates":[10.108301,45.552891],"type":"Point"}
}