{
  "type": "Feature",
  "properties": {
    "iso:country":"IT",
    "sg:address":"20095 Cusano Milanino",
    "sg:city":"Cusano Milanino",
    "sg:orig_category":"Biancheria, Telerie E Coperte",
    "sg:phone":"+39 02 619 2262",
    "sg:postcode":"20095",
    "sg:province":"Milano",
    "wof:name":"Fiorditela Snc Di Palermo A. & Ghezzi M.",
    "wof:placetype":"venue"
},
  "geometry": {"coordinates":[9.181095,45.550259],"type":"Point"}
}