{
  "type": "Feature",
  "properties": {
    "addr:full":"31100 Treviso Treviso Treviso 31100",
    "addr:postcode":"31100;31100",
    "iso:country":"IT",
    "sg:address":"31100 Treviso",
    "sg:city":"Treviso",
    "sg:orig_category":"Servizi Ausiliari Dei Mezzi Di Trasporto",
    "sg:phone":"+39 0422 55370",
    "sg:postcode":"31100",
    "sg:province":"Treviso",
    "sg:website":"http://www.agenziagobbo.it",
    "wof:name":"Agenzia Gobbo Snc",
    "wof:placetype":"venue"
},
  "geometry": {"coordinates":[12.150708,45.638901],"type":"Point"}
}