{
  "type": "Feature",
  "properties": {
    "iso:country":"IT",
    "sg:address":"44022 Comacchio",
    "sg:city":"Comacchio",
    "sg:orig_category":"Metalli E Leghe",
    "sg:phone":"+39 0533 382804",
    "sg:postcode":"44022",
    "sg:province":"Ferrara",
    "wof:name":"Csa Srl Comacchio Servizi Ambientali",
    "wof:placetype":"venue"
},
  "geometry": {"coordinates":[12.247256279,44.5990600586],"type":"Point"}
}