{
  "type": "Feature",
  "properties": {
    "addr:full":"36051 Creazzo Creazzo Vicenza 36051",
    "addr:postcode":"36051;36051",
    "iso:country":"IT",
    "sg:address":"36051 Creazzo",
    "sg:city":"Creazzo",
    "sg:orig_category":"Manufacturers: Prefabbricati",
    "sg:phone":"+39 0444 340133",
    "sg:postcode":"36051",
    "sg:province":"Vicenza",
    "sg:website":"http://www.paginegialle.it/siaf-01",
    "wof:name":"S.i.a.f. Di Pegoraro Italo & C. Snc",
    "wof:placetype":"venue"
},
  "geometry": {"coordinates":[11.49113,45.532654],"type":"Point"}
}