{
  "type": "Feature",
  "properties": {
    "iso:country":"IT",
    "sg:address":"20127 Milano",
    "sg:city":"Milano",
    "sg:orig_category":"Editoria",
    "sg:phone":"+39 02 287 1290",
    "sg:postcode":"20127",
    "sg:province":"Milano",
    "wof:name":"Bomba Cosimo Damiano",
    "wof:placetype":"venue"
},
  "geometry": {"coordinates":[9.220515,45.494762],"type":"Point"}
}