{
  "type": "Feature",
  "properties": {
    "iso:country":"IT",
    "sg:address":"Via Mazzel 20 21012 Cassano Magnago",
    "sg:city":"Cassano Magnago",
    "sg:classifiers":[
        {
            "category":"Home & Garden",
            "subcategory":"Building Materials",
            "type":"Retail Goods"
        }
    ],
    "sg:phone":"+39 0331 200576",
    "sg:postcode":"21012",
    "sg:province":"Varese",
    "sg:tags":[
        "machine",
        "workshop",
        "accessory"
    ],
    "sg:website":"www.viemme-macchineutensili.it",
    "wof:name":"Viemme Macc.ut. Srl",
    "wof:placetype":"venue"
},
  "geometry": {"coordinates":[8.820482,45.677296],"type":"Point"}
}