{
  "type": "Feature",
  "properties": {
    "addr:full":"20098 San Giuliano Milanese San Giuliano Milanese Milano 20098",
    "addr:housenumber":"20098",
    "addr:postcode":"20098",
    "addr:street":"San",
    "iso:country":"IT",
    "sg:address":"20098 San Giuliano Milanese",
    "sg:city":"San Giuliano Milanese",
    "sg:classifiers":[
        {
            "category":"Professional",
            "type":"Services"
        }
    ],
    "sg:phone":"+39 02 984 1626",
    "sg:postcode":"20098",
    "sg:province":"Milano",
    "sg:tags":[
        "activities",
        "supply",
        "commercial",
        "artisan",
        "supplies",
        "accommodation"
    ],
    "wof:name":"Piro Gas Srl",
    "wof:placetype":"venue"
},
  "geometry": {"coordinates":[9.291302,45.397369],"type":"Point"}
}