{
  "type": "Feature",
  "properties": {
    "iso:country":"IT",
    "sg:address":"20033 Desio",
    "sg:city":"Desio",
    "sg:orig_category":"Apparecchiature E Sistemi Per Magazzinaggio E Movimentazione",
    "sg:phone":"+39 036 230 1325",
    "sg:postcode":"20033",
    "sg:province":"Milano",
    "wof:name":"G.e.a.m. Snc",
    "wof:placetype":"venue"
},
  "geometry": {"coordinates":[9.16043,45.597851],"type":"Point"}
}