{
  "type": "Feature",
  "properties": {
    "iso:country":"IT",
    "sg:address":"59100 Prato",
    "sg:city":"Prato",
    "sg:orig_category":"Agenzie Viaggi E Turismo",
    "sg:phone":"+39 0574 38074",
    "sg:postcode":"59100",
    "sg:province":"Prato",
    "wof:name":"Week End A Firenze Srl",
    "wof:placetype":"venue"
},
  "geometry": {"coordinates":[11.060285,43.876511],"type":"Point"}
}