{
  "type": "Feature",
  "properties": {
    "iso:country":"IT",
    "sg:address":"64020 Bellante",
    "sg:city":"Bellante",
    "sg:orig_category":"Cartotecnica E Servizi. Articoli Per Imballaggio E Confezionamento",
    "sg:phone":"+39 0861 610525",
    "sg:postcode":"64020",
    "sg:province":"Teramo",
    "wof:name":"Paper's World Srl",
    "wof:placetype":"venue"
},
  "geometry": {"coordinates":[13.838299,42.706512],"type":"Point"}
}