{
  "type": "Feature",
  "properties": {
    "addr:full":"Via Palera 50 10040 Leini' Torino 10040",
    "addr:housenumber":"50",
    "addr:postcode":"10040 leini;10040",
    "addr:street":"Via Palera",
    "iso:country":"IT",
    "sg:address":"Via Palera 50 10040 Leini'",
    "sg:classifiers":[
        {
            "category":"Real Estate",
            "subcategory":"Real Estate Agent",
            "type":"Services"
        }
    ],
    "sg:phone":"+39 011 998 8733",
    "sg:postcode":"10040",
    "sg:province":"Torino",
    "sg:tags":[
        "lacquer"
    ],
    "sg:website":"www.verplast.net",
    "wof:name":"Ver Plast Srl",
    "wof:placetype":"venue"
},
  "geometry": {"coordinates":[7.722423,45.17696],"type":"Point"}
}