{
  "type": "Feature",
  "properties": {
    "iso:country":"IT",
    "sg:address":"41100 Modena",
    "sg:city":"Modena",
    "sg:orig_category":"Autobus, Filobus E Minibus",
    "sg:phone":"+39 059 250360",
    "sg:postcode":"41100",
    "sg:province":"Modena",
    "sg:website":"http://www.autodromo.it",
    "wof:name":"Carrozzeria Autodromo Modena Soc.coop.r.l.",
    "wof:placetype":"venue"
},
  "geometry": {"coordinates":[10.958122,44.652386],"type":"Point"}
}