{
  "type": "Feature",
  "properties": {
    "iso:country":"IT",
    "sg:address":"90124 Palermo",
    "sg:city":"Palermo",
    "sg:orig_category":"Agricoltura, Orticoltura E Floricoltura. Articoli Da Regalo",
    "sg:phone":"+39 091 630 3210",
    "sg:postcode":"90124",
    "sg:province":"Palermo",
    "wof:name":"Vivai La Franca Filippo Srl",
    "wof:placetype":"venue"
},
  "geometry": {"coordinates":[13.400867,38.08424],"type":"Point"}
}