{
  "type": "Feature",
  "properties": {
    "iso:country":"IT",
    "sg:address":"20026 Novate Milanese",
    "sg:city":"Novate Milanese",
    "sg:orig_category":"Scuole E Servizi Scolastici. Ricerca, Selezione E Formazione Del Personale. Pubblica Amministrazione",
    "sg:phone":"+39 02 356 4662",
    "sg:postcode":"20026",
    "sg:province":"Milano",
    "wof:name":"Comune Di Novate Milanese",
    "wof:placetype":"venue"
},
  "geometry": {"coordinates":[9.134186,45.530979],"type":"Point"}
}