{
  "type": "Feature",
  "properties": {
    "addr:full":"Corso Telesio 17, 87100 Cosenza, Cs Cosenza Cosenza 87100",
    "addr:housenumber":"17",
    "addr:postcode":"87100;87100",
    "addr:street":"Corso Telesio",
    "iso:country":"IT",
    "sg:address":"Corso Telesio 17, 87100 Cosenza, Cs",
    "sg:city":"Cosenza",
    "sg:classifiers":[
        {
            "category":"Banks & Credit Unions",
            "subcategory":"Bank",
            "type":"Services"
        }
    ],
    "sg:postcode":"87100",
    "sg:province":"Cosenza",
    "wof:name":"Cassa Di Risparmio Di Calabria E Di Lucania",
    "wof:placetype":"venue"
},
  "geometry": {"coordinates":[16.261314,39.287689],"type":"Point"}
}