{
  "type": "Feature",
  "properties": {
    "addr:full":"26, Strada Della Quaglia 10026 Santena Santena Torino 10026",
    "addr:postcode":"10026;10026",
    "addr:street":"Strada Della Quaglia",
    "iso:country":"IT",
    "sg:address":"26, Strada Della Quaglia 10026 Santena",
    "sg:city":"Santena",
    "sg:classifiers":[
        {
            "category":"Wholesale",
            "subcategory":"Drugs",
            "type":"Manufacturing & Wholesale Goods"
        }
    ],
    "sg:phone":"+39 011 945 5511",
    "sg:postcode":"10026",
    "sg:province":"Torino",
    "sg:tags":[
        "chemical",
        "pharmaceutical"
    ],
    "wof:name":"Sintesi & Ricerca S.p.a.",
    "wof:placetype":"venue"
},
  "geometry": {"coordinates":[7.686619,45.07056],"type":"Point"}
}