{
  "type": "Feature",
  "properties": {
    "iso:country":"IT",
    "sg:address":"50135 Firenze",
    "sg:city":"Firenze",
    "sg:orig_category":"Autoaccessori - Commercio",
    "sg:phone":"+39 055 613827",
    "sg:postcode":"50135",
    "sg:province":"Firenze",
    "wof:name":"Romano Roberto",
    "wof:placetype":"venue"
},
  "geometry": {"coordinates":[11.298026,43.77993],"type":"Point"}
}