{
  "type": "Feature",
  "properties": {
    "addr:full":"00161 Roma Roma Roma 00161",
    "addr:postcode":"00161;00161",
    "iso:country":"IT",
    "sg:address":"00161 Roma",
    "sg:city":"Roma",
    "sg:orig_category":"Articoli Medico-sanitari Ed Ortopedici. Impianti, Attrezzature E Forniture Sanitarie Ed Ospedaliere",
    "sg:postcode":"00161",
    "sg:province":"Roma",
    "wof:name":"Vanni Stefano",
    "wof:placetype":"venue"
},
  "geometry": {"coordinates":[12.508856,41.908951],"type":"Point"}
}