{
  "type": "Feature",
  "properties": {
    "iso:country":"IT",
    "sg:address":"16159 Genova",
    "sg:city":"Genova",
    "sg:orig_category":"Pubblica Amministrazione",
    "sg:phone":"+39 010 740 4538",
    "sg:postcode":"16159",
    "sg:province":"Genova",
    "wof:name":"Centro Addestramento Polizia Postale",
    "wof:placetype":"venue"
},
  "geometry": {"coordinates":[8.9016332626,44.4441642761],"type":"Point"}
}