{
  "type": "Feature",
  "properties": {
    "iso:country":"IT",
    "sg:address":"20121 Milano",
    "sg:city":"Milano",
    "sg:orig_category":"Non-classified Establishments",
    "sg:phone":"+39 02 659 0763",
    "sg:postcode":"20121",
    "sg:province":"Milano",
    "wof:name":"Corrent Snc Di Neri Angela & C.",
    "wof:placetype":"venue"
},
  "geometry": {"coordinates":[9.1949806213,45.47215271],"type":"Point"}
}