{
  "type": "Feature",
  "properties": {
    "addr:full":"5, Via Colombo 27018 Vidigulfo Vidigulfo Pavia 27018",
    "addr:postcode":"27018;27018",
    "addr:street":"Via Colombo",
    "iso:country":"IT",
    "sg:address":"5, Via Colombo 27018 Vidigulfo",
    "sg:city":"Vidigulfo",
    "sg:classifiers":[
        {
            "category":"Manufacturing",
            "subcategory":"Paper Products",
            "type":"Manufacturing & Wholesale Goods"
        }
    ],
    "sg:phone":"+39 39038269108",
    "sg:postcode":"27018",
    "sg:province":"Pavia",
    "sg:tags":[
        "cardboard"
    ],
    "wof:name":"Topflight Italia (s.p.a.)",
    "wof:placetype":"venue"
},
  "geometry": {"coordinates":[9.2368030548,45.2943305969],"type":"Point"}
}