{
  "type": "Feature",
  "properties": {
    "iso:country":"IT",
    "sg:address":"Via Meucci Antonio 50041 Calenzano",
    "sg:city":"Calenzano",
    "sg:classifiers":[
        {
            "category":"Shopping",
            "type":"Retail Goods"
        }
    ],
    "sg:phone":"+39 055 887 3445",
    "sg:postcode":"50041",
    "sg:province":"Firenze",
    "sg:tags":[
        "finished",
        "-",
        "metallic"
    ],
    "wof:name":"Silo Lorini (s.r.l.)",
    "wof:placetype":"venue"
},
  "geometry": {"coordinates":[11.2085819244,43.8370933533],"type":"Point"}
}