{
  "type": "Feature",
  "properties": {
    "addr:full":"10040 Leini' Torino 10040",
    "addr:housenumber":"10040",
    "addr:postcode":"10040",
    "addr:street":"Leini ' Torino",
    "iso:country":"IT",
    "sg:address":"10040 Leini'",
    "sg:orig_category":"Macchine Utensili E Impianti",
    "sg:phone":"+39 011 998 3119",
    "sg:postcode":"10040",
    "sg:province":"Torino",
    "wof:name":"Tech-in-sider",
    "wof:placetype":"venue"
},
  "geometry": {"coordinates":[7.712414,45.169174],"type":"Point"}
}