{
  "type": "Feature",
  "properties": {
    "iso:country":"IT",
    "sg:address":"Via Broggini 12 20122 Milano",
    "sg:city":"Milano",
    "sg:classifiers":[
        {
            "category":"Wholesale",
            "subcategory":"Machinery & Supplies",
            "type":"Manufacturing & Wholesale Goods"
        }
    ],
    "sg:phone":"+39 02 4891 1330",
    "sg:postcode":"20122",
    "sg:province":"Milano",
    "sg:tags":[
        "pin",
        "clevis"
    ],
    "sg:website":"www.balestri.com",
    "wof:name":"Balestri Bulloneria Srl",
    "wof:placetype":"venue"
},
  "geometry": {"coordinates":[9.210919,45.477829],"type":"Point"}
}