{
  "type": "Feature",
  "properties": {
    "iso:country":"IT",
    "sg:address":"10036 Settimo Torinese",
    "sg:city":"Settimo Torinese",
    "sg:orig_category":"Serramenti Ed Infissi. Forniture Industriali Per Prevenzione, Controllo E Sicurezza",
    "sg:phone":"+39 011 895 4000",
    "sg:postcode":"10036",
    "sg:province":"Torino",
    "sg:website":"http://www.potent.it",
    "wof:name":"Potent Srl",
    "wof:placetype":"venue"
},
  "geometry": {"coordinates":[7.750114,45.125469],"type":"Point"}
}