{
  "type": "Feature",
  "properties": {
    "addr:full":"65, Via Milano 25034 Orzinuovi Orzinuovi Brescia 25034",
    "addr:postcode":"25034;25034",
    "addr:street":"Via Milano",
    "iso:country":"IT",
    "sg:address":"65, Via Milano 25034 Orzinuovi",
    "sg:city":"Orzinuovi",
    "sg:classifiers":[
        {
            "category":"Shopping",
            "subcategory":"Clothing, Apparel, & Fashions",
            "type":"Retail Goods"
        }
    ],
    "sg:phone":"+39 39030941358",
    "sg:postcode":"25034",
    "sg:province":"Brescia",
    "sg:tags":[
        "clothes"
    ],
    "wof:name":"Ferrari",
    "wof:placetype":"venue"
},
  "geometry": {"coordinates":[9.903624,45.400555],"type":"Point"}
}