{
  "type": "Feature",
  "properties": {
    "iso:country":"IT",
    "sg:address":"93012 Gela",
    "sg:city":"Gela",
    "sg:orig_category":"Minuterie Metalliche E Ferramenta",
    "sg:phone":"+39 0933 927544",
    "sg:postcode":"93012",
    "sg:province":"Caltanissetta",
    "wof:name":"Sudmontaggi Srl",
    "wof:placetype":"venue"
},
  "geometry": {"coordinates":[14.3093757629,37.0850296021],"type":"Point"}
}