{
  "type": "Feature",
  "properties": {
    "iso:country":"IT",
    "sg:address":"60122 Ancona",
    "sg:city":"Ancona",
    "sg:orig_category":"Agenzie Marittime",
    "sg:phone":"+39 071 501011",
    "sg:postcode":"60122",
    "sg:province":"Ancona",
    "wof:name":"Humbert Kane Snc",
    "wof:placetype":"venue"
},
  "geometry": {"coordinates":[13.508414,43.616444],"type":"Point"}
}