{
  "type": "Feature",
  "properties": {
    "addr:full":"20022 Castano Primo Castano Primo Milano 20022",
    "addr:postcode":"20022;20022",
    "iso:country":"IT",
    "sg:address":"20022 Castano Primo",
    "sg:city":"Castano Primo",
    "sg:orig_category":"Macchine, Impianti Ed Attrezzature Per Abbigliamento E Pelletterie",
    "sg:phone":"+39 0331 899546",
    "sg:postcode":"20022",
    "sg:province":"Milano",
    "wof:name":"Vanoli Fratelli (s.n.c.)",
    "wof:placetype":"venue"
},
  "geometry": {"coordinates":[8.752298,45.540775],"type":"Point"}
}