{
  "type": "Feature",
  "properties": {
    "iso:country":"IT",
    "sg:address":"80035 Nola",
    "sg:city":"Nola",
    "sg:orig_category":"Forniture Per Abbigliamento E Pelletterie",
    "sg:phone":"+39 081 313 3605",
    "sg:postcode":"80035",
    "sg:province":"Napoli",
    "sg:website":"http://www.demarsud.com",
    "wof:name":"Demar Sud Italia Srl",
    "wof:placetype":"venue"
},
  "geometry": {"coordinates":[14.5130968094,40.9334526062],"type":"Point"}
}