{
  "type": "Feature",
  "properties": {
    "iso:country":"IT",
    "sg:address":"20154 Milano",
    "sg:city":"Milano",
    "sg:orig_category":"Servizi Culturali E Per Lo Spettacolo. Cine-foto-ottica",
    "sg:phone":"+39 02 657 2036",
    "sg:postcode":"20154",
    "sg:province":"Milano",
    "wof:name":"Blockbuster Italia S.p.a.",
    "wof:placetype":"venue"
},
  "geometry": {"coordinates":[9.186069,45.481144],"type":"Point"}
}