{
  "type": "Feature",
  "properties": {
    "addr:full":"55100 Lucca Lucca Lucca 55100",
    "addr:postcode":"55100;55100",
    "iso:country":"IT",
    "sg:address":"55100 Lucca",
    "sg:city":"Lucca",
    "sg:orig_category":"Filati E Materie Prime Tessili",
    "sg:phone":"+39 0583 997620",
    "sg:postcode":"55100",
    "sg:province":"Lucca",
    "wof:name":"American & Efird Italia Spa",
    "wof:placetype":"venue"
},
  "geometry": {"coordinates":[10.5388374329,43.8768463135],"type":"Point"}
}