{
  "type": "Feature",
  "properties": {
    "iso:country":"IT",
    "sg:address":"50055 Lastra A Signa",
    "sg:city":"Lastra a Signa",
    "sg:classifiers":[
        {
            "category":"Bars & Pubs",
            "subcategory":"Oxygen Bar",
            "type":"Food & Drink"
        }
    ],
    "sg:phone":"+39 055 872 4448",
    "sg:postcode":"50055",
    "sg:province":"Firenze",
    "sg:tags":[
        "liqueurs",
        "drinks",
        "shopping",
        "wine"
    ],
    "wof:name":"Cantine Bellosguardo Snc",
    "wof:placetype":"venue"
},
  "geometry": {"coordinates":[11.122337,43.769711],"type":"Point"}
}