{
  "type": "Feature",
  "properties": {
    "iso:country":"IT",
    "sg:address":"4, Via Cappuccini 20122 Milano",
    "sg:city":"Milano",
    "sg:classifiers":[
        {
            "category":"Communications",
            "subcategory":"Newspaper",
            "type":"Services"
        }
    ],
    "sg:phone":"+39 02 7600 4875",
    "sg:postcode":"20122",
    "sg:province":"Milano",
    "sg:tags":[
        "advertising"
    ],
    "wof:name":"Miofar S.r.l.",
    "wof:placetype":"venue"
},
  "geometry": {"coordinates":[9.202391,45.470322],"type":"Point"}
}