{
  "type": "Feature",
  "properties": {
    "iso:country":"IT",
    "sg:address":"31010 Ponte Della Priula",
    "sg:city":"Priula",
    "sg:orig_category":"Legno E Semilavorati",
    "sg:phone":"+39 0438 27019",
    "sg:postcode":"31010",
    "sg:province":"Treviso",
    "wof:name":"Forestale Veneta (s.p.a.)",
    "wof:placetype":"venue"
},
  "geometry": {"coordinates":[12.251344,45.82357],"type":"Point"}
}