{
  "type": "Feature",
  "properties": {
    "iso:country":"IT",
    "sg:address":"Vocabolo Mezzo Piano 06073 Corciano",
    "sg:city":"Corciano",
    "sg:classifiers":[
        {
            "category":"Shopping",
            "subcategory":"Crafts & Fabrics",
            "type":"Retail Goods"
        }
    ],
    "sg:phone":"+39 075 697 8477",
    "sg:postcode":"06073",
    "sg:province":"Perugia",
    "wof:name":"Filatura Grifo",
    "wof:placetype":"venue"
},
  "geometry": {"coordinates":[12.3891716003,43.1107025146],"type":"Point"}
}