{
  "type": "Feature",
  "properties": {
    "addr:full":"10136 Torino Torino Torino 10136",
    "addr:postcode":"10136;10136",
    "iso:country":"IT",
    "sg:address":"10136 Torino",
    "sg:city":"Torino",
    "sg:orig_category":"Servizi Per Lo Sport E Il Tempo Libero. Servizi Al Turismo. Acqua, Luce, Gas E Societa' Di Esercizio Pubblico",
    "sg:phone":"+39 011 309 1252",
    "sg:postcode":"10136",
    "sg:province":"Torino",
    "wof:name":"Agrifav S.r.l.",
    "wof:placetype":"venue"
},
  "geometry": {"coordinates":[7.623045,45.048962],"type":"Point"}
}