{
  "type": "Feature",
  "properties": {
    "iso:country":"IT",
    "sg:address":"39040 Castelrotto",
    "sg:city":"Castelrotto",
    "sg:orig_category":"Autonoleggio",
    "sg:phone":"+39 0471 706633",
    "sg:postcode":"39040",
    "sg:province":"Bolzano/Bozen",
    "sg:website":"http://www.silbernagl.it",
    "wof:name":"Silbernagl & Co. Sas",
    "wof:placetype":"venue"
},
  "geometry": {"coordinates":[11.369349,46.497406],"type":"Point"}
}