{
  "type": "Feature",
  "properties": {
    "iso:country":"IT",
    "sg:address":"45, Via Ermes Di Colloredo 33038 San Daniele Del Friuli",
    "sg:city":"San Daniele del Friuli",
    "sg:classifiers":[
        {
            "category":"Shopping",
            "subcategory":"Jewelry",
            "type":"Retail Goods"
        }
    ],
    "sg:phone":"+39 0432 957711",
    "sg:postcode":"33038",
    "sg:province":"Udine",
    "sg:tags":[
        "jewellery"
    ],
    "wof:name":"A.z. Bigiotterie Di Zanutto & C. (s.n.c.)",
    "wof:placetype":"venue"
},
  "geometry": {"coordinates":[12.999522,46.1549],"type":"Point"}
}