{
  "type": "Feature",
  "properties": {
    "addr:full":"910, V. Emilia Ovest 41100 Modena Modena Modena 41100",
    "addr:housenumber":"910",
    "addr:postcode":"41100;41100",
    "addr:street":"V. Emilia Ovest",
    "iso:country":"IT",
    "sg:address":"910, V. Emilia Ovest 41100 Modena",
    "sg:city":"Modena",
    "sg:classifiers":[
        {
            "category":"Wholesale",
            "subcategory":"Machinery & Supplies",
            "type":"Manufacturing & Wholesale Goods"
        }
    ],
    "sg:phone":"+39 39059334345",
    "sg:postcode":"41100",
    "sg:province":"Modena",
    "sg:tags":[
        "-",
        "agriculture",
        "equipment"
    ],
    "sg:website":"http://www.erma-rtmo.it:ws_end: :mark:ws:http://www.paginegialle.it/ermartmospa",
    "wof:name":"Erma-rtmo Spa",
    "wof:placetype":"venue"
},
  "geometry": {"coordinates":[10.879765,44.656029],"type":"Point"}
}