{
  "type": "Feature",
  "properties": {
    "addr:full":"70015 Noci Noci Bari 70015",
    "addr:postcode":"70015;70015",
    "iso:country":"IT",
    "sg:address":"70015 Noci",
    "sg:city":"Noci",
    "sg:orig_category":"Montaggi Industriali",
    "sg:phone":"+39 080 497 7153",
    "sg:postcode":"70015",
    "sg:province":"Bari",
    "wof:name":"So.co.in.system Srl",
    "wof:placetype":"venue"
},
  "geometry": {"coordinates":[17.1248207092,40.7695617676],"type":"Point"}
}