{
  "type": "Feature",
  "properties": {
    "iso:country":"IT",
    "sg:address":"20020 Arese",
    "sg:city":"Arese",
    "sg:orig_category":"Agenzie Ed Enti Turistici. Consulenze Tecniche, Amministrative E Perizie",
    "sg:phone":"+39 02 9358 1477",
    "sg:postcode":"20020",
    "sg:province":"Milano",
    "sg:website":"http://www.informer.it",
    "wof:name":"The Informer Di John Murphy",
    "wof:placetype":"venue"
},
  "geometry": {"coordinates":[9.07469,45.553246],"type":"Point"}
}