{
  "type": "Feature",
  "properties": {
    "iso:country":"IT",
    "sg:address":"20011 Corbetta",
    "sg:city":"Corbetta",
    "sg:orig_category":"Zootecnia E Pesca, Allevamento Piccoli Animali. Animali Domestici",
    "sg:phone":"+39 02 977 8697",
    "sg:postcode":"20011",
    "sg:province":"Milano",
    "wof:name":"Allevamento Il Quadrifoglio",
    "wof:placetype":"venue"
},
  "geometry": {"coordinates":[9.147903,45.476032],"type":"Point"}
}