{
  "type": "Feature",
  "properties": {
    "iso:country":"IT",
    "sg:address":"20/22, Via Dell' Artigianato 31020 San Zenone Degli Ezzelini",
    "sg:city":"San Zenone degli Ezzelini",
    "sg:classifiers":[
        {
            "category":"Manufacturing",
            "subcategory":"Wood Products",
            "type":"Manufacturing & Wholesale Goods"
        }
    ],
    "sg:phone":"+39 0423 968692",
    "sg:postcode":"31020",
    "sg:province":"Treviso",
    "sg:tags":[
        "furniture"
    ],
    "wof:name":"Agostini Paolo S.r.l.",
    "wof:placetype":"venue"
},
  "geometry": {"coordinates":[11.851788,45.777599],"type":"Point"}
}