{
  "type": "Feature",
  "properties": {
    "iso:country":"IT",
    "sg:address":"Via Roma 12; Alliste; 73040",
    "sg:city":"Alliste",
    "sg:classifiers":[
        {
            "category":"Banks & Credit Unions",
            "subcategory":"Bank",
            "type":"Services"
        }
    ],
    "sg:phone":"+39 0833 584099",
    "sg:postcode":"73040",
    "sg:province":"Lecce",
    "wof:name":"Banco Ambrosiano, Veneto Spa",
    "wof:placetype":"venue"
},
  "geometry": {"coordinates":[18.124052,39.971764],"type":"Point"}
}