{
  "type": "Feature",
  "properties": {
    "addr:full":"Via Garibaldi 102/is/3; Messina; 98100",
    "addr:housenumber":"102 / is / 3",
    "addr:postcode":"98100",
    "addr:street":"Via Garibaldi",
    "iso:country":"IT",
    "sg:address":"Via Garibaldi 102/is/3; Messina; 98100",
    "sg:classifiers":[
        {
            "category":"Banks & Credit Unions",
            "subcategory":"Bank",
            "type":"Services"
        }
    ],
    "sg:phone":"+39 090 77601",
    "wof:name":"Banco Di Sicilia",
    "wof:placetype":"venue"
},
  "geometry": {"coordinates":[15.556606,38.189789],"type":"Point"}
}