{
  "type": "Feature",
  "properties": {
    "iso:country":"IT",
    "sg:address":"151, Via Statale N.12 41036 Medolla",
    "sg:city":"Medolla",
    "sg:classifiers":[
        {
            "category":"Wholesale",
            "subcategory":"Medical Equipment & Supplies",
            "type":"Manufacturing & Wholesale Goods"
        }
    ],
    "sg:phone":"+39 39053551360",
    "sg:postcode":"41036",
    "sg:province":"Modena",
    "sg:tags":[
        "-",
        "health",
        "instrument"
    ],
    "wof:name":"Bloodline (s.p.a.)",
    "wof:placetype":"venue"
},
  "geometry": {"coordinates":[11.056199,44.839874],"type":"Point"}
}