{
  "type": "Feature",
  "properties": {
    "iso:country":"IT",
    "sg:address":"70037 Ruvo Di Puglia",
    "sg:city":"Ruvo di Puglia",
    "sg:orig_category":"Servizi E Lavori Per Agricoltura E Zootecnia. Servizi E Lavori Industria Chimica. Servizi Ausiliari Di Analisi, Controllo E Ricerca",
    "sg:phone":"+39 080 360 3001",
    "sg:postcode":"70037",
    "sg:province":"Bari",
    "wof:name":"Bio Service S.r.l.",
    "wof:placetype":"venue"
},
  "geometry": {"coordinates":[16.464146,41.064796],"type":"Point"}
}