{
  "type": "Feature",
  "properties": {
    "addr:full":"80147 Napoli Napoli Napoli 80147",
    "addr:postcode":"80147;80147",
    "iso:country":"IT",
    "sg:address":"80147 Napoli",
    "sg:city":"Napoli",
    "sg:classifiers":[
        {
            "category":"Health Services",
            "subcategory":"Health Practitioner",
            "type":"Services"
        }
    ],
    "sg:phone":"+39 081 596 5610",
    "sg:postcode":"80147",
    "sg:province":"Napoli",
    "sg:tags":[
        "medici"
    ],
    "wof:name":"Capasso Immacolata",
    "wof:placetype":"venue"
},
  "geometry": {"coordinates":[14.32101,40.853901],"type":"Point"}
}