{
  "type": "Feature",
  "properties": {
    "addr:full":"Corso Vittorio Emanuele Ii 99 10128 Torino Torino Torino 10128",
    "addr:housenumber":"99",
    "addr:postcode":"10128;10128",
    "addr:street":"Corso Vittorio Emanuele Ii",
    "iso:country":"IT",
    "sg:address":"Corso Vittorio Emanuele Ii 99 10128 Torino",
    "sg:city":"Torino",
    "sg:orig_category":"Ceiling Panels Of Stainless Steel",
    "sg:phone":"+39 011 560 7511",
    "sg:postcode":"10128",
    "sg:province":"Torino",
    "sg:website":"www.isolpack.com",
    "wof:name":"Isolpack Spa",
    "wof:placetype":"venue"
},
  "geometry": {"coordinates":[7.668016,45.06646],"type":"Point"}
}