{
  "type": "Feature",
  "properties": {
    "iso:country":"IT",
    "sg:address":"Via Moia, 78/82 20047 Brugherio",
    "sg:city":"Brugherio",
    "sg:classifiers":[
        {
            "category":"Home & Garden",
            "subcategory":"Building Materials",
            "type":"Retail Goods"
        }
    ],
    "sg:phone":"+39 039 287 3310",
    "sg:postcode":"20047",
    "sg:province":"Milano",
    "sg:tags":[
        "steel",
        "base"
    ],
    "sg:website":"www.fadflange.it",
    "wof:name":"Fad Flange Acciaio E Derivati Spa",
    "wof:placetype":"venue"
},
  "geometry": {"coordinates":[9.282034,45.556946],"type":"Point"}
}