{
  "type": "Feature",
  "properties": {
    "iso:country":"IT",
    "sg:address":"20123 Milano",
    "sg:city":"Milano",
    "sg:orig_category":"Servizi Per Aziende, Manifestazioni E Supporto Agli Scambi Commerciali. Ambasciate Ed Enti Internazionali",
    "sg:phone":"+39 02 880 0991",
    "sg:postcode":"20123",
    "sg:province":"Milano",
    "wof:name":"Enterprise Ireland-ufficio Irlandese Per Il Commercio E La Tecnologia",
    "wof:placetype":"venue"
},
  "geometry": {"coordinates":[9.18503,45.465656],"type":"Point"}
}