{
  "type": "Feature",
  "properties": {
    "addr:full":"Ctr Schettino 95047 Paterno' Catania 95047",
    "addr:postcode":"95047;95047",
    "addr:street":"Paterno ' Catania",
    "iso:country":"IT",
    "sg:address":"Ctr Schettino 95047 Paterno'",
    "sg:classifiers":[
        {
            "category":"Food & Beverages",
            "subcategory":"Chocolate",
            "type":"Retail Goods"
        }
    ],
    "sg:phone":"+39 095 622675",
    "sg:postcode":"95047",
    "sg:province":"Catania",
    "sg:tags":[
        "export"
    ],
    "wof:name":"Spinagrumi Srl",
    "wof:placetype":"venue"
},
  "geometry": {"coordinates":[14.9093093872,37.5648422241],"type":"Point"}
}