{
  "type": "Feature",
  "properties": {
    "iso:country":"IT",
    "sg:address":"37139 San Massimo All'adige",
    "sg:orig_category":"Automobili E Mezzi Di Trasporto",
    "sg:phone":"+39 045 890 0045",
    "sg:postcode":"37139",
    "sg:province":"Verona",
    "wof:name":"Dolci Sergio",
    "wof:placetype":"venue"
},
  "geometry": {"coordinates":[10.945898,45.43906],"type":"Point"}
}