{
  "type": "Feature",
  "properties": {
    "iso:country":"IT",
    "sg:address":"00147 Roma",
    "sg:city":"Roma",
    "sg:orig_category":"Servizi Per Aziende, Manifestazioni E Supporto Agli Scambi Commerciali",
    "sg:phone":"+39 0651781",
    "sg:postcode":"00147",
    "sg:province":"Roma",
    "sg:website":"http://www.fieradiroma.it",
    "wof:name":"Fiera Di Roma",
    "wof:placetype":"venue"
},
  "geometry": {"coordinates":[12.496833,41.856121],"type":"Point"}
}