{
  "type": "Feature",
  "properties": {
    "addr:full":"2, Via Inghilterra 46042 Castel Goffredo Castel Goffredo Mantova 46042",
    "addr:postcode":"46042;46042",
    "addr:street":"Via Inghilterra;Goffredo",
    "iso:country":"IT",
    "sg:address":"2, Via Inghilterra 46042 Castel Goffredo",
    "sg:city":"Castel Goffredo",
    "sg:classifiers":[
        {
            "category":"Communications",
            "subcategory":"Television Station",
            "type":"Services"
        }
    ],
    "sg:phone":"+39 39037677521",
    "sg:postcode":"46042",
    "sg:province":"Mantova",
    "sg:tags":[
        "equipment",
        "optical",
        "instrument"
    ],
    "wof:name":"Coemar S.p.a.",
    "wof:placetype":"venue"
},
  "geometry": {"coordinates":[10.476684,45.283997],"type":"Point"}
}