{
  "type": "Feature",
  "properties": {
    "iso:country":"IT",
    "sg:address":"Contrada Pandi Zona Ind. 72100 Brindisi",
    "sg:city":"Brindisi",
    "sg:classifiers":[
        {
            "category":"Real Estate",
            "subcategory":"Surveying",
            "type":"Services"
        }
    ],
    "sg:phone":"+39 0831 573064",
    "sg:postcode":"72100",
    "sg:province":"Brindisi",
    "sg:tags":[
        "equipment",
        "material",
        "good",
        "-",
        "handling"
    ],
    "wof:name":"Legnobotti (s.r.l.)",
    "wof:placetype":"venue"
},
  "geometry": {"coordinates":[17.942587,40.66259],"type":"Point"}
}