{
  "type": "Feature",
  "properties": {
    "addr:full":"98100 Messina ME",
    "addr:postcode":"98100",
    "iso:country":"IT",
    "sg:address":"98100 Messina",
    "sg:orig_category":"Macchine Utensili E Impianti",
    "sg:phone":"+39 800 737 069",
    "sg:province":"ME",
    "wof:name":"La Splendente",
    "wof:placetype":"venue"
},
  "geometry": {"coordinates":[15.552417,38.19001],"type":"Point"}
}