{
  "type": "Feature",
  "properties": {
    "iso:country":"IT",
    "sg:address":"31036 Istrana",
    "sg:city":"Istrana",
    "sg:orig_category":"Motori Ed Organi Di Trasmissione",
    "sg:phone":"+39 0422 832367",
    "sg:postcode":"31036",
    "sg:province":"Treviso",
    "wof:name":"O.m.g. Di Michieletto Giovanni",
    "wof:placetype":"venue"
},
  "geometry": {"coordinates":[12.3100004196,45.6204795837],"type":"Point"}
}