{
  "type": "Feature",
  "properties": {
    "iso:country":"IT",
    "sg:address":"20090 Trezzano Sul Naviglio",
    "sg:city":"Trezzano sul Naviglio",
    "sg:orig_category":"Cine-foto-ottica",
    "sg:phone":"+39 02 445 3120",
    "sg:postcode":"20090",
    "sg:province":"Milano",
    "wof:name":"Fraco S.a.s. Di Reina Fulvio & C.",
    "wof:placetype":"venue"
},
  "geometry": {"coordinates":[9.068303,45.427811],"type":"Point"}
}