{
  "type": "Feature",
  "properties": {
    "iso:country":"IT",
    "sg:address":"Via Pinerolo 14 22063 Cantu'",
    "sg:classifiers":[
        {
            "category":"Home & Garden",
            "subcategory":"Home Furnishings",
            "type":"Retail Goods"
        }
    ],
    "sg:phone":"+39 031 713745",
    "sg:postcode":"22063",
    "sg:province":"Como",
    "sg:tags":[
        "interior",
        "decoration"
    ],
    "wof:name":"Fmc Snc",
    "wof:placetype":"venue"
},
  "geometry": {"coordinates":[9.136381,45.727844],"type":"Point"}
}