{
  "type": "Feature",
  "properties": {
    "addr:full":"25038 Rovato Rovato Brescia 25038",
    "addr:postcode":"25038;25038",
    "iso:country":"IT",
    "sg:address":"25038 Rovato",
    "sg:city":"Rovato",
    "sg:orig_category":"Profumerie",
    "sg:phone":"+39 030 770 3265",
    "sg:postcode":"25038",
    "sg:province":"Brescia",
    "sg:website":"http://www.dfn.it/profumerievezzoli",
    "wof:name":"Profumerie Vezzoli Srl",
    "wof:placetype":"venue"
},
  "geometry": {"coordinates":[10.0476074219,45.5694580078],"type":"Point"}
}