{
  "type": "Feature",
  "properties": {
    "iso:country":"IT",
    "sg:address":"2, Via Michelangelo Buonarroti 21053 Castellanza",
    "sg:city":"Castellanza",
    "sg:classifiers":[
        {
            "category":"Professional",
            "subcategory":"Engineering",
            "type":"Services"
        }
    ],
    "sg:phone":"+39 0331 500407",
    "sg:postcode":"21053",
    "sg:province":"Varese",
    "sg:tags":[
        "machine",
        "-",
        "mechanical"
    ],
    "wof:name":"Mobert (s.r.l.)",
    "wof:placetype":"venue"
},
  "geometry": {"coordinates":[8.914983,45.613041],"type":"Point"}
}