{
  "type": "Feature",
  "properties": {
    "iso:country":"IT",
    "sg:address":"36030 Sarcedo",
    "sg:city":"Sarcedo",
    "sg:orig_category":"Utensili Meccanici E Materiali",
    "sg:phone":"+39 0445 380473",
    "sg:postcode":"36030",
    "sg:province":"Vicenza",
    "wof:name":"Eurostampi Srl",
    "wof:placetype":"venue"
},
  "geometry": {"coordinates":[11.511846,45.706509],"type":"Point"}
}