{
  "type": "Feature",
  "properties": {
    "iso:country":"IT",
    "sg:address":"00128 Roma",
    "sg:city":"Roma",
    "sg:classifiers":[
        {
            "category":"Professional",
            "type":"Services"
        }
    ],
    "sg:phone":"+39 06 5065 3260",
    "sg:postcode":"00128",
    "sg:province":"Roma",
    "sg:tags":[
        "auxiliary",
        "entertainment",
        "premises",
        "related",
        "catering",
        "public",
        "restaurants"
    ],
    "wof:name":"3m Srl",
    "wof:placetype":"venue"
},
  "geometry": {"coordinates":[12.476667,41.766666],"type":"Point"}
}