{
  "type": "Feature",
  "properties": {
    "addr:full":"19, Via Innocenzo Xi 22100 Como Como Como 22100",
    "addr:postcode":"22100;22100",
    "addr:street":"Via Innocenzo Xi",
    "iso:country":"IT",
    "sg:address":"19, Via Innocenzo Xi 22100 Como",
    "sg:city":"Como",
    "sg:classifiers":[
        {
            "category":"Shopping",
            "subcategory":"Clothing, Apparel, & Fashions",
            "type":"Retail Goods"
        }
    ],
    "sg:phone":"+39 39031261722",
    "sg:postcode":"22100",
    "sg:province":"Como",
    "sg:tags":[
        "clothes"
    ],
    "wof:name":"Bragard Italia (s.r.l.)",
    "wof:placetype":"venue"
},
  "geometry": {"coordinates":[9.077852,45.806911],"type":"Point"}
}