{
  "type": "Feature",
  "properties": {
    "iso:country":"IT",
    "sg:address":"43010 Polesine Parmense",
    "sg:city":"Polesine Parmense",
    "sg:orig_category":"Porte",
    "sg:phone":"+39 0574 98110",
    "sg:postcode":"43010",
    "sg:province":"Parma",
    "wof:name":"Zambelli Carlo",
    "wof:placetype":"venue"
},
  "geometry": {"coordinates":[10.0884628296,45.0173721313],"type":"Point"}
}