{
  "type": "Feature",
  "properties": {
    "iso:country":"IT",
    "sg:address":"88837 Petilia Policastro",
    "sg:city":"Petilia Policastro",
    "sg:orig_category":"Abbigliamento Esterno, Maglierie E Pelliccerie",
    "sg:phone":"+39 0962 434890",
    "sg:postcode":"88837",
    "sg:province":"Crotone",
    "wof:name":"Framar Sas Di Fico Francesco Salvatore",
    "wof:placetype":"venue"
},
  "geometry": {"coordinates":[16.782305,39.116055],"type":"Point"}
}