{
  "type": "Feature",
  "properties": {
    "iso:country":"IT",
    "sg:address":"25, Via Buozzi Bruno 40013 Castel Maggiore",
    "sg:city":"Castel Maggiore",
    "sg:classifiers":[
        {
            "category":"Manufacturing",
            "subcategory":"Motor Vehicles & Parts",
            "type":"Manufacturing & Wholesale Goods"
        }
    ],
    "sg:phone":"+39 39051700759",
    "sg:postcode":"40013",
    "sg:province":"Bologna",
    "sg:tags":[
        "engine"
    ],
    "wof:name":"Pulsar (s.r.l.)",
    "wof:placetype":"venue"
},
  "geometry": {"coordinates":[11.365514,44.558628],"type":"Point"}
}