{
  "type": "Feature",
  "properties": {
    "iso:country":"IT",
    "sg:address":"20124 Milano",
    "sg:city":"Milano",
    "sg:orig_category":"Sport - Articoli E Forniture",
    "sg:phone":"+39 02 2952 2027",
    "sg:postcode":"20124",
    "sg:province":"Milano",
    "sg:website":"http://www.lamontagnasport.com",
    "wof:name":"La Montagna Sport Sas",
    "wof:placetype":"venue"
},
  "geometry": {"coordinates":[9.203329,45.479156],"type":"Point"}
}