{
  "type": "Feature",
  "properties": {
    "addr:full":"1, Via Del Tappezziere 40138 Bologna Bologna Bologna 40138",
    "addr:postcode":"40138;40138",
    "addr:street":"Via Del Tappezziere",
    "iso:country":"IT",
    "sg:address":"1, Via Del Tappezziere 40138 Bologna",
    "sg:city":"Bologna",
    "sg:classifiers":[
        {
            "category":"Professional",
            "subcategory":"Printing & Photocopies",
            "type":"Services"
        }
    ],
    "sg:phone":"+39 39051530055",
    "sg:postcode":"40138",
    "sg:province":"Bologna",
    "wof:name":"Sa.bo Satellite Bologna S.r.l.",
    "wof:placetype":"venue"
},
  "geometry": {"coordinates":[11.4119691849,44.5027275085],"type":"Point"}
}