{
  "type": "Feature",
  "properties": {
    "iso:country":"IT",
    "sg:address":"20017 Rho",
    "sg:city":"Rho",
    "sg:orig_category":"Lavorazioni Meccaniche E Servizi",
    "sg:phone":"+39 02 930 8017",
    "sg:postcode":"20017",
    "sg:province":"Milano",
    "sg:website":"http://www.dav.it",
    "wof:name":"Dav. Srl",
    "wof:placetype":"venue"
},
  "geometry": {"coordinates":[9.207926,45.473534],"type":"Point"}
}