{
  "type": "Feature",
  "properties": {
    "iso:country":"IT",
    "sg:address":"29017 Fiorenzuola D'arda",
    "sg:orig_category":"Alluminio E Leghe",
    "sg:phone":"+39 0523 943228",
    "sg:postcode":"29017",
    "sg:province":"Piacenza",
    "wof:name":"S.a.f. Srl",
    "wof:placetype":"venue"
},
  "geometry": {"coordinates":[9.910099,44.925072],"type":"Point"}
}