{
  "type": "Feature",
  "properties": {
    "addr:full":"20040 Cornate D'adda Colnago Milano 20040",
    "addr:postcode":"20040;20040",
    "addr:street":"D'Adda Colnago",
    "iso:country":"IT",
    "sg:address":"20040 Cornate D'adda",
    "sg:city":"Colnago",
    "sg:orig_category":"Informatica - Consulenza E Servizi. Automazione E Macchine Per Ufficio. Servizi Ausiliari Di Analisi, Controllo E Ricerca. Servizi Per Aziende, Manifestazioni E Supporto Agli Scambi Commerciali",
    "sg:phone":"+39 039 628281",
    "sg:postcode":"20040",
    "sg:province":"Milano",
    "wof:name":"Delta Spa",
    "wof:placetype":"venue"
},
  "geometry": {"coordinates":[9.462363,45.649914],"type":"Point"}
}