{
  "type": "Feature",
  "properties": {
    "iso:country":"IT",
    "sg:address":"14100 Asti",
    "sg:city":"Asti",
    "sg:orig_category":"Associazioni Sindacali E Di Categoria",
    "sg:phone":"+39 0141 593420",
    "sg:postcode":"14100",
    "sg:province":"Asti",
    "wof:name":"Camera Confederale Del Lavoro",
    "wof:placetype":"venue"
},
  "geometry": {"coordinates":[8.312697,44.87907],"type":"Point"}
}