{
  "type": "Feature",
  "properties": {
    "iso:country":"IT",
    "sg:address":"40128 Bologna",
    "sg:city":"Bologna",
    "sg:orig_category":"Impiantistica E Prodotti Tecnologici Per Edilizia. Elettronica Professionale E Di Consumo. Accessori Dei Mezzi Di Trasporto. Forniture Industriali Per Prevenzione, Controllo E Sicurezza",
    "sg:phone":"+39 051 638 8078",
    "sg:postcode":"40128",
    "sg:province":"Bologna",
    "sg:website":"http://www.skyline-srl.com",
    "wof:name":"Skyline Srl",
    "wof:placetype":"venue"
},
  "geometry": {"coordinates":[11.359545,44.515892],"type":"Point"}
}