{
  "type": "Feature",
  "properties": {
    "iso:country":"IT",
    "sg:address":"62010 Montecassiano",
    "sg:city":"Montecassiano",
    "sg:orig_category":"Servizi E Lavori Per Edilizia E Lavori Pubblici",
    "sg:phone":"+39 0733 598321",
    "sg:postcode":"62010",
    "sg:province":"Macerata",
    "wof:name":"Restauri E Colori Di Latini Sergio & C. Snc",
    "wof:placetype":"venue"
},
  "geometry": {"coordinates":[13.439572,43.364647],"type":"Point"}
}