{
  "type": "Feature",
  "properties": {
    "iso:country":"IT",
    "sg:address":"42100 Reggio Emilia",
    "sg:orig_category":"Trattamenti Termici Metalli",
    "sg:phone":"+39 0522 517383",
    "sg:postcode":"42100",
    "sg:province":"Reggio Nell'Emilia",
    "wof:name":"Nuova Oria Metaltermica Srl",
    "wof:placetype":"venue"
},
  "geometry": {"coordinates":[10.645543,44.739311],"type":"Point"}
}