{
  "type": "Feature",
  "properties": {
    "iso:country":"IT",
    "sg:address":"13875 Ponderano",
    "sg:city":"Ponderano",
    "sg:orig_category":"Filati E Materie Prime Tessili",
    "sg:phone":"+39 015 541350",
    "sg:postcode":"13875",
    "sg:province":"Biella",
    "wof:name":"Zocco & C. Di Fardo S. & C. (s.n.c.)",
    "wof:placetype":"venue"
},
  "geometry": {"coordinates":[8.0577020645,45.5373497009],"type":"Point"}
}