{
  "type": "Feature",
  "properties": {
    "iso:country":"IT",
    "sg:address":"Via G. Garibaldi 33 51037 Montale",
    "sg:city":"Montale",
    "sg:classifiers":[
        {
            "category":"Manufacturing",
            "subcategory":"Textiles",
            "type":"Manufacturing & Wholesale Goods"
        }
    ],
    "sg:phone":"+39 0573 958126",
    "sg:postcode":"51037",
    "sg:province":"Pistoia",
    "sg:tags":[
        "raw",
        "material"
    ],
    "wof:name":"Eurofilament S.r.l.",
    "wof:placetype":"venue"
},
  "geometry": {"coordinates":[11.01412,43.919815],"type":"Point"}
}