{
  "type": "Feature",
  "properties": {
    "addr:full":"37060 Trevenzuolo Trevenzuolo Verona 37060",
    "addr:postcode":"37060;37060",
    "iso:country":"IT",
    "sg:address":"37060 Trevenzuolo",
    "sg:city":"Trevenzuolo",
    "sg:orig_category":"Termotecnica E Riscaldamento, Apparecchiature E Servizi. Prodotti Vari In Metallo",
    "sg:phone":"+39 045 735 0400",
    "sg:postcode":"37060",
    "sg:province":"Verona",
    "wof:name":"F.lli Montresoro Snc",
    "wof:placetype":"venue"
},
  "geometry": {"coordinates":[10.935481,45.270313],"type":"Point"}
}