{
  "type": "Feature",
  "properties": {
    "addr:full":"59, Via Porte Di Sopra 45026 Lendinara Lendinara Rovigo 45026",
    "addr:postcode":"45026;45026",
    "addr:street":"Via Porte Di Sopra",
    "iso:country":"IT",
    "sg:address":"59, Via Porte Di Sopra 45026 Lendinara",
    "sg:city":"Lendinara",
    "sg:classifiers":[
        {
            "category":"Farming",
            "subcategory":"Livestock Farm",
            "type":"Manufacturing & Wholesale Goods"
        }
    ],
    "sg:phone":"+39 0425 642757",
    "sg:postcode":"45026",
    "sg:province":"Rovigo",
    "sg:tags":[
        "agriculture"
    ],
    "wof:name":"Mainardi Nicola (s.r.l.)",
    "wof:placetype":"venue"
},
  "geometry": {"coordinates":[11.5882978439,45.0851478577],"type":"Point"}
}