{
  "type": "Feature",
  "properties": {
    "addr:full":"00193 Roma Roma Roma 00193",
    "addr:postcode":"00193;00193",
    "iso:country":"IT",
    "sg:address":"00193 Roma",
    "sg:city":"Roma",
    "sg:orig_category":"Non-classified Establishments",
    "sg:phone":"+39 06 323 5414",
    "sg:postcode":"00193",
    "sg:province":"Roma",
    "wof:name":"Ruberto Antonio",
    "wof:placetype":"venue"
},
  "geometry": {"coordinates":[12.491919,41.864872],"type":"Point"}
}