{
  "type": "Feature",
  "properties": {
    "iso:country":"IT",
    "sg:address":"25082 Botticino",
    "sg:city":"Botticino",
    "sg:orig_category":"Macchine Ed Impianti Per Edilizia E Lavori Pubblici",
    "sg:phone":"+39 030 219 0525",
    "sg:postcode":"25082",
    "sg:province":"Brescia",
    "wof:name":"Cooperativa Valverde Escavazione Marmo Botticino",
    "wof:placetype":"venue"
},
  "geometry": {"coordinates":[10.312754,45.534401],"type":"Point"}
}