{
  "type": "Feature",
  "properties": {
    "iso:country":"IT",
    "sg:address":"23, Via Battisti Cesare 30030 Martellago",
    "sg:city":"Martellago",
    "sg:classifiers":[
        {
            "category":"Shopping",
            "subcategory":"Jewelry",
            "type":"Retail Goods"
        }
    ],
    "sg:phone":"+39 39041909562",
    "sg:postcode":"30030",
    "sg:province":"Venezia",
    "sg:tags":[
        "jewellery"
    ],
    "wof:name":"Corbetta (s.n.c.)",
    "wof:placetype":"venue"
},
  "geometry": {"coordinates":[12.189906,45.515427],"type":"Point"}
}