{
  "type": "Feature",
  "properties": {
    "iso:country":"IT",
    "sg:address":"13, Piazzetta Riccardi Gabriele 73100 Lecce",
    "sg:city":"Lecce",
    "sg:classifiers":[
        {
            "category":"Travel",
            "subcategory":"Travel Agent",
            "type":"Entertainment"
        }
    ],
    "sg:phone":"+39 0832 245111",
    "sg:postcode":"73100",
    "sg:province":"Lecce",
    "sg:tags":[
        "business"
    ],
    "wof:name":"Albergo Patria Palace Hotel",
    "wof:placetype":"venue"
},
  "geometry": {"coordinates":[18.172289,40.35453],"type":"Point"}
}