{
  "type": "Feature",
  "properties": {
    "iso:country":"IT",
    "sg:address":"00187 Roma",
    "sg:city":"Roma",
    "sg:orig_category":"Chiese Ed Associazioni Religiose",
    "sg:phone":"+39 06 4201 1891",
    "sg:postcode":"00187",
    "sg:province":"Roma",
    "wof:name":"Padri Paulisti",
    "wof:placetype":"venue"
},
  "geometry": {"coordinates":[12.495555,41.905659],"type":"Point"}
}