{
  "type": "Feature",
  "properties": {
    "iso:country":"IT",
    "sg:address":"80147 Napoli",
    "sg:city":"Napoli",
    "sg:orig_category":"Apparecchiature E Sistemi Per Magazzinaggio E Movimentazione",
    "sg:phone":"+39 081 561 3049",
    "sg:postcode":"80147",
    "sg:province":"Napoli",
    "wof:name":"Centro Gru Di Tengo Salvatore",
    "wof:placetype":"venue"
},
  "geometry": {"coordinates":[14.333122,40.871284],"type":"Point"}
}