{
  "type": "Feature",
  "properties": {
    "addr:full":"95045 Misterbianco Misterbianco Catania 95045",
    "addr:postcode":"95045;95045",
    "iso:country":"IT",
    "sg:address":"95045 Misterbianco",
    "sg:city":"Misterbianco",
    "sg:orig_category":"Caffe' Crudo E Torrefatto",
    "sg:phone":"+39 095 476754",
    "sg:postcode":"95045",
    "sg:province":"Catania",
    "wof:name":"Brasilrecca Spa",
    "wof:placetype":"venue"
},
  "geometry": {"coordinates":[15.026312,37.51321],"type":"Point"}
}