{
  "type": "Feature",
  "properties": {
    "iso:country":"IT",
    "sg:address":"Via Alpiano Inferiore 3 28862 Crodo",
    "sg:city":"Crodo",
    "sg:orig_category":"Granite Pavers",
    "sg:phone":"+39 0324 61295",
    "sg:postcode":"28862",
    "sg:province":"Verbano-Cusio-Ossola",
    "sg:website":"www.moroserizzo.com",
    "wof:name":"Moro Serizzo Sas",
    "wof:placetype":"venue"
},
  "geometry": {"coordinates":[8.323332,46.202682],"type":"Point"}
}