{
  "type": "Feature",
  "properties": {
    "addr:full":"Via Ovada, 65 - Pievesestina 47023 Cesena Cesena Forl\u00ec-Cesena 47023",
    "addr:housenumber":"65",
    "addr:postcode":"47023;47023",
    "addr:street":"Via Ovada;Pievesestina",
    "iso:country":"IT",
    "sg:address":"Via Ovada, 65 - Pievesestina 47023 Cesena",
    "sg:city":"Cesena",
    "sg:classifiers":[
        {
            "category":"Wholesale",
            "subcategory":"Plants",
            "type":"Manufacturing & Wholesale Goods"
        }
    ],
    "sg:phone":"+39 0547 312811",
    "sg:postcode":"47023",
    "sg:province":"Forl\u00ec-Cesena",
    "sg:tags":[
        "packaging",
        "plants",
        "complete"
    ],
    "sg:website":"www.pieri.it",
    "wof:name":"Pieri Srl",
    "wof:placetype":"venue"
},
  "geometry": {"coordinates":[11.9804611206,43.9947662354],"type":"Point"}
}