{
  "type": "Feature",
  "properties": {
    "iso:country":"IT",
    "sg:address":"20146 Milano",
    "sg:city":"Milano",
    "sg:orig_category":"Ospedali E Servizi Sanitari. Servizi Sociali. Associazioni Ed Organismi Di Interesse Pubblico",
    "sg:phone":"+39 02 407 5165",
    "sg:postcode":"20146",
    "sg:province":"Milano",
    "wof:name":"Mani Tese",
    "wof:placetype":"venue"
},
  "geometry": {"coordinates":[9.142202,45.464531],"type":"Point"}
}