{
  "type": "Feature",
  "properties": {
    "addr:full":"24, Via Petrella Errico 20124 Milano Milano Milano 20124",
    "addr:postcode":"20124;20124",
    "addr:street":"Via Petrella Errico",
    "iso:country":"IT",
    "sg:address":"24, Via Petrella Errico 20124 Milano",
    "sg:city":"Milano",
    "sg:classifiers":[
        {
            "category":"Shopping",
            "subcategory":"Clothing, Apparel, & Fashions",
            "type":"Retail Goods"
        }
    ],
    "sg:phone":"+39 39026691424",
    "sg:postcode":"20124",
    "sg:province":"Milano",
    "sg:tags":[
        "clothes"
    ],
    "wof:name":"Manifattura A. Enfi & C.",
    "wof:placetype":"venue"
},
  "geometry": {"coordinates":[9.208953,45.48423],"type":"Point"}
}