{
  "type": "Feature",
  "properties": {
    "iso:country":"IT",
    "sg:address":"87064 Corigliano Calabro",
    "sg:city":"Corigliano Calabro",
    "sg:orig_category":"Agrumi",
    "sg:phone":"+39 0983 886001",
    "sg:postcode":"87064",
    "sg:province":"Cosenza",
    "wof:name":"Ortofrutticola Gallo Sas Di Gallo Natale Pietro",
    "wof:placetype":"venue"
},
  "geometry": {"coordinates":[16.511271,39.627613],"type":"Point"}
}