{
  "type": "Feature",
  "properties": {
    "iso:country":"IT",
    "sg:address":"00125 Roma",
    "sg:city":"Roma",
    "sg:orig_category":"Chiese Ed Associazioni Religiose",
    "sg:phone":"+39 06 5235 8178",
    "sg:postcode":"00125",
    "sg:province":"Roma",
    "wof:name":"Chiesa Di Altri Culti Cristiana Evangelica Comunita' Di Roma Decima Chiesa Apostolica",
    "wof:placetype":"venue"
},
  "geometry": {"coordinates":[12.360351,41.77409],"type":"Point"}
}