{
  "type": "Feature",
  "properties": {
    "addr:full":"6, Via Forgaria 33078 San Vito Al Tagliamento San Vito al Tagliamento Pordenone 33078",
    "addr:postcode":"33078;33078",
    "addr:street":"Via Forgaria",
    "iso:country":"IT",
    "sg:address":"6, Via Forgaria 33078 San Vito Al Tagliamento",
    "sg:city":"San Vito al Tagliamento",
    "sg:classifiers":[
        {
            "category":"Shopping",
            "subcategory":"Stationery & Office Supplies",
            "type":"Retail Goods"
        }
    ],
    "sg:phone":"+39 39043485091",
    "sg:postcode":"33078",
    "sg:province":"Pordenone",
    "sg:tags":[
        "professional"
    ],
    "wof:name":"Arrben S.n.c. Di Benvenuto Ottorino & C.",
    "wof:placetype":"venue"
},
  "geometry": {"coordinates":[12.8776674271,45.9426803589],"type":"Point"}
}