{
  "type": "Feature",
  "properties": {
    "addr:full":"Via Socrate 12 22070 Casnate Casnate Como 22070",
    "addr:housenumber":"12",
    "addr:postcode":"22070;22070",
    "addr:street":"Via Socrate",
    "iso:country":"IT",
    "sg:address":"Via Socrate 12 22070 Casnate",
    "sg:city":"Casnate",
    "sg:classifiers":[
        {
            "category":"Shopping",
            "subcategory":"Crafts & Fabrics",
            "type":"Retail Goods"
        }
    ],
    "sg:phone":"+39 031 451460",
    "sg:postcode":"22070",
    "sg:province":"Como",
    "sg:tags":[
        "textile",
        "machinery",
        "accessory"
    ],
    "sg:website":"www.zanfrini.com",
    "wof:name":"Zanfrini Srl",
    "wof:placetype":"venue"
},
  "geometry": {"coordinates":[9.086581,45.761532],"type":"Point"}
}