{
  "type": "Feature",
  "properties": {
    "iso:country":"IT",
    "sg:address":"Via Don Panizza, 29; Rovereto; 38068",
    "sg:city":"Rovereto",
    "sg:classifiers":[
        {
            "category":"Banks & Credit Unions",
            "subcategory":"Bank",
            "type":"Services"
        }
    ],
    "sg:phone":"+39 0464 421061",
    "sg:postcode":"38068",
    "sg:province":"Trento",
    "wof:name":"Cassa Rurale Di Lizzana",
    "wof:placetype":"venue"
},
  "geometry": {"coordinates":[11.03987,45.890648],"type":"Point"}
}