{
  "type": "Feature",
  "properties": {
    "iso:country":"IT",
    "sg:address":"28017 San Maurizio D'opaglio",
    "sg:orig_category":"Materiali Semilavorati Metallici",
    "sg:phone":"+39 0322 919942",
    "sg:postcode":"28017",
    "sg:province":"Novara",
    "wof:name":"Trafilerie Carlo Gnutti",
    "wof:placetype":"venue"
},
  "geometry": {"coordinates":[8.401864,45.771534],"type":"Point"}
}