{
  "type": "Feature",
  "properties": {
    "iso:country":"IT",
    "sg:address":"Via S.dalmazio 41028 Serramazzoni",
    "sg:city":"Serramazzoni",
    "sg:classifiers":[
        {
            "category":"Farming",
            "subcategory":"Livestock Farm",
            "type":"Manufacturing & Wholesale Goods"
        }
    ],
    "sg:phone":"+39 0536 953850",
    "sg:postcode":"41028",
    "sg:province":"Modena",
    "sg:tags":[
        "agriculture"
    ],
    "wof:name":"R.c. (s.r.l.)",
    "wof:placetype":"venue"
},
  "geometry": {"coordinates":[10.92522,44.647079],"type":"Point"}
}