{
  "type": "Feature",
  "properties": {
    "iso:country":"IT",
    "sg:address":"40069 Zola Predosa",
    "sg:city":"Zola",
    "sg:orig_category":"Servizi E Lavori Industria Chimica. Riparazione Dei Mezzi Di Trasporto",
    "sg:phone":"+39 051 758601",
    "sg:postcode":"40069",
    "sg:province":"Bologna",
    "wof:name":"Braglia Di Saguatti Liliana & C. Snc",
    "wof:placetype":"venue"
},
  "geometry": {"coordinates":[11.253942,44.496403],"type":"Point"}
}