{
  "type": "Feature",
  "properties": {
    "iso:country":"IT",
    "sg:address":"13900 Biella",
    "sg:city":"Biella",
    "sg:classifiers":[
        {
            "category":"Arena",
            "subcategory":"Sports Club",
            "type":"Entertainment"
        }
    ],
    "sg:phone":"+39 015 401173",
    "sg:postcode":"13900",
    "sg:province":"Biella",
    "sg:tags":[
        "e",
        "lo",
        "tempo",
        "libero",
        "per",
        "servizi",
        "il"
    ],
    "wof:name":"Chiarentin Marco",
    "wof:placetype":"venue"
},
  "geometry": {"coordinates":[8.041001,45.558258],"type":"Point"}
}