{
  "type": "Feature",
  "properties": {
    "addr:full":"29011 Borgonovo Val Tidone Borgonovo Val Tidone Piacenza 29011",
    "addr:postcode":"29011;tidone;29011",
    "iso:country":"IT",
    "sg:address":"29011 Borgonovo Val Tidone",
    "sg:city":"Borgonovo Val Tidone",
    "sg:orig_category":"Servizi E Lavori Per Industria Alimentare E Bevande",
    "sg:phone":"+39 0523 860012",
    "sg:postcode":"29011",
    "sg:province":"Piacenza",
    "wof:name":"Industria Molitoria Tirelli Snc",
    "wof:placetype":"venue"
},
  "geometry": {"coordinates":[9.463796,45.010178],"type":"Point"}
}