{
  "type": "Feature",
  "properties": {
    "addr:full":"20149 Milano Milano Milano 20149",
    "addr:postcode":"20149;20149",
    "iso:country":"IT",
    "sg:address":"20149 Milano",
    "sg:city":"Milano",
    "sg:orig_category":"Avvocati, Notai E Servizi Legali. Consulenze Tecniche, Amministrative E Perizie",
    "sg:phone":"+39 02 481 6361",
    "sg:postcode":"20149",
    "sg:province":"Milano",
    "wof:name":"De Pasquale Dr. Anna Maria",
    "wof:placetype":"venue"
},
  "geometry": {"coordinates":[9.147891,45.470936],"type":"Point"}
}