{
  "type": "Feature",
  "properties": {
    "iso:country":"IT",
    "sg:address":"1, Via Sile 36030 Monte Di Malo",
    "sg:city":"Monte di Malo",
    "sg:classifiers":[
        {
            "category":"Manufacturing",
            "subcategory":"Textiles",
            "type":"Manufacturing & Wholesale Goods"
        }
    ],
    "sg:phone":"+39 0445 605510",
    "sg:postcode":"36030",
    "sg:province":"Vicenza",
    "sg:tags":[
        "leather",
        "raw",
        "material",
        "-"
    ],
    "wof:name":"Schib Packaging (s.r.l.)",
    "wof:placetype":"venue"
},
  "geometry": {"coordinates":[11.39266,45.654709],"type":"Point"}
}