{
  "type": "Feature",
  "properties": {
    "iso:country":"IT",
    "sg:address":"41, V. Dell'artigianato 35010 Villa Del Conte",
    "sg:city":"Villa del Conte",
    "sg:classifiers":[
        {
            "category":"Wholesale",
            "subcategory":"Medical Equipment & Supplies",
            "type":"Manufacturing & Wholesale Goods"
        }
    ],
    "sg:phone":"+39 049 932 5733",
    "sg:postcode":"35010",
    "sg:province":"Padova",
    "sg:tags":[
        "-",
        "health",
        "instrument"
    ],
    "sg:website":"http://www.offcarr.com:ws_end: :mark:ws:http://www.paginegialle.it/offcar-01",
    "wof:name":"Off. Carr Snc",
    "wof:placetype":"venue"
},
  "geometry": {"coordinates":[11.797796,45.325653],"type":"Point"}
}