{
  "type": "Feature",
  "properties": {
    "iso:country":"IT",
    "sg:address":"20010 Casorezzo",
    "sg:city":"Casorezzo",
    "sg:orig_category":"Forniture Per Attivita' Industriali",
    "sg:phone":"+39 02 9029 7171",
    "sg:postcode":"20010",
    "sg:province":"Milano",
    "wof:name":"Italgom Sas Di S. Martorana E C.",
    "wof:placetype":"venue"
},
  "geometry": {"coordinates":[8.9013748169,45.5237960815],"type":"Point"}
}