{
  "type": "Feature",
  "properties": {
    "iso:country":"IT",
    "sg:address":"Via Rio Vallone 5 20050 Mezzago",
    "sg:city":"Mezzago",
    "sg:classifiers":[
        {
            "category":"Utilities",
            "subcategory":"Cable",
            "type":"Services"
        }
    ],
    "sg:phone":"+39 039 688 3300",
    "sg:postcode":"20050",
    "sg:province":"Milano",
    "sg:tags":[
        "connector"
    ],
    "sg:website":"www.kontek-comatel.com",
    "wof:name":"Kontek Comatel Spa",
    "wof:placetype":"venue"
},
  "geometry": {"coordinates":[9.44322,45.632656],"type":"Point"}
}