{
  "type": "Feature",
  "properties": {
    "addr:full":"21048 Solbiate Arno Solbiate Arno Varese 21048",
    "addr:housenumber":"arno",
    "addr:postcode":"21048;21048",
    "iso:country":"IT",
    "sg:address":"21048 Solbiate Arno",
    "sg:city":"Solbiate Arno",
    "sg:orig_category":"Utensili Meccanici E Materiali",
    "sg:phone":"+39 0331 985940",
    "sg:postcode":"21048",
    "sg:province":"Varese",
    "wof:name":"Fimad Srl",
    "wof:placetype":"venue"
},
  "geometry": {"coordinates":[8.816597,45.720737],"type":"Point"}
}