{
  "type": "Feature",
  "properties": {
    "addr:full":"52100 Arezzo Arezzo Arezzo 52100",
    "addr:postcode":"52100;52100",
    "iso:country":"IT",
    "sg:address":"52100 Arezzo",
    "sg:city":"Arezzo",
    "sg:orig_category":"Studi E Consulenze Amministrative, Commerciali E Aziendali. Consulenze Tecniche, Amministrative E Perizie. Professionisti - Studi E Servizi Ed Associazioni Di Interesse Aziendale",
    "sg:phone":"+39 0575 902590",
    "sg:postcode":"52100",
    "sg:province":"Arezzo",
    "wof:name":"Salvi Fabio",
    "wof:placetype":"venue"
},
  "geometry": {"coordinates":[11.875527,43.457539],"type":"Point"}
}