{
  "type": "Feature",
  "properties": {
    "addr:full":"45038 Polesella Polesella Rovigo 45038",
    "addr:postcode":"45038;45038",
    "iso:country":"IT",
    "sg:address":"45038 Polesella",
    "sg:city":"Polesella",
    "sg:orig_category":"Metalli E Leghe",
    "sg:phone":"+39 0425 444705",
    "sg:postcode":"45038",
    "sg:province":"Rovigo",
    "wof:name":"Lamitref Italia Srl",
    "wof:placetype":"venue"
},
  "geometry": {"coordinates":[11.7442817688,44.9626579285],"type":"Point"}
}