{
  "type": "Feature",
  "properties": {
    "iso:country":"IT",
    "sg:address":"Sda Statale 634- Km 2, Nr 32 70014 Conversano",
    "sg:city":"Conversano",
    "sg:classifiers":[
        {
            "category":"Wholesale",
            "subcategory":"Fruits & Vegetables",
            "type":"Manufacturing & Wholesale Goods"
        }
    ],
    "sg:phone":"+39 080 495 4125",
    "sg:postcode":"70014",
    "sg:province":"Bari",
    "sg:tags":[
        "preserve"
    ],
    "sg:website":"www.cinara.it",
    "wof:name":"Centrone Pietro & Figli S.r.l.",
    "wof:placetype":"venue"
},
  "geometry": {"coordinates":[16.869291,41.126053],"type":"Point"}
}