{
  "type": "Feature",
  "properties": {
    "iso:country":"IT",
    "sg:address":"16123 Genova",
    "sg:city":"Genova",
    "sg:orig_category":"Autoscuole",
    "sg:phone":"+39 010 247 1977",
    "sg:postcode":"16123",
    "sg:province":"Genova",
    "wof:name":"Autoscuola San Lorenzo",
    "wof:placetype":"venue"
},
  "geometry": {"coordinates":[8.915301,44.458557],"type":"Point"}
}