{
  "type": "Feature",
  "properties": {
    "iso:country":"IT",
    "sg:address":"13898 Occhieppo Superiore",
    "sg:city":"Occhieppo Superiore",
    "sg:orig_category":"Forniture Per Abbigliamento E Pelletterie",
    "sg:phone":"+39 015 590173",
    "sg:postcode":"13898",
    "sg:province":"Biella",
    "wof:name":"Sfilacciatura Canova Ostilio Di Poletti Carlo & C. (s.a.s.)",
    "wof:placetype":"venue"
},
  "geometry": {"coordinates":[8.0118722916,45.5597839355],"type":"Point"}
}