{
  "type": "Feature",
  "properties": {
    "addr:full":"23, V. Risorgimento 23834 Premana Premana Lecco 23834",
    "addr:housenumber":"23",
    "addr:postcode":"23834;23834",
    "addr:street":"V. Risorgimento",
    "iso:country":"IT",
    "sg:address":"23, V. Risorgimento 23834 Premana",
    "sg:city":"Premana",
    "sg:classifiers":[
        {
            "category":"Shopping",
            "type":"Retail Goods"
        }
    ],
    "sg:phone":"+39 0341 890121",
    "sg:postcode":"23834",
    "sg:province":"Lecco",
    "sg:tags":[
        "finished",
        "-",
        "metallic"
    ],
    "sg:website":"http://www.emmes.it:ws_end: :mark:ws:http://www.paginegialle.it/emmes",
    "wof:name":"Emmes Di Codega Dionigi Snc",
    "wof:placetype":"venue"
},
  "geometry": {"coordinates":[9.4204702377,46.0525741577],"type":"Point"}
}