{
  "type": "Feature",
  "properties": {
    "iso:country":"IT",
    "sg:address":"00197 Roma",
    "sg:city":"Roma",
    "sg:classifiers":[
        {
            "category":"Health Services",
            "subcategory":"Health Practitioner",
            "type":"Services"
        }
    ],
    "sg:phone":"+39 06 320 0931",
    "sg:postcode":"00197",
    "sg:province":"Roma",
    "sg:tags":[
        "medici"
    ],
    "wof:name":"Giacobini Elio",
    "wof:placetype":"venue"
},
  "geometry": {"coordinates":[12.476592,41.920742],"type":"Point"}
}