{
  "type": "Feature",
  "properties": {
    "iso:country":"IT",
    "sg:address":"139, Via Principale 31030 Casier",
    "sg:city":"Casier",
    "sg:classifiers":[
        {
            "category":"Manufacturing",
            "subcategory":"Printing",
            "type":"Manufacturing & Wholesale Goods"
        }
    ],
    "sg:phone":"+39 0422 670548",
    "sg:postcode":"31030",
    "sg:province":"Treviso",
    "sg:tags":[
        "publishing"
    ],
    "wof:name":"Novacart Snc Di Bertato Giorgio & C.",
    "wof:placetype":"venue"
},
  "geometry": {"coordinates":[12.3003501892,45.6382713318],"type":"Point"}
}