{
  "type": "Feature",
  "properties": {
    "iso:country":"IT",
    "sg:address":"29/a, V. Dei Ferrinanti - Z.i. Valpiana58020 Massa Marittima",
    "sg:classifiers":[
        {
            "category":"Bars & Pubs",
            "subcategory":"Nightclub",
            "type":"Food & Drink"
        }
    ],
    "sg:phone":"+39 0566 919923",
    "sg:postcode":"58020",
    "sg:province":"Grosseto",
    "sg:tags":[
        "cake",
        "bread"
    ],
    "sg:website":"http://www.lelogge.it",
    "wof:name":"Pasticceria Le Logge",
    "wof:placetype":"venue"
},
  "geometry": {"coordinates":[11.112782,42.762859],"type":"Point"}
}