{
  "type": "Feature",
  "properties": {
    "iso:country":"IT",
    "sg:address":"55, Via Panoramica Sera 25082 Botticino",
    "sg:city":"Botticino",
    "sg:classifiers":[
        {
            "category":"Shopping",
            "subcategory":"Clothing, Apparel, & Fashions",
            "type":"Retail Goods"
        }
    ],
    "sg:phone":"+39 030 269 1964",
    "sg:postcode":"25082",
    "sg:province":"Brescia",
    "sg:tags":[
        "clothes"
    ],
    "wof:name":"Sciotti",
    "wof:placetype":"venue"
},
  "geometry": {"coordinates":[10.298912,45.546783],"type":"Point"}
}