{
  "type": "Feature",
  "properties": {
    "addr:full":"160, Via Milano 13856 Vigliano Biellese Vigliano Biellese Biella 13856",
    "addr:housenumber":"160",
    "addr:postcode":"13856;13856",
    "addr:street":"Via Milano",
    "iso:country":"IT",
    "sg:address":"160, Via Milano 13856 Vigliano Biellese",
    "sg:city":"Vigliano Biellese",
    "sg:classifiers":[
        {
            "category":"Shopping",
            "subcategory":"Crafts & Fabrics",
            "type":"Retail Goods"
        }
    ],
    "sg:phone":"+39 39015811345",
    "sg:postcode":"13856",
    "sg:province":"Biella",
    "wof:name":"Filatura Di Chiavazza (s.p.a.)",
    "wof:placetype":"venue"
},
  "geometry": {"coordinates":[8.1061601639,45.5629615784],"type":"Point"}
}