{
  "type": "Feature",
  "properties": {
    "iso:country":"IT",
    "sg:address":"15100 Alessandria",
    "sg:city":"Alessandria",
    "sg:orig_category":"Climatizzazione E Condizionamento, Apparecchiature E Servizi. Accessori Dei Mezzi Di Trasporto",
    "sg:phone":"+39 0131 51646",
    "sg:postcode":"15100",
    "sg:province":"Alessandria",
    "wof:name":"Villavecchia Bruno Dei F. Lli Villavecchia & C. Snc",
    "wof:placetype":"venue"
},
  "geometry": {"coordinates":[8.624027,44.91605],"type":"Point"}
}