{
  "type": "Feature",
  "properties": {
    "iso:country":"IT",
    "sg:address":"15048 Valenza",
    "sg:city":"Valenza",
    "sg:orig_category":"Prodotti Di Base E Forniture Per Industria Alimentare E Bevande. Carta, Cartone E Prodotti Primari. Forniture Per Attivita' Commerciali Ed Artigianali",
    "sg:phone":"+39 0131 947947",
    "sg:postcode":"15048",
    "sg:province":"Alessandria",
    "wof:name":"Cartoservice Di Rovelli & C. Sas",
    "wof:placetype":"venue"
},
  "geometry": {"coordinates":[8.5087776184,44.9193878174],"type":"Point"}
}