{
  "type": "Feature",
  "properties": {
    "addr:full":"20060 Truccazzano Truccazzano Milano 20060",
    "addr:postcode":"20060;20060",
    "iso:country":"IT",
    "sg:address":"20060 Truccazzano",
    "sg:city":"Truccazzano",
    "sg:orig_category":"Sport And Leisure, Services. Tourism, Services. Motor Vehicles, Auxiliary Services. Transport, Auxiliary Services",
    "sg:phone":"+39 02 958 3076",
    "sg:postcode":"20060",
    "sg:province":"Milano",
    "wof:name":"Autoservizi Rovaris Srl",
    "wof:placetype":"venue"
},
  "geometry": {"coordinates":[9.493854,45.498798],"type":"Point"}
}