{
  "type": "Feature",
  "properties": {
    "iso:country":"IT",
    "sg:address":"50041 Calenzano",
    "sg:city":"Calenzano",
    "sg:orig_category":"Giardinaggio - Servizio",
    "sg:phone":"+39 055 881 9420",
    "sg:postcode":"50041",
    "sg:province":"Firenze",
    "sg:website":"http://www.menichelli.it",
    "wof:name":"Menichelli Massimo",
    "wof:placetype":"venue"
},
  "geometry": {"coordinates":[11.207866,43.827423],"type":"Point"}
}