{
  "type": "Feature",
  "properties": {
    "iso:country":"IT",
    "sg:address":"35010 Santa Giustina In Colle",
    "sg:city":"Santa Giustina in Colle",
    "sg:orig_category":"Macchine, Impianti Ed Attrezzature Per Agricoltura E Zootecnia",
    "sg:phone":"+39 049 930 1081",
    "sg:postcode":"35010",
    "sg:province":"Padova",
    "wof:name":"Bernardello Luigi",
    "wof:placetype":"venue"
},
  "geometry": {"coordinates":[11.892101,45.576012],"type":"Point"}
}