{
  "type": "Feature",
  "properties": {
    "addr:full":"Via Pirreri, 21 - Purgatorio 91015 Custonaci Custonaci Trapani 91015",
    "addr:housenumber":"21",
    "addr:postcode":"91015;91015",
    "addr:street":"Via Pirreri;Purgatorio",
    "iso:country":"IT",
    "sg:address":"Via Pirreri, 21 - Purgatorio 91015 Custonaci",
    "sg:city":"Custonaci",
    "sg:classifiers":[
        {
            "category":"Home & Garden",
            "subcategory":"Building Materials",
            "type":"Retail Goods"
        }
    ],
    "sg:phone":"+39 0923 971259",
    "sg:postcode":"91015",
    "sg:province":"Trapani",
    "sg:tags":[
        "slab",
        "marble"
    ],
    "sg:website":"www.santoromarmi.it",
    "wof:name":"Santoro Marmi S.r.l.",
    "wof:placetype":"venue"
},
  "geometry": {"coordinates":[12.712915,38.078373],"type":"Point"}
}