{
  "type": "Feature",
  "properties": {
    "iso:country":"IT",
    "sg:address":"37, Via Oltrecolle 22030 Lipomo",
    "sg:city":"Lipomo",
    "sg:classifiers":[
        {
            "category":"Professional",
            "subcategory":"Printing & Photocopies",
            "type":"Services"
        }
    ],
    "sg:phone":"+39 39031283333",
    "sg:postcode":"22030",
    "sg:province":"Como",
    "wof:name":"Pentagraf S.n.c.",
    "wof:placetype":"venue"
},
  "geometry": {"coordinates":[9.1011924744,45.7927742004],"type":"Point"}
}