{
  "type": "Feature",
  "properties": {
    "addr:full":"Via Colonna Vittoria 8 20149 Milano Milano Milano 20149",
    "addr:housenumber":"8",
    "addr:postcode":"20149;20149",
    "addr:street":"Via Colonna Vittoria",
    "iso:country":"IT",
    "sg:address":"Via Colonna Vittoria 8 20149 Milano",
    "sg:city":"Milano",
    "sg:classifiers":[
        {
            "category":"Personal",
            "subcategory":"Tanning Parlor",
            "type":"Services"
        }
    ],
    "sg:phone":"+39 02 463339",
    "sg:postcode":"20149",
    "sg:province":"Milano",
    "sg:tags":[
        "hide",
        "supply"
    ],
    "sg:website":"www.pizzocarosas.com",
    "wof:name":"Pizzocaro Sas Di Armando Pizzocaro E C",
    "wof:placetype":"venue"
},
  "geometry": {"coordinates":[9.153588,45.470505],"type":"Point"}
}