{
  "type": "Feature",
  "properties": {
    "iso:country":"IT",
    "sg:address":"44049 Vigarano Mainarda",
    "sg:city":"Vigarano Mainarda",
    "sg:classifiers":[
        {
            "category":"Professional",
            "subcategory":"Business Services",
            "type":"Services"
        }
    ],
    "sg:phone":"+39 0532 436910",
    "sg:postcode":"44049",
    "sg:province":"Ferrara",
    "sg:tags":[
        "support",
        "companies",
        "events",
        "trade"
    ],
    "sg:website":"http://www.rublan.it",
    "wof:name":"Rublan Snc Di Rubbi & Lanzoni",
    "wof:placetype":"venue"
},
  "geometry": {"coordinates":[11.505774,44.843197],"type":"Point"}
}