{
  "type": "Feature",
  "properties": {
    "addr:full":"80131 Napoli Napoli Napoli 80131",
    "addr:housenumber":"80131",
    "addr:postcode":"80131",
    "iso:country":"IT",
    "sg:address":"80131 Napoli",
    "sg:city":"Napoli",
    "sg:orig_category":"Guanti - Produzione E Commercio",
    "sg:phone":"+39 081 741 8713",
    "sg:postcode":"80131",
    "sg:province":"Napoli",
    "wof:name":"Florens Gloves Srl",
    "wof:placetype":"venue"
},
  "geometry": {"coordinates":[14.249039,40.870556],"type":"Point"}
}