{
  "type": "Feature",
  "properties": {
    "iso:country":"IT",
    "sg:address":"36011 Arsiero",
    "sg:city":"Arsiero",
    "sg:orig_category":"Prodotti Finiti Stampati. Forniture Per Uffici",
    "sg:phone":"+39 0445 740361",
    "sg:postcode":"36011",
    "sg:province":"Vicenza",
    "wof:name":"Diagramcarta Gasparotto (s.n.c.)",
    "wof:placetype":"venue"
},
  "geometry": {"coordinates":[11.5494747162,45.5491638184],"type":"Point"}
}