{
  "type": "Feature",
  "properties": {
    "iso:country":"IT",
    "sg:address":"70020 Binetto",
    "sg:city":"Binetto",
    "sg:orig_category":"Prodotti Alimentari",
    "sg:phone":"+39 080 783 9073",
    "sg:postcode":"70020",
    "sg:province":"Bari",
    "wof:name":"Charlie Brown Di De Filippis Francesca & C. S.n.c.",
    "wof:placetype":"venue"
},
  "geometry": {"coordinates":[16.6173419952,40.9735374451],"type":"Point"}
}