{
  "type": "Feature",
  "properties": {
    "addr:full":"50031 Barberino Di Mugello Barberino di Mugello Firenze 50031",
    "addr:postcode":"50031;50031",
    "iso:country":"IT",
    "sg:address":"50031 Barberino Di Mugello",
    "sg:city":"Barberino di Mugello",
    "sg:orig_category":"Tessuti E Stoffe",
    "sg:phone":"+39 055 847 9124",
    "sg:postcode":"50031",
    "sg:province":"Firenze",
    "wof:name":"Emme Tre Pi (s.r.l.)",
    "wof:placetype":"venue"
},
  "geometry": {"coordinates":[11.230533,43.994846],"type":"Point"}
}