{
  "type": "Feature",
  "properties": {
    "addr:full":"41/a, Strada Statale Romana Nord 41012 Carpi Carpi Modena 41012",
    "addr:housenumber":"41 / a",
    "addr:postcode":"41012;41012",
    "addr:street":"Strada Statale Romana Nord",
    "iso:country":"IT",
    "sg:address":"41/a, Strada Statale Romana Nord 41012 Carpi",
    "sg:city":"Carpi",
    "sg:classifiers":[
        {
            "category":"Professional",
            "subcategory":"Engineering",
            "type":"Services"
        }
    ],
    "sg:phone":"+39 39059686771",
    "sg:postcode":"41012",
    "sg:province":"Modena",
    "sg:tags":[
        "machine",
        "-",
        "mechanical"
    ],
    "wof:name":"Steton (s.p.a.)",
    "wof:placetype":"venue"
},
  "geometry": {"coordinates":[10.881453,44.805523],"type":"Point"}
}