{
  "type": "Feature",
  "properties": {
    "iso:country":"IT",
    "sg:address":"22035 Canzo",
    "sg:city":"Canzo",
    "sg:orig_category":"Prodotti E Manufatti In Materie Plastiche",
    "sg:phone":"+39 031 681246",
    "sg:postcode":"22035",
    "sg:province":"Como",
    "sg:website":"http://www.italformcanzo.com",
    "wof:name":"Italform Snc",
    "wof:placetype":"venue"
},
  "geometry": {"coordinates":[9.27617836,45.8541259766],"type":"Point"}
}