{
  "type": "Feature",
  "properties": {
    "iso:country":"IT",
    "sg:address":"59011 Seano",
    "sg:city":"Seano",
    "sg:orig_category":"Macchine, Impianti E Forniture Per Industria Grafica, Cartaria E Cartotecnica",
    "sg:phone":"+39 055 870 5550",
    "sg:postcode":"59011",
    "sg:province":"Prato",
    "wof:name":"Para Srl",
    "wof:placetype":"venue"
},
  "geometry": {"coordinates":[11.02221,43.827732],"type":"Point"}
}