{
  "type": "Feature",
  "properties": {
    "addr:full":"55100 Lucca Lucca Lucca 55100",
    "addr:postcode":"55100;55100",
    "iso:country":"IT",
    "sg:address":"55100 Lucca",
    "sg:city":"Lucca",
    "sg:orig_category":"Servizi Ausiliari Dei Mezzi Di Trasporto",
    "sg:phone":"+39 0583 582626",
    "sg:postcode":"55100",
    "sg:province":"Lucca",
    "wof:name":"Aci Automobil Club",
    "wof:placetype":"venue"
},
  "geometry": {"coordinates":[10.493588,43.842506],"type":"Point"}
}