{
  "type": "Feature",
  "properties": {
    "addr:full":"20019 Settimo Milanese Settimo Milanese Milano 20019",
    "addr:postcode":"20019;20019",
    "iso:country":"IT",
    "sg:address":"20019 Settimo Milanese",
    "sg:city":"Settimo Milanese",
    "sg:orig_category":"Motori Ed Organi Di Trasmissione. Ricambi E Componenti Dei Mezzi Di Trasporto",
    "sg:phone":"+39 02 3350 2335",
    "sg:postcode":"20019",
    "sg:province":"Milano",
    "wof:name":"Vibi Spa",
    "wof:placetype":"venue"
},
  "geometry": {"coordinates":[9.0682010651,45.4773216248],"type":"Point"}
}