{
  "type": "Feature",
  "properties": {
    "iso:country":"IT",
    "sg:address":"24059 Urgnano",
    "sg:city":"Urgnano",
    "sg:orig_category":"Arredamenti - Produzione E Ingrosso",
    "sg:phone":"+39 035 891183",
    "sg:postcode":"24059",
    "sg:province":"Bergamo",
    "wof:name":"Point",
    "wof:placetype":"venue"
},
  "geometry": {"coordinates":[9.684789,45.639492],"type":"Point"}
}