{
  "type": "Feature",
  "properties": {
    "iso:country":"IT",
    "sg:address":"12080 Vicoforte",
    "sg:city":"Vicoforte",
    "sg:orig_category":"Macchine Ed Impianti Per Edilizia E Lavori Pubblici",
    "sg:phone":"+39 0174 563068",
    "sg:postcode":"12080",
    "sg:province":"Cuneo",
    "wof:name":"Mamino Vincenzo",
    "wof:placetype":"venue"
},
  "geometry": {"coordinates":[7.873308,44.373722],"type":"Point"}
}