{
  "type": "Feature",
  "properties": {
    "addr:full":"00146 Roma Roma Roma 00146",
    "addr:postcode":"00146;00146",
    "iso:country":"IT",
    "sg:address":"00146 Roma",
    "sg:city":"Roma",
    "sg:orig_category":"Antenne Radio-televisione",
    "sg:phone":"+39 06 5236 4489",
    "sg:postcode":"00146",
    "sg:province":"Roma",
    "wof:name":"Aaaaa Aba Di Balocchi Edoardo",
    "wof:placetype":"venue"
},
  "geometry": {"coordinates":[12.466446,41.864483],"type":"Point"}
}