{
  "type": "Feature",
  "properties": {
    "iso:country":"IT",
    "sg:address":"60010 Ostra Vetere",
    "sg:city":"Ostra",
    "sg:orig_category":"Audiovisivi Filmati, Spot E Multimediali - Realizzazione E Duplicazione",
    "sg:phone":"+39 071 963 9006",
    "sg:postcode":"60010",
    "sg:province":"Ancona",
    "sg:website":"http://www.digitalvideo.it",
    "wof:name":"Digital Video Productions Di Brunetti G & C. Snc",
    "wof:placetype":"venue"
},
  "geometry": {"coordinates":[13.060962,43.605366],"type":"Point"}
}