{
  "type": "Feature",
  "properties": {
    "addr:full":"6 Via Selva Casilina, 03100 Frosinone Frosinone Frosinone 03100",
    "addr:postcode":"03100;03100",
    "addr:street":"Via Selva Casilina",
    "iso:country":"IT",
    "sg:address":"6 Via Selva Casilina, 03100 Frosinone",
    "sg:city":"Frosinone",
    "sg:classifiers":[
        {
            "category":"Banks & Credit Unions",
            "subcategory":"Financial Services",
            "type":"Services"
        }
    ],
    "sg:phone":"+39 0775 270658",
    "sg:postcode":"03100",
    "sg:province":"Frosinone",
    "sg:tags":[
        "banking",
        "finance",
        "insurance"
    ],
    "wof:name":"Deltapol Sud Soc Coop Per Azioni A R L",
    "wof:placetype":"venue"
},
  "geometry": {"coordinates":[13.3290424347,41.6514587402],"type":"Point"}
}