{
  "type": "Feature",
  "properties": {
    "iso:country":"IT",
    "sg:address":"25012 Calvisano",
    "sg:city":"Calvisano",
    "sg:orig_category":"Macchine, Impianti Ed Attrezzature Per Agricoltura E Zootecnia. Prodotti Vari In Metallo. Apparecchiature E Sistemi Per Magazzinaggio E Movimentazione",
    "sg:phone":"+39 030 968042",
    "sg:postcode":"25012",
    "sg:province":"Brescia",
    "wof:name":"Agritech Srl",
    "wof:placetype":"venue"
},
  "geometry": {"coordinates":[10.338762,45.355072],"type":"Point"}
}