{
  "type": "Feature",
  "properties": {
    "iso:country":"IT",
    "sg:address":"10026 Santena",
    "sg:city":"Santena",
    "sg:orig_category":"Articoli Da Regalo. Arte Ed Artigianato Artistico. Shopping. Regalistica Aziendale",
    "sg:phone":"+39 011 949 3856",
    "sg:postcode":"10026",
    "sg:province":"Torino",
    "sg:website":"http://www.accademiacornici.it",
    "wof:name":"Centro Della Cornice",
    "wof:placetype":"venue"
},
  "geometry": {"coordinates":[7.416408,44.869869],"type":"Point"}
}