{
  "type": "Feature",
  "properties": {
    "iso:country":"IT",
    "sg:address":"38, Via Gaeta 03023 Ceccano",
    "sg:city":"Ceccano",
    "sg:classifiers":[
        {
            "category":"Food & Beverages",
            "subcategory":"Dairy",
            "type":"Retail Goods"
        }
    ],
    "sg:phone":"+39 0775 600861",
    "sg:postcode":"03023",
    "sg:province":"Frosinone",
    "sg:tags":[
        "product"
    ],
    "wof:name":"Prolatt Srl",
    "wof:placetype":"venue"
},
  "geometry": {"coordinates":[13.337976,41.621101],"type":"Point"}
}