{
  "type": "Feature",
  "properties": {
    "iso:country":"IT",
    "sg:address":"356, Via Appia 72100 Brindisi",
    "sg:city":"Brindisi",
    "sg:classifiers":[
        {
            "category":"Professional",
            "subcategory":"Business Services",
            "type":"Services"
        }
    ],
    "sg:phone":"+39 0831 586683",
    "sg:postcode":"72100",
    "sg:province":"Brindisi",
    "sg:tags":[
        "advice"
    ],
    "wof:name":"Istituto Professionale Alberghiero Di Stato",
    "wof:placetype":"venue"
},
  "geometry": {"coordinates":[17.927864,40.630821],"type":"Point"}
}