{
  "type": "Feature",
  "properties": {
    "addr:full":"50133 Firenze Firenze Firenze 50133",
    "addr:postcode":"50133;50133",
    "iso:country":"IT",
    "sg:address":"50133 Firenze",
    "sg:city":"Firenze",
    "sg:orig_category":"Serramenti Ed Infissi. Arte Ed Artigianato Artistico. Shopping",
    "sg:phone":"+39 055 579900",
    "sg:postcode":"50133",
    "sg:province":"Firenze",
    "wof:name":"Nanni Di Nanni Fabio Snc",
    "wof:placetype":"venue"
},
  "geometry": {"coordinates":[11.277887,43.796101],"type":"Point"}
}