{
  "type": "Feature",
  "properties": {
    "iso:country":"IT",
    "sg:address":"72, V. Arco Di Travertino 00178 Roma",
    "sg:city":"Roma",
    "sg:classifiers":[
        {
            "category":"Sports & Exercise",
            "subcategory":"Playing Field",
            "type":"Entertainment"
        }
    ],
    "sg:phone":"+39 06 7834 5184",
    "sg:postcode":"00178",
    "sg:province":"Roma",
    "sg:tags":[
        "game"
    ],
    "sg:website":"http://www.paginegialle.it/almavending",
    "wof:name":"Al.ma Vending Srl",
    "wof:placetype":"venue"
},
  "geometry": {"coordinates":[12.535077,41.866028],"type":"Point"}
}