{
  "type": "Feature",
  "properties": {
    "addr:full":"24025 Gazzaniga Gazzaniga Bergamo 24025",
    "addr:postcode":"24025;24025",
    "iso:country":"IT",
    "sg:address":"24025 Gazzaniga",
    "sg:city":"Gazzaniga",
    "sg:orig_category":"Cromatura E Nichelatura",
    "sg:phone":"+39 035 712033",
    "sg:postcode":"24025",
    "sg:province":"Bergamo",
    "wof:name":"Riporti Industriali Srl",
    "wof:placetype":"venue"
},
  "geometry": {"coordinates":[9.827325,45.788605],"type":"Point"}
}