{
  "type": "Feature",
  "properties": {
    "iso:country":"IT",
    "sg:address":"35047 Solesino",
    "sg:city":"Solesino",
    "sg:classifiers":[
        {
            "category":"Building & Trades",
            "subcategory":"Equipment Rental",
            "type":"Services"
        }
    ],
    "sg:phone":"+39 0429 707000",
    "sg:postcode":"35047",
    "sg:province":"Padova",
    "sg:tags":[
        "services",
        "refrigeration",
        "accommodation",
        "supply"
    ],
    "sg:website":"http://www.eurocryor.it",
    "wof:name":"Euro' Cryor Spa",
    "wof:placetype":"venue"
},
  "geometry": {"coordinates":[11.748822,45.178818],"type":"Point"}
}