{
  "type": "Feature",
  "properties": {
    "addr:full":"81031 Aversa Aversa Caserta 81031",
    "addr:postcode":"81031;81031",
    "iso:country":"IT",
    "sg:address":"81031 Aversa",
    "sg:city":"Aversa",
    "sg:orig_category":"Agenzie Immobiliari",
    "sg:phone":"+39 081 811 1575",
    "sg:postcode":"81031",
    "sg:province":"Caserta",
    "wof:name":"Immobiliare Mattiello Di Mattiello Anna Maria",
    "wof:placetype":"venue"
},
  "geometry": {"coordinates":[14.334456,41.070026],"type":"Point"}
}