{
  "type": "Feature",
  "properties": {
    "iso:country":"IT",
    "sg:address":"Via Sarzanese 1216 55100 Lucca",
    "sg:city":"Lucca",
    "sg:classifiers":[
        {
            "category":"Exhibition Hall",
            "type":"Public Place"
        }
    ],
    "sg:phone":"+39 0583 327766",
    "sg:postcode":"55100",
    "sg:province":"Lucca",
    "sg:tags":[
        "equipping",
        "sale",
        "room",
        "show"
    ],
    "sg:website":"www.comas-arredamenti.it",
    "wof:name":"Co.m.a.s. S.r.l.",
    "wof:placetype":"venue"
},
  "geometry": {"coordinates":[10.453727,43.851498],"type":"Point"}
}