{
  "type": "Feature",
  "properties": {
    "iso:country":"IT",
    "sg:address":"205, Via Per Ospitaletto 25046 Cazzago San Martino",
    "sg:city":"Cazzago San Martino",
    "sg:classifiers":[
        {
            "category":"Manufacturing",
            "subcategory":"Metals",
            "type":"Manufacturing & Wholesale Goods"
        }
    ],
    "sg:phone":"+39 030 775 1611",
    "sg:postcode":"25046",
    "sg:province":"Brescia",
    "sg:tags":[
        "metallurgy",
        "metalworking"
    ],
    "wof:name":"Nex Line Srl",
    "wof:placetype":"venue"
},
  "geometry": {"coordinates":[10.0566196442,45.5720901489],"type":"Point"}
}