{
  "type": "Feature",
  "properties": {
    "iso:country":"IT",
    "sg:address":"40064 Ozzano Dell'emilia",
    "sg:orig_category":"Biliardi Ed Accessori",
    "sg:phone":"+39 051 799315",
    "sg:postcode":"40064",
    "sg:province":"Bologna",
    "sg:website":"http://www.biliardilatti.it",
    "wof:name":"Laffi Mauro",
    "wof:placetype":"venue"
},
  "geometry": {"coordinates":[11.435963,44.460243],"type":"Point"}
}