{
  "type": "Feature",
  "properties": {
    "addr:full":"Via Del Botteghino 24/26; Scandicci; Firenze; 50018 Scandicci Firenze 50018",
    "addr:housenumber":"24 / 26",
    "addr:postcode":"50018;50018",
    "addr:street":"Via Del Botteghino",
    "iso:country":"IT",
    "sg:address":"Via Del Botteghino 24/26; Scandicci; Firenze; 50018",
    "sg:city":"Scandicci",
    "sg:classifiers":[
        {
            "category":"Industrial Area",
            "type":"Public Place"
        }
    ],
    "sg:phone":"+39 390 557 2901",
    "sg:postcode":"50018",
    "sg:province":"Firenze",
    "sg:tags":[
        "large",
        "private"
    ],
    "sg:website":"www.sdb.it",
    "wof:name":"Savino Del Bene S.p.a",
    "wof:placetype":"venue"
},
  "geometry": {"coordinates":[11.1589250565,43.7688560486],"type":"Point"}
}