{
  "type": "Feature",
  "properties": {
    "iso:country":"IT",
    "sg:address":"12011 Borgo San Dalmazzo",
    "sg:city":"Borgo San Dalmazzo",
    "sg:orig_category":"Macchine Utensili E Impianti",
    "sg:phone":"+39 0171 265276",
    "sg:postcode":"12011",
    "sg:province":"Cuneo",
    "wof:name":"M.o. Di Rovera & C.sas",
    "wof:placetype":"venue"
},
  "geometry": {"coordinates":[7.507151,44.342911],"type":"Point"}
}