{
  "type": "Feature",
  "properties": {
    "iso:country":"IT",
    "sg:address":"50022 Greve In Chianti",
    "sg:city":"Greve in Chianti",
    "sg:orig_category":"Restaurants And Related Public Premises. Sport And Leisure, Services. Hotels And Hotel Facilities. Restaurants And Similar",
    "sg:phone":"+39 055 858 6103",
    "sg:postcode":"50022",
    "sg:province":"Firenze",
    "wof:name":"Il Leccio Agriturismo Di Landi",
    "wof:placetype":"venue"
},
  "geometry": {"coordinates":[11.320416,43.590641],"type":"Point"}
}