{
  "type": "Feature",
  "properties": {
    "addr:full":"Km 17,150, S.s. 387 09041 Dolianova Dolianova Cagliari 09041",
    "addr:housenumber":"17,150",
    "addr:postcode":"09041;09041",
    "addr:street":"S.S. 387",
    "iso:country":"IT",
    "sg:address":"Km 17,150, S.s. 387 09041 Dolianova",
    "sg:city":"Dolianova",
    "sg:classifiers":[
        {
            "category":"Food & Beverages",
            "subcategory":"Groceries & Convenience Stores",
            "type":"Retail Goods"
        }
    ],
    "sg:phone":"+39 39070744101",
    "sg:postcode":"09041",
    "sg:province":"Cagliari",
    "sg:tags":[
        "drink"
    ],
    "sg:website":"http://www.cantinedolianova.com:ws_end: :mark:ws:http://www.paginegialle.it/cantdol",
    "wof:name":"Cantine Di Dolianova",
    "wof:placetype":"venue"
},
  "geometry": {"coordinates":[9.109228,39.215458],"type":"Point"}
}