{
  "type": "Feature",
  "properties": {
    "addr:full":"19, Via Magenta 23871 Lomagna Lomagna Lecco 23871",
    "addr:postcode":"23871;23871",
    "addr:street":"Via Magenta",
    "iso:country":"IT",
    "sg:address":"19, Via Magenta 23871 Lomagna",
    "sg:city":"Lomagna",
    "sg:classifiers":[
        {
            "category":"Shopping",
            "type":"Retail Goods"
        }
    ],
    "sg:phone":"+39 039 530 0615",
    "sg:postcode":"23871",
    "sg:province":"Lecco",
    "sg:tags":[
        "finished",
        "-",
        "metallic"
    ],
    "wof:name":"Costruzioni Meccaniche Speciali (s.r.l.)",
    "wof:placetype":"venue"
},
  "geometry": {"coordinates":[9.3722877502,45.6661491394],"type":"Point"}
}