{
  "type": "Feature",
  "properties": {
    "iso:country":"IT",
    "sg:address":"20019 Settimo Milanese",
    "sg:city":"Settimo Milanese",
    "sg:orig_category":"Congressi E Conferenze - Organizzazione E Servizi",
    "sg:phone":"+39 02 4391 1641",
    "sg:postcode":"20019",
    "sg:province":"Milano",
    "wof:name":"Allestimenti Corrado Carmine E Corrado Marco Snc",
    "wof:placetype":"venue"
},
  "geometry": {"coordinates":[9.074924,45.472931],"type":"Point"}
}