{
  "type": "Feature",
  "properties": {
    "iso:country":"IT",
    "sg:address":"20144 Milano",
    "sg:city":"Milano",
    "sg:orig_category":"Pelliccerie",
    "sg:phone":"+39 02 463431",
    "sg:postcode":"20144",
    "sg:province":"Milano",
    "wof:name":"Frigerio Pellicce Srl",
    "wof:placetype":"venue"
},
  "geometry": {"coordinates":[9.1628541946,45.4662666321],"type":"Point"}
}