{
  "type": "Feature",
  "properties": {
    "iso:country":"IT",
    "sg:address":"64/b, Via Giuseppe Garibaldi 26010 Monte Cremasco",
    "sg:city":"Monte Cremasco",
    "sg:classifiers":[
        {
            "category":"Sports & Exercise",
            "subcategory":"Playing Field",
            "type":"Entertainment"
        }
    ],
    "sg:phone":"+39 0373 791281",
    "sg:postcode":"26010",
    "sg:province":"Cremona",
    "sg:tags":[
        "game"
    ],
    "wof:name":"Monte Di Bolzoni Fiorenzo & C. (s.n.c.)",
    "wof:placetype":"venue"
},
  "geometry": {"coordinates":[10.026135,45.133499],"type":"Point"}
}