{
  "type": "Feature",
  "properties": {
    "iso:country":"IT",
    "sg:address":"Via Cassia 791; Roma",
    "sg:classifiers":[
        {
            "category":"Banks & Credit Unions",
            "subcategory":"Bank",
            "type":"Services"
        }
    ],
    "sg:phone":"+39 06 3326 0000",
    "wof:name":"Banca Di Roma",
    "wof:placetype":"venue"
},
  "geometry": {"coordinates":[12.440961,41.966362],"type":"Point"}
}