{
  "type": "Feature",
  "properties": {
    "iso:country":"IT",
    "sg:address":"17051 Andora",
    "sg:city":"Andora",
    "sg:orig_category":"Alberghi E Strutture Extra Alberghiere. Ospedali E Servizi Sanitari",
    "sg:phone":"+39 0182 684578",
    "sg:postcode":"17051",
    "sg:province":"Savona",
    "wof:name":"Colonia Marina Comune Milano",
    "wof:placetype":"venue"
},
  "geometry": {"coordinates":[8.122932,43.987587],"type":"Point"}
}