{
  "type": "Feature",
  "properties": {
    "iso:country":"IT",
    "sg:address":"302/306, V. F. Di Benedetto 00173 Roma",
    "sg:city":"Roma",
    "sg:classifiers":[
        {
            "category":"Bars & Pubs",
            "subcategory":"Nightclub",
            "type":"Food & Drink"
        }
    ],
    "sg:phone":"+39 06 7267 0925",
    "sg:postcode":"00173",
    "sg:province":"Roma",
    "sg:tags":[
        "cake",
        "bread"
    ],
    "sg:website":"http://www.paginegialle.it/gelofood",
    "wof:name":"Gelo Food Srl",
    "wof:placetype":"venue"
},
  "geometry": {"coordinates":[12.598035,41.8396],"type":"Point"}
}