{
  "type": "Feature",
  "properties": {
    "iso:country":"IT",
    "sg:address":"20135 Milano",
    "sg:city":"Milano",
    "sg:classifiers":[
        {
            "category":"Professional",
            "subcategory":"Management & Consulting",
            "type":"Services"
        }
    ],
    "sg:phone":"+39 02 802 8181",
    "sg:postcode":"20135",
    "sg:province":"Milano",
    "sg:tags":[
        "control",
        "information",
        "auxiliary",
        "consultant",
        "support",
        "-",
        "analysis",
        "automation",
        "companies",
        "services",
        "events",
        "research",
        "technology",
        "trade",
        "machines"
    ],
    "sg:website":"http://www.individuallearning.it",
    "wof:name":"Individual Training Srl",
    "wof:placetype":"venue"
},
  "geometry": {"coordinates":[9.18723,45.470531],"type":"Point"}
}