{
  "type": "Feature",
  "properties": {
    "iso:country":"IT",
    "sg:address":"Via Chieri 61 10020 Andezeno",
    "sg:city":"Andezeno",
    "sg:classifiers":[
        {
            "category":"Manufacturing",
            "subcategory":"Pet Food",
            "type":"Manufacturing & Wholesale Goods"
        }
    ],
    "sg:phone":"+39 011 943 3311",
    "sg:postcode":"10020",
    "sg:province":"Torino",
    "sg:tags":[
        "speciality",
        "animal"
    ],
    "sg:website":"www.morando.it",
    "wof:name":"Morando Spa",
    "wof:placetype":"venue"
},
  "geometry": {"coordinates":[7.788448,45.036049],"type":"Point"}
}