{
  "type": "Feature",
  "properties": {
    "iso:country":"IT",
    "sg:address":"3476, Via Emilia 47020 Longiano",
    "sg:city":"Longiano",
    "sg:classifiers":[
        {
            "category":"Professional",
            "subcategory":"Engineering",
            "type":"Services"
        }
    ],
    "sg:phone":"+39 39054754054",
    "sg:postcode":"47020",
    "sg:province":"Forl\u00ec-Cesena",
    "sg:tags":[
        "machine",
        "-",
        "mechanical"
    ],
    "wof:name":"Illea (s.r.l.)",
    "wof:placetype":"venue"
},
  "geometry": {"coordinates":[12.328774,44.106544],"type":"Point"}
}