{
  "type": "Feature",
  "properties": {
    "iso:country":"IT",
    "sg:address":"20090 Opera",
    "sg:city":"Opera",
    "sg:orig_category":"Forniture Per Attivita' Industriali",
    "sg:phone":"+39 02 5760 1217",
    "sg:postcode":"20090",
    "sg:province":"Milano",
    "wof:name":"Kosmik Ruote Srl",
    "wof:placetype":"venue"
},
  "geometry": {"coordinates":[9.2089939117,45.3700180054],"type":"Point"}
}