{
  "type": "Feature",
  "properties": {
    "iso:country":"IT",
    "sg:address":"47900 Rimini",
    "sg:city":"Rimini",
    "sg:orig_category":"Trattamenti Termici E Superficiali Metalli, Galvanotecnica",
    "sg:phone":"+39 0541 741004",
    "sg:postcode":"47900",
    "sg:province":"Rimini",
    "wof:name":"Zincaturificio Romagnolo",
    "wof:placetype":"venue"
},
  "geometry": {"coordinates":[12.57964,44.058025],"type":"Point"}
}