{
  "type": "Feature",
  "properties": {
    "iso:country":"IT",
    "sg:address":"36051 Creazzo",
    "sg:city":"Creazzo",
    "sg:orig_category":"Lamiere - Commercio",
    "sg:phone":"+39 0444 520222",
    "sg:postcode":"36051",
    "sg:province":"Vicenza",
    "wof:name":"Nuova Co.si.vi. Srl",
    "wof:placetype":"venue"
},
  "geometry": {"coordinates":[11.496325,45.530422],"type":"Point"}
}