{
  "type": "Feature",
  "properties": {
    "addr:full":"95021 Aci Castello Aci Castello Catania 95021",
    "addr:postcode":"95021;95021",
    "iso:country":"IT",
    "sg:address":"95021 Aci Castello",
    "sg:city":"Aci Castello",
    "sg:orig_category":"Fiori E Piante - Ingrosso",
    "sg:phone":"+39 095 711 1177",
    "sg:postcode":"95021",
    "sg:province":"Catania",
    "wof:name":"Marano Giuseppa",
    "wof:placetype":"venue"
},
  "geometry": {"coordinates":[15.1331110001,37.5451660156],"type":"Point"}
}