{
  "type": "Feature",
  "properties": {
    "iso:country":"IT",
    "sg:address":"22100 Como",
    "sg:city":"Como",
    "sg:orig_category":"Servizi E Lavori Per Abbigliamento E Pelletterie",
    "sg:phone":"+39 031 261068",
    "sg:postcode":"22100",
    "sg:province":"Como",
    "wof:name":"Mostes Ines",
    "wof:placetype":"venue"
},
  "geometry": {"coordinates":[9.114847,45.791267],"type":"Point"}
}