{
  "type": "Feature",
  "properties": {
    "addr:full":"70043 Monopoli Monopoli Bari 70043",
    "addr:postcode":"70043;70043",
    "iso:country":"IT",
    "sg:address":"70043 Monopoli",
    "sg:city":"Monopoli",
    "sg:orig_category":"Dischi, Musicassette E Compact Disc - Vendita Al Dettaglio",
    "sg:phone":"+39 080 937 1588",
    "sg:postcode":"70043",
    "sg:province":"Bari",
    "sg:website":"http://www.diapasonhifi.it",
    "wof:name":"Diapason",
    "wof:placetype":"venue"
},
  "geometry": {"coordinates":[16.87034,41.001892],"type":"Point"}
}