{
  "type": "Feature",
  "properties": {
    "iso:country":"IT",
    "sg:address":"21100 Varese",
    "sg:city":"Varese",
    "sg:orig_category":"Non-classified Establishments",
    "sg:phone":"+39 0332 260799",
    "sg:postcode":"21100",
    "sg:province":"Varese",
    "wof:name":"Binda Stefania",
    "wof:placetype":"venue"
},
  "geometry": {"coordinates":[8.855154,45.801712],"type":"Point"}
}