{
  "type": "Feature",
  "properties": {
    "iso:country":"IT",
    "sg:address":"2, V. Della Repubblica 24064 Grumello Del Monte",
    "sg:city":"Grumello del Monte",
    "sg:classifiers":[
        {
            "category":"Shopping",
            "subcategory":"Clothing, Apparel, & Fashions",
            "type":"Retail Goods"
        }
    ],
    "sg:phone":"+39 39035833085",
    "sg:postcode":"24064",
    "sg:province":"Bergamo",
    "sg:tags":[
        "clothing",
        "accessory"
    ],
    "sg:website":"http://www.fec-serilabel.it:ws_end: :mark:ws:http://www.paginegialle.it/serilabel",
    "wof:name":"Etichettificio Fec",
    "wof:placetype":"venue"
},
  "geometry": {"coordinates":[9.899677,45.62199],"type":"Point"}
}