{
  "type": "Feature",
  "properties": {
    "iso:country":"IT",
    "sg:address":"00191 Roma",
    "sg:city":"Roma",
    "sg:orig_category":"Impiantistica E Prodotti Tecnologici Per Edilizia",
    "sg:phone":"+39 06 333 6677",
    "sg:postcode":"00191",
    "sg:province":"Roma",
    "sg:website":"http://www.mazzarda.it",
    "wof:name":"Mazzarda Marco Antonio Srl",
    "wof:placetype":"venue"
},
  "geometry": {"coordinates":[12.466977,41.935493],"type":"Point"}
}