{
  "type": "Feature",
  "properties": {
    "iso:country":"IT",
    "sg:address":"27100 Pavia",
    "sg:city":"Pavia",
    "sg:orig_category":"Tessuti Arredamento, Tende E Tappeti. Forniture Per Edilizia E Lavori Pubblici",
    "sg:phone":"+39 0382 572385",
    "sg:postcode":"27100",
    "sg:province":"Pavia",
    "wof:name":"Garlaschelli Giorgio",
    "wof:placetype":"venue"
},
  "geometry": {"coordinates":[9.159796,45.20089],"type":"Point"}
}