{
  "type": "Feature",
  "properties": {
    "addr:full":"Via Caselle 25081 Bedizzole Bedizzole Brescia 25081",
    "addr:postcode":"25081;25081",
    "addr:street":"Via Caselle",
    "iso:country":"IT",
    "sg:address":"Via Caselle 25081 Bedizzole",
    "sg:city":"Bedizzole",
    "sg:classifiers":[
        {
            "category":"Manufacturing",
            "subcategory":"Metals",
            "type":"Manufacturing & Wholesale Goods"
        }
    ],
    "sg:phone":"+39 030 687 2006",
    "sg:postcode":"25081",
    "sg:province":"Brescia",
    "sg:tags":[
        "metallurgy",
        "metalworking"
    ],
    "wof:name":"Fima (s.r.l.)",
    "wof:placetype":"venue"
},
  "geometry": {"coordinates":[11.1159410477,45.4183425903],"type":"Point"}
}