{
  "type": "Feature",
  "properties": {
    "iso:country":"IT",
    "sg:address":"20019 Settimo Milanese",
    "sg:city":"Settimo Milanese",
    "sg:orig_category":"Ricambi E Componenti Dei Mezzi Di Trasporto",
    "sg:phone":"+39 02 3350 1993",
    "sg:postcode":"20019",
    "sg:province":"Milano",
    "wof:name":"Do.ri. Snc",
    "wof:placetype":"venue"
},
  "geometry": {"coordinates":[9.05761,45.488724],"type":"Point"}
}