{
  "type": "Feature",
  "properties": {
    "addr:full":"00154 Roma Roma Roma 00154",
    "addr:postcode":"00154;00154",
    "iso:country":"IT",
    "sg:address":"00154 Roma",
    "sg:city":"Roma",
    "sg:orig_category":"Ospedali E Servizi Sanitari",
    "sg:phone":"+39 06 578 1819",
    "sg:postcode":"00154",
    "sg:province":"Roma",
    "wof:name":"Lotti Stefano",
    "wof:placetype":"venue"
},
  "geometry": {"coordinates":[12.486789,41.870888],"type":"Point"}
}