{
  "type": "Feature",
  "properties": {
    "addr:full":"90138 Palermo Palermo Palermo 90138",
    "addr:postcode":"90138;90138",
    "iso:country":"IT",
    "sg:address":"90138 Palermo",
    "sg:city":"Palermo",
    "sg:orig_category":"Articoli Da Regalo. Arte Ed Artigianato Artistico. Shopping. Regalistica Aziendale",
    "sg:phone":"+39 091 324839",
    "sg:postcode":"90138",
    "sg:province":"Palermo",
    "wof:name":"Rz Cornici",
    "wof:placetype":"venue"
},
  "geometry": {"coordinates":[13.348008,38.121845],"type":"Point"}
}