{
  "type": "Feature",
  "properties": {
    "iso:country":"IT",
    "sg:address":"39040 Ora",
    "sg:city":"Ora",
    "sg:orig_category":"Lavanderie Industriali E Noleggio Biancheria",
    "sg:phone":"+39 0471 802012",
    "sg:postcode":"39040",
    "sg:province":"Bolzano/Bozen",
    "wof:name":"Haas Markus & Christian Snc",
    "wof:placetype":"venue"
},
  "geometry": {"coordinates":[11.308475,46.348572],"type":"Point"}
}