{
  "type": "Feature",
  "properties": {
    "addr:full":"00013 Mentana Mentana Roma 00013",
    "addr:postcode":"00013;00013",
    "iso:country":"IT",
    "sg:address":"00013 Mentana",
    "sg:city":"Mentana",
    "sg:orig_category":"Termotecnica E Riscaldamento, Apparecchiature E Servizi",
    "sg:phone":"+39 06 905 0667",
    "sg:postcode":"00013",
    "sg:province":"Roma",
    "wof:name":"I.tic 98 Srl",
    "wof:placetype":"venue"
},
  "geometry": {"coordinates":[12.702301,42.05336],"type":"Point"}
}