{
  "type": "Feature",
  "properties": {
    "iso:country":"IT",
    "sg:address":"80023 Caivano",
    "sg:city":"Caivano",
    "sg:orig_category":"Scuole E Servizi Scolastici. Centri Di Estetica E Cosmesi E Servizi. Ricerca, Selezione E Formazione Del Personale",
    "sg:phone":"+39 081 835 3446",
    "sg:postcode":"80023",
    "sg:province":"Napoli",
    "wof:name":"Isen Di Daino Luigi Scuola Di Estetica",
    "wof:placetype":"venue"
},
  "geometry": {"coordinates":[14.34449,40.912373],"type":"Point"}
}