{
  "type": "Feature",
  "properties": {
    "addr:full":"56013 Marina Di Pisa PI",
    "addr:postcode":"56013",
    "addr:street":"Di Pisa Pi",
    "iso:country":"IT",
    "sg:address":"56013 Marina Di Pisa",
    "sg:orig_category":"Servizi Per Lo Sport E Il Tempo Libero. Servizi Ausiliari Dei Mezzi Di Trasporto",
    "sg:phone":"+39 050 35774",
    "sg:province":"PI",
    "wof:name":"Mariani Giuseppe",
    "wof:placetype":"venue"
},
  "geometry": {"coordinates":[10.301351,43.676479],"type":"Point"}
}