{
  "type": "Feature",
  "properties": {
    "iso:country":"IT",
    "sg:address":"36100 Vicenza",
    "sg:city":"Polegge",
    "sg:orig_category":"Modelli E Plastici",
    "sg:phone":"+39 0444 946185",
    "sg:postcode":"36100",
    "sg:province":"Vicenza",
    "sg:website":"http://www.plasticiporro.it",
    "wof:name":"Stefano Porro",
    "wof:placetype":"venue"
},
  "geometry": {"coordinates":[11.546546936,45.5915184021],"type":"Point"}
}