{
  "type": "Feature",
  "properties": {
    "iso:country":"IT",
    "sg:address":"20021 Baranzate",
    "sg:city":"Baranzate",
    "sg:orig_category":"Studi E Consulenze Tecniche E Industriali. Assicurazioni E Servizi Assicurativi. Consulenze Tecniche, Amministrative E Perizie",
    "sg:phone":"+39 02 3820 0148",
    "sg:postcode":"20021",
    "sg:province":"Milano",
    "wof:name":"Robecchi Enrico",
    "wof:placetype":"venue"
},
  "geometry": {"coordinates":[9.122062,45.522202],"type":"Point"}
}