{
  "type": "Feature",
  "properties": {
    "iso:country":"IT",
    "sg:address":"Via A. Figino 66 20016 Pero",
    "sg:city":"Pero",
    "sg:classifiers":[
        {
            "category":"Real Estate",
            "subcategory":"Surveying",
            "type":"Services"
        }
    ],
    "sg:phone":"+39 02 353 6700",
    "sg:postcode":"20016",
    "sg:province":"Milano",
    "sg:tags":[
        "stationery",
        "writing",
        "material",
        "creative"
    ],
    "wof:name":"Cwr Srl",
    "wof:placetype":"venue"
},
  "geometry": {"coordinates":[9.076372,45.504906],"type":"Point"}
}