{
  "type": "Feature",
  "properties": {
    "addr:full":"23844 Sirone Sirone Lecco 23844",
    "addr:postcode":"23844;23844",
    "iso:country":"IT",
    "sg:address":"23844 Sirone",
    "sg:city":"Sirone",
    "sg:orig_category":"Ricambi E Componenti Auto - Produzione",
    "sg:phone":"+39 031 850361",
    "sg:postcode":"23844",
    "sg:province":"Lecco",
    "wof:name":"Laces Di Spreafico Vitale & C. Snc",
    "wof:placetype":"venue"
},
  "geometry": {"coordinates":[9.326179,45.775585],"type":"Point"}
}