{
  "type": "Feature",
  "properties": {
    "iso:country":"IT",
    "sg:address":"45036 Ficarolo",
    "sg:city":"Ficarolo",
    "sg:orig_category":"Termotecnica E Riscaldamento, Apparecchiature E Servizi",
    "sg:phone":"+39 0425 727234",
    "sg:postcode":"45036",
    "sg:province":"Rovigo",
    "wof:name":"Donegatti Matteo",
    "wof:placetype":"venue"
},
  "geometry": {"coordinates":[11.447268,44.959045],"type":"Point"}
}