{
  "type": "Feature",
  "properties": {
    "iso:country":"IT",
    "sg:address":"16139 Genova",
    "sg:city":"Genova",
    "sg:classifiers":[
        {
            "category":"Health Services",
            "subcategory":"Health Practitioner",
            "type":"Services"
        }
    ],
    "sg:phone":"+39 010 839 8552",
    "sg:postcode":"16139",
    "sg:province":"Genova",
    "sg:tags":[
        "medici"
    ],
    "wof:name":"Farese Antonio",
    "wof:placetype":"venue"
},
  "geometry": {"coordinates":[8.954062,44.416954],"type":"Point"}
}