{
  "type": "Feature",
  "properties": {
    "iso:country":"IT",
    "sg:address":"87066 Longobucco",
    "sg:city":"Longobucco",
    "sg:orig_category":"Biancheria, Telerie E Coperte. Arredo Camera Letto E Complementi",
    "sg:phone":"+39 0983 71048",
    "sg:postcode":"87066",
    "sg:province":"Cosenza",
    "wof:name":"Cav. Mario Celestino",
    "wof:placetype":"venue"
},
  "geometry": {"coordinates":[16.611992,39.448097],"type":"Point"}
}