{
  "type": "Feature",
  "properties": {
    "iso:country":"IT",
    "sg:address":"25019 Sirmione",
    "sg:city":"Sirmione",
    "sg:orig_category":"Alberghi",
    "sg:phone":"+39 030 919383",
    "sg:postcode":"25019",
    "sg:province":"Brescia",
    "wof:name":"Hotel Alsazia Di Rizzi Roberto",
    "wof:placetype":"venue"
},
  "geometry": {"coordinates":[10.20856,45.531498],"type":"Point"}
}