{
  "type": "Feature",
  "properties": {
    "iso:country":"IT",
    "sg:address":"168, Via Latisana 33054 Lignano Sabbiadoro",
    "sg:city":"Lignano Sabbiadoro",
    "sg:classifiers":[
        {
            "category":"Travel",
            "subcategory":"Travel Agent",
            "type":"Entertainment"
        }
    ],
    "sg:phone":"+39 39043171489",
    "sg:postcode":"33054",
    "sg:province":"Udine",
    "sg:tags":[
        "business"
    ],
    "wof:name":"Hotel Consuelo",
    "wof:placetype":"venue"
},
  "geometry": {"coordinates":[13.130033,45.685932],"type":"Point"}
}