{
  "type": "Feature",
  "properties": {
    "iso:country":"IT",
    "sg:address":"10, Via Fosse Ardeatine 86100 Campobasso",
    "sg:city":"Campobasso",
    "sg:classifiers":[
        {
            "category":"Building & Trades",
            "subcategory":"Construction",
            "type":"Services"
        }
    ],
    "sg:phone":"+39 39087467476",
    "sg:postcode":"86100",
    "sg:province":"Campobasso",
    "sg:tags":[
        "work",
        "public"
    ],
    "wof:name":"Del Busso Giovanni",
    "wof:placetype":"venue"
},
  "geometry": {"coordinates":[14.668536,41.562237],"type":"Point"}
}