{
  "type": "Feature",
  "properties": {
    "iso:country":"IT",
    "sg:address":"30036 Santa Maria Di Sala",
    "sg:city":"Santa Maria di Sala",
    "sg:orig_category":"Dolciumi E Gelati. Shopping",
    "sg:phone":"+39 041 573 0375",
    "sg:postcode":"30036",
    "sg:province":"Venezia",
    "wof:name":"Gelateria 4\u00b0 Pianeta",
    "wof:placetype":"venue"
},
  "geometry": {"coordinates":[12.002378,45.480961],"type":"Point"}
}