{
  "type": "Feature",
  "properties": {
    "iso:country":"IT",
    "sg:address":"31040 Mansu\u00e8",
    "sg:orig_category":"Materie Plastiche - Produzione E Lavorazione",
    "sg:phone":"+39 0422 741849",
    "sg:postcode":"31040",
    "sg:province":"Treviso",
    "wof:name":"Tecno System Srl",
    "wof:placetype":"venue"
},
  "geometry": {"coordinates":[12.53471,45.811646],"type":"Point"}
}