{
  "type": "Feature",
  "properties": {
    "iso:country":"IT",
    "sg:address":"52028 Terranuova Bracciolini",
    "sg:city":"Terranuova Bracciolini",
    "sg:orig_category":"Forniture Per Abbigliamento E Pelletterie",
    "sg:phone":"+39 055 970 3985",
    "sg:postcode":"52028",
    "sg:province":"Arezzo",
    "wof:name":"Lauria Rocco Eredi",
    "wof:placetype":"venue"
},
  "geometry": {"coordinates":[11.5930271149,43.5630493164],"type":"Point"}
}