{
  "type": "Feature",
  "properties": {
    "iso:country":"IT",
    "sg:address":"Km. 1.500, Strada Provinciale 14 95032 Belpasso",
    "sg:city":"Belpasso",
    "sg:classifiers":[
        {
            "category":"Utilities",
            "subcategory":"Electric",
            "type":"Services"
        }
    ],
    "sg:phone":"+39 095 713 1689",
    "sg:postcode":"95032",
    "sg:province":"Catania",
    "sg:tags":[
        "component",
        "electronic"
    ],
    "wof:name":"Sudelettrica S.p.a.",
    "wof:placetype":"venue"
},
  "geometry": {"coordinates":[14.927204,37.520317],"type":"Point"}
}