{
  "type": "Feature",
  "properties": {
    "addr:full":"24129 Bergamo Bergamo Bergamo 24129",
    "addr:postcode":"24129;24129",
    "iso:country":"IT",
    "sg:address":"24129 Bergamo",
    "sg:city":"Bergamo",
    "sg:orig_category":"Ospedali E Servizi Sanitari",
    "sg:phone":"+39 035 255060",
    "sg:postcode":"24129",
    "sg:province":"Bergamo",
    "wof:name":"Duebi Laboratorio Odontotecnico Di Bassanelli E Bertuletti",
    "wof:placetype":"venue"
},
  "geometry": {"coordinates":[9.632908,45.694233],"type":"Point"}
}