{
  "type": "Feature",
  "properties": {
    "addr:full":"65023 Caramanico Terme Caramanico Terme Pescara 65023",
    "addr:postcode":"65023;65023",
    "addr:street":"Terme",
    "iso:country":"IT",
    "sg:address":"65023 Caramanico Terme",
    "sg:city":"Caramanico Terme",
    "sg:orig_category":"Servizi Per Lo Sport E Il Tempo Libero. Servizi Al Turismo. Acqua, Luce, Gas E Societa' Di Esercizio Pubblico",
    "sg:phone":"+39 085 923 1001",
    "sg:postcode":"65023",
    "sg:province":"Pescara",
    "wof:name":"Coord.territ.x L'amb.del Parco Naz.della Majella Del Corpo Forest.dello Stato.",
    "wof:placetype":"venue"
},
  "geometry": {"coordinates":[13.914934,42.21497],"type":"Point"}
}