{
  "type": "Feature",
  "properties": {
    "addr:full":"9, Via Natta 25036 Palazzolo Sull'oglio Brescia 25036",
    "addr:postcode":"25036;25036",
    "addr:street":"Via Natta",
    "iso:country":"IT",
    "sg:address":"9, Via Natta 25036 Palazzolo Sull'oglio",
    "sg:orig_category":"Miscellaneous Products",
    "sg:phone":"+39 030 740 1537",
    "sg:postcode":"25036",
    "sg:province":"Brescia",
    "wof:name":"Duepi Di E. Plebani & C. (s.n.c.)",
    "wof:placetype":"venue"
},
  "geometry": {"coordinates":[9.8879137039,45.5866584778],"type":"Point"}
}