{
  "type": "Feature",
  "properties": {
    "iso:country":"IT",
    "sg:address":"20123 Milano",
    "sg:city":"Milano",
    "sg:orig_category":"Lavoro Interinale E Temporaneo",
    "sg:phone":"+39 02 833871",
    "sg:postcode":"20123",
    "sg:province":"Milano",
    "sg:website":"http://www.quantagruppo.it",
    "wof:name":"Quanta Spa Soc. Fornitura Di Lavoro Temporaneo",
    "wof:placetype":"venue"
},
  "geometry": {"coordinates":[9.186123,45.464905],"type":"Point"}
}