{
  "type": "Feature",
  "properties": {
    "iso:country":"IT",
    "sg:address":"09124 Cagliari",
    "sg:city":"Cagliari",
    "sg:orig_category":"Forniture Per Uffici",
    "sg:phone":"+39 070 669145",
    "sg:postcode":"09124",
    "sg:province":"Cagliari",
    "wof:name":"Fratelli Dessi Di Mario Sas",
    "wof:placetype":"venue"
},
  "geometry": {"coordinates":[9.1137971878,39.218624115],"type":"Point"}
}