{
  "type": "Feature",
  "properties": {
    "iso:country":"IT",
    "sg:address":"20122 Milano",
    "sg:city":"Milano",
    "sg:orig_category":"Macchine, Impianti Ed Attrezzature Per Abbigliamento E Pelletterie",
    "sg:phone":"+39 02 7639 4365",
    "sg:postcode":"20122",
    "sg:province":"Milano",
    "wof:name":"Grant Thornton International Business Srl",
    "wof:placetype":"venue"
},
  "geometry": {"coordinates":[9.198932,45.46442],"type":"Point"}
}