{
  "type": "Feature",
  "properties": {
    "iso:country":"IT",
    "sg:address":"Via Barco 00019 Tivoli",
    "sg:city":"Tivoli",
    "sg:classifiers":[
        {
            "category":"Manufacturing",
            "subcategory":"Metals",
            "type":"Manufacturing & Wholesale Goods"
        }
    ],
    "sg:phone":"+39 0774 379262",
    "sg:postcode":"00019",
    "sg:province":"Roma",
    "sg:tags":[
        "processing"
    ],
    "wof:name":"Cinque",
    "wof:placetype":"venue"
},
  "geometry": {"coordinates":[12.7344665527,41.9500083923],"type":"Point"}
}