{
  "type": "Feature",
  "properties": {
    "iso:country":"IT",
    "sg:address":"90145 Palermo",
    "sg:city":"Palermo",
    "sg:orig_category":"Macchine, Impianti E Forniture Per Industria Grafica, Cartaria E Cartotecnica. Automazione E Macchine Per Ufficio",
    "sg:phone":"+39 091 681 4450",
    "sg:postcode":"90145",
    "sg:province":"Palermo",
    "wof:name":"Medi Copying",
    "wof:placetype":"venue"
},
  "geometry": {"coordinates":[13.339808,38.126919],"type":"Point"}
}