{
  "type": "Feature",
  "properties": {
    "iso:country":"IT",
    "sg:address":"41037 Mirandola",
    "sg:city":"Mirandola",
    "sg:orig_category":"Pubblica Amministrazione",
    "sg:phone":"+39 0535 29511",
    "sg:postcode":"41037",
    "sg:province":"Modena",
    "wof:name":"Comune Di Mirandola",
    "wof:placetype":"venue"
},
  "geometry": {"coordinates":[11.088470459,44.9287910461],"type":"Point"}
}