{
  "type": "Feature",
  "properties": {
    "addr:full":"Via Trossi 11 13900 Biella Biella Biella 13900",
    "addr:housenumber":"11",
    "addr:postcode":"13900;13900",
    "addr:street":"Via Trossi",
    "iso:country":"IT",
    "sg:address":"Via Trossi 11 13900 Biella",
    "sg:city":"Biella",
    "sg:classifiers":[
        {
            "category":"Wholesale",
            "subcategory":"Books, Periodicals, & Newspapers",
            "type":"Manufacturing & Wholesale Goods"
        }
    ],
    "sg:phone":"+39 015 849 3607",
    "sg:postcode":"13900",
    "sg:province":"Biella",
    "sg:tags":[
        "professional",
        "journal",
        "journals",
        "publisher"
    ],
    "sg:website":"www.italtextrends.com",
    "wof:name":"Italtex S.r.l.",
    "wof:placetype":"venue"
},
  "geometry": {"coordinates":[8.0678052902,45.5549201965],"type":"Point"}
}