{
  "type": "Feature",
  "properties": {
    "iso:country":"IT",
    "sg:address":"10139 Torino",
    "sg:city":"Torino",
    "sg:orig_category":"Serramenti Ed Infissi",
    "sg:phone":"+39 011 356475",
    "sg:postcode":"10139",
    "sg:province":"Torino",
    "wof:name":"Movin Sistemi Srl",
    "wof:placetype":"venue"
},
  "geometry": {"coordinates":[7.637277,45.039631],"type":"Point"}
}