{
  "type": "Feature",
  "properties": {
    "addr:full":"10152 Torino Torino Torino 10152",
    "addr:postcode":"10152;10152",
    "iso:country":"IT",
    "sg:address":"10152 Torino",
    "sg:city":"Torino",
    "sg:orig_category":"Petrolchimica - Impianti Ed Attrezzature",
    "sg:phone":"+39 011 857837",
    "sg:postcode":"10152",
    "sg:province":"Torino",
    "wof:name":"Sardo Srl",
    "wof:placetype":"venue"
},
  "geometry": {"coordinates":[7.6951584816,45.0798835754],"type":"Point"}
}