{
  "type": "Feature",
  "properties": {
    "iso:country":"IT",
    "sg:address":"22070 Montano Lucino",
    "sg:city":"Lucino",
    "sg:orig_category":"Seta Filati E Tessuti - Produzione E Ingrosso",
    "sg:phone":"+39 031 470072",
    "sg:postcode":"22070",
    "sg:province":"Como",
    "wof:name":"Fratelli Ricci Pronto Moda Srl",
    "wof:placetype":"venue"
},
  "geometry": {"coordinates":[9.049705,45.777023],"type":"Point"}
}