{
  "type": "Feature",
  "properties": {
    "iso:country":"IT",
    "sg:address":"Via Vittorio; Capriate San Gervasio; 24042",
    "sg:city":"Capriate San Gervasio",
    "sg:classifiers":[
        {
            "category":"Banks & Credit Unions",
            "subcategory":"Bank",
            "type":"Services"
        }
    ],
    "sg:phone":"+39 02 9096 1322",
    "sg:postcode":"24042",
    "sg:province":"Bergamo",
    "wof:name":"Credito Italiano Spa",
    "wof:placetype":"venue"
},
  "geometry": {"coordinates":[9.522699,45.622314],"type":"Point"}
}