{
  "type": "Feature",
  "properties": {
    "iso:country":"IT",
    "sg:address":"20145 Milano",
    "sg:city":"Milano",
    "sg:classifiers":[
        {
            "category":"Health Services",
            "subcategory":"Health Practitioner",
            "type":"Services"
        }
    ],
    "sg:phone":"+39 02 481 7929",
    "sg:postcode":"20145",
    "sg:province":"Milano",
    "sg:tags":[
        "medici"
    ],
    "wof:name":"Marcotti Giuseppe",
    "wof:placetype":"venue"
},
  "geometry": {"coordinates":[9.163265,45.470238],"type":"Point"}
}