{
  "type": "Feature",
  "properties": {
    "iso:country":"IT",
    "sg:address":"Ctr. Mattina 84031 Auletta",
    "sg:city":"Auletta",
    "sg:classifiers":[
        {
            "category":"Shopping",
            "subcategory":"Clothing, Apparel, & Fashions",
            "type":"Retail Goods"
        }
    ],
    "sg:phone":"+39 0975 392770",
    "sg:postcode":"84031",
    "sg:province":"Salerno",
    "sg:tags":[
        "clothes"
    ],
    "sg:website":"http://www.magister.it",
    "wof:name":"Magister Srl",
    "wof:placetype":"venue"
},
  "geometry": {"coordinates":[14.765912,40.677956],"type":"Point"}
}