{
  "type": "Feature",
  "properties": {
    "addr:full":"1, Strada Statale 150 64024 Notaresco Notaresco Teramo 64024",
    "addr:housenumber":"150",
    "addr:postcode":"64024;64024",
    "addr:street":"Strada Statale",
    "iso:country":"IT",
    "sg:address":"1, Strada Statale 150 64024 Notaresco",
    "sg:city":"Notaresco",
    "sg:classifiers":[
        {
            "category":"Shopping",
            "type":"Retail Goods"
        }
    ],
    "sg:phone":"+39 39085898253",
    "sg:postcode":"64024",
    "sg:province":"Teramo",
    "sg:tags":[
        "finished",
        "-",
        "metallic"
    ],
    "wof:name":"De Lauretis S.r.l.",
    "wof:placetype":"venue"
},
  "geometry": {"coordinates":[13.838973999,42.6281509399],"type":"Point"}
}