{
  "type": "Feature",
  "properties": {
    "iso:country":"IT",
    "sg:address":"13100 Vercelli",
    "sg:city":"Vercelli",
    "sg:orig_category":"Edilizia - Attrezzature",
    "sg:phone":"+39 0161 391344",
    "sg:postcode":"13100",
    "sg:province":"Vercelli",
    "sg:website":"http://www.comedvc.com",
    "wof:name":"Comed Di Carenzo P.a. & C.",
    "wof:placetype":"venue"
},
  "geometry": {"coordinates":[8.400068,45.325474],"type":"Point"}
}