{
  "type": "Feature",
  "properties": {
    "iso:country":"IT",
    "sg:address":"24060 Credaro",
    "sg:city":"Credaro",
    "sg:orig_category":"Macchine, Impianti Ed Attrezzature Industria Delle Materie Plastiche E Gomma",
    "sg:phone":"+39 035 935181",
    "sg:postcode":"24060",
    "sg:province":"Bergamo",
    "wof:name":"L.c.p. (s.n.c.)",
    "wof:placetype":"venue"
},
  "geometry": {"coordinates":[9.931942,45.661587],"type":"Point"}
}