{
  "type": "Feature",
  "properties": {
    "iso:country":"IT",
    "sg:address":"20019 Settimo Milanese",
    "sg:city":"Settimo Milanese",
    "sg:orig_category":"Trattamenti Termici E Superficiali Metalli, Galvanotecnica",
    "sg:phone":"+39 02 3350 3395",
    "sg:postcode":"20019",
    "sg:province":"Milano",
    "wof:name":"Pelle Angelo",
    "wof:placetype":"venue"
},
  "geometry": {"coordinates":[9.073986,45.474831],"type":"Point"}
}