{
  "type": "Feature",
  "properties": {
    "addr:full":"00159 Roma Roma Roma 00159",
    "addr:postcode":"00159;00159",
    "iso:country":"IT",
    "sg:address":"00159 Roma",
    "sg:city":"Roma",
    "sg:orig_category":"Fotografia - Servizi, Studi, Sviluppo E Stampa",
    "sg:phone":"+39 06 4359 9268",
    "sg:postcode":"00159",
    "sg:province":"Roma",
    "wof:name":"M. & C. Graphipoint",
    "wof:placetype":"venue"
},
  "geometry": {"coordinates":[12.5498819351,41.9030418396],"type":"Point"}
}