{
  "type": "Feature",
  "properties": {
    "addr:full":"Corso Piave 82; S. Stefano Belbo; 12058 Cuneo 12058",
    "addr:housenumber":"82",
    "addr:postcode":"12058;12058",
    "addr:street":"Corso Piave;S. Stefano Belbo",
    "iso:country":"IT",
    "sg:address":"Corso Piave 82; S. Stefano Belbo; 12058",
    "sg:classifiers":[
        {
            "category":"Banks & Credit Unions",
            "subcategory":"Bank",
            "type":"Services"
        }
    ],
    "sg:phone":"+39 0141 843181",
    "sg:postcode":"12058",
    "sg:province":"Cuneo",
    "wof:name":"Cassa Di Risparmio Di Cuneo",
    "wof:placetype":"venue"
},
  "geometry": {"coordinates":[8.227566,44.706631],"type":"Point"}
}