{
  "type": "Feature",
  "properties": {
    "iso:country":"IT",
    "sg:address":"8, Via Arturo Toscanini 20010 Ossona",
    "sg:city":"Ossona",
    "sg:classifiers":[
        {
            "category":"Shopping",
            "subcategory":"Crafts & Fabrics",
            "type":"Retail Goods"
        }
    ],
    "sg:phone":"+39 02 9038 0230",
    "sg:postcode":"20010",
    "sg:province":"Milano",
    "wof:name":"Tessil Asmonte Spa",
    "wof:placetype":"venue"
},
  "geometry": {"coordinates":[8.8793849945,45.507610321],"type":"Point"}
}