{
  "type": "Feature",
  "properties": {
    "iso:country":"IT",
    "sg:address":"50022 Greve In Chianti",
    "sg:city":"Greve in Chianti",
    "sg:orig_category":"Non-classified Establishments",
    "sg:phone":"+39 055 853864",
    "sg:postcode":"50022",
    "sg:province":"Firenze",
    "wof:name":"Il Melo Terrecotte",
    "wof:placetype":"venue"
},
  "geometry": {"coordinates":[11.320416,43.590641],"type":"Point"}
}