{
  "type": "Feature",
  "properties": {
    "iso:country":"IT",
    "sg:address":"17027 Pietra Ligure",
    "sg:city":"Pietra Ligure",
    "sg:orig_category":"Forniture Per Agricoltura E Zootecnia. Animali Domestici",
    "sg:phone":"+39 019 629 5112",
    "sg:postcode":"17027",
    "sg:province":"Savona",
    "wof:name":"Acquanimando Due",
    "wof:placetype":"venue"
},
  "geometry": {"coordinates":[8.2827100754,44.1488609314],"type":"Point"}
}