{
  "type": "Feature",
  "properties": {
    "iso:country":"IT",
    "sg:address":"Via Don Minzoni, 13/15 20020 Misinto",
    "sg:city":"Misinto",
    "sg:classifiers":[
        {
            "category":"Structure",
            "subcategory":"Bridge",
            "type":"Public Place"
        }
    ],
    "sg:phone":"+39 02 9632 0631",
    "sg:postcode":"20020",
    "sg:province":"Milano",
    "sg:tags":[
        "profile",
        "extruded",
        "tube"
    ],
    "sg:website":"www.tamburinigieffe.it",
    "wof:name":"Tamburini Gi-effe Srl",
    "wof:placetype":"venue"
},
  "geometry": {"coordinates":[9.101699,45.65596],"type":"Point"}
}