{
  "type": "Feature",
  "properties": {
    "addr:full":"24040 Ciserano Ciserano Bergamo 24040",
    "addr:postcode":"24040;24040",
    "iso:country":"IT",
    "sg:address":"24040 Ciserano",
    "sg:city":"Ciserano",
    "sg:orig_category":"Trattamenti Termici E Superficiali Metalli, Galvanotecnica",
    "sg:phone":"+39 035 419 1478",
    "sg:postcode":"24040",
    "sg:province":"Bergamo",
    "wof:name":"Anodicolor Srl",
    "wof:placetype":"venue"
},
  "geometry": {"coordinates":[9.593879,45.585083],"type":"Point"}
}