{
  "type": "Feature",
  "properties": {
    "addr:full":"31018 Francenigo Di Gaiarine Francenigo Treviso 31018",
    "addr:postcode":"31018;31018",
    "iso:country":"IT",
    "sg:address":"31018 Francenigo Di Gaiarine",
    "sg:city":"Francenigo",
    "sg:classifiers":[
        {
            "category":"Home & Garden",
            "subcategory":"Furniture",
            "type":"Retail Goods"
        }
    ],
    "sg:phone":"+39 0434 766711",
    "sg:postcode":"31018",
    "sg:province":"Treviso",
    "sg:tags":[
        "furnishing"
    ],
    "sg:website":"http://www.jesse.it",
    "wof:name":"Jesse Spa",
    "wof:placetype":"venue"
},
  "geometry": {"coordinates":[12.2420721054,45.6662864685],"type":"Point"}
}