{
  "type": "Feature",
  "properties": {
    "iso:country":"IT",
    "sg:address":"10085 Pont Canavese",
    "sg:orig_category":"Prodotti E Manufatti In Materie Plastiche",
    "sg:phone":"+39 0124 862311",
    "sg:postcode":"10085",
    "sg:province":"Torino",
    "wof:name":"Liri Industriale Srl S.u.",
    "wof:placetype":"venue"
},
  "geometry": {"coordinates":[7.6107616425,45.4189567566],"type":"Point"}
}