{
  "type": "Feature",
  "properties": {
    "iso:country":"IT",
    "sg:address":"Via Regina Margherita 74/c, 75017 Salandra, Mt",
    "sg:city":"Salandra",
    "sg:classifiers":[
        {
            "category":"Banks & Credit Unions",
            "subcategory":"Bank",
            "type":"Services"
        }
    ],
    "sg:postcode":"75017",
    "sg:province":"Matera",
    "wof:name":"Banca Di Credito Cooperativo Di Salandra",
    "wof:placetype":"venue"
},
  "geometry": {"coordinates":[16.319622,40.527061],"type":"Point"}
}