{
  "type": "Feature",
  "properties": {
    "iso:country":"IT",
    "sg:address":"00128 Roma",
    "sg:city":"Roma",
    "sg:orig_category":"Macchine, Impianti E Forniture Per Industria Grafica, Cartaria E Cartotecnica. Automazione E Macchine Per Ufficio",
    "sg:phone":"+39 06 5079 0020",
    "sg:postcode":"00128",
    "sg:province":"Roma",
    "sg:website":"http://www.mibex.it",
    "wof:name":"Mibex Rappresentanze Srl",
    "wof:placetype":"venue"
},
  "geometry": {"coordinates":[12.451583,41.799061],"type":"Point"}
}