{
  "type": "Feature",
  "properties": {
    "iso:country":"IT",
    "sg:address":"20095 Cusano Milanino",
    "sg:city":"Cusano Milanino",
    "sg:orig_category":"Agenzie Matrimoniali",
    "sg:phone":"+39 02 6640 2464",
    "sg:postcode":"20095",
    "sg:province":"Milano",
    "wof:name":"Agenzia Servizi Lap",
    "wof:placetype":"venue"
},
  "geometry": {"coordinates":[9.175054,45.548325],"type":"Point"}
}