{
  "type": "Feature",
  "properties": {
    "iso:country":"IT",
    "sg:address":"Viale Porta Adige 1; Rovigo",
    "sg:classifiers":[
        {
            "category":"Travel",
            "subcategory":"Travel Agent",
            "type":"Entertainment"
        }
    ],
    "wof:name":"Best Western Hotel Cristallo",
    "wof:placetype":"venue"
},
  "geometry": {"coordinates":[11.785158,45.076614],"type":"Point"}
}