{
  "type": "Feature",
  "properties": {
    "iso:country":"IT",
    "sg:address":"00048 Nettuno",
    "sg:city":"Nettuno",
    "sg:orig_category":"Porte",
    "sg:phone":"+39 06 985 8238",
    "sg:postcode":"00048",
    "sg:province":"Roma",
    "wof:name":"Marconi Lavorazione Metalli",
    "wof:placetype":"venue"
},
  "geometry": {"coordinates":[12.7103233337,41.4842948914],"type":"Point"}
}