{
  "type": "Feature",
  "properties": {
    "iso:country":"IT",
    "sg:address":"32036 Sedico",
    "sg:city":"Sedico",
    "sg:orig_category":"Lavorazioni Metalli, Stampaggio E Saldatura",
    "sg:phone":"+39 0437 83735",
    "sg:postcode":"32036",
    "sg:province":"Belluno",
    "wof:name":"Joint & Welding Srl",
    "wof:placetype":"venue"
},
  "geometry": {"coordinates":[12.092458,46.10318],"type":"Point"}
}