{
  "type": "Feature",
  "properties": {
    "addr:full":"06123 Perugia Perugia Perugia 06123",
    "addr:postcode":"06123;06123",
    "iso:country":"IT",
    "sg:address":"06123 Perugia",
    "sg:city":"Perugia",
    "sg:orig_category":"Librerie",
    "sg:phone":"+39 075 571 6091",
    "sg:postcode":"06123",
    "sg:province":"Perugia",
    "wof:name":"L'antro Libreria",
    "wof:placetype":"venue"
},
  "geometry": {"coordinates":[12.388584,43.111713],"type":"Point"}
}