{
  "type": "Feature",
  "properties": {
    "addr:full":"Via Boito 10, Milan, Mi",
    "addr:housenumber":"10",
    "addr:street":"Via Boito",
    "iso:country":"IT",
    "sg:address":"Via Boito 10, Milan, Mi",
    "sg:classifiers":[
        {
            "category":"Banks & Credit Unions",
            "subcategory":"Bank",
            "type":"Services"
        }
    ],
    "wof:name":"Cisalpina Gestioni Spa",
    "wof:placetype":"venue"
},
  "geometry": {"coordinates":[9.059296,45.422653],"type":"Point"}
}