{
  "type": "Feature",
  "properties": {
    "addr:full":"24047 Treviglio Treviglio Bergamo 24047",
    "addr:postcode":"24047;24047",
    "iso:country":"IT",
    "sg:address":"24047 Treviglio",
    "sg:city":"Treviglio",
    "sg:orig_category":"Prodotti Chimici Secondari. Tempo Libero - Articoli E Forniture. Servizi Per Lo Sport E Il Tempo Libero. Servizi Per Aziende, Manifestazioni E Supporto Agli Scambi Commerciali",
    "sg:phone":"+39 036 344198",
    "sg:postcode":"24047",
    "sg:province":"Bergamo",
    "wof:name":"La Bottega Del Timbro",
    "wof:placetype":"venue"
},
  "geometry": {"coordinates":[9.5914354324,45.5293388367],"type":"Point"}
}