{
  "type": "Feature",
  "properties": {
    "iso:country":"IT",
    "sg:address":"48014 Castel Bolognese",
    "sg:city":"Castel Bolognese",
    "sg:orig_category":"Automazione E Macchine Per Ufficio",
    "sg:phone":"+39 0546 656165",
    "sg:postcode":"48014",
    "sg:province":"Ravenna",
    "sg:website":"http://www.datasystem.it",
    "wof:name":"Data System Srl",
    "wof:placetype":"venue"
},
  "geometry": {"coordinates":[11.79606,44.321064],"type":"Point"}
}