{
  "type": "Feature",
  "properties": {
    "iso:country":"IT",
    "sg:address":"20123 Milano",
    "sg:city":"Milano",
    "sg:orig_category":"Servizi E Lavori Per Ecologia E Smaltimento Rifiuti. Termotecnica E Riscaldamento, Apparecchiature E Servizi. Servizi Ausiliari Di Sorveglianza, Manutenzione E Pulizia",
    "sg:phone":"+39 02 8940 9118",
    "sg:postcode":"20123",
    "sg:province":"Milano",
    "sg:website":"http://www.albiero.net",
    "wof:name":"Albiero Srl",
    "wof:placetype":"venue"
},
  "geometry": {"coordinates":[9.172346,45.456711],"type":"Point"}
}