{
  "type": "Feature",
  "properties": {
    "iso:country":"IT",
    "sg:address":"95128 Catania",
    "sg:city":"Catania",
    "sg:orig_category":"Servizi E Lavori Per Agricoltura E Zootecnia. Animali Domestici",
    "sg:phone":"+39 095 503241",
    "sg:postcode":"95128",
    "sg:province":"Catania",
    "wof:name":"Marchese Maria New Hobby Dog",
    "wof:placetype":"venue"
},
  "geometry": {"coordinates":[15.087892,37.517754],"type":"Point"}
}