{
  "type": "Feature",
  "properties": {
    "addr:full":"44100 Ferrara Ferrara Ferrara 44100",
    "addr:postcode":"44100;44100",
    "iso:country":"IT",
    "sg:address":"44100 Ferrara",
    "sg:city":"Ferrara",
    "sg:orig_category":"Prodotti Di Base E Forniture Per Industria Alimentare E Bevande. Prodotti Chimici Di Base",
    "sg:phone":"+39 0532 757474",
    "sg:postcode":"44100",
    "sg:province":"Ferrara",
    "wof:name":"Bigoni Liliana",
    "wof:placetype":"venue"
},
  "geometry": {"coordinates":[11.619389534,44.8383293152],"type":"Point"}
}