{
  "type": "Feature",
  "properties": {
    "iso:country":"IT",
    "sg:address":"20144 Milano",
    "sg:city":"Milano",
    "sg:orig_category":"Arredamenti E Mobili Professionali. Apparecchi, Attrezzature E Forniture Per Centri Estetici. Arredi Ed Attrezzature Per Attivita' Commerciali Ed Artigianali",
    "sg:phone":"+39 02 4801 3935",
    "sg:postcode":"20144",
    "sg:province":"Milano",
    "wof:name":"Fremis Snc",
    "wof:placetype":"venue"
},
  "geometry": {"coordinates":[9.161203,45.456848],"type":"Point"}
}