{
  "type": "Feature",
  "properties": {
    "iso:country":"IT",
    "sg:address":"20122 Milano",
    "sg:city":"Milano",
    "sg:orig_category":"Servizi Ausiliari Di Analisi, Controllo E Ricerca",
    "sg:phone":"+39 02 545 4646",
    "sg:postcode":"20122",
    "sg:province":"Milano",
    "wof:name":"In Arch.",
    "wof:placetype":"venue"
},
  "geometry": {"coordinates":[9.200757,45.459206],"type":"Point"}
}