{
  "type": "Feature",
  "properties": {
    "iso:country":"IT",
    "sg:address":"61100 Pesaro",
    "sg:city":"Pesaro",
    "sg:orig_category":"Autogru - Noleggio",
    "sg:phone":"+39 0721 279877",
    "sg:postcode":"61100",
    "sg:province":"Pesaro E Urbino",
    "wof:name":"Autotrasporti - Autogru' De Angelis",
    "wof:placetype":"venue"
},
  "geometry": {"coordinates":[12.865122,43.91254],"type":"Point"}
}