{
  "type": "Feature",
  "properties": {
    "addr:full":"2, V. Ansaldo Forl\u00ec-Cesena 47100",
    "addr:housenumber":"2",
    "addr:postcode":"47100",
    "addr:street":"V. Ansaldo",
    "iso:country":"IT",
    "sg:address":"2, V. Ansaldo",
    "sg:classifiers":[
        {
            "category":"Home & Garden",
            "subcategory":"Home Furnishings",
            "type":"Retail Goods"
        }
    ],
    "sg:phone":"+39 0543 782611",
    "sg:postcode":"47100",
    "sg:province":"Forl\u00ec-Cesena",
    "sg:tags":[
        "household"
    ],
    "sg:website":"http://www.cierreimbottiti.com",
    "wof:name":"Cierre Imbottiti Srl",
    "wof:placetype":"venue"
},
  "geometry": {"coordinates":[12.048979,44.231167],"type":"Point"}
}