{
  "type": "Feature",
  "properties": {
    "iso:country":"IT",
    "sg:address":"Via Crispi 61, 88100 Catanzaro, Cz",
    "sg:city":"Catanzaro",
    "sg:classifiers":[
        {
            "category":"Banks & Credit Unions",
            "subcategory":"Bank",
            "type":"Services"
        }
    ],
    "sg:postcode":"88100",
    "sg:province":"Catanzaro",
    "wof:name":"Fidart Calabria",
    "wof:placetype":"venue"
},
  "geometry": {"coordinates":[16.583744,38.913101],"type":"Point"}
}