{
  "type": "Feature",
  "properties": {
    "iso:country":"IT",
    "sg:address":"70034 Mariotto",
    "sg:orig_category":"Forniture Per Agricoltura E Zootecnia. Prodotti Chimici Secondari. Macchine E Forniture Per Ecologia E Smaltimento Rifiuti",
    "sg:phone":"+39 080 373 6002",
    "sg:province":"BA",
    "wof:name":"De.bo. Agricoltura Di Dellorusso Gaetano & C. Snc",
    "wof:placetype":"venue"
},
  "geometry": {"coordinates":[16.5603256226,41.0504264832],"type":"Point"}
}