{
  "type": "Feature",
  "properties": {
    "iso:country":"IT",
    "sg:address":"09040 Barrali",
    "sg:city":"Barrali",
    "sg:orig_category":"Pubblica Amministrazione",
    "sg:phone":"+39 070 983 1005",
    "sg:postcode":"09040",
    "sg:province":"Cagliari",
    "wof:name":"Carabinieri",
    "wof:placetype":"venue"
},
  "geometry": {"coordinates":[9.1099901199,39.2153587341],"type":"Point"}
}