{
  "type": "Feature",
  "properties": {
    "iso:country":"IT",
    "sg:address":"46 Via Giuseppe Garibaldi, 31010 Orsago",
    "sg:city":"Orsago",
    "sg:classifiers":[
        {
            "category":"Banks & Credit Unions",
            "subcategory":"Financial Services",
            "type":"Services"
        }
    ],
    "sg:phone":"+39 390 438 9931",
    "sg:postcode":"31010",
    "sg:province":"Treviso",
    "sg:tags":[
        "banking",
        "finance",
        "insurance"
    ],
    "wof:name":"Banca Di Credito Cooperativo Di Orsago Scarl",
    "wof:placetype":"venue"
},
  "geometry": {"coordinates":[12.4150352478,45.9345169067],"type":"Point"}
}