{
  "type": "Feature",
  "properties": {
    "iso:country":"IT",
    "sg:address":"Via Risorgimento 12 23845 Costa Masnaga",
    "sg:city":"Costa Masnaga",
    "sg:classifiers":[
        {
            "category":"Military Area",
            "subcategory":"Air Force Base",
            "type":"Public Place"
        }
    ],
    "sg:phone":"+39 031 856951",
    "sg:postcode":"23845",
    "sg:province":"Lecco",
    "sg:tags":[
        "technical",
        "wire",
        "purpose",
        "grating"
    ],
    "sg:website":"www.remsa.it",
    "wof:name":"Remsa Srl",
    "wof:placetype":"venue"
},
  "geometry": {"coordinates":[9.258488,45.768124],"type":"Point"}
}