{
  "type": "Feature",
  "properties": {
    "addr:full":"07047 Thiesi Thiesi Sassari 07047",
    "addr:postcode":"07047;07047",
    "iso:country":"IT",
    "sg:address":"07047 Thiesi",
    "sg:city":"Thiesi",
    "sg:orig_category":"Pubblica Amministrazione",
    "sg:phone":"+39 079 886606",
    "sg:postcode":"07047",
    "sg:province":"Sassari",
    "wof:name":"Carabinieri",
    "wof:placetype":"venue"
},
  "geometry": {"coordinates":[8.7421321869,40.5216064453],"type":"Point"}
}