{
  "type": "Feature",
  "properties": {
    "addr:full":"5, Via Don Cesare Scala 37020 Brentino Belluno Brentino Belluno Verona 37020",
    "addr:postcode":"37020;37020",
    "addr:street":"Via Don Cesare Scala",
    "iso:country":"IT",
    "sg:address":"5, Via Don Cesare Scala 37020 Brentino Belluno",
    "sg:city":"Brentino Belluno",
    "sg:classifiers":[
        {
            "category":"Manufacturing",
            "subcategory":"Paper Products",
            "type":"Manufacturing & Wholesale Goods"
        }
    ],
    "sg:phone":"+39 045 628 4063",
    "sg:postcode":"37020",
    "sg:province":"Verona",
    "sg:tags":[
        "cardboard"
    ],
    "wof:name":"Cartiera Cooperativa Rivalta A R.l.",
    "wof:placetype":"venue"
},
  "geometry": {"coordinates":[10.8907670975,45.6551017761],"type":"Point"}
}