{
  "type": "Feature",
  "properties": {
    "iso:country":"IT",
    "sg:address":"00198 Roma",
    "sg:city":"Roma",
    "sg:orig_category":"Servizi Per Aziende, Manifestazioni E Supporto Agli Scambi Commerciali",
    "sg:phone":"+39 06 8535 5401",
    "sg:postcode":"00198",
    "sg:province":"Roma",
    "wof:name":"Made In Museum Srl",
    "wof:placetype":"venue"
},
  "geometry": {"coordinates":[12.492872,41.919289],"type":"Point"}
}