{
  "type": "Feature",
  "properties": {
    "addr:full":"87064 Corigliano Calabro Corigliano Calabro Cosenza 87064",
    "addr:postcode":"87064;87064",
    "iso:country":"IT",
    "sg:address":"87064 Corigliano Calabro",
    "sg:city":"Corigliano Calabro",
    "sg:orig_category":"Prodotti Alimentari. Agricoltura, Orticoltura E Floricoltura",
    "sg:phone":"+39 0983 80740",
    "sg:postcode":"87064",
    "sg:province":"Cosenza",
    "wof:name":"Coab Soc.coop.r.l.",
    "wof:placetype":"venue"
},
  "geometry": {"coordinates":[16.5112705231,39.6276130676],"type":"Point"}
}