{
  "type": "Feature",
  "properties": {
    "iso:country":"IT",
    "sg:address":"37042 Caldiero",
    "sg:city":"Caldiero",
    "sg:orig_category":"Macchine Ed Impianti Per Edilizia E Lavori Pubblici",
    "sg:phone":"+39 045 615 2324",
    "sg:postcode":"37042",
    "sg:province":"Verona",
    "wof:name":"Tecnoecology S.n.c. Di Lavagnoli Marisa E Cristina & C.",
    "wof:placetype":"venue"
},
  "geometry": {"coordinates":[11.188879,45.414326],"type":"Point"}
}