{
  "type": "Feature",
  "properties": {
    "iso:country":"IT",
    "sg:address":"25, V. Molinara 52100 Arezzo",
    "sg:city":"Arezzo",
    "sg:classifiers":[
        {
            "category":"Shopping",
            "subcategory":"Jewelry",
            "type":"Retail Goods"
        }
    ],
    "sg:phone":"+39 0575 383127",
    "sg:postcode":"52100",
    "sg:province":"Arezzo",
    "sg:tags":[
        "jewellery"
    ],
    "sg:website":"http://www.microro.it",
    "wof:name":"Micr-oro Srl 1153ar",
    "wof:placetype":"venue"
},
  "geometry": {"coordinates":[11.82747,43.469131],"type":"Point"}
}