{
  "type": "Feature",
  "properties": {
    "addr:full":"09028 Sestu Sestu Cagliari 09028",
    "addr:postcode":"09028;09028",
    "iso:country":"IT",
    "sg:address":"09028 Sestu",
    "sg:city":"Sestu",
    "sg:orig_category":"Zanzariere",
    "sg:phone":"+39 070 262129",
    "sg:postcode":"09028",
    "sg:province":"Cagliari",
    "wof:name":"Secci Zanzariere",
    "wof:placetype":"venue"
},
  "geometry": {"coordinates":[9.0078334808,39.3598518372],"type":"Point"}
}