{
  "type": "Feature",
  "properties": {
    "iso:country":"IT",
    "sg:address":"23880 Casatenovo",
    "sg:city":"Casatenovo",
    "sg:orig_category":"Chimica, Cosmetica E Farmaceutica Industria - Macchine",
    "sg:phone":"+39 039 920 6244",
    "sg:postcode":"23880",
    "sg:province":"Lecco",
    "wof:name":"Costamac Di Fratelli Gerosa Srl",
    "wof:placetype":"venue"
},
  "geometry": {"coordinates":[9.3185510635,45.6806945801],"type":"Point"}
}