{
  "type": "Feature",
  "properties": {
    "iso:country":"IT",
    "sg:address":"Via Ippolito Nievo 12/b 35012 Camposampiero",
    "sg:city":"Camposampiero",
    "sg:classifiers":[
        {
            "category":"Utilities",
            "subcategory":"Electric",
            "type":"Services"
        }
    ],
    "sg:phone":"+39 049 930 0344",
    "sg:postcode":"35012",
    "sg:province":"Padova",
    "sg:tags":[
        "furnace"
    ],
    "sg:website":"www.technoeka.com",
    "wof:name":"Tecnoeka Srl",
    "wof:placetype":"venue"
},
  "geometry": {"coordinates":[11.876589,45.409569],"type":"Point"}
}