{
  "type": "Feature",
  "properties": {
    "addr:full":"7/9, Via Degli Olmi 48018 Faenza Faenza Ravenna 48018",
    "addr:housenumber":"7 / 9",
    "addr:postcode":"48018;48018",
    "addr:street":"Via Degli Olmi",
    "iso:country":"IT",
    "sg:address":"7/9, Via Degli Olmi 48018 Faenza",
    "sg:city":"Faenza",
    "sg:classifiers":[
        {
            "category":"Manufacturing",
            "subcategory":"Metals",
            "type":"Manufacturing & Wholesale Goods"
        }
    ],
    "sg:phone":"+39 39054626137",
    "sg:postcode":"48018",
    "sg:province":"Ravenna",
    "sg:tags":[
        "processing"
    ],
    "wof:name":"Torneria Automatica Faentina",
    "wof:placetype":"venue"
},
  "geometry": {"coordinates":[11.8894777298,44.3037528992],"type":"Point"}
}