{
  "type": "Feature",
  "properties": {
    "addr:full":"50019 Sesto Fiorentino Sesto Fiorentino Firenze 50019",
    "addr:postcode":"50019;50019",
    "iso:country":"IT",
    "sg:address":"50019 Sesto Fiorentino",
    "sg:city":"Sesto Fiorentino",
    "sg:orig_category":"Forniture Per Abbigliamento E Pelletterie",
    "sg:phone":"+39 055 374741",
    "sg:postcode":"50019",
    "sg:province":"Firenze",
    "wof:name":"Italfibbia Srl",
    "wof:placetype":"venue"
},
  "geometry": {"coordinates":[11.1747617722,43.8111381531],"type":"Point"}
}