{
  "type": "Feature",
  "properties": {
    "addr:full":"21040 Uboldo Uboldo Varese 21040",
    "addr:postcode":"21040;21040",
    "iso:country":"IT",
    "sg:address":"21040 Uboldo",
    "sg:city":"Uboldo",
    "sg:orig_category":"Petroli, Gas E Combustibili. Servizi E Lavori Industria Chimica. Servizi E Lavori Per Edilizia E Lavori Pubblici. Acqua, Luce, Gas E Societa' Di Esercizio Pubblico",
    "sg:phone":"+39 02 9678 9358",
    "sg:postcode":"21040",
    "sg:province":"Varese",
    "wof:name":"Compagnia Servizi Industriali Spa",
    "wof:placetype":"venue"
},
  "geometry": {"coordinates":[9.0050001144,45.6162605286],"type":"Point"}
}