{
  "type": "Feature",
  "properties": {
    "iso:country":"IT",
    "sg:address":"31044 Montebelluna",
    "sg:city":"Montebelluna",
    "sg:classifiers":[
        {
            "category":"Shopping",
            "subcategory":"Bicycles & Sporting Goods",
            "type":"Retail Goods"
        }
    ],
    "sg:phone":"+39 0423 22498",
    "sg:postcode":"31044",
    "sg:province":"Treviso",
    "sg:tags":[
        "e",
        "sport",
        "-",
        "forniture",
        "articoli"
    ],
    "sg:website":"http://www.simonatoweb.it",
    "wof:name":"Simonato Snc Di Simonato Elvio & C.",
    "wof:placetype":"venue"
},
  "geometry": {"coordinates":[12.054277,45.772205],"type":"Point"}
}