{
  "type": "Feature",
  "properties": {
    "iso:country":"IT",
    "sg:address":"87/bis, Via Regio Parco 10036 Settimo Torinese",
    "sg:city":"Settimo Torinese",
    "sg:classifiers":[
        {
            "category":"Shopping",
            "type":"Retail Goods"
        }
    ],
    "sg:phone":"+39 011 895 4000",
    "sg:postcode":"10036",
    "sg:province":"Torino",
    "sg:tags":[
        "finished",
        "-",
        "metallic"
    ],
    "wof:name":"Potent Di Vettorazzi & C. (s.a.s.)",
    "wof:placetype":"venue"
},
  "geometry": {"coordinates":[7.7501139641,45.1254692078],"type":"Point"}
}