{
  "type": "Feature",
  "properties": {
    "iso:country":"IT",
    "sg:address":"73011 Alezio",
    "sg:city":"Alezio",
    "sg:orig_category":"Agricoltura, Orticoltura E Floricoltura",
    "sg:phone":"+39 0833 282626",
    "sg:postcode":"73011",
    "sg:province":"Lecce",
    "wof:name":"Ligetta & Solida Snc - Mediterraneo Garden Center",
    "wof:placetype":"venue"
},
  "geometry": {"coordinates":[18.060514,40.058525],"type":"Point"}
}