{
  "type": "Feature",
  "properties": {
    "iso:country":"IT",
    "sg:address":"11, Via Ampere Andrea Maria 20019 Settimo Milanese",
    "sg:city":"Settimo Milanese",
    "sg:classifiers":[
        {
            "category":"Manufacturing",
            "subcategory":"Metals",
            "type":"Manufacturing & Wholesale Goods"
        }
    ],
    "sg:phone":"+39 02 3350 0633",
    "sg:postcode":"20019",
    "sg:province":"Milano",
    "sg:tags":[
        "metallurgy",
        "metalworking"
    ],
    "wof:name":"Promtec Italia S.p.a.",
    "wof:placetype":"venue"
},
  "geometry": {"coordinates":[9.1881408691,45.4636878967],"type":"Point"}
}