{
  "type": "Feature",
  "properties": {
    "iso:country":"IT",
    "sg:address":"16163 San Quirico",
    "sg:orig_category":"Prodotti Chimici Secondari. Macchine E Forniture Per Ecologia E Smaltimento Rifiuti. Forniture Per Attivita' Commerciali Ed Artigianali",
    "sg:phone":"+39 010 726 2040",
    "sg:postcode":"16163",
    "sg:province":"Genova",
    "wof:name":"Puligenova Di Florio Salvatore",
    "wof:placetype":"venue"
},
  "geometry": {"coordinates":[8.9015312195,44.480255127],"type":"Point"}
}