{
  "type": "Feature",
  "properties": {
    "iso:country":"IT",
    "sg:address":"20063 Cernusco Sul Naviglio",
    "sg:city":"Cernusco sul Naviglio",
    "sg:orig_category":"Utensili Meccanici E Materiali",
    "sg:phone":"+39 02 9210 7032",
    "sg:postcode":"20063",
    "sg:province":"Milano",
    "wof:name":"Almifer Srl",
    "wof:placetype":"venue"
},
  "geometry": {"coordinates":[9.336869,45.465385],"type":"Point"}
}