{
  "type": "Feature",
  "properties": {
    "iso:country":"IT",
    "sg:address":"Via Sacco E Vanzetti-stagno 57014 Collesalvetti",
    "sg:city":"Collesalvetti",
    "sg:classifiers":[
        {
            "category":"Autos & Motor Vehicles",
            "subcategory":"Automobile Sales",
            "type":"Retail Goods"
        }
    ],
    "sg:phone":"+39 0586 942454",
    "sg:postcode":"57014",
    "sg:province":"Livorno",
    "sg:tags":[
        "equipment",
        "transport"
    ],
    "wof:name":"Team Terminal Livorno Srl",
    "wof:placetype":"venue"
},
  "geometry": {"coordinates":[10.345482,43.579906],"type":"Point"}
}