{
  "type": "Feature",
  "properties": {
    "iso:country":"IT",
    "sg:address":"22, Via Eugenio L'emiro 90135 Palermo",
    "sg:city":"Palermo",
    "sg:classifiers":[
        {
            "category":"Shopping",
            "subcategory":"Clothing, Apparel, & Fashions",
            "type":"Retail Goods"
        }
    ],
    "sg:phone":"+39 39091217049",
    "sg:postcode":"90135",
    "sg:province":"Palermo",
    "sg:tags":[
        "clothes"
    ],
    "wof:name":"Zagy's S.r.l.",
    "wof:placetype":"venue"
},
  "geometry": {"coordinates":[13.34169,38.115002],"type":"Point"}
}