{
  "type": "Feature",
  "properties": {
    "iso:country":"IT",
    "sg:address":"15045 Sale",
    "sg:city":"Sale",
    "sg:orig_category":"Elettronica Industriale, Prodotti E Apparecchiature",
    "sg:phone":"+39 0131 828561",
    "sg:postcode":"15045",
    "sg:province":"Alessandria",
    "sg:website":"http://www.grecoluminarie.it",
    "wof:name":"Greco Luminarie Di Greco Battista",
    "wof:placetype":"venue"
},
  "geometry": {"coordinates":[8.808053,44.968922],"type":"Point"}
}