{
  "type": "Feature",
  "properties": {
    "iso:country":"IT",
    "sg:address":"Via Provinciale 3 43030 Casa Selvatica",
    "sg:classifiers":[
        {
            "category":"Building & Trades",
            "subcategory":"Cleaning & Sanitation",
            "type":"Services"
        }
    ],
    "sg:phone":"+39 0525 66137",
    "sg:postcode":"43030",
    "sg:province":"Parma",
    "sg:tags":[
        "machine",
        "barrel",
        "installation",
        "dressing"
    ],
    "sg:website":"www.veabitalia.com",
    "wof:name":"Veab Di Vescovi Paolo",
    "wof:placetype":"venue"
},
  "geometry": {"coordinates":[10.329548,44.807865],"type":"Point"}
}