{
  "type": "Feature",
  "properties": {
    "addr:full":"00135 Roma Roma Roma 00135",
    "addr:postcode":"00135;00135",
    "iso:country":"IT",
    "sg:address":"00135 Roma",
    "sg:city":"Roma",
    "sg:orig_category":"Materiali E Componenti Elettrotecnici",
    "sg:phone":"+39 06 305 4139",
    "sg:postcode":"00135",
    "sg:province":"Roma",
    "wof:name":"Elettromeccanica Walma Snc Di Passi Anna",
    "wof:placetype":"venue"
},
  "geometry": {"coordinates":[12.437539,41.937138],"type":"Point"}
}