{
  "type": "Feature",
  "properties": {
    "iso:country":"IT",
    "sg:address":"00125 Roma",
    "sg:city":"Roma",
    "sg:orig_category":"Servizi Per Lo Sport E Il Tempo Libero. Servizi Al Turismo",
    "sg:phone":"+39 06 5091 5830",
    "sg:postcode":"00125",
    "sg:province":"Roma",
    "wof:name":"Ubaldini Lucio",
    "wof:placetype":"venue"
},
  "geometry": {"coordinates":[12.369664,41.756512],"type":"Point"}
}