{
  "type": "Feature",
  "properties": {
    "iso:country":"IT",
    "sg:address":"10129 Torino",
    "sg:city":"Torino",
    "sg:orig_category":"Banche E Servizi Finanziari",
    "sg:phone":"+39 011 580 6005",
    "sg:postcode":"10129",
    "sg:province":"Torino",
    "wof:name":"Meridiana Sas",
    "wof:placetype":"venue"
},
  "geometry": {"coordinates":[7.660471,45.059643],"type":"Point"}
}