{
  "type": "Feature",
  "properties": {
    "addr:full":"50122 Firenze Firenze Firenze 50122",
    "addr:postcode":"50122;50122",
    "iso:country":"IT",
    "sg:address":"50122 Firenze",
    "sg:city":"Firenze",
    "sg:classifiers":[
        {
            "category":"Home & Garden",
            "subcategory":"Home Furnishings",
            "type":"Retail Goods"
        }
    ],
    "sg:phone":"+39 055 245940",
    "sg:postcode":"50122",
    "sg:province":"Firenze",
    "sg:tags":[
        "art",
        "furniture",
        "shopping",
        "artistic",
        "crafts"
    ],
    "wof:name":"Conto Vendita Di Passerini Daniela",
    "wof:placetype":"venue"
},
  "geometry": {"coordinates":[11.262298584,43.7681121826],"type":"Point"}
}