{
  "type": "Feature",
  "properties": {
    "iso:country":"IT",
    "sg:address":"142, Via Piave 21057 Olgiate Olona",
    "sg:city":"Olgiate Olona",
    "sg:classifiers":[
        {
            "category":"Shopping",
            "subcategory":"Clothing, Apparel, & Fashions",
            "type":"Retail Goods"
        }
    ],
    "sg:phone":"+39 0331 636589",
    "sg:postcode":"21057",
    "sg:province":"Varese",
    "sg:tags":[
        "clothes"
    ],
    "wof:name":"Maglificio P. Hamers S.r.l.",
    "wof:placetype":"venue"
},
  "geometry": {"coordinates":[8.870469,45.624443],"type":"Point"}
}