{
  "type": "Feature",
  "properties": {
    "iso:country":"IT",
    "sg:address":"20034 Giussano",
    "sg:city":"Giussano",
    "sg:orig_category":"Prodotti Di Base E Forniture Per Industria Alimentare E Bevande",
    "sg:phone":"+39 036 286 0483",
    "sg:postcode":"20034",
    "sg:province":"Milano",
    "wof:name":"Besana Giovanni",
    "wof:placetype":"venue"
},
  "geometry": {"coordinates":[9.1854763031,45.4767494202],"type":"Point"}
}