{
  "type": "Feature",
  "properties": {
    "iso:country":"IT",
    "sg:address":"64014 Martinsicuro",
    "sg:city":"Martinsicuro",
    "sg:orig_category":"Servizi Ausiliari Per Il Trasporto",
    "sg:phone":"+39 0861 796988",
    "sg:postcode":"64014",
    "sg:province":"Teramo",
    "wof:name":"Fabiani Luigi E Silvio",
    "wof:placetype":"venue"
},
  "geometry": {"coordinates":[13.893129,42.878925],"type":"Point"}
}