{
  "type": "Feature",
  "properties": {
    "addr:full":"Vocabolo Zona Artigianale 05026 Montecastrilli Montecastrilli Terni 05026",
    "addr:postcode":"05026;05026",
    "addr:street":"Vocabolo;Artigianale",
    "iso:country":"IT",
    "sg:address":"Vocabolo Zona Artigianale 05026 Montecastrilli",
    "sg:city":"Montecastrilli",
    "sg:classifiers":[
        {
            "category":"Shopping",
            "subcategory":"Stationery & Office Supplies",
            "type":"Retail Goods"
        }
    ],
    "sg:phone":"+39 0744 935021",
    "sg:postcode":"05026",
    "sg:province":"Terni",
    "sg:tags":[
        "professional"
    ],
    "wof:name":"F.u.m.u. S.n.c. Di Secondi M. & C.",
    "wof:placetype":"venue"
},
  "geometry": {"coordinates":[12.4953899384,42.6347999573],"type":"Point"}
}