{
  "type": "Feature",
  "properties": {
    "iso:country":"IT",
    "sg:address":"10030 Vische",
    "sg:city":"Vische",
    "sg:orig_category":"Macchine, Impianti Ed Attrezzature Industria Delle Materie Plastiche E Gomma",
    "sg:phone":"+39 011 983 7558",
    "sg:postcode":"10030",
    "sg:province":"Torino",
    "sg:website":"http://www.canavese.it",
    "wof:name":"Gruner Srl",
    "wof:placetype":"venue"
},
  "geometry": {"coordinates":[7.944851,45.335453],"type":"Point"}
}