{
  "type": "Feature",
  "properties": {
    "iso:country":"IT",
    "sg:address":"25085 Gavardo",
    "sg:city":"Gavardo",
    "sg:classifiers":[
        {
            "category":"Manufacturing",
            "subcategory":"Metals",
            "type":"Manufacturing & Wholesale Goods"
        }
    ],
    "sg:phone":"+39 036 537 4547",
    "sg:postcode":"25085",
    "sg:province":"Brescia",
    "sg:tags":[
        "forming",
        "working",
        "welding"
    ],
    "wof:name":"Tecnojet Snc Di Frapporti & C.",
    "wof:placetype":"venue"
},
  "geometry": {"coordinates":[10.4198980331,45.5896835327],"type":"Point"}
}