{
  "type": "Feature",
  "properties": {
    "iso:country":"IT",
    "sg:address":"20121 Milano",
    "sg:city":"Milano",
    "sg:orig_category":"Abbigliamento Esterno, Maglierie E Pelliccerie. Servizi E Lavori Per Abbigliamento E Pelletterie",
    "sg:phone":"+39 02 878741",
    "sg:postcode":"20121",
    "sg:province":"Milano",
    "wof:name":"Mayerna Camillo",
    "wof:placetype":"venue"
},
  "geometry": {"coordinates":[9.190742,45.465305],"type":"Point"}
}