{
  "type": "Feature",
  "properties": {
    "iso:country":"IT",
    "sg:address":"81030 Lusciano",
    "sg:city":"Lusciano",
    "sg:orig_category":"Aziende Agricole",
    "sg:phone":"+39 081 501 7308",
    "sg:postcode":"81030",
    "sg:province":"Caserta",
    "wof:name":"Coop. Agricola Ortofrutta Luscianese Arl",
    "wof:placetype":"venue"
},
  "geometry": {"coordinates":[14.185974,40.967293],"type":"Point"}
}