{
  "type": "Feature",
  "properties": {
    "addr:full":"10, Via Salvo D'acquisto 20020 Villa Cortese Villa Cortese Milano 20020",
    "addr:postcode":"20020;20020",
    "addr:street":"Via Salvo D'Acquisto;Cortese",
    "iso:country":"IT",
    "sg:address":"10, Via Salvo D'acquisto 20020 Villa Cortese",
    "sg:city":"Villa Cortese",
    "sg:classifiers":[
        {
            "category":"Professional",
            "subcategory":"Engineering",
            "type":"Services"
        }
    ],
    "sg:phone":"+39 0331 434511",
    "sg:postcode":"20020",
    "sg:province":"Milano",
    "sg:tags":[
        "machine",
        "-",
        "mechanical"
    ],
    "wof:name":"Pietro Carnaghi Spa",
    "wof:placetype":"venue"
},
  "geometry": {"coordinates":[8.878798,45.56765],"type":"Point"}
}