{
  "type": "Feature",
  "properties": {
    "addr:full":"Via Ca' Balotta 5/c 37010 Affi Affi Verona 37010",
    "addr:housenumber":"5 / c",
    "addr:postcode":"37010;37010",
    "addr:street":"Via Ca ' Balotta",
    "iso:country":"IT",
    "sg:address":"Via Ca' Balotta 5/c 37010 Affi",
    "sg:city":"Affi",
    "sg:classifiers":[
        {
            "category":"Building & Trades",
            "subcategory":"Construction",
            "type":"Services"
        }
    ],
    "sg:phone":"+39 045 620 0322",
    "sg:postcode":"37010",
    "sg:province":"Verona",
    "sg:tags":[
        "heat",
        "exchanger"
    ],
    "wof:name":"Thermont Industrie Montini S.p.a",
    "wof:placetype":"venue"
},
  "geometry": {"coordinates":[10.77104,45.565441],"type":"Point"}
}