{
  "type": "Feature",
  "properties": {
    "iso:country":"IT",
    "sg:address":"142, Via S. Giovanni Evangelista 41053 Maranello",
    "sg:city":"Maranello",
    "sg:classifiers":[
        {
            "category":"Professional",
            "subcategory":"Engineering",
            "type":"Services"
        }
    ],
    "sg:phone":"+39 0536 944105",
    "sg:postcode":"41053",
    "sg:province":"Modena",
    "sg:tags":[
        "machine",
        "-",
        "mechanical"
    ],
    "wof:name":"Tck S.r.l.",
    "wof:placetype":"venue"
},
  "geometry": {"coordinates":[10.865998,44.529224],"type":"Point"}
}