{
  "type": "Feature",
  "properties": {
    "iso:country":"IT",
    "sg:address":"20123 Milano",
    "sg:city":"Milano",
    "sg:orig_category":"Lampadari - Produzione E Ingrosso",
    "sg:phone":"+39 02 5810 6616",
    "sg:postcode":"20123",
    "sg:province":"Milano",
    "sg:website":"http://studiopizzol.com",
    "wof:name":"Studio Sante Pizzol",
    "wof:placetype":"venue"
},
  "geometry": {"coordinates":[9.176764,45.456375],"type":"Point"}
}