{
  "type": "Feature",
  "properties": {
    "iso:country":"IT",
    "sg:address":"21, Via Dell' Artigianato 35010 Vigonza",
    "sg:city":"Vigonza",
    "sg:classifiers":[
        {
            "category":"Professional",
            "subcategory":"Engineering",
            "type":"Services"
        }
    ],
    "sg:phone":"+39 049 893 0194",
    "sg:postcode":"35010",
    "sg:province":"Padova",
    "sg:tags":[
        "machine",
        "-",
        "mechanical"
    ],
    "wof:name":"Rettifica Nord (s.r.l.)",
    "wof:placetype":"venue"
},
  "geometry": {"coordinates":[11.953029,45.432724],"type":"Point"}
}