{
  "type": "Feature",
  "properties": {
    "iso:country":"IT",
    "sg:address":"31029 Farra D'alpago",
    "sg:orig_category":"Servizi Per Lo Sport E Il Tempo Libero. Alberghi E Strutture Extra Alberghiere",
    "sg:phone":"+39 0438 585353",
    "sg:postcode":"31029",
    "sg:province":"Treviso",
    "sg:website":"http://www.italiaabc.it/az/osvaldo/",
    "wof:name":"Grillo Renato - Rifugio Sant'osvaldo",
    "wof:placetype":"venue"
},
  "geometry": {"coordinates":[12.242072,45.666286],"type":"Point"}
}