{
  "type": "Feature",
  "properties": {
    "iso:country":"IT",
    "sg:address":"Localita' Castelnuovo 52010 Subbiano",
    "sg:city":"Subbiano",
    "sg:classifiers":[
        {
            "category":"Shopping",
            "subcategory":"Computers & Home Electronics",
            "type":"Retail Goods"
        }
    ],
    "sg:phone":"+39 39057542151",
    "sg:postcode":"52010",
    "sg:province":"Arezzo",
    "sg:tags":[
        "electronic",
        "electrical",
        "equipment"
    ],
    "wof:name":"Aec Illuminazione S.r.l.",
    "wof:placetype":"venue"
},
  "geometry": {"coordinates":[11.853749,43.558208],"type":"Point"}
}