{
  "type": "Feature",
  "properties": {
    "iso:country":"IT",
    "sg:address":"10024 Moncalieri",
    "sg:city":"Moncalieri",
    "sg:orig_category":"Gru - Costruzione E Commercio",
    "sg:phone":"+39 011 682 0205",
    "sg:postcode":"10024",
    "sg:province":"Torino",
    "sg:website":"http://www.gusella.net",
    "wof:name":"Gusella - Polipi Idraulici",
    "wof:placetype":"venue"
},
  "geometry": {"coordinates":[7.661454,45.008327],"type":"Point"}
}