{
  "type": "Feature",
  "properties": {
    "iso:country":"IT",
    "sg:address":"33010 Magnano In Riviera",
    "sg:city":"Magnano in Riviera",
    "sg:orig_category":"Arredamento Scuole E Comunita'",
    "sg:phone":"+39 0432 785112",
    "sg:postcode":"33010",
    "sg:province":"Udine",
    "sg:website":"http://www.cignini.it",
    "wof:name":"Arredamenti Cignini Di Cignini Franca & C. Snc",
    "wof:placetype":"venue"
},
  "geometry": {"coordinates":[13.192037,46.229389],"type":"Point"}
}