{
  "type": "Feature",
  "properties": {
    "iso:country":"IT",
    "sg:address":"71016 San Severo",
    "sg:city":"San Severo",
    "sg:classifiers":[
        {
            "category":"Autos & Motor Vehicles",
            "subcategory":"Fuel & Gas Station",
            "type":"Retail Goods"
        }
    ],
    "sg:phone":"+39 0882 240480",
    "sg:postcode":"71016",
    "sg:province":"Foggia",
    "sg:tags":[
        "repair",
        "part",
        "vehicles",
        "spare",
        "components"
    ],
    "wof:name":"Valerio Antonio",
    "wof:placetype":"venue"
},
  "geometry": {"coordinates":[15.4302387238,41.641582489],"type":"Point"}
}