{
  "type": "Feature",
  "properties": {
    "iso:country":"IT",
    "sg:address":"10073 Cirie'",
    "sg:classifiers":[
        {
            "category":"Professional",
            "subcategory":"Art Services",
            "type":"Services"
        }
    ],
    "sg:phone":"+39 011 922 2277",
    "sg:postcode":"10073",
    "sg:province":"Torino",
    "sg:tags":[
        "studi",
        "designer",
        "-"
    ],
    "sg:website":"http://www.webcreation.it",
    "wof:name":"Webcreation Di Bianco Federico",
    "wof:placetype":"venue"
},
  "geometry": {"coordinates":[7.6944,45.056976],"type":"Point"}
}