{
  "type": "Feature",
  "properties": {
    "iso:country":"IT",
    "sg:address":"Via Rigosa 3 40069 Zola Predosa",
    "sg:city":"Zola",
    "sg:classifiers":[
        {
            "category":"Wholesale",
            "subcategory":"Vending Machines",
            "type":"Manufacturing & Wholesale Goods"
        }
    ],
    "sg:phone":"+39 051 758925",
    "sg:postcode":"40069",
    "sg:province":"Bologna",
    "sg:tags":[
        "packing",
        "wrapping",
        "enveloping"
    ],
    "wof:name":"O.m.m.a. Srl",
    "wof:placetype":"venue"
},
  "geometry": {"coordinates":[11.227029,44.48875],"type":"Point"}
}