{
  "type": "Feature",
  "properties": {
    "iso:country":"IT",
    "sg:address":"70124 Bari",
    "sg:city":"Bari",
    "sg:classifiers":[
        {
            "category":"Wholesale",
            "subcategory":"Machinery & Supplies",
            "type":"Manufacturing & Wholesale Goods"
        }
    ],
    "sg:phone":"+39 080 504 6963",
    "sg:postcode":"70124",
    "sg:province":"Bari",
    "sg:tags":[
        "product",
        "industrial",
        "equipment",
        "engineering",
        "mechanical",
        "electronic"
    ],
    "wof:name":"Nte Spa Ingegneria E Automazione Industriale",
    "wof:placetype":"venue"
},
  "geometry": {"coordinates":[16.848211,41.101604],"type":"Point"}
}