{
  "type": "Feature",
  "properties": {
    "addr:full":"43100 Parma Parma Parma 43100",
    "addr:postcode":"43100;43100",
    "iso:country":"IT",
    "sg:address":"43100 Parma",
    "sg:city":"Parma",
    "sg:classifiers":[
        {
            "category":"Restaurant",
            "type":"Food & Drink"
        }
    ],
    "sg:phone":"+39 0521 460114",
    "sg:postcode":"43100",
    "sg:province":"Parma",
    "sg:tags":[
        "equipment",
        "industry",
        "machinery"
    ],
    "wof:name":"Fava Srl",
    "wof:placetype":"venue"
},
  "geometry": {"coordinates":[10.3316364288,44.7807769775],"type":"Point"}
}