{
  "type": "Feature",
  "properties": {
    "addr:full":"84129 Salerno Salerno Salerno 84129",
    "addr:postcode":"84129;84129",
    "iso:country":"IT",
    "sg:address":"84129 Salerno",
    "sg:city":"Salerno",
    "sg:orig_category":"Arredo Cucina Ed Elettrodomestici. Elettrodomestici",
    "sg:phone":"+39 089 721072",
    "sg:postcode":"84129",
    "sg:province":"Salerno",
    "wof:name":"Del Regno Nicola",
    "wof:placetype":"venue"
},
  "geometry": {"coordinates":[14.797312,40.662483],"type":"Point"}
}