{
  "type": "Feature",
  "properties": {
    "iso:country":"IT",
    "sg:address":"Via E Grella 55; Sturno",
    "sg:classifiers":[
        {
            "category":"Banks & Credit Unions",
            "subcategory":"Bank",
            "type":"Services"
        }
    ],
    "sg:phone":"+39 0825 437061",
    "wof:name":"Banca Di Roma",
    "wof:placetype":"venue"
},
  "geometry": {"coordinates":[15.112493,41.014774],"type":"Point"}
}