{
  "type": "Feature",
  "properties": {
    "addr:full":"20060 Pozzuolo Martesana Pozzuolo Martesana Milano 20060",
    "addr:postcode":"20060;20060",
    "iso:country":"IT",
    "sg:address":"20060 Pozzuolo Martesana",
    "sg:city":"Pozzuolo Martesana",
    "sg:orig_category":"Ospedali E Servizi Sanitari",
    "sg:phone":"+39 02 9535 9826",
    "sg:postcode":"20060",
    "sg:province":"Milano",
    "wof:name":"Croce Rossa Italiana",
    "wof:placetype":"venue"
},
  "geometry": {"coordinates":[9.4534,45.513584],"type":"Point"}
}