{
  "type": "Feature",
  "properties": {
    "addr:full":"20146 Milano Milano Milano 20146",
    "addr:postcode":"20146;20146",
    "iso:country":"IT",
    "sg:address":"20146 Milano",
    "sg:city":"Milano",
    "sg:orig_category":"Forniture Per Abbigliamento E Pelletterie",
    "sg:phone":"+39 02 4391 1753",
    "sg:postcode":"20146",
    "sg:province":"Milano",
    "wof:name":"Clemytex Srl",
    "wof:placetype":"venue"
},
  "geometry": {"coordinates":[9.1505784988,45.4661827087],"type":"Point"}
}