{
  "type": "Feature",
  "properties": {
    "iso:country":"IT",
    "sg:address":"10, Via Aldo Moro 24030 Ambivere",
    "sg:city":"Ambivere",
    "sg:classifiers":[
        {
            "category":"Professional",
            "subcategory":"Engineering",
            "type":"Services"
        }
    ],
    "sg:phone":"+39 39035909446",
    "sg:postcode":"24030",
    "sg:province":"Bergamo",
    "sg:tags":[
        "machine",
        "-",
        "mechanical"
    ],
    "wof:name":"Ma.spe Srl",
    "wof:placetype":"venue"
},
  "geometry": {"coordinates":[9.58002,45.735271],"type":"Point"}
}