{
  "type": "Feature",
  "properties": {
    "iso:country":"IT",
    "sg:address":"Corso Cavour 17; Verona; 37121",
    "sg:city":"Verona",
    "sg:classifiers":[
        {
            "category":"Banks & Credit Unions",
            "subcategory":"Bank",
            "type":"Services"
        }
    ],
    "sg:phone":"+39 045 800 4214",
    "sg:postcode":"37121",
    "sg:province":"Verona",
    "wof:name":"Rolo Banca 1473 Spa",
    "wof:placetype":"venue"
},
  "geometry": {"coordinates":[10.991779,45.441124],"type":"Point"}
}