{
  "type": "Feature",
  "properties": {
    "iso:country":"IT",
    "sg:address":"50052 Certaldo",
    "sg:city":"Certaldo",
    "sg:orig_category":"Prodotti E Manufatti In Materie Plastiche. Servizi E Lavori Industria Delle Materie Plastiche",
    "sg:phone":"+39 0571 665055",
    "sg:postcode":"50052",
    "sg:province":"Firenze",
    "sg:website":"http://www.gvm.it",
    "wof:name":"Gvm Spa",
    "wof:placetype":"venue"
},
  "geometry": {"coordinates":[11.0664424896,43.5304794312],"type":"Point"}
}