{
  "type": "Feature",
  "properties": {
    "iso:country":"IT",
    "sg:address":"2, Via Signorindico 82011 Forchia",
    "sg:city":"Forchia",
    "sg:classifiers":[
        {
            "category":"Manufacturing",
            "subcategory":"Rubber & Plastics",
            "type":"Manufacturing & Wholesale Goods"
        }
    ],
    "sg:phone":"+39 0823 804150",
    "sg:postcode":"82011",
    "sg:province":"Benevento",
    "wof:name":"Co.ma.p. Sud Srl",
    "wof:placetype":"venue"
},
  "geometry": {"coordinates":[14.5158758163,41.038230896],"type":"Point"}
}