{
  "type": "Feature",
  "properties": {
    "iso:country":"IT",
    "sg:address":"39, Via Metaponto 74100 Taranto",
    "sg:city":"Taranto",
    "sg:classifiers":[
        {
            "category":"Parking",
            "subcategory":"Lot",
            "type":"Transportation"
        }
    ],
    "sg:phone":"+39 099 471 5386",
    "sg:postcode":"74100",
    "sg:province":"Taranto",
    "sg:tags":[
        "transport",
        "road"
    ],
    "wof:name":"Consorzio Autocisterne Tarantine",
    "wof:placetype":"venue"
},
  "geometry": {"coordinates":[17.234667,40.474998],"type":"Point"}
}