{
  "type": "Feature",
  "properties": {
    "iso:country":"IT",
    "sg:address":"70031 Andria",
    "sg:city":"Andria",
    "sg:orig_category":"Antifurto",
    "sg:phone":"+39 0883 593566",
    "sg:postcode":"70031",
    "sg:province":"Bari",
    "wof:name":"Allarm Sud Snc",
    "wof:placetype":"venue"
},
  "geometry": {"coordinates":[16.298981,41.232334],"type":"Point"}
}