{
  "type": "Feature",
  "properties": {
    "iso:country":"IT",
    "sg:address":"20124 Milano",
    "sg:city":"Milano",
    "sg:orig_category":"Musica",
    "sg:phone":"+39 02 2940 6108",
    "sg:postcode":"20124",
    "sg:province":"Milano",
    "wof:name":"Mama Records Srl",
    "wof:placetype":"venue"
},
  "geometry": {"coordinates":[9.2073535919,45.4787216187],"type":"Point"}
}