{
  "type": "Feature",
  "properties": {
    "addr:full":"25, V. G. Rizzo 98057 Milazzo Milazzo Messina 98057",
    "addr:housenumber":"25",
    "addr:postcode":"98057;98057",
    "addr:street":"V. G. Rizzo",
    "iso:country":"IT",
    "sg:address":"25, V. G. Rizzo 98057 Milazzo",
    "sg:city":"Milazzo",
    "sg:classifiers":[
        {
            "category":"Autos & Motor Vehicles",
            "subcategory":"Boat Sales",
            "type":"Retail Goods"
        }
    ],
    "sg:phone":"+39 090 924 1616",
    "sg:postcode":"98057",
    "sg:province":"Messina",
    "sg:website":"http://www.diessemare.com",
    "wof:name":"Diessemare",
    "wof:placetype":"venue"
},
  "geometry": {"coordinates":[14.699453,38.093761],"type":"Point"}
}