{
  "type": "Feature",
  "properties": {
    "addr:full":"Viale Storchi 235; Modena; 41100 Modena Modena 41100",
    "addr:housenumber":"235",
    "addr:postcode":"41100;41100",
    "addr:street":"Viale Storchi",
    "iso:country":"IT",
    "sg:address":"Viale Storchi 235; Modena; 41100",
    "sg:city":"Modena",
    "sg:classifiers":[
        {
            "category":"Banks & Credit Unions",
            "subcategory":"Bank",
            "type":"Services"
        }
    ],
    "sg:phone":"+39 059 222862",
    "sg:postcode":"41100",
    "sg:province":"Modena",
    "wof:name":"Credito Emiliano Spa",
    "wof:placetype":"venue"
},
  "geometry": {"coordinates":[10.91662,44.652122],"type":"Point"}
}