{
  "type": "Feature",
  "properties": {
    "iso:country":"IT",
    "sg:address":"16149 Genova",
    "sg:city":"Genova",
    "sg:orig_category":"Imprese Di Costruzioni Civili Ed Industriali",
    "sg:phone":"+39 010 419325",
    "sg:postcode":"16149",
    "sg:province":"Genova",
    "sg:website":"http://www.parcheggi.it",
    "wof:name":"L.f. Lift Force",
    "wof:placetype":"venue"
},
  "geometry": {"coordinates":[8.899701,44.412285],"type":"Point"}
}