{
  "type": "Feature",
  "properties": {
    "addr:full":"7, Via S. Paolo 20121 Milano Milano Milano 20121",
    "addr:postcode":"20121;20121",
    "addr:street":"Via S. Paolo",
    "iso:country":"IT",
    "sg:address":"7, Via S. Paolo 20121 Milano",
    "sg:city":"Milano",
    "sg:classifiers":[
        {
            "category":"Banks & Credit Unions",
            "subcategory":"Financial Services",
            "type":"Services"
        }
    ],
    "sg:phone":"+39 390 287 6188",
    "sg:postcode":"20121",
    "sg:province":"Milano",
    "sg:tags":[
        "banking",
        "finance",
        "insurance"
    ],
    "wof:name":"Agenzia Generale Ina Assitalia Milano Bcf Ass.ni S.r.l.",
    "wof:placetype":"venue"
},
  "geometry": {"coordinates":[9.193618,45.465485],"type":"Point"}
}