{
  "type": "Feature",
  "properties": {
    "iso:country":"IT",
    "sg:address":"8, Via G. Galilei 46025 Poggio Rusco",
    "sg:city":"Poggio Rusco",
    "sg:classifiers":[
        {
            "category":"Wholesale",
            "subcategory":"Machinery & Supplies",
            "type":"Manufacturing & Wholesale Goods"
        }
    ],
    "sg:phone":"+39 39038651339",
    "sg:postcode":"46025",
    "sg:province":"Mantova",
    "sg:tags":[
        "-",
        "agriculture",
        "equipment"
    ],
    "wof:name":"Gilioli S.r.l.",
    "wof:placetype":"venue"
},
  "geometry": {"coordinates":[10.797698,45.160366],"type":"Point"}
}