{
  "type": "Feature",
  "properties": {
    "iso:country":"IT",
    "sg:address":"23864 Malgrate",
    "sg:city":"Malgrate",
    "sg:orig_category":"Automobili E Mezzi Di Trasporto",
    "sg:phone":"+39 0341 200616",
    "sg:postcode":"23864",
    "sg:province":"Lecco",
    "wof:name":"F.lli Valli Srl",
    "wof:placetype":"venue"
},
  "geometry": {"coordinates":[9.378668,45.849506],"type":"Point"}
}