{
  "type": "Feature",
  "properties": {
    "iso:country":"IT",
    "sg:address":"52015 Pratovecchio",
    "sg:city":"Pratovecchio",
    "sg:orig_category":"Ferramenta - Ingrosso",
    "sg:phone":"+39 0575 583739",
    "sg:postcode":"52015",
    "sg:province":"Arezzo",
    "sg:website":"http://www.alberti-net.com",
    "wof:name":"Alberti Giuseppe",
    "wof:placetype":"venue"
},
  "geometry": {"coordinates":[11.7218255997,43.7880783081],"type":"Point"}
}