{
  "type": "Feature",
  "properties": {
    "iso:country":"IT",
    "sg:address":"5, V. Lago Maggiore 36015 Schio",
    "sg:city":"Schio",
    "sg:classifiers":[
        {
            "category":"Shopping",
            "type":"Retail Goods"
        }
    ],
    "sg:phone":"+39 0445 575664",
    "sg:postcode":"36015",
    "sg:province":"Vicenza",
    "sg:tags":[
        "finished",
        "-",
        "metallic"
    ],
    "sg:website":"http://www.omaf.it",
    "wof:name":"O.m.a.f. Snc",
    "wof:placetype":"venue"
},
  "geometry": {"coordinates":[11.3994750977,45.7187232971],"type":"Point"}
}