{
  "type": "Feature",
  "properties": {
    "iso:country":"IT",
    "sg:address":"96010 Ferla",
    "sg:city":"Ferla",
    "sg:orig_category":"Pubblica Amministrazione",
    "sg:phone":"+39 0931 870136",
    "sg:postcode":"96010",
    "sg:province":"Siracusa",
    "sg:website":"http://www.comuneferla.com",
    "wof:name":"Comune Di Ferla",
    "wof:placetype":"venue"
},
  "geometry": {"coordinates":[14.9412679672,37.1185188293],"type":"Point"}
}