{
  "type": "Feature",
  "properties": {
    "iso:country":"IT",
    "sg:address":"95131 Catania",
    "sg:city":"Catania",
    "sg:orig_category":"Macchine Ed Impianti Per Edilizia E Lavori Pubblici. Apparecchiature Ed Attrezzature Meccaniche",
    "sg:phone":"+39 095 531538",
    "sg:postcode":"95131",
    "sg:province":"Catania",
    "wof:name":"Maglia Srl",
    "wof:placetype":"venue"
},
  "geometry": {"coordinates":[15.096665,37.505169],"type":"Point"}
}