{
  "type": "Feature",
  "properties": {
    "iso:country":"IT",
    "sg:address":"24126 Bergamo",
    "sg:city":"Bergamo",
    "sg:orig_category":"Autogru - Noleggio",
    "sg:phone":"+39 035 692944",
    "sg:postcode":"24126",
    "sg:province":"Bergamo",
    "wof:name":"Societ\u00c0 Trasporti Bergamo Srl",
    "wof:placetype":"venue"
},
  "geometry": {"coordinates":[9.657347,45.671482],"type":"Point"}
}