{
  "type": "Feature",
  "properties": {
    "iso:country":"IT",
    "sg:address":"36061 Bassano Del Grappa",
    "sg:city":"Bassano del Grappa",
    "sg:orig_category":"Tessuti E Stoffe. Tessuti Arredamento, Tende E Tappeti",
    "sg:phone":"+39 0424 507011",
    "sg:postcode":"36061",
    "sg:province":"Vicenza",
    "wof:name":"Bussandri Arte Srl",
    "wof:placetype":"venue"
},
  "geometry": {"coordinates":[11.696572,45.747662],"type":"Point"}
}