{
  "type": "Feature",
  "properties": {
    "addr:full":"44100 Ferrara Ferrara Ferrara 44100",
    "addr:postcode":"44100;44100",
    "iso:country":"IT",
    "sg:address":"44100 Ferrara",
    "sg:city":"Ferrara",
    "sg:orig_category":"Servizi Culturali E Per Lo Spettacolo. Cine-foto-ottica",
    "sg:phone":"+39 0532 249909",
    "sg:postcode":"44100",
    "sg:province":"Ferrara",
    "wof:name":"Bovolenta Marco Videostar",
    "wof:placetype":"venue"
},
  "geometry": {"coordinates":[11.61934,44.845245],"type":"Point"}
}