{
  "type": "Feature",
  "properties": {
    "iso:country":"IT",
    "sg:address":"53042 Chianciano Terme",
    "sg:city":"Chianciano Terme",
    "sg:orig_category":"Alberghi",
    "sg:phone":"+39 0578 63312",
    "sg:postcode":"53042",
    "sg:province":"Siena",
    "wof:name":"Albergo Santa Chiara",
    "wof:placetype":"venue"
},
  "geometry": {"coordinates":[11.832156,43.052078],"type":"Point"}
}