{
  "type": "Feature",
  "properties": {
    "addr:full":"23, Via Manzoni Alessandro 25047 Darfo Boario Terme Darfo Brescia 25047",
    "addr:postcode":"25047;25047",
    "addr:street":"Via Manzoni Alessandro",
    "iso:country":"IT",
    "sg:address":"23, Via Manzoni Alessandro 25047 Darfo Boario Terme",
    "sg:city":"Darfo",
    "sg:classifiers":[
        {
            "category":"Real Estate",
            "subcategory":"Surveying",
            "type":"Services"
        }
    ],
    "sg:phone":"+39 036 453 1658",
    "sg:postcode":"25047",
    "sg:province":"Brescia",
    "sg:tags":[
        "equipment",
        "material",
        "good",
        "-",
        "handling"
    ],
    "wof:name":"Slingofer Meccanica (s.p.a.)",
    "wof:placetype":"venue"
},
  "geometry": {"coordinates":[10.222958,45.539829],"type":"Point"}
}