{
  "type": "Feature",
  "properties": {
    "iso:country":"IT",
    "sg:address":"107-109, V. Vestricio Spurinna 00175 Roma",
    "sg:city":"Roma",
    "sg:classifiers":[
        {
            "category":"Wholesale",
            "subcategory":"Medical Equipment & Supplies",
            "type":"Manufacturing & Wholesale Goods"
        }
    ],
    "sg:phone":"+39 06 7641 56835",
    "sg:postcode":"00175",
    "sg:province":"Roma",
    "sg:tags":[
        "-",
        "health",
        "instrument"
    ],
    "sg:website":"http://www.centro.ortopedico2000.com",
    "wof:name":"Centro Ortopedico 2000 Srl",
    "wof:placetype":"venue"
},
  "geometry": {"coordinates":[12.555399,41.864197],"type":"Point"}
}