{
  "type": "Feature",
  "properties": {
    "iso:country":"IT",
    "sg:address":"17047 Vado Ligure",
    "sg:city":"Vado Ligure",
    "sg:orig_category":"Materiali Edili",
    "sg:phone":"+39 019 881567",
    "sg:postcode":"17047",
    "sg:province":"Savona",
    "wof:name":"Nuova Isoltermica (s.r.l.)",
    "wof:placetype":"venue"
},
  "geometry": {"coordinates":[8.427121,44.266945],"type":"Point"}
}