{
  "type": "Feature",
  "properties": {
    "iso:country":"IT",
    "sg:address":"Localita' Ponte Nuovo 33040 Torreano",
    "sg:city":"Torreano",
    "sg:classifiers":[
        {
            "category":"Home & Garden",
            "subcategory":"Home Furnishings",
            "type":"Retail Goods"
        }
    ],
    "sg:phone":"+39 0432 715246",
    "sg:postcode":"33040",
    "sg:province":"Udine",
    "sg:tags":[
        "household"
    ],
    "wof:name":"Ethon (s.r.l.)",
    "wof:placetype":"venue"
},
  "geometry": {"coordinates":[13.415656,46.115799],"type":"Point"}
}