{
  "type": "Feature",
  "properties": {
    "addr:full":"Via Montevecchio 51; Fano; 61032 Fano Pesaro E Urbino 61032",
    "addr:housenumber":"51",
    "addr:postcode":"61032;61032",
    "addr:street":"Via Montevecchio",
    "iso:country":"IT",
    "sg:address":"Via Montevecchio 51; Fano; 61032",
    "sg:city":"Fano",
    "sg:classifiers":[
        {
            "category":"Banks & Credit Unions",
            "subcategory":"Bank",
            "type":"Services"
        }
    ],
    "sg:phone":"+39 0721 803761",
    "sg:postcode":"61032",
    "sg:province":"Pesaro E Urbino",
    "wof:name":"Banca Nazionale Del Lavoro Spa",
    "wof:placetype":"venue"
},
  "geometry": {"coordinates":[13.016803,43.843761],"type":"Point"}
}