{
  "type": "Feature",
  "properties": {
    "addr:full":"41013 Castelfranco Emilia Castelfranco Emilia Modena 41013",
    "addr:postcode":"41013;41013",
    "iso:country":"IT",
    "sg:address":"41013 Castelfranco Emilia",
    "sg:city":"Castelfranco Emilia",
    "sg:orig_category":"Telecomunicazioni E Telefonia, Impianti, Apparecchi E Servizi. Automazione E Macchine Per Ufficio",
    "sg:phone":"+39 059 932083",
    "sg:postcode":"41013",
    "sg:province":"Modena",
    "wof:name":"Video Elettronica (s.n.c.)",
    "wof:placetype":"venue"
},
  "geometry": {"coordinates":[10.973092,44.626823],"type":"Point"}
}