{
  "type": "Feature",
  "properties": {
    "iso:country":"IT",
    "sg:address":"00061 Anguillara Sabazia",
    "sg:city":"Anguillara Sabazia",
    "sg:orig_category":"Servizi Culturali E Per Lo Spettacolo. Servizi Al Turismo. Acqua, Luce, Gas E Societa' Di Esercizio Pubblico",
    "sg:phone":"+39 06 996 8436",
    "sg:postcode":"00061",
    "sg:province":"Roma",
    "wof:name":"Comune Di Anguillara Sabazia",
    "wof:placetype":"venue"
},
  "geometry": {"coordinates":[12.269789,42.092911],"type":"Point"}
}