{
  "type": "Feature",
  "properties": {
    "addr:full":"20134 Milano Milano Milano 20134",
    "addr:postcode":"20134;20134",
    "iso:country":"IT",
    "sg:address":"20134 Milano",
    "sg:city":"Milano",
    "sg:orig_category":"Carni, Salumi E Pesci",
    "sg:phone":"+39 02 214 0510",
    "sg:postcode":"20134",
    "sg:province":"Milano",
    "wof:name":"Pescheria Rombon Di Fugaro Alessandro",
    "wof:placetype":"venue"
},
  "geometry": {"coordinates":[9.241261,45.486168],"type":"Point"}
}