{
  "type": "Feature",
  "properties": {
    "iso:country":"IT",
    "sg:address":"10091 Alpignano",
    "sg:city":"Alpignano",
    "sg:orig_category":"Forniture Per Agricoltura E Zootecnia. Forniture Per Attivita' Industriali",
    "sg:phone":"+39 011 967 6623",
    "sg:postcode":"10091",
    "sg:province":"Torino",
    "wof:name":"Rete Plastic S.r.l.",
    "wof:placetype":"venue"
},
  "geometry": {"coordinates":[7.5745100975,45.0941009521],"type":"Point"}
}