{
  "type": "Feature",
  "properties": {
    "iso:country":"IT",
    "sg:address":"03012 Anagni",
    "sg:city":"Anagni",
    "sg:orig_category":"Ristorazione E Locali Pubblici Affini. Servizi Ausiliari Di Ristorazione E Di Intrattenimento",
    "sg:phone":"+39 0775 725695",
    "sg:postcode":"03012",
    "sg:province":"Frosinone",
    "wof:name":"Ristorante Le Mimose Srl",
    "wof:placetype":"venue"
},
  "geometry": {"coordinates":[13.17977,41.746326],"type":"Point"}
}