{
  "type": "Feature",
  "properties": {
    "addr:full":"1, Via L. Romagnoli 42023 Cadelbosco Di Sopra Reggio Nell'Emilia 42023",
    "addr:postcode":"42023;42023",
    "addr:street":"Via L. Romagnoli",
    "iso:country":"IT",
    "sg:address":"1, Via L. Romagnoli 42023 Cadelbosco Di Sopra",
    "sg:classifiers":[
        {
            "category":"Manufacturing",
            "subcategory":"Metals",
            "type":"Manufacturing & Wholesale Goods"
        }
    ],
    "sg:phone":"+39 0522 911307",
    "sg:postcode":"42023",
    "sg:province":"Reggio Nell'Emilia",
    "sg:tags":[
        "processing"
    ],
    "wof:name":"Tecknomak Snc Di Rinaldi & C.",
    "wof:placetype":"venue"
},
  "geometry": {"coordinates":[10.6103992462,44.7942810059],"type":"Point"}
}