{
  "type": "Feature",
  "properties": {
    "iso:country":"IT",
    "sg:address":"Via Angeli 24 63019 Sant'elpidio A Mare",
    "sg:orig_category":"Soles, Heels",
    "sg:phone":"+39 0734 810204",
    "sg:postcode":"63019",
    "sg:province":"Ascoli Piceno",
    "wof:name":"Tacchificio 3m Sas",
    "wof:placetype":"venue"
},
  "geometry": {"coordinates":[13.692762,43.226143],"type":"Point"}
}