{
  "type": "Feature",
  "properties": {
    "addr:full":"36061 Bassano Del Grappa Bassano del Grappa Vicenza 36061",
    "addr:postcode":"36061;36061",
    "iso:country":"IT",
    "sg:address":"36061 Bassano Del Grappa",
    "sg:city":"Bassano del Grappa",
    "sg:orig_category":"Servizi E Lavori Per Arredamento E Industria Del Legno",
    "sg:phone":"+39 0424 502596",
    "sg:postcode":"36061",
    "sg:province":"Vicenza",
    "wof:name":"Guazzo Arch. Carlo",
    "wof:placetype":"venue"
},
  "geometry": {"coordinates":[11.730305,45.767864],"type":"Point"}
}