{
  "type": "Feature",
  "properties": {
    "iso:country":"IT",
    "sg:address":"Via C. Pisacane 9 10042 Nichelino",
    "sg:city":"Nichelino",
    "sg:classifiers":[
        {
            "category":"Bars & Pubs",
            "subcategory":"Hookah Bar",
            "type":"Food & Drink"
        }
    ],
    "sg:phone":"+39 011 6899 8411",
    "sg:postcode":"10042",
    "sg:province":"Torino",
    "sg:tags":[
        "herbal",
        "preparation"
    ],
    "wof:name":"D. Ulrich Spa",
    "wof:placetype":"venue"
},
  "geometry": {"coordinates":[7.635062,44.977558],"type":"Point"}
}