{
  "type": "Feature",
  "properties": {
    "iso:country":"IT",
    "sg:address":"Via Radici Nord 90/a 42014 Castellarano",
    "sg:classifiers":[
        {
            "category":"Home & Garden",
            "subcategory":"Building Materials",
            "type":"Retail Goods"
        }
    ],
    "sg:phone":"+39 0536 874600",
    "sg:postcode":"42014",
    "sg:province":"Reggio Nell'Emilia",
    "sg:tags":[
        "tile",
        "ceramic"
    ],
    "sg:website":"www.ceramicavalsecchia.it",
    "wof:name":"Ceramica Valsecchia Spa",
    "wof:placetype":"venue"
},
  "geometry": {"coordinates":[10.627794,44.696228],"type":"Point"}
}