{
  "type": "Feature",
  "properties": {
    "addr:full":"40012 Calderara Di Reno Calderara di Reno Bologna 40012",
    "addr:postcode":"40012;40012",
    "iso:country":"IT",
    "sg:address":"40012 Calderara Di Reno",
    "sg:city":"Calderara di Reno",
    "sg:orig_category":"Automazione E Macchine Per Ufficio",
    "sg:phone":"+39 051 646 5011",
    "sg:postcode":"40012",
    "sg:province":"Bologna",
    "wof:name":"Cim (s.p.a.)",
    "wof:placetype":"venue"
},
  "geometry": {"coordinates":[11.297067,44.544659],"type":"Point"}
}