{
  "type": "Feature",
  "properties": {
    "iso:country":"IT",
    "sg:address":"3/a, Piazza Rossetti Raffaele 16129 Genova",
    "sg:city":"Genova",
    "sg:classifiers":[
        {
            "category":"Manufacturing",
            "subcategory":"Wood Products",
            "type":"Manufacturing & Wholesale Goods"
        }
    ],
    "sg:phone":"+39 010 570 2924",
    "sg:postcode":"16129",
    "sg:province":"Genova",
    "sg:tags":[
        "furniture"
    ],
    "wof:name":"Commerciale Oceano Indiano S.r.l.",
    "wof:placetype":"venue"
},
  "geometry": {"coordinates":[8.933989,44.407063],"type":"Point"}
}