{
  "type": "Feature",
  "properties": {
    "addr:full":"95047 Patern\u00f2 Catania 95047",
    "addr:postcode":"95047;95047",
    "iso:country":"IT",
    "sg:address":"95047 Patern\u00f2",
    "sg:orig_category":"Servizi Culturali E Per Lo Spettacolo. Servizi Per Lo Sport E Il Tempo Libero. Servizi Per Aziende, Manifestazioni E Supporto Agli Scambi Commerciali",
    "sg:phone":"+39 0385 407 0871",
    "sg:postcode":"95047",
    "sg:province":"Catania",
    "wof:name":"Fallica Margherita",
    "wof:placetype":"venue"
},
  "geometry": {"coordinates":[14.868813,37.559101],"type":"Point"}
}