{
  "type": "Feature",
  "properties": {
    "iso:country":"IT",
    "sg:address":"Via Faentina 175 48100 Fornace Zarattini",
    "sg:city":"Fornace zarattini",
    "sg:classifiers":[
        {
            "category":"Bars & Pubs",
            "subcategory":"Nightclub",
            "type":"Food & Drink"
        }
    ],
    "sg:phone":"+39 0544 460762",
    "sg:postcode":"48100",
    "sg:province":"Ravenna",
    "sg:tags":[
        "cake",
        "bread"
    ],
    "wof:name":"Lapineta Soc Coop A Rl",
    "wof:placetype":"venue"
},
  "geometry": {"coordinates":[12.157523,44.4217],"type":"Point"}
}