{
  "type": "Feature",
  "properties": {
    "addr:full":"Via 20 Settembre 6/b 20061 Carugate Carugate Milano 20061",
    "addr:housenumber":"6 / b",
    "addr:postcode":"20061;20061",
    "addr:street":"Via 20 Settembre;Carugate",
    "iso:country":"IT",
    "sg:address":"Via 20 Settembre 6/b 20061 Carugate",
    "sg:city":"Carugate",
    "sg:classifiers":[
        {
            "category":"Travel",
            "subcategory":"Bed & Breakfast",
            "type":"Entertainment"
        }
    ],
    "sg:phone":"+39 02 9215 0000",
    "sg:postcode":"20061",
    "sg:province":"Milano",
    "sg:tags":[
        "molasses"
    ],
    "sg:website":"www.tateandlyle.com",
    "wof:name":"Melitaliana S.p.a.",
    "wof:placetype":"venue"
},
  "geometry": {"coordinates":[9.1881408691,45.4636878967],"type":"Point"}
}