{
  "type": "Feature",
  "properties": {
    "iso:country":"IT",
    "sg:address":"8, Via Giovanni Xxiii Papa 80018 Mugnano Di Napoli",
    "sg:city":"Mugnano di Napoli",
    "sg:classifiers":[
        {
            "category":"Personal",
            "subcategory":"Shoe Repair & Shine",
            "type":"Services"
        }
    ],
    "sg:phone":"+39 081 712 1144",
    "sg:postcode":"80018",
    "sg:province":"Napoli",
    "sg:tags":[
        "leather"
    ],
    "wof:name":"Vitulli (s.a.s.)",
    "wof:placetype":"venue"
},
  "geometry": {"coordinates":[14.193581,40.90976],"type":"Point"}
}