{
  "type": "Feature",
  "properties": {
    "iso:country":"IT",
    "sg:address":"20159 Milano",
    "sg:city":"Milano",
    "sg:orig_category":"Forniture Per Uffici",
    "sg:phone":"+39 02 606962",
    "sg:postcode":"20159",
    "sg:province":"Milano",
    "wof:name":"Zara Point Di Stefano Alberto Colombo",
    "wof:placetype":"venue"
},
  "geometry": {"coordinates":[9.1896886826,45.4900779724],"type":"Point"}
}