{
  "type": "Feature",
  "properties": {
    "addr:full":"Piazza Indipendenza 47; Latisana",
    "addr:housenumber":"47",
    "addr:street":"Piazza Indipendenza",
    "iso:country":"IT",
    "sg:address":"Piazza Indipendenza 47; Latisana",
    "sg:classifiers":[
        {
            "category":"Banks & Credit Unions",
            "subcategory":"Bank",
            "type":"Services"
        }
    ],
    "sg:phone":"+39 0431 520646",
    "wof:name":"Banca Popolare Friuladria",
    "wof:placetype":"venue"
},
  "geometry": {"coordinates":[12.994367,45.776878],"type":"Point"}
}