{
  "type": "Feature",
  "properties": {
    "addr:full":"239 Viale Casiraghi Fratelli, 20099 Sesto San Giovanni Sesto San Giovanni Milano 20099",
    "addr:postcode":"20099;20099",
    "addr:street":"Viale Casiraghi",
    "iso:country":"IT",
    "sg:address":"239 Viale Casiraghi Fratelli, 20099 Sesto San Giovanni",
    "sg:city":"Sesto San Giovanni",
    "sg:classifiers":[
        {
            "category":"Banks & Credit Unions",
            "subcategory":"Financial Services",
            "type":"Services"
        }
    ],
    "sg:phone":"+39 02 2622 0679",
    "sg:postcode":"20099",
    "sg:province":"Milano",
    "sg:tags":[
        "banking",
        "finance",
        "insurance"
    ],
    "wof:name":"Ticino Costruzioni Srl",
    "wof:placetype":"venue"
},
  "geometry": {"coordinates":[9.2346868515,45.5431022644],"type":"Point"}
}