{
  "type": "Feature",
  "properties": {
    "iso:country":"IT",
    "sg:address":"Via Pegrosse 421b 37020 Volargne",
    "sg:city":"Volargne",
    "sg:classifiers":[
        {
            "category":"Home & Garden",
            "subcategory":"Building Materials",
            "type":"Retail Goods"
        }
    ],
    "sg:phone":"+39 045 686 0933",
    "sg:postcode":"37020",
    "sg:province":"Verona",
    "sg:tags":[
        "slab",
        "marble"
    ],
    "sg:website":"www.marmitravertini.com",
    "wof:name":"Marmi E Travertini Srl",
    "wof:placetype":"venue"
},
  "geometry": {"coordinates":[10.813169,45.531517],"type":"Point"}
}