{
  "type": "Feature",
  "properties": {
    "iso:country":"IT",
    "sg:address":"50, Via Andreas Hofer 39031 Brunico",
    "sg:city":"Brunico",
    "sg:classifiers":[
        {
            "category":"Wholesale",
            "subcategory":"Machinery & Supplies",
            "type":"Manufacturing & Wholesale Goods"
        }
    ],
    "sg:phone":"+39 0474 554140",
    "sg:postcode":"39031",
    "sg:province":"Bolzano/Bozen",
    "sg:tags":[
        "equipment",
        "-",
        "instrument",
        "measurement"
    ],
    "wof:name":"Modultronic (s.r.l.)",
    "wof:placetype":"venue"
},
  "geometry": {"coordinates":[11.938428,46.798985],"type":"Point"}
}