{
  "type": "Feature",
  "properties": {
    "addr:full":"1, Via Della Chimica 28924 Verbania Verbania Verbano-Cusio-Ossola 28924",
    "addr:postcode":"28924;28924",
    "addr:street":"Via Della Chimica",
    "iso:country":"IT",
    "sg:address":"1, Via Della Chimica 28924 Verbania",
    "sg:city":"Verbania",
    "sg:classifiers":[
        {
            "category":"Manufacturing",
            "subcategory":"Rubber & Plastics",
            "type":"Manufacturing & Wholesale Goods"
        }
    ],
    "sg:phone":"+39 0323 586973",
    "sg:postcode":"28924",
    "sg:province":"Verbano-Cusio-Ossola",
    "wof:name":"Nuova F.lli Cane (s.r.l.)",
    "wof:placetype":"venue"
},
  "geometry": {"coordinates":[8.455496788,45.9318809509],"type":"Point"}
}