{
  "type": "Feature",
  "properties": {
    "addr:full":"83, Via Macrelli Edgardo 47023 Cesena Cesena Forl\u00ec-Cesena 47023",
    "addr:postcode":"47023;47023",
    "addr:street":"Via Macrelli Edgardo",
    "iso:country":"IT",
    "sg:address":"83, Via Macrelli Edgardo 47023 Cesena",
    "sg:city":"Cesena",
    "sg:classifiers":[
        {
            "category":"Food & Beverages",
            "subcategory":"Groceries & Convenience Stores",
            "type":"Retail Goods"
        }
    ],
    "sg:phone":"+39 0547 610642",
    "sg:postcode":"47023",
    "sg:province":"Forl\u00ec-Cesena",
    "sg:tags":[
        "product",
        "related"
    ],
    "wof:name":"Bejo Italia (s.r.l.)",
    "wof:placetype":"venue"
},
  "geometry": {"coordinates":[11.9804611206,43.9947662354],"type":"Point"}
}