{
  "type": "Feature",
  "properties": {
    "iso:country":"IT",
    "sg:address":"16124 Genova",
    "sg:city":"Genova",
    "sg:orig_category":"Petroli, Gas E Combustibili",
    "sg:phone":"+39 010 251 4279",
    "sg:postcode":"16124",
    "sg:province":"Genova",
    "wof:name":"Deutra Spa",
    "wof:placetype":"venue"
},
  "geometry": {"coordinates":[8.9345722198,44.4116592407],"type":"Point"}
}