{
  "type": "Feature",
  "properties": {
    "iso:country":"IT",
    "sg:address":"00055 Ladispoli",
    "sg:city":"Ladispoli",
    "sg:orig_category":"Servizi Per Lo Sport E Il Tempo Libero. Alberghi E Strutture Extra Alberghiere",
    "sg:phone":"+39 06 994 6045",
    "sg:postcode":"00055",
    "sg:province":"Roma",
    "wof:name":"Miramare 85 S.a.s.",
    "wof:placetype":"venue"
},
  "geometry": {"coordinates":[12.517396,41.904385],"type":"Point"}
}