{
  "type": "Feature",
  "properties": {
    "addr:full":"31033 Castelfranco Veneto Castelfranco Veneto Treviso 31033",
    "addr:postcode":"31033;31033",
    "iso:country":"IT",
    "sg:address":"31033 Castelfranco Veneto",
    "sg:city":"Castelfranco Veneto",
    "sg:classifiers":[
        {
            "category":"Health Services",
            "subcategory":"Health Practitioner",
            "type":"Services"
        }
    ],
    "sg:phone":"+39 0423 722126",
    "sg:postcode":"31033",
    "sg:province":"Treviso",
    "sg:tags":[
        "medici"
    ],
    "wof:name":"Di Vincenzo Dr. Antonio",
    "wof:placetype":"venue"
},
  "geometry": {"coordinates":[11.936238,45.669506],"type":"Point"}
}