{
  "type": "Feature",
  "properties": {
    "addr:full":"52100 Arezzo Arezzo Arezzo 52100",
    "addr:postcode":"52100;52100",
    "iso:country":"IT",
    "sg:address":"52100 Arezzo",
    "sg:city":"Arezzo",
    "sg:orig_category":"Antenne Radio-televisione",
    "sg:phone":"+39 0575 357849",
    "sg:postcode":"52100",
    "sg:province":"Arezzo",
    "wof:name":"I.f.el. Srl",
    "wof:placetype":"venue"
},
  "geometry": {"coordinates":[11.871545,43.471352],"type":"Point"}
}