{
  "type": "Feature",
  "properties": {
    "iso:country":"IT",
    "sg:address":"10133 Torino",
    "sg:city":"Torino",
    "sg:orig_category":"Prodotti Chimici Di Base",
    "sg:phone":"+39 011 660 6192",
    "sg:postcode":"10133",
    "sg:province":"Torino",
    "wof:name":"Retel Chemiel",
    "wof:placetype":"venue"
},
  "geometry": {"coordinates":[7.6940608025,45.0571060181],"type":"Point"}
}