{
  "type": "Feature",
  "properties": {
    "iso:country":"IT",
    "sg:address":"53018 Sovicille",
    "sg:city":"Sovicille",
    "sg:orig_category":"Specchi",
    "sg:phone":"+39 0577 314479",
    "sg:postcode":"53018",
    "sg:province":"Siena",
    "wof:name":"Antique Mirror Srl",
    "wof:placetype":"venue"
},
  "geometry": {"coordinates":[11.229711,43.256908],"type":"Point"}
}