{
  "type": "Feature",
  "properties": {
    "iso:country":"IT",
    "sg:address":"10034 Chivasso",
    "sg:city":"Chivasso",
    "sg:orig_category":"Automobili E Mezzi Di Trasporto",
    "sg:phone":"+39 011 917 7111",
    "sg:postcode":"10034",
    "sg:province":"Torino",
    "wof:name":"N. Technology S.p.a.",
    "wof:placetype":"venue"
},
  "geometry": {"coordinates":[7.938676,45.229736],"type":"Point"}
}