{
  "type": "Feature",
  "properties": {
    "iso:country":"IT",
    "sg:address":"20131 Milano",
    "sg:city":"Milano",
    "sg:orig_category":"Forniture Per Abbigliamento E Pelletterie",
    "sg:phone":"+39 02 7060 0315",
    "sg:postcode":"20131",
    "sg:province":"Milano",
    "wof:name":"Fodermoda Di Frontini Cinzia",
    "wof:placetype":"venue"
},
  "geometry": {"coordinates":[9.2299280167,45.4857254028],"type":"Point"}
}