{
  "type": "Feature",
  "properties": {
    "addr:full":"80141 Napoli Napoli Napoli 80141",
    "addr:housenumber":"80141",
    "addr:postcode":"80141",
    "iso:country":"IT",
    "sg:address":"80141 Napoli",
    "sg:city":"Napoli",
    "sg:orig_category":"Servizi Al Turismo. Trasporto Pubblico E Privato",
    "sg:phone":"+39 081 751 4377",
    "sg:postcode":"80141",
    "sg:province":"Napoli",
    "sg:website":"http://www.alifana.it",
    "wof:name":"Gestione Governativa Alifana E Benevento",
    "wof:placetype":"venue"
},
  "geometry": {"coordinates":[14.195582,40.908585],"type":"Point"}
}