{
  "type": "Feature",
  "properties": {
    "addr:full":"30/b, V. Massafra 74015 Martina Franca Martina Franca Taranto 74015",
    "addr:housenumber":"30 / b v.",
    "addr:postcode":"74015;74015",
    "iso:country":"IT",
    "sg:address":"30/b, V. Massafra 74015 Martina Franca",
    "sg:city":"Martina Franca",
    "sg:classifiers":[
        {
            "category":"Shopping",
            "subcategory":"Clothing, Apparel, & Fashions",
            "type":"Retail Goods"
        }
    ],
    "sg:phone":"+39 080 483 9393",
    "sg:postcode":"74015",
    "sg:province":"Taranto",
    "sg:tags":[
        "clothes"
    ],
    "sg:website":"http://www.confpetrelli.it:ws_end: :mark:ws:http://www.paginegialle.it/petrelli",
    "wof:name":"Petrelli Srl",
    "wof:placetype":"venue"
},
  "geometry": {"coordinates":[17.240009,40.469238],"type":"Point"}
}