{
  "type": "Feature",
  "properties": {
    "iso:country":"IT",
    "sg:address":"30, Strada Falletti 14100 Asti",
    "sg:city":"Asti",
    "sg:classifiers":[
        {
            "category":"Manufacturing",
            "subcategory":"Glass & Minerals",
            "type":"Manufacturing & Wholesale Goods"
        }
    ],
    "sg:phone":"+39 0141 590211",
    "sg:postcode":"14100",
    "sg:province":"Asti",
    "wof:name":"R.b. Glass S.r.l.",
    "wof:placetype":"venue"
},
  "geometry": {"coordinates":[8.188207,44.900757],"type":"Point"}
}