{
  "type": "Feature",
  "properties": {
    "addr:full":"Via Delle Industrie 9 31040 Mansue' Treviso 31040",
    "addr:housenumber":"9",
    "addr:postcode":"31040;31040",
    "addr:street":"Via Delle Industrie",
    "iso:country":"IT",
    "sg:address":"Via Delle Industrie 9 31040 Mansue'",
    "sg:classifiers":[
        {
            "category":"Home & Garden",
            "subcategory":"Furniture",
            "type":"Retail Goods"
        }
    ],
    "sg:phone":"+39 0422 801082",
    "sg:postcode":"31040",
    "sg:province":"Treviso",
    "sg:tags":[
        "system"
    ],
    "wof:name":"Emme.gi Srl",
    "wof:placetype":"venue"
},
  "geometry": {"coordinates":[12.529077,45.812347],"type":"Point"}
}