{
  "type": "Feature",
  "properties": {
    "iso:country":"IT",
    "sg:address":"73050 Secl\u00ec",
    "sg:orig_category":"Prefabbricati Edilizia",
    "sg:phone":"+39 0836 550022",
    "sg:postcode":"73050",
    "sg:province":"Lecce",
    "wof:name":"Fazio Cataldo",
    "wof:placetype":"venue"
},
  "geometry": {"coordinates":[18.0985870361,40.1306686401],"type":"Point"}
}