{
  "type": "Feature",
  "properties": {
    "iso:country":"IT",
    "sg:address":"7, Viale Kennedy 65010 Moscufo",
    "sg:city":"Moscufo",
    "sg:classifiers":[
        {
            "category":"Shopping",
            "subcategory":"Clothing, Apparel, & Fashions",
            "type":"Retail Goods"
        }
    ],
    "sg:phone":"+39 39085975242",
    "sg:postcode":"65010",
    "sg:province":"Pescara",
    "sg:tags":[
        "clothes"
    ],
    "wof:name":"Artide Laboratorio Pellicceria",
    "wof:placetype":"venue"
},
  "geometry": {"coordinates":[14.214094,42.464825],"type":"Point"}
}