{
  "type": "Feature",
  "properties": {
    "iso:country":"IT",
    "sg:address":"09018 Sarroch",
    "sg:city":"Sarroch",
    "sg:orig_category":"Studi E Consulenze Tecniche E Industriali. Consulenze Tecniche, Amministrative E Perizie",
    "sg:phone":"+39 070 902036",
    "sg:postcode":"09018",
    "sg:province":"Cagliari",
    "wof:name":"R.p. Sarda Srl",
    "wof:placetype":"venue"
},
  "geometry": {"coordinates":[9.009916,39.067371],"type":"Point"}
}