{
  "type": "Feature",
  "properties": {
    "iso:country":"IT",
    "sg:address":"10095 Grugliasco",
    "sg:city":"Grugliasco",
    "sg:orig_category":"Utensili Meccanici E Materiali",
    "sg:phone":"+39 011 408 3511",
    "sg:postcode":"10095",
    "sg:province":"Torino",
    "sg:website":"http://www.mo-ma.net",
    "wof:name":"Moma Srl",
    "wof:placetype":"venue"
},
  "geometry": {"coordinates":[7.584477,45.058224],"type":"Point"}
}