{
  "type": "Feature",
  "properties": {
    "iso:country":"IT",
    "sg:address":"20093 Cologno Monzese",
    "sg:city":"Cologno Monzese",
    "sg:orig_category":"Elettrotecnica Industriale, Prodotti E Apparecchiature",
    "sg:phone":"+39 02 2539 6169",
    "sg:postcode":"20093",
    "sg:province":"Milano",
    "wof:name":"Livsa Snc Di Sampietro M. E C.",
    "wof:placetype":"venue"
},
  "geometry": {"coordinates":[9.266791,45.520245],"type":"Point"}
}