{
  "type": "Feature",
  "properties": {
    "iso:country":"IT",
    "sg:address":"45, Strada Bressana Salice 27050 Codevilla",
    "sg:city":"Codevilla",
    "sg:classifiers":[
        {
            "category":"Sports & Exercise",
            "subcategory":"Playing Field",
            "type":"Entertainment"
        }
    ],
    "sg:phone":"+39 39038347372",
    "sg:postcode":"27050",
    "sg:province":"Pavia",
    "sg:tags":[
        "game"
    ],
    "wof:name":"Borghetti Grondaie S.n.c. Di Borghetti Luciano E C.",
    "wof:placetype":"venue"
},
  "geometry": {"coordinates":[9.034039,44.953518],"type":"Point"}
}