{
  "type": "Feature",
  "properties": {
    "iso:country":"IT",
    "sg:address":"Viale Industria 14/a 37030 Colognola Ai Colli",
    "sg:city":"Colognola ai Colli",
    "sg:classifiers":[
        {
            "category":"Manufacturing",
            "subcategory":"Wood Products",
            "type":"Manufacturing & Wholesale Goods"
        }
    ],
    "sg:phone":"+39 045 615 1250",
    "sg:postcode":"37030",
    "sg:province":"Verona",
    "sg:tags":[
        "gate",
        "made",
        "door"
    ],
    "sg:website":"www.albertini.it",
    "wof:name":"Albertini Spa",
    "wof:placetype":"venue"
},
  "geometry": {"coordinates":[10.991748,45.438366],"type":"Point"}
}