{
  "type": "Feature",
  "properties": {
    "iso:country":"IT",
    "sg:address":"37042 Caldiero",
    "sg:city":"Caldiero",
    "sg:orig_category":"Elettronica Professionale E Di Consumo. Musica. Forniture Per Congressi, Fiere E Manifestazioni",
    "sg:phone":"+39 045 615 1106",
    "sg:postcode":"37042",
    "sg:province":"Verona",
    "sg:website":"http://www.star-light.it",
    "wof:name":"Start Light Snc",
    "wof:placetype":"venue"
},
  "geometry": {"coordinates":[11.169472,45.415722],"type":"Point"}
}