{
  "type": "Feature",
  "properties": {
    "addr:full":"16010 Savignone Savignone Genova 16010",
    "addr:postcode":"16010;16010",
    "iso:country":"IT",
    "sg:address":"16010 Savignone",
    "sg:city":"Savignone",
    "sg:orig_category":"Carta E Cartone - Produzione E Commercio",
    "sg:phone":"+39 010 936 0055",
    "sg:postcode":"16010",
    "sg:province":"Genova",
    "wof:name":"Alicart Di Radole Roberto & C. Sas",
    "wof:placetype":"venue"
},
  "geometry": {"coordinates":[8.927384,44.538792],"type":"Point"}
}