{
  "type": "Feature",
  "properties": {
    "iso:country":"IT",
    "sg:address":"184, Via Veneto 25069 Villa Carcina",
    "sg:city":"Carcina",
    "sg:classifiers":[
        {
            "category":"Shopping",
            "type":"Retail Goods"
        }
    ],
    "sg:phone":"+39 030 898 0715",
    "sg:postcode":"25069",
    "sg:province":"Brescia",
    "sg:tags":[
        "finished",
        "-",
        "metallic"
    ],
    "wof:name":"O.m.f.a. Dei Fratelli Assisi Raul & Gianfranco (s.n.c.)",
    "wof:placetype":"venue"
},
  "geometry": {"coordinates":[10.2249917984,45.6031455994],"type":"Point"}
}