{
  "type": "Feature",
  "properties": {
    "iso:country":"IT",
    "sg:address":"1, Via Alessandro Volta 20010 San Giorgio Su Legnano",
    "sg:city":"San Giorgio su Legnano",
    "sg:classifiers":[
        {
            "category":"Professional",
            "subcategory":"Engineering",
            "type":"Services"
        }
    ],
    "sg:phone":"+39 0331 411373",
    "sg:postcode":"20010",
    "sg:province":"Milano",
    "sg:tags":[
        "machine",
        "-",
        "mechanical"
    ],
    "wof:name":"L'artigiana S.r.l.",
    "wof:placetype":"venue"
},
  "geometry": {"coordinates":[8.901023,45.566334],"type":"Point"}
}