{
  "type": "Feature",
  "properties": {
    "iso:country":"IT",
    "sg:address":"37051 Bovolone",
    "sg:city":"Bovolone",
    "sg:orig_category":"Servizi E Lavori Per Arredamento E Industria Del Legno",
    "sg:phone":"+39 045 710 0606",
    "sg:postcode":"37051",
    "sg:province":"Verona",
    "wof:name":"Cantiero Roberto",
    "wof:placetype":"venue"
},
  "geometry": {"coordinates":[10.879059,45.348122],"type":"Point"}
}