{
  "type": "Feature",
  "properties": {
    "iso:country":"IT",
    "sg:address":"Via Repubblioca 4 40013 Castel Maggiore",
    "sg:city":"Castel Maggiore",
    "sg:classifiers":[
        {
            "category":"Manufacturing",
            "subcategory":"Glass & Minerals",
            "type":"Manufacturing & Wholesale Goods"
        }
    ],
    "sg:phone":"+39 051 712276",
    "sg:postcode":"40013",
    "sg:province":"Bologna",
    "sg:tags":[
        "decorative",
        "artistic"
    ],
    "sg:website":"www.avavetreria.it",
    "wof:name":"Ava Di Forni Marco & C. Snc",
    "wof:placetype":"venue"
},
  "geometry": {"coordinates":[11.359949,44.574799],"type":"Point"}
}