{
  "type": "Feature",
  "properties": {
    "addr:full":"2, Via Venezia 44021 Codigoro Codigoro Ferrara 44021",
    "addr:postcode":"44021;44021",
    "addr:street":"Via Venezia",
    "iso:country":"IT",
    "sg:address":"2, Via Venezia 44021 Codigoro",
    "sg:city":"Codigoro",
    "sg:classifiers":[
        {
            "category":"Manufacturing",
            "subcategory":"Glass & Minerals",
            "type":"Manufacturing & Wholesale Goods"
        }
    ],
    "sg:phone":"+39 0533 711284",
    "sg:postcode":"44021",
    "sg:province":"Ferrara",
    "wof:name":"P.b.f. S.n.c.",
    "wof:placetype":"venue"
},
  "geometry": {"coordinates":[12.15301,44.837883],"type":"Point"}
}