{
  "type": "Feature",
  "properties": {
    "iso:country":"IT",
    "sg:address":"89128 Reggio Calabria",
    "sg:classifiers":[
        {
            "category":"Shopping",
            "subcategory":"Bicycles & Sporting Goods",
            "type":"Retail Goods"
        }
    ],
    "sg:phone":"+39 0965 641210",
    "sg:province":"RC",
    "sg:tags":[
        "tempo",
        "lo",
        "-",
        "libero",
        "per",
        "servizi",
        "forniture",
        "articoli",
        "e",
        "sport",
        "il"
    ],
    "wof:name":"Centro Interregionale Paracadutismo Sportivo Falchi Dello Stretto",
    "wof:placetype":"venue"
},
  "geometry": {"coordinates":[15.657382,38.101734],"type":"Point"}
}