{
  "type": "Feature",
  "properties": {
    "iso:country":"IT",
    "sg:address":"24060 Castelli Calepio",
    "sg:city":"Castelli Calepio",
    "sg:orig_category":"Forniture Per Attivita' Industriali",
    "sg:phone":"+39 035 442 5216",
    "sg:postcode":"24060",
    "sg:province":"Bergamo",
    "wof:name":"G.t.f. (s.r.l.)",
    "wof:placetype":"venue"
},
  "geometry": {"coordinates":[9.8899641037,45.6365280151],"type":"Point"}
}