{
  "type": "Feature",
  "properties": {
    "iso:country":"IT",
    "sg:address":"353, Via Delle Repubbliche Marinare 80146 Napoli",
    "sg:city":"Napoli",
    "sg:classifiers":[
        {
            "category":"Autos & Motor Vehicles",
            "subcategory":"Automobile Sales",
            "type":"Retail Goods"
        }
    ],
    "sg:phone":"+39 081 572 1718",
    "sg:postcode":"80146",
    "sg:province":"Napoli",
    "sg:tags":[
        "motor-cars"
    ],
    "wof:name":"Pluricar Europe Di Triassi Giuseppe",
    "wof:placetype":"venue"
},
  "geometry": {"coordinates":[14.2901544571,40.9243583679],"type":"Point"}
}