{
  "type": "Feature",
  "properties": {
    "addr:full":"15033 Casale Monferrato Casale Monferrato Alessandria 15033",
    "addr:postcode":"15033;15033",
    "iso:country":"IT",
    "sg:address":"15033 Casale Monferrato",
    "sg:city":"Casale Monferrato",
    "sg:orig_category":"Cartotecnica E Servizi. Composizione, Stampa E Confezione. Servizi E Lavori Industria Delle Materie Plastiche. Servizi Per Imballaggio E Confezionamento",
    "sg:phone":"+39 0142 454714",
    "sg:postcode":"15033",
    "sg:province":"Alessandria",
    "wof:name":"Come Industrie S.p.a.",
    "wof:placetype":"venue"
},
  "geometry": {"coordinates":[8.450464,45.135792],"type":"Point"}
}