{
  "type": "Feature",
  "properties": {
    "iso:country":"IT",
    "sg:address":"36075 Montecchio Maggiore",
    "sg:city":"Montecchio Maggiore",
    "sg:orig_category":"Motori Ed Organi Di Trasmissione",
    "sg:phone":"+39 0444 499234",
    "sg:postcode":"36075",
    "sg:province":"Vicenza",
    "sg:website":"http://www.rancan.com",
    "wof:name":"Rancan Srl",
    "wof:placetype":"venue"
},
  "geometry": {"coordinates":[11.451921463,45.5239372253],"type":"Point"}
}