{
  "type": "Feature",
  "properties": {
    "addr:full":"20132 Milano Milano Milano 20132",
    "addr:postcode":"20132;20132",
    "iso:country":"IT",
    "sg:address":"20132 Milano",
    "sg:city":"Milano",
    "sg:orig_category":"Impianti, Attrezzature E Forniture Sanitarie Ed Ospedaliere. Macchine, Strumenti Ed Apparecchi Per Attivita' Industriali",
    "sg:phone":"+39 02 284 0933",
    "sg:postcode":"20132",
    "sg:province":"Milano",
    "wof:name":"Microcontrol N.t.",
    "wof:placetype":"venue"
},
  "geometry": {"coordinates":[9.237513,45.500286],"type":"Point"}
}