{
  "type": "Feature",
  "properties": {
    "iso:country":"IT",
    "sg:address":"12025 Dronero",
    "sg:city":"Dronero",
    "sg:orig_category":"Macchine, Impianti Ed Attrezzature Per Industria Alimentare E Bevande",
    "sg:phone":"+39 0171 905242",
    "sg:postcode":"12025",
    "sg:province":"Cuneo",
    "wof:name":"Demaria Mario Giacomo",
    "wof:placetype":"venue"
},
  "geometry": {"coordinates":[7.382198,44.455803],"type":"Point"}
}