{
  "type": "Feature",
  "properties": {
    "iso:country":"IT",
    "sg:address":"Contrada Olivola 82100 Benevento",
    "sg:city":"Benevento",
    "sg:classifiers":[
        {
            "category":"Real Estate",
            "subcategory":"Architect",
            "type":"Services"
        }
    ],
    "sg:phone":"+39 0824 776655",
    "sg:postcode":"82100",
    "sg:province":"Benevento",
    "sg:tags":[
        "textile",
        "clothing"
    ],
    "wof:name":"Miky Blue Srl",
    "wof:placetype":"venue"
},
  "geometry": {"coordinates":[14.742126,41.178432],"type":"Point"}
}