{
  "type": "Feature",
  "properties": {
    "iso:country":"IT",
    "sg:address":"35020 Correzzola",
    "sg:city":"Correzzola",
    "sg:orig_category":"Servizi E Lavori Per Agricoltura E Zootecnia",
    "sg:phone":"+39 049 580 7299",
    "sg:postcode":"35020",
    "sg:province":"Padova",
    "wof:name":"Barbetta Onorio E Figli S.n.c.",
    "wof:placetype":"venue"
},
  "geometry": {"coordinates":[11.98443,45.216476],"type":"Point"}
}