{
  "type": "Feature",
  "properties": {
    "addr:full":"3, Via S. Giuseppe Loc.s.antonino 24060 Montello Montello Bergamo 24060",
    "addr:postcode":"24060;24060",
    "addr:street":"Via S. Giuseppe Loc.S.Antonino",
    "iso:country":"IT",
    "sg:address":"3, Via S. Giuseppe Loc.s.antonino 24060 Montello",
    "sg:city":"Montello",
    "sg:classifiers":[
        {
            "category":"Professional",
            "subcategory":"Printing & Photocopies",
            "type":"Services"
        }
    ],
    "sg:phone":"+39 39035686801",
    "sg:postcode":"24060",
    "sg:province":"Bergamo",
    "wof:name":"Litocartotecnica Zama (s.r.l.)",
    "wof:placetype":"venue"
},
  "geometry": {"coordinates":[9.6699523926,45.6949043274],"type":"Point"}
}