{
  "type": "Feature",
  "properties": {
    "addr:full":"91026 Mazara Del Vallo Mazara del Vallo Trapani 91026",
    "addr:postcode":"91026;91026",
    "iso:country":"IT",
    "sg:address":"91026 Mazara Del Vallo",
    "sg:city":"Mazara del Vallo",
    "sg:classifiers":[
        {
            "category":"Manufacturing",
            "subcategory":"Metals",
            "type":"Manufacturing & Wholesale Goods"
        }
    ],
    "sg:phone":"+39 0923 944308",
    "sg:postcode":"91026",
    "sg:province":"Trapani",
    "sg:tags":[
        "ferro"
    ],
    "wof:name":"Sicilferro Di Valfre' Luciano Fabio",
    "wof:placetype":"venue"
},
  "geometry": {"coordinates":[12.5852098465,37.6533470154],"type":"Point"}
}