{
  "type": "Feature",
  "properties": {
    "iso:country":"IT",
    "sg:address":"29100 Piacenza",
    "sg:city":"Piacenza",
    "sg:orig_category":"Forniture Industriali Per Prevenzione, Controllo E Sicurezza",
    "sg:phone":"+39 0523 576000",
    "sg:postcode":"29100",
    "sg:province":"Piacenza",
    "wof:name":"Protex Srl",
    "wof:placetype":"venue"
},
  "geometry": {"coordinates":[9.7673749924,45.050365448],"type":"Point"}
}