{
  "type": "Feature",
  "properties": {
    "iso:country":"IT",
    "sg:address":"00153 Roma",
    "sg:city":"Roma",
    "sg:orig_category":"Cartolerie",
    "sg:phone":"+39 06 5831 0021",
    "sg:postcode":"00153",
    "sg:province":"Roma",
    "wof:name":"Fiammeri E' Dal 1860",
    "wof:placetype":"venue"
},
  "geometry": {"coordinates":[12.45522,41.871948],"type":"Point"}
}