{
  "type": "Feature",
  "properties": {
    "addr:full":"12022 Busca Busca Cuneo 12022",
    "addr:postcode":"12022;12022",
    "iso:country":"IT",
    "sg:address":"12022 Busca",
    "sg:city":"Busca",
    "sg:orig_category":"Prodotti Chimici Di Base",
    "sg:phone":"+39 0171 944722",
    "sg:postcode":"12022",
    "sg:province":"Cuneo",
    "sg:website":"http://www.gemchimica.com",
    "wof:name":"Gem Chimica Di Cerutti Graziano & C. Snc",
    "wof:placetype":"venue"
},
  "geometry": {"coordinates":[7.4780750275,44.4868659973],"type":"Point"}
}