{
  "type": "Feature",
  "properties": {
    "iso:country":"IT",
    "sg:address":"10025 Pino Torinese",
    "sg:city":"Pino Torinese",
    "sg:orig_category":"Impianti Sportivi E Ricreativi - Esercizio",
    "sg:phone":"+39 011 811 1012",
    "sg:postcode":"10025",
    "sg:province":"Torino",
    "wof:name":"Centro Fitness Pino Torinese - Piscina Moby Dick",
    "wof:placetype":"venue"
},
  "geometry": {"coordinates":[7.787047,45.041931],"type":"Point"}
}