{
  "type": "Feature",
  "properties": {
    "iso:country":"IT",
    "sg:address":"1, Via Dell' Artigianato 36070 Trissino",
    "sg:city":"Trissino",
    "sg:classifiers":[
        {
            "category":"Shopping",
            "subcategory":"Stationery & Office Supplies",
            "type":"Retail Goods"
        }
    ],
    "sg:phone":"+39 0445 490777",
    "sg:postcode":"36070",
    "sg:province":"Vicenza",
    "sg:tags":[
        "professional"
    ],
    "wof:name":"Lovato (s.r.l.)",
    "wof:placetype":"venue"
},
  "geometry": {"coordinates":[11.2569990158,45.5830345154],"type":"Point"}
}