{
  "type": "Feature",
  "properties": {
    "addr:full":"80069 Vico Equense Vico Equense Napoli 80069",
    "addr:postcode":"80069;80069",
    "addr:street":"Vico;Vico",
    "iso:country":"IT",
    "sg:address":"80069 Vico Equense",
    "sg:city":"Vico Equense",
    "sg:orig_category":"Prodotti Chimici Secondari. Macchine, Impianti Ed Attrezzature Industria Chimica. Servizi E Lavori Industria Chimica",
    "sg:phone":"+39 081 801 5808",
    "sg:postcode":"80069",
    "sg:province":"Napoli",
    "wof:name":"Sole Blu Centro Abbronzante",
    "wof:placetype":"venue"
},
  "geometry": {"coordinates":[14.4548616409,40.6432914734],"type":"Point"}
}