{
  "type": "Feature",
  "properties": {
    "iso:country":"IT",
    "sg:address":"33038 San Daniele Friuli",
    "sg:orig_category":"Cartotecnica E Servizi. Articoli Per Imballaggio E Confezionamento",
    "sg:phone":"+39 0432 941744",
    "sg:postcode":"33038",
    "sg:province":"Udine",
    "wof:name":"Cressa & C. Srl",
    "wof:placetype":"venue"
},
  "geometry": {"coordinates":[13.004009,46.149929],"type":"Point"}
}