{
  "type": "Feature",
  "properties": {
    "addr:full":"80017 Melito Di Napoli Melito di Napoli Napoli 80017",
    "addr:postcode":"80017;80017",
    "iso:country":"IT",
    "sg:address":"80017 Melito Di Napoli",
    "sg:city":"Melito di Napoli",
    "sg:orig_category":"Vetro: Prodotti E Lavorazioni",
    "sg:phone":"+39 081 711 4787",
    "sg:postcode":"80017",
    "sg:province":"Napoli",
    "sg:website":"http://www.vetritaranto.it",
    "wof:name":"Fratelli Taranto Di Ciro E Patrizia Snc",
    "wof:placetype":"venue"
},
  "geometry": {"coordinates":[14.24639,40.916115],"type":"Point"}
}