{
  "type": "Feature",
  "properties": {
    "iso:country":"IT",
    "sg:address":"16129 Genova",
    "sg:city":"Genova",
    "sg:classifiers":[
        {
            "category":"Health Services",
            "subcategory":"Health Practitioner",
            "type":"Services"
        }
    ],
    "sg:phone":"+39 010 311107",
    "sg:postcode":"16129",
    "sg:province":"Genova",
    "sg:tags":[
        "medici"
    ],
    "wof:name":"Bulgarelli Sergio",
    "wof:placetype":"venue"
},
  "geometry": {"coordinates":[8.954791,44.402756],"type":"Point"}
}