{
  "type": "Feature",
  "properties": {
    "iso:country":"IT",
    "sg:address":"35138 Padova",
    "sg:city":"Padova",
    "sg:orig_category":"Automazione E Macchine Per Ufficio. Forniture Industriali Per Prevenzione, Controllo E Sicurezza",
    "sg:phone":"+39 049 871 0214",
    "sg:postcode":"35138",
    "sg:province":"Padova",
    "wof:name":"Valenz Di Valmassoi Barbara",
    "wof:placetype":"venue"
},
  "geometry": {"coordinates":[11.876589,45.409569],"type":"Point"}
}