{
  "type": "Feature",
  "properties": {
    "iso:country":"IT",
    "sg:address":"25050 Rodengo Saiano",
    "sg:orig_category":"Macchine Utensili - Attrezzature E Accessori",
    "sg:phone":"+39 030 681 0841",
    "sg:postcode":"25050",
    "sg:province":"Brescia",
    "wof:name":"G.b.c. Transfer Srl",
    "wof:placetype":"venue"
},
  "geometry": {"coordinates":[10.121976,45.582039],"type":"Point"}
}