{
  "type": "Feature",
  "properties": {
    "addr:full":"30, Vl. Cassiodoro 20145 Milano Milano Milano 20145",
    "addr:housenumber":"30",
    "addr:postcode":"20145;20145",
    "addr:street":"Vl. Cassiodoro",
    "iso:country":"IT",
    "sg:address":"30, Vl. Cassiodoro 20145 Milano",
    "sg:city":"Milano",
    "sg:classifiers":[
        {
            "category":"Shopping",
            "subcategory":"Stationery & Office Supplies",
            "type":"Retail Goods"
        }
    ],
    "sg:phone":"+39 02 4800 7149",
    "sg:postcode":"20145",
    "sg:province":"Milano",
    "sg:tags":[
        "professional"
    ],
    "sg:website":"http://www.ilcentropier.it",
    "wof:name":"Il Centro Pier Srl",
    "wof:placetype":"venue"
},
  "geometry": {"coordinates":[9.1601858139,45.4767494202],"type":"Point"}
}