{
  "type": "Feature",
  "properties": {
    "iso:country":"IT",
    "sg:address":"1 Passaggio Dei Canonici Lateranensi, 24121 Bergamo",
    "sg:city":"Bergamo",
    "sg:classifiers":[
        {
            "category":"Banks & Credit Unions",
            "subcategory":"Financial Services",
            "type":"Services"
        }
    ],
    "sg:phone":"+39 39035232022",
    "sg:postcode":"24121",
    "sg:province":"Bergamo",
    "sg:tags":[
        "banking",
        "finance",
        "insurance"
    ],
    "wof:name":"Centax (spa)",
    "wof:placetype":"venue"
},
  "geometry": {"coordinates":[9.6758346558,45.6976623535],"type":"Point"}
}