{
  "type": "Feature",
  "properties": {
    "addr:full":"Via Delle Molina 52 51010 Veneri Pistoia 51010",
    "addr:housenumber":"52",
    "addr:postcode":"51010;51010",
    "addr:street":"Via Delle Molina",
    "iso:country":"IT",
    "sg:address":"Via Delle Molina 52 51010 Veneri",
    "sg:classifiers":[
        {
            "category":"Shopping",
            "subcategory":"Stationery & Office Supplies",
            "type":"Retail Goods"
        }
    ],
    "sg:phone":"+39 0572 429069",
    "sg:postcode":"51010",
    "sg:province":"Pistoia",
    "sg:tags":[
        "cardboard"
    ],
    "sg:website":"www.cartieramenegazzo.com",
    "wof:name":"Cartiera Menegazzo Srl",
    "wof:placetype":"venue"
},
  "geometry": {"coordinates":[10.918524,43.932156],"type":"Point"}
}