{
  "type": "Feature",
  "properties": {
    "iso:country":"IT",
    "sg:address":"20144 Milano",
    "sg:city":"Milano",
    "sg:orig_category":"Calzature, Pelletterie E Pelli",
    "sg:phone":"+39 02 4771 9347",
    "sg:postcode":"20144",
    "sg:province":"Milano",
    "sg:website":"http://www.lotusart.it",
    "wof:name":"Lotus Art Srl",
    "wof:placetype":"venue"
},
  "geometry": {"coordinates":[9.156555,45.455269],"type":"Point"}
}