{
  "type": "Feature",
  "properties": {
    "addr:full":"2/a, Via Socrate 22070 Casnate Con Bernate Casnate Como 22070",
    "addr:housenumber":"2 / a",
    "addr:postcode":"22070;22070",
    "addr:street":"Via Socrate;Con Bernate Casnate",
    "iso:country":"IT",
    "sg:address":"2/a, Via Socrate 22070 Casnate Con Bernate",
    "sg:city":"Casnate",
    "sg:classifiers":[
        {
            "category":"Banks & Credit Unions",
            "subcategory":"Investment Brokerage",
            "type":"Services"
        }
    ],
    "sg:phone":"+39 39031564105",
    "sg:postcode":"22070",
    "sg:province":"Como",
    "sg:tags":[
        "-",
        "transport",
        "related"
    ],
    "wof:name":"C.d. Transport (s.r.l.)",
    "wof:placetype":"venue"
},
  "geometry": {"coordinates":[9.082871,45.760681],"type":"Point"}
}