{
  "type": "Feature",
  "properties": {
    "iso:country":"IT",
    "sg:address":"Via Fermi 5 20070 San Zenone Al Lambro",
    "sg:city":"San Zenone al Lambro",
    "sg:classifiers":[
        {
            "category":"Banks & Credit Unions",
            "subcategory":"Investment Brokerage",
            "type":"Services"
        }
    ],
    "sg:phone":"+39 02 9887 0023",
    "sg:postcode":"20070",
    "sg:province":"Milano",
    "sg:tags":[
        "lift",
        "truck"
    ],
    "sg:website":"www.fimsasrl.com",
    "wof:name":"Fimsa Dei Fratelli Rando S.r.l.",
    "wof:placetype":"venue"
},
  "geometry": {"coordinates":[9.188141,45.463688],"type":"Point"}
}