{
  "type": "Feature",
  "properties": {
    "iso:country":"IT",
    "sg:address":"20021 Bollate",
    "sg:city":"Bollate",
    "sg:orig_category":"Metalli E Leghe",
    "sg:phone":"+39 02 3330 1271",
    "sg:postcode":"20021",
    "sg:province":"Milano",
    "wof:name":"Piattine E Profili Inox (s.r.l.)",
    "wof:placetype":"venue"
},
  "geometry": {"coordinates":[9.1152553558,45.5433425903],"type":"Point"}
}