{
  "type": "Feature",
  "properties": {
    "iso:country":"IT",
    "sg:address":"25017 Lonato",
    "sg:city":"Lonato",
    "sg:orig_category":"Impiantistica E Prodotti Tecnologici Per Edilizia. Climatizzazione E Condizionamento, Apparecchiature E Servizi",
    "sg:phone":"+39 030 991 3204",
    "sg:postcode":"25017",
    "sg:province":"Brescia",
    "wof:name":"Air Brescia Srl",
    "wof:placetype":"venue"
},
  "geometry": {"coordinates":[10.47431,45.463322],"type":"Point"}
}