{
  "type": "Feature",
  "properties": {
    "iso:country":"IT",
    "sg:address":"03013 Ferentino",
    "sg:city":"Ferentino",
    "sg:orig_category":"Dolciumi - Produzione",
    "sg:phone":"+39 0775 396004",
    "sg:postcode":"03013",
    "sg:province":"Frosinone",
    "wof:name":"Salvatori Luciana",
    "wof:placetype":"venue"
},
  "geometry": {"coordinates":[13.353971,41.639378],"type":"Point"}
}