{
  "type": "Feature",
  "properties": {
    "iso:country":"IT",
    "sg:address":"66026 Ortona",
    "sg:city":"Ortona",
    "sg:orig_category":"Servizi Ausiliari Di Certificati, Riproduzioni, Disegni E Foto",
    "sg:phone":"+39 085 906 8418",
    "sg:postcode":"66026",
    "sg:province":"Chieti",
    "wof:name":"Sea Horse Srl",
    "wof:placetype":"venue"
},
  "geometry": {"coordinates":[14.410772,42.357704],"type":"Point"}
}