{
  "type": "Feature",
  "properties": {
    "iso:country":"IT",
    "sg:address":"00159 Roma",
    "sg:city":"Roma",
    "sg:orig_category":"Servizi Al Turismo. Servizi Ausiliari Dei Mezzi Di Trasporto. Servizi Ausiliari Per Il Trasporto. Acqua, Luce, Gas E Societa' Di Esercizio Pubblico",
    "sg:phone":"+39 06 438 1870",
    "sg:postcode":"00159",
    "sg:province":"Roma",
    "wof:name":"C S F Cerasi Servizi E Forniture Di Cerasi Tommaso",
    "wof:placetype":"venue"
},
  "geometry": {"coordinates":[12.5486,41.904541],"type":"Point"}
}