{
  "type": "Feature",
  "properties": {
    "addr:full":"1, Localita' Vat 38079 Tione Di Trento Tione di Trento Trento 38079",
    "addr:postcode":"38079;38079",
    "addr:street":"Localita ' Vat",
    "iso:country":"IT",
    "sg:address":"1, Localita' Vat 38079 Tione Di Trento",
    "sg:city":"Tione di Trento",
    "sg:classifiers":[
        {
            "category":"Shopping",
            "type":"Retail Goods"
        }
    ],
    "sg:phone":"+39 0465 321134",
    "sg:postcode":"38079",
    "sg:province":"Trento",
    "sg:tags":[
        "finished",
        "-",
        "metallic"
    ],
    "wof:name":"Metal-fer Di Castellani Ottavio & C. S.n.c.",
    "wof:placetype":"venue"
},
  "geometry": {"coordinates":[11.119052887,46.0667381287],"type":"Point"}
}