{
  "type": "Feature",
  "properties": {
    "iso:country":"IT",
    "sg:address":"Via Corridori 52 20037 Paderno Dugnano",
    "sg:city":"Paderno Dugnano",
    "sg:classifiers":[
        {
            "category":"Science Facility",
            "type":"Public Place"
        }
    ],
    "sg:phone":"+39 02 9904 3377",
    "sg:postcode":"20037",
    "sg:province":"Milano",
    "sg:tags":[
        "equipment",
        "audio-visual",
        "appliance",
        "projector",
        "overhead"
    ],
    "sg:website":"www.kcm.it",
    "wof:name":"K.c.m. Srl",
    "wof:placetype":"venue"
},
  "geometry": {"coordinates":[9.228443,45.539288],"type":"Point"}
}