{
  "type": "Feature",
  "properties": {
    "addr:full":"28100 Novara Novara Novara 28100",
    "addr:postcode":"28100;28100",
    "iso:country":"IT",
    "sg:address":"28100 Novara",
    "sg:city":"Novara",
    "sg:orig_category":"Apparecchiature Ed Attrezzature Meccaniche. Elettronica Industriale, Prodotti E Apparecchiature",
    "sg:phone":"+39 0321 640927",
    "sg:postcode":"28100",
    "sg:province":"Novara",
    "wof:name":"Specialized Electronic Automation",
    "wof:placetype":"venue"
},
  "geometry": {"coordinates":[8.599689,45.447224],"type":"Point"}
}