{
  "type": "Feature",
  "properties": {
    "iso:country":"IT",
    "sg:address":"20149 Milano",
    "sg:city":"Milano",
    "sg:classifiers":[
        {
            "category":"Health Services",
            "subcategory":"Health Practitioner",
            "type":"Services"
        }
    ],
    "sg:phone":"+39 02 498 2061",
    "sg:postcode":"20149",
    "sg:province":"Milano",
    "sg:tags":[
        "medici"
    ],
    "wof:name":"Gori Gabriele Ezio Franca",
    "wof:placetype":"venue"
},
  "geometry": {"coordinates":[9.148244,45.479156],"type":"Point"}
}