{
  "type": "Feature",
  "properties": {
    "iso:country":"IT",
    "sg:address":"50053 Empoli",
    "sg:city":"Empoli",
    "sg:orig_category":"Abbigliamento Industria - Forniture Ed Accessori",
    "sg:phone":"+39 0571 592912",
    "sg:postcode":"50053",
    "sg:province":"Firenze",
    "wof:name":"Sagit - Bottonificio Fontanelli Srl",
    "wof:placetype":"venue"
},
  "geometry": {"coordinates":[10.959046,43.726288],"type":"Point"}
}