{
  "type": "Feature",
  "properties": {
    "iso:country":"IT",
    "sg:address":"20098 S. Giuliano Milanese",
    "sg:orig_category":"Medaglie E Distintivi - Produzione E Ingrosso",
    "sg:phone":"+39 02 9828 1040",
    "sg:postcode":"20098",
    "sg:province":"Milano",
    "wof:name":"Landi Pietro Snc",
    "wof:placetype":"venue"
},
  "geometry": {"coordinates":[9.263249,45.399715],"type":"Point"}
}