{
  "type": "Feature",
  "properties": {
    "addr:full":"20093 Cologno Monzese Cologno Monzese Milano 20093",
    "addr:postcode":"20093;20093",
    "iso:country":"IT",
    "sg:address":"20093 Cologno Monzese",
    "sg:city":"Cologno Monzese",
    "sg:orig_category":"Autonoleggio",
    "sg:phone":"+39 02 2730 0687",
    "sg:postcode":"20093",
    "sg:province":"Milano",
    "wof:name":"Autonoleggio Garavelli",
    "wof:placetype":"venue"
},
  "geometry": {"coordinates":[9.286893,45.522629],"type":"Point"}
}