{
  "type": "Feature",
  "properties": {
    "iso:country":"IT",
    "sg:address":"57031 Capoliveri",
    "sg:city":"Capoliveri",
    "sg:orig_category":"Sport - Articoli E Forniture",
    "sg:phone":"+39 0565 964175",
    "sg:postcode":"57031",
    "sg:province":"Livorno",
    "wof:name":"New Professional Diving Center Di Mossini Giuseppe & C. Sas",
    "wof:placetype":"venue"
},
  "geometry": {"coordinates":[10.312745,42.758636],"type":"Point"}
}