{
  "type": "Feature",
  "properties": {
    "addr:full":"50018 Scandicci Scandicci Firenze 50018",
    "addr:postcode":"50018;50018",
    "iso:country":"IT",
    "sg:address":"50018 Scandicci",
    "sg:city":"Scandicci",
    "sg:orig_category":"Forniture Per Abbigliamento E Pelletterie",
    "sg:phone":"+39 055 751680",
    "sg:postcode":"50018",
    "sg:province":"Firenze",
    "wof:name":"F.lli Andrei Snc",
    "wof:placetype":"venue"
},
  "geometry": {"coordinates":[11.1633758545,43.7633857727],"type":"Point"}
}