{
  "type": "Feature",
  "properties": {
    "iso:country":"IT",
    "sg:address":"Via Industriale 30 25065 Lumezzane",
    "sg:city":"Lumezzane",
    "sg:classifiers":[
        {
            "category":"Bus Stop",
            "subcategory":"None",
            "type":"Transportation"
        }
    ],
    "sg:phone":"+39 030 825 0011",
    "sg:postcode":"25065",
    "sg:province":"Brescia",
    "sg:tags":[
        "ball-type",
        "valve",
        "non-return"
    ],
    "sg:website":"www.rubinetteriebresciane.it",
    "wof:name":"Rubinetterie Bresciane Bonomi Spa",
    "wof:placetype":"venue"
},
  "geometry": {"coordinates":[10.257871,45.647728],"type":"Point"}
}