{
  "type": "Feature",
  "properties": {
    "iso:country":"IT",
    "sg:address":"00199 Roma",
    "sg:city":"Roma",
    "sg:orig_category":"Scuole E Servizi Scolastici. Servizi Per Lo Sport E Il Tempo Libero",
    "sg:phone":"+39 06 841 2368",
    "sg:postcode":"00199",
    "sg:province":"Roma",
    "wof:name":"C.i.a.c.",
    "wof:placetype":"venue"
},
  "geometry": {"coordinates":[12.505602,41.923386],"type":"Point"}
}