{
  "type": "Feature",
  "properties": {
    "iso:country":"IT",
    "sg:address":"10090 Rosta",
    "sg:city":"Rosta",
    "sg:orig_category":"Automobili E Mezzi Di Trasporto",
    "sg:phone":"+39 011 956 7781",
    "sg:postcode":"10090",
    "sg:province":"Torino",
    "sg:website":"http://www.fratellidauria.it",
    "wof:name":"Fratelli D'auria Sas",
    "wof:placetype":"venue"
},
  "geometry": {"coordinates":[7.476749,45.021515],"type":"Point"}
}