{
  "type": "Feature",
  "properties": {
    "iso:country":"IT",
    "sg:address":"04014 Pontinia",
    "sg:city":"Pontinia",
    "sg:classifiers":[
        {
            "category":"Wholesale",
            "subcategory":"Chemicals & Plastics",
            "type":"Manufacturing & Wholesale Goods"
        }
    ],
    "sg:phone":"+39 0773 840042",
    "sg:postcode":"04014",
    "sg:province":"Latina",
    "sg:tags":[
        "article",
        "product",
        "plastics"
    ],
    "wof:name":"F.g.s. Europe 98 Srl",
    "wof:placetype":"venue"
},
  "geometry": {"coordinates":[13.1476011276,41.4386024475],"type":"Point"}
}