{
  "type": "Feature",
  "properties": {
    "addr:full":"20090 Assago Assago Milano 20090",
    "addr:postcode":"20090;20090",
    "addr:street":"Assago",
    "iso:country":"IT",
    "sg:address":"20090 Assago",
    "sg:city":"Assago",
    "sg:orig_category":"Articoli Medico-sanitari Ed Ortopedici. Impianti, Attrezzature E Forniture Sanitarie Ed Ospedaliere",
    "sg:phone":"+39 02 457921",
    "sg:postcode":"20090",
    "sg:province":"Milano",
    "wof:name":"Co.me.sa. S.p.a.",
    "wof:placetype":"venue"
},
  "geometry": {"coordinates":[9.122619,45.404831],"type":"Point"}
}