{
  "type": "Feature",
  "properties": {
    "iso:country":"IT",
    "sg:address":"09131 Cagliari",
    "sg:city":"Cagliari",
    "sg:orig_category":"Non-classified Establishments",
    "sg:phone":"+39 070 490339",
    "sg:postcode":"09131",
    "sg:province":"Cagliari",
    "wof:name":"Ar.mo. Arredamenti Moderni Srl",
    "wof:placetype":"venue"
},
  "geometry": {"coordinates":[9.129769,39.229961],"type":"Point"}
}