{
  "type": "Feature",
  "properties": {
    "iso:country":"IT",
    "sg:address":"400, Corso Europa 10088 Volpiano",
    "sg:city":"Volpiano",
    "sg:classifiers":[
        {
            "category":"Parking",
            "subcategory":"Lot",
            "type":"Transportation"
        }
    ],
    "sg:phone":"+39 011 988 2347",
    "sg:postcode":"10088",
    "sg:province":"Torino",
    "sg:tags":[
        "transport",
        "road"
    ],
    "wof:name":"Actis Guido (s.r.l.)",
    "wof:placetype":"venue"
},
  "geometry": {"coordinates":[7.800697,45.167572],"type":"Point"}
}