{
  "type": "Feature",
  "properties": {
    "iso:country":"IT",
    "sg:address":"43100 Parma",
    "sg:city":"Parma",
    "sg:classifiers":[
        {
            "category":"Shopping",
            "subcategory":"Stationery & Office Supplies",
            "type":"Retail Goods"
        }
    ],
    "sg:phone":"+39 0521 941170",
    "sg:postcode":"43100",
    "sg:province":"Parma",
    "sg:tags":[
        "business",
        "gift",
        "finished",
        "products",
        "printed",
        "supplies"
    ],
    "sg:website":"http://www.publiroom.com",
    "wof:name":"Publiroom Snc",
    "wof:placetype":"venue"
},
  "geometry": {"coordinates":[10.3229598999,44.7756004333],"type":"Point"}
}