{
  "type": "Feature",
  "properties": {
    "addr:full":"50012 Vallina Vallina Firenze 50012",
    "addr:postcode":"50012;50012",
    "addr:street":"Vallina",
    "iso:country":"IT",
    "sg:address":"50012 Vallina",
    "sg:city":"Vallina",
    "sg:orig_category":"Macchine, Impianti Ed Attrezzature Per Industria Alimentare E Bevande. Apparecchiature E Sistemi Per Imballaggio E Confezionamento",
    "sg:phone":"+39 055 696133",
    "sg:postcode":"50012",
    "sg:province":"Firenze",
    "wof:name":"Gibo.matic Srl",
    "wof:placetype":"venue"
},
  "geometry": {"coordinates":[11.363759,43.778908],"type":"Point"}
}