{
  "type": "Feature",
  "properties": {
    "iso:country":"IT",
    "sg:address":"20155 Milano",
    "sg:city":"Milano",
    "sg:orig_category":"Bigiotteria - Produzione E Ingrosso",
    "sg:phone":"+39 02 3310 3552",
    "sg:postcode":"20155",
    "sg:province":"Milano",
    "wof:name":"Unika Srl",
    "wof:placetype":"venue"
},
  "geometry": {"coordinates":[9.164459,45.489086],"type":"Point"}
}