{
  "type": "Feature",
  "properties": {
    "iso:country":"IT",
    "sg:address":"20133 Milano",
    "sg:city":"Milano",
    "sg:orig_category":"Ospedali E Servizi Sanitari",
    "sg:phone":"+39 02 706471",
    "sg:postcode":"20133",
    "sg:province":"Milano",
    "wof:name":"Istituti Clinici Di Perfezionamento",
    "wof:placetype":"venue"
},
  "geometry": {"coordinates":[9.224308,45.474224],"type":"Point"}
}