{
  "type": "Feature",
  "properties": {
    "iso:country":"IT",
    "sg:address":"38100 Trento",
    "sg:city":"Trento",
    "sg:orig_category":"Impiantistica E Prodotti Tecnologici Per Edilizia. Telecomunicazioni E Telefonia, Impianti, Apparecchi E Servizi",
    "sg:phone":"+39 0461 429931",
    "sg:postcode":"38100",
    "sg:province":"Trento",
    "sg:website":"http://elettrosystem.it",
    "wof:name":"Elettrosystem Srl",
    "wof:placetype":"venue"
},
  "geometry": {"coordinates":[11.101145,46.072113],"type":"Point"}
}