{
  "type": "Feature",
  "properties": {
    "iso:country":"IT",
    "sg:address":"10051 Avigliana",
    "sg:city":"Avigliana",
    "sg:orig_category":"Non-classified Establishments",
    "sg:phone":"+39 011 931 3049",
    "sg:postcode":"10051",
    "sg:province":"Torino",
    "wof:name":"Mavit Sas Di Monticone & C.",
    "wof:placetype":"venue"
},
  "geometry": {"coordinates":[7.388011,45.087639],"type":"Point"}
}