{
  "type": "Feature",
  "properties": {
    "iso:country":"IT",
    "sg:address":"Via T C Marini 33, Darzo, 38080 Storo, Tn",
    "sg:classifiers":[
        {
            "category":"Banks & Credit Unions",
            "subcategory":"Bank",
            "type":"Services"
        }
    ],
    "sg:postcode":"38080",
    "sg:province":"Trento",
    "wof:name":"Cassa Rurale Di Darzo E Lodrone-banca Di Credito Cooperativo Scarl",
    "wof:placetype":"venue"
},
  "geometry": {"coordinates":[10.543214,45.835514],"type":"Point"}
}