{
  "type": "Feature",
  "properties": {
    "iso:country":"IT",
    "sg:address":"Via Parugiano Di Sotto ,152/166 59013 Montemurlo",
    "sg:city":"Montemurlo",
    "sg:classifiers":[
        {
            "category":"Manufacturing",
            "subcategory":"Textiles",
            "type":"Manufacturing & Wholesale Goods"
        }
    ],
    "sg:phone":"+39 0574 650922",
    "sg:postcode":"59013",
    "sg:province":"Prato",
    "sg:tags":[
        "used",
        "machines"
    ],
    "sg:website":"www.ui.prato.it/cormatex",
    "wof:name":"Cormatex Srl",
    "wof:placetype":"venue"
},
  "geometry": {"coordinates":[11.043993,43.909729],"type":"Point"}
}