{
  "type": "Feature",
  "properties": {
    "iso:country":"IT",
    "sg:address":"00184 Roma",
    "sg:city":"Roma",
    "sg:orig_category":"Canne Fumarie, Ciminiere E Camini",
    "sg:phone":"+39 06 488 2543",
    "sg:postcode":"00184",
    "sg:province":"Roma",
    "wof:name":"Fumisteria Romana",
    "wof:placetype":"venue"
},
  "geometry": {"coordinates":[12.598533,41.801476],"type":"Point"}
}