{
  "type": "Feature",
  "properties": {
    "iso:country":"IT",
    "sg:address":"20124 Milano",
    "sg:city":"Milano",
    "sg:orig_category":"Apparecchiature E Sistemi Per Magazzinaggio E Movimentazione",
    "sg:phone":"+39 02 6702 0184",
    "sg:postcode":"20124",
    "sg:province":"Milano",
    "wof:name":"Ci.bi. Spa",
    "wof:placetype":"venue"
},
  "geometry": {"coordinates":[9.212057,45.484203],"type":"Point"}
}