{
  "type": "Feature",
  "properties": {
    "iso:country":"IT",
    "sg:address":"03013 Ferentino",
    "sg:city":"Ferentino",
    "sg:orig_category":"Elettronica Industriale, Prodotti E Apparecchiature",
    "sg:phone":"+39 0775 223083",
    "sg:postcode":"03013",
    "sg:province":"Frosinone",
    "sg:website":"http://spazioweb.inwind.it/cibertec",
    "wof:name":"Cosman Srl",
    "wof:placetype":"venue"
},
  "geometry": {"coordinates":[13.243263,41.684708],"type":"Point"}
}