{
  "type": "Feature",
  "properties": {
    "iso:country":"IT",
    "sg:address":"28891 Cesara",
    "sg:city":"Cesara",
    "sg:orig_category":"Pulitura E Lucidatura Metalli",
    "sg:phone":"+39 0323 877252",
    "sg:postcode":"28891",
    "sg:province":"Verbano-Cusio-Ossola",
    "wof:name":"Motta Giuseppe",
    "wof:placetype":"venue"
},
  "geometry": {"coordinates":[8.2724647522,46.1399688721],"type":"Point"}
}