{
  "type": "Feature",
  "properties": {
    "addr:full":"57121 Campiglia Marittima Livorno 57121",
    "addr:postcode":"57121;57121",
    "iso:country":"IT",
    "sg:address":"57121 Campiglia Marittima",
    "sg:orig_category":"Estetiste",
    "sg:phone":"+39 0565 857186",
    "sg:postcode":"57121",
    "sg:province":"Livorno",
    "wof:name":"Artestetica Di Cagnani Maria",
    "wof:placetype":"venue"
},
  "geometry": {"coordinates":[10.605532,43.029053],"type":"Point"}
}