{
  "type": "Feature",
  "properties": {
    "addr:full":"42100 Reggio Emilia Reggio Nell'Emilia 42100",
    "addr:postcode":"42100;42100",
    "iso:country":"IT",
    "sg:address":"42100 Reggio Emilia",
    "sg:orig_category":"Macchine Utensili E Impianti",
    "sg:phone":"+39 0522 307126",
    "sg:postcode":"42100",
    "sg:province":"Reggio Nell'Emilia",
    "wof:name":"Reggiana Bocce",
    "wof:placetype":"venue"
},
  "geometry": {"coordinates":[10.608147,44.724152],"type":"Point"}
}