{
  "type": "Feature",
  "properties": {
    "addr:full":"Vai Romeo Sartori 14; Roana; 36010 Roana Vicenza 36010",
    "addr:housenumber":"14",
    "addr:postcode":"36010;36010",
    "iso:country":"IT",
    "sg:address":"Vai Romeo Sartori 14; Roana; 36010",
    "sg:city":"Roana",
    "sg:classifiers":[
        {
            "category":"Banks & Credit Unions",
            "subcategory":"Bank",
            "type":"Services"
        }
    ],
    "sg:phone":"+39 0424 66727",
    "sg:postcode":"36010",
    "sg:province":"Vicenza",
    "wof:name":"Banca Popolare Vicentina",
    "wof:placetype":"venue"
},
  "geometry": {"coordinates":[11.464408,45.874493],"type":"Point"}
}