{
  "type": "Feature",
  "properties": {
    "iso:country":"IT",
    "sg:address":"61, Regione Oltre Rea 12060 Monchiero",
    "sg:city":"Monchiero",
    "sg:classifiers":[
        {
            "category":"Autos & Motor Vehicles",
            "subcategory":"Automobile Sales",
            "type":"Retail Goods"
        }
    ],
    "sg:phone":"+39 0173 780002",
    "sg:postcode":"12060",
    "sg:province":"Cuneo",
    "sg:tags":[
        "industrial"
    ],
    "wof:name":"B.o.b. Sistemi Idraulici S.p.a.",
    "wof:placetype":"venue"
},
  "geometry": {"coordinates":[7.547111,44.388798],"type":"Point"}
}