{
  "type": "Feature",
  "properties": {
    "iso:country":"IT",
    "sg:address":"21020 Bodio Lomnago",
    "sg:city":"Bodio",
    "sg:orig_category":"Carni, Salumi E Pesci. Ristorazione E Locali Pubblici Affini. Shopping",
    "sg:phone":"+39 0332 949080",
    "sg:postcode":"21020",
    "sg:province":"Varese",
    "wof:name":"Ennegi Srl",
    "wof:placetype":"venue"
},
  "geometry": {"coordinates":[8.745627,45.791233],"type":"Point"}
}