{
  "type": "Feature",
  "properties": {
    "addr:full":"36061 Bassano Del Grappa Bassano del Grappa Vicenza 36061",
    "addr:postcode":"36061;36061",
    "iso:country":"IT",
    "sg:address":"36061 Bassano Del Grappa",
    "sg:city":"Bassano del Grappa",
    "sg:classifiers":[
        {
            "category":"Shopping",
            "subcategory":"Jewelry",
            "type":"Retail Goods"
        }
    ],
    "sg:phone":"+39 0424 30658",
    "sg:postcode":"36061",
    "sg:province":"Vicenza",
    "sg:tags":[
        "watchmaker",
        "jewelers",
        "gold",
        "silversmith"
    ],
    "sg:website":"http://www.cenere.it",
    "wof:name":"Cenere Giovanni Snc",
    "wof:placetype":"venue"
},
  "geometry": {"coordinates":[11.730305,45.767864],"type":"Point"}
}