{
  "type": "Feature",
  "properties": {
    "iso:country":"IT",
    "sg:address":"36, Corso De Tullio Antonio 70122 Bari",
    "sg:city":"Bari",
    "sg:classifiers":[
        {
            "category":"Marine",
            "type":"Transportation"
        }
    ],
    "sg:phone":"+39 080 578 9811",
    "sg:postcode":"70122",
    "sg:province":"Bari",
    "sg:tags":[
        "transport",
        "sea"
    ],
    "wof:name":"Morfimare Srl",
    "wof:placetype":"venue"
},
  "geometry": {"coordinates":[16.867846,41.135384],"type":"Point"}
}