{
  "type": "Feature",
  "properties": {
    "iso:country":"IT",
    "sg:address":"12045 Fossano",
    "sg:city":"Fossano",
    "sg:orig_category":"Automobili E Mezzi Di Trasporto",
    "sg:phone":"+39 0172 691374",
    "sg:postcode":"12045",
    "sg:province":"Cuneo",
    "wof:name":"Randazzo Gianni & Giuseppe Snc",
    "wof:placetype":"venue"
},
  "geometry": {"coordinates":[7.584844,44.501465],"type":"Point"}
}