{
  "type": "Feature",
  "properties": {
    "iso:country":"IT",
    "sg:address":"15060 Borghetto Di Borbera",
    "sg:city":"Borghetto di Borbera",
    "sg:orig_category":"Legno E Semilavorati. Materiali Edili",
    "sg:phone":"+39 0143 69107",
    "sg:postcode":"15060",
    "sg:province":"Alessandria",
    "wof:name":"Fravega Srl",
    "wof:placetype":"venue"
},
  "geometry": {"coordinates":[8.94413,44.730694],"type":"Point"}
}