{
  "type": "Feature",
  "properties": {
    "addr:full":"70019 Triggiano Triggiano Bari 70019",
    "addr:postcode":"70019;70019",
    "iso:country":"IT",
    "sg:address":"70019 Triggiano",
    "sg:city":"Triggiano",
    "sg:orig_category":"Servizi Ausiliari Dei Mezzi Di Trasporto. Servizi Ausiliari Per Il Trasporto. Acqua, Luce, Gas E Societa' Di Esercizio Pubblico",
    "sg:phone":"+39 080 468 6563",
    "sg:postcode":"70019",
    "sg:province":"Bari",
    "wof:name":"Infostrada Spa",
    "wof:placetype":"venue"
},
  "geometry": {"coordinates":[16.919287,41.063221],"type":"Point"}
}