{
  "type": "Feature",
  "properties": {
    "addr:full":"20011 Corbetta Corbetta Milano 20011",
    "addr:postcode":"20011;20011",
    "iso:country":"IT",
    "sg:address":"20011 Corbetta",
    "sg:city":"Corbetta",
    "sg:orig_category":"Ristorazione E Locali Pubblici Affini. Ristoranti Ed Esercizi Affini. Servizi Ausiliari Di Ristorazione E Di Intrattenimento",
    "sg:phone":"+39 02 977 8777",
    "sg:postcode":"20011",
    "sg:province":"Milano",
    "sg:website":"http://www.paginegialle.it/iricevimentidibetty",
    "wof:name":"I Ricevimenti Di Betty",
    "wof:placetype":"venue"
},
  "geometry": {"coordinates":[8.920325,45.466579],"type":"Point"}
}