{
  "type": "Feature",
  "properties": {
    "addr:full":"33100 Udine Udine Udine 33100",
    "addr:postcode":"33100;33100",
    "iso:country":"IT",
    "sg:address":"33100 Udine",
    "sg:city":"Udine",
    "sg:orig_category":"Automobili E Mezzi Di Trasporto",
    "sg:phone":"+39 0432 42217",
    "sg:postcode":"33100",
    "sg:province":"Udine",
    "wof:name":"Poggi Gianni Eredi Di A. Poggi & C. Snc",
    "wof:placetype":"venue"
},
  "geometry": {"coordinates":[13.232025,46.089886],"type":"Point"}
}