{
  "type": "Feature",
  "properties": {
    "addr:full":"22, Via Cristina Di Belgioioso 20085 Locate Di Triulzi Locate di Triulzi Milano 20085",
    "addr:postcode":"20085;20085",
    "addr:street":"Via Cristina Di Belgioioso",
    "iso:country":"IT",
    "sg:address":"22, Via Cristina Di Belgioioso 20085 Locate Di Triulzi",
    "sg:city":"Locate di Triulzi",
    "sg:classifiers":[
        {
            "category":"Manufacturing",
            "subcategory":"Metals",
            "type":"Manufacturing & Wholesale Goods"
        }
    ],
    "sg:phone":"+39 02 9073 0925",
    "sg:postcode":"20085",
    "sg:province":"Milano",
    "sg:tags":[
        "processing"
    ],
    "wof:name":"Repossi Mario S.d.f.",
    "wof:placetype":"venue"
},
  "geometry": {"coordinates":[9.1881408691,45.4636878967],"type":"Point"}
}