{
  "type": "Feature",
  "properties": {
    "iso:country":"IT",
    "sg:address":"67051 Avezzano",
    "sg:orig_category":"Macchine Utensili E Impianti",
    "sg:phone":"+39 0863 401182",
    "sg:postcode":"67051",
    "sg:province":"L'Aquila",
    "wof:name":"Macromec S.n.c. Di Scipioni Sabatino E Pietro",
    "wof:placetype":"venue"
},
  "geometry": {"coordinates":[13.43158,42.019417],"type":"Point"}
}