{
  "type": "Feature",
  "properties": {
    "addr:full":"08048 Tortoli' Ogliastra 08048",
    "addr:postcode":"08048;08048",
    "iso:country":"IT",
    "sg:address":"08048 Tortoli'",
    "sg:orig_category":"Prodotti Alimentari",
    "sg:phone":"+39 0782 623241",
    "sg:postcode":"08048",
    "sg:province":"Ogliastra",
    "wof:name":"Balzano Andrea",
    "wof:placetype":"venue"
},
  "geometry": {"coordinates":[9.6675481796,39.9152603149],"type":"Point"}
}