{
  "type": "Feature",
  "properties": {
    "addr:full":"115, Localita' Maso Corto 39020 Senales Senales Bolzano/Bozen 39020",
    "addr:housenumber":"115",
    "addr:postcode":"39020;39020",
    "addr:street":"Localita ' Maso Corto",
    "iso:country":"IT",
    "sg:address":"115, Localita' Maso Corto 39020 Senales",
    "sg:city":"Senales",
    "sg:classifiers":[
        {
            "category":"Professional",
            "subcategory":"Engineering",
            "type":"Services"
        }
    ],
    "sg:phone":"+39 0473 662188",
    "sg:postcode":"39020",
    "sg:province":"Bolzano/Bozen",
    "sg:tags":[
        "machine",
        "-",
        "mechanical"
    ],
    "wof:name":"Hotel Apparthotel Zirm",
    "wof:placetype":"venue"
},
  "geometry": {"coordinates":[10.783467,46.756229],"type":"Point"}
}