{
  "type": "Feature",
  "properties": {
    "addr:full":"37064 Povegliano Veronese Povegliano Veronese Verona 37064",
    "addr:postcode":"37064;37064",
    "iso:country":"IT",
    "sg:address":"37064 Povegliano Veronese",
    "sg:city":"Povegliano Veronese",
    "sg:orig_category":"Macchine, Impianti Ed Attrezzature Per Agricoltura E Zootecnia. Macchine Ed Impianti Per Edilizia E Lavori Pubblici",
    "sg:phone":"+39 045 635 0393",
    "sg:postcode":"37064",
    "sg:province":"Verona",
    "sg:website":"http://www.2msrl.it",
    "wof:name":"2m Srl",
    "wof:placetype":"venue"
},
  "geometry": {"coordinates":[10.896791,45.449554],"type":"Point"}
}