{
  "type": "Feature",
  "properties": {
    "addr:full":"14, Via Ingham 90124 Palermo Palermo Palermo 90124",
    "addr:postcode":"90124;90124",
    "addr:street":"Via Ingham",
    "iso:country":"IT",
    "sg:address":"14, Via Ingham 90124 Palermo",
    "sg:city":"Palermo",
    "sg:classifiers":[
        {
            "category":"Home & Garden",
            "subcategory":"Home Furnishings",
            "type":"Retail Goods"
        }
    ],
    "sg:phone":"+39 39091392018",
    "sg:postcode":"90124",
    "sg:province":"Palermo",
    "sg:tags":[
        "household"
    ],
    "wof:name":"C & C Arredi S.r.l.",
    "wof:placetype":"venue"
},
  "geometry": {"coordinates":[12.941817,37.914299],"type":"Point"}
}