{
  "type": "Feature",
  "properties": {
    "addr:full":"00040 Lariano Lariano Roma 00040",
    "addr:postcode":"00040;00040",
    "iso:country":"IT",
    "sg:address":"00040 Lariano",
    "sg:city":"Lariano",
    "sg:orig_category":"Carta, Cartone E Prodotti Primari. Forniture E Materiali Per Imballaggio E Confezionamento",
    "sg:phone":"+39 06 965 6495",
    "sg:postcode":"00040",
    "sg:province":"Roma",
    "wof:name":"De Marchis Massimo",
    "wof:placetype":"venue"
},
  "geometry": {"coordinates":[12.778375,41.692184],"type":"Point"}
}