{
  "type": "Feature",
  "properties": {
    "addr:full":"Via Alessi 8 20020 Lainate Lainate Milano 20020",
    "addr:housenumber":"8",
    "addr:postcode":"20020;20020",
    "addr:street":"Via Alessi",
    "iso:country":"IT",
    "sg:address":"Via Alessi 8 20020 Lainate",
    "sg:city":"Lainate",
    "sg:classifiers":[
        {
            "category":"Building & Trades",
            "subcategory":"Construction",
            "type":"Services"
        }
    ],
    "sg:phone":"+39 02 937 0329",
    "sg:postcode":"20020",
    "sg:province":"Milano",
    "sg:tags":[
        "machine"
    ],
    "sg:website":"www.euralpha.it",
    "wof:name":"Euralpha Di Guido Festa Srl",
    "wof:placetype":"venue"
},
  "geometry": {"coordinates":[9.018383,45.578312],"type":"Point"}
}