{
  "type": "Feature",
  "properties": {
    "addr:full":"20090 Segrate Segrate Milano 20090",
    "addr:postcode":"20090;20090",
    "iso:country":"IT",
    "sg:address":"20090 Segrate",
    "sg:city":"Segrate",
    "sg:orig_category":"Pompe. Macchine, Strumenti Ed Apparecchi Per Attivita' Industriali",
    "sg:phone":"+39 02 213 4940",
    "sg:postcode":"20090",
    "sg:province":"Milano",
    "wof:name":"D.v.p. Vacuum Technology S.r.l.",
    "wof:placetype":"venue"
},
  "geometry": {"coordinates":[9.2687263489,45.4755592346],"type":"Point"}
}