{
  "type": "Feature",
  "properties": {
    "iso:country":"IT",
    "sg:address":"Via Dell' Industria 7/b 60127 Ancona",
    "sg:city":"Ancona",
    "sg:classifiers":[
        {
            "category":"Shopping Center",
            "type":"Public Place"
        }
    ],
    "sg:phone":"+39 071 280 1460",
    "sg:postcode":"60127",
    "sg:province":"Ancona",
    "sg:tags":[
        "case",
        "key"
    ],
    "wof:name":"Smart Di Gabrio Lanzavecchia & C. S Nc",
    "wof:placetype":"venue"
},
  "geometry": {"coordinates":[13.518757,43.615856],"type":"Point"}
}