{
  "type": "Feature",
  "properties": {
    "addr:full":"Viale Delle Industrie 80020 Casavatore Casavatore Napoli 80020",
    "addr:postcode":"80020;80020",
    "addr:street":"Viale Delle Industrie",
    "iso:country":"IT",
    "sg:address":"Viale Delle Industrie 80020 Casavatore",
    "sg:city":"Casavatore",
    "sg:classifiers":[
        {
            "category":"Shopping",
            "type":"Retail Goods"
        }
    ],
    "sg:phone":"+39 081 738 3246",
    "sg:postcode":"80020",
    "sg:province":"Napoli",
    "sg:tags":[
        "finished",
        "-",
        "metallic"
    ],
    "wof:name":"O.m.a.c. (s.r.l.)",
    "wof:placetype":"venue"
},
  "geometry": {"coordinates":[14.2740468979,40.8944969177],"type":"Point"}
}