{
  "type": "Feature",
  "properties": {
    "addr:full":"20090 Buccinasco Buccinasco Milano 20090",
    "addr:postcode":"20090;20090",
    "iso:country":"IT",
    "sg:address":"20090 Buccinasco",
    "sg:city":"Buccinasco",
    "sg:orig_category":"Utensili Meccanici E Materiali",
    "sg:phone":"+39 02 4884 2597",
    "sg:postcode":"20090",
    "sg:province":"Milano",
    "sg:website":"http://www.hodara.it",
    "wof:name":"Hodara Utensili Spa",
    "wof:placetype":"venue"
},
  "geometry": {"coordinates":[9.118313,45.423092],"type":"Point"}
}