{
  "type": "Feature",
  "properties": {
    "addr:full":"87055 San Giovanni In Fiore San Giovanni in Fiore Cosenza 87055",
    "addr:housenumber":"87055",
    "addr:postcode":"87055",
    "addr:street":"San",
    "iso:country":"IT",
    "sg:address":"87055 San Giovanni In Fiore",
    "sg:city":"San Giovanni in Fiore",
    "sg:orig_category":"Servizi Culturali E Per Lo Spettacolo. Servizi Per Lo Sport E Il Tempo Libero. Associazioni Ed Organismi Di Interesse Pubblico",
    "sg:phone":"+39 0984 970944",
    "sg:postcode":"87055",
    "sg:province":"Cosenza",
    "wof:name":"Circolo Arci-gola 'cariglio'",
    "wof:placetype":"venue"
},
  "geometry": {"coordinates":[16.65271,39.284508],"type":"Point"}
}