{
  "type": "Feature",
  "properties": {
    "addr:full":"80049 Somma Vesuviana Somma Vesuviana Napoli 80049",
    "addr:postcode":"80049;80049",
    "iso:country":"IT",
    "sg:address":"80049 Somma Vesuviana",
    "sg:city":"Somma Vesuviana",
    "sg:orig_category":"Calcestruzzo Preconfezionato",
    "sg:phone":"+39 081 531 7554",
    "sg:postcode":"80049",
    "sg:province":"Napoli",
    "wof:name":"Euromix Srl",
    "wof:placetype":"venue"
},
  "geometry": {"coordinates":[14.423505,40.894672],"type":"Point"}
}