{
  "type": "Feature",
  "properties": {
    "iso:country":"IT",
    "sg:address":"96019 Rosolini",
    "sg:city":"Rosolini",
    "sg:orig_category":"Elettrotecnica Industriale, Prodotti E Apparecchiature. Elettronica Industriale, Prodotti E Apparecchiature",
    "sg:phone":"+39 0931 502843",
    "sg:postcode":"96019",
    "sg:province":"Siracusa",
    "wof:name":"Floridia Srl",
    "wof:placetype":"venue"
},
  "geometry": {"coordinates":[14.966821,36.825748],"type":"Point"}
}