{
  "type": "Feature",
  "properties": {
    "addr:full":"34, Via Brescia 25020 Pavone Del Mella Pavone del Mella Brescia 25020",
    "addr:postcode":"25020;25020",
    "addr:street":"Via Brescia",
    "iso:country":"IT",
    "sg:address":"34, Via Brescia 25020 Pavone Del Mella",
    "sg:city":"Pavone del Mella",
    "sg:classifiers":[
        {
            "category":"Manufacturing",
            "subcategory":"Metals",
            "type":"Manufacturing & Wholesale Goods"
        }
    ],
    "sg:phone":"+39 39030959384",
    "sg:postcode":"25020",
    "sg:province":"Brescia",
    "sg:tags":[
        "metallurgy",
        "metalworking"
    ],
    "wof:name":"O.f.p.m. Di Losio Angelo E Pietro (s.n.c.)",
    "wof:placetype":"venue"
},
  "geometry": {"coordinates":[10.2114572525,45.31067276],"type":"Point"}
}