{
  "type": "Feature",
  "properties": {
    "iso:country":"IT",
    "sg:address":"10090 Bruino",
    "sg:city":"Bruino",
    "sg:orig_category":"Articoli Regalo - Produzione E Ingrosso",
    "sg:phone":"+39 011 405 4866",
    "sg:postcode":"10090",
    "sg:province":"Torino",
    "sg:website":"http://www.omlebruno.com",
    "wof:name":"Omle Sas Di Bruno Enrico & C.",
    "wof:placetype":"venue"
},
  "geometry": {"coordinates":[7.477774,45.011322],"type":"Point"}
}