{
  "type": "Feature",
  "properties": {
    "iso:country":"IT",
    "sg:address":"06073 Corciano",
    "sg:city":"Corciano",
    "sg:classifiers":[
        {
            "category":"Health Services",
            "subcategory":"Health Practitioner",
            "type":"Services"
        }
    ],
    "sg:phone":"+39 075 500 0200",
    "sg:postcode":"06073",
    "sg:province":"Perugia",
    "sg:tags":[
        "medici"
    ],
    "wof:name":"Lombi Riccardo",
    "wof:placetype":"venue"
},
  "geometry": {"coordinates":[12.318465,43.104435],"type":"Point"}
}