{
  "type": "Feature",
  "properties": {
    "iso:country":"IT",
    "sg:address":"31039 Riese Pio X",
    "sg:city":"Riese Pio X",
    "sg:orig_category":"Abbigliamento Intimo, Calze E Costumi Da Bagno. Articoli Medico-sanitari Ed Ortopedici",
    "sg:phone":"+39 0423 748440",
    "sg:postcode":"31039",
    "sg:province":"Treviso",
    "wof:name":"Levantes Srl",
    "wof:placetype":"venue"
},
  "geometry": {"coordinates":[11.912148,45.729633],"type":"Point"}
}