{
  "type": "Feature",
  "properties": {
    "iso:country":"IT",
    "sg:address":"26030 Cicognolo",
    "sg:city":"Cicognolo",
    "sg:orig_category":"Macchine, Impianti Ed Attrezzature Per Agricoltura E Zootecnia",
    "sg:phone":"+39 0372 835884",
    "sg:postcode":"26030",
    "sg:province":"Cremona",
    "wof:name":"Nazzari Alessandro E C. S.n.c.",
    "wof:placetype":"venue"
},
  "geometry": {"coordinates":[10.191801,45.168224],"type":"Point"}
}