{
  "type": "Feature",
  "properties": {
    "iso:country":"IT",
    "sg:address":"1, Via Vittorio Veneto 32040 Domegge Di Cadore",
    "sg:city":"Domegge di Cadore",
    "sg:classifiers":[
        {
            "category":"Wholesale",
            "subcategory":"Medical Equipment & Supplies",
            "type":"Manufacturing & Wholesale Goods"
        }
    ],
    "sg:phone":"+39 0435 728188",
    "sg:postcode":"32040",
    "sg:province":"Belluno",
    "sg:tags":[
        "-",
        "health",
        "instrument"
    ],
    "wof:name":"Diesse Srl Di De Silvestro Romeo Antonio & C.",
    "wof:placetype":"venue"
},
  "geometry": {"coordinates":[12.397843,46.450253],"type":"Point"}
}