{
  "type": "Feature",
  "properties": {
    "iso:country":"IT",
    "sg:address":"13/b, V. Etruria 00183 Roma",
    "sg:city":"Roma",
    "sg:classifiers":[
        {
            "category":"Wholesale",
            "subcategory":"Drugs",
            "type":"Manufacturing & Wholesale Goods"
        }
    ],
    "sg:phone":"+39 39067027449",
    "sg:postcode":"00183",
    "sg:province":"Roma",
    "sg:tags":[
        "chemical",
        "pharmaceutical"
    ],
    "sg:website":"http://www.farmacialopriore.com:ws_end: :mark:ws:http://www.paginegialle.it/lopriore",
    "wof:name":"Farmacia Lopriore Eredi Dr. Servino",
    "wof:placetype":"venue"
},
  "geometry": {"coordinates":[12.514594,41.87859],"type":"Point"}
}