{
  "type": "Feature",
  "properties": {
    "addr:full":"20089 Pontesesto Milano 20089",
    "addr:postcode":"20089;20089",
    "addr:street":"Pontesesto",
    "iso:country":"IT",
    "sg:address":"20089 Pontesesto",
    "sg:orig_category":"Petroli, Gas E Combustibili. Servizi E Lavori Industria Chimica. Servizi E Lavori Per Edilizia E Lavori Pubblici. Acqua, Luce, Gas E Societa' Di Esercizio Pubblico",
    "sg:phone":"+39 02 825 1680",
    "sg:postcode":"20089",
    "sg:province":"Milano",
    "wof:name":"Ama Azienda Multiservizi Ambientale Spa",
    "wof:placetype":"venue"
},
  "geometry": {"coordinates":[9.1779499054,45.3781547546],"type":"Point"}
}