{
  "type": "Feature",
  "properties": {
    "iso:country":"IT",
    "sg:address":"8901, V. Ugo La Malfa 90147 Palermo",
    "sg:city":"Palermo",
    "sg:classifiers":[
        {
            "category":"Home & Garden",
            "subcategory":"Home Furnishings",
            "type":"Retail Goods"
        }
    ],
    "sg:phone":"+39 39091241411",
    "sg:postcode":"90147",
    "sg:province":"Palermo",
    "sg:tags":[
        "household"
    ],
    "sg:website":"http://www.rimark.it:ws_end: :mark:ws:http://www.paginegialle.it/rimark",
    "wof:name":"Rimark Srl",
    "wof:placetype":"venue"
},
  "geometry": {"coordinates":[13.313894,38.162819],"type":"Point"}
}