{
  "type": "Feature",
  "properties": {
    "iso:country":"IT",
    "sg:address":"89021 Cinquefrondi",
    "sg:city":"Cinquefrondi",
    "sg:orig_category":"Forniture Per Edilizia E Lavori Pubblici",
    "sg:phone":"+39 0966 935286",
    "sg:postcode":"89021",
    "sg:province":"Reggio Di Calabria",
    "wof:name":"Center Pav Di Caridi Geom. Carmelo",
    "wof:placetype":"venue"
},
  "geometry": {"coordinates":[15.6501369476,38.1146888733],"type":"Point"}
}