{
  "type": "Feature",
  "properties": {
    "iso:country":"IT",
    "sg:address":"36016 Thiene",
    "sg:city":"Thiene",
    "sg:orig_category":"Affilatura Strumenti Ed Utensili",
    "sg:phone":"+39 0445 362091",
    "sg:postcode":"36016",
    "sg:province":"Vicenza",
    "wof:name":"Affilautensili Balasso Giobatta Di Balasso Enzo & C. Srl",
    "wof:placetype":"venue"
},
  "geometry": {"coordinates":[11.486689,45.693859],"type":"Point"}
}