{
  "type": "Feature",
  "properties": {
    "addr:full":"21046 Malnate Malnate Varese 21046",
    "addr:postcode":"21046;21046",
    "iso:country":"IT",
    "sg:address":"21046 Malnate",
    "sg:city":"Malnate",
    "sg:classifiers":[
        {
            "category":"Manufacturing",
            "subcategory":"Tools & Machinery",
            "type":"Manufacturing & Wholesale Goods"
        }
    ],
    "sg:phone":"+39 0332 426660",
    "sg:postcode":"21046",
    "sg:province":"Varese",
    "sg:tags":[
        "machining",
        "mechanical"
    ],
    "wof:name":"Car Mec Srl",
    "wof:placetype":"venue"
},
  "geometry": {"coordinates":[8.879545,45.786854],"type":"Point"}
}