{
  "type": "Feature",
  "properties": {
    "addr:full":"41036 Medolla Medolla Modena 41036",
    "addr:postcode":"41036;41036",
    "iso:country":"IT",
    "sg:address":"41036 Medolla",
    "sg:city":"Medolla",
    "sg:orig_category":"Lavorazioni Metalli, Stampaggio E Saldatura",
    "sg:phone":"+39 0535 59260",
    "sg:postcode":"41036",
    "sg:province":"Modena",
    "wof:name":"O.m.c. Srl",
    "wof:placetype":"venue"
},
  "geometry": {"coordinates":[11.067976,44.846085],"type":"Point"}
}