{
  "type": "Feature",
  "properties": {
    "iso:country":"IT",
    "sg:address":"10148 Torino",
    "sg:city":"Torino",
    "sg:orig_category":"Trasporti E Spedizioni Merci",
    "sg:phone":"+39 011 220 5946",
    "sg:postcode":"10148",
    "sg:province":"Torino",
    "wof:name":"Costantino Flavio",
    "wof:placetype":"venue"
},
  "geometry": {"coordinates":[7.676184,45.105171],"type":"Point"}
}