{
  "type": "Feature",
  "properties": {
    "iso:country":"IT",
    "sg:address":"23/r, Piazza Dei Pitti 50125 Firenze",
    "sg:city":"Firenze",
    "sg:classifiers":[
        {
            "category":"Shopping",
            "subcategory":"Crafts & Fabrics",
            "type":"Retail Goods"
        }
    ],
    "sg:phone":"+39 39055282127",
    "sg:postcode":"50125",
    "sg:province":"Firenze",
    "sg:tags":[
        "ceramic"
    ],
    "wof:name":"Mosaico Di Pitti Di De Filippis Emilio",
    "wof:placetype":"venue"
},
  "geometry": {"coordinates":[11.256902,43.768734],"type":"Point"}
}