{
  "type": "Feature",
  "properties": {
    "addr:full":"6, Via Vespucci Amerigo 24036 Ponte San Pietro Ponte San Pietro Bergamo 24036",
    "addr:postcode":"24036;24036",
    "addr:street":"Via Vespucci Amerigo",
    "iso:country":"IT",
    "sg:address":"6, Via Vespucci Amerigo 24036 Ponte San Pietro",
    "sg:city":"Ponte San Pietro",
    "sg:classifiers":[
        {
            "category":"Wholesale",
            "subcategory":"Drugs",
            "type":"Manufacturing & Wholesale Goods"
        }
    ],
    "sg:phone":"+39 39035611556",
    "sg:postcode":"24036",
    "sg:province":"Bergamo",
    "sg:tags":[
        "chemical",
        "pharmaceutical"
    ],
    "wof:name":"Colorificio Orobico Srl",
    "wof:placetype":"venue"
},
  "geometry": {"coordinates":[9.593173,45.708786],"type":"Point"}
}