{
  "type": "Feature",
  "properties": {
    "iso:country":"IT",
    "sg:address":"00181 Roma",
    "sg:city":"Roma",
    "sg:orig_category":"Non-classified Establishments",
    "sg:phone":"+39 06 782 0102",
    "sg:postcode":"00181",
    "sg:province":"Roma",
    "wof:name":"Mcs Di Ciarpaglini A. & C. Sas",
    "wof:placetype":"venue"
},
  "geometry": {"coordinates":[12.528365,41.877888],"type":"Point"}
}