{
  "type": "Feature",
  "properties": {
    "iso:country":"IT",
    "sg:address":"95126 Catania",
    "sg:city":"Catania",
    "sg:orig_category":"Nautica. Ricambi E Componenti Dei Mezzi Di Trasporto",
    "sg:phone":"+39 095 712 2383",
    "sg:postcode":"95126",
    "sg:province":"Catania",
    "wof:name":"O.r.a.m. Srl",
    "wof:placetype":"venue"
},
  "geometry": {"coordinates":[15.112455,37.528709],"type":"Point"}
}