{
  "type": "Feature",
  "properties": {
    "addr:full":"20090 Trezzano Sul Naviglio Trezzano sul Naviglio Milano 20090",
    "addr:postcode":"20090;20090",
    "iso:country":"IT",
    "sg:address":"20090 Trezzano Sul Naviglio",
    "sg:city":"Trezzano sul Naviglio",
    "sg:orig_category":"Motori Ed Organi Di Trasmissione. Ricambi E Componenti Dei Mezzi Di Trasporto",
    "sg:phone":"+39 02 445 5714",
    "sg:postcode":"20090",
    "sg:province":"Milano",
    "wof:name":"Officina Meccanica Tronconi & Taverna Snc",
    "wof:placetype":"venue"
},
  "geometry": {"coordinates":[9.055809021,45.4219474792],"type":"Point"}
}