{
  "type": "Feature",
  "properties": {
    "addr:full":"22, Via Xxv Aprile 25038 Rovato Rovato Brescia 25038",
    "addr:postcode":"25038;25038",
    "addr:street":"Via Xxv Aprile",
    "iso:country":"IT",
    "sg:address":"22, Via Xxv Aprile 25038 Rovato",
    "sg:city":"Rovato",
    "sg:classifiers":[
        {
            "category":"Home & Garden",
            "subcategory":"Home Furnishings",
            "type":"Retail Goods"
        }
    ],
    "sg:phone":"+39 030 772 1796",
    "sg:postcode":"25038",
    "sg:province":"Brescia",
    "sg:tags":[
        "household"
    ],
    "wof:name":"In.sa.b. Industrie Saleri Bagno",
    "wof:placetype":"venue"
},
  "geometry": {"coordinates":[10.222958,45.539829],"type":"Point"}
}