{
  "type": "Feature",
  "properties": {
    "addr:full":"25010 Pozzolengo Pozzolengo Brescia 25010",
    "addr:postcode":"25010;25010",
    "iso:country":"IT",
    "sg:address":"25010 Pozzolengo",
    "sg:city":"Pozzolengo",
    "sg:orig_category":"Minuterie Metalliche E Ferramenta",
    "sg:phone":"+39 030 991 8129",
    "sg:postcode":"25010",
    "sg:province":"Brescia",
    "wof:name":"Georg Fischer Pfci Srl",
    "wof:placetype":"venue"
},
  "geometry": {"coordinates":[10.2073698044,45.5457839966],"type":"Point"}
}