{
  "type": "Feature",
  "properties": {
    "iso:country":"IT",
    "sg:address":"86081 Agnone",
    "sg:city":"Agnone",
    "sg:orig_category":"Prodotti Alimentari",
    "sg:phone":"+39 0865 78606",
    "sg:postcode":"86081",
    "sg:province":"Isernia",
    "wof:name":"Di Menna Pietrino & Figli Snc",
    "wof:placetype":"venue"
},
  "geometry": {"coordinates":[14.3675527573,41.7917709351],"type":"Point"}
}