{
  "type": "Feature",
  "properties": {
    "iso:country":"IT",
    "sg:address":"Via Cellaimo 735 47032 Bertinoro",
    "sg:city":"Bertinoro",
    "sg:classifiers":[
        {
            "category":"Coffee & Tea",
            "type":"Food & Drink"
        }
    ],
    "sg:phone":"+39 0543 445130",
    "sg:postcode":"47032",
    "sg:province":"Forl\u00ec-Cesena",
    "sg:tags":[
        "aquavit"
    ],
    "sg:website":"www.fattoriacarossa.it",
    "wof:name":"Fattoria Ca' Rossa Di Masotti Massimo",
    "wof:placetype":"venue"
},
  "geometry": {"coordinates":[12.134468,44.152332],"type":"Point"}
}