{
  "type": "Feature",
  "properties": {
    "addr:full":"80045 Pompei Pompei Napoli 80045",
    "addr:housenumber":"80045",
    "addr:postcode":"80045",
    "iso:country":"IT",
    "sg:address":"80045 Pompei",
    "sg:city":"Pompei",
    "sg:orig_category":"Servizi E Lavori Per Abbigliamento E Pelletterie. Servizi Ausiliari Di Sorveglianza, Manutenzione E Pulizia",
    "sg:phone":"+39 081 863 2308",
    "sg:postcode":"80045",
    "sg:province":"Napoli",
    "wof:name":"Lavanderia Industriale Langella Sas",
    "wof:placetype":"venue"
},
  "geometry": {"coordinates":[14.502302,40.749584],"type":"Point"}
}