{
  "type": "Feature",
  "properties": {
    "addr:full":"16/b, Localita' Vallecascia 62010 Montecassiano Montecassiano Macerata 62010",
    "addr:housenumber":"16 / b",
    "addr:postcode":"62010;62010",
    "addr:street":"Localita ' Vallecascia",
    "iso:country":"IT",
    "sg:address":"16/b, Localita' Vallecascia 62010 Montecassiano",
    "sg:city":"Montecassiano",
    "sg:classifiers":[
        {
            "category":"Parking",
            "subcategory":"Lot",
            "type":"Transportation"
        }
    ],
    "sg:phone":"+39 0733 290000",
    "sg:postcode":"62010",
    "sg:province":"Macerata",
    "sg:tags":[
        "transport",
        "road"
    ],
    "wof:name":"C.a.c.i.m.",
    "wof:placetype":"venue"
},
  "geometry": {"coordinates":[13.435984,43.346363],"type":"Point"}
}