{
  "type": "Feature",
  "properties": {
    "iso:country":"IT",
    "sg:address":"09129 Cagliari",
    "sg:city":"Cagliari",
    "sg:orig_category":"Scuole E Servizi Scolastici. Ricerca, Selezione E Formazione Del Personale",
    "sg:postcode":"09129",
    "sg:province":"Cagliari",
    "wof:name":"Istam S.a.s.",
    "wof:placetype":"venue"
},
  "geometry": {"coordinates":[9.128633,39.217529],"type":"Point"}
}