{
  "type": "Feature",
  "properties": {
    "iso:country":"IT",
    "sg:address":"197, Via Canturina 22100 Como",
    "sg:city":"Como",
    "sg:classifiers":[
        {
            "category":"Autos & Motor Vehicles",
            "subcategory":"Automobile Sales",
            "type":"Retail Goods"
        }
    ],
    "sg:phone":"+39 39031507611",
    "sg:postcode":"22100",
    "sg:province":"Como",
    "sg:tags":[
        "motor-cars"
    ],
    "wof:name":"R & M Italia S.r.l.",
    "wof:placetype":"venue"
},
  "geometry": {"coordinates":[9.0994415283,45.7787437439],"type":"Point"}
}