{
  "type": "Feature",
  "properties": {
    "iso:country":"IT",
    "sg:address":"Via Scalette 23 35032 Arqua' Petrarca",
    "sg:classifiers":[
        {
            "category":"Food & Beverages",
            "subcategory":"Liquor & Beverages",
            "type":"Retail Goods"
        }
    ],
    "sg:phone":"+39 0429 777225",
    "sg:postcode":"35032",
    "sg:province":"Padova",
    "sg:tags":[
        "wine",
        "italian"
    ],
    "wof:name":"Azienda Agricola Vignalta",
    "wof:placetype":"venue"
},
  "geometry": {"coordinates":[11.711613,45.276524],"type":"Point"}
}