{
  "type": "Feature",
  "properties": {
    "addr:full":"20052 Monza Monza Milano 20052",
    "addr:postcode":"20052;20052",
    "iso:country":"IT",
    "sg:address":"20052 Monza",
    "sg:city":"Monza",
    "sg:orig_category":"Prodotti E Manufatti In Materie Plastiche. Forniture Per Edilizia E Lavori Pubblici. Forniture E Materiali Per Imballaggio E Confezionamento",
    "sg:phone":"+39 039 733909",
    "sg:postcode":"20052",
    "sg:province":"Milano",
    "wof:name":"Corioni S.a.s. Di Corioni Enrico & C.",
    "wof:placetype":"venue"
},
  "geometry": {"coordinates":[9.277879715,45.574420929],"type":"Point"}
}