{
  "type": "Feature",
  "properties": {
    "addr:full":"33010 Tavagnacco Tavagnacco Udine 33010",
    "addr:postcode":"33010;33010",
    "iso:country":"IT",
    "sg:address":"33010 Tavagnacco",
    "sg:city":"Tavagnacco",
    "sg:orig_category":"Metalli E Leghe",
    "sg:phone":"+39 0432 573751",
    "sg:postcode":"33010",
    "sg:province":"Udine",
    "wof:name":"Eurosider Service Srl",
    "wof:placetype":"venue"
},
  "geometry": {"coordinates":[13.2173223495,46.1114120483],"type":"Point"}
}