{
  "type": "Feature",
  "properties": {
    "iso:country":"IT",
    "sg:address":"47, Via Julia 35010 Vigonza",
    "sg:city":"Vigonza",
    "sg:classifiers":[
        {
            "category":"Professional",
            "subcategory":"Engineering",
            "type":"Services"
        }
    ],
    "sg:phone":"+39 39049725388",
    "sg:postcode":"35010",
    "sg:province":"Padova",
    "sg:tags":[
        "machine",
        "-",
        "mechanical"
    ],
    "wof:name":"Pac Service (s.r.l.)",
    "wof:placetype":"venue"
},
  "geometry": {"coordinates":[11.97597,45.421669],"type":"Point"}
}