{
  "type": "Feature",
  "properties": {
    "addr:full":"Via Cerreto 29013 Carpaneto Piacentino Carpaneto Piacentino Piacenza 29013",
    "addr:postcode":"29013;29013",
    "addr:street":"Via Cerreto",
    "iso:country":"IT",
    "sg:address":"Via Cerreto 29013 Carpaneto Piacentino",
    "sg:city":"Carpaneto Piacentino",
    "sg:classifiers":[
        {
            "category":"Real Estate",
            "subcategory":"Architect",
            "type":"Services"
        }
    ],
    "sg:phone":"+39 0523 852368",
    "sg:postcode":"29013",
    "sg:province":"Piacenza",
    "sg:tags":[
        "textile",
        "clothing"
    ],
    "wof:name":"Tintofil (s.r.l.)",
    "wof:placetype":"venue"
},
  "geometry": {"coordinates":[9.695142,45.053772],"type":"Point"}
}