{
  "type": "Feature",
  "properties": {
    "addr:full":"41057 Spilamberto Spilamberto Modena 41057",
    "addr:postcode":"41057;41057",
    "iso:country":"IT",
    "sg:address":"41057 Spilamberto",
    "sg:city":"Spilamberto",
    "sg:classifiers":[
        {
            "category":"Sports & Exercise",
            "subcategory":"Tennis Court",
            "type":"Entertainment"
        }
    ],
    "sg:phone":"+39 059 784449",
    "sg:postcode":"41057",
    "sg:province":"Modena",
    "sg:tags":[
        "e",
        "lo",
        "tempo",
        "libero",
        "per",
        "impianti",
        "il",
        "attrezzature"
    ],
    "wof:name":"Park Style (s.r.l.)",
    "wof:placetype":"venue"
},
  "geometry": {"coordinates":[11.019514,44.518482],"type":"Point"}
}