{
  "type": "Feature",
  "properties": {
    "iso:country":"IT",
    "sg:address":"Piazza Bertacchi 2; Madesimo",
    "sg:classifiers":[
        {
            "category":"Banks & Credit Unions",
            "subcategory":"Bank",
            "type":"Services"
        }
    ],
    "sg:phone":"+39 0343 53208",
    "wof:name":"Credito Valtellinese Scarl",
    "wof:placetype":"venue"
},
  "geometry": {"coordinates":[9.35739,46.434975],"type":"Point"}
}