{
  "type": "Feature",
  "properties": {
    "iso:country":"IT",
    "sg:address":"20, Via Milano 26016 Spino D'adda",
    "sg:classifiers":[
        {
            "category":"Shopping",
            "subcategory":"Crafts & Fabrics",
            "type":"Retail Goods"
        }
    ],
    "sg:phone":"+39 390 373 9891",
    "sg:postcode":"26016",
    "sg:province":"Cremona",
    "sg:tags":[
        "ceramic"
    ],
    "wof:name":"Welko Industriale S.p.a.",
    "wof:placetype":"venue"
},
  "geometry": {"coordinates":[9.477771,45.401352],"type":"Point"}
}