{
  "type": "Feature",
  "properties": {
    "addr:full":"28803 Premosello Chiovenda Verbano-Cusio-Ossola 28803",
    "addr:postcode":"28803;28803",
    "iso:country":"IT",
    "sg:address":"28803 Premosello Chiovenda",
    "sg:orig_category":"Carpenterie Ferro",
    "sg:phone":"+39 0324 844517",
    "sg:postcode":"28803",
    "sg:province":"Verbano-Cusio-Ossola",
    "wof:name":"Martini Luciana - Iron",
    "wof:placetype":"venue"
},
  "geometry": {"coordinates":[8.336092,46.001335],"type":"Point"}
}