{
  "type": "Feature",
  "properties": {
    "iso:country":"IT",
    "sg:address":"14, Via Belvedere 20043 Arcore",
    "sg:city":"Arcore",
    "sg:classifiers":[
        {
            "category":"Manufacturing",
            "subcategory":"Paper Products",
            "type":"Manufacturing & Wholesale Goods"
        }
    ],
    "sg:phone":"+39 039 618 0169",
    "sg:postcode":"20043",
    "sg:province":"Milano",
    "sg:tags":[
        "cardboard"
    ],
    "wof:name":"Tecnocarton Srl",
    "wof:placetype":"venue"
},
  "geometry": {"coordinates":[9.2885360718,45.6729660034],"type":"Point"}
}