{
  "type": "Feature",
  "properties": {
    "iso:country":"IT",
    "sg:address":"80022 Arzano",
    "sg:city":"Arzano",
    "sg:orig_category":"Accessori Moda D'abbigliamento",
    "sg:phone":"+39 081 573 4982",
    "sg:postcode":"80022",
    "sg:province":"Napoli",
    "wof:name":"Berrettificio De.pa. Srl",
    "wof:placetype":"venue"
},
  "geometry": {"coordinates":[14.262613,40.918629],"type":"Point"}
}