{
  "type": "Feature",
  "properties": {
    "addr:full":"33010 Reana Del Rojale Vergnacco Udine 33010",
    "addr:postcode":"33010;33010",
    "iso:country":"IT",
    "sg:address":"33010 Reana Del Rojale",
    "sg:city":"Vergnacco",
    "sg:orig_category":"Forniture Per Edilizia E Lavori Pubblici. Arredi Ed Attrezzature Per Attivita' Commerciali Ed Artigianali. Forniture Per Attivita' Industriali",
    "sg:phone":"+39 0432 880771",
    "sg:postcode":"33010",
    "sg:province":"Udine",
    "sg:website":"http://www.comello.com",
    "wof:name":"Comello Giobatta Parchetti Srl",
    "wof:placetype":"venue"
},
  "geometry": {"coordinates":[13.2469205856,46.1439437866],"type":"Point"}
}