{
  "type": "Feature",
  "properties": {
    "iso:country":"IT",
    "sg:address":"71043 Manfredonia",
    "sg:city":"Manfredonia",
    "sg:orig_category":"Elettrotecnica Industriale, Prodotti E Apparecchiature. Ricambi E Componenti Dei Mezzi Di Trasporto",
    "sg:phone":"+39 0884 589511",
    "sg:postcode":"71043",
    "sg:province":"Foggia",
    "wof:name":"I.b.f. Spa",
    "wof:placetype":"venue"
},
  "geometry": {"coordinates":[15.982095,41.674229],"type":"Point"}
}