{
  "type": "Feature",
  "properties": {
    "addr:full":"98122 Messina Messina Messina 98122",
    "addr:postcode":"98122;98122",
    "iso:country":"IT",
    "sg:address":"98122 Messina",
    "sg:city":"Messina",
    "sg:orig_category":"Gioielleria, Oreficeria E Argenteria. Shopping",
    "sg:phone":"+39 090 679015",
    "sg:postcode":"98122",
    "sg:province":"Messina",
    "wof:name":"Miragliotta Giuseppe",
    "wof:placetype":"venue"
},
  "geometry": {"coordinates":[15.558221,38.184521],"type":"Point"}
}