{
  "type": "Feature",
  "properties": {
    "iso:country":"IT",
    "sg:address":"19123 La Spezia",
    "sg:orig_category":"Metalli E Leghe",
    "sg:phone":"+39 0187 701170",
    "sg:province":"SP",
    "wof:name":"Mereta Giuseppe",
    "wof:placetype":"venue"
},
  "geometry": {"coordinates":[9.8020038605,44.1095581055],"type":"Point"}
}