{
  "type": "Feature",
  "properties": {
    "addr:full":"80016 Marano Di Napoli Marano di Napoli Napoli 80016",
    "addr:postcode":"80016;80016",
    "iso:country":"IT",
    "sg:address":"80016 Marano Di Napoli",
    "sg:city":"Marano di Napoli",
    "sg:orig_category":"Forniture Per Edilizia E Lavori Pubblici. Prodotti Vari In Metallo",
    "sg:phone":"+39 081 586 0090",
    "sg:postcode":"80016",
    "sg:province":"Napoli",
    "wof:name":"Ponteggi Frau Di Frau Nicola",
    "wof:placetype":"venue"
},
  "geometry": {"coordinates":[14.1919651031,40.8933906555],"type":"Point"}
}