{
  "type": "Feature",
  "properties": {
    "addr:full":"11, Via Nuova 10061 Cavour Cavour Torino 10061",
    "addr:postcode":"10061;10061",
    "addr:street":"Via Nuova",
    "iso:country":"IT",
    "sg:address":"11, Via Nuova 10061 Cavour",
    "sg:city":"Cavour",
    "sg:classifiers":[
        {
            "category":"Parking",
            "subcategory":"Lot",
            "type":"Transportation"
        }
    ],
    "sg:phone":"+39 390 121 6496",
    "sg:postcode":"10061",
    "sg:province":"Torino",
    "sg:tags":[
        "transport",
        "road"
    ],
    "wof:name":"Fratelli Rostan (s.r.l.)",
    "wof:placetype":"venue"
},
  "geometry": {"coordinates":[7.378839,44.790421],"type":"Point"}
}