{
  "type": "Feature",
  "properties": {
    "addr:full":"20123 Milano Milano Milano 20123",
    "addr:postcode":"20123;20123",
    "iso:country":"IT",
    "sg:address":"20123 Milano",
    "sg:city":"Milano",
    "sg:orig_category":"Scuole E Servizi Scolastici",
    "sg:phone":"+39 02 5810 5564",
    "sg:postcode":"20123",
    "sg:province":"Milano",
    "wof:name":"Istituto Leopardi S.r.l.",
    "wof:placetype":"venue"
},
  "geometry": {"coordinates":[9.174059,45.458214],"type":"Point"}
}