{
  "type": "Feature",
  "properties": {
    "addr:full":"62012 Civitanova Marche Civitanova Marche Macerata 62012",
    "addr:postcode":"62012;62012",
    "iso:country":"IT",
    "sg:address":"62012 Civitanova Marche",
    "sg:city":"Civitanova Marche",
    "sg:orig_category":"Calzaturifici E Calzolai - Forniture",
    "sg:phone":"+39 0733 814500",
    "sg:postcode":"62012",
    "sg:province":"Macerata",
    "sg:website":"http://www.labelsystem.com",
    "wof:name":"Etichettificio Label Sistem Srl",
    "wof:placetype":"venue"
},
  "geometry": {"coordinates":[13.705912,43.292931],"type":"Point"}
}