{
  "type": "Feature",
  "properties": {
    "iso:country":"IT",
    "sg:address":"58100 Grosseto",
    "sg:city":"Grosseto",
    "sg:orig_category":"Agenzie D'affari E Servizi Commerciali. Servizi Per Aziende, Manifestazioni E Supporto Agli Scambi Commerciali. Acqua, Luce, Gas E Societa' Di Esercizio Pubblico",
    "sg:phone":"+39 0564 430111",
    "sg:postcode":"58100",
    "sg:province":"Grosseto",
    "wof:name":"Camera Di Commercio Industria Artigianato Agricoltura Grosseto",
    "wof:placetype":"venue"
},
  "geometry": {"coordinates":[11.113504,42.761555],"type":"Point"}
}