{
  "type": "Feature",
  "properties": {
    "iso:country":"IT",
    "sg:address":"10053 Bussoleno",
    "sg:city":"Bussoleno",
    "sg:orig_category":"Pubblica Amministrazione",
    "sg:phone":"+39 0122 642800",
    "sg:postcode":"10053",
    "sg:province":"Torino",
    "wof:name":"Comunita' Montana Bassa Valle Di Susa E Val Cenischia",
    "wof:placetype":"venue"
},
  "geometry": {"coordinates":[7.1431455612,45.1375236511],"type":"Point"}
}