{
  "type": "Feature",
  "properties": {
    "iso:country":"IT",
    "sg:address":"Via Carego' 14 - Crosio Della Valle 21020 Daverio",
    "sg:city":"Crosio della Valle",
    "sg:orig_category":"Vertical Turning Lathes",
    "sg:phone":"+39 0332 966110",
    "sg:postcode":"21020",
    "sg:province":"Varese",
    "sg:website":"www.imtintermato.it",
    "wof:name":"Imt Intermato S.p.a.",
    "wof:placetype":"venue"
},
  "geometry": {"coordinates":[8.765436,45.761471],"type":"Point"}
}