{
  "type": "Feature",
  "properties": {
    "iso:country":"IT",
    "sg:address":"35042 Este",
    "sg:city":"Este",
    "sg:orig_category":"Nautica. Forniture Per Attivita' Commerciali Ed Artigianali",
    "sg:phone":"+39 0429 55965",
    "sg:postcode":"35042",
    "sg:province":"Padova",
    "wof:name":"Magon Mirco - Nord Est Avvolgibili",
    "wof:placetype":"venue"
},
  "geometry": {"coordinates":[11.695925,45.216591],"type":"Point"}
}