{
  "type": "Feature",
  "properties": {
    "addr:full":"84016 Pagani Pagani Salerno 84016",
    "addr:postcode":"84016;84016",
    "iso:country":"IT",
    "sg:address":"84016 Pagani",
    "sg:city":"Pagani",
    "sg:orig_category":"Servizi E Lavori Per Industria Alimentare E Bevande",
    "sg:phone":"+39 081 954139",
    "sg:postcode":"84016",
    "sg:province":"Salerno",
    "wof:name":"Europa 95 Srl",
    "wof:placetype":"venue"
},
  "geometry": {"coordinates":[14.618696,40.755455],"type":"Point"}
}