{
  "type": "Feature",
  "properties": {
    "iso:country":"IT",
    "sg:address":"Strada Della Repubblica 4/a; Parma; 43100",
    "sg:city":"Parma",
    "sg:classifiers":[
        {
            "category":"Banks & Credit Unions",
            "subcategory":"Bank",
            "type":"Services"
        }
    ],
    "sg:phone":"+39 0521 208051",
    "sg:postcode":"43100",
    "sg:province":"Parma",
    "wof:name":"Credito Italiano Spa",
    "wof:placetype":"venue"
},
  "geometry": {"coordinates":[10.32911,44.801224],"type":"Point"}
}