{
  "type": "Feature",
  "properties": {
    "iso:country":"IT",
    "sg:address":"70122 Bari",
    "sg:city":"Bari",
    "sg:orig_category":"Articoli Da Regalo. Hobbistica. Shopping",
    "sg:phone":"+39 080 523 2094",
    "sg:postcode":"70122",
    "sg:province":"Bari",
    "wof:name":"Golden Side",
    "wof:placetype":"venue"
},
  "geometry": {"coordinates":[16.870203,41.125751],"type":"Point"}
}