{
  "type": "Feature",
  "properties": {
    "iso:country":"IT",
    "sg:address":"18038 Sanremo",
    "sg:orig_category":"Abbigliamento Esterno, Maglierie E Pelliccerie. Calzature, Pelletterie E Pelli. Shopping",
    "sg:phone":"+39 0184 504349",
    "sg:postcode":"18038",
    "sg:province":"Imperia",
    "wof:name":"Pellicceria Karina",
    "wof:placetype":"venue"
},
  "geometry": {"coordinates":[7.77427,43.841179],"type":"Point"}
}