{
  "type": "Feature",
  "properties": {
    "iso:country":"IT",
    "sg:address":"00046 Grottaferrata",
    "sg:city":"Grottaferrata",
    "sg:orig_category":"Chiese Ed Associazioni Religiose",
    "sg:phone":"+39 06 941 2059",
    "sg:postcode":"00046",
    "sg:province":"Roma",
    "wof:name":"D'armi Lino",
    "wof:placetype":"venue"
},
  "geometry": {"coordinates":[12.673301,41.784138],"type":"Point"}
}