{
  "type": "Feature",
  "properties": {
    "iso:country":"IT",
    "sg:address":"50019 Sesto Fiorentino",
    "sg:city":"Sesto Fiorentino",
    "sg:orig_category":"Elettrotecnica",
    "sg:phone":"+39 055 421 0551",
    "sg:postcode":"50019",
    "sg:province":"Firenze",
    "wof:name":"Uni Lamp Srl",
    "wof:placetype":"venue"
},
  "geometry": {"coordinates":[11.191278,43.841381],"type":"Point"}
}