{
  "type": "Feature",
  "properties": {
    "iso:country":"IT",
    "sg:address":"12, Via Cancelliera 00040 Ariccia",
    "sg:city":"Ariccia",
    "sg:classifiers":[
        {
            "category":"Wholesale",
            "subcategory":"Drugs",
            "type":"Manufacturing & Wholesale Goods"
        }
    ],
    "sg:phone":"+39 39069345406",
    "sg:postcode":"00040",
    "sg:province":"Roma",
    "sg:tags":[
        "chemical",
        "pharmaceutical"
    ],
    "wof:name":"Medosan Ricerca Srl",
    "wof:placetype":"venue"
},
  "geometry": {"coordinates":[12.630213,41.714863],"type":"Point"}
}