{
  "type": "Feature",
  "properties": {
    "addr:full":"32, Via Vittorio Veneto 28922 Verbania Verbania Verbano-Cusio-Ossola 28922",
    "addr:postcode":"28922;28922",
    "addr:street":"Via Vittorio Veneto",
    "iso:country":"IT",
    "sg:address":"32, Via Vittorio Veneto 28922 Verbania",
    "sg:city":"Verbania",
    "sg:classifiers":[
        {
            "category":"Travel",
            "subcategory":"Travel Agent",
            "type":"Entertainment"
        }
    ],
    "sg:phone":"+39 0323 504261",
    "sg:postcode":"28922",
    "sg:province":"Verbano-Cusio-Ossola",
    "sg:tags":[
        "business"
    ],
    "wof:name":"Albergo Astor Hotel",
    "wof:placetype":"venue"
},
  "geometry": {"coordinates":[8.557554,45.917622],"type":"Point"}
}