{
  "type": "Feature",
  "properties": {
    "addr:full":"2, Via Nuvolari Tazio 41053 Maranello Maranello Modena 41053",
    "addr:postcode":"41053;41053",
    "addr:street":"Via Nuvolari Tazio",
    "iso:country":"IT",
    "sg:address":"2, Via Nuvolari Tazio 41053 Maranello",
    "sg:city":"Maranello",
    "sg:classifiers":[
        {
            "category":"Shopping",
            "subcategory":"Crafts & Fabrics",
            "type":"Retail Goods"
        }
    ],
    "sg:phone":"+39 0536 943944",
    "sg:postcode":"41053",
    "sg:province":"Modena",
    "sg:tags":[
        "ceramic"
    ],
    "wof:name":"Studiolive Srl",
    "wof:placetype":"venue"
},
  "geometry": {"coordinates":[10.86857,44.534241],"type":"Point"}
}