{
  "type": "Feature",
  "properties": {
    "iso:country":"IT",
    "sg:address":"20021 Bollate",
    "sg:city":"Bollate",
    "sg:orig_category":"Macchine, Impianti E Forniture Per Industria Grafica, Cartaria E Cartotecnica",
    "sg:phone":"+39 02 3830 3230",
    "sg:postcode":"20021",
    "sg:province":"Milano",
    "wof:name":"A.r.t.e.a. Snc",
    "wof:placetype":"venue"
},
  "geometry": {"coordinates":[9.093642,45.542805],"type":"Point"}
}