{
  "type": "Feature",
  "properties": {
    "iso:country":"IT",
    "sg:address":"24040 Boltiere",
    "sg:city":"Boltiere",
    "sg:orig_category":"Arredo Camera Letto E Complementi",
    "sg:phone":"+39 035 806054",
    "sg:postcode":"24040",
    "sg:province":"Bergamo",
    "sg:website":"http://www.arredamentibertola.it",
    "wof:name":"Arredamenti Bertola",
    "wof:placetype":"venue"
},
  "geometry": {"coordinates":[9.579537,45.601891],"type":"Point"}
}