{
  "type": "Feature",
  "properties": {
    "addr:full":"Via G. Rossa 2 40056 Crespellano Crespellano Bologna 40056",
    "addr:housenumber":"2",
    "addr:postcode":"40056;40056",
    "addr:street":"Via G. Rossa",
    "iso:country":"IT",
    "sg:address":"Via G. Rossa 2 40056 Crespellano",
    "sg:city":"Crespellano",
    "sg:orig_category":"Floor Sealing Products",
    "sg:phone":"+39 051 969068",
    "sg:postcode":"40056",
    "sg:province":"Bologna",
    "sg:website":"www.pigal.it",
    "wof:name":"Pigal Spa",
    "wof:placetype":"venue"
},
  "geometry": {"coordinates":[11.3464813232,44.4942207336],"type":"Point"}
}