{
  "type": "Feature",
  "properties": {
    "iso:country":"IT",
    "sg:address":"1/d, Via Lago 38038 Tesero",
    "sg:city":"Tesero",
    "sg:classifiers":[
        {
            "category":"Manufacturing",
            "subcategory":"Rubber & Plastics",
            "type":"Manufacturing & Wholesale Goods"
        }
    ],
    "sg:phone":"+39 0462 814745",
    "sg:postcode":"38038",
    "sg:province":"Trento",
    "wof:name":"Frade (s.r.l.)",
    "wof:placetype":"venue"
},
  "geometry": {"coordinates":[11.5190544128,46.2829360962],"type":"Point"}
}