{
  "type": "Feature",
  "properties": {
    "iso:country":"IT",
    "sg:address":"20144 Milano",
    "sg:city":"Milano",
    "sg:orig_category":"Cartotecnica E Servizi. Forniture Per Uffici",
    "sg:phone":"+39 02 498 1622",
    "sg:postcode":"20144",
    "sg:province":"Milano",
    "wof:name":"Shades International Srl",
    "wof:placetype":"venue"
},
  "geometry": {"coordinates":[9.156268,45.465195],"type":"Point"}
}