{
  "type": "Feature",
  "properties": {
    "addr:full":"00159 Roma Roma Roma 00159",
    "addr:postcode":"00159;00159",
    "iso:country":"IT",
    "sg:address":"00159 Roma",
    "sg:city":"Roma",
    "sg:classifiers":[
        {
            "category":"Professional",
            "subcategory":"Advertising",
            "type":"Services"
        }
    ],
    "sg:phone":"+39 06 439 3130",
    "sg:postcode":"00159",
    "sg:province":"Roma",
    "sg:tags":[
        "services",
        "shopping",
        "publishing"
    ],
    "sg:website":"http://www.binacci.it",
    "wof:name":"Binacci Arredamenti Srl",
    "wof:placetype":"venue"
},
  "geometry": {"coordinates":[12.5386314392,41.9083557129],"type":"Point"}
}