{
  "type": "Feature",
  "properties": {
    "iso:country":"IT",
    "sg:address":"74010 Statte",
    "sg:city":"Statte",
    "sg:orig_category":"Frigotecnica, Apparecchiature E Servizi",
    "sg:phone":"+39 099 473 8917",
    "sg:postcode":"74010",
    "sg:province":"Taranto",
    "wof:name":"Nuova Sa.ca. Frigo. Srl",
    "wof:placetype":"venue"
},
  "geometry": {"coordinates":[17.2311782837,40.5462837219],"type":"Point"}
}