{
  "type": "Feature",
  "properties": {
    "iso:country":"IT",
    "sg:address":"15, Via Castellazzo 20010 Pregnana Milanese",
    "sg:city":"Pregnana Milanese",
    "sg:classifiers":[
        {
            "category":"Manufacturing",
            "subcategory":"Paper Products",
            "type":"Manufacturing & Wholesale Goods"
        }
    ],
    "sg:phone":"+39 390 293 2731",
    "sg:postcode":"20010",
    "sg:province":"Milano",
    "sg:tags":[
        "cardboard"
    ],
    "wof:name":"Sacchital S.p.a.",
    "wof:placetype":"venue"
},
  "geometry": {"coordinates":[9.0137796402,45.522769928],"type":"Point"}
}