{
  "type": "Feature",
  "properties": {
    "iso:country":"IT",
    "sg:address":"50144 Firenze",
    "sg:city":"Firenze",
    "sg:orig_category":"Alberghi E Strutture Extra Alberghiere",
    "sg:phone":"+39 055 334041",
    "sg:postcode":"50144",
    "sg:province":"Firenze",
    "sg:website":"http://www.congressmeetingshotels.com",
    "wof:name":"1st Stop Reservation Center Di Bidini Cinzia",
    "wof:placetype":"venue"
},
  "geometry": {"coordinates":[11.226877,43.782269],"type":"Point"}
}