{
  "type": "Feature",
  "properties": {
    "addr:full":"20125 Milano Milano Milano 20125",
    "addr:postcode":"20125;20125",
    "iso:country":"IT",
    "sg:address":"20125 Milano",
    "sg:city":"Milano",
    "sg:orig_category":"Carni, Salumi E Pesci. Zootecnia E Pesca, Allevamento Piccoli Animali",
    "sg:phone":"+39 02 6698 0460",
    "sg:postcode":"20125",
    "sg:province":"Milano",
    "wof:name":"Cismapesca (s.n.c.)",
    "wof:placetype":"venue"
},
  "geometry": {"coordinates":[9.207474,45.49078],"type":"Point"}
}