{
  "type": "Feature",
  "properties": {
    "iso:country":"IT",
    "sg:address":"88060 Satriano",
    "sg:city":"Satriano",
    "sg:classifiers":[
        {
            "category":"Home & Garden",
            "subcategory":"Building Materials",
            "type":"Retail Goods"
        }
    ],
    "sg:phone":"+39 0967 521338",
    "sg:postcode":"88060",
    "sg:province":"Catanzaro",
    "sg:tags":[
        "curtain",
        "furnishing",
        "fabrics",
        "carpet"
    ],
    "sg:website":"http://www.lp-primerano.com",
    "wof:name":"Laboratori Primerano Snc",
    "wof:placetype":"venue"
},
  "geometry": {"coordinates":[16.4820728302,38.6679534912],"type":"Point"}
}