{
  "type": "Feature",
  "properties": {
    "iso:country":"IT",
    "sg:address":"83038 Montemiletto",
    "sg:city":"Montemiletto",
    "sg:orig_category":"Materiali Edili",
    "sg:phone":"+39 0825 963412",
    "sg:postcode":"83038",
    "sg:province":"Avellino",
    "wof:name":"Centrella Vincenzo",
    "wof:placetype":"venue"
},
  "geometry": {"coordinates":[14.909684,41.0005],"type":"Point"}
}