{
  "type": "Feature",
  "properties": {
    "iso:country":"IT",
    "sg:address":"Via Roma 75; Urbe; 17040",
    "sg:classifiers":[
        {
            "category":"Banks & Credit Unions",
            "subcategory":"Bank",
            "type":"Services"
        }
    ],
    "sg:phone":"+39 019 726051",
    "sg:postcode":"17040",
    "sg:province":"Savona",
    "wof:name":"Cassa Risparmio Di Savona",
    "wof:placetype":"venue"
},
  "geometry": {"coordinates":[8.592044,44.488804],"type":"Point"}
}