{
  "type": "Feature",
  "properties": {
    "iso:country":"IT",
    "sg:address":"Via Romaiano 20 56024 Ponte A Egola",
    "sg:city":"Ponte a egola",
    "sg:orig_category":"Harness Leather",
    "sg:phone":"+39 0571 41511",
    "sg:postcode":"56024",
    "sg:province":"Pisa",
    "sg:website":"www.gbcuoio.com",
    "wof:name":"Concerie Riunite G.b. Spa",
    "wof:placetype":"venue"
},
  "geometry": {"coordinates":[10.784959,43.691685],"type":"Point"}
}