{
  "type": "Feature",
  "properties": {
    "iso:country":"IT",
    "sg:address":"202, Viale Monza 20128 Milano",
    "sg:city":"Milano",
    "sg:classifiers":[
        {
            "category":"Wholesale",
            "subcategory":"Medical Equipment & Supplies",
            "type":"Manufacturing & Wholesale Goods"
        }
    ],
    "sg:phone":"+39 02 2700 0351",
    "sg:postcode":"20128",
    "sg:province":"Milano",
    "sg:tags":[
        "-",
        "health",
        "instrument"
    ],
    "wof:name":"Girgom Srl",
    "wof:placetype":"venue"
},
  "geometry": {"coordinates":[9.22409,45.51038],"type":"Point"}
}