{
  "type": "Feature",
  "properties": {
    "iso:country":"IT",
    "sg:address":"87064 Corigliano Calabro",
    "sg:city":"Corigliano Calabro",
    "sg:classifiers":[
        {
            "category":"Shopping",
            "subcategory":"Stationery & Office Supplies",
            "type":"Retail Goods"
        }
    ],
    "sg:phone":"+39 0983 851305",
    "sg:postcode":"87064",
    "sg:province":"Cosenza",
    "sg:tags":[
        "equipment",
        "furniture",
        "furnishing",
        "professional"
    ],
    "sg:website":"http://www.ladycucine.it",
    "wof:name":"Lady Srl",
    "wof:placetype":"venue"
},
  "geometry": {"coordinates":[16.5112705231,39.6276130676],"type":"Point"}
}