{
  "type": "Feature",
  "properties": {
    "iso:country":"IT",
    "sg:address":"49, Corso Della Giovecca 44100 Ferrara",
    "sg:city":"Ferrara",
    "sg:classifiers":[
        {
            "category":"Travel",
            "subcategory":"Travel Agent",
            "type":"Entertainment"
        }
    ],
    "sg:phone":"+39 0532 205456",
    "sg:postcode":"44100",
    "sg:province":"Ferrara",
    "sg:tags":[
        "business"
    ],
    "wof:name":"Alberghi Europa Hotel",
    "wof:placetype":"venue"
},
  "geometry": {"coordinates":[11.6219,44.837231],"type":"Point"}
}