{
  "type": "Feature",
  "properties": {
    "iso:country":"IT",
    "sg:address":"Via Francesco Soave 1 22100 Como",
    "sg:city":"Como",
    "sg:classifiers":[
        {
            "category":"Utilities",
            "subcategory":"Mobile Phone",
            "type":"Services"
        }
    ],
    "sg:phone":"+39 031 530915",
    "sg:postcode":"22100",
    "sg:province":"Como",
    "sg:tags":[
        "battery",
        "operated",
        "clock"
    ],
    "wof:name":"Fabbrica Orologi Cavadini Giuseppe Snc",
    "wof:placetype":"venue"
},
  "geometry": {"coordinates":[9.050122,45.825748],"type":"Point"}
}