{
  "type": "Feature",
  "properties": {
    "iso:country":"IT",
    "sg:address":"20127 Milano",
    "sg:city":"Milano",
    "sg:orig_category":"Valvole E Apparecchiature Di Misura. Elettrotecnica Industriale, Prodotti E Apparecchiature",
    "sg:phone":"+39 02 2611 0643",
    "sg:postcode":"20127",
    "sg:province":"Milano",
    "wof:name":"Ivo Leuze Vogtle Malanca Srl",
    "wof:placetype":"venue"
},
  "geometry": {"coordinates":[9.213197,45.491096],"type":"Point"}
}