{
  "type": "Feature",
  "properties": {
    "iso:country":"IT",
    "sg:address":"41100 Modena",
    "sg:city":"Modena",
    "sg:orig_category":"Pubblica Amministrazione",
    "sg:phone":"+39 059117",
    "sg:postcode":"41100",
    "sg:province":"Modena",
    "wof:name":"Guardia Di Finanza",
    "wof:placetype":"venue"
},
  "geometry": {"coordinates":[10.9285869598,44.646697998],"type":"Point"}
}