{
  "type": "Feature",
  "properties": {
    "iso:country":"IT",
    "sg:address":"97100 Ragusa",
    "sg:city":"Ragusa",
    "sg:orig_category":"Materiali Edili",
    "sg:phone":"+39 0932 652480",
    "sg:postcode":"97100",
    "sg:province":"Ragusa",
    "wof:name":"Inox System Snc",
    "wof:placetype":"venue"
},
  "geometry": {"coordinates":[14.721209,36.920349],"type":"Point"}
}