{
  "type": "Feature",
  "properties": {
    "addr:full":"36028 Rossano Veneto Rossano Veneto Vicenza 36028",
    "addr:postcode":"36028;36028",
    "addr:street":"Veneto",
    "iso:country":"IT",
    "sg:address":"36028 Rossano Veneto",
    "sg:city":"Rossano Veneto",
    "sg:orig_category":"Macchine, Impianti Ed Attrezzature Per Abbigliamento E Pelletterie",
    "sg:phone":"+39 0424 549027",
    "sg:postcode":"36028",
    "sg:province":"Vicenza",
    "wof:name":"Battistella Guerrino E C. (s.n.c.)",
    "wof:placetype":"venue"
},
  "geometry": {"coordinates":[11.812602,45.716518],"type":"Point"}
}