{
  "type": "Feature",
  "properties": {
    "iso:country":"IT",
    "sg:address":"25047 Darfo Boario Terme",
    "sg:city":"Darfo",
    "sg:orig_category":"Impiantistica E Prodotti Tecnologici Per Edilizia. Elettronica Professionale E Di Consumo",
    "sg:phone":"+39 036 453 6168",
    "sg:postcode":"25047",
    "sg:province":"Brescia",
    "wof:name":"Elettrotecnica S.e.l. Srl",
    "wof:placetype":"venue"
},
  "geometry": {"coordinates":[10.190662,45.89587],"type":"Point"}
}