{
  "type": "Feature",
  "properties": {
    "iso:country":"IT",
    "sg:address":"Via Benedetto Zalassi 1/3 Z.i. 53100 Siena",
    "sg:city":"Siena",
    "sg:classifiers":[
        {
            "category":"Banks & Credit Unions",
            "subcategory":"Investment Brokerage",
            "type":"Services"
        }
    ],
    "sg:phone":"+39 0577 247720",
    "sg:postcode":"53100",
    "sg:province":"Siena",
    "sg:tags":[
        "machine",
        "pharmaceutical",
        "cosmetic",
        "apparatus"
    ],
    "wof:name":"Pharmasiena Service Srl",
    "wof:placetype":"venue"
},
  "geometry": {"coordinates":[11.3305139542,43.3186607361],"type":"Point"}
}