{
  "type": "Feature",
  "properties": {
    "iso:country":"IT",
    "sg:address":"20019 Settimo Milanese",
    "sg:city":"Settimo Milanese",
    "sg:orig_category":"Lucernari",
    "sg:phone":"+39 02 3350 0562",
    "sg:postcode":"20019",
    "sg:province":"Milano",
    "wof:name":"Archital Srl",
    "wof:placetype":"venue"
},
  "geometry": {"coordinates":[9.066506,45.468803],"type":"Point"}
}