{
  "type": "Feature",
  "properties": {
    "addr:full":"38017 Mezzolombardo Mezzolombardo Trento 38017",
    "addr:postcode":"38017;38017",
    "iso:country":"IT",
    "sg:address":"38017 Mezzolombardo",
    "sg:city":"Mezzolombardo",
    "sg:classifiers":[
        {
            "category":"Bars & Pubs",
            "subcategory":"Champagne Bar",
            "type":"Food & Drink"
        }
    ],
    "sg:phone":"+39 0461 601038",
    "sg:postcode":"38017",
    "sg:province":"Trento",
    "sg:tags":[
        "caffe'",
        "e"
    ],
    "wof:name":"Bar Ristorante Mirtillo",
    "wof:placetype":"venue"
},
  "geometry": {"coordinates":[11.092855,46.212711],"type":"Point"}
}