{
  "type": "Feature",
  "properties": {
    "iso:country":"IT",
    "sg:address":"12038 Savigliano",
    "sg:city":"Savigliano",
    "sg:orig_category":"Motori Ed Organi Di Trasmissione. Ricambi E Componenti Dei Mezzi Di Trasporto",
    "sg:phone":"+39 0172 715488",
    "sg:postcode":"12038",
    "sg:province":"Cuneo",
    "wof:name":"Agrinova Snc",
    "wof:placetype":"venue"
},
  "geometry": {"coordinates":[7.6765155792,44.6487617493],"type":"Point"}
}