{
  "type": "Feature",
  "properties": {
    "addr:full":"27029 Vigevano Vigevano Pavia 27029",
    "addr:postcode":"27029;27029",
    "iso:country":"IT",
    "sg:address":"27029 Vigevano",
    "sg:city":"Vigevano",
    "sg:orig_category":"Forniture Per Abbigliamento E Pelletterie. Forniture Per Attivita' Commerciali Ed Artigianali",
    "sg:phone":"+39 0381 344109",
    "sg:postcode":"27029",
    "sg:province":"Pavia",
    "wof:name":"Fustellificio Ellepi Snc Di Lo Presti Luigi E C.",
    "wof:placetype":"venue"
},
  "geometry": {"coordinates":[8.8671789169,45.3039894104],"type":"Point"}
}