{
  "type": "Feature",
  "properties": {
    "iso:country":"IT",
    "sg:address":"20146 Milano",
    "sg:city":"Milano",
    "sg:orig_category":"Servizi Ausiliari Dei Mezzi Di Trasporto",
    "sg:phone":"+39 02 469 1630",
    "sg:postcode":"20146",
    "sg:province":"Milano",
    "wof:name":"Leggio Mario",
    "wof:placetype":"venue"
},
  "geometry": {"coordinates":[9.154948,45.460526],"type":"Point"}
}