{
  "type": "Feature",
  "properties": {
    "iso:country":"IT",
    "sg:address":"33100 Udine",
    "sg:city":"Udine",
    "sg:orig_category":"Ospedali E Servizi Sanitari",
    "sg:phone":"+39 0432 204888",
    "sg:postcode":"33100",
    "sg:province":"Udine",
    "wof:name":"Studio Medico Sinicco Dr. Giovanna",
    "wof:placetype":"venue"
},
  "geometry": {"coordinates":[13.238317,46.063122],"type":"Point"}
}