{
  "type": "Feature",
  "properties": {
    "iso:country":"IT",
    "sg:address":"20037 Paderno Dugnano",
    "sg:city":"Paderno Dugnano",
    "sg:orig_category":"Arte Ed Artigianato Artistico",
    "sg:phone":"+39 02 9904 9663",
    "sg:postcode":"20037",
    "sg:province":"Milano",
    "wof:name":"Lainati Giorgio",
    "wof:placetype":"venue"
},
  "geometry": {"coordinates":[9.148685,45.572369],"type":"Point"}
}