{
  "type": "Feature",
  "properties": {
    "addr:full":"73012 Campi Salentina Campi Salentina Lecce 73012",
    "addr:postcode":"73012;73012",
    "iso:country":"IT",
    "sg:address":"73012 Campi Salentina",
    "sg:city":"Campi Salentina",
    "sg:orig_category":"Articoli Da Regalo. Forniture Per Attivita' Commerciali Ed Artigianali",
    "sg:phone":"+39 0832 792613",
    "sg:postcode":"73012",
    "sg:province":"Lecce",
    "wof:name":"Il Mondo Dei Fiori Srl",
    "wof:placetype":"venue"
},
  "geometry": {"coordinates":[18.03879,40.395985],"type":"Point"}
}