{
  "type": "Feature",
  "properties": {
    "iso:country":"IT",
    "sg:address":"28062 Cameri",
    "sg:city":"Cameri",
    "sg:orig_category":"Termotecnica E Riscaldamento, Apparecchiature E Servizi",
    "sg:phone":"+39 0321 518328",
    "sg:postcode":"28062",
    "sg:province":"Novara",
    "wof:name":"Vapor Nova (s.n.c.)",
    "wof:placetype":"venue"
},
  "geometry": {"coordinates":[8.657999,45.502205],"type":"Point"}
}