{
  "type": "Feature",
  "properties": {
    "addr:full":"Strada Statale 98, Km 80,100 70026 Modugno Modugno Bari 70026",
    "addr:housenumber":"km 80,100",
    "addr:postcode":"70026;70026",
    "addr:street":"Strada Statale 98",
    "iso:country":"IT",
    "sg:address":"Strada Statale 98, Km 80,100 70026 Modugno",
    "sg:city":"Modugno",
    "sg:classifiers":[
        {
            "category":"Parking",
            "subcategory":"Lot",
            "type":"Transportation"
        }
    ],
    "sg:phone":"+39 080 535 8782",
    "sg:postcode":"70026",
    "sg:province":"Bari",
    "sg:tags":[
        "pot",
        "cooking",
        "enamelled"
    ],
    "sg:website":"www.casavivalife.com",
    "wof:name":"Casaviva Life Srl",
    "wof:placetype":"venue"
},
  "geometry": {"coordinates":[16.869291,41.126053],"type":"Point"}
}