{
  "type": "Feature",
  "properties": {
    "addr:full":"20153 Milano Milano Milano 20153",
    "addr:postcode":"20153;20153",
    "iso:country":"IT",
    "sg:address":"20153 Milano",
    "sg:city":"Milano",
    "sg:orig_category":"Prodotti Finiti Stampati. Forniture E Materiali Per Imballaggio E Confezionamento. Forniture Per Attivita' Commerciali Ed Artigianali",
    "sg:phone":"+39 02 4820 1705",
    "sg:postcode":"20153",
    "sg:province":"Milano",
    "wof:name":"Vi.pa. Di Barbaglia Patrizia",
    "wof:placetype":"venue"
},
  "geometry": {"coordinates":[9.1612615585,45.4684066772],"type":"Point"}
}