{
  "type": "Feature",
  "properties": {
    "iso:country":"IT",
    "sg:address":"44022 Comacchio",
    "sg:city":"Comacchio",
    "sg:orig_category":"Agenzie Marittime",
    "sg:phone":"+39 348 415 2027",
    "sg:postcode":"44022",
    "sg:province":"Ferrara",
    "wof:name":"Tino Service Di Carletti Agostino",
    "wof:placetype":"venue"
},
  "geometry": {"coordinates":[12.240963,44.670483],"type":"Point"}
}