{
  "type": "Feature",
  "properties": {
    "iso:country":"IT",
    "sg:address":"28/h, Via Citta' 2000 87100 Cosenza",
    "sg:city":"Cosenza",
    "sg:classifiers":[
        {
            "category":"Shopping",
            "subcategory":"Stationery & Office Supplies",
            "type":"Retail Goods"
        }
    ],
    "sg:phone":"+39 39098438347",
    "sg:postcode":"87100",
    "sg:province":"Cosenza",
    "sg:tags":[
        "professional"
    ],
    "wof:name":"Porcaro & C.(s.r.l.)",
    "wof:placetype":"venue"
},
  "geometry": {"coordinates":[16.2538089752,39.2982635498],"type":"Point"}
}