{
  "type": "Feature",
  "properties": {
    "iso:country":"IT",
    "sg:address":"56030 Perignano",
    "sg:orig_category":"Prodotti E Manufatti In Materie Plastiche",
    "sg:phone":"+39 0587 616202",
    "sg:postcode":"56030",
    "sg:province":"Pisa",
    "wof:name":"I.l.m.e. S.r.l.",
    "wof:placetype":"venue"
},
  "geometry": {"coordinates":[10.4286832809,43.7079391479],"type":"Point"}
}