{
  "type": "Feature",
  "properties": {
    "iso:country":"IT",
    "sg:address":"10036 Settimo Torinese",
    "sg:city":"Settimo Torinese",
    "sg:orig_category":"Abbigliamento Esterno, Maglierie E Pelliccerie. Calzature, Pelletterie E Pelli",
    "sg:phone":"+39 011 898 2522",
    "sg:postcode":"10036",
    "sg:province":"Torino",
    "wof:name":"Week End Srl",
    "wof:placetype":"venue"
},
  "geometry": {"coordinates":[7.742941,45.128586],"type":"Point"}
}