{
  "type": "Feature",
  "properties": {
    "addr:full":"20123 Milano Milano Milano 20123",
    "addr:postcode":"20123;20123",
    "iso:country":"IT",
    "sg:address":"20123 Milano",
    "sg:city":"Milano",
    "sg:orig_category":"Studi E Consulenze Amministrative, Commerciali E Aziendali. Studi E Consulenze Tecniche E Industriali. Consulenze Tecniche, Amministrative E Perizie",
    "sg:phone":"+39 02 8699 6653",
    "sg:postcode":"20123",
    "sg:province":"Milano",
    "wof:name":"Asstech Italia Srl",
    "wof:placetype":"venue"
},
  "geometry": {"coordinates":[9.188788,45.462734],"type":"Point"}
}