{
  "type": "Feature",
  "properties": {
    "addr:full":"40069 Zola Predosa Zola Bologna 40069",
    "addr:postcode":"40069;40069",
    "iso:country":"IT",
    "sg:address":"40069 Zola Predosa",
    "sg:city":"Zola",
    "sg:orig_category":"Apparecchi, Attrezzature E Forniture Per Centri Estetici",
    "sg:phone":"+39 051 752044",
    "sg:postcode":"40069",
    "sg:province":"Bologna",
    "wof:name":"Aestetica Srl",
    "wof:placetype":"venue"
},
  "geometry": {"coordinates":[11.23728,44.501251],"type":"Point"}
}