{
  "type": "Feature",
  "properties": {
    "iso:country":"IT",
    "sg:address":"00049 Velletri",
    "sg:city":"Velletri",
    "sg:orig_category":"Autoaccessori - Commercio",
    "sg:phone":"+39 06 963 7455",
    "sg:postcode":"00049",
    "sg:province":"Roma",
    "wof:name":"Emmeffe Auto",
    "wof:placetype":"venue"
},
  "geometry": {"coordinates":[12.772668,41.68578],"type":"Point"}
}