{
  "type": "Feature",
  "properties": {
    "addr:full":"20, Via Don A. Jula 35037 Teolo Teolo Padova 35037",
    "addr:postcode":"35037;35037",
    "addr:street":"Via Don A. Jula",
    "iso:country":"IT",
    "sg:address":"20, Via Don A. Jula 35037 Teolo",
    "sg:city":"Teolo",
    "sg:classifiers":[
        {
            "category":"Manufacturing",
            "subcategory":"Metals",
            "type":"Manufacturing & Wholesale Goods"
        }
    ],
    "sg:phone":"+39 049 990 0162",
    "sg:postcode":"35037",
    "sg:province":"Padova",
    "sg:tags":[
        "metallurgy",
        "metalworking"
    ],
    "wof:name":"Frabo (s.r.l.)",
    "wof:placetype":"venue"
},
  "geometry": {"coordinates":[11.8765888214,45.4095687866],"type":"Point"}
}