{
  "type": "Feature",
  "properties": {
    "addr:full":"20068 Peschiera Borromeo Peschiera Borromeo Milano 20068",
    "addr:postcode":"20068;20068",
    "iso:country":"IT",
    "sg:address":"20068 Peschiera Borromeo",
    "sg:city":"Peschiera Borromeo",
    "sg:orig_category":"Tempo Libero - Articoli E Forniture. Forniture Per Congressi, Fiere E Manifestazioni. Regalistica Aziendale",
    "sg:phone":"+39 02 5530 5425",
    "sg:postcode":"20068",
    "sg:province":"Milano",
    "wof:name":"Becam Snc Di Bedusi Valter & Camerini Osvaldo",
    "wof:placetype":"venue"
},
  "geometry": {"coordinates":[9.288527,45.431061],"type":"Point"}
}