{
  "type": "Feature",
  "properties": {
    "iso:country":"IT",
    "sg:address":"Via Cave 1 28831 Baveno",
    "sg:city":"Baveno",
    "sg:classifiers":[
        {
            "category":"Home & Garden",
            "subcategory":"Household Appliances",
            "type":"Retail Goods"
        }
    ],
    "sg:phone":"+39 0323 924115",
    "sg:postcode":"28831",
    "sg:province":"Verbano-Cusio-Ossola",
    "sg:tags":[
        "implement",
        "gardening",
        "tool"
    ],
    "sg:website":"www.generalgarden.it",
    "wof:name":"General Garden Srl",
    "wof:placetype":"venue"
},
  "geometry": {"coordinates":[8.272465,46.139969],"type":"Point"}
}