{
  "type": "Feature",
  "properties": {
    "iso:country":"IT",
    "sg:address":"63012 Cupra Marittima",
    "sg:city":"Cupra Marittima",
    "sg:orig_category":"Componenti Elettronici",
    "sg:phone":"+39 0735 778350",
    "sg:postcode":"63012",
    "sg:province":"Ascoli Piceno",
    "wof:name":"Elettromeccanica Piersimoni Di Piersimoni Simone, Sgrilli Rito & C. Snc",
    "wof:placetype":"venue"
},
  "geometry": {"coordinates":[13.843897,43.035278],"type":"Point"}
}