{
  "type": "Feature",
  "properties": {
    "iso:country":"IT",
    "sg:address":"54011 Aulla",
    "sg:city":"Aulla",
    "sg:classifiers":[
        {
            "category":"Health Services",
            "subcategory":"Nursing And Care Facility",
            "type":"Services"
        }
    ],
    "sg:phone":"+39 0187 421731",
    "sg:postcode":"54011",
    "sg:province":"Massa-Carrara",
    "sg:tags":[
        "case",
        "riposo",
        "di"
    ],
    "wof:name":"Gestione Case Di Cura Sanatrix Srl",
    "wof:placetype":"venue"
},
  "geometry": {"coordinates":[9.970749,44.210735],"type":"Point"}
}