{
  "type": "Feature",
  "properties": {
    "addr:full":"20024 Garbagnate Milanese Garbagnate Milanese Milano 20024",
    "addr:postcode":"20024;20024",
    "iso:country":"IT",
    "sg:address":"20024 Garbagnate Milanese",
    "sg:city":"Garbagnate Milanese",
    "sg:orig_category":"Scuole E Servizi Scolastici. Servizi Vari Di Interesse Pubblico",
    "sg:phone":"+39 02 995 5251",
    "sg:postcode":"20024",
    "sg:province":"Milano",
    "wof:name":"Asilo Nido",
    "wof:placetype":"venue"
},
  "geometry": {"coordinates":[9.03254,45.526024],"type":"Point"}
}