{
  "type": "Feature",
  "properties": {
    "iso:country":"IT",
    "sg:address":"89047 Roccella Jonica",
    "sg:orig_category":"Apparecchiature E Sistemi Per Magazzinaggio E Movimentazione",
    "sg:phone":"+39 0964 86001",
    "sg:postcode":"89047",
    "sg:province":"Reggio Di Calabria",
    "wof:name":"Circosta Vincenzo V.i. Srl",
    "wof:placetype":"venue"
},
  "geometry": {"coordinates":[15.650137,38.114689],"type":"Point"}
}