{
  "type": "Feature",
  "properties": {
    "addr:full":"33010 Pagnacco Pagnacco Udine 33010",
    "addr:postcode":"33010;33010",
    "iso:country":"IT",
    "sg:address":"33010 Pagnacco",
    "sg:city":"Pagnacco",
    "sg:orig_category":"Macchine, Impianti E Forniture Per Industria Grafica, Cartaria E Cartotecnica. Automazione E Macchine Per Ufficio",
    "sg:phone":"+39 0432 650165",
    "sg:postcode":"33010",
    "sg:province":"Udine",
    "wof:name":"Pevere Nicola",
    "wof:placetype":"venue"
},
  "geometry": {"coordinates":[13.184323,46.129837],"type":"Point"}
}