{
  "type": "Feature",
  "properties": {
    "iso:country":"IT",
    "sg:address":"35025 Cartura",
    "sg:city":"Cartura",
    "sg:orig_category":"Riparazione Dei Mezzi Di Trasporto",
    "sg:phone":"+39 049 955 5479",
    "sg:postcode":"35025",
    "sg:province":"Padova",
    "wof:name":"Carrozzeria Barison Snc",
    "wof:placetype":"venue"
},
  "geometry": {"coordinates":[11.864575,45.282181],"type":"Point"}
}