{
  "type": "Feature",
  "properties": {
    "iso:country":"IT",
    "sg:address":"Via Meucci Antonio 7 37135 Verona",
    "sg:city":"Verona",
    "sg:classifiers":[
        {
            "category":"Shopping",
            "subcategory":"Photographic Equipment",
            "type":"Retail Goods"
        }
    ],
    "sg:phone":"+39 045 878 1531",
    "sg:postcode":"37135",
    "sg:province":"Verona",
    "sg:tags":[
        "photo-lithography"
    ],
    "wof:name":"Live Scan Srl",
    "wof:placetype":"venue"
},
  "geometry": {"coordinates":[10.9732503891,45.4047012329],"type":"Point"}
}