{
  "type": "Feature",
  "properties": {
    "addr:full":"37066 Sommacampagna Sommacampagna Verona 37066",
    "addr:postcode":"37066;37066",
    "iso:country":"IT",
    "sg:address":"37066 Sommacampagna",
    "sg:city":"Sommacampagna",
    "sg:orig_category":"Pubblicita', Marketing E Comunicazione",
    "sg:phone":"+39 045 858 1718",
    "sg:postcode":"37066",
    "sg:province":"Verona",
    "wof:name":"Cdn Pressing Sas",
    "wof:placetype":"venue"
},
  "geometry": {"coordinates":[10.8872566223,45.4102478027],"type":"Point"}
}