{
  "type": "Feature",
  "properties": {
    "addr:full":"00040 Pomezia Pomezia Roma 00040",
    "addr:postcode":"00040;roma 00040",
    "iso:country":"IT",
    "sg:address":"00040 Pomezia",
    "sg:city":"Pomezia",
    "sg:orig_category":"Forniture Per Uffici",
    "sg:phone":"+39 06 9162 3044",
    "sg:postcode":"00040",
    "sg:province":"Roma",
    "sg:website":"http://www.semper.it",
    "wof:name":"Semper Srl",
    "wof:placetype":"venue"
},
  "geometry": {"coordinates":[12.549574852,41.7138748169],"type":"Point"}
}