{
  "type": "Feature",
  "properties": {
    "iso:country":"IT",
    "sg:address":"20010 Cornaredo",
    "sg:city":"Cornaredo",
    "sg:orig_category":"Servizi E Lavori Per Arredamento E Industria Del Legno. Servizi E Lavori Per Edilizia E Lavori Pubblici",
    "sg:phone":"+39 02 936 3110",
    "sg:postcode":"20010",
    "sg:province":"Milano",
    "wof:name":"Cecchetti Giuseppe",
    "wof:placetype":"venue"
},
  "geometry": {"coordinates":[9.030388,45.49728],"type":"Point"}
}