{
  "type": "Feature",
  "properties": {
    "addr:full":"V. Piemonte 86170 Isernia Isernia Isernia 86170",
    "addr:postcode":"86170;86170",
    "addr:street":"Piemonte",
    "iso:country":"IT",
    "sg:address":"V. Piemonte 86170 Isernia",
    "sg:city":"Isernia",
    "sg:classifiers":[
        {
            "category":"Banks & Credit Unions",
            "subcategory":"Financial Services",
            "type":"Services"
        }
    ],
    "sg:phone":"+39 39086526733",
    "sg:postcode":"86170",
    "sg:province":"Isernia",
    "sg:tags":[
        "banking",
        "finance",
        "insurance"
    ],
    "sg:website":"http://www.servicenetwork.it",
    "wof:name":"Galasso Fernando",
    "wof:placetype":"venue"
},
  "geometry": {"coordinates":[14.239739,41.596073],"type":"Point"}
}