{
  "type": "Feature",
  "properties": {
    "iso:country":"IT",
    "sg:address":"31036 Istrana",
    "sg:city":"Istrana",
    "sg:orig_category":"Macchine, Impianti E Forniture Per Industria Grafica, Cartaria E Cartotecnica",
    "sg:phone":"+39 0422 730803",
    "sg:postcode":"31036",
    "sg:province":"Treviso",
    "wof:name":"Galloni Alessandro",
    "wof:placetype":"venue"
},
  "geometry": {"coordinates":[12.254557,45.672398],"type":"Point"}
}