{
  "type": "Feature",
  "properties": {
    "iso:country":"IT",
    "sg:address":"09131 Cagliari",
    "sg:city":"Cagliari",
    "sg:classifiers":[
        {
            "category":"Structure",
            "subcategory":"Factory",
            "type":"Public Place"
        }
    ],
    "sg:phone":"+39 070 503707",
    "sg:postcode":"09131",
    "sg:province":"Cagliari",
    "sg:tags":[
        "steelworks",
        "foundry"
    ],
    "wof:name":"La Nuova Fucina",
    "wof:placetype":"venue"
},
  "geometry": {"coordinates":[9.121222,39.237377],"type":"Point"}
}