{
  "type": "Feature",
  "properties": {
    "addr:full":"36060 Romano D'ezzelino Vicenza 36060",
    "addr:postcode":"36060;36060",
    "iso:country":"IT",
    "sg:address":"36060 Romano D'ezzelino",
    "sg:orig_category":"Prodotti E Manufatti In Materie Plastiche",
    "sg:phone":"+39 0424 513510",
    "sg:postcode":"36060",
    "sg:province":"Vicenza",
    "wof:name":"Idealplast S.r.l.",
    "wof:placetype":"venue"
},
  "geometry": {"coordinates":[11.749876976,45.7597045898],"type":"Point"}
}