{
  "type": "Feature",
  "properties": {
    "addr:full":"35, Strada Statale Adriatica Nord 60019 Senigallia Senigallia Ancona 60019",
    "addr:postcode":"60019;60019",
    "addr:street":"Strada Statale Adriatica Nord",
    "iso:country":"IT",
    "sg:address":"35, Strada Statale Adriatica Nord 60019 Senigallia",
    "sg:city":"Senigallia",
    "sg:classifiers":[
        {
            "category":"Manufacturing",
            "subcategory":"Paper Products",
            "type":"Manufacturing & Wholesale Goods"
        }
    ],
    "sg:phone":"+39 390 716 6061",
    "sg:postcode":"60019",
    "sg:province":"Ancona",
    "sg:tags":[
        "cardboard"
    ],
    "wof:name":"Fiorini Industrial Packaging S.r.l.",
    "wof:placetype":"venue"
},
  "geometry": {"coordinates":[13.1894054413,43.7364425659],"type":"Point"}
}