{
  "type": "Feature",
  "properties": {
    "iso:country":"IT",
    "sg:address":"90134 Palermo",
    "sg:city":"Palermo",
    "sg:orig_category":"Macchine, Impianti Ed Attrezzature Per Abbigliamento E Pelletterie",
    "sg:phone":"+39 091 651 7162",
    "sg:postcode":"90134",
    "sg:province":"Palermo",
    "wof:name":"Fernandez Giovanni",
    "wof:placetype":"venue"
},
  "geometry": {"coordinates":[13.359552,38.108833],"type":"Point"}
}