{
  "type": "Feature",
  "properties": {
    "iso:country":"IT",
    "sg:address":"Viale Quattro; Arzignano",
    "sg:classifiers":[
        {
            "category":"Banks & Credit Unions",
            "subcategory":"Bank",
            "type":"Services"
        }
    ],
    "sg:phone":"+39 0444 451842",
    "wof:name":"Banca Di Roma",
    "wof:placetype":"venue"
},
  "geometry": {"coordinates":[11.33912,45.519527],"type":"Point"}
}