{
  "type": "Feature",
  "properties": {
    "iso:country":"IT",
    "sg:address":"00153 Roma",
    "sg:city":"Roma",
    "sg:orig_category":"Assicurazioni",
    "sg:phone":"+39 06 575 8751",
    "sg:postcode":"00153",
    "sg:province":"Roma",
    "wof:name":"Assitekna Srl",
    "wof:placetype":"venue"
},
  "geometry": {"coordinates":[12.475321,41.881931],"type":"Point"}
}