{
  "type": "Feature",
  "properties": {
    "iso:country":"IT",
    "sg:address":"7, Via Buricchi Fratelli 59021 Vaiano",
    "sg:city":"Vaiano",
    "sg:classifiers":[
        {
            "category":"Professional",
            "subcategory":"Engineering",
            "type":"Services"
        }
    ],
    "sg:phone":"+39 0574 989131",
    "sg:postcode":"59021",
    "sg:province":"Prato",
    "sg:tags":[
        "machine",
        "-",
        "mechanical"
    ],
    "wof:name":"Gavazzi S.a.s. Di Gavazzi Aldo & C.",
    "wof:placetype":"venue"
},
  "geometry": {"coordinates":[11.126768,43.959995],"type":"Point"}
}