{
  "type": "Feature",
  "properties": {
    "addr:full":"8, Via Dell' Industria 20040 Bellusco Bellusco Milano 20040",
    "addr:postcode":"20040;20040",
    "addr:street":"Via Dell ' Industria",
    "iso:country":"IT",
    "sg:address":"8, Via Dell' Industria 20040 Bellusco",
    "sg:city":"Bellusco",
    "sg:classifiers":[
        {
            "category":"Manufacturing",
            "subcategory":"Rubber & Plastics",
            "type":"Manufacturing & Wholesale Goods"
        }
    ],
    "sg:phone":"+39 39039620891",
    "sg:postcode":"20040",
    "sg:province":"Milano",
    "wof:name":"Union Foam Spa",
    "wof:placetype":"venue"
},
  "geometry": {"coordinates":[9.44324,45.614552],"type":"Point"}
}