{
  "type": "Feature",
  "properties": {
    "iso:country":"IT",
    "sg:address":"40067 Rastignano",
    "sg:city":"Pianoro",
    "sg:classifiers":[
        {
            "category":"Professional",
            "subcategory":"Printing & Photocopies",
            "type":"Services"
        }
    ],
    "sg:phone":"+39 051 744818",
    "sg:postcode":"40067",
    "sg:province":"Bologna",
    "sg:tags":[
        "packaging",
        "setting"
    ],
    "wof:name":"Aslay Srl",
    "wof:placetype":"venue"
},
  "geometry": {"coordinates":[11.352322,44.431965],"type":"Point"}
}