{
  "type": "Feature",
  "properties": {
    "iso:country":"IT",
    "sg:address":"80035 Nola",
    "sg:city":"Nola",
    "sg:orig_category":"Macchine Ed Impianti Per Edilizia E Lavori Pubblici",
    "sg:phone":"+39 081 821 0288",
    "sg:postcode":"80035",
    "sg:province":"Napoli",
    "wof:name":"G I M A R - S.r.l.",
    "wof:placetype":"venue"
},
  "geometry": {"coordinates":[14.460505,40.985767],"type":"Point"}
}