{
  "type": "Feature",
  "properties": {
    "addr:full":"13011 Borgosesia Borgosesia Vercelli 13011",
    "addr:postcode":"13011;13011",
    "iso:country":"IT",
    "sg:address":"13011 Borgosesia",
    "sg:city":"Borgosesia",
    "sg:orig_category":"Servizi E Lavori Per Abbigliamento E Pelletterie",
    "sg:phone":"+39 0163 21883",
    "sg:postcode":"13011",
    "sg:province":"Vercelli",
    "wof:name":"Canestro Emilio Ratex",
    "wof:placetype":"venue"
},
  "geometry": {"coordinates":[8.40287,45.33773],"type":"Point"}
}