{
  "type": "Feature",
  "properties": {
    "addr:full":"21056 Induno Olona Induno Olona Varese 21056",
    "addr:postcode":"21056;21056",
    "iso:country":"IT",
    "sg:address":"21056 Induno Olona",
    "sg:city":"Induno Olona",
    "sg:orig_category":"Articoli Medico-sanitari Ed Ortopedici",
    "sg:phone":"+39 0332 200360",
    "sg:postcode":"21056",
    "sg:province":"Varese",
    "wof:name":"Rainhard Riabilitazione Snc",
    "wof:placetype":"venue"
},
  "geometry": {"coordinates":[8.841941,45.838448],"type":"Point"}
}