{
  "type": "Feature",
  "properties": {
    "iso:country":"IT",
    "sg:address":"62012 Civitanova Marche",
    "sg:city":"Civitanova Marche",
    "sg:orig_category":"Avvocati - Studi",
    "sg:phone":"+39 0733 811734",
    "sg:postcode":"62012",
    "sg:province":"Macerata",
    "wof:name":"Lelli Dr. Claudio",
    "wof:placetype":"venue"
},
  "geometry": {"coordinates":[13.727442,43.299561],"type":"Point"}
}