{
  "type": "Feature",
  "properties": {
    "iso:country":"IT",
    "sg:address":"5/i, Viale Mecenate 52100 Arezzo",
    "sg:city":"Arezzo",
    "sg:classifiers":[
        {
            "category":"Wholesale",
            "subcategory":"Medical Equipment & Supplies",
            "type":"Manufacturing & Wholesale Goods"
        }
    ],
    "sg:phone":"+39 39057521412",
    "sg:postcode":"52100",
    "sg:province":"Arezzo",
    "sg:tags":[
        "-",
        "health",
        "instrument"
    ],
    "wof:name":"A.f.m. Spa",
    "wof:placetype":"venue"
},
  "geometry": {"coordinates":[11.863062,43.471203],"type":"Point"}
}