{
  "type": "Feature",
  "properties": {
    "iso:country":"IT",
    "sg:address":"80040 Striano",
    "sg:city":"Striano",
    "sg:orig_category":"Tempo Libero - Articoli E Forniture. Automobili E Mezzi Di Trasporto. Riparazione Dei Mezzi Di Trasporto",
    "sg:phone":"+39 081 865 4745",
    "sg:postcode":"80040",
    "sg:province":"Napoli",
    "wof:name":"Nunziata Moto",
    "wof:placetype":"venue"
},
  "geometry": {"coordinates":[14.525764,40.861984],"type":"Point"}
}