{
  "type": "Feature",
  "properties": {
    "addr:full":"Viale Delle Industrie 21 20040 Cambiago Cambiago Milano 20040",
    "addr:housenumber":"21",
    "addr:postcode":"20040;20040",
    "addr:street":"Viale Delle Industrie",
    "iso:country":"IT",
    "sg:address":"Viale Delle Industrie 21 20040 Cambiago",
    "sg:city":"Cambiago",
    "sg:orig_category":"Cardboard Sleeves, Tubes, Rolls",
    "sg:phone":"+39 02 950 6174",
    "sg:postcode":"20040",
    "sg:province":"Milano",
    "sg:website":"www.bonotubi.it",
    "wof:name":"Bono Imballaggi Spa",
    "wof:placetype":"venue"
},
  "geometry": {"coordinates":[9.434307,45.579643],"type":"Point"}
}