{
  "type": "Feature",
  "properties": {
    "iso:country":"IT",
    "sg:address":"04012 Cisterna Di Latina",
    "sg:city":"Cisterna di Latina",
    "sg:orig_category":"Trattamenti Termici E Superficiali Metalli, Galvanotecnica",
    "sg:phone":"+39 06 968 5513",
    "sg:postcode":"04012",
    "sg:province":"Latina",
    "wof:name":"Laziale Zinco Srl",
    "wof:placetype":"venue"
},
  "geometry": {"coordinates":[12.857932,41.483932],"type":"Point"}
}