{
  "type": "Feature",
  "properties": {
    "iso:country":"IT",
    "sg:address":"9, Via Golgi Camillo 25064 Gussago",
    "sg:city":"Gussago",
    "sg:classifiers":[
        {
            "category":"Professional",
            "subcategory":"Engineering",
            "type":"Services"
        }
    ],
    "sg:phone":"+39 030 373 7105",
    "sg:postcode":"25064",
    "sg:province":"Brescia",
    "sg:tags":[
        "machine",
        "-",
        "mechanical"
    ],
    "wof:name":"Industrial Service Srl",
    "wof:placetype":"venue"
},
  "geometry": {"coordinates":[10.15875,45.558434],"type":"Point"}
}