{
  "type": "Feature",
  "properties": {
    "addr:full":"50124 Firenze Firenze Firenze 50124",
    "addr:postcode":"50124;50124",
    "iso:country":"IT",
    "sg:address":"50124 Firenze",
    "sg:city":"Firenze",
    "sg:orig_category":"Servizi E Lavori Per Ecologia E Smaltimento Rifiuti. Arte Ed Artigianato Artistico. Servizi Ausiliari Di Sorveglianza, Manutenzione E Pulizia",
    "sg:phone":"+39 055 233 6543",
    "sg:postcode":"50124",
    "sg:province":"Firenze",
    "wof:name":"Fratelli Chiaverini S.d.f.",
    "wof:placetype":"venue"
},
  "geometry": {"coordinates":[11.213861,43.708355],"type":"Point"}
}