{
  "type": "Feature",
  "properties": {
    "iso:country":"IT",
    "sg:address":"86100 Campobasso",
    "sg:city":"Campobasso",
    "sg:orig_category":"Materiali Edili",
    "sg:phone":"+39 0874 441992",
    "sg:postcode":"86100",
    "sg:province":"Campobasso",
    "wof:name":"Mascioli Dino Guglielmo & Figlio Snc",
    "wof:placetype":"venue"
},
  "geometry": {"coordinates":[14.734141,41.761238],"type":"Point"}
}