{
  "type": "Feature",
  "properties": {
    "iso:country":"IT",
    "sg:address":"16136 Genova",
    "sg:city":"Genova",
    "sg:orig_category":"Servizi E Lavori Per Edilizia E Lavori Pubblici. Servizi E Lavori Per Ecologia E Smaltimento Rifiuti",
    "sg:phone":"+39 010 272 2114",
    "sg:postcode":"16136",
    "sg:province":"Genova",
    "wof:name":"Sangoi & Figli Srl",
    "wof:placetype":"venue"
},
  "geometry": {"coordinates":[8.928324,44.416477],"type":"Point"}
}