{
  "type": "Feature",
  "properties": {
    "iso:country":"IT",
    "sg:address":"Piazza Alighieri, 95; Galatina; 73013",
    "sg:city":"Galatina",
    "sg:classifiers":[
        {
            "category":"Banks & Credit Unions",
            "subcategory":"Bank",
            "type":"Services"
        }
    ],
    "sg:phone":"+39 0836 69231",
    "sg:postcode":"73013",
    "sg:province":"Lecce",
    "wof:name":"Banca Vallone Spa",
    "wof:placetype":"venue"
},
  "geometry": {"coordinates":[18.167894,40.174847],"type":"Point"}
}