{
  "type": "Feature",
  "properties": {
    "iso:country":"IT",
    "sg:address":"33047 Remanzacco",
    "sg:city":"Remanzacco",
    "sg:orig_category":"Forniture Per Abbigliamento E Pelletterie",
    "sg:phone":"+39 0432 668113",
    "sg:postcode":"33047",
    "sg:province":"Udine",
    "wof:name":"Cascamificio Friulano (s.p.a.)",
    "wof:placetype":"venue"
},
  "geometry": {"coordinates":[13.3094301224,46.075012207],"type":"Point"}
}