{
  "type": "Feature",
  "properties": {
    "addr:full":"Via Bellini 6 40065 Pianoro Pianoro Bologna 40065",
    "addr:housenumber":"6",
    "addr:postcode":"40065;40065",
    "addr:street":"Via Bellini",
    "iso:country":"IT",
    "sg:address":"Via Bellini 6 40065 Pianoro",
    "sg:city":"Pianoro",
    "sg:classifiers":[
        {
            "category":"Manufacturing",
            "subcategory":"Electronics",
            "type":"Manufacturing & Wholesale Goods"
        }
    ],
    "sg:phone":"+39 051 626 0070",
    "sg:postcode":"40065",
    "sg:province":"Bologna",
    "sg:tags":[
        "large",
        "machine",
        "industrial",
        "electrical",
        "equipment"
    ],
    "wof:name":"Logomat Srl",
    "wof:placetype":"venue"
},
  "geometry": {"coordinates":[11.347623,44.422562],"type":"Point"}
}