{
  "type": "Feature",
  "properties": {
    "iso:country":"IT",
    "sg:address":"29, Via Amendola 47039 Savignano Sul Rubicone",
    "sg:city":"Savignano sul Rubicone",
    "sg:classifiers":[
        {
            "category":"Manufacturing",
            "subcategory":"Rubber & Plastics",
            "type":"Manufacturing & Wholesale Goods"
        }
    ],
    "sg:phone":"+39 0541 942246",
    "sg:postcode":"47039",
    "sg:province":"Forl\u00ec-Cesena",
    "wof:name":"Confezioni Plax S.r.l.",
    "wof:placetype":"venue"
},
  "geometry": {"coordinates":[11.9804611206,43.9947662354],"type":"Point"}
}