{
  "type": "Feature",
  "properties": {
    "iso:country":"IT",
    "sg:address":"25020 Offlaga",
    "sg:city":"Offlaga",
    "sg:orig_category":"Abbigliamento Industria - Forniture Ed Accessori",
    "sg:phone":"+39 030 979166",
    "sg:postcode":"25020",
    "sg:province":"Brescia",
    "wof:name":"Seierre",
    "wof:placetype":"venue"
},
  "geometry": {"coordinates":[10.214974,45.550026],"type":"Point"}
}