{
  "type": "Feature",
  "properties": {
    "addr:full":"73042 Casarano Casarano Lecce 73042",
    "addr:postcode":"73042;73042",
    "iso:country":"IT",
    "sg:address":"73042 Casarano",
    "sg:city":"Casarano",
    "sg:orig_category":"Utensili Meccanici E Materiali. Forniture Per Attivita' Industriali",
    "sg:phone":"+39 0833 502557",
    "sg:postcode":"73042",
    "sg:province":"Lecce",
    "wof:name":"Kosmos",
    "wof:placetype":"venue"
},
  "geometry": {"coordinates":[18.298445,39.938129],"type":"Point"}
}