{
  "type": "Feature",
  "properties": {
    "iso:country":"IT",
    "sg:address":"39042 Bressanone",
    "sg:city":"Bressanone",
    "sg:orig_category":"Prodotti Chimici Secondari. Prodotti Cosmetici E Da Toeletta",
    "sg:phone":"+39 0472 833321",
    "sg:postcode":"39042",
    "sg:province":"Bolzano/Bozen",
    "sg:website":"http://www.brugger-cosmetics.com",
    "wof:name":"Brugger Luis Cosmetics Srl",
    "wof:placetype":"venue"
},
  "geometry": {"coordinates":[11.35800457,46.4967155457],"type":"Point"}
}