{
  "type": "Feature",
  "properties": {
    "iso:country":"IT",
    "sg:address":"04011 Aprilia",
    "sg:city":"Aprilia",
    "sg:orig_category":"Arredo Cucina Ed Elettrodomestici. Elettrodomestici",
    "sg:phone":"+39 06 9270 3332",
    "sg:postcode":"04011",
    "sg:province":"Latina",
    "wof:name":"Capparelli Giada",
    "wof:placetype":"venue"
},
  "geometry": {"coordinates":[12.64892,41.594509],"type":"Point"}
}