{
  "type": "Feature",
  "properties": {
    "iso:country":"IT",
    "sg:address":"18/20, Via A. Volta 21020 Ternate",
    "sg:city":"Ternate",
    "sg:classifiers":[
        {
            "category":"Shopping",
            "subcategory":"Crafts & Fabrics",
            "type":"Retail Goods"
        }
    ],
    "sg:phone":"+39 0332 960033",
    "sg:postcode":"21020",
    "sg:province":"Varese",
    "wof:name":"Ternate Coating S.r.l.",
    "wof:placetype":"venue"
},
  "geometry": {"coordinates":[8.704864502,45.7819442749],"type":"Point"}
}