{
  "type": "Feature",
  "properties": {
    "addr:full":"20153 Milano Milano Milano 20153",
    "addr:postcode":"20153;20153",
    "iso:country":"IT",
    "sg:address":"20153 Milano",
    "sg:city":"Milano",
    "sg:orig_category":"Attrezzature E Forniture Per Officine Riparazione E Servizi Ausiliari",
    "sg:phone":"+39 02 452 2459",
    "sg:postcode":"20153",
    "sg:province":"Milano",
    "wof:name":"Suma Snc Di Suma Corrado & C.",
    "wof:placetype":"venue"
},
  "geometry": {"coordinates":[9.089931,45.480263],"type":"Point"}
}