{
  "type": "Feature",
  "properties": {
    "iso:country":"IT",
    "sg:address":"Via Gombion 15/a 37050 Belfiore D'adige",
    "sg:city":"Belfiore",
    "sg:classifiers":[
        {
            "category":"Home & Garden",
            "subcategory":"Carpets & Floor Coverings",
            "type":"Retail Goods"
        }
    ],
    "sg:phone":"+39 045 615 0184",
    "sg:postcode":"37050",
    "sg:province":"Verona",
    "sg:tags":[
        "cellulose",
        "cover"
    ],
    "wof:name":"Mo - Cel Srl",
    "wof:placetype":"venue"
},
  "geometry": {"coordinates":[10.991748,45.438366],"type":"Point"}
}