{
  "type": "Feature",
  "properties": {
    "addr:full":"20149 Milano Milano Milano 20149",
    "addr:postcode":"20149;20149",
    "iso:country":"IT",
    "sg:address":"20149 Milano",
    "sg:city":"Milano",
    "sg:orig_category":"Cinematografia E Radiotelevisione",
    "sg:phone":"+39 02 439 0557",
    "sg:postcode":"20149",
    "sg:province":"Milano",
    "wof:name":"Aran Endemol Spa",
    "wof:placetype":"venue"
},
  "geometry": {"coordinates":[9.153193,45.4734],"type":"Point"}
}