{
  "type": "Feature",
  "properties": {
    "iso:country":"IT",
    "sg:address":"46, Via Provinciale Sarno 84014 Nocera Inferiore",
    "sg:city":"Nocera Inferiore",
    "sg:classifiers":[
        {
            "category":"Manufacturing",
            "subcategory":"Aerospace",
            "type":"Manufacturing & Wholesale Goods"
        }
    ],
    "sg:phone":"+39 39081939033",
    "sg:postcode":"84014",
    "sg:province":"Salerno",
    "sg:tags":[
        "aeronautic"
    ],
    "wof:name":"De Info Srl",
    "wof:placetype":"venue"
},
  "geometry": {"coordinates":[14.765912,40.677956],"type":"Point"}
}