{
  "type": "Feature",
  "properties": {
    "iso:country":"IT",
    "sg:address":"00015 Monterotondo",
    "sg:city":"Monterotondo",
    "sg:orig_category":"Articoli Medico-sanitari Ed Ortopedici. Impianti, Attrezzature E Forniture Sanitarie Ed Ospedaliere",
    "sg:phone":"+39 06 906 8981",
    "sg:postcode":"00015",
    "sg:province":"Roma",
    "wof:name":"Calafiore Alessandro",
    "wof:placetype":"venue"
},
  "geometry": {"coordinates":[12.633103,42.076763],"type":"Point"}
}