{
  "type": "Feature",
  "properties": {
    "addr:full":"33044 Manzano Manzano Udine 33044",
    "addr:postcode":"33044;33044",
    "iso:country":"IT",
    "sg:address":"33044 Manzano",
    "sg:city":"Manzano",
    "sg:classifiers":[
        {
            "category":"Wholesale",
            "subcategory":"Home Furnishings",
            "type":"Manufacturing & Wholesale Goods"
        }
    ],
    "sg:phone":"+39 0432 754127",
    "sg:postcode":"33044",
    "sg:province":"Udine",
    "sg:tags":[
        "household",
        "appliance",
        "furnishings",
        "appliances",
        "kitchen"
    ],
    "sg:website":"http://www.omenetto.com",
    "wof:name":"Mobili Omenetto Snc Dei Fratelli Omenetto",
    "wof:placetype":"venue"
},
  "geometry": {"coordinates":[13.3709106445,45.987247467],"type":"Point"}
}