{
  "type": "Feature",
  "properties": {
    "addr:full":"20135 Milano Milano Milano 20135",
    "addr:postcode":"20135;20135",
    "iso:country":"IT",
    "sg:address":"20135 Milano",
    "sg:city":"Milano",
    "sg:orig_category":"Servizi Ausiliari Dei Mezzi Di Trasporto. Servizi Ausiliari Per Il Trasporto. Acqua, Luce, Gas E Societa' Di Esercizio Pubblico",
    "sg:phone":"+39 02 550591",
    "sg:postcode":"20135",
    "sg:province":"Milano",
    "wof:name":"Sina S.p.a.",
    "wof:placetype":"venue"
},
  "geometry": {"coordinates":[9.19984,45.446571],"type":"Point"}
}