{
  "type": "Feature",
  "properties": {
    "iso:country":"IT",
    "sg:address":"10135 Torino",
    "sg:city":"Torino",
    "sg:orig_category":"Legno E Semilavorati",
    "sg:phone":"+39 011 341559",
    "sg:postcode":"10135",
    "sg:province":"Torino",
    "wof:name":"Gherzo Pietro",
    "wof:placetype":"venue"
},
  "geometry": {"coordinates":[7.624039,45.021557],"type":"Point"}
}