{
  "type": "Feature",
  "properties": {
    "addr:full":"20125 Milano Milano Milano 20125",
    "addr:postcode":"20125;20125",
    "iso:country":"IT",
    "sg:address":"20125 Milano",
    "sg:city":"Milano",
    "sg:classifiers":[
        {
            "category":"Banks & Credit Unions",
            "subcategory":"Bank",
            "type":"Services"
        }
    ],
    "sg:phone":"+39 02 670 9432",
    "sg:postcode":"20125",
    "sg:province":"Milano",
    "sg:tags":[
        "services",
        "publishing",
        "supply"
    ],
    "sg:website":"http://www.trophee-from-italy.com",
    "wof:name":"Caribbean A.p. - Trophee - Leatherware Division",
    "wof:placetype":"venue"
},
  "geometry": {"coordinates":[9.2060556412,45.4915313721],"type":"Point"}
}