{
  "type": "Feature",
  "properties": {
    "addr:full":"10, Via Mattei 25050 Rodengo Saiano Brescia 25050",
    "addr:postcode":"25050;25050",
    "addr:street":"Mattei",
    "iso:country":"IT",
    "sg:address":"10, Via Mattei 25050 Rodengo Saiano",
    "sg:classifiers":[
        {
            "category":"Manufacturing",
            "subcategory":"Metals",
            "type":"Manufacturing & Wholesale Goods"
        }
    ],
    "sg:phone":"+39 39030610910",
    "sg:postcode":"25050",
    "sg:province":"Brescia",
    "sg:tags":[
        "processing"
    ],
    "wof:name":"Ossidal (s.r.l.)",
    "wof:placetype":"venue"
},
  "geometry": {"coordinates":[10.1220026016,45.5802574158],"type":"Point"}
}