{
  "type": "Feature",
  "properties": {
    "iso:country":"IT",
    "sg:address":"20157 Milano",
    "sg:city":"Milano",
    "sg:orig_category":"Macchine Utensili E Impianti",
    "sg:phone":"+39 02 355 3148",
    "sg:postcode":"20157",
    "sg:province":"Milano",
    "wof:name":"Cri.pi. Di Sarcina Cristian",
    "wof:placetype":"venue"
},
  "geometry": {"coordinates":[9.135863,45.514584],"type":"Point"}
}