{
  "type": "Feature",
  "properties": {
    "iso:country":"IT",
    "sg:address":"Via Carroccio 4/6 20038 Seregno",
    "sg:city":"Seregno",
    "sg:orig_category":"Furniture, General",
    "sg:phone":"+39 036 232 5365",
    "sg:postcode":"20038",
    "sg:province":"Milano",
    "sg:website":"www.busnelliuno.it",
    "wof:name":"Busnelli Uno Srl",
    "wof:placetype":"venue"
},
  "geometry": {"coordinates":[9.2125205994,45.657333374],"type":"Point"}
}