{
  "type": "Feature",
  "properties": {
    "iso:country":"IT",
    "sg:address":"73100 Lecce",
    "sg:city":"Lecce",
    "sg:orig_category":"Abbigliamento - Produzione E Ingrosso",
    "sg:phone":"+39 0832 398078",
    "sg:postcode":"73100",
    "sg:province":"Lecce",
    "wof:name":"Genesis Florence Fashion Di R. Marsano",
    "wof:placetype":"venue"
},
  "geometry": {"coordinates":[18.180937,40.362534],"type":"Point"}
}