{
  "type": "Feature",
  "properties": {
    "addr:full":"16132 Genova Genova Genova 16132",
    "addr:postcode":"16132;16132",
    "iso:country":"IT",
    "sg:address":"16132 Genova",
    "sg:city":"Genova",
    "sg:orig_category":"Servizi E Lavori Per Agricoltura E Zootecnia. Servizi E Lavori Industria Chimica. Servizi Ausiliari Di Analisi, Controllo E Ricerca",
    "sg:phone":"+39 010 529 9247",
    "sg:postcode":"16132",
    "sg:province":"Genova",
    "wof:name":"Philogen Srl",
    "wof:placetype":"venue"
},
  "geometry": {"coordinates":[8.982509,44.415142],"type":"Point"}
}