{
  "type": "Feature",
  "properties": {
    "addr:full":"36078 Valdagno Valdagno Vicenza 36078",
    "addr:postcode":"36078;36078",
    "iso:country":"IT",
    "sg:address":"36078 Valdagno",
    "sg:city":"Valdagno",
    "sg:orig_category":"Metalli E Leghe",
    "sg:phone":"+39 0445 410044",
    "sg:postcode":"36078",
    "sg:province":"Vicenza",
    "wof:name":"Petrin Luciano",
    "wof:placetype":"venue"
},
  "geometry": {"coordinates":[11.2856225967,45.6405181885],"type":"Point"}
}