{
  "type": "Feature",
  "properties": {
    "addr:full":"4, Piazzale Dei Ss. Pietro E Paolo 00144 Roma Roma Roma 00144",
    "addr:postcode":"00144;00144",
    "addr:street":"Piazzale Dei Ss. Pietro E Paolo",
    "iso:country":"IT",
    "sg:address":"4, Piazzale Dei Ss. Pietro E Paolo 00144 Roma",
    "sg:city":"Roma",
    "sg:classifiers":[
        {
            "category":"Communications",
            "subcategory":"Newspaper",
            "type":"Services"
        }
    ],
    "sg:phone":"+39 39065915526",
    "sg:postcode":"00144",
    "sg:province":"Roma",
    "sg:tags":[
        "advertising"
    ],
    "wof:name":"Media Planning Sas",
    "wof:placetype":"venue"
},
  "geometry": {"coordinates":[12.482325,41.895466],"type":"Point"}
}