{
  "type": "Feature",
  "properties": {
    "iso:country":"IT",
    "sg:address":"23883 Brivio",
    "sg:city":"Brivio",
    "sg:orig_category":"Materiali Semilavorati Metallici",
    "sg:phone":"+39 039 932921",
    "sg:postcode":"23883",
    "sg:province":"Lecco",
    "wof:name":"D.e.l.n.a. (s.p.a.)",
    "wof:placetype":"venue"
},
  "geometry": {"coordinates":[9.442411,45.724319],"type":"Point"}
}