{
  "type": "Feature",
  "properties": {
    "iso:country":"IT",
    "sg:address":"48, Viale Pasubio 36036 Torrebelvicino",
    "sg:city":"Torrebelvicino",
    "sg:classifiers":[
        {
            "category":"Real Estate",
            "subcategory":"Architect",
            "type":"Services"
        }
    ],
    "sg:phone":"+39 0445 661969",
    "sg:postcode":"36036",
    "sg:province":"Vicenza",
    "sg:tags":[
        "textile",
        "clothing"
    ],
    "wof:name":"Valbrana (s.r.l.)",
    "wof:placetype":"venue"
},
  "geometry": {"coordinates":[11.321508,45.715256],"type":"Point"}
}