{
  "type": "Feature",
  "properties": {
    "addr:full":"10156 Torino Torino Torino 10156",
    "addr:postcode":"10156;10156",
    "iso:country":"IT",
    "sg:address":"10156 Torino",
    "sg:city":"Torino",
    "sg:orig_category":"Automobili E Mezzi Di Trasporto",
    "sg:phone":"+39 011 223 9904",
    "sg:postcode":"10156",
    "sg:province":"Torino",
    "wof:name":"Aviatec Srl",
    "wof:placetype":"venue"
},
  "geometry": {"coordinates":[7.70615,45.119347],"type":"Point"}
}