{
  "type": "Feature",
  "properties": {
    "iso:country":"IT",
    "sg:address":"91025 Marsala",
    "sg:city":"Marsala",
    "sg:orig_category":"Cabine Elettriche Di Trasformazione E Comando",
    "sg:phone":"+39 0923 966550",
    "sg:postcode":"91025",
    "sg:province":"Trapani",
    "wof:name":"Pro.si.tec. Ed Engineering Di Angileri Vito",
    "wof:placetype":"venue"
},
  "geometry": {"coordinates":[12.552751,37.832535],"type":"Point"}
}