{
  "type": "Feature",
  "properties": {
    "addr:full":"12, Via Riviera 27100 Pavia Pavia Pavia 27100",
    "addr:postcode":"27100;27100",
    "addr:street":"Via Riviera",
    "iso:country":"IT",
    "sg:address":"12, Via Riviera 27100 Pavia",
    "sg:city":"Pavia",
    "sg:classifiers":[
        {
            "category":"Manufacturing",
            "subcategory":"Metals",
            "type":"Manufacturing & Wholesale Goods"
        }
    ],
    "sg:phone":"+39 0382 526290",
    "sg:postcode":"27100",
    "sg:province":"Pavia",
    "sg:tags":[
        "metallurgy",
        "metalworking"
    ],
    "wof:name":"Repetto & Fontanella",
    "wof:placetype":"venue"
},
  "geometry": {"coordinates":[9.1780500412,45.2342033386],"type":"Point"}
}