{
  "type": "Feature",
  "properties": {
    "addr:full":"Via Resegone 2 24020 Gorle Gorle Bergamo 24020",
    "addr:housenumber":"2",
    "addr:postcode":"24020;24020",
    "addr:street":"Via Resegone",
    "iso:country":"IT",
    "sg:address":"Via Resegone 2 24020 Gorle",
    "sg:city":"Gorle",
    "sg:classifiers":[
        {
            "category":"Building & Trades",
            "subcategory":"Construction",
            "type":"Services"
        }
    ],
    "sg:phone":"+39 035 293590",
    "sg:postcode":"24020",
    "sg:province":"Bergamo",
    "sg:tags":[
        "pattern",
        "foundry"
    ],
    "wof:name":"Briccoli Srl",
    "wof:placetype":"venue"
},
  "geometry": {"coordinates":[9.7119750977,45.6901435852],"type":"Point"}
}