{
  "type": "Feature",
  "properties": {
    "addr:full":"20159 Milano Milano Milano 20159",
    "addr:postcode":"20159;20159",
    "iso:country":"IT",
    "sg:address":"20159 Milano",
    "sg:city":"Milano",
    "sg:orig_category":"Non-classified Establishments",
    "sg:phone":"+39 02 607 1764",
    "sg:postcode":"20159",
    "sg:province":"Milano",
    "wof:name":"Spazio 29 Srl",
    "wof:placetype":"venue"
},
  "geometry": {"coordinates":[9.188951,45.488808],"type":"Point"}
}