{
  "type": "Feature",
  "properties": {
    "addr:full":"33/a, Via Molino 35010 Vigonza Vigonza Padova 35010",
    "addr:housenumber":"33 / a",
    "addr:postcode":"35010;35010",
    "addr:street":"Molino",
    "iso:country":"IT",
    "sg:address":"33/a, Via Molino 35010 Vigonza",
    "sg:city":"Vigonza",
    "sg:classifiers":[
        {
            "category":"Shopping",
            "subcategory":"Clothing, Apparel, & Fashions",
            "type":"Retail Goods"
        }
    ],
    "sg:phone":"+39 049 809 7260",
    "sg:postcode":"35010",
    "sg:province":"Padova",
    "sg:tags":[
        "clothes"
    ],
    "wof:name":"Confezioni Claudia Di Claudia Baritono",
    "wof:placetype":"venue"
},
  "geometry": {"coordinates":[11.985497,45.43784],"type":"Point"}
}