{
  "type": "Feature",
  "properties": {
    "iso:country":"IT",
    "sg:address":"Numero Civico 68, Santa Massenza, 38070 Vezzano, Tn",
    "sg:city":"Vezzano",
    "sg:classifiers":[
        {
            "category":"Banks & Credit Unions",
            "subcategory":"Bank",
            "type":"Services"
        }
    ],
    "sg:postcode":"38070",
    "sg:province":"Trento",
    "wof:name":"Cassa Rurale Di Santa Massenza-banca Di Credito Cooperativo Scarl",
    "wof:placetype":"venue"
},
  "geometry": {"coordinates":[11.119053,46.066738],"type":"Point"}
}