{
  "type": "Feature",
  "properties": {
    "addr:full":"19126 La Spezia SP",
    "addr:housenumber":"19126",
    "iso:country":"IT",
    "sg:address":"19126 La Spezia",
    "sg:orig_category":"Pompe. Macchine, Strumenti Ed Apparecchi Per Attivita' Industriali",
    "sg:phone":"+39 0187 599601",
    "sg:province":"SP",
    "wof:name":"Emg Engine Mechanical Group Srl",
    "wof:placetype":"venue"
},
  "geometry": {"coordinates":[9.8416175842,44.1125144958],"type":"Point"}
}