{
  "type": "Feature",
  "properties": {
    "addr:full":"40127 Bologna Bologna Bologna 40127",
    "addr:postcode":"40127;40127",
    "iso:country":"IT",
    "sg:address":"40127 Bologna",
    "sg:city":"Bologna",
    "sg:orig_category":"Automobili E Mezzi Di Trasporto",
    "sg:phone":"+39 051 633 1402",
    "sg:postcode":"40127",
    "sg:province":"Bologna",
    "wof:name":"Alpha Centauri",
    "wof:placetype":"venue"
},
  "geometry": {"coordinates":[11.36066,44.506905],"type":"Point"}
}