{
  "type": "Feature",
  "properties": {
    "iso:country":"IT",
    "sg:address":"Corso Stamira 16, 60100 Ancona, An",
    "sg:classifiers":[
        {
            "category":"Banks & Credit Unions",
            "subcategory":"Bank",
            "type":"Services"
        }
    ],
    "sg:phone":"+39 071 203978",
    "wof:name":"Esaleasing",
    "wof:placetype":"venue"
},
  "geometry": {"coordinates":[13.510504,43.618023],"type":"Point"}
}