{
  "type": "Feature",
  "properties": {
    "iso:country":"IT",
    "sg:address":"47900 Rimini",
    "sg:city":"Rimini",
    "sg:classifiers":[
        {
            "category":"Farming",
            "subcategory":"Fish & Marine Products",
            "type":"Manufacturing & Wholesale Goods"
        }
    ],
    "sg:phone":"+39 0541 56228",
    "sg:postcode":"47900",
    "sg:province":"Rimini",
    "sg:tags":[
        "medical-health",
        "orthopedic"
    ],
    "wof:name":"Centro Acustico Rimini",
    "wof:placetype":"venue"
},
  "geometry": {"coordinates":[12.565389,44.061687],"type":"Point"}
}