{
  "type": "Feature",
  "properties": {
    "addr:full":"10155 Torino Torino Torino 10155",
    "addr:postcode":"10155;10155",
    "iso:country":"IT",
    "sg:address":"10155 Torino",
    "sg:city":"Torino",
    "sg:orig_category":"Elettrodomestici - Riparazione E Vendita Al Dettaglio Di Accessori",
    "sg:phone":"+39 011 205 0064",
    "sg:postcode":"10155",
    "sg:province":"Torino",
    "wof:name":"Riccobene Sas",
    "wof:placetype":"venue"
},
  "geometry": {"coordinates":[8.39892,45.462345],"type":"Point"}
}