{
  "type": "Feature",
  "properties": {
    "iso:country":"IT",
    "sg:address":"Via Flli Cervi 21 81030 Parete",
    "sg:city":"Parete",
    "sg:classifiers":[
        {
            "category":"Community Center",
            "subcategory":"Senior",
            "type":"Public Place"
        }
    ],
    "sg:phone":"+39 081 503 0251",
    "sg:postcode":"81030",
    "sg:province":"Caserta",
    "sg:tags":[
        "pen",
        "ball",
        "point"
    ],
    "sg:website":"www.deltapen.it",
    "wof:name":"Delta Srl",
    "wof:placetype":"venue"
},
  "geometry": {"coordinates":[14.332194,41.075417],"type":"Point"}
}