{
  "type": "Feature",
  "properties": {
    "addr:full":"41/a, S.s. 35 Dei Giovi 15057 Tortona Tortona Alessandria 15057",
    "addr:housenumber":"41 / a",
    "addr:postcode":"15057;15057",
    "addr:street":"S.S. 35 Dei Giovi",
    "iso:country":"IT",
    "sg:address":"41/a, S.s. 35 Dei Giovi 15057 Tortona",
    "sg:city":"Tortona",
    "sg:classifiers":[
        {
            "category":"Manufacturing",
            "subcategory":"Rubber & Plastics",
            "type":"Manufacturing & Wholesale Goods"
        }
    ],
    "sg:phone":"+39 0131 820443",
    "sg:postcode":"15057",
    "sg:province":"Alessandria",
    "sg:website":"http://www.cncontinental.it",
    "wof:name":"Cn Continental Spa",
    "wof:placetype":"venue"
},
  "geometry": {"coordinates":[8.7396841049,44.8321495056],"type":"Point"}
}