{
  "type": "Feature",
  "properties": {
    "addr:full":"20033 Desio Desio Milano 20033",
    "addr:postcode":"20033;20033",
    "iso:country":"IT",
    "sg:address":"20033 Desio",
    "sg:city":"Desio",
    "sg:orig_category":"Carni, Salumi E Pesci. Zootecnia E Pesca, Allevamento Piccoli Animali",
    "sg:phone":"+39 036 262 6883",
    "sg:postcode":"20033",
    "sg:province":"Milano",
    "wof:name":"Eredi Di Caiani Franco Sas Di Caiani Lorenzo & C.",
    "wof:placetype":"venue"
},
  "geometry": {"coordinates":[9.178795,45.453033],"type":"Point"}
}