{
  "type": "Feature",
  "properties": {
    "iso:country":"IT",
    "sg:address":"31044 Montebelluna",
    "sg:city":"Montebelluna",
    "sg:classifiers":[
        {
            "category":"Shopping",
            "subcategory":"Clothing, Apparel, & Fashions",
            "type":"Retail Goods"
        }
    ],
    "sg:phone":"+39 0423 600487",
    "sg:postcode":"31044",
    "sg:province":"Treviso",
    "sg:tags":[
        "activities",
        "goods",
        "supply",
        "leather",
        "commercial",
        "artisan",
        "supplies",
        "clothing"
    ],
    "sg:website":"http://www.brufatto.it",
    "wof:name":"Brufatto Maria Antonietta",
    "wof:placetype":"venue"
},
  "geometry": {"coordinates":[12.063586,45.768723],"type":"Point"}
}