{
  "type": "Feature",
  "properties": {
    "iso:country":"IT",
    "sg:address":"Via Dell' Artigianato 31 - Bancole 46047 Porto Mantovano",
    "sg:city":"Porto Mantovano",
    "sg:classifiers":[
        {
            "category":"Shopping",
            "subcategory":"Clothing, Apparel, & Fashions",
            "type":"Retail Goods"
        }
    ],
    "sg:phone":"+39 0376 398991",
    "sg:postcode":"46047",
    "sg:province":"Mantova",
    "sg:tags":[
        "gown",
        "evening",
        "dress",
        "cocktail"
    ],
    "wof:name":"Bardini Trasformazione Tessile Srl",
    "wof:placetype":"venue"
},
  "geometry": {"coordinates":[10.796236,45.218338],"type":"Point"}
}