{
  "type": "Feature",
  "properties": {
    "iso:country":"IT",
    "sg:address":"50145 Firenze",
    "sg:city":"Firenze",
    "sg:orig_category":"Tessuti Arredamento - Produzione E Ingrosso",
    "sg:phone":"+39 055 310522",
    "sg:postcode":"50145",
    "sg:province":"Firenze",
    "wof:name":"Stock Style 2000 Srl",
    "wof:placetype":"venue"
},
  "geometry": {"coordinates":[11.182194,43.796722],"type":"Point"}
}