{
  "type": "Feature",
  "properties": {
    "addr:full":"167, Via Noalese 30036 Santa Maria Di Sala Santa Maria di Sala Venezia 30036",
    "addr:housenumber":"167",
    "addr:postcode":"30036;30036",
    "addr:street":"Via Noalese;Maria",
    "iso:country":"IT",
    "sg:address":"167, Via Noalese 30036 Santa Maria Di Sala",
    "sg:city":"Santa Maria di Sala",
    "sg:classifiers":[
        {
            "category":"Manufacturing",
            "subcategory":"Metals",
            "type":"Manufacturing & Wholesale Goods"
        }
    ],
    "sg:phone":"+39 041 573 0222",
    "sg:postcode":"30036",
    "sg:province":"Venezia",
    "sg:tags":[
        "metallurgy",
        "metalworking"
    ],
    "wof:name":"Beato Edoardo - Materiali Ferrosi - S.r.l.",
    "wof:placetype":"venue"
},
  "geometry": {"coordinates":[12.0278959274,45.5059432983],"type":"Point"}
}