{
  "type": "Feature",
  "properties": {
    "addr:full":"Via Lama 4 41012 Carpi Carpi Modena 41012",
    "addr:housenumber":"4",
    "addr:postcode":"41012;41012",
    "addr:street":"Via Lama",
    "iso:country":"IT",
    "sg:address":"Via Lama 4 41012 Carpi",
    "sg:city":"Carpi",
    "sg:orig_category":"Hoisiery Goods",
    "sg:phone":"+39 059 695251",
    "sg:postcode":"41012",
    "sg:province":"Modena",
    "sg:website":"www.belmondi.it",
    "wof:name":"Maglificio Belmondi Spa",
    "wof:placetype":"venue"
},
  "geometry": {"coordinates":[10.925589,44.808414],"type":"Point"}
}