{
  "type": "Feature",
  "properties": {
    "iso:country":"IT",
    "sg:address":"35010 Curtarolo",
    "sg:city":"Curtarolo",
    "sg:orig_category":"Lavorazioni Metalli, Stampaggio E Saldatura",
    "sg:phone":"+39 049 962 0216",
    "sg:postcode":"35010",
    "sg:province":"Padova",
    "wof:name":"Europrofilam Srl",
    "wof:placetype":"venue"
},
  "geometry": {"coordinates":[11.917576,45.411549],"type":"Point"}
}