{
  "type": "Feature",
  "properties": {
    "iso:country":"IT",
    "sg:address":"230, Via Lamarmora Alessandro 25124 Brescia",
    "sg:city":"Brescia",
    "sg:classifiers":[
        {
            "category":"Utilities",
            "subcategory":"Electric",
            "type":"Services"
        }
    ],
    "sg:phone":"+39 030 350 0002",
    "sg:postcode":"25124",
    "sg:province":"Brescia",
    "sg:tags":[
        "electricity"
    ],
    "wof:name":"Azienda Servizi Municipalizzati Del Comune Di Brescia",
    "wof:placetype":"venue"
},
  "geometry": {"coordinates":[10.222958,45.539829],"type":"Point"}
}