{
  "type": "Feature",
  "properties": {
    "iso:country":"IT",
    "sg:address":"83100 Avellino",
    "sg:city":"Avellino",
    "sg:classifiers":[
        {
            "category":"Health Services",
            "subcategory":"Health Practitioner",
            "type":"Services"
        }
    ],
    "sg:phone":"+39 0825 23479",
    "sg:postcode":"83100",
    "sg:province":"Avellino",
    "sg:tags":[
        "medici"
    ],
    "wof:name":"Iandolo Amelia",
    "wof:placetype":"venue"
},
  "geometry": {"coordinates":[14.786333,40.918839],"type":"Point"}
}