{
  "type": "Feature",
  "properties": {
    "iso:country":"IT",
    "sg:address":"20132 Milano",
    "sg:city":"Milano",
    "sg:orig_category":"Servizi E Lavori Per Edilizia E Lavori Pubblici. Servizi E Lavori Per Ecologia E Smaltimento Rifiuti. Macchine E Forniture Per Ecologia E Smaltimento Rifiuti. Acqua, Luce, Gas E Societa' Di Esercizio ",
    "sg:phone":"+39 02 259 0112",
    "sg:postcode":"20132",
    "sg:province":"Milano",
    "wof:name":"Corpo Volontari Protezione Civile",
    "wof:placetype":"venue"
},
  "geometry": {"coordinates":[9.242467,45.49968],"type":"Point"}
}