{
  "type": "Feature",
  "properties": {
    "iso:country":"IT",
    "sg:address":"6, V. Pacinotti 20064 Gorgonzola",
    "sg:city":"Gorgonzola",
    "sg:classifiers":[
        {
            "category":"Manufacturing",
            "subcategory":"Printing",
            "type":"Manufacturing & Wholesale Goods"
        }
    ],
    "sg:phone":"+39 39029516800",
    "sg:postcode":"20064",
    "sg:province":"Milano",
    "sg:tags":[
        "publishing"
    ],
    "wof:name":"Palos Srl",
    "wof:placetype":"venue"
},
  "geometry": {"coordinates":[9.3973312378,45.5295829773],"type":"Point"}
}