{
  "type": "Feature",
  "properties": {
    "addr:full":"20146 Milano Milano Milano 20146",
    "addr:postcode":"20146;20146",
    "iso:country":"IT",
    "sg:address":"20146 Milano",
    "sg:city":"Milano",
    "sg:orig_category":"Servizi E Lavori Industria Della Gomma",
    "sg:phone":"+39 02 423 4704",
    "sg:postcode":"20146",
    "sg:province":"Milano",
    "wof:name":"Vulcanizzazione Lorenteggio",
    "wof:placetype":"venue"
},
  "geometry": {"coordinates":[9.15031,45.453979],"type":"Point"}
}