{
  "type": "Feature",
  "properties": {
    "addr:full":"C. Peschiera 10141 Torino Torino Torino 10141",
    "addr:postcode":"10141;10141",
    "iso:country":"IT",
    "sg:address":"C. Peschiera 10141 Torino",
    "sg:city":"Torino",
    "sg:classifiers":[
        {
            "category":"Communications",
            "subcategory":"Newspaper",
            "type":"Services"
        }
    ],
    "sg:phone":"+39 011 773 2266",
    "sg:postcode":"10141",
    "sg:province":"Torino",
    "sg:tags":[
        "advertising"
    ],
    "sg:website":"http://www.fbisrl.com",
    "wof:name":"Fbi - Fashion & Basic Image",
    "wof:placetype":"venue"
},
  "geometry": {"coordinates":[7.64096,45.06781],"type":"Point"}
}