{
  "type": "Feature",
  "properties": {
    "iso:country":"IT",
    "sg:address":"22100 Como",
    "sg:city":"Como",
    "sg:orig_category":"Climatizzazione E Condizionamento, Apparecchiature E Servizi. Elettrodomestici",
    "sg:phone":"+39 031 523015",
    "sg:postcode":"22100",
    "sg:province":"Como",
    "wof:name":"Ferrari Romolo & C. Snc",
    "wof:placetype":"venue"
},
  "geometry": {"coordinates":[9.075356,45.786381],"type":"Point"}
}