{
  "type": "Feature",
  "properties": {
    "iso:country":"IT",
    "sg:address":"59016 Poggio A Caiano",
    "sg:city":"Poggio a Caiano",
    "sg:orig_category":"Campionari",
    "sg:phone":"+39 055 877 8323",
    "sg:postcode":"59016",
    "sg:province":"Prato",
    "wof:name":"Cateni Marco",
    "wof:placetype":"venue"
},
  "geometry": {"coordinates":[11.059041,43.814575],"type":"Point"}
}