{
  "type": "Feature",
  "properties": {
    "iso:country":"IT",
    "sg:address":"47, Via Pisana 50021 Barberino Val D'elsa",
    "sg:classifiers":[
        {
            "category":"Home & Garden",
            "subcategory":"Home Furnishings",
            "type":"Retail Goods"
        }
    ],
    "sg:phone":"+39 055 807 8828",
    "sg:postcode":"50021",
    "sg:province":"Firenze",
    "sg:tags":[
        "household"
    ],
    "wof:name":"Formichi Srl",
    "wof:placetype":"venue"
},
  "geometry": {"coordinates":[11.112608,43.499966],"type":"Point"}
}