{
  "type": "Feature",
  "properties": {
    "addr:full":"36100 Vicenza Vicenza Vicenza 36100",
    "addr:postcode":"36100;36100",
    "iso:country":"IT",
    "sg:address":"36100 Vicenza",
    "sg:city":"Vicenza",
    "sg:orig_category":"Elettrodomestici. Elettronica Professionale E Di Consumo. Arredi Ed Attrezzature Per Attivita' Commerciali Ed Artigianali. Macchine, Strumenti Ed Apparecchi Per Attivita' Industriali",
    "sg:phone":"+39 0444 963666",
    "sg:postcode":"36100",
    "sg:province":"Vicenza",
    "sg:website":"http://www.bottazzi.it",
    "wof:name":"Bottazzi Srl",
    "wof:placetype":"venue"
},
  "geometry": {"coordinates":[11.561045,45.53619],"type":"Point"}
}