{
  "type": "Feature",
  "properties": {
    "iso:country":"IT",
    "sg:address":"1, Via G. Rossa 43058 Sorbolo",
    "sg:city":"Sorbolo",
    "sg:classifiers":[
        {
            "category":"Professional",
            "subcategory":"Printing & Photocopies",
            "type":"Services"
        }
    ],
    "sg:phone":"+39 0521 604345",
    "sg:postcode":"43058",
    "sg:province":"Parma",
    "wof:name":"Abbati (s.n.c.)",
    "wof:placetype":"venue"
},
  "geometry": {"coordinates":[10.4039402008,44.8320846558],"type":"Point"}
}