{
  "type": "Feature",
  "properties": {
    "addr:full":"Via Virginio, 376 - Anselmo 50025 Montespertoli Montespertoli Firenze 50025",
    "addr:housenumber":"376",
    "addr:postcode":"50025;50025",
    "addr:street":"Via Virginio;Anselmo",
    "iso:country":"IT",
    "sg:address":"Via Virginio, 376 - Anselmo 50025 Montespertoli",
    "sg:city":"Montespertoli",
    "sg:orig_category":"Ladies' Shoes",
    "sg:phone":"+39 0571 671414",
    "sg:postcode":"50025",
    "sg:province":"Firenze",
    "wof:name":"Calzaturificio Petra Spa",
    "wof:placetype":"venue"
},
  "geometry": {"coordinates":[11.256902,43.768734],"type":"Point"}
}