{
  "type": "Feature",
  "properties": {
    "addr:full":"Borgo San Martino 3; Pocapaglia; 12060 Pocapaglia Cuneo 12060",
    "addr:housenumber":"3",
    "addr:postcode":"12060;12060",
    "addr:street":"Borgo San Martino;Pocapaglia",
    "iso:country":"IT",
    "sg:address":"Borgo San Martino 3; Pocapaglia; 12060",
    "sg:city":"Pocapaglia",
    "sg:classifiers":[
        {
            "category":"Banks & Credit Unions",
            "subcategory":"Bank",
            "type":"Services"
        }
    ],
    "sg:phone":"+39 0172 423669",
    "sg:postcode":"12060",
    "sg:province":"Cuneo",
    "wof:name":"Banca Sella",
    "wof:placetype":"venue"
},
  "geometry": {"coordinates":[7.881902,44.697964],"type":"Point"}
}