{
  "type": "Feature",
  "properties": {
    "iso:country":"IT",
    "sg:address":"00186 Roma",
    "sg:city":"Roma",
    "sg:orig_category":"Autoradio",
    "sg:phone":"+39 06 686 5102",
    "sg:postcode":"00186",
    "sg:province":"Roma",
    "wof:name":"Cucciollo Srl",
    "wof:placetype":"venue"
},
  "geometry": {"coordinates":[12.486511,41.891712],"type":"Point"}
}