{
  "type": "Feature",
  "properties": {
    "iso:country":"IT",
    "sg:address":"36060 Romano D'ezzelino",
    "sg:classifiers":[
        {
            "category":"Shopping",
            "subcategory":"Jewelry",
            "type":"Retail Goods"
        }
    ],
    "sg:phone":"+39 0424 512929",
    "sg:postcode":"36060",
    "sg:province":"Vicenza",
    "sg:tags":[
        "watchmaker",
        "jewelers",
        "gold",
        "silversmith"
    ],
    "sg:website":"http://www.livior.it",
    "wof:name":"Li.vi.or Srl",
    "wof:placetype":"venue"
},
  "geometry": {"coordinates":[11.7583122253,45.7962722778],"type":"Point"}
}