{
  "type": "Feature",
  "properties": {
    "addr:full":"96014 Floridia Floridia Siracusa 96014",
    "addr:postcode":"96014;96014",
    "iso:country":"IT",
    "sg:address":"96014 Floridia",
    "sg:city":"Floridia",
    "sg:orig_category":"Dolciumi E Gelati",
    "sg:phone":"+39 0931 942046",
    "sg:postcode":"96014",
    "sg:province":"Siracusa",
    "wof:name":"Sortino Sebastiano",
    "wof:placetype":"venue"
},
  "geometry": {"coordinates":[15.139476,37.088184],"type":"Point"}
}