{
  "type": "Feature",
  "properties": {
    "iso:country":"IT",
    "sg:address":"98039 Taormina",
    "sg:city":"Taormina",
    "sg:orig_category":"Campeggio. Alberghi E Strutture Extra Alberghiere",
    "sg:phone":"+39 0942 628698",
    "sg:postcode":"98039",
    "sg:province":"Messina",
    "wof:name":"Hotel Del Corso",
    "wof:placetype":"venue"
},
  "geometry": {"coordinates":[15.248737,37.837151],"type":"Point"}
}