{
  "type": "Feature",
  "properties": {
    "iso:country":"IT",
    "sg:address":"04011 Aprilia",
    "sg:city":"Aprilia",
    "sg:orig_category":"Disinfezione, Disinfestazione E Derattizzazione",
    "sg:phone":"+39 06 9250 0317",
    "sg:postcode":"04011",
    "sg:province":"Latina",
    "wof:name":"Insea 2000 - Initiative 2000 S.e.a. Srl",
    "wof:placetype":"venue"
},
  "geometry": {"coordinates":[12.619854,41.62706],"type":"Point"}
}