{
  "type": "Feature",
  "properties": {
    "iso:country":"IT",
    "sg:address":"7, Via Carroccio 20020 Magnago",
    "sg:city":"Magnago",
    "sg:classifiers":[
        {
            "category":"Professional",
            "subcategory":"Engineering",
            "type":"Services"
        }
    ],
    "sg:phone":"+39 0331 657385",
    "sg:postcode":"20020",
    "sg:province":"Milano",
    "sg:tags":[
        "machine",
        "-",
        "mechanical"
    ],
    "wof:name":"Sider Progetti (s.n.c.)",
    "wof:placetype":"venue"
},
  "geometry": {"coordinates":[8.786724,45.576176],"type":"Point"}
}