{
  "type": "Feature",
  "properties": {
    "iso:country":"IT",
    "sg:address":"Via Vecchianino 5 47016 Predappio",
    "sg:city":"Predappio",
    "sg:orig_category":"Hoisiery Goods",
    "sg:phone":"+39 0543 922674",
    "sg:postcode":"47016",
    "sg:province":"Forl\u00ec-Cesena",
    "wof:name":"Gulp Srl",
    "wof:placetype":"venue"
},
  "geometry": {"coordinates":[11.980361,44.113544],"type":"Point"}
}