{
  "type": "Feature",
  "properties": {
    "addr:full":"21, Via Brignano 24047 Treviglio Treviglio Bergamo 24047",
    "addr:postcode":"24047;24047",
    "addr:street":"Via Brignano",
    "iso:country":"IT",
    "sg:address":"21, Via Brignano 24047 Treviglio",
    "sg:city":"Treviglio",
    "sg:classifiers":[
        {
            "category":"Manufacturing",
            "subcategory":"Metals",
            "type":"Manufacturing & Wholesale Goods"
        }
    ],
    "sg:phone":"+39 036 330 3155",
    "sg:postcode":"24047",
    "sg:province":"Bergamo",
    "sg:tags":[
        "metallurgy",
        "metalworking"
    ],
    "wof:name":"Superflex (s.r.l.)",
    "wof:placetype":"venue"
},
  "geometry": {"coordinates":[9.6059532166,45.5270462036],"type":"Point"}
}