{
  "type": "Feature",
  "properties": {
    "iso:country":"IT",
    "sg:address":"46040 Cavriana",
    "sg:city":"Cavriana",
    "sg:orig_category":"Mangimi, Foraggi Ed Integratori Zootecnici",
    "sg:phone":"+39 0376 804015",
    "sg:postcode":"46040",
    "sg:province":"Mantova",
    "wof:name":"Castiglione Srl",
    "wof:placetype":"venue"
},
  "geometry": {"coordinates":[10.597379,45.342049],"type":"Point"}
}