{
  "type": "Feature",
  "properties": {
    "iso:country":"IT",
    "sg:address":"4, Via Regia 35010 Vigonza",
    "sg:city":"Vigonza",
    "sg:classifiers":[
        {
            "category":"Manufacturing",
            "subcategory":"Metals",
            "type":"Manufacturing & Wholesale Goods"
        }
    ],
    "sg:phone":"+39 39049628788",
    "sg:postcode":"35010",
    "sg:province":"Padova",
    "sg:tags":[
        "metallurgy",
        "metalworking"
    ],
    "wof:name":"Doni (s.p.a.)",
    "wof:placetype":"venue"
},
  "geometry": {"coordinates":[11.9619674683,45.426776886],"type":"Point"}
}