{
  "type": "Feature",
  "properties": {
    "iso:country":"IT",
    "sg:address":"Via Mazzini, 95; Alassio; 17021",
    "sg:city":"Alassio",
    "sg:classifiers":[
        {
            "category":"Banks & Credit Unions",
            "subcategory":"Bank",
            "type":"Services"
        }
    ],
    "sg:phone":"+39 0182 640091",
    "sg:postcode":"17021",
    "sg:province":"Savona",
    "wof:name":"Banca D'america E D'italia",
    "wof:placetype":"venue"
},
  "geometry": {"coordinates":[8.172996,44.008305],"type":"Point"}
}