{
  "type": "Feature",
  "properties": {
    "iso:country":"IT",
    "sg:address":"09131 Cagliari",
    "sg:city":"Cagliari",
    "sg:orig_category":"Tessuti Arredamento, Tende E Tappeti",
    "sg:phone":"+39 070 494784",
    "sg:postcode":"09131",
    "sg:province":"Cagliari",
    "wof:name":"Baratella Paul Centro Tende",
    "wof:placetype":"venue"
},
  "geometry": {"coordinates":[9.1284,39.226665],"type":"Point"}
}