{
  "type": "Feature",
  "properties": {
    "addr:full":"28047 Oleggio Oleggio Novara 28047",
    "addr:postcode":"28047;28047",
    "iso:country":"IT",
    "sg:address":"28047 Oleggio",
    "sg:city":"Oleggio",
    "sg:orig_category":"Imprese Di Costruzioni Civili Ed Industriali",
    "sg:phone":"+39 0321 998050",
    "sg:postcode":"28047",
    "sg:province":"Novara",
    "wof:name":"Furia Salvatore",
    "wof:placetype":"venue"
},
  "geometry": {"coordinates":[8.642652,45.593365],"type":"Point"}
}