{
  "type": "Feature",
  "properties": {
    "iso:country":"IT",
    "sg:address":"80036 Palma Campania",
    "sg:city":"Palma Campania",
    "sg:orig_category":"Impiantistica E Prodotti Tecnologici Per Edilizia. Elettronica Professionale E Di Consumo",
    "sg:phone":"+39 081 824 2153",
    "sg:postcode":"80036",
    "sg:province":"Napoli",
    "sg:website":"http://www.vfelectronics.com",
    "wof:name":"V.f. Electronics Srl",
    "wof:placetype":"venue"
},
  "geometry": {"coordinates":[14.55374,40.864521],"type":"Point"}
}