{
  "type": "Feature",
  "properties": {
    "addr:full":"57128 Livorno Livorno Livorno 57128",
    "addr:postcode":"57128;57128",
    "iso:country":"IT",
    "sg:address":"57128 Livorno",
    "sg:city":"Livorno",
    "sg:orig_category":"Carrozzelle E Poltrone Per Infermi",
    "sg:phone":"+39 0586 500440",
    "sg:postcode":"57128",
    "sg:province":"Livorno",
    "wof:name":"Centro Ortopedico Sanitari Ardenza",
    "wof:placetype":"venue"
},
  "geometry": {"coordinates":[10.322684,43.517189],"type":"Point"}
}