{
  "type": "Feature",
  "properties": {
    "iso:country":"IT",
    "sg:address":"Via Gregorcic 28 34170 Gorizia",
    "sg:city":"Gorizia",
    "sg:classifiers":[
        {
            "category":"Coffee & Tea",
            "type":"Food & Drink"
        }
    ],
    "sg:phone":"+39 0481 21971",
    "sg:postcode":"34170",
    "sg:province":"Gorizia",
    "sg:tags":[
        "aquavit"
    ],
    "wof:name":"Ciemme Liquori S.p.a.",
    "wof:placetype":"venue"
},
  "geometry": {"coordinates":[13.595297,45.915714],"type":"Point"}
}