{
  "type": "Feature",
  "properties": {
    "addr:full":"00133 Roma Roma Roma 00133",
    "addr:postcode":"00133;00133",
    "iso:country":"IT",
    "sg:address":"00133 Roma",
    "sg:city":"Roma",
    "sg:orig_category":"Scuole E Servizi Scolastici. Centri Di Estetica E Cosmesi E Servizi. Ricerca, Selezione E Formazione Del Personale",
    "sg:phone":"+39 06 202 3311",
    "sg:postcode":"00133",
    "sg:province":"Roma",
    "wof:name":"Ninfea Di Morelli Pierluigi & C. Snc",
    "wof:placetype":"venue"
},
  "geometry": {"coordinates":[12.438555,41.855312],"type":"Point"}
}