{
  "type": "Feature",
  "properties": {
    "addr:full":"Via Rostoncello 25 36010 Carre' Vicenza 36010",
    "addr:housenumber":"25",
    "addr:postcode":"36010;36010",
    "addr:street":"Via Rostoncello;Carre ' Vicenza",
    "iso:country":"IT",
    "sg:address":"Via Rostoncello 25 36010 Carre'",
    "sg:classifiers":[
        {
            "category":"Shopping",
            "subcategory":"Clothing, Apparel, & Fashions",
            "type":"Retail Goods"
        }
    ],
    "sg:phone":"+39 0445 315136",
    "sg:postcode":"36010",
    "sg:province":"Vicenza",
    "sg:tags":[
        "work",
        "clothes"
    ],
    "wof:name":"Simap S.r.l.",
    "wof:placetype":"venue"
},
  "geometry": {"coordinates":[11.443399,45.737965],"type":"Point"}
}