{
  "type": "Feature",
  "properties": {
    "iso:country":"IT",
    "sg:address":"80141 Napoli",
    "sg:city":"Napoli",
    "sg:orig_category":"Animali Domestici - Toeletta",
    "sg:phone":"+39 081 780 8021",
    "sg:postcode":"80141",
    "sg:province":"Napoli",
    "wof:name":"Laterza Dr. Bruno",
    "wof:placetype":"venue"
},
  "geometry": {"coordinates":[14.256747,40.869087],"type":"Point"}
}