{
  "type": "Feature",
  "properties": {
    "iso:country":"IT",
    "sg:address":"13043 Cigliano",
    "sg:city":"Cigliano",
    "sg:orig_category":"Articoli Medico-sanitari Ed Ortopedici. Impianti, Attrezzature E Forniture Sanitarie Ed Ospedaliere",
    "sg:phone":"+39 0161 426411",
    "sg:postcode":"13043",
    "sg:province":"Vercelli",
    "wof:name":"F.m. Srl",
    "wof:placetype":"venue"
},
  "geometry": {"coordinates":[8.429574,45.32378],"type":"Point"}
}