{
  "type": "Feature",
  "properties": {
    "addr:full":"34, Via Legnano 15100 Alessandria Alessandria Alessandria 15100",
    "addr:postcode":"15100;15100",
    "addr:street":"Via Legnano",
    "iso:country":"IT",
    "sg:address":"34, Via Legnano 15100 Alessandria",
    "sg:city":"Alessandria",
    "sg:classifiers":[
        {
            "category":"Professional",
            "subcategory":"Business Services",
            "type":"Services"
        }
    ],
    "sg:phone":"+39 0131 201511",
    "sg:postcode":"15100",
    "sg:province":"Alessandria",
    "sg:tags":[
        "advice"
    ],
    "wof:name":"Unione Industriale Della Provincia Di Alessandria",
    "wof:placetype":"venue"
},
  "geometry": {"coordinates":[8.610722,44.91069],"type":"Point"}
}