{
  "type": "Feature",
  "properties": {
    "iso:country":"IT",
    "sg:address":"87032 Amantea",
    "sg:city":"Amantea",
    "sg:orig_category":"Ristorazione E Locali Pubblici Affini. Ristoranti Ed Esercizi Affini. Servizi Ausiliari Di Ristorazione E Di Intrattenimento",
    "sg:phone":"+39 0982 424590",
    "sg:postcode":"87032",
    "sg:province":"Cosenza",
    "sg:website":"http://www.casalbergolatonnara.it",
    "wof:name":"Perri Giuseppe Casalbergo La Tonnara",
    "wof:placetype":"venue"
},
  "geometry": {"coordinates":[16.079268,39.104149],"type":"Point"}
}