{
  "type": "Feature",
  "properties": {
    "addr:full":"Via Arturo Toscanini 48/b 46043 Castiglione Delle Stiviere Castiglione delle Stiviere Mantova 46043",
    "addr:housenumber":"48 / b",
    "addr:postcode":"46043;46043",
    "addr:street":"Via Arturo Toscanini",
    "iso:country":"IT",
    "sg:address":"Via Arturo Toscanini 48/b 46043 Castiglione Delle Stiviere",
    "sg:city":"Castiglione delle Stiviere",
    "sg:classifiers":[
        {
            "category":"Wholesale",
            "subcategory":"Vending Machines",
            "type":"Manufacturing & Wholesale Goods"
        }
    ],
    "sg:phone":"+39 0376 638479",
    "sg:postcode":"46043",
    "sg:province":"Mantova",
    "sg:tags":[
        "packing",
        "baked",
        "pastry"
    ],
    "sg:website":"www.mbp.it",
    "wof:name":"M.b.p. S.r.l",
    "wof:placetype":"venue"
},
  "geometry": {"coordinates":[10.7976980209,45.1603660583],"type":"Point"}
}