{
  "type": "Feature",
  "properties": {
    "iso:country":"IT",
    "sg:address":"31028 Vazzola",
    "sg:city":"Vazzola",
    "sg:classifiers":[
        {
            "category":"Home & Garden",
            "subcategory":"Furniture",
            "type":"Retail Goods"
        }
    ],
    "sg:phone":"+39 0438 4441",
    "sg:postcode":"31028",
    "sg:province":"Treviso",
    "sg:tags":[
        "furnishing"
    ],
    "sg:website":"http://www.antarescucine.com",
    "wof:name":"Antares Cucine Spa",
    "wof:placetype":"venue"
},
  "geometry": {"coordinates":[12.3841495514,45.8279304504],"type":"Point"}
}