{
  "type": "Feature",
  "properties": {
    "addr:full":"10, Via Mozzi 24030 Mozzo Mozzo Bergamo 24030",
    "addr:postcode":"24030;24030",
    "addr:street":"Via Mozzi",
    "iso:country":"IT",
    "sg:address":"10, Via Mozzi 24030 Mozzo",
    "sg:city":"Mozzo",
    "sg:classifiers":[
        {
            "category":"Personal",
            "subcategory":"Shoe Repair & Shine",
            "type":"Services"
        }
    ],
    "sg:phone":"+39 39035527635",
    "sg:postcode":"24030",
    "sg:province":"Bergamo",
    "sg:tags":[
        "leather"
    ],
    "wof:name":"I.s.g. Italian Stylistic Group S.r.l.",
    "wof:placetype":"venue"
},
  "geometry": {"coordinates":[9.638453,45.675068],"type":"Point"}
}