{
  "type": "Feature",
  "properties": {
    "iso:country":"IT",
    "sg:address":"20123 Milano",
    "sg:city":"Milano",
    "sg:orig_category":"Avvocati, Notai E Servizi Legali. Consulenze Tecniche, Amministrative E Perizie",
    "sg:phone":"+39 02 4801 4216",
    "sg:postcode":"20123",
    "sg:province":"Milano",
    "wof:name":"Studio Torta S.r.l.",
    "wof:placetype":"venue"
},
  "geometry": {"coordinates":[9.173284,45.465725],"type":"Point"}
}