{
  "type": "Feature",
  "properties": {
    "addr:full":"235, V. Casalotti 00166 Roma Roma Roma 00166",
    "addr:housenumber":"235",
    "addr:postcode":"00166;00166",
    "addr:street":"V. Casalotti",
    "iso:country":"IT",
    "sg:address":"235, V. Casalotti 00166 Roma",
    "sg:city":"Roma",
    "sg:classifiers":[
        {
            "category":"Shopping",
            "subcategory":"Stationery & Office Supplies",
            "type":"Retail Goods"
        }
    ],
    "sg:postcode":"00166",
    "sg:province":"Roma",
    "sg:tags":[
        "professional"
    ],
    "sg:website":"http://www.paginegialle.it/romaeuropa2000",
    "wof:name":"Roma Europa 2000 Snc",
    "wof:placetype":"venue"
},
  "geometry": {"coordinates":[12.366651535,41.9150238037],"type":"Point"}
}