{
  "type": "Feature",
  "properties": {
    "iso:country":"IT",
    "sg:address":"24060 Castelli Calepio",
    "sg:city":"Castelli Calepio",
    "sg:orig_category":"Trattamenti Termici Metalli",
    "sg:phone":"+39 030 743 8859",
    "sg:postcode":"24060",
    "sg:province":"Bergamo",
    "wof:name":"Galvaniche F.b.",
    "wof:placetype":"venue"
},
  "geometry": {"coordinates":[9.893527,45.616623],"type":"Point"}
}