{
  "type": "Feature",
  "properties": {
    "addr:full":"30025 Teglio Veneto Teglio Veneto Venezia 30025",
    "addr:postcode":"30025;30025",
    "iso:country":"IT",
    "sg:address":"30025 Teglio Veneto",
    "sg:city":"Teglio Veneto",
    "sg:orig_category":"Forniture Per Attivita' Industriali",
    "sg:postcode":"30025",
    "sg:province":"Venezia",
    "wof:name":"Gentile Giuseppe",
    "wof:placetype":"venue"
},
  "geometry": {"coordinates":[12.8705835342,45.8190917969],"type":"Point"}
}