{
  "type": "Feature",
  "properties": {
    "addr:full":"46030 Dosolo Correggioverde Mantova 46030",
    "addr:postcode":"46030;46030",
    "iso:country":"IT",
    "sg:address":"46030 Dosolo",
    "sg:city":"Correggioverde",
    "sg:orig_category":"Legno E Semilavorati",
    "sg:phone":"+39 0375 86612",
    "sg:postcode":"46030",
    "sg:province":"Mantova",
    "wof:name":"G.g.l. Di Gozzi Gino Luigi & C. Snc",
    "wof:placetype":"venue"
},
  "geometry": {"coordinates":[10.616608,44.93185],"type":"Point"}
}