{
  "type": "Feature",
  "properties": {
    "iso:country":"IT",
    "sg:address":"20124 Milano",
    "sg:city":"Milano",
    "sg:orig_category":"Servizi Ausiliari Dei Mezzi Di Trasporto",
    "sg:phone":"+39 02 284 6001",
    "sg:postcode":"20124",
    "sg:province":"Milano",
    "wof:name":"Garage Macchi Di Gariboldi Paolo",
    "wof:placetype":"venue"
},
  "geometry": {"coordinates":[9.212481,45.489372],"type":"Point"}
}