{
  "type": "Feature",
  "properties": {
    "iso:country":"IT",
    "sg:address":"43013 Langhirano",
    "sg:city":"Langhirano",
    "sg:orig_category":"Prodotti Alimentari",
    "sg:phone":"+39 0521 354211",
    "sg:postcode":"43013",
    "sg:province":"Parma",
    "sg:website":"http://www.galloniprosciutto.it",
    "wof:name":"Galloni Fratelli Spa",
    "wof:placetype":"venue"
},
  "geometry": {"coordinates":[10.2385778427,44.6988716125],"type":"Point"}
}