{
  "type": "Feature",
  "properties": {
    "addr:full":"00198 Roma Roma Roma 00198",
    "addr:postcode":"00198;00198",
    "iso:country":"IT",
    "sg:address":"00198 Roma",
    "sg:city":"Roma",
    "sg:orig_category":"Servizi Culturali E Per Lo Spettacolo",
    "sg:phone":"+39 06 855 4305",
    "sg:postcode":"00198",
    "sg:province":"Roma",
    "wof:name":"Cinematografo Rouge Et Noir",
    "wof:placetype":"venue"
},
  "geometry": {"coordinates":[12.497826,41.912067],"type":"Point"}
}