{
  "type": "Feature",
  "properties": {
    "addr:full":"22060 Carugo Carugo Como 22060",
    "addr:postcode":"22060;22060",
    "iso:country":"IT",
    "sg:address":"22060 Carugo",
    "sg:city":"Carugo",
    "sg:orig_category":"Servizi E Lavori Per Arredamento E Industria Del Legno",
    "sg:phone":"+39 031 761267",
    "sg:postcode":"22060",
    "sg:province":"Como",
    "sg:website":"http://www.arredaesse.it",
    "wof:name":"Arredaesse Srl",
    "wof:placetype":"venue"
},
  "geometry": {"coordinates":[9.050306,45.743973],"type":"Point"}
}