{
  "type": "Feature",
  "properties": {
    "iso:country":"IT",
    "sg:address":"40064 Ozzano Dell'emilia",
    "sg:orig_category":"Zincatura Elettrolitica",
    "sg:phone":"+39 051 799385",
    "sg:postcode":"40064",
    "sg:province":"Bologna",
    "wof:name":"Zingal Srl",
    "wof:placetype":"venue"
},
  "geometry": {"coordinates":[11.503625,44.463188],"type":"Point"}
}