{
  "type": "Feature",
  "properties": {
    "addr:full":"Via Dei Ronchi 8 20045 Besana In Brianza Besana in Brianza Milano 20045",
    "addr:housenumber":"8",
    "addr:postcode":"20045;20045",
    "addr:street":"Via Dei Ronchi",
    "iso:country":"IT",
    "sg:address":"Via Dei Ronchi 8 20045 Besana In Brianza",
    "sg:city":"Besana in Brianza",
    "sg:classifiers":[
        {
            "category":"Organizations",
            "subcategory":"Labor Organization",
            "type":"Services"
        }
    ],
    "sg:phone":"+39 036 299 4357",
    "sg:postcode":"20045",
    "sg:province":"Milano",
    "sg:tags":[
        "varnishing",
        "painting",
        "system"
    ],
    "wof:name":"M.i. S.a.s.",
    "wof:placetype":"venue"
},
  "geometry": {"coordinates":[9.2626247406,45.6756629944],"type":"Point"}
}