{
  "type": "Feature",
  "properties": {
    "addr:full":"20019 Settimo Milanese Settimo Milanese Milano 20019",
    "addr:postcode":"20019;20019",
    "iso:country":"IT",
    "sg:address":"20019 Settimo Milanese",
    "sg:city":"Settimo Milanese",
    "sg:orig_category":"Articoli Pulizia",
    "sg:phone":"+39 02 4892 0270",
    "sg:postcode":"20019",
    "sg:province":"Milano",
    "sg:website":"http://www.braidlux.com",
    "wof:name":"Braidlux Srl",
    "wof:placetype":"venue"
},
  "geometry": {"coordinates":[9.072936,45.458527],"type":"Point"}
}