{
  "type": "Feature",
  "properties": {
    "addr:full":"38100 Trento Trento Trento 38100",
    "addr:postcode":"38100;38100",
    "iso:country":"IT",
    "sg:address":"38100 Trento",
    "sg:city":"Trento",
    "sg:orig_category":"Impianti Sportivi E Ricreativi - Attrezzature E Costruzione",
    "sg:phone":"+39 0461 826449",
    "sg:postcode":"38100",
    "sg:province":"Trento",
    "sg:website":"http://www.ecogrips.com",
    "wof:name":"Ecogrips Di David Jonathan Hall",
    "wof:placetype":"venue"
},
  "geometry": {"coordinates":[11.122849,46.083523],"type":"Point"}
}