{
  "type": "Feature",
  "properties": {
    "iso:country":"IT",
    "sg:address":"16149 Genova",
    "sg:city":"Genova",
    "sg:orig_category":"Macchine Ed Impianti Per Edilizia E Lavori Pubblici",
    "sg:phone":"+39 010 415314",
    "sg:postcode":"16149",
    "sg:province":"Genova",
    "wof:name":"Sardagru' S. R. L.",
    "wof:placetype":"venue"
},
  "geometry": {"coordinates":[8.904764,44.410954],"type":"Point"}
}