{
  "type": "Feature",
  "properties": {
    "iso:country":"IT",
    "sg:address":"14011 Baldichieri D'asti",
    "sg:orig_category":"Videogiochi, Flippers E Biliardini - Produzione E Ingrosso",
    "sg:phone":"+39 0141 66521",
    "sg:postcode":"14011",
    "sg:province":"Asti",
    "wof:name":"P.v. Games Di Pace Antonio Sas",
    "wof:placetype":"venue"
},
  "geometry": {"coordinates":[8.090796,44.905476],"type":"Point"}
}