{
  "type": "Feature",
  "properties": {
    "iso:country":"IT",
    "sg:address":"50123 Firenze",
    "sg:city":"Firenze",
    "sg:orig_category":"Tempo Libero - Articoli E Forniture. Automobili E Mezzi Di Trasporto. Riparazione Dei Mezzi Di Trasporto",
    "sg:phone":"+39 055 294296",
    "sg:postcode":"50123",
    "sg:province":"Firenze",
    "wof:name":"Scarpelli Snc",
    "wof:placetype":"venue"
},
  "geometry": {"coordinates":[11.246154,43.7738],"type":"Point"}
}