{
  "type": "Feature",
  "properties": {
    "addr:full":"Via G. Savonarola 67; Rovigo; 45100 Rovigo Rovigo 45100",
    "addr:housenumber":"67",
    "addr:postcode":"45100;45100",
    "addr:street":"Via G. Savonarola",
    "iso:country":"IT",
    "sg:address":"Via G. Savonarola 67; Rovigo; 45100",
    "sg:city":"Rovigo",
    "sg:classifiers":[
        {
            "category":"Banks & Credit Unions",
            "subcategory":"Bank",
            "type":"Services"
        }
    ],
    "sg:phone":"+39 0425 28680",
    "sg:postcode":"45100",
    "sg:province":"Rovigo",
    "wof:name":"Banca Popolare Veneta",
    "wof:placetype":"venue"
},
  "geometry": {"coordinates":[11.790598,45.040752],"type":"Point"}
}