{
  "type": "Feature",
  "properties": {
    "addr:full":"Via Majani Augusto 2 40122 Bologna Bologna Bologna 40122",
    "addr:housenumber":"2",
    "addr:postcode":"40122;40122",
    "addr:street":"Via Majani Augusto",
    "iso:country":"IT",
    "sg:address":"Via Majani Augusto 2 40122 Bologna",
    "sg:city":"Bologna",
    "sg:classifiers":[
        {
            "category":"Animal Shelter",
            "type":"Public Place"
        }
    ],
    "sg:phone":"+39 051 277011",
    "sg:postcode":"40122",
    "sg:province":"Bologna",
    "sg:tags":[
        "feedstuff",
        "raw",
        "material"
    ],
    "wof:name":"S.v.g Italia Srl",
    "wof:placetype":"venue"
},
  "geometry": {"coordinates":[11.346481,44.494221],"type":"Point"}
}