{
  "type": "Feature",
  "properties": {
    "iso:country":"IT",
    "sg:address":"50, Via Della Pace 28100 Novara",
    "sg:city":"Novara",
    "sg:classifiers":[
        {
            "category":"Parking",
            "subcategory":"Lot",
            "type":"Transportation"
        }
    ],
    "sg:phone":"+39 0321 477912",
    "sg:postcode":"28100",
    "sg:province":"Novara",
    "sg:tags":[
        "transport",
        "road"
    ],
    "wof:name":"The Best Int. Transport Srl",
    "wof:placetype":"venue"
},
  "geometry": {"coordinates":[8.611891,45.469456],"type":"Point"}
}