{
  "type": "Feature",
  "properties": {
    "iso:country":"IT",
    "sg:address":"10, Via Melilli 95121 Catania",
    "sg:city":"Catania",
    "sg:classifiers":[
        {
            "category":"Autos & Motor Vehicles",
            "subcategory":"Automobile Sales",
            "type":"Retail Goods"
        }
    ],
    "sg:phone":"+39 39095347511",
    "sg:postcode":"95121",
    "sg:province":"Catania",
    "sg:tags":[
        "industrial"
    ],
    "wof:name":"Comer Sud (s.p.a.)",
    "wof:placetype":"venue"
},
  "geometry": {"coordinates":[15.073309,37.472145],"type":"Point"}
}