{
  "type": "Feature",
  "properties": {
    "iso:country":"IT",
    "sg:address":"181, Viale Italia 19124 La Spezia",
    "sg:classifiers":[
        {
            "category":"Autos & Motor Vehicles",
            "subcategory":"Boat Sales",
            "type":"Retail Goods"
        }
    ],
    "sg:phone":"+39 0187 734995",
    "sg:province":"SP",
    "wof:name":"F.t.n. Forniture Tecniche Navali Snc",
    "wof:placetype":"venue"
},
  "geometry": {"coordinates":[9.834224,44.110863],"type":"Point"}
}