{
  "type": "Feature",
  "properties": {
    "iso:country":"IT",
    "sg:address":"18039 Ventimiglia",
    "sg:city":"Ventimiglia",
    "sg:classifiers":[
        {
            "category":"Health Services",
            "subcategory":"Health Practitioner",
            "type":"Services"
        }
    ],
    "sg:phone":"+39 0184 231951",
    "sg:postcode":"18039",
    "sg:province":"Imperia",
    "sg:tags":[
        "medici"
    ],
    "wof:name":"Centro Medico Sportivo 'r. Barilla'",
    "wof:placetype":"venue"
},
  "geometry": {"coordinates":[7.615696,43.789268],"type":"Point"}
}