{
  "type": "Feature",
  "properties": {
    "addr:full":"91100 Trapani Trapani Trapani 91100",
    "addr:postcode":"91100;91100",
    "iso:country":"IT",
    "sg:address":"91100 Trapani",
    "sg:city":"Trapani",
    "sg:orig_category":"Servizi Vari Di Interesse Pubblico",
    "sg:phone":"+39 0923 553334",
    "sg:postcode":"91100",
    "sg:province":"Trapani",
    "wof:name":"Il Paese Delle Meraviglie",
    "wof:placetype":"venue"
},
  "geometry": {"coordinates":[12.538327,38.018913],"type":"Point"}
}