{
  "type": "Feature",
  "properties": {
    "addr:full":"15100 Alessandria Alessandria Alessandria 15100",
    "addr:postcode":"15100;15100",
    "iso:country":"IT",
    "sg:address":"15100 Alessandria",
    "sg:city":"Alessandria",
    "sg:orig_category":"Servizi E Lavori Per Agricoltura E Zootecnia. Servizi E Lavori Industria Chimica. Servizi Ausiliari Di Analisi, Controllo E Ricerca",
    "sg:phone":"+39 0131 68632",
    "sg:postcode":"15100",
    "sg:province":"Alessandria",
    "wof:name":"Icea Istituto Per La Certificazione Etica Ed Ambientale",
    "wof:placetype":"venue"
},
  "geometry": {"coordinates":[8.607091,44.910675],"type":"Point"}
}