{
  "type": "Feature",
  "properties": {
    "addr:full":"28, Via Dell' Industria 35010 Borgoricco Borgoricco Padova 35010",
    "addr:postcode":"35010;35010",
    "addr:street":"Via Dell ' Industria",
    "iso:country":"IT",
    "sg:address":"28, Via Dell' Industria 35010 Borgoricco",
    "sg:city":"Borgoricco",
    "sg:classifiers":[
        {
            "category":"Professional",
            "subcategory":"Engineering",
            "type":"Services"
        }
    ],
    "sg:phone":"+39 049 933 6379",
    "sg:postcode":"35010",
    "sg:province":"Padova",
    "sg:tags":[
        "machine",
        "-",
        "mechanical"
    ],
    "wof:name":"Plastic Systems S.r.l.",
    "wof:placetype":"venue"
},
  "geometry": {"coordinates":[11.955914,45.534458],"type":"Point"}
}