{
  "type": "Feature",
  "properties": {
    "iso:country":"IT",
    "sg:address":"00054 Fiumicino",
    "sg:city":"Fiumicino",
    "sg:orig_category":"Forniture Per Agricoltura E Zootecnia. Prodotti Chimici Secondari. Macchine E Forniture Per Ecologia E Smaltimento Rifiuti",
    "sg:phone":"+39 06 652 2797",
    "sg:postcode":"00054",
    "sg:province":"Roma",
    "wof:name":"Guiducci Pietro",
    "wof:placetype":"venue"
},
  "geometry": {"coordinates":[12.2308530807,41.7648506165],"type":"Point"}
}