{
  "type": "Feature",
  "properties": {
    "addr:full":"24068 Seriate Seriate Bergamo 24068",
    "addr:postcode":"24068;24068",
    "iso:country":"IT",
    "sg:address":"24068 Seriate",
    "sg:city":"Seriate",
    "sg:orig_category":"Macchine E Forniture Per Arredamento E Industria Del Legno",
    "sg:phone":"+39 035 295302",
    "sg:postcode":"24068",
    "sg:province":"Bergamo",
    "wof:name":"Lorenzi Macchine",
    "wof:placetype":"venue"
},
  "geometry": {"coordinates":[9.727594,45.688652],"type":"Point"}
}