{
  "type": "Feature",
  "properties": {
    "iso:country":"IT",
    "sg:address":"65121 Pescara",
    "sg:city":"Pescara",
    "sg:orig_category":"Pubblicita' Diretta",
    "sg:phone":"+39 085 421 5780",
    "sg:postcode":"65121",
    "sg:province":"Pescara",
    "wof:name":"Traversa Teodolinda - Promoservice",
    "wof:placetype":"venue"
},
  "geometry": {"coordinates":[14.214887619,42.4663505554],"type":"Point"}
}