{
  "type": "Feature",
  "properties": {
    "iso:country":"IT",
    "sg:address":"4, Via Statale 45 Bis 25020 Poncarale",
    "sg:city":"Poncarale",
    "sg:classifiers":[
        {
            "category":"Autos & Motor Vehicles",
            "subcategory":"Automobile Sales",
            "type":"Retail Goods"
        }
    ],
    "sg:phone":"+39 030 264 0100",
    "sg:postcode":"25020",
    "sg:province":"Brescia",
    "sg:tags":[
        "equipment",
        "transport"
    ],
    "wof:name":"Ancilla Scalvini S.p.a.",
    "wof:placetype":"venue"
},
  "geometry": {"coordinates":[10.21022,45.470486],"type":"Point"}
}