{
  "type": "Feature",
  "properties": {
    "addr:full":"74015 Martina Franca Martina Franca Taranto 74015",
    "addr:housenumber":"74015",
    "addr:postcode":"74015",
    "iso:country":"IT",
    "sg:address":"74015 Martina Franca",
    "sg:city":"Martina Franca",
    "sg:orig_category":"Prodotti Cosmetici E Da Toeletta",
    "sg:phone":"+39 080 430 3461",
    "sg:postcode":"74015",
    "sg:province":"Taranto",
    "wof:name":"Agrusta Donato",
    "wof:placetype":"venue"
},
  "geometry": {"coordinates":[17.3343582153,40.7042655945],"type":"Point"}
}