{
  "type": "Feature",
  "properties": {
    "iso:country":"IT",
    "sg:address":"92100 Agrigento",
    "sg:city":"Agrigento",
    "sg:classifiers":[
        {
            "category":"Bars & Pubs",
            "subcategory":"Champagne Bar",
            "type":"Food & Drink"
        }
    ],
    "sg:phone":"+39 0922 598686",
    "sg:postcode":"92100",
    "sg:province":"Agrigento",
    "sg:tags":[
        "caffe'",
        "e"
    ],
    "wof:name":"Bar Simboly",
    "wof:placetype":"venue"
},
  "geometry": {"coordinates":[13.562466,37.297092],"type":"Point"}
}