{
  "type": "Feature",
  "properties": {
    "iso:country":"IT",
    "sg:address":"Via Roccolo 2 21048 Solbiate Arno",
    "sg:city":"Solbiate Arno",
    "sg:orig_category":"Rings, Rolled",
    "sg:phone":"+39 0331 999600",
    "sg:postcode":"21048",
    "sg:province":"Varese",
    "sg:website":"www.mollasrl.it",
    "wof:name":"Molla Srl",
    "wof:placetype":"venue"
},
  "geometry": {"coordinates":[8.815057,45.723118],"type":"Point"}
}