{
  "type": "Feature",
  "properties": {
    "addr:full":"14, Via Torino 21013 Gallarate Gallarate Varese 21013",
    "addr:postcode":"21013;21013",
    "addr:street":"Via Torino",
    "iso:country":"IT",
    "sg:address":"14, Via Torino 21013 Gallarate",
    "sg:city":"Gallarate",
    "sg:classifiers":[
        {
            "category":"Communications",
            "subcategory":"Newspaper",
            "type":"Services"
        }
    ],
    "sg:phone":"+39 0331 797010",
    "sg:postcode":"21013",
    "sg:province":"Varese",
    "sg:tags":[
        "advertising"
    ],
    "wof:name":"Tps S.r.l.",
    "wof:placetype":"venue"
},
  "geometry": {"coordinates":[8.796625,45.654156],"type":"Point"}
}