{
  "type": "Feature",
  "properties": {
    "addr:full":"Via Del Mella 13 25131 Brescia Brescia Brescia 25131",
    "addr:housenumber":"13",
    "addr:postcode":"25131;25131",
    "addr:street":"Via Del Mella",
    "iso:country":"IT",
    "sg:address":"Via Del Mella 13 25131 Brescia",
    "sg:city":"Brescia",
    "sg:orig_category":"Mining Machinery For Underground Mining",
    "sg:phone":"+39 030 265 9625",
    "sg:postcode":"25131",
    "sg:province":"Brescia",
    "wof:name":"F.p.e. Srl - Fluid Power Equipment",
    "wof:placetype":"venue"
},
  "geometry": {"coordinates":[10.224524498,45.4819030762],"type":"Point"}
}