{
  "type": "Feature",
  "properties": {
    "iso:country":"IT",
    "sg:address":"1 Via Porta Carlo, 20121 Milano",
    "sg:city":"Milano",
    "sg:classifiers":[
        {
            "category":"Banks & Credit Unions",
            "subcategory":"Financial Services",
            "type":"Services"
        }
    ],
    "sg:phone":"+39 39026596126",
    "sg:postcode":"20121",
    "sg:province":"Milano",
    "sg:tags":[
        "banking",
        "finance",
        "insurance"
    ],
    "wof:name":"Finleasing Lombarda (spa)",
    "wof:placetype":"venue"
},
  "geometry": {"coordinates":[9.194606781,45.4739532471],"type":"Point"}
}