{
  "type": "Feature",
  "properties": {
    "iso:country":"IT",
    "sg:address":"35122 Padova",
    "sg:city":"Padova",
    "sg:orig_category":"Pubblica Amministrazione",
    "sg:phone":"+39 0982 05111",
    "sg:postcode":"35122",
    "sg:province":"Padova",
    "sg:website":"http://www.comune.padova.it",
    "wof:name":"Comune Di Padova",
    "wof:placetype":"venue"
},
  "geometry": {"coordinates":[11.8638439178,45.3199195862],"type":"Point"}
}