{
  "type": "Feature",
  "properties": {
    "addr:full":"Vle Dell' Industria 5 37036 San Martino Buon Albergo San Martino Buon Albergo Verona 37036",
    "addr:housenumber":"5",
    "addr:postcode":"37036;buon albergo;37036",
    "addr:street":"Vle Dell ' Industria",
    "iso:country":"IT",
    "sg:address":"Vle Dell' Industria 5 37036 San Martino Buon Albergo",
    "sg:city":"San Martino Buon Albergo",
    "sg:classifiers":[
        {
            "category":"Sports & Exercise",
            "subcategory":"Race Track",
            "type":"Entertainment"
        }
    ],
    "sg:phone":"+39 045 887 1333",
    "sg:postcode":"37036",
    "sg:province":"Verona",
    "sg:tags":[
        "tincture"
    ],
    "wof:name":"T.r.t. Tintoria Resinatura Tessuti",
    "wof:placetype":"venue"
},
  "geometry": {"coordinates":[10.991748,45.438366],"type":"Point"}
}