{
  "type": "Feature",
  "properties": {
    "addr:full":"Corso Sicilia 30; Catania; 95131 Catania Catania 95131",
    "addr:housenumber":"30",
    "addr:postcode":"95131;95131",
    "addr:street":"Corso Sicilia",
    "iso:country":"IT",
    "sg:address":"Corso Sicilia 30; Catania; 95131",
    "sg:city":"Catania",
    "sg:classifiers":[
        {
            "category":"Banks & Credit Unions",
            "subcategory":"Bank",
            "type":"Services"
        }
    ],
    "sg:phone":"+39 095 231111",
    "sg:postcode":"95131",
    "sg:province":"Catania",
    "wof:name":"Banca Nazionale Del Lavoro Spa",
    "wof:placetype":"venue"
},
  "geometry": {"coordinates":[15.088584,37.507469],"type":"Point"}
}