{
  "type": "Feature",
  "properties": {
    "iso:country":"IT",
    "sg:address":"07041 Alghero",
    "sg:city":"Alghero",
    "sg:orig_category":"Prodotti Alimentari",
    "sg:phone":"+39 079 951254",
    "sg:postcode":"07041",
    "sg:province":"Sassari",
    "wof:name":"Delogu Michelangelo",
    "wof:placetype":"venue"
},
  "geometry": {"coordinates":[8.316069603,40.5766296387],"type":"Point"}
}