{
  "type": "Feature",
  "properties": {
    "addr:full":"46/c, Viale Del Lavoro 37036 San Martino Buon Albergo San Martino Buon Albergo Verona 37036",
    "addr:housenumber":"46 / c",
    "addr:postcode":"37036;buon albergo;37036",
    "addr:street":"Viale Del Lavoro",
    "iso:country":"IT",
    "sg:address":"46/c, Viale Del Lavoro 37036 San Martino Buon Albergo",
    "sg:city":"San Martino Buon Albergo",
    "sg:classifiers":[
        {
            "category":"Professional",
            "subcategory":"Printing & Photocopies",
            "type":"Services"
        }
    ],
    "sg:phone":"+39 045 878 0622",
    "sg:postcode":"37036",
    "sg:province":"Verona",
    "wof:name":"Scanner Service (s.r.l.)",
    "wof:placetype":"venue"
},
  "geometry": {"coordinates":[11.0424833298,45.388961792],"type":"Point"}
}