{
  "type": "Feature",
  "properties": {
    "iso:country":"IT",
    "sg:address":"13900 Biella",
    "sg:city":"Biella",
    "sg:orig_category":"Sport - Articoli E Forniture",
    "sg:phone":"+39 015 21511",
    "sg:postcode":"13900",
    "sg:province":"Biella",
    "wof:name":"Senini Vincenzo",
    "wof:placetype":"venue"
},
  "geometry": {"coordinates":[8.059948,45.563202],"type":"Point"}
}