{
  "type": "Feature",
  "properties": {
    "iso:country":"IT",
    "sg:address":"95127 Catania",
    "sg:city":"Catania",
    "sg:orig_category":"Macchine, Impianti Ed Attrezzature Industria Chimica",
    "sg:phone":"+39 095 434804",
    "sg:postcode":"95127",
    "sg:province":"Catania",
    "wof:name":"Petrolite Italiana (s.p.a.)",
    "wof:placetype":"venue"
},
  "geometry": {"coordinates":[15.09145,37.519596],"type":"Point"}
}