{
  "type": "Feature",
  "properties": {
    "addr:full":"350/19, Via Manin Daniele 20099 Sesto San Giovanni Sesto San Giovanni Milano 20099",
    "addr:housenumber":"350 / 19",
    "addr:postcode":"20099;20099",
    "addr:street":"Via Manin Daniele",
    "iso:country":"IT",
    "sg:address":"350/19, Via Manin Daniele 20099 Sesto San Giovanni",
    "sg:city":"Sesto San Giovanni",
    "sg:classifiers":[
        {
            "category":"Shopping",
            "subcategory":"Computers & Home Electronics",
            "type":"Retail Goods"
        }
    ],
    "sg:phone":"+39 39022410181",
    "sg:postcode":"20099",
    "sg:province":"Milano",
    "sg:tags":[
        "electronic",
        "electrical",
        "equipment"
    ],
    "wof:name":"Cosme S.r.l.",
    "wof:placetype":"venue"
},
  "geometry": {"coordinates":[9.256093,45.521233],"type":"Point"}
}