{
  "type": "Feature",
  "properties": {
    "iso:country":"IT",
    "sg:address":"V Aretin Sieci; Pontassieve; 50065",
    "sg:city":"Pontassieve",
    "sg:classifiers":[
        {
            "category":"Banks & Credit Unions",
            "subcategory":"Bank",
            "type":"Services"
        }
    ],
    "sg:phone":"+39 055 836 3008",
    "sg:postcode":"50065",
    "sg:province":"Firenze",
    "wof:name":"Cassa Di Risparmio Di Firenze",
    "wof:placetype":"venue"
},
  "geometry": {"coordinates":[11.396597,43.78701],"type":"Point"}
}