{
  "type": "Feature",
  "properties": {
    "iso:country":"IT",
    "sg:address":"00151 Roma",
    "sg:city":"Roma",
    "sg:orig_category":"Abbigliamento Intimo, Calze E Costumi Da Bagno",
    "sg:phone":"+39 06 5823 0803",
    "sg:postcode":"00151",
    "sg:province":"Roma",
    "wof:name":"Sereni Di Angelo E Giacomo Sereni & C. Sas",
    "wof:placetype":"venue"
},
  "geometry": {"coordinates":[12.444886,41.871506],"type":"Point"}
}