{
  "type": "Feature",
  "properties": {
    "addr:full":"30123 Venezia Dorsoduro Venezia 30123",
    "addr:postcode":"30123;30123",
    "iso:country":"IT",
    "sg:address":"30123 Venezia",
    "sg:city":"Dorsoduro",
    "sg:orig_category":"Acciaierie E Fonderie",
    "sg:phone":"+39 041 522 4195",
    "sg:postcode":"30123",
    "sg:province":"Venezia",
    "wof:name":"Rosettin Diego",
    "wof:placetype":"venue"
},
  "geometry": {"coordinates":[12.325557,45.433952],"type":"Point"}
}