{
  "type": "Feature",
  "properties": {
    "addr:full":"Via Roma 272; Colle Salvetti; 57014 Livorno 57014",
    "addr:housenumber":"272",
    "addr:postcode":"57014;57014",
    "addr:street":"Via Roma;Salvetti",
    "iso:country":"IT",
    "sg:address":"Via Roma 272; Colle Salvetti; 57014",
    "sg:classifiers":[
        {
            "category":"Banks & Credit Unions",
            "subcategory":"Bank",
            "type":"Services"
        }
    ],
    "sg:phone":"+39 0586 962016",
    "sg:postcode":"57014",
    "sg:province":"Livorno",
    "wof:name":"Banca Toscana Spa",
    "wof:placetype":"venue"
},
  "geometry": {"coordinates":[10.474422,43.589581],"type":"Point"}
}