{
  "type": "Feature",
  "properties": {
    "addr:full":"90040 Giardinello Giardinello Palermo 90040",
    "addr:postcode":"90040;90040",
    "iso:country":"IT",
    "sg:address":"90040 Giardinello",
    "sg:city":"Giardinello",
    "sg:orig_category":"Prodotti Alimentari",
    "sg:phone":"+39 091 898 4683",
    "sg:postcode":"90040",
    "sg:province":"Palermo",
    "sg:website":"http://www.provenzano.it",
    "wof:name":"Alimentari Provenzano Srl",
    "wof:placetype":"venue"
},
  "geometry": {"coordinates":[13.1581230164,38.0891990662],"type":"Point"}
}