{
  "type": "Feature",
  "properties": {
    "addr:full":"59100 Prato Prato Prato 59100",
    "addr:postcode":"59100;59100",
    "iso:country":"IT",
    "sg:address":"59100 Prato",
    "sg:city":"Prato",
    "sg:orig_category":"Servizi E Lavori Per Abbigliamento E Pelletterie",
    "sg:phone":"+39 0574 577041",
    "sg:postcode":"59100",
    "sg:province":"Prato",
    "wof:name":"Vela Srl",
    "wof:placetype":"venue"
},
  "geometry": {"coordinates":[11.106703,43.860168],"type":"Point"}
}