{
  "type": "Feature",
  "properties": {
    "addr:full":"Via Nenni 9 45026 Lendinara Lendinara Rovigo 45026",
    "addr:housenumber":"9",
    "addr:postcode":"45026;45026",
    "addr:street":"Via Nenni",
    "iso:country":"IT",
    "sg:address":"Via Nenni 9 45026 Lendinara",
    "sg:city":"Lendinara",
    "sg:orig_category":"Monofilaments",
    "sg:phone":"+39 0425 641254",
    "sg:postcode":"45026",
    "sg:province":"Rovigo",
    "sg:website":"www.neofibre.it",
    "wof:name":"Neofibre Bresciani Spa",
    "wof:placetype":"venue"
},
  "geometry": {"coordinates":[11.6362705231,45.0277061462],"type":"Point"}
}