{
  "type": "Feature",
  "properties": {
    "iso:country":"IT",
    "sg:address":"56126 Pisa",
    "sg:city":"Pisa",
    "sg:orig_category":"Servizi E Lavori Per Abbigliamento E Pelletterie",
    "sg:phone":"+39 050 48353",
    "sg:postcode":"56126",
    "sg:province":"Pisa",
    "wof:name":"Speedy Wash Di Perrotti Carmela",
    "wof:placetype":"venue"
},
  "geometry": {"coordinates":[10.395217,43.716843],"type":"Point"}
}