{
  "type": "Feature",
  "properties": {
    "iso:country":"IT",
    "sg:address":"36050 Bolzano Vicentino",
    "sg:city":"Bolzano Vicentino",
    "sg:orig_category":"Macchine, Impianti E Forniture Per Industria Grafica, Cartaria E Cartotecnica. Automazione E Macchine Per Ufficio",
    "sg:phone":"+39 0444 354300",
    "sg:postcode":"36050",
    "sg:province":"Vicenza",
    "wof:name":"Maner Srl",
    "wof:placetype":"venue"
},
  "geometry": {"coordinates":[11.634526,45.602417],"type":"Point"}
}