{
  "type": "Feature",
  "properties": {
    "iso:country":"IT",
    "sg:address":"42014 Castellarano",
    "sg:orig_category":"Ceramiche E Refrattari - Impianti, Macchine E Materiali",
    "sg:phone":"+39 0536 850451",
    "sg:postcode":"42014",
    "sg:province":"Reggio Nell'Emilia",
    "wof:name":"Officina Alce Snc",
    "wof:placetype":"venue"
},
  "geometry": {"coordinates":[10.627794,44.696228],"type":"Point"}
}