{
  "type": "Feature",
  "properties": {
    "addr:full":"Via Verona 10 36020 Pove Del Grappa Pove del Grappa Vicenza 36020",
    "addr:housenumber":"10",
    "addr:postcode":"36020;36020",
    "addr:street":"Via Verona",
    "iso:country":"IT",
    "sg:address":"Via Verona 10 36020 Pove Del Grappa",
    "sg:city":"Pove del Grappa",
    "sg:classifiers":[
        {
            "category":"Manufacturing",
            "subcategory":"Rubber & Plastics",
            "type":"Manufacturing & Wholesale Goods"
        }
    ],
    "sg:phone":"+39 0424 80654",
    "sg:postcode":"36020",
    "sg:province":"Vicenza",
    "sg:tags":[
        "coating"
    ],
    "sg:website":"www.sigmaproduzioni.it",
    "wof:name":"Sigma Produzioni Spa",
    "wof:placetype":"venue"
},
  "geometry": {"coordinates":[11.7227878571,45.7906608582],"type":"Point"}
}