{
  "type": "Feature",
  "properties": {
    "iso:country":"IT",
    "sg:address":"00040 Pomezia",
    "sg:city":"Pomezia",
    "sg:orig_category":"Prodotti E Manufatti In Materie Plastiche",
    "sg:phone":"+39 06 912 1065",
    "sg:postcode":"00040",
    "sg:province":"Roma",
    "wof:name":"Repsol Polivar Spa",
    "wof:placetype":"venue"
},
  "geometry": {"coordinates":[12.4959793091,41.6900100708],"type":"Point"}
}