{
  "type": "Feature",
  "properties": {
    "iso:country":"IT",
    "sg:address":"50123 Firenze",
    "sg:city":"Firenze",
    "sg:orig_category":"Agriturismo",
    "sg:phone":"+39 055 281877",
    "sg:postcode":"50123",
    "sg:province":"Firenze",
    "wof:name":"Hotel Stella Mary",
    "wof:placetype":"venue"
},
  "geometry": {"coordinates":[11.249726,43.777702],"type":"Point"}
}