{
  "type": "Feature",
  "properties": {
    "iso:country":"IT",
    "sg:address":"39049 Vipiteno",
    "sg:city":"Vipiteno",
    "sg:orig_category":"Imprese Di Costruzioni Civili Ed Industriali",
    "sg:phone":"+39 0472 764463",
    "sg:postcode":"39049",
    "sg:province":"Bolzano/Bozen",
    "wof:name":"Wipptaler Bau A.g.",
    "wof:placetype":"venue"
},
  "geometry": {"coordinates":[11.081414,45.929028],"type":"Point"}
}