{
  "type": "Feature",
  "properties": {
    "iso:country":"IT",
    "sg:address":"Via Risorgimento 384/2 40069 Zola Predosa",
    "sg:city":"Zola",
    "sg:classifiers":[
        {
            "category":"Shopping",
            "subcategory":"Clothing, Apparel, & Fashions",
            "type":"Retail Goods"
        }
    ],
    "sg:phone":"+39 051 756930",
    "sg:postcode":"40069",
    "sg:province":"Bologna",
    "sg:tags":[
        "blouse",
        "ladies'",
        "dress"
    ],
    "sg:website":"www.ritaenne.it",
    "wof:name":"Rita Enne Sas",
    "wof:placetype":"venue"
},
  "geometry": {"coordinates":[11.245013,44.484306],"type":"Point"}
}