{
  "type": "Feature",
  "properties": {
    "iso:country":"IT",
    "sg:address":"19032 Lerici",
    "sg:city":"Lerici",
    "sg:orig_category":"Non-classified Establishments",
    "sg:phone":"+39 0187 280355",
    "sg:postcode":"19032",
    "sg:province":"La Spezia",
    "wof:name":"La Timoniera",
    "wof:placetype":"venue"
},
  "geometry": {"coordinates":[9.923468,44.070442],"type":"Point"}
}