{
  "type": "Feature",
  "properties": {
    "iso:country":"IT",
    "sg:address":"20143 Milano",
    "sg:city":"Milano",
    "sg:orig_category":"Ospedali E Servizi Sanitari. Servizi Sociali",
    "sg:phone":"+39 02 813 4711",
    "sg:postcode":"20143",
    "sg:province":"Milano",
    "wof:name":"Cooperativa Sociale Graffiti A Responsabilita' Limitata",
    "wof:placetype":"venue"
},
  "geometry": {"coordinates":[9.159029,45.441505],"type":"Point"}
}