{
  "type": "Feature",
  "properties": {
    "addr:full":"20048 Carate Brianza Carate Brianza Milano 20048",
    "addr:postcode":"20048;20048",
    "iso:country":"IT",
    "sg:address":"20048 Carate Brianza",
    "sg:city":"Carate Brianza",
    "sg:orig_category":"Articoli Per Imballaggio E Confezionamento",
    "sg:phone":"+39 036 299 3016",
    "sg:postcode":"20048",
    "sg:province":"Milano",
    "wof:name":"Anfra Di Bona Angelo",
    "wof:placetype":"venue"
},
  "geometry": {"coordinates":[9.238965,45.662987],"type":"Point"}
}