{
  "type": "Feature",
  "properties": {
    "addr:full":"89029 Taurianova Taurianova Reggio Di Calabria 89029",
    "addr:postcode":"89029;89029",
    "iso:country":"IT",
    "sg:address":"89029 Taurianova",
    "sg:city":"Taurianova",
    "sg:orig_category":"Cartotecnica E Servizi. Articoli Per Imballaggio E Confezionamento",
    "sg:phone":"+39 0965 610647",
    "sg:postcode":"89029",
    "sg:province":"Reggio Di Calabria",
    "wof:name":"Meridional Plast Srl",
    "wof:placetype":"venue"
},
  "geometry": {"coordinates":[15.650137,38.114689],"type":"Point"}
}