{
  "type": "Feature",
  "properties": {
    "iso:country":"IT",
    "sg:address":"20131 Milano",
    "sg:city":"Milano",
    "sg:orig_category":"Musica",
    "sg:phone":"+39 02 284 0271",
    "sg:postcode":"20131",
    "sg:province":"Milano",
    "wof:name":"Video Express",
    "wof:placetype":"venue"
},
  "geometry": {"coordinates":[9.2280368805,45.4860801697],"type":"Point"}
}