{
  "type": "Feature",
  "properties": {
    "iso:country":"IT",
    "sg:address":"31049 Valdobbiadene",
    "sg:city":"Valdobbiadene",
    "sg:orig_category":"Elettrotecnica Industriale, Prodotti E Apparecchiature",
    "sg:phone":"+39 0423 982107",
    "sg:postcode":"31049",
    "sg:province":"Treviso",
    "wof:name":"Zp Motori Elettrici Srl",
    "wof:placetype":"venue"
},
  "geometry": {"coordinates":[12.009171,45.870064],"type":"Point"}
}