{
  "type": "Feature",
  "properties": {
    "iso:country":"IT",
    "sg:address":"Via Bernini 1/a 21010 Besnate",
    "sg:city":"Besnate",
    "sg:classifiers":[
        {
            "category":"Home & Garden",
            "subcategory":"Building Materials",
            "type":"Retail Goods"
        }
    ],
    "sg:phone":"+39 0331 275750",
    "sg:postcode":"21010",
    "sg:province":"Varese",
    "sg:tags":[
        "installation",
        "electric"
    ],
    "sg:website":"www.cdrelettronica.it",
    "wof:name":"Cdr Elettronica Srl",
    "wof:placetype":"venue"
},
  "geometry": {"coordinates":[8.826385,45.817604],"type":"Point"}
}