{
  "type": "Feature",
  "properties": {
    "addr:full":"38042 Baselga Di Pin\u00e8 San Mauro Trento 38042",
    "addr:postcode":"38042;38042",
    "iso:country":"IT",
    "sg:address":"38042 Baselga Di Pin\u00e8",
    "sg:city":"San Mauro",
    "sg:orig_category":"Porfidi E Pietre Per Pavimenti E Rivestimenti",
    "sg:phone":"+39 0461 557473",
    "sg:postcode":"38042",
    "sg:province":"Trento",
    "wof:name":"Compagnia Produttori Porfido Pin\u00c8 Srl",
    "wof:placetype":"venue"
},
  "geometry": {"coordinates":[11.257484436,46.1243057251],"type":"Point"}
}