{
  "type": "Feature",
  "properties": {
    "iso:country":"IT",
    "sg:address":"82021 Apice",
    "sg:city":"Apice",
    "sg:orig_category":"Servizi Per Lo Sport E Il Tempo Libero. Servizi Al Turismo",
    "sg:phone":"+39 0824 922885",
    "sg:postcode":"82021",
    "sg:province":"Benevento",
    "wof:name":"Babylandia Di Porcelli Bianca Maria",
    "wof:placetype":"venue"
},
  "geometry": {"coordinates":[14.912485,41.11832],"type":"Point"}
}