{
  "type": "Feature",
  "properties": {
    "addr:full":"80144 Napoli Napoli Napoli 80144",
    "addr:housenumber":"80144",
    "addr:postcode":"80144",
    "iso:country":"IT",
    "sg:address":"80144 Napoli",
    "sg:city":"Napoli",
    "sg:classifiers":[
        {
            "category":"Parking",
            "subcategory":"Lot",
            "type":"Transportation"
        }
    ],
    "sg:phone":"+39 081 579 9808",
    "sg:postcode":"80144",
    "sg:province":"Napoli",
    "sg:tags":[
        "good",
        "shipment",
        "transport"
    ],
    "wof:name":"Simeoli Ferdinando",
    "wof:placetype":"venue"
},
  "geometry": {"coordinates":[14.25949,40.900028],"type":"Point"}
}