{
  "type": "Feature",
  "properties": {
    "iso:country":"IT",
    "sg:address":"Via Teodosio, 55; Milano; 20131",
    "sg:city":"Milano",
    "sg:classifiers":[
        {
            "category":"Banks & Credit Unions",
            "subcategory":"Bank",
            "type":"Services"
        }
    ],
    "sg:phone":"+39 02 289 4478",
    "sg:postcode":"20131",
    "sg:province":"Milano",
    "wof:name":"Credito Lombardo",
    "wof:placetype":"venue"
},
  "geometry": {"coordinates":[9.229878,45.486187],"type":"Point"}
}