{
  "type": "Feature",
  "properties": {
    "iso:country":"IT",
    "sg:address":"Via Orna, 38/62 36040 Brendola",
    "sg:city":"Brendola",
    "sg:classifiers":[
        {
            "category":"Organizations",
            "subcategory":"Labor Organization",
            "type":"Services"
        }
    ],
    "sg:phone":"+39 0444 601401",
    "sg:postcode":"36040",
    "sg:province":"Vicenza",
    "sg:tags":[
        "woodworking",
        "machinery"
    ],
    "wof:name":"Imef Sas",
    "wof:placetype":"venue"
},
  "geometry": {"coordinates":[11.432014,45.480385],"type":"Point"}
}