{
  "type": "Feature",
  "properties": {
    "addr:full":"Via E. Longoni 3; Roma",
    "addr:housenumber":"3",
    "addr:street":"Via E. Longoni",
    "iso:country":"IT",
    "sg:address":"Via E. Longoni 3; Roma",
    "sg:classifiers":[
        {
            "category":"Banks & Credit Unions",
            "subcategory":"Bank",
            "type":"Services"
        }
    ],
    "sg:phone":"+39 06 565 1490",
    "wof:name":"Banca Di Roma",
    "wof:placetype":"venue"
},
  "geometry": {"coordinates":[12.603319,41.893383],"type":"Point"}
}