{
  "type": "Feature",
  "properties": {
    "addr:full":"48, Via Gandhi 41100 Modena Modena Modena 41100",
    "addr:postcode":"41100;41100",
    "addr:street":"Via Gandhi",
    "iso:country":"IT",
    "sg:address":"48, Via Gandhi 41100 Modena",
    "sg:city":"Modena",
    "sg:classifiers":[
        {
            "category":"Professional",
            "subcategory":"Engineering",
            "type":"Services"
        }
    ],
    "sg:phone":"+39 39059251051",
    "sg:postcode":"41100",
    "sg:province":"Modena",
    "sg:tags":[
        "machine",
        "-",
        "mechanical"
    ],
    "wof:name":"B.z.v. (s.r.l.)",
    "wof:placetype":"venue"
},
  "geometry": {"coordinates":[10.964642,44.658726],"type":"Point"}
}