{
  "type": "Feature",
  "properties": {
    "iso:country":"IT",
    "sg:address":"70011 Alberobello",
    "sg:city":"Alberobello",
    "sg:orig_category":"Carpenterie Metalliche",
    "sg:phone":"+39 080 432 2678",
    "sg:postcode":"70011",
    "sg:province":"Bari",
    "wof:name":"Fratelli Plantone Stefano E Pietro Snc",
    "wof:placetype":"venue"
},
  "geometry": {"coordinates":[17.231178,40.782818],"type":"Point"}
}