{
  "type": "Feature",
  "properties": {
    "iso:country":"IT",
    "sg:address":"37026 Pescantina",
    "sg:city":"Pescantina",
    "sg:orig_category":"Macchine, Impianti E Forniture Per Industria Grafica, Cartaria E Cartotecnica",
    "sg:phone":"+39 045 670 0298",
    "sg:postcode":"37026",
    "sg:province":"Verona",
    "wof:name":"V.a.s. (s.p.a.)",
    "wof:placetype":"venue"
},
  "geometry": {"coordinates":[10.907929,45.476891],"type":"Point"}
}