{
  "type": "Feature",
  "properties": {
    "addr:full":"70126 Bari Bari Bari 70126",
    "addr:postcode":"70126;70126",
    "iso:country":"IT",
    "sg:address":"70126 Bari",
    "sg:city":"Bari",
    "sg:orig_category":"Macchine, Impianti Ed Attrezzature Per Abbigliamento E Pelletterie",
    "sg:phone":"+39 080 554 9762",
    "sg:postcode":"70126",
    "sg:province":"Bari",
    "wof:name":"Amoruso Nicoletta",
    "wof:placetype":"venue"
},
  "geometry": {"coordinates":[16.894169,41.109219],"type":"Point"}
}