{
  "type": "Feature",
  "properties": {
    "iso:country":"IT",
    "sg:address":"20010 Arluno",
    "sg:city":"Arluno",
    "sg:orig_category":"Professionisti - Studi E Servizi Ed Associazioni Di Interesse Aziendale. Associazioni Ed Organismi Di Interesse Pubblico",
    "sg:phone":"+39 02 901 2444",
    "sg:postcode":"20010",
    "sg:province":"Milano",
    "wof:name":"A.v.i.s. Sez. Comunale",
    "wof:placetype":"venue"
},
  "geometry": {"coordinates":[9.1632852554,45.4472541809],"type":"Point"}
}