{
  "type": "Feature",
  "properties": {
    "addr:full":"31, Via Rea 36020 Pove Del Grappa Pove del Grappa Vicenza 36020",
    "addr:postcode":"36020;36020",
    "addr:street":"Via Rea",
    "iso:country":"IT",
    "sg:address":"31, Via Rea 36020 Pove Del Grappa",
    "sg:city":"Pove del Grappa",
    "sg:classifiers":[
        {
            "category":"Wholesale",
            "subcategory":"Drugs",
            "type":"Manufacturing & Wholesale Goods"
        }
    ],
    "sg:phone":"+39 0424 808241",
    "sg:postcode":"36020",
    "sg:province":"Vicenza",
    "sg:tags":[
        "chemical",
        "pharmaceutical"
    ],
    "wof:name":"R.i.v.a.l. (s.p.a.)",
    "wof:placetype":"venue"
},
  "geometry": {"coordinates":[11.718286,45.797565],"type":"Point"}
}