{
  "type": "Feature",
  "properties": {
    "iso:country":"IT",
    "sg:address":"36075 Montecchio Maggiore",
    "sg:city":"Alte ceccato",
    "sg:orig_category":"Alberghi E Strutture Extra Alberghiere. Servizi Per Aziende, Manifestazioni E Supporto Agli Scambi Commerciali",
    "sg:phone":"+39 0444 697366",
    "sg:postcode":"36075",
    "sg:province":"Vicenza",
    "sg:website":"http://www.hotelcastelli.it",
    "wof:name":"Hotel Castelli Srl",
    "wof:placetype":"venue"
},
  "geometry": {"coordinates":[11.43957,45.50386],"type":"Point"}
}