{
  "type": "Feature",
  "properties": {
    "addr:full":"21, Via Palmiro Togliatti 20024 Garbagnate Milanese Garbagnate Milanese Milano 20024",
    "addr:postcode":"20024;20024",
    "addr:street":"Via Palmiro Togliatti",
    "iso:country":"IT",
    "sg:address":"21, Via Palmiro Togliatti 20024 Garbagnate Milanese",
    "sg:city":"Garbagnate Milanese",
    "sg:classifiers":[
        {
            "category":"Utilities",
            "subcategory":"Electric",
            "type":"Services"
        }
    ],
    "sg:phone":"+39 02 9901 0593",
    "sg:postcode":"20024",
    "sg:province":"Milano",
    "sg:tags":[
        "component",
        "electronic"
    ],
    "wof:name":"Resistor (s.r.l.)",
    "wof:placetype":"venue"
},
  "geometry": {"coordinates":[9.072466,45.532814],"type":"Point"}
}