{
  "type": "Feature",
  "properties": {
    "addr:full":"25033 Cologne Cologne Brescia 25033",
    "addr:postcode":"25033;25033",
    "iso:country":"IT",
    "sg:address":"25033 Cologne",
    "sg:city":"Cologne",
    "sg:orig_category":"Forniture Per Edilizia E Lavori Pubblici. Forniture Per Attivita' Industriali",
    "sg:phone":"+39 030 705 0264",
    "sg:postcode":"25033",
    "sg:province":"Brescia",
    "wof:name":"Marcandelli Piergiuseppe",
    "wof:placetype":"venue"
},
  "geometry": {"coordinates":[10.220366478,45.5462532043],"type":"Point"}
}