{
  "type": "Feature",
  "properties": {
    "iso:country":"IT",
    "sg:address":"36028 Rossano Veneto",
    "sg:city":"Rossano Veneto",
    "sg:orig_category":"Sport - Articoli E Forniture",
    "sg:phone":"+39 0424 84959",
    "sg:postcode":"36028",
    "sg:province":"Vicenza",
    "wof:name":"Dolphin Sas",
    "wof:placetype":"venue"
},
  "geometry": {"coordinates":[11.79562,45.713661],"type":"Point"}
}