{
  "type": "Feature",
  "properties": {
    "addr:full":"16121 Genova Genova Genova 16121",
    "addr:postcode":"16121;16121",
    "iso:country":"IT",
    "sg:address":"16121 Genova",
    "sg:city":"Genova",
    "sg:orig_category":"Servizi E Lavori Per Abbigliamento E Pelletterie",
    "sg:phone":"+39 010 588848",
    "sg:postcode":"16121",
    "sg:province":"Genova",
    "wof:name":"Urbani Paolo Antonio",
    "wof:placetype":"venue"
},
  "geometry": {"coordinates":[8.942877,44.404736],"type":"Point"}
}