{
  "type": "Feature",
  "properties": {
    "iso:country":"IT",
    "sg:address":"09134 Cagliari",
    "sg:city":"Cagliari",
    "sg:orig_category":"Servizi Per Lo Sport E Il Tempo Libero. Servizi Al Turismo",
    "sg:phone":"+39 070 540700",
    "sg:postcode":"09134",
    "sg:province":"Cagliari",
    "wof:name":"Associazione Sportiva Muscle Power",
    "wof:placetype":"venue"
},
  "geometry": {"coordinates":[9.109178,39.251057],"type":"Point"}
}