{
  "type": "Feature",
  "properties": {
    "iso:country":"IT",
    "sg:address":"00196 Roma",
    "sg:city":"Roma",
    "sg:orig_category":"Ospedali E Servizi Sanitari",
    "sg:phone":"+39 06 361 4253",
    "sg:postcode":"00196",
    "sg:province":"Roma",
    "wof:name":"Silver Time Srl",
    "wof:placetype":"venue"
},
  "geometry": {"coordinates":[12.471398,41.922535],"type":"Point"}
}