{
  "type": "Feature",
  "properties": {
    "addr:full":"53, Via Strozzi Filippo Loc. Oste 59013 Montemurlo Montemurlo Prato 59013",
    "addr:postcode":"59013;59013",
    "addr:street":"Via Strozzi Filippo Loc. Oste",
    "iso:country":"IT",
    "sg:address":"53, Via Strozzi Filippo Loc. Oste 59013 Montemurlo",
    "sg:city":"Montemurlo",
    "sg:classifiers":[
        {
            "category":"Shopping",
            "subcategory":"Crafts & Fabrics",
            "type":"Retail Goods"
        }
    ],
    "sg:phone":"+39 0574 680781",
    "sg:postcode":"59013",
    "sg:province":"Prato",
    "wof:name":"Breda Filati S.r.l",
    "wof:placetype":"venue"
},
  "geometry": {"coordinates":[11.0963125229,43.879699707],"type":"Point"}
}