{
  "type": "Feature",
  "properties": {
    "addr:full":"10, Via Monte Albenza 20052 Monza Monza Milano 20052",
    "addr:postcode":"20052;20052",
    "addr:street":"Via Monte Albenza",
    "iso:country":"IT",
    "sg:address":"10, Via Monte Albenza 20052 Monza",
    "sg:city":"Monza",
    "sg:classifiers":[
        {
            "category":"Shopping",
            "type":"Retail Goods"
        }
    ],
    "sg:phone":"+39 39039740429",
    "sg:postcode":"20052",
    "sg:province":"Milano",
    "sg:tags":[
        "finished",
        "-",
        "metallic"
    ],
    "wof:name":"Industria Commercio Lamiere Affini (s.p.a.)",
    "wof:placetype":"venue"
},
  "geometry": {"coordinates":[9.2486104965,45.5811767578],"type":"Point"}
}