{
  "type": "Feature",
  "properties": {
    "iso:country":"IT",
    "sg:address":"80143 Napoli",
    "sg:city":"Napoli",
    "sg:orig_category":"Artigianato Tipico",
    "sg:phone":"+39 081 250 8392",
    "sg:postcode":"80143",
    "sg:province":"Napoli",
    "wof:name":"Creazioni Artigianali Di Rega Rosa",
    "wof:placetype":"venue"
},
  "geometry": {"coordinates":[14.295682,40.867855],"type":"Point"}
}