{
  "type": "Feature",
  "properties": {
    "iso:country":"IT",
    "sg:address":"24052 Azzano San Paolo",
    "sg:city":"Azzano San Paolo",
    "sg:orig_category":"Macchine Utensili E Impianti",
    "sg:phone":"+39 035 530212",
    "sg:postcode":"24052",
    "sg:province":"Bergamo",
    "wof:name":"Marossi Macchine Utensili (s.r.l.)",
    "wof:placetype":"venue"
},
  "geometry": {"coordinates":[9.669468,45.663136],"type":"Point"}
}