{
  "type": "Feature",
  "properties": {
    "addr:full":"Via Fermi Enrico 8 37136 Verona Verona Verona 37136",
    "addr:housenumber":"8",
    "addr:postcode":"37136;37136",
    "addr:street":"Via Fermi Enrico",
    "iso:country":"IT",
    "sg:address":"Via Fermi Enrico 8 37136 Verona",
    "sg:city":"Verona",
    "sg:classifiers":[
        {
            "category":"Autos & Motor Vehicles",
            "subcategory":"Auto Supplies",
            "type":"Retail Goods"
        }
    ],
    "sg:phone":"+39 045 828 1311",
    "sg:postcode":"37136",
    "sg:province":"Verona",
    "sg:tags":[
        "automobile",
        "part",
        "spare"
    ],
    "sg:website":"www.federalmogul.com",
    "wof:name":"Federal Mogul Operation Italy Srl",
    "wof:placetype":"venue"
},
  "geometry": {"coordinates":[10.967583,45.403214],"type":"Point"}
}