{
  "type": "Feature",
  "properties": {
    "iso:country":"IT",
    "sg:address":"33082 Azzano Decimo",
    "sg:city":"Azzano Decimo",
    "sg:orig_category":"Elettrotecnica Industriale, Prodotti E Apparecchiature",
    "sg:phone":"+39 0434 640077",
    "sg:postcode":"33082",
    "sg:province":"Pordenone",
    "wof:name":"Maschietto Luigino Di L. Maschietto & C. Snc",
    "wof:placetype":"venue"
},
  "geometry": {"coordinates":[12.661629,45.943668],"type":"Point"}
}