{
  "type": "Feature",
  "properties": {
    "iso:country":"IT",
    "sg:address":"44100 Ferrara",
    "sg:city":"Ferrara",
    "sg:orig_category":"Carte Geografiche, Topografiche E Nautiche",
    "sg:phone":"+39 0532 55129",
    "sg:postcode":"44100",
    "sg:province":"Ferrara",
    "wof:name":"Tecno Graph Service Sas Di Cavallari Mirco",
    "wof:placetype":"venue"
},
  "geometry": {"coordinates":[11.608005,44.854462],"type":"Point"}
}