{
  "type": "Feature",
  "properties": {
    "iso:country":"IT",
    "sg:address":"26900 Lodi",
    "sg:city":"Lodi",
    "sg:orig_category":"Macchine, Impianti Ed Attrezzature Per Industria Alimentare E Bevande",
    "sg:phone":"+39 0371 31469",
    "sg:postcode":"26900",
    "sg:province":"Lodi",
    "wof:name":"Tecnolatte Sas Di Parpani Gianluigi & C.",
    "wof:placetype":"venue"
},
  "geometry": {"coordinates":[9.510137,45.301468],"type":"Point"}
}