{
  "type": "Feature",
  "properties": {
    "iso:country":"IT",
    "sg:address":"35020 Arzergrande",
    "sg:city":"Arzergrande",
    "sg:orig_category":"Insonorizzazione Industriale",
    "sg:phone":"+39 049 580 0704",
    "sg:postcode":"35020",
    "sg:province":"Padova",
    "sg:website":"http://www.rocar.com",
    "wof:name":"Ro.car Srl",
    "wof:placetype":"venue"
},
  "geometry": {"coordinates":[11.91729,45.411797],"type":"Point"}
}