{
  "type": "Feature",
  "properties": {
    "iso:country":"IT",
    "sg:address":"00173 Roma",
    "sg:city":"Roma",
    "sg:classifiers":[
        {
            "category":"Home & Garden",
            "subcategory":"Building Materials",
            "type":"Retail Goods"
        }
    ],
    "sg:phone":"+39 06 721 0943",
    "sg:postcode":"00173",
    "sg:province":"Roma",
    "sg:tags":[
        "gas",
        "caldaie"
    ],
    "wof:name":"Bruschi Francesco",
    "wof:placetype":"venue"
},
  "geometry": {"coordinates":[12.59292,41.842037],"type":"Point"}
}