{
  "type": "Feature",
  "properties": {
    "iso:country":"IT",
    "sg:address":"28065 Cerano",
    "sg:city":"Cerano",
    "sg:orig_category":"Tempo Libero - Articoli E Forniture. Forniture Per Congressi, Fiere E Manifestazioni. Regalistica Aziendale",
    "sg:phone":"+39 0321 726564",
    "sg:postcode":"28065",
    "sg:province":"Novara",
    "wof:name":"Confezioni Alba",
    "wof:placetype":"venue"
},
  "geometry": {"coordinates":[8.778496,45.407066],"type":"Point"}
}