{
  "type": "Feature",
  "properties": {
    "iso:country":"IT",
    "sg:address":"20124 Milano",
    "sg:city":"Milano",
    "sg:orig_category":"Banche E Servizi Finanziari",
    "sg:phone":"+39 02 676 2351",
    "sg:postcode":"20124",
    "sg:province":"Milano",
    "wof:name":"Sella Asset Management S.g.r.p.a.",
    "wof:placetype":"venue"
},
  "geometry": {"coordinates":[9.199878,45.484055],"type":"Point"}
}