{
  "type": "Feature",
  "properties": {
    "addr:full":"25, Via Traversa Valdichiana Est 53049 Torrita Di Siena Torrita di Siena Siena 53049",
    "addr:postcode":"53049;53049",
    "addr:street":"Via Traversa Valdichiana Est",
    "iso:country":"IT",
    "sg:address":"25, Via Traversa Valdichiana Est 53049 Torrita Di Siena",
    "sg:city":"Torrita di Siena",
    "sg:classifiers":[
        {
            "category":"Home & Garden",
            "subcategory":"Home Furnishings",
            "type":"Retail Goods"
        }
    ],
    "sg:phone":"+39 0577 685186",
    "sg:postcode":"53049",
    "sg:province":"Siena",
    "sg:tags":[
        "household"
    ],
    "wof:name":"Mobilificio V.r.i.n.e.l.",
    "wof:placetype":"venue"
},
  "geometry": {"coordinates":[11.78808,43.177391],"type":"Point"}
}