{
  "type": "Feature",
  "properties": {
    "addr:full":"25039 Travagliato Travagliato Brescia 25039",
    "addr:postcode":"25039;25039",
    "iso:country":"IT",
    "sg:address":"25039 Travagliato",
    "sg:city":"Travagliato",
    "sg:orig_category":"Impianti, Attrezzature E Forniture Sanitarie Ed Ospedaliere",
    "sg:phone":"+39 030 686 9311",
    "sg:postcode":"25039",
    "sg:province":"Brescia",
    "sg:website":"http://www.padanaeverest.it",
    "wof:name":"Padana Everest Spa",
    "wof:placetype":"venue"
},
  "geometry": {"coordinates":[10.186989,45.541252],"type":"Point"}
}