{
  "type": "Feature",
  "properties": {
    "iso:country":"IT",
    "sg:address":"2, Via Della Quadra 23032 Bormio",
    "sg:city":"Bormio",
    "sg:classifiers":[
        {
            "category":"Real Estate",
            "subcategory":"Architect",
            "type":"Services"
        }
    ],
    "sg:phone":"+39 0342 903444",
    "sg:postcode":"23032",
    "sg:province":"Sondrio",
    "sg:tags":[
        "textile",
        "clothing"
    ],
    "wof:name":"H.g.h. Srl",
    "wof:placetype":"venue"
},
  "geometry": {"coordinates":[10.367275,46.460709],"type":"Point"}
}