{
  "type": "Feature",
  "properties": {
    "iso:country":"IT",
    "sg:address":"Via Vicenza 113 36015 Schio",
    "sg:city":"Schio",
    "sg:classifiers":[
        {
            "category":"Utilities",
            "subcategory":"Natural Gas",
            "type":"Services"
        }
    ],
    "sg:phone":"+39 0445 597111",
    "sg:postcode":"36015",
    "sg:province":"Vicenza",
    "sg:tags":[
        "industry",
        "petrochemical",
        "heat",
        "exchanger"
    ],
    "sg:website":"www.zanon.com",
    "wof:name":"Ettore Zanon Spa",
    "wof:placetype":"venue"
},
  "geometry": {"coordinates":[11.370108,45.706112],"type":"Point"}
}