{
  "type": "Feature",
  "properties": {
    "addr:full":"22, Via N. Sauro 20040 Cornate D'adda Milano 20040",
    "addr:postcode":"20040;20040",
    "addr:street":"Via N. Sauro",
    "iso:country":"IT",
    "sg:address":"22, Via N. Sauro 20040 Cornate D'adda",
    "sg:classifiers":[
        {
            "category":"Professional",
            "subcategory":"Engineering",
            "type":"Services"
        }
    ],
    "sg:phone":"+39 39039692156",
    "sg:postcode":"20040",
    "sg:province":"Milano",
    "sg:tags":[
        "machine",
        "-",
        "mechanical"
    ],
    "wof:name":"Meccanica Scotti (s.r.l.)",
    "wof:placetype":"venue"
},
  "geometry": {"coordinates":[9.188141,45.463688],"type":"Point"}
}