{
  "type": "Feature",
  "properties": {
    "iso:country":"IT",
    "sg:address":"Via Campo Di Maggio 46 21020 Brunello",
    "sg:city":"Brunello",
    "sg:classifiers":[
        {
            "category":"Shopping",
            "subcategory":"Hobbies, Toys, & Games",
            "type":"Retail Goods"
        }
    ],
    "sg:phone":"+39 0332 463418",
    "sg:postcode":"21020",
    "sg:province":"Varese",
    "sg:tags":[
        "sand",
        "toy",
        "garden"
    ],
    "sg:website":"www.frabar.com",
    "wof:name":"Frabar Di Bardelli Francesco & C. Sas",
    "wof:placetype":"venue"
},
  "geometry": {"coordinates":[8.802224,45.767933],"type":"Point"}
}