{
  "type": "Feature",
  "properties": {
    "iso:country":"IT",
    "sg:address":"43, Via Val D'assa 36010 Carre'",
    "sg:classifiers":[
        {
            "category":"Shopping",
            "subcategory":"Clothing, Apparel, & Fashions",
            "type":"Retail Goods"
        }
    ],
    "sg:phone":"+39 0445 314147",
    "sg:postcode":"36010",
    "sg:province":"Vicenza",
    "sg:tags":[
        "clothes"
    ],
    "wof:name":"Sportswear International (s.p.a.)",
    "wof:placetype":"venue"
},
  "geometry": {"coordinates":[11.439109,45.739441],"type":"Point"}
}