{
  "type": "Feature",
  "properties": {
    "addr:full":"63023 Fermo Fermo Ascoli Piceno 63023",
    "addr:postcode":"63023;63023",
    "addr:street":"Piceno",
    "iso:country":"IT",
    "sg:address":"63023 Fermo",
    "sg:city":"Fermo",
    "sg:orig_category":"Prodotti Vari In Metallo",
    "sg:phone":"+39 0734 227959",
    "sg:postcode":"63023",
    "sg:province":"Ascoli Piceno",
    "wof:name":"Seles S.r.l.",
    "wof:placetype":"venue"
},
  "geometry": {"coordinates":[13.5749769211,42.8554000854],"type":"Point"}
}