{
  "type": "Feature",
  "properties": {
    "iso:country":"IT",
    "sg:address":"24030 Valtrighe",
    "sg:orig_category":"Forniture Per Abbigliamento E Pelletterie",
    "sg:phone":"+39 035 909151",
    "sg:postcode":"24030",
    "sg:province":"Bergamo",
    "wof:name":"Cavagna Alberto",
    "wof:placetype":"venue"
},
  "geometry": {"coordinates":[9.5752744675,45.7168312073],"type":"Point"}
}