{
  "type": "Feature",
  "properties": {
    "iso:country":"IT",
    "sg:address":"Via Roma 07026 Olbia",
    "sg:city":"Olbia",
    "sg:classifiers":[
        {
            "category":"Communications",
            "subcategory":"Television Station",
            "type":"Services"
        }
    ],
    "sg:phone":"+39 39078924100",
    "sg:postcode":"07026",
    "sg:province":"Olbia-Tempio",
    "sg:tags":[
        "audio-visual"
    ],
    "wof:name":"Manconi",
    "wof:placetype":"venue"
},
  "geometry": {"coordinates":[9.278559,40.826839],"type":"Point"}
}