{
  "type": "Feature",
  "properties": {
    "iso:country":"IT",
    "sg:address":"80127 Napoli",
    "sg:city":"Napoli",
    "sg:orig_category":"Agricoltura, Orticoltura E Floricoltura",
    "sg:phone":"+39 081 579 8432",
    "sg:postcode":"80127",
    "sg:province":"Napoli",
    "wof:name":"Monopoli Di Stato",
    "wof:placetype":"venue"
},
  "geometry": {"coordinates":[14.194573,40.907742],"type":"Point"}
}