{
  "type": "Feature",
  "properties": {
    "iso:country":"IT",
    "sg:address":"18012 Bordighera",
    "sg:city":"Bordighera",
    "sg:orig_category":"Agenzie Immobiliari",
    "sg:phone":"+39 0184 260269",
    "sg:postcode":"18012",
    "sg:province":"Imperia",
    "wof:name":"Mediterraneo",
    "wof:placetype":"venue"
},
  "geometry": {"coordinates":[7.660378,43.779938],"type":"Point"}
}