{
  "type": "Feature",
  "properties": {
    "iso:country":"IT",
    "sg:address":"84135 Salerno",
    "sg:city":"Salerno",
    "sg:orig_category":"Macchine Utensili E Impianti",
    "sg:phone":"+39 089 271878",
    "sg:postcode":"84135",
    "sg:province":"Salerno",
    "wof:name":"Deco' Dei F. Lli Langella & C. Snc",
    "wof:placetype":"venue"
},
  "geometry": {"coordinates":[14.804785,40.821457],"type":"Point"}
}