{
  "type": "Feature",
  "properties": {
    "iso:country":"IT",
    "sg:address":"69, Via Giuseppe Mazzini 35040 Vescovana",
    "sg:city":"Vescovana",
    "sg:classifiers":[
        {
            "category":"Bars & Pubs",
            "subcategory":"Nightclub",
            "type":"Food & Drink"
        }
    ],
    "sg:phone":"+39 0425 958006",
    "sg:postcode":"35040",
    "sg:province":"Padova",
    "sg:tags":[
        "cake",
        "bread"
    ],
    "wof:name":"Com. Al. Srl",
    "wof:placetype":"venue"
},
  "geometry": {"coordinates":[11.715727,45.136009],"type":"Point"}
}