{
  "type": "Feature",
  "properties": {
    "iso:country":"IT",
    "sg:address":"10, Via Leonardo Da Vinci 20016 Pero",
    "sg:city":"Pero",
    "sg:classifiers":[
        {
            "category":"Bars & Pubs",
            "subcategory":"Nightclub",
            "type":"Food & Drink"
        }
    ],
    "sg:phone":"+39 39023538826",
    "sg:postcode":"20016",
    "sg:province":"Milano",
    "sg:tags":[
        "cake",
        "bread"
    ],
    "wof:name":"Rachelli Italia S.r.l.",
    "wof:placetype":"venue"
},
  "geometry": {"coordinates":[9.087481,45.499847],"type":"Point"}
}