{
  "type": "Feature",
  "properties": {
    "addr:full":"33040 Chiopris Viscone Visco Udine 33040",
    "addr:postcode":"33040;33040",
    "iso:country":"IT",
    "sg:address":"33040 Chiopris Viscone",
    "sg:city":"Visco",
    "sg:orig_category":"Climatizzazione E Condizionamento, Apparecchiature E Servizi",
    "sg:phone":"+39 0432 991294",
    "sg:postcode":"33040",
    "sg:province":"Udine",
    "sg:website":"http://www.lammec.com",
    "wof:name":"La.m.mec. Snc Di Berin Maurizio & C.",
    "wof:placetype":"venue"
},
  "geometry": {"coordinates":[13.166289,46.140797],"type":"Point"}
}