{
  "type": "Feature",
  "properties": {
    "iso:country":"IT",
    "sg:address":"52043 Castiglion Fiorentino",
    "sg:city":"Castiglion Fiorentino",
    "sg:orig_category":"Minuterie Metalliche E Ferramenta",
    "sg:phone":"+39 0575 657080",
    "sg:postcode":"52043",
    "sg:province":"Arezzo",
    "wof:name":"Centroferr Spa",
    "wof:placetype":"venue"
},
  "geometry": {"coordinates":[11.9055328369,43.3520126343],"type":"Point"}
}