{
  "type": "Feature",
  "properties": {
    "addr:full":"33085 Maniago Maniago Pordenone 33085",
    "addr:postcode":"33085;33085",
    "iso:country":"IT",
    "sg:address":"33085 Maniago",
    "sg:city":"Maniago",
    "sg:orig_category":"Servizi E Lavori Per Arredamento E Industria Del Legno",
    "sg:phone":"+39 0427 701202",
    "sg:postcode":"33085",
    "sg:province":"Pordenone",
    "wof:name":"L'impronta Grafica Di Antonio Massarutto",
    "wof:placetype":"venue"
},
  "geometry": {"coordinates":[12.596722,45.893703],"type":"Point"}
}