{
  "type": "Feature",
  "properties": {
    "addr:full":"21055 Prospiano Varese 21055",
    "addr:postcode":"21055;21055",
    "iso:country":"IT",
    "sg:address":"21055 Prospiano",
    "sg:orig_category":"Forniture Per Abbigliamento E Pelletterie",
    "sg:phone":"+39 0331 600043",
    "sg:postcode":"21055",
    "sg:province":"Varese",
    "wof:name":"Porotti Ada",
    "wof:placetype":"venue"
},
  "geometry": {"coordinates":[8.8136863708,45.8196105957],"type":"Point"}
}