{
  "type": "Feature",
  "properties": {
    "iso:country":"IT",
    "sg:address":"80144 Napoli",
    "sg:city":"Napoli",
    "sg:orig_category":"Dolciumi E Gelati",
    "sg:phone":"+39 081 736 7321",
    "sg:postcode":"80144",
    "sg:province":"Napoli",
    "wof:name":"D'auria Industria Dolciaria",
    "wof:placetype":"venue"
},
  "geometry": {"coordinates":[14.290082,40.893574],"type":"Point"}
}