{
  "type": "Feature",
  "properties": {
    "iso:country":"IT",
    "sg:address":"24050 Bariano",
    "sg:city":"Bariano",
    "sg:orig_category":"Valvole E Apparecchiature Di Misura",
    "sg:phone":"+39 036 395 8244",
    "sg:postcode":"24050",
    "sg:province":"Bergamo",
    "wof:name":"Materind Srl",
    "wof:placetype":"venue"
},
  "geometry": {"coordinates":[9.699903,45.51186],"type":"Point"}
}