{
  "type": "Feature",
  "properties": {
    "iso:country":"IT",
    "sg:address":"29100 Piacenza",
    "sg:city":"Piacenza",
    "sg:orig_category":"Tappezzerie E Sellerie Veicoli - Lavorazione E Riparazione",
    "sg:phone":"+39 0523 615482",
    "sg:postcode":"29100",
    "sg:province":"Piacenza",
    "wof:name":"Fodercar Di Peveri Danilo",
    "wof:placetype":"venue"
},
  "geometry": {"coordinates":[9.720122,45.039406],"type":"Point"}
}