{
  "type": "Feature",
  "properties": {
    "iso:country":"IT",
    "sg:address":"Strada Tuscanese Km 3,300 75/c 01100 Viterbo",
    "sg:city":"Viterbo",
    "sg:classifiers":[
        {
            "category":"Communications",
            "subcategory":"Film & Video Production",
            "type":"Services"
        }
    ],
    "sg:phone":"+39 0761 352422",
    "sg:postcode":"01100",
    "sg:province":"Viterbo",
    "sg:tags":[
        "cloth",
        "tent"
    ],
    "sg:website":"www.lanzistyl.it",
    "wof:name":"Lanzi Styl Snc",
    "wof:placetype":"venue"
},
  "geometry": {"coordinates":[12.064167,42.430279],"type":"Point"}
}