{
  "type": "Feature",
  "properties": {
    "addr:full":"00135 Roma Roma Roma 00135",
    "addr:postcode":"00135;00135",
    "iso:country":"IT",
    "sg:address":"00135 Roma",
    "sg:city":"Roma",
    "sg:orig_category":"Prodotti E Manufatti In Gomma",
    "sg:phone":"+39 06 305 1558",
    "sg:postcode":"00135",
    "sg:province":"Roma",
    "wof:name":"Mosele Paolo",
    "wof:placetype":"venue"
},
  "geometry": {"coordinates":[12.4383907318,41.9351081848],"type":"Point"}
}