{
  "type": "Feature",
  "properties": {
    "iso:country":"IT",
    "sg:address":"20131 Milano",
    "sg:city":"Milano",
    "sg:orig_category":"Calzature, Pelletterie E Pelli. Servizi E Lavori Per Abbigliamento E Pelletterie",
    "sg:phone":"+39 02 261 3063",
    "sg:postcode":"20131",
    "sg:province":"Milano",
    "wof:name":"Tricella Felice",
    "wof:placetype":"venue"
},
  "geometry": {"coordinates":[9.219304,45.486839],"type":"Point"}
}