{
  "type": "Feature",
  "properties": {
    "addr:full":"Piazza Mazzini 15; Aulla; 54011 Aulla Massa-Carrara 54011",
    "addr:housenumber":"15",
    "addr:postcode":"54011;54011",
    "addr:street":"Piazza Mazzini",
    "iso:country":"IT",
    "sg:address":"Piazza Mazzini 15; Aulla; 54011",
    "sg:city":"Aulla",
    "sg:classifiers":[
        {
            "category":"Banks & Credit Unions",
            "subcategory":"Bank",
            "type":"Services"
        }
    ],
    "sg:phone":"+39 0187 408215",
    "sg:postcode":"54011",
    "sg:province":"Massa-Carrara",
    "wof:name":"Banca Toscana Spa",
    "wof:placetype":"venue"
},
  "geometry": {"coordinates":[9.968831,44.20892],"type":"Point"}
}