{
  "type": "Feature",
  "properties": {
    "iso:country":"IT",
    "sg:address":"06124 Perugia",
    "sg:city":"Perugia",
    "sg:classifiers":[
        {
            "category":"Health Services",
            "subcategory":"Nursing And Care Facility",
            "type":"Services"
        }
    ],
    "sg:phone":"+39 075 572 2531",
    "sg:postcode":"06124",
    "sg:province":"Perugia",
    "sg:tags":[
        "case",
        "cura",
        "private",
        "di"
    ],
    "wof:name":"Casa Di Cura Villa Fiorita Srl",
    "wof:placetype":"venue"
},
  "geometry": {"coordinates":[12.379323,43.107155],"type":"Point"}
}