{
  "type": "Feature",
  "properties": {
    "iso:country":"IT",
    "sg:address":"52100 Arezzo",
    "sg:city":"Arezzo",
    "sg:orig_category":"Studi E Consulenze Tecniche E Industriali. Consulenze Tecniche, Amministrative E Perizie. Servizi Ausiliari Di Analisi, Controllo E Ricerca",
    "sg:phone":"+39 0575 302719",
    "sg:postcode":"52100",
    "sg:province":"Arezzo",
    "sg:website":"http://www.paginegialle.it/fgfengineering",
    "wof:name":"Fgf Engineering Srl",
    "wof:placetype":"venue"
},
  "geometry": {"coordinates":[11.872122,43.467297],"type":"Point"}
}