{
  "type": "Feature",
  "properties": {
    "iso:country":"IT",
    "sg:address":"12, Via Rossa Guido 20037 Paderno Dugnano",
    "sg:city":"Paderno Dugnano",
    "sg:classifiers":[
        {
            "category":"Manufacturing",
            "subcategory":"Printing",
            "type":"Manufacturing & Wholesale Goods"
        }
    ],
    "sg:phone":"+39 02 9904 0373",
    "sg:postcode":"20037",
    "sg:province":"Milano",
    "sg:tags":[
        "publishing"
    ],
    "wof:name":"Casiraghi Colour Cards Srl",
    "wof:placetype":"venue"
},
  "geometry": {"coordinates":[9.1512851715,45.5680160522],"type":"Point"}
}