{
  "type": "Feature",
  "properties": {
    "addr:full":"43013 Langhirano Langhirano Parma 43013",
    "addr:postcode":"43013;43013",
    "iso:country":"IT",
    "sg:address":"43013 Langhirano",
    "sg:city":"Langhirano",
    "sg:orig_category":"Ceramiche: Prodotti E Lavorazioni",
    "sg:phone":"+39 0521 639235",
    "sg:postcode":"43013",
    "sg:province":"Parma",
    "wof:name":"Edilizia 2000 Srl",
    "wof:placetype":"venue"
},
  "geometry": {"coordinates":[10.289168,44.684017],"type":"Point"}
}