{
  "type": "Feature",
  "properties": {
    "iso:country":"IT",
    "sg:address":"529, Viale Giusti Giuseppe S. Concordio C. 55100 Lucca",
    "sg:city":"Lucca",
    "sg:classifiers":[
        {
            "category":"Autos & Motor Vehicles",
            "subcategory":"Automobile Sales",
            "type":"Retail Goods"
        }
    ],
    "sg:phone":"+39 0583 955858",
    "sg:postcode":"55100",
    "sg:province":"Lucca",
    "sg:tags":[
        "industrial"
    ],
    "wof:name":"L. Nardi (s.r.l.)",
    "wof:placetype":"venue"
},
  "geometry": {"coordinates":[10.507994,43.843014],"type":"Point"}
}