{
  "type": "Feature",
  "properties": {
    "iso:country":"IT",
    "sg:address":"15048 Valenza",
    "sg:city":"Valenza",
    "sg:orig_category":"Gioielleria, Oreficeria E Argenteria",
    "sg:phone":"+39 0131 947237",
    "sg:postcode":"15048",
    "sg:province":"Alessandria",
    "wof:name":"Lava Antonio",
    "wof:placetype":"venue"
},
  "geometry": {"coordinates":[8.642362,45.008007],"type":"Point"}
}