{
  "type": "Feature",
  "properties": {
    "addr:full":"10132 Torino Torino Torino 10132",
    "addr:postcode":"10132;10132",
    "iso:country":"IT",
    "sg:address":"10132 Torino",
    "sg:city":"Torino",
    "sg:orig_category":"Prodotti Finiti Stampati. Articoli Da Regalo. Arte Ed Artigianato Artistico. Shopping",
    "sg:phone":"+39 011 899 4531",
    "sg:postcode":"10132",
    "sg:province":"Torino",
    "wof:name":"Petrosso Davide",
    "wof:placetype":"venue"
},
  "geometry": {"coordinates":[7.4545555115,44.8989067078],"type":"Point"}
}