{
  "type": "Feature",
  "properties": {
    "addr:full":"21057 Olgiate Olona Olgiate Olona Varese 21057",
    "addr:postcode":"21057;21057",
    "iso:country":"IT",
    "sg:address":"21057 Olgiate Olona",
    "sg:city":"Olgiate Olona",
    "sg:orig_category":"Prodotti Vari In Metallo",
    "sg:phone":"+39 0331 622445",
    "sg:postcode":"21057",
    "sg:province":"Varese",
    "sg:website":"http://www.paginegialle.it/brevettidv",
    "wof:name":"Officina Meccanica Brevetti Dv Snc Di Don\u00c0 E C.",
    "wof:placetype":"venue"
},
  "geometry": {"coordinates":[8.8814134598,45.6298980713],"type":"Point"}
}