{
  "type": "Feature",
  "properties": {
    "iso:country":"IT",
    "sg:address":"Corso Federico Ii,1; L'aquila; 67100",
    "sg:classifiers":[
        {
            "category":"Banks & Credit Unions",
            "subcategory":"Bank",
            "type":"Services"
        }
    ],
    "sg:phone":"+39 0862 69641",
    "sg:postcode":"67100",
    "sg:province":"L'Aquila",
    "wof:name":"Banca D'italia",
    "wof:placetype":"venue"
},
  "geometry": {"coordinates":[13.398403,42.348175],"type":"Point"}
}