{
  "type": "Feature",
  "properties": {
    "iso:country":"IT",
    "sg:address":"Via Albrizzi Alle Pozzette 10 31030 Dosson",
    "sg:city":"Dosson",
    "sg:classifiers":[
        {
            "category":"Professional",
            "subcategory":"Business Services",
            "type":"Services"
        }
    ],
    "sg:phone":"+39 0422 497411",
    "sg:postcode":"31030",
    "sg:province":"Treviso",
    "sg:tags":[
        "import",
        "industrial"
    ],
    "sg:website":"www.serconsult.com",
    "wof:name":"Serconsult China S.r.l.",
    "wof:placetype":"venue"
},
  "geometry": {"coordinates":[12.246207,45.626431],"type":"Point"}
}