{
  "type": "Feature",
  "properties": {
    "addr:full":"33/bis, Via Sella Quintino 21052 Busto Arsizio Busto Arsizio Varese 21052",
    "addr:housenumber":"33 / bis",
    "addr:postcode":"21052;21052",
    "addr:street":"Via Sella Quintino",
    "iso:country":"IT",
    "sg:address":"33/bis, Via Sella Quintino 21052 Busto Arsizio",
    "sg:city":"Busto Arsizio",
    "sg:classifiers":[
        {
            "category":"Professional",
            "subcategory":"Printing & Photocopies",
            "type":"Services"
        }
    ],
    "sg:phone":"+39 0331 682407",
    "sg:postcode":"21052",
    "sg:province":"Varese",
    "wof:name":"S.i.m. Serigrafia Incisoria Meccanica (s.r.l.)",
    "wof:placetype":"venue"
},
  "geometry": {"coordinates":[8.8263845444,45.8176040649],"type":"Point"}
}