{
  "type": "Feature",
  "properties": {
    "iso:country":"IT",
    "sg:address":"Strada Provinciale 26833 Merlino",
    "sg:city":"Merlino",
    "sg:classifiers":[
        {
            "category":"Home & Garden",
            "subcategory":"Home Furnishings",
            "type":"Retail Goods"
        }
    ],
    "sg:phone":"+39 02 906 5001",
    "sg:postcode":"26833",
    "sg:province":"Lodi",
    "sg:tags":[
        "air-conditioners"
    ],
    "wof:name":"Nova- Therm Srl",
    "wof:placetype":"venue"
},
  "geometry": {"coordinates":[9.427431,45.420086],"type":"Point"}
}