{
  "type": "Feature",
  "properties": {
    "iso:country":"IT",
    "sg:address":"20, Via Padova 30037 Scorze'",
    "sg:orig_category":"Miscellaneous Products",
    "sg:phone":"+39 39041446677",
    "sg:postcode":"30037",
    "sg:province":"Venezia",
    "wof:name":"Pennelli Tigre (s.r.l.)",
    "wof:placetype":"venue"
},
  "geometry": {"coordinates":[12.1049671173,45.568145752],"type":"Point"}
}