{
  "type": "Feature",
  "properties": {
    "addr:full":"88044 Marcellinara Marcellinara Catanzaro 88044",
    "addr:postcode":"88044;88044",
    "iso:country":"IT",
    "sg:address":"88044 Marcellinara",
    "sg:city":"Marcellinara",
    "sg:orig_category":"Legno E Semilavorati. Manufatti Edili E Prefabbricati",
    "sg:postcode":"88044",
    "sg:province":"Catanzaro",
    "wof:name":"Co.me.c. Srl",
    "wof:placetype":"venue"
},
  "geometry": {"coordinates":[16.470036,38.910805],"type":"Point"}
}