{
  "type": "Feature",
  "properties": {
    "iso:country":"IT",
    "sg:address":"95123 Catania",
    "sg:city":"Catania",
    "sg:orig_category":"Scuole E Servizi Scolastici. Servizi Per Lo Sport E Il Tempo Libero",
    "sg:phone":"+39 095 731 5630",
    "sg:postcode":"95123",
    "sg:province":"Catania",
    "wof:name":"Centro Sportivo Okinawa",
    "wof:placetype":"venue"
},
  "geometry": {"coordinates":[15.068007,37.512554],"type":"Point"}
}