{
  "type": "Feature",
  "properties": {
    "iso:country":"IT",
    "sg:address":"237, Via Provinciale Nord 42017 Novellara",
    "sg:classifiers":[
        {
            "category":"Professional",
            "subcategory":"Engineering",
            "type":"Services"
        }
    ],
    "sg:phone":"+39 0522 654258",
    "sg:postcode":"42017",
    "sg:province":"Reggio Nell'Emilia",
    "sg:tags":[
        "machine",
        "-",
        "mechanical"
    ],
    "wof:name":"Buzzi Officine Meccaniche S.r.l.",
    "wof:placetype":"venue"
},
  "geometry": {"coordinates":[10.67786,44.782547],"type":"Point"}
}