{
  "type": "Feature",
  "properties": {
    "iso:country":"IT",
    "sg:address":"75100 Matera",
    "sg:city":"La Martella",
    "sg:orig_category":"Serramenti Ed Infissi",
    "sg:phone":"+39 0835 262717",
    "sg:postcode":"75100",
    "sg:province":"Matera",
    "sg:website":"http://www.metallucana.com",
    "wof:name":"Metalmeccanica Lucana Di Toscano Rocco & C. Snc",
    "wof:placetype":"venue"
},
  "geometry": {"coordinates":[16.573351,40.673241],"type":"Point"}
}