{
  "type": "Feature",
  "properties": {
    "addr:full":"40122 Bologna Bologna Bologna 40122",
    "addr:postcode":"40122;40122",
    "iso:country":"IT",
    "sg:address":"40122 Bologna",
    "sg:city":"Bologna",
    "sg:orig_category":"Nastri Ferro E Acciaio",
    "sg:phone":"+39 051 554408",
    "sg:postcode":"40122",
    "sg:province":"Bologna",
    "wof:name":"Sacta Sas",
    "wof:placetype":"venue"
},
  "geometry": {"coordinates":[11.328903,44.497448],"type":"Point"}
}