{
  "type": "Feature",
  "properties": {
    "iso:country":"IT",
    "sg:address":"43044 Stradella",
    "sg:city":"Gaiano",
    "sg:orig_category":"Macchine, Impianti Ed Attrezzature Per Industria Alimentare E Bevande",
    "sg:phone":"+39 0521 303408",
    "sg:postcode":"43044",
    "sg:province":"Parma",
    "wof:name":"Fps Group Srl",
    "wof:placetype":"venue"
},
  "geometry": {"coordinates":[10.208331,44.748379],"type":"Point"}
}