{
  "type": "Feature",
  "properties": {
    "addr:full":"00199 Roma Roma Roma 00199",
    "addr:postcode":"00199;00199",
    "iso:country":"IT",
    "sg:address":"00199 Roma",
    "sg:city":"Roma",
    "sg:orig_category":"Servizi Editoriali. Shopping",
    "sg:phone":"+39 06 8621 1527",
    "sg:postcode":"00199",
    "sg:province":"Roma",
    "wof:name":"Natale Sonia",
    "wof:placetype":"venue"
},
  "geometry": {"coordinates":[12.514151,41.928398],"type":"Point"}
}