{
  "type": "Feature",
  "properties": {
    "addr:full":"29/l, Lgbisagno Istria 16141 Genova Genova Genova 16141",
    "addr:housenumber":"29 / l",
    "addr:postcode":"16141;16141",
    "addr:street":"Lgbisagno Istria",
    "iso:country":"IT",
    "sg:address":"29/l, Lgbisagno Istria 16141 Genova",
    "sg:city":"Genova",
    "sg:classifiers":[
        {
            "category":"Shopping",
            "type":"Retail Goods"
        }
    ],
    "sg:phone":"+39 010 835 6016",
    "sg:postcode":"16141",
    "sg:province":"Genova",
    "sg:tags":[
        "finished",
        "-",
        "metallic"
    ],
    "sg:website":"http://www.getecno.com",
    "wof:name":"Getecno Srl",
    "wof:placetype":"venue"
},
  "geometry": {"coordinates":[8.9769849777,44.438999176],"type":"Point"}
}