{
  "type": "Feature",
  "properties": {
    "iso:country":"IT",
    "sg:address":"80038 Pomigliano D'arco",
    "sg:orig_category":"Servizi E Lavori Per Edilizia E Lavori Pubblici. Servizi E Lavori Per Ecologia E Smaltimento Rifiuti. Macchine E Forniture Per Ecologia E Smaltimento Rifiuti. Acqua, Luce, Gas E Societa' Di Esercizio ",
    "sg:phone":"+39 081 803 6969",
    "sg:postcode":"80038",
    "sg:province":"Napoli",
    "wof:name":"Centro Operativo Volontari Protezione Civile",
    "wof:placetype":"venue"
},
  "geometry": {"coordinates":[14.399154,40.916176],"type":"Point"}
}