{
  "type": "Feature",
  "properties": {
    "iso:country":"IT",
    "sg:address":"62019 Recanati",
    "sg:city":"Recanati",
    "sg:orig_category":"Animali Domestici - Allevamento E Addestramento",
    "sg:phone":"+39 071 982451",
    "sg:postcode":"62019",
    "sg:province":"Macerata",
    "wof:name":"Tanoni Alessandra",
    "wof:placetype":"venue"
},
  "geometry": {"coordinates":[13.570481,43.425018],"type":"Point"}
}