{
  "type": "Feature",
  "properties": {
    "iso:country":"IT",
    "sg:address":"74100 Taranto",
    "sg:city":"Taranto",
    "sg:orig_category":"Macchine E Forniture Per Ecologia E Smaltimento Rifiuti. Ricambi E Componenti Dei Mezzi Di Trasporto",
    "sg:phone":"+39 099 471 6565",
    "sg:postcode":"74100",
    "sg:province":"Taranto",
    "wof:name":"Filtromeccanica Sud S.r.l.",
    "wof:placetype":"venue"
},
  "geometry": {"coordinates":[17.225061,40.481712],"type":"Point"}
}