{
  "type": "Feature",
  "properties": {
    "iso:country":"IT",
    "sg:address":"61100 Pesaro",
    "sg:city":"Pesaro",
    "sg:orig_category":"Riparazione Dei Mezzi Di Trasporto",
    "sg:phone":"+39 0721 25433",
    "sg:postcode":"61100",
    "sg:province":"Pesaro E Urbino",
    "wof:name":"Elettrauto Zeno Snc Di Tonelli A. & C.",
    "wof:placetype":"venue"
},
  "geometry": {"coordinates":[12.897084,43.909908],"type":"Point"}
}