{
  "type": "Feature",
  "properties": {
    "addr:full":"62032 Morrovalle Morro Macerata 62032",
    "addr:postcode":"62032;62032",
    "iso:country":"IT",
    "sg:address":"62032 Morrovalle",
    "sg:city":"Morro",
    "sg:orig_category":"Pelletterie - Produzione E Ingrosso",
    "sg:phone":"+39 0733 865496",
    "sg:postcode":"62032",
    "sg:province":"Macerata",
    "sg:website":"http://www.giudi.com",
    "wof:name":"Pelletterie Giudi Srl",
    "wof:placetype":"venue"
},
  "geometry": {"coordinates":[13.4562616348,43.3007469177],"type":"Point"}
}