{
  "type": "Feature",
  "properties": {
    "addr:full":"30027 San Don\u00e0 Di Piave Venezia 30027",
    "addr:housenumber":"30027",
    "addr:postcode":"30027",
    "iso:country":"IT",
    "sg:address":"30027 San Don\u00e0 Di Piave",
    "sg:orig_category":"Forniture Per Edilizia E Lavori Pubblici. Prodotti Vari In Metallo",
    "sg:phone":"+39 0421 53441",
    "sg:postcode":"30027",
    "sg:province":"Venezia",
    "wof:name":"Officina Meccanica Fabbrile Snc Di Picchetti F.",
    "wof:placetype":"venue"
},
  "geometry": {"coordinates":[12.5627155304,45.7261276245],"type":"Point"}
}