{
  "type": "Feature",
  "properties": {
    "iso:country":"IT",
    "sg:address":"20081 Abbiategrasso",
    "sg:city":"Abbiategrasso",
    "sg:orig_category":"Materiali Semilavorati Metallici",
    "sg:phone":"+39 02 946 6412",
    "sg:postcode":"20081",
    "sg:province":"Milano",
    "wof:name":"Italiana Lamiere (s.r.l.)",
    "wof:placetype":"venue"
},
  "geometry": {"coordinates":[8.918743,45.386814],"type":"Point"}
}