{
  "type": "Feature",
  "properties": {
    "addr:full":"Zona Industriale 33050 Pavia Di Udine Pavia di Udine Udine 33050",
    "addr:postcode":"33050;33050",
    "addr:street":"Zona Industriale",
    "iso:country":"IT",
    "sg:address":"Zona Industriale 33050 Pavia Di Udine",
    "sg:city":"Pavia di Udine",
    "sg:classifiers":[
        {
            "category":"Manufacturing",
            "subcategory":"Metals",
            "type":"Manufacturing & Wholesale Goods"
        }
    ],
    "sg:phone":"+39 0432 675186",
    "sg:postcode":"33050",
    "sg:province":"Udine",
    "sg:tags":[
        "metallurgy",
        "metalworking"
    ],
    "wof:name":"O.t.p. S.r.l.",
    "wof:placetype":"venue"
},
  "geometry": {"coordinates":[13.2307243347,46.0649414062],"type":"Point"}
}