{
  "type": "Feature",
  "properties": {
    "iso:country":"IT",
    "sg:address":"18013 Diano Marina",
    "sg:city":"Diano Marina",
    "sg:orig_category":"Traslochi",
    "sg:phone":"+39 0183 402837",
    "sg:postcode":"18013",
    "sg:province":"Imperia",
    "wof:name":"T3 Traslochi Di Morro Casimira & C. Snc",
    "wof:placetype":"venue"
},
  "geometry": {"coordinates":[8.085329,43.912445],"type":"Point"}
}