{
  "type": "Feature",
  "properties": {
    "addr:full":"13856 Vigliano Biellese Vigliano Biellese Biella 13856",
    "addr:postcode":"13856;13856",
    "iso:country":"IT",
    "sg:address":"13856 Vigliano Biellese",
    "sg:city":"Vigliano Biellese",
    "sg:orig_category":"Elettronica Professionale E Di Consumo. Musica",
    "sg:phone":"+39 015 510806",
    "sg:postcode":"13856",
    "sg:province":"Biella",
    "sg:website":"http://www.number-one.it",
    "wof:name":"Number One Srl",
    "wof:placetype":"venue"
},
  "geometry": {"coordinates":[8.098245,45.560738],"type":"Point"}
}