{
  "type": "Feature",
  "properties": {
    "addr:full":"10127 Torino Torino Torino 10127",
    "addr:postcode":"10127;10127",
    "iso:country":"IT",
    "sg:address":"10127 Torino",
    "sg:city":"Torino",
    "sg:orig_category":"Ricambi E Componenti Dei Mezzi Di Trasporto. Riparazione Dei Mezzi Di Trasporto",
    "sg:phone":"+39 011 317 8653",
    "sg:postcode":"10127",
    "sg:province":"Torino",
    "wof:name":"Auto Impero Srl",
    "wof:placetype":"venue"
},
  "geometry": {"coordinates":[7.655608,45.017593],"type":"Point"}
}