{
  "type": "Feature",
  "properties": {
    "addr:full":"80144 Napoli Napoli Napoli 80144",
    "addr:housenumber":"80144",
    "addr:postcode":"80144",
    "iso:country":"IT",
    "sg:address":"80144 Napoli",
    "sg:city":"Napoli",
    "sg:orig_category":"Salotti, Poltrone, Sedie E Tavoli",
    "sg:phone":"+39 081 751 7287",
    "sg:postcode":"80144",
    "sg:province":"Napoli",
    "sg:website":"http://www.salottideriso.com",
    "wof:name":"Salotti De Riso Srl",
    "wof:placetype":"venue"
},
  "geometry": {"coordinates":[14.276102,40.877949],"type":"Point"}
}