{
  "type": "Feature",
  "properties": {
    "addr:full":"16, Via Della Chiusa 42048 Rubiera Reggio Nell'Emilia 42048",
    "addr:postcode":"42048;42048",
    "addr:street":"Via Della Chiusa",
    "iso:country":"IT",
    "sg:address":"16, Via Della Chiusa 42048 Rubiera",
    "sg:classifiers":[
        {
            "category":"Manufacturing",
            "subcategory":"Glass & Minerals",
            "type":"Manufacturing & Wholesale Goods"
        }
    ],
    "sg:phone":"+39 0522 620943",
    "sg:postcode":"42048",
    "sg:province":"Reggio Nell'Emilia",
    "sg:tags":[
        "building",
        "material"
    ],
    "wof:name":"Domus Linea (s.p.a.)",
    "wof:placetype":"venue"
},
  "geometry": {"coordinates":[10.774261,44.639744],"type":"Point"}
}