{
  "type": "Feature",
  "properties": {
    "iso:country":"IT",
    "sg:address":"12, Via S. Giovanni Bosco 24040 Suisio",
    "sg:city":"Suisio",
    "sg:classifiers":[
        {
            "category":"Professional",
            "subcategory":"Engineering",
            "type":"Services"
        }
    ],
    "sg:phone":"+39 035 493 4411",
    "sg:postcode":"24040",
    "sg:province":"Bergamo",
    "sg:tags":[
        "machine",
        "-",
        "mechanical"
    ],
    "wof:name":"Belotti Spa",
    "wof:placetype":"venue"
},
  "geometry": {"coordinates":[9.669952,45.694904],"type":"Point"}
}