{
  "type": "Feature",
  "properties": {
    "addr:full":"30010 Cona Cona Venezia 30010",
    "addr:postcode":"30010;30010",
    "iso:country":"IT",
    "sg:address":"30010 Cona",
    "sg:city":"Cona",
    "sg:orig_category":"Forniture Per Agricoltura E Zootecnia. Animali Domestici",
    "sg:phone":"+39 0426 308158",
    "sg:postcode":"30010",
    "sg:province":"Venezia",
    "wof:name":"Dorado S.r.l.",
    "wof:placetype":"venue"
},
  "geometry": {"coordinates":[12.134510994,45.3333473206],"type":"Point"}
}