{
  "type": "Feature",
  "properties": {
    "iso:country":"IT",
    "sg:address":"20070 Cerro Al Lambro",
    "sg:city":"Cerro al Lambro",
    "sg:orig_category":"Servizi Culturali E Per Lo Spettacolo. Servizi Al Turismo. Acqua, Luce, Gas E Societa' Di Esercizio Pubblico",
    "sg:phone":"+39 02 9823 1978",
    "sg:postcode":"20070",
    "sg:province":"Milano",
    "wof:name":"Comune Di Cerro Al Lambro",
    "wof:placetype":"venue"
},
  "geometry": {"coordinates":[9.34163,45.331017],"type":"Point"}
}