{
  "type": "Feature",
  "properties": {
    "iso:country":"IT",
    "sg:address":"66/d/e, V. Martiri Della Libert\u00e0 42019 Scandiano",
    "sg:classifiers":[
        {
            "category":"Manufacturing",
            "subcategory":"Metals",
            "type":"Manufacturing & Wholesale Goods"
        }
    ],
    "sg:phone":"+39 0522 852291",
    "sg:postcode":"42019",
    "sg:province":"Reggio Nell'Emilia",
    "sg:tags":[
        "metallurgy",
        "metalworking"
    ],
    "wof:name":"Euro Impianti Srl",
    "wof:placetype":"venue"
},
  "geometry": {"coordinates":[10.6952886581,44.6033287048],"type":"Point"}
}