{
  "type": "Feature",
  "properties": {
    "iso:country":"IT",
    "sg:address":"53, Via Cal Lusent 31040 Pederobba",
    "sg:city":"Pederobba",
    "sg:classifiers":[
        {
            "category":"Manufacturing",
            "subcategory":"Tools & Machinery",
            "type":"Manufacturing & Wholesale Goods"
        }
    ],
    "sg:phone":"+39 0423 688553",
    "sg:postcode":"31040",
    "sg:province":"Treviso",
    "sg:tags":[
        "environment",
        "equipment",
        "-"
    ],
    "wof:name":"Ventilservice (s.r.l.)",
    "wof:placetype":"venue"
},
  "geometry": {"coordinates":[11.96941,45.866825],"type":"Point"}
}