{
  "type": "Feature",
  "properties": {
    "addr:full":"43100 Parma Parma Parma 43100",
    "addr:postcode":"43100;43100",
    "iso:country":"IT",
    "sg:address":"43100 Parma",
    "sg:city":"Parma",
    "sg:orig_category":"Prodotti Chimici Di Base",
    "sg:phone":"+39 0521 772460",
    "sg:postcode":"43100",
    "sg:province":"Parma",
    "wof:name":"Purissima (s.n.c.)",
    "wof:placetype":"venue"
},
  "geometry": {"coordinates":[10.3305807114,44.808380127],"type":"Point"}
}