{
  "type": "Feature",
  "properties": {
    "iso:country":"IT",
    "sg:address":"Piazza Castello, 8; Belluno; 32100",
    "sg:city":"Belluno",
    "sg:classifiers":[
        {
            "category":"Banks & Credit Unions",
            "subcategory":"Bank",
            "type":"Services"
        }
    ],
    "sg:phone":"+39 0437 940025",
    "sg:postcode":"32100",
    "sg:province":"Belluno",
    "wof:name":"Banca Popolare Di Novara",
    "wof:placetype":"venue"
},
  "geometry": {"coordinates":[12.215846,46.138355],"type":"Point"}
}