{
  "type": "Feature",
  "properties": {
    "iso:country":"IT",
    "sg:address":"20045 Besana In Brianza",
    "sg:city":"Besana in Brianza",
    "sg:orig_category":"Serramenti Ed Infissi",
    "sg:phone":"+39 036 299 6060",
    "sg:postcode":"20045",
    "sg:province":"Milano",
    "sg:website":"http://www.paginegialle.it/scaccabaro",
    "wof:name":"Fratelli Scaccabarozzi Snc Di Laura, Roberto, Luca E Stefano",
    "wof:placetype":"venue"
},
  "geometry": {"coordinates":[9.278868,45.70303],"type":"Point"}
}