{
  "type": "Feature",
  "properties": {
    "addr:full":"20081 Abbiategrasso Abbiategrasso Milano 20081",
    "addr:postcode":"20081;20081",
    "iso:country":"IT",
    "sg:address":"20081 Abbiategrasso",
    "sg:city":"Abbiategrasso",
    "sg:orig_category":"Banche E Servizi Finanziari",
    "sg:phone":"+39 02 948 5551",
    "sg:postcode":"20081",
    "sg:province":"Milano",
    "wof:name":"Banca Fideuram Spa",
    "wof:placetype":"venue"
},
  "geometry": {"coordinates":[9.174146,45.453987],"type":"Point"}
}