{
  "type": "Feature",
  "properties": {
    "iso:country":"IT",
    "sg:address":"1, Via Pietra Alta 10040 Caselette",
    "sg:city":"Caselette",
    "sg:classifiers":[
        {
            "category":"Shopping",
            "subcategory":"Computers & Home Electronics",
            "type":"Retail Goods"
        }
    ],
    "sg:phone":"+39 011 968 8170",
    "sg:postcode":"10040",
    "sg:province":"Torino",
    "sg:tags":[
        "electronic",
        "electrical",
        "equipment"
    ],
    "wof:name":"C.a.s.i.t. Comandi Automatici Sheds Infissi Teleco",
    "wof:placetype":"venue"
},
  "geometry": {"coordinates":[7.391369,45.079884],"type":"Point"}
}