{
  "type": "Feature",
  "properties": {
    "iso:country":"IT",
    "sg:address":"40055 Castenaso",
    "sg:city":"Castenaso",
    "sg:orig_category":"Informatica - Consulenza E Software",
    "sg:phone":"+39 051 781510",
    "sg:postcode":"40055",
    "sg:province":"Bologna",
    "wof:name":"A.t.e. Srl",
    "wof:placetype":"venue"
},
  "geometry": {"coordinates":[11.436601,44.50428],"type":"Point"}
}