{
  "type": "Feature",
  "properties": {
    "addr:full":"3, Viale Maria 00054 Fiumicino Fiumicino Roma 00054",
    "addr:postcode":"00054;roma 00054",
    "addr:street":"Viale Maria",
    "iso:country":"IT",
    "sg:address":"3, Viale Maria 00054 Fiumicino",
    "sg:city":"Fiumicino",
    "sg:classifiers":[
        {
            "category":"Food & Beverages",
            "subcategory":"Dairy",
            "type":"Retail Goods"
        }
    ],
    "sg:phone":"+39 39066679341",
    "sg:postcode":"00054",
    "sg:province":"Roma",
    "sg:tags":[
        "product"
    ],
    "wof:name":"Maccarese Spa (gia' Forus Spa)",
    "wof:placetype":"venue"
},
  "geometry": {"coordinates":[12.215542,41.87788],"type":"Point"}
}