{
  "type": "Feature",
  "properties": {
    "iso:country":"IT",
    "sg:address":"35010 Limena",
    "sg:city":"Limena",
    "sg:orig_category":"Impiantistica E Prodotti Tecnologici Per Edilizia. Forniture Industriali Per Prevenzione, Controllo E Sicurezza",
    "sg:phone":"+39 049 884 1520",
    "sg:postcode":"35010",
    "sg:province":"Padova",
    "wof:name":"A.e.s. Srl",
    "wof:placetype":"venue"
},
  "geometry": {"coordinates":[11.842185,45.474121],"type":"Point"}
}