{
  "type": "Feature",
  "properties": {
    "iso:country":"IT",
    "sg:address":"20059 Vimercate",
    "sg:city":"Vimercate",
    "sg:orig_category":"Automobili E Mezzi Di Trasporto",
    "sg:phone":"+39 039 667151",
    "sg:postcode":"20059",
    "sg:province":"Milano",
    "sg:website":"http://www.farina.fiat.com",
    "wof:name":"Farina Spa",
    "wof:placetype":"venue"
},
  "geometry": {"coordinates":[9.368833,45.619343],"type":"Point"}
}