{
  "type": "Feature",
  "properties": {
    "iso:country":"IT",
    "sg:address":"31020 Sernaglia Della Battaglia",
    "sg:city":"Sernaglia della Battaglia",
    "sg:classifiers":[
        {
            "category":"Professional",
            "subcategory":"Employment Agencies",
            "type":"Services"
        }
    ],
    "sg:phone":"+39 0438 903186",
    "sg:postcode":"31020",
    "sg:province":"Treviso",
    "sg:tags":[
        "activities",
        "commercial",
        "equipment",
        "artisan",
        "supplies",
        "furniture",
        "accommodation",
        "furnishing"
    ],
    "wof:name":"Inhouse Srl",
    "wof:placetype":"venue"
},
  "geometry": {"coordinates":[12.166806221,45.8636932373],"type":"Point"}
}