{
  "type": "Feature",
  "properties": {
    "iso:country":"IT",
    "sg:address":"52020 Castelfranco Di Sopra",
    "sg:city":"Castelfranco di Sopra",
    "sg:orig_category":"Macchine, Impianti Ed Attrezzature Per Abbigliamento E Pelletterie",
    "sg:phone":"+39 055 914 9207",
    "sg:postcode":"52020",
    "sg:province":"Arezzo",
    "wof:name":"Zetolink Srl",
    "wof:placetype":"venue"
},
  "geometry": {"coordinates":[11.557054,43.62112],"type":"Point"}
}