{
  "type": "Feature",
  "properties": {
    "iso:country":"IT",
    "sg:address":"20144 Milano",
    "sg:city":"Milano",
    "sg:orig_category":"Servizi Ausiliari Dei Mezzi Di Trasporto",
    "sg:phone":"+39 02 498 0548",
    "sg:postcode":"20144",
    "sg:province":"Milano",
    "wof:name":"Assi Autorimessa Settimio Severo S.r.l.",
    "wof:placetype":"venue"
},
  "geometry": {"coordinates":[9.159781,45.453289],"type":"Point"}
}