{
  "type": "Feature",
  "properties": {
    "addr:full":"52026 Faella - Pian Di Sc\u00f2 Faella Arezzo 52026",
    "addr:postcode":"52026;52026",
    "addr:street":"Arezzo",
    "iso:country":"IT",
    "sg:address":"52026 Faella - Pian Di Sc\u00f2",
    "sg:city":"Faella",
    "sg:orig_category":"Articoli Per Imballaggio E Confezionamento",
    "sg:phone":"+39 055 914 6187",
    "sg:postcode":"52026",
    "sg:province":"Arezzo",
    "wof:name":"P.g. Astucci Di Piccardi Gabriele",
    "wof:placetype":"venue"
},
  "geometry": {"coordinates":[11.514683,43.626427],"type":"Point"}
}