{
  "type": "Feature",
  "properties": {
    "addr:full":"15063 Cassano Spinola Cassano Spinola Alessandria 15063",
    "addr:postcode":"15063;15063",
    "iso:country":"IT",
    "sg:address":"15063 Cassano Spinola",
    "sg:city":"Cassano Spinola",
    "sg:orig_category":"Motocicli E Motocarri - Commercio E Riparazione",
    "sg:phone":"+39 0143 477155",
    "sg:postcode":"15063",
    "sg:province":"Alessandria",
    "wof:name":"Scooter House Di Persi Francesco",
    "wof:placetype":"venue"
},
  "geometry": {"coordinates":[8.8626003265,44.7654418945],"type":"Point"}
}