{
  "type": "Feature",
  "properties": {
    "iso:country":"IT",
    "sg:address":"60035 Jesi",
    "sg:city":"Jesi",
    "sg:classifiers":[
        {
            "category":"Manufacturing",
            "subcategory":"Motor Vehicles & Parts",
            "type":"Manufacturing & Wholesale Goods"
        }
    ],
    "sg:phone":"+39 0731 56085",
    "sg:postcode":"60035",
    "sg:province":"Ancona",
    "sg:tags":[
        "vehicles",
        "accessory"
    ],
    "wof:name":"Gianangeli Delio",
    "wof:placetype":"venue"
},
  "geometry": {"coordinates":[13.263215065,43.5360908508],"type":"Point"}
}