{
  "type": "Feature",
  "properties": {
    "iso:country":"IT",
    "sg:address":"10149 Torino",
    "sg:city":"Torino",
    "sg:orig_category":"Metalli E Leghe",
    "sg:phone":"+39 011 216 1275",
    "sg:postcode":"10149",
    "sg:province":"Torino",
    "wof:name":"A.m.d. Di Fraccaro G. E C. Snc",
    "wof:placetype":"venue"
},
  "geometry": {"coordinates":[7.6643404961,45.0994567871],"type":"Point"}
}