{
  "type": "Feature",
  "properties": {
    "addr:full":"20136 Milano Milano Milano 20136",
    "addr:postcode":"20136;20136",
    "iso:country":"IT",
    "sg:address":"20136 Milano",
    "sg:city":"Milano",
    "sg:orig_category":"Prodotti Finiti Stampati. Articoli Da Regalo. Arte Ed Artigianato Artistico. Shopping",
    "sg:phone":"+39 02 5810 5663",
    "sg:postcode":"20136",
    "sg:province":"Milano",
    "wof:name":"Lorenzi Daniela",
    "wof:placetype":"venue"
},
  "geometry": {"coordinates":[9.1799173355,45.4506034851],"type":"Point"}
}