{
  "type": "Feature",
  "properties": {
    "addr:full":"12, Via Adda 22070 Casnate Con Bernate Casnate Como 22070",
    "addr:postcode":"22070;22070",
    "addr:street":"Via Adda;Con Bernate Casnate",
    "iso:country":"IT",
    "sg:address":"12, Via Adda 22070 Casnate Con Bernate",
    "sg:city":"Casnate",
    "sg:classifiers":[
        {
            "category":"Shopping",
            "subcategory":"Crafts & Fabrics",
            "type":"Retail Goods"
        }
    ],
    "sg:phone":"+39 39031450318",
    "sg:postcode":"22070",
    "sg:province":"Como",
    "wof:name":"Italstyle S.r.l.",
    "wof:placetype":"venue"
},
  "geometry": {"coordinates":[9.036400795,45.779800415],"type":"Point"}
}