{
  "type": "Feature",
  "properties": {
    "addr:full":"25018 Montichiari Montichiari Brescia 25018",
    "addr:postcode":"25018;25018",
    "iso:country":"IT",
    "sg:address":"25018 Montichiari",
    "sg:city":"Montichiari",
    "sg:orig_category":"Imprese Di Costruzioni Civili Ed Industriali",
    "sg:phone":"+39 030 996 2787",
    "sg:postcode":"25018",
    "sg:province":"Brescia",
    "wof:name":"Prelco Italia Srl",
    "wof:placetype":"venue"
},
  "geometry": {"coordinates":[10.3672132492,45.4135360718],"type":"Point"}
}