{
  "type": "Feature",
  "properties": {
    "iso:country":"IT",
    "sg:address":"80134 Napoli",
    "sg:city":"Napoli",
    "sg:orig_category":"Non-classified Establishments",
    "sg:phone":"+39 081 551 2774",
    "sg:postcode":"80134",
    "sg:province":"Napoli",
    "wof:name":"L'antico Vascello Sas Di Grazia Riccio E C.",
    "wof:placetype":"venue"
},
  "geometry": {"coordinates":[14.158528,40.858261],"type":"Point"}
}