{
  "type": "Feature",
  "properties": {
    "iso:country":"IT",
    "sg:address":"37, Via Nazionale 39040 Salorno",
    "sg:city":"Naz",
    "sg:classifiers":[
        {
            "category":"Manufacturing",
            "subcategory":"Lumber",
            "type":"Manufacturing & Wholesale Goods"
        }
    ],
    "sg:phone":"+39 0471 884148",
    "sg:postcode":"39040",
    "sg:province":"Bolzano/Bozen",
    "sg:tags":[
        "wood"
    ],
    "wof:name":"Joko (s.r.l.)",
    "wof:placetype":"venue"
},
  "geometry": {"coordinates":[11.214859,46.248238],"type":"Point"}
}