{
  "type": "Feature",
  "properties": {
    "addr:full":"09129 Cagliari Cagliari Cagliari 09129",
    "addr:postcode":"09129;09129",
    "iso:country":"IT",
    "sg:address":"09129 Cagliari",
    "sg:city":"Cagliari",
    "sg:orig_category":"Servizi Ausiliari Di Analisi, Controllo E Ricerca",
    "sg:phone":"+39 070 400333",
    "sg:postcode":"09129",
    "sg:province":"Cagliari",
    "wof:name":"Poma Luigi",
    "wof:placetype":"venue"
},
  "geometry": {"coordinates":[9.128921,39.224445],"type":"Point"}
}