{
  "type": "Feature",
  "properties": {
    "addr:full":"63030 Monsanpolo Del Tronto Ascoli Piceno 63030",
    "addr:postcode":"63030;63030",
    "addr:street":"Piceno",
    "iso:country":"IT",
    "sg:address":"63030 Monsanpolo Del Tronto",
    "sg:orig_category":"Trasporti E Spedizioni Merci",
    "sg:phone":"+39 0735 704888",
    "sg:postcode":"63030",
    "sg:province":"Ascoli Piceno",
    "wof:name":"Cavalieri Trasporti Spa",
    "wof:placetype":"venue"
},
  "geometry": {"coordinates":[13.711783,42.860195],"type":"Point"}
}