{
  "type": "Feature",
  "properties": {
    "iso:country":"IT",
    "sg:address":"50, Via Toscana 56035 Lari",
    "sg:city":"Lari",
    "sg:classifiers":[
        {
            "category":"Manufacturing",
            "subcategory":"Metals",
            "type":"Manufacturing & Wholesale Goods"
        }
    ],
    "sg:phone":"+39 0587 617288",
    "sg:postcode":"56035",
    "sg:province":"Pisa",
    "sg:tags":[
        "processing"
    ],
    "wof:name":"Art-ferro Di Volpi & Tempesti & Tommasini",
    "wof:placetype":"venue"
},
  "geometry": {"coordinates":[10.6094446182,43.611240387],"type":"Point"}
}