{
  "type": "Feature",
  "properties": {
    "iso:country":"IT",
    "sg:address":"59100 Prato",
    "sg:city":"Prato",
    "sg:orig_category":"Servizi Vari Di Interesse Pubblico",
    "sg:phone":"+39 0574 22512",
    "sg:postcode":"59100",
    "sg:province":"Prato",
    "wof:name":"Energie Benessere",
    "wof:placetype":"venue"
},
  "geometry": {"coordinates":[11.085249,43.890057],"type":"Point"}
}