{
  "type": "Feature",
  "properties": {
    "iso:country":"IT",
    "sg:address":"Via Pre' 36061 Bassano Del Grappa",
    "sg:city":"Bassano del Grappa",
    "sg:classifiers":[
        {
            "category":"Manufacturing",
            "subcategory":"Glass & Minerals",
            "type":"Manufacturing & Wholesale Goods"
        }
    ],
    "sg:phone":"+39 0424 828018",
    "sg:postcode":"36061",
    "sg:province":"Vicenza",
    "sg:tags":[
        "building",
        "material"
    ],
    "wof:name":"Ceramiche Bravo (s.n.c.)",
    "wof:placetype":"venue"
},
  "geometry": {"coordinates":[11.540307,45.545906],"type":"Point"}
}