{
  "type": "Feature",
  "properties": {
    "iso:country":"IT",
    "sg:address":"25010 Borgosatollo",
    "sg:city":"Borgosatollo",
    "sg:orig_category":"Attrezzature E Forniture Per Officine Riparazione E Servizi Ausiliari",
    "sg:phone":"+39 030 270 2387",
    "sg:postcode":"25010",
    "sg:province":"Brescia",
    "wof:name":"Pesci Attrezzature (s.r.l.)",
    "wof:placetype":"venue"
},
  "geometry": {"coordinates":[10.250657,45.482632],"type":"Point"}
}