{
  "type": "Feature",
  "properties": {
    "iso:country":"IT",
    "sg:address":"39040 Castelrotto",
    "sg:city":"Castelrotto",
    "sg:orig_category":"Ospedali E Servizi Sanitari",
    "sg:phone":"+39 0471 706553",
    "sg:postcode":"39040",
    "sg:province":"Bolzano/Bozen",
    "wof:name":"Gschwendt Gudrun",
    "wof:placetype":"venue"
},
  "geometry": {"coordinates":[11.559031,46.565369],"type":"Point"}
}