{
  "type": "Feature",
  "properties": {
    "addr:full":"46030 Pomponesco Pomponesco Mantova 46030",
    "addr:postcode":"46030;46030",
    "iso:country":"IT",
    "sg:address":"46030 Pomponesco",
    "sg:city":"Pomponesco",
    "sg:orig_category":"Impiantistica E Prodotti Tecnologici Per Edilizia. Forniture Industriali Per Prevenzione, Controllo E Sicurezza",
    "sg:phone":"+39 0375 85201",
    "sg:postcode":"46030",
    "sg:province":"Mantova",
    "wof:name":"Pezzali Carlo Di Pezzali Alessandro E Cesarina Paola Snc",
    "wof:placetype":"venue"
},
  "geometry": {"coordinates":[10.574001,44.950943],"type":"Point"}
}