{
  "type": "Feature",
  "properties": {
    "addr:full":"20144 Milano Milano Milano 20144",
    "addr:postcode":"20144;20144",
    "iso:country":"IT",
    "sg:address":"20144 Milano",
    "sg:city":"Milano",
    "sg:orig_category":"Servizi E Lavori Per Agricoltura E Zootecnia. Animali Domestici",
    "sg:phone":"+39 02 498 4958",
    "sg:postcode":"20144",
    "sg:province":"Milano",
    "wof:name":"Clinica Veterinaria Di Via Dezza",
    "wof:placetype":"venue"
},
  "geometry": {"coordinates":[9.160426,45.460541],"type":"Point"}
}