{
  "type": "Feature",
  "properties": {
    "addr:full":"22060 Cabiate Cabiate Como 22060",
    "addr:postcode":"22060;22060",
    "iso:country":"IT",
    "sg:address":"22060 Cabiate",
    "sg:city":"Cabiate",
    "sg:orig_category":"Materassi - Produzione E Ingrosso",
    "sg:phone":"+39 031 767038",
    "sg:postcode":"22060",
    "sg:province":"Como",
    "wof:name":"Polires Sas",
    "wof:placetype":"venue"
},
  "geometry": {"coordinates":[9.181753,45.663128],"type":"Point"}
}