{
  "type": "Feature",
  "properties": {
    "addr:full":"80142 Napoli Napoli Napoli 80142",
    "addr:housenumber":"80142",
    "addr:postcode":"80142",
    "iso:country":"IT",
    "sg:address":"80142 Napoli",
    "sg:city":"Napoli",
    "sg:orig_category":"Ristorazione E Locali Pubblici Affini. Servizi Ausiliari Di Ristorazione E Di Intrattenimento",
    "sg:phone":"+39 081 734 0427",
    "sg:postcode":"80142",
    "sg:province":"Napoli",
    "sg:website":"http://www.scuotto.com",
    "wof:name":"Alfonso Scuotto Group Srl",
    "wof:placetype":"venue"
},
  "geometry": {"coordinates":[14.285844,40.851196],"type":"Point"}
}