{
  "type": "Feature",
  "properties": {
    "iso:country":"IT",
    "sg:address":"59013 Montemurlo",
    "sg:city":"Montemurlo",
    "sg:orig_category":"Abbigliamento Esterno, Maglierie E Pelliccerie",
    "sg:phone":"+39 0574 799083",
    "sg:postcode":"59013",
    "sg:province":"Prato",
    "sg:website":"http://www.missaccessori.it",
    "wof:name":"Miss Accessori Srl",
    "wof:placetype":"venue"
},
  "geometry": {"coordinates":[11.037578,43.912151],"type":"Point"}
}