{
  "type": "Feature",
  "properties": {
    "iso:country":"IT",
    "sg:address":"20125 Milano",
    "sg:city":"Milano",
    "sg:orig_category":"Gas Auto Impianti - Produzione, Commercio E Installazione",
    "sg:phone":"+39 02 6610 6800",
    "sg:postcode":"20125",
    "sg:province":"Milano",
    "sg:website":"http://www.selcatecnica.it",
    "wof:name":"Selca Srl",
    "wof:placetype":"venue"
},
  "geometry": {"coordinates":[9.204624,45.501907],"type":"Point"}
}