{
  "type": "Feature",
  "properties": {
    "iso:country":"IT",
    "sg:address":"108, Via De Nicola Enrico 03043 Cassino",
    "sg:city":"Cassino",
    "sg:classifiers":[
        {
            "category":"Parking",
            "subcategory":"Lot",
            "type":"Transportation"
        }
    ],
    "sg:phone":"+39 39077621604",
    "sg:postcode":"03043",
    "sg:province":"Frosinone",
    "sg:tags":[
        "transport",
        "road"
    ],
    "wof:name":"Martucci",
    "wof:placetype":"venue"
},
  "geometry": {"coordinates":[13.351902,41.640137],"type":"Point"}
}