{
  "type": "Feature",
  "properties": {
    "addr:full":"10152 Torino Torino Torino 10152",
    "addr:postcode":"10152;10152",
    "iso:country":"IT",
    "sg:address":"10152 Torino",
    "sg:city":"Torino",
    "sg:orig_category":"Ponteggi Per Edilizia",
    "sg:phone":"+39 011 859337",
    "sg:postcode":"10152",
    "sg:province":"Torino",
    "wof:name":"Mais Geom. Stefano",
    "wof:placetype":"venue"
},
  "geometry": {"coordinates":[7.6830306053,45.0880317688],"type":"Point"}
}