{
  "type": "Feature",
  "properties": {
    "iso:country":"IT",
    "sg:address":"24020 Fiorano Al Serio",
    "sg:city":"Fiorano al Serio",
    "sg:orig_category":"Macchine E Forniture Per Ecologia E Smaltimento Rifiuti",
    "sg:phone":"+39 035 711005",
    "sg:postcode":"24020",
    "sg:province":"Bergamo",
    "sg:website":"http://www.mebimpianti.it",
    "wof:name":"Meb Impianti Srl",
    "wof:placetype":"venue"
},
  "geometry": {"coordinates":[9.844559,45.802849],"type":"Point"}
}