{
  "type": "Feature",
  "properties": {
    "iso:country":"IT",
    "sg:address":"Via Palestro, 22/24 21052 Busto Arsizio",
    "sg:city":"Busto Arsizio",
    "sg:classifiers":[
        {
            "category":"Manufacturing",
            "subcategory":"Rubber & Plastics",
            "type":"Manufacturing & Wholesale Goods"
        }
    ],
    "sg:phone":"+39 0331 632546",
    "sg:postcode":"21052",
    "sg:province":"Varese",
    "sg:tags":[
        "technical",
        "item",
        "us"
    ],
    "sg:website":"www.silgra.com",
    "wof:name":"S.i.l.g.r.a. Spa",
    "wof:placetype":"venue"
},
  "geometry": {"coordinates":[8.839897,45.611755],"type":"Point"}
}