{
  "type": "Feature",
  "properties": {
    "iso:country":"IT",
    "sg:address":"93014 Mussomeli",
    "sg:city":"Mussomeli",
    "sg:orig_category":"Metalli E Leghe",
    "sg:phone":"+39 0934 952048",
    "sg:postcode":"93014",
    "sg:province":"Caltanissetta",
    "wof:name":"Ca.me.si. F.lli Valenza",
    "wof:placetype":"venue"
},
  "geometry": {"coordinates":[13.8841190338,37.4867706299],"type":"Point"}
}