{
  "type": "Feature",
  "properties": {
    "iso:country":"IT",
    "sg:address":"37060 Castel D'azzano",
    "sg:city":"Azzano",
    "sg:orig_category":"Legno E Semilavorati. Macchine E Forniture Per Arredamento E Industria Del Legno. Hobbistica",
    "sg:phone":"+39 045 512844",
    "sg:postcode":"37060",
    "sg:province":"Verona",
    "sg:website":"http://www.fimac.com",
    "wof:name":"Fimac Spa",
    "wof:placetype":"venue"
},
  "geometry": {"coordinates":[10.960901,45.376141],"type":"Point"}
}