{
  "type": "Feature",
  "properties": {
    "iso:country":"IT",
    "sg:address":"Via Piave 18; Peveragno; 12016",
    "sg:city":"Peveragno",
    "sg:classifiers":[
        {
            "category":"Banks & Credit Unions",
            "subcategory":"Bank",
            "type":"Services"
        }
    ],
    "sg:phone":"+39 0171 383730",
    "sg:postcode":"12016",
    "sg:province":"Cuneo",
    "wof:name":"Banca Cassa Di Risparmio, Di Savigliano Spa",
    "wof:placetype":"venue"
},
  "geometry": {"coordinates":[7.617905,44.329594],"type":"Point"}
}