{
  "type": "Feature",
  "properties": {
    "addr:full":"34, Via Goffredo Mameli 22074 Lomazzo Lomazzo Como 22074",
    "addr:postcode":"22074;22074",
    "addr:street":"Via Goffredo Mameli",
    "iso:country":"IT",
    "sg:address":"34, Via Goffredo Mameli 22074 Lomazzo",
    "sg:city":"Lomazzo",
    "sg:classifiers":[
        {
            "category":"Shopping",
            "subcategory":"Stationery & Office Supplies",
            "type":"Retail Goods"
        }
    ],
    "sg:phone":"+39 02 9637 0538",
    "sg:postcode":"22074",
    "sg:province":"Como",
    "sg:tags":[
        "professional"
    ],
    "wof:name":"Marzorati Enrico (s.n.c.)",
    "wof:placetype":"venue"
},
  "geometry": {"coordinates":[9.0854558945,45.8119659424],"type":"Point"}
}