{
  "type": "Feature",
  "properties": {
    "iso:country":"IT",
    "sg:address":"12030 Caramagna Piemonte",
    "sg:city":"Caramagna Piemonte",
    "sg:orig_category":"Trattamenti Termici E Superficiali Metalli, Galvanotecnica",
    "sg:phone":"+39 0172 89381",
    "sg:postcode":"12030",
    "sg:province":"Cuneo",
    "wof:name":"Zinca (s.r.l.)",
    "wof:placetype":"venue"
},
  "geometry": {"coordinates":[7.750316,44.782352],"type":"Point"}
}