{
  "type": "Feature",
  "properties": {
    "iso:country":"IT",
    "sg:address":"Via Barberini 50; Roma; 00187",
    "sg:city":"Roma",
    "sg:classifiers":[
        {
            "category":"Banks & Credit Unions",
            "subcategory":"Bank",
            "type":"Services"
        }
    ],
    "sg:phone":"+39 06 495 9394",
    "sg:postcode":"00187",
    "sg:province":"Roma",
    "wof:name":"Bank Sepah",
    "wof:placetype":"venue"
},
  "geometry": {"coordinates":[12.491888,41.904652],"type":"Point"}
}