{
  "type": "Feature",
  "properties": {
    "addr:full":"24122 Bergamo Bergamo Bergamo 24122",
    "addr:postcode":"24122;24122",
    "iso:country":"IT",
    "sg:address":"24122 Bergamo",
    "sg:city":"Bergamo",
    "sg:orig_category":"Materiali Edili",
    "sg:phone":"+39 035 242864",
    "sg:postcode":"24122",
    "sg:province":"Bergamo",
    "wof:name":"Cugini Giuseppe Di Luca Cugini Sas",
    "wof:placetype":"venue"
},
  "geometry": {"coordinates":[9.66629,45.693398],"type":"Point"}
}