{
  "type": "Feature",
  "properties": {
    "iso:country":"IT",
    "sg:address":"80032 Casamarciano",
    "sg:city":"Casamarciano",
    "sg:orig_category":"Scuole E Servizi Scolastici. Servizi Per Lo Sport E Il Tempo Libero",
    "sg:phone":"+39 081 512 3188",
    "sg:postcode":"80032",
    "sg:province":"Napoli",
    "wof:name":"Autoscuola Motonautica La Pompeiana Iv Di Franzese Giuseppe",
    "wof:placetype":"venue"
},
  "geometry": {"coordinates":[14.559701,40.937366],"type":"Point"}
}