{
  "type": "Feature",
  "properties": {
    "addr:full":"7, Via Dante Alighieri 22070 Rovello Porro Rovello Porro Como 22070",
    "addr:postcode":"22070;22070",
    "addr:street":"Via Dante Alighieri",
    "iso:country":"IT",
    "sg:address":"7, Via Dante Alighieri 22070 Rovello Porro",
    "sg:city":"Rovello Porro",
    "sg:classifiers":[
        {
            "category":"Home & Garden",
            "subcategory":"Home Furnishings",
            "type":"Retail Goods"
        }
    ],
    "sg:phone":"+39 39029696171",
    "sg:postcode":"22070",
    "sg:province":"Como",
    "sg:tags":[
        "household"
    ],
    "wof:name":"Monti Di Rovello Srl",
    "wof:placetype":"venue"
},
  "geometry": {"coordinates":[9.002233,45.69912],"type":"Point"}
}