{
  "type": "Feature",
  "properties": {
    "iso:country":"IT",
    "sg:address":"20158 Milano",
    "sg:city":"Milano",
    "sg:orig_category":"Apparecchi, Attrezzature E Forniture Per Centri Estetici",
    "sg:phone":"+39 02 3932 1742",
    "sg:postcode":"20158",
    "sg:province":"Milano",
    "wof:name":"Fuar Schomberg S.r.l.",
    "wof:placetype":"venue"
},
  "geometry": {"coordinates":[9.169043,45.500031],"type":"Point"}
}