{
  "type": "Feature",
  "properties": {
    "addr:full":"24060 Cividino Cividino Bergamo 24060",
    "addr:postcode":"24060;24060",
    "iso:country":"IT",
    "sg:address":"24060 Cividino",
    "sg:city":"Cividino",
    "sg:orig_category":"Bevande, Vini E Liquori. Servizi E Lavori Per Industria Alimentare E Bevande",
    "sg:phone":"+39 030 743 8897",
    "sg:postcode":"24060",
    "sg:province":"Bergamo",
    "wof:name":"Distillerie Valdoglio (s.p.a.)",
    "wof:placetype":"venue"
},
  "geometry": {"coordinates":[9.897108,45.621315],"type":"Point"}
}