{
  "type": "Feature",
  "properties": {
    "addr:full":"10098 Rivoli Rivoli Torino 10098",
    "addr:postcode":"10098;10098",
    "iso:country":"IT",
    "sg:address":"10098 Rivoli",
    "sg:city":"Rivoli",
    "sg:orig_category":"Forniture Per Attivita' Industriali",
    "sg:phone":"+39 011 958 8315",
    "sg:postcode":"10098",
    "sg:province":"Torino",
    "wof:name":"Ctl Service Sas",
    "wof:placetype":"venue"
},
  "geometry": {"coordinates":[7.5484514236,45.0664901733],"type":"Point"}
}