{
  "type": "Feature",
  "properties": {
    "iso:country":"IT",
    "sg:address":"20090 Segrate",
    "sg:city":"Segrate",
    "sg:orig_category":"Tessuti E Stoffe. Tessuti Arredamento, Tende E Tappeti",
    "sg:phone":"+39 02 269031",
    "sg:postcode":"20090",
    "sg:province":"Milano",
    "sg:website":"http://www.silentgliss.it",
    "wof:name":"Silent Gliss Medit Srl",
    "wof:placetype":"venue"
},
  "geometry": {"coordinates":[9.267924,45.481659],"type":"Point"}
}