{
  "type": "Feature",
  "properties": {
    "addr:full":"21017 Samarate Samarate Varese 21017",
    "addr:postcode":"21017;21017",
    "iso:country":"IT",
    "sg:address":"21017 Samarate",
    "sg:city":"Samarate",
    "sg:orig_category":"Apparecchiature E Sistemi Per Magazzinaggio E Movimentazione",
    "sg:phone":"+39 0331 220338",
    "sg:postcode":"21017",
    "sg:province":"Varese",
    "wof:name":"Sipur Snc",
    "wof:placetype":"venue"
},
  "geometry": {"coordinates":[8.795109,45.634125],"type":"Point"}
}