{
  "type": "Feature",
  "properties": {
    "addr:full":"31050 Ponzano Veneto Ponzano Veneto Treviso 31050",
    "addr:postcode":"31050;31050",
    "iso:country":"IT",
    "sg:address":"31050 Ponzano Veneto",
    "sg:city":"Ponzano Veneto",
    "sg:orig_category":"Macchine, Impianti Ed Attrezzature Per Industria Alimentare E Bevande",
    "sg:phone":"+39 0422 440716",
    "sg:postcode":"31050",
    "sg:province":"Treviso",
    "wof:name":"Linea Gel Italiana Srl",
    "wof:placetype":"venue"
},
  "geometry": {"coordinates":[12.215297,45.7076],"type":"Point"}
}