{
  "type": "Feature",
  "properties": {
    "addr:full":"80144 Napoli Napoli Napoli 80144",
    "addr:housenumber":"80144",
    "addr:postcode":"80144",
    "iso:country":"IT",
    "sg:address":"80144 Napoli",
    "sg:city":"Napoli",
    "sg:orig_category":"Servizi E Lavori Per Abbigliamento E Pelletterie",
    "sg:phone":"+39 081 702 0186",
    "sg:postcode":"80144",
    "sg:province":"Napoli",
    "wof:name":"Iodice Maria",
    "wof:placetype":"venue"
},
  "geometry": {"coordinates":[14.254457,40.898903],"type":"Point"}
}