{
  "type": "Feature",
  "properties": {
    "iso:country":"IT",
    "sg:address":"Via Pietro Nenni 15 90014 Casteldaccia",
    "sg:city":"Casteldaccia",
    "sg:classifiers":[
        {
            "category":"Food & Beverages",
            "subcategory":"Specialty",
            "type":"Retail Goods"
        }
    ],
    "sg:phone":"+39 091 942423",
    "sg:postcode":"90014",
    "sg:province":"Palermo",
    "sg:tags":[
        "olive-oil"
    ],
    "sg:website":"www.tomaselloolii.com",
    "wof:name":"Tomasello Olii Gruppo Alimentare Srl",
    "wof:placetype":"venue"
},
  "geometry": {"coordinates":[13.529399,38.046783],"type":"Point"}
}