{
  "type": "Feature",
  "properties": {
    "iso:country":"IT",
    "sg:address":"25030 Adro",
    "sg:city":"Adro",
    "sg:orig_category":"Tende Da Sole",
    "sg:phone":"+39 030 745 0341",
    "sg:postcode":"25030",
    "sg:province":"Brescia",
    "sg:website":"http://www.tendasol.it",
    "wof:name":"Tendasol Srl",
    "wof:placetype":"venue"
},
  "geometry": {"coordinates":[9.935673,45.617577],"type":"Point"}
}