{
  "type": "Feature",
  "properties": {
    "iso:country":"IT",
    "sg:address":"27058 Voghera",
    "sg:city":"Voghera",
    "sg:orig_category":"Macchine, Impianti Ed Attrezzature Per Industria Alimentare E Bevande",
    "sg:phone":"+39 0383 367028",
    "sg:postcode":"27058",
    "sg:province":"Pavia",
    "wof:name":"Contardi Mauro",
    "wof:placetype":"venue"
},
  "geometry": {"coordinates":[9.013552,44.986153],"type":"Point"}
}