{
  "type": "Feature",
  "properties": {
    "iso:country":"IT",
    "sg:address":"37019 Peschiera Del Garda",
    "sg:city":"Peschiera del Garda",
    "sg:orig_category":"Pubblica Amministrazione",
    "sg:phone":"+39 045 640 2155",
    "sg:postcode":"37019",
    "sg:province":"Verona",
    "wof:name":"Polizia Di Stato",
    "wof:placetype":"venue"
},
  "geometry": {"coordinates":[10.6959819794,45.4397087097],"type":"Point"}
}