{
  "type": "Feature",
  "properties": {
    "iso:country":"IT",
    "sg:address":"37030 Colognola Ai Colli",
    "sg:city":"Colognola ai Colli",
    "sg:orig_category":"Lavorazioni Metalli, Stampaggio E Saldatura",
    "sg:phone":"+39 045 765 1699",
    "sg:postcode":"37030",
    "sg:province":"Verona",
    "wof:name":"Lentini Tommaso",
    "wof:placetype":"venue"
},
  "geometry": {"coordinates":[11.185791,45.417347],"type":"Point"}
}