{
  "type": "Feature",
  "properties": {
    "iso:country":"IT",
    "sg:address":"25075 Nave",
    "sg:city":"Nave",
    "sg:orig_category":"Autoveicoli Usati",
    "sg:phone":"+39 030 253 1779",
    "sg:postcode":"25075",
    "sg:province":"Brescia",
    "sg:website":"http://www.ilcamper.com",
    "wof:name":"Tonni Bazza E Bordonari",
    "wof:placetype":"venue"
},
  "geometry": {"coordinates":[10.275569,45.577034],"type":"Point"}
}