{
  "type": "Feature",
  "properties": {
    "iso:country":"IT",
    "sg:address":"10090 Cinzano",
    "sg:city":"Cinzano",
    "sg:orig_category":"Forniture Per Abbigliamento E Pelletterie",
    "sg:phone":"+39 011 960 8288",
    "sg:postcode":"10090",
    "sg:province":"Torino",
    "wof:name":"Albertazzi (s.r.l.)",
    "wof:placetype":"venue"
},
  "geometry": {"coordinates":[7.9322052002,45.0855522156],"type":"Point"}
}