{
  "type": "Feature",
  "properties": {
    "addr:full":"36071 Arzignano Arzignano Vicenza 36071",
    "addr:postcode":"36071;36071",
    "iso:country":"IT",
    "sg:address":"36071 Arzignano",
    "sg:city":"Arzignano",
    "sg:orig_category":"Forniture Per Abbigliamento E Pelletterie",
    "sg:phone":"+39 0444 670539",
    "sg:postcode":"36071",
    "sg:province":"Vicenza",
    "wof:name":"Ranzato Diego (s.a.s.)",
    "wof:placetype":"venue"
},
  "geometry": {"coordinates":[11.3453445435,45.5074729919],"type":"Point"}
}