{
  "type": "Feature",
  "properties": {
    "addr:full":"36, Via Adua 25034 Orzinuovi Orzinuovi Brescia 25034",
    "addr:postcode":"25034;25034",
    "addr:street":"Via Adua",
    "iso:country":"IT",
    "sg:address":"36, Via Adua 25034 Orzinuovi",
    "sg:city":"Orzinuovi",
    "sg:classifiers":[
        {
            "category":"Food & Beverages",
            "subcategory":"Groceries & Convenience Stores",
            "type":"Retail Goods"
        }
    ],
    "sg:phone":"+39 39030941502",
    "sg:postcode":"25034",
    "sg:province":"Brescia",
    "sg:tags":[
        "drink"
    ],
    "wof:name":"Prandelli F.lli S.r.l.",
    "wof:placetype":"venue"
},
  "geometry": {"coordinates":[9.934538,45.409634],"type":"Point"}
}