{
  "type": "Feature",
  "properties": {
    "addr:full":"20068 Peschiera Borromeo Peschiera Borromeo Milano 20068",
    "addr:postcode":"20068;20068",
    "iso:country":"IT",
    "sg:address":"20068 Peschiera Borromeo",
    "sg:city":"Peschiera Borromeo",
    "sg:orig_category":"Materiali E Componenti Elettrotecnici",
    "sg:phone":"+39 02 5530 3536",
    "sg:postcode":"20068",
    "sg:province":"Milano",
    "wof:name":"Open Line Fiberoptic (s.r.l.)",
    "wof:placetype":"venue"
},
  "geometry": {"coordinates":[9.287141,45.427883],"type":"Point"}
}