{
  "type": "Feature",
  "properties": {
    "addr:full":"70021 Acquaviva Delle Fonti Acquaviva delle Fonti Bari 70021",
    "addr:postcode":"70021;70021",
    "iso:country":"IT",
    "sg:address":"70021 Acquaviva Delle Fonti",
    "sg:city":"Acquaviva delle Fonti",
    "sg:orig_category":"Tessuti E Stoffe. Tessuti Arredamento, Tende E Tappeti. Shopping",
    "sg:phone":"+39 080 761358",
    "sg:postcode":"70021",
    "sg:province":"Bari",
    "wof:name":"Natile Ottavio",
    "wof:placetype":"venue"
},
  "geometry": {"coordinates":[16.844805,40.892803],"type":"Point"}
}