{
  "type": "Feature",
  "properties": {
    "iso:country":"IT",
    "sg:address":"16128 Genova",
    "sg:city":"Genova",
    "sg:orig_category":"Riparazione Dei Mezzi Di Trasporto. Servizi Ausiliari Dei Mezzi Di Trasporto",
    "sg:phone":"+39 010 246 6025",
    "sg:postcode":"16128",
    "sg:province":"Genova",
    "wof:name":"Rm Srl Uninominale",
    "wof:placetype":"venue"
},
  "geometry": {"coordinates":[8.926111,44.399822],"type":"Point"}
}