{
  "type": "Feature",
  "properties": {
    "iso:country":"IT",
    "sg:address":"21055 Gorla Minore",
    "sg:city":"Gorla Minore",
    "sg:orig_category":"Ospedali E Servizi Sanitari",
    "sg:phone":"+39 0331 600665",
    "sg:postcode":"21055",
    "sg:province":"Varese",
    "wof:name":"Tovagliari Trentin Silvia",
    "wof:placetype":"venue"
},
  "geometry": {"coordinates":[8.902699,45.645348],"type":"Point"}
}