{
  "type": "Feature",
  "properties": {
    "iso:country":"IT",
    "sg:address":"80133 Napoli",
    "sg:city":"Napoli",
    "sg:orig_category":"Servizi Ausiliari Per Il Trasporto. Agenzie D'affari E Servizi Commerciali",
    "sg:phone":"+39 081 552 3412",
    "sg:postcode":"80133",
    "sg:province":"Napoli",
    "wof:name":"Rotary Trading Ltd (s.r.l.)",
    "wof:placetype":"venue"
},
  "geometry": {"coordinates":[14.25237,40.842663],"type":"Point"}
}