{
  "type": "Feature",
  "properties": {
    "iso:country":"IT",
    "sg:address":"22035 Canzo",
    "sg:city":"Canzo",
    "sg:orig_category":"Non-classified Establishments",
    "sg:phone":"+39 031 682910",
    "sg:postcode":"22035",
    "sg:province":"Como",
    "sg:website":"http://www.pontiggiasnc.it",
    "wof:name":"Pontiggia Alfredo & C. Snc",
    "wof:placetype":"venue"
},
  "geometry": {"coordinates":[9.069874,45.831223],"type":"Point"}
}