{
  "type": "Feature",
  "properties": {
    "addr:full":"97019 Vittoria Vittoria Ragusa 97019",
    "addr:postcode":"97019;97019",
    "iso:country":"IT",
    "sg:address":"97019 Vittoria",
    "sg:city":"Vittoria",
    "sg:orig_category":"Rifiuti Civili, Industriali E Speciali - Impianti, Macchine E Attrezzature",
    "sg:phone":"+39 0932 866969",
    "sg:postcode":"97019",
    "sg:province":"Ragusa",
    "sg:website":"http://www.ecodep.it",
    "wof:name":"Eco.dep. Di Morando G. & C. Snc",
    "wof:placetype":"venue"
},
  "geometry": {"coordinates":[14.535599,36.94899],"type":"Point"}
}