{
  "type": "Feature",
  "properties": {
    "addr:full":"80078 Pozzuoli Pozzuoli Napoli 80078",
    "addr:postcode":"80078;80078",
    "iso:country":"IT",
    "sg:address":"80078 Pozzuoli",
    "sg:city":"Pozzuoli",
    "sg:orig_category":"Scuole E Servizi Scolastici. Ricerca, Selezione E Formazione Del Personale",
    "sg:phone":"+39 081 866 3137",
    "sg:postcode":"80078",
    "sg:province":"Napoli",
    "wof:name":"Centro Scolastico Futura Srl",
    "wof:placetype":"venue"
},
  "geometry": {"coordinates":[14.094924,40.832817],"type":"Point"}
}