{
  "type": "Feature",
  "properties": {
    "iso:country":"IT",
    "sg:address":"20059 Vimercate",
    "sg:city":"Vimercate",
    "sg:orig_category":"Dolciumi E Gelati. Condimenti, Spezie, Infusi E Caffe'",
    "sg:phone":"+39 039 661 2425",
    "sg:postcode":"20059",
    "sg:province":"Milano",
    "wof:name":"Cerestar Spa",
    "wof:placetype":"venue"
},
  "geometry": {"coordinates":[9.394711,45.633064],"type":"Point"}
}