{
  "type": "Feature",
  "properties": {
    "addr:full":"22100 Como Como Como 22100",
    "addr:postcode":"22100;22100",
    "iso:country":"IT",
    "sg:address":"22100 Como",
    "sg:city":"Como",
    "sg:orig_category":"Hobbistica",
    "sg:phone":"+39 031 555494",
    "sg:postcode":"22100",
    "sg:province":"Como",
    "wof:name":"Rossi Lamberto",
    "wof:placetype":"venue"
},
  "geometry": {"coordinates":[9.101192,45.792774],"type":"Point"}
}