{
  "type": "Feature",
  "properties": {
    "iso:country":"IT",
    "sg:address":"64, V. Ripamonti20035 Seregno",
    "sg:classifiers":[
        {
            "category":"Home & Garden",
            "subcategory":"Home Furnishings",
            "type":"Retail Goods"
        }
    ],
    "sg:phone":"+39 036 223 5997",
    "sg:postcode":"20035",
    "sg:province":"Milano",
    "sg:tags":[
        "household"
    ],
    "sg:website":"http://www.lampolet.it:ws_end: :mark:ws:http://www.paginegialle.it/springs",
    "wof:name":"Spring Srl - Gruppo Lampolet",
    "wof:placetype":"venue"
},
  "geometry": {"coordinates":[9.188141,45.463688],"type":"Point"}
}