{
  "type": "Feature",
  "properties": {
    "addr:full":"20093 Cologno Monzese Cologno Monzese Milano 20093",
    "addr:postcode":"20093;20093",
    "iso:country":"IT",
    "sg:address":"20093 Cologno Monzese",
    "sg:city":"Cologno Monzese",
    "sg:orig_category":"Nautica. Automobili E Mezzi Di Trasporto",
    "sg:phone":"+39 02 2539 1134",
    "sg:postcode":"20093",
    "sg:province":"Milano",
    "wof:name":"Nuova Jolly Sas",
    "wof:placetype":"venue"
},
  "geometry": {"coordinates":[9.284288,45.539425],"type":"Point"}
}