{
  "type": "Feature",
  "properties": {
    "addr:full":"90127 Palermo Palermo Palermo 90127",
    "addr:postcode":"90127;90127",
    "iso:country":"IT",
    "sg:address":"90127 Palermo",
    "sg:city":"Palermo",
    "sg:orig_category":"Carni, Salumi E Pesci",
    "sg:phone":"+39 091 616 1568",
    "sg:postcode":"90127",
    "sg:province":"Palermo",
    "wof:name":"Siciliana Carni Di Trapani Massimo",
    "wof:placetype":"venue"
},
  "geometry": {"coordinates":[13.364649,38.103855],"type":"Point"}
}