{
  "type": "Feature",
  "properties": {
    "iso:country":"IT",
    "sg:address":"13894 Gaglianico",
    "sg:city":"Gaglianico",
    "sg:orig_category":"Tessuti E Stoffe. Filati E Materie Prime Tessili",
    "sg:phone":"+39 015 254 3341",
    "sg:postcode":"13894",
    "sg:province":"Biella",
    "wof:name":"Caligaris Maison Royale Italia Di G.caligaris & C. S.a.s.",
    "wof:placetype":"venue"
},
  "geometry": {"coordinates":[8.060443,45.562836],"type":"Point"}
}