{
  "type": "Feature",
  "properties": {
    "iso:country":"IT",
    "sg:address":"5, V. Fallena 03034 Casalvieri",
    "sg:city":"Casalvieri",
    "sg:classifiers":[
        {
            "category":"Sports & Exercise",
            "subcategory":"Playing Field",
            "type":"Entertainment"
        }
    ],
    "sg:phone":"+39 0776 617197",
    "sg:postcode":"03034",
    "sg:province":"Frosinone",
    "sg:tags":[
        "game"
    ],
    "sg:website":"http://www.rifco.it:ws_end: :mark:ws:http://www.paginegialle.it/rifco-fr",
    "wof:name":"Rifco World Group Srl",
    "wof:placetype":"venue"
},
  "geometry": {"coordinates":[13.351902,41.640137],"type":"Point"}
}