{
  "type": "Feature",
  "properties": {
    "iso:country":"IT",
    "sg:address":"20124 Milano",
    "sg:city":"Milano",
    "sg:orig_category":"Telecomunicazioni E Telefonia, Impianti, Apparecchi E Servizi. Acqua, Luce, Gas E Societa' Di Esercizio Pubblico. Servizi Vari Di Interesse Pubblico",
    "sg:phone":"+39 02 2953 6358",
    "sg:postcode":"20124",
    "sg:province":"Milano",
    "wof:name":"Max Call Link International",
    "wof:placetype":"venue"
},
  "geometry": {"coordinates":[9.205994,45.477623],"type":"Point"}
}