{
  "type": "Feature",
  "properties": {
    "iso:country":"IT",
    "sg:address":"25, Via Jesina 60022 Castelfidardo",
    "sg:city":"Castelfidardo",
    "sg:classifiers":[
        {
            "category":"Manufacturing",
            "subcategory":"Metals",
            "type":"Manufacturing & Wholesale Goods"
        }
    ],
    "sg:phone":"+39 39071780602",
    "sg:postcode":"60022",
    "sg:province":"Ancona",
    "sg:tags":[
        "processing"
    ],
    "wof:name":"Elezinco Srl",
    "wof:placetype":"venue"
},
  "geometry": {"coordinates":[13.5523195267,43.4464416504],"type":"Point"}
}