{
  "type": "Feature",
  "properties": {
    "iso:country":"IT",
    "sg:address":"20020 Bienate Di Magnago",
    "sg:city":"Bienate",
    "sg:orig_category":"Apparecchiature E Sistemi Per Magazzinaggio E Movimentazione. Macchine E Impianti Per Attivita' Commerciali Ed Artigianali. Macchine, Strumenti Ed Apparecchi Per Attivita' Industriali",
    "sg:phone":"+39 0331 306740",
    "sg:postcode":"20020",
    "sg:province":"Milano",
    "wof:name":"Iemmegi S.r.l.",
    "wof:placetype":"venue"
},
  "geometry": {"coordinates":[9.119956,45.54184],"type":"Point"}
}