{
  "type": "Feature",
  "properties": {
    "iso:country":"IT",
    "sg:address":"Via Novara 9 22063 Cantu'",
    "sg:classifiers":[
        {
            "category":"Manufacturing",
            "subcategory":"Rubber & Plastics",
            "type":"Manufacturing & Wholesale Goods"
        }
    ],
    "sg:phone":"+39 031 716604",
    "sg:postcode":"22063",
    "sg:province":"Como",
    "sg:tags":[
        "made",
        "component",
        "furniture"
    ],
    "sg:website":"www.nuovakomart.it",
    "wof:name":"Nuova Komart Sas Di Tagliabue Emanuela & C",
    "wof:placetype":"venue"
},
  "geometry": {"coordinates":[9.1152696609,45.7293052673],"type":"Point"}
}