{
  "type": "Feature",
  "properties": {
    "addr:full":"20, Via S. Donino 25028 Verolanuova Verolanuova Brescia 25028",
    "addr:postcode":"25028;25028",
    "addr:street":"Via S. Donino",
    "iso:country":"IT",
    "sg:address":"20, Via S. Donino 25028 Verolanuova",
    "sg:city":"Verolanuova",
    "sg:classifiers":[
        {
            "category":"Shopping",
            "subcategory":"Computers & Home Electronics",
            "type":"Retail Goods"
        }
    ],
    "sg:phone":"+39 030 992 0991",
    "sg:postcode":"25028",
    "sg:province":"Brescia",
    "sg:tags":[
        "electronic",
        "electrical",
        "equipment"
    ],
    "wof:name":"Blu Italia S.r.l.",
    "wof:placetype":"venue"
},
  "geometry": {"coordinates":[10.222958,45.539829],"type":"Point"}
}