{
  "type": "Feature",
  "properties": {
    "iso:country":"IT",
    "sg:address":"24044 Dalmine",
    "sg:city":"Dalmine",
    "sg:orig_category":"Automazione E Robotica - Apparecchiature E Componenti",
    "sg:phone":"+39 035 563525",
    "sg:postcode":"24044",
    "sg:province":"Bergamo",
    "sg:website":"http://www.minipack-torre.it",
    "wof:name":"Minipack - Torre Spa",
    "wof:placetype":"venue"
},
  "geometry": {"coordinates":[9.615947,45.645271],"type":"Point"}
}