{
  "type": "Feature",
  "properties": {
    "iso:country":"IT",
    "sg:address":"36, Via Travagliato 25030 Torbole Casaglia",
    "sg:city":"Torbole Casaglia",
    "sg:classifiers":[
        {
            "category":"Manufacturing",
            "subcategory":"Rubber & Plastics",
            "type":"Manufacturing & Wholesale Goods"
        }
    ],
    "sg:phone":"+39 030 265 0316",
    "sg:postcode":"25030",
    "sg:province":"Brescia",
    "wof:name":"Bettoni Plastca S.r.l.",
    "wof:placetype":"venue"
},
  "geometry": {"coordinates":[10.1095371246,45.5165634155],"type":"Point"}
}