{
  "type": "Feature",
  "properties": {
    "addr:full":"24050 Grassobbio Grassobbio Bergamo 24050",
    "addr:postcode":"24050;24050",
    "iso:country":"IT",
    "sg:address":"24050 Grassobbio",
    "sg:city":"Grassobbio",
    "sg:orig_category":"Edilizia - Attrezzature",
    "sg:phone":"+39 035 335371",
    "sg:postcode":"24050",
    "sg:province":"Bergamo",
    "wof:name":"Lombarda Inerti Srl",
    "wof:placetype":"venue"
},
  "geometry": {"coordinates":[9.729794,45.650349],"type":"Point"}
}