{
  "type": "Feature",
  "properties": {
    "iso:country":"IT",
    "sg:address":"Via Lomellina 134 27058 Voghera",
    "sg:city":"Voghera",
    "sg:classifiers":[
        {
            "category":"Food & Beverages",
            "subcategory":"Groceries & Convenience Stores",
            "type":"Retail Goods"
        }
    ],
    "sg:phone":"+39 0383 343711",
    "sg:postcode":"27058",
    "sg:province":"Pavia",
    "sg:tags":[
        "cap",
        "bottle"
    ],
    "sg:website":"www.crowncork.com",
    "wof:name":"Crown Cork Company Italy - Compagnia Tappi Corona Spa",
    "wof:placetype":"venue"
},
  "geometry": {"coordinates":[8.979279,44.996559],"type":"Point"}
}