{
  "type": "Feature",
  "properties": {
    "addr:full":"72, Via Salaria 00198 Roma Roma Roma 00198",
    "addr:postcode":"00198;00198",
    "addr:street":"Via Salaria",
    "iso:country":"IT",
    "sg:address":"72, Via Salaria 00198 Roma",
    "sg:city":"Roma",
    "sg:classifiers":[
        {
            "category":"Shopping",
            "subcategory":"Stationery & Office Supplies",
            "type":"Retail Goods"
        }
    ],
    "sg:phone":"+39 39068417283",
    "sg:postcode":"00198",
    "sg:province":"Roma",
    "sg:tags":[
        "professional"
    ],
    "wof:name":"Rotoclass Srl",
    "wof:placetype":"venue"
},
  "geometry": {"coordinates":[12.4977359772,41.9126777649],"type":"Point"}
}