{
  "type": "Feature",
  "properties": {
    "iso:country":"IT",
    "sg:address":"90030 Bolognetta",
    "sg:city":"Bolognetta",
    "sg:orig_category":"Agriturismo",
    "sg:phone":"+39 091 829 1323",
    "sg:postcode":"90030",
    "sg:province":"Palermo",
    "wof:name":"Antica Masseria",
    "wof:placetype":"venue"
},
  "geometry": {"coordinates":[13.456853,37.966263],"type":"Point"}
}