{
  "type": "Feature",
  "properties": {
    "addr:full":"98121 Messina Messina Messina 98121",
    "addr:postcode":"98121;98121",
    "iso:country":"IT",
    "sg:address":"98121 Messina",
    "sg:city":"Messina",
    "sg:classifiers":[
        {
            "category":"Banks & Credit Unions",
            "subcategory":"Bureau De Change",
            "type":"Services"
        }
    ],
    "sg:phone":"+39 090 361300",
    "sg:postcode":"98121",
    "sg:province":"Messina",
    "sg:tags":[
        "services",
        "tourism",
        "public",
        "private",
        "transport"
    ],
    "sg:website":"http://www.tourist-ferry-boat.it",
    "wof:name":"Tourist Ferry Boat Spa",
    "wof:placetype":"venue"
},
  "geometry": {"coordinates":[15.562325,38.21365],"type":"Point"}
}