{
  "type": "Feature",
  "properties": {
    "iso:country":"IT",
    "sg:address":"Via Trebbia, 22 Qunto De'stampi 20089 Rozzano",
    "sg:city":"Rozzano",
    "sg:classifiers":[
        {
            "category":"Wholesale",
            "subcategory":"Vending Machines",
            "type":"Manufacturing & Wholesale Goods"
        }
    ],
    "sg:phone":"+39 02 824521",
    "sg:postcode":"20089",
    "sg:province":"Milano",
    "sg:tags":[
        "food",
        "special-design",
        "processing",
        "industry"
    ],
    "sg:website":"www.carle-montanari.it",
    "wof:name":"Carle & Montanari Spa",
    "wof:placetype":"venue"
},
  "geometry": {"coordinates":[9.188141,45.463688],"type":"Point"}
}