{
  "type": "Feature",
  "properties": {
    "iso:country":"IT",
    "sg:address":"20043 Arcore",
    "sg:city":"Arcore",
    "sg:orig_category":"Arredamenti E Mobili Professionali. Arredi Ed Attrezzature Per Uffici",
    "sg:phone":"+39 039 601 3918",
    "sg:postcode":"20043",
    "sg:province":"Milano",
    "wof:name":"Brianza Ufficio (s.r.l.)",
    "wof:placetype":"venue"
},
  "geometry": {"coordinates":[9.315864,45.622726],"type":"Point"}
}