{
  "type": "Feature",
  "properties": {
    "iso:country":"IT",
    "sg:address":"34131 Trieste",
    "sg:city":"Trieste",
    "sg:orig_category":"Servizi E Lavori Per Ecologia E Smaltimento Rifiuti. Arte Ed Artigianato Artistico. Servizi Ausiliari Di Sorveglianza, Manutenzione E Pulizia",
    "sg:phone":"+39 040 764319",
    "sg:postcode":"34131",
    "sg:province":"Trieste",
    "wof:name":"Riva Silvio",
    "wof:placetype":"venue"
},
  "geometry": {"coordinates":[13.875,45.64167],"type":"Point"}
}