{
  "type": "Feature",
  "properties": {
    "addr:full":"25085 Gavardo Gavardo Brescia 25085",
    "addr:postcode":"25085;25085",
    "iso:country":"IT",
    "sg:address":"25085 Gavardo",
    "sg:city":"Gavardo",
    "sg:orig_category":"Prodotti Chimici Di Base",
    "sg:phone":"+39 036 531218",
    "sg:postcode":"25085",
    "sg:province":"Brescia",
    "wof:name":"Mazzoli Fernando",
    "wof:placetype":"venue"
},
  "geometry": {"coordinates":[10.445025444,45.5894927979],"type":"Point"}
}