{
  "type": "Feature",
  "properties": {
    "iso:country":"IT",
    "sg:address":"80042 Boscotrecase",
    "sg:city":"Boscotrecase",
    "sg:orig_category":"Abbigliamento Intimo, Calze E Costumi Da Bagno. Sport - Articoli E Forniture. Shopping",
    "sg:phone":"+39 081 537 4479",
    "sg:postcode":"80042",
    "sg:province":"Napoli",
    "sg:website":"http://www.saramare.it",
    "wof:name":"Sara Di Severino Silvana & C. Snc",
    "wof:placetype":"venue"
},
  "geometry": {"coordinates":[14.469685,40.772766],"type":"Point"}
}