{
  "type": "Feature",
  "properties": {
    "addr:full":"84135 Salerno Salerno Salerno 84135",
    "addr:postcode":"84135;84135",
    "iso:country":"IT",
    "sg:address":"84135 Salerno",
    "sg:city":"Salerno",
    "sg:orig_category":"Macchine E Forniture Per Ecologia E Smaltimento Rifiuti. Termotecnica E Riscaldamento, Apparecchiature E Servizi",
    "sg:phone":"+39 089 798735",
    "sg:postcode":"84135",
    "sg:province":"Salerno",
    "wof:name":"Termosolar Srl",
    "wof:placetype":"venue"
},
  "geometry": {"coordinates":[14.776468,40.684628],"type":"Point"}
}