{
  "type": "Feature",
  "properties": {
    "iso:country":"IT",
    "sg:address":"21042 Caronno Pertusella",
    "sg:city":"Caronno Pertusella",
    "sg:orig_category":"Forniture E Materiali Per Imballaggio E Confezionamento",
    "sg:phone":"+39 02 9645 0119",
    "sg:postcode":"21042",
    "sg:province":"Varese",
    "sg:website":"http://www.vodipack.it",
    "wof:name":"Vodi Pack Spa",
    "wof:placetype":"venue"
},
  "geometry": {"coordinates":[9.0459775925,45.5978775024],"type":"Point"}
}