{
  "type": "Feature",
  "properties": {
    "iso:country":"IT",
    "sg:address":"20098 S.giuliano Milanese",
    "sg:orig_category":"Gomma Articoli Tecnici - Produzione E Commercio",
    "sg:phone":"+39 02 988 0913",
    "sg:postcode":"20098",
    "sg:province":"Milano",
    "wof:name":"Treco Srl",
    "wof:placetype":"venue"
},
  "geometry": {"coordinates":[9.188141,45.463688],"type":"Point"}
}