{
  "type": "Feature",
  "properties": {
    "addr:full":"20121 Milano Milano Milano 20121",
    "addr:postcode":"20121;20121",
    "iso:country":"IT",
    "sg:address":"20121 Milano",
    "sg:city":"Milano",
    "sg:orig_category":"Cine-foto-ottica",
    "sg:phone":"+39 02 659 6382",
    "sg:postcode":"20121",
    "sg:province":"Milano",
    "wof:name":"Free Lens Srl",
    "wof:placetype":"venue"
},
  "geometry": {"coordinates":[9.193685,45.476101],"type":"Point"}
}