{
  "type": "Feature",
  "properties": {
    "iso:country":"IT",
    "sg:address":"09127 Cagliari",
    "sg:city":"Cagliari",
    "sg:orig_category":"Autonoleggio",
    "sg:phone":"+39 070 669409",
    "sg:postcode":"09127",
    "sg:province":"Cagliari",
    "wof:name":"Autonoleggio Sina",
    "wof:placetype":"venue"
},
  "geometry": {"coordinates":[9.122096,39.215393],"type":"Point"}
}