{
  "type": "Feature",
  "properties": {
    "addr:full":"Via Pradego 34 33070 Caneva Caneva Pordenone 33070",
    "addr:housenumber":"34",
    "addr:postcode":"33070;33070",
    "addr:street":"Via Pradego",
    "iso:country":"IT",
    "sg:address":"Via Pradego 34 33070 Caneva",
    "sg:city":"Caneva",
    "sg:classifiers":[
        {
            "category":"Military Area",
            "subcategory":"Air Force Base",
            "type":"Public Place"
        }
    ],
    "sg:phone":"+39 0434 79063",
    "sg:postcode":"33070",
    "sg:province":"Pordenone",
    "sg:tags":[
        "calcium",
        "carbonate"
    ],
    "wof:name":"S.i.m.f. Calcit Srl",
    "wof:placetype":"venue"
},
  "geometry": {"coordinates":[12.465096,45.974159],"type":"Point"}
}