{
  "type": "Feature",
  "properties": {
    "iso:country":"IT",
    "sg:address":"39, V. De Gasperi 36064 Villaraspa Di Mason Vicentino",
    "sg:city":"Mason Vicentino",
    "sg:classifiers":[
        {
            "category":"Professional",
            "subcategory":"Engineering",
            "type":"Services"
        }
    ],
    "sg:phone":"+39 0424 411325",
    "sg:postcode":"36064",
    "sg:province":"Vicenza",
    "sg:tags":[
        "machine",
        "-",
        "mechanical"
    ],
    "sg:website":"http://www.bassanina.com",
    "wof:name":"Bassanina Srl",
    "wof:placetype":"venue"
},
  "geometry": {"coordinates":[11.526389,45.575279],"type":"Point"}
}