{
  "type": "Feature",
  "properties": {
    "iso:country":"IT",
    "sg:address":"20131 Milano",
    "sg:city":"Milano",
    "sg:orig_category":"Servizi Ausiliari Dei Mezzi Di Trasporto",
    "sg:phone":"+39 02 261 3676",
    "sg:postcode":"20131",
    "sg:province":"Milano",
    "wof:name":"Autorimessa Durante Sdf",
    "wof:placetype":"venue"
},
  "geometry": {"coordinates":[9.224492,45.488911],"type":"Point"}
}