{
  "type": "Feature",
  "properties": {
    "addr:full":"87100 Cosenza Cosenza Cosenza 87100",
    "addr:postcode":"87100;87100",
    "iso:country":"IT",
    "sg:address":"87100 Cosenza",
    "sg:city":"Cosenza",
    "sg:orig_category":"Studi E Consulenze Tecniche E Industriali. Servizi E Lavori Per Edilizia E Lavori Pubblici. Professionisti - Studi E Servizi Ed Associazioni Di Interesse Aziendale",
    "sg:phone":"+39 0984 73986",
    "sg:postcode":"87100",
    "sg:province":"Cosenza",
    "wof:name":"Amoroso Arch. Sergio",
    "wof:placetype":"venue"
},
  "geometry": {"coordinates":[16.203266,39.27721],"type":"Point"}
}