{
  "type": "Feature",
  "properties": {
    "iso:country":"IT",
    "sg:address":"20066 Melzo",
    "sg:city":"Melzo",
    "sg:orig_category":"Prodotti Chimici Secondari. Prodotti Cosmetici E Da Toeletta",
    "sg:phone":"+39 02 9573 5225",
    "sg:postcode":"20066",
    "sg:province":"Milano",
    "wof:name":"Dolce Pelle Di Miele Di D'acquisto C. & C. Sas",
    "wof:placetype":"venue"
},
  "geometry": {"coordinates":[9.3952255249,45.5266876221],"type":"Point"}
}