{
  "type": "Feature",
  "properties": {
    "iso:country":"IT",
    "sg:address":"20124 Milano",
    "sg:city":"Milano",
    "sg:orig_category":"Impianti, Attrezzature E Forniture Sanitarie Ed Ospedaliere",
    "sg:phone":"+39 02 669 9291",
    "sg:postcode":"20124",
    "sg:province":"Milano",
    "wof:name":"Welch Allyn Italia Srl",
    "wof:placetype":"venue"
},
  "geometry": {"coordinates":[9.203065,45.483391],"type":"Point"}
}