{
  "type": "Feature",
  "properties": {
    "iso:country":"IT",
    "sg:address":"00163 Roma",
    "sg:city":"Roma",
    "sg:orig_category":"Cinematografia E Radiotelevisione",
    "sg:phone":"+39 06 666 3304",
    "sg:postcode":"00163",
    "sg:province":"Roma",
    "wof:name":"Laura Srl",
    "wof:placetype":"venue"
},
  "geometry": {"coordinates":[12.369645,41.863174],"type":"Point"}
}