{
  "type": "Feature",
  "properties": {
    "iso:country":"IT",
    "sg:address":"16153 Genova",
    "sg:city":"Genova",
    "sg:orig_category":"Arte Ed Artigianato Artistico",
    "sg:phone":"+39 010 604 4741",
    "sg:postcode":"16153",
    "sg:province":"Genova",
    "wof:name":"Pestelli Valdieri",
    "wof:placetype":"venue"
},
  "geometry": {"coordinates":[8.848947,44.428249],"type":"Point"}
}