{
  "type": "Feature",
  "properties": {
    "iso:country":"IT",
    "sg:address":"25018 Montichiari",
    "sg:city":"Montichiari",
    "sg:orig_category":"Automobili E Mezzi Di Trasporto",
    "sg:phone":"+39 030 996 2441",
    "sg:postcode":"25018",
    "sg:province":"Brescia",
    "sg:website":"http://www.pezzaioli.net",
    "wof:name":"Carrozzeria Pezzaioli Srl",
    "wof:placetype":"venue"
},
  "geometry": {"coordinates":[10.367213,45.413536],"type":"Point"}
}