{
  "type": "Feature",
  "properties": {
    "addr:full":"47031 Repubblica S. Marino SM",
    "addr:postcode":"47031",
    "addr:street":"Repubblica",
    "iso:country":"IT",
    "sg:address":"47031 Repubblica S. Marino",
    "sg:classifiers":[
        {
            "category":"Shopping",
            "subcategory":"Luggage & Leather Goods",
            "type":"Retail Goods"
        }
    ],
    "sg:phone":"+39 0549 905250",
    "sg:province":"SM",
    "sg:tags":[
        "footwear",
        "skins"
    ],
    "wof:name":"Arca International Sa",
    "wof:placetype":"venue"
},
  "geometry": {"coordinates":[-85.1686706543,39.075340271],"type":"Point"}
}