{
  "type": "Feature",
  "properties": {
    "iso:country":"IT",
    "sg:address":"77, Via Lattanzio 20137 Milano",
    "sg:city":"Milano",
    "sg:classifiers":[
        {
            "category":"Professional",
            "subcategory":"Business Services",
            "type":"Services"
        }
    ],
    "sg:phone":"+39 02 5519 3000",
    "sg:postcode":"20137",
    "sg:province":"Milano",
    "sg:tags":[
        "advice"
    ],
    "wof:name":"Rossari E Associati S.a.s. Di Ambrogio Rossari & C.",
    "wof:placetype":"venue"
},
  "geometry": {"coordinates":[9.203226,45.482468],"type":"Point"}
}