{
  "type": "Feature",
  "properties": {
    "iso:country":"IT",
    "sg:address":"37051 Bovolone",
    "sg:city":"Bovolone",
    "sg:orig_category":"Arredo Camera Letto E Complementi",
    "sg:phone":"+39 045 710 2904",
    "sg:postcode":"37051",
    "sg:province":"Verona",
    "wof:name":"Battistella Renato",
    "wof:placetype":"venue"
},
  "geometry": {"coordinates":[11.103507,45.248722],"type":"Point"}
}