{
  "type": "Feature",
  "properties": {
    "iso:country":"IT",
    "sg:address":"Via G. Zanella 18 36043 Camisano Vicentino",
    "sg:city":"Camisano Vicentino",
    "sg:classifiers":[
        {
            "category":"Manufacturing",
            "subcategory":"Glass & Minerals",
            "type":"Manufacturing & Wholesale Goods"
        }
    ],
    "sg:phone":"+39 0444 410731",
    "sg:postcode":"36043",
    "sg:province":"Vicenza",
    "sg:tags":[
        "crystal"
    ],
    "sg:website":"www.nuovavetro.com",
    "wof:name":"Nuova Vetro Srl",
    "wof:placetype":"venue"
},
  "geometry": {"coordinates":[11.617019,45.504852],"type":"Point"}
}