{
  "type": "Feature",
  "properties": {
    "addr:full":"70020 Bitritto Bitritto Bari 70020",
    "addr:postcode":"70020;70020",
    "iso:country":"IT",
    "sg:address":"70020 Bitritto",
    "sg:city":"Bitritto",
    "sg:orig_category":"Prodotti Alimentari",
    "sg:phone":"+39 080 630253",
    "sg:postcode":"70020",
    "sg:province":"Bari",
    "wof:name":"Alberga Giuseppe",
    "wof:placetype":"venue"
},
  "geometry": {"coordinates":[16.8265895844,41.0456619263],"type":"Point"}
}