{
  "type": "Feature",
  "properties": {
    "addr:full":"77, Via Pontebbana 33031 Basiliano Basiliano Udine 33031",
    "addr:postcode":"33031;33031",
    "addr:street":"Via Pontebbana",
    "iso:country":"IT",
    "sg:address":"77, Via Pontebbana 33031 Basiliano",
    "sg:city":"Basiliano",
    "sg:classifiers":[
        {
            "category":"Shopping",
            "subcategory":"Crafts & Fabrics",
            "type":"Retail Goods"
        }
    ],
    "sg:phone":"+39 0432 830231",
    "sg:postcode":"33031",
    "sg:province":"Udine",
    "sg:tags":[
        "ceramic"
    ],
    "wof:name":"Megaron S.r.l.",
    "wof:placetype":"venue"
},
  "geometry": {"coordinates":[13.119418,46.007767],"type":"Point"}
}