{
  "type": "Feature",
  "properties": {
    "iso:country":"IT",
    "sg:address":"15057 Tortona",
    "sg:city":"Tortona",
    "sg:orig_category":"Prodotti Alimentari",
    "sg:phone":"+39 0131 870097",
    "sg:postcode":"15057",
    "sg:province":"Alessandria",
    "wof:name":"G.r.d. Sas",
    "wof:placetype":"venue"
},
  "geometry": {"coordinates":[8.8437108994,44.9004821777],"type":"Point"}
}