{
  "type": "Feature",
  "properties": {
    "iso:country":"IT",
    "sg:address":"719, Via Archimede 21042 Caronno Pertusella",
    "sg:city":"Caronno Pertusella",
    "sg:classifiers":[
        {
            "category":"Professional",
            "subcategory":"Engineering",
            "type":"Services"
        }
    ],
    "sg:phone":"+39 39029650596",
    "sg:postcode":"21042",
    "sg:province":"Varese",
    "sg:tags":[
        "machine",
        "-",
        "mechanical"
    ],
    "wof:name":"Comec (s.n.c.)",
    "wof:placetype":"venue"
},
  "geometry": {"coordinates":[9.04595,45.610409],"type":"Point"}
}