{
  "type": "Feature",
  "properties": {
    "iso:country":"IT",
    "sg:address":"4, Via Piemonte 36015 Schio",
    "sg:city":"Schio",
    "sg:classifiers":[
        {
            "category":"Shopping",
            "subcategory":"Jewelry",
            "type":"Retail Goods"
        }
    ],
    "sg:phone":"+39 0445 595511",
    "sg:postcode":"36015",
    "sg:province":"Vicenza",
    "sg:tags":[
        "jewellery"
    ],
    "wof:name":"Sisma (s.p.a.)",
    "wof:placetype":"venue"
},
  "geometry": {"coordinates":[11.386357,45.717289],"type":"Point"}
}