{
  "type": "Feature",
  "properties": {
    "iso:country":"IT",
    "sg:address":"30, Corso Mortara 10149 Torino",
    "sg:city":"Torino",
    "sg:classifiers":[
        {
            "category":"Shopping",
            "subcategory":"Computers & Home Electronics",
            "type":"Retail Goods"
        }
    ],
    "sg:phone":"+39 011 229 9611",
    "sg:postcode":"10149",
    "sg:province":"Torino",
    "sg:tags":[
        "electronic",
        "electrical",
        "equipment"
    ],
    "wof:name":"Pianelli & Traversa Sistemi S.r.l.",
    "wof:placetype":"venue"
},
  "geometry": {"coordinates":[7.670731,45.090778],"type":"Point"}
}