{
  "type": "Feature",
  "properties": {
    "addr:full":"00122 Lido Di Ostia Roma 00122",
    "addr:postcode":"00122;00122",
    "addr:street":"Di Ostia Roma",
    "iso:country":"IT",
    "sg:address":"00122 Lido Di Ostia",
    "sg:orig_category":"Accessori Moda D'abbigliamento. Shopping",
    "sg:phone":"+39 06 562 1212",
    "sg:postcode":"00122",
    "sg:province":"Roma",
    "wof:name":"Federici Rosa",
    "wof:placetype":"venue"
},
  "geometry": {"coordinates":[12.280807,41.730843],"type":"Point"}
}