{
  "type": "Feature",
  "properties": {
    "iso:country":"IT",
    "sg:address":"38089 Storo",
    "sg:city":"Storo",
    "sg:orig_category":"Carni, Salumi E Pesci",
    "sg:phone":"+39 0465 685057",
    "sg:postcode":"38089",
    "sg:province":"Trento",
    "wof:name":"Azienda Agricola Armanini S.s.",
    "wof:placetype":"venue"
},
  "geometry": {"coordinates":[10.544749,45.817497],"type":"Point"}
}