{
  "type": "Feature",
  "properties": {
    "addr:full":"10064 Pinerolo Pinerolo Torino 10064",
    "addr:postcode":"10064;10064",
    "iso:country":"IT",
    "sg:address":"10064 Pinerolo",
    "sg:city":"Pinerolo",
    "sg:classifiers":[
        {
            "category":"Health Services",
            "subcategory":"Health Practitioner",
            "type":"Services"
        }
    ],
    "sg:phone":"+39 0121 72550",
    "sg:postcode":"10064",
    "sg:province":"Torino",
    "sg:tags":[
        "medici"
    ],
    "wof:name":"Giovannelli Umberto",
    "wof:placetype":"venue"
},
  "geometry": {"coordinates":[7.340702,44.884979],"type":"Point"}
}