{
  "type": "Feature",
  "properties": {
    "iso:country":"IT",
    "sg:address":"60127 Ancona",
    "sg:city":"Ancona",
    "sg:orig_category":"Clothing, Accessories",
    "sg:phone":"+39 071 895241",
    "sg:postcode":"60127",
    "sg:province":"Ancona",
    "wof:name":"G & B Pelletterie Di Brunozzi Fabrizio",
    "wof:placetype":"venue"
},
  "geometry": {"coordinates":[13.598353,43.52803],"type":"Point"}
}