{
  "type": "Feature",
  "properties": {
    "iso:country":"IT",
    "sg:address":"58022 Follonica",
    "sg:city":"Follonica",
    "sg:orig_category":"Agenzie Immobiliari",
    "sg:phone":"+39 0566 41013",
    "sg:postcode":"58022",
    "sg:province":"Grosseto",
    "sg:website":"http://www.immobiliareballerini.com",
    "wof:name":"Ballerini Alvaro",
    "wof:placetype":"venue"
},
  "geometry": {"coordinates":[11.136556,42.706383],"type":"Point"}
}