{
  "type": "Feature",
  "properties": {
    "addr:full":"56030 Perignano Pisa 56030",
    "addr:postcode":"56030;56030",
    "iso:country":"IT",
    "sg:address":"56030 Perignano",
    "sg:orig_category":"Arredamenti - Vendita Al Dettaglio",
    "sg:phone":"+39 0587 616085",
    "sg:postcode":"56030",
    "sg:province":"Pisa",
    "wof:name":"Turini Arredamenti",
    "wof:placetype":"venue"
},
  "geometry": {"coordinates":[10.396585,43.716137],"type":"Point"}
}