{
  "type": "Feature",
  "properties": {
    "addr:full":"Via I Maggio 15 40050 Quarto Inferiore Bologna 40050",
    "addr:housenumber":"15",
    "addr:postcode":"40050;40050",
    "addr:street":"Via I Maggio;Inferiore",
    "iso:country":"IT",
    "sg:address":"Via I Maggio 15 40050 Quarto Inferiore",
    "sg:classifiers":[
        {
            "category":"Government",
            "subcategory":"Department Of Motor Vehicles",
            "type":"Public Place"
        }
    ],
    "sg:phone":"+39 051 767363",
    "sg:postcode":"40050",
    "sg:province":"Bologna",
    "sg:tags":[
        "machine",
        "closing",
        "vacuum"
    ],
    "wof:name":"Mapa Srl",
    "wof:placetype":"venue"
},
  "geometry": {"coordinates":[11.413461,44.531219],"type":"Point"}
}