{
  "type": "Feature",
  "properties": {
    "iso:country":"IT",
    "sg:address":"10086 Rivarolo Canavese",
    "sg:city":"Rivarolo Canavese",
    "sg:orig_category":"Zootecnia E Pesca, Allevamento Piccoli Animali. Animali Domestici",
    "sg:phone":"+39 0124 424113",
    "sg:postcode":"10086",
    "sg:province":"Torino",
    "wof:name":"Quattrozampe Di Bonaudo Anna Maria",
    "wof:placetype":"venue"
},
  "geometry": {"coordinates":[7.725088,45.332489],"type":"Point"}
}