{
  "type": "Feature",
  "properties": {
    "iso:country":"IT",
    "sg:address":"36015 Schio",
    "sg:city":"Schio",
    "sg:orig_category":"Servizi E Lavori Industria Chimica. Riparazione Dei Mezzi Di Trasporto",
    "sg:phone":"+39 0445 575040",
    "sg:postcode":"36015",
    "sg:province":"Vicenza",
    "wof:name":"V.a.r.m. Srl",
    "wof:placetype":"venue"
},
  "geometry": {"coordinates":[11.393225,45.721237],"type":"Point"}
}