{
  "type": "Feature",
  "properties": {
    "iso:country":"IT",
    "sg:address":"11/13, V. L. Buffoli 25032 Chiari",
    "sg:city":"Chiari",
    "sg:classifiers":[
        {
            "category":"Shopping",
            "subcategory":"Crafts & Fabrics",
            "type":"Retail Goods"
        }
    ],
    "sg:phone":"+39 39030700711",
    "sg:postcode":"25032",
    "sg:province":"Brescia",
    "sg:website":"http://www.grupponk.it",
    "wof:name":"Niggeler & Kupfer Tessiture",
    "wof:placetype":"venue"
},
  "geometry": {"coordinates":[9.9307327271,45.5392379761],"type":"Point"}
}