{
  "type": "Feature",
  "properties": {
    "iso:country":"IT",
    "sg:address":"Via Per Ospitaletto 189 25046 Cazzago San Martino",
    "sg:city":"Cazzago San Martino",
    "sg:classifiers":[
        {
            "category":"Manufacturing",
            "subcategory":"Printing",
            "type":"Manufacturing & Wholesale Goods"
        }
    ],
    "sg:phone":"+39 030 775 1145",
    "sg:postcode":"25046",
    "sg:province":"Brescia",
    "sg:tags":[
        "plastic"
    ],
    "sg:website":"www.vcmcompany.it",
    "wof:name":"Vcm Snc",
    "wof:placetype":"venue"
},
  "geometry": {"coordinates":[10.0566196442,45.5720901489],"type":"Point"}
}