{
  "type": "Feature",
  "properties": {
    "addr:full":"25061 Bovegno Bovegno Brescia 25061",
    "addr:postcode":"25061;25061",
    "iso:country":"IT",
    "sg:address":"25061 Bovegno",
    "sg:city":"Bovegno",
    "sg:orig_category":"Servizi E Lavori Per Arredamento E Industria Del Legno. Servizi E Lavori Per Edilizia E Lavori Pubblici",
    "sg:phone":"+39 030 926398",
    "sg:postcode":"25061",
    "sg:province":"Brescia",
    "wof:name":"Tanghetti Franco",
    "wof:placetype":"venue"
},
  "geometry": {"coordinates":[10.270183,45.789429],"type":"Point"}
}