{
  "type": "Feature",
  "properties": {
    "addr:full":"06127 Ferro Di Cavallo Perugia 06127",
    "addr:postcode":"06127;06127",
    "addr:street":"Di Cavallo",
    "iso:country":"IT",
    "sg:address":"06127 Ferro Di Cavallo",
    "sg:orig_category":"Ospedali E Servizi Sanitari",
    "sg:phone":"+39 075 505 2507",
    "sg:postcode":"06127",
    "sg:province":"Perugia",
    "wof:name":"Amorini Gian Daniele",
    "wof:placetype":"venue"
},
  "geometry": {"coordinates":[12.341782,43.10487],"type":"Point"}
}