{
  "type": "Feature",
  "properties": {
    "iso:country":"IT",
    "sg:address":"9, Via Lisbona 50065 Pontassieve",
    "sg:city":"Pontassieve",
    "sg:classifiers":[
        {
            "category":"Shopping",
            "subcategory":"Computers & Home Electronics",
            "type":"Retail Goods"
        }
    ],
    "sg:phone":"+39 055 836 9050",
    "sg:postcode":"50065",
    "sg:province":"Firenze",
    "sg:tags":[
        "electronic",
        "electrical",
        "equipment"
    ],
    "wof:name":"Ceza (s.r.l.)",
    "wof:placetype":"venue"
},
  "geometry": {"coordinates":[11.426304,43.773045],"type":"Point"}
}