{
  "type": "Feature",
  "properties": {
    "iso:country":"IT",
    "sg:address":"20010 Arluno",
    "sg:city":"Arluno",
    "sg:orig_category":"Elettrotecnica Industriale, Prodotti E Apparecchiature",
    "sg:phone":"+39 02 901 5051",
    "sg:postcode":"20010",
    "sg:province":"Milano",
    "wof:name":"Ineltec Costruzioni S.r.l.",
    "wof:placetype":"venue"
},
  "geometry": {"coordinates":[9.279234,45.538986],"type":"Point"}
}