{
  "type": "Feature",
  "properties": {
    "iso:country":"IT",
    "sg:address":"18038 Sanremo",
    "sg:orig_category":"Fotocomposizione",
    "sg:phone":"+39 0184 576260",
    "sg:postcode":"18038",
    "sg:province":"Imperia",
    "wof:name":"Studio A4 Service",
    "wof:placetype":"venue"
},
  "geometry": {"coordinates":[7.7742700577,43.841178894],"type":"Point"}
}