{
  "type": "Feature",
  "properties": {
    "iso:country":"IT",
    "sg:address":"09016 Iglesias",
    "sg:city":"Iglesias",
    "sg:orig_category":"Materiali E Componenti Elettrotecnici",
    "sg:phone":"+39 0781 22470",
    "sg:postcode":"09016",
    "sg:province":"Carbonia-Iglesias",
    "wof:name":"Aldo Sias Di Giovanni Sias",
    "wof:placetype":"venue"
},
  "geometry": {"coordinates":[8.642139,39.275295],"type":"Point"}
}