{
  "type": "Feature",
  "properties": {
    "addr:full":"65017 Penne Penne Pescara 65017",
    "addr:postcode":"65017;65017",
    "iso:country":"IT",
    "sg:address":"65017 Penne",
    "sg:city":"Penne",
    "sg:orig_category":"Forniture Per Edilizia E Lavori Pubblici",
    "sg:phone":"+39 085 827 0717",
    "sg:postcode":"65017",
    "sg:province":"Pescara",
    "wof:name":"Edilpav Srl",
    "wof:placetype":"venue"
},
  "geometry": {"coordinates":[13.9027986526,42.4703521729],"type":"Point"}
}