{
  "type": "Feature",
  "properties": {
    "iso:country":"IT",
    "sg:address":"25121 Brescia",
    "sg:city":"Brescia",
    "sg:orig_category":"Servizi E Lavori Per Edilizia E Lavori Pubblici. Acqua, Luce, Gas E Societa' Di Esercizio Pubblico",
    "sg:phone":"+39 030 375 9505",
    "sg:postcode":"25121",
    "sg:province":"Brescia",
    "wof:name":"Brescia Barte Di Bettini Silvio & C. S.a.s.",
    "wof:placetype":"venue"
},
  "geometry": {"coordinates":[10.229647,45.531193],"type":"Point"}
}