{
  "type": "Feature",
  "properties": {
    "iso:country":"IT",
    "sg:address":"Via Torricelli 20089 Rozzano",
    "sg:city":"Rozzano",
    "sg:classifiers":[
        {
            "category":"Shopping",
            "subcategory":"Computers & Home Electronics",
            "type":"Retail Goods"
        }
    ],
    "sg:phone":"+39 39028251055",
    "sg:postcode":"20089",
    "sg:province":"Milano",
    "sg:tags":[
        "electronic",
        "electrical",
        "equipment"
    ],
    "wof:name":"C.o.c.e.m.",
    "wof:placetype":"venue"
},
  "geometry": {"coordinates":[9.16446,45.378033],"type":"Point"}
}