{
  "type": "Feature",
  "properties": {
    "addr:full":"73, Via Sicilia 56035 Lari Lari Pisa 56035",
    "addr:postcode":"56035;56035",
    "addr:street":"Via Sicilia",
    "iso:country":"IT",
    "sg:address":"73, Via Sicilia 56035 Lari",
    "sg:city":"Lari",
    "sg:classifiers":[
        {
            "category":"Shopping",
            "type":"Retail Goods"
        }
    ],
    "sg:phone":"+39 0587 618238",
    "sg:postcode":"56035",
    "sg:province":"Pisa",
    "sg:tags":[
        "finished",
        "-",
        "metallic"
    ],
    "wof:name":"Il Ferro Battuto Di Landi Paolo E C. Snc",
    "wof:placetype":"venue"
},
  "geometry": {"coordinates":[10.607049942,43.6150245667],"type":"Point"}
}