{
  "type": "Feature",
  "properties": {
    "addr:full":"00060 Capena Capena Roma 00060",
    "addr:postcode":"00060;roma 00060",
    "iso:country":"IT",
    "sg:address":"00060 Capena",
    "sg:city":"Capena",
    "sg:orig_category":"Servizi E Lavori Per Agricoltura E Zootecnia. Consulenze Tecniche, Amministrative E Perizie",
    "sg:phone":"+39 06 9037 5020",
    "sg:postcode":"00060",
    "sg:province":"Roma",
    "wof:name":"Dallari Daniele",
    "wof:placetype":"venue"
},
  "geometry": {"coordinates":[12.541722,42.142666],"type":"Point"}
}