{
  "type": "Feature",
  "properties": {
    "iso:country":"IT",
    "sg:address":"63025 Magliano Di Tenna",
    "sg:city":"Magliano di Tenna",
    "sg:classifiers":[
        {
            "category":"Shopping",
            "type":"Retail Goods"
        }
    ],
    "sg:phone":"+39 0734 632984",
    "sg:postcode":"63025",
    "sg:province":"Ascoli Piceno",
    "sg:tags":[
        "letti"
    ],
    "wof:name":"Nicoletti Teresa",
    "wof:placetype":"venue"
},
  "geometry": {"coordinates":[13.586459,43.139088],"type":"Point"}
}