{
  "type": "Feature",
  "properties": {
    "addr:full":"06074 Perugia PG",
    "addr:postcode":"06074",
    "addr:street":"Pg",
    "iso:country":"IT",
    "sg:address":"06074 Perugia",
    "sg:orig_category":"Forniture Per Edilizia E Lavori Pubblici. Prodotti Vari In Metallo",
    "sg:phone":"+39 075 517 9441",
    "sg:province":"PG",
    "wof:name":"Mericat Srl",
    "wof:placetype":"venue"
},
  "geometry": {"coordinates":[-72.57963562010001,41.8445320129],"type":"Point"}
}