{
  "type": "Feature",
  "properties": {
    "iso:country":"IT",
    "sg:address":"24060 Endine Gaiano",
    "sg:city":"Endine",
    "sg:orig_category":"Servizi E Lavori Industria Della Gomma",
    "sg:phone":"+39 035 826066",
    "sg:postcode":"24060",
    "sg:province":"Bergamo",
    "wof:name":"Cmg (s.r.l.)",
    "wof:placetype":"venue"
},
  "geometry": {"coordinates":[9.970166,45.793446],"type":"Point"}
}