{
  "type": "Feature",
  "properties": {
    "addr:full":"20161 Milano Milano Milano 20161",
    "addr:postcode":"20161;20161",
    "iso:country":"IT",
    "sg:address":"20161 Milano",
    "sg:city":"Milano",
    "sg:classifiers":[
        {
            "category":"Manufacturing",
            "subcategory":"Tools & Machinery",
            "type":"Manufacturing & Wholesale Goods"
        }
    ],
    "sg:phone":"+39 02 6620 2258",
    "sg:postcode":"20161",
    "sg:province":"Milano",
    "sg:tags":[
        "machine",
        "system"
    ],
    "wof:name":"Recam Sas",
    "wof:placetype":"venue"
},
  "geometry": {"coordinates":[9.17084,45.523651],"type":"Point"}
}