{
  "type": "Feature",
  "properties": {
    "iso:country":"IT",
    "sg:address":"Via Latifondi 6 36020 Cismon Del Grappa",
    "sg:city":"Cismon del Grappa",
    "sg:classifiers":[
        {
            "category":"Home & Garden",
            "subcategory":"Carpets & Floor Coverings",
            "type":"Retail Goods"
        }
    ],
    "sg:phone":"+39 0424 92138",
    "sg:postcode":"36020",
    "sg:province":"Vicenza",
    "sg:tags":[
        "animal",
        "skin"
    ],
    "wof:name":"Conceria Val Cismon Srl",
    "wof:placetype":"venue"
},
  "geometry": {"coordinates":[11.728229,45.920448],"type":"Point"}
}