{
  "type": "Feature",
  "properties": {
    "addr:full":"23030 Tovo Di Sant'agata Sondrio 23030",
    "addr:postcode":"23030;23030",
    "addr:street":"Sant'Agata",
    "iso:country":"IT",
    "sg:address":"23030 Tovo Di Sant'agata",
    "sg:orig_category":"Articoli Medico-sanitari Ed Ortopedici. Impianti, Attrezzature E Forniture Sanitarie Ed Ospedaliere",
    "sg:phone":"+39 0342 771017",
    "sg:postcode":"23030",
    "sg:province":"Sondrio",
    "wof:name":"Gobbi Frattini Paolo Giuseppe",
    "wof:placetype":"venue"
},
  "geometry": {"coordinates":[10.257003,46.2621],"type":"Point"}
}