{
  "type": "Feature",
  "properties": {
    "addr:full":"Corso Liberta 112; Vercelli; 13100 Vercelli Vercelli 13100",
    "addr:housenumber":"112",
    "addr:postcode":"13100;13100",
    "addr:street":"Corso Liberta",
    "iso:country":"IT",
    "sg:address":"Corso Liberta 112; Vercelli; 13100",
    "sg:city":"Vercelli",
    "sg:classifiers":[
        {
            "category":"Banks & Credit Unions",
            "subcategory":"Bank",
            "type":"Services"
        }
    ],
    "sg:phone":"+39 0161 64021",
    "sg:postcode":"13100",
    "sg:province":"Vercelli",
    "wof:name":"Credito Italiano Spa",
    "wof:placetype":"venue"
},
  "geometry": {"coordinates":[8.424092,45.324757],"type":"Point"}
}