{
  "type": "Feature",
  "properties": {
    "iso:country":"IT",
    "sg:address":"25126 Brescia",
    "sg:city":"Brescia",
    "sg:orig_category":"Apparecchi, Attrezzature E Forniture Per Centri Estetici. Forniture Per Attivita' Commerciali Ed Artigianali",
    "sg:phone":"+39 030 45242",
    "sg:postcode":"25126",
    "sg:province":"Brescia",
    "wof:name":"Cosmetic Company Srl",
    "wof:placetype":"venue"
},
  "geometry": {"coordinates":[10.18075,45.52071],"type":"Point"}
}