{
  "type": "Feature",
  "properties": {
    "iso:country":"IT",
    "sg:address":"Viale Bassani 86; Thiene",
    "sg:classifiers":[
        {
            "category":"Banks & Credit Unions",
            "subcategory":"Bank",
            "type":"Services"
        }
    ],
    "sg:phone":"+39 0445 360314",
    "wof:name":"Banca Antoniana, Popolare Veneta Scarl",
    "wof:placetype":"venue"
},
  "geometry": {"coordinates":[11.480579,45.709457],"type":"Point"}
}