{
  "type": "Feature",
  "properties": {
    "iso:country":"IT",
    "sg:address":"30175 Mestre",
    "sg:city":"Mestre",
    "sg:orig_category":"Pubblica Amministrazione",
    "sg:phone":"+39 041 269 7111",
    "sg:postcode":"30175",
    "sg:province":"Venezia",
    "wof:name":"Vigili Del Fuoco",
    "wof:placetype":"venue"
},
  "geometry": {"coordinates":[12.2437543869,45.5176200867],"type":"Point"}
}