{
  "type": "Feature",
  "properties": {
    "addr:full":"67100 L'aquila L'Aquila 67100",
    "addr:postcode":"67100;67100",
    "iso:country":"IT",
    "sg:address":"67100 L'aquila",
    "sg:orig_category":"Arredo Urbano",
    "sg:phone":"+39 0862 404518",
    "sg:postcode":"67100",
    "sg:province":"L'Aquila",
    "wof:name":"Mancinelli Nello",
    "wof:placetype":"venue"
},
  "geometry": {"coordinates":[13.404154,42.359642],"type":"Point"}
}