{
  "type": "Feature",
  "properties": {
    "iso:country":"IT",
    "sg:address":"47900 Rimini",
    "sg:city":"Rimini",
    "sg:orig_category":"Avvocati - Studi",
    "sg:phone":"+39 0541 383392",
    "sg:postcode":"47900",
    "sg:province":"Rimini",
    "wof:name":"Zaina Airaudo Penalisti Associati",
    "wof:placetype":"venue"
},
  "geometry": {"coordinates":[12.626846,44.019012],"type":"Point"}
}