{
  "type": "Feature",
  "properties": {
    "iso:country":"IT",
    "sg:address":"33097 Spilimbergo",
    "sg:city":"Spilimbergo",
    "sg:orig_category":"Mosaici Artistici",
    "sg:phone":"+39 0427 2077",
    "sg:postcode":"33097",
    "sg:province":"Pordenone",
    "wof:name":"Consorzio Per La Scuola Mosaicisti Del Friuli",
    "wof:placetype":"venue"
},
  "geometry": {"coordinates":[12.9011659622,46.1138458252],"type":"Point"}
}