{
  "type": "Feature",
  "properties": {
    "addr:full":"31100 Treviso Treviso Treviso 31100",
    "addr:postcode":"31100;31100",
    "iso:country":"IT",
    "sg:address":"31100 Treviso",
    "sg:city":"Treviso",
    "sg:orig_category":"Non-classified Establishments",
    "sg:phone":"+39 0422 543354",
    "sg:postcode":"31100",
    "sg:province":"Treviso",
    "wof:name":"Produzione...image & Comunication",
    "wof:placetype":"venue"
},
  "geometry": {"coordinates":[12.167514,45.600922],"type":"Point"}
}