{
  "type": "Feature",
  "properties": {
    "addr:full":"71043 Manfredonia Manfredonia Foggia 71043",
    "addr:postcode":"71043;71043",
    "iso:country":"IT",
    "sg:address":"71043 Manfredonia",
    "sg:city":"Manfredonia",
    "sg:orig_category":"Macchine, Impianti Ed Attrezzature Industria Chimica",
    "sg:phone":"+39 0884 536928",
    "sg:postcode":"71043",
    "sg:province":"Foggia",
    "wof:name":"Agricoltura S.p.a. In Liquidazione",
    "wof:placetype":"venue"
},
  "geometry": {"coordinates":[15.982095,41.674229],"type":"Point"}
}