{
  "type": "Feature",
  "properties": {
    "addr:full":"03038 Roccasecca Roccasecca Frosinone 03038",
    "addr:postcode":"03038;03038",
    "iso:country":"IT",
    "sg:address":"03038 Roccasecca",
    "sg:city":"Roccasecca",
    "sg:classifiers":[
        {
            "category":"Banks & Credit Unions",
            "subcategory":"Financial Services",
            "type":"Services"
        }
    ],
    "sg:phone":"+39 0776 590038",
    "sg:postcode":"03038",
    "sg:province":"Frosinone",
    "sg:tags":[
        "services",
        "notary",
        "lawyers",
        "legal"
    ],
    "wof:name":"Ined Snc",
    "wof:placetype":"venue"
},
  "geometry": {"coordinates":[13.341129,41.639771],"type":"Point"}
}