{
  "type": "Feature",
  "properties": {
    "iso:country":"IT",
    "sg:address":"20154 Milano",
    "sg:city":"Milano",
    "sg:orig_category":"Accessori Moda D'abbigliamento",
    "sg:phone":"+39 02 331 4896",
    "sg:postcode":"20154",
    "sg:province":"Milano",
    "wof:name":"Falcon's Srl",
    "wof:placetype":"venue"
},
  "geometry": {"coordinates":[9.175256,45.480679],"type":"Point"}
}