{
  "type": "Feature",
  "properties": {
    "iso:country":"IT",
    "sg:address":"31030 Carbonera",
    "sg:city":"Carbonera",
    "sg:orig_category":"Materiali Semilavorati Metallici",
    "sg:phone":"+39 0422 398159",
    "sg:postcode":"31030",
    "sg:province":"Treviso",
    "wof:name":"Tecnogronde Di L. E L. Schiavon (s.n.c.)",
    "wof:placetype":"venue"
},
  "geometry": {"coordinates":[12.262164,45.697708],"type":"Point"}
}