{
  "type": "Feature",
  "properties": {
    "addr:full":"20038 Seregno Seregno Milano 20038",
    "addr:postcode":"20038;20038",
    "iso:country":"IT",
    "sg:address":"20038 Seregno",
    "sg:city":"Seregno",
    "sg:classifiers":[
        {
            "category":"Home & Garden",
            "subcategory":"Home Furnishings",
            "type":"Retail Goods"
        }
    ],
    "sg:phone":"+39 036 223 0442",
    "sg:postcode":"20038",
    "sg:province":"Milano",
    "sg:tags":[
        "activities",
        "commercial",
        "equipment",
        "artisan",
        "professional",
        "furniture"
    ],
    "sg:website":"http://italvetrine.it",
    "wof:name":"Italvetrine Srl",
    "wof:placetype":"venue"
},
  "geometry": {"coordinates":[9.1736850739,45.4856872559],"type":"Point"}
}