{
  "type": "Feature",
  "properties": {
    "iso:country":"IT",
    "sg:address":"52010 Capolona",
    "sg:city":"Capolona",
    "sg:orig_category":"Argenteria - Lavorazione E Ingrosso",
    "sg:phone":"+39 0575 420686",
    "sg:postcode":"52010",
    "sg:province":"Arezzo",
    "wof:name":"La Metor Srl",
    "wof:placetype":"venue"
},
  "geometry": {"coordinates":[11.859814,43.565533],"type":"Point"}
}