{
  "type": "Feature",
  "properties": {
    "iso:country":"IT",
    "sg:address":"Via Palmarina 115 33048 San Giovanni Al Natisone",
    "sg:city":"San Giovanni al Natisone",
    "sg:classifiers":[
        {
            "category":"Manufacturing",
            "subcategory":"Glass & Minerals",
            "type":"Manufacturing & Wholesale Goods"
        }
    ],
    "sg:phone":"+39 0432 757170",
    "sg:postcode":"33048",
    "sg:province":"Udine",
    "sg:tags":[
        "industry",
        "beverage",
        "jar",
        "bottle"
    ],
    "sg:website":"www.vetrofriuli.it",
    "wof:name":"Vetro Friuli Srl",
    "wof:placetype":"venue"
},
  "geometry": {"coordinates":[13.396964,45.96154],"type":"Point"}
}