{
  "type": "Feature",
  "properties": {
    "iso:country":"IT",
    "sg:address":"00049 Velletri",
    "sg:city":"Velletri",
    "sg:orig_category":"Chiese Ed Associazioni Religiose",
    "sg:phone":"+39 06 964 0823",
    "sg:postcode":"00049",
    "sg:province":"Roma",
    "wof:name":"Centro S. Maria Dell'acero",
    "wof:placetype":"venue"
},
  "geometry": {"coordinates":[12.730062,41.725807],"type":"Point"}
}