{
  "type": "Feature",
  "properties": {
    "addr:full":"21042 Caronno Pertusella Caronno Pertusella Varese 21042",
    "addr:postcode":"21042;pertusella;21042",
    "addr:street":"Pertusella",
    "iso:country":"IT",
    "sg:address":"21042 Caronno Pertusella",
    "sg:city":"Caronno Pertusella",
    "sg:orig_category":"Forniture Per Agricoltura E Zootecnia",
    "sg:phone":"+39 02 9645 0464",
    "sg:postcode":"21042",
    "sg:province":"Varese",
    "sg:website":"http://www.allpet.it",
    "wof:name":"All Pet Srl",
    "wof:placetype":"venue"
},
  "geometry": {"coordinates":[9.0593118668,45.5893287659],"type":"Point"}
}