{
  "type": "Feature",
  "properties": {
    "iso:country":"IT",
    "sg:address":"Via Alberghi Ang 26, Castellare, 51012 Pescia, Pt",
    "sg:city":"Pescia",
    "sg:classifiers":[
        {
            "category":"Banks & Credit Unions",
            "subcategory":"Bank",
            "type":"Services"
        }
    ],
    "sg:postcode":"51012",
    "sg:province":"Pistoia",
    "wof:name":"Banca Di Pescia-credito Cooperativo Scarl",
    "wof:placetype":"venue"
},
  "geometry": {"coordinates":[10.918524,43.932156],"type":"Point"}
}