{
  "type": "Feature",
  "properties": {
    "iso:country":"IT",
    "sg:address":"20149 Milano",
    "sg:city":"Milano",
    "sg:classifiers":[
        {
            "category":"Autos & Motor Vehicles",
            "subcategory":"Fuel & Gas Station",
            "type":"Retail Goods"
        }
    ],
    "sg:phone":"+39 02 3360 2525",
    "sg:postcode":"20149",
    "sg:province":"Milano",
    "sg:tags":[
        "activities",
        "industrial",
        "instrument",
        "equipment",
        "pumps",
        "machines"
    ],
    "sg:website":"http://www.vogtgroup.com",
    "wof:name":"Pinedo Srl",
    "wof:placetype":"venue"
},
  "geometry": {"coordinates":[9.1600751877,45.4836654663],"type":"Point"}
}