{
  "type": "Feature",
  "properties": {
    "addr:full":"40069 Zola Predosa Zola Bologna 40069",
    "addr:postcode":"40069;40069",
    "iso:country":"IT",
    "sg:address":"40069 Zola Predosa",
    "sg:city":"Zola",
    "sg:orig_category":"Accessori Dei Mezzi Di Trasporto",
    "sg:phone":"+39 051 617 6011",
    "sg:postcode":"40069",
    "sg:province":"Bologna",
    "sg:website":"http://www.verlicchi.it",
    "wof:name":"Verlicchi Nino & Figli Spa",
    "wof:placetype":"venue"
},
  "geometry": {"coordinates":[11.26053,44.49844],"type":"Point"}
}