{
  "type": "Feature",
  "properties": {
    "iso:country":"IT",
    "sg:address":"80138 Napoli",
    "sg:city":"Napoli",
    "sg:orig_category":"Scuole E Servizi Scolastici. Ricerca, Selezione E Formazione Del Personale",
    "sg:phone":"+39 081 262048",
    "sg:postcode":"80138",
    "sg:province":"Napoli",
    "sg:website":"http://www.istitutorubens.it",
    "wof:name":"Istituto Rubens Di T. Manes",
    "wof:placetype":"venue"
},
  "geometry": {"coordinates":[14.180674,40.860336],"type":"Point"}
}