{
  "type": "Feature",
  "properties": {
    "addr:full":"46100 Mantova Mantova Mantova 46100",
    "addr:postcode":"46100;46100",
    "iso:country":"IT",
    "sg:address":"46100 Mantova",
    "sg:city":"Mantova",
    "sg:orig_category":"Fotografia - Servizi, Studi, Sviluppo E Stampa",
    "sg:phone":"+39 0376 365574",
    "sg:postcode":"46100",
    "sg:province":"Mantova",
    "wof:name":"Photocolor Di Querci F. & C. Snc",
    "wof:placetype":"venue"
},
  "geometry": {"coordinates":[10.790555954,45.1613388062],"type":"Point"}
}