{
  "type": "Feature",
  "properties": {
    "iso:country":"IT",
    "sg:address":"21, Via Zona Industriale 64027 Sant'omero",
    "sg:classifiers":[
        {
            "category":"Autos & Motor Vehicles",
            "subcategory":"Automobile Sales",
            "type":"Retail Goods"
        }
    ],
    "sg:phone":"+39 39086181201",
    "sg:postcode":"64027",
    "sg:province":"Teramo",
    "sg:tags":[
        "industrial"
    ],
    "wof:name":"M.i.v.v.spa Metal Industria Val Vibrata",
    "wof:placetype":"venue"
},
  "geometry": {"coordinates":[13.698531,42.66127],"type":"Point"}
}