{
  "type": "Feature",
  "properties": {
    "addr:full":"Via Asse Attrezzato 03100 Frosinone Frosinone Frosinone 03100",
    "addr:postcode":"03100;03100",
    "addr:street":"Via Asse Attrezzato",
    "iso:country":"IT",
    "sg:address":"Via Asse Attrezzato 03100 Frosinone",
    "sg:city":"Frosinone",
    "sg:classifiers":[
        {
            "category":"Manufacturing",
            "subcategory":"Paper Products",
            "type":"Manufacturing & Wholesale Goods"
        }
    ],
    "sg:phone":"+39 0775 292422",
    "sg:postcode":"03100",
    "sg:province":"Frosinone",
    "sg:tags":[
        "cardboard"
    ],
    "wof:name":"Regma Italia Spa",
    "wof:placetype":"venue"
},
  "geometry": {"coordinates":[13.3519020081,41.6401367188],"type":"Point"}
}