{
  "type": "Feature",
  "properties": {
    "addr:full":"57 Via Mezzofanti Giuseppe, 40137 Bologna Bologna Bologna 40137",
    "addr:postcode":"40137;40137",
    "addr:street":"Via Mezzofanti Giuseppe",
    "iso:country":"IT",
    "sg:address":"57 Via Mezzofanti Giuseppe, 40137 Bologna",
    "sg:city":"Bologna",
    "sg:classifiers":[
        {
            "category":"Banks & Credit Unions",
            "subcategory":"Financial Services",
            "type":"Services"
        }
    ],
    "sg:phone":"+39 39051307686",
    "sg:postcode":"40137",
    "sg:province":"Bologna",
    "sg:tags":[
        "banking",
        "finance",
        "insurance"
    ],
    "wof:name":"Inco (sas)",
    "wof:placetype":"venue"
},
  "geometry": {"coordinates":[11.3464813232,44.4942207336],"type":"Point"}
}