{
  "type": "Feature",
  "properties": {
    "addr:full":"80, Via Due Giugno 13866 Masserano Masserano Biella 13866",
    "addr:postcode":"13866;13866",
    "addr:street":"Via Due Giugno;Masserano",
    "iso:country":"IT",
    "sg:address":"80, Via Due Giugno 13866 Masserano",
    "sg:city":"Masserano",
    "sg:classifiers":[
        {
            "category":"Shopping",
            "subcategory":"Crafts & Fabrics",
            "type":"Retail Goods"
        }
    ],
    "sg:phone":"+39 015 951 5411",
    "sg:postcode":"13866",
    "sg:province":"Biella",
    "wof:name":"Union (s.p.a.)",
    "wof:placetype":"venue"
},
  "geometry": {"coordinates":[8.0582695007,45.5628356934],"type":"Point"}
}