{
  "type": "Feature",
  "properties": {
    "iso:country":"IT",
    "sg:address":"10044 Pianezza",
    "sg:city":"Pianezza",
    "sg:orig_category":"Aspirazione Impianti",
    "sg:phone":"+39 011 966 1274",
    "sg:postcode":"10044",
    "sg:province":"Torino",
    "sg:website":"http://www.isar.it",
    "wof:name":"Isar Snc Di Sini E Raviolo",
    "wof:placetype":"venue"
},
  "geometry": {"coordinates":[7.593248,45.096569],"type":"Point"}
}