{
  "type": "Feature",
  "properties": {
    "addr:full":"261, Via Del Santo 98148 Messina Messina Messina 98148",
    "addr:housenumber":"261",
    "addr:postcode":"98148;98148",
    "addr:street":"Via Del Santo",
    "iso:country":"IT",
    "sg:address":"261, Via Del Santo 98148 Messina",
    "sg:city":"Messina",
    "sg:classifiers":[
        {
            "category":"Manufacturing",
            "subcategory":"Metals",
            "type":"Manufacturing & Wholesale Goods"
        }
    ],
    "sg:phone":"+39 39090692078",
    "sg:postcode":"98148",
    "sg:province":"Messina",
    "sg:tags":[
        "metallurgy",
        "metalworking"
    ],
    "wof:name":"Metal 2000 Snc",
    "wof:placetype":"venue"
},
  "geometry": {"coordinates":[15.5151567459,38.1671066284],"type":"Point"}
}