{
  "type": "Feature",
  "properties": {
    "addr:full":"20154 Milano Milano Milano 20154",
    "addr:postcode":"20154;20154",
    "iso:country":"IT",
    "sg:address":"20154 Milano",
    "sg:city":"Milano",
    "sg:orig_category":"Servizi Editoriali. Professionisti - Studi E Servizi Ed Associazioni Di Interesse Aziendale",
    "sg:phone":"+39 02 3310 5481",
    "sg:postcode":"20154",
    "sg:province":"Milano",
    "wof:name":"Nanetti Associati S.r.l.",
    "wof:placetype":"venue"
},
  "geometry": {"coordinates":[9.178205,45.477215],"type":"Point"}
}