{
  "type": "Feature",
  "properties": {
    "addr:full":"16044 Cicagna Cicagna Genova 16044",
    "addr:postcode":"16044;16044",
    "iso:country":"IT",
    "sg:address":"16044 Cicagna",
    "sg:city":"Cicagna",
    "sg:orig_category":"Marmo, Pietre Ed Affini",
    "sg:phone":"+39 0185 971000",
    "sg:postcode":"16044",
    "sg:province":"Genova",
    "wof:name":"Carlo Giuffra Ardesie Srl",
    "wof:placetype":"venue"
},
  "geometry": {"coordinates":[9.261259,44.398777],"type":"Point"}
}