{
  "type": "Feature",
  "properties": {
    "iso:country":"IT",
    "sg:address":"24044 Dalmine",
    "sg:city":"Dalmine",
    "sg:orig_category":"Materiali Edili",
    "sg:phone":"+39 035 564455",
    "sg:postcode":"24044",
    "sg:province":"Bergamo",
    "wof:name":"Sider Refrattari",
    "wof:placetype":"venue"
},
  "geometry": {"coordinates":[9.610618,45.646519],"type":"Point"}
}