{
  "type": "Feature",
  "properties": {
    "addr:full":"4, Via Affarosa 42010 Rio Saliceto Reggio Nell'Emilia 42010",
    "addr:postcode":"42010;42010",
    "addr:street":"Via Affarosa",
    "iso:country":"IT",
    "sg:address":"4, Via Affarosa 42010 Rio Saliceto",
    "sg:classifiers":[
        {
            "category":"Retail",
            "subcategory":"Animal Services",
            "type":"Services"
        }
    ],
    "sg:phone":"+39 0522 649160",
    "sg:postcode":"42010",
    "sg:province":"Reggio Nell'Emilia",
    "sg:tags":[
        "breeding"
    ],
    "wof:name":"Industria Italiana Integratori Tre I (s.p.a.)",
    "wof:placetype":"venue"
},
  "geometry": {"coordinates":[10.785678,44.813648],"type":"Point"}
}