{
  "type": "Feature",
  "properties": {
    "iso:country":"IT",
    "sg:address":"20144 Milano",
    "sg:city":"Milano",
    "sg:orig_category":"Musica",
    "sg:phone":"+39 02 839 4686",
    "sg:postcode":"20144",
    "sg:province":"Milano",
    "sg:website":"http://www.jacaranda.it",
    "wof:name":"Liuteria Artigiana Jacaranda",
    "wof:placetype":"venue"
},
  "geometry": {"coordinates":[9.1734380722,45.4522285461],"type":"Point"}
}