{
  "type": "Feature",
  "properties": {
    "addr:full":"30030 Venezia Venezia 30030",
    "addr:postcode":"30030;30030",
    "iso:country":"IT",
    "sg:address":"30030 Venezia",
    "sg:orig_category":"Autotrasporti",
    "sg:phone":"+39 347 240 2168",
    "sg:postcode":"30030",
    "sg:province":"Venezia",
    "wof:name":"Mi.da. Srl",
    "wof:placetype":"venue"
},
  "geometry": {"coordinates":[12.690209,45.714836],"type":"Point"}
}