{
  "type": "Feature",
  "properties": {
    "iso:country":"IT",
    "sg:address":"21020 Casale Litta",
    "sg:city":"Casale Litta",
    "sg:orig_category":"Servizi E Lavori Industria Della Gomma",
    "sg:phone":"+39 0332 945800",
    "sg:postcode":"21020",
    "sg:province":"Varese",
    "wof:name":"Baratelli Emilia Ernesta",
    "wof:placetype":"venue"
},
  "geometry": {"coordinates":[8.742039,45.753044],"type":"Point"}
}