{
  "type": "Feature",
  "properties": {
    "addr:full":"1, Via Enrico Fermi 24035 Curno Curno Bergamo 24035",
    "addr:postcode":"24035;24035",
    "addr:street":"Via Enrico Fermi",
    "iso:country":"IT",
    "sg:address":"1, Via Enrico Fermi 24035 Curno",
    "sg:city":"Curno",
    "sg:classifiers":[
        {
            "category":"Shopping",
            "subcategory":"Crafts & Fabrics",
            "type":"Retail Goods"
        }
    ],
    "sg:phone":"+39 39035462522",
    "sg:postcode":"24035",
    "sg:province":"Bergamo",
    "sg:tags":[
        "ceramic"
    ],
    "wof:name":"I Negozi Del Sole (s.r.l.)",
    "wof:placetype":"venue"
},
  "geometry": {"coordinates":[9.616645,45.683575],"type":"Point"}
}