{
  "type": "Feature",
  "properties": {
    "iso:country":"IT",
    "sg:address":"53, Via Xxv Aprile 23868 Valmadrera",
    "sg:city":"Valmadrera",
    "sg:classifiers":[
        {
            "category":"Professional",
            "subcategory":"Engineering",
            "type":"Services"
        }
    ],
    "sg:phone":"+39 0341 581522",
    "sg:postcode":"23868",
    "sg:province":"Lecco",
    "sg:tags":[
        "machine",
        "-",
        "mechanical"
    ],
    "wof:name":"Metallurgica Manente Di Manente L. & C. (s.n.c.)",
    "wof:placetype":"venue"
},
  "geometry": {"coordinates":[9.390071,45.852982],"type":"Point"}
}