{
  "type": "Feature",
  "properties": {
    "iso:country":"IT",
    "sg:address":"39028 Silandro",
    "sg:city":"Silandro",
    "sg:orig_category":"Pubblica Amministrazione",
    "sg:phone":"+39 0473 736800",
    "sg:postcode":"39028",
    "sg:province":"Bolzano/Bozen",
    "wof:name":"Comunita' Comprensoriale Val Venosta",
    "wof:placetype":"venue"
},
  "geometry": {"coordinates":[10.7741994858,46.6278038025],"type":"Point"}
}