{
  "type": "Feature",
  "properties": {
    "addr:full":"2, Via Raffaello 42100 Reggio Emilia Reggio Nell'Emilia 42100",
    "addr:postcode":"42100;42100",
    "addr:street":"Via Raffaello",
    "iso:country":"IT",
    "sg:address":"2, Via Raffaello 42100 Reggio Emilia",
    "sg:classifiers":[
        {
            "category":"Real Estate",
            "subcategory":"Surveying",
            "type":"Services"
        }
    ],
    "sg:phone":"+39 0522 922000",
    "sg:postcode":"42100",
    "sg:province":"Reggio Nell'Emilia",
    "sg:tags":[
        "equipment",
        "material",
        "good",
        "-",
        "handling"
    ],
    "wof:name":"Cuccolini S.r.l.",
    "wof:placetype":"venue"
},
  "geometry": {"coordinates":[10.649907,44.731277],"type":"Point"}
}