{
  "type": "Feature",
  "properties": {
    "iso:country":"IT",
    "sg:address":"20121 Milano",
    "sg:city":"Milano",
    "sg:orig_category":"Servizi Ausiliari Di Certificati, Riproduzioni, Disegni E Foto",
    "sg:phone":"+39 02 655 4350",
    "sg:postcode":"20121",
    "sg:province":"Milano",
    "wof:name":"Autoscuola Brera Di Bianco Valeria & C. Sas",
    "wof:placetype":"venue"
},
  "geometry": {"coordinates":[9.183851,45.47588],"type":"Point"}
}