{
  "type": "Feature",
  "properties": {
    "iso:country":"IT",
    "sg:address":"20146 Milano",
    "sg:city":"Milano",
    "sg:orig_category":"Arte Ed Artigianato Artistico",
    "sg:phone":"+39 02 4819 4750",
    "sg:postcode":"20146",
    "sg:province":"Milano",
    "wof:name":"Zucca Massimiliano",
    "wof:placetype":"venue"
},
  "geometry": {"coordinates":[9.151175,45.465973],"type":"Point"}
}