{
  "type": "Feature",
  "properties": {
    "iso:country":"IT",
    "sg:address":"21047 Saronno",
    "sg:city":"Saronno",
    "sg:orig_category":"Utensili Meccanici E Materiali. Elettrotecnica Industriale, Prodotti E Apparecchiature",
    "sg:phone":"+39 02 962 5523",
    "sg:postcode":"21047",
    "sg:province":"Varese",
    "wof:name":"S.a.e. Elettromeccanica (s.n.c.)",
    "wof:placetype":"venue"
},
  "geometry": {"coordinates":[9.032098,45.627552],"type":"Point"}
}