{
  "type": "Feature",
  "properties": {
    "iso:country":"IT",
    "sg:address":"Via Cavour 30; Torino; 10123",
    "sg:city":"Torino",
    "sg:classifiers":[
        {
            "category":"Banks & Credit Unions",
            "subcategory":"Bank",
            "type":"Services"
        }
    ],
    "sg:phone":"+39 011 885222",
    "sg:postcode":"10123",
    "sg:province":"Torino",
    "wof:name":"Efibanca Ente Finanziario, Interbancario Spa",
    "wof:placetype":"venue"
},
  "geometry": {"coordinates":[7.687027,45.063793],"type":"Point"}
}