{
  "type": "Feature",
  "properties": {
    "iso:country":"IT",
    "sg:address":"39055 Laives",
    "sg:city":"Laives",
    "sg:orig_category":"Servizi E Lavori Per Agricoltura E Zootecnia. Animali Domestici",
    "sg:phone":"+39 333 217 0709",
    "sg:postcode":"39055",
    "sg:province":"Bolzano/Bozen",
    "wof:name":"Schiliro' Dott. Giuseppe",
    "wof:placetype":"venue"
},
  "geometry": {"coordinates":[11.343304,46.427269],"type":"Point"}
}