{
  "type": "Feature",
  "properties": {
    "iso:country":"IT",
    "sg:address":"19, V. Mazzoni 50134 Firenze",
    "sg:city":"Firenze",
    "sg:classifiers":[
        {
            "category":"Shopping",
            "subcategory":"Clothing, Apparel, & Fashions",
            "type":"Retail Goods"
        }
    ],
    "sg:phone":"+39 39055428851",
    "sg:postcode":"50134",
    "sg:province":"Firenze",
    "sg:tags":[
        "clothing",
        "accessory"
    ],
    "sg:website":"http://www.afbsrl.com",
    "wof:name":"A.f.b. Srl",
    "wof:placetype":"venue"
},
  "geometry": {"coordinates":[11.242778,43.793957],"type":"Point"}
}