{
  "type": "Feature",
  "properties": {
    "addr:full":"89018 Villa San Giovanni Villa San Giovanni Reggio Di Calabria 89018",
    "addr:housenumber":"89018",
    "addr:postcode":"89018",
    "addr:street":"Villa San Giovanni Villa San",
    "iso:country":"IT",
    "sg:address":"89018 Villa San Giovanni",
    "sg:city":"Villa San Giovanni",
    "sg:orig_category":"Servizi Al Turismo. Trasporto Pubblico E Privato",
    "sg:phone":"+39 0965 793111",
    "sg:postcode":"89018",
    "sg:province":"Reggio Di Calabria",
    "sg:website":"http://www.carontespa.it",
    "wof:name":"Caronte Spa",
    "wof:placetype":"venue"
},
  "geometry": {"coordinates":[15.645871,38.165047],"type":"Point"}
}