{
  "type": "Feature",
  "properties": {
    "addr:full":"418, Circonv. Nomentana00162 Roma Roma Roma 00162",
    "addr:housenumber":"418;nomentana00162",
    "addr:postcode":"00162",
    "addr:street":"Circonv.",
    "iso:country":"IT",
    "sg:address":"418, Circonv. Nomentana00162 Roma",
    "sg:city":"Roma",
    "sg:classifiers":[
        {
            "category":"Banks & Credit Unions",
            "subcategory":"Investment Brokerage",
            "type":"Services"
        }
    ],
    "sg:phone":"+39 39064404615",
    "sg:postcode":"00162",
    "sg:province":"Roma",
    "sg:tags":[
        "-",
        "transport",
        "related"
    ],
    "sg:website":"http://www.alimerci.com",
    "wof:name":"Alimerci Srl",
    "wof:placetype":"venue"
},
  "geometry": {"coordinates":[12.482325,41.895466],"type":"Point"}
}