{
  "type": "Feature",
  "properties": {
    "iso:country":"IT",
    "sg:address":"04012 Cisterna Di Latina",
    "sg:city":"Cisterna di Latina",
    "sg:orig_category":"Scuole E Servizi Scolastici",
    "sg:phone":"+39 06 969 6502",
    "sg:postcode":"04012",
    "sg:province":"Latina",
    "wof:name":"Comune",
    "wof:placetype":"venue"
},
  "geometry": {"coordinates":[12.828477,41.575401],"type":"Point"}
}