{
  "type": "Feature",
  "properties": {
    "iso:country":"IT",
    "sg:address":"36078 Valdagno",
    "sg:city":"Valdagno",
    "sg:orig_category":"Elettrotecnica Industriale, Prodotti E Apparecchiature. Ricambi E Componenti Dei Mezzi Di Trasporto",
    "sg:phone":"+39 0445 404849",
    "sg:postcode":"36078",
    "sg:province":"Vicenza",
    "wof:name":"Nuova Polo (s.r.l.)",
    "wof:placetype":"venue"
},
  "geometry": {"coordinates":[11.308367,45.63393],"type":"Point"}
}