{
  "type": "Feature",
  "properties": {
    "iso:country":"IT",
    "sg:address":"25020 Flero",
    "sg:city":"Flero",
    "sg:orig_category":"Apparecchi, Attrezzature E Forniture Per Centri Estetici. Forniture Per Attivita' Commerciali Ed Artigianali",
    "sg:phone":"+39 030 254 0252",
    "sg:postcode":"25020",
    "sg:province":"Brescia",
    "sg:website":"http://www.sciar.it",
    "wof:name":"S.c.i.a.r. Srl",
    "wof:placetype":"venue"
},
  "geometry": {"coordinates":[10.178535,45.470486],"type":"Point"}
}