{
  "type": "Feature",
  "properties": {
    "iso:country":"IT",
    "sg:address":"35015 Galliera Veneta",
    "sg:city":"Galliera Veneta",
    "sg:orig_category":"Metalli E Leghe",
    "sg:phone":"+39 049 596 8844",
    "sg:postcode":"35015",
    "sg:province":"Padova",
    "sg:website":"http://www.angelogabrielli.it",
    "wof:name":"Angelo Gabrielli & C. Srl",
    "wof:placetype":"venue"
},
  "geometry": {"coordinates":[11.8180789948,45.6675453186],"type":"Point"}
}