{
  "type": "Feature",
  "properties": {
    "iso:country":"IT",
    "sg:address":"50, Via Gandhi 41100 Modena",
    "sg:city":"Modena",
    "sg:classifiers":[
        {
            "category":"Professional",
            "subcategory":"Engineering",
            "type":"Services"
        }
    ],
    "sg:phone":"+39 39059251009",
    "sg:postcode":"41100",
    "sg:province":"Modena",
    "sg:tags":[
        "machine",
        "-",
        "mechanical"
    ],
    "wof:name":"Belloi & Romagnoli (s.r.l.)",
    "wof:placetype":"venue"
},
  "geometry": {"coordinates":[10.964553,44.658985],"type":"Point"}
}