{
  "type": "Feature",
  "properties": {
    "addr:full":"13, Via Frinco 14036 Moncalvo Moncalvo Asti 14036",
    "addr:postcode":"14036;14036",
    "addr:street":"Via Frinco",
    "iso:country":"IT",
    "sg:address":"13, Via Frinco 14036 Moncalvo",
    "sg:city":"Moncalvo",
    "sg:classifiers":[
        {
            "category":"Manufacturing",
            "subcategory":"Metals",
            "type":"Manufacturing & Wholesale Goods"
        }
    ],
    "sg:phone":"+39 0141 917573",
    "sg:postcode":"14036",
    "sg:province":"Asti",
    "sg:tags":[
        "processing"
    ],
    "wof:name":"Comes (s.p.a.)",
    "wof:placetype":"venue"
},
  "geometry": {"coordinates":[8.2644090652,45.0541496277],"type":"Point"}
}