{
  "type": "Feature",
  "properties": {
    "iso:country":"IT",
    "sg:address":"24020 Casnigo",
    "sg:city":"Casnigo",
    "sg:orig_category":"Tessuti Arredamento, Tende E Tappeti. Forniture Per Edilizia E Lavori Pubblici",
    "sg:phone":"+39 035 724207",
    "sg:postcode":"24020",
    "sg:province":"Bergamo",
    "sg:website":"http://www.texima.com",
    "wof:name":"Texima Srl",
    "wof:placetype":"venue"
},
  "geometry": {"coordinates":[9.697618,45.708645],"type":"Point"}
}