{
  "type": "Feature",
  "properties": {
    "iso:country":"IT",
    "sg:address":"50, Via Montefortini 59015 Carmignano",
    "sg:city":"Carmignano",
    "sg:classifiers":[
        {
            "category":"Shopping",
            "subcategory":"Clothing, Apparel, & Fashions",
            "type":"Retail Goods"
        }
    ],
    "sg:phone":"+39 390 558 7441",
    "sg:postcode":"59015",
    "sg:province":"Prato",
    "sg:tags":[
        "clothes"
    ],
    "wof:name":"Franco Rossi Srl",
    "wof:placetype":"venue"
},
  "geometry": {"coordinates":[11.071518,43.791569],"type":"Point"}
}