{
  "type": "Feature",
  "properties": {
    "iso:country":"IT",
    "sg:address":"20056 Grezzago",
    "sg:city":"Grezzago",
    "sg:orig_category":"Cartotecnica E Servizi. Prodotti E Manufatti In Materie Plastiche. Articoli Per Imballaggio E Confezionamento",
    "sg:phone":"+39 02 9096 8585",
    "sg:postcode":"20056",
    "sg:province":"Milano",
    "wof:name":"Mamor (s.p.a.)",
    "wof:placetype":"venue"
},
  "geometry": {"coordinates":[9.207017,45.455441],"type":"Point"}
}