{
  "type": "Feature",
  "properties": {
    "iso:country":"IT",
    "sg:address":"16, Via Lago Di Bracciano 36015 Schio",
    "sg:city":"Schio",
    "sg:classifiers":[
        {
            "category":"Professional",
            "subcategory":"Engineering",
            "type":"Services"
        }
    ],
    "sg:phone":"+39 0445 576596",
    "sg:postcode":"36015",
    "sg:province":"Vicenza",
    "sg:tags":[
        "machine",
        "-",
        "mechanical"
    ],
    "wof:name":"G.f.p.meccanica Snc",
    "wof:placetype":"venue"
},
  "geometry": {"coordinates":[11.414253,45.715431],"type":"Point"}
}