{
  "type": "Feature",
  "properties": {
    "iso:country":"IT",
    "sg:address":"2, V. Delle Ferriere 25068 Sarezzo",
    "sg:city":"Sarezzo",
    "sg:classifiers":[
        {
            "category":"Shopping",
            "type":"Retail Goods"
        }
    ],
    "sg:phone":"+39 030 890 1108",
    "sg:postcode":"25068",
    "sg:province":"Brescia",
    "sg:tags":[
        "finished",
        "-",
        "metallic"
    ],
    "sg:website":"http://www.bossvalves.it",
    "wof:name":"Bossini Bortolo Srl",
    "wof:placetype":"venue"
},
  "geometry": {"coordinates":[10.2032394409,45.647769928],"type":"Point"}
}