{
  "type": "Feature",
  "properties": {
    "iso:country":"IT",
    "sg:address":"00044 Frascati",
    "sg:city":"Frascati",
    "sg:orig_category":"Servizi Di Magazzinaggio E Movimentazione",
    "sg:phone":"+39 06 946 4160",
    "sg:postcode":"00044",
    "sg:province":"Roma",
    "wof:name":"Mag-di Srl",
    "wof:placetype":"venue"
},
  "geometry": {"coordinates":[12.657987,41.837254],"type":"Point"}
}