{
  "type": "Feature",
  "properties": {
    "addr:full":"60020 Agugliano Agugliano Ancona 60020",
    "addr:postcode":"60020;60020",
    "iso:country":"IT",
    "sg:address":"60020 Agugliano",
    "sg:city":"Agugliano",
    "sg:orig_category":"Trattamenti Termici E Superficiali Metalli, Galvanotecnica",
    "sg:phone":"+39 071 907885",
    "sg:postcode":"60020",
    "sg:province":"Ancona",
    "wof:name":"C.p. Snc Di Canali & Paoletti",
    "wof:placetype":"venue"
},
  "geometry": {"coordinates":[13.388291,43.546978],"type":"Point"}
}