{
  "type": "Feature",
  "properties": {
    "addr:full":"16162 Genova Genova Genova 16162",
    "addr:postcode":"16162;16162",
    "iso:country":"IT",
    "sg:address":"16162 Genova",
    "sg:city":"Genova",
    "sg:orig_category":"Macchine Ed Impianti Per Edilizia E Lavori Pubblici. Forniture Per Edilizia E Lavori Pubblici",
    "sg:phone":"+39 010 717 0070",
    "sg:postcode":"16162",
    "sg:province":"Genova",
    "wof:name":"Nova Ponteggi Srl",
    "wof:placetype":"venue"
},
  "geometry": {"coordinates":[8.913922,44.474525],"type":"Point"}
}