{
  "type": "Feature",
  "properties": {
    "iso:country":"IT",
    "sg:address":"01015 Sutri",
    "sg:city":"Sutri",
    "sg:orig_category":"Associazioni E Federazioni Sportive",
    "sg:phone":"+39 0761 600871",
    "sg:postcode":"01015",
    "sg:province":"Viterbo",
    "wof:name":"Sporting Center Colle Diana",
    "wof:placetype":"venue"
},
  "geometry": {"coordinates":[12.214389,42.262352],"type":"Point"}
}