{
  "type": "Feature",
  "properties": {
    "addr:full":"50125 Firenze Firenze Firenze 50125",
    "addr:postcode":"50125;50125",
    "iso:country":"IT",
    "sg:address":"50125 Firenze",
    "sg:city":"Firenze",
    "sg:orig_category":"Pizzerie",
    "sg:phone":"+39 055 210437",
    "sg:postcode":"50125",
    "sg:province":"Firenze",
    "wof:name":"Bebi Di Gargelli A. E Gozzi Snc",
    "wof:placetype":"venue"
},
  "geometry": {"coordinates":[11.2580471039,43.7437095642],"type":"Point"}
}