{
  "type": "Feature",
  "properties": {
    "iso:country":"IT",
    "sg:address":"20135 Milano",
    "sg:city":"Milano",
    "sg:orig_category":"Agenzie D'affari E Servizi Commerciali",
    "sg:phone":"+39 02 551 0123",
    "sg:postcode":"20135",
    "sg:province":"Milano",
    "wof:name":"Rotunno Snc Di Rotunno Franco E Maurizio",
    "wof:placetype":"venue"
},
  "geometry": {"coordinates":[9.213831,45.458412],"type":"Point"}
}