{
  "type": "Feature",
  "properties": {
    "iso:country":"IT",
    "sg:address":"Via Dei Tornabuoni 17 50123 Firenze",
    "sg:city":"Firenze",
    "sg:orig_category":"Ladies' Shoes",
    "sg:phone":"+39 055 215844",
    "sg:postcode":"50123",
    "sg:province":"Firenze",
    "wof:name":"Asap Ltd Import-export Spa",
    "wof:placetype":"venue"
},
  "geometry": {"coordinates":[11.256902,43.768734],"type":"Point"}
}