{
  "type": "Feature",
  "properties": {
    "iso:country":"IT",
    "sg:address":"22010 Gera Lario",
    "sg:city":"Gera Lario",
    "sg:orig_category":"Scuole E Servizi Scolastici. Servizi Per Lo Sport E Il Tempo Libero",
    "sg:phone":"+39 0344 94062",
    "sg:postcode":"22010",
    "sg:province":"Como",
    "wof:name":"Tabo Surf Center",
    "wof:placetype":"venue"
},
  "geometry": {"coordinates":[9.368759,46.172054],"type":"Point"}
}