{
  "type": "Feature",
  "properties": {
    "iso:country":"IT",
    "sg:address":"41, V. De Gasperi 74017 Mottola",
    "sg:city":"Mottola",
    "sg:classifiers":[
        {
            "category":"Food & Beverages",
            "subcategory":"Groceries & Convenience Stores",
            "type":"Retail Goods"
        }
    ],
    "sg:phone":"+39 099 886 3722",
    "sg:postcode":"74017",
    "sg:province":"Taranto",
    "sg:tags":[
        "product",
        "related"
    ],
    "sg:website":"http://www.paginegialle.it/intinipastificio",
    "wof:name":"Intini Pastificio Snc",
    "wof:placetype":"venue"
},
  "geometry": {"coordinates":[17.2400093079,40.4692382812],"type":"Point"}
}