{
  "type": "Feature",
  "properties": {
    "iso:country":"IT",
    "sg:address":"221, Via Fanelli Giuseppe 70125 Bari",
    "sg:city":"Bari",
    "sg:classifiers":[
        {
            "category":"Utilities",
            "subcategory":"Telephone",
            "type":"Services"
        }
    ],
    "sg:phone":"+39 080 502 6544",
    "sg:postcode":"70125",
    "sg:province":"Bari",
    "sg:tags":[
        "telecommunication"
    ],
    "wof:name":"Infotelecom Bari S.r.l.",
    "wof:placetype":"venue"
},
  "geometry": {"coordinates":[16.88616,41.080578],"type":"Point"}
}