{
  "type": "Feature",
  "properties": {
    "addr:full":"Piazza Degli Affari 6, 20123 Milan, Mi Milano 20123",
    "addr:housenumber":"6",
    "addr:postcode":"20123;20123",
    "addr:street":"Piazza Degli Affari",
    "iso:country":"IT",
    "sg:address":"Piazza Degli Affari 6, 20123 Milan, Mi",
    "sg:classifiers":[
        {
            "category":"Banks & Credit Unions",
            "subcategory":"Bank",
            "type":"Services"
        }
    ],
    "sg:phone":"+39 02 7242 6207",
    "sg:postcode":"20123",
    "sg:province":"Milano",
    "sg:website":"http://www.borsaitalia.it",
    "wof:name":"Borsa Italiana Spa",
    "wof:placetype":"venue"
},
  "geometry": {"coordinates":[9.183251,45.464928],"type":"Point"}
}