{
  "type": "Feature",
  "properties": {
    "addr:full":"63018 Porto Sant'elpidio Ascoli Piceno 63018",
    "addr:housenumber":"63018",
    "addr:postcode":"63018",
    "iso:country":"IT",
    "sg:address":"63018 Porto Sant'elpidio",
    "sg:orig_category":"Forniture Per Abbigliamento E Pelletterie",
    "sg:phone":"+39 0734 993646",
    "sg:postcode":"63018",
    "sg:province":"Ascoli Piceno",
    "wof:name":"Ligmar Gomma Srl",
    "wof:placetype":"venue"
},
  "geometry": {"coordinates":[13.7395429611,43.2879943848],"type":"Point"}
}