{
  "type": "Feature",
  "properties": {
    "addr:full":"18, Via Germonio Anastasio 10095 Grugliasco Grugliasco Torino 10095",
    "addr:postcode":"10095;10095",
    "addr:street":"Via Germonio Anastasio",
    "iso:country":"IT",
    "sg:address":"18, Via Germonio Anastasio 10095 Grugliasco",
    "sg:city":"Grugliasco",
    "sg:classifiers":[
        {
            "category":"Shopping",
            "type":"Retail Goods"
        }
    ],
    "sg:phone":"+39 011 707 3120",
    "sg:postcode":"10095",
    "sg:province":"Torino",
    "sg:tags":[
        "finished",
        "-",
        "metallic"
    ],
    "wof:name":"Prisma (s.r.l.)",
    "wof:placetype":"venue"
},
  "geometry": {"coordinates":[7.6112966537,45.069896698],"type":"Point"}
}