{
  "type": "Feature",
  "properties": {
    "addr:full":"00189 Roma Roma Roma 00189",
    "addr:postcode":"00189;00189",
    "iso:country":"IT",
    "sg:address":"00189 Roma",
    "sg:city":"Roma",
    "sg:classifiers":[
        {
            "category":"Retail",
            "subcategory":"Animal Services",
            "type":"Services"
        }
    ],
    "sg:phone":"+39 06 3089 2821",
    "sg:postcode":"00189",
    "sg:province":"Roma",
    "sg:tags":[
        "animals",
        "livestock",
        "leisure",
        "fishing",
        "small",
        "breeding",
        "sport"
    ],
    "sg:website":"http://www.teamhorses.com",
    "wof:name":"Te.am. Horses",
    "wof:placetype":"venue"
},
  "geometry": {"coordinates":[12.44055,41.974659],"type":"Point"}
}