{
  "type": "Feature",
  "properties": {
    "addr:full":"25020 Dello Dello Brescia 25020",
    "addr:postcode":"25020;25020",
    "iso:country":"IT",
    "sg:address":"25020 Dello",
    "sg:city":"Dello",
    "sg:orig_category":"Prodotti Chimici Di Base",
    "sg:phone":"+39 030 977 1066",
    "sg:postcode":"25020",
    "sg:province":"Brescia",
    "wof:name":"Kemper Srl",
    "wof:placetype":"venue"
},
  "geometry": {"coordinates":[10.289141655,45.4006233215],"type":"Point"}
}