{
  "type": "Feature",
  "properties": {
    "iso:country":"IT",
    "sg:address":"17100 Savona",
    "sg:city":"Savona",
    "sg:orig_category":"Carta, Cartone E Prodotti Primari. Forniture E Materiali Per Imballaggio E Confezionamento",
    "sg:phone":"+39 019 850453",
    "sg:postcode":"17100",
    "sg:province":"Savona",
    "wof:name":"Bolla Angelo (s.a.s.)",
    "wof:placetype":"venue"
},
  "geometry": {"coordinates":[7.779292,44.641384],"type":"Point"}
}