{
  "type": "Feature",
  "properties": {
    "addr:full":"10125 Torino Torino Torino 10125",
    "addr:postcode":"10125;10125",
    "iso:country":"IT",
    "sg:address":"10125 Torino",
    "sg:city":"Torino",
    "sg:orig_category":"Biliardi Ed Accessori",
    "sg:phone":"+39 011 655538",
    "sg:postcode":"10125",
    "sg:province":"Torino",
    "wof:name":"Bianco Ezio",
    "wof:placetype":"venue"
},
  "geometry": {"coordinates":[7.679117,45.059277],"type":"Point"}
}