{
  "type": "Feature",
  "properties": {
    "iso:country":"IT",
    "sg:address":"Via Vescovado, 28/32; Potenza; 85100",
    "sg:city":"Potenza",
    "sg:classifiers":[
        {
            "category":"Banks & Credit Unions",
            "subcategory":"Bank",
            "type":"Services"
        }
    ],
    "sg:phone":"+39 0971 25446",
    "sg:postcode":"85100",
    "sg:province":"Potenza",
    "wof:name":"Banca Popolare Del Materano",
    "wof:placetype":"venue"
},
  "geometry": {"coordinates":[15.807402,40.640564],"type":"Point"}
}