{
  "type": "Feature",
  "properties": {
    "iso:country":"IT",
    "sg:address":"44, Via Garibaldi Giuseppe 20047 Brugherio",
    "sg:city":"Brugherio",
    "sg:classifiers":[
        {
            "category":"Shopping",
            "type":"Retail Goods"
        }
    ],
    "sg:phone":"+39 039 287 2888",
    "sg:postcode":"20047",
    "sg:province":"Milano",
    "sg:tags":[
        "finished",
        "-",
        "metallic"
    ],
    "wof:name":"Sib Italia Srl",
    "wof:placetype":"venue"
},
  "geometry": {"coordinates":[9.2939100266,45.5442047119],"type":"Point"}
}