{
  "type": "Feature",
  "properties": {
    "iso:country":"IT",
    "sg:address":"Via Roma 12; Montecchio Maggiore; 36075",
    "sg:city":"Montecchio Maggiore",
    "sg:classifiers":[
        {
            "category":"Banks & Credit Unions",
            "subcategory":"Bank",
            "type":"Services"
        }
    ],
    "sg:phone":"+39 0444 706111",
    "sg:postcode":"36075",
    "sg:province":"Vicenza",
    "wof:name":"Cariverona Banca Spa",
    "wof:placetype":"venue"
},
  "geometry": {"coordinates":[11.407556,45.505714],"type":"Point"}
}