{
  "type": "Feature",
  "properties": {
    "iso:country":"IT",
    "sg:address":"Via Dei Boschi 2 33040 Pradamano",
    "sg:city":"Pradamano",
    "sg:classifiers":[
        {
            "category":"Shopping",
            "subcategory":"Stationery & Office Supplies",
            "type":"Retail Goods"
        }
    ],
    "sg:phone":"+39 0432 671758",
    "sg:postcode":"33040",
    "sg:province":"Udine",
    "sg:tags":[
        "uninterruptible",
        "unit",
        "ups",
        "power"
    ],
    "sg:website":"www.microdowell.com",
    "wof:name":"Micro Dowell Spa",
    "wof:placetype":"venue"
},
  "geometry": {"coordinates":[13.288265,46.021519],"type":"Point"}
}