{
  "type": "Feature",
  "properties": {
    "iso:country":"IT",
    "sg:address":"Via Vittorio Emanuele Ii 76/2 35018 San Martino Di Lupari",
    "sg:city":"San Martino di Lupari",
    "sg:classifiers":[
        {
            "category":"Wholesale",
            "subcategory":"Home Furnishings",
            "type":"Manufacturing & Wholesale Goods"
        }
    ],
    "sg:phone":"+39 049 946 9216",
    "sg:postcode":"35018",
    "sg:province":"Padova",
    "sg:tags":[
        "accessory"
    ],
    "sg:website":"www.luparense.com",
    "wof:name":"Luparense Srl",
    "wof:placetype":"venue"
},
  "geometry": {"coordinates":[11.85964,45.654896],"type":"Point"}
}