{
  "type": "Feature",
  "properties": {
    "addr:full":"38100 Madonna Di Campiglio Trento 38100",
    "addr:postcode":"38100;38100",
    "iso:country":"IT",
    "sg:address":"38100 Madonna Di Campiglio",
    "sg:orig_category":"Funivie, Sciovie E Impianti Di Risalita - Societa' Di Esercizio",
    "sg:phone":"+39 0465 447744",
    "sg:postcode":"38100",
    "sg:province":"Trento",
    "sg:website":"http://www.funiviecampiglio.it",
    "wof:name":"Funivie M. Di Campiglio",
    "wof:placetype":"venue"
},
  "geometry": {"coordinates":[10.8261785507,46.2300643921],"type":"Point"}
}