{
  "type": "Feature",
  "properties": {
    "iso:country":"IT",
    "sg:address":"38068 Rovereto",
    "sg:city":"Rovereto",
    "sg:orig_category":"Ospedali E Servizi Sanitari. Servizi Ausiliari Di Analisi, Controllo E Ricerca",
    "sg:phone":"+39 0464 432935",
    "sg:postcode":"38068",
    "sg:province":"Trento",
    "wof:name":"Bonini Alessia",
    "wof:placetype":"venue"
},
  "geometry": {"coordinates":[11.041907,45.890697],"type":"Point"}
}