{
  "type": "Feature",
  "properties": {
    "iso:country":"IT",
    "sg:address":"50018 Scandicci",
    "sg:city":"Scandicci",
    "sg:orig_category":"Impianti, Attrezzature E Forniture Sanitarie Ed Ospedaliere",
    "sg:phone":"+39 055 731 0793",
    "sg:postcode":"50018",
    "sg:province":"Firenze",
    "wof:name":"Emmegi Biomedica S.r.l.",
    "wof:placetype":"venue"
},
  "geometry": {"coordinates":[11.180352,43.764431],"type":"Point"}
}