{
  "type": "Feature",
  "properties": {
    "iso:country":"IT",
    "sg:address":"3, Via Delle Fonti 50018 Scandicci",
    "sg:city":"Scandicci",
    "sg:orig_category":"Miscellaneous Products",
    "sg:phone":"+39 39055722861",
    "sg:postcode":"50018",
    "sg:province":"Firenze",
    "wof:name":"Sunrise Srl",
    "wof:placetype":"venue"
},
  "geometry": {"coordinates":[11.1464014053,43.7588043213],"type":"Point"}
}