{
  "type": "Feature",
  "properties": {
    "iso:country":"IT",
    "sg:address":"87064 Corigliano Calabro",
    "sg:city":"Corigliano Calabro",
    "sg:orig_category":"Agrumi",
    "sg:phone":"+39 0983 80740",
    "sg:postcode":"87064",
    "sg:province":"Cosenza",
    "wof:name":"Coab Soc.coop.r.l.",
    "wof:placetype":"venue"
},
  "geometry": {"coordinates":[16.511271,39.627613],"type":"Point"}
}