{
  "type": "Feature",
  "properties": {
    "addr:full":"Via Roma 90/b 25049 Iseo Iseo Brescia 25049",
    "addr:housenumber":"90 / b",
    "addr:postcode":"25049;25049",
    "addr:street":"Via Roma",
    "iso:country":"IT",
    "sg:address":"Via Roma 90/b 25049 Iseo",
    "sg:city":"Iseo",
    "sg:classifiers":[
        {
            "category":"Utilities",
            "subcategory":"Cable",
            "type":"Services"
        }
    ],
    "sg:phone":"+39 030 980484",
    "sg:postcode":"25049",
    "sg:province":"Brescia",
    "sg:tags":[
        "resistant",
        "cables",
        "high-temperature"
    ],
    "sg:website":"www.caviterm.com",
    "wof:name":"Caviterm Srl",
    "wof:placetype":"venue"
},
  "geometry": {"coordinates":[10.222958,45.539829],"type":"Point"}
}