{
  "type": "Feature",
  "properties": {
    "iso:country":"IT",
    "sg:address":"11, Via Canonico Coupers 52036 Pieve Santo Stefano",
    "sg:city":"Pieve Santo Stefano",
    "sg:classifiers":[
        {
            "category":"Shopping",
            "subcategory":"Clothing, Apparel, & Fashions",
            "type":"Retail Goods"
        }
    ],
    "sg:phone":"+39 0575 798072",
    "sg:postcode":"52036",
    "sg:province":"Arezzo",
    "sg:tags":[
        "clothes"
    ],
    "wof:name":"Ci Gi Srl Unipersonale",
    "wof:placetype":"venue"
},
  "geometry": {"coordinates":[12.044849,43.666538],"type":"Point"}
}