{
  "type": "Feature",
  "properties": {
    "iso:country":"IT",
    "sg:address":"84086 Roccapiemonte",
    "sg:city":"Roccapiemonte",
    "sg:orig_category":"Agenzie Immobiliari",
    "sg:phone":"+39 081 514 4826",
    "sg:postcode":"84086",
    "sg:province":"Salerno",
    "wof:name":"Agenzia Di Servizi C.i.s. Sas Di Romano Piazzetta & C.",
    "wof:placetype":"venue"
},
  "geometry": {"coordinates":[14.689991,40.761929],"type":"Point"}
}