{
  "type": "Feature",
  "properties": {
    "iso:country":"IT",
    "sg:address":"12, V. Dell'industria 42019 Scandiano",
    "sg:classifiers":[
        {
            "category":"Wholesale",
            "subcategory":"Drugs",
            "type":"Manufacturing & Wholesale Goods"
        }
    ],
    "sg:phone":"+39 0522 854473",
    "sg:postcode":"42019",
    "sg:province":"Reggio Nell'Emilia",
    "sg:tags":[
        "chemical",
        "pharmaceutical"
    ],
    "sg:website":"http://www.raster.it/sear:ws_end: :mark:ws:http://www.paginegialle.it/sear-01",
    "wof:name":"S.e.a.r. Snc",
    "wof:placetype":"venue"
},
  "geometry": {"coordinates":[10.674072,44.623127],"type":"Point"}
}