{
  "type": "Feature",
  "properties": {
    "iso:country":"IT",
    "sg:address":"00197 Roma",
    "sg:city":"Roma",
    "sg:orig_category":"Arte Ed Artigianato Artistico. Scuole E Servizi Scolastici. Servizi Ausiliari Di Analisi, Controllo E Ricerca",
    "sg:phone":"+39 06 320 1407",
    "sg:postcode":"00197",
    "sg:province":"Roma",
    "wof:name":"Accademia Del Belgio",
    "wof:placetype":"venue"
},
  "geometry": {"coordinates":[12.479274,41.916595],"type":"Point"}
}