{
  "type": "Feature",
  "properties": {
    "addr:full":"22036 Erba Erba Como 22036",
    "addr:postcode":"22036;22036",
    "iso:country":"IT",
    "sg:address":"22036 Erba",
    "sg:city":"Erba",
    "sg:orig_category":"Materiali Edili",
    "sg:phone":"+39 031 645735",
    "sg:postcode":"22036",
    "sg:province":"Como",
    "wof:name":"Grippi Anna & C. Snc",
    "wof:placetype":"venue"
},
  "geometry": {"coordinates":[9.244796,45.806591],"type":"Point"}
}