{
  "type": "Feature",
  "properties": {
    "iso:country":"IT",
    "sg:address":"65124 Pescara",
    "sg:city":"Pescara",
    "sg:orig_category":"Serramenti Ed Infissi. Prodotti Vari In Metallo",
    "sg:phone":"+39 085 471 0808",
    "sg:postcode":"65124",
    "sg:province":"Pescara",
    "wof:name":"Le Porte... E Non Solo",
    "wof:placetype":"venue"
},
  "geometry": {"coordinates":[14.196523,42.476696],"type":"Point"}
}