{
  "type": "Feature",
  "properties": {
    "addr:full":"90145 Palermo Palermo Palermo 90145",
    "addr:postcode":"90145;90145",
    "iso:country":"IT",
    "sg:address":"90145 Palermo",
    "sg:city":"Palermo",
    "sg:orig_category":"Servizi Culturali E Per Lo Spettacolo. Servizi Per Lo Sport E Il Tempo Libero. Servizi Per Aziende, Manifestazioni E Supporto Agli Scambi Commerciali",
    "sg:phone":"+39 091 405279",
    "sg:postcode":"90145",
    "sg:province":"Palermo",
    "wof:name":"La G.d.d. Eventi & Servizi Snc",
    "wof:placetype":"venue"
},
  "geometry": {"coordinates":[13.327569,38.125053],"type":"Point"}
}