{
  "type": "Feature",
  "properties": {
    "addr:full":"20091 Bresso Bresso Milano 20091",
    "addr:postcode":"20091;20091",
    "iso:country":"IT",
    "sg:address":"20091 Bresso",
    "sg:city":"Bresso",
    "sg:orig_category":"Macchine E Forniture Per Ecologia E Smaltimento Rifiuti. Elettrodomestici. Forniture Alle Strutture Ricettive. Macchine, Strumenti Ed Apparecchi Per Attivita' Industriali",
    "sg:phone":"+39 02 610 4877",
    "sg:postcode":"20091",
    "sg:province":"Milano",
    "wof:name":"Fo.p.a.c. Di Pellacani Fabio",
    "wof:placetype":"venue"
},
  "geometry": {"coordinates":[9.18452,45.53957],"type":"Point"}
}