{
  "type": "Feature",
  "properties": {
    "addr:full":"15011 Acqui Terme Acqui Terme Alessandria 15011",
    "addr:postcode":"15011;15011",
    "iso:country":"IT",
    "sg:address":"15011 Acqui Terme",
    "sg:city":"Acqui Terme",
    "sg:orig_category":"Petroli, Gas E Combustibili",
    "sg:phone":"+39 0144 594268",
    "sg:postcode":"15011",
    "sg:province":"Alessandria",
    "wof:name":"Restiani Spa",
    "wof:placetype":"venue"
},
  "geometry": {"coordinates":[8.4732713699,44.6762619019],"type":"Point"}
}