{
  "type": "Feature",
  "properties": {
    "iso:country":"IT",
    "sg:address":"20149 Milano",
    "sg:city":"Milano",
    "sg:orig_category":"Servizi Per Aziende, Manifestazioni E Supporto Agli Scambi Commerciali. Ambasciate Ed Enti Internazionali",
    "sg:phone":"+39 02 4800 8812",
    "sg:postcode":"20149",
    "sg:province":"Milano",
    "wof:name":"Sportland S.r.l.",
    "wof:placetype":"venue"
},
  "geometry": {"coordinates":[9.15024,45.472336],"type":"Point"}
}