{
  "type": "Feature",
  "properties": {
    "iso:country":"IT",
    "sg:address":"10, Via Alighieri Dante 50055 Lastra A Signa",
    "sg:city":"Lastra a Signa",
    "sg:classifiers":[
        {
            "category":"Personal",
            "subcategory":"Shoe Repair & Shine",
            "type":"Services"
        }
    ],
    "sg:phone":"+39 055 872 0151",
    "sg:postcode":"50055",
    "sg:province":"Firenze",
    "sg:tags":[
        "leather"
    ],
    "wof:name":"Rodo Firenze (s.r.l.)",
    "wof:placetype":"venue"
},
  "geometry": {"coordinates":[11.256902,43.768734],"type":"Point"}
}