{
  "type": "Feature",
  "properties": {
    "addr:full":"22070 Casnate Con Bernate Casnate Como 22070",
    "addr:postcode":"22070;22070",
    "addr:street":"Con Bernate Casnate",
    "iso:country":"IT",
    "sg:address":"22070 Casnate Con Bernate",
    "sg:city":"Casnate",
    "sg:orig_category":"Trasporti Internazionali",
    "sg:phone":"+39 031 564105",
    "sg:postcode":"22070",
    "sg:province":"Como",
    "wof:name":"C.d. Transport Srl",
    "wof:placetype":"venue"
},
  "geometry": {"coordinates":[9.082871,45.760681],"type":"Point"}
}