{
  "type": "Feature",
  "properties": {
    "addr:full":"30038 Spinea Spinea Venezia 30038",
    "addr:postcode":"30038;30038",
    "iso:country":"IT",
    "sg:address":"30038 Spinea",
    "sg:city":"Spinea",
    "sg:orig_category":"Ospedali E Servizi Sanitari",
    "sg:phone":"+39 041 994833",
    "sg:postcode":"30038",
    "sg:province":"Venezia",
    "wof:name":"Centro Clinico Chimico Srl",
    "wof:placetype":"venue"
},
  "geometry": {"coordinates":[12.165243,45.489773],"type":"Point"}
}