{
  "type": "Feature",
  "properties": {
    "iso:country":"IT",
    "sg:address":"72023 Mesagne",
    "sg:city":"Mesagne",
    "sg:orig_category":"Avvolgimenti Elettrici",
    "sg:phone":"+39 0831 771050",
    "sg:postcode":"72023",
    "sg:province":"Brindisi",
    "wof:name":"D'ancona Srl",
    "wof:placetype":"venue"
},
  "geometry": {"coordinates":[17.78731,40.548409],"type":"Point"}
}