{
  "type": "Feature",
  "properties": {
    "iso:country":"IT",
    "sg:address":"28010 Pella",
    "sg:city":"Alzo",
    "sg:classifiers":[
        {
            "category":"Wholesale",
            "subcategory":"Machinery & Supplies",
            "type":"Manufacturing & Wholesale Goods"
        }
    ],
    "sg:phone":"+39 0322 969241",
    "sg:postcode":"28010",
    "sg:province":"Novara",
    "sg:tags":[
        "equipment",
        "mechanical"
    ],
    "wof:name":"Gattoni Rubinetteria Spa",
    "wof:placetype":"venue"
},
  "geometry": {"coordinates":[8.378692,45.795265],"type":"Point"}
}