{
  "type": "Feature",
  "properties": {
    "iso:country":"IT",
    "sg:address":"65015 Montesilvano",
    "sg:city":"Montesilvano",
    "sg:orig_category":"Telecomunicazioni E Telefonia, Impianti, Apparecchi E Servizi",
    "sg:phone":"+39 085 445 0701",
    "sg:postcode":"65015",
    "sg:province":"Pescara",
    "wof:name":"Europhone Telefonia",
    "wof:placetype":"venue"
},
  "geometry": {"coordinates":[14.161299,42.507133],"type":"Point"}
}