{
  "type": "Feature",
  "properties": {
    "addr:full":"1/2, V. Delle Industrie - Z.i. 33070 Polcenigo Polcenigo Pordenone 33070",
    "addr:housenumber":"1 / 2 v.",
    "addr:postcode":"33070;33070",
    "addr:street":"Delle Industrie",
    "iso:country":"IT",
    "sg:address":"1/2, V. Delle Industrie - Z.i. 33070 Polcenigo",
    "sg:city":"Polcenigo",
    "sg:classifiers":[
        {
            "category":"Real Estate",
            "subcategory":"Surveying",
            "type":"Services"
        }
    ],
    "sg:phone":"+39 0434 749404",
    "sg:postcode":"33070",
    "sg:province":"Pordenone",
    "sg:tags":[
        "equipment",
        "material",
        "good",
        "-",
        "handling"
    ],
    "sg:website":"http://www.paginegialle.it/impiantiindustrialisrl",
    "wof:name":"Impianti Industriali Srl",
    "wof:placetype":"venue"
},
  "geometry": {"coordinates":[12.655044,45.96265],"type":"Point"}
}