{
  "type": "Feature",
  "properties": {
    "iso:country":"IT",
    "sg:address":"72, Via Europa 29021 Bettola",
    "sg:city":"Bettola",
    "sg:classifiers":[
        {
            "category":"Shopping",
            "subcategory":"Clothing, Apparel, & Fashions",
            "type":"Retail Goods"
        }
    ],
    "sg:phone":"+39 0523 917753",
    "sg:postcode":"29021",
    "sg:province":"Piacenza",
    "sg:tags":[
        "clothes"
    ],
    "wof:name":"Missauga (s.a.s.)",
    "wof:placetype":"venue"
},
  "geometry": {"coordinates":[9.609223,44.777924],"type":"Point"}
}