{
  "type": "Feature",
  "properties": {
    "iso:country":"IT",
    "sg:address":"10, Via Delle Tuberose 20146 Milano",
    "sg:city":"Milano",
    "sg:classifiers":[
        {
            "category":"Shopping",
            "subcategory":"Stationery & Office Supplies",
            "type":"Retail Goods"
        }
    ],
    "sg:phone":"+39 02 4830 4735",
    "sg:postcode":"20146",
    "sg:province":"Milano",
    "sg:tags":[
        "professional"
    ],
    "wof:name":"Priolinox S.p.a.",
    "wof:placetype":"venue"
},
  "geometry": {"coordinates":[9.1366453171,45.45860672],"type":"Point"}
}