{
  "type": "Feature",
  "properties": {
    "iso:country":"IT",
    "sg:address":"204, Via Varesina 20156 Milano",
    "sg:city":"Milano",
    "sg:classifiers":[
        {
            "category":"Manufacturing",
            "subcategory":"Metals",
            "type":"Manufacturing & Wholesale Goods"
        }
    ],
    "sg:phone":"+39 39023024161",
    "sg:postcode":"20156",
    "sg:province":"Milano",
    "sg:tags":[
        "metallurgy",
        "metalworking"
    ],
    "wof:name":"Bahco Italia Spa",
    "wof:placetype":"venue"
},
  "geometry": {"coordinates":[9.1481275558,45.4948272705],"type":"Point"}
}