{
  "type": "Feature",
  "properties": {
    "iso:country":"IT",
    "sg:address":"40125 Bologna",
    "sg:city":"Bologna",
    "sg:orig_category":"Servizi Culturali E Per Lo Spettacolo. Arte Ed Artigianato Artistico. Servizi Al Turismo",
    "sg:phone":"+39 051 237652",
    "sg:postcode":"40125",
    "sg:province":"Bologna",
    "wof:name":"Nanni Dr. Paolo",
    "wof:placetype":"venue"
},
  "geometry": {"coordinates":[11.353748,44.486675],"type":"Point"}
}