{
  "type": "Feature",
  "properties": {
    "iso:country":"IT",
    "sg:address":"Via Don A. Pedrinelli 118 24030 Carvico",
    "sg:city":"Carvico",
    "sg:classifiers":[
        {
            "category":"Home & Garden",
            "subcategory":"Building Materials",
            "type":"Retail Goods"
        }
    ],
    "sg:phone":"+39 035 438 3311",
    "sg:postcode":"24030",
    "sg:province":"Bergamo",
    "sg:tags":[
        "prefabricated"
    ],
    "sg:website":"www.magnetti.it",
    "wof:name":"Larco Astori Spa",
    "wof:placetype":"venue"
},
  "geometry": {"coordinates":[9.6699523926,45.6949043274],"type":"Point"}
}