{
  "type": "Feature",
  "properties": {
    "addr:full":"55054 Massarosa Massarosa Lucca 55054",
    "addr:postcode":"55054;55054",
    "iso:country":"IT",
    "sg:address":"55054 Massarosa",
    "sg:city":"Massarosa",
    "sg:orig_category":"Metalli E Leghe",
    "sg:phone":"+39 0584 954791",
    "sg:postcode":"55054",
    "sg:province":"Lucca",
    "wof:name":"Sitec Srl",
    "wof:placetype":"venue"
},
  "geometry": {"coordinates":[10.3161125183,43.8664665222],"type":"Point"}
}