{
  "type": "Feature",
  "properties": {
    "iso:country":"IT",
    "sg:address":"27058 Voghera",
    "sg:city":"Voghera",
    "sg:orig_category":"Metalli E Leghe",
    "sg:phone":"+39 0383 43777",
    "sg:postcode":"27058",
    "sg:province":"Pavia",
    "wof:name":"Rubinetteria - Metalli Silvio Bertolini Di Zoccola Zaira",
    "wof:placetype":"venue"
},
  "geometry": {"coordinates":[9.1633777618,45.1847381592],"type":"Point"}
}