{
  "type": "Feature",
  "properties": {
    "addr:full":"59013 Montemurlo Montemurlo Prato 59013",
    "addr:postcode":"59013;59013",
    "iso:country":"IT",
    "sg:address":"59013 Montemurlo",
    "sg:city":"Montemurlo",
    "sg:classifiers":[
        {
            "category":"Home & Garden",
            "subcategory":"Hardware",
            "type":"Retail Goods"
        }
    ],
    "sg:phone":"+39 0574 683138",
    "sg:postcode":"59013",
    "sg:province":"Prato",
    "sg:tags":[
        "activities",
        "industrial",
        "supply"
    ],
    "wof:name":"Mollificio Toscano Srl",
    "wof:placetype":"venue"
},
  "geometry": {"coordinates":[11.059862,43.928516],"type":"Point"}
}