{
  "type": "Feature",
  "properties": {
    "iso:country":"IT",
    "sg:address":"27058 Voghera",
    "sg:city":"Voghera",
    "sg:orig_category":"Servizi E Lavori Per Edilizia E Lavori Pubblici. Acqua, Luce, Gas E Societa' Di Esercizio Pubblico",
    "sg:phone":"+39 0383 41310",
    "sg:postcode":"27058",
    "sg:province":"Pavia",
    "wof:name":"A.s.m. Voghera Spa",
    "wof:placetype":"venue"
},
  "geometry": {"coordinates":[9.007853,45.00032],"type":"Point"}
}