{
  "type": "Feature",
  "properties": {
    "addr:full":"06039 Bovara Perugia 06039",
    "addr:postcode":"06039;06039",
    "iso:country":"IT",
    "sg:address":"06039 Bovara",
    "sg:orig_category":"Non-classified Establishments",
    "sg:phone":"+39 0742 780038",
    "sg:postcode":"06039",
    "sg:province":"Perugia",
    "wof:name":"Cardinali Scota Adele",
    "wof:placetype":"venue"
},
  "geometry": {"coordinates":[12.74813,42.865482],"type":"Point"}
}