{
  "type": "Feature",
  "properties": {
    "iso:country":"IT",
    "sg:address":"30 Piazza Matteotti Giacomo, 53100 Siena",
    "sg:city":"Siena",
    "sg:classifiers":[
        {
            "category":"Banks & Credit Unions",
            "subcategory":"Financial Services",
            "type":"Services"
        }
    ],
    "sg:phone":"+39 39057748102",
    "sg:postcode":"53100",
    "sg:province":"Siena",
    "sg:tags":[
        "banking",
        "finance",
        "insurance"
    ],
    "wof:name":"Finanziaria Senese Di Sviluppo (spa)",
    "wof:placetype":"venue"
},
  "geometry": {"coordinates":[11.3291730881,43.3216438293],"type":"Point"}
}