{
  "type": "Feature",
  "properties": {
    "addr:full":"10028 Trofarello Trofarello Torino 10028",
    "addr:postcode":"10028;10028",
    "iso:country":"IT",
    "sg:address":"10028 Trofarello",
    "sg:city":"Trofarello",
    "sg:orig_category":"Prodotti E Manufatti In Materie Plastiche",
    "sg:phone":"+39 011 649 7928",
    "sg:postcode":"10028",
    "sg:province":"Torino",
    "wof:name":"Gimac Di Mallamaci & C. (s.n.c.)",
    "wof:placetype":"venue"
},
  "geometry": {"coordinates":[7.7453656197,44.9758605957],"type":"Point"}
}