{
  "type": "Feature",
  "properties": {
    "iso:country":"IT",
    "sg:address":"46019 Viadana",
    "sg:city":"Viadana",
    "sg:orig_category":"Pennelli",
    "sg:phone":"+39 0375 790204",
    "sg:postcode":"46019",
    "sg:province":"Mantova",
    "sg:website":"http://www.pennellicervus.com",
    "wof:name":"Cervus Industria Pennelli Sas",
    "wof:placetype":"venue"
},
  "geometry": {"coordinates":[10.4843330383,44.9419517517],"type":"Point"}
}