{
  "type": "Feature",
  "properties": {
    "iso:country":"IT",
    "sg:address":"21050 Marnate",
    "sg:city":"Marnate",
    "sg:orig_category":"Torrefazione Di Caffe' Ed Affini - Lavorazione E Ingrosso",
    "sg:phone":"+39 0331 600426",
    "sg:postcode":"21050",
    "sg:province":"Varese",
    "sg:website":"http://www.elmundo.it",
    "wof:name":"Nuova El Mundo Srl",
    "wof:placetype":"venue"
},
  "geometry": {"coordinates":[8.905758,45.62838],"type":"Point"}
}