{
  "type": "Feature",
  "properties": {
    "iso:country":"IT",
    "sg:address":"6, Via Piave 80126 Napoli",
    "sg:city":"Napoli",
    "sg:classifiers":[
        {
            "category":"Marine",
            "type":"Transportation"
        }
    ],
    "sg:phone":"+39 081 714 5103",
    "sg:postcode":"80126",
    "sg:province":"Napoli",
    "sg:tags":[
        "transport",
        "sea"
    ],
    "wof:name":"Maglia Sas Di Gennaro Maglia & C",
    "wof:placetype":"venue"
},
  "geometry": {"coordinates":[14.214425,40.838482],"type":"Point"}
}