{
  "type": "Feature",
  "properties": {
    "iso:country":"IT",
    "sg:address":"Viale Trieste 56; Pasturo",
    "sg:classifiers":[
        {
            "category":"Banks & Credit Unions",
            "subcategory":"Bank",
            "type":"Services"
        }
    ],
    "sg:phone":"+39 0341 955198",
    "wof:name":"Credito Valtellinese Scarl",
    "wof:placetype":"venue"
},
  "geometry": {"coordinates":[9.444556,45.951889],"type":"Point"}
}