{
  "type": "Feature",
  "properties": {
    "iso:country":"IT",
    "sg:address":"24034 Cisano Bergamasco",
    "sg:city":"Cisano Bergamasco",
    "sg:classifiers":[
        {
            "category":"Wholesale",
            "subcategory":"Chemicals & Plastics",
            "type":"Manufacturing & Wholesale Goods"
        }
    ],
    "sg:phone":"+39 035 781108",
    "sg:postcode":"24034",
    "sg:province":"Bergamo",
    "sg:tags":[
        "article",
        "product",
        "plastics"
    ],
    "sg:website":"http://www.arcaprofil.com",
    "wof:name":"Arcaprofil Spa",
    "wof:placetype":"venue"
},
  "geometry": {"coordinates":[9.4692850113,45.7446289062],"type":"Point"}
}