{
  "type": "Feature",
  "properties": {
    "iso:country":"IT",
    "sg:address":"31020 San Zenone Degli Ezzelini",
    "sg:city":"San Zenone degli Ezzelini",
    "sg:orig_category":"Termotecnica E Riscaldamento, Apparecchiature E Servizi",
    "sg:phone":"+39 0423 968402",
    "sg:postcode":"31020",
    "sg:province":"Treviso",
    "wof:name":"Nuova Imas (s.r.l.)",
    "wof:placetype":"venue"
},
  "geometry": {"coordinates":[11.836135,45.779217],"type":"Point"}
}