{
  "type": "Feature",
  "properties": {
    "addr:full":"30016 Jesolo Venezia 30016",
    "addr:postcode":"30016;30016",
    "iso:country":"IT",
    "sg:address":"30016 Jesolo",
    "sg:orig_category":"Geometri - Studi",
    "sg:phone":"+39 0421 351047",
    "sg:postcode":"30016",
    "sg:province":"Venezia",
    "wof:name":"Bortoluzzo Geom. Andrea",
    "wof:placetype":"venue"
},
  "geometry": {"coordinates":[12.240273,45.493011],"type":"Point"}
}