{
  "type": "Feature",
  "properties": {
    "addr:full":"Cascina Luna 26866 Marudo Marudo Lodi 26866",
    "addr:postcode":"26866;26866",
    "iso:country":"IT",
    "sg:address":"Cascina Luna 26866 Marudo",
    "sg:city":"Marudo",
    "sg:classifiers":[
        {
            "category":"Farming",
            "subcategory":"Livestock Farm",
            "type":"Manufacturing & Wholesale Goods"
        }
    ],
    "sg:phone":"+39 0371 933148",
    "sg:postcode":"26866",
    "sg:province":"Lodi",
    "sg:tags":[
        "agriculture"
    ],
    "wof:name":"Toninelli Fratelli Sas Di Toninelli Giovanni",
    "wof:placetype":"venue"
},
  "geometry": {"coordinates":[9.371692,45.250408],"type":"Point"}
}