{
  "type": "Feature",
  "properties": {
    "iso:country":"IT",
    "sg:address":"11, Via Arda 29100 Piacenza",
    "sg:city":"Piacenza",
    "sg:classifiers":[
        {
            "category":"Manufacturing",
            "subcategory":"Rubber & Plastics",
            "type":"Manufacturing & Wholesale Goods"
        }
    ],
    "sg:phone":"+39 0523 594400",
    "sg:postcode":"29100",
    "sg:province":"Piacenza",
    "sg:tags":[
        "packaging",
        "material",
        "-"
    ],
    "wof:name":"S.a.f.t.a. (s.p.a.)",
    "wof:placetype":"venue"
},
  "geometry": {"coordinates":[10.1211681366,45.2473983765],"type":"Point"}
}