{
  "type": "Feature",
  "properties": {
    "iso:country":"IT",
    "sg:address":"Via E. Ferrari 5 47853 Coriano",
    "sg:city":"Coriano",
    "sg:classifiers":[
        {
            "category":"Government",
            "subcategory":"Court House",
            "type":"Public Place"
        }
    ],
    "sg:phone":"+39 0541 657382",
    "sg:postcode":"47853",
    "sg:province":"Rimini",
    "sg:tags":[
        "accommodation",
        "furniture"
    ],
    "sg:website":"www.cace.it",
    "wof:name":"Ca.ce. Srl",
    "wof:placetype":"venue"
},
  "geometry": {"coordinates":[12.632522,43.986301],"type":"Point"}
}