{
  "type": "Feature",
  "properties": {
    "iso:country":"IT",
    "sg:address":"00167 Roma",
    "sg:city":"Roma",
    "sg:orig_category":"Valvole E Apparecchiature Di Misura",
    "sg:phone":"+39 06 627 7946",
    "sg:postcode":"00167",
    "sg:province":"Roma",
    "wof:name":"Di Mario Mario",
    "wof:placetype":"venue"
},
  "geometry": {"coordinates":[12.419456,41.90892],"type":"Point"}
}