{
  "type": "Feature",
  "properties": {
    "addr:full":"42017 Novellara Reggio Nell'Emilia 42017",
    "addr:postcode":"42017;42017",
    "iso:country":"IT",
    "sg:address":"42017 Novellara",
    "sg:orig_category":"Automobili E Mezzi Di Trasporto",
    "sg:phone":"+39 0522 653235",
    "sg:postcode":"42017",
    "sg:province":"Reggio Nell'Emilia",
    "wof:name":"Valli Snc Di Valli Viscardo & C.",
    "wof:placetype":"venue"
},
  "geometry": {"coordinates":[10.677962,44.7687],"type":"Point"}
}