{
  "type": "Feature",
  "properties": {
    "iso:country":"IT",
    "sg:address":"Via Modigliani 22 20010 Inveruno",
    "sg:city":"Inveruno",
    "sg:classifiers":[
        {
            "category":"Shopping",
            "subcategory":"Clothing, Apparel, & Fashions",
            "type":"Retail Goods"
        }
    ],
    "sg:phone":"+39 02 9728 9649",
    "sg:postcode":"20010",
    "sg:province":"Milano",
    "sg:tags":[
        "jean"
    ],
    "sg:website":"www.itasrl.it",
    "wof:name":"Ita S.r.l.",
    "wof:placetype":"venue"
},
  "geometry": {"coordinates":[8.836638,45.514118],"type":"Point"}
}