{
  "type": "Feature",
  "properties": {
    "addr:full":"84087 Sarno Sarno Salerno 84087",
    "addr:postcode":"84087;84087",
    "iso:country":"IT",
    "sg:address":"84087 Sarno",
    "sg:city":"Sarno",
    "sg:orig_category":"Scuole E Servizi Scolastici. Centri Di Estetica E Cosmesi E Servizi. Ricerca, Selezione E Formazione Del Personale",
    "sg:phone":"+39 081 944790",
    "sg:postcode":"84087",
    "sg:province":"Salerno",
    "wof:name":"Mancini Arcangelo",
    "wof:placetype":"venue"
},
  "geometry": {"coordinates":[14.599942,40.805676],"type":"Point"}
}