{
  "type": "Feature",
  "properties": {
    "iso:country":"IT",
    "sg:address":"20090 Segrate",
    "sg:city":"Segrate",
    "sg:classifiers":[
        {
            "category":"Sports & Exercise",
            "subcategory":"Tennis Court",
            "type":"Entertainment"
        }
    ],
    "sg:phone":"+39 02 756 0404",
    "sg:postcode":"20090",
    "sg:province":"Milano",
    "sg:tags":[
        "e",
        "lo",
        "tempo",
        "libero",
        "per",
        "impianti",
        "il",
        "attrezzature"
    ],
    "wof:name":"Fiume Rapido (s.r.l.)",
    "wof:placetype":"venue"
},
  "geometry": {"coordinates":[9.291694,45.501144],"type":"Point"}
}