{
  "type": "Feature",
  "properties": {
    "addr:full":"20124 Milano Milano Milano 20124",
    "addr:postcode":"20124;20124",
    "iso:country":"IT",
    "sg:address":"20124 Milano",
    "sg:city":"Milano",
    "sg:orig_category":"Metalli E Leghe. Gioielleria, Oreficeria E Argenteria",
    "sg:phone":"+39 02 668 4290",
    "sg:postcode":"20124",
    "sg:province":"Milano",
    "sg:website":"http://www.battiloro.it",
    "wof:name":"Brambilla Battiloro Srl",
    "wof:placetype":"venue"
},
  "geometry": {"coordinates":[9.1936855316,45.4934768677],"type":"Point"}
}