{
  "type": "Feature",
  "properties": {
    "iso:country":"IT",
    "sg:address":"52100 Arezzo",
    "sg:city":"Arezzo",
    "sg:classifiers":[
        {
            "category":"Government",
            "subcategory":"Office",
            "type":"Public Place"
        }
    ],
    "sg:phone":"+39 0575 3770",
    "sg:postcode":"52100",
    "sg:province":"Arezzo",
    "sg:tags":[
        "administration"
    ],
    "sg:website":"http://www.comune.arezzo.it",
    "wof:name":"Comune Di Arezzo",
    "wof:placetype":"venue"
},
  "geometry": {"coordinates":[11.8819732666,43.4667472839],"type":"Point"}
}