{
  "type": "Feature",
  "properties": {
    "iso:country":"IT",
    "sg:address":"16100 Genova",
    "sg:orig_category":"Frigotecnica, Apparecchiature E Servizi",
    "sg:phone":"+39 010 311131",
    "sg:province":"GE",
    "wof:name":"Manerba C. & Figli S.a.s.",
    "wof:placetype":"venue"
},
  "geometry": {"coordinates":[8.9255619049,44.4482803345],"type":"Point"}
}