{
  "type": "Feature",
  "properties": {
    "iso:country":"IT",
    "sg:address":"Via Fragale 98070 Torrenova",
    "sg:city":"Torrenova",
    "sg:classifiers":[
        {
            "category":"Real Estate",
            "subcategory":"Architect",
            "type":"Services"
        }
    ],
    "sg:phone":"+39 0941 784376",
    "sg:postcode":"98070",
    "sg:province":"Messina",
    "sg:tags":[
        "textile",
        "clothing"
    ],
    "wof:name":"Robertino Di Roberto Corpina",
    "wof:placetype":"venue"
},
  "geometry": {"coordinates":[14.687767,38.098652],"type":"Point"}
}