{
  "type": "Feature",
  "properties": {
    "addr:full":"20131 Milano Milano Milano 20131",
    "addr:postcode":"20131;20131",
    "iso:country":"IT",
    "sg:address":"20131 Milano",
    "sg:city":"Milano",
    "sg:orig_category":"Elettronica Professionale E Di Consumo. Automazione E Macchine Per Ufficio. Forniture Per Congressi, Fiere E Manifestazioni",
    "sg:phone":"+39 02 236 2467",
    "sg:postcode":"20131",
    "sg:province":"Milano",
    "wof:name":"Elitalia S.r.l.",
    "wof:placetype":"venue"
},
  "geometry": {"coordinates":[9.234276,45.482437],"type":"Point"}
}