{
  "type": "Feature",
  "properties": {
    "iso:country":"IT",
    "sg:address":"21013 Gallarate",
    "sg:city":"Gallarate",
    "sg:orig_category":"Servizi E Lavori Per Abbigliamento E Pelletterie",
    "sg:phone":"+39 0331 775443",
    "sg:postcode":"21013",
    "sg:province":"Varese",
    "sg:website":"http://www.fotodiamante.com",
    "wof:name":"Fotoincisione Diamante Srl",
    "wof:placetype":"venue"
},
  "geometry": {"coordinates":[8.796224,45.665981],"type":"Point"}
}