{
  "type": "Feature",
  "properties": {
    "addr:full":"Km. 115, Strada St. 126 09094 Marrubiu Marrubiu Oristano 09094",
    "addr:housenumber":"126",
    "addr:postcode":"09094;09094",
    "addr:street":"Strada St.",
    "iso:country":"IT",
    "sg:address":"Km. 115, Strada St. 126 09094 Marrubiu",
    "sg:city":"Marrubiu",
    "sg:classifiers":[
        {
            "category":"Utilities",
            "subcategory":"Electric",
            "type":"Services"
        }
    ],
    "sg:phone":"+39 0783 858305",
    "sg:postcode":"09094",
    "sg:province":"Oristano",
    "sg:tags":[
        "component",
        "electronic"
    ],
    "wof:name":"Elia S.r.l.",
    "wof:placetype":"venue"
},
  "geometry": {"coordinates":[8.59633255,39.9052734375],"type":"Point"}
}