{
  "type": "Feature",
  "properties": {
    "iso:country":"IT",
    "sg:address":"148, Via Giulia 00186 Roma",
    "sg:city":"Roma",
    "sg:classifiers":[
        {
            "category":"Sports & Exercise",
            "subcategory":"Playing Field",
            "type":"Entertainment"
        }
    ],
    "sg:phone":"+39 39066861443",
    "sg:postcode":"00186",
    "sg:province":"Roma",
    "sg:tags":[
        "game"
    ],
    "wof:name":"Galleria Giulia (s.a.s.)",
    "wof:placetype":"venue"
},
  "geometry": {"coordinates":[12.448003,41.871704],"type":"Point"}
}