{
  "type": "Feature",
  "properties": {
    "iso:country":"IT",
    "sg:address":"27055 Rivanazzano",
    "sg:city":"Rivanazzano",
    "sg:orig_category":"Macchine Utensili - Commercio",
    "sg:phone":"+39 0383 92134",
    "sg:postcode":"27055",
    "sg:province":"Pavia",
    "wof:name":"M.t.t. Machine Tools Trading Srl",
    "wof:placetype":"venue"
},
  "geometry": {"coordinates":[9.017974,44.928997],"type":"Point"}
}