{
  "type": "Feature",
  "properties": {
    "addr:full":"20063 Cernusco Sul Naviglio Cernusco sul Naviglio Milano 20063",
    "addr:postcode":"20063;20063",
    "iso:country":"IT",
    "sg:address":"20063 Cernusco Sul Naviglio",
    "sg:city":"Cernusco sul Naviglio",
    "sg:orig_category":"Chiese Ed Associazioni Religiose",
    "sg:phone":"+39 02 923 0679",
    "sg:postcode":"20063",
    "sg:province":"Milano",
    "wof:name":"Chiesa Neo - Apostolica In Italia",
    "wof:placetype":"venue"
},
  "geometry": {"coordinates":[9.296041,45.494297],"type":"Point"}
}