{
  "type": "Feature",
  "properties": {
    "iso:country":"IT",
    "sg:address":"80133 Napoli",
    "sg:city":"Napoli",
    "sg:orig_category":"Servizi E Lavori Per Ecologia E Smaltimento Rifiuti. Servizi Ausiliari Di Sorveglianza, Manutenzione E Pulizia",
    "sg:phone":"+39 081 542 2000",
    "sg:postcode":"80133",
    "sg:province":"Napoli",
    "sg:website":"http://www.italboll.it",
    "wof:name":"Italboll Srl",
    "wof:placetype":"venue"
},
  "geometry": {"coordinates":[14.255583,40.841072],"type":"Point"}
}