{
  "type": "Feature",
  "properties": {
    "iso:country":"IT",
    "sg:address":"00157 Roma",
    "sg:city":"Roma",
    "sg:orig_category":"Campeggio. Automobili E Mezzi Di Trasporto",
    "sg:phone":"+39 06 451 0236",
    "sg:postcode":"00157",
    "sg:province":"Roma",
    "wof:name":"Plini E Gigliotti Srl",
    "wof:placetype":"venue"
},
  "geometry": {"coordinates":[12.538407,41.914082],"type":"Point"}
}