{
  "type": "Feature",
  "properties": {
    "addr:full":"10124 Torino Torino Torino 10124",
    "addr:postcode":"10124;10124",
    "iso:country":"IT",
    "sg:address":"10124 Torino",
    "sg:city":"Torino",
    "sg:orig_category":"Lavorazioni Metalli, Stampaggio E Saldatura",
    "sg:phone":"+39 011 888020",
    "sg:postcode":"10124",
    "sg:province":"Torino",
    "wof:name":"Pignataro Franco",
    "wof:placetype":"venue"
},
  "geometry": {"coordinates":[7.695603,45.071083],"type":"Point"}
}