{
  "type": "Feature",
  "properties": {
    "addr:full":"15048 Valenza Valenza Alessandria 15048",
    "addr:postcode":"15048;15048",
    "iso:country":"IT",
    "sg:address":"15048 Valenza",
    "sg:city":"Valenza",
    "sg:orig_category":"Esportatori Ed Importatori",
    "sg:phone":"+39 0131 942078",
    "sg:postcode":"15048",
    "sg:province":"Alessandria",
    "wof:name":"Mg Gold Di Mandirola Giorgio Sas",
    "wof:placetype":"venue"
},
  "geometry": {"coordinates":[8.676943,44.999279],"type":"Point"}
}