{
  "type": "Feature",
  "properties": {
    "addr:full":"00179 Roma Roma Roma 00179",
    "addr:postcode":"00179;00179",
    "iso:country":"IT",
    "sg:address":"00179 Roma",
    "sg:city":"Roma",
    "sg:orig_category":"Prodotti E Manufatti In Materie Plastiche",
    "sg:phone":"+39 06 780 6100",
    "sg:postcode":"00179",
    "sg:province":"Roma",
    "wof:name":"Giordano Eva",
    "wof:placetype":"venue"
},
  "geometry": {"coordinates":[12.5214490891,41.8738517761],"type":"Point"}
}