{
  "type": "Feature",
  "properties": {
    "iso:country":"IT",
    "sg:address":"113, Via Giardini 41026 Pavullo Nel Frignano",
    "sg:city":"Pavullo nel Frignano",
    "sg:classifiers":[
        {
            "category":"Manufacturing",
            "subcategory":"Food",
            "type":"Manufacturing & Wholesale Goods"
        }
    ],
    "sg:phone":"+39 39053620694",
    "sg:postcode":"41026",
    "sg:province":"Modena",
    "sg:tags":[
        "equipment",
        "processing",
        "-",
        "machinery"
    ],
    "wof:name":"F.lli Rovinalti S.n.c.",
    "wof:placetype":"venue"
},
  "geometry": {"coordinates":[10.833697319,44.3369445801],"type":"Point"}
}