{
  "type": "Feature",
  "properties": {
    "addr:full":"76, Via Oderzo 31040 Mansue' Treviso 31040",
    "addr:postcode":"31040;31040",
    "addr:street":"Via Oderzo",
    "iso:country":"IT",
    "sg:address":"76, Via Oderzo 31040 Mansue'",
    "sg:classifiers":[
        {
            "category":"Shopping",
            "subcategory":"Stationery & Office Supplies",
            "type":"Retail Goods"
        }
    ],
    "sg:phone":"+39 0422 713224",
    "sg:postcode":"31040",
    "sg:province":"Treviso",
    "sg:tags":[
        "professional"
    ],
    "wof:name":"Tregi S.r.l.",
    "wof:placetype":"venue"
},
  "geometry": {"coordinates":[12.5264501572,45.8104858398],"type":"Point"}
}