{
  "type": "Feature",
  "properties": {
    "addr:full":"20041 Agrate Brianza Agrate Brianza Milano 20041",
    "addr:postcode":"20041;20041",
    "iso:country":"IT",
    "sg:address":"20041 Agrate Brianza",
    "sg:city":"Agrate Brianza",
    "sg:orig_category":"Macchine Ed Impianti Per Edilizia E Lavori Pubblici",
    "sg:phone":"+39 039 653731",
    "sg:postcode":"20041",
    "sg:province":"Milano",
    "wof:name":"Errecer Di Renato Federico Toniolo",
    "wof:placetype":"venue"
},
  "geometry": {"coordinates":[9.350808,45.571938],"type":"Point"}
}