{
  "type": "Feature",
  "properties": {
    "addr:full":"33, Lungo Mallero Diaz 23100 Sondrio Sondrio Sondrio 23100",
    "addr:housenumber":"33",
    "addr:postcode":"23100;23100",
    "addr:street":"Lungo Mallero Diaz",
    "iso:country":"IT",
    "sg:address":"33, Lungo Mallero Diaz 23100 Sondrio",
    "sg:city":"Sondrio",
    "sg:classifiers":[
        {
            "category":"Building & Trades",
            "subcategory":"Construction",
            "type":"Services"
        }
    ],
    "sg:phone":"+39 0342 215357",
    "sg:postcode":"23100",
    "sg:province":"Sondrio",
    "sg:tags":[
        "work",
        "public"
    ],
    "wof:name":"Redilcom Srl",
    "wof:placetype":"venue"
},
  "geometry": {"coordinates":[9.866734,46.170338],"type":"Point"}
}