{
  "type": "Feature",
  "properties": {
    "addr:full":"12, V. G. D. Vittorio - Loc. Pian Dell'isola 50067 Rignano Sull'arno Firenze 50067",
    "addr:housenumber":"12",
    "addr:postcode":"50067;50067",
    "addr:street":"V. G. D. Vittorio Loc. Pian Dell'Isola",
    "iso:country":"IT",
    "sg:address":"12, V. G. D. Vittorio - Loc. Pian Dell'isola 50067 Rignano Sull'arno",
    "sg:classifiers":[
        {
            "category":"Shopping",
            "subcategory":"Computers & Home Electronics",
            "type":"Retail Goods"
        }
    ],
    "sg:phone":"+39 055 834 7136",
    "sg:postcode":"50067",
    "sg:province":"Firenze",
    "sg:tags":[
        "electronic",
        "electrical",
        "equipment"
    ],
    "sg:website":"http://www.paginegialle.it/artelucesrl",
    "wof:name":"Arte Luce Srl",
    "wof:placetype":"venue"
},
  "geometry": {"coordinates":[11.256902,43.768734],"type":"Point"}
}