{
  "type": "Feature",
  "properties": {
    "addr:full":"Via Cigliano 31 10153 Torino Torino Torino 10153",
    "addr:housenumber":"31",
    "addr:postcode":"10153;10153",
    "addr:street":"Via Cigliano",
    "iso:country":"IT",
    "sg:address":"Via Cigliano 31 10153 Torino",
    "sg:city":"Torino",
    "sg:classifiers":[
        {
            "category":"Transit Center",
            "subcategory":"Passenger",
            "type":"Transportation"
        }
    ],
    "sg:phone":"+39 011 818 2301",
    "sg:postcode":"10153",
    "sg:province":"Torino",
    "sg:tags":[
        "essence",
        "flavourings",
        "baking",
        "aromatic",
        "essences"
    ],
    "sg:website":"www.aromitalia.com",
    "wof:name":"G.e.i. Spa",
    "wof:placetype":"venue"
},
  "geometry": {"coordinates":[8.39892,45.462345],"type":"Point"}
}