{
  "type": "Feature",
  "properties": {
    "iso:country":"IT",
    "sg:address":"31030 Casier",
    "sg:city":"Casier",
    "sg:orig_category":"Materiali Semilavorati Metallici",
    "sg:postcode":"31030",
    "sg:province":"Treviso",
    "wof:name":"Paglianti (s.p.a.)",
    "wof:placetype":"venue"
},
  "geometry": {"coordinates":[12.295763,45.643879],"type":"Point"}
}