{
  "type": "Feature",
  "properties": {
    "iso:country":"IT",
    "sg:address":"20089 Rozzano",
    "sg:city":"Rozzano",
    "sg:orig_category":"Tempo Libero - Articoli E Forniture. Regalistica Aziendale",
    "sg:phone":"+39 02 5750 4055",
    "sg:postcode":"20089",
    "sg:province":"Milano",
    "wof:name":"Ciao S.r.l.",
    "wof:placetype":"venue"
},
  "geometry": {"coordinates":[9.151986,45.390106],"type":"Point"}
}