{
  "type": "Feature",
  "properties": {
    "addr:full":"37013 Caprino Veronese Caprino Veronese Verona 37013",
    "addr:postcode":"37013;37013",
    "iso:country":"IT",
    "sg:address":"37013 Caprino Veronese",
    "sg:city":"Caprino Veronese",
    "sg:orig_category":"Materiali E Componenti Elettrotecnici. Elettrotecnica Industriale, Prodotti E Apparecchiature",
    "sg:phone":"+39 045 623 0855",
    "sg:postcode":"37013",
    "sg:province":"Verona",
    "sg:website":"http://www.elettrarenon.com",
    "wof:name":"Elettra Renon Di Renon Stefano",
    "wof:placetype":"venue"
},
  "geometry": {"coordinates":[11.290629,45.26487],"type":"Point"}
}