{
  "type": "Feature",
  "properties": {
    "iso:country":"IT",
    "sg:address":"38015 Lavis",
    "sg:city":"Lavis",
    "sg:orig_category":"Arredamenti - Produzione E Ingrosso",
    "sg:phone":"+39 0461 245151",
    "sg:postcode":"38015",
    "sg:province":"Trento",
    "sg:website":"http://www.paginegialle.it/aet-tn",
    "wof:name":"A & T Multimedia - Arredamenti E Tecnologie",
    "wof:placetype":"venue"
},
  "geometry": {"coordinates":[11.095579,46.145737],"type":"Point"}
}