{
  "type": "Feature",
  "properties": {
    "iso:country":"IT",
    "sg:address":"160, Via Rivera 10040 Almese",
    "sg:city":"Almese",
    "sg:classifiers":[
        {
            "category":"Shopping",
            "type":"Retail Goods"
        }
    ],
    "sg:phone":"+39 011 935 0732",
    "sg:postcode":"10040",
    "sg:province":"Torino",
    "sg:tags":[
        "finished",
        "-",
        "metallic"
    ],
    "wof:name":"Landra (s.r.l.)",
    "wof:placetype":"venue"
},
  "geometry": {"coordinates":[7.4118700027,45.1116104126],"type":"Point"}
}