{
  "type": "Feature",
  "properties": {
    "iso:country":"IT",
    "sg:address":"Via G. Marconi 32 24068 Seriate",
    "sg:city":"Seriate",
    "sg:classifiers":[
        {
            "category":"Manufacturing",
            "subcategory":"Metals",
            "type":"Manufacturing & Wholesale Goods"
        }
    ],
    "sg:phone":"+39 035 291234",
    "sg:postcode":"24068",
    "sg:province":"Bergamo",
    "sg:tags":[
        "ironmongery"
    ],
    "sg:website":"www.mazzoleni.it",
    "wof:name":"Mazzoleni Industriale Commerciale Spa",
    "wof:placetype":"venue"
},
  "geometry": {"coordinates":[9.729886,45.67918],"type":"Point"}
}