{
  "type": "Feature",
  "properties": {
    "iso:country":"IT",
    "sg:address":"35, Via Gessi Lanfranco 48022 Lugo",
    "sg:city":"Lugo",
    "sg:classifiers":[
        {
            "category":"Personal",
            "subcategory":"Shoe Repair & Shine",
            "type":"Services"
        }
    ],
    "sg:phone":"+39 39054530879",
    "sg:postcode":"48022",
    "sg:province":"Ravenna",
    "sg:tags":[
        "leather"
    ],
    "wof:name":"S.t.a. Sviluppo Tecnologie Avanzate S.r.l.",
    "wof:placetype":"venue"
},
  "geometry": {"coordinates":[12.196571,44.41573],"type":"Point"}
}