{
  "type": "Feature",
  "properties": {
    "iso:country":"IT",
    "sg:address":"80141 Napoli",
    "sg:city":"Napoli",
    "sg:orig_category":"Materiali E Componenti Elettrotecnici",
    "sg:phone":"+39 081 751 2651",
    "sg:postcode":"80141",
    "sg:province":"Napoli",
    "wof:name":"Mozzillo Carmine",
    "wof:placetype":"venue"
},
  "geometry": {"coordinates":[14.26104,40.879154],"type":"Point"}
}