{
  "type": "Feature",
  "properties": {
    "iso:country":"IT",
    "sg:address":"20090 Assago",
    "sg:city":"Assago",
    "sg:orig_category":"Banche E Servizi Finanziari",
    "sg:phone":"+39 02 892581",
    "sg:postcode":"20090",
    "sg:province":"Milano",
    "wof:name":"Intesa Italia Sim",
    "wof:placetype":"venue"
},
  "geometry": {"coordinates":[9.148091,45.403061],"type":"Point"}
}