{
  "type": "Feature",
  "properties": {
    "addr:full":"04024 Gaeta Gaeta Latina 04024",
    "addr:postcode":"04024;04024",
    "iso:country":"IT",
    "sg:address":"04024 Gaeta",
    "sg:city":"Gaeta",
    "sg:orig_category":"Trasporti",
    "sg:phone":"+39 0771 470320",
    "sg:postcode":"04024",
    "sg:province":"Latina",
    "wof:name":"Di Cecca Srl",
    "wof:placetype":"venue"
},
  "geometry": {"coordinates":[13.555261,41.244724],"type":"Point"}
}