{
  "type": "Feature",
  "properties": {
    "iso:country":"IT",
    "sg:address":"18, Via Venezian Giacomo 20133 Milano",
    "sg:city":"Milano",
    "sg:classifiers":[
        {
            "category":"Wholesale",
            "subcategory":"Medical Equipment & Supplies",
            "type":"Manufacturing & Wholesale Goods"
        }
    ],
    "sg:phone":"+39 39022664641",
    "sg:postcode":"20133",
    "sg:province":"Milano",
    "sg:tags":[
        "-",
        "health",
        "instrument"
    ],
    "wof:name":"Sana Med Srl",
    "wof:placetype":"venue"
},
  "geometry": {"coordinates":[9.232235,45.474274],"type":"Point"}
}