{
  "type": "Feature",
  "properties": {
    "iso:country":"IT",
    "sg:address":"Via Pian Masino 12/a 16011 Arenzano",
    "sg:city":"Arenzano",
    "sg:orig_category":"Ship Lavatories, Self-flushing",
    "sg:phone":"+39 010 913251",
    "sg:postcode":"16011",
    "sg:province":"Genova",
    "sg:website":"www.giumma.com",
    "wof:name":"Giumma Spa",
    "wof:placetype":"venue"
},
  "geometry": {"coordinates":[8.662693,44.404552],"type":"Point"}
}