{
  "type": "Feature",
  "properties": {
    "iso:country":"IT",
    "sg:address":"22100 Como",
    "sg:city":"Como",
    "sg:orig_category":"Accessori Moda D'abbigliamento. Complementi Di Arredamento. Tempo Libero - Articoli E Forniture",
    "sg:phone":"+39 031 269500",
    "sg:postcode":"22100",
    "sg:province":"Como",
    "wof:name":"Molteni Pietro",
    "wof:placetype":"venue"
},
  "geometry": {"coordinates":[9.084011,45.807423],"type":"Point"}
}