{
  "type": "Feature",
  "properties": {
    "addr:full":"00045 Genzano Di Roma Genzano di Roma Roma 00045",
    "addr:postcode":"00045;00045",
    "iso:country":"IT",
    "sg:address":"00045 Genzano Di Roma",
    "sg:city":"Genzano di Roma",
    "sg:orig_category":"Macchine, Impianti Ed Attrezzature Industria Chimica. Vetro: Prodotti E Lavorazioni",
    "sg:phone":"+39 06 936 2164",
    "sg:postcode":"00045",
    "sg:province":"Roma",
    "wof:name":"Vetro Scientifica Srl",
    "wof:placetype":"venue"
},
  "geometry": {"coordinates":[12.677425,41.695606],"type":"Point"}
}