{
  "type": "Feature",
  "properties": {
    "iso:country":"IT",
    "sg:address":"10034 Chivasso",
    "sg:city":"Chivasso",
    "sg:orig_category":"Materie Plastiche Articoli Vari - Produzione E Ingrosso",
    "sg:phone":"+39 011 919 5321",
    "sg:postcode":"10034",
    "sg:province":"Torino",
    "wof:name":"Borgaro Marisa",
    "wof:placetype":"venue"
},
  "geometry": {"coordinates":[7.910016,45.213978],"type":"Point"}
}