{
  "type": "Feature",
  "properties": {
    "iso:country":"IT",
    "sg:address":"06024 Gubbio",
    "sg:city":"Gubbio",
    "sg:orig_category":"Macchine, Impianti Ed Attrezzature Per Agricoltura E Zootecnia. Macchine E Forniture Per Arredamento E Industria Del Legno",
    "sg:phone":"+39 075 927 3961",
    "sg:postcode":"06024",
    "sg:province":"Perugia",
    "wof:name":"Marinetti Luigi",
    "wof:placetype":"venue"
},
  "geometry": {"coordinates":[12.386757,43.26778],"type":"Point"}
}