{
  "type": "Feature",
  "properties": {
    "addr:full":"121, Via Borgomanero 28010 Briga Novarese Briga Novarese Novara 28010",
    "addr:housenumber":"121",
    "addr:postcode":"28010;28010",
    "addr:street":"Via Borgomanero",
    "iso:country":"IT",
    "sg:address":"121, Via Borgomanero 28010 Briga Novarese",
    "sg:city":"Briga Novarese",
    "sg:classifiers":[
        {
            "category":"Shopping",
            "type":"Retail Goods"
        }
    ],
    "sg:phone":"+39 39032294847",
    "sg:postcode":"28010",
    "sg:province":"Novara",
    "sg:tags":[
        "finished",
        "-",
        "metallic"
    ],
    "wof:name":"Vinzia Fratelli (s.p.a.)",
    "wof:placetype":"venue"
},
  "geometry": {"coordinates":[8.4472866058,45.7231712341],"type":"Point"}
}