{
  "type": "Feature",
  "properties": {
    "iso:country":"IT",
    "sg:address":"58, Via Vicenza 00185 Roma",
    "sg:city":"Roma",
    "sg:classifiers":[
        {
            "category":"Travel",
            "subcategory":"Travel Agent",
            "type":"Entertainment"
        }
    ],
    "sg:phone":"+39 39064457770",
    "sg:postcode":"00185",
    "sg:province":"Roma",
    "sg:tags":[
        "business"
    ],
    "wof:name":"Albergo Canada S.r.l.",
    "wof:placetype":"venue"
},
  "geometry": {"coordinates":[12.505512,41.904949],"type":"Point"}
}