{
  "type": "Feature",
  "properties": {
    "iso:country":"IT",
    "sg:address":"41043 Formigine",
    "sg:city":"Formigine",
    "sg:orig_category":"Trattamenti Termici E Superficiali Metalli, Galvanotecnica",
    "sg:phone":"+39 059 570596",
    "sg:postcode":"41043",
    "sg:province":"Modena",
    "wof:name":"Noxid (s.r.l.)",
    "wof:placetype":"venue"
},
  "geometry": {"coordinates":[10.84866,44.563179],"type":"Point"}
}