{
  "type": "Feature",
  "properties": {
    "addr:full":"31020 Villorba Villorba Treviso 31020",
    "addr:postcode":"31020;31020",
    "iso:country":"IT",
    "sg:address":"31020 Villorba",
    "sg:city":"Villorba",
    "sg:orig_category":"Ceramiche Per Pavimenti E Rivestimenti - Produzione E Ingrosso",
    "sg:phone":"+39 0422 608500",
    "sg:postcode":"31020",
    "sg:province":"Treviso",
    "sg:website":"http://www.ceramicaditreviso.it",
    "wof:name":"Ceramica Di Treviso Sas Di Dolfato Mario & C.",
    "wof:placetype":"venue"
},
  "geometry": {"coordinates":[12.240235,45.731651],"type":"Point"}
}