{
  "type": "Feature",
  "properties": {
    "addr:full":"56017 San Martino A Ulmiano Pisa 56017",
    "addr:postcode":"56017;56017",
    "addr:street":"Martino A Ulmiano",
    "iso:country":"IT",
    "sg:address":"56017 San Martino A Ulmiano",
    "sg:orig_category":"Tempo Libero - Articoli E Forniture. Forniture Per Congressi, Fiere E Manifestazioni. Regalistica Aziendale",
    "sg:phone":"+39 050 820300",
    "sg:postcode":"56017",
    "sg:province":"Pisa",
    "wof:name":"Seritalia Toscana S.r.l.",
    "wof:placetype":"venue"
},
  "geometry": {"coordinates":[10.403426,43.754478],"type":"Point"}
}