{
  "type": "Feature",
  "properties": {
    "iso:country":"IT",
    "sg:address":"Via Pagliarina 21 36075 Montecchio Maggiore",
    "sg:city":"Montecchio Maggiore",
    "sg:classifiers":[
        {
            "category":"Manufacturing",
            "subcategory":"Tools & Machinery",
            "type":"Manufacturing & Wholesale Goods"
        }
    ],
    "sg:phone":"+39 0444 492236",
    "sg:postcode":"36075",
    "sg:province":"Vicenza",
    "sg:tags":[
        "machine",
        "allround",
        "turning",
        "milling",
        "drilling"
    ],
    "sg:website":"www.torneriapms.com",
    "wof:name":"Torneria Pms S.r.l.",
    "wof:placetype":"venue"
},
  "geometry": {"coordinates":[11.540307,45.545906],"type":"Point"}
}