{
  "type": "Feature",
  "properties": {
    "iso:country":"IT",
    "sg:address":"244, Via Pantanelli 61025 Montelabbate",
    "sg:city":"Montelabbate",
    "sg:classifiers":[
        {
            "category":"Home & Garden",
            "subcategory":"Home Furnishings",
            "type":"Retail Goods"
        }
    ],
    "sg:phone":"+39 0721 490694",
    "sg:postcode":"61025",
    "sg:province":"Pesaro E Urbino",
    "sg:tags":[
        "household"
    ],
    "wof:name":"Mobilificio Errebi (s.p.a.)",
    "wof:placetype":"venue"
},
  "geometry": {"coordinates":[12.79343,43.863632],"type":"Point"}
}