{
  "type": "Feature",
  "properties": {
    "iso:country":"IT",
    "sg:address":"00168 Roma",
    "sg:city":"Roma",
    "sg:orig_category":"Servizi Al Turismo. Trasporto Pubblico E Privato",
    "sg:phone":"+39 06 301 6406",
    "sg:postcode":"00168",
    "sg:province":"Roma",
    "wof:name":"Federazione Italiana Vela Iv Zona",
    "wof:placetype":"venue"
},
  "geometry": {"coordinates":[12.426512,41.927647],"type":"Point"}
}