{
  "type": "Feature",
  "properties": {
    "iso:country":"IT",
    "sg:address":"95126 Catania",
    "sg:city":"Catania",
    "sg:classifiers":[
        {
            "category":"Health Services",
            "subcategory":"Health Practitioner",
            "type":"Services"
        }
    ],
    "sg:phone":"+39 095 552040",
    "sg:postcode":"95126",
    "sg:province":"Catania",
    "sg:tags":[
        "medici"
    ],
    "wof:name":"Cavallaro Consolato",
    "wof:placetype":"venue"
},
  "geometry": {"coordinates":[15.094331,37.526192],"type":"Point"}
}