{
  "type": "Feature",
  "properties": {
    "iso:country":"IT",
    "sg:address":"47, Via Dell' Industria 25010 Isorella",
    "sg:city":"Isorella",
    "sg:classifiers":[
        {
            "category":"Shopping",
            "subcategory":"Clothing, Apparel, & Fashions",
            "type":"Retail Goods"
        }
    ],
    "sg:phone":"+39 030 995 8105",
    "sg:postcode":"25010",
    "sg:province":"Brescia",
    "sg:tags":[
        "clothes"
    ],
    "wof:name":"Tecnoriver (s.r.l.)",
    "wof:placetype":"venue"
},
  "geometry": {"coordinates":[10.320268,45.302711],"type":"Point"}
}