{
  "type": "Feature",
  "properties": {
    "addr:full":"7, Via Giuseppe Di Vittorio 61022 Colbordolo Colbordolo Pesaro E Urbino 61022",
    "addr:postcode":"61022;61022",
    "addr:street":"Via Giuseppe Di Vittorio",
    "iso:country":"IT",
    "sg:address":"7, Via Giuseppe Di Vittorio 61022 Colbordolo",
    "sg:city":"Colbordolo",
    "sg:classifiers":[
        {
            "category":"Manufacturing",
            "subcategory":"Rubber & Plastics",
            "type":"Manufacturing & Wholesale Goods"
        }
    ],
    "sg:phone":"+39 0721 479178",
    "sg:postcode":"61022",
    "sg:province":"Pesaro E Urbino",
    "wof:name":"Delta S.r.l.",
    "wof:placetype":"venue"
},
  "geometry": {"coordinates":[12.7208833694,43.8348960876],"type":"Point"}
}