{
  "type": "Feature",
  "properties": {
    "iso:country":"IT",
    "sg:address":"42017 Novellara",
    "sg:orig_category":"Materie Plastiche - Produzione E Lavorazione",
    "sg:phone":"+39 0522 657492",
    "sg:postcode":"42017",
    "sg:province":"Reggio Nell'Emilia",
    "wof:name":"Zinani E Bussei Snc",
    "wof:placetype":"venue"
},
  "geometry": {"coordinates":[10.627794,44.696228],"type":"Point"}
}