{
  "type": "Feature",
  "properties": {
    "addr:full":"30100 Venezia VE",
    "addr:postcode":"30100",
    "addr:street":"Ve",
    "iso:country":"IT",
    "sg:address":"30100 Venezia",
    "sg:orig_category":"Pubblica Amministrazione",
    "sg:phone":"+39 041 523 0836",
    "sg:province":"VE",
    "wof:name":"Carabinieri",
    "wof:placetype":"venue"
},
  "geometry": {"coordinates":[12.2908992767,45.3731994629],"type":"Point"}
}