{
  "type": "Feature",
  "properties": {
    "addr:full":"13, Via Alcide De Gasperi 23847 Molteno Molteno Lecco 23847",
    "addr:postcode":"23847;23847",
    "addr:street":"Via Alcide De Gasperi",
    "iso:country":"IT",
    "sg:address":"13, Via Alcide De Gasperi 23847 Molteno",
    "sg:city":"Molteno",
    "sg:classifiers":[
        {
            "category":"Manufacturing",
            "subcategory":"Metals",
            "type":"Manufacturing & Wholesale Goods"
        }
    ],
    "sg:phone":"+39 39031852265",
    "sg:postcode":"23847",
    "sg:province":"Lecco",
    "sg:tags":[
        "metallurgy",
        "metalworking"
    ],
    "wof:name":"Abs (s.r.l.)",
    "wof:placetype":"venue"
},
  "geometry": {"coordinates":[9.3117961884,45.7782173157],"type":"Point"}
}