{
  "type": "Feature",
  "properties": {
    "addr:full":"26853 Caselle Lurani Caselle Lurani Lodi 26853",
    "addr:postcode":"26853;26853",
    "iso:country":"IT",
    "sg:address":"26853 Caselle Lurani",
    "sg:city":"Caselle Lurani",
    "sg:orig_category":"Macchine, Impianti Ed Attrezzature Industria Chimica. Attrezzature E Forniture Per Officine Riparazione E Servizi Ausiliari",
    "sg:phone":"+39 0371 96255",
    "sg:postcode":"26853",
    "sg:province":"Lodi",
    "wof:name":"Verniciatura Gmg Srl",
    "wof:placetype":"venue"
},
  "geometry": {"coordinates":[9.384479,45.269283],"type":"Point"}
}