{
  "type": "Feature",
  "properties": {
    "iso:country":"IT",
    "sg:address":"42, Via Vicarese 56012 Calcinaia",
    "sg:city":"Calcinaia",
    "sg:classifiers":[
        {
            "category":"Personal",
            "subcategory":"Shoe Repair & Shine",
            "type":"Services"
        }
    ],
    "sg:phone":"+39 0587 489398",
    "sg:postcode":"56012",
    "sg:province":"Pisa",
    "sg:tags":[
        "leather"
    ],
    "wof:name":"Il Veliero (s.n.c.)",
    "wof:placetype":"venue"
},
  "geometry": {"coordinates":[10.537642,43.688446],"type":"Point"}
}