{
  "type": "Feature",
  "properties": {
    "iso:country":"IT",
    "sg:address":"34, Corso Monte Grappa 16137 Genova",
    "sg:city":"Genova",
    "sg:classifiers":[
        {
            "category":"Building & Trades",
            "subcategory":"Construction",
            "type":"Services"
        }
    ],
    "sg:phone":"+39 010 839 1436",
    "sg:postcode":"16137",
    "sg:province":"Genova",
    "sg:tags":[
        "work",
        "public"
    ],
    "wof:name":"Controlchemi (s.r.l.)",
    "wof:placetype":"venue"
},
  "geometry": {"coordinates":[8.950131,44.410751],"type":"Point"}
}