{
  "type": "Feature",
  "properties": {
    "addr:full":"56012 Calcinaia Calcinaia Pisa 56012",
    "addr:postcode":"56012;56012",
    "iso:country":"IT",
    "sg:address":"56012 Calcinaia",
    "sg:city":"Calcinaia",
    "sg:orig_category":"Prodotti E Manufatti In Gomma. Servizi E Lavori Industria Della Gomma. Ricambi E Componenti Dei Mezzi Di Trasporto. Riparazione Dei Mezzi Di Trasporto",
    "sg:phone":"+39 0587 283111",
    "sg:postcode":"56012",
    "sg:province":"Pisa",
    "sg:website":"http://www.intergomma.it",
    "wof:name":"Intergomma Spa",
    "wof:placetype":"venue"
},
  "geometry": {"coordinates":[10.5277633667,43.6788215637],"type":"Point"}
}