{
  "type": "Feature",
  "properties": {
    "iso:country":"IT",
    "sg:address":"15, Via Tempesta Guglielmino 35124 Padova",
    "sg:city":"Padova",
    "sg:classifiers":[
        {
            "category":"Wholesale",
            "subcategory":"Drugs",
            "type":"Manufacturing & Wholesale Goods"
        }
    ],
    "sg:phone":"+39 049 880 4856",
    "sg:postcode":"35124",
    "sg:province":"Padova",
    "sg:tags":[
        "chemical",
        "pharmaceutical"
    ],
    "wof:name":"Alifax (s.p.a.)",
    "wof:placetype":"venue"
},
  "geometry": {"coordinates":[11.844167,45.397499],"type":"Point"}
}