{
  "type": "Feature",
  "properties": {
    "iso:country":"IT",
    "sg:address":"9/11, Via Isonzo 33076 Pravisdomini",
    "sg:city":"Pravisdomini",
    "sg:classifiers":[
        {
            "category":"Manufacturing",
            "subcategory":"Lumber",
            "type":"Manufacturing & Wholesale Goods"
        }
    ],
    "sg:phone":"+39 0434 644711",
    "sg:postcode":"33076",
    "sg:province":"Pordenone",
    "sg:tags":[
        "wood"
    ],
    "wof:name":"C.r.c. Di Zamuner Claudio & C. S.n.c.",
    "wof:placetype":"venue"
},
  "geometry": {"coordinates":[12.683856,45.810551],"type":"Point"}
}