{
  "type": "Feature",
  "properties": {
    "iso:country":"IT",
    "sg:address":"Via Fonda Di Mezzana 46 59100 Prato",
    "sg:city":"Mezzana",
    "sg:classifiers":[
        {
            "category":"Parking",
            "subcategory":"Lot",
            "type":"Transportation"
        }
    ],
    "sg:phone":"+39 0574 570462",
    "sg:postcode":"59100",
    "sg:province":"Prato",
    "sg:tags":[
        "stockinette",
        "yarn"
    ],
    "sg:website":"www.fantafil.it",
    "wof:name":"Fantafil Spa",
    "wof:placetype":"venue"
},
  "geometry": {"coordinates":[11.099821,43.84795],"type":"Point"}
}