{
  "type": "Feature",
  "properties": {
    "iso:country":"IT",
    "sg:address":"20090 Trezzano Sul Naviglio",
    "sg:city":"Trezzano sul Naviglio",
    "sg:orig_category":"Agenzie D'affari E Servizi Commerciali",
    "sg:phone":"+39 02 445 3292",
    "sg:postcode":"20090",
    "sg:province":"Milano",
    "wof:name":"Pruftechnik Srl",
    "wof:placetype":"venue"
},
  "geometry": {"coordinates":[9.054585,45.421513],"type":"Point"}
}