{
  "type": "Feature",
  "properties": {
    "iso:country":"IT",
    "sg:address":"50126 Firenze",
    "sg:city":"Firenze",
    "sg:orig_category":"Prodotti Finiti Stampati. Servizi Editoriali. Tempo Libero - Articoli E Forniture",
    "sg:phone":"+39 055 681 0441",
    "sg:postcode":"50126",
    "sg:province":"Firenze",
    "wof:name":"Aermap (s.r.l.)",
    "wof:placetype":"venue"
},
  "geometry": {"coordinates":[11.2457475662,43.7753562927],"type":"Point"}
}