{
  "type": "Feature",
  "properties": {
    "addr:full":"6, V. Romanino 24050 Cavernago Cavernago Bergamo 24050",
    "addr:housenumber":"6",
    "addr:postcode":"24050;24050",
    "addr:street":"Romanino",
    "iso:country":"IT",
    "sg:address":"6, V. Romanino 24050 Cavernago",
    "sg:city":"Cavernago",
    "sg:classifiers":[
        {
            "category":"Shopping",
            "subcategory":"Crafts & Fabrics",
            "type":"Retail Goods"
        }
    ],
    "sg:phone":"+39 035 449 8478",
    "sg:postcode":"24050",
    "sg:province":"Bergamo",
    "sg:website":"http://www.italiantex.it",
    "wof:name":"Italiantex Srl",
    "wof:placetype":"venue"
},
  "geometry": {"coordinates":[9.7768211365,45.6171417236],"type":"Point"}
}