{
  "type": "Feature",
  "properties": {
    "iso:country":"IT",
    "sg:address":"95040 Ramacca",
    "sg:city":"Ramacca",
    "sg:orig_category":"Manufacturers: Prefabbricati",
    "sg:phone":"+39 095 653601",
    "sg:postcode":"95040",
    "sg:province":"Catania",
    "wof:name":"Munaf\u00d2 Fortunato",
    "wof:placetype":"venue"
},
  "geometry": {"coordinates":[14.693581,37.385128],"type":"Point"}
}