{
  "type": "Feature",
  "properties": {
    "iso:country":"IT",
    "sg:address":"07040 Uri",
    "sg:city":"Uri",
    "sg:orig_category":"Maglieria - Produzione E Ingrosso",
    "sg:phone":"+39 079 419895",
    "sg:postcode":"07040",
    "sg:province":"Sassari",
    "wof:name":"Paolina Di Salaris Paolina",
    "wof:placetype":"venue"
},
  "geometry": {"coordinates":[8.483235,40.639019],"type":"Point"}
}