{
  "type": "Feature",
  "properties": {
    "iso:country":"IT",
    "sg:address":"37062 Dossobuono Di Villafranca",
    "sg:city":"Dossobuono",
    "sg:classifiers":[
        {
            "category":"Utilities",
            "subcategory":"Mobile Phone",
            "type":"Services"
        }
    ],
    "sg:phone":"+39 045 860 0924",
    "sg:postcode":"37062",
    "sg:province":"Verona",
    "sg:tags":[
        "equipment",
        "telecommunication",
        "systems",
        "telephony"
    ],
    "sg:website":"http://www.mgstelecom.it",
    "wof:name":"M.g.s. Tecnoimpianti Srl",
    "wof:placetype":"venue"
},
  "geometry": {"coordinates":[10.905089,45.38892],"type":"Point"}
}