{
  "type": "Feature",
  "properties": {
    "iso:country":"IT",
    "sg:address":"42100 Reggio Emilia",
    "sg:orig_category":"Stampaggio Materie Plastiche",
    "sg:phone":"+39 0522 551472",
    "sg:postcode":"42100",
    "sg:province":"Reggio Nell'Emilia",
    "wof:name":"Bear Plast Spa",
    "wof:placetype":"venue"
},
  "geometry": {"coordinates":[10.652462,44.68],"type":"Point"}
}