{
  "type": "Feature",
  "properties": {
    "iso:country":"IT",
    "sg:address":"59013 Montemurlo",
    "sg:city":"Montemurlo",
    "sg:orig_category":"Tessuti E Stoffe. Forniture Per Attivita' Industriali",
    "sg:phone":"+39 0574 720589",
    "sg:postcode":"59013",
    "sg:province":"Prato",
    "wof:name":"Sa - Me (s.r.l.)",
    "wof:placetype":"venue"
},
  "geometry": {"coordinates":[11.053926,43.906189],"type":"Point"}
}