{
  "type": "Feature",
  "properties": {
    "addr:full":"16126 Genova Genova Genova 16126",
    "addr:postcode":"16126;16126",
    "iso:country":"IT",
    "sg:address":"16126 Genova",
    "sg:city":"Genova",
    "sg:orig_category":"Petroli, Gas E Combustibili",
    "sg:phone":"+39 010 246 2917",
    "sg:postcode":"16126",
    "sg:province":"Genova",
    "wof:name":"Giordo (s.r.l.)",
    "wof:placetype":"venue"
},
  "geometry": {"coordinates":[8.9093580246,44.405670166],"type":"Point"}
}