{
  "type": "Feature",
  "properties": {
    "iso:country":"IT",
    "sg:address":"64100 Teramo",
    "sg:city":"Teramo",
    "sg:orig_category":"Pubblica Amministrazione",
    "sg:phone":"+39 0861 243166",
    "sg:postcode":"64100",
    "sg:province":"Teramo",
    "wof:name":"Protezione Civile",
    "wof:placetype":"venue"
},
  "geometry": {"coordinates":[13.7057495117,42.6772766113],"type":"Point"}
}