{
  "type": "Feature",
  "properties": {
    "addr:full":"Via 3 Strada 7 35026 Conselve Conselve Padova 35026",
    "addr:housenumber":"7",
    "addr:postcode":"35026;35026",
    "addr:street":"Via;Strada",
    "iso:country":"IT",
    "sg:address":"Via 3 Strada 7 35026 Conselve",
    "sg:city":"Conselve",
    "sg:classifiers":[
        {
            "category":"Shopping",
            "subcategory":"Hobbies, Toys, & Games",
            "type":"Retail Goods"
        }
    ],
    "sg:phone":"+39 049 950 0799",
    "sg:postcode":"35026",
    "sg:province":"Padova",
    "sg:tags":[
        "toy",
        "animals",
        "plush",
        "stuffed"
    ],
    "sg:website":"www.fantasytoys.it",
    "wof:name":"Fantasy Toys S.r.l.",
    "wof:placetype":"venue"
},
  "geometry": {"coordinates":[11.876589,45.409569],"type":"Point"}
}