{
  "type": "Feature",
  "properties": {
    "iso:country":"IT",
    "sg:address":"33030 Campoformido",
    "sg:city":"Basaldella",
    "sg:orig_category":"Antifurto",
    "sg:phone":"+39 0432 562696",
    "sg:postcode":"33030",
    "sg:province":"Udine",
    "sg:website":"http://www.kronotech.it",
    "wof:name":"Zucchetti Italia Srl - Divisione Kronotech",
    "wof:placetype":"venue"
},
  "geometry": {"coordinates":[13.201025,46.031986],"type":"Point"}
}