{
  "type": "Feature",
  "properties": {
    "iso:country":"IT",
    "sg:address":"20123 Milano",
    "sg:city":"Milano",
    "sg:classifiers":[
        {
            "category":"Health Services",
            "subcategory":"Health Practitioner",
            "type":"Services"
        }
    ],
    "sg:phone":"+39 02 837 8146",
    "sg:postcode":"20123",
    "sg:province":"Milano",
    "sg:tags":[
        "medici"
    ],
    "wof:name":"Croce Luigi",
    "wof:placetype":"venue"
},
  "geometry": {"coordinates":[9.176232,45.454647],"type":"Point"}
}