{
  "type": "Feature",
  "properties": {
    "addr:full":"Viale Umberto 75; Thiesi",
    "addr:housenumber":"75",
    "addr:street":"Viale Umberto",
    "iso:country":"IT",
    "sg:address":"Viale Umberto 75; Thiesi",
    "sg:classifiers":[
        {
            "category":"Banks & Credit Unions",
            "subcategory":"Bank",
            "type":"Services"
        }
    ],
    "sg:phone":"+39 079 886002",
    "wof:name":"Banco Di Sardegna Spa",
    "wof:placetype":"venue"
},
  "geometry": {"coordinates":[8.723819,40.506023],"type":"Point"}
}