{
  "type": "Feature",
  "properties": {
    "addr:full":"Via Zona Artigianale P.i.p. 62019 Recanati Recanati Macerata 62019",
    "addr:postcode":"62019;62019",
    "addr:street":"Via Zona Artigianale P.I.P.",
    "iso:country":"IT",
    "sg:address":"Via Zona Artigianale P.i.p. 62019 Recanati",
    "sg:city":"Recanati",
    "sg:classifiers":[
        {
            "category":"Manufacturing",
            "subcategory":"Printing",
            "type":"Manufacturing & Wholesale Goods"
        }
    ],
    "sg:phone":"+39 071 757 8017",
    "sg:postcode":"62019",
    "sg:province":"Macerata",
    "sg:tags":[
        "publishing"
    ],
    "wof:name":"Bieffe Srl",
    "wof:placetype":"venue"
},
  "geometry": {"coordinates":[13.4562616348,43.3007469177],"type":"Point"}
}