{
  "type": "Feature",
  "properties": {
    "iso:country":"IT",
    "sg:address":"Via G. Di Vittorio 56 58 38015 Lavis",
    "sg:city":"Lavis",
    "sg:classifiers":[
        {
            "category":"Community Center",
            "subcategory":"Youth",
            "type":"Public Place"
        }
    ],
    "sg:phone":"+39 0461 246792",
    "sg:postcode":"38015",
    "sg:province":"Trento",
    "sg:tags":[
        "wooden",
        "hand-crafted",
        "items"
    ],
    "sg:website":"www.zambiasi.com",
    "wof:name":"Zambiasi Commerciale Srl",
    "wof:placetype":"venue"
},
  "geometry": {"coordinates":[11.08705,46.13353],"type":"Point"}
}