{
  "type": "Feature",
  "properties": {
    "iso:country":"IT",
    "sg:address":"98076 Sant'agata Di Militello",
    "sg:orig_category":"Bevande, Vini E Liquori",
    "sg:phone":"+39 0941 703266",
    "sg:postcode":"98076",
    "sg:province":"Messina",
    "wof:name":"Amata Calogero - Vini Genuini",
    "wof:placetype":"venue"
},
  "geometry": {"coordinates":[14.637715,38.067585],"type":"Point"}
}