{
  "type": "Feature",
  "properties": {
    "iso:country":"IT",
    "sg:address":"28, Via Rupe 38017 Mezzolombardo",
    "sg:city":"Mezzolombardo",
    "sg:classifiers":[
        {
            "category":"Autos & Motor Vehicles",
            "subcategory":"Automobile Sales",
            "type":"Retail Goods"
        }
    ],
    "sg:phone":"+39 0461 604149",
    "sg:postcode":"38017",
    "sg:province":"Trento",
    "sg:tags":[
        "equipment",
        "transport"
    ],
    "wof:name":"Cicli Francesco Moser",
    "wof:placetype":"venue"
},
  "geometry": {"coordinates":[11.097796,46.192043],"type":"Point"}
}