{
  "type": "Feature",
  "properties": {
    "iso:country":"IT",
    "sg:address":"25020 Seniga",
    "sg:city":"Seniga",
    "sg:orig_category":"Non-classified Establishments",
    "sg:phone":"+39 030 995 5019",
    "sg:postcode":"25020",
    "sg:province":"Brescia",
    "sg:website":"http://www.safcacucine.it",
    "wof:name":"Safca Snc",
    "wof:placetype":"venue"
},
  "geometry": {"coordinates":[10.181028,45.247215],"type":"Point"}
}