{
  "type": "Feature",
  "properties": {
    "iso:country":"IT",
    "sg:address":"30028 San Michele Al Tagliamento",
    "sg:city":"San Michele al Tagliamento",
    "sg:orig_category":"Prodotti Di Base E Forniture Per Industria Alimentare E Bevande. Forniture Per Attivita' Commerciali Ed Artigianali",
    "sg:phone":"+39 0431 510526",
    "sg:postcode":"30028",
    "sg:province":"Venezia",
    "wof:name":"Sivieri Di Tosato L.c.",
    "wof:placetype":"venue"
},
  "geometry": {"coordinates":[12.9820079803,45.7690658569],"type":"Point"}
}