{
  "type": "Feature",
  "properties": {
    "addr:full":"35020 Casalserugo Casalserugo Padova 35020",
    "addr:postcode":"35020;35020",
    "iso:country":"IT",
    "sg:address":"35020 Casalserugo",
    "sg:city":"Casalserugo",
    "sg:classifiers":[
        {
            "category":"Professional",
            "subcategory":"Printing & Photocopies",
            "type":"Services"
        }
    ],
    "sg:phone":"+39 049 643088",
    "sg:postcode":"35020",
    "sg:province":"Padova",
    "sg:tags":[
        "publishing"
    ],
    "sg:website":"http://www.portobello.it",
    "wof:name":"Portobello Padova",
    "wof:placetype":"venue"
},
  "geometry": {"coordinates":[11.9113826752,45.311882019],"type":"Point"}
}