{
  "type": "Feature",
  "properties": {
    "iso:country":"IT",
    "sg:address":"03100 Frosinone",
    "sg:city":"Frosinone",
    "sg:orig_category":"Lavorazioni Metalli, Stampaggio E Saldatura",
    "sg:phone":"+39 0775 290420",
    "sg:postcode":"03100",
    "sg:province":"Frosinone",
    "wof:name":"Osp Srl",
    "wof:placetype":"venue"
},
  "geometry": {"coordinates":[13.32173,41.636753],"type":"Point"}
}