{
  "type": "Feature",
  "properties": {
    "addr:full":"Via Delle Mura Merlate 1; Gallese",
    "addr:housenumber":"1",
    "addr:street":"Via Delle Mura Merlate",
    "iso:country":"IT",
    "sg:address":"Via Delle Mura Merlate 1; Gallese",
    "sg:classifiers":[
        {
            "category":"Banks & Credit Unions",
            "subcategory":"Bank",
            "type":"Services"
        }
    ],
    "sg:phone":"+39 0761 495014",
    "wof:name":"Banca Di Roma",
    "wof:placetype":"venue"
},
  "geometry": {"coordinates":[12.402404,42.372124],"type":"Point"}
}