{
  "type": "Feature",
  "properties": {
    "iso:country":"IT",
    "sg:address":"00171 Roma",
    "sg:city":"Roma",
    "sg:orig_category":"Materiali E Componenti Elettrotecnici",
    "sg:phone":"+39 06 259 2851",
    "sg:postcode":"00171",
    "sg:province":"Roma",
    "wof:name":"Elettromeccanica Sarda Snc",
    "wof:placetype":"venue"
},
  "geometry": {"coordinates":[12.563227,41.893002],"type":"Point"}
}