{
  "type": "Feature",
  "properties": {
    "iso:country":"IT",
    "sg:address":"95047 Patern\u00f2",
    "sg:orig_category":"Medicali Articoli - Commercio",
    "sg:phone":"+39 095 798 1384",
    "sg:postcode":"95047",
    "sg:province":"Catania",
    "wof:name":"Ronsivalle Orazio",
    "wof:placetype":"venue"
},
  "geometry": {"coordinates":[14.868813,37.559101],"type":"Point"}
}