{
  "type": "Feature",
  "properties": {
    "iso:country":"IT",
    "sg:address":"66020 San Giovanni Teatino",
    "sg:city":"San Giovanni Teatino",
    "sg:orig_category":"Apparecchiature Ed Attrezzature Meccaniche",
    "sg:phone":"+39 085 446 2721",
    "sg:postcode":"66020",
    "sg:province":"Chieti",
    "wof:name":"Centro Aria Compressa Srl",
    "wof:placetype":"venue"
},
  "geometry": {"coordinates":[14.198356,42.442387],"type":"Point"}
}