{
  "type": "Feature",
  "properties": {
    "addr:full":"00165 Roma Roma Roma 00165",
    "addr:postcode":"00165;00165",
    "iso:country":"IT",
    "sg:address":"00165 Roma",
    "sg:city":"Roma",
    "sg:orig_category":"Servizi E Lavori Per Arredamento E Industria Del Legno",
    "sg:phone":"+39 06 3938 7555",
    "sg:postcode":"00165",
    "sg:province":"Roma",
    "sg:website":"http://www.stuarr.com",
    "wof:name":"Formanova Stuarr Srl",
    "wof:placetype":"venue"
},
  "geometry": {"coordinates":[12.443496,41.895996],"type":"Point"}
}