{
  "type": "Feature",
  "properties": {
    "addr:full":"65020 Salle Nuova Salle Pescara 65020",
    "addr:postcode":"65020;65020",
    "iso:country":"IT",
    "sg:address":"65020 Salle Nuova",
    "sg:city":"Salle",
    "sg:orig_category":"Musica",
    "sg:phone":"+39 085 928135",
    "sg:postcode":"65020",
    "sg:province":"Pescara",
    "sg:website":"http://www.doraziostrings.it",
    "wof:name":"D'orazio Strigs",
    "wof:placetype":"venue"
},
  "geometry": {"coordinates":[13.9622039795,42.1779823303],"type":"Point"}
}