{
  "type": "Feature",
  "properties": {
    "addr:full":"38100 Trento Trento Trento 38100",
    "addr:postcode":"38100;38100",
    "iso:country":"IT",
    "sg:address":"38100 Trento",
    "sg:city":"Trento",
    "sg:orig_category":"Servizi Di Magazzinaggio E Movimentazione. Servizi Ausiliari Di Sorveglianza, Manutenzione E Pulizia. Servizi Per Aziende, Manifestazioni E Supporto Agli Scambi Commerciali",
    "sg:phone":"+39 0461 824001",
    "sg:postcode":"38100",
    "sg:province":"Trento",
    "wof:name":"A.p.o.t. Assoc. Produt. Ortofrut. Trentini",
    "wof:placetype":"venue"
},
  "geometry": {"coordinates":[11.115395,46.092079],"type":"Point"}
}