{
  "type": "Feature",
  "properties": {
    "addr:full":"10098 Rivoli Cascine vica Torino 10098",
    "addr:postcode":"10098;10098",
    "iso:country":"IT",
    "sg:address":"10098 Rivoli",
    "sg:city":"Cascine vica",
    "sg:orig_category":"Aspirazione Impianti",
    "sg:phone":"+39 011 959 2841",
    "sg:postcode":"10098",
    "sg:province":"Torino",
    "wof:name":"Ecoindustrie Sas",
    "wof:placetype":"venue"
},
  "geometry": {"coordinates":[7.550313,45.063961],"type":"Point"}
}