{
  "type": "Feature",
  "properties": {
    "iso:country":"IT",
    "sg:address":"00154 Roma",
    "sg:city":"Roma",
    "sg:orig_category":"Serramenti Ed Infissi",
    "sg:phone":"+39 06 513 7141",
    "sg:postcode":"00154",
    "sg:province":"Roma",
    "sg:website":"http://www.paginegialle.it/metalleria",
    "wof:name":"Metalleria Ostiense Di Del Vescovo & C. Snc",
    "wof:placetype":"venue"
},
  "geometry": {"coordinates":[12.481079,41.861313],"type":"Point"}
}