{
  "type": "Feature",
  "properties": {
    "iso:country":"IT",
    "sg:address":"00136 Roma",
    "sg:city":"Roma",
    "sg:classifiers":[
        {
            "category":"Health Services",
            "subcategory":"Health Practitioner",
            "type":"Services"
        }
    ],
    "sg:phone":"+39 06 3973 7995",
    "sg:postcode":"00136",
    "sg:province":"Roma",
    "sg:tags":[
        "medici"
    ],
    "wof:name":"Canali Pierluigi",
    "wof:placetype":"venue"
},
  "geometry": {"coordinates":[12.44324,41.911278],"type":"Point"}
}