{
  "type": "Feature",
  "properties": {
    "addr:full":"Lungomare; Otranto; 73028 Otranto Lecce 73028",
    "addr:postcode":"73028;73028",
    "addr:street":"Lungomare Otranto",
    "iso:country":"IT",
    "sg:address":"Lungomare; Otranto; 73028",
    "sg:city":"Otranto",
    "sg:classifiers":[
        {
            "category":"Banks & Credit Unions",
            "subcategory":"Bank",
            "type":"Services"
        }
    ],
    "sg:phone":"+39 0836 801791",
    "sg:postcode":"73028",
    "sg:province":"Lecce",
    "wof:name":"Rolo Banca 1473 Spa",
    "wof:placetype":"venue"
},
  "geometry": {"coordinates":[18.487394,40.147541],"type":"Point"}
}