{
  "type": "Feature",
  "properties": {
    "addr:full":"27100 Pavia Pavia Pavia 27100",
    "addr:postcode":"27100;27100",
    "iso:country":"IT",
    "sg:address":"27100 Pavia",
    "sg:city":"Pavia",
    "sg:orig_category":"Macchine, Impianti Ed Attrezzature Per Abbigliamento E Pelletterie. Macchine E Impianti Per Attivita' Commerciali Ed Artigianali",
    "sg:phone":"+39 0382 528385",
    "sg:postcode":"27100",
    "sg:province":"Pavia",
    "wof:name":"Centro Assistenza Di Nodari Gilberto",
    "wof:placetype":"venue"
},
  "geometry": {"coordinates":[9.132423,45.189419],"type":"Point"}
}