{
  "type": "Feature",
  "properties": {
    "iso:country":"IT",
    "sg:address":"20099 Sesto San Giovanni",
    "sg:city":"Sesto San Giovanni",
    "sg:orig_category":"Arredo Camera Letto E Complementi",
    "sg:phone":"+39 02 2247 4136",
    "sg:postcode":"20099",
    "sg:province":"Milano",
    "wof:name":"Idea Notte Snc Di Beltrami F.",
    "wof:placetype":"venue"
},
  "geometry": {"coordinates":[9.229418,45.532051],"type":"Point"}
}