{
  "type": "Feature",
  "properties": {
    "iso:country":"IT",
    "sg:address":"Localita' Passovecchio 88900 Crotone",
    "sg:city":"Crotone",
    "sg:classifiers":[
        {
            "category":"Shopping",
            "subcategory":"Computers & Home Electronics",
            "type":"Retail Goods"
        }
    ],
    "sg:phone":"+39 0962 930443",
    "sg:postcode":"88900",
    "sg:province":"Crotone",
    "sg:tags":[
        "electronic",
        "electrical",
        "equipment"
    ],
    "wof:name":"I.c.el. S.a.s.",
    "wof:placetype":"venue"
},
  "geometry": {"coordinates":[17.127079,39.080738],"type":"Point"}
}