{
  "type": "Feature",
  "properties": {
    "iso:country":"IT",
    "sg:address":"00043 Ciampino",
    "sg:city":"Ciampino",
    "sg:orig_category":"Arredo Camera Letto E Complementi",
    "sg:phone":"+39 06 791 3773",
    "sg:postcode":"00043",
    "sg:province":"Roma",
    "wof:name":"Saccheri Emiliano",
    "wof:placetype":"venue"
},
  "geometry": {"coordinates":[12.600946,41.804863],"type":"Point"}
}