{
  "type": "Feature",
  "properties": {
    "iso:country":"IT",
    "sg:address":"35030 Caselle",
    "sg:city":"Caselle",
    "sg:orig_category":"Accessori Dei Mezzi Di Trasporto. Riparazione Dei Mezzi Di Trasporto",
    "sg:phone":"+39 049 898 7117",
    "sg:postcode":"35030",
    "sg:province":"Padova",
    "wof:name":"S.d.m. S.r.l.",
    "wof:placetype":"venue"
},
  "geometry": {"coordinates":[11.857192,45.404293],"type":"Point"}
}