{
  "type": "Feature",
  "properties": {
    "addr:full":"12/1, Via Convertite 48018 Faenza Faenza Ravenna 48018",
    "addr:housenumber":"12 / 1",
    "addr:postcode":"48018;48018",
    "addr:street":"Via Convertite",
    "iso:country":"IT",
    "sg:address":"12/1, Via Convertite 48018 Faenza",
    "sg:city":"Faenza",
    "sg:classifiers":[
        {
            "category":"Food & Beverages",
            "subcategory":"Groceries & Convenience Stores",
            "type":"Retail Goods"
        }
    ],
    "sg:phone":"+39 0546 622721",
    "sg:postcode":"48018",
    "sg:province":"Ravenna",
    "sg:tags":[
        "drink"
    ],
    "wof:name":"Ca.vi.ro",
    "wof:placetype":"venue"
},
  "geometry": {"coordinates":[11.867232,44.307423],"type":"Point"}
}