{
  "type": "Feature",
  "properties": {
    "iso:country":"IT",
    "sg:address":"70032 Bitonto",
    "sg:city":"Bitonto",
    "sg:orig_category":"Oli Alimentari E Frantoi Oleari",
    "sg:phone":"+39 080 375 1118",
    "sg:postcode":"70032",
    "sg:province":"Bari",
    "sg:website":"http://www.ilbosco.it",
    "wof:name":"Il Bosco Di Parisi Francesco",
    "wof:placetype":"venue"
},
  "geometry": {"coordinates":[16.687143,41.108089],"type":"Point"}
}