{
  "type": "Feature",
  "properties": {
    "addr:full":"33097 Spilimbergo Spilimbergo Pordenone 33097",
    "addr:postcode":"33097;33097",
    "iso:country":"IT",
    "sg:address":"33097 Spilimbergo",
    "sg:city":"Spilimbergo",
    "sg:orig_category":"Studi E Consulenze Amministrative, Commerciali E Aziendali. Consulenze Tecniche, Amministrative E Perizie",
    "sg:phone":"+39 0427 2400",
    "sg:postcode":"33097",
    "sg:province":"Pordenone",
    "sg:website":"http://www.nordest9000.it",
    "wof:name":"Nord Est 9000 Srl",
    "wof:placetype":"venue"
},
  "geometry": {"coordinates":[12.654538,45.931217],"type":"Point"}
}