{
  "type": "Feature",
  "properties": {
    "iso:country":"IT",
    "sg:address":"Via Magrom 3 24012 Brembilla",
    "sg:city":"Brembilla",
    "sg:classifiers":[
        {
            "category":"Shopping Center",
            "type":"Public Place"
        }
    ],
    "sg:phone":"+39 0345 99333",
    "sg:postcode":"24012",
    "sg:province":"Bergamo",
    "sg:tags":[
        "turning"
    ],
    "sg:website":"www.lodofin.it",
    "wof:name":"Lodofin Spa",
    "wof:placetype":"venue"
},
  "geometry": {"coordinates":[9.669952,45.694904],"type":"Point"}
}