{
  "type": "Feature",
  "properties": {
    "addr:full":"50127 Firenze Firenze Firenze 50127",
    "addr:postcode":"50127;50127",
    "iso:country":"IT",
    "sg:address":"50127 Firenze",
    "sg:city":"Firenze",
    "sg:orig_category":"Rifiuti Industriali E Speciali Smaltimento E Trattamento - Servizio",
    "sg:phone":"+39 055 436 1453",
    "sg:postcode":"50127",
    "sg:province":"Firenze",
    "wof:name":"Fallani Spurghi Srl",
    "wof:placetype":"venue"
},
  "geometry": {"coordinates":[11.221661,43.790874],"type":"Point"}
}