{
  "type": "Feature",
  "properties": {
    "addr:full":"21047 Saronno Saronno Varese 21047",
    "addr:postcode":"21047;21047",
    "iso:country":"IT",
    "sg:address":"21047 Saronno",
    "sg:city":"Saronno",
    "sg:orig_category":"Chiese Ed Associazioni Religiose",
    "sg:phone":"+39 02 960 2942",
    "sg:postcode":"21047",
    "sg:province":"Varese",
    "wof:name":"Oratorio Parrocchiale Assistente",
    "wof:placetype":"venue"
},
  "geometry": {"coordinates":[8.8199224472,45.8363342285],"type":"Point"}
}