{
  "type": "Feature",
  "properties": {
    "addr:full":"16129 Genova Genova Genova 16129",
    "addr:postcode":"16129;16129",
    "iso:country":"IT",
    "sg:address":"16129 Genova",
    "sg:city":"Genova",
    "sg:orig_category":"Professionisti - Studi E Servizi Ed Associazioni Di Interesse Aziendale. Associazioni Ed Organismi Di Interesse Pubblico",
    "sg:phone":"+39 010 562389",
    "sg:postcode":"16129",
    "sg:province":"Genova",
    "wof:name":"Albo Consulenti Del Lavoro",
    "wof:placetype":"venue"
},
  "geometry": {"coordinates":[8.9467058182,44.3999023438],"type":"Point"}
}