{
  "type": "Feature",
  "properties": {
    "iso:country":"IT",
    "sg:address":"19, Via Imbriani Matteo 26041 Casalmaggiore",
    "sg:city":"Casalmaggiore",
    "sg:classifiers":[
        {
            "category":"Shopping",
            "subcategory":"Clothing, Apparel, & Fashions",
            "type":"Retail Goods"
        }
    ],
    "sg:phone":"+39 39037541326",
    "sg:postcode":"26041",
    "sg:province":"Cremona",
    "sg:tags":[
        "clothes"
    ],
    "wof:name":"Confezioni Giusy (s.n.c.)",
    "wof:placetype":"venue"
},
  "geometry": {"coordinates":[10.026135,45.133499],"type":"Point"}
}