{
  "type": "Feature",
  "properties": {
    "iso:country":"IT",
    "sg:address":"1, Via Brianza 22040 Lurago D'erba",
    "sg:classifiers":[
        {
            "category":"Farming",
            "subcategory":"Livestock Farm",
            "type":"Manufacturing & Wholesale Goods"
        }
    ],
    "sg:phone":"+39 39031699749",
    "sg:postcode":"22040",
    "sg:province":"Como",
    "sg:tags":[
        "agriculture"
    ],
    "wof:name":"Vivai Nord Snc Di A.g. Sartori E C.",
    "wof:placetype":"venue"
},
  "geometry": {"coordinates":[9.229456,45.757355],"type":"Point"}
}