{
  "type": "Feature",
  "properties": {
    "addr:full":"15059 Volpedo Volpedo Alessandria 15059",
    "addr:postcode":"15059;15059",
    "iso:country":"IT",
    "sg:address":"15059 Volpedo",
    "sg:city":"Volpedo",
    "sg:orig_category":"Servizi Ausiliari Per Il Trasporto. Agenzie D'affari E Servizi Commerciali",
    "sg:phone":"+39 0131 80127",
    "sg:postcode":"15059",
    "sg:province":"Alessandria",
    "wof:name":"Stringa Gustavo",
    "wof:placetype":"venue"
},
  "geometry": {"coordinates":[8.981454,44.890129],"type":"Point"}
}