{
  "type": "Feature",
  "properties": {
    "iso:country":"IT",
    "sg:address":"95123 Catania",
    "sg:city":"Catania",
    "sg:orig_category":"Pubblicita', Marketing E Comunicazione",
    "sg:phone":"+39 095 362408",
    "sg:postcode":"95123",
    "sg:province":"Catania",
    "wof:name":"3ggi Pubblicita' Snc",
    "wof:placetype":"venue"
},
  "geometry": {"coordinates":[15.1001157761,37.5713500977],"type":"Point"}
}