{
  "type": "Feature",
  "properties": {
    "iso:country":"IT",
    "sg:address":"00040 Roma",
    "sg:orig_category":"Tempo Libero - Articoli E Forniture. Forniture Per Congressi, Fiere E Manifestazioni. Regalistica Aziendale",
    "sg:phone":"+39 06 7984 1641",
    "sg:postcode":"00040",
    "sg:province":"Roma",
    "wof:name":"Raphael Print Srl",
    "wof:placetype":"venue"
},
  "geometry": {"coordinates":[12.622579,41.806831],"type":"Point"}
}