{
  "type": "Feature",
  "properties": {
    "iso:country":"IT",
    "sg:address":"86039 Termoli",
    "sg:city":"Termoli",
    "sg:orig_category":"Elettronica Professionale E Di Consumo. Automazione E Macchine Per Ufficio. Forniture Industriali Per Prevenzione, Controllo E Sicurezza",
    "sg:phone":"+39 0875 706685",
    "sg:postcode":"86039",
    "sg:province":"Campobasso",
    "wof:name":"La Vigilanza Di Astore Pasquale & C.",
    "wof:placetype":"venue"
},
  "geometry": {"coordinates":[14.999867,41.991184],"type":"Point"}
}