{
  "type": "Feature",
  "properties": {
    "addr:full":"15, Via Butti Enrico Annibale 20158 Milano Milano Milano 20158",
    "addr:postcode":"20158;20158",
    "addr:street":"Via Butti Enrico Annibale",
    "iso:country":"IT",
    "sg:address":"15, Via Butti Enrico Annibale 20158 Milano",
    "sg:city":"Milano",
    "sg:classifiers":[
        {
            "category":"Banks & Credit Unions",
            "subcategory":"Investment Brokerage",
            "type":"Services"
        }
    ],
    "sg:phone":"+39 02 6680 0092",
    "sg:postcode":"20158",
    "sg:province":"Milano",
    "sg:tags":[
        "-",
        "transport",
        "related"
    ],
    "wof:name":"La Generale Srl Centro Distribuzione Merci",
    "wof:placetype":"venue"
},
  "geometry": {"coordinates":[9.174602,45.497108],"type":"Point"}
}