{
  "type": "Feature",
  "properties": {
    "iso:country":"IT",
    "sg:address":"00011 Bagni Di Tivoli",
    "sg:city":"Tivoli",
    "sg:orig_category":"Verniciatura A Fuoco E A Forno",
    "sg:phone":"+39 0774 379262",
    "sg:postcode":"00011",
    "sg:province":"Roma",
    "wof:name":"3c Di Cinque Emma",
    "wof:placetype":"venue"
},
  "geometry": {"coordinates":[12.731491,41.949421],"type":"Point"}
}