{
  "type": "Feature",
  "properties": {
    "iso:country":"IT",
    "sg:address":"Piazza F Guella 1/g, Lizzana, 38068 Rovereto, Tn",
    "sg:city":"Rovereto",
    "sg:classifiers":[
        {
            "category":"Banks & Credit Unions",
            "subcategory":"Bank",
            "type":"Services"
        }
    ],
    "sg:postcode":"38068",
    "sg:province":"Trento",
    "wof:name":"Cassa Rurale Di Lizzana-banca Di Credito Cooperativo Scarl",
    "wof:placetype":"venue"
},
  "geometry": {"coordinates":[11.032068,45.867016],"type":"Point"}
}