{
  "type": "Feature",
  "properties": {
    "iso:country":"IT",
    "sg:address":"61020 Montecchio",
    "sg:city":"Montecchio",
    "sg:orig_category":"Legno E Semilavorati",
    "sg:postcode":"61020",
    "sg:province":"Pesaro E Urbino",
    "wof:name":"Paolini Telemaco",
    "wof:placetype":"venue"
},
  "geometry": {"coordinates":[12.784852,43.856739],"type":"Point"}
}