{
  "type": "Feature",
  "properties": {
    "iso:country":"IT",
    "sg:address":"12081 Beinette",
    "sg:city":"Beinette",
    "sg:orig_category":"Autodemolizioni",
    "sg:phone":"+39 0171 384094",
    "sg:postcode":"12081",
    "sg:province":"Cuneo",
    "wof:name":"Onnimpex Sas Di F. Gianoglio & C.",
    "wof:placetype":"venue"
},
  "geometry": {"coordinates":[7.678666,44.376511],"type":"Point"}
}