{
  "type": "Feature",
  "properties": {
    "addr:full":"50143 Firenze Firenze Firenze 50143",
    "addr:postcode":"50143;50143",
    "iso:country":"IT",
    "sg:address":"50143 Firenze",
    "sg:city":"Firenze",
    "sg:orig_category":"Cartotecnica E Servizi. Forniture Per Attivita' Commerciali Ed Artigianali",
    "sg:phone":"+39 055 732 0707",
    "sg:postcode":"50143",
    "sg:province":"Firenze",
    "wof:name":"Fioralba Di Focardi Fioralba",
    "wof:placetype":"venue"
},
  "geometry": {"coordinates":[11.20988,43.765041],"type":"Point"}
}