{
  "type": "Feature",
  "properties": {
    "addr:full":"91026 Mazara Del Vallo Mazara del Vallo Trapani 91026",
    "addr:postcode":"91026;91026",
    "iso:country":"IT",
    "sg:address":"91026 Mazara Del Vallo",
    "sg:city":"Mazara del Vallo",
    "sg:orig_category":"Serramenti Ed Infissi. Arte Ed Artigianato Artistico. Shopping",
    "sg:phone":"+39 340 256 2190",
    "sg:postcode":"91026",
    "sg:province":"Trapani",
    "wof:name":"Serial Production Pqs Di Pantaleo Michele",
    "wof:placetype":"venue"
},
  "geometry": {"coordinates":[12.594745,37.66412],"type":"Point"}
}