{
  "type": "Feature",
  "properties": {
    "addr:full":"70125 Bari Bari Bari 70125",
    "addr:postcode":"70125;70125",
    "iso:country":"IT",
    "sg:address":"70125 Bari",
    "sg:city":"Bari",
    "sg:orig_category":"Cine-foto-ottica",
    "sg:phone":"+39 080 502 8671",
    "sg:postcode":"70125",
    "sg:province":"Bari",
    "wof:name":"Mancino Giuseppe",
    "wof:placetype":"venue"
},
  "geometry": {"coordinates":[16.876266,41.102627],"type":"Point"}
}