{
  "type": "Feature",
  "properties": {
    "iso:country":"IT",
    "sg:address":"62012 Civitanova Marche",
    "sg:city":"Civitanova Marche",
    "sg:orig_category":"Climatizzazione E Condizionamento, Apparecchiature E Servizi. Elettrotecnica Professionale E Di Consumo",
    "sg:phone":"+39 0733 810580",
    "sg:postcode":"62012",
    "sg:province":"Macerata",
    "wof:name":"Leombruni Termoidraulica",
    "wof:placetype":"venue"
},
  "geometry": {"coordinates":[13.726117,43.305992],"type":"Point"}
}