{
  "type": "Feature",
  "properties": {
    "addr:full":"98071 Capo D'orlando Messina 98071",
    "addr:postcode":"98071;98071",
    "iso:country":"IT",
    "sg:address":"98071 Capo D'orlando",
    "sg:orig_category":"Non-classified Establishments",
    "sg:phone":"+39 0941 901480",
    "sg:postcode":"98071",
    "sg:province":"Messina",
    "wof:name":"Baby Birba Di Letizia Giuseppe",
    "wof:placetype":"venue"
},
  "geometry": {"coordinates":[14.746261,38.150974],"type":"Point"}
}