{
  "type": "Feature",
  "properties": {
    "iso:country":"IT",
    "sg:address":"00182 Roma",
    "sg:city":"Roma",
    "sg:orig_category":"Serramenti Ed Infissi. Prodotti Vari In Metallo",
    "sg:phone":"+39 06 701 3873",
    "sg:postcode":"00182",
    "sg:province":"Roma",
    "wof:name":"Ottoni D'arte",
    "wof:placetype":"venue"
},
  "geometry": {"coordinates":[12.521403,41.888199],"type":"Point"}
}