{
  "type": "Feature",
  "properties": {
    "addr:full":"142, V. Giuseppe Garibaldi 31049 Valdobbiadene Valdobbiadene Treviso 31049",
    "addr:housenumber":"142",
    "addr:postcode":"31049;31049",
    "addr:street":"V. Giuseppe Garibaldi",
    "iso:country":"IT",
    "sg:address":"142, V. Giuseppe Garibaldi 31049 Valdobbiadene",
    "sg:city":"Valdobbiadene",
    "sg:classifiers":[
        {
            "category":"Food & Beverages",
            "subcategory":"Groceries & Convenience Stores",
            "type":"Retail Goods"
        }
    ],
    "sg:phone":"+39 0423 974911",
    "sg:postcode":"31049",
    "sg:province":"Treviso",
    "sg:tags":[
        "drink"
    ],
    "sg:website":"http://www.bortolomiol.com",
    "wof:name":"Bortolomiol Spa",
    "wof:placetype":"venue"
},
  "geometry": {"coordinates":[12.242072,45.666286],"type":"Point"}
}