{
  "type": "Feature",
  "properties": {
    "addr:full":"51039 Quarrata Olmi Pistoia 51039",
    "addr:postcode":"51039;51039",
    "addr:street":"Olmi",
    "iso:country":"IT",
    "sg:address":"51039 Quarrata",
    "sg:city":"Olmi",
    "sg:orig_category":"Cartotecnica E Servizi. Articoli Per Imballaggio E Confezionamento",
    "sg:phone":"+39 0573 718903",
    "sg:postcode":"51039",
    "sg:province":"Pistoia",
    "wof:name":"Imballaggi Vettori Di Vettori Federico",
    "wof:placetype":"venue"
},
  "geometry": {"coordinates":[10.98157,43.883781],"type":"Point"}
}