{
  "type": "Feature",
  "properties": {
    "iso:country":"IT",
    "sg:address":"20052 Monza",
    "sg:city":"Monza",
    "sg:orig_category":"Cucine, Forni E Fornelli Uso Domestico",
    "sg:phone":"+39 039 284 2027",
    "sg:postcode":"20052",
    "sg:province":"Milano",
    "wof:name":"Marelli A.r. Expert",
    "wof:placetype":"venue"
},
  "geometry": {"coordinates":[9.212047,45.50338],"type":"Point"}
}