{
  "type": "Feature",
  "properties": {
    "iso:country":"IT",
    "sg:address":"40, Via Del Trionfo 52100 Arezzo",
    "sg:city":"Arezzo",
    "sg:classifiers":[
        {
            "category":"Food & Beverages",
            "subcategory":"Groceries & Convenience Stores",
            "type":"Retail Goods"
        }
    ],
    "sg:phone":"+39 0575 910011",
    "sg:postcode":"52100",
    "sg:province":"Arezzo",
    "sg:tags":[
        "product",
        "related"
    ],
    "wof:name":"Crocini (s.r.l.)",
    "wof:placetype":"venue"
},
  "geometry": {"coordinates":[11.8705339432,43.4565505981],"type":"Point"}
}