{
  "type": "Feature",
  "properties": {
    "iso:country":"IT",
    "sg:address":"29, V. Del Cantone 50019 Sesto Fiorentino",
    "sg:city":"Sesto Fiorentino",
    "sg:classifiers":[
        {
            "category":"Shopping",
            "subcategory":"Clothing, Apparel, & Fashions",
            "type":"Retail Goods"
        }
    ],
    "sg:phone":"+39 390 553 2421",
    "sg:postcode":"50019",
    "sg:province":"Firenze",
    "sg:tags":[
        "clothes"
    ],
    "sg:website":"http://www.robertocavalli.it",
    "wof:name":"Roberto Cavalli",
    "wof:placetype":"venue"
},
  "geometry": {"coordinates":[11.178014,43.80658],"type":"Point"}
}