{
  "type": "Feature",
  "properties": {
    "addr:full":"6, Via Amburgo 24049 Verdellino Bergamo 24049",
    "addr:postcode":"24049;24049",
    "addr:street":"Via Amburgo",
    "iso:country":"IT",
    "sg:address":"6, Via Amburgo 24049 Verdellino",
    "sg:classifiers":[
        {
            "category":"Utilities",
            "subcategory":"Electric",
            "type":"Services"
        }
    ],
    "sg:phone":"+39 035 482 1951",
    "sg:postcode":"24049",
    "sg:province":"Bergamo",
    "sg:tags":[
        "component",
        "electronic"
    ],
    "wof:name":"Auxilium S.r.l.",
    "wof:placetype":"venue"
},
  "geometry": {"coordinates":[9.669952,45.694904],"type":"Point"}
}