{
  "type": "Feature",
  "properties": {
    "iso:country":"IT",
    "sg:address":"Via Roma 14; Cesana Torinese; 10054",
    "sg:city":"Cesana Torinese",
    "sg:classifiers":[
        {
            "category":"Banks & Credit Unions",
            "subcategory":"Bank",
            "type":"Services"
        }
    ],
    "sg:phone":"+39 0122 89133",
    "sg:postcode":"10054",
    "sg:province":"Torino",
    "wof:name":"Istituto Bancario, San Paolo Di Torino Spa",
    "wof:placetype":"venue"
},
  "geometry": {"coordinates":[6.79374,44.953926],"type":"Point"}
}