{
  "type": "Feature",
  "properties": {
    "addr:full":"62012 Civitanova Marche Civitanova Marche Macerata 62012",
    "addr:postcode":"62012;62012",
    "iso:country":"IT",
    "sg:address":"62012 Civitanova Marche",
    "sg:city":"Civitanova Marche",
    "sg:orig_category":"Forniture Per Abbigliamento E Pelletterie. Forniture Per Attivita' Commerciali Ed Artigianali",
    "sg:phone":"+39 0733 897875",
    "sg:postcode":"62012",
    "sg:province":"Macerata",
    "wof:name":"Mondial Fonderia Snc",
    "wof:placetype":"venue"
},
  "geometry": {"coordinates":[13.6941671371,43.3182144165],"type":"Point"}
}