{
  "type": "Feature",
  "properties": {
    "iso:country":"IT",
    "sg:address":"05034 Ferentillo",
    "sg:city":"Ferentillo",
    "sg:orig_category":"Prodotti E Manufatti In Materie Plastiche. Servizi E Lavori Industria Delle Materie Plastiche",
    "sg:phone":"+39 0744 780769",
    "sg:postcode":"05034",
    "sg:province":"Terni",
    "sg:website":"http://www.cfplast.com",
    "wof:name":"Cf Srl",
    "wof:placetype":"venue"
},
  "geometry": {"coordinates":[12.8284769058,42.6264305115],"type":"Point"}
}