{
  "type": "Feature",
  "properties": {
    "addr:full":"03019 Supino Supino Frosinone 03019",
    "addr:postcode":"03019;03019",
    "iso:country":"IT",
    "sg:address":"03019 Supino",
    "sg:city":"Supino",
    "sg:orig_category":"Attrezzature E Forniture Per Officine Riparazione E Servizi Ausiliari",
    "sg:phone":"+39 0775 227254",
    "sg:postcode":"03019",
    "sg:province":"Frosinone",
    "wof:name":"Palazzolo Andrea",
    "wof:placetype":"venue"
},
  "geometry": {"coordinates":[13.232158,41.624603],"type":"Point"}
}