{
  "type": "Feature",
  "properties": {
    "addr:full":"42100 Reggio Emilia Reggio Nell'Emilia 42100",
    "addr:postcode":"42100;42100",
    "iso:country":"IT",
    "sg:address":"42100 Reggio Emilia",
    "sg:orig_category":"Prodotti Finiti Stampati. Servizi Editoriali. Tempo Libero - Articoli E Forniture",
    "sg:phone":"+39 0522 924206",
    "sg:postcode":"42100",
    "sg:province":"Reggio Nell'Emilia",
    "wof:name":"Geomedia (s.n.c.)",
    "wof:placetype":"venue"
},
  "geometry": {"coordinates":[10.6365041733,44.7122650146],"type":"Point"}
}