{
  "type": "Feature",
  "properties": {
    "addr:full":"23030 Livigno Livigno Sondrio 23030",
    "addr:postcode":"23030;23030",
    "iso:country":"IT",
    "sg:address":"23030 Livigno",
    "sg:city":"Livigno",
    "sg:orig_category":"Pneumatici - Commercio E Riparazione",
    "sg:phone":"+39 0342 996724",
    "sg:postcode":"23030",
    "sg:province":"Sondrio",
    "wof:name":"B.b. Gomme Snc",
    "wof:placetype":"venue"
},
  "geometry": {"coordinates":[10.1390285492,46.5404129028],"type":"Point"}
}