{
  "type": "Feature",
  "properties": {
    "iso:country":"IT",
    "sg:address":"09018 Sarroch",
    "sg:city":"Sarroch",
    "sg:orig_category":"Carpenterie Ferro",
    "sg:phone":"+39 070 900426",
    "sg:postcode":"09018",
    "sg:province":"Cagliari",
    "wof:name":"Sar.co.mi. Soc.coop.r.l.",
    "wof:placetype":"venue"
},
  "geometry": {"coordinates":[8.990794,39.077259],"type":"Point"}
}