{
  "type": "Feature",
  "properties": {
    "iso:country":"IT",
    "sg:address":"Viale Della Liberta; Aversa; 81031",
    "sg:city":"Aversa",
    "sg:classifiers":[
        {
            "category":"Banks & Credit Unions",
            "subcategory":"Bank",
            "type":"Services"
        }
    ],
    "sg:phone":"+39 081 503 1624",
    "sg:postcode":"81031",
    "sg:province":"Caserta",
    "wof:name":"Credito Italiano Spa",
    "wof:placetype":"venue"
},
  "geometry": {"coordinates":[14.212028,40.979271],"type":"Point"}
}