{
  "type": "Feature",
  "properties": {
    "addr:full":"Via Canova ,4/6 36055 Nove Nove Vicenza 36055",
    "addr:housenumber":"4 / 6",
    "addr:postcode":"36055;36055",
    "addr:street":"Via Canova",
    "iso:country":"IT",
    "sg:address":"Via Canova ,4/6 36055 Nove",
    "sg:city":"Nove",
    "sg:classifiers":[
        {
            "category":"Home & Garden",
            "subcategory":"Household Appliances",
            "type":"Retail Goods"
        }
    ],
    "sg:phone":"+39 0424 590646",
    "sg:postcode":"36055",
    "sg:province":"Vicenza",
    "sg:tags":[
        "implement",
        "gardening",
        "tool"
    ],
    "sg:website":"www.handyofficinepiazza.it",
    "wof:name":"Officine Piazza Srl",
    "wof:placetype":"venue"
},
  "geometry": {"coordinates":[11.674691,45.711826],"type":"Point"}
}