{
  "type": "Feature",
  "properties": {
    "iso:country":"IT",
    "sg:address":"37122 Verona",
    "sg:city":"Verona",
    "sg:orig_category":"Servizi Ausiliari Dei Mezzi Di Trasporto",
    "sg:phone":"+39 045 596032",
    "sg:postcode":"37122",
    "sg:province":"Verona",
    "wof:name":"Furri Andrea",
    "wof:placetype":"venue"
},
  "geometry": {"coordinates":[10.994007,45.428917],"type":"Point"}
}