{
  "type": "Feature",
  "properties": {
    "addr:full":"Via Morandi 6 40026 Imola Imola Bologna 40026",
    "addr:housenumber":"6",
    "addr:postcode":"40026;40026",
    "addr:street":"Via Morandi",
    "iso:country":"IT",
    "sg:address":"Via Morandi 6 40026 Imola",
    "sg:city":"Imola",
    "sg:classifiers":[
        {
            "category":"Banks & Credit Unions",
            "subcategory":"Investment Brokerage",
            "type":"Services"
        }
    ],
    "sg:phone":"+39 0542 641738",
    "sg:postcode":"40026",
    "sg:province":"Bologna",
    "sg:tags":[
        "hand-carts",
        "truck",
        "transporting",
        "devices",
        "hand"
    ],
    "sg:website":"www.filomarket.it",
    "wof:name":"Filomarket Srl",
    "wof:placetype":"venue"
},
  "geometry": {"coordinates":[11.719091,44.371742],"type":"Point"}
}