{
  "type": "Feature",
  "properties": {
    "addr:full":"72100 Brindisi Brindisi Brindisi 72100",
    "addr:postcode":"72100;72100",
    "iso:country":"IT",
    "sg:address":"72100 Brindisi",
    "sg:city":"Brindisi",
    "sg:orig_category":"Arredamenti - Vendita Al Dettaglio",
    "sg:phone":"+39 0831 526132",
    "sg:postcode":"72100",
    "sg:province":"Brindisi",
    "wof:name":"Adriatica Arredamenti Srl",
    "wof:placetype":"venue"
},
  "geometry": {"coordinates":[17.932384,40.634602],"type":"Point"}
}