{
  "type": "Feature",
  "properties": {
    "iso:country":"IT",
    "sg:address":"53048 Sinalunga",
    "sg:city":"Sinalunga",
    "sg:orig_category":"Apparecchiature Ed Attrezzature Meccaniche",
    "sg:phone":"+39 0577 632228",
    "sg:postcode":"53048",
    "sg:province":"Siena",
    "wof:name":"Effe Emme Snc",
    "wof:placetype":"venue"
},
  "geometry": {"coordinates":[11.754844,43.219986],"type":"Point"}
}