{
  "type": "Feature",
  "properties": {
    "iso:country":"IT",
    "sg:address":"00134 Roma",
    "sg:city":"Roma",
    "sg:orig_category":"Forniture Per Agricoltura E Zootecnia",
    "sg:phone":"+39 06 7130 0193",
    "sg:postcode":"00134",
    "sg:province":"Roma",
    "wof:name":"Kronens Italia Di Allegri Attilio Sas",
    "wof:placetype":"venue"
},
  "geometry": {"coordinates":[12.5048074722,41.8625106812],"type":"Point"}
}