{
  "type": "Feature",
  "properties": {
    "addr:full":"Via Parini 18 40033 Casalecchio Di Reno Casalecchio di Reno Bologna 40033",
    "addr:housenumber":"18",
    "addr:postcode":"40033;40033",
    "addr:street":"Via Parini;Di Reno",
    "iso:country":"IT",
    "sg:address":"Via Parini 18 40033 Casalecchio Di Reno",
    "sg:city":"Casalecchio di Reno",
    "sg:classifiers":[
        {
            "category":"Military Area",
            "subcategory":"Air Force Base",
            "type":"Public Place"
        }
    ],
    "sg:phone":"+39 051 590490",
    "sg:postcode":"40033",
    "sg:province":"Bologna",
    "sg:tags":[
        "helical",
        "gear"
    ],
    "sg:website":"www.iii.it/itq",
    "wof:name":"Ital Gear Srl",
    "wof:placetype":"venue"
},
  "geometry": {"coordinates":[11.261971,44.490891],"type":"Point"}
}