{
  "type": "Feature",
  "properties": {
    "addr:full":"20159 Milano Milano Milano 20159",
    "addr:postcode":"20159;20159",
    "iso:country":"IT",
    "sg:address":"20159 Milano",
    "sg:city":"Milano",
    "sg:orig_category":"Professionisti - Studi E Servizi Ed Associazioni Di Interesse Aziendale. Associazioni Ed Organismi Di Interesse Pubblico",
    "sg:phone":"+39 02 6680 0032",
    "sg:postcode":"20159",
    "sg:province":"Milano",
    "wof:name":"Partito Della Rifondazione Comunista",
    "wof:placetype":"venue"
},
  "geometry": {"coordinates":[9.1865978241,45.4860305786],"type":"Point"}
}