{
  "type": "Feature",
  "properties": {
    "iso:country":"IT",
    "sg:address":"40017 San Giovanni In Persiceto",
    "sg:city":"San Giovanni in Persiceto",
    "sg:orig_category":"Accessori Moda D'abbigliamento. Forniture Per Abbigliamento E Pelletterie",
    "sg:phone":"+39 051 826075",
    "sg:postcode":"40017",
    "sg:province":"Bologna",
    "sg:website":"http://www.arem.it",
    "wof:name":"Arem Due Srl",
    "wof:placetype":"venue"
},
  "geometry": {"coordinates":[11.209474,44.6632],"type":"Point"}
}