{
  "type": "Feature",
  "properties": {
    "addr:full":"28068 Romentino Romentino Novara 28068",
    "addr:postcode":"28068;28068",
    "iso:country":"IT",
    "sg:address":"28068 Romentino",
    "sg:city":"Romentino",
    "sg:orig_category":"Servizi E Lavori Per Ecologia E Smaltimento Rifiuti. Servizi Ausiliari Di Analisi, Controllo E Ricerca",
    "sg:phone":"+39 0321 860707",
    "sg:postcode":"28068",
    "sg:province":"Novara",
    "wof:name":"Salerno Giuseppe",
    "wof:placetype":"venue"
},
  "geometry": {"coordinates":[8.718015,45.462563],"type":"Point"}
}