{
  "type": "Feature",
  "properties": {
    "iso:country":"IT",
    "sg:address":"31040 Volpago Del Montello",
    "sg:city":"Volpago del Montello",
    "sg:orig_category":"Macchine E Forniture Per Arredamento E Industria Del Legno",
    "sg:phone":"+39 0423 8774",
    "sg:postcode":"31040",
    "sg:province":"Treviso",
    "wof:name":"Tecnopool Srl",
    "wof:placetype":"venue"
},
  "geometry": {"coordinates":[12.155796,45.771446],"type":"Point"}
}