{
  "type": "Feature",
  "properties": {
    "addr:full":"70021 Acquaviva Delle Fonti Acquaviva delle Fonti Bari 70021",
    "addr:postcode":"70021;70021",
    "iso:country":"IT",
    "sg:address":"70021 Acquaviva Delle Fonti",
    "sg:city":"Acquaviva delle Fonti",
    "sg:classifiers":[
        {
            "category":"Banks & Credit Unions",
            "subcategory":"Financial Services",
            "type":"Services"
        }
    ],
    "sg:phone":"+39 080 775355",
    "sg:postcode":"70021",
    "sg:province":"Bari",
    "sg:tags":[
        "articles",
        "product",
        "plastics",
        "industry",
        "work",
        "plastic"
    ],
    "wof:name":"Ricicplast Srl",
    "wof:placetype":"venue"
},
  "geometry": {"coordinates":[16.8629932404,40.8821678162],"type":"Point"}
}