{
  "type": "Feature",
  "properties": {
    "iso:country":"IT",
    "sg:address":"34, Via Umberto I 33038 San Daniele Del Friuli",
    "sg:city":"San Daniele del Friuli",
    "sg:classifiers":[
        {
            "category":"Shopping",
            "subcategory":"Computers & Home Electronics",
            "type":"Retail Goods"
        }
    ],
    "sg:phone":"+39 0432 945711",
    "sg:postcode":"33038",
    "sg:province":"Udine",
    "sg:tags":[
        "electronic",
        "electrical",
        "equipment"
    ],
    "wof:name":"Giovanni Vignuda Automazioni S.r.l.",
    "wof:placetype":"venue"
},
  "geometry": {"coordinates":[13.009972,46.158936],"type":"Point"}
}