{
  "type": "Feature",
  "properties": {
    "addr:full":"81100 Caserta Caserta Caserta 81100",
    "addr:postcode":"81100;81100",
    "iso:country":"IT",
    "sg:address":"81100 Caserta",
    "sg:city":"Caserta",
    "sg:orig_category":"Arredo Cucina Ed Elettrodomestici. Elettrodomestici",
    "sg:phone":"+39 0823 443415",
    "sg:postcode":"81100",
    "sg:province":"Caserta",
    "wof:name":"Audiotime Sas",
    "wof:placetype":"venue"
},
  "geometry": {"coordinates":[14.333961,41.075108],"type":"Point"}
}