{
  "type": "Feature",
  "properties": {
    "iso:country":"IT",
    "sg:address":"24030 Brembate Di Sopra",
    "sg:city":"Brembate di Sopra",
    "sg:orig_category":"Alberghi E Strutture Extra Alberghiere. Ospedali E Servizi Sanitari",
    "sg:phone":"+39 035 620560",
    "sg:postcode":"24030",
    "sg:province":"Bergamo",
    "wof:name":"Comune Di Brembate Sopra",
    "wof:placetype":"venue"
},
  "geometry": {"coordinates":[9.587069,45.720642],"type":"Point"}
}