{
  "type": "Feature",
  "properties": {
    "iso:country":"IT",
    "sg:address":"Via Pievaiola 06064 Panicale",
    "sg:city":"Panicale",
    "sg:classifiers":[
        {
            "category":"Utilities",
            "subcategory":"Electric",
            "type":"Services"
        }
    ],
    "sg:phone":"+39 39075835371",
    "sg:postcode":"06064",
    "sg:province":"Perugia",
    "sg:tags":[
        "component",
        "electronic"
    ],
    "wof:name":"Trafomec S.p.a.",
    "wof:placetype":"venue"
},
  "geometry": {"coordinates":[12.208618,43.026779],"type":"Point"}
}