{
  "type": "Feature",
  "properties": {
    "iso:country":"IT",
    "sg:address":"20010 Boffalora Sopra Ticino",
    "sg:city":"Boffalora sopra Ticino",
    "sg:orig_category":"Forniture Per Abbigliamento E Pelletterie. Forniture E Materiali Per Imballaggio E Confezionamento",
    "sg:phone":"+39 02 975 6028",
    "sg:postcode":"20010",
    "sg:province":"Milano",
    "wof:name":"Corderie Pastori Srl",
    "wof:placetype":"venue"
},
  "geometry": {"coordinates":[8.848033905,45.4680213928],"type":"Point"}
}