{
  "type": "Feature",
  "properties": {
    "addr:full":"20093 Cologno Monzese Cologno Monzese Milano 20093",
    "addr:postcode":"20093;20093",
    "iso:country":"IT",
    "sg:address":"20093 Cologno Monzese",
    "sg:city":"Cologno Monzese",
    "sg:orig_category":"Ceramiche: Prodotti E Lavorazioni",
    "sg:phone":"+39 02 253 2826",
    "sg:postcode":"20093",
    "sg:province":"Milano",
    "sg:website":"http://www.paginegialle.it/rigoldisas",
    "wof:name":"Rigoldi Sas",
    "wof:placetype":"venue"
},
  "geometry": {"coordinates":[9.270267,45.535931],"type":"Point"}
}