{
  "type": "Feature",
  "properties": {
    "iso:country":"IT",
    "sg:address":"32036 Sedico",
    "sg:city":"Sedico",
    "sg:orig_category":"Minuterie Metalliche E Ferramenta",
    "sg:phone":"+39 0437 83606",
    "sg:postcode":"32036",
    "sg:province":"Belluno",
    "sg:website":"http://www.eyewear.net/comp/decolletages/index.html",
    "wof:name":"Roldo Mario",
    "wof:placetype":"venue"
},
  "geometry": {"coordinates":[12.1171751022,46.1373405457],"type":"Point"}
}