{
  "type": "Feature",
  "properties": {
    "iso:country":"IT",
    "sg:address":"82030 Ponte",
    "sg:city":"Ponte",
    "sg:orig_category":"Forniture Per Edilizia E Lavori Pubblici",
    "sg:phone":"+39 0824 875189",
    "sg:postcode":"82030",
    "sg:province":"Benevento",
    "sg:website":"http://www.carsrl.com",
    "wof:name":"Car Segnaletica Stradale Srl",
    "wof:placetype":"venue"
},
  "geometry": {"coordinates":[14.6935396194,41.213973999],"type":"Point"}
}