{
  "type": "Feature",
  "properties": {
    "iso:country":"IT",
    "sg:address":"Via Salvatore Quasimodo 20010 Santo Stefano Ticino",
    "sg:city":"Santo Stefano Ticino",
    "sg:classifiers":[
        {
            "category":"Manufacturing",
            "subcategory":"Rubber & Plastics",
            "type":"Manufacturing & Wholesale Goods"
        }
    ],
    "sg:phone":"+39 39029778188",
    "sg:postcode":"20010",
    "sg:province":"Milano",
    "wof:name":"Cerri Luigi E C. Sas",
    "wof:placetype":"venue"
},
  "geometry": {"coordinates":[8.9398126602,45.4599494934],"type":"Point"}
}