{
  "type": "Feature",
  "properties": {
    "iso:country":"IT",
    "sg:address":"20060 Cassina De' Pecchi",
    "sg:orig_category":"Antifurto",
    "sg:phone":"+39 02 952 1099",
    "sg:postcode":"20060",
    "sg:province":"Milano",
    "wof:name":"Fumagalli Giulio",
    "wof:placetype":"venue"
},
  "geometry": {"coordinates":[9.365531,45.519764],"type":"Point"}
}