{
  "type": "Feature",
  "properties": {
    "iso:country":"IT",
    "sg:address":"48, Via G.b. Fattori 42044 Gualtieri",
    "sg:classifiers":[
        {
            "category":"Food & Beverages",
            "subcategory":"Groceries & Convenience Stores",
            "type":"Retail Goods"
        }
    ],
    "sg:phone":"+39 0522 829580",
    "sg:postcode":"42044",
    "sg:province":"Reggio Nell'Emilia",
    "sg:tags":[
        "drink"
    ],
    "wof:name":"Bre - Ca (s.r.l.)",
    "wof:placetype":"venue"
},
  "geometry": {"coordinates":[10.627794,44.696228],"type":"Point"}
}