{
  "type": "Feature",
  "properties": {
    "iso:country":"IT",
    "sg:address":"1945, Strada Statale Adriatica 47042 Cesenatico",
    "sg:city":"Cesenatico",
    "sg:classifiers":[
        {
            "category":"Utilities",
            "subcategory":"Telephone",
            "type":"Services"
        }
    ],
    "sg:phone":"+39 39054783843",
    "sg:postcode":"47042",
    "sg:province":"Forl\u00ec-Cesena",
    "sg:tags":[
        "telecommunication"
    ],
    "wof:name":"Mazzeo (s.r.l.)",
    "wof:placetype":"venue"
},
  "geometry": {"coordinates":[12.388108,44.203869],"type":"Point"}
}