{
  "type": "Feature",
  "properties": {
    "iso:country":"IT",
    "sg:address":"27/1, Via Pagliarola 41014 Castelvetro",
    "sg:classifiers":[
        {
            "category":"Farming",
            "subcategory":"Livestock Farm",
            "type":"Manufacturing & Wholesale Goods"
        }
    ],
    "sg:phone":"+39 39059791427",
    "sg:postcode":"41014",
    "sg:province":"Modena",
    "sg:tags":[
        "agriculture"
    ],
    "wof:name":"La Fortezza Azienda Agricola S.s.",
    "wof:placetype":"venue"
},
  "geometry": {"coordinates":[10.904061,44.508011],"type":"Point"}
}