{
  "type": "Feature",
  "properties": {
    "addr:full":"00138 Roma Roma Roma 00138",
    "addr:postcode":"00138;00138",
    "iso:country":"IT",
    "sg:address":"00138 Roma",
    "sg:city":"Roma",
    "sg:orig_category":"Attrezzature E Forniture Per Officine Riparazione E Servizi Ausiliari",
    "sg:phone":"+39 06 888 7520",
    "sg:postcode":"00138",
    "sg:province":"Roma",
    "wof:name":"Carema Snc",
    "wof:placetype":"venue"
},
  "geometry": {"coordinates":[12.527212,42.006016],"type":"Point"}
}