{
  "type": "Feature",
  "properties": {
    "addr:full":"Viale Dell' Artigianato 24062 Costa Volpino Costa Volpino Bergamo 24062",
    "addr:housenumber":"volpino",
    "addr:postcode":"24062;24062",
    "addr:street":"Viale Dell ' Artigianato",
    "iso:country":"IT",
    "sg:address":"Viale Dell' Artigianato 24062 Costa Volpino",
    "sg:city":"Costa Volpino",
    "sg:classifiers":[
        {
            "category":"Personal",
            "subcategory":"Shoe Repair & Shine",
            "type":"Services"
        }
    ],
    "sg:phone":"+39 39035972955",
    "sg:postcode":"24062",
    "sg:province":"Bergamo",
    "sg:tags":[
        "leather"
    ],
    "wof:name":"P.m.i. Di Bonetti Gianbattista & C.(s.a.s.)",
    "wof:placetype":"venue"
},
  "geometry": {"coordinates":[10.107443,45.817554],"type":"Point"}
}