{
  "type": "Feature",
  "properties": {
    "iso:country":"IT",
    "sg:address":"24067 Sarnico",
    "sg:city":"Sarnico",
    "sg:orig_category":"Articoli Medico-sanitari Ed Ortopedici",
    "sg:phone":"+39 035 914140",
    "sg:postcode":"24067",
    "sg:province":"Bergamo",
    "wof:name":"Centro Ottico Sarnico Sas",
    "wof:placetype":"venue"
},
  "geometry": {"coordinates":[9.743498,45.738541],"type":"Point"}
}