{
  "type": "Feature",
  "properties": {
    "addr:full":"26, Via Delle Industrie 06083 Bastia Bastia Perugia 06083",
    "addr:postcode":"06083;06083",
    "addr:street":"Via Delle Industrie",
    "iso:country":"IT",
    "sg:address":"26, Via Delle Industrie 06083 Bastia",
    "sg:city":"Bastia",
    "sg:classifiers":[
        {
            "category":"Bars & Pubs",
            "subcategory":"Nightclub",
            "type":"Food & Drink"
        }
    ],
    "sg:phone":"+39 075 801 1025",
    "sg:postcode":"06083",
    "sg:province":"Perugia",
    "sg:tags":[
        "cake",
        "bread"
    ],
    "wof:name":"Meschini (s.r.l.)",
    "wof:placetype":"venue"
},
  "geometry": {"coordinates":[12.548079,43.05825],"type":"Point"}
}