{
  "type": "Feature",
  "properties": {
    "iso:country":"IT",
    "sg:address":"20092 Cinisello Balsamo",
    "sg:city":"Cinisello Balsamo",
    "sg:orig_category":"Telecomunicazioni E Telefonia, Impianti, Apparecchi E Servizi",
    "sg:phone":"+39 02 660721",
    "sg:postcode":"20092",
    "sg:province":"Milano",
    "sg:website":"http://www.vobis.it",
    "wof:name":"Vobis Microcomputer Spa",
    "wof:placetype":"venue"
},
  "geometry": {"coordinates":[9.224836,45.535404],"type":"Point"}
}