{
  "type": "Feature",
  "properties": {
    "addr:full":"Via Del Maccabreccia 13 40012 Calderara Di Reno Calderara di Reno Bologna 40012",
    "addr:housenumber":"13",
    "addr:postcode":"40012;40012",
    "addr:street":"Via Del Maccabreccia",
    "iso:country":"IT",
    "sg:address":"Via Del Maccabreccia 13 40012 Calderara Di Reno",
    "sg:city":"Calderara di Reno",
    "sg:classifiers":[
        {
            "category":"Bars & Pubs",
            "subcategory":"Hookah Bar",
            "type":"Food & Drink"
        }
    ],
    "sg:phone":"+39 051 726207",
    "sg:postcode":"40012",
    "sg:province":"Bologna",
    "sg:tags":[
        "steel",
        "punch",
        "knife"
    ],
    "sg:website":"www.molinati.com",
    "wof:name":"Orlando Molinati & C. Sas",
    "wof:placetype":"venue"
},
  "geometry": {"coordinates":[11.2961044312,44.5431785583],"type":"Point"}
}