{
  "type": "Feature",
  "properties": {
    "iso:country":"IT",
    "sg:address":"Via G. Di Vittorio 43 59021 Vaiano",
    "sg:city":"Vaiano",
    "sg:classifiers":[
        {
            "category":"Manufacturing",
            "subcategory":"Building Materials",
            "type":"Manufacturing & Wholesale Goods"
        }
    ],
    "sg:phone":"+39 0574 946400",
    "sg:postcode":"59021",
    "sg:province":"Prato",
    "sg:tags":[
        "fleece",
        "fabric"
    ],
    "wof:name":"Tessuti Industriali Srl",
    "wof:placetype":"venue"
},
  "geometry": {"coordinates":[11.1294002533,43.9550857544],"type":"Point"}
}