{
  "type": "Feature",
  "properties": {
    "iso:country":"IT",
    "sg:address":"21, Via Dei Chiosi 20040 Cavenago Di Brianza",
    "sg:city":"Cavenago di Brianza",
    "sg:classifiers":[
        {
            "category":"Shopping",
            "subcategory":"Computers & Home Electronics",
            "type":"Retail Goods"
        }
    ],
    "sg:phone":"+39 02 9533 9516",
    "sg:postcode":"20040",
    "sg:province":"Milano",
    "sg:tags":[
        "electronic",
        "electrical",
        "equipment"
    ],
    "wof:name":"Ortea S.p.a.",
    "wof:placetype":"venue"
},
  "geometry": {"coordinates":[9.409551,45.579952],"type":"Point"}
}