{
  "type": "Feature",
  "properties": {
    "iso:country":"IT",
    "sg:address":"20131 Milano",
    "sg:city":"Milano",
    "sg:orig_category":"Ospedali E Servizi Sanitari",
    "sg:phone":"+39 02 284 1523",
    "sg:postcode":"20131",
    "sg:province":"Milano",
    "wof:name":"Zipoli Marisa",
    "wof:placetype":"venue"
},
  "geometry": {"coordinates":[9.229666,45.489029],"type":"Point"}
}