{
  "type": "Feature",
  "properties": {
    "iso:country":"IT",
    "sg:address":"Via Cristoforo Colombo 6 29010 Sarmato",
    "sg:city":"Sarmato",
    "sg:classifiers":[
        {
            "category":"Manufacturing",
            "subcategory":"Rubber & Plastics",
            "type":"Manufacturing & Wholesale Goods"
        }
    ],
    "sg:phone":"+39 0523 886243",
    "sg:postcode":"29010",
    "sg:province":"Piacenza",
    "sg:tags":[
        "material"
    ],
    "wof:name":"Braghieri Plastic Srl",
    "wof:placetype":"venue"
},
  "geometry": {"coordinates":[9.4770832062,45.0573501587],"type":"Point"}
}