{
  "type": "Feature",
  "properties": {
    "addr:full":"30020 Noventa Di Piave Noventa di Piave Venezia 30020",
    "addr:postcode":"30020;30020",
    "iso:country":"IT",
    "sg:address":"30020 Noventa Di Piave",
    "sg:city":"Noventa di Piave",
    "sg:orig_category":"Prodotti Chimici Di Base. Forniture Per Attivita' Industriali",
    "sg:phone":"+39 0421 65561",
    "sg:postcode":"30020",
    "sg:province":"Venezia",
    "wof:name":"Vercoll S.r.l.",
    "wof:placetype":"venue"
},
  "geometry": {"coordinates":[12.5527620316,45.6762123108],"type":"Point"}
}