{
  "type": "Feature",
  "properties": {
    "iso:country":"IT",
    "sg:address":"56040 Castellina Marittima",
    "sg:city":"Castellina Marittima",
    "sg:orig_category":"Animali Domestici - Allevamento E Addestramento",
    "sg:phone":"+39 050 696014",
    "sg:postcode":"56040",
    "sg:province":"Pisa",
    "wof:name":"Allevamento Di Spicciano",
    "wof:placetype":"venue"
},
  "geometry": {"coordinates":[10.536585,43.411217],"type":"Point"}
}