{
  "type": "Feature",
  "properties": {
    "iso:country":"IT",
    "sg:address":"25030 Roncadelle",
    "sg:city":"Roncadelle",
    "sg:orig_category":"Articoli Da Regalo. Arte Ed Artigianato Artistico. Shopping",
    "sg:phone":"+39 030 258 7033",
    "sg:postcode":"25030",
    "sg:province":"Brescia",
    "wof:name":"Ardin Snc",
    "wof:placetype":"venue"
},
  "geometry": {"coordinates":[10.149697,45.522095],"type":"Point"}
}