{
  "type": "Feature",
  "properties": {
    "iso:country":"IT",
    "sg:address":"70051 Barletta",
    "sg:city":"Barletta",
    "sg:orig_category":"Calzature, Pelletterie E Pelli",
    "sg:phone":"+39 0883 333802",
    "sg:postcode":"70051",
    "sg:province":"Bari",
    "wof:name":"Calzaturificio Exelle Di Cozzi Daniele",
    "wof:placetype":"venue"
},
  "geometry": {"coordinates":[16.783525,41.084335],"type":"Point"}
}