{
  "type": "Feature",
  "properties": {
    "iso:country":"IT",
    "sg:address":"52044 Cortona",
    "sg:city":"Cortona",
    "sg:orig_category":"Ospedali E Servizi Sanitari",
    "sg:phone":"+39 0575 605033",
    "sg:postcode":"52044",
    "sg:province":"Arezzo",
    "wof:name":"Paganini Claudio",
    "wof:placetype":"venue"
},
  "geometry": {"coordinates":[11.986127,43.275177],"type":"Point"}
}