{
  "type": "Feature",
  "properties": {
    "iso:country":"IT",
    "sg:address":"10093 Collegno",
    "sg:city":"Collegno",
    "sg:orig_category":"Impiantistica E Prodotti Tecnologici Per Edilizia. Forniture Industriali Per Prevenzione, Controllo E Sicurezza",
    "sg:phone":"+39 011 781998",
    "sg:postcode":"10093",
    "sg:province":"Torino",
    "wof:name":"Uni Mas Snc",
    "wof:placetype":"venue"
},
  "geometry": {"coordinates":[7.581889,45.073059],"type":"Point"}
}