{
  "type": "Feature",
  "properties": {
    "iso:country":"IT",
    "sg:address":"Via Verona 5 20063 Cernusco Sul Naviglio",
    "sg:city":"Cernusco sul Naviglio",
    "sg:classifiers":[
        {
            "category":"Home & Garden",
            "subcategory":"Home Furnishings",
            "type":"Retail Goods"
        }
    ],
    "sg:phone":"+39 02 9210 2318",
    "sg:postcode":"20063",
    "sg:province":"Milano",
    "sg:tags":[
        "bathroom",
        "wc",
        "fitting"
    ],
    "wof:name":"Mecaplast Commerciali Srl",
    "wof:placetype":"venue"
},
  "geometry": {"coordinates":[9.294978,45.52977],"type":"Point"}
}