{
  "type": "Feature",
  "properties": {
    "addr:full":"Viale Pieve, 15/17/19 46040 Cavriana Cavriana Mantova 46040",
    "addr:housenumber":"15 / 17 / 19",
    "addr:postcode":"46040;46040",
    "addr:street":"Viale Pieve",
    "iso:country":"IT",
    "sg:address":"Viale Pieve, 15/17/19 46040 Cavriana",
    "sg:city":"Cavriana",
    "sg:classifiers":[
        {
            "category":"Banks & Credit Unions",
            "subcategory":"Investment Brokerage",
            "type":"Services"
        }
    ],
    "sg:phone":"+39 0376 806125",
    "sg:postcode":"46040",
    "sg:province":"Mantova",
    "sg:tags":[
        "sanitary",
        "fixture",
        "accessory"
    ],
    "sg:website":"www.visentin.it",
    "wof:name":"Fais Italia Spa",
    "wof:placetype":"venue"
},
  "geometry": {"coordinates":[10.797698,45.160366],"type":"Point"}
}