{
  "type": "Feature",
  "properties": {
    "addr:full":"12100 Cuneo Cuneo Cuneo 12100",
    "addr:postcode":"12100;12100",
    "iso:country":"IT",
    "sg:address":"12100 Cuneo",
    "sg:city":"Cuneo",
    "sg:orig_category":"Petroli, Gas E Combustibili",
    "sg:phone":"+39 0171 411084",
    "sg:postcode":"12100",
    "sg:province":"Cuneo",
    "wof:name":"Salca Srl",
    "wof:placetype":"venue"
},
  "geometry": {"coordinates":[7.5495724678,44.4149475098],"type":"Point"}
}