{
  "type": "Feature",
  "properties": {
    "addr:full":"90129 Palermo Palermo Palermo 90129",
    "addr:postcode":"90129;90129",
    "iso:country":"IT",
    "sg:address":"90129 Palermo",
    "sg:city":"Palermo",
    "sg:orig_category":"Prodotti Chimici Di Base. Forniture Per Attivita' Industriali",
    "sg:phone":"+39 091 668 7103",
    "sg:postcode":"90129",
    "sg:province":"Palermo",
    "wof:name":"Gennaro Antonino",
    "wof:placetype":"venue"
},
  "geometry": {"coordinates":[13.3325796127,38.0858955383],"type":"Point"}
}