{
  "type": "Feature",
  "properties": {
    "iso:country":"IT",
    "sg:address":"30038 Spinea",
    "sg:city":"Spinea",
    "sg:orig_category":"Frigotecnica, Apparecchiature E Servizi. Forniture Alle Strutture Ricettive",
    "sg:phone":"+39 041 999090",
    "sg:postcode":"30038",
    "sg:province":"Venezia",
    "sg:website":"http://www.gimaritalia.it",
    "wof:name":"Gimar Italia Srl",
    "wof:placetype":"venue"
},
  "geometry": {"coordinates":[12.1407327652,45.5021934509],"type":"Point"}
}