{
  "type": "Feature",
  "properties": {
    "addr:full":"11020 Donnas Donnas Aosta 11020",
    "addr:housenumber":"11020",
    "addr:postcode":"11020",
    "addr:street":"Donnas Donnas Aosta",
    "iso:country":"IT",
    "sg:address":"11020 Donnas",
    "sg:city":"Donnas",
    "sg:orig_category":"Imprese Di Costruzioni Civili Ed Industriali",
    "sg:phone":"+39 0125 806204",
    "sg:postcode":"11020",
    "sg:province":"Aosta",
    "wof:name":"Franceschi Walter - Wafran",
    "wof:placetype":"venue"
},
  "geometry": {"coordinates":[7.770258,45.604008],"type":"Point"}
}