{
  "type": "Feature",
  "properties": {
    "iso:country":"IT",
    "sg:address":"Via Umberto Saba 18 45035 Castelmassa",
    "sg:city":"Castelmassa",
    "sg:orig_category":"Hoisiery Goods",
    "sg:phone":"+39 0425 840086",
    "sg:postcode":"45035",
    "sg:province":"Rovigo",
    "sg:website":"www.grecotex.it",
    "wof:name":"Grecotex Srl",
    "wof:placetype":"venue"
},
  "geometry": {"coordinates":[11.789797,45.070736],"type":"Point"}
}