{
  "type": "Feature",
  "properties": {
    "iso:country":"IT",
    "sg:address":"52011 Bibbiena",
    "sg:city":"Bibbiena",
    "sg:orig_category":"Ospedali E Servizi Sanitari. Servizi Ausiliari Di Analisi, Controllo E Ricerca",
    "sg:phone":"+39 0575 536537",
    "sg:postcode":"52011",
    "sg:province":"Arezzo",
    "wof:name":"Ecoservizi Industriali Srl",
    "wof:placetype":"venue"
},
  "geometry": {"coordinates":[11.808396,43.69556],"type":"Point"}
}