{
  "type": "Feature",
  "properties": {
    "iso:country":"IT",
    "sg:address":"20144 Milano",
    "sg:city":"Milano",
    "sg:orig_category":"Informatica - Consulenza E Servizi. Automazione E Macchine Per Ufficio. Servizi Ausiliari Di Analisi, Controllo E Ricerca. Servizi Per Aziende, Manifestazioni E Supporto Agli Scambi Commerciali",
    "sg:phone":"+39 02 8942 0276",
    "sg:postcode":"20144",
    "sg:province":"Milano",
    "sg:website":"http://www.apissoftware.com",
    "wof:name":"Apis Software Srl",
    "wof:placetype":"venue"
},
  "geometry": {"coordinates":[9.1689,45.454708],"type":"Point"}
}