{
  "type": "Feature",
  "properties": {
    "addr:full":"1/3, Via Lago Di Lesina 36015 Schio Schio Vicenza 36015",
    "addr:housenumber":"1 / 3",
    "addr:postcode":"36015;36015",
    "addr:street":"Via Lago Di Lesina",
    "iso:country":"IT",
    "sg:address":"1/3, Via Lago Di Lesina 36015 Schio",
    "sg:city":"Schio",
    "sg:classifiers":[
        {
            "category":"Shopping",
            "subcategory":"Crafts & Fabrics",
            "type":"Retail Goods"
        }
    ],
    "sg:phone":"+39 0445 575124",
    "sg:postcode":"36015",
    "sg:province":"Vicenza",
    "sg:tags":[
        "linen"
    ],
    "wof:name":"Arcaro Srl",
    "wof:placetype":"venue"
},
  "geometry": {"coordinates":[11.4090824127,45.7211418152],"type":"Point"}
}