{
  "type": "Feature",
  "properties": {
    "iso:country":"IT",
    "sg:address":"91100 Trapani",
    "sg:city":"Trapani",
    "sg:orig_category":"Frigotecnica, Apparecchiature E Servizi. Forniture Alle Strutture Ricettive",
    "sg:phone":"+39 0923 537741",
    "sg:postcode":"91100",
    "sg:province":"Trapani",
    "wof:name":"Bica Diego",
    "wof:placetype":"venue"
},
  "geometry": {"coordinates":[12.5463275909,37.9978866577],"type":"Point"}
}