{
  "type": "Feature",
  "properties": {
    "addr:full":"246, Via Di Salone 00131 Roma Roma Roma 00131",
    "addr:housenumber":"246",
    "addr:postcode":"00131;00131",
    "addr:street":"Via Di Salone",
    "iso:country":"IT",
    "sg:address":"246, Via Di Salone 00131 Roma",
    "sg:city":"Roma",
    "sg:classifiers":[
        {
            "category":"Manufacturing",
            "subcategory":"Lumber",
            "type":"Manufacturing & Wholesale Goods"
        }
    ],
    "sg:phone":"+39 39064190255",
    "sg:postcode":"00131",
    "sg:province":"Roma",
    "sg:tags":[
        "wood"
    ],
    "wof:name":"Lumaca Legnami S.p.a.",
    "wof:placetype":"venue"
},
  "geometry": {"coordinates":[12.629007,41.927933],"type":"Point"}
}