{
  "type": "Feature",
  "properties": {
    "iso:country":"IT",
    "sg:address":"25125 Brescia",
    "sg:city":"Brescia",
    "sg:orig_category":"Metalli E Leghe",
    "sg:phone":"+39 030 354 1880",
    "sg:postcode":"25125",
    "sg:province":"Brescia",
    "wof:name":"Seco Tools Italia (s.p.a.)",
    "wof:placetype":"venue"
},
  "geometry": {"coordinates":[10.182267189,45.5294914246],"type":"Point"}
}