{
  "type": "Feature",
  "properties": {
    "iso:country":"IT",
    "sg:address":"Via Nuova Cliternia 86042 Campomarino",
    "sg:city":"Campomarino",
    "sg:classifiers":[
        {
            "category":"Food & Beverages",
            "subcategory":"Groceries & Convenience Stores",
            "type":"Retail Goods"
        }
    ],
    "sg:phone":"+39 39087557416",
    "sg:postcode":"86042",
    "sg:province":"Campobasso",
    "sg:tags":[
        "drink"
    ],
    "wof:name":"Cantina Cliternia Scarl",
    "wof:placetype":"venue"
},
  "geometry": {"coordinates":[15.071197,41.897602],"type":"Point"}
}