{
  "type": "Feature",
  "properties": {
    "iso:country":"IT",
    "sg:address":"85050 Baragiano",
    "sg:city":"Baragiano",
    "sg:orig_category":"Antincendio - Impianti, Attrezzature E Materiali",
    "sg:phone":"+39 0971 993804",
    "sg:postcode":"85050",
    "sg:province":"Potenza",
    "wof:name":"Global's Group Srl",
    "wof:placetype":"venue"
},
  "geometry": {"coordinates":[15.572106,40.694347],"type":"Point"}
}