{
  "type": "Feature",
  "properties": {
    "iso:country":"IT",
    "sg:address":"24020 Selvino",
    "sg:city":"Selvino",
    "sg:orig_category":"Cosmetici, Prodotti Di Bellezza E Di Igiene",
    "sg:phone":"+39 035 763051",
    "sg:postcode":"24020",
    "sg:province":"Bergamo",
    "wof:name":"Farmacia Castelli Dott. Marco",
    "wof:placetype":"venue"
},
  "geometry": {"coordinates":[9.755651,45.782482],"type":"Point"}
}