{
  "type": "Feature",
  "properties": {
    "iso:country":"IT",
    "sg:address":"35020 Saonara",
    "sg:city":"Saonara",
    "sg:orig_category":"Carni, Salumi E Pesci",
    "sg:phone":"+39 049 644821",
    "sg:postcode":"35020",
    "sg:province":"Padova",
    "wof:name":"Macelleria Equina Degan & Borgato (s.n.c.)",
    "wof:placetype":"venue"
},
  "geometry": {"coordinates":[11.9798,45.372475],"type":"Point"}
}