{
  "type": "Feature",
  "properties": {
    "iso:country":"IT",
    "sg:address":"51037 Montale",
    "sg:city":"Montale",
    "sg:classifiers":[
        {
            "category":"Manufacturing",
            "subcategory":"Textiles",
            "type":"Manufacturing & Wholesale Goods"
        }
    ],
    "sg:phone":"+39 0573 558430",
    "sg:postcode":"51037",
    "sg:province":"Pistoia",
    "sg:tags":[
        "raw",
        "material",
        "yarn",
        "textiles"
    ],
    "wof:name":"For.mar Di Marseo Enrico E C. Sas",
    "wof:placetype":"venue"
},
  "geometry": {"coordinates":[11.011125,43.913204],"type":"Point"}
}