{
  "type": "Feature",
  "properties": {
    "addr:full":"40012 Calderara Di Reno Calderara di Reno Bologna 40012",
    "addr:postcode":"40012;40012",
    "iso:country":"IT",
    "sg:address":"40012 Calderara Di Reno",
    "sg:city":"Calderara di Reno",
    "sg:classifiers":[
        {
            "category":"Manufacturing",
            "subcategory":"Motor Vehicles & Parts",
            "type":"Manufacturing & Wholesale Goods"
        }
    ],
    "sg:phone":"+39 051 646 7711",
    "sg:postcode":"40012",
    "sg:province":"Bologna",
    "sg:tags":[
        "drive"
    ],
    "wof:name":"S.t.m. Spa",
    "wof:placetype":"venue"
},
  "geometry": {"coordinates":[11.2961044312,44.5431785583],"type":"Point"}
}