{
  "type": "Feature",
  "properties": {
    "iso:country":"IT",
    "sg:address":"30125 Venezia",
    "sg:city":"Venezia",
    "sg:orig_category":"Pubblica Amministrazione",
    "sg:phone":"+39 041 275 0395",
    "sg:postcode":"30125",
    "sg:province":"Venezia",
    "wof:name":"Uffici Giudiziari",
    "wof:placetype":"venue"
},
  "geometry": {"coordinates":[12.3320322037,45.4394798279],"type":"Point"}
}