{
  "type": "Feature",
  "properties": {
    "addr:full":"64025 Pineto Pineto Teramo 64025",
    "addr:postcode":"64025;64025",
    "iso:country":"IT",
    "sg:address":"64025 Pineto",
    "sg:city":"Pineto",
    "sg:orig_category":"Servizi Per Aziende, Manifestazioni E Supporto Agli Scambi Commerciali",
    "sg:phone":"+39 085 949 2988",
    "sg:postcode":"64025",
    "sg:province":"Teramo",
    "wof:name":"Sara Investigazioni Di Passamonti Gianfranco & C. Sas",
    "wof:placetype":"venue"
},
  "geometry": {"coordinates":[14.042065,42.607063],"type":"Point"}
}