{
  "type": "Feature",
  "properties": {
    "iso:country":"IT",
    "sg:address":"2, Via Vallazza 21012 Cassano Magnago",
    "sg:city":"Cassano Magnago",
    "sg:classifiers":[
        {
            "category":"Shopping",
            "subcategory":"Clothing, Apparel, & Fashions",
            "type":"Retail Goods"
        }
    ],
    "sg:phone":"+39 0331 200710",
    "sg:postcode":"21012",
    "sg:province":"Varese",
    "sg:tags":[
        "clothes"
    ],
    "wof:name":"Confezioni Santa Maria Di Taglioretti Ambrosetti &",
    "wof:placetype":"venue"
},
  "geometry": {"coordinates":[8.815873,45.669617],"type":"Point"}
}