{
  "type": "Feature",
  "properties": {
    "addr:full":"Via Sempione 187 28053 Castelletto Ticino Novara 28053",
    "addr:housenumber":"187",
    "addr:postcode":"28053;28053",
    "addr:street":"Via Sempione;Ticino",
    "iso:country":"IT",
    "sg:address":"Via Sempione 187 28053 Castelletto Ticino",
    "sg:classifiers":[
        {
            "category":"Manufacturing",
            "subcategory":"Tools & Machinery",
            "type":"Manufacturing & Wholesale Goods"
        }
    ],
    "sg:phone":"+39 0331 913171",
    "sg:postcode":"28053",
    "sg:province":"Novara",
    "sg:tags":[
        "measuring",
        "precision"
    ],
    "sg:website":"www.gnr.it",
    "wof:name":"Gnr Srl",
    "wof:placetype":"venue"
},
  "geometry": {"coordinates":[8.6038684845,45.719455719],"type":"Point"}
}