{
  "type": "Feature",
  "properties": {
    "iso:country":"IT",
    "sg:address":"113, Via Padova 35030 Selvazzano Dentro",
    "sg:city":"Selvazzano Dentro",
    "sg:classifiers":[
        {
            "category":"Home & Garden",
            "subcategory":"Home Furnishings",
            "type":"Retail Goods"
        }
    ],
    "sg:phone":"+39 39049620666",
    "sg:postcode":"35030",
    "sg:province":"Padova",
    "sg:tags":[
        "household"
    ],
    "wof:name":"Salata (s.r.l.)",
    "wof:placetype":"venue"
},
  "geometry": {"coordinates":[11.813714,45.392075],"type":"Point"}
}