{
  "type": "Feature",
  "properties": {
    "iso:country":"IT",
    "sg:address":"Loc Pertinace 23 12050 Treiso",
    "sg:city":"Treiso",
    "sg:classifiers":[
        {
            "category":"Manufacturing",
            "subcategory":"Paper Products",
            "type":"Manufacturing & Wholesale Goods"
        }
    ],
    "sg:phone":"+39 0173 363611",
    "sg:postcode":"12050",
    "sg:province":"Cuneo",
    "sg:tags":[
        "cardboard",
        "package"
    ],
    "sg:website":"www.baldisnc.it",
    "wof:name":"Baldi Snc",
    "wof:placetype":"venue"
},
  "geometry": {"coordinates":[7.547111,44.388798],"type":"Point"}
}