{
  "type": "Feature",
  "properties": {
    "iso:country":"IT",
    "sg:address":"15, Strada Di Vagno 05035 Narni",
    "sg:city":"Narni",
    "sg:classifiers":[
        {
            "category":"Shopping",
            "subcategory":"Computers & Home Electronics",
            "type":"Retail Goods"
        }
    ],
    "sg:phone":"+39 0744 793024",
    "sg:postcode":"05035",
    "sg:province":"Terni",
    "sg:tags":[
        "electronic",
        "electrical",
        "equipment"
    ],
    "wof:name":"C.m.2 Srl",
    "wof:placetype":"venue"
},
  "geometry": {"coordinates":[12.50686,42.50803],"type":"Point"}
}