{
  "type": "Feature",
  "properties": {
    "iso:country":"IT",
    "sg:address":"20123 Milano",
    "sg:city":"Milano",
    "sg:orig_category":"Studi E Consulenze Amministrative, Commerciali E Aziendali. Consulenze Tecniche, Amministrative E Perizie. Professionisti - Studi E Servizi Ed Associazioni Di Interesse Aziendale",
    "sg:phone":"+39 02 8691 5444",
    "sg:postcode":"20123",
    "sg:province":"Milano",
    "wof:name":"Studio Associato Tributario E Legale Cimmino Bellini Lo Maglio",
    "wof:placetype":"venue"
},
  "geometry": {"coordinates":[9.180667,45.47171],"type":"Point"}
}