{
  "type": "Feature",
  "properties": {
    "addr:full":"20010 Mesero Mesero Milano 20010",
    "addr:postcode":"20010;20010",
    "iso:country":"IT",
    "sg:address":"20010 Mesero",
    "sg:city":"Mesero",
    "sg:orig_category":"Professionisti - Studi E Servizi Ed Associazioni Di Interesse Aziendale. Associazioni Ed Organismi Di Interesse Pubblico. Chiese Ed Associazioni Religiose",
    "sg:phone":"+39 02 978 7273",
    "sg:postcode":"20010",
    "sg:province":"Milano",
    "wof:name":"Associazione Fides",
    "wof:placetype":"venue"
},
  "geometry": {"coordinates":[8.8577699661,45.5010643005],"type":"Point"}
}