{
  "type": "Feature",
  "properties": {
    "iso:country":"IT",
    "sg:address":"20151 Milano",
    "sg:city":"Milano",
    "sg:orig_category":"Professionisti - Studi E Servizi Ed Associazioni Di Interesse Aziendale. Associazioni Ed Organismi Di Interesse Pubblico",
    "sg:phone":"+39 02 3800 3024",
    "sg:postcode":"20151",
    "sg:province":"Milano",
    "wof:name":"Partito Democratico Della Sinistra",
    "wof:placetype":"venue"
},
  "geometry": {"coordinates":[9.1232528687,45.4772720337],"type":"Point"}
}