{
  "type": "Feature",
  "properties": {
    "addr:full":"Via Saliceto 11 40013 Castel Maggiore Castel Maggiore Bologna 40013",
    "addr:housenumber":"11",
    "addr:postcode":"40013;40013",
    "addr:street":"Via Saliceto",
    "iso:country":"IT",
    "sg:address":"Via Saliceto 11 40013 Castel Maggiore",
    "sg:city":"Castel Maggiore",
    "sg:classifiers":[
        {
            "category":"Manufacturing",
            "subcategory":"Printing",
            "type":"Manufacturing & Wholesale Goods"
        }
    ],
    "sg:phone":"+39 051 712079",
    "sg:postcode":"40013",
    "sg:province":"Bologna",
    "sg:tags":[
        "plastic"
    ],
    "sg:website":"www.plastfur.it",
    "wof:name":"Plastifur Srl",
    "wof:placetype":"venue"
},
  "geometry": {"coordinates":[11.3788957596,44.5672950745],"type":"Point"}
}