{
  "type": "Feature",
  "properties": {
    "addr:full":"Via Gonzaga Maurizio 5 20123 Milano Milano Milano 20123",
    "addr:housenumber":"5",
    "addr:postcode":"20123;20123",
    "addr:street":"Via Gonzaga Maurizio",
    "iso:country":"IT",
    "sg:address":"Via Gonzaga Maurizio 5 20123 Milano",
    "sg:city":"Milano",
    "sg:classifiers":[
        {
            "category":"Shopping",
            "subcategory":"Jewelry",
            "type":"Retail Goods"
        }
    ],
    "sg:phone":"+39 02 875154",
    "sg:postcode":"20123",
    "sg:province":"Milano",
    "sg:tags":[
        "gemstone",
        "jewellery"
    ],
    "wof:name":"Art Or Srl",
    "wof:placetype":"venue"
},
  "geometry": {"coordinates":[9.189231,45.461628],"type":"Point"}
}