{
  "type": "Feature",
  "properties": {
    "iso:country":"IT",
    "sg:address":"Strada Stazione 05026 Montecastrilli",
    "sg:city":"Montecastrilli",
    "sg:classifiers":[
        {
            "category":"Shopping",
            "subcategory":"Clothing, Apparel, & Fashions",
            "type":"Retail Goods"
        }
    ],
    "sg:phone":"+39 0744 930761",
    "sg:postcode":"05026",
    "sg:province":"Terni",
    "sg:tags":[
        "clothes"
    ],
    "wof:name":"Maglificio Novella Confezioni",
    "wof:placetype":"venue"
},
  "geometry": {"coordinates":[12.531769,42.657684],"type":"Point"}
}