{
  "type": "Feature",
  "properties": {
    "iso:country":"IT",
    "sg:address":"7, Via Brianza 30034 Mira",
    "sg:city":"Mira",
    "sg:classifiers":[
        {
            "category":"Manufacturing",
            "subcategory":"Printing",
            "type":"Manufacturing & Wholesale Goods"
        }
    ],
    "sg:phone":"+39 041 565 9057",
    "sg:postcode":"30034",
    "sg:province":"Venezia",
    "sg:tags":[
        "publishing"
    ],
    "wof:name":"Storti Edizioni S.r.l.",
    "wof:placetype":"venue"
},
  "geometry": {"coordinates":[12.1693267822,45.4629859924],"type":"Point"}
}