{
  "type": "Feature",
  "properties": {
    "iso:country":"IT",
    "sg:address":"10036 Settimo Torinese",
    "sg:city":"Settimo Torinese",
    "sg:orig_category":"Servizi Di Magazzinaggio E Movimentazione. Servizi Ausiliari Di Sorveglianza, Manutenzione E Pulizia. Servizi Per Aziende, Manifestazioni E Supporto Agli Scambi Commerciali",
    "sg:phone":"+39 011 800 4829",
    "sg:postcode":"10036",
    "sg:province":"Torino",
    "sg:website":"http://www.paginegialle.it/cooperativaairone",
    "wof:name":"Cooperativa Airone",
    "wof:placetype":"venue"
},
  "geometry": {"coordinates":[7.773123,45.140766],"type":"Point"}
}