{
  "type": "Feature",
  "properties": {
    "iso:country":"IT",
    "sg:address":"Cso Savona 45 10029 Villastellone",
    "sg:city":"Villastellone",
    "sg:classifiers":[
        {
            "category":"Wholesale",
            "subcategory":"Auto Parts",
            "type":"Manufacturing & Wholesale Goods"
        }
    ],
    "sg:phone":"+39 011 961 9161",
    "sg:postcode":"10029",
    "sg:province":"Torino",
    "sg:tags":[
        "automobile",
        "component",
        "structural"
    ],
    "wof:name":"Gallino Plasturgia Srl",
    "wof:placetype":"venue"
},
  "geometry": {"coordinates":[7.71664,44.950481],"type":"Point"}
}