{
  "type": "Feature",
  "properties": {
    "addr:full":"Via Campagnola 20 28887 Omegna Omegna Verbano-Cusio-Ossola 28887",
    "addr:housenumber":"20",
    "addr:postcode":"28887;28887",
    "addr:street":"Via Campagnola",
    "iso:country":"IT",
    "sg:address":"Via Campagnola 20 28887 Omegna",
    "sg:city":"Omegna",
    "sg:orig_category":"Pulleys For Trolley Hoists",
    "sg:phone":"+39 0323 643072",
    "sg:postcode":"28887",
    "sg:province":"Verbano-Cusio-Ossola",
    "wof:name":"I.l.p.e. S.r.l.",
    "wof:placetype":"venue"
},
  "geometry": {"coordinates":[8.4073705673,45.8824081421],"type":"Point"}
}