{
  "type": "Feature",
  "properties": {
    "addr:full":"17028 Bergeggi Bergeggi Savona 17028",
    "addr:postcode":"17028;17028",
    "iso:country":"IT",
    "sg:address":"17028 Bergeggi",
    "sg:city":"Bergeggi",
    "sg:orig_category":"Agenti D'affari In Mediazione",
    "sg:phone":"+39 019 859580",
    "sg:postcode":"17028",
    "sg:province":"Savona",
    "wof:name":"Venturi Elisa",
    "wof:placetype":"venue"
},
  "geometry": {"coordinates":[8.441326,44.238197],"type":"Point"}
}