{
  "type": "Feature",
  "properties": {
    "addr:full":"20124 Milano Milano Milano 20124",
    "addr:postcode":"20124;20124",
    "iso:country":"IT",
    "sg:address":"20124 Milano",
    "sg:city":"Milano",
    "sg:orig_category":"Abbigliamento Intimo, Calze E Costumi Da Bagno",
    "sg:phone":"+39 02 670 5511",
    "sg:postcode":"20124",
    "sg:province":"Milano",
    "wof:name":"T.l. Di Tumolo Luigi",
    "wof:placetype":"venue"
},
  "geometry": {"coordinates":[9.208263,45.483936],"type":"Point"}
}