{
  "type": "Feature",
  "properties": {
    "iso:country":"IT",
    "sg:address":"62100 Macerata",
    "sg:city":"Macerata",
    "sg:orig_category":"Carta Da Parati - Vendita Al Dettaglio",
    "sg:phone":"+39 0733 262155",
    "sg:postcode":"62100",
    "sg:province":"Macerata",
    "wof:name":"Gtp Parati Di Evangelisti Giacomo",
    "wof:placetype":"venue"
},
  "geometry": {"coordinates":[13.45583,43.297695],"type":"Point"}
}