{
  "type": "Feature",
  "properties": {
    "iso:country":"IT",
    "sg:address":"5, Via Campostino Di Mezzana 59100 Prato",
    "sg:city":"Mezzana",
    "sg:classifiers":[
        {
            "category":"Shopping",
            "subcategory":"Crafts & Fabrics",
            "type":"Retail Goods"
        }
    ],
    "sg:phone":"+39 0574 597370",
    "sg:postcode":"59100",
    "sg:province":"Prato",
    "wof:name":"Aquila 2000 Srl",
    "wof:placetype":"venue"
},
  "geometry": {"coordinates":[11.1003351212,43.853767395],"type":"Point"}
}