{
  "type": "Feature",
  "properties": {
    "addr:full":"85, V. Procopio 62010 Urbisaglia Urbisaglia Macerata 62010",
    "addr:housenumber":"85",
    "addr:postcode":"62010;62010",
    "addr:street":"V. Procopio",
    "iso:country":"IT",
    "sg:address":"85, V. Procopio 62010 Urbisaglia",
    "sg:city":"Urbisaglia",
    "sg:classifiers":[
        {
            "category":"Shopping",
            "subcategory":"Clothing, Apparel, & Fashions",
            "type":"Retail Goods"
        }
    ],
    "sg:phone":"+39 0733 511511",
    "sg:postcode":"62010",
    "sg:province":"Macerata",
    "sg:tags":[
        "clothes"
    ],
    "sg:website":"http://www.tombolini.it",
    "wof:name":"Tombolini",
    "wof:placetype":"venue"
},
  "geometry": {"coordinates":[13.373828,43.191792],"type":"Point"}
}