{
  "type": "Feature",
  "properties": {
    "addr:full":"22 Via Leonardo Da Vinci, 50132 Firenze Firenze Firenze 50132",
    "addr:postcode":"50132;50132",
    "addr:street":"Via Leonardo Da Vinci",
    "iso:country":"IT",
    "sg:address":"22 Via Leonardo Da Vinci, 50132 Firenze",
    "sg:city":"Firenze",
    "sg:classifiers":[
        {
            "category":"Banks & Credit Unions",
            "subcategory":"Financial Services",
            "type":"Services"
        }
    ],
    "sg:phone":"+39 390 555 0911",
    "sg:postcode":"50132",
    "sg:province":"Firenze",
    "sg:tags":[
        "banking",
        "finance",
        "insurance"
    ],
    "wof:name":"Banca Credito Fondiario Toscano (spa)",
    "wof:placetype":"venue"
},
  "geometry": {"coordinates":[11.2639837265,43.784362793],"type":"Point"}
}