{
  "type": "Feature",
  "properties": {
    "iso:country":"IT",
    "sg:address":"20056 Trezzo Sull'adda",
    "sg:orig_category":"Grafite",
    "sg:phone":"+39 02 9096 4116",
    "sg:postcode":"20056",
    "sg:province":"Milano",
    "sg:website":"http://www.atalgrafiti.it",
    "wof:name":"A.t.a.l. Srl",
    "wof:placetype":"venue"
},
  "geometry": {"coordinates":[9.521315,45.607029],"type":"Point"}
}