{
  "type": "Feature",
  "properties": {
    "addr:full":"54, Via Mantova 37019 Peschiera Del Garda Peschiera del Garda Verona 37019",
    "addr:postcode":"37019;37019",
    "addr:street":"Via Mantova",
    "iso:country":"IT",
    "sg:address":"54, Via Mantova 37019 Peschiera Del Garda",
    "sg:city":"Peschiera del Garda",
    "sg:classifiers":[
        {
            "category":"Travel",
            "subcategory":"Travel Agent",
            "type":"Entertainment"
        }
    ],
    "sg:phone":"+39 045 640 0279",
    "sg:postcode":"37019",
    "sg:province":"Verona",
    "sg:tags":[
        "business"
    ],
    "wof:name":"Green Park Hotel (s.r.l.)",
    "wof:placetype":"venue"
},
  "geometry": {"coordinates":[10.685565,45.425785],"type":"Point"}
}