{
  "type": "Feature",
  "properties": {
    "addr:full":"36010 Carr\u00e8 Vicenza 36010",
    "addr:postcode":"36010;36010",
    "iso:country":"IT",
    "sg:address":"36010 Carr\u00e8",
    "sg:orig_category":"Prodotti E Manufatti In Materie Plastiche. Servizi E Lavori Industria Delle Materie Plastiche",
    "sg:phone":"+39 0445 314128",
    "sg:postcode":"36010",
    "sg:province":"Vicenza",
    "sg:website":"http://www.gimatec.com",
    "wof:name":"Gimatec Srl",
    "wof:placetype":"venue"
},
  "geometry": {"coordinates":[11.4433994293,45.7379646301],"type":"Point"}
}