{
  "type": "Feature",
  "properties": {
    "iso:country":"IT",
    "sg:address":"90146 Palermo",
    "sg:city":"Palermo",
    "sg:orig_category":"Impiantistica E Prodotti Tecnologici Per Edilizia. Climatizzazione E Condizionamento, Apparecchiature E Servizi",
    "sg:phone":"+39 091 688 5308",
    "sg:postcode":"90146",
    "sg:province":"Palermo",
    "sg:website":"http://infcom.it/aertec",
    "wof:name":"Aertec Srl",
    "wof:placetype":"venue"
},
  "geometry": {"coordinates":[13.315532,38.151001],"type":"Point"}
}