{
  "type": "Feature",
  "properties": {
    "addr:full":"07100 Sassari Sassari Sassari 07100",
    "addr:postcode":"07100;07100",
    "iso:country":"IT",
    "sg:address":"07100 Sassari",
    "sg:city":"Sassari",
    "sg:orig_category":"Ristorazione E Locali Pubblici Affini. Ristoranti Ed Esercizi Affini. Servizi Ausiliari Di Ristorazione E Di Intrattenimento",
    "sg:phone":"+39 079 274598",
    "sg:postcode":"07100",
    "sg:province":"Sassari",
    "wof:name":"Trattoria Del Giamaranto",
    "wof:placetype":"venue"
},
  "geometry": {"coordinates":[8.564317,40.719929],"type":"Point"}
}