{
  "type": "Feature",
  "properties": {
    "addr:full":"24040 Lallio Lallio Bergamo 24040",
    "addr:postcode":"24040;24040",
    "iso:country":"IT",
    "sg:address":"24040 Lallio",
    "sg:city":"Lallio",
    "sg:orig_category":"Prodotti E Manufatti In Materie Plastiche",
    "sg:phone":"+39 035 201260",
    "sg:postcode":"24040",
    "sg:province":"Bergamo",
    "wof:name":"Lamin.plast Di F. Nava & C. Sas",
    "wof:placetype":"venue"
},
  "geometry": {"coordinates":[9.6258535385,45.6591949463],"type":"Point"}
}