{
  "type": "Feature",
  "properties": {
    "addr:full":"40128 Bologna Bologna Bologna 40128",
    "addr:postcode":"40128;40128",
    "iso:country":"IT",
    "sg:address":"40128 Bologna",
    "sg:city":"Bologna",
    "sg:orig_category":"Elettronica Professionale E Di Consumo. Forniture Per Il Settore Dello Spettacolo. Automazione E Macchine Per Ufficio. Forniture Per Congressi, Fiere E Manifestazioni",
    "sg:phone":"+39 051 320218",
    "sg:postcode":"40128",
    "sg:province":"Bologna",
    "wof:name":"Landini Audio Sas",
    "wof:placetype":"venue"
},
  "geometry": {"coordinates":[11.355947,44.544075],"type":"Point"}
}