{
  "type": "Feature",
  "properties": {
    "iso:country":"IT",
    "sg:address":"Via Lecco, 115 - Ponte Pietra 47023 Cesena",
    "sg:city":"Cesena",
    "sg:classifiers":[
        {
            "category":"Shopping",
            "subcategory":"Clothing, Apparel, & Fashions",
            "type":"Retail Goods"
        }
    ],
    "sg:phone":"+39 0547 645320",
    "sg:postcode":"47023",
    "sg:province":"Forl\u00ec-Cesena",
    "sg:tags":[
        "work",
        "clothes"
    ],
    "sg:website":"www.antonellaspada.com",
    "wof:name":"Elle Esse Confezioni Sas",
    "wof:placetype":"venue"
},
  "geometry": {"coordinates":[11.980461,43.994766],"type":"Point"}
}