{
  "type": "Feature",
  "properties": {
    "iso:country":"IT",
    "sg:address":"36078 Valdagno",
    "sg:city":"Valdagno",
    "sg:orig_category":"Forniture Per Attivita' Industriali",
    "sg:phone":"+39 0445 406107",
    "sg:postcode":"36078",
    "sg:province":"Vicenza",
    "wof:name":"Valresine S.n.c. Di Campi Edoardo & C.",
    "wof:placetype":"venue"
},
  "geometry": {"coordinates":[11.3089513779,45.625328064],"type":"Point"}
}