{
  "type": "Feature",
  "properties": {
    "iso:country":"IT",
    "sg:address":"41057 Spilamberto",
    "sg:city":"Spilamberto",
    "sg:orig_category":"Caravans, Campers, Roulottes E Accessori",
    "sg:phone":"+39 059 784395",
    "sg:postcode":"41057",
    "sg:province":"Modena",
    "wof:name":"Iacconi Agostino",
    "wof:placetype":"venue"
},
  "geometry": {"coordinates":[11.021365,44.519852],"type":"Point"}
}