{
  "type": "Feature",
  "properties": {
    "addr:full":"Via La Lucense 8 37020 Lugo Di Grezzana Verona 37020",
    "addr:housenumber":"8",
    "addr:postcode":"37020;37020",
    "addr:street":"Via La Lucense",
    "iso:country":"IT",
    "sg:address":"Via La Lucense 8 37020 Lugo Di Grezzana",
    "sg:classifiers":[
        {
            "category":"Juice Bar",
            "subcategory":"None",
            "type":"Food & Drink"
        }
    ],
    "sg:phone":"+39 045 880 1111",
    "sg:postcode":"37020",
    "sg:province":"Verona",
    "sg:tags":[
        "granite",
        "slab"
    ],
    "wof:name":"Graniti Montegrappa Srl",
    "wof:placetype":"venue"
},
  "geometry": {"coordinates":[10.991748,45.438366],"type":"Point"}
}