{
  "type": "Feature",
  "properties": {
    "iso:country":"IT",
    "sg:address":"61100 Pesaro",
    "sg:city":"Pesaro",
    "sg:orig_category":"Legno E Semilavorati",
    "sg:phone":"+39 0721 202522",
    "sg:postcode":"61100",
    "sg:province":"Pesaro E Urbino",
    "wof:name":"Arredo Meta (s.r.l)",
    "wof:placetype":"venue"
},
  "geometry": {"coordinates":[12.833082,43.884762],"type":"Point"}
}