{
  "type": "Feature",
  "properties": {
    "addr:full":"130, Via Tiberina 00188 Roma Roma Roma 00188",
    "addr:housenumber":"130",
    "addr:postcode":"00188;00188",
    "addr:street":"Via Tiberina",
    "iso:country":"IT",
    "sg:address":"130, Via Tiberina 00188 Roma",
    "sg:city":"Roma",
    "sg:classifiers":[
        {
            "category":"Shopping",
            "subcategory":"Stationery & Office Supplies",
            "type":"Retail Goods"
        }
    ],
    "sg:phone":"+39 06 3362 4954",
    "sg:postcode":"00188",
    "sg:province":"Roma",
    "sg:tags":[
        "professional"
    ],
    "wof:name":"Lineart S R L",
    "wof:placetype":"venue"
},
  "geometry": {"coordinates":[12.4912309647,41.8475418091],"type":"Point"}
}