{
  "type": "Feature",
  "properties": {
    "iso:country":"IT",
    "sg:address":"33100 Udine",
    "sg:city":"Udine",
    "sg:orig_category":"Avvocati, Notai E Servizi Legali. Consulenze Tecniche, Amministrative E Perizie",
    "sg:phone":"+39 0432 506388",
    "sg:postcode":"33100",
    "sg:province":"Udine",
    "sg:website":"http://www.gpl.it",
    "wof:name":"Glp Srl",
    "wof:placetype":"venue"
},
  "geometry": {"coordinates":[13.245426,46.06356],"type":"Point"}
}