{
  "type": "Feature",
  "properties": {
    "iso:country":"IT",
    "sg:address":"40013 Castel Maggiore",
    "sg:city":"Castel Maggiore",
    "sg:orig_category":"Macchine E Forniture Per Industria Orafa E Per Orologeria",
    "sg:phone":"+39 051 700033",
    "sg:postcode":"40013",
    "sg:province":"Bologna",
    "wof:name":"Andreoli Guglielmo (s.r.l.)",
    "wof:placetype":"venue"
},
  "geometry": {"coordinates":[11.349238,44.555984],"type":"Point"}
}