{
  "type": "Feature",
  "properties": {
    "addr:full":"84, Via Collegno 10091 Alpignano Alpignano Torino 10091",
    "addr:postcode":"10091;10091",
    "addr:street":"Via Collegno",
    "iso:country":"IT",
    "sg:address":"84, Via Collegno 10091 Alpignano",
    "sg:city":"Alpignano",
    "sg:classifiers":[
        {
            "category":"Shopping",
            "type":"Retail Goods"
        }
    ],
    "sg:phone":"+39 011 967 8198",
    "sg:postcode":"10091",
    "sg:province":"Torino",
    "sg:tags":[
        "finished",
        "-",
        "metallic"
    ],
    "wof:name":"I.s.i.l. (s.r.l.)",
    "wof:placetype":"venue"
},
  "geometry": {"coordinates":[7.5725569725,45.1070137024],"type":"Point"}
}