{
  "type": "Feature",
  "properties": {
    "iso:country":"IT",
    "sg:address":"Viale Polibio, 26; Siracusa; 96100",
    "sg:city":"Siracusa",
    "sg:classifiers":[
        {
            "category":"Banks & Credit Unions",
            "subcategory":"Bank",
            "type":"Services"
        }
    ],
    "sg:phone":"+39 0931 32421",
    "sg:postcode":"96100",
    "sg:province":"Siracusa",
    "wof:name":"Banca Del Monte S. Agata",
    "wof:placetype":"venue"
},
  "geometry": {"coordinates":[15.28777,37.08379],"type":"Point"}
}