{
  "type": "Feature",
  "properties": {
    "iso:country":"IT",
    "sg:address":"141/i, Via Petrarca Francesco 80122 Napoli",
    "sg:city":"Napoli",
    "sg:classifiers":[
        {
            "category":"Professional",
            "subcategory":"Advertising",
            "type":"Services"
        }
    ],
    "sg:phone":"+39 081 575 2480",
    "sg:postcode":"80122",
    "sg:province":"Napoli",
    "sg:tags":[
        "communication",
        "medium"
    ],
    "wof:name":"Mackross Di Colella Nello",
    "wof:placetype":"venue"
},
  "geometry": {"coordinates":[14.299187,40.90379],"type":"Point"}
}