{
  "type": "Feature",
  "properties": {
    "iso:country":"IT",
    "sg:address":"8, Via Trevisani Nel Mondo 31058 Susegana",
    "sg:city":"Susegana",
    "sg:classifiers":[
        {
            "category":"Utilities",
            "subcategory":"Electric",
            "type":"Services"
        }
    ],
    "sg:phone":"+39 39043864155",
    "sg:postcode":"31058",
    "sg:province":"Treviso",
    "sg:tags":[
        "component",
        "electronic"
    ],
    "wof:name":"Zanardo S.p.a.",
    "wof:placetype":"venue"
},
  "geometry": {"coordinates":[12.291569,45.899433],"type":"Point"}
}