{
  "type": "Feature",
  "properties": {
    "addr:full":"31031 Caerano Di S. Marco Treviso 31031",
    "addr:postcode":"31031;31031",
    "addr:street":"Caerano Di S. Marco Treviso",
    "iso:country":"IT",
    "sg:address":"31031 Caerano Di S. Marco",
    "sg:orig_category":"Autogru - Noleggio",
    "sg:phone":"+39 0423 85494",
    "sg:postcode":"31031",
    "sg:province":"Treviso",
    "wof:name":"Poloniato Srl",
    "wof:placetype":"venue"
},
  "geometry": {"coordinates":[12.002752,45.782501],"type":"Point"}
}