{
  "type": "Feature",
  "properties": {
    "iso:country":"IT",
    "sg:address":"Via Graziano Ferdinando 80022 Arzano",
    "sg:city":"Arzano",
    "sg:orig_category":"Miscellaneous Products",
    "sg:phone":"+39 081 731 2074",
    "sg:postcode":"80022",
    "sg:province":"Napoli",
    "wof:name":"Cristalleria Arzanese",
    "wof:placetype":"venue"
},
  "geometry": {"coordinates":[14.2627344131,40.9227752686],"type":"Point"}
}