{
  "type": "Feature",
  "properties": {
    "iso:country":"IT",
    "sg:address":"210, Via Della Beverara 40131 Bologna",
    "sg:city":"Bologna",
    "sg:classifiers":[
        {
            "category":"Shopping",
            "subcategory":"Computers & Home Electronics",
            "type":"Retail Goods"
        }
    ],
    "sg:phone":"+39 051 634 2367",
    "sg:postcode":"40131",
    "sg:province":"Bologna",
    "sg:tags":[
        "electronic",
        "electrical",
        "equipment"
    ],
    "wof:name":"C.f.e. S.r.l.",
    "wof:placetype":"venue"
},
  "geometry": {"coordinates":[11.331427,44.518356],"type":"Point"}
}