{
  "type": "Feature",
  "properties": {
    "iso:country":"IT",
    "sg:address":"25036 Palazzolo Sull'oglio",
    "sg:orig_category":"Articoli Per Imballaggio E Confezionamento",
    "sg:phone":"+39 030 730 1426",
    "sg:postcode":"25036",
    "sg:province":"Brescia",
    "wof:name":"Arca Box",
    "wof:placetype":"venue"
},
  "geometry": {"coordinates":[9.891552,45.584633],"type":"Point"}
}