{
  "type": "Feature",
  "properties": {
    "addr:full":"56040 Crespina Cenaia Pisa 56040",
    "addr:postcode":"56040;56040",
    "iso:country":"IT",
    "sg:address":"56040 Crespina",
    "sg:city":"Cenaia",
    "sg:orig_category":"Bevande, Vini E Liquori. Agricoltura, Orticoltura E Floricoltura",
    "sg:phone":"+39 050 643996",
    "sg:postcode":"56040",
    "sg:province":"Pisa",
    "sg:website":"http://www.cantinacollinepisane.it",
    "wof:name":"Cantina Delle Colline Pisane",
    "wof:placetype":"venue"
},
  "geometry": {"coordinates":[10.537548,43.60667],"type":"Point"}
}