{
  "type": "Feature",
  "properties": {
    "iso:country":"IT",
    "sg:address":"00198 Roma",
    "sg:city":"Roma",
    "sg:orig_category":"Medici. Assicurazioni E Servizi Assicurativi. Avvocati, Notai E Servizi Legali. Professionisti - Studi E Servizi Ed Associazioni Di Interesse Aziendale",
    "sg:phone":"+39 06 841 9231",
    "sg:postcode":"00198",
    "sg:province":"Roma",
    "wof:name":"Angioni Carlo",
    "wof:placetype":"venue"
},
  "geometry": {"coordinates":[12.5039920807,41.917881012],"type":"Point"}
}