{
  "type": "Feature",
  "properties": {
    "iso:country":"IT",
    "sg:address":"13/15, Via Puecher 20060 Pozzuolo Martesana",
    "sg:city":"Pozzuolo Martesana",
    "sg:classifiers":[
        {
            "category":"Shopping",
            "subcategory":"Clothing, Apparel, & Fashions",
            "type":"Retail Goods"
        }
    ],
    "sg:phone":"+39 02 9535 8256",
    "sg:postcode":"20060",
    "sg:province":"Milano",
    "sg:tags":[
        "clothing",
        "accessory"
    ],
    "wof:name":"Pessani S.r.l.",
    "wof:placetype":"venue"
},
  "geometry": {"coordinates":[9.468272,45.521481],"type":"Point"}
}