{
  "type": "Feature",
  "properties": {
    "iso:country":"IT",
    "sg:address":"80123 Napoli",
    "sg:city":"Napoli",
    "sg:orig_category":"Servizi Per Lo Sport E Il Tempo Libero. Servizi Al Turismo. Servizi Ausiliari Dei Mezzi Di Trasporto. Servizi Ausiliari Per Il Trasporto",
    "sg:phone":"+39 081 769 1713",
    "sg:postcode":"80123",
    "sg:province":"Napoli",
    "sg:website":"http://www.posillipo.it",
    "wof:name":"Posillipo Travel Sas",
    "wof:placetype":"venue"
},
  "geometry": {"coordinates":[14.209278,40.907398],"type":"Point"}
}