{
  "type": "Feature",
  "properties": {
    "iso:country":"IT",
    "sg:address":"2/bis, V. Cappella Nuova 80059 Torre Del Greco",
    "sg:city":"Torre del Greco",
    "sg:classifiers":[
        {
            "category":"Autos & Motor Vehicles",
            "subcategory":"Boat Sales",
            "type":"Retail Goods"
        }
    ],
    "sg:phone":"+39 081 883 1900",
    "sg:postcode":"80059",
    "sg:province":"Napoli",
    "sg:website":"http://www.brunasso.it",
    "wof:name":"Brunasso Di Mattia E Mario Sas",
    "wof:placetype":"venue"
},
  "geometry": {"coordinates":[14.516899,40.745766],"type":"Point"}
}