{
  "type": "Feature",
  "properties": {
    "iso:country":"IT",
    "sg:address":"40054 Budrio",
    "sg:city":"Budrio",
    "sg:classifiers":[
        {
            "category":"Wholesale",
            "subcategory":"Machinery & Supplies",
            "type":"Manufacturing & Wholesale Goods"
        }
    ],
    "sg:phone":"+39 051 802511",
    "sg:postcode":"40054",
    "sg:province":"Bologna",
    "sg:tags":[
        "activities",
        "commercial",
        "system",
        "machine",
        "artisan",
        "supplies",
        "accommodation"
    ],
    "wof:name":"Tecnosystem Srl",
    "wof:placetype":"venue"
},
  "geometry": {"coordinates":[11.603824,44.49078],"type":"Point"}
}