{
  "type": "Feature",
  "properties": {
    "iso:country":"IT",
    "sg:address":"22078 Turate",
    "sg:city":"Turate",
    "sg:orig_category":"Prodotti E Manufatti In Materie Plastiche",
    "sg:phone":"+39 02 964171",
    "sg:postcode":"22078",
    "sg:province":"Como",
    "wof:name":"F.i.a.p. Spa",
    "wof:placetype":"venue"
},
  "geometry": {"coordinates":[9.0606012344,45.8011054993],"type":"Point"}
}