{
  "type": "Feature",
  "properties": {
    "iso:country":"IT",
    "sg:address":"00043 Ciampino",
    "sg:city":"Ciampino",
    "sg:orig_category":"Studi E Consulenze Tecniche E Industriali. Servizi E Lavori Per Edilizia E Lavori Pubblici. Professionisti - Studi E Servizi Ed Associazioni Di Interesse Aziendale",
    "sg:phone":"+39 06 796 1749",
    "sg:postcode":"00043",
    "sg:province":"Roma",
    "sg:website":"http://www.abacoservizi.it",
    "wof:name":"Colella Enrico - Abaco Servizi",
    "wof:placetype":"venue"
},
  "geometry": {"coordinates":[12.60028,41.804596],"type":"Point"}
}