{
  "type": "Feature",
  "properties": {
    "iso:country":"IT",
    "sg:address":"12039 Verzuolo",
    "sg:city":"Verzuolo",
    "sg:orig_category":"Macchine, Impianti E Forniture Per Industria Grafica, Cartaria E Cartotecnica",
    "sg:phone":"+39 0175 289391",
    "sg:postcode":"12039",
    "sg:province":"Cuneo",
    "wof:name":"Valmet Corporation Oy",
    "wof:placetype":"venue"
},
  "geometry": {"coordinates":[7.48897,44.596146],"type":"Point"}
}