{
  "type": "Feature",
  "properties": {
    "iso:country":"IT",
    "sg:address":"12020 Villafalletto",
    "sg:city":"Villafalletto",
    "sg:orig_category":"Macchine E Forniture Per Ecologia E Smaltimento Rifiuti. Macchine, Strumenti Ed Apparecchi Per Attivita' Industriali",
    "sg:phone":"+39 0171 938967",
    "sg:postcode":"12020",
    "sg:province":"Cuneo",
    "wof:name":"Bodrero Giuseppe",
    "wof:placetype":"venue"
},
  "geometry": {"coordinates":[7.54573,44.526581],"type":"Point"}
}