{
  "type": "Feature",
  "properties": {
    "iso:country":"IT",
    "sg:address":"63100 Ascoli Piceno",
    "sg:city":"Ascoli Piceno",
    "sg:orig_category":"Cabine Elettriche Di Trasformazione E Comando",
    "sg:phone":"+39 0736 253829",
    "sg:postcode":"63100",
    "sg:province":"Ascoli Piceno",
    "wof:name":"Eredi Luzi Mario Di Luzi Piero & C. Snc",
    "wof:placetype":"venue"
},
  "geometry": {"coordinates":[13.566831,42.84753],"type":"Point"}
}