{
  "type": "Feature",
  "properties": {
    "iso:country":"IT",
    "sg:address":"00146 Roma",
    "sg:city":"Roma",
    "sg:orig_category":"Non-classified Establishments",
    "sg:phone":"+39 06 5530 0273",
    "sg:postcode":"00146",
    "sg:province":"Roma",
    "wof:name":"Supermercati Pam S.p.a.",
    "wof:placetype":"venue"
},
  "geometry": {"coordinates":[12.469565,41.870567],"type":"Point"}
}