{
  "type": "Feature",
  "properties": {
    "iso:country":"IT",
    "sg:address":"90023 Ciminna",
    "sg:city":"Ciminna",
    "sg:orig_category":"Prodotti Alimentari. Agricoltura, Orticoltura E Floricoltura",
    "sg:phone":"+39 091 829 3564",
    "sg:postcode":"90023",
    "sg:province":"Palermo",
    "wof:name":"Molino S.vito Soc.coop.arl",
    "wof:placetype":"venue"
},
  "geometry": {"coordinates":[13.5552606583,37.8763961792],"type":"Point"}
}