{
  "type": "Feature",
  "properties": {
    "addr:full":"12040 Sanfre' Cuneo 12040",
    "addr:housenumber":"12040",
    "addr:postcode":"12040",
    "addr:street":"Sanfre ' Cuneo",
    "iso:country":"IT",
    "sg:address":"12040 Sanfre'",
    "sg:orig_category":"Materiali Semilavorati Metallici",
    "sg:phone":"+39 0172 587234",
    "sg:postcode":"12040",
    "sg:province":"Cuneo",
    "wof:name":"Cravero Lamiere Forate Di Cravero G.mario S.n.c.",
    "wof:placetype":"venue"
},
  "geometry": {"coordinates":[7.796813,44.747704],"type":"Point"}
}