{
  "type": "Feature",
  "properties": {
    "iso:country":"IT",
    "sg:address":"3, Via Cacciatori 20051 Limbiate",
    "sg:city":"Limbiate",
    "sg:classifiers":[
        {
            "category":"Wholesale",
            "subcategory":"Drugs",
            "type":"Manufacturing & Wholesale Goods"
        }
    ],
    "sg:phone":"+39 39029964661",
    "sg:postcode":"20051",
    "sg:province":"Milano",
    "sg:tags":[
        "chemical",
        "pharmaceutical"
    ],
    "wof:name":"Effedue Di Ferrario Flavio Carlo",
    "wof:placetype":"venue"
},
  "geometry": {"coordinates":[9.11331,45.603367],"type":"Point"}
}