{
  "type": "Feature",
  "properties": {
    "addr:full":"21, Via Latiro Giuseppe 16039 Sestri Levante Sestri Levante Genova 16039",
    "addr:postcode":"16039;16039",
    "addr:street":"Via Latiro Giuseppe",
    "iso:country":"IT",
    "sg:address":"21, Via Latiro Giuseppe 16039 Sestri Levante",
    "sg:city":"Sestri Levante",
    "sg:orig_category":"Miscellaneous Products",
    "sg:phone":"+39 0185 482321",
    "sg:postcode":"16039",
    "sg:province":"Genova",
    "wof:name":"Scubapro Italy Srl",
    "wof:placetype":"venue"
},
  "geometry": {"coordinates":[8.9339885712,44.4070625305],"type":"Point"}
}