{
  "type": "Feature",
  "properties": {
    "addr:full":"Via Monteleone 99 21013 Gallarate Gallarate Varese 21013",
    "addr:housenumber":"99",
    "addr:postcode":"21013;21013",
    "addr:street":"Via Monteleone",
    "iso:country":"IT",
    "sg:address":"Via Monteleone 99 21013 Gallarate",
    "sg:city":"Gallarate",
    "sg:classifiers":[
        {
            "category":"Wholesale",
            "subcategory":"Machinery & Supplies",
            "type":"Manufacturing & Wholesale Goods"
        }
    ],
    "sg:phone":"+39 0331 773773",
    "sg:postcode":"21013",
    "sg:province":"Varese",
    "sg:tags":[
        "pin",
        "clevis"
    ],
    "sg:website":"www.emmeviviterie.com",
    "wof:name":"Emme Vi Snc",
    "wof:placetype":"venue"
},
  "geometry": {"coordinates":[8.826385,45.817604],"type":"Point"}
}