{
  "type": "Feature",
  "properties": {
    "iso:country":"IT",
    "sg:address":"09131 Cagliari",
    "sg:city":"Cagliari",
    "sg:orig_category":"Servizi E Lavori Per Edilizia E Lavori Pubblici. Servizi Al Turismo",
    "sg:phone":"+39 070 505274",
    "sg:postcode":"09131",
    "sg:province":"Cagliari",
    "sg:website":"http://www.sardegnacostarei.com",
    "wof:name":"Holiday Service Snc",
    "wof:placetype":"venue"
},
  "geometry": {"coordinates":[9.127629,39.232998],"type":"Point"}
}