{
  "type": "Feature",
  "properties": {
    "addr:full":"25010 Borgosatollo Borgosatollo Brescia 25010",
    "addr:postcode":"25010;25010",
    "iso:country":"IT",
    "sg:address":"25010 Borgosatollo",
    "sg:city":"Borgosatollo",
    "sg:orig_category":"Macchine, Impianti Ed Attrezzature Industria Delle Materie Plastiche E Gomma",
    "sg:phone":"+39 030 250 0920",
    "sg:postcode":"25010",
    "sg:province":"Brescia",
    "wof:name":"Marist S.r.l.",
    "wof:placetype":"venue"
},
  "geometry": {"coordinates":[10.254131,45.474392],"type":"Point"}
}