{
  "type": "Feature",
  "properties": {
    "iso:country":"IT",
    "sg:address":"9, Viale Delle Industrie 21015 Lonate Pozzolo",
    "sg:city":"Lonate Pozzolo",
    "sg:classifiers":[
        {
            "category":"Shopping",
            "subcategory":"Crafts & Fabrics",
            "type":"Retail Goods"
        }
    ],
    "sg:phone":"+39 0331 302980",
    "sg:postcode":"21015",
    "sg:province":"Varese",
    "wof:name":"Allavelli Michele S.r.l.",
    "wof:placetype":"venue"
},
  "geometry": {"coordinates":[8.8263845444,45.8176040649],"type":"Point"}
}