{
  "type": "Feature",
  "properties": {
    "iso:country":"IT",
    "sg:address":"10153 Torino",
    "sg:city":"Torino",
    "sg:orig_category":"Arredi Ed Attrezzature Per Attivita' Commerciali Ed Artigianali",
    "sg:phone":"+39 011 817 7707",
    "sg:postcode":"10153",
    "sg:province":"Torino",
    "sg:website":"http://www.expobonomi.com",
    "wof:name":"Espositori Bonomi Sas Di Toscano Diana",
    "wof:placetype":"venue"
},
  "geometry": {"coordinates":[7.711234,45.069626],"type":"Point"}
}