{
  "type": "Feature",
  "properties": {
    "iso:country":"IT",
    "sg:address":"194/a, Via Cornazzano 43100 Parma",
    "sg:city":"Parma",
    "sg:classifiers":[
        {
            "category":"Manufacturing",
            "subcategory":"Tools & Machinery",
            "type":"Manufacturing & Wholesale Goods"
        }
    ],
    "sg:phone":"+39 0521 605441",
    "sg:postcode":"43100",
    "sg:province":"Parma",
    "sg:tags":[
        "environment",
        "equipment",
        "-"
    ],
    "wof:name":"S.o.v.e. Costruzioni (s.p.a.)",
    "wof:placetype":"venue"
},
  "geometry": {"coordinates":[10.29492,44.823208],"type":"Point"}
}