{
  "type": "Feature",
  "properties": {
    "iso:country":"IT",
    "sg:address":"25, V. Silvio Pellico 80040 Cercola",
    "sg:city":"Cercola",
    "sg:classifiers":[
        {
            "category":"Retail",
            "subcategory":"Animal Services",
            "type":"Services"
        }
    ],
    "sg:phone":"+39 081 555 1431",
    "sg:postcode":"80040",
    "sg:province":"Napoli",
    "sg:tags":[
        "breeding"
    ],
    "wof:name":"Eurocuoio",
    "wof:placetype":"venue"
},
  "geometry": {"coordinates":[14.359228,40.859108],"type":"Point"}
}