{
  "type": "Feature",
  "properties": {
    "iso:country":"IT",
    "sg:address":"2765, Via Emilia Ponente 40024 Castel San Pietro Terme",
    "sg:city":"Castel San Pietro Terme",
    "sg:classifiers":[
        {
            "category":"Manufacturing",
            "subcategory":"Tools & Machinery",
            "type":"Manufacturing & Wholesale Goods"
        }
    ],
    "sg:phone":"+39 39051942072",
    "sg:postcode":"40024",
    "sg:province":"Bologna",
    "sg:tags":[
        "environment",
        "equipment",
        "-"
    ],
    "wof:name":"Cams Srl",
    "wof:placetype":"venue"
},
  "geometry": {"coordinates":[11.580718,44.40934],"type":"Point"}
}