{
  "type": "Feature",
  "properties": {
    "iso:country":"IT",
    "sg:address":"38014 Gardolo",
    "sg:orig_category":"Apparecchiature E Sistemi Per Magazzinaggio E Movimentazione. Servizi Di Magazzinaggio E Movimentazione",
    "sg:phone":"+39 0461 990100",
    "sg:province":"TN",
    "sg:website":"http://www.santoniautogru.com",
    "wof:name":"Santoni Srl",
    "wof:placetype":"venue"
},
  "geometry": {"coordinates":[11.11063,46.124554],"type":"Point"}
}