{
  "type": "Feature",
  "properties": {
    "iso:country":"IT",
    "sg:address":"89124 Reggio Calabria",
    "sg:orig_category":"Studi E Consulenze Amministrative, Commerciali E Aziendali. Banche E Servizi Finanziari. Agenzie D'affari E Servizi Commerciali. Consulenze Tecniche, Amministrative E Perizie",
    "sg:phone":"+39 0965 312279",
    "sg:province":"RC",
    "sg:website":"http://www.emmeservice.it",
    "wof:name":"Emmeservice Sas Di Mensitieri Edoardo & Figli",
    "wof:placetype":"venue"
},
  "geometry": {"coordinates":[15.661781,38.115322],"type":"Point"}
}