{
  "type": "Feature",
  "properties": {
    "addr:full":"12022 Busca Busca Cuneo 12022",
    "addr:postcode":"12022;12022",
    "iso:country":"IT",
    "sg:address":"12022 Busca",
    "sg:city":"Busca",
    "sg:classifiers":[
        {
            "category":"Manufacturing",
            "subcategory":"Rubber & Plastics",
            "type":"Manufacturing & Wholesale Goods"
        }
    ],
    "sg:phone":"+39 0171 945406",
    "sg:postcode":"12022",
    "sg:province":"Cuneo",
    "sg:tags":[
        "building",
        "articles",
        "product",
        "plastics",
        "material"
    ],
    "sg:website":"http://www.tegeabusca.it",
    "wof:name":"Tegea Snc Di Abello Franco & C.",
    "wof:placetype":"venue"
},
  "geometry": {"coordinates":[7.4780750275,44.4868659973],"type":"Point"}
}