{
  "type": "Feature",
  "properties": {
    "iso:country":"IT",
    "sg:address":"1, Via Arco Torre 83029 Solofra",
    "sg:city":"Solofra",
    "sg:classifiers":[
        {
            "category":"Wholesale",
            "subcategory":"Drugs",
            "type":"Manufacturing & Wholesale Goods"
        }
    ],
    "sg:phone":"+39 0825 534733",
    "sg:postcode":"83029",
    "sg:province":"Avellino",
    "sg:tags":[
        "chemical",
        "pharmaceutical"
    ],
    "wof:name":"C.g. Chemical Spa",
    "wof:placetype":"venue"
},
  "geometry": {"coordinates":[14.792723,40.914749],"type":"Point"}
}