{
  "type": "Feature",
  "properties": {
    "iso:country":"IT",
    "sg:address":"61032 Fano",
    "sg:city":"Bellocchi",
    "sg:orig_category":"Porte Pieghevoli E Scorrevoli",
    "sg:phone":"+39 0721 855448",
    "sg:postcode":"61032",
    "sg:province":"Pesaro E Urbino",
    "wof:name":"Fanoflex Di Fenzi Marinella",
    "wof:placetype":"venue"
},
  "geometry": {"coordinates":[13.0089902878,43.7861328125],"type":"Point"}
}