{
  "type": "Feature",
  "properties": {
    "addr:full":"22, Via Grandi Achille 97100 Ragusa Ragusa Ragusa 97100",
    "addr:postcode":"97100;97100",
    "addr:street":"Via Grandi Achille",
    "iso:country":"IT",
    "sg:address":"22, Via Grandi Achille 97100 Ragusa",
    "sg:city":"Ragusa",
    "sg:classifiers":[
        {
            "category":"Autos & Motor Vehicles",
            "subcategory":"Automobile Sales",
            "type":"Retail Goods"
        }
    ],
    "sg:phone":"+39 0932 621212",
    "sg:postcode":"97100",
    "sg:province":"Ragusa",
    "sg:tags":[
        "motor-cars"
    ],
    "wof:name":"Gi.bi.auto (s.r.l.)",
    "wof:placetype":"venue"
},
  "geometry": {"coordinates":[14.7285032272,36.9259109497],"type":"Point"}
}