{
  "type": "Feature",
  "properties": {
    "iso:country":"IT",
    "sg:address":"13, Via Pietro Nenni 61042 Apecchio",
    "sg:city":"Apecchio",
    "sg:classifiers":[
        {
            "category":"Shopping",
            "subcategory":"Clothing, Apparel, & Fashions",
            "type":"Retail Goods"
        }
    ],
    "sg:phone":"+39 39072298001",
    "sg:postcode":"61042",
    "sg:province":"Pesaro E Urbino",
    "sg:tags":[
        "clothes"
    ],
    "wof:name":"Maglificio Fb S.r.l.",
    "wof:placetype":"venue"
},
  "geometry": {"coordinates":[12.429591,43.560883],"type":"Point"}
}