{
  "type": "Feature",
  "properties": {
    "addr:full":"20127 Milano Milano Milano 20127",
    "addr:postcode":"20127;20127",
    "iso:country":"IT",
    "sg:address":"20127 Milano",
    "sg:city":"Milano",
    "sg:orig_category":"Motori Ed Organi Di Trasmissione",
    "sg:phone":"+39 02 669 0651",
    "sg:postcode":"20127",
    "sg:province":"Milano",
    "wof:name":"Marzorati (s.p.a.)",
    "wof:placetype":"venue"
},
  "geometry": {"coordinates":[9.2096633911,45.4880714417],"type":"Point"}
}