{
  "type": "Feature",
  "properties": {
    "iso:country":"IT",
    "sg:address":"3, Via Monte Rosa 20020 Arese",
    "sg:city":"Arese",
    "sg:classifiers":[
        {
            "category":"Professional",
            "subcategory":"Engineering",
            "type":"Services"
        }
    ],
    "sg:phone":"+39 39029380825",
    "sg:postcode":"20020",
    "sg:province":"Milano",
    "sg:tags":[
        "machine",
        "-",
        "mechanical"
    ],
    "wof:name":"Cam Costruzione Apparecchiature Meccaniche (s.p.a.)",
    "wof:placetype":"venue"
},
  "geometry": {"coordinates":[9.08219,45.552532],"type":"Point"}
}