{
  "type": "Feature",
  "properties": {
    "iso:country":"IT",
    "sg:address":"11, Contrada Cucullo 66026 Ortona",
    "sg:city":"Ortona",
    "sg:classifiers":[
        {
            "category":"Wholesale",
            "subcategory":"Medical Equipment & Supplies",
            "type":"Manufacturing & Wholesale Goods"
        }
    ],
    "sg:phone":"+39 085 903 2184",
    "sg:postcode":"66026",
    "sg:province":"Chieti",
    "sg:tags":[
        "-",
        "health",
        "instrument"
    ],
    "wof:name":"Artsana Sud S.p.a.",
    "wof:placetype":"venue"
},
  "geometry": {"coordinates":[14.361895,42.306915],"type":"Point"}
}