{
  "type": "Feature",
  "properties": {
    "addr:full":"80144 Napoli Napoli Napoli 80144",
    "addr:housenumber":"80144",
    "addr:postcode":"80144",
    "iso:country":"IT",
    "sg:address":"80144 Napoli",
    "sg:city":"Napoli",
    "sg:orig_category":"Medicinali E Prodotti Parafarmaceutici. Prodotti Cosmetici E Da Toeletta",
    "sg:phone":"+39 081 701 2658",
    "sg:postcode":"80144",
    "sg:province":"Napoli",
    "wof:name":"Farmacia Basile Giannini Snc",
    "wof:placetype":"venue"
},
  "geometry": {"coordinates":[14.2360887527,40.9021720886],"type":"Point"}
}