{
  "type": "Feature",
  "properties": {
    "iso:country":"IT",
    "sg:address":"7, Via Albert Einstein 63025 Montegiorgio",
    "sg:city":"Montegiorgio",
    "sg:classifiers":[
        {
            "category":"Personal",
            "subcategory":"Shoe Repair & Shine",
            "type":"Services"
        }
    ],
    "sg:phone":"+39 0734 967224",
    "sg:postcode":"63025",
    "sg:province":"Ascoli Piceno",
    "sg:tags":[
        "leather"
    ],
    "wof:name":"Calzaturificio Melania Spa",
    "wof:placetype":"venue"
},
  "geometry": {"coordinates":[13.561673,43.113651],"type":"Point"}
}