{
  "type": "Feature",
  "properties": {
    "iso:country":"IT",
    "sg:address":"Via Fratelli Micheli, 1/3 26845 Codogno",
    "sg:city":"Codogno",
    "sg:classifiers":[
        {
            "category":"Manufacturing",
            "subcategory":"Chemicals & Compounds",
            "type":"Manufacturing & Wholesale Goods"
        }
    ],
    "sg:phone":"+39 0377 430429",
    "sg:postcode":"26845",
    "sg:province":"Lodi",
    "sg:tags":[
        "industry",
        "pump"
    ],
    "sg:website":"www.ipipompe.it",
    "wof:name":"Ipi Srl",
    "wof:placetype":"venue"
},
  "geometry": {"coordinates":[9.6932191849,45.1658058167],"type":"Point"}
}