{
  "type": "Feature",
  "properties": {
    "iso:country":"IT",
    "sg:address":"20124 Milano",
    "sg:city":"Milano",
    "sg:orig_category":"Macchine Tessili",
    "sg:phone":"+39 02 2951 3133",
    "sg:postcode":"20124",
    "sg:province":"Milano",
    "wof:name":"Sacconaghi Monaco Srl",
    "wof:placetype":"venue"
},
  "geometry": {"coordinates":[9.206601,45.478512],"type":"Point"}
}