{
  "type": "Feature",
  "properties": {
    "iso:country":"IT",
    "sg:address":"52100 Arezzo",
    "sg:city":"Arezzo",
    "sg:orig_category":"Serramenti Ed Infissi",
    "sg:phone":"+39 0575 398411",
    "sg:postcode":"52100",
    "sg:province":"Arezzo",
    "sg:website":"http://www.tecnser.it",
    "wof:name":"Tecnoserramenti Srl",
    "wof:placetype":"venue"
},
  "geometry": {"coordinates":[11.890934,43.460911],"type":"Point"}
}