{
  "type": "Feature",
  "properties": {
    "iso:country":"IT",
    "sg:address":"1, Via Venezia 10092 Beinasco",
    "sg:city":"Beinasco",
    "sg:classifiers":[
        {
            "category":"Manufacturing",
            "subcategory":"Motor Vehicles & Parts",
            "type":"Manufacturing & Wholesale Goods"
        }
    ],
    "sg:phone":"+39 011 397 2472",
    "sg:postcode":"10092",
    "sg:province":"Torino",
    "sg:tags":[
        "engine"
    ],
    "wof:name":"Lifel (s.a.s.)",
    "wof:placetype":"venue"
},
  "geometry": {"coordinates":[7.603141,45.028374],"type":"Point"}
}