{
  "type": "Feature",
  "properties": {
    "iso:country":"IT",
    "sg:address":"39, Via Lavoro E Industria 25030 Coccaglio",
    "sg:city":"Coccaglio",
    "sg:classifiers":[
        {
            "category":"Manufacturing",
            "subcategory":"Metals",
            "type":"Manufacturing & Wholesale Goods"
        }
    ],
    "sg:phone":"+39 030 772 1495",
    "sg:postcode":"25030",
    "sg:province":"Brescia",
    "sg:tags":[
        "metallurgy",
        "metalworking"
    ],
    "wof:name":"Fil Stampi",
    "wof:placetype":"venue"
},
  "geometry": {"coordinates":[9.9562110901,45.5696640015],"type":"Point"}
}