{
  "type": "Feature",
  "properties": {
    "addr:full":"Via Dell'industria 36036 Torrebelvicino Torrebelvicino Vicenza 36036",
    "addr:postcode":"36036;36036",
    "addr:street":"Via Dell'Industria",
    "iso:country":"IT",
    "sg:address":"Via Dell'industria 36036 Torrebelvicino",
    "sg:city":"Torrebelvicino",
    "sg:classifiers":[
        {
            "category":"Organizations",
            "subcategory":"Labor Organization",
            "type":"Services"
        }
    ],
    "sg:phone":"+39 0445 661299",
    "sg:postcode":"36036",
    "sg:province":"Vicenza",
    "sg:tags":[
        "woodworking",
        "machinery"
    ],
    "wof:name":"S.i.m.a.l. Srl",
    "wof:placetype":"venue"
},
  "geometry": {"coordinates":[11.323957,45.712246],"type":"Point"}
}