{
  "type": "Feature",
  "properties": {
    "iso:country":"IT",
    "sg:address":"92026 Favara",
    "sg:city":"Favara",
    "sg:orig_category":"Macchine Per Cucire - Commercio E Riparazione",
    "sg:phone":"+39 0922 34666",
    "sg:postcode":"92026",
    "sg:province":"Agrigento",
    "wof:name":"Gandolfo Raimondo",
    "wof:placetype":"venue"
},
  "geometry": {"coordinates":[13.671006,37.298168],"type":"Point"}
}