{
  "type": "Feature",
  "properties": {
    "iso:country":"IT",
    "sg:address":"24122 Bergamo",
    "sg:city":"Bergamo",
    "sg:orig_category":"Ospedali E Servizi Sanitari. Centri Di Estetica E Cosmesi E Servizi",
    "sg:phone":"+39 035 245265",
    "sg:postcode":"24122",
    "sg:province":"Bergamo",
    "wof:name":"Centro Podografico S.r.l.",
    "wof:placetype":"venue"
},
  "geometry": {"coordinates":[9.665857,45.694897],"type":"Point"}
}