{
  "type": "Feature",
  "properties": {
    "addr:full":"50020 Cerbaia Cerbaia Firenze 50020",
    "addr:postcode":"50020;50020",
    "addr:street":"Cerbaia",
    "iso:country":"IT",
    "sg:address":"50020 Cerbaia",
    "sg:city":"Cerbaia",
    "sg:orig_category":"Motori Ed Organi Di Trasmissione. Ricambi E Componenti Dei Mezzi Di Trasporto",
    "sg:phone":"+39 055 826303",
    "sg:postcode":"50020",
    "sg:province":"Firenze",
    "wof:name":"Cipriani Rappresentanze",
    "wof:placetype":"venue"
},
  "geometry": {"coordinates":[11.162443161,43.6993408203],"type":"Point"}
}