{
  "type": "Feature",
  "properties": {
    "iso:country":"IT",
    "sg:address":"80013 Casalnuovo",
    "sg:orig_category":"Impiantistica E Prodotti Tecnologici Per Edilizia",
    "sg:phone":"+39 081 842 1211",
    "sg:postcode":"80013",
    "sg:province":"Napoli",
    "sg:website":"http://www.rimasrl.com",
    "wof:name":"Rima Srl",
    "wof:placetype":"venue"
},
  "geometry": {"coordinates":[14.338778,40.923759],"type":"Point"}
}