{
  "type": "Feature",
  "properties": {
    "iso:country":"IT",
    "sg:address":"Via Delle Querce 6 61040 Sant'ippolito",
    "sg:classifiers":[
        {
            "category":"Shopping",
            "subcategory":"Discount & Variety Stores",
            "type":"Retail Goods"
        }
    ],
    "sg:phone":"+39 0721 8881",
    "sg:postcode":"61040",
    "sg:province":"Pesaro E Urbino",
    "sg:tags":[
        "shop",
        "fitting"
    ],
    "sg:website":"www.mep.it",
    "wof:name":"Mep Spa",
    "wof:placetype":"venue"
},
  "geometry": {"coordinates":[12.5298032761,43.633556366],"type":"Point"}
}