{
  "type": "Feature",
  "properties": {
    "iso:country":"IT",
    "sg:address":"50028 Tavarnelle Val Di Pesa",
    "sg:city":"Sambuca",
    "sg:orig_category":"Maglieria - Produzione E Ingrosso",
    "sg:phone":"+39 055 807 1759",
    "sg:postcode":"50028",
    "sg:province":"Firenze",
    "wof:name":"Extramaglia",
    "wof:placetype":"venue"
},
  "geometry": {"coordinates":[11.218378,43.553329],"type":"Point"}
}