{
  "type": "Feature",
  "properties": {
    "iso:country":"IT",
    "sg:address":"70016 Noicattaro",
    "sg:city":"Noicattaro",
    "sg:orig_category":"Alberghi E Strutture Extra Alberghiere. Ospedali E Servizi Sanitari",
    "sg:phone":"+39 080 543 3317",
    "sg:postcode":"70016",
    "sg:province":"Bari",
    "wof:name":"Ge.se.ma. Srl",
    "wof:placetype":"venue"
},
  "geometry": {"coordinates":[16.994894,41.054417],"type":"Point"}
}