{
  "type": "Feature",
  "properties": {
    "iso:country":"IT",
    "sg:address":"20143 Milano",
    "sg:city":"Milano",
    "sg:orig_category":"Professionisti - Studi E Servizi Ed Associazioni Di Interesse Aziendale. Servizi Sociali. Associazioni Ed Organismi Di Interesse Pubblico",
    "sg:phone":"+39 02 819566",
    "sg:postcode":"20143",
    "sg:province":"Milano",
    "wof:name":"Cassa Pensioni Ai Sanitari",
    "wof:placetype":"venue"
},
  "geometry": {"coordinates":[9.171746254,45.4160003662],"type":"Point"}
}