{
  "type": "Feature",
  "properties": {
    "iso:country":"IT",
    "sg:address":"74100 Taranto",
    "sg:city":"Taranto",
    "sg:orig_category":"Impiantistica E Prodotti Tecnologici Per Edilizia. Forniture Industriali Per Prevenzione, Controllo E Sicurezza",
    "sg:phone":"+39 099 736 5634",
    "sg:postcode":"74100",
    "sg:province":"Taranto",
    "wof:name":"F E I P Di Penna Luigi",
    "wof:placetype":"venue"
},
  "geometry": {"coordinates":[17.245663,40.46825],"type":"Point"}
}