{
  "type": "Feature",
  "properties": {
    "iso:country":"IT",
    "sg:address":"73029 Vernole",
    "sg:city":"Vernole",
    "sg:orig_category":"Impiantistica E Prodotti Tecnologici Per Edilizia. Elettronica Professionale E Di Consumo. Accessori Dei Mezzi Di Trasporto. Forniture Industriali Per Prevenzione, Controllo E Sicurezza",
    "sg:phone":"+39 0832 891230",
    "sg:postcode":"73029",
    "sg:province":"Lecce",
    "wof:name":"Istituto Di Vigilanza Alma Roma",
    "wof:placetype":"venue"
},
  "geometry": {"coordinates":[18.268848,40.262238],"type":"Point"}
}