{
  "type": "Feature",
  "properties": {
    "iso:country":"IT",
    "sg:address":"10043 Orbassano",
    "sg:city":"Orbassano",
    "sg:orig_category":"Forniture Per Edilizia E Lavori Pubblici. Forniture Industriali Per Prevenzione, Controllo E Sicurezza",
    "sg:phone":"+39 011 901 4849",
    "sg:postcode":"10043",
    "sg:province":"Torino",
    "wof:name":"Infosegnali Di Vicario Massimo",
    "wof:placetype":"venue"
},
  "geometry": {"coordinates":[7.5513453484,44.9949645996],"type":"Point"}
}