{
  "type": "Feature",
  "properties": {
    "iso:country":"IT",
    "sg:address":"50028 Tavarnelle Val Di Pesa",
    "sg:city":"Sambuca",
    "sg:classifiers":[
        {
            "category":"Shopping",
            "subcategory":"Hobbies, Toys, & Games",
            "type":"Retail Goods"
        }
    ],
    "sg:phone":"+39 055 807 0309",
    "sg:postcode":"50028",
    "sg:province":"Firenze",
    "sg:tags":[
        "article",
        "sport",
        "supply"
    ],
    "wof:name":"Carbon Dream Spa",
    "wof:placetype":"venue"
},
  "geometry": {"coordinates":[11.218378,43.553329],"type":"Point"}
}