{
  "type": "Feature",
  "properties": {
    "iso:country":"IT",
    "sg:address":"83, Via Crevada 31020 San Pietro Di Feletto",
    "sg:city":"San Pietro di Feletto",
    "sg:classifiers":[
        {
            "category":"Manufacturing",
            "subcategory":"Wood Products",
            "type":"Manufacturing & Wholesale Goods"
        }
    ],
    "sg:phone":"+39 39043864820",
    "sg:postcode":"31020",
    "sg:province":"Treviso",
    "sg:tags":[
        "furniture"
    ],
    "wof:name":"Amorim Cork Italia S.p.a.",
    "wof:placetype":"venue"
},
  "geometry": {"coordinates":[12.252101,45.869621],"type":"Point"}
}