{
  "type": "Feature",
  "properties": {
    "addr:full":"27029 Vigevano Vigevano Pavia 27029",
    "addr:postcode":"27029;27029",
    "iso:country":"IT",
    "sg:address":"27029 Vigevano",
    "sg:city":"Vigevano",
    "sg:orig_category":"Forniture Per Edilizia E Lavori Pubblici. Forniture Industriali Per Prevenzione, Controllo E Sicurezza",
    "sg:phone":"+39 0381 344098",
    "sg:postcode":"27029",
    "sg:province":"Pavia",
    "wof:name":"C.e.v. Costruzione Estintori Vigevanese",
    "wof:placetype":"venue"
},
  "geometry": {"coordinates":[8.8671789169,45.3039894104],"type":"Point"}
}