{
  "type": "Feature",
  "properties": {
    "addr:full":"20154 Milano Milano Milano 20154",
    "addr:postcode":"20154;20154",
    "iso:country":"IT",
    "sg:address":"20154 Milano",
    "sg:city":"Milano",
    "sg:orig_category":"Forniture Per Abbigliamento E Pelletterie. Forniture E Materiali Per Imballaggio E Confezionamento",
    "sg:phone":"+39 02 347021",
    "sg:postcode":"20154",
    "sg:province":"Milano",
    "wof:name":"Alfieri Rosalinda",
    "wof:placetype":"venue"
},
  "geometry": {"coordinates":[9.1687889099,45.4854164124],"type":"Point"}
}