{
  "type": "Feature",
  "properties": {
    "iso:country":"IT",
    "sg:address":"00185 Roma",
    "sg:city":"Roma",
    "sg:orig_category":"Lavorazioni Meccaniche E Servizi",
    "sg:phone":"+39 06 7045 3473",
    "sg:postcode":"00185",
    "sg:province":"Roma",
    "wof:name":"Zoppo Sergio",
    "wof:placetype":"venue"
},
  "geometry": {"coordinates":[12.501666,41.892483],"type":"Point"}
}