{
  "type": "Feature",
  "properties": {
    "iso:country":"IT",
    "sg:address":"46, Via Limitese 50059 Vinci",
    "sg:city":"Vinci",
    "sg:classifiers":[
        {
            "category":"Manufacturing",
            "subcategory":"Glass & Minerals",
            "type":"Manufacturing & Wholesale Goods"
        }
    ],
    "sg:phone":"+39 0571 902311",
    "sg:postcode":"50059",
    "sg:province":"Firenze",
    "wof:name":"Glass Design",
    "wof:placetype":"venue"
},
  "geometry": {"coordinates":[10.956163,43.73341],"type":"Point"}
}