{
  "type": "Feature",
  "properties": {
    "iso:country":"IT",
    "sg:address":"Piazza Duca D'aosta 12 20124 Milano",
    "sg:city":"Milano",
    "sg:classifiers":[
        {
            "category":"Manufacturing",
            "subcategory":"Chemicals & Compounds",
            "type":"Manufacturing & Wholesale Goods"
        }
    ],
    "sg:phone":"+39 02 670 3441",
    "sg:postcode":"20124",
    "sg:province":"Milano",
    "sg:tags":[
        "base"
    ],
    "wof:name":"Telma Srl",
    "wof:placetype":"venue"
},
  "geometry": {"coordinates":[9.203326,45.485268],"type":"Point"}
}