{
  "type": "Feature",
  "properties": {
    "iso:country":"IT",
    "sg:address":"106/a, Via Fila 13835 Trivero",
    "sg:city":"Trivero",
    "sg:classifiers":[
        {
            "category":"Professional",
            "subcategory":"Engineering",
            "type":"Services"
        }
    ],
    "sg:phone":"+39 39015737459",
    "sg:postcode":"13835",
    "sg:province":"Biella",
    "sg:tags":[
        "machine",
        "-",
        "mechanical"
    ],
    "wof:name":"Ritorcitura Rita Di Foglia Gianola & C. (s.n.c.)",
    "wof:placetype":"venue"
},
  "geometry": {"coordinates":[8.05827,45.562836],"type":"Point"}
}