{
  "type": "Feature",
  "properties": {
    "iso:country":"IT",
    "sg:address":"03040 San Vittore Del Lazio",
    "sg:city":"San Vittore del Lazio",
    "sg:orig_category":"Prodotti Chimici Secondari",
    "sg:phone":"+39 0776 335444",
    "sg:postcode":"03040",
    "sg:province":"Frosinone",
    "wof:name":"Vano Sud Srl",
    "wof:placetype":"venue"
},
  "geometry": {"coordinates":[13.9337778091,41.4625015259],"type":"Point"}
}