{
  "type": "Feature",
  "properties": {
    "iso:country":"IT",
    "sg:address":"33044 Manzano",
    "sg:city":"Manzano",
    "sg:orig_category":"Arredamento Alberghi",
    "sg:phone":"+39 0432 754004",
    "sg:postcode":"33044",
    "sg:province":"Udine",
    "sg:website":"http://www.triangolo-export.it",
    "wof:name":"Triangolo Export Srl",
    "wof:placetype":"venue"
},
  "geometry": {"coordinates":[13.374782,45.985203],"type":"Point"}
}