{
  "type": "Feature",
  "properties": {
    "addr:full":"35030 Selvazzano Dentro Selvazzano Dentro Padova 35030",
    "addr:postcode":"35030;35030",
    "iso:country":"IT",
    "sg:address":"35030 Selvazzano Dentro",
    "sg:city":"Selvazzano Dentro",
    "sg:orig_category":"Macchine Ed Impianti Per Edilizia E Lavori Pubblici",
    "sg:phone":"+39 049 637180",
    "sg:postcode":"35030",
    "sg:province":"Padova",
    "wof:name":"Sorme Di Pressato Luigi",
    "wof:placetype":"venue"
},
  "geometry": {"coordinates":[11.785865,45.386845],"type":"Point"}
}