{
  "type": "Feature",
  "properties": {
    "iso:country":"IT",
    "sg:address":"14, Via Raso 25036 Palazzolo Sull'oglio",
    "sg:classifiers":[
        {
            "category":"Professional",
            "subcategory":"Engineering",
            "type":"Services"
        }
    ],
    "sg:phone":"+39 030 740 0120",
    "sg:postcode":"25036",
    "sg:province":"Brescia",
    "sg:tags":[
        "machine",
        "-",
        "mechanical"
    ],
    "wof:name":"Fustellificio P.l. Di Lancini E Pagani (s.n.c.)",
    "wof:placetype":"venue"
},
  "geometry": {"coordinates":[9.890089,45.584728],"type":"Point"}
}