{
  "type": "Feature",
  "properties": {
    "addr:full":"30175 Mestre Mestre Venezia 30175",
    "addr:postcode":"30175;30175",
    "addr:street":"Mestre Mestre Venezia",
    "iso:country":"IT",
    "sg:address":"30175 Mestre",
    "sg:city":"Mestre",
    "sg:orig_category":"Avvocati, Notai E Servizi Legali. Consulenze Tecniche, Amministrative E Perizie",
    "sg:phone":"+39 041 531 8104",
    "sg:postcode":"30175",
    "sg:province":"Venezia",
    "wof:name":"Venimm S.r.l.",
    "wof:placetype":"venue"
},
  "geometry": {"coordinates":[12.249589,45.479744],"type":"Point"}
}