{
  "type": "Feature",
  "properties": {
    "iso:country":"IT",
    "sg:address":"Via A. Colombo 205 21055 Gorla Minore",
    "sg:city":"Gorla Minore",
    "sg:classifiers":[
        {
            "category":"Wholesale",
            "subcategory":"Painting Supplies",
            "type":"Manufacturing & Wholesale Goods"
        }
    ],
    "sg:phone":"+39 0331 365300",
    "sg:postcode":"21055",
    "sg:province":"Varese",
    "sg:tags":[
        "canvas"
    ],
    "wof:name":"Gencla Srl",
    "wof:placetype":"venue"
},
  "geometry": {"coordinates":[8.826385,45.817604],"type":"Point"}
}