{
  "type": "Feature",
  "properties": {
    "iso:country":"IT",
    "sg:address":"36050 Bolzano Vicentino",
    "sg:city":"Bolzano Vicentino",
    "sg:orig_category":"Ponteggi Per Edilizia",
    "sg:phone":"+39 0444 350262",
    "sg:postcode":"36050",
    "sg:province":"Vicenza",
    "wof:name":"Edilnoleggi Valente Di Valente Ampelio & C. Snc",
    "wof:placetype":"venue"
},
  "geometry": {"coordinates":[11.6374349594,45.5946922302],"type":"Point"}
}