{
  "type": "Feature",
  "properties": {
    "iso:country":"IT",
    "sg:address":"16149 Genova",
    "sg:city":"Genova",
    "sg:orig_category":"Abbigliamento Esterno, Maglierie E Pelliccerie",
    "sg:phone":"+39 010 252035",
    "sg:postcode":"16149",
    "sg:province":"Genova",
    "wof:name":"Riberti Luigi",
    "wof:placetype":"venue"
},
  "geometry": {"coordinates":[8.903655,44.408272],"type":"Point"}
}