{
  "type": "Feature",
  "properties": {
    "iso:country":"IT",
    "sg:address":"Corso Di Porta Nuova 3/a, 20121 Milan, Mi",
    "sg:classifiers":[
        {
            "category":"Banks & Credit Unions",
            "subcategory":"Bank",
            "type":"Services"
        }
    ],
    "sg:phone":"+39 02 762931",
    "sg:postcode":"20121",
    "sg:province":"Milano",
    "sg:website":"http://www.bcigestioni.it",
    "wof:name":"Nextra Investment Management Sgr",
    "wof:placetype":"venue"
},
  "geometry": {"coordinates":[9.191386,45.473984],"type":"Point"}
}