{
  "type": "Feature",
  "properties": {
    "addr:full":"Via Malpaga 7 20088 Rosate Rosate Milano 20088",
    "addr:housenumber":"7",
    "addr:postcode":"20088;20088",
    "addr:street":"Via Malpaga",
    "iso:country":"IT",
    "sg:address":"Via Malpaga 7 20088 Rosate",
    "sg:city":"Rosate",
    "sg:classifiers":[
        {
            "category":"Retail",
            "subcategory":"Car Wash",
            "type":"Services"
        }
    ],
    "sg:phone":"+39 02 9084 8291",
    "sg:postcode":"20088",
    "sg:province":"Milano",
    "sg:tags":[
        "motor",
        "washing",
        "cleaning",
        "agent",
        "vehicle"
    ],
    "sg:website":"www.sacirest.com",
    "wof:name":"Sacir Est Di Rischio Antonio E Giuseppe Prodotti Snc",
    "wof:placetype":"venue"
},
  "geometry": {"coordinates":[9.013252,45.342995],"type":"Point"}
}