{
  "type": "Feature",
  "properties": {
    "addr:full":"19, Via Ponticello 35129 Padova Padova Padova 35129",
    "addr:postcode":"35129;35129",
    "addr:street":"Via Ponticello",
    "iso:country":"IT",
    "sg:address":"19, Via Ponticello 35129 Padova",
    "sg:city":"Padova",
    "sg:classifiers":[
        {
            "category":"Wholesale",
            "subcategory":"Drugs",
            "type":"Manufacturing & Wholesale Goods"
        }
    ],
    "sg:phone":"+39 39049773077",
    "sg:postcode":"35129",
    "sg:province":"Padova",
    "sg:tags":[
        "chemical",
        "pharmaceutical"
    ],
    "wof:name":"Q8 Quaser S.r.l.",
    "wof:placetype":"venue"
},
  "geometry": {"coordinates":[11.656878,44.977913],"type":"Point"}
}