{
  "type": "Feature",
  "properties": {
    "iso:country":"IT",
    "sg:address":"20092 Cinisello Balsamo",
    "sg:city":"Cinisello Balsamo",
    "sg:orig_category":"Elettrotecnica Industriale, Prodotti E Apparecchiature. Ricambi E Componenti Dei Mezzi Di Trasporto",
    "sg:phone":"+39 02 6601 7224",
    "sg:postcode":"20092",
    "sg:province":"Milano",
    "wof:name":"M Sicurezza Sas",
    "wof:placetype":"venue"
},
  "geometry": {"coordinates":[9.252127,45.556271],"type":"Point"}
}