{
  "type": "Feature",
  "properties": {
    "iso:country":"IT",
    "sg:address":"00198 Roma",
    "sg:city":"Roma",
    "sg:classifiers":[
        {
            "category":"Health Services",
            "subcategory":"Health Practitioner",
            "type":"Services"
        }
    ],
    "sg:phone":"+39 06 855 1715",
    "sg:postcode":"00198",
    "sg:province":"Roma",
    "sg:tags":[
        "medici"
    ],
    "wof:name":"Bormioli Pietro",
    "wof:placetype":"venue"
},
  "geometry": {"coordinates":[12.496678,41.920944],"type":"Point"}
}