{
  "type": "Feature",
  "properties": {
    "addr:full":"50126 Firenze Firenze Firenze 50126",
    "addr:postcode":"50126;50126",
    "iso:country":"IT",
    "sg:address":"50126 Firenze",
    "sg:city":"Firenze",
    "sg:orig_category":"Alimenti Dietetici, Macrobiotici E Biologici - Vendita Al Dettaglio",
    "sg:phone":"+39 055 689488",
    "sg:postcode":"50126",
    "sg:province":"Firenze",
    "wof:name":"Istituto Di Estetica Cambi",
    "wof:placetype":"venue"
},
  "geometry": {"coordinates":[10.747909,43.860737],"type":"Point"}
}