{
  "type": "Feature",
  "properties": {
    "addr:full":"40050 Argelato Argelato Bologna 40050",
    "addr:postcode":"40050;40050",
    "iso:country":"IT",
    "sg:address":"40050 Argelato",
    "sg:city":"Argelato",
    "sg:orig_category":"Ristorazione E Locali Pubblici Affini. Ristoranti Ed Esercizi Affini",
    "sg:phone":"+39 051 869711",
    "sg:postcode":"40050",
    "sg:province":"Bologna",
    "sg:website":"http://www.orma2.it",
    "wof:name":"Orma Srl",
    "wof:placetype":"venue"
},
  "geometry": {"coordinates":[11.362763,44.60516],"type":"Point"}
}