{
  "type": "Feature",
  "properties": {
    "iso:country":"IT",
    "sg:address":"14, Via Avrese Pietro 37045 Legnago",
    "sg:city":"Legnago",
    "sg:classifiers":[
        {
            "category":"Shopping",
            "subcategory":"Clothing, Apparel, & Fashions",
            "type":"Retail Goods"
        }
    ],
    "sg:phone":"+39 39044222138",
    "sg:postcode":"37045",
    "sg:province":"Verona",
    "sg:tags":[
        "clothes"
    ],
    "wof:name":"Sillo (s.r.l.)",
    "wof:placetype":"venue"
},
  "geometry": {"coordinates":[11.308832,45.192356],"type":"Point"}
}