{
  "type": "Feature",
  "properties": {
    "iso:country":"IT",
    "sg:address":"21022 Azzate",
    "sg:city":"Azzate",
    "sg:classifiers":[
        {
            "category":"Professional",
            "subcategory":"Printing & Photocopies",
            "type":"Services"
        }
    ],
    "sg:phone":"+39 0332 457753",
    "sg:postcode":"21022",
    "sg:province":"Varese",
    "sg:tags":[
        "publishing"
    ],
    "wof:name":"Rb Grafiche Musicali",
    "wof:placetype":"venue"
},
  "geometry": {"coordinates":[8.7919740677,45.7823143005],"type":"Point"}
}