{
  "type": "Feature",
  "properties": {
    "iso:country":"IT",
    "sg:address":"20089 Rozzano",
    "sg:city":"Rozzano",
    "sg:orig_category":"Termotecnica E Riscaldamento, Apparecchiature E Servizi. Prodotti Vari In Metallo",
    "sg:phone":"+39 02 825 5134",
    "sg:postcode":"20089",
    "sg:province":"Milano",
    "wof:name":"Laderchi Alessandro",
    "wof:placetype":"venue"
},
  "geometry": {"coordinates":[9.1584062576,45.3804512024],"type":"Point"}
}