{
  "type": "Feature",
  "properties": {
    "iso:country":"IT",
    "sg:address":"40057 Granarolo Emilia",
    "sg:orig_category":"Stampaggio Gomma",
    "sg:phone":"+39 051 763456",
    "sg:postcode":"40057",
    "sg:province":"Bologna",
    "wof:name":"Sial Di Alessio Simoncini",
    "wof:placetype":"venue"
},
  "geometry": {"coordinates":[11.431458,44.566097],"type":"Point"}
}