{
  "type": "Feature",
  "properties": {
    "addr:full":"Zona Industriale 55060 Guamo Guamo Lucca 55060",
    "addr:postcode":"55060;55060",
    "addr:street":"Zona Industriale",
    "iso:country":"IT",
    "sg:address":"Zona Industriale 55060 Guamo",
    "sg:city":"Guamo",
    "sg:classifiers":[
        {
            "category":"Military Area",
            "subcategory":"Air Force Base",
            "type":"Public Place"
        }
    ],
    "sg:phone":"+39 0583 94446",
    "sg:postcode":"55060",
    "sg:province":"Lucca",
    "sg:tags":[
        "component",
        "occupational",
        "safety"
    ],
    "sg:website":"www.labor-auser.it",
    "wof:name":"Labor S.n.c. Dei F.lli Boschi",
    "wof:placetype":"venue"
},
  "geometry": {"coordinates":[10.507994,43.843014],"type":"Point"}
}