{
  "type": "Feature",
  "properties": {
    "addr:full":"52011 Bibbiena Bibbiena Arezzo 52011",
    "addr:postcode":"52011;52011",
    "iso:country":"IT",
    "sg:address":"52011 Bibbiena",
    "sg:city":"Bibbiena",
    "sg:orig_category":"Abbigliamento Esterno, Maglierie E Pelliccerie. Shopping",
    "sg:phone":"+39 0575 594591",
    "sg:postcode":"52011",
    "sg:province":"Arezzo",
    "wof:name":"Battistoni Maglieria",
    "wof:placetype":"venue"
},
  "geometry": {"coordinates":[11.815875,43.701],"type":"Point"}
}