{
  "type": "Feature",
  "properties": {
    "addr:full":"50013 Campi Bisenzio Campi Bisenzio Firenze 50013",
    "addr:postcode":"50013;50013",
    "addr:street":"Bisenzio",
    "iso:country":"IT",
    "sg:address":"50013 Campi Bisenzio",
    "sg:city":"Campi Bisenzio",
    "sg:orig_category":"Filati E Materie Prime Tessili",
    "sg:phone":"+39 055 89881",
    "sg:postcode":"50013",
    "sg:province":"Firenze",
    "wof:name":"Apollo Spa",
    "wof:placetype":"venue"
},
  "geometry": {"coordinates":[11.1655378342,43.7696685791],"type":"Point"}
}