{
  "type": "Feature",
  "properties": {
    "iso:country":"IT",
    "sg:address":"13, Via Olmo 36055 Nove",
    "sg:city":"Nove",
    "sg:classifiers":[
        {
            "category":"Manufacturing",
            "subcategory":"Glass & Minerals",
            "type":"Manufacturing & Wholesale Goods"
        }
    ],
    "sg:phone":"+39 0424 590311",
    "sg:postcode":"36055",
    "sg:province":"Vicenza",
    "sg:tags":[
        "building",
        "material"
    ],
    "wof:name":"Ceramiche Trea Di Sonda Giovanni & Tolio Adriano",
    "wof:placetype":"venue"
},
  "geometry": {"coordinates":[11.540307,45.545906],"type":"Point"}
}