{
  "type": "Feature",
  "properties": {
    "iso:country":"IT",
    "sg:address":"7/b, Via Per Cento 41034 Finale Emilia",
    "sg:city":"Finale Emilia",
    "sg:classifiers":[
        {
            "category":"Professional",
            "subcategory":"Engineering",
            "type":"Services"
        }
    ],
    "sg:phone":"+39 39053592213",
    "sg:postcode":"41034",
    "sg:province":"Modena",
    "sg:tags":[
        "machine",
        "-",
        "mechanical"
    ],
    "wof:name":"C.d.m. (s.n.c.)",
    "wof:placetype":"venue"
},
  "geometry": {"coordinates":[10.867708,44.650753],"type":"Point"}
}