{
  "type": "Feature",
  "properties": {
    "addr:full":"20047 Brugherio Brugherio Milano 20047",
    "addr:postcode":"20047;20047",
    "iso:country":"IT",
    "sg:address":"20047 Brugherio",
    "sg:city":"Brugherio",
    "sg:orig_category":"Edilizia - Materiali",
    "sg:phone":"+39 039 287 6124",
    "sg:postcode":"20047",
    "sg:province":"Milano",
    "wof:name":"Picchi Srl",
    "wof:placetype":"venue"
},
  "geometry": {"coordinates":[9.22452,45.505966],"type":"Point"}
}