{
  "type": "Feature",
  "properties": {
    "iso:country":"IT",
    "sg:address":"00045 Genzano Di Roma",
    "sg:city":"Genzano di Roma",
    "sg:orig_category":"Prodotti Finiti Stampati. Forniture E Materiali Per Imballaggio E Confezionamento. Forniture Per Attivita' Commerciali Ed Artigianali",
    "sg:phone":"+39 06 939 1501",
    "sg:postcode":"00045",
    "sg:province":"Roma",
    "wof:name":"Rossini Alessandro",
    "wof:placetype":"venue"
},
  "geometry": {"coordinates":[12.6912050247,41.7044715881],"type":"Point"}
}