{
  "type": "Feature",
  "properties": {
    "iso:country":"IT",
    "sg:address":"52037 Sansepolcro",
    "sg:city":"Sansepolcro",
    "sg:orig_category":"Lavorazioni Metalli, Stampaggio E Saldatura",
    "sg:phone":"+39 0575 720537",
    "sg:postcode":"52037",
    "sg:province":"Arezzo",
    "sg:website":"http://www.valentinoborghesicostruzionimeccaniche.it",
    "wof:name":"Borghesi Valentino",
    "wof:placetype":"venue"
},
  "geometry": {"coordinates":[11.885961,43.470135],"type":"Point"}
}