{
  "type": "Feature",
  "properties": {
    "iso:country":"IT",
    "sg:address":"Via Hugo Von Taufers; Campo Tures; 39032",
    "sg:city":"Campo Tures",
    "sg:classifiers":[
        {
            "category":"Banks & Credit Unions",
            "subcategory":"Bank",
            "type":"Services"
        }
    ],
    "sg:phone":"+39 0474 679355",
    "sg:postcode":"39032",
    "sg:province":"Bolzano/Bozen",
    "wof:name":"Banca Di Trento E Bolzano Spa",
    "wof:placetype":"venue"
},
  "geometry": {"coordinates":[11.954383,46.918098],"type":"Point"}
}