{
  "type": "Feature",
  "properties": {
    "iso:country":"IT",
    "sg:address":"Via Ripalta Arpina 19 26020 Madignano",
    "sg:city":"Madignano",
    "sg:classifiers":[
        {
            "category":"Food & Beverages",
            "subcategory":"Meat & Fish",
            "type":"Retail Goods"
        }
    ],
    "sg:phone":"+39 0373 658086",
    "sg:postcode":"26020",
    "sg:province":"Cremona",
    "sg:tags":[
        "product"
    ],
    "sg:website":"www.famascarni.it",
    "wof:name":"Famas Carni Di Ciccioli Primo & C. Sas",
    "wof:placetype":"venue"
},
  "geometry": {"coordinates":[9.705159,45.33445],"type":"Point"}
}