{
  "type": "Feature",
  "properties": {
    "iso:country":"IT",
    "sg:address":"13, Strada Consortile Del Salino 10133 Torino",
    "sg:city":"Torino",
    "sg:classifiers":[
        {
            "category":"Shopping",
            "type":"Retail Goods"
        }
    ],
    "sg:phone":"+39 011 661 3056",
    "sg:postcode":"10133",
    "sg:province":"Torino",
    "sg:tags":[
        "finished",
        "-",
        "metallic"
    ],
    "wof:name":"Cernuschi",
    "wof:placetype":"venue"
},
  "geometry": {"coordinates":[7.6841568947,45.0397148132],"type":"Point"}
}