{
  "type": "Feature",
  "properties": {
    "iso:country":"IT",
    "sg:address":"10135 Torino",
    "sg:city":"Torino",
    "sg:orig_category":"Lavorazioni Meccaniche E Servizi. Riparazione Dei Mezzi Di Trasporto",
    "sg:phone":"+39 011 348 8624",
    "sg:postcode":"10135",
    "sg:province":"Torino",
    "wof:name":"Martoglio & Lentini - Torino (s.r.l.)",
    "wof:placetype":"venue"
},
  "geometry": {"coordinates":[7.624039,45.021557],"type":"Point"}
}