{
  "type": "Feature",
  "properties": {
    "iso:country":"IT",
    "sg:address":"25050 Monte Isola",
    "sg:city":"Monte Isola",
    "sg:orig_category":"Forniture Per Agricoltura E Zootecnia. Forniture Per Attivita' Industriali",
    "sg:phone":"+39 030 988 6129",
    "sg:postcode":"25050",
    "sg:province":"Brescia",
    "wof:name":"Ribola Giovanni",
    "wof:placetype":"venue"
},
  "geometry": {"coordinates":[10.0926589966,45.6936645508],"type":"Point"}
}