{
  "type": "Feature",
  "properties": {
    "iso:country":"IT",
    "sg:address":"25065 Lumezzane",
    "sg:city":"Lumezzane",
    "sg:classifiers":[
        {
            "category":"Government",
            "subcategory":"Office",
            "type":"Public Place"
        }
    ],
    "sg:phone":"+39 030 892 1854",
    "sg:postcode":"25065",
    "sg:province":"Brescia",
    "sg:tags":[
        "e",
        "lo",
        "tempo",
        "libero",
        "per",
        "spettacolo",
        "servizi",
        "culturali",
        "sport",
        "il"
    ],
    "wof:name":"Banda Cittadina Con Majorettes",
    "wof:placetype":"venue"
},
  "geometry": {"coordinates":[10.215693,45.607391],"type":"Point"}
}