{
  "type": "Feature",
  "properties": {
    "iso:country":"IT",
    "sg:address":"Via Fondovalle 2887 41054 Marano Sul Panaro",
    "sg:city":"Marano sul Panaro",
    "sg:classifiers":[
        {
            "category":"Building & Trades",
            "subcategory":"Plumbing",
            "type":"Services"
        }
    ],
    "sg:phone":"+39 059 703151",
    "sg:postcode":"41054",
    "sg:province":"Modena",
    "sg:tags":[
        "steel",
        "pipe",
        "chair"
    ],
    "sg:website":"www.sirotti.com",
    "wof:name":"Sirotti Srl",
    "wof:placetype":"venue"
},
  "geometry": {"coordinates":[10.920126,44.432083],"type":"Point"}
}