{
  "type": "Feature",
  "properties": {
    "addr:full":"Via Saluyyo 34a 12036 Revello Revello Cuneo 12036",
    "addr:housenumber":"34a",
    "addr:postcode":"12036;12036",
    "addr:street":"Via Saluyyo",
    "iso:country":"IT",
    "sg:address":"Via Saluyyo 34a 12036 Revello",
    "sg:city":"Revello",
    "sg:classifiers":[
        {
            "category":"Bus Stop",
            "subcategory":"None",
            "type":"Transportation"
        }
    ],
    "sg:phone":"+39 0175 257276",
    "sg:postcode":"12036",
    "sg:province":"Cuneo",
    "sg:tags":[
        "period",
        "furniture"
    ],
    "wof:name":"Fratelli Balangero Silvano Luigi & Mario Snc",
    "wof:placetype":"venue"
},
  "geometry": {"coordinates":[7.5471105576,44.38879776],"type":"Point"}
}