{
  "type": "Feature",
  "properties": {
    "addr:full":"20094 Corsico Corsico Milano 20094",
    "addr:postcode":"20094;20094",
    "iso:country":"IT",
    "sg:address":"20094 Corsico",
    "sg:city":"Corsico",
    "sg:orig_category":"Professionisti - Studi E Servizi Ed Associazioni Di Interesse Aziendale. Associazioni Ed Organismi Di Interesse Pubblico",
    "sg:phone":"+39 02 440 4115",
    "sg:postcode":"20094",
    "sg:province":"Milano",
    "wof:name":"Genitori Uniti Per L'integrazione Degli Handicappati",
    "wof:placetype":"venue"
},
  "geometry": {"coordinates":[9.1091156006,45.4454727173],"type":"Point"}
}