{
  "type": "Feature",
  "properties": {
    "addr:full":"40129 Bologna Bologna Bologna 40129",
    "addr:postcode":"40129;40129",
    "iso:country":"IT",
    "sg:address":"40129 Bologna",
    "sg:city":"Bologna",
    "sg:orig_category":"Articoli Da Regalo. Hobbistica. Shopping",
    "sg:phone":"+39 051 353922",
    "sg:postcode":"40129",
    "sg:province":"Bologna",
    "wof:name":"Guerra Romano",
    "wof:placetype":"venue"
},
  "geometry": {"coordinates":[11.345089,44.511265],"type":"Point"}
}