{
  "type": "Feature",
  "properties": {
    "iso:country":"IT",
    "sg:address":"20132 Milano",
    "sg:city":"Milano",
    "sg:orig_category":"Aghi E Spilli",
    "sg:phone":"+39 02 284 0375",
    "sg:postcode":"20132",
    "sg:province":"Milano",
    "wof:name":"Haase+k\u00dchn Italia Srl",
    "wof:placetype":"venue"
},
  "geometry": {"coordinates":[9.236906,45.500679],"type":"Point"}
}