{
  "type": "Feature",
  "properties": {
    "addr:full":"Contrada Monte 89024 Polistena Polistena Reggio Di Calabria 89024",
    "addr:postcode":"89024;89024",
    "addr:street":"Contrada Monte",
    "iso:country":"IT",
    "sg:address":"Contrada Monte 89024 Polistena",
    "sg:city":"Polistena",
    "sg:classifiers":[
        {
            "category":"Farming",
            "subcategory":"Livestock Farm",
            "type":"Manufacturing & Wholesale Goods"
        }
    ],
    "sg:phone":"+39 0966 940712",
    "sg:postcode":"89024",
    "sg:province":"Reggio Di Calabria",
    "sg:tags":[
        "agriculture"
    ],
    "wof:name":"Il Monte Societa' Cooperativa Ortofrutticola Agrumaria A R.l.",
    "wof:placetype":"venue"
},
  "geometry": {"coordinates":[15.650137,38.114689],"type":"Point"}
}