{
  "type": "Feature",
  "properties": {
    "iso:country":"IT",
    "sg:address":"10036 Settimo Torinese",
    "sg:city":"Settimo Torinese",
    "sg:orig_category":"Shopping. Prodotti Cosmetici E Da Toeletta",
    "sg:phone":"+39 011 802 3411",
    "sg:postcode":"10036",
    "sg:province":"Torino",
    "wof:name":"Farmen Srl",
    "wof:placetype":"venue"
},
  "geometry": {"coordinates":[7.729383,45.148468],"type":"Point"}
}