{
  "type": "Feature",
  "properties": {
    "addr:full":"80020 Casavatore Casavatore Napoli 80020",
    "addr:postcode":"80020;80020",
    "iso:country":"IT",
    "sg:address":"80020 Casavatore",
    "sg:city":"Casavatore",
    "sg:orig_category":"Servizi E Lavori Per Arredamento E Industria Del Legno. Forniture Per Congressi, Fiere E Manifestazioni. Servizi Per Aziende, Manifestazioni E Supporto Agli Scambi Commerciali",
    "sg:phone":"+39 081 736 3933",
    "sg:postcode":"80020",
    "sg:province":"Napoli",
    "sg:website":"http://www.napoli.com/aletta",
    "wof:name":"Aletta Raffaele & Figli Snc",
    "wof:placetype":"venue"
},
  "geometry": {"coordinates":[14.269464,40.896355],"type":"Point"}
}