{
  "type": "Feature",
  "properties": {
    "iso:country":"IT",
    "sg:address":"20018 Sedriano",
    "sg:city":"Sedriano",
    "sg:orig_category":"Prodotti Alimentari. Shopping",
    "sg:phone":"+39 02 902 1900",
    "sg:postcode":"20018",
    "sg:province":"Milano",
    "wof:name":"Meneghin Tranquillo",
    "wof:placetype":"venue"
},
  "geometry": {"coordinates":[9.0166835785,45.4858856201],"type":"Point"}
}