{
  "type": "Feature",
  "properties": {
    "iso:country":"IT",
    "sg:address":"81100 Caserta",
    "sg:city":"Caserta",
    "sg:orig_category":"Servizi E Lavori Per Edilizia E Lavori Pubblici. Consulenze Tecniche, Amministrative E Perizie",
    "sg:phone":"+39 0823 323686",
    "sg:postcode":"81100",
    "sg:province":"Caserta",
    "wof:name":"Del Gaizo Prof. Avv. Fortuna",
    "wof:placetype":"venue"
},
  "geometry": {"coordinates":[14.338593,41.082939],"type":"Point"}
}