{
  "type": "Feature",
  "properties": {
    "iso:country":"IT",
    "sg:address":"09032 Assemini",
    "sg:city":"Assemini",
    "sg:orig_category":"Ospedali E Servizi Sanitari. Servizi Ausiliari Di Analisi, Controllo E Ricerca",
    "sg:phone":"+39 070 247403",
    "sg:postcode":"09032",
    "sg:province":"Cagliari",
    "wof:name":"Agrostudio Snc Di Farci Maria Laura",
    "wof:placetype":"venue"
},
  "geometry": {"coordinates":[8.994449,39.232208],"type":"Point"}
}