{
  "type": "Feature",
  "properties": {
    "addr:full":"S.da Carignano 33 10040 La Loggia La Loggia Torino 10040",
    "addr:housenumber":"33",
    "addr:postcode":"10040;10040",
    "addr:street":"S.Da Carignano",
    "iso:country":"IT",
    "sg:address":"S.da Carignano 33 10040 La Loggia",
    "sg:city":"La Loggia",
    "sg:classifiers":[
        {
            "category":"Restaurant",
            "type":"Food & Drink"
        }
    ],
    "sg:phone":"+39 011 962 8126",
    "sg:postcode":"10040",
    "sg:province":"Torino",
    "sg:tags":[
        "pasta"
    ],
    "sg:website":"www.italpasta.it",
    "wof:name":"Italpasta S.p.a.",
    "wof:placetype":"venue"
},
  "geometry": {"coordinates":[7.6866188049,45.0705604553],"type":"Point"}
}