{
  "type": "Feature",
  "properties": {
    "addr:full":"60015 Falconara Marittima Falconara Marittima Ancona 60015",
    "addr:postcode":"60015;60015",
    "iso:country":"IT",
    "sg:address":"60015 Falconara Marittima",
    "sg:city":"Falconara Marittima",
    "sg:orig_category":"Tempo Libero - Articoli E Forniture. Regalistica Aziendale",
    "sg:phone":"+39 071 916 0710",
    "sg:postcode":"60015",
    "sg:province":"Ancona",
    "wof:name":"Il Giocattolo Di Marranconi Piero",
    "wof:placetype":"venue"
},
  "geometry": {"coordinates":[13.395361,43.630306],"type":"Point"}
}