{
  "type": "Feature",
  "properties": {
    "iso:country":"IT",
    "sg:address":"58019 Porto Santo Stefano",
    "sg:city":"Porto Santo Stefano",
    "sg:orig_category":"Macchine, Impianti Ed Attrezzature Per Agricoltura E Zootecnia",
    "sg:phone":"+39 0564 812213",
    "sg:postcode":"58019",
    "sg:province":"Grosseto",
    "wof:name":"Sclano Giovanni",
    "wof:placetype":"venue"
},
  "geometry": {"coordinates":[11.202424,42.385544],"type":"Point"}
}