{
  "type": "Feature",
  "properties": {
    "iso:country":"IT",
    "sg:address":"20098 San Giuliano Milanese",
    "sg:city":"San Giuliano Milanese",
    "sg:orig_category":"Non-classified Establishments",
    "sg:phone":"+39 02 9849 0542",
    "sg:postcode":"20098",
    "sg:province":"Milano",
    "wof:name":"Famsa Di De Filippis Mirco",
    "wof:placetype":"venue"
},
  "geometry": {"coordinates":[9.285596,45.383781],"type":"Point"}
}