{
  "type": "Feature",
  "properties": {
    "iso:country":"IT",
    "sg:address":"Piazza Gramsci Antonio 10 20154 Milano",
    "sg:city":"Milano",
    "sg:classifiers":[
        {
            "category":"Manufacturing",
            "subcategory":"Chemicals & Compounds",
            "type":"Manufacturing & Wholesale Goods"
        }
    ],
    "sg:phone":"+39 02 3310 5361",
    "sg:postcode":"20154",
    "sg:province":"Milano",
    "sg:tags":[
        "base"
    ],
    "wof:name":"Chimimec Srl",
    "wof:placetype":"venue"
},
  "geometry": {"coordinates":[9.16836,45.482151],"type":"Point"}
}