{
  "type": "Feature",
  "properties": {
    "addr:full":"Km. 57, Via Casilina 03018 Paliano Paliano Frosinone 03018",
    "addr:postcode":"03018;03018",
    "addr:street":"Km. 57 Via Casilina",
    "iso:country":"IT",
    "sg:address":"Km. 57, Via Casilina 03018 Paliano",
    "sg:city":"Paliano",
    "sg:classifiers":[
        {
            "category":"Shopping",
            "subcategory":"Crafts & Fabrics",
            "type":"Retail Goods"
        }
    ],
    "sg:phone":"+39 0775 576501",
    "sg:postcode":"03018",
    "sg:province":"Frosinone",
    "wof:name":"Novalis Fibres S.r.l.",
    "wof:placetype":"venue"
},
  "geometry": {"coordinates":[13.3519020081,41.6401367188],"type":"Point"}
}