{
  "type": "Feature",
  "properties": {
    "iso:country":"IT",
    "sg:address":"20037 Paderno Dugnano",
    "sg:city":"Paderno Dugnano",
    "sg:orig_category":"Servizi E Lavori Per Arredamento E Industria Del Legno",
    "sg:phone":"+39 02 918 7246",
    "sg:postcode":"20037",
    "sg:province":"Milano",
    "wof:name":"Rossetti & Carucci",
    "wof:placetype":"venue"
},
  "geometry": {"coordinates":[9.183072,45.56094],"type":"Point"}
}