{
  "type": "Feature",
  "properties": {
    "iso:country":"IT",
    "sg:address":"89, Corso Europa 17024 Finale Ligure",
    "sg:city":"Finale Ligure",
    "sg:classifiers":[
        {
            "category":"Travel",
            "subcategory":"Travel Agent",
            "type":"Entertainment"
        }
    ],
    "sg:phone":"+39 39019601784",
    "sg:postcode":"17024",
    "sg:province":"Savona",
    "sg:tags":[
        "business"
    ],
    "wof:name":"Hotel Bel Sit",
    "wof:placetype":"venue"
},
  "geometry": {"coordinates":[8.353761,44.171162],"type":"Point"}
}