{
  "type": "Feature",
  "properties": {
    "addr:full":"93010 Delia Delia Caltanissetta 93010",
    "addr:postcode":"93010;93010",
    "iso:country":"IT",
    "sg:address":"93010 Delia",
    "sg:city":"Delia",
    "sg:orig_category":"Servizi E Lavori Per Agricoltura E Zootecnia. Consulenze Tecniche, Amministrative E Perizie",
    "sg:phone":"+39 0922 820800",
    "sg:postcode":"93010",
    "sg:province":"Caltanissetta",
    "wof:name":"Insalaca Dott. Calogero - Agronomo",
    "wof:placetype":"venue"
},
  "geometry": {"coordinates":[13.927819,37.357018],"type":"Point"}
}