{
  "type": "Feature",
  "properties": {
    "iso:country":"IT",
    "sg:address":"Via Dell'industria 13 63018 Porto Sant'elpidio",
    "sg:orig_category":"Ladies' Shoes",
    "sg:phone":"+39 0734 903129",
    "sg:postcode":"63018",
    "sg:province":"Ascoli Piceno",
    "wof:name":"Calzaturificio Ferracuti Dei F.lli Ferracuti & C. Snc",
    "wof:placetype":"venue"
},
  "geometry": {"coordinates":[13.74757,43.237137],"type":"Point"}
}