{
  "type": "Feature",
  "properties": {
    "iso:country":"IT",
    "sg:address":"21, V. Staffali37062 Dossobuono",
    "sg:city":"Dossobuono",
    "sg:classifiers":[
        {
            "category":"Professional",
            "subcategory":"Engineering",
            "type":"Services"
        }
    ],
    "sg:phone":"+39 045 860 0479",
    "sg:postcode":"37062",
    "sg:province":"Verona",
    "sg:tags":[
        "machine",
        "-",
        "mechanical"
    ],
    "sg:website":"http://www.paginegialle.it/venplastsrl",
    "wof:name":"Venplast Srl",
    "wof:placetype":"venue"
},
  "geometry": {"coordinates":[10.906247,45.388058],"type":"Point"}
}