{
  "type": "Feature",
  "properties": {
    "iso:country":"IT",
    "sg:address":"10019 Strambino",
    "sg:city":"Strambino",
    "sg:orig_category":"Accessori Dei Mezzi Di Trasporto. Riparazione Dei Mezzi Di Trasporto",
    "sg:phone":"+39 0125 637432",
    "sg:postcode":"10019",
    "sg:province":"Torino",
    "wof:name":"Militello Concetta",
    "wof:placetype":"venue"
},
  "geometry": {"coordinates":[7.879985,45.383354],"type":"Point"}
}