{
  "type": "Feature",
  "properties": {
    "iso:country":"IT",
    "sg:address":"76, V. Nicol\u00f2 Dall'arca 41100 Modena",
    "sg:city":"Modena",
    "sg:classifiers":[
        {
            "category":"Wholesale",
            "subcategory":"Machinery & Supplies",
            "type":"Manufacturing & Wholesale Goods"
        }
    ],
    "sg:phone":"+39 39059345161",
    "sg:postcode":"41100",
    "sg:province":"Modena",
    "sg:tags":[
        "equipment",
        "precision"
    ],
    "sg:website":"http://www.laserw.com",
    "wof:name":"Laserwave",
    "wof:placetype":"venue"
},
  "geometry": {"coordinates":[10.9144287109,44.6639442444],"type":"Point"}
}