{
  "type": "Feature",
  "properties": {
    "addr:full":"00191 Roma Roma Roma 00191",
    "addr:postcode":"00191;00191",
    "iso:country":"IT",
    "sg:address":"00191 Roma",
    "sg:city":"Roma",
    "sg:orig_category":"Forniture Per Abbigliamento E Pelletterie",
    "sg:phone":"+39 06 329 4333",
    "sg:postcode":"00191",
    "sg:province":"Roma",
    "wof:name":"Le Tableau Di Elisabetta Lavagana",
    "wof:placetype":"venue"
},
  "geometry": {"coordinates":[12.6796159744,41.8266181946],"type":"Point"}
}