{
  "type": "Feature",
  "properties": {
    "iso:country":"IT",
    "sg:address":"30020 Bibione",
    "sg:city":"Bibione",
    "sg:orig_category":"Alberghi",
    "sg:phone":"+39 0431 438459",
    "sg:postcode":"30020",
    "sg:province":"Venezia",
    "wof:name":"Hotel Firenze Di Zamburlini Marisa & C. Sas",
    "wof:placetype":"venue"
},
  "geometry": {"coordinates":[13.051355,45.636372],"type":"Point"}
}