{
  "type": "Feature",
  "properties": {
    "iso:country":"IT",
    "sg:address":"50, Via Monte Corno 37057 San Giovanni Lupatoto",
    "sg:city":"San Giovanni Lupatoto",
    "sg:classifiers":[
        {
            "category":"Manufacturing",
            "subcategory":"Lumber",
            "type":"Manufacturing & Wholesale Goods"
        }
    ],
    "sg:phone":"+39 045 877 8580",
    "sg:postcode":"37057",
    "sg:province":"Verona",
    "sg:tags":[
        "wood"
    ],
    "wof:name":"Ottolini Legnami S.r.l.",
    "wof:placetype":"venue"
},
  "geometry": {"coordinates":[11.02121,45.389832],"type":"Point"}
}