{
  "type": "Feature",
  "properties": {
    "iso:country":"IT",
    "sg:address":"20123 Milano",
    "sg:city":"Milano",
    "sg:classifiers":[
        {
            "category":"Banks & Credit Unions",
            "subcategory":"Financial Services",
            "type":"Services"
        }
    ],
    "sg:phone":"+39 02 722 2271",
    "sg:postcode":"20123",
    "sg:province":"Milano",
    "sg:website":"http://www.realieassociati.it",
    "wof:name":"Reali E Associati Sim Spa",
    "wof:placetype":"venue"
},
  "geometry": {"coordinates":[9.184428,45.468719],"type":"Point"}
}