{
  "type": "Feature",
  "properties": {
    "addr:full":"22100 Como Como Como 22100",
    "addr:postcode":"22100;22100",
    "iso:country":"IT",
    "sg:address":"22100 Como",
    "sg:city":"Como",
    "sg:orig_category":"Non-classified Establishments",
    "sg:phone":"+39 031 523325",
    "sg:postcode":"22100",
    "sg:province":"Como",
    "wof:name":"Toys Center",
    "wof:placetype":"venue"
},
  "geometry": {"coordinates":[9.060271,45.783863],"type":"Point"}
}