{
  "type": "Feature",
  "properties": {
    "addr:full":"Via Piedirocca 7 84086 Roccapiemonte Roccapiemonte Salerno 84086",
    "addr:housenumber":"7",
    "addr:postcode":"84086;84086",
    "addr:street":"Via Piedirocca",
    "iso:country":"IT",
    "sg:address":"Via Piedirocca 7 84086 Roccapiemonte",
    "sg:city":"Roccapiemonte",
    "sg:classifiers":[
        {
            "category":"Professional",
            "subcategory":"Printing & Photocopies",
            "type":"Services"
        }
    ],
    "sg:phone":"+39 081 514 2783",
    "sg:postcode":"84086",
    "sg:province":"Salerno",
    "sg:tags":[
        "machine",
        "label"
    ],
    "wof:name":"Grafica Artistica Meridionale G.a.m Srl",
    "wof:placetype":"venue"
},
  "geometry": {"coordinates":[14.683318,40.759571],"type":"Point"}
}