{
  "type": "Feature",
  "properties": {
    "addr:full":"10128 Torino Torino Torino 10128",
    "addr:postcode":"10128;10128",
    "iso:country":"IT",
    "sg:address":"10128 Torino",
    "sg:city":"Torino",
    "sg:orig_category":"Studi E Consulenze Amministrative, Commerciali E Aziendali. Consulenze Tecniche, Amministrative E Perizie. Professionisti - Studi E Servizi Ed Associazioni Di Interesse Aziendale",
    "sg:phone":"+39 011 535267",
    "sg:postcode":"10128",
    "sg:province":"Torino",
    "wof:name":"Studio Associato Catalano Ugliola",
    "wof:placetype":"venue"
},
  "geometry": {"coordinates":[7.67474,45.06403],"type":"Point"}
}