{
  "type": "Feature",
  "properties": {
    "iso:country":"IT",
    "sg:address":"96, Via Caduti Di Cefalonia 50127 Firenze",
    "sg:city":"Firenze",
    "sg:classifiers":[
        {
            "category":"Wholesale",
            "subcategory":"Machinery & Supplies",
            "type":"Manufacturing & Wholesale Goods"
        }
    ],
    "sg:phone":"+39 39055431795",
    "sg:postcode":"50127",
    "sg:province":"Firenze",
    "sg:tags":[
        "equipment",
        "precision"
    ],
    "wof:name":"Sicep Spa",
    "wof:placetype":"venue"
},
  "geometry": {"coordinates":[11.2203788757,43.7931976318],"type":"Point"}
}