{
  "type": "Feature",
  "properties": {
    "addr:full":"33, V. Padana Superiore 25080 Molinetto Di Mazzano Mazzano Brescia 25080",
    "addr:housenumber":"33",
    "addr:postcode":"25080;25080",
    "addr:street":"V. Padana Superiore",
    "iso:country":"IT",
    "sg:address":"33, V. Padana Superiore 25080 Molinetto Di Mazzano",
    "sg:city":"Mazzano",
    "sg:classifiers":[
        {
            "category":"Shopping",
            "subcategory":"Gifts & Souvenirs",
            "type":"Retail Goods"
        }
    ],
    "sg:phone":"+39 030 212 2376",
    "sg:postcode":"25080",
    "sg:province":"Brescia",
    "sg:website":"http://www.fantasyline.it",
    "wof:name":"Stancanelli Fantasy Line Srl",
    "wof:placetype":"venue"
},
  "geometry": {"coordinates":[10.354178,45.496162],"type":"Point"}
}