{
  "type": "Feature",
  "properties": {
    "iso:country":"IT",
    "sg:address":"42019 Scandiano",
    "sg:orig_category":"Edilizia - Materiali",
    "sg:phone":"+39 0522 857255",
    "sg:postcode":"42019",
    "sg:province":"Reggio Nell'Emilia",
    "wof:name":"Cme Srl",
    "wof:placetype":"venue"
},
  "geometry": {"coordinates":[10.681251,44.596241],"type":"Point"}
}