{
  "type": "Feature",
  "properties": {
    "addr:full":"241, Viale Caduti Sul Lavoro 41100 Modena Modena Modena 41100",
    "addr:postcode":"41100;41100",
    "addr:street":"Viale Caduti Sul Lavoro",
    "iso:country":"IT",
    "sg:address":"241, Viale Caduti Sul Lavoro 41100 Modena",
    "sg:city":"Modena",
    "sg:classifiers":[
        {
            "category":"Manufacturing",
            "subcategory":"Metals",
            "type":"Manufacturing & Wholesale Goods"
        }
    ],
    "sg:phone":"+39 39059281337",
    "sg:postcode":"41100",
    "sg:province":"Modena",
    "sg:tags":[
        "metallurgy",
        "metalworking"
    ],
    "wof:name":"La Spada Srl",
    "wof:placetype":"venue"
},
  "geometry": {"coordinates":[10.9750289917,44.6385116577],"type":"Point"}
}