{
  "type": "Feature",
  "properties": {
    "iso:country":"IT",
    "sg:address":"35010 Limena",
    "sg:city":"Limena",
    "sg:orig_category":"Materiali E Componenti Elettrotecnici",
    "sg:phone":"+39 049 884 8011",
    "sg:postcode":"35010",
    "sg:province":"Padova",
    "wof:name":"Trendfin (s.r.l.)",
    "wof:placetype":"venue"
},
  "geometry": {"coordinates":[11.849422,45.462589],"type":"Point"}
}