{
  "type": "Feature",
  "properties": {
    "iso:country":"IT",
    "sg:address":"21027 Ispra",
    "sg:city":"Ispra",
    "sg:orig_category":"Pompe",
    "sg:phone":"+39 0332 781275",
    "sg:postcode":"21027",
    "sg:province":"Varese",
    "wof:name":"Nuova Ema Automazione Di Lombardi Leopoldo",
    "wof:placetype":"venue"
},
  "geometry": {"coordinates":[8.8267631531,45.8177375793],"type":"Point"}
}