{
  "type": "Feature",
  "properties": {
    "addr:full":"84098 Pontecagnano Faiano Faiano Salerno 84098",
    "addr:postcode":"84098;84098",
    "iso:country":"IT",
    "sg:address":"84098 Pontecagnano Faiano",
    "sg:city":"Faiano",
    "sg:classifiers":[
        {
            "category":"Manufacturing",
            "subcategory":"Food",
            "type":"Manufacturing & Wholesale Goods"
        }
    ],
    "sg:phone":"+39 089 202044",
    "sg:postcode":"84098",
    "sg:province":"Salerno",
    "sg:tags":[
        "product"
    ],
    "wof:name":"Palilia Srl",
    "wof:placetype":"venue"
},
  "geometry": {"coordinates":[14.8804893494,40.6230278015],"type":"Point"}
}