{
  "type": "Feature",
  "properties": {
    "addr:full":"40036 Monzuno Monzuno Bologna 40036",
    "addr:postcode":"40036;monzuno bologna 40036",
    "iso:country":"IT",
    "sg:address":"40036 Monzuno",
    "sg:city":"Monzuno",
    "sg:orig_category":"Servizi E Lavori Per Edilizia E Lavori Pubblici. Servizi Al Turismo",
    "sg:phone":"+39 051 677 3053",
    "sg:postcode":"40036",
    "sg:province":"Bologna",
    "sg:website":"http://www.eaglekeeper.it",
    "wof:name":"Eagle Keeper Divisione Immobiliare Srl",
    "wof:placetype":"venue"
},
  "geometry": {"coordinates":[11.501509,44.436287],"type":"Point"}
}