{
  "type": "Feature",
  "properties": {
    "addr:full":"90139 Palermo Palermo Palermo 90139",
    "addr:postcode":"90139;90139",
    "iso:country":"IT",
    "sg:address":"90139 Palermo",
    "sg:city":"Palermo",
    "sg:orig_category":"Agenzie Ed Enti Turistici. Consulenze Tecniche, Amministrative E Perizie",
    "sg:phone":"+39 091 331207",
    "sg:postcode":"90139",
    "sg:province":"Palermo",
    "sg:website":"http://www.guccioneviaggi.it",
    "wof:name":"Guccione Viaggi Srl",
    "wof:placetype":"venue"
},
  "geometry": {"coordinates":[13.3572845459,38.1294631958],"type":"Point"}
}