{
  "type": "Feature",
  "properties": {
    "iso:country":"IT",
    "sg:address":"9, Via Muratori Ludovico 41012 Carpi",
    "sg:city":"Carpi",
    "sg:classifiers":[
        {
            "category":"Shopping",
            "subcategory":"Clothing, Apparel, & Fashions",
            "type":"Retail Goods"
        }
    ],
    "sg:phone":"+39 39059633411",
    "sg:postcode":"41012",
    "sg:province":"Modena",
    "sg:tags":[
        "clothing",
        "accessory"
    ],
    "wof:name":"Tessilgraf Srl",
    "wof:placetype":"venue"
},
  "geometry": {"coordinates":[10.922732,44.736858],"type":"Point"}
}