{
  "type": "Feature",
  "properties": {
    "iso:country":"IT",
    "sg:address":"63100 Ascoli Piceno",
    "sg:city":"Ascoli Piceno",
    "sg:orig_category":"Forniture E Prodotti Informatici. Forniture Per Uffici",
    "sg:phone":"+39 0736 48433",
    "sg:postcode":"63100",
    "sg:province":"Ascoli Piceno",
    "sg:website":"http://obiprint.it",
    "wof:name":"Obiprint Piccola Soc.coop.r.l.",
    "wof:placetype":"venue"
},
  "geometry": {"coordinates":[13.5866031647,42.8500404358],"type":"Point"}
}