{
  "type": "Feature",
  "properties": {
    "iso:country":"IT",
    "sg:address":"16, Via Mauro 40054 Budrio",
    "sg:city":"Budrio",
    "sg:classifiers":[
        {
            "category":"Wholesale",
            "subcategory":"Machinery & Supplies",
            "type":"Manufacturing & Wholesale Goods"
        }
    ],
    "sg:phone":"+39 39051802102",
    "sg:postcode":"40054",
    "sg:province":"Bologna",
    "sg:tags":[
        "-",
        "agriculture",
        "equipment"
    ],
    "wof:name":"F.m. Matras (s.r.l.)",
    "wof:placetype":"venue"
},
  "geometry": {"coordinates":[11.54088,44.542046],"type":"Point"}
}