{
  "type": "Feature",
  "properties": {
    "iso:country":"IT",
    "sg:address":"85025 Melfi",
    "sg:city":"Melfi",
    "sg:orig_category":"Materiali Semilavorati Metallici",
    "sg:phone":"+39 0972 762147",
    "sg:postcode":"85025",
    "sg:province":"Potenza",
    "wof:name":"Tower Automotive Melfi Srl",
    "wof:placetype":"venue"
},
  "geometry": {"coordinates":[15.641253,41.044483],"type":"Point"}
}