{
  "type": "Feature",
  "properties": {
    "addr:full":"56021 Cascina Cascina Pisa 56021",
    "addr:postcode":"56021;56021",
    "addr:street":"Cascina Pisa",
    "iso:country":"IT",
    "sg:address":"56021 Cascina",
    "sg:city":"Cascina",
    "sg:orig_category":"Non-classified Establishments",
    "sg:phone":"+39 050 760763",
    "sg:postcode":"56021",
    "sg:province":"Pisa",
    "wof:name":"Cecchetti & C. Snc",
    "wof:placetype":"venue"
},
  "geometry": {"coordinates":[10.481183,43.680546],"type":"Point"}
}