{
  "type": "Feature",
  "properties": {
    "iso:country":"IT",
    "sg:address":"06081 Assisi",
    "sg:city":"Assisi",
    "sg:orig_category":"Arredamenti E Mobili Professionali. Complementi Di Arredamento",
    "sg:phone":"+39 075 815 5116",
    "sg:postcode":"06081",
    "sg:province":"Perugia",
    "wof:name":"Laboratorio San Francesco",
    "wof:placetype":"venue"
},
  "geometry": {"coordinates":[12.609016,43.073795],"type":"Point"}
}