{
  "type": "Feature",
  "properties": {
    "iso:country":"IT",
    "sg:address":"20131 Milano",
    "sg:city":"Milano",
    "sg:orig_category":"Abbigliamento Esterno, Maglierie E Pelliccerie. Servizi E Lavori Per Abbigliamento E Pelletterie",
    "sg:phone":"+39 02 236 0520",
    "sg:postcode":"20131",
    "sg:province":"Milano",
    "wof:name":"Modart Di Alda Misani In Ancora",
    "wof:placetype":"venue"
},
  "geometry": {"coordinates":[9.223649,45.481953],"type":"Point"}
}