{
  "type": "Feature",
  "properties": {
    "iso:country":"IT",
    "sg:address":"11024 Chatillon",
    "sg:city":"Chatillon",
    "sg:orig_category":"Tende Da Sole",
    "sg:phone":"+39 0166 61329",
    "sg:postcode":"11024",
    "sg:province":"Aosta",
    "wof:name":"Ellebi Di Barberio Vitaliano",
    "wof:placetype":"venue"
},
  "geometry": {"coordinates":[7.615063,45.750408],"type":"Point"}
}