{
  "type": "Feature",
  "properties": {
    "iso:country":"IT",
    "sg:address":"37028 Rovere'veronese",
    "sg:orig_category":"Servizi Per Lo Sport E Il Tempo Libero. Alberghi E Strutture Extra Alberghiere",
    "sg:phone":"+39 045 783 5955",
    "sg:postcode":"37028",
    "sg:province":"Verona",
    "wof:name":"Rifugio Dosso Alto Srl",
    "wof:placetype":"venue"
},
  "geometry": {"coordinates":[11.085713,45.56385],"type":"Point"}
}