{
  "type": "Feature",
  "properties": {
    "iso:country":"IT",
    "sg:address":"98064 Librizzi",
    "sg:city":"Librizzi",
    "sg:orig_category":"Ospedali E Servizi Sanitari",
    "sg:phone":"+39 0941 367008",
    "sg:postcode":"98064",
    "sg:province":"Messina",
    "wof:name":"L'onoranza Di La Spada Egidio & C.",
    "wof:placetype":"venue"
},
  "geometry": {"coordinates":[14.968091,38.081032],"type":"Point"}
}