{
  "type": "Feature",
  "properties": {
    "iso:country":"IT",
    "sg:address":"34129 Trieste",
    "sg:city":"Trieste",
    "sg:orig_category":"Sport - Articoli E Forniture",
    "sg:phone":"+39 040 347 6135",
    "sg:postcode":"34129",
    "sg:province":"Trieste",
    "wof:name":"G.t. Di Trampus Graziella",
    "wof:placetype":"venue"
},
  "geometry": {"coordinates":[13.784409,45.647839],"type":"Point"}
}