{
  "type": "Feature",
  "properties": {
    "iso:country":"IT",
    "sg:address":"00153 Roma",
    "sg:city":"Roma",
    "sg:orig_category":"Scuole E Servizi Scolastici. Ricerca, Selezione E Formazione Del Personale",
    "sg:phone":"+39 06 574 1081",
    "sg:postcode":"00153",
    "sg:province":"Roma",
    "sg:website":"http://www.istitutomeschini.it",
    "wof:name":"Istittuto G. Meschini Sas",
    "wof:placetype":"venue"
},
  "geometry": {"coordinates":[12.482219,41.876644],"type":"Point"}
}