{
  "type": "Feature",
  "properties": {
    "iso:country":"IT",
    "sg:address":"56029 Santa Croce Sull'arno",
    "sg:orig_category":"Petroli, Gas E Combustibili",
    "sg:phone":"+39 0571 30559",
    "sg:postcode":"56029",
    "sg:province":"Pisa",
    "wof:name":"Cavallaro Giuseppe Srl",
    "wof:placetype":"venue"
},
  "geometry": {"coordinates":[10.7605237961,43.7257919312],"type":"Point"}
}