{
  "type": "Feature",
  "properties": {
    "addr:full":"22077 Olgiate Comasco Olgiate Comasco Como 22077",
    "addr:postcode":"22077;22077",
    "iso:country":"IT",
    "sg:address":"22077 Olgiate Comasco",
    "sg:city":"Olgiate Comasco",
    "sg:orig_category":"Ospedali E Servizi Sanitari",
    "sg:phone":"+39 031 990456",
    "sg:postcode":"22077",
    "sg:province":"Como",
    "wof:name":"H24 Srl",
    "wof:placetype":"venue"
},
  "geometry": {"coordinates":[8.967593,45.781948],"type":"Point"}
}