{
  "type": "Feature",
  "properties": {
    "iso:country":"IT",
    "sg:address":"Via Castiglioni Giuseppe 7 21052 Busto Arsizio",
    "sg:city":"Busto Arsizio",
    "sg:classifiers":[
        {
            "category":"Shopping",
            "subcategory":"Crafts & Fabrics",
            "type":"Retail Goods"
        }
    ],
    "sg:phone":"+39 0331 631013",
    "sg:postcode":"21052",
    "sg:province":"Varese",
    "sg:tags":[
        "industry",
        "shoe"
    ],
    "wof:name":"Omniatex S.r.l.",
    "wof:placetype":"venue"
},
  "geometry": {"coordinates":[8.8263845444,45.8176040649],"type":"Point"}
}