{
  "type": "Feature",
  "properties": {
    "addr:full":"27, Via Altichieri Da Zevio 35132 Padova Padova Padova 35132",
    "addr:postcode":"35132;35132",
    "addr:street":"Via Altichieri Da Zevio",
    "iso:country":"IT",
    "sg:address":"27, Via Altichieri Da Zevio 35132 Padova",
    "sg:city":"Padova",
    "sg:classifiers":[
        {
            "category":"Wholesale",
            "subcategory":"Machinery & Supplies",
            "type":"Manufacturing & Wholesale Goods"
        }
    ],
    "sg:phone":"+39 39049606413",
    "sg:postcode":"35132",
    "sg:province":"Padova",
    "sg:tags":[
        "equipment",
        "-",
        "instrument",
        "measurement"
    ],
    "wof:name":"Montagna",
    "wof:placetype":"venue"
},
  "geometry": {"coordinates":[11.844167,45.397499],"type":"Point"}
}