{
  "type": "Feature",
  "properties": {
    "addr:full":"00187 Roma Roma Roma 00187",
    "addr:postcode":"00187;00187",
    "iso:country":"IT",
    "sg:address":"00187 Roma",
    "sg:city":"Roma",
    "sg:orig_category":"Agenzie D'affari E Servizi Commerciali. Avvocati, Notai E Servizi Legali. Consulenze Tecniche, Amministrative E Perizie",
    "sg:phone":"+39 06 482971",
    "sg:postcode":"00187",
    "sg:province":"Roma",
    "wof:name":"Arthur Andersen S.p.a.",
    "wof:placetype":"venue"
},
  "geometry": {"coordinates":[12.366143,42.128746],"type":"Point"}
}