{
  "type": "Feature",
  "properties": {
    "iso:country":"IT",
    "sg:address":"28100 Novara",
    "sg:city":"Novara",
    "sg:orig_category":"Servizi E Lavori Industria Della Gomma",
    "sg:phone":"+39 0321 620357",
    "sg:postcode":"28100",
    "sg:province":"Novara",
    "wof:name":"Carfora Clemente",
    "wof:placetype":"venue"
},
  "geometry": {"coordinates":[8.599689,45.447224],"type":"Point"}
}