{
  "type": "Feature",
  "properties": {
    "iso:country":"IT",
    "sg:address":"1, V. Scopari 80047 San Giuseppe Vesuviano",
    "sg:city":"San Giuseppe Vesuviano",
    "sg:classifiers":[
        {
            "category":"Shopping",
            "subcategory":"Clothing, Apparel, & Fashions",
            "type":"Retail Goods"
        }
    ],
    "sg:phone":"+39 081 827 1512",
    "sg:postcode":"80047",
    "sg:province":"Napoli",
    "sg:tags":[
        "clothes"
    ],
    "sg:website":"http://www.kixa.it",
    "wof:name":"Kixa Group Sas",
    "wof:placetype":"venue"
},
  "geometry": {"coordinates":[14.495596,40.835705],"type":"Point"}
}