{
  "type": "Feature",
  "properties": {
    "addr:full":"Via Sardegna 3 42100 Reggio Emilia Reggio Nell'Emilia 42100",
    "addr:housenumber":"3",
    "addr:postcode":"42100;42100",
    "addr:street":"Via Sardegna",
    "iso:country":"IT",
    "sg:address":"Via Sardegna 3 42100 Reggio Emilia",
    "sg:classifiers":[
        {
            "category":"Ice Cream",
            "type":"Food & Drink"
        }
    ],
    "sg:phone":"+39 0522 331600",
    "sg:postcode":"42100",
    "sg:province":"Reggio Nell'Emilia",
    "sg:tags":[
        "ice-cream"
    ],
    "sg:website":"www.morseg.it",
    "wof:name":"Segmagel S.r.l.",
    "wof:placetype":"venue"
},
  "geometry": {"coordinates":[10.654314,44.692917],"type":"Point"}
}