{
  "type": "Feature",
  "properties": {
    "iso:country":"IT",
    "sg:address":"20154 Milano",
    "sg:city":"Milano",
    "sg:orig_category":"Arredo Camera Letto E Complementi",
    "sg:phone":"+39 02 313138",
    "sg:postcode":"20154",
    "sg:province":"Milano",
    "wof:name":"Barbieri Interni Di S. Barbieri",
    "wof:placetype":"venue"
},
  "geometry": {"coordinates":[9.16483,45.483128],"type":"Point"}
}