{
  "type": "Feature",
  "properties": {
    "iso:country":"IT",
    "sg:address":"90040 Isola Delle Femmine",
    "sg:city":"Isola delle Femmine",
    "sg:orig_category":"Imprese Di Costruzioni Civili Ed Industriali",
    "sg:phone":"+39 091 867 7207",
    "sg:postcode":"90040",
    "sg:province":"Palermo",
    "sg:website":"http://www.rbianchini.it",
    "wof:name":"Roberto Bianchini Snc",
    "wof:placetype":"venue"
},
  "geometry": {"coordinates":[13.253008,38.195778],"type":"Point"}
}