{
  "type": "Feature",
  "properties": {
    "iso:country":"IT",
    "sg:address":"31014 Colle Umberto",
    "sg:city":"Colle Umberto",
    "sg:orig_category":"Geologia, Geotecnica E Topografia - Studi E Servizi",
    "sg:phone":"+39 0438 434068",
    "sg:postcode":"31014",
    "sg:province":"Treviso",
    "sg:website":"http://www.eurogeo.com",
    "wof:name":"Eurogeo Srl",
    "wof:placetype":"venue"
},
  "geometry": {"coordinates":[12.348811,45.947544],"type":"Point"}
}