{
  "type": "Feature",
  "properties": {
    "iso:country":"IT",
    "sg:address":"56125 Pisa",
    "sg:city":"Pisa",
    "sg:orig_category":"Impiantistica E Prodotti Tecnologici Per Edilizia. Termotecnica E Riscaldamento, Apparecchiature E Servizi",
    "sg:phone":"+39 050 43077",
    "sg:postcode":"56125",
    "sg:province":"Pisa",
    "wof:name":"Impresa Edile Carrani Geometra Stefano",
    "wof:placetype":"venue"
},
  "geometry": {"coordinates":[10.401732,43.71069],"type":"Point"}
}