{
  "type": "Feature",
  "properties": {
    "iso:country":"IT",
    "sg:address":"29, Via Brocchi Giambattista 25129 Brescia",
    "sg:city":"Brescia",
    "sg:classifiers":[
        {
            "category":"Building & Trades",
            "subcategory":"Construction",
            "type":"Services"
        }
    ],
    "sg:phone":"+39 030 230 1482",
    "sg:postcode":"25129",
    "sg:province":"Brescia",
    "sg:tags":[
        "work",
        "public"
    ],
    "wof:name":"Sef Costruzioni E Impianti S.r.l.",
    "wof:placetype":"venue"
},
  "geometry": {"coordinates":[10.222958,45.539829],"type":"Point"}
}