{
  "type": "Feature",
  "properties": {
    "iso:country":"IT",
    "sg:address":"20059 Vimercate",
    "sg:city":"Vimercate",
    "sg:orig_category":"Apparecchiature Ed Attrezzature Meccaniche",
    "sg:phone":"+39 039 608 1329",
    "sg:postcode":"20059",
    "sg:province":"Milano",
    "wof:name":"Redaelli Curva Profilati Di Redaelli Claudio",
    "wof:placetype":"venue"
},
  "geometry": {"coordinates":[9.368833,45.619343],"type":"Point"}
}