{
  "type": "Feature",
  "properties": {
    "addr:full":"14100 Asti Asti Asti 14100",
    "addr:postcode":"14100;14100",
    "iso:country":"IT",
    "sg:address":"14100 Asti",
    "sg:city":"Asti",
    "sg:orig_category":"Prodotti Alimentari",
    "sg:phone":"+39 0141 3971",
    "sg:postcode":"14100",
    "sg:province":"Asti",
    "sg:website":"http://www.sacla.it",
    "wof:name":"Sacla' Fratelli Spa",
    "wof:placetype":"venue"
},
  "geometry": {"coordinates":[8.2136564255,44.9102401733],"type":"Point"}
}