{
  "type": "Feature",
  "properties": {
    "iso:country":"IT",
    "sg:address":"20131 Milano",
    "sg:city":"Milano",
    "sg:orig_category":"Servizi Ausiliari Di Certificati, Riproduzioni, Disegni E Foto",
    "sg:phone":"+39 02 282 6139",
    "sg:postcode":"20131",
    "sg:province":"Milano",
    "wof:name":"Timbroloreto Copyline Srl",
    "wof:placetype":"venue"
},
  "geometry": {"coordinates":[9.22013,45.487114],"type":"Point"}
}