{
  "type": "Feature",
  "properties": {
    "iso:country":"IT",
    "sg:address":"40121 Bologna",
    "sg:city":"Bologna",
    "sg:orig_category":"Casseforti E Armadi Blindati",
    "sg:phone":"+39 051 225812",
    "sg:postcode":"40121",
    "sg:province":"Bologna",
    "wof:name":"Ferramenta Boriani Di Saverio Piancastelli & C. Sas",
    "wof:placetype":"venue"
},
  "geometry": {"coordinates":[11.340929,44.495689],"type":"Point"}
}