{
  "type": "Feature",
  "properties": {
    "iso:country":"IT",
    "sg:address":"Strada Del Montefeltro 61100 Pesaro",
    "sg:city":"Pesaro",
    "sg:classifiers":[
        {
            "category":"Manufacturing",
            "subcategory":"Motor Vehicles & Parts",
            "type":"Manufacturing & Wholesale Goods"
        }
    ],
    "sg:phone":"+39 0721 202669",
    "sg:postcode":"61100",
    "sg:province":"Pesaro E Urbino",
    "sg:tags":[
        "engine"
    ],
    "wof:name":"Motori Mc Kart Srl",
    "wof:placetype":"venue"
},
  "geometry": {"coordinates":[12.529803,43.633556],"type":"Point"}
}