{
  "type": "Feature",
  "properties": {
    "addr:full":"Vle Rimembranze 9 20050 Triuggio Triuggio Milano 20050",
    "addr:housenumber":"9",
    "addr:postcode":"20050;20050",
    "addr:street":"Vle Rimembranze",
    "iso:country":"IT",
    "sg:address":"Vle Rimembranze 9 20050 Triuggio",
    "sg:city":"Triuggio",
    "sg:classifiers":[
        {
            "category":"Shopping",
            "subcategory":"Clothing, Apparel, & Fashions",
            "type":"Retail Goods"
        }
    ],
    "sg:phone":"+39 036 294 3052",
    "sg:postcode":"20050",
    "sg:province":"Milano",
    "sg:tags":[
        "image",
        "clothing",
        "basic"
    ],
    "sg:website":"www.civas.it",
    "wof:name":"Civas Dei Fratelli Crippa Srl",
    "wof:placetype":"venue"
},
  "geometry": {"coordinates":[9.188141,45.463688],"type":"Point"}
}