{
  "type": "Feature",
  "properties": {
    "addr:full":"104, Via Spezia 43044 Collecchio Collecchio Parma 43044",
    "addr:housenumber":"104",
    "addr:postcode":"43044;43044",
    "addr:street":"Via Spezia",
    "iso:country":"IT",
    "sg:address":"104, Via Spezia 43044 Collecchio",
    "sg:city":"Collecchio",
    "sg:classifiers":[
        {
            "category":"Food & Beverages",
            "subcategory":"Groceries & Convenience Stores",
            "type":"Retail Goods"
        }
    ],
    "sg:phone":"+39 0521 800080",
    "sg:postcode":"43044",
    "sg:province":"Parma",
    "sg:tags":[
        "product",
        "related"
    ],
    "wof:name":"Ugo Annoni (s.p.a.)",
    "wof:placetype":"venue"
},
  "geometry": {"coordinates":[10.210817337,44.7496376038],"type":"Point"}
}