{
  "type": "Feature",
  "properties": {
    "iso:country":"IT",
    "sg:address":"24060 San Paolo D'argon",
    "sg:orig_category":"Utensili Meccanici E Materiali",
    "sg:phone":"+39 035 959147",
    "sg:postcode":"24060",
    "sg:province":"Bergamo",
    "wof:name":"Diamex Srl",
    "wof:placetype":"venue"
},
  "geometry": {"coordinates":[9.756733,45.702053],"type":"Point"}
}