{
  "type": "Feature",
  "properties": {
    "addr:full":"7, Via Carducci 10092 Beinasco Beinasco Torino 10092",
    "addr:postcode":"10092;10092",
    "addr:street":"Via Carducci",
    "iso:country":"IT",
    "sg:address":"7, Via Carducci 10092 Beinasco",
    "sg:city":"Beinasco",
    "sg:orig_category":"Miscellaneous Products",
    "sg:phone":"+39 011 349 8157",
    "sg:postcode":"10092",
    "sg:province":"Torino",
    "wof:name":"Driver Italia S.r.l.",
    "wof:placetype":"venue"
},
  "geometry": {"coordinates":[7.573908329,45.013217926],"type":"Point"}
}