{
  "type": "Feature",
  "properties": {
    "iso:country":"IT",
    "sg:address":"25015 Desenzano Del Garda",
    "sg:city":"Desenzano del Garda",
    "sg:orig_category":"Servizi E Lavori Per Abbigliamento E Pelletterie",
    "sg:phone":"+39 030 990 1233",
    "sg:postcode":"25015",
    "sg:province":"Brescia",
    "wof:name":"Longi Massimo",
    "wof:placetype":"venue"
},
  "geometry": {"coordinates":[10.58685,45.458538],"type":"Point"}
}