{
  "type": "Feature",
  "properties": {
    "iso:country":"IT",
    "sg:address":"Centro Direzionale Is A/3 80143 Napoli",
    "sg:city":"Napoli",
    "sg:classifiers":[
        {
            "category":"Parking",
            "subcategory":"Lot",
            "type":"Transportation"
        }
    ],
    "sg:phone":"+39 081 562 5194",
    "sg:postcode":"80143",
    "sg:province":"Napoli",
    "sg:tags":[
        "transport",
        "road"
    ],
    "sg:website":"http://www.paginegialle.it/buonocoregennaro",
    "wof:name":"Buonocore Gennaro Trasporti Sas",
    "wof:placetype":"venue"
},
  "geometry": {"coordinates":[14.282045,40.856991],"type":"Point"}
}