{
  "type": "Feature",
  "properties": {
    "iso:country":"IT",
    "sg:address":"Via Dismano 114/p/m 48100 Ravenna",
    "sg:city":"Ravenna",
    "sg:classifiers":[
        {
            "category":"Shopping",
            "subcategory":"Computers & Home Electronics",
            "type":"Retail Goods"
        }
    ],
    "sg:phone":"+39 0544 470095",
    "sg:postcode":"48100",
    "sg:province":"Ravenna",
    "sg:tags":[
        "system",
        "automation"
    ],
    "sg:website":"www.er-elettronica.it",
    "wof:name":"Er Elettronica Srl",
    "wof:placetype":"venue"
},
  "geometry": {"coordinates":[12.213957,44.263042],"type":"Point"}
}