{
  "type": "Feature",
  "properties": {
    "addr:full":"12, Strada Casale Torino 15030 Coniolo Coniolo Alessandria 15030",
    "addr:postcode":"15030;15030",
    "addr:street":"Strada Casale",
    "iso:country":"IT",
    "sg:address":"12, Strada Casale Torino 15030 Coniolo",
    "sg:city":"Coniolo",
    "sg:classifiers":[
        {
            "category":"Professional",
            "subcategory":"Engineering",
            "type":"Services"
        }
    ],
    "sg:phone":"+39 0142 563597",
    "sg:postcode":"15030",
    "sg:province":"Alessandria",
    "sg:tags":[
        "machine",
        "-",
        "mechanical"
    ],
    "wof:name":"C.m.c. (s.n.c.)",
    "wof:placetype":"venue"
},
  "geometry": {"coordinates":[7.73478,45.087868],"type":"Point"}
}