{
  "type": "Feature",
  "properties": {
    "addr:full":"Via Mattia Battistini, 71; Roma",
    "addr:housenumber":"71",
    "addr:street":"Via Mattia Battistini",
    "iso:country":"IT",
    "sg:address":"Via Mattia Battistini, 71; Roma",
    "sg:classifiers":[
        {
            "category":"Banks & Credit Unions",
            "subcategory":"Bank",
            "type":"Services"
        }
    ],
    "sg:phone":"+39 06 628 1753",
    "wof:name":"Banca Di Roma",
    "wof:placetype":"venue"
},
  "geometry": {"coordinates":[12.412484,41.906048],"type":"Point"}
}