{
  "type": "Feature",
  "properties": {
    "iso:country":"IT",
    "sg:address":"20123 Milano",
    "sg:city":"Milano",
    "sg:orig_category":"Servizi Per Aziende, Manifestazioni E Supporto Agli Scambi Commerciali. Ambasciate Ed Enti Internazionali",
    "sg:phone":"+39 02 861100",
    "sg:postcode":"20123",
    "sg:province":"Milano",
    "wof:name":"Rappresentanza Commerciale Dell'uruguay",
    "wof:placetype":"venue"
},
  "geometry": {"coordinates":[9.189665,45.462635],"type":"Point"}
}