{
  "type": "Feature",
  "properties": {
    "iso:country":"IT",
    "sg:address":"3, Via Del Parco 32013 Longarone",
    "sg:city":"Longarone",
    "sg:classifiers":[
        {
            "category":"Travel",
            "subcategory":"Travel Agent",
            "type":"Entertainment"
        }
    ],
    "sg:phone":"+39 0437 577577",
    "sg:postcode":"32013",
    "sg:province":"Belluno",
    "sg:tags":[
        "business"
    ],
    "wof:name":"Longarone Fiere Srl",
    "wof:placetype":"venue"
},
  "geometry": {"coordinates":[12.303752,46.268627],"type":"Point"}
}