{
  "type": "Feature",
  "properties": {
    "addr:full":"40057 Granarolo Dell'emilia Bologna 40057",
    "addr:postcode":"40057;40057",
    "iso:country":"IT",
    "sg:address":"40057 Granarolo Dell'emilia",
    "sg:orig_category":"Attrezzature E Forniture Per Officine Riparazione E Servizi Ausiliari",
    "sg:phone":"+39 051 766441",
    "sg:postcode":"40057",
    "sg:province":"Bologna",
    "wof:name":"Paoloni Spa",
    "wof:placetype":"venue"
},
  "geometry": {"coordinates":[11.395157,44.549484],"type":"Point"}
}