{
  "type": "Feature",
  "properties": {
    "iso:country":"IT",
    "sg:address":"27029 Vigevano",
    "sg:city":"Vigevano",
    "sg:orig_category":"Condizionatori Aria - Commercio",
    "sg:phone":"+39 0381 79437",
    "sg:postcode":"27029",
    "sg:province":"Pavia",
    "wof:name":"Centro Assistenza Ricambi Multimarche Di Perrotta Stefano Sas",
    "wof:placetype":"venue"
},
  "geometry": {"coordinates":[8.850966,45.323463],"type":"Point"}
}