{
  "type": "Feature",
  "properties": {
    "addr:full":"20025 Legnano Legnano Milano 20025",
    "addr:postcode":"20025;20025",
    "iso:country":"IT",
    "sg:address":"20025 Legnano",
    "sg:city":"Legnano",
    "sg:orig_category":"Musica",
    "sg:phone":"+39 0331 548690",
    "sg:postcode":"20025",
    "sg:province":"Milano",
    "wof:name":"Sozzi Claudio",
    "wof:placetype":"venue"
},
  "geometry": {"coordinates":[8.9038257599,45.5900611877],"type":"Point"}
}