{
  "type": "Feature",
  "properties": {
    "iso:country":"IT",
    "sg:address":"72100 Brindisi",
    "sg:city":"Brindisi",
    "sg:orig_category":"Musica",
    "sg:phone":"+39 0831 529848",
    "sg:postcode":"72100",
    "sg:province":"Brindisi",
    "wof:name":"Casa Musicale Di Errico Andrea & C. Sas",
    "wof:placetype":"venue"
},
  "geometry": {"coordinates":[17.9471149445,40.6384925842],"type":"Point"}
}