{
  "type": "Feature",
  "properties": {
    "iso:country":"IT",
    "sg:address":"50122 Firenze",
    "sg:city":"Firenze",
    "sg:orig_category":"Alberghi E Strutture Extra Alberghiere",
    "sg:phone":"+39 055 210185",
    "sg:postcode":"50122",
    "sg:province":"Firenze",
    "sg:website":"http://www.leduefontane.it",
    "wof:name":"Due Fontane Srl",
    "wof:placetype":"venue"
},
  "geometry": {"coordinates":[11.262299,43.768112],"type":"Point"}
}