{
  "type": "Feature",
  "properties": {
    "iso:country":"IT",
    "sg:address":"00037 Segni",
    "sg:city":"Segni",
    "sg:orig_category":"Agricoltura, Orticoltura E Floricoltura",
    "sg:phone":"+39 06 970 3039",
    "sg:postcode":"00037",
    "sg:province":"Roma",
    "wof:name":"Centro Commerciale Agricolo",
    "wof:placetype":"venue"
},
  "geometry": {"coordinates":[13.050476,41.668556],"type":"Point"}
}