{
  "type": "Feature",
  "properties": {
    "iso:country":"IT",
    "sg:address":"55100 Lucca",
    "sg:city":"Lucca",
    "sg:orig_category":"Informatica - Consulenza E Software",
    "sg:phone":"+39 0583 491210",
    "sg:postcode":"55100",
    "sg:province":"Lucca",
    "sg:website":"http://www.anfyteam.com",
    "wof:name":"Anfy Team Di Fabio Ciucci",
    "wof:placetype":"venue"
},
  "geometry": {"coordinates":[10.511705,43.851662],"type":"Point"}
}