{
  "type": "Feature",
  "properties": {
    "addr:full":"00137 Roma Roma Roma 00137",
    "addr:postcode":"00137;00137",
    "iso:country":"IT",
    "sg:address":"00137 Roma",
    "sg:city":"Roma",
    "sg:orig_category":"Prodotti Chimici Di Base. Forniture Per Attivita' Industriali",
    "sg:phone":"+39 06 827 7083",
    "sg:postcode":"00137",
    "sg:province":"Roma",
    "wof:name":"Nurax S.r.l.",
    "wof:placetype":"venue"
},
  "geometry": {"coordinates":[12.3538942337,42.1184959412],"type":"Point"}
}