{
  "type": "Feature",
  "properties": {
    "addr:full":"36016 Thiene Thiene Vicenza 36016",
    "addr:postcode":"36016;36016",
    "iso:country":"IT",
    "sg:address":"36016 Thiene",
    "sg:city":"Thiene",
    "sg:orig_category":"Vetri E Cristalli Temperati E Di Sicurezza",
    "sg:phone":"+39 0445 363017",
    "sg:postcode":"36016",
    "sg:province":"Vicenza",
    "wof:name":"Vetreria Thienese Di Farina Antonio & C.",
    "wof:placetype":"venue"
},
  "geometry": {"coordinates":[11.485816,45.707741],"type":"Point"}
}