{
  "type": "Feature",
  "properties": {
    "addr:full":"46, V. A. Cecchi 10152 Torino Torino Torino 10152",
    "addr:housenumber":"46",
    "addr:postcode":"10152;10152",
    "addr:street":"V. A. Cecchi",
    "iso:country":"IT",
    "sg:address":"46, V. A. Cecchi 10152 Torino",
    "sg:city":"Torino",
    "sg:classifiers":[
        {
            "category":"Wholesale",
            "subcategory":"Drugs",
            "type":"Manufacturing & Wholesale Goods"
        }
    ],
    "sg:phone":"+39 39011855495",
    "sg:postcode":"10152",
    "sg:province":"Torino",
    "sg:tags":[
        "chemical",
        "pharmaceutical"
    ],
    "sg:website":"http://www.paginegialle.it/carisma",
    "wof:name":"Carisma Snc",
    "wof:placetype":"venue"
},
  "geometry": {"coordinates":[7.680787,45.087402],"type":"Point"}
}