{
  "type": "Feature",
  "properties": {
    "addr:full":"80137 Napoli Napoli Napoli 80137",
    "addr:housenumber":"80137",
    "addr:postcode":"80137",
    "iso:country":"IT",
    "sg:address":"80137 Napoli",
    "sg:city":"Napoli",
    "sg:orig_category":"Arredo Cucina Ed Elettrodomestici. Frigotecnica, Apparecchiature E Servizi. Elettrodomestici",
    "sg:phone":"+39 081 570 7251",
    "sg:postcode":"80137",
    "sg:province":"Napoli",
    "wof:name":"Maia Di Filippone Snc",
    "wof:placetype":"venue"
},
  "geometry": {"coordinates":[14.261397,40.862652],"type":"Point"}
}