{
  "type": "Feature",
  "properties": {
    "iso:country":"IT",
    "sg:address":"Ctr Spinazzo Sn 70042 Mola Di Bari",
    "sg:city":"Mola di Bari",
    "sg:classifiers":[
        {
            "category":"Food & Beverages",
            "subcategory":"Fruits & Vegetables",
            "type":"Retail Goods"
        }
    ],
    "sg:phone":"+39 080 473 3669",
    "sg:postcode":"70042",
    "sg:province":"Bari",
    "wof:name":"Azienda Agricola Masseria Pepe Di Martinelli Gaetano & C. Snc",
    "wof:placetype":"venue"
},
  "geometry": {"coordinates":[16.8692913055,41.1260528564],"type":"Point"}
}