{
  "type": "Feature",
  "properties": {
    "addr:full":"20122 Milano Milano Milano 20122",
    "addr:postcode":"20122;20122",
    "iso:country":"IT",
    "sg:address":"20122 Milano",
    "sg:city":"Milano",
    "sg:classifiers":[
        {
            "category":"Home & Garden",
            "subcategory":"Carpets & Floor Coverings",
            "type":"Retail Goods"
        }
    ],
    "sg:phone":"+39 02 3931 4426",
    "sg:postcode":"20122",
    "sg:province":"Milano",
    "sg:tags":[
        "linoleum"
    ],
    "wof:name":"M. & C. Carpets Co. Srl",
    "wof:placetype":"venue"
},
  "geometry": {"coordinates":[9.203688,45.455826],"type":"Point"}
}