{
  "type": "Feature",
  "properties": {
    "addr:full":"38068 Rovereto Rovereto Trento 38068",
    "addr:postcode":"38068;38068",
    "iso:country":"IT",
    "sg:address":"38068 Rovereto",
    "sg:city":"Rovereto",
    "sg:classifiers":[
        {
            "category":"Bars & Pubs",
            "subcategory":"Champagne Bar",
            "type":"Food & Drink"
        }
    ],
    "sg:phone":"+39 0464 439236",
    "sg:postcode":"38068",
    "sg:province":"Trento",
    "sg:tags":[
        "caffe'",
        "e"
    ],
    "wof:name":"Ristorante Stazione Di F.lli Brescioni & C. Snc",
    "wof:placetype":"venue"
},
  "geometry": {"coordinates":[11.07172,45.882092],"type":"Point"}
}