{
  "type": "Feature",
  "properties": {
    "addr:full":"23849 Rogeno Rogeno Lecco 23849",
    "addr:postcode":"23849;23849",
    "iso:country":"IT",
    "sg:address":"23849 Rogeno",
    "sg:city":"Rogeno",
    "sg:orig_category":"Morsetterie Elettriche",
    "sg:phone":"+39 031 876500",
    "sg:postcode":"23849",
    "sg:province":"Lecco",
    "sg:website":"http://www.interforgia.com",
    "wof:name":"Interforgia Srl",
    "wof:placetype":"venue"
},
  "geometry": {"coordinates":[9.2682723999,45.7839279175],"type":"Point"}
}