{
  "type": "Feature",
  "properties": {
    "addr:full":"Via Per Casaloldo 46041 Asola Asola Mantova 46041",
    "addr:postcode":"46041;46041",
    "addr:street":"Via Per Casaloldo",
    "iso:country":"IT",
    "sg:address":"Via Per Casaloldo 46041 Asola",
    "sg:city":"Asola",
    "sg:classifiers":[
        {
            "category":"Shopping",
            "subcategory":"Crafts & Fabrics",
            "type":"Retail Goods"
        }
    ],
    "sg:phone":"+39 39037674110",
    "sg:postcode":"46041",
    "sg:province":"Mantova",
    "wof:name":"Tintoria Manifattura Barbara (s.p.a.)",
    "wof:placetype":"venue"
},
  "geometry": {"coordinates":[10.4585084915,45.2482376099],"type":"Point"}
}