{
  "type": "Feature",
  "properties": {
    "iso:country":"IT",
    "sg:address":"12012 Boves",
    "sg:city":"Boves",
    "sg:orig_category":"Grigliati E Griglie",
    "sg:phone":"+39 0171 380418",
    "sg:postcode":"12012",
    "sg:province":"Cuneo",
    "wof:name":"Migliore Aldo",
    "wof:placetype":"venue"
},
  "geometry": {"coordinates":[7.562092,44.331478],"type":"Point"}
}