{
  "type": "Feature",
  "properties": {
    "iso:country":"IT",
    "sg:address":"37025 Verona",
    "sg:orig_category":"Forniture Per Agricoltura E Zootecnia. Animali Domestici",
    "sg:phone":"+39 045 889 0112",
    "sg:province":"VR",
    "wof:name":"Anubi Srl",
    "wof:placetype":"venue"
},
  "geometry": {"coordinates":[-87.2916717529,35.9609947205],"type":"Point"}
}