{
  "type": "Feature",
  "properties": {
    "iso:country":"IT",
    "sg:address":"59, Corso Alba 12043 Canale",
    "sg:city":"Canale",
    "sg:classifiers":[
        {
            "category":"Parking",
            "subcategory":"Lot",
            "type":"Transportation"
        }
    ],
    "sg:phone":"+39 0173 979008",
    "sg:postcode":"12043",
    "sg:province":"Cuneo",
    "sg:tags":[
        "transport",
        "road"
    ],
    "wof:name":"Renato Casale (s.p.a.)",
    "wof:placetype":"venue"
},
  "geometry": {"coordinates":[7.59418,44.376274],"type":"Point"}
}