{
  "type": "Feature",
  "properties": {
    "iso:country":"IT",
    "sg:address":"Piazza Dell'olmo 29; Boves; 12012",
    "sg:city":"Boves",
    "sg:classifiers":[
        {
            "category":"Banks & Credit Unions",
            "subcategory":"Bank",
            "type":"Services"
        }
    ],
    "sg:phone":"+39 0171 880180",
    "sg:postcode":"12012",
    "sg:province":"Cuneo",
    "wof:name":"Cassa Di Risparmio Di Cuneo",
    "wof:placetype":"venue"
},
  "geometry": {"coordinates":[7.550355,44.328934],"type":"Point"}
}