{
  "type": "Feature",
  "properties": {
    "iso:country":"IT",
    "sg:address":"36061 Bassano Del Grappa",
    "sg:city":"Bassano del Grappa",
    "sg:orig_category":"Associazioni Ed Organismi Di Interesse Pubblico",
    "sg:phone":"+39 0424 523117",
    "sg:postcode":"36061",
    "sg:province":"Vicenza",
    "wof:name":"Sindacato C.i.s.l.",
    "wof:placetype":"venue"
},
  "geometry": {"coordinates":[11.730305,45.767864],"type":"Point"}
}