{
  "type": "Feature",
  "properties": {
    "iso:country":"IT",
    "sg:address":"20060 Masate",
    "sg:city":"Masate",
    "sg:orig_category":"Servizi Vari Di Interesse Pubblico",
    "sg:phone":"+39 02 9576 4045",
    "sg:postcode":"20060",
    "sg:province":"Milano",
    "wof:name":"Gallina Margherita Michela",
    "wof:placetype":"venue"
},
  "geometry": {"coordinates":[9.192035,45.48035],"type":"Point"}
}