{
  "type": "Feature",
  "properties": {
    "addr:full":"53100 Siena Siena Siena 53100",
    "addr:postcode":"53100;53100",
    "iso:country":"IT",
    "sg:address":"53100 Siena",
    "sg:city":"Siena",
    "sg:orig_category":"Servizi Di Magazzinaggio E Movimentazione. Servizi Ausiliari Di Sorveglianza, Manutenzione E Pulizia",
    "sg:phone":"+39 0577 42000",
    "sg:postcode":"53100",
    "sg:province":"Siena",
    "wof:name":"C.a.l.l. Snc",
    "wof:placetype":"venue"
},
  "geometry": {"coordinates":[11.365801,43.31971],"type":"Point"}
}