{
  "type": "Feature",
  "properties": {
    "iso:country":"IT",
    "sg:address":"1, Via Barbieri Ulisse 46100 Mantova",
    "sg:city":"Mantova",
    "sg:classifiers":[
        {
            "category":"Professional",
            "subcategory":"Engineering",
            "type":"Services"
        }
    ],
    "sg:phone":"+39 390 376 2391",
    "sg:postcode":"46100",
    "sg:province":"Mantova",
    "sg:tags":[
        "machine",
        "-",
        "mechanical"
    ],
    "wof:name":"Sogefi Filtration S.p.a.",
    "wof:placetype":"venue"
},
  "geometry": {"coordinates":[10.829494,45.153759],"type":"Point"}
}