{
  "type": "Feature",
  "properties": {
    "addr:full":"24040 Lallio Lallio Bergamo 24040",
    "addr:postcode":"24040;24040",
    "iso:country":"IT",
    "sg:address":"24040 Lallio",
    "sg:city":"Lallio",
    "sg:orig_category":"Macchine, Strumenti Ed Apparecchi Per Attivita' Industriali",
    "sg:phone":"+39 035 203448",
    "sg:postcode":"24040",
    "sg:province":"Bergamo",
    "wof:name":"Field S.r.l.",
    "wof:placetype":"venue"
},
  "geometry": {"coordinates":[9.615017,45.644154],"type":"Point"}
}