{
  "type": "Feature",
  "properties": {
    "addr:full":"Via Dosdega' 65 37060 Alpo Verona 37060",
    "addr:housenumber":"65",
    "addr:postcode":"37060;37060",
    "addr:street":"Via Dosdega '",
    "iso:country":"IT",
    "sg:address":"Via Dosdega' 65 37060 Alpo",
    "sg:classifiers":[
        {
            "category":"Manufacturing",
            "subcategory":"Chemicals & Compounds",
            "type":"Manufacturing & Wholesale Goods"
        }
    ],
    "sg:phone":"+39 045 986844",
    "sg:postcode":"37060",
    "sg:province":"Verona",
    "sg:tags":[
        "industrial"
    ],
    "wof:name":"De Stefani Srl",
    "wof:placetype":"venue"
},
  "geometry": {"coordinates":[10.90783,45.373016],"type":"Point"}
}