{
  "type": "Feature",
  "properties": {
    "iso:country":"IT",
    "sg:address":"25125 Brescia",
    "sg:city":"Brescia",
    "sg:orig_category":"Bullonerie",
    "sg:phone":"+39 030 35891",
    "sg:postcode":"25125",
    "sg:province":"Brescia",
    "sg:website":"http://www.info.it",
    "wof:name":"M.f.u. Spa",
    "wof:placetype":"venue"
},
  "geometry": {"coordinates":[10.164043,45.50655],"type":"Point"}
}