{
  "type": "Feature",
  "properties": {
    "iso:country":"IT",
    "sg:address":"10139 Torino",
    "sg:city":"Torino",
    "sg:orig_category":"Valvole E Apparecchiature Di Misura. Ricambi E Componenti Dei Mezzi Di Trasporto",
    "sg:phone":"+39 011 447 2262",
    "sg:postcode":"10139",
    "sg:province":"Torino",
    "wof:name":"Gilardi Giuseppe & C.snc",
    "wof:placetype":"venue"
},
  "geometry": {"coordinates":[7.120077,45.126019],"type":"Point"}
}