{
  "type": "Feature",
  "properties": {
    "iso:country":"IT",
    "sg:address":"30026 Portogruaro",
    "sg:city":"Portogruaro",
    "sg:orig_category":"Abbigliamento Esterno, Maglierie E Pelliccerie. Sport - Articoli E Forniture",
    "sg:phone":"+39 0421 394453",
    "sg:postcode":"30026",
    "sg:province":"Venezia",
    "wof:name":"Zanco Mauro",
    "wof:placetype":"venue"
},
  "geometry": {"coordinates":[12.848757,45.775112],"type":"Point"}
}