{
  "type": "Feature",
  "properties": {
    "iso:country":"IT",
    "sg:address":"35010 Limena",
    "sg:city":"Limena",
    "sg:orig_category":"Acciai Inossidabili - Commercio",
    "sg:phone":"+39 049 768222",
    "sg:postcode":"35010",
    "sg:province":"Padova",
    "sg:website":"http://www.inoxtubi.it",
    "wof:name":"Inoxtubi Padova Di Camera Franco & Camera Roberto & C. Sas",
    "wof:placetype":"venue"
},
  "geometry": {"coordinates":[11.843575,45.466488],"type":"Point"}
}