{
  "type": "Feature",
  "properties": {
    "iso:country":"IT",
    "sg:address":"20090 Segrate",
    "sg:city":"Segrate",
    "sg:orig_category":"Macchine, Strumenti Ed Apparecchi Per Attivita' Industriali",
    "sg:phone":"+39 02 269 9181",
    "sg:postcode":"20090",
    "sg:province":"Milano",
    "wof:name":"Alpa Srl",
    "wof:placetype":"venue"
},
  "geometry": {"coordinates":[9.297943,45.500908],"type":"Point"}
}