{
  "type": "Feature",
  "properties": {
    "iso:country":"IT",
    "sg:address":"84014 Nocera Inferiore",
    "sg:city":"Nocera Inferiore",
    "sg:classifiers":[
        {
            "category":"Train Station",
            "subcategory":"Light Rail",
            "type":"Transportation"
        }
    ],
    "sg:phone":"+39 081 937007",
    "sg:postcode":"84014",
    "sg:province":"Salerno",
    "sg:tags":[
        "plating",
        "treatments",
        "metals",
        "heat",
        "electroforming",
        "surface"
    ],
    "wof:name":"Ve.pr.al. Snc",
    "wof:placetype":"venue"
},
  "geometry": {"coordinates":[14.641292572,40.7584381104],"type":"Point"}
}