{
  "type": "Feature",
  "properties": {
    "addr:full":"20128 Milano Milano Milano 20128",
    "addr:postcode":"20128;20128",
    "iso:country":"IT",
    "sg:address":"20128 Milano",
    "sg:city":"Milano",
    "sg:orig_category":"Audiovisivi Filmati, Spot E Multimediali - Realizzazione E Duplicazione",
    "sg:phone":"+39 02 2600 5033",
    "sg:postcode":"20128",
    "sg:province":"Milano",
    "sg:website":"http://www.cdplant.it",
    "wof:name":"Cd Plant Italia Sas",
    "wof:placetype":"venue"
},
  "geometry": {"coordinates":[9.227371,45.506596],"type":"Point"}
}