{
  "type": "Feature",
  "properties": {
    "iso:country":"IT",
    "sg:address":"37051 Bovolone",
    "sg:city":"Bovolone",
    "sg:orig_category":"Carta, Cartone E Prodotti Primari",
    "sg:phone":"+39 045 690 1636",
    "sg:postcode":"37051",
    "sg:province":"Verona",
    "sg:website":"http://www.fazioni.it",
    "wof:name":"Fazioni Gabriele & C. Snc",
    "wof:placetype":"venue"
},
  "geometry": {"coordinates":[10.977481,45.413849],"type":"Point"}
}