{
  "type": "Feature",
  "properties": {
    "iso:country":"IT",
    "sg:address":"80134 Napoli",
    "sg:city":"Napoli",
    "sg:orig_category":"Accessori Moda D'abbigliamento",
    "sg:phone":"+39 081 759 9995",
    "sg:postcode":"80134",
    "sg:province":"Napoli",
    "wof:name":"Emmetre Di Esposito Melania",
    "wof:placetype":"venue"
},
  "geometry": {"coordinates":[14.1977920532,40.8507270813],"type":"Point"}
}