{
  "type": "Feature",
  "properties": {
    "iso:country":"IT",
    "sg:address":"1, Via Moscova 20017 Rho",
    "sg:city":"Rho",
    "sg:classifiers":[
        {
            "category":"Shopping",
            "subcategory":"Clothing, Apparel, & Fashions",
            "type":"Retail Goods"
        }
    ],
    "sg:phone":"+39 39029317971",
    "sg:postcode":"20017",
    "sg:province":"Milano",
    "sg:tags":[
        "clothing",
        "accessory"
    ],
    "wof:name":"Euronil S.p.a.",
    "wof:placetype":"venue"
},
  "geometry": {"coordinates":[9.053149,45.523849],"type":"Point"}
}