{
  "type": "Feature",
  "properties": {
    "iso:country":"IT",
    "sg:address":"25, Via Primo Maggio 20021 Bollate",
    "sg:city":"Bollate",
    "sg:classifiers":[
        {
            "category":"Autos & Motor Vehicles",
            "subcategory":"Automobile Sales",
            "type":"Retail Goods"
        }
    ],
    "sg:phone":"+39 39023822101",
    "sg:postcode":"20021",
    "sg:province":"Milano",
    "sg:tags":[
        "motor-cars"
    ],
    "wof:name":"Azienda Industriale Commerciale Automobilistica Spa",
    "wof:placetype":"venue"
},
  "geometry": {"coordinates":[9.1172676086,45.5250053406],"type":"Point"}
}