{
  "type": "Feature",
  "properties": {
    "iso:country":"IT",
    "sg:address":"00191 Roma",
    "sg:city":"Roma",
    "sg:orig_category":"Discoteche, Locali Notturni E Sale Da Ballo",
    "sg:phone":"+39 06 333 8729",
    "sg:postcode":"00191",
    "sg:province":"Roma",
    "wof:name":"William's Club",
    "wof:placetype":"venue"
},
  "geometry": {"coordinates":[12.471948,41.942154],"type":"Point"}
}