{
  "type": "Feature",
  "properties": {
    "iso:country":"IT",
    "sg:address":"24126 Bergamo",
    "sg:city":"Bergamo",
    "sg:orig_category":"Prodotti Di Base E Forniture Per Industria Alimentare E Bevande. Forniture Per Attivita' Commerciali Ed Artigianali",
    "sg:phone":"+39 035 315544",
    "sg:postcode":"24126",
    "sg:province":"Bergamo",
    "wof:name":"Ostificio Minora",
    "wof:placetype":"venue"
},
  "geometry": {"coordinates":[9.6573467255,45.6714820862],"type":"Point"}
}