{
  "type": "Feature",
  "properties": {
    "addr:full":"41012 Carpi Carpi Modena 41012",
    "addr:postcode":"41012;41012",
    "iso:country":"IT",
    "sg:address":"41012 Carpi",
    "sg:city":"Carpi",
    "sg:classifiers":[
        {
            "category":"Shopping",
            "subcategory":"Crafts & Fabrics",
            "type":"Retail Goods"
        }
    ],
    "sg:phone":"+39 059 697266",
    "sg:postcode":"41012",
    "sg:province":"Modena",
    "sg:tags":[
        "material"
    ],
    "wof:name":"Orvac Srl",
    "wof:placetype":"venue"
},
  "geometry": {"coordinates":[10.8946933746,44.794090271],"type":"Point"}
}