{
  "type": "Feature",
  "properties": {
    "iso:country":"IT",
    "sg:address":"40050 Monte San Pietro",
    "sg:city":"Monte San Pietro",
    "sg:orig_category":"Forniture Per Edilizia E Lavori Pubblici. Prodotti Vari In Metallo",
    "sg:phone":"+39 051 676 6873",
    "sg:postcode":"40050",
    "sg:province":"Bologna",
    "wof:name":"Susini Bruno Snc",
    "wof:placetype":"venue"
},
  "geometry": {"coordinates":[11.1590509415,44.4911155701],"type":"Point"}
}