{
  "type": "Feature",
  "properties": {
    "iso:country":"IT",
    "sg:address":"91027 Paceco",
    "sg:city":"Paceco",
    "sg:orig_category":"Forniture Per Edilizia E Lavori Pubblici",
    "sg:phone":"+39 0380 251 2817",
    "sg:postcode":"91027",
    "sg:province":"Trapani",
    "wof:name":"Brignone Michele",
    "wof:placetype":"venue"
},
  "geometry": {"coordinates":[12.5519351959,37.9919204712],"type":"Point"}
}