{
  "type": "Feature",
  "properties": {
    "iso:country":"IT",
    "sg:address":"Via Veneto, 20/22 31040 Gorgo Al Monticano",
    "sg:city":"Gorgo al Monticano",
    "sg:classifiers":[
        {
            "category":"Home & Garden",
            "subcategory":"Home Furnishings",
            "type":"Retail Goods"
        }
    ],
    "sg:phone":"+39 0422 8004",
    "sg:postcode":"31040",
    "sg:province":"Treviso",
    "sg:tags":[
        "knob",
        "handle",
        "furniture"
    ],
    "sg:website":"www.eurekaitalia.it",
    "wof:name":"Eureka Srl",
    "wof:placetype":"venue"
},
  "geometry": {"coordinates":[12.5648345947,45.7879638672],"type":"Point"}
}