{
  "type": "Feature",
  "properties": {
    "addr:full":"35011 Campodarsego Campodarsego Padova 35011",
    "addr:postcode":"35011;35011",
    "iso:country":"IT",
    "sg:address":"35011 Campodarsego",
    "sg:city":"Campodarsego",
    "sg:orig_category":"Prodotti E Manufatti In Materie Plastiche",
    "sg:phone":"+39 049 556 4166",
    "sg:postcode":"35011",
    "sg:province":"Padova",
    "wof:name":"Nuova Ume Veneto (s.r.l.)",
    "wof:placetype":"venue"
},
  "geometry": {"coordinates":[11.9146146774,45.4967193604],"type":"Point"}
}