{
  "type": "Feature",
  "properties": {
    "iso:country":"IT",
    "sg:address":"18016 San Bartolomeo Al Mare",
    "sg:city":"San Bartolomeo al Mare",
    "sg:orig_category":"Campeggi, Ostelli E Villaggi Turistici",
    "sg:phone":"+39 0183 401098",
    "sg:postcode":"18016",
    "sg:province":"Imperia",
    "sg:website":"http://www.ilfrantoiocamping.it",
    "wof:name":"Parco Vacanze Il Frantoio",
    "wof:placetype":"venue"
},
  "geometry": {"coordinates":[8.102023,43.921509],"type":"Point"}
}