{
  "type": "Feature",
  "properties": {
    "addr:full":"Frazione Valgera 49 14100 Asti Asti Asti 14100",
    "addr:housenumber":"49",
    "addr:postcode":"14100;14100",
    "addr:street":"Frazione Valgera",
    "iso:country":"IT",
    "sg:address":"Frazione Valgera 49 14100 Asti",
    "sg:city":"Asti",
    "sg:classifiers":[
        {
            "category":"Train Station",
            "subcategory":"Rail",
            "type":"Transportation"
        }
    ],
    "sg:phone":"+39 0141 470325",
    "sg:postcode":"14100",
    "sg:province":"Asti",
    "sg:tags":[
        "barrier"
    ],
    "sg:website":"www.hastasider.it",
    "wof:name":"Hastasider Servizi Srl",
    "wof:placetype":"venue"
},
  "geometry": {"coordinates":[8.244795,44.923183],"type":"Point"}
}