{
  "type": "Feature",
  "properties": {
    "iso:country":"IT",
    "sg:address":"20060 Gessate",
    "sg:city":"Gessate",
    "sg:orig_category":"Macchine, Impianti Ed Attrezzature Industria Chimica. Attrezzature E Forniture Per Officine Riparazione E Servizi Ausiliari",
    "sg:phone":"+39 02 9538 2098",
    "sg:postcode":"20060",
    "sg:province":"Milano",
    "wof:name":"Pre.mix Srl",
    "wof:placetype":"venue"
},
  "geometry": {"coordinates":[9.442004,45.542183],"type":"Point"}
}