{
  "type": "Feature",
  "properties": {
    "addr:full":"6, Via Giovanni Pascoli 24040 Filago Filago Bergamo 24040",
    "addr:postcode":"24040;24040",
    "addr:street":"Via Giovanni Pascoli",
    "iso:country":"IT",
    "sg:address":"6, Via Giovanni Pascoli 24040 Filago",
    "sg:city":"Filago",
    "sg:classifiers":[
        {
            "category":"Manufacturing",
            "subcategory":"Rubber & Plastics",
            "type":"Manufacturing & Wholesale Goods"
        }
    ],
    "sg:phone":"+39 035 494 2201",
    "sg:postcode":"24040",
    "sg:province":"Bergamo",
    "wof:name":"Preformati B.m.c. (s.r.l.)",
    "wof:placetype":"venue"
},
  "geometry": {"coordinates":[9.5622854233,45.6425018311],"type":"Point"}
}