{
  "type": "Feature",
  "properties": {
    "addr:full":"1, Via Toma 73032 Andrano Andrano Lecce 73032",
    "addr:postcode":"73032;73032",
    "addr:street":"Via Toma",
    "iso:country":"IT",
    "sg:address":"1, Via Toma 73032 Andrano",
    "sg:city":"Andrano",
    "sg:classifiers":[
        {
            "category":"Shopping",
            "subcategory":"Clothing, Apparel, & Fashions",
            "type":"Retail Goods"
        }
    ],
    "sg:phone":"+39 0836 925807",
    "sg:postcode":"73032",
    "sg:province":"Lecce",
    "sg:tags":[
        "clothes"
    ],
    "wof:name":"Zefiro Srl",
    "wof:placetype":"venue"
},
  "geometry": {"coordinates":[18.377306,39.979828],"type":"Point"}
}