{
  "type": "Feature",
  "properties": {
    "iso:country":"IT",
    "sg:address":"Corso Raffaello 28 10125 Torino",
    "sg:city":"Torino",
    "sg:classifiers":[
        {
            "category":"Shopping",
            "subcategory":"Books",
            "type":"Retail Goods"
        }
    ],
    "sg:phone":"+39 011 209 9111",
    "sg:postcode":"10125",
    "sg:province":"Torino",
    "sg:website":"www.utet.com",
    "wof:name":"Utet Spa",
    "wof:placetype":"venue"
},
  "geometry": {"coordinates":[7.680004,45.050934],"type":"Point"}
}