{
  "type": "Feature",
  "properties": {
    "iso:country":"IT",
    "sg:address":"20146 Milano",
    "sg:city":"Milano",
    "sg:orig_category":"Servizi E Lavori Per Abbigliamento E Pelletterie",
    "sg:phone":"+39 02 468674",
    "sg:postcode":"20146",
    "sg:province":"Milano",
    "wof:name":"Camisa Luigi",
    "wof:placetype":"venue"
},
  "geometry": {"coordinates":[9.153034,45.458248],"type":"Point"}
}