{
  "type": "Feature",
  "properties": {
    "addr:full":"80124 Napoli Napoli Napoli 80124",
    "addr:housenumber":"80124",
    "addr:postcode":"80124",
    "iso:country":"IT",
    "sg:address":"80124 Napoli",
    "sg:city":"Napoli",
    "sg:orig_category":"Apparecchiature Ed Attrezzature Meccaniche. Ricambi E Componenti Dei Mezzi Di Trasporto",
    "sg:phone":"+39 081 762 6628",
    "sg:postcode":"80124",
    "sg:province":"Napoli",
    "wof:name":"Schwick Bruno",
    "wof:placetype":"venue"
},
  "geometry": {"coordinates":[14.158042,40.926483],"type":"Point"}
}