{
  "type": "Feature",
  "properties": {
    "iso:country":"IT",
    "sg:address":"Via G. Garibaldi 24a 25086 Rezzato",
    "sg:city":"Rezzato",
    "sg:classifiers":[
        {
            "category":"Banks & Credit Unions",
            "subcategory":"Investment Brokerage",
            "type":"Services"
        }
    ],
    "sg:phone":"+39 030 279 2589",
    "sg:postcode":"25086",
    "sg:province":"Brescia",
    "sg:tags":[
        "children's",
        "stocking"
    ],
    "sg:website":"www.generaltex.com",
    "wof:name":"General Textile Srl",
    "wof:placetype":"venue"
},
  "geometry": {"coordinates":[10.314512,45.511219],"type":"Point"}
}