{
  "type": "Feature",
  "properties": {
    "iso:country":"IT",
    "sg:address":"47, Vl. Don Sturzo",
    "sg:city":"Bari",
    "sg:classifiers":[
        {
            "category":"Shopping",
            "subcategory":"Computers & Home Electronics",
            "type":"Retail Goods"
        }
    ],
    "sg:phone":"+39 080 542 1247",
    "sg:postcode":"70125",
    "sg:province":"Bari",
    "sg:tags":[
        "electronic",
        "electrical",
        "equipment"
    ],
    "sg:website":"http://www.paginegialle.it/cvrmarcoli",
    "wof:name":"Cvr Srl",
    "wof:placetype":"venue"
},
  "geometry": {"coordinates":[16.871712,41.106861],"type":"Point"}
}