{
  "type": "Feature",
  "properties": {
    "iso:country":"IT",
    "sg:address":"80016 Marano Di Napoli",
    "sg:city":"Marano di Napoli",
    "sg:orig_category":"Medicinali E Prodotti Parafarmaceutici",
    "sg:phone":"+39 081 742 8807",
    "sg:postcode":"80016",
    "sg:province":"Napoli",
    "wof:name":"Farmacia S. Francesco",
    "wof:placetype":"venue"
},
  "geometry": {"coordinates":[14.1832685471,40.9026832581],"type":"Point"}
}