{
  "type": "Feature",
  "properties": {
    "iso:country":"IT",
    "sg:address":"65129 Pescara",
    "sg:city":"Pescara",
    "sg:orig_category":"Apparecchiature Ed Attrezzature Meccaniche. Elettrotecnica Industriale, Prodotti E Apparecchiature",
    "sg:phone":"+39 085 50291",
    "sg:postcode":"65129",
    "sg:province":"Pescara",
    "wof:name":"Sge Srl",
    "wof:placetype":"venue"
},
  "geometry": {"coordinates":[14.212396,42.446861],"type":"Point"}
}