{
  "type": "Feature",
  "properties": {
    "iso:country":"IT",
    "sg:address":"20143 Milano",
    "sg:city":"Milano",
    "sg:orig_category":"Cine-foto-ottica",
    "sg:phone":"+39 02 891 0958",
    "sg:postcode":"20143",
    "sg:province":"Milano",
    "wof:name":"Artigiangrafica Snc",
    "wof:placetype":"venue"
},
  "geometry": {"coordinates":[9.143398,45.443699],"type":"Point"}
}