{
  "type": "Feature",
  "properties": {
    "addr:full":"90144 Palermo Palermo Palermo 90144",
    "addr:postcode":"90144;90144",
    "iso:country":"IT",
    "sg:address":"90144 Palermo",
    "sg:city":"Palermo",
    "sg:orig_category":"Impiantistica E Prodotti Tecnologici Per Edilizia",
    "sg:phone":"+39 091 343545",
    "sg:postcode":"90144",
    "sg:province":"Palermo",
    "sg:website":"http://www.rimma.it",
    "wof:name":"Rimma Snc",
    "wof:placetype":"venue"
},
  "geometry": {"coordinates":[13.342617,38.139629],"type":"Point"}
}