{
  "type": "Feature",
  "properties": {
    "iso:country":"IT",
    "sg:address":"7, V. Per Boletto 28010 Alzo Di Pella",
    "sg:city":"Alzo",
    "sg:classifiers":[
        {
            "category":"Shopping",
            "type":"Retail Goods"
        }
    ],
    "sg:phone":"+39 0322 969165",
    "sg:postcode":"28010",
    "sg:province":"Novara",
    "sg:tags":[
        "finished",
        "-",
        "metallic"
    ],
    "sg:website":"http://www.fratelligiacomini.it",
    "wof:name":"Giacomini F.lli Snc",
    "wof:placetype":"venue"
},
  "geometry": {"coordinates":[8.6186714172,45.4450836182],"type":"Point"}
}