{
  "type": "Feature",
  "properties": {
    "iso:country":"IT",
    "sg:address":"Via Roma 108/112; Battipaglia; 84091",
    "sg:city":"Battipaglia",
    "sg:classifiers":[
        {
            "category":"Banks & Credit Unions",
            "subcategory":"Bank",
            "type":"Services"
        }
    ],
    "sg:phone":"+39 0828 303949",
    "sg:postcode":"84091",
    "sg:province":"Salerno",
    "wof:name":"Banca Popolare Dell'irpinia Scarl",
    "wof:placetype":"venue"
},
  "geometry": {"coordinates":[14.981033,40.608406],"type":"Point"}
}