{
  "type": "Feature",
  "properties": {
    "iso:country":"IT",
    "sg:address":"Via Migliara 46 04016 Sabaudia",
    "sg:city":"Sabaudia",
    "sg:classifiers":[
        {
            "category":"Utilities",
            "subcategory":"Electric",
            "type":"Services"
        }
    ],
    "sg:phone":"+39 0773 562080",
    "sg:postcode":"04016",
    "sg:province":"Latina",
    "sg:tags":[
        "component",
        "electronic"
    ],
    "wof:name":"Nlc Sistemi Metallici Spa",
    "wof:placetype":"venue"
},
  "geometry": {"coordinates":[13.036778,41.380951],"type":"Point"}
}