{
  "type": "Feature",
  "properties": {
    "iso:country":"IT",
    "sg:address":"10, Via Al Ticino 21019 Somma Lombardo",
    "sg:city":"Somma Lombardo",
    "sg:classifiers":[
        {
            "category":"Manufacturing",
            "subcategory":"Paper Products",
            "type":"Manufacturing & Wholesale Goods"
        }
    ],
    "sg:phone":"+39 0331 251662",
    "sg:postcode":"21019",
    "sg:province":"Varese",
    "sg:tags":[
        "cardboard"
    ],
    "wof:name":"Norda Imballaggi S.r.l.",
    "wof:placetype":"venue"
},
  "geometry": {"coordinates":[8.6797199249,45.6618041992],"type":"Point"}
}