{
  "type": "Feature",
  "properties": {
    "iso:country":"IT",
    "sg:address":"63033 Monte Prandone",
    "sg:orig_category":"Abbigliamento - Produzione E Ingrosso",
    "sg:phone":"+39 0735 751507",
    "sg:postcode":"63033",
    "sg:province":"Ascoli Piceno",
    "wof:name":"Mirna Snc",
    "wof:placetype":"venue"
},
  "geometry": {"coordinates":[13.6275,42.909702],"type":"Point"}
}