{
  "type": "Feature",
  "properties": {
    "iso:country":"IT",
    "sg:address":"87040 Tarsia",
    "sg:city":"Tarsia",
    "sg:orig_category":"Batterie, Accumulatori E Pile - Commercio",
    "sg:phone":"+39 0981 952715",
    "sg:postcode":"87040",
    "sg:province":"Cosenza",
    "wof:name":"Basile P.i. Angelo",
    "wof:placetype":"venue"
},
  "geometry": {"coordinates":[16.271263,39.621761],"type":"Point"}
}