{
  "type": "Feature",
  "properties": {
    "addr:full":"62, Via Monferrato 20098 San Giuliano Milanese San Giuliano Milanese Milano 20098",
    "addr:postcode":"20098;20098",
    "addr:street":"Via Monferrato",
    "iso:country":"IT",
    "sg:address":"62, Via Monferrato 20098 San Giuliano Milanese",
    "sg:city":"San Giuliano Milanese",
    "sg:classifiers":[
        {
            "category":"Shopping",
            "subcategory":"Clothing, Apparel, & Fashions",
            "type":"Retail Goods"
        }
    ],
    "sg:phone":"+39 39029822911",
    "sg:postcode":"20098",
    "sg:province":"Milano",
    "sg:tags":[
        "clothes"
    ],
    "wof:name":"Rentex Spa",
    "wof:placetype":"venue"
},
  "geometry": {"coordinates":[9.257906,45.400867],"type":"Point"}
}