{
  "type": "Feature",
  "properties": {
    "iso:country":"IT",
    "sg:address":"62012 Civitanova Marche",
    "sg:city":"Civitanova Marche",
    "sg:orig_category":"Calzature, Pelletterie E Pelli",
    "sg:phone":"+39 0733 817575",
    "sg:postcode":"62012",
    "sg:province":"Macerata",
    "wof:name":"Calzaturificio Chiara Catini Di Catini Giovanni",
    "wof:placetype":"venue"
},
  "geometry": {"coordinates":[13.726153,43.307144],"type":"Point"}
}