{
  "type": "Feature",
  "properties": {
    "iso:country":"IT",
    "sg:address":"Piazza 4 Novembre; Carr\u00e8; 36010",
    "sg:classifiers":[
        {
            "category":"Banks & Credit Unions",
            "subcategory":"Bank",
            "type":"Services"
        }
    ],
    "sg:phone":"+39 0445 892777",
    "sg:postcode":"36010",
    "sg:province":"Vicenza",
    "wof:name":"Banca Populare Vicentina",
    "wof:placetype":"venue"
},
  "geometry": {"coordinates":[11.459018,45.747391],"type":"Point"}
}