{
  "type": "Feature",
  "properties": {
    "addr:full":"10014 Caluso Caluso Torino 10014",
    "addr:postcode":"10014;10014",
    "iso:country":"IT",
    "sg:address":"10014 Caluso",
    "sg:city":"Caluso",
    "sg:orig_category":"Prodotti Vari In Metallo. Articoli Per Imballaggio E Confezionamento",
    "sg:phone":"+39 011 983 2118",
    "sg:postcode":"10014",
    "sg:province":"Torino",
    "sg:website":"http://www.omp-cost-met.it",
    "wof:name":"Omp Di Ponzetto & C. Snc",
    "wof:placetype":"venue"
},
  "geometry": {"coordinates":[7.8895792961,45.3022003174],"type":"Point"}
}