{
  "type": "Feature",
  "properties": {
    "iso:country":"IT",
    "sg:address":"Via Venezia 38056 Levico Terme",
    "sg:city":"Levico Terme",
    "sg:classifiers":[
        {
            "category":"Professional",
            "subcategory":"Engineering",
            "type":"Services"
        }
    ],
    "sg:phone":"+39 0461 707084",
    "sg:postcode":"38056",
    "sg:province":"Trento",
    "sg:tags":[
        "machine",
        "-",
        "mechanical"
    ],
    "wof:name":"Hollander Idrotermica",
    "wof:placetype":"venue"
},
  "geometry": {"coordinates":[11.315179,46.010056],"type":"Point"}
}