{
  "type": "Feature",
  "properties": {
    "iso:country":"IT",
    "sg:address":"Via Artigiani 2 25030 Maclodio",
    "sg:city":"Maclodio",
    "sg:classifiers":[
        {
            "category":"Autos & Motor Vehicles",
            "subcategory":"Fuel & Gas Station",
            "type":"Retail Goods"
        }
    ],
    "sg:phone":"+39 030 978 9000",
    "sg:postcode":"25030",
    "sg:province":"Brescia",
    "sg:tags":[
        "engine",
        "set",
        "diesel"
    ],
    "wof:name":"Gnutti Carlo Spa",
    "wof:placetype":"venue"
},
  "geometry": {"coordinates":[10.049411,45.471001],"type":"Point"}
}