{
  "type": "Feature",
  "properties": {
    "addr:full":"34, Via Pralafera 10062 Luserna San Giovanni Luserna Torino 10062",
    "addr:postcode":"10062;10062",
    "addr:street":"Via Pralafera",
    "iso:country":"IT",
    "sg:address":"34, Via Pralafera 10062 Luserna San Giovanni",
    "sg:city":"Luserna",
    "sg:classifiers":[
        {
            "category":"Professional",
            "subcategory":"Printing & Photocopies",
            "type":"Services"
        }
    ],
    "sg:phone":"+39 0121 954480",
    "sg:postcode":"10062",
    "sg:province":"Torino",
    "wof:name":"Tipolitografia Sanmori",
    "wof:placetype":"venue"
},
  "geometry": {"coordinates":[7.2352232933,44.8158378601],"type":"Point"}
}