{
  "type": "Feature",
  "properties": {
    "addr:full":"18, Via Einaudi 10060 San Secondo Di Pinerolo San Secondo di Pinerolo Torino 10060",
    "addr:postcode":"10060;10060",
    "addr:street":"Via Einaudi",
    "iso:country":"IT",
    "sg:address":"18, Via Einaudi 10060 San Secondo Di Pinerolo",
    "sg:city":"San Secondo di Pinerolo",
    "sg:classifiers":[
        {
            "category":"Shopping",
            "subcategory":"Computers & Home Electronics",
            "type":"Retail Goods"
        }
    ],
    "sg:phone":"+39 0121 500795",
    "sg:postcode":"10060",
    "sg:province":"Torino",
    "sg:tags":[
        "electronic",
        "electrical",
        "equipment"
    ],
    "wof:name":"Elettromeccanica Santavicca E C. S.n.c.",
    "wof:placetype":"venue"
},
  "geometry": {"coordinates":[7.305559,44.874973],"type":"Point"}
}