{
  "type": "Feature",
  "properties": {
    "addr:full":"59100 Prato Prato Prato 59100",
    "addr:postcode":"59100;59100",
    "iso:country":"IT",
    "sg:address":"59100 Prato",
    "sg:city":"Prato",
    "sg:orig_category":"Elettrotecnica Industriale, Prodotti E Apparecchiature. Ricambi E Componenti Dei Mezzi Di Trasporto",
    "sg:phone":"+39 0574 620303",
    "sg:postcode":"59100",
    "sg:province":"Prato",
    "wof:name":"Fabbrica Italiana Accumulatori Motocarri Montecchio Spa",
    "wof:placetype":"venue"
},
  "geometry": {"coordinates":[11.046121,43.859016],"type":"Point"}
}