{
  "type": "Feature",
  "properties": {
    "iso:country":"IT",
    "sg:address":"3, Via Firenze 20060 Bussero",
    "sg:city":"Bussero",
    "sg:classifiers":[
        {
            "category":"Manufacturing",
            "subcategory":"Motor Vehicles & Parts",
            "type":"Manufacturing & Wholesale Goods"
        }
    ],
    "sg:phone":"+39 39029524301",
    "sg:postcode":"20060",
    "sg:province":"Milano",
    "sg:tags":[
        "engine"
    ],
    "wof:name":"Re S.p.a",
    "wof:placetype":"venue"
},
  "geometry": {"coordinates":[9.369598,45.528782],"type":"Point"}
}