{
  "type": "Feature",
  "properties": {
    "iso:country":"IT",
    "sg:address":"33074 Fontanafredda",
    "sg:city":"Fontanafredda",
    "sg:classifiers":[
        {
            "category":"Health Services",
            "subcategory":"Health Practitioner",
            "type":"Services"
        }
    ],
    "sg:phone":"+39 0434 999203",
    "sg:postcode":"33074",
    "sg:province":"Pordenone",
    "sg:tags":[
        "medici"
    ],
    "wof:name":"Silverii Gianfranco",
    "wof:placetype":"venue"
},
  "geometry": {"coordinates":[12.6183338165,46.0125007629],"type":"Point"}
}