{
  "type": "Feature",
  "properties": {
    "iso:country":"IT",
    "sg:address":"Vle Italia, 67 - Olmo 36051 Creazzo",
    "sg:city":"Creazzo",
    "sg:classifiers":[
        {
            "category":"Shopping",
            "subcategory":"Clothing, Apparel, & Fashions",
            "type":"Retail Goods"
        }
    ],
    "sg:phone":"+39 0444 520333",
    "sg:postcode":"36051",
    "sg:province":"Vicenza",
    "sg:tags":[
        "image",
        "clothing",
        "basic"
    ],
    "sg:website":"www.nogara.it",
    "wof:name":"Nogara S.p.a.",
    "wof:placetype":"venue"
},
  "geometry": {"coordinates":[11.486341,45.529747],"type":"Point"}
}