{
  "type": "Feature",
  "properties": {
    "iso:country":"IT",
    "sg:address":"20093 Cologno Monzese",
    "sg:city":"Cologno Monzese",
    "sg:orig_category":"Servizi E Lavori Per Arredamento E Industria Del Legno. Servizi E Lavori Per Edilizia E Lavori Pubblici",
    "sg:phone":"+39 02 2670 0812",
    "sg:postcode":"20093",
    "sg:province":"Milano",
    "wof:name":"Fattoruso Francesco",
    "wof:placetype":"venue"
},
  "geometry": {"coordinates":[9.281496,45.534924],"type":"Point"}
}