{
  "type": "Feature",
  "properties": {
    "addr:full":"49, Viale Europa 31018 Gaiarine Gaiarine Treviso 31018",
    "addr:housenumber":"49",
    "addr:postcode":"31018;31018",
    "addr:street":"Viale Europa",
    "iso:country":"IT",
    "sg:address":"49, Viale Europa 31018 Gaiarine",
    "sg:city":"Gaiarine",
    "sg:classifiers":[
        {
            "category":"Home & Garden",
            "subcategory":"Home Furnishings",
            "type":"Retail Goods"
        }
    ],
    "sg:phone":"+39 0434 759292",
    "sg:postcode":"31018",
    "sg:province":"Treviso",
    "sg:tags":[
        "household"
    ],
    "wof:name":"Mobiltrevi (s.r.l.)",
    "wof:placetype":"venue"
},
  "geometry": {"coordinates":[12.509391,45.883339],"type":"Point"}
}