{
  "type": "Feature",
  "properties": {
    "iso:country":"IT",
    "sg:address":"Piazza Monte Di Piet\u00e1, 3, 31100 Treviso, Tv",
    "sg:city":"Treviso",
    "sg:classifiers":[
        {
            "category":"Banks & Credit Unions",
            "subcategory":"Bank",
            "type":"Services"
        }
    ],
    "sg:phone":"+39 0422 6541",
    "sg:postcode":"31100",
    "sg:province":"Treviso",
    "sg:website":"http://www.cassamarca.it",
    "wof:name":"Cassamarca, Cassa Di Risparmio Della Marca Trivigiana Spa",
    "wof:placetype":"venue"
},
  "geometry": {"coordinates":[12.20272,45.651211],"type":"Point"}
}