{
  "type": "Feature",
  "properties": {
    "iso:country":"IT",
    "sg:address":"16, Via Grandi Achille 20090 Vimodrone",
    "sg:city":"Vimodrone",
    "sg:classifiers":[
        {
            "category":"Manufacturing",
            "subcategory":"Rubber & Plastics",
            "type":"Manufacturing & Wholesale Goods"
        }
    ],
    "sg:phone":"+39 39022504222",
    "sg:postcode":"20090",
    "sg:province":"Milano",
    "wof:name":"Tecnoresina (s.r.l.)",
    "wof:placetype":"venue"
},
  "geometry": {"coordinates":[9.2942771912,45.51146698],"type":"Point"}
}