{
  "type": "Feature",
  "properties": {
    "iso:country":"IT",
    "sg:address":"10134 Torino",
    "sg:city":"Torino",
    "sg:orig_category":"Servizi Vari Di Interesse Pubblico",
    "sg:phone":"+39 011 304 0070",
    "sg:postcode":"10134",
    "sg:province":"Torino",
    "wof:name":"Centro Esoterico",
    "wof:placetype":"venue"
},
  "geometry": {"coordinates":[7.659695,45.040279],"type":"Point"}
}