{
  "type": "Feature",
  "properties": {
    "iso:country":"IT",
    "sg:address":"20132 Milano",
    "sg:city":"Milano",
    "sg:orig_category":"Servizi Ausiliari Dei Mezzi Di Trasporto",
    "sg:phone":"+39 02 215 3481",
    "sg:postcode":"20132",
    "sg:province":"Milano",
    "wof:name":"Garage Pordenon S.r.l.",
    "wof:placetype":"venue"
},
  "geometry": {"coordinates":[9.235792,45.490639],"type":"Point"}
}