{
  "type": "Feature",
  "properties": {
    "addr:full":"3, Via Guglielmo Marconi 37040 Bonavigo Bonavigo Verona 37040",
    "addr:postcode":"37040;37040",
    "addr:street":"Via Guglielmo Marconi",
    "iso:country":"IT",
    "sg:address":"3, Via Guglielmo Marconi 37040 Bonavigo",
    "sg:city":"Bonavigo",
    "sg:classifiers":[
        {
            "category":"Shopping",
            "subcategory":"Computers & Home Electronics",
            "type":"Retail Goods"
        }
    ],
    "sg:phone":"+39 0442 640992",
    "sg:postcode":"37040",
    "sg:province":"Verona",
    "sg:tags":[
        "electronic",
        "electrical",
        "equipment"
    ],
    "wof:name":"Tempo",
    "wof:placetype":"venue"
},
  "geometry": {"coordinates":[11.311217,45.228771],"type":"Point"}
}