{
  "type": "Feature",
  "properties": {
    "iso:country":"IT",
    "sg:address":"Via Charta 77n. 16/c 50018 Scandicci",
    "sg:city":"Scandicci",
    "sg:classifiers":[
        {
            "category":"Shopping",
            "subcategory":"Jewelry",
            "type":"Retail Goods"
        }
    ],
    "sg:phone":"+39 055 722 1158",
    "sg:postcode":"50018",
    "sg:province":"Firenze",
    "sg:tags":[
        "item",
        "made",
        "silver",
        "gift"
    ],
    "wof:name":"De Vita Sas Di De Vita Fabio & C.",
    "wof:placetype":"venue"
},
  "geometry": {"coordinates":[11.160096,43.763443],"type":"Point"}
}