{
  "type": "Feature",
  "properties": {
    "iso:country":"IT",
    "sg:address":"109, Via Alfredo Di Dio 28877 Ornavasso",
    "sg:city":"Ornavasso",
    "sg:classifiers":[
        {
            "category":"Shopping",
            "subcategory":"Computers & Home Electronics",
            "type":"Retail Goods"
        }
    ],
    "sg:phone":"+39 0323 837368",
    "sg:postcode":"28877",
    "sg:province":"Verbano-Cusio-Ossola",
    "sg:tags":[
        "electronic",
        "electrical",
        "equipment"
    ],
    "wof:name":"La Celsia (s.a.s.)",
    "wof:placetype":"venue"
},
  "geometry": {"coordinates":[8.418724,45.964851],"type":"Point"}
}