{
  "type": "Feature",
  "properties": {
    "addr:full":"20017 Rho Rho Milano 20017",
    "addr:postcode":"20017;20017",
    "iso:country":"IT",
    "sg:address":"20017 Rho",
    "sg:city":"Rho",
    "sg:orig_category":"Servizi Ausiliari Di Analisi, Controllo E Ricerca",
    "sg:phone":"+39 02 9390 6088",
    "sg:postcode":"20017",
    "sg:province":"Milano",
    "wof:name":"Newton S.r.l.",
    "wof:placetype":"venue"
},
  "geometry": {"coordinates":[9.086661,45.528194],"type":"Point"}
}