{
  "type": "Feature",
  "properties": {
    "iso:country":"IT",
    "sg:address":"88842 Cutro",
    "sg:city":"Cutro",
    "sg:classifiers":[
        {
            "category":"Health Services",
            "subcategory":"Nursing And Care Facility",
            "type":"Services"
        }
    ],
    "sg:phone":"+39 0962 781214",
    "sg:postcode":"88842",
    "sg:province":"Crotone",
    "sg:tags":[
        "case",
        "riposo",
        "di"
    ],
    "wof:name":"Fondazione Casa Della Speranza Onlus",
    "wof:placetype":"venue"
},
  "geometry": {"coordinates":[16.982834,39.036427],"type":"Point"}
}