{
  "type": "Feature",
  "properties": {
    "addr:full":"3, Via Corsi Lamberto 60044 Fabriano Fabriano Ancona 60044",
    "addr:postcode":"60044;60044",
    "addr:street":"Via Corsi Lamberto",
    "iso:country":"IT",
    "sg:address":"3, Via Corsi Lamberto 60044 Fabriano",
    "sg:city":"Fabriano",
    "sg:classifiers":[
        {
            "category":"Manufacturing",
            "subcategory":"Paper Products",
            "type":"Manufacturing & Wholesale Goods"
        }
    ],
    "sg:phone":"+39 39073223521",
    "sg:postcode":"60044",
    "sg:province":"Ancona",
    "sg:tags":[
        "cardboard"
    ],
    "wof:name":"Chartae S.r.l.",
    "wof:placetype":"venue"
},
  "geometry": {"coordinates":[13.5187568665,43.6158561707],"type":"Point"}
}