{
  "type": "Feature",
  "properties": {
    "addr:full":"35040 Urbana Urbana Padova 35040",
    "addr:postcode":"35040;35040",
    "iso:country":"IT",
    "sg:address":"35040 Urbana",
    "sg:city":"Urbana",
    "sg:orig_category":"Tessuti E Stoffe",
    "sg:phone":"+39 0429 878173",
    "sg:postcode":"35040",
    "sg:province":"Padova",
    "wof:name":"Biribo' Di Calonego Barbara",
    "wof:placetype":"venue"
},
  "geometry": {"coordinates":[11.429468,45.193802],"type":"Point"}
}