{
  "type": "Feature",
  "properties": {
    "iso:country":"IT",
    "sg:address":"40068 San Lazzaro Di Savena",
    "sg:city":"San Lazzaro",
    "sg:orig_category":"Elettronica Industriale, Prodotti E Apparecchiature",
    "sg:phone":"+39 051 499 9811",
    "sg:postcode":"40068",
    "sg:province":"Bologna",
    "sg:website":"http://www.tebo.it",
    "wof:name":"Tebo Spa",
    "wof:placetype":"venue"
},
  "geometry": {"coordinates":[11.424501,44.45163],"type":"Point"}
}