{
  "type": "Feature",
  "properties": {
    "iso:country":"IT",
    "sg:address":"20129 Milano",
    "sg:city":"Milano",
    "sg:classifiers":[
        {
            "category":"Health Services",
            "subcategory":"Health Practitioner",
            "type":"Services"
        }
    ],
    "sg:phone":"+39 02 2024 0280",
    "sg:postcode":"20129",
    "sg:province":"Milano",
    "sg:tags":[
        "medici"
    ],
    "wof:name":"Spadon Marko Vincenzo",
    "wof:placetype":"venue"
},
  "geometry": {"coordinates":[9.2130861282,45.4794044495],"type":"Point"}
}