{
  "type": "Feature",
  "properties": {
    "iso:country":"IT",
    "sg:address":"10057 S. Ambrogio Di Torino",
    "sg:orig_category":"Serramenti Ed Infissi. Forniture Industriali Per Prevenzione, Controllo E Sicurezza",
    "sg:phone":"+39 011 934 3111",
    "sg:postcode":"10057",
    "sg:province":"Torino",
    "sg:website":"http://www.mottura.it",
    "wof:name":"Mottura Spa - Serrature Di Sicurezza",
    "wof:placetype":"venue"
},
  "geometry": {"coordinates":[8.010125,45.394104],"type":"Point"}
}