{
  "type": "Feature",
  "properties": {
    "iso:country":"IT",
    "sg:address":"10128 Torino",
    "sg:city":"Torino",
    "sg:orig_category":"Articoli Medico-sanitari Ed Ortopedici",
    "sg:phone":"+39 011 581 8864",
    "sg:postcode":"10128",
    "sg:province":"Torino",
    "sg:website":"http://www.zumaglini.it",
    "wof:name":"Officina Ortopedica Zumaglini Srl",
    "wof:placetype":"venue"
},
  "geometry": {"coordinates":[7.665637,45.051918],"type":"Point"}
}