{
  "type": "Feature",
  "properties": {
    "iso:country":"IT",
    "sg:address":"Via Strada Vecchia 21, 39022 Lagundo, Bz",
    "sg:city":"Lagundo",
    "sg:classifiers":[
        {
            "category":"Banks & Credit Unions",
            "subcategory":"Bank",
            "type":"Services"
        }
    ],
    "sg:postcode":"39022",
    "sg:province":"Bolzano/Bozen",
    "wof:name":"Cassa Raiffeisen Di Lagundo Scrl",
    "wof:placetype":"venue"
},
  "geometry": {"coordinates":[11.095398,46.682396],"type":"Point"}
}