{
  "type": "Feature",
  "properties": {
    "iso:country":"IT",
    "sg:address":"70031 Andria",
    "sg:city":"Andria",
    "sg:orig_category":"Abbigliamento Intimo, Calze E Costumi Da Bagno",
    "sg:phone":"+39 0883 597976",
    "sg:postcode":"70031",
    "sg:province":"Bari",
    "wof:name":"Confezioni Baby G. Snc",
    "wof:placetype":"venue"
},
  "geometry": {"coordinates":[16.22868,41.138248],"type":"Point"}
}