{
  "type": "Feature",
  "properties": {
    "iso:country":"IT",
    "sg:address":"Via Fermi Enrico 6 37135 Verona",
    "sg:city":"Verona",
    "sg:classifiers":[
        {
            "category":"Manufacturing",
            "subcategory":"Food",
            "type":"Manufacturing & Wholesale Goods"
        }
    ],
    "sg:phone":"+39 045 809 7111",
    "sg:postcode":"37135",
    "sg:province":"Verona",
    "sg:tags":[
        "industry",
        "additive"
    ],
    "sg:website":"www.hero.it",
    "wof:name":"Hero Italia Spa",
    "wof:placetype":"venue"
},
  "geometry": {"coordinates":[10.969576,45.402302],"type":"Point"}
}