{
  "type": "Feature",
  "properties": {
    "iso:country":"IT",
    "sg:address":"Loc Prella 1 43021 Corniglio",
    "sg:city":"Corniglio",
    "sg:classifiers":[
        {
            "category":"Food & Beverages",
            "subcategory":"Meat & Fish",
            "type":"Retail Goods"
        }
    ],
    "sg:phone":"+39 0521 881206",
    "sg:postcode":"43021",
    "sg:province":"Parma",
    "sg:tags":[
        "bacon",
        "ham"
    ],
    "sg:website":"www.san-nicola.com",
    "wof:name":"San Nicola Prosciuttificio Del Sole Spa",
    "wof:placetype":"venue"
},
  "geometry": {"coordinates":[10.329548,44.807865],"type":"Point"}
}