{
  "type": "Feature",
  "properties": {
    "iso:country":"IT",
    "sg:address":"Via Sansaluto 81 27043 Broni",
    "sg:city":"Broni",
    "sg:classifiers":[
        {
            "category":"Food & Beverages",
            "subcategory":"Liquor & Beverages",
            "type":"Retail Goods"
        }
    ],
    "sg:phone":"+39 0385 51505",
    "sg:postcode":"27043",
    "sg:province":"Pavia",
    "sg:tags":[
        "wine",
        "italian"
    ],
    "wof:name":"Cantina Sociale Intercomunale Di Broni Scrl",
    "wof:placetype":"venue"
},
  "geometry": {"coordinates":[9.156563,45.185886],"type":"Point"}
}