{
  "type": "Feature",
  "properties": {
    "addr:full":"24054 Calcio Calcio Bergamo 24054",
    "addr:postcode":"24054;24054",
    "iso:country":"IT",
    "sg:address":"24054 Calcio",
    "sg:city":"Calcio",
    "sg:orig_category":"Prodotti Di Base E Forniture Per Industria Alimentare E Bevande",
    "sg:phone":"+39 036 396 9098",
    "sg:postcode":"24054",
    "sg:province":"Bergamo",
    "wof:name":"Calbu (s.n.c.)",
    "wof:placetype":"venue"
},
  "geometry": {"coordinates":[9.8475265503,45.5026512146],"type":"Point"}
}