{
  "type": "Feature",
  "properties": {
    "iso:country":"IT",
    "sg:address":"10073 Cirie'",
    "sg:orig_category":"Cosmetici, Prodotti Di Bellezza E Di Igiene",
    "sg:phone":"+39 011 922 2283",
    "sg:postcode":"10073",
    "sg:province":"Torino",
    "wof:name":"Valnat\u00cc Sas Di Valvason Natalia",
    "wof:placetype":"venue"
},
  "geometry": {"coordinates":[7.701959,45.062534],"type":"Point"}
}