{
  "type": "Feature",
  "properties": {
    "addr:full":"246, Via Coriano 47900 Rimini Rimini Rimini 47900",
    "addr:housenumber":"246",
    "addr:postcode":"47900;47900",
    "addr:street":"Via Coriano",
    "iso:country":"IT",
    "sg:address":"246, Via Coriano 47900 Rimini",
    "sg:city":"Rimini",
    "sg:classifiers":[
        {
            "category":"Manufacturing",
            "subcategory":"Motor Vehicles & Parts",
            "type":"Manufacturing & Wholesale Goods"
        }
    ],
    "sg:phone":"+39 0541 730262",
    "sg:postcode":"47900",
    "sg:province":"Rimini",
    "sg:tags":[
        "engine"
    ],
    "wof:name":"Amaducci Srl",
    "wof:placetype":"venue"
},
  "geometry": {"coordinates":[12.599289,44.008263],"type":"Point"}
}