{
  "type": "Feature",
  "properties": {
    "addr:full":"5, Via Frejus 10092 Beinasco Beinasco Torino 10092",
    "addr:postcode":"10092;10092",
    "addr:street":"Via Frejus",
    "iso:country":"IT",
    "sg:address":"5, Via Frejus 10092 Beinasco",
    "sg:city":"Beinasco",
    "sg:classifiers":[
        {
            "category":"Professional",
            "subcategory":"Printing & Photocopies",
            "type":"Services"
        }
    ],
    "sg:phone":"+39 011 349 8866",
    "sg:postcode":"10092",
    "sg:province":"Torino",
    "wof:name":"Roggero & Tortia Poligrafico (s.p.a.)",
    "wof:placetype":"venue"
},
  "geometry": {"coordinates":[7.5845079422,45.0271530151],"type":"Point"}
}