{
  "type": "Feature",
  "properties": {
    "addr:full":"34072 Gradisca D'isonzo Gorizia 34072",
    "addr:postcode":"34072;34072",
    "iso:country":"IT",
    "sg:address":"34072 Gradisca D'isonzo",
    "sg:orig_category":"Frigotecnica, Apparecchiature E Servizi. Climatizzazione E Condizionamento, Apparecchiature E Servizi",
    "sg:phone":"+39 0481 961300",
    "sg:postcode":"34072",
    "sg:province":"Gorizia",
    "wof:name":"Refrigerazione Industriale Di Gorian Franco",
    "wof:placetype":"venue"
},
  "geometry": {"coordinates":[13.4933958054,45.8862266541],"type":"Point"}
}