{
  "type": "Feature",
  "properties": {
    "iso:country":"IT",
    "sg:address":"08100 Nuoro",
    "sg:city":"Nuoro",
    "sg:orig_category":"Arredamento Bar E Ristoranti",
    "sg:phone":"+39 0784 35044",
    "sg:postcode":"08100",
    "sg:province":"Nuoro",
    "wof:name":"Allestil Snc Di Chessa & Vacca",
    "wof:placetype":"venue"
},
  "geometry": {"coordinates":[9.33509,40.325932],"type":"Point"}
}