{
  "type": "Feature",
  "properties": {
    "iso:country":"IT",
    "sg:address":"227, Vl. Gramsci 41100 Modena",
    "sg:city":"Modena",
    "sg:classifiers":[
        {
            "category":"Shopping",
            "subcategory":"Stationery & Office Supplies",
            "type":"Retail Goods"
        }
    ],
    "sg:phone":"+39 39059314685",
    "sg:postcode":"41100",
    "sg:province":"Modena",
    "sg:tags":[
        "professional"
    ],
    "sg:website":"http://www.taglieri.it",
    "wof:name":"Taglieri International",
    "wof:placetype":"venue"
},
  "geometry": {"coordinates":[10.9379358292,44.6587677002],"type":"Point"}
}