{
  "type": "Feature",
  "properties": {
    "addr:full":"10146 Torino Torino Torino 10146",
    "addr:postcode":"10146;10146",
    "iso:country":"IT",
    "sg:address":"10146 Torino",
    "sg:city":"Torino",
    "sg:orig_category":"Autodemolizioni",
    "sg:phone":"+39 011 779 4979",
    "sg:postcode":"10146",
    "sg:province":"Torino",
    "wof:name":"Cossa Autodemolizioni Snc Di De Pace Giuseppe",
    "wof:placetype":"venue"
},
  "geometry": {"coordinates":[7.627969,45.087784],"type":"Point"}
}