{
  "type": "Feature",
  "properties": {
    "iso:country":"IT",
    "sg:address":"16129 Genova",
    "sg:city":"Genova",
    "sg:orig_category":"Musica",
    "sg:phone":"+39 010 590775",
    "sg:postcode":"16129",
    "sg:province":"Genova",
    "wof:name":"Centrodisco Di Bertozzi E C. Snc",
    "wof:placetype":"venue"
},
  "geometry": {"coordinates":[8.9490776062,44.3953170776],"type":"Point"}
}