{
  "type": "Feature",
  "properties": {
    "iso:country":"IT",
    "sg:address":"21013 Gallarate",
    "sg:city":"Gallarate",
    "sg:orig_category":"Abbigliamento - Produzione E Ingrosso",
    "sg:phone":"+39 0331 786400",
    "sg:postcode":"21013",
    "sg:province":"Varese",
    "wof:name":"Confezioni Stella Due G. Di L. Grandino & C.",
    "wof:placetype":"venue"
},
  "geometry": {"coordinates":[8.782217,45.650597],"type":"Point"}
}