{
  "type": "Feature",
  "properties": {
    "iso:country":"IT",
    "sg:address":"06081 Assisi",
    "sg:city":"Assisi",
    "sg:orig_category":"Prodotti E Manufatti In Materie Plastiche. Articoli Per Imballaggio E Confezionamento",
    "sg:phone":"+39 075 803 9033",
    "sg:postcode":"06081",
    "sg:province":"Perugia",
    "wof:name":"Polycart Srl",
    "wof:placetype":"venue"
},
  "geometry": {"coordinates":[12.5430707932,43.1025810242],"type":"Point"}
}