{
  "type": "Feature",
  "properties": {
    "iso:country":"IT",
    "sg:address":"17, Via Provinciale Est 31040 Salgareda",
    "sg:city":"Salgareda",
    "sg:classifiers":[
        {
            "category":"Professional",
            "subcategory":"Engineering",
            "type":"Services"
        }
    ],
    "sg:phone":"+39 0422 804192",
    "sg:postcode":"31040",
    "sg:province":"Treviso",
    "sg:tags":[
        "machine",
        "-",
        "mechanical"
    ],
    "wof:name":"S T A R S.r.l.",
    "wof:placetype":"venue"
},
  "geometry": {"coordinates":[12.506091,45.701633],"type":"Point"}
}