{
  "type": "Feature",
  "properties": {
    "iso:country":"IT",
    "sg:address":"37040 Veronella",
    "sg:city":"Veronella",
    "sg:orig_category":"Biancheria Intima Ed Abbigliamento Intimo - Produzione E Ingrosso",
    "sg:phone":"+39 0442 47688",
    "sg:postcode":"37040",
    "sg:province":"Verona",
    "wof:name":"Maglificio Antonella Spa",
    "wof:placetype":"venue"
},
  "geometry": {"coordinates":[11.324538,45.323135],"type":"Point"}
}