{
  "type": "Feature",
  "properties": {
    "iso:country":"IT",
    "sg:address":"Via Peruzzi 7/7a; S. Giovanni Valdarno; 52027",
    "sg:classifiers":[
        {
            "category":"Banks & Credit Unions",
            "subcategory":"Bank",
            "type":"Services"
        }
    ],
    "sg:phone":"+39 055 912 2866",
    "sg:postcode":"52027",
    "sg:province":"Arezzo",
    "wof:name":"Credito Italiano Spa",
    "wof:placetype":"venue"
},
  "geometry": {"coordinates":[11.528522,43.566933],"type":"Point"}
}