{
  "type": "Feature",
  "properties": {
    "addr:full":"10123 Torino Torino Torino 10123",
    "addr:postcode":"10123;10123",
    "iso:country":"IT",
    "sg:address":"10123 Torino",
    "sg:city":"Torino",
    "sg:orig_category":"Hobbistica",
    "sg:phone":"+39 011 541205",
    "sg:postcode":"10123",
    "sg:province":"Torino",
    "wof:name":"Bolaffi S.p.a.",
    "wof:placetype":"venue"
},
  "geometry": {"coordinates":[7.581069,45.021954],"type":"Point"}
}