{
  "type": "Feature",
  "properties": {
    "iso:country":"IT",
    "sg:address":"04019 Terracina",
    "sg:city":"Terracina",
    "sg:orig_category":"Dolciumi - Vendita Al Dettaglio",
    "sg:phone":"+39 0773 765222",
    "sg:postcode":"04019",
    "sg:province":"Latina",
    "wof:name":"Punto Dolce Di D'amico Alvaro & C. Snc",
    "wof:placetype":"venue"
},
  "geometry": {"coordinates":[13.197106,41.336266],"type":"Point"}
}