{
  "type": "Feature",
  "properties": {
    "iso:country":"IT",
    "sg:address":"20090 Segrate",
    "sg:city":"Segrate",
    "sg:orig_category":"Forniture Per Agricoltura E Zootecnia. Animali Domestici",
    "sg:phone":"+39 02 2692 1362",
    "sg:postcode":"20090",
    "sg:province":"Milano",
    "wof:name":"Dog Smart Di Cucina Stefano",
    "wof:placetype":"venue"
},
  "geometry": {"coordinates":[9.3003311157,45.4876785278],"type":"Point"}
}