{
  "type": "Feature",
  "properties": {
    "addr:full":"12, Via Chiesa Damiano 20030 Seveso Seveso Milano 20030",
    "addr:postcode":"20030;20030",
    "addr:street":"Via Chiesa Damiano",
    "iso:country":"IT",
    "sg:address":"12, Via Chiesa Damiano 20030 Seveso",
    "sg:city":"Seveso",
    "sg:classifiers":[
        {
            "category":"Shopping",
            "subcategory":"Clothing, Apparel, & Fashions",
            "type":"Retail Goods"
        }
    ],
    "sg:phone":"+39 036 252 1748",
    "sg:postcode":"20030",
    "sg:province":"Milano",
    "sg:tags":[
        "clothes"
    ],
    "wof:name":"Winter 83",
    "wof:placetype":"venue"
},
  "geometry": {"coordinates":[9.188141,45.463688],"type":"Point"}
}