{
  "type": "Feature",
  "properties": {
    "addr:full":"Via Casamassimasamassima 70010 Capurso Capurso Bari 70010",
    "addr:postcode":"70010;70010",
    "addr:street":"Via Casamassimasamassima",
    "iso:country":"IT",
    "sg:address":"Via Casamassimasamassima 70010 Capurso",
    "sg:city":"Capurso",
    "sg:classifiers":[
        {
            "category":"Shopping",
            "subcategory":"Clothing, Apparel, & Fashions",
            "type":"Retail Goods"
        }
    ],
    "sg:phone":"+39 080 455 1013",
    "sg:postcode":"70010",
    "sg:province":"Bari",
    "sg:tags":[
        "children's",
        "clothing"
    ],
    "wof:name":"Miral Manifatture Di Fraddosio Rosa",
    "wof:placetype":"venue"
},
  "geometry": {"coordinates":[16.869291,41.126053],"type":"Point"}
}