{
  "type": "Feature",
  "properties": {
    "iso:country":"IT",
    "sg:address":"00179 Roma",
    "sg:city":"Roma",
    "sg:orig_category":"Studi E Consulenze Tecniche E Industriali. Consulenze Tecniche, Amministrative E Perizie. Professionisti - Studi E Servizi Ed Associazioni Di Interesse Aziendale",
    "sg:phone":"+39 06 788 6389",
    "sg:postcode":"00179",
    "sg:province":"Roma",
    "wof:name":"Bernardi Sabrina",
    "wof:placetype":"venue"
},
  "geometry": {"coordinates":[12.529524,41.866653],"type":"Point"}
}