{
  "type": "Feature",
  "properties": {
    "addr:full":"57124 Livorno Livorno Livorno 57124",
    "addr:postcode":"57124;57124",
    "iso:country":"IT",
    "sg:address":"57124 Livorno",
    "sg:city":"Livorno",
    "sg:orig_category":"Pubblica Amministrazione",
    "sg:phone":"+39 0586 868111",
    "sg:postcode":"57124",
    "sg:province":"Livorno",
    "wof:name":"Vigili Del Fuoco",
    "wof:placetype":"venue"
},
  "geometry": {"coordinates":[10.3366651535,43.5361099243],"type":"Point"}
}