{
  "type": "Feature",
  "properties": {
    "addr:full":"Via San Michele 1/3/5 70010 Casamassima Casamassima Bari 70010",
    "addr:housenumber":"1 / 3 / 5",
    "addr:postcode":"70010;70010",
    "addr:street":"Via San Michele",
    "iso:country":"IT",
    "sg:address":"Via San Michele 1/3/5 70010 Casamassima",
    "sg:city":"Casamassima",
    "sg:classifiers":[
        {
            "category":"Food & Beverages",
            "subcategory":"Fruits & Vegetables",
            "type":"Retail Goods"
        }
    ],
    "sg:phone":"+39 080 673521",
    "sg:postcode":"70010",
    "sg:province":"Bari",
    "wof:name":"Nicola Saponaro E Figli Srl",
    "wof:placetype":"venue"
},
  "geometry": {"coordinates":[16.9445571899,40.8880233765],"type":"Point"}
}