{
  "type": "Feature",
  "properties": {
    "addr:full":"84123 Salerno Salerno Salerno 84123",
    "addr:postcode":"84123;84123",
    "iso:country":"IT",
    "sg:address":"84123 Salerno",
    "sg:city":"Salerno",
    "sg:orig_category":"Cine-foto-ottica. Shopping",
    "sg:phone":"+39 089 226828",
    "sg:postcode":"84123",
    "sg:province":"Salerno",
    "wof:name":"Erotica Sexy Shop Di Noschese Francesco",
    "wof:placetype":"venue"
},
  "geometry": {"coordinates":[14.770326,40.675312],"type":"Point"}
}