{
  "type": "Feature",
  "properties": {
    "addr:full":"35013 Cittadella Cittadella Padova 35013",
    "addr:postcode":"35013;35013",
    "iso:country":"IT",
    "sg:address":"35013 Cittadella",
    "sg:city":"Cittadella",
    "sg:orig_category":"Forniture Per Abbigliamento E Pelletterie",
    "sg:phone":"+39 049 940 3975",
    "sg:postcode":"35013",
    "sg:province":"Padova",
    "wof:name":"Acab S.r.l.",
    "wof:placetype":"venue"
},
  "geometry": {"coordinates":[11.9578056335,45.3506507874],"type":"Point"}
}