{
  "type": "Feature",
  "properties": {
    "addr:full":"335, V. Iv Novembre 48014 Castel Bolognese Castel Bolognese Ravenna 48014",
    "addr:housenumber":"335",
    "addr:postcode":"48014;48014",
    "addr:street":"V. Iv Novembre",
    "iso:country":"IT",
    "sg:address":"335, V. Iv Novembre 48014 Castel Bolognese",
    "sg:city":"Castel Bolognese",
    "sg:classifiers":[
        {
            "category":"Manufacturing",
            "subcategory":"Metals",
            "type":"Manufacturing & Wholesale Goods"
        }
    ],
    "sg:phone":"+39 39054650163",
    "sg:postcode":"48014",
    "sg:province":"Ravenna",
    "sg:tags":[
        "processing"
    ],
    "sg:website":"http://www.isaf-otap.it",
    "wof:name":"Nuova Otap Snc",
    "wof:placetype":"venue"
},
  "geometry": {"coordinates":[12.1965713501,44.4157295227],"type":"Point"}
}