{
  "type": "Feature",
  "properties": {
    "iso:country":"IT",
    "sg:address":"20124 Milano",
    "sg:city":"Milano",
    "sg:orig_category":"Servizi Culturali E Per Lo Spettacolo. Musica",
    "sg:phone":"+39 02 6749 0271",
    "sg:postcode":"20124",
    "sg:province":"Milano",
    "wof:name":"Baby Records International Srl",
    "wof:placetype":"venue"
},
  "geometry": {"coordinates":[9.198712,45.490673],"type":"Point"}
}