{
  "type": "Feature",
  "properties": {
    "iso:country":"IT",
    "sg:address":"91, Via Padana Superiore 25045 Castegnato",
    "sg:city":"Castegnato",
    "sg:classifiers":[
        {
            "category":"Autos & Motor Vehicles",
            "subcategory":"Automobile Sales",
            "type":"Retail Goods"
        }
    ],
    "sg:phone":"+39 030 214 6611",
    "sg:postcode":"25045",
    "sg:province":"Brescia",
    "sg:tags":[
        "equipment",
        "transport"
    ],
    "wof:name":"Sprint Bike Srl",
    "wof:placetype":"venue"
},
  "geometry": {"coordinates":[10.115006,45.551834],"type":"Point"}
}