{
  "type": "Feature",
  "properties": {
    "addr:full":"Via Ancona 65 63015 Monte Urano Monte Urano Ascoli Piceno 63015",
    "addr:housenumber":"65",
    "addr:postcode":"63015;63015",
    "addr:street":"Via Ancona",
    "iso:country":"IT",
    "sg:address":"Via Ancona 65 63015 Monte Urano",
    "sg:city":"Monte Urano",
    "sg:classifiers":[
        {
            "category":"Shopping",
            "subcategory":"Shoes",
            "type":"Retail Goods"
        }
    ],
    "sg:phone":"+39 0734 841015",
    "sg:postcode":"63015",
    "sg:province":"Ascoli Piceno",
    "sg:tags":[
        "children's"
    ],
    "sg:website":"www.missouri.it",
    "wof:name":"Missouri Srl",
    "wof:placetype":"venue"
},
  "geometry": {"coordinates":[13.674335,43.201813],"type":"Point"}
}