{
  "type": "Feature",
  "properties": {
    "addr:full":"Via Dogali 20 98123 Messina Messina Messina 98123",
    "addr:housenumber":"20",
    "addr:postcode":"98123;98123",
    "addr:street":"Via Dogali",
    "iso:country":"IT",
    "sg:address":"Via Dogali 20 98123 Messina",
    "sg:city":"Messina",
    "sg:classifiers":[
        {
            "category":"Manufacturing",
            "subcategory":"Food",
            "type":"Manufacturing & Wholesale Goods"
        }
    ],
    "sg:phone":"+39 090 651 0400",
    "sg:postcode":"98123",
    "sg:province":"Messina",
    "sg:tags":[
        "raw",
        "material"
    ],
    "wof:name":"Food Technical Services Di Nocilla",
    "wof:placetype":"venue"
},
  "geometry": {"coordinates":[15.5574045181,38.185459137],"type":"Point"}
}