{
  "type": "Feature",
  "properties": {
    "iso:country":"IT",
    "sg:address":"31033 Castelfranco Veneto",
    "sg:city":"Castelfranco Veneto",
    "sg:orig_category":"Elaboratori Elettronici",
    "sg:phone":"+39 0423 4247",
    "sg:postcode":"31033",
    "sg:province":"Treviso",
    "sg:website":"http://www.ergon.it",
    "wof:name":"Ergon Informatica Srl",
    "wof:placetype":"venue"
},
  "geometry": {"coordinates":[11.96002,45.685497],"type":"Point"}
}