{
  "type": "Feature",
  "properties": {
    "iso:country":"IT",
    "sg:address":"00139 Roma",
    "sg:city":"Roma",
    "sg:orig_category":"Arredo Cucina Ed Elettrodomestici. Elettrodomestici",
    "sg:phone":"+39 06 810 5294",
    "sg:postcode":"00139",
    "sg:province":"Roma",
    "wof:name":"Elettronica Salario",
    "wof:placetype":"venue"
},
  "geometry": {"coordinates":[12.421122,41.858242],"type":"Point"}
}