{
  "type": "Feature",
  "properties": {
    "iso:country":"IT",
    "sg:address":"8, Viale Delle Industrie 31018 Gaiarine",
    "sg:city":"Gaiarine",
    "sg:classifiers":[
        {
            "category":"Professional",
            "subcategory":"Engineering",
            "type":"Services"
        }
    ],
    "sg:phone":"+39 0434 758790",
    "sg:postcode":"31018",
    "sg:province":"Treviso",
    "sg:tags":[
        "machine",
        "-",
        "mechanical"
    ],
    "wof:name":"Tec Service S.r.l.",
    "wof:placetype":"venue"
},
  "geometry": {"coordinates":[12.505413,45.879383],"type":"Point"}
}