{
  "type": "Feature",
  "properties": {
    "iso:country":"IT",
    "sg:address":"16132 Genova",
    "sg:city":"Genova",
    "sg:orig_category":"Materiali Edili",
    "sg:phone":"+39 010 522 0011",
    "sg:postcode":"16132",
    "sg:province":"Genova",
    "wof:name":"Lugli Enrico",
    "wof:placetype":"venue"
},
  "geometry": {"coordinates":[8.969427,44.413837],"type":"Point"}
}