{
  "type": "Feature",
  "properties": {
    "iso:country":"IT",
    "sg:address":"21017 Samarate",
    "sg:city":"Samarate",
    "sg:orig_category":"Abbigliamento Esterno, Maglierie E Pelliccerie. Calzature, Pelletterie E Pelli",
    "sg:phone":"+39 0331 721218",
    "sg:postcode":"21017",
    "sg:province":"Varese",
    "wof:name":"Kastinger Italia S.r.l.",
    "wof:placetype":"venue"
},
  "geometry": {"coordinates":[8.797558,45.637585],"type":"Point"}
}