{
  "type": "Feature",
  "properties": {
    "iso:country":"IT",
    "sg:address":"10090 Bruino",
    "sg:city":"Bruino",
    "sg:orig_category":"Macchine Utensili E Impianti",
    "sg:phone":"+39 011 904 8184",
    "sg:postcode":"10090",
    "sg:province":"Torino",
    "wof:name":"R.i.s.s.o. Srl",
    "wof:placetype":"venue"
},
  "geometry": {"coordinates":[7.480196,45.01186],"type":"Point"}
}