{
  "type": "Feature",
  "properties": {
    "iso:country":"IT",
    "sg:address":"88100 Catanzaro",
    "sg:city":"Catanzaro",
    "sg:orig_category":"Sport - Articoli E Forniture",
    "sg:phone":"+39 0961 783763",
    "sg:postcode":"88100",
    "sg:province":"Catanzaro",
    "wof:name":"Russo Antonio",
    "wof:placetype":"venue"
},
  "geometry": {"coordinates":[16.606611,38.831097],"type":"Point"}
}