{
  "type": "Feature",
  "properties": {
    "iso:country":"IT",
    "sg:address":"36077 Altavilla Vicentina",
    "sg:city":"Altavilla Vicentina",
    "sg:orig_category":"Metalli E Leghe",
    "sg:postcode":"36077",
    "sg:province":"Vicenza",
    "wof:name":"Ferlat Acciai S.p.a.",
    "wof:placetype":"venue"
},
  "geometry": {"coordinates":[11.455124855,45.5115776062],"type":"Point"}
}