{
  "type": "Feature",
  "properties": {
    "iso:country":"IT",
    "sg:address":"20123 Milano",
    "sg:city":"Milano",
    "sg:orig_category":"Trasporti E Spedizioni Merci",
    "sg:phone":"+39 02 8940 6816",
    "sg:postcode":"20123",
    "sg:province":"Milano",
    "sg:website":"http://www.milanoservice.com",
    "wof:name":"Milanoservice Srl",
    "wof:placetype":"venue"
},
  "geometry": {"coordinates":[9.175213,45.457001],"type":"Point"}
}