{
  "type": "Feature",
  "properties": {
    "addr:full":"Via Gemona, 3; Udine; 33100 Udine Udine 33100",
    "addr:housenumber":"3",
    "addr:postcode":"33100;33100",
    "addr:street":"Via Gemona",
    "iso:country":"IT",
    "sg:address":"Via Gemona, 3; Udine; 33100",
    "sg:city":"Udine",
    "sg:classifiers":[
        {
            "category":"Banks & Credit Unions",
            "subcategory":"Bank",
            "type":"Services"
        }
    ],
    "sg:phone":"+39 0432 506641",
    "sg:postcode":"33100",
    "sg:province":"Udine",
    "wof:name":"Banca D'italia",
    "wof:placetype":"venue"
},
  "geometry": {"coordinates":[13.233782,46.068325],"type":"Point"}
}