{
  "type": "Feature",
  "properties": {
    "iso:country":"IT",
    "sg:address":"25045 Castegnato",
    "sg:city":"Castegnato",
    "sg:orig_category":"Lavorazioni Metalli, Stampaggio E Saldatura",
    "sg:phone":"+39 030 373 3761",
    "sg:postcode":"25045",
    "sg:province":"Brescia",
    "wof:name":"S.i.r.m. Srl",
    "wof:placetype":"venue"
},
  "geometry": {"coordinates":[10.114379,45.551884],"type":"Point"}
}