{
  "type": "Feature",
  "properties": {
    "iso:country":"IT",
    "sg:address":"34123 Trieste",
    "sg:city":"Trieste",
    "sg:orig_category":"Prodotti E Manufatti In Materie Plastiche. Prodotti Cosmetici E Da Toeletta. Forniture Per Attivita' Industriali",
    "sg:phone":"+39 040 301746",
    "sg:postcode":"34123",
    "sg:province":"Trieste",
    "wof:name":"Gasteiger & Ci",
    "wof:placetype":"venue"
},
  "geometry": {"coordinates":[13.7637901306,45.6421928406],"type":"Point"}
}