{
  "type": "Feature",
  "properties": {
    "iso:country":"IT",
    "sg:address":"Via Del Lavoro 8/10 30030 Pianiga",
    "sg:city":"Pianiga",
    "sg:classifiers":[
        {
            "category":"Home & Garden",
            "subcategory":"Household Appliances",
            "type":"Retail Goods"
        }
    ],
    "sg:phone":"+39 041 513 9611",
    "sg:postcode":"30030",
    "sg:province":"Venezia",
    "sg:tags":[
        "electric"
    ],
    "sg:website":"www.simac-vetrella.com",
    "wof:name":"Delonghi Spa",
    "wof:placetype":"venue"
},
  "geometry": {"coordinates":[12.080393,45.448769],"type":"Point"}
}