{
  "type": "Feature",
  "properties": {
    "addr:full":"20060 Vignate Vignate Milano 20060",
    "addr:postcode":"20060;20060",
    "iso:country":"IT",
    "sg:address":"20060 Vignate",
    "sg:city":"Vignate",
    "sg:orig_category":"Lavorazioni Metalli, Stampaggio E Saldatura",
    "sg:phone":"+39 02 956 0542",
    "sg:postcode":"20060",
    "sg:province":"Milano",
    "wof:name":"T.f.g. Di Terzi F. & G. (s.n.c.)",
    "wof:placetype":"venue"
},
  "geometry": {"coordinates":[9.225269,45.377327],"type":"Point"}
}