{
  "type": "Feature",
  "properties": {
    "iso:country":"IT",
    "sg:address":"20157 Milano",
    "sg:city":"Milano",
    "sg:orig_category":"Forni Industriali",
    "sg:phone":"+39 02 357 0554",
    "sg:postcode":"20157",
    "sg:province":"Milano",
    "sg:website":"http://www.caspelifter.com",
    "wof:name":"Ca.spe. Lifter Srl",
    "wof:placetype":"venue"
},
  "geometry": {"coordinates":[9.1435279846,45.519859314],"type":"Point"}
}