{
  "type": "Feature",
  "properties": {
    "iso:country":"IT",
    "sg:address":"28, Via Gregorcic Anton 34170 Gorizia",
    "sg:city":"Gorizia",
    "sg:classifiers":[
        {
            "category":"Food & Beverages",
            "subcategory":"Groceries & Convenience Stores",
            "type":"Retail Goods"
        }
    ],
    "sg:phone":"+39 39048121971",
    "sg:postcode":"34170",
    "sg:province":"Gorizia",
    "sg:tags":[
        "drink"
    ],
    "wof:name":"Ciemme Liquori (s.p.a.)",
    "wof:placetype":"venue"
},
  "geometry": {"coordinates":[13.595297,45.915714],"type":"Point"}
}