{
  "type": "Feature",
  "properties": {
    "iso:country":"IT",
    "sg:address":"22030 Castelmarte",
    "sg:city":"Castelmarte",
    "sg:orig_category":"Telecomunicazioni E Telefonia, Impianti, Apparecchi E Servizi",
    "sg:phone":"+39 031 620018",
    "sg:postcode":"22030",
    "sg:province":"Como",
    "wof:name":"Net Project S.n.c.",
    "wof:placetype":"venue"
},
  "geometry": {"coordinates":[9.085924,45.781212],"type":"Point"}
}