{
  "type": "Feature",
  "properties": {
    "iso:country":"IT",
    "sg:address":"13, Via Lomazzo Paolo 20154 Milano",
    "sg:city":"Milano",
    "sg:classifiers":[
        {
            "category":"Communications",
            "subcategory":"Newspaper",
            "type":"Services"
        }
    ],
    "sg:phone":"+39 390 231 2203",
    "sg:postcode":"20154",
    "sg:province":"Milano",
    "sg:tags":[
        "advertising"
    ],
    "wof:name":"Gioia",
    "wof:placetype":"venue"
},
  "geometry": {"coordinates":[9.172696,45.481522],"type":"Point"}
}