{
  "type": "Feature",
  "properties": {
    "iso:country":"IT",
    "sg:address":"24046 Osio Sotto",
    "sg:city":"Osio Sotto",
    "sg:orig_category":"Macchine E Forniture Per Industria Orafa E Per Orologeria",
    "sg:phone":"+39 035 482 3919",
    "sg:postcode":"24046",
    "sg:province":"Bergamo",
    "wof:name":"Serena Di Ferruccio Carminati E C. (s.n.c.)",
    "wof:placetype":"venue"
},
  "geometry": {"coordinates":[9.587333,45.613022],"type":"Point"}
}