{
  "type": "Feature",
  "properties": {
    "iso:country":"IT",
    "sg:address":"87, Via Laghi Antonio 48018 Faenza",
    "sg:city":"Faenza",
    "sg:classifiers":[
        {
            "category":"Wholesale",
            "subcategory":"Medical Equipment & Supplies",
            "type":"Manufacturing & Wholesale Goods"
        }
    ],
    "sg:phone":"+39 0546 661542",
    "sg:postcode":"48018",
    "sg:province":"Ravenna",
    "sg:tags":[
        "-",
        "health",
        "instrument"
    ],
    "wof:name":"Medilab-pd S.r.l.",
    "wof:placetype":"venue"
},
  "geometry": {"coordinates":[12.196571,44.41573],"type":"Point"}
}