{
  "type": "Feature",
  "properties": {
    "addr:full":"2, Via Di Marmiceto Ospedaletto 56121 Pisa Pisa Pisa 56121",
    "addr:postcode":"56121;56121",
    "addr:street":"Via Di Marmiceto",
    "iso:country":"IT",
    "sg:address":"2, Via Di Marmiceto Ospedaletto 56121 Pisa",
    "sg:city":"Pisa",
    "sg:classifiers":[
        {
            "category":"Communications",
            "subcategory":"Television Station",
            "type":"Services"
        }
    ],
    "sg:phone":"+39 39050985314",
    "sg:postcode":"56121",
    "sg:province":"Pisa",
    "sg:tags":[
        "audio-visual"
    ],
    "wof:name":"Archidee S.r.l.",
    "wof:placetype":"venue"
},
  "geometry": {"coordinates":[10.429723,43.686165],"type":"Point"}
}