{
  "type": "Feature",
  "properties": {
    "iso:country":"IT",
    "sg:address":"2, Via Tiepolo Giovanni Battista 35010 Cadoneghe",
    "sg:city":"Cadoneghe",
    "sg:classifiers":[
        {
            "category":"Professional",
            "subcategory":"Engineering",
            "type":"Services"
        }
    ],
    "sg:phone":"+39 049 887 3055",
    "sg:postcode":"35010",
    "sg:province":"Padova",
    "sg:tags":[
        "machine",
        "-",
        "mechanical"
    ],
    "wof:name":"Refrigeration (s.p.a.)",
    "wof:placetype":"venue"
},
  "geometry": {"coordinates":[11.876589,45.409569],"type":"Point"}
}