{
  "type": "Feature",
  "properties": {
    "addr:full":"15050 Villalvernia Villalvernia Alessandria 15050",
    "addr:housenumber":"15050",
    "addr:postcode":"15050",
    "addr:street":"Villalvernia Villalvernia",
    "iso:country":"IT",
    "sg:address":"15050 Villalvernia",
    "sg:city":"Villalvernia",
    "sg:orig_category":"Materiali Semilavorati Metallici",
    "sg:phone":"+39 0131 836211",
    "sg:postcode":"15050",
    "sg:province":"Alessandria",
    "wof:name":"Albasider S.p.a.",
    "wof:placetype":"venue"
},
  "geometry": {"coordinates":[8.855315,44.814522],"type":"Point"}
}