{
  "type": "Feature",
  "properties": {
    "iso:country":"IT",
    "sg:address":"10147 Torino",
    "sg:city":"Torino",
    "sg:orig_category":"Arredamenti - Vendita Al Dettaglio",
    "sg:phone":"+39 011 223 0512",
    "sg:postcode":"10147",
    "sg:province":"Torino",
    "sg:website":"http://mobilus.it",
    "wof:name":"S.e.m. Spa",
    "wof:placetype":"venue"
},
  "geometry": {"coordinates":[7.672458,45.101341],"type":"Point"}
}