{
  "type": "Feature",
  "properties": {
    "iso:country":"IT",
    "sg:address":"Via Mainardo 36 39012 Meran",
    "sg:classifiers":[
        {
            "category":"Manufacturing",
            "subcategory":"Wood Products",
            "type":"Manufacturing & Wholesale Goods"
        }
    ],
    "sg:phone":"+39 0473 222840",
    "sg:postcode":"39012",
    "sg:province":"Bolzano/Bozen",
    "sg:tags":[
        "firework",
        "pyrotechnic",
        "except"
    ],
    "wof:name":"R. Riedlinger Srl",
    "wof:placetype":"venue"
},
  "geometry": {"coordinates":[11.1580591202,46.6726303101],"type":"Point"}
}