{
  "type": "Feature",
  "properties": {
    "addr:full":"20090 Trezzano Sul Naviglio Trezzano sul Naviglio Milano 20090",
    "addr:postcode":"20090;20090",
    "iso:country":"IT",
    "sg:address":"20090 Trezzano Sul Naviglio",
    "sg:city":"Trezzano sul Naviglio",
    "sg:orig_category":"Servizi Per Lo Sport E Il Tempo Libero. Associazioni Ed Organismi Di Interesse Pubblico",
    "sg:phone":"+39 02 445 5639",
    "sg:postcode":"20090",
    "sg:province":"Milano",
    "wof:name":"Atletic Trezzano U.s.",
    "wof:placetype":"venue"
},
  "geometry": {"coordinates":[9.066118,45.422001],"type":"Point"}
}