{
  "type": "Feature",
  "properties": {
    "iso:country":"IT",
    "sg:address":"00192 Roma",
    "sg:city":"Roma",
    "sg:orig_category":"Forniture Alberghi, Bar, Ristoranti E Comunita'",
    "sg:phone":"+39 06 3973 0253",
    "sg:postcode":"00192",
    "sg:province":"Roma",
    "wof:name":"Cafiero Mario",
    "wof:placetype":"venue"
},
  "geometry": {"coordinates":[12.4518585205,41.9072952271],"type":"Point"}
}