{
  "type": "Feature",
  "properties": {
    "iso:country":"IT",
    "sg:address":"64028 Silvi",
    "sg:city":"Silvi",
    "sg:orig_category":"Elettrotecnica Industriale, Prodotti E Apparecchiature",
    "sg:phone":"+39 085 935 2699",
    "sg:postcode":"64028",
    "sg:province":"Teramo",
    "sg:website":"http://www.disiimpianti.it",
    "wof:name":"Disi Impianti Srl",
    "wof:placetype":"venue"
},
  "geometry": {"coordinates":[14.088517,42.562817],"type":"Point"}
}