{
  "type": "Feature",
  "properties": {
    "iso:country":"IT",
    "sg:address":"91100 Trapani",
    "sg:city":"Trapani",
    "sg:classifiers":[
        {
            "category":"Health Services",
            "subcategory":"Health Practitioner",
            "type":"Services"
        }
    ],
    "sg:phone":"+39 0923 872054",
    "sg:postcode":"91100",
    "sg:province":"Trapani",
    "sg:tags":[
        "medici"
    ],
    "wof:name":"Elhamamsy Ahmed",
    "wof:placetype":"venue"
},
  "geometry": {"coordinates":[12.215379,37.388165],"type":"Point"}
}