{
  "type": "Feature",
  "properties": {
    "iso:country":"IT",
    "sg:address":"Via Brandizzo 22; Volpiano",
    "sg:classifiers":[
        {
            "category":"Banks & Credit Unions",
            "subcategory":"Bank",
            "type":"Services"
        }
    ],
    "sg:phone":"+39 011 988 1275",
    "wof:name":"Banca Di Roma",
    "wof:placetype":"venue"
},
  "geometry": {"coordinates":[7.781486,45.200363],"type":"Point"}
}