{
  "type": "Feature",
  "properties": {
    "iso:country":"IT",
    "sg:address":"Via G. Mazzini 19 25020 Flero",
    "sg:city":"Flero",
    "sg:classifiers":[
        {
            "category":"Communications",
            "subcategory":"Radio Station",
            "type":"Services"
        }
    ],
    "sg:phone":"+39 030 276 1599",
    "sg:postcode":"25020",
    "sg:province":"Brescia",
    "sg:tags":[
        "link",
        "system"
    ],
    "sg:website":"www.suono.com",
    "wof:name":"Suono Telecom Srl",
    "wof:placetype":"venue"
},
  "geometry": {"coordinates":[10.171635,45.459766],"type":"Point"}
}