{
  "type": "Feature",
  "properties": {
    "addr:full":"Via Savigliano 5 12030 Lagnasco Lagnasco Cuneo 12030",
    "addr:housenumber":"5",
    "addr:postcode":"12030;12030",
    "addr:street":"Via Savigliano",
    "iso:country":"IT",
    "sg:address":"Via Savigliano 5 12030 Lagnasco",
    "sg:city":"Lagnasco",
    "sg:orig_category":"Apples, Fresh",
    "sg:phone":"+39 0175 72124",
    "sg:postcode":"12030",
    "sg:province":"Cuneo",
    "wof:name":"Sacchetto C. Scarl",
    "wof:placetype":"venue"
},
  "geometry": {"coordinates":[7.561391,44.627663],"type":"Point"}
}