{
  "type": "Feature",
  "properties": {
    "iso:country":"IT",
    "sg:address":"3, Via Togliatti 41030 Bomporto",
    "sg:city":"Bomporto",
    "sg:classifiers":[
        {
            "category":"Food & Beverages",
            "subcategory":"Dairy",
            "type":"Retail Goods"
        }
    ],
    "sg:phone":"+39 39059909814",
    "sg:postcode":"41030",
    "sg:province":"Modena",
    "sg:tags":[
        "product"
    ],
    "wof:name":"La Fonte (s.r.l.)",
    "wof:placetype":"venue"
},
  "geometry": {"coordinates":[10.99596,44.725353],"type":"Point"}
}