{
  "type": "Feature",
  "properties": {
    "iso:country":"IT",
    "sg:address":"20129 Milano",
    "sg:city":"Milano",
    "sg:orig_category":"Forniture Per Agricoltura E Zootecnia",
    "sg:phone":"+39 02 2940 0977",
    "sg:postcode":"20129",
    "sg:province":"Milano",
    "wof:name":"Euromet Srl",
    "wof:placetype":"venue"
},
  "geometry": {"coordinates":[9.2147407532,45.4771347046],"type":"Point"}
}