{
  "type": "Feature",
  "properties": {
    "iso:country":"IT",
    "sg:address":"17, Via Confienza 27030 Palestro",
    "sg:city":"Confienza",
    "sg:classifiers":[
        {
            "category":"Professional",
            "subcategory":"Engineering",
            "type":"Services"
        }
    ],
    "sg:phone":"+39 0384 680970",
    "sg:postcode":"27030",
    "sg:province":"Pavia",
    "sg:tags":[
        "machine",
        "-",
        "mechanical"
    ],
    "wof:name":"Officina Meccanica C.m. Di Case' Mariolino",
    "wof:placetype":"venue"
},
  "geometry": {"coordinates":[8.535599,45.306595],"type":"Point"}
}