{
  "type": "Feature",
  "properties": {
    "addr:full":"45 Via Del Monte Guidubaldo, 00197 Roma Roma Roma 00197",
    "addr:postcode":"00197;00197",
    "addr:street":"Via Del Monte Guidubaldo",
    "iso:country":"IT",
    "sg:address":"45 Via Del Monte Guidubaldo, 00197 Roma",
    "sg:city":"Roma",
    "sg:classifiers":[
        {
            "category":"Banks & Credit Unions",
            "subcategory":"Financial Services",
            "type":"Services"
        }
    ],
    "sg:phone":"+39 390 680 9741",
    "sg:postcode":"00197",
    "sg:province":"Roma",
    "sg:tags":[
        "banking",
        "finance",
        "insurance"
    ],
    "wof:name":"Gan Italia Spa",
    "wof:placetype":"venue"
},
  "geometry": {"coordinates":[12.4823246002,41.8954658508],"type":"Point"}
}