{
  "type": "Feature",
  "properties": {
    "iso:country":"IT",
    "sg:address":"9, Localita' Steccaia Canonica 53037 San Gimignano",
    "sg:city":"San Gimignano",
    "sg:classifiers":[
        {
            "category":"Personal",
            "subcategory":"Shoe Repair & Shine",
            "type":"Services"
        }
    ],
    "sg:phone":"+39 0577 944884",
    "sg:postcode":"53037",
    "sg:province":"Siena",
    "sg:tags":[
        "leather"
    ],
    "wof:name":"G.l.p. Srl",
    "wof:placetype":"venue"
},
  "geometry": {"coordinates":[11.330514,43.318661],"type":"Point"}
}