{
  "type": "Feature",
  "properties": {
    "iso:country":"IT",
    "sg:address":"06132 Perugia",
    "sg:city":"Perugia",
    "sg:orig_category":"Fiere, Mostre E Saloni - Allestimento E Servizi",
    "sg:phone":"+39 075 527 9235",
    "sg:postcode":"06132",
    "sg:province":"Perugia",
    "sg:website":"http://www.totemgroup.net",
    "wof:name":"Totem Srl",
    "wof:placetype":"venue"
},
  "geometry": {"coordinates":[12.3387727737,43.0741615295],"type":"Point"}
}