{
  "type": "Feature",
  "properties": {
    "iso:country":"IT",
    "sg:address":"20122 Milano",
    "sg:city":"Milano",
    "sg:orig_category":"Banche E Servizi Finanziari",
    "sg:phone":"+39 02 771171",
    "sg:postcode":"20122",
    "sg:province":"Milano",
    "wof:name":"F G Spa Finanziaria Generale",
    "wof:placetype":"venue"
},
  "geometry": {"coordinates":[9.19824,45.466328],"type":"Point"}
}