{
  "type": "Feature",
  "properties": {
    "addr:full":"35020 Albignasego Albignasego Padova 35020",
    "addr:postcode":"35020;35020",
    "iso:country":"IT",
    "sg:address":"35020 Albignasego",
    "sg:city":"Albignasego",
    "sg:orig_category":"Forniture Per Edilizia E Lavori Pubblici",
    "sg:phone":"+39 049 882 8828",
    "sg:postcode":"35020",
    "sg:province":"Padova",
    "wof:name":"Cassini Fabio Rappresentanze Edili",
    "wof:placetype":"venue"
},
  "geometry": {"coordinates":[11.8533773422,45.3775482178],"type":"Point"}
}