{
  "type": "Feature",
  "properties": {
    "iso:country":"IT",
    "sg:address":"Via S. Vitale 33-z.i. Canaletti 40054 Budrio",
    "sg:city":"Budrio",
    "sg:classifiers":[
        {
            "category":"Manufacturing",
            "subcategory":"Tools & Machinery",
            "type":"Manufacturing & Wholesale Goods"
        }
    ],
    "sg:phone":"+39 051 802437",
    "sg:postcode":"40054",
    "sg:province":"Bologna",
    "sg:tags":[
        "steel",
        "marker",
        "industry",
        "making"
    ],
    "sg:website":"www.berma.com",
    "wof:name":"Berma Macchine Snc",
    "wof:placetype":"venue"
},
  "geometry": {"coordinates":[11.588166,44.494022],"type":"Point"}
}