{
  "type": "Feature",
  "properties": {
    "addr:full":"25033 Cologne Cologne Brescia 25033",
    "addr:postcode":"25033;25033",
    "iso:country":"IT",
    "sg:address":"25033 Cologne",
    "sg:city":"Cologne",
    "sg:orig_category":"Forniture Per Abbigliamento E Pelletterie",
    "sg:phone":"+39 030 705 0464",
    "sg:postcode":"25033",
    "sg:province":"Brescia",
    "wof:name":"Salp 2 S.r.l.",
    "wof:placetype":"venue"
},
  "geometry": {"coordinates":[10.2089424133,45.525592804],"type":"Point"}
}