{
  "type": "Feature",
  "properties": {
    "iso:country":"IT",
    "sg:address":"24030 Valbrembo",
    "sg:city":"Valbrembo",
    "sg:orig_category":"Lavorazioni Meccaniche E Servizi",
    "sg:phone":"+39 035 527729",
    "sg:postcode":"24030",
    "sg:province":"Bergamo",
    "wof:name":"C.m.s. Snc Di Siboldi Maurizio",
    "wof:placetype":"venue"
},
  "geometry": {"coordinates":[9.617256,45.697262],"type":"Point"}
}