{
  "type": "Feature",
  "properties": {
    "iso:country":"IT",
    "sg:address":"29010 Rottofreno",
    "sg:city":"Rottofreno",
    "sg:classifiers":[
        {
            "category":"Manufacturing",
            "subcategory":"Tools & Machinery",
            "type":"Manufacturing & Wholesale Goods"
        }
    ],
    "sg:phone":"+39 0523 780210",
    "sg:postcode":"29010",
    "sg:province":"Piacenza",
    "sg:tags":[
        "leather",
        "equipment",
        "goods",
        "clothing"
    ],
    "wof:name":"Price Srl",
    "wof:placetype":"venue"
},
  "geometry": {"coordinates":[9.548926,45.058445],"type":"Point"}
}