{
  "type": "Feature",
  "properties": {
    "addr:full":"74, Via Trieste 34170 Gorizia Gorizia Gorizia 34170",
    "addr:postcode":"34170;34170",
    "addr:street":"Via Trieste",
    "iso:country":"IT",
    "sg:address":"74, Via Trieste 34170 Gorizia",
    "sg:city":"Gorizia",
    "sg:classifiers":[
        {
            "category":"Manufacturing",
            "subcategory":"Lumber",
            "type":"Manufacturing & Wholesale Goods"
        }
    ],
    "sg:phone":"+39 39048120661",
    "sg:postcode":"34170",
    "sg:province":"Gorizia",
    "sg:tags":[
        "wood"
    ],
    "wof:name":"S.i.l.e.s. S.r.l",
    "wof:placetype":"venue"
},
  "geometry": {"coordinates":[13.612975,45.927006],"type":"Point"}
}