{
  "type": "Feature",
  "properties": {
    "iso:country":"IT",
    "sg:address":"60131 Ancona",
    "sg:city":"Ancona",
    "sg:orig_category":"Macchine Utensili E Impianti",
    "sg:phone":"+39 071 286 6845",
    "sg:postcode":"60131",
    "sg:province":"Ancona",
    "wof:name":"Pesaresi Renato",
    "wof:placetype":"venue"
},
  "geometry": {"coordinates":[13.51249,43.572762],"type":"Point"}
}