{
  "type": "Feature",
  "properties": {
    "addr:full":"43100 Parma Parma Parma 43100",
    "addr:postcode":"43100;43100",
    "iso:country":"IT",
    "sg:address":"43100 Parma",
    "sg:city":"Parma",
    "sg:orig_category":"Pompe",
    "sg:phone":"+39 0521 274911",
    "sg:postcode":"43100",
    "sg:province":"Parma",
    "sg:website":"http://www.robuschi.it",
    "wof:name":"Robuschi & C. Spa",
    "wof:placetype":"venue"
},
  "geometry": {"coordinates":[10.3310394287,44.814163208],"type":"Point"}
}