{
  "type": "Feature",
  "properties": {
    "iso:country":"IT",
    "sg:address":"41043 Formigine",
    "sg:city":"Formigine",
    "sg:classifiers":[
        {
            "category":"Personal",
            "subcategory":"Nail Salon",
            "type":"Services"
        }
    ],
    "sg:phone":"+39 059 571011",
    "sg:postcode":"41043",
    "sg:province":"Modena",
    "sg:tags":[
        "scale"
    ],
    "wof:name":"B.c.s. Snc",
    "wof:placetype":"venue"
},
  "geometry": {"coordinates":[10.935554,44.554535],"type":"Point"}
}