{
  "type": "Feature",
  "properties": {
    "iso:country":"IT",
    "sg:address":"25031 Capriolo",
    "sg:city":"Capriolo",
    "sg:orig_category":"Tessuti E Stoffe. Filati E Materie Prime Tessili",
    "sg:phone":"+39 030 736386",
    "sg:postcode":"25031",
    "sg:province":"Brescia",
    "wof:name":"Filature Niggeler E Kupfer (s.p.a.)",
    "wof:placetype":"venue"
},
  "geometry": {"coordinates":[9.93292,45.644623],"type":"Point"}
}