{
  "type": "Feature",
  "properties": {
    "addr:full":"Localita' Venella 52044 Cortona Cortona Arezzo 52044",
    "addr:postcode":"52044;52044",
    "addr:street":"Localita ' Venella",
    "iso:country":"IT",
    "sg:address":"Localita' Venella 52044 Cortona",
    "sg:city":"Cortona",
    "sg:classifiers":[
        {
            "category":"Wholesale",
            "subcategory":"Medical Equipment & Supplies",
            "type":"Manufacturing & Wholesale Goods"
        }
    ],
    "sg:phone":"+39 39057567172",
    "sg:postcode":"52044",
    "sg:province":"Arezzo",
    "sg:tags":[
        "-",
        "health",
        "instrument"
    ],
    "wof:name":"Esafarma (s.a.s.)",
    "wof:placetype":"venue"
},
  "geometry": {"coordinates":[11.863062,43.471203],"type":"Point"}
}