{
  "type": "Feature",
  "properties": {
    "iso:country":"IT",
    "sg:address":"94015 Piazza Armerina",
    "sg:city":"Piazza Armerina",
    "sg:orig_category":"Disinfezione, Disinfestazione E Derattizzazione",
    "sg:phone":"+39 0935 686029",
    "sg:postcode":"94015",
    "sg:province":"Enna",
    "wof:name":"Datola Filippo",
    "wof:placetype":"venue"
},
  "geometry": {"coordinates":[14.355916,37.372974],"type":"Point"}
}