{
  "type": "Feature",
  "properties": {
    "iso:country":"IT",
    "sg:address":"177, Via Spilimbergo 33034 Fagagna",
    "sg:city":"Fagagna",
    "sg:classifiers":[
        {
            "category":"Autos & Motor Vehicles",
            "subcategory":"Automobile Sales",
            "type":"Retail Goods"
        }
    ],
    "sg:phone":"+39 0432 810441",
    "sg:postcode":"33034",
    "sg:province":"Udine",
    "sg:tags":[
        "motor-cars"
    ],
    "wof:name":"Kappa S.r.l.",
    "wof:placetype":"venue"
},
  "geometry": {"coordinates":[13.1558666229,46.0871696472],"type":"Point"}
}