{
  "type": "Feature",
  "properties": {
    "addr:full":"1, Localita' Casone 58020 Scarlino Scarlino Grosseto 58020",
    "addr:postcode":"58020;58020",
    "addr:street":"Localita ' Casone",
    "iso:country":"IT",
    "sg:address":"1, Localita' Casone 58020 Scarlino",
    "sg:city":"Scarlino",
    "sg:classifiers":[
        {
            "category":"Wholesale",
            "subcategory":"Drugs",
            "type":"Manufacturing & Wholesale Goods"
        }
    ],
    "sg:phone":"+39 39056671111",
    "sg:postcode":"58020",
    "sg:province":"Grosseto",
    "sg:tags":[
        "chemical",
        "pharmaceutical"
    ],
    "wof:name":"Tioxide Europe Srl",
    "wof:placetype":"venue"
},
  "geometry": {"coordinates":[11.112782,42.762859],"type":"Point"}
}