{
  "type": "Feature",
  "properties": {
    "iso:country":"IT",
    "sg:address":"47023 Cesena",
    "sg:city":"Cesena",
    "sg:orig_category":"Spedizioni Internazionali",
    "sg:phone":"+39 0547 318400",
    "sg:postcode":"47023",
    "sg:province":"Forl\u00ec-Cesena",
    "wof:name":"Casa Di Spedizioni L'autofrigo Srl",
    "wof:placetype":"venue"
},
  "geometry": {"coordinates":[12.214767,44.185745],"type":"Point"}
}