{
  "type": "Feature",
  "properties": {
    "iso:country":"IT",
    "sg:address":"51017 Pescia",
    "sg:city":"Pescia",
    "sg:orig_category":"Attrezzature E Forniture Per Officine Riparazione E Servizi Ausiliari",
    "sg:phone":"+39 0572 444577",
    "sg:postcode":"51017",
    "sg:province":"Pistoia",
    "wof:name":"Car Auto Snc Di Pellegrini Paolo E Raspabene Rolando",
    "wof:placetype":"venue"
},
  "geometry": {"coordinates":[10.678802,43.880054],"type":"Point"}
}