{
  "type": "Feature",
  "properties": {
    "iso:country":"IT",
    "sg:address":"5, Via Grandi 40013 Castel Maggiore",
    "sg:city":"Castel Maggiore",
    "sg:classifiers":[
        {
            "category":"Utilities",
            "subcategory":"Electric",
            "type":"Services"
        }
    ],
    "sg:phone":"+39 39051715758",
    "sg:postcode":"40013",
    "sg:province":"Bologna",
    "sg:tags":[
        "component",
        "electronic"
    ],
    "wof:name":"Selcom Elettronica (s.r.l.)",
    "wof:placetype":"venue"
},
  "geometry": {"coordinates":[11.371689,44.560692],"type":"Point"}
}