{
  "type": "Feature",
  "properties": {
    "iso:country":"IT",
    "sg:address":"63013 Grottammare",
    "sg:city":"Grottammare",
    "sg:orig_category":"Macchine, Impianti Ed Attrezzature Per Agricoltura E Zootecnia. Forniture Per Agricoltura E Zootecnia",
    "sg:phone":"+39 0735 632254",
    "sg:postcode":"63013",
    "sg:province":"Ascoli Piceno",
    "wof:name":"Agricola Salvan Di Merli Luigi E Bruni & C. Sas",
    "wof:placetype":"venue"
},
  "geometry": {"coordinates":[13.859494,42.980572],"type":"Point"}
}