{
  "type": "Feature",
  "properties": {
    "iso:country":"IT",
    "sg:address":"00185 Roma",
    "sg:city":"Roma",
    "sg:orig_category":"Prodotti Chimici Secondari. Prodotti Cosmetici E Da Toeletta",
    "sg:phone":"+39 06 474 4698",
    "sg:postcode":"00185",
    "sg:province":"Roma",
    "wof:name":"Manin Snc",
    "wof:placetype":"venue"
},
  "geometry": {"coordinates":[12.4989519119,41.8987159729],"type":"Point"}
}