{
  "type": "Feature",
  "properties": {
    "iso:country":"IT",
    "sg:address":"86, Via Aria Libera 25047 Darfo Boario Terme",
    "sg:city":"Darfo",
    "sg:classifiers":[
        {
            "category":"Parking",
            "subcategory":"Lot",
            "type":"Transportation"
        }
    ],
    "sg:phone":"+39 036 453 0061",
    "sg:postcode":"25047",
    "sg:province":"Brescia",
    "sg:tags":[
        "transport",
        "road"
    ],
    "wof:name":"Burlotti Spedizioni (s.p.a.)",
    "wof:placetype":"venue"
},
  "geometry": {"coordinates":[10.168413,45.877789],"type":"Point"}
}