{
  "type": "Feature",
  "properties": {
    "iso:country":"IT",
    "sg:address":"80144 Napoli",
    "sg:city":"Napoli",
    "sg:classifiers":[
        {
            "category":"Personal",
            "subcategory":"Nail Salon",
            "type":"Services"
        }
    ],
    "sg:phone":"+39 081 544 1821",
    "sg:postcode":"80144",
    "sg:province":"Napoli",
    "sg:tags":[
        "scale"
    ],
    "wof:name":"Gamma Scale",
    "wof:placetype":"venue"
},
  "geometry": {"coordinates":[14.280296,40.883812],"type":"Point"}
}