{
  "type": "Feature",
  "properties": {
    "iso:country":"IT",
    "sg:address":"10151 Torino",
    "sg:city":"Torino",
    "sg:orig_category":"Petroli, Gas E Combustibili",
    "sg:phone":"+39 011 455 3792",
    "sg:postcode":"10151",
    "sg:province":"Torino",
    "sg:website":"http://www.tecnicoedilizia.it",
    "wof:name":"Tecni.co Edilizia Srl",
    "wof:placetype":"venue"
},
  "geometry": {"coordinates":[7.6492066383,45.110622406],"type":"Point"}
}