{
  "type": "Feature",
  "properties": {
    "iso:country":"IT",
    "sg:address":"20090 Buccinasco",
    "sg:city":"Buccinasco",
    "sg:orig_category":"Apparecchiature Ed Attrezzature Meccaniche",
    "sg:phone":"+39 02 4884 4648",
    "sg:postcode":"20090",
    "sg:province":"Milano",
    "wof:name":"Lubrimpianti S.n.c. Di Genova Rosario & C.",
    "wof:placetype":"venue"
},
  "geometry": {"coordinates":[9.112329,45.421242],"type":"Point"}
}