{
  "type": "Feature",
  "properties": {
    "addr:full":"Via Enrico Fermi, 12/14 25020 Flero Flero Brescia 25020",
    "addr:housenumber":"12 / 14",
    "addr:postcode":"25020;25020",
    "addr:street":"Via Enrico Fermi",
    "iso:country":"IT",
    "sg:address":"Via Enrico Fermi, 12/14 25020 Flero",
    "sg:city":"Flero",
    "sg:orig_category":"Foundry Moulding Materials",
    "sg:phone":"+39 030 268 0261",
    "sg:postcode":"25020",
    "sg:province":"Brescia",
    "sg:website":"www.metalleghegroup.com",
    "wof:name":"Metalleghe Spa",
    "wof:placetype":"venue"
},
  "geometry": {"coordinates":[10.1509466171,45.4827156067],"type":"Point"}
}