{
  "type": "Feature",
  "properties": {
    "addr:full":"3/b, Via Brigata Julia 35020 Pernumia Pernumia Padova 35020",
    "addr:housenumber":"3 / b",
    "addr:postcode":"35020;35020",
    "addr:street":"Via Brigata Julia",
    "iso:country":"IT",
    "sg:address":"3/b, Via Brigata Julia 35020 Pernumia",
    "sg:city":"Pernumia",
    "sg:classifiers":[
        {
            "category":"Shopping",
            "subcategory":"Stationery & Office Supplies",
            "type":"Retail Goods"
        }
    ],
    "sg:phone":"+39 0429 778087",
    "sg:postcode":"35020",
    "sg:province":"Padova",
    "sg:tags":[
        "professional"
    ],
    "wof:name":"Uffici E Arredi Di Veronese Silvana & C. S.n.c.",
    "wof:placetype":"venue"
},
  "geometry": {"coordinates":[11.8765888214,45.4095687866],"type":"Point"}
}