{
  "type": "Feature",
  "properties": {
    "addr:full":"37029 San Pietro In Cariano San Pietro in Cariano Verona 37029",
    "addr:housenumber":"37029",
    "addr:postcode":"37029",
    "addr:street":"San",
    "iso:country":"IT",
    "sg:address":"37029 San Pietro In Cariano",
    "sg:city":"San Pietro in Cariano",
    "sg:orig_category":"Carni, Salumi E Pesci",
    "sg:phone":"+39 045 770 2404",
    "sg:postcode":"37029",
    "sg:province":"Verona",
    "wof:name":"Conti Marco & C. S.n.c.",
    "wof:placetype":"venue"
},
  "geometry": {"coordinates":[10.872418,45.494122],"type":"Point"}
}