{
  "type": "Feature",
  "properties": {
    "addr:full":"12100 San Benigno San benigno Cuneo 12100",
    "addr:housenumber":"12100",
    "addr:postcode":"benigno;12100",
    "addr:street":"San;Benigno Cuneo",
    "iso:country":"IT",
    "sg:address":"12100 San Benigno",
    "sg:city":"San benigno",
    "sg:orig_category":"Non-classified Establishments",
    "sg:phone":"+39 0171 682735",
    "sg:postcode":"12100",
    "sg:province":"Cuneo",
    "wof:name":"Vimin - Box (s.r.l.)",
    "wof:placetype":"venue"
},
  "geometry": {"coordinates":[7.532273,44.470875],"type":"Point"}
}