{
  "type": "Feature",
  "properties": {
    "iso:country":"IT",
    "sg:address":"12, Via Sicilia 56035 Lari",
    "sg:city":"Lari",
    "sg:classifiers":[
        {
            "category":"Manufacturing",
            "subcategory":"Rubber & Plastics",
            "type":"Manufacturing & Wholesale Goods"
        }
    ],
    "sg:phone":"+39 0587 617534",
    "sg:postcode":"56035",
    "sg:province":"Pisa",
    "wof:name":"Toscana Cubic Center S.r.l.",
    "wof:placetype":"venue"
},
  "geometry": {"coordinates":[10.607049942,43.6150245667],"type":"Point"}
}