{
  "type": "Feature",
  "properties": {
    "addr:full":"31050 Villorba Treviso 31050",
    "addr:postcode":"31050;31050",
    "iso:country":"IT",
    "sg:address":"31050 Villorba",
    "sg:orig_category":"Macchine Ed Impianti Per Edilizia E Lavori Pubblici. Forniture Per Edilizia E Lavori Pubblici",
    "sg:phone":"+39 0422 910058",
    "sg:postcode":"31050",
    "sg:province":"Treviso",
    "sg:website":"http://www.edicom.it",
    "wof:name":"Edicom Srl",
    "wof:placetype":"venue"
},
  "geometry": {"coordinates":[12.246993,45.733234],"type":"Point"}
}