{
  "type": "Feature",
  "properties": {
    "addr:full":"24020 Gorle Gorle Bergamo 24020",
    "addr:postcode":"24020;24020",
    "iso:country":"IT",
    "sg:address":"24020 Gorle",
    "sg:city":"Gorle",
    "sg:orig_category":"Prodotti Finiti Stampati. Forniture E Prodotti Informatici. Forniture Per Uffici",
    "sg:phone":"+39 035 423 7311",
    "sg:postcode":"24020",
    "sg:province":"Bergamo",
    "sg:website":"http://www.errebi-srl.it",
    "wof:name":"Rotolificio Bergamasco Srl",
    "wof:placetype":"venue"
},
  "geometry": {"coordinates":[9.7145252228,45.6974754333],"type":"Point"}
}