{
  "type": "Feature",
  "properties": {
    "addr:full":"36, Via Pedrada 33074 Fontanafredda Fontanafredda Pordenone 33074",
    "addr:postcode":"33074;33074",
    "addr:street":"Via Pedrada",
    "iso:country":"IT",
    "sg:address":"36, Via Pedrada 33074 Fontanafredda",
    "sg:city":"Fontanafredda",
    "sg:classifiers":[
        {
            "category":"Home & Garden",
            "subcategory":"Home Furnishings",
            "type":"Retail Goods"
        }
    ],
    "sg:phone":"+39 0434 997664",
    "sg:postcode":"33074",
    "sg:province":"Pordenone",
    "sg:tags":[
        "household"
    ],
    "wof:name":"D.s.a. S.p.a.",
    "wof:placetype":"venue"
},
  "geometry": {"coordinates":[12.522274,45.975376],"type":"Point"}
}