{
  "type": "Feature",
  "properties": {
    "addr:full":"32100 Belluno Belluno Belluno 32100",
    "addr:postcode":"32100;32100",
    "iso:country":"IT",
    "sg:address":"32100 Belluno",
    "sg:city":"Belluno",
    "sg:orig_category":"Musica",
    "sg:phone":"+39 0437 944972",
    "sg:postcode":"32100",
    "sg:province":"Belluno",
    "wof:name":"Dolomitica Giochi",
    "wof:placetype":"venue"
},
  "geometry": {"coordinates":[12.2209663391,46.1344451904],"type":"Point"}
}