{
  "type": "Feature",
  "properties": {
    "iso:country":"IT",
    "sg:address":"22070 Casnate Con Bernate",
    "sg:city":"Casnate",
    "sg:orig_category":"Articoli Da Regalo. Regalistica Aziendale",
    "sg:phone":"+39 031 396141",
    "sg:postcode":"22070",
    "sg:province":"Como",
    "wof:name":"Comarco Sas",
    "wof:placetype":"venue"
},
  "geometry": {"coordinates":[9.083675,45.80962],"type":"Point"}
}