{
  "type": "Feature",
  "properties": {
    "addr:full":"17, Via Iv Novembre 28832 Belgirate Belgirate Verbano-Cusio-Ossola 28832",
    "addr:postcode":"28832;28832",
    "addr:street":"Via Iv Novembre",
    "iso:country":"IT",
    "sg:address":"17, Via Iv Novembre 28832 Belgirate",
    "sg:city":"Belgirate",
    "sg:classifiers":[
        {
            "category":"Building & Trades",
            "subcategory":"Construction",
            "type":"Services"
        }
    ],
    "sg:phone":"+39 39032276751",
    "sg:postcode":"28832",
    "sg:province":"Verbano-Cusio-Ossola",
    "sg:tags":[
        "work",
        "public"
    ],
    "wof:name":"Impresa Prini (s.r.l.)",
    "wof:placetype":"venue"
},
  "geometry": {"coordinates":[8.272465,46.139969],"type":"Point"}
}