{
  "type": "Feature",
  "properties": {
    "addr:full":"Ctr Imperatore 87043 Bisignano Bisignano Cosenza 87043",
    "addr:postcode":"87043;87043",
    "iso:country":"IT",
    "sg:address":"Ctr Imperatore 87043 Bisignano",
    "sg:city":"Bisignano",
    "sg:classifiers":[
        {
            "category":"Building & Trades",
            "subcategory":"Plumbing",
            "type":"Services"
        }
    ],
    "sg:phone":"+39 0984 940314",
    "sg:postcode":"87043",
    "sg:province":"Cosenza",
    "sg:tags":[
        "tank"
    ],
    "wof:name":"Dfb Srl",
    "wof:placetype":"venue"
},
  "geometry": {"coordinates":[16.253809,39.298264],"type":"Point"}
}