{
  "type": "Feature",
  "properties": {
    "iso:country":"IT",
    "sg:address":"5, Via Vespucci Amerigo 35020 Albignasego",
    "sg:city":"Albignasego",
    "sg:classifiers":[
        {
            "category":"Shopping",
            "type":"Retail Goods"
        }
    ],
    "sg:phone":"+39 049 881 0611",
    "sg:postcode":"35020",
    "sg:province":"Padova",
    "sg:tags":[
        "finished",
        "-",
        "metallic"
    ],
    "wof:name":"Capica Minuterie S.p.a.",
    "wof:placetype":"venue"
},
  "geometry": {"coordinates":[11.8487815857,45.3708229065],"type":"Point"}
}