{
  "type": "Feature",
  "properties": {
    "addr:full":"Ctr Lenne 74019 Palagiano Palagiano Taranto 74019",
    "addr:postcode":"74019;74019",
    "iso:country":"IT",
    "sg:address":"Ctr Lenne 74019 Palagiano",
    "sg:city":"Palagiano",
    "sg:classifiers":[
        {
            "category":"Food & Beverages",
            "subcategory":"Fruits & Vegetables",
            "type":"Retail Goods"
        }
    ],
    "sg:phone":"+39 099 888 6892",
    "sg:postcode":"74019",
    "sg:province":"Taranto",
    "wof:name":"San Filippo Soc. Coop. Agricola A.r.l.",
    "wof:placetype":"venue"
},
  "geometry": {"coordinates":[17.2400093079,40.4692382812],"type":"Point"}
}