{
  "type": "Feature",
  "properties": {
    "addr:full":"Via Bidino 10 21056 Induno Olona Induno Olona Varese 21056",
    "addr:housenumber":"10",
    "addr:postcode":"21056;21056",
    "addr:street":"Via Bidino",
    "iso:country":"IT",
    "sg:address":"Via Bidino 10 21056 Induno Olona",
    "sg:city":"Induno Olona",
    "sg:classifiers":[
        {
            "category":"Manufacturing",
            "subcategory":"Paper Products",
            "type":"Manufacturing & Wholesale Goods"
        }
    ],
    "sg:phone":"+39 0332 203229",
    "sg:postcode":"21056",
    "sg:province":"Varese",
    "sg:tags":[
        "cardboard",
        "package"
    ],
    "wof:name":"Scatolificio Prealpino Milan Guido S.r.l.",
    "wof:placetype":"venue"
},
  "geometry": {"coordinates":[8.838753,45.839165],"type":"Point"}
}