{
  "type": "Feature",
  "properties": {
    "addr:full":"00194 Roma Roma Roma 00194",
    "addr:postcode":"00194;00194",
    "iso:country":"IT",
    "sg:address":"00194 Roma",
    "sg:city":"Roma",
    "sg:orig_category":"Servizi Editoriali. Pubblicita', Marketing E Comunicazione",
    "sg:phone":"+39 06 332 2721",
    "sg:postcode":"00194",
    "sg:province":"Roma",
    "wof:name":"Kompass Italia Spa",
    "wof:placetype":"venue"
},
  "geometry": {"coordinates":[12.465197,41.936943],"type":"Point"}
}