{
  "type": "Feature",
  "properties": {
    "addr:full":"20099 Sesto San Giovanni Sesto San Giovanni Milano 20099",
    "addr:postcode":"20099;20099",
    "iso:country":"IT",
    "sg:address":"20099 Sesto San Giovanni",
    "sg:city":"Sesto San Giovanni",
    "sg:orig_category":"Apparecchi, Attrezzature E Forniture Per Centri Estetici. Forniture Per Attivita' Commerciali Ed Artigianali",
    "sg:phone":"+39 02 242 4139",
    "sg:postcode":"20099",
    "sg:province":"Milano",
    "wof:name":"Marinor",
    "wof:placetype":"venue"
},
  "geometry": {"coordinates":[9.229769,45.529606],"type":"Point"}
}