{
  "type": "Feature",
  "properties": {
    "addr:full":"73030 Tiggiano Tiggiano Lecce 73030",
    "addr:postcode":"73030;73030",
    "iso:country":"IT",
    "sg:address":"73030 Tiggiano",
    "sg:city":"Tiggiano",
    "sg:orig_category":"Metalli E Leghe",
    "sg:phone":"+39 0833 533287",
    "sg:postcode":"73030",
    "sg:province":"Lecce",
    "wof:name":"Quality Tools Srl",
    "wof:placetype":"venue"
},
  "geometry": {"coordinates":[18.3653335571,39.9068870544],"type":"Point"}
}