{
  "type": "Feature",
  "properties": {
    "iso:country":"IT",
    "sg:address":"22036 Erba",
    "sg:city":"Erba",
    "sg:classifiers":[
        {
            "category":"Health Services",
            "subcategory":"Health Practitioner",
            "type":"Services"
        }
    ],
    "sg:phone":"+39 031 611269",
    "sg:postcode":"22036",
    "sg:province":"Como",
    "sg:tags":[
        "medici"
    ],
    "wof:name":"Patacca Luigi",
    "wof:placetype":"venue"
},
  "geometry": {"coordinates":[9.050951004,45.8255081177],"type":"Point"}
}