{
  "type": "Feature",
  "properties": {
    "iso:country":"IT",
    "sg:address":"90040 Isola Delle Femmine",
    "sg:city":"Isola delle Femmine",
    "sg:orig_category":"Lavorazioni Meccaniche E Servizi",
    "sg:phone":"+39 091 867 1681",
    "sg:postcode":"90040",
    "sg:province":"Palermo",
    "sg:website":"http://www.exit.it/gruppomarino",
    "wof:name":"Officine Antonio Marino Srl",
    "wof:placetype":"venue"
},
  "geometry": {"coordinates":[13.251075,38.190414],"type":"Point"}
}