{
  "type": "Feature",
  "properties": {
    "addr:full":"40018 S.pietro In Casale Bologna 40018",
    "addr:postcode":"40018;40018",
    "addr:street":"In Casale",
    "iso:country":"IT",
    "sg:address":"40018 S.pietro In Casale",
    "sg:orig_category":"Lavorazioni Meccaniche E Servizi",
    "sg:phone":"+39 051 810710",
    "sg:postcode":"40018",
    "sg:province":"Bologna",
    "sg:website":"http://www.oemmegi.it",
    "wof:name":"O.m.g. Snc Di Bruno Orlandini & C.",
    "wof:placetype":"venue"
},
  "geometry": {"coordinates":[11.257648,44.479992],"type":"Point"}
}