{
  "type": "Feature",
  "properties": {
    "iso:country":"IT",
    "sg:address":"Via Clerici 22070 Bulgarograsso",
    "sg:city":"Bulgarograsso",
    "sg:classifiers":[
        {
            "category":"Manufacturing",
            "subcategory":"Metals",
            "type":"Manufacturing & Wholesale Goods"
        }
    ],
    "sg:phone":"+39 39031932282",
    "sg:postcode":"22070",
    "sg:province":"Como",
    "sg:tags":[
        "processing"
    ],
    "wof:name":"G. Dz. (s.r.l.)",
    "wof:placetype":"venue"
},
  "geometry": {"coordinates":[9.0115604401,45.7507591248],"type":"Point"}
}