{
  "type": "Feature",
  "properties": {
    "iso:country":"IT",
    "sg:address":"32010 Pieve D'alpago",
    "sg:orig_category":"Serramenti Ed Infissi. Prodotti Vari In Metallo",
    "sg:phone":"+39 0437 989037",
    "sg:postcode":"32010",
    "sg:province":"Belluno",
    "sg:website":"http://www.nuoviprogetti.net",
    "wof:name":"Nuovi Progetti Srl",
    "wof:placetype":"venue"
},
  "geometry": {"coordinates":[12.324777,46.145302],"type":"Point"}
}