{
  "type": "Feature",
  "properties": {
    "iso:country":"IT",
    "sg:address":"11, Via Campana Dino 59100 Prato",
    "sg:city":"Prato",
    "sg:classifiers":[
        {
            "category":"Shopping",
            "subcategory":"Crafts & Fabrics",
            "type":"Retail Goods"
        }
    ],
    "sg:phone":"+39 0574 692607",
    "sg:postcode":"59100",
    "sg:province":"Prato",
    "wof:name":"Filatura Alma Srl",
    "wof:placetype":"venue"
},
  "geometry": {"coordinates":[11.1125278473,43.9045791626],"type":"Point"}
}