{
  "type": "Feature",
  "properties": {
    "iso:country":"IT",
    "sg:address":"00040 Ariccia",
    "sg:city":"Ariccia",
    "sg:orig_category":"Servizi Ausiliari Dei Mezzi Di Trasporto",
    "sg:phone":"+39 06 934 2458",
    "sg:postcode":"00040",
    "sg:province":"Roma",
    "wof:name":"A.l.i. Di Attenni F.",
    "wof:placetype":"venue"
},
  "geometry": {"coordinates":[12.664095,41.708027],"type":"Point"}
}