{
  "type": "Feature",
  "properties": {
    "iso:country":"IT",
    "sg:address":"59100 Prato",
    "sg:city":"Prato",
    "sg:orig_category":"Tessuti E Stoffe. Forniture Per Attivita' Industriali",
    "sg:phone":"+39 0574 639767",
    "sg:postcode":"59100",
    "sg:province":"Prato",
    "wof:name":"Protech 1 Srl",
    "wof:placetype":"venue"
},
  "geometry": {"coordinates":[11.093808,43.878033],"type":"Point"}
}