{
  "type": "Feature",
  "properties": {
    "iso:country":"IT",
    "sg:address":"00174 Roma",
    "sg:city":"Roma",
    "sg:orig_category":"Servizi E Lavori Per Agricoltura E Zootecnia. Animali Domestici",
    "sg:phone":"+39 06 7154 3167",
    "sg:postcode":"00174",
    "sg:province":"Roma",
    "wof:name":"The Black Cat",
    "wof:placetype":"venue"
},
  "geometry": {"coordinates":[12.563847,41.853081],"type":"Point"}
}