{
  "type": "Feature",
  "properties": {
    "iso:country":"IT",
    "sg:address":"20090 Pantigliate",
    "sg:city":"Pantigliate",
    "sg:orig_category":"Lavorazioni Meccaniche E Servizi",
    "sg:phone":"+39 02 9060 0508",
    "sg:postcode":"20090",
    "sg:province":"Milano",
    "wof:name":"Afis Di Buratta Vittorio",
    "wof:placetype":"venue"
},
  "geometry": {"coordinates":[9.095222,45.4491],"type":"Point"}
}