{
  "type": "Feature",
  "properties": {
    "iso:country":"IT",
    "sg:address":"17031 Albenga",
    "sg:city":"Albenga",
    "sg:orig_category":"Barche, Canotti Pneumatici E Motoscafi - Vendita Al Dettaglio",
    "sg:phone":"+39 0182 65360",
    "sg:postcode":"17031",
    "sg:province":"Savona",
    "wof:name":"Cantieri Navali Vadino Srl",
    "wof:placetype":"venue"
},
  "geometry": {"coordinates":[8.214158,44.038731],"type":"Point"}
}