{
  "type": "Feature",
  "properties": {
    "addr:full":"15, V. Brodolini - Z.i. Pesciola 50051 Castelfiorentino Castelfiorentino Firenze 50051",
    "addr:housenumber":"15",
    "addr:postcode":"50051;50051",
    "addr:street":"V. Brodolini Z.I. Pesciola",
    "iso:country":"IT",
    "sg:address":"15, V. Brodolini - Z.i. Pesciola 50051 Castelfiorentino",
    "sg:city":"Castelfiorentino",
    "sg:classifiers":[
        {
            "category":"Manufacturing",
            "subcategory":"Glass & Minerals",
            "type":"Manufacturing & Wholesale Goods"
        }
    ],
    "sg:phone":"+39 0571 636336",
    "sg:postcode":"50051",
    "sg:province":"Firenze",
    "sg:website":"http://www.paginegialle.it/",
    "wof:name":"V.b. Vetreria Bertolini",
    "wof:placetype":"venue"
},
  "geometry": {"coordinates":[11.256902,43.768734],"type":"Point"}
}