{
  "type": "Feature",
  "properties": {
    "iso:country":"IT",
    "sg:address":"14, Via Londonio Francesco 20154 Milano",
    "sg:city":"Milano",
    "sg:classifiers":[
        {
            "category":"Utilities",
            "subcategory":"Electric",
            "type":"Services"
        }
    ],
    "sg:phone":"+39 390 231 011",
    "sg:postcode":"20154",
    "sg:province":"Milano",
    "sg:tags":[
        "energy"
    ],
    "wof:name":"A. Rettagliata S.p.a.",
    "wof:placetype":"venue"
},
  "geometry": {"coordinates":[9.169875,45.479584],"type":"Point"}
}