{
  "type": "Feature",
  "properties": {
    "addr:full":"22100 Como Como Como 22100",
    "addr:postcode":"22100;22100",
    "iso:country":"IT",
    "sg:address":"22100 Como",
    "sg:city":"Como",
    "sg:orig_category":"Macchine E Forniture Per Ecologia E Smaltimento Rifiuti. Macchine, Strumenti Ed Apparecchi Per Attivita' Industriali",
    "sg:phone":"+39 031 524643",
    "sg:postcode":"22100",
    "sg:province":"Como",
    "sg:website":"http://www.ercosystem.net",
    "wof:name":"Aresta Valter - Erco System",
    "wof:placetype":"venue"
},
  "geometry": {"coordinates":[9.084005,45.786503],"type":"Point"}
}