{
  "type": "Feature",
  "properties": {
    "iso:country":"IT",
    "sg:address":"73, Via Vecchia Madonna Sterpeto 70051 Barletta",
    "sg:city":"Barletta",
    "sg:classifiers":[
        {
            "category":"Personal",
            "subcategory":"Shoe Repair & Shine",
            "type":"Services"
        }
    ],
    "sg:phone":"+39 0883 333949",
    "sg:postcode":"70051",
    "sg:province":"Bari",
    "sg:tags":[
        "leather"
    ],
    "wof:name":"Free Line Srl",
    "wof:placetype":"venue"
},
  "geometry": {"coordinates":[16.304062,41.309566],"type":"Point"}
}