{
  "type": "Feature",
  "properties": {
    "iso:country":"IT",
    "sg:address":"39100 Bolzano",
    "sg:city":"Bolzano",
    "sg:orig_category":"Motori Ed Organi Di Trasmissione",
    "sg:phone":"+39 0471 971545",
    "sg:postcode":"39100",
    "sg:province":"Bolzano/Bozen",
    "wof:name":"De Angeli Ing. Andrea Srl",
    "wof:placetype":"venue"
},
  "geometry": {"coordinates":[11.3041219711,46.4796867371],"type":"Point"}
}