{
  "type": "Feature",
  "properties": {
    "iso:country":"IT",
    "sg:address":"27016 Sant'alessio Con Vialone",
    "sg:orig_category":"Prodotti Di Base E Forniture Per Industria Alimentare E Bevande",
    "sg:phone":"+39 0382 944660",
    "sg:postcode":"27016",
    "sg:province":"Pavia",
    "wof:name":"Giannini Gino",
    "wof:placetype":"venue"
},
  "geometry": {"coordinates":[9.2272033691,45.2234611511],"type":"Point"}
}