{
  "type": "Feature",
  "properties": {
    "iso:country":"IT",
    "sg:address":"Via Volta 4; Varese; 21100",
    "sg:city":"Varese",
    "sg:classifiers":[
        {
            "category":"Banks & Credit Unions",
            "subcategory":"Bank",
            "type":"Services"
        }
    ],
    "sg:phone":"+39 0332 233334",
    "sg:postcode":"21100",
    "sg:province":"Varese",
    "wof:name":"Banca Popolare Di Novara",
    "wof:placetype":"venue"
},
  "geometry": {"coordinates":[8.826748,45.817154],"type":"Point"}
}