{
  "type": "Feature",
  "properties": {
    "addr:full":"00176 Roma Roma Roma 00176",
    "addr:postcode":"00176;00176",
    "iso:country":"IT",
    "sg:address":"00176 Roma",
    "sg:city":"Roma",
    "sg:orig_category":"Panetterie",
    "sg:phone":"+39 06 2430 5155",
    "sg:postcode":"00176",
    "sg:province":"Roma",
    "wof:name":"Panificio Franco Maddaloni",
    "wof:placetype":"venue"
},
  "geometry": {"coordinates":[12.5377817154,41.8779640198],"type":"Point"}
}