{
  "type": "Feature",
  "properties": {
    "iso:country":"IT",
    "sg:address":"42044 Gualtieri",
    "sg:orig_category":"Servizi Per Aziende, Manifestazioni E Supporto Agli Scambi Commerciali",
    "sg:phone":"+39 0522 227045",
    "sg:postcode":"42044",
    "sg:province":"Reggio Nell'Emilia",
    "sg:website":"http://utenti.tripod.it/astro2000service/index.html",
    "wof:name":"Zavatta Service",
    "wof:placetype":"venue"
},
  "geometry": {"coordinates":[10.642037,44.862206],"type":"Point"}
}