{
  "type": "Feature",
  "properties": {
    "iso:country":"IT",
    "sg:address":"10156 Torino",
    "sg:city":"Torino",
    "sg:orig_category":"Cinematografia E Radiotelevisione. Servizi Per Aziende, Manifestazioni E Supporto Agli Scambi Commerciali",
    "sg:phone":"+39 011 223 7247",
    "sg:postcode":"10156",
    "sg:province":"Torino",
    "wof:name":"Media Store Snc",
    "wof:placetype":"venue"
},
  "geometry": {"coordinates":[7.736893,45.135956],"type":"Point"}
}