{
  "type": "Feature",
  "properties": {
    "iso:country":"IT",
    "sg:address":"Via Sangervasio 28 25062 Concesio",
    "sg:city":"Concesio",
    "sg:classifiers":[
        {
            "category":"Professional",
            "subcategory":"Accounting & Tax Preparation",
            "type":"Services"
        }
    ],
    "sg:phone":"+39 030 275 3861",
    "sg:postcode":"25062",
    "sg:province":"Brescia",
    "sg:tags":[
        "additive",
        "baking"
    ],
    "wof:name":"Monteverdi Srl",
    "wof:placetype":"venue"
},
  "geometry": {"coordinates":[10.216644,45.601803],"type":"Point"}
}