{
  "type": "Feature",
  "properties": {
    "iso:country":"IT",
    "sg:address":"55, Viale Trento 36078 Valdagno",
    "sg:city":"Valdagno",
    "sg:classifiers":[
        {
            "category":"Wholesale",
            "subcategory":"Drugs",
            "type":"Manufacturing & Wholesale Goods"
        }
    ],
    "sg:phone":"+39 0445 406216",
    "sg:postcode":"36078",
    "sg:province":"Vicenza",
    "sg:tags":[
        "chemical",
        "pharmaceutical"
    ],
    "wof:name":"Pellizzari (s.r.l.)",
    "wof:placetype":"venue"
},
  "geometry": {"coordinates":[11.301996,45.645744],"type":"Point"}
}