{
  "type": "Feature",
  "properties": {
    "iso:country":"IT",
    "sg:address":"11020 Antey-saint-andre'",
    "sg:orig_category":"Pubblica Amministrazione",
    "sg:phone":"+39 0166 549106",
    "sg:postcode":"11020",
    "sg:province":"Aosta",
    "wof:name":"Comunita' Montana M.cervino-communaute' De Montagne M.cervin",
    "wof:placetype":"venue"
},
  "geometry": {"coordinates":[7.5900182724,45.8076667786],"type":"Point"}
}