{
  "type": "Feature",
  "properties": {
    "iso:country":"IT",
    "sg:address":"137, Via Gaudiello 80023 Caivano",
    "sg:city":"Caivano",
    "sg:classifiers":[
        {
            "category":"Professional",
            "subcategory":"Engineering",
            "type":"Services"
        }
    ],
    "sg:phone":"+39 081 831 4864",
    "sg:postcode":"80023",
    "sg:province":"Napoli",
    "sg:tags":[
        "machine",
        "-",
        "mechanical"
    ],
    "wof:name":"Guida S.r.l.",
    "wof:placetype":"venue"
},
  "geometry": {"coordinates":[14.251636,40.840096],"type":"Point"}
}