{
  "type": "Feature",
  "properties": {
    "iso:country":"IT",
    "sg:address":"56031 Bientina",
    "sg:city":"Bientina",
    "sg:orig_category":"Impiantistica E Prodotti Tecnologici Per Edilizia. Serramenti Ed Infissi",
    "sg:phone":"+39 0587 756602",
    "sg:postcode":"56031",
    "sg:province":"Pisa",
    "sg:website":"http://www.artisan.ven.cc",
    "wof:name":"Artisan Di Dell'antico Iuri",
    "wof:placetype":"venue"
},
  "geometry": {"coordinates":[10.653444,43.721691],"type":"Point"}
}