{
  "type": "Feature",
  "properties": {
    "addr:full":"98060 Falcone Falcone Messina 98060",
    "addr:postcode":"98060;98060",
    "iso:country":"IT",
    "sg:address":"98060 Falcone",
    "sg:city":"Falcone",
    "sg:orig_category":"Metalli E Leghe",
    "sg:phone":"+39 0941 349175",
    "sg:postcode":"98060",
    "sg:province":"Messina",
    "wof:name":"Co.me.co. Snc",
    "wof:placetype":"venue"
},
  "geometry": {"coordinates":[15.1199388504,38.1230964661],"type":"Point"}
}