{
  "type": "Feature",
  "properties": {
    "iso:country":"IT",
    "sg:address":"50067 Rignano Sull'arno",
    "sg:orig_category":"Ristorazione E Locali Pubblici Affini. Ristoranti Ed Esercizi Affini. Servizi Ausiliari Di Ristorazione E Di Intrattenimento",
    "sg:phone":"+39 055 830 5175",
    "sg:postcode":"50067",
    "sg:province":"Firenze",
    "sg:website":"http://www.fattoria-pagnana.it",
    "wof:name":"Fattoria Pagnana Spa",
    "wof:placetype":"venue"
},
  "geometry": {"coordinates":[11.422559,43.7225],"type":"Point"}
}