{
  "type": "Feature",
  "properties": {
    "addr:full":"35010 Carmignano Di Brenta Carmignano di Brenta Padova 35010",
    "addr:postcode":"35010;35010",
    "addr:street":"Di Brenta",
    "iso:country":"IT",
    "sg:address":"35010 Carmignano Di Brenta",
    "sg:city":"Carmignano di Brenta",
    "sg:orig_category":"Macchine, Impianti E Forniture Per Industria Grafica, Cartaria E Cartotecnica",
    "sg:phone":"+39 049 943 0207",
    "sg:postcode":"35010",
    "sg:province":"Padova",
    "wof:name":"Cartiera Di Carmignano (s.p.a.)",
    "wof:placetype":"venue"
},
  "geometry": {"coordinates":[11.711038,45.630974],"type":"Point"}
}