{
  "type": "Feature",
  "properties": {
    "iso:country":"IT",
    "sg:address":"Via Augusto Maderna 9 20030 Seveso",
    "sg:city":"Seveso",
    "sg:classifiers":[
        {
            "category":"Bus Stop",
            "subcategory":"None",
            "type":"Transportation"
        }
    ],
    "sg:phone":"+39 036 250 1654",
    "sg:postcode":"20030",
    "sg:province":"Milano",
    "sg:tags":[
        "period",
        "furniture"
    ],
    "wof:name":"Ditta Elli Francesco E C Snc",
    "wof:placetype":"venue"
},
  "geometry": {"coordinates":[9.1416940689,45.6509513855],"type":"Point"}
}