{
  "type": "Feature",
  "properties": {
    "iso:country":"IT",
    "sg:address":"Via Monte San Michele 5/a 42100 Reggio Emilia",
    "sg:classifiers":[
        {
            "category":"Wholesale",
            "subcategory":"Painting Supplies",
            "type":"Manufacturing & Wholesale Goods"
        }
    ],
    "sg:phone":"+39 0522 455331",
    "sg:postcode":"42100",
    "sg:province":"Reggio Nell'Emilia",
    "sg:tags":[
        "ceramic"
    ],
    "wof:name":"Eurec S.r.l.",
    "wof:placetype":"venue"
},
  "geometry": {"coordinates":[10.640117,44.695782],"type":"Point"}
}