{
  "type": "Feature",
  "properties": {
    "iso:country":"IT",
    "sg:address":"3, Via Cremona 10152 Torino",
    "sg:city":"Torino",
    "sg:classifiers":[
        {
            "category":"Farming",
            "subcategory":"Livestock Farm",
            "type":"Manufacturing & Wholesale Goods"
        }
    ],
    "sg:phone":"+39 39011284842",
    "sg:postcode":"10152",
    "sg:province":"Torino",
    "sg:tags":[
        "agriculture"
    ],
    "wof:name":"Corno",
    "wof:placetype":"venue"
},
  "geometry": {"coordinates":[7.690288,45.085854],"type":"Point"}
}