{
  "type": "Feature",
  "properties": {
    "iso:country":"IT",
    "sg:address":"40, Via S. Anna 80046 San Giorgio A Cremano",
    "sg:city":"San Giorgio a Cremano",
    "sg:classifiers":[
        {
            "category":"Manufacturing",
            "subcategory":"Tools & Machinery",
            "type":"Manufacturing & Wholesale Goods"
        }
    ],
    "sg:phone":"+39 081 607 5078",
    "sg:postcode":"80046",
    "sg:province":"Napoli",
    "sg:tags":[
        "environment",
        "equipment",
        "-"
    ],
    "wof:name":"M.i.t.a. Spa",
    "wof:placetype":"venue"
},
  "geometry": {"coordinates":[14.338503,40.833126],"type":"Point"}
}