{
  "type": "Feature",
  "properties": {
    "addr:full":"22032 Albese Con Cassano Albese con Cassano Como 22032",
    "addr:postcode":"22032;22032",
    "iso:country":"IT",
    "sg:address":"22032 Albese Con Cassano",
    "sg:city":"Albese con Cassano",
    "sg:orig_category":"Marmo, Pietre Ed Affini. Arte Ed Artigianato Artistico",
    "sg:phone":"+39 031 420058",
    "sg:postcode":"22032",
    "sg:province":"Como",
    "wof:name":"Bonfanti Mario",
    "wof:placetype":"venue"
},
  "geometry": {"coordinates":[9.160205,45.79578],"type":"Point"}
}