{
  "type": "Feature",
  "properties": {
    "addr:full":"35010 Limena Limena Padova 35010",
    "addr:postcode":"35010;35010",
    "iso:country":"IT",
    "sg:address":"35010 Limena",
    "sg:city":"Limena",
    "sg:orig_category":"Legno Compensato E Profilati - Produzione E Ingrosso",
    "sg:phone":"+39 049 884 0900",
    "sg:postcode":"35010",
    "sg:province":"Padova",
    "sg:website":"http://www.arcawood.it",
    "wof:name":"Arca Wood Srl",
    "wof:placetype":"venue"
},
  "geometry": {"coordinates":[11.841495,45.472019],"type":"Point"}
}