{
  "type": "Feature",
  "properties": {
    "iso:country":"IT",
    "sg:address":"Via Oliero Di Sotto 36020 Valstagna",
    "sg:city":"Valstagna",
    "sg:classifiers":[
        {
            "category":"Shopping",
            "subcategory":"Computers & Home Electronics",
            "type":"Retail Goods"
        }
    ],
    "sg:phone":"+39 39042498327",
    "sg:postcode":"36020",
    "sg:province":"Vicenza",
    "sg:tags":[
        "electronic",
        "electrical",
        "equipment"
    ],
    "wof:name":"Lametal-like",
    "wof:placetype":"venue"
},
  "geometry": {"coordinates":[11.671425,45.844513],"type":"Point"}
}