{
  "type": "Feature",
  "properties": {
    "addr:full":"31020 San Fior San Fior Treviso 31020",
    "addr:housenumber":"31020;fior",
    "addr:postcode":"fior;31020",
    "addr:street":"San",
    "iso:country":"IT",
    "sg:address":"31020 San Fior",
    "sg:city":"San Fior",
    "sg:orig_category":"Climatizzazione E Condizionamento, Apparecchiature E Servizi",
    "sg:phone":"+39 0438 76111",
    "sg:postcode":"31020",
    "sg:province":"Treviso",
    "sg:website":"http://www.puntoservice.it",
    "wof:name":"Punto Service By Punto Casa Srl",
    "wof:placetype":"venue"
},
  "geometry": {"coordinates":[12.365653,45.924084],"type":"Point"}
}