{
  "type": "Feature",
  "properties": {
    "addr:full":"50013 Campi Bisenzio Campi Bisenzio Firenze 50013",
    "addr:postcode":"50013;50013",
    "addr:street":"Bisenzio",
    "iso:country":"IT",
    "sg:address":"50013 Campi Bisenzio",
    "sg:city":"Campi Bisenzio",
    "sg:classifiers":[
        {
            "category":"Home & Garden",
            "subcategory":"Hardware",
            "type":"Retail Goods"
        }
    ],
    "sg:phone":"+39 055 898 5700",
    "sg:postcode":"50013",
    "sg:province":"Firenze",
    "wof:name":"Bull Vit Srl",
    "wof:placetype":"venue"
},
  "geometry": {"coordinates":[11.127766,43.827488],"type":"Point"}
}