{
  "type": "Feature",
  "properties": {
    "iso:country":"IT",
    "sg:address":"20121 Milano",
    "sg:city":"Milano",
    "sg:orig_category":"Servizi Per Lo Sport E Il Tempo Libero. Associazioni Ed Organismi Di Interesse Pubblico",
    "sg:phone":"+39 02 865666",
    "sg:postcode":"20121",
    "sg:province":"Milano",
    "wof:name":"Federazione Italiana Pesca Sportiva E Attivita' Subacquee",
    "wof:placetype":"venue"
},
  "geometry": {"coordinates":[9.182853,45.472488],"type":"Point"}
}