{
  "type": "Feature",
  "properties": {
    "iso:country":"IT",
    "sg:address":"5, Via C. Allisio 10067 Vigone",
    "sg:city":"Vigone",
    "sg:classifiers":[
        {
            "category":"Utilities",
            "subcategory":"Electric",
            "type":"Services"
        }
    ],
    "sg:phone":"+39 011 980 2365",
    "sg:postcode":"10067",
    "sg:province":"Torino",
    "sg:tags":[
        "component",
        "electronic"
    ],
    "wof:name":"Effegi Elettronica Srl",
    "wof:placetype":"venue"
},
  "geometry": {"coordinates":[7.686619,45.07056],"type":"Point"}
}