{
  "type": "Feature",
  "properties": {
    "addr:full":"29017 Fiorenzuola D'arda Piacenza 29017",
    "addr:postcode":"29017;29017",
    "iso:country":"IT",
    "sg:address":"29017 Fiorenzuola D'arda",
    "sg:orig_category":"Prodotti Di Base E Forniture Per Industria Alimentare E Bevande",
    "sg:phone":"+39 0523 983486",
    "sg:postcode":"29017",
    "sg:province":"Piacenza",
    "wof:name":"Butri Di A. Lambri",
    "wof:placetype":"venue"
},
  "geometry": {"coordinates":[9.9100990295,44.9250717163],"type":"Point"}
}