{
  "type": "Feature",
  "properties": {
    "addr:full":"57126 Livorno Livorno Livorno 57126",
    "addr:postcode":"57126;57126",
    "iso:country":"IT",
    "sg:address":"57126 Livorno",
    "sg:city":"Livorno",
    "sg:orig_category":"Trasporti E Spedizioni Merci",
    "sg:phone":"+39 0586 808362",
    "sg:postcode":"57126",
    "sg:province":"Livorno",
    "wof:name":"M.c.s. Srl Mediterranean Customs Services",
    "wof:placetype":"venue"
},
  "geometry": {"coordinates":[11.723791,40.850327],"type":"Point"}
}