{
  "type": "Feature",
  "properties": {
    "iso:country":"IT",
    "sg:address":"80022 Arzano",
    "sg:city":"Arzano",
    "sg:orig_category":"Forniture Per Abbigliamento E Pelletterie",
    "sg:phone":"+39 081 731 1901",
    "sg:postcode":"80022",
    "sg:province":"Napoli",
    "wof:name":"Piesse Tacchi Srl",
    "wof:placetype":"venue"
},
  "geometry": {"coordinates":[14.2672777176,40.9060020447],"type":"Point"}
}