{
  "type": "Feature",
  "properties": {
    "iso:country":"IT",
    "sg:address":"96018 Pachino",
    "sg:city":"Pachino",
    "sg:orig_category":"Macchine, Impianti Ed Attrezzature Per Agricoltura E Zootecnia",
    "sg:phone":"+39 0931 591416",
    "sg:postcode":"96018",
    "sg:province":"Siracusa",
    "wof:name":"Euroserre S.r.l.",
    "wof:placetype":"venue"
},
  "geometry": {"coordinates":[15.067431,36.705448],"type":"Point"}
}