{
  "type": "Feature",
  "properties": {
    "addr:full":"83, Via Milano 21019 Somma Lombardo Somma Lombardo Varese 21019",
    "addr:postcode":"21019;21019",
    "addr:street":"Via Milano",
    "iso:country":"IT",
    "sg:address":"83, Via Milano 21019 Somma Lombardo",
    "sg:city":"Somma Lombardo",
    "sg:classifiers":[
        {
            "category":"Shopping",
            "type":"Retail Goods"
        }
    ],
    "sg:phone":"+39 0331 256235",
    "sg:postcode":"21019",
    "sg:province":"Varese",
    "sg:tags":[
        "finished",
        "-",
        "metallic"
    ],
    "wof:name":"Sacim (s.r.l.)",
    "wof:placetype":"venue"
},
  "geometry": {"coordinates":[8.7169456482,45.6812782288],"type":"Point"}
}