{
  "type": "Feature",
  "properties": {
    "iso:country":"IT",
    "sg:address":"20099 Sesto San Giovanni",
    "sg:city":"Sesto San Giovanni",
    "sg:orig_category":"Motori Ed Organi Di Trasmissione. Ricambi E Componenti Dei Mezzi Di Trasporto",
    "sg:phone":"+39 02 2626 3488",
    "sg:postcode":"20099",
    "sg:province":"Milano",
    "wof:name":"M.a.g. Sas Di Franco Francia & C.",
    "wof:placetype":"venue"
},
  "geometry": {"coordinates":[9.2217111588,45.5314712524],"type":"Point"}
}