{
  "type": "Feature",
  "properties": {
    "addr:full":"16128 Genova Genova Genova 16128",
    "addr:postcode":"16128;16128",
    "iso:country":"IT",
    "sg:address":"16128 Genova",
    "sg:city":"Genova",
    "sg:orig_category":"Trasporti E Spedizioni Merci",
    "sg:phone":"+39 010 235811",
    "sg:postcode":"16128",
    "sg:province":"Genova",
    "sg:website":"http://www.priano.sis-net.it",
    "wof:name":"Priano Marchelli & C. Srl",
    "wof:placetype":"venue"
},
  "geometry": {"coordinates":[8.926362,44.407154],"type":"Point"}
}