{
  "type": "Feature",
  "properties": {
    "addr:full":"40, Via Dolomiti 63014 Montegranaro Montegranaro Ascoli Piceno 63014",
    "addr:postcode":"63014;63014",
    "addr:street":"Via Dolomiti",
    "iso:country":"IT",
    "sg:address":"40, Via Dolomiti 63014 Montegranaro",
    "sg:city":"Montegranaro",
    "sg:classifiers":[
        {
            "category":"Personal",
            "subcategory":"Shoe Repair & Shine",
            "type":"Services"
        }
    ],
    "sg:phone":"+39 0734 891057",
    "sg:postcode":"63014",
    "sg:province":"Ascoli Piceno",
    "sg:tags":[
        "leather"
    ],
    "wof:name":"Calzaturificio Foreste (s.n.c.)",
    "wof:placetype":"venue"
},
  "geometry": {"coordinates":[13.649199,43.257568],"type":"Point"}
}