{
  "type": "Feature",
  "properties": {
    "iso:country":"IT",
    "sg:address":"20060 Liscate",
    "sg:city":"Liscate",
    "sg:orig_category":"Manufacturers: Prefabbricati",
    "sg:phone":"+39 02 9535 1062",
    "sg:postcode":"20060",
    "sg:province":"Milano",
    "wof:name":"Crespi Spa",
    "wof:placetype":"venue"
},
  "geometry": {"coordinates":[9.395903,45.480293],"type":"Point"}
}