{
  "type": "Feature",
  "properties": {
    "iso:country":"IT",
    "sg:address":"Corso V Colonna 108/a; Marino",
    "sg:classifiers":[
        {
            "category":"Banks & Credit Unions",
            "subcategory":"Bank",
            "type":"Services"
        }
    ],
    "sg:phone":"+39 06 938 7641",
    "wof:name":"Banca Di Roma",
    "wof:placetype":"venue"
},
  "geometry": {"coordinates":[12.666474,41.770306],"type":"Point"}
}