{
  "type": "Feature",
  "properties": {
    "addr:full":"63010 Montefiore Dell'aso Ascoli Piceno 63010",
    "addr:postcode":"63010;63010",
    "iso:country":"IT",
    "sg:address":"63010 Montefiore Dell'aso",
    "sg:orig_category":"Calzature - Produzione E Ingrosso",
    "sg:phone":"+39 0734 938721",
    "sg:postcode":"63010",
    "sg:province":"Ascoli Piceno",
    "wof:name":"Imac Spa",
    "wof:placetype":"venue"
},
  "geometry": {"coordinates":[13.750215,43.049919],"type":"Point"}
}