{
  "type": "Feature",
  "properties": {
    "iso:country":"IT",
    "sg:address":"Via Arrighi Cletto 16 20134 Milano",
    "sg:city":"Milano",
    "sg:classifiers":[
        {
            "category":"Wholesale",
            "subcategory":"Chemicals & Plastics",
            "type":"Manufacturing & Wholesale Goods"
        }
    ],
    "sg:phone":"+39 02 210031",
    "sg:postcode":"20134",
    "sg:province":"Milano",
    "sg:tags":[
        "dyestuff"
    ],
    "sg:website":"www.minerprint.it",
    "wof:name":"Minerva Spa",
    "wof:placetype":"venue"
},
  "geometry": {"coordinates":[9.249035,45.482597],"type":"Point"}
}