{
  "type": "Feature",
  "properties": {
    "iso:country":"IT",
    "sg:address":"57/b, Via Adriatica Nord 66023 Francavilla Al Mare",
    "sg:city":"Francavilla al Mare",
    "sg:classifiers":[
        {
            "category":"Shopping",
            "type":"Retail Goods"
        }
    ],
    "sg:phone":"+39 39085810203",
    "sg:postcode":"66023",
    "sg:province":"Chieti",
    "sg:tags":[
        "finished",
        "-",
        "metallic"
    ],
    "wof:name":"Formetal (s.n.c.)",
    "wof:placetype":"venue"
},
  "geometry": {"coordinates":[14.2635269165,42.4339370728],"type":"Point"}
}