{
  "type": "Feature",
  "properties": {
    "addr:full":"80025 Casandrino Casandrino Napoli 80025",
    "addr:postcode":"80025;80025",
    "iso:country":"IT",
    "sg:address":"80025 Casandrino",
    "sg:city":"Casandrino",
    "sg:orig_category":"Forniture Per Attivita' Industriali",
    "sg:phone":"+39 081 505 5498",
    "sg:postcode":"80025",
    "sg:province":"Napoli",
    "wof:name":"Pennellificio Tecopennelli S.n.c.",
    "wof:placetype":"venue"
},
  "geometry": {"coordinates":[14.2454957962,40.933303833],"type":"Point"}
}