{
  "type": "Feature",
  "properties": {
    "addr:full":"54100 Massa Massa Massa-Carrara 54100",
    "addr:postcode":"54100;54100",
    "iso:country":"IT",
    "sg:address":"54100 Massa",
    "sg:city":"Massa",
    "sg:orig_category":"Pubblica Amministrazione",
    "sg:phone":"+39 0585 259711",
    "sg:postcode":"54100",
    "sg:province":"Massa-Carrara",
    "wof:name":"Comando Provinciale Vigili Del Fuoco Di Massa",
    "wof:placetype":"venue"
},
  "geometry": {"coordinates":[10.0953235626,44.0273857117],"type":"Point"}
}