{
  "type": "Feature",
  "properties": {
    "addr:full":"Via Bessi 15 50041 Calenzano Calenzano Firenze 50041",
    "addr:housenumber":"15",
    "addr:postcode":"50041;50041",
    "addr:street":"Via Bessi",
    "iso:country":"IT",
    "sg:address":"Via Bessi 15 50041 Calenzano",
    "sg:city":"Calenzano",
    "sg:classifiers":[
        {
            "category":"Building & Trades",
            "subcategory":"Locksmith",
            "type":"Services"
        }
    ],
    "sg:phone":"+39 055 882 5444",
    "sg:postcode":"50041",
    "sg:province":"Firenze",
    "sg:tags":[
        "machine",
        "accessory"
    ],
    "sg:website":"www.rototype.com",
    "wof:name":"Rototype Spa",
    "wof:placetype":"venue"
},
  "geometry": {"coordinates":[11.179752,43.860928],"type":"Point"}
}