{
  "type": "Feature",
  "properties": {
    "iso:country":"IT",
    "sg:address":"30175 Marghera",
    "sg:city":"Marghera",
    "sg:classifiers":[
        {
            "category":"Health Services",
            "subcategory":"Health Practitioner",
            "type":"Services"
        }
    ],
    "sg:phone":"+39 041 929434",
    "sg:postcode":"30175",
    "sg:province":"Venezia",
    "sg:tags":[
        "medici"
    ],
    "wof:name":"Tressich Emilio",
    "wof:placetype":"venue"
},
  "geometry": {"coordinates":[12.2227468491,45.4736633301],"type":"Point"}
}