{
  "type": "Feature",
  "properties": {
    "iso:country":"IT",
    "sg:address":"00046 Grottaferrata",
    "sg:city":"Grottaferrata",
    "sg:orig_category":"Tempo Libero - Articoli E Forniture. Accessori Dei Mezzi Di Trasporto",
    "sg:phone":"+39 06 941 1733",
    "sg:postcode":"00046",
    "sg:province":"Roma",
    "wof:name":"Francioni Laura",
    "wof:placetype":"venue"
},
  "geometry": {"coordinates":[12.683228,41.779896],"type":"Point"}
}