{
  "type": "Feature",
  "properties": {
    "addr:full":"10151 Torino Torino Torino 10151",
    "addr:housenumber":"10151",
    "addr:postcode":"10151",
    "iso:country":"IT",
    "sg:address":"10151 Torino",
    "sg:city":"Torino",
    "sg:orig_category":"Motori Ed Organi Di Trasmissione",
    "sg:phone":"+39 011 739 5187",
    "sg:postcode":"10151",
    "sg:province":"Torino",
    "wof:name":"Benetti Elettronica Di Potenza Sas Di Benatti Angelo E Carlo & C.",
    "wof:placetype":"venue"
},
  "geometry": {"coordinates":[7.66755867,45.1048774719],"type":"Point"}
}