{
  "type": "Feature",
  "properties": {
    "addr:full":"21, Viale Europa 24040 Bottanuco Bottanuco Bergamo 24040",
    "addr:housenumber":"21",
    "addr:postcode":"24040;24040",
    "addr:street":"Viale Europa",
    "iso:country":"IT",
    "sg:address":"21, Viale Europa 24040 Bottanuco",
    "sg:city":"Bottanuco",
    "sg:classifiers":[
        {
            "category":"Shopping",
            "type":"Retail Goods"
        }
    ],
    "sg:phone":"+39 39035906022",
    "sg:postcode":"24040",
    "sg:province":"Bergamo",
    "sg:tags":[
        "finished",
        "-",
        "metallic"
    ],
    "wof:name":"Sistema Lamiere (s.r.l.)",
    "wof:placetype":"venue"
},
  "geometry": {"coordinates":[9.5172395706,45.6393280029],"type":"Point"}
}