{
  "type": "Feature",
  "properties": {
    "addr:full":"66020 San Giovanni Teatino Sambuceto Chieti 66020",
    "addr:housenumber":"66020",
    "addr:postcode":"66020",
    "iso:country":"IT",
    "sg:address":"66020 San Giovanni Teatino",
    "sg:city":"Sambuceto",
    "sg:orig_category":"Motori Ed Organi Di Trasmissione",
    "sg:phone":"+39 085 446 2696",
    "sg:postcode":"66020",
    "sg:province":"Chieti",
    "sg:website":"http://www.gruppofit.it",
    "wof:name":"Contasta Componenti Srl",
    "wof:placetype":"venue"
},
  "geometry": {"coordinates":[14.1715755463,42.4160842896],"type":"Point"}
}