{
  "type": "Feature",
  "properties": {
    "iso:country":"IT",
    "sg:address":"Viale Lombardia 107; Rozzano; 20089",
    "sg:city":"Rozzano",
    "sg:classifiers":[
        {
            "category":"Banks & Credit Unions",
            "subcategory":"Bank",
            "type":"Services"
        }
    ],
    "sg:phone":"+39 02 8920 0282",
    "sg:postcode":"20089",
    "sg:province":"Milano",
    "wof:name":"Credito Italiano Spa",
    "wof:placetype":"venue"
},
  "geometry": {"coordinates":[9.151848,45.385067],"type":"Point"}
}