{
  "type": "Feature",
  "properties": {
    "iso:country":"IT",
    "sg:address":"46, V. Delle Brigole 23877 Paderno D'adda",
    "sg:classifiers":[
        {
            "category":"Shopping",
            "subcategory":"Clothing, Apparel, & Fashions",
            "type":"Retail Goods"
        }
    ],
    "sg:phone":"+39 039 928 1268",
    "sg:postcode":"23877",
    "sg:province":"Lecco",
    "sg:tags":[
        "clothes"
    ],
    "sg:website":"http://www.paginegialle.it/contel",
    "wof:name":"Contel Srl",
    "wof:placetype":"venue"
},
  "geometry": {"coordinates":[9.434854,45.678871],"type":"Point"}
}