{
  "type": "Feature",
  "properties": {
    "iso:country":"IT",
    "sg:address":"19, Via Don Minzoni 20020 Misinto",
    "sg:city":"Misinto",
    "sg:classifiers":[
        {
            "category":"Professional",
            "subcategory":"Engineering",
            "type":"Services"
        }
    ],
    "sg:phone":"+39 02 9672 0633",
    "sg:postcode":"20020",
    "sg:province":"Milano",
    "sg:tags":[
        "machine",
        "-",
        "mechanical"
    ],
    "wof:name":"Gbs International Srl",
    "wof:placetype":"venue"
},
  "geometry": {"coordinates":[9.103235,45.655884],"type":"Point"}
}