{
  "type": "Feature",
  "properties": {
    "iso:country":"IT",
    "sg:address":"Corso Garibaldi 321 13045 Gattinara",
    "sg:city":"Gattinara",
    "sg:classifiers":[
        {
            "category":"Home & Garden",
            "subcategory":"Building Materials",
            "type":"Retail Goods"
        }
    ],
    "sg:phone":"+39 0163 89336",
    "sg:postcode":"13045",
    "sg:province":"Vercelli",
    "sg:tags":[
        "brick",
        "fire-proof"
    ],
    "wof:name":"Sanac Spa",
    "wof:placetype":"venue"
},
  "geometry": {"coordinates":[8.4263935089,45.3210601807],"type":"Point"}
}