{
  "type": "Feature",
  "properties": {
    "iso:country":"IT",
    "sg:address":"Via Aretina 403d 50136 Firenze",
    "sg:city":"Firenze",
    "sg:orig_category":"Ladies' Shoes",
    "sg:phone":"+39 055 690013",
    "sg:postcode":"50136",
    "sg:province":"Firenze",
    "wof:name":"Calzaturificio Dino Buccioni S.n.c.",
    "wof:placetype":"venue"
},
  "geometry": {"coordinates":[11.307672,43.766937],"type":"Point"}
}