{
  "type": "Feature",
  "properties": {
    "addr:full":"Zona Industriale Villa Musone 62019 Recanati Musone Macerata 62019",
    "addr:postcode":"62019;62019",
    "addr:street":"Zona Industriale;Musone",
    "iso:country":"IT",
    "sg:address":"Zona Industriale Villa Musone 62019 Recanati",
    "sg:city":"Musone",
    "sg:classifiers":[
        {
            "category":"Manufacturing",
            "subcategory":"Metals",
            "type":"Manufacturing & Wholesale Goods"
        }
    ],
    "sg:phone":"+39 071 750 1018",
    "sg:postcode":"62019",
    "sg:province":"Macerata",
    "sg:tags":[
        "processing"
    ],
    "sg:website":"http://www.gimaspa.com:ws_end: :mark:ws:http://www.paginegialle.it/gimaspa-mc",
    "wof:name":"Gima Spa",
    "wof:placetype":"venue"
},
  "geometry": {"coordinates":[13.4562616348,43.3007469177],"type":"Point"}
}