{
  "type": "Feature",
  "properties": {
    "addr:full":"70021 Acquaviva Delle Fonti Acquaviva delle Fonti Bari 70021",
    "addr:postcode":"70021;70021",
    "iso:country":"IT",
    "sg:address":"70021 Acquaviva Delle Fonti",
    "sg:city":"Acquaviva delle Fonti",
    "sg:orig_category":"Calzature - Produzione E Ingrosso",
    "sg:phone":"+39 080 767819",
    "sg:postcode":"70021",
    "sg:province":"Bari",
    "wof:name":"Casucci Calzature Srl",
    "wof:placetype":"venue"
},
  "geometry": {"coordinates":[16.902403,40.834782],"type":"Point"}
}