{
  "type": "Feature",
  "properties": {
    "iso:country":"IT",
    "sg:address":"Via Dei Banchi 5, 50123 Florence, Fi",
    "sg:classifiers":[
        {
            "category":"Banks & Credit Unions",
            "subcategory":"Bank",
            "type":"Services"
        }
    ],
    "sg:postcode":"50123",
    "sg:province":"Firenze",
    "wof:name":"Banca Federico Del Vecchio",
    "wof:placetype":"venue"
},
  "geometry": {"coordinates":[11.25199,43.773403],"type":"Point"}
}