{
  "type": "Feature",
  "properties": {
    "iso:country":"IT",
    "sg:address":"36100 Vicenza",
    "sg:city":"Vicenza",
    "sg:orig_category":"Macchine E Forniture Per Industria Orafa E Per Orologeria",
    "sg:phone":"+39 0444 566211",
    "sg:postcode":"36100",
    "sg:province":"Vicenza",
    "sg:website":"http://www.fov.it",
    "wof:name":"Fov Sas",
    "wof:placetype":"venue"
},
  "geometry": {"coordinates":[11.368759,45.742668],"type":"Point"}
}