{
  "type": "Feature",
  "properties": {
    "iso:country":"IT",
    "sg:address":"Via Panagulis 47100 Forli'",
    "sg:classifiers":[
        {
            "category":"Manufacturing",
            "subcategory":"Metals",
            "type":"Manufacturing & Wholesale Goods"
        }
    ],
    "sg:phone":"+39 39054385170",
    "sg:postcode":"47100",
    "sg:province":"Forl\u00ec-Cesena",
    "sg:tags":[
        "processing"
    ],
    "wof:name":"Meccanica Orlandi S.r.l.",
    "wof:placetype":"venue"
},
  "geometry": {"coordinates":[11.9804611206,43.9947662354],"type":"Point"}
}