{
  "type": "Feature",
  "properties": {
    "iso:country":"IT",
    "sg:address":"Via Carlo Piscane 23; Centola; 84064",
    "sg:classifiers":[
        {
            "category":"Banks & Credit Unions",
            "subcategory":"Bank",
            "type":"Services"
        }
    ],
    "sg:phone":"+39 0974 938389",
    "wof:name":"Banco Di Napoli Spa",
    "wof:placetype":"venue"
},
  "geometry": {"coordinates":[15.28665,40.037003],"type":"Point"}
}