{
  "type": "Feature",
  "properties": {
    "addr:full":"5, Via Cagnaghe 25065 Lumezzane Lumezzane Brescia 25065",
    "addr:postcode":"25065;25065",
    "addr:street":"Via Cagnaghe",
    "iso:country":"IT",
    "sg:address":"5, Via Cagnaghe 25065 Lumezzane",
    "sg:city":"Lumezzane",
    "sg:classifiers":[
        {
            "category":"Professional",
            "subcategory":"Engineering",
            "type":"Services"
        }
    ],
    "sg:phone":"+39 030 897 0851",
    "sg:postcode":"25065",
    "sg:province":"Brescia",
    "sg:tags":[
        "machine",
        "-",
        "mechanical"
    ],
    "wof:name":"Mori Domenico",
    "wof:placetype":"venue"
},
  "geometry": {"coordinates":[10.219884,45.66486],"type":"Point"}
}