{
  "type": "Feature",
  "properties": {
    "addr:full":"09047 Selargius Selargius Cagliari 09047",
    "addr:postcode":"09047;09047",
    "iso:country":"IT",
    "sg:address":"09047 Selargius",
    "sg:city":"Selargius",
    "sg:orig_category":"Termotecnica E Riscaldamento, Apparecchiature E Servizi",
    "sg:phone":"+39 070 846462",
    "sg:postcode":"09047",
    "sg:province":"Cagliari",
    "sg:website":"http://www.tecnoinstal.com",
    "wof:name":"Tecno Instal",
    "wof:placetype":"venue"
},
  "geometry": {"coordinates":[9.167456,39.253719],"type":"Point"}
}