{
  "type": "Feature",
  "properties": {
    "addr:full":"Via Trieste 603 21042 Caronno Pertusella Caronno Pertusella Varese 21042",
    "addr:housenumber":"603",
    "addr:postcode":"21042;pertusella;21042",
    "addr:street":"Via Trieste;Pertusella",
    "iso:country":"IT",
    "sg:address":"Via Trieste 603 21042 Caronno Pertusella",
    "sg:city":"Caronno Pertusella",
    "sg:classifiers":[
        {
            "category":"Food & Beverages",
            "subcategory":"Meat & Fish",
            "type":"Retail Goods"
        }
    ],
    "sg:phone":"+39 02 9645 0470",
    "sg:postcode":"21042",
    "sg:province":"Varese",
    "sg:tags":[
        "domestic",
        "animal"
    ],
    "sg:website":"www.allpett.it",
    "wof:name":"All Pet Srl",
    "wof:placetype":"venue"
},
  "geometry": {"coordinates":[9.059312,45.589329],"type":"Point"}
}