{
  "type": "Feature",
  "properties": {
    "iso:country":"IT",
    "sg:address":"70044 Polignano A Mare",
    "sg:city":"Polignano a Mare",
    "sg:orig_category":"Ricevimenti E Banchetti - Sale E Servizi",
    "sg:phone":"+39 080 424 1560",
    "sg:postcode":"70044",
    "sg:province":"Bari",
    "sg:website":"http://www.tuccino.it",
    "wof:name":"Ristorante 'da Tuccino'",
    "wof:placetype":"venue"
},
  "geometry": {"coordinates":[17.183903,40.966835],"type":"Point"}
}