{
  "type": "Feature",
  "properties": {
    "iso:country":"IT",
    "sg:address":"10, Via Saluzzo 12030 Lagnasco",
    "sg:city":"Lagnasco",
    "sg:classifiers":[
        {
            "category":"Manufacturing",
            "subcategory":"Lumber",
            "type":"Manufacturing & Wholesale Goods"
        }
    ],
    "sg:phone":"+39 39017572403",
    "sg:postcode":"12030",
    "sg:province":"Cuneo",
    "sg:tags":[
        "wood"
    ],
    "wof:name":"Parizia S.r.l.",
    "wof:placetype":"venue"
},
  "geometry": {"coordinates":[7.55456,44.626076],"type":"Point"}
}