{
  "type": "Feature",
  "properties": {
    "iso:country":"IT",
    "sg:address":"25080 Calvagese Riviera",
    "sg:orig_category":"Agenzie Di Spettacolo E Di Animazione",
    "sg:phone":"+39 030 680 0081",
    "sg:postcode":"25080",
    "sg:province":"Brescia",
    "wof:name":"Pedeni Angela - Ars Nova Gi.pi. Spettacoli",
    "wof:placetype":"venue"
},
  "geometry": {"coordinates":[10.562986,45.560436],"type":"Point"}
}