{
  "type": "Feature",
  "properties": {
    "addr:full":"45, Via Napoli 20030 Bovisio Masciago Bovisio Milano 20030",
    "addr:postcode":"20030;20030",
    "addr:street":"Via Napoli",
    "iso:country":"IT",
    "sg:address":"45, Via Napoli 20030 Bovisio Masciago",
    "sg:city":"Bovisio",
    "sg:classifiers":[
        {
            "category":"Professional",
            "subcategory":"Engineering",
            "type":"Services"
        }
    ],
    "sg:phone":"+39 036 259 0736",
    "sg:postcode":"20030",
    "sg:province":"Milano",
    "sg:tags":[
        "machine",
        "-",
        "mechanical"
    ],
    "wof:name":"Arivent Italiana (s.r.l.)",
    "wof:placetype":"venue"
},
  "geometry": {"coordinates":[9.161393,45.614433],"type":"Point"}
}