{
  "type": "Feature",
  "properties": {
    "addr:full":"Centro Comm Le Etrusco; Chiusi; 53043 Chiusi Siena 53043",
    "addr:postcode":"53043;53043",
    "iso:country":"IT",
    "sg:address":"Centro Comm Le Etrusco; Chiusi; 53043",
    "sg:city":"Chiusi",
    "sg:classifiers":[
        {
            "category":"Banks & Credit Unions",
            "subcategory":"Bank",
            "type":"Services"
        }
    ],
    "sg:phone":"+39 0578 274412",
    "sg:postcode":"53043",
    "sg:province":"Siena",
    "wof:name":"Banco Di Napoli Spa",
    "wof:placetype":"venue"
},
  "geometry": {"coordinates":[11.923396,43.023342],"type":"Point"}
}