{
  "type": "Feature",
  "properties": {
    "addr:full":"26041 Casalmaggiore Casalmaggiore Cremona 26041",
    "addr:housenumber":"26041",
    "addr:postcode":"26041",
    "addr:street":"Casalmaggiore Casalmaggiore Cremona",
    "iso:country":"IT",
    "sg:address":"26041 Casalmaggiore",
    "sg:city":"Casalmaggiore",
    "sg:orig_category":"Non-classified Establishments",
    "sg:phone":"+39 0375 283011",
    "sg:postcode":"26041",
    "sg:province":"Cremona",
    "wof:name":"Industrie Emiliana Parati S.p.a.",
    "wof:placetype":"venue"
},
  "geometry": {"coordinates":[10.440308,44.999828],"type":"Point"}
}