{
  "type": "Feature",
  "properties": {
    "addr:full":"51030 Serravalle Pistoiese Serravalle Pistoiese Pistoia 51030",
    "addr:postcode":"51030;51030",
    "iso:country":"IT",
    "sg:address":"51030 Serravalle Pistoiese",
    "sg:city":"Serravalle Pistoiese",
    "sg:classifiers":[
        {
            "category":"Organizations",
            "subcategory":"Professional Association",
            "type":"Services"
        }
    ],
    "sg:phone":"+39 0573 929362",
    "sg:postcode":"51030",
    "sg:province":"Pistoia",
    "sg:tags":[
        "activities",
        "commercial",
        "non-professional",
        "equipment",
        "engineering",
        "electrical",
        "artisan",
        "supplies",
        "accommodation",
        "furnishing"
    ],
    "sg:website":"http://www.linearoll.it",
    "wof:name":"Linea Roll Srl",
    "wof:placetype":"venue"
},
  "geometry": {"coordinates":[10.8343095779,43.9061470032],"type":"Point"}
}