{
  "type": "Feature",
  "properties": {
    "iso:country":"IT",
    "sg:address":"122, Via Delle Regioni 50052 Certaldo",
    "sg:city":"Certaldo",
    "sg:classifiers":[
        {
            "category":"Parking",
            "subcategory":"Lot",
            "type":"Transportation"
        }
    ],
    "sg:phone":"+39 0571 668977",
    "sg:postcode":"50052",
    "sg:province":"Firenze",
    "sg:tags":[
        "transport",
        "road"
    ],
    "wof:name":"Autotrasporti Signorini Gigi (s.r.l.)",
    "wof:placetype":"venue"
},
  "geometry": {"coordinates":[11.021688,43.569851],"type":"Point"}
}