{
  "type": "Feature",
  "properties": {
    "addr:full":"00175 Roma Roma Roma 00175",
    "addr:postcode":"00175;00175",
    "iso:country":"IT",
    "sg:address":"00175 Roma",
    "sg:city":"Roma",
    "sg:orig_category":"Sport - Articoli E Forniture",
    "sg:phone":"+39 06 7151 0778",
    "sg:postcode":"00175",
    "sg:province":"Roma",
    "wof:name":"Tutto Per La Pesca Di Mancini Stefano Maria",
    "wof:placetype":"venue"
},
  "geometry": {"coordinates":[12.565207,41.85833],"type":"Point"}
}