{
  "type": "Feature",
  "properties": {
    "addr:full":"40, Via Pier Fortunato Calvi 20020 Magnago Magnago Milano 20020",
    "addr:postcode":"20020;20020",
    "addr:street":"Via Pier Fortunato Calvi",
    "iso:country":"IT",
    "sg:address":"40, Via Pier Fortunato Calvi 20020 Magnago",
    "sg:city":"Magnago",
    "sg:classifiers":[
        {
            "category":"Shopping",
            "type":"Retail Goods"
        }
    ],
    "sg:phone":"+39 0331 307015",
    "sg:postcode":"20020",
    "sg:province":"Milano",
    "sg:tags":[
        "finished",
        "-",
        "metallic"
    ],
    "wof:name":"Aquatechnik S.p.a.",
    "wof:placetype":"venue"
},
  "geometry": {"coordinates":[8.8087520599,45.5932655334],"type":"Point"}
}