{
  "type": "Feature",
  "properties": {
    "addr:full":"20124 Milano Milano Milano 20124",
    "addr:postcode":"20124;20124",
    "iso:country":"IT",
    "sg:address":"20124 Milano",
    "sg:city":"Milano",
    "sg:orig_category":"Scuole Private - Licei",
    "sg:phone":"+39 02 659 9933",
    "sg:postcode":"20124",
    "sg:province":"Milano",
    "sg:website":"http://www.cscartesio.it",
    "wof:name":"Centro Studi Cartesio Srl",
    "wof:placetype":"venue"
},
  "geometry": {"coordinates":[9.200895,45.476658],"type":"Point"}
}