{
  "type": "Feature",
  "properties": {
    "iso:country":"IT",
    "sg:address":"13874 Mottalciata",
    "sg:city":"Mottalciata",
    "sg:orig_category":"Servizi E Lavori Per Agricoltura E Zootecnia",
    "sg:phone":"+39 0161 857708",
    "sg:postcode":"13874",
    "sg:province":"Biella",
    "wof:name":"Bellan Emanuele",
    "wof:placetype":"venue"
},
  "geometry": {"coordinates":[8.207815,45.506111],"type":"Point"}
}