{
  "type": "Feature",
  "properties": {
    "addr:full":"Via Roma 1; Pomezia; 00040 Pomezia Roma 00040",
    "addr:housenumber":"1",
    "addr:postcode":"00040;roma 00040",
    "addr:street":"Via Roma",
    "iso:country":"IT",
    "sg:address":"Via Roma 1; Pomezia; 00040",
    "sg:city":"Pomezia",
    "sg:classifiers":[
        {
            "category":"Banks & Credit Unions",
            "subcategory":"Bank",
            "type":"Services"
        }
    ],
    "sg:phone":"+39 06 910 6556",
    "sg:postcode":"00040",
    "sg:province":"Roma",
    "wof:name":"Istituto Bancario San Paolo, Di Torino Spa",
    "wof:placetype":"venue"
},
  "geometry": {"coordinates":[12.50169,41.670498],"type":"Point"}
}