{
  "type": "Feature",
  "properties": {
    "iso:country":"IT",
    "sg:address":"09048 Sinnai",
    "sg:city":"Sinnai",
    "sg:orig_category":"Forniture Per Edilizia E Lavori Pubblici. Arredi Ed Attrezzature Per Attivita' Commerciali Ed Artigianali. Forniture Per Attivita' Industriali",
    "sg:phone":"+39 070 767074",
    "sg:postcode":"09048",
    "sg:province":"Cagliari",
    "wof:name":"Mascia F.lli Di Fabrizio Mascia",
    "wof:placetype":"venue"
},
  "geometry": {"coordinates":[9.3007364273,39.3415031433],"type":"Point"}
}