{
  "type": "Feature",
  "properties": {
    "iso:country":"IT",
    "sg:address":"Via S. Predengo 29 26022 Castelverde",
    "sg:city":"Castelverde",
    "sg:classifiers":[
        {
            "category":"Real Estate",
            "subcategory":"Real Estate Operator",
            "type":"Services"
        }
    ],
    "sg:phone":"+39 0372 471579",
    "sg:postcode":"26022",
    "sg:province":"Cremona",
    "sg:tags":[
        "instrument",
        "throughput",
        "measurement"
    ],
    "sg:website":"www.tecnosite.it",
    "wof:name":"I.n.t. Srl",
    "wof:placetype":"venue"
},
  "geometry": {"coordinates":[9.973519,45.168041],"type":"Point"}
}