{
  "type": "Feature",
  "properties": {
    "addr:full":"41053 Maranello Maranello Modena 41053",
    "addr:postcode":"41053;41053",
    "iso:country":"IT",
    "sg:address":"41053 Maranello",
    "sg:city":"Maranello",
    "sg:orig_category":"Accessori Moda D'abbigliamento. Forniture Per Abbigliamento E Pelletterie",
    "sg:phone":"+39 0536 941219",
    "sg:postcode":"41053",
    "sg:province":"Modena",
    "sg:website":"http://www.nuovamancos.com",
    "wof:name":"Ricamificio Nuova Mancos Di Costetti Carlo & C. Snc",
    "wof:placetype":"venue"
},
  "geometry": {"coordinates":[10.868578,44.52433],"type":"Point"}
}