{
  "type": "Feature",
  "properties": {
    "iso:country":"IT",
    "sg:address":"30030 Favaro Veneto",
    "sg:orig_category":"Forniture Per Abbigliamento E Pelletterie",
    "sg:phone":"+39 041 633211",
    "sg:postcode":"30030",
    "sg:province":"Venezia",
    "wof:name":"Volpato Caterina",
    "wof:placetype":"venue"
},
  "geometry": {"coordinates":[12.2743444443,45.5138626099],"type":"Point"}
}