{
  "type": "Feature",
  "properties": {
    "iso:country":"IT",
    "sg:address":"20019 Settimo Milanese",
    "sg:city":"Settimo Milanese",
    "sg:orig_category":"Prodotti Alimentari",
    "sg:phone":"+39 02 328 8098",
    "sg:postcode":"20019",
    "sg:province":"Milano",
    "wof:name":"L'albero Della Frutta Di Giola & C. Sas",
    "wof:placetype":"venue"
},
  "geometry": {"coordinates":[9.0539598465,45.4820594788],"type":"Point"}
}