{
  "type": "Feature",
  "properties": {
    "iso:country":"IT",
    "sg:address":"80124 Napoli",
    "sg:city":"Napoli",
    "sg:orig_category":"Armadi Guardaroba",
    "sg:phone":"+39 081 762 6269",
    "sg:postcode":"80124",
    "sg:province":"Napoli",
    "wof:name":"Aesse Design",
    "wof:placetype":"venue"
},
  "geometry": {"coordinates":[14.178563,40.809799],"type":"Point"}
}