{
  "type": "Feature",
  "properties": {
    "iso:country":"IT",
    "sg:address":"7, Via Guglielmo Marconi 35010 Villanova Di Camposampiero",
    "sg:city":"Villanova",
    "sg:classifiers":[
        {
            "category":"Autos & Motor Vehicles",
            "subcategory":"Automobile Sales",
            "type":"Retail Goods"
        }
    ],
    "sg:phone":"+39 049 922 1792",
    "sg:postcode":"35010",
    "sg:province":"Padova",
    "sg:tags":[
        "equipment",
        "transport"
    ],
    "wof:name":"Frames And Services Snc Di Mattia Antonello E Marangon Luca",
    "wof:placetype":"venue"
},
  "geometry": {"coordinates":[11.910565,45.463024],"type":"Point"}
}