{
  "type": "Feature",
  "properties": {
    "iso:country":"IT",
    "sg:address":"48018 Faenza",
    "sg:city":"Faenza",
    "sg:orig_category":"Lavorazioni Meccaniche E Servizi. Riparazione Dei Mezzi Di Trasporto",
    "sg:phone":"+39 0546 620988",
    "sg:postcode":"48018",
    "sg:province":"Ravenna",
    "sg:website":"http://www.sora.it",
    "wof:name":"S.o.r.a. Societ\u00c0 Officine Rettifiche E Affini",
    "wof:placetype":"venue"
},
  "geometry": {"coordinates":[11.861426,44.303825],"type":"Point"}
}