{
  "type": "Feature",
  "properties": {
    "iso:country":"IT",
    "sg:address":"27018 Vidigulfo",
    "sg:city":"Vidigulfo",
    "sg:orig_category":"Serramenti Ed Infissi. Arte Ed Artigianato Artistico. Shopping",
    "sg:phone":"+39 0382 619087",
    "sg:postcode":"27018",
    "sg:province":"Pavia",
    "wof:name":"Lanfranchi Snc Di Lanfranchi Domenico & C.",
    "wof:placetype":"venue"
},
  "geometry": {"coordinates":[9.237024,45.288292],"type":"Point"}
}