{
  "type": "Feature",
  "properties": {
    "iso:country":"IT",
    "sg:address":"72020 Erchie",
    "sg:city":"Erchie",
    "sg:classifiers":[
        {
            "category":"Health Services",
            "subcategory":"Health Practitioner",
            "type":"Services"
        }
    ],
    "sg:phone":"+39 0831 763214",
    "sg:postcode":"72020",
    "sg:province":"Brindisi",
    "sg:tags":[
        "medici"
    ],
    "wof:name":"Valente Lucia",
    "wof:placetype":"venue"
},
  "geometry": {"coordinates":[17.7354450226,40.434589386],"type":"Point"}
}