{
  "type": "Feature",
  "properties": {
    "iso:country":"IT",
    "sg:address":"00061 Anguillara Sabazia",
    "sg:city":"Anguillara Sabazia",
    "sg:orig_category":"Apparecchiature Elettroniche",
    "sg:phone":"+39 06 9990 0874",
    "sg:postcode":"00061",
    "sg:province":"Roma",
    "wof:name":"Ital Gm Srl",
    "wof:placetype":"venue"
},
  "geometry": {"coordinates":[12.283628,42.082283],"type":"Point"}
}