{
  "type": "Feature",
  "properties": {
    "iso:country":"IT",
    "sg:address":"19, Via Trento 20090 Cesano Boscone",
    "sg:city":"Cesano Boscone",
    "sg:classifiers":[
        {
            "category":"Wholesale",
            "subcategory":"Drugs",
            "type":"Manufacturing & Wholesale Goods"
        }
    ],
    "sg:phone":"+39 02 4860 1278",
    "sg:postcode":"20090",
    "sg:province":"Milano",
    "sg:tags":[
        "chemical",
        "pharmaceutical"
    ],
    "wof:name":"Motip Dupli Italia S.p.a.",
    "wof:placetype":"venue"
},
  "geometry": {"coordinates":[9.084805,45.448112],"type":"Point"}
}