{
  "type": "Feature",
  "properties": {
    "iso:country":"IT",
    "sg:address":"Piazza De Angeli Ernesto 1 20146 Milano",
    "sg:city":"Milano",
    "sg:orig_category":"Hasps And Staples",
    "sg:phone":"+39 02 4800 6893",
    "sg:postcode":"20146",
    "sg:province":"Milano",
    "wof:name":"Clemytex Srl",
    "wof:placetype":"venue"
},
  "geometry": {"coordinates":[9.150578,45.466183],"type":"Point"}
}