{
  "type": "Feature",
  "properties": {
    "addr:full":"46010 Curtatone Curtatone Mantova 46010",
    "addr:postcode":"46010;46010",
    "iso:country":"IT",
    "sg:address":"46010 Curtatone",
    "sg:city":"Curtatone",
    "sg:classifiers":[
        {
            "category":"Farming",
            "subcategory":"Livestock Farm",
            "type":"Manufacturing & Wholesale Goods"
        }
    ],
    "sg:phone":"+39 0376 47512",
    "sg:postcode":"46010",
    "sg:province":"Mantova",
    "sg:tags":[
        "equipment",
        "breeding",
        "agriculture",
        "machinery"
    ],
    "wof:name":"Gemelli Bruno",
    "wof:placetype":"venue"
},
  "geometry": {"coordinates":[10.735107,45.109978],"type":"Point"}
}