{
  "type": "Feature",
  "properties": {
    "addr:full":"20123 Milano Milano Milano 20123",
    "addr:postcode":"20123;20123",
    "iso:country":"IT",
    "sg:address":"20123 Milano",
    "sg:city":"Milano",
    "sg:orig_category":"Imprese Di Costruzioni Civili Ed Industriali",
    "sg:phone":"+39 02 8940 9118",
    "sg:postcode":"20123",
    "sg:province":"Milano",
    "sg:website":"http://www.albiero.net",
    "wof:name":"Albiero Srl",
    "wof:placetype":"venue"
},
  "geometry": {"coordinates":[9.172346,45.456711],"type":"Point"}
}