{
  "type": "Feature",
  "properties": {
    "iso:country":"IT",
    "sg:address":"41019 Soliera",
    "sg:city":"Soliera",
    "sg:orig_category":"Articoli Da Regalo. Forniture Per Attivita' Commerciali Ed Artigianali",
    "sg:phone":"+39 059 859664",
    "sg:postcode":"41019",
    "sg:province":"Modena",
    "wof:name":"Ferrari Stefano E Malagoli Paola E C. Snc",
    "wof:placetype":"venue"
},
  "geometry": {"coordinates":[10.9123,44.726517],"type":"Point"}
}