{
  "type": "Feature",
  "properties": {
    "iso:country":"IT",
    "sg:address":"14019 Villanova D'asti",
    "sg:orig_category":"Alimentari - Produzione E Ingrosso",
    "sg:phone":"+39 011 948917",
    "sg:postcode":"14019",
    "sg:province":"Asti",
    "wof:name":"Trevisan Dolciaria Srl",
    "wof:placetype":"venue"
},
  "geometry": {"coordinates":[7.948398,44.961487],"type":"Point"}
}