{
  "type": "Feature",
  "properties": {
    "addr:full":"4, Via Dei Pioppi 55049 Viareggio Viareggio Lucca 55049",
    "addr:postcode":"55049;55049",
    "addr:street":"Via Dei Pioppi",
    "iso:country":"IT",
    "sg:address":"4, Via Dei Pioppi 55049 Viareggio",
    "sg:city":"Viareggio",
    "sg:classifiers":[
        {
            "category":"Autos & Motor Vehicles",
            "subcategory":"Boat Sales",
            "type":"Retail Goods"
        }
    ],
    "sg:phone":"+39 39058445833",
    "sg:postcode":"55049",
    "sg:province":"Lucca",
    "wof:name":"Cantiere Navale C.t.f. Di Trentacoste E C. Snc",
    "wof:placetype":"venue"
},
  "geometry": {"coordinates":[10.270601,43.872692],"type":"Point"}
}