{
  "type": "Feature",
  "properties": {
    "iso:country":"IT",
    "sg:address":"37069 Villafranca Verona",
    "sg:orig_category":"Analisi Chimiche, Industriali E Merceologiche",
    "sg:phone":"+39 045 860 1040",
    "sg:postcode":"37069",
    "sg:province":"Verona",
    "wof:name":"Chimica Servizi Srl",
    "wof:placetype":"venue"
},
  "geometry": {"coordinates":[10.912833,45.396408],"type":"Point"}
}