{
  "type": "Feature",
  "properties": {
    "iso:country":"IT",
    "sg:address":"35121 Padova",
    "sg:city":"Padova",
    "sg:orig_category":"Servizi E Lavori Per Ecologia E Smaltimento Rifiuti. Arte Ed Artigianato Artistico. Servizi Ausiliari Di Sorveglianza, Manutenzione E Pulizia",
    "sg:phone":"+39 049 658212",
    "sg:postcode":"35121",
    "sg:province":"Padova",
    "wof:name":"Maciste Sgomberi Gian Paolo",
    "wof:placetype":"venue"
},
  "geometry": {"coordinates":[11.115941,45.418343],"type":"Point"}
}