{
  "type": "Feature",
  "properties": {
    "iso:country":"IT",
    "sg:address":"20077 Melegnano",
    "sg:city":"Melegnano",
    "sg:orig_category":"Servizi Editoriali. Servizi Per Aziende, Manifestazioni E Supporto Agli Scambi Commerciali",
    "sg:phone":"+39 02 9823 3100",
    "sg:postcode":"20077",
    "sg:province":"Milano",
    "sg:website":"http://www.club.it/montedit",
    "wof:name":"Montedit Di Montefameglio Antonella",
    "wof:placetype":"venue"
},
  "geometry": {"coordinates":[9.325457,45.35445],"type":"Point"}
}