{
  "type": "Feature",
  "properties": {
    "iso:country":"IT",
    "sg:address":"20019 Settimo Milanese",
    "sg:city":"Settimo Milanese",
    "sg:orig_category":"Servizi E Lavori Per Abbigliamento E Pelletterie",
    "sg:phone":"+39 02 328 1287",
    "sg:postcode":"20019",
    "sg:province":"Milano",
    "wof:name":"Allegri Dante",
    "wof:placetype":"venue"
},
  "geometry": {"coordinates":[9.074924,45.472931],"type":"Point"}
}