{
  "type": "Feature",
  "properties": {
    "addr:full":"04100 Latina Latina Latina 04100",
    "addr:postcode":"04100;04100",
    "iso:country":"IT",
    "sg:address":"04100 Latina",
    "sg:city":"Latina",
    "sg:orig_category":"Tessuti Arredamento, Tende E Tappeti. Forniture Per Edilizia E Lavori Pubblici",
    "sg:phone":"+39 0773 695919",
    "sg:postcode":"04100",
    "sg:province":"Latina",
    "wof:name":"Carabot Lucia Adele",
    "wof:placetype":"venue"
},
  "geometry": {"coordinates":[12.909343,41.455894],"type":"Point"}
}