{
  "type": "Feature",
  "properties": {
    "iso:country":"IT",
    "sg:address":"Piazza Martiri 3; Carpi; 41012",
    "sg:city":"Carpi",
    "sg:classifiers":[
        {
            "category":"Banks & Credit Unions",
            "subcategory":"Bank",
            "type":"Services"
        }
    ],
    "sg:phone":"+39 059 640204",
    "sg:postcode":"41012",
    "sg:province":"Modena",
    "wof:name":"Cassa Risparmio Carpi Spa",
    "wof:placetype":"venue"
},
  "geometry": {"coordinates":[10.884742,44.782543],"type":"Point"}
}