{
  "type": "Feature",
  "properties": {
    "addr:full":"10036 Settimo Torinese Settimo Torinese Torino 10036",
    "addr:postcode":"10036;10036",
    "iso:country":"IT",
    "sg:address":"10036 Settimo Torinese",
    "sg:city":"Settimo Torinese",
    "sg:orig_category":"Cartotecnica E Servizi. Forniture Per Uffici",
    "sg:phone":"+39 011 897 6900",
    "sg:postcode":"10036",
    "sg:province":"Torino",
    "wof:name":"Anna Talarico Snc Di Talarico Anna & C.",
    "wof:placetype":"venue"
},
  "geometry": {"coordinates":[7.779249,45.141235],"type":"Point"}
}