{
  "type": "Feature",
  "properties": {
    "addr:full":"32030 Fonzaso Arten Belluno 32030",
    "addr:postcode":"32030;32030",
    "iso:country":"IT",
    "sg:address":"32030 Fonzaso",
    "sg:city":"Arten",
    "sg:orig_category":"Arredo Cucina Ed Elettrodomestici",
    "sg:phone":"+39 0439 56051",
    "sg:postcode":"32030",
    "sg:province":"Belluno",
    "sg:website":"http://www.francescon.com",
    "wof:name":"Gescu Francescon Di Gesiot Dott. Luciano",
    "wof:placetype":"venue"
},
  "geometry": {"coordinates":[11.835704,45.996994],"type":"Point"}
}