{
  "type": "Feature",
  "properties": {
    "addr:full":"06132 Perugia Perugia Perugia 06132",
    "addr:postcode":"06132;06132",
    "iso:country":"IT",
    "sg:address":"06132 Perugia",
    "sg:city":"Perugia",
    "sg:orig_category":"Case Editrici",
    "sg:phone":"+39 075 527 0295",
    "sg:postcode":"06132",
    "sg:province":"Perugia",
    "wof:name":"Rux E.d.e.l. Sas",
    "wof:placetype":"venue"
},
  "geometry": {"coordinates":[12.347547,43.074627],"type":"Point"}
}