{
  "type": "Feature",
  "properties": {
    "iso:country":"IT",
    "sg:address":"20127 Milano",
    "sg:city":"Milano",
    "sg:orig_category":"Servizi Per Aziende, Manifestazioni E Supporto Agli Scambi Commerciali",
    "sg:phone":"+39 02 2851 0106",
    "sg:postcode":"20127",
    "sg:province":"Milano",
    "wof:name":"Calcaterra Stefania",
    "wof:placetype":"venue"
},
  "geometry": {"coordinates":[9.217155,45.493061],"type":"Point"}
}