{
  "type": "Feature",
  "properties": {
    "addr:full":"35129 Padova Padova Padova 35129",
    "addr:postcode":"35129;35129",
    "iso:country":"IT",
    "sg:address":"35129 Padova",
    "sg:city":"Padova",
    "sg:orig_category":"Articoli Per Imballaggio E Confezionamento",
    "sg:phone":"+39 049 774350",
    "sg:postcode":"35129",
    "sg:province":"Padova",
    "sg:website":"http://www.stefanostefani.com",
    "wof:name":"Stefani Srl",
    "wof:placetype":"venue"
},
  "geometry": {"coordinates":[11.925999,45.426647],"type":"Point"}
}