{
  "type": "Feature",
  "properties": {
    "addr:full":"20058 Villasanta Villasanta Milano 20058",
    "addr:postcode":"20058;20058",
    "iso:country":"IT",
    "sg:address":"20058 Villasanta",
    "sg:city":"Villasanta",
    "sg:orig_category":"Materiali E Componenti Elettrotecnici",
    "sg:phone":"+39 039 205 0300",
    "sg:postcode":"20058",
    "sg:province":"Milano",
    "sg:website":"http://www.saplist.it",
    "wof:name":"Saplist Di Megali Rosa",
    "wof:placetype":"venue"
},
  "geometry": {"coordinates":[9.303258,45.61586],"type":"Point"}
}