{
  "type": "Feature",
  "properties": {
    "addr:full":"5/c, Via Guidizzolo 46040 Cavriana Cavriana Mantova 46040",
    "addr:housenumber":"5 / c",
    "addr:postcode":"46040;46040",
    "addr:street":"Via Guidizzolo",
    "iso:country":"IT",
    "sg:address":"5/c, Via Guidizzolo 46040 Cavriana",
    "sg:city":"Cavriana",
    "sg:classifiers":[
        {
            "category":"Personal",
            "subcategory":"Shoe Repair & Shine",
            "type":"Services"
        }
    ],
    "sg:phone":"+39 0376 815074",
    "sg:postcode":"46040",
    "sg:province":"Mantova",
    "sg:tags":[
        "leather"
    ],
    "wof:name":"Methis Di Magnabosco Oscar E C. Snc",
    "wof:placetype":"venue"
},
  "geometry": {"coordinates":[10.797698,45.160366],"type":"Point"}
}