{
  "type": "Feature",
  "properties": {
    "addr:full":"Largo Caduti Del Lavoro 1/a; Bologna; 40122 Bologna Bologna 40122",
    "addr:housenumber":"1 / a",
    "addr:postcode":"40122;40122",
    "addr:street":"Largo Caduti Del Lavoro",
    "iso:country":"IT",
    "sg:address":"Largo Caduti Del Lavoro 1/a; Bologna; 40122",
    "sg:city":"Bologna",
    "sg:classifiers":[
        {
            "category":"Banks & Credit Unions",
            "subcategory":"Bank",
            "type":"Services"
        }
    ],
    "sg:phone":"+39 051 242912",
    "sg:postcode":"40122",
    "sg:province":"Bologna",
    "wof:name":"Cassa Di Risparmio Di Cesena Spa",
    "wof:placetype":"venue"
},
  "geometry": {"coordinates":[11.338668,44.500122],"type":"Point"}
}