{
  "type": "Feature",
  "properties": {
    "addr:full":"48018 Faenza Faenza Ravenna 48018",
    "addr:postcode":"48018;48018",
    "iso:country":"IT",
    "sg:address":"48018 Faenza",
    "sg:city":"Faenza",
    "sg:orig_category":"Manufacturers: Prefabbricati",
    "sg:phone":"+39 0546 44154",
    "sg:postcode":"48018",
    "sg:province":"Ravenna",
    "sg:website":"http://www.poliflor.net",
    "wof:name":"Poliflor Soc. Coop. Arl",
    "wof:placetype":"venue"
},
  "geometry": {"coordinates":[11.947185,44.322975],"type":"Point"}
}