{
  "type": "Feature",
  "properties": {
    "addr:full":"73040 Collepasso Collepasso Lecce 73040",
    "addr:postcode":"73040;73040",
    "iso:country":"IT",
    "sg:address":"73040 Collepasso",
    "sg:city":"Collepasso",
    "sg:orig_category":"Servizi E Lavori Per Arredamento E Industria Del Legno",
    "sg:phone":"+39 0833 342000",
    "sg:postcode":"73040",
    "sg:province":"Lecce",
    "sg:website":"http://www.latornilegno.com",
    "wof:name":"La Tornilegno Di Schirinzi Giuliano",
    "wof:placetype":"venue"
},
  "geometry": {"coordinates":[18.164852,40.072498],"type":"Point"}
}