{
  "type": "Feature",
  "properties": {
    "iso:country":"IT",
    "sg:address":"Via G. Leopardi 8a 37010 Sandra'",
    "sg:orig_category":"Ladies' Trousers Suits, Suits, Jackets, Skirts, And Trousers",
    "sg:phone":"+39 045 759 6280",
    "sg:postcode":"37010",
    "sg:province":"Verona",
    "wof:name":"Pierr Day S.n.c. Di Paroni Vilma E C.",
    "wof:placetype":"venue"
},
  "geometry": {"coordinates":[10.991748,45.438366],"type":"Point"}
}