{
  "type": "Feature",
  "properties": {
    "addr:full":"41100 Modena Modena Modena 41100",
    "addr:postcode":"41100;41100",
    "iso:country":"IT",
    "sg:address":"41100 Modena",
    "sg:city":"Modena",
    "sg:orig_category":"Prodotti Di Base E Forniture Per Industria Alimentare E Bevande",
    "sg:phone":"+39 059 468452",
    "sg:postcode":"41100",
    "sg:province":"Modena",
    "sg:website":"http://www.gibispa.it",
    "wof:name":"Gi.bi. Spa",
    "wof:placetype":"venue"
},
  "geometry": {"coordinates":[10.9738130569,44.5969047546],"type":"Point"}
}