{
  "type": "Feature",
  "properties": {
    "iso:country":"IT",
    "sg:address":"Galleria De Cristoforis 1, Milan, Mi",
    "sg:classifiers":[
        {
            "category":"Banks & Credit Unions",
            "subcategory":"Bank",
            "type":"Services"
        }
    ],
    "wof:name":"Bipiemme Vita Spa",
    "wof:placetype":"venue"
},
  "geometry": {"coordinates":[9.19481,45.465687],"type":"Point"}
}