{
  "type": "Feature",
  "properties": {
    "iso:country":"IT",
    "sg:address":"50059 Vinci",
    "sg:city":"Vinci",
    "sg:orig_category":"Servizi E Lavori Per Abbigliamento E Pelletterie. Cartotecnica E Servizi. Servizi E Lavori Industria Delle Materie Plastiche",
    "sg:phone":"+39 0571 902695",
    "sg:postcode":"50059",
    "sg:province":"Firenze",
    "wof:name":"Agoda Di Agostelli Auro E Diego Sdf",
    "wof:placetype":"venue"
},
  "geometry": {"coordinates":[10.924196,43.771671],"type":"Point"}
}