{
  "type": "Feature",
  "properties": {
    "iso:country":"IT",
    "sg:address":"25082 Botticino",
    "sg:city":"Botticino",
    "sg:orig_category":"Assemblaggio Conto Terzi",
    "sg:phone":"+39 030 219 0812",
    "sg:postcode":"25082",
    "sg:province":"Brescia",
    "wof:name":"Lonati Snc Di Elio Lonati & C.",
    "wof:placetype":"venue"
},
  "geometry": {"coordinates":[10.310137,45.529755],"type":"Point"}
}