{
  "type": "Feature",
  "properties": {
    "addr:full":"15/e, Via Miglietti Vincenzo Maria 10144 Torino Torino Torino 10144",
    "addr:housenumber":"15 / e",
    "addr:postcode":"10144;10144",
    "addr:street":"Via Miglietti Vincenzo Maria",
    "iso:country":"IT",
    "sg:address":"15/e, Via Miglietti Vincenzo Maria 10144 Torino",
    "sg:city":"Torino",
    "sg:classifiers":[
        {
            "category":"Personal",
            "subcategory":"Shoe Repair & Shine",
            "type":"Services"
        }
    ],
    "sg:phone":"+39 011 473 2941",
    "sg:postcode":"10144",
    "sg:province":"Torino",
    "sg:tags":[
        "leather"
    ],
    "wof:name":"Mafotex (s.r.l.)",
    "wof:placetype":"venue"
},
  "geometry": {"coordinates":[7.669047,45.079247],"type":"Point"}
}