{
  "type": "Feature",
  "properties": {
    "iso:country":"IT",
    "sg:address":"Corso Cavour 114; Dormelletto; 28040",
    "sg:city":"Dormelletto",
    "sg:classifiers":[
        {
            "category":"Banks & Credit Unions",
            "subcategory":"Bank",
            "type":"Services"
        }
    ],
    "sg:phone":"+39 0322 497600",
    "sg:postcode":"28040",
    "sg:province":"Novara",
    "wof:name":"Banca Popolare Di Intra",
    "wof:placetype":"venue"
},
  "geometry": {"coordinates":[8.577671,45.729511],"type":"Point"}
}