{
  "type": "Feature",
  "properties": {
    "iso:country":"IT",
    "sg:address":"06132 San Sisto",
    "sg:orig_category":"Servizi Per Aziende, Manifestazioni E Supporto Agli Scambi Commerciali",
    "sg:phone":"+39 075 529 2077",
    "sg:postcode":"06132",
    "sg:province":"Perugia",
    "wof:name":"Piccini Gianfranco",
    "wof:placetype":"venue"
},
  "geometry": {"coordinates":[12.343537,43.087952],"type":"Point"}
}