{
  "type": "Feature",
  "properties": {
    "iso:country":"IT",
    "sg:address":"28, Galleria Vittorio Veneto 59100 Prato",
    "sg:city":"Prato",
    "sg:classifiers":[
        {
            "category":"Professional",
            "subcategory":"Computer Services",
            "type":"Services"
        }
    ],
    "sg:phone":"+39 0574 442238",
    "sg:postcode":"59100",
    "sg:province":"Prato",
    "sg:tags":[
        "information",
        "technology"
    ],
    "wof:name":"Hypersoft-net S.r.l.",
    "wof:placetype":"venue"
},
  "geometry": {"coordinates":[11.104583,43.877354],"type":"Point"}
}