{
  "type": "Feature",
  "properties": {
    "iso:country":"IT",
    "sg:address":"07022 Berchidda",
    "sg:city":"Berchidda",
    "sg:orig_category":"Legno E Semilavorati",
    "sg:phone":"+39 079 704036",
    "sg:postcode":"07022",
    "sg:province":"Olbia-Tempio",
    "wof:name":"Bottega Del Sughero Di Sebastiano Gaias",
    "wof:placetype":"venue"
},
  "geometry": {"coordinates":[9.278559,40.826839],"type":"Point"}
}