{
  "type": "Feature",
  "properties": {
    "iso:country":"IT",
    "sg:address":"84095 Giffoni Valle Piana",
    "sg:city":"Giffoni Valle Piana",
    "sg:orig_category":"Pubblica Amministrazione",
    "sg:phone":"+39 089 866729",
    "sg:postcode":"84095",
    "sg:province":"Salerno",
    "wof:name":"Comunita' Montana Dei Monti Picentini",
    "wof:placetype":"venue"
},
  "geometry": {"coordinates":[14.9383945465,40.7248725891],"type":"Point"}
}