{
  "type": "Feature",
  "properties": {
    "iso:country":"IT",
    "sg:address":"19124 La Spezia",
    "sg:orig_category":"Banche E Servizi Finanziari. Acqua, Luce, Gas E Societa' Di Esercizio Pubblico",
    "sg:phone":"+39 0187 752173",
    "sg:province":"SP",
    "wof:name":"Cassa Di Risparmio Della Spezia",
    "wof:placetype":"venue"
},
  "geometry": {"coordinates":[9.825048,44.114086],"type":"Point"}
}