{
  "type": "Feature",
  "properties": {
    "iso:country":"IT",
    "sg:address":"44100 Ferrara",
    "sg:city":"Ferrara",
    "sg:orig_category":"Metalli E Leghe",
    "sg:phone":"+39 0532 461486",
    "sg:postcode":"44100",
    "sg:province":"Ferrara",
    "wof:name":"Sidermet Srl",
    "wof:placetype":"venue"
},
  "geometry": {"coordinates":[11.6078643799,44.8809242249],"type":"Point"}
}