{
  "type": "Feature",
  "properties": {
    "iso:country":"IT",
    "sg:address":"80142 Napoli",
    "sg:city":"Napoli",
    "sg:orig_category":"Servizi Al Turismo. Trasporto Pubblico E Privato. Acqua, Luce, Gas E Societa' Di Esercizio Pubblico",
    "sg:phone":"+39 081 227 2111",
    "sg:postcode":"80142",
    "sg:province":"Napoli",
    "wof:name":"Mn Metropolitana Di Napoli",
    "wof:placetype":"venue"
},
  "geometry": {"coordinates":[14.111812,40.875256],"type":"Point"}
}