{
  "type": "Feature",
  "properties": {
    "addr:full":"20122 Milano Milano Milano 20122",
    "addr:postcode":"20122;20122",
    "iso:country":"IT",
    "sg:address":"20122 Milano",
    "sg:city":"Milano",
    "sg:orig_category":"Apparecchiature Ed Attrezzature Meccaniche. Elettronica Industriale, Prodotti E Apparecchiature. Impianti, Attrezzature E Forniture Sanitarie Ed Ospedaliere. Apparecchi, Attrezzature E Forniture Per C",
    "sg:phone":"+39 02 5412 0948",
    "sg:postcode":"20122",
    "sg:province":"Milano",
    "wof:name":"Eufoton S.r.l.",
    "wof:placetype":"venue"
},
  "geometry": {"coordinates":[9.202685,45.454494],"type":"Point"}
}