{
  "type": "Feature",
  "properties": {
    "addr:full":"19124 La Spezia SP",
    "addr:housenumber":"19124",
    "iso:country":"IT",
    "sg:address":"19124 La Spezia",
    "sg:orig_category":"Ospedali E Servizi Sanitari",
    "sg:phone":"+39 0187 733945",
    "sg:province":"SP",
    "wof:name":"Antismoking Center Di Budriesi Maria Letizia",
    "wof:placetype":"venue"
},
  "geometry": {"coordinates":[9.835274,44.111614],"type":"Point"}
}