{
  "type": "Feature",
  "properties": {
    "iso:country":"IT",
    "sg:address":"95125 Catania",
    "sg:city":"Catania",
    "sg:orig_category":"Prodotti Chimici Secondari. Macchine E Forniture Per Ecologia E Smaltimento Rifiuti",
    "sg:phone":"+39 095 223618",
    "sg:postcode":"95125",
    "sg:province":"Catania",
    "sg:website":"http://www.ddtservice.com",
    "wof:name":"Ddt Di Bruno Angela",
    "wof:placetype":"venue"
},
  "geometry": {"coordinates":[15.0840272903,37.5405807495],"type":"Point"}
}