{
  "type": "Feature",
  "properties": {
    "iso:country":"IT",
    "sg:address":"20036 Meda",
    "sg:city":"Meda",
    "sg:orig_category":"Articoli Per Imballaggio E Confezionamento",
    "sg:phone":"+39 036 234 0881",
    "sg:postcode":"20036",
    "sg:province":"Milano",
    "wof:name":"Bellotti E Cavasin",
    "wof:placetype":"venue"
},
  "geometry": {"coordinates":[9.142787,45.660889],"type":"Point"}
}