{
  "type": "Feature",
  "properties": {
    "iso:country":"IT",
    "sg:address":"Viale Della Navigazione Interna 75 35129 Padova",
    "sg:city":"Padova",
    "sg:classifiers":[
        {
            "category":"Sports & Exercise",
            "subcategory":"Playing Field",
            "type":"Entertainment"
        }
    ],
    "sg:phone":"+39 049 808 9033",
    "sg:postcode":"35129",
    "sg:province":"Padova",
    "sg:tags":[
        "athletic",
        "equipment",
        "recreational"
    ],
    "sg:website":"www.rizzato.com",
    "wof:name":"Rizzato Personalsport Srl",
    "wof:placetype":"venue"
},
  "geometry": {"coordinates":[11.934345,45.408543],"type":"Point"}
}