{
  "type": "Feature",
  "properties": {
    "iso:country":"IT",
    "sg:address":"55010 Capannori",
    "sg:city":"Capannori",
    "sg:orig_category":"Calzature, Pelletterie E Pelli. Servizi E Lavori Per Abbigliamento E Pelletterie",
    "sg:phone":"+39 0583 927159",
    "sg:postcode":"55010",
    "sg:province":"Lucca",
    "wof:name":"Mauro Pieraccini",
    "wof:placetype":"venue"
},
  "geometry": {"coordinates":[10.57459,43.88311],"type":"Point"}
}