{
  "type": "Feature",
  "properties": {
    "iso:country":"IT",
    "sg:address":"Molo Trapezio 80121 Salerno",
    "sg:classifiers":[
        {
            "category":"Banks & Credit Unions",
            "subcategory":"Investment Brokerage",
            "type":"Services"
        }
    ],
    "sg:phone":"+39 39089253500",
    "sg:postcode":"80121",
    "sg:province":"Napoli",
    "sg:tags":[
        "-",
        "transport",
        "related"
    ],
    "wof:name":"Salerno Container Terminal Spa",
    "wof:placetype":"venue"
},
  "geometry": {"coordinates":[14.741256,40.674778],"type":"Point"}
}