{
  "type": "Feature",
  "properties": {
    "addr:full":"54, Via Molinello 21048 Solbiate Arno Solbiate Arno Varese 21048",
    "addr:housenumber":"arno",
    "addr:postcode":"21048;21048",
    "addr:street":"Via Molinello",
    "iso:country":"IT",
    "sg:address":"54, Via Molinello 21048 Solbiate Arno",
    "sg:city":"Solbiate Arno",
    "sg:classifiers":[
        {
            "category":"Manufacturing",
            "subcategory":"Metals",
            "type":"Manufacturing & Wholesale Goods"
        }
    ],
    "sg:phone":"+39 0331 985455",
    "sg:postcode":"21048",
    "sg:province":"Varese",
    "sg:tags":[
        "metallurgy",
        "metalworking"
    ],
    "wof:name":"Moldex S.r.l.",
    "wof:placetype":"venue"
},
  "geometry": {"coordinates":[8.8103132248,45.7140693665],"type":"Point"}
}