{
  "type": "Feature",
  "properties": {
    "iso:country":"IT",
    "sg:address":"20091 Bresso",
    "sg:city":"Bresso",
    "sg:orig_category":"Prodotti Di Base E Forniture Per Industria Alimentare E Bevande. Prodotti Chimici Di Base",
    "sg:phone":"+39 02 6650 1970",
    "sg:postcode":"20091",
    "sg:province":"Milano",
    "wof:name":"Select Alimenta (s.r.l.)",
    "wof:placetype":"venue"
},
  "geometry": {"coordinates":[9.1925201416,45.5449409485],"type":"Point"}
}