{
  "type": "Feature",
  "properties": {
    "addr:full":"10098 Rivoli Cascine vica Torino 10098",
    "addr:postcode":"10098;10098",
    "iso:country":"IT",
    "sg:address":"10098 Rivoli",
    "sg:city":"Cascine vica",
    "sg:orig_category":"Valvole E Apparecchiature Di Misura. Forniture Per Attivita' Industriali",
    "sg:phone":"+39 011 957 6353",
    "sg:postcode":"10098",
    "sg:province":"Torino",
    "wof:name":"Chiaperotti Spa",
    "wof:placetype":"venue"
},
  "geometry": {"coordinates":[7.558924,45.061798],"type":"Point"}
}