{
  "type": "Feature",
  "properties": {
    "iso:country":"IT",
    "sg:address":"6, Via Beneventano Del Bosco 96100 Siracusa",
    "sg:city":"Siracusa",
    "sg:classifiers":[
        {
            "category":"Shopping",
            "subcategory":"Computers & Home Electronics",
            "type":"Retail Goods"
        }
    ],
    "sg:phone":"+39 0931 704155",
    "sg:postcode":"96100",
    "sg:province":"Siracusa",
    "sg:tags":[
        "electronic",
        "electrical",
        "equipment"
    ],
    "wof:name":"Il Modulo Srl",
    "wof:placetype":"venue"
},
  "geometry": {"coordinates":[15.292855,37.089615],"type":"Point"}
}