{
  "type": "Feature",
  "properties": {
    "addr:full":"20123 Milano Milano Milano 20123",
    "addr:postcode":"20123;20123",
    "iso:country":"IT",
    "sg:address":"20123 Milano",
    "sg:city":"Milano",
    "sg:orig_category":"Materiali Edili",
    "sg:phone":"+39 02 878516",
    "sg:postcode":"20123",
    "sg:province":"Milano",
    "wof:name":"Galotti (s.p.a.)",
    "wof:placetype":"venue"
},
  "geometry": {"coordinates":[9.174111,45.461628],"type":"Point"}
}