{
  "type": "Feature",
  "properties": {
    "iso:country":"IT",
    "sg:address":"5, Via Bezzecca 25080 Tignale",
    "sg:city":"Tignale",
    "sg:classifiers":[
        {
            "category":"Professional",
            "subcategory":"Engineering",
            "type":"Services"
        }
    ],
    "sg:phone":"+39 036 576 0112",
    "sg:postcode":"25080",
    "sg:province":"Brescia",
    "sg:tags":[
        "machine",
        "-",
        "mechanical"
    ],
    "wof:name":"O.m.p. Di Locatelli Mirella & C. S.n.c.",
    "wof:placetype":"venue"
},
  "geometry": {"coordinates":[10.731105,45.752113],"type":"Point"}
}