{
  "type": "Feature",
  "properties": {
    "addr:full":"70052 Bisceglie Bisceglie Bari 70052",
    "addr:postcode":"70052;70052",
    "iso:country":"IT",
    "sg:address":"70052 Bisceglie",
    "sg:city":"Bisceglie",
    "sg:orig_category":"Dolciumi E Gelati",
    "sg:phone":"+39 080 396 8632",
    "sg:postcode":"70052",
    "sg:province":"Bari",
    "wof:name":"Antichi Sapori Di Losapio & C.",
    "wof:placetype":"venue"
},
  "geometry": {"coordinates":[16.87067,41.112923],"type":"Point"}
}