{
  "type": "Feature",
  "properties": {
    "addr:full":"Km. 11.200, Strada Statale 554 09045 Quartu Sant'elena Cagliari 09045",
    "addr:housenumber":"554",
    "addr:postcode":"09045;09045",
    "addr:street":"Km.;Strada Statale",
    "iso:country":"IT",
    "sg:address":"Km. 11.200, Strada Statale 554 09045 Quartu Sant'elena",
    "sg:classifiers":[
        {
            "category":"Professional",
            "subcategory":"Engineering",
            "type":"Services"
        }
    ],
    "sg:phone":"+39 39070813462",
    "sg:postcode":"09045",
    "sg:province":"Cagliari",
    "sg:tags":[
        "machine",
        "-",
        "mechanical"
    ],
    "wof:name":"Carpenteria Metallica Fadda Luigi & C. Snc",
    "wof:placetype":"venue"
},
  "geometry": {"coordinates":[9.109228,39.215458],"type":"Point"}
}