{
  "type": "Feature",
  "properties": {
    "iso:country":"IT",
    "sg:address":"Via G. Galilei 168 41100 Modena",
    "sg:city":"Modena",
    "sg:classifiers":[
        {
            "category":"Professional",
            "subcategory":"Art Services",
            "type":"Services"
        }
    ],
    "sg:phone":"+39 059 530366",
    "sg:postcode":"41100",
    "sg:province":"Modena",
    "sg:tags":[
        "stand",
        "construction",
        "exhibition",
        "fair",
        "trade"
    ],
    "sg:website":"www.mecdesign.it",
    "wof:name":"M.e.c. Design Srl",
    "wof:placetype":"venue"
},
  "geometry": {"coordinates":[10.975072,44.557484],"type":"Point"}
}