{
  "type": "Feature",
  "properties": {
    "addr:full":"42100 Reggio Emilia Reggio Nell'Emilia 42100",
    "addr:postcode":"42100;42100",
    "iso:country":"IT",
    "sg:address":"42100 Reggio Emilia",
    "sg:orig_category":"Tessuti E Stoffe",
    "sg:phone":"+39 0522 555907",
    "sg:postcode":"42100",
    "sg:province":"Reggio Nell'Emilia",
    "wof:name":"Linea Mor\u00cd",
    "wof:placetype":"venue"
},
  "geometry": {"coordinates":[10.644439,44.691711],"type":"Point"}
}