{
  "type": "Feature",
  "properties": {
    "addr:full":"37069 Villafranca Di Verona Villafranca di Verona Verona 37069",
    "addr:postcode":"37069;37069",
    "addr:street":"Verona",
    "iso:country":"IT",
    "sg:address":"37069 Villafranca Di Verona",
    "sg:city":"Villafranca di Verona",
    "sg:orig_category":"Servizi E Lavori Per Abbigliamento E Pelletterie. Arte Ed Artigianato Artistico. Shopping",
    "sg:phone":"+39 045 630 0743",
    "sg:postcode":"37069",
    "sg:province":"Verona",
    "wof:name":"Prodotti Alfa S.p.a.",
    "wof:placetype":"venue"
},
  "geometry": {"coordinates":[10.842979,45.353401],"type":"Point"}
}