{
  "type": "Feature",
  "properties": {
    "addr:full":"Via Palermo 95046 Palagonia Palagonia Catania 95046",
    "addr:postcode":"95046;95046",
    "addr:street":"Via Palermo",
    "iso:country":"IT",
    "sg:address":"Via Palermo 95046 Palagonia",
    "sg:city":"Palagonia",
    "sg:classifiers":[
        {
            "category":"Food & Beverages",
            "subcategory":"Fruits & Vegetables",
            "type":"Retail Goods"
        }
    ],
    "sg:phone":"+39 095 795 2033",
    "sg:postcode":"95046",
    "sg:province":"Catania",
    "sg:website":"www.dragarancia.it",
    "wof:name":"Pirracchio Pietra",
    "wof:placetype":"venue"
},
  "geometry": {"coordinates":[14.7432889938,37.3319320679],"type":"Point"}
}