{
  "type": "Feature",
  "properties": {
    "iso:country":"IT",
    "sg:address":"27029 Vigevano",
    "sg:city":"Vigevano",
    "sg:orig_category":"Acciaierie E Fonderie",
    "sg:phone":"+39 0381 70334",
    "sg:postcode":"27029",
    "sg:province":"Pavia",
    "wof:name":"Fonderia S.b.s. Snc Di G. Salzano E A. Biondi",
    "wof:placetype":"venue"
},
  "geometry": {"coordinates":[8.83547,45.315491],"type":"Point"}
}