{
  "type": "Feature",
  "properties": {
    "iso:country":"IT",
    "sg:address":"90145 Palermo",
    "sg:city":"Palermo",
    "sg:orig_category":"Trasporti E Spedizioni Merci",
    "sg:phone":"+39 091 682 3800",
    "sg:postcode":"90145",
    "sg:province":"Palermo",
    "wof:name":"Ferrovie Dello Stato",
    "wof:placetype":"venue"
},
  "geometry": {"coordinates":[13.341968,38.130238],"type":"Point"}
}