{
  "type": "Feature",
  "properties": {
    "iso:country":"IT",
    "sg:address":"80035 Nola",
    "sg:city":"Nola",
    "sg:orig_category":"Abbigliamento Esterno, Maglierie E Pelliccerie",
    "sg:phone":"+39 081 510 8401",
    "sg:postcode":"80035",
    "sg:province":"Napoli",
    "wof:name":"Kemitch",
    "wof:placetype":"venue"
},
  "geometry": {"coordinates":[14.513097,40.933453],"type":"Point"}
}