{
  "type": "Feature",
  "properties": {
    "iso:country":"IT",
    "sg:address":"95131 Catania",
    "sg:city":"Catania",
    "sg:classifiers":[
        {
            "category":"Building & Trades",
            "subcategory":"Construction",
            "type":"Services"
        }
    ],
    "sg:phone":"+39 095 322669",
    "sg:postcode":"95131",
    "sg:province":"Catania",
    "sg:tags":[
        "control",
        "climate",
        "household",
        "appliance",
        "equipment",
        "conditioning",
        "services"
    ],
    "sg:website":"http://www.bruno.it",
    "wof:name":"Bruno Domenico & Figli Srl",
    "wof:placetype":"venue"
},
  "geometry": {"coordinates":[15.090031,37.508667],"type":"Point"}
}