{
  "type": "Feature",
  "properties": {
    "addr:full":"25028 Verolanuova Verolanuova Brescia 25028",
    "addr:postcode":"25028;25028",
    "iso:country":"IT",
    "sg:address":"25028 Verolanuova",
    "sg:city":"Verolanuova",
    "sg:orig_category":"Servizi Per Lo Sport E Il Tempo Libero. Servizi Ausiliari Dei Mezzi Di Trasporto",
    "sg:postcode":"25028",
    "sg:province":"Brescia",
    "wof:name":"Gamma",
    "wof:placetype":"venue"
},
  "geometry": {"coordinates":[10.238801,45.561214],"type":"Point"}
}