{
  "type": "Feature",
  "properties": {
    "iso:country":"IT",
    "sg:address":"20068 Peschiera Borromeo",
    "sg:city":"Peschiera Borromeo",
    "sg:orig_category":"Zootecnia E Pesca, Allevamento Piccoli Animali. Servizi Per Lo Sport E Il Tempo Libero",
    "sg:phone":"+39 02 547 0133",
    "sg:postcode":"20068",
    "sg:province":"Milano",
    "wof:name":"Associazione Centro Ippico Il Quadrifoglio",
    "wof:placetype":"venue"
},
  "geometry": {"coordinates":[9.324217,45.435337],"type":"Point"}
}