{
  "type": "Feature",
  "properties": {
    "iso:country":"IT",
    "sg:address":"60015 Falconara Marittima",
    "sg:city":"Falconara Marittima",
    "sg:classifiers":[
        {
            "category":"Bars & Pubs",
            "subcategory":"Champagne Bar",
            "type":"Food & Drink"
        }
    ],
    "sg:phone":"+39 071 917 2524",
    "sg:postcode":"60015",
    "sg:province":"Ancona",
    "sg:tags":[
        "caffe'",
        "e"
    ],
    "wof:name":"Basili Fabiano",
    "wof:placetype":"venue"
},
  "geometry": {"coordinates":[13.398416,43.625614],"type":"Point"}
}