{
  "type": "Feature",
  "properties": {
    "addr:full":"Via San Michele 334 34170 Gorizia Gorizia Gorizia 34170",
    "addr:housenumber":"334",
    "addr:postcode":"34170;34170",
    "addr:street":"Via San Michele",
    "iso:country":"IT",
    "sg:address":"Via San Michele 334 34170 Gorizia",
    "sg:city":"Gorizia",
    "sg:classifiers":[
        {
            "category":"Structure",
            "subcategory":"Tunnel",
            "type":"Public Place"
        }
    ],
    "sg:phone":"+39 0481 21711",
    "sg:postcode":"34170",
    "sg:province":"Gorizia",
    "sg:tags":[
        "catheter"
    ],
    "sg:website":"www.mark-medical.it",
    "wof:name":"Mark Srl",
    "wof:placetype":"venue"
},
  "geometry": {"coordinates":[13.602826,45.923401],"type":"Point"}
}