{
  "type": "Feature",
  "properties": {
    "iso:country":"IT",
    "sg:address":"16, Via Dolomiti 31052 Maserada Sul Piave",
    "sg:city":"Maserada sul Piave",
    "sg:classifiers":[
        {
            "category":"Wholesale",
            "subcategory":"Drugs",
            "type":"Manufacturing & Wholesale Goods"
        }
    ],
    "sg:phone":"+39 0422 777737",
    "sg:postcode":"31052",
    "sg:province":"Treviso",
    "sg:tags":[
        "chemical",
        "pharmaceutical"
    ],
    "wof:name":"Service 2003 Srl",
    "wof:placetype":"venue"
},
  "geometry": {"coordinates":[12.30954,45.760151],"type":"Point"}
}