{
  "type": "Feature",
  "properties": {
    "iso:country":"IT",
    "sg:address":"31046 Oderzo",
    "sg:city":"Oderzo",
    "sg:orig_category":"Ricerca, Selezione E Formazione Del Personale",
    "sg:phone":"+39 0422 718555",
    "sg:postcode":"31046",
    "sg:province":"Treviso",
    "wof:name":"Umana Spa",
    "wof:placetype":"venue"
},
  "geometry": {"coordinates":[12.499269,45.76228],"type":"Point"}
}