{
  "type": "Feature",
  "properties": {
    "iso:country":"IT",
    "sg:address":"35026 Conselve",
    "sg:city":"Conselve",
    "sg:orig_category":"Servizi Al Turismo. Servizi Ausiliari Dei Mezzi Di Trasporto. Servizi Ausiliari Per Il Trasporto. Acqua, Luce, Gas E Societa' Di Esercizio Pubblico",
    "sg:phone":"+39 049 538 4125",
    "sg:postcode":"35026",
    "sg:province":"Padova",
    "sg:website":"http://www.officinebertoli.com",
    "wof:name":"Bertoli Vincenzo & Figlio Snc",
    "wof:placetype":"venue"
},
  "geometry": {"coordinates":[11.89222,45.216019],"type":"Point"}
}