{
  "type": "Feature",
  "properties": {
    "addr:full":"Strada Provinciale 27 26847 Cornovecchio Lodi 26847",
    "addr:housenumber":"27",
    "addr:postcode":"26847;26847",
    "addr:street":"Strada Provinciale",
    "iso:country":"IT",
    "sg:address":"Strada Provinciale 27 26847 Cornovecchio",
    "sg:orig_category":"Miscellaneous Products",
    "sg:phone":"+39 0377 709853",
    "sg:postcode":"26847",
    "sg:province":"Lodi",
    "wof:name":"Zorsol Srl",
    "wof:placetype":"venue"
},
  "geometry": {"coordinates":[9.7716264725,45.156036377],"type":"Point"}
}