{
  "type": "Feature",
  "properties": {
    "iso:country":"IT",
    "sg:address":"03012 Anagni",
    "sg:city":"Anagni",
    "sg:orig_category":"Manufacturers: Prefabbricati",
    "sg:phone":"+39 0775 725252",
    "sg:postcode":"03012",
    "sg:province":"Frosinone",
    "wof:name":"Onoranze Funebri Marocca Di Biasiotti Francesca",
    "wof:placetype":"venue"
},
  "geometry": {"coordinates":[13.162928,41.741501],"type":"Point"}
}