{
  "type": "Feature",
  "properties": {
    "addr:full":"60015 Falconara Marittima Falconara Marittima Ancona 60015",
    "addr:postcode":"60015;60015",
    "iso:country":"IT",
    "sg:address":"60015 Falconara Marittima",
    "sg:city":"Falconara Marittima",
    "sg:orig_category":"Macchine, Impianti E Forniture Per Industria Grafica, Cartaria E Cartotecnica. Automazione E Macchine Per Ufficio",
    "sg:phone":"+39 071 911280",
    "sg:postcode":"60015",
    "sg:province":"Ancona",
    "wof:name":"Severini Bruno",
    "wof:placetype":"venue"
},
  "geometry": {"coordinates":[13.400353,43.628742],"type":"Point"}
}