{
  "type": "Feature",
  "properties": {
    "iso:country":"IT",
    "sg:address":"80125 Napoli",
    "sg:city":"Napoli",
    "sg:orig_category":"Cinematografia E Radiotelevisione. Pubblicita', Marketing E Comunicazione. Acqua, Luce, Gas E Societa' Di Esercizio Pubblico",
    "sg:phone":"+39 081 239 0122",
    "sg:postcode":"80125",
    "sg:province":"Napoli",
    "wof:name":"Rai Radiotelevisione Italiana",
    "wof:placetype":"venue"
},
  "geometry": {"coordinates":[14.202742,40.90736],"type":"Point"}
}