{
  "type": "Feature",
  "properties": {
    "iso:country":"IT",
    "sg:address":"21047 Saronno",
    "sg:city":"Saronno",
    "sg:orig_category":"Cartotecnica E Servizi. Forniture Per Attivita' Commerciali Ed Artigianali",
    "sg:phone":"+39 02 9624 8688",
    "sg:postcode":"21047",
    "sg:province":"Varese",
    "wof:name":"Professionals Sas Di Seveso Adalberto & C.",
    "wof:placetype":"venue"
},
  "geometry": {"coordinates":[9.032098,45.627552],"type":"Point"}
}