{
  "type": "Feature",
  "properties": {
    "iso:country":"IT",
    "sg:address":"Via Nuova Consortile 84084 Fisciano",
    "sg:city":"Fisciano",
    "sg:classifiers":[
        {
            "category":"Manufacturing",
            "subcategory":"Glass & Minerals",
            "type":"Manufacturing & Wholesale Goods"
        }
    ],
    "sg:phone":"+39 39089825454",
    "sg:postcode":"84084",
    "sg:province":"Salerno",
    "wof:name":"Vetro Sud S.r.l.",
    "wof:placetype":"venue"
},
  "geometry": {"coordinates":[14.765912,40.677956],"type":"Point"}
}