{
  "type": "Feature",
  "properties": {
    "addr:full":"Via Dei Biccelli 33 55014 Marlia Marlia Lucca 55014",
    "addr:housenumber":"33",
    "addr:postcode":"55014;55014",
    "addr:street":"Via Dei Biccelli;Marlia Lucca",
    "iso:country":"IT",
    "sg:address":"Via Dei Biccelli 33 55014 Marlia",
    "sg:city":"Marlia",
    "sg:orig_category":"Ladies' Shoes",
    "sg:phone":"+39 0583 30151",
    "sg:postcode":"55014",
    "sg:province":"Lucca",
    "sg:website":"www.nuovapr.com",
    "wof:name":"Calzaturificio Nuova P.r. Sas Di Pera Giuseppe Michael Mirko & C.",
    "wof:placetype":"venue"
},
  "geometry": {"coordinates":[10.583333,43.833332],"type":"Point"}
}