{
  "type": "Feature",
  "properties": {
    "addr:full":"12030 Polonghera Casalgrasso Cuneo 12030",
    "addr:housenumber":"12030",
    "addr:postcode":"12030",
    "addr:street":"Polonghera",
    "iso:country":"IT",
    "sg:address":"12030 Polonghera",
    "sg:city":"Casalgrasso",
    "sg:orig_category":"Fabbri",
    "sg:phone":"+39 011 974722",
    "sg:postcode":"12030",
    "sg:province":"Cuneo",
    "wof:name":"Mondo Sole Srl",
    "wof:placetype":"venue"
},
  "geometry": {"coordinates":[7.6259737015,44.8182983398],"type":"Point"}
}