{
  "type": "Feature",
  "properties": {
    "addr:full":"40017 San Giovanni In Persiceto San Giovanni in Persiceto Bologna 40017",
    "addr:housenumber":"40017",
    "addr:postcode":"40017",
    "iso:country":"IT",
    "sg:address":"40017 San Giovanni In Persiceto",
    "sg:city":"San Giovanni in Persiceto",
    "sg:orig_category":"Ospedali E Servizi Sanitari",
    "sg:phone":"+39 051 821292",
    "sg:postcode":"40017",
    "sg:province":"Bologna",
    "wof:name":"Morisi Capelli Giulia",
    "wof:placetype":"venue"
},
  "geometry": {"coordinates":[11.190281868,44.638469696],"type":"Point"}
}