{
  "type": "Feature",
  "properties": {
    "iso:country":"IT",
    "sg:address":"Via Indipendenza 5, 31100 Treviso, Tv",
    "sg:city":"Treviso",
    "sg:classifiers":[
        {
            "category":"Banks & Credit Unions",
            "subcategory":"Bank",
            "type":"Services"
        }
    ],
    "sg:postcode":"31100",
    "sg:province":"Treviso",
    "wof:name":"Cardine Investmenti Sgr Spa",
    "wof:placetype":"venue"
},
  "geometry": {"coordinates":[12.20272,45.651211],"type":"Point"}
}