{
  "type": "Feature",
  "properties": {
    "addr:full":"30175 Marghera Marghera Venezia 30175",
    "addr:postcode":"30175;30175",
    "iso:country":"IT",
    "sg:address":"30175 Marghera",
    "sg:city":"Marghera",
    "sg:orig_category":"Porti, Darsene E Servizi Portuali",
    "sg:phone":"+39 041 259 1100",
    "sg:postcode":"30175",
    "sg:province":"Venezia",
    "wof:name":"Interporto Di Venezia Spa",
    "wof:placetype":"venue"
},
  "geometry": {"coordinates":[12.2245750427,45.4639358521],"type":"Point"}
}