{
  "type": "Feature",
  "properties": {
    "iso:country":"IT",
    "sg:address":"36015 Schio",
    "sg:city":"Schio",
    "sg:orig_category":"Forniture Per Abbigliamento E Pelletterie",
    "sg:phone":"+39 0445 575311",
    "sg:postcode":"36015",
    "sg:province":"Vicenza",
    "wof:name":"Erredi Snc",
    "wof:placetype":"venue"
},
  "geometry": {"coordinates":[11.5472345352,45.5752296448],"type":"Point"}
}