{
  "type": "Feature",
  "properties": {
    "iso:country":"IT",
    "sg:address":"00040 Ariccia",
    "sg:city":"Ariccia",
    "sg:orig_category":"Banche E Servizi Finanziari. Acqua, Luce, Gas E Societa' Di Esercizio Pubblico",
    "sg:phone":"+39 06 933 0038",
    "sg:postcode":"00040",
    "sg:province":"Roma",
    "wof:name":"I.c.a. Srl",
    "wof:placetype":"venue"
},
  "geometry": {"coordinates":[12.671422,41.720249],"type":"Point"}
}