{
  "type": "Feature",
  "properties": {
    "iso:country":"IT",
    "sg:address":"8, Via Aosta 10044 Pianezza",
    "sg:city":"Pianezza",
    "sg:classifiers":[
        {
            "category":"Professional",
            "subcategory":"Engineering",
            "type":"Services"
        }
    ],
    "sg:phone":"+39 011 966 3263",
    "sg:postcode":"10044",
    "sg:province":"Torino",
    "sg:tags":[
        "machine",
        "-",
        "mechanical"
    ],
    "wof:name":"Sib Srl",
    "wof:placetype":"venue"
},
  "geometry": {"coordinates":[7.575243,45.086811],"type":"Point"}
}