{
  "type": "Feature",
  "properties": {
    "addr:full":"86039 Termoli Termoli Campobasso 86039",
    "addr:postcode":"86039;86039",
    "iso:country":"IT",
    "sg:address":"86039 Termoli",
    "sg:city":"Termoli",
    "sg:orig_category":"Legno E Semilavorati. Articoli Per Imballaggio E Confezionamento",
    "sg:phone":"+39 0875 752514",
    "sg:postcode":"86039",
    "sg:province":"Campobasso",
    "wof:name":"Pimav Srl",
    "wof:placetype":"venue"
},
  "geometry": {"coordinates":[14.997303,41.962578],"type":"Point"}
}