{
  "type": "Feature",
  "properties": {
    "addr:full":"25, Via Rossini Gioacchino 40026 Imola Imola Bologna 40026",
    "addr:postcode":"40026;40026",
    "addr:street":"Via Rossini Gioacchino",
    "iso:country":"IT",
    "sg:address":"25, Via Rossini Gioacchino 40026 Imola",
    "sg:city":"Imola",
    "sg:classifiers":[
        {
            "category":"Travel",
            "subcategory":"Travel Agent",
            "type":"Entertainment"
        }
    ],
    "sg:phone":"+39 0542 680800",
    "sg:postcode":"40026",
    "sg:province":"Bologna",
    "sg:tags":[
        "business"
    ],
    "wof:name":"Albergo Hotel Donatello",
    "wof:placetype":"venue"
},
  "geometry": {"coordinates":[11.346481,44.494221],"type":"Point"}
}