{
  "type": "Feature",
  "properties": {
    "iso:country":"IT",
    "sg:address":"9, Via Castellazzo 20010 Pregnana Milanese",
    "sg:city":"Pregnana Milanese",
    "sg:classifiers":[
        {
            "category":"Professional",
            "subcategory":"Engineering",
            "type":"Services"
        }
    ],
    "sg:phone":"+39 02 9329 0904",
    "sg:postcode":"20010",
    "sg:province":"Milano",
    "sg:tags":[
        "machine",
        "-",
        "mechanical"
    ],
    "wof:name":"Valsesia S.r.l.",
    "wof:placetype":"venue"
},
  "geometry": {"coordinates":[9.014882,45.521641],"type":"Point"}
}