{
  "type": "Feature",
  "properties": {
    "addr:full":"1/2, Via Dei Lapidari 40129 Bologna Bologna Bologna 40129",
    "addr:housenumber":"1 / 2",
    "addr:postcode":"40129;40129",
    "addr:street":"Via Dei Lapidari",
    "iso:country":"IT",
    "sg:address":"1/2, Via Dei Lapidari 40129 Bologna",
    "sg:city":"Bologna",
    "sg:classifiers":[
        {
            "category":"Professional",
            "subcategory":"Printing & Photocopies",
            "type":"Services"
        }
    ],
    "sg:phone":"+39 39051326518",
    "sg:postcode":"40129",
    "sg:province":"Bologna",
    "wof:name":"Tipografia Moderna (s.r.l.)",
    "wof:placetype":"venue"
},
  "geometry": {"coordinates":[11.3505983353,44.5377693176],"type":"Point"}
}