{
  "type": "Feature",
  "properties": {
    "iso:country":"IT",
    "sg:address":"Viale Della Vittoria 50/52; Vittorio Veneto; 31029",
    "sg:city":"Vittorio Veneto",
    "sg:classifiers":[
        {
            "category":"Banks & Credit Unions",
            "subcategory":"Bank",
            "type":"Services"
        }
    ],
    "sg:phone":"+39 0438 941200",
    "sg:postcode":"31029",
    "sg:province":"Treviso",
    "wof:name":"Credito Italiano Spa",
    "wof:placetype":"venue"
},
  "geometry": {"coordinates":[12.294188,45.991856],"type":"Point"}
}