{
  "type": "Feature",
  "properties": {
    "iso:country":"IT",
    "sg:address":"37060 Mozzecane",
    "sg:city":"Mozzecane",
    "sg:classifiers":[
        {
            "category":"Travel",
            "subcategory":"Hotels & Motels",
            "type":"Entertainment"
        }
    ],
    "sg:phone":"+39 045 634 0799",
    "sg:postcode":"37060",
    "sg:province":"Verona",
    "sg:tags":[
        "support",
        "companies",
        "trade",
        "facilities",
        "events",
        "hotels"
    ],
    "sg:website":"http://www.villavecellicavriani.it",
    "wof:name":"Versal Spa - Villa Vecelli Cavriani",
    "wof:placetype":"venue"
},
  "geometry": {"coordinates":[10.817343,45.309116],"type":"Point"}
}