{
  "type": "Feature",
  "properties": {
    "iso:country":"IT",
    "sg:address":"25040 Corte Franca",
    "sg:city":"Corte Franca",
    "sg:orig_category":"Impiantistica E Prodotti Tecnologici Per Edilizia. Telecomunicazioni E Telefonia, Impianti, Apparecchi E Servizi",
    "sg:phone":"+39 030 984367",
    "sg:postcode":"25040",
    "sg:province":"Brescia",
    "wof:name":"F.c.m. Quadri Elettrici Srl",
    "wof:placetype":"venue"
},
  "geometry": {"coordinates":[9.989232,45.631023],"type":"Point"}
}