{
  "type": "Feature",
  "properties": {
    "iso:country":"IT",
    "sg:address":"80078 Pozzuoli",
    "sg:city":"Pozzuoli",
    "sg:orig_category":"Articoli Da Regalo. Forniture Per Uffici. Regalistica Aziendale",
    "sg:phone":"+39 081 570 8553",
    "sg:postcode":"80078",
    "sg:province":"Napoli",
    "wof:name":"The Lalex Pen Co. Italy Srl",
    "wof:placetype":"venue"
},
  "geometry": {"coordinates":[14.088517,40.843346],"type":"Point"}
}