{
  "type": "Feature",
  "properties": {
    "addr:full":"98123 Messina Messina Messina 98123",
    "addr:postcode":"98123;98123",
    "iso:country":"IT",
    "sg:address":"98123 Messina",
    "sg:city":"Messina",
    "sg:orig_category":"Scuole E Servizi Scolastici",
    "sg:phone":"+39 090 692202",
    "sg:postcode":"98123",
    "sg:province":"Messina",
    "wof:name":"Istituto Tecnico Industriale - Verona Trento -",
    "wof:placetype":"venue"
},
  "geometry": {"coordinates":[15.554668,38.182083],"type":"Point"}
}