{
  "type": "Feature",
  "properties": {
    "iso:country":"IT",
    "sg:address":"00148 Roma",
    "sg:city":"Roma",
    "sg:orig_category":"Arredamenti E Mobili Professionali. Arredi Ed Attrezzature Per Uffici",
    "sg:phone":"+39 06 653 5348",
    "sg:postcode":"00148",
    "sg:province":"Roma",
    "sg:website":"http://www.paginegialle.it/catalini",
    "wof:name":"Arredamenti Catalini Snc",
    "wof:placetype":"venue"
},
  "geometry": {"coordinates":[12.43827,41.83239],"type":"Point"}
}