{
  "type": "Feature",
  "properties": {
    "iso:country":"IT",
    "sg:address":"107, Via Cornaggia 22076 Mozzate",
    "sg:city":"Mozzate",
    "sg:classifiers":[
        {
            "category":"Professional",
            "subcategory":"Engineering",
            "type":"Services"
        }
    ],
    "sg:phone":"+39 0331 823511",
    "sg:postcode":"22076",
    "sg:province":"Como",
    "sg:tags":[
        "machine",
        "-",
        "mechanical"
    ],
    "wof:name":"A.p.i. Srl",
    "wof:placetype":"venue"
},
  "geometry": {"coordinates":[8.951271,45.671047],"type":"Point"}
}