{
  "type": "Feature",
  "properties": {
    "iso:country":"IT",
    "sg:address":"57, Via Lova 30010 Campolongo Maggiore",
    "sg:city":"Lova",
    "sg:classifiers":[
        {
            "category":"Manufacturing",
            "subcategory":"Metals",
            "type":"Manufacturing & Wholesale Goods"
        }
    ],
    "sg:phone":"+39 049 580 9249",
    "sg:postcode":"30010",
    "sg:province":"Venezia",
    "sg:tags":[
        "metallurgy",
        "metalworking"
    ],
    "wof:name":"Palfer (s.n.c.)",
    "wof:placetype":"venue"
},
  "geometry": {"coordinates":[12.0888948441,45.3366699219],"type":"Point"}
}