{
  "type": "Feature",
  "properties": {
    "addr:full":"00146 Roma Roma Roma 00146",
    "addr:postcode":"00146;00146",
    "iso:country":"IT",
    "sg:address":"00146 Roma",
    "sg:city":"Roma",
    "sg:orig_category":"Riparazione Dei Mezzi Di Trasporto. Servizi Ausiliari Dei Mezzi Di Trasporto",
    "sg:phone":"+39 06 5530 0570",
    "sg:postcode":"00146",
    "sg:province":"Roma",
    "wof:name":"Iaccarino Stefano",
    "wof:placetype":"venue"
},
  "geometry": {"coordinates":[12.469259,41.862217],"type":"Point"}
}