{
  "type": "Feature",
  "properties": {
    "addr:full":"Via Vaninetti Giuseppe 11 10148 Torino Torino Torino 10148",
    "addr:housenumber":"11",
    "addr:postcode":"10148;10148",
    "addr:street":"Via Vaninetti Giuseppe",
    "iso:country":"IT",
    "sg:address":"Via Vaninetti Giuseppe 11 10148 Torino",
    "sg:city":"Torino",
    "sg:classifiers":[
        {
            "category":"Organizations",
            "subcategory":"Professional Association",
            "type":"Services"
        }
    ],
    "sg:phone":"+39 011 220 3166",
    "sg:postcode":"10148",
    "sg:province":"Torino",
    "sg:tags":[
        "control",
        "production",
        "industry",
        "planning",
        "software"
    ],
    "wof:name":"Elind Srl",
    "wof:placetype":"venue"
},
  "geometry": {"coordinates":[7.686619,45.07056],"type":"Point"}
}