{
  "type": "Feature",
  "properties": {
    "iso:country":"IT",
    "sg:address":"S. Croce 30135 Venezia",
    "sg:city":"Venezia",
    "sg:classifiers":[
        {
            "category":"Manufacturing",
            "subcategory":"Printing",
            "type":"Manufacturing & Wholesale Goods"
        }
    ],
    "sg:phone":"+39 041 523 8352",
    "sg:postcode":"30135",
    "sg:province":"Venezia",
    "sg:tags":[
        "publishing"
    ],
    "wof:name":"Giornale Marco Polo",
    "wof:placetype":"venue"
},
  "geometry": {"coordinates":[12.3266267776,45.4408950806],"type":"Point"}
}