{
  "type": "Feature",
  "properties": {
    "addr:full":"34, Via Dal Garda 38068 Rovereto Rovereto Trento 38068",
    "addr:postcode":"38068;38068",
    "addr:street":"Via Dal Garda",
    "iso:country":"IT",
    "sg:address":"34, Via Dal Garda 38068 Rovereto",
    "sg:city":"Rovereto",
    "sg:classifiers":[
        {
            "category":"Manufacturing",
            "subcategory":"Food",
            "type":"Manufacturing & Wholesale Goods"
        }
    ],
    "sg:phone":"+39 0464 436080",
    "sg:postcode":"38068",
    "sg:province":"Trento",
    "sg:tags":[
        "equipment",
        "processing",
        "-",
        "machinery"
    ],
    "wof:name":"Sasib Food Machinery Mv (s.p.a.)",
    "wof:placetype":"venue"
},
  "geometry": {"coordinates":[11.119052887,46.0667381287],"type":"Point"}
}