{
  "type": "Feature",
  "properties": {
    "addr:full":"34/1, Via Andreuzza 33030 Buia Udine 33030",
    "addr:housenumber":"34 / 1",
    "addr:postcode":"33030;33030",
    "addr:street":"Via Andreuzza",
    "iso:country":"IT",
    "sg:address":"34/1, Via Andreuzza 33030 Buia",
    "sg:classifiers":[
        {
            "category":"Manufacturing",
            "subcategory":"Metals",
            "type":"Manufacturing & Wholesale Goods"
        }
    ],
    "sg:phone":"+39 0432 968111",
    "sg:postcode":"33030",
    "sg:province":"Udine",
    "sg:tags":[
        "metallurgy",
        "metalworking"
    ],
    "wof:name":"Friuli Laminati Speciali S.p.a.",
    "wof:placetype":"venue"
},
  "geometry": {"coordinates":[13.1066026688,46.2073822021],"type":"Point"}
}