{
  "type": "Feature",
  "properties": {
    "iso:country":"IT",
    "sg:address":"00040 Pomezia",
    "sg:city":"Pomezia",
    "sg:orig_category":"Vetro: Prodotti E Lavorazioni. Forniture Industriali Per Prevenzione, Controllo E Sicurezza",
    "sg:phone":"+39 06 912 1951",
    "sg:postcode":"00040",
    "sg:province":"Roma",
    "wof:name":"Morrone Mario",
    "wof:placetype":"venue"
},
  "geometry": {"coordinates":[12.499419,41.6726],"type":"Point"}
}