{
  "type": "Feature",
  "properties": {
    "iso:country":"IT",
    "sg:address":"86034 Guglionesi",
    "sg:city":"Guglionesi",
    "sg:orig_category":"Materiali Edili",
    "sg:phone":"+39 0875 680086",
    "sg:postcode":"86034",
    "sg:province":"Campobasso",
    "wof:name":"Bpb Italia Spa",
    "wof:placetype":"venue"
},
  "geometry": {"coordinates":[14.903845,41.936169],"type":"Point"}
}