{
  "type": "Feature",
  "properties": {
    "addr:full":"83, Via Filzi Fabio 36051 Creazzo Creazzo Vicenza 36051",
    "addr:postcode":"36051;36051",
    "addr:street":"Via Filzi Fabio",
    "iso:country":"IT",
    "sg:address":"83, Via Filzi Fabio 36051 Creazzo",
    "sg:city":"Creazzo",
    "sg:classifiers":[
        {
            "category":"Professional",
            "subcategory":"Engineering",
            "type":"Services"
        }
    ],
    "sg:phone":"+39 0444 349544",
    "sg:postcode":"36051",
    "sg:province":"Vicenza",
    "sg:tags":[
        "machine",
        "-",
        "mechanical"
    ],
    "wof:name":"O.c.s.a. (s.r.l.)",
    "wof:placetype":"venue"
},
  "geometry": {"coordinates":[11.498992,45.532272],"type":"Point"}
}