{
  "type": "Feature",
  "properties": {
    "iso:country":"IT",
    "sg:address":"40, Via Majorana Ettore 48022 Lugo",
    "sg:city":"Lugo",
    "sg:classifiers":[
        {
            "category":"Personal",
            "subcategory":"Shoe Repair & Shine",
            "type":"Services"
        }
    ],
    "sg:phone":"+39 39054534441",
    "sg:postcode":"48022",
    "sg:province":"Ravenna",
    "sg:tags":[
        "leather"
    ],
    "wof:name":"Calzaturificio La Rocca(s.r.l.)",
    "wof:placetype":"venue"
},
  "geometry": {"coordinates":[12.196571,44.41573],"type":"Point"}
}