{
  "type": "Feature",
  "properties": {
    "addr:full":"69, Via Dell' Orsa Minore 90124 Palermo Palermo Palermo 90124",
    "addr:postcode":"90124;90124",
    "addr:street":"Via Dell ' Orsa Minore",
    "iso:country":"IT",
    "sg:address":"69, Via Dell' Orsa Minore 90124 Palermo",
    "sg:city":"Palermo",
    "sg:classifiers":[
        {
            "category":"Shopping",
            "subcategory":"Clothing, Apparel, & Fashions",
            "type":"Retail Goods"
        }
    ],
    "sg:phone":"+39 091 647 1799",
    "sg:postcode":"90124",
    "sg:province":"Palermo",
    "sg:tags":[
        "clothes"
    ],
    "wof:name":"Delizie Di Minneci Maria",
    "wof:placetype":"venue"
},
  "geometry": {"coordinates":[13.36581,38.092968],"type":"Point"}
}