{
  "type": "Feature",
  "properties": {
    "iso:country":"IT",
    "sg:address":"63013 Grottammare",
    "sg:city":"Grottammare",
    "sg:orig_category":"Serre - Impianti Ed Attrezzature",
    "sg:phone":"+39 0735 90484",
    "sg:postcode":"63013",
    "sg:province":"Ascoli Piceno",
    "wof:name":"Ascani Antonio",
    "wof:placetype":"venue"
},
  "geometry": {"coordinates":[13.870488,42.982166],"type":"Point"}
}