{
  "type": "Feature",
  "properties": {
    "iso:country":"IT",
    "sg:address":"20090 Trezzano Sul Naviglio",
    "sg:city":"Trezzano sul Naviglio",
    "sg:orig_category":"Climatizzazione E Condizionamento, Apparecchiature E Servizi. Accessori Dei Mezzi Di Trasporto",
    "sg:phone":"+39 02 4840 3771",
    "sg:postcode":"20090",
    "sg:province":"Milano",
    "wof:name":"Autosystem Climatronic S.r.l.",
    "wof:placetype":"venue"
},
  "geometry": {"coordinates":[9.049053,45.427998],"type":"Point"}
}