{
  "type": "Feature",
  "properties": {
    "addr:full":"84098 Pontecagnano Faiano Faiano Salerno 84098",
    "addr:postcode":"84098;84098",
    "iso:country":"IT",
    "sg:address":"84098 Pontecagnano Faiano",
    "sg:city":"Faiano",
    "sg:orig_category":"Materiali Edili",
    "sg:phone":"+39 089 381831",
    "sg:postcode":"84098",
    "sg:province":"Salerno",
    "wof:name":"S.a.c. Di De Rosa V. E Fiorillo F. E C. S.n.c.",
    "wof:placetype":"venue"
},
  "geometry": {"coordinates":[14.868209,40.642029],"type":"Point"}
}