{
  "type": "Feature",
  "properties": {
    "iso:country":"IT",
    "sg:address":"35027 Noventa Padovana",
    "sg:city":"Noventa Padovana",
    "sg:orig_category":"Materiali Edili",
    "sg:phone":"+39 049 628628",
    "sg:postcode":"35027",
    "sg:province":"Padova",
    "wof:name":"Betta Commerciale Di Di Sanavia Roberta & C. (s.a.s.)",
    "wof:placetype":"venue"
},
  "geometry": {"coordinates":[11.943444,45.421471],"type":"Point"}
}