{
  "type": "Feature",
  "properties": {
    "addr:full":"28069 Trecate Trecate Novara 28069",
    "addr:postcode":"28069;28069",
    "iso:country":"IT",
    "sg:address":"28069 Trecate",
    "sg:city":"Trecate",
    "sg:orig_category":"Antifurto",
    "sg:phone":"+39 0321 71397",
    "sg:postcode":"28069",
    "sg:province":"Novara",
    "wof:name":"Thermoelektra Snc",
    "wof:placetype":"venue"
},
  "geometry": {"coordinates":[8.7538509369,45.4369926453],"type":"Point"}
}