{
  "type": "Feature",
  "properties": {
    "addr:full":"Piazza Della Vittoria 8; Monselica; 35043 Padova 35043",
    "addr:housenumber":"8",
    "addr:postcode":"35043;35043",
    "addr:street":"Piazza Della Vittoria",
    "iso:country":"IT",
    "sg:address":"Piazza Della Vittoria 8; Monselica; 35043",
    "sg:classifiers":[
        {
            "category":"Banks & Credit Unions",
            "subcategory":"Bank",
            "type":"Services"
        }
    ],
    "sg:phone":"+39 0429 780944",
    "sg:postcode":"35043",
    "sg:province":"Padova",
    "wof:name":"Banca Nazionale Del Lavoro Spa",
    "wof:placetype":"venue"
},
  "geometry": {"coordinates":[11.749964,45.23933],"type":"Point"}
}