{
  "type": "Feature",
  "properties": {
    "iso:country":"IT",
    "sg:address":"20069 Vaprio D'adda",
    "sg:orig_category":"Arredi Ed Attrezzature Per Uffici",
    "sg:phone":"+39 02 9096 6272",
    "sg:postcode":"20069",
    "sg:province":"Milano",
    "wof:name":"Pastori Angelo",
    "wof:placetype":"venue"
},
  "geometry": {"coordinates":[9.555199,45.605625],"type":"Point"}
}