{
  "type": "Feature",
  "properties": {
    "addr:full":"83020 San Michele Di Serino San Michele di Serino Avellino 83020",
    "addr:housenumber":"83020",
    "addr:postcode":"di serino;83020",
    "addr:street":"San;Di Serino Avellino",
    "iso:country":"IT",
    "sg:address":"83020 San Michele Di Serino",
    "sg:city":"San Michele di Serino",
    "sg:orig_category":"Salotti, Poltrone, Sedie E Tavoli",
    "sg:phone":"+39 0825 595734",
    "sg:postcode":"83020",
    "sg:province":"Avellino",
    "wof:name":"De Vita Vincenzo - Devitarredo",
    "wof:placetype":"venue"
},
  "geometry": {"coordinates":[14.844231,40.891724],"type":"Point"}
}