{
  "type": "Feature",
  "properties": {
    "addr:full":"Via Pio X 31/a 31010 Francenigo Di Gaiarine Treviso 31010",
    "addr:housenumber":"31 / a",
    "addr:postcode":"31010;31010",
    "addr:street":"Via Pio X",
    "iso:country":"IT",
    "sg:address":"Via Pio X 31/a 31010 Francenigo Di Gaiarine",
    "sg:classifiers":[
        {
            "category":"Shopping",
            "subcategory":"Stationery & Office Supplies",
            "type":"Retail Goods"
        }
    ],
    "sg:phone":"+39 0434 768021",
    "sg:postcode":"31010",
    "sg:province":"Treviso",
    "sg:tags":[
        "furniture"
    ],
    "wof:name":"D.p.s. Mobili S.r.l.",
    "wof:placetype":"venue"
},
  "geometry": {"coordinates":[12.242072,45.666286],"type":"Point"}
}