{
  "type": "Feature",
  "properties": {
    "addr:full":"91021 Campobello Di Mazara Campobello di Mazara Trapani 91021",
    "addr:housenumber":"di mazara",
    "addr:postcode":"91021;91021",
    "iso:country":"IT",
    "sg:address":"91021 Campobello Di Mazara",
    "sg:city":"Campobello di Mazara",
    "sg:orig_category":"Prodotti Chimici Di Base",
    "sg:phone":"+39 0924 911033",
    "sg:postcode":"91021",
    "sg:province":"Trapani",
    "wof:name":"Tonastucchi Di La Rosa & Manzo S.n.c.",
    "wof:placetype":"venue"
},
  "geometry": {"coordinates":[12.517124176,38.0186080933],"type":"Point"}
}