{
  "type": "Feature",
  "properties": {
    "iso:country":"IT",
    "sg:address":"55010 Capannori",
    "sg:city":"Capannori",
    "sg:orig_category":"Elettrotecnica Industriale, Prodotti E Apparecchiature",
    "sg:phone":"+39 0583 429430",
    "sg:postcode":"55010",
    "sg:province":"Lucca",
    "sg:website":"http://www.cacinispa.com",
    "wof:name":"Cacini & C. Spa",
    "wof:placetype":"venue"
},
  "geometry": {"coordinates":[10.579061,43.857315],"type":"Point"}
}