{
  "type": "Feature",
  "properties": {
    "addr:full":"25030 Orzivecchi Orzivecchi Brescia 25030",
    "addr:postcode":"25030;25030",
    "iso:country":"IT",
    "sg:address":"25030 Orzivecchi",
    "sg:city":"Orzivecchi",
    "sg:orig_category":"Dolciumi E Gelati",
    "sg:phone":"+39 030 946 5199",
    "sg:postcode":"25030",
    "sg:province":"Brescia",
    "wof:name":"Poli Dolci Di Poli Oscar & C. S.a.s.",
    "wof:placetype":"venue"
},
  "geometry": {"coordinates":[9.962425,45.422237],"type":"Point"}
}