{
  "type": "Feature",
  "properties": {
    "iso:country":"IT",
    "sg:address":"Via Nazionale 3; S. Pietro Berbenno; 23010",
    "sg:classifiers":[
        {
            "category":"Banks & Credit Unions",
            "subcategory":"Bank",
            "type":"Services"
        }
    ],
    "sg:phone":"+39 0342 492115",
    "sg:postcode":"23010",
    "sg:province":"Sondrio",
    "wof:name":"Banca Popolare Di Sondrio Scarl",
    "wof:placetype":"venue"
},
  "geometry": {"coordinates":[9.746273,46.168739],"type":"Point"}
}