{
  "type": "Feature",
  "properties": {
    "addr:full":"70016 Noicattaro Noicattaro Bari 70016",
    "addr:postcode":"70016;70016",
    "iso:country":"IT",
    "sg:address":"70016 Noicattaro",
    "sg:city":"Noicattaro",
    "sg:orig_category":"Bevande, Vini E Liquori",
    "sg:phone":"+39 080 478 2214",
    "sg:postcode":"70016",
    "sg:province":"Bari",
    "wof:name":"Ressa Sabino",
    "wof:placetype":"venue"
},
  "geometry": {"coordinates":[16.989836,41.03521],"type":"Point"}
}