{
  "type": "Feature",
  "properties": {
    "iso:country":"IT",
    "sg:address":"12/b, Via Ragazzi Del '99 42100 Reggio Emilia",
    "sg:classifiers":[
        {
            "category":"Shopping",
            "subcategory":"Clothing, Apparel, & Fashions",
            "type":"Retail Goods"
        }
    ],
    "sg:phone":"+39 0522 922578",
    "sg:postcode":"42100",
    "sg:province":"Reggio Nell'Emilia",
    "sg:tags":[
        "clothes"
    ],
    "wof:name":"Maglifio Kopertina S.r.l.",
    "wof:placetype":"venue"
},
  "geometry": {"coordinates":[10.645807,44.741093],"type":"Point"}
}