{
  "type": "Feature",
  "properties": {
    "iso:country":"IT",
    "sg:address":"Viale Rimembranza, 5; Castellanza; 21053",
    "sg:city":"Castellanza",
    "sg:classifiers":[
        {
            "category":"Banks & Credit Unions",
            "subcategory":"Bank",
            "type":"Services"
        }
    ],
    "sg:phone":"+39 0331 501529",
    "sg:postcode":"21053",
    "sg:province":"Varese",
    "wof:name":"Banca Popolare Di Novara",
    "wof:placetype":"venue"
},
  "geometry": {"coordinates":[8.901865,45.611633],"type":"Point"}
}