{
  "type": "Feature",
  "properties": {
    "iso:country":"IT",
    "sg:address":"1, Via Michelangelo 36050 Zermeghedo",
    "sg:city":"Zermeghedo",
    "sg:classifiers":[
        {
            "category":"Professional",
            "subcategory":"Engineering",
            "type":"Services"
        }
    ],
    "sg:phone":"+39 0444 685515",
    "sg:postcode":"36050",
    "sg:province":"Vicenza",
    "sg:tags":[
        "machine",
        "-",
        "mechanical"
    ],
    "wof:name":"Muraro (s.p.a.)",
    "wof:placetype":"venue"
},
  "geometry": {"coordinates":[11.378917,45.473522],"type":"Point"}
}