{
  "type": "Feature",
  "properties": {
    "iso:country":"IT",
    "sg:address":"34010 Sgonico",
    "sg:city":"Sgonico",
    "sg:orig_category":"Banche E Servizi Finanziari. Acqua, Luce, Gas E Societa' Di Esercizio Pubblico. Pubblica Amministrazione",
    "sg:phone":"+39 040 225209",
    "sg:postcode":"34010",
    "sg:province":"Trieste",
    "wof:name":"Agenzia Delle Dogane",
    "wof:placetype":"venue"
},
  "geometry": {"coordinates":[13.752771,45.731796],"type":"Point"}
}