{
  "type": "Feature",
  "properties": {
    "addr:full":"42, Zona Industriale Gresal 32036 Sedico Sedico Belluno 32036",
    "addr:housenumber":"42",
    "addr:postcode":"32036;32036",
    "addr:street":"Zona Industriale Gresal",
    "iso:country":"IT",
    "sg:address":"42, Zona Industriale Gresal 32036 Sedico",
    "sg:city":"Sedico",
    "sg:classifiers":[
        {
            "category":"Manufacturing",
            "subcategory":"Metals",
            "type":"Manufacturing & Wholesale Goods"
        }
    ],
    "sg:phone":"+39 39043783047",
    "sg:postcode":"32036",
    "sg:province":"Belluno",
    "sg:tags":[
        "metallurgy",
        "metalworking"
    ],
    "wof:name":"La Bellunese Ferro S.r.l.",
    "wof:placetype":"venue"
},
  "geometry": {"coordinates":[12.110408783,46.1099700928],"type":"Point"}
}