{
  "type": "Feature",
  "properties": {
    "addr:full":"85050 San Cataldo Di Bella Potenza 85050",
    "addr:housenumber":"85050",
    "addr:postcode":"85050",
    "iso:country":"IT",
    "sg:address":"85050 San Cataldo Di Bella",
    "sg:orig_category":"Serramenti Ed Infissi",
    "sg:phone":"+39 0976 73247",
    "sg:postcode":"85050",
    "sg:province":"Potenza",
    "wof:name":"Edilserramenti Snc",
    "wof:placetype":"venue"
},
  "geometry": {"coordinates":[15.802221,40.637241],"type":"Point"}
}