{
  "type": "Feature",
  "properties": {
    "iso:country":"IT",
    "sg:address":"40133 Bologna",
    "sg:city":"Bologna",
    "sg:orig_category":"Ospedali E Servizi Sanitari. Centri Di Estetica E Cosmesi E Servizi",
    "sg:phone":"+39 051 619 3011",
    "sg:postcode":"40133",
    "sg:province":"Bologna",
    "wof:name":"Centro Di Riabilitazione Axia Cooperativa Di Produzione Lavoro Soc. Coop. A",
    "wof:placetype":"venue"
},
  "geometry": {"coordinates":[11.297159,44.491875],"type":"Point"}
}