{
  "type": "Feature",
  "properties": {
    "iso:country":"IT",
    "sg:address":"30035 Mirano",
    "sg:city":"Mirano",
    "sg:orig_category":"Servizi E Lavori Per Ecologia E Smaltimento Rifiuti. Servizi Ausiliari Di Sorveglianza, Manutenzione E Pulizia",
    "sg:phone":"+39 041 572 8484",
    "sg:postcode":"30035",
    "sg:province":"Venezia",
    "sg:website":"http://www.centroplastica.it",
    "wof:name":"Centro Plastica Srl",
    "wof:placetype":"venue"
},
  "geometry": {"coordinates":[12.146634,45.497246],"type":"Point"}
}