{
  "type": "Feature",
  "properties": {
    "addr:full":"33100 Udine Udine Udine 33100",
    "addr:postcode":"33100;33100",
    "iso:country":"IT",
    "sg:address":"33100 Udine",
    "sg:city":"Udine",
    "sg:orig_category":"Pubblicita', Marketing E Comunicazione",
    "sg:phone":"+39 0432 504587",
    "sg:postcode":"33100",
    "sg:province":"Udine",
    "wof:name":"Fima Di Tempesta Claudio",
    "wof:placetype":"venue"
},
  "geometry": {"coordinates":[13.2758407593,45.9786376953],"type":"Point"}
}