{
  "type": "Feature",
  "properties": {
    "iso:country":"IT",
    "sg:address":"32/34, Viale Dell' Industria 36034 Malo",
    "sg:city":"Malo",
    "sg:classifiers":[
        {
            "category":"Manufacturing",
            "subcategory":"Metals",
            "type":"Manufacturing & Wholesale Goods"
        }
    ],
    "sg:phone":"+39 0445 637020",
    "sg:postcode":"36034",
    "sg:province":"Vicenza",
    "sg:tags":[
        "metallurgy",
        "metalworking"
    ],
    "wof:name":"Torneria F.lli Buzzolan (s.r.l.)",
    "wof:placetype":"venue"
},
  "geometry": {"coordinates":[11.3712320328,45.7089347839],"type":"Point"}
}