{
  "type": "Feature",
  "properties": {
    "addr:full":"22036 Erba Erba Como 22036",
    "addr:postcode":"22036;22036",
    "iso:country":"IT",
    "sg:address":"22036 Erba",
    "sg:city":"Erba",
    "sg:orig_category":"Chiese Ed Associazioni Religiose",
    "sg:phone":"+39 031 643770",
    "sg:postcode":"22036",
    "sg:province":"Como",
    "wof:name":"Chiesa Cristiana Evangelica",
    "wof:placetype":"venue"
},
  "geometry": {"coordinates":[9.159925,45.783813],"type":"Point"}
}