{
  "type": "Feature",
  "properties": {
    "iso:country":"IT",
    "sg:address":"1, Via Donizetti 22032 Albese Con Cassano",
    "sg:city":"Albese con Cassano",
    "sg:classifiers":[
        {
            "category":"Professional",
            "subcategory":"Printing & Photocopies",
            "type":"Services"
        }
    ],
    "sg:phone":"+39 39031426437",
    "sg:postcode":"22032",
    "sg:province":"Como",
    "wof:name":"Fotoincisione Rodilosso (s.r.l.)",
    "wof:placetype":"venue"
},
  "geometry": {"coordinates":[9.1525068283,45.7953491211],"type":"Point"}
}