{
  "type": "Feature",
  "properties": {
    "iso:country":"IT",
    "sg:address":"110, Viale Monastir 09122 Cagliari",
    "sg:city":"Cagliari",
    "sg:classifiers":[
        {
            "category":"Wholesale",
            "subcategory":"Machinery & Supplies",
            "type":"Manufacturing & Wholesale Goods"
        }
    ],
    "sg:phone":"+39 39070281636",
    "sg:postcode":"09122",
    "sg:province":"Cagliari",
    "sg:tags":[
        "equipment",
        "-",
        "instrument",
        "measurement"
    ],
    "wof:name":"Bioanalisi Centro Sud Di Perseu Sinibaldo Snc",
    "wof:placetype":"venue"
},
  "geometry": {"coordinates":[9.094766,39.24815],"type":"Point"}
}