{
  "type": "Feature",
  "properties": {
    "addr:full":"21059 Viggiu' Varese 21059",
    "addr:postcode":"21059;21059",
    "addr:street":"Viggiu ' Varese",
    "iso:country":"IT",
    "sg:address":"21059 Viggiu'",
    "sg:orig_category":"Motori Ed Organi Di Trasmissione. Ricambi E Componenti Dei Mezzi Di Trasporto",
    "sg:phone":"+39 0332 485108",
    "sg:postcode":"21059",
    "sg:province":"Varese",
    "wof:name":"Brusco Franco",
    "wof:placetype":"venue"
},
  "geometry": {"coordinates":[8.8968153,45.8236885071],"type":"Point"}
}