{
  "type": "Feature",
  "properties": {
    "iso:country":"IT",
    "sg:address":"00197 Roma",
    "sg:city":"Roma",
    "sg:orig_category":"Climatizzazione E Condizionamento, Apparecchiature E Servizi",
    "sg:phone":"+39 06 807 5146",
    "sg:postcode":"00197",
    "sg:province":"Roma",
    "wof:name":"D.m. Srl",
    "wof:placetype":"venue"
},
  "geometry": {"coordinates":[12.488333,41.926353],"type":"Point"}
}