{
  "type": "Feature",
  "properties": {
    "iso:country":"IT",
    "sg:address":"21, Via Bassi Ugo 20159 Milano",
    "sg:city":"Milano",
    "sg:classifiers":[
        {
            "category":"Sports & Exercise",
            "subcategory":"Playing Field",
            "type":"Entertainment"
        }
    ],
    "sg:phone":"+39 390 266 8961",
    "sg:postcode":"20159",
    "sg:province":"Milano",
    "sg:tags":[
        "game"
    ],
    "wof:name":"Sanford Italy Srl",
    "wof:placetype":"venue"
},
  "geometry": {"coordinates":[9.187291,45.489754],"type":"Point"}
}