{
  "type": "Feature",
  "properties": {
    "iso:country":"IT",
    "sg:address":"88100 Catanzaro",
    "sg:city":"Catanzaro",
    "sg:orig_category":"Servizi E Lavori Per Agricoltura E Zootecnia. Imprese Di Costruzioni Civili Ed Industriali",
    "sg:phone":"+39 0961 710006",
    "sg:postcode":"88100",
    "sg:province":"Catanzaro",
    "wof:name":"Greco Sandro",
    "wof:placetype":"venue"
},
  "geometry": {"coordinates":[16.610727,38.870102],"type":"Point"}
}