{
  "type": "Feature",
  "properties": {
    "iso:country":"IT",
    "sg:address":"Via Dell'ecologia 5/11 57127 Livorno",
    "sg:city":"Livorno",
    "sg:classifiers":[
        {
            "category":"Food & Beverages",
            "subcategory":"Groceries & Convenience Stores",
            "type":"Retail Goods"
        }
    ],
    "sg:phone":"+39 0586 410134",
    "sg:postcode":"57127",
    "sg:province":"Livorno",
    "sg:tags":[
        "fresh"
    ],
    "wof:name":"C.d. & S. Srl",
    "wof:placetype":"venue"
},
  "geometry": {"coordinates":[10.3521404266,43.5738639832],"type":"Point"}
}