{
  "type": "Feature",
  "properties": {
    "iso:country":"IT",
    "sg:address":"20154 Milano",
    "sg:city":"Milano",
    "sg:orig_category":"Materiali Semilavorati Metallici",
    "sg:phone":"+39 02 3453 2040",
    "sg:postcode":"20154",
    "sg:province":"Milano",
    "wof:name":"Siac Srl",
    "wof:placetype":"venue"
},
  "geometry": {"coordinates":[9.180756,45.478378],"type":"Point"}
}