{
  "type": "Feature",
  "properties": {
    "addr:full":"Via Brioni 2 59100 Prato Prato Prato 59100",
    "addr:housenumber":"2",
    "addr:postcode":"59100;59100",
    "addr:street":"Via Brioni",
    "iso:country":"IT",
    "sg:address":"Via Brioni 2 59100 Prato",
    "sg:city":"Prato",
    "sg:classifiers":[
        {
            "category":"Shopping",
            "subcategory":"Crafts & Fabrics",
            "type":"Retail Goods"
        }
    ],
    "sg:phone":"+39 0574 462354",
    "sg:postcode":"59100",
    "sg:province":"Prato",
    "sg:tags":[
        "ladies'",
        "wear"
    ],
    "wof:name":"Lanificio Etruria Srl",
    "wof:placetype":"venue"
},
  "geometry": {"coordinates":[11.095454216,43.900138855],"type":"Point"}
}