{
  "type": "Feature",
  "properties": {
    "iso:country":"IT",
    "sg:address":"22021 Bellagio",
    "sg:city":"Bellagio",
    "sg:orig_category":"Servizi Culturali E Per Lo Spettacolo. Arte Ed Artigianato Artistico. Servizi Al Turismo",
    "sg:phone":"+39 031 950002",
    "sg:postcode":"22021",
    "sg:province":"Como",
    "sg:website":"http://www.valentinarte.com",
    "wof:name":"Galleria Valentinarte Di Falconi Emanuele",
    "wof:placetype":"venue"
},
  "geometry": {"coordinates":[9.246164,45.96413],"type":"Point"}
}