{
  "type": "Feature",
  "properties": {
    "addr:full":"180, Via Milano 28883 Gravellona Toce Gravellona Toce Verbano-Cusio-Ossola 28883",
    "addr:housenumber":"180",
    "addr:postcode":"28883;28883",
    "addr:street":"Via Milano",
    "iso:country":"IT",
    "sg:address":"180, Via Milano 28883 Gravellona Toce",
    "sg:city":"Gravellona Toce",
    "sg:classifiers":[
        {
            "category":"Shopping",
            "subcategory":"Crafts & Fabrics",
            "type":"Retail Goods"
        }
    ],
    "sg:phone":"+39 0323 848334",
    "sg:postcode":"28883",
    "sg:province":"Verbano-Cusio-Ossola",
    "wof:name":"P.m.s. (s.r.l.)",
    "wof:placetype":"venue"
},
  "geometry": {"coordinates":[8.4443874359,45.9240226746],"type":"Point"}
}