{
  "type": "Feature",
  "properties": {
    "iso:country":"IT",
    "sg:address":"20125 Milano",
    "sg:city":"Milano",
    "sg:orig_category":"Articoli Per Imballaggio E Confezionamento",
    "sg:phone":"+39 02 6698 7652",
    "sg:postcode":"20125",
    "sg:province":"Milano",
    "wof:name":"Loberg Di Annalisa Lolli",
    "wof:placetype":"venue"
},
  "geometry": {"coordinates":[9.246372,45.510372],"type":"Point"}
}