{
  "type": "Feature",
  "properties": {
    "addr:full":"Corso Del Popolo 185, 45100 Rovigo, Ro Rovigo Rovigo 45100",
    "addr:housenumber":"185",
    "addr:postcode":"45100;45100",
    "addr:street":"Corso Del Popolo",
    "iso:country":"IT",
    "sg:address":"Corso Del Popolo 185, 45100 Rovigo, Ro",
    "sg:city":"Rovigo",
    "sg:classifiers":[
        {
            "category":"Banks & Credit Unions",
            "subcategory":"Bank",
            "type":"Services"
        }
    ],
    "sg:postcode":"45100",
    "sg:province":"Rovigo",
    "wof:name":"Banca Del Monte Di Rovigo Spa",
    "wof:placetype":"venue"
},
  "geometry": {"coordinates":[11.793826,45.064953],"type":"Point"}
}