{
  "type": "Feature",
  "properties": {
    "iso:country":"IT",
    "sg:address":"Merceria 2 Aprile 5051/6; Venezia; 30100",
    "sg:classifiers":[
        {
            "category":"Banks & Credit Unions",
            "subcategory":"Bank",
            "type":"Services"
        }
    ],
    "sg:phone":"+39 041 521 9711",
    "wof:name":"Banco Di Sicilia",
    "wof:placetype":"venue"
},
  "geometry": {"coordinates":[12.290899,45.373199],"type":"Point"}
}