{
  "type": "Feature",
  "properties": {
    "iso:country":"IT",
    "sg:address":"57016 Rosignano Marittimo",
    "sg:city":"Rosignano Marittimo",
    "sg:orig_category":"Campeggio. Automobili E Mezzi Di Trasporto",
    "sg:phone":"+39 0586 760878",
    "sg:postcode":"57016",
    "sg:province":"Livorno",
    "wof:name":"Semboloni Adelmo",
    "wof:placetype":"venue"
},
  "geometry": {"coordinates":[10.462136,43.406693],"type":"Point"}
}