{
  "type": "Feature",
  "properties": {
    "iso:country":"IT",
    "sg:address":"1, Via Cibrario Luigi 16154 Genova",
    "sg:city":"Genova",
    "sg:classifiers":[
        {
            "category":"Autos & Motor Vehicles",
            "subcategory":"Boat Sales",
            "type":"Retail Goods"
        }
    ],
    "sg:phone":"+39 010 651 1384",
    "sg:postcode":"16154",
    "sg:province":"Genova",
    "wof:name":"Cantieri Navali Genovesi",
    "wof:placetype":"venue"
},
  "geometry": {"coordinates":[8.933989,44.407063],"type":"Point"}
}