{
  "type": "Feature",
  "properties": {
    "addr:full":"80137 Napoli Napoli Napoli 80137",
    "addr:housenumber":"80137",
    "addr:postcode":"80137",
    "iso:country":"IT",
    "sg:address":"80137 Napoli",
    "sg:city":"Napoli",
    "sg:orig_category":"Giornali, Libri E Riviste - Distribuzione E Diffusione",
    "sg:phone":"+39 081 457391",
    "sg:postcode":"80137",
    "sg:province":"Napoli",
    "wof:name":"Pironti Srl",
    "wof:placetype":"venue"
},
  "geometry": {"coordinates":[14.271605,40.944221],"type":"Point"}
}