{
  "type": "Feature",
  "properties": {
    "iso:country":"IT",
    "sg:address":"Via Fratelli Calvi 41 24060 Credaro",
    "sg:city":"Credaro",
    "sg:orig_category":"Ethylene-propylene Rubber",
    "sg:phone":"+39 035 935309",
    "sg:postcode":"24060",
    "sg:province":"Bergamo",
    "sg:website":"www.lavelgomma.it",
    "wof:name":"Lav.el. Gomma Srl",
    "wof:placetype":"venue"
},
  "geometry": {"coordinates":[9.926517,45.662014],"type":"Point"}
}