{
  "type": "Feature",
  "properties": {
    "iso:country":"IT",
    "sg:address":"Via Camurati, 36 Ang Via Manzoni 15048 Valenza",
    "sg:city":"Valenza",
    "sg:classifiers":[
        {
            "category":"Shopping",
            "subcategory":"Jewelry",
            "type":"Retail Goods"
        }
    ],
    "sg:phone":"+39 0131 954526",
    "sg:postcode":"15048",
    "sg:province":"Alessandria",
    "sg:tags":[
        "jewellery",
        "gold"
    ],
    "wof:name":"Quemme Srl",
    "wof:placetype":"venue"
},
  "geometry": {"coordinates":[8.616951,44.913216],"type":"Point"}
}