{
  "type": "Feature",
  "properties": {
    "iso:country":"IT",
    "sg:address":"Via Fatebenefratelli 15 20121 Milano",
    "sg:city":"Milano",
    "sg:classifiers":[
        {
            "category":"Transit Center",
            "subcategory":"Freight",
            "type":"Transportation"
        }
    ],
    "sg:phone":"+39 02 2900 1089",
    "sg:postcode":"20121",
    "sg:province":"Milano",
    "sg:tags":[
        "necktie"
    ],
    "sg:website":"www.danielfashion.com",
    "wof:name":"Daniel Manifattura Italiana Cravatte Snc",
    "wof:placetype":"venue"
},
  "geometry": {"coordinates":[9.193815,45.472645],"type":"Point"}
}