{
  "type": "Feature",
  "properties": {
    "iso:country":"IT",
    "sg:address":"10023 Chieri",
    "sg:city":"Chieri",
    "sg:orig_category":"Biancheria, Telerie E Coperte. Arredo Camera Letto E Complementi",
    "sg:phone":"+39 011 941 3030",
    "sg:postcode":"10023",
    "sg:province":"Torino",
    "wof:name":"Mb Snc Trapuntificio Conf.di Magarotto B. Portaro G. & C.",
    "wof:placetype":"venue"
},
  "geometry": {"coordinates":[7.878725,45.046387],"type":"Point"}
}