{
  "type": "Feature",
  "properties": {
    "addr:full":"551, V. Zamenhof 36100 Vicenza Vicenza Vicenza 36100",
    "addr:housenumber":"551",
    "addr:postcode":"36100;36100",
    "addr:street":"V. Zamenhof",
    "iso:country":"IT",
    "sg:address":"551, V. Zamenhof 36100 Vicenza",
    "sg:city":"Vicenza",
    "sg:classifiers":[
        {
            "category":"Shopping",
            "subcategory":"Jewelry",
            "type":"Retail Goods"
        }
    ],
    "sg:phone":"+39 0444 239293",
    "sg:postcode":"36100",
    "sg:province":"Vicenza",
    "sg:tags":[
        "jewellery"
    ],
    "sg:website":"http://www.caodurogold.com",
    "wof:name":"Caoduro Goldmakers",
    "wof:placetype":"venue"
},
  "geometry": {"coordinates":[11.590003,45.528736],"type":"Point"}
}