{
  "type": "Feature",
  "properties": {
    "addr:full":"Via Alfieri 92 50013 Campi Bisenzio Campi Bisenzio Firenze 50013",
    "addr:housenumber":"92",
    "addr:postcode":"50013;50013",
    "addr:street":"Via Alfieri;Bisenzio",
    "iso:country":"IT",
    "sg:address":"Via Alfieri 92 50013 Campi Bisenzio",
    "sg:city":"Campi Bisenzio",
    "sg:classifiers":[
        {
            "category":"Shopping",
            "subcategory":"Crafts & Fabrics",
            "type":"Retail Goods"
        }
    ],
    "sg:phone":"+39 055 87421",
    "sg:postcode":"50013",
    "sg:province":"Firenze",
    "sg:tags":[
        "ladies'",
        "wear"
    ],
    "sg:website":"www.falierosarti.com",
    "wof:name":"Lanificio Faliero Sarti E Figli Spa",
    "wof:placetype":"venue"
},
  "geometry": {"coordinates":[11.1270437241,43.8307800293],"type":"Point"}
}