{
  "type": "Feature",
  "properties": {
    "iso:country":"IT",
    "sg:address":"20122 Milano",
    "sg:city":"Milano",
    "sg:orig_category":"Banche E Servizi Finanziari",
    "sg:phone":"+39 02 806 8891",
    "sg:postcode":"20122",
    "sg:province":"Milano",
    "wof:name":"Abf Leasing Spa",
    "wof:placetype":"venue"
},
  "geometry": {"coordinates":[9.189885,45.458752],"type":"Point"}
}