{
  "type": "Feature",
  "properties": {
    "iso:country":"IT",
    "sg:address":"15011 Acqui Terme",
    "sg:city":"Acqui Terme",
    "sg:orig_category":"Elettrotecnica Industriale, Prodotti E Apparecchiature",
    "sg:phone":"+39 0144 359311",
    "sg:postcode":"15011",
    "sg:province":"Alessandria",
    "wof:name":"C.t.e. Costruzioni Tecno Elettriche Spa",
    "wof:placetype":"venue"
},
  "geometry": {"coordinates":[8.483903,44.679501],"type":"Point"}
}