{
  "type": "Feature",
  "properties": {
    "addr:full":"20139 Milano Milano Milano 20139",
    "addr:postcode":"20139;20139",
    "iso:country":"IT",
    "sg:address":"20139 Milano",
    "sg:city":"Milano",
    "sg:orig_category":"Scuole E Servizi Scolastici. Ricerca, Selezione E Formazione Del Personale. Pubblica Amministrazione",
    "sg:phone":"+39 02 537225",
    "sg:postcode":"20139",
    "sg:province":"Milano",
    "wof:name":"Istituto Tecnico Statale Per Il Turismo",
    "wof:placetype":"venue"
},
  "geometry": {"coordinates":[9.158166,45.445717],"type":"Point"}
}