{
  "type": "Feature",
  "properties": {
    "iso:country":"IT",
    "sg:address":"20016 Pero",
    "sg:city":"Pero",
    "sg:orig_category":"Macchine, Impianti Ed Attrezzature Industria Chimica",
    "sg:phone":"+39 02 339 5501",
    "sg:postcode":"20016",
    "sg:province":"Milano",
    "wof:name":"Rondine Azienda Petrochimica Spa",
    "wof:placetype":"venue"
},
  "geometry": {"coordinates":[9.079712,45.511955],"type":"Point"}
}