{
  "type": "Feature",
  "properties": {
    "iso:country":"IT",
    "sg:address":"9, V. Vallepiana 63039 San Benedetto Del Tronto",
    "sg:city":"San Benedetto del Tronto",
    "sg:classifiers":[
        {
            "category":"Autos & Motor Vehicles",
            "subcategory":"Automobile Sales",
            "type":"Retail Goods"
        }
    ],
    "sg:phone":"+39 0735 650324",
    "sg:postcode":"63039",
    "sg:province":"Ascoli Piceno",
    "sg:tags":[
        "industrial"
    ],
    "sg:website":"http://www.tmtcostruzioni.it",
    "wof:name":"T.m.t. Costruzioni Srl",
    "wof:placetype":"venue"
},
  "geometry": {"coordinates":[13.88501,42.900696],"type":"Point"}
}