{
  "type": "Feature",
  "properties": {
    "iso:country":"IT",
    "sg:address":"25010 Tremosine",
    "sg:city":"Tremosine",
    "sg:orig_category":"Servizi Per Lo Sport E Il Tempo Libero. Servizi Ausiliari Dei Mezzi Di Trasporto",
    "sg:phone":"+39 036 591 6018",
    "sg:postcode":"25010",
    "sg:province":"Brescia",
    "wof:name":"Garda Yachting Charter Di Pietro Scontrino & C.",
    "wof:placetype":"venue"
},
  "geometry": {"coordinates":[10.760198,45.771557],"type":"Point"}
}