{
  "type": "Feature",
  "properties": {
    "addr:full":"1, Traversa S. Domenico 80044 Ottaviano Ottaviano Napoli 80044",
    "addr:housenumber":"1",
    "addr:postcode":"80044;80044",
    "addr:street":"Traversa S. Domenico",
    "iso:country":"IT",
    "sg:address":"1, Traversa S. Domenico 80044 Ottaviano",
    "sg:city":"Ottaviano",
    "sg:classifiers":[
        {
            "category":"Manufacturing",
            "subcategory":"Glass & Minerals",
            "type":"Manufacturing & Wholesale Goods"
        }
    ],
    "sg:phone":"+39 081 338 3111",
    "sg:postcode":"80044",
    "sg:province":"Napoli",
    "wof:name":"San Domenico Vetraria Srl",
    "wof:placetype":"venue"
},
  "geometry": {"coordinates":[14.251636,40.840096],"type":"Point"}
}