{
  "type": "Feature",
  "properties": {
    "addr:full":"20020 Arese Arese Milano 20020",
    "addr:postcode":"20020;20020",
    "iso:country":"IT",
    "sg:address":"20020 Arese",
    "sg:city":"Arese",
    "sg:orig_category":"Metalli E Leghe",
    "sg:phone":"+39 02 937 7031",
    "sg:postcode":"20020",
    "sg:province":"Milano",
    "wof:name":"Coronal Spa",
    "wof:placetype":"venue"
},
  "geometry": {"coordinates":[9.0886478424,45.5345687866],"type":"Point"}
}