{
  "type": "Feature",
  "properties": {
    "addr:full":"2887, Via Fondovalle 41054 Marano Sul Panaro Marano sul Panaro Modena 41054",
    "addr:housenumber":"2887",
    "addr:postcode":"41054;41054",
    "addr:street":"Via Fondovalle",
    "iso:country":"IT",
    "sg:address":"2887, Via Fondovalle 41054 Marano Sul Panaro",
    "sg:city":"Marano sul Panaro",
    "sg:classifiers":[
        {
            "category":"Home & Garden",
            "subcategory":"Home Furnishings",
            "type":"Retail Goods"
        }
    ],
    "sg:phone":"+39 39059703151",
    "sg:postcode":"41054",
    "sg:province":"Modena",
    "sg:tags":[
        "household"
    ],
    "wof:name":"Sirotti (s.r.l.)",
    "wof:placetype":"venue"
},
  "geometry": {"coordinates":[10.920126,44.432083],"type":"Point"}
}