{
  "type": "Feature",
  "properties": {
    "iso:country":"IT",
    "sg:address":"84, Via Laghi 36056 Tezze Sul Brenta",
    "sg:city":"Tezze sul Brenta",
    "sg:classifiers":[
        {
            "category":"Home & Garden",
            "subcategory":"Home Furnishings",
            "type":"Retail Goods"
        }
    ],
    "sg:phone":"+39 0424 560534",
    "sg:postcode":"36056",
    "sg:province":"Vicenza",
    "sg:tags":[
        "household"
    ],
    "wof:name":"Zilio Mobili S.r.l.",
    "wof:placetype":"venue"
},
  "geometry": {"coordinates":[11.761621,45.678265],"type":"Point"}
}