{
  "type": "Feature",
  "properties": {
    "iso:country":"IT",
    "sg:address":"V.le Don Bosco 35 62018 Potenza Picena",
    "sg:city":"Potenza Picena",
    "sg:classifiers":[
        {
            "category":"Bus Stop",
            "subcategory":"None",
            "type":"Transportation"
        }
    ],
    "sg:phone":"+39 0733 8851",
    "sg:postcode":"62018",
    "sg:province":"Macerata",
    "sg:tags":[
        "switch",
        "contact",
        "electronic"
    ],
    "sg:website":"www.bontempi.com",
    "wof:name":"Farfisa Srl",
    "wof:placetype":"venue"
},
  "geometry": {"coordinates":[13.616762,43.363003],"type":"Point"}
}