{
  "type": "Feature",
  "properties": {
    "iso:country":"IT",
    "sg:address":"37026 Pescantina",
    "sg:city":"Pescantina",
    "sg:orig_category":"Macchine Ed Impianti Per Edilizia E Lavori Pubblici",
    "sg:phone":"+39 045 676 6597",
    "sg:postcode":"37026",
    "sg:province":"Verona",
    "wof:name":"Campagnola & Fedeli Marmomecc Srl",
    "wof:placetype":"venue"
},
  "geometry": {"coordinates":[10.917358,45.480186],"type":"Point"}
}