{
  "type": "Feature",
  "properties": {
    "iso:country":"IT",
    "sg:address":"25020 Offlaga",
    "sg:city":"Offlaga",
    "sg:orig_category":"Apparecchiature Ed Attrezzature Meccaniche",
    "sg:phone":"+39 030 979468",
    "sg:postcode":"25020",
    "sg:province":"Brescia",
    "wof:name":"Hidro - Press Di Maiandi Gianfranco & C. (s.n.c.)",
    "wof:placetype":"venue"
},
  "geometry": {"coordinates":[10.217531,45.495434],"type":"Point"}
}