{
  "type": "Feature",
  "properties": {
    "iso:country":"IT",
    "sg:address":"37133 Verona",
    "sg:city":"Verona",
    "sg:orig_category":"Acciaierie E Fonderie. Arte Ed Artigianato Artistico",
    "sg:phone":"+39 045 521087",
    "sg:postcode":"37133",
    "sg:province":"Verona",
    "wof:name":"Baroni Fonderia Artistica",
    "wof:placetype":"venue"
},
  "geometry": {"coordinates":[10.872304,45.348148],"type":"Point"}
}