{
  "type": "Feature",
  "properties": {
    "iso:country":"IT",
    "sg:address":"80017 Melito Di Napoli",
    "sg:city":"Melito di Napoli",
    "sg:orig_category":"Macchine, Impianti Ed Attrezzature Per Industria Alimentare E Bevande",
    "sg:phone":"+39 081 711 3050",
    "sg:postcode":"80017",
    "sg:province":"Napoli",
    "wof:name":"Guarino Silverio",
    "wof:placetype":"venue"
},
  "geometry": {"coordinates":[14.233781,40.919384],"type":"Point"}
}