{
  "type": "Feature",
  "properties": {
    "iso:country":"IT",
    "sg:address":"47822 Santarcangelo Di Romagna",
    "sg:city":"Santarcangelo di Romagna",
    "sg:orig_category":"Prodotti Finiti Stampati. Articoli Da Regalo. Arte Ed Artigianato Artistico. Shopping",
    "sg:phone":"+39 0541 623328",
    "sg:postcode":"47822",
    "sg:province":"Rimini",
    "wof:name":"Serigrafia 2000",
    "wof:placetype":"venue"
},
  "geometry": {"coordinates":[12.4690408707,44.0690956116],"type":"Point"}
}