{
  "type": "Feature",
  "properties": {
    "addr:full":"Via Ferrero 100 10090 Cascine Vica Torino 10090",
    "addr:housenumber":"100",
    "addr:postcode":"10090;10090",
    "addr:street":"Via Ferrero",
    "iso:country":"IT",
    "sg:address":"Via Ferrero 100 10090 Cascine Vica",
    "sg:classifiers":[
        {
            "category":"Wholesale",
            "subcategory":"Plants",
            "type":"Manufacturing & Wholesale Goods"
        }
    ],
    "sg:phone":"+39 011 957 6353",
    "sg:postcode":"10090",
    "sg:province":"Torino",
    "sg:tags":[
        "machine",
        "industrial",
        "automation"
    ],
    "sg:website":"www.chiaperotti.com",
    "wof:name":"Chiaperotti Spa",
    "wof:placetype":"venue"
},
  "geometry": {"coordinates":[7.558924,45.061798],"type":"Point"}
}