{
  "type": "Feature",
  "properties": {
    "iso:country":"IT",
    "sg:address":"95131 Catania",
    "sg:city":"Catania",
    "sg:orig_category":"Prodotti E Manufatti In Gomma",
    "sg:phone":"+39 095 534264",
    "sg:postcode":"95131",
    "sg:province":"Catania",
    "wof:name":"Cannavo Srl",
    "wof:placetype":"venue"
},
  "geometry": {"coordinates":[15.0942707062,37.5111808777],"type":"Point"}
}