{
  "type": "Feature",
  "properties": {
    "iso:country":"IT",
    "sg:address":"66020 San Giovanni Teatino",
    "sg:city":"San Giovanni Teatino",
    "sg:orig_category":"Mobili Per Ufficio",
    "sg:phone":"+39 085 446 5719",
    "sg:postcode":"66020",
    "sg:province":"Chieti",
    "wof:name":"Formica Srl",
    "wof:placetype":"venue"
},
  "geometry": {"coordinates":[14.176197052,42.415813446],"type":"Point"}
}