{
  "type": "Feature",
  "properties": {
    "addr:full":"2, Via Cardano 20041 Agrate Brianza Agrate Brianza Milano 20041",
    "addr:postcode":"20041;20041",
    "addr:street":"Via Cardano",
    "iso:country":"IT",
    "sg:address":"2, Via Cardano 20041 Agrate Brianza",
    "sg:city":"Agrate Brianza",
    "sg:classifiers":[
        {
            "category":"Wholesale",
            "subcategory":"Machinery & Supplies",
            "type":"Manufacturing & Wholesale Goods"
        }
    ],
    "sg:phone":"+39 39039656081",
    "sg:postcode":"20041",
    "sg:province":"Milano",
    "sg:tags":[
        "equipment",
        "-",
        "instrument",
        "measurement"
    ],
    "wof:name":"Tokyo Electron Italia S.p.a.",
    "wof:placetype":"venue"
},
  "geometry": {"coordinates":[9.336547,45.572495],"type":"Point"}
}