{
  "type": "Feature",
  "properties": {
    "addr:full":"6, Via Manta 12033 Moretta Moretta Cuneo 12033",
    "addr:postcode":"12033;12033",
    "addr:street":"Via Manta",
    "iso:country":"IT",
    "sg:address":"6, Via Manta 12033 Moretta",
    "sg:city":"Moretta",
    "sg:classifiers":[
        {
            "category":"Manufacturing",
            "subcategory":"Food",
            "type":"Manufacturing & Wholesale Goods"
        }
    ],
    "sg:phone":"+39 39017294067",
    "sg:postcode":"12033",
    "sg:province":"Cuneo",
    "sg:tags":[
        "equipment",
        "processing",
        "-",
        "machinery"
    ],
    "wof:name":"Prima Di Pansa Penna & C. (s.n.c.)",
    "wof:placetype":"venue"
},
  "geometry": {"coordinates":[7.5322561264,44.7530937195],"type":"Point"}
}