{
  "type": "Feature",
  "properties": {
    "iso:country":"IT",
    "sg:address":"Via Buca 45; Neviano Arduini",
    "sg:classifiers":[
        {
            "category":"Banks & Credit Unions",
            "subcategory":"Bank",
            "type":"Services"
        }
    ],
    "sg:phone":"+39 0521 843135",
    "wof:name":"Cassa Di Risparmio Di Parma, E Piacenza Spa",
    "wof:placetype":"venue"
},
  "geometry": {"coordinates":[10.315495,44.581905],"type":"Point"}
}