{
  "type": "Feature",
  "properties": {
    "addr:full":"Via Dell'industria 8 33041 Aiello Del Friuli Aiello del Friuli Udine 33041",
    "addr:housenumber":"8",
    "addr:postcode":"33041;33041",
    "addr:street":"Via Dell'Industria",
    "iso:country":"IT",
    "sg:address":"Via Dell'industria 8 33041 Aiello Del Friuli",
    "sg:city":"Aiello del Friuli",
    "sg:classifiers":[
        {
            "category":"Shopping",
            "subcategory":"Used Merchandise",
            "type":"Retail Goods"
        }
    ],
    "sg:phone":"+39 0431 99023",
    "sg:postcode":"33041",
    "sg:province":"Udine",
    "sg:tags":[
        "ribbon"
    ],
    "wof:name":"Tessitura Aiellese Srl",
    "wof:placetype":"venue"
},
  "geometry": {"coordinates":[13.349618,45.880024],"type":"Point"}
}