{
  "type": "Feature",
  "properties": {
    "addr:full":"60021 Camerano Aspio Terme Ancona 60021",
    "addr:postcode":"60021;60021",
    "iso:country":"IT",
    "sg:address":"60021 Camerano",
    "sg:city":"Aspio Terme",
    "sg:orig_category":"Prodotti E Manufatti In Materie Plastiche. Forniture Per Edilizia E Lavori Pubblici. Forniture E Materiali Per Imballaggio E Confezionamento",
    "sg:phone":"+39 071 959102",
    "sg:postcode":"60021",
    "sg:province":"Ancona",
    "wof:name":"Nuova Italiana Espansi S.r.l.",
    "wof:placetype":"venue"
},
  "geometry": {"coordinates":[13.5209589005,43.5263557434],"type":"Point"}
}