{
  "type": "Feature",
  "properties": {
    "iso:country":"IT",
    "sg:address":"51100 Pistoia",
    "sg:city":"Pistoia",
    "sg:orig_category":"Arredamento Uffici",
    "sg:phone":"+39 0573 22160",
    "sg:postcode":"51100",
    "sg:province":"Pistoia",
    "wof:name":"Toscodata Srl",
    "wof:placetype":"venue"
},
  "geometry": {"coordinates":[10.897873,43.932137],"type":"Point"}
}