{
  "type": "Feature",
  "properties": {
    "addr:full":"20122 Milano Milano Milano 20122",
    "addr:postcode":"20122;20122",
    "iso:country":"IT",
    "sg:address":"20122 Milano",
    "sg:city":"Milano",
    "sg:orig_category":"Piastrelle Per Pavimenti E Rivestimenti",
    "sg:phone":"+39 02 7639 8106",
    "sg:postcode":"20122",
    "sg:province":"Milano",
    "wof:name":"Geologica Milano Srl",
    "wof:placetype":"venue"
},
  "geometry": {"coordinates":[9.1987752914,45.4631996155],"type":"Point"}
}