{
  "type": "Feature",
  "properties": {
    "iso:country":"IT",
    "sg:address":"22, Via Lombardia 20040 Bellusco",
    "sg:city":"Bellusco",
    "sg:classifiers":[
        {
            "category":"Manufacturing",
            "subcategory":"Glass & Minerals",
            "type":"Manufacturing & Wholesale Goods"
        }
    ],
    "sg:phone":"+39 039 606 7260",
    "sg:postcode":"20040",
    "sg:province":"Milano",
    "wof:name":"Artevetro Serena",
    "wof:placetype":"venue"
},
  "geometry": {"coordinates":[9.415891,45.61351],"type":"Point"}
}