{
  "type": "Feature",
  "properties": {
    "iso:country":"IT",
    "sg:address":"10123 Torino",
    "sg:city":"Torino",
    "sg:orig_category":"Sport - Articoli E Forniture",
    "sg:phone":"+39 011 562 0254",
    "sg:postcode":"10123",
    "sg:province":"Torino",
    "wof:name":"Armeria Nord Ovest (s.r.l.)",
    "wof:placetype":"venue"
},
  "geometry": {"coordinates":[7.686757,45.063103],"type":"Point"}
}