{
  "type": "Feature",
  "properties": {
    "addr:full":"00157 Roma Roma Roma 00157",
    "addr:postcode":"00157;00157",
    "iso:country":"IT",
    "sg:address":"00157 Roma",
    "sg:city":"Roma",
    "sg:orig_category":"Accessori Dei Mezzi Di Trasporto",
    "sg:phone":"+39 06 450 1586",
    "sg:postcode":"00157",
    "sg:province":"Roma",
    "wof:name":"Visa Motors & Yachts Srl",
    "wof:placetype":"venue"
},
  "geometry": {"coordinates":[12.544421,41.917988],"type":"Point"}
}