{
  "type": "Feature",
  "properties": {
    "addr:full":"30030 Salzano Salzano Venezia 30030",
    "addr:postcode":"30030;30030",
    "iso:country":"IT",
    "sg:address":"30030 Salzano",
    "sg:city":"Salzano",
    "sg:orig_category":"Centri Di Estetica E Cosmesi E Servizi",
    "sg:phone":"+39 041 574 6355",
    "sg:postcode":"30030",
    "sg:province":"Venezia",
    "sg:website":"http://www.esteticaparadise.it",
    "wof:name":"Estetica Paradise Sas Di Scarpa C. & Scarpa M. & C",
    "wof:placetype":"venue"
},
  "geometry": {"coordinates":[12.2552585602,45.4934043884],"type":"Point"}
}