{
  "type": "Feature",
  "properties": {
    "addr:full":"58100 Grosseto Grosseto Grosseto 58100",
    "addr:postcode":"58100;58100",
    "iso:country":"IT",
    "sg:address":"58100 Grosseto",
    "sg:city":"Grosseto",
    "sg:classifiers":[
        {
            "category":"Autos & Motor Vehicles",
            "subcategory":"Fuel & Gas Station",
            "type":"Retail Goods"
        }
    ],
    "sg:phone":"+39 0564 416409",
    "sg:postcode":"58100",
    "sg:province":"Grosseto",
    "sg:tags":[
        "activities",
        "industrial",
        "instrument",
        "equipment",
        "pumps",
        "machines"
    ],
    "wof:name":"F.a.m. Snc",
    "wof:placetype":"venue"
},
  "geometry": {"coordinates":[11.1079645157,42.7450294495],"type":"Point"}
}