{
  "type": "Feature",
  "properties": {
    "addr:full":"57121 Livorno Livorno Livorno 57121",
    "addr:postcode":"57121;57121",
    "iso:country":"IT",
    "sg:address":"57121 Livorno",
    "sg:city":"Livorno",
    "sg:orig_category":"Trasporti E Spedizioni Merci",
    "sg:phone":"+39 0586 420999",
    "sg:postcode":"57121",
    "sg:province":"Livorno",
    "sg:website":"http://www.sosema-ship-supply.com",
    "wof:name":"So.se.ma. Srl",
    "wof:placetype":"venue"
},
  "geometry": {"coordinates":[10.353201,43.57354],"type":"Point"}
}