{
  "type": "Feature",
  "properties": {
    "iso:country":"IT",
    "sg:address":"09072 Cabras",
    "sg:city":"Cabras",
    "sg:orig_category":"Vini E Spumanti - Produzione E Ingrosso",
    "sg:phone":"+39 0783 290806",
    "sg:postcode":"09072",
    "sg:province":"Oristano",
    "wof:name":"Azienda Vinicola Attilio Contini Spa",
    "wof:placetype":"venue"
},
  "geometry": {"coordinates":[8.528835,39.93362],"type":"Point"}
}