{
  "type": "Feature",
  "properties": {
    "iso:country":"IT",
    "sg:address":"Via Cristoforo Colombo, 212; Roma; 00145",
    "sg:city":"Roma",
    "sg:classifiers":[
        {
            "category":"Travel",
            "subcategory":"Travel Agent",
            "type":"Entertainment"
        }
    ],
    "sg:postcode":"00145",
    "sg:province":"Roma",
    "sg:website":"regione.lazio.it",
    "wof:name":"Latium Region",
    "wof:placetype":"venue"
},
  "geometry": {"coordinates":[12.489189,41.853645],"type":"Point"}
}