{
  "type": "Feature",
  "properties": {
    "iso:country":"IT",
    "sg:address":"00015 Monterotondo",
    "sg:city":"Monterotondo",
    "sg:orig_category":"Macchine Ed Impianti Per Edilizia E Lavori Pubblici",
    "sg:phone":"+39 06 906 0095",
    "sg:postcode":"00015",
    "sg:province":"Roma",
    "wof:name":"Saveco Srl",
    "wof:placetype":"venue"
},
  "geometry": {"coordinates":[12.591771,42.076248],"type":"Point"}
}