{
  "type": "Feature",
  "properties": {
    "iso:country":"IT",
    "sg:address":"21054 Fagnano Olona",
    "sg:city":"Fagnano Olona",
    "sg:orig_category":"Cavi E Conduttori Elettrici E Telefonici",
    "sg:phone":"+39 0331 617331",
    "sg:postcode":"21054",
    "sg:province":"Varese",
    "wof:name":"Stamplastic Srl",
    "wof:placetype":"venue"
},
  "geometry": {"coordinates":[8.870319,45.668877],"type":"Point"}
}