{
  "type": "Feature",
  "properties": {
    "iso:country":"IT",
    "sg:address":"00053 Civitavecchia",
    "sg:city":"Civitavecchia",
    "sg:orig_category":"Arredo Cucina Ed Elettrodomestici. Elettrodomestici",
    "sg:phone":"+39 0766 24387",
    "sg:postcode":"00053",
    "sg:province":"Roma",
    "wof:name":"Audia Di Nardini Andrea E Marzi Massimiliano Snc",
    "wof:placetype":"venue"
},
  "geometry": {"coordinates":[11.820757,42.115593],"type":"Point"}
}