{
  "type": "Feature",
  "properties": {
    "addr:full":"25121 Brescia Brescia Brescia 25121",
    "addr:postcode":"25121;25121",
    "iso:country":"IT",
    "sg:address":"25121 Brescia",
    "sg:city":"Brescia",
    "sg:orig_category":"Servizi Per Lo Sport E Il Tempo Libero. Servizi Vari Di Interesse Pubblico",
    "sg:phone":"+39 030 295939",
    "sg:postcode":"25121",
    "sg:province":"Brescia",
    "wof:name":"Agenzia Ippica Samba Di Ruscalla C. & C. (s.n.c.)",
    "wof:placetype":"venue"
},
  "geometry": {"coordinates":[10.229219,45.531303],"type":"Point"}
}