{
  "type": "Feature",
  "properties": {
    "iso:country":"IT",
    "sg:address":"42019 Scandiano",
    "sg:orig_category":"Materie Plastiche In Granuli, Polveri E Pasta",
    "sg:phone":"+39 0522 854473",
    "sg:postcode":"42019",
    "sg:province":"Reggio Nell'Emilia",
    "wof:name":"S.e.a.r. Snc",
    "wof:placetype":"venue"
},
  "geometry": {"coordinates":[10.674072,44.623127],"type":"Point"}
}