{
  "type": "Feature",
  "properties": {
    "addr:full":"94010 Centuripe Centuripe Enna 94010",
    "addr:postcode":"94010;94010",
    "iso:country":"IT",
    "sg:address":"94010 Centuripe",
    "sg:city":"Centuripe",
    "sg:orig_category":"Ceramiche: Prodotti E Lavorazioni. Articoli Da Regalo. Arte Ed Artigianato Artistico. Shopping",
    "sg:phone":"+39 0935 73361",
    "sg:postcode":"94010",
    "sg:province":"Enna",
    "wof:name":"Ken Art Ceramiche",
    "wof:placetype":"venue"
},
  "geometry": {"coordinates":[14.289562,37.552757],"type":"Point"}
}