{
  "type": "Feature",
  "properties": {
    "iso:country":"IT",
    "sg:address":"95125 Catania",
    "sg:city":"Catania",
    "sg:orig_category":"Odontotecnici - Laboratori",
    "sg:phone":"+39 095 449587",
    "sg:postcode":"95125",
    "sg:province":"Catania",
    "wof:name":"O.b.s. Di Benintende Sebastiano - Laboratorio Ortodontico",
    "wof:placetype":"venue"
},
  "geometry": {"coordinates":[15.082469,37.515678],"type":"Point"}
}