{
  "type": "Feature",
  "properties": {
    "iso:country":"IT",
    "sg:address":"53040 Radicofani",
    "sg:city":"Radicofani",
    "sg:orig_category":"Ospedali E Servizi Sanitari",
    "sg:phone":"+39 0578 52036",
    "sg:postcode":"53040",
    "sg:province":"Siena",
    "wof:name":"Masci Cinagli Angela",
    "wof:placetype":"venue"
},
  "geometry": {"coordinates":[11.771111,42.896572],"type":"Point"}
}