{
  "type": "Feature",
  "properties": {
    "iso:country":"IT",
    "sg:address":"5, Via De Ponti 26010 Dovera",
    "sg:city":"Dovera",
    "sg:classifiers":[
        {
            "category":"Manufacturing",
            "subcategory":"Tools & Machinery",
            "type":"Manufacturing & Wholesale Goods"
        }
    ],
    "sg:phone":"+39 0373 978278",
    "sg:postcode":"26010",
    "sg:province":"Cremona",
    "sg:tags":[
        "environment",
        "equipment",
        "-"
    ],
    "wof:name":"Same Di Eredi Marzagalli (s.n.c.)",
    "wof:placetype":"venue"
},
  "geometry": {"coordinates":[9.54708,45.362633],"type":"Point"}
}