{
  "type": "Feature",
  "properties": {
    "iso:country":"IT",
    "sg:address":"Postino; 26010",
    "sg:classifiers":[
        {
            "category":"Banks & Credit Unions",
            "subcategory":"Bank",
            "type":"Services"
        }
    ],
    "sg:phone":"+39 0373 94014",
    "sg:postcode":"26010",
    "sg:province":"Cremona",
    "wof:name":"Cassa Rurale Ed Artigiana, Di Postino",
    "wof:placetype":"venue"
},
  "geometry": {"coordinates":[9.554115,45.363117],"type":"Point"}
}