{
  "type": "Feature",
  "properties": {
    "iso:country":"IT",
    "sg:address":"44039 Final Di Rero",
    "sg:city":"Final di Rero",
    "sg:orig_category":"Prodotti Vari In Metallo. Articoli Per Imballaggio E Confezionamento",
    "sg:phone":"+39 0533 602006",
    "sg:postcode":"44039",
    "sg:province":"Ferrara",
    "wof:name":"A.r.a. Di Pocaterra Abdon & C. S.d.f.",
    "wof:placetype":"venue"
},
  "geometry": {"coordinates":[11.8768520355,44.8082275391],"type":"Point"}
}