{
  "type": "Feature",
  "properties": {
    "addr:full":"7/bis, Via Arno' Riccardo 10151 Torino Torino Torino 10151",
    "addr:housenumber":"7 / bis",
    "addr:postcode":"10151;10151",
    "addr:street":"Via Arno ' Riccardo",
    "iso:country":"IT",
    "sg:address":"7/bis, Via Arno' Riccardo 10151 Torino",
    "sg:city":"Torino",
    "sg:classifiers":[
        {
            "category":"Manufacturing",
            "subcategory":"Printing",
            "type":"Manufacturing & Wholesale Goods"
        }
    ],
    "sg:phone":"+39 011 455 9550",
    "sg:postcode":"10151",
    "sg:province":"Torino",
    "sg:tags":[
        "publishing"
    ],
    "wof:name":"Cartotecnica Taglietti Di Virbino Enzo & C. S.a.s.",
    "wof:placetype":"venue"
},
  "geometry": {"coordinates":[7.6866188049,45.0705604553],"type":"Point"}
}