{
  "type": "Feature",
  "properties": {
    "iso:country":"IT",
    "sg:address":"64032 Atri",
    "sg:city":"Atri",
    "sg:orig_category":"Vetrerie Artistiche - Produzione E Ingrosso",
    "sg:phone":"+39 085 87363",
    "sg:postcode":"64032",
    "sg:province":"Teramo",
    "sg:website":"http://www.paginegialle.it/camper",
    "wof:name":"Maglione Anna",
    "wof:placetype":"venue"
},
  "geometry": {"coordinates":[13.976793,42.582821],"type":"Point"}
}