{
  "type": "Feature",
  "properties": {
    "addr:full":"30010 Camponogara Camponogara Venezia 30010",
    "addr:postcode":"30010;30010",
    "iso:country":"IT",
    "sg:address":"30010 Camponogara",
    "sg:city":"Camponogara",
    "sg:orig_category":"Servizi E Lavori Per Arredamento E Industria Del Legno. Vetro: Prodotti E Lavorazioni",
    "sg:phone":"+39 041 462285",
    "sg:postcode":"30010",
    "sg:province":"Venezia",
    "wof:name":"Vetreria Fasolato Snc",
    "wof:placetype":"venue"
},
  "geometry": {"coordinates":[12.072398,45.383408],"type":"Point"}
}