{
  "type": "Feature",
  "properties": {
    "iso:country":"IT",
    "sg:address":"24020 Torre Boldone",
    "sg:city":"Torre Boldone",
    "sg:orig_category":"Automazione E Macchine Per Ufficio. Servizi Ausiliari Di Certificati, Riproduzioni, Disegni E Foto",
    "sg:phone":"+39 035 344246",
    "sg:postcode":"24020",
    "sg:province":"Bergamo",
    "wof:name":"Fondazione Alasca",
    "wof:placetype":"venue"
},
  "geometry": {"coordinates":[9.704786,45.714783],"type":"Point"}
}