{
  "type": "Feature",
  "properties": {
    "iso:country":"IT",
    "sg:address":"20091 Bresso",
    "sg:city":"Bresso",
    "sg:orig_category":"Termotecnica E Riscaldamento, Apparecchiature E Servizi",
    "sg:phone":"+39 02 610 8059",
    "sg:postcode":"20091",
    "sg:province":"Milano",
    "wof:name":"Wago Power Bruciatori (s.r.l.)",
    "wof:placetype":"venue"
},
  "geometry": {"coordinates":[9.18452,45.53957],"type":"Point"}
}