{
  "type": "Feature",
  "properties": {
    "iso:country":"IT",
    "sg:address":"9, Via Pavoni Lodovico 25128 Brescia",
    "sg:city":"Brescia",
    "sg:classifiers":[
        {
            "category":"Professional",
            "subcategory":"Printing & Photocopies",
            "type":"Services"
        }
    ],
    "sg:phone":"+39 39030300261",
    "sg:postcode":"25128",
    "sg:province":"Brescia",
    "wof:name":"Com & Print Srl",
    "wof:placetype":"venue"
},
  "geometry": {"coordinates":[10.2229576111,45.5398292542],"type":"Point"}
}