{
  "type": "Feature",
  "properties": {
    "addr:full":"92027 Licata Licata Agrigento 92027",
    "addr:postcode":"92027;92027",
    "iso:country":"IT",
    "sg:address":"92027 Licata",
    "sg:city":"Licata",
    "sg:orig_category":"Servizi Per Lo Sport E Il Tempo Libero. Ristoranti Ed Esercizi Affini. Servizi Ausiliari Di Ristorazione E Di Intrattenimento",
    "sg:phone":"+39 0922 801777",
    "sg:postcode":"92027",
    "sg:province":"Agrigento",
    "wof:name":"Faraci Rosa Blu Garden",
    "wof:placetype":"venue"
},
  "geometry": {"coordinates":[13.937602,37.130039],"type":"Point"}
}