{
  "type": "Feature",
  "properties": {
    "iso:country":"IT",
    "sg:address":"1/c, Via Albero 37040 Roveredo Di Gua'",
    "sg:classifiers":[
        {
            "category":"Professional",
            "subcategory":"Advertising",
            "type":"Services"
        }
    ],
    "sg:phone":"+39 39044286315",
    "sg:postcode":"37040",
    "sg:province":"Verona",
    "sg:tags":[
        "communication",
        "medium"
    ],
    "wof:name":"Fotoceramica Bertelli Silvio & C. (s.n.c.)",
    "wof:placetype":"venue"
},
  "geometry": {"coordinates":[10.991748,45.438366],"type":"Point"}
}