{
  "type": "Feature",
  "properties": {
    "addr:full":"37060 Castel D'azzano Azzano Verona 37060",
    "addr:postcode":"37060;37060",
    "iso:country":"IT",
    "sg:address":"37060 Castel D'azzano",
    "sg:city":"Azzano",
    "sg:orig_category":"Saldatura E Taglio - Impianti Ed Attrezzature",
    "sg:phone":"+39 045 852 0944",
    "sg:postcode":"37060",
    "sg:province":"Verona",
    "sg:website":"http://www.lippasrl.com",
    "wof:name":"Lippa Srl",
    "wof:placetype":"venue"
},
  "geometry": {"coordinates":[10.956391,45.361916],"type":"Point"}
}