{
  "type": "Feature",
  "properties": {
    "iso:country":"IT",
    "sg:address":"10146 Torino",
    "sg:city":"Torino",
    "sg:orig_category":"Associazioni Ed Organismi Di Interesse Pubblico",
    "sg:phone":"+39 011 776 4744",
    "sg:postcode":"10146",
    "sg:province":"Torino",
    "wof:name":"Associazione Naz.alpini",
    "wof:placetype":"venue"
},
  "geometry": {"coordinates":[7.120077,45.126019],"type":"Point"}
}