{
  "type": "Feature",
  "properties": {
    "addr:full":"56, Via Fiano 10070 Varisella Fiano Torino 10070",
    "addr:postcode":"10070;10070",
    "addr:street":"Via Fiano",
    "iso:country":"IT",
    "sg:address":"56, Via Fiano 10070 Varisella",
    "sg:city":"Fiano",
    "sg:classifiers":[
        {
            "category":"Shopping",
            "type":"Retail Goods"
        }
    ],
    "sg:phone":"+39 011 924 9343",
    "sg:postcode":"10070",
    "sg:province":"Torino",
    "sg:tags":[
        "finished",
        "-",
        "metallic"
    ],
    "wof:name":"Otcm Di Caglio Giuseppe",
    "wof:placetype":"venue"
},
  "geometry": {"coordinates":[7.4858326912,45.209487915],"type":"Point"}
}