{
  "type": "Feature",
  "properties": {
    "addr:full":"37032 Monteforte D'alpone Verona 37032",
    "addr:postcode":"37032;37032",
    "iso:country":"IT",
    "sg:address":"37032 Monteforte D'alpone",
    "sg:classifiers":[
        {
            "category":"Professional",
            "subcategory":"Advertising",
            "type":"Services"
        }
    ],
    "sg:phone":"+39 045 610 1158",
    "sg:postcode":"37032",
    "sg:province":"Verona",
    "sg:tags":[
        "marketing",
        "communication"
    ],
    "sg:website":"http://www.rcpromotion.com",
    "wof:name":"R. & C. Promotion Srl",
    "wof:placetype":"venue"
},
  "geometry": {"coordinates":[11.283405,45.41692],"type":"Point"}
}