{
  "type": "Feature",
  "properties": {
    "iso:country":"IT",
    "sg:address":"00187 Roma",
    "sg:city":"Roma",
    "sg:orig_category":"Teatri",
    "sg:phone":"+39 06 679 1439",
    "sg:postcode":"00187",
    "sg:province":"Roma",
    "wof:name":"Teatro Salone Margherita Il Bagaglino",
    "wof:placetype":"venue"
},
  "geometry": {"coordinates":[12.484384,41.903854],"type":"Point"}
}