{
  "type": "Feature",
  "properties": {
    "iso:country":"IT",
    "sg:address":"Via O. Respighi 6/b 50018 Scandicci",
    "sg:city":"Scandicci",
    "sg:classifiers":[
        {
            "category":"Shopping",
            "subcategory":"Clothing, Apparel, & Fashions",
            "type":"Retail Goods"
        }
    ],
    "sg:phone":"+39 055 751662",
    "sg:postcode":"50018",
    "sg:province":"Firenze",
    "sg:tags":[
        "blouse",
        "ladies'",
        "dress"
    ],
    "wof:name":"Straccali Lorenzo",
    "wof:placetype":"venue"
},
  "geometry": {"coordinates":[11.169543,43.763397],"type":"Point"}
}