{
  "type": "Feature",
  "properties": {
    "iso:country":"IT",
    "sg:address":"35016 Piazzola Sul Brenta",
    "sg:city":"Piazzola sul Brenta",
    "sg:orig_category":"Trattamenti Termici E Superficiali Metalli, Galvanotecnica",
    "sg:phone":"+39 049 559 1345",
    "sg:postcode":"35016",
    "sg:province":"Padova",
    "wof:name":"Stc Snc",
    "wof:placetype":"venue"
},
  "geometry": {"coordinates":[11.82801,45.508438],"type":"Point"}
}