{
  "type": "Feature",
  "properties": {
    "iso:country":"IT",
    "sg:address":"37040 Terrazzo",
    "sg:city":"Terrazzo",
    "sg:orig_category":"Mobili Artistici In Stile - Produzione E Ingrosso",
    "sg:phone":"+39 0442 94112",
    "sg:postcode":"37040",
    "sg:province":"Verona",
    "wof:name":"Fratelli Bubola Di Bubola Stefano & C. Snc",
    "wof:placetype":"venue"
},
  "geometry": {"coordinates":[11.3905420303,45.1733283997],"type":"Point"}
}