{
  "type": "Feature",
  "properties": {
    "iso:country":"IT",
    "sg:address":"62014 Corridonia",
    "sg:city":"Corridonia",
    "sg:orig_category":"Antifurto",
    "sg:phone":"+39 0733 281233",
    "sg:postcode":"62014",
    "sg:province":"Macerata",
    "wof:name":"Cem Srl",
    "wof:placetype":"venue"
},
  "geometry": {"coordinates":[13.487051,43.266212],"type":"Point"}
}