{
  "type": "Feature",
  "properties": {
    "iso:country":"IT",
    "sg:address":"89122 Reggio Calabria",
    "sg:orig_category":"Box Prefabbricati",
    "sg:phone":"+39 0965 644480",
    "sg:province":"RC",
    "wof:name":"Ci.effe Service E Management Srl",
    "wof:placetype":"venue"
},
  "geometry": {"coordinates":[15.667647,38.124836],"type":"Point"}
}