{
  "type": "Feature",
  "properties": {
    "addr:full":"90011 Bagheria Bagheria Palermo 90011",
    "addr:postcode":"90011;90011",
    "iso:country":"IT",
    "sg:address":"90011 Bagheria",
    "sg:city":"Bagheria",
    "sg:orig_category":"Materiali Edili",
    "sg:phone":"+39 091 931287",
    "sg:postcode":"90011",
    "sg:province":"Palermo",
    "wof:name":"Tripoli Domenico Olaf",
    "wof:placetype":"venue"
},
  "geometry": {"coordinates":[13.461237,38.059669],"type":"Point"}
}