{
  "type": "Feature",
  "properties": {
    "addr:full":"63100 Ascoli Piceno Ascoli Piceno Ascoli Piceno 63100",
    "addr:postcode":"63100;63100",
    "iso:country":"IT",
    "sg:address":"63100 Ascoli Piceno",
    "sg:city":"Ascoli Piceno",
    "sg:orig_category":"Alluminio E Leghe",
    "sg:phone":"+39 0736 43302",
    "sg:postcode":"63100",
    "sg:province":"Ascoli Piceno",
    "wof:name":"Castelli Giuseppe",
    "wof:placetype":"venue"
},
  "geometry": {"coordinates":[13.644351,42.84531],"type":"Point"}
}