{
  "type": "Feature",
  "properties": {
    "iso:country":"IT",
    "sg:address":"37036 San Martino Buon Albergo",
    "sg:city":"San Martino Buon Albergo",
    "sg:orig_category":"Spedizioni Aeree, Marittime E Terrestri",
    "sg:phone":"+39 045 878 0310",
    "sg:postcode":"37036",
    "sg:province":"Verona",
    "wof:name":"Mt Srl",
    "wof:placetype":"venue"
},
  "geometry": {"coordinates":[11.108653,45.420353],"type":"Point"}
}