{
  "type": "Feature",
  "properties": {
    "iso:country":"IT",
    "sg:address":"20145 Milano",
    "sg:city":"Milano",
    "sg:orig_category":"Studi E Consulenze Amministrative, Commerciali E Aziendali. Banche E Servizi Finanziari. Agenzie D'affari E Servizi Commerciali. Consulenze Tecniche, Amministrative E Perizie",
    "sg:phone":"+39 02 469 5741",
    "sg:postcode":"20145",
    "sg:province":"Milano",
    "sg:website":"http://www.export-drive.com",
    "wof:name":"Aitec Srl",
    "wof:placetype":"venue"
},
  "geometry": {"coordinates":[9.163954,45.471054],"type":"Point"}
}