{
  "type": "Feature",
  "properties": {
    "addr:full":"40139 Bologna Bologna Bologna 40139",
    "addr:postcode":"40139;40139",
    "iso:country":"IT",
    "sg:address":"40139 Bologna",
    "sg:city":"Bologna",
    "sg:orig_category":"Imprese Di Costruzioni Civili Ed Industriali. Servizi E Lavori Per Ecologia E Smaltimento Rifiuti",
    "sg:phone":"+39 051 462302",
    "sg:postcode":"40139",
    "sg:province":"Bologna",
    "wof:name":"Impresa Loro Giovanni Srl",
    "wof:placetype":"venue"
},
  "geometry": {"coordinates":[11.394464,44.483433],"type":"Point"}
}