{
  "type": "Feature",
  "properties": {
    "iso:country":"IT",
    "sg:address":"24050 Calcinate",
    "sg:city":"Calcinate",
    "sg:classifiers":[
        {
            "category":"Manufacturing",
            "subcategory":"Tools & Machinery",
            "type":"Manufacturing & Wholesale Goods"
        }
    ],
    "sg:phone":"+39 035 442 3151",
    "sg:postcode":"24050",
    "sg:province":"Bergamo",
    "sg:tags":[
        "machining",
        "mechanical"
    ],
    "wof:name":"Co.me.do. Srl",
    "wof:placetype":"venue"
},
  "geometry": {"coordinates":[9.824924,45.596554],"type":"Point"}
}