{
  "type": "Feature",
  "properties": {
    "iso:country":"IT",
    "sg:address":"50019 Sesto Fiorentino",
    "sg:city":"Sesto Fiorentino",
    "sg:orig_category":"Automobili E Mezzi Di Trasporto. Riparazione Dei Mezzi Di Trasporto",
    "sg:phone":"+39 055 449 4082",
    "sg:postcode":"50019",
    "sg:province":"Firenze",
    "sg:website":"http://www.desmoquattro.it",
    "wof:name":"Officine Desmoquattro Di Galeotti Luca",
    "wof:placetype":"venue"
},
  "geometry": {"coordinates":[11.194633,43.835773],"type":"Point"}
}