{
  "type": "Feature",
  "properties": {
    "iso:country":"IT",
    "sg:address":"10155 Torino",
    "sg:city":"Torino",
    "sg:orig_category":"Bagno - Accessori E Mobili",
    "sg:phone":"+39 011 242 4108",
    "sg:postcode":"10155",
    "sg:province":"Torino",
    "wof:name":"S.a.e. Di Schirripa Anna Rita",
    "wof:placetype":"venue"
},
  "geometry": {"coordinates":[7.693903,45.096745],"type":"Point"}
}