{
  "type": "Feature",
  "properties": {
    "iso:country":"IT",
    "sg:address":"20132 Milano",
    "sg:city":"Milano",
    "sg:orig_category":"Motori Ed Organi Di Trasmissione",
    "sg:postcode":"20132",
    "sg:province":"Milano",
    "wof:name":"Ce.pi Cesati Piacentini (s.r.l.)",
    "wof:placetype":"venue"
},
  "geometry": {"coordinates":[9.2455425262,45.5038299561],"type":"Point"}
}