{
  "type": "Feature",
  "properties": {
    "iso:country":"IT",
    "sg:address":"Zona Industriale Udinese Loc. Lauza 33050 Pavia Di Udine",
    "sg:city":"Pavia di Udine",
    "sg:classifiers":[
        {
            "category":"Government",
            "subcategory":"Court House",
            "type":"Public Place"
        }
    ],
    "sg:phone":"+39 0432 675513",
    "sg:postcode":"33050",
    "sg:province":"Udine",
    "sg:tags":[
        "accommodation",
        "furniture"
    ],
    "sg:website":"www.softline-allkit.com",
    "wof:name":"All Kit Srl",
    "wof:placetype":"venue"
},
  "geometry": {"coordinates":[13.230724,46.064941],"type":"Point"}
}