{
  "type": "Feature",
  "properties": {
    "addr:full":"9, Via Grazia 40069 Zola Predosa Zola Bologna 40069",
    "addr:postcode":"40069;40069",
    "addr:street":"Via Grazia",
    "iso:country":"IT",
    "sg:address":"9, Via Grazia 40069 Zola Predosa",
    "sg:city":"Zola",
    "sg:classifiers":[
        {
            "category":"Professional",
            "subcategory":"Engineering",
            "type":"Services"
        }
    ],
    "sg:phone":"+39 39051752275",
    "sg:postcode":"40069",
    "sg:province":"Bologna",
    "sg:tags":[
        "machine",
        "-",
        "mechanical"
    ],
    "wof:name":"Rivelica Industriale (s.r.l.)",
    "wof:placetype":"venue"
},
  "geometry": {"coordinates":[11.236042,44.502331],"type":"Point"}
}