{
  "type": "Feature",
  "properties": {
    "iso:country":"IT",
    "sg:address":"50014 Fiesole",
    "sg:city":"Fiesole",
    "sg:orig_category":"Studi E Consulenze Tecniche E Industriali. Servizi E Lavori Per Edilizia E Lavori Pubblici. Professionisti - Studi E Servizi Ed Associazioni Di Interesse Aziendale",
    "sg:phone":"+39 055 540690",
    "sg:postcode":"50014",
    "sg:province":"Firenze",
    "wof:name":"Bonelli Riccardo",
    "wof:placetype":"venue"
},
  "geometry": {"coordinates":[11.338279,43.845325],"type":"Point"}
}