{
  "type": "Feature",
  "properties": {
    "iso:country":"IT",
    "sg:address":"15011 Acqui Terme",
    "sg:city":"Acqui Terme",
    "sg:orig_category":"Medici Specialisti - Angiologia",
    "sg:phone":"+39 0144 320154",
    "sg:postcode":"15011",
    "sg:province":"Alessandria",
    "wof:name":"Ivaldi Dr. Claudio",
    "wof:placetype":"venue"
},
  "geometry": {"coordinates":[8.472935,44.67292],"type":"Point"}
}