{
  "type": "Feature",
  "properties": {
    "iso:country":"IT",
    "sg:address":"22066 Mariano Comense",
    "sg:city":"Mariano Comense",
    "sg:orig_category":"Dolciumi E Gelati",
    "sg:postcode":"22066",
    "sg:province":"Como",
    "wof:name":"Mondial Miele S.a.s.",
    "wof:placetype":"venue"
},
  "geometry": {"coordinates":[9.172262,45.699215],"type":"Point"}
}