{
  "type": "Feature",
  "properties": {
    "iso:country":"IT",
    "sg:address":"37063 Tarmassia",
    "sg:city":"Tarmassia",
    "sg:orig_category":"Forniture E Materiali Per Imballaggio E Confezionamento",
    "sg:phone":"+39 045 733 5181",
    "sg:postcode":"37063",
    "sg:province":"Verona",
    "wof:name":"Zanda Walter",
    "wof:placetype":"venue"
},
  "geometry": {"coordinates":[11.0586080551,45.2669639587],"type":"Point"}
}