{
  "type": "Feature",
  "properties": {
    "iso:country":"IT",
    "sg:address":"Via Forgaria 7 33078 San Vito Al Tagliamento",
    "sg:city":"San Vito al Tagliamento",
    "sg:classifiers":[
        {
            "category":"Organizations",
            "subcategory":"Membership Organization",
            "type":"Services"
        }
    ],
    "sg:phone":"+39 0434 85183",
    "sg:postcode":"33078",
    "sg:province":"Pordenone",
    "sg:tags":[
        "control",
        "electronic",
        "component",
        "system",
        "controls"
    ],
    "sg:website":"www.atex.it",
    "wof:name":"Atex Spa",
    "wof:placetype":"venue"
},
  "geometry": {"coordinates":[12.879382,45.944057],"type":"Point"}
}