{
  "type": "Feature",
  "properties": {
    "iso:country":"IT",
    "sg:address":"26029 Soncino",
    "sg:city":"Soncino",
    "sg:orig_category":"Servizi E Lavori Per Abbigliamento E Pelletterie",
    "sg:phone":"+39 0374 85093",
    "sg:postcode":"26029",
    "sg:province":"Cremona",
    "wof:name":"Cappetti Silvia",
    "wof:placetype":"venue"
},
  "geometry": {"coordinates":[10.027497,45.135586],"type":"Point"}
}