{
  "type": "Feature",
  "properties": {
    "addr:full":"30026 Portogruaro Portogruaro Venezia 30026",
    "addr:postcode":"30026;30026",
    "iso:country":"IT",
    "sg:address":"30026 Portogruaro",
    "sg:city":"Portogruaro",
    "sg:orig_category":"Macchine Ed Impianti Per Edilizia E Lavori Pubblici",
    "sg:phone":"+39 0421 280003",
    "sg:postcode":"30026",
    "sg:province":"Venezia",
    "wof:name":"Taurus & Co. S.r.l.",
    "wof:placetype":"venue"
},
  "geometry": {"coordinates":[12.848577,45.778072],"type":"Point"}
}