{
  "type": "Feature",
  "properties": {
    "addr:full":"Via Della Galdina 20010 Arluno Arluno Milano 20010",
    "addr:postcode":"20010;20010",
    "addr:street":"Via Della Galdina",
    "iso:country":"IT",
    "sg:address":"Via Della Galdina 20010 Arluno",
    "sg:city":"Arluno",
    "sg:orig_category":"Aluminium-glass Fa\u00e7ades",
    "sg:phone":"+39 02 901 5762",
    "sg:postcode":"20010",
    "sg:province":"Milano",
    "sg:website":"www.metalsigma.it",
    "wof:name":"Metalsigma Tunesi S.p.a.",
    "wof:placetype":"venue"
},
  "geometry": {"coordinates":[9.188141,45.463688],"type":"Point"}
}