{
  "type": "Feature",
  "properties": {
    "iso:country":"IT",
    "sg:address":"16158 Genova",
    "sg:city":"Genova",
    "sg:orig_category":"Arredo Cucina Ed Elettrodomestici. Elettrodomestici",
    "sg:phone":"+39 010 613 6437",
    "sg:postcode":"16158",
    "sg:province":"Genova",
    "wof:name":"Massa Agostino Srl",
    "wof:placetype":"venue"
},
  "geometry": {"coordinates":[8.747303,44.428589],"type":"Point"}
}