{
  "type": "Feature",
  "properties": {
    "iso:country":"IT",
    "sg:address":"51031 Agliana",
    "sg:city":"Agliana",
    "sg:classifiers":[
        {
            "category":"Shopping",
            "subcategory":"Clothing, Apparel, & Fashions",
            "type":"Retail Goods"
        }
    ],
    "sg:phone":"+39 0574 750238",
    "sg:postcode":"51031",
    "sg:province":"Pistoia",
    "sg:tags":[
        "activities",
        "goods",
        "supply",
        "leather",
        "commercial",
        "artisan",
        "supplies",
        "clothing"
    ],
    "wof:name":"Tipografia Mariotti",
    "wof:placetype":"venue"
},
  "geometry": {"coordinates":[10.994849,43.910248],"type":"Point"}
}