{
  "type": "Feature",
  "properties": {
    "iso:country":"IT",
    "sg:address":"24040 Bonate Sopra",
    "sg:city":"Bonate Sopra",
    "sg:orig_category":"Serigrafia",
    "sg:phone":"+39 035 494 2668",
    "sg:postcode":"24040",
    "sg:province":"Bergamo",
    "sg:website":"http://www.gierreserigrafia.com",
    "wof:name":"Testa Giulio - Gierre Serigrafia",
    "wof:placetype":"venue"
},
  "geometry": {"coordinates":[9.584919,45.698063],"type":"Point"}
}