{
  "type": "Feature",
  "properties": {
    "addr:full":"15, Via S. Cristoforo 06083 Bastia Bastia Perugia 06083",
    "addr:postcode":"06083;06083",
    "addr:street":"Via S. Cristoforo",
    "iso:country":"IT",
    "sg:address":"15, Via S. Cristoforo 06083 Bastia",
    "sg:city":"Bastia",
    "sg:classifiers":[
        {
            "category":"Professional",
            "subcategory":"Engineering",
            "type":"Services"
        }
    ],
    "sg:phone":"+39 075 801 0489",
    "sg:postcode":"06083",
    "sg:province":"Perugia",
    "sg:tags":[
        "machine",
        "-",
        "mechanical"
    ],
    "wof:name":"Frigo Impianti (s.r.l.)",
    "wof:placetype":"venue"
},
  "geometry": {"coordinates":[12.498651,43.078136],"type":"Point"}
}