{
  "type": "Feature",
  "properties": {
    "iso:country":"IT",
    "sg:address":"40, Viale Monastir 09122 Cagliari",
    "sg:city":"Cagliari",
    "sg:classifiers":[
        {
            "category":"Retail",
            "subcategory":"Animal Services",
            "type":"Services"
        }
    ],
    "sg:phone":"+39 39070283357",
    "sg:postcode":"09122",
    "sg:province":"Cagliari",
    "sg:tags":[
        "breeding"
    ],
    "wof:name":"Novelli",
    "wof:placetype":"venue"
},
  "geometry": {"coordinates":[9.09689,39.236042],"type":"Point"}
}