{
  "type": "Feature",
  "properties": {
    "iso:country":"IT",
    "sg:address":"10040 San Gillio",
    "sg:city":"San Gillio",
    "sg:orig_category":"Macchine, Impianti Ed Attrezzature Per Agricoltura E Zootecnia. Macchine, Impianti Ed Attrezzature Industria Chimica. Macchine Utensili E Impianti",
    "sg:phone":"+39 011 994 9946",
    "sg:postcode":"10040",
    "sg:province":"Torino",
    "wof:name":"P.a. International S.r.l.",
    "wof:placetype":"venue"
},
  "geometry": {"coordinates":[7.536164,45.142765],"type":"Point"}
}