{
  "type": "Feature",
  "properties": {
    "addr:full":"12, V. Per Lonate 21050 Cairate Cairate Varese 21050",
    "addr:housenumber":"12",
    "addr:postcode":"21050;21050",
    "addr:street":"V. Per Lonate",
    "iso:country":"IT",
    "sg:address":"12, V. Per Lonate 21050 Cairate",
    "sg:city":"Cairate",
    "sg:classifiers":[
        {
            "category":"Manufacturing",
            "subcategory":"Tools & Machinery",
            "type":"Manufacturing & Wholesale Goods"
        }
    ],
    "sg:phone":"+39 0331 360404",
    "sg:postcode":"21050",
    "sg:province":"Varese",
    "sg:tags":[
        "environment",
        "equipment",
        "-"
    ],
    "sg:website":"http://www.paginegialle.it/leporisnc",
    "wof:name":"Lepori Snc",
    "wof:placetype":"venue"
},
  "geometry": {"coordinates":[8.87472,45.695934],"type":"Point"}
}