{
  "type": "Feature",
  "properties": {
    "iso:country":"IT",
    "sg:address":"00121 Lido Di Ostia",
    "sg:orig_category":"Carni, Salumi E Pesci",
    "sg:phone":"+39 06 564 5936",
    "sg:postcode":"00121",
    "sg:province":"Roma",
    "wof:name":"Livi Mery",
    "wof:placetype":"venue"
},
  "geometry": {"coordinates":[12.264,41.73991],"type":"Point"}
}