{
  "type": "Feature",
  "properties": {
    "addr:full":"27, Vl. Delle Industrie 35010 Ronchi Di Villafranca Padova 35010",
    "addr:housenumber":"27",
    "addr:postcode":"35010;35010",
    "addr:street":"Vl. Delle Industrie",
    "iso:country":"IT",
    "sg:address":"27, Vl. Delle Industrie 35010 Ronchi Di Villafranca",
    "sg:classifiers":[
        {
            "category":"Professional",
            "subcategory":"Engineering",
            "type":"Services"
        }
    ],
    "sg:phone":"+39 049 907 0172",
    "sg:postcode":"35010",
    "sg:province":"Padova",
    "sg:tags":[
        "machine",
        "-",
        "mechanical"
    ],
    "wof:name":"Zoin Refrigerazione Srl",
    "wof:placetype":"venue"
},
  "geometry": {"coordinates":[11.876589,45.409569],"type":"Point"}
}