{
  "type": "Feature",
  "properties": {
    "addr:full":"Vle Dell' Artigianato 20036 Meda Meda Milano 20036",
    "addr:postcode":"20036;20036",
    "addr:street":"Vle Dell ' Artigianato",
    "iso:country":"IT",
    "sg:address":"Vle Dell' Artigianato 20036 Meda",
    "sg:city":"Meda",
    "sg:classifiers":[
        {
            "category":"Wholesale",
            "subcategory":"Home Furnishings",
            "type":"Manufacturing & Wholesale Goods"
        }
    ],
    "sg:phone":"+39 036 270739",
    "sg:postcode":"20036",
    "sg:province":"Milano",
    "sg:tags":[
        "chair"
    ],
    "wof:name":"Emilio E Carlo Cassina S.n.c.",
    "wof:placetype":"venue"
},
  "geometry": {"coordinates":[9.188141,45.463688],"type":"Point"}
}