{
  "type": "Feature",
  "properties": {
    "iso:country":"IT",
    "sg:address":"Via Bologna 220 10154 Torino",
    "sg:city":"Torino",
    "sg:classifiers":[
        {
            "category":"Manufacturing",
            "subcategory":"Rubber & Plastics",
            "type":"Manufacturing & Wholesale Goods"
        }
    ],
    "sg:phone":"+39 011 857779",
    "sg:postcode":"10154",
    "sg:province":"Torino",
    "sg:tags":[
        "part",
        "pressed"
    ],
    "wof:name":"Pidikei Di F. Mattiuzza",
    "wof:placetype":"venue"
},
  "geometry": {"coordinates":[7.7070021629,45.0876426697],"type":"Point"}
}