{
  "type": "Feature",
  "properties": {
    "addr:full":"24, V. Dei Trasporti 20060 Vignate Vignate Milano 20060",
    "addr:housenumber":"24",
    "addr:postcode":"20060;20060",
    "addr:street":"V. Dei Trasporti",
    "iso:country":"IT",
    "sg:address":"24, V. Dei Trasporti 20060 Vignate",
    "sg:city":"Vignate",
    "sg:classifiers":[
        {
            "category":"Parking",
            "subcategory":"Lot",
            "type":"Transportation"
        }
    ],
    "sg:phone":"+39 390 295 9331",
    "sg:postcode":"20060",
    "sg:province":"Milano",
    "sg:tags":[
        "transport",
        "road"
    ],
    "sg:website":"http://www.gondrand.it",
    "wof:name":"Gondrand Spa",
    "wof:placetype":"venue"
},
  "geometry": {"coordinates":[9.188141,45.463688],"type":"Point"}
}