{
  "type": "Feature",
  "properties": {
    "addr:full":"90020 Blufi Blufi Palermo 90020",
    "addr:postcode":"90020;90020",
    "iso:country":"IT",
    "sg:address":"90020 Blufi",
    "sg:city":"Blufi",
    "sg:orig_category":"Ospedali E Servizi Sanitari",
    "sg:phone":"+39 0921 648001",
    "sg:postcode":"90020",
    "sg:province":"Palermo",
    "wof:name":"Coop.va Sociale Mediterranea Soc.coop.va A.r.l.",
    "wof:placetype":"venue"
},
  "geometry": {"coordinates":[14.076881,37.761383],"type":"Point"}
}