{
  "type": "Feature",
  "properties": {
    "addr:full":"Via Regio Parco 9; Settimo Torinese",
    "addr:housenumber":"9",
    "addr:street":"Via Regio Parco",
    "iso:country":"IT",
    "sg:address":"Via Regio Parco 9; Settimo Torinese",
    "sg:classifiers":[
        {
            "category":"Banks & Credit Unions",
            "subcategory":"Bank",
            "type":"Services"
        }
    ],
    "sg:phone":"+39 011 898 4464",
    "wof:name":"Banca Di Roma",
    "wof:placetype":"venue"
},
  "geometry": {"coordinates":[7.753439,45.128517],"type":"Point"}
}