{
  "type": "Feature",
  "properties": {
    "addr:full":"00062 Bracciano Bracciano Roma 00062",
    "addr:postcode":"00062;roma 00062",
    "iso:country":"IT",
    "sg:address":"00062 Bracciano",
    "sg:city":"Bracciano",
    "sg:orig_category":"Studi E Consulenze Amministrative, Commerciali E Aziendali. Consulenze Tecniche, Amministrative E Perizie. Professionisti - Studi E Servizi Ed Associazioni Di Interesse Aziendale",
    "sg:phone":"+39 06 998 7466",
    "sg:postcode":"00062",
    "sg:province":"Roma",
    "wof:name":"Pompei Dr. Gino",
    "wof:placetype":"venue"
},
  "geometry": {"coordinates":[12.169458,42.099308],"type":"Point"}
}