{
  "type": "Feature",
  "properties": {
    "iso:country":"IT",
    "sg:address":"70124 Bari",
    "sg:city":"Bari",
    "sg:orig_category":"Non-classified Establishments",
    "sg:phone":"+39 080 561 8309",
    "sg:postcode":"70124",
    "sg:province":"Bari",
    "wof:name":"Nuova Bottega Artigiana",
    "wof:placetype":"venue"
},
  "geometry": {"coordinates":[16.849241,41.102673],"type":"Point"}
}