{
  "type": "Feature",
  "properties": {
    "iso:country":"IT",
    "sg:address":"39, Via Papa Giovanni Xxiii 23855 Pescate",
    "sg:city":"Pescate",
    "sg:classifiers":[
        {
            "category":"Manufacturing",
            "subcategory":"Metals",
            "type":"Manufacturing & Wholesale Goods"
        }
    ],
    "sg:phone":"+39 0341 361578",
    "sg:postcode":"23855",
    "sg:province":"Lecco",
    "sg:tags":[
        "metallurgy",
        "metalworking"
    ],
    "wof:name":"Invernizzi E Tomei (s.r.l.)",
    "wof:placetype":"venue"
},
  "geometry": {"coordinates":[9.3957719803,45.8592300415],"type":"Point"}
}