{
  "type": "Feature",
  "properties": {
    "addr:full":"00145 Roma Roma Roma 00145",
    "addr:postcode":"00145;00145",
    "iso:country":"IT",
    "sg:address":"00145 Roma",
    "sg:city":"Roma",
    "sg:orig_category":"Prodotti Finiti Stampati. Forniture Per Uffici",
    "sg:phone":"+39 06 5143 5038",
    "sg:postcode":"00145",
    "sg:province":"Roma",
    "wof:name":"Officine Stampa Srl",
    "wof:placetype":"venue"
},
  "geometry": {"coordinates":[12.4937505722,41.8601608276],"type":"Point"}
}