{
  "type": "Feature",
  "properties": {
    "addr:full":"Via Butrio-fraz.carniaco 33050 Pozzuolo Del Friuli Pozzuolo del Friuli Udine 33050",
    "addr:postcode":"33050;33050",
    "addr:street":"Via Butrio-Fraz.Carniaco;Del Friuli",
    "iso:country":"IT",
    "sg:address":"Via Butrio-fraz.carniaco 33050 Pozzuolo Del Friuli",
    "sg:city":"Pozzuolo del Friuli",
    "sg:classifiers":[
        {
            "category":"Building & Trades",
            "subcategory":"Construction",
            "type":"Services"
        }
    ],
    "sg:phone":"+39 0432 6071",
    "sg:postcode":"33050",
    "sg:province":"Udine",
    "sg:tags":[
        "bridge",
        "equipment"
    ],
    "sg:website":"www.rizzanideeccher.com",
    "wof:name":"De Eccher Alga Combined Technologie Spa",
    "wof:placetype":"venue"
},
  "geometry": {"coordinates":[13.230724,46.064941],"type":"Point"}
}