{
  "type": "Feature",
  "properties": {
    "iso:country":"IT",
    "sg:address":"80078 Licola",
    "sg:orig_category":"Pubblica Amministrazione",
    "sg:phone":"+39 081 867 8275",
    "sg:postcode":"80078",
    "sg:province":"Napoli",
    "wof:name":"Carabinieri",
    "wof:placetype":"venue"
},
  "geometry": {"coordinates":[14.3565797806,40.8624725342],"type":"Point"}
}