{
  "type": "Feature",
  "properties": {
    "addr:full":"1, Via Moscuso 81049 Mignano Monte Lungo Mignano Monte Lungo Caserta 81049",
    "addr:postcode":"81049;81049",
    "addr:street":"Via Moscuso;Lungo Mignano Monte Lungo Caserta",
    "iso:country":"IT",
    "sg:address":"1, Via Moscuso 81049 Mignano Monte Lungo",
    "sg:city":"Mignano Monte Lungo",
    "sg:classifiers":[
        {
            "category":"Shopping",
            "type":"Retail Goods"
        }
    ],
    "sg:phone":"+39 0823 904144",
    "sg:postcode":"81049",
    "sg:province":"Caserta",
    "sg:tags":[
        "finished",
        "-",
        "metallic"
    ],
    "wof:name":"Tekmind Srl",
    "wof:placetype":"venue"
},
  "geometry": {"coordinates":[13.9566144943,41.4141731262],"type":"Point"}
}