{
  "type": "Feature",
  "properties": {
    "iso:country":"IT",
    "sg:address":"84, V. Triumvirato 40132 Bologna",
    "sg:city":"Bologna",
    "sg:classifiers":[
        {
            "category":"Airport",
            "subcategory":"General Aviation",
            "type":"Transportation"
        }
    ],
    "sg:phone":"+39 051 647 9615",
    "sg:postcode":"40132",
    "sg:province":"Bologna",
    "sg:tags":[
        "transport",
        "air"
    ],
    "sg:website":"http://www.bologna-airport.it",
    "wof:name":"Aeroporto Bologna G. Marconi",
    "wof:placetype":"venue"
},
  "geometry": {"coordinates":[11.296445,44.521103],"type":"Point"}
}