{
  "type": "Feature",
  "properties": {
    "addr:full":"20092 Cinisello Balsamo Cinisello Balsamo Milano 20092",
    "addr:postcode":"20092;20092",
    "iso:country":"IT",
    "sg:address":"20092 Cinisello Balsamo",
    "sg:city":"Cinisello Balsamo",
    "sg:orig_category":"Forniture E Materiali Per Imballaggio E Confezionamento. Forniture Per Uffici. Forniture Per Attivita' Commerciali Ed Artigianali",
    "sg:phone":"+39 02 6604 1414",
    "sg:postcode":"20092",
    "sg:province":"Milano",
    "sg:website":"http://www.gruppolna.it",
    "wof:name":"L.n.a. Srl",
    "wof:placetype":"venue"
},
  "geometry": {"coordinates":[9.2190637589,45.5554161072],"type":"Point"}
}