{
  "type": "Feature",
  "properties": {
    "addr:full":"26028 Sesto Ed Uniti Sesto ed Uniti Cremona 26028",
    "addr:postcode":"26028;26028",
    "iso:country":"IT",
    "sg:address":"26028 Sesto Ed Uniti",
    "sg:city":"Sesto ed Uniti",
    "sg:classifiers":[
        {
            "category":"Shopping",
            "subcategory":"Clothing, Apparel, & Fashions",
            "type":"Retail Goods"
        }
    ],
    "sg:phone":"+39 0372 76766",
    "sg:postcode":"26028",
    "sg:province":"Cremona",
    "sg:tags":[
        "knitwear",
        "furs",
        "clothing"
    ],
    "wof:name":"P.b.m. Confezione Srl",
    "wof:placetype":"venue"
},
  "geometry": {"coordinates":[9.974378,45.148712],"type":"Point"}
}