{
  "type": "Feature",
  "properties": {
    "addr:full":"20099 Sesto San Giovanni Sesto San Giovanni Milano 20099",
    "addr:postcode":"20099;20099",
    "iso:country":"IT",
    "sg:address":"20099 Sesto San Giovanni",
    "sg:city":"Sesto San Giovanni",
    "sg:orig_category":"Prodotti Chimici Di Base",
    "sg:phone":"+39 02 2247 4744",
    "sg:postcode":"20099",
    "sg:province":"Milano",
    "sg:website":"http://www.chimedi.it",
    "wof:name":"Chimedi Marketing Services Srl",
    "wof:placetype":"venue"
},
  "geometry": {"coordinates":[9.2299108505,45.5274467468],"type":"Point"}
}