{
  "type": "Feature",
  "properties": {
    "iso:country":"IT",
    "sg:address":"15048 Valenza",
    "sg:city":"Valenza",
    "sg:orig_category":"Arredamenti - Vendita Al Dettaglio",
    "sg:phone":"+39 0131 943280",
    "sg:postcode":"15048",
    "sg:province":"Alessandria",
    "wof:name":"Pedrina Mobili Srl",
    "wof:placetype":"venue"
},
  "geometry": {"coordinates":[8.649408,45.011917],"type":"Point"}
}