{
  "type": "Feature",
  "properties": {
    "iso:country":"IT",
    "sg:address":"Via Scorine 38 25050 Ome",
    "sg:city":"Ome",
    "sg:classifiers":[
        {
            "category":"Personal",
            "subcategory":"Beauty Salon",
            "type":"Services"
        }
    ],
    "sg:phone":"+39 030 652000",
    "sg:postcode":"25050",
    "sg:province":"Brescia",
    "sg:tags":[
        "hairpin"
    ],
    "wof:name":"Red Hill Snc Di Bonomini Riccardo & C",
    "wof:placetype":"venue"
},
  "geometry": {"coordinates":[10.119786,45.623863],"type":"Point"}
}