{
  "type": "Feature",
  "properties": {
    "addr:full":"46/10, Strada Carignano 10024 Moncalieri Moncalieri Torino 10024",
    "addr:housenumber":"46 / 10",
    "addr:postcode":"10024;10024",
    "addr:street":"Strada Carignano",
    "iso:country":"IT",
    "sg:address":"46/10, Strada Carignano 10024 Moncalieri",
    "sg:city":"Moncalieri",
    "sg:classifiers":[
        {
            "category":"Manufacturing",
            "subcategory":"Rubber & Plastics",
            "type":"Manufacturing & Wholesale Goods"
        }
    ],
    "sg:phone":"+39 011 682 9133",
    "sg:postcode":"10024",
    "sg:province":"Torino",
    "wof:name":"Bottino Girardi E C. (s.n.c.)",
    "wof:placetype":"venue"
},
  "geometry": {"coordinates":[7.66984272,44.991733551],"type":"Point"}
}