{
  "type": "Feature",
  "properties": {
    "iso:country":"IT",
    "sg:address":"155, Via Virgilio 55049 Viareggio",
    "sg:city":"Viareggio",
    "sg:classifiers":[
        {
            "category":"Autos & Motor Vehicles",
            "subcategory":"Boat Sales",
            "type":"Retail Goods"
        }
    ],
    "sg:phone":"+39 0584 388495",
    "sg:postcode":"55049",
    "sg:province":"Lucca",
    "wof:name":"Simare Srl",
    "wof:placetype":"venue"
},
  "geometry": {"coordinates":[10.246935,43.862022],"type":"Point"}
}