{
  "type": "Feature",
  "properties": {
    "addr:full":"20146 Milano Milano Milano 20146",
    "addr:postcode":"20146;20146",
    "iso:country":"IT",
    "sg:address":"20146 Milano",
    "sg:city":"Milano",
    "sg:orig_category":"Scuole E Servizi Scolastici. Ospedali E Servizi Sanitari",
    "sg:phone":"+39 02 4837 6277",
    "sg:postcode":"20146",
    "sg:province":"Milano",
    "wof:name":"Associazione Rosa Dei Venti",
    "wof:placetype":"venue"
},
  "geometry": {"coordinates":[9.142772,45.454659],"type":"Point"}
}