{
  "type": "Feature",
  "properties": {
    "iso:country":"IT",
    "sg:address":"Via Postumia 85, 31047 Ponte Di Piave, Tv",
    "sg:city":"Ponte di Piave",
    "sg:classifiers":[
        {
            "category":"Banks & Credit Unions",
            "subcategory":"Bank",
            "type":"Services"
        }
    ],
    "sg:phone":"+39 0422 8191",
    "sg:postcode":"31047",
    "sg:province":"Treviso",
    "wof:name":"Stefanel Spa",
    "wof:placetype":"venue"
},
  "geometry": {"coordinates":[12.466658,45.71703],"type":"Point"}
}