{
  "type": "Feature",
  "properties": {
    "iso:country":"IT",
    "sg:address":"62032 Camerino",
    "sg:city":"Camerino",
    "sg:orig_category":"Prodotti Chimici Di Base",
    "sg:phone":"+39 0737 632615",
    "sg:postcode":"62032",
    "sg:province":"Macerata",
    "wof:name":"R.m. Service Sas Di Righetti Luigi & C.",
    "wof:placetype":"venue"
},
  "geometry": {"coordinates":[13.073849678,43.1450157166],"type":"Point"}
}