{
  "type": "Feature",
  "properties": {
    "iso:country":"IT",
    "sg:address":"20093 Cologno Monzese",
    "sg:city":"Cologno Monzese",
    "sg:orig_category":"Articoli Da Regalo. Regalistica Aziendale",
    "sg:phone":"+39 02 2539 0984",
    "sg:postcode":"20093",
    "sg:province":"Milano",
    "wof:name":"Plastigas",
    "wof:placetype":"venue"
},
  "geometry": {"coordinates":[9.263535,45.538273],"type":"Point"}
}