{
  "type": "Feature",
  "properties": {
    "addr:full":"00161 Roma Roma Roma 00161",
    "addr:postcode":"00161;00161",
    "iso:country":"IT",
    "sg:address":"00161 Roma",
    "sg:city":"Roma",
    "sg:orig_category":"Abbigliamento Intimo, Calze E Costumi Da Bagno",
    "sg:phone":"+39 06 4429 2922",
    "sg:postcode":"00161",
    "sg:province":"Roma",
    "wof:name":"Giordano Anna Maddalena",
    "wof:placetype":"venue"
},
  "geometry": {"coordinates":[12.518226,41.911289],"type":"Point"}
}