{
  "type": "Feature",
  "properties": {
    "iso:country":"IT",
    "sg:address":"23893 Cassago Brianza",
    "sg:city":"Cassago Brianza",
    "sg:orig_category":"Legno E Semilavorati. Articoli Per Imballaggio E Confezionamento",
    "sg:phone":"+39 039 955934",
    "sg:postcode":"23893",
    "sg:province":"Lecco",
    "sg:website":"http://www.moltenipallets.com",
    "wof:name":"Molteni Srl",
    "wof:placetype":"venue"
},
  "geometry": {"coordinates":[9.288828,45.738789],"type":"Point"}
}