{
  "type": "Feature",
  "properties": {
    "iso:country":"IT",
    "sg:address":"Via Giolitti 2 36056 Tezze Sul Brenta",
    "sg:city":"Tezze sul Brenta",
    "sg:classifiers":[
        {
            "category":"Manufacturing",
            "subcategory":"Tools & Machinery",
            "type":"Manufacturing & Wholesale Goods"
        }
    ],
    "sg:phone":"+39 0424 539415",
    "sg:postcode":"36056",
    "sg:province":"Vicenza",
    "sg:tags":[
        "machine",
        "special"
    ],
    "wof:name":"Mz Macchine Srl",
    "wof:placetype":"venue"
},
  "geometry": {"coordinates":[11.728829,45.69101],"type":"Point"}
}