{
  "type": "Feature",
  "properties": {
    "iso:country":"IT",
    "sg:address":"1, Via Rio Primario 34149 Trieste",
    "sg:city":"Trieste",
    "sg:classifiers":[
        {
            "category":"Food & Beverages",
            "subcategory":"Groceries & Convenience Stores",
            "type":"Retail Goods"
        }
    ],
    "sg:phone":"+39 39040816378",
    "sg:postcode":"34149",
    "sg:province":"Trieste",
    "sg:tags":[
        "product",
        "related"
    ],
    "wof:name":"Miramar S.p.a.",
    "wof:placetype":"venue"
},
  "geometry": {"coordinates":[13.7874498367,45.6192703247],"type":"Point"}
}