{
  "type": "Feature",
  "properties": {
    "addr:full":"00171 Roma Roma Roma 00171",
    "addr:postcode":"00171;00171",
    "iso:country":"IT",
    "sg:address":"00171 Roma",
    "sg:city":"Roma",
    "sg:orig_category":"Pubblica Amministrazione",
    "sg:phone":"+39 06 231 2033",
    "sg:postcode":"00171",
    "sg:province":"Roma",
    "wof:name":"Carabinieri",
    "wof:placetype":"venue"
},
  "geometry": {"coordinates":[12.4418497086,41.81873703],"type":"Point"}
}