{
  "type": "Feature",
  "properties": {
    "iso:country":"IT",
    "sg:address":"80023 Caivano",
    "sg:city":"Caivano",
    "sg:orig_category":"Petroli, Gas E Combustibili",
    "sg:phone":"+39 081 834 9123",
    "sg:postcode":"80023",
    "sg:province":"Napoli",
    "wof:name":"Mi.so. S.r.l.",
    "wof:placetype":"venue"
},
  "geometry": {"coordinates":[14.3210096359,40.9727401733],"type":"Point"}
}