{
  "type": "Feature",
  "properties": {
    "iso:country":"IT",
    "sg:address":"Via Amendola 13 66046 Tornareccio",
    "sg:city":"Tornareccio",
    "sg:orig_category":"Restaurants: Furniture",
    "sg:phone":"+39 0872 868335",
    "sg:postcode":"66046",
    "sg:province":"Chieti",
    "wof:name":"Fratelli Betti & C. Snc",
    "wof:placetype":"venue"
},
  "geometry": {"coordinates":[14.167151,42.351791],"type":"Point"}
}