{
  "type": "Feature",
  "properties": {
    "iso:country":"IT",
    "sg:address":"12045 Fossano",
    "sg:city":"Fossano",
    "sg:classifiers":[
        {
            "category":"Health Services",
            "subcategory":"Health Practitioner",
            "type":"Services"
        }
    ],
    "sg:phone":"+39 0172 695988",
    "sg:postcode":"12045",
    "sg:province":"Cuneo",
    "sg:tags":[
        "medici"
    ],
    "wof:name":"Chiavassa Elio",
    "wof:placetype":"venue"
},
  "geometry": {"coordinates":[7.676516,44.536499],"type":"Point"}
}