{
  "type": "Feature",
  "properties": {
    "iso:country":"IT",
    "sg:address":"81055 S. Maria Capua Vetere",
    "sg:orig_category":"Prodotti Finiti Stampati. Articoli Da Regalo. Arte Ed Artigianato Artistico. Shopping",
    "sg:phone":"+39 0823 846833",
    "sg:postcode":"81055",
    "sg:province":"Caserta",
    "wof:name":"Meddi Maddalena",
    "wof:placetype":"venue"
},
  "geometry": {"coordinates":[14.2555971146,41.0754394531],"type":"Point"}
}