{
  "type": "Feature",
  "properties": {
    "iso:country":"IT",
    "sg:address":"80026 Casoria",
    "sg:city":"Casoria",
    "sg:orig_category":"Forniture Per Attivita' Commerciali Ed Artigianali. Arredi Ed Attrezzature Per Attivita' Commerciali Ed Artigianali",
    "sg:phone":"+39 081 237 8111",
    "sg:postcode":"80026",
    "sg:province":"Napoli",
    "wof:name":"Marr Napoli",
    "wof:placetype":"venue"
},
  "geometry": {"coordinates":[14.3151922226,40.8893203735],"type":"Point"}
}