{
  "type": "Feature",
  "properties": {
    "iso:country":"IT",
    "sg:address":"65128 Pescara",
    "sg:city":"Pescara",
    "sg:orig_category":"Arredamenti - Produzione E Ingrosso",
    "sg:phone":"+39 085 50241",
    "sg:postcode":"65128",
    "sg:province":"Pescara",
    "sg:website":"http://www.meccanicaforni.it",
    "wof:name":"La Meccanica Forni Srl",
    "wof:placetype":"venue"
},
  "geometry": {"coordinates":[14.177982,42.433735],"type":"Point"}
}