{
  "type": "Feature",
  "properties": {
    "iso:country":"IT",
    "sg:address":"18, V. Levi 59100 Prato",
    "sg:city":"Prato",
    "sg:classifiers":[
        {
            "category":"Shopping",
            "subcategory":"Crafts & Fabrics",
            "type":"Retail Goods"
        }
    ],
    "sg:phone":"+39 0574 662807",
    "sg:postcode":"59100",
    "sg:province":"Prato",
    "sg:website":"http://www.eurotex.it",
    "wof:name":"Eurotex Srl",
    "wof:placetype":"venue"
},
  "geometry": {"coordinates":[11.0400075912,43.8813209534],"type":"Point"}
}