{
  "type": "Feature",
  "properties": {
    "addr:full":"50028 Tavarnelle Val Di Pesa Tavarnelle Val di Pesa Firenze 50028",
    "addr:postcode":"50028;50028",
    "addr:street":"Val Di Pesa",
    "iso:country":"IT",
    "sg:address":"50028 Tavarnelle Val Di Pesa",
    "sg:city":"Tavarnelle Val di Pesa",
    "sg:orig_category":"Macchine, Impianti Ed Attrezzature Per Abbigliamento E Pelletterie. Apparecchiature Ed Attrezzature Meccaniche. Elettrotecnica Industriale, Prodotti E Apparecchiature",
    "sg:phone":"+39 055 807 7010",
    "sg:postcode":"50028",
    "sg:province":"Firenze",
    "wof:name":"Axis (s.p.a.)",
    "wof:placetype":"venue"
},
  "geometry": {"coordinates":[11.178349,43.56258],"type":"Point"}
}