{
  "type": "Feature",
  "properties": {
    "iso:country":"IT",
    "sg:address":"21053 Castellanza",
    "sg:city":"Castellanza",
    "sg:orig_category":"Filati E Materie Prime Tessili",
    "sg:phone":"+39 0331 621316",
    "sg:postcode":"21053",
    "sg:province":"Varese",
    "wof:name":"All Trade Sas Di Martorella",
    "wof:placetype":"venue"
},
  "geometry": {"coordinates":[8.8772211075,45.6114273071],"type":"Point"}
}