{
  "type": "Feature",
  "properties": {
    "iso:country":"IT",
    "sg:address":"Via Industria 24043 Caravaggio",
    "sg:city":"Caravaggio",
    "sg:classifiers":[
        {
            "category":"Manufacturing",
            "subcategory":"Metals",
            "type":"Manufacturing & Wholesale Goods"
        }
    ],
    "sg:phone":"+39 036 335 1014",
    "sg:postcode":"24043",
    "sg:province":"Bergamo",
    "sg:tags":[
        "processing"
    ],
    "wof:name":"Cattaneo & Motta (s.p.a.)",
    "wof:placetype":"venue"
},
  "geometry": {"coordinates":[9.6504507065,45.4851531982],"type":"Point"}
}