{
  "type": "Feature",
  "properties": {
    "addr:full":"44, Via Caravaggio 20092 Cinisello Balsamo Cinisello Balsamo Milano 20092",
    "addr:postcode":"20092;20092",
    "addr:street":"Via Caravaggio",
    "iso:country":"IT",
    "sg:address":"44, Via Caravaggio 20092 Cinisello Balsamo",
    "sg:city":"Cinisello Balsamo",
    "sg:classifiers":[
        {
            "category":"Utilities",
            "subcategory":"Electric",
            "type":"Services"
        }
    ],
    "sg:phone":"+39 39026127148",
    "sg:postcode":"20092",
    "sg:province":"Milano",
    "sg:tags":[
        "component",
        "electronic"
    ],
    "wof:name":"Elfes (s.n.c.)",
    "wof:placetype":"venue"
},
  "geometry": {"coordinates":[9.199547,45.548168],"type":"Point"}
}