{
  "type": "Feature",
  "properties": {
    "iso:country":"IT",
    "sg:address":"56017 San Giuliano Terme",
    "sg:city":"San Giuliano Terme",
    "sg:orig_category":"Alberghi",
    "sg:phone":"+39 050 814111",
    "sg:postcode":"56017",
    "sg:province":"Pisa",
    "wof:name":"Hotel Granduca",
    "wof:placetype":"venue"
},
  "geometry": {"coordinates":[10.405589,43.723713],"type":"Point"}
}