{
  "type": "Feature",
  "properties": {
    "addr:full":"42014 Castellarano Reggio Nell'Emilia 42014",
    "addr:housenumber":"42014",
    "addr:postcode":"42014",
    "iso:country":"IT",
    "sg:address":"42014 Castellarano",
    "sg:orig_category":"Utensili Meccanici E Materiali",
    "sg:phone":"+39 0536 851654",
    "sg:postcode":"42014",
    "sg:province":"Reggio Nell'Emilia",
    "wof:name":"M.e.m. Srl",
    "wof:placetype":"venue"
},
  "geometry": {"coordinates":[10.680069,44.484123],"type":"Point"}
}