{
  "type": "Feature",
  "properties": {
    "addr:full":"10036 Settimo Torinese Settimo Torinese Torino 10036",
    "addr:postcode":"10036;10036",
    "iso:country":"IT",
    "sg:address":"10036 Settimo Torinese",
    "sg:city":"Settimo Torinese",
    "sg:orig_category":"Filati E Materie Prime Tessili",
    "sg:phone":"+39 011 895 3225",
    "sg:postcode":"10036",
    "sg:province":"Torino",
    "wof:name":"Bursi Irma & Sberveglieri Peppino Srl",
    "wof:placetype":"venue"
},
  "geometry": {"coordinates":[7.7429409027,45.1285858154],"type":"Point"}
}