{
  "type": "Feature",
  "properties": {
    "addr:full":"1, Via A.grandi 47030 San Mauro Pascoli San Mauro Pascoli Forl\u00ec-Cesena 47030",
    "addr:postcode":"47030;47030",
    "addr:street":"Via A.Grandi",
    "iso:country":"IT",
    "sg:address":"1, Via A.grandi 47030 San Mauro Pascoli",
    "sg:city":"San Mauro Pascoli",
    "sg:classifiers":[
        {
            "category":"Food & Beverages",
            "subcategory":"Groceries & Convenience Stores",
            "type":"Retail Goods"
        }
    ],
    "sg:phone":"+39 0541 932759",
    "sg:postcode":"47030",
    "sg:province":"Forl\u00ec-Cesena",
    "sg:tags":[
        "drink"
    ],
    "wof:name":"Baiocchi S.r.l.",
    "wof:placetype":"venue"
},
  "geometry": {"coordinates":[11.980461,43.994766],"type":"Point"}
}