{
  "type": "Feature",
  "properties": {
    "iso:country":"IT",
    "sg:address":"04100 Latina",
    "sg:city":"Latina",
    "sg:orig_category":"Ricambi E Componenti Dei Mezzi Di Trasporto",
    "sg:phone":"+39 0773 486622",
    "sg:postcode":"04100",
    "sg:province":"Latina",
    "wof:name":"La Casa Del Carburatore",
    "wof:placetype":"venue"
},
  "geometry": {"coordinates":[12.874495,41.452148],"type":"Point"}
}