{
  "type": "Feature",
  "properties": {
    "iso:country":"IT",
    "sg:address":"33, Via Zambaldi Antonio 30026 Portogruaro",
    "sg:city":"Portogruaro",
    "sg:classifiers":[
        {
            "category":"Autos & Motor Vehicles",
            "subcategory":"Boat Sales",
            "type":"Retail Goods"
        }
    ],
    "sg:phone":"+39 39042171419",
    "sg:postcode":"30026",
    "sg:province":"Venezia",
    "wof:name":"Camuffo",
    "wof:placetype":"venue"
},
  "geometry": {"coordinates":[12.834009,45.772747],"type":"Point"}
}