{
  "type": "Feature",
  "properties": {
    "iso:country":"IT",
    "sg:address":"20121 Milano",
    "sg:city":"Milano",
    "sg:orig_category":"Bevande, Vini E Liquori",
    "sg:phone":"+39 02 657 2995",
    "sg:postcode":"20121",
    "sg:province":"Milano",
    "wof:name":"Enoteca Cotti Snc",
    "wof:placetype":"venue"
},
  "geometry": {"coordinates":[9.188234,45.478252],"type":"Point"}
}