{
  "type": "Feature",
  "properties": {
    "iso:country":"IT",
    "sg:address":"10138 Torino",
    "sg:city":"Torino",
    "sg:orig_category":"Metalli E Leghe",
    "sg:phone":"+39 011 434 1462",
    "sg:postcode":"10138",
    "sg:province":"Torino",
    "wof:name":"Diasinter Di Teja Roberto",
    "wof:placetype":"venue"
},
  "geometry": {"coordinates":[7.6652798653,45.0724487305],"type":"Point"}
}