{
  "type": "Feature",
  "properties": {
    "addr:full":"23, Via Del Parlamento Europeo 50018 Scandicci Scandicci Firenze 50018",
    "addr:postcode":"50018;50018",
    "addr:street":"Via Del Parlamento Europeo",
    "iso:country":"IT",
    "sg:address":"23, Via Del Parlamento Europeo 50018 Scandicci",
    "sg:city":"Scandicci",
    "sg:classifiers":[
        {
            "category":"Manufacturing",
            "subcategory":"Lumber",
            "type":"Manufacturing & Wholesale Goods"
        }
    ],
    "sg:phone":"+39 055 731 0465",
    "sg:postcode":"50018",
    "sg:province":"Firenze",
    "sg:tags":[
        "wood"
    ],
    "wof:name":"Pelletterie Artistiche Florence",
    "wof:placetype":"venue"
},
  "geometry": {"coordinates":[11.155793,43.762646],"type":"Point"}
}