{
  "type": "Feature",
  "properties": {
    "iso:country":"IT",
    "sg:address":"21058 Solbiate Olona",
    "sg:city":"Solbiate Olona",
    "sg:orig_category":"Macchine, Impianti E Forniture Per Industria Grafica, Cartaria E Cartotecnica",
    "sg:phone":"+39 0331 642953",
    "sg:postcode":"21058",
    "sg:province":"Varese",
    "wof:name":"Tecnoindustria S.r.l.",
    "wof:placetype":"venue"
},
  "geometry": {"coordinates":[8.87587,45.649384],"type":"Point"}
}