{
  "type": "Feature",
  "properties": {
    "iso:country":"IT",
    "sg:address":"52011 Bibbiena",
    "sg:city":"Bibbiena",
    "sg:orig_category":"Servizi E Lavori Per Arredamento E Industria Del Legno",
    "sg:phone":"+39 0575 560242",
    "sg:postcode":"52011",
    "sg:province":"Arezzo",
    "wof:name":"Renzetti Saverio & Fratelli Snc",
    "wof:placetype":"venue"
},
  "geometry": {"coordinates":[11.812037,43.730331],"type":"Point"}
}