{
  "type": "Feature",
  "properties": {
    "addr:full":"01100 Viterbo Viterbo Viterbo 01100",
    "addr:postcode":"01100;01100",
    "iso:country":"IT",
    "sg:address":"01100 Viterbo",
    "sg:city":"Viterbo",
    "sg:orig_category":"Falegnami",
    "sg:phone":"+39 0761 321031",
    "sg:postcode":"01100",
    "sg:province":"Viterbo",
    "wof:name":"Falegnameria Marignoli Marco",
    "wof:placetype":"venue"
},
  "geometry": {"coordinates":[12.0955762863,42.4370269775],"type":"Point"}
}