{
  "type": "Feature",
  "properties": {
    "addr:full":"00199 Roma Roma Roma 00199",
    "addr:postcode":"00199;00199",
    "iso:country":"IT",
    "sg:address":"00199 Roma",
    "sg:city":"Roma",
    "sg:orig_category":"Arredi Ed Attrezzature Per Uffici. Forniture Per Congressi, Fiere E Manifestazioni",
    "sg:phone":"+39 06 884 0340",
    "sg:postcode":"00199",
    "sg:province":"Roma",
    "wof:name":"2m Di Marcello Masi",
    "wof:placetype":"venue"
},
  "geometry": {"coordinates":[12.508398,41.926289],"type":"Point"}
}