{
  "type": "Feature",
  "properties": {
    "iso:country":"IT",
    "sg:address":"42015 Correggio",
    "sg:orig_category":"Prodotti E Manufatti In Materie Plastiche. Articoli Per Imballaggio E Confezionamento",
    "sg:phone":"+39 0522 693445",
    "sg:postcode":"42015",
    "sg:province":"Reggio Nell'Emilia",
    "sg:website":"http://www.isiplast.com",
    "wof:name":"Isi Plast Spa",
    "wof:placetype":"venue"
},
  "geometry": {"coordinates":[10.7927236557,44.7684669495],"type":"Point"}
}