{
  "type": "Feature",
  "properties": {
    "iso:country":"IT",
    "sg:address":"16152 Genova",
    "sg:city":"Genova",
    "sg:orig_category":"Termotecnica E Riscaldamento, Apparecchiature E Servizi. Valvole E Apparecchiature Di Misura. Macchine, Strumenti Ed Apparecchi Per Attivita' Industriali",
    "sg:phone":"+39 010 651 8670",
    "sg:postcode":"16152",
    "sg:province":"Genova",
    "wof:name":"Master (s.r.l.)",
    "wof:placetype":"venue"
},
  "geometry": {"coordinates":[8.88023,44.421707],"type":"Point"}
}