{
  "type": "Feature",
  "properties": {
    "iso:country":"IT",
    "sg:address":"Via S. Martino 11/15 22021 Bellagio",
    "sg:city":"Bellagio",
    "sg:classifiers":[
        {
            "category":"Structure",
            "subcategory":"Factory",
            "type":"Public Place"
        }
    ],
    "sg:phone":"+39 031 950379",
    "sg:postcode":"22021",
    "sg:province":"Como",
    "sg:tags":[
        "milking",
        "machine",
        "plant"
    ],
    "sg:website":"www.royal-mungitrici.com",
    "wof:name":"Royal Di Silva Valerio",
    "wof:placetype":"venue"
},
  "geometry": {"coordinates":[9.2648639679,45.9994773865],"type":"Point"}
}