{
  "type": "Feature",
  "properties": {
    "addr:full":"36050 Pozzoleone Pozzoleone Vicenza 36050",
    "addr:postcode":"36050;36050",
    "iso:country":"IT",
    "sg:address":"36050 Pozzoleone",
    "sg:city":"Pozzoleone",
    "sg:orig_category":"Pubblicita' - Agenzie Studi",
    "sg:phone":"+39 0444 462334",
    "sg:postcode":"36050",
    "sg:province":"Vicenza",
    "wof:name":"Carrozzeria Conzato Di Mansueto Conzato & C. Snc",
    "wof:placetype":"venue"
},
  "geometry": {"coordinates":[11.6640129089,45.6418228149],"type":"Point"}
}