{
  "type": "Feature",
  "properties": {
    "iso:country":"IT",
    "sg:address":"20144 Milano",
    "sg:city":"Milano",
    "sg:orig_category":"Dolciumi E Gelati",
    "sg:phone":"+39 02 8940 6259",
    "sg:postcode":"20144",
    "sg:province":"Milano",
    "wof:name":"Pane Cioccolato Di Riccardo Penta Sas",
    "wof:placetype":"venue"
},
  "geometry": {"coordinates":[9.16593,45.456051],"type":"Point"}
}