{
  "type": "Feature",
  "properties": {
    "iso:country":"IT",
    "sg:address":"20145 Milano",
    "sg:city":"Milano",
    "sg:orig_category":"Materiali E Componenti Elettronici",
    "sg:phone":"+39 02 4800 2447",
    "sg:postcode":"20145",
    "sg:province":"Milano",
    "wof:name":"Nowel S.r.l.",
    "wof:placetype":"venue"
},
  "geometry": {"coordinates":[9.15981,45.4729],"type":"Point"}
}