{
  "type": "Feature",
  "properties": {
    "iso:country":"IT",
    "sg:address":"22030 Castelmarte",
    "sg:city":"Castelmarte",
    "sg:orig_category":"Abbigliamento Intimo, Calze E Costumi Da Bagno. Articoli Medico-sanitari Ed Ortopedici",
    "sg:phone":"+39 031 621616",
    "sg:postcode":"22030",
    "sg:province":"Como",
    "wof:name":"Novaflex Di Forni E. & C. Snc",
    "wof:placetype":"venue"
},
  "geometry": {"coordinates":[9.25006,45.818825],"type":"Point"}
}