{
  "type": "Feature",
  "properties": {
    "iso:country":"IT",
    "sg:address":"Via Repubblica 4; Costermano; 37010",
    "sg:city":"Costermano",
    "sg:classifiers":[
        {
            "category":"Banks & Credit Unions",
            "subcategory":"Bank",
            "type":"Services"
        }
    ],
    "sg:phone":"+39 045 720 0855",
    "sg:postcode":"37010",
    "sg:province":"Verona",
    "wof:name":"Cassa Rurale Ed Artigiana, Di Costermano",
    "wof:placetype":"venue"
},
  "geometry": {"coordinates":[10.741405,45.585056],"type":"Point"}
}