{
  "type": "Feature",
  "properties": {
    "addr:full":"314, Via Madonna 37051 Bovolone Bovolone Verona 37051",
    "addr:housenumber":"314",
    "addr:postcode":"37051;37051",
    "addr:street":"Via Madonna",
    "iso:country":"IT",
    "sg:address":"314, Via Madonna 37051 Bovolone",
    "sg:city":"Bovolone",
    "sg:classifiers":[
        {
            "category":"Shopping",
            "subcategory":"Crafts & Fabrics",
            "type":"Retail Goods"
        }
    ],
    "sg:phone":"+39 045 710 3588",
    "sg:postcode":"37051",
    "sg:province":"Verona",
    "wof:name":"Abramtex Di Abram Pietro E C. (s.n.c.)",
    "wof:placetype":"venue"
},
  "geometry": {"coordinates":[11.1004829407,45.2705421448],"type":"Point"}
}