{
  "type": "Feature",
  "properties": {
    "iso:country":"IT",
    "sg:address":"1, Via La Forna 60020 Sirolo",
    "sg:city":"Sirolo",
    "sg:classifiers":[
        {
            "category":"Manufacturing",
            "subcategory":"Rubber & Plastics",
            "type":"Manufacturing & Wholesale Goods"
        }
    ],
    "sg:phone":"+39 071 736 0014",
    "sg:postcode":"60020",
    "sg:province":"Ancona",
    "wof:name":"Esse Bi Plastic",
    "wof:placetype":"venue"
},
  "geometry": {"coordinates":[13.6084089279,43.5150108337],"type":"Point"}
}