{
  "type": "Feature",
  "properties": {
    "iso:country":"IT",
    "sg:address":"20122 Milano",
    "sg:city":"Milano",
    "sg:orig_category":"Scuole E Servizi Scolastici. Alberghi E Strutture Extra Alberghiere",
    "sg:phone":"+39 02 722171",
    "sg:postcode":"20122",
    "sg:province":"Milano",
    "wof:name":"Pensionato Padre Semeria",
    "wof:placetype":"venue"
},
  "geometry": {"coordinates":[9.188178,45.460888],"type":"Point"}
}