{
  "type": "Feature",
  "properties": {
    "iso:country":"IT",
    "sg:address":"24, Via Guido Rossa 26025 Pandino",
    "sg:city":"Pandino",
    "sg:classifiers":[
        {
            "category":"Manufacturing",
            "subcategory":"Lumber",
            "type":"Manufacturing & Wholesale Goods"
        }
    ],
    "sg:phone":"+39 0373 920437",
    "sg:postcode":"26025",
    "sg:province":"Cremona",
    "sg:tags":[
        "wood"
    ],
    "wof:name":"I Falegnami Di Valota Angelo E C. S.n.c.",
    "wof:placetype":"venue"
},
  "geometry": {"coordinates":[9.543603,45.398075],"type":"Point"}
}