{
  "type": "Feature",
  "properties": {
    "iso:country":"IT",
    "sg:address":"20129 Milano",
    "sg:city":"Milano",
    "sg:orig_category":"Clothing, Accessories",
    "sg:phone":"+39 02 2940 0557",
    "sg:postcode":"20129",
    "sg:province":"Milano",
    "wof:name":"Duca Cravatte Snc",
    "wof:placetype":"venue"
},
  "geometry": {"coordinates":[9.208474,45.474632],"type":"Point"}
}