{
  "type": "Feature",
  "properties": {
    "iso:country":"IT",
    "sg:address":"70010 Sammichele Di Bari",
    "sg:city":"Sammichele di Bari",
    "sg:orig_category":"Arredamenti - Vendita Al Dettaglio",
    "sg:phone":"+39 080 891 7377",
    "sg:postcode":"70010",
    "sg:province":"Bari",
    "sg:website":"http://www.mobilibattista.it",
    "wof:name":"Battista Vito Antonio",
    "wof:placetype":"venue"
},
  "geometry": {"coordinates":[16.94828,40.887512],"type":"Point"}
}