{
  "type": "Feature",
  "properties": {
    "iso:country":"IT",
    "sg:address":"11, Via Garibaldi 22070 Montano Lucino",
    "sg:city":"Lucino",
    "sg:classifiers":[
        {
            "category":"Shopping",
            "subcategory":"Crafts & Fabrics",
            "type":"Retail Goods"
        }
    ],
    "sg:phone":"+39 39031470104",
    "sg:postcode":"22070",
    "sg:province":"Como",
    "wof:name":"Tessitura Serica Luigi Arnaboldi (s.r.l.)",
    "wof:placetype":"venue"
},
  "geometry": {"coordinates":[9.079123497,45.8112792969],"type":"Point"}
}