{
  "type": "Feature",
  "properties": {
    "iso:country":"IT",
    "sg:address":"27, Via Bixio Nino 20129 Milano",
    "sg:city":"Milano",
    "sg:classifiers":[
        {
            "category":"Professional",
            "subcategory":"Advertising",
            "type":"Services"
        }
    ],
    "sg:phone":"+39 39022043365",
    "sg:postcode":"20129",
    "sg:province":"Milano",
    "sg:tags":[
        "communication",
        "medium"
    ],
    "wof:name":"Damioli & Damioli S.r.l.",
    "wof:placetype":"venue"
},
  "geometry": {"coordinates":[9.208471,45.472183],"type":"Point"}
}