{
  "type": "Feature",
  "properties": {
    "iso:country":"IT",
    "sg:address":"50068 Rufina",
    "sg:city":"Rufina",
    "sg:orig_category":"Servizi Per Aziende, Manifestazioni E Supporto Agli Scambi Commerciali",
    "sg:phone":"+39 055 839 8477",
    "sg:postcode":"50068",
    "sg:province":"Firenze",
    "wof:name":"Mucelli Giovanni",
    "wof:placetype":"venue"
},
  "geometry": {"coordinates":[11.495967,43.81892],"type":"Point"}
}