{
  "type": "Feature",
  "properties": {
    "iso:country":"IT",
    "sg:address":"Localita' Sa Mattanosa Cala Liberotto 08028 Orosei",
    "sg:city":"Cala Liberotto",
    "sg:classifiers":[
        {
            "category":"Travel",
            "subcategory":"Travel Agent",
            "type":"Entertainment"
        }
    ],
    "sg:phone":"+39 39078491230",
    "sg:postcode":"08028",
    "sg:province":"Nuoro",
    "sg:tags":[
        "business"
    ],
    "wof:name":"Club Hotel Torre Moresca",
    "wof:placetype":"venue"
},
  "geometry": {"coordinates":[9.330436,40.321007],"type":"Point"}
}