{
  "type": "Feature",
  "properties": {
    "iso:country":"IT",
    "sg:address":"30027 San Dona'dipiave",
    "sg:orig_category":"Servizi E Lavori Per Agricoltura E Zootecnia",
    "sg:phone":"+39 0421 320404",
    "sg:postcode":"30027",
    "sg:province":"Venezia",
    "wof:name":"Serafin Roberto",
    "wof:placetype":"venue"
},
  "geometry": {"coordinates":[12.593511,45.636463],"type":"Point"}
}