{
  "type": "Feature",
  "properties": {
    "iso:country":"IT",
    "sg:address":"91020 Petrosino",
    "sg:city":"Petrosino",
    "sg:orig_category":"Articoli Pulizia. Carta, Cartone E Prodotti Primari. Prodotti Cosmetici E Da Toeletta",
    "sg:phone":"+39 0923 961958",
    "sg:postcode":"91020",
    "sg:province":"Trapani",
    "wof:name":"Diana 2000 Srl",
    "wof:placetype":"venue"
},
  "geometry": {"coordinates":[12.526904,37.716999],"type":"Point"}
}