{
  "type": "Feature",
  "properties": {
    "iso:country":"IT",
    "sg:address":"33080 San Quirino",
    "sg:city":"San Quirino",
    "sg:orig_category":"Prodotti E Manufatti In Materie Plastiche",
    "sg:phone":"+39 0434 917053",
    "sg:postcode":"33080",
    "sg:province":"Pordenone",
    "sg:website":"http://www.imacsrl.it",
    "wof:name":"I.ma.c. Srl",
    "wof:placetype":"venue"
},
  "geometry": {"coordinates":[12.6504964828,46.0310707092],"type":"Point"}
}