{
  "type": "Feature",
  "properties": {
    "addr:full":"53100 Castiglione D'orcia Siena Siena 53100",
    "addr:postcode":"53100;53100",
    "iso:country":"IT",
    "sg:address":"53100 Castiglione D'orcia",
    "sg:city":"Siena",
    "sg:orig_category":"Petroli, Gas E Combustibili. Servizi E Lavori Industria Chimica. Servizi E Lavori Per Edilizia E Lavori Pubblici. Acqua, Luce, Gas E Societa' Di Esercizio Pubblico",
    "sg:phone":"+39 0577 264511",
    "sg:postcode":"53100",
    "sg:province":"Siena",
    "wof:name":"Intesa Consorzio Intercomunale Energia Servizi Acqua",
    "wof:placetype":"venue"
},
  "geometry": {"coordinates":[11.3305139542,43.3186607361],"type":"Point"}
}