{
  "type": "Feature",
  "properties": {
    "iso:country":"IT",
    "sg:address":"00132 Roma",
    "sg:city":"Roma",
    "sg:orig_category":"Servizi Di Magazzinaggio E Movimentazione. Servizi Ausiliari Di Sorveglianza, Manutenzione E Pulizia",
    "sg:phone":"+39 06 2076 1805",
    "sg:postcode":"00132",
    "sg:province":"Roma",
    "sg:website":"http://www.trades-on-line.it",
    "wof:name":"Tra.d.e S. Soc.coop.r.l",
    "wof:placetype":"venue"
},
  "geometry": {"coordinates":[12.691764,41.875683],"type":"Point"}
}