{
  "type": "Feature",
  "properties": {
    "addr:full":"01027 Montefiascone Montefiascone Viterbo 01027",
    "addr:postcode":"01027;01027",
    "iso:country":"IT",
    "sg:address":"01027 Montefiascone",
    "sg:city":"Montefiascone",
    "sg:orig_category":"Prodotti Alimentari",
    "sg:phone":"+39 0761 823182",
    "sg:postcode":"01027",
    "sg:province":"Viterbo",
    "wof:name":"Ingrosso Jolly Jel Di Ranucci Antonella",
    "wof:placetype":"venue"
},
  "geometry": {"coordinates":[12.0942411423,42.5468902588],"type":"Point"}
}