{
  "type": "Feature",
  "properties": {
    "iso:country":"IT",
    "sg:address":"14100 Asti",
    "sg:city":"Asti",
    "sg:orig_category":"Pianoforti",
    "sg:phone":"+39 0141 530078",
    "sg:postcode":"14100",
    "sg:province":"Asti",
    "sg:website":"http://www.cerratopianoforti.com",
    "wof:name":"Cerrato Davide",
    "wof:placetype":"venue"
},
  "geometry": {"coordinates":[8.2136564255,44.9102401733],"type":"Point"}
}