{
  "type": "Feature",
  "properties": {
    "iso:country":"IT",
    "sg:address":"00187 Roma",
    "sg:city":"Roma",
    "sg:orig_category":"Agenzie Ed Enti Turistici. Acqua, Luce, Gas E Societa' Di Esercizio Pubblico",
    "sg:phone":"+39 06 474 4988",
    "sg:postcode":"00187",
    "sg:province":"Roma",
    "wof:name":"Sicilia Ufficio Di Promozione Turistica Di Ruggieri Massimo",
    "wof:placetype":"venue"
},
  "geometry": {"coordinates":[12.372405,42.131073],"type":"Point"}
}