{
  "type": "Feature",
  "properties": {
    "iso:country":"IT",
    "sg:address":"95020 Acibonaccorsi",
    "sg:orig_category":"Prodotti Chimici Secondari. Macchine E Forniture Per Ecologia E Smaltimento Rifiuti. Forniture Per Attivita' Industriali",
    "sg:phone":"+39 095 789379",
    "sg:postcode":"95020",
    "sg:province":"Catania",
    "wof:name":"Ilcom Srl",
    "wof:placetype":"venue"
},
  "geometry": {"coordinates":[15.1480493546,37.5557365417],"type":"Point"}
}