{
  "type": "Feature",
  "properties": {
    "iso:country":"IT",
    "sg:address":"27, Via Maestri Del Lavoro 05100 Terni",
    "sg:city":"Terni",
    "sg:classifiers":[
        {
            "category":"Home & Garden",
            "subcategory":"Home Furnishings",
            "type":"Retail Goods"
        }
    ],
    "sg:phone":"+39 0744 814253",
    "sg:postcode":"05100",
    "sg:province":"Terni",
    "sg:tags":[
        "household"
    ],
    "wof:name":"Mobilnova Di Cianchetta M. & C.(s.n.c.)",
    "wof:placetype":"venue"
},
  "geometry": {"coordinates":[12.605523,42.549316],"type":"Point"}
}