{
  "type": "Feature",
  "properties": {
    "addr:full":"20089 Rozzano Rozzano Milano 20089",
    "addr:postcode":"20089;20089",
    "iso:country":"IT",
    "sg:address":"20089 Rozzano",
    "sg:city":"Rozzano",
    "sg:orig_category":"Arte Ed Artigianato Artistico",
    "sg:phone":"+39 02 825 9326",
    "sg:postcode":"20089",
    "sg:province":"Milano",
    "wof:name":"L.m. Lavorazione Metalli S.r.l.",
    "wof:placetype":"venue"
},
  "geometry": {"coordinates":[9.172891,45.398281],"type":"Point"}
}