{
  "type": "Feature",
  "properties": {
    "addr:full":"Piazza Liberta 11; Azzano",
    "addr:housenumber":"11",
    "addr:street":"Piazza Liberta",
    "iso:country":"IT",
    "sg:address":"Piazza Liberta 11; Azzano",
    "sg:classifiers":[
        {
            "category":"Banks & Credit Unions",
            "subcategory":"Bank",
            "type":"Services"
        }
    ],
    "sg:phone":"+39 0434 631981",
    "wof:name":"Banca Popolare Friuladria",
    "wof:placetype":"venue"
},
  "geometry": {"coordinates":[12.71363,45.881626],"type":"Point"}
}