{
  "type": "Feature",
  "properties": {
    "addr:full":"92100 Agrigento Agrigento Agrigento 92100",
    "addr:postcode":"92100;92100",
    "iso:country":"IT",
    "sg:address":"92100 Agrigento",
    "sg:city":"Agrigento",
    "sg:orig_category":"Pelliccerie",
    "sg:phone":"+39 0922 554703",
    "sg:postcode":"92100",
    "sg:province":"Agrigento",
    "wof:name":"Alaimo Giovanna",
    "wof:placetype":"venue"
},
  "geometry": {"coordinates":[13.5828609467,37.3136825562],"type":"Point"}
}