{
  "type": "Feature",
  "properties": {
    "addr:full":"16161 Genova Rivarolo Genova Genova 16161",
    "addr:housenumber":"16161",
    "addr:postcode":"16161",
    "iso:country":"IT",
    "sg:address":"16161 Genova Rivarolo",
    "sg:city":"Genova",
    "sg:orig_category":"Nautica. Automobili E Mezzi Di Trasporto",
    "sg:phone":"+39 010 749 2509",
    "sg:postcode":"16161",
    "sg:province":"Genova",
    "wof:name":"Campello Marco",
    "wof:placetype":"venue"
},
  "geometry": {"coordinates":[8.892963,44.43853],"type":"Point"}
}