{
  "type": "Feature",
  "properties": {
    "iso:country":"IT",
    "sg:address":"00166 Roma",
    "sg:city":"Roma",
    "sg:orig_category":"Servizi E Lavori Per Arredamento E Industria Del Legno. Servizi Di Magazzinaggio E Movimentazione",
    "sg:phone":"+39 06 6190 1738",
    "sg:postcode":"00166",
    "sg:province":"Roma",
    "wof:name":"Trasporti Nazionali 2001 Coop. Arl",
    "wof:placetype":"venue"
},
  "geometry": {"coordinates":[12.351637,41.915562],"type":"Point"}
}