{
  "type": "Feature",
  "properties": {
    "addr:full":"04011 Aprilia Aprilia Latina 04011",
    "addr:postcode":"04011;04011",
    "iso:country":"IT",
    "sg:address":"04011 Aprilia",
    "sg:city":"Aprilia",
    "sg:orig_category":"Macchine Utensili E Impianti",
    "sg:phone":"+39 06 9274 6192",
    "sg:postcode":"04011",
    "sg:province":"Latina",
    "wof:name":"Gima S.r.l.",
    "wof:placetype":"venue"
},
  "geometry": {"coordinates":[12.638071,41.551136],"type":"Point"}
}