{
  "type": "Feature",
  "properties": {
    "iso:country":"IT",
    "sg:address":"Via Vitelleschi 34; Rome",
    "sg:classifiers":[
        {
            "category":"Travel",
            "subcategory":"Travel Agent",
            "type":"Entertainment"
        }
    ],
    "wof:name":"Atlante Hotels",
    "wof:placetype":"venue"
},
  "geometry": {"coordinates":[12.462029,41.904583],"type":"Point"}
}