{
  "type": "Feature",
  "properties": {
    "addr:full":"20041 Agrate Brianza Agrate Brianza Milano 20041",
    "addr:postcode":"20041;20041",
    "iso:country":"IT",
    "sg:address":"20041 Agrate Brianza",
    "sg:city":"Agrate Brianza",
    "sg:classifiers":[
        {
            "category":"Professional",
            "subcategory":"Engineering",
            "type":"Services"
        }
    ],
    "sg:phone":"+39 039 605 7069",
    "sg:postcode":"20041",
    "sg:province":"Milano",
    "sg:tags":[
        "equipment",
        "product",
        "industrial",
        "electronic"
    ],
    "sg:website":"http://www.advantest.com",
    "wof:name":"Advantest (europe Gmbh)",
    "wof:placetype":"venue"
},
  "geometry": {"coordinates":[9.353541,45.572975],"type":"Point"}
}