{
  "type": "Feature",
  "properties": {
    "addr:full":"4, Via Provinciale 26010 Corte De' Frati Cremona 26010",
    "addr:postcode":"26010;26010",
    "addr:street":"Via Provinciale;De ' Frati Cremona",
    "iso:country":"IT",
    "sg:address":"4, Via Provinciale 26010 Corte De' Frati",
    "sg:classifiers":[
        {
            "category":"Bars & Pubs",
            "subcategory":"Nightclub",
            "type":"Food & Drink"
        }
    ],
    "sg:phone":"+39 39037293156",
    "sg:postcode":"26010",
    "sg:province":"Cremona",
    "sg:tags":[
        "cake",
        "bread"
    ],
    "wof:name":"Gadeschi Dolciaria (s.p.a.)",
    "wof:placetype":"venue"
},
  "geometry": {"coordinates":[10.026135,45.133499],"type":"Point"}
}