{
  "type": "Feature",
  "properties": {
    "addr:full":"14, Viale Dei Mareschi 10051 Avigliana Avigliana Torino 10051",
    "addr:housenumber":"14",
    "addr:postcode":"10051;10051",
    "addr:street":"Viale Dei Mareschi",
    "iso:country":"IT",
    "sg:address":"14, Viale Dei Mareschi 10051 Avigliana",
    "sg:city":"Avigliana",
    "sg:classifiers":[
        {
            "category":"Shopping",
            "type":"Retail Goods"
        }
    ],
    "sg:phone":"+39 011 936 9389",
    "sg:postcode":"10051",
    "sg:province":"Torino",
    "sg:tags":[
        "finished",
        "-",
        "metallic"
    ],
    "wof:name":"Secam (s.r.l.)",
    "wof:placetype":"venue"
},
  "geometry": {"coordinates":[7.3818182945,45.0837440491],"type":"Point"}
}