{
  "type": "Feature",
  "properties": {
    "iso:country":"IT",
    "sg:address":"Strada Comunale S. Leucio 86170 Isernia",
    "sg:city":"Isernia",
    "sg:classifiers":[
        {
            "category":"Shopping",
            "subcategory":"Clothing, Apparel, & Fashions",
            "type":"Retail Goods"
        }
    ],
    "sg:phone":"+39 0865 451241",
    "sg:postcode":"86170",
    "sg:province":"Isernia",
    "sg:tags":[
        "clothes"
    ],
    "wof:name":"2 C Corredi (s.n.c.)",
    "wof:placetype":"venue"
},
  "geometry": {"coordinates":[14.230827,41.594334],"type":"Point"}
}