{
  "type": "Feature",
  "properties": {
    "iso:country":"IT",
    "sg:address":"80144 Chiaiano",
    "sg:city":"Napoli",
    "sg:orig_category":"Magazzini Custodia Mobili",
    "sg:phone":"+39 081 740 7762",
    "sg:postcode":"80144",
    "sg:province":"Napoli",
    "wof:name":"Petito Massimo",
    "wof:placetype":"venue"
},
  "geometry": {"coordinates":[14.224893,40.885658],"type":"Point"}
}