{
  "type": "Feature",
  "properties": {
    "iso:country":"IT",
    "sg:address":"Via E. Fermi 6 20040 Burago Di Molgora",
    "sg:city":"Burago di Molgora",
    "sg:classifiers":[
        {
            "category":"Wholesale",
            "subcategory":"Metals & Minerals",
            "type":"Manufacturing & Wholesale Goods"
        }
    ],
    "sg:phone":"+39 039 608 1118",
    "sg:postcode":"20040",
    "sg:province":"Milano",
    "sg:tags":[
        "heavy",
        "plate",
        "sheet",
        "thin"
    ],
    "sg:website":"www.lamierecollaudate.com",
    "wof:name":"Lamiere Collaudate Spa",
    "wof:placetype":"venue"
},
  "geometry": {"coordinates":[9.188141,45.463688],"type":"Point"}
}