{
  "type": "Feature",
  "properties": {
    "iso:country":"IT",
    "sg:address":"28078 Romagnano Sesia",
    "sg:city":"Romagnano Sesia",
    "sg:orig_category":"Apparecchiature E Sistemi Per Magazzinaggio E Movimentazione. Servizi Di Magazzinaggio E Movimentazione",
    "sg:phone":"+39 0163 834280",
    "sg:postcode":"28078",
    "sg:province":"Novara",
    "wof:name":"Brugo Pierantonio",
    "wof:placetype":"venue"
},
  "geometry": {"coordinates":[8.386773,45.629932],"type":"Point"}
}