{
  "type": "Feature",
  "properties": {
    "iso:country":"IT",
    "sg:address":"00141 Roma",
    "sg:city":"Roma",
    "sg:classifiers":[
        {
            "category":"Health Services",
            "subcategory":"Health Practitioner",
            "type":"Services"
        }
    ],
    "sg:phone":"+39 06 817 3245",
    "sg:postcode":"00141",
    "sg:province":"Roma",
    "sg:tags":[
        "medici"
    ],
    "wof:name":"Giardina Marco Maria",
    "wof:placetype":"venue"
},
  "geometry": {"coordinates":[12.536616,41.938503],"type":"Point"}
}