{
  "type": "Feature",
  "properties": {
    "iso:country":"IT",
    "sg:address":"01034 Fabrica Di Roma",
    "sg:city":"Fabrica di Roma",
    "sg:orig_category":"Ceramica Uso Tecnico Ed Industriale",
    "sg:phone":"+39 0761 513488",
    "sg:postcode":"01034",
    "sg:province":"Viterbo",
    "wof:name":"Euromodel Srl",
    "wof:placetype":"venue"
},
  "geometry": {"coordinates":[12.352063,42.293777],"type":"Point"}
}