{
  "type": "Feature",
  "properties": {
    "addr:full":"04100 Latina Latina Latina 04100",
    "addr:postcode":"04100;04100",
    "iso:country":"IT",
    "sg:address":"04100 Latina",
    "sg:city":"Latina",
    "sg:orig_category":"Pubblica Amministrazione",
    "sg:phone":"+39 0773 40861",
    "sg:postcode":"04100",
    "sg:province":"Latina",
    "wof:name":"Vigili Del Fuoco",
    "wof:placetype":"venue"
},
  "geometry": {"coordinates":[12.901558876,41.5774269104],"type":"Point"}
}