{
  "type": "Feature",
  "properties": {
    "addr:full":"5, Via Monte Cimone 37057 San Giovanni Lupatoto San Giovanni Lupatoto Verona 37057",
    "addr:postcode":"37057;37057",
    "addr:street":"Via Monte Cimone;Verona",
    "iso:country":"IT",
    "sg:address":"5, Via Monte Cimone 37057 San Giovanni Lupatoto",
    "sg:city":"San Giovanni Lupatoto",
    "sg:classifiers":[
        {
            "category":"Manufacturing",
            "subcategory":"Glass & Minerals",
            "type":"Manufacturing & Wholesale Goods"
        }
    ],
    "sg:phone":"+39 39045549055",
    "sg:postcode":"37057",
    "sg:province":"Verona",
    "wof:name":"Gibo S.a.s.",
    "wof:placetype":"venue"
},
  "geometry": {"coordinates":[11.03078,45.391815],"type":"Point"}
}