{
  "type": "Feature",
  "properties": {
    "addr:full":"22021 Bellagio Bellagio Como 22021",
    "addr:postcode":"22021;22021",
    "iso:country":"IT",
    "sg:address":"22021 Bellagio",
    "sg:city":"Bellagio",
    "sg:orig_category":"Alberghi",
    "sg:phone":"+39 031 950216",
    "sg:postcode":"22021",
    "sg:province":"Como",
    "sg:website":"http://www.villaserbelloni.it",
    "wof:name":"Grand Hotel Villa Serbelloni",
    "wof:placetype":"venue"
},
  "geometry": {"coordinates":[8.928926,45.788612],"type":"Point"}
}