{
  "type": "Feature",
  "properties": {
    "addr:full":"33, Via Cervito Zona Industriale 84084 Fisciano Fisciano Salerno 84084",
    "addr:postcode":"84084;84084",
    "addr:street":"Via Cervito Zona Industriale",
    "iso:country":"IT",
    "sg:address":"33, Via Cervito Zona Industriale 84084 Fisciano",
    "sg:city":"Fisciano",
    "sg:classifiers":[
        {
            "category":"Shopping",
            "subcategory":"Crafts & Fabrics",
            "type":"Retail Goods"
        }
    ],
    "sg:phone":"+39 39089826169",
    "sg:postcode":"84084",
    "sg:province":"Salerno",
    "sg:tags":[
        "ceramic"
    ],
    "wof:name":"Ceramica Artistica G. De Maio S.r.l.",
    "wof:placetype":"venue"
},
  "geometry": {"coordinates":[14.765912,40.677956],"type":"Point"}
}