{
  "type": "Feature",
  "properties": {
    "iso:country":"IT",
    "sg:address":"Via Trieste 7; Alte Di Montecchio Maggiore; 36041",
    "sg:classifiers":[
        {
            "category":"Banks & Credit Unions",
            "subcategory":"Bank",
            "type":"Services"
        }
    ],
    "sg:phone":"+39 0444 698090",
    "wof:name":"Banca Popolare Vicentina Scarl",
    "wof:placetype":"venue"
},
  "geometry": {"coordinates":[11.431554,45.495522],"type":"Point"}
}