{
  "type": "Feature",
  "properties": {
    "iso:country":"IT",
    "sg:address":"02032 Fara In Sabina",
    "sg:city":"Fara in Sabina",
    "sg:orig_category":"Servizi Ausiliari Per Il Trasporto. Servizi Vari Di Interesse Pubblico",
    "sg:phone":"+39 0765 488144",
    "sg:postcode":"02032",
    "sg:province":"Rieti",
    "sg:website":"http://www.ofionoranzefunebri.it",
    "wof:name":"O.f.i. Onoranze Funebri Internazionali",
    "wof:placetype":"venue"
},
  "geometry": {"coordinates":[12.862378,42.397469],"type":"Point"}
}