{
  "type": "Feature",
  "properties": {
    "iso:country":"IT",
    "sg:address":"Sda Ferrari 38 43014 Medesano",
    "sg:city":"Medesano",
    "sg:classifiers":[
        {
            "category":"Bars & Pubs",
            "subcategory":"Dive Bar",
            "type":"Food & Drink"
        }
    ],
    "sg:phone":"+39 0525 420929",
    "sg:postcode":"43014",
    "sg:province":"Parma",
    "sg:tags":[
        "hammer"
    ],
    "sg:website":"www.socomec-spa.com",
    "wof:name":"Socomec Costruzioni Meccaniche Spa",
    "wof:placetype":"venue"
},
  "geometry": {"coordinates":[10.170564,44.805717],"type":"Point"}
}