{
  "type": "Feature",
  "properties": {
    "iso:country":"IT",
    "sg:address":"20099 Sesto San Giovanni",
    "sg:city":"Sesto San Giovanni",
    "sg:orig_category":"Impiantistica E Prodotti Tecnologici Per Edilizia. Macchine, Strumenti Ed Apparecchi Per Attivita' Industriali",
    "sg:phone":"+39 02 262971",
    "sg:postcode":"20099",
    "sg:province":"Milano",
    "wof:name":"Foxboro Italia S.p.a.",
    "wof:placetype":"venue"
},
  "geometry": {"coordinates":[9.221711,45.531471],"type":"Point"}
}