{
  "type": "Feature",
  "properties": {
    "iso:country":"IT",
    "sg:address":"74026 Marina Di Pulsano",
    "sg:city":"Pulsano",
    "sg:orig_category":"Alberghi E Strutture Extra Alberghiere. Ospedali E Servizi Sanitari",
    "sg:phone":"+39 099 533 3089",
    "sg:postcode":"74026",
    "sg:province":"Taranto",
    "wof:name":"Suore Stimmatine Asilo Nido E Materna",
    "wof:placetype":"venue"
},
  "geometry": {"coordinates":[17.347822,40.359978],"type":"Point"}
}