{
  "type": "Feature",
  "properties": {
    "iso:country":"IT",
    "sg:address":"U. Le Puccini,; Lucca",
    "sg:classifiers":[
        {
            "category":"Banks & Credit Unions",
            "subcategory":"Bank",
            "type":"Services"
        }
    ],
    "sg:phone":"+39 0583 450408",
    "wof:name":"Banca Del Monte, Di Lucca Spa",
    "wof:placetype":"venue"
},
  "geometry": {"coordinates":[10.434979,43.730755],"type":"Point"}
}