{
  "type": "Feature",
  "properties": {
    "iso:country":"IT",
    "sg:address":"90145 Palermo",
    "sg:city":"Palermo",
    "sg:orig_category":"Disinfezione, Disinfestazione E Derattizzazione",
    "sg:phone":"+39 091 682 1297",
    "sg:postcode":"90145",
    "sg:province":"Palermo",
    "wof:name":"A.s.i.f. Srl",
    "wof:placetype":"venue"
},
  "geometry": {"coordinates":[13.33426,38.129833],"type":"Point"}
}