{
  "type": "Feature",
  "properties": {
    "iso:country":"IT",
    "sg:address":"Via Della Liberta 36b; Busana; 42036",
    "sg:classifiers":[
        {
            "category":"Banks & Credit Unions",
            "subcategory":"Bank",
            "type":"Services"
        }
    ],
    "sg:phone":"+39 0522 891372",
    "wof:name":"Cassa Di Risparmio, Di Reggio Emilia Spa",
    "wof:placetype":"venue"
},
  "geometry": {"coordinates":[10.32431,44.368855],"type":"Point"}
}