{
  "type": "Feature",
  "properties": {
    "addr:full":"20146 Milano Milano Milano 20146",
    "addr:postcode":"20146;20146",
    "iso:country":"IT",
    "sg:address":"20146 Milano",
    "sg:city":"Milano",
    "sg:orig_category":"Pubblicita', Marketing E Comunicazione",
    "sg:phone":"+39 02 4640 0400",
    "sg:postcode":"20146",
    "sg:province":"Milano",
    "sg:website":"http://www.viacavo.it",
    "wof:name":"Viacavo Divis. Stratos Srl",
    "wof:placetype":"venue"
},
  "geometry": {"coordinates":[9.155005455,45.4650344849],"type":"Point"}
}