{
  "type": "Feature",
  "properties": {
    "iso:country":"IT",
    "sg:address":"36020 Campiglia Dei Berici",
    "sg:city":"Campiglia dei Berici",
    "sg:orig_category":"Abbigliamento Donna",
    "sg:phone":"+39 0444 866482",
    "sg:postcode":"36020",
    "sg:province":"Vicenza",
    "wof:name":"Avitex Sas",
    "wof:placetype":"venue"
},
  "geometry": {"coordinates":[11.543445,45.335796],"type":"Point"}
}