{
  "type": "Feature",
  "properties": {
    "addr:full":"Via Appiani Andrea 9 20121 Milano Milano Milano 20121",
    "addr:housenumber":"9",
    "addr:postcode":"20121;20121",
    "addr:street":"Via Appiani Andrea",
    "iso:country":"IT",
    "sg:address":"Via Appiani Andrea 9 20121 Milano",
    "sg:city":"Milano",
    "sg:classifiers":[
        {
            "category":"Manufacturing",
            "subcategory":"Glass & Minerals",
            "type":"Manufacturing & Wholesale Goods"
        }
    ],
    "sg:phone":"+39 02 655 4888",
    "sg:postcode":"20121",
    "sg:province":"Milano",
    "sg:tags":[
        "machine",
        "flat",
        "working"
    ],
    "wof:name":"Cmb Costruzioni Meccaniche Besana Srl",
    "wof:placetype":"venue"
},
  "geometry": {"coordinates":[9.1938886642,45.4770584106],"type":"Point"}
}