{
  "type": "Feature",
  "properties": {
    "iso:country":"IT",
    "sg:address":"Via S Modestino 45; Mercogliano; 83013",
    "sg:city":"Mercogliano",
    "sg:classifiers":[
        {
            "category":"Banks & Credit Unions",
            "subcategory":"Bank",
            "type":"Services"
        }
    ],
    "sg:phone":"+39 0825 788788",
    "sg:postcode":"83013",
    "sg:province":"Avellino",
    "wof:name":"Banco Di Napoli Spa",
    "wof:placetype":"venue"
},
  "geometry": {"coordinates":[14.744214,40.92252],"type":"Point"}
}