{
  "type": "Feature",
  "properties": {
    "iso:country":"IT",
    "sg:address":"14, Corso Savona 10029 Villastellone",
    "sg:city":"Villastellone",
    "sg:classifiers":[
        {
            "category":"Manufacturing",
            "subcategory":"Lumber",
            "type":"Manufacturing & Wholesale Goods"
        }
    ],
    "sg:phone":"+39 011 961 0780",
    "sg:postcode":"10029",
    "sg:province":"Torino",
    "sg:tags":[
        "wood"
    ],
    "wof:name":"Romagnolo (s.r.l.)",
    "wof:placetype":"venue"
},
  "geometry": {"coordinates":[7.71664,44.950481],"type":"Point"}
}