{
  "type": "Feature",
  "properties": {
    "iso:country":"IT",
    "sg:address":"7, Via S. Antonino 23864 Malgrate",
    "sg:city":"Malgrate",
    "sg:classifiers":[
        {
            "category":"Professional",
            "subcategory":"Engineering",
            "type":"Services"
        }
    ],
    "sg:phone":"+39 0341 202008",
    "sg:postcode":"23864",
    "sg:province":"Lecco",
    "sg:tags":[
        "machine",
        "-",
        "mechanical"
    ],
    "wof:name":"Moroni & C. Srl",
    "wof:placetype":"venue"
},
  "geometry": {"coordinates":[9.375713,45.850384],"type":"Point"}
}