{
  "type": "Feature",
  "properties": {
    "addr:full":"7, Via Del Bersagliere 37069 Villafranca Di Verona Villafranca di Verona Verona 37069",
    "addr:postcode":"37069;37069",
    "addr:street":"Via Del Bersagliere;Verona",
    "iso:country":"IT",
    "sg:address":"7, Via Del Bersagliere 37069 Villafranca Di Verona",
    "sg:city":"Villafranca di Verona",
    "sg:classifiers":[
        {
            "category":"Manufacturing",
            "subcategory":"Metals",
            "type":"Manufacturing & Wholesale Goods"
        }
    ],
    "sg:phone":"+39 045 630 1365",
    "sg:postcode":"37069",
    "sg:province":"Verona",
    "sg:tags":[
        "metallurgy",
        "metalworking"
    ],
    "wof:name":"Cusini",
    "wof:placetype":"venue"
},
  "geometry": {"coordinates":[10.8328123093,45.3480911255],"type":"Point"}
}