{
  "type": "Feature",
  "properties": {
    "addr:full":"10134 Torino Torino Torino 10134",
    "addr:postcode":"10134;10134",
    "iso:country":"IT",
    "sg:address":"10134 Torino",
    "sg:city":"Torino",
    "sg:orig_category":"Pubblicita', Marketing E Comunicazione",
    "sg:phone":"+39 011 317 4317",
    "sg:postcode":"10134",
    "sg:province":"Torino",
    "wof:name":"Ditta Peraldo Di Decarolis",
    "wof:placetype":"venue"
},
  "geometry": {"coordinates":[7.6442813873,45.0336227417],"type":"Point"}
}