{
  "type": "Feature",
  "properties": {
    "iso:country":"IT",
    "sg:address":"50012 Bagno A Ripoli",
    "sg:city":"Bagno a Ripoli",
    "sg:classifiers":[
        {
            "category":"Government",
            "subcategory":"Office",
            "type":"Public Place"
        }
    ],
    "sg:phone":"+39 055 649 9108",
    "sg:postcode":"50012",
    "sg:province":"Firenze",
    "sg:tags":[
        "graphic",
        "publishing",
        "supply",
        "industry",
        "equipment",
        "paper",
        "machinery",
        "supplies"
    ],
    "wof:name":"Nuova Cecconi & Nutini Soc. Coop. R.l.",
    "wof:placetype":"venue"
},
  "geometry": {"coordinates":[11.303851,43.706833],"type":"Point"}
}