{
  "type": "Feature",
  "properties": {
    "iso:country":"IT",
    "sg:address":"80012 Calvizzano",
    "sg:city":"Calvizzano",
    "sg:orig_category":"Elettronica Professionale E Di Consumo. Automazione E Macchine Per Ufficio",
    "sg:phone":"+39 081 713 1655",
    "sg:postcode":"80012",
    "sg:province":"Napoli",
    "wof:name":"Castelluccio Vincenzo",
    "wof:placetype":"venue"
},
  "geometry": {"coordinates":[14.185215,40.905495],"type":"Point"}
}