{
  "type": "Feature",
  "properties": {
    "addr:full":"57, Rampe Brancaccio 80132 Napoli Napoli Napoli 80132",
    "addr:housenumber":"57",
    "addr:postcode":"80132;80132",
    "addr:street":"Rampe Brancaccio",
    "iso:country":"IT",
    "sg:address":"57, Rampe Brancaccio 80132 Napoli",
    "sg:city":"Napoli",
    "sg:classifiers":[
        {
            "category":"Real Estate",
            "subcategory":"Surveying",
            "type":"Services"
        }
    ],
    "sg:phone":"+39 39081422924",
    "sg:postcode":"80132",
    "sg:province":"Napoli",
    "sg:tags":[
        "equipment",
        "material",
        "good",
        "-",
        "handling"
    ],
    "wof:name":"Bonavolonta' Fratelli (s.a.s.)",
    "wof:placetype":"venue"
},
  "geometry": {"coordinates":[14.2406959534,40.8371429443],"type":"Point"}
}