{
  "type": "Feature",
  "properties": {
    "addr:full":"Corso Dante 76; Chiavari; 16043 Chiavari Genova 16043",
    "addr:housenumber":"76",
    "addr:postcode":"16043;16043",
    "addr:street":"Corso Dante",
    "iso:country":"IT",
    "sg:address":"Corso Dante 76; Chiavari; 16043",
    "sg:city":"Chiavari",
    "sg:classifiers":[
        {
            "category":"Banks & Credit Unions",
            "subcategory":"Bank",
            "type":"Services"
        }
    ],
    "sg:phone":"+39 0185 304651",
    "sg:postcode":"16043",
    "sg:province":"Genova",
    "wof:name":"Istituto Bancario, San Paolo Di Torino Spa",
    "wof:placetype":"venue"
},
  "geometry": {"coordinates":[9.333172,44.313999],"type":"Point"}
}