{
  "type": "Feature",
  "properties": {
    "iso:country":"IT",
    "sg:address":"35030 Saccolongo",
    "sg:city":"Saccolongo",
    "sg:orig_category":"Trattamenti Termici E Superficiali Metalli, Galvanotecnica",
    "sg:phone":"+39 049 801 5200",
    "sg:postcode":"35030",
    "sg:province":"Padova",
    "wof:name":"C.o.s.m.a.p. Srl",
    "wof:placetype":"venue"
},
  "geometry": {"coordinates":[11.74714,45.403816],"type":"Point"}
}