{
  "type": "Feature",
  "properties": {
    "addr:full":"06024 Gubbio Gubbio Perugia 06024",
    "addr:postcode":"06024;06024",
    "iso:country":"IT",
    "sg:address":"06024 Gubbio",
    "sg:city":"Gubbio",
    "sg:classifiers":[
        {
            "category":"Travel",
            "subcategory":"Hotels & Motels",
            "type":"Entertainment"
        }
    ],
    "sg:phone":"+39 075 922 7004",
    "sg:postcode":"06024",
    "sg:province":"Perugia",
    "sg:tags":[
        "hotels",
        "facility"
    ],
    "wof:name":"Azienda Agrituristica Oasi Verde Mengara Di Rossi E Corsini",
    "wof:placetype":"venue"
},
  "geometry": {"coordinates":[12.575703,43.363045],"type":"Point"}
}