{
  "type": "Feature",
  "properties": {
    "iso:country":"IT",
    "sg:address":"40033 Casalecchio Di Reno",
    "sg:city":"Casalecchio di Reno",
    "sg:orig_category":"Automobili E Mezzi Di Trasporto. Riparazione Dei Mezzi Di Trasporto",
    "sg:phone":"+39 051 619 2111",
    "sg:postcode":"40033",
    "sg:province":"Bologna",
    "wof:name":"Carrozzeria Dello Scalo Snc",
    "wof:placetype":"venue"
},
  "geometry": {"coordinates":[11.286526,44.484917],"type":"Point"}
}