{
  "type": "Feature",
  "properties": {
    "addr:full":"42048 Rubiera Reggio Nell'Emilia 42048",
    "addr:postcode":"42048;42048",
    "iso:country":"IT",
    "sg:address":"42048 Rubiera",
    "sg:orig_category":"Pompe. Ricambi E Componenti Dei Mezzi Di Trasporto",
    "sg:phone":"+39 0522 628482",
    "sg:postcode":"42048",
    "sg:province":"Reggio Nell'Emilia",
    "wof:name":"Nuova Pompe Iniettori",
    "wof:placetype":"venue"
},
  "geometry": {"coordinates":[10.7738008499,44.6550827026],"type":"Point"}
}