{
  "type": "Feature",
  "properties": {
    "iso:country":"IT",
    "sg:address":"Via Dei Mille, 11/17 26015 Soresina",
    "sg:city":"Soresina",
    "sg:classifiers":[
        {
            "category":"Food & Beverages",
            "subcategory":"Dairy",
            "type":"Retail Goods"
        }
    ],
    "sg:phone":"+39 0374 349111",
    "sg:postcode":"26015",
    "sg:province":"Cremona",
    "sg:tags":[
        "product",
        "milk"
    ],
    "sg:website":"www.latteriasoresina.it",
    "wof:name":"Soc. Coop. Arl Latteria Soresina",
    "wof:placetype":"venue"
},
  "geometry": {"coordinates":[9.863743782,45.2855949402],"type":"Point"}
}