{
  "type": "Feature",
  "properties": {
    "iso:country":"IT",
    "sg:address":"2, Via Dei Cappuccini 62018 Potenza Picena",
    "sg:city":"Potenza Picena",
    "sg:classifiers":[
        {
            "category":"Real Estate",
            "subcategory":"Architect",
            "type":"Services"
        }
    ],
    "sg:phone":"+39 0733 672350",
    "sg:postcode":"62018",
    "sg:province":"Macerata",
    "sg:tags":[
        "textile",
        "clothing"
    ],
    "wof:name":"Bassi Giuseppe",
    "wof:placetype":"venue"
},
  "geometry": {"coordinates":[13.626274,43.369274],"type":"Point"}
}