{
  "type": "Feature",
  "properties": {
    "iso:country":"IT",
    "sg:address":"Via Artigianato 18 20090 Vimodrone",
    "sg:city":"Vimodrone",
    "sg:orig_category":"Boys' Clothing",
    "sg:phone":"+39 02 2740 1453",
    "sg:postcode":"20090",
    "sg:province":"Milano",
    "sg:website":"www.gmitaliane.com",
    "wof:name":"Gruppo Manifatture Italiane Srl",
    "wof:placetype":"venue"
},
  "geometry": {"coordinates":[9.301891,45.515907],"type":"Point"}
}