{
  "type": "Feature",
  "properties": {
    "iso:country":"IT",
    "sg:address":"00136 Roma",
    "sg:city":"Roma",
    "sg:orig_category":"Automazione E Macchine Per Ufficio",
    "sg:phone":"+39 06 3972 7811",
    "sg:postcode":"00136",
    "sg:province":"Roma",
    "sg:website":"http://www.aicsrl.it",
    "wof:name":"A.i.c. Imp. Exp. Srl",
    "wof:placetype":"venue"
},
  "geometry": {"coordinates":[12.446501,41.906895],"type":"Point"}
}