{
  "type": "Feature",
  "properties": {
    "iso:country":"IT",
    "sg:address":"26831 Casalmaiocco",
    "sg:city":"Casalmaiocco",
    "sg:orig_category":"Servizi Al Turismo. Trasporto Pubblico E Privato",
    "sg:phone":"+39 02 9826 4079",
    "sg:postcode":"26831",
    "sg:province":"Lodi",
    "wof:name":"Avio Services Srl",
    "wof:placetype":"venue"
},
  "geometry": {"coordinates":[9.375393,45.355057],"type":"Point"}
}