{
  "type": "Feature",
  "properties": {
    "iso:country":"IT",
    "sg:address":"00040 Pomezia",
    "sg:city":"Pomezia",
    "sg:orig_category":"Trasporto Pubblico E Privato",
    "sg:phone":"+39 06 910 5216",
    "sg:postcode":"00040",
    "sg:province":"Roma",
    "wof:name":"Co.a.p. (cooperativa Autonoleggio Pomezia) Piccola A R.l.",
    "wof:placetype":"venue"
},
  "geometry": {"coordinates":[12.522448,41.660942],"type":"Point"}
}