{
  "type": "Feature",
  "properties": {
    "iso:country":"IT",
    "sg:address":"31033 Castelfranco Veneto",
    "sg:city":"Castelfranco Veneto",
    "sg:orig_category":"Cartotecnica E Servizi. Forniture Per Uffici",
    "sg:phone":"+39 0423 723033",
    "sg:postcode":"31033",
    "sg:province":"Treviso",
    "sg:website":"http://www.cartocontabile.it",
    "wof:name":"Cartocontabile Snc Dei Fratelli Liberali & C.",
    "wof:placetype":"venue"
},
  "geometry": {"coordinates":[11.933923,45.682755],"type":"Point"}
}