{
  "type": "Feature",
  "properties": {
    "addr:full":"09030 Sardara Cagliari 09030",
    "addr:postcode":"09030;09030",
    "iso:country":"IT",
    "sg:address":"09030 Sardara",
    "sg:orig_category":"Alberghi E Strutture Extra Alberghiere. Ospedali E Servizi Sanitari",
    "sg:phone":"+39 070 938 7025",
    "sg:postcode":"09030",
    "sg:province":"Cagliari",
    "wof:name":"Idroterme Sardara S.r.l.",
    "wof:placetype":"venue"
},
  "geometry": {"coordinates":[8.820771,39.613796],"type":"Point"}
}