{
  "type": "Feature",
  "properties": {
    "iso:country":"IT",
    "sg:address":"20149 Milano",
    "sg:city":"Milano",
    "sg:orig_category":"Banche E Servizi Finanziari",
    "sg:phone":"+39 02 4851 9641",
    "sg:postcode":"20149",
    "sg:province":"Milano",
    "wof:name":"Farmafactoring Spa",
    "wof:placetype":"venue"
},
  "geometry": {"coordinates":[9.150227,45.473595],"type":"Point"}
}