{
  "type": "Feature",
  "properties": {
    "iso:country":"IT",
    "sg:address":"66, Via Piave 04100 Latina",
    "sg:city":"Latina",
    "sg:classifiers":[
        {
            "category":"Shopping",
            "subcategory":"Stationery & Office Supplies",
            "type":"Retail Goods"
        }
    ],
    "sg:phone":"+39 0773 693703",
    "sg:postcode":"04100",
    "sg:province":"Latina",
    "sg:tags":[
        "professional"
    ],
    "wof:name":"Kam S.r.l.",
    "wof:placetype":"venue"
},
  "geometry": {"coordinates":[12.8697223663,41.4797821045],"type":"Point"}
}