{
  "type": "Feature",
  "properties": {
    "iso:country":"IT",
    "sg:address":"5, Via Del Carmine 15033 Casale Monferrato",
    "sg:city":"Casale Monferrato",
    "sg:classifiers":[
        {
            "category":"Manufacturing",
            "subcategory":"Printing",
            "type":"Manufacturing & Wholesale Goods"
        }
    ],
    "sg:phone":"+39 390 142 3361",
    "sg:postcode":"15033",
    "sg:province":"Alessandria",
    "sg:tags":[
        "publishing"
    ],
    "wof:name":"Piemme Edizioni S.p.a.",
    "wof:placetype":"venue"
},
  "geometry": {"coordinates":[8.4483642578,45.132194519],"type":"Point"}
}