{
  "type": "Feature",
  "properties": {
    "addr:full":"39, V. Della Bozzana Est 55049 Viareggio Viareggio Lucca 55049",
    "addr:housenumber":"39",
    "addr:postcode":"55049;55049",
    "addr:street":"V. Della Bozzana Est",
    "iso:country":"IT",
    "sg:address":"39, V. Della Bozzana Est 55049 Viareggio",
    "sg:city":"Viareggio",
    "sg:classifiers":[
        {
            "category":"Shopping",
            "type":"Retail Goods"
        }
    ],
    "sg:phone":"+39 0584 391104",
    "sg:postcode":"55049",
    "sg:province":"Lucca",
    "sg:tags":[
        "finished",
        "-",
        "metallic"
    ],
    "wof:name":"Sca-met",
    "wof:placetype":"venue"
},
  "geometry": {"coordinates":[10.281003952,43.8482933044],"type":"Point"}
}