{
  "type": "Feature",
  "properties": {
    "addr:full":"20141 Milano Milano Milano 20141",
    "addr:postcode":"20141;20141",
    "iso:country":"IT",
    "sg:address":"20141 Milano",
    "sg:city":"Milano",
    "sg:orig_category":"Pelletterie - Produzione E Ingrosso",
    "sg:phone":"+39 02 5730 9910",
    "sg:postcode":"20141",
    "sg:province":"Milano",
    "sg:website":"http://www.maximabags.com",
    "wof:name":"Maxima Srl",
    "wof:placetype":"venue"
},
  "geometry": {"coordinates":[9.1997509003,45.4239616394],"type":"Point"}
}