{
  "type": "Feature",
  "properties": {
    "addr:full":"90, Via Colombo Cristoforo 21054 Fagnano Olona Fagnano Olona Varese 21054",
    "addr:postcode":"21054;21054",
    "addr:street":"Via Colombo Cristoforo",
    "iso:country":"IT",
    "sg:address":"90, Via Colombo Cristoforo 21054 Fagnano Olona",
    "sg:city":"Fagnano Olona",
    "sg:orig_category":"Miscellaneous Products",
    "sg:phone":"+39 0331 612388",
    "sg:postcode":"21054",
    "sg:province":"Varese",
    "wof:name":"Italtessile Di Musti Ferdinando & C. - S.a.s.",
    "wof:placetype":"venue"
},
  "geometry": {"coordinates":[8.8263845444,45.8176040649],"type":"Point"}
}