{
  "type": "Feature",
  "properties": {
    "addr:full":"20081 Abbiategrasso Abbiategrasso Milano 20081",
    "addr:postcode":"20081;20081",
    "iso:country":"IT",
    "sg:address":"20081 Abbiategrasso",
    "sg:city":"Abbiategrasso",
    "sg:orig_category":"Servizi E Lavori Industria Della Gomma",
    "sg:phone":"+39 02 9496 7648",
    "sg:postcode":"20081",
    "sg:province":"Milano",
    "wof:name":"Feltrin Glauco",
    "wof:placetype":"venue"
},
  "geometry": {"coordinates":[9.171325,45.437176],"type":"Point"}
}