{
  "type": "Feature",
  "properties": {
    "iso:country":"IT",
    "sg:address":"Via Mai Ceu 1; Ventimiglia Di Sicilia; 90020",
    "sg:city":"Ventimiglia di Sicilia",
    "sg:classifiers":[
        {
            "category":"Banks & Credit Unions",
            "subcategory":"Bank",
            "type":"Services"
        }
    ],
    "sg:phone":"+39 091 820 9569",
    "sg:postcode":"90020",
    "sg:province":"Palermo",
    "wof:name":"Credito Emiliano Spa",
    "wof:placetype":"venue"
},
  "geometry": {"coordinates":[13.569283,37.922771],"type":"Point"}
}