{
  "type": "Feature",
  "properties": {
    "iso:country":"IT",
    "sg:address":"90142 Palermo",
    "sg:city":"Palermo",
    "sg:orig_category":"Scuole E Servizi Scolastici. Ricerca, Selezione E Formazione Del Personale",
    "sg:phone":"+39 091 362058",
    "sg:postcode":"90142",
    "sg:province":"Palermo",
    "sg:website":"http://www.mondolingua.it",
    "wof:name":"Mondolingua",
    "wof:placetype":"venue"
},
  "geometry": {"coordinates":[13.364505,38.153286],"type":"Point"}
}