{
  "type": "Feature",
  "properties": {
    "iso:country":"IT",
    "sg:address":"21054 Fagnano Olona",
    "sg:city":"Fagnano Olona",
    "sg:orig_category":"Autodemolizioni",
    "sg:phone":"+39 0331 685525",
    "sg:postcode":"21054",
    "sg:province":"Varese",
    "wof:name":"Socoma Srl",
    "wof:placetype":"venue"
},
  "geometry": {"coordinates":[8.870319,45.668877],"type":"Point"}
}