{
  "type": "Feature",
  "properties": {
    "iso:country":"IT",
    "sg:address":"62, V. F. De Sanctis 59100 Prato",
    "sg:city":"Prato",
    "sg:classifiers":[
        {
            "category":"Wholesale",
            "subcategory":"Drugs",
            "type":"Manufacturing & Wholesale Goods"
        }
    ],
    "sg:phone":"+39 39057458901",
    "sg:postcode":"59100",
    "sg:province":"Prato",
    "sg:tags":[
        "chemical",
        "pharmaceutical"
    ],
    "sg:website":"http://www.toscochimica.com",
    "wof:name":"Toscochimica Spa",
    "wof:placetype":"venue"
},
  "geometry": {"coordinates":[11.092058,43.859486],"type":"Point"}
}