{
  "type": "Feature",
  "properties": {
    "iso:country":"IT",
    "sg:address":"24040 Suisio",
    "sg:city":"Suisio",
    "sg:orig_category":"Servizi E Lavori Per Edilizia E Lavori Pubblici",
    "sg:phone":"+39 035 902195",
    "sg:postcode":"24040",
    "sg:province":"Bergamo",
    "wof:name":"Marco Longhi",
    "wof:placetype":"venue"
},
  "geometry": {"coordinates":[9.501219,45.658527],"type":"Point"}
}