{
  "type": "Feature",
  "properties": {
    "addr:full":"20144 Milano Milano Milano 20144",
    "addr:postcode":"20144;20144",
    "iso:country":"IT",
    "sg:address":"20144 Milano",
    "sg:city":"Milano",
    "sg:orig_category":"Filati E Materie Prime Tessili",
    "sg:phone":"+39 02 469 0338",
    "sg:postcode":"20144",
    "sg:province":"Milano",
    "wof:name":"Centro Della Lana (s.n.c.)",
    "wof:placetype":"venue"
},
  "geometry": {"coordinates":[9.1644334793,45.4587936401],"type":"Point"}
}