{
  "type": "Feature",
  "properties": {
    "iso:country":"IT",
    "sg:address":"131, Via Torino 30172 Venezia",
    "sg:city":"Venezia",
    "sg:classifiers":[
        {
            "category":"Autos & Motor Vehicles",
            "subcategory":"Automobile Sales",
            "type":"Retail Goods"
        }
    ],
    "sg:phone":"+39 041 531 0222",
    "sg:postcode":"30172",
    "sg:province":"Venezia",
    "sg:tags":[
        "industrial"
    ],
    "wof:name":"Linea Autocar Laguna",
    "wof:placetype":"venue"
},
  "geometry": {"coordinates":[12.780014,45.824844],"type":"Point"}
}