{
  "type": "Feature",
  "properties": {
    "iso:country":"IT",
    "sg:address":"35010 Cadoneghe",
    "sg:city":"Cadoneghe",
    "sg:orig_category":"Trattamenti Termici E Superficiali Metalli, Galvanotecnica",
    "sg:phone":"+39 049 887 3711",
    "sg:postcode":"35010",
    "sg:province":"Padova",
    "wof:name":"Bagarolo Argenti Snc",
    "wof:placetype":"venue"
},
  "geometry": {"coordinates":[11.903712,45.471596],"type":"Point"}
}