{
  "type": "Feature",
  "properties": {
    "iso:country":"IT",
    "sg:address":"16, Via Comignago 28040 Oleggio Castello",
    "sg:city":"Oleggio Castello",
    "sg:classifiers":[
        {
            "category":"Manufacturing",
            "subcategory":"Lumber",
            "type":"Manufacturing & Wholesale Goods"
        }
    ],
    "sg:phone":"+39 0322 538021",
    "sg:postcode":"28040",
    "sg:province":"Novara",
    "sg:tags":[
        "wood"
    ],
    "wof:name":"Delfino Vincenzo (s.p.a.)",
    "wof:placetype":"venue"
},
  "geometry": {"coordinates":[8.533191,45.736156],"type":"Point"}
}