{
  "type": "Feature",
  "properties": {
    "iso:country":"IT",
    "sg:address":"63018 Porto S. Elpidio",
    "sg:orig_category":"Calzature - Produzione E Ingrosso",
    "sg:phone":"+39 0734 994452",
    "sg:postcode":"63018",
    "sg:province":"Ascoli Piceno",
    "wof:name":"A.ni.la. Srl",
    "wof:placetype":"venue"
},
  "geometry": {"coordinates":[13.574977,42.8554],"type":"Point"}
}