{
  "type": "Feature",
  "properties": {
    "addr:full":"47838 Riccione Riccione Rimini 47838",
    "addr:postcode":"47838;47838",
    "iso:country":"IT",
    "sg:address":"47838 Riccione",
    "sg:city":"Riccione",
    "sg:orig_category":"Servizi E Lavori Per Abbigliamento E Pelletterie",
    "sg:phone":"+39 0541 660176",
    "sg:postcode":"47838",
    "sg:province":"Rimini",
    "wof:name":"Sistemi Evolutivi Di Lorenzo Motta",
    "wof:placetype":"venue"
},
  "geometry": {"coordinates":[12.635495,44.009312],"type":"Point"}
}