{
  "type": "Feature",
  "properties": {
    "addr:full":"30175 Marghera Marghera Venezia 30175",
    "addr:postcode":"30175;30175",
    "iso:country":"IT",
    "sg:address":"30175 Marghera",
    "sg:city":"Marghera",
    "sg:orig_category":"Macchine E Forniture Per Ecologia E Smaltimento Rifiuti",
    "sg:phone":"+39 041 698206",
    "sg:postcode":"30175",
    "sg:province":"Venezia",
    "wof:name":"Herhof-ladurner Impianto Venezia S.c. A R.l.",
    "wof:placetype":"venue"
},
  "geometry": {"coordinates":[12.260911,45.470318],"type":"Point"}
}