{
  "type": "Feature",
  "properties": {
    "iso:country":"IT",
    "sg:address":"00186 Roma",
    "sg:city":"Roma",
    "sg:orig_category":"Hobbistica",
    "sg:phone":"+39 06 683 3283",
    "sg:postcode":"00186",
    "sg:province":"Roma",
    "wof:name":"Squillace Tommaso",
    "wof:placetype":"venue"
},
  "geometry": {"coordinates":[12.473819,41.897888],"type":"Point"}
}