{
  "type": "Feature",
  "properties": {
    "addr:full":"6, Via Dell' Artigianato 37014 Castelnuovo Del Garda Castelnuovo del Garda Verona 37014",
    "addr:postcode":"37014;37014",
    "addr:street":"Via Dell ' Artigianato",
    "iso:country":"IT",
    "sg:address":"6, Via Dell' Artigianato 37014 Castelnuovo Del Garda",
    "sg:city":"Castelnuovo del Garda",
    "sg:classifiers":[
        {
            "category":"Manufacturing",
            "subcategory":"Metals",
            "type":"Manufacturing & Wholesale Goods"
        }
    ],
    "sg:phone":"+39 045 757 0305",
    "sg:postcode":"37014",
    "sg:province":"Verona",
    "sg:tags":[
        "processing"
    ],
    "wof:name":"Generalmeccanica",
    "wof:placetype":"venue"
},
  "geometry": {"coordinates":[10.7642412186,45.4282112122],"type":"Point"}
}