{
  "type": "Feature",
  "properties": {
    "iso:country":"IT",
    "sg:address":"9, Viale Diaz 10023 Chieri",
    "sg:city":"Chieri",
    "sg:classifiers":[
        {
            "category":"Shopping",
            "subcategory":"Crafts & Fabrics",
            "type":"Retail Goods"
        }
    ],
    "sg:phone":"+39 011 942 5666",
    "sg:postcode":"10023",
    "sg:province":"Torino",
    "wof:name":"Saroglia & Taverna (s.p.a.)",
    "wof:placetype":"venue"
},
  "geometry": {"coordinates":[7.9020733833,45.0435066223],"type":"Point"}
}