{
  "type": "Feature",
  "properties": {
    "addr:full":"Zona Industriale 04023 Formia Formia Latina 04023",
    "addr:postcode":"04023;04023",
    "addr:street":"Zona Industriale",
    "iso:country":"IT",
    "sg:address":"Zona Industriale 04023 Formia",
    "sg:city":"Formia",
    "sg:classifiers":[
        {
            "category":"Banks & Credit Unions",
            "subcategory":"Investment Brokerage",
            "type":"Services"
        }
    ],
    "sg:phone":"+39 0771 736871",
    "sg:postcode":"04023",
    "sg:province":"Latina",
    "sg:tags":[
        "cosmetic",
        "preparations",
        "bath"
    ],
    "wof:name":"Rca S.r.l.",
    "wof:placetype":"venue"
},
  "geometry": {"coordinates":[12.9037,41.467598],"type":"Point"}
}