{
  "type": "Feature",
  "properties": {
    "iso:country":"IT",
    "sg:address":"Via Brodolini 4 60035 Jesi",
    "sg:city":"Jesi",
    "sg:classifiers":[
        {
            "category":"Transit Center",
            "subcategory":"Freight",
            "type":"Transportation"
        }
    ],
    "sg:phone":"+39 0731 200350",
    "sg:postcode":"60035",
    "sg:province":"Ancona",
    "sg:tags":[
        "high",
        "lift",
        "truck"
    ],
    "sg:website":"www.pieralisi.it",
    "wof:name":"Pieralisi Spa",
    "wof:placetype":"venue"
},
  "geometry": {"coordinates":[13.266126,43.538422],"type":"Point"}
}