{
  "type": "Feature",
  "properties": {
    "iso:country":"IT",
    "sg:address":"Via Virginio 524 50025 Montespertoli",
    "sg:city":"Montespertoli",
    "sg:classifiers":[
        {
            "category":"Bars & Pubs",
            "subcategory":"Nightclub",
            "type":"Food & Drink"
        }
    ],
    "sg:phone":"+39 0571 671918",
    "sg:postcode":"50025",
    "sg:province":"Firenze",
    "sg:tags":[
        "lamp",
        "ceramic"
    ],
    "sg:website":"www.penteres.it/leona",
    "wof:name":"Ceramiche Leona Snc Di Leoncini Danilo E Tiberio",
    "wof:placetype":"venue"
},
  "geometry": {"coordinates":[11.071945,43.685314],"type":"Point"}
}