{
  "type": "Feature",
  "properties": {
    "addr:full":"35013 Cittadella Cittadella Padova 35013",
    "addr:postcode":"35013;35013",
    "iso:country":"IT",
    "sg:address":"35013 Cittadella",
    "sg:city":"Cittadella",
    "sg:orig_category":"Analisi Chimiche, Industriali E Merceologiche",
    "sg:phone":"+39 049 597 0547",
    "sg:postcode":"35013",
    "sg:province":"Padova",
    "wof:name":"Zuolo Italo Almat",
    "wof:placetype":"venue"
},
  "geometry": {"coordinates":[11.786617,45.666035],"type":"Point"}
}