{
  "type": "Feature",
  "properties": {
    "iso:country":"IT",
    "sg:address":"21052 Busto Arsizio",
    "sg:city":"Busto Arsizio",
    "sg:orig_category":"Estetiste",
    "sg:phone":"+39 0331 632710",
    "sg:postcode":"21052",
    "sg:province":"Varese",
    "wof:name":"Peacock Beauty Center Di Capraro Veronique",
    "wof:placetype":"venue"
},
  "geometry": {"coordinates":[8.845797,45.608871],"type":"Point"}
}