{
  "type": "Feature",
  "properties": {
    "addr:full":"7, Via Volta Alessandro 42013 Casalgrande Reggio Nell'Emilia 42013",
    "addr:postcode":"42013;42013",
    "addr:street":"Via Volta Alessandro",
    "iso:country":"IT",
    "sg:address":"7, Via Volta Alessandro 42013 Casalgrande",
    "sg:classifiers":[
        {
            "category":"Manufacturing",
            "subcategory":"Glass & Minerals",
            "type":"Manufacturing & Wholesale Goods"
        }
    ],
    "sg:phone":"+39 0522 849600",
    "sg:postcode":"42013",
    "sg:province":"Reggio Nell'Emilia",
    "sg:tags":[
        "building",
        "material"
    ],
    "wof:name":"Ellegi Ceramiche (s.r.l.)",
    "wof:placetype":"venue"
},
  "geometry": {"coordinates":[10.777562,44.653923],"type":"Point"}
}