{
  "type": "Feature",
  "properties": {
    "addr:full":"10036 Settimo Torinese Settimo Torinese Torino 10036",
    "addr:postcode":"10036;10036",
    "iso:country":"IT",
    "sg:address":"10036 Settimo Torinese",
    "sg:city":"Settimo Torinese",
    "sg:orig_category":"Modelli E Plastici",
    "sg:phone":"+39 011 897 5943",
    "sg:postcode":"10036",
    "sg:province":"Torino",
    "wof:name":"Stilmodel",
    "wof:placetype":"venue"
},
  "geometry": {"coordinates":[7.7301602364,45.148273468],"type":"Point"}
}