{
  "type": "Feature",
  "properties": {
    "iso:country":"IT",
    "sg:address":"73014 Gallipoli",
    "sg:city":"Gallipoli",
    "sg:orig_category":"Pizzerie",
    "sg:phone":"+39 0833 266538",
    "sg:postcode":"73014",
    "sg:province":"Lecce",
    "wof:name":"Fiore Albino - Taverna Del Ciclope",
    "wof:placetype":"venue"
},
  "geometry": {"coordinates":[18.0302276611,40.0198631287],"type":"Point"}
}