{
  "type": "Feature",
  "properties": {
    "addr:full":"6, Via Vecellio 20039 Varedo Varedo Milano 20039",
    "addr:postcode":"20039;20039",
    "addr:street":"Via Vecellio",
    "iso:country":"IT",
    "sg:address":"6, Via Vecellio 20039 Varedo",
    "sg:city":"Varedo",
    "sg:classifiers":[
        {
            "category":"Professional",
            "subcategory":"Engineering",
            "type":"Services"
        }
    ],
    "sg:phone":"+39 036 258 0026",
    "sg:postcode":"20039",
    "sg:province":"Milano",
    "sg:tags":[
        "machine",
        "-",
        "mechanical"
    ],
    "wof:name":"Immco Srl",
    "wof:placetype":"venue"
},
  "geometry": {"coordinates":[9.14595,45.559875],"type":"Point"}
}