{
  "type": "Feature",
  "properties": {
    "iso:country":"IT",
    "sg:address":"2, Via Colombo Cristoforo 20068 Peschiera Borromeo",
    "sg:city":"Peschiera Borromeo",
    "sg:classifiers":[
        {
            "category":"Shopping",
            "subcategory":"Stationery & Office Supplies",
            "type":"Retail Goods"
        }
    ],
    "sg:phone":"+39 02 5165 0290",
    "sg:postcode":"20068",
    "sg:province":"Milano",
    "sg:tags":[
        "professional"
    ],
    "wof:name":"Lail Lavorazione Industriale Legno (s.r.l.)",
    "wof:placetype":"venue"
},
  "geometry": {"coordinates":[9.2825469971,45.4404411316],"type":"Point"}
}