{
  "type": "Feature",
  "properties": {
    "iso:country":"IT",
    "sg:address":"25011 Calcinato",
    "sg:city":"Calcinato",
    "sg:orig_category":"Petroli, Gas E Combustibili",
    "sg:phone":"+39 030 358 1511",
    "sg:postcode":"25011",
    "sg:province":"Brescia",
    "wof:name":"Unichem Srl",
    "wof:placetype":"venue"
},
  "geometry": {"coordinates":[10.3956031799,45.4584960938],"type":"Point"}
}