{
  "type": "Feature",
  "properties": {
    "iso:country":"IT",
    "sg:address":"84091 Battipaglia",
    "sg:city":"Battipaglia",
    "sg:orig_category":"Agricoltura - Attrezzi, Prodotti E Forniture",
    "sg:phone":"+39 0828 673706",
    "sg:postcode":"84091",
    "sg:province":"Salerno",
    "wof:name":"Farmagricolina Salernitana Snc Dei F.lli Calvanese",
    "wof:placetype":"venue"
},
  "geometry": {"coordinates":[14.950567,40.593929],"type":"Point"}
}