{
  "type": "Feature",
  "properties": {
    "iso:country":"IT",
    "sg:address":"25047 Darfo Boario Terme",
    "sg:city":"Darfo",
    "sg:orig_category":"Apparecchiature Ed Attrezzature Meccaniche. Elettrotecnica Industriale, Prodotti E Apparecchiature",
    "sg:phone":"+39 036 453 1629",
    "sg:postcode":"25047",
    "sg:province":"Brescia",
    "wof:name":"Rebaioli (s.p.a.)",
    "wof:placetype":"venue"
},
  "geometry": {"coordinates":[10.165507,45.854935],"type":"Point"}
}