{
  "type": "Feature",
  "properties": {
    "addr:full":"37, Via Muselle 37050 Isola Rizza Isola Rizza Verona 37050",
    "addr:postcode":"37050;37050",
    "addr:street":"Via Muselle",
    "iso:country":"IT",
    "sg:address":"37, Via Muselle 37050 Isola Rizza",
    "sg:city":"Isola Rizza",
    "sg:classifiers":[
        {
            "category":"Home & Garden",
            "subcategory":"Home Furnishings",
            "type":"Retail Goods"
        }
    ],
    "sg:phone":"+39 045 697 1147",
    "sg:postcode":"37050",
    "sg:province":"Verona",
    "sg:tags":[
        "household"
    ],
    "wof:name":"Mobil Sedia 2000 S.r.l.",
    "wof:placetype":"venue"
},
  "geometry": {"coordinates":[11.182497,45.284332],"type":"Point"}
}