{
  "type": "Feature",
  "properties": {
    "addr:full":"43, Via Azzone Visconti 20052 Monza Monza Milano 20052",
    "addr:postcode":"20052;20052",
    "addr:street":"Via Azzone Visconti",
    "iso:country":"IT",
    "sg:address":"43, Via Azzone Visconti 20052 Monza",
    "sg:city":"Monza",
    "sg:classifiers":[
        {
            "category":"Food & Beverages",
            "subcategory":"Groceries & Convenience Stores",
            "type":"Retail Goods"
        }
    ],
    "sg:phone":"+39 039 230 1980",
    "sg:postcode":"20052",
    "sg:province":"Milano",
    "sg:tags":[
        "drink"
    ],
    "wof:name":"Meregalli Giuseppe (s.r.l.)",
    "wof:placetype":"venue"
},
  "geometry": {"coordinates":[9.281284,45.583473],"type":"Point"}
}