{
  "type": "Feature",
  "properties": {
    "iso:country":"IT",
    "sg:address":"13811 Tavigliano",
    "sg:city":"Tavigliano",
    "sg:orig_category":"Manufacturers: Prefabbricati",
    "sg:phone":"+39 015 471535",
    "sg:postcode":"13811",
    "sg:province":"Biella",
    "wof:name":"Nelva Mauro",
    "wof:placetype":"venue"
},
  "geometry": {"coordinates":[8.057803,45.626617],"type":"Point"}
}