{
  "type": "Feature",
  "properties": {
    "iso:country":"IT",
    "sg:address":"20061 Carugate",
    "sg:city":"Carugate",
    "sg:classifiers":[
        {
            "category":"Home & Garden",
            "subcategory":"Furniture",
            "type":"Retail Goods"
        }
    ],
    "sg:phone":"+39 02 925 3978",
    "sg:postcode":"20061",
    "sg:province":"Milano",
    "sg:tags":[
        "furnishing"
    ],
    "wof:name":"Riboldi Fratelli Snc",
    "wof:placetype":"venue"
},
  "geometry": {"coordinates":[9.3360319138,45.5553779602],"type":"Point"}
}