{
  "type": "Feature",
  "properties": {
    "iso:country":"IT",
    "sg:address":"67051 Avezzano",
    "sg:orig_category":"Alberghi",
    "sg:phone":"+39 0863 4601",
    "sg:postcode":"67051",
    "sg:province":"L'Aquila",
    "sg:website":"http://www.serenamajesticgroup.it",
    "wof:name":"Hotel Dei Marsi",
    "wof:placetype":"venue"
},
  "geometry": {"coordinates":[13.39785,42.350151],"type":"Point"}
}