{
  "type": "Feature",
  "properties": {
    "iso:country":"IT",
    "sg:address":"00159 Roma",
    "sg:city":"Roma",
    "sg:orig_category":"Macchine Ed Impianti Per Edilizia E Lavori Pubblici",
    "sg:phone":"+39 06 4080 0616",
    "sg:postcode":"00159",
    "sg:province":"Roma",
    "wof:name":"Decama Snc",
    "wof:placetype":"venue"
},
  "geometry": {"coordinates":[12.564425,41.918232],"type":"Point"}
}