{
  "type": "Feature",
  "properties": {
    "addr:full":"40, Via Del Seprio 22074 Lomazzo Lomazzo Como 22074",
    "addr:postcode":"22074;22074",
    "addr:street":"Via Del Seprio",
    "iso:country":"IT",
    "sg:address":"40, Via Del Seprio 22074 Lomazzo",
    "sg:city":"Lomazzo",
    "sg:classifiers":[
        {
            "category":"Shopping",
            "subcategory":"Crafts & Fabrics",
            "type":"Retail Goods"
        }
    ],
    "sg:phone":"+39 02 9677 9646",
    "sg:postcode":"22074",
    "sg:province":"Como",
    "sg:tags":[
        "ceramic"
    ],
    "wof:name":"Royale Srl",
    "wof:placetype":"venue"
},
  "geometry": {"coordinates":[9.024534,45.699379],"type":"Point"}
}