{
  "type": "Feature",
  "properties": {
    "addr:full":"4, Via Del Pozzaccio 60013 Corinaldo Corinaldo Ancona 60013",
    "addr:postcode":"60013;60013",
    "addr:street":"Via Del Pozzaccio",
    "iso:country":"IT",
    "sg:address":"4, Via Del Pozzaccio 60013 Corinaldo",
    "sg:city":"Corinaldo",
    "sg:classifiers":[
        {
            "category":"Shopping",
            "subcategory":"Clothing, Apparel, & Fashions",
            "type":"Retail Goods"
        }
    ],
    "sg:phone":"+39 071 797 6164",
    "sg:postcode":"60013",
    "sg:province":"Ancona",
    "sg:tags":[
        "clothes"
    ],
    "wof:name":"Falcinelli Gianfranco",
    "wof:placetype":"venue"
},
  "geometry": {"coordinates":[13.043262,43.65633],"type":"Point"}
}