{
  "type": "Feature",
  "properties": {
    "iso:country":"IT",
    "sg:address":"6, Via Silvio Pellico 22032 Albese Con Cassano",
    "sg:city":"Albese con Cassano",
    "sg:classifiers":[
        {
            "category":"Personal",
            "subcategory":"Shoe Repair & Shine",
            "type":"Services"
        }
    ],
    "sg:phone":"+39 031 429 1111",
    "sg:postcode":"22032",
    "sg:province":"Como",
    "sg:tags":[
        "leather"
    ],
    "wof:name":"Meddy Italia Srl",
    "wof:placetype":"venue"
},
  "geometry": {"coordinates":[9.085456,45.811966],"type":"Point"}
}