{
  "type": "Feature",
  "properties": {
    "iso:country":"IT",
    "sg:address":"Via Parisi 90011 Bagheria",
    "sg:city":"Bagheria",
    "sg:classifiers":[
        {
            "category":"Farming",
            "subcategory":"Livestock Farm",
            "type":"Manufacturing & Wholesale Goods"
        }
    ],
    "sg:phone":"+39 39091931755",
    "sg:postcode":"90011",
    "sg:province":"Palermo",
    "sg:tags":[
        "agriculture"
    ],
    "wof:name":"Capeo (s.r.l.)",
    "wof:placetype":"venue"
},
  "geometry": {"coordinates":[13.511326,38.090225],"type":"Point"}
}