{
  "type": "Feature",
  "properties": {
    "addr:full":"22100 Como Como Como 22100",
    "addr:postcode":"22100;22100",
    "iso:country":"IT",
    "sg:address":"22100 Como",
    "sg:city":"Como",
    "sg:orig_category":"Distributors: Automatici - Commercio E Gestione",
    "sg:phone":"+39 031 506221",
    "sg:postcode":"22100",
    "sg:province":"Como",
    "wof:name":"Elledi Sas",
    "wof:placetype":"venue"
},
  "geometry": {"coordinates":[9.068803,45.783859],"type":"Point"}
}