{
  "type": "Feature",
  "properties": {
    "iso:country":"IT",
    "sg:address":"1, Via Galileo Galilei 42020 San Polo D'enza",
    "sg:classifiers":[
        {
            "category":"Utilities",
            "subcategory":"Electric",
            "type":"Services"
        }
    ],
    "sg:phone":"+39 0522 874721",
    "sg:postcode":"42020",
    "sg:province":"Reggio Nell'Emilia",
    "sg:tags":[
        "component",
        "electronic"
    ],
    "wof:name":"El.ca. (s.r.l.)",
    "wof:placetype":"venue"
},
  "geometry": {"coordinates":[10.478217,44.66713],"type":"Point"}
}