{
  "type": "Feature",
  "properties": {
    "addr:full":"40122 Bologna Bologna Bologna 40122",
    "addr:postcode":"40122;40122",
    "iso:country":"IT",
    "sg:address":"40122 Bologna",
    "sg:city":"Bologna",
    "sg:orig_category":"Forniture Per Attivita' Industriali",
    "sg:phone":"+39 051 520502",
    "sg:postcode":"40122",
    "sg:province":"Bologna",
    "wof:name":"Pavimenti (s.a.s.)",
    "wof:placetype":"venue"
},
  "geometry": {"coordinates":[11.3320274353,44.5018234253],"type":"Point"}
}