{
  "type": "Feature",
  "properties": {
    "iso:country":"IT",
    "sg:address":"3/b, Via Camuzzoni Giulio 37138 Verona",
    "sg:city":"Verona",
    "sg:classifiers":[
        {
            "category":"Travel",
            "subcategory":"Travel Agent",
            "type":"Entertainment"
        }
    ],
    "sg:phone":"+39 39045569400",
    "sg:postcode":"37138",
    "sg:province":"Verona",
    "sg:tags":[
        "business"
    ],
    "wof:name":"Albergo Martini Hotel",
    "wof:placetype":"venue"
},
  "geometry": {"coordinates":[10.991748,45.438366],"type":"Point"}
}