{
  "type": "Feature",
  "properties": {
    "iso:country":"IT",
    "sg:address":"02010 Vazia",
    "sg:orig_category":"Carta, Cartone E Prodotti Primari. Forniture Per Uffici",
    "sg:phone":"+39 0746 229004",
    "sg:postcode":"02010",
    "sg:province":"Rieti",
    "wof:name":"Beta Rotoli Spa",
    "wof:placetype":"venue"
},
  "geometry": {"coordinates":[12.919065,42.430374],"type":"Point"}
}