{
  "type": "Feature",
  "properties": {
    "addr:full":"30122 Venezia Castello Venezia 30122",
    "addr:postcode":"30122;30122",
    "iso:country":"IT",
    "sg:address":"30122 Venezia",
    "sg:city":"Castello",
    "sg:orig_category":"Abbigliamento Esterno, Maglierie E Pelliccerie. Forniture Per Il Settore Dello Spettacolo",
    "sg:phone":"+39 041 528 7429",
    "sg:postcode":"30122",
    "sg:province":"Venezia",
    "wof:name":"Flavia Artigianato Scelto Per Voi Di Zorzo Flavia Flavia",
    "wof:placetype":"venue"
},
  "geometry": {"coordinates":[12.338284,45.437645],"type":"Point"}
}