{
  "type": "Feature",
  "properties": {
    "iso:country":"IT",
    "sg:address":"25135 Brescia",
    "sg:city":"Brescia",
    "sg:orig_category":"Riparazione Dei Mezzi Di Trasporto. Servizi Ausiliari Dei Mezzi Di Trasporto",
    "sg:phone":"+39 030 360450",
    "sg:postcode":"25135",
    "sg:province":"Brescia",
    "wof:name":"Top Ricambi Srl",
    "wof:placetype":"venue"
},
  "geometry": {"coordinates":[10.289363,45.518723],"type":"Point"}
}