{
  "type": "Feature",
  "properties": {
    "iso:country":"IT",
    "sg:address":"00193 Roma",
    "sg:city":"Roma",
    "sg:orig_category":"Scuole E Servizi Scolastici. Ospedali E Servizi Sanitari",
    "sg:phone":"+39 06 324 3839",
    "sg:postcode":"00193",
    "sg:province":"Roma",
    "wof:name":"C.r.e.a.",
    "wof:placetype":"venue"
},
  "geometry": {"coordinates":[12.46242,41.904129],"type":"Point"}
}