{
  "type": "Feature",
  "properties": {
    "iso:country":"IT",
    "sg:address":"473, Via Aurelia 00165 Roma",
    "sg:city":"Roma",
    "sg:classifiers":[
        {
            "category":"Food & Beverages",
            "subcategory":"Dairy",
            "type":"Retail Goods"
        }
    ],
    "sg:phone":"+39 39066626171",
    "sg:postcode":"00165",
    "sg:province":"Roma",
    "sg:tags":[
        "product"
    ],
    "wof:name":"Euroformaggi Srl",
    "wof:placetype":"venue"
},
  "geometry": {"coordinates":[12.42038,41.896687],"type":"Point"}
}