{
  "type": "Feature",
  "properties": {
    "iso:country":"IT",
    "sg:address":"00139 Roma",
    "sg:city":"Roma",
    "sg:orig_category":"Pubblicita', Marketing E Comunicazione",
    "sg:phone":"+39 06 8712 0450",
    "sg:postcode":"00139",
    "sg:province":"Roma",
    "wof:name":"Call Center Telefobia Sas",
    "wof:placetype":"venue"
},
  "geometry": {"coordinates":[12.447974205,41.7880630493],"type":"Point"}
}