{
  "type": "Feature",
  "properties": {
    "iso:country":"IT",
    "sg:address":"17, V. Casone Ugolino 57022 Castagneto Carducci",
    "sg:city":"Castagneto Carducci",
    "sg:classifiers":[
        {
            "category":"Manufacturing",
            "subcategory":"Lumber",
            "type":"Manufacturing & Wholesale Goods"
        }
    ],
    "sg:phone":"+39 0586 773192",
    "sg:postcode":"57022",
    "sg:province":"Livorno",
    "sg:tags":[
        "wood"
    ],
    "sg:website":"http://www.paginegialle.it/afcindbosc",
    "wof:name":"Industria Boschiva 'a.f.c.'",
    "wof:placetype":"venue"
},
  "geometry": {"coordinates":[10.581364,43.167938],"type":"Point"}
}