{
  "type": "Feature",
  "properties": {
    "addr:full":"16033 Lavagna Lavagna Genova 16033",
    "addr:postcode":"16033;16033",
    "iso:country":"IT",
    "sg:address":"16033 Lavagna",
    "sg:city":"Lavagna",
    "sg:orig_category":"Non-classified Establishments",
    "sg:phone":"+39 0185 303657",
    "sg:postcode":"16033",
    "sg:province":"Genova",
    "wof:name":"Arredo Mare Morello Carlo",
    "wof:placetype":"venue"
},
  "geometry": {"coordinates":[8.978994,44.39801],"type":"Point"}
}