{
  "type": "Feature",
  "properties": {
    "iso:country":"IT",
    "sg:address":"46046 Medole",
    "sg:city":"Medole",
    "sg:orig_category":"Servizi E Lavori Per Arredamento E Industria Del Legno",
    "sg:phone":"+39 0376 868048",
    "sg:postcode":"46046",
    "sg:province":"Mantova",
    "wof:name":"Eredi Di Piadena Gianni Di Piadena Mauro E C. Snc",
    "wof:placetype":"venue"
},
  "geometry": {"coordinates":[10.519159,45.31868],"type":"Point"}
}