{
  "type": "Feature",
  "properties": {
    "iso:country":"IT",
    "sg:address":"21047 Saronno",
    "sg:city":"Saronno",
    "sg:orig_category":"Macchine, Impianti Ed Attrezzature Industria Chimica",
    "sg:phone":"+39 02 9670 2726",
    "sg:postcode":"21047",
    "sg:province":"Varese",
    "sg:website":"http://www.bmcii.it",
    "wof:name":"B.m.c.i.i. Srl",
    "wof:placetype":"venue"
},
  "geometry": {"coordinates":[9.032098,45.627552],"type":"Point"}
}