{
  "type": "Feature",
  "properties": {
    "addr:full":"21038 Sangiano Sangiano Varese 21038",
    "addr:postcode":"21038;21038",
    "iso:country":"IT",
    "sg:address":"21038 Sangiano",
    "sg:city":"Sangiano",
    "sg:orig_category":"Forniture Per Edilizia E Lavori Pubblici. Forniture Industriali Per Prevenzione, Controllo E Sicurezza",
    "sg:phone":"+39 0332 648590",
    "sg:postcode":"21038",
    "sg:province":"Varese",
    "wof:name":"Cmaa Errebi Estintori Srl",
    "wof:placetype":"venue"
},
  "geometry": {"coordinates":[8.6326179504,45.8758583069],"type":"Point"}
}