{
  "type": "Feature",
  "properties": {
    "iso:country":"IT",
    "sg:address":"20012 Cuggiono",
    "sg:city":"Cuggiono",
    "sg:orig_category":"Forniture Per Uffici. Servizi Vari Di Interesse Pubblico",
    "sg:phone":"+39 02 974366",
    "sg:postcode":"20012",
    "sg:province":"Milano",
    "wof:name":"Due Gi Di Valsecchi A. & Figlio",
    "wof:placetype":"venue"
},
  "geometry": {"coordinates":[9.1953763962,45.4654159546],"type":"Point"}
}