{
  "type": "Feature",
  "properties": {
    "iso:country":"IT",
    "sg:address":"20142 Milano",
    "sg:city":"Milano",
    "sg:orig_category":"Minuterie Metalliche E Ferramenta",
    "sg:phone":"+39 02 8930 5017",
    "sg:postcode":"20142",
    "sg:province":"Milano",
    "wof:name":"Fratelli Maderna Snc",
    "wof:placetype":"venue"
},
  "geometry": {"coordinates":[9.1627626419,45.4141082764],"type":"Point"}
}