{
  "type": "Feature",
  "properties": {
    "addr:full":"77, Via Fantin 31035 Crocetta Del Montello Crocetta del Montello Treviso 31035",
    "addr:postcode":"31035;31035",
    "addr:street":"Via Fantin",
    "iso:country":"IT",
    "sg:address":"77, Via Fantin 31035 Crocetta Del Montello",
    "sg:city":"Crocetta del Montello",
    "sg:classifiers":[
        {
            "category":"Building & Trades",
            "subcategory":"Construction",
            "type":"Services"
        }
    ],
    "sg:phone":"+39 39042384027",
    "sg:postcode":"31035",
    "sg:province":"Treviso",
    "sg:tags":[
        "work",
        "public"
    ],
    "wof:name":"Impresa Stradale Montello Di Covolan & C. S.a.s.",
    "wof:placetype":"venue"
},
  "geometry": {"coordinates":[12.046854,45.820698],"type":"Point"}
}