{
  "type": "Feature",
  "properties": {
    "addr:full":"90030 Bolognetta Bolognetta Palermo 90030",
    "addr:postcode":"90030;90030",
    "iso:country":"IT",
    "sg:address":"90030 Bolognetta",
    "sg:city":"Bolognetta",
    "sg:orig_category":"Climatizzazione E Condizionamento, Apparecchiature E Servizi. Elettrodomestici",
    "sg:phone":"+39 091 873 7482",
    "sg:postcode":"90030",
    "sg:province":"Palermo",
    "wof:name":"P.v.r. Centro Commerciale Di Costa Paolo & C. Sas",
    "wof:placetype":"venue"
},
  "geometry": {"coordinates":[13.456853,37.966263],"type":"Point"}
}