{
  "type": "Feature",
  "properties": {
    "iso:country":"IT",
    "sg:address":"56125 Pisa",
    "sg:city":"Pisa",
    "sg:orig_category":"Zootecnia E Pesca, Allevamento Piccoli Animali. Animali Domestici",
    "sg:phone":"+39 050 501527",
    "sg:postcode":"56125",
    "sg:province":"Pisa",
    "sg:website":"http://utenti.tripod.it/aquarium",
    "wof:name":"Mantovani Alberto - Aquarium",
    "wof:placetype":"venue"
},
  "geometry": {"coordinates":[10.401732,43.71069],"type":"Point"}
}