{
  "type": "Feature",
  "properties": {
    "iso:country":"IT",
    "sg:address":"165, Via Quarantadue Martiri 28924 Verbania",
    "sg:city":"Verbania",
    "sg:classifiers":[
        {
            "category":"Professional",
            "subcategory":"Printing & Photocopies",
            "type":"Services"
        }
    ],
    "sg:phone":"+39 0323 496103",
    "sg:postcode":"28924",
    "sg:province":"Verbano-Cusio-Ossola",
    "wof:name":"Spadacini Arti Grafiche",
    "wof:placetype":"venue"
},
  "geometry": {"coordinates":[8.4712638855,45.9427337646],"type":"Point"}
}