{
  "type": "Feature",
  "properties": {
    "iso:country":"IT",
    "sg:address":"26824 Cavenago D'adda",
    "sg:orig_category":"Imprese Di Costruzioni Civili Ed Industriali",
    "sg:phone":"+39 0371 70122",
    "sg:postcode":"26824",
    "sg:province":"Lodi",
    "sg:website":"http://www.defabiani.com",
    "wof:name":"De Fabiani Giuseppe & C. Snc",
    "wof:placetype":"venue"
},
  "geometry": {"coordinates":[9.593732,45.280846],"type":"Point"}
}