{
  "type": "Feature",
  "properties": {
    "iso:country":"IT",
    "sg:address":"10137 Torino",
    "sg:city":"Torino",
    "sg:orig_category":"Lavorazioni Metalli, Stampaggio E Saldatura",
    "sg:phone":"+39 011 357601",
    "sg:postcode":"10137",
    "sg:province":"Torino",
    "wof:name":"Verlucca Davide",
    "wof:placetype":"venue"
},
  "geometry": {"coordinates":[7.628976,45.039993],"type":"Point"}
}