{
  "type": "Feature",
  "properties": {
    "addr:full":"98161 Messina Messina Messina 98161",
    "addr:postcode":"98161;98161",
    "iso:country":"IT",
    "sg:address":"98161 Messina",
    "sg:city":"Messina",
    "sg:orig_category":"Prodotti Vari In Metallo. Articoli Per Imballaggio E Confezionamento",
    "sg:phone":"+39 090 632254",
    "sg:postcode":"98161",
    "sg:province":"Messina",
    "wof:name":"A. Pilato & Company Snc",
    "wof:placetype":"venue"
},
  "geometry": {"coordinates":[15.5506401062,38.2047462463],"type":"Point"}
}