{
  "type": "Feature",
  "properties": {
    "iso:country":"IT",
    "sg:address":"Via Dante 10/a; Alassio; 17021",
    "sg:city":"Alassio",
    "sg:classifiers":[
        {
            "category":"Banks & Credit Unions",
            "subcategory":"Bank",
            "type":"Services"
        }
    ],
    "sg:phone":"+39 0182 644948",
    "sg:postcode":"17021",
    "sg:province":"Savona",
    "wof:name":"Banco Ambrosiano",
    "wof:placetype":"venue"
},
  "geometry": {"coordinates":[8.158756,43.98019],"type":"Point"}
}