{
  "type": "Feature",
  "properties": {
    "iso:country":"IT",
    "sg:address":"194, V. Della Stazione Di Ciampino 00040 Ciampino",
    "sg:classifiers":[
        {
            "category":"Parking",
            "subcategory":"Lot",
            "type":"Transportation"
        }
    ],
    "sg:phone":"+39 39067900260",
    "sg:postcode":"00040",
    "sg:province":"Roma",
    "sg:tags":[
        "transport",
        "road"
    ],
    "sg:website":"http://www.lapiramidesnc.it",
    "wof:name":"Onoranze Funebri La Piramide",
    "wof:placetype":"venue"
},
  "geometry": {"coordinates":[12.610861,41.808784],"type":"Point"}
}