{
  "type": "Feature",
  "properties": {
    "addr:full":"69, Via Bisenzio 59013 Montemurlo Montemurlo Prato 59013",
    "addr:postcode":"59013;59013",
    "addr:street":"Via Bisenzio",
    "iso:country":"IT",
    "sg:address":"69, Via Bisenzio 59013 Montemurlo",
    "sg:city":"Montemurlo",
    "sg:classifiers":[
        {
            "category":"Real Estate",
            "subcategory":"Architect",
            "type":"Services"
        }
    ],
    "sg:phone":"+39 0574 652321",
    "sg:postcode":"59013",
    "sg:province":"Prato",
    "sg:tags":[
        "textile",
        "clothing"
    ],
    "wof:name":"Lanificio Fortex (s.p.a.)",
    "wof:placetype":"venue"
},
  "geometry": {"coordinates":[11.04677,43.907227],"type":"Point"}
}