{
  "type": "Feature",
  "properties": {
    "addr:full":"12, Via Tre Avieri 33030 Talmassons Talmassons Udine 33030",
    "addr:postcode":"33030;33030",
    "addr:street":"Via Tre Avieri",
    "iso:country":"IT",
    "sg:address":"12, Via Tre Avieri 33030 Talmassons",
    "sg:city":"Talmassons",
    "sg:classifiers":[
        {
            "category":"Food & Beverages",
            "subcategory":"Groceries & Convenience Stores",
            "type":"Retail Goods"
        }
    ],
    "sg:phone":"+39 0432 766248",
    "sg:postcode":"33030",
    "sg:province":"Udine",
    "sg:tags":[
        "drink"
    ],
    "wof:name":"Distilleria Mangilli (s.p.a.)",
    "wof:placetype":"venue"
},
  "geometry": {"coordinates":[13.138256,45.920639],"type":"Point"}
}