{
  "type": "Feature",
  "properties": {
    "iso:country":"IT",
    "sg:address":"28100 Novara",
    "sg:city":"Novara",
    "sg:orig_category":"Apparecchi, Attrezzature E Forniture Per Centri Estetici. Forniture Per Attivita' Commerciali Ed Artigianali",
    "sg:phone":"+39 0321 623326",
    "sg:postcode":"28100",
    "sg:province":"Novara",
    "sg:website":"http://www.srprogetti.it",
    "wof:name":"S.r. Progetti Srl",
    "wof:placetype":"venue"
},
  "geometry": {"coordinates":[8.621284,45.45097],"type":"Point"}
}