{
  "type": "Feature",
  "properties": {
    "iso:country":"IT",
    "sg:address":"110, V. Primo D'altri 47023 Cesena",
    "sg:city":"Cesena",
    "sg:classifiers":[
        {
            "category":"Professional",
            "subcategory":"Engineering",
            "type":"Services"
        }
    ],
    "sg:phone":"+39 0547 347008",
    "sg:postcode":"47023",
    "sg:province":"Forl\u00ec-Cesena",
    "sg:tags":[
        "machine",
        "-",
        "mechanical"
    ],
    "sg:website":"http://www.pantanigiovanni.com:ws_end: :mark:ws:http://www.paginegialle.it/pantani",
    "wof:name":"Pantani Divisione Tubi",
    "wof:placetype":"venue"
},
  "geometry": {"coordinates":[12.1927919388,44.1565856934],"type":"Point"}
}