{
  "type": "Feature",
  "properties": {
    "iso:country":"IT",
    "sg:address":"20090 Assago",
    "sg:city":"Assago",
    "sg:orig_category":"Valvole E Apparecchiature Di Misura. Minuterie Metalliche E Ferramenta. Forniture Per Attivita' Industriali",
    "sg:phone":"+39 02 488 2509",
    "sg:postcode":"20090",
    "sg:province":"Milano",
    "wof:name":"Ridart S.r.l.",
    "wof:placetype":"venue"
},
  "geometry": {"coordinates":[9.126291,45.409103],"type":"Point"}
}