{
  "type": "Feature",
  "properties": {
    "iso:country":"IT",
    "sg:address":"Via Crosa, 14/18 28065 Cerano",
    "sg:city":"Cerano",
    "sg:classifiers":[
        {
            "category":"Banks & Credit Unions",
            "subcategory":"Investment Brokerage",
            "type":"Services"
        }
    ],
    "sg:phone":"+39 0321 7781",
    "sg:postcode":"28065",
    "sg:province":"Novara",
    "sg:tags":[
        "women's",
        "clothing",
        "accessory"
    ],
    "sg:website":"www.micheleletizia.com",
    "wof:name":"Michele Letizia Spa",
    "wof:placetype":"venue"
},
  "geometry": {"coordinates":[8.796262,45.406376],"type":"Point"}
}