{
  "type": "Feature",
  "properties": {
    "iso:country":"IT",
    "sg:address":"00040 Pomezia",
    "sg:city":"Pomezia",
    "sg:orig_category":"Servizi E Lavori Per Abbigliamento E Pelletterie. Servizi Ausiliari Di Sorveglianza, Manutenzione E Pulizia",
    "sg:phone":"+39 06 914 5190",
    "sg:postcode":"00040",
    "sg:province":"Roma",
    "wof:name":"Lai Sud Srl",
    "wof:placetype":"venue"
},
  "geometry": {"coordinates":[12.444936,41.776138],"type":"Point"}
}