{
  "type": "Feature",
  "properties": {
    "iso:country":"IT",
    "sg:address":"01010 Marta",
    "sg:city":"Marta",
    "sg:orig_category":"Liquori - Vendita Al Dettaglio",
    "sg:phone":"+39 0761 871535",
    "sg:postcode":"01010",
    "sg:province":"Viterbo",
    "wof:name":"Torrefazione Fida Di Sassara Guerrino & C. Snc",
    "wof:placetype":"venue"
},
  "geometry": {"coordinates":[11.929184,42.534382],"type":"Point"}
}