{
  "type": "Feature",
  "properties": {
    "iso:country":"IT",
    "sg:address":"30015 Chioggia",
    "sg:city":"Chioggia",
    "sg:orig_category":"Prodotti Di Base E Forniture Per Industria Alimentare E Bevande. Prodotti Chimici Secondari. Forniture Alle Strutture Ricettive",
    "sg:phone":"+39 041 402087",
    "sg:postcode":"30015",
    "sg:province":"Venezia",
    "wof:name":"Casa Del Ghiaccio",
    "wof:placetype":"venue"
},
  "geometry": {"coordinates":[12.2832012177,45.219871521],"type":"Point"}
}