{
  "type": "Feature",
  "properties": {
    "addr:full":"Via Montello 31040 Nervesa Della Battaglia Nervesa della Battaglia Treviso 31040",
    "addr:housenumber":"della",
    "addr:postcode":"31040;31040",
    "addr:street":"Via Montello;Treviso",
    "iso:country":"IT",
    "sg:address":"Via Montello 31040 Nervesa Della Battaglia",
    "sg:city":"Nervesa della Battaglia",
    "sg:classifiers":[
        {
            "category":"Wholesale",
            "subcategory":"Medical Equipment & Supplies",
            "type":"Manufacturing & Wholesale Goods"
        }
    ],
    "sg:phone":"+39 0422 887584",
    "sg:postcode":"31040",
    "sg:province":"Treviso",
    "sg:tags":[
        "-",
        "health",
        "instrument"
    ],
    "wof:name":"Rehateam Di Pivato & Casagrande S.a.s.",
    "wof:placetype":"venue"
},
  "geometry": {"coordinates":[12.244928,45.809914],"type":"Point"}
}