{
  "type": "Feature",
  "properties": {
    "addr:full":"67051 Avezzano L'Aquila 67051",
    "addr:postcode":"67051;67051",
    "iso:country":"IT",
    "sg:address":"67051 Avezzano",
    "sg:orig_category":"Automobili E Mezzi Di Trasporto",
    "sg:phone":"+39 0863 412012",
    "sg:postcode":"67051",
    "sg:province":"L'Aquila",
    "wof:name":"Brenta Euroindustrie S.p.a.",
    "wof:placetype":"venue"
},
  "geometry": {"coordinates":[13.399934,42.350697],"type":"Point"}
}