{
  "type": "Feature",
  "properties": {
    "iso:country":"IT",
    "sg:address":"28021 Borgomanero",
    "sg:city":"Borgomanero",
    "sg:orig_category":"Informatica - Consulenza E Servizi. Automazione E Macchine Per Ufficio. Servizi Ausiliari Di Analisi, Controllo E Ricerca. Servizi Per Aziende, Manifestazioni E Supporto Agli Scambi Commerciali",
    "sg:phone":"+39 0322 846081",
    "sg:postcode":"28021",
    "sg:province":"Novara",
    "sg:website":"http://www.spaziopersonal.it",
    "wof:name":"Spazio Personal Srl",
    "wof:placetype":"venue"
},
  "geometry": {"coordinates":[8.465839,45.700108],"type":"Point"}
}