{
  "type": "Feature",
  "properties": {
    "addr:full":"55, Via Lamarmora Alfonso 50121 Firenze Firenze Firenze 50121",
    "addr:postcode":"50121;50121",
    "addr:street":"Via Lamarmora Alfonso",
    "iso:country":"IT",
    "sg:address":"55, Via Lamarmora Alfonso 50121 Firenze",
    "sg:city":"Firenze",
    "sg:classifiers":[
        {
            "category":"Shopping",
            "subcategory":"Clothing, Apparel, & Fashions",
            "type":"Retail Goods"
        }
    ],
    "sg:phone":"+39 39055577863",
    "sg:postcode":"50121",
    "sg:province":"Firenze",
    "sg:tags":[
        "clothes"
    ],
    "wof:name":"Pellicceria Oesse S.r.l.",
    "wof:placetype":"venue"
},
  "geometry": {"coordinates":[11.256902,43.768734],"type":"Point"}
}