{
  "type": "Feature",
  "properties": {
    "addr:full":"14, Via G. Pascoli 25013 Carpenedolo Carpenedolo Brescia 25013",
    "addr:postcode":"25013;25013",
    "addr:street":"Via G. Pascoli",
    "iso:country":"IT",
    "sg:address":"14, Via G. Pascoli 25013 Carpenedolo",
    "sg:city":"Carpenedolo",
    "sg:classifiers":[
        {
            "category":"Personal",
            "subcategory":"Shoe Repair & Shine",
            "type":"Services"
        }
    ],
    "sg:phone":"+39 030 996 5431",
    "sg:postcode":"25013",
    "sg:province":"Brescia",
    "sg:tags":[
        "leather"
    ],
    "wof:name":"P.b.s. Di Sorrentino M. & C. (s.r.l.)",
    "wof:placetype":"venue"
},
  "geometry": {"coordinates":[10.222958,45.539829],"type":"Point"}
}