{
  "type": "Feature",
  "properties": {
    "addr:full":"20090 Opera Opera Milano 20090",
    "addr:postcode":"20090;20090",
    "iso:country":"IT",
    "sg:address":"20090 Opera",
    "sg:city":"Opera",
    "sg:orig_category":"Cartotecnica E Servizi. Articoli Per Imballaggio E Confezionamento",
    "sg:phone":"+39 02 5760 2644",
    "sg:postcode":"20090",
    "sg:province":"Milano",
    "wof:name":"Asticarta (s.r.l.)",
    "wof:placetype":"venue"
},
  "geometry": {"coordinates":[9.207747,45.367241],"type":"Point"}
}