{
  "type": "Feature",
  "properties": {
    "iso:country":"IT",
    "sg:address":"20019 Settimo Milanese",
    "sg:city":"Settimo Milanese",
    "sg:orig_category":"Insonorizzazione Industriale",
    "sg:phone":"+39 02 328 8055",
    "sg:postcode":"20019",
    "sg:province":"Milano",
    "sg:website":"http://www.pumasrl.it",
    "wof:name":"Puma Srl",
    "wof:placetype":"venue"
},
  "geometry": {"coordinates":[9.074924,45.472931],"type":"Point"}
}