{
  "type": "Feature",
  "properties": {
    "iso:country":"IT",
    "sg:address":"34147 Trieste",
    "sg:city":"Trieste",
    "sg:orig_category":"Legno E Semilavorati",
    "sg:phone":"+39 040 899 1111",
    "sg:postcode":"34147",
    "sg:province":"Trieste",
    "sg:website":"http://www.colombin.it",
    "wof:name":"Colombin G. M. & Figlio Spa",
    "wof:placetype":"venue"
},
  "geometry": {"coordinates":[13.81501,45.615524],"type":"Point"}
}