{
  "type": "Feature",
  "properties": {
    "iso:country":"IT",
    "sg:address":"10136 Torino",
    "sg:city":"Torino",
    "sg:orig_category":"Bagno - Accessori E Mobili",
    "sg:phone":"+39 011 329 0027",
    "sg:postcode":"10136",
    "sg:province":"Torino",
    "sg:website":"http://www.chiabotto.it",
    "wof:name":"Chiabotto",
    "wof:placetype":"venue"
},
  "geometry": {"coordinates":[7.642694,45.049938],"type":"Point"}
}