{
  "type": "Feature",
  "properties": {
    "addr:full":"31030 Carbonera Carbonera Treviso 31030",
    "addr:postcode":"31030;31030",
    "iso:country":"IT",
    "sg:address":"31030 Carbonera",
    "sg:city":"Carbonera",
    "sg:orig_category":"Motocicli E Motocarri - Commercio E Riparazione",
    "sg:phone":"+39 0422 445436",
    "sg:postcode":"31030",
    "sg:province":"Treviso",
    "wof:name":"Rebuschi Racing Srl",
    "wof:placetype":"venue"
},
  "geometry": {"coordinates":[12.2839345932,45.6905326843],"type":"Point"}
}