{
  "type": "Feature",
  "properties": {
    "iso:country":"IT",
    "sg:address":"Via Guido Rossa, 1/3 42044 Gualtieri",
    "sg:classifiers":[
        {
            "category":"Home & Garden",
            "subcategory":"Home Furnishings",
            "type":"Retail Goods"
        }
    ],
    "sg:phone":"+39 0522 22601",
    "sg:postcode":"42044",
    "sg:province":"Reggio Nell'Emilia",
    "sg:tags":[
        "air-conditioners"
    ],
    "sg:website":"www.olimpiasplendid.it",
    "wof:name":"Olimpia Splendid Spa",
    "wof:placetype":"venue"
},
  "geometry": {"coordinates":[10.627794,44.696228],"type":"Point"}
}