{
  "type": "Feature",
  "properties": {
    "iso:country":"IT",
    "sg:address":"13, Via G. Puccini 33040 Campolongo Al Torre",
    "sg:city":"Campolongo al Torre",
    "sg:classifiers":[
        {
            "category":"Shopping",
            "type":"Retail Goods"
        }
    ],
    "sg:phone":"+39 0431 973338",
    "sg:postcode":"33040",
    "sg:province":"Udine",
    "sg:tags":[
        "finished",
        "-",
        "metallic"
    ],
    "wof:name":"Piemme (s.r.l.)",
    "wof:placetype":"venue"
},
  "geometry": {"coordinates":[13.2307243347,46.0649414062],"type":"Point"}
}