{
  "type": "Feature",
  "properties": {
    "iso:country":"IT",
    "sg:address":"26010 Postino",
    "sg:orig_category":"Impiantistica E Prodotti Tecnologici Per Edilizia. Forniture Industriali Per Prevenzione, Controllo E Sicurezza",
    "sg:phone":"+39 0373 978015",
    "sg:postcode":"26010",
    "sg:province":"Cremona",
    "wof:name":"Same Di Eredi Marzagalli (s.n.c.)",
    "wof:placetype":"venue"
},
  "geometry": {"coordinates":[9.54708,45.362633],"type":"Point"}
}