{
  "type": "Feature",
  "properties": {
    "iso:country":"IT",
    "sg:address":"27, Via Sali 48018 Faenza",
    "sg:city":"Faenza",
    "sg:classifiers":[
        {
            "category":"Shopping",
            "subcategory":"Clothing, Apparel, & Fashions",
            "type":"Retail Goods"
        }
    ],
    "sg:phone":"+39 0546 620229",
    "sg:postcode":"48018",
    "sg:province":"Ravenna",
    "sg:tags":[
        "clothes"
    ],
    "wof:name":"Calzificio Nonni",
    "wof:placetype":"venue"
},
  "geometry": {"coordinates":[11.856049,44.298733],"type":"Point"}
}