{
  "type": "Feature",
  "properties": {
    "iso:country":"IT",
    "sg:address":"06034 Foligno",
    "sg:city":"Foligno",
    "sg:orig_category":"Elettronica Professionale E Di Consumo. Musica",
    "sg:phone":"+39 0742 24164",
    "sg:postcode":"06034",
    "sg:province":"Perugia",
    "wof:name":"Pinchi Fabbrica Artigiana Di Organi Di Pinchi G.&c. Sas",
    "wof:placetype":"venue"
},
  "geometry": {"coordinates":[12.328445,43.095852],"type":"Point"}
}