{
  "type": "Feature",
  "properties": {
    "iso:country":"IT",
    "sg:address":"Via Marconi 62 13835 Trivero",
    "sg:city":"Trivero",
    "sg:classifiers":[
        {
            "category":"Shopping",
            "subcategory":"Clothing, Apparel, & Fashions",
            "type":"Retail Goods"
        }
    ],
    "sg:phone":"+39 015 759 2300",
    "sg:postcode":"13835",
    "sg:province":"Biella",
    "sg:tags":[
        "clothing",
        "fabric"
    ],
    "wof:name":"Lanificio Mario Zegna S.p.a.",
    "wof:placetype":"venue"
},
  "geometry": {"coordinates":[8.003205,45.565845],"type":"Point"}
}