{
  "type": "Feature",
  "properties": {
    "iso:country":"IT",
    "sg:address":"20131 Milano",
    "sg:city":"Milano",
    "sg:orig_category":"Traduttori Ed Interpreti",
    "sg:phone":"+39 02 287 0336",
    "sg:postcode":"20131",
    "sg:province":"Milano",
    "sg:website":"http://www.aniti.it",
    "wof:name":"A.n.i.t.i. - Associazione Nazionale Italiana Traduttori Interpreti",
    "wof:placetype":"venue"
},
  "geometry": {"coordinates":[9.226311,45.489155],"type":"Point"}
}