{
  "type": "Feature",
  "properties": {
    "iso:country":"IT",
    "sg:address":"7, Via Primavera 27043 Broni",
    "sg:city":"Broni",
    "sg:classifiers":[
        {
            "category":"Shopping",
            "subcategory":"Jewelry",
            "type":"Retail Goods"
        }
    ],
    "sg:phone":"+39 39038556093",
    "sg:postcode":"27043",
    "sg:province":"Pavia",
    "sg:tags":[
        "jewellery"
    ],
    "wof:name":"Canzian Gioielli Di Canzian Alberto",
    "wof:placetype":"venue"
},
  "geometry": {"coordinates":[9.255414,45.051456],"type":"Point"}
}