{
  "type": "Feature",
  "properties": {
    "iso:country":"IT",
    "sg:address":"10024 Moncalieri",
    "sg:city":"Moncalieri",
    "sg:orig_category":"Autofficine, Gommisti E Autolavaggi - Attrezzature",
    "sg:phone":"+39 011 627 1895",
    "sg:postcode":"10024",
    "sg:province":"Torino",
    "wof:name":"Nuova Alfa Di Nicastri Francesco",
    "wof:placetype":"venue"
},
  "geometry": {"coordinates":[7.663428,45.001148],"type":"Point"}
}