{
  "type": "Feature",
  "properties": {
    "iso:country":"IT",
    "sg:address":"26100 Cremona",
    "sg:city":"Cremona",
    "sg:orig_category":"Alberghi E Strutture Extra Alberghiere. Ospedali E Servizi Sanitari",
    "sg:phone":"+39 0372 533511",
    "sg:postcode":"26100",
    "sg:province":"Cremona",
    "wof:name":"F. Soldi Centro Geriatrico Cremonese",
    "wof:placetype":"venue"
},
  "geometry": {"coordinates":[10.034232,45.143322],"type":"Point"}
}