{
  "type": "Feature",
  "properties": {
    "iso:country":"IT",
    "sg:address":"20090 Pieve Emanuele",
    "sg:city":"Pieve Emanuele",
    "sg:orig_category":"Motori Ed Organi Di Trasmissione. Ricambi E Componenti Dei Mezzi Di Trasporto",
    "sg:phone":"+39 02 9042 0039",
    "sg:postcode":"20090",
    "sg:province":"Milano",
    "sg:website":"http://www.coelmotori.it",
    "wof:name":"Coel Motori Srl",
    "wof:placetype":"venue"
},
  "geometry": {"coordinates":[9.176363945,45.3751106262],"type":"Point"}
}