{
  "type": "Feature",
  "properties": {
    "iso:country":"IT",
    "sg:address":"10/12, Via Divisione Acqui 25065 Lumezzane",
    "sg:city":"Lumezzane",
    "sg:classifiers":[
        {
            "category":"Professional",
            "subcategory":"Printing & Photocopies",
            "type":"Services"
        }
    ],
    "sg:phone":"+39 030 892 0276",
    "sg:postcode":"25065",
    "sg:province":"Brescia",
    "wof:name":"Tipolitografia Pagani S.r.l.",
    "wof:placetype":"venue"
},
  "geometry": {"coordinates":[10.2680454254,45.6375770569],"type":"Point"}
}