{
  "type": "Feature",
  "properties": {
    "iso:country":"IT",
    "sg:address":"Via Delle Citta' 200 50052 Certaldo",
    "sg:city":"Certaldo",
    "sg:classifiers":[
        {
            "category":"Government",
            "subcategory":"Customs House",
            "type":"Public Place"
        }
    ],
    "sg:phone":"+39 0571 62711",
    "sg:postcode":"50052",
    "sg:province":"Firenze",
    "sg:tags":[
        "caravan",
        "folding"
    ],
    "sg:website":"www.shelbox.it",
    "wof:name":"Shelbox Srl",
    "wof:placetype":"venue"
},
  "geometry": {"coordinates":[11.0664424896,43.5304794312],"type":"Point"}
}