{
  "type": "Feature",
  "properties": {
    "addr:full":"Via Garibaldi 70 22060 Carugo Carugo Como 22060",
    "addr:housenumber":"70",
    "addr:postcode":"22060;22060",
    "addr:street":"Via Garibaldi",
    "iso:country":"IT",
    "sg:address":"Via Garibaldi 70 22060 Carugo",
    "sg:city":"Carugo",
    "sg:orig_category":"Furniture, General",
    "sg:phone":"+39 031 761267",
    "sg:postcode":"22060",
    "sg:province":"Como",
    "sg:website":"www.arredaesse.it",
    "wof:name":"Arredaesse Srl",
    "wof:placetype":"venue"
},
  "geometry": {"coordinates":[9.2029790878,45.7134895325],"type":"Point"}
}