{
  "type": "Feature",
  "properties": {
    "iso:country":"IT",
    "sg:address":"Via Isonzo 153; Latina; 04100",
    "sg:city":"Latina",
    "sg:classifiers":[
        {
            "category":"Banks & Credit Unions",
            "subcategory":"Bank",
            "type":"Services"
        }
    ],
    "sg:phone":"+39 0773 660123",
    "sg:postcode":"04100",
    "sg:province":"Latina",
    "wof:name":"Istituto Bancario, San Paolo Di Torino Spa",
    "wof:placetype":"venue"
},
  "geometry": {"coordinates":[12.906453,41.45311],"type":"Point"}
}