{
  "type": "Feature",
  "properties": {
    "iso:country":"IT",
    "sg:address":"267, Localita' Pino 50052 Certaldo",
    "sg:city":"Certaldo",
    "sg:classifiers":[
        {
            "category":"Home & Garden",
            "subcategory":"Home Furnishings",
            "type":"Retail Goods"
        }
    ],
    "sg:phone":"+39 0571 668658",
    "sg:postcode":"50052",
    "sg:province":"Firenze",
    "sg:tags":[
        "household"
    ],
    "wof:name":"Walmar Co.mo.t S.r.l.",
    "wof:placetype":"venue"
},
  "geometry": {"coordinates":[11.117519,43.587368],"type":"Point"}
}