{
  "type": "Feature",
  "properties": {
    "addr:full":"00042 Anzio Anzio Roma 00042",
    "addr:postcode":"00042;roma 00042",
    "iso:country":"IT",
    "sg:address":"00042 Anzio",
    "sg:city":"Anzio",
    "sg:orig_category":"Ospedali E Servizi Sanitari. Centri Di Estetica E Cosmesi E Servizi",
    "sg:phone":"+39 06 984 5797",
    "sg:postcode":"00042",
    "sg:province":"Roma",
    "wof:name":"Viviani Giovanni",
    "wof:placetype":"venue"
},
  "geometry": {"coordinates":[12.463281,41.915287],"type":"Point"}
}