{
  "type": "Feature",
  "properties": {
    "addr:full":"24042 Capriate San Gervasio Capriate San Gervasio Bergamo 24042",
    "addr:housenumber":"24042",
    "addr:postcode":"24042",
    "addr:street":"Capriate",
    "iso:country":"IT",
    "sg:address":"24042 Capriate San Gervasio",
    "sg:city":"Capriate San Gervasio",
    "sg:orig_category":"Abbigliamento Intimo, Calze E Costumi Da Bagno",
    "sg:phone":"+39 02 9096 4240",
    "sg:postcode":"24042",
    "sg:province":"Bergamo",
    "wof:name":"Esseti S.r.l.",
    "wof:placetype":"venue"
},
  "geometry": {"coordinates":[9.526007,45.618259],"type":"Point"}
}