{
  "type": "Feature",
  "properties": {
    "iso:country":"IT",
    "sg:address":"36061 Bassano Del Grappa",
    "sg:city":"Bassano del Grappa",
    "sg:orig_category":"Servizi E Lavori Per Edilizia E Lavori Pubblici. Servizi Al Turismo",
    "sg:phone":"+39 0424 529502",
    "sg:postcode":"36061",
    "sg:province":"Vicenza",
    "sg:website":"http://www.immobiliareroma.it",
    "wof:name":"Agenzia D'affari Immobiliare Roma Di Grando Giampaolo & C. Sas",
    "wof:placetype":"venue"
},
  "geometry": {"coordinates":[11.734739,45.766273],"type":"Point"}
}