{
  "type": "Feature",
  "properties": {
    "iso:country":"IT",
    "sg:address":"20089 Rozzano",
    "sg:city":"Rozzano",
    "sg:orig_category":"Articoli Per Imballaggio E Confezionamento",
    "sg:phone":"+39 02 5751 1471",
    "sg:postcode":"20089",
    "sg:province":"Milano",
    "wof:name":"Ve.lia Srl",
    "wof:placetype":"venue"
},
  "geometry": {"coordinates":[9.167731,45.380188],"type":"Point"}
}