{
  "type": "Feature",
  "properties": {
    "addr:full":"80078 Pozzuoli Pozzuoli Napoli 80078",
    "addr:postcode":"80078;80078",
    "iso:country":"IT",
    "sg:address":"80078 Pozzuoli",
    "sg:city":"Pozzuoli",
    "sg:orig_category":"Acciai Inossidabili - Lavorazione",
    "sg:phone":"+39 081 866 4591",
    "sg:postcode":"80078",
    "sg:province":"Napoli",
    "sg:website":"http://www.carafa.it",
    "wof:name":"Carafa Snc",
    "wof:placetype":"venue"
},
  "geometry": {"coordinates":[14.334374,40.849602],"type":"Point"}
}