{
  "type": "Feature",
  "properties": {
    "iso:country":"IT",
    "sg:address":"45, Via Camagre 37063 Isola Della Scala",
    "sg:city":"Isola della Scala",
    "sg:classifiers":[
        {
            "category":"Professional",
            "subcategory":"Engineering",
            "type":"Services"
        }
    ],
    "sg:phone":"+39 045 664 8300",
    "sg:postcode":"37063",
    "sg:province":"Verona",
    "sg:tags":[
        "machine",
        "-",
        "mechanical"
    ],
    "wof:name":"Sierra S.p.a.",
    "wof:placetype":"venue"
},
  "geometry": {"coordinates":[11.005299,45.251801],"type":"Point"}
}