{
  "type": "Feature",
  "properties": {
    "iso:country":"IT",
    "sg:address":"98066 Patti",
    "sg:city":"Patti",
    "sg:orig_category":"Non-classified Establishments",
    "sg:phone":"+39 0941 21778",
    "sg:postcode":"98066",
    "sg:province":"Messina",
    "wof:name":"Salomi Pasquale",
    "wof:placetype":"venue"
},
  "geometry": {"coordinates":[14.963554,38.155125],"type":"Point"}
}