{
  "type": "Feature",
  "properties": {
    "iso:country":"IT",
    "sg:address":"Via Baviera 11 35027 Noventa Padovana",
    "sg:city":"Noventa Padovana",
    "sg:classifiers":[
        {
            "category":"Sports & Exercise",
            "subcategory":"Gym",
            "type":"Entertainment"
        }
    ],
    "sg:phone":"+39 049 870 4875",
    "sg:postcode":"35027",
    "sg:province":"Padova",
    "sg:tags":[
        "athletic",
        "equipment",
        "gymnastic"
    ],
    "wof:name":"Valsport S.p.a.",
    "wof:placetype":"venue"
},
  "geometry": {"coordinates":[11.93668,45.404648],"type":"Point"}
}