{
  "type": "Feature",
  "properties": {
    "iso:country":"IT",
    "sg:address":"24043 Caravaggio",
    "sg:city":"Caravaggio",
    "sg:orig_category":"Motori Ed Organi Di Trasmissione. Ricambi E Componenti Dei Mezzi Di Trasporto",
    "sg:phone":"+39 036 335 0768",
    "sg:postcode":"24043",
    "sg:province":"Bergamo",
    "wof:name":"Sorem Trasmissioni Meccaniche S.p.a.",
    "wof:placetype":"venue"
},
  "geometry": {"coordinates":[9.6581792831,45.4705200195],"type":"Point"}
}