{
  "type": "Feature",
  "properties": {
    "iso:country":"IT",
    "sg:address":"10098 Rivoli",
    "sg:city":"Rivoli",
    "sg:classifiers":[
        {
            "category":"Wholesale",
            "subcategory":"Machinery & Supplies",
            "type":"Manufacturing & Wholesale Goods"
        }
    ],
    "sg:phone":"+39 011 957 4025",
    "sg:postcode":"10098",
    "sg:province":"Torino",
    "sg:tags":[
        "activities",
        "industrial"
    ],
    "wof:name":"Taurus Sages Srl",
    "wof:placetype":"venue"
},
  "geometry": {"coordinates":[7.556763,45.079773],"type":"Point"}
}