{
  "type": "Feature",
  "properties": {
    "iso:country":"IT",
    "sg:address":"4, Via Kennedy 22030 Lipomo",
    "sg:city":"Lipomo",
    "sg:classifiers":[
        {
            "category":"Manufacturing",
            "subcategory":"Tools & Machinery",
            "type":"Manufacturing & Wholesale Goods"
        }
    ],
    "sg:phone":"+39 39031280915",
    "sg:postcode":"22030",
    "sg:province":"Como",
    "sg:tags":[
        "environment",
        "equipment",
        "-"
    ],
    "wof:name":"V.r.e.i.",
    "wof:placetype":"venue"
},
  "geometry": {"coordinates":[9.1255,45.791813],"type":"Point"}
}