{
  "type": "Feature",
  "properties": {
    "addr:full":"29010 Nibbiano Nibbiano Piacenza 29010",
    "addr:postcode":"29010;29010",
    "iso:country":"IT",
    "sg:address":"29010 Nibbiano",
    "sg:city":"Nibbiano",
    "sg:classifiers":[
        {
            "category":"Professional",
            "subcategory":"Printing & Photocopies",
            "type":"Services"
        }
    ],
    "sg:phone":"+39 0523 992055",
    "sg:postcode":"29010",
    "sg:province":"Piacenza",
    "sg:tags":[
        "publishing"
    ],
    "wof:name":"Casa Editrice Albertini Di Palombo Clelia",
    "wof:placetype":"venue"
},
  "geometry": {"coordinates":[9.3980178833,44.9507141113],"type":"Point"}
}