{
  "type": "Feature",
  "properties": {
    "addr:full":"36, Localita' Ghiara Sabbioni 43012 Fontanellato Fontanellato Parma 43012",
    "addr:postcode":"43012;43012",
    "addr:street":"Localita ' Ghiara Sabbioni",
    "iso:country":"IT",
    "sg:address":"36, Localita' Ghiara Sabbioni 43012 Fontanellato",
    "sg:city":"Fontanellato",
    "sg:classifiers":[
        {
            "category":"Manufacturing",
            "subcategory":"Rubber & Plastics",
            "type":"Manufacturing & Wholesale Goods"
        }
    ],
    "sg:phone":"+39 0521 824211",
    "sg:postcode":"43012",
    "sg:province":"Parma",
    "wof:name":"Selip Spa",
    "wof:placetype":"venue"
},
  "geometry": {"coordinates":[10.201125145,44.8890037537],"type":"Point"}
}