{
  "type": "Feature",
  "properties": {
    "addr:full":"Via Mazzini 161 15067 Novi Ligure Novi Ligure Alessandria 15067",
    "addr:housenumber":"161",
    "addr:postcode":"15067;15067",
    "addr:street":"Via Mazzini",
    "iso:country":"IT",
    "sg:address":"Via Mazzini 161 15067 Novi Ligure",
    "sg:city":"Novi Ligure",
    "sg:classifiers":[
        {
            "category":"Banks & Credit Unions",
            "subcategory":"Bureau De Change",
            "type":"Services"
        }
    ],
    "sg:phone":"+39 0143 2148",
    "sg:postcode":"15067",
    "sg:province":"Alessandria",
    "sg:tags":[
        "dental",
        "gypsum"
    ],
    "sg:website":"www.zingardi.com",
    "wof:name":"Industria Zingardi Srl",
    "wof:placetype":"venue"
},
  "geometry": {"coordinates":[8.789386,44.770988],"type":"Point"}
}