{
  "type": "Feature",
  "properties": {
    "addr:full":"10042 Nichelino Nichelino Torino 10042",
    "addr:postcode":"10042;10042",
    "iso:country":"IT",
    "sg:address":"10042 Nichelino",
    "sg:city":"Nichelino",
    "sg:orig_category":"Prodotti Vari In Metallo",
    "sg:phone":"+39 011 606 9268",
    "sg:postcode":"10042",
    "sg:province":"Torino",
    "wof:name":"Metalfuni Srl",
    "wof:placetype":"venue"
},
  "geometry": {"coordinates":[7.6464476585,45.0032081604],"type":"Point"}
}