{
  "type": "Feature",
  "properties": {
    "iso:country":"IT",
    "sg:address":"12042 Bra",
    "sg:city":"Bra",
    "sg:orig_category":"Apparecchiature E Sistemi Per Magazzinaggio E Movimentazione",
    "sg:phone":"+39 0172 457444",
    "sg:postcode":"12042",
    "sg:province":"Cuneo",
    "sg:website":"http://www.ocs-italia.it",
    "wof:name":"Ocs Srl",
    "wof:placetype":"venue"
},
  "geometry": {"coordinates":[7.537202,44.377537],"type":"Point"}
}