{
  "type": "Feature",
  "properties": {
    "addr:full":"Via Provinciale Saronnese 59 20027 Rescaldina Rescaldina Milano 20027",
    "addr:housenumber":"59",
    "addr:postcode":"20027;20027",
    "addr:street":"Via Provinciale Saronnese",
    "iso:country":"IT",
    "sg:address":"Via Provinciale Saronnese 59 20027 Rescaldina",
    "sg:city":"Rescaldina",
    "sg:classifiers":[
        {
            "category":"Home & Garden",
            "subcategory":"Household Appliances",
            "type":"Retail Goods"
        }
    ],
    "sg:phone":"+39 0331 576447",
    "sg:postcode":"20027",
    "sg:province":"Milano",
    "sg:tags":[
        "electric"
    ],
    "wof:name":"I.c.f. Srl",
    "wof:placetype":"venue"
},
  "geometry": {"coordinates":[8.959425,45.61219],"type":"Point"}
}