{
  "type": "Feature",
  "properties": {
    "iso:country":"IT",
    "sg:address":"15048 Valenza",
    "sg:city":"Valenza",
    "sg:orig_category":"Cesellatori Ed Incassatori",
    "sg:phone":"+39 0131 945306",
    "sg:postcode":"15048",
    "sg:province":"Alessandria",
    "wof:name":"L'incastoneria Snc Di Ognibene D. & Bellarosa D.",
    "wof:placetype":"venue"
},
  "geometry": {"coordinates":[8.610498,44.908798],"type":"Point"}
}