{
  "type": "Feature",
  "properties": {
    "addr:full":"25033 Cologne Cologne Brescia 25033",
    "addr:postcode":"25033;25033",
    "iso:country":"IT",
    "sg:address":"25033 Cologne",
    "sg:city":"Cologne",
    "sg:orig_category":"Apparecchiature E Sistemi Per Imballaggio E Confezionamento",
    "sg:phone":"+39 030 715 6960",
    "sg:postcode":"25033",
    "sg:province":"Brescia",
    "wof:name":"Bonardi Srl",
    "wof:placetype":"venue"
},
  "geometry": {"coordinates":[9.941092,45.577713],"type":"Point"}
}