{
  "type": "Feature",
  "properties": {
    "iso:country":"IT",
    "sg:address":"80056 Ercolano",
    "sg:city":"Ercolano",
    "sg:orig_category":"Servizi Ausiliari Di Analisi, Controllo E Ricerca. Acqua, Luce, Gas E Societa' Di Esercizio Pubblico",
    "sg:phone":"+39 081 777 7149",
    "sg:postcode":"80056",
    "sg:province":"Napoli",
    "wof:name":"Osservatorio Vesuviano",
    "wof:placetype":"venue"
},
  "geometry": {"coordinates":[14.385011,40.821007],"type":"Point"}
}