{
  "type": "Feature",
  "properties": {
    "addr:full":"06132 Perugia Perugia Perugia 06132",
    "addr:postcode":"06132;06132",
    "iso:country":"IT",
    "sg:address":"06132 Perugia",
    "sg:city":"Perugia",
    "sg:orig_category":"Arredo Cucina Ed Elettrodomestici. Elettrodomestici",
    "sg:phone":"+39 075 528 7800",
    "sg:postcode":"06132",
    "sg:province":"Perugia",
    "wof:name":"Finistauri E Bianchi Snc",
    "wof:placetype":"venue"
},
  "geometry": {"coordinates":[12.351051,43.080471],"type":"Point"}
}