{
  "type": "Feature",
  "properties": {
    "addr:full":"20123 Milano Milano Milano 20123",
    "addr:postcode":"20123;20123",
    "iso:country":"IT",
    "sg:address":"20123 Milano",
    "sg:city":"Milano",
    "sg:orig_category":"Petroli, Gas E Combustibili. Servizi E Lavori Industria Chimica. Servizi E Lavori Per Edilizia E Lavori Pubblici. Acqua, Luce, Gas E Societa' Di Esercizio Pubblico",
    "sg:phone":"+39 02 498 9335",
    "sg:postcode":"20123",
    "sg:province":"Milano",
    "wof:name":"Nettis Impianti Spa",
    "wof:placetype":"venue"
},
  "geometry": {"coordinates":[9.1736650467,45.4675445557],"type":"Point"}
}