{
  "type": "Feature",
  "properties": {
    "iso:country":"IT",
    "sg:address":"Via Milano 36 21010 Cardano Al Campo",
    "sg:city":"Cardano al Campo",
    "sg:orig_category":"Hoisiery Goods",
    "sg:phone":"+39 0331 261110",
    "sg:postcode":"21010",
    "sg:province":"Varese",
    "wof:name":"Confezioni Helen S.r.l.",
    "wof:placetype":"venue"
},
  "geometry": {"coordinates":[8.770771,45.635521],"type":"Point"}
}