{
  "type": "Feature",
  "properties": {
    "iso:country":"IT",
    "sg:address":"31, C. Del Popolo 30172 Mestre",
    "sg:classifiers":[
        {
            "category":"Parking",
            "subcategory":"Lot",
            "type":"Transportation"
        }
    ],
    "sg:phone":"+39 39041962084",
    "sg:postcode":"30172",
    "sg:province":"Venezia",
    "sg:tags":[
        "transport",
        "road"
    ],
    "sg:website":"http://www.paginegialle.it/traslochiexpress",
    "wof:name":"Traslochi Express",
    "wof:placetype":"venue"
},
  "geometry": {"coordinates":[12.244577,45.490189],"type":"Point"}
}