{
  "type": "Feature",
  "properties": {
    "iso:country":"IT",
    "sg:address":"25050 Provaglio D'iseo",
    "sg:orig_category":"Apparecchiature Ed Attrezzature Meccaniche",
    "sg:phone":"+39 030 983 0611",
    "sg:postcode":"25050",
    "sg:province":"Brescia",
    "sg:website":"http://www.omfb.it",
    "wof:name":"O.m.f.b. Spa Hydraulic Components",
    "wof:placetype":"venue"
},
  "geometry": {"coordinates":[10.033995,45.623707],"type":"Point"}
}