{
  "type": "Feature",
  "properties": {
    "iso:country":"IT",
    "sg:address":"25020 Flero",
    "sg:city":"Flero",
    "sg:orig_category":"Impiantistica E Prodotti Tecnologici Per Edilizia. Termotecnica E Riscaldamento, Apparecchiature E Servizi",
    "sg:phone":"+39 030 264 1191",
    "sg:postcode":"25020",
    "sg:province":"Brescia",
    "sg:website":"http://www.tubisteel.it",
    "wof:name":"Tubisteel Srl",
    "wof:placetype":"venue"
},
  "geometry": {"coordinates":[10.177958,45.47065],"type":"Point"}
}