{
  "type": "Feature",
  "properties": {
    "iso:country":"IT",
    "sg:address":"V. S. Lorenzo, 21; Alessandria; 15100",
    "sg:city":"Alessandria",
    "sg:classifiers":[
        {
            "category":"Shopping",
            "subcategory":"Computers & Home Electronics",
            "type":"Retail Goods"
        }
    ],
    "sg:phone":"+39 390 131 3131",
    "sg:postcode":"15100",
    "sg:province":"Alessandria",
    "sg:tags":[
        "chamber",
        "commerce"
    ],
    "sg:website":"www.al.camcom.it",
    "wof:name":"Alessandria Chamber Of Commerce & Industry",
    "wof:placetype":"venue"
},
  "geometry": {"coordinates":[8.614091,44.91304],"type":"Point"}
}