{
  "type": "Feature",
  "properties": {
    "iso:country":"IT",
    "sg:address":"26040 Martignana Di Po",
    "sg:city":"Martignana di Po",
    "sg:orig_category":"Coperture Edili E Tetti",
    "sg:phone":"+39 0375 263011",
    "sg:postcode":"26040",
    "sg:province":"Cremona",
    "sg:website":"http://www.grupposereni.it",
    "wof:name":"Laterizi Sereni Spa",
    "wof:placetype":"venue"
},
  "geometry": {"coordinates":[10.379208,45.007355],"type":"Point"}
}