{
  "type": "Feature",
  "properties": {
    "iso:country":"IT",
    "sg:address":"Via Europa 110 21015 Lonate Pozzolo",
    "sg:city":"Lonate Pozzolo",
    "sg:classifiers":[
        {
            "category":"Manufacturing",
            "subcategory":"Chemicals & Compounds",
            "type":"Manufacturing & Wholesale Goods"
        }
    ],
    "sg:phone":"+39 0331 301818",
    "sg:postcode":"21015",
    "sg:province":"Varese",
    "sg:tags":[
        "industry",
        "plant"
    ],
    "sg:website":"www.utenti.tripod.it/chemco/",
    "wof:name":"Chemco Srl",
    "wof:placetype":"venue"
},
  "geometry": {"coordinates":[8.7352571487,45.5892677307],"type":"Point"}
}