{
  "type": "Feature",
  "properties": {
    "iso:country":"IT",
    "sg:address":"20020 Solaro",
    "sg:city":"Solaro",
    "sg:orig_category":"Termotecnica E Riscaldamento, Apparecchiature E Servizi. Prodotti Vari In Metallo",
    "sg:phone":"+39 02 969 3383",
    "sg:postcode":"20020",
    "sg:province":"Milano",
    "wof:name":"Calor Service Srl",
    "wof:placetype":"venue"
},
  "geometry": {"coordinates":[9.219376,45.480286],"type":"Point"}
}