{
  "type": "Feature",
  "properties": {
    "addr:full":"20123 Milano Milano Milano 20123",
    "addr:postcode":"20123;20123",
    "iso:country":"IT",
    "sg:address":"20123 Milano",
    "sg:city":"Milano",
    "sg:orig_category":"Servizi E Lavori Per Edilizia E Lavori Pubblici. Banche E Servizi Finanziari",
    "sg:phone":"+39 02 7200 3003",
    "sg:postcode":"20123",
    "sg:province":"Milano",
    "wof:name":"Alban Cooper Italia Sviluppo",
    "wof:placetype":"venue"
},
  "geometry": {"coordinates":[9.174335,45.463634],"type":"Point"}
}