{
  "type": "Feature",
  "properties": {
    "iso:country":"IT",
    "sg:address":"Via Pontevecchio 55 16042 Carasco",
    "sg:city":"Carasco",
    "sg:orig_category":"Glycerin",
    "sg:phone":"+39 0185 35251",
    "sg:postcode":"16042",
    "sg:province":"Genova",
    "sg:website":"www.spiganord.it",
    "wof:name":"Spiga Nord Spa",
    "wof:placetype":"venue"
},
  "geometry": {"coordinates":[9.342564,44.348267],"type":"Point"}
}