{
  "type": "Feature",
  "properties": {
    "addr:full":"15100 Alessandria Alessandria Alessandria 15100",
    "addr:postcode":"15100;15100",
    "iso:country":"IT",
    "sg:address":"15100 Alessandria",
    "sg:city":"Alessandria",
    "sg:orig_category":"Apparecchiature Ed Attrezzature Meccaniche",
    "sg:postcode":"15100",
    "sg:province":"Alessandria",
    "wof:name":"Adelfia Chimica S.n.c.",
    "wof:placetype":"venue"
},
  "geometry": {"coordinates":[8.71055,44.910763],"type":"Point"}
}