{
  "type": "Feature",
  "properties": {
    "addr:full":"10123 Torino Torino Torino 10123",
    "addr:postcode":"10123;10123",
    "iso:country":"IT",
    "sg:address":"10123 Torino",
    "sg:city":"Torino",
    "sg:orig_category":"Macchine E Forniture Per Industria Orafa E Per Orologeria",
    "sg:phone":"+39 011 538730",
    "sg:postcode":"10123",
    "sg:province":"Torino",
    "wof:name":"Evor (s.n.c.)",
    "wof:placetype":"venue"
},
  "geometry": {"coordinates":[7.546341,45.001106],"type":"Point"}
}