{
  "type": "Feature",
  "properties": {
    "iso:country":"IT",
    "sg:address":"00166 Roma",
    "sg:city":"Roma",
    "sg:orig_category":"Automazione E Macchine Per Ufficio",
    "sg:phone":"+39 06 6155 0404",
    "sg:postcode":"00166",
    "sg:province":"Roma",
    "wof:name":"Assufficio Snc",
    "wof:placetype":"venue"
},
  "geometry": {"coordinates":[12.36832,41.918915],"type":"Point"}
}