{
  "type": "Feature",
  "properties": {
    "iso:country":"IT",
    "sg:address":"40129 Bologna",
    "sg:city":"Bologna",
    "sg:orig_category":"Servizi E Lavori Per Edilizia E Lavori Pubblici",
    "sg:phone":"+39 051 360862",
    "sg:postcode":"40129",
    "sg:province":"Bologna",
    "wof:name":"Zanetti Livio Srl",
    "wof:placetype":"venue"
},
  "geometry": {"coordinates":[11.339482,44.52161],"type":"Point"}
}