{
  "type": "Feature",
  "properties": {
    "addr:full":"91100 Trapani Trapani Trapani 91100",
    "addr:postcode":"91100;91100",
    "iso:country":"IT",
    "sg:address":"91100 Trapani",
    "sg:city":"Trapani",
    "sg:orig_category":"Forniture Per Edilizia E Lavori Pubblici",
    "sg:phone":"+39 0923 568360",
    "sg:postcode":"91100",
    "sg:province":"Trapani",
    "wof:name":"Arredil Srl",
    "wof:placetype":"venue"
},
  "geometry": {"coordinates":[12.5527505875,37.9160804749],"type":"Point"}
}