{
  "type": "Feature",
  "properties": {
    "iso:country":"IT",
    "sg:address":"20092 Cinisello Balsamo",
    "sg:city":"Cinisello Balsamo",
    "sg:orig_category":"Servizi Editoriali. Professionisti - Studi E Servizi Ed Associazioni Di Interesse Aziendale",
    "sg:phone":"+39 02 242 2371",
    "sg:postcode":"20092",
    "sg:province":"Milano",
    "wof:name":"Moneda Carlo",
    "wof:placetype":"venue"
},
  "geometry": {"coordinates":[9.232902,45.547131],"type":"Point"}
}