{
  "type": "Feature",
  "properties": {
    "addr:full":"28076 Pogno Pogno Novara 28076",
    "addr:postcode":"28076;28076",
    "iso:country":"IT",
    "sg:address":"28076 Pogno",
    "sg:city":"Pogno",
    "sg:orig_category":"Arredo Bagno Ed Idrosanitari. Idrosanitari E Accessori",
    "sg:phone":"+39 0322 97423",
    "sg:postcode":"28076",
    "sg:province":"Novara",
    "wof:name":"Gaboli Luigi & C. Snc",
    "wof:placetype":"venue"
},
  "geometry": {"coordinates":[8.383156,45.757168],"type":"Point"}
}