{
  "type": "Feature",
  "properties": {
    "iso:country":"IT",
    "sg:address":"Via Olmetto 5; Milan; 20123",
    "sg:classifiers":[
        {
            "category":"Travel",
            "subcategory":"Travel Agent",
            "type":"Entertainment"
        }
    ],
    "sg:phone":"+39 390 286 4521",
    "sg:postcode":"20123",
    "sg:province":"Milano",
    "sg:website":"www.europeatcost.com",
    "wof:name":"Europe At Cost, Ltd 'e.a.c.'",
    "wof:placetype":"venue"
},
  "geometry": {"coordinates":[9.185597,45.459797],"type":"Point"}
}