{
  "type": "Feature",
  "properties": {
    "iso:country":"IT",
    "sg:address":"38, Via Palu' 31020 San Vendemiano",
    "sg:city":"San Vendemiano",
    "sg:classifiers":[
        {
            "category":"Shopping",
            "subcategory":"Clothing, Apparel, & Fashions",
            "type":"Retail Goods"
        }
    ],
    "sg:phone":"+39 0438 777115",
    "sg:postcode":"31020",
    "sg:province":"Treviso",
    "sg:tags":[
        "clothes"
    ],
    "wof:name":"Margara Marco",
    "wof:placetype":"venue"
},
  "geometry": {"coordinates":[12.364076,45.875931],"type":"Point"}
}