{
  "type": "Feature",
  "properties": {
    "addr:full":"24020 Ranica Ranica Bergamo 24020",
    "addr:postcode":"24020;24020",
    "iso:country":"IT",
    "sg:address":"24020 Ranica",
    "sg:city":"Ranica",
    "sg:orig_category":"Servizi E Lavori Per Edilizia E Lavori Pubblici. Servizi E Lavori Per Ecologia E Smaltimento Rifiuti",
    "sg:phone":"+39 035 342 2828",
    "sg:postcode":"24020",
    "sg:province":"Bergamo",
    "sg:website":"http://www.paganirodolfo.it",
    "wof:name":"Pagani Rodolfo Srl",
    "wof:placetype":"venue"
},
  "geometry": {"coordinates":[9.716424,45.722588],"type":"Point"}
}