{
  "type": "Feature",
  "properties": {
    "iso:country":"IT",
    "sg:address":"00195 Roma",
    "sg:city":"Roma",
    "sg:orig_category":"Impiantistica E Prodotti Tecnologici Per Edilizia. Servizi Ausiliari Di Sorveglianza, Manutenzione E Pulizia",
    "sg:phone":"+39 06 370 1127",
    "sg:postcode":"00195",
    "sg:province":"Roma",
    "wof:name":"Ice Pan S.r.l.",
    "wof:placetype":"venue"
},
  "geometry": {"coordinates":[12.458121,41.918045],"type":"Point"}
}