{
  "type": "Feature",
  "properties": {
    "addr:full":"47023 Cesena Cesena Forl\u00ec-Cesena 47023",
    "addr:postcode":"47023;47023",
    "iso:country":"IT",
    "sg:address":"47023 Cesena",
    "sg:city":"Cesena",
    "sg:orig_category":"Arredo Bagno Ed Idrosanitari. Forniture Alle Strutture Ricettive. Apparecchi, Attrezzature E Forniture Per Centri Estetici",
    "sg:phone":"+39 0547 323644",
    "sg:postcode":"47023",
    "sg:province":"Forl\u00ec-Cesena",
    "wof:name":"Effegibi Italia Srl",
    "wof:placetype":"venue"
},
  "geometry": {"coordinates":[12.180778,44.059166],"type":"Point"}
}