{
  "type": "Feature",
  "properties": {
    "iso:country":"IT",
    "sg:address":"05100 Terni",
    "sg:city":"Terni",
    "sg:orig_category":"Climatizzazione E Condizionamento, Apparecchiature E Servizi. Accessori Dei Mezzi Di Trasporto",
    "sg:phone":"+39 0744 306591",
    "sg:postcode":"05100",
    "sg:province":"Terni",
    "wof:name":"Truck Service Srl",
    "wof:placetype":"venue"
},
  "geometry": {"coordinates":[12.601192,42.589951],"type":"Point"}
}