{
  "type": "Feature",
  "properties": {
    "iso:country":"IT",
    "sg:address":"20010 Cornaredo",
    "sg:city":"Cornaredo",
    "sg:orig_category":"Cine-foto-ottica. Articoli Medico-sanitari Ed Ortopedici. Impianti, Attrezzature E Forniture Sanitarie Ed Ospedaliere",
    "sg:phone":"+39 02 9356 9087",
    "sg:postcode":"20010",
    "sg:province":"Milano",
    "wof:name":"Ottica Devizzi Di Devizzi Francesco E C. Snc",
    "wof:placetype":"venue"
},
  "geometry": {"coordinates":[9.013348,45.488094],"type":"Point"}
}