{
  "type": "Feature",
  "properties": {
    "iso:country":"IT",
    "sg:address":"40057 Granarolo Emilia",
    "sg:classifiers":[
        {
            "category":"Utilities",
            "subcategory":"Refuse",
            "type":"Services"
        }
    ],
    "sg:phone":"+39 051 765666",
    "sg:postcode":"40057",
    "sg:province":"Bologna",
    "sg:tags":[
        "auxiliary",
        "disposal",
        "surveillance",
        "environmental",
        "protection",
        "cleaning",
        "maintenance",
        "works"
    ],
    "wof:name":"Se.am. Italia Srl",
    "wof:placetype":"venue"
},
  "geometry": {"coordinates":[11.395209,44.548065],"type":"Point"}
}