{
  "type": "Feature",
  "properties": {
    "iso:country":"IT",
    "sg:address":"20084 Lacchiarella",
    "sg:city":"Lacchiarella",
    "sg:orig_category":"Pubblica Amministrazione",
    "sg:phone":"+39 02 9007 6950",
    "sg:postcode":"20084",
    "sg:province":"Milano",
    "wof:name":"Provincia Di Milano",
    "wof:placetype":"venue"
},
  "geometry": {"coordinates":[9.0697307587,45.4178237915],"type":"Point"}
}