{
  "type": "Feature",
  "properties": {
    "iso:country":"IT",
    "sg:address":"22, Via Zanussi Lino 33033 Codroipo",
    "sg:city":"Codroipo",
    "sg:classifiers":[
        {
            "category":"Professional",
            "subcategory":"Engineering",
            "type":"Services"
        }
    ],
    "sg:phone":"+39 0432 907048",
    "sg:postcode":"33033",
    "sg:province":"Udine",
    "sg:tags":[
        "machine",
        "-",
        "mechanical"
    ],
    "wof:name":"Turco Franco & C. S.n.c.",
    "wof:placetype":"venue"
},
  "geometry": {"coordinates":[13.230724,46.064941],"type":"Point"}
}