{
  "type": "Feature",
  "properties": {
    "iso:country":"IT",
    "sg:address":"00199 Roma",
    "sg:city":"Roma",
    "sg:orig_category":"Macchine Utensili E Impianti",
    "sg:phone":"+39 06 8620 6812",
    "sg:postcode":"00199",
    "sg:province":"Roma",
    "wof:name":"Barigelli Pietro",
    "wof:placetype":"venue"
},
  "geometry": {"coordinates":[12.512455,41.928925],"type":"Point"}
}