{
  "type": "Feature",
  "properties": {
    "addr:full":"24064 Grumello Del Monte Grumello del Monte Bergamo 24064",
    "addr:postcode":"24064;24064",
    "iso:country":"IT",
    "sg:address":"24064 Grumello Del Monte",
    "sg:city":"Grumello del Monte",
    "sg:orig_category":"Cartotecnica E Servizi. Prodotti E Manufatti In Materie Plastiche. Articoli Per Imballaggio E Confezionamento",
    "sg:phone":"+39 035 830344",
    "sg:postcode":"24064",
    "sg:province":"Bergamo",
    "wof:name":"Jolly Plast Snc",
    "wof:placetype":"venue"
},
  "geometry": {"coordinates":[9.880617,45.637054],"type":"Point"}
}