{
  "type": "Feature",
  "properties": {
    "iso:country":"IT",
    "sg:address":"92019 Sciacca",
    "sg:city":"Sciacca",
    "sg:classifiers":[
        {
            "category":"Health Services",
            "subcategory":"Dentist",
            "type":"Services"
        }
    ],
    "sg:phone":"+39 0925 83297",
    "sg:postcode":"92019",
    "sg:province":"Agrigento",
    "sg:tags":[
        "hospital"
    ],
    "wof:name":"Agenzia Onoranze Funebri Gallo Ignazio",
    "wof:placetype":"venue"
},
  "geometry": {"coordinates":[13.05874,37.567631],"type":"Point"}
}