{
  "type": "Feature",
  "properties": {
    "iso:country":"IT",
    "sg:address":"28064 Sillavengo",
    "sg:city":"Sillavengo",
    "sg:orig_category":"Tessuti E Stoffe",
    "sg:phone":"+39 0321 824090",
    "sg:postcode":"28064",
    "sg:province":"Novara",
    "wof:name":"Elastica (s.n.c.)",
    "wof:placetype":"venue"
},
  "geometry": {"coordinates":[8.440185,45.517715],"type":"Point"}
}