{
  "type": "Feature",
  "properties": {
    "iso:country":"IT",
    "sg:address":"53048 Sinalunga",
    "sg:city":"Sinalunga",
    "sg:orig_category":"Aria Compressa - Impianti Ed Attrezzature",
    "sg:phone":"+39 0577 679978",
    "sg:postcode":"53048",
    "sg:province":"Siena",
    "wof:name":"Mugnai & Falciani",
    "wof:placetype":"venue"
},
  "geometry": {"coordinates":[11.748916,43.214779],"type":"Point"}
}