{
  "type": "Feature",
  "properties": {
    "iso:country":"IT",
    "sg:address":"48100 Villanova",
    "sg:orig_category":"Macchine, Impianti E Forniture Per Industria Grafica, Cartaria E Cartotecnica. Automazione E Macchine Per Ufficio",
    "sg:phone":"+39 0544 499255",
    "sg:postcode":"48100",
    "sg:province":"Ravenna",
    "wof:name":"Di Marino Alessandro",
    "wof:placetype":"venue"
},
  "geometry": {"coordinates":[12.116137,44.383305],"type":"Point"}
}