{
  "type": "Feature",
  "properties": {
    "iso:country":"IT",
    "sg:address":"206, Via Manin Daniele 31015 Conegliano",
    "sg:city":"Conegliano",
    "sg:classifiers":[
        {
            "category":"Autos & Motor Vehicles",
            "subcategory":"Automobile Sales",
            "type":"Retail Goods"
        }
    ],
    "sg:phone":"+39 39043862465",
    "sg:postcode":"31015",
    "sg:province":"Treviso",
    "sg:tags":[
        "equipment",
        "transport"
    ],
    "wof:name":"Barro Giovanni & Luigi (s.r.l.)",
    "wof:placetype":"venue"
},
  "geometry": {"coordinates":[12.242072,45.666286],"type":"Point"}
}