{
  "type": "Feature",
  "properties": {
    "iso:country":"IT",
    "sg:address":"119, Via Trento Trieste 41043 Formigine",
    "sg:city":"Formigine",
    "sg:classifiers":[
        {
            "category":"Shopping",
            "subcategory":"Clothing, Apparel, & Fashions",
            "type":"Retail Goods"
        }
    ],
    "sg:phone":"+39 39059573320",
    "sg:postcode":"41043",
    "sg:province":"Modena",
    "sg:tags":[
        "clothes"
    ],
    "wof:name":"Muratori (s.r.l.)",
    "wof:placetype":"venue"
},
  "geometry": {"coordinates":[10.848119,44.577595],"type":"Point"}
}