{
  "type": "Feature",
  "properties": {
    "iso:country":"IT",
    "sg:address":"84095 Giffoni Valle Piana",
    "sg:city":"Giffoni Valle Piana",
    "sg:orig_category":"Materassi - Vendita Al Dettaglio",
    "sg:phone":"+39 089 868706",
    "sg:postcode":"84095",
    "sg:province":"Salerno",
    "wof:name":"Valflex Snc Di Rinaldi Giuseppe & C.",
    "wof:placetype":"venue"
},
  "geometry": {"coordinates":[14.96225,40.761116],"type":"Point"}
}