{
  "type": "Feature",
  "properties": {
    "addr:full":"Via Stucchi 18 22075 Lurate Caccivio Lurate Caccivio Como 22075",
    "addr:housenumber":"18;caccivio",
    "addr:postcode":"22075;22075",
    "addr:street":"Via Stucchi;Caccivio",
    "iso:country":"IT",
    "sg:address":"Via Stucchi 18 22075 Lurate Caccivio",
    "sg:city":"Lurate Caccivio",
    "sg:classifiers":[
        {
            "category":"Shopping",
            "subcategory":"Crafts & Fabrics",
            "type":"Retail Goods"
        }
    ],
    "sg:phone":"+39 031 490022",
    "sg:postcode":"22075",
    "sg:province":"Como",
    "sg:tags":[
        "silk"
    ],
    "sg:website":"www.serikos.it",
    "wof:name":"Serikos Neckwear - S.r.l.",
    "wof:placetype":"venue"
},
  "geometry": {"coordinates":[9.00661,45.768272],"type":"Point"}
}