{
  "type": "Feature",
  "properties": {
    "iso:country":"IT",
    "sg:address":"20099 Sesto San Giovanni",
    "sg:city":"Sesto San Giovanni",
    "sg:classifiers":[
        {
            "category":"Health Services",
            "subcategory":"Health Practitioner",
            "type":"Services"
        }
    ],
    "sg:phone":"+39 02 240 9539",
    "sg:postcode":"20099",
    "sg:province":"Milano",
    "sg:tags":[
        "medici"
    ],
    "wof:name":"Ogliari Luigi",
    "wof:placetype":"venue"
},
  "geometry": {"coordinates":[9.2391605377,45.5353126526],"type":"Point"}
}