{
  "type": "Feature",
  "properties": {
    "addr:full":"09100 Cagliari CA",
    "addr:postcode":"09100",
    "iso:country":"IT",
    "sg:address":"09100 Cagliari",
    "sg:orig_category":"Pubblica Amministrazione",
    "sg:phone":"+39 070 240100",
    "sg:province":"CA",
    "wof:name":"Guardia Di Finanza",
    "wof:placetype":"venue"
},
  "geometry": {"coordinates":[9.0581302643,39.2526741028],"type":"Point"}
}