{
  "type": "Feature",
  "properties": {
    "addr:full":"80122 Napoli Napoli Napoli 80122",
    "addr:housenumber":"80122",
    "addr:postcode":"80122",
    "iso:country":"IT",
    "sg:address":"80122 Napoli",
    "sg:city":"Napoli",
    "sg:orig_category":"Non-classified Establishments",
    "sg:phone":"+39 081 246 1126",
    "sg:postcode":"80122",
    "sg:province":"Napoli",
    "wof:name":"La Casetta Di Tiziana Tesorone",
    "wof:placetype":"venue"
},
  "geometry": {"coordinates":[14.223865,40.834232],"type":"Point"}
}