{
  "type": "Feature",
  "properties": {
    "addr:full":"72100 Brindisi Brindisi Brindisi 72100",
    "addr:postcode":"72100;72100",
    "iso:country":"IT",
    "sg:address":"72100 Brindisi",
    "sg:city":"Brindisi",
    "sg:orig_category":"Lavorazioni Meccaniche E Servizi",
    "sg:phone":"+39 0831 452000",
    "sg:postcode":"72100",
    "sg:province":"Brindisi",
    "sg:website":"http://www.brindisiweb.com",
    "wof:name":"Cannone Teodoro Srl",
    "wof:placetype":"venue"
},
  "geometry": {"coordinates":[17.882084,40.612133],"type":"Point"}
}