{
  "type": "Feature",
  "properties": {
    "iso:country":"IT",
    "sg:address":"90018 Termini Imerese",
    "sg:city":"Termini Imerese",
    "sg:orig_category":"Materiali Edili",
    "sg:phone":"+39 091 811 2218",
    "sg:postcode":"90018",
    "sg:province":"Palermo",
    "wof:name":"Gessarte Di Emanuele Giordano",
    "wof:placetype":"venue"
},
  "geometry": {"coordinates":[13.702414,37.980206],"type":"Point"}
}