{
  "type": "Feature",
  "properties": {
    "iso:country":"IT",
    "sg:address":"00040 Pomezia",
    "sg:city":"Pomezia",
    "sg:orig_category":"Forniture Per Uffici. Arredi Ed Attrezzature Per Uffici. Automazione E Macchine Per Ufficio",
    "sg:phone":"+39 06 912 3222",
    "sg:postcode":"00040",
    "sg:province":"Roma",
    "wof:name":"Office System Srl",
    "wof:placetype":"venue"
},
  "geometry": {"coordinates":[12.4950590134,41.6904830933],"type":"Point"}
}