{
  "type": "Feature",
  "properties": {
    "addr:full":"24, Via G.di Vittorio 40020 Casalfiumanese Casalfiumanese Bologna 40020",
    "addr:postcode":"40020;40020",
    "addr:street":"Via G.Di Vittorio",
    "iso:country":"IT",
    "sg:address":"24, Via G.di Vittorio 40020 Casalfiumanese",
    "sg:city":"Casalfiumanese",
    "sg:classifiers":[
        {
            "category":"Shopping",
            "subcategory":"Crafts & Fabrics",
            "type":"Retail Goods"
        }
    ],
    "sg:phone":"+39 0542 664157",
    "sg:postcode":"40020",
    "sg:province":"Bologna",
    "sg:tags":[
        "ceramic"
    ],
    "wof:name":"Leonardo 1502 Ceramica S.p.a.",
    "wof:placetype":"venue"
},
  "geometry": {"coordinates":[11.346481,44.494221],"type":"Point"}
}