{
  "type": "Feature",
  "properties": {
    "iso:country":"IT",
    "sg:address":"110, V. Guelfa 50129 Firenze",
    "sg:city":"Firenze",
    "sg:classifiers":[
        {
            "category":"Professional",
            "subcategory":"Engineering",
            "type":"Services"
        }
    ],
    "sg:phone":"+39 39055489844",
    "sg:postcode":"50129",
    "sg:province":"Firenze",
    "sg:tags":[
        "machine",
        "-",
        "mechanical"
    ],
    "sg:website":"http://www.hotelmearini.com",
    "wof:name":"Hotel Mearini",
    "wof:placetype":"venue"
},
  "geometry": {"coordinates":[11.253626,43.778118],"type":"Point"}
}