{
  "type": "Feature",
  "properties": {
    "iso:country":"IT",
    "sg:address":"4, Via Calabria 56029 Santa Croce Sull'arno",
    "sg:classifiers":[
        {
            "category":"Manufacturing",
            "subcategory":"Textiles",
            "type":"Manufacturing & Wholesale Goods"
        }
    ],
    "sg:phone":"+39 0571 360836",
    "sg:postcode":"56029",
    "sg:province":"Pisa",
    "sg:tags":[
        "leather",
        "raw",
        "material",
        "-"
    ],
    "wof:name":"Masoni Industria Conciaria Spa",
    "wof:placetype":"venue"
},
  "geometry": {"coordinates":[10.764245,43.716183],"type":"Point"}
}