{
  "type": "Feature",
  "properties": {
    "iso:country":"IT",
    "sg:address":"20019 Settimo Milanese",
    "sg:city":"Settimo Milanese",
    "sg:orig_category":"Accessori Dei Mezzi Di Trasporto",
    "sg:phone":"+39 02 3350 1111",
    "sg:postcode":"20019",
    "sg:province":"Milano",
    "wof:name":"Eliocell Srl",
    "wof:placetype":"venue"
},
  "geometry": {"coordinates":[9.068621,45.467239],"type":"Point"}
}