{
  "type": "Feature",
  "properties": {
    "iso:country":"IT",
    "sg:address":"80053 Castellammare Di Stabia",
    "sg:city":"Castellammare di Stabia",
    "sg:orig_category":"Zootecnia E Pesca, Allevamento Piccoli Animali. Animali Domestici",
    "sg:phone":"+39 081 870 4437",
    "sg:postcode":"80053",
    "sg:province":"Napoli",
    "wof:name":"Esposito Catello",
    "wof:placetype":"venue"
},
  "geometry": {"coordinates":[14.486726,40.699387],"type":"Point"}
}