{
  "type": "Feature",
  "properties": {
    "iso:country":"IT",
    "sg:address":"10147 Torino",
    "sg:city":"Torino",
    "sg:orig_category":"Abbigliamento Intimo, Calze E Costumi Da Bagno. Sport - Articoli E Forniture. Shopping",
    "sg:phone":"+39 011 216 4193",
    "sg:postcode":"10147",
    "sg:province":"Torino",
    "wof:name":"Jantelle Di Cirigliano M. E C. (s.n.c.)",
    "wof:placetype":"venue"
},
  "geometry": {"coordinates":[7.67878,45.102512],"type":"Point"}
}