{
  "type": "Feature",
  "properties": {
    "iso:country":"IT",
    "sg:address":"Via Zona Industriale 66050 San Salvo",
    "sg:city":"San Salvo",
    "sg:classifiers":[
        {
            "category":"Manufacturing",
            "subcategory":"Glass & Minerals",
            "type":"Manufacturing & Wholesale Goods"
        }
    ],
    "sg:phone":"+39 390 873 5401",
    "sg:postcode":"66050",
    "sg:province":"Chieti",
    "wof:name":"Siv Societa' Italiana Vetro",
    "wof:placetype":"venue"
},
  "geometry": {"coordinates":[14.167151,42.351791],"type":"Point"}
}