{
  "type": "Feature",
  "properties": {
    "iso:country":"IT",
    "sg:address":"35010 Curtarolo",
    "sg:city":"Curtarolo",
    "sg:orig_category":"Servizi E Lavori Industria Chimica",
    "sg:phone":"+39 049 552469",
    "sg:postcode":"35010",
    "sg:province":"Padova",
    "wof:name":"Tecnover (s.a.s.)",
    "wof:placetype":"venue"
},
  "geometry": {"coordinates":[11.832399,45.522835],"type":"Point"}
}