{
  "type": "Feature",
  "properties": {
    "iso:country":"IT",
    "sg:address":"19, Corso P. Ferrero 12060 Farigliano",
    "sg:city":"Farigliano",
    "sg:classifiers":[
        {
            "category":"Shopping",
            "subcategory":"Clothing, Apparel, & Fashions",
            "type":"Retail Goods"
        }
    ],
    "sg:phone":"+39 39017376127",
    "sg:postcode":"12060",
    "sg:province":"Cuneo",
    "sg:tags":[
        "clothing",
        "accessory"
    ],
    "wof:name":"F.i.e.t.'s Di Quaranta Giorgio & C. (s.r.l.)",
    "wof:placetype":"venue"
},
  "geometry": {"coordinates":[7.547111,44.388798],"type":"Point"}
}