{
  "type": "Feature",
  "properties": {
    "iso:country":"IT",
    "sg:address":"24126 Bergamo",
    "sg:city":"Bergamo",
    "sg:orig_category":"Abbigliamento Alta Moda E Stilisti - Boutiques",
    "sg:phone":"+39 035 313531",
    "sg:postcode":"24126",
    "sg:province":"Bergamo",
    "wof:name":"Oberti Di Poli Gabriella & C. Snc",
    "wof:placetype":"venue"
},
  "geometry": {"coordinates":[9.661963,45.672466],"type":"Point"}
}