{
  "type": "Feature",
  "properties": {
    "iso:country":"IT",
    "sg:address":"84122 Salerno",
    "sg:city":"Salerno",
    "sg:orig_category":"Scuole E Servizi Scolastici",
    "sg:phone":"+39 089 231677",
    "sg:postcode":"84122",
    "sg:province":"Salerno",
    "wof:name":"50 Distretto Scolastico",
    "wof:placetype":"venue"
},
  "geometry": {"coordinates":[14.765949,40.678368],"type":"Point"}
}