{
  "type": "Feature",
  "properties": {
    "addr:full":"10138 Torino Torino Torino 10138",
    "addr:housenumber":"10138",
    "addr:postcode":"10138",
    "iso:country":"IT",
    "sg:address":"10138 Torino",
    "sg:city":"Torino",
    "sg:orig_category":"Informatica - Consulenza E Servizi. Editoria",
    "sg:phone":"+39 0114351",
    "sg:postcode":"10138",
    "sg:province":"Torino",
    "sg:website":"http://www.seat.it",
    "wof:name":"Seat Pagine Gialle Spa",
    "wof:placetype":"venue"
},
  "geometry": {"coordinates":[7.651598,45.0737],"type":"Point"}
}