{
  "type": "Feature",
  "properties": {
    "addr:full":"10151 Torino Torino Torino 10151",
    "addr:housenumber":"10151",
    "addr:postcode":"10151",
    "iso:country":"IT",
    "sg:address":"10151 Torino",
    "sg:city":"Torino",
    "sg:orig_category":"Escavatori E Draghe",
    "sg:phone":"+39 011 274 5217",
    "sg:postcode":"10151",
    "sg:province":"Torino",
    "wof:name":"Aldisi Super Trasporti Di Aldisi R.",
    "wof:placetype":"venue"
},
  "geometry": {"coordinates":[7.663383,45.104523],"type":"Point"}
}