{
  "type": "Feature",
  "properties": {
    "iso:country":"IT",
    "sg:address":"50125 Firenze",
    "sg:city":"Firenze",
    "sg:classifiers":[
        {
            "category":"Professional",
            "subcategory":"Printing & Photocopies",
            "type":"Services"
        }
    ],
    "sg:phone":"+39 055 223952",
    "sg:postcode":"50125",
    "sg:province":"Firenze",
    "sg:tags":[
        "packaging",
        "setting"
    ],
    "wof:name":"Legatoria Basilotta",
    "wof:placetype":"venue"
},
  "geometry": {"coordinates":[11.2445,43.765701],"type":"Point"}
}