{
  "type": "Feature",
  "properties": {
    "iso:country":"IT",
    "sg:address":"Strada Campagne' 12 13900 Biella",
    "sg:city":"Biella",
    "sg:classifiers":[
        {
            "category":"Insurance",
            "subcategory":"Insurance Agent",
            "type":"Services"
        }
    ],
    "sg:phone":"+39 015 403353",
    "sg:postcode":"13900",
    "sg:province":"Biella",
    "sg:tags":[
        "textile",
        "mediator"
    ],
    "wof:name":"Renato Gallo & Figli Sas",
    "wof:placetype":"venue"
},
  "geometry": {"coordinates":[8.040997,45.556629],"type":"Point"}
}