{
  "type": "Feature",
  "properties": {
    "addr:full":"6, Via Pr. S. Marco 25039 Travagliato Travagliato Brescia 25039",
    "addr:postcode":"25039;25039",
    "addr:street":"Via Pr.",
    "iso:country":"IT",
    "sg:address":"6, Via Pr. S. Marco 25039 Travagliato",
    "sg:city":"Travagliato",
    "sg:classifiers":[
        {
            "category":"Shopping",
            "subcategory":"Clothing, Apparel, & Fashions",
            "type":"Retail Goods"
        }
    ],
    "sg:phone":"+39 39030661122",
    "sg:postcode":"25039",
    "sg:province":"Brescia",
    "sg:tags":[
        "clothes"
    ],
    "wof:name":"Giacinto Diffusione (s.r.l.)",
    "wof:placetype":"venue"
},
  "geometry": {"coordinates":[10.222958,45.539829],"type":"Point"}
}