{
  "type": "Feature",
  "properties": {
    "addr:full":"20062 Groppello D'adda Milano 20062",
    "addr:postcode":"20062;20062",
    "addr:street":"D'Adda",
    "iso:country":"IT",
    "sg:address":"20062 Groppello D'adda",
    "sg:orig_category":"Prodotti Di Base E Forniture Per Industria Alimentare E Bevande",
    "sg:phone":"+39 036 360821",
    "sg:postcode":"20062",
    "sg:province":"Milano",
    "wof:name":"Motta Alberto E C. (s.n.c.)",
    "wof:placetype":"venue"
},
  "geometry": {"coordinates":[9.5035200119,45.5562438965],"type":"Point"}
}