{
  "type": "Feature",
  "properties": {
    "iso:country":"IT",
    "sg:address":"Piazza Roma, 23; Ascoli Piceno; 63100",
    "sg:city":"Ascoli Piceno",
    "sg:classifiers":[
        {
            "category":"Banks & Credit Unions",
            "subcategory":"Bank",
            "type":"Services"
        }
    ],
    "sg:phone":"+39 0736 250341",
    "sg:postcode":"63100",
    "sg:province":"Ascoli Piceno",
    "wof:name":"Banco Di Roma",
    "wof:placetype":"venue"
},
  "geometry": {"coordinates":[13.575425,42.853878],"type":"Point"}
}