{
  "type": "Feature",
  "properties": {
    "iso:country":"IT",
    "sg:address":"84010 Sant'egidio Del Monte Albino",
    "sg:orig_category":"Acciaierie E Fonderie",
    "sg:phone":"+39 081 954697",
    "sg:postcode":"84010",
    "sg:province":"Salerno",
    "wof:name":"Metal Fusion Srl",
    "wof:placetype":"venue"
},
  "geometry": {"coordinates":[14.595346,40.750977],"type":"Point"}
}