{
  "type": "Feature",
  "properties": {
    "iso:country":"IT",
    "sg:address":"20095 Cusano Milanino",
    "sg:city":"Cusano Milanino",
    "sg:orig_category":"Forniture Per Attivita' Industriali",
    "sg:phone":"+39 02 619 3626",
    "sg:postcode":"20095",
    "sg:province":"Milano",
    "wof:name":"Isopren Srl",
    "wof:placetype":"venue"
},
  "geometry": {"coordinates":[9.1845636368,45.5467681885],"type":"Point"}
}