{
  "type": "Feature",
  "properties": {
    "addr:full":"80040 Massa Di Somma Massa di Somma Napoli 80040",
    "addr:postcode":"80040;80040",
    "iso:country":"IT",
    "sg:address":"80040 Massa Di Somma",
    "sg:city":"Massa di Somma",
    "sg:orig_category":"Materiali Edili",
    "sg:phone":"+39 081 771 6273",
    "sg:postcode":"80040",
    "sg:province":"Napoli",
    "wof:name":"Co.man. Sas",
    "wof:placetype":"venue"
},
  "geometry": {"coordinates":[14.379858,40.843033],"type":"Point"}
}