{
  "type": "Feature",
  "properties": {
    "iso:country":"IT",
    "sg:address":"40128 Bologna",
    "sg:city":"Bologna",
    "sg:orig_category":"Non-classified Establishments",
    "sg:phone":"+39 051 371001",
    "sg:postcode":"40128",
    "sg:province":"Bologna",
    "wof:name":"Elettromania S.n.c.",
    "wof:placetype":"venue"
},
  "geometry": {"coordinates":[11.351348,44.510891],"type":"Point"}
}