{
  "type": "Feature",
  "properties": {
    "iso:country":"IT",
    "sg:address":"30, Via Ca' Morosin 36061 Bassano Del Grappa",
    "sg:city":"Bassano del Grappa",
    "sg:classifiers":[
        {
            "category":"Manufacturing",
            "subcategory":"Textiles",
            "type":"Manufacturing & Wholesale Goods"
        }
    ],
    "sg:phone":"+39 0424 501717",
    "sg:postcode":"36061",
    "sg:province":"Vicenza",
    "sg:tags":[
        "leather",
        "raw",
        "material",
        "-"
    ],
    "wof:name":"Conceria Zonta (s.p.a.)",
    "wof:placetype":"venue"
},
  "geometry": {"coordinates":[11.540307,45.545906],"type":"Point"}
}