{
  "type": "Feature",
  "properties": {
    "iso:country":"IT",
    "sg:address":"21100 Varese",
    "sg:city":"Varese",
    "sg:classifiers":[
        {
            "category":"Health Services",
            "subcategory":"Health Practitioner",
            "type":"Services"
        }
    ],
    "sg:phone":"+39 0332 286563",
    "sg:postcode":"21100",
    "sg:province":"Varese",
    "sg:tags":[
        "medici"
    ],
    "wof:name":"Rizzi Alberto",
    "wof:placetype":"venue"
},
  "geometry": {"coordinates":[8.8185167313,45.8208808899],"type":"Point"}
}