{
  "type": "Feature",
  "properties": {
    "iso:country":"IT",
    "sg:address":"64028 Silvi",
    "sg:city":"Silvi",
    "sg:orig_category":"Alberghi",
    "sg:phone":"+39 085 935 0989",
    "sg:postcode":"64028",
    "sg:province":"Teramo",
    "sg:website":"http://www.parcodellerose.it",
    "wof:name":"Hotel Parco Delle Rose",
    "wof:placetype":"venue"
},
  "geometry": {"coordinates":[14.113645,42.55714],"type":"Point"}
}