{
  "type": "Feature",
  "properties": {
    "iso:country":"IT",
    "sg:address":"34018 San Dorligo Valle",
    "sg:orig_category":"Impianti Elettrici Industriali E Civili - Installazione E Manutenzione",
    "sg:phone":"+39 040 830448",
    "sg:postcode":"34018",
    "sg:province":"Trieste",
    "sg:website":"http://www.essebiimpianti.it",
    "wof:name":"Essebi Impianti & Servizi",
    "wof:placetype":"venue"
},
  "geometry": {"coordinates":[13.844191,45.604942],"type":"Point"}
}