{
  "type": "Feature",
  "properties": {
    "addr:full":"65129 Pescara Pescara Pescara 65129",
    "addr:postcode":"65129;65129",
    "iso:country":"IT",
    "sg:address":"65129 Pescara",
    "sg:city":"Pescara",
    "sg:orig_category":"Centri Di Estetica E Cosmesi E Servizi",
    "sg:phone":"+39 085 63811",
    "sg:postcode":"65129",
    "sg:province":"Pescara",
    "sg:website":"http://www.bisun.it",
    "wof:name":"Bi' Sun Di Valeria Capozucco & C. Sas",
    "wof:placetype":"venue"
},
  "geometry": {"coordinates":[14.246178,42.449802],"type":"Point"}
}