{
  "type": "Feature",
  "properties": {
    "addr:full":"20145 Milano Milano Milano 20145",
    "addr:postcode":"20145;20145",
    "iso:country":"IT",
    "sg:address":"20145 Milano",
    "sg:city":"Milano",
    "sg:orig_category":"Servizi Per Aziende, Manifestazioni E Supporto Agli Scambi Commerciali",
    "sg:phone":"+39 02 435041",
    "sg:postcode":"20145",
    "sg:province":"Milano",
    "sg:website":"http://www.aaginternational.com",
    "wof:name":"A.a.g. Events Management",
    "wof:placetype":"venue"
},
  "geometry": {"coordinates":[9.155647,45.469814],"type":"Point"}
}