{
  "type": "Feature",
  "properties": {
    "iso:country":"IT",
    "sg:address":"20050 Lesmo",
    "sg:city":"Lesmo",
    "sg:orig_category":"Termotecnica E Riscaldamento, Apparecchiature E Servizi",
    "sg:phone":"+39 039 606 4540",
    "sg:postcode":"20050",
    "sg:province":"Milano",
    "wof:name":"S.a.m.i.a. (s.r.l.)",
    "wof:placetype":"venue"
},
  "geometry": {"coordinates":[9.306628,45.650002],"type":"Point"}
}