{
  "type": "Feature",
  "properties": {
    "iso:country":"IT",
    "sg:address":"40128 Bologna",
    "sg:city":"Bologna",
    "sg:orig_category":"Servizi E Lavori Per Agricoltura E Zootecnia",
    "sg:phone":"+39 051 320034",
    "sg:postcode":"40128",
    "sg:province":"Bologna",
    "wof:name":"Bortolotti Dino",
    "wof:placetype":"venue"
},
  "geometry": {"coordinates":[11.357116,44.545399],"type":"Point"}
}