{
  "type": "Feature",
  "properties": {
    "iso:country":"IT",
    "sg:address":"Corso Risorgimento 44; Novara; 28100",
    "sg:city":"Novara",
    "sg:classifiers":[
        {
            "category":"Banks & Credit Unions",
            "subcategory":"Bank",
            "type":"Services"
        }
    ],
    "sg:phone":"+39 0321 621681",
    "sg:postcode":"28100",
    "sg:province":"Novara",
    "wof:name":"Banco Ambrosiano Veneto Spa",
    "wof:placetype":"venue"
},
  "geometry": {"coordinates":[8.61729,45.457848],"type":"Point"}
}