{
  "type": "Feature",
  "properties": {
    "iso:country":"IT",
    "sg:address":"20158 Milano",
    "sg:city":"Milano",
    "sg:classifiers":[
        {
            "category":"Health Services",
            "subcategory":"Health Practitioner",
            "type":"Services"
        }
    ],
    "sg:phone":"+39 02 683351",
    "sg:postcode":"20158",
    "sg:province":"Milano",
    "sg:tags":[
        "medici"
    ],
    "wof:name":"Cocchiara Guido",
    "wof:placetype":"venue"
},
  "geometry": {"coordinates":[9.19005,45.463478],"type":"Point"}
}