{
  "type": "Feature",
  "properties": {
    "iso:country":"IT",
    "sg:address":"58, Via Laurin 39012 Merano",
    "sg:city":"Merano",
    "sg:classifiers":[
        {
            "category":"Travel",
            "subcategory":"Travel Agent",
            "type":"Entertainment"
        }
    ],
    "sg:phone":"+39 0473 448800",
    "sg:postcode":"39012",
    "sg:province":"Bolzano/Bozen",
    "sg:tags":[
        "business"
    ],
    "wof:name":"Hotel Steiner",
    "wof:placetype":"venue"
},
  "geometry": {"coordinates":[11.146877,46.682796],"type":"Point"}
}