{
  "type": "Feature",
  "properties": {
    "iso:country":"IT",
    "sg:address":"00151 Roma",
    "sg:city":"Roma",
    "sg:orig_category":"Macchine, Impianti E Forniture Per Industria Grafica, Cartaria E Cartotecnica. Automazione E Macchine Per Ufficio",
    "sg:phone":"+39 06 6574 0041",
    "sg:postcode":"00151",
    "sg:province":"Roma",
    "wof:name":"Tektronic Srl",
    "wof:placetype":"venue"
},
  "geometry": {"coordinates":[12.443478,41.863106],"type":"Point"}
}