{
  "type": "Feature",
  "properties": {
    "addr:full":"20094 Corsico Corsico Milano 20094",
    "addr:postcode":"20094;20094",
    "iso:country":"IT",
    "sg:address":"20094 Corsico",
    "sg:city":"Corsico",
    "sg:orig_category":"Arredamento Uffici",
    "sg:phone":"+39 02 447 3117",
    "sg:postcode":"20094",
    "sg:province":"Milano",
    "wof:name":"Bmc Di Malandra Carlo",
    "wof:placetype":"venue"
},
  "geometry": {"coordinates":[9.116712,45.432594],"type":"Point"}
}