{
  "type": "Feature",
  "properties": {
    "addr:full":"via Mario Idiomi 3/17 Assago 20090",
    "addr:housenumber":"3 / 17",
    "addr:postcode":"20090",
    "addr:street":"Via Mario Idiomi;Assago",
    "iso:country":"IT",
    "sg:address":"via Mario Idiomi 3/17",
    "sg:city":"Assago",
    "sg:classifiers":[
        {
            "category":"Manufacturing",
            "subcategory":"Electronics",
            "type":"Manufacturing & Wholesale Goods"
        }
    ],
    "sg:postcode":"20090",
    "sg:tags":[
        "graphic-arts",
        "service",
        "ctp",
        "consumables",
        "proofing",
        "drop-on-demand"
    ],
    "sg:website":"http://www.esagrafica.com",
    "wof:name":"Esagrafica Service Solutions",
    "wof:placetype":"venue"
},
  "geometry": {"coordinates":[9.126291,45.409118],"type":"Point"}
}