{
  "type": "Feature",
  "properties": {
    "iso:country":"IT",
    "sg:address":"Via Capitello 10 33087 Pasiano Di Pordenone",
    "sg:city":"Pasiano",
    "sg:classifiers":[
        {
            "category":"Bars & Pubs",
            "subcategory":"Sports Bar",
            "type":"Food & Drink"
        }
    ],
    "sg:phone":"+39 0434 628183",
    "sg:postcode":"33087",
    "sg:province":"Pordenone",
    "sg:tags":[
        "dy",
        "forging"
    ],
    "sg:website":"www.tolomeo.it/eurostampi",
    "wof:name":"Eurostampi Di Moras Gabriella E C. Sas",
    "wof:placetype":"venue"
},
  "geometry": {"coordinates":[12.6163434982,45.8442764282],"type":"Point"}
}