{
  "type": "Feature",
  "properties": {
    "iso:country":"IT",
    "sg:address":"95011 Calatabiano",
    "sg:city":"Calatabiano",
    "sg:orig_category":"Arredo Urbano",
    "sg:phone":"+39 095 649351",
    "sg:postcode":"95011",
    "sg:province":"Catania",
    "wof:name":"Etna Garden Di Caudo M. Aurelio",
    "wof:placetype":"venue"
},
  "geometry": {"coordinates":[15.20778,37.81662],"type":"Point"}
}