{
  "type": "Feature",
  "properties": {
    "iso:country":"IT",
    "sg:address":"16161 Genova",
    "sg:city":"Genova",
    "sg:orig_category":"Servizi E Lavori Per Edilizia E Lavori Pubblici. Acqua, Luce, Gas E Societa' Di Esercizio Pubblico",
    "sg:phone":"+39 010 740 7342",
    "sg:postcode":"16161",
    "sg:province":"Genova",
    "wof:name":"Acquedotto Nicolay (s.p.a.)",
    "wof:placetype":"venue"
},
  "geometry": {"coordinates":[8.904123,44.456394],"type":"Point"}
}