{
  "type": "Feature",
  "properties": {
    "iso:country":"IT",
    "sg:address":"23875 Osnago",
    "sg:city":"Osnago",
    "sg:orig_category":"Impiantistica E Prodotti Tecnologici Per Edilizia. Climatizzazione E Condizionamento, Apparecchiature E Servizi",
    "sg:phone":"+39 039 928 0111",
    "sg:postcode":"23875",
    "sg:province":"Lecco",
    "sg:website":"http://www.klima2000.it",
    "wof:name":"Klima 2000 Srl",
    "wof:placetype":"venue"
},
  "geometry": {"coordinates":[9.400135,45.69257],"type":"Point"}
}