{
  "type": "Feature",
  "properties": {
    "iso:country":"IT",
    "sg:address":"115, Corso Allamano Canonico Giuseppe 10098 Rivoli",
    "sg:city":"Rivoli",
    "sg:classifiers":[
        {
            "category":"Parking",
            "subcategory":"Lot",
            "type":"Transportation"
        }
    ],
    "sg:phone":"+39 011 958 8320",
    "sg:postcode":"10098",
    "sg:province":"Torino",
    "sg:tags":[
        "transport",
        "road"
    ],
    "wof:name":"Cotrama Arts Cooperativa S.r.l.",
    "wof:placetype":"venue"
},
  "geometry": {"coordinates":[7.587491,45.05204],"type":"Point"}
}