{
  "type": "Feature",
  "properties": {
    "iso:country":"IT",
    "sg:address":"Via Roma 186, 38081 Breguzzo, Tn",
    "sg:city":"Breguzzo",
    "sg:classifiers":[
        {
            "category":"Banks & Credit Unions",
            "subcategory":"Bank",
            "type":"Services"
        }
    ],
    "sg:postcode":"38081",
    "sg:province":"Trento",
    "wof:name":"Cassa Rurale Di Bondo Breguzzo E Roncone-banca Di Credito Cooperativo Scarl",
    "wof:placetype":"venue"
},
  "geometry": {"coordinates":[10.696451,46.005104],"type":"Point"}
}