{
  "type": "Feature",
  "properties": {
    "addr:full":"10, Via Torquato Tasso 24020 Gorle Gorle Bergamo 24020",
    "addr:postcode":"24020;24020",
    "addr:street":"Via Torquato Tasso",
    "iso:country":"IT",
    "sg:address":"10, Via Torquato Tasso 24020 Gorle",
    "sg:city":"Gorle",
    "sg:classifiers":[
        {
            "category":"Manufacturing",
            "subcategory":"Printing",
            "type":"Manufacturing & Wholesale Goods"
        }
    ],
    "sg:phone":"+39 39035664245",
    "sg:postcode":"24020",
    "sg:province":"Bergamo",
    "sg:tags":[
        "publishing"
    ],
    "wof:name":"Editrice Velar S.p.a.",
    "wof:placetype":"venue"
},
  "geometry": {"coordinates":[9.7092580795,45.7063484192],"type":"Point"}
}