{
  "type": "Feature",
  "properties": {
    "addr:full":"Via Fossato 35 25075 Nave Nave Brescia 25075",
    "addr:housenumber":"35",
    "addr:postcode":"25075;25075",
    "addr:street":"Via Fossato",
    "iso:country":"IT",
    "sg:address":"Via Fossato 35 25075 Nave",
    "sg:city":"Nave",
    "sg:classifiers":[
        {
            "category":"Wholesale",
            "subcategory":"Construction Materials",
            "type":"Manufacturing & Wholesale Goods"
        }
    ],
    "sg:phone":"+39 030 253 0100",
    "sg:postcode":"25075",
    "sg:province":"Brescia",
    "sg:tags":[
        "formwork",
        "system",
        "element"
    ],
    "sg:website":"www.ilpalegno.com",
    "wof:name":"Ilpa Srl",
    "wof:placetype":"venue"
},
  "geometry": {"coordinates":[10.282418251,45.5879592896],"type":"Point"}
}