{
  "type": "Feature",
  "properties": {
    "iso:country":"IT",
    "sg:address":"31050 Ponzano Veneto",
    "sg:city":"Ponzano Veneto",
    "sg:orig_category":"Cancelli, Porte E Portoni Automatici E Telecomandati",
    "sg:phone":"+39 0422 440734",
    "sg:postcode":"31050",
    "sg:province":"Treviso",
    "wof:name":"Tiveron Serramenti Srl",
    "wof:placetype":"venue"
},
  "geometry": {"coordinates":[12.211783,45.710754],"type":"Point"}
}