{
  "type": "Feature",
  "properties": {
    "addr:full":"23, Via Pisacane Carlo 10042 Nichelino Nichelino Torino 10042",
    "addr:postcode":"10042;10042",
    "addr:street":"Via Pisacane Carlo",
    "iso:country":"IT",
    "sg:address":"23, Via Pisacane Carlo 10042 Nichelino",
    "sg:city":"Nichelino",
    "sg:classifiers":[
        {
            "category":"Food & Beverages",
            "subcategory":"Bakery",
            "type":"Retail Goods"
        }
    ],
    "sg:phone":"+39 011 627 9775",
    "sg:postcode":"10042",
    "sg:province":"Torino",
    "sg:tags":[
        "grain",
        "cereal"
    ],
    "wof:name":"Equilibra Srl",
    "wof:placetype":"venue"
},
  "geometry": {"coordinates":[7.655343,45.013432],"type":"Point"}
}