{
  "type": "Feature",
  "properties": {
    "iso:country":"IT",
    "sg:address":"33048 San Giovanni Al Natisone",
    "sg:city":"San Giovanni al Natisone",
    "sg:orig_category":"Arredamenti E Mobili Professionali. Forniture Alle Strutture Ricettive",
    "sg:phone":"+39 0432 747511",
    "sg:postcode":"33048",
    "sg:province":"Udine",
    "sg:website":"http://www.lisa.it",
    "wof:name":"L.i.s.a. Spa",
    "wof:placetype":"venue"
},
  "geometry": {"coordinates":[13.422132,45.970116],"type":"Point"}
}