{
  "type": "Feature",
  "properties": {
    "iso:country":"IT",
    "sg:address":"20098 San Giuliano Milanese",
    "sg:city":"San Giuliano Milanese",
    "sg:orig_category":"Elettrotecnica Industriale, Prodotti E Apparecchiature. Ricambi E Componenti Dei Mezzi Di Trasporto",
    "sg:phone":"+39 02 988 0287",
    "sg:postcode":"20098",
    "sg:province":"Milano",
    "sg:website":"http://www.tecnid.it",
    "wof:name":"Tecnid Spa",
    "wof:placetype":"venue"
},
  "geometry": {"coordinates":[9.25342,45.397518],"type":"Point"}
}