{
  "type": "Feature",
  "properties": {
    "addr:full":"Via Adamello 37 20020 Lazzate Lazzate Milano 20020",
    "addr:housenumber":"37",
    "addr:postcode":"20020;20020",
    "addr:street":"Via Adamello",
    "iso:country":"IT",
    "sg:address":"Via Adamello 37 20020 Lazzate",
    "sg:city":"Lazzate",
    "sg:classifiers":[
        {
            "category":"Home & Garden",
            "subcategory":"Carpets & Floor Coverings",
            "type":"Retail Goods"
        }
    ],
    "sg:phone":"+39 02 9632 8188",
    "sg:postcode":"20020",
    "sg:province":"Milano",
    "sg:tags":[
        "flooring",
        "parquet"
    ],
    "sg:website":"www.caimispa.com",
    "wof:name":"Caimi Spa",
    "wof:placetype":"venue"
},
  "geometry": {"coordinates":[9.0718803406,45.6698570251],"type":"Point"}
}