{
  "type": "Feature",
  "properties": {
    "addr:full":"35122 Padova Padova Padova 35122",
    "addr:postcode":"35122;35122",
    "iso:country":"IT",
    "sg:address":"35122 Padova",
    "sg:city":"Padova",
    "sg:orig_category":"Filati E Materie Prime Tessili",
    "sg:phone":"+39 049 656655",
    "sg:postcode":"35122",
    "sg:province":"Padova",
    "wof:name":"M.t. Filati",
    "wof:placetype":"venue"
},
  "geometry": {"coordinates":[11.9126281738,45.3184661865],"type":"Point"}
}