{
  "type": "Feature",
  "properties": {
    "iso:country":"IT",
    "sg:address":"20155 Milano",
    "sg:city":"Milano",
    "sg:orig_category":"Articoli Da Regalo. Regalistica Aziendale",
    "sg:phone":"+39 02 345 0078",
    "sg:postcode":"20155",
    "sg:province":"Milano",
    "wof:name":"Lubinski Srl",
    "wof:placetype":"venue"
},
  "geometry": {"coordinates":[9.164156,45.491085],"type":"Point"}
}