{
  "type": "Feature",
  "properties": {
    "addr:full":"Viale Della Liberazione 16/18; Milano; 20124 Milano Milano 20124",
    "addr:housenumber":"16 / 18",
    "addr:postcode":"20124;20124",
    "addr:street":"Viale Della Liberazione",
    "iso:country":"IT",
    "sg:address":"Viale Della Liberazione 16/18; Milano; 20124",
    "sg:city":"Milano",
    "sg:classifiers":[
        {
            "category":"Banks & Credit Unions",
            "subcategory":"Bank",
            "type":"Services"
        }
    ],
    "sg:phone":"+39 02 656391",
    "sg:postcode":"20124",
    "sg:province":"Milano",
    "wof:name":"Bank Of Tokyo Ltd",
    "wof:placetype":"venue"
},
  "geometry": {"coordinates":[9.195287,45.482346],"type":"Point"}
}