{
  "type": "Feature",
  "properties": {
    "addr:full":"25, Via Europa 46047 Porto Mantovano Porto Mantovano Mantova 46047",
    "addr:postcode":"46047;46047",
    "addr:street":"Via Europa",
    "iso:country":"IT",
    "sg:address":"25, Via Europa 46047 Porto Mantovano",
    "sg:city":"Porto Mantovano",
    "sg:classifiers":[
        {
            "category":"Manufacturing",
            "subcategory":"Food",
            "type":"Manufacturing & Wholesale Goods"
        }
    ],
    "sg:phone":"+39 0376 389311",
    "sg:postcode":"46047",
    "sg:province":"Mantova",
    "sg:tags":[
        "equipment",
        "processing",
        "-",
        "machinery"
    ],
    "wof:name":"P.e. S.r.l.",
    "wof:placetype":"venue"
},
  "geometry": {"coordinates":[10.7681217194,45.197845459],"type":"Point"}
}