{
  "type": "Feature",
  "properties": {
    "addr:full":"19038 Sarzana Sarzana La Spezia 19038",
    "addr:postcode":"19038;19038",
    "iso:country":"IT",
    "sg:address":"19038 Sarzana",
    "sg:city":"Sarzana",
    "sg:orig_category":"Mobili - Produzione E Ingrosso",
    "sg:phone":"+39 330 797 233",
    "sg:postcode":"19038",
    "sg:province":"La Spezia",
    "wof:name":"Bonello Jose Maria",
    "wof:placetype":"venue"
},
  "geometry": {"coordinates":[9.7678689957,44.2447929382],"type":"Point"}
}