{
  "type": "Feature",
  "properties": {
    "iso:country":"IT",
    "sg:address":"180, Corso Milano 28883 Gravellona Toce",
    "sg:city":"Gravellona Toce",
    "sg:classifiers":[
        {
            "category":"Utilities",
            "subcategory":"Electric",
            "type":"Services"
        }
    ],
    "sg:phone":"+39 0323 869311",
    "sg:postcode":"28883",
    "sg:province":"Verbano-Cusio-Ossola",
    "sg:tags":[
        "component",
        "electronic"
    ],
    "wof:name":"Mectronic S.r.l.",
    "wof:placetype":"venue"
},
  "geometry": {"coordinates":[8.444387,45.924023],"type":"Point"}
}