{
  "type": "Feature",
  "properties": {
    "iso:country":"IT",
    "sg:address":"20154 Milano",
    "sg:city":"Milano",
    "sg:orig_category":"Autolavaggio",
    "sg:phone":"+39 02 331 5837",
    "sg:postcode":"20154",
    "sg:province":"Milano",
    "wof:name":"Motor D.a.t.a. Srl",
    "wof:placetype":"venue"
},
  "geometry": {"coordinates":[9.168324,45.488689],"type":"Point"}
}