{
  "type": "Feature",
  "properties": {
    "iso:country":"IT",
    "sg:address":"Via Nazionale 7, 38070 Padergnone, Tn",
    "sg:city":"Padergnone",
    "sg:classifiers":[
        {
            "category":"Banks & Credit Unions",
            "subcategory":"Bank",
            "type":"Services"
        }
    ],
    "sg:postcode":"38070",
    "sg:province":"Trento",
    "wof:name":"Cassa Rurale Della Valle Dei Laghi-banca Di Credito Cooperativo Scarl",
    "wof:placetype":"venue"
},
  "geometry": {"coordinates":[10.990379,46.060257],"type":"Point"}
}