{
  "type": "Feature",
  "properties": {
    "iso:country":"IT",
    "sg:address":"Via Garzoli 17; Lainate",
    "sg:classifiers":[
        {
            "category":"Banks & Credit Unions",
            "subcategory":"Bank",
            "type":"Services"
        }
    ],
    "sg:phone":"+39 02 937 3581",
    "wof:name":"Banca Popolare Commercio, E Industria Scarl",
    "wof:placetype":"venue"
},
  "geometry": {"coordinates":[9.027191,45.570534],"type":"Point"}
}