{
  "type": "Feature",
  "properties": {
    "iso:country":"IT",
    "sg:address":"06121 Perugia",
    "sg:city":"Perugia",
    "sg:orig_category":"Universita' Ed Istituti Superiori E Liberi",
    "sg:phone":"+39 075 572 7100",
    "sg:postcode":"06121",
    "sg:province":"Perugia",
    "wof:name":"Cepu Srl",
    "wof:placetype":"venue"
},
  "geometry": {"coordinates":[12.389453,43.108696],"type":"Point"}
}