{
  "type": "Feature",
  "properties": {
    "iso:country":"IT",
    "sg:address":"28, Via Mario Asso 21044 Cavaria Con Premezzo",
    "sg:city":"Cavaria con Premezzo",
    "sg:classifiers":[
        {
            "category":"Shopping",
            "subcategory":"Clothing, Apparel, & Fashions",
            "type":"Retail Goods"
        }
    ],
    "sg:phone":"+39 0331 217119",
    "sg:postcode":"21044",
    "sg:province":"Varese",
    "sg:tags":[
        "clothes"
    ],
    "wof:name":"B.i.a.m. Di Broggini Claudio & C. (s.n.c.)",
    "wof:placetype":"venue"
},
  "geometry": {"coordinates":[8.826385,45.817604],"type":"Point"}
}