{
  "type": "Feature",
  "properties": {
    "iso:country":"IT",
    "sg:address":"37010 Albare'",
    "sg:orig_category":"Macchine, Impianti Ed Attrezzature Per Agricoltura E Zootecnia",
    "sg:phone":"+39 045 720 0888",
    "sg:postcode":"37010",
    "sg:province":"Verona",
    "wof:name":"Sita Societa' Installazioni Tecnologie Agricole (s.r.l.)",
    "wof:placetype":"venue"
},
  "geometry": {"coordinates":[10.991748,45.438366],"type":"Point"}
}