{
  "type": "Feature",
  "properties": {
    "iso:country":"IT",
    "sg:address":"00156 Roma",
    "sg:city":"Roma",
    "sg:orig_category":"Bricolage E Fai Da Te",
    "sg:phone":"+39 06 411 5715",
    "sg:postcode":"00156",
    "sg:province":"Roma",
    "sg:website":"http://www.areacom.it/biz/superlegno",
    "wof:name":"Superlegno Srl",
    "wof:placetype":"venue"
},
  "geometry": {"coordinates":[12.581442,41.941071],"type":"Point"}
}