{
  "type": "Feature",
  "properties": {
    "iso:country":"IT",
    "sg:address":"89822 Serra San Bruno",
    "sg:city":"Serra San Bruno",
    "sg:orig_category":"Prodotti Chimici Secondari",
    "sg:phone":"+39 0963 72065",
    "sg:postcode":"89822",
    "sg:province":"Vibo Valentia",
    "wof:name":"Sudesplosivi S.a.s.",
    "wof:placetype":"venue"
},
  "geometry": {"coordinates":[16.3308639526,38.5780258179],"type":"Point"}
}