{
  "type": "Feature",
  "properties": {
    "addr:full":"23842 Bosisio Parini Bosisio Parini Lecco 23842",
    "addr:postcode":"23842;23842",
    "iso:country":"IT",
    "sg:address":"23842 Bosisio Parini",
    "sg:city":"Bosisio Parini",
    "sg:orig_category":"Materiali Semilavorati Metallici",
    "sg:phone":"+39 031 865430",
    "sg:postcode":"23842",
    "sg:province":"Lecco",
    "wof:name":"Rigamonti Fratelli",
    "wof:placetype":"venue"
},
  "geometry": {"coordinates":[9.268275,45.814686],"type":"Point"}
}