{
  "type": "Feature",
  "properties": {
    "iso:country":"IT",
    "sg:address":"00141 Roma",
    "sg:city":"Roma",
    "sg:orig_category":"Forniture Per Uffici",
    "sg:phone":"+39 06 810 0683",
    "sg:postcode":"00141",
    "sg:province":"Roma",
    "wof:name":"Teknoart Srl",
    "wof:placetype":"venue"
},
  "geometry": {"coordinates":[12.5153055191,41.9445381165],"type":"Point"}
}