{
  "type": "Feature",
  "properties": {
    "iso:country":"IT",
    "sg:address":"Via Del Santo 1 35010 Loreggia",
    "sg:city":"Loreggia",
    "sg:orig_category":"Acrylic Paints",
    "sg:phone":"+39 049 579 0933",
    "sg:postcode":"35010",
    "sg:province":"Padova",
    "sg:website":"www.nuovacoprik.com",
    "wof:name":"Nuova Coprik Srl",
    "wof:placetype":"venue"
},
  "geometry": {"coordinates":[11.946084,45.606804],"type":"Point"}
}