{
  "type": "Feature",
  "properties": {
    "addr:full":"17041 Altare Altare Savona 17041",
    "addr:postcode":"17041;17041",
    "iso:country":"IT",
    "sg:address":"17041 Altare",
    "sg:city":"Altare",
    "sg:orig_category":"Mobili - Vendita Al Dettaglio",
    "sg:phone":"+39 019 58163",
    "sg:postcode":"17041",
    "sg:province":"Savona",
    "wof:name":"Mm Mobili Malagamba Giovanni E Lorenzo Snc",
    "wof:placetype":"venue"
},
  "geometry": {"coordinates":[8.3415336609,44.3354759216],"type":"Point"}
}