{
  "type": "Feature",
  "properties": {
    "iso:country":"IT",
    "sg:address":"00186 Roma",
    "sg:city":"Roma",
    "sg:orig_category":"Professionisti - Studi E Servizi Ed Associazioni Di Interesse Aziendale. Associazioni Ed Organismi Di Interesse Pubblico",
    "sg:phone":"+39 06 686271",
    "sg:postcode":"00186",
    "sg:province":"Roma",
    "sg:website":"http://www.comunisti-italiani.it",
    "wof:name":"Partito Dei Comunisti Italiani",
    "wof:placetype":"venue"
},
  "geometry": {"coordinates":[12.4708719254,41.8973045349],"type":"Point"}
}