{
  "type": "Feature",
  "properties": {
    "iso:country":"IT",
    "sg:address":"43015 Noceto",
    "sg:city":"Noceto",
    "sg:orig_category":"Autosoccorso",
    "sg:phone":"+39 0521 625260",
    "sg:postcode":"43015",
    "sg:province":"Parma",
    "wof:name":"Autocarrozzeria Paterlini Guido & C. Snc",
    "wof:placetype":"venue"
},
  "geometry": {"coordinates":[10.181496,44.814617],"type":"Point"}
}