{
  "type": "Feature",
  "properties": {
    "iso:country":"IT",
    "sg:address":"60127 Ancona",
    "sg:city":"Ancona",
    "sg:orig_category":"Tessuti Arredamento, Tende E Tappeti. Forniture Per Edilizia E Lavori Pubblici",
    "sg:phone":"+39 071 894089",
    "sg:postcode":"60127",
    "sg:province":"Ancona",
    "wof:name":"Tende Tendenze Di Zaccone C. & C. Sas",
    "wof:placetype":"venue"
},
  "geometry": {"coordinates":[13.504948,43.597767],"type":"Point"}
}