{
  "type": "Feature",
  "properties": {
    "addr:full":"10, Viale Vittorio Veneto 20124 Milano Milano Milano 20124",
    "addr:housenumber":"10",
    "addr:postcode":"20124;20124",
    "addr:street":"Viale Vittorio Veneto",
    "iso:country":"IT",
    "sg:address":"10, Viale Vittorio Veneto 20124 Milano",
    "sg:city":"Milano",
    "sg:classifiers":[
        {
            "category":"Wholesale",
            "subcategory":"Medical Equipment & Supplies",
            "type":"Manufacturing & Wholesale Goods"
        }
    ],
    "sg:phone":"+39 02 2040 4813",
    "sg:postcode":"20124",
    "sg:province":"Milano",
    "sg:tags":[
        "-",
        "health",
        "instrument"
    ],
    "wof:name":"Atc Italia S.r.l.",
    "wof:placetype":"venue"
},
  "geometry": {"coordinates":[9.202645,45.47588],"type":"Point"}
}