{
  "type": "Feature",
  "properties": {
    "addr:full":"Via Beccadello 1/3; Castelleone",
    "addr:housenumber":"1 / 3",
    "addr:street":"Via Beccadello",
    "iso:country":"IT",
    "sg:address":"Via Beccadello 1/3; Castelleone",
    "sg:classifiers":[
        {
            "category":"Banks & Credit Unions",
            "subcategory":"Bank",
            "type":"Services"
        }
    ],
    "sg:phone":"+39 0374 350000",
    "wof:name":"Banca Agricola Mantovana Scarl",
    "wof:placetype":"venue"
},
  "geometry": {"coordinates":[9.764138,45.291622],"type":"Point"}
}