{
  "type": "Feature",
  "properties": {
    "iso:country":"IT",
    "sg:address":"80134 Napoli",
    "sg:city":"Napoli",
    "sg:orig_category":"Gastronomie, Salumerie E Rosticcerie",
    "sg:phone":"+39 081 551 3088",
    "sg:postcode":"80134",
    "sg:province":"Napoli",
    "wof:name":"Antiche Delizie Di Venosa Luisa Sas",
    "wof:placetype":"venue"
},
  "geometry": {"coordinates":[14.248278,40.846066],"type":"Point"}
}