{
  "type": "Feature",
  "properties": {
    "addr:full":"292/294, V. Statale - Dosso 44047 Sant'agostino Dosso Ferrara 44047",
    "addr:housenumber":"292 / 294 v.",
    "addr:postcode":"44047;44047",
    "iso:country":"IT",
    "sg:address":"292/294, V. Statale - Dosso 44047 Sant'agostino",
    "sg:city":"Dosso",
    "sg:classifiers":[
        {
            "category":"Manufacturing",
            "subcategory":"Metals",
            "type":"Manufacturing & Wholesale Goods"
        }
    ],
    "sg:phone":"+39 0532 848377",
    "sg:postcode":"44047",
    "sg:province":"Ferrara",
    "sg:tags":[
        "metallurgy",
        "metalworking"
    ],
    "sg:website":"http://www.tecopress.com",
    "wof:name":"Tecopress Spa",
    "wof:placetype":"venue"
},
  "geometry": {"coordinates":[11.6204395294,44.8378944397],"type":"Point"}
}