{
  "type": "Feature",
  "properties": {
    "iso:country":"IT",
    "sg:address":"10048 Vinovo",
    "sg:city":"Vinovo",
    "sg:orig_category":"Pompe - Commercio",
    "sg:phone":"+39 011 965 1120",
    "sg:postcode":"10048",
    "sg:province":"Torino",
    "wof:name":"Montiglio Pozzi Di Montiglio G. & C. Snc",
    "wof:placetype":"venue"
},
  "geometry": {"coordinates":[7.6320910454,44.9687690735],"type":"Point"}
}