{
  "type": "Feature",
  "properties": {
    "iso:country":"IT",
    "sg:address":"24020 Fiorano Al Serio",
    "sg:city":"Fiorano al Serio",
    "sg:orig_category":"Tessuti E Stoffe. Forniture Per Attivita' Industriali",
    "sg:phone":"+39 035 715111",
    "sg:postcode":"24020",
    "sg:province":"Bergamo",
    "wof:name":"Societa' Cristini Giuseppe",
    "wof:placetype":"venue"
},
  "geometry": {"coordinates":[9.845246,45.801075],"type":"Point"}
}