{
  "type": "Feature",
  "properties": {
    "addr:full":"16131 Genova Genova Genova 16131",
    "addr:postcode":"16131;16131",
    "iso:country":"IT",
    "sg:address":"16131 Genova",
    "sg:city":"Genova",
    "sg:orig_category":"Registratori Di Cassa",
    "sg:phone":"+39 010 377 8444",
    "sg:postcode":"16131",
    "sg:province":"Genova",
    "sg:website":"http://www.fadel-informatica.it",
    "wof:name":"Fadel Elettronica Snc",
    "wof:placetype":"venue"
},
  "geometry": {"coordinates":[8.977234,44.404423],"type":"Point"}
}