{
  "type": "Feature",
  "properties": {
    "iso:country":"IT",
    "sg:address":"21055 Gorla Minore",
    "sg:city":"Gorla Minore",
    "sg:orig_category":"Forniture Per Edilizia E Lavori Pubblici",
    "sg:phone":"+39 0331 601147",
    "sg:postcode":"21055",
    "sg:province":"Varese",
    "wof:name":"Posalinoleum",
    "wof:placetype":"venue"
},
  "geometry": {"coordinates":[8.9024515152,45.6418380737],"type":"Point"}
}