{
  "type": "Feature",
  "properties": {
    "addr:full":"56030 Laiatico Pisa 56030",
    "addr:postcode":"56030;56030",
    "iso:country":"IT",
    "sg:address":"56030 Laiatico",
    "sg:orig_category":"Colori, Vernici E Smalti - Produzione E Ingrosso",
    "sg:phone":"+39 0587 642066",
    "sg:postcode":"56030",
    "sg:province":"Pisa",
    "wof:name":"Colorlegno",
    "wof:placetype":"venue"
},
  "geometry": {"coordinates":[10.727037,43.499222],"type":"Point"}
}