{
  "type": "Feature",
  "properties": {
    "iso:country":"IT",
    "sg:address":"18, Via Marco Polo 10090 Bruino",
    "sg:city":"Bruino",
    "sg:classifiers":[
        {
            "category":"Professional",
            "subcategory":"Engineering",
            "type":"Services"
        }
    ],
    "sg:phone":"+39 011 904 8624",
    "sg:postcode":"10090",
    "sg:province":"Torino",
    "sg:tags":[
        "machine",
        "-",
        "mechanical"
    ],
    "wof:name":"Comas S.r.l.",
    "wof:placetype":"venue"
},
  "geometry": {"coordinates":[7.519011,45.008907],"type":"Point"}
}