{
  "type": "Feature",
  "properties": {
    "iso:country":"IT",
    "sg:address":"80025 Casandrino",
    "sg:city":"Casandrino",
    "sg:orig_category":"Arredamenti - Produzione E Ingrosso",
    "sg:phone":"+39 081 833 2170",
    "sg:postcode":"80025",
    "sg:province":"Napoli",
    "wof:name":"Emerson Snc",
    "wof:placetype":"venue"
},
  "geometry": {"coordinates":[14.24883,40.928555],"type":"Point"}
}