{
  "type": "Feature",
  "properties": {
    "addr:full":"29100 Piacenza Piacenza Piacenza 29100",
    "addr:postcode":"29100;29100",
    "iso:country":"IT",
    "sg:address":"29100 Piacenza",
    "sg:city":"Piacenza",
    "sg:orig_category":"Servizi Vari Di Interesse Pubblico",
    "sg:phone":"+39 0523 325726",
    "sg:postcode":"29100",
    "sg:province":"Piacenza",
    "wof:name":"Gramigna Anna",
    "wof:placetype":"venue"
},
  "geometry": {"coordinates":[9.690254,45.048031],"type":"Point"}
}