{
  "type": "Feature",
  "properties": {
    "iso:country":"IT",
    "sg:address":"00185 Roma",
    "sg:city":"Roma",
    "sg:orig_category":"Acciaierie E Fonderie",
    "sg:phone":"+39 06 445 6671",
    "sg:postcode":"00185",
    "sg:province":"Roma",
    "wof:name":"Brai Alessio",
    "wof:placetype":"venue"
},
  "geometry": {"coordinates":[12.51668,41.899605],"type":"Point"}
}