{
  "type": "Feature",
  "properties": {
    "iso:country":"IT",
    "sg:address":"10129 Torino",
    "sg:city":"Torino",
    "sg:orig_category":"Macchine E Forniture Per Arredamento E Industria Del Legno. Forniture Per Edilizia E Lavori Pubblici",
    "sg:phone":"+39 011 500143",
    "sg:postcode":"10129",
    "sg:province":"Torino",
    "wof:name":"Dilillo Giuseppe",
    "wof:placetype":"venue"
},
  "geometry": {"coordinates":[7.656142,45.055153],"type":"Point"}
}