{
  "type": "Feature",
  "properties": {
    "iso:country":"IT",
    "sg:address":"21052 Busto Arsizio",
    "sg:city":"Busto Arsizio",
    "sg:orig_category":"Servizi E Lavori Per Abbigliamento E Pelletterie",
    "sg:phone":"+39 0331 632372",
    "sg:postcode":"21052",
    "sg:province":"Varese",
    "wof:name":"Cesare Cerana Industriale Spa",
    "wof:placetype":"venue"
},
  "geometry": {"coordinates":[8.841069,45.611778],"type":"Point"}
}