{
  "type": "Feature",
  "properties": {
    "iso:country":"IT",
    "sg:address":"30033 Noale",
    "sg:city":"Noale",
    "sg:orig_category":"Prodotti Finiti Stampati. Forniture Per Attivita' Commerciali Ed Artigianali",
    "sg:phone":"+39 041 580 1965",
    "sg:postcode":"30033",
    "sg:province":"Venezia",
    "wof:name":"Vedoato Sas Di Vedoato Stefano",
    "wof:placetype":"venue"
},
  "geometry": {"coordinates":[12.062836647,45.5602416992],"type":"Point"}
}