{
  "type": "Feature",
  "properties": {
    "iso:country":"IT",
    "sg:address":"Via Olanda 51 41100 Modena",
    "sg:city":"Modena",
    "sg:classifiers":[
        {
            "category":"Manufacturing",
            "subcategory":"Motor Vehicles & Parts",
            "type":"Manufacturing & Wholesale Goods"
        }
    ],
    "sg:phone":"+39 059 420111",
    "sg:postcode":"41100",
    "sg:province":"Modena",
    "sg:tags":[
        "units",
        "braking",
        "electronic"
    ],
    "sg:website":"www.saispa.it",
    "wof:name":"S.a.i. Societa' Apparecchiature Idr Auliche Spa",
    "wof:placetype":"venue"
},
  "geometry": {"coordinates":[10.938227,44.673512],"type":"Point"}
}