{
  "type": "Feature",
  "properties": {
    "iso:country":"IT",
    "sg:address":"Via L Einaudi 30; Fano",
    "sg:classifiers":[
        {
            "category":"Banks & Credit Unions",
            "subcategory":"Bank",
            "type":"Services"
        }
    ],
    "sg:phone":"+39 0721 854034",
    "wof:name":"Banca Di Roma",
    "wof:placetype":"venue"
},
  "geometry": {"coordinates":[13.006789,43.794678],"type":"Point"}
}