{
  "type": "Feature",
  "properties": {
    "addr:full":"20132 Milano Milano Milano 20132",
    "addr:postcode":"20132;20132",
    "iso:country":"IT",
    "sg:address":"20132 Milano",
    "sg:city":"Milano",
    "sg:orig_category":"Cine-foto-ottica",
    "sg:phone":"+39 02 289 8074",
    "sg:postcode":"20132",
    "sg:province":"Milano",
    "wof:name":"International Foto Center (s.r.l.)",
    "wof:placetype":"venue"
},
  "geometry": {"coordinates":[9.236657,45.496929],"type":"Point"}
}