{
  "type": "Feature",
  "properties": {
    "addr:full":"76, Corso D'amato Salvatore 80022 Arzano Arzano Napoli 80022",
    "addr:postcode":"80022;80022",
    "addr:street":"Corso D'Amato Salvatore",
    "iso:country":"IT",
    "sg:address":"76, Corso D'amato Salvatore 80022 Arzano",
    "sg:city":"Arzano",
    "sg:classifiers":[
        {
            "category":"Shopping",
            "type":"Retail Goods"
        }
    ],
    "sg:phone":"+39 081 731 7237",
    "sg:postcode":"80022",
    "sg:province":"Napoli",
    "sg:tags":[
        "finished",
        "-",
        "metallic"
    ],
    "wof:name":"Metaltecnica Srl",
    "wof:placetype":"venue"
},
  "geometry": {"coordinates":[14.2753381729,40.9130821228],"type":"Point"}
}