{
  "type": "Feature",
  "properties": {
    "iso:country":"IT",
    "sg:address":"31020 Villorba",
    "sg:city":"Villorba",
    "sg:orig_category":"Impiantistica E Prodotti Tecnologici Per Edilizia. Elettrotecnica Industriale, Prodotti E Apparecchiature. Elettrotecnica Professionale E Di Consumo",
    "sg:phone":"+39 0422 910274",
    "sg:postcode":"31020",
    "sg:province":"Treviso",
    "wof:name":"Euro Ni.me Impianti Srl",
    "wof:placetype":"venue"
},
  "geometry": {"coordinates":[12.260084,45.713669],"type":"Point"}
}