{
  "type": "Feature",
  "properties": {
    "iso:country":"IT",
    "sg:address":"12042 Bra",
    "sg:city":"Bra",
    "sg:orig_category":"Studi E Consulenze Tecniche E Industriali. Consulenze Tecniche, Amministrative E Perizie. Servizi Ausiliari Di Analisi, Controllo E Ricerca",
    "sg:phone":"+39 0172 431775",
    "sg:postcode":"12042",
    "sg:province":"Cuneo",
    "sg:website":"http://www.prometeo7.it",
    "wof:name":"Cerato Giovanni",
    "wof:placetype":"venue"
},
  "geometry": {"coordinates":[7.849086,44.696365],"type":"Point"}
}