{
  "type": "Feature",
  "properties": {
    "addr:full":"63010 Monte San Pietrangeli Monte San Pietrangeli Ascoli Piceno 63010",
    "addr:housenumber":"63010",
    "addr:postcode":"63010",
    "addr:street":"Monte San;Monte San",
    "iso:country":"IT",
    "sg:address":"63010 Monte San Pietrangeli",
    "sg:city":"Monte San Pietrangeli",
    "sg:orig_category":"Frigotecnica, Apparecchiature E Servizi. Forniture Alle Strutture Ricettive",
    "sg:phone":"+39 0734 960063",
    "sg:postcode":"63010",
    "sg:province":"Ascoli Piceno",
    "wof:name":"Recon Di Trobbiani Ginesio",
    "wof:placetype":"venue"
},
  "geometry": {"coordinates":[13.5740442276,43.18567276],"type":"Point"}
}