{
  "type": "Feature",
  "properties": {
    "iso:country":"IT",
    "sg:address":"166, Via Venticinque Aprile 10042 Nichelino",
    "sg:city":"Nichelino",
    "sg:classifiers":[
        {
            "category":"Professional",
            "subcategory":"Engineering",
            "type":"Services"
        }
    ],
    "sg:phone":"+39 011 680 7114",
    "sg:postcode":"10042",
    "sg:province":"Torino",
    "sg:tags":[
        "machine",
        "-",
        "mechanical"
    ],
    "wof:name":"Bocca & Malandrone Sunebo S.p.a.",
    "wof:placetype":"venue"
},
  "geometry": {"coordinates":[7.686619,45.07056],"type":"Point"}
}