{
  "type": "Feature",
  "properties": {
    "iso:country":"IT",
    "sg:address":"00044 Frascati",
    "sg:city":"Frascati",
    "sg:orig_category":"Servizi E Lavori Per Edilizia E Lavori Pubblici. Acqua, Luce, Gas E Societa' Di Esercizio Pubblico",
    "sg:postcode":"00044",
    "sg:province":"Roma",
    "wof:name":"Gestione Acquedotto Algidosiasrl",
    "wof:placetype":"venue"
},
  "geometry": {"coordinates":[12.673301,41.823296],"type":"Point"}
}