{
  "type": "Feature",
  "properties": {
    "iso:country":"IT",
    "sg:address":"3, Regione Curetta 15040 Pietra Marazzi",
    "sg:city":"Pietra Marazzi",
    "sg:classifiers":[
        {
            "category":"Professional",
            "subcategory":"Engineering",
            "type":"Services"
        }
    ],
    "sg:phone":"+39 0131 355355",
    "sg:postcode":"15040",
    "sg:province":"Alessandria",
    "sg:tags":[
        "machine",
        "-",
        "mechanical"
    ],
    "wof:name":"A.s.t.r.a. Refrigeranti S.p.a.",
    "wof:placetype":"venue"
},
  "geometry": {"coordinates":[8.653938,44.94241],"type":"Point"}
}