{
  "type": "Feature",
  "properties": {
    "addr:full":"Via Per Trecate 19/a 28068 Romentino Romentino Novara 28068",
    "addr:housenumber":"19 / a",
    "addr:postcode":"28068;28068",
    "addr:street":"Via Per Trecate",
    "iso:country":"IT",
    "sg:address":"Via Per Trecate 19/a 28068 Romentino",
    "sg:city":"Romentino",
    "sg:classifiers":[
        {
            "category":"Autos & Motor Vehicles",
            "subcategory":"Auto Supplies",
            "type":"Retail Goods"
        }
    ],
    "sg:phone":"+39 0321 860786",
    "sg:postcode":"28068",
    "sg:province":"Novara",
    "sg:tags":[
        "machine",
        "cover"
    ],
    "wof:name":"Ferrari & Malerba Spa",
    "wof:placetype":"venue"
},
  "geometry": {"coordinates":[8.680804,45.456997],"type":"Point"}
}