{
  "type": "Feature",
  "properties": {
    "iso:country":"IT",
    "sg:address":"29010 Sarmato",
    "sg:city":"Sarmato",
    "sg:orig_category":"Termotecnica E Riscaldamento, Apparecchiature E Servizi",
    "sg:phone":"+39 0523 887938",
    "sg:postcode":"29010",
    "sg:province":"Piacenza",
    "wof:name":"I.t.a. (s.r.l.)",
    "wof:placetype":"venue"
},
  "geometry": {"coordinates":[9.493444,45.05798],"type":"Point"}
}