{
  "type": "Feature",
  "properties": {
    "iso:country":"IT",
    "sg:address":"25080 Calvagese Della Riviera",
    "sg:city":"Calvagese della Riviera",
    "sg:orig_category":"Valvole E Apparecchiature Di Misura. Forniture Per Attivita' Industriali",
    "sg:phone":"+39 030 601061",
    "sg:postcode":"25080",
    "sg:province":"Brescia",
    "wof:name":"Enne.pi. (s.r.l.)",
    "wof:placetype":"venue"
},
  "geometry": {"coordinates":[10.301274,45.539223],"type":"Point"}
}