{
  "type": "Feature",
  "properties": {
    "addr:full":"47035 Gambettola Gambettola Forl\u00ec-Cesena 47035",
    "addr:postcode":"47035;47035",
    "iso:country":"IT",
    "sg:address":"47035 Gambettola",
    "sg:city":"Gambettola",
    "sg:orig_category":"Servizi E Lavori Industria Chimica. Trattamenti Termici E Superficiali Metalli, Galvanotecnica",
    "sg:phone":"+39 0547 52040",
    "sg:postcode":"47035",
    "sg:province":"Forl\u00ec-Cesena",
    "wof:name":"Ideal System Di Sfienti Marco",
    "wof:placetype":"venue"
},
  "geometry": {"coordinates":[12.331952,44.113937],"type":"Point"}
}