{
  "type": "Feature",
  "properties": {
    "addr:full":"00192 Roma Roma Roma 00192",
    "addr:postcode":"00192;00192",
    "iso:country":"IT",
    "sg:address":"00192 Roma",
    "sg:city":"Roma",
    "sg:orig_category":"Servizi Editoriali. Shopping",
    "sg:phone":"+39 06 321 9601",
    "sg:postcode":"00192",
    "sg:province":"Roma",
    "wof:name":"Corradi Daniele",
    "wof:placetype":"venue"
},
  "geometry": {"coordinates":[12.46394,41.91077],"type":"Point"}
}