{
  "type": "Feature",
  "properties": {
    "iso:country":"IT",
    "sg:address":"31033 Castelfranco Veneto",
    "sg:city":"Castelfranco Veneto",
    "sg:orig_category":"Impiantistica E Prodotti Tecnologici Per Edilizia. Macchine, Strumenti Ed Apparecchi Per Attivita' Industriali",
    "sg:phone":"+39 0423 495556",
    "sg:postcode":"31033",
    "sg:province":"Treviso",
    "wof:name":"Milanottica Di Scarparo Guerrino",
    "wof:placetype":"venue"
},
  "geometry": {"coordinates":[11.936238,45.669506],"type":"Point"}
}