{
  "type": "Feature",
  "properties": {
    "iso:country":"IT",
    "sg:address":"17024 Finale Ligure",
    "sg:city":"Finale Ligure",
    "sg:orig_category":"Non-classified Establishments",
    "sg:phone":"+39 019 680457",
    "sg:postcode":"17024",
    "sg:province":"Savona",
    "wof:name":"Love Potions Shop Srl",
    "wof:placetype":"venue"
},
  "geometry": {"coordinates":[8.34533,44.169064],"type":"Point"}
}