{
  "type": "Feature",
  "properties": {
    "iso:country":"IT",
    "sg:address":"35015 Galliera Veneta",
    "sg:city":"Galliera Veneta",
    "sg:orig_category":"Serramenti Ed Infissi",
    "sg:phone":"+39 049 596 5097",
    "sg:postcode":"35015",
    "sg:province":"Padova",
    "wof:name":"Sicc Srl",
    "wof:placetype":"venue"
},
  "geometry": {"coordinates":[11.818079,45.667545],"type":"Point"}
}