{
  "type": "Feature",
  "properties": {
    "iso:country":"IT",
    "sg:address":"20068 Peschiera Borromeo",
    "sg:city":"Peschiera Borromeo",
    "sg:orig_category":"Trasporti E Spedizioni Merci",
    "sg:phone":"+39 02 5165 0474",
    "sg:postcode":"20068",
    "sg:province":"Milano",
    "wof:name":"Recapiti Unifret Vidale Union Shipping Spa",
    "wof:placetype":"venue"
},
  "geometry": {"coordinates":[9.317017,45.427929],"type":"Point"}
}