{
  "type": "Feature",
  "properties": {
    "iso:country":"IT",
    "sg:address":"2, Via Dei Fabbri 48011 Alfonsine",
    "sg:city":"Alfonsine",
    "sg:classifiers":[
        {
            "category":"Manufacturing",
            "subcategory":"Metals",
            "type":"Manufacturing & Wholesale Goods"
        }
    ],
    "sg:phone":"+39 39054484380",
    "sg:postcode":"48011",
    "sg:province":"Ravenna",
    "sg:tags":[
        "metallurgy",
        "metalworking"
    ],
    "wof:name":"Fonderia Taroni Di Taroni Roberto & C. (s.n.c.)",
    "wof:placetype":"venue"
},
  "geometry": {"coordinates":[12.0206642151,44.5075035095],"type":"Point"}
}