{
  "type": "Feature",
  "properties": {
    "iso:country":"IT",
    "sg:address":"Via Nerucci Gherardo 3 51031 Agliana",
    "sg:city":"Agliana",
    "sg:classifiers":[
        {
            "category":"Shopping",
            "subcategory":"Clothing, Apparel, & Fashions",
            "type":"Retail Goods"
        }
    ],
    "sg:phone":"+39 0574 751357",
    "sg:postcode":"51031",
    "sg:province":"Pistoia",
    "sg:tags":[
        "clothing",
        "guild",
        "accessory"
    ],
    "sg:website":"www.gibiwear.it",
    "wof:name":"Gibiwear Srl",
    "wof:placetype":"venue"
},
  "geometry": {"coordinates":[10.984684,43.908142],"type":"Point"}
}