{
  "type": "Feature",
  "properties": {
    "iso:country":"IT",
    "sg:address":"10060 Scalenghe",
    "sg:city":"Scalenghe",
    "sg:orig_category":"Macchine, Impianti Ed Attrezzature Per Agricoltura E Zootecnia",
    "sg:phone":"+39 011 986 1755",
    "sg:postcode":"10060",
    "sg:province":"Torino",
    "wof:name":"Gallo Sebastiano",
    "wof:placetype":"venue"
},
  "geometry": {"coordinates":[7.497775,44.886219],"type":"Point"}
}