{
  "type": "Feature",
  "properties": {
    "addr:full":"00151 Roma Roma Roma 00151",
    "addr:postcode":"00151;00151",
    "iso:country":"IT",
    "sg:address":"00151 Roma",
    "sg:city":"Roma",
    "sg:orig_category":"Servizi Per Aziende, Manifestazioni E Supporto Agli Scambi Commerciali. Ambasciate Ed Enti Internazionali",
    "sg:phone":"+39 06 657501",
    "sg:postcode":"00151",
    "sg:province":"Roma",
    "wof:name":"Centro Nazionale Trasfusione Sangue C.r.i.",
    "wof:placetype":"venue"
},
  "geometry": {"coordinates":[12.451096,41.863152],"type":"Point"}
}