{
  "type": "Feature",
  "properties": {
    "iso:country":"IT",
    "sg:address":"Via Stazione 108 27020 Valle Lomellina",
    "sg:city":"Valle Lomellina",
    "sg:classifiers":[
        {
            "category":"Utilities",
            "subcategory":"Water",
            "type":"Services"
        }
    ],
    "sg:phone":"+39 0384 79038",
    "sg:postcode":"27020",
    "sg:province":"Pavia",
    "sg:tags":[
        "screw",
        "special-purpose"
    ],
    "sg:website":"www.viteriafusani.it",
    "wof:name":"Viteria F.fusani Snc Di Fusani Tino & F. Lli",
    "wof:placetype":"venue"
},
  "geometry": {"coordinates":[8.683117,45.150562],"type":"Point"}
}