{
  "type": "Feature",
  "properties": {
    "addr:full":"Ctr. Tenna 89 63025 Rapagnano Rapagnano Ascoli Piceno 63025",
    "addr:housenumber":"89",
    "addr:postcode":"63025;63025",
    "addr:street":"Tenna",
    "iso:country":"IT",
    "sg:address":"Ctr. Tenna 89 63025 Rapagnano",
    "sg:city":"Rapagnano",
    "sg:orig_category":"Plastic Parts According To Drawing",
    "sg:phone":"+39 0734 628002",
    "sg:postcode":"63025",
    "sg:province":"Ascoli Piceno",
    "sg:website":"www.tsm.it",
    "wof:name":"T.s.m. Fondi Srl",
    "wof:placetype":"venue"
},
  "geometry": {"coordinates":[13.5749769211,42.8554000854],"type":"Point"}
}