{
  "type": "Feature",
  "properties": {
    "addr:full":"20141 Milano Milano Milano 20141",
    "addr:postcode":"20141;20141",
    "iso:country":"IT",
    "sg:address":"20141 Milano",
    "sg:city":"Milano",
    "sg:classifiers":[
        {
            "category":"Health Services",
            "subcategory":"Health Practitioner",
            "type":"Services"
        }
    ],
    "sg:phone":"+39 02 5740 3270",
    "sg:postcode":"20141",
    "sg:province":"Milano",
    "sg:tags":[
        "medici"
    ],
    "wof:name":"Furlotti Dr. Raffaele",
    "wof:placetype":"venue"
},
  "geometry": {"coordinates":[9.199751,45.423962],"type":"Point"}
}