{
  "type": "Feature",
  "properties": {
    "addr:full":"26013 Crema Crema Cremona 26013",
    "addr:postcode":"26013;26013",
    "iso:country":"IT",
    "sg:address":"26013 Crema",
    "sg:city":"Crema",
    "sg:orig_category":"Medici Specialisti - Otorinolaringoiatria",
    "sg:phone":"+39 0373 250549",
    "sg:postcode":"26013",
    "sg:province":"Cremona",
    "wof:name":"Fontanella Dott. Walter Maurizio",
    "wof:placetype":"venue"
},
  "geometry": {"coordinates":[9.68926,45.363892],"type":"Point"}
}