{
  "type": "Feature",
  "properties": {
    "iso:country":"IT",
    "sg:address":"25025 Manerbio",
    "sg:city":"Manerbio",
    "sg:orig_category":"Servizi E Lavori Per Ecologia E Smaltimento Rifiuti. Servizi Ausiliari Di Sorveglianza, Manutenzione E Pulizia",
    "sg:phone":"+39 030 938 3488",
    "sg:postcode":"25025",
    "sg:province":"Brescia",
    "wof:name":"Girelli Elisa & C. Srl",
    "wof:placetype":"venue"
},
  "geometry": {"coordinates":[10.121168,45.247398],"type":"Point"}
}