{
  "type": "Feature",
  "properties": {
    "iso:country":"IT",
    "sg:address":"Piazza Vittorio; Racconigi; 12035",
    "sg:city":"Racconigi",
    "sg:classifiers":[
        {
            "category":"Banks & Credit Unions",
            "subcategory":"Bank",
            "type":"Services"
        }
    ],
    "sg:phone":"+39 0172 811904",
    "sg:postcode":"12035",
    "sg:province":"Cuneo",
    "wof:name":"Cariverona Banca Spa",
    "wof:placetype":"venue"
},
  "geometry": {"coordinates":[7.677441,44.768391],"type":"Point"}
}