{
  "type": "Feature",
  "properties": {
    "iso:country":"IT",
    "sg:address":"13, Via Rui Stort 31010 Farra Di Soligo",
    "sg:city":"Farra di Soligo",
    "sg:classifiers":[
        {
            "category":"Home & Garden",
            "subcategory":"Home Furnishings",
            "type":"Retail Goods"
        }
    ],
    "sg:phone":"+39 0438 900253",
    "sg:postcode":"31010",
    "sg:province":"Treviso",
    "sg:tags":[
        "household"
    ],
    "wof:name":"Hoffmann Italia S.r.l.",
    "wof:placetype":"venue"
},
  "geometry": {"coordinates":[12.105807,45.899315],"type":"Point"}
}