{
  "type": "Feature",
  "properties": {
    "iso:country":"IT",
    "sg:address":"Via Ca' Brus\u00e0 9 37050 Vago",
    "sg:classifiers":[
        {
            "category":"Animal Shelter",
            "type":"Public Place"
        }
    ],
    "sg:phone":"+39 045 982022",
    "sg:postcode":"37050",
    "sg:province":"Verona",
    "sg:tags":[
        "feed",
        "system",
        "dispensing"
    ],
    "wof:name":"Nuova Cizo Srl",
    "wof:placetype":"venue"
},
  "geometry": {"coordinates":[11.099649,45.446156],"type":"Point"}
}