{
  "type": "Feature",
  "properties": {
    "addr:full":"26864 Ospedaletto Lodigiano Ospedaletto Lodigiano Lodi 26864",
    "addr:housenumber":"lodigiano",
    "addr:postcode":"26864;26864",
    "iso:country":"IT",
    "sg:address":"26864 Ospedaletto Lodigiano",
    "sg:city":"Ospedaletto Lodigiano",
    "sg:orig_category":"Elettrotecnica Industriale, Prodotti E Apparecchiature",
    "sg:phone":"+39 0377 86501",
    "sg:postcode":"26864",
    "sg:province":"Lodi",
    "wof:name":"Bticino Spa",
    "wof:placetype":"venue"
},
  "geometry": {"coordinates":[9.57907,45.170418],"type":"Point"}
}