{
  "type": "Feature",
  "properties": {
    "iso:country":"IT",
    "sg:address":"10070 Vauda Canavese",
    "sg:city":"Vauda Canavese",
    "sg:orig_category":"Forniture Per Abbigliamento E Pelletterie",
    "sg:phone":"+39 011 924 2619",
    "sg:postcode":"10070",
    "sg:province":"Torino",
    "wof:name":"Studio 9 Di Biancardi E Paratore Snc",
    "wof:placetype":"venue"
},
  "geometry": {"coordinates":[7.6172475815,45.2804031372],"type":"Point"}
}