{
  "type": "Feature",
  "properties": {
    "iso:country":"IT",
    "sg:address":"Corso Mazzini 1/a; Pavia; 27100",
    "sg:city":"Pavia",
    "sg:classifiers":[
        {
            "category":"Banks & Credit Unions",
            "subcategory":"Bank",
            "type":"Services"
        }
    ],
    "sg:phone":"+39 0382 21141",
    "sg:postcode":"27100",
    "sg:province":"Pavia",
    "wof:name":"Credito Italiano Spa",
    "wof:placetype":"venue"
},
  "geometry": {"coordinates":[9.155468,45.185368],"type":"Point"}
}