{
  "type": "Feature",
  "properties": {
    "addr:full":"50127 Firenze Firenze Firenze 50127",
    "addr:postcode":"50127;50127",
    "iso:country":"IT",
    "sg:address":"50127 Firenze",
    "sg:city":"Firenze",
    "sg:orig_category":"Chiese Ed Associazioni Religiose",
    "sg:phone":"+39 055 416723",
    "sg:postcode":"50127",
    "sg:province":"Firenze",
    "wof:name":"Comunita' Ebraica Di Firenze",
    "wof:placetype":"venue"
},
  "geometry": {"coordinates":[11.230812,43.798878],"type":"Point"}
}