{
  "type": "Feature",
  "properties": {
    "addr:full":"Via Jesi, 15/19 61100 Pesaro Pesaro Pesaro E Urbino 61100",
    "addr:housenumber":"15 / 19",
    "addr:postcode":"61100;61100",
    "addr:street":"Via Jesi",
    "iso:country":"IT",
    "sg:address":"Via Jesi, 15/19 61100 Pesaro",
    "sg:city":"Pesaro",
    "sg:classifiers":[
        {
            "category":"Landmark",
            "subcategory":"Marketplace",
            "type":"Public Place"
        }
    ],
    "sg:phone":"+39 0721 402049",
    "sg:postcode":"61100",
    "sg:province":"Pesaro E Urbino",
    "sg:tags":[
        "industry",
        "part",
        "bought-in",
        "furniture"
    ],
    "sg:website":"www.ornamobil.it",
    "wof:name":"Ornamobil Srl",
    "wof:placetype":"venue"
},
  "geometry": {"coordinates":[12.887675,43.90424],"type":"Point"}
}