{
  "type": "Feature",
  "properties": {
    "addr:full":"37019 Peschiera Del Garda Peschiera del Garda Verona 37019",
    "addr:postcode":"37019;37019",
    "iso:country":"IT",
    "sg:address":"37019 Peschiera Del Garda",
    "sg:city":"Peschiera del Garda",
    "sg:orig_category":"Prodotti Alimentari",
    "sg:phone":"+39 045 755 0157",
    "sg:postcode":"37019",
    "sg:province":"Verona",
    "wof:name":"Gianello Luciano",
    "wof:placetype":"venue"
},
  "geometry": {"coordinates":[10.6964883804,45.4398956299],"type":"Point"}
}