{
  "type": "Feature",
  "properties": {
    "addr:full":"31033 Castelfranco Veneto Castelfranco Veneto Treviso 31033",
    "addr:postcode":"31033;31033",
    "iso:country":"IT",
    "sg:address":"31033 Castelfranco Veneto",
    "sg:city":"Castelfranco Veneto",
    "sg:orig_category":"Parcheggio - Impianti Ed Attrezzature",
    "sg:phone":"+39 0423 721993",
    "sg:postcode":"31033",
    "sg:province":"Treviso",
    "wof:name":"Progesis Srl",
    "wof:placetype":"venue"
},
  "geometry": {"coordinates":[11.9362382889,45.669506073],"type":"Point"}
}