{
  "type": "Feature",
  "properties": {
    "iso:country":"IT",
    "sg:address":"Riviera Tiot Livio, 28; Padova; 35100",
    "sg:classifiers":[
        {
            "category":"Banks & Credit Unions",
            "subcategory":"Bank",
            "type":"Services"
        }
    ],
    "sg:phone":"+39 049 875 4500",
    "wof:name":"Banca D'italia",
    "wof:placetype":"venue"
},
  "geometry": {"coordinates":[11.876953,45.404926],"type":"Point"}
}