{
  "type": "Feature",
  "properties": {
    "iso:country":"IT",
    "sg:address":"20033 Desio",
    "sg:city":"Desio",
    "sg:orig_category":"Arredo Camera Letto E Complementi",
    "sg:phone":"+39 036 262 2784",
    "sg:postcode":"20033",
    "sg:province":"Milano",
    "wof:name":"La Mia Victorflex Srl",
    "wof:placetype":"venue"
},
  "geometry": {"coordinates":[9.198744,45.61895],"type":"Point"}
}