{
  "type": "Feature",
  "properties": {
    "addr:full":"33170 Pordenone Pordenone Pordenone 33170",
    "addr:postcode":"33170;33170",
    "iso:country":"IT",
    "sg:address":"33170 Pordenone",
    "sg:city":"Pordenone",
    "sg:orig_category":"Forniture Per Attivita' Industriali",
    "sg:phone":"+39 0434 45304",
    "sg:postcode":"33170",
    "sg:province":"Pordenone",
    "sg:website":"http://www.trasmecc.it",
    "wof:name":"Trasmecc Di Zavagno A. & C. Sas",
    "wof:placetype":"venue"
},
  "geometry": {"coordinates":[12.6845712662,45.958366394],"type":"Point"}
}