{
  "type": "Feature",
  "properties": {
    "addr:full":"17019 Varazze Varazze Savona 17019",
    "addr:postcode":"17019;17019",
    "iso:country":"IT",
    "sg:address":"17019 Varazze",
    "sg:city":"Varazze",
    "sg:classifiers":[
        {
            "category":"Health Services",
            "subcategory":"Nursing And Care Facility",
            "type":"Services"
        }
    ],
    "sg:phone":"+39 019 934630",
    "sg:postcode":"17019",
    "sg:province":"Savona",
    "sg:tags":[
        "case",
        "cura",
        "private",
        "di"
    ],
    "wof:name":"Albergo Ate Srl",
    "wof:placetype":"venue"
},
  "geometry": {"coordinates":[8.561114,44.389042],"type":"Point"}
}