{
  "type": "Feature",
  "properties": {
    "addr:full":"10093 Collegno Collegno Torino 10093",
    "addr:postcode":"10093;10093",
    "iso:country":"IT",
    "sg:address":"10093 Collegno",
    "sg:city":"Collegno",
    "sg:orig_category":"Studi E Consulenze Tecniche E Industriali. Consulenze Tecniche, Amministrative E Perizie. Professionisti - Studi E Servizi Ed Associazioni Di Interesse Aziendale",
    "sg:phone":"+39 011 405 5180",
    "sg:postcode":"10093",
    "sg:province":"Torino",
    "wof:name":"Faggiani Franco",
    "wof:placetype":"venue"
},
  "geometry": {"coordinates":[7.574013,45.074944],"type":"Point"}
}