{
  "type": "Feature",
  "properties": {
    "iso:country":"IT",
    "sg:address":"00149 Roma",
    "sg:city":"Roma",
    "sg:orig_category":"Arredamento Alberghi",
    "sg:phone":"+39 06 552 7359",
    "sg:postcode":"00149",
    "sg:province":"Roma",
    "wof:name":"Cris & Val Arredo Sas",
    "wof:placetype":"venue"
},
  "geometry": {"coordinates":[12.449043,41.849892],"type":"Point"}
}