{
  "type": "Feature",
  "properties": {
    "iso:country":"IT",
    "sg:address":"40010 Bentivoglio",
    "sg:city":"Bentivoglio",
    "sg:orig_category":"Cine-foto-ottica. Articoli Medico-sanitari Ed Ortopedici. Impianti, Attrezzature E Forniture Sanitarie Ed Ospedaliere",
    "sg:phone":"+39 051 899111",
    "sg:postcode":"40010",
    "sg:province":"Bologna",
    "sg:website":"http://www.it.marposs.com",
    "wof:name":"Marposs Italia Spa",
    "wof:placetype":"venue"
},
  "geometry": {"coordinates":[11.381878,44.571251],"type":"Point"}
}