{
  "type": "Feature",
  "properties": {
    "iso:country":"IT",
    "sg:address":"66020 S.giovanni Teatino",
    "sg:city":"Sambuceto",
    "sg:orig_category":"Prodotti Vari In Metallo",
    "sg:phone":"+39 085 446 0880",
    "sg:postcode":"66020",
    "sg:province":"Chieti",
    "wof:name":"Tecnoacciai Snc Di Francesco Claudio & C.",
    "wof:placetype":"venue"
},
  "geometry": {"coordinates":[14.1682014465,42.4184150696],"type":"Point"}
}