{
  "type": "Feature",
  "properties": {
    "iso:country":"IT",
    "sg:address":"25011 Calcinato",
    "sg:city":"Calcinato",
    "sg:orig_category":"Tessuti E Stoffe. Filati E Materie Prime Tessili",
    "sg:phone":"+39 030 996 4785",
    "sg:postcode":"25011",
    "sg:province":"Brescia",
    "wof:name":"Tessival S.p.a.",
    "wof:placetype":"venue"
},
  "geometry": {"coordinates":[10.415888,45.455811],"type":"Point"}
}