{
  "type": "Feature",
  "properties": {
    "iso:country":"IT",
    "sg:address":"20099 Sesto San Giovanni",
    "sg:city":"Sesto San Giovanni",
    "sg:orig_category":"Dolciumi E Gelati",
    "sg:phone":"+39 02 248 3236",
    "sg:postcode":"20099",
    "sg:province":"Milano",
    "wof:name":"G.b. Gestione Bar Di Luoni Carlo & C. Sas",
    "wof:placetype":"venue"
},
  "geometry": {"coordinates":[9.230653,45.533012],"type":"Point"}
}