{
  "type": "Feature",
  "properties": {
    "iso:country":"IT",
    "sg:address":"300, Viale Commercio 27029 Vigevano",
    "sg:city":"Vigevano",
    "sg:classifiers":[
        {
            "category":"Professional",
            "subcategory":"Engineering",
            "type":"Services"
        }
    ],
    "sg:phone":"+39 39038142162",
    "sg:postcode":"27029",
    "sg:province":"Pavia",
    "sg:tags":[
        "machine",
        "-",
        "mechanical"
    ],
    "wof:name":"Officina Meccanica Silpar Di Rossi F. & C. (s.n.c.)",
    "wof:placetype":"venue"
},
  "geometry": {"coordinates":[8.856829,45.299892],"type":"Point"}
}