{
  "type": "Feature",
  "properties": {
    "iso:country":"IT",
    "sg:address":"20097 San Donato Milanese",
    "sg:city":"San Donato Milanese",
    "sg:orig_category":"Servizi Ausiliari Dei Mezzi Di Trasporto",
    "sg:phone":"+39 02 523 0162",
    "sg:postcode":"20097",
    "sg:province":"Milano",
    "wof:name":"Fratelli Cerabino Di Cerabino Michele E Savino Snc",
    "wof:placetype":"venue"
},
  "geometry": {"coordinates":[9.258321,45.411835],"type":"Point"}
}