{
  "type": "Feature",
  "properties": {
    "iso:country":"IT",
    "sg:address":"38082 Cimego",
    "sg:city":"Cimego",
    "sg:orig_category":"Macchine Ed Impianti Per Edilizia E Lavori Pubblici",
    "sg:phone":"+39 0465 621333",
    "sg:postcode":"38082",
    "sg:province":"Trento",
    "wof:name":"Scavi Nord Di Zulberti Rinaldo & C. (s.n.c.)",
    "wof:placetype":"venue"
},
  "geometry": {"coordinates":[10.617971,45.914093],"type":"Point"}
}