{
  "type": "Feature",
  "properties": {
    "addr:full":"16, Via Monte Bianco 20022 Castano Primo Castano Primo Milano 20022",
    "addr:postcode":"20022;20022",
    "addr:street":"Via Monte Bianco",
    "iso:country":"IT",
    "sg:address":"16, Via Monte Bianco 20022 Castano Primo",
    "sg:city":"Castano Primo",
    "sg:classifiers":[
        {
            "category":"Professional",
            "subcategory":"Engineering",
            "type":"Services"
        }
    ],
    "sg:phone":"+39 0331 880491",
    "sg:postcode":"20022",
    "sg:province":"Milano",
    "sg:tags":[
        "machine",
        "-",
        "mechanical"
    ],
    "wof:name":"Gualdoni (s.r.l.)",
    "wof:placetype":"venue"
},
  "geometry": {"coordinates":[8.776527,45.584171],"type":"Point"}
}