{
  "type": "Feature",
  "properties": {
    "addr:full":"51100 Bottegone Bottegone Pistoia 51100",
    "addr:postcode":"51100;51100",
    "iso:country":"IT",
    "sg:address":"51100 Bottegone",
    "sg:city":"Bottegone",
    "sg:orig_category":"Prodotti E Manufatti In Materie Plastiche",
    "sg:phone":"+39 0573 545184",
    "sg:postcode":"51100",
    "sg:province":"Pistoia",
    "wof:name":"Mas Italia Spa",
    "wof:placetype":"venue"
},
  "geometry": {"coordinates":[10.9573307037,43.8883399963],"type":"Point"}
}