{
  "type": "Feature",
  "properties": {
    "addr:full":"Viale Europa 154 51039 Quarrata Quarrata Pistoia 51039",
    "addr:housenumber":"154",
    "addr:postcode":"51039;51039",
    "addr:street":"Viale Europa",
    "iso:country":"IT",
    "sg:address":"Viale Europa 154 51039 Quarrata",
    "sg:city":"Quarrata",
    "sg:classifiers":[
        {
            "category":"Wholesale",
            "subcategory":"Furniture",
            "type":"Manufacturing & Wholesale Goods"
        }
    ],
    "sg:phone":"+39 0573 72048",
    "sg:postcode":"51039",
    "sg:province":"Pistoia",
    "sg:tags":[
        "upholstered"
    ],
    "wof:name":"Piemme Group Srl",
    "wof:placetype":"venue"
},
  "geometry": {"coordinates":[10.955957,43.85899],"type":"Point"}
}