{
  "type": "Feature",
  "properties": {
    "iso:country":"IT",
    "sg:address":"06081 Assisi",
    "sg:city":"Assisi",
    "sg:orig_category":"Agriturismo",
    "sg:phone":"+39 075 813513",
    "sg:postcode":"06081",
    "sg:province":"Perugia",
    "wof:name":"Agriturismo Pro Vobis Country House",
    "wof:placetype":"venue"
},
  "geometry": {"coordinates":[12.644587,43.069424],"type":"Point"}
}