{
  "type": "Feature",
  "properties": {
    "addr:full":"03049 Sant'elia Fiumerapido Frosinone 03049",
    "addr:postcode":"03049;03049",
    "iso:country":"IT",
    "sg:address":"03049 Sant'elia Fiumerapido",
    "sg:orig_category":"Automazione E Macchine Per Ufficio. Servizi Ausiliari Di Certificati, Riproduzioni, Disegni E Foto",
    "sg:phone":"+39 0776 429730",
    "sg:postcode":"03049",
    "sg:province":"Frosinone",
    "wof:name":"C.s.i. Di Valente Valentino",
    "wof:placetype":"venue"
},
  "geometry": {"coordinates":[13.863633,41.526218],"type":"Point"}
}