{
  "type": "Feature",
  "properties": {
    "iso:country":"IT",
    "sg:address":"50022 Greve In Chianti",
    "sg:city":"Greve in Chianti",
    "sg:orig_category":"Servizi E Lavori Per Abbigliamento E Pelletterie",
    "sg:phone":"+39 055 854 7406",
    "sg:postcode":"50022",
    "sg:province":"Firenze",
    "wof:name":"Lavanderia Angelo Azzurro Di Pelli Angela",
    "wof:placetype":"venue"
},
  "geometry": {"coordinates":[11.320416,43.590641],"type":"Point"}
}