{
  "type": "Feature",
  "properties": {
    "addr:full":"20122 Milano Milano Milano 20122",
    "addr:postcode":"20122;20122",
    "iso:country":"IT",
    "sg:address":"20122 Milano",
    "sg:city":"Milano",
    "sg:orig_category":"Lavoro Interinale E Temporaneo",
    "sg:phone":"+39 02 770741",
    "sg:postcode":"20122",
    "sg:province":"Milano",
    "sg:website":"http://www.manpower.it",
    "wof:name":"Manpower Spa",
    "wof:placetype":"venue"
},
  "geometry": {"coordinates":[9.195673,45.465492],"type":"Point"}
}