{
  "type": "Feature",
  "properties": {
    "iso:country":"IT",
    "sg:address":"36075 Montecchio Maggiore",
    "sg:city":"Montecchio Maggiore",
    "sg:orig_category":"Automazione E Robotica - Apparecchiature E Componenti",
    "sg:phone":"+39 0444 499015",
    "sg:postcode":"36075",
    "sg:province":"Vicenza",
    "wof:name":"A-zeta Automazioni Srl",
    "wof:placetype":"venue"
},
  "geometry": {"coordinates":[11.406491,45.492477],"type":"Point"}
}