{
  "type": "Feature",
  "properties": {
    "iso:country":"IT",
    "sg:address":"20090 Buccinasco",
    "sg:city":"Buccinasco",
    "sg:orig_category":"Prodotti Chimici Di Base. Prodotti Cosmetici E Da Toeletta",
    "sg:phone":"+39 02 4571 2366",
    "sg:postcode":"20090",
    "sg:province":"Milano",
    "wof:name":"Creative Flavours & Fragrances S.r.l.",
    "wof:placetype":"venue"
},
  "geometry": {"coordinates":[9.1125669479,45.4238243103],"type":"Point"}
}