{
  "type": "Feature",
  "properties": {
    "iso:country":"IT",
    "sg:address":"27, Via Albani Francesco 20148 Milano",
    "sg:city":"Milano",
    "sg:classifiers":[
        {
            "category":"Professional",
            "subcategory":"Engineering",
            "type":"Services"
        }
    ],
    "sg:phone":"+39 02 4801 2424",
    "sg:postcode":"20148",
    "sg:province":"Milano",
    "sg:tags":[
        "machine",
        "-",
        "mechanical"
    ],
    "wof:name":"Metasald (s.r.l.)",
    "wof:placetype":"venue"
},
  "geometry": {"coordinates":[9.147597,45.479866],"type":"Point"}
}