{
  "type": "Feature",
  "properties": {
    "iso:country":"IT",
    "sg:address":"71100 Foggia",
    "sg:city":"Foggia",
    "sg:orig_category":"Camere Di Commercio",
    "sg:phone":"+39 0881 7971",
    "sg:postcode":"71100",
    "sg:province":"Foggia",
    "wof:name":"Camera Di Commercio Industria Artigianato E Agricoltura",
    "wof:placetype":"venue"
},
  "geometry": {"coordinates":[15.547438,41.449795],"type":"Point"}
}