{
  "type": "Feature",
  "properties": {
    "iso:country":"IT",
    "sg:address":"00040 Ardea",
    "sg:city":"Ardea",
    "sg:orig_category":"Servizi Culturali E Per Lo Spettacolo",
    "sg:phone":"+39 06 913 5200",
    "sg:postcode":"00040",
    "sg:province":"Roma",
    "wof:name":"Cine Ardeatino (s.r.l.)",
    "wof:placetype":"venue"
},
  "geometry": {"coordinates":[12.412555,41.984901],"type":"Point"}
}