{
  "type": "Feature",
  "properties": {
    "iso:country":"IT",
    "sg:address":"25018 Montichiari",
    "sg:city":"Montichiari",
    "sg:classifiers":[
        {
            "category":"Farming",
            "subcategory":"Berry Farm",
            "type":"Manufacturing & Wholesale Goods"
        }
    ],
    "sg:phone":"+39 030 998 1381",
    "sg:postcode":"25018",
    "sg:province":"Brescia",
    "sg:tags":[
        "vegetable",
        "growing",
        "flower",
        "agriculture"
    ],
    "wof:name":"Flormercati Coop Scrl",
    "wof:placetype":"venue"
},
  "geometry": {"coordinates":[10.295234,45.473972],"type":"Point"}
}