{
  "type": "Feature",
  "properties": {
    "iso:country":"IT",
    "sg:address":"S.s. 10 Padana Ovest Zona Ind. 15029 Solero",
    "sg:city":"Solero",
    "sg:orig_category":"Polyurethane Adhesives",
    "sg:phone":"+39 0131 217408",
    "sg:postcode":"15029",
    "sg:province":"Alessandria",
    "wof:name":"Al.p.a.s. Srl",
    "wof:placetype":"venue"
},
  "geometry": {"coordinates":[8.6169509888,44.9132156372],"type":"Point"}
}