{
  "type": "Feature",
  "properties": {
    "addr:full":"30020 Marcon Marcon Venezia 30020",
    "addr:postcode":"30020;30020",
    "iso:country":"IT",
    "sg:address":"30020 Marcon",
    "sg:city":"Marcon",
    "sg:orig_category":"Servizi E Lavori Per Arredamento E Industria Del Legno",
    "sg:phone":"+39 041 595 0965",
    "sg:postcode":"30020",
    "sg:province":"Venezia",
    "wof:name":"Top Legno S.r.l.",
    "wof:placetype":"venue"
},
  "geometry": {"coordinates":[12.29197,45.546219],"type":"Point"}
}