{
  "type": "Feature",
  "properties": {
    "iso:country":"IT",
    "sg:address":"20125 Milano",
    "sg:city":"Milano",
    "sg:orig_category":"Elettrodomestici - Vendita Al Dettaglio",
    "sg:phone":"+39 02 688 4540",
    "sg:postcode":"20125",
    "sg:province":"Milano",
    "wof:name":"Spinelli Roberto Snc",
    "wof:placetype":"venue"
},
  "geometry": {"coordinates":[9.192922,45.492645],"type":"Point"}
}