{
  "type": "Feature",
  "properties": {
    "iso:country":"IT",
    "sg:address":"20010 Ossona",
    "sg:city":"Ossona",
    "sg:orig_category":"Dolciumi E Gelati",
    "sg:phone":"+39 02 9038 0651",
    "sg:postcode":"20010",
    "sg:province":"Milano",
    "wof:name":"Dolcissimo S.r.l.",
    "wof:placetype":"venue"
},
  "geometry": {"coordinates":[9.263186,45.497051],"type":"Point"}
}