{
  "type": "Feature",
  "properties": {
    "iso:country":"IT",
    "sg:address":"70021 Acquaviva Delle Fonti",
    "sg:city":"Acquaviva delle Fonti",
    "sg:classifiers":[
        {
            "category":"Farming",
            "subcategory":"Fish & Marine Products",
            "type":"Manufacturing & Wholesale Goods"
        }
    ],
    "sg:phone":"+39 080 775355",
    "sg:postcode":"70021",
    "sg:province":"Bari",
    "sg:tags":[
        "packaging",
        "articles",
        "packing",
        "plastics",
        "article"
    ],
    "wof:name":"Ricicplast Srl",
    "wof:placetype":"venue"
},
  "geometry": {"coordinates":[16.8629932404,40.8821678162],"type":"Point"}
}