{
  "type": "Feature",
  "properties": {
    "iso:country":"IT",
    "sg:address":"20094 Corsico",
    "sg:city":"Corsico",
    "sg:orig_category":"Apparecchiature Ed Attrezzature Meccaniche. Elettronica Industriale, Prodotti E Apparecchiature. Impianti, Attrezzature E Forniture Sanitarie Ed Ospedaliere. Apparecchi, Attrezzature E Forniture Per C",
    "sg:phone":"+39 02 4510 9145",
    "sg:postcode":"20094",
    "sg:province":"Milano",
    "wof:name":"A.c. Service Srl",
    "wof:placetype":"venue"
},
  "geometry": {"coordinates":[9.114178,45.434864],"type":"Point"}
}