{
  "type": "Feature",
  "properties": {
    "addr:full":"05034 Ferentillo Ferentillo Terni 05034",
    "addr:postcode":"05034;05034",
    "iso:country":"IT",
    "sg:address":"05034 Ferentillo",
    "sg:city":"Ferentillo",
    "sg:orig_category":"Ristorazione E Locali Pubblici Affini. Servizi Per Lo Sport E Il Tempo Libero. Alberghi E Strutture Extra Alberghiere. Ristoranti Ed Esercizi Affini",
    "sg:phone":"+39 0744 780772",
    "sg:postcode":"05034",
    "sg:province":"Terni",
    "wof:name":"Albergo Ristorante Monterivoso",
    "wof:placetype":"venue"
},
  "geometry": {"coordinates":[12.828477,42.626431],"type":"Point"}
}