{
  "type": "Feature",
  "properties": {
    "iso:country":"IT",
    "sg:address":"4/6, Via Lago Ascianghi 04100 Latina",
    "sg:city":"Latina",
    "sg:classifiers":[
        {
            "category":"Retail",
            "subcategory":"Animal Services",
            "type":"Services"
        }
    ],
    "sg:phone":"+39 0773 663671",
    "sg:postcode":"04100",
    "sg:province":"Latina",
    "sg:tags":[
        "breeding"
    ],
    "wof:name":"Galanti Imo & C.",
    "wof:placetype":"venue"
},
  "geometry": {"coordinates":[12.909445,41.543056],"type":"Point"}
}