{
  "type": "Feature",
  "properties": {
    "iso:country":"IT",
    "sg:address":"24021 Albino",
    "sg:city":"Albino",
    "sg:orig_category":"Servizi E Lavori Per Ecologia E Smaltimento Rifiuti. Termotecnica E Riscaldamento, Apparecchiature E Servizi. Servizi Ausiliari Di Sorveglianza, Manutenzione E Pulizia",
    "sg:phone":"+39 035 753698",
    "sg:postcode":"24021",
    "sg:province":"Bergamo",
    "sg:website":"http://www.lospazzacamino.it",
    "wof:name":"Lo Spazzacamino Di Zanetti & Zanetti",
    "wof:placetype":"venue"
},
  "geometry": {"coordinates":[9.834871,45.756577],"type":"Point"}
}