{
  "type": "Feature",
  "properties": {
    "iso:country":"IT",
    "sg:address":"60127 Ancona",
    "sg:city":"Ancona",
    "sg:orig_category":"Servizi E Lavori Per Ecologia E Smaltimento Rifiuti. Arte Ed Artigianato Artistico. Servizi Ausiliari Di Sorveglianza, Manutenzione E Pulizia",
    "sg:phone":"+39 071 281 1355",
    "sg:postcode":"60127",
    "sg:province":"Ancona",
    "wof:name":"Portofranco Di Moretti Massimo & C. Snc",
    "wof:placetype":"venue"
},
  "geometry": {"coordinates":[13.50328,43.59621],"type":"Point"}
}