{
  "type": "Feature",
  "properties": {
    "iso:country":"IT",
    "sg:address":"70010 Turi",
    "sg:city":"Turi",
    "sg:orig_category":"Distributors: Automatici - Commercio E Gestione",
    "sg:phone":"+39 080 891 2872",
    "sg:postcode":"70010",
    "sg:province":"Bari",
    "wof:name":"Break Service Srl",
    "wof:placetype":"venue"
},
  "geometry": {"coordinates":[16.949396,40.887417],"type":"Point"}
}