{
  "type": "Feature",
  "properties": {
    "addr:full":"00047 Marino Marino Roma 00047",
    "addr:postcode":"00047;00047",
    "addr:street":"Marino Roma",
    "iso:country":"IT",
    "sg:address":"00047 Marino",
    "sg:city":"Marino",
    "sg:orig_category":"Abbigliamento Intimo, Calze E Costumi Da Bagno",
    "sg:phone":"+39 06 935 2724",
    "sg:postcode":"00047",
    "sg:province":"Roma",
    "wof:name":"Fra-pri Dei Fratelli Prisco",
    "wof:placetype":"venue"
},
  "geometry": {"coordinates":[12.610842,41.776707],"type":"Point"}
}