{
  "type": "Feature",
  "properties": {
    "addr:full":"Via Cima D' Aosta 73040 Melissano Melissano Lecce 73040",
    "addr:postcode":"73040;73040",
    "addr:street":"Via Cima D ' Aosta",
    "iso:country":"IT",
    "sg:address":"Via Cima D' Aosta 73040 Melissano",
    "sg:city":"Melissano",
    "sg:classifiers":[
        {
            "category":"Banks & Credit Unions",
            "subcategory":"Investment Brokerage",
            "type":"Services"
        }
    ],
    "sg:phone":"+39 0833 588570",
    "sg:postcode":"73040",
    "sg:province":"Lecce",
    "sg:tags":[
        "children's",
        "stocking"
    ],
    "sg:website":"www.megatex.it",
    "wof:name":"Megatex S.r.l.",
    "wof:placetype":"venue"
},
  "geometry": {"coordinates":[18.117861,39.977661],"type":"Point"}
}