{
  "type": "Feature",
  "properties": {
    "iso:country":"IT",
    "sg:address":"5, Via Lamarmora 23900 Lecco",
    "sg:city":"Lecco",
    "sg:classifiers":[
        {
            "category":"Manufacturing",
            "subcategory":"Motor Vehicles & Parts",
            "type":"Manufacturing & Wholesale Goods"
        }
    ],
    "sg:phone":"+39 0341 250496",
    "sg:postcode":"23900",
    "sg:province":"Lecco",
    "sg:tags":[
        "engine"
    ],
    "wof:name":"Me.p.la. (s.r.l.)",
    "wof:placetype":"venue"
},
  "geometry": {"coordinates":[9.407782,45.856716],"type":"Point"}
}