{
  "type": "Feature",
  "properties": {
    "iso:country":"IT",
    "sg:address":"50127 Firenze",
    "sg:city":"Firenze",
    "sg:orig_category":"Impiantistica E Prodotti Tecnologici Per Edilizia. Elettrotecnica Professionale E Di Consumo. Telecomunicazioni E Telefonia, Impianti, Apparecchi E Servizi",
    "sg:phone":"+39 055 430420",
    "sg:postcode":"50127",
    "sg:province":"Firenze",
    "wof:name":"T.im.e Di Corsi & Talini",
    "wof:placetype":"venue"
},
  "geometry": {"coordinates":[11.224044,43.803814],"type":"Point"}
}