{
  "type": "Feature",
  "properties": {
    "iso:country":"IT",
    "sg:address":"21100 Varese",
    "sg:city":"Varese",
    "sg:classifiers":[
        {
            "category":"Restaurant",
            "type":"Food & Drink"
        }
    ],
    "sg:phone":"+39 0332 223537",
    "sg:postcode":"21100",
    "sg:province":"Varese",
    "sg:tags":[
        "auxiliary",
        "entertainment",
        "premises",
        "related",
        "catering",
        "similar",
        "public",
        "restaurants"
    ],
    "wof:name":"Vela Srl Hotel Plaza",
    "wof:placetype":"venue"
},
  "geometry": {"coordinates":[8.80387,45.826042],"type":"Point"}
}