{
  "type": "Feature",
  "properties": {
    "iso:country":"IT",
    "sg:address":"20063 Cernusco Sul Naviglio",
    "sg:city":"Cernusco sul Naviglio",
    "sg:orig_category":"Materiali E Componenti Elettrotecnici. Elettrotecnica Industriale, Prodotti E Apparecchiature",
    "sg:phone":"+39 02 924 2103",
    "sg:postcode":"20063",
    "sg:province":"Milano",
    "wof:name":"Delta I (s.r.l.)",
    "wof:placetype":"venue"
},
  "geometry": {"coordinates":[9.289932,45.517666],"type":"Point"}
}