{
  "type": "Feature",
  "properties": {
    "addr:full":"Via Dell' Artigianato 16 22079 Villa Guardia Villa Guardia Como 22079",
    "addr:housenumber":"16;guardia",
    "addr:postcode":"22079;22079",
    "addr:street":"Via Dell ' Artigianato;Guardia",
    "iso:country":"IT",
    "sg:address":"Via Dell' Artigianato 16 22079 Villa Guardia",
    "sg:city":"Villa Guardia",
    "sg:orig_category":"Wire Netting",
    "sg:phone":"+39 031 480350",
    "sg:postcode":"22079",
    "sg:province":"Como",
    "sg:website":"www.ttmrossi.it",
    "wof:name":"Tessitura Tele Metalliche Rossi Oli Viero Srl",
    "wof:placetype":"venue"
},
  "geometry": {"coordinates":[9.033789,45.769905],"type":"Point"}
}