{
  "type": "Feature",
  "properties": {
    "iso:country":"IT",
    "sg:address":"57123 Livorno",
    "sg:city":"Livorno",
    "sg:orig_category":"Amianto - Bonifica E Smantellamento",
    "sg:phone":"+39 0586 405272",
    "sg:postcode":"57123",
    "sg:province":"Livorno",
    "sg:website":"http://www.labromare.it",
    "wof:name":"Faro Verde Srl",
    "wof:placetype":"venue"
},
  "geometry": {"coordinates":[10.310501,43.577747],"type":"Point"}
}