{
  "type": "Feature",
  "properties": {
    "iso:country":"IT",
    "sg:address":"25017 Lonato",
    "sg:city":"Lonato",
    "sg:orig_category":"Dolciumi E Gelati",
    "sg:phone":"+39 030 991 4196",
    "sg:postcode":"25017",
    "sg:province":"Brescia",
    "wof:name":"Garda Miele Srl",
    "wof:placetype":"venue"
},
  "geometry": {"coordinates":[10.48619,45.462898],"type":"Point"}
}