{
  "type": "Feature",
  "properties": {
    "iso:country":"IT",
    "sg:address":"06034 Foligno",
    "sg:city":"Foligno",
    "sg:orig_category":"Imprese Di Costruzioni Civili Ed Industriali. Servizi Ausiliari Di Sorveglianza, Manutenzione E Pulizia",
    "sg:phone":"+39 0742 39291",
    "sg:postcode":"06034",
    "sg:province":"Perugia",
    "sg:website":"http://www.colombocentrocostruzioni.it",
    "wof:name":"Colombo Centro Costruzioni",
    "wof:placetype":"venue"
},
  "geometry": {"coordinates":[12.307821,43.059982],"type":"Point"}
}