{
  "type": "Feature",
  "properties": {
    "addr:full":"9, Via Grosso 10080 Rivara Rivara Torino 10080",
    "addr:postcode":"10080;10080",
    "addr:street":"Via Grosso",
    "iso:country":"IT",
    "sg:address":"9, Via Grosso 10080 Rivara",
    "sg:city":"Rivara",
    "sg:classifiers":[
        {
            "category":"Professional",
            "subcategory":"Engineering",
            "type":"Services"
        }
    ],
    "sg:phone":"+39 39012448058",
    "sg:postcode":"10080",
    "sg:province":"Torino",
    "sg:tags":[
        "machine",
        "-",
        "mechanical"
    ],
    "wof:name":"O.m.b.m. (s.r.l.)",
    "wof:placetype":"venue"
},
  "geometry": {"coordinates":[7.686619,45.07056],"type":"Point"}
}