{
  "type": "Feature",
  "properties": {
    "iso:country":"IT",
    "sg:address":"104, Via Roma 31020 San Vendemiano",
    "sg:city":"San Vendemiano",
    "sg:classifiers":[
        {
            "category":"Shopping",
            "subcategory":"Clothing, Apparel, & Fashions",
            "type":"Retail Goods"
        }
    ],
    "sg:phone":"+39 0438 400037",
    "sg:postcode":"31020",
    "sg:province":"Treviso",
    "sg:tags":[
        "clothes"
    ],
    "wof:name":"De Marchi Sport S.r.l.",
    "wof:placetype":"venue"
},
  "geometry": {"coordinates":[12.329108,45.899975],"type":"Point"}
}