{
  "type": "Feature",
  "properties": {
    "addr:full":"20010 Bareggio Bareggio Milano 20010",
    "addr:postcode":"20010;20010",
    "iso:country":"IT",
    "sg:address":"20010 Bareggio",
    "sg:city":"Bareggio",
    "sg:orig_category":"Specchi",
    "sg:phone":"+39 02 901 3019",
    "sg:postcode":"20010",
    "sg:province":"Milano",
    "wof:name":"Vetreria Cislaghi Snc Di Cislaghi Carlo & C.",
    "wof:placetype":"venue"
},
  "geometry": {"coordinates":[9.004726,45.485695],"type":"Point"}
}