{
  "type": "Feature",
  "properties": {
    "iso:country":"IT",
    "sg:address":"91025 Marsala",
    "sg:city":"Marsala",
    "sg:orig_category":"Servizi E Lavori Per Ecologia E Smaltimento Rifiuti",
    "sg:phone":"+39 0923 723246",
    "sg:postcode":"91025",
    "sg:province":"Trapani",
    "wof:name":"Bytek Di Bonomo Nicol\u00d2",
    "wof:placetype":"venue"
},
  "geometry": {"coordinates":[12.453517,37.796223],"type":"Point"}
}