{
  "type": "Feature",
  "properties": {
    "iso:country":"IT",
    "sg:address":"Via Sicilia 1 56021 Cascina",
    "sg:city":"Cascina",
    "sg:classifiers":[
        {
            "category":"Home & Garden",
            "subcategory":"Furniture",
            "type":"Retail Goods"
        }
    ],
    "sg:phone":"+39 050 701719",
    "sg:postcode":"56021",
    "sg:province":"Pisa",
    "sg:website":"www.ombrellificiotoscano.com",
    "wof:name":"Ombrellificio Toscano Srl",
    "wof:placetype":"venue"
},
  "geometry": {"coordinates":[10.54478,43.666508],"type":"Point"}
}