{
  "type": "Feature",
  "properties": {
    "iso:country":"IT",
    "sg:address":"23023 Chiesa In Valmalenco",
    "sg:city":"Chiesa in Valmalenco",
    "sg:orig_category":"Marmo Ed Affini - Lavorazione",
    "sg:phone":"+39 0342 451473",
    "sg:postcode":"23023",
    "sg:province":"Sondrio",
    "sg:website":"http://www.italexport.it",
    "wof:name":"Ital Export Valmalenco Snc",
    "wof:placetype":"venue"
},
  "geometry": {"coordinates":[9.845535,46.256145],"type":"Point"}
}