{
  "type": "Feature",
  "properties": {
    "iso:country":"IT",
    "sg:address":"2/4, Via Rizzi Bruno 37012 Bussolengo",
    "sg:city":"Bussolengo",
    "sg:classifiers":[
        {
            "category":"Communications",
            "subcategory":"Newspaper",
            "type":"Services"
        }
    ],
    "sg:phone":"+39 045 676 0555",
    "sg:postcode":"37012",
    "sg:province":"Verona",
    "sg:tags":[
        "advertising"
    ],
    "wof:name":"Adpresscommunications S.p.a.",
    "wof:placetype":"venue"
},
  "geometry": {"coordinates":[10.848565,45.445305],"type":"Point"}
}