{
  "type": "Feature",
  "properties": {
    "addr:full":"25030 Rudiano Rudiano Brescia 25030",
    "addr:postcode":"25030;25030",
    "iso:country":"IT",
    "sg:address":"25030 Rudiano",
    "sg:city":"Rudiano",
    "sg:orig_category":"Legatorie",
    "sg:phone":"+39 030 716202",
    "sg:postcode":"25030",
    "sg:province":"Brescia",
    "wof:name":"G.a.m. Di Mena Angelo & C. Snc",
    "wof:placetype":"venue"
},
  "geometry": {"coordinates":[9.880263,45.498222],"type":"Point"}
}