{
  "type": "Feature",
  "properties": {
    "addr:full":"25089 Villanuova Sul Clisi Villanuova sul Clisi Brescia 25089",
    "addr:postcode":"25089;25089",
    "iso:country":"IT",
    "sg:address":"25089 Villanuova Sul Clisi",
    "sg:city":"Villanuova sul Clisi",
    "sg:orig_category":"Fustelle E Fustellatrici",
    "sg:phone":"+39 036 537 3593",
    "sg:postcode":"25089",
    "sg:province":"Brescia",
    "wof:name":"Fustellificio Gardabox",
    "wof:placetype":"venue"
},
  "geometry": {"coordinates":[10.4607219696,45.6040496826],"type":"Point"}
}