{
  "type": "Feature",
  "properties": {
    "addr:full":"Vle Della Vittoria, 5/3 20058 Villasanta Villasanta Milano 20058",
    "addr:housenumber":"5 / 3",
    "addr:postcode":"20058;20058",
    "addr:street":"Vle Della Vittoria",
    "iso:country":"IT",
    "sg:address":"Vle Della Vittoria, 5/3 20058 Villasanta",
    "sg:city":"Villasanta",
    "sg:classifiers":[
        {
            "category":"Sports & Exercise",
            "subcategory":"Race Track",
            "type":"Entertainment"
        }
    ],
    "sg:phone":"+39 039 205941",
    "sg:postcode":"20058",
    "sg:province":"Milano",
    "sg:tags":[
        "tincture"
    ],
    "sg:website":"www.rossilorenzoefigli.it",
    "wof:name":"Rossi Lorenzo & Figli Snc Di Rossi Luigi & C.",
    "wof:placetype":"venue"
},
  "geometry": {"coordinates":[9.188141,45.463688],"type":"Point"}
}