{
  "type": "Feature",
  "properties": {
    "iso:country":"IT",
    "sg:address":"27022 Casorate Primo",
    "sg:city":"Casorate Primo",
    "sg:orig_category":"Carrelli Elevatori E Trasportatori - Commercio E Noleggio",
    "sg:phone":"+39 02 9005 6182",
    "sg:postcode":"27022",
    "sg:province":"Pavia",
    "wof:name":"Pancar Sas Di G. Pangallo",
    "wof:placetype":"venue"
},
  "geometry": {"coordinates":[9.021405,45.310802],"type":"Point"}
}