{
  "type": "Feature",
  "properties": {
    "addr:full":"Via Santa Maria Di Leuca 10 73049 Ruffano Ruffano Lecce 73049",
    "addr:housenumber":"10",
    "addr:postcode":"73049;73049",
    "addr:street":"Via Santa Maria Di Leuca",
    "iso:country":"IT",
    "sg:address":"Via Santa Maria Di Leuca 10 73049 Ruffano",
    "sg:city":"Ruffano",
    "sg:classifiers":[
        {
            "category":"Shopping",
            "subcategory":"Shoes",
            "type":"Retail Goods"
        }
    ],
    "sg:phone":"+39 0833 691099",
    "sg:postcode":"73049",
    "sg:province":"Lecce",
    "sg:tags":[
        "men's",
        "boot"
    ],
    "wof:name":"Eurovimar S.r.l.",
    "wof:placetype":"venue"
},
  "geometry": {"coordinates":[18.2172088623,39.951385498],"type":"Point"}
}