{
  "type": "Feature",
  "properties": {
    "iso:country":"IT",
    "sg:address":"Via Montini 151/5; Lumezzane; 25065",
    "sg:city":"Lumezzane",
    "sg:classifiers":[
        {
            "category":"Banks & Credit Unions",
            "subcategory":"Bank",
            "type":"Services"
        }
    ],
    "sg:phone":"+39 030 828870",
    "sg:postcode":"25065",
    "sg:province":"Brescia",
    "wof:name":"Istituto Bancario, San Paolo Di Torino Spa",
    "wof:placetype":"venue"
},
  "geometry": {"coordinates":[10.274949,45.649891],"type":"Point"}
}