{
  "type": "Feature",
  "properties": {
    "iso:country":"IT",
    "sg:address":"26862 Guardamiglio",
    "sg:city":"Guardamiglio",
    "sg:orig_category":"Depurazione E Trattamento Delle Acque - Impianti Ed Apparecchi",
    "sg:phone":"+39 0377 451 1262",
    "sg:postcode":"26862",
    "sg:province":"Lodi",
    "sg:website":"http://www.acqualinepe.com",
    "wof:name":"I.s.e.a.",
    "wof:placetype":"venue"
},
  "geometry": {"coordinates":[9.677205,45.109936],"type":"Point"}
}