{
  "type": "Feature",
  "properties": {
    "iso:country":"IT",
    "sg:address":"95131 Catania",
    "sg:city":"Catania",
    "sg:orig_category":"Banche E Servizi Finanziari",
    "sg:phone":"+39 095 314721",
    "sg:postcode":"95131",
    "sg:province":"Catania",
    "wof:name":"Caldarella Sebastiano",
    "wof:placetype":"venue"
},
  "geometry": {"coordinates":[15.085965,37.527954],"type":"Point"}
}