{
  "type": "Feature",
  "properties": {
    "iso:country":"IT",
    "sg:address":"58019 Monte Argentario",
    "sg:city":"Monte Argentario",
    "sg:orig_category":"Impianti Sportivi E Ricreativi - Esercizio",
    "sg:phone":"+39 0564 810145",
    "sg:postcode":"58019",
    "sg:province":"Grosseto",
    "wof:name":"Cala Galera Diving Center",
    "wof:placetype":"venue"
},
  "geometry": {"coordinates":[11.120657,42.435669],"type":"Point"}
}