{
  "type": "Feature",
  "properties": {
    "iso:country":"IT",
    "sg:address":"40122 Bologna",
    "sg:city":"Bologna",
    "sg:orig_category":"Macchine, Impianti E Forniture Per Industria Grafica, Cartaria E Cartotecnica. Automazione E Macchine Per Ufficio",
    "sg:phone":"+39 051 558770",
    "sg:postcode":"40122",
    "sg:province":"Bologna",
    "wof:name":"Cattabriga E Cotti Snc",
    "wof:placetype":"venue"
},
  "geometry": {"coordinates":[11.333766,44.498585],"type":"Point"}
}