{
  "type": "Feature",
  "properties": {
    "iso:country":"IT",
    "sg:address":"50063 Figline Valdarno",
    "sg:city":"Figline Valdarno",
    "sg:orig_category":"Argenteria - Lavorazione E Ingrosso",
    "sg:phone":"+39 055 915 4012",
    "sg:postcode":"50063",
    "sg:province":"Firenze",
    "sg:website":"http://www.argenterielatorre.com",
    "wof:name":"Argenterie La Torre Srl",
    "wof:placetype":"venue"
},
  "geometry": {"coordinates":[11.411205,43.619465],"type":"Point"}
}