{
  "type": "Feature",
  "properties": {
    "addr:full":"49, Via Enrico Fermi 36057 Arcugnano Arcugnano Vicenza 36057",
    "addr:postcode":"36057;36057",
    "addr:street":"Via Enrico Fermi",
    "iso:country":"IT",
    "sg:address":"49, Via Enrico Fermi 36057 Arcugnano",
    "sg:city":"Arcugnano",
    "sg:classifiers":[
        {
            "category":"Utilities",
            "subcategory":"Electric",
            "type":"Services"
        }
    ],
    "sg:phone":"+39 0444 962964",
    "sg:postcode":"36057",
    "sg:province":"Vicenza",
    "sg:tags":[
        "component",
        "electronic"
    ],
    "wof:name":"E.c.s. Elettronica Circuiti Stampati (s.r.l.)",
    "wof:placetype":"venue"
},
  "geometry": {"coordinates":[11.508529,45.508999],"type":"Point"}
}