{
  "type": "Feature",
  "properties": {
    "iso:country":"IT",
    "sg:address":"00171 Roma",
    "sg:city":"Roma",
    "sg:orig_category":"Carpenterie Meccaniche",
    "sg:phone":"+39 06 2180 7678",
    "sg:postcode":"00171",
    "sg:province":"Roma",
    "wof:name":"Antonio Corvaglia Srl",
    "wof:placetype":"venue"
},
  "geometry": {"coordinates":[12.563763,41.891361],"type":"Point"}
}