{
  "type": "Feature",
  "properties": {
    "iso:country":"IT",
    "sg:address":"95041 Caltagirone",
    "sg:city":"Caltagirone",
    "sg:orig_category":"Alberghi",
    "sg:phone":"+39 0933 23898",
    "sg:postcode":"95041",
    "sg:province":"Catania",
    "wof:name":"Bed & Breakfast 'antico Palmento' Di Sellaroli E.",
    "wof:placetype":"venue"
},
  "geometry": {"coordinates":[14.383384,37.150536],"type":"Point"}
}