{
  "type": "Feature",
  "properties": {
    "iso:country":"IT",
    "sg:address":"Corso Vittorio Emanuele, 30; Mantova; 46100",
    "sg:city":"Mantova",
    "sg:classifiers":[
        {
            "category":"Industrial Area",
            "type":"Public Place"
        }
    ],
    "sg:phone":"+39 390 376 3311",
    "sg:postcode":"46100",
    "sg:province":"Mantova",
    "sg:tags":[
        "large",
        "private"
    ],
    "sg:website":"www.bam.it",
    "wof:name":"Banca Agricola Mantovana Scrl",
    "wof:placetype":"venue"
},
  "geometry": {"coordinates":[10.787320137,45.1575622559],"type":"Point"}
}