{
  "type": "Feature",
  "properties": {
    "iso:country":"IT",
    "sg:address":"21050 Cairate",
    "sg:city":"Cairate",
    "sg:orig_category":"Legno E Semilavorati. Apparecchiature E Sistemi Per Magazzinaggio E Movimentazione",
    "sg:phone":"+39 0331 311352",
    "sg:postcode":"21050",
    "sg:province":"Varese",
    "wof:name":"Autotrasporti Sommella",
    "wof:placetype":"venue"
},
  "geometry": {"coordinates":[8.798387,45.676182],"type":"Point"}
}