{
  "type": "Feature",
  "properties": {
    "iso:country":"IT",
    "sg:address":"20041 Agrate Brianza",
    "sg:city":"Agrate Brianza",
    "sg:orig_category":"Studi E Consulenze Amministrative, Commerciali E Aziendali. Studi E Consulenze Tecniche E Industriali. Consulenze Tecniche, Amministrative E Perizie",
    "sg:phone":"+39 039 634701",
    "sg:postcode":"20041",
    "sg:province":"Milano",
    "sg:website":"http://www.american-appraisal.it",
    "wof:name":"American Appraisal Holding Spa",
    "wof:placetype":"venue"
},
  "geometry": {"coordinates":[9.334373,45.571369],"type":"Point"}
}