{
  "type": "Feature",
  "properties": {
    "iso:country":"IT",
    "sg:address":"10, Viale Dell' Industria 38068 Rovereto",
    "sg:city":"Rovereto",
    "sg:classifiers":[
        {
            "category":"Manufacturing",
            "subcategory":"Metals",
            "type":"Manufacturing & Wholesale Goods"
        }
    ],
    "sg:phone":"+39 0464 421505",
    "sg:postcode":"38068",
    "sg:province":"Trento",
    "sg:tags":[
        "processing"
    ],
    "wof:name":"Gal Tre S.r.l.",
    "wof:placetype":"venue"
},
  "geometry": {"coordinates":[11.0208463669,45.8716278076],"type":"Point"}
}