{
  "type": "Feature",
  "properties": {
    "addr:full":"Via Novara 73042 Casarano Casarano Lecce 73042",
    "addr:postcode":"73042;73042",
    "addr:street":"Via Novara",
    "iso:country":"IT",
    "sg:address":"Via Novara 73042 Casarano",
    "sg:city":"Casarano",
    "sg:classifiers":[
        {
            "category":"Personal",
            "subcategory":"Shoe Repair & Shine",
            "type":"Services"
        }
    ],
    "sg:phone":"+39 0833 501622",
    "sg:postcode":"73042",
    "sg:province":"Lecce",
    "sg:tags":[
        "leather"
    ],
    "wof:name":"Calzaturificio Romar Srl",
    "wof:placetype":"venue"
},
  "geometry": {"coordinates":[18.174015,40.353291],"type":"Point"}
}