{
  "type": "Feature",
  "properties": {
    "iso:country":"IT",
    "sg:address":"16141 Genova",
    "sg:city":"Genova",
    "sg:orig_category":"Arte Ed Artigianato Artistico",
    "sg:phone":"+39 010 836 1449",
    "sg:postcode":"16141",
    "sg:province":"Genova",
    "wof:name":"Fratelli Bertozzi E Figlio Di M. Bertozzi",
    "wof:placetype":"venue"
},
  "geometry": {"coordinates":[8.976985,44.438999],"type":"Point"}
}