{
  "type": "Feature",
  "properties": {
    "iso:country":"IT",
    "sg:address":"Via Cella 70; Piacenza",
    "sg:classifiers":[
        {
            "category":"Banks & Credit Unions",
            "subcategory":"Bank",
            "type":"Services"
        }
    ],
    "sg:phone":"+39 0523 453168",
    "wof:name":"Banca Agricola Mantovana Scarl",
    "wof:placetype":"venue"
},
  "geometry": {"coordinates":[9.671838,45.045307],"type":"Point"}
}