{
  "type": "Feature",
  "properties": {
    "iso:country":"IT",
    "sg:address":"Via Cavour 9 31013 Codogne'",
    "sg:classifiers":[
        {
            "category":"Manufacturing",
            "subcategory":"Rubber & Plastics",
            "type":"Manufacturing & Wholesale Goods"
        }
    ],
    "sg:phone":"+39 0438 794784",
    "sg:postcode":"31013",
    "sg:province":"Treviso",
    "sg:tags":[
        "ash",
        "furnace"
    ],
    "sg:website":"www.carmetitalia.it",
    "wof:name":"Car - Met Spa",
    "wof:placetype":"venue"
},
  "geometry": {"coordinates":[12.242072,45.666286],"type":"Point"}
}