{
  "type": "Feature",
  "properties": {
    "addr:full":"00175 Roma Roma Roma 00175",
    "addr:postcode":"00175;00175",
    "iso:country":"IT",
    "sg:address":"00175 Roma",
    "sg:city":"Roma",
    "sg:orig_category":"Forniture Per Attivita' Industriali. Servizi Ausiliari Di Sorveglianza, Manutenzione E Pulizia",
    "sg:phone":"+39 06 241 7521",
    "sg:postcode":"00175",
    "sg:province":"Roma",
    "sg:website":"http://www.derosametalli.it",
    "wof:name":"De Rosa Metalli",
    "wof:placetype":"venue"
},
  "geometry": {"coordinates":[12.5447835922,41.8724517822],"type":"Point"}
}