{
  "type": "Feature",
  "properties": {
    "iso:country":"IT",
    "sg:address":"47100 Forli'",
    "sg:orig_category":"Impianti Sportivi E Ricreativi - Attrezzature E Costruzione",
    "sg:phone":"+39 0543 85429",
    "sg:postcode":"47100",
    "sg:province":"Forl\u00ec-Cesena",
    "sg:website":"http://www.olimpiacostruzioni.it",
    "wof:name":"Olimpia Costruzione Srl",
    "wof:placetype":"venue"
},
  "geometry": {"coordinates":[11.980461,43.994766],"type":"Point"}
}