{
  "type": "Feature",
  "properties": {
    "iso:country":"IT",
    "sg:address":"64011 Alba Adriatica",
    "sg:city":"Alba Adriatica",
    "sg:orig_category":"Ristorazione E Locali Pubblici Affini. Ristoranti Ed Esercizi Affini. Servizi Ausiliari Di Ristorazione E Di Intrattenimento",
    "sg:phone":"+39 0861 712467",
    "sg:postcode":"64011",
    "sg:province":"Teramo",
    "wof:name":"Albergo Selene Snc Di Picchini L. & C.",
    "wof:placetype":"venue"
},
  "geometry": {"coordinates":[13.920199,42.828377],"type":"Point"}
}