{
  "type": "Feature",
  "properties": {
    "iso:country":"IT",
    "sg:address":"Via Garibaldi 17, 13900 Biella, Bi",
    "sg:city":"Biella",
    "sg:classifiers":[
        {
            "category":"Banks & Credit Unions",
            "subcategory":"Bank",
            "type":"Services"
        }
    ],
    "sg:phone":"+39 015 35081",
    "sg:postcode":"13900",
    "sg:province":"Biella",
    "wof:name":"Fondazione Cassa Di Risparmio Di Biella",
    "wof:placetype":"venue"
},
  "geometry": {"coordinates":[8.05827,45.562836],"type":"Point"}
}