{
  "type": "Feature",
  "properties": {
    "iso:country":"IT",
    "sg:address":"Via Parri 212 47023 Cesena",
    "sg:city":"Cesena",
    "sg:classifiers":[
        {
            "category":"Manufacturing",
            "subcategory":"Electronics",
            "type":"Manufacturing & Wholesale Goods"
        }
    ],
    "sg:phone":"+39 0547 333346",
    "sg:postcode":"47023",
    "sg:province":"Forl\u00ec-Cesena",
    "sg:tags":[
        "large",
        "machine",
        "industrial",
        "electrical",
        "equipment"
    ],
    "wof:name":"Co.el.me. Spa",
    "wof:placetype":"venue"
},
  "geometry": {"coordinates":[12.216054,44.151691],"type":"Point"}
}