{
  "type": "Feature",
  "properties": {
    "iso:country":"IT",
    "sg:address":"14045 Incisa Scapaccino",
    "sg:city":"Incisa Scapaccino",
    "sg:classifiers":[
        {
            "category":"Health Services",
            "subcategory":"Nursing And Care Facility",
            "type":"Services"
        }
    ],
    "sg:phone":"+39 0141 747074",
    "sg:postcode":"14045",
    "sg:province":"Asti",
    "sg:tags":[
        "case",
        "riposo",
        "di"
    ],
    "wof:name":"Villa Cora Srl",
    "wof:placetype":"venue"
},
  "geometry": {"coordinates":[8.376466,44.795856],"type":"Point"}
}