{
  "type": "Feature",
  "properties": {
    "iso:country":"IT",
    "sg:address":"10063 Perosa Argentina",
    "sg:city":"Perosa Argentina",
    "sg:orig_category":"Motori Ed Organi Di Trasmissione",
    "sg:phone":"+39 0121 803820",
    "sg:postcode":"10063",
    "sg:province":"Torino",
    "wof:name":"Martin E C. Srl",
    "wof:placetype":"venue"
},
  "geometry": {"coordinates":[7.1925673485,44.9557991028],"type":"Point"}
}