{
  "type": "Feature",
  "properties": {
    "addr:full":"Via Martiri 12 28075 Grignasco Grignasco Novara 28075",
    "addr:housenumber":"12",
    "addr:postcode":"28075;28075",
    "addr:street":"Via Martiri",
    "iso:country":"IT",
    "sg:address":"Via Martiri 12 28075 Grignasco",
    "sg:city":"Grignasco",
    "sg:classifiers":[
        {
            "category":"Government",
            "subcategory":"Court House",
            "type":"Public Place"
        }
    ],
    "sg:phone":"+39 0163 418869",
    "sg:postcode":"28075",
    "sg:province":"Novara",
    "sg:tags":[
        "accommodation",
        "furniture"
    ],
    "sg:website":"www.sopromiglom.com",
    "wof:name":"Sopromi Glom Srl",
    "wof:placetype":"venue"
},
  "geometry": {"coordinates":[8.336536,45.682343],"type":"Point"}
}