{
  "type": "Feature",
  "properties": {
    "addr:full":"44042 Cento Cento Ferrara 44042",
    "addr:postcode":"44042;44042",
    "iso:country":"IT",
    "sg:address":"44042 Cento",
    "sg:city":"Cento",
    "sg:orig_category":"Legno E Semilavorati. Macchine E Forniture Per Arredamento E Industria Del Legno. Hobbistica",
    "sg:phone":"+39 051 902605",
    "sg:postcode":"44042",
    "sg:province":"Ferrara",
    "sg:website":"http://www.superutensileria.it",
    "wof:name":"Super Utensileria Snc",
    "wof:placetype":"venue"
},
  "geometry": {"coordinates":[11.291046,44.748875],"type":"Point"}
}