{
  "type": "Feature",
  "properties": {
    "iso:country":"IT",
    "sg:address":"10154 Torino",
    "sg:city":"Torino",
    "sg:orig_category":"Automobili E Mezzi Di Trasporto. Riparazione Dei Mezzi Di Trasporto",
    "sg:phone":"+39 011 241 2301",
    "sg:postcode":"10154",
    "sg:province":"Torino",
    "sg:website":"http://www.nuovaitalcar.it",
    "wof:name":"Nuova Italcar Spa",
    "wof:placetype":"venue"
},
  "geometry": {"coordinates":[7.830617,45.487606],"type":"Point"}
}