{
  "type": "Feature",
  "properties": {
    "iso:country":"IT",
    "sg:address":"3, V. F. De Paolis, Loc Coste S. Agostino 64100 Teramo",
    "sg:city":"Teramo",
    "sg:classifiers":[
        {
            "category":"Sports & Exercise",
            "subcategory":"Playing Field",
            "type":"Entertainment"
        }
    ],
    "sg:phone":"+39 0861 211451",
    "sg:postcode":"64100",
    "sg:province":"Teramo",
    "sg:tags":[
        "game"
    ],
    "sg:website":"http://www.paginegialle.it/olympusproduction",
    "wof:name":"Gruppo Olympus Production",
    "wof:placetype":"venue"
},
  "geometry": {"coordinates":[13.70575,42.677277],"type":"Point"}
}