{
  "type": "Feature",
  "properties": {
    "addr:full":"22, Via John Kennedy 22060 Figino Serenza Figino Serenza Como 22060",
    "addr:housenumber":"serenza",
    "addr:postcode":"22060;22060",
    "addr:street":"Via John Kennedy;Como",
    "iso:country":"IT",
    "sg:address":"22, Via John Kennedy 22060 Figino Serenza",
    "sg:city":"Figino Serenza",
    "sg:classifiers":[
        {
            "category":"Home & Garden",
            "subcategory":"Home Furnishings",
            "type":"Retail Goods"
        }
    ],
    "sg:phone":"+39 39031780146",
    "sg:postcode":"22060",
    "sg:province":"Como",
    "sg:tags":[
        "household"
    ],
    "wof:name":"Radice Giovanni & Nipoti S.n.c.",
    "wof:placetype":"venue"
},
  "geometry": {"coordinates":[9.123761,45.74173],"type":"Point"}
}