{
  "type": "Feature",
  "properties": {
    "addr:full":"20010 Pogliano Milanese Pogliano Milanese Milano 20010",
    "addr:postcode":"20010;20010",
    "iso:country":"IT",
    "sg:address":"20010 Pogliano Milanese",
    "sg:city":"Pogliano Milanese",
    "sg:orig_category":"Fustelle E Fustellatrici",
    "sg:phone":"+39 02 934 1766",
    "sg:postcode":"20010",
    "sg:province":"Milano",
    "wof:name":"Ydeal Sas Di Crivelli Giuseppe & C.",
    "wof:placetype":"venue"
},
  "geometry": {"coordinates":[8.9894371033,45.5364761353],"type":"Point"}
}