{
  "type": "Feature",
  "properties": {
    "iso:country":"IT",
    "sg:address":"24062 Costa Volpino",
    "sg:city":"Costa Volpino",
    "sg:orig_category":"Elettrotecnica Industriale, Prodotti E Apparecchiature. Ricambi E Componenti Dei Mezzi Di Trasporto",
    "sg:phone":"+39 035 971819",
    "sg:postcode":"24062",
    "sg:province":"Bergamo",
    "wof:name":"A.b.m.",
    "wof:placetype":"venue"
},
  "geometry": {"coordinates":[10.115739,45.829376],"type":"Point"}
}