{
  "type": "Feature",
  "properties": {
    "addr:full":"00055 Ladispoli Ladispoli Roma 00055",
    "addr:postcode":"00055;roma 00055",
    "iso:country":"IT",
    "sg:address":"00055 Ladispoli",
    "sg:city":"Ladispoli",
    "sg:orig_category":"Servizi Per Lo Sport E Il Tempo Libero. Servizi Ausiliari Dei Mezzi Di Trasporto",
    "sg:phone":"+39 06 991 3796",
    "sg:postcode":"00055",
    "sg:province":"Roma",
    "wof:name":"Iazzi Silvano",
    "wof:placetype":"venue"
},
  "geometry": {"coordinates":[12.061181,41.956024],"type":"Point"}
}