{
  "type": "Feature",
  "properties": {
    "iso:country":"IT",
    "sg:address":"36030 Monte Di Malo",
    "sg:city":"Monte di Malo",
    "sg:orig_category":"Servizi E Lavori Industria Della Gomma. Servizi E Lavori Industria Delle Materie Plastiche. Forniture Per Edilizia E Lavori Pubblici",
    "sg:phone":"+39 0445 606939",
    "sg:postcode":"36030",
    "sg:province":"Vicenza",
    "wof:name":"Rimet A Division Of Praxair Surface Technologies Spa",
    "wof:placetype":"venue"
},
  "geometry": {"coordinates":[11.38868,45.655441],"type":"Point"}
}