{
  "type": "Feature",
  "properties": {
    "iso:country":"IT",
    "sg:address":"1/a, Via Ballabio 22070 Rovello Porro",
    "sg:city":"Rovello Porro",
    "sg:classifiers":[
        {
            "category":"Professional",
            "subcategory":"Printing & Photocopies",
            "type":"Services"
        }
    ],
    "sg:phone":"+39 02 9675 2491",
    "sg:postcode":"22070",
    "sg:province":"Como",
    "wof:name":"Tipolitografia Raimondi",
    "wof:placetype":"venue"
},
  "geometry": {"coordinates":[9.0854558945,45.8119659424],"type":"Point"}
}