{
  "type": "Feature",
  "properties": {
    "addr:full":"22070 Grandate Grandate Como 22070",
    "addr:postcode":"22070;22070",
    "iso:country":"IT",
    "sg:address":"22070 Grandate",
    "sg:city":"Grandate",
    "sg:orig_category":"Servizi E Lavori Per Arredamento E Industria Del Legno. Servizi Di Magazzinaggio E Movimentazione",
    "sg:phone":"+39 031 564800",
    "sg:postcode":"22070",
    "sg:province":"Como",
    "wof:name":"Magazzini Doganali Lariani Srl",
    "wof:placetype":"venue"
},
  "geometry": {"coordinates":[9.055353,45.769749],"type":"Point"}
}