{
  "type": "Feature",
  "properties": {
    "addr:full":"20143 Milano Milano Milano 20143",
    "addr:postcode":"20143;20143",
    "iso:country":"IT",
    "sg:address":"20143 Milano",
    "sg:city":"Milano",
    "sg:orig_category":"Elettronica Professionale E Di Consumo. Automazione E Macchine Per Ufficio",
    "sg:phone":"+39 02 5810 1765",
    "sg:postcode":"20143",
    "sg:province":"Milano",
    "wof:name":"Fa.ru.sistemi (s.r.l.)",
    "wof:placetype":"venue"
},
  "geometry": {"coordinates":[9.165223,45.444447],"type":"Point"}
}