{
  "type": "Feature",
  "properties": {
    "iso:country":"IT",
    "sg:address":"Via Emilia Ovest 30/a 42048 Rubiera",
    "sg:classifiers":[
        {
            "category":"Retail",
            "subcategory":"Animal Services",
            "type":"Services"
        }
    ],
    "sg:phone":"+39 0522 620457",
    "sg:postcode":"42048",
    "sg:province":"Reggio Nell'Emilia",
    "sg:tags":[
        "supplies",
        "husbandry"
    ],
    "wof:name":"Mec - Zoo Snc",
    "wof:placetype":"venue"
},
  "geometry": {"coordinates":[10.776823,44.654263],"type":"Point"}
}