{
  "type": "Feature",
  "properties": {
    "addr:full":"161, Via Matteotti 40013 Castel Maggiore Castel Maggiore Bologna 40013",
    "addr:housenumber":"161",
    "addr:postcode":"40013;40013",
    "addr:street":"Via Matteotti",
    "iso:country":"IT",
    "sg:address":"161, Via Matteotti 40013 Castel Maggiore",
    "sg:city":"Castel Maggiore",
    "sg:classifiers":[
        {
            "category":"Professional",
            "subcategory":"Engineering",
            "type":"Services"
        }
    ],
    "sg:phone":"+39 39800848079",
    "sg:postcode":"40013",
    "sg:province":"Bologna",
    "sg:tags":[
        "machine",
        "-",
        "mechanical"
    ],
    "wof:name":"Technofrigo Dell'orto S.p.a.",
    "wof:placetype":"venue"
},
  "geometry": {"coordinates":[11.375947,44.572334],"type":"Point"}
}