{
  "type": "Feature",
  "properties": {
    "iso:country":"IT",
    "sg:address":"00146 Roma",
    "sg:city":"Roma",
    "sg:orig_category":"Macchine, Impianti Ed Attrezzature Industria Chimica",
    "sg:phone":"+39 06 543 3140",
    "sg:postcode":"00146",
    "sg:province":"Roma",
    "wof:name":"Diciesse Petroleum (s.r.l.)",
    "wof:placetype":"venue"
},
  "geometry": {"coordinates":[12.476233,41.853924],"type":"Point"}
}