{
  "type": "Feature",
  "properties": {
    "addr:full":"23834 Premana Premana Lecco 23834",
    "addr:postcode":"23834;23834",
    "iso:country":"IT",
    "sg:address":"23834 Premana",
    "sg:city":"Premana",
    "sg:orig_category":"Non-classified Establishments",
    "sg:phone":"+39 0341 890395",
    "sg:postcode":"23834",
    "sg:province":"Lecco",
    "wof:name":"Vittori Snc Dei F.lli Vittori",
    "wof:placetype":"venue"
},
  "geometry": {"coordinates":[9.410996,45.848045],"type":"Point"}
}