{
  "type": "Feature",
  "properties": {
    "iso:country":"IT",
    "sg:address":"21050 Marnate",
    "sg:city":"Marnate",
    "sg:orig_category":"Abbigliamento In Pelle - Produzione E Ingrosso",
    "sg:phone":"+39 0331 658344",
    "sg:postcode":"21050",
    "sg:province":"Varese",
    "wof:name":"Euromaglia Srl",
    "wof:placetype":"venue"
},
  "geometry": {"coordinates":[8.88412,45.648724],"type":"Point"}
}