{
  "type": "Feature",
  "properties": {
    "iso:country":"IT",
    "sg:address":"4, Via I. Nievo 24030 Mozzo",
    "sg:city":"Mozzo",
    "sg:classifiers":[
        {
            "category":"Professional",
            "subcategory":"Engineering",
            "type":"Services"
        }
    ],
    "sg:phone":"+39 39035615593",
    "sg:postcode":"24030",
    "sg:province":"Bergamo",
    "sg:tags":[
        "machine",
        "-",
        "mechanical"
    ],
    "wof:name":"Ronzoni Di Ronzoni G. E C. (s.n.c.)",
    "wof:placetype":"venue"
},
  "geometry": {"coordinates":[9.594808,45.700703],"type":"Point"}
}