{
  "type": "Feature",
  "properties": {
    "addr:full":"76, Via Roma 23892 Bulciago Bulciago Lecco 23892",
    "addr:postcode":"23892;23892",
    "addr:street":"Via Roma",
    "iso:country":"IT",
    "sg:address":"76, Via Roma 23892 Bulciago",
    "sg:city":"Bulciago",
    "sg:classifiers":[
        {
            "category":"Shopping",
            "subcategory":"Crafts & Fabrics",
            "type":"Retail Goods"
        }
    ],
    "sg:phone":"+39 39031874339",
    "sg:postcode":"23892",
    "sg:province":"Lecco",
    "wof:name":"Prosetex Tessitura Jacquard (s.p.a.)",
    "wof:placetype":"venue"
},
  "geometry": {"coordinates":[9.2802639008,45.7486000061],"type":"Point"}
}