{
  "type": "Feature",
  "properties": {
    "iso:country":"IT",
    "sg:address":"3/a, V. San Felice E Piteccio51030 S. Felice",
    "sg:classifiers":[
        {
            "category":"Shopping",
            "subcategory":"Clothing, Apparel, & Fashions",
            "type":"Retail Goods"
        }
    ],
    "sg:phone":"+39 0573 998008",
    "sg:postcode":"51030",
    "sg:province":"Pistoia",
    "sg:tags":[
        "clothes"
    ],
    "sg:website":"http://www.paginegialle.it/texplisse",
    "wof:name":"Texpliss\u00c8 Spa",
    "wof:placetype":"venue"
},
  "geometry": {"coordinates":[10.918524,43.932156],"type":"Point"}
}