{
  "type": "Feature",
  "properties": {
    "iso:country":"IT",
    "sg:address":"35026 Conselve",
    "sg:city":"Conselve",
    "sg:orig_category":"Climatizzazione E Condizionamento, Apparecchiature E Servizi",
    "sg:phone":"+39 049 538 5127",
    "sg:postcode":"35026",
    "sg:province":"Padova",
    "wof:name":"Tra - Bo (s.n.c.)",
    "wof:placetype":"venue"
},
  "geometry": {"coordinates":[11.916757,45.412285],"type":"Point"}
}