{
  "type": "Feature",
  "properties": {
    "iso:country":"IT",
    "sg:address":"1, Via Piave 22060 Cabiate",
    "sg:city":"Cabiate",
    "sg:classifiers":[
        {
            "category":"Shopping",
            "subcategory":"Crafts & Fabrics",
            "type":"Retail Goods"
        }
    ],
    "sg:phone":"+39 39031766301",
    "sg:postcode":"22060",
    "sg:province":"Como",
    "wof:name":"Italtex (s.p.a.)",
    "wof:placetype":"venue"
},
  "geometry": {"coordinates":[9.1421556473,45.6954193115],"type":"Point"}
}