{
  "type": "Feature",
  "properties": {
    "iso:country":"IT",
    "sg:address":"12010 S. Defendente",
    "sg:orig_category":"Macchine Ed Impianti Per Edilizia E Lavori Pubblici",
    "sg:phone":"+39 0171 614111",
    "sg:postcode":"12010",
    "sg:province":"Cuneo",
    "sg:website":"http://www.merlo.com",
    "wof:name":"Merlo Spa",
    "wof:placetype":"venue"
},
  "geometry": {"coordinates":[7.497764,44.39632],"type":"Point"}
}