{
  "type": "Feature",
  "properties": {
    "addr:full":"70022 Altamura Altamura Bari 70022",
    "addr:postcode":"70022;70022",
    "iso:country":"IT",
    "sg:address":"70022 Altamura",
    "sg:city":"Altamura",
    "sg:orig_category":"Servizi E Lavori Per Arredamento E Industria Del Legno. Servizi E Lavori Per Edilizia E Lavori Pubblici",
    "sg:phone":"+39 080 310 1040",
    "sg:postcode":"70022",
    "sg:province":"Bari",
    "wof:name":"Ferrulli Nicola",
    "wof:placetype":"venue"
},
  "geometry": {"coordinates":[16.535498,40.827805],"type":"Point"}
}