{
  "type": "Feature",
  "properties": {
    "iso:country":"IT",
    "sg:address":"20068 Peschiera Borromeo",
    "sg:city":"Peschiera Borromeo",
    "sg:classifiers":[
        {
            "category":"Personal",
            "subcategory":"Piercing",
            "type":"Services"
        }
    ],
    "sg:phone":"+39 02 5530 8377",
    "sg:postcode":"20068",
    "sg:province":"Milano",
    "sg:tags":[
        "e",
        "tatuaggi"
    ],
    "wof:name":"Pelle Ribelle - Tatto Studio Di Fabio Tatto",
    "wof:placetype":"venue"
},
  "geometry": {"coordinates":[9.31577,45.435673],"type":"Point"}
}