{
  "type": "Feature",
  "properties": {
    "addr:full":"33085 Maniago Maniago Pordenone 33085",
    "addr:postcode":"33085;33085",
    "iso:country":"IT",
    "sg:address":"33085 Maniago",
    "sg:city":"Maniago",
    "sg:classifiers":[
        {
            "category":"Home & Garden",
            "subcategory":"Kitchen Supply",
            "type":"Retail Goods"
        }
    ],
    "sg:phone":"+39 0427 700153",
    "sg:postcode":"33085",
    "sg:province":"Pordenone",
    "sg:tags":[
        "activities",
        "houseware",
        "utensil",
        "tool",
        "commercial",
        "materials",
        "artisan",
        "mechanical"
    ],
    "wof:name":"Tecnocut Snc",
    "wof:placetype":"venue"
},
  "geometry": {"coordinates":[12.727261,46.158466],"type":"Point"}
}