{
  "type": "Feature",
  "properties": {
    "iso:country":"IT",
    "sg:address":"Piazza Nicola Nusco 30; Ginosa; 74013",
    "sg:city":"Ginosa",
    "sg:classifiers":[
        {
            "category":"Banks & Credit Unions",
            "subcategory":"Bank",
            "type":"Services"
        }
    ],
    "sg:phone":"+39 099 829 4047",
    "sg:postcode":"74013",
    "sg:province":"Taranto",
    "wof:name":"Banco Di Napoli Spa",
    "wof:placetype":"venue"
},
  "geometry": {"coordinates":[16.794241,40.503563],"type":"Point"}
}