{
  "type": "Feature",
  "properties": {
    "addr:full":"Via Redecesio 7 20090 Segrate Segrate Milano 20090",
    "addr:housenumber":"7",
    "addr:postcode":"20090;20090",
    "addr:street":"Via Redecesio",
    "iso:country":"IT",
    "sg:address":"Via Redecesio 7 20090 Segrate",
    "sg:city":"Segrate",
    "sg:classifiers":[
        {
            "category":"Manufacturing",
            "subcategory":"Food",
            "type":"Manufacturing & Wholesale Goods"
        }
    ],
    "sg:phone":"+39 02 213 9251",
    "sg:postcode":"20090",
    "sg:province":"Milano",
    "sg:tags":[
        "raw",
        "material"
    ],
    "wof:name":"Ser Fruits S.r.l.",
    "wof:placetype":"venue"
},
  "geometry": {"coordinates":[9.2751808167,45.4843521118],"type":"Point"}
}