{
  "type": "Feature",
  "properties": {
    "iso:country":"IT",
    "sg:address":"Via Vittorio Veneto 15, Collelungo Sabino, 02030 Casaprota, Rn",
    "sg:city":"Casaprota",
    "sg:classifiers":[
        {
            "category":"Banks & Credit Unions",
            "subcategory":"Bank",
            "type":"Services"
        }
    ],
    "sg:postcode":"02030",
    "sg:province":"Rieti",
    "wof:name":"Banca Di Credito Cooperativo Della Sabina-casaprota (ri) Scrl",
    "wof:placetype":"venue"
},
  "geometry": {"coordinates":[12.814609,42.248123],"type":"Point"}
}