{
  "type": "Feature",
  "properties": {
    "addr:full":"10148 Torino Torino Torino 10148",
    "addr:postcode":"10148;10148",
    "iso:country":"IT",
    "sg:address":"10148 Torino",
    "sg:city":"Torino",
    "sg:orig_category":"Motori Ed Organi Di Trasmissione",
    "sg:phone":"+39 011 226 7146",
    "sg:postcode":"10148",
    "sg:province":"Torino",
    "wof:name":"Chiaravalli Trasmissioni S.p.a.",
    "wof:placetype":"venue"
},
  "geometry": {"coordinates":[7.6666693687,45.1081390381],"type":"Point"}
}