{
  "type": "Feature",
  "properties": {
    "iso:country":"IT",
    "sg:address":"Via Matteotti 115 28077 Prato Sesia",
    "sg:city":"Prato Sesia",
    "sg:orig_category":"Underwear, Woven",
    "sg:phone":"+39 0163 853611",
    "sg:postcode":"28077",
    "sg:province":"Novara",
    "sg:website":"www.maglieriaragno.it",
    "wof:name":"Manifattura Di Valduggia Spa",
    "wof:placetype":"venue"
},
  "geometry": {"coordinates":[8.360957,45.657276],"type":"Point"}
}