{
  "type": "Feature",
  "properties": {
    "iso:country":"IT",
    "sg:address":"34170 Gorizia",
    "sg:city":"Gorizia",
    "sg:orig_category":"Hobbistica",
    "sg:phone":"+39 0481 536322",
    "sg:postcode":"34170",
    "sg:province":"Gorizia",
    "wof:name":"Cambio Isontino S.a.s.",
    "wof:placetype":"venue"
},
  "geometry": {"coordinates":[13.62106,45.943958],"type":"Point"}
}