{
  "type": "Feature",
  "properties": {
    "iso:country":"IT",
    "sg:address":"27030 Carbonara Al Ticino",
    "sg:orig_category":"Strade - Costruzione E Manutenzione",
    "sg:phone":"+39 0382 400091",
    "sg:postcode":"27030",
    "sg:province":"Pavia",
    "wof:name":"Impresa Caff\u00da Srl",
    "wof:placetype":"venue"
},
  "geometry": {"coordinates":[9.076012,45.160175],"type":"Point"}
}