{
  "type": "Feature",
  "properties": {
    "iso:country":"IT",
    "sg:address":"16122 Genova",
    "sg:city":"Genova",
    "sg:orig_category":"Professionisti - Studi E Servizi Ed Associazioni Di Interesse Aziendale. Associazioni Ed Organismi Di Interesse Pubblico",
    "sg:phone":"+39 010 839 3703",
    "sg:postcode":"16122",
    "sg:province":"Genova",
    "wof:name":"Consiglio Notarile Di Genova",
    "wof:placetype":"venue"
},
  "geometry": {"coordinates":[8.9382266998,44.4111175537],"type":"Point"}
}