{
  "type": "Feature",
  "properties": {
    "iso:country":"IT",
    "sg:address":"35031 Abano Terme",
    "sg:city":"Abano Terme",
    "sg:orig_category":"Alberghi E Strutture Extra Alberghiere. Ospedali E Servizi Sanitari",
    "sg:phone":"+39 049 866 9443",
    "sg:postcode":"35031",
    "sg:province":"Padova",
    "sg:website":"http://inforeti.it/eden/",
    "wof:name":"Hotel Eden Terme",
    "wof:placetype":"venue"
},
  "geometry": {"coordinates":[11.789929,45.350033],"type":"Point"}
}