{
  "type": "Feature",
  "properties": {
    "iso:country":"IT",
    "sg:address":"00122 Lido Di Ostia",
    "sg:orig_category":"Servizi Per Lo Sport E Il Tempo Libero. Servizi Al Turismo",
    "sg:phone":"+39 06 562 2395",
    "sg:postcode":"00122",
    "sg:province":"Roma",
    "wof:name":"Leda Video Games Alfredo",
    "wof:placetype":"venue"
},
  "geometry": {"coordinates":[12.277022,41.730366],"type":"Point"}
}