{
  "type": "Feature",
  "properties": {
    "iso:country":"IT",
    "sg:address":"20090 Settala",
    "sg:city":"Settala",
    "sg:orig_category":"Lavorazioni Metalli, Stampaggio E Saldatura",
    "sg:phone":"+39 02 9577 0229",
    "sg:postcode":"20090",
    "sg:province":"Milano",
    "wof:name":"Ferri Bruno",
    "wof:placetype":"venue"
},
  "geometry": {"coordinates":[9.159298,45.560715],"type":"Point"}
}