{
  "type": "Feature",
  "properties": {
    "addr:full":"Via Vittorio Amedeo Ii 18 10121 Torino Torino Torino 10121",
    "addr:housenumber":"18",
    "addr:postcode":"10121;10121",
    "addr:street":"Via Vittorio Amedeo Ii",
    "iso:country":"IT",
    "sg:address":"Via Vittorio Amedeo Ii 18 10121 Torino",
    "sg:city":"Torino",
    "sg:classifiers":[
        {
            "category":"Shopping",
            "subcategory":"Books",
            "type":"Retail Goods"
        }
    ],
    "sg:phone":"+39 011 565 4111",
    "sg:postcode":"10121",
    "sg:province":"Torino",
    "sg:tags":[
        "text",
        "school",
        "books",
        "material",
        "learning"
    ],
    "sg:website":"www.loescher.it",
    "wof:name":"Loescher Editori Srl",
    "wof:placetype":"venue"
},
  "geometry": {"coordinates":[7.669327,45.07],"type":"Point"}
}