{
  "type": "Feature",
  "properties": {
    "iso:country":"IT",
    "sg:address":"35141 Padova",
    "sg:city":"Padova",
    "sg:orig_category":"Servizi E Lavori Per Abbigliamento E Pelletterie",
    "sg:phone":"+39 049 871 0013",
    "sg:postcode":"35141",
    "sg:province":"Padova",
    "wof:name":"Beria Emanuela",
    "wof:placetype":"venue"
},
  "geometry": {"coordinates":[11.867803,45.402088],"type":"Point"}
}