{
  "type": "Feature",
  "properties": {
    "addr:full":"Via Fieschi 51/a 16036 Recco Recco Genova 16036",
    "addr:housenumber":"51 / a",
    "addr:postcode":"16036;16036",
    "addr:street":"Via Fieschi",
    "iso:country":"IT",
    "sg:address":"Via Fieschi 51/a 16036 Recco",
    "sg:city":"Recco",
    "sg:classifiers":[
        {
            "category":"Science Facility",
            "type":"Public Place"
        }
    ],
    "sg:phone":"+39 0185 720315",
    "sg:postcode":"16036",
    "sg:province":"Genova",
    "sg:tags":[
        "appliance",
        "biomedical"
    ],
    "sg:website":"www.meditalia.net",
    "wof:name":"Med Italia Biomedica Srl",
    "wof:placetype":"venue"
},
  "geometry": {"coordinates":[8.933989,44.407063],"type":"Point"}
}