{
  "type": "Feature",
  "properties": {
    "addr:full":"Via Di Voltaia Nel Corso 2/4, 53045 Montepulciano, Si Montepulciano Siena 53045",
    "addr:housenumber":"2 / 4",
    "addr:postcode":"53045;53045",
    "addr:street":"Via Di Voltaia Nel Corso",
    "iso:country":"IT",
    "sg:address":"Via Di Voltaia Nel Corso 2/4, 53045 Montepulciano, Si",
    "sg:city":"Montepulciano",
    "sg:classifiers":[
        {
            "category":"Banks & Credit Unions",
            "subcategory":"Bank",
            "type":"Services"
        }
    ],
    "sg:postcode":"53045",
    "sg:province":"Siena",
    "wof:name":"Banca Di Credito Cooperativo Di Montepulciano",
    "wof:placetype":"venue"
},
  "geometry": {"coordinates":[11.781796,43.09333],"type":"Point"}
}