{
  "type": "Feature",
  "properties": {
    "addr:full":"10, Via Dell' Artigianato 35010 Massanzago Massanzago Padova 35010",
    "addr:postcode":"35010;35010",
    "addr:street":"Via Dell ' Artigianato",
    "iso:country":"IT",
    "sg:address":"10, Via Dell' Artigianato 35010 Massanzago",
    "sg:city":"Massanzago",
    "sg:classifiers":[
        {
            "category":"Manufacturing",
            "subcategory":"Metals",
            "type":"Manufacturing & Wholesale Goods"
        }
    ],
    "sg:phone":"+39 049 579 7760",
    "sg:postcode":"35010",
    "sg:province":"Padova",
    "sg:tags":[
        "processing"
    ],
    "wof:name":"Aba (s.r.l.)",
    "wof:placetype":"venue"
},
  "geometry": {"coordinates":[12.0125389099,45.5532531738],"type":"Point"}
}