{
  "type": "Feature",
  "properties": {
    "addr:full":"27049 Stradella Stradella Pavia 27049",
    "addr:postcode":"27049;27049",
    "iso:country":"IT",
    "sg:address":"27049 Stradella",
    "sg:city":"Stradella",
    "sg:orig_category":"Servizi E Lavori Per Edilizia E Lavori Pubblici. Professionisti - Studi E Servizi Ed Associazioni Di Interesse Aziendale",
    "sg:phone":"+39 0385 246111",
    "sg:postcode":"27049",
    "sg:province":"Pavia",
    "wof:name":"Ital Geo Sas Di Conca Carlo & C.",
    "wof:placetype":"venue"
},
  "geometry": {"coordinates":[9.301888,45.074074],"type":"Point"}
}