{
  "type": "Feature",
  "properties": {
    "iso:country":"IT",
    "sg:address":"21029 Vergiate",
    "sg:city":"Vergiate",
    "sg:orig_category":"Arredamenti Ed Architettura D'interni",
    "sg:phone":"+39 0331 948659",
    "sg:postcode":"21029",
    "sg:province":"Varese",
    "wof:name":"Manni Marmi Snc",
    "wof:placetype":"venue"
},
  "geometry": {"coordinates":[8.821146,45.821304],"type":"Point"}
}