{
  "type": "Feature",
  "properties": {
    "addr:full":"40125 Bologna Bologna Bologna 40125",
    "addr:postcode":"40125;40125",
    "iso:country":"IT",
    "sg:address":"40125 Bologna",
    "sg:city":"Bologna",
    "sg:orig_category":"Cinematografia E Radiotelevisione. Pubblicita', Marketing E Comunicazione",
    "sg:phone":"+39 051 264037",
    "sg:postcode":"40125",
    "sg:province":"Bologna",
    "wof:name":"Rosanna & Associati Sas",
    "wof:placetype":"venue"
},
  "geometry": {"coordinates":[11.352723,44.488308],"type":"Point"}
}