{
  "type": "Feature",
  "properties": {
    "iso:country":"IT",
    "sg:address":"20080 Vermezzo",
    "sg:city":"Vermezzo",
    "sg:orig_category":"Servizi Editoriali. Servizi Ausiliari Per Il Trasporto",
    "sg:phone":"+39 02 9494 3136",
    "sg:postcode":"20080",
    "sg:province":"Milano",
    "wof:name":"Sagi Distribuzione Srl",
    "wof:placetype":"venue"
},
  "geometry": {"coordinates":[9.291194,45.525963],"type":"Point"}
}