{
  "type": "Feature",
  "properties": {
    "addr:full":"167, V. Nazionale - Gallico89055 Reggio Calabria",
    "addr:housenumber":"167",
    "addr:street":"V. Nazionale Gallico89055",
    "iso:country":"IT",
    "sg:address":"167, V. Nazionale - Gallico89055 Reggio Calabria",
    "sg:classifiers":[
        {
            "category":"Food & Beverages",
            "subcategory":"Groceries & Convenience Stores",
            "type":"Retail Goods"
        }
    ],
    "sg:phone":"+39 0965 650382",
    "sg:tags":[
        "drink"
    ],
    "wof:name":"Agrumaria Reggina Srl",
    "wof:placetype":"venue"
},
  "geometry": {"coordinates":[15.658066,38.232887],"type":"Point"}
}