{
  "type": "Feature",
  "properties": {
    "addr:full":"15/4, V. Verdi40067 Rastignano Rastignano Bologna 40067",
    "addr:housenumber":"15 / 4 v. verdi40067 rastignano",
    "addr:postcode":"40067",
    "addr:street":"Bologna",
    "iso:country":"IT",
    "sg:address":"15/4, V. Verdi40067 Rastignano",
    "sg:city":"Rastignano",
    "sg:classifiers":[
        {
            "category":"Personal",
            "subcategory":"Shoe Repair & Shine",
            "type":"Services"
        }
    ],
    "sg:phone":"+39 051 626 0336",
    "sg:postcode":"40067",
    "sg:province":"Bologna",
    "sg:tags":[
        "leather"
    ],
    "sg:website":"http://www.nuovascama.com",
    "wof:name":"Nuova Scama Sas",
    "wof:placetype":"venue"
},
  "geometry": {"coordinates":[11.349903,44.421791],"type":"Point"}
}