{
  "type": "Feature",
  "properties": {
    "iso:country":"IT",
    "sg:address":"90143 Palermo",
    "sg:city":"Palermo",
    "sg:orig_category":"Servizi Per Aziende, Manifestazioni E Supporto Agli Scambi Commerciali",
    "sg:phone":"+39 091 302655",
    "sg:postcode":"90143",
    "sg:province":"Palermo",
    "sg:website":"http://www.eurocongress.it",
    "wof:name":"Eurocongressi Srl",
    "wof:placetype":"venue"
},
  "geometry": {"coordinates":[13.346519,38.138649],"type":"Point"}
}