{
  "type": "Feature",
  "properties": {
    "addr:full":"Via Treves, 57/59 20090 Trezzano Sul Naviglio Trezzano sul Naviglio Milano 20090",
    "addr:housenumber":"57 / 59",
    "addr:postcode":"20090;20090",
    "addr:street":"Via Treves",
    "iso:country":"IT",
    "sg:address":"Via Treves, 57/59 20090 Trezzano Sul Naviglio",
    "sg:city":"Trezzano sul Naviglio",
    "sg:classifiers":[
        {
            "category":"Utilities",
            "subcategory":"Natural Gas",
            "type":"Services"
        }
    ],
    "sg:phone":"+39 02 4846 3138",
    "sg:postcode":"20090",
    "sg:province":"Milano",
    "sg:tags":[
        "exhaust",
        "detoxification",
        "unit"
    ],
    "wof:name":"I.t.i. Impianti E Tecnologie Industriali Srl",
    "wof:placetype":"venue"
},
  "geometry": {"coordinates":[9.062302,45.416885],"type":"Point"}
}