{
  "type": "Feature",
  "properties": {
    "iso:country":"IT",
    "sg:address":"04016 Sabaudia",
    "sg:city":"Sabaudia",
    "sg:orig_category":"Forniture Per Attivita' Commerciali Ed Artigianali",
    "sg:phone":"+39 0773 515850",
    "sg:postcode":"04016",
    "sg:province":"Latina",
    "wof:name":"Sanna Francesco",
    "wof:placetype":"venue"
},
  "geometry": {"coordinates":[13.0312223434,41.2989807129],"type":"Point"}
}