{
  "type": "Feature",
  "properties": {
    "iso:country":"IT",
    "sg:address":"48 Vinschgauer Str.; Laas; 39023",
    "sg:classifiers":[
        {
            "category":"Banks & Credit Unions",
            "subcategory":"Bank",
            "type":"Services"
        }
    ],
    "sg:phone":"+39 0473 73518",
    "sg:postcode":"39023",
    "sg:province":"Bolzano/Bozen",
    "wof:name":"Raiffeisenkasse Laas",
    "wof:placetype":"venue"
},
  "geometry": {"coordinates":[10.638235,46.630344],"type":"Point"}
}