{
  "type": "Feature",
  "properties": {
    "iso:country":"IT",
    "sg:address":"230, Localita' Piani Della Rugginosa 50066 Reggello",
    "sg:city":"Reggello",
    "sg:classifiers":[
        {
            "category":"Manufacturing",
            "subcategory":"Metals",
            "type":"Manufacturing & Wholesale Goods"
        }
    ],
    "sg:phone":"+39 055 866 2167",
    "sg:postcode":"50066",
    "sg:province":"Firenze",
    "sg:tags":[
        "processing"
    ],
    "wof:name":"Promedea Srl",
    "wof:placetype":"venue"
},
  "geometry": {"coordinates":[11.4640016556,43.6596031189],"type":"Point"}
}