{
  "type": "Feature",
  "properties": {
    "addr:full":"00044 Frascati Frascati Roma 00044",
    "addr:postcode":"00044;00044",
    "iso:country":"IT",
    "sg:address":"00044 Frascati",
    "sg:city":"Frascati",
    "sg:orig_category":"Forniture Per Attivita' Industriali. Servizi Ausiliari Di Sorveglianza, Manutenzione E Pulizia",
    "sg:phone":"+39 06 940 9140",
    "sg:postcode":"00044",
    "sg:province":"Roma",
    "sg:website":"http://www.ecotras.it",
    "wof:name":"Ecotras Spa",
    "wof:placetype":"venue"
},
  "geometry": {"coordinates":[12.6321773529,41.8239555359],"type":"Point"}
}