{
  "type": "Feature",
  "properties": {
    "iso:country":"IT",
    "sg:address":"7/e, V. Tito Speri - Nigoline 25040 Corte Franca",
    "sg:city":"Corte Franca",
    "sg:classifiers":[
        {
            "category":"Shopping",
            "subcategory":"Computers & Home Electronics",
            "type":"Retail Goods"
        }
    ],
    "sg:phone":"+39 39030984128",
    "sg:postcode":"25040",
    "sg:province":"Brescia",
    "sg:tags":[
        "electronic",
        "electrical",
        "equipment"
    ],
    "sg:website":"http://www.omtsrl.com:ws_end: :mark:ws:http://www.paginegialle.it/omtsrl-03",
    "wof:name":"O.m.t. Srl",
    "wof:placetype":"venue"
},
  "geometry": {"coordinates":[10.222958,45.539829],"type":"Point"}
}