{
  "type": "Feature",
  "properties": {
    "iso:country":"IT",
    "sg:address":"41100 Modena",
    "sg:city":"Modena",
    "sg:classifiers":[
        {
            "category":"Wholesale",
            "subcategory":"Machinery & Supplies",
            "type":"Manufacturing & Wholesale Goods"
        }
    ],
    "sg:phone":"+39 059 310236",
    "sg:postcode":"41100",
    "sg:province":"Modena",
    "sg:tags":[
        "pump"
    ],
    "wof:name":"Off. Meccanica Amadei Di Amadei Lino & C. Snc",
    "wof:placetype":"venue"
},
  "geometry": {"coordinates":[10.9376020432,44.6724433899],"type":"Point"}
}