{
  "type": "Feature",
  "properties": {
    "iso:country":"IT",
    "sg:address":"20127 Milano",
    "sg:city":"Milano",
    "sg:orig_category":"Carni, Salumi E Pesci",
    "sg:phone":"+39 02 257 5991",
    "sg:postcode":"20127",
    "sg:province":"Milano",
    "wof:name":"Tavaglione Francesco",
    "wof:placetype":"venue"
},
  "geometry": {"coordinates":[9.222405,45.504726],"type":"Point"}
}