{
  "type": "Feature",
  "properties": {
    "iso:country":"IT",
    "sg:address":"51100 Pistoia",
    "sg:city":"Pistoia",
    "sg:classifiers":[
        {
            "category":"Home & Garden",
            "subcategory":"Building Materials",
            "type":"Retail Goods"
        }
    ],
    "sg:phone":"+39 0573 532077",
    "sg:postcode":"51100",
    "sg:province":"Pistoia",
    "sg:tags":[
        "window",
        "door",
        "frame"
    ],
    "wof:name":"Martinelli Pietro Srl",
    "wof:placetype":"venue"
},
  "geometry": {"coordinates":[10.935494,43.987713],"type":"Point"}
}