{
  "type": "Feature",
  "properties": {
    "addr:full":"Corso Umberto 119, 93100 Caltanissetta, Cl Caltanissetta Caltanissetta 93100",
    "addr:housenumber":"119",
    "addr:postcode":"93100;93100",
    "addr:street":"Corso Umberto",
    "iso:country":"IT",
    "sg:address":"Corso Umberto 119, 93100 Caltanissetta, Cl",
    "sg:city":"Caltanissetta",
    "sg:classifiers":[
        {
            "category":"Banks & Credit Unions",
            "subcategory":"Bank",
            "type":"Services"
        }
    ],
    "sg:postcode":"93100",
    "sg:province":"Caltanissetta",
    "wof:name":"Banca Di Credito Cooperativo San Michele Di Caltanissetta Scarl",
    "wof:placetype":"venue"
},
  "geometry": {"coordinates":[14.063217,37.490334],"type":"Point"}
}