{
  "type": "Feature",
  "properties": {
    "addr:full":"53042 Chianciano Terme Chianciano Terme Siena 53042",
    "addr:postcode":"53042;53042",
    "iso:country":"IT",
    "sg:address":"53042 Chianciano Terme",
    "sg:city":"Chianciano Terme",
    "sg:orig_category":"Alberghi E Strutture Extra Alberghiere. Ospedali E Servizi Sanitari",
    "sg:phone":"+39 0578 63741",
    "sg:postcode":"53042",
    "sg:province":"Siena",
    "wof:name":"Albergo Bellavista",
    "wof:placetype":"venue"
},
  "geometry": {"coordinates":[11.821004,43.037918],"type":"Point"}
}