{
  "type": "Feature",
  "properties": {
    "addr:full":"Via Emanuele Filiberto S. N. 73020 Cutrofiano Cutrofiano Lecce 73020",
    "addr:postcode":"73020;73020",
    "addr:street":"Via Emanuele Filiberto S. N.",
    "iso:country":"IT",
    "sg:address":"Via Emanuele Filiberto S. N. 73020 Cutrofiano",
    "sg:city":"Cutrofiano",
    "sg:classifiers":[
        {
            "category":"Food & Beverages",
            "subcategory":"Fruits & Vegetables",
            "type":"Retail Goods"
        }
    ],
    "sg:phone":"+39 0836 515365",
    "sg:postcode":"73020",
    "sg:province":"Lecce",
    "wof:name":"Eurofrutta S.a.s. Di Franco E Lorenzo Giannotta",
    "wof:placetype":"venue"
},
  "geometry": {"coordinates":[18.1740150452,40.3532905579],"type":"Point"}
}