{
  "type": "Feature",
  "properties": {
    "iso:country":"IT",
    "sg:address":"30030 Fosso'",
    "sg:orig_category":"Bagno - Accessori E Mobili",
    "sg:phone":"+39 041 462598",
    "sg:postcode":"30030",
    "sg:province":"Venezia",
    "sg:website":"http://www.ansa-lux.com",
    "wof:name":"Ansa-lux Sas",
    "wof:placetype":"venue"
},
  "geometry": {"coordinates":[12.050482,45.386276],"type":"Point"}
}