{
  "type": "Feature",
  "properties": {
    "iso:country":"IT",
    "sg:address":"Via Di Vannina 80 00156 Roma",
    "sg:city":"Roma",
    "sg:classifiers":[
        {
            "category":"Banks & Credit Unions",
            "subcategory":"Financial Services",
            "type":"Services"
        }
    ],
    "sg:phone":"+39 06 4121 7154",
    "sg:postcode":"00156",
    "sg:province":"Roma",
    "sg:tags":[
        "washing",
        "agents",
        "cleaning",
        "liquid"
    ],
    "wof:name":"Samec Srl",
    "wof:placetype":"venue"
},
  "geometry": {"coordinates":[12.591997,41.930786],"type":"Point"}
}