{
  "type": "Feature",
  "properties": {
    "addr:full":"110, Via S. Alessandro 22066 Mariano Comense Mariano Comense Como 22066",
    "addr:housenumber":"110",
    "addr:postcode":"22066;22066",
    "addr:street":"Via S. Alessandro",
    "iso:country":"IT",
    "sg:address":"110, Via S. Alessandro 22066 Mariano Comense",
    "sg:city":"Mariano Comense",
    "sg:classifiers":[
        {
            "category":"Shopping",
            "subcategory":"Crafts & Fabrics",
            "type":"Retail Goods"
        }
    ],
    "sg:phone":"+39 39031744666",
    "sg:postcode":"22066",
    "sg:province":"Como",
    "wof:name":"T.c.m. (s.r.l.)",
    "wof:placetype":"venue"
},
  "geometry": {"coordinates":[9.0854558945,45.8119659424],"type":"Point"}
}