{
  "type": "Feature",
  "properties": {
    "iso:country":"IT",
    "sg:address":"45037 Melara",
    "sg:city":"Melara",
    "sg:classifiers":[
        {
            "category":"Retail",
            "subcategory":"Storage",
            "type":"Services"
        }
    ],
    "sg:phone":"+39 0425 89689",
    "sg:postcode":"45037",
    "sg:province":"Rovigo",
    "sg:tags":[
        "equipment",
        "handling",
        "system"
    ],
    "sg:website":"http://www.borghi.net",
    "wof:name":"Fratelli Borghi Snc Di Borghi D. E C.",
    "wof:placetype":"venue"
},
  "geometry": {"coordinates":[11.186046,45.068653],"type":"Point"}
}