{
  "type": "Feature",
  "properties": {
    "iso:country":"IT",
    "sg:address":"Via Dei Lauri 8; Aprilia; 04011",
    "sg:city":"Aprilia",
    "sg:classifiers":[
        {
            "category":"Banks & Credit Unions",
            "subcategory":"Bank",
            "type":"Services"
        }
    ],
    "sg:phone":"+39 06 920 5566",
    "sg:postcode":"04011",
    "sg:province":"Latina",
    "wof:name":"Banco Di Santo Spirito",
    "wof:placetype":"venue"
},
  "geometry": {"coordinates":[12.649066,41.594604],"type":"Point"}
}