{
  "type": "Feature",
  "properties": {
    "addr:full":"34/a, V. Paolo Orsi 00178 Roma Roma Roma 00178",
    "addr:housenumber":"34 / a",
    "addr:postcode":"00178;00178",
    "addr:street":"V. Paolo Orsi",
    "iso:country":"IT",
    "sg:address":"34/a, V. Paolo Orsi 00178 Roma",
    "sg:city":"Roma",
    "sg:classifiers":[
        {
            "category":"Shopping",
            "subcategory":"Stationery & Office Supplies",
            "type":"Retail Goods"
        }
    ],
    "sg:phone":"+39 39067235152",
    "sg:postcode":"00178",
    "sg:province":"Roma",
    "sg:tags":[
        "professional"
    ],
    "sg:website":"http://www.paginegialle.it/teamarredo",
    "wof:name":"Team Arredo Di Bruno Bucci",
    "wof:placetype":"venue"
},
  "geometry": {"coordinates":[12.583814621,41.821521759],"type":"Point"}
}