{
  "type": "Feature",
  "properties": {
    "iso:country":"IT",
    "sg:address":"Contrada Zappulla 98070 Torrenova",
    "sg:city":"Torrenova",
    "sg:classifiers":[
        {
            "category":"Farming",
            "subcategory":"Livestock Farm",
            "type":"Manufacturing & Wholesale Goods"
        }
    ],
    "sg:phone":"+39 0941 958007",
    "sg:postcode":"98070",
    "sg:province":"Messina",
    "sg:tags":[
        "agriculture"
    ],
    "wof:name":"Fratelli Damiano & C. S.r.l.",
    "wof:placetype":"venue"
},
  "geometry": {"coordinates":[14.699453,38.093761],"type":"Point"}
}