{
  "type": "Feature",
  "properties": {
    "addr:full":"51, Via Garibaldi Giuseppe 51016 Montecatini Terme Pistoia 51016",
    "addr:postcode":"51016;51016",
    "addr:street":"Via Garibaldi Giuseppe",
    "iso:country":"IT",
    "sg:address":"51, Via Garibaldi Giuseppe 51016 Montecatini Terme",
    "sg:classifiers":[
        {
            "category":"Professional",
            "subcategory":"Engineering",
            "type":"Services"
        }
    ],
    "sg:phone":"+39 0572 911110",
    "sg:postcode":"51016",
    "sg:province":"Pistoia",
    "sg:tags":[
        "machine",
        "-",
        "mechanical"
    ],
    "wof:name":"Buonocore Pietro",
    "wof:placetype":"venue"
},
  "geometry": {"coordinates":[10.832026,43.905579],"type":"Point"}
}