{
  "type": "Feature",
  "properties": {
    "addr:full":"Via San Francesco; Maddaloni; 81024 Maddaloni Caserta 81024",
    "addr:postcode":"81024;81024",
    "addr:street":"Via San Francesco Maddaloni",
    "iso:country":"IT",
    "sg:address":"Via San Francesco; Maddaloni; 81024",
    "sg:city":"Maddaloni",
    "sg:classifiers":[
        {
            "category":"Banks & Credit Unions",
            "subcategory":"Bank",
            "type":"Services"
        }
    ],
    "sg:phone":"+39 0823 405215",
    "sg:postcode":"81024",
    "sg:province":"Caserta",
    "wof:name":"Banca Di Credito Popolare Scarl",
    "wof:placetype":"venue"
},
  "geometry": {"coordinates":[14.385798,41.037491],"type":"Point"}
}