{
  "type": "Feature",
  "properties": {
    "iso:country":"IT",
    "sg:address":"00182 Roma",
    "sg:city":"Roma",
    "sg:orig_category":"Serramenti Ed Infissi. Prodotti Vari In Metallo",
    "sg:phone":"+39 06 7030 6770",
    "sg:postcode":"00182",
    "sg:province":"Roma",
    "wof:name":"Airklima Srl",
    "wof:placetype":"venue"
},
  "geometry": {"coordinates":[12.514094,41.887234],"type":"Point"}
}