{
  "type": "Feature",
  "properties": {
    "iso:country":"IT",
    "sg:address":"Via Ugolini Giuseppe 3 20125 Milano",
    "sg:city":"Milano",
    "sg:classifiers":[
        {
            "category":"Shopping Center",
            "type":"Public Place"
        }
    ],
    "sg:phone":"+39 02 6610 1982",
    "sg:postcode":"20125",
    "sg:province":"Milano",
    "sg:tags":[
        "ball"
    ],
    "sg:website":"www.rgpinter.it",
    "wof:name":"Rgp International Srl",
    "wof:placetype":"venue"
},
  "geometry": {"coordinates":[9.203226,45.482468],"type":"Point"}
}