{
  "type": "Feature",
  "properties": {
    "iso:country":"IT",
    "sg:address":"33030 Basaldella Del Cormor",
    "sg:city":"Basaldella",
    "sg:orig_category":"Accessori Moda D'abbigliamento",
    "sg:postcode":"33030",
    "sg:province":"Udine",
    "wof:name":"Wolf Di Della Vedova & C. (s.n.c.)",
    "wof:placetype":"venue"
},
  "geometry": {"coordinates":[13.21892,46.037048],"type":"Point"}
}