{
  "type": "Feature",
  "properties": {
    "addr:full":"Via Bergamo 2; Ranzanico; 24060 Ranzanico Bergamo 24060",
    "addr:housenumber":"2",
    "addr:postcode":"24060;24060",
    "addr:street":"Via Bergamo",
    "iso:country":"IT",
    "sg:address":"Via Bergamo 2; Ranzanico; 24060",
    "sg:city":"Ranzanico",
    "sg:classifiers":[
        {
            "category":"Banks & Credit Unions",
            "subcategory":"Bank",
            "type":"Services"
        }
    ],
    "sg:phone":"+39 035 829260",
    "sg:postcode":"24060",
    "sg:province":"Bergamo",
    "wof:name":"Istituto Bancario, San Paolo Di Torino Spa",
    "wof:placetype":"venue"
},
  "geometry": {"coordinates":[9.932476,45.780586],"type":"Point"}
}