{
  "type": "Feature",
  "properties": {
    "iso:country":"IT",
    "sg:address":"10131 Torino",
    "sg:city":"Torino",
    "sg:orig_category":"Alberghi E Strutture Extra Alberghiere. Ospedali E Servizi Sanitari",
    "sg:phone":"+39 011 661 8223",
    "sg:postcode":"10131",
    "sg:province":"Torino",
    "sg:website":"http://www.residenzamillenium.it",
    "wof:name":"Residenza Millenium",
    "wof:placetype":"venue"
},
  "geometry": {"coordinates":[7.694828,45.058914],"type":"Point"}
}