{
  "type": "Feature",
  "properties": {
    "iso:country":"IT",
    "sg:address":"22070 Rovello Porro",
    "sg:city":"Rovello Porro",
    "sg:classifiers":[
        {
            "category":"Health Services",
            "subcategory":"Health Practitioner",
            "type":"Services"
        }
    ],
    "sg:phone":"+39 02 9675 1436",
    "sg:postcode":"22070",
    "sg:province":"Como",
    "sg:tags":[
        "medici"
    ],
    "wof:name":"Giudici Luigi",
    "wof:placetype":"venue"
},
  "geometry": {"coordinates":[9.036174,45.649853],"type":"Point"}
}