{
  "type": "Feature",
  "properties": {
    "iso:country":"IT",
    "sg:address":"10123 Torino",
    "sg:city":"Torino",
    "sg:orig_category":"Accessori Moda D'abbigliamento. Shopping",
    "sg:phone":"+39 011 530489",
    "sg:postcode":"10123",
    "sg:province":"Torino",
    "wof:name":"Foresto Cappelleria",
    "wof:placetype":"venue"
},
  "geometry": {"coordinates":[7.592328,45.029629],"type":"Point"}
}