{
  "type": "Feature",
  "properties": {
    "addr:full":"Via Indipendenza 16; Treviso; 31100 Treviso Treviso 31100",
    "addr:housenumber":"16",
    "addr:postcode":"31100;31100",
    "addr:street":"Via Indipendenza",
    "iso:country":"IT",
    "sg:address":"Via Indipendenza 16; Treviso; 31100",
    "sg:city":"Treviso",
    "sg:classifiers":[
        {
            "category":"Banks & Credit Unions",
            "subcategory":"Bank",
            "type":"Services"
        }
    ],
    "sg:phone":"+39 0422 5851",
    "sg:postcode":"31100",
    "sg:province":"Treviso",
    "wof:name":"Banco Ambrosiano Veneto Spa",
    "wof:placetype":"venue"
},
  "geometry": {"coordinates":[12.246286,45.665443],"type":"Point"}
}