{
  "type": "Feature",
  "properties": {
    "iso:country":"IT",
    "sg:address":"15, V. S. Giusto",
    "sg:city":"Fabbrica",
    "sg:classifiers":[
        {
            "category":"Communications",
            "subcategory":"Television Station",
            "type":"Services"
        }
    ],
    "sg:phone":"+39 0587 697147",
    "sg:postcode":"56037",
    "sg:province":"Pisa",
    "sg:tags":[
        "equipment",
        "optical",
        "instrument"
    ],
    "sg:website":"http://www.ilfotoamatore.it:ws_end: :mark:ws:http://www.paginegialle.it/",
    "wof:name":"Il Fotoamatore Srl",
    "wof:placetype":"venue"
},
  "geometry": {"coordinates":[10.396585,43.716137],"type":"Point"}
}