{
  "type": "Feature",
  "properties": {
    "addr:full":"20034 Giussano Giussano Milano 20034",
    "addr:postcode":"20034;20034",
    "iso:country":"IT",
    "sg:address":"20034 Giussano",
    "sg:city":"Giussano",
    "sg:orig_category":"Armadi Guardaroba",
    "sg:phone":"+39 036 286 0221",
    "sg:postcode":"20034",
    "sg:province":"Milano",
    "wof:name":"Feg Industria Mobili Di Rosa Elli & C. Sas",
    "wof:placetype":"venue"
},
  "geometry": {"coordinates":[9.187652,45.500088],"type":"Point"}
}