{
  "type": "Feature",
  "properties": {
    "iso:country":"IT",
    "sg:address":"Zona Industriale 38100 Trento",
    "sg:city":"Trento",
    "sg:classifiers":[
        {
            "category":"Professional",
            "subcategory":"Engineering",
            "type":"Services"
        }
    ],
    "sg:phone":"+39 0461 968300",
    "sg:postcode":"38100",
    "sg:province":"Trento",
    "sg:tags":[
        "machine",
        "-",
        "mechanical"
    ],
    "wof:name":"Officine Brennero S.p.a.",
    "wof:placetype":"venue"
},
  "geometry": {"coordinates":[11.646719,46.008396],"type":"Point"}
}