{
  "type": "Feature",
  "properties": {
    "addr:full":"90143 Palermo Palermo Palermo 90143",
    "addr:postcode":"90143;90143",
    "iso:country":"IT",
    "sg:address":"90143 Palermo",
    "sg:city":"Palermo",
    "sg:orig_category":"Non-classified Establishments",
    "sg:phone":"+39 091 364055",
    "sg:postcode":"90143",
    "sg:province":"Palermo",
    "wof:name":"Antarte Sas Di Claudio Gentile & C.",
    "wof:placetype":"venue"
},
  "geometry": {"coordinates":[13.348543,38.142933],"type":"Point"}
}