{
  "type": "Feature",
  "properties": {
    "iso:country":"IT",
    "sg:address":"33047 Remanzacco",
    "sg:city":"Remanzacco",
    "sg:orig_category":"Arti Grafiche",
    "sg:phone":"+39 0432 668118",
    "sg:postcode":"33047",
    "sg:province":"Udine",
    "wof:name":"Elleti Snc Di Lazzaro & Tonutti",
    "wof:placetype":"venue"
},
  "geometry": {"coordinates":[13.330841,46.067265],"type":"Point"}
}