{
  "type": "Feature",
  "properties": {
    "addr:full":"195, Via Pantanelli 61025 Montelabbate Montelabbate Pesaro E Urbino 61025",
    "addr:housenumber":"195",
    "addr:postcode":"61025;61025",
    "addr:street":"Via Pantanelli",
    "iso:country":"IT",
    "sg:address":"195, Via Pantanelli 61025 Montelabbate",
    "sg:city":"Montelabbate",
    "sg:classifiers":[
        {
            "category":"Home & Garden",
            "subcategory":"Home Furnishings",
            "type":"Retail Goods"
        }
    ],
    "sg:phone":"+39 0721 497299",
    "sg:postcode":"61025",
    "sg:province":"Pesaro E Urbino",
    "sg:tags":[
        "household"
    ],
    "wof:name":"Italcomma Spa",
    "wof:placetype":"venue"
},
  "geometry": {"coordinates":[12.7985134125,43.8679466248],"type":"Point"}
}