{
  "type": "Feature",
  "properties": {
    "iso:country":"IT",
    "sg:address":"38060 Villa Lagarina",
    "sg:city":"Villa Lagarina",
    "sg:orig_category":"Serramenti Ed Infissi",
    "sg:phone":"+39 0464 461515",
    "sg:postcode":"38060",
    "sg:province":"Trento",
    "wof:name":"Tecnoinfisso Srl",
    "wof:placetype":"venue"
},
  "geometry": {"coordinates":[11.035868,45.919899],"type":"Point"}
}