{
  "type": "Feature",
  "properties": {
    "iso:country":"IT",
    "sg:address":"18, Via Arrigo Da Settimello 59100 Prato",
    "sg:city":"Prato",
    "sg:classifiers":[
        {
            "category":"Shopping",
            "subcategory":"Crafts & Fabrics",
            "type":"Retail Goods"
        }
    ],
    "sg:phone":"+39 0574 636354",
    "sg:postcode":"59100",
    "sg:province":"Prato",
    "wof:name":"Stamperia Altair S.r.l.",
    "wof:placetype":"venue"
},
  "geometry": {"coordinates":[11.083990097,43.8576545715],"type":"Point"}
}