{
  "type": "Feature",
  "properties": {
    "iso:country":"IT",
    "sg:address":"00163 Roma",
    "sg:city":"Roma",
    "sg:orig_category":"Agenzie D'affari E Servizi Commerciali. Acqua, Luce, Gas E Societa' Di Esercizio Pubblico",
    "sg:phone":"+39 06 6614 1523",
    "sg:postcode":"00163",
    "sg:province":"Roma",
    "wof:name":"Apas Srl",
    "wof:placetype":"venue"
},
  "geometry": {"coordinates":[12.390224,41.865974],"type":"Point"}
}