{
  "type": "Feature",
  "properties": {
    "iso:country":"IT",
    "sg:address":"00043 Ciampino",
    "sg:city":"Ciampino",
    "sg:classifiers":[
        {
            "category":"Professional",
            "type":"Services"
        }
    ],
    "sg:phone":"+39 06 790791",
    "sg:postcode":"00043",
    "sg:province":"Roma",
    "sg:tags":[
        "activities",
        "supply",
        "commercial",
        "artisan",
        "supplies",
        "accommodation"
    ],
    "wof:name":"Acquario Di Petrucci A.p.m. Snc",
    "wof:placetype":"venue"
},
  "geometry": {"coordinates":[12.591387,41.818844],"type":"Point"}
}