{
  "type": "Feature",
  "properties": {
    "iso:country":"IT",
    "sg:address":"20123 Milano",
    "sg:city":"Milano",
    "sg:orig_category":"Editoria",
    "sg:phone":"+39 02 8646 0202",
    "sg:postcode":"20123",
    "sg:province":"Milano",
    "wof:name":"Il Mattino",
    "wof:placetype":"venue"
},
  "geometry": {"coordinates":[9.185398,45.464699],"type":"Point"}
}