{
  "type": "Feature",
  "properties": {
    "addr:full":"Via Nazionale 87010 Torano Castello Torano Castello Cosenza 87010",
    "addr:postcode":"87010;87010",
    "addr:street":"Via Nazionale",
    "iso:country":"IT",
    "sg:address":"Via Nazionale 87010 Torano Castello",
    "sg:city":"Torano Castello",
    "sg:classifiers":[
        {
            "category":"Professional",
            "subcategory":"Engineering",
            "type":"Services"
        }
    ],
    "sg:phone":"+39 0984 506020",
    "sg:postcode":"87010",
    "sg:province":"Cosenza",
    "sg:tags":[
        "machine",
        "-",
        "mechanical"
    ],
    "wof:name":"Greco Achille",
    "wof:placetype":"venue"
},
  "geometry": {"coordinates":[16.253809,39.298264],"type":"Point"}
}