{
  "type": "Feature",
  "properties": {
    "iso:country":"IT",
    "sg:address":"22, Viale Guglielmo Marconi 46045 Marmirolo",
    "sg:city":"Marmirolo",
    "sg:classifiers":[
        {
            "category":"Professional",
            "subcategory":"Engineering",
            "type":"Services"
        }
    ],
    "sg:phone":"+39 0376 298311",
    "sg:postcode":"46045",
    "sg:province":"Mantova",
    "sg:tags":[
        "machine",
        "-",
        "mechanical"
    ],
    "wof:name":"Cortellazzi Fintec Srl",
    "wof:placetype":"venue"
},
  "geometry": {"coordinates":[10.759682,45.219376],"type":"Point"}
}