{
  "type": "Feature",
  "properties": {
    "iso:country":"IT",
    "sg:address":"10123 Torino",
    "sg:city":"Torino",
    "sg:orig_category":"Ospedali E Servizi Sanitari. Servizi Sociali. Associazioni Ed Organismi Di Interesse Pubblico",
    "sg:phone":"+39 011 815 3222",
    "sg:postcode":"10123",
    "sg:province":"Torino",
    "sg:website":"http://www.arpa.piemonte.it",
    "wof:name":"A.r.p.a. Agenzia Regionale Per La Protezione Ambientale",
    "wof:placetype":"venue"
},
  "geometry": {"coordinates":[8.39892,45.462345],"type":"Point"}
}