{
  "type": "Feature",
  "properties": {
    "addr:full":"16123 Genova Genova Genova 16123",
    "addr:postcode":"16123;16123",
    "iso:country":"IT",
    "sg:address":"16123 Genova",
    "sg:city":"Genova",
    "sg:orig_category":"Forniture Per Abbigliamento E Pelletterie",
    "sg:phone":"+39 010 247 4511",
    "sg:postcode":"16123",
    "sg:province":"Genova",
    "wof:name":"Ferrari Roberto",
    "wof:placetype":"venue"
},
  "geometry": {"coordinates":[8.9314336777,44.4086227417],"type":"Point"}
}