{
  "type": "Feature",
  "properties": {
    "iso:country":"IT",
    "sg:address":"Via Verona 1, 37048 Legnago, Vr",
    "sg:classifiers":[
        {
            "category":"Banks & Credit Unions",
            "subcategory":"Bank",
            "type":"Services"
        }
    ],
    "wof:name":"Banca Di Credito Cooperativo Scaligera Orientale",
    "wof:placetype":"venue"
},
  "geometry": {"coordinates":[11.27996,45.186146],"type":"Point"}
}