{
  "type": "Feature",
  "properties": {
    "addr:full":"14100 Asti Asti Asti 14100",
    "addr:postcode":"14100;14100",
    "iso:country":"IT",
    "sg:address":"14100 Asti",
    "sg:city":"Asti",
    "sg:orig_category":"Fotografia - Servizi, Studi, Sviluppo E Stampa",
    "sg:phone":"+39 0141 353803",
    "sg:postcode":"14100",
    "sg:province":"Asti",
    "wof:name":"Zeta Solutions & C. Snc",
    "wof:placetype":"venue"
},
  "geometry": {"coordinates":[8.2136564255,44.9102401733],"type":"Point"}
}