{
  "type": "Feature",
  "properties": {
    "addr:full":"20092 Cinisello Balsamo Cinisello Balsamo Milano 20092",
    "addr:postcode":"20092;20092",
    "iso:country":"IT",
    "sg:address":"20092 Cinisello Balsamo",
    "sg:city":"Cinisello Balsamo",
    "sg:orig_category":"Apparecchiature E Sistemi Per Magazzinaggio E Movimentazione",
    "sg:phone":"+39 02 6604 8834",
    "sg:postcode":"20092",
    "sg:province":"Milano",
    "wof:name":"Locar Cinghie Srl",
    "wof:placetype":"venue"
},
  "geometry": {"coordinates":[9.194357,45.547085],"type":"Point"}
}