{
  "type": "Feature",
  "properties": {
    "addr:full":"40/a, Via Dossi 25050 Pian Camuno Pian Camuno Brescia 25050",
    "addr:housenumber":"40 / a",
    "addr:postcode":"25050;25050",
    "addr:street":"Via Dossi",
    "iso:country":"IT",
    "sg:address":"40/a, Via Dossi 25050 Pian Camuno",
    "sg:city":"Pian Camuno",
    "sg:classifiers":[
        {
            "category":"Manufacturing",
            "subcategory":"Metals",
            "type":"Manufacturing & Wholesale Goods"
        }
    ],
    "sg:phone":"+39 036 459 8998",
    "sg:postcode":"25050",
    "sg:province":"Brescia",
    "sg:tags":[
        "processing"
    ],
    "wof:name":"Selenia Metalli S.n.c.",
    "wof:placetype":"venue"
},
  "geometry": {"coordinates":[10.2229576111,45.5398292542],"type":"Point"}
}