{
  "type": "Feature",
  "properties": {
    "iso:country":"IT",
    "sg:address":"20090 Segrate",
    "sg:city":"Segrate",
    "sg:orig_category":"Apparecchiature E Sistemi Per Imballaggio E Confezionamento. Apparecchiature E Sistemi Per Magazzinaggio E Movimentazione",
    "sg:phone":"+39 02 7030 0547",
    "sg:postcode":"20090",
    "sg:province":"Milano",
    "wof:name":"Coop.e.l.p.e.a. Arl",
    "wof:placetype":"venue"
},
  "geometry": {"coordinates":[9.28811,45.474987],"type":"Point"}
}