{
  "type": "Feature",
  "properties": {
    "addr:full":"64016 Sant'egidio Alla Vibrata Paolantonio Teramo 64016",
    "addr:postcode":"64016;64016",
    "iso:country":"IT",
    "sg:address":"64016 Sant'egidio Alla Vibrata",
    "sg:city":"Paolantonio",
    "sg:orig_category":"Abbigliamento Esterno, Maglierie E Pelliccerie",
    "sg:phone":"+39 0861 840160",
    "sg:postcode":"64016",
    "sg:province":"Teramo",
    "wof:name":"Manifatture Lord (s.r.l.)",
    "wof:placetype":"venue"
},
  "geometry": {"coordinates":[13.711541,42.825233],"type":"Point"}
}