{
  "type": "Feature",
  "properties": {
    "iso:country":"IT",
    "sg:address":"Contrada Giungolo 70042 Mola Di Bari",
    "sg:city":"Mola di Bari",
    "sg:classifiers":[
        {
            "category":"Manufacturing",
            "subcategory":"Lumber",
            "type":"Manufacturing & Wholesale Goods"
        }
    ],
    "sg:phone":"+39 080 474 5853",
    "sg:postcode":"70042",
    "sg:province":"Bari",
    "sg:tags":[
        "wood"
    ],
    "wof:name":"Cooperativa Imballaggi Ortofrutticoli S.r.l.",
    "wof:placetype":"venue"
},
  "geometry": {"coordinates":[16.869291,41.126053],"type":"Point"}
}