{
  "type": "Feature",
  "properties": {
    "iso:country":"IT",
    "sg:address":"20144 Milano",
    "sg:city":"Milano",
    "sg:orig_category":"Informatica - Consulenza E Servizi. Pubblicita', Marketing E Comunicazione",
    "sg:phone":"+39 02 4895 2053",
    "sg:postcode":"20144",
    "sg:province":"Milano",
    "sg:website":"http://www.assetweb.it",
    "wof:name":"Asset Web Advisors Srl",
    "wof:placetype":"venue"
},
  "geometry": {"coordinates":[9.156719,45.453972],"type":"Point"}
}