{
  "type": "Feature",
  "properties": {
    "addr:full":"00141 Roma Roma Roma 00141",
    "addr:postcode":"00141;00141",
    "iso:country":"IT",
    "sg:address":"00141 Roma",
    "sg:city":"Roma",
    "sg:classifiers":[
        {
            "category":"Health Services",
            "subcategory":"Health Practitioner",
            "type":"Services"
        }
    ],
    "sg:phone":"+39 06 812 6232",
    "sg:postcode":"00141",
    "sg:province":"Roma",
    "sg:tags":[
        "medici"
    ],
    "wof:name":"Stanzione Arturo",
    "wof:placetype":"venue"
},
  "geometry": {"coordinates":[12.519944191,41.9432220459],"type":"Point"}
}