{
  "type": "Feature",
  "properties": {
    "iso:country":"IT",
    "sg:address":"25, Via Della Liberta' 10095 Grugliasco",
    "sg:city":"Grugliasco",
    "sg:classifiers":[
        {
            "category":"Shopping",
            "type":"Retail Goods"
        }
    ],
    "sg:phone":"+39 011 780 3432",
    "sg:postcode":"10095",
    "sg:province":"Torino",
    "sg:tags":[
        "finished",
        "-",
        "metallic"
    ],
    "wof:name":"Nuova Model-auto S.r.l.",
    "wof:placetype":"venue"
},
  "geometry": {"coordinates":[7.5890302658,45.0441169739],"type":"Point"}
}