{
  "type": "Feature",
  "properties": {
    "iso:country":"IT",
    "sg:address":"00131 Roma",
    "sg:city":"Roma",
    "sg:orig_category":"Autogru - Noleggio",
    "sg:phone":"+39 06 419 0048",
    "sg:postcode":"00131",
    "sg:province":"Roma",
    "wof:name":"A.c.f.",
    "wof:placetype":"venue"
},
  "geometry": {"coordinates":[12.650533,41.960419],"type":"Point"}
}