{
  "type": "Feature",
  "properties": {
    "addr:full":"Piazza Don Minzoni; Somma Vesuviana; 80049 Somma Vesuviana Napoli 80049",
    "addr:postcode":"80049;80049",
    "addr:street":"Piazza Don Minzoni",
    "iso:country":"IT",
    "sg:address":"Piazza Don Minzoni; Somma Vesuviana; 80049",
    "sg:city":"Somma Vesuviana",
    "sg:classifiers":[
        {
            "category":"Banks & Credit Unions",
            "subcategory":"Bank",
            "type":"Services"
        }
    ],
    "sg:phone":"+39 081 899 6675",
    "sg:postcode":"80049",
    "sg:province":"Napoli",
    "wof:name":"Istituto Bancario, San Paolo Di Torino Spa",
    "wof:placetype":"venue"
},
  "geometry": {"coordinates":[14.44093,40.87336],"type":"Point"}
}