{
  "type": "Feature",
  "properties": {
    "addr:full":"38051 Borgo Valsugana Borgo Trento 38051",
    "addr:postcode":"38051;38051",
    "iso:country":"IT",
    "sg:address":"38051 Borgo Valsugana",
    "sg:city":"Borgo",
    "sg:orig_category":"Servizi E Lavori Per Abbigliamento E Pelletterie. Scuole E Servizi Scolastici. Ricerca, Selezione E Formazione Del Personale",
    "sg:phone":"+39 0461 757217",
    "sg:postcode":"38051",
    "sg:province":"Trento",
    "wof:name":"Fondazione Romani - Sette - Smid",
    "wof:placetype":"venue"
},
  "geometry": {"coordinates":[11.454782,46.052979],"type":"Point"}
}