{
  "type": "Feature",
  "properties": {
    "iso:country":"IT",
    "sg:address":"44011 Argenta",
    "sg:city":"Argenta",
    "sg:orig_category":"Non-classified Establishments",
    "sg:phone":"+39 0532 310280",
    "sg:postcode":"44011",
    "sg:province":"Ferrara",
    "wof:name":"Dal Pozzo Andrea",
    "wof:placetype":"venue"
},
  "geometry": {"coordinates":[11.872684,44.623608],"type":"Point"}
}