{
  "type": "Feature",
  "properties": {
    "iso:country":"IT",
    "sg:address":"Via Iv Novembre, 13; Zibello; 43010",
    "sg:city":"Zibello",
    "sg:classifiers":[
        {
            "category":"Banks & Credit Unions",
            "subcategory":"Bank",
            "type":"Services"
        }
    ],
    "sg:phone":"+39 0524 95177",
    "sg:postcode":"43010",
    "sg:province":"Parma",
    "wof:name":"Cassa Di Risparmio Di Parma",
    "wof:placetype":"venue"
},
  "geometry": {"coordinates":[10.130796,45.019554],"type":"Point"}
}