{
  "type": "Feature",
  "properties": {
    "iso:country":"IT",
    "sg:address":"Via Asolana 7 43056 San Polo",
    "sg:city":"San Polo",
    "sg:classifiers":[
        {
            "category":"Wholesale",
            "subcategory":"Vending Machines",
            "type":"Manufacturing & Wholesale Goods"
        }
    ],
    "sg:phone":"+39 0521 819629",
    "sg:postcode":"43056",
    "sg:province":"Parma",
    "sg:tags":[
        "dispensing",
        "cup"
    ],
    "sg:website":"www.vendorplast.it",
    "wof:name":"Vendorplast Spa",
    "wof:placetype":"venue"
},
  "geometry": {"coordinates":[10.354818,44.890408],"type":"Point"}
}