{
  "type": "Feature",
  "properties": {
    "iso:country":"IT",
    "sg:address":"Strada Statale 98n 37 70033 Corato",
    "sg:city":"Corato",
    "sg:classifiers":[
        {
            "category":"Shopping",
            "subcategory":"Baby Store",
            "type":"Retail Goods"
        }
    ],
    "sg:phone":"+39 080 898 5200",
    "sg:postcode":"70033",
    "sg:province":"Bari",
    "sg:tags":[
        "children's",
        "underwear"
    ],
    "sg:website":"www.feelingmode.com",
    "wof:name":"Feeling Mode Srl",
    "wof:placetype":"venue"
},
  "geometry": {"coordinates":[16.869291,41.126053],"type":"Point"}
}