{
  "type": "Feature",
  "properties": {
    "iso:country":"IT",
    "sg:address":"47842 San Giovanni Marignano",
    "sg:orig_category":"Articoli Per Imballaggio E Confezionamento",
    "sg:phone":"+39 0541 957204",
    "sg:postcode":"47842",
    "sg:province":"Rimini",
    "wof:name":"Artigiana Borse Snc",
    "wof:placetype":"venue"
},
  "geometry": {"coordinates":[12.568791,44.06284],"type":"Point"}
}