{
  "type": "Feature",
  "properties": {
    "iso:country":"IT",
    "sg:address":"Via G.da Fabriano 2/4; Ancona; 60125",
    "sg:city":"Ancona",
    "sg:classifiers":[
        {
            "category":"Banks & Credit Unions",
            "subcategory":"Bank",
            "type":"Services"
        }
    ],
    "sg:phone":"+39 071 82721",
    "sg:postcode":"60125",
    "sg:province":"Ancona",
    "wof:name":"Instituto Di Credito Fondiario",
    "wof:placetype":"venue"
},
  "geometry": {"coordinates":[13.508392,43.610165],"type":"Point"}
}