{
  "type": "Feature",
  "properties": {
    "addr:full":"24, V. Verga 24127 Bergamo Bergamo Bergamo 24127",
    "addr:housenumber":"24",
    "addr:postcode":"24127;24127",
    "addr:street":"V. Verga",
    "iso:country":"IT",
    "sg:address":"24, V. Verga 24127 Bergamo",
    "sg:city":"Bergamo",
    "sg:classifiers":[
        {
            "category":"Professional",
            "subcategory":"Engineering",
            "type":"Services"
        }
    ],
    "sg:phone":"+39 035 454 8111",
    "sg:postcode":"24127",
    "sg:province":"Bergamo",
    "sg:tags":[
        "machine",
        "-",
        "mechanical"
    ],
    "sg:website":"http://www.elframo.it:ws_end: :mark:ws:http://www.paginegialle.it/elframosrl",
    "wof:name":"Elframo Srl",
    "wof:placetype":"venue"
},
  "geometry": {"coordinates":[9.638633,45.675056],"type":"Point"}
}