{
  "type": "Feature",
  "properties": {
    "iso:country":"IT",
    "sg:address":"Zona Industriale 73100 Lecce",
    "sg:city":"Lecce",
    "sg:classifiers":[
        {
            "category":"Building & Trades",
            "subcategory":"Construction",
            "type":"Services"
        }
    ],
    "sg:phone":"+39 0832 240967",
    "sg:postcode":"73100",
    "sg:province":"Lecce",
    "sg:tags":[
        "work",
        "public"
    ],
    "wof:name":"Impresa Latino S.r.l.",
    "wof:placetype":"venue"
},
  "geometry": {"coordinates":[18.139355,40.366394],"type":"Point"}
}