{
  "type": "Feature",
  "properties": {
    "iso:country":"IT",
    "sg:address":"20143 Milano",
    "sg:city":"Milano",
    "sg:orig_category":"Servizi E Lavori Per Ecologia E Smaltimento Rifiuti. Termotecnica E Riscaldamento, Apparecchiature E Servizi. Servizi Ausiliari Di Sorveglianza, Manutenzione E Pulizia",
    "sg:phone":"+39 02 837 3237",
    "sg:postcode":"20143",
    "sg:province":"Milano",
    "wof:name":"Bergamaschi Antonio",
    "wof:placetype":"venue"
},
  "geometry": {"coordinates":[9.162944,45.447426],"type":"Point"}
}