{
  "type": "Feature",
  "properties": {
    "addr:full":"00040 Monte Porzio Catone Monte Porzio Catone Roma 00040",
    "addr:housenumber":"00040",
    "addr:postcode":"00040",
    "addr:street":"Monte",
    "iso:country":"IT",
    "sg:address":"00040 Monte Porzio Catone",
    "sg:city":"Monte Porzio Catone",
    "sg:orig_category":"Acciaierie E Fonderie",
    "sg:phone":"+39 06 941 7943",
    "sg:postcode":"00040",
    "sg:province":"Roma",
    "wof:name":"Ferri Claudio",
    "wof:placetype":"venue"
},
  "geometry": {"coordinates":[12.686859,41.813194],"type":"Point"}
}