{
  "type": "Feature",
  "properties": {
    "iso:country":"IT",
    "sg:address":"28883 Gravellona Toce",
    "sg:city":"Gravellona Toce",
    "sg:classifiers":[
        {
            "category":"Government",
            "subcategory":"Office",
            "type":"Public Place"
        }
    ],
    "sg:phone":"+39 0323 848154",
    "sg:postcode":"28883",
    "sg:province":"Verbano-Cusio-Ossola",
    "sg:tags":[
        "graphic",
        "publishing",
        "supply",
        "industry",
        "equipment",
        "paper",
        "machinery",
        "supplies"
    ],
    "wof:name":"Zucchi Incisori Snc Di Zucchi Giancarlo E Davide & C.",
    "wof:placetype":"venue"
},
  "geometry": {"coordinates":[8.272465,46.139969],"type":"Point"}
}