{
  "type": "Feature",
  "properties": {
    "iso:country":"IT",
    "sg:address":"22075 Lurate Caccivio",
    "sg:city":"Lurate Caccivio",
    "sg:orig_category":"Trasporti E Spedizioni Merci",
    "sg:phone":"+39 031 390814",
    "sg:postcode":"22075",
    "sg:province":"Como",
    "wof:name":"Bartolini Spa",
    "wof:placetype":"venue"
},
  "geometry": {"coordinates":[9.018231,45.793938],"type":"Point"}
}