{
  "type": "Feature",
  "properties": {
    "iso:country":"IT",
    "sg:address":"21013 Gallarate",
    "sg:city":"Gallarate",
    "sg:orig_category":"Servizi Per Aziende, Manifestazioni E Supporto Agli Scambi Commerciali",
    "sg:phone":"+39 0331 794139",
    "sg:postcode":"21013",
    "sg:province":"Varese",
    "wof:name":"Ambietti Enrico",
    "wof:placetype":"venue"
},
  "geometry": {"coordinates":[8.789274,45.67371],"type":"Point"}
}