{
  "type": "Feature",
  "properties": {
    "iso:country":"IT",
    "sg:address":"50122 Firenze",
    "sg:city":"Firenze",
    "sg:orig_category":"Scuole E Servizi Scolastici. Ricerca, Selezione E Formazione Del Personale",
    "sg:phone":"+39 055 267171",
    "sg:postcode":"50122",
    "sg:province":"Firenze",
    "wof:name":"Centro Di Telemarketing Spa",
    "wof:placetype":"venue"
},
  "geometry": {"coordinates":[11.256194,43.773697],"type":"Point"}
}