{
  "type": "Feature",
  "properties": {
    "addr:full":"80, Via Cussignacco 33040 Pradamano Pradamano Udine 33040",
    "addr:postcode":"33040;33040",
    "addr:street":"Via Cussignacco",
    "iso:country":"IT",
    "sg:address":"80, Via Cussignacco 33040 Pradamano",
    "sg:city":"Pradamano",
    "sg:classifiers":[
        {
            "category":"Food & Beverages",
            "subcategory":"Groceries & Convenience Stores",
            "type":"Retail Goods"
        }
    ],
    "sg:phone":"+39 0432 670864",
    "sg:postcode":"33040",
    "sg:province":"Udine",
    "sg:tags":[
        "drink"
    ],
    "wof:name":"Fantinel (s.p.a.)",
    "wof:placetype":"venue"
},
  "geometry": {"coordinates":[13.276899,46.024677],"type":"Point"}
}