{
  "type": "Feature",
  "properties": {
    "addr:full":"10040 Almese Almese Torino 10040",
    "addr:housenumber":"10040",
    "addr:postcode":"10040",
    "addr:street":"Almese Almese",
    "iso:country":"IT",
    "sg:address":"10040 Almese",
    "sg:city":"Almese",
    "sg:orig_category":"Automazione E Macchine Per Ufficio. Servizi Ausiliari Di Certificati, Riproduzioni, Disegni E Foto",
    "sg:phone":"+39 011 935 2643",
    "sg:postcode":"10040",
    "sg:province":"Torino",
    "sg:website":"http://www.euroged.it",
    "wof:name":"Euroged Srl",
    "wof:placetype":"venue"
},
  "geometry": {"coordinates":[7.39916,45.117329],"type":"Point"}
}