{
  "type": "Feature",
  "properties": {
    "addr:full":"29, Via Camillo Cavour 26010 Robecco D'oglio Cremona 26010",
    "addr:postcode":"26010;26010",
    "addr:street":"Via Camillo Cavour",
    "iso:country":"IT",
    "sg:address":"29, Via Camillo Cavour 26010 Robecco D'oglio",
    "sg:classifiers":[
        {
            "category":"Professional",
            "subcategory":"Printing & Photocopies",
            "type":"Services"
        }
    ],
    "sg:phone":"+39 0372 921183",
    "sg:postcode":"26010",
    "sg:province":"Cremona",
    "wof:name":"Eredi Salami Ferruccio Di Salami G. & M. (s.n.c.)",
    "wof:placetype":"venue"
},
  "geometry": {"coordinates":[10.0261354446,45.1334991455],"type":"Point"}
}