{
  "type": "Feature",
  "properties": {
    "addr:full":"09131 Cagliari Cagliari Cagliari 09131",
    "addr:postcode":"09131;09131",
    "iso:country":"IT",
    "sg:address":"09131 Cagliari",
    "sg:city":"Cagliari",
    "sg:classifiers":[
        {
            "category":"Professional",
            "subcategory":"Engineering",
            "type":"Services"
        }
    ],
    "sg:phone":"+39 070 452 0046",
    "sg:postcode":"09131",
    "sg:province":"Cagliari",
    "sg:tags":[
        "equipment",
        "product",
        "industrial",
        "electrical"
    ],
    "wof:name":"Gattermayer Srl",
    "wof:placetype":"venue"
},
  "geometry": {"coordinates":[9.127629,39.232998],"type":"Point"}
}