{
  "type": "Feature",
  "properties": {
    "iso:country":"IT",
    "sg:address":"19, Via Pola 10135 Torino",
    "sg:city":"Torino",
    "sg:orig_category":"Miscellaneous Products",
    "sg:phone":"+39 011 397 9600",
    "sg:postcode":"10135",
    "sg:province":"Torino",
    "wof:name":"Pasa (s.a.s.)",
    "wof:placetype":"venue"
},
  "geometry": {"coordinates":[7.5683588982,45.0681114197],"type":"Point"}
}