{
  "type": "Feature",
  "properties": {
    "iso:country":"IT",
    "sg:address":"71, Localita' Amerique 11020 Quart",
    "sg:city":"Quart",
    "sg:classifiers":[
        {
            "category":"Shopping",
            "subcategory":"Clothing, Apparel, & Fashions",
            "type":"Retail Goods"
        }
    ],
    "sg:phone":"+39 0165 773511",
    "sg:postcode":"11020",
    "sg:province":"Aosta",
    "sg:tags":[
        "clothes"
    ],
    "wof:name":"Green Sport Monte Bianco S.r.l.",
    "wof:placetype":"venue"
},
  "geometry": {"coordinates":[7.375489,45.741497],"type":"Point"}
}