{
  "type": "Feature",
  "properties": {
    "addr:full":"89129 Reggio Calabria RC",
    "addr:postcode":"89129",
    "iso:country":"IT",
    "sg:address":"89129 Reggio Calabria",
    "sg:orig_category":"Prodotti E Manufatti In Materie Plastiche. Forniture Per Edilizia E Lavori Pubblici",
    "sg:phone":"+39 0965 51483",
    "sg:province":"RC",
    "wof:name":"Icom Srl",
    "wof:placetype":"venue"
},
  "geometry": {"coordinates":[15.6383199692,38.0823974609],"type":"Point"}
}