{
  "type": "Feature",
  "properties": {
    "iso:country":"IT",
    "sg:address":"Via Marco Polo 2 36075 Montecchio Maggiore",
    "sg:city":"Montecchio Maggiore",
    "sg:classifiers":[
        {
            "category":"Home & Garden",
            "subcategory":"Hardware",
            "type":"Retail Goods"
        }
    ],
    "sg:phone":"+39 0444 499059",
    "sg:postcode":"36075",
    "sg:province":"Vicenza",
    "sg:tags":[
        "compressor",
        "air"
    ],
    "sg:website":"www.goldnet.it",
    "wof:name":"F.lli. Ghiotto Snc",
    "wof:placetype":"venue"
},
  "geometry": {"coordinates":[11.486465,45.523853],"type":"Point"}
}