{
  "type": "Feature",
  "properties": {
    "iso:country":"IT",
    "sg:address":"2, Via Giacomo Matteotti 33044 Manzano",
    "sg:city":"Manzano",
    "sg:classifiers":[
        {
            "category":"Home & Garden",
            "subcategory":"Home Furnishings",
            "type":"Retail Goods"
        }
    ],
    "sg:phone":"+39 0432 742311",
    "sg:postcode":"33044",
    "sg:province":"Udine",
    "sg:tags":[
        "household"
    ],
    "wof:name":"Group Sedia S.r.l.",
    "wof:placetype":"venue"
},
  "geometry": {"coordinates":[13.391801,45.992702],"type":"Point"}
}