{
  "type": "Feature",
  "properties": {
    "iso:country":"IT",
    "sg:address":"Via Cernobbio 22100 Como",
    "sg:city":"Como",
    "sg:classifiers":[
        {
            "category":"Travel",
            "subcategory":"Travel Agent",
            "type":"Entertainment"
        }
    ],
    "sg:phone":"+39 390 315 161",
    "sg:postcode":"22100",
    "sg:province":"Como",
    "sg:tags":[
        "business"
    ],
    "wof:name":"Albergo Grand Hotel Di Como",
    "wof:placetype":"venue"
},
  "geometry": {"coordinates":[9.097437,45.817856],"type":"Point"}
}