{
  "type": "Feature",
  "properties": {
    "iso:country":"IT",
    "sg:address":"Via Sisemol 30 36100 Vicenza",
    "sg:city":"Vicenza",
    "sg:classifiers":[
        {
            "category":"Shopping",
            "subcategory":"Jewelry",
            "type":"Retail Goods"
        }
    ],
    "sg:phone":"+39 0444 570900",
    "sg:postcode":"36100",
    "sg:province":"Vicenza",
    "sg:tags":[
        "jewellery",
        "gold"
    ],
    "wof:name":"Mario Carlan & C. Snc",
    "wof:placetype":"venue"
},
  "geometry": {"coordinates":[11.526389,45.575279],"type":"Point"}
}