{
  "type": "Feature",
  "properties": {
    "iso:country":"IT",
    "sg:address":"Via Del Lazzaretto 60044 Fabriano",
    "sg:city":"Fabriano",
    "sg:classifiers":[
        {
            "category":"Manufacturing",
            "subcategory":"Lumber",
            "type":"Manufacturing & Wholesale Goods"
        }
    ],
    "sg:phone":"+39 0732 629262",
    "sg:postcode":"60044",
    "sg:province":"Ancona",
    "sg:tags":[
        "wood"
    ],
    "wof:name":"I.p.f. (s.r.l.)",
    "wof:placetype":"venue"
},
  "geometry": {"coordinates":[12.913117,43.344955],"type":"Point"}
}