{
  "type": "Feature",
  "properties": {
    "iso:country":"IT",
    "sg:address":"21, Via Cooperazione 38010 Taio",
    "sg:classifiers":[
        {
            "category":"Farming",
            "subcategory":"Livestock Farm",
            "type":"Manufacturing & Wholesale Goods"
        }
    ],
    "sg:phone":"+39 0463 461500",
    "sg:postcode":"38010",
    "sg:province":"Trento",
    "sg:tags":[
        "agriculture"
    ],
    "wof:name":"C.o.c.e.a. Cooperativa Ortofrutticola Centro Anaunia S.c.r.l.",
    "wof:placetype":"venue"
},
  "geometry": {"coordinates":[11.070822,46.301449],"type":"Point"}
}