{
  "type": "Feature",
  "properties": {
    "iso:country":"IT",
    "sg:address":"26837 Cassino D'alberi",
    "sg:orig_category":"Forniture Per Abbigliamento E Pelletterie",
    "sg:phone":"+39 02 989168",
    "sg:postcode":"26837",
    "sg:province":"Lodi",
    "wof:name":"Passero Luciano",
    "wof:placetype":"venue"
},
  "geometry": {"coordinates":[9.388256073,45.3915138245],"type":"Point"}
}