{
  "type": "Feature",
  "properties": {
    "iso:country":"IT",
    "sg:address":"55012 Capannori",
    "sg:city":"Capannori",
    "sg:orig_category":"Alberghi E Strutture Extra Alberghiere",
    "sg:phone":"+39 0583 979168",
    "sg:postcode":"55012",
    "sg:province":"Lucca",
    "sg:website":"http://www.lindavacanze.it",
    "wof:name":"Linda Di Mei Marco & C. Sas",
    "wof:placetype":"venue"
},
  "geometry": {"coordinates":[10.571397,43.764362],"type":"Point"}
}