{
  "type": "Feature",
  "properties": {
    "iso:country":"IT",
    "sg:address":"41016 Novi Di Modena",
    "sg:city":"Novi di Modena",
    "sg:classifiers":[
        {
            "category":"Personal",
            "subcategory":"Nail Salon",
            "type":"Services"
        }
    ],
    "sg:phone":"+39 059 676220",
    "sg:postcode":"41016",
    "sg:province":"Modena",
    "sg:tags":[
        "scale"
    ],
    "wof:name":"Ideal Scale",
    "wof:placetype":"venue"
},
  "geometry": {"coordinates":[10.889512,44.882446],"type":"Point"}
}