{
  "type": "Feature",
  "properties": {
    "iso:country":"IT",
    "sg:address":"Via Umberto I 86; Bagni Di Lucca; 55022",
    "sg:city":"Bagni di Lucca",
    "sg:classifiers":[
        {
            "category":"Banks & Credit Unions",
            "subcategory":"Bank",
            "type":"Services"
        }
    ],
    "sg:phone":"+39 0583 87744",
    "sg:postcode":"55022",
    "sg:province":"Lucca",
    "wof:name":"Banca Toscana Spa",
    "wof:placetype":"venue"
},
  "geometry": {"coordinates":[10.591592,44.01086],"type":"Point"}
}