{
  "type": "Feature",
  "properties": {
    "addr:full":"26010 Bagnolo Cremasco Bagnolo Cremasco Cremona 26010",
    "addr:postcode":"26010;cremasco;26010",
    "addr:street":"Cremona",
    "iso:country":"IT",
    "sg:address":"26010 Bagnolo Cremasco",
    "sg:city":"Bagnolo Cremasco",
    "sg:orig_category":"Macchine, Impianti Ed Attrezzature Industria Delle Materie Plastiche E Gomma",
    "sg:phone":"+39 0373 649620",
    "sg:postcode":"26010",
    "sg:province":"Cremona",
    "wof:name":"A.p.i. S.r.l.",
    "wof:placetype":"venue"
},
  "geometry": {"coordinates":[9.621364,45.364315],"type":"Point"}
}