{
  "type": "Feature",
  "properties": {
    "addr:full":"20038 Seregno Seregno Milano 20038",
    "addr:postcode":"20038;20038",
    "iso:country":"IT",
    "sg:address":"20038 Seregno",
    "sg:city":"Seregno",
    "sg:orig_category":"Biancheria Intima Ed Abbigliamento Intimo - Produzione E Ingrosso",
    "sg:phone":"+39 036 223 8068",
    "sg:postcode":"20038",
    "sg:province":"Milano",
    "wof:name":"Venere Srl",
    "wof:placetype":"venue"
},
  "geometry": {"coordinates":[9.203573,45.651917],"type":"Point"}
}