{
  "type": "Feature",
  "properties": {
    "addr:full":"18, Strada Rocca Grimalda 15076 Ovada Ovada Alessandria 15076",
    "addr:postcode":"15076;15076",
    "addr:street":"Strada Rocca Grimalda",
    "iso:country":"IT",
    "sg:address":"18, Strada Rocca Grimalda 15076 Ovada",
    "sg:city":"Ovada",
    "sg:classifiers":[
        {
            "category":"Autos & Motor Vehicles",
            "subcategory":"Automobile Sales",
            "type":"Retail Goods"
        }
    ],
    "sg:phone":"+39 0143 838200",
    "sg:postcode":"15076",
    "sg:province":"Alessandria",
    "sg:tags":[
        "motor-cars"
    ],
    "wof:name":"Francesco Cavanna S.p.a.",
    "wof:placetype":"venue"
},
  "geometry": {"coordinates":[8.6464090347,44.6466636658],"type":"Point"}
}