{
  "type": "Feature",
  "properties": {
    "iso:country":"IT",
    "sg:address":"131, Corso Allamano Canonico Giuseppe 10098 Rivoli",
    "sg:city":"Rivoli",
    "sg:classifiers":[
        {
            "category":"Shopping",
            "type":"Retail Goods"
        }
    ],
    "sg:phone":"+39 011 959 3808",
    "sg:postcode":"10098",
    "sg:province":"Torino",
    "sg:tags":[
        "finished",
        "-",
        "metallic"
    ],
    "wof:name":"I.e.m. Snc",
    "wof:placetype":"venue"
},
  "geometry": {"coordinates":[7.5874910355,45.0520401001],"type":"Point"}
}