{
  "type": "Feature",
  "properties": {
    "addr:full":"Via Xi Febbraio 58 20040 Briosco Briosco Milano 20040",
    "addr:housenumber":"58",
    "addr:postcode":"20040;20040",
    "addr:street":"Via Xi Febbraio",
    "iso:country":"IT",
    "sg:address":"Via Xi Febbraio 58 20040 Briosco",
    "sg:city":"Briosco",
    "sg:classifiers":[
        {
            "category":"Train Station",
            "subcategory":"Light Rail",
            "type":"Transportation"
        }
    ],
    "sg:phone":"+39 036 295056",
    "sg:postcode":"20040",
    "sg:province":"Milano",
    "sg:tags":[
        "lighting"
    ],
    "sg:website":"www.betalux.it",
    "wof:name":"Betalux Srl",
    "wof:placetype":"venue"
},
  "geometry": {"coordinates":[9.188141,45.463688],"type":"Point"}
}