{
  "type": "Feature",
  "properties": {
    "addr:full":"98, V. Del Perlar 37135 Verona Verona Verona 37135",
    "addr:housenumber":"98",
    "addr:postcode":"37135;37135",
    "addr:street":"V. Del Perlar",
    "iso:country":"IT",
    "sg:address":"98, V. Del Perlar 37135 Verona",
    "sg:city":"Verona",
    "sg:classifiers":[
        {
            "category":"Shopping",
            "type":"Retail Goods"
        }
    ],
    "sg:phone":"+39 39045500855",
    "sg:postcode":"37135",
    "sg:province":"Verona",
    "sg:tags":[
        "finished",
        "-",
        "metallic"
    ],
    "sg:website":"http://www.zape.it",
    "wof:name":"Zap\u00c8 Spa",
    "wof:placetype":"venue"
},
  "geometry": {"coordinates":[10.9684076309,45.4103622437],"type":"Point"}
}