{
  "type": "Feature",
  "properties": {
    "addr:full":"28, Via Resegone 20050 Camparada Camparada Milano 20050",
    "addr:postcode":"20050;20050",
    "addr:street":"Via Resegone",
    "iso:country":"IT",
    "sg:address":"28, Via Resegone 20050 Camparada",
    "sg:city":"Camparada",
    "sg:classifiers":[
        {
            "category":"Manufacturing",
            "subcategory":"Paper Products",
            "type":"Manufacturing & Wholesale Goods"
        }
    ],
    "sg:phone":"+39 039 698 1551",
    "sg:postcode":"20050",
    "sg:province":"Milano",
    "sg:tags":[
        "cardboard"
    ],
    "wof:name":"Indes Imballaggi (s.r.l.)",
    "wof:placetype":"venue"
},
  "geometry": {"coordinates":[9.287352562,45.6555747986],"type":"Point"}
}