{
  "type": "Feature",
  "properties": {
    "iso:country":"IT",
    "sg:address":"12, Via John Fitzgerald Kennedy 46020 Pegognaga",
    "sg:city":"Pegognaga",
    "sg:classifiers":[
        {
            "category":"Professional",
            "subcategory":"Engineering",
            "type":"Services"
        }
    ],
    "sg:phone":"+39 39037655431",
    "sg:postcode":"46020",
    "sg:province":"Mantova",
    "sg:tags":[
        "machine",
        "-",
        "mechanical"
    ],
    "wof:name":"Lavorwash S.r.l.",
    "wof:placetype":"venue"
},
  "geometry": {"coordinates":[10.797698,45.160366],"type":"Point"}
}