{
  "type": "Feature",
  "properties": {
    "iso:country":"IT",
    "sg:address":"56/b, Via Emilia Ovest 42048 Rubiera",
    "sg:classifiers":[
        {
            "category":"Shopping",
            "subcategory":"Crafts & Fabrics",
            "type":"Retail Goods"
        }
    ],
    "sg:phone":"+39 0522 621111",
    "sg:postcode":"42048",
    "sg:province":"Reggio Nell'Emilia",
    "sg:tags":[
        "ceramic"
    ],
    "wof:name":"Ceramica C.i.r. (s.p.a.)",
    "wof:placetype":"venue"
},
  "geometry": {"coordinates":[10.772233,44.654705],"type":"Point"}
}