{
  "type": "Feature",
  "properties": {
    "iso:country":"IT",
    "sg:address":"220, Via Degli Archi 91026 Mazara Del Vallo",
    "sg:city":"Mazara del Vallo",
    "sg:classifiers":[
        {
            "category":"Professional",
            "subcategory":"Engineering",
            "type":"Services"
        }
    ],
    "sg:phone":"+39 0923 934159",
    "sg:postcode":"91026",
    "sg:province":"Trapani",
    "sg:tags":[
        "machine",
        "-",
        "mechanical"
    ],
    "wof:name":"Mav International Spa",
    "wof:placetype":"venue"
},
  "geometry": {"coordinates":[12.594131,37.666924],"type":"Point"}
}