{
  "type": "Feature",
  "properties": {
    "addr:full":"Via Campano, 51/c; Venafro; 86079 Venafro Isernia 86079",
    "addr:housenumber":"51 / c",
    "addr:postcode":"86079;86079",
    "addr:street":"Via Campano;Venafro",
    "iso:country":"IT",
    "sg:address":"Via Campano, 51/c; Venafro; 86079",
    "sg:city":"Venafro",
    "sg:classifiers":[
        {
            "category":"Banks & Credit Unions",
            "subcategory":"Bank",
            "type":"Services"
        }
    ],
    "sg:phone":"+39 0865 900717",
    "sg:postcode":"86079",
    "sg:province":"Isernia",
    "wof:name":"Cassa Di Risparmio Di Roma",
    "wof:placetype":"venue"
},
  "geometry": {"coordinates":[14.046198,41.485207],"type":"Point"}
}