{
  "type": "Feature",
  "properties": {
    "iso:country":"IT",
    "sg:address":"57025 Piombino",
    "sg:city":"Piombino",
    "sg:orig_category":"Servizi Al Turismo. Trasporto Pubblico E Privato",
    "sg:phone":"+39 0565 260111",
    "sg:postcode":"57025",
    "sg:province":"Livorno",
    "sg:website":"http://www.paginegialle.it/atmlivorno",
    "wof:name":"Atm Spa",
    "wof:placetype":"venue"
},
  "geometry": {"coordinates":[10.323494,43.581089],"type":"Point"}
}