{
  "type": "Feature",
  "properties": {
    "addr:full":"Cso L. G. Pecile 80/82 33034 Fagagna Fagagna Udine 33034",
    "addr:housenumber":"80 / 82",
    "addr:postcode":"33034;33034",
    "addr:street":"Cso;G. Pecile",
    "iso:country":"IT",
    "sg:address":"Cso L. G. Pecile 80/82 33034 Fagagna",
    "sg:city":"Fagagna",
    "sg:classifiers":[
        {
            "category":"Manufacturing",
            "subcategory":"Paper Products",
            "type":"Manufacturing & Wholesale Goods"
        }
    ],
    "sg:phone":"+39 0432 800341",
    "sg:postcode":"33034",
    "sg:province":"Udine",
    "sg:tags":[
        "adhesive",
        "self-adhesive",
        "labels",
        "label"
    ],
    "sg:website":"www.grafiche-tonutti.it",
    "wof:name":"Tonutti Tecniche Grafiche Spa",
    "wof:placetype":"venue"
},
  "geometry": {"coordinates":[13.230724,46.064941],"type":"Point"}
}