{
  "type": "Feature",
  "properties": {
    "addr:full":"35010 Vigonza Vigonza Padova 35010",
    "addr:postcode":"35010;35010",
    "iso:country":"IT",
    "sg:address":"35010 Vigonza",
    "sg:city":"Vigonza",
    "sg:orig_category":"Minuterie - Produzione E Commercio",
    "sg:phone":"+39 049 893 3051",
    "sg:postcode":"35010",
    "sg:province":"Padova",
    "wof:name":"Promistamp Snc",
    "wof:placetype":"venue"
},
  "geometry": {"coordinates":[11.9563064575,45.4359664917],"type":"Point"}
}