{
  "type": "Feature",
  "properties": {
    "iso:country":"IT",
    "sg:address":"20052 Monza",
    "sg:city":"Monza",
    "sg:orig_category":"Impiantistica E Prodotti Tecnologici Per Edilizia. Elettronica Professionale E Di Consumo. Accessori Dei Mezzi Di Trasporto. Forniture Industriali Per Prevenzione, Controllo E Sicurezza",
    "sg:phone":"+39 039 200 4239",
    "sg:postcode":"20052",
    "sg:province":"Milano",
    "sg:website":"http://www.cnasicurezza.it",
    "wof:name":"C.n.a. Sicurezza",
    "wof:placetype":"venue"
},
  "geometry": {"coordinates":[9.206251,45.558376],"type":"Point"}
}