{
  "type": "Feature",
  "properties": {
    "iso:country":"IT",
    "sg:address":"48100 Ravenna",
    "sg:city":"Ravenna",
    "sg:orig_category":"Autotrasporti",
    "sg:phone":"+39 0544 436501",
    "sg:postcode":"48100",
    "sg:province":"Ravenna",
    "wof:name":"C.a.p.a. Consorzio Artigiano Piccoli Autotrasporti",
    "wof:placetype":"venue"
},
  "geometry": {"coordinates":[11.874741,44.436066],"type":"Point"}
}