{
  "type": "Feature",
  "properties": {
    "iso:country":"IT",
    "sg:address":"20156 Milano",
    "sg:city":"Milano",
    "sg:orig_category":"Utensili Meccanici E Materiali",
    "sg:phone":"+39 02 308 3884",
    "sg:postcode":"20156",
    "sg:province":"Milano",
    "wof:name":"Twm Di Tomasi Ermes & C. (s.a.s.)",
    "wof:placetype":"venue"
},
  "geometry": {"coordinates":[9.149088,45.499359],"type":"Point"}
}