{
  "type": "Feature",
  "properties": {
    "iso:country":"IT",
    "sg:address":"09010 Pula",
    "sg:city":"Pula",
    "sg:orig_category":"Studi E Consulenze Amministrative, Commerciali E Aziendali. Consulenze Tecniche, Amministrative E Perizie. Professionisti - Studi E Servizi Ed Associazioni Di Interesse Aziendale",
    "sg:phone":"+39 070 920 9955",
    "sg:postcode":"09010",
    "sg:province":"Cagliari",
    "wof:name":"Studio Data Snc",
    "wof:placetype":"venue"
},
  "geometry": {"coordinates":[9.020523,39.282539],"type":"Point"}
}