{
  "type": "Feature",
  "properties": {
    "iso:country":"IT",
    "sg:address":"70, Viale Falzarego 41049 Sassuolo",
    "sg:city":"Sassuolo",
    "sg:classifiers":[
        {
            "category":"Professional",
            "subcategory":"Printing & Photocopies",
            "type":"Services"
        }
    ],
    "sg:phone":"+39 0536 998411",
    "sg:postcode":"41049",
    "sg:province":"Modena",
    "wof:name":"Serigrafica Tosi (s.r.l.)",
    "wof:placetype":"venue"
},
  "geometry": {"coordinates":[10.8046417236,44.5590171814],"type":"Point"}
}