{
  "type": "Feature",
  "properties": {
    "iso:country":"IT",
    "sg:address":"2, Via Grecia 06012 Citta' Di Castello",
    "sg:classifiers":[
        {
            "category":"Professional",
            "subcategory":"Engineering",
            "type":"Services"
        }
    ],
    "sg:phone":"+39 075 854 0021",
    "sg:postcode":"06012",
    "sg:province":"Perugia",
    "sg:tags":[
        "machine",
        "-",
        "mechanical"
    ],
    "wof:name":"Sitrex (s.r.l.)",
    "wof:placetype":"venue"
},
  "geometry": {"coordinates":[12.240748,43.36784],"type":"Point"}
}