{
  "type": "Feature",
  "properties": {
    "iso:country":"IT",
    "sg:address":"16123 Genova",
    "sg:city":"Genova",
    "sg:orig_category":"Forniture Alle Strutture Ricettive. Forniture Per Attivita' Commerciali Ed Artigianali",
    "sg:phone":"+39 010 248 5560",
    "sg:postcode":"16123",
    "sg:province":"Genova",
    "sg:website":"http://www.radif.it",
    "wof:name":"Radif Spa",
    "wof:placetype":"venue"
},
  "geometry": {"coordinates":[8.9328975677,44.4073448181],"type":"Point"}
}