{
  "type": "Feature",
  "properties": {
    "iso:country":"IT",
    "sg:address":"47, Via Carmine 84016 Pagani",
    "sg:city":"Pagani",
    "sg:classifiers":[
        {
            "category":"Banks & Credit Unions",
            "subcategory":"Investment Brokerage",
            "type":"Services"
        }
    ],
    "sg:phone":"+39 39081916066",
    "sg:postcode":"84016",
    "sg:province":"Salerno",
    "sg:tags":[
        "-",
        "transport",
        "related"
    ],
    "wof:name":"Depositi Sud (s.r.l.)",
    "wof:placetype":"venue"
},
  "geometry": {"coordinates":[14.623005,40.741283],"type":"Point"}
}