{
  "type": "Feature",
  "properties": {
    "addr:full":"80016 Marano Di Napoli Marano di Napoli Napoli 80016",
    "addr:postcode":"80016;80016",
    "iso:country":"IT",
    "sg:address":"80016 Marano Di Napoli",
    "sg:city":"Marano di Napoli",
    "sg:orig_category":"Automobili - Commercio",
    "sg:phone":"+39 081 576 2361",
    "sg:postcode":"80016",
    "sg:province":"Napoli",
    "wof:name":"Polverino Auto",
    "wof:placetype":"venue"
},
  "geometry": {"coordinates":[14.165874,40.896626],"type":"Point"}
}