{
  "type": "Feature",
  "properties": {
    "addr:full":"Via Trento 2; Stradella; 27049 Stradella Pavia 27049",
    "addr:housenumber":"2",
    "addr:postcode":"27049;27049",
    "addr:street":"Via Trento",
    "iso:country":"IT",
    "sg:address":"Via Trento 2; Stradella; 27049",
    "sg:city":"Stradella",
    "sg:classifiers":[
        {
            "category":"Banks & Credit Unions",
            "subcategory":"Bank",
            "type":"Services"
        }
    ],
    "sg:phone":"+39 0385 42423",
    "sg:postcode":"27049",
    "sg:province":"Pavia",
    "wof:name":"Banca Nazionale Del Lavoro Spa",
    "wof:placetype":"venue"
},
  "geometry": {"coordinates":[9.298689,45.075844],"type":"Point"}
}