{
  "type": "Feature",
  "properties": {
    "iso:country":"IT",
    "sg:address":"18, Piazza Dei Tintori 41057 Spilamberto",
    "sg:city":"Spilamberto",
    "sg:classifiers":[
        {
            "category":"Real Estate",
            "subcategory":"Surveying",
            "type":"Services"
        }
    ],
    "sg:phone":"+39 39059781159",
    "sg:postcode":"41057",
    "sg:province":"Modena",
    "sg:tags":[
        "equipment",
        "material",
        "good",
        "-",
        "handling"
    ],
    "wof:name":"Mocar (s.r.l.)",
    "wof:placetype":"venue"
},
  "geometry": {"coordinates":[11.008211,44.543819],"type":"Point"}
}