{
  "type": "Feature",
  "properties": {
    "iso:country":"IT",
    "sg:address":"37124 Verona",
    "sg:city":"Verona",
    "sg:orig_category":"Associazioni Sindacali E Di Categoria",
    "sg:phone":"+39 045 830 0219",
    "sg:postcode":"37124",
    "sg:province":"Verona",
    "wof:name":"C.n.a. - Confederazione Nazionale Artigianato E Piccola E Media Impresa",
    "wof:placetype":"venue"
},
  "geometry": {"coordinates":[10.973129,45.459595],"type":"Point"}
}