{
  "type": "Feature",
  "properties": {
    "addr:full":"46029 Suzzara Sailetto Mantova 46029",
    "addr:postcode":"46029;46029",
    "iso:country":"IT",
    "sg:address":"46029 Suzzara",
    "sg:city":"Sailetto",
    "sg:orig_category":"Formaggi E Latticini - Produzione E Ingrosso",
    "sg:phone":"+39 0376 527045",
    "sg:postcode":"46029",
    "sg:province":"Mantova",
    "wof:name":"Industria Casearia Belladelli Snc",
    "wof:placetype":"venue"
},
  "geometry": {"coordinates":[10.7406024933,45.0293655396],"type":"Point"}
}