{
  "type": "Feature",
  "properties": {
    "iso:country":"IT",
    "sg:address":"20142 Milano",
    "sg:city":"Milano",
    "sg:classifiers":[
        {
            "category":"Health Services",
            "subcategory":"Health Practitioner",
            "type":"Services"
        }
    ],
    "sg:phone":"+39 02 8951 1676",
    "sg:postcode":"20142",
    "sg:province":"Milano",
    "sg:tags":[
        "medici"
    ],
    "wof:name":"Pedone Alberto",
    "wof:placetype":"venue"
},
  "geometry": {"coordinates":[9.1725549698,45.4427146912],"type":"Point"}
}