{
  "type": "Feature",
  "properties": {
    "iso:country":"IT",
    "sg:address":"88900 Crotone",
    "sg:city":"Crotone",
    "sg:classifiers":[
        {
            "category":"Health Services",
            "subcategory":"Health Practitioner",
            "type":"Services"
        }
    ],
    "sg:phone":"+39 0962 905205",
    "sg:postcode":"88900",
    "sg:province":"Crotone",
    "sg:tags":[
        "medici"
    ],
    "wof:name":"Loiero Dr. Rosa Anna",
    "wof:placetype":"venue"
},
  "geometry": {"coordinates":[17.077566,39.100124],"type":"Point"}
}