{
  "type": "Feature",
  "properties": {
    "iso:country":"IT",
    "sg:address":"Via Matteotti 2; Gubbio; 06024",
    "sg:city":"Gubbio",
    "sg:classifiers":[
        {
            "category":"Banks & Credit Unions",
            "subcategory":"Bank",
            "type":"Services"
        }
    ],
    "sg:phone":"+39 075 922 0091",
    "sg:postcode":"06024",
    "sg:province":"Perugia",
    "wof:name":"Banca Toscana Spa",
    "wof:placetype":"venue"
},
  "geometry": {"coordinates":[12.575749,43.350941],"type":"Point"}
}