{
  "type": "Feature",
  "properties": {
    "iso:country":"IT",
    "sg:address":"23, Via Marcello 35011 Campodarsego",
    "sg:city":"Campodarsego",
    "sg:classifiers":[
        {
            "category":"Manufacturing",
            "subcategory":"Rubber & Plastics",
            "type":"Manufacturing & Wholesale Goods"
        }
    ],
    "sg:phone":"+39 049 920 1193",
    "sg:postcode":"35011",
    "sg:province":"Padova",
    "wof:name":"Nord Gomma",
    "wof:placetype":"venue"
},
  "geometry": {"coordinates":[11.9007863998,45.4979248047],"type":"Point"}
}