{
  "type": "Feature",
  "properties": {
    "iso:country":"IT",
    "sg:address":"57127 Livorno",
    "sg:city":"Livorno",
    "sg:classifiers":[
        {
            "category":"Building & Trades",
            "subcategory":"Construction",
            "type":"Services"
        }
    ],
    "sg:phone":"+39 0586 403324",
    "sg:postcode":"57127",
    "sg:province":"Livorno",
    "sg:tags":[
        "equipment",
        "heat",
        "heating",
        "engineering"
    ],
    "wof:name":"Scotti & C. Srl",
    "wof:placetype":"venue"
},
  "geometry": {"coordinates":[10.321787,43.577908],"type":"Point"}
}