{
  "type": "Feature",
  "properties": {
    "iso:country":"IT",
    "sg:address":"16138 Genova",
    "sg:city":"Genova",
    "sg:orig_category":"Non-classified Establishments",
    "sg:phone":"+39 010 835 4022",
    "sg:postcode":"16138",
    "sg:province":"Genova",
    "wof:name":"Ar.co.arredamenti Srl",
    "wof:placetype":"venue"
},
  "geometry": {"coordinates":[8.982195,44.463146],"type":"Point"}
}