{
  "type": "Feature",
  "properties": {
    "iso:country":"IT",
    "sg:address":"67, Via Paolo Emilio 00192 Roma",
    "sg:city":"Roma",
    "sg:classifiers":[
        {
            "category":"Food & Beverages",
            "subcategory":"Groceries & Convenience Stores",
            "type":"Retail Goods"
        }
    ],
    "sg:phone":"+39 39063243548",
    "sg:postcode":"00192",
    "sg:province":"Roma",
    "sg:tags":[
        "product",
        "related"
    ],
    "wof:name":"Giuliani Giulio",
    "wof:placetype":"venue"
},
  "geometry": {"coordinates":[12.4629964828,41.9098510742],"type":"Point"}
}