{
  "type": "Feature",
  "properties": {
    "iso:country":"IT",
    "sg:address":"Via Pier Paolo Vergerio 44; Padova; 35126",
    "sg:city":"Padova",
    "sg:classifiers":[
        {
            "category":"Banks & Credit Unions",
            "subcategory":"Bank",
            "type":"Services"
        }
    ],
    "sg:phone":"+39 049 802 2316",
    "sg:postcode":"35126",
    "sg:province":"Padova",
    "wof:name":"Cariverona Banca Spa",
    "wof:placetype":"venue"
},
  "geometry": {"coordinates":[11.885617,45.393753],"type":"Point"}
}