{
  "type": "Feature",
  "properties": {
    "addr:full":"10121 Torino Torino Torino 10121",
    "addr:postcode":"10121;10121",
    "iso:country":"IT",
    "sg:address":"10121 Torino",
    "sg:city":"Torino",
    "sg:orig_category":"Banche E Servizi Finanziari",
    "sg:phone":"+39 011 518 4541",
    "sg:postcode":"10121",
    "sg:province":"Torino",
    "wof:name":"B.n.p. Sim S.p.a.",
    "wof:placetype":"venue"
},
  "geometry": {"coordinates":[7.578364,45.062443],"type":"Point"}
}