{
  "type": "Feature",
  "properties": {
    "iso:country":"IT",
    "sg:address":"96100 Siracusa",
    "sg:city":"Siracusa",
    "sg:orig_category":"Macchine, Impianti Ed Attrezzature Per Industria Alimentare E Bevande. Elettrodomestici. Macchine E Impianti Per Attivita' Commerciali Ed Artigianali",
    "sg:phone":"+39 0931 491515",
    "sg:postcode":"96100",
    "sg:province":"Siracusa",
    "wof:name":"S.a.r.c. Srl",
    "wof:placetype":"venue"
},
  "geometry": {"coordinates":[15.272404,37.095722],"type":"Point"}
}