{
  "type": "Feature",
  "properties": {
    "iso:country":"IT",
    "sg:address":"40121 Bologna",
    "sg:city":"Bologna",
    "sg:orig_category":"Istituti Di Bellezza",
    "sg:phone":"+39 051 248826",
    "sg:postcode":"40121",
    "sg:province":"Bologna",
    "wof:name":"New Genesis",
    "wof:placetype":"venue"
},
  "geometry": {"coordinates":[11.341296,44.501881],"type":"Point"}
}