{
  "type": "Feature",
  "properties": {
    "addr:full":"37132 Verona Verona Verona 37132",
    "addr:postcode":"37132;37132",
    "iso:country":"IT",
    "sg:address":"37132 Verona",
    "sg:city":"Verona",
    "sg:orig_category":"Elaboratori Elettronici",
    "sg:phone":"+39 349 533 8471",
    "sg:postcode":"37132",
    "sg:province":"Verona",
    "wof:name":"Aerre System Di Rossi Alessandro",
    "wof:placetype":"venue"
},
  "geometry": {"coordinates":[11.058744,45.419487],"type":"Point"}
}