{
  "type": "Feature",
  "properties": {
    "iso:country":"IT",
    "sg:address":"Via La Pira 23 10028 Trofarello",
    "sg:city":"Trofarello",
    "sg:classifiers":[
        {
            "category":"Building & Trades",
            "subcategory":"Equipment Rental",
            "type":"Services"
        }
    ],
    "sg:phone":"+39 011 680 4222",
    "sg:postcode":"10028",
    "sg:province":"Torino",
    "sg:tags":[
        "plant",
        "industrial",
        "electrotechnical"
    ],
    "sg:website":"www.forteck.it",
    "wof:name":"Forteck Srl",
    "wof:placetype":"venue"
},
  "geometry": {"coordinates":[7.733247,44.974609],"type":"Point"}
}