{
  "type": "Feature",
  "properties": {
    "addr:full":"20031 Cesano Maderno Cesano Maderno Milano 20031",
    "addr:postcode":"20031;20031",
    "iso:country":"IT",
    "sg:address":"20031 Cesano Maderno",
    "sg:city":"Cesano Maderno",
    "sg:orig_category":"Servizi Di Magazzinaggio E Movimentazione",
    "sg:phone":"+39 036 264 1201",
    "sg:postcode":"20031",
    "sg:province":"Milano",
    "wof:name":"Logistica Service Soc.coop.r.l.",
    "wof:placetype":"venue"
},
  "geometry": {"coordinates":[9.146258,45.6189],"type":"Point"}
}