{
  "type": "Feature",
  "properties": {
    "iso:country":"IT",
    "sg:address":"07046 Porto Torres",
    "sg:city":"Porto Torres",
    "sg:orig_category":"Edilizia - Materiali",
    "sg:phone":"+39 079 516017",
    "sg:postcode":"07046",
    "sg:province":"Sassari",
    "wof:name":"Turris Espansi Packaging Srl",
    "wof:placetype":"venue"
},
  "geometry": {"coordinates":[8.341701,40.828373],"type":"Point"}
}