{
  "type": "Feature",
  "properties": {
    "addr:full":"80146 Napoli Napoli Napoli 80146",
    "addr:housenumber":"80146",
    "addr:postcode":"80146",
    "iso:country":"IT",
    "sg:address":"80146 Napoli",
    "sg:city":"Napoli",
    "sg:orig_category":"Articoli Da Regalo. Arte Ed Artigianato Artistico. Shopping",
    "sg:phone":"+39 081 559 3269",
    "sg:postcode":"80146",
    "sg:province":"Napoli",
    "wof:name":"Scialo' Alfredo",
    "wof:placetype":"venue"
},
  "geometry": {"coordinates":[14.306034,40.836189],"type":"Point"}
}