{
  "type": "Feature",
  "properties": {
    "iso:country":"IT",
    "sg:address":"Via Industriale 28 39023 Laas",
    "sg:classifiers":[
        {
            "category":"Food & Beverages",
            "subcategory":"Fruits & Vegetables",
            "type":"Retail Goods"
        }
    ],
    "sg:phone":"+39 0473 626160",
    "sg:postcode":"39023",
    "sg:province":"Bolzano/Bozen",
    "sg:website":"www.vi-p.it",
    "wof:name":"Alpe Alpine Landwirtschaftliche Coop",
    "wof:placetype":"venue"
},
  "geometry": {"coordinates":[10.6893854141,46.6211700439],"type":"Point"}
}