{
  "type": "Feature",
  "properties": {
    "iso:country":"IT",
    "sg:address":"21013 Gallarate",
    "sg:city":"Gallarate",
    "sg:orig_category":"Casellari E Cassette Postali, Bacheche",
    "sg:phone":"+39 0331 795413",
    "sg:postcode":"21013",
    "sg:province":"Varese",
    "wof:name":"Minoli Ferramenta Di Minoli Alessandra & C. Snc",
    "wof:placetype":"venue"
},
  "geometry": {"coordinates":[8.795529,45.707436],"type":"Point"}
}