{
  "type": "Feature",
  "properties": {
    "addr:full":"Via Cav. Vallero Pietro 6 10080 Salassa Salassa Torino 10080",
    "addr:housenumber":"6",
    "addr:postcode":"10080;10080",
    "addr:street":"Via Cav. Vallero Pietro",
    "iso:country":"IT",
    "sg:address":"Via Cav. Vallero Pietro 6 10080 Salassa",
    "sg:city":"Salassa",
    "sg:classifiers":[
        {
            "category":"Organizations",
            "subcategory":"Labor Organization",
            "type":"Services"
        }
    ],
    "sg:phone":"+39 0124 36333",
    "sg:postcode":"10080",
    "sg:province":"Torino",
    "sg:tags":[
        "purification",
        "system",
        "air"
    ],
    "wof:name":"Ecoplus S.r.l.",
    "wof:placetype":"venue"
},
  "geometry": {"coordinates":[7.686619,45.07056],"type":"Point"}
}