{
  "type": "Feature",
  "properties": {
    "iso:country":"IT",
    "sg:address":"1, Via Amendola 84087 Sarno",
    "sg:city":"Sarno",
    "sg:classifiers":[
        {
            "category":"Food & Beverages",
            "subcategory":"Groceries & Convenience Stores",
            "type":"Retail Goods"
        }
    ],
    "sg:phone":"+39 081 513 6594",
    "sg:postcode":"84087",
    "sg:province":"Salerno",
    "sg:tags":[
        "product",
        "related"
    ],
    "wof:name":"Damiano Mancuso Da.ma. Spa",
    "wof:placetype":"venue"
},
  "geometry": {"coordinates":[14.765912056,40.6779556274],"type":"Point"}
}