{
  "type": "Feature",
  "properties": {
    "addr:full":"47023 Cesena Cesena Forl\u00ec-Cesena 47023",
    "addr:postcode":"47023;47023",
    "iso:country":"IT",
    "sg:address":"47023 Cesena",
    "sg:city":"Cesena",
    "sg:orig_category":"Articoli Per Imballaggio E Confezionamento",
    "sg:phone":"+39 0547 353190",
    "sg:postcode":"47023",
    "sg:province":"Forl\u00ec-Cesena",
    "wof:name":"Concessione Placuzzi Di Placuzzi Rosella E C. Snc",
    "wof:placetype":"venue"
},
  "geometry": {"coordinates":[12.268746,44.197124],"type":"Point"}
}