{
  "type": "Feature",
  "properties": {
    "iso:country":"IT",
    "sg:address":"00144 Roma",
    "sg:city":"Roma",
    "sg:orig_category":"Animali Domestici, Articoli Ed Alimenti - Vendita Al Dettaglio",
    "sg:phone":"+39 06 501 0073",
    "sg:postcode":"00144",
    "sg:province":"Roma",
    "wof:name":"Animalmania",
    "wof:placetype":"venue"
},
  "geometry": {"coordinates":[12.470948,41.81834],"type":"Point"}
}