{
  "type": "Feature",
  "properties": {
    "addr:full":"Via E. Mattei, 9/10 62010 Pollenza Pollenza Macerata 62010",
    "addr:housenumber":"9 / 10",
    "addr:postcode":"62010;62010",
    "addr:street":"Via E. Mattei",
    "iso:country":"IT",
    "sg:address":"Via E. Mattei, 9/10 62010 Pollenza",
    "sg:city":"Pollenza",
    "sg:classifiers":[
        {
            "category":"Banks & Credit Unions",
            "subcategory":"Bureau De Change",
            "type":"Services"
        }
    ],
    "sg:phone":"+39 0733 202124",
    "sg:postcode":"62010",
    "sg:province":"Macerata",
    "sg:tags":[
        "drawer"
    ],
    "sg:website":"www.dezilegnami.it",
    "wof:name":"Dezi Legnami Spa",
    "wof:placetype":"venue"
},
  "geometry": {"coordinates":[13.396723,43.251236],"type":"Point"}
}