{
  "type": "Feature",
  "properties": {
    "iso:country":"IT",
    "sg:address":"10154 Torino",
    "sg:city":"Torino",
    "sg:orig_category":"Pasticceria E Confetteria Prodotti - Produzione E Ingrosso",
    "sg:phone":"+39 011 248 5620",
    "sg:postcode":"10154",
    "sg:province":"Torino",
    "wof:name":"3p Ingros Srl",
    "wof:placetype":"venue"
},
  "geometry": {"coordinates":[8.3989200592,45.4623451233],"type":"Point"}
}