{
  "type": "Feature",
  "properties": {
    "iso:country":"IT",
    "sg:address":"84091 Battipaglia",
    "sg:city":"Battipaglia",
    "sg:orig_category":"Impianti Idraulici E Termoidraulici",
    "sg:phone":"+39 0828 303131",
    "sg:postcode":"84091",
    "sg:province":"Salerno",
    "wof:name":"Termotecnica Industriale Srl",
    "wof:placetype":"venue"
},
  "geometry": {"coordinates":[14.989319,40.595394],"type":"Point"}
}