{
  "type": "Feature",
  "properties": {
    "addr:full":"Contrada Piana Marsala 90015 Cefalu' Palermo 90015",
    "addr:postcode":"90015 cefalu;90015",
    "addr:street":"Contrada Piana Marsala",
    "iso:country":"IT",
    "sg:address":"Contrada Piana Marsala 90015 Cefalu'",
    "sg:classifiers":[
        {
            "category":"Food & Beverages",
            "subcategory":"Groceries & Convenience Stores",
            "type":"Retail Goods"
        }
    ],
    "sg:phone":"+39 0921 427396",
    "sg:postcode":"90015",
    "sg:province":"Palermo",
    "sg:tags":[
        "product",
        "related"
    ],
    "wof:name":"Ankora Sas Di Ranzino Adriana",
    "wof:placetype":"venue"
},
  "geometry": {"coordinates":[13.3613758087,38.1156196594],"type":"Point"}
}