{
  "type": "Feature",
  "properties": {
    "addr:full":"22060 Carugo Carugo Como 22060",
    "addr:postcode":"22060;22060",
    "iso:country":"IT",
    "sg:address":"22060 Carugo",
    "sg:city":"Carugo",
    "sg:orig_category":"Forniture Per Edilizia E Lavori Pubblici",
    "sg:phone":"+39 031 758216",
    "sg:postcode":"22060",
    "sg:province":"Como",
    "wof:name":"Bosisio Tiziano",
    "wof:placetype":"venue"
},
  "geometry": {"coordinates":[9.1978549957,45.7090835571],"type":"Point"}
}