{
  "type": "Feature",
  "properties": {
    "addr:full":"Via Iv Novembre 11; Cison Di Valmarino; 31030 Cison di Valmarino Treviso 31030",
    "addr:housenumber":"11",
    "addr:postcode":"31030;31030",
    "addr:street":"Via Iv Novembre;Valmarino",
    "iso:country":"IT",
    "sg:address":"Via Iv Novembre 11; Cison Di Valmarino; 31030",
    "sg:city":"Cison di Valmarino",
    "sg:classifiers":[
        {
            "category":"Banks & Credit Unions",
            "subcategory":"Bank",
            "type":"Services"
        }
    ],
    "sg:phone":"+39 0438 975375",
    "sg:postcode":"31030",
    "sg:province":"Treviso",
    "wof:name":"Banca Popolare, C. Piva Di Valdobbiadene Scarl",
    "wof:placetype":"venue"
},
  "geometry": {"coordinates":[12.14424,45.967369],"type":"Point"}
}