{
  "type": "Feature",
  "properties": {
    "addr:full":"Via Roma, 28; Ventimiglia; 18039 Ventimiglia Imperia 18039",
    "addr:housenumber":"28",
    "addr:postcode":"18039;18039",
    "addr:street":"Via Roma",
    "iso:country":"IT",
    "sg:address":"Via Roma, 28; Ventimiglia; 18039",
    "sg:city":"Ventimiglia",
    "sg:classifiers":[
        {
            "category":"Banks & Credit Unions",
            "subcategory":"Bank",
            "type":"Services"
        }
    ],
    "sg:phone":"+39 0184 358155",
    "sg:postcode":"18039",
    "sg:province":"Imperia",
    "wof:name":"Banco Di Roma",
    "wof:placetype":"venue"
},
  "geometry": {"coordinates":[7.610896,43.789761],"type":"Point"}
}