{
  "type": "Feature",
  "properties": {
    "addr:full":"90010 Ficarazzi Ficarazzi Palermo 90010",
    "addr:postcode":"90010;90010",
    "iso:country":"IT",
    "sg:address":"90010 Ficarazzi",
    "sg:city":"Ficarazzi",
    "sg:orig_category":"Agenzie Immobiliari",
    "sg:phone":"+39 091 636 0925",
    "sg:postcode":"90010",
    "sg:province":"Palermo",
    "wof:name":"Romano Nancy Agenzia Immobiliare",
    "wof:placetype":"venue"
},
  "geometry": {"coordinates":[13.458046,38.087589],"type":"Point"}
}