{
  "type": "Feature",
  "properties": {
    "iso:country":"IT",
    "sg:address":"18012 Bordighera",
    "sg:city":"Bordighera",
    "sg:orig_category":"Non-classified Establishments",
    "sg:phone":"+39 0184 295028",
    "sg:postcode":"18012",
    "sg:province":"Imperia",
    "wof:name":"Forieri Sestilio",
    "wof:placetype":"venue"
},
  "geometry": {"coordinates":[7.659338,43.792419],"type":"Point"}
}