{
  "type": "Feature",
  "properties": {
    "iso:country":"IT",
    "sg:address":"110, Via Statale 63 42044 Gualtieri",
    "sg:classifiers":[
        {
            "category":"Professional",
            "subcategory":"Engineering",
            "type":"Services"
        }
    ],
    "sg:phone":"+39 0522 833024",
    "sg:postcode":"42044",
    "sg:province":"Reggio Nell'Emilia",
    "sg:tags":[
        "machine",
        "-",
        "mechanical"
    ],
    "wof:name":"Omas (s.r.l.)",
    "wof:placetype":"venue"
},
  "geometry": {"coordinates":[10.629029,44.876484],"type":"Point"}
}