{
  "type": "Feature",
  "properties": {
    "addr:full":"00168 Roma Roma Roma 00168",
    "addr:postcode":"00168;00168",
    "iso:country":"IT",
    "sg:address":"00168 Roma",
    "sg:city":"Roma",
    "sg:classifiers":[
        {
            "category":"Health Services",
            "subcategory":"Health Practitioner",
            "type":"Services"
        }
    ],
    "sg:phone":"+39 06 338 1929",
    "sg:postcode":"00168",
    "sg:province":"Roma",
    "sg:tags":[
        "medici"
    ],
    "wof:name":"Crescenzi Sergio",
    "wof:placetype":"venue"
},
  "geometry": {"coordinates":[12.421564,41.93528],"type":"Point"}
}