{
  "type": "Feature",
  "properties": {
    "addr:full":"21052 Busto Arsizio Busto Arsizio Varese 21052",
    "addr:postcode":"21052;21052",
    "iso:country":"IT",
    "sg:address":"21052 Busto Arsizio",
    "sg:city":"Busto Arsizio",
    "sg:orig_category":"Accessori Dei Mezzi Di Trasporto",
    "sg:phone":"+39 0331 382793",
    "sg:postcode":"21052",
    "sg:province":"Varese",
    "wof:name":"Autoteam Srl",
    "wof:placetype":"venue"
},
  "geometry": {"coordinates":[8.820677,45.670712],"type":"Point"}
}