{
  "type": "Feature",
  "properties": {
    "iso:country":"IT",
    "sg:address":"43100 Parma",
    "sg:city":"Baganzola",
    "sg:orig_category":"Materiali Semilavorati Metallici",
    "sg:phone":"+39 0521 603038",
    "sg:postcode":"43100",
    "sg:province":"Parma",
    "wof:name":"C.e.i. Art Consorzio Elettromeccanici Imprese Artigiane",
    "wof:placetype":"venue"
},
  "geometry": {"coordinates":[10.309288,44.857605],"type":"Point"}
}