{
  "type": "Feature",
  "properties": {
    "addr:full":"Via Tangenziale Est 02100 Rieti Rieti Rieti 02100",
    "addr:postcode":"02100;02100",
    "addr:street":"Via Tangenziale Est",
    "iso:country":"IT",
    "sg:address":"Via Tangenziale Est 02100 Rieti",
    "sg:city":"Rieti",
    "sg:classifiers":[
        {
            "category":"Manufacturing",
            "subcategory":"Metals",
            "type":"Manufacturing & Wholesale Goods"
        }
    ],
    "sg:phone":"+39 0746 220185",
    "sg:postcode":"02100",
    "sg:province":"Rieti",
    "sg:tags":[
        "metallurgy",
        "metalworking"
    ],
    "wof:name":"Aguzzi F.lli Costruzioni Meccaniche Ed Affini",
    "wof:placetype":"venue"
},
  "geometry": {"coordinates":[12.8611793518,42.4030570984],"type":"Point"}
}