{
  "type": "Feature",
  "properties": {
    "iso:country":"IT",
    "sg:address":"62029 Tolentino",
    "sg:city":"Tolentino",
    "sg:orig_category":"Automobili E Mezzi Di Trasporto",
    "sg:phone":"+39 0733 968190",
    "sg:postcode":"62029",
    "sg:province":"Macerata",
    "wof:name":"Rascioni Elio Snc Di Rascioni Corrado & C.",
    "wof:placetype":"venue"
},
  "geometry": {"coordinates":[13.289436,43.22419],"type":"Point"}
}