{
  "type": "Feature",
  "properties": {
    "iso:country":"IT",
    "sg:address":"20124 Milano",
    "sg:city":"Milano",
    "sg:orig_category":"Ristorazione E Locali Pubblici Affini. Servizi Per Lo Sport E Il Tempo Libero. Alberghi E Strutture Extra Alberghiere. Ristoranti Ed Esercizi Affini",
    "sg:phone":"+39 02 670 5544",
    "sg:postcode":"20124",
    "sg:province":"Milano",
    "sg:website":"http://www.turismoverdelombardia.org",
    "wof:name":"Turismo Verde Lombardia",
    "wof:placetype":"venue"
},
  "geometry": {"coordinates":[9.20997,45.485718],"type":"Point"}
}