{
  "type": "Feature",
  "properties": {
    "iso:country":"IT",
    "sg:address":"47900 Rimini",
    "sg:city":"Rimini",
    "sg:orig_category":"Idraulici E Lattonieri",
    "sg:phone":"+39 0541 384118",
    "sg:postcode":"47900",
    "sg:province":"Rimini",
    "wof:name":"La Zincogronda Di Vannini & Canini Snc",
    "wof:placetype":"venue"
},
  "geometry": {"coordinates":[12.571202,44.026272],"type":"Point"}
}