{
  "type": "Feature",
  "properties": {
    "iso:country":"IT",
    "sg:address":"20123 Milano",
    "sg:city":"Milano",
    "sg:orig_category":"Agenzie Ed Enti Turistici. Acqua, Luce, Gas E Societa' Di Esercizio Pubblico",
    "sg:phone":"+39 02 880 8151",
    "sg:postcode":"20123",
    "sg:province":"Milano",
    "sg:website":"http://www.visitbritain.com/ciao",
    "wof:name":"Ente Nazionale Turismo Britannico",
    "wof:placetype":"venue"
},
  "geometry": {"coordinates":[9.176592,45.466015],"type":"Point"}
}