{
  "type": "Feature",
  "properties": {
    "iso:country":"IT",
    "sg:address":"42100 Reggio Emilia",
    "sg:orig_category":"Centri Di Estetica E Cosmesi E Servizi",
    "sg:phone":"+39 0522 551090",
    "sg:postcode":"42100",
    "sg:province":"Reggio Nell'Emilia",
    "wof:name":"Replay Style Snc",
    "wof:placetype":"venue"
},
  "geometry": {"coordinates":[10.653484,44.690685],"type":"Point"}
}