{
  "type": "Feature",
  "properties": {
    "iso:country":"IT",
    "sg:address":"00171 Roma",
    "sg:city":"Roma",
    "sg:orig_category":"Non-classified Establishments",
    "sg:phone":"+39 06 215 3211",
    "sg:postcode":"00171",
    "sg:province":"Roma",
    "wof:name":"Medical S.p.o. Srl",
    "wof:placetype":"venue"
},
  "geometry": {"coordinates":[12.567095,41.891357],"type":"Point"}
}