{
  "type": "Feature",
  "properties": {
    "addr:full":"14, Via Ciro Menotti 24024 Gandino Gandino Bergamo 24024",
    "addr:postcode":"24024;24024",
    "addr:street":"Via Ciro Menotti",
    "iso:country":"IT",
    "sg:address":"14, Via Ciro Menotti 24024 Gandino",
    "sg:city":"Gandino",
    "sg:classifiers":[
        {
            "category":"Shopping",
            "subcategory":"Crafts & Fabrics",
            "type":"Retail Goods"
        }
    ],
    "sg:phone":"+39 39035745185",
    "sg:postcode":"24024",
    "sg:province":"Bergamo",
    "sg:tags":[
        "linen"
    ],
    "wof:name":"Lanificio Rudelli S.r.l.",
    "wof:placetype":"venue"
},
  "geometry": {"coordinates":[9.9061737061,45.8089942932],"type":"Point"}
}