{
  "type": "Feature",
  "properties": {
    "addr:full":"15020 Ponzano Monferrato Ponzano Monferrato Alessandria 15020",
    "addr:postcode":"15020;15020",
    "iso:country":"IT",
    "sg:address":"15020 Ponzano Monferrato",
    "sg:city":"Ponzano Monferrato",
    "sg:orig_category":"Servizi Per Lo Sport E Il Tempo Libero. Servizi Al Turismo. Acqua, Luce, Gas E Societa' Di Esercizio Pubblico",
    "sg:phone":"+39 0141 927120",
    "sg:postcode":"15020",
    "sg:province":"Alessandria",
    "wof:name":"Parco Naturale E Area Attrezzata Del Sacro Monte Di Crea",
    "wof:placetype":"venue"
},
  "geometry": {"coordinates":[8.263227,45.085468],"type":"Point"}
}