{
  "type": "Feature",
  "properties": {
    "addr:full":"Via Pasubio, 38; 20025 Legnano, Milano, Italy Legnano Milano 20025",
    "addr:housenumber":"38",
    "addr:postcode":"20025;20025",
    "addr:street":"Via Pasubio",
    "iso:country":"IT",
    "sg:address":"Via Pasubio, 38; 20025 Legnano, Milano, Italy",
    "sg:city":"Legnano",
    "sg:classifiers":[
        {
            "category":"Industrial Area",
            "type":"Public Place"
        }
    ],
    "sg:phone":"+39 0331 446302",
    "sg:postcode":"20025",
    "sg:province":"Milano",
    "sg:tags":[
        "large",
        "private"
    ],
    "sg:website":"www.crespi.it",
    "wof:name":"Giovanni Crespi S.p.a.",
    "wof:placetype":"venue"
},
  "geometry": {"coordinates":[8.9189376831,45.5751571655],"type":"Point"}
}