{
  "type": "Feature",
  "properties": {
    "iso:country":"IT",
    "sg:address":"25040 Corte Franca",
    "sg:city":"Corte Franca",
    "sg:orig_category":"Agricoltura - Attrezzi, Prodotti E Forniture",
    "sg:phone":"+39 030 984491",
    "sg:postcode":"25040",
    "sg:province":"Brescia",
    "wof:name":"Marini Srl",
    "wof:placetype":"venue"
},
  "geometry": {"coordinates":[9.99867,45.647156],"type":"Point"}
}