{
  "type": "Feature",
  "properties": {
    "addr:full":"7, Via Bernina 20158 Milano Milano Milano 20158",
    "addr:postcode":"20158;20158",
    "addr:street":"Via Bernina",
    "iso:country":"IT",
    "sg:address":"7, Via Bernina 20158 Milano",
    "sg:city":"Milano",
    "sg:classifiers":[
        {
            "category":"Shopping",
            "subcategory":"Computers & Home Electronics",
            "type":"Retail Goods"
        }
    ],
    "sg:phone":"+39 390 269 6321",
    "sg:postcode":"20158",
    "sg:province":"Milano",
    "sg:tags":[
        "electronic",
        "electrical",
        "equipment"
    ],
    "wof:name":"C & A Buying Support Company It. Srl",
    "wof:placetype":"venue"
},
  "geometry": {"coordinates":[9.180695,45.4944],"type":"Point"}
}