{
  "type": "Feature",
  "properties": {
    "iso:country":"IT",
    "sg:address":"20133 Milano",
    "sg:city":"Milano",
    "sg:classifiers":[
        {
            "category":"Health Services",
            "subcategory":"Health Practitioner",
            "type":"Services"
        }
    ],
    "sg:phone":"+39 02 730587",
    "sg:postcode":"20133",
    "sg:province":"Milano",
    "sg:tags":[
        "medici"
    ],
    "wof:name":"De Liso Sebastiano",
    "wof:placetype":"venue"
},
  "geometry": {"coordinates":[9.229692,45.471371],"type":"Point"}
}