{
  "type": "Feature",
  "properties": {
    "addr:full":"Via Consolare 97/a; Priverno",
    "addr:housenumber":"97 / a",
    "addr:street":"Via Consolare",
    "iso:country":"IT",
    "sg:address":"Via Consolare 97/a; Priverno",
    "sg:classifiers":[
        {
            "category":"Banks & Credit Unions",
            "subcategory":"Bank",
            "type":"Services"
        }
    ],
    "sg:phone":"+39 0773 903323",
    "wof:name":"Banca Di Roma",
    "wof:placetype":"venue"
},
  "geometry": {"coordinates":[13.181355,41.473965],"type":"Point"}
}