{
  "type": "Feature",
  "properties": {
    "addr:full":"Via A. Varisco 18 42020 Albinea Reggio Nell'Emilia 42020",
    "addr:housenumber":"18",
    "addr:postcode":"42020;42020",
    "addr:street":"Via A. Varisco",
    "iso:country":"IT",
    "sg:address":"Via A. Varisco 18 42020 Albinea",
    "sg:classifiers":[
        {
            "category":"Retail",
            "subcategory":"Repair Shop",
            "type":"Services"
        }
    ],
    "sg:phone":"+39 0522 347511",
    "sg:postcode":"42020",
    "sg:province":"Reggio Nell'Emilia",
    "sg:tags":[
        "milking",
        "pail"
    ],
    "sg:website":"www.interpuls.com",
    "wof:name":"Interpuls Spa",
    "wof:placetype":"venue"
},
  "geometry": {"coordinates":[10.5751543045,44.6252746582],"type":"Point"}
}