{
  "type": "Feature",
  "properties": {
    "addr:full":"Via Pastore,10 - Viserba Monte 47900 Rimini Rimini Rimini 47900",
    "addr:housenumber":"10",
    "addr:postcode":"47900;47900",
    "addr:street":"Via Pastore;Viserba Monte",
    "iso:country":"IT",
    "sg:address":"Via Pastore,10 - Viserba Monte 47900 Rimini",
    "sg:city":"Rimini",
    "sg:classifiers":[
        {
            "category":"Shopping",
            "subcategory":"Clothing, Apparel, & Fashions",
            "type":"Retail Goods"
        }
    ],
    "sg:phone":"+39 0541 733390",
    "sg:postcode":"47900",
    "sg:province":"Rimini",
    "sg:tags":[
        "image",
        "clothing",
        "basic"
    ],
    "wof:name":"Milo & Co Di Mini Loris & C.",
    "wof:placetype":"venue"
},
  "geometry": {"coordinates":[12.566257,44.06078],"type":"Point"}
}