{
  "type": "Feature",
  "properties": {
    "iso:country":"IT",
    "sg:address":"20124 Milano",
    "sg:city":"Milano",
    "sg:orig_category":"Cinematografia E Radiotelevisione. Servizi Per Aziende, Manifestazioni E Supporto Agli Scambi Commerciali",
    "sg:phone":"+39 02 6707 5753",
    "sg:postcode":"20124",
    "sg:province":"Milano",
    "wof:name":"Andriolo Gianni - V.g.a.",
    "wof:placetype":"venue"
},
  "geometry": {"coordinates":[9.200332,45.482574],"type":"Point"}
}