{
  "type": "Feature",
  "properties": {
    "iso:country":"IT",
    "sg:address":"37064 Povegliano Veronese",
    "sg:city":"Povegliano Veronese",
    "sg:orig_category":"Carni, Salumi E Pesci. Zootecnia E Pesca, Allevamento Piccoli Animali",
    "sg:phone":"+39 045 797 1120",
    "sg:postcode":"37064",
    "sg:province":"Verona",
    "wof:name":"Perina Srl",
    "wof:placetype":"venue"
},
  "geometry": {"coordinates":[10.871801,45.349277],"type":"Point"}
}