{
  "type": "Feature",
  "properties": {
    "addr:full":"15046 San Salvatore Monferrato San Salvatore Monferrato Alessandria 15046",
    "addr:housenumber":"15046",
    "addr:postcode":"15046",
    "addr:street":"San",
    "iso:country":"IT",
    "sg:address":"15046 San Salvatore Monferrato",
    "sg:city":"San Salvatore Monferrato",
    "sg:orig_category":"Gioielleria, Oreficeria E Argenteria",
    "sg:phone":"+39 0131 237949",
    "sg:postcode":"15046",
    "sg:province":"Alessandria",
    "wof:name":"Marinotto & Frascarolo",
    "wof:placetype":"venue"
},
  "geometry": {"coordinates":[8.566776,44.991219],"type":"Point"}
}