{
  "type": "Feature",
  "properties": {
    "iso:country":"IT",
    "sg:address":"33030 Campoformido",
    "sg:city":"Campoformido",
    "sg:orig_category":"Pompe. Ricambi E Componenti Dei Mezzi Di Trasporto",
    "sg:phone":"+39 0432 663370",
    "sg:postcode":"33030",
    "sg:province":"Udine",
    "wof:name":"Diesel Car Snc Di Lius Della Pieta' Giorgio & C.",
    "wof:placetype":"venue"
},
  "geometry": {"coordinates":[13.1752309799,46.0297317505],"type":"Point"}
}