{
  "type": "Feature",
  "properties": {
    "iso:country":"IT",
    "sg:address":"60124 Ancona",
    "sg:city":"Ancona",
    "sg:orig_category":"Televisori, Videoregistratori E Radio - Vendita Al Dettaglio",
    "sg:phone":"+39 071 358 0405",
    "sg:postcode":"60124",
    "sg:province":"Ancona",
    "sg:website":"http://www.beostore.it",
    "wof:name":"Beostore Snc Di Calderigi & D'onofrio",
    "wof:placetype":"venue"
},
  "geometry": {"coordinates":[13.531687,43.614643],"type":"Point"}
}