{
  "type": "Feature",
  "properties": {
    "addr:full":"Via Galileo Ferraris 44 21042 Caronno Pertusella Caronno Pertusella Varese 21042",
    "addr:housenumber":"44",
    "addr:postcode":"21042;pertusella;21042",
    "addr:street":"Via Galileo Ferraris;Pertusella",
    "iso:country":"IT",
    "sg:address":"Via Galileo Ferraris 44 21042 Caronno Pertusella",
    "sg:city":"Caronno Pertusella",
    "sg:classifiers":[
        {
            "category":"Utilities",
            "subcategory":"Fuel Oil & Lpg",
            "type":"Services"
        }
    ],
    "sg:phone":"+39 02 966 5121",
    "sg:postcode":"21042",
    "sg:province":"Varese",
    "sg:tags":[
        "medicinal",
        "extract",
        "herb"
    ],
    "sg:website":"www.hammerpharma.it",
    "wof:name":"Hammer Pharma S.p.a.",
    "wof:placetype":"venue"
},
  "geometry": {"coordinates":[9.042025,45.608383],"type":"Point"}
}