{
  "type": "Feature",
  "properties": {
    "iso:country":"IT",
    "sg:address":"Viale Dell'industria Z.i.p.a 18 60035 Jesi",
    "sg:city":"Jesi",
    "sg:classifiers":[
        {
            "category":"Home & Garden",
            "subcategory":"Home Furnishings",
            "type":"Retail Goods"
        }
    ],
    "sg:phone":"+39 0731 61531",
    "sg:postcode":"60035",
    "sg:province":"Ancona",
    "sg:tags":[
        "interior",
        "decoration"
    ],
    "sg:website":"www.clabogroup.com",
    "wof:name":"Artic Srl",
    "wof:placetype":"venue"
},
  "geometry": {"coordinates":[13.35832,43.532978],"type":"Point"}
}