{
  "type": "Feature",
  "properties": {
    "addr:full":"Via De Gasperi-san Nicol\u00f2 A Tordino 64100 Teramo Teramo Teramo 64100",
    "addr:postcode":"64100;64100",
    "addr:street":"Via De Gasperi-San Nicolo\u0300 A Tordino",
    "iso:country":"IT",
    "sg:address":"Via De Gasperi-san Nicol\u00f2 A Tordino 64100 Teramo",
    "sg:city":"Teramo",
    "sg:classifiers":[
        {
            "category":"Home & Garden",
            "subcategory":"Furniture",
            "type":"Retail Goods"
        }
    ],
    "sg:phone":"+39 0861 587167",
    "sg:postcode":"64100",
    "sg:province":"Teramo",
    "sg:tags":[
        "kitchen"
    ],
    "wof:name":"La Piramide Srl",
    "wof:placetype":"venue"
},
  "geometry": {"coordinates":[13.698531,42.66127],"type":"Point"}
}