{
  "type": "Feature",
  "properties": {
    "iso:country":"IT",
    "sg:address":"06012 Citta'dicastello",
    "sg:classifiers":[
        {
            "category":"Home & Garden",
            "subcategory":"Furniture",
            "type":"Retail Goods"
        }
    ],
    "sg:phone":"+39 075 851 1419",
    "sg:postcode":"06012",
    "sg:province":"Perugia",
    "sg:tags":[
        "craft",
        "art",
        "furnishing",
        "artistic"
    ],
    "wof:name":"S.a.l.a. Di Volpi Marinelli Nesci Snc",
    "wof:placetype":"venue"
},
  "geometry": {"coordinates":[12.2319049835,43.4577865601],"type":"Point"}
}