{
  "type": "Feature",
  "properties": {
    "addr:full":"Via Guasti 20020 Misinto Misinto Milano 20020",
    "addr:postcode":"20020;20020",
    "addr:street":"Via Guasti",
    "iso:country":"IT",
    "sg:address":"Via Guasti 20020 Misinto",
    "sg:city":"Misinto",
    "sg:classifiers":[
        {
            "category":"Shopping",
            "subcategory":"Computers & Home Electronics",
            "type":"Retail Goods"
        }
    ],
    "sg:phone":"+39 02 9632 8058",
    "sg:postcode":"20020",
    "sg:province":"Milano",
    "sg:tags":[
        "electronic",
        "electrical",
        "equipment"
    ],
    "wof:name":"Co - Me (s.r.l.)",
    "wof:placetype":"venue"
},
  "geometry": {"coordinates":[9.089102,45.660423],"type":"Point"}
}