{
  "type": "Feature",
  "properties": {
    "addr:full":"35010 Vigodarzere Vigodarzere Padova 35010",
    "addr:postcode":"35010;35010",
    "iso:country":"IT",
    "sg:address":"35010 Vigodarzere",
    "sg:city":"Vigodarzere",
    "sg:orig_category":"Abbigliamento Esterno, Maglierie E Pelliccerie. Calzature, Pelletterie E Pelli. Shopping",
    "sg:phone":"+39 049 702573",
    "sg:postcode":"35010",
    "sg:province":"Padova",
    "wof:name":"Luise Mauro Pellicceria",
    "wof:placetype":"venue"
},
  "geometry": {"coordinates":[11.885983,45.452625],"type":"Point"}
}