{
  "type": "Feature",
  "properties": {
    "iso:country":"IT",
    "sg:address":"Via Turati Filippo 29 20121 Milano",
    "sg:city":"Milano",
    "sg:classifiers":[
        {
            "category":"Bus Stop",
            "subcategory":"None",
            "type":"Transportation"
        }
    ],
    "sg:phone":"+39 0262651",
    "sg:postcode":"20121",
    "sg:province":"Milano",
    "sg:tags":[
        "chip",
        "fry",
        "french",
        "potato"
    ],
    "wof:name":"San Carlo Mantova Spa",
    "wof:placetype":"venue"
},
  "geometry": {"coordinates":[9.1958112717,45.4771728516],"type":"Point"}
}