{
  "type": "Feature",
  "properties": {
    "addr:full":"98100 Messina ME",
    "addr:postcode":"98100",
    "iso:country":"IT",
    "sg:address":"98100 Messina",
    "sg:orig_category":"Legno E Semilavorati. Apparecchiature E Sistemi Per Magazzinaggio E Movimentazione",
    "sg:phone":"+39 368 404 060",
    "sg:province":"ME",
    "wof:name":"D'anna Umberto",
    "wof:placetype":"venue"
},
  "geometry": {"coordinates":[15.5034723282,38.1397705078],"type":"Point"}
}