{
  "type": "Feature",
  "properties": {
    "iso:country":"IT",
    "sg:address":"Via Salceto 87 53036 Poggibonsi",
    "sg:city":"Poggibonsi",
    "sg:classifiers":[
        {
            "category":"Manufacturing",
            "subcategory":"Rubber & Plastics",
            "type":"Manufacturing & Wholesale Goods"
        }
    ],
    "sg:phone":"+39 0577 937156",
    "sg:postcode":"53036",
    "sg:province":"Siena",
    "sg:tags":[
        "ab",
        "styrene",
        "butadiene",
        "foil",
        "slab",
        "acrylonitrile"
    ],
    "sg:website":"www.atassieco.com",
    "wof:name":"Atassi & Co. Srl",
    "wof:placetype":"venue"
},
  "geometry": {"coordinates":[11.152577,43.469707],"type":"Point"}
}