{
  "type": "Feature",
  "properties": {
    "iso:country":"IT",
    "sg:address":"22, V. Salvo D'acquisto - Berzonno 28076 Pogno",
    "sg:city":"Pogno",
    "sg:classifiers":[
        {
            "category":"Shopping",
            "type":"Retail Goods"
        }
    ],
    "sg:phone":"+39 39032297157",
    "sg:postcode":"28076",
    "sg:province":"Novara",
    "sg:tags":[
        "finished",
        "-",
        "metallic"
    ],
    "sg:website":"http://www.giulini.it:ws_end: :mark:ws:http://www.paginegialle.it/giulinig",
    "wof:name":"Rubinetteria Giulini Giovanni Snc",
    "wof:placetype":"venue"
},
  "geometry": {"coordinates":[8.3916721344,45.7595214844],"type":"Point"}
}