{
  "type": "Feature",
  "properties": {
    "iso:country":"IT",
    "sg:address":"10149 Torino",
    "sg:city":"Torino",
    "sg:orig_category":"Servizi Al Turismo. Trasporto Pubblico E Privato. Acqua, Luce, Gas E Societa' Di Esercizio Pubblico",
    "sg:phone":"+39 011 295972",
    "sg:postcode":"10149",
    "sg:province":"Torino",
    "wof:name":"Spa Torinese Trasporti Intercomunali S.a.t.t.i.",
    "wof:placetype":"venue"
},
  "geometry": {"coordinates":[7.67422,45.093323],"type":"Point"}
}