{
  "type": "Feature",
  "properties": {
    "iso:country":"IT",
    "sg:address":"Via N. Sauro 6/b; Bologna; 40121",
    "sg:city":"Bologna",
    "sg:classifiers":[
        {
            "category":"Banks & Credit Unions",
            "subcategory":"Bank",
            "type":"Services"
        }
    ],
    "sg:phone":"+39 051 231602",
    "sg:postcode":"40121",
    "sg:province":"Bologna",
    "wof:name":"Banca Del Monte",
    "wof:placetype":"venue"
},
  "geometry": {"coordinates":[11.33917,44.496056],"type":"Point"}
}