{
  "type": "Feature",
  "properties": {
    "addr:full":"41100 Modena Modena Modena 41100",
    "addr:postcode":"41100;41100",
    "iso:country":"IT",
    "sg:address":"41100 Modena",
    "sg:city":"Modena",
    "sg:orig_category":"Servizi Vari Di Interesse Pubblico",
    "sg:phone":"+39 059 245103",
    "sg:postcode":"41100",
    "sg:province":"Modena",
    "wof:name":"L' Isola Che C'e S.c.r.a.l.",
    "wof:placetype":"venue"
},
  "geometry": {"coordinates":[10.915619,44.645988],"type":"Point"}
}