{
  "type": "Feature",
  "properties": {
    "addr:full":"20052 Monza Monza Milano 20052",
    "addr:postcode":"20052;20052",
    "iso:country":"IT",
    "sg:address":"20052 Monza",
    "sg:city":"Monza",
    "sg:orig_category":"Accessori Moda D'abbigliamento",
    "sg:phone":"+39 039 323769",
    "sg:postcode":"20052",
    "sg:province":"Milano",
    "wof:name":"I.m.o.r. (s.n.c.)",
    "wof:placetype":"venue"
},
  "geometry": {"coordinates":[9.281041,45.582996],"type":"Point"}
}