{
  "type": "Feature",
  "properties": {
    "iso:country":"IT",
    "sg:address":"24027 Nembro",
    "sg:city":"Nembro",
    "sg:orig_category":"Coperture Edili Impermeabili",
    "sg:phone":"+39 035 520434",
    "sg:postcode":"24027",
    "sg:province":"Bergamo",
    "wof:name":"Cantini Srl Tecnologie Di Impermeabilizzazioni",
    "wof:placetype":"venue"
},
  "geometry": {"coordinates":[9.742715,45.73893],"type":"Point"}
}