{
  "type": "Feature",
  "properties": {
    "iso:country":"IT",
    "sg:address":"25081 Bedizzole",
    "sg:city":"Bedizzole",
    "sg:orig_category":"Arredamenti E Mobili Professionali. Arredi Ed Attrezzature Per Uffici",
    "sg:phone":"+39 030 687 0057",
    "sg:postcode":"25081",
    "sg:province":"Brescia",
    "wof:name":"Scaroni Fratelli (s.n.c.)",
    "wof:placetype":"venue"
},
  "geometry": {"coordinates":[10.418576,45.50832],"type":"Point"}
}