{
  "type": "Feature",
  "properties": {
    "addr:full":"35, Via Dell' Avena 70022 Altamura Altamura Bari 70022",
    "addr:postcode":"70022;70022",
    "addr:street":"Via Dell ' Avena",
    "iso:country":"IT",
    "sg:address":"35, Via Dell' Avena 70022 Altamura",
    "sg:city":"Altamura",
    "sg:classifiers":[
        {
            "category":"Manufacturing",
            "subcategory":"Food",
            "type":"Manufacturing & Wholesale Goods"
        }
    ],
    "sg:phone":"+39 080 310 1016",
    "sg:postcode":"70022",
    "sg:province":"Bari",
    "sg:tags":[
        "equipment",
        "processing",
        "-",
        "machinery"
    ],
    "wof:name":"Molitecnica Sud (s.n.c.)",
    "wof:placetype":"venue"
},
  "geometry": {"coordinates":[16.5203170776,40.822845459],"type":"Point"}
}