{
  "type": "Feature",
  "properties": {
    "addr:full":"53048 Sinalunga Sinalunga Siena 53048",
    "addr:postcode":"53048;53048",
    "iso:country":"IT",
    "sg:address":"53048 Sinalunga",
    "sg:city":"Sinalunga",
    "sg:orig_category":"Materiali E Componenti Elettrotecnici",
    "sg:phone":"+39 0577 678000",
    "sg:postcode":"53048",
    "sg:province":"Siena",
    "wof:name":"Innocenti & Cammelli Spa",
    "wof:placetype":"venue"
},
  "geometry": {"coordinates":[11.755262,43.21909],"type":"Point"}
}