{
  "type": "Feature",
  "properties": {
    "addr:full":"50145 Firenze Firenze Firenze 50145",
    "addr:postcode":"50145;50145",
    "iso:country":"IT",
    "sg:address":"50145 Firenze",
    "sg:city":"Firenze",
    "sg:orig_category":"Ricambi E Componenti Dei Mezzi Di Trasporto",
    "sg:phone":"+39 055 310491",
    "sg:postcode":"50145",
    "sg:province":"Firenze",
    "sg:website":"http://www.arauto.it",
    "wof:name":"Arauto Di Cianferoni Giancarlo & C. Sas",
    "wof:placetype":"venue"
},
  "geometry": {"coordinates":[11.214993,43.711075],"type":"Point"}
}