{
  "type": "Feature",
  "properties": {
    "iso:country":"IT",
    "sg:address":"30/2, V. Marconi 40010 Bentivoglio",
    "sg:city":"Bentivoglio",
    "sg:classifiers":[
        {
            "category":"Parking",
            "subcategory":"Lot",
            "type":"Transportation"
        }
    ],
    "sg:phone":"+39 051 664 0034",
    "sg:postcode":"40010",
    "sg:province":"Bologna",
    "sg:tags":[
        "transport",
        "road"
    ],
    "sg:website":"http://www.paginegialle.it/ottanisnc",
    "wof:name":"Ottani Snc",
    "wof:placetype":"venue"
},
  "geometry": {"coordinates":[11.43877,44.574169],"type":"Point"}
}