{
  "type": "Feature",
  "properties": {
    "iso:country":"IT",
    "sg:address":"10128 Torino",
    "sg:city":"Torino",
    "sg:orig_category":"Medici. Assicurazioni E Servizi Assicurativi. Avvocati, Notai E Servizi Legali. Professionisti - Studi E Servizi Ed Associazioni Di Interesse Aziendale",
    "sg:phone":"+39 011 503266",
    "sg:postcode":"10128",
    "sg:province":"Torino",
    "wof:name":"Bechis Franca",
    "wof:placetype":"venue"
},
  "geometry": {"coordinates":[7.6657505035,45.0540046692],"type":"Point"}
}