{
  "type": "Feature",
  "properties": {
    "iso:country":"IT",
    "sg:address":"30, Via Ca' Da Pi' 24024 Gandino",
    "sg:city":"Gandino",
    "sg:classifiers":[
        {
            "category":"Real Estate",
            "subcategory":"Architect",
            "type":"Services"
        }
    ],
    "sg:phone":"+39 39035745250",
    "sg:postcode":"24024",
    "sg:province":"Bergamo",
    "sg:tags":[
        "textile",
        "clothing"
    ],
    "wof:name":"Creazioni Mary (s.n.c.)",
    "wof:placetype":"venue"
},
  "geometry": {"coordinates":[9.903061,45.817074],"type":"Point"}
}