{
  "type": "Feature",
  "properties": {
    "iso:country":"IT",
    "sg:address":"52, V. Piazzon 36051 Creazzo",
    "sg:city":"Creazzo",
    "sg:classifiers":[
        {
            "category":"Shopping",
            "subcategory":"Jewelry",
            "type":"Retail Goods"
        }
    ],
    "sg:phone":"+39 0444 349494",
    "sg:postcode":"36051",
    "sg:province":"Vicenza",
    "sg:tags":[
        "jewellery"
    ],
    "wof:name":"Deoro Srl",
    "wof:placetype":"venue"
},
  "geometry": {"coordinates":[11.498617,45.531361],"type":"Point"}
}