{
  "type": "Feature",
  "properties": {
    "iso:country":"IT",
    "sg:address":"20146 Milano",
    "sg:city":"Milano",
    "sg:orig_category":"Servizi Al Turismo. Trasporto Pubblico E Privato. Acqua, Luce, Gas E Societa' Di Esercizio Pubblico",
    "sg:postcode":"20146",
    "sg:province":"Milano",
    "wof:name":"Oniesjan",
    "wof:placetype":"venue"
},
  "geometry": {"coordinates":[9.146502,45.455086],"type":"Point"}
}