{
  "type": "Feature",
  "properties": {
    "iso:country":"IT",
    "sg:address":"29100 Piacenza",
    "sg:city":"Piacenza",
    "sg:orig_category":"Forniture Alle Strutture Ricettive. Macchine E Impianti Per Attivita' Commerciali Ed Artigianali",
    "sg:phone":"+39 0523 606715",
    "sg:postcode":"29100",
    "sg:province":"Piacenza",
    "wof:name":"Eurocoffee Srl",
    "wof:placetype":"venue"
},
  "geometry": {"coordinates":[9.7484731674,45.0238265991],"type":"Point"}
}