{
  "type": "Feature",
  "properties": {
    "iso:country":"IT",
    "sg:address":"40124 Bologna",
    "sg:city":"Bologna",
    "sg:orig_category":"Abbigliamento Esterno, Maglierie E Pelliccerie. Shopping",
    "sg:phone":"+39 051 234955",
    "sg:postcode":"40124",
    "sg:province":"Bologna",
    "wof:name":"Lalla Bernardoni Srl",
    "wof:placetype":"venue"
},
  "geometry": {"coordinates":[11.344012,44.493362],"type":"Point"}
}