{
  "type": "Feature",
  "properties": {
    "addr:full":"25039 Travagliato Travagliato Brescia 25039",
    "addr:postcode":"25039;25039",
    "iso:country":"IT",
    "sg:address":"25039 Travagliato",
    "sg:city":"Travagliato",
    "sg:orig_category":"Apparecchiature E Sistemi Per Magazzinaggio E Movimentazione. Servizi Di Magazzinaggio E Movimentazione",
    "sg:phone":"+39 030 686 4180",
    "sg:postcode":"25039",
    "sg:province":"Brescia",
    "wof:name":"Travel Autotrasporti",
    "wof:placetype":"venue"
},
  "geometry": {"coordinates":[10.075254,45.538685],"type":"Point"}
}