{
  "type": "Feature",
  "properties": {
    "addr:full":"00053 Civitavecchia Aurelia Roma 00053",
    "addr:postcode":"00053;00053",
    "addr:street":"Aurelia Roma",
    "iso:country":"IT",
    "sg:address":"00053 Civitavecchia",
    "sg:city":"Aurelia",
    "sg:orig_category":"Servizi E Lavori Per Edilizia E Lavori Pubblici",
    "sg:phone":"+39 0766 568024",
    "sg:postcode":"00053",
    "sg:province":"Roma",
    "wof:name":"S.m.e.s.",
    "wof:placetype":"venue"
},
  "geometry": {"coordinates":[11.820757,42.115593],"type":"Point"}
}