{
  "type": "Feature",
  "properties": {
    "iso:country":"IT",
    "sg:address":"20011 Corbetta",
    "sg:city":"Corbetta",
    "sg:classifiers":[
        {
            "category":"Shopping",
            "subcategory":"Clothing, Apparel, & Fashions",
            "type":"Retail Goods"
        }
    ],
    "sg:phone":"+39 02 977 9106",
    "sg:postcode":"20011",
    "sg:province":"Milano",
    "sg:tags":[
        "clothing",
        "fur",
        "knitwear"
    ],
    "wof:name":"Egan Snc Di Cislaghi S. & Elia S. & C.",
    "wof:placetype":"venue"
},
  "geometry": {"coordinates":[9.001282,45.475124],"type":"Point"}
}