{
  "type": "Feature",
  "properties": {
    "iso:country":"IT",
    "sg:address":"98076 S. Agata Di Militello",
    "sg:classifiers":[
        {
            "category":"Military Area",
            "subcategory":"Coast Guard Base",
            "type":"Public Place"
        }
    ],
    "sg:phone":"+39 0941 722222",
    "sg:postcode":"98076",
    "sg:province":"Messina",
    "sg:tags":[
        "accessories",
        "linen",
        "furnishing",
        "bedroom",
        "blankets",
        "drapery"
    ],
    "sg:website":"http://www.casadellino.it",
    "wof:name":"Morello Nitto - Casa Del Lino",
    "wof:placetype":"venue"
},
  "geometry": {"coordinates":[14.634133,38.069588],"type":"Point"}
}