{
  "type": "Feature",
  "properties": {
    "iso:country":"IT",
    "sg:address":"21052 Busto Arsizio",
    "sg:city":"Busto Arsizio",
    "sg:orig_category":"Tubi Flessibili Per Pressioni",
    "sg:phone":"+39 0331 329909",
    "sg:postcode":"21052",
    "sg:province":"Varese",
    "wof:name":"Duegi Snc",
    "wof:placetype":"venue"
},
  "geometry": {"coordinates":[8.863618,45.601551],"type":"Point"}
}