{
  "type": "Feature",
  "properties": {
    "iso:country":"IT",
    "sg:address":"16132 Genova",
    "sg:city":"Genova",
    "sg:orig_category":"Giardinaggio - Servizio",
    "sg:phone":"+39 010 374 2206",
    "sg:postcode":"16132",
    "sg:province":"Genova",
    "wof:name":"Nuova Verde Impianti Snc",
    "wof:placetype":"venue"
},
  "geometry": {"coordinates":[8.927588,44.41013],"type":"Point"}
}