{
  "type": "Feature",
  "properties": {
    "addr:full":"28069 Trecate Trecate Novara 28069",
    "addr:postcode":"28069;28069",
    "iso:country":"IT",
    "sg:address":"28069 Trecate",
    "sg:city":"Trecate",
    "sg:orig_category":"Carni, Salumi E Pesci. Zootecnia E Pesca, Allevamento Piccoli Animali",
    "sg:phone":"+39 0321 770736",
    "sg:postcode":"28069",
    "sg:province":"Novara",
    "wof:name":"Aqua Food Srl",
    "wof:placetype":"venue"
},
  "geometry": {"coordinates":[8.742596,45.437202],"type":"Point"}
}