{
  "type": "Feature",
  "properties": {
    "iso:country":"IT",
    "sg:address":"325, Via Statale 44047 Sant'agostino",
    "sg:classifiers":[
        {
            "category":"Wholesale",
            "subcategory":"Machinery & Supplies",
            "type":"Manufacturing & Wholesale Goods"
        }
    ],
    "sg:phone":"+39 0532 848091",
    "sg:postcode":"44047",
    "sg:province":"Ferrara",
    "sg:tags":[
        "-",
        "agriculture",
        "equipment"
    ],
    "wof:name":"Meccanica Benassi (s.p.a.)",
    "wof:placetype":"venue"
},
  "geometry": {"coordinates":[11.62044,44.837894],"type":"Point"}
}