{
  "type": "Feature",
  "properties": {
    "iso:country":"IT",
    "sg:address":"44, Via Marconi 28881 Casale Corte Cerro",
    "sg:city":"Casale Corte Cerro",
    "sg:classifiers":[
        {
            "category":"Shopping",
            "type":"Retail Goods"
        }
    ],
    "sg:phone":"+39 39032360139",
    "sg:postcode":"28881",
    "sg:province":"Verbano-Cusio-Ossola",
    "sg:tags":[
        "finished",
        "-",
        "metallic"
    ],
    "wof:name":"Melloni Anacleto (s.r.l.)",
    "wof:placetype":"venue"
},
  "geometry": {"coordinates":[8.2724647522,46.1399688721],"type":"Point"}
}