{
  "type": "Feature",
  "properties": {
    "iso:country":"IT",
    "sg:address":"35010 Villafranca Padovana",
    "sg:city":"Villafranca Padovana",
    "sg:orig_category":"Pubblicita' - Cartelli, Insegne E Targhe",
    "sg:phone":"+39 049 907 0267",
    "sg:postcode":"35010",
    "sg:province":"Padova",
    "wof:name":"Publiday Snc",
    "wof:placetype":"venue"
},
  "geometry": {"coordinates":[11.7752799988,45.4547729492],"type":"Point"}
}