{
  "type": "Feature",
  "properties": {
    "iso:country":"IT",
    "sg:address":"Localita' Sentino 53040 Rapolano Terme",
    "sg:city":"Rapolano Terme",
    "sg:classifiers":[
        {
            "category":"Real Estate",
            "subcategory":"Architect",
            "type":"Services"
        }
    ],
    "sg:phone":"+39 39057770521",
    "sg:postcode":"53040",
    "sg:province":"Siena",
    "sg:tags":[
        "textile",
        "clothing"
    ],
    "wof:name":"Jammy Srl",
    "wof:placetype":"venue"
},
  "geometry": {"coordinates":[11.621543,43.259178],"type":"Point"}
}