{
  "type": "Feature",
  "properties": {
    "iso:country":"IT",
    "sg:address":"01031 Bagnaia",
    "sg:orig_category":"Forniture Per Edilizia E Lavori Pubblici. Arredi Ed Attrezzature Per Attivita' Commerciali Ed Artigianali. Forniture Per Attivita' Industriali",
    "sg:phone":"+39 0761 289622",
    "sg:province":"VT",
    "sg:website":"http://www.decosrl.com",
    "wof:name":"Deco Srl",
    "wof:placetype":"venue"
},
  "geometry": {"coordinates":[-72.22453308110001,42.3259315491],"type":"Point"}
}