{
  "type": "Feature",
  "properties": {
    "iso:country":"IT",
    "sg:address":"Via Pulsaria 16; Torre Orsaia; 84077",
    "sg:city":"Torre Orsaia",
    "sg:classifiers":[
        {
            "category":"Banks & Credit Unions",
            "subcategory":"Bank",
            "type":"Services"
        }
    ],
    "sg:phone":"+39 0974 985760",
    "sg:postcode":"84077",
    "sg:province":"Salerno",
    "wof:name":"Banco Di Napoli Spa",
    "wof:placetype":"venue"
},
  "geometry": {"coordinates":[15.469761,40.130119],"type":"Point"}
}