{
  "type": "Feature",
  "properties": {
    "iso:country":"IT",
    "sg:address":"40013 Castel Maggiore",
    "sg:city":"Castel Maggiore",
    "sg:classifiers":[
        {
            "category":"Manufacturing",
            "subcategory":"Rubber & Plastics",
            "type":"Manufacturing & Wholesale Goods"
        }
    ],
    "sg:phone":"+39 051 700321",
    "sg:postcode":"40013",
    "sg:province":"Bologna",
    "sg:tags":[
        "article",
        "product"
    ],
    "sg:website":"http://www.satitrading.it",
    "wof:name":"Sati Trading Srl",
    "wof:placetype":"venue"
},
  "geometry": {"coordinates":[11.370451,44.559994],"type":"Point"}
}