{
  "type": "Feature",
  "properties": {
    "iso:country":"IT",
    "sg:address":"36030 Sarcedo",
    "sg:city":"Sarcedo",
    "sg:orig_category":"Giardinaggio - Macchine Ed Attrezzi",
    "sg:phone":"+39 0445 381022",
    "sg:postcode":"36030",
    "sg:province":"Vicenza",
    "wof:name":"Wec Srl",
    "wof:placetype":"venue"
},
  "geometry": {"coordinates":[11.492407,45.729568],"type":"Point"}
}