{
  "type": "Feature",
  "properties": {
    "iso:country":"IT",
    "sg:address":"91013 Calatafimi Segesta",
    "sg:city":"Calatafimi",
    "sg:orig_category":"Prodotti Di Base E Forniture Per Industria Alimentare E Bevande",
    "sg:phone":"+39 0924 952179",
    "sg:postcode":"91013",
    "sg:province":"Trapani",
    "wof:name":"Sicilbudella Di Guastella Maria",
    "wof:placetype":"venue"
},
  "geometry": {"coordinates":[12.8744945526,37.922618866],"type":"Point"}
}