{
  "type": "Feature",
  "properties": {
    "iso:country":"IT",
    "sg:address":"44022 Comacchio",
    "sg:city":"Comacchio",
    "sg:classifiers":[
        {
            "category":"Travel",
            "subcategory":"Hotels & Motels",
            "type":"Entertainment"
        }
    ],
    "sg:phone":"+39 0533 330534",
    "sg:postcode":"44022",
    "sg:province":"Ferrara",
    "sg:tags":[
        "camping",
        "facility"
    ],
    "sg:website":"http://www.agenziailgabbiano.com",
    "wof:name":"Agenzia Immobiliare Il Gabbiano Di Simoni Pietro",
    "wof:placetype":"venue"
},
  "geometry": {"coordinates":[12.249218,44.651138],"type":"Point"}
}