{
  "type": "Feature",
  "properties": {
    "iso:country":"IT",
    "sg:address":"26, Borgo Degli Albizi 50122 Firenze",
    "sg:city":"Firenze",
    "sg:classifiers":[
        {
            "category":"Sports & Exercise",
            "subcategory":"Playing Field",
            "type":"Entertainment"
        }
    ],
    "sg:phone":"+39 055 234 0830",
    "sg:postcode":"50122",
    "sg:province":"Firenze",
    "sg:tags":[
        "game"
    ],
    "wof:name":"Istituto Vendite Giudiziarie Pandolfini Cav. Luigi",
    "wof:placetype":"venue"
},
  "geometry": {"coordinates":[11.261759,43.771488],"type":"Point"}
}