{
  "type": "Feature",
  "properties": {
    "iso:country":"IT",
    "sg:address":"53026 Pienza",
    "sg:city":"Pienza",
    "sg:orig_category":"Legno E Semilavorati. Manufatti Edili E Prefabbricati",
    "sg:phone":"+39 0578 748572",
    "sg:postcode":"53026",
    "sg:province":"Siena",
    "wof:name":"Anselmi Bruno",
    "wof:placetype":"venue"
},
  "geometry": {"coordinates":[11.744154,43.125645],"type":"Point"}
}