{
  "type": "Feature",
  "properties": {
    "iso:country":"IT",
    "sg:address":"20037 Paderno Dugnano",
    "sg:city":"Paderno Dugnano",
    "sg:orig_category":"Ospedali E Servizi Sanitari. Servizi Sociali. Associazioni Ed Organismi Di Interesse Pubblico",
    "sg:phone":"+39 02 918 4483",
    "sg:postcode":"20037",
    "sg:province":"Milano",
    "wof:name":"A.v.i.s.",
    "wof:placetype":"venue"
},
  "geometry": {"coordinates":[9.169582,45.570248],"type":"Point"}
}