{
  "type": "Feature",
  "properties": {
    "addr:full":"73100 Lecce Lecce Lecce 73100",
    "addr:postcode":"73100;73100",
    "iso:country":"IT",
    "sg:address":"73100 Lecce",
    "sg:city":"Lecce",
    "sg:orig_category":"Macchine, Impianti Ed Attrezzature Per Industria Alimentare E Bevande",
    "sg:phone":"+39 0832 343611",
    "sg:postcode":"73100",
    "sg:province":"Lecce",
    "wof:name":"Comagri (s.p.a.)",
    "wof:placetype":"venue"
},
  "geometry": {"coordinates":[18.169058,40.34111],"type":"Point"}
}