{
  "type": "Feature",
  "properties": {
    "addr:full":"Via Brezzi 26 10081 Castellamonte Castellamonte Torino 10081",
    "addr:housenumber":"26",
    "addr:postcode":"10081;10081",
    "addr:street":"Via Brezzi",
    "iso:country":"IT",
    "sg:address":"Via Brezzi 26 10081 Castellamonte",
    "sg:city":"Castellamonte",
    "sg:orig_category":"Hardmetals",
    "sg:phone":"+39 0124 513650",
    "sg:postcode":"10081",
    "sg:province":"Torino",
    "sg:website":"www.wolframcarb.it",
    "wof:name":"Wolframcarb Spa",
    "wof:placetype":"venue"
},
  "geometry": {"coordinates":[7.716776,45.381935],"type":"Point"}
}