{
  "type": "Feature",
  "properties": {
    "iso:country":"IT",
    "sg:address":"10093 Collegno",
    "sg:city":"Collegno",
    "sg:orig_category":"Articoli Pulizia",
    "sg:phone":"+39 011 415 5221",
    "sg:postcode":"10093",
    "sg:province":"Torino",
    "wof:name":"Sissoldo Gilberto",
    "wof:placetype":"venue"
},
  "geometry": {"coordinates":[7.272747,45.107044],"type":"Point"}
}