{
  "type": "Feature",
  "properties": {
    "addr:full":"80145 Napoli Napoli Napoli 80145",
    "addr:postcode":"80145;80145",
    "iso:country":"IT",
    "sg:address":"80145 Napoli",
    "sg:city":"Napoli",
    "sg:orig_category":"Macchine Ed Impianti Per Edilizia E Lavori Pubblici",
    "sg:phone":"+39 081 585 2624",
    "sg:postcode":"80145",
    "sg:province":"Napoli",
    "wof:name":"La Gitana Soc.coop.arl",
    "wof:placetype":"venue"
},
  "geometry": {"coordinates":[14.232814,40.879669],"type":"Point"}
}