{
  "type": "Feature",
  "properties": {
    "iso:country":"IT",
    "sg:address":"38100 Trento",
    "sg:city":"Trento",
    "sg:orig_category":"Articoli Da Regalo. Regalistica Aziendale",
    "sg:phone":"+39 0461 233017",
    "sg:postcode":"38100",
    "sg:province":"Trento",
    "wof:name":"Tabaccheria De Paoli",
    "wof:placetype":"venue"
},
  "geometry": {"coordinates":[11.119843,46.069733],"type":"Point"}
}