{
  "type": "Feature",
  "properties": {
    "iso:country":"IT",
    "sg:address":"Via Isonzo 4 20049 Concorezzo",
    "sg:city":"Concorezzo",
    "sg:classifiers":[
        {
            "category":"Food & Beverages",
            "subcategory":"Bakery",
            "type":"Retail Goods"
        }
    ],
    "sg:phone":"+39 039 604 0437",
    "sg:postcode":"20049",
    "sg:province":"Milano",
    "sg:tags":[
        "oven",
        "bread"
    ],
    "wof:name":"Meroni Natale Snc",
    "wof:placetype":"venue"
},
  "geometry": {"coordinates":[9.304732,45.568497],"type":"Point"}
}