{
  "type": "Feature",
  "properties": {
    "iso:country":"IT",
    "sg:address":"36022 Cassola",
    "sg:city":"Cassola",
    "sg:classifiers":[
        {
            "category":"Manufacturing",
            "subcategory":"Tools & Machinery",
            "type":"Manufacturing & Wholesale Goods"
        }
    ],
    "sg:phone":"+39 0424 533 4041",
    "sg:postcode":"36022",
    "sg:province":"Vicenza",
    "sg:tags":[
        "machine",
        "system"
    ],
    "wof:name":"Panamac Srl",
    "wof:placetype":"venue"
},
  "geometry": {"coordinates":[11.59173,45.539696],"type":"Point"}
}