{
  "type": "Feature",
  "properties": {
    "iso:country":"IT",
    "sg:address":"09128 Cagliari",
    "sg:city":"Cagliari",
    "sg:orig_category":"Arredo Camera Letto E Complementi",
    "sg:phone":"+39 070 495609",
    "sg:postcode":"09128",
    "sg:province":"Cagliari",
    "wof:name":"Casa Del Materasso Di R. & B. Di Daccomi Brunella",
    "wof:placetype":"venue"
},
  "geometry": {"coordinates":[9.12254,39.223331],"type":"Point"}
}