{
  "type": "Feature",
  "properties": {
    "iso:country":"IT",
    "sg:address":"16038 Santa Margherita Ligure",
    "sg:city":"Santa Margherita Ligure",
    "sg:orig_category":"Tessuti Arredamento, Tende E Tappeti. Forniture Per Edilizia E Lavori Pubblici",
    "sg:phone":"+39 339 673 5375",
    "sg:postcode":"16038",
    "sg:province":"Genova",
    "wof:name":"Buzzati Luca",
    "wof:placetype":"venue"
},
  "geometry": {"coordinates":[9.204484,44.335751],"type":"Point"}
}