{
  "type": "Feature",
  "properties": {
    "addr:full":"Via P. Apostoli 8-10 35042 Este Este Padova 35042",
    "addr:housenumber":"8-10",
    "addr:postcode":"35042;35042",
    "addr:street":"Via P. Apostoli",
    "iso:country":"IT",
    "sg:address":"Via P. Apostoli 8-10 35042 Este",
    "sg:city":"Este",
    "sg:classifiers":[
        {
            "category":"Real Estate",
            "subcategory":"Surveying",
            "type":"Services"
        }
    ],
    "sg:phone":"+39 0429 56311",
    "sg:postcode":"35042",
    "sg:province":"Padova",
    "sg:tags":[
        "stationery",
        "writing",
        "material",
        "creative"
    ],
    "sg:website":"www.gexon.com",
    "wof:name":"Gexon Srl",
    "wof:placetype":"venue"
},
  "geometry": {"coordinates":[11.876589,45.409569],"type":"Point"}
}