{
  "type": "Feature",
  "properties": {
    "iso:country":"IT",
    "sg:address":"46100 Mantova",
    "sg:city":"Mantova",
    "sg:orig_category":"Carta, Cartone E Prodotti Primari. Forniture Per Attivita' Commerciali Ed Artigianali",
    "sg:phone":"+39 0376 276411",
    "sg:postcode":"46100",
    "sg:province":"Mantova",
    "sg:website":"http://www.smurfit-packaging.com",
    "wof:name":"Smurfit Packaging Italia Spa",
    "wof:placetype":"venue"
},
  "geometry": {"coordinates":[10.848905,45.139706],"type":"Point"}
}