{
  "type": "Feature",
  "properties": {
    "iso:country":"IT",
    "sg:address":"1, Corso Repubblica 28041 Arona",
    "sg:city":"Arona",
    "sg:classifiers":[
        {
            "category":"Travel",
            "subcategory":"Travel Agent",
            "type":"Entertainment"
        }
    ],
    "sg:phone":"+39 39032245994",
    "sg:postcode":"28041",
    "sg:province":"Novara",
    "sg:tags":[
        "business"
    ],
    "wof:name":"Albergo Giardino Di Bertalli Ezio & C. S.a.s.",
    "wof:placetype":"venue"
},
  "geometry": {"coordinates":[8.560119,45.757462],"type":"Point"}
}