{
  "type": "Feature",
  "properties": {
    "iso:country":"IT",
    "sg:address":"22077 Olgiate Comasco",
    "sg:city":"Olgiate Comasco",
    "sg:orig_category":"Marmo Ed Affini - Lavorazione",
    "sg:phone":"+39 031 945310",
    "sg:postcode":"22077",
    "sg:province":"Como",
    "wof:name":"Monumenti Artistici Snc Di Ghilotti & Boarin",
    "wof:placetype":"venue"
},
  "geometry": {"coordinates":[8.96654,45.792393],"type":"Point"}
}