{
  "type": "Feature",
  "properties": {
    "iso:country":"IT",
    "sg:address":"Via Generale; Valledolmo; 90029",
    "sg:city":"Valledolmo",
    "sg:classifiers":[
        {
            "category":"Banks & Credit Unions",
            "subcategory":"Bank",
            "type":"Services"
        }
    ],
    "sg:phone":"+39 0921 542012",
    "sg:postcode":"90029",
    "sg:province":"Palermo",
    "wof:name":"Banco Di Sicilia Spa",
    "wof:placetype":"venue"
},
  "geometry": {"coordinates":[13.825377,37.747234],"type":"Point"}
}