{
  "type": "Feature",
  "properties": {
    "iso:country":"IT",
    "sg:address":"19, Via Primo Maggio 20060 Pessano Con Bornago",
    "sg:city":"Ornago",
    "sg:classifiers":[
        {
            "category":"Shopping",
            "subcategory":"Computers & Home Electronics",
            "type":"Retail Goods"
        }
    ],
    "sg:phone":"+39 02 9574 0355",
    "sg:postcode":"20060",
    "sg:province":"Milano",
    "sg:tags":[
        "electronic",
        "electrical",
        "equipment"
    ],
    "wof:name":"Pessano Cavi (s.p.a.)",
    "wof:placetype":"venue"
},
  "geometry": {"coordinates":[9.397371,45.541561],"type":"Point"}
}