{
  "type": "Feature",
  "properties": {
    "addr:full":"57014 Collesalvetti Collesalvetti Livorno 57014",
    "addr:postcode":"57014;57014",
    "iso:country":"IT",
    "sg:address":"57014 Collesalvetti",
    "sg:city":"Collesalvetti",
    "sg:orig_category":"Carpenterie Meccaniche",
    "sg:phone":"+39 0586 966453",
    "sg:postcode":"57014",
    "sg:province":"Livorno",
    "wof:name":"Lottini F.m. Sdf",
    "wof:placetype":"venue"
},
  "geometry": {"coordinates":[10.319055,43.570789],"type":"Point"}
}