{
  "type": "Feature",
  "properties": {
    "addr:full":"Via Castelletto Sn - Zona Artigian. 46048 Roverbella Roverbella Mantova 46048",
    "addr:housenumber":"sn",
    "addr:postcode":"46048;46048",
    "addr:street":"Via Castelletto;Artigian.",
    "iso:country":"IT",
    "sg:address":"Via Castelletto Sn - Zona Artigian. 46048 Roverbella",
    "sg:city":"Roverbella",
    "sg:classifiers":[
        {
            "category":"Retail",
            "subcategory":"Car Wash",
            "type":"Services"
        }
    ],
    "sg:phone":"+39 0376 694814",
    "sg:postcode":"46048",
    "sg:province":"Mantova",
    "sg:tags":[
        "washer",
        "rinsers",
        "bottle"
    ],
    "sg:website":"www.costec.it",
    "wof:name":"Costec Costruzioni Tecniche S.r.l.",
    "wof:placetype":"venue"
},
  "geometry": {"coordinates":[10.797698,45.160366],"type":"Point"}
}