{
  "type": "Feature",
  "properties": {
    "iso:country":"IT",
    "sg:address":"Via Caltana 5/7, 35011 Campodarsego, Pd",
    "sg:city":"Campodarsego",
    "sg:classifiers":[
        {
            "category":"Banks & Credit Unions",
            "subcategory":"Bank",
            "type":"Services"
        }
    ],
    "sg:postcode":"35011",
    "sg:province":"Padova",
    "wof:name":"Banca Di Credito Cooperativo Dell'alta Padovana-campodarsego (padova)",
    "wof:placetype":"venue"
},
  "geometry": {"coordinates":[11.909712,45.5014],"type":"Point"}
}