{
  "type": "Feature",
  "properties": {
    "addr:full":"10125 Torino Torino Torino 10125",
    "addr:postcode":"10125;10125",
    "iso:country":"IT",
    "sg:address":"10125 Torino",
    "sg:city":"Torino",
    "sg:orig_category":"Musica",
    "sg:phone":"+39 011 650 4000",
    "sg:postcode":"10125",
    "sg:province":"Torino",
    "wof:name":"Casa Musicale Scavino (s.n.c.)",
    "wof:placetype":"venue"
},
  "geometry": {"coordinates":[7.6796693802,45.0510520935],"type":"Point"}
}