{
  "type": "Feature",
  "properties": {
    "addr:full":"3, Via Zona Industriale 33086 Montereale Valcellina Montereale Valcellina Pordenone 33086",
    "addr:postcode":"33086;33086",
    "addr:street":"Via Zona Industriale",
    "iso:country":"IT",
    "sg:address":"3, Via Zona Industriale 33086 Montereale Valcellina",
    "sg:city":"Montereale Valcellina",
    "sg:classifiers":[
        {
            "category":"Shopping",
            "subcategory":"Crafts & Fabrics",
            "type":"Retail Goods"
        }
    ],
    "sg:phone":"+39 0427 799421",
    "sg:postcode":"33086",
    "sg:province":"Pordenone",
    "wof:name":"Montereale Filati (s.p.a.)",
    "wof:placetype":"venue"
},
  "geometry": {"coordinates":[12.655043602,45.9626502991],"type":"Point"}
}