{
  "type": "Feature",
  "properties": {
    "addr:full":"26100 Cremona Cremona Cremona 26100",
    "addr:postcode":"26100;26100",
    "iso:country":"IT",
    "sg:address":"26100 Cremona",
    "sg:city":"Cremona",
    "sg:orig_category":"Pubblicita' - Consulenza E Servizi",
    "sg:phone":"+39 0372 450467",
    "sg:postcode":"26100",
    "sg:province":"Cremona",
    "wof:name":"Gruppo Agoros Srl",
    "wof:placetype":"venue"
},
  "geometry": {"coordinates":[10.0328149796,45.1331634521],"type":"Point"}
}