{
  "type": "Feature",
  "properties": {
    "iso:country":"IT",
    "sg:address":"81034 Mondragone",
    "sg:city":"Mondragone",
    "sg:orig_category":"Prodotti Di Base E Forniture Per Industria Alimentare E Bevande. Prodotti Chimici Secondari. Forniture Alle Strutture Ricettive",
    "sg:phone":"+39 0823 978043",
    "sg:postcode":"81034",
    "sg:province":"Caserta",
    "wof:name":"Sorrentino Vincenzo",
    "wof:placetype":"venue"
},
  "geometry": {"coordinates":[14.3604183197,41.0944633484],"type":"Point"}
}