{
  "type": "Feature",
  "properties": {
    "iso:country":"IT",
    "sg:address":"Via Dei Laghi 61030 Calcinelli",
    "sg:city":"Calcinelli",
    "sg:classifiers":[
        {
            "category":"Autos & Motor Vehicles",
            "subcategory":"Boat Sales",
            "type":"Retail Goods"
        }
    ],
    "sg:phone":"+39 0721 877265",
    "sg:postcode":"61030",
    "sg:province":"Pesaro E Urbino",
    "sg:tags":[
        "machine",
        "metal",
        "profiling",
        "sheet",
        "strip"
    ],
    "wof:name":"Nuova Saf Srl",
    "wof:placetype":"venue"
},
  "geometry": {"coordinates":[12.5298032761,43.633556366],"type":"Point"}
}