{
  "type": "Feature",
  "properties": {
    "addr:full":"13018 Valduggia Valduggia Vercelli 13018",
    "addr:housenumber":"13018",
    "addr:postcode":"13018",
    "addr:street":"Valduggia Valduggia",
    "iso:country":"IT",
    "sg:address":"13018 Valduggia",
    "sg:city":"Valduggia",
    "sg:classifiers":[
        {
            "category":"Utilities",
            "subcategory":"Water",
            "type":"Services"
        }
    ],
    "sg:phone":"+39 0163 48165",
    "sg:postcode":"13018",
    "sg:province":"Vercelli",
    "sg:tags":[
        "equipment",
        "valve",
        "measurement"
    ],
    "sg:website":"http://www.officinerigamonti.it",
    "wof:name":"Officine Rigamonti Spa",
    "wof:placetype":"venue"
},
  "geometry": {"coordinates":[8.278388,45.711861],"type":"Point"}
}