{
  "type": "Feature",
  "properties": {
    "iso:country":"IT",
    "sg:address":"50029 Tavarnuzze",
    "sg:orig_category":"Ceramiche: Prodotti E Lavorazioni",
    "sg:phone":"+39 055 202 0342",
    "sg:province":"FI",
    "wof:name":"Calosi Riziero",
    "wof:placetype":"venue"
},
  "geometry": {"coordinates":[-94.5418167114,41.8102378845],"type":"Point"}
}