{
  "type": "Feature",
  "properties": {
    "iso:country":"IT",
    "sg:address":"Km. 403.600, Strada Statale 16 Adriatica 64018 Tortoreto",
    "sg:city":"Tortoreto",
    "sg:classifiers":[
        {
            "category":"Shopping",
            "subcategory":"Clothing, Apparel, & Fashions",
            "type":"Retail Goods"
        }
    ],
    "sg:phone":"+39 0861 786641",
    "sg:postcode":"64018",
    "sg:province":"Teramo",
    "sg:tags":[
        "clothes"
    ],
    "wof:name":"Camiceria Adipca Di Di Paolo Alfano (s.r.l.)",
    "wof:placetype":"venue"
},
  "geometry": {"coordinates":[13.698531,42.66127],"type":"Point"}
}