{
  "type": "Feature",
  "properties": {
    "iso:country":"IT",
    "sg:address":"65127 Pescara",
    "sg:city":"Pescara",
    "sg:orig_category":"Non-classified Establishments",
    "sg:phone":"+39 085 63630",
    "sg:postcode":"65127",
    "sg:province":"Pescara",
    "wof:name":"Fabiani Arturo",
    "wof:placetype":"venue"
},
  "geometry": {"coordinates":[14.215029,42.458572],"type":"Point"}
}