{
  "type": "Feature",
  "properties": {
    "addr:full":"36, Via Lombardia 20089 Rozzano Rozzano Milano 20089",
    "addr:postcode":"20089;20089",
    "addr:street":"Via Lombardia",
    "iso:country":"IT",
    "sg:address":"36, Via Lombardia 20089 Rozzano",
    "sg:city":"Rozzano",
    "sg:classifiers":[
        {
            "category":"Professional",
            "subcategory":"Engineering",
            "type":"Services"
        }
    ],
    "sg:phone":"+39 39028259004",
    "sg:postcode":"20089",
    "sg:province":"Milano",
    "sg:tags":[
        "machine",
        "-",
        "mechanical"
    ],
    "wof:name":"Officina Meccanica Bazzano (s.r.l.)",
    "wof:placetype":"venue"
},
  "geometry": {"coordinates":[9.152091,45.385025],"type":"Point"}
}