{
  "type": "Feature",
  "properties": {
    "addr:full":"21011 Casorate Sempione Casorate Sempione Varese 21011",
    "addr:postcode":"21011;21011",
    "iso:country":"IT",
    "sg:address":"21011 Casorate Sempione",
    "sg:city":"Casorate Sempione",
    "sg:orig_category":"Riparazione Dei Mezzi Di Trasporto",
    "sg:phone":"+39 0331 295293",
    "sg:postcode":"21011",
    "sg:province":"Varese",
    "sg:website":"http://www.redmotors.it",
    "wof:name":"Red Motors Srl",
    "wof:placetype":"venue"
},
  "geometry": {"coordinates":[8.749435,45.671986],"type":"Point"}
}