{
  "type": "Feature",
  "properties": {
    "iso:country":"IT",
    "sg:address":"80125 Napoli",
    "sg:city":"Napoli",
    "sg:orig_category":"Materiali Edili",
    "sg:phone":"+39 081 570 1801",
    "sg:postcode":"80125",
    "sg:province":"Napoli",
    "wof:name":"Co.ap. Generali Srl",
    "wof:placetype":"venue"
},
  "geometry": {"coordinates":[14.170432,40.860298],"type":"Point"}
}