{
  "type": "Feature",
  "properties": {
    "addr:full":"4, Via Italia 24030 Valbrembo Valbrembo Bergamo 24030",
    "addr:postcode":"24030;24030",
    "addr:street":"Via Italia",
    "iso:country":"IT",
    "sg:address":"4, Via Italia 24030 Valbrembo",
    "sg:city":"Valbrembo",
    "sg:classifiers":[
        {
            "category":"Manufacturing",
            "subcategory":"Metals",
            "type":"Manufacturing & Wholesale Goods"
        }
    ],
    "sg:phone":"+39 035 437 8087",
    "sg:postcode":"24030",
    "sg:province":"Bergamo",
    "sg:tags":[
        "metallurgy",
        "metalworking"
    ],
    "wof:name":"M.a.b. Di G. Galbusera & C. Snc",
    "wof:placetype":"venue"
},
  "geometry": {"coordinates":[9.6006202698,45.7123565674],"type":"Point"}
}