{
  "type": "Feature",
  "properties": {
    "addr:full":"46019 Viadana Cogozzo Mantova 46019",
    "addr:postcode":"46019;46019",
    "iso:country":"IT",
    "sg:address":"46019 Viadana",
    "sg:city":"Cogozzo",
    "sg:orig_category":"Prodotti E Manufatti In Materie Plastiche. Prodotti Cosmetici E Da Toeletta. Forniture Per Attivita' Industriali",
    "sg:phone":"+39 0375 88224",
    "sg:postcode":"46019",
    "sg:province":"Mantova",
    "sg:website":"http://www.binicasa.it",
    "wof:name":"Bini Pietro & C. Snc",
    "wof:placetype":"venue"
},
  "geometry": {"coordinates":[10.4930448532,44.9358901978],"type":"Point"}
}