{
  "type": "Feature",
  "properties": {
    "iso:country":"IT",
    "sg:address":"65126 Pescara",
    "sg:city":"Pescara",
    "sg:orig_category":"Servizi E Lavori Per Arredamento E Industria Del Legno. Servizi E Lavori Per Edilizia E Lavori Pubblici",
    "sg:phone":"+39 085 440 6145",
    "sg:postcode":"65126",
    "sg:province":"Pescara",
    "wof:name":"Di Luca Anna",
    "wof:placetype":"venue"
},
  "geometry": {"coordinates":[14.22506,42.461456],"type":"Point"}
}