{
  "type": "Feature",
  "properties": {
    "iso:country":"IT",
    "sg:address":"20153 Milano",
    "sg:city":"Milano",
    "sg:orig_category":"Arredo Cucina Ed Elettrodomestici",
    "sg:phone":"+39 02 4820 3492",
    "sg:postcode":"20153",
    "sg:province":"Milano",
    "sg:website":"http://www.peregoarreda.it",
    "wof:name":"Perego & C. Srl - Peregoarreda",
    "wof:placetype":"venue"
},
  "geometry": {"coordinates":[9.089931,45.480263],"type":"Point"}
}