{
  "type": "Feature",
  "properties": {
    "iso:country":"IT",
    "sg:address":"36016 Thiene",
    "sg:city":"Thiene",
    "sg:orig_category":"Servizi Ausiliari Per Il Trasporto",
    "sg:phone":"+39 0445 370968",
    "sg:postcode":"36016",
    "sg:province":"Vicenza",
    "wof:name":"Elipiu' Srl",
    "wof:placetype":"venue"
},
  "geometry": {"coordinates":[11.47261,45.705593],"type":"Point"}
}