{
  "type": "Feature",
  "properties": {
    "addr:full":"36028 Rossano Veneto Rossano Veneto Vicenza 36028",
    "addr:postcode":"36028;36028",
    "addr:street":"Veneto",
    "iso:country":"IT",
    "sg:address":"36028 Rossano Veneto",
    "sg:city":"Rossano Veneto",
    "sg:orig_category":"Minuterie Metalliche E Ferramenta",
    "sg:phone":"+39 0424 540639",
    "sg:postcode":"36028",
    "sg:province":"Vicenza",
    "sg:website":"http://www.agostinellicamillo.com",
    "wof:name":"Agostinelli Srl",
    "wof:placetype":"venue"
},
  "geometry": {"coordinates":[11.8098106384,45.7067756653],"type":"Point"}
}