{
  "type": "Feature",
  "properties": {
    "addr:full":"48022 Lugo Lugo Ravenna 48022",
    "addr:postcode":"48022;48022",
    "iso:country":"IT",
    "sg:address":"48022 Lugo",
    "sg:city":"Lugo",
    "sg:orig_category":"Fiori E Piante - Vendita Al Dettaglio",
    "sg:phone":"+39 0545 24101",
    "sg:postcode":"48022",
    "sg:province":"Ravenna",
    "wof:name":"Arte Floreale",
    "wof:placetype":"venue"
},
  "geometry": {"coordinates":[11.9029254913,44.423992157],"type":"Point"}
}