{
  "type": "Feature",
  "properties": {
    "iso:country":"IT",
    "sg:address":"40/42, Via Francesco Lana 25020 Flero",
    "sg:city":"Flero",
    "sg:classifiers":[
        {
            "category":"Professional",
            "subcategory":"Engineering",
            "type":"Services"
        }
    ],
    "sg:phone":"+39 030 358 0412",
    "sg:postcode":"25020",
    "sg:province":"Brescia",
    "sg:tags":[
        "machine",
        "-",
        "mechanical"
    ],
    "wof:name":"Filippini (s.r.l.)",
    "wof:placetype":"venue"
},
  "geometry": {"coordinates":[10.154611,45.483856],"type":"Point"}
}