{
  "type": "Feature",
  "properties": {
    "iso:country":"IT",
    "sg:address":"56019 Vecchiano",
    "sg:city":"Migliarino",
    "sg:orig_category":"Accessori Dei Mezzi Di Trasporto",
    "sg:phone":"+39 050 804291",
    "sg:postcode":"56019",
    "sg:province":"Pisa",
    "wof:name":"T.m.m. Srl Trasformazione Materiali Metallici",
    "wof:placetype":"venue"
},
  "geometry": {"coordinates":[10.347758,43.795502],"type":"Point"}
}