{
  "type": "Feature",
  "properties": {
    "iso:country":"IT",
    "sg:address":"25030 Roncadelle",
    "sg:city":"Roncadelle",
    "sg:orig_category":"Utensili Meccanici E Materiali",
    "sg:phone":"+39 030 278211",
    "sg:postcode":"25030",
    "sg:province":"Brescia",
    "wof:name":"U O P Spa",
    "wof:placetype":"venue"
},
  "geometry": {"coordinates":[10.215673,45.534576],"type":"Point"}
}