{
  "type": "Feature",
  "properties": {
    "addr:full":"6, Via Arcane 31049 Valdobbiadene Valdobbiadene Treviso 31049",
    "addr:postcode":"31049;31049",
    "addr:street":"Via Arcane",
    "iso:country":"IT",
    "sg:address":"6, Via Arcane 31049 Valdobbiadene",
    "sg:city":"Valdobbiadene",
    "sg:classifiers":[
        {
            "category":"Food & Beverages",
            "subcategory":"Groceries & Convenience Stores",
            "type":"Retail Goods"
        }
    ],
    "sg:phone":"+39 0423 975668",
    "sg:postcode":"31049",
    "sg:province":"Treviso",
    "sg:tags":[
        "drink"
    ],
    "wof:name":"Cantine Bortolotti Umberto (s.r.l.)",
    "wof:placetype":"venue"
},
  "geometry": {"coordinates":[12.002067,45.900379],"type":"Point"}
}