{
  "type": "Feature",
  "properties": {
    "iso:country":"IT",
    "sg:address":"36031 Dueville",
    "sg:city":"Dueville",
    "sg:orig_category":"Chiusini",
    "sg:phone":"+39 0444 360250",
    "sg:postcode":"36031",
    "sg:province":"Vicenza",
    "wof:name":"F.a.s.p. Augusto Sbalchiero Spa",
    "wof:placetype":"venue"
},
  "geometry": {"coordinates":[11.569936,45.625668],"type":"Point"}
}