{
  "type": "Feature",
  "properties": {
    "iso:country":"IT",
    "sg:address":"41057 Spilamberto",
    "sg:city":"Spilamberto",
    "sg:orig_category":"Cartotecnica E Servizi. Articoli Per Imballaggio E Confezionamento",
    "sg:phone":"+39 059 785804",
    "sg:postcode":"41057",
    "sg:province":"Modena",
    "wof:name":"Union P.k. Srl",
    "wof:placetype":"venue"
},
  "geometry": {"coordinates":[11.008236,44.545284],"type":"Point"}
}