{
  "type": "Feature",
  "properties": {
    "addr:full":"24124 Bergamo Bergamo Bergamo 24124",
    "addr:postcode":"24124;24124",
    "iso:country":"IT",
    "sg:address":"24124 Bergamo",
    "sg:city":"Bergamo",
    "sg:classifiers":[
        {
            "category":"Manufacturing",
            "subcategory":"Leather Goods",
            "type":"Manufacturing & Wholesale Goods"
        }
    ],
    "sg:phone":"+39 035 368411",
    "sg:postcode":"24124",
    "sg:province":"Bergamo",
    "sg:tags":[
        "footwear",
        "skin"
    ],
    "sg:website":"http://www.solesport.com",
    "wof:name":"Sole Sport Srl",
    "wof:placetype":"venue"
},
  "geometry": {"coordinates":[9.6915426254,45.7121047974],"type":"Point"}
}