{
  "type": "Feature",
  "properties": {
    "iso:country":"IT",
    "sg:address":"51100 Pistoia",
    "sg:city":"Pistoia",
    "sg:orig_category":"Abbigliamento Esterno, Maglierie E Pelliccerie. Calzature, Pelletterie E Pelli",
    "sg:phone":"+39 0573 20052",
    "sg:postcode":"51100",
    "sg:province":"Pistoia",
    "wof:name":"Paolo Ardisson Forniture Appalti Governativi Sas",
    "wof:placetype":"venue"
},
  "geometry": {"coordinates":[10.915415,43.938667],"type":"Point"}
}