{
  "type": "Feature",
  "properties": {
    "iso:country":"IT",
    "sg:address":"Via Don A. Battistoni 35; Jesi; 60035",
    "sg:city":"Jesi",
    "sg:classifiers":[
        {
            "category":"Banks & Credit Unions",
            "subcategory":"Bank",
            "type":"Services"
        }
    ],
    "sg:phone":"+39 0731 6471",
    "sg:postcode":"60035",
    "sg:province":"Ancona",
    "wof:name":"Banca Popolare Di Ancona Spa",
    "wof:placetype":"venue"
},
  "geometry": {"coordinates":[13.266004,43.535931],"type":"Point"}
}