{
  "type": "Feature",
  "properties": {
    "addr:full":"15, Via Frugoni Carlo Innocenzo 20162 Milano Milano Milano 20162",
    "addr:postcode":"20162;20162",
    "addr:street":"Via Frugoni Carlo Innocenzo",
    "iso:country":"IT",
    "sg:address":"15, Via Frugoni Carlo Innocenzo 20162 Milano",
    "sg:city":"Milano",
    "sg:classifiers":[
        {
            "category":"Shopping",
            "subcategory":"Clothing, Apparel, & Fashions",
            "type":"Retail Goods"
        }
    ],
    "sg:phone":"+39 39026435420",
    "sg:postcode":"20162",
    "sg:province":"Milano",
    "sg:tags":[
        "clothes"
    ],
    "wof:name":"Josfer Dei Fratelli Ferrari (s.n.c.)",
    "wof:placetype":"venue"
},
  "geometry": {"coordinates":[9.203226,45.482468],"type":"Point"}
}