{
  "type": "Feature",
  "properties": {
    "iso:country":"IT",
    "sg:address":"55, Via Piceno Aprutina 63100 Ascoli Piceno",
    "sg:city":"Ascoli Piceno",
    "sg:classifiers":[
        {
            "category":"Shopping",
            "subcategory":"Crafts & Fabrics",
            "type":"Retail Goods"
        }
    ],
    "sg:phone":"+39 0736 343042",
    "sg:postcode":"63100",
    "sg:province":"Ascoli Piceno",
    "wof:name":"Pirelli Cavi E Sistemi Energia Italia Spa",
    "wof:placetype":"venue"
},
  "geometry": {"coordinates":[13.6200313568,42.8437271118],"type":"Point"}
}