{
  "type": "Feature",
  "properties": {
    "addr:full":"00040 Montecompatri Montecompatri Roma 00040",
    "addr:postcode":"00040;roma 00040",
    "iso:country":"IT",
    "sg:address":"00040 Montecompatri",
    "sg:city":"Montecompatri",
    "sg:orig_category":"Forniture Per Edilizia E Lavori Pubblici. Prodotti Vari In Metallo",
    "sg:phone":"+39 06 947 6167",
    "sg:postcode":"00040",
    "sg:province":"Roma",
    "wof:name":"Officine Metalcola Grigliati",
    "wof:placetype":"venue"
},
  "geometry": {"coordinates":[12.7202892303,41.8597183228],"type":"Point"}
}