{
  "type": "Feature",
  "properties": {
    "iso:country":"IT",
    "sg:address":"20144 Milano",
    "sg:city":"Milano",
    "sg:orig_category":"Casellari E Cassette Postali, Bacheche",
    "sg:phone":"+39 02 481 4140",
    "sg:postcode":"20144",
    "sg:province":"Milano",
    "wof:name":"Aer-lux Nuova",
    "wof:placetype":"venue"
},
  "geometry": {"coordinates":[9.163122,45.461727],"type":"Point"}
}