{
  "type": "Feature",
  "properties": {
    "iso:country":"IT",
    "sg:address":"24048 Treviolo",
    "sg:city":"Treviolo",
    "sg:orig_category":"Elettrotecnica",
    "sg:phone":"+39 035 692171",
    "sg:postcode":"24048",
    "sg:province":"Bergamo",
    "sg:website":"http://www.smeasrl.it",
    "wof:name":"Smea Srl",
    "wof:placetype":"venue"
},
  "geometry": {"coordinates":[9.623471,45.672096],"type":"Point"}
}