{
  "type": "Feature",
  "properties": {
    "addr:full":"7, Via Dello Scime' 22044 Inverigo Inverigo Como 22044",
    "addr:postcode":"22044;22044",
    "addr:street":"Via Dello Scime '",
    "iso:country":"IT",
    "sg:address":"7, Via Dello Scime' 22044 Inverigo",
    "sg:city":"Inverigo",
    "sg:classifiers":[
        {
            "category":"Home & Garden",
            "subcategory":"Home Furnishings",
            "type":"Retail Goods"
        }
    ],
    "sg:phone":"+39 39031608398",
    "sg:postcode":"22044",
    "sg:province":"Como",
    "sg:tags":[
        "household"
    ],
    "wof:name":"Sg 2 S.n.c.",
    "wof:placetype":"venue"
},
  "geometry": {"coordinates":[9.213641,45.72398],"type":"Point"}
}