{
  "type": "Feature",
  "properties": {
    "iso:country":"IT",
    "sg:address":"3, Via Peter Mayr 39042 Bressanone",
    "sg:city":"Bressanone",
    "sg:classifiers":[
        {
            "category":"Wholesale",
            "subcategory":"Machinery & Supplies",
            "type":"Manufacturing & Wholesale Goods"
        }
    ],
    "sg:phone":"+39 0472 830746",
    "sg:postcode":"39042",
    "sg:province":"Bolzano/Bozen",
    "sg:tags":[
        "-",
        "agriculture",
        "equipment"
    ],
    "wof:name":"Blasbichler",
    "wof:placetype":"venue"
},
  "geometry": {"coordinates":[11.653217,46.720108],"type":"Point"}
}