{
  "type": "Feature",
  "properties": {
    "addr:full":"10040 Rivalta Di Torino Rivalta di Torino Torino 10040",
    "addr:postcode":"10040;10040",
    "iso:country":"IT",
    "sg:address":"10040 Rivalta Di Torino",
    "sg:city":"Rivalta di Torino",
    "sg:orig_category":"Utensili Meccanici E Materiali",
    "sg:phone":"+39 011 903 8572",
    "sg:postcode":"10040",
    "sg:province":"Torino",
    "wof:name":"Gts Italia S.r.l.",
    "wof:placetype":"venue"
},
  "geometry": {"coordinates":[7.47298,44.989906],"type":"Point"}
}