{
  "type": "Feature",
  "properties": {
    "iso:country":"IT",
    "sg:address":"Via Vittorio Emanuele Ii 25 25030 Roncadelle",
    "sg:city":"Roncadelle",
    "sg:classifiers":[
        {
            "category":"Food & Beverages",
            "subcategory":"Liquor & Beverages",
            "type":"Retail Goods"
        }
    ],
    "sg:phone":"+39 030 278 0125",
    "sg:postcode":"25030",
    "sg:province":"Brescia",
    "sg:tags":[
        "wine",
        "italian"
    ],
    "wof:name":"Barbi Srl",
    "wof:placetype":"venue"
},
  "geometry": {"coordinates":[10.16398,45.528965],"type":"Point"}
}