{
  "type": "Feature",
  "properties": {
    "addr:full":"90040 Torretta Capaci Palermo 90040",
    "addr:postcode":"90040;90040",
    "iso:country":"IT",
    "sg:address":"90040 Torretta",
    "sg:city":"Capaci",
    "sg:classifiers":[
        {
            "category":"Bars & Pubs",
            "subcategory":"Champagne Bar",
            "type":"Food & Drink"
        }
    ],
    "sg:phone":"+39 091 861 3063",
    "sg:postcode":"90040",
    "sg:province":"Palermo",
    "sg:tags":[
        "caffe'",
        "e"
    ],
    "wof:name":"Bar Pizzeria Trattoria Mignano",
    "wof:placetype":"venue"
},
  "geometry": {"coordinates":[13.228781,38.149536],"type":"Point"}
}