{
  "type": "Feature",
  "properties": {
    "addr:full":"6, Via G.massarenti 40057 Granarolo Dell'emilia Bologna 40057",
    "addr:postcode":"40057;40057",
    "addr:street":"Via G.Massarenti",
    "iso:country":"IT",
    "sg:address":"6, Via G.massarenti 40057 Granarolo Dell'emilia",
    "sg:classifiers":[
        {
            "category":"Professional",
            "subcategory":"Engineering",
            "type":"Services"
        }
    ],
    "sg:phone":"+39 39051766140",
    "sg:postcode":"40057",
    "sg:province":"Bologna",
    "sg:tags":[
        "machine",
        "-",
        "mechanical"
    ],
    "wof:name":"Protek S.r.l.",
    "wof:placetype":"venue"
},
  "geometry": {"coordinates":[11.395654,44.549618],"type":"Point"}
}