{
  "type": "Feature",
  "properties": {
    "iso:country":"IT",
    "sg:address":"56029 Santa Croce Sull'arno",
    "sg:orig_category":"Servizi E Lavori Per Abbigliamento E Pelletterie. Arte Ed Artigianato Artistico. Shopping",
    "sg:phone":"+39 0571 33653",
    "sg:postcode":"56029",
    "sg:province":"Pisa",
    "wof:name":"Alfa Di Ciampi Leontina",
    "wof:placetype":"venue"
},
  "geometry": {"coordinates":[10.760524,43.725792],"type":"Point"}
}