{
  "type": "Feature",
  "properties": {
    "iso:country":"IT",
    "sg:address":"20097 San Donato Milanese",
    "sg:city":"San Donato Milanese",
    "sg:orig_category":"Pubblica Amministrazione",
    "sg:phone":"+39 02 556 9111",
    "sg:postcode":"20097",
    "sg:province":"Milano",
    "wof:name":"Amministrazione Provinciale Di Milano",
    "wof:placetype":"venue"
},
  "geometry": {"coordinates":[9.2677326202,45.4047546387],"type":"Point"}
}