{
  "type": "Feature",
  "properties": {
    "iso:country":"IT",
    "sg:address":"00154 Roma",
    "sg:city":"Roma",
    "sg:orig_category":"Servizi Ausiliari Dei Mezzi Di Trasporto",
    "sg:phone":"+39 06 5160 4988",
    "sg:postcode":"00154",
    "sg:province":"Roma",
    "wof:name":"Jo Service Srl",
    "wof:placetype":"venue"
},
  "geometry": {"coordinates":[12.494942,41.864979],"type":"Point"}
}