{
  "type": "Feature",
  "properties": {
    "addr:full":"80129 Napoli Napoli Napoli 80129",
    "addr:housenumber":"80129",
    "addr:postcode":"80129",
    "iso:country":"IT",
    "sg:address":"80129 Napoli",
    "sg:city":"Napoli",
    "sg:orig_category":"Medici Specialisti - Ostetricia E Ginecologia",
    "sg:phone":"+39 081 558 4704",
    "sg:postcode":"80129",
    "sg:province":"Napoli",
    "wof:name":"Guida Dr. Maurizio",
    "wof:placetype":"venue"
},
  "geometry": {"coordinates":[14.27348,40.892498],"type":"Point"}
}