{
  "type": "Feature",
  "properties": {
    "iso:country":"IT",
    "sg:address":"23100 Sondrio",
    "sg:city":"Sondrio",
    "sg:orig_category":"Alberghi",
    "sg:phone":"+39 0342 533888",
    "sg:postcode":"23100",
    "sg:province":"Sondrio",
    "sg:website":"http://vittoriahotel.com",
    "wof:name":"Hotel Vittoria",
    "wof:placetype":"venue"
},
  "geometry": {"coordinates":[9.861529,46.170135],"type":"Point"}
}