{
  "type": "Feature",
  "properties": {
    "addr:full":"33043 Cividale Del Friuli Cividale del Friuli Udine 33043",
    "addr:postcode":"33043;33043",
    "iso:country":"IT",
    "sg:address":"33043 Cividale Del Friuli",
    "sg:city":"Cividale del Friuli",
    "sg:orig_category":"Amianto - Bonifica E Smantellamento",
    "sg:phone":"+39 0432 734277",
    "sg:postcode":"33043",
    "sg:province":"Udine",
    "sg:website":"http://www.mereucoperture.com",
    "wof:name":"F.lli Mereu Snc Di Daniele Mereu & C.",
    "wof:placetype":"venue"
},
  "geometry": {"coordinates":[13.433127,46.080143],"type":"Point"}
}