{
  "type": "Feature",
  "properties": {
    "iso:country":"IT",
    "sg:address":"89030 Caraffa Del Bianco",
    "sg:city":"Caraffa del Bianco",
    "sg:orig_category":"Automobili E Mezzi Di Trasporto. Riparazione Dei Mezzi Di Trasporto",
    "sg:phone":"+39 0961 953186",
    "sg:postcode":"89030",
    "sg:province":"Reggio Di Calabria",
    "wof:name":"Lombardo Paolo",
    "wof:placetype":"venue"
},
  "geometry": {"coordinates":[16.086466,38.092499],"type":"Point"}
}