{
  "type": "Feature",
  "properties": {
    "iso:country":"IT",
    "sg:address":"Stradello Aggazzotti 104 41010 San Damaso",
    "sg:classifiers":[
        {
            "category":"Professional",
            "subcategory":"Testing Lab",
            "type":"Services"
        }
    ],
    "sg:phone":"+39 059 461711",
    "sg:postcode":"41010",
    "sg:province":"Modena",
    "sg:tags":[
        "biochemical",
        "analysis"
    ],
    "sg:website":"www.neotron.it",
    "wof:name":"Neotron Spa",
    "wof:placetype":"venue"
},
  "geometry": {"coordinates":[10.973394,44.604187],"type":"Point"}
}