{
  "type": "Feature",
  "properties": {
    "addr:full":"91100 Trapani Trapani Trapani 91100",
    "addr:postcode":"91100;91100",
    "iso:country":"IT",
    "sg:address":"91100 Trapani",
    "sg:city":"Trapani",
    "sg:orig_category":"Elettrodomestici. Elettronica Professionale E Di Consumo. Arredi Ed Attrezzature Per Attivita' Commerciali Ed Artigianali. Macchine, Strumenti Ed Apparecchi Per Attivita' Industriali",
    "sg:phone":"+39 0923 27299",
    "sg:postcode":"91100",
    "sg:province":"Trapani",
    "wof:name":"Romano Massimo",
    "wof:placetype":"venue"
},
  "geometry": {"coordinates":[12.215379,37.388165],"type":"Point"}
}