{
  "type": "Feature",
  "properties": {
    "addr:full":"37060 Mozzecane Mozzecane Verona 37060",
    "addr:postcode":"37060;37060",
    "iso:country":"IT",
    "sg:address":"37060 Mozzecane",
    "sg:city":"Mozzecane",
    "sg:orig_category":"Autocarri",
    "sg:phone":"+39 045 793 0005",
    "sg:postcode":"37060",
    "sg:province":"Verona",
    "sg:website":"http://www.tagicar.com",
    "wof:name":"Tagi Car Italia Srl",
    "wof:placetype":"venue"
},
  "geometry": {"coordinates":[10.825217,45.315948],"type":"Point"}
}