{
  "type": "Feature",
  "properties": {
    "iso:country":"IT",
    "sg:address":"81020 Casapulla",
    "sg:city":"Casapulla",
    "sg:orig_category":"Abbigliamento Esterno, Maglierie E Pelliccerie. Shopping",
    "sg:phone":"+39 0823 460381",
    "sg:postcode":"81020",
    "sg:province":"Caserta",
    "wof:name":"Rosita Papa Camicie",
    "wof:placetype":"venue"
},
  "geometry": {"coordinates":[14.292462,41.076393],"type":"Point"}
}