{
  "type": "Feature",
  "properties": {
    "addr:full":"20098 San Giuliano Milanese San Giuliano Milanese Milano 20098",
    "addr:housenumber":"20098",
    "addr:postcode":"20098",
    "addr:street":"San",
    "iso:country":"IT",
    "sg:address":"20098 San Giuliano Milanese",
    "sg:city":"San Giuliano Milanese",
    "sg:orig_category":"Prodotti E Manufatti In Materie Plastiche",
    "sg:phone":"+39 02 9824 8125",
    "sg:postcode":"20098",
    "sg:province":"Milano",
    "wof:name":"Aerre Gomma Srl",
    "wof:placetype":"venue"
},
  "geometry": {"coordinates":[9.296421051,45.3932571411],"type":"Point"}
}