{
  "type": "Feature",
  "properties": {
    "iso:country":"IT",
    "sg:address":"43058 Sorbolo",
    "sg:city":"Sorbolo",
    "sg:orig_category":"Lucidatura, Laccatura E Verniciatura Mobili",
    "sg:phone":"+39 0521 694344",
    "sg:postcode":"43058",
    "sg:province":"Parma",
    "wof:name":"Nicoli Snc Di Nicoli Claudio & C.",
    "wof:placetype":"venue"
},
  "geometry": {"coordinates":[10.451044,44.843254],"type":"Point"}
}