{
  "type": "Feature",
  "properties": {
    "iso:country":"IT",
    "sg:address":"20, Via Provinciale Saronnese 20027 Rescaldina",
    "sg:city":"Rescaldina",
    "sg:classifiers":[
        {
            "category":"Professional",
            "subcategory":"Engineering",
            "type":"Services"
        }
    ],
    "sg:phone":"+39 0331 576400",
    "sg:postcode":"20027",
    "sg:province":"Milano",
    "sg:tags":[
        "machine",
        "-",
        "mechanical"
    ],
    "wof:name":"Lobbiani Macchine Di Lobbiani Angelo E C. S.a.s.",
    "wof:placetype":"venue"
},
  "geometry": {"coordinates":[8.959425,45.61219],"type":"Point"}
}