{
  "type": "Feature",
  "properties": {
    "iso:country":"IT",
    "sg:address":"20092 Cinisello Balsamo",
    "sg:city":"Cinisello Balsamo",
    "sg:classifiers":[
        {
            "category":"Health Services",
            "subcategory":"Health Practitioner",
            "type":"Services"
        }
    ],
    "sg:phone":"+39 02 6601 6638",
    "sg:postcode":"20092",
    "sg:province":"Milano",
    "sg:tags":[
        "medici"
    ],
    "wof:name":"Bosotti Guido",
    "wof:placetype":"venue"
},
  "geometry": {"coordinates":[9.218866,45.554657],"type":"Point"}
}