{
  "type": "Feature",
  "properties": {
    "iso:country":"IT",
    "sg:address":"20026 Novate Milanese",
    "sg:city":"Novate Milanese",
    "sg:orig_category":"Autobetoniere E Betoniere",
    "sg:phone":"+39 02 354761",
    "sg:postcode":"20026",
    "sg:province":"Milano",
    "wof:name":"Cifa Spa",
    "wof:placetype":"venue"
},
  "geometry": {"coordinates":[9.143185,45.530064],"type":"Point"}
}