{
  "type": "Feature",
  "properties": {
    "addr:full":"24026 Leffe Leffe Bergamo 24026",
    "addr:postcode":"24026;24026",
    "iso:country":"IT",
    "sg:address":"24026 Leffe",
    "sg:city":"Leffe",
    "sg:orig_category":"Forniture Per Abbigliamento E Pelletterie. Forniture E Materiali Per Imballaggio E Confezionamento",
    "sg:phone":"+39 035 731571",
    "sg:postcode":"24026",
    "sg:province":"Bergamo",
    "wof:name":"Euronastri Sas",
    "wof:placetype":"venue"
},
  "geometry": {"coordinates":[9.7251396179,45.68542099],"type":"Point"}
}