{
  "type": "Feature",
  "properties": {
    "iso:country":"IT",
    "sg:address":"V.le Togliatti 22; Spicchio; 50053",
    "sg:classifiers":[
        {
            "category":"Banks & Credit Unions",
            "subcategory":"Bank",
            "type":"Services"
        }
    ],
    "sg:phone":"+39 0571 508613",
    "sg:postcode":"50053",
    "sg:province":"Firenze",
    "wof:name":"Cassa Di Risparmio Di San Miniato",
    "wof:placetype":"venue"
},
  "geometry": {"coordinates":[10.943758,43.725872],"type":"Point"}
}