{
  "type": "Feature",
  "properties": {
    "addr:full":"25065 Lumezzane Lumezzane Brescia 25065",
    "addr:postcode":"25065;25065",
    "iso:country":"IT",
    "sg:address":"25065 Lumezzane",
    "sg:city":"Lumezzane",
    "sg:classifiers":[
        {
            "category":"Manufacturing",
            "subcategory":"Tools & Machinery",
            "type":"Manufacturing & Wholesale Goods"
        }
    ],
    "sg:phone":"+39 030 828000",
    "sg:postcode":"25065",
    "sg:province":"Brescia",
    "sg:tags":[
        "material",
        "mechanical"
    ],
    "wof:name":"Mfb Di Bonomi Eliseo & C. Snc",
    "wof:placetype":"venue"
},
  "geometry": {"coordinates":[10.271279,45.641235],"type":"Point"}
}