{
  "type": "Feature",
  "properties": {
    "addr:full":"00157 Roma Roma Roma 00157",
    "addr:postcode":"00157;00157",
    "iso:country":"IT",
    "sg:address":"00157 Roma",
    "sg:city":"Roma",
    "sg:orig_category":"Ecologia - Studi Consulenza E Servizi",
    "sg:phone":"+39 06 451 1372",
    "sg:postcode":"00157",
    "sg:province":"Roma",
    "wof:name":"Farma Srl",
    "wof:placetype":"venue"
},
  "geometry": {"coordinates":[12.546671,41.918308],"type":"Point"}
}