{
  "type": "Feature",
  "properties": {
    "addr:full":"2/4, Via Marangoni Leopoldo 20030 Bovisio Masciago Bovisio Milano 20030",
    "addr:housenumber":"2 / 4",
    "addr:postcode":"20030;20030",
    "addr:street":"Via Marangoni Leopoldo",
    "iso:country":"IT",
    "sg:address":"2/4, Via Marangoni Leopoldo 20030 Bovisio Masciago",
    "sg:city":"Bovisio",
    "sg:classifiers":[
        {
            "category":"Home & Garden",
            "subcategory":"Home Furnishings",
            "type":"Retail Goods"
        }
    ],
    "sg:phone":"+39 036 255 8999",
    "sg:postcode":"20030",
    "sg:province":"Milano",
    "sg:tags":[
        "household"
    ],
    "wof:name":"Aste Briantea Srl",
    "wof:placetype":"venue"
},
  "geometry": {"coordinates":[9.188141,45.463688],"type":"Point"}
}