{
  "type": "Feature",
  "properties": {
    "iso:country":"IT",
    "sg:address":"20121 Milano",
    "sg:city":"Milano",
    "sg:orig_category":"Arredamenti E Mobili Professionali. Arredi Ed Attrezzature Per Uffici",
    "sg:phone":"+39 02 7602 2365",
    "sg:postcode":"20121",
    "sg:province":"Milano",
    "sg:website":"http://www.monteravagnan.it",
    "wof:name":"Monte & Ravagnan Snc",
    "wof:placetype":"venue"
},
  "geometry": {"coordinates":[9.194113,45.46701],"type":"Point"}
}