{
  "type": "Feature",
  "properties": {
    "addr:full":"26041 Roncadello Roncadello Cremona 26041",
    "addr:postcode":"26041;26041",
    "iso:country":"IT",
    "sg:address":"26041 Roncadello",
    "sg:city":"Roncadello",
    "sg:orig_category":"Forniture Per Attivita' Industriali",
    "sg:phone":"+39 0375 59646",
    "sg:postcode":"26041",
    "sg:province":"Cremona",
    "wof:name":"Flisi Fabio",
    "wof:placetype":"venue"
},
  "geometry": {"coordinates":[10.0261354446,45.1334991455],"type":"Point"}
}