{
  "type": "Feature",
  "properties": {
    "addr:full":"Via Athos Maestri 8 00054 Fiumicino Fiumicino Roma 00054",
    "addr:housenumber":"8",
    "addr:postcode":"00054;roma 00054",
    "addr:street":"Via Athos Maestri",
    "iso:country":"IT",
    "sg:address":"Via Athos Maestri 8 00054 Fiumicino",
    "sg:city":"Fiumicino",
    "sg:classifiers":[
        {
            "category":"Home & Garden",
            "subcategory":"Furniture",
            "type":"Retail Goods"
        }
    ],
    "sg:phone":"+39 06 6502 8987",
    "sg:postcode":"00054",
    "sg:province":"Roma",
    "sg:tags":[
        "small",
        "occasional"
    ],
    "sg:website":"www.artem.it",
    "wof:name":"Artem International Srl",
    "wof:placetype":"venue"
},
  "geometry": {"coordinates":[12.2649364471,41.7611083984],"type":"Point"}
}