{
  "type": "Feature",
  "properties": {
    "iso:country":"IT",
    "sg:address":"20017 Rho",
    "sg:city":"Rho",
    "sg:orig_category":"Prodotti Di Base E Forniture Per Industria Alimentare E Bevande. Prodotti Chimici Di Base",
    "sg:phone":"+39 02 9390 6123",
    "sg:postcode":"20017",
    "sg:province":"Milano",
    "wof:name":"Flavourland Srl",
    "wof:placetype":"venue"
},
  "geometry": {"coordinates":[9.087937355,45.5257911682],"type":"Point"}
}