{
  "type": "Feature",
  "properties": {
    "iso:country":"IT",
    "sg:address":"3, Regione Isella 28804 San Bernardino Verbano",
    "sg:city":"San Bernardino Verbano",
    "sg:classifiers":[
        {
            "category":"Professional",
            "subcategory":"Engineering",
            "type":"Services"
        }
    ],
    "sg:phone":"+39 0323 553588",
    "sg:postcode":"28804",
    "sg:province":"Verbano-Cusio-Ossola",
    "sg:tags":[
        "machine",
        "-",
        "mechanical"
    ],
    "wof:name":"Eco - Inter S.r.l.",
    "wof:placetype":"venue"
},
  "geometry": {"coordinates":[8.529173851,45.9542427063],"type":"Point"}
}