{
  "type": "Feature",
  "properties": {
    "addr:full":"35020 Terrassa Padovana Terrassa Padovana Padova 35020",
    "addr:postcode":"35020;35020",
    "iso:country":"IT",
    "sg:address":"35020 Terrassa Padovana",
    "sg:city":"Terrassa Padovana",
    "sg:orig_category":"Carpenterie Meccaniche",
    "sg:phone":"+39 049 950 0710",
    "sg:postcode":"35020",
    "sg:province":"Padova",
    "wof:name":"Betto Lauro",
    "wof:placetype":"venue"
},
  "geometry": {"coordinates":[11.893687,45.252934],"type":"Point"}
}