{
  "type": "Feature",
  "properties": {
    "iso:country":"IT",
    "sg:address":"00198 Roma",
    "sg:city":"Roma",
    "sg:orig_category":"Automobili - Commercio",
    "sg:phone":"+39 06 8535 0841",
    "sg:postcode":"00198",
    "sg:province":"Roma",
    "wof:name":"Collina Srl",
    "wof:placetype":"venue"
},
  "geometry": {"coordinates":[12.371494,42.130253],"type":"Point"}
}