{
  "type": "Feature",
  "properties": {
    "iso:country":"IT",
    "sg:address":"32, V. Dell'artigianato 31050 Zenson Di Piave",
    "sg:city":"Zenson di Piave",
    "sg:classifiers":[
        {
            "category":"Shopping",
            "type":"Retail Goods"
        }
    ],
    "sg:phone":"+39 0421 344681",
    "sg:postcode":"31050",
    "sg:province":"Treviso",
    "sg:tags":[
        "finished",
        "-",
        "metallic"
    ],
    "sg:website":"http://www.paginegialle.it/geainox",
    "wof:name":"G. & A. Inox Srl",
    "wof:placetype":"venue"
},
  "geometry": {"coordinates":[12.4823694229,45.678565979],"type":"Point"}
}