{
  "type": "Feature",
  "properties": {
    "addr:full":"5, Via Roma 24020 Colzate Colzate Bergamo 24020",
    "addr:postcode":"24020;24020",
    "addr:street":"Via Roma",
    "iso:country":"IT",
    "sg:address":"5, Via Roma 24020 Colzate",
    "sg:city":"Colzate",
    "sg:classifiers":[
        {
            "category":"Utilities",
            "subcategory":"Electric",
            "type":"Services"
        }
    ],
    "sg:phone":"+39 39035713419",
    "sg:postcode":"24020",
    "sg:province":"Bergamo",
    "sg:tags":[
        "component",
        "electronic"
    ],
    "wof:name":"Elettromeccanica Pulcini (s.r.l.)",
    "wof:placetype":"venue"
},
  "geometry": {"coordinates":[9.857039,45.812149],"type":"Point"}
}