{
  "type": "Feature",
  "properties": {
    "iso:country":"IT",
    "sg:address":"40012 Calderara Di Reno",
    "sg:city":"Bargellino",
    "sg:classifiers":[
        {
            "category":"Manufacturing",
            "subcategory":"Motor Vehicles & Parts",
            "type":"Manufacturing & Wholesale Goods"
        }
    ],
    "sg:phone":"+39 051 727325",
    "sg:postcode":"40012",
    "sg:province":"Bologna",
    "sg:tags":[
        "drive"
    ],
    "sg:website":"http://www.coppieconiche.com",
    "wof:name":"Malaguti Di Brunetti Gianni",
    "wof:placetype":"venue"
},
  "geometry": {"coordinates":[11.2699184418,44.5373649597],"type":"Point"}
}