{
  "type": "Feature",
  "properties": {
    "iso:country":"IT",
    "sg:address":"20098 San Giuliano Milanese",
    "sg:city":"San Giuliano Milanese",
    "sg:orig_category":"Autofficine E Centri Assistenza",
    "sg:phone":"+39 02 9823 1744",
    "sg:postcode":"20098",
    "sg:province":"Milano",
    "wof:name":"C.s.m. Marmitte",
    "wof:placetype":"venue"
},
  "geometry": {"coordinates":[9.285596,45.383781],"type":"Point"}
}