{
  "type": "Feature",
  "properties": {
    "iso:country":"IT",
    "sg:address":"33170 Pordenone",
    "sg:city":"Pordenone",
    "sg:classifiers":[
        {
            "category":"Professional",
            "subcategory":"Business Services",
            "type":"Services"
        }
    ],
    "sg:phone":"+39 0434 524411",
    "sg:postcode":"33170",
    "sg:province":"Pordenone",
    "sg:tags":[
        "support",
        "companies",
        "events",
        "trade"
    ],
    "sg:website":"http://www.viaggilucangeli.it",
    "wof:name":"Agenzia Lucangeli Snc",
    "wof:placetype":"venue"
},
  "geometry": {"coordinates":[12.661452,45.956367],"type":"Point"}
}