{
  "type": "Feature",
  "properties": {
    "iso:country":"IT",
    "sg:address":"53020 Petroio",
    "sg:city":"Petroio",
    "sg:orig_category":"Materiali Edili",
    "sg:phone":"+39 0577 665267",
    "sg:postcode":"53020",
    "sg:province":"Siena",
    "wof:name":"S.l.a.p. S.r.l.",
    "wof:placetype":"venue"
},
  "geometry": {"coordinates":[11.079904,43.444469],"type":"Point"}
}