{
  "type": "Feature",
  "properties": {
    "iso:country":"IT",
    "sg:address":"17, Viale Dell' Industria 21052 Busto Arsizio",
    "sg:city":"Busto Arsizio",
    "sg:classifiers":[
        {
            "category":"Professional",
            "subcategory":"Engineering",
            "type":"Services"
        }
    ],
    "sg:phone":"+39 0331 352011",
    "sg:postcode":"21052",
    "sg:province":"Varese",
    "sg:tags":[
        "machine",
        "-",
        "mechanical"
    ],
    "wof:name":"Muzzi Costruzioni Meccaniche (s.r.l.)",
    "wof:placetype":"venue"
},
  "geometry": {"coordinates":[8.831161,45.586861],"type":"Point"}
}