{
  "type": "Feature",
  "properties": {
    "iso:country":"IT",
    "sg:address":"09125 Cagliari",
    "sg:city":"Cagliari",
    "sg:orig_category":"Materiali Edili",
    "sg:phone":"+39 070 303859",
    "sg:postcode":"09125",
    "sg:province":"Cagliari",
    "wof:name":"Di Naro Alberto",
    "wof:placetype":"venue"
},
  "geometry": {"coordinates":[9.130208,39.212528],"type":"Point"}
}