{
  "type": "Feature",
  "properties": {
    "iso:country":"IT",
    "sg:address":"100, V. Trieste 21023 Besozzo",
    "sg:city":"Besozzo",
    "sg:classifiers":[
        {
            "category":"Manufacturing",
            "subcategory":"Metals",
            "type":"Manufacturing & Wholesale Goods"
        }
    ],
    "sg:phone":"+39 0332 773940",
    "sg:postcode":"21023",
    "sg:province":"Varese",
    "sg:tags":[
        "processing"
    ],
    "sg:website":"http://www.paginegialle.it/vpajessy",
    "wof:name":"V.p.a. Snc",
    "wof:placetype":"venue"
},
  "geometry": {"coordinates":[8.6682157516,45.8643074036],"type":"Point"}
}