{
  "type": "Feature",
  "properties": {
    "iso:country":"IT",
    "sg:address":"16122 Genova",
    "sg:city":"Genova",
    "sg:orig_category":"Scuole E Servizi Scolastici. Ricerca, Selezione E Formazione Del Personale",
    "sg:phone":"+39 010 837 6001",
    "sg:postcode":"16122",
    "sg:province":"Genova",
    "wof:name":"Aesseffe Scpa - Agenzia Servizi Formativi",
    "wof:placetype":"venue"
},
  "geometry": {"coordinates":[8.942699,44.411369],"type":"Point"}
}