{
  "type": "Feature",
  "properties": {
    "iso:country":"IT",
    "sg:address":"21040 Oggiona Santo Stefano",
    "sg:city":"Oggiona",
    "sg:orig_category":"Forniture Per Attivita' Commerciali Ed Artigianali. Arredi Ed Attrezzature Per Attivita' Commerciali Ed Artigianali",
    "sg:phone":"+39 0331 739004",
    "sg:postcode":"21040",
    "sg:province":"Varese",
    "wof:name":"R.b.a. Srl",
    "wof:placetype":"venue"
},
  "geometry": {"coordinates":[8.8319005966,45.816608429],"type":"Point"}
}