{
  "type": "Feature",
  "properties": {
    "iso:country":"IT",
    "sg:address":"Via Brennero 45 39040 Varna",
    "sg:city":"Varna",
    "sg:classifiers":[
        {
            "category":"Home & Garden",
            "subcategory":"Building Materials",
            "type":"Retail Goods"
        }
    ],
    "sg:phone":"+39 0472 837074",
    "sg:postcode":"39040",
    "sg:province":"Bolzano/Bozen",
    "sg:tags":[
        "aluminium",
        "window"
    ],
    "sg:website":"www.kaser.it",
    "wof:name":"Kaser Srl",
    "wof:placetype":"venue"
},
  "geometry": {"coordinates":[11.081414,45.929028],"type":"Point"}
}