{
  "type": "Feature",
  "properties": {
    "iso:country":"IT",
    "sg:address":"108/c, Via Europa 25062 Concesio",
    "sg:city":"Concesio",
    "sg:classifiers":[
        {
            "category":"Communications",
            "subcategory":"Newspaper",
            "type":"Services"
        }
    ],
    "sg:phone":"+39 030 218 0935",
    "sg:postcode":"25062",
    "sg:province":"Brescia",
    "sg:tags":[
        "advertising"
    ],
    "wof:name":"Foto & Grafica S.r.l.",
    "wof:placetype":"venue"
},
  "geometry": {"coordinates":[10.223664,45.598415],"type":"Point"}
}