{
  "type": "Feature",
  "properties": {
    "addr:full":"44016 San Biagio San Biagio Ferrara 44016",
    "addr:housenumber":"44016",
    "addr:postcode":"biagio;44016",
    "addr:street":"San",
    "iso:country":"IT",
    "sg:address":"44016 San Biagio",
    "sg:city":"San Biagio",
    "sg:orig_category":"Cine-foto-ottica. Shopping",
    "sg:phone":"+39 0532 809151",
    "sg:postcode":"44016",
    "sg:province":"Ferrara",
    "wof:name":"Paprika",
    "wof:placetype":"venue"
},
  "geometry": {"coordinates":[11.866722,44.586407],"type":"Point"}
}