{
  "type": "Feature",
  "properties": {
    "addr:full":"193, Via Dell' Acqua Traversa 00135 Roma Roma Roma 00135",
    "addr:housenumber":"193",
    "addr:postcode":"00135;00135",
    "addr:street":"Via Dell ' Acqua Traversa",
    "iso:country":"IT",
    "sg:address":"193, Via Dell' Acqua Traversa 00135 Roma",
    "sg:city":"Roma",
    "sg:classifiers":[
        {
            "category":"Manufacturing",
            "subcategory":"Printing",
            "type":"Manufacturing & Wholesale Goods"
        }
    ],
    "sg:phone":"+39 39063313000",
    "sg:postcode":"00135",
    "sg:province":"Roma",
    "sg:tags":[
        "publishing"
    ],
    "wof:name":"Epc S.r.l.",
    "wof:placetype":"venue"
},
  "geometry": {"coordinates":[12.7087478638,41.8276023865],"type":"Point"}
}