{
  "type": "Feature",
  "properties": {
    "iso:country":"IT",
    "sg:address":"Via Bovisasca 24/26 20026 Novate Milanese",
    "sg:city":"Novate Milanese",
    "sg:classifiers":[
        {
            "category":"Depot",
            "subcategory":"Bus",
            "type":"Transportation"
        }
    ],
    "sg:phone":"+39 02 3910 0533",
    "sg:postcode":"20026",
    "sg:province":"Milano",
    "sg:tags":[
        "insulator"
    ],
    "sg:website":"www.erim.it",
    "wof:name":"Erim Srl",
    "wof:placetype":"venue"
},
  "geometry": {"coordinates":[9.148807,45.525776],"type":"Point"}
}