{
  "type": "Feature",
  "properties": {
    "addr:full":"2, Via Delfini Antonio 41100 Modena Modena Modena 41100",
    "addr:postcode":"41100;41100",
    "addr:street":"Via Delfini Antonio",
    "iso:country":"IT",
    "sg:address":"2, Via Delfini Antonio 41100 Modena",
    "sg:city":"Modena",
    "sg:classifiers":[
        {
            "category":"Shopping",
            "subcategory":"Crafts & Fabrics",
            "type":"Retail Goods"
        }
    ],
    "sg:phone":"+39 39059828875",
    "sg:postcode":"41100",
    "sg:province":"Modena",
    "wof:name":"Modenflex (s.r.l.)",
    "wof:placetype":"venue"
},
  "geometry": {"coordinates":[10.9252195358,44.6470794678],"type":"Point"}
}