{
  "type": "Feature",
  "properties": {
    "addr:full":"50129 Firenze Firenze Firenze 50129",
    "addr:postcode":"50129;50129",
    "iso:country":"IT",
    "sg:address":"50129 Firenze",
    "sg:city":"Firenze",
    "sg:orig_category":"Scuole E Servizi Scolastici. Centri Di Estetica E Cosmesi E Servizi. Ricerca, Selezione E Formazione Del Personale",
    "sg:phone":"+39 055 495157",
    "sg:postcode":"50129",
    "sg:province":"Firenze",
    "wof:name":"Scuola S.e.m. Scuola Di Estetica Moderna",
    "wof:placetype":"venue"
},
  "geometry": {"coordinates":[11.257915,43.78056],"type":"Point"}
}