{
  "type": "Feature",
  "properties": {
    "iso:country":"IT",
    "sg:address":"00152 Roma",
    "sg:city":"Roma",
    "sg:orig_category":"Argenterie - Vendita Al Dettaglio",
    "sg:phone":"+39 06 5823 7736",
    "sg:postcode":"00152",
    "sg:province":"Roma",
    "wof:name":"L'angolo Del Regalo Snc",
    "wof:placetype":"venue"
},
  "geometry": {"coordinates":[12.437986,41.872963],"type":"Point"}
}