{
  "type": "Feature",
  "properties": {
    "addr:full":"4, Viale Francia 35020 Tribano Tribano Padova 35020",
    "addr:postcode":"35020;35020",
    "addr:street":"Viale Francia",
    "iso:country":"IT",
    "sg:address":"4, Viale Francia 35020 Tribano",
    "sg:city":"Tribano",
    "sg:classifiers":[
        {
            "category":"Professional",
            "subcategory":"Engineering",
            "type":"Services"
        }
    ],
    "sg:phone":"+39 049 958 5233",
    "sg:postcode":"35020",
    "sg:province":"Padova",
    "sg:tags":[
        "machine",
        "-",
        "mechanical"
    ],
    "wof:name":"I.me.p. Srl",
    "wof:placetype":"venue"
},
  "geometry": {"coordinates":[11.84246,45.212711],"type":"Point"}
}