{
  "type": "Feature",
  "properties": {
    "iso:country":"IT",
    "sg:address":"00054 Fiumicino",
    "sg:city":"Fiumicino",
    "sg:orig_category":"Arte Ed Artigianato Artistico",
    "sg:phone":"+39 06 658 1655",
    "sg:postcode":"00054",
    "sg:province":"Roma",
    "wof:name":"Artiontema Srl",
    "wof:placetype":"venue"
},
  "geometry": {"coordinates":[12.261734,41.765865],"type":"Point"}
}