{
  "type": "Feature",
  "properties": {
    "addr:full":"20036 Meda Meda Milano 20036",
    "addr:postcode":"20036;20036",
    "iso:country":"IT",
    "sg:address":"20036 Meda",
    "sg:city":"Meda",
    "sg:orig_category":"Legno E Semilavorati",
    "sg:phone":"+39 036 272143",
    "sg:postcode":"20036",
    "sg:province":"Milano",
    "sg:website":"http://www.mottatranciati.com",
    "wof:name":"Motta Tranciati Legno Spa",
    "wof:placetype":"venue"
},
  "geometry": {"coordinates":[9.178869,45.662613],"type":"Point"}
}