{
  "type": "Feature",
  "properties": {
    "iso:country":"IT",
    "sg:address":"Via Monte Ortigara 95 36073 Cornedo Vicentino",
    "sg:city":"Cornedo Vicentino",
    "sg:classifiers":[
        {
            "category":"Banks & Credit Unions",
            "subcategory":"Investment Brokerage",
            "type":"Services"
        }
    ],
    "sg:phone":"+39 0445 402888",
    "sg:postcode":"36073",
    "sg:province":"Vicenza",
    "sg:tags":[
        "embossed",
        "label"
    ],
    "sg:website":"www.lariplast.com",
    "wof:name":"Lariplast Srl",
    "wof:placetype":"venue"
},
  "geometry": {"coordinates":[11.313228,45.625893],"type":"Point"}
}