{
  "type": "Feature",
  "properties": {
    "addr:full":"20122 Milano Milano Milano 20122",
    "addr:postcode":"20122;20122",
    "iso:country":"IT",
    "sg:address":"20122 Milano",
    "sg:city":"Milano",
    "sg:orig_category":"Forniture Per Abbigliamento E Pelletterie",
    "sg:postcode":"20122",
    "sg:province":"Milano",
    "wof:name":"Fontana Bruna",
    "wof:placetype":"venue"
},
  "geometry": {"coordinates":[9.2244319916,45.4689865112],"type":"Point"}
}