{
  "type": "Feature",
  "properties": {
    "addr:full":"20021 Baranzate Baranzate Milano 20021",
    "addr:postcode":"20021;20021",
    "iso:country":"IT",
    "sg:address":"20021 Baranzate",
    "sg:city":"Baranzate",
    "sg:orig_category":"Elettrodomestici. Forniture Alle Strutture Ricettive",
    "sg:phone":"+39 02 356 2800",
    "sg:postcode":"20021",
    "sg:province":"Milano",
    "wof:name":"Aiesse (s.r.l.)",
    "wof:placetype":"venue"
},
  "geometry": {"coordinates":[9.117011,45.52739],"type":"Point"}
}