{
  "type": "Feature",
  "properties": {
    "iso:country":"IT",
    "sg:address":"33057 Palmanova",
    "sg:city":"Palmanova",
    "sg:classifiers":[
        {
            "category":"Health Services",
            "subcategory":"Health Practitioner",
            "type":"Services"
        }
    ],
    "sg:phone":"+39 0432 924323",
    "sg:postcode":"33057",
    "sg:province":"Udine",
    "sg:tags":[
        "medici"
    ],
    "wof:name":"Lanzafame Rosario",
    "wof:placetype":"venue"
},
  "geometry": {"coordinates":[13.323956,45.910294],"type":"Point"}
}