{
  "type": "Feature",
  "properties": {
    "addr:full":"38043 Bedollo Bedollo Trento 38043",
    "addr:housenumber":"38043",
    "addr:postcode":"38043",
    "addr:street":"Bedollo Bedollo Trento",
    "iso:country":"IT",
    "sg:address":"38043 Bedollo",
    "sg:city":"Bedollo",
    "sg:orig_category":"Manufacturers: Prefabbricati",
    "sg:phone":"+39 0461 555013",
    "sg:postcode":"38043",
    "sg:province":"Trento",
    "wof:name":"Perforazioni Opere Specializzate S.r.l.",
    "wof:placetype":"venue"
},
  "geometry": {"coordinates":[11.304,46.161041],"type":"Point"}
}