{
  "type": "Feature",
  "properties": {
    "iso:country":"IT",
    "sg:address":"1, Via Adda 22070 Senna Comasco",
    "sg:city":"Senna Comasco",
    "sg:classifiers":[
        {
            "category":"Shopping",
            "subcategory":"Computers & Home Electronics",
            "type":"Retail Goods"
        }
    ],
    "sg:phone":"+39 39031461311",
    "sg:postcode":"22070",
    "sg:province":"Como",
    "sg:tags":[
        "electronic",
        "electrical",
        "equipment"
    ],
    "wof:name":"Tecnoelettrica Lariana (s.n.c.)",
    "wof:placetype":"venue"
},
  "geometry": {"coordinates":[9.113506,45.76355],"type":"Point"}
}