{
  "type": "Feature",
  "properties": {
    "addr:full":"31058 Susegana Susegana Treviso 31058",
    "addr:postcode":"31058;31058",
    "iso:country":"IT",
    "sg:address":"31058 Susegana",
    "sg:city":"Susegana",
    "sg:classifiers":[
        {
            "category":"Home & Garden",
            "subcategory":"Home Furnishings",
            "type":"Retail Goods"
        }
    ],
    "sg:phone":"+39 0438 435151",
    "sg:postcode":"31058",
    "sg:province":"Treviso",
    "sg:tags":[
        "professional",
        "furniture"
    ],
    "sg:website":"http://www.caloi.it",
    "wof:name":"Caloi Industria Srl",
    "wof:placetype":"venue"
},
  "geometry": {"coordinates":[12.2772531509,45.872833252],"type":"Point"}
}