{
  "type": "Feature",
  "properties": {
    "addr:full":"21010 Arsago Seprio Arsago Seprio Varese 21010",
    "addr:postcode":"21010;21010",
    "iso:country":"IT",
    "sg:address":"21010 Arsago Seprio",
    "sg:city":"Arsago Seprio",
    "sg:classifiers":[
        {
            "category":"Wholesale",
            "subcategory":"Machinery & Supplies",
            "type":"Manufacturing & Wholesale Goods"
        }
    ],
    "sg:phone":"+39 0331 295236",
    "sg:postcode":"21010",
    "sg:province":"Varese",
    "sg:tags":[
        "activities",
        "industrial"
    ],
    "sg:website":"http://www.dialine.it",
    "wof:name":"Dialine Srl",
    "wof:placetype":"venue"
},
  "geometry": {"coordinates":[8.742976,45.685528],"type":"Point"}
}