{
  "type": "Feature",
  "properties": {
    "addr:full":"20143 Milano Milano Milano 20143",
    "addr:postcode":"20143;20143",
    "iso:country":"IT",
    "sg:address":"20143 Milano",
    "sg:city":"Milano",
    "sg:orig_category":"Articoli Per Imballaggio E Confezionamento",
    "sg:phone":"+39 02 8912 4309",
    "sg:postcode":"20143",
    "sg:province":"Milano",
    "wof:name":"L'imballaggio Moderno Sas",
    "wof:placetype":"venue"
},
  "geometry": {"coordinates":[9.156911,45.444118],"type":"Point"}
}