{
  "type": "Feature",
  "properties": {
    "addr:full":"20050 Ronco Briantino Ronco Briantino Milano 20050",
    "addr:postcode":"20050;20050",
    "iso:country":"IT",
    "sg:address":"20050 Ronco Briantino",
    "sg:city":"Ronco Briantino",
    "sg:orig_category":"Servizi Per Aziende, Manifestazioni E Supporto Agli Scambi Commerciali",
    "sg:phone":"+39 039 607 9053",
    "sg:postcode":"20050",
    "sg:province":"Milano",
    "sg:website":"http://www.citi.it",
    "wof:name":"C.i.t.i. Centro Italiano Traduttori Interpreti Snc",
    "wof:placetype":"venue"
},
  "geometry": {"coordinates":[9.404388,45.666119],"type":"Point"}
}