{
  "type": "Feature",
  "properties": {
    "addr:full":"4, Via Pagnina 40027 Mordano Mordano Bologna 40027",
    "addr:postcode":"40027;mordano bologna 40027",
    "addr:street":"Via Pagnina",
    "iso:country":"IT",
    "sg:address":"4, Via Pagnina 40027 Mordano",
    "sg:city":"Mordano",
    "sg:classifiers":[
        {
            "category":"Shopping",
            "subcategory":"Computers & Home Electronics",
            "type":"Retail Goods"
        }
    ],
    "sg:phone":"+39 39054258511",
    "sg:postcode":"40027",
    "sg:province":"Bologna",
    "sg:tags":[
        "electronic",
        "electrical",
        "equipment"
    ],
    "wof:name":"Elettrotecnica Imolese (s.r.l.)",
    "wof:placetype":"venue"
},
  "geometry": {"coordinates":[11.775769,44.416157],"type":"Point"}
}