{
  "type": "Feature",
  "properties": {
    "iso:country":"IT",
    "sg:address":"Via Cingolina 31 35030 Galzignano Terme",
    "sg:city":"Galzignano",
    "sg:classifiers":[
        {
            "category":"Food & Beverages",
            "subcategory":"Fruits & Vegetables",
            "type":"Retail Goods"
        }
    ],
    "sg:phone":"+39 049 913 0136",
    "sg:postcode":"35030",
    "sg:province":"Padova",
    "wof:name":"La Boutique Della Frutta S.n.c. Di Santi Antonio E C.",
    "wof:placetype":"venue"
},
  "geometry": {"coordinates":[11.8765888214,45.4095687866],"type":"Point"}
}