{
  "type": "Feature",
  "properties": {
    "addr:full":"00141 Roma Roma Roma 00141",
    "addr:postcode":"00141;00141",
    "iso:country":"IT",
    "sg:address":"00141 Roma",
    "sg:city":"Roma",
    "sg:orig_category":"Tessuti E Stoffe",
    "sg:phone":"+39 06 886 1556",
    "sg:postcode":"00141",
    "sg:province":"Roma",
    "wof:name":"Moscato David - Non Solo Moda",
    "wof:placetype":"venue"
},
  "geometry": {"coordinates":[12.516823,41.943687],"type":"Point"}
}