{
  "type": "Feature",
  "properties": {
    "iso:country":"IT",
    "sg:address":"62100 Macerata",
    "sg:city":"Macerata",
    "sg:orig_category":"Trasporti E Spedizioni Merci",
    "sg:phone":"+39 0733 233832",
    "sg:postcode":"62100",
    "sg:province":"Macerata",
    "wof:name":"Corriere Simonetti Srl",
    "wof:placetype":"venue"
},
  "geometry": {"coordinates":[13.428059,43.28381],"type":"Point"}
}