{
  "type": "Feature",
  "properties": {
    "addr:full":"40122 Bologna Bologna Bologna 40122",
    "addr:postcode":"40122;40122",
    "iso:country":"IT",
    "sg:address":"40122 Bologna",
    "sg:city":"Bologna",
    "sg:orig_category":"Forniture Per Edilizia E Lavori Pubblici",
    "sg:phone":"+39 051 551309",
    "sg:postcode":"40122",
    "sg:province":"Bologna",
    "sg:website":"http://www.arcostil.it",
    "wof:name":"Arcostil Di Craparotta Antonio",
    "wof:placetype":"venue"
},
  "geometry": {"coordinates":[11.3363771439,44.4987297058],"type":"Point"}
}