{
  "type": "Feature",
  "properties": {
    "iso:country":"IT",
    "sg:address":"12088 Roccaforte Mondovi'",
    "sg:orig_category":"Acque Minerali E Bevande, Naturali E Gassate - Produzione",
    "sg:phone":"+39 0174 683221",
    "sg:postcode":"12088",
    "sg:province":"Cuneo",
    "wof:name":"Lurisia Acqua Minerali Srl",
    "wof:placetype":"venue"
},
  "geometry": {"coordinates":[7.677778,44.320988],"type":"Point"}
}