{
  "type": "Feature",
  "properties": {
    "iso:country":"IT",
    "sg:address":"21012 Cassano Magnago",
    "sg:city":"Cassano Magnago",
    "sg:orig_category":"Filati E Tessuti - Trattamenti",
    "sg:phone":"+39 0331 205212",
    "sg:postcode":"21012",
    "sg:province":"Varese",
    "wof:name":"C.f.m. Srl",
    "wof:placetype":"venue"
},
  "geometry": {"coordinates":[8.8248729706,45.6724128723],"type":"Point"}
}