{
  "type": "Feature",
  "properties": {
    "iso:country":"IT",
    "sg:address":"8/c, Via Danimarca 20093 Cologno Monzese",
    "sg:city":"Cologno Monzese",
    "sg:classifiers":[
        {
            "category":"Utilities",
            "subcategory":"Electric",
            "type":"Services"
        }
    ],
    "sg:phone":"+39 39022543974",
    "sg:postcode":"20093",
    "sg:province":"Milano",
    "sg:tags":[
        "component",
        "electronic"
    ],
    "wof:name":"Gi.pe Elettromeccanica S.a.s. Di Giussani Marialuisa & C.",
    "wof:placetype":"venue"
},
  "geometry": {"coordinates":[9.264175,45.51936],"type":"Point"}
}