{
  "type": "Feature",
  "properties": {
    "addr:full":"00019 Tivoli Tivoli Roma 00019",
    "addr:postcode":"00019;roma 00019",
    "iso:country":"IT",
    "sg:address":"00019 Tivoli",
    "sg:city":"Tivoli",
    "sg:orig_category":"Impiantistica E Prodotti Tecnologici Per Edilizia. Climatizzazione E Condizionamento, Apparecchiature E Servizi",
    "sg:phone":"+39 0774 339761",
    "sg:postcode":"00019",
    "sg:province":"Roma",
    "sg:website":"http://www.efficaceclima.it",
    "wof:name":"Efficace Clima Snc",
    "wof:placetype":"venue"
},
  "geometry": {"coordinates":[12.804905,41.957001],"type":"Point"}
}