{
  "type": "Feature",
  "properties": {
    "iso:country":"IT",
    "sg:address":"71100 Foggia",
    "sg:city":"Foggia",
    "sg:orig_category":"Studi E Consulenze Amministrative, Commerciali E Aziendali. Banche E Servizi Finanziari. Agenzie D'affari E Servizi Commerciali. Consulenze Tecniche, Amministrative E Perizie",
    "sg:phone":"+39 0881 707309",
    "sg:postcode":"71100",
    "sg:province":"Foggia",
    "wof:name":"European Consulting",
    "wof:placetype":"venue"
},
  "geometry": {"coordinates":[16.088297,41.358295],"type":"Point"}
}