{
  "type": "Feature",
  "properties": {
    "iso:country":"IT",
    "sg:address":"37060 Sorga'",
    "sg:orig_category":"Forniture Per Agricoltura E Zootecnia",
    "sg:phone":"+39 045 732 5025",
    "sg:postcode":"37060",
    "sg:province":"Verona",
    "wof:name":"Pavenzoo (s.n.c.)",
    "wof:placetype":"venue"
},
  "geometry": {"coordinates":[10.9765720367,45.2243232727],"type":"Point"}
}