{
  "type": "Feature",
  "properties": {
    "iso:country":"IT",
    "sg:address":"04016 Sabaudia",
    "sg:city":"Sabaudia",
    "sg:classifiers":[
        {
            "category":"Retail",
            "subcategory":"Auto Repair",
            "type":"Services"
        }
    ],
    "sg:phone":"+39 0773 517477",
    "sg:postcode":"04016",
    "sg:province":"Latina",
    "sg:tags":[
        "articles",
        "product",
        "components",
        "industry",
        "vehicles",
        "rubber",
        "part",
        "spare",
        "motor",
        "works"
    ],
    "wof:name":"La Navaltirrena Srl",
    "wof:placetype":"venue"
},
  "geometry": {"coordinates":[12.982752,41.364979],"type":"Point"}
}