{
  "type": "Feature",
  "properties": {
    "iso:country":"IT",
    "sg:address":"52, Via De Zan 33081 Aviano",
    "sg:city":"Aviano",
    "sg:classifiers":[
        {
            "category":"Manufacturing",
            "subcategory":"Metals",
            "type":"Manufacturing & Wholesale Goods"
        }
    ],
    "sg:phone":"+39 0434 652545",
    "sg:postcode":"33081",
    "sg:province":"Pordenone",
    "sg:tags":[
        "processing"
    ],
    "wof:name":"Euro Tools S.r.l.",
    "wof:placetype":"venue"
},
  "geometry": {"coordinates":[12.6074542999,46.065071106],"type":"Point"}
}