{
  "type": "Feature",
  "properties": {
    "iso:country":"IT",
    "sg:address":"20010 San Pietro All'olmo",
    "sg:orig_category":"Dolciumi E Gelati",
    "sg:phone":"+39 02 9356 9774",
    "sg:postcode":"20010",
    "sg:province":"Milano",
    "wof:name":"Vanzulli Ernesto",
    "wof:placetype":"venue"
},
  "geometry": {"coordinates":[9.011767,45.485573],"type":"Point"}
}