{
  "type": "Feature",
  "properties": {
    "iso:country":"IT",
    "sg:address":"65122 Pescara",
    "sg:city":"Pescara",
    "sg:classifiers":[
        {
            "category":"Health Services",
            "subcategory":"Health Practitioner",
            "type":"Services"
        }
    ],
    "sg:phone":"+39 085 421 6710",
    "sg:postcode":"65122",
    "sg:province":"Pescara",
    "sg:tags":[
        "medici"
    ],
    "sg:website":"http://www.nianet.it",
    "wof:name":"Studio Medico Ledda Bottari",
    "wof:placetype":"venue"
},
  "geometry": {"coordinates":[14.2090749741,42.4719009399],"type":"Point"}
}