{
  "type": "Feature",
  "properties": {
    "addr:full":"21, Via Lugagnano 37066 Sommacampagna Sommacampagna Verona 37066",
    "addr:postcode":"37066;37066",
    "addr:street":"Via Lugagnano",
    "iso:country":"IT",
    "sg:address":"21, Via Lugagnano 37066 Sommacampagna",
    "sg:city":"Sommacampagna",
    "sg:classifiers":[
        {
            "category":"Shopping",
            "subcategory":"Stationery & Office Supplies",
            "type":"Retail Goods"
        }
    ],
    "sg:phone":"+39 045 858 1189",
    "sg:postcode":"37066",
    "sg:province":"Verona",
    "sg:tags":[
        "professional"
    ],
    "wof:name":"Arredamenti F.lli Cona (s.n.c.)",
    "wof:placetype":"venue"
},
  "geometry": {"coordinates":[10.9382238388,45.4388694763],"type":"Point"}
}