{
  "type": "Feature",
  "properties": {
    "addr:full":"83, Via Margutta 00187 Roma Roma Roma 00187",
    "addr:postcode":"00187;00187",
    "addr:street":"Via Margutta",
    "iso:country":"IT",
    "sg:address":"83, Via Margutta 00187 Roma",
    "sg:city":"Roma",
    "sg:classifiers":[
        {
            "category":"Shopping",
            "subcategory":"Stationery & Office Supplies",
            "type":"Retail Goods"
        }
    ],
    "sg:phone":"+39 06 3600 1924",
    "sg:postcode":"00187",
    "sg:province":"Roma",
    "sg:tags":[
        "professional"
    ],
    "wof:name":"Expo Studio S.r.l.",
    "wof:placetype":"venue"
},
  "geometry": {"coordinates":[12.4798927307,41.9082717896],"type":"Point"}
}