{
  "type": "Feature",
  "properties": {
    "addr:full":"Via Zona Industriale 5d 10090 Trana Trana Torino 10090",
    "addr:housenumber":"5d",
    "addr:postcode":"10090;10090",
    "addr:street":"Via Zona Industriale",
    "iso:country":"IT",
    "sg:address":"Via Zona Industriale 5d 10090 Trana",
    "sg:city":"Trana",
    "sg:classifiers":[
        {
            "category":"Wholesale",
            "subcategory":"Chemicals & Plastics",
            "type":"Manufacturing & Wholesale Goods"
        }
    ],
    "sg:phone":"+39 011 933 8371",
    "sg:postcode":"10090",
    "sg:province":"Torino",
    "sg:tags":[
        "acrylic",
        "mirror"
    ],
    "wof:name":"S.a.i. Specchi Acrilici Italia Spa",
    "wof:placetype":"venue"
},
  "geometry": {"coordinates":[7.686619,45.07056],"type":"Point"}
}