{
  "type": "Feature",
  "properties": {
    "iso:country":"IT",
    "sg:address":"38010 Nave San Rocco",
    "sg:city":"Nave San Rocco",
    "sg:orig_category":"Macchine Ed Impianti Per Edilizia E Lavori Pubblici. Impianti E Attrezzature Per Lo Sport E Il Tempo Libero",
    "sg:phone":"+39 0461 870333",
    "sg:postcode":"38010",
    "sg:province":"Trento",
    "wof:name":"Dallapiccola Vulcan Luciana",
    "wof:placetype":"venue"
},
  "geometry": {"coordinates":[11.105777,46.165676],"type":"Point"}
}