{
  "type": "Feature",
  "properties": {
    "addr:full":"P. Mameli 5, 17100 Savona Savona Savona 17100",
    "addr:housenumber":"5",
    "addr:postcode":"17100;17100",
    "addr:street":"P. Mameli",
    "iso:country":"IT",
    "sg:address":"P. Mameli 5, 17100 Savona",
    "sg:city":"Savona",
    "sg:classifiers":[
        {
            "category":"Banks & Credit Unions",
            "subcategory":"Financial Services",
            "type":"Services"
        }
    ],
    "sg:phone":"+39 39019812252",
    "sg:postcode":"17100",
    "sg:province":"Savona",
    "sg:tags":[
        "banking",
        "finance",
        "insurance"
    ],
    "wof:name":"Ligure Leasing Spa",
    "wof:placetype":"venue"
},
  "geometry": {"coordinates":[8.4772462845,44.3110694885],"type":"Point"}
}