{
  "type": "Feature",
  "properties": {
    "addr:full":"10040 Lein\u00ec Torino 10040",
    "addr:postcode":"10040;10040",
    "iso:country":"IT",
    "sg:address":"10040 Lein\u00ec",
    "sg:orig_category":"Apparecchiature Oleodinamiche",
    "sg:phone":"+39 011 998 3119",
    "sg:postcode":"10040",
    "sg:province":"Torino",
    "wof:name":"Tech-in-sider Srl",
    "wof:placetype":"venue"
},
  "geometry": {"coordinates":[7.765614,45.133144],"type":"Point"}
}