{
  "type": "Feature",
  "properties": {
    "iso:country":"IT",
    "sg:address":"Via Tartaglia 11 70033 Corato",
    "sg:city":"Corato",
    "sg:orig_category":"Nightwear, Pyjamas, Nightgowns",
    "sg:phone":"+39 080 898 4602",
    "sg:postcode":"70033",
    "sg:province":"Bari",
    "sg:website":"www.nuovagood.it",
    "wof:name":"Nuova Good S.r.l.",
    "wof:placetype":"venue"
},
  "geometry": {"coordinates":[16.419186,41.152359],"type":"Point"}
}