{
  "type": "Feature",
  "properties": {
    "iso:country":"IT",
    "sg:address":"20128 Milano",
    "sg:city":"Milano",
    "sg:orig_category":"Termotecnica E Riscaldamento, Apparecchiature E Servizi",
    "sg:phone":"+39 02 257 1776",
    "sg:postcode":"20128",
    "sg:province":"Milano",
    "wof:name":"Cordara Srl",
    "wof:placetype":"venue"
},
  "geometry": {"coordinates":[9.230169,45.505947],"type":"Point"}
}