{
  "type": "Feature",
  "properties": {
    "iso:country":"IT",
    "sg:address":"16129 Genova",
    "sg:city":"Genova",
    "sg:orig_category":"Banche E Servizi Finanziari",
    "sg:phone":"+39 010 570 1203",
    "sg:postcode":"16129",
    "sg:province":"Genova",
    "wof:name":"Play-s.a.s. Di L.matteoni",
    "wof:placetype":"venue"
},
  "geometry": {"coordinates":[8.945777,44.398617],"type":"Point"}
}