{
  "type": "Feature",
  "properties": {
    "iso:country":"IT",
    "sg:address":"21047 Saronno",
    "sg:city":"Saronno",
    "sg:orig_category":"Termotecnica E Riscaldamento, Apparecchiature E Servizi",
    "sg:phone":"+39 02 962 8831",
    "sg:postcode":"21047",
    "sg:province":"Varese",
    "wof:name":"Viterra Energy Servicves Srl",
    "wof:placetype":"venue"
},
  "geometry": {"coordinates":[9.023209,45.630737],"type":"Point"}
}