{
  "type": "Feature",
  "properties": {
    "addr:full":"14, Via Matteo Fabbian 31030 Borso Del Grappa Borso del Grappa Treviso 31030",
    "addr:postcode":"31030;31030",
    "addr:street":"Via Matteo Fabbian",
    "iso:country":"IT",
    "sg:address":"14, Via Matteo Fabbian 31030 Borso Del Grappa",
    "sg:city":"Borso del Grappa",
    "sg:classifiers":[
        {
            "category":"Manufacturing",
            "subcategory":"Metals",
            "type":"Manufacturing & Wholesale Goods"
        }
    ],
    "sg:phone":"+39 0423 910088",
    "sg:postcode":"31030",
    "sg:province":"Treviso",
    "sg:tags":[
        "metallurgy",
        "metalworking"
    ],
    "wof:name":"Mb (s.r.l.)",
    "wof:placetype":"venue"
},
  "geometry": {"coordinates":[11.8023338318,45.8169708252],"type":"Point"}
}