{
  "type": "Feature",
  "properties": {
    "iso:country":"IT",
    "sg:address":"59100 Prato",
    "sg:city":"Prato",
    "sg:orig_category":"Servizi E Lavori Per Abbigliamento E Pelletterie",
    "sg:phone":"+39 0574 62571",
    "sg:postcode":"59100",
    "sg:province":"Prato",
    "wof:name":"Fenice Spa",
    "wof:placetype":"venue"
},
  "geometry": {"coordinates":[11.06354,43.8578],"type":"Point"}
}