{
  "type": "Feature",
  "properties": {
    "iso:country":"IT",
    "sg:address":"06012 Citta'dicastello",
    "sg:orig_category":"Cartotecnica E Servizi",
    "sg:phone":"+39 075 857 7027",
    "sg:postcode":"06012",
    "sg:province":"Perugia",
    "wof:name":"Deko Italia Sas",
    "wof:placetype":"venue"
},
  "geometry": {"coordinates":[12.359038,43.094009],"type":"Point"}
}