{
  "type": "Feature",
  "properties": {
    "addr:full":"1, Via Dossi Carlo 27100 Pavia Pavia Pavia 27100",
    "addr:postcode":"27100;27100",
    "addr:street":"Via Dossi Carlo",
    "iso:country":"IT",
    "sg:address":"1, Via Dossi Carlo 27100 Pavia",
    "sg:city":"Pavia",
    "sg:classifiers":[
        {
            "category":"Food & Beverages",
            "subcategory":"Groceries & Convenience Stores",
            "type":"Retail Goods"
        }
    ],
    "sg:phone":"+39 0382 575353",
    "sg:postcode":"27100",
    "sg:province":"Pavia",
    "sg:tags":[
        "product",
        "related"
    ],
    "wof:name":"Brocchetta Riccardo S.r.l.",
    "wof:placetype":"venue"
},
  "geometry": {"coordinates":[9.1565628052,45.1858863831],"type":"Point"}
}