{
  "type": "Feature",
  "properties": {
    "iso:country":"IT",
    "sg:address":"00165 Roma",
    "sg:city":"Roma",
    "sg:classifiers":[
        {
            "category":"Travel",
            "subcategory":"Hotels & Motels",
            "type":"Entertainment"
        }
    ],
    "sg:phone":"+39 06 3973 1610",
    "sg:postcode":"00165",
    "sg:province":"Roma",
    "sg:tags":[
        "hotels",
        "facility"
    ],
    "wof:name":"Anna Maria Pascucci",
    "wof:placetype":"venue"
},
  "geometry": {"coordinates":[12.453641,41.900166],"type":"Point"}
}