{
  "type": "Feature",
  "properties": {
    "addr:full":"24126 Bergamo Bergamo Bergamo 24126",
    "addr:postcode":"24126;24126",
    "iso:country":"IT",
    "sg:address":"24126 Bergamo",
    "sg:city":"Bergamo",
    "sg:orig_category":"Legno E Semilavorati. Macchine E Forniture Per Arredamento E Industria Del Legno. Hobbistica",
    "sg:phone":"+39 035 318488",
    "sg:postcode":"24126",
    "sg:province":"Bergamo",
    "wof:name":"Colorificio Ferraris Srl",
    "wof:placetype":"venue"
},
  "geometry": {"coordinates":[9.672618,45.678257],"type":"Point"}
}