{
  "type": "Feature",
  "properties": {
    "addr:full":"20060 Pozzuolo Martesana Pozzuolo Martesana Milano 20060",
    "addr:postcode":"20060;20060",
    "iso:country":"IT",
    "sg:address":"20060 Pozzuolo Martesana",
    "sg:city":"Pozzuolo Martesana",
    "sg:orig_category":"Materiali Edili",
    "sg:phone":"+39 02 9535 9063",
    "sg:postcode":"20060",
    "sg:province":"Milano",
    "wof:name":"Cave R.p.r. (s.p.a.)",
    "wof:placetype":"venue"
},
  "geometry": {"coordinates":[9.458786,45.50111],"type":"Point"}
}