{
  "type": "Feature",
  "properties": {
    "iso:country":"IT",
    "sg:address":"Via Papa Giovanni Xxiii 96 13882 Cerrione",
    "sg:city":"Cerrione",
    "sg:classifiers":[
        {
            "category":"Shopping",
            "subcategory":"Clothing, Apparel, & Fashions",
            "type":"Retail Goods"
        }
    ],
    "sg:phone":"+39 015 258 3653",
    "sg:postcode":"13882",
    "sg:province":"Biella",
    "sg:tags":[
        "children's",
        "clothing"
    ],
    "sg:website":"www.lenouveau-ne.it",
    "wof:name":"River S.r.l",
    "wof:placetype":"venue"
},
  "geometry": {"coordinates":[8.089682,45.486362],"type":"Point"}
}