{
  "type": "Feature",
  "properties": {
    "addr:full":"76, Via Emilio Lussu 09038 Serramanna Serramanna Medio Campidano 09038",
    "addr:postcode":"09038;09038",
    "addr:street":"Via Emilio Lussu",
    "iso:country":"IT",
    "sg:address":"76, Via Emilio Lussu 09038 Serramanna",
    "sg:city":"Serramanna",
    "sg:classifiers":[
        {
            "category":"Shopping",
            "subcategory":"Clothing, Apparel, & Fashions",
            "type":"Retail Goods"
        }
    ],
    "sg:phone":"+39 070 913 9081",
    "sg:postcode":"09038",
    "sg:province":"Medio Campidano",
    "sg:tags":[
        "clothes"
    ],
    "wof:name":"Gruppo F.lli Collu S.r.l",
    "wof:placetype":"venue"
},
  "geometry": {"coordinates":[8.941146,39.377815],"type":"Point"}
}