{
  "type": "Feature",
  "properties": {
    "iso:country":"IT",
    "sg:address":"30015 Chioggia",
    "sg:city":"Chioggia",
    "sg:orig_category":"Zootecnia E Pesca, Allevamento Piccoli Animali",
    "sg:phone":"+39 041 550 7576",
    "sg:postcode":"30015",
    "sg:province":"Venezia",
    "wof:name":"Cooperativa Lagunare Allevatori Molluschi C.l.a.m. S.r.l.",
    "wof:placetype":"venue"
},
  "geometry": {"coordinates":[12.227665,45.227699],"type":"Point"}
}