{
  "type": "Feature",
  "properties": {
    "addr:full":"2, Cascina Canova 26867 Somaglia Somaglia Lodi 26867",
    "addr:housenumber":"2",
    "addr:postcode":"26867;26867",
    "addr:street":"Cascina Canova",
    "iso:country":"IT",
    "sg:address":"2, Cascina Canova 26867 Somaglia",
    "sg:city":"Somaglia",
    "sg:classifiers":[
        {
            "category":"Autos & Motor Vehicles",
            "subcategory":"Automobile Sales",
            "type":"Retail Goods"
        }
    ],
    "sg:phone":"+39 39037751379",
    "sg:postcode":"26867",
    "sg:province":"Lodi",
    "sg:tags":[
        "motor-cars"
    ],
    "wof:name":"T.m.l. Di Maurizio Goberti",
    "wof:placetype":"venue"
},
  "geometry": {"coordinates":[9.4978504181,45.312877655],"type":"Point"}
}