{
  "type": "Feature",
  "properties": {
    "iso:country":"IT",
    "sg:address":"10152 Torino",
    "sg:city":"Torino",
    "sg:orig_category":"Apparecchiature Ed Attrezzature Meccaniche",
    "sg:phone":"+39 011 248 1531",
    "sg:postcode":"10152",
    "sg:province":"Torino",
    "wof:name":"Gal - Flex",
    "wof:placetype":"venue"
},
  "geometry": {"coordinates":[7.691844,45.086136],"type":"Point"}
}