{
  "type": "Feature",
  "properties": {
    "addr:full":"87036 Rende Rende Cosenza 87036",
    "addr:postcode":"87036;87036",
    "iso:country":"IT",
    "sg:address":"87036 Rende",
    "sg:city":"Rende",
    "sg:orig_category":"Arredamenti Ed Architettura D'interni",
    "sg:phone":"+39 0984 408476",
    "sg:postcode":"87036",
    "sg:province":"Cosenza",
    "wof:name":"Glassart Srl",
    "wof:placetype":"venue"
},
  "geometry": {"coordinates":[16.238113,39.323486],"type":"Point"}
}