{
  "type": "Feature",
  "properties": {
    "addr:full":"41053 Maranello Maranello Modena 41053",
    "addr:postcode":"41053;41053",
    "iso:country":"IT",
    "sg:address":"41053 Maranello",
    "sg:city":"Maranello",
    "sg:orig_category":"Calzature, Pelletterie E Pelli",
    "sg:phone":"+39 0536 948938",
    "sg:postcode":"41053",
    "sg:province":"Modena",
    "wof:name":"Ipam Di Avoni Paolo E C. S.n.c.",
    "wof:placetype":"venue"
},
  "geometry": {"coordinates":[10.892617,44.525574],"type":"Point"}
}