{
  "type": "Feature",
  "properties": {
    "iso:country":"IT",
    "sg:address":"24010 Sorisole",
    "sg:city":"Sorisole",
    "sg:orig_category":"Arredi Ed Attrezzature Per Uffici",
    "sg:phone":"+39 035 572633",
    "sg:postcode":"24010",
    "sg:province":"Bergamo",
    "wof:name":"Vin Service",
    "wof:placetype":"venue"
},
  "geometry": {"coordinates":[9.642852,45.735214],"type":"Point"}
}