{
  "type": "Feature",
  "properties": {
    "iso:country":"IT",
    "sg:address":"59016 Poggio A Caiano",
    "sg:city":"Poggio a Caiano",
    "sg:orig_category":"Cappelli Signora",
    "sg:phone":"+39 055 879 9143",
    "sg:postcode":"59016",
    "sg:province":"Prato",
    "wof:name":"Il Granaio",
    "wof:placetype":"venue"
},
  "geometry": {"coordinates":[11.046133,43.813545],"type":"Point"}
}