{
  "type": "Feature",
  "properties": {
    "addr:full":"Via Olmo 250 30030 Martellago Martellago Venezia 30030",
    "addr:housenumber":"250",
    "addr:postcode":"30030;30030",
    "addr:street":"Via Olmo",
    "iso:country":"IT",
    "sg:address":"Via Olmo 250 30030 Martellago",
    "sg:city":"Martellago",
    "sg:classifiers":[
        {
            "category":"Government",
            "subcategory":"Post Office",
            "type":"Public Place"
        }
    ],
    "sg:phone":"+39 041 907500",
    "sg:postcode":"30030",
    "sg:province":"Venezia",
    "sg:tags":[
        "thermoformed",
        "parts",
        "plastic"
    ],
    "wof:name":"Tecnopack Impresa Individuale",
    "wof:placetype":"venue"
},
  "geometry": {"coordinates":[12.1821155548,45.5186271667],"type":"Point"}
}