{
  "type": "Feature",
  "properties": {
    "iso:country":"IT",
    "sg:address":"25046 Cazzago San Martino",
    "sg:city":"Cazzago San Martino",
    "sg:orig_category":"Lavorazioni Metalli, Stampaggio E Saldatura",
    "sg:phone":"+39 030 725 4087",
    "sg:postcode":"25046",
    "sg:province":"Brescia",
    "sg:website":"http://www.polimedia.it/belleri",
    "wof:name":"Belleri Luigi & C. Snc",
    "wof:placetype":"venue"
},
  "geometry": {"coordinates":[10.033444,45.572075],"type":"Point"}
}