{
  "type": "Feature",
  "properties": {
    "addr:full":"1, Strada St. 115 92014 Porto Empedocle Porto Empedocle Agrigento 92014",
    "addr:housenumber":"115",
    "addr:postcode":"92014;92014",
    "addr:street":"Strada St.",
    "iso:country":"IT",
    "sg:address":"1, Strada St. 115 92014 Porto Empedocle",
    "sg:city":"Porto Empedocle",
    "sg:classifiers":[
        {
            "category":"Shopping",
            "subcategory":"Stationery & Office Supplies",
            "type":"Retail Goods"
        }
    ],
    "sg:phone":"+39 0922 635696",
    "sg:postcode":"92014",
    "sg:province":"Agrigento",
    "sg:tags":[
        "professional"
    ],
    "wof:name":"Spazio Car Srl",
    "wof:placetype":"venue"
},
  "geometry": {"coordinates":[13.5769557953,37.3111877441],"type":"Point"}
}