{
  "type": "Feature",
  "properties": {
    "addr:full":"50050 Gambassi Terme Badia a cerreto Firenze 50050",
    "addr:postcode":"50050;50050",
    "addr:street":"A",
    "iso:country":"IT",
    "sg:address":"50050 Gambassi Terme",
    "sg:city":"Badia a cerreto",
    "sg:orig_category":"Prodotti E Manufatti In Materie Plastiche. Articoli Per Imballaggio E Confezionamento",
    "sg:phone":"+39 0571 65051",
    "sg:postcode":"50050",
    "sg:province":"Firenze",
    "wof:name":"Termoplast Srl",
    "wof:placetype":"venue"
},
  "geometry": {"coordinates":[11.0259447098,43.5459632874],"type":"Point"}
}