{
  "type": "Feature",
  "properties": {
    "addr:full":"Via Nuova Circonvallazione 27035 Mede Mede Pavia 27035",
    "addr:postcode":"27035;27035",
    "addr:street":"Via Nuova Circonvallazione;Mede",
    "iso:country":"IT",
    "sg:address":"Via Nuova Circonvallazione 27035 Mede",
    "sg:city":"Mede",
    "sg:classifiers":[
        {
            "category":"Retail",
            "subcategory":"Animal Services",
            "type":"Services"
        }
    ],
    "sg:phone":"+39 0384 820493",
    "sg:postcode":"27035",
    "sg:province":"Pavia",
    "sg:tags":[
        "breeding"
    ],
    "wof:name":"Nuova Fitochimica (s.r.l.)",
    "wof:placetype":"venue"
},
  "geometry": {"coordinates":[9.156563,45.185886],"type":"Point"}
}