{
  "type": "Feature",
  "properties": {
    "iso:country":"IT",
    "sg:address":"17, Cd. S. Marco 66026 Ortona",
    "sg:city":"Ortona",
    "sg:classifiers":[
        {
            "category":"Parking",
            "subcategory":"Lot",
            "type":"Transportation"
        }
    ],
    "sg:phone":"+39 085 919 6288",
    "sg:postcode":"66026",
    "sg:province":"Chieti",
    "sg:tags":[
        "transport",
        "road"
    ],
    "wof:name":"Autotrasporti Di Sipio S.r.l.",
    "wof:placetype":"venue"
},
  "geometry": {"coordinates":[14.167151,42.351791],"type":"Point"}
}