{
  "type": "Feature",
  "properties": {
    "iso:country":"IT",
    "sg:address":"74, Via Asmara 00199 Roma",
    "sg:city":"Roma",
    "sg:classifiers":[
        {
            "category":"Travel",
            "subcategory":"Travel Agent",
            "type":"Entertainment"
        }
    ],
    "sg:phone":"+39 39068610062",
    "sg:postcode":"00199",
    "sg:province":"Roma",
    "sg:tags":[
        "business"
    ],
    "wof:name":"Lo Scacciapensieri (s.n.c.)",
    "wof:placetype":"venue"
},
  "geometry": {"coordinates":[12.516692,41.925297],"type":"Point"}
}