{
  "type": "Feature",
  "properties": {
    "addr:full":"11100 Aosta Aosta Aosta 11100",
    "addr:postcode":"11100;11100",
    "iso:country":"IT",
    "sg:address":"11100 Aosta",
    "sg:city":"Aosta",
    "sg:orig_category":"Termotecnica E Riscaldamento, Apparecchiature E Servizi",
    "sg:phone":"+39 0165 238112",
    "sg:postcode":"11100",
    "sg:province":"Aosta",
    "wof:name":"Gastaldi Diego",
    "wof:placetype":"venue"
},
  "geometry": {"coordinates":[7.314676,45.733025],"type":"Point"}
}