{
  "type": "Feature",
  "properties": {
    "iso:country":"IT",
    "sg:address":"20091 Bresso",
    "sg:city":"Bresso",
    "sg:orig_category":"Musica",
    "sg:phone":"+39 02 6650 3595",
    "sg:postcode":"20091",
    "sg:province":"Milano",
    "wof:name":"Geo - Media Srl",
    "wof:placetype":"venue"
},
  "geometry": {"coordinates":[9.1962051392,45.529914856],"type":"Point"}
}