{
  "type": "Feature",
  "properties": {
    "iso:country":"IT",
    "sg:address":"24020 Gorle",
    "sg:city":"Gorle",
    "sg:orig_category":"Servizi E Lavori Per Abbigliamento E Pelletterie",
    "sg:phone":"+39 035 301678",
    "sg:postcode":"24020",
    "sg:province":"Bergamo",
    "wof:name":"Modastir",
    "wof:placetype":"venue"
},
  "geometry": {"coordinates":[9.680186,45.715767],"type":"Point"}
}