{
  "type": "Feature",
  "properties": {
    "iso:country":"IT",
    "sg:address":"27, V. Filettite 84016 Pagani",
    "sg:city":"Pagani",
    "sg:classifiers":[
        {
            "category":"Wholesale",
            "subcategory":"Drugs",
            "type":"Manufacturing & Wholesale Goods"
        }
    ],
    "sg:phone":"+39 39081915500",
    "sg:postcode":"84016",
    "sg:province":"Salerno",
    "sg:tags":[
        "chemical",
        "pharmaceutical"
    ],
    "sg:website":"http://www.dinagas.it",
    "wof:name":"Dinagas Srl",
    "wof:placetype":"venue"
},
  "geometry": {"coordinates":[14.765912,40.677956],"type":"Point"}
}