{
  "type": "Feature",
  "properties": {
    "iso:country":"IT",
    "sg:address":"70025 Grumo Appula",
    "sg:city":"Grumo Appula",
    "sg:orig_category":"Prodotti Alimentari",
    "sg:phone":"+39 080 783 5723",
    "sg:postcode":"70025",
    "sg:province":"Bari",
    "wof:name":"Apulia Mandorle Srl",
    "wof:placetype":"venue"
},
  "geometry": {"coordinates":[16.7012042999,41.0104789734],"type":"Point"}
}