{
  "type": "Feature",
  "properties": {
    "addr:full":"9, Via Don Giuseppe Fogale 31036 Istrana Istrana Treviso 31036",
    "addr:postcode":"31036;31036",
    "addr:street":"Via Don Giuseppe Fogale",
    "iso:country":"IT",
    "sg:address":"9, Via Don Giuseppe Fogale 31036 Istrana",
    "sg:city":"Istrana",
    "sg:classifiers":[
        {
            "category":"Banks & Credit Unions",
            "subcategory":"Bank",
            "type":"Services"
        }
    ],
    "sg:phone":"+39 390 422 8314",
    "sg:postcode":"31036",
    "sg:province":"Treviso",
    "sg:tags":[
        "banking",
        "institution"
    ],
    "wof:name":"Cassa Rurale Ed Artigiana Di Treviso",
    "wof:placetype":"venue"
},
  "geometry": {"coordinates":[12.095658,45.663002],"type":"Point"}
}