{
  "type": "Feature",
  "properties": {
    "iso:country":"IT",
    "sg:address":"Via Reiss Romoli Guglielmo 122/4 10148 Torino",
    "sg:city":"Torino",
    "sg:classifiers":[
        {
            "category":"Wholesale",
            "subcategory":"Vending Machines",
            "type":"Manufacturing & Wholesale Goods"
        }
    ],
    "sg:phone":"+39 011 220 2660",
    "sg:postcode":"10148",
    "sg:province":"Torino",
    "sg:tags":[
        "hot-melt",
        "marking"
    ],
    "sg:website":"www.erotech.it",
    "wof:name":"Erotech Srl",
    "wof:placetype":"venue"
},
  "geometry": {"coordinates":[7.686619,45.07056],"type":"Point"}
}