{
  "type": "Feature",
  "properties": {
    "iso:country":"IT",
    "sg:address":"40057 Granarolo Dell'emilia",
    "sg:orig_category":"Elettrotecnica Professionale E Di Consumo. Forniture Alle Strutture Ricettive. Arredi Ed Attrezzature Per Attivita' Commerciali Ed Artigianali",
    "sg:phone":"+39 051 766131",
    "sg:postcode":"40057",
    "sg:province":"Bologna",
    "wof:name":"Paredes Italia Srl",
    "wof:placetype":"venue"
},
  "geometry": {"coordinates":[11.431458,44.566097],"type":"Point"}
}