{
  "type": "Feature",
  "properties": {
    "addr:full":"62012 Civitanova Marche Civitanova Marche Macerata 62012",
    "addr:postcode":"62012;62012",
    "iso:country":"IT",
    "sg:address":"62012 Civitanova Marche",
    "sg:city":"Civitanova Marche",
    "sg:orig_category":"Amianto - Bonifica E Smantellamento",
    "sg:phone":"+39 0733 811448",
    "sg:postcode":"62012",
    "sg:province":"Macerata",
    "sg:website":"http://www.testella.it",
    "wof:name":"Testella Sas",
    "wof:placetype":"venue"
},
  "geometry": {"coordinates":[13.722043,43.302849],"type":"Point"}
}