{
  "type": "Feature",
  "properties": {
    "iso:country":"IT",
    "sg:address":"00186 Roma",
    "sg:city":"Roma",
    "sg:orig_category":"Arte Ed Artigianato Artistico. Scuole E Servizi Scolastici. Servizi Ausiliari Di Analisi, Controllo E Ricerca",
    "sg:phone":"+39 06 6880 8555",
    "sg:postcode":"00186",
    "sg:province":"Roma",
    "wof:name":"Accademia Nazionale Sartori",
    "wof:placetype":"venue"
},
  "geometry": {"coordinates":[12.475321,41.896603],"type":"Point"}
}