{
  "type": "Feature",
  "properties": {
    "iso:country":"IT",
    "sg:address":"00181 Roma",
    "sg:city":"Roma",
    "sg:orig_category":"Cinematografia E Radiotelevisione",
    "sg:postcode":"00181",
    "sg:province":"Roma",
    "wof:name":"Studio Cine (s.r.l)",
    "wof:placetype":"venue"
},
  "geometry": {"coordinates":[12.52955,41.876755],"type":"Point"}
}