{
  "type": "Feature",
  "properties": {
    "addr:full":"65015 Montesilvano Montesilvano Pescara 65015",
    "addr:postcode":"65015;65015",
    "iso:country":"IT",
    "sg:address":"65015 Montesilvano",
    "sg:city":"Montesilvano",
    "sg:orig_category":"Ottica, Lenti A Contatto Ed Occhiali - Vendita Al Dettaglio",
    "sg:phone":"+39 085 445 2308",
    "sg:postcode":"65015",
    "sg:province":"Pescara",
    "sg:website":"http://www.otticadipietro.com",
    "wof:name":"Ottica Di Pietro",
    "wof:placetype":"venue"
},
  "geometry": {"coordinates":[14.1543588638,42.5128555298],"type":"Point"}
}