{
  "type": "Feature",
  "properties": {
    "addr:full":"Via U. La Malfa, 38/40 20066 Melzo Melzo Milano 20066",
    "addr:housenumber":"38 / 40",
    "addr:postcode":"20066;20066",
    "addr:street":"Via U. La Malfa",
    "iso:country":"IT",
    "sg:address":"Via U. La Malfa, 38/40 20066 Melzo",
    "sg:city":"Melzo",
    "sg:classifiers":[
        {
            "category":"Manufacturing",
            "subcategory":"Glass & Minerals",
            "type":"Manufacturing & Wholesale Goods"
        }
    ],
    "sg:phone":"+39 02 955 1383",
    "sg:postcode":"20066",
    "sg:province":"Milano",
    "sg:tags":[
        "machine"
    ],
    "wof:name":"Alfema S.n.c.",
    "wof:placetype":"venue"
},
  "geometry": {"coordinates":[9.188141,45.463688],"type":"Point"}
}