{
  "type": "Feature",
  "properties": {
    "iso:country":"IT",
    "sg:address":"00187 Roma",
    "sg:city":"Roma",
    "sg:orig_category":"Hobbistica",
    "sg:phone":"+39 06 487 1458",
    "sg:postcode":"00187",
    "sg:province":"Roma",
    "wof:name":"Il Fiorino Srl",
    "wof:placetype":"venue"
},
  "geometry": {"coordinates":[12.372405,42.131073],"type":"Point"}
}