{
  "type": "Feature",
  "properties": {
    "addr:full":"37121 Verona Verona Verona 37121",
    "addr:postcode":"37121;37121",
    "iso:country":"IT",
    "sg:address":"37121 Verona",
    "sg:city":"Verona",
    "sg:classifiers":[
        {
            "category":"Shopping",
            "subcategory":"Clothing, Apparel, & Fashions",
            "type":"Retail Goods"
        }
    ],
    "sg:phone":"+39 045 800 0311",
    "sg:postcode":"37121",
    "sg:province":"Verona",
    "sg:tags":[
        "activities",
        "goods",
        "supply",
        "leather",
        "commercial",
        "artisan",
        "supplies",
        "clothing"
    ],
    "wof:name":"Cappelletti Di Falziroli Monica",
    "wof:placetype":"venue"
},
  "geometry": {"coordinates":[10.996259,45.441048],"type":"Point"}
}