{
  "type": "Feature",
  "properties": {
    "addr:full":"Ctr Santa Rosa Galina 72023 Mesagne Mesagne Brindisi 72023",
    "addr:postcode":"72023;72023",
    "iso:country":"IT",
    "sg:address":"Ctr Santa Rosa Galina 72023 Mesagne",
    "sg:city":"Mesagne",
    "sg:classifiers":[
        {
            "category":"Food & Beverages",
            "subcategory":"Fruits & Vegetables",
            "type":"Retail Goods"
        }
    ],
    "sg:phone":"+39 0831 775611",
    "sg:postcode":"72023",
    "sg:province":"Brindisi",
    "sg:website":"www.ruggierogroup.it",
    "wof:name":"F.lli Ruggiero Di Antonio Ruggiero E C. S.n.c.",
    "wof:placetype":"venue"
},
  "geometry": {"coordinates":[17.7873096466,40.5484085083],"type":"Point"}
}