{
  "type": "Feature",
  "properties": {
    "iso:country":"IT",
    "sg:address":"28100 Novara",
    "sg:city":"Novara",
    "sg:orig_category":"Centri Di Estetica E Cosmesi E Servizi",
    "sg:phone":"+39 0321 640049",
    "sg:postcode":"28100",
    "sg:province":"Novara",
    "wof:name":"Gavassa Giancarlo",
    "wof:placetype":"venue"
},
  "geometry": {"coordinates":[8.61802,45.451862],"type":"Point"}
}