{
  "type": "Feature",
  "properties": {
    "addr:full":"Km. 1.800, Contrada Minoto 74028 Sava Sava Taranto 74028",
    "addr:postcode":"74028;74028",
    "addr:street":"Km. 1.800 Contrada Minoto",
    "iso:country":"IT",
    "sg:address":"Km. 1.800, Contrada Minoto 74028 Sava",
    "sg:city":"Sava",
    "sg:classifiers":[
        {
            "category":"Professional",
            "subcategory":"Engineering",
            "type":"Services"
        }
    ],
    "sg:phone":"+39 099 972 1468",
    "sg:postcode":"74028",
    "sg:province":"Taranto",
    "sg:tags":[
        "machine",
        "-",
        "mechanical"
    ],
    "wof:name":"Tre D.impianti Tecnologici Srl",
    "wof:placetype":"venue"
},
  "geometry": {"coordinates":[17.240009,40.469238],"type":"Point"}
}