{
  "type": "Feature",
  "properties": {
    "iso:country":"IT",
    "sg:address":"4, Via Roma 32040 Lozzo Di Cadore",
    "sg:city":"Lozzo di Cadore",
    "sg:classifiers":[
        {
            "category":"Wholesale",
            "subcategory":"Medical Equipment & Supplies",
            "type":"Manufacturing & Wholesale Goods"
        }
    ],
    "sg:phone":"+39 39043576123",
    "sg:postcode":"32040",
    "sg:province":"Belluno",
    "sg:tags":[
        "-",
        "health",
        "instrument"
    ],
    "wof:name":"Luxol - Occhialeria",
    "wof:placetype":"venue"
},
  "geometry": {"coordinates":[12.435852,46.47517],"type":"Point"}
}