{
  "type": "Feature",
  "properties": {
    "iso:country":"IT",
    "sg:address":"20121 Milano",
    "sg:city":"Milano",
    "sg:orig_category":"Abbigliamento Intimo, Calze E Costumi Da Bagno. Articoli Medico-sanitari Ed Ortopedici",
    "sg:phone":"+39 02 877405",
    "sg:postcode":"20121",
    "sg:province":"Milano",
    "wof:name":"Rapetti Di Cabassi Carlo",
    "wof:placetype":"venue"
},
  "geometry": {"coordinates":[9.181145,45.466587],"type":"Point"}
}