{
  "type": "Feature",
  "properties": {
    "addr:full":"20, Via Del Maspino 52100 Arezzo Arezzo Arezzo 52100",
    "addr:postcode":"52100;52100",
    "addr:street":"Via Del Maspino",
    "iso:country":"IT",
    "sg:address":"20, Via Del Maspino 52100 Arezzo",
    "sg:city":"Arezzo",
    "sg:classifiers":[
        {
            "category":"Manufacturing",
            "subcategory":"Metals",
            "type":"Manufacturing & Wholesale Goods"
        }
    ],
    "sg:phone":"+39 0575 984151",
    "sg:postcode":"52100",
    "sg:province":"Arezzo",
    "sg:tags":[
        "metallurgy",
        "metalworking"
    ],
    "wof:name":"Se.or (s.n.c.)",
    "wof:placetype":"venue"
},
  "geometry": {"coordinates":[11.8615961075,43.4801673889],"type":"Point"}
}