{
  "type": "Feature",
  "properties": {
    "addr:full":"81100 Caserta Caserta Caserta 81100",
    "addr:postcode":"81100;81100",
    "iso:country":"IT",
    "sg:address":"81100 Caserta",
    "sg:city":"Caserta",
    "sg:orig_category":"Scuole E Servizi Scolastici",
    "sg:phone":"+39 0823 328803",
    "sg:postcode":"81100",
    "sg:province":"Caserta",
    "wof:name":"Cts Centro Teatro Studio",
    "wof:placetype":"venue"
},
  "geometry": {"coordinates":[14.339524,41.081696],"type":"Point"}
}