{
  "type": "Feature",
  "properties": {
    "iso:country":"IT",
    "sg:address":"38, Via Camussone 27010 Vellezzo Bellini",
    "sg:city":"Vellezzo Bellini",
    "sg:classifiers":[
        {
            "category":"Wholesale",
            "subcategory":"Drugs",
            "type":"Manufacturing & Wholesale Goods"
        }
    ],
    "sg:phone":"+39 0382 926895",
    "sg:postcode":"27010",
    "sg:province":"Pavia",
    "sg:tags":[
        "chemical",
        "pharmaceutical"
    ],
    "wof:name":"Plasveroi International Srl",
    "wof:placetype":"venue"
},
  "geometry": {"coordinates":[9.118031,45.27174],"type":"Point"}
}