{
  "type": "Feature",
  "properties": {
    "addr:full":"20066 Melzo Melzo Milano 20066",
    "addr:postcode":"20066;20066",
    "iso:country":"IT",
    "sg:address":"20066 Melzo",
    "sg:city":"Melzo",
    "sg:orig_category":"Agenzie D'affari E Servizi Commerciali. Acqua, Luce, Gas E Societa' Di Esercizio Pubblico",
    "sg:phone":"+39 02 9573 5217",
    "sg:postcode":"20066",
    "sg:province":"Milano",
    "wof:name":"Bettinelli Antonia",
    "wof:placetype":"venue"
},
  "geometry": {"coordinates":[9.177595,45.543152],"type":"Point"}
}