{
  "type": "Feature",
  "properties": {
    "addr:full":"60025 Loreto Loreto Ancona 60025",
    "addr:postcode":"60025;60025",
    "iso:country":"IT",
    "sg:address":"60025 Loreto",
    "sg:city":"Loreto",
    "sg:classifiers":[
        {
            "category":"Wholesale",
            "subcategory":"Machinery & Supplies",
            "type":"Manufacturing & Wholesale Goods"
        }
    ],
    "sg:phone":"+39 071 750 1447",
    "sg:postcode":"60025",
    "sg:province":"Ancona",
    "sg:tags":[
        "component",
        "engineering",
        "material",
        "electrical"
    ],
    "wof:name":"Stacchiotti Pierino",
    "wof:placetype":"venue"
},
  "geometry": {"coordinates":[13.618908,43.43631],"type":"Point"}
}