{
  "type": "Feature",
  "properties": {
    "iso:country":"IT",
    "sg:address":"Piazza Lenti, 27; Camagna Monferrato; 15030",
    "sg:city":"Camagna Monferrato",
    "sg:classifiers":[
        {
            "category":"Banks & Credit Unions",
            "subcategory":"Bank",
            "type":"Services"
        }
    ],
    "sg:phone":"+39 0142 925124",
    "sg:postcode":"15030",
    "sg:province":"Alessandria",
    "wof:name":"Banca Popolare Di Novara",
    "wof:placetype":"venue"
},
  "geometry": {"coordinates":[8.428599,45.017384],"type":"Point"}
}