{
  "type": "Feature",
  "properties": {
    "iso:country":"IT",
    "sg:address":"20094 Corsico",
    "sg:city":"Corsico",
    "sg:orig_category":"Tessuti E Stoffe. Forniture Per Attivita' Industriali",
    "sg:phone":"+39 02 458 1893",
    "sg:postcode":"20094",
    "sg:province":"Milano",
    "wof:name":"Arrinova Sas",
    "wof:placetype":"venue"
},
  "geometry": {"coordinates":[9.109357,45.449951],"type":"Point"}
}