{
  "type": "Feature",
  "properties": {
    "addr:full":"35010 Vigonza Vigonza Padova 35010",
    "addr:postcode":"35010;35010",
    "iso:country":"IT",
    "sg:address":"35010 Vigonza",
    "sg:city":"Vigonza",
    "sg:orig_category":"Metalli E Leghe",
    "sg:phone":"+39 049 629733",
    "sg:postcode":"35010",
    "sg:province":"Padova",
    "wof:name":"Destro Roberto Eredi Srl",
    "wof:placetype":"venue"
},
  "geometry": {"coordinates":[11.9675674438,45.4252891541],"type":"Point"}
}