{
  "type": "Feature",
  "properties": {
    "addr:full":"3, Piazzale S. Giuseppe 27100 Pavia Pavia Pavia 27100",
    "addr:postcode":"27100;27100",
    "addr:street":"Piazzale S. Giuseppe",
    "iso:country":"IT",
    "sg:address":"3, Piazzale S. Giuseppe 27100 Pavia",
    "sg:city":"Pavia",
    "sg:classifiers":[
        {
            "category":"Retail",
            "subcategory":"Animal Services",
            "type":"Services"
        }
    ],
    "sg:phone":"+39 0382 477062",
    "sg:postcode":"27100",
    "sg:province":"Pavia",
    "sg:tags":[
        "breeding"
    ],
    "wof:name":"Sildamin C-o Mancini Mirella",
    "wof:placetype":"venue"
},
  "geometry": {"coordinates":[9.158755,45.197731],"type":"Point"}
}