{
  "type": "Feature",
  "properties": {
    "iso:country":"IT",
    "sg:address":"10091 Alpignano",
    "sg:city":"Alpignano",
    "sg:orig_category":"Servizi E Lavori Per Edilizia E Lavori Pubblici. Acqua, Luce, Gas E Societa' Di Esercizio Pubblico",
    "sg:phone":"+39 011 967 6688",
    "sg:postcode":"10091",
    "sg:province":"Torino",
    "wof:name":"Societa' Per La Condotta Di Acque Potabili (s.p.a.)",
    "wof:placetype":"venue"
},
  "geometry": {"coordinates":[7.57946,45.071362],"type":"Point"}
}