{
  "type": "Feature",
  "properties": {
    "addr:full":"22063 Cantu' Como 22063",
    "addr:postcode":"22063;22063",
    "addr:street":"Cantu ' Como",
    "iso:country":"IT",
    "sg:address":"22063 Cantu'",
    "sg:orig_category":"Vetro: Prodotti E Lavorazioni",
    "sg:phone":"+39 031 714973",
    "sg:postcode":"22063",
    "sg:province":"Como",
    "wof:name":"Rossi Mirko - Mi.ro. Glass",
    "wof:placetype":"venue"
},
  "geometry": {"coordinates":[9.133175,45.728283],"type":"Point"}
}