{
  "type": "Feature",
  "properties": {
    "addr:full":"334, Via Del Lavoro 37050 Angiari Angiari Verona 37050",
    "addr:housenumber":"334",
    "addr:postcode":"37050;37050",
    "addr:street":"Via Del Lavoro",
    "iso:country":"IT",
    "sg:address":"334, Via Del Lavoro 37050 Angiari",
    "sg:city":"Angiari",
    "sg:classifiers":[
        {
            "category":"Professional",
            "subcategory":"Engineering",
            "type":"Services"
        }
    ],
    "sg:phone":"+39 39044298405",
    "sg:postcode":"37050",
    "sg:province":"Verona",
    "sg:tags":[
        "machine",
        "-",
        "mechanical"
    ],
    "wof:name":"Extrusion Hi. Tech. S.r.l.",
    "wof:placetype":"venue"
},
  "geometry": {"coordinates":[11.242513,45.226917],"type":"Point"}
}