{
  "type": "Feature",
  "properties": {
    "iso:country":"IT",
    "sg:address":"00165 Roma",
    "sg:city":"Roma",
    "sg:orig_category":"Serramenti Ed Infissi",
    "sg:phone":"+39 06 3937 9055",
    "sg:postcode":"00165",
    "sg:province":"Roma",
    "wof:name":"Cds Srl",
    "wof:placetype":"venue"
},
  "geometry": {"coordinates":[12.438174,41.893383],"type":"Point"}
}