{
  "type": "Feature",
  "properties": {
    "addr:full":"11, Via Ponte Vecchio 27017 Pieve Porto Morone Pieve Porto Morone Pavia 27017",
    "addr:postcode":"27017;27017",
    "addr:street":"Via Ponte Vecchio;Morone",
    "iso:country":"IT",
    "sg:address":"11, Via Ponte Vecchio 27017 Pieve Porto Morone",
    "sg:city":"Pieve Porto Morone",
    "sg:classifiers":[
        {
            "category":"Shopping",
            "subcategory":"Crafts & Fabrics",
            "type":"Retail Goods"
        }
    ],
    "sg:phone":"+39 39038278373",
    "sg:postcode":"27017",
    "sg:province":"Pavia",
    "wof:name":"Torcitura Padana Srl",
    "wof:placetype":"venue"
},
  "geometry": {"coordinates":[9.440448761,45.1064682007],"type":"Point"}
}