{
  "type": "Feature",
  "properties": {
    "iso:country":"IT",
    "sg:address":"26, Viale Dei Mille 48100 Ravenna",
    "sg:city":"Ravenna",
    "sg:classifiers":[
        {
            "category":"Utilities",
            "subcategory":"Telephone",
            "type":"Services"
        }
    ],
    "sg:phone":"+39 0544 531713",
    "sg:postcode":"48100",
    "sg:province":"Ravenna",
    "sg:tags":[
        "telecommunication"
    ],
    "wof:name":"P.m. Marina Di Galassi Luca & Belletti Mauro S.n.c.",
    "wof:placetype":"venue"
},
  "geometry": {"coordinates":[12.279572,44.487839],"type":"Point"}
}