{
  "type": "Feature",
  "properties": {
    "addr:full":"35/37, Strada Provinciale Pavia 15100 Alessandria Alessandria Alessandria 15100",
    "addr:housenumber":"35 / 37",
    "addr:postcode":"15100;15100",
    "addr:street":"Strada Provinciale",
    "iso:country":"IT",
    "sg:address":"35/37, Strada Provinciale Pavia 15100 Alessandria",
    "sg:city":"Alessandria",
    "sg:classifiers":[
        {
            "category":"Manufacturing",
            "subcategory":"Metals",
            "type":"Manufacturing & Wholesale Goods"
        }
    ],
    "sg:phone":"+39 0131 507676",
    "sg:postcode":"15100",
    "sg:province":"Alessandria",
    "sg:tags":[
        "metallurgy",
        "metalworking"
    ],
    "wof:name":"Banco 77",
    "wof:placetype":"venue"
},
  "geometry": {"coordinates":[8.6095685959,44.9653968811],"type":"Point"}
}