{
  "type": "Feature",
  "properties": {
    "addr:full":"Via Litoranea Mattinata 71030 Mattinata Mattinata Foggia 71030",
    "addr:postcode":"71030;71030",
    "addr:street":"Via Litoranea",
    "iso:country":"IT",
    "sg:address":"Via Litoranea Mattinata 71030 Mattinata",
    "sg:city":"Mattinata",
    "sg:classifiers":[
        {
            "category":"Travel",
            "subcategory":"Travel Agent",
            "type":"Entertainment"
        }
    ],
    "sg:phone":"+39 0884 550155",
    "sg:postcode":"71030",
    "sg:province":"Foggia",
    "sg:tags":[
        "business"
    ],
    "wof:name":"Albergo Baia Delle Zagare",
    "wof:placetype":"venue"
},
  "geometry": {"coordinates":[15.5447,41.462334],"type":"Point"}
}