{
  "type": "Feature",
  "properties": {
    "iso:country":"IT",
    "sg:address":"21040 Origgio",
    "sg:city":"Origgio",
    "sg:orig_category":"Carta, Cartone E Prodotti Primari. Forniture E Materiali Per Imballaggio E Confezionamento",
    "sg:phone":"+39 02 9673 0727",
    "sg:postcode":"21040",
    "sg:province":"Varese",
    "wof:name":"Fasson Italia (s.p.a.)",
    "wof:placetype":"venue"
},
  "geometry": {"coordinates":[9.015004,45.568249],"type":"Point"}
}