{
  "type": "Feature",
  "properties": {
    "addr:full":"20094 Corsico Corsico Milano 20094",
    "addr:postcode":"20094;20094",
    "iso:country":"IT",
    "sg:address":"20094 Corsico",
    "sg:city":"Corsico",
    "sg:orig_category":"Scuole E Servizi Scolastici. Ricerca, Selezione E Formazione Del Personale. Pubblica Amministrazione",
    "sg:phone":"+39 02 447 8206",
    "sg:postcode":"20094",
    "sg:province":"Milano",
    "wof:name":"Municipio Di Corsico Asili Nido",
    "wof:placetype":"venue"
},
  "geometry": {"coordinates":[9.116217,45.432938],"type":"Point"}
}