{
  "type": "Feature",
  "properties": {
    "addr:full":"Viale Italia 373; La Spezia; 19100",
    "addr:housenumber":"373",
    "addr:postcode":"19100",
    "addr:street":"Viale Italia",
    "iso:country":"IT",
    "sg:address":"Viale Italia 373; La Spezia; 19100",
    "sg:classifiers":[
        {
            "category":"Banks & Credit Unions",
            "subcategory":"Bank",
            "type":"Services"
        }
    ],
    "sg:phone":"+39 0187 524691",
    "wof:name":"Cassa Di Risparmio Di Carrara Spa",
    "wof:placetype":"venue"
},
  "geometry": {"coordinates":[9.839199,44.114986],"type":"Point"}
}