{
  "type": "Feature",
  "properties": {
    "addr:full":"37, Via Pedaci 73040 Acquarica Del Capo Acquarica del Capo Lecce 73040",
    "addr:postcode":"73040;73040",
    "addr:street":"Via Pedaci",
    "iso:country":"IT",
    "sg:address":"37, Via Pedaci 73040 Acquarica Del Capo",
    "sg:city":"Acquarica del Capo",
    "sg:classifiers":[
        {
            "category":"Shopping",
            "subcategory":"Clothing, Apparel, & Fashions",
            "type":"Retail Goods"
        }
    ],
    "sg:phone":"+39 0833 722550",
    "sg:postcode":"73040",
    "sg:province":"Lecce",
    "sg:tags":[
        "clothes"
    ],
    "wof:name":"Calzificio Pedaci Antonio",
    "wof:placetype":"venue"
},
  "geometry": {"coordinates":[18.247133,39.907986],"type":"Point"}
}