{
  "type": "Feature",
  "properties": {
    "iso:country":"IT",
    "sg:address":"00197 Roma",
    "sg:city":"Roma",
    "sg:orig_category":"Scuole E Servizi Scolastici. Alberghi E Strutture Extra Alberghiere",
    "sg:phone":"+39 06 807 4768",
    "sg:postcode":"00197",
    "sg:province":"Roma",
    "wof:name":"Suore Sac.cuore Di Maria V.i.",
    "wof:placetype":"venue"
},
  "geometry": {"coordinates":[12.494775,41.929569],"type":"Point"}
}