{
  "type": "Feature",
  "properties": {
    "iso:country":"IT",
    "sg:address":"74100 Taranto",
    "sg:city":"Taranto",
    "sg:orig_category":"Abbigliamento Esterno, Maglierie E Pelliccerie. Calzature, Pelletterie E Pelli",
    "sg:phone":"+39 099 452 6648",
    "sg:postcode":"74100",
    "sg:province":"Taranto",
    "wof:name":"Giacoia Massimo S.a.s.",
    "wof:placetype":"venue"
},
  "geometry": {"coordinates":[17.248468,40.470325],"type":"Point"}
}