{
  "type": "Feature",
  "properties": {
    "iso:country":"IT",
    "sg:address":"Via Sile 41",
    "sg:city":"Roncade TV",
    "sg:classifiers":[
        {
            "category":"Professional",
            "subcategory":"Computer Services",
            "type":"Services"
        }
    ],
    "sg:postcode":"31056",
    "sg:tags":[
        "alternate-reality-game",
        "immersive-game",
        "travel",
        "interactive-web-serial",
        "chaotic-fiction"
    ],
    "sg:website":"http://log607.com",
    "wof:name":"LOG607",
    "wof:placetype":"venue"
},
  "geometry": {"coordinates":[12.436354,45.564209],"type":"Point"}
}