{
  "type": "Feature",
  "properties": {
    "iso:country":"IT",
    "sg:address":"59013 Montemurlo",
    "sg:city":"Montemurlo",
    "sg:orig_category":"Tessuti E Stoffe - Produzione E Ingrosso",
    "sg:phone":"+39 0574 791506",
    "sg:postcode":"59013",
    "sg:province":"Prato",
    "sg:website":"http://www.euromaglia.it",
    "wof:name":"Euromaglia Srl",
    "wof:placetype":"venue"
},
  "geometry": {"coordinates":[11.061433,43.895218],"type":"Point"}
}