{
  "type": "Feature",
  "properties": {
    "addr:full":"34, Vl. Della Repubblica 47015 Modigliana Modigliana Forl\u00ec-Cesena 47015",
    "addr:housenumber":"34",
    "addr:postcode":"47015;47015",
    "addr:street":"Vl. Della Repubblica",
    "iso:country":"IT",
    "sg:address":"34, Vl. Della Repubblica 47015 Modigliana",
    "sg:city":"Modigliana",
    "sg:classifiers":[
        {
            "category":"Manufacturing",
            "subcategory":"Lumber",
            "type":"Manufacturing & Wholesale Goods"
        }
    ],
    "sg:phone":"+39 0546 945411",
    "sg:postcode":"47015",
    "sg:province":"Forl\u00ec-Cesena",
    "sg:tags":[
        "wood"
    ],
    "sg:website":"http://www.alpiwood.com:ws_end: :mark:ws:http://www.paginegialle.it/alpispa",
    "wof:name":"Alpi Spa",
    "wof:placetype":"venue"
},
  "geometry": {"coordinates":[11.797306,44.163719],"type":"Point"}
}