{
  "type": "Feature",
  "properties": {
    "iso:country":"IT",
    "sg:address":"40033 Casalecchio Di Reno",
    "sg:city":"Casalecchio di Reno",
    "sg:orig_category":"Scuole E Servizi Scolastici. Servizi Ausiliari Dei Mezzi Di Trasporto. Ricerca, Selezione E Formazione Del Personale",
    "sg:phone":"+39 051 571343",
    "sg:postcode":"40033",
    "sg:province":"Bologna",
    "wof:name":"Autoscuola Boschi Srl",
    "wof:placetype":"venue"
},
  "geometry": {"coordinates":[11.274692,44.474445],"type":"Point"}
}