{
  "type": "Feature",
  "properties": {
    "addr:full":"31040 Mansue' Treviso 31040",
    "addr:postcode":"31040;31040",
    "addr:street":"Mansue ' Treviso",
    "iso:country":"IT",
    "sg:address":"31040 Mansue'",
    "sg:orig_category":"Alimentari - Vendita Al Dettaglio",
    "sg:phone":"+39 0422 741146",
    "sg:postcode":"31040",
    "sg:province":"Treviso",
    "wof:name":"Alimentari Cazorzi",
    "wof:placetype":"venue"
},
  "geometry": {"coordinates":[12.245823,45.661327],"type":"Point"}
}