{
  "type": "Feature",
  "properties": {
    "addr:full":"24040 Calvenzano Calvenzano Bergamo 24040",
    "addr:postcode":"24040;24040",
    "iso:country":"IT",
    "sg:address":"24040 Calvenzano",
    "sg:city":"Calvenzano",
    "sg:orig_category":"Termotecnica E Riscaldamento, Apparecchiature E Servizi. Valvole E Apparecchiature Di Misura. Macchine, Strumenti Ed Apparecchi Per Attivita' Industriali",
    "sg:phone":"+39 036 333 5561",
    "sg:postcode":"24040",
    "sg:province":"Bergamo",
    "wof:name":"Gusmini E Balconi S.r.l.",
    "wof:placetype":"venue"
},
  "geometry": {"coordinates":[9.544339,45.577583],"type":"Point"}
}