{
  "type": "Feature",
  "properties": {
    "addr:full":"20125 Milano Milano Milano 20125",
    "addr:postcode":"20125;20125",
    "iso:country":"IT",
    "sg:address":"20125 Milano",
    "sg:city":"Milano",
    "sg:orig_category":"Frigotecnica, Apparecchiature E Servizi",
    "sg:phone":"+39 02 6698 6699",
    "sg:postcode":"20125",
    "sg:province":"Milano",
    "wof:name":"Sanital (s.r.l.)",
    "wof:placetype":"venue"
},
  "geometry": {"coordinates":[9.205370903,45.4960174561],"type":"Point"}
}