{
  "type": "Feature",
  "properties": {
    "iso:country":"IT",
    "sg:address":"20121 Milano",
    "sg:city":"Milano",
    "sg:orig_category":"Servizi E Lavori Per Agricoltura E Zootecnia",
    "sg:phone":"+39 02 760541",
    "sg:postcode":"20121",
    "sg:province":"Milano",
    "wof:name":"Co.re.pla.",
    "wof:placetype":"venue"
},
  "geometry": {"coordinates":[9.196691,45.472267],"type":"Point"}
}