{
  "type": "Feature",
  "properties": {
    "iso:country":"IT",
    "sg:address":"55100 Lucca",
    "sg:city":"Lucca",
    "sg:orig_category":"Condizionamento Aria Impianti - Installazione E Manutenzione",
    "sg:phone":"+39 0583 490556",
    "sg:postcode":"55100",
    "sg:province":"Lucca",
    "sg:website":"http://www.idroimpianti.it",
    "wof:name":"Idroimpianti Bieffe",
    "wof:placetype":"venue"
},
  "geometry": {"coordinates":[10.52889,43.851151],"type":"Point"}
}