{
  "type": "Feature",
  "properties": {
    "addr:full":"56018 Tirrenia PI",
    "addr:housenumber":"56018",
    "addr:street":"Pi",
    "iso:country":"IT",
    "sg:address":"56018 Tirrenia",
    "sg:orig_category":"Pubblica Amministrazione",
    "sg:phone":"+39 050 32685",
    "sg:province":"PI",
    "wof:name":"A.m.comando 46 Aerobrigata Pisa",
    "wof:placetype":"venue"
},
  "geometry": {"coordinates":[10.2915458679,43.6271018982],"type":"Point"}
}