{
  "type": "Feature",
  "properties": {
    "addr:full":"Via Toscoromagnola; Cascina; 56021 Cascina Pisa 56021",
    "addr:postcode":"56021;56021",
    "addr:street":"Via Toscoromagnola Cascina",
    "iso:country":"IT",
    "sg:address":"Via Toscoromagnola; Cascina; 56021",
    "sg:city":"Cascina",
    "sg:classifiers":[
        {
            "category":"Banks & Credit Unions",
            "subcategory":"Bank",
            "type":"Services"
        }
    ],
    "sg:phone":"+39 050 701625",
    "sg:postcode":"56021",
    "sg:province":"Pisa",
    "wof:name":"Cassa Di Risparmio Di Pisa Spa",
    "wof:placetype":"venue"
},
  "geometry": {"coordinates":[10.470207,43.689842],"type":"Point"}
}