{
  "type": "Feature",
  "properties": {
    "iso:country":"IT",
    "sg:address":"34074 Monfalcone",
    "sg:city":"Monfalcone",
    "sg:classifiers":[
        {
            "category":"Retail",
            "subcategory":"Auto Repair",
            "type":"Services"
        }
    ],
    "sg:phone":"+39 0481 413305",
    "sg:postcode":"34074",
    "sg:province":"Gorizia",
    "sg:tags":[
        "repairs",
        "vehicles",
        "auxiliary",
        "motor"
    ],
    "wof:name":"Ocean Marine Srl",
    "wof:placetype":"venue"
},
  "geometry": {"coordinates":[13.5686578751,45.7968711853],"type":"Point"}
}