{
  "type": "Feature",
  "properties": {
    "addr:full":"Via Trieste 21; Limbiate; 20051 Limbiate Milano 20051",
    "addr:housenumber":"21",
    "addr:postcode":"20051;20051",
    "addr:street":"Via Trieste",
    "iso:country":"IT",
    "sg:address":"Via Trieste 21; Limbiate; 20051",
    "sg:city":"Limbiate",
    "sg:classifiers":[
        {
            "category":"Banks & Credit Unions",
            "subcategory":"Bank",
            "type":"Services"
        }
    ],
    "sg:phone":"+39 02 9905 6277",
    "sg:postcode":"20051",
    "sg:province":"Milano",
    "wof:name":"Credito Italiano Spa",
    "wof:placetype":"venue"
},
  "geometry": {"coordinates":[9.133866,45.594788],"type":"Point"}
}