{
  "type": "Feature",
  "properties": {
    "iso:country":"IT",
    "sg:address":"39011 Lana",
    "sg:city":"Lana",
    "sg:orig_category":"Macchine E Forniture Per Ecologia E Smaltimento Rifiuti. Macchine, Strumenti Ed Apparecchi Per Attivita' Industriali",
    "sg:phone":"+39 0473 562302",
    "sg:postcode":"39011",
    "sg:province":"Bolzano/Bozen",
    "sg:website":"http://www.pulicenter.com",
    "wof:name":"Pulicenter Commerz Sas",
    "wof:placetype":"venue"
},
  "geometry": {"coordinates":[11.362533,46.496414],"type":"Point"}
}