{
  "type": "Feature",
  "properties": {
    "iso:country":"IT",
    "sg:address":"00143 Roma",
    "sg:city":"Roma",
    "sg:orig_category":"Prodotti Alimentari",
    "sg:phone":"+39 06 504 3479",
    "sg:postcode":"00143",
    "sg:province":"Roma",
    "wof:name":"Enimar Di Nicolino Zoppo E C. Sas",
    "wof:placetype":"venue"
},
  "geometry": {"coordinates":[12.5088357925,41.8235397339],"type":"Point"}
}