{
  "type": "Feature",
  "properties": {
    "addr:full":"1, Via Ovada 16158 Genova Genova Genova 16158",
    "addr:postcode":"16158;16158",
    "addr:street":"Via Ovada",
    "iso:country":"IT",
    "sg:address":"1, Via Ovada 16158 Genova",
    "sg:city":"Genova",
    "sg:classifiers":[
        {
            "category":"Food & Beverages",
            "subcategory":"Groceries & Convenience Stores",
            "type":"Retail Goods"
        }
    ],
    "sg:phone":"+39 010 613 3741",
    "sg:postcode":"16158",
    "sg:province":"Genova",
    "sg:tags":[
        "product",
        "related"
    ],
    "wof:name":"Giolfo & Calcagno (s.p.a.)",
    "wof:placetype":"venue"
},
  "geometry": {"coordinates":[8.7480735779,44.4350471497],"type":"Point"}
}