{
  "type": "Feature",
  "properties": {
    "iso:country":"IT",
    "sg:address":"12, Via Lombardia 56029 Santa Croce Sull'arno",
    "sg:classifiers":[
        {
            "category":"Manufacturing",
            "subcategory":"Textiles",
            "type":"Manufacturing & Wholesale Goods"
        }
    ],
    "sg:phone":"+39 0571 366682",
    "sg:postcode":"56029",
    "sg:province":"Pisa",
    "sg:tags":[
        "leather",
        "raw",
        "material",
        "-"
    ],
    "wof:name":"Conceria Centrorettili S.p.a.",
    "wof:placetype":"venue"
},
  "geometry": {"coordinates":[10.76451,43.716965],"type":"Point"}
}