{
  "type": "Feature",
  "properties": {
    "addr:full":"Via Volpiano 64 10040 Leini' Torino 10040",
    "addr:housenumber":"64",
    "addr:postcode":"10040 leini;10040",
    "addr:street":"Via Volpiano",
    "iso:country":"IT",
    "sg:address":"Via Volpiano 64 10040 Leini'",
    "sg:classifiers":[
        {
            "category":"Organizations",
            "subcategory":"Labor Organization",
            "type":"Services"
        }
    ],
    "sg:phone":"+39 011 997 8230",
    "sg:postcode":"10040",
    "sg:province":"Torino",
    "sg:tags":[
        "purification",
        "system",
        "air"
    ],
    "sg:website":"www.coindsrl.com",
    "wof:name":"Costruzioni Industriali Ecologiche",
    "wof:placetype":"venue"
},
  "geometry": {"coordinates":[7.662356,45.152454],"type":"Point"}
}