{
  "type": "Feature",
  "properties": {
    "addr:full":"Via Milano 54/56 20089 Rozzano Rozzano Milano 20089",
    "addr:housenumber":"54 / 56",
    "addr:postcode":"20089;20089",
    "addr:street":"Via Milano",
    "iso:country":"IT",
    "sg:address":"Via Milano 54/56 20089 Rozzano",
    "sg:city":"Rozzano",
    "sg:classifiers":[
        {
            "category":"Building & Trades",
            "subcategory":"Construction",
            "type":"Services"
        }
    ],
    "sg:phone":"+39 02 892 3911",
    "sg:postcode":"20089",
    "sg:province":"Milano",
    "sg:tags":[
        "installation",
        "underfloor",
        "material",
        "electrical"
    ],
    "sg:website":"www.bm-spa.com",
    "wof:name":"Bm Spa",
    "wof:placetype":"venue"
},
  "geometry": {"coordinates":[9.150804,45.386463],"type":"Point"}
}