{
  "type": "Feature",
  "properties": {
    "iso:country":"IT",
    "sg:address":"24062 Costa Volpino",
    "sg:city":"Costa Volpino",
    "sg:orig_category":"Macchine E Forniture Per Ecologia E Smaltimento Rifiuti. Termotecnica E Riscaldamento, Apparecchiature E Servizi",
    "sg:phone":"+39 035 970661",
    "sg:postcode":"24062",
    "sg:province":"Bergamo",
    "wof:name":"Termotecnica Sebina Snc",
    "wof:placetype":"venue"
},
  "geometry": {"coordinates":[10.086751,45.844608],"type":"Point"}
}