{
  "type": "Feature",
  "properties": {
    "iso:country":"IT",
    "sg:address":"24021 Albino",
    "sg:city":"Albino",
    "sg:orig_category":"Macchine, Impianti E Forniture Per Industria Grafica, Cartaria E Cartotecnica. Prodotti Chimici Secondari",
    "sg:phone":"+39 035 751231",
    "sg:postcode":"24021",
    "sg:province":"Bergamo",
    "wof:name":"Druckfarben Srl",
    "wof:placetype":"venue"
},
  "geometry": {"coordinates":[9.834871,45.756577],"type":"Point"}
}