{
  "type": "Feature",
  "properties": {
    "iso:country":"IT",
    "sg:address":"33048 S. Giovanni Al Natisone",
    "sg:orig_category":"Suites, Armchairs, Chairs And Tables",
    "sg:phone":"+39 0432 756634",
    "sg:postcode":"33048",
    "sg:province":"Udine",
    "wof:name":"Co.s.ma Snc Di Calligaris E Gon",
    "wof:placetype":"venue"
},
  "geometry": {"coordinates":[13.166289,46.140797],"type":"Point"}
}