{
  "type": "Feature",
  "properties": {
    "addr:full":"38, Via I. Nievo 33050 Santa Maria La Longa Santa Maria Udine 33050",
    "addr:postcode":"33050;33050",
    "addr:street":"Via I. Nievo;Maria La;Maria",
    "iso:country":"IT",
    "sg:address":"38, Via I. Nievo 33050 Santa Maria La Longa",
    "sg:city":"Santa Maria",
    "sg:classifiers":[
        {
            "category":"Manufacturing",
            "subcategory":"Wood Products",
            "type":"Manufacturing & Wholesale Goods"
        }
    ],
    "sg:phone":"+39 0432 995045",
    "sg:postcode":"33050",
    "sg:province":"Udine",
    "sg:tags":[
        "furniture"
    ],
    "wof:name":"Api Legno Srl",
    "wof:placetype":"venue"
},
  "geometry": {"coordinates":[13.293521,45.933857],"type":"Point"}
}