{
  "type": "Feature",
  "properties": {
    "iso:country":"IT",
    "sg:address":"20038 Seregno",
    "sg:city":"Seregno",
    "sg:orig_category":"Macchine Utensili - Commercio",
    "sg:phone":"+39 036 223 5087",
    "sg:postcode":"20038",
    "sg:province":"Milano",
    "wof:name":"Brimac Sas Di Giorgio Gioia & C.",
    "wof:placetype":"venue"
},
  "geometry": {"coordinates":[9.203573,45.651917],"type":"Point"}
}