{
  "type": "Feature",
  "properties": {
    "addr:full":"20095 Cusano Milanino Cusano Milanino Milano 20095",
    "addr:postcode":"20095;20095",
    "iso:country":"IT",
    "sg:address":"20095 Cusano Milanino",
    "sg:city":"Cusano Milanino",
    "sg:orig_category":"Studi E Consulenze Tecniche E Industriali. Consulenze Tecniche, Amministrative E Perizie. Professionisti - Studi E Servizi Ed Associazioni Di Interesse Aziendale",
    "sg:phone":"+39 02 6640 2100",
    "sg:postcode":"20095",
    "sg:province":"Milano",
    "wof:name":"Zapparoli Luca Giovanni",
    "wof:placetype":"venue"
},
  "geometry": {"coordinates":[9.181999,45.550411],"type":"Point"}
}