{
  "type": "Feature",
  "properties": {
    "iso:country":"IT",
    "sg:address":"10034 Chivasso",
    "sg:city":"Chivasso",
    "sg:orig_category":"Forniture Per Edilizia E Lavori Pubblici. Prodotti Vari In Metallo",
    "sg:phone":"+39 011 911 3825",
    "sg:postcode":"10034",
    "sg:province":"Torino",
    "wof:name":"Brockett John",
    "wof:placetype":"venue"
},
  "geometry": {"coordinates":[8.3989200592,45.4623451233],"type":"Point"}
}