{
  "type": "Feature",
  "properties": {
    "iso:country":"IT",
    "sg:address":"147, Via Adige 35040 Urbana",
    "sg:city":"Urbana",
    "sg:classifiers":[
        {
            "category":"Professional",
            "subcategory":"Engineering",
            "type":"Services"
        }
    ],
    "sg:phone":"+39 0429 878624",
    "sg:postcode":"35040",
    "sg:province":"Padova",
    "sg:tags":[
        "machine",
        "-",
        "mechanical"
    ],
    "wof:name":"Pam Rollers Factory S.p.a.",
    "wof:placetype":"venue"
},
  "geometry": {"coordinates":[11.447852,45.203484],"type":"Point"}
}