{
  "type": "Feature",
  "properties": {
    "addr:full":"10092 Borgaretto Borgaretto Torino 10092",
    "addr:postcode":"10092;10092",
    "iso:country":"IT",
    "sg:address":"10092 Borgaretto",
    "sg:city":"Borgaretto",
    "sg:orig_category":"Macchine Utensili E Impianti. Apparecchiature Ed Attrezzature Meccaniche",
    "sg:phone":"+39 011 34011",
    "sg:postcode":"10092",
    "sg:province":"Torino",
    "wof:name":"Vagnone & Boeri (s.r.l.)",
    "wof:placetype":"venue"
},
  "geometry": {"coordinates":[7.597305,45.009609],"type":"Point"}
}