{
  "type": "Feature",
  "properties": {
    "addr:full":"00173 Roma Roma Roma 00173",
    "addr:postcode":"00173;00173",
    "iso:country":"IT",
    "sg:address":"00173 Roma",
    "sg:city":"Roma",
    "sg:orig_category":"Materiali Semilavorati Metallici",
    "sg:phone":"+39 06 723 4022",
    "sg:postcode":"00173",
    "sg:province":"Roma",
    "sg:website":"http://www.ellegielle.com",
    "wof:name":"Lgl Lavorazioni Generali Lamiere Srl",
    "wof:placetype":"venue"
},
  "geometry": {"coordinates":[12.59242,41.828922],"type":"Point"}
}