{
  "type": "Feature",
  "properties": {
    "iso:country":"IT",
    "sg:address":"90144 Palermo",
    "sg:city":"Palermo",
    "sg:orig_category":"Non-classified Establishments",
    "sg:phone":"+39 091 345491",
    "sg:postcode":"90144",
    "sg:province":"Palermo",
    "wof:name":"Dante Maria Concetta",
    "wof:placetype":"venue"
},
  "geometry": {"coordinates":[13.346194,38.131321],"type":"Point"}
}