{
  "type": "Feature",
  "properties": {
    "iso:country":"IT",
    "sg:address":"17047 Vado Ligure",
    "sg:city":"Vado Ligure",
    "sg:orig_category":"Ascensori - Costruzione",
    "sg:phone":"+39 019 886270",
    "sg:postcode":"17047",
    "sg:province":"Savona",
    "wof:name":"C.l.l. Snc Di Macri' Giuseppe & C.",
    "wof:placetype":"venue"
},
  "geometry": {"coordinates":[8.437476,44.268631],"type":"Point"}
}