{
  "type": "Feature",
  "properties": {
    "iso:country":"IT",
    "sg:address":"37058 Sanguinetto",
    "sg:city":"Sanguinetto",
    "sg:orig_category":"Arredamenti Ed Architettura D'interni",
    "sg:phone":"+39 0442 365432",
    "sg:postcode":"37058",
    "sg:province":"Verona",
    "sg:website":"http://www.rossettisergio.com",
    "wof:name":"Rossetti Angelo Snc Di Rossetti Sergio & C.",
    "wof:placetype":"venue"
},
  "geometry": {"coordinates":[11.166101,45.178425],"type":"Point"}
}