{
  "type": "Feature",
  "properties": {
    "addr:full":"11/a, Via Casalgrasso 12030 Polonghera Casalgrasso Cuneo 12030",
    "addr:housenumber":"11 / a",
    "addr:postcode":"12030;12030",
    "addr:street":"Via Casalgrasso",
    "iso:country":"IT",
    "sg:address":"11/a, Via Casalgrasso 12030 Polonghera",
    "sg:city":"Casalgrasso",
    "sg:classifiers":[
        {
            "category":"Professional",
            "subcategory":"Engineering",
            "type":"Services"
        }
    ],
    "sg:phone":"+39 39011974690",
    "sg:postcode":"12030",
    "sg:province":"Cuneo",
    "sg:tags":[
        "machine",
        "-",
        "mechanical"
    ],
    "wof:name":"Fasmap",
    "wof:placetype":"venue"
},
  "geometry": {"coordinates":[7.547111,44.388798],"type":"Point"}
}