{
  "type": "Feature",
  "properties": {
    "addr:full":"3, Via Giuseppe Verdi 20080 Zibido San Giacomo Zibido San Giacomo Milano 20080",
    "addr:postcode":"20080;20080",
    "addr:street":"Via Giuseppe Verdi;San",
    "iso:country":"IT",
    "sg:address":"3, Via Giuseppe Verdi 20080 Zibido San Giacomo",
    "sg:city":"Zibido San Giacomo",
    "sg:classifiers":[
        {
            "category":"Wholesale",
            "subcategory":"Drugs",
            "type":"Manufacturing & Wholesale Goods"
        }
    ],
    "sg:phone":"+39 02 9000 3141",
    "sg:postcode":"20080",
    "sg:province":"Milano",
    "sg:tags":[
        "chemical",
        "pharmaceutical"
    ],
    "wof:name":"Carbocrom Srl",
    "wof:placetype":"venue"
},
  "geometry": {"coordinates":[9.06337,45.426193],"type":"Point"}
}