{
  "type": "Feature",
  "properties": {
    "iso:country":"IT",
    "sg:address":"Via Fornace 30 40023 Castel Guelfo Di Bologna",
    "sg:city":"Castel Guelfo di Bologna",
    "sg:classifiers":[
        {
            "category":"Communications",
            "subcategory":"Radio Station",
            "type":"Services"
        }
    ],
    "sg:phone":"+39 0542 632111",
    "sg:postcode":"40023",
    "sg:province":"Bologna",
    "sg:tags":[
        "generating",
        "set",
        "emergency"
    ],
    "sg:website":"www.chloridetower.com",
    "wof:name":"Chloride Spa",
    "wof:placetype":"venue"
},
  "geometry": {"coordinates":[11.612321,44.438],"type":"Point"}
}