{
  "type": "Feature",
  "properties": {
    "iso:country":"IT",
    "sg:address":"22070 Vertemate Con Minoprio",
    "sg:city":"Minoprio",
    "sg:orig_category":"Servizi Per Aziende, Manifestazioni E Supporto Agli Scambi Commerciali",
    "sg:phone":"+39 031 887315",
    "sg:postcode":"22070",
    "sg:province":"Como",
    "wof:name":"C.enne Detective",
    "wof:placetype":"venue"
},
  "geometry": {"coordinates":[9.127019,45.736053],"type":"Point"}
}