{
  "type": "Feature",
  "properties": {
    "iso:country":"IT",
    "sg:address":"44043 Mirabello",
    "sg:city":"Mirabello",
    "sg:orig_category":"Valvole E Apparecchiature Di Misura",
    "sg:phone":"+39 0532 847793",
    "sg:postcode":"44043",
    "sg:province":"Ferrara",
    "wof:name":"C.m.v. Servizi S.r.l.",
    "wof:placetype":"venue"
},
  "geometry": {"coordinates":[11.458241,44.824032],"type":"Point"}
}