{
  "type": "Feature",
  "properties": {
    "addr:full":"20131 Milano Milano Milano 20131",
    "addr:postcode":"20131;20131",
    "iso:country":"IT",
    "sg:address":"20131 Milano",
    "sg:city":"Milano",
    "sg:orig_category":"Agenzie Ed Uffici Commerciali",
    "sg:phone":"+39 02 2668 1372",
    "sg:postcode":"20131",
    "sg:province":"Milano",
    "wof:name":"Aspide Di D'ambrosio Alfonso",
    "wof:placetype":"venue"
},
  "geometry": {"coordinates":[9.233442,45.482464],"type":"Point"}
}