{
  "type": "Feature",
  "properties": {
    "addr:full":"25023 Gottolengo Gottolengo Brescia 25023",
    "addr:postcode":"25023;25023",
    "iso:country":"IT",
    "sg:address":"25023 Gottolengo",
    "sg:city":"Gottolengo",
    "sg:orig_category":"Prodotti Alimentari",
    "sg:phone":"+39 030 951452",
    "sg:postcode":"25023",
    "sg:province":"Brescia",
    "wof:name":"Ovochef Snc Di Lampugnani Evio E C.",
    "wof:placetype":"venue"
},
  "geometry": {"coordinates":[10.2229576111,45.5398292542],"type":"Point"}
}