{
  "type": "Feature",
  "properties": {
    "iso:country":"IT",
    "sg:address":"20090 Buccinasco",
    "sg:city":"Buccinasco",
    "sg:orig_category":"Alluminio E Leghe",
    "sg:phone":"+39 02 4884 0910",
    "sg:postcode":"20090",
    "sg:province":"Milano",
    "wof:name":"Ralcom Srl",
    "wof:placetype":"venue"
},
  "geometry": {"coordinates":[9.108614,45.422104],"type":"Point"}
}