{
  "type": "Feature",
  "properties": {
    "addr:full":"59011 Carmignano Carmignano Prato 59011",
    "addr:postcode":"59011;59011",
    "iso:country":"IT",
    "sg:address":"59011 Carmignano",
    "sg:city":"Carmignano",
    "sg:orig_category":"Abbigliamento - Produzione E Ingrosso",
    "sg:phone":"+39 055 870 5061",
    "sg:postcode":"59011",
    "sg:province":"Prato",
    "wof:name":"Maglieria Elisa Di Carlesi Claudio & C. Sas",
    "wof:placetype":"venue"
},
  "geometry": {"coordinates":[11.013321,43.846394],"type":"Point"}
}