{
  "type": "Feature",
  "properties": {
    "iso:country":"IT",
    "sg:address":"22046 Merone",
    "sg:city":"Merone",
    "sg:orig_category":"Telecomunicazioni E Telefonia, Impianti, Apparecchi E Servizi",
    "sg:phone":"+39 031 618 2001",
    "sg:postcode":"22046",
    "sg:province":"Como",
    "wof:name":"Kft Spa",
    "wof:placetype":"venue"
},
  "geometry": {"coordinates":[9.217101,45.759335],"type":"Point"}
}