{
  "type": "Feature",
  "properties": {
    "addr:full":"Via Salemi 75 91025 Marsala Marsala Trapani 91025",
    "addr:housenumber":"75",
    "addr:postcode":"91025;91025",
    "addr:street":"Via Salemi",
    "iso:country":"IT",
    "sg:address":"Via Salemi 75 91025 Marsala",
    "sg:city":"Marsala",
    "sg:classifiers":[
        {
            "category":"Professional",
            "subcategory":"Computer Services",
            "type":"Services"
        }
    ],
    "sg:phone":"+39 0923 722198",
    "sg:postcode":"91025",
    "sg:province":"Trapani",
    "sg:tags":[
        "services",
        "consulting",
        "internet"
    ],
    "sg:website":"www.aidacom.net",
    "wof:name":"A.i.d.a. Communication",
    "wof:placetype":"venue"
},
  "geometry": {"coordinates":[12.454682,37.792389],"type":"Point"}
}