{
  "type": "Feature",
  "properties": {
    "addr:full":"Via Istria 25/e 35135 Padova Padova Padova 35135",
    "addr:housenumber":"25 / e",
    "addr:postcode":"35135;35135",
    "addr:street":"Via Istria",
    "iso:country":"IT",
    "sg:address":"Via Istria 25/e 35135 Padova",
    "sg:city":"Padova",
    "sg:classifiers":[
        {
            "category":"Health Services",
            "subcategory":"Nursing And Care Facility",
            "type":"Services"
        }
    ],
    "sg:phone":"+39 049 853 0101",
    "sg:postcode":"35135",
    "sg:province":"Padova",
    "sg:tags":[
        "fa\u00e7ades",
        "treatment",
        "hydrophobic"
    ],
    "sg:website":"www.eternoivica.com",
    "wof:name":"Eterno - Ivica Spa",
    "wof:placetype":"venue"
},
  "geometry": {"coordinates":[11.844167,45.397499],"type":"Point"}
}