{
  "type": "Feature",
  "properties": {
    "iso:country":"IT",
    "sg:address":"Piazzetta Scala 1; Verona; 37121",
    "sg:city":"Verona",
    "sg:classifiers":[
        {
            "category":"Banks & Credit Unions",
            "subcategory":"Bank",
            "type":"Services"
        }
    ],
    "sg:phone":"+39 045 809 9111",
    "sg:postcode":"37121",
    "sg:province":"Verona",
    "wof:name":"Banca Commerciale Italiana Spa",
    "wof:placetype":"venue"
},
  "geometry": {"coordinates":[10.996454,45.441036],"type":"Point"}
}