{
  "type": "Feature",
  "properties": {
    "addr:full":"Via Porta Nuova 36 70052 Bisceglie Bisceglie Bari 70052",
    "addr:housenumber":"36",
    "addr:postcode":"70052;70052",
    "addr:street":"Via Porta Nuova",
    "iso:country":"IT",
    "sg:address":"Via Porta Nuova 36 70052 Bisceglie",
    "sg:city":"Bisceglie",
    "sg:classifiers":[
        {
            "category":"Food & Beverages",
            "subcategory":"Fruits & Vegetables",
            "type":"Retail Goods"
        }
    ],
    "sg:phone":"+39 080 395 8862",
    "sg:postcode":"70052",
    "sg:province":"Bari",
    "sg:website":"www.leuci.net",
    "wof:name":"Ortofrutta Leuci Srl.",
    "wof:placetype":"venue"
},
  "geometry": {"coordinates":[16.5058784485,41.2394104004],"type":"Point"}
}