{
  "type": "Feature",
  "properties": {
    "addr:full":"3, Via Fieschi 16121 Genova Genova Genova 16121",
    "addr:postcode":"16121;16121",
    "addr:street":"Via Fieschi",
    "iso:country":"IT",
    "sg:address":"3, Via Fieschi 16121 Genova",
    "sg:city":"Genova",
    "sg:classifiers":[
        {
            "category":"Marine",
            "type":"Transportation"
        }
    ],
    "sg:phone":"+39 390 105 4441",
    "sg:postcode":"16121",
    "sg:province":"Genova",
    "sg:tags":[
        "transport",
        "sea"
    ],
    "wof:name":"Premuda Spa",
    "wof:placetype":"venue"
},
  "geometry": {"coordinates":[8.936664,44.405415],"type":"Point"}
}