{
  "type": "Feature",
  "properties": {
    "iso:country":"IT",
    "sg:address":"56040 Montecatini Val Di Cecina",
    "sg:city":"Montecatini Val di Cecina",
    "sg:orig_category":"Prodotti Alimentari",
    "sg:phone":"+39 0588 37304",
    "sg:postcode":"56040",
    "sg:province":"Pisa",
    "wof:name":"Alimentari Bassini",
    "wof:placetype":"venue"
},
  "geometry": {"coordinates":[10.7443494797,43.3356170654],"type":"Point"}
}