{
  "type": "Feature",
  "properties": {
    "iso:country":"IT",
    "sg:address":"20131 Milano",
    "sg:city":"Milano",
    "sg:orig_category":"Animali Domestici - Allevamento E Addestramento",
    "sg:phone":"+39 02 236 0418",
    "sg:postcode":"20131",
    "sg:province":"Milano",
    "wof:name":"Ciao Cucciolo Di Bonvini C.",
    "wof:placetype":"venue"
},
  "geometry": {"coordinates":[9.220038,45.480286],"type":"Point"}
}