{
  "type": "Feature",
  "properties": {
    "iso:country":"IT",
    "sg:address":"50145 Firenze",
    "sg:city":"Firenze",
    "sg:orig_category":"Forniture Per Attivita' Industriali",
    "sg:phone":"+39 055 301275",
    "sg:postcode":"50145",
    "sg:province":"Firenze",
    "wof:name":"U.m.g. Srl",
    "wof:placetype":"venue"
},
  "geometry": {"coordinates":[11.1938962936,43.8008804321],"type":"Point"}
}