{
  "type": "Feature",
  "properties": {
    "addr:full":"13835 Trivero Trivero Biella 13835",
    "addr:housenumber":"13835",
    "addr:postcode":"13835",
    "iso:country":"IT",
    "sg:address":"13835 Trivero",
    "sg:city":"Trivero",
    "sg:orig_category":"Tintorie - Servizio Conto Terzi",
    "sg:phone":"+39 015 738 7690",
    "sg:postcode":"13835",
    "sg:province":"Biella",
    "wof:name":"Tintoria Di Trivero Srl",
    "wof:placetype":"venue"
},
  "geometry": {"coordinates":[8.076365,45.587189],"type":"Point"}
}