{
  "type": "Feature",
  "properties": {
    "iso:country":"IT",
    "sg:address":"11100 Aosta",
    "sg:city":"Aosta",
    "sg:orig_category":"Abbigliamento In Pelle - Vendita Al Dettaglio",
    "sg:phone":"+39 0165 230964",
    "sg:postcode":"11100",
    "sg:province":"Aosta",
    "wof:name":"Emozioni - Sexy Shop",
    "wof:placetype":"venue"
},
  "geometry": {"coordinates":[7.311283,45.738503],"type":"Point"}
}