{
  "type": "Feature",
  "properties": {
    "addr:full":"81, Viale Trento 38068 Rovereto Rovereto Trento 38068",
    "addr:housenumber":"81",
    "addr:postcode":"38068;38068",
    "addr:street":"Viale Trento",
    "iso:country":"IT",
    "sg:address":"81, Viale Trento 38068 Rovereto",
    "sg:city":"Rovereto",
    "sg:classifiers":[
        {
            "category":"Food & Beverages",
            "subcategory":"Dairy",
            "type":"Retail Goods"
        }
    ],
    "sg:phone":"+39 0464 412111",
    "sg:postcode":"38068",
    "sg:province":"Trento",
    "sg:tags":[
        "product"
    ],
    "wof:name":"S.a.v. Societa' Agricoltori Vallagarina",
    "wof:placetype":"venue"
},
  "geometry": {"coordinates":[11.040396,45.907673],"type":"Point"}
}