{
  "type": "Feature",
  "properties": {
    "addr:full":"16149 Genova Genova Genova 16149",
    "addr:postcode":"16149;16149",
    "iso:country":"IT",
    "sg:address":"16149 Genova",
    "sg:city":"Genova",
    "sg:orig_category":"Forniture Per Attivita' Industriali",
    "sg:phone":"+39 010 415288",
    "sg:postcode":"16149",
    "sg:province":"Genova",
    "wof:name":"Inoflex (s.r.l.)",
    "wof:placetype":"venue"
},
  "geometry": {"coordinates":[8.8967428207,44.446269989],"type":"Point"}
}