{
  "type": "Feature",
  "properties": {
    "addr:full":"06080 Perugia PG",
    "addr:postcode":"06080",
    "addr:street":"Pg",
    "iso:country":"IT",
    "sg:address":"06080 Perugia",
    "sg:orig_category":"Articoli Regalo - Vendita Al Dettaglio",
    "sg:phone":"+39 075 599 6044",
    "sg:province":"PG",
    "wof:name":"Imago Grafica Snc",
    "wof:placetype":"venue"
},
  "geometry": {"coordinates":[12.479795,43.086018],"type":"Point"}
}