{
  "type": "Feature",
  "properties": {
    "iso:country":"IT",
    "sg:address":"24044 Dalmine",
    "sg:city":"Dalmine",
    "sg:orig_category":"Automobili E Mezzi Di Trasporto",
    "sg:phone":"+39 035 561390",
    "sg:postcode":"24044",
    "sg:province":"Bergamo",
    "wof:name":"Auto Industriale Bergamasca Spa",
    "wof:placetype":"venue"
},
  "geometry": {"coordinates":[9.628035,45.648403],"type":"Point"}
}