{
  "type": "Feature",
  "properties": {
    "iso:country":"IT",
    "sg:address":"20019 Settimo Milanese",
    "sg:city":"Settimo Milanese",
    "sg:orig_category":"Abrasivi",
    "sg:phone":"+39 02 328 2000",
    "sg:postcode":"20019",
    "sg:province":"Milano",
    "wof:name":"Vm Di E. Volpato & C. Sas",
    "wof:placetype":"venue"
},
  "geometry": {"coordinates":[9.061002,45.473225],"type":"Point"}
}