{
  "type": "Feature",
  "properties": {
    "iso:country":"IT",
    "sg:address":"2/e, Via Industrie 31040 Nervesa Della Battaglia",
    "sg:city":"Nervesa della Battaglia",
    "sg:classifiers":[
        {
            "category":"Home & Garden",
            "subcategory":"Home Furnishings",
            "type":"Retail Goods"
        }
    ],
    "sg:phone":"+39 0422 773043",
    "sg:postcode":"31040",
    "sg:province":"Treviso",
    "sg:tags":[
        "household"
    ],
    "wof:name":"Industria Cornici D'arte (s.r.l.)",
    "wof:placetype":"venue"
},
  "geometry": {"coordinates":[12.242072,45.666286],"type":"Point"}
}