{
  "type": "Feature",
  "properties": {
    "iso:country":"IT",
    "sg:address":"Via Schiavonesca Nuova 41 31040 Volpago Del Montello",
    "sg:city":"Volpago del Montello",
    "sg:classifiers":[
        {
            "category":"Military Area",
            "subcategory":"Coast Guard Base",
            "type":"Public Place"
        }
    ],
    "sg:phone":"+39 0423 620311",
    "sg:postcode":"31040",
    "sg:province":"Treviso",
    "sg:tags":[
        "gear",
        "rack"
    ],
    "sg:website":"www.zanattagroup.it",
    "wof:name":"Romeo Zanatta & C. Snc",
    "wof:placetype":"venue"
},
  "geometry": {"coordinates":[12.17217,45.728268],"type":"Point"}
}