{
  "type": "Feature",
  "properties": {
    "iso:country":"IT",
    "sg:address":"94, Via Europa 06083 Bastia",
    "sg:city":"Bastia",
    "sg:classifiers":[
        {
            "category":"Farming",
            "subcategory":"Livestock Farm",
            "type":"Manufacturing & Wholesale Goods"
        }
    ],
    "sg:phone":"+39 075 801 0198",
    "sg:postcode":"06083",
    "sg:province":"Perugia",
    "sg:tags":[
        "agriculture"
    ],
    "wof:name":"Dondi S.r.l.",
    "wof:placetype":"venue"
},
  "geometry": {"coordinates":[12.526342,43.083183],"type":"Point"}
}