{
  "type": "Feature",
  "properties": {
    "iso:country":"IT",
    "sg:address":"10043 Orbassano",
    "sg:city":"Orbassano",
    "sg:orig_category":"Fonderie Pressofusione",
    "sg:phone":"+39 011 903 2091",
    "sg:postcode":"10043",
    "sg:province":"Torino",
    "wof:name":"Metfon Snc",
    "wof:placetype":"venue"
},
  "geometry": {"coordinates":[7.5478730202,45.0084190369],"type":"Point"}
}