{
  "type": "Feature",
  "properties": {
    "addr:full":"40050 Monteveglio Monteveglio Bologna 40050",
    "addr:postcode":"40050;40050",
    "iso:country":"IT",
    "sg:address":"40050 Monteveglio",
    "sg:city":"Monteveglio",
    "sg:orig_category":"Serigrafia",
    "sg:phone":"+39 051 960817",
    "sg:postcode":"40050",
    "sg:province":"Bologna",
    "wof:name":"Stamperia Coral Snc Di Marra Maria & C.",
    "wof:placetype":"venue"
},
  "geometry": {"coordinates":[11.101873,44.471668],"type":"Point"}
}