{
  "type": "Feature",
  "properties": {
    "iso:country":"IT",
    "sg:address":"Via R. Sanzio, 33/35 20021 Bollate",
    "sg:city":"Bollate",
    "sg:classifiers":[
        {
            "category":"Wholesale",
            "subcategory":"Office Equipment",
            "type":"Manufacturing & Wholesale Goods"
        }
    ],
    "sg:phone":"+39 02 351 0345",
    "sg:postcode":"20021",
    "sg:province":"Milano",
    "sg:tags":[
        "packaging",
        "corrugated",
        "cardboard",
        "punched"
    ],
    "wof:name":"Scatolificio Messa F.lli Snc",
    "wof:placetype":"venue"
},
  "geometry": {"coordinates":[9.1462593079,45.5637435913],"type":"Point"}
}