{
  "type": "Feature",
  "properties": {
    "iso:country":"IT",
    "sg:address":"22030 Longone Al Segrino",
    "sg:city":"Eupilio",
    "sg:orig_category":"Servizi E Lavori Per Abbigliamento E Pelletterie",
    "sg:phone":"+39 031 640155",
    "sg:postcode":"22030",
    "sg:province":"Como",
    "wof:name":"Redaelli Giovanni",
    "wof:placetype":"venue"
},
  "geometry": {"coordinates":[9.249585,45.818813],"type":"Point"}
}