{
  "type": "Feature",
  "properties": {
    "iso:country":"IT",
    "sg:address":"44100 Ferrara",
    "sg:city":"Ferrara",
    "sg:orig_category":"Servizi Di Magazzinaggio E Movimentazione. Servizi Ausiliari Di Sorveglianza, Manutenzione E Pulizia",
    "sg:phone":"+39 0532 56571",
    "sg:postcode":"44100",
    "sg:province":"Ferrara",
    "wof:name":"Coop. Co.se.f. Soc.coop.r.l.",
    "wof:placetype":"venue"
},
  "geometry": {"coordinates":[11.641193,44.816753],"type":"Point"}
}