{
  "type": "Feature",
  "properties": {
    "iso:country":"IT",
    "sg:address":"00060 Capena",
    "sg:city":"Capena",
    "sg:orig_category":"Materiali E Componenti Elettronici",
    "sg:phone":"+39 06 9038 0504",
    "sg:postcode":"00060",
    "sg:province":"Roma",
    "wof:name":"Elco Electronic Components Italiana Spa",
    "wof:placetype":"venue"
},
  "geometry": {"coordinates":[12.599704,42.090946],"type":"Point"}
}