{
  "type": "Feature",
  "properties": {
    "iso:country":"IT",
    "sg:address":"00172 Roma",
    "sg:city":"Roma",
    "sg:orig_category":"Prodotti Alimentari",
    "sg:phone":"+39 06 241 1141",
    "sg:postcode":"00172",
    "sg:province":"Roma",
    "wof:name":"Casaburi Mario",
    "wof:placetype":"venue"
},
  "geometry": {"coordinates":[12.6204042435,41.7066726685],"type":"Point"}
}