{
  "type": "Feature",
  "properties": {
    "iso:country":"IT",
    "sg:address":"46042 Castel Goffredo",
    "sg:city":"Castel Goffredo",
    "sg:orig_category":"Calze E Collants - Produzione E Ingrosso",
    "sg:phone":"+39 0376 770836",
    "sg:postcode":"46042",
    "sg:province":"Mantova",
    "wof:name":"Danasi Aldo - Manifattura Daniel",
    "wof:placetype":"venue"
},
  "geometry": {"coordinates":[10.46656,45.285118],"type":"Point"}
}