{
  "type": "Feature",
  "properties": {
    "iso:country":"IT",
    "sg:address":"31015 Conegliano",
    "sg:city":"Conegliano",
    "sg:orig_category":"Apparecchiature Ed Attrezzature Meccaniche. Elettronica Industriale, Prodotti E Apparecchiature",
    "sg:phone":"+39 0438 410419",
    "sg:postcode":"31015",
    "sg:province":"Treviso",
    "wof:name":"Ceschin Impianti Elettrici Snc",
    "wof:placetype":"venue"
},
  "geometry": {"coordinates":[12.212324,45.685944],"type":"Point"}
}