{
  "type": "Feature",
  "properties": {
    "addr:full":"20125 Milano Milano Milano 20125",
    "addr:postcode":"20125;20125",
    "iso:country":"IT",
    "sg:address":"20125 Milano",
    "sg:city":"Milano",
    "sg:orig_category":"Forniture Per Edilizia E Lavori Pubblici. Forniture Per Attivita' Industriali",
    "sg:phone":"+39 02 6698 0366",
    "sg:postcode":"20125",
    "sg:province":"Milano",
    "wof:name":"Rabolini Ovidio",
    "wof:placetype":"venue"
},
  "geometry": {"coordinates":[9.2051057816,45.4884376526],"type":"Point"}
}