{
  "type": "Feature",
  "properties": {
    "iso:country":"IT",
    "sg:address":"20099 Sesto San Giovanni",
    "sg:city":"Sesto San Giovanni",
    "sg:orig_category":"Pubblica Amministrazione",
    "sg:phone":"+39 02 244 0045",
    "sg:postcode":"20099",
    "sg:province":"Milano",
    "wof:name":"Municipio Di Sesto S. Giovanni/numeri Telefonici Diretti",
    "wof:placetype":"venue"
},
  "geometry": {"coordinates":[9.2335319519,45.5333061218],"type":"Point"}
}