{
  "type": "Feature",
  "properties": {
    "addr:full":"21, Rione Pollenza Scalo 62010 Pollenza Pollenza Macerata 62010",
    "addr:housenumber":"21",
    "addr:postcode":"62010;62010",
    "addr:street":"Rione Pollenza Scalo",
    "iso:country":"IT",
    "sg:address":"21, Rione Pollenza Scalo 62010 Pollenza",
    "sg:city":"Pollenza",
    "sg:classifiers":[
        {
            "category":"Shopping",
            "type":"Retail Goods"
        }
    ],
    "sg:phone":"+39 0733 203645",
    "sg:postcode":"62010",
    "sg:province":"Macerata",
    "sg:tags":[
        "finished",
        "-",
        "metallic"
    ],
    "wof:name":"Montiplast S.r.l.",
    "wof:placetype":"venue"
},
  "geometry": {"coordinates":[13.3716392517,43.2409362793],"type":"Point"}
}