{
  "type": "Feature",
  "properties": {
    "iso:country":"IT",
    "sg:address":"Via Piave 61-63; Codroipo; 33033",
    "sg:city":"Codroipo",
    "sg:classifiers":[
        {
            "category":"Banks & Credit Unions",
            "subcategory":"Bank",
            "type":"Services"
        }
    ],
    "sg:phone":"+39 0432 905418",
    "sg:postcode":"33033",
    "sg:province":"Udine",
    "wof:name":"Cassa Di Risparmio Di Gorizia Spa",
    "wof:placetype":"venue"
},
  "geometry": {"coordinates":[12.974628,45.962048],"type":"Point"}
}