{
  "type": "Feature",
  "properties": {
    "iso:country":"IT",
    "sg:address":"Via Campania 20090 Segrate",
    "sg:city":"Segrate",
    "sg:classifiers":[
        {
            "category":"Wholesale",
            "subcategory":"Drugs",
            "type":"Manufacturing & Wholesale Goods"
        }
    ],
    "sg:phone":"+39 39022133283",
    "sg:postcode":"20090",
    "sg:province":"Milano",
    "sg:tags":[
        "chemical",
        "pharmaceutical"
    ],
    "wof:name":"Tavecchio L. E C. (s.r.l.)",
    "wof:placetype":"venue"
},
  "geometry": {"coordinates":[9.274627,45.486275],"type":"Point"}
}