{
  "type": "Feature",
  "properties": {
    "iso:country":"IT",
    "sg:address":"14, Str. Marziana 27020 Parona",
    "sg:city":"Parona",
    "sg:classifiers":[
        {
            "category":"Manufacturing",
            "subcategory":"Paper Products",
            "type":"Manufacturing & Wholesale Goods"
        }
    ],
    "sg:phone":"+39 0384 253133",
    "sg:postcode":"27020",
    "sg:province":"Pavia",
    "sg:tags":[
        "cardboard"
    ],
    "wof:name":"Luxoro Deposito Srl",
    "wof:placetype":"venue"
},
  "geometry": {"coordinates":[9.1565628052,45.1858863831],"type":"Point"}
}