{
  "type": "Feature",
  "properties": {
    "addr:full":"6, Via Dell' Artigianato 36050 Montorso Vicentino Montorso Vicentino Vicenza 36050",
    "addr:postcode":"36050;36050",
    "addr:street":"Via Dell ' Artigianato;Vicentino;Vicentino",
    "iso:country":"IT",
    "sg:address":"6, Via Dell' Artigianato 36050 Montorso Vicentino",
    "sg:city":"Montorso Vicentino",
    "sg:classifiers":[
        {
            "category":"Manufacturing",
            "subcategory":"Textiles",
            "type":"Manufacturing & Wholesale Goods"
        }
    ],
    "sg:phone":"+39 0444 685838",
    "sg:postcode":"36050",
    "sg:province":"Vicenza",
    "sg:tags":[
        "leather",
        "raw",
        "material",
        "-"
    ],
    "wof:name":"F.lli Bettega & Priante Di Bettega Giorgio & C. Snc",
    "wof:placetype":"venue"
},
  "geometry": {"coordinates":[11.402923,45.497093],"type":"Point"}
}