{
  "type": "Feature",
  "properties": {
    "iso:country":"IT",
    "sg:address":"20035 Lissone",
    "sg:city":"Lissone",
    "sg:orig_category":"Riparazione Dei Mezzi Di Trasporto",
    "sg:phone":"+39 039 465270",
    "sg:postcode":"20035",
    "sg:province":"Milano",
    "wof:name":"Autotecnica Granetto Snc",
    "wof:placetype":"venue"
},
  "geometry": {"coordinates":[9.240172,45.62035],"type":"Point"}
}