{
  "type": "Feature",
  "properties": {
    "addr:full":"57021 Campiglia Marittima Campiglia Marittima Livorno 57021",
    "addr:postcode":"57021;57021",
    "iso:country":"IT",
    "sg:address":"57021 Campiglia Marittima",
    "sg:city":"Campiglia Marittima",
    "sg:orig_category":"Agenzie Marittime",
    "sg:phone":"+39 0565 850600",
    "sg:postcode":"57021",
    "sg:province":"Livorno",
    "wof:name":"Picasso Viaggi",
    "wof:placetype":"venue"
},
  "geometry": {"coordinates":[10.601763,43.02882],"type":"Point"}
}