{
  "type": "Feature",
  "properties": {
    "addr:full":"00152 Roma Roma Roma 00152",
    "addr:postcode":"00152;00152",
    "iso:country":"IT",
    "sg:address":"00152 Roma",
    "sg:city":"Roma",
    "sg:orig_category":"Trasporti E Spedizioni Merci",
    "sg:phone":"+39 06 6567 1428",
    "sg:postcode":"00152",
    "sg:province":"Roma",
    "sg:website":"http://www.paginegialle.it/hdr",
    "wof:name":"Hand Delivery Roma A R.l.",
    "wof:placetype":"venue"
},
  "geometry": {"coordinates":[12.412872,41.846653],"type":"Point"}
}