{
  "type": "Feature",
  "properties": {
    "addr:full":"Via Pomposa 123; Ferrara",
    "addr:housenumber":"123",
    "addr:street":"Via Pomposa",
    "iso:country":"IT",
    "sg:address":"Via Pomposa 123; Ferrara",
    "sg:classifiers":[
        {
            "category":"Banks & Credit Unions",
            "subcategory":"Bank",
            "type":"Services"
        }
    ],
    "sg:phone":"+39 0532 742070",
    "wof:name":"Cassa Di Risparmio In Bologna Spa",
    "wof:placetype":"venue"
},
  "geometry": {"coordinates":[12.146554,44.765495],"type":"Point"}
}