{
  "type": "Feature",
  "properties": {
    "iso:country":"IT",
    "sg:address":"80133 Napoli",
    "sg:city":"Napoli",
    "sg:orig_category":"Servizi Culturali E Per Lo Spettacolo. Servizi Al Turismo. Acqua, Luce, Gas E Societa' Di Esercizio Pubblico",
    "sg:phone":"+39 081 552 0468",
    "sg:postcode":"80133",
    "sg:province":"Napoli",
    "wof:name":"Instituto Cervantes",
    "wof:placetype":"venue"
},
  "geometry": {"coordinates":[14.2507,40.843193],"type":"Point"}
}