{
  "type": "Feature",
  "properties": {
    "addr:full":"Via Caduti Sul Lavoro 25033 Cologne Cologne Brescia 25033",
    "addr:postcode":"25033;25033",
    "addr:street":"Via Caduti Sul Lavoro",
    "iso:country":"IT",
    "sg:address":"Via Caduti Sul Lavoro 25033 Cologne",
    "sg:city":"Cologne",
    "sg:classifiers":[
        {
            "category":"Home & Garden",
            "subcategory":"Home Furnishings",
            "type":"Retail Goods"
        }
    ],
    "sg:phone":"+39 030 705 0026",
    "sg:postcode":"25033",
    "sg:province":"Brescia",
    "sg:tags":[
        "household"
    ],
    "wof:name":"Besana (s.r.l.)",
    "wof:placetype":"venue"
},
  "geometry": {"coordinates":[9.945464,45.570671],"type":"Point"}
}