{
  "type": "Feature",
  "properties": {
    "addr:full":"00171 Roma Roma Roma 00171",
    "addr:postcode":"00171;00171",
    "iso:country":"IT",
    "sg:address":"00171 Roma",
    "sg:city":"Roma",
    "sg:orig_category":"Servizi E Lavori Per Edilizia E Lavori Pubblici",
    "sg:phone":"+39 06 2189 3770",
    "sg:postcode":"00171",
    "sg:province":"Roma",
    "wof:name":"Eurorestauri Edili Di David Arnold",
    "wof:placetype":"venue"
},
  "geometry": {"coordinates":[12.561559,41.888611],"type":"Point"}
}