{
  "type": "Feature",
  "properties": {
    "iso:country":"IT",
    "sg:address":"1, Via San Barnaba 20010 Casorezzo",
    "sg:city":"Casorezzo",
    "sg:classifiers":[
        {
            "category":"Bars & Pubs",
            "subcategory":"Nightclub",
            "type":"Food & Drink"
        }
    ],
    "sg:phone":"+39 02 9029 6229",
    "sg:postcode":"20010",
    "sg:province":"Milano",
    "sg:tags":[
        "cake",
        "bread"
    ],
    "wof:name":"Pandal Srl",
    "wof:placetype":"venue"
},
  "geometry": {"coordinates":[8.908398,45.52071],"type":"Point"}
}