{
  "type": "Feature",
  "properties": {
    "iso:country":"IT",
    "sg:address":"36075 Montecchio Maggiore",
    "sg:city":"Montecchio Maggiore",
    "sg:orig_category":"Macchine Ed Impianti Per Edilizia E Lavori Pubblici. Macchine, Strumenti Ed Apparecchi Per Attivita' Industriali",
    "sg:phone":"+39 0444 493494",
    "sg:postcode":"36075",
    "sg:province":"Vicenza",
    "wof:name":"Revimac Srl",
    "wof:placetype":"venue"
},
  "geometry": {"coordinates":[11.405453,45.513783],"type":"Point"}
}