{
  "type": "Feature",
  "properties": {
    "addr:full":"24, Via Umbria 50052 Certaldo Certaldo Firenze 50052",
    "addr:postcode":"50052;50052",
    "addr:street":"Via Umbria",
    "iso:country":"IT",
    "sg:address":"24, Via Umbria 50052 Certaldo",
    "sg:city":"Certaldo",
    "sg:classifiers":[
        {
            "category":"Manufacturing",
            "subcategory":"Paper Products",
            "type":"Manufacturing & Wholesale Goods"
        }
    ],
    "sg:phone":"+39 0571 666146",
    "sg:postcode":"50052",
    "sg:province":"Firenze",
    "sg:tags":[
        "cardboard"
    ],
    "wof:name":"Centro Imballaggi (s.r.l.)",
    "wof:placetype":"venue"
},
  "geometry": {"coordinates":[11.0267095566,43.5628051758],"type":"Point"}
}