{
  "type": "Feature",
  "properties": {
    "iso:country":"IT",
    "sg:address":"25124 Brescia",
    "sg:city":"Brescia",
    "sg:orig_category":"Metalli Non Ferrosi E Leghe",
    "sg:phone":"+39 030 351 3411",
    "sg:postcode":"25124",
    "sg:province":"Brescia",
    "sg:website":"http://www.eredignutti.it",
    "wof:name":"S.a. Eredi Gnutti Metalli Spa",
    "wof:placetype":"venue"
},
  "geometry": {"coordinates":[10.214761734,45.5266609192],"type":"Point"}
}