{
  "type": "Feature",
  "properties": {
    "iso:country":"IT",
    "sg:address":"25123 Brescia",
    "sg:city":"Brescia",
    "sg:orig_category":"Valvole E Apparecchiature Di Misura",
    "sg:phone":"+39 030 300046",
    "sg:postcode":"25123",
    "sg:province":"Brescia",
    "wof:name":"Pialorsi Giannantonio",
    "wof:placetype":"venue"
},
  "geometry": {"coordinates":[10.227466,45.554096],"type":"Point"}
}