{
  "type": "Feature",
  "properties": {
    "addr:full":"34018 San Dorligo Della Valle San Dorligo della Valle Trieste 34018",
    "addr:postcode":"34018;dorligo della valle san;34018",
    "addr:street":"San",
    "iso:country":"IT",
    "sg:address":"34018 San Dorligo Della Valle",
    "sg:city":"San Dorligo della Valle",
    "sg:orig_category":"Prodotti E Manufatti In Materie Plastiche",
    "sg:phone":"+39 040 820144",
    "sg:postcode":"34018",
    "sg:province":"Trieste",
    "wof:name":"Plastidite (s.p.a.)",
    "wof:placetype":"venue"
},
  "geometry": {"coordinates":[13.8441905975,45.6049423218],"type":"Point"}
}