{
  "type": "Feature",
  "properties": {
    "addr:full":"15, V. Della Pescaia 56032 Cascine Di Buti Buti Pisa 56032",
    "addr:housenumber":"15",
    "addr:postcode":"56032;56032",
    "addr:street":"V. Della Pescaia",
    "iso:country":"IT",
    "sg:address":"15, V. Della Pescaia 56032 Cascine Di Buti",
    "sg:city":"Buti",
    "sg:orig_category":"Miscellaneous Products",
    "sg:phone":"+39 0587 722014",
    "sg:postcode":"56032",
    "sg:province":"Pisa",
    "sg:website":"http://www.paginegialle.it/duebsas",
    "wof:name":"Due B Cose Antiche",
    "wof:placetype":"venue"
},
  "geometry": {"coordinates":[10.3965845108,43.7161369324],"type":"Point"}
}