{
  "type": "Feature",
  "properties": {
    "iso:country":"IT",
    "sg:address":"80035 Nola",
    "sg:city":"Nola",
    "sg:orig_category":"Vetro: Prodotti E Lavorazioni. Forniture Per Attivita' Industriali",
    "sg:phone":"+39 081 823 4182",
    "sg:postcode":"80035",
    "sg:province":"Napoli",
    "sg:website":"http://www.mercogliano.it",
    "wof:name":"G & C Mercogliano Snc Di Giovanni E Carlo Mercogliano 'vetrai In Nola'",
    "wof:placetype":"venue"
},
  "geometry": {"coordinates":[14.513097,40.933453],"type":"Point"}
}