{
  "type": "Feature",
  "properties": {
    "iso:country":"IT",
    "sg:address":"20090 Buccinasco",
    "sg:city":"Buccinasco",
    "sg:orig_category":"Prodotti Chimici Di Base",
    "sg:phone":"+39 02 457911",
    "sg:postcode":"20090",
    "sg:province":"Milano",
    "wof:name":"Tillmanns S.p.a.",
    "wof:placetype":"venue"
},
  "geometry": {"coordinates":[9.100317955,45.409576416],"type":"Point"}
}