{
  "type": "Feature",
  "properties": {
    "iso:country":"IT",
    "sg:address":"45026 Lendinara",
    "sg:city":"Lendinara",
    "sg:orig_category":"Macchine, Impianti E Forniture Per Industria Grafica, Cartaria E Cartotecnica. Automazione E Macchine Per Ufficio",
    "sg:phone":"+39 0425 601676",
    "sg:postcode":"45026",
    "sg:province":"Rovigo",
    "wof:name":"Gamma Copie",
    "wof:placetype":"venue"
},
  "geometry": {"coordinates":[11.591523,45.07663],"type":"Point"}
}