{
  "type": "Feature",
  "properties": {
    "iso:country":"IT",
    "sg:address":"46019 Viadana",
    "sg:city":"Viadana",
    "sg:orig_category":"Coperte E Copriletti",
    "sg:phone":"+39 0375 830121",
    "sg:postcode":"46019",
    "sg:province":"Mantova",
    "sg:website":"http://www.dondi.it",
    "wof:name":"Dondi Finanziaria Spa",
    "wof:placetype":"venue"
},
  "geometry": {"coordinates":[10.525985,44.944809],"type":"Point"}
}