{
  "type": "Feature",
  "properties": {
    "iso:country":"IT",
    "sg:address":"Via Scopari 15 80047 San Giuseppe Vesuviano",
    "sg:city":"San Giuseppe Vesuviano",
    "sg:orig_category":"Menswear, Suits, Trousers, Sports Jackets",
    "sg:phone":"+39 081 529 5049",
    "sg:postcode":"80047",
    "sg:province":"Napoli",
    "wof:name":"Annunziata Fioravante Srl",
    "wof:placetype":"venue"
},
  "geometry": {"coordinates":[14.4950056076,40.8360061646],"type":"Point"}
}