{
  "type": "Feature",
  "properties": {
    "addr:full":"17, Viale Ravenna 48024 Massa Lombarda Massa Lombarda Ravenna 48024",
    "addr:housenumber":"17",
    "addr:postcode":"48024;48024",
    "addr:street":"Viale Ravenna",
    "iso:country":"IT",
    "sg:address":"17, Viale Ravenna 48024 Massa Lombarda",
    "sg:city":"Massa Lombarda",
    "sg:classifiers":[
        {
            "category":"Farming",
            "subcategory":"Livestock Farm",
            "type":"Manufacturing & Wholesale Goods"
        }
    ],
    "sg:phone":"+39 39054582428",
    "sg:postcode":"48024",
    "sg:province":"Ravenna",
    "sg:tags":[
        "agriculture"
    ],
    "wof:name":"Bagnaresi Fausto",
    "wof:placetype":"venue"
},
  "geometry": {"coordinates":[11.842017,44.446041],"type":"Point"}
}