{
  "type": "Feature",
  "properties": {
    "iso:country":"IT",
    "sg:address":"00141 Roma",
    "sg:city":"Roma",
    "sg:orig_category":"Servizi Al Turismo. Ambasciate Ed Enti Internazionali",
    "sg:phone":"+39 06 818 9762",
    "sg:postcode":"00141",
    "sg:province":"Roma",
    "wof:name":"Ambasciata Presso Lo Stato Italiano India",
    "wof:placetype":"venue"
},
  "geometry": {"coordinates":[12.534286,41.939575],"type":"Point"}
}