{
  "type": "Feature",
  "properties": {
    "iso:country":"IT",
    "sg:address":"Via Burlamacchi 2; Milano; 20135",
    "sg:city":"Milano",
    "sg:classifiers":[
        {
            "category":"Banks & Credit Unions",
            "subcategory":"Bank",
            "type":"Services"
        }
    ],
    "sg:phone":"+39 02 585250",
    "sg:postcode":"20135",
    "sg:province":"Milano",
    "wof:name":"Banca Agricola Milanese Spa",
    "wof:placetype":"venue"
},
  "geometry": {"coordinates":[9.205458,45.450542],"type":"Point"}
}