{
  "type": "Feature",
  "properties": {
    "iso:country":"IT",
    "sg:address":"24, Strada Bagnolo 27055 Rivanazzano",
    "sg:city":"Rivanazzano",
    "sg:classifiers":[
        {
            "category":"Professional",
            "subcategory":"Engineering",
            "type":"Services"
        }
    ],
    "sg:phone":"+39 39038391950",
    "sg:postcode":"27055",
    "sg:province":"Pavia",
    "sg:tags":[
        "machine",
        "-",
        "mechanical"
    ],
    "wof:name":"G M G Lathes Srl",
    "wof:placetype":"venue"
},
  "geometry": {"coordinates":[9.010653,44.935013],"type":"Point"}
}