{
  "type": "Feature",
  "properties": {
    "addr:full":"20017 Rho Rho Milano 20017",
    "addr:postcode":"20017;20017",
    "iso:country":"IT",
    "sg:address":"20017 Rho",
    "sg:city":"Rho",
    "sg:orig_category":"Prodotti Di Base E Forniture Per Industria Alimentare E Bevande",
    "sg:phone":"+39 02 930 1751",
    "sg:postcode":"20017",
    "sg:province":"Milano",
    "wof:name":"Confalonieri Giulio",
    "wof:placetype":"venue"
},
  "geometry": {"coordinates":[9.1445007324,45.5341911316],"type":"Point"}
}