{
  "type": "Feature",
  "properties": {
    "addr:full":"00187 Roma Roma Roma 00187",
    "addr:postcode":"00187;00187",
    "iso:country":"IT",
    "sg:address":"00187 Roma",
    "sg:city":"Roma",
    "sg:classifiers":[
        {
            "category":"Travel",
            "subcategory":"Travel Agent",
            "type":"Entertainment"
        }
    ],
    "sg:phone":"+39 0765 455292",
    "sg:postcode":"00187",
    "sg:province":"Roma",
    "sg:tags":[
        "operator",
        "tour",
        "tourist"
    ],
    "wof:name":"Hotel Planning Soc. Coop. A R.l.",
    "wof:placetype":"venue"
},
  "geometry": {"coordinates":[12.488222,41.906181],"type":"Point"}
}