{
  "type": "Feature",
  "properties": {
    "iso:country":"IT",
    "sg:address":"15067 Novi Ligure",
    "sg:city":"Novi Ligure",
    "sg:orig_category":"Ottica Apparecchi E Strumenti - Produzione E Ingrosso",
    "sg:phone":"+39 0143 2731",
    "sg:postcode":"15067",
    "sg:province":"Alessandria",
    "wof:name":"Pastorelli Ottico - Optometrista Di M. Pastorelli & C. Sas",
    "wof:placetype":"venue"
},
  "geometry": {"coordinates":[8.787167,44.761768],"type":"Point"}
}