{
  "type": "Feature",
  "properties": {
    "iso:country":"IT",
    "sg:address":"Via Oberdan 21/23; Mantova; 46100",
    "sg:city":"Mantova",
    "sg:classifiers":[
        {
            "category":"Banks & Credit Unions",
            "subcategory":"Bank",
            "type":"Services"
        }
    ],
    "sg:phone":"+39 0376 2411",
    "sg:postcode":"46100",
    "sg:province":"Mantova",
    "wof:name":"Cassa Di Risparmio Di Parma, E Piacenza Spa",
    "wof:placetype":"venue"
},
  "geometry": {"coordinates":[10.79158,45.158154],"type":"Point"}
}