{
  "type": "Feature",
  "properties": {
    "iso:country":"IT",
    "sg:address":"62100 Macerata",
    "sg:city":"Macerata",
    "sg:orig_category":"Servizi Ausiliari Di Sorveglianza, Manutenzione E Pulizia",
    "sg:phone":"+39 0733 281706",
    "sg:postcode":"62100",
    "sg:province":"Macerata",
    "wof:name":"Mattioli Sicurgroup Srl",
    "wof:placetype":"venue"
},
  "geometry": {"coordinates":[13.428059,43.28381],"type":"Point"}
}