{
  "type": "Feature",
  "properties": {
    "addr:full":"06063 Magione Magione Perugia 06063",
    "addr:postcode":"06063;06063",
    "iso:country":"IT",
    "sg:address":"06063 Magione",
    "sg:city":"Magione",
    "sg:classifiers":[
        {
            "category":"Home & Garden",
            "subcategory":"Building Materials",
            "type":"Retail Goods"
        }
    ],
    "sg:phone":"+39 075 848039",
    "sg:postcode":"06063",
    "sg:province":"Perugia",
    "sg:tags":[
        "case",
        "bungalow",
        "e",
        "prefabbricate"
    ],
    "wof:name":"Arredogarden",
    "wof:placetype":"venue"
},
  "geometry": {"coordinates":[12.159074,43.084557],"type":"Point"}
}