{
  "type": "Feature",
  "properties": {
    "iso:country":"IT",
    "sg:address":"31044 Montebelluna",
    "sg:city":"Montebelluna",
    "sg:orig_category":"Servizi E Lavori Per Ecologia E Smaltimento Rifiuti",
    "sg:phone":"+39 0423 602202",
    "sg:postcode":"31044",
    "sg:province":"Treviso",
    "sg:website":"http://www.acquatech.net",
    "wof:name":"Acquatech Snc Di Chimenton Mauro & C.",
    "wof:placetype":"venue"
},
  "geometry": {"coordinates":[12.078346,45.773216],"type":"Point"}
}