{
  "type": "Feature",
  "properties": {
    "iso:country":"IT",
    "sg:address":"Via Nola 8 80030 Comiziano",
    "sg:city":"Comiziano",
    "sg:orig_category":"Fruit, Candied",
    "sg:phone":"+39 081 825 1139",
    "sg:postcode":"80030",
    "sg:province":"Napoli",
    "wof:name":"Fratelli Santorelli Di Domenico E Santorelli E C Sas",
    "wof:placetype":"venue"
},
  "geometry": {"coordinates":[14.544716835,40.9367599487],"type":"Point"}
}