{
  "type": "Feature",
  "properties": {
    "iso:country":"IT",
    "sg:address":"13882 Vergnasco",
    "sg:city":"Vergnasco",
    "sg:orig_category":"Filati E Materie Prime Tessili",
    "sg:phone":"+39 015 671631",
    "sg:postcode":"13882",
    "sg:province":"Biella",
    "wof:name":"Verlene Di Botto & C. (s.a.s.)",
    "wof:placetype":"venue"
},
  "geometry": {"coordinates":[8.0885686874,45.488986969],"type":"Point"}
}