{
  "type": "Feature",
  "properties": {
    "iso:country":"IT",
    "sg:address":"54033 Carrara",
    "sg:city":"Carrara",
    "sg:orig_category":"Utensili Meccanici E Materiali. Forniture Per Attivita' Industriali",
    "sg:postcode":"54033",
    "sg:province":"Massa-Carrara",
    "wof:name":"Ferriera Di Cittadella Spa",
    "wof:placetype":"venue"
},
  "geometry": {"coordinates":[10.041605,44.053871],"type":"Point"}
}