{
  "type": "Feature",
  "properties": {
    "iso:country":"IT",
    "sg:address":"00152 Roma",
    "sg:city":"Roma",
    "sg:classifiers":[
        {
            "category":"Professional",
            "subcategory":"Printing & Photocopies",
            "type":"Services"
        }
    ],
    "sg:phone":"+39 06 5833 1045",
    "sg:postcode":"00152",
    "sg:province":"Roma",
    "sg:tags":[
        "packaging",
        "setting"
    ],
    "sg:website":"http://www.moody93.com",
    "wof:name":"Moody - Croma Multimedia Srl",
    "wof:placetype":"venue"
},
  "geometry": {"coordinates":[12.456517,41.880642],"type":"Point"}
}