{
  "type": "Feature",
  "properties": {
    "addr:full":"19122 La Spezia SP",
    "addr:housenumber":"19122",
    "iso:country":"IT",
    "sg:address":"19122 La Spezia",
    "sg:orig_category":"Termotecnica E Riscaldamento, Apparecchiature E Servizi",
    "sg:phone":"+39 0187 705030",
    "sg:province":"SP",
    "wof:name":"G.t. Idraulica Snc Di Gianpietri & Tarabella",
    "wof:placetype":"venue"
},
  "geometry": {"coordinates":[9.808967,44.111126],"type":"Point"}
}