{
  "type": "Feature",
  "properties": {
    "addr:full":"63, Via Della Liberazione 20068 Peschiera Borromeo Peschiera Borromeo Milano 20068",
    "addr:postcode":"20068;20068",
    "addr:street":"Via Della Liberazione",
    "iso:country":"IT",
    "sg:address":"63, Via Della Liberazione 20068 Peschiera Borromeo",
    "sg:city":"Peschiera Borromeo",
    "sg:classifiers":[
        {
            "category":"Manufacturing",
            "subcategory":"Rubber & Plastics",
            "type":"Manufacturing & Wholesale Goods"
        }
    ],
    "sg:phone":"+39 39025475575",
    "sg:postcode":"20068",
    "sg:province":"Milano",
    "wof:name":"Cedic (s.r.l.)",
    "wof:placetype":"venue"
},
  "geometry": {"coordinates":[9.3170166016,45.4279289246],"type":"Point"}
}