{
  "type": "Feature",
  "properties": {
    "iso:country":"IT",
    "sg:address":"20014 Nerviano",
    "sg:city":"Nerviano",
    "sg:orig_category":"Macchine, Impianti Ed Attrezzature Industria Delle Materie Plastiche E Gomma",
    "sg:phone":"+39 0331 580274",
    "sg:postcode":"20014",
    "sg:province":"Milano",
    "wof:name":"Gasp Di Franzon Katia",
    "wof:placetype":"venue"
},
  "geometry": {"coordinates":[8.968319,45.546581],"type":"Point"}
}