{
  "type": "Feature",
  "properties": {
    "addr:full":"09081 Ardauli Ardauli Oristano 09081",
    "addr:postcode":"09081;09081",
    "iso:country":"IT",
    "sg:address":"09081 Ardauli",
    "sg:city":"Ardauli",
    "sg:orig_category":"Patatine Fritte E Prodotti Da Snack",
    "sg:phone":"+39 0783 651619",
    "sg:postcode":"09081",
    "sg:province":"Oristano",
    "wof:name":"Su Guttiau Srl",
    "wof:placetype":"venue"
},
  "geometry": {"coordinates":[8.9117431641,40.0861282349],"type":"Point"}
}