{
  "type": "Feature",
  "properties": {
    "iso:country":"IT",
    "sg:address":"69, Via Molini 25017 Lonato",
    "sg:city":"Lonato",
    "sg:classifiers":[
        {
            "category":"Manufacturing",
            "subcategory":"Rubber & Plastics",
            "type":"Manufacturing & Wholesale Goods"
        }
    ],
    "sg:phone":"+39 030 913 2489",
    "sg:postcode":"25017",
    "sg:province":"Brescia",
    "wof:name":"Bampi S.p.a.",
    "wof:placetype":"venue"
},
  "geometry": {"coordinates":[10.4429855347,45.4606056213],"type":"Point"}
}