{
  "type": "Feature",
  "properties": {
    "iso:country":"IT",
    "sg:address":"26, Via Torre 35129 Padova",
    "sg:city":"Padova",
    "sg:classifiers":[
        {
            "category":"Shopping",
            "type":"Retail Goods"
        }
    ],
    "sg:phone":"+39 39049725623",
    "sg:postcode":"35129",
    "sg:province":"Padova",
    "sg:tags":[
        "finished",
        "-",
        "metallic"
    ],
    "wof:name":"Mazzari Giancarlo",
    "wof:placetype":"venue"
},
  "geometry": {"coordinates":[11.9201145172,45.4286460876],"type":"Point"}
}