{
  "type": "Feature",
  "properties": {
    "addr:full":"67100 L'aquila L'Aquila 67100",
    "addr:postcode":"67100;67100",
    "iso:country":"IT",
    "sg:address":"67100 L'aquila",
    "sg:orig_category":"Macchine Ed Impianti Per Edilizia E Lavori Pubblici. Impianti E Attrezzature Per Lo Sport E Il Tempo Libero",
    "sg:phone":"+39 0862 24541",
    "sg:postcode":"67100",
    "sg:province":"L'Aquila",
    "wof:name":"Effegi (s.r.l.)",
    "wof:placetype":"venue"
},
  "geometry": {"coordinates":[13.396106,42.356594],"type":"Point"}
}