{
  "type": "Feature",
  "properties": {
    "iso:country":"IT",
    "sg:address":"45100 Rovigo",
    "sg:city":"Rovigo",
    "sg:orig_category":"Macchine Ed Impianti Per Edilizia E Lavori Pubblici",
    "sg:phone":"+39 0425 474703",
    "sg:postcode":"45100",
    "sg:province":"Rovigo",
    "wof:name":"Rossini Giorgio",
    "wof:placetype":"venue"
},
  "geometry": {"coordinates":[11.780509,45.050468],"type":"Point"}
}