{
  "type": "Feature",
  "properties": {
    "iso:country":"IT",
    "sg:address":"23030 Villa Di Tirano",
    "sg:city":"Villa di Tirano",
    "sg:orig_category":"Manufacturers: Prefabbricati. Forniture Per Edilizia E Lavori Pubblici",
    "sg:phone":"+39 0342 795175",
    "sg:postcode":"23030",
    "sg:province":"Sondrio",
    "wof:name":"Artigiana Costruzioni Snc Di Orgnoni Pasquale & C.",
    "wof:placetype":"venue"
},
  "geometry": {"coordinates":[10.1216316223,46.1951065063],"type":"Point"}
}