{
  "type": "Feature",
  "properties": {
    "addr:full":"Via L. Scotti 1; Barano D'ischia; 80070 Napoli 80070",
    "addr:housenumber":"1",
    "addr:postcode":"80070;80070",
    "addr:street":"Via L. Scotti;D'Ischia",
    "iso:country":"IT",
    "sg:address":"Via L. Scotti 1; Barano D'ischia; 80070",
    "sg:classifiers":[
        {
            "category":"Banks & Credit Unions",
            "subcategory":"Bank",
            "type":"Services"
        }
    ],
    "sg:phone":"+39 081 906182",
    "sg:postcode":"80070",
    "sg:province":"Napoli",
    "wof:name":"Banco Di Napoli Spa",
    "wof:placetype":"venue"
},
  "geometry": {"coordinates":[13.925949,40.716],"type":"Point"}
}