{
  "type": "Feature",
  "properties": {
    "iso:country":"IT",
    "sg:address":"20060 Cassina De'pecchi",
    "sg:orig_category":"Pubblica Amministrazione",
    "sg:phone":"+39 02 9529 9236",
    "sg:postcode":"20060",
    "sg:province":"Milano",
    "wof:name":"Comando Stazione Carabinieri",
    "wof:placetype":"venue"
},
  "geometry": {"coordinates":[9.3288831711,45.5028457642],"type":"Point"}
}