{
  "type": "Feature",
  "properties": {
    "iso:country":"IT",
    "sg:address":"; Trasacco; 67059",
    "sg:classifiers":[
        {
            "category":"Banks & Credit Unions",
            "subcategory":"Bank",
            "type":"Services"
        }
    ],
    "sg:phone":"+39 39086393233",
    "sg:postcode":"67059",
    "sg:province":"L'Aquila",
    "wof:name":"Cassa Di Risparmio Della, Provincia Dell'aquila",
    "wof:placetype":"venue"
},
  "geometry": {"coordinates":[13.532124,41.953384],"type":"Point"}
}