{
  "type": "Feature",
  "properties": {
    "addr:full":"36, Via Barletta 85027 Rapolla Rapolla Potenza 85027",
    "addr:postcode":"85027;85027",
    "addr:street":"Via Barletta",
    "iso:country":"IT",
    "sg:address":"36, Via Barletta 85027 Rapolla",
    "sg:city":"Rapolla",
    "sg:classifiers":[
        {
            "category":"Food & Beverages",
            "subcategory":"Groceries & Convenience Stores",
            "type":"Retail Goods"
        }
    ],
    "sg:phone":"+39 39800258174",
    "sg:postcode":"85027",
    "sg:province":"Potenza",
    "sg:tags":[
        "product",
        "related"
    ],
    "wof:name":"Olearia Giuseppe Lallo",
    "wof:placetype":"venue"
},
  "geometry": {"coordinates":[15.6756563187,40.9779167175],"type":"Point"}
}