{
  "type": "Feature",
  "properties": {
    "addr:full":"10022 Carmagnola Carmagnola Torino 10022",
    "addr:postcode":"10022;10022",
    "iso:country":"IT",
    "sg:address":"10022 Carmagnola",
    "sg:city":"Carmagnola",
    "sg:orig_category":"Fognature",
    "sg:phone":"+39 011 972 2198",
    "sg:postcode":"10022",
    "sg:province":"Torino",
    "sg:website":"http://www.piemonteco.it",
    "wof:name":"Piemonte Spurghi Snc",
    "wof:placetype":"venue"
},
  "geometry": {"coordinates":[7.6269049644,44.82006073],"type":"Point"}
}