{
  "type": "Feature",
  "properties": {
    "iso:country":"IT",
    "sg:address":"162, Strada Provinciale Le Di Golese 43030 Torrile",
    "sg:classifiers":[
        {
            "category":"Food & Beverages",
            "subcategory":"Dairy",
            "type":"Retail Goods"
        }
    ],
    "sg:phone":"+39 0521 520611",
    "sg:postcode":"43030",
    "sg:province":"Parma",
    "sg:tags":[
        "product"
    ],
    "wof:name":"Boni S.p.a.",
    "wof:placetype":"venue"
},
  "geometry": {"coordinates":[10.329548,44.807865],"type":"Point"}
}