{
  "type": "Feature",
  "properties": {
    "addr:full":"45039 Stienta Stienta Rovigo 45039",
    "addr:postcode":"45039;45039",
    "iso:country":"IT",
    "sg:address":"45039 Stienta",
    "sg:city":"Stienta",
    "sg:orig_category":"Macchine, Impianti Ed Attrezzature Per Agricoltura E Zootecnia",
    "sg:phone":"+39 0425 746075",
    "sg:postcode":"45039",
    "sg:province":"Rovigo",
    "sg:website":"http://www.hymach.it",
    "wof:name":"Hymach Srl",
    "wof:placetype":"venue"
},
  "geometry": {"coordinates":[11.559533,44.934235],"type":"Point"}
}