{
  "type": "Feature",
  "properties": {
    "iso:country":"IT",
    "sg:address":"55049 Viareggio",
    "sg:city":"Viareggio",
    "sg:orig_category":"Animali Domestici - Allevamento E Addestramento",
    "sg:phone":"+39 0584 962090",
    "sg:postcode":"55049",
    "sg:province":"Lucca",
    "wof:name":"Bonini Mariella",
    "wof:placetype":"venue"
},
  "geometry": {"coordinates":[10.242864,43.886604],"type":"Point"}
}