{
  "type": "Feature",
  "properties": {
    "iso:country":"IT",
    "sg:address":"16149 Genova",
    "sg:city":"Genova",
    "sg:orig_category":"Servizi Al Turismo. Trasporto Pubblico E Privato",
    "sg:phone":"+39 010 60691",
    "sg:postcode":"16149",
    "sg:province":"Genova",
    "wof:name":"Costa Container Lines Spa",
    "wof:placetype":"venue"
},
  "geometry": {"coordinates":[8.901312,44.407501],"type":"Point"}
}