{
  "type": "Feature",
  "properties": {
    "addr:full":"73100 Lecce Lecce Lecce 73100",
    "addr:postcode":"73100;73100",
    "iso:country":"IT",
    "sg:address":"73100 Lecce",
    "sg:city":"Lecce",
    "sg:orig_category":"Forniture Per Abbigliamento E Pelletterie",
    "sg:phone":"+39 0832 493917",
    "sg:postcode":"73100",
    "sg:province":"Lecce",
    "wof:name":"Italzip Di Rutigliano Loredana",
    "wof:placetype":"venue"
},
  "geometry": {"coordinates":[18.1761016846,40.3613586426],"type":"Point"}
}