{
  "type": "Feature",
  "properties": {
    "iso:country":"IT",
    "sg:address":"20016 Pero",
    "sg:city":"Pero",
    "sg:orig_category":"Metalli E Leghe. Gioielleria, Oreficeria E Argenteria",
    "sg:phone":"+39 02 339 5511",
    "sg:postcode":"20016",
    "sg:province":"Milano",
    "wof:name":"Italbras S.p.a.",
    "wof:placetype":"venue"
},
  "geometry": {"coordinates":[9.0955324173,45.5122070312],"type":"Point"}
}