{
  "type": "Feature",
  "properties": {
    "iso:country":"IT",
    "sg:address":"Via Cozzolino 77 80056 Ercolano",
    "sg:city":"Ercolano",
    "sg:classifiers":[
        {
            "category":"Shopping",
            "subcategory":"Pharmacy",
            "type":"Retail Goods"
        }
    ],
    "sg:phone":"+39 081 777 2746",
    "sg:postcode":"80056",
    "sg:province":"Napoli",
    "sg:tags":[
        "pharmaceutical"
    ],
    "wof:name":"La.fa.re. Srl",
    "wof:placetype":"venue"
},
  "geometry": {"coordinates":[14.3686847687,40.8079872131],"type":"Point"}
}