{
  "type": "Feature",
  "properties": {
    "addr:full":"Strada Statale Asti; Asti; 14037 Asti Asti 14037",
    "addr:postcode":"14037;14037",
    "addr:street":"Strada Statale",
    "iso:country":"IT",
    "sg:address":"Strada Statale Asti; Asti; 14037",
    "sg:city":"Asti",
    "sg:classifiers":[
        {
            "category":"Banks & Credit Unions",
            "subcategory":"Bank",
            "type":"Services"
        }
    ],
    "sg:phone":"+39 0141 410424",
    "sg:postcode":"14037",
    "sg:province":"Asti",
    "wof:name":"Istituto Bancario, San Paolo Di Torino Spa",
    "wof:placetype":"venue"
},
  "geometry": {"coordinates":[8.101562,45.003719],"type":"Point"}
}