{
  "type": "Feature",
  "properties": {
    "addr:full":"00159 Roma Roma Roma 00159",
    "addr:postcode":"00159;00159",
    "iso:country":"IT",
    "sg:address":"00159 Roma",
    "sg:city":"Roma",
    "sg:orig_category":"Forniture Per Edilizia E Lavori Pubblici. Forniture Per Attivita' Industriali",
    "sg:phone":"+39 06 4358 8201",
    "sg:postcode":"00159",
    "sg:province":"Roma",
    "wof:name":"S.a.p.i.g.",
    "wof:placetype":"venue"
},
  "geometry": {"coordinates":[12.5347728729,41.9080924988],"type":"Point"}
}