{
  "type": "Feature",
  "properties": {
    "iso:country":"IT",
    "sg:address":"35128 Padova",
    "sg:city":"Padova",
    "sg:orig_category":"Impiantistica E Prodotti Tecnologici Per Edilizia. Elettronica Professionale E Di Consumo. Accessori Dei Mezzi Di Trasporto. Forniture Industriali Per Prevenzione, Controllo E Sicurezza",
    "sg:phone":"+39 049 775381",
    "sg:postcode":"35128",
    "sg:province":"Padova",
    "sg:website":"http://www.sei-sicurezza.it",
    "wof:name":"S.e.i. Snc",
    "wof:placetype":"venue"
},
  "geometry": {"coordinates":[11.904662,45.3979],"type":"Point"}
}