{
  "type": "Feature",
  "properties": {
    "addr:full":"15057 Tortona Tortona Alessandria 15057",
    "addr:postcode":"15057;15057",
    "iso:country":"IT",
    "sg:address":"15057 Tortona",
    "sg:city":"Tortona",
    "sg:orig_category":"Forniture Per Edilizia E Lavori Pubblici",
    "sg:phone":"+39 0131 870064",
    "sg:postcode":"15057",
    "sg:province":"Alessandria",
    "wof:name":"Generali Costruzioni Srl",
    "wof:placetype":"venue"
},
  "geometry": {"coordinates":[8.8050012589,44.892780304],"type":"Point"}
}