{
  "type": "Feature",
  "properties": {
    "addr:full":"20098 San Giuliano Milanese San Giuliano Milanese Milano 20098",
    "addr:housenumber":"20098",
    "addr:postcode":"20098",
    "addr:street":"San",
    "iso:country":"IT",
    "sg:address":"20098 San Giuliano Milanese",
    "sg:city":"San Giuliano Milanese",
    "sg:orig_category":"Cartotecnica E Servizi. Prodotti E Manufatti In Materie Plastiche. Articoli Per Imballaggio E Confezionamento",
    "sg:phone":"+39 02 988 0379",
    "sg:postcode":"20098",
    "sg:province":"Milano",
    "wof:name":"Facover Srl",
    "wof:placetype":"venue"
},
  "geometry": {"coordinates":[9.25379,45.397049],"type":"Point"}
}