{
  "type": "Feature",
  "properties": {
    "iso:country":"IT",
    "sg:address":"86039 Termoli",
    "sg:city":"Termoli",
    "sg:orig_category":"Articoli Natalizi",
    "sg:phone":"+39 0875 81122",
    "sg:postcode":"86039",
    "sg:province":"Campobasso",
    "wof:name":"Marcovaldo",
    "wof:placetype":"venue"
},
  "geometry": {"coordinates":[14.659891,41.560799],"type":"Point"}
}