{
  "type": "Feature",
  "properties": {
    "addr:full":"56025 Pontedera Pontedera Pisa 56025",
    "addr:postcode":"56025;56025",
    "iso:country":"IT",
    "sg:address":"56025 Pontedera",
    "sg:city":"Pontedera",
    "sg:orig_category":"Prodotti Chimici Secondari. Tempo Libero - Articoli E Forniture. Servizi Per Lo Sport E Il Tempo Libero. Servizi Per Aziende, Manifestazioni E Supporto Agli Scambi Commerciali",
    "sg:phone":"+39 0587 296008",
    "sg:postcode":"56025",
    "sg:province":"Pisa",
    "wof:name":"Maiva Di Scacciati Marzia",
    "wof:placetype":"venue"
},
  "geometry": {"coordinates":[10.5956697464,43.6431694031],"type":"Point"}
}