{
  "type": "Feature",
  "properties": {
    "iso:country":"IT",
    "sg:address":"19038 Sarzana",
    "sg:city":"Sarzana",
    "sg:orig_category":"Campeggio. Automobili E Mezzi Di Trasporto",
    "sg:phone":"+39 0187 627269",
    "sg:postcode":"19038",
    "sg:province":"La Spezia",
    "sg:website":"http://www.lunicaravan.com",
    "wof:name":"Lunicaravan Sas",
    "wof:placetype":"venue"
},
  "geometry": {"coordinates":[9.767869,44.244793],"type":"Point"}
}