{
  "type": "Feature",
  "properties": {
    "iso:country":"IT",
    "sg:address":"101/b, V. Consalvo 80125 Napoli",
    "sg:city":"Napoli",
    "sg:classifiers":[
        {
            "category":"Shopping",
            "subcategory":"Jewelry",
            "type":"Retail Goods"
        }
    ],
    "sg:phone":"+39 081 593 9706",
    "sg:postcode":"80125",
    "sg:province":"Napoli",
    "sg:tags":[
        "jewellery"
    ],
    "sg:website":"http://www.bizzarroonline.com",
    "wof:name":"Shantj",
    "wof:placetype":"venue"
},
  "geometry": {"coordinates":[14.206915,40.831326],"type":"Point"}
}