{
  "type": "Feature",
  "properties": {
    "addr:full":"20021 Baranzate Baranzate Milano 20021",
    "addr:postcode":"20021;20021",
    "iso:country":"IT",
    "sg:address":"20021 Baranzate",
    "sg:city":"Baranzate",
    "sg:orig_category":"Servizi E Lavori Per Abbigliamento E Pelletterie",
    "sg:phone":"+39 02 356 0528",
    "sg:postcode":"20021",
    "sg:province":"Milano",
    "wof:name":"Tintoria Cristina",
    "wof:placetype":"venue"
},
  "geometry": {"coordinates":[9.12215,45.522209],"type":"Point"}
}