{
  "type": "Feature",
  "properties": {
    "iso:country":"IT",
    "sg:address":"Via Cesare Battisti 14, Cremona, Cr",
    "sg:classifiers":[
        {
            "category":"Banks & Credit Unions",
            "subcategory":"Bank",
            "type":"Services"
        }
    ],
    "sg:phone":"+39 0372 4041",
    "sg:website":"http://www.popcremona.it",
    "wof:name":"Banca Popolare Di Cremona Scarl",
    "wof:placetype":"venue"
},
  "geometry": {"coordinates":[10.022989,45.136742],"type":"Point"}
}