{
  "type": "Feature",
  "properties": {
    "addr:full":"9, Via Siemens 41012 Carpi Carpi Modena 41012",
    "addr:postcode":"41012;41012",
    "addr:street":"Via Siemens",
    "iso:country":"IT",
    "sg:address":"9, Via Siemens 41012 Carpi",
    "sg:city":"Carpi",
    "sg:classifiers":[
        {
            "category":"Manufacturing",
            "subcategory":"Rubber & Plastics",
            "type":"Manufacturing & Wholesale Goods"
        }
    ],
    "sg:phone":"+39 39059682065",
    "sg:postcode":"41012",
    "sg:province":"Modena",
    "wof:name":"C.m.s.",
    "wof:placetype":"venue"
},
  "geometry": {"coordinates":[10.9252195358,44.6470794678],"type":"Point"}
}