{
  "type": "Feature",
  "properties": {
    "iso:country":"IT",
    "sg:address":"60010 Ponterio Di Monterado",
    "sg:city":"Monterado",
    "sg:orig_category":"Servizi Per Aziende, Manifestazioni E Supporto Agli Scambi Commerciali",
    "sg:phone":"+39 071 795 0511",
    "sg:postcode":"60010",
    "sg:province":"Ancona",
    "sg:website":"http://www.barberiniallestimenti.it",
    "wof:name":"Barberini Allestimenti Srl",
    "wof:placetype":"venue"
},
  "geometry": {"coordinates":[13.518757,43.615856],"type":"Point"}
}