{
  "type": "Feature",
  "properties": {
    "addr:full":"Via Ostiglia 46100 Mantova Mantova Mantova 46100",
    "addr:postcode":"46100;46100",
    "addr:street":"Via Ostiglia",
    "iso:country":"IT",
    "sg:address":"Via Ostiglia 46100 Mantova",
    "sg:city":"Mantova",
    "sg:classifiers":[
        {
            "category":"Manufacturing",
            "subcategory":"Paper Products",
            "type":"Manufacturing & Wholesale Goods"
        }
    ],
    "sg:phone":"+39 390 376 2381",
    "sg:postcode":"46100",
    "sg:province":"Mantova",
    "sg:tags":[
        "cardboard"
    ],
    "wof:name":"Grossi Carta Mantova Spa",
    "wof:placetype":"venue"
},
  "geometry": {"coordinates":[10.8546085358,45.1382102966],"type":"Point"}
}