{
  "type": "Feature",
  "properties": {
    "iso:country":"IT",
    "sg:address":"Via C\u00e0 Rossa 7/9 20023 Cerro Maggiore",
    "sg:city":"Cerro Maggiore",
    "sg:classifiers":[
        {
            "category":"Shopping",
            "subcategory":"Stationery & Office Supplies",
            "type":"Retail Goods"
        }
    ],
    "sg:phone":"+39 0331 447800",
    "sg:postcode":"20023",
    "sg:province":"Milano",
    "sg:tags":[
        "furniture"
    ],
    "sg:website":"www.sacea.com",
    "wof:name":"Sacea S.p.a.",
    "wof:placetype":"venue"
},
  "geometry": {"coordinates":[9.188141,45.463688],"type":"Point"}
}