{
  "type": "Feature",
  "properties": {
    "iso:country":"IT",
    "sg:address":"37060 Buttapietra",
    "sg:city":"Bovo",
    "sg:orig_category":"Servizi E Lavori Per Industria Alimentare E Bevande",
    "sg:phone":"+39 045 666 0506",
    "sg:postcode":"37060",
    "sg:province":"Verona",
    "wof:name":"Molino Rosso Mirandola S.n.c.",
    "wof:placetype":"venue"
},
  "geometry": {"coordinates":[11.013218,45.349876],"type":"Point"}
}