{
  "type": "Feature",
  "properties": {
    "iso:country":"IT",
    "sg:address":"Strada Provinciale 107n.7 26816 Ossago",
    "sg:classifiers":[
        {
            "category":"Government",
            "subcategory":"Post Office",
            "type":"Public Place"
        }
    ],
    "sg:phone":"+39 0371 289943",
    "sg:postcode":"26816",
    "sg:province":"Lodi",
    "sg:tags":[
        "item",
        "household",
        "design"
    ],
    "sg:website":"www.snips.it",
    "wof:name":"Snips Srl",
    "wof:placetype":"venue"
},
  "geometry": {"coordinates":[9.522606,45.277954],"type":"Point"}
}