{
  "type": "Feature",
  "properties": {
    "addr:full":"20144 Milano Milano Milano 20144",
    "addr:postcode":"20144;20144",
    "iso:country":"IT",
    "sg:address":"20144 Milano",
    "sg:city":"Milano",
    "sg:orig_category":"Professionisti - Studi E Servizi Ed Associazioni Di Interesse Aziendale. Associazioni Ed Organismi Di Interesse Pubblico",
    "sg:phone":"+39 02 4801 2002",
    "sg:postcode":"20144",
    "sg:province":"Milano",
    "wof:name":"A.n.a.c. Associazione Nazionale Allevatori Cavalli Purosangue",
    "wof:placetype":"venue"
},
  "geometry": {"coordinates":[9.163064003,45.4602279663],"type":"Point"}
}