{
  "type": "Feature",
  "properties": {
    "addr:full":"40064 Ozzano Dell'emilia Bologna 40064",
    "addr:postcode":"40064;40064",
    "iso:country":"IT",
    "sg:address":"40064 Ozzano Dell'emilia",
    "sg:orig_category":"Prodotti Chimici Di Base. Prodotti Cosmetici E Da Toeletta",
    "sg:phone":"+39 051 796899",
    "sg:postcode":"40064",
    "sg:province":"Bologna",
    "wof:name":"Deve' Srl",
    "wof:placetype":"venue"
},
  "geometry": {"coordinates":[11.4461460114,44.4561653137],"type":"Point"}
}