{
  "type": "Feature",
  "properties": {
    "iso:country":"IT",
    "sg:address":"37135 Verona",
    "sg:city":"Verona",
    "sg:orig_category":"Apparecchiature E Sistemi Per Magazzinaggio E Movimentazione",
    "sg:phone":"+39 045 501968",
    "sg:postcode":"37135",
    "sg:province":"Verona",
    "wof:name":"Cristanini Leonida",
    "wof:placetype":"venue"
},
  "geometry": {"coordinates":[10.969789,45.407616],"type":"Point"}
}