{
  "type": "Feature",
  "properties": {
    "addr:full":"00194 Roma Roma Roma 00194",
    "addr:postcode":"00194;00194",
    "iso:country":"IT",
    "sg:address":"00194 Roma",
    "sg:city":"Roma",
    "sg:orig_category":"Scuole E Servizi Scolastici. Servizi Per Lo Sport E Il Tempo Libero",
    "sg:phone":"+39 06 329 1640",
    "sg:postcode":"00194",
    "sg:province":"Roma",
    "sg:website":"http://www.scuolavela.com",
    "wof:name":"La Scuola Della Vela",
    "wof:placetype":"venue"
},
  "geometry": {"coordinates":[12.461508,41.947399],"type":"Point"}
}