{
  "type": "Feature",
  "properties": {
    "iso:country":"IT",
    "sg:address":"24121 Bergamo",
    "sg:city":"Bergamo",
    "sg:orig_category":"Serramenti Ed Infissi",
    "sg:phone":"+39 035 249078",
    "sg:postcode":"24121",
    "sg:province":"Bergamo",
    "sg:website":"http://www.saiga-srl.it",
    "wof:name":"Saiga Articoli Tecnici Industriali Srl",
    "wof:placetype":"venue"
},
  "geometry": {"coordinates":[9.674878,45.693245],"type":"Point"}
}