{
  "type": "Feature",
  "properties": {
    "iso:country":"IT",
    "sg:address":"38, Via S. Antonio Inferiore 13831 Mezzana Mortigliengo",
    "sg:city":"Mezzana Mortigliengo",
    "sg:classifiers":[
        {
            "category":"Professional",
            "subcategory":"Engineering",
            "type":"Services"
        }
    ],
    "sg:phone":"+39 39015742201",
    "sg:postcode":"13831",
    "sg:province":"Biella",
    "sg:tags":[
        "machine",
        "-",
        "mechanical"
    ],
    "wof:name":"Comix S.r.l.",
    "wof:placetype":"venue"
},
  "geometry": {"coordinates":[8.05827,45.562836],"type":"Point"}
}