{
  "type": "Feature",
  "properties": {
    "iso:country":"IT",
    "sg:address":"98100 Messina",
    "sg:orig_category":"Agenzie Immobiliari",
    "sg:phone":"+39 090 651 2000",
    "sg:province":"ME",
    "wof:name":"Sindona Immobiliare",
    "wof:placetype":"venue"
},
  "geometry": {"coordinates":[15.551676,38.180782],"type":"Point"}
}