{
  "type": "Feature",
  "properties": {
    "addr:full":"64/68/70, Via Coralli Ugo 40026 Imola Imola Bologna 40026",
    "addr:housenumber":"64 / 68 / 70",
    "addr:postcode":"40026;40026",
    "addr:street":"Via Coralli Ugo",
    "iso:country":"IT",
    "sg:address":"64/68/70, Via Coralli Ugo 40026 Imola",
    "sg:city":"Imola",
    "sg:classifiers":[
        {
            "category":"Utilities",
            "subcategory":"Electric",
            "type":"Services"
        }
    ],
    "sg:phone":"+39 0542 641857",
    "sg:postcode":"40026",
    "sg:province":"Bologna",
    "sg:tags":[
        "component",
        "electronic"
    ],
    "wof:name":"2cs (s.r.l.)",
    "wof:placetype":"venue"
},
  "geometry": {"coordinates":[11.346481,44.494221],"type":"Point"}
}