{
  "type": "Feature",
  "properties": {
    "iso:country":"IT",
    "sg:address":"10098 Rivoli",
    "sg:city":"Cascine vica",
    "sg:orig_category":"Macchine Utensili - Commercio",
    "sg:phone":"+39 011 959 2228",
    "sg:postcode":"10098",
    "sg:province":"Torino",
    "wof:name":"Sirmu Artigiana Snc",
    "wof:placetype":"venue"
},
  "geometry": {"coordinates":[7.559412,45.063061],"type":"Point"}
}