{
  "type": "Feature",
  "properties": {
    "addr:full":"21012 Cassano Magnago Cassano Magnago Varese 21012",
    "addr:postcode":"21012;21012",
    "iso:country":"IT",
    "sg:address":"21012 Cassano Magnago",
    "sg:city":"Cassano Magnago",
    "sg:orig_category":"Cartotecnica",
    "sg:phone":"+39 0331 792059",
    "sg:postcode":"21012",
    "sg:province":"Varese",
    "wof:name":"Dante Bertoni Srl",
    "wof:placetype":"venue"
},
  "geometry": {"coordinates":[8.825473,45.651218],"type":"Point"}
}