{
  "type": "Feature",
  "properties": {
    "iso:country":"IT",
    "sg:address":"00138 Roma",
    "sg:city":"Roma",
    "sg:orig_category":"Macchine, Impianti E Forniture Per Industria Grafica, Cartaria E Cartotecnica. Automazione E Macchine Per Ufficio",
    "sg:phone":"+39 06 880 0950",
    "sg:postcode":"00138",
    "sg:province":"Roma",
    "sg:website":"http://www.ncs-tognetto.it",
    "wof:name":"Ncs Tognetto Srl",
    "wof:placetype":"venue"
},
  "geometry": {"coordinates":[12.512959,41.981155],"type":"Point"}
}