{
  "type": "Feature",
  "properties": {
    "addr:full":"80, Via C. Battisti 21020 Daverio Daverio Varese 21020",
    "addr:postcode":"21020;21020",
    "addr:street":"Via C. Battisti",
    "iso:country":"IT",
    "sg:address":"80, Via C. Battisti 21020 Daverio",
    "sg:city":"Daverio",
    "sg:classifiers":[
        {
            "category":"Food & Beverages",
            "subcategory":"Dairy",
            "type":"Retail Goods"
        }
    ],
    "sg:phone":"+39 0332 949312",
    "sg:postcode":"21020",
    "sg:province":"Varese",
    "sg:tags":[
        "product"
    ],
    "wof:name":"Burrificio Campo Dei Fiori (s.r.l.)",
    "wof:placetype":"venue"
},
  "geometry": {"coordinates":[8.774257,45.769909],"type":"Point"}
}