{
  "type": "Feature",
  "properties": {
    "iso:country":"IT",
    "sg:address":"6, Via Crispi Francesco 51100 Pistoia",
    "sg:city":"Pistoia",
    "sg:classifiers":[
        {
            "category":"Travel",
            "subcategory":"Travel Agent",
            "type":"Entertainment"
        }
    ],
    "sg:phone":"+39 39057325187",
    "sg:postcode":"51100",
    "sg:province":"Pistoia",
    "sg:tags":[
        "business"
    ],
    "wof:name":"Albergo Patria Hotel",
    "wof:placetype":"venue"
},
  "geometry": {"coordinates":[10.918524,43.932156],"type":"Point"}
}