{
  "type": "Feature",
  "properties": {
    "iso:country":"IT",
    "sg:address":"Localita' Ampella 53020 San Giovanni D'asso",
    "sg:classifiers":[
        {
            "category":"Home & Garden",
            "subcategory":"Home Furnishings",
            "type":"Retail Goods"
        }
    ],
    "sg:phone":"+39 0577 803000",
    "sg:postcode":"53020",
    "sg:province":"Siena",
    "sg:tags":[
        "household"
    ],
    "wof:name":"Terrecotte Artistiche Senesi (s.n.c.)",
    "wof:placetype":"venue"
},
  "geometry": {"coordinates":[11.330514,43.318661],"type":"Point"}
}