{
  "type": "Feature",
  "properties": {
    "iso:country":"IT",
    "sg:address":"20017 Rho",
    "sg:city":"Rho",
    "sg:orig_category":"Impianti, Attrezzature E Forniture Sanitarie Ed Ospedaliere",
    "sg:phone":"+39 02 9397 0800",
    "sg:postcode":"20017",
    "sg:province":"Milano",
    "wof:name":"Ab Medica Srl",
    "wof:placetype":"venue"
},
  "geometry": {"coordinates":[9.087514,45.52512],"type":"Point"}
}