{
  "type": "Feature",
  "properties": {
    "addr:full":"2/d, Via Amalfi 41034 Finale Emilia Finale Emilia Modena 41034",
    "addr:housenumber":"2 / d",
    "addr:postcode":"41034;41034",
    "addr:street":"Via Amalfi",
    "iso:country":"IT",
    "sg:address":"2/d, Via Amalfi 41034 Finale Emilia",
    "sg:city":"Finale Emilia",
    "sg:classifiers":[
        {
            "category":"Manufacturing",
            "subcategory":"Metals",
            "type":"Manufacturing & Wholesale Goods"
        }
    ],
    "sg:phone":"+39 39053598375",
    "sg:postcode":"41034",
    "sg:province":"Modena",
    "sg:tags":[
        "processing"
    ],
    "wof:name":"Ferioli F.lli (s.r.l.)",
    "wof:placetype":"venue"
},
  "geometry": {"coordinates":[10.8677082062,44.6507530212],"type":"Point"}
}