{
  "type": "Feature",
  "properties": {
    "iso:country":"IT",
    "sg:address":"84025 Eboli",
    "sg:city":"Eboli",
    "sg:orig_category":"Imprese Di Costruzioni Civili Ed Industriali. Servizi Ausiliari Di Sorveglianza, Manutenzione E Pulizia",
    "sg:phone":"+39 0828 601119",
    "sg:postcode":"84025",
    "sg:province":"Salerno",
    "wof:name":"M.g.a. Srl",
    "wof:placetype":"venue"
},
  "geometry": {"coordinates":[14.96225,40.522766],"type":"Point"}
}