{
  "type": "Feature",
  "properties": {
    "iso:country":"IT",
    "sg:address":"00195 Roma",
    "sg:city":"Roma",
    "sg:orig_category":"Cinematografia E Radiotelevisione. Forniture Per Il Settore Dello Spettacolo",
    "sg:phone":"+39 06 321 7773",
    "sg:postcode":"00195",
    "sg:province":"Roma",
    "wof:name":"Stage Srl",
    "wof:placetype":"venue"
},
  "geometry": {"coordinates":[12.465898,41.915283],"type":"Point"}
}