{
  "type": "Feature",
  "properties": {
    "iso:country":"IT",
    "sg:address":"20131 Milano",
    "sg:city":"Milano",
    "sg:orig_category":"Serramenti Ed Infissi. Prodotti Vari In Metallo",
    "sg:phone":"+39 02 2611 2000",
    "sg:postcode":"20131",
    "sg:province":"Milano",
    "sg:website":"http://www.finporte.it",
    "wof:name":"Finporte Snc Di Sanfilippo A. & M.",
    "wof:placetype":"venue"
},
  "geometry": {"coordinates":[9.231596,45.487965],"type":"Point"}
}