{
  "type": "Feature",
  "properties": {
    "addr:full":"00198 Roma Roma Roma 00198",
    "addr:postcode":"00198;00198",
    "iso:country":"IT",
    "sg:address":"00198 Roma",
    "sg:city":"Roma",
    "sg:orig_category":"Agenzie Stampa",
    "sg:phone":"+39 06 8530 4594",
    "sg:postcode":"00198",
    "sg:province":"Roma",
    "wof:name":"Granata Press Service Srl",
    "wof:placetype":"venue"
},
  "geometry": {"coordinates":[12.498414,41.922016],"type":"Point"}
}