{
  "type": "Feature",
  "properties": {
    "iso:country":"IT",
    "sg:address":"00184 Roma",
    "sg:city":"Roma",
    "sg:orig_category":"Servizi Culturali E Per Lo Spettacolo. Servizi Al Turismo. Acqua, Luce, Gas E Societa' Di Esercizio Pubblico",
    "sg:phone":"+39 06 481 7003",
    "sg:postcode":"00184",
    "sg:province":"Roma",
    "wof:name":"Teatro Dell'opera",
    "wof:placetype":"venue"
},
  "geometry": {"coordinates":[12.495309,41.900524],"type":"Point"}
}