{
  "type": "Feature",
  "properties": {
    "iso:country":"IT",
    "sg:address":"Via Autostrada Del Sole Mi-bo 20070 San Zenone Al Lambro",
    "sg:city":"San Zenone al Lambro",
    "sg:classifiers":[
        {
            "category":"Travel",
            "subcategory":"Travel Agent",
            "type":"Entertainment"
        }
    ],
    "sg:phone":"+39 02 9887 0039",
    "sg:postcode":"20070",
    "sg:province":"Milano",
    "sg:tags":[
        "business"
    ],
    "wof:name":"S. Zenone S.r.l.",
    "wof:placetype":"venue"
},
  "geometry": {"coordinates":[9.188141,45.463688],"type":"Point"}
}