{
  "type": "Feature",
  "properties": {
    "addr:full":"06081 Assisi Assisi Perugia 06081",
    "addr:postcode":"06081;06081",
    "iso:country":"IT",
    "sg:address":"06081 Assisi",
    "sg:city":"Assisi",
    "sg:orig_category":"Macchine, Impianti Ed Attrezzature Per Agricoltura E Zootecnia",
    "sg:phone":"+39 075 804 1105",
    "sg:postcode":"06081",
    "sg:province":"Perugia",
    "wof:name":"Co.m.an. Srl",
    "wof:placetype":"venue"
},
  "geometry": {"coordinates":[12.680844,42.828106],"type":"Point"}
}