{
  "type": "Feature",
  "properties": {
    "iso:country":"IT",
    "sg:address":"06049 Spoleto",
    "sg:city":"Spoleto",
    "sg:orig_category":"Banche Ed Istituti Di Credito E Risparmio",
    "sg:phone":"+39 0743 2151",
    "sg:postcode":"06049",
    "sg:province":"Perugia",
    "sg:website":"http://www.bpspoleto.it",
    "wof:name":"Banca Popolare Di Spoleto",
    "wof:placetype":"venue"
},
  "geometry": {"coordinates":[12.690533,42.719028],"type":"Point"}
}