{
  "type": "Feature",
  "properties": {
    "iso:country":"IT",
    "sg:address":"28010 Fontaneto D'agogna",
    "sg:orig_category":"Oli Industriali",
    "sg:phone":"+39 0322 89467",
    "sg:postcode":"28010",
    "sg:province":"Novara",
    "wof:name":"Fornara & C. Snc",
    "wof:placetype":"venue"
},
  "geometry": {"coordinates":[8.47928,45.646542],"type":"Point"}
}