{
  "type": "Feature",
  "properties": {
    "addr:full":"2, Via Roma 20010 San Giorgio Su Legnano San Giorgio su Legnano Milano 20010",
    "addr:postcode":"20010;20010",
    "addr:street":"Via Roma",
    "iso:country":"IT",
    "sg:address":"2, Via Roma 20010 San Giorgio Su Legnano",
    "sg:city":"San Giorgio su Legnano",
    "sg:classifiers":[
        {
            "category":"Real Estate",
            "subcategory":"Architect",
            "type":"Services"
        }
    ],
    "sg:phone":"+39 0331 413000",
    "sg:postcode":"20010",
    "sg:province":"Milano",
    "sg:tags":[
        "textile",
        "clothing"
    ],
    "wof:name":"Tessiture Di Nosate E San Giorgio",
    "wof:placetype":"venue"
},
  "geometry": {"coordinates":[8.910221,45.575993],"type":"Point"}
}