{
  "type": "Feature",
  "properties": {
    "addr:full":"9, Via Marigonda 31040 Gorgo Al Monticano Gorgo al Monticano Treviso 31040",
    "addr:housenumber":"monticano",
    "addr:postcode":"31040;al;31040",
    "addr:street":"Via Marigonda",
    "iso:country":"IT",
    "sg:address":"9, Via Marigonda 31040 Gorgo Al Monticano",
    "sg:city":"Gorgo al Monticano",
    "sg:classifiers":[
        {
            "category":"Home & Garden",
            "subcategory":"Home Furnishings",
            "type":"Retail Goods"
        }
    ],
    "sg:phone":"+39 0422 742184",
    "sg:postcode":"31040",
    "sg:province":"Treviso",
    "sg:tags":[
        "household"
    ],
    "wof:name":"Idea (s.r.l.)",
    "wof:placetype":"venue"
},
  "geometry": {"coordinates":[12.592633,45.807549],"type":"Point"}
}