{
  "type": "Feature",
  "properties": {
    "iso:country":"IT",
    "sg:address":"10099 San Mauro Torinese",
    "sg:city":"San Mauro Torinese",
    "sg:orig_category":"Termotecnica E Riscaldamento, Apparecchiature E Servizi",
    "sg:phone":"+39 011 274 0804",
    "sg:postcode":"10099",
    "sg:province":"Torino",
    "wof:name":"Arcotrading Spa",
    "wof:placetype":"venue"
},
  "geometry": {"coordinates":[7.745466,45.115791],"type":"Point"}
}