{
  "type": "Feature",
  "properties": {
    "iso:country":"IT",
    "sg:address":"35122 Padova",
    "sg:city":"Padova",
    "sg:orig_category":"Abbigliamento - Vendita Al Dettaglio",
    "sg:phone":"+39 049 661566",
    "sg:postcode":"35122",
    "sg:province":"Padova",
    "wof:name":"Z\u00dct Sas",
    "wof:placetype":"venue"
},
  "geometry": {"coordinates":[11.917498,45.3545],"type":"Point"}
}