{
  "type": "Feature",
  "properties": {
    "iso:country":"IT",
    "sg:address":"37012 Bussolengo",
    "sg:city":"Bussolengo",
    "sg:orig_category":"Shopping. Prodotti Cosmetici E Da Toeletta",
    "sg:phone":"+39 045 676 7065",
    "sg:postcode":"37012",
    "sg:province":"Verona",
    "wof:name":"Griff'i Srl",
    "wof:placetype":"venue"
},
  "geometry": {"coordinates":[10.875427,45.447472],"type":"Point"}
}