{
  "type": "Feature",
  "properties": {
    "addr:full":"40011 Anzola Dell'emilia Bologna 40011",
    "addr:postcode":"40011;40011",
    "iso:country":"IT",
    "sg:address":"40011 Anzola Dell'emilia",
    "sg:orig_category":"Motori Ed Organi Di Trasmissione",
    "sg:phone":"+39 051 731487",
    "sg:postcode":"40011",
    "sg:province":"Bologna",
    "wof:name":"Transtecno (s.r.l.)",
    "wof:placetype":"venue"
},
  "geometry": {"coordinates":[11.2157850266,44.5401954651],"type":"Point"}
}