{
  "type": "Feature",
  "properties": {
    "addr:full":"57023 Cecina Cecina Livorno 57023",
    "addr:postcode":"57023;57023",
    "iso:country":"IT",
    "sg:address":"57023 Cecina",
    "sg:city":"Cecina",
    "sg:orig_category":"Prodotti Finiti Stampati. Servizi Editoriali. Tempo Libero - Articoli E Forniture",
    "sg:phone":"+39 0586 661220",
    "sg:postcode":"57023",
    "sg:province":"Livorno",
    "wof:name":"Organizzazione Mare Srl",
    "wof:placetype":"venue"
},
  "geometry": {"coordinates":[10.4958677292,43.3176383972],"type":"Point"}
}