{
  "type": "Feature",
  "properties": {
    "addr:full":"10127 Torino Torino Torino 10127",
    "addr:postcode":"10127;10127",
    "iso:country":"IT",
    "sg:address":"10127 Torino",
    "sg:city":"Torino",
    "sg:orig_category":"Pompe. Ricambi E Componenti Dei Mezzi Di Trasporto",
    "sg:phone":"+39 011 611502",
    "sg:postcode":"10127",
    "sg:province":"Torino",
    "wof:name":"Romano Vincenzo",
    "wof:placetype":"venue"
},
  "geometry": {"coordinates":[7.6559157372,45.0240249634],"type":"Point"}
}