{
  "type": "Feature",
  "properties": {
    "iso:country":"IT",
    "sg:address":"Via Foggia 47 70051 Barletta",
    "sg:city":"Barletta",
    "sg:classifiers":[
        {
            "category":"Manufacturing",
            "subcategory":"Rubber & Plastics",
            "type":"Manufacturing & Wholesale Goods"
        }
    ],
    "sg:phone":"+39 0883 526118",
    "sg:postcode":"70051",
    "sg:province":"Bari",
    "sg:tags":[
        "bags",
        "polyethylene",
        "sack",
        "bag"
    ],
    "sg:website":"www.isalp.it",
    "wof:name":"I.s.a.l.p. Srl",
    "wof:placetype":"venue"
},
  "geometry": {"coordinates":[16.2347106934,41.3255577087],"type":"Point"}
}