{
  "type": "Feature",
  "properties": {
    "iso:country":"IT",
    "sg:address":"24069 Trescore Balneario",
    "sg:city":"Trescore Balneario",
    "sg:orig_category":"Servizi E Lavori Per Abbigliamento E Pelletterie",
    "sg:phone":"+39 035 940314",
    "sg:postcode":"24069",
    "sg:province":"Bergamo",
    "wof:name":"Texlima Srl",
    "wof:placetype":"venue"
},
  "geometry": {"coordinates":[9.846543,45.694912],"type":"Point"}
}