{
  "type": "Feature",
  "properties": {
    "addr:full":"00149 Roma Roma Roma 00149",
    "addr:postcode":"00149;00149",
    "iso:country":"IT",
    "sg:address":"00149 Roma",
    "sg:city":"Roma",
    "sg:orig_category":"Litografie",
    "sg:phone":"+39 06 558 5048",
    "sg:postcode":"00149",
    "sg:province":"Roma",
    "wof:name":"Grafroma Srl",
    "wof:placetype":"venue"
},
  "geometry": {"coordinates":[12.454273,41.861481],"type":"Point"}
}