{
  "type": "Feature",
  "properties": {
    "iso:country":"IT",
    "sg:address":"98039 Taormina",
    "sg:city":"Taormina",
    "sg:orig_category":"Manufacturers: Prefabbricati",
    "sg:phone":"+39 0942 577110",
    "sg:postcode":"98039",
    "sg:province":"Messina",
    "wof:name":"Lombardo Belardo Marmi",
    "wof:placetype":"venue"
},
  "geometry": {"coordinates":[15.247752,37.832092],"type":"Point"}
}