{
  "type": "Feature",
  "properties": {
    "iso:country":"IT",
    "sg:address":"Viale Croce Rossa 25 90144 Palermo",
    "sg:city":"Palermo",
    "sg:orig_category":"Software For Pharmaceuticals Databases",
    "sg:phone":"+39 091 580707",
    "sg:postcode":"90144",
    "sg:province":"Palermo",
    "wof:name":"Ecotime S.n.c. Di Clementi Grazia",
    "wof:placetype":"venue"
},
  "geometry": {"coordinates":[13.341304,38.147156],"type":"Point"}
}