{
  "type": "Feature",
  "properties": {
    "addr:full":"41049 Sassuolo Sassuolo Modena 41049",
    "addr:postcode":"41049;41049",
    "iso:country":"IT",
    "sg:address":"41049 Sassuolo",
    "sg:city":"Sassuolo",
    "sg:orig_category":"Motori Ed Organi Di Trasmissione",
    "sg:phone":"+39 0536 802092",
    "sg:postcode":"41049",
    "sg:province":"Modena",
    "wof:name":"Nuova Ferrari & Zagni Snc",
    "wof:placetype":"venue"
},
  "geometry": {"coordinates":[10.7832984924,44.5362815857],"type":"Point"}
}