{
  "type": "Feature",
  "properties": {
    "addr:full":"Via Della Molina 39 50010 San Donnino Di Campi Firenze 50010",
    "addr:housenumber":"39;campi",
    "addr:postcode":"50010;50010",
    "addr:street":"Via Della Molina",
    "iso:country":"IT",
    "sg:address":"Via Della Molina 39 50010 San Donnino Di Campi",
    "sg:classifiers":[
        {
            "category":"Manufacturing",
            "subcategory":"Soap",
            "type":"Manufacturing & Wholesale Goods"
        }
    ],
    "sg:phone":"+39 055 873 9401",
    "sg:postcode":"50010",
    "sg:province":"Firenze",
    "sg:tags":[
        "bubble",
        "individual",
        "hotel",
        "portions",
        "bath"
    ],
    "sg:website":"www.nestidante.com",
    "wof:name":"Nesti Dante Srl",
    "wof:placetype":"venue"
},
  "geometry": {"coordinates":[11.128516,43.792767],"type":"Point"}
}