{
  "type": "Feature",
  "properties": {
    "iso:country":"IT",
    "sg:address":"46042 Castel Goffredo",
    "sg:city":"Castel Goffredo",
    "sg:orig_category":"Forniture Per Attivita' Industriali",
    "sg:phone":"+39 0376 771607",
    "sg:postcode":"46042",
    "sg:province":"Mantova",
    "wof:name":"Neotec Di Fava Guglielmo & C. Snc",
    "wof:placetype":"venue"
},
  "geometry": {"coordinates":[10.4680109024,45.2868843079],"type":"Point"}
}