{
  "type": "Feature",
  "properties": {
    "addr:full":"00186 Roma Roma Roma 00186",
    "addr:postcode":"00186;00186",
    "iso:country":"IT",
    "sg:address":"00186 Roma",
    "sg:city":"Roma",
    "sg:orig_category":"Forniture Per Abbigliamento E Pelletterie",
    "sg:phone":"+39 06 687 9698",
    "sg:postcode":"00186",
    "sg:province":"Roma",
    "wof:name":"Modelli Glen",
    "wof:placetype":"venue"
},
  "geometry": {"coordinates":[12.4894676208,41.8583297729],"type":"Point"}
}