{
  "type": "Feature",
  "properties": {
    "addr:full":"10091 Alpignano Alpignano Torino 10091",
    "addr:postcode":"10091;10091",
    "iso:country":"IT",
    "sg:address":"10091 Alpignano",
    "sg:city":"Alpignano",
    "sg:orig_category":"Prodotti Finiti Stampati. Forniture E Materiali Per Imballaggio E Confezionamento. Forniture Per Attivita' Commerciali Ed Artigianali",
    "sg:phone":"+39 011 967 7525",
    "sg:postcode":"10091",
    "sg:province":"Torino",
    "wof:name":"La Mecca Della Carta Sas",
    "wof:placetype":"venue"
},
  "geometry": {"coordinates":[7.693546772,45.0285110474],"type":"Point"}
}