{
  "type": "Feature",
  "properties": {
    "iso:country":"IT",
    "sg:address":"37121 Verona",
    "sg:city":"Verona",
    "sg:orig_category":"Shopping. Prodotti Cosmetici E Da Toeletta",
    "sg:phone":"+39 045 800 9407",
    "sg:postcode":"37121",
    "sg:province":"Verona",
    "wof:name":"Omni Services Srl",
    "wof:placetype":"venue"
},
  "geometry": {"coordinates":[10.940104,45.494457],"type":"Point"}
}