{
  "type": "Feature",
  "properties": {
    "iso:country":"IT",
    "sg:address":"70, Via Trento 33031 Basiliano",
    "sg:city":"Basiliano",
    "sg:classifiers":[
        {
            "category":"Wholesale",
            "subcategory":"Drugs",
            "type":"Manufacturing & Wholesale Goods"
        }
    ],
    "sg:phone":"+39 39043284197",
    "sg:postcode":"33031",
    "sg:province":"Udine",
    "sg:tags":[
        "chemical",
        "pharmaceutical"
    ],
    "wof:name":"E.p.m. S.a.s. Di Persello Alberto & C.",
    "wof:placetype":"venue"
},
  "geometry": {"coordinates":[13.092651,46.022682],"type":"Point"}
}