{
  "type": "Feature",
  "properties": {
    "iso:country":"IT",
    "sg:address":"Via Sant' Orsola 219 25135 Brescia",
    "sg:city":"Brescia",
    "sg:classifiers":[
        {
            "category":"Banks & Credit Unions",
            "subcategory":"Investment Brokerage",
            "type":"Services"
        }
    ],
    "sg:phone":"+39 030 219 0838",
    "sg:postcode":"25135",
    "sg:province":"Brescia",
    "sg:tags":[
        "children's",
        "stocking"
    ],
    "wof:name":"Calzificio Busi S.a.s. Di Busi Mauro",
    "wof:placetype":"venue"
},
  "geometry": {"coordinates":[10.294371,45.531292],"type":"Point"}
}