{
  "type": "Feature",
  "properties": {
    "iso:country":"IT",
    "sg:address":"9, Via Trento 13039 Trino",
    "sg:city":"Trino",
    "sg:classifiers":[
        {
            "category":"Professional",
            "subcategory":"Engineering",
            "type":"Services"
        }
    ],
    "sg:phone":"+39 0161 802072",
    "sg:postcode":"13039",
    "sg:province":"Vercelli",
    "sg:tags":[
        "machine",
        "-",
        "mechanical"
    ],
    "wof:name":"Elettromeccanica Va.ma.",
    "wof:placetype":"venue"
},
  "geometry": {"coordinates":[8.292466,45.191124],"type":"Point"}
}