{
  "type": "Feature",
  "properties": {
    "iso:country":"IT",
    "sg:address":"25020 Pavone Del Mella",
    "sg:city":"Pavone del Mella",
    "sg:orig_category":"Forniture Per Agricoltura E Zootecnia. Animali Domestici",
    "sg:phone":"+39 030 682 0546",
    "sg:postcode":"25020",
    "sg:province":"Brescia",
    "wof:name":"Dog And Cat Snc",
    "wof:placetype":"venue"
},
  "geometry": {"coordinates":[10.2106027603,45.3024978638],"type":"Point"}
}