{
  "type": "Feature",
  "properties": {
    "iso:country":"IT",
    "sg:address":"18, Via Lario 20052 Monza",
    "sg:city":"Monza",
    "sg:classifiers":[
        {
            "category":"Professional",
            "subcategory":"Engineering",
            "type":"Services"
        }
    ],
    "sg:phone":"+39 39039367334",
    "sg:postcode":"20052",
    "sg:province":"Milano",
    "sg:tags":[
        "machine",
        "-",
        "mechanical"
    ],
    "wof:name":"Papetti E Colombo (s.p.a.)",
    "wof:placetype":"venue"
},
  "geometry": {"coordinates":[9.211413,45.55814],"type":"Point"}
}