{
  "type": "Feature",
  "properties": {
    "addr:full":"12, Via Zona Industriale 60020 Sirolo Sirolo Ancona 60020",
    "addr:postcode":"60020;60020",
    "addr:street":"Via Zona Industriale",
    "iso:country":"IT",
    "sg:address":"12, Via Zona Industriale 60020 Sirolo",
    "sg:city":"Sirolo",
    "sg:classifiers":[
        {
            "category":"Shopping",
            "type":"Retail Goods"
        }
    ],
    "sg:phone":"+39 071 933 0578",
    "sg:postcode":"60020",
    "sg:province":"Ancona",
    "sg:tags":[
        "finished",
        "-",
        "metallic"
    ],
    "wof:name":"A.s.lavorazione Materie Plastiche Sas Di Dubbini Sara & C.",
    "wof:placetype":"venue"
},
  "geometry": {"coordinates":[13.6074819565,43.515625],"type":"Point"}
}