{
  "type": "Feature",
  "properties": {
    "iso:country":"IT",
    "sg:address":"38066 Riva Del Garda",
    "sg:city":"Riva del Garda",
    "sg:orig_category":"Scuole E Servizi Scolastici. Servizi Per Lo Sport E Il Tempo Libero",
    "sg:postcode":"38066",
    "sg:province":"Trento",
    "wof:name":"Pro Center Michiel Bouwmeester",
    "wof:placetype":"venue"
},
  "geometry": {"coordinates":[10.8249320984,45.8965415955],"type":"Point"}
}