{
  "type": "Feature",
  "properties": {
    "addr:full":"17, Via Manzoni Alessandro 20121 Milano Milano Milano 20121",
    "addr:postcode":"20121;20121",
    "addr:street":"Via Manzoni Alessandro",
    "iso:country":"IT",
    "sg:address":"17, Via Manzoni Alessandro 20121 Milano",
    "sg:city":"Milano",
    "sg:classifiers":[
        {
            "category":"Shopping",
            "subcategory":"Clothing, Apparel, & Fashions",
            "type":"Retail Goods"
        }
    ],
    "sg:phone":"+39 02 7202 2685",
    "sg:postcode":"20121",
    "sg:province":"Milano",
    "sg:tags":[
        "clothes"
    ],
    "wof:name":"Teodori Spa",
    "wof:placetype":"venue"
},
  "geometry": {"coordinates":[9.191802,45.469208],"type":"Point"}
}