{
  "type": "Feature",
  "properties": {
    "iso:country":"IT",
    "sg:address":"3, Via Feltrina Centro 31044 Montebelluna",
    "sg:city":"Montebelluna",
    "sg:classifiers":[
        {
            "category":"Personal",
            "subcategory":"Shoe Repair & Shine",
            "type":"Services"
        }
    ],
    "sg:phone":"+39 390 423 2851",
    "sg:postcode":"31044",
    "sg:province":"Treviso",
    "sg:tags":[
        "leather"
    ],
    "wof:name":"Calzaturificio Dolomite S.p.a.",
    "wof:placetype":"venue"
},
  "geometry": {"coordinates":[12.050365,45.788048],"type":"Point"}
}