{
  "type": "Feature",
  "properties": {
    "iso:country":"IT",
    "sg:address":"55, Rione De Gasperi Alcide 80147 Napoli",
    "sg:city":"Napoli",
    "sg:orig_category":"Miscellaneous Products",
    "sg:phone":"+39 081 552 5308",
    "sg:postcode":"80147",
    "sg:province":"Napoli",
    "wof:name":"Morelli Giulio S.p.a.",
    "wof:placetype":"venue"
},
  "geometry": {"coordinates":[14.2516355515,40.84009552],"type":"Point"}
}