{
  "type": "Feature",
  "properties": {
    "iso:country":"IT",
    "sg:address":"89015 Palmi",
    "sg:city":"Palmi",
    "sg:orig_category":"Fotocomposizione",
    "sg:phone":"+39 0966 23575",
    "sg:postcode":"89015",
    "sg:province":"Reggio Di Calabria",
    "wof:name":"Balzama' Rocco Tipografia",
    "wof:placetype":"venue"
},
  "geometry": {"coordinates":[15.6501369476,38.1146888733],"type":"Point"}
}