{
  "type": "Feature",
  "properties": {
    "addr:full":"03013 Ferentino Ferentino Frosinone 03013",
    "addr:postcode":"03013;03013",
    "iso:country":"IT",
    "sg:address":"03013 Ferentino",
    "sg:city":"Ferentino",
    "sg:orig_category":"Materiali E Componenti Elettrotecnici. Elettrotecnica Industriale, Prodotti E Apparecchiature",
    "sg:phone":"+39 0775 397873",
    "sg:postcode":"03013",
    "sg:province":"Frosinone",
    "wof:name":"Palombo Antonio",
    "wof:placetype":"venue"
},
  "geometry": {"coordinates":[13.26155,41.696651],"type":"Point"}
}