{
  "type": "Feature",
  "properties": {
    "addr:full":"Via Polesine 1 37043 Castagnaro Castagnaro Verona 37043",
    "addr:housenumber":"1",
    "addr:postcode":"37043;37043",
    "addr:street":"Via Polesine",
    "iso:country":"IT",
    "sg:address":"Via Polesine 1 37043 Castagnaro",
    "sg:city":"Castagnaro",
    "sg:classifiers":[
        {
            "category":"Wholesale",
            "subcategory":"Farm Supplies",
            "type":"Manufacturing & Wholesale Goods"
        }
    ],
    "sg:phone":"+39 0442 92025",
    "sg:postcode":"37043",
    "sg:province":"Verona",
    "sg:tags":[
        "agricultural",
        "part",
        "spare",
        "machinery",
        "accessory"
    ],
    "sg:website":"www.spedo.it",
    "wof:name":"Spedo Flli Di Spedo Romenio E C Snc",
    "wof:placetype":"venue"
},
  "geometry": {"coordinates":[11.414225,45.119129],"type":"Point"}
}