{
  "type": "Feature",
  "properties": {
    "addr:full":"7, Via S. Martino 12033 Moretta Moretta Cuneo 12033",
    "addr:postcode":"12033;12033",
    "addr:street":"Via S. Martino",
    "iso:country":"IT",
    "sg:address":"7, Via S. Martino 12033 Moretta",
    "sg:city":"Moretta",
    "sg:classifiers":[
        {
            "category":"Manufacturing",
            "subcategory":"Metals",
            "type":"Manufacturing & Wholesale Goods"
        }
    ],
    "sg:phone":"+39 39017294003",
    "sg:postcode":"12033",
    "sg:province":"Cuneo",
    "sg:tags":[
        "processing"
    ],
    "wof:name":"Neograf (s.r.l.)",
    "wof:placetype":"venue"
},
  "geometry": {"coordinates":[8.1145133972,44.7810707092],"type":"Point"}
}