{
  "type": "Feature",
  "properties": {
    "addr:full":"Via Oriolo 35 26020 Madignano Madignano Cremona 26020",
    "addr:housenumber":"35",
    "addr:postcode":"26020;26020",
    "addr:street":"Via Oriolo",
    "iso:country":"IT",
    "sg:address":"Via Oriolo 35 26020 Madignano",
    "sg:city":"Madignano",
    "sg:classifiers":[
        {
            "category":"Wholesale",
            "subcategory":"Construction Materials",
            "type":"Manufacturing & Wholesale Goods"
        }
    ],
    "sg:phone":"+39 0373 65381",
    "sg:postcode":"26020",
    "sg:province":"Cremona",
    "sg:tags":[
        "packaging",
        "polyethylene"
    ],
    "sg:website":"www.cadeiemerletti.it",
    "wof:name":"Cadei & Merletti Srl",
    "wof:placetype":"venue"
},
  "geometry": {"coordinates":[9.7350549698,45.3340873718],"type":"Point"}
}