{
  "type": "Feature",
  "properties": {
    "iso:country":"IT",
    "sg:address":"00137 Roma",
    "sg:city":"Roma",
    "sg:orig_category":"Filati E Materie Prime Tessili",
    "sg:phone":"+39 06 8200 0175",
    "sg:postcode":"00137",
    "sg:province":"Roma",
    "wof:name":"Ellegi Srl",
    "wof:placetype":"venue"
},
  "geometry": {"coordinates":[12.5607481003,41.9451522827],"type":"Point"}
}