{
  "type": "Feature",
  "properties": {
    "iso:country":"IT",
    "sg:address":"5/h, Via Del Casalino 24121 Bergamo",
    "sg:city":"Bergamo",
    "sg:classifiers":[
        {
            "category":"Professional",
            "subcategory":"Business Services",
            "type":"Services"
        }
    ],
    "sg:phone":"+39 39035220116",
    "sg:postcode":"24121",
    "sg:province":"Bergamo",
    "sg:tags":[
        "advice"
    ],
    "wof:name":"Studio First (s.n.c.)",
    "wof:placetype":"venue"
},
  "geometry": {"coordinates":[9.669952,45.694904],"type":"Point"}
}