{
  "type": "Feature",
  "properties": {
    "addr:full":"12078 Ormea Ormea Cuneo 12078",
    "addr:postcode":"12078;12078",
    "iso:country":"IT",
    "sg:address":"12078 Ormea",
    "sg:city":"Ormea",
    "sg:orig_category":"Non-classified Establishments",
    "sg:phone":"+39 338 594 4749",
    "sg:postcode":"12078",
    "sg:province":"Cuneo",
    "wof:name":"Decorart",
    "wof:placetype":"venue"
},
  "geometry": {"coordinates":[7.909747,44.147503],"type":"Point"}
}