{
  "type": "Feature",
  "properties": {
    "addr:full":"07041 Alghero Alghero Sassari 07041",
    "addr:postcode":"07041;07041",
    "iso:country":"IT",
    "sg:address":"07041 Alghero",
    "sg:city":"Alghero",
    "sg:orig_category":"Nautica. Ricambi E Componenti Dei Mezzi Di Trasporto",
    "sg:phone":"+39 079 952025",
    "sg:postcode":"07041",
    "sg:province":"Sassari",
    "wof:name":"Centro Nauti Sport Di Gervasio",
    "wof:placetype":"venue"
},
  "geometry": {"coordinates":[8.286948,40.641041],"type":"Point"}
}