{
  "type": "Feature",
  "properties": {
    "addr:full":"20037 Paderno Dugnano Paderno Dugnano Milano 20037",
    "addr:postcode":"20037;20037",
    "iso:country":"IT",
    "sg:address":"20037 Paderno Dugnano",
    "sg:city":"Paderno Dugnano",
    "sg:classifiers":[
        {
            "category":"Home & Garden",
            "subcategory":"Home Furnishings",
            "type":"Retail Goods"
        }
    ],
    "sg:phone":"+39 02 910 6730",
    "sg:postcode":"20037",
    "sg:province":"Milano",
    "sg:tags":[
        "plumbing",
        "bathroom",
        "fitting",
        "accessories",
        "accessory"
    ],
    "wof:name":"Comet Snc",
    "wof:placetype":"venue"
},
  "geometry": {"coordinates":[9.1651544571,45.5692901611],"type":"Point"}
}