{
  "type": "Feature",
  "properties": {
    "iso:country":"IT",
    "sg:address":"41042 Fiorano Modenese",
    "sg:city":"Fiorano Modenese",
    "sg:orig_category":"Ceramiche: Prodotti E Lavorazioni",
    "sg:phone":"+39 0536 925911",
    "sg:postcode":"41042",
    "sg:province":"Modena",
    "wof:name":"Ceramica D'elite By Worldker Srl",
    "wof:placetype":"venue"
},
  "geometry": {"coordinates":[10.828492,44.531971],"type":"Point"}
}