{
  "type": "Feature",
  "properties": {
    "addr:full":"20049 Concorezzo Concorezzo Milano 20049",
    "addr:postcode":"20049;20049",
    "iso:country":"IT",
    "sg:address":"20049 Concorezzo",
    "sg:city":"Concorezzo",
    "sg:orig_category":"Servizi Per Aziende, Manifestazioni E Supporto Agli Scambi Commerciali",
    "sg:phone":"+39 039 647819",
    "sg:postcode":"20049",
    "sg:province":"Milano",
    "wof:name":"Studio F.m. Di Mattavelli",
    "wof:placetype":"venue"
},
  "geometry": {"coordinates":[9.327076,45.590023],"type":"Point"}
}