{
  "type": "Feature",
  "properties": {
    "addr:full":"33010 Branco Udine 33010",
    "addr:postcode":"33010;33010",
    "addr:street":"Branco",
    "iso:country":"IT",
    "sg:address":"33010 Branco",
    "sg:orig_category":"Forniture Per Attivita' Industriali",
    "sg:phone":"+39 0432 572856",
    "sg:postcode":"33010",
    "sg:province":"Udine",
    "wof:name":"La Cernita",
    "wof:placetype":"venue"
},
  "geometry": {"coordinates":[13.2001361847,46.1138305664],"type":"Point"}
}