{
  "type": "Feature",
  "properties": {
    "iso:country":"IT",
    "sg:address":"153, Via Cuneo 12012 Boves",
    "sg:city":"Boves",
    "sg:classifiers":[
        {
            "category":"Professional",
            "subcategory":"Engineering",
            "type":"Services"
        }
    ],
    "sg:phone":"+39 0171 391511",
    "sg:postcode":"12012",
    "sg:province":"Cuneo",
    "sg:tags":[
        "machine",
        "-",
        "mechanical"
    ],
    "wof:name":"Officine Meccaniche Bovesane S.r.l.",
    "wof:placetype":"venue"
},
  "geometry": {"coordinates":[7.557841,44.345032],"type":"Point"}
}