{
  "type": "Feature",
  "properties": {
    "iso:country":"IT",
    "sg:address":"37, V. Del Lavoro - Cimavilla 31013 Codogn\u00e8",
    "sg:classifiers":[
        {
            "category":"Professional",
            "subcategory":"Engineering",
            "type":"Services"
        }
    ],
    "sg:phone":"+39 0438 778504",
    "sg:postcode":"31013",
    "sg:province":"Treviso",
    "sg:tags":[
        "machine",
        "-",
        "mechanical"
    ],
    "sg:website":"http://www.gemm-srl.com:ws_end: :mark:ws:http://www.paginegialle.it/gemm",
    "wof:name":"Gemm Srl",
    "wof:placetype":"venue"
},
  "geometry": {"coordinates":[12.376339,45.864826],"type":"Point"}
}