{
  "type": "Feature",
  "properties": {
    "iso:country":"IT",
    "sg:address":"61, Via Monte Rosa 20149 Milano",
    "sg:city":"Milano",
    "sg:classifiers":[
        {
            "category":"Wholesale",
            "subcategory":"Drugs",
            "type":"Manufacturing & Wholesale Goods"
        }
    ],
    "sg:phone":"+39 39024981851",
    "sg:postcode":"20149",
    "sg:province":"Milano",
    "sg:tags":[
        "chemical",
        "pharmaceutical"
    ],
    "wof:name":"Prochifar (s.r.l.)",
    "wof:placetype":"venue"
},
  "geometry": {"coordinates":[9.14898,45.475174],"type":"Point"}
}