{
  "type": "Feature",
  "properties": {
    "iso:country":"IT",
    "sg:address":"20122 Milano",
    "sg:city":"Milano",
    "sg:classifiers":[
        {
            "category":"Shopping",
            "subcategory":"Jewelry",
            "type":"Retail Goods"
        }
    ],
    "sg:phone":"+39 02 545 6353",
    "sg:postcode":"20122",
    "sg:province":"Milano",
    "sg:tags":[
        "watchmaker",
        "jewelers",
        "gold",
        "silversmiths"
    ],
    "sg:website":"http://www.buttura.it",
    "wof:name":"Buttura Mario Srl",
    "wof:placetype":"venue"
},
  "geometry": {"coordinates":[9.200422,45.461826],"type":"Point"}
}