{
  "type": "Feature",
  "properties": {
    "iso:country":"IT",
    "sg:address":"32, V. Mattei 60019 Senigallia",
    "sg:city":"Senigallia",
    "sg:classifiers":[
        {
            "category":"Manufacturing",
            "subcategory":"Paper Products",
            "type":"Manufacturing & Wholesale Goods"
        }
    ],
    "sg:phone":"+39 390 716 6061",
    "sg:postcode":"60019",
    "sg:province":"Ancona",
    "sg:tags":[
        "cardboard"
    ],
    "sg:website":"http://www.fiorinipack.it",
    "wof:name":"Fiorini Spa",
    "wof:placetype":"venue"
},
  "geometry": {"coordinates":[13.1707706451,43.7405815125],"type":"Point"}
}