{
  "type": "Feature",
  "properties": {
    "addr:full":"43100 Parma Parma Parma 43100",
    "addr:postcode":"43100;43100",
    "iso:country":"IT",
    "sg:address":"43100 Parma",
    "sg:city":"Parma",
    "sg:orig_category":"Materiali E Componenti Elettrotecnici",
    "sg:phone":"+39 0521 780724",
    "sg:postcode":"43100",
    "sg:province":"Parma",
    "wof:name":"Elettrotermica Gandolfi G. (s.a.s.)",
    "wof:placetype":"venue"
},
  "geometry": {"coordinates":[10.342345,44.81105],"type":"Point"}
}