{
  "type": "Feature",
  "properties": {
    "iso:country":"IT",
    "sg:address":"20145 Milano",
    "sg:city":"Milano",
    "sg:orig_category":"Articoli Da Regalo. Arte Ed Artigianato Artistico. Shopping",
    "sg:postcode":"20145",
    "sg:province":"Milano",
    "wof:name":"Bengal Di Pozzo Renata Corrieri",
    "wof:placetype":"venue"
},
  "geometry": {"coordinates":[9.155805,45.46854],"type":"Point"}
}