{
  "type": "Feature",
  "properties": {
    "iso:country":"IT",
    "sg:address":"25030 Barbariga",
    "sg:city":"Barbariga",
    "sg:classifiers":[
        {
            "category":"Shopping",
            "subcategory":"Computers & Home Electronics",
            "type":"Retail Goods"
        }
    ],
    "sg:phone":"+39 030 997 1288",
    "sg:postcode":"25030",
    "sg:province":"Brescia",
    "sg:tags":[
        "personal",
        "ed",
        "accessori"
    ],
    "sg:website":"http://www.servicebassini.it",
    "wof:name":"Service Bassini",
    "wof:placetype":"venue"
},
  "geometry": {"coordinates":[10.055480957,45.4061126709],"type":"Point"}
}