{
  "type": "Feature",
  "properties": {
    "addr:full":"12, Via Galvani Luigi 20054 Nova Milanese Nova Milanese Milano 20054",
    "addr:postcode":"20054;20054",
    "addr:street":"Via Galvani Luigi",
    "iso:country":"IT",
    "sg:address":"12, Via Galvani Luigi 20054 Nova Milanese",
    "sg:city":"Nova Milanese",
    "sg:classifiers":[
        {
            "category":"Manufacturing",
            "subcategory":"Metals",
            "type":"Manufacturing & Wholesale Goods"
        }
    ],
    "sg:phone":"+39 036 236 6924",
    "sg:postcode":"20054",
    "sg:province":"Milano",
    "sg:tags":[
        "processing"
    ],
    "wof:name":"Tecnomec S.n.c.",
    "wof:placetype":"venue"
},
  "geometry": {"coordinates":[9.1881408691,45.4636878967],"type":"Point"}
}