{
  "type": "Feature",
  "properties": {
    "iso:country":"IT",
    "sg:address":"90123 Palermo",
    "sg:city":"Palermo",
    "sg:orig_category":"Impiantistica E Prodotti Tecnologici Per Edilizia",
    "sg:phone":"+39 091 474456",
    "sg:postcode":"90123",
    "sg:province":"Palermo",
    "wof:name":"Savem Srl",
    "wof:placetype":"venue"
},
  "geometry": {"coordinates":[13.390911,38.10268],"type":"Point"}
}