{
  "type": "Feature",
  "properties": {
    "addr:full":"84014 Nocera Inferiore Nocera Inferiore Salerno 84014",
    "addr:postcode":"84014;84014",
    "iso:country":"IT",
    "sg:address":"84014 Nocera Inferiore",
    "sg:city":"Nocera Inferiore",
    "sg:classifiers":[
        {
            "category":"Utilities",
            "subcategory":"Natural Gas",
            "type":"Services"
        }
    ],
    "sg:phone":"+39 081 937007",
    "sg:postcode":"84014",
    "sg:province":"Salerno",
    "sg:tags":[
        "alloy",
        "metal"
    ],
    "wof:name":"Ve.pr.al. Snc",
    "wof:placetype":"venue"
},
  "geometry": {"coordinates":[14.641292572,40.7584381104],"type":"Point"}
}