{
  "type": "Feature",
  "properties": {
    "addr:full":"16, Via Antonio Locatelli 24069 Trescore Balneario Trescore Balneario Bergamo 24069",
    "addr:postcode":"24069;24069",
    "addr:street":"Via Antonio Locatelli",
    "iso:country":"IT",
    "sg:address":"16, Via Antonio Locatelli 24069 Trescore Balneario",
    "sg:city":"Trescore Balneario",
    "sg:classifiers":[
        {
            "category":"Bars & Pubs",
            "subcategory":"Nightclub",
            "type":"Food & Drink"
        }
    ],
    "sg:phone":"+39 39035940344",
    "sg:postcode":"24069",
    "sg:province":"Bergamo",
    "sg:tags":[
        "cake",
        "bread"
    ],
    "wof:name":"Pasticceria Giovanni Pina S.n.c. Di Lucia Anita E Giovanni Pina & C.",
    "wof:placetype":"venue"
},
  "geometry": {"coordinates":[9.84052,45.695072],"type":"Point"}
}