{
  "type": "Feature",
  "properties": {
    "iso:country":"IT",
    "sg:address":"25064 Gussago",
    "sg:city":"Gussago",
    "sg:orig_category":"Gioielleria, Oreficeria E Argenteria. Articoli Da Regalo. Shopping",
    "sg:phone":"+39 030 277 2383",
    "sg:postcode":"25064",
    "sg:province":"Brescia",
    "wof:name":"Peroni Attilio",
    "wof:placetype":"venue"
},
  "geometry": {"coordinates":[10.136017,45.594807],"type":"Point"}
}