{
  "type": "Feature",
  "properties": {
    "iso:country":"IT",
    "sg:address":"00154 Roma",
    "sg:city":"Roma",
    "sg:orig_category":"Apparecchiature E Sistemi Per Magazzinaggio E Movimentazione",
    "sg:phone":"+39 06 513 5249",
    "sg:postcode":"00154",
    "sg:province":"Roma",
    "wof:name":"Minguzzi Srl",
    "wof:placetype":"venue"
},
  "geometry": {"coordinates":[12.486796,41.863792],"type":"Point"}
}