{
  "type": "Feature",
  "properties": {
    "iso:country":"IT",
    "sg:address":"24020 Azzone",
    "sg:city":"Azzone",
    "sg:orig_category":"Apparecchiature Ed Attrezzature Meccaniche. Elettrotecnica Industriale, Prodotti E Apparecchiature",
    "sg:phone":"+39 0346 54362",
    "sg:postcode":"24020",
    "sg:province":"Bergamo",
    "wof:name":"Nord Impianti (s.r.l.)",
    "wof:placetype":"venue"
},
  "geometry": {"coordinates":[10.111897,45.979233],"type":"Point"}
}