{
  "type": "Feature",
  "properties": {
    "iso:country":"IT",
    "sg:address":"20134 Milano",
    "sg:city":"Milano",
    "sg:orig_category":"Studi E Consulenze Tecniche E Industriali. Assicurazioni E Servizi Assicurativi. Consulenze Tecniche, Amministrative E Perizie",
    "sg:phone":"+39 02 2159 7506",
    "sg:postcode":"20134",
    "sg:province":"Milano",
    "wof:name":"Rossi Diego",
    "wof:placetype":"venue"
},
  "geometry": {"coordinates":[9.24231,45.48737],"type":"Point"}
}