{
  "type": "Feature",
  "properties": {
    "addr:full":"25049 Iseo Iseo Brescia 25049",
    "addr:postcode":"25049;25049",
    "iso:country":"IT",
    "sg:address":"25049 Iseo",
    "sg:city":"Iseo",
    "sg:orig_category":"Centri Di Estetica E Cosmesi E Servizi",
    "sg:phone":"+39 030 984 0970",
    "sg:postcode":"25049",
    "sg:province":"Brescia",
    "wof:name":"Riva Alioscia",
    "wof:placetype":"venue"
},
  "geometry": {"coordinates":[10.050583,45.659042],"type":"Point"}
}