{
  "type": "Feature",
  "properties": {
    "addr:full":"35010 Santa Giustina In Colle Santa Giustina in Colle Padova 35010",
    "addr:postcode":"35010;35010",
    "addr:street":"Santa Giustina In Colle;Giustina In Colle",
    "iso:country":"IT",
    "sg:address":"35010 Santa Giustina In Colle",
    "sg:city":"Santa Giustina in Colle",
    "sg:orig_category":"Servizi E Lavori Industria Chimica",
    "sg:phone":"+39 049 932 0046",
    "sg:postcode":"35010",
    "sg:province":"Padova",
    "wof:name":"Bernardo Renato",
    "wof:placetype":"venue"
},
  "geometry": {"coordinates":[11.89171,45.572922],"type":"Point"}
}