{
  "type": "Feature",
  "properties": {
    "addr:full":"30175 Marghera Marghera Venezia 30175",
    "addr:postcode":"30175;30175",
    "iso:country":"IT",
    "sg:address":"30175 Marghera",
    "sg:city":"Marghera",
    "sg:orig_category":"Prodotti Chimici Secondari. Servizi E Lavori Industria Chimica. Servizi E Lavori Per Ecologia E Smaltimento Rifiuti. Macchine E Forniture Per Ecologia E Smaltimento Rifiuti. Servizi Ausiliari Di Sorve",
    "sg:phone":"+39 041 921260",
    "sg:postcode":"30175",
    "sg:province":"Venezia",
    "wof:name":"S.i.t. Di Maggiori Roberto & C. S.n.c.",
    "wof:placetype":"venue"
},
  "geometry": {"coordinates":[12.2163209915,45.4657516479],"type":"Point"}
}