{
  "type": "Feature",
  "properties": {
    "addr:full":"40052 San Gabriele San Gabriele Bologna 40052",
    "addr:housenumber":"40052",
    "addr:postcode":"40052",
    "addr:street":"San Gabriele San Gabriele",
    "iso:country":"IT",
    "sg:address":"40052 San Gabriele",
    "sg:city":"San Gabriele",
    "sg:orig_category":"Servizi E Lavori Per Edilizia E Lavori Pubblici. Servizi E Lavori Per Ecologia E Smaltimento Rifiuti. Macchine E Forniture Per Ecologia E Smaltimento Rifiuti. Acqua, Luce, Gas E Societa' Di Esercizio ",
    "sg:phone":"+39 051 874365",
    "sg:postcode":"40052",
    "sg:province":"Bologna",
    "wof:name":"Prometeo' Associazione Volontari Protezione Civile",
    "wof:placetype":"venue"
},
  "geometry": {"coordinates":[11.577721,44.665264],"type":"Point"}
}