{
  "type": "Feature",
  "properties": {
    "addr:full":"95027 San Gregorio Di Catania San Gregorio di Catania Catania 95027",
    "addr:housenumber":"95027",
    "addr:postcode":"95027",
    "addr:street":"San",
    "iso:country":"IT",
    "sg:address":"95027 San Gregorio Di Catania",
    "sg:city":"San Gregorio di Catania",
    "sg:orig_category":"Ceramiche Artistiche",
    "sg:phone":"+39 095 524231",
    "sg:postcode":"95027",
    "sg:province":"Catania",
    "wof:name":"Sorgi Salvatore",
    "wof:placetype":"venue"
},
  "geometry": {"coordinates":[15.10577,37.565979],"type":"Point"}
}