{
  "type": "Feature",
  "properties": {
    "iso:country":"IT",
    "sg:address":"96010 Solarino",
    "sg:city":"Solarino",
    "sg:orig_category":"Ceramiche: Prodotti E Lavorazioni. Articoli Da Regalo. Arte Ed Artigianato Artistico. Shopping",
    "sg:phone":"+39 0931 922997",
    "sg:postcode":"96010",
    "sg:province":"Siracusa",
    "wof:name":"Bottega Del Verrocchio",
    "wof:placetype":"venue"
},
  "geometry": {"coordinates":[15.12138,37.102169],"type":"Point"}
}