{
  "type": "Feature",
  "properties": {
    "iso:country":"IT",
    "sg:address":"81031 Aversa",
    "sg:city":"Aversa",
    "sg:orig_category":"Arredo Cucina Ed Elettrodomestici. Elettrodomestici",
    "sg:phone":"+39 081 812 4002",
    "sg:postcode":"81031",
    "sg:province":"Caserta",
    "wof:name":"Ime Sud Europe Snc",
    "wof:placetype":"venue"
},
  "geometry": {"coordinates":[14.201299,41.01815],"type":"Point"}
}