{
  "type": "Feature",
  "properties": {
    "addr:full":"13, Via Del Portello 35129 Padova Padova Padova 35129",
    "addr:postcode":"35129;35129",
    "addr:street":"Via Del Portello",
    "iso:country":"IT",
    "sg:address":"13, Via Del Portello 35129 Padova",
    "sg:city":"Padova",
    "sg:classifiers":[
        {
            "category":"Communications",
            "subcategory":"Television Station",
            "type":"Services"
        }
    ],
    "sg:phone":"+39 049 807 1275",
    "sg:postcode":"35129",
    "sg:province":"Padova",
    "sg:tags":[
        "equipment",
        "optical",
        "instrument"
    ],
    "wof:name":"Burloni G. (s.r.l.)",
    "wof:placetype":"venue"
},
  "geometry": {"coordinates":[11.844167,45.397499],"type":"Point"}
}