{
  "type": "Feature",
  "properties": {
    "iso:country":"IT",
    "sg:address":"80142 Napoli",
    "sg:city":"Napoli",
    "sg:orig_category":"Utensili Meccanici E Materiali",
    "sg:phone":"+39 081 553 5846",
    "sg:postcode":"80142",
    "sg:province":"Napoli",
    "wof:name":"Forget S.a.s.",
    "wof:placetype":"venue"
},
  "geometry": {"coordinates":[14.275728,40.849861],"type":"Point"}
}