{
  "type": "Feature",
  "properties": {
    "iso:country":"IT",
    "sg:address":"46040 Cavriana",
    "sg:city":"Cavriana",
    "sg:orig_category":"Spazzole Industriali",
    "sg:phone":"+39 0376 82345",
    "sg:postcode":"46040",
    "sg:province":"Mantova",
    "wof:name":"Trebeschi Pierino",
    "wof:placetype":"venue"
},
  "geometry": {"coordinates":[10.543116,45.245449],"type":"Point"}
}