{
  "type": "Feature",
  "properties": {
    "addr:full":"Via Genova, 9/11 20096 Pioltello Pioltello Milano 20096",
    "addr:housenumber":"9 / 11",
    "addr:postcode":"20096;20096",
    "addr:street":"Via Genova",
    "iso:country":"IT",
    "sg:address":"Via Genova, 9/11 20096 Pioltello",
    "sg:city":"Pioltello",
    "sg:classifiers":[
        {
            "category":"Wholesale",
            "subcategory":"Machinery & Supplies",
            "type":"Manufacturing & Wholesale Goods"
        }
    ],
    "sg:phone":"+39 02 9216 1780",
    "sg:postcode":"20096",
    "sg:province":"Milano",
    "sg:tags":[
        "dyeing",
        "machine",
        "piece"
    ],
    "wof:name":"Bertazzo Enzo Meccanica E Stampaggio",
    "wof:placetype":"venue"
},
  "geometry": {"coordinates":[9.3353624344,45.4872131348],"type":"Point"}
}