{
  "type": "Feature",
  "properties": {
    "addr:full":"20092 Cinisello Balsamo Cinisello Balsamo Milano 20092",
    "addr:postcode":"20092;20092",
    "iso:country":"IT",
    "sg:address":"20092 Cinisello Balsamo",
    "sg:city":"Cinisello Balsamo",
    "sg:orig_category":"Prodotti Vari In Metallo",
    "sg:phone":"+39 02 6604 8661",
    "sg:postcode":"20092",
    "sg:province":"Milano",
    "wof:name":"Trafilerie E Corderie Italiane (s.p.a.)",
    "wof:placetype":"venue"
},
  "geometry": {"coordinates":[9.2255105972,45.5467796326],"type":"Point"}
}