{
  "type": "Feature",
  "properties": {
    "addr:full":"10138 Torino Torino Torino 10138",
    "addr:housenumber":"10138",
    "addr:postcode":"10138",
    "iso:country":"IT",
    "sg:address":"10138 Torino",
    "sg:city":"Torino",
    "sg:orig_category":"Agenzie Investigative",
    "sg:phone":"+39 011 433 0771",
    "sg:postcode":"10138",
    "sg:province":"Torino",
    "wof:name":"Turinform Sas",
    "wof:placetype":"venue"
},
  "geometry": {"coordinates":[7.6624588966,45.0748786926],"type":"Point"}
}