{
  "type": "Feature",
  "properties": {
    "addr:full":"37060 Sorga' Bonferraro Verona 37060",
    "addr:postcode":"37060;37060",
    "addr:street":"Sorga",
    "iso:country":"IT",
    "sg:address":"37060 Sorga'",
    "sg:city":"Bonferraro",
    "sg:orig_category":"Articoli Pulizia. Macchine E Forniture Per Ecologia E Smaltimento Rifiuti. Forniture Per Attivita' Commerciali Ed Artigianali",
    "sg:phone":"+39 045 665 5113",
    "sg:postcode":"37060",
    "sg:province":"Verona",
    "wof:name":"Rasmas Di Menegollo Marco",
    "wof:placetype":"venue"
},
  "geometry": {"coordinates":[10.999274,45.18037],"type":"Point"}
}