{
  "type": "Feature",
  "properties": {
    "iso:country":"IT",
    "sg:address":"00185 Roma",
    "sg:city":"Roma",
    "sg:orig_category":"Non-classified Establishments",
    "sg:phone":"+39 06 4470 2777",
    "sg:postcode":"00185",
    "sg:province":"Roma",
    "wof:name":"Industrie Emiliana Parati S.r.l.",
    "wof:placetype":"venue"
},
  "geometry": {"coordinates":[12.511761,41.897079],"type":"Point"}
}