{
  "type": "Feature",
  "properties": {
    "iso:country":"IT",
    "sg:address":"24020 Cerete",
    "sg:city":"Cerete",
    "sg:orig_category":"Macchine Ed Impianti Per Edilizia E Lavori Pubblici",
    "sg:postcode":"24020",
    "sg:province":"Bergamo",
    "wof:name":"Bettoni (s.r.l.)",
    "wof:placetype":"venue"
},
  "geometry": {"coordinates":[9.690362,45.676464],"type":"Point"}
}