{
  "type": "Feature",
  "properties": {
    "iso:country":"IT",
    "sg:address":"17100 Savona",
    "sg:city":"Savona",
    "sg:orig_category":"Tappeti Persiani Ed Orientali",
    "sg:phone":"+39 019 812894",
    "sg:postcode":"17100",
    "sg:province":"Savona",
    "wof:name":"Gulli Tappeti",
    "wof:placetype":"venue"
},
  "geometry": {"coordinates":[8.335277,44.334545],"type":"Point"}
}