{
  "type": "Feature",
  "properties": {
    "iso:country":"IT",
    "sg:address":"Via Brianza 8 22040 Lurago D'erba",
    "sg:classifiers":[
        {
            "category":"Military Area",
            "subcategory":"Air Force Base",
            "type":"Public Place"
        }
    ],
    "sg:phone":"+39 031 699907",
    "sg:postcode":"22040",
    "sg:province":"Como",
    "sg:tags":[
        "corrugated",
        "cardboard",
        "folding"
    ],
    "sg:website":"www.ondolutalecchese.it",
    "wof:name":"Ondulato Lecchese Spa",
    "wof:placetype":"venue"
},
  "geometry": {"coordinates":[9.2319278717,45.758102417],"type":"Point"}
}