{
  "type": "Feature",
  "properties": {
    "iso:country":"IT",
    "sg:address":"Contrada Rinelli 97019 Vittoria",
    "sg:city":"Vittoria",
    "sg:classifiers":[
        {
            "category":"Farming",
            "subcategory":"Livestock Farm",
            "type":"Manufacturing & Wholesale Goods"
        }
    ],
    "sg:phone":"+39 0932 867257",
    "sg:postcode":"97019",
    "sg:province":"Ragusa",
    "sg:tags":[
        "agriculture"
    ],
    "wof:name":"Libretti Srl",
    "wof:placetype":"venue"
},
  "geometry": {"coordinates":[14.728503,36.925911],"type":"Point"}
}