{
  "type": "Feature",
  "properties": {
    "iso:country":"IT",
    "sg:address":"Via Emilia, 3862 - Budrio 47020 Longiano",
    "sg:city":"Budrio",
    "sg:orig_category":"Hotels: Furniture",
    "sg:phone":"+39 0547 58050",
    "sg:postcode":"47020",
    "sg:province":"Forl\u00ec-Cesena",
    "sg:website":"www.pollinimobili.it",
    "wof:name":"Mobilificio R.g.r Di Pollini & Figl",
    "wof:placetype":"venue"
},
  "geometry": {"coordinates":[12.322224,44.107643],"type":"Point"}
}