{
  "type": "Feature",
  "properties": {
    "iso:country":"IT",
    "sg:address":"8, Corso Sempione 28802 Mergozzo",
    "sg:city":"Mergozzo",
    "sg:classifiers":[
        {
            "category":"Manufacturing",
            "subcategory":"Rubber & Plastics",
            "type":"Manufacturing & Wholesale Goods"
        }
    ],
    "sg:phone":"+39 0323 846886",
    "sg:postcode":"28802",
    "sg:province":"Verbano-Cusio-Ossola",
    "wof:name":"G.m. Plast S.r.l.",
    "wof:placetype":"venue"
},
  "geometry": {"coordinates":[8.4476165771,45.9609413147],"type":"Point"}
}