{
  "type": "Feature",
  "properties": {
    "addr:full":"Via Berettine 2b 43010 Fontevivo Fontevivo Parma 43010",
    "addr:housenumber":"2b",
    "addr:postcode":"43010;43010",
    "addr:street":"Via Berettine",
    "iso:country":"IT",
    "sg:address":"Via Berettine 2b 43010 Fontevivo",
    "sg:city":"Fontevivo",
    "sg:classifiers":[
        {
            "category":"Social Services",
            "subcategory":"Job Training",
            "type":"Services"
        }
    ],
    "sg:phone":"+39 0521 610700",
    "sg:postcode":"43010",
    "sg:province":"Parma",
    "sg:tags":[
        "industrial",
        "printer"
    ],
    "sg:website":"www.custom.it",
    "wof:name":"Custom Engineering Spa",
    "wof:placetype":"venue"
},
  "geometry": {"coordinates":[10.172961,44.858578],"type":"Point"}
}