{
  "type": "Feature",
  "properties": {
    "iso:country":"IT",
    "sg:address":"Via Spezia 74; Collecchio; 43044",
    "sg:city":"Collecchio",
    "sg:classifiers":[
        {
            "category":"Banks & Credit Unions",
            "subcategory":"Bank",
            "type":"Services"
        }
    ],
    "sg:phone":"+39 0521 806209",
    "sg:postcode":"43044",
    "sg:province":"Parma",
    "wof:name":"Credito Milano Spa",
    "wof:placetype":"venue"
},
  "geometry": {"coordinates":[10.214657,44.751545],"type":"Point"}
}