{
  "type": "Feature",
  "properties": {
    "iso:country":"IT",
    "sg:address":"4, Vicolo Ariosto 20029 Turbigo",
    "sg:city":"Turbigo",
    "sg:classifiers":[
        {
            "category":"Personal",
            "subcategory":"Shoe Repair & Shine",
            "type":"Services"
        }
    ],
    "sg:phone":"+39 0331 890243",
    "sg:postcode":"20029",
    "sg:province":"Milano",
    "sg:tags":[
        "leather"
    ],
    "wof:name":"Merisio Fratelli Di Angelo Merisio E C. (s.n.c.)",
    "wof:placetype":"venue"
},
  "geometry": {"coordinates":[8.737409,45.537849],"type":"Point"}
}