{
  "type": "Feature",
  "properties": {
    "addr:full":"Via Papa Giovanni Xxiii 8a 13882 Cerrione Cerrione Biella 13882",
    "addr:housenumber":"8a",
    "addr:postcode":"13882;13882",
    "addr:street":"Via Papa Giovanni Xxiii",
    "iso:country":"IT",
    "sg:address":"Via Papa Giovanni Xxiii 8a 13882 Cerrione",
    "sg:city":"Cerrione",
    "sg:classifiers":[
        {
            "category":"Shopping",
            "subcategory":"Clothing, Apparel, & Fashions",
            "type":"Retail Goods"
        }
    ],
    "sg:phone":"+39 015 258 3067",
    "sg:postcode":"13882",
    "sg:province":"Biella",
    "sg:tags":[
        "shawl",
        "scarf"
    ],
    "sg:website":"www.maalbi.com",
    "wof:name":"Ma.al.bi. S.r.l.",
    "wof:placetype":"venue"
},
  "geometry": {"coordinates":[8.089296,45.487617],"type":"Point"}
}