{
  "type": "Feature",
  "properties": {
    "addr:full":"90143 Palermo Palermo Palermo 90143",
    "addr:postcode":"90143;90143",
    "iso:country":"IT",
    "sg:address":"90143 Palermo",
    "sg:city":"Palermo",
    "sg:orig_category":"Prodotti Alimentari",
    "sg:phone":"+39 091 626 9504",
    "sg:postcode":"90143",
    "sg:province":"Palermo",
    "wof:name":"Lodama Di D'antoni Eugenio",
    "wof:placetype":"venue"
},
  "geometry": {"coordinates":[13.3560857773,38.1355934143],"type":"Point"}
}