{
  "type": "Feature",
  "properties": {
    "addr:full":"40011 Anzola Dell'emilia Bologna 40011",
    "addr:postcode":"40011;40011",
    "iso:country":"IT",
    "sg:address":"40011 Anzola Dell'emilia",
    "sg:orig_category":"Servizi E Lavori Per Arredamento E Industria Del Legno. Servizi E Lavori Per Edilizia E Lavori Pubblici",
    "sg:phone":"+39 051 732222",
    "sg:postcode":"40011",
    "sg:province":"Bologna",
    "sg:website":"http://www.laporta.it",
    "wof:name":"La Porta",
    "wof:placetype":"venue"
},
  "geometry": {"coordinates":[11.22014,44.53677],"type":"Point"}
}