{
  "type": "Feature",
  "properties": {
    "iso:country":"IT",
    "sg:address":"88, Via Zorutti 33030 Campoformido",
    "sg:city":"Campoformido",
    "sg:classifiers":[
        {
            "category":"Wholesale",
            "subcategory":"Drugs",
            "type":"Manufacturing & Wholesale Goods"
        }
    ],
    "sg:phone":"+39 0432 653711",
    "sg:postcode":"33030",
    "sg:province":"Udine",
    "sg:tags":[
        "chemical",
        "pharmaceutical"
    ],
    "wof:name":"Friulanagas S.p.a.",
    "wof:placetype":"venue"
},
  "geometry": {"coordinates":[13.229218,46.06638],"type":"Point"}
}