{
  "type": "Feature",
  "properties": {
    "iso:country":"IT",
    "sg:address":"20146 Milano",
    "sg:city":"Milano",
    "sg:orig_category":"Agenzie D'affari E Servizi Commerciali",
    "sg:phone":"+39 02 418967",
    "sg:postcode":"20146",
    "sg:province":"Milano",
    "wof:name":"My Line Di Noak Roberto Lorenzo",
    "wof:placetype":"venue"
},
  "geometry": {"coordinates":[9.135799,45.45623],"type":"Point"}
}