{
  "type": "Feature",
  "properties": {
    "addr:full":"77, Via Toscana 41053 Maranello Maranello Modena 41053",
    "addr:postcode":"41053;41053",
    "addr:street":"Via Toscana",
    "iso:country":"IT",
    "sg:address":"77, Via Toscana 41053 Maranello",
    "sg:city":"Maranello",
    "sg:classifiers":[
        {
            "category":"Shopping",
            "subcategory":"Crafts & Fabrics",
            "type":"Retail Goods"
        }
    ],
    "sg:phone":"+39 0536 948018",
    "sg:postcode":"41053",
    "sg:province":"Modena",
    "sg:tags":[
        "ceramic"
    ],
    "wof:name":"Stilnovo S.r.l.",
    "wof:placetype":"venue"
},
  "geometry": {"coordinates":[10.875392,44.530663],"type":"Point"}
}