{
  "type": "Feature",
  "properties": {
    "addr:full":"41051 Castelnuovo Rangone Castelnuovo Rangone Modena 41051",
    "addr:postcode":"41051;41051",
    "iso:country":"IT",
    "sg:address":"41051 Castelnuovo Rangone",
    "sg:city":"Castelnuovo Rangone",
    "sg:orig_category":"Macchine Ed Impianti Per Edilizia E Lavori Pubblici",
    "sg:phone":"+39 059 537460",
    "sg:postcode":"41051",
    "sg:province":"Modena",
    "wof:name":"United Symbol S.r.l.",
    "wof:placetype":"venue"
},
  "geometry": {"coordinates":[10.929661,44.54298],"type":"Point"}
}