{
  "type": "Feature",
  "properties": {
    "iso:country":"IT",
    "sg:address":"20091 Bresso",
    "sg:city":"Bresso",
    "sg:orig_category":"Forniture Per Abbigliamento E Pelletterie",
    "sg:phone":"+39 02 610 5710",
    "sg:postcode":"20091",
    "sg:province":"Milano",
    "wof:name":"Bresso Bottoni Moda (s.r.l.)",
    "wof:placetype":"venue"
},
  "geometry": {"coordinates":[9.1966743469,45.539932251],"type":"Point"}
}