{
  "type": "Feature",
  "properties": {
    "iso:country":"IT",
    "sg:address":"43040 Varano De'melegari",
    "sg:orig_category":"Motori Ed Organi Di Trasmissione. Ricambi E Componenti Dei Mezzi Di Trasporto",
    "sg:phone":"+39 0525 53525",
    "sg:postcode":"43040",
    "sg:province":"Parma",
    "wof:name":"Cazzaniga Francesco",
    "wof:placetype":"venue"
},
  "geometry": {"coordinates":[10.0124998093,44.68907547],"type":"Point"}
}