{
  "type": "Feature",
  "properties": {
    "addr:full":"V. E. Codignola 50018 Scandicci Scandicci Firenze 50018",
    "addr:postcode":"50018;50018",
    "addr:street":"V.",
    "iso:country":"IT",
    "sg:address":"V. E. Codignola 50018 Scandicci",
    "sg:city":"Scandicci",
    "sg:classifiers":[
        {
            "category":"Personal",
            "subcategory":"Shoe Repair & Shine",
            "type":"Services"
        }
    ],
    "sg:phone":"+39 39055735061",
    "sg:postcode":"50018",
    "sg:province":"Firenze",
    "sg:tags":[
        "leather"
    ],
    "sg:website":"http://www.thebridge.it:ws_end: :mark:ws:http://www.paginegialle.it/thebridge",
    "wof:name":"Il Ponte Pelletteria Spa",
    "wof:placetype":"venue"
},
  "geometry": {"coordinates":[11.167,43.765202],"type":"Point"}
}