{
  "type": "Feature",
  "properties": {
    "iso:country":"IT",
    "sg:address":"Localita' Neziole 25055 Pisogne",
    "sg:city":"Pisogne",
    "sg:classifiers":[
        {
            "category":"Shopping",
            "type":"Retail Goods"
        }
    ],
    "sg:phone":"+39 036 489 9020",
    "sg:postcode":"25055",
    "sg:province":"Brescia",
    "sg:tags":[
        "finished",
        "-",
        "metallic"
    ],
    "wof:name":"R.e.i. Tregi Di Gervasoni Maurilio E C. (s.a.s.)",
    "wof:placetype":"venue"
},
  "geometry": {"coordinates":[10.1241703033,45.8208656311],"type":"Point"}
}