{
  "type": "Feature",
  "properties": {
    "iso:country":"IT",
    "sg:address":"Via Negrelli 8 39100 Bolzano",
    "sg:city":"Bolzano",
    "sg:classifiers":[
        {
            "category":"Retail",
            "subcategory":"Repair Shop",
            "type":"Services"
        }
    ],
    "sg:phone":"+39 0471 204330",
    "sg:postcode":"39100",
    "sg:province":"Bolzano/Bozen",
    "sg:tags":[
        "car",
        "equipment"
    ],
    "sg:website":"www.foerch.it",
    "wof:name":"F\u00d6rch Srl",
    "wof:placetype":"venue"
},
  "geometry": {"coordinates":[11.328239,46.461643],"type":"Point"}
}