{
  "type": "Feature",
  "properties": {
    "addr:full":"25121 Brescia Brescia Brescia 25121",
    "addr:postcode":"25121;25121",
    "iso:country":"IT",
    "sg:address":"25121 Brescia",
    "sg:city":"Brescia",
    "sg:orig_category":"Ricevimenti E Banchetti - Sale E Servizi",
    "sg:phone":"+39 030 295603",
    "sg:postcode":"25121",
    "sg:province":"Brescia",
    "sg:website":"http://www.lasosta.it",
    "wof:name":"Ristorante La Sosta Srl",
    "wof:placetype":"venue"
},
  "geometry": {"coordinates":[11.115941,45.418343],"type":"Point"}
}