{
  "type": "Feature",
  "properties": {
    "addr:full":"73012 Campi Salentina Campi Salentina Lecce 73012",
    "addr:postcode":"73012;73012",
    "iso:country":"IT",
    "sg:address":"73012 Campi Salentina",
    "sg:city":"Campi Salentina",
    "sg:orig_category":"Manufacturers: Prefabbricati",
    "sg:phone":"+39 0832 791254",
    "sg:postcode":"73012",
    "sg:province":"Lecce",
    "wof:name":"Taurino Antonio",
    "wof:placetype":"venue"
},
  "geometry": {"coordinates":[18.065685,40.40641],"type":"Point"}
}