{
  "type": "Feature",
  "properties": {
    "iso:country":"IT",
    "sg:address":"18, Via Delle Vigne 21040 Venegono Inferiore",
    "sg:city":"Venegono Inferiore",
    "sg:classifiers":[
        {
            "category":"Shopping",
            "type":"Retail Goods"
        }
    ],
    "sg:phone":"+39 0331 864669",
    "sg:postcode":"21040",
    "sg:province":"Varese",
    "sg:tags":[
        "finished",
        "-",
        "metallic"
    ],
    "wof:name":"Gi.bi. (s.r.l.)",
    "wof:placetype":"venue"
},
  "geometry": {"coordinates":[8.8817777634,45.7323112488],"type":"Point"}
}