{
  "type": "Feature",
  "properties": {
    "iso:country":"IT",
    "sg:address":"00154 Roma",
    "sg:city":"Roma",
    "sg:orig_category":"Scuole E Servizi Scolastici. Ricerca, Selezione E Formazione Del Personale",
    "sg:phone":"+39 06 575 7185",
    "sg:postcode":"00154",
    "sg:province":"Roma",
    "sg:website":"http://www.scuolarestauro.it",
    "wof:name":"Istituto Italiano Arte Artigianato E Restauro Srl",
    "wof:placetype":"venue"
},
  "geometry": {"coordinates":[12.486789,41.870888],"type":"Point"}
}