{
  "type": "Feature",
  "properties": {
    "addr:full":"56040 Montescudaio Montescudaio Pisa 56040",
    "addr:postcode":"56040;56040",
    "iso:country":"IT",
    "sg:address":"56040 Montescudaio",
    "sg:city":"Montescudaio",
    "sg:orig_category":"Prodotti E Manufatti In Materie Plastiche. Forniture Per Edilizia E Lavori Pubblici",
    "sg:phone":"+39 0586 764690",
    "sg:postcode":"56040",
    "sg:province":"Pisa",
    "wof:name":"Resin Tubi",
    "wof:placetype":"venue"
},
  "geometry": {"coordinates":[10.6270370483,43.3270378113],"type":"Point"}
}