{
  "type": "Feature",
  "properties": {
    "iso:country":"IT",
    "sg:address":"20134 Milano",
    "sg:city":"Milano",
    "sg:orig_category":"Servizi Per Lo Sport E Il Tempo Libero. Associazioni Ed Organismi Di Interesse Pubblico",
    "sg:phone":"+39 02 217221",
    "sg:postcode":"20134",
    "sg:province":"Milano",
    "wof:name":"F.i.g.c. Lega Nazionale Dilettanti",
    "wof:placetype":"venue"
},
  "geometry": {"coordinates":[9.245799,45.47971],"type":"Point"}
}