{
  "type": "Feature",
  "properties": {
    "iso:country":"IT",
    "sg:address":"Via Padre Vittorio; Villaricca; 80010",
    "sg:city":"Villaricca",
    "sg:classifiers":[
        {
            "category":"Banks & Credit Unions",
            "subcategory":"Bank",
            "type":"Services"
        }
    ],
    "sg:phone":"+39 081 506 0921",
    "sg:postcode":"80010",
    "sg:province":"Napoli",
    "wof:name":"Banca Nazionale Del Lavoro Spa",
    "wof:placetype":"venue"
},
  "geometry": {"coordinates":[14.187824,40.921021],"type":"Point"}
}