{
  "type": "Feature",
  "properties": {
    "addr:full":"55012 Capannori Capannori Lucca 55012",
    "addr:postcode":"55012;55012",
    "iso:country":"IT",
    "sg:address":"55012 Capannori",
    "sg:city":"Capannori",
    "sg:classifiers":[
        {
            "category":"Manufacturing",
            "subcategory":"Leather Goods",
            "type":"Manufacturing & Wholesale Goods"
        }
    ],
    "sg:phone":"+39 0583 928107",
    "sg:postcode":"55012",
    "sg:province":"Lucca",
    "sg:tags":[
        "footwear",
        "skin"
    ],
    "sg:website":"http://www.orienteshoes.it",
    "wof:name":"Oriente Shoes Srl",
    "wof:placetype":"venue"
},
  "geometry": {"coordinates":[10.5930318832,43.8841514587],"type":"Point"}
}