{
  "type": "Feature",
  "properties": {
    "iso:country":"IT",
    "sg:address":"50010 Campi Bisenzio",
    "sg:classifiers":[
        {
            "category":"Wholesale",
            "subcategory":"Machinery & Supplies",
            "type":"Manufacturing & Wholesale Goods"
        }
    ],
    "sg:phone":"+39 055 898 6235",
    "sg:postcode":"50010",
    "sg:province":"Firenze",
    "sg:tags":[
        "component",
        "engineering",
        "material",
        "electrical"
    ],
    "sg:website":"http://www.dga.it",
    "wof:name":"Dga Fibre Ottiche Srl",
    "wof:placetype":"venue"
},
  "geometry": {"coordinates":[11.131623,43.836643],"type":"Point"}
}