{
  "type": "Feature",
  "properties": {
    "iso:country":"IT",
    "sg:address":"37137 Verona",
    "sg:city":"Verona",
    "sg:orig_category":"Automobili E Mezzi Di Trasporto",
    "sg:phone":"+39 045 809 1111",
    "sg:postcode":"37137",
    "sg:province":"Verona",
    "wof:name":"Volkswagen",
    "wof:placetype":"venue"
},
  "geometry": {"coordinates":[10.932043,45.421734],"type":"Point"}
}