{
  "type": "Feature",
  "properties": {
    "addr:full":"Via Trento 113 25123 Brescia Brescia Brescia 25123",
    "addr:housenumber":"113",
    "addr:postcode":"25123;25123",
    "addr:street":"Via Trento",
    "iso:country":"IT",
    "sg:address":"Via Trento 113 25123 Brescia",
    "sg:city":"Brescia",
    "sg:classifiers":[
        {
            "category":"Manufacturing",
            "subcategory":"Motor Vehicles & Parts",
            "type":"Manufacturing & Wholesale Goods"
        }
    ],
    "sg:phone":"+39 030 381812",
    "sg:postcode":"25123",
    "sg:province":"Brescia",
    "sg:tags":[
        "engine",
        "diesel",
        "accessory"
    ],
    "sg:website":"www.dispa.it",
    "wof:name":"Dispa Srl",
    "wof:placetype":"venue"
},
  "geometry": {"coordinates":[10.221648,45.54884],"type":"Point"}
}