{
  "type": "Feature",
  "properties": {
    "addr:full":"20034 Giussano Giussano Milano 20034",
    "addr:postcode":"20034;20034",
    "iso:country":"IT",
    "sg:address":"20034 Giussano",
    "sg:city":"Giussano",
    "sg:orig_category":"Forniture Per Edilizia E Lavori Pubblici",
    "sg:phone":"+39 036 235321",
    "sg:postcode":"20034",
    "sg:province":"Milano",
    "wof:name":"Veco S.p.a.",
    "wof:placetype":"venue"
},
  "geometry": {"coordinates":[9.1339969635,45.5329818726],"type":"Point"}
}