{
  "type": "Feature",
  "properties": {
    "addr:full":"Via A. De Gasperi 2 48010 Cotignola Cotignola Ravenna 48010",
    "addr:housenumber":"2",
    "addr:postcode":"48010;48010",
    "addr:street":"Via A. De Gasperi",
    "iso:country":"IT",
    "sg:address":"Via A. De Gasperi 2 48010 Cotignola",
    "sg:city":"Cotignola",
    "sg:classifiers":[
        {
            "category":"Manufacturing",
            "subcategory":"Rubber & Plastics",
            "type":"Manufacturing & Wholesale Goods"
        }
    ],
    "sg:phone":"+39 0545 37411",
    "sg:postcode":"48010",
    "sg:province":"Ravenna",
    "sg:tags":[
        "material"
    ],
    "sg:website":"www.vulcaflex.com",
    "wof:name":"Vulcaflex Spa",
    "wof:placetype":"venue"
},
  "geometry": {"coordinates":[12.0316610336,44.3762931824],"type":"Point"}
}