{
  "type": "Feature",
  "properties": {
    "iso:country":"IT",
    "sg:address":"37053 Cerea",
    "sg:city":"Cerea",
    "sg:orig_category":"Macchine, Impianti Ed Attrezzature Industria Chimica. Attrezzature E Forniture Per Officine Riparazione E Servizi Ausiliari",
    "sg:phone":"+39 0442 31990",
    "sg:postcode":"37053",
    "sg:province":"Verona",
    "wof:name":"Angelini Emilio & C. Snc",
    "wof:placetype":"venue"
},
  "geometry": {"coordinates":[11.227091,45.189163],"type":"Point"}
}