{
  "type": "Feature",
  "properties": {
    "iso:country":"IT",
    "sg:address":"25/27, Via Emilia Romagna 56029 Santa Croce Sull'arno",
    "sg:classifiers":[
        {
            "category":"Manufacturing",
            "subcategory":"Textiles",
            "type":"Manufacturing & Wholesale Goods"
        }
    ],
    "sg:phone":"+39 39057133757",
    "sg:postcode":"56029",
    "sg:province":"Pisa",
    "sg:tags":[
        "leather",
        "raw",
        "material",
        "-"
    ],
    "wof:name":"Conceria Lloyd (s.p.a.)",
    "wof:placetype":"venue"
},
  "geometry": {"coordinates":[10.763826,43.720539],"type":"Point"}
}