{
  "type": "Feature",
  "properties": {
    "addr:full":"35010 Limena Limena Padova 35010",
    "addr:postcode":"35010;35010",
    "iso:country":"IT",
    "sg:address":"35010 Limena",
    "sg:city":"Limena",
    "sg:orig_category":"Sport - Articoli E Forniture",
    "sg:phone":"+39 049 767325",
    "sg:postcode":"35010",
    "sg:province":"Padova",
    "wof:name":"German Di Gabban Marco E Luca S.n.c.",
    "wof:placetype":"venue"
},
  "geometry": {"coordinates":[11.848577,45.464165],"type":"Point"}
}