{
  "type": "Feature",
  "properties": {
    "iso:country":"IT",
    "sg:address":"06089 Torgiano",
    "sg:city":"Torgiano",
    "sg:orig_category":"Macchine, Impianti Ed Attrezzature Per Agricoltura E Zootecnia. Prodotti Vari In Metallo. Apparecchiature E Sistemi Per Magazzinaggio E Movimentazione",
    "sg:phone":"+39 075 982972",
    "sg:postcode":"06089",
    "sg:province":"Perugia",
    "wof:name":"Metal Serbatoi Snc",
    "wof:placetype":"venue"
},
  "geometry": {"coordinates":[12.417305,43.020512],"type":"Point"}
}