{
  "type": "Feature",
  "properties": {
    "iso:country":"IT",
    "sg:address":"10141 Torino",
    "sg:city":"Torino",
    "sg:orig_category":"Forniture Per Attivita' Industriali",
    "sg:phone":"+39 011 335 2739",
    "sg:postcode":"10141",
    "sg:province":"Torino",
    "wof:name":"Ar.tec. Di Vergano Giuseppe & C. Sas",
    "wof:placetype":"venue"
},
  "geometry": {"coordinates":[7.5854568481,45.0251655579],"type":"Point"}
}