{
  "type": "Feature",
  "properties": {
    "addr:full":"93, Localita' Confin 30020 Torre Di Mosto Torre di Mosto Venezia 30020",
    "addr:postcode":"30020;30020",
    "addr:street":"Localita ' Confin",
    "iso:country":"IT",
    "sg:address":"93, Localita' Confin 30020 Torre Di Mosto",
    "sg:city":"Torre di Mosto",
    "sg:classifiers":[
        {
            "category":"Home & Garden",
            "subcategory":"Home Furnishings",
            "type":"Retail Goods"
        }
    ],
    "sg:phone":"+39 0421 325472",
    "sg:postcode":"30020",
    "sg:province":"Venezia",
    "sg:tags":[
        "household"
    ],
    "wof:name":"Free Line S.r.l.",
    "wof:placetype":"venue"
},
  "geometry": {"coordinates":[12.68953,45.688007],"type":"Point"}
}