{
  "type": "Feature",
  "properties": {
    "iso:country":"IT",
    "sg:address":"Via Roma 105; Tonezza Del Cimone; 36040",
    "sg:city":"Tonezza del Cimone",
    "sg:classifiers":[
        {
            "category":"Banks & Credit Unions",
            "subcategory":"Bank",
            "type":"Services"
        }
    ],
    "sg:phone":"+39 0445 749630",
    "sg:postcode":"36040",
    "sg:province":"Vicenza",
    "wof:name":"Cariverona Banca Spa",
    "wof:placetype":"venue"
},
  "geometry": {"coordinates":[11.347595,45.860241],"type":"Point"}
}