{
  "type": "Feature",
  "properties": {
    "iso:country":"IT",
    "sg:address":"23868 Pare'",
    "sg:orig_category":"Materiali Semilavorati Metallici",
    "sg:phone":"+39 0341 582374",
    "sg:postcode":"23868",
    "sg:province":"Lecco",
    "wof:name":"Frigerio Fratelli",
    "wof:placetype":"venue"
},
  "geometry": {"coordinates":[9.378644,45.849491],"type":"Point"}
}