{
  "type": "Feature",
  "properties": {
    "addr:full":"24, Via Ronca 83047 Lioni Lioni Avellino 83047",
    "addr:postcode":"83047;83047",
    "addr:street":"Via Ronca",
    "iso:country":"IT",
    "sg:address":"24, Via Ronca 83047 Lioni",
    "sg:city":"Lioni",
    "sg:classifiers":[
        {
            "category":"Real Estate",
            "subcategory":"Architect",
            "type":"Services"
        }
    ],
    "sg:phone":"+39 0827 270000",
    "sg:postcode":"83047",
    "sg:province":"Avellino",
    "sg:tags":[
        "textile",
        "clothing"
    ],
    "wof:name":"Iorlano",
    "wof:placetype":"venue"
},
  "geometry": {"coordinates":[15.191108,40.876339],"type":"Point"}
}