{
  "type": "Feature",
  "properties": {
    "iso:country":"IT",
    "sg:address":"90146 Palermo",
    "sg:city":"Palermo",
    "sg:classifiers":[
        {
            "category":"Health Services",
            "subcategory":"Health Practitioner",
            "type":"Services"
        }
    ],
    "sg:phone":"+39 091 528380",
    "sg:postcode":"90146",
    "sg:province":"Palermo",
    "sg:tags":[
        "medici"
    ],
    "wof:name":"Giacalone Rosanna",
    "wof:placetype":"venue"
},
  "geometry": {"coordinates":[13.329242,38.153969],"type":"Point"}
}