{
  "type": "Feature",
  "properties": {
    "iso:country":"IT",
    "sg:address":"40136 Bologna",
    "sg:city":"Bologna",
    "sg:orig_category":"Istituti Di Bellezza",
    "sg:phone":"+39 051 333357",
    "sg:postcode":"40136",
    "sg:province":"Bologna",
    "wof:name":"Istituto Delle Gambe Srl",
    "wof:placetype":"venue"
},
  "geometry": {"coordinates":[11.327122,44.482002],"type":"Point"}
}