{
  "type": "Feature",
  "properties": {
    "iso:country":"IT",
    "sg:address":"38, Via Newton Isacco 42100 Reggio Emilia",
    "sg:classifiers":[
        {
            "category":"Food & Beverages",
            "subcategory":"Dairy",
            "type":"Retail Goods"
        }
    ],
    "sg:phone":"+39 0522 944251",
    "sg:postcode":"42100",
    "sg:province":"Reggio Nell'Emilia",
    "sg:tags":[
        "product"
    ],
    "wof:name":"Montanari & Gruzza S.p.a.",
    "wof:placetype":"venue"
},
  "geometry": {"coordinates":[10.505796,44.741966],"type":"Point"}
}