{
  "type": "Feature",
  "properties": {
    "addr:full":"38, Via Newton Isacco 42100 Reggio Emilia Reggio Nell'Emilia 42100",
    "addr:postcode":"42100;42100",
    "addr:street":"Via Newton Isacco",
    "iso:country":"IT",
    "sg:address":"38, Via Newton Isacco 42100 Reggio Emilia",
    "sg:classifiers":[
        {
            "category":"Food & Beverages",
            "subcategory":"Dairy",
            "type":"Retail Goods"
        }
    ],
    "sg:phone":"+39 0522 944251",
    "sg:postcode":"42100",
    "sg:province":"Reggio Nell'Emilia",
    "sg:tags":[
        "product"
    ],
    "wof:name":"Montanari & Gruzza S.p.a.",
    "wof:placetype":"venue"
},
  "geometry": {"coordinates":[10.505796,44.741966],"type":"Point"}
}