{
  "type": "Feature",
  "properties": {
    "iso:country":"IT",
    "sg:address":"20135 Milano",
    "sg:city":"Milano",
    "sg:orig_category":"Prodotti Chimici Di Base. Prodotti Cosmetici E Da Toeletta",
    "sg:phone":"+39 02 5832 0332",
    "sg:postcode":"20135",
    "sg:province":"Milano",
    "wof:name":"Edelweiss Di Villa Laura",
    "wof:placetype":"venue"
},
  "geometry": {"coordinates":[9.2025079727,45.4507713318],"type":"Point"}
}