{
  "type": "Feature",
  "properties": {
    "iso:country":"IT",
    "sg:address":"80023 Caivano",
    "sg:city":"Caivano",
    "sg:orig_category":"Alberghi E Strutture Extra Alberghiere. Ospedali E Servizi Sanitari",
    "sg:phone":"+39 081 835 4333",
    "sg:postcode":"80023",
    "sg:province":"Napoli",
    "wof:name":"Villa Rachele",
    "wof:placetype":"venue"
},
  "geometry": {"coordinates":[14.305758,40.924114],"type":"Point"}
}