{
  "type": "Feature",
  "properties": {
    "iso:country":"IT",
    "sg:address":"21052 Busto Arsizio",
    "sg:city":"Busto Arsizio",
    "sg:orig_category":"Cartotecnica E Servizi. Forniture Per Uffici",
    "sg:phone":"+39 0331 635679",
    "sg:postcode":"21052",
    "sg:province":"Varese",
    "sg:website":"http://www.boragno.it",
    "wof:name":"Cartolibreria Centrale Boragno Srl",
    "wof:placetype":"venue"
},
  "geometry": {"coordinates":[8.843622,45.614246],"type":"Point"}
}