{
  "type": "Feature",
  "properties": {
    "iso:country":"IT",
    "sg:address":"Via Delle Camane 10 21015 Lonate Pozzolo",
    "sg:city":"Lonate Pozzolo",
    "sg:classifiers":[
        {
            "category":"Manufacturing",
            "subcategory":"Tools & Machinery",
            "type":"Manufacturing & Wholesale Goods"
        }
    ],
    "sg:phone":"+39 0331 668171",
    "sg:postcode":"21015",
    "sg:province":"Varese",
    "sg:tags":[
        "plants",
        "chip",
        "machining",
        "removal"
    ],
    "wof:name":"Comec Srl",
    "wof:placetype":"venue"
},
  "geometry": {"coordinates":[8.746845,45.599625],"type":"Point"}
}