{
  "type": "Feature",
  "properties": {
    "iso:country":"IT",
    "sg:address":"28100 Novara",
    "sg:city":"Novara",
    "sg:orig_category":"Gomma Articoli Tecnici - Produzione E Commercio",
    "sg:phone":"+39 0321 696603",
    "sg:postcode":"28100",
    "sg:province":"Novara",
    "wof:name":"Tosetti Vittorio - Gumax",
    "wof:placetype":"venue"
},
  "geometry": {"coordinates":[8.631194,45.448051],"type":"Point"}
}