{
  "type": "Feature",
  "properties": {
    "addr:full":"00182 Roma Roma Roma 00182",
    "addr:postcode":"00182;00182",
    "iso:country":"IT",
    "sg:address":"00182 Roma",
    "sg:city":"Roma",
    "sg:orig_category":"Pompe. Ricambi E Componenti Dei Mezzi Di Trasporto",
    "sg:phone":"+39 06 701 1909",
    "sg:postcode":"00182",
    "sg:province":"Roma",
    "wof:name":"Emporio Del Diesel (s.r.l.)",
    "wof:placetype":"venue"
},
  "geometry": {"coordinates":[12.5190649033,41.8801651001],"type":"Point"}
}