{
  "type": "Feature",
  "properties": {
    "iso:country":"IT",
    "sg:address":"30174 Venezia",
    "sg:city":"Mestre",
    "sg:orig_category":"Impiantistica E Prodotti Tecnologici Per Edilizia. Elettronica Professionale E Di Consumo",
    "sg:phone":"+39 041 504 0025",
    "sg:postcode":"30174",
    "sg:province":"Venezia",
    "wof:name":"Erreci Snc",
    "wof:placetype":"venue"
},
  "geometry": {"coordinates":[12.227034,45.499805],"type":"Point"}
}