{
  "type": "Feature",
  "properties": {
    "addr:full":"14034 Castello Di Annone Castello di Annone Asti 14034",
    "addr:housenumber":"14034",
    "addr:postcode":"14034",
    "addr:street":"Castello",
    "iso:country":"IT",
    "sg:address":"14034 Castello Di Annone",
    "sg:city":"Castello di Annone",
    "sg:orig_category":"Prodotti Di Base E Forniture Per Industria Alimentare E Bevande. Vetro: Prodotti E Lavorazioni. Articoli Per Imballaggio E Confezionamento",
    "sg:phone":"+39 0141 401844",
    "sg:postcode":"14034",
    "sg:province":"Asti",
    "wof:name":"Ri.da.p.",
    "wof:placetype":"venue"
},
  "geometry": {"coordinates":[8.3228158951,44.8778114319],"type":"Point"}
}