{
  "type": "Feature",
  "properties": {
    "addr:full":"Via Roma, 7; Trieste; 34100",
    "addr:housenumber":"7",
    "addr:postcode":"34100",
    "addr:street":"Via Roma",
    "iso:country":"IT",
    "sg:address":"Via Roma, 7; Trieste; 34100",
    "sg:classifiers":[
        {
            "category":"Banks & Credit Unions",
            "subcategory":"Bank",
            "type":"Services"
        }
    ],
    "sg:phone":"+39 040 631925",
    "wof:name":"Banca D'america E D'italia",
    "wof:placetype":"venue"
},
  "geometry": {"coordinates":[13.771737,45.651333],"type":"Point"}
}