{
  "type": "Feature",
  "properties": {
    "addr:full":"5, Cascina Michele 15020 Cerrina Monferrato Cerrina Monferrato Alessandria 15020",
    "addr:housenumber":"5",
    "addr:postcode":"15020;15020",
    "addr:street":"Cascina Michele",
    "iso:country":"IT",
    "sg:address":"5, Cascina Michele 15020 Cerrina Monferrato",
    "sg:city":"Cerrina Monferrato",
    "sg:classifiers":[
        {
            "category":"Manufacturing",
            "subcategory":"Rubber & Plastics",
            "type":"Manufacturing & Wholesale Goods"
        }
    ],
    "sg:phone":"+39 39014294112",
    "sg:postcode":"15020",
    "sg:province":"Alessandria",
    "wof:name":"Flavio Petrini & C. (s.n.c.)",
    "wof:placetype":"venue"
},
  "geometry": {"coordinates":[8.2032241821,45.1081771851],"type":"Point"}
}