{
  "type": "Feature",
  "properties": {
    "addr:full":"50019 Sesto Fiorentino Sesto Fiorentino Firenze 50019",
    "addr:postcode":"50019;50019",
    "iso:country":"IT",
    "sg:address":"50019 Sesto Fiorentino",
    "sg:city":"Sesto Fiorentino",
    "sg:classifiers":[
        {
            "category":"Professional",
            "subcategory":"Engineering",
            "type":"Services"
        }
    ],
    "sg:phone":"+39 055 421 1245",
    "sg:postcode":"50019",
    "sg:province":"Firenze",
    "sg:tags":[
        "equipment",
        "product",
        "industrial",
        "electronic"
    ],
    "wof:name":"Macchiavelli Marta",
    "wof:placetype":"venue"
},
  "geometry": {"coordinates":[11.181546,43.830357],"type":"Point"}
}