{
  "type": "Feature",
  "properties": {
    "iso:country":"IT",
    "sg:address":"00040 Roma",
    "sg:orig_category":"Forniture Per Edilizia E Lavori Pubblici. Forniture Industriali Per Prevenzione, Controllo E Sicurezza",
    "sg:phone":"+39 06 7984 5567",
    "sg:postcode":"00040",
    "sg:province":"Roma",
    "wof:name":"Graphic Art Snc Di Marco Favorini & C.",
    "wof:placetype":"venue"
},
  "geometry": {"coordinates":[12.6020593643,41.8145065308],"type":"Point"}
}