{
  "type": "Feature",
  "properties": {
    "addr:full":"10044 Pianezza Pianezza Torino 10044",
    "addr:postcode":"10044;10044",
    "iso:country":"IT",
    "sg:address":"10044 Pianezza",
    "sg:city":"Pianezza",
    "sg:orig_category":"Scuole E Servizi Scolastici. Ospedali E Servizi Sanitari",
    "sg:phone":"+39 011 967 6317",
    "sg:postcode":"10044",
    "sg:province":"Torino",
    "wof:name":"Istituto Dei Sordomuti Di Torino Centro Audiologopedico",
    "wof:placetype":"venue"
},
  "geometry": {"coordinates":[7.571543,45.107975],"type":"Point"}
}