{
  "type": "Feature",
  "properties": {
    "iso:country":"IT",
    "sg:address":"66023 Francavilla Al Mare",
    "sg:city":"Francavilla al Mare",
    "sg:orig_category":"Climatizzazione E Condizionamento, Apparecchiature E Servizi",
    "sg:phone":"+39 085 491 0422",
    "sg:postcode":"66023",
    "sg:province":"Chieti",
    "wof:name":"Marinucci Giancarlo",
    "wof:placetype":"venue"
},
  "geometry": {"coordinates":[14.261557,42.43523],"type":"Point"}
}