{
  "type": "Feature",
  "properties": {
    "iso:country":"IT",
    "sg:address":"40064 Ozzano Dell'emilia",
    "sg:orig_category":"Lamiere - Commercio",
    "sg:phone":"+39 051 799635",
    "sg:postcode":"40064",
    "sg:province":"Bologna",
    "wof:name":"Metaltranciati Srl",
    "wof:placetype":"venue"
},
  "geometry": {"coordinates":[11.4876,44.45348],"type":"Point"}
}