{
  "type": "Feature",
  "properties": {
    "iso:country":"IT",
    "sg:address":"Via B. Buozzi 18/20 20097 San Donato Milanese",
    "sg:city":"San Donato Milanese",
    "sg:classifiers":[
        {
            "category":"Manufacturing",
            "subcategory":"Chemicals & Compounds",
            "type":"Manufacturing & Wholesale Goods"
        }
    ],
    "sg:phone":"+39 02 518941",
    "sg:postcode":"20097",
    "sg:province":"Milano",
    "sg:tags":[
        "salt",
        "galvanic"
    ],
    "sg:website":"www.cooksonelectronics.com",
    "wof:name":"Enthone S.r.l.",
    "wof:placetype":"venue"
},
  "geometry": {"coordinates":[9.257586,45.412437],"type":"Point"}
}