{
  "type": "Feature",
  "properties": {
    "iso:country":"IT",
    "sg:address":"34074 Monfalcone",
    "sg:city":"Monfalcone",
    "sg:orig_category":"Falegnami",
    "sg:phone":"+39 0481 483838",
    "sg:postcode":"34074",
    "sg:province":"Gorizia",
    "wof:name":"Falegnameria Adria Di Cechet Paolo & C. Snc",
    "wof:placetype":"venue"
},
  "geometry": {"coordinates":[13.6150121689,45.9527587891],"type":"Point"}
}