{
  "type": "Feature",
  "properties": {
    "addr:full":"00184 Roma Roma Roma 00184",
    "addr:postcode":"00184;00184",
    "iso:country":"IT",
    "sg:address":"00184 Roma",
    "sg:city":"Roma",
    "sg:orig_category":"Campeggio. Alberghi E Strutture Extra Alberghiere",
    "sg:phone":"+39 06 487 1152",
    "sg:postcode":"00184",
    "sg:province":"Roma",
    "sg:website":"http://www.hostels-aig.org",
    "wof:name":"Associazione Italiana Alberghi Per La Gioventu'",
    "wof:placetype":"venue"
},
  "geometry": {"coordinates":[12.495065,41.896439],"type":"Point"}
}