{
  "type": "Feature",
  "properties": {
    "iso:country":"IT",
    "sg:address":"10135 Torino",
    "sg:city":"Torino",
    "sg:orig_category":"Automobili E Mezzi Di Trasporto",
    "sg:postcode":"10135",
    "sg:province":"Torino",
    "wof:name":"Fiat Auto (s.p.a.)",
    "wof:placetype":"venue"
},
  "geometry": {"coordinates":[7.555872,45.000053],"type":"Point"}
}