{
  "type": "Feature",
  "properties": {
    "iso:country":"IT",
    "sg:address":"20124 Milano",
    "sg:city":"Milano",
    "sg:orig_category":"Macchine, Impianti Ed Attrezzature Per Industria Alimentare E Bevande",
    "sg:phone":"+39 02 2940 3068",
    "sg:postcode":"20124",
    "sg:province":"Milano",
    "wof:name":"Panseri & C. S.a.s.",
    "wof:placetype":"venue"
},
  "geometry": {"coordinates":[9.21126,45.482761],"type":"Point"}
}