{
  "type": "Feature",
  "properties": {
    "addr:full":"20, Via Lombardia 40024 Castel San Pietro Terme Castel San Pietro Terme Bologna 40024",
    "addr:postcode":"40024;40024",
    "addr:street":"Via Lombardia",
    "iso:country":"IT",
    "sg:address":"20, Via Lombardia 40024 Castel San Pietro Terme",
    "sg:city":"Castel San Pietro Terme",
    "sg:classifiers":[
        {
            "category":"Bars & Pubs",
            "subcategory":"Nightclub",
            "type":"Food & Drink"
        }
    ],
    "sg:phone":"+39 39051945013",
    "sg:postcode":"40024",
    "sg:province":"Bologna",
    "sg:tags":[
        "cake",
        "bread"
    ],
    "wof:name":"Pasticceria O.e. S.n.c. Di Trovato G. & Rescazzi V",
    "wof:placetype":"venue"
},
  "geometry": {"coordinates":[11.525658,44.428982],"type":"Point"}
}