{
  "type": "Feature",
  "properties": {
    "iso:country":"IT",
    "sg:address":"20154 Milano",
    "sg:city":"Milano",
    "sg:orig_category":"Musica",
    "sg:phone":"+39 02 344886",
    "sg:postcode":"20154",
    "sg:province":"Milano",
    "wof:name":"Pallotti Giuseppe",
    "wof:placetype":"venue"
},
  "geometry": {"coordinates":[9.1718769073,45.4823570251],"type":"Point"}
}