{
  "type": "Feature",
  "properties": {
    "iso:country":"IT",
    "sg:address":"1, Centro Comm.le 37047 San Bonifacio",
    "sg:city":"San Bonifacio",
    "sg:classifiers":[
        {
            "category":"Banks & Credit Unions",
            "subcategory":"Bank",
            "type":"Services"
        }
    ],
    "sg:phone":"+39 045 761 1899",
    "sg:postcode":"37047",
    "sg:province":"Verona",
    "sg:tags":[
        "banking",
        "institution"
    ],
    "wof:name":"Veneta Leasing (s.p.a.)",
    "wof:placetype":"venue"
},
  "geometry": {"coordinates":[10.991748,45.438366],"type":"Point"}
}