{
  "type": "Feature",
  "properties": {
    "iso:country":"IT",
    "sg:address":"00, Contrada S.paolo 82020 Reino",
    "sg:city":"Reino",
    "sg:classifiers":[
        {
            "category":"Manufacturing",
            "subcategory":"Glass & Minerals",
            "type":"Manufacturing & Wholesale Goods"
        }
    ],
    "sg:phone":"+39 0824 985492",
    "sg:postcode":"82020",
    "sg:province":"Benevento",
    "sg:tags":[
        "building",
        "material"
    ],
    "wof:name":"Edilux S.r.l.",
    "wof:placetype":"venue"
},
  "geometry": {"coordinates":[14.781174,41.130447],"type":"Point"}
}