{
  "type": "Feature",
  "properties": {
    "iso:country":"IT",
    "sg:address":"Via Ortigara 75; Pare Di Conegliano; 31015",
    "sg:city":"Conegliano",
    "sg:classifiers":[
        {
            "category":"Banks & Credit Unions",
            "subcategory":"Bank",
            "type":"Services"
        }
    ],
    "sg:phone":"+39 0438 451200",
    "sg:postcode":"31015",
    "sg:province":"Treviso",
    "wof:name":"Rolo Banca 1473 Spa",
    "wof:placetype":"venue"
},
  "geometry": {"coordinates":[12.261617,45.8703],"type":"Point"}
}