{
  "type": "Feature",
  "properties": {
    "addr:full":"20037 Paderno Dugnano Paderno Dugnano Milano 20037",
    "addr:postcode":"20037;20037",
    "iso:country":"IT",
    "sg:address":"20037 Paderno Dugnano",
    "sg:city":"Paderno Dugnano",
    "sg:orig_category":"Forniture Per Attivita' Industriali",
    "sg:phone":"+39 02 918 3327",
    "sg:postcode":"20037",
    "sg:province":"Milano",
    "wof:name":"Siltech Srl",
    "wof:placetype":"venue"
},
  "geometry": {"coordinates":[9.1651544571,45.5692901611],"type":"Point"}
}