{
  "type": "Feature",
  "properties": {
    "addr:full":"11, Viale Guglielmo Marconi 10019 Strambino Strambino Torino 10019",
    "addr:housenumber":"11",
    "addr:postcode":"10019;10019",
    "addr:street":"Viale Guglielmo Marconi",
    "iso:country":"IT",
    "sg:address":"11, Viale Guglielmo Marconi 10019 Strambino",
    "sg:city":"Strambino",
    "sg:classifiers":[
        {
            "category":"Utilities",
            "subcategory":"Telephone",
            "type":"Services"
        }
    ],
    "sg:phone":"+39 0125 637711",
    "sg:postcode":"10019",
    "sg:province":"Torino",
    "sg:tags":[
        "telecommunication"
    ],
    "wof:name":"Progem S.r.l.",
    "wof:placetype":"venue"
},
  "geometry": {"coordinates":[7.875381,45.384815],"type":"Point"}
}