{
  "type": "Feature",
  "properties": {
    "iso:country":"IT",
    "sg:address":"10145 Torino",
    "sg:city":"Torino",
    "sg:orig_category":"Motori Ed Organi Di Trasmissione",
    "sg:phone":"+39 011 744804",
    "sg:postcode":"10145",
    "sg:province":"Torino",
    "wof:name":"Var - Mo (s.a.s.)",
    "wof:placetype":"venue"
},
  "geometry": {"coordinates":[7.6421961784,45.0766906738],"type":"Point"}
}