{
  "type": "Feature",
  "properties": {
    "addr:full":"52, V. Monsignor Siino 90040 Capaci Capaci Palermo 90040",
    "addr:housenumber":"52",
    "addr:postcode":"90040;90040",
    "addr:street":"V. Monsignor Siino",
    "iso:country":"IT",
    "sg:address":"52, V. Monsignor Siino 90040 Capaci",
    "sg:city":"Capaci",
    "sg:classifiers":[
        {
            "category":"Food & Beverages",
            "subcategory":"Dairy",
            "type":"Retail Goods"
        }
    ],
    "sg:phone":"+39 091 867 1917",
    "sg:postcode":"90040",
    "sg:province":"Palermo",
    "sg:tags":[
        "product"
    ],
    "sg:website":"http://www.latte-puccio.com",
    "wof:name":"Industria Alimentare Puccio",
    "wof:placetype":"venue"
},
  "geometry": {"coordinates":[13.23392,38.170391],"type":"Point"}
}