{
  "type": "Feature",
  "properties": {
    "addr:full":"25012 Calvisano Calvisano Brescia 25012",
    "addr:postcode":"25012;25012",
    "iso:country":"IT",
    "sg:address":"25012 Calvisano",
    "sg:city":"Calvisano",
    "sg:orig_category":"Zootecnia E Pesca, Allevamento Piccoli Animali",
    "sg:phone":"+39 030 968445",
    "sg:postcode":"25012",
    "sg:province":"Brescia",
    "wof:name":"Ferrari Eugenio",
    "wof:placetype":"venue"
},
  "geometry": {"coordinates":[10.337032,45.37846],"type":"Point"}
}