{
  "type": "Feature",
  "properties": {
    "iso:country":"IT",
    "sg:address":"00165 Roma",
    "sg:city":"Roma",
    "sg:orig_category":"Prodotti Chimici Di Base. Macchine E Forniture Per Ecologia E Smaltimento Rifiuti",
    "sg:phone":"+39 06 3936 7275",
    "sg:postcode":"00165",
    "sg:province":"Roma",
    "wof:name":"Aermaster Italia Srl",
    "wof:placetype":"venue"
},
  "geometry": {"coordinates":[12.4409236908,41.895488739],"type":"Point"}
}