{
  "type": "Feature",
  "properties": {
    "iso:country":"IT",
    "sg:address":"80019 Qualiano",
    "sg:city":"Qualiano",
    "sg:orig_category":"Arredo Urbano",
    "sg:phone":"+39 081 818 1140",
    "sg:postcode":"80019",
    "sg:province":"Napoli",
    "wof:name":"Artistica Pianese Srl",
    "wof:placetype":"venue"
},
  "geometry": {"coordinates":[14.171168,40.923161],"type":"Point"}
}