{
  "type": "Feature",
  "properties": {
    "addr:full":"Via I Maggio 54 21048 Solbiate Arno Solbiate Arno Varese 21048",
    "addr:housenumber":"54;arno",
    "addr:postcode":"21048;21048",
    "addr:street":"Via I Maggio",
    "iso:country":"IT",
    "sg:address":"Via I Maggio 54 21048 Solbiate Arno",
    "sg:city":"Solbiate Arno",
    "sg:classifiers":[
        {
            "category":"Shopping",
            "subcategory":"Crafts & Fabrics",
            "type":"Retail Goods"
        }
    ],
    "sg:phone":"+39 0331 999333",
    "sg:postcode":"21048",
    "sg:province":"Varese",
    "sg:tags":[
        "printing",
        "unfinished"
    ],
    "sg:website":"www.nemesis.it",
    "wof:name":"Nemesis Spa",
    "wof:placetype":"venue"
},
  "geometry": {"coordinates":[8.8263845444,45.8176040649],"type":"Point"}
}