{
  "type": "Feature",
  "properties": {
    "iso:country":"IT",
    "sg:address":"80044 Ottaviano",
    "sg:city":"Ottaviano",
    "sg:classifiers":[
        {
            "category":"Professional",
            "subcategory":"Art Services",
            "type":"Services"
        }
    ],
    "sg:phone":"+39 081 528 9221",
    "sg:postcode":"80044",
    "sg:province":"Napoli",
    "sg:tags":[
        "gifts",
        "craft",
        "artistic"
    ],
    "sg:website":"http://www.amarischia.com",
    "wof:name":"Amarischia Spa",
    "wof:placetype":"venue"
},
  "geometry": {"coordinates":[13.89678,40.718403],"type":"Point"}
}