{
  "type": "Feature",
  "properties": {
    "iso:country":"IT",
    "sg:address":"70122 Bari",
    "sg:city":"Bari",
    "sg:orig_category":"Macchine, Impianti Ed Attrezzature Per Agricoltura E Zootecnia",
    "sg:phone":"+39 080 521 6648",
    "sg:postcode":"70122",
    "sg:province":"Bari",
    "wof:name":"Ferrante Cosimo",
    "wof:placetype":"venue"
},
  "geometry": {"coordinates":[16.866278,41.124207],"type":"Point"}
}