{
  "type": "Feature",
  "properties": {
    "iso:country":"IT",
    "sg:address":"19126 La Spezia",
    "sg:orig_category":"Nautica. Accessori Dei Mezzi Di Trasporto. Servizi Ausiliari Dei Mezzi Di Trasporto",
    "sg:phone":"+39 0187 511474",
    "sg:province":"SP",
    "wof:name":"Ceresa Carlo",
    "wof:placetype":"venue"
},
  "geometry": {"coordinates":[9.859933,44.107529],"type":"Point"}
}