{
  "type": "Feature",
  "properties": {
    "addr:full":"1, Zona Industriale Pantaniello 86090 Pettoranello Del Molise Pettoranello del Molise Isernia 86090",
    "addr:housenumber":"1",
    "addr:postcode":"86090;86090",
    "addr:street":"Zona Industriale Pantaniello;Del Molise",
    "iso:country":"IT",
    "sg:address":"1, Zona Industriale Pantaniello 86090 Pettoranello Del Molise",
    "sg:city":"Pettoranello del Molise",
    "sg:classifiers":[
        {
            "category":"Shopping",
            "subcategory":"Clothing, Apparel, & Fashions",
            "type":"Retail Goods"
        }
    ],
    "sg:phone":"+39 390 865 4461",
    "sg:postcode":"86090",
    "sg:province":"Isernia",
    "sg:tags":[
        "clothes"
    ],
    "wof:name":"Ittierre S.p.a.",
    "wof:placetype":"venue"
},
  "geometry": {"coordinates":[14.230827,41.594334],"type":"Point"}
}