{
  "type": "Feature",
  "properties": {
    "addr:full":"16137 Genova Genova Genova 16137",
    "addr:postcode":"16137;16137",
    "iso:country":"IT",
    "sg:address":"16137 Genova",
    "sg:city":"Genova",
    "sg:orig_category":"Elettronica Professionale E Di Consumo. Musica. Forniture Per Congressi, Fiere E Manifestazioni",
    "sg:phone":"+39 010 810806",
    "sg:postcode":"16137",
    "sg:province":"Genova",
    "wof:name":"M.k. Knezevich Snc",
    "wof:placetype":"venue"
},
  "geometry": {"coordinates":[8.951416,44.411816],"type":"Point"}
}