{
  "type": "Feature",
  "properties": {
    "iso:country":"IT",
    "sg:address":"36028 Rossano Veneto",
    "sg:city":"Rossano Veneto",
    "sg:classifiers":[
        {
            "category":"Manufacturing",
            "subcategory":"Wood Products",
            "type":"Manufacturing & Wholesale Goods"
        }
    ],
    "sg:phone":"+39 0424 540465",
    "sg:postcode":"36028",
    "sg:province":"Vicenza",
    "sg:tags":[
        "semi-finished"
    ],
    "wof:name":"Ferplac Spa",
    "wof:placetype":"venue"
},
  "geometry": {"coordinates":[11.809811,45.706776],"type":"Point"}
}