{
  "type": "Feature",
  "properties": {
    "iso:country":"IT",
    "sg:address":"30036 Santa Maria Di Sala",
    "sg:city":"Santa Maria di Sala",
    "sg:classifiers":[
        {
            "category":"Communications",
            "subcategory":"Film & Video Production",
            "type":"Services"
        }
    ],
    "sg:phone":"+39 041 573 0216",
    "sg:postcode":"30036",
    "sg:province":"Venezia",
    "sg:tags":[
        "reti",
        "per",
        "letti"
    ],
    "wof:name":"Cazzin Snc",
    "wof:placetype":"venue"
},
  "geometry": {"coordinates":[12.003579,45.481861],"type":"Point"}
}