{
  "type": "Feature",
  "properties": {
    "addr:full":"00147 Roma Roma Roma 00147",
    "addr:postcode":"00147;00147",
    "iso:country":"IT",
    "sg:address":"00147 Roma",
    "sg:city":"Roma",
    "sg:orig_category":"Forniture E Prodotti Informatici. Forniture Per Uffici",
    "sg:phone":"+39 06 540 2536",
    "sg:postcode":"00147",
    "sg:province":"Roma",
    "wof:name":"Eco Roma System Sas",
    "wof:placetype":"venue"
},
  "geometry": {"coordinates":[12.4908056259,41.8468971252],"type":"Point"}
}