{
  "type": "Feature",
  "properties": {
    "addr:full":"31, Via Dei Mulini 22100 Como Como Como 22100",
    "addr:postcode":"22100;22100",
    "addr:street":"Via Dei Mulini",
    "iso:country":"IT",
    "sg:address":"31, Via Dei Mulini 22100 Como",
    "sg:city":"Como",
    "sg:classifiers":[
        {
            "category":"Building & Trades",
            "subcategory":"Construction",
            "type":"Services"
        }
    ],
    "sg:phone":"+39 39031505212",
    "sg:postcode":"22100",
    "sg:province":"Como",
    "sg:tags":[
        "work",
        "public"
    ],
    "wof:name":"La Metaltecnica S.r.l.",
    "wof:placetype":"venue"
},
  "geometry": {"coordinates":[9.085485,45.787487],"type":"Point"}
}