{
  "type": "Feature",
  "properties": {
    "addr:full":"Via Stiria , 45,6/7 Loc Partigros 33100 Udine Udine Udine 33100",
    "addr:housenumber":"45,6 / 7",
    "addr:postcode":"33100;33100",
    "addr:street":"Via Stiria;Loc Partigros",
    "iso:country":"IT",
    "sg:address":"Via Stiria , 45,6/7 Loc Partigros 33100 Udine",
    "sg:city":"Udine",
    "sg:orig_category":"Hosiery, Nightwear, Daywear",
    "sg:phone":"+39 0432 521520",
    "sg:postcode":"33100",
    "sg:province":"Udine",
    "wof:name":"Commercio Ingrosso Bertolutti Snc",
    "wof:placetype":"venue"
},
  "geometry": {"coordinates":[13.230724,46.064941],"type":"Point"}
}