{
  "type": "Feature",
  "properties": {
    "addr:full":"95021 Cannizzaro Cannizzaro Catania 95021",
    "addr:postcode":"95021;95021",
    "iso:country":"IT",
    "sg:address":"95021 Cannizzaro",
    "sg:city":"Cannizzaro",
    "sg:orig_category":"Macchine Utensili E Impianti",
    "sg:phone":"+39 095 712 8885",
    "sg:postcode":"95021",
    "sg:province":"Catania",
    "wof:name":"Sandretto Industrie S.p.a",
    "wof:placetype":"venue"
},
  "geometry": {"coordinates":[15.128862,37.542774],"type":"Point"}
}