{
  "type": "Feature",
  "properties": {
    "iso:country":"IT",
    "sg:address":"8, Corso Spagna 35127 Padova",
    "sg:city":"Padova",
    "sg:classifiers":[
        {
            "category":"Parking",
            "subcategory":"Lot",
            "type":"Transportation"
        }
    ],
    "sg:phone":"+39 049 870 0347",
    "sg:postcode":"35127",
    "sg:province":"Padova",
    "sg:tags":[
        "transport",
        "road"
    ],
    "wof:name":"Effetielle (soc.coop.r.l.)",
    "wof:placetype":"venue"
},
  "geometry": {"coordinates":[11.92522,45.354546],"type":"Point"}
}