{
  "type": "Feature",
  "properties": {
    "addr:full":"Via Del Tempio Degli Arvali 41/45 00148 Roma Roma Roma 00148",
    "addr:housenumber":"41 / 45",
    "addr:postcode":"00148;00148",
    "addr:street":"Via Del Tempio Degli Arvali",
    "iso:country":"IT",
    "sg:address":"Via Del Tempio Degli Arvali 41/45 00148 Roma",
    "sg:city":"Roma",
    "sg:classifiers":[
        {
            "category":"Coffee & Tea",
            "type":"Food & Drink"
        }
    ],
    "sg:phone":"+39 06 653 9735",
    "sg:postcode":"00148",
    "sg:province":"Roma",
    "sg:tags":[
        "roasted"
    ],
    "sg:website":"www.danesi-caffe.com",
    "wof:name":"Danesi Caffe' Spa",
    "wof:placetype":"venue"
},
  "geometry": {"coordinates":[12.434426,41.834625],"type":"Point"}
}