{
  "type": "Feature",
  "properties": {
    "iso:country":"IT",
    "sg:address":"80046 San Giorgio A Cremano",
    "sg:city":"San Giorgio a Cremano",
    "sg:orig_category":"Bilance, Bilici E Bascule",
    "sg:phone":"+39 081 482024",
    "sg:postcode":"80046",
    "sg:province":"Napoli",
    "wof:name":"Becosystem",
    "wof:placetype":"venue"
},
  "geometry": {"coordinates":[14.326973,40.827908],"type":"Point"}
}