{
  "type": "Feature",
  "properties": {
    "iso:country":"IT",
    "sg:address":"83100 Avellino",
    "sg:city":"Avellino",
    "sg:orig_category":"Informatica - Consulenza E Software",
    "sg:phone":"+39 0825 35776",
    "sg:postcode":"83100",
    "sg:province":"Avellino",
    "sg:website":"http://www.cdfgroup.com",
    "wof:name":"Cdf Informatica Srl",
    "wof:placetype":"venue"
},
  "geometry": {"coordinates":[14.780128,40.918484],"type":"Point"}
}