{
  "type": "Feature",
  "properties": {
    "addr:full":"Via Fiorentina 96/c 50063 Figline Valdarno Figline Valdarno Firenze 50063",
    "addr:housenumber":"96 / c",
    "addr:postcode":"50063;50063",
    "addr:street":"Via Fiorentina;Valdarno",
    "iso:country":"IT",
    "sg:address":"Via Fiorentina 96/c 50063 Figline Valdarno",
    "sg:city":"Figline Valdarno",
    "sg:classifiers":[
        {
            "category":"Home & Garden",
            "subcategory":"Carpets & Floor Coverings",
            "type":"Retail Goods"
        }
    ],
    "sg:phone":"+39 055 958886",
    "sg:postcode":"50063",
    "sg:province":"Firenze",
    "sg:tags":[
        "suction-scrubbing",
        "industrial",
        "single-disc",
        "machine",
        "mac",
        "cleaning",
        "wet",
        "polishing",
        "scrubbers",
        "automatic",
        "machines"
    ],
    "wof:name":"Self",
    "wof:placetype":"venue"
},
  "geometry": {"coordinates":[11.4540901184,43.6370658875],"type":"Point"}
}