{
  "type": "Feature",
  "properties": {
    "addr:full":"Ctr. Tembrietta Teramo 64045",
    "addr:postcode":"64045",
    "iso:country":"IT",
    "sg:address":"Ctr. Tembrietta",
    "sg:orig_category":"Miscellaneous Products",
    "sg:phone":"+39 0861 975384",
    "sg:postcode":"64045",
    "sg:province":"Teramo",
    "sg:website":"http://www.tiessearte.it",
    "wof:name":"Tiesse Srl",
    "wof:placetype":"venue"
},
  "geometry": {"coordinates":[13.6985311508,42.6612701416],"type":"Point"}
}