{
  "type": "Feature",
  "properties": {
    "iso:country":"IT",
    "sg:address":"84038 Sassano",
    "sg:city":"Sassano",
    "sg:orig_category":"Paste Alimentari - Produzione E Ingrosso",
    "sg:phone":"+39 0975 72676",
    "sg:postcode":"84038",
    "sg:province":"Salerno",
    "wof:name":"I Sapori Del Vallo",
    "wof:placetype":"venue"
},
  "geometry": {"coordinates":[15.5878334045,40.3606300354],"type":"Point"}
}