{
  "type": "Feature",
  "properties": {
    "iso:country":"IT",
    "sg:address":"00040 Pomezia",
    "sg:city":"Pomezia",
    "sg:orig_category":"Ospedali E Servizi Sanitari. Centri Di Estetica E Cosmesi E Servizi",
    "sg:phone":"+39 06 912 3018",
    "sg:postcode":"00040",
    "sg:province":"Roma",
    "wof:name":"Pacifici Susanna",
    "wof:placetype":"venue"
},
  "geometry": {"coordinates":[12.506445,41.894501],"type":"Point"}
}