{
  "type": "Feature",
  "properties": {
    "addr:full":"Via Cosimo Del Fante 12; Milan; 20122 Milano 20122",
    "addr:housenumber":"12",
    "addr:postcode":"20122;20122",
    "addr:street":"Via Cosimo Del Fante",
    "iso:country":"IT",
    "sg:address":"Via Cosimo Del Fante 12; Milan; 20122",
    "sg:classifiers":[
        {
            "category":"Travel",
            "subcategory":"Travel Agent",
            "type":"Entertainment"
        }
    ],
    "sg:phone":"+39 390 258 4314",
    "sg:postcode":"20122",
    "sg:province":"Milano",
    "sg:website":"www.scalaonline.it",
    "wof:name":"Scala International Travel",
    "wof:placetype":"venue"
},
  "geometry": {"coordinates":[9.185135,45.455376],"type":"Point"}
}