{
  "type": "Feature",
  "properties": {
    "addr:full":"Via Della Resistenza 11a 22075 Lurate Caccivio Lurate Caccivio Como 22075",
    "addr:housenumber":"11a;caccivio",
    "addr:postcode":"22075;22075",
    "addr:street":"Via Della Resistenza;Caccivio",
    "iso:country":"IT",
    "sg:address":"Via Della Resistenza 11a 22075 Lurate Caccivio",
    "sg:city":"Lurate Caccivio",
    "sg:classifiers":[
        {
            "category":"Shopping",
            "subcategory":"Crafts & Fabrics",
            "type":"Retail Goods"
        }
    ],
    "sg:phone":"+39 031 390024",
    "sg:postcode":"22075",
    "sg:province":"Como",
    "sg:tags":[
        "ladies'",
        "wear"
    ],
    "wof:name":"Insieme Spa",
    "wof:placetype":"venue"
},
  "geometry": {"coordinates":[8.9922399521,45.7721138],"type":"Point"}
}