{
  "type": "Feature",
  "properties": {
    "addr:full":"95030 Sant'agata Li Battiati Catania 95030",
    "addr:postcode":"95030;95030",
    "iso:country":"IT",
    "sg:address":"95030 Sant'agata Li Battiati",
    "sg:classifiers":[
        {
            "category":"Health Services",
            "subcategory":"Health Practitioner",
            "type":"Services"
        }
    ],
    "sg:phone":"+39 095 211273",
    "sg:postcode":"95030",
    "sg:province":"Catania",
    "sg:tags":[
        "medici"
    ],
    "wof:name":"Barlotta Dr. Francesco",
    "wof:placetype":"venue"
},
  "geometry": {"coordinates":[15.045562,37.57325],"type":"Point"}
}