{
  "type": "Feature",
  "properties": {
    "iso:country":"IT",
    "sg:address":"100, Via Olanda 41100 Modena",
    "sg:city":"Modena",
    "sg:classifiers":[
        {
            "category":"Wholesale",
            "subcategory":"Drugs",
            "type":"Manufacturing & Wholesale Goods"
        }
    ],
    "sg:phone":"+39 39059312030",
    "sg:postcode":"41100",
    "sg:province":"Modena",
    "sg:tags":[
        "chemical",
        "pharmaceutical"
    ],
    "wof:name":"Bedini (s.r.l.)",
    "wof:placetype":"venue"
},
  "geometry": {"coordinates":[10.942642,44.672421],"type":"Point"}
}