{
  "type": "Feature",
  "properties": {
    "iso:country":"IT",
    "sg:address":"20080 Vermezzo",
    "sg:city":"Vermezzo",
    "sg:orig_category":"Utensili Meccanici E Materiali. Elettrotecnica Industriale, Prodotti E Apparecchiature",
    "sg:phone":"+39 02 946941",
    "sg:postcode":"20080",
    "sg:province":"Milano",
    "wof:name":"Rupes Spa",
    "wof:placetype":"venue"
},
  "geometry": {"coordinates":[9.052203,45.424095],"type":"Point"}
}