{
  "type": "Feature",
  "properties": {
    "iso:country":"IT",
    "sg:address":"11, Via Faustinella 25015 Desenzano Del Garda",
    "sg:city":"Desenzano del Garda",
    "sg:classifiers":[
        {
            "category":"Professional",
            "subcategory":"Engineering",
            "type":"Services"
        }
    ],
    "sg:phone":"+39 030 914 8511",
    "sg:postcode":"25015",
    "sg:province":"Brescia",
    "sg:tags":[
        "machine",
        "-",
        "mechanical"
    ],
    "wof:name":"Fiorentini Minereg S.p.a.",
    "wof:placetype":"venue"
},
  "geometry": {"coordinates":[10.517112,45.446178],"type":"Point"}
}