{
  "type": "Feature",
  "properties": {
    "addr:full":"Corso Europa 82 23801 Calolziocorte Calolziocorte Lecco 23801",
    "addr:housenumber":"82",
    "addr:postcode":"23801;23801",
    "addr:street":"Corso Europa",
    "iso:country":"IT",
    "sg:address":"Corso Europa 82 23801 Calolziocorte",
    "sg:city":"Calolziocorte",
    "sg:orig_category":"Spring Wire, Patent-drawn",
    "sg:phone":"+39 0341 641113",
    "sg:postcode":"23801",
    "sg:province":"Lecco",
    "sg:website":"www.brambillaspa.it",
    "wof:name":"Trafilerie Brambilla Spa",
    "wof:placetype":"venue"
},
  "geometry": {"coordinates":[9.439022,45.790291],"type":"Point"}
}