{
  "type": "Feature",
  "properties": {
    "iso:country":"IT",
    "sg:address":"33035 Martignacco",
    "sg:city":"Martignacco",
    "sg:classifiers":[
        {
            "category":"Manufacturing",
            "subcategory":"Furniture",
            "type":"Manufacturing & Wholesale Goods"
        }
    ],
    "sg:phone":"+39 0432 677280",
    "sg:postcode":"33035",
    "sg:province":"Udine",
    "sg:tags":[
        "wood",
        "industry",
        "work",
        "furnishing"
    ],
    "sg:website":"http://www.biepi.it",
    "wof:name":"Bi & Pi Srl",
    "wof:placetype":"venue"
},
  "geometry": {"coordinates":[13.1712026596,46.081867218],"type":"Point"}
}