{
  "type": "Feature",
  "properties": {
    "iso:country":"IT",
    "sg:address":"12, Via Arciprete Catananti 89016 Rizziconi",
    "sg:city":"Rizziconi",
    "sg:classifiers":[
        {
            "category":"Parking",
            "subcategory":"Lot",
            "type":"Transportation"
        }
    ],
    "sg:phone":"+39 39096653414",
    "sg:postcode":"89016",
    "sg:province":"Reggio Di Calabria",
    "sg:tags":[
        "transport",
        "road"
    ],
    "wof:name":"Anile Antonio",
    "wof:placetype":"venue"
},
  "geometry": {"coordinates":[15.966127,38.408798],"type":"Point"}
}