{
  "type": "Feature",
  "properties": {
    "iso:country":"IT",
    "sg:address":"41012 Carpi",
    "sg:city":"Carpi",
    "sg:orig_category":"Macchine, Impianti Ed Attrezzature Per Abbigliamento E Pelletterie",
    "sg:phone":"+39 059 699887",
    "sg:postcode":"41012",
    "sg:province":"Modena",
    "wof:name":"Giuliani Paolo",
    "wof:placetype":"venue"
},
  "geometry": {"coordinates":[10.954882,44.843655],"type":"Point"}
}