{
  "type": "Feature",
  "properties": {
    "addr:full":"22066 Mariano Comense Mariano Comense Como 22066",
    "addr:housenumber":"22066",
    "addr:postcode":"22066",
    "iso:country":"IT",
    "sg:address":"22066 Mariano Comense",
    "sg:city":"Mariano Comense",
    "sg:orig_category":"Poltrone E Divani - Vendita Al Dettaglio",
    "sg:phone":"+39 031 751214",
    "sg:postcode":"22066",
    "sg:province":"Como",
    "wof:name":"Faverio Snc Di Giuseppe Faverio & C.",
    "wof:placetype":"venue"
},
  "geometry": {"coordinates":[9.169093132,45.7089653015],"type":"Point"}
}