{
  "type": "Feature",
  "properties": {
    "iso:country":"IT",
    "sg:address":"80026 Casoria",
    "sg:city":"Casoria",
    "sg:orig_category":"Ricami - Produzione E Ingrosso",
    "sg:phone":"+39 081 738 3587",
    "sg:postcode":"80026",
    "sg:province":"Napoli",
    "sg:website":"http://www.amgpro.it",
    "wof:name":"Amg Di Ascione Antonello",
    "wof:placetype":"venue"
},
  "geometry": {"coordinates":[14.308832,40.896267],"type":"Point"}
}