{
  "type": "Feature",
  "properties": {
    "iso:country":"IT",
    "sg:address":"20098 San Giuliano Milanese",
    "sg:city":"San Giuliano Milanese",
    "sg:orig_category":"Pubblicita' - Articoli Ed Oggetti",
    "sg:phone":"+39 02 9828 1722",
    "sg:postcode":"20098",
    "sg:province":"Milano",
    "wof:name":"2 B Promotion Srl",
    "wof:placetype":"venue"
},
  "geometry": {"coordinates":[9.2573213577,45.3850059509],"type":"Point"}
}