{
  "type": "Feature",
  "properties": {
    "iso:country":"IT",
    "sg:address":"62010 Cingoli",
    "sg:orig_category":"Materiali Semilavorati Metallici",
    "sg:phone":"+39 0733 612909",
    "sg:postcode":"62010",
    "sg:province":"Macerata",
    "wof:name":"Metaldomo Dei F.lli Borvecchi E C. Snc",
    "wof:placetype":"venue"
},
  "geometry": {"coordinates":[13.456262,43.300747],"type":"Point"}
}