{
  "type": "Feature",
  "properties": {
    "addr:full":"10076 Nole Nole Torino 10076",
    "addr:postcode":"10076;10076",
    "iso:country":"IT",
    "sg:address":"10076 Nole",
    "sg:city":"Nole",
    "sg:orig_category":"Serramenti Ed Infissi. Arte Ed Artigianato Artistico. Shopping",
    "sg:phone":"+39 011 929 6508",
    "sg:postcode":"10076",
    "sg:province":"Torino",
    "wof:name":"Scatom Snc",
    "wof:placetype":"venue"
},
  "geometry": {"coordinates":[7.571059,45.241379],"type":"Point"}
}