{
  "type": "Feature",
  "properties": {
    "iso:country":"IT",
    "sg:address":"00185 Roma",
    "sg:city":"Roma",
    "sg:orig_category":"Gioielleria, Oreficeria E Argenteria. Shopping",
    "sg:phone":"+39 06 446 6140",
    "sg:postcode":"00185",
    "sg:province":"Roma",
    "wof:name":"Fonsi Srl",
    "wof:placetype":"venue"
},
  "geometry": {"coordinates":[12.503886,41.896648],"type":"Point"}
}