{
  "type": "Feature",
  "properties": {
    "addr:full":"66, Via Vittorio Veneto 89121 Reggio Calabria RC",
    "addr:postcode":"89121",
    "addr:street":"Via Vittorio Veneto",
    "iso:country":"IT",
    "sg:address":"66, Via Vittorio Veneto 89121 Reggio Calabria",
    "sg:classifiers":[
        {
            "category":"Travel",
            "subcategory":"Travel Agent",
            "type":"Entertainment"
        }
    ],
    "sg:phone":"+39 0965 812211",
    "sg:province":"RC",
    "sg:tags":[
        "business"
    ],
    "wof:name":"Grande Hotel Excelsiorl",
    "wof:placetype":"venue"
},
  "geometry": {"coordinates":[15.651007,38.115097],"type":"Point"}
}