{
  "type": "Feature",
  "properties": {
    "iso:country":"IT",
    "sg:address":"1, Fondamenta Daniele Manin 30100 Venezia",
    "sg:classifiers":[
        {
            "category":"Manufacturing",
            "subcategory":"Glass & Minerals",
            "type":"Manufacturing & Wholesale Goods"
        }
    ],
    "sg:phone":"+39 39041739801",
    "sg:province":"VE",
    "wof:name":"Vetreria Artistica Gritti (s.r.l.)",
    "wof:placetype":"venue"
},
  "geometry": {"coordinates":[12.350627,45.452267],"type":"Point"}
}