{
  "type": "Feature",
  "properties": {
    "iso:country":"IT",
    "sg:address":"17, Via Dell' Artigianato 35040 Ponso",
    "sg:city":"Ponso",
    "sg:classifiers":[
        {
            "category":"Shopping",
            "subcategory":"Clothing, Apparel, & Fashions",
            "type":"Retail Goods"
        }
    ],
    "sg:phone":"+39 0429 656656",
    "sg:postcode":"35040",
    "sg:province":"Padova",
    "sg:tags":[
        "clothes"
    ],
    "wof:name":"Camiceria Padana (s.r.l.)",
    "wof:placetype":"venue"
},
  "geometry": {"coordinates":[11.876589,45.409569],"type":"Point"}
}