{
  "type": "Feature",
  "properties": {
    "iso:country":"IT",
    "sg:address":"21, Via Monte Orfano 13864 Crevacuore",
    "sg:city":"Crevacuore",
    "sg:classifiers":[
        {
            "category":"Wholesale",
            "subcategory":"Medical Equipment & Supplies",
            "type":"Manufacturing & Wholesale Goods"
        }
    ],
    "sg:phone":"+39 39015768256",
    "sg:postcode":"13864",
    "sg:province":"Biella",
    "sg:tags":[
        "-",
        "health",
        "instrument"
    ],
    "wof:name":"Yanga S.r.l.",
    "wof:placetype":"venue"
},
  "geometry": {"coordinates":[8.235654,45.684761],"type":"Point"}
}