{
  "type": "Feature",
  "properties": {
    "iso:country":"IT",
    "sg:address":"12040 Sant'albano Stura",
    "sg:orig_category":"Automobili E Mezzi Di Trasporto. Riparazione Dei Mezzi Di Trasporto",
    "sg:phone":"+39 0172 67354",
    "sg:postcode":"12040",
    "sg:province":"Cuneo",
    "wof:name":"B. & C. Srl",
    "wof:placetype":"venue"
},
  "geometry": {"coordinates":[7.723319,44.507778],"type":"Point"}
}