{
  "type": "Feature",
  "properties": {
    "iso:country":"IT",
    "sg:address":"10152 Torino",
    "sg:city":"Torino",
    "sg:orig_category":"Riparazione Dei Mezzi Di Trasporto",
    "sg:phone":"+39 011 248 7353",
    "sg:postcode":"10152",
    "sg:province":"Torino",
    "wof:name":"Dembech Fratelli Snc",
    "wof:placetype":"venue"
},
  "geometry": {"coordinates":[7.695384,45.079823],"type":"Point"}
}