{
  "type": "Feature",
  "properties": {
    "iso:country":"IT",
    "sg:address":"73016 S.cesario Di Lecce",
    "sg:orig_category":"Bottoni",
    "sg:phone":"+39 0832 202442",
    "sg:postcode":"73016",
    "sg:province":"Lecce",
    "wof:name":"Mazzotta Lucio Fashion Buttons",
    "wof:placetype":"venue"
},
  "geometry": {"coordinates":[18.161495,40.304325],"type":"Point"}
}