{
  "type": "Feature",
  "properties": {
    "iso:country":"IT",
    "sg:address":"00019 Tivoli",
    "sg:city":"Empolitana",
    "sg:orig_category":"Pubblicita' - Agenzie Studi",
    "sg:phone":"+39 0774 314991",
    "sg:postcode":"00019",
    "sg:province":"Roma",
    "wof:name":"Jack Spot Grafica",
    "wof:placetype":"venue"
},
  "geometry": {"coordinates":[12.8061542511,41.9548568726],"type":"Point"}
}