{
  "type": "Feature",
  "properties": {
    "iso:country":"IT",
    "sg:address":"11, Via Cesare Battisti 21020 Daverio",
    "sg:city":"Daverio",
    "sg:classifiers":[
        {
            "category":"Real Estate",
            "subcategory":"Architect",
            "type":"Services"
        }
    ],
    "sg:phone":"+39 0332 947454",
    "sg:postcode":"21020",
    "sg:province":"Varese",
    "sg:tags":[
        "textile",
        "clothing"
    ],
    "wof:name":"Tessitura W.mantegazza Srl",
    "wof:placetype":"venue"
},
  "geometry": {"coordinates":[8.751417,45.789196],"type":"Point"}
}