{
  "type": "Feature",
  "properties": {
    "iso:country":"IT",
    "sg:address":"67100 L'aquila",
    "sg:orig_category":"Servizi Al Turismo. Trasporto Pubblico E Privato",
    "sg:phone":"+39 0862 319621",
    "sg:postcode":"67100",
    "sg:province":"L'Aquila",
    "sg:website":"http://www.ognivia.com",
    "wof:name":"Ognivia Autoservizi Srl",
    "wof:placetype":"venue"
},
  "geometry": {"coordinates":[13.381328,42.35516],"type":"Point"}
}