{
  "type": "Feature",
  "properties": {
    "iso:country":"IT",
    "sg:address":"26013 Ombriano",
    "sg:city":"Ombriano",
    "sg:orig_category":"Telecomunicazioni E Telefonia, Impianti, Apparecchi E Servizi",
    "sg:phone":"+39 0373 31809",
    "sg:postcode":"26013",
    "sg:province":"Cremona",
    "wof:name":"A. C. Lan",
    "wof:placetype":"venue"
},
  "geometry": {"coordinates":[10.026497,45.136406],"type":"Point"}
}