{
  "type": "Feature",
  "properties": {
    "iso:country":"IT",
    "sg:address":"16129 Genova",
    "sg:city":"Genova",
    "sg:orig_category":"Climatizzazione E Condizionamento, Apparecchiature E Servizi. Elettrodomestici",
    "sg:phone":"+39 010 595 6567",
    "sg:postcode":"16129",
    "sg:province":"Genova",
    "wof:name":"Progetto Aria Sas",
    "wof:placetype":"venue"
},
  "geometry": {"coordinates":[8.950755,44.400074],"type":"Point"}
}