{
  "type": "Feature",
  "properties": {
    "iso:country":"IT",
    "sg:address":"20128 Milano",
    "sg:city":"Milano",
    "sg:orig_category":"Macchine, Impianti E Forniture Per Industria Grafica, Cartaria E Cartotecnica",
    "sg:phone":"+39 02 2720 2798",
    "sg:postcode":"20128",
    "sg:province":"Milano",
    "sg:website":"http://www.weko.com",
    "wof:name":"Weko Italia Srl",
    "wof:placetype":"venue"
},
  "geometry": {"coordinates":[9.237557,45.513493],"type":"Point"}
}