{
  "type": "Feature",
  "properties": {
    "addr:full":"57/a, Strada Comunale Di Altessano 10151 Torino Torino Torino 10151",
    "addr:housenumber":"57 / a",
    "addr:postcode":"10151;10151",
    "addr:street":"Strada Comunale Di Altessano",
    "iso:country":"IT",
    "sg:address":"57/a, Strada Comunale Di Altessano 10151 Torino",
    "sg:city":"Torino",
    "sg:classifiers":[
        {
            "category":"Autos & Motor Vehicles",
            "subcategory":"Automobile Sales",
            "type":"Retail Goods"
        }
    ],
    "sg:phone":"+39 011 455 0777",
    "sg:postcode":"10151",
    "sg:province":"Torino",
    "sg:tags":[
        "motor-cars"
    ],
    "wof:name":"Reamcarto (s.r.l.)",
    "wof:placetype":"venue"
},
  "geometry": {"coordinates":[7.6866188049,45.0705604553],"type":"Point"}
}