{
  "type": "Feature",
  "properties": {
    "addr:full":"103, Corso Gelone 96100 Siracusa Siracusa Siracusa 96100",
    "addr:housenumber":"103",
    "addr:postcode":"96100;96100",
    "addr:street":"Corso Gelone",
    "iso:country":"IT",
    "sg:address":"103, Corso Gelone 96100 Siracusa",
    "sg:city":"Siracusa",
    "sg:classifiers":[
        {
            "category":"Professional",
            "subcategory":"Engineering",
            "type":"Services"
        }
    ],
    "sg:phone":"+39 0931 463622",
    "sg:postcode":"96100",
    "sg:province":"Siracusa",
    "sg:tags":[
        "machine",
        "-",
        "mechanical"
    ],
    "wof:name":"Stea S.r.l.",
    "wof:placetype":"venue"
},
  "geometry": {"coordinates":[15.281868,37.073536],"type":"Point"}
}