{
  "type": "Feature",
  "properties": {
    "addr:full":"35030 Selvazzano Dentro Selvazzano Dentro Padova 35030",
    "addr:postcode":"35030;35030",
    "iso:country":"IT",
    "sg:address":"35030 Selvazzano Dentro",
    "sg:city":"Selvazzano Dentro",
    "sg:classifiers":[
        {
            "category":"Health Services",
            "subcategory":"Hospital",
            "type":"Services"
        }
    ],
    "sg:phone":"+39 049 638787",
    "sg:postcode":"35030",
    "sg:province":"Padova",
    "sg:tags":[
        "control",
        "refuse",
        "auxiliary",
        "disposal",
        "analysis",
        "research",
        "environmental",
        "protection",
        "services",
        "works"
    ],
    "wof:name":"Ag.ec. Srl",
    "wof:placetype":"venue"
},
  "geometry": {"coordinates":[11.790954,45.386463],"type":"Point"}
}