{
  "type": "Feature",
  "properties": {
    "iso:country":"IT",
    "sg:address":"13045 Gattinara",
    "sg:city":"Gattinara",
    "sg:orig_category":"Servizi E Lavori Per Abbigliamento E Pelletterie",
    "sg:phone":"+39 0163 834695",
    "sg:postcode":"13045",
    "sg:province":"Vercelli",
    "wof:name":"Berto Oriana",
    "wof:placetype":"venue"
},
  "geometry": {"coordinates":[8.411088,45.33234],"type":"Point"}
}