{
  "type": "Feature",
  "properties": {
    "iso:country":"IT",
    "sg:address":"Bivio Cioffi 84025 Eboli",
    "sg:city":"Eboli",
    "sg:classifiers":[
        {
            "category":"Wholesale",
            "subcategory":"Machinery & Supplies",
            "type":"Manufacturing & Wholesale Goods"
        }
    ],
    "sg:phone":"+39 0828 347063",
    "sg:postcode":"84025",
    "sg:province":"Salerno",
    "sg:tags":[
        "-",
        "agriculture",
        "equipment"
    ],
    "wof:name":"Te.ni.ce. Sud Snc Di Celano N. & C.",
    "wof:placetype":"venue"
},
  "geometry": {"coordinates":[14.988685,40.550034],"type":"Point"}
}