{
  "type": "Feature",
  "properties": {
    "iso:country":"IT",
    "sg:address":"40, P. Borgo Pila 16121 Genova",
    "sg:city":"Genova",
    "sg:classifiers":[
        {
            "category":"Communications",
            "subcategory":"Newspaper",
            "type":"Services"
        }
    ],
    "sg:phone":"+39 39010592626",
    "sg:postcode":"16121",
    "sg:province":"Genova",
    "sg:tags":[
        "advertising"
    ],
    "sg:website":"http://www.dmponline.it",
    "wof:name":"Dmp - Distribuzione Pubblicitaria",
    "wof:placetype":"venue"
},
  "geometry": {"coordinates":[8.948334,44.404446],"type":"Point"}
}