{
  "type": "Feature",
  "properties": {
    "addr:full":"Via G. Marchetti 22; Bologna",
    "addr:housenumber":"22",
    "addr:street":"Via G. Marchetti",
    "iso:country":"IT",
    "sg:address":"Via G. Marchetti 22; Bologna",
    "sg:classifiers":[
        {
            "category":"Banks & Credit Unions",
            "subcategory":"Bank",
            "type":"Services"
        }
    ],
    "sg:phone":"+39 051 623 6682",
    "wof:name":"Cassa Di Risparmio In Bologna Spa",
    "wof:placetype":"venue"
},
  "geometry": {"coordinates":[11.362324,44.476768],"type":"Point"}
}