{
  "type": "Feature",
  "properties": {
    "addr:full":"10148 Torino Torino Torino 10148",
    "addr:postcode":"10148;10148",
    "iso:country":"IT",
    "sg:address":"10148 Torino",
    "sg:city":"Torino",
    "sg:orig_category":"Macchine E Forniture Per Ecologia E Smaltimento Rifiuti. Forniture Per Attivita' Industriali",
    "sg:phone":"+39 011 229 1389",
    "sg:postcode":"10148",
    "sg:province":"Torino",
    "wof:name":"Sofin Di Milo Roberto",
    "wof:placetype":"venue"
},
  "geometry": {"coordinates":[7.696059,45.10627],"type":"Point"}
}