{
  "type": "Feature",
  "properties": {
    "addr:full":"Via Sarzanese Int. 55054 Massarosa Massarosa Lucca 55054",
    "addr:postcode":"55054;55054",
    "addr:street":"Via Sarzanese Int.",
    "iso:country":"IT",
    "sg:address":"Via Sarzanese Int. 55054 Massarosa",
    "sg:city":"Massarosa",
    "sg:classifiers":[
        {
            "category":"Utilities",
            "subcategory":"Electric",
            "type":"Services"
        }
    ],
    "sg:phone":"+39 0584 939924",
    "sg:postcode":"55054",
    "sg:province":"Lucca",
    "sg:tags":[
        "component",
        "electronic"
    ],
    "wof:name":"Gifas Electric Forniture Elettricoindustriali S.r.l.",
    "wof:placetype":"venue"
},
  "geometry": {"coordinates":[10.409595,43.855106],"type":"Point"}
}