{
  "type": "Feature",
  "properties": {
    "iso:country":"IT",
    "sg:address":"Via Veneto 29/31 35020 Due Carrare",
    "sg:city":"Due Carrare",
    "sg:classifiers":[
        {
            "category":"Manufacturing",
            "subcategory":"Furniture",
            "type":"Manufacturing & Wholesale Goods"
        }
    ],
    "sg:phone":"+39 049 529 0222",
    "sg:postcode":"35020",
    "sg:province":"Padova",
    "sg:tags":[
        "dental"
    ],
    "sg:website":"www.tavom.com",
    "wof:name":"Tavom Spa",
    "wof:placetype":"venue"
},
  "geometry": {"coordinates":[11.863928,45.300568],"type":"Point"}
}