{
  "type": "Feature",
  "properties": {
    "addr:full":"22044 Inverigo Inverigo Como 22044",
    "addr:postcode":"22044;22044",
    "iso:country":"IT",
    "sg:address":"22044 Inverigo",
    "sg:city":"Inverigo",
    "sg:orig_category":"Macchine E Forniture Per Arredamento E Industria Del Legno",
    "sg:phone":"+39 031 359 0042",
    "sg:postcode":"22044",
    "sg:province":"Como",
    "wof:name":"Pozzolidue Snc",
    "wof:placetype":"venue"
},
  "geometry": {"coordinates":[9.173009,45.704895],"type":"Point"}
}