{
  "type": "Feature",
  "properties": {
    "iso:country":"IT",
    "sg:address":"71013 San Giovanni Rotondo",
    "sg:city":"San Giovanni Rotondo",
    "sg:orig_category":"Ospedali",
    "sg:phone":"+39 0882 410111",
    "sg:postcode":"71013",
    "sg:province":"Foggia",
    "wof:name":"Fondazione Di Religione E Culto Casa Sollievo Sofferenza",
    "wof:placetype":"venue"
},
  "geometry": {"coordinates":[15.713593,41.708244],"type":"Point"}
}