{
  "type": "Feature",
  "properties": {
    "iso:country":"IT",
    "sg:address":"25065 Lumezzane",
    "sg:city":"Lumezzane",
    "sg:orig_category":"Rubinetterie Ed Accessori",
    "sg:phone":"+39 030 892 0386",
    "sg:postcode":"25065",
    "sg:province":"Brescia",
    "wof:name":"Bianchi F. Lli Srl",
    "wof:placetype":"venue"
},
  "geometry": {"coordinates":[10.266423,45.647583],"type":"Point"}
}