{
  "type": "Feature",
  "properties": {
    "addr:full":"Via Casottina 27013 Chignolo Po Chignolo Po Pavia 27013",
    "addr:postcode":"27013;27013",
    "addr:street":"Via Casottina",
    "iso:country":"IT",
    "sg:address":"Via Casottina 27013 Chignolo Po",
    "sg:city":"Chignolo Po",
    "sg:classifiers":[
        {
            "category":"Manufacturing",
            "subcategory":"Paper Products",
            "type":"Manufacturing & Wholesale Goods"
        }
    ],
    "sg:phone":"+39 39038276108",
    "sg:postcode":"27013",
    "sg:province":"Pavia",
    "sg:tags":[
        "cardboard"
    ],
    "wof:name":"Baroni Fratelli S.a.s.",
    "wof:placetype":"venue"
},
  "geometry": {"coordinates":[9.4726343155,45.1473121643],"type":"Point"}
}