{
  "type": "Feature",
  "properties": {
    "iso:country":"IT",
    "sg:address":"Via Zona Industriale 64015 Nereto",
    "sg:city":"Nereto",
    "sg:classifiers":[
        {
            "category":"Wholesale",
            "subcategory":"Medical Equipment & Supplies",
            "type":"Manufacturing & Wholesale Goods"
        }
    ],
    "sg:phone":"+39 0861 808249",
    "sg:postcode":"64015",
    "sg:province":"Teramo",
    "sg:tags":[
        "-",
        "health",
        "instrument"
    ],
    "wof:name":"Tecno Bags Srl Unipersonale",
    "wof:placetype":"venue"
},
  "geometry": {"coordinates":[13.698531,42.66127],"type":"Point"}
}