{
  "type": "Feature",
  "properties": {
    "iso:country":"IT",
    "sg:address":"Via Lungo Chiampo 123 36054 Montebello Vicentino",
    "sg:city":"Montebello Vicentino",
    "sg:classifiers":[
        {
            "category":"Home & Garden",
            "subcategory":"Carpets & Floor Coverings",
            "type":"Retail Goods"
        }
    ],
    "sg:phone":"+39 0444 449511",
    "sg:postcode":"36054",
    "sg:province":"Vicenza",
    "sg:tags":[
        "animal",
        "skin"
    ],
    "sg:website":"www.montebello-tannery.it",
    "wof:name":"Conceria Montebello Spa",
    "wof:placetype":"venue"
},
  "geometry": {"coordinates":[11.387379,45.465969],"type":"Point"}
}