{
  "type": "Feature",
  "properties": {
    "addr:full":"13, V. Zandonai 44100 Ferrara Ferrara Ferrara 44100",
    "addr:housenumber":"13",
    "addr:postcode":"44100;44100",
    "addr:street":"V. Zandonai",
    "iso:country":"IT",
    "sg:address":"13, V. Zandonai 44100 Ferrara",
    "sg:city":"Ferrara",
    "sg:classifiers":[
        {
            "category":"Autos & Motor Vehicles",
            "subcategory":"Automobile Sales",
            "type":"Retail Goods"
        }
    ],
    "sg:phone":"+39 39053291984",
    "sg:postcode":"44100",
    "sg:province":"Ferrara",
    "sg:tags":[
        "equipment",
        "transport"
    ],
    "sg:website":"http://www.cd-italia.it:ws_end: :mark:ws:http://www.paginegialle.it/cditalia",
    "wof:name":"Cd Italia",
    "wof:placetype":"venue"
},
  "geometry": {"coordinates":[11.5963,44.814869],"type":"Point"}
}