{
  "type": "Feature",
  "properties": {
    "iso:country":"IT",
    "sg:address":"26034 Drizzona",
    "sg:city":"Drizzona",
    "sg:orig_category":"Non-classified Establishments",
    "sg:phone":"+39 0375 98384",
    "sg:postcode":"26034",
    "sg:province":"Cremona",
    "wof:name":"Giemme Srl",
    "wof:placetype":"venue"
},
  "geometry": {"coordinates":[10.346722,45.134644],"type":"Point"}
}