{
  "type": "Feature",
  "properties": {
    "addr:full":"50010 Scandicci Firenze 50010",
    "addr:postcode":"50010;50010",
    "iso:country":"IT",
    "sg:address":"50010 Scandicci",
    "sg:orig_category":"Macchine, Impianti E Forniture Per Industria Grafica, Cartaria E Cartotecnica",
    "sg:phone":"+39 055 731 1265",
    "sg:postcode":"50010",
    "sg:province":"Firenze",
    "wof:name":"Foldyn Srl",
    "wof:placetype":"venue"
},
  "geometry": {"coordinates":[11.256902,43.768734],"type":"Point"}
}