{
  "type": "Feature",
  "properties": {
    "iso:country":"IT",
    "sg:address":"38, Via Roma 20055 Renate",
    "sg:city":"Renate",
    "sg:classifiers":[
        {
            "category":"Shopping",
            "subcategory":"Computers & Home Electronics",
            "type":"Retail Goods"
        }
    ],
    "sg:phone":"+39 036 292 4713",
    "sg:postcode":"20055",
    "sg:province":"Milano",
    "sg:tags":[
        "electronic",
        "electrical",
        "equipment"
    ],
    "wof:name":"Rovelli Antonio (s.p.a.)",
    "wof:placetype":"venue"
},
  "geometry": {"coordinates":[9.279308,45.729458],"type":"Point"}
}