{
  "type": "Feature",
  "properties": {
    "iso:country":"IT",
    "sg:address":"Via P. Togliatti 2/a 42020 Quattro Castella",
    "sg:orig_category":"Solvent Distillations Devices",
    "sg:phone":"+39 0522 880321",
    "sg:postcode":"42020",
    "sg:province":"Reggio Nell'Emilia",
    "sg:website":"www.irac.it",
    "wof:name":"Irac Srl",
    "wof:placetype":"venue"
},
  "geometry": {"coordinates":[10.567183,44.642696],"type":"Point"}
}