{
  "type": "Feature",
  "properties": {
    "iso:country":"IT",
    "sg:address":"90135 Palermo",
    "sg:city":"Palermo",
    "sg:orig_category":"Automazione E Macchine Per Ufficio. Arredi Ed Attrezzature Per Attivita' Commerciali Ed Artigianali",
    "sg:phone":"+39 091 652 3622",
    "sg:postcode":"90135",
    "sg:province":"Palermo",
    "wof:name":"Sistem Copy Di Vincenzo Cambria",
    "wof:placetype":"venue"
},
  "geometry": {"coordinates":[13.330477,38.1105],"type":"Point"}
}