{
  "type": "Feature",
  "properties": {
    "iso:country":"IT",
    "sg:address":"20040 Cambiago",
    "sg:city":"Cambiago",
    "sg:orig_category":"Metalli E Leghe",
    "sg:phone":"+39 02 951 2980",
    "sg:postcode":"20040",
    "sg:province":"Milano",
    "wof:name":"Ims Spa",
    "wof:placetype":"venue"
},
  "geometry": {"coordinates":[9.421330452,45.5717430115],"type":"Point"}
}