{
  "type": "Feature",
  "properties": {
    "iso:country":"IT",
    "sg:address":"128, Via Ulivi 56022 Castelfranco Di Sotto",
    "sg:city":"Castelfranco di Sotto",
    "sg:classifiers":[
        {
            "category":"Food & Beverages",
            "subcategory":"Dairy",
            "type":"Retail Goods"
        }
    ],
    "sg:phone":"+39 0583 289163",
    "sg:postcode":"56022",
    "sg:province":"Pisa",
    "sg:tags":[
        "product"
    ],
    "wof:name":"Buralli Group",
    "wof:placetype":"venue"
},
  "geometry": {"coordinates":[10.68623,43.787659],"type":"Point"}
}