{
  "type": "Feature",
  "properties": {
    "addr:full":"40050 Castenaso Bologna 40050",
    "addr:postcode":"40050;40050",
    "iso:country":"IT",
    "sg:address":"40050 Castenaso",
    "sg:orig_category":"Macchine Utensili E Impianti. Macchine, Strumenti Ed Apparecchi Per Attivita' Industriali",
    "sg:phone":"+39 051 605 3006",
    "sg:postcode":"40050",
    "sg:province":"Bologna",
    "sg:website":"http://www.becker.it",
    "wof:name":"Becker Italia Srl",
    "wof:placetype":"venue"
},
  "geometry": {"coordinates":[11.439557,44.51133],"type":"Point"}
}