{
  "type": "Feature",
  "properties": {
    "iso:country":"IT",
    "sg:address":"95126 Catania",
    "sg:city":"Catania",
    "sg:orig_category":"Impiantistica E Prodotti Tecnologici Per Edilizia. Elettrotecnica Professionale E Di Consumo. Telecomunicazioni E Telefonia, Impianti, Apparecchi E Servizi",
    "sg:phone":"+39 095 504450",
    "sg:postcode":"95126",
    "sg:province":"Catania",
    "sg:website":"http://www.paginegialle.it/cgelettronica",
    "wof:name":"C.g. Elettronica Snc",
    "wof:placetype":"venue"
},
  "geometry": {"coordinates":[15.094791,37.524994],"type":"Point"}
}