{
  "type": "Feature",
  "properties": {
    "addr:full":"108, Via Bologna 40017 San Giovanni In Persiceto San Giovanni in Persiceto Bologna 40017",
    "addr:housenumber":"108",
    "addr:postcode":"40017;40017",
    "addr:street":"Via Bologna",
    "iso:country":"IT",
    "sg:address":"108, Via Bologna 40017 San Giovanni In Persiceto",
    "sg:city":"San Giovanni in Persiceto",
    "sg:classifiers":[
        {
            "category":"Autos & Motor Vehicles",
            "subcategory":"Automobile Sales",
            "type":"Retail Goods"
        }
    ],
    "sg:phone":"+39 39051821471",
    "sg:postcode":"40017",
    "sg:province":"Bologna",
    "sg:tags":[
        "motor-cars"
    ],
    "wof:name":"Poli Auto Service S.r.l.",
    "wof:placetype":"venue"
},
  "geometry": {"coordinates":[11.1929101944,44.6312408447],"type":"Point"}
}