{
  "type": "Feature",
  "properties": {
    "addr:full":"11/13, Via Palestro 50013 Campi Bisenzio Campi Bisenzio Firenze 50013",
    "addr:housenumber":"11 / 13",
    "addr:postcode":"50013;50013",
    "addr:street":"Via Palestro;Bisenzio",
    "iso:country":"IT",
    "sg:address":"11/13, Via Palestro 50013 Campi Bisenzio",
    "sg:city":"Campi Bisenzio",
    "sg:classifiers":[
        {
            "category":"Shopping",
            "subcategory":"Clothing, Apparel, & Fashions",
            "type":"Retail Goods"
        }
    ],
    "sg:phone":"+39 055 895 4584",
    "sg:postcode":"50013",
    "sg:province":"Firenze",
    "sg:tags":[
        "clothes"
    ],
    "wof:name":"Maglificio P & F Spa",
    "wof:placetype":"venue"
},
  "geometry": {"coordinates":[11.120631,43.824512],"type":"Point"}
}