{
  "type": "Feature",
  "properties": {
    "iso:country":"IT",
    "sg:address":"Via Pirelli 32, 20100 Milan, Mi",
    "sg:classifiers":[
        {
            "category":"Banks & Credit Unions",
            "subcategory":"Bank",
            "type":"Services"
        }
    ],
    "wof:name":"Xelion Sim Spa",
    "wof:placetype":"venue"
},
  "geometry": {"coordinates":[9.197003,45.484009],"type":"Point"}
}