{
  "type": "Feature",
  "properties": {
    "iso:country":"IT",
    "sg:address":"80044 Ottaviano",
    "sg:city":"Ottaviano",
    "sg:orig_category":"Caffe' Crudo E Torrefatto",
    "sg:phone":"+39 081 528 9573",
    "sg:postcode":"80044",
    "sg:province":"Napoli",
    "wof:name":"Pask\u00c0 Srl",
    "wof:placetype":"venue"
},
  "geometry": {"coordinates":[14.491347,40.863033],"type":"Point"}
}