{
  "type": "Feature",
  "properties": {
    "iso:country":"IT",
    "sg:address":"35037 Teolo",
    "sg:city":"Teolo",
    "sg:orig_category":"Porfidi E Pietre Per Pavimenti E Rivestimenti",
    "sg:phone":"+39 049 990 2550",
    "sg:postcode":"35037",
    "sg:province":"Padova",
    "wof:name":"Sinigaglia Valentino Snc",
    "wof:placetype":"venue"
},
  "geometry": {"coordinates":[11.7964439392,45.3701553345],"type":"Point"}
}