{
  "type": "Feature",
  "properties": {
    "iso:country":"IT",
    "sg:address":"Via Revine 25 30027 San Dona' Di Piave",
    "sg:classifiers":[
        {
            "category":"Utilities",
            "subcategory":"Mobile Phone",
            "type":"Services"
        }
    ],
    "sg:phone":"+39 0421 492111",
    "sg:postcode":"30027",
    "sg:province":"Venezia",
    "sg:tags":[
        "battery",
        "operated",
        "clock"
    ],
    "sg:website":"www.intermediatime.it",
    "wof:name":"Intermedia Time S.p.a.",
    "wof:placetype":"venue"
},
  "geometry": {"coordinates":[12.338784,45.434338],"type":"Point"}
}