{
  "type": "Feature",
  "properties": {
    "addr:full":"13900 Biella Biella Biella 13900",
    "addr:postcode":"13900;13900",
    "iso:country":"IT",
    "sg:address":"13900 Biella",
    "sg:city":"Biella",
    "sg:orig_category":"Servizi E Lavori Per Industria Alimentare E Bevande. Servizi E Lavori Per Abbigliamento E Pelletterie. Servizi E Lavori Per Arredamento E Industria Del Legno. Servizi Vari Di Interesse Pubblico",
    "sg:phone":"+39 015 840 9382",
    "sg:postcode":"13900",
    "sg:province":"Biella",
    "wof:name":"Fabricha S.r.l.",
    "wof:placetype":"venue"
},
  "geometry": {"coordinates":[8.063158,45.558571],"type":"Point"}
}