{
  "type": "Feature",
  "properties": {
    "addr:full":"80144 Napoli Napoli Napoli 80144",
    "addr:housenumber":"80144",
    "addr:postcode":"80144",
    "iso:country":"IT",
    "sg:address":"80144 Napoli",
    "sg:city":"Napoli",
    "sg:orig_category":"Prodotti Di Base E Forniture Per Industria Alimentare E Bevande",
    "sg:phone":"+39 081 754 4384",
    "sg:postcode":"80144",
    "sg:province":"Napoli",
    "wof:name":"Puzone Antonio",
    "wof:placetype":"venue"
},
  "geometry": {"coordinates":[14.2627773285,40.8950767517],"type":"Point"}
}