{
  "type": "Feature",
  "properties": {
    "addr:full":"16/4, V. Colombo 16121 Genova Genova Genova 16121",
    "addr:housenumber":"16 / 4 v.",
    "addr:postcode":"16121;16121",
    "addr:street":"Colombo",
    "iso:country":"IT",
    "sg:address":"16/4, V. Colombo 16121 Genova",
    "sg:city":"Genova",
    "sg:classifiers":[
        {
            "category":"Professional",
            "subcategory":"Engineering",
            "type":"Services"
        }
    ],
    "sg:phone":"+39 39010588412",
    "sg:postcode":"16121",
    "sg:province":"Genova",
    "sg:tags":[
        "machine",
        "-",
        "mechanical"
    ],
    "sg:website":"http://www.paginegialle.it/h-carletto",
    "wof:name":"Albergo Carletto",
    "wof:placetype":"venue"
},
  "geometry": {"coordinates":[8.944666,44.405994],"type":"Point"}
}