{
  "type": "Feature",
  "properties": {
    "iso:country":"IT",
    "sg:address":"66034 Lanciano",
    "sg:city":"Lanciano",
    "sg:orig_category":"Automobili - Commercio",
    "sg:phone":"+39 0872 42291",
    "sg:postcode":"66034",
    "sg:province":"Chieti",
    "wof:name":"Autosalone Zulli Di Zulli Luciano",
    "wof:placetype":"venue"
},
  "geometry": {"coordinates":[14.387874,42.22691],"type":"Point"}
}