{
  "type": "Feature",
  "properties": {
    "iso:country":"IT",
    "sg:address":"20090 Cesano Boscone",
    "sg:city":"Cesano Boscone",
    "sg:orig_category":"Arredo Cucina Ed Elettrodomestici. Frigotecnica, Apparecchiature E Servizi. Elettrodomestici",
    "sg:phone":"+39 02 458 5890",
    "sg:postcode":"20090",
    "sg:province":"Milano",
    "wof:name":"Gobetti Luigi",
    "wof:placetype":"venue"
},
  "geometry": {"coordinates":[9.09371,45.446434],"type":"Point"}
}