{
  "type": "Feature",
  "properties": {
    "iso:country":"IT",
    "sg:address":"68, Via Albisola 16162 Genova",
    "sg:city":"Genova",
    "sg:classifiers":[
        {
            "category":"Autos & Motor Vehicles",
            "subcategory":"Boat Sales",
            "type":"Retail Goods"
        }
    ],
    "sg:phone":"+39 39010711583",
    "sg:postcode":"16162",
    "sg:province":"Genova",
    "wof:name":"Ranieri Tonissi S.p.a",
    "wof:placetype":"venue"
},
  "geometry": {"coordinates":[8.89543,44.469631],"type":"Point"}
}