{
  "type": "Feature",
  "properties": {
    "addr:full":"1, Via Enrico Fermi 35040 Santa Margherita D'adige Padova 35040",
    "addr:postcode":"35040;35040",
    "addr:street":"Via Enrico Fermi",
    "iso:country":"IT",
    "sg:address":"1, Via Enrico Fermi 35040 Santa Margherita D'adige",
    "sg:classifiers":[
        {
            "category":"Shopping",
            "subcategory":"Clothing, Apparel, & Fashions",
            "type":"Retail Goods"
        }
    ],
    "sg:phone":"+39 39042986632",
    "sg:postcode":"35040",
    "sg:province":"Padova",
    "sg:tags":[
        "clothes"
    ],
    "wof:name":"Vadore Luciana",
    "wof:placetype":"venue"
},
  "geometry": {"coordinates":[11.876589,45.409569],"type":"Point"}
}