{
  "type": "Feature",
  "properties": {
    "iso:country":"IT",
    "sg:address":"41057 Spilamberto",
    "sg:city":"Spilamberto",
    "sg:orig_category":"Elettrotecnica Industriale, Prodotti E Apparecchiature",
    "sg:phone":"+39 059 784108",
    "sg:postcode":"41057",
    "sg:province":"Modena",
    "wof:name":"P.b.m. (s.p.a.)",
    "wof:placetype":"venue"
},
  "geometry": {"coordinates":[11.007039,44.544132],"type":"Point"}
}