{
  "type": "Feature",
  "properties": {
    "iso:country":"IT",
    "sg:address":"06012 Trestina",
    "sg:orig_category":"Agricoltura, Orticoltura E Floricoltura",
    "sg:phone":"+39 075 864 2459",
    "sg:postcode":"06012",
    "sg:province":"Perugia",
    "wof:name":"A.pro.ta.v.",
    "wof:placetype":"venue"
},
  "geometry": {"coordinates":[12.235799,43.368687],"type":"Point"}
}