{
  "type": "Feature",
  "properties": {
    "iso:country":"IT",
    "sg:address":"20156 Milano",
    "sg:city":"Milano",
    "sg:orig_category":"Accessori Dei Mezzi Di Trasporto",
    "sg:phone":"+39 02 3926 5586",
    "sg:postcode":"20156",
    "sg:province":"Milano",
    "wof:name":"Honeywell Garrett Spa",
    "wof:placetype":"venue"
},
  "geometry": {"coordinates":[9.154981,45.497654],"type":"Point"}
}