{
  "type": "Feature",
  "properties": {
    "addr:full":"14100 Asti Asti Asti 14100",
    "addr:postcode":"14100;14100",
    "iso:country":"IT",
    "sg:address":"14100 Asti",
    "sg:city":"Asti",
    "sg:orig_category":"Architetti - Studi",
    "sg:phone":"+39 0141 532148",
    "sg:postcode":"14100",
    "sg:province":"Asti",
    "wof:name":"Edil.co Di Arch. Secondo Cotto & C. Sas",
    "wof:placetype":"venue"
},
  "geometry": {"coordinates":[8.205588,44.896614],"type":"Point"}
}