{
  "type": "Feature",
  "properties": {
    "iso:country":"IT",
    "sg:address":"20030 Senago",
    "sg:city":"Senago",
    "sg:orig_category":"Imprese Di Costruzioni Civili Ed Industriali",
    "sg:phone":"+39 02 9905 7173",
    "sg:postcode":"20030",
    "sg:province":"Milano",
    "sg:website":"http://www.gallialessandro.it",
    "wof:name":"Galli Alessandro",
    "wof:placetype":"venue"
},
  "geometry": {"coordinates":[9.392757,45.649235],"type":"Point"}
}