{
  "type": "Feature",
  "properties": {
    "addr:full":"12, Via Dei Grimani 20144 Milano Milano Milano 20144",
    "addr:postcode":"20144;20144",
    "addr:street":"Via Dei Grimani",
    "iso:country":"IT",
    "sg:address":"12, Via Dei Grimani 20144 Milano",
    "sg:city":"Milano",
    "sg:classifiers":[
        {
            "category":"Wholesale",
            "subcategory":"Medical Equipment & Supplies",
            "type":"Manufacturing & Wholesale Goods"
        }
    ],
    "sg:phone":"+39 02 4895 2697",
    "sg:postcode":"20144",
    "sg:province":"Milano",
    "sg:tags":[
        "-",
        "health",
        "instrument"
    ],
    "wof:name":"Robecchi Di Francesco Fasciano E C. (s.a.s.)",
    "wof:placetype":"venue"
},
  "geometry": {"coordinates":[9.15576,45.457249],"type":"Point"}
}