{
  "type": "Feature",
  "properties": {
    "iso:country":"IT",
    "sg:address":"Via Miggiano 73056 Taurisano",
    "sg:city":"Taurisano",
    "sg:classifiers":[
        {
            "category":"Farming",
            "subcategory":"Livestock Farm",
            "type":"Manufacturing & Wholesale Goods"
        }
    ],
    "sg:phone":"+39 0833 622899",
    "sg:postcode":"73056",
    "sg:province":"Lecce",
    "sg:tags":[
        "agriculture"
    ],
    "wof:name":"Industria Alimentare Carni F.lli Scarlino Srl",
    "wof:placetype":"venue"
},
  "geometry": {"coordinates":[18.223455,39.958637],"type":"Point"}
}