{
  "type": "Feature",
  "properties": {
    "iso:country":"IT",
    "sg:address":"53014 Monteroni D'arbia",
    "sg:orig_category":"Lavori Agricoli E Forestali",
    "sg:phone":"+39 0577 372203",
    "sg:postcode":"53014",
    "sg:province":"Siena",
    "wof:name":"Agritecno Srl",
    "wof:placetype":"venue"
},
  "geometry": {"coordinates":[11.37715,43.213531],"type":"Point"}
}