{
  "type": "Feature",
  "properties": {
    "iso:country":"IT",
    "sg:address":"80141 Napoli",
    "sg:city":"Napoli",
    "sg:orig_category":"Macchine, Impianti E Forniture Per Industria Grafica, Cartaria E Cartotecnica",
    "sg:phone":"+39 081 751 4157",
    "sg:postcode":"80141",
    "sg:province":"Napoli",
    "wof:name":"Rotunno Srl",
    "wof:placetype":"venue"
},
  "geometry": {"coordinates":[14.265802,40.872143],"type":"Point"}
}