{
  "type": "Feature",
  "properties": {
    "iso:country":"IT",
    "sg:address":"42100 Reggio Emilia",
    "sg:orig_category":"Impiantistica E Prodotti Tecnologici Per Edilizia. Elettronica Professionale E Di Consumo",
    "sg:phone":"+39 0522 302670",
    "sg:postcode":"42100",
    "sg:province":"Reggio Nell'Emilia",
    "sg:website":"http://www.aggetto.it",
    "wof:name":"A.a. Aggetto Srl",
    "wof:placetype":"venue"
},
  "geometry": {"coordinates":[10.628794,44.703697],"type":"Point"}
}