{
  "type": "Feature",
  "properties": {
    "addr:full":"37121 Verona Verona Verona 37121",
    "addr:postcode":"37121;37121",
    "iso:country":"IT",
    "sg:address":"37121 Verona",
    "sg:city":"Verona",
    "sg:orig_category":"Pasticceria E Confetteria Prodotti - Produzione E Ingrosso",
    "sg:phone":"+39 045 800 3055",
    "sg:postcode":"37121",
    "sg:province":"Verona",
    "wof:name":"Cordioli Maurizio Pasticceria",
    "wof:placetype":"venue"
},
  "geometry": {"coordinates":[10.9988183975,45.4413414001],"type":"Point"}
}