{
  "type": "Feature",
  "properties": {
    "addr:full":"1, Localita' Aeroporto 17038 Villanova Di Albenga Savona 17038",
    "addr:postcode":"17038;17038",
    "addr:street":"Localita '",
    "iso:country":"IT",
    "sg:address":"1, Localita' Aeroporto 17038 Villanova Di Albenga",
    "sg:classifiers":[
        {
            "category":"Airport",
            "subcategory":"General Aviation",
            "type":"Transportation"
        }
    ],
    "sg:phone":"+39 0182 582033",
    "sg:postcode":"17038",
    "sg:province":"Savona",
    "sg:tags":[
        "transport",
        "air"
    ],
    "wof:name":"Aeroporto Di Villanova D'albenga S.p.a.",
    "wof:placetype":"venue"
},
  "geometry": {"coordinates":[8.477246,44.311069],"type":"Point"}
}