{
  "type": "Feature",
  "properties": {
    "addr:full":"28021 Borgomanero Borgomanero Novara 28021",
    "addr:postcode":"28021;28021",
    "iso:country":"IT",
    "sg:address":"28021 Borgomanero",
    "sg:city":"Borgomanero",
    "sg:orig_category":"Accessori Moda D'abbigliamento. Shopping",
    "sg:phone":"+39 0322 836054",
    "sg:postcode":"28021",
    "sg:province":"Novara",
    "wof:name":"Salsa Barbara Centro Sposa M. & G.",
    "wof:placetype":"venue"
},
  "geometry": {"coordinates":[8.465034,45.695923],"type":"Point"}
}