{
  "type": "Feature",
  "properties": {
    "addr:full":"30010 Campolongo Maggiore Campolongo Maggiore Venezia 30010",
    "addr:postcode":"30010;30010",
    "addr:street":"Maggiore",
    "iso:country":"IT",
    "sg:address":"30010 Campolongo Maggiore",
    "sg:city":"Campolongo Maggiore",
    "sg:orig_category":"Fognature",
    "sg:phone":"+39 049 584 8533",
    "sg:postcode":"30010",
    "sg:province":"Venezia",
    "wof:name":"Lando Tiziano",
    "wof:placetype":"venue"
},
  "geometry": {"coordinates":[12.0450839996,45.3228416443],"type":"Point"}
}