{
  "type": "Feature",
  "properties": {
    "addr:full":"50144 Firenze Firenze Firenze 50144",
    "addr:postcode":"50144;50144",
    "iso:country":"IT",
    "sg:address":"50144 Firenze",
    "sg:city":"Firenze",
    "sg:orig_category":"Macchine E Forniture Per Industria Orafa E Per Orologeria",
    "sg:phone":"+39 055 330872",
    "sg:postcode":"50144",
    "sg:province":"Firenze",
    "wof:name":"Zagli Stefano E C. Sas",
    "wof:placetype":"venue"
},
  "geometry": {"coordinates":[11.23077,43.788155],"type":"Point"}
}