{
  "type": "Feature",
  "properties": {
    "iso:country":"IT",
    "sg:address":"10143 Torino",
    "sg:city":"Torino",
    "sg:orig_category":"Arte Ed Artigianato Artistico",
    "sg:phone":"+39 011 437 1973",
    "sg:postcode":"10143",
    "sg:province":"Torino",
    "wof:name":"Alberto Donini Sas",
    "wof:placetype":"venue"
},
  "geometry": {"coordinates":[7.662772,45.078381],"type":"Point"}
}