{
  "type": "Feature",
  "properties": {
    "iso:country":"IT",
    "sg:address":"20099 Sesto San Giovanni",
    "sg:city":"Sesto San Giovanni",
    "sg:orig_category":"Riparazione Dei Mezzi Di Trasporto. Servizi Ausiliari Dei Mezzi Di Trasporto",
    "sg:phone":"+39 02 240 9650",
    "sg:postcode":"20099",
    "sg:province":"Milano",
    "wof:name":"Tecno Motor Di Cappelletti Emilio",
    "wof:placetype":"venue"
},
  "geometry": {"coordinates":[9.259979,45.553982],"type":"Point"}
}