{
  "type": "Feature",
  "properties": {
    "iso:country":"IT",
    "sg:address":"72015 Fasano",
    "sg:city":"Fasano",
    "sg:orig_category":"Telecomunicazioni E Telefonia, Impianti, Apparecchi E Servizi",
    "sg:phone":"+39 080 442 5167",
    "sg:postcode":"72015",
    "sg:province":"Brindisi",
    "wof:name":"Radio Diaconia",
    "wof:placetype":"venue"
},
  "geometry": {"coordinates":[17.358696,40.834309],"type":"Point"}
}