{
  "type": "Feature",
  "properties": {
    "iso:country":"IT",
    "sg:address":"Via Montanara 15 29015 Castel San Giovanni",
    "sg:city":"Castel San Giovanni",
    "sg:classifiers":[
        {
            "category":"Food & Beverages",
            "subcategory":"Liquor & Beverages",
            "type":"Retail Goods"
        }
    ],
    "sg:phone":"+39 0523 844441",
    "sg:postcode":"29015",
    "sg:province":"Piacenza",
    "sg:tags":[
        "wine",
        "italian"
    ],
    "wof:name":"C.e.a.v.a. Srl",
    "wof:placetype":"venue"
},
  "geometry": {"coordinates":[9.436519,45.055935],"type":"Point"}
}