{
  "type": "Feature",
  "properties": {
    "addr:full":"Strada Lanzo, 138 Bis 10148 Torino Torino Torino 10148",
    "addr:housenumber":"138 bis",
    "addr:postcode":"10148;10148",
    "addr:street":"Strada Lanzo",
    "iso:country":"IT",
    "sg:address":"Strada Lanzo, 138 Bis 10148 Torino",
    "sg:city":"Torino",
    "sg:classifiers":[
        {
            "category":"Autos & Motor Vehicles",
            "subcategory":"Automobile Sales",
            "type":"Retail Goods"
        }
    ],
    "sg:phone":"+39 011 226 2452",
    "sg:postcode":"10148",
    "sg:province":"Torino",
    "sg:tags":[
        "car",
        "mirror"
    ],
    "sg:website":"www.velgraf.it",
    "wof:name":"Velgraf S.a.s. Di Scodeller Maurizio",
    "wof:placetype":"venue"
},
  "geometry": {"coordinates":[7.657543,45.117073],"type":"Point"}
}