{
  "type": "Feature",
  "properties": {
    "iso:country":"IT",
    "sg:address":"30027 San Don\u00e0 Di Piave",
    "sg:orig_category":"Motori Diesel E Componenti",
    "sg:phone":"+39 0421 42314",
    "sg:postcode":"30027",
    "sg:province":"Venezia",
    "sg:website":"http://www.mabosnc.com",
    "wof:name":"Mabo Snc Di Boem Giorgio & C.",
    "wof:placetype":"venue"
},
  "geometry": {"coordinates":[12.6318349838,45.7180213928],"type":"Point"}
}