{
  "type": "Feature",
  "properties": {
    "addr:full":"16121 Genova Genova Genova 16121",
    "addr:postcode":"16121;16121",
    "iso:country":"IT",
    "sg:address":"16121 Genova",
    "sg:city":"Genova",
    "sg:orig_category":"Informatica - Consulenza E Software",
    "sg:phone":"+39 010 543608",
    "sg:postcode":"16121",
    "sg:province":"Genova",
    "sg:website":"http://www.formentini.com",
    "wof:name":"Formentini Lionello & C. Snc",
    "wof:placetype":"venue"
},
  "geometry": {"coordinates":[8.943597,44.406944],"type":"Point"}
}