{
  "type": "Feature",
  "properties": {
    "iso:country":"IT",
    "sg:address":"3, Via Don Giovanni Verita' 20052 Monza",
    "sg:city":"Monza",
    "sg:classifiers":[
        {
            "category":"Professional",
            "subcategory":"Engineering",
            "type":"Services"
        }
    ],
    "sg:phone":"+39 39039323129",
    "sg:postcode":"20052",
    "sg:province":"Milano",
    "sg:tags":[
        "machine",
        "-",
        "mechanical"
    ],
    "wof:name":"La Meccanica Fumagalli (s.r.l.)",
    "wof:placetype":"venue"
},
  "geometry": {"coordinates":[9.258119,45.589512],"type":"Point"}
}