{
  "type": "Feature",
  "properties": {
    "iso:country":"IT",
    "sg:address":"Via Leonardo; Montecchio Maggiore; 36041",
    "sg:classifiers":[
        {
            "category":"Banks & Credit Unions",
            "subcategory":"Bank",
            "type":"Services"
        }
    ],
    "sg:phone":"+39 0444 490400",
    "wof:name":"Banco Ambrosiano Veneto Spa",
    "wof:placetype":"venue"
},
  "geometry": {"coordinates":[11.396119,45.513386],"type":"Point"}
}