{
  "type": "Feature",
  "properties": {
    "addr:full":"25036 Palazzolo Sull'oglio Brescia 25036",
    "addr:postcode":"25036;25036",
    "iso:country":"IT",
    "sg:address":"25036 Palazzolo Sull'oglio",
    "sg:orig_category":"Forniture Per Abbigliamento E Pelletterie",
    "sg:phone":"+39 030 740 1152",
    "sg:postcode":"25036",
    "sg:province":"Brescia",
    "wof:name":"Gu.ma. Di Pozzi Manuela",
    "wof:placetype":"venue"
},
  "geometry": {"coordinates":[9.8897514343,45.5855064392],"type":"Point"}
}