{
  "type": "Feature",
  "properties": {
    "addr:full":"340/b1, Via Selice 48017 Conselice Conselice Ravenna 48017",
    "addr:housenumber":"340 / b1",
    "addr:postcode":"48017;48017",
    "addr:street":"Via Selice",
    "iso:country":"IT",
    "sg:address":"340/b1, Via Selice 48017 Conselice",
    "sg:city":"Conselice",
    "sg:classifiers":[
        {
            "category":"Manufacturing",
            "subcategory":"Metals",
            "type":"Manufacturing & Wholesale Goods"
        }
    ],
    "sg:phone":"+39 39054580690",
    "sg:postcode":"48017",
    "sg:province":"Ravenna",
    "sg:tags":[
        "processing"
    ],
    "wof:name":"Off. Za.bo. Srl",
    "wof:placetype":"venue"
},
  "geometry": {"coordinates":[11.8597335815,44.5570869446],"type":"Point"}
}