{
  "type": "Feature",
  "properties": {
    "addr:full":"Via Sampoi 68 32020 Limana Limana Belluno 32020",
    "addr:housenumber":"68",
    "addr:postcode":"32020;32020",
    "addr:street":"Via Sampoi",
    "iso:country":"IT",
    "sg:address":"Via Sampoi 68 32020 Limana",
    "sg:city":"Limana",
    "sg:classifiers":[
        {
            "category":"Wholesale",
            "subcategory":"Plants",
            "type":"Manufacturing & Wholesale Goods"
        }
    ],
    "sg:phone":"+39 0437 967429",
    "sg:postcode":"32020",
    "sg:province":"Belluno",
    "sg:tags":[
        "cooling",
        "industrial"
    ],
    "wof:name":"Fontana Soffiro Frigoriferi Snc Di Fontana Soffiro E C.",
    "wof:placetype":"venue"
},
  "geometry": {"coordinates":[12.186262,46.103851],"type":"Point"}
}