{
  "type": "Feature",
  "properties": {
    "addr:full":"90143 Palermo Palermo Palermo 90143",
    "addr:postcode":"90143;90143",
    "iso:country":"IT",
    "sg:address":"90143 Palermo",
    "sg:city":"Palermo",
    "sg:orig_category":"Informatica - Consulenza E Software",
    "sg:phone":"+39 091 626 2332",
    "sg:postcode":"90143",
    "sg:province":"Palermo",
    "sg:website":"http://www.deskservice.com",
    "wof:name":"Desk Srl",
    "wof:placetype":"venue"
},
  "geometry": {"coordinates":[13.349214,38.141289],"type":"Point"}
}