{
  "type": "Feature",
  "properties": {
    "addr:full":"21013 Gallarate Gallarate Varese 21013",
    "addr:postcode":"21013;21013",
    "iso:country":"IT",
    "sg:address":"21013 Gallarate",
    "sg:city":"Gallarate",
    "sg:orig_category":"Metalli Non Ferrosi E Leghe",
    "sg:phone":"+39 0331 792028",
    "sg:postcode":"21013",
    "sg:province":"Varese",
    "sg:website":"http://www.crespimetalli.com",
    "wof:name":"Mario Crespi Spa",
    "wof:placetype":"venue"
},
  "geometry": {"coordinates":[8.8324108124,45.8183135986],"type":"Point"}
}