{
  "type": "Feature",
  "properties": {
    "iso:country":"IT",
    "sg:address":"59, Via Vittorio Veneto 31053 Pieve Di Soligo",
    "sg:city":"Pieve di Soligo",
    "sg:classifiers":[
        {
            "category":"Shopping",
            "subcategory":"Clothing, Apparel, & Fashions",
            "type":"Retail Goods"
        }
    ],
    "sg:phone":"+39 0438 980358",
    "sg:postcode":"31053",
    "sg:province":"Treviso",
    "sg:tags":[
        "clothes"
    ],
    "wof:name":"Stilfix (s.r.l.)",
    "wof:placetype":"venue"
},
  "geometry": {"coordinates":[12.163132,45.903267],"type":"Point"}
}