{
  "type": "Feature",
  "properties": {
    "iso:country":"IT",
    "sg:address":"25027 Quinzano D'oglio",
    "sg:orig_category":"Non-classified Establishments",
    "sg:phone":"+39 030 933033",
    "sg:postcode":"25027",
    "sg:province":"Brescia",
    "wof:name":"Rivadossi Fratelli (s.a.s.)",
    "wof:placetype":"venue"
},
  "geometry": {"coordinates":[10.015853,45.306885],"type":"Point"}
}