{
  "type": "Feature",
  "properties": {
    "iso:country":"IT",
    "sg:address":"41100 Modena",
    "sg:city":"Modena",
    "sg:orig_category":"Cancelleria",
    "sg:phone":"+39 059 331292",
    "sg:postcode":"41100",
    "sg:province":"Modena",
    "wof:name":"Ruggeri Vasco & Figli Spa",
    "wof:placetype":"venue"
},
  "geometry": {"coordinates":[10.901419,44.647861],"type":"Point"}
}