{
  "type": "Feature",
  "properties": {
    "iso:country":"IT",
    "sg:address":"20123 Milano",
    "sg:city":"Milano",
    "sg:orig_category":"Musica",
    "sg:phone":"+39 02 481 6125",
    "sg:postcode":"20123",
    "sg:province":"Milano",
    "wof:name":"Ecofina S.r.l.",
    "wof:placetype":"venue"
},
  "geometry": {"coordinates":[9.1691904068,45.470905304],"type":"Point"}
}