{
  "type": "Feature",
  "properties": {
    "iso:country":"IT",
    "sg:address":"16153 Genova",
    "sg:city":"Genova",
    "sg:orig_category":"Elettrotecnica Industriale, Prodotti E Apparecchiature",
    "sg:phone":"+39 010 650 5646",
    "sg:postcode":"16153",
    "sg:province":"Genova",
    "wof:name":"Reba S.r.l.",
    "wof:placetype":"venue"
},
  "geometry": {"coordinates":[8.816593,44.427673],"type":"Point"}
}