{
  "type": "Feature",
  "properties": {
    "iso:country":"IT",
    "sg:address":"00043 Ciampino",
    "sg:city":"Ciampino",
    "sg:orig_category":"Ossidazione Anodica",
    "sg:phone":"+39 06 791 1709",
    "sg:postcode":"00043",
    "sg:province":"Roma",
    "wof:name":"Oxal Di Fabian Nicola",
    "wof:placetype":"venue"
},
  "geometry": {"coordinates":[12.613312,41.807041],"type":"Point"}
}