{
  "type": "Feature",
  "properties": {
    "iso:country":"IT",
    "sg:address":"41019 Soliera",
    "sg:city":"Soliera",
    "sg:orig_category":"Termotecnica E Riscaldamento, Apparecchiature E Servizi",
    "sg:phone":"+39 059 857 0120",
    "sg:postcode":"41019",
    "sg:province":"Modena",
    "sg:website":"http://www.sigmazero.net",
    "wof:name":"Sigmazero Srl",
    "wof:placetype":"venue"
},
  "geometry": {"coordinates":[10.917381,44.732838],"type":"Point"}
}