{
  "type": "Feature",
  "properties": {
    "iso:country":"IT",
    "sg:address":"35010 Limena",
    "sg:city":"Limena",
    "sg:orig_category":"Prodotti E Manufatti In Materie Plastiche",
    "sg:phone":"+39 049 769529",
    "sg:postcode":"35010",
    "sg:province":"Padova",
    "wof:name":"Tecno Gomma (s.n.c.)",
    "wof:placetype":"venue"
},
  "geometry": {"coordinates":[11.8448705673,45.4732971191],"type":"Point"}
}