{
  "type": "Feature",
  "properties": {
    "addr:full":"04100 Latina Latina Latina 04100",
    "addr:postcode":"04100;04100",
    "iso:country":"IT",
    "sg:address":"04100 Latina",
    "sg:city":"Latina",
    "sg:orig_category":"Arti Grafiche - Accessori E Forniture",
    "sg:phone":"+39 0773 694963",
    "sg:postcode":"04100",
    "sg:province":"Latina",
    "wof:name":"Linea Verde",
    "wof:placetype":"venue"
},
  "geometry": {"coordinates":[12.779326,41.566307],"type":"Point"}
}