{
  "type": "Feature",
  "properties": {
    "iso:country":"IT",
    "sg:address":"30, Via Vercelli 28060 Casalino",
    "sg:city":"Casalino",
    "sg:classifiers":[
        {
            "category":"Manufacturing",
            "subcategory":"Rubber & Plastics",
            "type":"Manufacturing & Wholesale Goods"
        }
    ],
    "sg:phone":"+39 0321 879443",
    "sg:postcode":"28060",
    "sg:province":"Novara",
    "wof:name":"Vipa Srl",
    "wof:placetype":"venue"
},
  "geometry": {"coordinates":[8.5330257416,45.3959083557],"type":"Point"}
}