{
  "type": "Feature",
  "properties": {
    "addr:full":"Via Cernaia 82; Firenze; 50129 Firenze Firenze 50129",
    "addr:housenumber":"82",
    "addr:postcode":"50129;50129",
    "addr:street":"Via Cernaia",
    "iso:country":"IT",
    "sg:address":"Via Cernaia 82; Firenze; 50129",
    "sg:city":"Firenze",
    "sg:classifiers":[
        {
            "category":"Banks & Credit Unions",
            "subcategory":"Bank",
            "type":"Services"
        }
    ],
    "sg:phone":"+39 055 490745",
    "sg:postcode":"50129",
    "sg:province":"Firenze",
    "wof:name":"Cassa Di Risparmio Di Firenze",
    "wof:placetype":"venue"
},
  "geometry": {"coordinates":[11.250842,43.78537],"type":"Point"}
}