{
  "type": "Feature",
  "properties": {
    "iso:country":"IT",
    "sg:address":"81030 Castel Volturno",
    "sg:city":"Castel Volturno",
    "sg:orig_category":"Nautica. Automobili E Mezzi Di Trasporto",
    "sg:phone":"+39 081 509 1909",
    "sg:postcode":"81030",
    "sg:province":"Caserta",
    "wof:name":"Teknonautica Sas Di Alberto Coletta & C.",
    "wof:placetype":"venue"
},
  "geometry": {"coordinates":[13.982357,40.983643],"type":"Point"}
}