{
  "type": "Feature",
  "properties": {
    "iso:country":"IT",
    "sg:address":"00045 Genzano Di Roma",
    "sg:city":"Genzano di Roma",
    "sg:orig_category":"Dolciumi E Gelati",
    "sg:phone":"+39 06 939 6603",
    "sg:postcode":"00045",
    "sg:province":"Roma",
    "wof:name":"Ciccia Irene",
    "wof:placetype":"venue"
},
  "geometry": {"coordinates":[12.650665,41.749958],"type":"Point"}
}