{
  "type": "Feature",
  "properties": {
    "iso:country":"IT",
    "sg:address":"71043 Manfredonia",
    "sg:city":"Manfredonia",
    "sg:classifiers":[
        {
            "category":"Health Services",
            "subcategory":"Health Practitioner",
            "type":"Services"
        }
    ],
    "sg:phone":"+39 0884 534520",
    "sg:postcode":"71043",
    "sg:province":"Foggia",
    "sg:tags":[
        "medici"
    ],
    "wof:name":"Vairo Giuseppe",
    "wof:placetype":"venue"
},
  "geometry": {"coordinates":[15.8055467606,41.5505065918],"type":"Point"}
}