{
  "type": "Feature",
  "properties": {
    "iso:country":"IT",
    "sg:address":"20136 Milano",
    "sg:city":"Milano",
    "sg:orig_category":"Cinematografia E Radiotelevisione. Cine-foto-ottica",
    "sg:phone":"+39 02 5831 6185",
    "sg:postcode":"20136",
    "sg:province":"Milano",
    "wof:name":"Punto Rosso",
    "wof:placetype":"venue"
},
  "geometry": {"coordinates":[9.1964,45.446293],"type":"Point"}
}