{
  "type": "Feature",
  "properties": {
    "iso:country":"IT",
    "sg:address":"6, Via Laviano Z.i.p.r. 33078 San Vito Al Tagliamento",
    "sg:city":"San Vito al Tagliamento",
    "sg:classifiers":[
        {
            "category":"Shopping",
            "type":"Retail Goods"
        }
    ],
    "sg:phone":"+39 39043485139",
    "sg:postcode":"33078",
    "sg:province":"Pordenone",
    "sg:tags":[
        "finished",
        "-",
        "metallic"
    ],
    "wof:name":"Ambrosio F.lli (s.n.c.)",
    "wof:placetype":"venue"
},
  "geometry": {"coordinates":[12.655043602,45.9626502991],"type":"Point"}
}