{
  "type": "Feature",
  "properties": {
    "iso:country":"IT",
    "sg:address":"5, Via Dell' Artigianato 35020 Albignasego",
    "sg:city":"Albignasego",
    "sg:classifiers":[
        {
            "category":"Food & Beverages",
            "subcategory":"Groceries & Convenience Stores",
            "type":"Retail Goods"
        }
    ],
    "sg:phone":"+39 049 731 3229",
    "sg:postcode":"35020",
    "sg:province":"Padova",
    "sg:tags":[
        "drink"
    ],
    "wof:name":"Bottaro & Rizzo S.r.l.",
    "wof:placetype":"venue"
},
  "geometry": {"coordinates":[11.822266,45.329178],"type":"Point"}
}