{
  "type": "Feature",
  "properties": {
    "iso:country":"IT",
    "sg:address":"248, Contrada Volta Del Camino 84034 Padula",
    "sg:city":"Padula",
    "sg:classifiers":[
        {
            "category":"Personal",
            "subcategory":"Shoe Repair & Shine",
            "type":"Services"
        }
    ],
    "sg:phone":"+39 0975 574055",
    "sg:postcode":"84034",
    "sg:province":"Salerno",
    "sg:tags":[
        "leather"
    ],
    "wof:name":"Febo Snc Di Giovanni Abbruzzese E Giambattista Chi",
    "wof:placetype":"venue"
},
  "geometry": {"coordinates":[14.765912,40.677956],"type":"Point"}
}