{
  "type": "Feature",
  "properties": {
    "addr:full":"51037 Montale Montale Pistoia 51037",
    "addr:postcode":"51037;51037",
    "iso:country":"IT",
    "sg:address":"51037 Montale",
    "sg:city":"Montale",
    "sg:orig_category":"Lattiero Casearia Industria - Macchine",
    "sg:phone":"+39 0573 557741",
    "sg:postcode":"51037",
    "sg:province":"Pistoia",
    "wof:name":"Ml Sas Di Gianfranco Mattei & C.",
    "wof:placetype":"venue"
},
  "geometry": {"coordinates":[11.024898,43.937439],"type":"Point"}
}