{
  "type": "Feature",
  "properties": {
    "addr:full":"Via Marconi 18/b 16010 Savignone Savignone Genova 16010",
    "addr:housenumber":"18 / b",
    "addr:postcode":"16010;16010",
    "addr:street":"Via Marconi",
    "iso:country":"IT",
    "sg:address":"Via Marconi 18/b 16010 Savignone",
    "sg:city":"Savignone",
    "sg:classifiers":[
        {
            "category":"Shopping",
            "subcategory":"Clothing, Apparel, & Fashions",
            "type":"Retail Goods"
        }
    ],
    "sg:phone":"+39 010 936 0095",
    "sg:postcode":"16010",
    "sg:province":"Genova",
    "sg:tags":[
        "gown",
        "evening",
        "dress",
        "cocktail"
    ],
    "sg:website":"www.aldonegri.com",
    "wof:name":"Ditta Aldo Negri Di Maria Luisa Negri",
    "wof:placetype":"venue"
},
  "geometry": {"coordinates":[8.927384,44.538792],"type":"Point"}
}