{
  "type": "Feature",
  "properties": {
    "iso:country":"IT",
    "sg:address":"12, Via Alessandro Manzoni 22060 Arosio",
    "sg:city":"Arosio",
    "sg:classifiers":[
        {
            "category":"Shopping",
            "subcategory":"Computers & Home Electronics",
            "type":"Retail Goods"
        }
    ],
    "sg:phone":"+39 39031764069",
    "sg:postcode":"22060",
    "sg:province":"Como",
    "sg:tags":[
        "electronic",
        "electrical",
        "equipment"
    ],
    "wof:name":"Val Matic Srl",
    "wof:placetype":"venue"
},
  "geometry": {"coordinates":[9.197453,45.758301],"type":"Point"}
}