{
  "type": "Feature",
  "properties": {
    "iso:country":"IT",
    "sg:address":"33019 Tricesimo",
    "sg:city":"Tricesimo",
    "sg:classifiers":[
        {
            "category":"Government",
            "subcategory":"Office",
            "type":"Public Place"
        }
    ],
    "sg:phone":"+39 0432 854560",
    "sg:postcode":"33019",
    "sg:province":"Udine",
    "sg:tags":[
        "e",
        "lo",
        "tempo",
        "libero",
        "per",
        "spettacolo",
        "servizi",
        "culturali",
        "sport",
        "il"
    ],
    "wof:name":"Gruppo Bandistico Folk 'rosade Furlane'",
    "wof:placetype":"venue"
},
  "geometry": {"coordinates":[13.266809,46.074158],"type":"Point"}
}