{
  "type": "Feature",
  "properties": {
    "addr:full":"40062 Molinella Molinella Bologna 40062",
    "addr:postcode":"40062;40062",
    "iso:country":"IT",
    "sg:address":"40062 Molinella",
    "sg:city":"Molinella",
    "sg:orig_category":"Macchine, Impianti Ed Attrezzature Per Industria Alimentare E Bevande",
    "sg:phone":"+39 051 887052",
    "sg:postcode":"40062",
    "sg:province":"Bologna",
    "wof:name":"Enotrading S.a.s Di Gianpaolo Gulinelli & C.",
    "wof:placetype":"venue"
},
  "geometry": {"coordinates":[11.267696,44.483101],"type":"Point"}
}