{
  "type": "Feature",
  "properties": {
    "iso:country":"IT",
    "sg:address":"74100 Taranto",
    "sg:city":"Taranto",
    "sg:orig_category":"Servizi Editoriali. Servizi Per Aziende, Manifestazioni E Supporto Agli Scambi Commerciali",
    "sg:phone":"+39 099 455 3111",
    "sg:postcode":"74100",
    "sg:province":"Taranto",
    "sg:website":"http://www.corgiorno.it",
    "wof:name":"Corriere Del Giorno Di Puglia E Lucania",
    "wof:placetype":"venue"
},
  "geometry": {"coordinates":[17.313931,40.503941],"type":"Point"}
}