{
  "type": "Feature",
  "properties": {
    "iso:country":"IT",
    "sg:address":"01027 Montefiascone",
    "sg:city":"Montefiascone",
    "sg:orig_category":"Prodotti E Manufatti In Materie Plastiche. Articoli Per Imballaggio E Confezionamento",
    "sg:phone":"+39 0761 827115",
    "sg:postcode":"01027",
    "sg:province":"Viterbo",
    "wof:name":"Manzi Aurelio S.r.l.",
    "wof:placetype":"venue"
},
  "geometry": {"coordinates":[12.0692949295,42.4815559387],"type":"Point"}
}