{
  "type": "Feature",
  "properties": {
    "iso:country":"IT",
    "sg:address":"230, Corso Valsesia 13045 Gattinara",
    "sg:city":"Gattinara",
    "sg:classifiers":[
        {
            "category":"Food & Beverages",
            "subcategory":"Groceries & Convenience Stores",
            "type":"Retail Goods"
        }
    ],
    "sg:phone":"+39 0163 826135",
    "sg:postcode":"13045",
    "sg:province":"Vercelli",
    "sg:tags":[
        "drink"
    ],
    "wof:name":"Casa Vinicola Bellavita Srl",
    "wof:placetype":"venue"
},
  "geometry": {"coordinates":[8.37151,45.62521],"type":"Point"}
}