{
  "type": "Feature",
  "properties": {
    "iso:country":"IT",
    "sg:address":"1/a, Via Quattro Piccoli Martiri 25040 Cividate Camuno",
    "sg:city":"Cividate Camuno",
    "sg:classifiers":[
        {
            "category":"Shopping",
            "subcategory":"Computers & Home Electronics",
            "type":"Retail Goods"
        }
    ],
    "sg:phone":"+39 036 434 1113",
    "sg:postcode":"25040",
    "sg:province":"Brescia",
    "sg:tags":[
        "electronic",
        "electrical",
        "equipment"
    ],
    "wof:name":"Esea 2g Sistemi Ed Automazione Elettrica Di Gheza Luigi E C",
    "wof:placetype":"venue"
},
  "geometry": {"coordinates":[10.222958,45.539829],"type":"Point"}
}