{
  "type": "Feature",
  "properties": {
    "addr:full":"32100 Belluno Belluno Belluno 32100",
    "addr:postcode":"32100;32100",
    "iso:country":"IT",
    "sg:address":"32100 Belluno",
    "sg:city":"Belluno",
    "sg:orig_category":"Ferramenta - Produzione",
    "sg:phone":"+39 0437 930866",
    "sg:postcode":"32100",
    "sg:province":"Belluno",
    "wof:name":"Bortoluzzi Sistemi Srl",
    "wof:placetype":"venue"
},
  "geometry": {"coordinates":[12.2552871704,46.1715431213],"type":"Point"}
}