{
  "type": "Feature",
  "properties": {
    "iso:country":"IT",
    "sg:address":"90129 Palermo",
    "sg:city":"Palermo",
    "sg:orig_category":"Forniture Per Agricoltura E Zootecnia. Prodotti Chimici Secondari. Macchine E Forniture Per Ecologia E Smaltimento Rifiuti",
    "sg:phone":"+39 091 426137",
    "sg:postcode":"90129",
    "sg:province":"Palermo",
    "wof:name":"Aviagricola",
    "wof:placetype":"venue"
},
  "geometry": {"coordinates":[13.3397712708,38.1068725586],"type":"Point"}
}