{
  "type": "Feature",
  "properties": {
    "iso:country":"IT",
    "sg:address":"Via Dei Fiori 8c-meledo 36040 Sarego",
    "sg:city":"Meledo",
    "sg:classifiers":[
        {
            "category":"Wholesale",
            "subcategory":"Plants",
            "type":"Manufacturing & Wholesale Goods"
        }
    ],
    "sg:phone":"+39 0444 820788",
    "sg:postcode":"36040",
    "sg:province":"Vicenza",
    "sg:tags":[
        "machine",
        "industrial",
        "automation"
    ],
    "sg:website":"www.aei-srl.com",
    "wof:name":"Aei Srl",
    "wof:placetype":"venue"
},
  "geometry": {"coordinates":[11.412645,45.436344],"type":"Point"}
}