{
  "type": "Feature",
  "properties": {
    "iso:country":"IT",
    "sg:address":"31032 Casale Sul Sile",
    "sg:city":"Casale sul Sile",
    "sg:orig_category":"Imprese Edili",
    "sg:phone":"+39 0422 821513",
    "sg:postcode":"31032",
    "sg:province":"Treviso",
    "wof:name":"R.d. Intonaci Snc Di Casadei Radames & C.",
    "wof:placetype":"venue"
},
  "geometry": {"coordinates":[12.313213,45.632111],"type":"Point"}
}