{
  "type": "Feature",
  "properties": {
    "iso:country":"IT",
    "sg:address":"27010 Valle Salimbene",
    "sg:city":"Valle Salimbene",
    "sg:orig_category":"Isolanti Termici Ed Acustici - Produzione",
    "sg:phone":"+39 0382 485068",
    "sg:postcode":"27010",
    "sg:province":"Pavia",
    "wof:name":"Fratelli Maestri Sdf",
    "wof:placetype":"venue"
},
  "geometry": {"coordinates":[9.226804,45.172558],"type":"Point"}
}