{
  "type": "Feature",
  "properties": {
    "addr:full":"26100 Cremona Cremona Cremona 26100",
    "addr:postcode":"26100;26100",
    "iso:country":"IT",
    "sg:address":"26100 Cremona",
    "sg:city":"Cremona",
    "sg:orig_category":"Pelletterie - Vendita Al Dettaglio",
    "sg:phone":"+39 0372 22593",
    "sg:postcode":"26100",
    "sg:province":"Cremona",
    "wof:name":"Stanga Fratelli Snc",
    "wof:placetype":"venue"
},
  "geometry": {"coordinates":[10.0325498581,45.1404190063],"type":"Point"}
}