{
  "type": "Feature",
  "properties": {
    "addr:full":"00151 Roma Roma Roma 00151",
    "addr:postcode":"00151;00151",
    "iso:country":"IT",
    "sg:address":"00151 Roma",
    "sg:city":"Roma",
    "sg:orig_category":"Amianto - Bonifica E Smantellamento",
    "sg:phone":"+39 06 532 7031",
    "sg:postcode":"00151",
    "sg:province":"Roma",
    "sg:website":"http://www.igeam.it",
    "wof:name":"Igeam Srl Servizi E Studi Per Lo Sviluppo Sostenibile",
    "wof:placetype":"venue"
},
  "geometry": {"coordinates":[12.445526,41.8713],"type":"Point"}
}