{
  "type": "Feature",
  "properties": {
    "iso:country":"IT",
    "sg:address":"44, Via Marconi 31055 Quinto Di Treviso",
    "sg:city":"Quinto di Treviso",
    "sg:classifiers":[
        {
            "category":"Manufacturing",
            "subcategory":"Lumber",
            "type":"Manufacturing & Wholesale Goods"
        }
    ],
    "sg:phone":"+39 0422 378826",
    "sg:postcode":"31055",
    "sg:province":"Treviso",
    "sg:tags":[
        "wood"
    ],
    "wof:name":"Eurokart (s.r.l.)",
    "wof:placetype":"venue"
},
  "geometry": {"coordinates":[12.164129,45.635185],"type":"Point"}
}