{
  "type": "Feature",
  "properties": {
    "iso:country":"IT",
    "sg:address":"63039 San Benedetto Del Tronto",
    "sg:city":"San Benedetto del Tronto",
    "sg:orig_category":"Forniture Per Attivita' Commerciali Ed Artigianali. Pubblicita', Marketing E Comunicazione",
    "sg:phone":"+39 0735 757114",
    "sg:postcode":"63039",
    "sg:province":"Ascoli Piceno",
    "sg:website":"http://www.publisport.it",
    "wof:name":"Publisport Srl",
    "wof:placetype":"venue"
},
  "geometry": {"coordinates":[13.8738031387,42.929725647],"type":"Point"}
}