{
  "type": "Feature",
  "properties": {
    "addr:full":"35139 Padova Padova Padova 35139",
    "addr:postcode":"35139;35139",
    "iso:country":"IT",
    "sg:address":"35139 Padova",
    "sg:city":"Padova",
    "sg:orig_category":"Macchine Ed Impianti Per Edilizia E Lavori Pubblici",
    "sg:postcode":"35139",
    "sg:province":"Padova",
    "wof:name":"Bedeschi Inter Continental",
    "wof:placetype":"venue"
},
  "geometry": {"coordinates":[11.903307,45.324089],"type":"Point"}
}