{
  "type": "Feature",
  "properties": {
    "iso:country":"IT",
    "sg:address":"20127 Milano",
    "sg:city":"Milano",
    "sg:orig_category":"Cinematografia E Radiotelevisione. Cine-foto-ottica",
    "sg:phone":"+39 02 2611 6042",
    "sg:postcode":"20127",
    "sg:province":"Milano",
    "wof:name":"Medusa Film Spa",
    "wof:placetype":"venue"
},
  "geometry": {"coordinates":[9.211558,45.489887],"type":"Point"}
}