{
  "type": "Feature",
  "properties": {
    "addr:full":"00196 Roma Roma Roma 00196",
    "addr:postcode":"00196;00196",
    "iso:country":"IT",
    "sg:address":"00196 Roma",
    "sg:city":"Roma",
    "sg:classifiers":[
        {
            "category":"Health Services",
            "subcategory":"Health Practitioner",
            "type":"Services"
        }
    ],
    "sg:phone":"+39 06 361 1127",
    "sg:postcode":"00196",
    "sg:province":"Roma",
    "sg:tags":[
        "medici"
    ],
    "wof:name":"Di Girolamo Alberto",
    "wof:placetype":"venue"
},
  "geometry": {"coordinates":[12.48705,41.828243],"type":"Point"}
}