{
  "type": "Feature",
  "properties": {
    "iso:country":"IT",
    "sg:address":"10153 Torino",
    "sg:city":"Torino",
    "sg:orig_category":"Pubblica Amministrazione",
    "sg:phone":"+39 011 812 8448",
    "sg:postcode":"10153",
    "sg:province":"Torino",
    "wof:name":"I.a.l. =franco Gheddo=",
    "wof:placetype":"venue"
},
  "geometry": {"coordinates":[7.711209774,45.0698127747],"type":"Point"}
}