{
  "type": "Feature",
  "properties": {
    "iso:country":"IT",
    "sg:address":"66013 Chieti Scalo",
    "sg:orig_category":"Cartotecnica E Servizi. Forniture Per Uffici",
    "sg:phone":"+39 0871 564572",
    "sg:province":"CH",
    "wof:name":"G.b. Grafica",
    "wof:placetype":"venue"
},
  "geometry": {"coordinates":[-94.696716,38.736904],"type":"Point"}
}