{
  "type": "Feature",
  "properties": {
    "iso:country":"IT",
    "sg:address":"35028 Piove Di Sacco",
    "sg:city":"Piove di Sacco",
    "sg:classifiers":[
        {
            "category":"Arts & Performance",
            "subcategory":"Dance",
            "type":"Entertainment"
        }
    ],
    "sg:phone":"+39 049 584 0970",
    "sg:postcode":"35028",
    "sg:province":"Padova",
    "sg:tags":[
        "decorative",
        "craft",
        "objects",
        "furnishings",
        "artistic"
    ],
    "wof:name":"Medoacus Di Picin Ilaria",
    "wof:placetype":"venue"
},
  "geometry": {"coordinates":[12.032333374,45.2987937927],"type":"Point"}
}