{
  "type": "Feature",
  "properties": {
    "addr:full":"67068 Scurcola Marsicana L'Aquila 67068",
    "addr:postcode":"67068;l'aquila 67068",
    "iso:country":"IT",
    "sg:address":"67068 Scurcola Marsicana",
    "sg:orig_category":"Gasolio, Kerosene E Nafta",
    "sg:phone":"+39 0863 22980",
    "sg:postcode":"67068",
    "sg:province":"L'Aquila",
    "wof:name":"Lilli Petroli Spa",
    "wof:placetype":"venue"
},
  "geometry": {"coordinates":[13.347178,42.053238],"type":"Point"}
}