{
  "type": "Feature",
  "properties": {
    "iso:country":"IT",
    "sg:address":"20070 Vizzolo Predabissi",
    "sg:city":"Vizzolo Predabissi",
    "sg:orig_category":"Servizi E Lavori Per Abbigliamento E Pelletterie",
    "sg:phone":"+39 02 983 3338",
    "sg:postcode":"20070",
    "sg:province":"Milano",
    "wof:name":"E.b.e. Di Conca M. & C. (s.a.s.)",
    "wof:placetype":"venue"
},
  "geometry": {"coordinates":[9.329241,45.358791],"type":"Point"}
}