{
  "type": "Feature",
  "properties": {
    "iso:country":"IT",
    "sg:address":"17, Localita' La Fila 56037 Peccioli",
    "sg:city":"Peccioli",
    "sg:classifiers":[
        {
            "category":"Home & Garden",
            "subcategory":"Home Furnishings",
            "type":"Retail Goods"
        }
    ],
    "sg:phone":"+39 0587 606021",
    "sg:postcode":"56037",
    "sg:province":"Pisa",
    "sg:tags":[
        "household"
    ],
    "wof:name":"Granducato Arredi S.r.l.- Centralino",
    "wof:placetype":"venue"
},
  "geometry": {"coordinates":[10.396585,43.716137],"type":"Point"}
}