{
  "type": "Feature",
  "properties": {
    "addr:full":"Via Marconi 23; Borgo Tossignano; 40021 Borgo Tossignano Bologna 40021",
    "addr:housenumber":"23",
    "addr:postcode":"40021;40021",
    "addr:street":"Via Marconi;Tossignano",
    "iso:country":"IT",
    "sg:address":"Via Marconi 23; Borgo Tossignano; 40021",
    "sg:city":"Borgo Tossignano",
    "sg:classifiers":[
        {
            "category":"Banks & Credit Unions",
            "subcategory":"Bank",
            "type":"Services"
        }
    ],
    "sg:phone":"+39 0542 91116",
    "sg:postcode":"40021",
    "sg:province":"Bologna",
    "wof:name":"Cassa Di Risparmio Di Imola Spa",
    "wof:placetype":"venue"
},
  "geometry": {"coordinates":[11.58779,44.27747],"type":"Point"}
}