{
  "type": "Feature",
  "properties": {
    "iso:country":"IT",
    "sg:address":"103, V. Pilanuova 73048 Nard\u00f2",
    "sg:classifiers":[
        {
            "category":"Parking",
            "subcategory":"Lot",
            "type":"Transportation"
        }
    ],
    "sg:phone":"+39 0833 871329",
    "sg:postcode":"73048",
    "sg:province":"Lecce",
    "sg:tags":[
        "transport",
        "road"
    ],
    "sg:website":"http://www.paginegialle.it/lineaverdecroceverde",
    "wof:name":"Fiorentino Maurizio",
    "wof:placetype":"venue"
},
  "geometry": {"coordinates":[18.037788,40.177452],"type":"Point"}
}