{
  "type": "Feature",
  "properties": {
    "addr:full":"74100 Taranto Taranto Taranto 74100",
    "addr:postcode":"74100;74100",
    "iso:country":"IT",
    "sg:address":"74100 Taranto",
    "sg:city":"Taranto",
    "sg:orig_category":"Elettricita' Materiali - Ingrosso",
    "sg:phone":"+39 099 776 1769",
    "sg:postcode":"74100",
    "sg:province":"Taranto",
    "wof:name":"F.i.m.e.l. Srl",
    "wof:placetype":"venue"
},
  "geometry": {"coordinates":[17.259945,40.43541],"type":"Point"}
}