{
  "type": "Feature",
  "properties": {
    "addr:full":"Via Mazzini 68-70; Molinella; 40062 Molinella Bologna 40062",
    "addr:housenumber":"68-70",
    "addr:postcode":"40062;40062",
    "addr:street":"Via Mazzini",
    "iso:country":"IT",
    "sg:address":"Via Mazzini 68-70; Molinella; 40062",
    "sg:city":"Molinella",
    "sg:classifiers":[
        {
            "category":"Banks & Credit Unions",
            "subcategory":"Bank",
            "type":"Services"
        }
    ],
    "sg:phone":"+39 051 690 0230",
    "sg:postcode":"40062",
    "sg:province":"Bologna",
    "wof:name":"Rolo Banca 1473",
    "wof:placetype":"venue"
},
  "geometry": {"coordinates":[11.669083,44.620686],"type":"Point"}
}