{
  "type": "Feature",
  "properties": {
    "iso:country":"IT",
    "sg:address":"35015 Galliera Veneta",
    "sg:city":"Galliera Veneta",
    "sg:orig_category":"Elettrotecnica Industriale, Prodotti E Apparecchiature. Elettronica Industriale, Prodotti E Apparecchiature",
    "sg:phone":"+39 049 596 8980",
    "sg:postcode":"35015",
    "sg:province":"Padova",
    "wof:name":"C.s. Di Cecchin Sergio & C. (s.n.c.)",
    "wof:placetype":"venue"
},
  "geometry": {"coordinates":[11.828774,45.662857],"type":"Point"}
}