{
  "type": "Feature",
  "properties": {
    "iso:country":"IT",
    "sg:address":"25020 Flero",
    "sg:city":"Flero",
    "sg:orig_category":"Termotecnica E Riscaldamento, Apparecchiature E Servizi",
    "sg:phone":"+39 030 268 0900",
    "sg:postcode":"25020",
    "sg:province":"Brescia",
    "wof:name":"Compagnoni Franco",
    "wof:placetype":"venue"
},
  "geometry": {"coordinates":[10.182297,45.487247],"type":"Point"}
}