{
  "type": "Feature",
  "properties": {
    "iso:country":"IT",
    "sg:address":"56020 Montecalvoli",
    "sg:city":"Montecalvoli",
    "sg:orig_category":"Macchine Utensili E Impianti. Elettrotecnica Industriale, Prodotti E Apparecchiature",
    "sg:phone":"+39 0587 749037",
    "sg:postcode":"56020",
    "sg:province":"Pisa",
    "wof:name":"Pellitteri Gianluigi",
    "wof:placetype":"venue"
},
  "geometry": {"coordinates":[10.66464,43.684727],"type":"Point"}
}