{
  "type": "Feature",
  "properties": {
    "addr:full":"16158 Genova Genova Genova 16158",
    "addr:postcode":"16158;16158",
    "iso:country":"IT",
    "sg:address":"16158 Genova",
    "sg:city":"Genova",
    "sg:orig_category":"Servizi Ausiliari Dei Mezzi Di Trasporto. Servizi Ausiliari Per Il Trasporto. Acqua, Luce, Gas E Societa' Di Esercizio Pubblico",
    "sg:phone":"+39 010 613 5422",
    "sg:postcode":"16158",
    "sg:province":"Genova",
    "wof:name":"Autorita'portuale Di Genova",
    "wof:placetype":"venue"
},
  "geometry": {"coordinates":[8.693069,44.454037],"type":"Point"}
}