{
  "type": "Feature",
  "properties": {
    "iso:country":"IT",
    "sg:address":"00044 Frascati",
    "sg:city":"Frascati",
    "sg:orig_category":"Associazioni Ed Organismi Di Interesse Pubblico",
    "sg:phone":"+39 06 942 5252",
    "sg:postcode":"00044",
    "sg:province":"Roma",
    "wof:name":"Associazione Nazionale Bersaglieri Sez.ne Frascati",
    "wof:placetype":"venue"
},
  "geometry": {"coordinates":[12.684524,41.810772],"type":"Point"}
}