{
  "type": "Feature",
  "properties": {
    "iso:country":"IT",
    "sg:address":"15, Via Del Boscone 25014 Castenedolo",
    "sg:city":"Castenedolo",
    "sg:classifiers":[
        {
            "category":"Retail",
            "subcategory":"Animal Services",
            "type":"Services"
        }
    ],
    "sg:phone":"+39 030 273 9611",
    "sg:postcode":"25014",
    "sg:province":"Brescia",
    "sg:tags":[
        "breeding"
    ],
    "wof:name":"Vitasol Spa",
    "wof:placetype":"venue"
},
  "geometry": {"coordinates":[10.272513,45.4776],"type":"Point"}
}