{
  "type": "Feature",
  "properties": {
    "addr:full":"50144 Firenze Firenze Firenze 50144",
    "addr:postcode":"50144;50144",
    "iso:country":"IT",
    "sg:address":"50144 Firenze",
    "sg:city":"Firenze",
    "sg:classifiers":[
        {
            "category":"Professional",
            "subcategory":"Management & Consulting",
            "type":"Services"
        }
    ],
    "sg:phone":"+39 055 334046",
    "sg:postcode":"50144",
    "sg:province":"Firenze",
    "sg:tags":[
        "control",
        "information",
        "auxiliary",
        "consultant",
        "support",
        "-",
        "analysis",
        "automation",
        "companies",
        "services",
        "events",
        "research",
        "technology",
        "trade",
        "machines"
    ],
    "wof:name":"Microware Srl",
    "wof:placetype":"venue"
},
  "geometry": {"coordinates":[11.234336,43.783779],"type":"Point"}
}