{
  "type": "Feature",
  "properties": {
    "iso:country":"IT",
    "sg:address":"31038 Paese",
    "sg:city":"Castagnole",
    "sg:orig_category":"Carta E Cartone - Produzione E Commercio",
    "sg:phone":"+39 0422 431130",
    "sg:postcode":"31038",
    "sg:province":"Treviso",
    "wof:name":"Dalla Giustina G. & C. Sas",
    "wof:placetype":"venue"
},
  "geometry": {"coordinates":[12.193121,45.690788],"type":"Point"}
}