{
  "type": "Feature",
  "properties": {
    "iso:country":"IT",
    "sg:address":"Contrada Carone 98054 Furnari",
    "sg:city":"Furnari",
    "sg:classifiers":[
        {
            "category":"Building & Trades",
            "subcategory":"Construction",
            "type":"Services"
        }
    ],
    "sg:phone":"+39 0941 802026",
    "sg:postcode":"98054",
    "sg:province":"Messina",
    "sg:tags":[
        "work",
        "public"
    ],
    "wof:name":"Ventura S.p.a.",
    "wof:placetype":"venue"
},
  "geometry": {"coordinates":[15.09998,38.111664],"type":"Point"}
}