{
  "type": "Feature",
  "properties": {
    "addr:full":"Via Mercurino; Vercello; 13100 Vercelli 13100",
    "addr:postcode":"13100;13100",
    "addr:street":"Via Mercurino Vercello",
    "iso:country":"IT",
    "sg:address":"Via Mercurino; Vercello; 13100",
    "sg:classifiers":[
        {
            "category":"Banks & Credit Unions",
            "subcategory":"Bank",
            "type":"Services"
        }
    ],
    "sg:phone":"+39 0161 5991",
    "sg:postcode":"13100",
    "sg:province":"Vercelli",
    "wof:name":"Banca Nazionale Del Lavoro Spa",
    "wof:placetype":"venue"
},
  "geometry": {"coordinates":[8.420221,45.32505],"type":"Point"}
}