{
  "type": "Feature",
  "properties": {
    "iso:country":"IT",
    "sg:address":"00010 Roma",
    "sg:orig_category":"Servizi E Lavori Per Arredamento E Industria Del Legno",
    "sg:phone":"+39 06 226 1740",
    "sg:postcode":"00010",
    "sg:province":"Roma",
    "wof:name":"Orlandi Sergio E Attilio Sdf",
    "wof:placetype":"venue"
},
  "geometry": {"coordinates":[12.679595,41.895809],"type":"Point"}
}