{
  "type": "Feature",
  "properties": {
    "iso:country":"IT",
    "sg:address":"Via Rosenthal 5 20089 Rozzano",
    "sg:city":"Rozzano",
    "sg:classifiers":[
        {
            "category":"Government",
            "subcategory":"Fire Station",
            "type":"Public Place"
        }
    ],
    "sg:phone":"+39 02 892131",
    "sg:postcode":"20089",
    "sg:province":"Milano",
    "sg:tags":[
        "alloy",
        "light",
        "aluminium",
        "processing"
    ],
    "wof:name":"Becromal Spa",
    "wof:placetype":"venue"
},
  "geometry": {"coordinates":[9.168765,45.387623],"type":"Point"}
}