{
  "type": "Feature",
  "properties": {
    "addr:full":"44, Via Colline 56038 Ponsacco Ponsacco Pisa 56038",
    "addr:postcode":"56038;56038",
    "addr:street":"Via Colline",
    "iso:country":"IT",
    "sg:address":"44, Via Colline 56038 Ponsacco",
    "sg:city":"Ponsacco",
    "sg:classifiers":[
        {
            "category":"Home & Garden",
            "subcategory":"Home Furnishings",
            "type":"Retail Goods"
        }
    ],
    "sg:phone":"+39 0587 475195",
    "sg:postcode":"56038",
    "sg:province":"Pisa",
    "sg:tags":[
        "household"
    ],
    "wof:name":"Nuova Ursus 2000 (s.r.l.)",
    "wof:placetype":"venue"
},
  "geometry": {"coordinates":[10.64995,43.642166],"type":"Point"}
}