{
  "type": "Feature",
  "properties": {
    "addr:full":"20146 Milano Milano Milano 20146",
    "addr:postcode":"20146;20146",
    "iso:country":"IT",
    "sg:address":"20146 Milano",
    "sg:city":"Milano",
    "sg:classifiers":[
        {
            "category":"Health Services",
            "subcategory":"Health Practitioner",
            "type":"Services"
        }
    ],
    "sg:phone":"+39 02 423 1797",
    "sg:postcode":"20146",
    "sg:province":"Milano",
    "sg:tags":[
        "medici"
    ],
    "wof:name":"Goglio Renato",
    "wof:placetype":"venue"
},
  "geometry": {"coordinates":[9.14755,45.45834],"type":"Point"}
}