{
  "type": "Feature",
  "properties": {
    "iso:country":"IT",
    "sg:address":"Loc Centrale Pontetto Ro 3/5 28864 Montecrestese",
    "sg:city":"Montecrestese",
    "sg:classifiers":[
        {
            "category":"Home & Garden",
            "subcategory":"Building Materials",
            "type":"Retail Goods"
        }
    ],
    "sg:phone":"+39 0324 35281",
    "sg:postcode":"28864",
    "sg:province":"Verbano-Cusio-Ossola",
    "sg:tags":[
        "granite",
        "syenite"
    ],
    "wof:name":"Nuova Isorno Graniti Srl",
    "wof:placetype":"venue"
},
  "geometry": {"coordinates":[8.272465,46.139969],"type":"Point"}
}