{
  "type": "Feature",
  "properties": {
    "addr:full":"Via Del Lavoro Artigiano, 7/9 25032 Chiari Chiari Brescia 25032",
    "addr:housenumber":"7 / 9",
    "addr:postcode":"25032;25032",
    "addr:street":"Via Del Lavoro Artigiano",
    "iso:country":"IT",
    "sg:address":"Via Del Lavoro Artigiano, 7/9 25032 Chiari",
    "sg:city":"Chiari",
    "sg:classifiers":[
        {
            "category":"Wholesale",
            "subcategory":"Vending Machines",
            "type":"Manufacturing & Wholesale Goods"
        }
    ],
    "sg:phone":"+39 030 700 0761",
    "sg:postcode":"25032",
    "sg:province":"Brescia",
    "sg:tags":[
        "packing",
        "baked",
        "pastry"
    ],
    "sg:website":"www.colimatic.it",
    "wof:name":"Colimatic Srl",
    "wof:placetype":"venue"
},
  "geometry": {"coordinates":[9.9156522751,45.5322990417],"type":"Point"}
}