{
  "type": "Feature",
  "properties": {
    "addr:full":"60021 Camerano Aspio Terme Ancona 60021",
    "addr:postcode":"60021;60021",
    "iso:country":"IT",
    "sg:address":"60021 Camerano",
    "sg:city":"Aspio Terme",
    "sg:orig_category":"Pubblicita' - Consulenza E Servizi",
    "sg:phone":"+39 071 730 4164",
    "sg:postcode":"60021",
    "sg:province":"Ancona",
    "sg:website":"http://www.skantinato.it",
    "wof:name":"Skantinato Snc",
    "wof:placetype":"venue"
},
  "geometry": {"coordinates":[13.5209589005,43.5263557434],"type":"Point"}
}