{
  "type": "Feature",
  "properties": {
    "iso:country":"IT",
    "sg:address":"20090 Opera",
    "sg:city":"Opera",
    "sg:orig_category":"Materiali Semilavorati Metallici",
    "sg:phone":"+39 02 5760 2675",
    "sg:postcode":"20090",
    "sg:province":"Milano",
    "wof:name":"Stainless Steel International Tubes S.p.a.",
    "wof:placetype":"venue"
},
  "geometry": {"coordinates":[9.195628,45.370373],"type":"Point"}
}