{
  "type": "Feature",
  "properties": {
    "iso:country":"IT",
    "sg:address":"95040 Ramacca",
    "sg:city":"Ramacca",
    "sg:orig_category":"Alberghi E Strutture Extra Alberghiere. Ospedali E Servizi Sanitari",
    "sg:phone":"+39 095 653856",
    "sg:postcode":"95040",
    "sg:province":"Catania",
    "wof:name":"Istituto Sacro Cuore",
    "wof:placetype":"venue"
},
  "geometry": {"coordinates":[15.113025,37.73761],"type":"Point"}
}