{
  "type": "Feature",
  "properties": {
    "iso:country":"IT",
    "sg:address":"Via Nigaiola 1/a, 38021 Brez, Tn",
    "sg:city":"Brez",
    "sg:classifiers":[
        {
            "category":"Banks & Credit Unions",
            "subcategory":"Bank",
            "type":"Services"
        }
    ],
    "sg:postcode":"38021",
    "sg:province":"Trento",
    "wof:name":"Cassa Rurale Di Brez-banca Di Credito Coop-scarl",
    "wof:placetype":"venue"
},
  "geometry": {"coordinates":[11.119053,46.066738],"type":"Point"}
}