{
  "type": "Feature",
  "properties": {
    "iso:country":"IT",
    "sg:address":"68, V. Marinaro 80025 Casandrino",
    "sg:city":"Casandrino",
    "sg:classifiers":[
        {
            "category":"Personal",
            "subcategory":"Shoe Repair & Shine",
            "type":"Services"
        }
    ],
    "sg:phone":"+39 081 395 3100",
    "sg:postcode":"80025",
    "sg:province":"Napoli",
    "sg:tags":[
        "leather"
    ],
    "sg:website":"http://www.ritaeliseo.it:ws_end: :mark:ws:http://www.paginegialle.it/calzaturificioeliseo",
    "wof:name":"Calzaturificio Eliseo Srl",
    "wof:placetype":"venue"
},
  "geometry": {"coordinates":[14.252418,40.923748],"type":"Point"}
}