{
  "type": "Feature",
  "properties": {
    "addr:full":"50053 Empoli Empoli Firenze 50053",
    "addr:postcode":"50053;50053",
    "iso:country":"IT",
    "sg:address":"50053 Empoli",
    "sg:city":"Empoli",
    "sg:orig_category":"Medici Specialisti - Andrologia",
    "sg:phone":"+39 0571 73922",
    "sg:postcode":"50053",
    "sg:province":"Firenze",
    "wof:name":"Giorgi Paolo Michele",
    "wof:placetype":"venue"
},
  "geometry": {"coordinates":[11.186373,43.751163],"type":"Point"}
}