{
  "type": "Feature",
  "properties": {
    "iso:country":"IT",
    "sg:address":"89, Via Tecchio 36075 Montecchio Maggiore",
    "sg:city":"Montecchio Maggiore",
    "sg:classifiers":[
        {
            "category":"Shopping",
            "subcategory":"Computers & Home Electronics",
            "type":"Retail Goods"
        }
    ],
    "sg:phone":"+39 0444 490515",
    "sg:postcode":"36075",
    "sg:province":"Vicenza",
    "sg:tags":[
        "electronic",
        "electrical",
        "equipment"
    ],
    "wof:name":"Sumoto (s.r.l.)",
    "wof:placetype":"venue"
},
  "geometry": {"coordinates":[11.427153,45.502018],"type":"Point"}
}