{
  "type": "Feature",
  "properties": {
    "addr:full":"71100 Foggia Foggia Foggia 71100",
    "addr:postcode":"71100;71100",
    "iso:country":"IT",
    "sg:address":"71100 Foggia",
    "sg:city":"Foggia",
    "sg:orig_category":"Pubblicita', Marketing E Comunicazione",
    "sg:phone":"+39 0881 653043",
    "sg:postcode":"71100",
    "sg:province":"Foggia",
    "wof:name":"Gipp Srl Promozioni & Marketing",
    "wof:placetype":"venue"
},
  "geometry": {"coordinates":[15.5474376678,41.4497947693],"type":"Point"}
}