{
  "type": "Feature",
  "properties": {
    "iso:country":"IT",
    "sg:address":"21100 Varese",
    "sg:city":"Varese",
    "sg:orig_category":"Gioielleria, Oreficeria E Argenteria. Shopping",
    "sg:phone":"+39 0332 238006",
    "sg:postcode":"21100",
    "sg:province":"Varese",
    "wof:name":"Corti Gioielli",
    "wof:placetype":"venue"
},
  "geometry": {"coordinates":[8.747584,45.908314],"type":"Point"}
}