{
  "type": "Feature",
  "properties": {
    "addr:full":"18, Via S. Caterina Da Siena 20011 Corbetta Corbetta Milano 20011",
    "addr:postcode":"20011;20011",
    "addr:street":"Via S. Caterina Da Siena",
    "iso:country":"IT",
    "sg:address":"18, Via S. Caterina Da Siena 20011 Corbetta",
    "sg:city":"Corbetta",
    "sg:classifiers":[
        {
            "category":"Shopping",
            "type":"Retail Goods"
        }
    ],
    "sg:phone":"+39 02 9727 1259",
    "sg:postcode":"20011",
    "sg:province":"Milano",
    "sg:tags":[
        "finished",
        "-",
        "metallic"
    ],
    "wof:name":"Geater Srl",
    "wof:placetype":"venue"
},
  "geometry": {"coordinates":[9.1881408691,45.4636878967],"type":"Point"}
}