{
  "type": "Feature",
  "properties": {
    "iso:country":"IT",
    "sg:address":"57, Via Teodosio 20131 Milano",
    "sg:city":"Milano",
    "sg:classifiers":[
        {
            "category":"Manufacturing",
            "subcategory":"Rubber & Plastics",
            "type":"Manufacturing & Wholesale Goods"
        }
    ],
    "sg:phone":"+39 39022828384",
    "sg:postcode":"20131",
    "sg:province":"Milano",
    "wof:name":"La Politecnica (s.r.l.)",
    "wof:placetype":"venue"
},
  "geometry": {"coordinates":[9.2298793793,45.4863929749],"type":"Point"}
}