{
  "type": "Feature",
  "properties": {
    "addr:full":"20099 Sesto San Giovanni Sesto San Giovanni Milano 20099",
    "addr:postcode":"20099;20099",
    "iso:country":"IT",
    "sg:address":"20099 Sesto San Giovanni",
    "sg:city":"Sesto San Giovanni",
    "sg:orig_category":"Trasporto Pubblico E Privato",
    "sg:phone":"+39 02 242 1989",
    "sg:postcode":"20099",
    "sg:province":"Milano",
    "wof:name":"Taxi",
    "wof:placetype":"venue"
},
  "geometry": {"coordinates":[9.238544,45.541405],"type":"Point"}
}