{
  "type": "Feature",
  "properties": {
    "iso:country":"IT",
    "sg:address":"09010 Pula",
    "sg:city":"Pula",
    "sg:classifiers":[
        {
            "category":"Health Services",
            "subcategory":"Health Practitioner",
            "type":"Services"
        }
    ],
    "sg:phone":"+39 070 924 5673",
    "sg:postcode":"09010",
    "sg:province":"Cagliari",
    "sg:tags":[
        "medici"
    ],
    "wof:name":"Studio Medico Diagnostico Dei Dottori Tuveri Cabasino E Granese",
    "wof:placetype":"venue"
},
  "geometry": {"coordinates":[9.117770195,39.2171134949],"type":"Point"}
}