{
  "type": "Feature",
  "properties": {
    "addr:full":"20024 Garbagnate Milanese Garbagnate Milanese Milano 20024",
    "addr:postcode":"20024;20024",
    "iso:country":"IT",
    "sg:address":"20024 Garbagnate Milanese",
    "sg:city":"Garbagnate Milanese",
    "sg:orig_category":"Elettrotecnica Industriale, Prodotti E Apparecchiature",
    "sg:phone":"+39 02 995111",
    "sg:postcode":"20024",
    "sg:province":"Milano",
    "sg:website":"http://www.elettrogarben.it",
    "wof:name":"Elettrogarben Srl",
    "wof:placetype":"venue"
},
  "geometry": {"coordinates":[9.086569,45.580948],"type":"Point"}
}