{
  "type": "Feature",
  "properties": {
    "iso:country":"IT",
    "sg:address":"Via Vittorio Veneto 16a, 20124 Milan, Mi",
    "sg:classifiers":[
        {
            "category":"Banks & Credit Unions",
            "subcategory":"Bank",
            "type":"Services"
        }
    ],
    "sg:postcode":"20124",
    "sg:province":"Milano",
    "wof:name":"Bnl Fondi Immobiliari Sgrpa",
    "wof:placetype":"venue"
},
  "geometry": {"coordinates":[9.201837,45.476246],"type":"Point"}
}