{
  "type": "Feature",
  "properties": {
    "iso:country":"IT",
    "sg:address":"20127 Milano",
    "sg:city":"Milano",
    "sg:orig_category":"Servizi E Lavori Per Abbigliamento E Pelletterie",
    "sg:phone":"+39 02 257 4027",
    "sg:postcode":"20127",
    "sg:province":"Milano",
    "wof:name":"La Milano",
    "wof:placetype":"venue"
},
  "geometry": {"coordinates":[9.222985,45.506668],"type":"Point"}
}