{
  "type": "Feature",
  "properties": {
    "addr:full":"20092 Cinisello Balsamo Cinisello Balsamo Milano 20092",
    "addr:postcode":"20092;20092",
    "iso:country":"IT",
    "sg:address":"20092 Cinisello Balsamo",
    "sg:city":"Cinisello Balsamo",
    "sg:orig_category":"Prodotti Finiti Stampati. Forniture Per Attivita' Commerciali Ed Artigianali",
    "sg:phone":"+39 02 6601 5651",
    "sg:postcode":"20092",
    "sg:province":"Milano",
    "wof:name":"N. Cibitek Di Cavallini Paolo E Brambilla Marco (s.n.c.)",
    "wof:placetype":"venue"
},
  "geometry": {"coordinates":[9.2144804001,45.5600013733],"type":"Point"}
}