{
  "type": "Feature",
  "properties": {
    "addr:full":"25020 Capriano Del Colle Capriano del Colle Brescia 25020",
    "addr:postcode":"25020;25020",
    "addr:street":"Del Colle",
    "iso:country":"IT",
    "sg:address":"25020 Capriano Del Colle",
    "sg:city":"Capriano del Colle",
    "sg:orig_category":"Forniture Per Agricoltura E Zootecnia. Prodotti Chimici Secondari",
    "sg:phone":"+39 030 974 8890",
    "sg:postcode":"25020",
    "sg:province":"Brescia",
    "wof:name":"Gaspari Ezio",
    "wof:placetype":"venue"
},
  "geometry": {"coordinates":[10.1355628967,45.4529838562],"type":"Point"}
}