{
  "type": "Feature",
  "properties": {
    "addr:full":"Via Cino Da Pistoia 24 59013 Montemurlo Montemurlo Prato 59013",
    "addr:housenumber":"24",
    "addr:postcode":"59013;59013",
    "addr:street":"Via Cino Da Pistoia",
    "iso:country":"IT",
    "sg:address":"Via Cino Da Pistoia 24 59013 Montemurlo",
    "sg:city":"Montemurlo",
    "sg:classifiers":[
        {
            "category":"Manufacturing",
            "subcategory":"Textiles",
            "type":"Manufacturing & Wholesale Goods"
        }
    ],
    "sg:phone":"+39 0574 720488",
    "sg:postcode":"59013",
    "sg:province":"Prato",
    "sg:tags":[
        "woollen",
        "fabric"
    ],
    "wof:name":"Stemar S.r.l.",
    "wof:placetype":"venue"
},
  "geometry": {"coordinates":[11.063458,43.9077],"type":"Point"}
}