{
  "type": "Feature",
  "properties": {
    "iso:country":"IT",
    "sg:address":"20146 Milano",
    "sg:city":"Milano",
    "sg:orig_category":"Servizi Culturali E Per Lo Spettacolo. Servizi Per Lo Sport E Il Tempo Libero. Associazioni Ed Organismi Di Interesse Pubblico",
    "sg:phone":"+39 02 437110",
    "sg:postcode":"20146",
    "sg:province":"Milano",
    "wof:name":"Moto Club",
    "wof:placetype":"venue"
},
  "geometry": {"coordinates":[9.15502,45.461857],"type":"Point"}
}