{
  "type": "Feature",
  "properties": {
    "addr:full":"Via San Giuseppe 20 30015 Chioggia Chioggia Venezia 30015",
    "addr:housenumber":"20",
    "addr:postcode":"30015;30015",
    "addr:street":"Via San Giuseppe",
    "iso:country":"IT",
    "sg:address":"Via San Giuseppe 20 30015 Chioggia",
    "sg:city":"Chioggia",
    "sg:classifiers":[
        {
            "category":"Food & Beverages",
            "subcategory":"Fruits & Vegetables",
            "type":"Retail Goods"
        }
    ],
    "sg:phone":"+39 041 498161",
    "sg:postcode":"30015",
    "sg:province":"Venezia",
    "sg:website":"www.fasiolo.it",
    "wof:name":"Fasiolo S.n.c. Di Tiozzo Mirko",
    "wof:placetype":"venue"
},
  "geometry": {"coordinates":[12.2992391586,45.1604766846],"type":"Point"}
}