{
  "type": "Feature",
  "properties": {
    "addr:full":"Via Postumia 11 35010 Carmignano Di Brenta Carmignano di Brenta Padova 35010",
    "addr:housenumber":"11",
    "addr:postcode":"35010;35010",
    "addr:street":"Via Postumia;Di Brenta",
    "iso:country":"IT",
    "sg:address":"Via Postumia 11 35010 Carmignano Di Brenta",
    "sg:city":"Carmignano di Brenta",
    "sg:classifiers":[
        {
            "category":"Manufacturing",
            "subcategory":"Rubber & Plastics",
            "type":"Manufacturing & Wholesale Goods"
        }
    ],
    "sg:phone":"+39 049 595 7196",
    "sg:postcode":"35010",
    "sg:province":"Padova",
    "sg:tags":[
        "material"
    ],
    "sg:website":"www.plastitex.com",
    "wof:name":"Plastitex Spa",
    "wof:placetype":"venue"
},
  "geometry": {"coordinates":[11.6985282898,45.6154556274],"type":"Point"}
}