{
  "type": "Feature",
  "properties": {
    "iso:country":"IT",
    "sg:address":"2, Via Ghirlandaio 20096 Pioltello",
    "sg:city":"Pioltello",
    "sg:classifiers":[
        {
            "category":"Shopping",
            "type":"Retail Goods"
        }
    ],
    "sg:phone":"+39 02 9210 3801",
    "sg:postcode":"20096",
    "sg:province":"Milano",
    "sg:tags":[
        "finished",
        "-",
        "metallic"
    ],
    "wof:name":"Galassi & Ortolani S.p.a.",
    "wof:placetype":"venue"
},
  "geometry": {"coordinates":[9.3326826096,45.509021759],"type":"Point"}
}