{
  "type": "Feature",
  "properties": {
    "iso:country":"IT",
    "sg:address":"33084 Cordenons",
    "sg:city":"Cordenons",
    "sg:orig_category":"Amianto - Bonifica E Smantellamento",
    "sg:phone":"+39 0434 930058",
    "sg:postcode":"33084",
    "sg:province":"Pordenone",
    "wof:name":"De Marco Srl",
    "wof:placetype":"venue"
},
  "geometry": {"coordinates":[12.698204,45.987309],"type":"Point"}
}