{
  "type": "Feature",
  "properties": {
    "iso:country":"IT",
    "sg:address":"Via Torino 49 12084 Mondovi'",
    "sg:classifiers":[
        {
            "category":"Wholesale",
            "subcategory":"Vending Machines",
            "type":"Manufacturing & Wholesale Goods"
        }
    ],
    "sg:phone":"+39 0174 43159",
    "sg:postcode":"12084",
    "sg:province":"Cuneo",
    "sg:tags":[
        "carpentry"
    ],
    "sg:website":"www.omcm.net",
    "wof:name":"O.m.c.m. Snc",
    "wof:placetype":"venue"
},
  "geometry": {"coordinates":[7.591802,44.511032],"type":"Point"}
}