{
  "type": "Feature",
  "properties": {
    "iso:country":"IT",
    "sg:address":"10040 Leini'",
    "sg:classifiers":[
        {
            "category":"Health Services",
            "subcategory":"Health Practitioner",
            "type":"Services"
        }
    ],
    "sg:phone":"+39 011 997 4898",
    "sg:postcode":"10040",
    "sg:province":"Torino",
    "sg:tags":[
        "medici"
    ],
    "wof:name":"Bertino Giorgio",
    "wof:placetype":"venue"
},
  "geometry": {"coordinates":[7.772906,45.134319],"type":"Point"}
}