{
  "type": "Feature",
  "properties": {
    "iso:country":"IT",
    "sg:address":"90142 Palermo",
    "sg:city":"Palermo",
    "sg:orig_category":"Impiantistica E Prodotti Tecnologici Per Edilizia. Elettronica Professionale E Di Consumo",
    "sg:phone":"+39 091 548190",
    "sg:postcode":"90142",
    "sg:province":"Palermo",
    "wof:name":"Saf Impianti Di Provvidenza Busalacchi",
    "wof:placetype":"venue"
},
  "geometry": {"coordinates":[13.360489,38.135502],"type":"Point"}
}