{
  "type": "Feature",
  "properties": {
    "addr:full":"40012 Calderara Di Reno Calderara di Reno Bologna 40012",
    "addr:postcode":"40012;40012",
    "iso:country":"IT",
    "sg:address":"40012 Calderara Di Reno",
    "sg:city":"Calderara di Reno",
    "sg:orig_category":"Motori Ed Organi Di Trasmissione",
    "sg:phone":"+39 051 647 3111",
    "sg:postcode":"40012",
    "sg:province":"Bologna",
    "wof:name":"Bonfiglioli Riduttori S.p.a.",
    "wof:placetype":"venue"
},
  "geometry": {"coordinates":[11.3019390106,44.5375175476],"type":"Point"}
}