{
  "type": "Feature",
  "properties": {
    "addr:full":"509, C.i.s. Isola 5 Torre 5 80035 Nola Nola Napoli 80035",
    "addr:housenumber":"509;5;5",
    "addr:postcode":"80035;80035",
    "addr:street":"C.I.S. Isola",
    "iso:country":"IT",
    "sg:address":"509, C.i.s. Isola 5 Torre 5 80035 Nola",
    "sg:city":"Nola",
    "sg:orig_category":"Miscellaneous Products",
    "sg:phone":"+39 081 510 9233",
    "sg:postcode":"80035",
    "sg:province":"Napoli",
    "wof:name":"Spazio Italia Import-export Srl",
    "wof:placetype":"venue"
},
  "geometry": {"coordinates":[14.2516355515,40.84009552],"type":"Point"}
}