{
  "type": "Feature",
  "properties": {
    "iso:country":"IT",
    "sg:address":"87067 Rossano",
    "sg:city":"Rossano",
    "sg:orig_category":"Trasporti E Spedizioni Merci",
    "sg:phone":"+39 0983 64356",
    "sg:postcode":"87067",
    "sg:province":"Cosenza",
    "wof:name":"Antonio Straface Trasporti - Spedizioni Sas Di Lorenzo Straface & F.lli",
    "wof:placetype":"venue"
},
  "geometry": {"coordinates":[16.667814,39.604702],"type":"Point"}
}