{
  "type": "Feature",
  "properties": {
    "addr:full":"30172 Venezia Venezia Venezia 30172",
    "addr:postcode":"30172;30172",
    "iso:country":"IT",
    "sg:address":"30172 Venezia",
    "sg:city":"Venezia",
    "sg:orig_category":"Giornali, Libri E Riviste - Distribuzione E Diffusione",
    "sg:phone":"+39 041 531 5374",
    "sg:postcode":"30172",
    "sg:province":"Venezia",
    "wof:name":"Agenzia Distribuzione Giornali Di Bonfa' Gino & Sas",
    "wof:placetype":"venue"
},
  "geometry": {"coordinates":[12.242305,45.480576],"type":"Point"}
}