{
  "type": "Feature",
  "properties": {
    "iso:country":"IT",
    "sg:address":"20094 Corsico",
    "sg:city":"Corsico",
    "sg:orig_category":"Impianti, Attrezzature E Forniture Sanitarie Ed Ospedaliere",
    "sg:phone":"+39 02 450 3807",
    "sg:postcode":"20094",
    "sg:province":"Milano",
    "wof:name":"Leader Italia Srl",
    "wof:placetype":"venue"
},
  "geometry": {"coordinates":[9.105818,45.444828],"type":"Point"}
}