{
  "type": "Feature",
  "properties": {
    "iso:country":"IT",
    "sg:address":"11, Via Martiri Di Civitella 52100 Arezzo",
    "sg:city":"Arezzo",
    "sg:classifiers":[
        {
            "category":"Building & Trades",
            "subcategory":"Construction",
            "type":"Services"
        }
    ],
    "sg:phone":"+39 0575 333275",
    "sg:postcode":"52100",
    "sg:province":"Arezzo",
    "sg:tags":[
        "work",
        "public"
    ],
    "wof:name":"Sacies Srl",
    "wof:placetype":"venue"
},
  "geometry": {"coordinates":[11.722747,43.417797],"type":"Point"}
}