{
  "type": "Feature",
  "properties": {
    "iso:country":"IT",
    "sg:address":"41019 Soliera",
    "sg:city":"Soliera",
    "sg:orig_category":"Agenzie Ed Enti Turistici",
    "sg:phone":"+39 059 859814",
    "sg:postcode":"41019",
    "sg:province":"Modena",
    "sg:website":"http://www.tripcap.com",
    "wof:name":"Deserto Blu Srl",
    "wof:placetype":"venue"
},
  "geometry": {"coordinates":[10.912289,44.725574],"type":"Point"}
}