{
  "type": "Feature",
  "properties": {
    "iso:country":"IT",
    "sg:address":"83, Via Mure 31030 Altivole",
    "sg:city":"Altivole",
    "sg:classifiers":[
        {
            "category":"Manufacturing",
            "subcategory":"Rubber & Plastics",
            "type":"Manufacturing & Wholesale Goods"
        }
    ],
    "sg:phone":"+39 0423 569499",
    "sg:postcode":"31030",
    "sg:province":"Treviso",
    "wof:name":"Xero Wheels S.r.l.",
    "wof:placetype":"venue"
},
  "geometry": {"coordinates":[11.9752283096,45.7570648193],"type":"Point"}
}