{
  "type": "Feature",
  "properties": {
    "addr:full":"2, Via Madrid 24040 Zingonia Zingonia Bergamo 24040",
    "addr:postcode":"24040;24040",
    "addr:street":"Via Madrid",
    "iso:country":"IT",
    "sg:address":"2, Via Madrid 24040 Zingonia",
    "sg:city":"Zingonia",
    "sg:classifiers":[
        {
            "category":"Shopping",
            "subcategory":"Crafts & Fabrics",
            "type":"Retail Goods"
        }
    ],
    "sg:phone":"+39 39035883342",
    "sg:postcode":"24040",
    "sg:province":"Bergamo",
    "wof:name":"Maglificio Jems (snc)",
    "wof:placetype":"venue"
},
  "geometry": {"coordinates":[9.6136779785,45.5956878662],"type":"Point"}
}