{
  "type": "Feature",
  "properties": {
    "iso:country":"IT",
    "sg:address":"Str. Prov. Binasco-rosate Km 3 20088 Rosate",
    "sg:city":"Rosate",
    "sg:classifiers":[
        {
            "category":"Professional",
            "subcategory":"Employment Agencies",
            "type":"Services"
        }
    ],
    "sg:phone":"+39 02 905 4396",
    "sg:postcode":"20088",
    "sg:province":"Milano",
    "sg:tags":[
        "castor",
        "furniture"
    ],
    "wof:name":"Luigi Perego Srl",
    "wof:placetype":"venue"
},
  "geometry": {"coordinates":[9.188141,45.463688],"type":"Point"}
}