{
  "type": "Feature",
  "properties": {
    "addr:full":"95037 S. Giovanni La Punta Catania 95037",
    "addr:housenumber":"95037",
    "addr:postcode":"95037",
    "addr:street":"S. Giovanni La Punta",
    "iso:country":"IT",
    "sg:address":"95037 S. Giovanni La Punta",
    "sg:orig_category":"Agenzie Immobiliari",
    "sg:phone":"+39 095 791 4793",
    "sg:postcode":"95037",
    "sg:province":"Catania",
    "wof:name":"Azzurra Immobiliare",
    "wof:placetype":"venue"
},
  "geometry": {"coordinates":[15.087834,37.502483],"type":"Point"}
}