{
  "type": "Feature",
  "properties": {
    "iso:country":"IT",
    "sg:address":"00165 Roma",
    "sg:city":"Roma",
    "sg:orig_category":"Scuole E Servizi Scolastici. Alberghi E Strutture Extra Alberghiere",
    "sg:phone":"+39 06 660621",
    "sg:postcode":"00165",
    "sg:province":"Roma",
    "wof:name":"Pontificio Collegio Seminario Filippino",
    "wof:placetype":"venue"
},
  "geometry": {"coordinates":[12.42114,41.897114],"type":"Point"}
}