{
  "type": "Feature",
  "properties": {
    "addr:full":"70051 Barletta Barletta Bari 70051",
    "addr:postcode":"70051;70051",
    "iso:country":"IT",
    "sg:address":"70051 Barletta",
    "sg:city":"Barletta",
    "sg:orig_category":"Abbigliamento - Produzione E Ingrosso",
    "sg:phone":"+39 0883 510789",
    "sg:postcode":"70051",
    "sg:province":"Bari",
    "wof:name":"Confezioni Noisei Sas",
    "wof:placetype":"venue"
},
  "geometry": {"coordinates":[16.069635,41.304806],"type":"Point"}
}