{
  "type": "Feature",
  "properties": {
    "addr:full":"80053 Castellammare Di Stabia Castellammare di Stabia Napoli 80053",
    "addr:postcode":"80053;80053",
    "iso:country":"IT",
    "sg:address":"80053 Castellammare Di Stabia",
    "sg:city":"Castellammare di Stabia",
    "sg:orig_category":"Ospedali E Servizi Sanitari",
    "sg:phone":"+39 081 871 7917",
    "sg:postcode":"80053",
    "sg:province":"Napoli",
    "wof:name":"Odontotecnica Bonifacio Gaetano",
    "wof:placetype":"venue"
},
  "geometry": {"coordinates":[14.4898,40.698475],"type":"Point"}
}