{
  "type": "Feature",
  "properties": {
    "iso:country":"IT",
    "sg:address":"50032 Borgo San Lorenzo",
    "sg:city":"Borgo San Lorenzo",
    "sg:orig_category":"Lavorazioni Metalli, Stampaggio E Saldatura",
    "sg:phone":"+39 055 849 0270",
    "sg:postcode":"50032",
    "sg:province":"Firenze",
    "wof:name":"Fanti Franco",
    "wof:placetype":"venue"
},
  "geometry": {"coordinates":[11.415688,43.942974],"type":"Point"}
}