{
  "type": "Feature",
  "properties": {
    "iso:country":"IT",
    "sg:address":"Via Della Treccia 16/18 50145 Firenze",
    "sg:city":"Firenze",
    "sg:classifiers":[
        {
            "category":"Communications",
            "subcategory":"Film & Video Production",
            "type":"Services"
        }
    ],
    "sg:phone":"+39 055 317976",
    "sg:postcode":"50145",
    "sg:province":"Firenze",
    "sg:tags":[
        "projector"
    ],
    "sg:website":"www.cinemec.it",
    "wof:name":"Cinemec Snc",
    "wof:placetype":"venue"
},
  "geometry": {"coordinates":[11.1875019073,43.7995758057],"type":"Point"}
}