{
  "type": "Feature",
  "properties": {
    "addr:full":"25030 Torbole Casaglia Torbole Casaglia Brescia 25030",
    "addr:postcode":"25030;25030",
    "iso:country":"IT",
    "sg:address":"25030 Torbole Casaglia",
    "sg:city":"Torbole Casaglia",
    "sg:orig_category":"Macchine Utensili E Impianti",
    "sg:phone":"+39 030 215 0008",
    "sg:postcode":"25030",
    "sg:province":"Brescia",
    "wof:name":"Stp Presse Srl",
    "wof:placetype":"venue"
},
  "geometry": {"coordinates":[10.11486,45.523087],"type":"Point"}
}