{
  "type": "Feature",
  "properties": {
    "addr:full":"74100 Taranto Taranto Taranto 74100",
    "addr:postcode":"74100;74100",
    "iso:country":"IT",
    "sg:address":"74100 Taranto",
    "sg:city":"Taranto",
    "sg:orig_category":"Forniture Di Bordo E Navali",
    "sg:phone":"+39 099 459 0587",
    "sg:postcode":"74100",
    "sg:province":"Taranto",
    "wof:name":"International Shipchandler",
    "wof:placetype":"venue"
},
  "geometry": {"coordinates":[17.2387485504,40.473991394],"type":"Point"}
}