{
  "type": "Feature",
  "properties": {
    "iso:country":"IT",
    "sg:address":"36050 Sovizzo",
    "sg:city":"Sovizzo",
    "sg:orig_category":"Macchine, Impianti Ed Attrezzature Per Abbigliamento E Pelletterie. Macchine E Impianti Per Attivita' Commerciali Ed Artigianali",
    "sg:phone":"+39 0444 536366",
    "sg:postcode":"36050",
    "sg:province":"Vicenza",
    "wof:name":"S.b. Elettromeccanica",
    "wof:placetype":"venue"
},
  "geometry": {"coordinates":[11.451499,45.525288],"type":"Point"}
}