{
  "type": "Feature",
  "properties": {
    "iso:country":"IT",
    "sg:address":"Viale Moro 46/48; Como; 22100",
    "sg:city":"Como",
    "sg:classifiers":[
        {
            "category":"Banks & Credit Unions",
            "subcategory":"Bank",
            "type":"Services"
        }
    ],
    "sg:phone":"+39 031 267047",
    "sg:postcode":"22100",
    "sg:province":"Como",
    "wof:name":"Banca Populare Di Luino, E Di Varese",
    "wof:placetype":"venue"
},
  "geometry": {"coordinates":[9.090851,45.803833],"type":"Point"}
}