{
  "type": "Feature",
  "properties": {
    "addr:full":"95047 Patern\u00f2 Catania 95047",
    "addr:postcode":"95047;95047",
    "iso:country":"IT",
    "sg:address":"95047 Patern\u00f2",
    "sg:orig_category":"Assicurazioni",
    "sg:phone":"+39 095 623009",
    "sg:postcode":"95047",
    "sg:province":"Catania",
    "wof:name":"Assinicolosi Sas",
    "wof:placetype":"venue"
},
  "geometry": {"coordinates":[14.434147,37.577026],"type":"Point"}
}