{
  "type": "Feature",
  "properties": {
    "iso:country":"IT",
    "sg:address":"37129 Verona",
    "sg:city":"Verona",
    "sg:classifiers":[
        {
            "category":"Home & Garden",
            "subcategory":"Building Materials",
            "type":"Retail Goods"
        }
    ],
    "sg:phone":"+39 045 590133",
    "sg:postcode":"37129",
    "sg:province":"Verona",
    "sg:tags":[
        "window",
        "door",
        "frame"
    ],
    "wof:name":"Rancani Gianfranco",
    "wof:placetype":"venue"
},
  "geometry": {"coordinates":[11.005755,45.446079],"type":"Point"}
}