{
  "type": "Feature",
  "properties": {
    "iso:country":"IT",
    "sg:address":"03017 Morolo",
    "sg:city":"Morolo",
    "sg:orig_category":"Materiali Edili",
    "sg:phone":"+39 0775 229471",
    "sg:postcode":"03017",
    "sg:province":"Frosinone",
    "wof:name":"Colacem Spa",
    "wof:placetype":"venue"
},
  "geometry": {"coordinates":[13.18557,41.642426],"type":"Point"}
}