{
  "type": "Feature",
  "properties": {
    "iso:country":"IT",
    "sg:address":"9, Via Todi 21052 Busto Arsizio",
    "sg:city":"Busto Arsizio",
    "sg:classifiers":[
        {
            "category":"Shopping",
            "subcategory":"Crafts & Fabrics",
            "type":"Retail Goods"
        }
    ],
    "sg:phone":"+39 0331 677050",
    "sg:postcode":"21052",
    "sg:province":"Varese",
    "wof:name":"Nastritex Srl",
    "wof:placetype":"venue"
},
  "geometry": {"coordinates":[8.8746023178,45.6124610901],"type":"Point"}
}