{
  "type": "Feature",
  "properties": {
    "iso:country":"IT",
    "sg:address":"2, Piazza Lincoln Abramo 95128 Catania",
    "sg:city":"Catania",
    "sg:classifiers":[
        {
            "category":"Wholesale",
            "subcategory":"Medical Equipment & Supplies",
            "type":"Manufacturing & Wholesale Goods"
        }
    ],
    "sg:phone":"+39 39095505040",
    "sg:postcode":"95128",
    "sg:province":"Catania",
    "sg:tags":[
        "-",
        "health",
        "instrument"
    ],
    "wof:name":"Europtical Group Srl",
    "wof:placetype":"venue"
},
  "geometry": {"coordinates":[15.088569,37.521389],"type":"Point"}
}