{
  "type": "Feature",
  "properties": {
    "iso:country":"IT",
    "sg:address":"36061 Bassano Del Grappa",
    "sg:city":"Bassano del Grappa",
    "sg:orig_category":"Telecomunicazioni E Telefonia, Impianti, Apparecchi E Servizi. Automazione E Macchine Per Ufficio",
    "sg:phone":"+39 0424 32918",
    "sg:postcode":"36061",
    "sg:province":"Vicenza",
    "wof:name":"Pastega Elettronica Professionale (s.r.l.)",
    "wof:placetype":"venue"
},
  "geometry": {"coordinates":[11.7450685501,45.7716331482],"type":"Point"}
}