{
  "type": "Feature",
  "properties": {
    "iso:country":"IT",
    "sg:address":"10147 Torino",
    "sg:city":"Torino",
    "sg:classifiers":[
        {
            "category":"Home & Garden",
            "subcategory":"Building Materials",
            "type":"Retail Goods"
        }
    ],
    "sg:phone":"+39 011 257844",
    "sg:postcode":"10147",
    "sg:province":"Torino",
    "sg:tags":[
        "gas",
        "caldaie"
    ],
    "wof:name":"Vaiargas Eurogas Di Trentinella",
    "wof:placetype":"venue"
},
  "geometry": {"coordinates":[7.676065,45.093807],"type":"Point"}
}