{
  "type": "Feature",
  "properties": {
    "iso:country":"IT",
    "sg:address":"68, Via Delle Cateratte 57122 Livorno",
    "sg:city":"Livorno",
    "sg:classifiers":[
        {
            "category":"Farming",
            "subcategory":"Livestock Farm",
            "type":"Manufacturing & Wholesale Goods"
        }
    ],
    "sg:phone":"+39 0586 249999",
    "sg:postcode":"57122",
    "sg:province":"Livorno",
    "sg:tags":[
        "agriculture"
    ],
    "wof:name":"Cerealtoscana Spa",
    "wof:placetype":"venue"
},
  "geometry": {"coordinates":[10.312929,43.565918],"type":"Point"}
}