{
  "type": "Feature",
  "properties": {
    "addr:full":"41100 Modena Modena Modena 41100",
    "addr:postcode":"41100;41100",
    "iso:country":"IT",
    "sg:address":"41100 Modena",
    "sg:city":"Modena",
    "sg:orig_category":"Articoli Da Regalo. Forniture Per Attivita' Commerciali Ed Artigianali",
    "sg:phone":"+39 059 253705",
    "sg:postcode":"41100",
    "sg:province":"Modena",
    "wof:name":"Azienda Agricola Minutaria Sas",
    "wof:placetype":"venue"
},
  "geometry": {"coordinates":[10.976004,44.663414],"type":"Point"}
}