{
  "type": "Feature",
  "properties": {
    "iso:country":"IT",
    "sg:address":"154, Contrada Villa Tucci 66014 Crecchio",
    "sg:city":"Crecchio",
    "sg:classifiers":[
        {
            "category":"Farming",
            "subcategory":"Livestock Farm",
            "type":"Manufacturing & Wholesale Goods"
        }
    ],
    "sg:phone":"+39 0871 936268",
    "sg:postcode":"66014",
    "sg:province":"Chieti",
    "sg:tags":[
        "agriculture"
    ],
    "wof:name":"Societa' Cooperativa Agricola Villa Tucci",
    "wof:placetype":"venue"
},
  "geometry": {"coordinates":[14.330021,42.314262],"type":"Point"}
}