{
  "type": "Feature",
  "properties": {
    "iso:country":"IT",
    "sg:address":"41100 Modena",
    "sg:city":"Modena",
    "sg:orig_category":"Servizi E Lavori Per Agricoltura E Zootecnia. Servizi E Lavori Per Edilizia E Lavori Pubblici",
    "sg:phone":"+39 059 300199",
    "sg:postcode":"41100",
    "sg:province":"Modena",
    "sg:website":"http://www.happyflor.it",
    "wof:name":"Fertilcoop Soc.coop.r.l.",
    "wof:placetype":"venue"
},
  "geometry": {"coordinates":[10.914429,44.663944],"type":"Point"}
}