{
  "type": "Feature",
  "properties": {
    "iso:country":"IT",
    "sg:address":"25040 Sacca",
    "sg:city":"Sacca",
    "sg:orig_category":"Servizi Al Turismo. Trasporto Pubblico E Privato",
    "sg:phone":"+39 036 446387",
    "sg:postcode":"25040",
    "sg:province":"Brescia",
    "wof:name":"Eli - Fly (s.p.a.)",
    "wof:placetype":"venue"
},
  "geometry": {"coordinates":[10.226036,45.905872],"type":"Point"}
}