{
  "type": "Feature",
  "properties": {
    "iso:country":"IT",
    "sg:address":"Via Provinciale 69 13891 Camburzano",
    "sg:city":"Camburzano",
    "sg:classifiers":[
        {
            "category":"Retail",
            "subcategory":"Event Space",
            "type":"Services"
        }
    ],
    "sg:phone":"+39 015 591754",
    "sg:postcode":"13891",
    "sg:province":"Biella",
    "sg:tags":[
        "decorative",
        "ribbon"
    ],
    "wof:name":"I.n.a.b. Snc",
    "wof:placetype":"venue"
},
  "geometry": {"coordinates":[8.011469,45.534771],"type":"Point"}
}