{
  "type": "Feature",
  "properties": {
    "addr:full":"Corso Ara Di Giove, 115; Pedara; 95030 Pedara Catania 95030",
    "addr:housenumber":"115",
    "addr:postcode":"95030;95030",
    "addr:street":"Corso Ara Di Giove",
    "iso:country":"IT",
    "sg:address":"Corso Ara Di Giove, 115; Pedara; 95030",
    "sg:city":"Pedara",
    "sg:classifiers":[
        {
            "category":"Banks & Credit Unions",
            "subcategory":"Bank",
            "type":"Services"
        }
    ],
    "sg:phone":"+39 095 915583",
    "sg:postcode":"95030",
    "sg:province":"Catania",
    "wof:name":"Banca Popolare Di Catania",
    "wof:placetype":"venue"
},
  "geometry": {"coordinates":[15.060822,37.618313],"type":"Point"}
}