{
  "type": "Feature",
  "properties": {
    "iso:country":"IT",
    "sg:address":"10070 Fiano",
    "sg:city":"Fiano",
    "sg:orig_category":"Prodotti Alimentari",
    "sg:phone":"+39 011 925 4259",
    "sg:postcode":"10070",
    "sg:province":"Torino",
    "wof:name":"Fantolino Franco Azienda Agricola Di Gabriella Fantolino",
    "wof:placetype":"venue"
},
  "geometry": {"coordinates":[7.6598520279,45.0737075806],"type":"Point"}
}