{
  "type": "Feature",
  "properties": {
    "iso:country":"IT",
    "sg:address":"60030 Mergo",
    "sg:city":"Mergo",
    "sg:orig_category":"Arredo Cucina Ed Elettrodomestici. Climatizzazione E Condizionamento, Apparecchiature E Servizi",
    "sg:phone":"+39 0731 81771",
    "sg:postcode":"60030",
    "sg:province":"Ancona",
    "wof:name":"Elica S.p.a.",
    "wof:placetype":"venue"
},
  "geometry": {"coordinates":[13.051301,43.459427],"type":"Point"}
}