{
  "type": "Feature",
  "properties": {
    "addr:full":"24127 Bergamo Bergamo Bergamo 24127",
    "addr:postcode":"24127;24127",
    "iso:country":"IT",
    "sg:address":"24127 Bergamo",
    "sg:city":"Bergamo",
    "sg:orig_category":"Materiali Semilavorati Metallici",
    "sg:phone":"+39 035 400758",
    "sg:postcode":"24127",
    "sg:province":"Bergamo",
    "wof:name":"Santini Funi Srl",
    "wof:placetype":"venue"
},
  "geometry": {"coordinates":[9.645346,45.679661],"type":"Point"}
}