{
  "type": "Feature",
  "properties": {
    "iso:country":"IT",
    "sg:address":"20154 Milano",
    "sg:city":"Milano",
    "sg:classifiers":[
        {
            "category":"Banks & Credit Unions",
            "subcategory":"Financial Services",
            "type":"Services"
        }
    ],
    "sg:phone":"+39 02 349 4205",
    "sg:postcode":"20154",
    "sg:province":"Milano",
    "sg:tags":[
        "articles",
        "product",
        "plastics",
        "industry",
        "work",
        "plastic"
    ],
    "wof:name":"Antonio Noberini Srl",
    "wof:placetype":"venue"
},
  "geometry": {"coordinates":[9.1719026566,45.4880561829],"type":"Point"}
}