{
  "type": "Feature",
  "properties": {
    "iso:country":"IT",
    "sg:address":"00184 Roma",
    "sg:city":"Roma",
    "sg:orig_category":"Ristorazione E Locali Pubblici Affini. Ristoranti Ed Esercizi Affini. Servizi Ausiliari Di Ristorazione E Di Intrattenimento",
    "sg:phone":"+39 06 679 0706",
    "sg:postcode":"00184",
    "sg:province":"Roma",
    "sg:website":"http://www.massenzioaifori.it",
    "wof:name":"Massenzio Ristorante",
    "wof:placetype":"venue"
},
  "geometry": {"coordinates":[12.498258,41.889187],"type":"Point"}
}