{
  "type": "Feature",
  "properties": {
    "iso:country":"IT",
    "sg:address":"Via Giardino 2; Triulzi; 20085",
    "sg:classifiers":[
        {
            "category":"Banks & Credit Unions",
            "subcategory":"Bank",
            "type":"Services"
        }
    ],
    "sg:phone":"+39 02 907 7851",
    "sg:postcode":"20085",
    "sg:province":"Milano",
    "wof:name":"Istituto Bancario, San Paolo Di Torino Spa",
    "wof:placetype":"venue"
},
  "geometry": {"coordinates":[9.221699,45.376503],"type":"Point"}
}