{
  "type": "Feature",
  "properties": {
    "iso:country":"IT",
    "sg:address":"14100 Asti",
    "sg:city":"Asti",
    "sg:orig_category":"Automobili E Mezzi Di Trasporto",
    "sg:phone":"+39 0141 476022",
    "sg:postcode":"14100",
    "sg:province":"Asti",
    "wof:name":"Asti Service Srl",
    "wof:placetype":"venue"
},
  "geometry": {"coordinates":[8.236151,44.912334],"type":"Point"}
}