{
  "type": "Feature",
  "properties": {
    "addr:full":"Via Passera 4 28100 Novara Novara Novara 28100",
    "addr:housenumber":"4",
    "addr:postcode":"28100;28100",
    "addr:street":"Via Passera",
    "iso:country":"IT",
    "sg:address":"Via Passera 4 28100 Novara",
    "sg:city":"Novara",
    "sg:classifiers":[
        {
            "category":"Manufacturing",
            "subcategory":"Rubber & Plastics",
            "type":"Manufacturing & Wholesale Goods"
        }
    ],
    "sg:phone":"+39 0321 473783",
    "sg:postcode":"28100",
    "sg:province":"Novara",
    "sg:tags":[
        "mould",
        "industry"
    ],
    "wof:name":"O.m.a.s. Sas",
    "wof:placetype":"venue"
},
  "geometry": {"coordinates":[8.6367454529,45.4783554077],"type":"Point"}
}