{
  "type": "Feature",
  "properties": {
    "iso:country":"IT",
    "sg:address":"00185 Roma",
    "sg:city":"Roma",
    "sg:orig_category":"Scuole E Servizi Scolastici. Ricerca, Selezione E Formazione Del Personale",
    "sg:phone":"+39 06 481 5450",
    "sg:postcode":"00185",
    "sg:province":"Roma",
    "wof:name":"Disand Di Kostov Kostantin",
    "wof:placetype":"venue"
},
  "geometry": {"coordinates":[12.500421,41.905159],"type":"Point"}
}