{
  "type": "Feature",
  "properties": {
    "iso:country":"IT",
    "sg:address":"36015 Schio",
    "sg:city":"Schio",
    "sg:orig_category":"Prodotti E Manufatti In Materie Plastiche. Servizi E Lavori Industria Delle Materie Plastiche",
    "sg:phone":"+39 0445 575249",
    "sg:postcode":"36015",
    "sg:province":"Vicenza",
    "wof:name":"Liras Srl",
    "wof:placetype":"venue"
},
  "geometry": {"coordinates":[11.3701076508,45.706111908],"type":"Point"}
}