{
  "type": "Feature",
  "properties": {
    "addr:full":"55049 Viareggio Viareggio Lucca 55049",
    "addr:postcode":"55049;55049",
    "iso:country":"IT",
    "sg:address":"55049 Viareggio",
    "sg:city":"Viareggio",
    "sg:orig_category":"Forniture Alle Strutture Ricettive. Macchine E Impianti Per Attivita' Commerciali Ed Artigianali",
    "sg:phone":"+39 0584 425422",
    "sg:postcode":"55049",
    "sg:province":"Lucca",
    "wof:name":"Silv.a Srl",
    "wof:placetype":"venue"
},
  "geometry": {"coordinates":[10.2508792877,43.8760490417],"type":"Point"}
}