{
  "type": "Feature",
  "properties": {
    "iso:country":"IT",
    "sg:address":"09127 Cagliari",
    "sg:city":"Cagliari",
    "sg:orig_category":"Servizi Per Aziende, Manifestazioni E Supporto Agli Scambi Commerciali",
    "sg:phone":"+39 070 662402",
    "sg:postcode":"09127",
    "sg:province":"Cagliari",
    "wof:name":"Oropakaging Di Vacca Ignazia & C. Sas",
    "wof:placetype":"venue"
},
  "geometry": {"coordinates":[9.122096,39.215393],"type":"Point"}
}