{
  "type": "Feature",
  "properties": {
    "iso:country":"IT",
    "sg:address":"78, Via Giotto 90145 Palermo",
    "sg:city":"Palermo",
    "sg:classifiers":[
        {
            "category":"Wholesale",
            "subcategory":"Medical Equipment & Supplies",
            "type":"Manufacturing & Wholesale Goods"
        }
    ],
    "sg:phone":"+39 39091225558",
    "sg:postcode":"90145",
    "sg:province":"Palermo",
    "sg:tags":[
        "-",
        "health",
        "instrument"
    ],
    "wof:name":"Sicil - Diagnostica (s.r.l.)",
    "wof:placetype":"venue"
},
  "geometry": {"coordinates":[13.332808,38.130768],"type":"Point"}
}