{
  "type": "Feature",
  "properties": {
    "iso:country":"IT",
    "sg:address":"Regione Peschiera 76/d 12020 Rossana",
    "sg:city":"Rossana",
    "sg:classifiers":[
        {
            "category":"Banks & Credit Unions",
            "subcategory":"Investment Brokerage",
            "type":"Services"
        }
    ],
    "sg:phone":"+39 0175 646111",
    "sg:postcode":"12020",
    "sg:province":"Cuneo",
    "sg:tags":[
        "control",
        "equipment",
        "switch",
        "automatic",
        "switching"
    ],
    "wof:name":"Bitron Spa",
    "wof:placetype":"venue"
},
  "geometry": {"coordinates":[7.547111,44.388798],"type":"Point"}
}