{
  "type": "Feature",
  "properties": {
    "addr:full":"65128 Pescara Pescara Pescara 65128",
    "addr:postcode":"65128;65128",
    "iso:country":"IT",
    "sg:address":"65128 Pescara",
    "sg:city":"Pescara",
    "sg:orig_category":"Petroli, Gas E Combustibili",
    "sg:phone":"+39 800 112 277",
    "sg:postcode":"65128",
    "sg:province":"Pescara",
    "wof:name":"Shell Gas Italia Spa",
    "wof:placetype":"venue"
},
  "geometry": {"coordinates":[14.1901855469,42.4417686462],"type":"Point"}
}