{
  "type": "Feature",
  "properties": {
    "iso:country":"IT",
    "sg:address":"33050 Bagnaria Arsa",
    "sg:city":"Bagnaria Arsa",
    "sg:classifiers":[
        {
            "category":"Government",
            "subcategory":"Office",
            "type":"Public Place"
        }
    ],
    "sg:phone":"+39 0432 996387",
    "sg:postcode":"33050",
    "sg:province":"Udine",
    "sg:tags":[
        "e",
        "lo",
        "tempo",
        "libero",
        "per",
        "spettacolo",
        "servizi",
        "culturali",
        "sport",
        "il"
    ],
    "wof:name":"Gruppo Teatro Concerto 'le Scuelute '",
    "wof:placetype":"venue"
},
  "geometry": {"coordinates":[13.301046,45.837254],"type":"Point"}
}