{
  "type": "Feature",
  "properties": {
    "addr:full":"10064 Pinerolo Pinerolo Torino 10064",
    "addr:postcode":"10064;10064",
    "iso:country":"IT",
    "sg:address":"10064 Pinerolo",
    "sg:city":"Pinerolo",
    "sg:orig_category":"Servizi Ausiliari Per Il Trasporto. Servizi Vari Di Interesse Pubblico",
    "sg:phone":"+39 0121 322238",
    "sg:postcode":"10064",
    "sg:province":"Torino",
    "wof:name":"Manassero & Pira",
    "wof:placetype":"venue"
},
  "geometry": {"coordinates":[7.331052,44.884636],"type":"Point"}
}