{
  "type": "Feature",
  "properties": {
    "addr:full":"Corso Italia 110, 34170 Gorizia, Go Gorizia Gorizia 34170",
    "addr:housenumber":"110",
    "addr:postcode":"34170;34170",
    "addr:street":"Corso Italia",
    "iso:country":"IT",
    "sg:address":"Corso Italia 110, 34170 Gorizia, Go",
    "sg:city":"Gorizia",
    "sg:classifiers":[
        {
            "category":"Banks & Credit Unions",
            "subcategory":"Bank",
            "type":"Services"
        }
    ],
    "sg:postcode":"34170",
    "sg:province":"Gorizia",
    "wof:name":"Fondazione Cassa Di Risparmio Di Gorizia",
    "wof:placetype":"venue"
},
  "geometry": {"coordinates":[13.615675,45.940285],"type":"Point"}
}