{
  "type": "Feature",
  "properties": {
    "addr:full":"Via Del Piano 72 18018 Taggia Taggia Imperia 18018",
    "addr:housenumber":"72",
    "addr:postcode":"18018;18018",
    "addr:street":"Via Del Piano",
    "iso:country":"IT",
    "sg:address":"Via Del Piano 72 18018 Taggia",
    "sg:city":"Taggia",
    "sg:classifiers":[
        {
            "category":"Taxi",
            "type":"Transportation"
        }
    ],
    "sg:phone":"+39 0184 476252",
    "sg:postcode":"18018",
    "sg:province":"Imperia",
    "sg:tags":[
        "geared",
        "electric",
        "motor"
    ],
    "sg:website":"www.vialesistemi.com",
    "wof:name":"Viale Sistemi Srl",
    "wof:placetype":"venue"
},
  "geometry": {"coordinates":[7.852298,43.849682],"type":"Point"}
}