{
  "type": "Feature",
  "properties": {
    "iso:country":"IT",
    "sg:address":"19124 La Spezia",
    "sg:orig_category":"Servizi Al Turismo. Servizi Ausiliari Per Il Trasporto",
    "sg:phone":"+39 0187 76441",
    "sg:province":"SP",
    "wof:name":"Dario Perioli Spa",
    "wof:placetype":"venue"
},
  "geometry": {"coordinates":[9.832987,44.109791],"type":"Point"}
}