{
  "type": "Feature",
  "properties": {
    "addr:full":"Ctr. Imperatore - Zona Asi 87043 Bisignano Bisignano Cosenza 87043",
    "addr:postcode":"87043;87043",
    "addr:street":"Zona Asi",
    "iso:country":"IT",
    "sg:address":"Ctr. Imperatore - Zona Asi 87043 Bisignano",
    "sg:city":"Bisignano",
    "sg:classifiers":[
        {
            "category":"Professional",
            "subcategory":"Computer Services",
            "type":"Services"
        }
    ],
    "sg:phone":"+39 0984 940313",
    "sg:postcode":"87043",
    "sg:province":"Cosenza",
    "sg:tags":[
        "information",
        "technology"
    ],
    "sg:website":"http://www.neotek.com",
    "wof:name":"Neotek Piccola Soc Coop R L",
    "wof:placetype":"venue"
},
  "geometry": {"coordinates":[16.253809,39.298264],"type":"Point"}
}