{
  "type": "Feature",
  "properties": {
    "iso:country":"IT",
    "sg:address":"34170 Gorizia",
    "sg:city":"Gorizia",
    "sg:orig_category":"Autostrade, Trafori E Autoporti",
    "sg:phone":"+39 0481 523868",
    "sg:postcode":"34170",
    "sg:province":"Gorizia",
    "wof:name":"Kodetra Srl",
    "wof:placetype":"venue"
},
  "geometry": {"coordinates":[13.599144,45.943825],"type":"Point"}
}