{
  "type": "Feature",
  "properties": {
    "addr:full":"38015 Lavis Lavis Trento 38015",
    "addr:postcode":"38015;38015",
    "iso:country":"IT",
    "sg:address":"38015 Lavis",
    "sg:city":"Lavis",
    "sg:orig_category":"Forniture Per Agricoltura E Zootecnia. Prodotti Chimici Secondari. Macchine E Forniture Per Ecologia E Smaltimento Rifiuti",
    "sg:phone":"+39 0461 246108",
    "sg:postcode":"38015",
    "sg:province":"Trento",
    "wof:name":"Ortal Di Zanolli Corrado",
    "wof:placetype":"venue"
},
  "geometry": {"coordinates":[11.0941400528,46.1387176514],"type":"Point"}
}