{
  "type": "Feature",
  "properties": {
    "iso:country":"IT",
    "sg:address":"35, Via Malallevo 51100 Pistoia",
    "sg:city":"Pistoia",
    "sg:classifiers":[
        {
            "category":"Farming",
            "subcategory":"Livestock Farm",
            "type":"Manufacturing & Wholesale Goods"
        }
    ],
    "sg:phone":"+39 0573 544073",
    "sg:postcode":"51100",
    "sg:province":"Pistoia",
    "sg:tags":[
        "agriculture"
    ],
    "wof:name":"Azienda Agricola Righetti Raffaele",
    "wof:placetype":"venue"
},
  "geometry": {"coordinates":[10.956691,43.898144],"type":"Point"}
}