{
  "type": "Feature",
  "properties": {
    "iso:country":"IT",
    "sg:address":"20124 Milano",
    "sg:city":"Milano",
    "sg:classifiers":[
        {
            "category":"Travel",
            "subcategory":"Hotels & Motels",
            "type":"Entertainment"
        }
    ],
    "sg:phone":"+39 02 6698 5851",
    "sg:postcode":"20124",
    "sg:province":"Milano",
    "sg:tags":[
        "hotels",
        "facility"
    ],
    "sg:website":"http://www.virtualia.it/auriga",
    "wof:name":"Hotel Auriga",
    "wof:placetype":"venue"
},
  "geometry": {"coordinates":[9.201383,45.484249],"type":"Point"}
}