{
  "type": "Feature",
  "properties": {
    "iso:country":"IT",
    "sg:address":"20129 Milano",
    "sg:city":"Milano",
    "sg:orig_category":"Motori Ed Organi Di Trasmissione. Ricambi E Componenti Dei Mezzi Di Trasporto",
    "sg:phone":"+39 02 2941 2466",
    "sg:postcode":"20129",
    "sg:province":"Milano",
    "wof:name":"Adler S P A",
    "wof:placetype":"venue"
},
  "geometry": {"coordinates":[9.2157344818,45.4797019958],"type":"Point"}
}