{
  "type": "Feature",
  "properties": {
    "iso:country":"IT",
    "sg:address":"20052 Monza",
    "sg:city":"Monza",
    "sg:orig_category":"Lavorazioni Metalli, Stampaggio E Saldatura",
    "sg:phone":"+39 039 322958",
    "sg:postcode":"20052",
    "sg:province":"Milano",
    "wof:name":"Mauri Antonio",
    "wof:placetype":"venue"
},
  "geometry": {"coordinates":[9.1894,45.45993],"type":"Point"}
}