{
  "type": "Feature",
  "properties": {
    "addr:full":"48100 Ravenna Ravenna Ravenna 48100",
    "addr:housenumber":"48100",
    "addr:postcode":"48100",
    "iso:country":"IT",
    "sg:address":"48100 Ravenna",
    "sg:city":"Ravenna",
    "sg:orig_category":"Servizi Per Lo Sport E Il Tempo Libero. Servizi Al Turismo",
    "sg:phone":"+39 0544 219938",
    "sg:postcode":"48100",
    "sg:province":"Ravenna",
    "sg:website":"http://www.ravennaservice.net",
    "wof:name":"Centro Prenotaz. Servizi Turistici Culturali E Souvenir Shopping On Line",
    "wof:placetype":"venue"
},
  "geometry": {"coordinates":[12.224458,44.380314],"type":"Point"}
}