{
  "type": "Feature",
  "properties": {
    "addr:full":"20, Via Torquato Tasso 24014 Piazza Brembana Piazza Brembana Bergamo 24014",
    "addr:postcode":"24014;24014",
    "addr:street":"Via Torquato Tasso;Piazza Brembana Piazza",
    "iso:country":"IT",
    "sg:address":"20, Via Torquato Tasso 24014 Piazza Brembana",
    "sg:city":"Piazza Brembana",
    "sg:classifiers":[
        {
            "category":"Shopping",
            "subcategory":"Clothing, Apparel, & Fashions",
            "type":"Retail Goods"
        }
    ],
    "sg:phone":"+39 39034581278",
    "sg:postcode":"24014",
    "sg:province":"Bergamo",
    "sg:tags":[
        "clothes"
    ],
    "wof:name":"Confezioni Carmen S.a.s Di Milani Mario & C.",
    "wof:placetype":"venue"
},
  "geometry": {"coordinates":[9.671392,45.94838],"type":"Point"}
}