{
  "type": "Feature",
  "properties": {
    "iso:country":"IT",
    "sg:address":"20052 Monza",
    "sg:city":"Monza",
    "sg:orig_category":"Scuole Di Lingue",
    "sg:phone":"+39 039 284 8495",
    "sg:postcode":"20052",
    "sg:province":"Milano",
    "sg:website":"http://www.shenkermonza.it",
    "wof:name":"The Shenker Institute Of English Sas",
    "wof:placetype":"venue"
},
  "geometry": {"coordinates":[9.156013,45.444324],"type":"Point"}
}