{
  "type": "Feature",
  "properties": {
    "iso:country":"IT",
    "sg:address":"09170 Oristano",
    "sg:city":"Oristano",
    "sg:orig_category":"Prodotti Di Base E Forniture Per Industria Alimentare E Bevande. Forniture Per Attivita' Commerciali Ed Artigianali",
    "sg:phone":"+39 0783 300200",
    "sg:postcode":"09170",
    "sg:province":"Oristano",
    "wof:name":"Conificio Schiano Snc",
    "wof:placetype":"venue"
},
  "geometry": {"coordinates":[8.6050739288,39.9178123474],"type":"Point"}
}