{
  "type": "Feature",
  "properties": {
    "addr:full":"00030 Castel San Pietro Romano Castel San Pietro Romano Roma 00030",
    "addr:postcode":"00030;roma 00030",
    "iso:country":"IT",
    "sg:address":"00030 Castel San Pietro Romano",
    "sg:city":"Castel San Pietro Romano",
    "sg:orig_category":"Telecomunicazioni E Telefonia, Impianti, Apparecchi E Servizi",
    "sg:phone":"+39 06 953 8004",
    "sg:postcode":"00030",
    "sg:province":"Roma",
    "wof:name":"Tvr Voxon S.p.a.",
    "wof:placetype":"venue"
},
  "geometry": {"coordinates":[12.89499,41.846409],"type":"Point"}
}