{
  "type": "Feature",
  "properties": {
    "addr:full":"20019 Settimo Milanese Settimo Milanese Milano 20019",
    "addr:postcode":"20019;20019",
    "iso:country":"IT",
    "sg:address":"20019 Settimo Milanese",
    "sg:city":"Settimo Milanese",
    "sg:orig_category":"Bevande, Vini E Liquori",
    "sg:phone":"+39 02 3350 0555",
    "sg:postcode":"20019",
    "sg:province":"Milano",
    "wof:name":"Civitelli Import Srl",
    "wof:placetype":"venue"
},
  "geometry": {"coordinates":[9.055449,45.465675],"type":"Point"}
}