{
  "type": "Feature",
  "properties": {
    "iso:country":"IT",
    "sg:address":"21044 Cavaria",
    "sg:orig_category":"Materie Plastiche - Produzione E Lavorazione",
    "sg:phone":"+39 0331 217207",
    "sg:postcode":"21044",
    "sg:province":"Varese",
    "sg:website":"http://www.newglass.it",
    "wof:name":"New Glass Srl",
    "wof:placetype":"venue"
},
  "geometry": {"coordinates":[8.804368,45.690685],"type":"Point"}
}