{
  "type": "Feature",
  "properties": {
    "iso:country":"IT",
    "sg:address":"20059 Vimercate",
    "sg:city":"Vimercate",
    "sg:classifiers":[
        {
            "category":"Government",
            "subcategory":"Office",
            "type":"Public Place"
        }
    ],
    "sg:phone":"+39 039 669165",
    "sg:postcode":"20059",
    "sg:province":"Milano",
    "sg:tags":[
        "decorative",
        "equipment",
        "objects",
        "furnishings",
        "furnishing"
    ],
    "wof:name":"Rotra Snc",
    "wof:placetype":"venue"
},
  "geometry": {"coordinates":[9.3688325882,45.619342804],"type":"Point"}
}