{
  "type": "Feature",
  "properties": {
    "iso:country":"IT",
    "sg:address":"Via Occhieppo Superiore 22 13814 Pollone",
    "sg:city":"Pollone",
    "sg:classifiers":[
        {
            "category":"Manufacturing",
            "subcategory":"Textiles",
            "type":"Manufacturing & Wholesale Goods"
        }
    ],
    "sg:phone":"+39 015 256 3025",
    "sg:postcode":"13814",
    "sg:province":"Biella",
    "sg:tags":[
        "woollen",
        "fabric"
    ],
    "wof:name":"Lanificio Tallia Galoppo Verzoletto Spa",
    "wof:placetype":"venue"
},
  "geometry": {"coordinates":[8.005811,45.574921],"type":"Point"}
}