{
  "type": "Feature",
  "properties": {
    "iso:country":"IT",
    "sg:address":"63020 Montappone",
    "sg:city":"Montappone",
    "sg:orig_category":"Tempo Libero - Articoli E Forniture. Forniture Per Congressi, Fiere E Manifestazioni. Regalistica Aziendale",
    "sg:phone":"+39 0734 760097",
    "sg:postcode":"63020",
    "sg:province":"Ascoli Piceno",
    "wof:name":"Nori Floriano Promos",
    "wof:placetype":"venue"
},
  "geometry": {"coordinates":[13.574977,42.8554],"type":"Point"}
}