{
  "type": "Feature",
  "properties": {
    "iso:country":"IT",
    "sg:address":"20052 Monza",
    "sg:city":"Monza",
    "sg:orig_category":"Avvocati, Notai E Servizi Legali. Consulenze Tecniche, Amministrative E Perizie",
    "sg:phone":"+39 039 231 2143",
    "sg:postcode":"20052",
    "sg:province":"Milano",
    "wof:name":"Franco Martegani Srl",
    "wof:placetype":"venue"
},
  "geometry": {"coordinates":[9.288399,45.532249],"type":"Point"}
}