{
  "type": "Feature",
  "properties": {
    "iso:country":"IT",
    "sg:address":"40128 Bologna",
    "sg:city":"Bologna",
    "sg:orig_category":"Servizi E Lavori Per Abbigliamento E Pelletterie",
    "sg:phone":"+39 051 355404",
    "sg:postcode":"40128",
    "sg:province":"Bologna",
    "wof:name":"Pulitura A Secco Dagnini Di Quaiotto Graziella E C. Snc",
    "wof:placetype":"venue"
},
  "geometry": {"coordinates":[11.374809,44.552971],"type":"Point"}
}