{
  "type": "Feature",
  "properties": {
    "iso:country":"IT",
    "sg:address":"2/4, Via Marzocchi A. 40012 Calderara Di Reno",
    "sg:city":"Calderara di Reno",
    "sg:classifiers":[
        {
            "category":"Professional",
            "subcategory":"Printing & Photocopies",
            "type":"Services"
        }
    ],
    "sg:phone":"+39 39051727052",
    "sg:postcode":"40012",
    "sg:province":"Bologna",
    "wof:name":"Poligrafici Calderara (s.p.a.)",
    "wof:placetype":"venue"
},
  "geometry": {"coordinates":[11.2640886307,44.5471076965],"type":"Point"}
}