{
  "type": "Feature",
  "properties": {
    "iso:country":"IT",
    "sg:address":"25088 Toscolano Maderno",
    "sg:city":"Maderno",
    "sg:orig_category":"Non-classified Establishments",
    "sg:phone":"+39 036 564 1006",
    "sg:postcode":"25088",
    "sg:province":"Brescia",
    "wof:name":"Zani Industria Dell'acciaio (s.p.a.)",
    "wof:placetype":"venue"
},
  "geometry": {"coordinates":[10.513698,45.611141],"type":"Point"}
}