{
  "type": "Feature",
  "properties": {
    "addr:full":"70123 Bari Bari Bari 70123",
    "addr:postcode":"70123;70123",
    "iso:country":"IT",
    "sg:address":"70123 Bari",
    "sg:city":"Bari",
    "sg:orig_category":"Motori Ed Organi Di Trasmissione. Ricambi E Componenti Dei Mezzi Di Trasporto",
    "sg:phone":"+39 080 521 4062",
    "sg:postcode":"70123",
    "sg:province":"Bari",
    "wof:name":"Ruggieri Aniello",
    "wof:placetype":"venue"
},
  "geometry": {"coordinates":[16.8605976105,41.1273231506],"type":"Point"}
}