{
  "type": "Feature",
  "properties": {
    "addr:full":"40141 Bologna Bologna Bologna 40141",
    "addr:postcode":"40141;40141",
    "iso:country":"IT",
    "sg:address":"40141 Bologna",
    "sg:city":"Bologna",
    "sg:orig_category":"Prodotti E Manufatti In Gomma",
    "sg:phone":"+39 051 474866",
    "sg:postcode":"40141",
    "sg:province":"Bologna",
    "wof:name":"Plastigomma",
    "wof:placetype":"venue"
},
  "geometry": {"coordinates":[11.3701972961,44.4719200134],"type":"Point"}
}