{
  "type": "Feature",
  "properties": {
    "iso:country":"IT",
    "sg:address":"36071 Arzignano",
    "sg:city":"Arzignano",
    "sg:orig_category":"Elettrotecnica Industriale, Prodotti E Apparecchiature",
    "sg:phone":"+39 0444 673712",
    "sg:postcode":"36071",
    "sg:province":"Vicenza",
    "wof:name":"C.g.m. Gruppi Elettrogeni Srl",
    "wof:placetype":"venue"
},
  "geometry": {"coordinates":[11.358827,45.513668],"type":"Point"}
}