{
  "type": "Feature",
  "properties": {
    "iso:country":"IT",
    "sg:address":"36066 Sandrigo",
    "sg:city":"Sandrigo",
    "sg:orig_category":"Macchine Utensili E Impianti. Elettrotecnica Industriale, Prodotti E Apparecchiature",
    "sg:phone":"+39 0444 666999",
    "sg:postcode":"36066",
    "sg:province":"Vicenza",
    "wof:name":"Helvi S.p.a.",
    "wof:placetype":"venue"
},
  "geometry": {"coordinates":[11.550232,45.633148],"type":"Point"}
}