{
  "type": "Feature",
  "properties": {
    "iso:country":"IT",
    "sg:address":"98/h, V. Comunale Napoli80100 Napoli",
    "sg:classifiers":[
        {
            "category":"Personal",
            "subcategory":"Shoe Repair & Shine",
            "type":"Services"
        }
    ],
    "sg:phone":"+39 081 1957 6283",
    "sg:tags":[
        "leather"
    ],
    "sg:website":"http://www.paginegialle.it/pelletteriamatteus",
    "wof:name":"Pelletteria Matteus",
    "wof:placetype":"venue"
},
  "geometry": {"coordinates":[14.178893,40.860989],"type":"Point"}
}