{
  "type": "Feature",
  "properties": {
    "iso:country":"IT",
    "sg:address":"Via Xx Settembre 95-97; San Martino; 37036",
    "sg:classifiers":[
        {
            "category":"Banks & Credit Unions",
            "subcategory":"Bank",
            "type":"Services"
        }
    ],
    "sg:phone":"+39 045 878 0220",
    "sg:postcode":"37036",
    "sg:province":"Verona",
    "wof:name":"Rolo Banca 1473 Spa",
    "wof:placetype":"venue"
},
  "geometry": {"coordinates":[11.097646,45.410915],"type":"Point"}
}