{
  "type": "Feature",
  "properties": {
    "addr:full":"Corso Roma, 35; Alessandria; 15100 Alessandria Alessandria 15100",
    "addr:housenumber":"35",
    "addr:postcode":"15100;15100",
    "addr:street":"Corso Roma",
    "iso:country":"IT",
    "sg:address":"Corso Roma, 35; Alessandria; 15100",
    "sg:city":"Alessandria",
    "sg:classifiers":[
        {
            "category":"Banks & Credit Unions",
            "subcategory":"Bank",
            "type":"Services"
        }
    ],
    "sg:phone":"+39 0131 446222",
    "sg:postcode":"15100",
    "sg:province":"Alessandria",
    "wof:name":"Banca Popolare Di Novara",
    "wof:placetype":"venue"
},
  "geometry": {"coordinates":[8.613002,44.912212],"type":"Point"}
}