{
  "type": "Feature",
  "properties": {
    "iso:country":"IT",
    "sg:address":"20090 Vimodrone",
    "sg:city":"Vimodrone",
    "sg:classifiers":[
        {
            "category":"Health Services",
            "subcategory":"Health Practitioner",
            "type":"Services"
        }
    ],
    "sg:phone":"+39 02 265 0103",
    "sg:postcode":"20090",
    "sg:province":"Milano",
    "sg:tags":[
        "medici"
    ],
    "wof:name":"Arrotta Ubaldo",
    "wof:placetype":"venue"
},
  "geometry": {"coordinates":[9.288439,45.514774],"type":"Point"}
}