{
  "type": "Feature",
  "properties": {
    "addr:full":"39100 Bolzano Bolzano Bolzano/Bozen 39100",
    "addr:postcode":"39100;39100",
    "iso:country":"IT",
    "sg:address":"39100 Bolzano",
    "sg:city":"Bolzano",
    "sg:orig_category":"Antifurto",
    "sg:phone":"+39 0471 264197",
    "sg:postcode":"39100",
    "sg:province":"Bolzano/Bozen",
    "wof:name":"Sos Sicurezza Snc",
    "wof:placetype":"venue"
},
  "geometry": {"coordinates":[11.335704,46.4963],"type":"Point"}
}