{
  "type": "Feature",
  "properties": {
    "iso:country":"IT",
    "sg:address":"20133 Milano",
    "sg:city":"Milano",
    "sg:orig_category":"Prodotti Finiti Stampati. Forniture Per Uffici. Regalistica Aziendale",
    "sg:phone":"+39 02 749 1191",
    "sg:postcode":"20133",
    "sg:province":"Milano",
    "sg:website":"http://www.bellomi.it",
    "wof:name":"Bellomi A. Srl",
    "wof:placetype":"venue"
},
  "geometry": {"coordinates":[9.1238231659,45.4160766602],"type":"Point"}
}