{
  "type": "Feature",
  "properties": {
    "iso:country":"IT",
    "sg:address":"42015 Correggio",
    "sg:orig_category":"Cancelleria",
    "sg:phone":"+39 0522 631084",
    "sg:postcode":"42015",
    "sg:province":"Reggio Nell'Emilia",
    "wof:name":"Sire Srl",
    "wof:placetype":"venue"
},
  "geometry": {"coordinates":[10.62069,44.705395],"type":"Point"}
}