{
  "type": "Feature",
  "properties": {
    "iso:country":"IT",
    "sg:address":"17, Viale Dell' Industria 10078 Venaria",
    "sg:classifiers":[
        {
            "category":"Professional",
            "subcategory":"Engineering",
            "type":"Services"
        }
    ],
    "sg:phone":"+39 011 455 7979",
    "sg:postcode":"10078",
    "sg:province":"Torino",
    "sg:tags":[
        "machine",
        "-",
        "mechanical"
    ],
    "wof:name":"Emmedi S.p.a.",
    "wof:placetype":"venue"
},
  "geometry": {"coordinates":[7.668163,45.080368],"type":"Point"}
}