{
  "type": "Feature",
  "properties": {
    "iso:country":"IT",
    "sg:address":"20032 Cormano",
    "sg:city":"Cormano",
    "sg:orig_category":"Macchine, Impianti E Forniture Per Industria Grafica, Cartaria E Cartotecnica",
    "sg:phone":"+39 02 6630 2183",
    "sg:postcode":"20032",
    "sg:province":"Milano",
    "wof:name":"Petoletti Macchine Grafiche Di Petoletti Fabio E C. (s.a.s.)",
    "wof:placetype":"venue"
},
  "geometry": {"coordinates":[9.158612,45.541386],"type":"Point"}
}