{
  "type": "Feature",
  "properties": {
    "iso:country":"IT",
    "sg:address":"67, Via Principale 39054 Renon",
    "sg:city":"Renon",
    "sg:classifiers":[
        {
            "category":"Manufacturing",
            "subcategory":"Lumber",
            "type":"Manufacturing & Wholesale Goods"
        }
    ],
    "sg:phone":"+39 0471 359012",
    "sg:postcode":"39054",
    "sg:province":"Bolzano/Bozen",
    "sg:tags":[
        "wood"
    ],
    "wof:name":"Toni Lobis S.n.c. Dei F.lli Lobis",
    "wof:placetype":"venue"
},
  "geometry": {"coordinates":[11.439371,46.511955],"type":"Point"}
}