{
  "type": "Feature",
  "properties": {
    "addr:full":"24060 Bagnatica Bagnatica Bergamo 24060",
    "addr:postcode":"24060;24060",
    "iso:country":"IT",
    "sg:address":"24060 Bagnatica",
    "sg:city":"Bagnatica",
    "sg:orig_category":"Trattamenti Termici E Superficiali Metalli, Galvanotecnica",
    "sg:phone":"+39 035 676139",
    "sg:postcode":"24060",
    "sg:province":"Bergamo",
    "wof:name":"Marcolli Enrico S.n.c.",
    "wof:placetype":"venue"
},
  "geometry": {"coordinates":[9.693901,45.706505],"type":"Point"}
}