{
  "type": "Feature",
  "properties": {
    "iso:country":"IT",
    "sg:address":"Via Roma 26, 34070 Villesse, Go",
    "sg:city":"Villesse",
    "sg:classifiers":[
        {
            "category":"Banks & Credit Unions",
            "subcategory":"Bank",
            "type":"Services"
        }
    ],
    "sg:postcode":"34070",
    "sg:province":"Gorizia",
    "wof:name":"Cassa Rurale E Artigiana Di Villesse",
    "wof:placetype":"venue"
},
  "geometry": {"coordinates":[13.438483,45.860043],"type":"Point"}
}