{
  "type": "Feature",
  "properties": {
    "iso:country":"IT",
    "sg:address":"20033 Desio",
    "sg:city":"Desio",
    "sg:orig_category":"Forniture Per Attivita' Commerciali Ed Artigianali",
    "sg:phone":"+39 036 262 6656",
    "sg:postcode":"20033",
    "sg:province":"Milano",
    "wof:name":"Garide Snc",
    "wof:placetype":"venue"
},
  "geometry": {"coordinates":[9.2036552429,45.6032333374],"type":"Point"}
}