{
  "type": "Feature",
  "properties": {
    "iso:country":"IT",
    "sg:address":"37051 Bovolone",
    "sg:city":"Bovolone",
    "sg:orig_category":"Imprese Di Costruzioni Civili Ed Industriali",
    "sg:phone":"+39 045 710 0722",
    "sg:postcode":"37051",
    "sg:province":"Verona",
    "wof:name":"Elettrini Luigi Adelino & C. Snc",
    "wof:placetype":"venue"
},
  "geometry": {"coordinates":[11.131127,45.265282],"type":"Point"}
}