{
  "type": "Feature",
  "properties": {
    "iso:country":"IT",
    "sg:address":"41057 San Vito",
    "sg:city":"San Vito",
    "sg:orig_category":"Prodotti Di Base E Forniture Per Industria Alimentare E Bevande",
    "sg:phone":"+39 059 798923",
    "sg:postcode":"41057",
    "sg:province":"Modena",
    "wof:name":"Spaggiari Giancarlo (s.n.c.)",
    "wof:placetype":"venue"
},
  "geometry": {"coordinates":[10.9883127213,44.5509490967],"type":"Point"}
}