{
  "type": "Feature",
  "properties": {
    "iso:country":"IT",
    "sg:address":"9, Via Grecale 09126 Cagliari",
    "sg:city":"Cagliari",
    "sg:classifiers":[
        {
            "category":"Banks & Credit Unions",
            "subcategory":"Bank",
            "type":"Services"
        }
    ],
    "sg:phone":"+39 39070380720",
    "sg:postcode":"09126",
    "sg:province":"Cagliari",
    "sg:tags":[
        "banking",
        "institution"
    ],
    "wof:name":"Cooperativa Vigilanza Sardegna (s.r.l.)",
    "wof:placetype":"venue"
},
  "geometry": {"coordinates":[9.146488,39.200947],"type":"Point"}
}