{
  "type": "Feature",
  "properties": {
    "iso:country":"IT",
    "sg:address":"19122 La Spezia",
    "sg:orig_category":"Non-classified Establishments",
    "sg:phone":"+39 0187 713360",
    "sg:province":"SP",
    "wof:name":"Carillon Di Marchini Andrea",
    "wof:placetype":"venue"
},
  "geometry": {"coordinates":[9.809704,44.111881],"type":"Point"}
}