{
  "type": "Feature",
  "properties": {
    "iso:country":"IT",
    "sg:address":"64, Via Macina 25014 Castenedolo",
    "sg:city":"Castenedolo",
    "sg:classifiers":[
        {
            "category":"Food & Beverages",
            "subcategory":"Dairy",
            "type":"Retail Goods"
        }
    ],
    "sg:phone":"+39 030 273 3061",
    "sg:postcode":"25014",
    "sg:province":"Brescia",
    "sg:tags":[
        "product"
    ],
    "wof:name":"Caseificio Boldini G.b. S.p.a.",
    "wof:placetype":"venue"
},
  "geometry": {"coordinates":[10.315145,45.511971],"type":"Point"}
}