{
  "type": "Feature",
  "properties": {
    "addr:full":"27, Via Odoardo Neri 46023 Gonzaga Gonzaga Mantova 46023",
    "addr:postcode":"46023;46023",
    "addr:street":"Via Odoardo Neri",
    "iso:country":"IT",
    "sg:address":"27, Via Odoardo Neri 46023 Gonzaga",
    "sg:city":"Gonzaga",
    "sg:classifiers":[
        {
            "category":"Manufacturing",
            "subcategory":"Metals",
            "type":"Manufacturing & Wholesale Goods"
        }
    ],
    "sg:phone":"+39 0376 528452",
    "sg:postcode":"46023",
    "sg:province":"Mantova",
    "sg:tags":[
        "processing"
    ],
    "wof:name":"Foresi (s.p.a.)",
    "wof:placetype":"venue"
},
  "geometry": {"coordinates":[10.8095378876,44.9564323425],"type":"Point"}
}