{
  "type": "Feature",
  "properties": {
    "addr:full":"16038 Santa Margherita Ligure Santa Margherita Ligure Genova 16038",
    "addr:housenumber":"16038",
    "addr:postcode":"16038",
    "addr:street":"Santa",
    "iso:country":"IT",
    "sg:address":"16038 Santa Margherita Ligure",
    "sg:city":"Santa Margherita Ligure",
    "sg:orig_category":"Coperte E Copriletti",
    "sg:phone":"+39 0185 288191",
    "sg:postcode":"16038",
    "sg:province":"Genova",
    "wof:name":"Mondo Vip",
    "wof:placetype":"venue"
},
  "geometry": {"coordinates":[9.213346,44.335709],"type":"Point"}
}