{
  "type": "Feature",
  "properties": {
    "addr:full":"Via Bologna 242; Torino; 10154 Torino Torino 10154",
    "addr:housenumber":"242",
    "addr:postcode":"10154;10154",
    "addr:street":"Via Bologna",
    "iso:country":"IT",
    "sg:address":"Via Bologna 242; Torino; 10154",
    "sg:city":"Torino",
    "sg:classifiers":[
        {
            "category":"Banks & Credit Unions",
            "subcategory":"Bank",
            "type":"Services"
        }
    ],
    "sg:phone":"+39 011 242 4063",
    "sg:postcode":"10154",
    "sg:province":"Torino",
    "wof:name":"Banca Sella Spa",
    "wof:placetype":"venue"
},
  "geometry": {"coordinates":[7.71238,45.090801],"type":"Point"}
}