{
  "type": "Feature",
  "properties": {
    "iso:country":"IT",
    "sg:address":"105, Via Biella 13862 Brusnengo",
    "sg:city":"Brusnengo",
    "sg:classifiers":[
        {
            "category":"Shopping",
            "subcategory":"Crafts & Fabrics",
            "type":"Retail Goods"
        }
    ],
    "sg:phone":"+39 39015985344",
    "sg:postcode":"13862",
    "sg:province":"Biella",
    "wof:name":"Tessilsport (s.r.l.)",
    "wof:placetype":"venue"
},
  "geometry": {"coordinates":[8.2543983459,45.5775566101],"type":"Point"}
}