{
  "type": "Feature",
  "properties": {
    "addr:full":"Via Giotto 51039 Quarrata Quarrata Pistoia 51039",
    "addr:postcode":"51039;51039",
    "addr:street":"Via Giotto",
    "iso:country":"IT",
    "sg:address":"Via Giotto 51039 Quarrata",
    "sg:city":"Quarrata",
    "sg:classifiers":[
        {
            "category":"Parking",
            "subcategory":"Lot",
            "type":"Transportation"
        }
    ],
    "sg:phone":"+39 0573 738662",
    "sg:postcode":"51039",
    "sg:province":"Pistoia",
    "sg:tags":[
        "transport",
        "road"
    ],
    "wof:name":"Chiti Autotrasporti Srl",
    "wof:placetype":"venue"
},
  "geometry": {"coordinates":[10.984031,43.853699],"type":"Point"}
}