{
  "type": "Feature",
  "properties": {
    "iso:country":"IT",
    "sg:address":"Via Del Corso 337, 00186 Rome, Rm",
    "sg:classifiers":[
        {
            "category":"Banks & Credit Unions",
            "subcategory":"Bank",
            "type":"Services"
        }
    ],
    "sg:postcode":"00186",
    "sg:province":"Roma",
    "wof:name":"Prominvestment-societ\u00e0 Per La Promozione Degli Investimenti Spa",
    "wof:placetype":"venue"
},
  "geometry": {"coordinates":[12.4807281494,41.9001808167],"type":"Point"}
}