{
  "type": "Feature",
  "properties": {
    "addr:full":"20019 Settimo Milanese Settimo Milanese Milano 20019",
    "addr:postcode":"20019;20019",
    "iso:country":"IT",
    "sg:address":"20019 Settimo Milanese",
    "sg:city":"Settimo Milanese",
    "sg:orig_category":"Forniture Per Attivita' Industriali",
    "sg:phone":"+39 02 4892 0025",
    "sg:postcode":"20019",
    "sg:province":"Milano",
    "wof:name":"Parini & C. Srl",
    "wof:placetype":"venue"
},
  "geometry": {"coordinates":[9.0652275085,45.4659461975],"type":"Point"}
}