{
  "type": "Feature",
  "properties": {
    "iso:country":"IT",
    "sg:address":"66020 S.giovanni Teatino",
    "sg:city":"Sambuceto",
    "sg:orig_category":"Macchine, Impianti Ed Attrezzature Industria Chimica. Macchine Ed Impianti Per Edilizia E Lavori Pubblici",
    "sg:phone":"+39 085 446 1801",
    "sg:postcode":"66020",
    "sg:province":"Chieti",
    "wof:name":"Ve.ma.pla Sas Di Andreoli Luigi & C.",
    "wof:placetype":"venue"
},
  "geometry": {"coordinates":[14.202207,42.410213],"type":"Point"}
}