{
  "type": "Feature",
  "properties": {
    "addr:full":"22, Via Enrico Mattei 33083 Chions Chions Pordenone 33083",
    "addr:postcode":"33083;33083",
    "addr:street":"Via Enrico Mattei",
    "iso:country":"IT",
    "sg:address":"22, Via Enrico Mattei 33083 Chions",
    "sg:city":"Chions",
    "sg:classifiers":[
        {
            "category":"Home & Garden",
            "subcategory":"Home Furnishings",
            "type":"Retail Goods"
        }
    ],
    "sg:phone":"+39 0434 630680",
    "sg:postcode":"33083",
    "sg:province":"Pordenone",
    "sg:tags":[
        "household"
    ],
    "wof:name":"Office & C. S.r.l.",
    "wof:placetype":"venue"
},
  "geometry": {"coordinates":[12.770578,45.866333],"type":"Point"}
}