{
  "type": "Feature",
  "properties": {
    "addr:full":"4, Via Dell' Industria 20090 Buccinasco Buccinasco Milano 20090",
    "addr:postcode":"20090;20090",
    "addr:street":"Via Dell ' Industria",
    "iso:country":"IT",
    "sg:address":"4, Via Dell' Industria 20090 Buccinasco",
    "sg:city":"Buccinasco",
    "sg:classifiers":[
        {
            "category":"Shopping",
            "type":"Retail Goods"
        }
    ],
    "sg:phone":"+39 02 4571 1008",
    "sg:postcode":"20090",
    "sg:province":"Milano",
    "sg:tags":[
        "finished",
        "-",
        "metallic"
    ],
    "wof:name":"Pro- Co Stamp S.r.l.",
    "wof:placetype":"venue"
},
  "geometry": {"coordinates":[9.1005582809,45.411239624],"type":"Point"}
}