{
  "type": "Feature",
  "properties": {
    "iso:country":"IT",
    "sg:address":"Zona Industriale E. Fermi 62010 Montelupone",
    "sg:city":"Montelupone",
    "sg:classifiers":[
        {
            "category":"Manufacturing",
            "subcategory":"Rubber & Plastics",
            "type":"Manufacturing & Wholesale Goods"
        }
    ],
    "sg:phone":"+39 0733 220401",
    "sg:postcode":"62010",
    "sg:province":"Macerata",
    "sg:tags":[
        "material"
    ],
    "wof:name":"Telma Guzzini Srl",
    "wof:placetype":"venue"
},
  "geometry": {"coordinates":[13.4562616348,43.3007469177],"type":"Point"}
}