{
  "type": "Feature",
  "properties": {
    "addr:full":"82, V. Ausa - Cerasolo Ausa 47853 Coriano Cerasolo Rimini 47853",
    "addr:housenumber":"82",
    "addr:postcode":"47853;47853",
    "addr:street":"V. Ausa;Ausa",
    "iso:country":"IT",
    "sg:address":"82, V. Ausa - Cerasolo Ausa 47853 Coriano",
    "sg:city":"Cerasolo",
    "sg:classifiers":[
        {
            "category":"Manufacturing",
            "subcategory":"Tools & Machinery",
            "type":"Manufacturing & Wholesale Goods"
        }
    ],
    "sg:phone":"+39 0541 756777",
    "sg:postcode":"47853",
    "sg:province":"Rimini",
    "sg:tags":[
        "environment",
        "equipment",
        "-"
    ],
    "sg:website":"http://www.cemfrigoriferi.it",
    "wof:name":"C.e.m. Srl",
    "wof:placetype":"venue"
},
  "geometry": {"coordinates":[12.566257,44.06078],"type":"Point"}
}