{
  "type": "Feature",
  "properties": {
    "iso:country":"IT",
    "sg:address":"40043 Marzabotto",
    "sg:city":"Marzabotto",
    "sg:orig_category":"Servizi Ausiliari Dei Mezzi Di Trasporto",
    "sg:phone":"+39 051 931000",
    "sg:postcode":"40043",
    "sg:province":"Bologna",
    "wof:name":"Tassi Enzo",
    "wof:placetype":"venue"
},
  "geometry": {"coordinates":[11.2043,44.341557],"type":"Point"}
}