{
  "type": "Feature",
  "properties": {
    "addr:full":"00155 Roma Roma Roma 00155",
    "addr:postcode":"00155;00155",
    "iso:country":"IT",
    "sg:address":"00155 Roma",
    "sg:city":"Roma",
    "sg:orig_category":"Servizi E Lavori Per Abbigliamento E Pelletterie",
    "sg:phone":"+39 06 228 0264",
    "sg:postcode":"00155",
    "sg:province":"Roma",
    "wof:name":"Lavanderia Pierina Di Segoni Pierina & Figli",
    "wof:placetype":"venue"
},
  "geometry": {"coordinates":[12.587167,41.903679],"type":"Point"}
}