{
  "type": "Feature",
  "properties": {
    "iso:country":"IT",
    "sg:address":"20049 Concorezzo",
    "sg:city":"Concorezzo",
    "sg:orig_category":"Prodotti Chimici Di Base. Prodotti Cosmetici E Da Toeletta",
    "sg:phone":"+39 039 611581",
    "sg:postcode":"20049",
    "sg:province":"Milano",
    "wof:name":"Variati E Co Spa",
    "wof:placetype":"venue"
},
  "geometry": {"coordinates":[9.3368177414,45.5933952332],"type":"Point"}
}