{
  "type": "Feature",
  "properties": {
    "iso:country":"IT",
    "sg:address":"72017 Ostuni",
    "sg:city":"Ostuni",
    "sg:orig_category":"Avvocati - Studi",
    "sg:phone":"+39 0831 301418",
    "sg:postcode":"72017",
    "sg:province":"Brindisi",
    "wof:name":"D'ambrosio Avv. Camillo",
    "wof:placetype":"venue"
},
  "geometry": {"coordinates":[17.941296,40.635284],"type":"Point"}
}