{
  "type": "Feature",
  "properties": {
    "iso:country":"IT",
    "sg:address":"Via Larga 15/8/f 40138 Bologna",
    "sg:city":"Bologna",
    "sg:classifiers":[
        {
            "category":"Utilities",
            "subcategory":"Water",
            "type":"Services"
        }
    ],
    "sg:phone":"+39 051 533986",
    "sg:postcode":"40138",
    "sg:province":"Bologna",
    "sg:tags":[
        "cleaner",
        "drinking",
        "system"
    ],
    "wof:name":"Idrotecno Srl",
    "wof:placetype":"venue"
},
  "geometry": {"coordinates":[11.346481,44.494221],"type":"Point"}
}