{
  "type": "Feature",
  "properties": {
    "iso:country":"IT",
    "sg:address":"20037 Paderno Dugnano",
    "sg:city":"Paderno Dugnano",
    "sg:orig_category":"Prodotti E Manufatti In Materie Plastiche",
    "sg:phone":"+39 02 910 3015",
    "sg:postcode":"20037",
    "sg:province":"Milano",
    "wof:name":"La Plexast Di Figini Elvezio",
    "wof:placetype":"venue"
},
  "geometry": {"coordinates":[9.1509504318,45.5588607788],"type":"Point"}
}