{
  "type": "Feature",
  "properties": {
    "addr:full":"20037 Paderno Dugnano Paderno Dugnano Milano 20037",
    "addr:postcode":"20037;20037",
    "iso:country":"IT",
    "sg:address":"20037 Paderno Dugnano",
    "sg:city":"Paderno Dugnano",
    "sg:orig_category":"Prodotti E Manufatti In Materie Plastiche",
    "sg:phone":"+39 02 9904 4109",
    "sg:postcode":"20037",
    "sg:province":"Milano",
    "wof:name":"Italplast Di Officioso Merendina",
    "wof:placetype":"venue"
},
  "geometry": {"coordinates":[9.1562318802,45.5625915527],"type":"Point"}
}