{
  "type": "Feature",
  "properties": {
    "iso:country":"IT",
    "sg:address":"Via Roma 7; Trichiana; 32028",
    "sg:city":"Trichiana",
    "sg:classifiers":[
        {
            "category":"Banks & Credit Unions",
            "subcategory":"Bank",
            "type":"Services"
        }
    ],
    "sg:phone":"+39 0437 754221",
    "sg:postcode":"32028",
    "sg:province":"Belluno",
    "wof:name":"Cariverona Banca Spa",
    "wof:placetype":"venue"
},
  "geometry": {"coordinates":[12.133545,46.074299],"type":"Point"}
}