{
  "type": "Feature",
  "properties": {
    "addr:full":"29, Via Dei Mille 06055 Marsciano Marsciano Perugia 06055",
    "addr:postcode":"06055;06055",
    "addr:street":"Via Dei Mille",
    "iso:country":"IT",
    "sg:address":"29, Via Dei Mille 06055 Marsciano",
    "sg:city":"Marsciano",
    "sg:classifiers":[
        {
            "category":"Shopping",
            "subcategory":"Clothing, Apparel, & Fashions",
            "type":"Retail Goods"
        }
    ],
    "sg:phone":"+39 075 874 9770",
    "sg:postcode":"06055",
    "sg:province":"Perugia",
    "sg:tags":[
        "clothes"
    ],
    "wof:name":"Punto Tre Srl",
    "wof:placetype":"venue"
},
  "geometry": {"coordinates":[12.332987,42.920086],"type":"Point"}
}