{
  "type": "Feature",
  "properties": {
    "iso:country":"IT",
    "sg:address":"1, Via Argonne 16145 Genova",
    "sg:city":"Genova",
    "sg:classifiers":[
        {
            "category":"Food & Beverages",
            "subcategory":"Groceries & Convenience Stores",
            "type":"Retail Goods"
        }
    ],
    "sg:phone":"+39 39010313849",
    "sg:postcode":"16145",
    "sg:province":"Genova",
    "sg:tags":[
        "drink"
    ],
    "wof:name":"Moon Import S.a.s.",
    "wof:placetype":"venue"
},
  "geometry": {"coordinates":[8.953623,44.396889],"type":"Point"}
}