{
  "type": "Feature",
  "properties": {
    "iso:country":"IT",
    "sg:address":"06083 Bastia",
    "sg:city":"Bastia",
    "sg:orig_category":"Automazione E Macchine Per Ufficio. Arredi Ed Attrezzature Per Attivita' Commerciali Ed Artigianali",
    "sg:phone":"+39 075 800 1419",
    "sg:postcode":"06083",
    "sg:province":"Perugia",
    "wof:name":"Desantisufficio Snc Di Leandro De Santis & C.",
    "wof:placetype":"venue"
},
  "geometry": {"coordinates":[12.549567,43.06638],"type":"Point"}
}