{
  "type": "Feature",
  "properties": {
    "iso:country":"IT",
    "sg:address":"45021 Badia Polesine",
    "sg:city":"Badia Polesine",
    "sg:classifiers":[
        {
            "category":"Manufacturing",
            "subcategory":"Tools & Machinery",
            "type":"Manufacturing & Wholesale Goods"
        }
    ],
    "sg:phone":"+39 0425 594457",
    "sg:postcode":"45021",
    "sg:province":"Rovigo",
    "sg:tags":[
        "leather",
        "equipment",
        "goods",
        "clothing"
    ],
    "sg:website":"http://www.filtecsas.it",
    "wof:name":"Filtec Di Baracco Giovanni & C. Sas",
    "wof:placetype":"venue"
},
  "geometry": {"coordinates":[11.485435,45.089157],"type":"Point"}
}