{
  "type": "Feature",
  "properties": {
    "iso:country":"IT",
    "sg:address":"00179 Roma",
    "sg:city":"Roma",
    "sg:orig_category":"Materiali Semilavorati Metallici",
    "sg:phone":"+39 06 788 6672",
    "sg:postcode":"00179",
    "sg:province":"Roma",
    "wof:name":"Striani Tende",
    "wof:placetype":"venue"
},
  "geometry": {"coordinates":[12.609404,41.675095],"type":"Point"}
}