{
  "type": "Feature",
  "properties": {
    "iso:country":"IT",
    "sg:address":"57124 Livorno",
    "sg:city":"Livorno",
    "sg:orig_category":"Automatismi Elettrici, Elettronici E Pneumatici",
    "sg:phone":"+39 0586 854725",
    "sg:postcode":"57124",
    "sg:province":"Livorno",
    "wof:name":"Cristiani Rossano",
    "wof:placetype":"venue"
},
  "geometry": {"coordinates":[10.337444,43.541187],"type":"Point"}
}