{
  "type": "Feature",
  "properties": {
    "iso:country":"IT",
    "sg:address":"24040 Ciserano",
    "sg:city":"Ciserano",
    "sg:orig_category":"Trattamenti Termici E Superficiali Metalli, Galvanotecnica",
    "sg:phone":"+39 035 884647",
    "sg:postcode":"24040",
    "sg:province":"Bergamo",
    "wof:name":"Alucolor Ox (s.r.l.)",
    "wof:placetype":"venue"
},
  "geometry": {"coordinates":[9.608953,45.591782],"type":"Point"}
}