{
  "type": "Feature",
  "properties": {
    "iso:country":"IT",
    "sg:address":"Via Cesano 27 20033 Desio",
    "sg:city":"Desio",
    "sg:classifiers":[
        {
            "category":"Military Area",
            "subcategory":"Air Force Base",
            "type":"Public Place"
        }
    ],
    "sg:phone":"+39 036 262 2190",
    "sg:postcode":"20033",
    "sg:province":"Milano",
    "sg:tags":[
        "electronic",
        "wound",
        "components"
    ],
    "wof:name":"E. Manzotti Sas",
    "wof:placetype":"venue"
},
  "geometry": {"coordinates":[9.189415,45.624733],"type":"Point"}
}