{
  "type": "Feature",
  "properties": {
    "addr:full":"Via Dottorina N 95; Gozzolina",
    "addr:housenumber":"95",
    "addr:street":"Via Dottorina N",
    "iso:country":"IT",
    "sg:address":"Via Dottorina N 95; Gozzolina",
    "sg:classifiers":[
        {
            "category":"Banks & Credit Unions",
            "subcategory":"Bank",
            "type":"Services"
        }
    ],
    "sg:phone":"+39 0376 631069",
    "wof:name":"Banca Agricola Mantovana Scarl",
    "wof:placetype":"venue"
},
  "geometry": {"coordinates":[10.486237,45.359428],"type":"Point"}
}