{
  "type": "Feature",
  "properties": {
    "addr:full":"20, Via Ca' Brusa' 37014 Castelnuovo Del Garda Castelnuovo del Garda Verona 37014",
    "addr:postcode":"37014;37014",
    "addr:street":"Via Ca ' Brusa '",
    "iso:country":"IT",
    "sg:address":"20, Via Ca' Brusa' 37014 Castelnuovo Del Garda",
    "sg:city":"Castelnuovo del Garda",
    "sg:classifiers":[
        {
            "category":"Manufacturing",
            "subcategory":"Tools & Machinery",
            "type":"Manufacturing & Wholesale Goods"
        }
    ],
    "sg:phone":"+39 045 757 5363",
    "sg:postcode":"37014",
    "sg:province":"Verona",
    "sg:tags":[
        "environment",
        "equipment",
        "-"
    ],
    "wof:name":"Martini Aeroimpianti (s.r.l.)",
    "wof:placetype":"venue"
},
  "geometry": {"coordinates":[10.764338,45.4245],"type":"Point"}
}