{
  "type": "Feature",
  "properties": {
    "addr:full":"30038 Spinea Spinea Venezia 30038",
    "addr:postcode":"30038;30038",
    "iso:country":"IT",
    "sg:address":"30038 Spinea",
    "sg:city":"Spinea",
    "sg:orig_category":"Trasporti E Spedizioni Merci",
    "sg:phone":"+39 041 999655",
    "sg:postcode":"30038",
    "sg:province":"Venezia",
    "wof:name":"Antonucci Trasporti Deperibili",
    "wof:placetype":"venue"
},
  "geometry": {"coordinates":[12.142241,45.501686],"type":"Point"}
}