{
  "type": "Feature",
  "properties": {
    "iso:country":"IT",
    "sg:address":"16, Via Sila 63018 Porto Sant'elpidio",
    "sg:classifiers":[
        {
            "category":"Personal",
            "subcategory":"Shoe Repair & Shine",
            "type":"Services"
        }
    ],
    "sg:phone":"+39 0734 991706",
    "sg:postcode":"63018",
    "sg:province":"Ascoli Piceno",
    "sg:tags":[
        "leather"
    ],
    "wof:name":"Calzaturificio Fra.ca Di Capponi & Pesaresi",
    "wof:placetype":"venue"
},
  "geometry": {"coordinates":[13.748096,43.252201],"type":"Point"}
}