{
  "type": "Feature",
  "properties": {
    "iso:country":"IT",
    "sg:address":"20122 Milano",
    "sg:city":"Milano",
    "sg:orig_category":"Pietre Dure Semipreziose - Lavorazione E Ingrosso",
    "sg:phone":"+39 02 5831 8040",
    "sg:postcode":"20122",
    "sg:province":"Milano",
    "wof:name":"Mineralgemme Di Antonucci & C. Sas",
    "wof:placetype":"venue"
},
  "geometry": {"coordinates":[9.2020950317,45.4522132874],"type":"Point"}
}