{
  "type": "Feature",
  "properties": {
    "iso:country":"IT",
    "sg:address":"43100 Parma",
    "sg:city":"Parma",
    "sg:orig_category":"Ospedali E Servizi Sanitari",
    "sg:phone":"+39 0521 228385",
    "sg:postcode":"43100",
    "sg:province":"Parma",
    "wof:name":"Bio-tech Biotechnology Laboratories Srl",
    "wof:placetype":"venue"
},
  "geometry": {"coordinates":[9.996408,44.693462],"type":"Point"}
}