{
  "type": "Feature",
  "properties": {
    "addr:full":"22, Via S. Pietro 26018 Trigolo Trigolo Cremona 26018",
    "addr:postcode":"26018;26018",
    "addr:street":"Via S. Pietro",
    "iso:country":"IT",
    "sg:address":"22, Via S. Pietro 26018 Trigolo",
    "sg:city":"Trigolo",
    "sg:classifiers":[
        {
            "category":"Manufacturing",
            "subcategory":"Rubber & Plastics",
            "type":"Manufacturing & Wholesale Goods"
        }
    ],
    "sg:phone":"+39 0374 370203",
    "sg:postcode":"26018",
    "sg:province":"Cremona",
    "wof:name":"C.m.p. (s.r.l.)",
    "wof:placetype":"venue"
},
  "geometry": {"coordinates":[10.026135,45.133499],"type":"Point"}
}