{
  "type": "Feature",
  "properties": {
    "addr:full":"26, Via Molini Emili 25030 Maclodio Maclodio Brescia 25030",
    "addr:postcode":"25030;25030",
    "addr:street":"Via Molini Emili",
    "iso:country":"IT",
    "sg:address":"26, Via Molini Emili 25030 Maclodio",
    "sg:city":"Maclodio",
    "sg:classifiers":[
        {
            "category":"Shopping",
            "subcategory":"Computers & Home Electronics",
            "type":"Retail Goods"
        }
    ],
    "sg:phone":"+39 39030978361",
    "sg:postcode":"25030",
    "sg:province":"Brescia",
    "sg:tags":[
        "electronic",
        "electrical",
        "equipment"
    ],
    "wof:name":"Piombifera Bresciana (s.p.a.)",
    "wof:placetype":"venue"
},
  "geometry": {"coordinates":[10.222958,45.539829],"type":"Point"}
}