{
  "type": "Feature",
  "properties": {
    "addr:full":"18, C. Novara 10078 Venaria Torino 10078",
    "addr:housenumber":"18",
    "addr:postcode":"10078;10078",
    "addr:street":"C. Novara",
    "iso:country":"IT",
    "sg:address":"18, C. Novara 10078 Venaria",
    "sg:classifiers":[
        {
            "category":"Shopping",
            "type":"Retail Goods"
        }
    ],
    "sg:phone":"+39 011 424 0673",
    "sg:postcode":"10078",
    "sg:province":"Torino",
    "sg:tags":[
        "finished",
        "-",
        "metallic"
    ],
    "sg:website":"http://www.ellemme.biz:ws_end: :mark:ws:http://www.paginegialle.it/ellemme-to",
    "wof:name":"Lm Srl",
    "wof:placetype":"venue"
},
  "geometry": {"coordinates":[7.6336064339,45.115688324],"type":"Point"}
}