{
  "type": "Feature",
  "properties": {
    "addr:full":"42023 Cadelbosco Di Sopra Reggio Nell'Emilia 42023",
    "addr:postcode":"42023;42023",
    "iso:country":"IT",
    "sg:address":"42023 Cadelbosco Di Sopra",
    "sg:orig_category":"Elettrotecnica Industriale, Prodotti E Apparecchiature",
    "sg:phone":"+39 0522 917925",
    "sg:postcode":"42023",
    "sg:province":"Reggio Nell'Emilia",
    "sg:website":"http://www.tmt-prefabbricati.it",
    "wof:name":"T.m.t. Prefabbricati Metallici Srl",
    "wof:placetype":"venue"
},
  "geometry": {"coordinates":[10.599562,44.753254],"type":"Point"}
}