{
  "type": "Feature",
  "properties": {
    "addr:full":"08100 Nuoro Nuoro Nuoro 08100",
    "addr:postcode":"08100;08100",
    "iso:country":"IT",
    "sg:address":"08100 Nuoro",
    "sg:city":"Nuoro",
    "sg:classifiers":[
        {
            "category":"Shopping",
            "subcategory":"Stationery & Office Supplies",
            "type":"Retail Goods"
        }
    ],
    "sg:phone":"+39 0784 31102",
    "sg:postcode":"08100",
    "sg:province":"Nuoro",
    "sg:tags":[
        "making",
        "watch",
        "clock"
    ],
    "sg:website":"http://www.gioielleriarosas.com",
    "wof:name":"Gioielleria Rosas Sas",
    "wof:placetype":"venue"
},
  "geometry": {"coordinates":[9.333573,40.321194],"type":"Point"}
}