{
  "type": "Feature",
  "properties": {
    "iso:country":"IT",
    "sg:address":"20139 Milano",
    "sg:city":"Milano",
    "sg:orig_category":"Servizi E Lavori Per Arredamento E Industria Del Legno. Servizi E Lavori Per Edilizia E Lavori Pubblici",
    "sg:phone":"+39 02 537335",
    "sg:postcode":"20139",
    "sg:province":"Milano",
    "wof:name":"Episcopo Nicola",
    "wof:placetype":"venue"
},
  "geometry": {"coordinates":[9.227516,45.428825],"type":"Point"}
}