{
  "type": "Feature",
  "properties": {
    "addr:full":"93010 Campofranco Campofranco Caltanissetta 93010",
    "addr:postcode":"93010;93010",
    "iso:country":"IT",
    "sg:address":"93010 Campofranco",
    "sg:city":"Campofranco",
    "sg:orig_category":"Automobili - Commercio",
    "sg:phone":"+39 0934 999314",
    "sg:postcode":"93010",
    "sg:province":"Caltanissetta",
    "wof:name":"Mondial Car Srl",
    "wof:placetype":"venue"
},
  "geometry": {"coordinates":[13.713577,37.512325],"type":"Point"}
}