{
  "type": "Feature",
  "properties": {
    "iso:country":"IT",
    "sg:address":"35010 Loreggia",
    "sg:city":"Loreggia",
    "sg:orig_category":"Agenzie D'affari E Servizi Commerciali. Avvocati, Notai E Servizi Legali. Consulenze Tecniche, Amministrative E Perizie",
    "sg:phone":"+39 049 579 2457",
    "sg:postcode":"35010",
    "sg:province":"Padova",
    "wof:name":"Chiaro & Chiaro Service Sas",
    "wof:placetype":"venue"
},
  "geometry": {"coordinates":[11.946278,45.595001],"type":"Point"}
}