{
  "type": "Feature",
  "properties": {
    "iso:country":"IT",
    "sg:address":"Via Giosue' Carducci 11 21045 Gazzada",
    "sg:city":"Gazzada",
    "sg:orig_category":"Plastics, Granulated",
    "sg:phone":"+39 0332 461096",
    "sg:postcode":"21045",
    "sg:province":"Varese",
    "wof:name":"Gibaplast Sas Di Barbieri Giovanni",
    "wof:placetype":"venue"
},
  "geometry": {"coordinates":[8.8184919357,45.7708740234],"type":"Point"}
}