{
  "type": "Feature",
  "properties": {
    "addr:full":"12, Via Villetta Stra' 13881 Cavaglia' Biella 13881",
    "addr:postcode":"13881;13881",
    "addr:street":"Via Villetta Stra ';' Biella",
    "iso:country":"IT",
    "sg:address":"12, Via Villetta Stra' 13881 Cavaglia'",
    "sg:classifiers":[
        {
            "category":"Manufacturing",
            "subcategory":"Metals",
            "type":"Manufacturing & Wholesale Goods"
        }
    ],
    "sg:phone":"+39 39016196044",
    "sg:postcode":"13881",
    "sg:province":"Biella",
    "sg:tags":[
        "metallurgy",
        "metalworking"
    ],
    "wof:name":"Machieraldo Gustavo (s.p.a.)",
    "wof:placetype":"venue"
},
  "geometry": {"coordinates":[8.0845060349,45.4082984924],"type":"Point"}
}