{
  "type": "Feature",
  "properties": {
    "iso:country":"IT",
    "sg:address":"00023 Arsoli",
    "sg:city":"Arsoli",
    "sg:orig_category":"Macchine, Impianti Ed Attrezzature Industria Chimica. Valvole E Apparecchiature Di Misura",
    "sg:phone":"+39 0774 920215",
    "sg:postcode":"00023",
    "sg:province":"Roma",
    "wof:name":"Seven Seas Sas",
    "wof:placetype":"venue"
},
  "geometry": {"coordinates":[13.014069,42.043072],"type":"Point"}
}