{
  "type": "Feature",
  "properties": {
    "addr:full":"95, Via Giovanni Xxiii Papa 28845 Domodossola Domodossola Verbano-Cusio-Ossola 28845",
    "addr:postcode":"28845;28845",
    "addr:street":"Via Giovanni Xxiii Papa",
    "iso:country":"IT",
    "sg:address":"95, Via Giovanni Xxiii Papa 28845 Domodossola",
    "sg:city":"Domodossola",
    "sg:classifiers":[
        {
            "category":"Travel",
            "subcategory":"Travel Agent",
            "type":"Entertainment"
        }
    ],
    "sg:phone":"+39 0324 243081",
    "sg:postcode":"28845",
    "sg:province":"Verbano-Cusio-Ossola",
    "sg:tags":[
        "business"
    ],
    "wof:name":"Albergo Residence Mafalda",
    "wof:placetype":"venue"
},
  "geometry": {"coordinates":[8.272465,46.139969],"type":"Point"}
}