{
  "type": "Feature",
  "properties": {
    "addr:full":"53045 Montepulciano Montepulciano Siena 53045",
    "addr:postcode":"53045;53045",
    "iso:country":"IT",
    "sg:address":"53045 Montepulciano",
    "sg:city":"Montepulciano",
    "sg:orig_category":"Scuole E Servizi Scolastici",
    "sg:phone":"+39 0578 717020",
    "sg:postcode":"53045",
    "sg:province":"Siena",
    "wof:name":"Conservatorio S. Girolamo",
    "wof:placetype":"venue"
},
  "geometry": {"coordinates":[11.78535,43.096443],"type":"Point"}
}