{
  "type": "Feature",
  "properties": {
    "addr:full":"5, Via Calvi Di Coenzo 42100 Reggio Emilia Reggio Nell'Emilia 42100",
    "addr:postcode":"42100;42100",
    "addr:street":"Via Calvi Di Coenzo",
    "iso:country":"IT",
    "sg:address":"5, Via Calvi Di Coenzo 42100 Reggio Emilia",
    "sg:classifiers":[
        {
            "category":"Real Estate",
            "subcategory":"Architect",
            "type":"Services"
        }
    ],
    "sg:phone":"+39 0522 509111",
    "sg:postcode":"42100",
    "sg:province":"Reggio Nell'Emilia",
    "sg:tags":[
        "textile",
        "clothing"
    ],
    "wof:name":"Imax (s.r.l.)",
    "wof:placetype":"venue"
},
  "geometry": {"coordinates":[10.652098,44.739048],"type":"Point"}
}