{
  "type": "Feature",
  "properties": {
    "addr:full":"70121 Bari Bari Bari 70121",
    "addr:postcode":"70121;70121",
    "iso:country":"IT",
    "sg:address":"70121 Bari",
    "sg:city":"Bari",
    "sg:orig_category":"Forniture Per Abbigliamento E Pelletterie",
    "sg:phone":"+39 080 523 1685",
    "sg:postcode":"70121",
    "sg:province":"Bari",
    "wof:name":"Angil Srl Casa & Casa",
    "wof:placetype":"venue"
},
  "geometry": {"coordinates":[16.8697242737,41.1217422485],"type":"Point"}
}