{
  "type": "Feature",
  "properties": {
    "addr:full":"80131 Napoli Napoli Napoli 80131",
    "addr:housenumber":"80131",
    "addr:postcode":"80131",
    "iso:country":"IT",
    "sg:address":"80131 Napoli",
    "sg:city":"Napoli",
    "sg:orig_category":"Servizi E Lavori Industria Della Gomma",
    "sg:phone":"+39 081 546 6862",
    "sg:postcode":"80131",
    "sg:province":"Napoli",
    "wof:name":"Punzolo Salvatore",
    "wof:placetype":"venue"
},
  "geometry": {"coordinates":[14.221587,40.861561],"type":"Point"}
}