{
  "type": "Feature",
  "properties": {
    "iso:country":"IT",
    "sg:address":"22, Via Dell' Imbrecciato 00149 Roma",
    "sg:city":"Roma",
    "sg:classifiers":[
        {
            "category":"Professional",
            "subcategory":"Computer Services",
            "type":"Services"
        }
    ],
    "sg:phone":"+39 39065501682",
    "sg:postcode":"00149",
    "sg:province":"Roma",
    "sg:tags":[
        "information",
        "technology"
    ],
    "wof:name":"Semac Srl",
    "wof:placetype":"venue"
},
  "geometry": {"coordinates":[12.448318,41.844757],"type":"Point"}
}