{
  "type": "Feature",
  "properties": {
    "iso:country":"IT",
    "sg:address":"28016 Orta San Giulio",
    "sg:city":"Orta San Giulio",
    "sg:classifiers":[
        {
            "category":"Professional",
            "subcategory":"Business Services",
            "type":"Services"
        }
    ],
    "sg:phone":"+39 0322 911977",
    "sg:postcode":"28016",
    "sg:province":"Novara",
    "sg:tags":[
        "support",
        "companies",
        "events",
        "trade"
    ],
    "sg:website":"http://www.hotelsanrocco.it",
    "wof:name":"Hotel San Rocco",
    "wof:placetype":"venue"
},
  "geometry": {"coordinates":[8.404902,45.800655],"type":"Point"}
}