{
  "type": "Feature",
  "properties": {
    "iso:country":"IT",
    "sg:address":"40068 San Lazzaro Di Savena",
    "sg:city":"San Lazzaro",
    "sg:classifiers":[
        {
            "category":"Manufacturing",
            "subcategory":"Tools & Machinery",
            "type":"Manufacturing & Wholesale Goods"
        }
    ],
    "sg:phone":"+39 051 463093",
    "sg:postcode":"40068",
    "sg:province":"Bologna",
    "sg:tags":[
        "machining",
        "mechanical"
    ],
    "wof:name":"Fiocchi Libero Srl",
    "wof:placetype":"venue"
},
  "geometry": {"coordinates":[11.411803,44.477028],"type":"Point"}
}