{
  "type": "Feature",
  "properties": {
    "iso:country":"IT",
    "sg:address":"66100 Chieti",
    "sg:city":"Chieti",
    "sg:orig_category":"Elettronica Professionale E Di Consumo. Musica",
    "sg:phone":"+39 0871 574926",
    "sg:postcode":"66100",
    "sg:province":"Chieti",
    "wof:name":"Pm Acoustic",
    "wof:placetype":"venue"
},
  "geometry": {"coordinates":[14.14131,42.364925],"type":"Point"}
}