{
  "type": "Feature",
  "properties": {
    "iso:country":"IT",
    "sg:address":"41049 Sassuolo",
    "sg:city":"Sassuolo",
    "sg:orig_category":"Apparecchiature E Sistemi Per Magazzinaggio E Movimentazione",
    "sg:phone":"+39 0536 800214",
    "sg:postcode":"41049",
    "sg:province":"Modena",
    "wof:name":"Martinelli Ettore Srl",
    "wof:placetype":"venue"
},
  "geometry": {"coordinates":[10.899242,44.656029],"type":"Point"}
}