{
  "type": "Feature",
  "properties": {
    "addr:full":"00183 Roma Roma Roma 00183",
    "addr:postcode":"00183;00183",
    "iso:country":"IT",
    "sg:address":"00183 Roma",
    "sg:city":"Roma",
    "sg:orig_category":"Ricambi E Componenti Dei Mezzi Di Trasporto",
    "sg:phone":"+39 06 700 4736",
    "sg:postcode":"00183",
    "sg:province":"Roma",
    "wof:name":"Terranova Rodolfo",
    "wof:placetype":"venue"
},
  "geometry": {"coordinates":[12.507798,41.87532],"type":"Point"}
}