{
  "type": "Feature",
  "properties": {
    "iso:country":"IT",
    "sg:address":"22066 Mariano Comense",
    "sg:city":"Mariano Comense",
    "sg:orig_category":"Macchine E Forniture Per Arredamento E Industria Del Legno",
    "sg:phone":"+39 031 751983",
    "sg:postcode":"22066",
    "sg:province":"Como",
    "wof:name":"Bi Matic (s.r.l.)",
    "wof:placetype":"venue"
},
  "geometry": {"coordinates":[9.172735,45.705784],"type":"Point"}
}