{
  "type": "Feature",
  "properties": {
    "iso:country":"IT",
    "sg:address":"Via Carnovali Giovanni 93 24126 Bergamo",
    "sg:city":"Bergamo",
    "sg:classifiers":[
        {
            "category":"Shopping",
            "subcategory":"Clothing, Apparel, & Fashions",
            "type":"Retail Goods"
        }
    ],
    "sg:phone":"+39 035 319381",
    "sg:postcode":"24126",
    "sg:province":"Bergamo",
    "sg:tags":[
        "blouse",
        "ladies'",
        "dress"
    ],
    "wof:name":"Texbo S.r.l.",
    "wof:placetype":"venue"
},
  "geometry": {"coordinates":[9.669952,45.694904],"type":"Point"}
}