{
  "type": "Feature",
  "properties": {
    "iso:country":"IT",
    "sg:address":"33050 Pavia Di Udine",
    "sg:city":"Pavia di Udine",
    "sg:orig_category":"Suites, Armchairs, Chairs And Tables",
    "sg:phone":"+39 0432 676368",
    "sg:postcode":"33050",
    "sg:province":"Udine",
    "sg:website":"http://www.lestuzzi.it",
    "wof:name":"Lestuzzi Fratelli Srl",
    "wof:placetype":"venue"
},
  "geometry": {"coordinates":[13.305166,45.997372],"type":"Point"}
}