{
  "type": "Feature",
  "properties": {
    "addr:full":"Viale Eginardo 29, 20149 Milan, Mi Milano 20149",
    "addr:housenumber":"29",
    "addr:postcode":"20149;20149",
    "addr:street":"Viale Eginardo",
    "iso:country":"IT",
    "sg:address":"Viale Eginardo 29, 20149 Milan, Mi",
    "sg:classifiers":[
        {
            "category":"Banks & Credit Unions",
            "subcategory":"Bank",
            "type":"Services"
        }
    ],
    "sg:postcode":"20149",
    "sg:province":"Milano",
    "wof:name":"Banca Akros Spa",
    "wof:placetype":"venue"
},
  "geometry": {"coordinates":[9.151542,45.480457],"type":"Point"}
}