{
  "type": "Feature",
  "properties": {
    "addr:full":"04011 Aprilia Aprilia Latina 04011",
    "addr:postcode":"04011;04011",
    "iso:country":"IT",
    "sg:address":"04011 Aprilia",
    "sg:city":"Aprilia",
    "sg:classifiers":[
        {
            "category":"Health Services",
            "subcategory":"Health Practitioner",
            "type":"Services"
        }
    ],
    "sg:phone":"+39 06 9290 3131",
    "sg:postcode":"04011",
    "sg:province":"Latina",
    "sg:tags":[
        "medici"
    ],
    "wof:name":"Prevenzione S. Andrea Di Bruschini F. & Ciancaglini G. Snc",
    "wof:placetype":"venue"
},
  "geometry": {"coordinates":[12.764919281,41.5521965027],"type":"Point"}
}