{
  "type": "Feature",
  "properties": {
    "addr:full":"20060 Gessate Gessate Milano 20060",
    "addr:postcode":"20060;20060",
    "iso:country":"IT",
    "sg:address":"20060 Gessate",
    "sg:city":"Gessate",
    "sg:orig_category":"Forniture Per Agricoltura E Zootecnia. Animali Domestici",
    "sg:phone":"+39 02 9578 1450",
    "sg:postcode":"20060",
    "sg:province":"Milano",
    "wof:name":"Piccioni (s.n.c.)",
    "wof:placetype":"venue"
},
  "geometry": {"coordinates":[9.4349880219,45.555770874],"type":"Point"}
}