{
  "type": "Feature",
  "properties": {
    "iso:country":"IT",
    "sg:address":"09045 Quartu Sant'elena",
    "sg:orig_category":"Arredamenti E Mobili Professionali. Arredi Ed Attrezzature Per Uffici",
    "sg:phone":"+39 070 881146",
    "sg:postcode":"09045",
    "sg:province":"Cagliari",
    "wof:name":"Franz Mobili Srl",
    "wof:placetype":"venue"
},
  "geometry": {"coordinates":[9.17361,39.24292],"type":"Point"}
}