{
  "type": "Feature",
  "properties": {
    "iso:country":"IT",
    "sg:address":"14, Corso Spagna 35127 Padova",
    "sg:city":"Padova",
    "sg:classifiers":[
        {
            "category":"Marine",
            "type":"Transportation"
        }
    ],
    "sg:phone":"+39 049 870 3325",
    "sg:postcode":"35127",
    "sg:province":"Padova",
    "sg:tags":[
        "transport",
        "sea"
    ],
    "wof:name":"Dgt World Srl",
    "wof:placetype":"venue"
},
  "geometry": {"coordinates":[11.923043,45.353905],"type":"Point"}
}