{
  "type": "Feature",
  "properties": {
    "addr:full":"10146 Torino Torino Torino 10146",
    "addr:postcode":"10146;10146",
    "iso:country":"IT",
    "sg:address":"10146 Torino",
    "sg:city":"Torino",
    "sg:orig_category":"Attrezzature E Forniture Per Officine Riparazione E Servizi Ausiliari",
    "sg:phone":"+39 011 749 5758",
    "sg:postcode":"10146",
    "sg:province":"Torino",
    "wof:name":"Granata Antonio",
    "wof:placetype":"venue"
},
  "geometry": {"coordinates":[7.120077,45.126019],"type":"Point"}
}