{
  "type": "Feature",
  "properties": {
    "iso:country":"IT",
    "sg:address":"10090 S.raffaele Cimena",
    "sg:orig_category":"Imballaggi In Cartone",
    "sg:phone":"+39 011 981 1270",
    "sg:postcode":"10090",
    "sg:province":"Torino",
    "sg:website":"http://www.scatolificiomonterosa.com",
    "wof:name":"Scatolificio Monterosa Srl",
    "wof:placetype":"venue"
},
  "geometry": {"coordinates":[7.783453,45.136497],"type":"Point"}
}