{
  "type": "Feature",
  "properties": {
    "iso:country":"IT",
    "sg:address":"38100 Trento",
    "sg:city":"Trento",
    "sg:classifiers":[
        {
            "category":"Restaurant",
            "type":"Food & Drink"
        }
    ],
    "sg:phone":"+39 0461 822245",
    "sg:postcode":"38100",
    "sg:province":"Trento",
    "sg:tags":[
        "supplies",
        "product",
        "chemicals",
        "industry",
        "basic"
    ],
    "wof:name":"Vedal Srl",
    "wof:placetype":"venue"
},
  "geometry": {"coordinates":[11.104388237,46.092716217],"type":"Point"}
}