{
  "type": "Feature",
  "properties": {
    "iso:country":"IT",
    "sg:address":"00196 Roma",
    "sg:city":"Roma",
    "sg:orig_category":"Servizi Al Turismo. Ambasciate Ed Enti Internazionali",
    "sg:phone":"+39 06 323 1840",
    "sg:postcode":"00196",
    "sg:province":"Roma",
    "wof:name":"Consolato Islanda",
    "wof:placetype":"venue"
},
  "geometry": {"coordinates":[12.467323,41.932781],"type":"Point"}
}