{
  "type": "Feature",
  "properties": {
    "iso:country":"IT",
    "sg:address":"31023 Resana",
    "sg:city":"Resana",
    "sg:orig_category":"Imprese Di Costruzioni Civili Ed Industriali",
    "sg:phone":"+39 0423 720371",
    "sg:postcode":"31023",
    "sg:province":"Treviso",
    "sg:website":"http://www.vecchiato.com",
    "wof:name":"Prof. Pietro Vecchiato Spa",
    "wof:placetype":"venue"
},
  "geometry": {"coordinates":[12.09551,45.655888],"type":"Point"}
}