{
  "type": "Feature",
  "properties": {
    "iso:country":"IT",
    "sg:address":"1, Via Cimitero 10092 Beinasco",
    "sg:city":"Beinasco",
    "sg:classifiers":[
        {
            "category":"Wholesale",
            "subcategory":"Drugs",
            "type":"Manufacturing & Wholesale Goods"
        }
    ],
    "sg:phone":"+39 390 113 4011",
    "sg:postcode":"10092",
    "sg:province":"Torino",
    "sg:tags":[
        "chemical",
        "pharmaceutical"
    ],
    "wof:name":"Vagnone & Boeri (s.r.l.)",
    "wof:placetype":"venue"
},
  "geometry": {"coordinates":[7.597305,45.009609],"type":"Point"}
}