{
  "type": "Feature",
  "properties": {
    "addr:full":"Via Del Lavoro 67 40033 Casalecchio Di Reno Casalecchio di Reno Bologna 40033",
    "addr:housenumber":"67",
    "addr:postcode":"40033;40033",
    "addr:street":"Via Del Lavoro;Di Reno",
    "iso:country":"IT",
    "sg:address":"Via Del Lavoro 67 40033 Casalecchio Di Reno",
    "sg:city":"Casalecchio di Reno",
    "sg:classifiers":[
        {
            "category":"Professional",
            "subcategory":"Employment Agencies",
            "type":"Services"
        }
    ],
    "sg:phone":"+39 051 571717",
    "sg:postcode":"40033",
    "sg:province":"Bologna",
    "sg:tags":[
        "overseas",
        "shipping"
    ],
    "sg:website":"www.emilcargo.com",
    "wof:name":"Emilcargo Srl",
    "wof:placetype":"venue"
},
  "geometry": {"coordinates":[11.25895,44.488422],"type":"Point"}
}