{
  "type": "Feature",
  "properties": {
    "addr:full":"28041 Arona Arona Novara 28041",
    "addr:postcode":"28041;28041",
    "iso:country":"IT",
    "sg:address":"28041 Arona",
    "sg:city":"Arona",
    "sg:orig_category":"Musica",
    "sg:phone":"+39 0322 242179",
    "sg:postcode":"28041",
    "sg:province":"Novara",
    "wof:name":"De Giuliani Giovanni",
    "wof:placetype":"venue"
},
  "geometry": {"coordinates":[8.556643486,45.7477836609],"type":"Point"}
}