{
  "type": "Feature",
  "properties": {
    "iso:country":"IT",
    "sg:address":"Via A. Salieri 4 37050 Oppeano",
    "sg:city":"Oppeano",
    "sg:classifiers":[
        {
            "category":"Manufacturing",
            "subcategory":"Printing",
            "type":"Manufacturing & Wholesale Goods"
        }
    ],
    "sg:phone":"+39 045 699 7555",
    "sg:postcode":"37050",
    "sg:province":"Verona",
    "sg:tags":[
        "plate",
        "offset"
    ],
    "sg:website":"www.lastragroup.com",
    "wof:name":"Plurimetal Srl",
    "wof:placetype":"venue"
},
  "geometry": {"coordinates":[11.060934,45.348042],"type":"Point"}
}