{
  "type": "Feature",
  "properties": {
    "iso:country":"IT",
    "sg:address":"40033 Casalecchio Di Reno",
    "sg:city":"Casalecchio di Reno",
    "sg:orig_category":"Impianti, Attrezzature E Forniture Sanitarie Ed Ospedaliere",
    "sg:phone":"+39 051 619 5747",
    "sg:postcode":"40033",
    "sg:province":"Bologna",
    "wof:name":"Gamberini Srl",
    "wof:placetype":"venue"
},
  "geometry": {"coordinates":[11.286526,44.484917],"type":"Point"}
}