{
  "type": "Feature",
  "properties": {
    "addr:full":"30030 Fosso' Venezia 30030",
    "addr:postcode":"30030;30030",
    "addr:street":"Fosso ' Venezia",
    "iso:country":"IT",
    "sg:address":"30030 Fosso'",
    "sg:orig_category":"Servizi E Lavori Industria Della Gomma. Servizi E Lavori Industria Delle Materie Plastiche. Forniture Per Edilizia E Lavori Pubblici",
    "sg:phone":"+39 041 416 5856",
    "sg:postcode":"30030",
    "sg:province":"Venezia",
    "wof:name":"Futurplastic S.n.c.",
    "wof:placetype":"venue"
},
  "geometry": {"coordinates":[12.050482,45.386276],"type":"Point"}
}