{
  "type": "Feature",
  "properties": {
    "iso:country":"IT",
    "sg:address":"20154 Milano",
    "sg:city":"Milano",
    "sg:orig_category":"Articoli Medico-sanitari Ed Ortopedici",
    "sg:phone":"+39 02 3310 5347",
    "sg:postcode":"20154",
    "sg:province":"Milano",
    "wof:name":"Centro Acustico Monaco Di Monaco Carmelo & C. (s.a.s.)",
    "wof:placetype":"venue"
},
  "geometry": {"coordinates":[9.174948,45.479061],"type":"Point"}
}