{
  "type": "Feature",
  "properties": {
    "iso:country":"IT",
    "sg:address":"Via Tulipani 00041 Albano Laziale",
    "sg:city":"Albano Laziale",
    "sg:classifiers":[
        {
            "category":"Food & Beverages",
            "subcategory":"Groceries & Convenience Stores",
            "type":"Retail Goods"
        }
    ],
    "sg:phone":"+39 39069343944",
    "sg:postcode":"00041",
    "sg:province":"Roma",
    "sg:tags":[
        "product",
        "related"
    ],
    "wof:name":"L'oasi Del Tortellino",
    "wof:placetype":"venue"
},
  "geometry": {"coordinates":[12.6155939102,41.733165741],"type":"Point"}
}