{
  "type": "Feature",
  "properties": {
    "addr:full":"131, Via Milano 20033 Desio Desio Milano 20033",
    "addr:housenumber":"131",
    "addr:postcode":"20033;20033",
    "addr:street":"Via Milano",
    "iso:country":"IT",
    "sg:address":"131, Via Milano 20033 Desio",
    "sg:city":"Desio",
    "sg:classifiers":[
        {
            "category":"Personal",
            "subcategory":"Shoe Repair & Shine",
            "type":"Services"
        }
    ],
    "sg:phone":"+39 036 262 2149",
    "sg:postcode":"20033",
    "sg:province":"Milano",
    "sg:tags":[
        "leather"
    ],
    "wof:name":"Calzaturificio Arpa (s.n.c.)",
    "wof:placetype":"venue"
},
  "geometry": {"coordinates":[9.201225,45.612179],"type":"Point"}
}