{
  "type": "Feature",
  "properties": {
    "iso:country":"IT",
    "sg:address":"10, Regione Brasse Piccolo 12033 Moretta",
    "sg:city":"Moretta",
    "sg:classifiers":[
        {
            "category":"Manufacturing",
            "subcategory":"Aerospace",
            "type":"Manufacturing & Wholesale Goods"
        }
    ],
    "sg:phone":"+39 39017294322",
    "sg:postcode":"12033",
    "sg:province":"Cuneo",
    "sg:tags":[
        "aeronautic"
    ],
    "wof:name":"Vanzetti Engineering S.r.l.",
    "wof:placetype":"venue"
},
  "geometry": {"coordinates":[7.532536,44.752487],"type":"Point"}
}