{
  "type": "Feature",
  "properties": {
    "addr:full":"40126 Bologna Bologna Bologna 40126",
    "addr:postcode":"40126;40126",
    "iso:country":"IT",
    "sg:address":"40126 Bologna",
    "sg:city":"Bologna",
    "sg:orig_category":"Ristorazione E Locali Pubblici Affini. Ristoranti Ed Esercizi Affini",
    "sg:phone":"+39 051 237718",
    "sg:postcode":"40126",
    "sg:province":"Bologna",
    "wof:name":"Erib Di Sacchetti Enrico & C. Sas",
    "wof:placetype":"venue"
},
  "geometry": {"coordinates":[11.346722,44.494911],"type":"Point"}
}