{
  "type": "Feature",
  "properties": {
    "iso:country":"IT",
    "sg:address":"80040 Poggiomarino",
    "sg:city":"Poggiomarino",
    "sg:orig_category":"Forniture Per Abbigliamento E Pelletterie",
    "sg:phone":"+39 081 528 4205",
    "sg:postcode":"80040",
    "sg:province":"Napoli",
    "wof:name":"Sartoria Di Luggo Gerardo",
    "wof:placetype":"venue"
},
  "geometry": {"coordinates":[14.543586731,40.8032951355],"type":"Point"}
}