{
  "type": "Feature",
  "properties": {
    "iso:country":"IT",
    "sg:address":"Via Togni 25064 Gussago",
    "sg:city":"Gussago",
    "sg:classifiers":[
        {
            "category":"Food & Beverages",
            "subcategory":"Groceries & Convenience Stores",
            "type":"Retail Goods"
        }
    ],
    "sg:phone":"+39 030 373 3091",
    "sg:postcode":"25064",
    "sg:province":"Brescia",
    "sg:tags":[
        "product",
        "related"
    ],
    "wof:name":"Leonessa Industria Dolciaria S.r.l.",
    "wof:placetype":"venue"
},
  "geometry": {"coordinates":[10.1445636749,45.5646133423],"type":"Point"}
}