{
  "type": "Feature",
  "properties": {
    "iso:country":"IT",
    "sg:address":"41100 Modena",
    "sg:city":"Modena",
    "sg:orig_category":"Lavorazioni Metalli, Stampaggio E Saldatura",
    "sg:phone":"+39 059 454640",
    "sg:postcode":"41100",
    "sg:province":"Modena",
    "sg:website":"http://www.meccanicabaraldi.it",
    "wof:name":"Meccanica Baraldi Srl",
    "wof:placetype":"venue"
},
  "geometry": {"coordinates":[10.939271,44.671471],"type":"Point"}
}