{
  "type": "Feature",
  "properties": {
    "addr:full":"419, Via Fiorentina 51100 Pistoia Pistoia Pistoia 51100",
    "addr:housenumber":"419",
    "addr:postcode":"51100;51100",
    "addr:street":"Via Fiorentina",
    "iso:country":"IT",
    "sg:address":"419, Via Fiorentina 51100 Pistoia",
    "sg:city":"Pistoia",
    "sg:classifiers":[
        {
            "category":"Food & Beverages",
            "subcategory":"Bakery",
            "type":"Retail Goods"
        }
    ],
    "sg:phone":"+39 0573 545141",
    "sg:postcode":"51100",
    "sg:province":"Pistoia",
    "sg:tags":[
        "grain",
        "cereal"
    ],
    "wof:name":"Nove Alpi Di Bolognesi Grazia E C. Srl",
    "wof:placetype":"venue"
},
  "geometry": {"coordinates":[10.94745,43.902004],"type":"Point"}
}