{
  "type": "Feature",
  "properties": {
    "iso:country":"IT",
    "sg:address":"00185 Roma",
    "sg:city":"Roma",
    "sg:classifiers":[
        {
            "category":"Health Services",
            "subcategory":"Health Practitioner",
            "type":"Services"
        }
    ],
    "sg:phone":"+39 06 446 5259",
    "sg:postcode":"00185",
    "sg:province":"Roma",
    "sg:tags":[
        "medici"
    ],
    "wof:name":"Vizzaccaro Massimo",
    "wof:placetype":"venue"
},
  "geometry": {"coordinates":[12.5034189224,41.8985786438],"type":"Point"}
}