{
  "type": "Feature",
  "properties": {
    "iso:country":"IT",
    "sg:address":"10024 Moncalieri",
    "sg:city":"Moncalieri",
    "sg:orig_category":"Assemblaggio Conto Terzi",
    "sg:phone":"+39 011 646012",
    "sg:postcode":"10024",
    "sg:province":"Torino",
    "wof:name":"Capello Giuseppe Di Capello Guido & C. Snc",
    "wof:placetype":"venue"
},
  "geometry": {"coordinates":[7.670582,44.980469],"type":"Point"}
}