{
  "type": "Feature",
  "properties": {
    "addr:full":"Via Vettabbia 7 20122 Milano Milano Milano 20122",
    "addr:housenumber":"7",
    "addr:postcode":"20122;20122",
    "addr:street":"Via Vettabbia",
    "iso:country":"IT",
    "sg:address":"Via Vettabbia 7 20122 Milano",
    "sg:city":"Milano",
    "sg:classifiers":[
        {
            "category":"Wholesale",
            "subcategory":"Books, Periodicals, & Newspapers",
            "type":"Manufacturing & Wholesale Goods"
        }
    ],
    "sg:phone":"+39 02 5831 0413",
    "sg:postcode":"20122",
    "sg:province":"Milano",
    "sg:tags":[
        "professional",
        "journal",
        "journals",
        "publisher"
    ],
    "sg:website":"www.manidifata.it",
    "wof:name":"Casa Editrice Mani Di Fata Srl",
    "wof:placetype":"venue"
},
  "geometry": {"coordinates":[9.1842718124,45.4557418823],"type":"Point"}
}