{
  "type": "Feature",
  "properties": {
    "addr:full":"Via Emilia 9/11; Tortona; 15057 Tortona Alessandria 15057",
    "addr:housenumber":"9 / 11",
    "addr:postcode":"15057;15057",
    "addr:street":"Via Emilia",
    "iso:country":"IT",
    "sg:address":"Via Emilia 9/11; Tortona; 15057",
    "sg:city":"Tortona",
    "sg:classifiers":[
        {
            "category":"Banks & Credit Unions",
            "subcategory":"Bank",
            "type":"Services"
        }
    ],
    "sg:phone":"+39 0131 821220",
    "sg:postcode":"15057",
    "sg:province":"Alessandria",
    "wof:name":"Cassa Di Risparmio Di Alessandria Spa",
    "wof:placetype":"venue"
},
  "geometry": {"coordinates":[8.862638,44.893986],"type":"Point"}
}