{
  "type": "Feature",
  "properties": {
    "addr:full":"10155 Torino Torino Torino 10155",
    "addr:postcode":"10155;10155",
    "iso:country":"IT",
    "sg:address":"10155 Torino",
    "sg:city":"Torino",
    "sg:orig_category":"Forniture Per Edilizia E Lavori Pubblici. Prodotti Vari In Metallo",
    "sg:phone":"+39 011 246 2180",
    "sg:postcode":"10155",
    "sg:province":"Torino",
    "wof:name":"Msp Servizi S.a.s.",
    "wof:placetype":"venue"
},
  "geometry": {"coordinates":[7.6955523491,45.113483429],"type":"Point"}
}