{
  "type": "Feature",
  "properties": {
    "iso:country":"IT",
    "sg:address":"00191 Roma",
    "sg:city":"Roma",
    "sg:orig_category":"Estetiste",
    "sg:phone":"+39 06 333 8710",
    "sg:postcode":"00191",
    "sg:province":"Roma",
    "sg:website":"http://www.dcdestetica.it",
    "wof:name":"Dc Dcd Srl",
    "wof:placetype":"venue"
},
  "geometry": {"coordinates":[12.471931,41.942093],"type":"Point"}
}