{
  "type": "Feature",
  "properties": {
    "iso:country":"IT",
    "sg:address":"24057 Martinengo",
    "sg:city":"Martinengo",
    "sg:orig_category":"Non-classified Establishments",
    "sg:phone":"+39 036 398 7010",
    "sg:postcode":"24057",
    "sg:province":"Bergamo",
    "wof:name":"Morosini Lamellari S.r.l.",
    "wof:placetype":"venue"
},
  "geometry": {"coordinates":[9.693567,45.694675],"type":"Point"}
}