{
  "type": "Feature",
  "properties": {
    "iso:country":"IT",
    "sg:address":"36075 Montecchio Maggiore",
    "sg:city":"Montecchio Maggiore",
    "sg:orig_category":"Cavi E Conduttori Elettrici E Telefonici",
    "sg:phone":"+39 0444 499023",
    "sg:postcode":"36075",
    "sg:province":"Vicenza",
    "wof:name":"Elcon Elettromeccanica Snc",
    "wof:placetype":"venue"
},
  "geometry": {"coordinates":[11.410027,45.482239],"type":"Point"}
}