{
  "type": "Feature",
  "properties": {
    "iso:country":"IT",
    "sg:address":"33047 Remanzacco",
    "sg:city":"Remanzacco",
    "sg:orig_category":"Climatizzazione E Condizionamento, Apparecchiature E Servizi",
    "sg:phone":"+39 0432 667795",
    "sg:postcode":"33047",
    "sg:province":"Udine",
    "wof:name":"F.p.e. Sas Di Francesco Zampollo & C.",
    "wof:placetype":"venue"
},
  "geometry": {"coordinates":[13.303938,46.073997],"type":"Point"}
}