{
  "type": "Feature",
  "properties": {
    "addr:full":"151, Via Torino 30172 Venezia Venezia Venezia 30172",
    "addr:housenumber":"151",
    "addr:postcode":"30172;30172",
    "addr:street":"Via Torino",
    "iso:country":"IT",
    "sg:address":"151, Via Torino 30172 Venezia",
    "sg:city":"Venezia",
    "sg:classifiers":[
        {
            "category":"Farming",
            "subcategory":"Livestock Farm",
            "type":"Manufacturing & Wholesale Goods"
        }
    ],
    "sg:phone":"+39 041 531 0800",
    "sg:postcode":"30172",
    "sg:province":"Venezia",
    "sg:tags":[
        "agriculture"
    ],
    "wof:name":"Timperi S.r.l.",
    "wof:placetype":"venue"
},
  "geometry": {"coordinates":[12.780014,45.824844],"type":"Point"}
}