{
  "type": "Feature",
  "properties": {
    "addr:full":"40026 Imola Imola Bologna 40026",
    "addr:postcode":"40026;40026",
    "iso:country":"IT",
    "sg:address":"40026 Imola",
    "sg:city":"Imola",
    "sg:orig_category":"Arredamenti E Mobili Professionali. Impianti, Attrezzature E Forniture Sanitarie Ed Ospedaliere",
    "sg:phone":"+39 0542 35920",
    "sg:postcode":"40026",
    "sg:province":"Bologna",
    "wof:name":"Gordini Giancarlo",
    "wof:placetype":"venue"
},
  "geometry": {"coordinates":[11.71738,44.355137],"type":"Point"}
}