{
  "type": "Feature",
  "properties": {
    "addr:full":"25025 Manerbio Manerbio Brescia 25025",
    "addr:postcode":"25025;25025",
    "iso:country":"IT",
    "sg:address":"25025 Manerbio",
    "sg:city":"Manerbio",
    "sg:orig_category":"Prodotti Vari In Metallo. Articoli Per Imballaggio E Confezionamento",
    "sg:phone":"+39 030 993 8152",
    "sg:postcode":"25025",
    "sg:province":"Brescia",
    "wof:name":"Zenith (s.p.a.)",
    "wof:placetype":"venue"
},
  "geometry": {"coordinates":[10.3678951263,45.5703849792],"type":"Point"}
}