{
  "type": "Feature",
  "properties": {
    "addr:full":"87036 Rende Rende Cosenza 87036",
    "addr:postcode":"87036;87036",
    "iso:country":"IT",
    "sg:address":"87036 Rende",
    "sg:city":"Rende",
    "sg:orig_category":"Servizi Ausiliari Di Analisi, Controllo E Ricerca",
    "sg:phone":"+39 0984 8351",
    "sg:postcode":"87036",
    "sg:province":"Cosenza",
    "wof:name":"Cnr Area Della Ricerca",
    "wof:placetype":"venue"
},
  "geometry": {"coordinates":[16.243126,39.338753],"type":"Point"}
}