{
  "type": "Feature",
  "properties": {
    "iso:country":"IT",
    "sg:address":"Via Baldeschi 61 06073 Corciano",
    "sg:city":"Corciano",
    "sg:orig_category":"Accessories For Automatic Painting And Varnishing Systems",
    "sg:phone":"+39 075 697 8345",
    "sg:postcode":"06073",
    "sg:province":"Perugia",
    "sg:website":"www.officinepacini.it",
    "wof:name":"Officine Industriali Pacini Snc Di Primo Pacini E C.",
    "wof:placetype":"venue"
},
  "geometry": {"coordinates":[12.278882,43.120232],"type":"Point"}
}