{
  "type": "Feature",
  "properties": {
    "addr:full":"45018 Porto Tolle Porto Tolle Rovigo 45018",
    "addr:housenumber":"45018",
    "addr:postcode":"45018",
    "iso:country":"IT",
    "sg:address":"45018 Porto Tolle",
    "sg:city":"Porto Tolle",
    "sg:orig_category":"Pubblica Amministrazione",
    "sg:phone":"+39 0426 380279",
    "sg:postcode":"45018",
    "sg:province":"Rovigo",
    "wof:name":"Corpo Forestale Dello Stato",
    "wof:placetype":"venue"
},
  "geometry": {"coordinates":[12.4284896851,44.9025192261],"type":"Point"}
}