{
  "type": "Feature",
  "properties": {
    "addr:full":"Via Del Tappezziere 7 40138 Bologna Bologna Bologna 40138",
    "addr:housenumber":"7",
    "addr:postcode":"40138;40138",
    "addr:street":"Via Del Tappezziere",
    "iso:country":"IT",
    "sg:address":"Via Del Tappezziere 7 40138 Bologna",
    "sg:city":"Bologna",
    "sg:classifiers":[
        {
            "category":"Home & Garden",
            "subcategory":"Building Materials",
            "type":"Retail Goods"
        }
    ],
    "sg:phone":"+39 051 531093",
    "sg:postcode":"40138",
    "sg:province":"Bologna",
    "sg:tags":[
        "steel",
        "base"
    ],
    "sg:website":"www.trafital.it",
    "wof:name":"Trafital Spa",
    "wof:placetype":"venue"
},
  "geometry": {"coordinates":[11.414549,44.501499],"type":"Point"}
}