{
  "type": "Feature",
  "properties": {
    "iso:country":"IT",
    "sg:address":"37057 S. Giovanni Lupatoto",
    "sg:orig_category":"Dolciumi E Gelati",
    "sg:phone":"+39 045 877 8521",
    "sg:postcode":"37057",
    "sg:province":"Verona",
    "wof:name":"Rigodanza Serafino & C. Spa",
    "wof:placetype":"venue"
},
  "geometry": {"coordinates":[11.02931,45.377617],"type":"Point"}
}