{
  "type": "Feature",
  "properties": {
    "iso:country":"IT",
    "sg:address":"Via Milano 394 21020 Mercallo",
    "sg:city":"Mercallo",
    "sg:classifiers":[
        {
            "category":"Wholesale",
            "subcategory":"Construction Materials",
            "type":"Manufacturing & Wholesale Goods"
        }
    ],
    "sg:phone":"+39 0331 968126",
    "sg:postcode":"21020",
    "sg:province":"Varese",
    "sg:tags":[
        "railway"
    ],
    "sg:website":"www.mercallese.it",
    "wof:name":"Metalmeccanica Mercallese Srl",
    "wof:placetype":"venue"
},
  "geometry": {"coordinates":[8.673451,45.744339],"type":"Point"}
}