{
  "type": "Feature",
  "properties": {
    "addr:full":"2, Via Dell' Artigianato 35010 Grantorto Grantorto Padova 35010",
    "addr:postcode":"35010;35010",
    "addr:street":"Via Dell ' Artigianato",
    "iso:country":"IT",
    "sg:address":"2, Via Dell' Artigianato 35010 Grantorto",
    "sg:city":"Grantorto",
    "sg:classifiers":[
        {
            "category":"Personal",
            "subcategory":"Shoe Repair & Shine",
            "type":"Services"
        }
    ],
    "sg:phone":"+39 049 949 0047",
    "sg:postcode":"35010",
    "sg:province":"Padova",
    "sg:tags":[
        "leather"
    ],
    "wof:name":"Paola Di Tardivo Sergio & C. (s.n.c.)",
    "wof:placetype":"venue"
},
  "geometry": {"coordinates":[11.719357,45.597363],"type":"Point"}
}