{
  "type": "Feature",
  "properties": {
    "iso:country":"IT",
    "sg:address":"11026 Pont-saint-martin",
    "sg:city":"Pont-Saint-Martin",
    "sg:orig_category":"Marmo, Pietre Ed Affini",
    "sg:phone":"+39 0125 807260",
    "sg:postcode":"11026",
    "sg:province":"Aosta",
    "wof:name":"Vima Marmi Imp. Valdostana Marmi",
    "wof:placetype":"venue"
},
  "geometry": {"coordinates":[7.795361,45.590054],"type":"Point"}
}