{
  "type": "Feature",
  "properties": {
    "iso:country":"IT",
    "sg:address":"57121 Livorno",
    "sg:city":"Livorno",
    "sg:orig_category":"Carta, Cartone E Prodotti Primari",
    "sg:phone":"+39 0586 425090",
    "sg:postcode":"57121",
    "sg:province":"Livorno",
    "wof:name":"Chierchietti & Mencari Snc",
    "wof:placetype":"venue"
},
  "geometry": {"coordinates":[10.340579,43.56469],"type":"Point"}
}