{
  "type": "Feature",
  "properties": {
    "iso:country":"IT",
    "sg:address":"20145 Milano",
    "sg:city":"Milano",
    "sg:orig_category":"Articoli Da Regalo. Hobbistica. Shopping",
    "sg:phone":"+39 02 435000",
    "sg:postcode":"20145",
    "sg:province":"Milano",
    "wof:name":"I Sassi",
    "wof:placetype":"venue"
},
  "geometry": {"coordinates":[9.162433,45.468224],"type":"Point"}
}