{
  "type": "Feature",
  "properties": {
    "iso:country":"IT",
    "sg:address":"20094 Corsico",
    "sg:city":"Corsico",
    "sg:orig_category":"Materiali Semilavorati Metallici",
    "sg:phone":"+39 02 4586 9888",
    "sg:postcode":"20094",
    "sg:province":"Milano",
    "wof:name":"Monaci Profilati Tubolari Di Monaci Carolina E C. Srl",
    "wof:placetype":"venue"
},
  "geometry": {"coordinates":[9.081708,45.431778],"type":"Point"}
}