{
  "type": "Feature",
  "properties": {
    "iso:country":"IT",
    "sg:address":"00040 Pomezia",
    "sg:city":"Pomezia",
    "sg:orig_category":"Servizi E Lavori Per Edilizia E Lavori Pubblici. Acqua, Luce, Gas E Societa' Di Esercizio Pubblico",
    "sg:phone":"+39 06 911 6631",
    "sg:postcode":"00040",
    "sg:province":"Roma",
    "wof:name":"Enel Spa",
    "wof:placetype":"venue"
},
  "geometry": {"coordinates":[12.489266,41.668358],"type":"Point"}
}