{
  "type": "Feature",
  "properties": {
    "addr:full":"20010 Bareggio Bareggio Milano 20010",
    "addr:postcode":"20010;20010",
    "iso:country":"IT",
    "sg:address":"20010 Bareggio",
    "sg:city":"Bareggio",
    "sg:orig_category":"Carni, Salumi E Pesci. Zootecnia E Pesca, Allevamento Piccoli Animali",
    "sg:phone":"+39 02 9036 0988",
    "sg:postcode":"20010",
    "sg:province":"Milano",
    "wof:name":"Milangel S.n.c. Di Frigerio Sergio E C.",
    "wof:placetype":"venue"
},
  "geometry": {"coordinates":[9.004776,45.470676],"type":"Point"}
}