{
  "type": "Feature",
  "properties": {
    "iso:country":"IT",
    "sg:address":"23/f, Via Foggia 70051 Barletta",
    "sg:city":"Barletta",
    "sg:classifiers":[
        {
            "category":"Shopping",
            "subcategory":"Clothing, Apparel, & Fashions",
            "type":"Retail Goods"
        }
    ],
    "sg:phone":"+39 0883 526757",
    "sg:postcode":"70051",
    "sg:province":"Bari",
    "sg:tags":[
        "clothes"
    ],
    "wof:name":"Maglificio Erredi",
    "wof:placetype":"venue"
},
  "geometry": {"coordinates":[16.869291,41.126053],"type":"Point"}
}