{
  "type": "Feature",
  "properties": {
    "iso:country":"IT",
    "sg:address":"Zona Industriale 73019 Trepuzzi",
    "sg:city":"Trepuzzi",
    "sg:classifiers":[
        {
            "category":"Shopping",
            "subcategory":"Shoes",
            "type":"Retail Goods"
        }
    ],
    "sg:phone":"+39 0832 755864",
    "sg:postcode":"73019",
    "sg:province":"Lecce",
    "sg:tags":[
        "men's",
        "boot"
    ],
    "wof:name":"Calzaturificio F.lli Fernando E Massimo Benegiamo S.n.c.",
    "wof:placetype":"venue"
},
  "geometry": {"coordinates":[18.1254329681,40.3781967163],"type":"Point"}
}