{
  "type": "Feature",
  "properties": {
    "iso:country":"IT",
    "sg:address":"1, Via Della Zecca 40121 Bologna",
    "sg:city":"Bologna",
    "sg:classifiers":[
        {
            "category":"Farming",
            "subcategory":"Livestock Farm",
            "type":"Manufacturing & Wholesale Goods"
        }
    ],
    "sg:phone":"+39 39051229291",
    "sg:postcode":"40121",
    "sg:province":"Bologna",
    "sg:tags":[
        "agriculture"
    ],
    "wof:name":"Sementi Samoggia (s.r.l.)",
    "wof:placetype":"venue"
},
  "geometry": {"coordinates":[11.340242,44.494995],"type":"Point"}
}