{
  "type": "Feature",
  "properties": {
    "addr:full":"Via Bracanelli 21; Vitulano",
    "addr:housenumber":"21",
    "addr:street":"Via Bracanelli",
    "iso:country":"IT",
    "sg:address":"Via Bracanelli 21; Vitulano",
    "sg:classifiers":[
        {
            "category":"Banks & Credit Unions",
            "subcategory":"Bank",
            "type":"Services"
        }
    ],
    "sg:phone":"+39 0824 878415",
    "wof:name":"Banca Di Roma",
    "wof:placetype":"venue"
},
  "geometry": {"coordinates":[14.641685,41.174068],"type":"Point"}
}