{
  "type": "Feature",
  "properties": {
    "addr:full":"47900 Rimini Rimini Rimini 47900",
    "addr:postcode":"47900;47900",
    "iso:country":"IT",
    "sg:address":"47900 Rimini",
    "sg:city":"Rimini",
    "sg:classifiers":[
        {
            "category":"Health Services",
            "subcategory":"Health Practitioner",
            "type":"Services"
        }
    ],
    "sg:phone":"+39 0541 389251",
    "sg:postcode":"47900",
    "sg:province":"Rimini",
    "sg:tags":[
        "medici"
    ],
    "wof:name":"Panicali Paola",
    "wof:placetype":"venue"
},
  "geometry": {"coordinates":[12.5936908722,44.0454826355],"type":"Point"}
}