{
  "type": "Feature",
  "properties": {
    "addr:full":"6, Via Delle Industrie 32032 Feltre Feltre Belluno 32032",
    "addr:postcode":"32032;32032",
    "addr:street":"Via Delle Industrie",
    "iso:country":"IT",
    "sg:address":"6, Via Delle Industrie 32032 Feltre",
    "sg:city":"Feltre",
    "sg:classifiers":[
        {
            "category":"Manufacturing",
            "subcategory":"Rubber & Plastics",
            "type":"Manufacturing & Wholesale Goods"
        }
    ],
    "sg:phone":"+39 0439 304044",
    "sg:postcode":"32032",
    "sg:province":"Belluno",
    "wof:name":"Marangoni Pneumatici S.p.a.",
    "wof:placetype":"venue"
},
  "geometry": {"coordinates":[11.921948,46.023327],"type":"Point"}
}