{
  "type": "Feature",
  "properties": {
    "iso:country":"IT",
    "sg:address":"19, Via Malago 24050 Palosco",
    "sg:city":"Palosco",
    "sg:classifiers":[
        {
            "category":"Professional",
            "subcategory":"Engineering",
            "type":"Services"
        }
    ],
    "sg:phone":"+39 39035845577",
    "sg:postcode":"24050",
    "sg:province":"Bergamo",
    "sg:tags":[
        "machine",
        "-",
        "mechanical"
    ],
    "wof:name":"F.e.l.p. (s.n.c.)",
    "wof:placetype":"venue"
},
  "geometry": {"coordinates":[9.831817,45.582253],"type":"Point"}
}