{
  "type": "Feature",
  "properties": {
    "addr:full":"1, Via Pigna Giovan Battista 44100 Ferrara Ferrara Ferrara 44100",
    "addr:postcode":"44100;44100",
    "addr:street":"Via Pigna Giovan Battista",
    "iso:country":"IT",
    "sg:address":"1, Via Pigna Giovan Battista 44100 Ferrara",
    "sg:city":"Ferrara",
    "sg:classifiers":[
        {
            "category":"Travel",
            "subcategory":"Travel Agent",
            "type":"Entertainment"
        }
    ],
    "sg:phone":"+39 0532 977155",
    "sg:postcode":"44100",
    "sg:province":"Ferrara",
    "sg:tags":[
        "business"
    ],
    "wof:name":"Nettuno Hotel Srl",
    "wof:placetype":"venue"
},
  "geometry": {"coordinates":[11.62044,44.837894],"type":"Point"}
}