{
  "type": "Feature",
  "properties": {
    "iso:country":"IT",
    "sg:address":"23895 Nibionno",
    "sg:city":"Nibionno",
    "sg:orig_category":"Servizi E Lavori Per Arredamento E Industria Del Legno. Arte Ed Artigianato Artistico",
    "sg:phone":"+39 031 690407",
    "sg:postcode":"23895",
    "sg:province":"Lecco",
    "wof:name":"Negri Ambrogio",
    "wof:placetype":"venue"
},
  "geometry": {"coordinates":[9.261809,45.749786],"type":"Point"}
}