{
  "type": "Feature",
  "properties": {
    "iso:country":"IT",
    "sg:address":"20031 Cesano Maderno",
    "sg:city":"Cesano Maderno",
    "sg:orig_category":"Abbigliamento Esterno, Maglierie E Pelliccerie. Servizi E Lavori Per Abbigliamento E Pelletterie",
    "sg:phone":"+39 036 250 6826",
    "sg:postcode":"20031",
    "sg:province":"Milano",
    "wof:name":"Confezioni Livia Snc Di Crenna Livia & C.",
    "wof:placetype":"venue"
},
  "geometry": {"coordinates":[9.14702,45.627964],"type":"Point"}
}