{
  "type": "Feature",
  "properties": {
    "addr:full":"6, Via Professor Don Angelo Dalla Torre 31047 Ponte Di Piave Ponte di Piave Treviso 31047",
    "addr:housenumber":"di piave",
    "addr:postcode":"31047;31047",
    "addr:street":"Via Professor Don Angelo Dalla Torre",
    "iso:country":"IT",
    "sg:address":"6, Via Professor Don Angelo Dalla Torre 31047 Ponte Di Piave",
    "sg:city":"Ponte di Piave",
    "sg:classifiers":[
        {
            "category":"Shopping",
            "type":"Retail Goods"
        }
    ],
    "sg:phone":"+39 0422 202611",
    "sg:postcode":"31047",
    "sg:province":"Treviso",
    "sg:tags":[
        "finished",
        "-",
        "metallic"
    ],
    "wof:name":"Eurimp S.r.l.",
    "wof:placetype":"venue"
},
  "geometry": {"coordinates":[12.4716844559,45.7397460938],"type":"Point"}
}