{
  "type": "Feature",
  "properties": {
    "addr:full":"Contrada Borsellino 92100 Agrigento Agrigento Agrigento 92100",
    "addr:postcode":"92100;92100",
    "addr:street":"Contrada Borsellino",
    "iso:country":"IT",
    "sg:address":"Contrada Borsellino 92100 Agrigento",
    "sg:city":"Agrigento",
    "sg:classifiers":[
        {
            "category":"Manufacturing",
            "subcategory":"Metals",
            "type":"Manufacturing & Wholesale Goods"
        }
    ],
    "sg:phone":"+39 0922 418208",
    "sg:postcode":"92100",
    "sg:province":"Agrigento",
    "sg:tags":[
        "processing"
    ],
    "wof:name":"Bartolomeo Snc",
    "wof:placetype":"venue"
},
  "geometry": {"coordinates":[13.5769557953,37.3111877441],"type":"Point"}
}