{
  "type": "Feature",
  "properties": {
    "iso:country":"IT",
    "sg:address":"23855 Pescate",
    "sg:city":"Pescate",
    "sg:orig_category":"Lavorazioni Meccaniche E Servizi. Servizi Per Imballaggio E Confezionamento",
    "sg:phone":"+39 0341 272872",
    "sg:postcode":"23855",
    "sg:province":"Lecco",
    "sg:website":"http://www.omel.it",
    "wof:name":"Omel Di Panzeri G. & C. Snc",
    "wof:placetype":"venue"
},
  "geometry": {"coordinates":[9.395351,45.832069],"type":"Point"}
}