{
  "type": "Feature",
  "properties": {
    "iso:country":"IT",
    "sg:address":"00141 Roma",
    "sg:city":"Roma",
    "sg:orig_category":"Nautica. Accessori Dei Mezzi Di Trasporto",
    "sg:phone":"+39 06 8620 6042",
    "sg:postcode":"00141",
    "sg:province":"Roma",
    "sg:website":"http://web.tiscali.it/giaro/",
    "wof:name":"Rimessa 'giaro' Snc",
    "wof:placetype":"venue"
},
  "geometry": {"coordinates":[12.523556,41.932568],"type":"Point"}
}