{
  "type": "Feature",
  "properties": {
    "iso:country":"IT",
    "sg:address":"Via Legnano 51 20027 Rescaldina",
    "sg:city":"Rescaldina",
    "sg:orig_category":"Cranes For Metallurgical Plants And Rolling Mills, Foundry Cranes, Mixer Cranes, Stripper Cranes, Pit Furnace Cranes, Open Hearth Furnace Charging Cranes, Claw Cranes",
    "sg:phone":"+39 0331 576427",
    "sg:postcode":"20027",
    "sg:province":"Milano",
    "wof:name":"Borghi Vincenzo Sas",
    "wof:placetype":"venue"
},
  "geometry": {"coordinates":[8.945937,45.612049],"type":"Point"}
}