{
  "type": "Feature",
  "properties": {
    "iso:country":"IT",
    "sg:address":"20099 Sesto San Giovanni",
    "sg:city":"Sesto San Giovanni",
    "sg:orig_category":"Servizi E Lavori Per Industria Alimentare E Bevande",
    "sg:phone":"+39 02 2247 0272",
    "sg:postcode":"20099",
    "sg:province":"Milano",
    "wof:name":"Cooperativa Edificatrice Nuova Torretta Scrl",
    "wof:placetype":"venue"
},
  "geometry": {"coordinates":[9.222718,45.538597],"type":"Point"}
}