{
  "type": "Feature",
  "properties": {
    "iso:country":"IT",
    "sg:address":"20016 Pero",
    "sg:city":"Pero",
    "sg:orig_category":"Utensili Meccanici E Materiali. Forniture Per Attivita' Industriali",
    "sg:postcode":"20016",
    "sg:province":"Milano",
    "wof:name":"Romani Angelo (s.p.a.)",
    "wof:placetype":"venue"
},
  "geometry": {"coordinates":[9.082224,45.514225],"type":"Point"}
}