{
  "type": "Feature",
  "properties": {
    "iso:country":"IT",
    "sg:address":"43100 Parma",
    "sg:city":"Parma",
    "sg:orig_category":"Servizi Per Lo Sport E Il Tempo Libero. Servizi Al Turismo. Servizi Ausiliari Dei Mezzi Di Trasporto. Servizi Ausiliari Per Il Trasporto",
    "sg:phone":"+39 0521 2141",
    "sg:postcode":"43100",
    "sg:province":"Parma",
    "sg:website":"http://www.tep.pr.it",
    "wof:name":"Tep Spa",
    "wof:placetype":"venue"
},
  "geometry": {"coordinates":[10.32296,44.7756],"type":"Point"}
}