{
  "type": "Feature",
  "properties": {
    "iso:country":"IT",
    "sg:address":"1, Via Morgagni Giovanni Battista 20129 Milano",
    "sg:city":"Milano",
    "sg:classifiers":[
        {
            "category":"Communications",
            "subcategory":"Newspaper",
            "type":"Services"
        }
    ],
    "sg:phone":"+39 02 2952 9862",
    "sg:postcode":"20129",
    "sg:province":"Milano",
    "sg:tags":[
        "advertising"
    ],
    "wof:name":"Health Adv Srl",
    "wof:placetype":"venue"
},
  "geometry": {"coordinates":[9.210711,45.477016],"type":"Point"}
}