{
  "type": "Feature",
  "properties": {
    "iso:country":"IT",
    "sg:address":"70125 Bari",
    "sg:city":"Bari",
    "sg:orig_category":"Imprese Di Costruzioni Civili Ed Industriali",
    "sg:phone":"+39 080 501 0507",
    "sg:postcode":"70125",
    "sg:province":"Bari",
    "wof:name":"Esprotecnica Snc",
    "wof:placetype":"venue"
},
  "geometry": {"coordinates":[16.879791,41.088921],"type":"Point"}
}