{
  "type": "Feature",
  "properties": {
    "addr:full":"23, Corso Buenos Aires 20124 Milano Milano Milano 20124",
    "addr:postcode":"20124;20124",
    "addr:street":"Corso Buenos Aires",
    "iso:country":"IT",
    "sg:address":"23, Corso Buenos Aires 20124 Milano",
    "sg:city":"Milano",
    "sg:classifiers":[
        {
            "category":"Shopping",
            "subcategory":"Clothing, Apparel, & Fashions",
            "type":"Retail Goods"
        }
    ],
    "sg:phone":"+39 02 2940 3081",
    "sg:postcode":"20124",
    "sg:province":"Milano",
    "sg:tags":[
        "clothes"
    ],
    "wof:name":"Santagostino Modelli (s.r.l.)",
    "wof:placetype":"venue"
},
  "geometry": {"coordinates":[9.209334,45.478771],"type":"Point"}
}