{
  "type": "Feature",
  "properties": {
    "addr:full":"9, Via Raso 25036 Palazzolo Sull'oglio Brescia 25036",
    "addr:postcode":"25036;25036",
    "addr:street":"Via Raso",
    "iso:country":"IT",
    "sg:address":"9, Via Raso 25036 Palazzolo Sull'oglio",
    "sg:classifiers":[
        {
            "category":"Personal",
            "subcategory":"Shoe Repair & Shine",
            "type":"Services"
        }
    ],
    "sg:phone":"+39 030 740 1182",
    "sg:postcode":"25036",
    "sg:province":"Brescia",
    "sg:tags":[
        "leather"
    ],
    "wof:name":"Volonghi Anna Maria",
    "wof:placetype":"venue"
},
  "geometry": {"coordinates":[9.890333,45.586208],"type":"Point"}
}