{
  "type": "Feature",
  "properties": {
    "iso:country":"IT",
    "sg:address":"20122 Milano",
    "sg:city":"Milano",
    "sg:orig_category":"Cine-foto-ottica. Articoli Medico-sanitari Ed Ortopedici",
    "sg:phone":"+39 02 7600 2340",
    "sg:postcode":"20122",
    "sg:province":"Milano",
    "wof:name":"Luxottica S.r.l.",
    "wof:placetype":"venue"
},
  "geometry": {"coordinates":[9.202716,45.470238],"type":"Point"}
}