{
  "type": "Feature",
  "properties": {
    "addr:full":"3/a, Via Pellico Silvio 35129 Padova Padova Padova 35129",
    "addr:housenumber":"3 / a",
    "addr:postcode":"35129;35129",
    "addr:street":"Via Pellico Silvio",
    "iso:country":"IT",
    "sg:address":"3/a, Via Pellico Silvio 35129 Padova",
    "sg:city":"Padova",
    "sg:classifiers":[
        {
            "category":"Professional",
            "subcategory":"Engineering",
            "type":"Services"
        }
    ],
    "sg:phone":"+39 39049776288",
    "sg:postcode":"35129",
    "sg:province":"Padova",
    "sg:tags":[
        "machine",
        "-",
        "mechanical"
    ],
    "wof:name":"Mitec (s.r.l.)",
    "wof:placetype":"venue"
},
  "geometry": {"coordinates":[11.858907,45.337482],"type":"Point"}
}