{
  "type": "Feature",
  "properties": {
    "addr:full":"30, Via Caduti Del Lavoro 25013 Carpenedolo Carpenedolo Brescia 25013",
    "addr:postcode":"25013;25013",
    "addr:street":"Via Caduti Del Lavoro",
    "iso:country":"IT",
    "sg:address":"30, Via Caduti Del Lavoro 25013 Carpenedolo",
    "sg:city":"Carpenedolo",
    "sg:classifiers":[
        {
            "category":"Personal",
            "subcategory":"Shoe Repair & Shine",
            "type":"Services"
        }
    ],
    "sg:phone":"+39 030 969 7076",
    "sg:postcode":"25013",
    "sg:province":"Brescia",
    "sg:tags":[
        "leather"
    ],
    "wof:name":"Perini Di Perini Giampaolo & C. Snc",
    "wof:placetype":"venue"
},
  "geometry": {"coordinates":[10.432881,45.354904],"type":"Point"}
}