{
  "type": "Feature",
  "properties": {
    "addr:full":"95127 Catania Catania Catania 95127",
    "addr:postcode":"95127;95127",
    "iso:country":"IT",
    "sg:address":"95127 Catania",
    "sg:city":"Catania",
    "sg:orig_category":"Musica",
    "sg:phone":"+39 095 431119",
    "sg:postcode":"95127",
    "sg:province":"Catania",
    "wof:name":"Music Center Di La Piana Anna Maria",
    "wof:placetype":"venue"
},
  "geometry": {"coordinates":[15.0937757492,37.5176849365],"type":"Point"}
}