{
  "type": "Feature",
  "properties": {
    "iso:country":"IT",
    "sg:address":"56, Via Giuseppe Garibaldi 26040 Scandolara Ravara",
    "sg:city":"Scandolara Ravara",
    "sg:classifiers":[
        {
            "category":"Wholesale",
            "subcategory":"Machinery & Supplies",
            "type":"Manufacturing & Wholesale Goods"
        }
    ],
    "sg:phone":"+39 39037595135",
    "sg:postcode":"26040",
    "sg:province":"Cremona",
    "sg:tags":[
        "-",
        "agriculture",
        "equipment"
    ],
    "wof:name":"Barbieri S.n.c. Di Barbieri Fausto Angelo E C.",
    "wof:placetype":"venue"
},
  "geometry": {"coordinates":[10.304649,45.054924],"type":"Point"}
}