{
  "type": "Feature",
  "properties": {
    "addr:full":"96100 Siracusa Siracusa Siracusa 96100",
    "addr:postcode":"96100;96100",
    "iso:country":"IT",
    "sg:address":"96100 Siracusa",
    "sg:city":"Siracusa",
    "sg:classifiers":[
        {
            "category":"Health Services",
            "subcategory":"Health Practitioner",
            "type":"Services"
        }
    ],
    "sg:phone":"+39 0931 68776",
    "sg:postcode":"96100",
    "sg:province":"Siracusa",
    "sg:tags":[
        "medici"
    ],
    "wof:name":"Novara Francesco",
    "wof:placetype":"venue"
},
  "geometry": {"coordinates":[15.2837972641,37.0700721741],"type":"Point"}
}