{
  "type": "Feature",
  "properties": {
    "iso:country":"IT",
    "sg:address":"25046 Cazzago San Martino",
    "sg:city":"Cazzago San Martino",
    "sg:orig_category":"Accessori Moda D'abbigliamento",
    "sg:phone":"+39 030 725 5008",
    "sg:postcode":"25046",
    "sg:province":"Brescia",
    "wof:name":"Cinturificio Maivar Di Assoni Claudio & C. S.n.c.",
    "wof:placetype":"venue"
},
  "geometry": {"coordinates":[10.016649,45.573128],"type":"Point"}
}