{
  "type": "Feature",
  "properties": {
    "iso:country":"IT",
    "sg:address":"6, Via Sette Gocce 20048 Carate Brianza",
    "sg:city":"Carate Brianza",
    "sg:classifiers":[
        {
            "category":"Manufacturing",
            "subcategory":"Paper Products",
            "type":"Manufacturing & Wholesale Goods"
        }
    ],
    "sg:phone":"+39 036 290 2972",
    "sg:postcode":"20048",
    "sg:province":"Milano",
    "sg:tags":[
        "cardboard"
    ],
    "wof:name":"Cesana Giampiero & C. Snc",
    "wof:placetype":"venue"
},
  "geometry": {"coordinates":[9.2489433289,45.676864624],"type":"Point"}
}