{
  "type": "Feature",
  "properties": {
    "addr:full":"11020 Ayas Ayas Aosta 11020",
    "addr:postcode":"11020;11020",
    "iso:country":"IT",
    "sg:address":"11020 Ayas",
    "sg:city":"Ayas",
    "sg:orig_category":"Alberghi E Strutture Extra Alberghiere. Ospedali E Servizi Sanitari",
    "sg:phone":"+39 0125 307651",
    "sg:postcode":"11020",
    "sg:province":"Aosta",
    "wof:name":"Casa Alpina La Fontanella",
    "wof:placetype":"venue"
},
  "geometry": {"coordinates":[7.690326,45.816116],"type":"Point"}
}