{
  "type": "Feature",
  "properties": {
    "addr:full":"20141 Milano Milano Milano 20141",
    "addr:postcode":"20141;20141",
    "iso:country":"IT",
    "sg:address":"20141 Milano",
    "sg:city":"Milano",
    "sg:orig_category":"Telecomunicazioni E Telefonia, Impianti, Apparecchi E Servizi. Acqua, Luce, Gas E Societa' Di Esercizio Pubblico. Servizi Vari Di Interesse Pubblico",
    "sg:phone":"+39 02 8954 6211",
    "sg:postcode":"20141",
    "sg:province":"Milano",
    "wof:name":"Mbarka Samiben Garci",
    "wof:placetype":"venue"
},
  "geometry": {"coordinates":[9.199751,45.423962],"type":"Point"}
}