{
  "type": "Feature",
  "properties": {
    "addr:full":"21100 Varese Varese Varese 21100",
    "addr:postcode":"21100;21100",
    "iso:country":"IT",
    "sg:address":"21100 Varese",
    "sg:city":"Varese",
    "sg:orig_category":"Abbigliamento In Pelle - Vendita Al Dettaglio",
    "sg:phone":"+39 0332 286498",
    "sg:postcode":"21100",
    "sg:province":"Varese",
    "wof:name":"Motoforniture Varesine Di Federico Caro",
    "wof:placetype":"venue"
},
  "geometry": {"coordinates":[8.790314,45.886604],"type":"Point"}
}