{
  "type": "Feature",
  "properties": {
    "addr:full":"Via Don Milani 8 24050 Zanica Zanica Bergamo 24050",
    "addr:housenumber":"8",
    "addr:postcode":"24050;24050",
    "addr:street":"Via Don Milani",
    "iso:country":"IT",
    "sg:address":"Via Don Milani 8 24050 Zanica",
    "sg:city":"Zanica",
    "sg:classifiers":[
        {
            "category":"Wholesale",
            "subcategory":"Drugs",
            "type":"Manufacturing & Wholesale Goods"
        }
    ],
    "sg:phone":"+39 39035673948",
    "sg:postcode":"24050",
    "sg:province":"Bergamo",
    "sg:tags":[
        "chemical",
        "pharmaceutical"
    ],
    "wof:name":"Bellini Srl",
    "wof:placetype":"venue"
},
  "geometry": {"coordinates":[9.688554,45.624104],"type":"Point"}
}