{
  "type": "Feature",
  "properties": {
    "iso:country":"IT",
    "sg:address":"Via A. Coppi 56 41043 Formigine",
    "sg:city":"Formigine",
    "sg:classifiers":[
        {
            "category":"Wholesale",
            "subcategory":"Plants",
            "type":"Manufacturing & Wholesale Goods"
        }
    ],
    "sg:phone":"+39 059 557325",
    "sg:postcode":"41043",
    "sg:province":"Modena",
    "sg:tags":[
        "machine",
        "industrial",
        "automation"
    ],
    "wof:name":"Sigmat Automazioni Industriali Srl",
    "wof:placetype":"venue"
},
  "geometry": {"coordinates":[10.935554,44.554535],"type":"Point"}
}