{
  "type": "Feature",
  "properties": {
    "iso:country":"IT",
    "sg:address":"22100 Como",
    "sg:city":"Como",
    "sg:orig_category":"Tessuti E Stoffe. Filati E Materie Prime Tessili",
    "sg:phone":"+39 031 303440",
    "sg:postcode":"22100",
    "sg:province":"Como",
    "sg:website":"http://www.gbinda.it",
    "wof:name":"Tessitura Serica Binda Gianni Srl",
    "wof:placetype":"venue"
},
  "geometry": {"coordinates":[9.082118,45.817867],"type":"Point"}
}