{
  "type": "Feature",
  "properties": {
    "iso:country":"IT",
    "sg:address":"43100 Parma",
    "sg:city":"Parma",
    "sg:classifiers":[
        {
            "category":"Wholesale",
            "subcategory":"Machinery & Supplies",
            "type":"Manufacturing & Wholesale Goods"
        }
    ],
    "sg:phone":"+39 0521 270705",
    "sg:postcode":"43100",
    "sg:province":"Parma",
    "sg:tags":[
        "pump"
    ],
    "wof:name":"F.i.p. Srl",
    "wof:placetype":"venue"
},
  "geometry": {"coordinates":[10.3229598999,44.7756004333],"type":"Point"}
}