{
  "type": "Feature",
  "properties": {
    "iso:country":"IT",
    "sg:address":"33050 Precenicco",
    "sg:city":"Precenicco",
    "sg:orig_category":"Ceramiche: Prodotti E Lavorazioni",
    "sg:phone":"+39 0431 58085",
    "sg:postcode":"33050",
    "sg:province":"Udine",
    "sg:website":"http://www.florimar.it",
    "wof:name":"Ceramiche Florimar Srl",
    "wof:placetype":"venue"
},
  "geometry": {"coordinates":[13.078444,45.789852],"type":"Point"}
}