{
  "type": "Feature",
  "properties": {
    "addr:full":"50065 Pontassieve Pontassieve Firenze 50065",
    "addr:postcode":"50065;50065",
    "iso:country":"IT",
    "sg:address":"50065 Pontassieve",
    "sg:city":"Pontassieve",
    "sg:orig_category":"Gruppi Elettrogeni E Di Continuita'",
    "sg:phone":"+39 055 836 7455",
    "sg:postcode":"50065",
    "sg:province":"Firenze",
    "sg:website":"http://www.tecnoware.com",
    "wof:name":"Tecnoware Srl",
    "wof:placetype":"venue"
},
  "geometry": {"coordinates":[11.426304,43.773045],"type":"Point"}
}