{
  "type": "Feature",
  "properties": {
    "iso:country":"IT",
    "sg:address":"20080 Vernate",
    "sg:city":"Vernate",
    "sg:orig_category":"Macchine Utensili - Commercio",
    "sg:phone":"+39 02 905 2513",
    "sg:postcode":"20080",
    "sg:province":"Milano",
    "wof:name":"Sibimex Italiana Spa",
    "wof:placetype":"venue"
},
  "geometry": {"coordinates":[9.086044,45.322376],"type":"Point"}
}