{
  "type": "Feature",
  "properties": {
    "iso:country":"IT",
    "sg:address":"6, Via Bandello Matteo 20123 Milano",
    "sg:city":"Milano",
    "sg:classifiers":[
        {
            "category":"Communications",
            "subcategory":"Television Station",
            "type":"Services"
        }
    ],
    "sg:phone":"+39 02 4800 6090",
    "sg:postcode":"20123",
    "sg:province":"Milano",
    "sg:tags":[
        "equipment",
        "optical",
        "instrument"
    ],
    "wof:name":"Dpf Photocenter (s.r.l.)",
    "wof:placetype":"venue"
},
  "geometry": {"coordinates":[9.16823,45.465195],"type":"Point"}
}