{
  "type": "Feature",
  "properties": {
    "iso:country":"IT",
    "sg:address":"Via Lamarmora 30 25065 Lumezzane",
    "sg:city":"Lumezzane",
    "sg:orig_category":"Fittings, Valves",
    "sg:phone":"+39 030 890 1108",
    "sg:postcode":"25065",
    "sg:province":"Brescia",
    "wof:name":"Bossini Bortolo & Figli Srl",
    "wof:placetype":"venue"
},
  "geometry": {"coordinates":[10.2636728287,45.6472892761],"type":"Point"}
}