{
  "type": "Feature",
  "properties": {
    "iso:country":"IT",
    "sg:address":"43100 Parma",
    "sg:city":"Parma",
    "sg:orig_category":"Acqua Potabile - Societa' Di Esercizio",
    "sg:phone":"+39 0521 2481",
    "sg:postcode":"43100",
    "sg:province":"Parma",
    "sg:website":"http://www.amps.it",
    "wof:name":"Amps Spa",
    "wof:placetype":"venue"
},
  "geometry": {"coordinates":[10.327456,44.798355],"type":"Point"}
}