{
  "type": "Feature",
  "properties": {
    "iso:country":"IT",
    "sg:address":"14, Via Percoto Caterina 33100 Udine",
    "sg:city":"Udine",
    "sg:classifiers":[
        {
            "category":"Communications",
            "subcategory":"Television Station",
            "type":"Services"
        }
    ],
    "sg:phone":"+39 0432 512075",
    "sg:postcode":"33100",
    "sg:province":"Udine",
    "sg:tags":[
        "audio-visual"
    ],
    "wof:name":"Exco (s.r.l.)",
    "wof:placetype":"venue"
},
  "geometry": {"coordinates":[13.30072,46.037861],"type":"Point"}
}