{
  "type": "Feature",
  "properties": {
    "iso:country":"IT",
    "sg:address":"00187 Roma",
    "sg:city":"Roma",
    "sg:orig_category":"Professionisti - Studi E Servizi Ed Associazioni Di Interesse Aziendale. Associazioni Ed Organismi Di Interesse Pubblico",
    "sg:phone":"+39 06 485923",
    "sg:postcode":"00187",
    "sg:province":"Roma",
    "wof:name":"Federazione Nazionale Degli Ordini Dei Veterinari Italiani",
    "wof:placetype":"venue"
},
  "geometry": {"coordinates":[12.4875736237,41.9033317566],"type":"Point"}
}