{
  "type": "Feature",
  "properties": {
    "iso:country":"IT",
    "sg:address":"20080 Vernate",
    "sg:city":"Vernate",
    "sg:orig_category":"Prodotti Alimentari",
    "sg:phone":"+39 02 9009 6500",
    "sg:postcode":"20080",
    "sg:province":"Milano",
    "wof:name":"Sitia Yomo Spa",
    "wof:placetype":"venue"
},
  "geometry": {"coordinates":[9.0604219437,45.3163490295],"type":"Point"}
}