{
  "type": "Feature",
  "properties": {
    "addr:full":"10073 Cirie' Torino 10073",
    "addr:housenumber":"10073",
    "addr:postcode":"10073",
    "addr:street":"Cirie ' Torino",
    "iso:country":"IT",
    "sg:address":"10073 Cirie'",
    "sg:orig_category":"Pellicce E Pelli - Custodia E Pulitura",
    "sg:phone":"+39 011 920 8785",
    "sg:postcode":"10073",
    "sg:province":"Torino",
    "wof:name":"Contiero Pellicce Snc Di Contiero R. & C.",
    "wof:placetype":"venue"
},
  "geometry": {"coordinates":[7.5948557854,45.2256584167],"type":"Point"}
}