{
  "type": "Feature",
  "properties": {
    "addr:full":"10099 San Mauro Torinese San Mauro Torinese Torino 10099",
    "addr:housenumber":"10099",
    "addr:postcode":"10099",
    "addr:street":"San",
    "iso:country":"IT",
    "sg:address":"10099 San Mauro Torinese",
    "sg:city":"San Mauro Torinese",
    "sg:orig_category":"Climatizzazione E Condizionamento, Apparecchiature E Servizi",
    "sg:phone":"+39 011 822 7414",
    "sg:postcode":"10099",
    "sg:province":"Torino",
    "wof:name":"Speedy Di Nervo Clementino",
    "wof:placetype":"venue"
},
  "geometry": {"coordinates":[7.745439,45.1082],"type":"Point"}
}