{
  "type": "Feature",
  "properties": {
    "iso:country":"IT",
    "sg:address":"61/a/b, V. Genova 10098 Rivoli",
    "sg:city":"Rivoli",
    "sg:classifiers":[
        {
            "category":"Professional",
            "subcategory":"Engineering",
            "type":"Services"
        }
    ],
    "sg:phone":"+39 011 957 4740",
    "sg:postcode":"10098",
    "sg:province":"Torino",
    "sg:tags":[
        "machine",
        "-",
        "mechanical"
    ],
    "sg:website":"http://www.paginegialle.it/ometomt",
    "wof:name":"O.me.t Srl",
    "wof:placetype":"venue"
},
  "geometry": {"coordinates":[7.556605,45.063923],"type":"Point"}
}