{
  "type": "Feature",
  "properties": {
    "iso:country":"IT",
    "sg:address":"10, V. Alberto Da Giussano 21057 Olgiate Olona",
    "sg:city":"Olgiate Olona",
    "sg:classifiers":[
        {
            "category":"Shopping",
            "subcategory":"Clothing, Apparel, & Fashions",
            "type":"Retail Goods"
        }
    ],
    "sg:phone":"+39 0331 643070",
    "sg:postcode":"21057",
    "sg:province":"Varese",
    "sg:tags":[
        "clothes"
    ],
    "sg:website":"http://www.maglificiovp.it",
    "wof:name":"Maglificio Pinuccio Venegoni Srl",
    "wof:placetype":"venue"
},
  "geometry": {"coordinates":[8.857593,45.609657],"type":"Point"}
}