{
  "type": "Feature",
  "properties": {
    "iso:country":"IT",
    "sg:address":"40133 Bologna",
    "sg:city":"Bologna",
    "sg:orig_category":"Impianti, Attrezzature E Forniture Sanitarie Ed Ospedaliere",
    "sg:phone":"+39 051 413 8000",
    "sg:postcode":"40133",
    "sg:province":"Bologna",
    "sg:website":"http://www.coloplast.it",
    "wof:name":"Coloplast Spa",
    "wof:placetype":"venue"
},
  "geometry": {"coordinates":[11.656878,44.977913],"type":"Point"}
}