{
  "type": "Feature",
  "properties": {
    "iso:country":"IT",
    "sg:address":"20019 Settimo Milanese",
    "sg:city":"Settimo Milanese",
    "sg:orig_category":"Professionisti - Studi E Servizi Ed Associazioni Di Interesse Aziendale. Associazioni Ed Organismi Di Interesse Pubblico",
    "sg:phone":"+39 02 328 4773",
    "sg:postcode":"20019",
    "sg:province":"Milano",
    "wof:name":"Lega Nord Per L'indipendenza Della Padania",
    "wof:placetype":"venue"
},
  "geometry": {"coordinates":[9.053519249,45.4830322266],"type":"Point"}
}