{
  "type": "Feature",
  "properties": {
    "addr:full":"40127 Bologna Bologna Bologna 40127",
    "addr:postcode":"40127;40127",
    "iso:country":"IT",
    "sg:address":"40127 Bologna",
    "sg:city":"Bologna",
    "sg:orig_category":"Pubblica Amministrazione",
    "sg:phone":"+39 051 327633",
    "sg:postcode":"40127",
    "sg:province":"Bologna",
    "wof:name":"Direzione Casa Circondariale Bologna",
    "wof:placetype":"venue"
},
  "geometry": {"coordinates":[11.3679790497,44.5343589783],"type":"Point"}
}