{
  "type": "Feature",
  "properties": {
    "iso:country":"IT",
    "sg:address":"1, Via Urbino 91016 Erice",
    "sg:city":"Erice",
    "sg:classifiers":[
        {
            "category":"Food & Beverages",
            "subcategory":"Groceries & Convenience Stores",
            "type":"Retail Goods"
        }
    ],
    "sg:phone":"+39 0923 560111",
    "sg:postcode":"91016",
    "sg:province":"Trapani",
    "sg:tags":[
        "product",
        "related"
    ],
    "wof:name":"Siciliana Pasti Sas",
    "wof:placetype":"venue"
},
  "geometry": {"coordinates":[12.5394458771,38.0314826965],"type":"Point"}
}