{
  "type": "Feature",
  "properties": {
    "addr:full":"20122 Milano Milano Milano 20122",
    "addr:postcode":"20122;20122",
    "iso:country":"IT",
    "sg:address":"20122 Milano",
    "sg:city":"Milano",
    "sg:orig_category":"Studi E Consulenze Legali E Notarili. Avvocati, Notai E Servizi Legali. Professionisti - Studi E Servizi Ed Associazioni Di Interesse Aziendale",
    "sg:phone":"+39 02 545 5995",
    "sg:postcode":"20122",
    "sg:province":"Milano",
    "wof:name":"Scognamiglio Adriana",
    "wof:placetype":"venue"
},
  "geometry": {"coordinates":[9.203715,45.456188],"type":"Point"}
}