{
  "type": "Feature",
  "properties": {
    "iso:country":"IT",
    "sg:address":"27/d, Via Fornaci 25040 Corte Franca",
    "sg:city":"Corte Franca",
    "sg:classifiers":[
        {
            "category":"Personal",
            "subcategory":"Shoe Repair & Shine",
            "type":"Services"
        }
    ],
    "sg:phone":"+39 030 982 6604",
    "sg:postcode":"25040",
    "sg:province":"Brescia",
    "sg:tags":[
        "leather"
    ],
    "wof:name":"Zoccolificio E Calzaturificio Bresciano",
    "wof:placetype":"venue"
},
  "geometry": {"coordinates":[9.614247,45.640415],"type":"Point"}
}