{
  "type": "Feature",
  "properties": {
    "addr:full":"00147 Roma Roma Roma 00147",
    "addr:postcode":"00147;00147",
    "iso:country":"IT",
    "sg:address":"00147 Roma",
    "sg:city":"Roma",
    "sg:orig_category":"Ospedali E Servizi Sanitari",
    "sg:phone":"+39 06 513 7873",
    "sg:postcode":"00147",
    "sg:province":"Roma",
    "wof:name":"La Farina Dr.ssa Milena",
    "wof:placetype":"venue"
},
  "geometry": {"coordinates":[12.500006,41.861691],"type":"Point"}
}