{
  "type": "Feature",
  "properties": {
    "iso:country":"IT",
    "sg:address":"20124 Milano",
    "sg:city":"Milano",
    "sg:orig_category":"Macchine, Impianti E Forniture Per Industria Grafica, Cartaria E Cartotecnica",
    "sg:phone":"+39 02 6710 0091",
    "sg:postcode":"20124",
    "sg:province":"Milano",
    "wof:name":"Top Graphic Snc Di Binda Karima E C.",
    "wof:placetype":"venue"
},
  "geometry": {"coordinates":[9.197481,45.489067],"type":"Point"}
}