{
  "type": "Feature",
  "properties": {
    "iso:country":"IT",
    "sg:address":"20124 Milano",
    "sg:city":"Milano",
    "sg:orig_category":"Cinematografia E Radiotelevisione. Pubblicita', Marketing E Comunicazione",
    "sg:phone":"+39 02 671431",
    "sg:postcode":"20124",
    "sg:province":"Milano",
    "sg:website":"http://www.opus.it",
    "wof:name":"Opus Tv",
    "wof:placetype":"venue"
},
  "geometry": {"coordinates":[9.197351,45.483932],"type":"Point"}
}