{
  "type": "Feature",
  "properties": {
    "iso:country":"IT",
    "sg:address":"50134 Firenze",
    "sg:city":"Firenze",
    "sg:orig_category":"Prodotti Finiti Stampati. Servizi Editoriali. Tempo Libero - Articoli E Forniture",
    "sg:phone":"+39 055 411688",
    "sg:postcode":"50134",
    "sg:province":"Firenze",
    "wof:name":"Libreria Stella Alpina",
    "wof:placetype":"venue"
},
  "geometry": {"coordinates":[11.2418651581,43.793006897],"type":"Point"}
}