{
  "type": "Feature",
  "properties": {
    "iso:country":"IT",
    "sg:address":"00182 Roma",
    "sg:city":"Roma",
    "sg:orig_category":"Cinematografia E Radiotelevisione",
    "sg:phone":"+39 06 707 0011",
    "sg:postcode":"00182",
    "sg:province":"Roma",
    "wof:name":"Studio Emme Di Brizzolari Donatella E C. S.a.s.",
    "wof:placetype":"venue"
},
  "geometry": {"coordinates":[12.517794,41.880505],"type":"Point"}
}