{
  "type": "Feature",
  "properties": {
    "iso:country":"IT",
    "sg:address":"20060 Bussero",
    "sg:city":"Bussero",
    "sg:orig_category":"Servizi E Lavori Per Industria Alimentare E Bevande",
    "sg:phone":"+39 02 9503 9650",
    "sg:postcode":"20060",
    "sg:province":"Milano",
    "wof:name":"Coop. Unione Di Trezzo Sull'adda Scrl",
    "wof:placetype":"venue"
},
  "geometry": {"coordinates":[9.265395,45.52636],"type":"Point"}
}