{
  "type": "Feature",
  "properties": {
    "iso:country":"IT",
    "sg:address":"79, Via Verdi Giuseppe 31046 Oderzo",
    "sg:city":"Oderzo",
    "sg:classifiers":[
        {
            "category":"Shopping",
            "subcategory":"Crafts & Fabrics",
            "type":"Retail Goods"
        }
    ],
    "sg:phone":"+39 0422 716140",
    "sg:postcode":"31046",
    "sg:province":"Treviso",
    "sg:tags":[
        "linen"
    ],
    "wof:name":"Aurora (s.r.l.)",
    "wof:placetype":"venue"
},
  "geometry": {"coordinates":[12.462477684,45.7180290222],"type":"Point"}
}