{
  "type": "Feature",
  "properties": {
    "addr:full":"95025 Aci Sant'antonio Catania 95025",
    "addr:postcode":"95025;95025",
    "iso:country":"IT",
    "sg:address":"95025 Aci Sant'antonio",
    "sg:orig_category":"Arredamenti E Mobili Professionali. Apparecchi, Attrezzature E Forniture Per Centri Estetici. Arredi Ed Attrezzature Per Attivita' Commerciali Ed Artigianali",
    "sg:phone":"+39 095 789 2085",
    "sg:postcode":"95025",
    "sg:province":"Catania",
    "wof:name":"Monti Arredamenti Di Monti Ernesto",
    "wof:placetype":"venue"
},
  "geometry": {"coordinates":[15.118647,37.604233],"type":"Point"}
}