{
  "type": "Feature",
  "properties": {
    "iso:country":"IT",
    "sg:address":"11, Via Rossini 47822 Santarcangelo Di Romagna",
    "sg:city":"Santarcangelo di Romagna",
    "sg:classifiers":[
        {
            "category":"Shopping",
            "subcategory":"Clothing, Apparel, & Fashions",
            "type":"Retail Goods"
        }
    ],
    "sg:phone":"+39 0541 621870",
    "sg:postcode":"47822",
    "sg:province":"Rimini",
    "sg:tags":[
        "clothes"
    ],
    "wof:name":"Fox Trot Di De Nicolo' Marta Maria",
    "wof:placetype":"venue"
},
  "geometry": {"coordinates":[12.452065,44.069313],"type":"Point"}
}