{
  "type": "Feature",
  "properties": {
    "addr:full":"27027 Gropello Cairoli Gropello Cairoli Pavia 27027",
    "addr:postcode":"27027;27027",
    "iso:country":"IT",
    "sg:address":"27027 Gropello Cairoli",
    "sg:city":"Gropello Cairoli",
    "sg:orig_category":"Macchine Ed Impianti Per Edilizia E Lavori Pubblici",
    "sg:phone":"+39 0382 814207",
    "sg:postcode":"27027",
    "sg:province":"Pavia",
    "wof:name":"Zorzoli Roberto",
    "wof:placetype":"venue"
},
  "geometry": {"coordinates":[8.988814,45.180653],"type":"Point"}
}