{
  "type": "Feature",
  "properties": {
    "addr:full":"Via N. Fabrizi 102, Pescara, Pe",
    "addr:housenumber":"102",
    "addr:street":"Via N. Fabrizi",
    "iso:country":"IT",
    "sg:address":"Via N. Fabrizi 102, Pescara, Pe",
    "sg:classifiers":[
        {
            "category":"Banks & Credit Unions",
            "subcategory":"Bank",
            "type":"Services"
        }
    ],
    "wof:name":"Fincap",
    "wof:placetype":"venue"
},
  "geometry": {"coordinates":[14.213652,42.469017],"type":"Point"}
}