{
  "type": "Feature",
  "properties": {
    "iso:country":"IT",
    "sg:address":"35031 Abano Terme",
    "sg:city":"Abano Terme",
    "sg:orig_category":"Legno E Semilavorati",
    "sg:phone":"+39 049 812449",
    "sg:postcode":"35031",
    "sg:province":"Padova",
    "wof:name":"F.lli Zilio Di Zilio Raffaele Zilio Dario & C. S.n.c.",
    "wof:placetype":"venue"
},
  "geometry": {"coordinates":[11.81276,45.351189],"type":"Point"}
}