{
  "type": "Feature",
  "properties": {
    "addr:full":"33, Via Vittorio Veneto 22073 Fino Mornasco Fino Mornasco Como 22073",
    "addr:postcode":"22073;22073",
    "addr:street":"Via Vittorio Veneto",
    "iso:country":"IT",
    "sg:address":"33, Via Vittorio Veneto 22073 Fino Mornasco",
    "sg:city":"Fino Mornasco",
    "sg:classifiers":[
        {
            "category":"Shopping",
            "subcategory":"Crafts & Fabrics",
            "type":"Retail Goods"
        }
    ],
    "sg:phone":"+39 39031883511",
    "sg:postcode":"22073",
    "sg:province":"Como",
    "wof:name":"Effepierre (s.p.a.)",
    "wof:placetype":"venue"
},
  "geometry": {"coordinates":[9.0441255569,45.7373352051],"type":"Point"}
}