{
  "type": "Feature",
  "properties": {
    "addr:full":"70124 Bari Bari Bari 70124",
    "addr:postcode":"70124;70124",
    "iso:country":"IT",
    "sg:address":"70124 Bari",
    "sg:city":"Bari",
    "sg:orig_category":"Arredo Cucina Ed Elettrodomestici. Frigotecnica, Apparecchiature E Servizi. Elettrodomestici",
    "sg:phone":"+39 080 504 2759",
    "sg:postcode":"70124",
    "sg:province":"Bari",
    "wof:name":"Di Bello Elettroservice S.n.c.",
    "wof:placetype":"venue"
},
  "geometry": {"coordinates":[16.861057,41.10815],"type":"Point"}
}