{
  "type": "Feature",
  "properties": {
    "iso:country":"IT",
    "sg:address":"24050 Grassobbio",
    "sg:city":"Grassobbio",
    "sg:orig_category":"Impianti, Attrezzature E Forniture Sanitarie Ed Ospedaliere",
    "sg:phone":"+39 035 335675",
    "sg:postcode":"24050",
    "sg:province":"Bergamo",
    "wof:name":"Technix (s.p.a.)",
    "wof:placetype":"venue"
},
  "geometry": {"coordinates":[9.710856,45.65237],"type":"Point"}
}