{
  "type": "Feature",
  "properties": {
    "iso:country":"IT",
    "sg:address":"12, Via Nazionale 24060 Spinone Al Lago",
    "sg:city":"Spinone al Lago",
    "sg:classifiers":[
        {
            "category":"Travel",
            "subcategory":"Travel Agent",
            "type":"Entertainment"
        }
    ],
    "sg:phone":"+39 39035810241",
    "sg:postcode":"24060",
    "sg:province":"Bergamo",
    "sg:tags":[
        "business"
    ],
    "wof:name":"Hotel S. Carlo",
    "wof:placetype":"venue"
},
  "geometry": {"coordinates":[9.92037,45.762318],"type":"Point"}
}