{
  "type": "Feature",
  "properties": {
    "iso:country":"IT",
    "sg:address":"Vle Cesare Battisti 26 13900 Biella",
    "sg:city":"Biella",
    "sg:classifiers":[
        {
            "category":"Sports & Exercise",
            "subcategory":"Ski Slope",
            "type":"Entertainment"
        }
    ],
    "sg:phone":"+39 015 34141",
    "sg:postcode":"13900",
    "sg:province":"Biella",
    "sg:tags":[
        "accessory"
    ],
    "sg:website":"www.filasport.it",
    "wof:name":"Fila Sport Spa",
    "wof:placetype":"venue"
},
  "geometry": {"coordinates":[8.05827,45.562836],"type":"Point"}
}