{
  "type": "Feature",
  "properties": {
    "iso:country":"IT",
    "sg:address":"53040 San Casciano Dei Bagni",
    "sg:city":"San Casciano dei Bagni",
    "sg:orig_category":"Ceramiche: Prodotti E Lavorazioni",
    "sg:phone":"+39 0578 50059",
    "sg:postcode":"53040",
    "sg:province":"Siena",
    "wof:name":"Tatfin Spa",
    "wof:placetype":"venue"
},
  "geometry": {"coordinates":[11.875212,42.871563],"type":"Point"}
}