{
  "type": "Feature",
  "properties": {
    "iso:country":"IT",
    "sg:address":"56, Via Bellinzago 28010 Caltignaga",
    "sg:city":"Caltignaga",
    "sg:classifiers":[
        {
            "category":"Food & Beverages",
            "subcategory":"Dairy",
            "type":"Retail Goods"
        }
    ],
    "sg:phone":"+39 0321 652198",
    "sg:postcode":"28010",
    "sg:province":"Novara",
    "sg:tags":[
        "product"
    ],
    "wof:name":"A. & L. Di Invernizzi Renato & C. Sas",
    "wof:placetype":"venue"
},
  "geometry": {"coordinates":[8.577285,45.538654],"type":"Point"}
}