{
  "type": "Feature",
  "properties": {
    "iso:country":"IT",
    "sg:address":"25012 Calvisano",
    "sg:city":"Calvisano",
    "sg:orig_category":"Utensili Meccanici E Materiali",
    "sg:phone":"+39 030 968 6204",
    "sg:postcode":"25012",
    "sg:province":"Brescia",
    "wof:name":"Chiro Snc Di Chiappani & Rosa",
    "wof:placetype":"venue"
},
  "geometry": {"coordinates":[10.334808,45.697723],"type":"Point"}
}