{
  "type": "Feature",
  "properties": {
    "addr:full":"Localita' Bettolino 25030 Brandico Brandico Brescia 25030",
    "addr:postcode":"25030;25030",
    "addr:street":"Localita ' Bettolino",
    "iso:country":"IT",
    "sg:address":"Localita' Bettolino 25030 Brandico",
    "sg:city":"Brandico",
    "sg:classifiers":[
        {
            "category":"Manufacturing",
            "subcategory":"Metals",
            "type":"Manufacturing & Wholesale Goods"
        }
    ],
    "sg:phone":"+39 030 997 2043",
    "sg:postcode":"25030",
    "sg:province":"Brescia",
    "sg:tags":[
        "processing"
    ],
    "wof:name":"Vedal S.r.l.",
    "wof:placetype":"venue"
},
  "geometry": {"coordinates":[10.2229576111,45.5398292542],"type":"Point"}
}