{
  "type": "Feature",
  "properties": {
    "iso:country":"IT",
    "sg:address":"Via Bari 44 59013 Montemurlo",
    "sg:city":"Montemurlo",
    "sg:classifiers":[
        {
            "category":"Shopping",
            "subcategory":"Crafts & Fabrics",
            "type":"Retail Goods"
        }
    ],
    "sg:phone":"+39 0574 791423",
    "sg:postcode":"59013",
    "sg:province":"Prato",
    "sg:tags":[
        "silk"
    ],
    "sg:website":"www.mtrisaliti.it",
    "wof:name":"Manifattura Tessile Risaliti Srl",
    "wof:placetype":"venue"
},
  "geometry": {"coordinates":[11.026532,43.92345],"type":"Point"}
}