{
  "type": "Feature",
  "properties": {
    "iso:country":"IT",
    "sg:address":"50041 Settimello",
    "sg:city":"Settimello",
    "sg:orig_category":"Prodotti E Manufatti In Materie Plastiche",
    "sg:phone":"+39 055 882 4516",
    "sg:postcode":"50041",
    "sg:province":"Firenze",
    "wof:name":"Bigattini Caterina",
    "wof:placetype":"venue"
},
  "geometry": {"coordinates":[11.1779642105,43.8503456116],"type":"Point"}
}