{
  "type": "Feature",
  "properties": {
    "iso:country":"IT",
    "sg:address":"5, Via Brigate Garibaldi 56035 Lari",
    "sg:city":"Lari",
    "sg:classifiers":[
        {
            "category":"Home & Garden",
            "subcategory":"Home Furnishings",
            "type":"Retail Goods"
        }
    ],
    "sg:phone":"+39 0587 616829",
    "sg:postcode":"56035",
    "sg:province":"Pisa",
    "sg:tags":[
        "household"
    ],
    "wof:name":"2b Srl",
    "wof:placetype":"venue"
},
  "geometry": {"coordinates":[10.396585,43.716137],"type":"Point"}
}