{
  "type": "Feature",
  "properties": {
    "iso:country":"IT",
    "sg:address":"4, Via Brodolini 40056 Crespellano",
    "sg:city":"Crespellano",
    "sg:classifiers":[
        {
            "category":"Food & Beverages",
            "subcategory":"Groceries & Convenience Stores",
            "type":"Retail Goods"
        }
    ],
    "sg:phone":"+39 39051969072",
    "sg:postcode":"40056",
    "sg:province":"Bologna",
    "sg:tags":[
        "product",
        "related"
    ],
    "wof:name":"Dino Corsini S.r.l.",
    "wof:placetype":"venue"
},
  "geometry": {"coordinates":[11.174448967,44.5189361572],"type":"Point"}
}