{
  "type": "Feature",
  "properties": {
    "addr:full":"37050 Oppeano Oppeano Verona 37050",
    "addr:postcode":"37050;37050",
    "iso:country":"IT",
    "sg:address":"37050 Oppeano",
    "sg:city":"Oppeano",
    "sg:orig_category":"Prodotti Chimici Di Base",
    "sg:phone":"+39 045 698 4236",
    "sg:postcode":"37050",
    "sg:province":"Verona",
    "wof:name":"Isover Di Puttini Mauro E C. Snc",
    "wof:placetype":"venue"
},
  "geometry": {"coordinates":[11.0816907883,45.3269729614],"type":"Point"}
}