{
  "type": "Feature",
  "properties": {
    "iso:country":"IT",
    "sg:address":"00185 Roma",
    "sg:city":"Roma",
    "sg:orig_category":"Banche E Servizi Finanziari",
    "sg:phone":"+39 06 487 2737",
    "sg:postcode":"00185",
    "sg:province":"Roma",
    "wof:name":"Tranchina Francesco",
    "wof:placetype":"venue"
},
  "geometry": {"coordinates":[12.499718,41.895851],"type":"Point"}
}