{
  "type": "Feature",
  "properties": {
    "addr:full":"Via M. Zanagnolo 8/c 25065 Lumezzane Lumezzane Brescia 25065",
    "addr:housenumber":"8 / c",
    "addr:postcode":"25065;25065",
    "addr:street":"Via M. Zanagnolo",
    "iso:country":"IT",
    "sg:address":"Via M. Zanagnolo 8/c 25065 Lumezzane",
    "sg:city":"Lumezzane",
    "sg:classifiers":[
        {
            "category":"Professional",
            "type":"Services"
        }
    ],
    "sg:phone":"+39 030 872064",
    "sg:postcode":"25065",
    "sg:province":"Brescia",
    "sg:tags":[
        "mould",
        "construction"
    ],
    "sg:website":"www.mariofernando.com",
    "wof:name":"Mario Fernando Srl",
    "wof:placetype":"venue"
},
  "geometry": {"coordinates":[10.2229576111,45.5398292542],"type":"Point"}
}