{
  "type": "Feature",
  "properties": {
    "iso:country":"IT",
    "sg:address":"37047 San Bonifacio",
    "sg:city":"San Bonifacio",
    "sg:orig_category":"Magazzinaggio E Logistica Industriale - Impianti Ed Attrezzature",
    "sg:phone":"+39 045 761 4434",
    "sg:postcode":"37047",
    "sg:province":"Verona",
    "wof:name":"Siat Sas",
    "wof:placetype":"venue"
},
  "geometry": {"coordinates":[11.273354,45.400429],"type":"Point"}
}