{
  "type": "Feature",
  "properties": {
    "iso:country":"IT",
    "sg:address":"14, Contrada Lisoni 82024 Colle Sannita",
    "sg:city":"Colle Sannita",
    "sg:classifiers":[
        {
            "category":"Real Estate",
            "subcategory":"Architect",
            "type":"Services"
        }
    ],
    "sg:phone":"+39 0824 931562",
    "sg:postcode":"82024",
    "sg:province":"Benevento",
    "sg:tags":[
        "textile",
        "clothing"
    ],
    "wof:name":"Piacquadio Carmela",
    "wof:placetype":"venue"
},
  "geometry": {"coordinates":[14.854473,41.384052],"type":"Point"}
}