{
  "type": "Feature",
  "properties": {
    "iso:country":"IT",
    "sg:address":"38, Viuzzo Di Porto 50018 Scandicci",
    "sg:city":"Scandicci",
    "sg:classifiers":[
        {
            "category":"Personal",
            "subcategory":"Shoe Repair & Shine",
            "type":"Services"
        }
    ],
    "sg:phone":"+39 39055722101",
    "sg:postcode":"50018",
    "sg:province":"Firenze",
    "sg:tags":[
        "leather"
    ],
    "wof:name":"Coach Europe Services Srl",
    "wof:placetype":"venue"
},
  "geometry": {"coordinates":[11.156737,43.769733],"type":"Point"}
}