{
  "type": "Feature",
  "properties": {
    "addr:full":"Via Aiello 84096 Montecorvino Rovella Montecorvino Rovella Salerno 84096",
    "addr:postcode":"84096;84096",
    "addr:street":"Via Aiello",
    "iso:country":"IT",
    "sg:address":"Via Aiello 84096 Montecorvino Rovella",
    "sg:city":"Montecorvino Rovella",
    "sg:classifiers":[
        {
            "category":"Real Estate",
            "subcategory":"Architect",
            "type":"Services"
        }
    ],
    "sg:phone":"+39 39089800878",
    "sg:postcode":"84096",
    "sg:province":"Salerno",
    "sg:tags":[
        "textile",
        "clothing"
    ],
    "wof:name":"C.p.confezioni Sas Di Castagna Pasquale & C",
    "wof:placetype":"venue"
},
  "geometry": {"coordinates":[16.209755,39.50251],"type":"Point"}
}