{
  "type": "Feature",
  "properties": {
    "iso:country":"IT",
    "sg:address":"16158 Genova",
    "sg:city":"Genova",
    "sg:orig_category":"Apparecchiature E Sistemi Per Imballaggio E Confezionamento. Apparecchiature E Sistemi Per Magazzinaggio E Movimentazione",
    "sg:phone":"+39 010 612 1695",
    "sg:postcode":"16158",
    "sg:province":"Genova",
    "wof:name":"Dgt World Srl",
    "wof:placetype":"venue"
},
  "geometry": {"coordinates":[8.693069,44.454037],"type":"Point"}
}