{
  "type": "Feature",
  "properties": {
    "iso:country":"IT",
    "sg:address":"Localita' Ponte Giulio 05018 Orvieto",
    "sg:city":"Orvieto",
    "sg:classifiers":[
        {
            "category":"Home & Garden",
            "subcategory":"Home Furnishings",
            "type":"Retail Goods"
        }
    ],
    "sg:phone":"+39 0763 316044",
    "sg:postcode":"05018",
    "sg:province":"Terni",
    "sg:tags":[
        "household"
    ],
    "wof:name":"Ponte Giulio (s.p.a.)",
    "wof:placetype":"venue"
},
  "geometry": {"coordinates":[12.055044,42.766045],"type":"Point"}
}