{
  "type": "Feature",
  "properties": {
    "iso:country":"IT",
    "sg:address":"109, Via Gaetano Donizetti 24030 Brembate Di Sopra",
    "sg:city":"Brembate di Sopra",
    "sg:classifiers":[
        {
            "category":"Personal",
            "subcategory":"Shoe Repair & Shine",
            "type":"Services"
        }
    ],
    "sg:phone":"+39 39035621847",
    "sg:postcode":"24030",
    "sg:province":"Bergamo",
    "sg:tags":[
        "leather"
    ],
    "wof:name":"Anna Rossi Di Rossi Anna Maria",
    "wof:placetype":"venue"
},
  "geometry": {"coordinates":[9.58511,45.70895],"type":"Point"}
}