{
  "type": "Feature",
  "properties": {
    "iso:country":"IT",
    "sg:address":"34122 Trieste",
    "sg:city":"Trieste",
    "sg:orig_category":"Servizi Vari Di Interesse Pubblico",
    "sg:phone":"+39 040 364173",
    "sg:postcode":"34122",
    "sg:province":"Trieste",
    "wof:name":"Amicamente Di Bandi Roberto",
    "wof:placetype":"venue"
},
  "geometry": {"coordinates":[13.777056,45.650249],"type":"Point"}
}