{
  "type": "Feature",
  "properties": {
    "iso:country":"IT",
    "sg:address":"11010 Introd",
    "sg:city":"Introd",
    "sg:orig_category":"Alberghi E Strutture Extra Alberghiere. Ospedali E Servizi Sanitari",
    "sg:phone":"+39 0165 99205",
    "sg:postcode":"11010",
    "sg:province":"Aosta",
    "wof:name":"Soggiorno Alpino Don Bosco",
    "wof:placetype":"venue"
},
  "geometry": {"coordinates":[7.182156,45.692921],"type":"Point"}
}