{
  "type": "Feature",
  "properties": {
    "iso:country":"IT",
    "sg:address":"17, Via Bonetti 20024 Garbagnate Milanese",
    "sg:city":"Garbagnate Milanese",
    "sg:classifiers":[
        {
            "category":"Shopping",
            "type":"Retail Goods"
        }
    ],
    "sg:phone":"+39 390 299 0721",
    "sg:postcode":"20024",
    "sg:province":"Milano",
    "sg:tags":[
        "finished",
        "-",
        "metallic"
    ],
    "wof:name":"Bonetti Cesare S.p.a.",
    "wof:placetype":"venue"
},
  "geometry": {"coordinates":[9.0713329315,45.580165863],"type":"Point"}
}