{
  "type": "Feature",
  "properties": {
    "iso:country":"IT",
    "sg:address":"Via Collegio Di Spagna 34 40064 Ozzano Dell'emilia",
    "sg:orig_category":"Fuel Funnels",
    "sg:phone":"+39 051 799229",
    "sg:postcode":"40064",
    "sg:province":"Bologna",
    "sg:website":"www.silea.it",
    "wof:name":"Silea Spa",
    "wof:placetype":"venue"
},
  "geometry": {"coordinates":[11.4813928604,44.4403381348],"type":"Point"}
}