{
  "type": "Feature",
  "properties": {
    "addr:full":"20127 Milano Milano Milano 20127",
    "addr:postcode":"20127;20127",
    "iso:country":"IT",
    "sg:address":"20127 Milano",
    "sg:city":"Milano",
    "sg:classifiers":[
        {
            "category":"Structure",
            "subcategory":"Factory",
            "type":"Public Place"
        }
    ],
    "sg:phone":"+39 02 284 7286",
    "sg:postcode":"20127",
    "sg:province":"Milano",
    "sg:tags":[
        "steelworks",
        "foundry"
    ],
    "wof:name":"Fonderia D'arte M.a.f. Snc",
    "wof:placetype":"venue"
},
  "geometry": {"coordinates":[9.21195,45.490257],"type":"Point"}
}