{
  "type": "Feature",
  "properties": {
    "iso:country":"IT",
    "sg:address":"20025 Legnano",
    "sg:city":"Legnano",
    "sg:orig_category":"Macchine Tessili - Accessori E Forniture",
    "sg:phone":"+39 0331 459675",
    "sg:postcode":"20025",
    "sg:province":"Milano",
    "wof:name":"Ace Di Barbui Davide & Figli Srl",
    "wof:placetype":"venue"
},
  "geometry": {"coordinates":[9.217262,45.479286],"type":"Point"}
}