{
  "type": "Feature",
  "properties": {
    "iso:country":"IT",
    "sg:address":"9, Via Paolo Baffi 70024 Gravina In Puglia",
    "sg:city":"Gravina in Puglia",
    "sg:classifiers":[
        {
            "category":"Home & Garden",
            "subcategory":"Home Furnishings",
            "type":"Retail Goods"
        }
    ],
    "sg:phone":"+39 080 325 6366",
    "sg:postcode":"70024",
    "sg:province":"Bari",
    "sg:tags":[
        "household"
    ],
    "wof:name":"Nuova Immagine Srl",
    "wof:placetype":"venue"
},
  "geometry": {"coordinates":[16.869291,41.126053],"type":"Point"}
}