{
  "type": "Feature",
  "properties": {
    "addr:full":"10094 Giaveno Giaveno Torino 10094",
    "addr:postcode":"10094;10094",
    "iso:country":"IT",
    "sg:address":"10094 Giaveno",
    "sg:city":"Giaveno",
    "sg:orig_category":"Prodotti Vari In Metallo",
    "sg:phone":"+39 011 937 6977",
    "sg:postcode":"10094",
    "sg:province":"Torino",
    "wof:name":"Ferlanda Daniele",
    "wof:placetype":"venue"
},
  "geometry": {"coordinates":[7.3524036407,45.0419120789],"type":"Point"}
}