{
  "type": "Feature",
  "properties": {
    "iso:country":"IT",
    "sg:address":"26900 Lodi",
    "sg:city":"Lodi",
    "sg:classifiers":[
        {
            "category":"Health Services",
            "subcategory":"Health Practitioner",
            "type":"Services"
        }
    ],
    "sg:phone":"+39 0371 98065",
    "sg:postcode":"26900",
    "sg:province":"Lodi",
    "sg:tags":[
        "medici"
    ],
    "wof:name":"Bianchi Dr. Maurizio",
    "wof:placetype":"venue"
},
  "geometry": {"coordinates":[9.505635,45.310959],"type":"Point"}
}