{
  "type": "Feature",
  "properties": {
    "iso:country":"IT",
    "sg:address":"05022 Amelia",
    "sg:city":"Amelia",
    "sg:classifiers":[
        {
            "category":"Restaurant",
            "type":"Food & Drink"
        }
    ],
    "sg:phone":"+39 0744 983925",
    "sg:postcode":"05022",
    "sg:province":"Terni",
    "sg:tags":[
        "auxiliary",
        "entertainment",
        "premises",
        "related",
        "catering",
        "similar",
        "public",
        "restaurants"
    ],
    "sg:website":"http://www.giubileoitalia.com/carleni",
    "wof:name":"Carleni",
    "wof:placetype":"venue"
},
  "geometry": {"coordinates":[12.413044,42.557377],"type":"Point"}
}