{
  "type": "Feature",
  "properties": {
    "iso:country":"IT",
    "sg:address":"Via Sabbioni 2 35024 Bovolenta",
    "sg:city":"Bovolenta",
    "sg:classifiers":[
        {
            "category":"Bus Stop",
            "subcategory":"None",
            "type":"Transportation"
        }
    ],
    "sg:phone":"+39 049 884 0322",
    "sg:postcode":"35024",
    "sg:province":"Padova",
    "sg:tags":[
        "autoclave"
    ],
    "sg:website":"www.varem.com",
    "wof:name":"Varem S.p.a.",
    "wof:placetype":"venue"
},
  "geometry": {"coordinates":[11.92722,45.267864],"type":"Point"}
}