{
  "type": "Feature",
  "properties": {
    "iso:country":"IT",
    "sg:address":"31040 Porcellengo",
    "sg:orig_category":"Tempo Libero - Articoli E Forniture. Regalistica Aziendale",
    "sg:phone":"+39 0422 480380",
    "sg:postcode":"31040",
    "sg:province":"Treviso",
    "wof:name":"Karnaval Di Carnevale Franco & C. S.a.s.",
    "wof:placetype":"venue"
},
  "geometry": {"coordinates":[12.242072,45.666286],"type":"Point"}
}