{
  "type": "Feature",
  "properties": {
    "iso:country":"IT",
    "sg:address":"25010 San Zeno Naviglio",
    "sg:city":"San Zeno Naviglio",
    "sg:orig_category":"Servizi Culturali E Per Lo Spettacolo. Servizi Al Turismo. Acqua, Luce, Gas E Societa' Di Esercizio Pubblico",
    "sg:phone":"+39 030 266486",
    "sg:postcode":"25010",
    "sg:province":"Brescia",
    "wof:name":"Municipio",
    "wof:placetype":"venue"
},
  "geometry": {"coordinates":[10.213227,45.489998],"type":"Point"}
}