{
  "type": "Feature",
  "properties": {
    "iso:country":"IT",
    "sg:address":"83030 Manocalzati",
    "sg:city":"Manocalzati",
    "sg:orig_category":"Prodotti Chimici Di Base. Ospedali E Servizi Sanitari",
    "sg:phone":"+39 0825 675395",
    "sg:postcode":"83030",
    "sg:province":"Avellino",
    "wof:name":"Son Spa",
    "wof:placetype":"venue"
},
  "geometry": {"coordinates":[14.8506298065,40.9426651001],"type":"Point"}
}