{
  "type": "Feature",
  "properties": {
    "iso:country":"IT",
    "sg:address":"20091 Bresso",
    "sg:city":"Bresso",
    "sg:orig_category":"Apparecchiature Ed Attrezzature Meccaniche",
    "sg:phone":"+39 02 614 2925",
    "sg:postcode":"20091",
    "sg:province":"Milano",
    "wof:name":"Costruzioni Elettriche Cerruti Srl",
    "wof:placetype":"venue"
},
  "geometry": {"coordinates":[9.195135,45.531784],"type":"Point"}
}