{
  "type": "Feature",
  "properties": {
    "addr:full":"03100 Frosinone Frosinone Frosinone 03100",
    "addr:postcode":"03100;03100",
    "iso:country":"IT",
    "sg:address":"03100 Frosinone",
    "sg:city":"Frosinone",
    "sg:orig_category":"Arredamenti E Mobili Professionali. Impianti, Attrezzature E Forniture Sanitarie Ed Ospedaliere",
    "sg:phone":"+39 0775 250042",
    "sg:postcode":"03100",
    "sg:province":"Frosinone",
    "wof:name":"Martelletti Sergio",
    "wof:placetype":"venue"
},
  "geometry": {"coordinates":[13.347377,41.638233],"type":"Point"}
}