{
  "type": "Feature",
  "properties": {
    "iso:country":"IT",
    "sg:address":"19, Via Artigianato 25034 Orzinuovi",
    "sg:city":"Orzinuovi",
    "sg:classifiers":[
        {
            "category":"Wholesale",
            "subcategory":"Machinery & Supplies",
            "type":"Manufacturing & Wholesale Goods"
        }
    ],
    "sg:phone":"+39 39030944153",
    "sg:postcode":"25034",
    "sg:province":"Brescia",
    "sg:tags":[
        "-",
        "agriculture",
        "equipment"
    ],
    "wof:name":"Fbf Fossi Srl",
    "wof:placetype":"venue"
},
  "geometry": {"coordinates":[9.943603,45.410786],"type":"Point"}
}