{
  "type": "Feature",
  "properties": {
    "iso:country":"IT",
    "sg:address":"00144 Roma",
    "sg:city":"Roma",
    "sg:orig_category":"Orologeria. Shopping",
    "sg:phone":"+39 06 529 7317",
    "sg:postcode":"00144",
    "sg:province":"Roma",
    "sg:website":"http://www.giftregali.it",
    "wof:name":"Gift",
    "wof:placetype":"venue"
},
  "geometry": {"coordinates":[12.453806,41.820316],"type":"Point"}
}