{
  "type": "Feature",
  "properties": {
    "iso:country":"IT",
    "sg:address":"01100 Viterbo",
    "sg:city":"Viterbo",
    "sg:orig_category":"Prodotti Alimentari",
    "sg:phone":"+39 0761 333050",
    "sg:postcode":"01100",
    "sg:province":"Viterbo",
    "sg:website":"http://www.vitamin-store.net",
    "wof:name":"Commingest Srl",
    "wof:placetype":"venue"
},
  "geometry": {"coordinates":[12.0489788055,42.4415359497],"type":"Point"}
}