{
  "type": "Feature",
  "properties": {
    "addr:full":"20019 Settimo Milanese Settimo Milanese Milano 20019",
    "addr:postcode":"20019;20019",
    "iso:country":"IT",
    "sg:address":"20019 Settimo Milanese",
    "sg:city":"Settimo Milanese",
    "sg:orig_category":"Servizi E Lavori Per Industria Alimentare E Bevande",
    "sg:phone":"+39 02 328 1391",
    "sg:postcode":"20019",
    "sg:province":"Milano",
    "wof:name":"Sviluppo Discount S.p.a.",
    "wof:placetype":"venue"
},
  "geometry": {"coordinates":[9.053477,45.487156],"type":"Point"}
}