{
  "type": "Feature",
  "properties": {
    "iso:country":"IT",
    "sg:address":"59100 Prato",
    "sg:city":"Prato",
    "sg:orig_category":"Forniture Per Agricoltura E Zootecnia. Animali Domestici",
    "sg:phone":"+39 0574 25112",
    "sg:postcode":"59100",
    "sg:province":"Prato",
    "wof:name":"L'arca Di Noe' Di Calabrese Mauro",
    "wof:placetype":"venue"
},
  "geometry": {"coordinates":[11.0938081741,43.8780326843],"type":"Point"}
}