{
  "type": "Feature",
  "properties": {
    "iso:country":"IT",
    "sg:address":"33100 Udine",
    "sg:city":"Udine",
    "sg:orig_category":"Servizi Di Magazzinaggio E Movimentazione. Servizi Ausiliari Di Sorveglianza, Manutenzione E Pulizia",
    "sg:phone":"+39 0432 523220",
    "sg:postcode":"33100",
    "sg:province":"Udine",
    "wof:name":"Cooperativa Smistamento Merci E Portabagagli",
    "wof:placetype":"venue"
},
  "geometry": {"coordinates":[13.250272,46.05666],"type":"Point"}
}