{
  "type": "Feature",
  "properties": {
    "addr:full":"36020 Solagna Solagna Vicenza 36020",
    "addr:postcode":"36020;36020",
    "iso:country":"IT",
    "sg:address":"36020 Solagna",
    "sg:city":"Solagna",
    "sg:orig_category":"Pubblica Amministrazione",
    "sg:phone":"+39 0424 558293",
    "sg:postcode":"36020",
    "sg:province":"Vicenza",
    "wof:name":"Comune Di Solagna",
    "wof:placetype":"venue"
},
  "geometry": {"coordinates":[11.4985456467,45.5945358276],"type":"Point"}
}