{
  "type": "Feature",
  "properties": {
    "iso:country":"IT",
    "sg:address":"74/d, Strada Statale 231 12066 Monticello D'alba",
    "sg:classifiers":[
        {
            "category":"Professional",
            "subcategory":"Engineering",
            "type":"Services"
        }
    ],
    "sg:phone":"+39 0173 361525",
    "sg:postcode":"12066",
    "sg:province":"Cuneo",
    "sg:tags":[
        "machine",
        "-",
        "mechanical"
    ],
    "wof:name":"C.r.e. (s.r.l.)",
    "wof:placetype":"venue"
},
  "geometry": {"coordinates":[7.547111,44.388798],"type":"Point"}
}