{
  "type": "Feature",
  "properties": {
    "iso:country":"IT",
    "sg:address":"Via Superstr.san Marino Km.7 47853 Coriano",
    "sg:city":"Coriano",
    "sg:classifiers":[
        {
            "category":"Farming",
            "subcategory":"Livestock Farm",
            "type":"Manufacturing & Wholesale Goods"
        }
    ],
    "sg:phone":"+39 0541 759448",
    "sg:postcode":"47853",
    "sg:province":"Rimini",
    "sg:tags":[
        "agriculture"
    ],
    "wof:name":"Italsementi S.a.s. Di Annibali Iliano & C.",
    "wof:placetype":"venue"
},
  "geometry": {"coordinates":[12.566257,44.06078],"type":"Point"}
}