{
  "type": "Feature",
  "properties": {
    "addr:full":"20134 Milano Milano Milano 20134",
    "addr:postcode":"20134;20134",
    "iso:country":"IT",
    "sg:address":"20134 Milano",
    "sg:city":"Milano",
    "sg:classifiers":[
        {
            "category":"Health Services",
            "subcategory":"Health Practitioner",
            "type":"Services"
        }
    ],
    "sg:phone":"+39 02 215 7876",
    "sg:postcode":"20134",
    "sg:province":"Milano",
    "sg:tags":[
        "medici"
    ],
    "wof:name":"Tedone Luigi",
    "wof:placetype":"venue"
},
  "geometry": {"coordinates":[9.2407646179,45.4877586365],"type":"Point"}
}