{
  "type": "Feature",
  "properties": {
    "iso:country":"IT",
    "sg:address":"26, Via Alpignano 10040 San Gillio",
    "sg:city":"San Gillio",
    "sg:classifiers":[
        {
            "category":"Shopping",
            "subcategory":"Computers & Home Electronics",
            "type":"Retail Goods"
        }
    ],
    "sg:phone":"+39 011 984 0744",
    "sg:postcode":"10040",
    "sg:province":"Torino",
    "sg:tags":[
        "electronic",
        "electrical",
        "equipment"
    ],
    "wof:name":"Ge.d.a.t. (s.n.c.)",
    "wof:placetype":"venue"
},
  "geometry": {"coordinates":[7.571543,45.107975],"type":"Point"}
}