{
  "type": "Feature",
  "properties": {
    "iso:country":"IT",
    "sg:address":"44, Via Monti Vincenzo 20123 Milano",
    "sg:city":"Milano",
    "sg:classifiers":[
        {
            "category":"Food & Beverages",
            "subcategory":"Groceries & Convenience Stores",
            "type":"Retail Goods"
        }
    ],
    "sg:phone":"+39 02 4801 1737",
    "sg:postcode":"20123",
    "sg:province":"Milano",
    "sg:tags":[
        "drink"
    ],
    "wof:name":"Savini Claudio & Figli (s.r.l.)",
    "wof:placetype":"venue"
},
  "geometry": {"coordinates":[9.16919,45.470905],"type":"Point"}
}