{
  "type": "Feature",
  "properties": {
    "addr:full":"10071 Borgaro Torinese Borgaro Torinese Torino 10071",
    "addr:postcode":"10071;10071",
    "iso:country":"IT",
    "sg:address":"10071 Borgaro Torinese",
    "sg:city":"Borgaro Torinese",
    "sg:orig_category":"Accessori Moda D'abbigliamento. Forniture Per Abbigliamento E Pelletterie. Shopping",
    "sg:phone":"+39 011 470 2946",
    "sg:postcode":"10071",
    "sg:province":"Torino",
    "wof:name":"Idea Ricamo",
    "wof:placetype":"venue"
},
  "geometry": {"coordinates":[7.658764,45.137989],"type":"Point"}
}