{
  "type": "Feature",
  "properties": {
    "iso:country":"IT",
    "sg:address":"20021 Bollate",
    "sg:city":"Bollate",
    "sg:classifiers":[
        {
            "category":"Health Services",
            "subcategory":"Health Practitioner",
            "type":"Services"
        }
    ],
    "sg:phone":"+39 02 350 2759",
    "sg:postcode":"20021",
    "sg:province":"Milano",
    "sg:tags":[
        "medici"
    ],
    "wof:name":"Uboldi Luigi",
    "wof:placetype":"venue"
},
  "geometry": {"coordinates":[9.111415863,45.5399932861],"type":"Point"}
}