{
  "type": "Feature",
  "properties": {
    "iso:country":"IT",
    "sg:address":"20144 Milano",
    "sg:city":"Milano",
    "sg:orig_category":"Servizi E Lavori Per Abbigliamento E Pelletterie",
    "sg:phone":"+39 02 468566",
    "sg:postcode":"20144",
    "sg:province":"Milano",
    "wof:name":"Ingenito Sabatina",
    "wof:placetype":"venue"
},
  "geometry": {"coordinates":[9.162424,45.456051],"type":"Point"}
}