{
  "type": "Feature",
  "properties": {
    "addr:full":"20090 Cusago Cusago Milano 20090",
    "addr:postcode":"20090;20090",
    "iso:country":"IT",
    "sg:address":"20090 Cusago",
    "sg:city":"Cusago",
    "sg:orig_category":"Scuole E Servizi Scolastici",
    "sg:phone":"+39 02 901 9096",
    "sg:postcode":"20090",
    "sg:province":"Milano",
    "wof:name":"Scuola Elementare G. Pascoli",
    "wof:placetype":"venue"
},
  "geometry": {"coordinates":[9.034652,45.447605],"type":"Point"}
}