{
  "type": "Feature",
  "properties": {
    "iso:country":"IT",
    "sg:address":"Via Maretto 13 43010 Roncopascolo Parma",
    "sg:classifiers":[
        {
            "category":"Shopping",
            "subcategory":"Beauty & Cosmetics",
            "type":"Retail Goods"
        }
    ],
    "sg:phone":"+39 0521 662111",
    "sg:postcode":"43010",
    "sg:province":"Parma",
    "sg:tags":[
        "perfume"
    ],
    "sg:website":"www.henkel.com",
    "wof:name":"Morris Profumi",
    "wof:placetype":"venue"
},
  "geometry": {"coordinates":[10.2771816254,44.8606567383],"type":"Point"}
}