{
  "type": "Feature",
  "properties": {
    "iso:country":"IT",
    "sg:address":"5, Via Alcide De Gasperi 24050 Pumenengo",
    "sg:city":"Pumenengo",
    "sg:classifiers":[
        {
            "category":"Professional",
            "subcategory":"Engineering",
            "type":"Services"
        }
    ],
    "sg:phone":"+39 036 399 4019",
    "sg:postcode":"24050",
    "sg:province":"Bergamo",
    "sg:tags":[
        "machine",
        "-",
        "mechanical"
    ],
    "wof:name":"Sepam Srl",
    "wof:placetype":"venue"
},
  "geometry": {"coordinates":[9.866211,45.482578],"type":"Point"}
}