{
  "type": "Feature",
  "properties": {
    "addr:full":"214, Corso Chieri 10132 Torino Torino Torino 10132",
    "addr:postcode":"10132;10132",
    "addr:street":"Corso Chieri",
    "iso:country":"IT",
    "sg:address":"214, Corso Chieri 10132 Torino",
    "sg:city":"Torino",
    "sg:classifiers":[
        {
            "category":"Professional",
            "subcategory":"Printing & Photocopies",
            "type":"Services"
        }
    ],
    "sg:phone":"+39 011 898 0549",
    "sg:postcode":"10132",
    "sg:province":"Torino",
    "wof:name":"Scaletta Carlo (s.n.c.)",
    "wof:placetype":"venue"
},
  "geometry": {"coordinates":[7.7469277382,45.0543365479],"type":"Point"}
}