{
  "type": "Feature",
  "properties": {
    "addr:full":"Via Della Casella 51/a 50142 Firenze Firenze Firenze 50142",
    "addr:housenumber":"51 / a",
    "addr:postcode":"50142;50142",
    "addr:street":"Via Della Casella",
    "iso:country":"IT",
    "sg:address":"Via Della Casella 51/a 50142 Firenze",
    "sg:city":"Firenze",
    "sg:orig_category":"Ladies' Hats",
    "sg:phone":"+39 055 787 7261",
    "sg:postcode":"50142",
    "sg:province":"Firenze",
    "wof:name":"Memar Srl",
    "wof:placetype":"venue"
},
  "geometry": {"coordinates":[11.256902,43.768734],"type":"Point"}
}