{
  "type": "Feature",
  "properties": {
    "iso:country":"IT",
    "sg:address":"25122 Brescia",
    "sg:city":"Brescia",
    "sg:orig_category":"Associazioni Ed Istituti Di Previdenza Ed Assistenza",
    "sg:phone":"+39 030 289061",
    "sg:postcode":"25122",
    "sg:province":"Brescia",
    "wof:name":"Cassa Assistenziale Paritetica Edile",
    "wof:placetype":"venue"
},
  "geometry": {"coordinates":[10.215284,45.540356],"type":"Point"}
}