{
  "type": "Feature",
  "properties": {
    "addr:full":"63039 San Benedetto Tronto Ascoli Piceno 63039",
    "addr:housenumber":"63039",
    "addr:postcode":"63039",
    "addr:street":"San;Tronto;Piceno",
    "iso:country":"IT",
    "sg:address":"63039 San Benedetto Tronto",
    "sg:orig_category":"Apparecchiature Ed Attrezzature Meccaniche",
    "sg:phone":"+39 0735 76171",
    "sg:postcode":"63039",
    "sg:province":"Ascoli Piceno",
    "sg:website":"http://www.tecnoforniture.it",
    "wof:name":"Tecnoforniture Srl",
    "wof:placetype":"venue"
},
  "geometry": {"coordinates":[13.895902,42.899284],"type":"Point"}
}