{
  "type": "Feature",
  "properties": {
    "addr:full":"70126 Bari Bari Bari 70126",
    "addr:postcode":"70126;70126",
    "iso:country":"IT",
    "sg:address":"70126 Bari",
    "sg:city":"Bari",
    "sg:orig_category":"Prodotti Chimici Secondari. Macchine E Forniture Per Ecologia E Smaltimento Rifiuti",
    "sg:phone":"+39 080 556 1205",
    "sg:postcode":"70126",
    "sg:province":"Bari",
    "wof:name":"Sogea Di Falconieri Francesco & C. S.a.s.",
    "wof:placetype":"venue"
},
  "geometry": {"coordinates":[16.9181537628,41.0904960632],"type":"Point"}
}