{
  "type": "Feature",
  "properties": {
    "iso:country":"IT",
    "sg:address":"15/e, Via Castel Morrone 16161 Genova",
    "sg:city":"Genova",
    "sg:classifiers":[
        {
            "category":"Shopping",
            "type":"Retail Goods"
        }
    ],
    "sg:phone":"+39 010 740 3924",
    "sg:postcode":"16161",
    "sg:province":"Genova",
    "sg:tags":[
        "finished",
        "-",
        "metallic"
    ],
    "wof:name":"Officine Mario Bacigalupi Di Antonino Marchica & C. Snc",
    "wof:placetype":"venue"
},
  "geometry": {"coordinates":[8.8895225525,44.449508667],"type":"Point"}
}