{
  "type": "Feature",
  "properties": {
    "iso:country":"IT",
    "sg:address":"56127 Pisa",
    "sg:city":"Pisa",
    "sg:orig_category":"Agenzie D'affari E Servizi Commerciali. Acqua, Luce, Gas E Societa' Di Esercizio Pubblico",
    "sg:phone":"+39 050 554790",
    "sg:postcode":"56127",
    "sg:province":"Pisa",
    "wof:name":"Istituto Vendite Giudiziarie",
    "wof:placetype":"venue"
},
  "geometry": {"coordinates":[10.407223,43.724106],"type":"Point"}
}