{
  "type": "Feature",
  "properties": {
    "addr:full":"03014 Fiuggi Fiuggi Frosinone 03014",
    "addr:postcode":"03014;03014",
    "iso:country":"IT",
    "sg:address":"03014 Fiuggi",
    "sg:city":"Fiuggi",
    "sg:orig_category":"Ospedali E Servizi Sanitari",
    "sg:phone":"+39 0775 505199",
    "sg:postcode":"03014",
    "sg:province":"Frosinone",
    "wof:name":"Croce Verde Anticolana S.n.c. Di Tucciarelli M. & Girolami A.",
    "wof:placetype":"venue"
},
  "geometry": {"coordinates":[13.216766,41.802368],"type":"Point"}
}