{
  "type": "Feature",
  "properties": {
    "iso:country":"IT",
    "sg:address":"53036 Poggibonsi",
    "sg:city":"Poggibonsi",
    "sg:orig_category":"Studi E Consulenze Tecniche E Industriali. Consulenze Tecniche, Amministrative E Perizie",
    "sg:phone":"+39 0577 982560",
    "sg:postcode":"53036",
    "sg:province":"Siena",
    "sg:website":"http://www.ctp.it",
    "wof:name":"Ctp Tecnologie Di Processo Srl",
    "wof:placetype":"venue"
},
  "geometry": {"coordinates":[11.152577,43.469707],"type":"Point"}
}