{
  "type": "Feature",
  "properties": {
    "iso:country":"IT",
    "sg:address":"2, Via Dei Carroz 09131 Cagliari",
    "sg:city":"Cagliari",
    "sg:classifiers":[
        {
            "category":"Autos & Motor Vehicles",
            "subcategory":"Automobile Sales",
            "type":"Retail Goods"
        }
    ],
    "sg:phone":"+39 390 705 5051",
    "sg:postcode":"09131",
    "sg:province":"Cagliari",
    "sg:tags":[
        "motor-cars"
    ],
    "wof:name":"Acentro S.r.l.",
    "wof:placetype":"venue"
},
  "geometry": {"coordinates":[9.1212215424,39.2373771667],"type":"Point"}
}