{
  "type": "Feature",
  "properties": {
    "iso:country":"IT",
    "sg:address":"Via B Cremagnani 13; Vimercate",
    "sg:classifiers":[
        {
            "category":"Banks & Credit Unions",
            "subcategory":"Bank",
            "type":"Services"
        }
    ],
    "sg:phone":"+39 039 685 2171",
    "wof:name":"Banca Di Roma",
    "wof:placetype":"venue"
},
  "geometry": {"coordinates":[9.362523,45.613499],"type":"Point"}
}