{
  "type": "Feature",
  "properties": {
    "addr:full":"25134 Brescia Brescia Brescia 25134",
    "addr:postcode":"25134;25134",
    "iso:country":"IT",
    "sg:address":"25134 Brescia",
    "sg:city":"Brescia",
    "sg:orig_category":"Articoli Da Regalo. Shopping. Regalistica Aziendale",
    "sg:phone":"+39 030 230 0821",
    "sg:postcode":"25134",
    "sg:province":"Brescia",
    "sg:website":"http://www.denea.it",
    "wof:name":"Denea",
    "wof:placetype":"venue"
},
  "geometry": {"coordinates":[10.260243,45.514969],"type":"Point"}
}