{
  "type": "Feature",
  "properties": {
    "addr:full":"24060 Costa Di Mezzate Costa di Mezzate Bergamo 24060",
    "addr:housenumber":"24060;di",
    "addr:postcode":"24060",
    "addr:street":"Costa;Mezzate Bergamo",
    "iso:country":"IT",
    "sg:address":"24060 Costa Di Mezzate",
    "sg:city":"Costa di Mezzate",
    "sg:orig_category":"Fotolito",
    "sg:phone":"+39 035 681322",
    "sg:postcode":"24060",
    "sg:province":"Bergamo",
    "wof:name":"C.p.z. Litografia Di Carrara Carlo E Marzio Sas",
    "wof:placetype":"venue"
},
  "geometry": {"coordinates":[9.7971868515,45.6781311035],"type":"Point"}
}