{
  "type": "Feature",
  "properties": {
    "iso:country":"IT",
    "sg:address":"Via Fratelli Bandiera 53 53034 Colle Di Val D'elsa",
    "sg:classifiers":[
        {
            "category":"Manufacturing",
            "subcategory":"Glass & Minerals",
            "type":"Manufacturing & Wholesale Goods"
        }
    ],
    "sg:phone":"+39 0577 929188",
    "sg:postcode":"53034",
    "sg:province":"Siena",
    "sg:tags":[
        "crystal"
    ],
    "sg:website":"www.vilca.it",
    "wof:name":"Vilca Sas",
    "wof:placetype":"venue"
},
  "geometry": {"coordinates":[11.133996,43.401859],"type":"Point"}
}