{
  "type": "Feature",
  "properties": {
    "addr:full":"20017 Rho Rho Milano 20017",
    "addr:postcode":"20017;20017",
    "iso:country":"IT",
    "sg:address":"20017 Rho",
    "sg:city":"Rho",
    "sg:orig_category":"Servizi Di Magazzinaggio E Movimentazione",
    "sg:phone":"+39 02 9390 1315",
    "sg:postcode":"20017",
    "sg:province":"Milano",
    "wof:name":"So.ge.dil. (s.r.l.)",
    "wof:placetype":"venue"
},
  "geometry": {"coordinates":[9.076866,45.526367],"type":"Point"}
}