{
  "type": "Feature",
  "properties": {
    "iso:country":"IT",
    "sg:address":"2, Via Della Tecnica 35020 Codevigo",
    "sg:city":"Codevigo",
    "sg:classifiers":[
        {
            "category":"Professional",
            "subcategory":"Engineering",
            "type":"Services"
        }
    ],
    "sg:phone":"+39 049 975 0068",
    "sg:postcode":"35020",
    "sg:province":"Padova",
    "sg:tags":[
        "machine",
        "-",
        "mechanical"
    ],
    "wof:name":"L.a.f.a.",
    "wof:placetype":"venue"
},
  "geometry": {"coordinates":[12.089219,45.270573],"type":"Point"}
}