{
  "type": "Feature",
  "properties": {
    "iso:country":"IT",
    "sg:address":"24020 Azzone",
    "sg:city":"Azzone",
    "sg:orig_category":"Servizi E Lavori Per Arredamento E Industria Del Legno",
    "sg:phone":"+39 0346 53489",
    "sg:postcode":"24020",
    "sg:province":"Bergamo",
    "wof:name":"Segheria Bettoni Srl",
    "wof:placetype":"venue"
},
  "geometry": {"coordinates":[10.111897,45.979233],"type":"Point"}
}