{
  "type": "Feature",
  "properties": {
    "addr:full":"19/bis, Corso Regina Margherita 10124 Torino Torino Torino 10124",
    "addr:housenumber":"19 / bis",
    "addr:postcode":"10124;10124",
    "addr:street":"Corso Regina Margherita",
    "iso:country":"IT",
    "sg:address":"19/bis, Corso Regina Margherita 10124 Torino",
    "sg:city":"Torino",
    "sg:classifiers":[
        {
            "category":"Sports & Exercise",
            "subcategory":"Playing Field",
            "type":"Entertainment"
        }
    ],
    "sg:phone":"+39 011 817 7860",
    "sg:postcode":"10124",
    "sg:province":"Torino",
    "sg:tags":[
        "game"
    ],
    "wof:name":"Paganini Sas",
    "wof:placetype":"venue"
},
  "geometry": {"coordinates":[7.686619,45.07056],"type":"Point"}
}