{
  "type": "Feature",
  "properties": {
    "addr:full":"41013 Castelfranco Emilia Castelfranco Emilia Modena 41013",
    "addr:postcode":"41013;41013",
    "iso:country":"IT",
    "sg:address":"41013 Castelfranco Emilia",
    "sg:city":"Castelfranco Emilia",
    "sg:orig_category":"Macchine, Impianti Ed Attrezzature Per Agricoltura E Zootecnia",
    "sg:phone":"+39 059 920997",
    "sg:postcode":"41013",
    "sg:province":"Modena",
    "wof:name":"Veronesi Impianti S.r.l.",
    "wof:placetype":"venue"
},
  "geometry": {"coordinates":[11.066912,44.59317],"type":"Point"}
}