{
  "type": "Feature",
  "properties": {
    "addr:full":"20148 Milano Milano Milano 20148",
    "addr:postcode":"20148;20148",
    "iso:country":"IT",
    "sg:address":"20148 Milano",
    "sg:city":"Milano",
    "sg:orig_category":"Banche E Servizi Finanziari",
    "sg:phone":"+39 02 404 4169",
    "sg:postcode":"20148",
    "sg:province":"Milano",
    "wof:name":"Zanframundo Francesco",
    "wof:placetype":"venue"
},
  "geometry": {"coordinates":[9.128001,45.470005],"type":"Point"}
}