{
  "type": "Feature",
  "properties": {
    "iso:country":"IT",
    "sg:address":"20154 Milano",
    "sg:city":"Milano",
    "sg:orig_category":"Odontotecnici - Laboratori",
    "sg:phone":"+39 02 345 0763",
    "sg:postcode":"20154",
    "sg:province":"Milano",
    "wof:name":"D3 Snc",
    "wof:placetype":"venue"
},
  "geometry": {"coordinates":[9.169607,45.485443],"type":"Point"}
}