{
  "type": "Feature",
  "properties": {
    "addr:full":"6, Via Trieste 13039 Trino Trino Vercelli 13039",
    "addr:postcode":"13039;13039",
    "addr:street":"Via Trieste",
    "iso:country":"IT",
    "sg:address":"6, Via Trieste 13039 Trino",
    "sg:city":"Trino",
    "sg:classifiers":[
        {
            "category":"Farming",
            "subcategory":"Livestock Farm",
            "type":"Manufacturing & Wholesale Goods"
        }
    ],
    "sg:phone":"+39 0161 801234",
    "sg:postcode":"13039",
    "sg:province":"Vercelli",
    "sg:tags":[
        "agriculture"
    ],
    "wof:name":"Riseria Giuseppe Martinotti S.r.l.",
    "wof:placetype":"venue"
},
  "geometry": {"coordinates":[8.29713,45.1903],"type":"Point"}
}