{
  "type": "Feature",
  "properties": {
    "iso:country":"IT",
    "sg:address":"00198 Roma",
    "sg:city":"Roma",
    "sg:orig_category":"Non-classified Establishments",
    "sg:phone":"+39 06 884 8990",
    "sg:postcode":"00198",
    "sg:province":"Roma",
    "wof:name":"Vivarte Di S. Del Balzo (s.a.s.)",
    "wof:placetype":"venue"
},
  "geometry": {"coordinates":[12.495358,41.916584],"type":"Point"}
}