{
  "type": "Feature",
  "properties": {
    "addr:full":"70126 Bari Bari Bari 70126",
    "addr:postcode":"70126;70126",
    "iso:country":"IT",
    "sg:address":"70126 Bari",
    "sg:city":"Bari",
    "sg:orig_category":"Agricoltura, Orticoltura E Floricoltura. Articoli Da Regalo. Shopping",
    "sg:phone":"+39 080 554 0231",
    "sg:postcode":"70126",
    "sg:province":"Bari",
    "wof:name":"Creazioni Floreali Di Veronico",
    "wof:placetype":"venue"
},
  "geometry": {"coordinates":[16.865814,41.089779],"type":"Point"}
}