{
  "type": "Feature",
  "properties": {
    "iso:country":"IT",
    "sg:address":"20142 Milano",
    "sg:city":"Milano",
    "sg:classifiers":[
        {
            "category":"Health Services",
            "subcategory":"Health Practitioner",
            "type":"Services"
        }
    ],
    "sg:phone":"+39 02 846 4109",
    "sg:postcode":"20142",
    "sg:province":"Milano",
    "sg:tags":[
        "medici"
    ],
    "wof:name":"Como Maria Luisa",
    "wof:placetype":"venue"
},
  "geometry": {"coordinates":[9.171787,45.440609],"type":"Point"}
}