{
  "type": "Feature",
  "properties": {
    "addr:full":"900, Via Cerreto 47020 Longiano Longiano Forl\u00ec-Cesena 47020",
    "addr:housenumber":"900",
    "addr:postcode":"47020;47020",
    "addr:street":"Via Cerreto",
    "iso:country":"IT",
    "sg:address":"900, Via Cerreto 47020 Longiano",
    "sg:city":"Longiano",
    "sg:classifiers":[
        {
            "category":"Manufacturing",
            "subcategory":"Lumber",
            "type":"Manufacturing & Wholesale Goods"
        }
    ],
    "sg:phone":"+39 0547 665347",
    "sg:postcode":"47020",
    "sg:province":"Forl\u00ec-Cesena",
    "sg:tags":[
        "wood"
    ],
    "wof:name":"Bielle Group Snc Di Baiardi Luciano E C.",
    "wof:placetype":"venue"
},
  "geometry": {"coordinates":[12.327749,44.08543],"type":"Point"}
}