{
  "type": "Feature",
  "properties": {
    "addr:full":"50032 Borgo San Lorenzo Borgo San Lorenzo Firenze 50032",
    "addr:postcode":"50032;50032",
    "addr:street":"Borgo San Lorenzo Borgo San Lorenzo",
    "iso:country":"IT",
    "sg:address":"50032 Borgo San Lorenzo",
    "sg:city":"Borgo San Lorenzo",
    "sg:orig_category":"Tempo Libero - Articoli E Forniture. Automobili E Mezzi Di Trasporto. Riparazione Dei Mezzi Di Trasporto",
    "sg:phone":"+39 055 845 8713",
    "sg:postcode":"50032",
    "sg:province":"Firenze",
    "wof:name":"Arinci Antonio",
    "wof:placetype":"venue"
},
  "geometry": {"coordinates":[11.388445,43.951675],"type":"Point"}
}