{
  "type": "Feature",
  "properties": {
    "addr:full":"10, Via Canova 36055 Nove Nove Vicenza 36055",
    "addr:postcode":"36055;36055",
    "addr:street":"Via Canova",
    "iso:country":"IT",
    "sg:address":"10, Via Canova 36055 Nove",
    "sg:city":"Nove",
    "sg:classifiers":[
        {
            "category":"Sports & Exercise",
            "subcategory":"Playing Field",
            "type":"Entertainment"
        }
    ],
    "sg:phone":"+39 0424 829092",
    "sg:postcode":"36055",
    "sg:province":"Vicenza",
    "sg:tags":[
        "game"
    ],
    "wof:name":"Ceramiche Ars Di Marchiorello - Tosin & C. (s.n.c.)",
    "wof:placetype":"venue"
},
  "geometry": {"coordinates":[11.674627,45.712791],"type":"Point"}
}