{
  "type": "Feature",
  "properties": {
    "iso:country":"IT",
    "sg:address":"38049 Vigolo Vattaro",
    "sg:city":"Vattaro",
    "sg:orig_category":"Legno E Semilavorati",
    "sg:phone":"+39 0461 845082",
    "sg:postcode":"38049",
    "sg:province":"Trento",
    "wof:name":"Ideal Legno Srl Di Holler Carlo & Susat Gilberto",
    "wof:placetype":"venue"
},
  "geometry": {"coordinates":[11.19987,46.006573],"type":"Point"}
}