{
  "type": "Feature",
  "properties": {
    "addr:full":"25020 Flero Flero Brescia 25020",
    "addr:postcode":"25020;25020",
    "iso:country":"IT",
    "sg:address":"25020 Flero",
    "sg:city":"Flero",
    "sg:orig_category":"Macchine Utensili E Impianti",
    "sg:phone":"+39 030 268 0233",
    "sg:postcode":"25020",
    "sg:province":"Brescia",
    "wof:name":"Savoldi Bruno",
    "wof:placetype":"venue"
},
  "geometry": {"coordinates":[10.14863,45.481419],"type":"Point"}
}