{
  "type": "Feature",
  "properties": {
    "addr:full":"51036 Larciano Larciano Pistoia 51036",
    "addr:postcode":"51036;51036",
    "iso:country":"IT",
    "sg:address":"51036 Larciano",
    "sg:city":"Larciano",
    "sg:orig_category":"Prodotti E Manufatti In Materie Plastiche. Prodotti Cosmetici E Da Toeletta. Forniture Per Attivita' Industriali",
    "sg:phone":"+39 0573 84177",
    "sg:postcode":"51036",
    "sg:province":"Pistoia",
    "wof:name":"Bonfanti (s.r.l.)",
    "wof:placetype":"venue"
},
  "geometry": {"coordinates":[10.9151849747,43.8689804077],"type":"Point"}
}