{
  "type": "Feature",
  "properties": {
    "addr:full":"1, Via Voghera 27050 Corana Corana Pavia 27050",
    "addr:postcode":"27050;27050",
    "addr:street":"Via Voghera",
    "iso:country":"IT",
    "sg:address":"1, Via Voghera 27050 Corana",
    "sg:city":"Corana",
    "sg:classifiers":[
        {
            "category":"Wholesale",
            "subcategory":"Drugs",
            "type":"Manufacturing & Wholesale Goods"
        }
    ],
    "sg:phone":"+39 390 383 3311",
    "sg:postcode":"27050",
    "sg:province":"Pavia",
    "sg:tags":[
        "chemical",
        "pharmaceutical"
    ],
    "wof:name":"Diaspa Spa",
    "wof:placetype":"venue"
},
  "geometry": {"coordinates":[8.907641,45.096535],"type":"Point"}
}