{
  "type": "Feature",
  "properties": {
    "addr:full":"Piazza Regina Margherita,; Maschito; 85020 Maschito Potenza 85020",
    "addr:postcode":"85020;85020",
    "addr:street":"Piazza Regina Margherita",
    "iso:country":"IT",
    "sg:address":"Piazza Regina Margherita,; Maschito; 85020",
    "sg:city":"Maschito",
    "sg:classifiers":[
        {
            "category":"Banks & Credit Unions",
            "subcategory":"Bank",
            "type":"Services"
        }
    ],
    "sg:phone":"+39 0972 33117",
    "sg:postcode":"85020",
    "sg:province":"Potenza",
    "wof:name":"Banca Popolare Coop. Di Pescopagano",
    "wof:placetype":"venue"
},
  "geometry": {"coordinates":[15.855126,40.859642],"type":"Point"}
}