{
  "type": "Feature",
  "properties": {
    "addr:full":"20091 Bresso Bresso Milano 20091",
    "addr:postcode":"20091;20091",
    "iso:country":"IT",
    "sg:address":"20091 Bresso",
    "sg:city":"Bresso",
    "sg:orig_category":"Grigliati E Griglie",
    "sg:phone":"+39 02 610 1321",
    "sg:postcode":"20091",
    "sg:province":"Milano",
    "wof:name":"Zincatura Viotto Srl",
    "wof:placetype":"venue"
},
  "geometry": {"coordinates":[9.193199,45.532589],"type":"Point"}
}