{
  "type": "Feature",
  "properties": {
    "addr:full":"Via Iv Novembre 1; Chiuro",
    "addr:housenumber":"1",
    "addr:street":"Via Iv Novembre",
    "iso:country":"IT",
    "sg:address":"Via Iv Novembre 1; Chiuro",
    "sg:classifiers":[
        {
            "category":"Banks & Credit Unions",
            "subcategory":"Bank",
            "type":"Services"
        }
    ],
    "sg:phone":"+39 0342 482243",
    "wof:name":"Credito Valtellinese Scarl",
    "wof:placetype":"venue"
},
  "geometry": {"coordinates":[9.982037,46.165943],"type":"Point"}
}