{
  "type": "Feature",
  "properties": {
    "addr:full":"20124 Milano Milano Milano 20124",
    "addr:postcode":"20124;20124",
    "iso:country":"IT",
    "sg:address":"20124 Milano",
    "sg:city":"Milano",
    "sg:orig_category":"Pubblicita', Marketing E Comunicazione",
    "sg:phone":"+39 02 202 0211",
    "sg:postcode":"20124",
    "sg:province":"Milano",
    "wof:name":"Text 100 Italy Srl",
    "wof:placetype":"venue"
},
  "geometry": {"coordinates":[9.2102222443,45.4824714661],"type":"Point"}
}