{
  "type": "Feature",
  "properties": {
    "iso:country":"IT",
    "sg:address":"24/c, Via Grandi Achille 22063 Cantu'",
    "sg:classifiers":[
        {
            "category":"Home & Garden",
            "subcategory":"Home Furnishings",
            "type":"Retail Goods"
        }
    ],
    "sg:phone":"+39 39031704541",
    "sg:postcode":"22063",
    "sg:province":"Como",
    "sg:tags":[
        "household"
    ],
    "wof:name":"Mara (s.r.l.)",
    "wof:placetype":"venue"
},
  "geometry": {"coordinates":[9.120039,45.742401],"type":"Point"}
}