{
  "type": "Feature",
  "properties": {
    "iso:country":"IT",
    "sg:address":"Via Della Tecnica 19 23875 Osnago",
    "sg:city":"Osnago",
    "sg:classifiers":[
        {
            "category":"Banks & Credit Unions",
            "subcategory":"Investment Brokerage",
            "type":"Services"
        }
    ],
    "sg:phone":"+39 039 587506",
    "sg:postcode":"23875",
    "sg:province":"Lecco",
    "sg:tags":[
        "lighting",
        "system"
    ],
    "sg:website":"www.caril.com",
    "wof:name":"Cariboni Illuminazione Srl",
    "wof:placetype":"venue"
},
  "geometry": {"coordinates":[9.39485,45.671238],"type":"Point"}
}