{
  "type": "Feature",
  "properties": {
    "iso:country":"IT",
    "sg:address":"00040 Pomezia",
    "sg:city":"Pomezia",
    "sg:orig_category":"Servizi Per Lo Sport E Il Tempo Libero. Servizi Al Turismo",
    "sg:phone":"+39 06 9160 3209",
    "sg:postcode":"00040",
    "sg:province":"Roma",
    "wof:name":"Le Erbe Amiche Dott. De Murtas",
    "wof:placetype":"venue"
},
  "geometry": {"coordinates":[12.502814,41.672955],"type":"Point"}
}