{
  "type": "Feature",
  "properties": {
    "addr:full":"31030 Tovena Tovena Treviso 31030",
    "addr:postcode":"31030;31030",
    "addr:street":"Tovena Treviso",
    "iso:country":"IT",
    "sg:address":"31030 Tovena",
    "sg:city":"Tovena",
    "sg:orig_category":"Filati E Materie Prime Tessili",
    "sg:postcode":"31030",
    "sg:province":"Treviso",
    "wof:name":"Gandin Aldo",
    "wof:placetype":"venue"
},
  "geometry": {"coordinates":[12.2462863922,45.6654434204],"type":"Point"}
}