{
  "type": "Feature",
  "properties": {
    "iso:country":"IT",
    "sg:address":"33080 San Quirino",
    "sg:city":"San Quirino",
    "sg:classifiers":[
        {
            "category":"Utilities",
            "subcategory":"Refuse",
            "type":"Services"
        }
    ],
    "sg:phone":"+39 0434 919281",
    "sg:postcode":"33080",
    "sg:province":"Pordenone",
    "sg:tags":[
        "control",
        "industrial",
        "supply",
        "disposal",
        "environmental",
        "protection",
        "safety",
        "works",
        "prevention"
    ],
    "sg:website":"http://www.cabinebiemme.com",
    "wof:name":"Biemme Insonorizzazione Srl",
    "wof:placetype":"venue"
},
  "geometry": {"coordinates":[12.650496,46.031071],"type":"Point"}
}