{
  "type": "Feature",
  "properties": {
    "iso:country":"IT",
    "sg:address":"23, Via Leonardo Da Vinci 20090 Segrate",
    "sg:city":"Segrate",
    "sg:classifiers":[
        {
            "category":"Utilities",
            "subcategory":"Electric",
            "type":"Services"
        }
    ],
    "sg:phone":"+39 39022138538",
    "sg:postcode":"20090",
    "sg:province":"Milano",
    "sg:tags":[
        "component",
        "electronic"
    ],
    "wof:name":"F.t. Automation S.p.a.",
    "wof:placetype":"venue"
},
  "geometry": {"coordinates":[9.280835,45.492172],"type":"Point"}
}