{
  "type": "Feature",
  "properties": {
    "iso:country":"IT",
    "sg:address":"3, Via Emilia Romagna 35020 Saonara",
    "sg:city":"Saonara",
    "sg:classifiers":[
        {
            "category":"Shopping",
            "type":"Retail Goods"
        }
    ],
    "sg:phone":"+39 049 879 0540",
    "sg:postcode":"35020",
    "sg:province":"Padova",
    "sg:tags":[
        "finished",
        "-",
        "metallic"
    ],
    "wof:name":"Md3 Metalmeccanica Srl",
    "wof:placetype":"venue"
},
  "geometry": {"coordinates":[11.9578199387,45.3788528442],"type":"Point"}
}