{
  "type": "Feature",
  "properties": {
    "iso:country":"IT",
    "sg:address":"16042 Carasco",
    "sg:city":"Carasco",
    "sg:orig_category":"Arredo Cucina Ed Elettrodomestici. Climatizzazione E Condizionamento, Apparecchiature E Servizi",
    "sg:phone":"+39 0185 350004",
    "sg:postcode":"16042",
    "sg:province":"Genova",
    "wof:name":"Fa.mo.s. (s.a.s.)",
    "wof:placetype":"venue"
},
  "geometry": {"coordinates":[9.342564,44.348267],"type":"Point"}
}