{
  "type": "Feature",
  "properties": {
    "addr:full":"6, Via Campagnetta 21046 Malnate Malnate Varese 21046",
    "addr:postcode":"21046;21046",
    "addr:street":"Via Campagnetta",
    "iso:country":"IT",
    "sg:address":"6, Via Campagnetta 21046 Malnate",
    "sg:city":"Malnate",
    "sg:classifiers":[
        {
            "category":"Personal",
            "subcategory":"Shoe Repair & Shine",
            "type":"Services"
        }
    ],
    "sg:phone":"+39 0332 425274",
    "sg:postcode":"21046",
    "sg:province":"Varese",
    "sg:tags":[
        "leather"
    ],
    "wof:name":"La Casa Della Valigia Di Ragno Anna E C. Snc",
    "wof:placetype":"venue"
},
  "geometry": {"coordinates":[8.870789,45.787384],"type":"Point"}
}