{
  "type": "Feature",
  "properties": {
    "iso:country":"IT",
    "sg:address":"50, V. Laerte 00133 Roma",
    "sg:city":"Roma",
    "sg:classifiers":[
        {
            "category":"Shopping",
            "type":"Retail Goods"
        }
    ],
    "sg:phone":"+39 39062011218",
    "sg:postcode":"00133",
    "sg:province":"Roma",
    "sg:tags":[
        "finished",
        "-",
        "metallic"
    ],
    "sg:website":"http://www.rosiserrature.com",
    "wof:name":"Rosi Srl",
    "wof:placetype":"venue"
},
  "geometry": {"coordinates":[12.6155700684,41.8696365356],"type":"Point"}
}