{
  "type": "Feature",
  "properties": {
    "iso:country":"IT",
    "sg:address":"41013 Castelfranco Emilia",
    "sg:city":"Castelfranco Emilia",
    "sg:orig_category":"Macchine Ed Impianti Per Edilizia E Lavori Pubblici",
    "sg:phone":"+39 059 923110",
    "sg:postcode":"41013",
    "sg:province":"Modena",
    "wof:name":"Negrini Fratelli Snc",
    "wof:placetype":"venue"
},
  "geometry": {"coordinates":[11.067969,44.590458],"type":"Point"}
}