{
  "type": "Feature",
  "properties": {
    "iso:country":"IT",
    "sg:address":"00127 Roma",
    "sg:city":"Roma",
    "sg:orig_category":"Materiali E Componenti Elettrotecnici",
    "sg:phone":"+39 06 5237 3114",
    "sg:postcode":"00127",
    "sg:province":"Roma",
    "wof:name":"Levinsson Consulting Srl",
    "wof:placetype":"venue"
},
  "geometry": {"coordinates":[12.412043,41.78883],"type":"Point"}
}