{
  "type": "Feature",
  "properties": {
    "iso:country":"IT",
    "sg:address":"116, V. Salaria 00198 Roma",
    "sg:city":"Roma",
    "sg:classifiers":[
        {
            "category":"Shopping",
            "subcategory":"Computers & Home Electronics",
            "type":"Retail Goods"
        }
    ],
    "sg:phone":"+39 39064402066",
    "sg:postcode":"00198",
    "sg:province":"Roma",
    "sg:tags":[
        "electronic",
        "electrical",
        "equipment"
    ],
    "sg:website":"http://www.belluccielectronics.com",
    "wof:name":"Bellucci",
    "wof:placetype":"venue"
},
  "geometry": {"coordinates":[12.497157,41.915176],"type":"Point"}
}