{
  "type": "Feature",
  "properties": {
    "addr:full":"80055 Portici Portici Napoli 80055",
    "addr:postcode":"80055;80055",
    "iso:country":"IT",
    "sg:address":"80055 Portici",
    "sg:city":"Portici",
    "sg:classifiers":[
        {
            "category":"Health Services",
            "subcategory":"Health Practitioner",
            "type":"Services"
        }
    ],
    "sg:phone":"+39 081 472932",
    "sg:postcode":"80055",
    "sg:province":"Napoli",
    "sg:tags":[
        "medici"
    ],
    "wof:name":"M E D I C E N T E R",
    "wof:placetype":"venue"
},
  "geometry": {"coordinates":[14.331356,40.818401],"type":"Point"}
}