{
  "type": "Feature",
  "properties": {
    "addr:full":"24057 Martinengo Martinengo Bergamo 24057",
    "addr:postcode":"24057;24057",
    "iso:country":"IT",
    "sg:address":"24057 Martinengo",
    "sg:city":"Martinengo",
    "sg:orig_category":"Prefabbricati Cemento",
    "sg:phone":"+39 036 398 7310",
    "sg:postcode":"24057",
    "sg:province":"Bergamo",
    "sg:website":"http://www.lamera.it",
    "wof:name":"Prefabbricati Lamera Srl",
    "wof:placetype":"venue"
},
  "geometry": {"coordinates":[9.7786521912,45.5702819824],"type":"Point"}
}