{
  "type": "Feature",
  "properties": {
    "iso:country":"IT",
    "sg:address":"31, Via Dolegnano Di Sotto 33048 San Giovanni Al Natisone",
    "sg:city":"Dolegnano",
    "sg:classifiers":[
        {
            "category":"Manufacturing",
            "subcategory":"Lumber",
            "type":"Manufacturing & Wholesale Goods"
        }
    ],
    "sg:phone":"+39 0432 756187",
    "sg:postcode":"33048",
    "sg:province":"Udine",
    "sg:tags":[
        "wood"
    ],
    "wof:name":"Torneria Friulana Di Mario Piani & F.lli S.n.c.",
    "wof:placetype":"venue"
},
  "geometry": {"coordinates":[13.425055,45.982021],"type":"Point"}
}