{
  "type": "Feature",
  "properties": {
    "addr:full":"20090 Segrate Segrate Milano 20090",
    "addr:postcode":"20090;20090",
    "iso:country":"IT",
    "sg:address":"20090 Segrate",
    "sg:city":"Segrate",
    "sg:orig_category":"Alimentare E Conserviera Industria - Macchine",
    "sg:phone":"+39 02 213 7241",
    "sg:postcode":"20090",
    "sg:province":"Milano",
    "wof:name":"Eurosicma Spa",
    "wof:placetype":"venue"
},
  "geometry": {"coordinates":[9.293935,45.486591],"type":"Point"}
}