{
  "type": "Feature",
  "properties": {
    "iso:country":"IT",
    "sg:address":"39030 Valdaora",
    "sg:city":"Valdaora",
    "sg:orig_category":"Legno E Semilavorati",
    "sg:phone":"+39 0474 496533",
    "sg:postcode":"39030",
    "sg:province":"Bolzano/Bozen",
    "wof:name":"Alpenholz Mair (s.r.l.)",
    "wof:placetype":"venue"
},
  "geometry": {"coordinates":[12.031817,46.765984],"type":"Point"}
}