{
  "type": "Feature",
  "properties": {
    "addr:full":"48018 Faenza Faenza Ravenna 48018",
    "addr:postcode":"48018;48018",
    "iso:country":"IT",
    "sg:address":"48018 Faenza",
    "sg:city":"Faenza",
    "sg:orig_category":"Prodotti Chimici Di Base",
    "sg:phone":"+39 0546 30537",
    "sg:postcode":"48018",
    "sg:province":"Ravenna",
    "wof:name":"Emiliani Sante",
    "wof:placetype":"venue"
},
  "geometry": {"coordinates":[12.2136173248,44.2664527893],"type":"Point"}
}