{
  "type": "Feature",
  "properties": {
    "iso:country":"IT",
    "sg:address":"00179 Roma",
    "sg:city":"Roma",
    "sg:orig_category":"Ristorazione E Locali Pubblici Affini. Ristoranti Ed Esercizi Affini. Servizi Ausiliari Di Ristorazione E Di Intrattenimento",
    "sg:phone":"+39 06 7720 8434",
    "sg:postcode":"00179",
    "sg:province":"Roma",
    "wof:name":"Ristorante Ar Montarozzo",
    "wof:placetype":"venue"
},
  "geometry": {"coordinates":[12.521309,41.851513],"type":"Point"}
}