{
  "type": "Feature",
  "properties": {
    "addr:full":"33010 Venzone Venzone Udine 33010",
    "addr:postcode":"33010;33010",
    "iso:country":"IT",
    "sg:address":"33010 Venzone",
    "sg:city":"Venzone",
    "sg:orig_category":"Acciaierie E Fonderie",
    "sg:phone":"+39 0432 978124",
    "sg:postcode":"33010",
    "sg:province":"Udine",
    "wof:name":"Impresa Elettrica Dante Nigris Di Luca E Luigi Nigris (s.n.c.)",
    "wof:placetype":"venue"
},
  "geometry": {"coordinates":[13.140486,46.332195],"type":"Point"}
}