{
  "type": "Feature",
  "properties": {
    "addr:full":"90143 Palermo Palermo Palermo 90143",
    "addr:postcode":"90143;90143",
    "iso:country":"IT",
    "sg:address":"90143 Palermo",
    "sg:city":"Palermo",
    "sg:orig_category":"Impiantistica E Prodotti Tecnologici Per Edilizia. Forniture Industriali Per Prevenzione, Controllo E Sicurezza",
    "sg:phone":"+39 091 868 5160",
    "sg:postcode":"90143",
    "sg:province":"Palermo",
    "wof:name":"Amato Impianti Srl",
    "wof:placetype":"venue"
},
  "geometry": {"coordinates":[13.349258,38.13863],"type":"Point"}
}