{
  "type": "Feature",
  "properties": {
    "addr:full":"50123 Firenze Firenze Firenze 50123",
    "addr:postcode":"50123;50123",
    "iso:country":"IT",
    "sg:address":"50123 Firenze",
    "sg:city":"Firenze",
    "sg:orig_category":"Olografia",
    "sg:phone":"+39 055 283727",
    "sg:postcode":"50123",
    "sg:province":"Firenze",
    "wof:name":"Aletheia",
    "wof:placetype":"venue"
},
  "geometry": {"coordinates":[11.253303,43.77663],"type":"Point"}
}