{
  "type": "Feature",
  "properties": {
    "addr:full":"00141 Roma Roma Roma 00141",
    "addr:postcode":"00141;00141",
    "iso:country":"IT",
    "sg:address":"00141 Roma",
    "sg:city":"Roma",
    "sg:orig_category":"Forniture Per Agricoltura E Zootecnia. Prodotti Chimici Secondari. Macchine E Forniture Per Ecologia E Smaltimento Rifiuti",
    "sg:phone":"+39 06 8864 2700",
    "sg:postcode":"00141",
    "sg:province":"Roma",
    "wof:name":"Chimisistem",
    "wof:placetype":"venue"
},
  "geometry": {"coordinates":[12.5195999146,41.9424095154],"type":"Point"}
}