{
  "type": "Feature",
  "properties": {
    "iso:country":"IT",
    "sg:address":"22040 Lurago D'erba",
    "sg:orig_category":"Servizi E Lavori Industria Chimica. Riparazione Dei Mezzi Di Trasporto",
    "sg:phone":"+39 031 696047",
    "sg:postcode":"22040",
    "sg:province":"Como",
    "wof:name":"Ferraioli Angelo",
    "wof:placetype":"venue"
},
  "geometry": {"coordinates":[9.220297,45.762779],"type":"Point"}
}