{
  "type": "Feature",
  "properties": {
    "iso:country":"IT",
    "sg:address":"22029 Uggiate Trevano",
    "sg:orig_category":"Scuole E Servizi Scolastici. Servizi Per Lo Sport E Il Tempo Libero",
    "sg:phone":"+39 031 809420",
    "sg:postcode":"22029",
    "sg:province":"Como",
    "wof:name":"Thema Sport Di Zambello Eleonora & C. Snc",
    "wof:placetype":"venue"
},
  "geometry": {"coordinates":[8.941323,45.788937],"type":"Point"}
}