{
  "type": "Feature",
  "properties": {
    "addr:full":"16019 Ronco Scrivia Ronco Scrivia Genova 16019",
    "addr:postcode":"16019;16019",
    "iso:country":"IT",
    "sg:address":"16019 Ronco Scrivia",
    "sg:city":"Ronco Scrivia",
    "sg:orig_category":"Lavorazioni Meccaniche E Servizi",
    "sg:phone":"+39 010 964 2411",
    "sg:postcode":"16019",
    "sg:province":"Genova",
    "wof:name":"Rasore Stefano Snc",
    "wof:placetype":"venue"
},
  "geometry": {"coordinates":[8.838406,44.433384],"type":"Point"}
}