{
  "type": "Feature",
  "properties": {
    "addr:full":"56, Via Mestrina 30172 Venezia Venezia Venezia 30172",
    "addr:postcode":"30172;30172",
    "addr:street":"Via Mestrina",
    "iso:country":"IT",
    "sg:address":"56, Via Mestrina 30172 Venezia",
    "sg:city":"Venezia",
    "sg:classifiers":[
        {
            "category":"Shopping",
            "subcategory":"Crafts & Fabrics",
            "type":"Retail Goods"
        }
    ],
    "sg:phone":"+39 39041950095",
    "sg:postcode":"30172",
    "sg:province":"Venezia",
    "wof:name":"Luciano Marcato (s.r.l.)",
    "wof:placetype":"venue"
},
  "geometry": {"coordinates":[12.3266267776,45.4408950806],"type":"Point"}
}