{
  "type": "Feature",
  "properties": {
    "iso:country":"IT",
    "sg:address":"94017 Regalbuto",
    "sg:city":"Regalbuto",
    "sg:orig_category":"Prodotti Alimentari",
    "sg:phone":"+39 0935 71166",
    "sg:postcode":"94017",
    "sg:province":"Enna",
    "wof:name":"Paratore Giuseppe",
    "wof:placetype":"venue"
},
  "geometry": {"coordinates":[14.5902824402,37.5518074036],"type":"Point"}
}