{
  "type": "Feature",
  "properties": {
    "iso:country":"IT",
    "sg:address":"00133 Roma",
    "sg:city":"Roma",
    "sg:orig_category":"Impianti, Attrezzature E Forniture Sanitarie Ed Ospedaliere",
    "sg:phone":"+39 06 205 5943",
    "sg:postcode":"00133",
    "sg:province":"Roma",
    "wof:name":"Laboratori Guantera Sas",
    "wof:placetype":"venue"
},
  "geometry": {"coordinates":[12.653594,41.866314],"type":"Point"}
}