{
  "type": "Feature",
  "properties": {
    "addr:full":"Strada Statale 195 09018 Sarroch Sarroch Cagliari 09018",
    "addr:housenumber":"195",
    "addr:postcode":"09018;09018",
    "addr:street":"Strada Statale",
    "iso:country":"IT",
    "sg:address":"Strada Statale 195 09018 Sarroch",
    "sg:city":"Sarroch",
    "sg:classifiers":[
        {
            "category":"Shopping",
            "type":"Retail Goods"
        }
    ],
    "sg:phone":"+39 39070900391",
    "sg:postcode":"09018",
    "sg:province":"Cagliari",
    "sg:tags":[
        "finished",
        "-",
        "metallic"
    ],
    "wof:name":"G.d.s. (s.r.l.)",
    "wof:placetype":"venue"
},
  "geometry": {"coordinates":[9.0157604218,39.1501998901],"type":"Point"}
}