{
  "type": "Feature",
  "properties": {
    "addr:full":"21055 Gorla Minore Gorla Minore Varese 21055",
    "addr:postcode":"21055;21055",
    "iso:country":"IT",
    "sg:address":"21055 Gorla Minore",
    "sg:city":"Gorla Minore",
    "sg:classifiers":[
        {
            "category":"Manufacturing",
            "subcategory":"Chemicals & Compounds",
            "type":"Manufacturing & Wholesale Goods"
        }
    ],
    "sg:phone":"+39 0331 604772",
    "sg:postcode":"21055",
    "sg:province":"Varese",
    "sg:tags":[
        "product",
        "chemicals",
        "basic"
    ],
    "wof:name":"Raro Chem Srl",
    "wof:placetype":"venue"
},
  "geometry": {"coordinates":[8.909954,45.646717],"type":"Point"}
}