{
  "type": "Feature",
  "properties": {
    "iso:country":"IT",
    "sg:address":"Zona Industriale Sul Cosa 1 33097 Spilimbergo",
    "sg:city":"Spilimbergo",
    "sg:classifiers":[
        {
            "category":"Home & Garden",
            "subcategory":"Home Furnishings",
            "type":"Retail Goods"
        }
    ],
    "sg:phone":"+39 0427 519311",
    "sg:postcode":"33097",
    "sg:province":"Pordenone",
    "sg:tags":[
        "metal",
        "furniture"
    ],
    "sg:website":"www.sintesi2.it",
    "wof:name":"Galvanotecnica Spa",
    "wof:placetype":"venue"
},
  "geometry": {"coordinates":[12.655043602,45.9626502991],"type":"Point"}
}