{
  "type": "Feature",
  "properties": {
    "iso:country":"IT",
    "sg:address":"63, Via Seano 51039 Quarrata",
    "sg:city":"Quarrata",
    "sg:classifiers":[
        {
            "category":"Shopping",
            "subcategory":"Clothing, Apparel, & Fashions",
            "type":"Retail Goods"
        }
    ],
    "sg:phone":"+39 0573 744633",
    "sg:postcode":"51039",
    "sg:province":"Pistoia",
    "sg:tags":[
        "clothes"
    ],
    "wof:name":"Antica Maglieria Toscana Srl",
    "wof:placetype":"venue"
},
  "geometry": {"coordinates":[11.013447,43.837002],"type":"Point"}
}