{
  "type": "Feature",
  "properties": {
    "iso:country":"IT",
    "sg:address":"20051 Limbiate",
    "sg:city":"Limbiate",
    "sg:orig_category":"Climatizzazione E Condizionamento, Apparecchiature E Servizi. Elettrotecnica Professionale E Di Consumo",
    "sg:phone":"+39 02 9905 7519",
    "sg:postcode":"20051",
    "sg:province":"Milano",
    "wof:name":"Mistral Aspiratori E Ventilatori Srl",
    "wof:placetype":"venue"
},
  "geometry": {"coordinates":[9.150106,45.451046],"type":"Point"}
}