{
  "type": "Feature",
  "properties": {
    "addr:full":"52, Via Toscana 56035 Lari Lari Pisa 56035",
    "addr:postcode":"56035;56035",
    "addr:street":"Via Toscana",
    "iso:country":"IT",
    "sg:address":"52, Via Toscana 56035 Lari",
    "sg:city":"Lari",
    "sg:classifiers":[
        {
            "category":"Professional",
            "subcategory":"Engineering",
            "type":"Services"
        }
    ],
    "sg:phone":"+39 0587 616385",
    "sg:postcode":"56035",
    "sg:province":"Pisa",
    "sg:tags":[
        "machine",
        "-",
        "mechanical"
    ],
    "wof:name":"E.t. (s.r.l.)",
    "wof:placetype":"venue"
},
  "geometry": {"coordinates":[10.609445,43.61124],"type":"Point"}
}