{
  "type": "Feature",
  "properties": {
    "iso:country":"IT",
    "sg:address":"20122 Milano",
    "sg:city":"Milano",
    "sg:orig_category":"Professionisti - Studi E Servizi Ed Associazioni Di Interesse Aziendale. Servizi Sociali. Associazioni Ed Organismi Di Interesse Pubblico",
    "sg:phone":"+39 02 551 2010",
    "sg:postcode":"20122",
    "sg:province":"Milano",
    "wof:name":"Associazione Nazionale Mutilati E Invalidi Di Guerra",
    "wof:placetype":"venue"
},
  "geometry": {"coordinates":[9.1997146606,45.4598350525],"type":"Point"}
}