{
  "type": "Feature",
  "properties": {
    "iso:country":"IT",
    "sg:address":"20026 Novate Milanese",
    "sg:city":"Novate Milanese",
    "sg:orig_category":"Materiali E Componenti Elettrotecnici",
    "sg:phone":"+39 02 3910 1120",
    "sg:postcode":"20026",
    "sg:province":"Milano",
    "wof:name":"Industria Lombarda Materiale Elettrico Spa",
    "wof:placetype":"venue"
},
  "geometry": {"coordinates":[9.149301,45.524506],"type":"Point"}
}