{
  "type": "Feature",
  "properties": {
    "iso:country":"IT",
    "sg:address":"31030 Carbonera",
    "sg:city":"Carbonera",
    "sg:orig_category":"Forniture Per Edilizia E Lavori Pubblici",
    "sg:phone":"+39 0422 396366",
    "sg:postcode":"31030",
    "sg:province":"Treviso",
    "sg:website":"http://www.ceramgres.com",
    "wof:name":"Ceramgres Srl",
    "wof:placetype":"venue"
},
  "geometry": {"coordinates":[12.3193531036,45.6889381409],"type":"Point"}
}