{
  "type": "Feature",
  "properties": {
    "addr:full":"33, Via Pavese 47853 Coriano Coriano Rimini 47853",
    "addr:postcode":"47853;47853",
    "addr:street":"Via Pavese",
    "iso:country":"IT",
    "sg:address":"33, Via Pavese 47853 Coriano",
    "sg:city":"Coriano",
    "sg:classifiers":[
        {
            "category":"Manufacturing",
            "subcategory":"Metals",
            "type":"Manufacturing & Wholesale Goods"
        }
    ],
    "sg:phone":"+39 0541 759408",
    "sg:postcode":"47853",
    "sg:province":"Rimini",
    "sg:tags":[
        "metallurgy",
        "metalworking"
    ],
    "wof:name":"S.i.a. (s.r.l.)",
    "wof:placetype":"venue"
},
  "geometry": {"coordinates":[12.5272674561,43.9912338257],"type":"Point"}
}