{
  "type": "Feature",
  "properties": {
    "addr:full":"70121 Bari Bari Bari 70121",
    "addr:postcode":"70121;70121",
    "iso:country":"IT",
    "sg:address":"70121 Bari",
    "sg:city":"Bari",
    "sg:orig_category":"Articoli Da Regalo. Hobbistica. Shopping",
    "sg:phone":"+39 080 524 7407",
    "sg:postcode":"70121",
    "sg:province":"Bari",
    "wof:name":"De Martino Vincenza",
    "wof:placetype":"venue"
},
  "geometry": {"coordinates":[16.872904,41.12006],"type":"Point"}
}