{
  "type": "Feature",
  "properties": {
    "addr:full":"31016 Cordignano Cordignano Treviso 31016",
    "addr:postcode":"31016;31016",
    "iso:country":"IT",
    "sg:address":"31016 Cordignano",
    "sg:city":"Cordignano",
    "sg:orig_category":"Pompe. Ricambi E Componenti Dei Mezzi Di Trasporto",
    "sg:phone":"+39 0438 995362",
    "sg:postcode":"31016",
    "sg:province":"Treviso",
    "wof:name":"Bit Renato & C. Snc",
    "wof:placetype":"venue"
},
  "geometry": {"coordinates":[12.2549371719,45.6725540161],"type":"Point"}
}