{
  "type": "Feature",
  "properties": {
    "addr:full":"104, Via Milano 21011 Casorate Sempione Casorate Sempione Varese 21011",
    "addr:housenumber":"104",
    "addr:postcode":"21011;21011",
    "addr:street":"Via Milano",
    "iso:country":"IT",
    "sg:address":"104, Via Milano 21011 Casorate Sempione",
    "sg:city":"Casorate Sempione",
    "sg:orig_category":"Miscellaneous Products",
    "sg:phone":"+39 0331 295347",
    "sg:postcode":"21011",
    "sg:province":"Varese",
    "wof:name":"A & B Sas",
    "wof:placetype":"venue"
},
  "geometry": {"coordinates":[8.7438383102,45.6732826233],"type":"Point"}
}