{
  "type": "Feature",
  "properties": {
    "addr:full":"Via Vittorio Veneto 34 22070 Rovello Porro Rovello Porro Como 22070",
    "addr:housenumber":"34",
    "addr:postcode":"22070;22070",
    "addr:street":"Via Vittorio Veneto",
    "iso:country":"IT",
    "sg:address":"Via Vittorio Veneto 34 22070 Rovello Porro",
    "sg:city":"Rovello Porro",
    "sg:classifiers":[
        {
            "category":"Health Services",
            "subcategory":"Dentist",
            "type":"Services"
        }
    ],
    "sg:phone":"+39 02 9675 0972",
    "sg:postcode":"22070",
    "sg:province":"Como",
    "sg:tags":[
        "dental",
        "material",
        "protheses"
    ],
    "wof:name":"Quattroti Srl",
    "wof:placetype":"venue"
},
  "geometry": {"coordinates":[9.033655,45.652008],"type":"Point"}
}