{
  "type": "Feature",
  "properties": {
    "iso:country":"IT",
    "sg:address":"Strada Castiglione 2 12030 Cavallermaggiore",
    "sg:city":"Cavallermaggiore",
    "sg:classifiers":[
        {
            "category":"Wholesale",
            "subcategory":"Plants",
            "type":"Manufacturing & Wholesale Goods"
        }
    ],
    "sg:phone":"+39 0172 382829",
    "sg:postcode":"12030",
    "sg:province":"Cuneo",
    "sg:tags":[
        "forest"
    ],
    "sg:website":"www.alasiavivai.com",
    "wof:name":"Alasia Vivai S.s.",
    "wof:placetype":"venue"
},
  "geometry": {"coordinates":[7.859541893,44.6630210876],"type":"Point"}
}