{
  "type": "Feature",
  "properties": {
    "iso:country":"IT",
    "sg:address":"39014 Postal",
    "sg:city":"Postal",
    "sg:orig_category":"Legno E Semilavorati",
    "sg:phone":"+39 0473 291449",
    "sg:postcode":"39014",
    "sg:province":"Bolzano/Bozen",
    "wof:name":"Lochmann Reinhold & Co Sas",
    "wof:placetype":"venue"
},
  "geometry": {"coordinates":[11.186624,46.609615],"type":"Point"}
}