{
  "type": "Feature",
  "properties": {
    "addr:full":"41019 Soliera Soliera Modena 41019",
    "addr:postcode":"41019;41019",
    "iso:country":"IT",
    "sg:address":"41019 Soliera",
    "sg:city":"Soliera",
    "sg:orig_category":"Prodotti E Manufatti In Materie Plastiche. Articoli Per Imballaggio E Confezionamento",
    "sg:phone":"+39 059 561741",
    "sg:postcode":"41019",
    "sg:province":"Modena",
    "wof:name":"Man Plast Srl",
    "wof:placetype":"venue"
},
  "geometry": {"coordinates":[10.9058160782,44.7672615051],"type":"Point"}
}