{
  "type": "Feature",
  "properties": {
    "iso:country":"IT",
    "sg:address":"20060 Bussero",
    "sg:city":"Bussero",
    "sg:classifiers":[
        {
            "category":"Health Services",
            "subcategory":"Health Practitioner",
            "type":"Services"
        }
    ],
    "sg:phone":"+39 02 9503 9834",
    "sg:postcode":"20060",
    "sg:province":"Milano",
    "sg:tags":[
        "medici"
    ],
    "wof:name":"Formis Rodolfo",
    "wof:placetype":"venue"
},
  "geometry": {"coordinates":[9.377799,45.531918],"type":"Point"}
}