{
  "type": "Feature",
  "properties": {
    "addr:full":"84013 Cava De'tirreni Salerno 84013",
    "addr:postcode":"84013;84013",
    "addr:street":"De'Tirreni",
    "iso:country":"IT",
    "sg:address":"84013 Cava De'tirreni",
    "sg:classifiers":[
        {
            "category":"Manufacturing",
            "subcategory":"Wood Products",
            "type":"Manufacturing & Wholesale Goods"
        }
    ],
    "sg:phone":"+39 089 464302",
    "sg:postcode":"84013",
    "sg:province":"Salerno",
    "sg:tags":[
        "decorative",
        "building",
        "furnishings",
        "semi-finished",
        "industry",
        "objects",
        "article"
    ],
    "wof:name":"Cereria Virno Di Gallo Alfredo",
    "wof:placetype":"venue"
},
  "geometry": {"coordinates":[14.6937675476,40.7069854736],"type":"Point"}
}