{
  "type": "Feature",
  "properties": {
    "addr:full":"10024 Moncalieri Moncalieri Torino 10024",
    "addr:postcode":"10024;10024",
    "iso:country":"IT",
    "sg:address":"10024 Moncalieri",
    "sg:city":"Moncalieri",
    "sg:orig_category":"Apparecchiature Ed Attrezzature Meccaniche",
    "sg:phone":"+39 011 682 8068",
    "sg:postcode":"10024",
    "sg:province":"Torino",
    "wof:name":"A.a. Abrate Antonio & C. Sas",
    "wof:placetype":"venue"
},
  "geometry": {"coordinates":[7.691845,44.99511],"type":"Point"}
}