{
  "type": "Feature",
  "properties": {
    "iso:country":"IT",
    "sg:address":"257, C. Italia 80011 Acerra",
    "sg:city":"Acerra",
    "sg:classifiers":[
        {
            "category":"Autos & Motor Vehicles",
            "subcategory":"Boat Sales",
            "type":"Retail Goods"
        }
    ],
    "sg:phone":"+39 081 520 9717",
    "sg:postcode":"80011",
    "sg:province":"Napoli",
    "sg:website":"http://www.vivianaeilmare.it",
    "wof:name":"Viviana E Il Mare",
    "wof:placetype":"venue"
},
  "geometry": {"coordinates":[14.372628,40.937946],"type":"Point"}
}