{
  "type": "Feature",
  "properties": {
    "iso:country":"IT",
    "sg:address":"20083 Gaggiano",
    "sg:city":"Gaggiano",
    "sg:orig_category":"Non-classified Establishments",
    "sg:phone":"+39 02 908 5238",
    "sg:postcode":"20083",
    "sg:province":"Milano",
    "wof:name":"Bonomi Daniele",
    "wof:placetype":"venue"
},
  "geometry": {"coordinates":[9.11984,45.410942],"type":"Point"}
}