{
  "type": "Feature",
  "properties": {
    "iso:country":"IT",
    "sg:address":"28, Viale Lacchin Giuseppe 33077 Sacile",
    "sg:city":"Sacile",
    "sg:classifiers":[
        {
            "category":"Manufacturing",
            "subcategory":"Wood Products",
            "type":"Manufacturing & Wholesale Goods"
        }
    ],
    "sg:phone":"+39 0434 780660",
    "sg:postcode":"33077",
    "sg:province":"Pordenone",
    "sg:tags":[
        "furniture"
    ],
    "wof:name":"Anthea",
    "wof:placetype":"venue"
},
  "geometry": {"coordinates":[12.655044,45.96265],"type":"Point"}
}