{
  "type": "Feature",
  "properties": {
    "iso:country":"IT",
    "sg:address":"20080 Albairate",
    "sg:city":"Albairate",
    "sg:orig_category":"Materiali Semilavorati Metallici",
    "sg:phone":"+39 02 940 6739",
    "sg:postcode":"20080",
    "sg:province":"Milano",
    "sg:website":"http://www.alce.it",
    "wof:name":"Alce Srl",
    "wof:placetype":"venue"
},
  "geometry": {"coordinates":[8.926709,45.413429],"type":"Point"}
}