{
  "type": "Feature",
  "properties": {
    "iso:country":"IT",
    "sg:address":"00142 Roma",
    "sg:city":"Roma",
    "sg:orig_category":"Fotoriproduttori E Fotocopiatrici",
    "sg:phone":"+39 06 540 6873",
    "sg:postcode":"00142",
    "sg:province":"Roma",
    "sg:website":"http://www.diario-srl.it",
    "wof:name":"Diario Srl",
    "wof:placetype":"venue"
},
  "geometry": {"coordinates":[12.4896554947,41.8338775635],"type":"Point"}
}