{
  "type": "Feature",
  "properties": {
    "addr:full":"10090 Bruino Bruino Torino 10090",
    "addr:postcode":"10090;10090",
    "iso:country":"IT",
    "sg:address":"10090 Bruino",
    "sg:city":"Bruino",
    "sg:orig_category":"Macchine Utensili E Impianti",
    "sg:phone":"+39 011 908 5786",
    "sg:postcode":"10090",
    "sg:province":"Torino",
    "sg:website":"http://www.gamec.com",
    "wof:name":"G.a.mec. Srl",
    "wof:placetype":"venue"
},
  "geometry": {"coordinates":[7.670655,45.068172],"type":"Point"}
}