{
  "type": "Feature",
  "properties": {
    "iso:country":"IT",
    "sg:address":"95021 Aci Castello",
    "sg:city":"Aci Castello",
    "sg:orig_category":"Servizi Ausiliari Per Il Trasporto",
    "sg:phone":"+39 095 711 6970",
    "sg:postcode":"95021",
    "sg:province":"Catania",
    "wof:name":"Federazione Armatori Siciliani",
    "wof:placetype":"venue"
},
  "geometry": {"coordinates":[15.131743,37.551105],"type":"Point"}
}