{
  "type": "Feature",
  "properties": {
    "iso:country":"IT",
    "sg:address":"02046 Magliano Sabina",
    "sg:city":"Magliano Sabina",
    "sg:orig_category":"Arredamenti - Materiali",
    "sg:phone":"+39 0744 91639",
    "sg:postcode":"02046",
    "sg:province":"Rieti",
    "wof:name":"Marinucci Sergio",
    "wof:placetype":"venue"
},
  "geometry": {"coordinates":[12.480337,42.361649],"type":"Point"}
}