{
  "type": "Feature",
  "properties": {
    "iso:country":"IT",
    "sg:address":"38019 Tuenno",
    "sg:city":"Tuenno",
    "sg:orig_category":"Minuterie Metalliche E Ferramenta",
    "sg:phone":"+39 0463 450195",
    "sg:postcode":"38019",
    "sg:province":"Trento",
    "wof:name":"Trafileria Punteria Ghezzi (s.n.c.)",
    "wof:placetype":"venue"
},
  "geometry": {"coordinates":[11.0538835526,46.3415336609],"type":"Point"}
}