{
  "type": "Feature",
  "properties": {
    "iso:country":"IT",
    "sg:address":"46020 Motteggiana",
    "sg:city":"Motteggiana",
    "sg:orig_category":"Apparecchiature Ed Attrezzature Meccaniche",
    "sg:phone":"+39 0376 510900",
    "sg:postcode":"46020",
    "sg:province":"Mantova",
    "wof:name":"Mts Components Srl",
    "wof:placetype":"venue"
},
  "geometry": {"coordinates":[10.838754,45.167194],"type":"Point"}
}