{
  "type": "Feature",
  "properties": {
    "addr:full":"06121 Perugia Perugia Perugia 06121",
    "addr:postcode":"06121;06121",
    "iso:country":"IT",
    "sg:address":"06121 Perugia",
    "sg:city":"Perugia",
    "sg:orig_category":"Scuole E Servizi Scolastici. Ricerca, Selezione E Formazione Del Personale",
    "sg:phone":"+39 075 583 8115",
    "sg:postcode":"06121",
    "sg:province":"Perugia",
    "wof:name":"Cepu Srl",
    "wof:placetype":"venue"
},
  "geometry": {"coordinates":[12.387114,43.100693],"type":"Point"}
}