{
  "type": "Feature",
  "properties": {
    "addr:full":"01033 Civita Castellana Civita Castellana Viterbo 01033",
    "addr:postcode":"01033;01033",
    "iso:country":"IT",
    "sg:address":"01033 Civita Castellana",
    "sg:city":"Civita Castellana",
    "sg:orig_category":"Articoli Da Regalo. Arte Ed Artigianato Artistico. Shopping. Regalistica Aziendale",
    "sg:phone":"+39 0761 598111",
    "sg:postcode":"01033",
    "sg:province":"Viterbo",
    "wof:name":"Pill Boxes Di Edoardo Livolsi",
    "wof:placetype":"venue"
},
  "geometry": {"coordinates":[12.420336,42.289425],"type":"Point"}
}