{
  "type": "Feature",
  "properties": {
    "iso:country":"IT",
    "sg:address":"10152 Torino",
    "sg:city":"Torino",
    "sg:orig_category":"Non-classified Establishments",
    "sg:phone":"+39 011 857088",
    "sg:postcode":"10152",
    "sg:province":"Torino",
    "wof:name":"Rolando Perino Giuseppe",
    "wof:placetype":"venue"
},
  "geometry": {"coordinates":[7.692527,45.083775],"type":"Point"}
}