{
  "type": "Feature",
  "properties": {
    "iso:country":"IT",
    "sg:address":"Via Statale 33 23888 Rovagnate",
    "sg:city":"Rovagnate",
    "sg:classifiers":[
        {
            "category":"Building & Trades",
            "subcategory":"Construction",
            "type":"Services"
        }
    ],
    "sg:phone":"+39 039 57433",
    "sg:postcode":"23888",
    "sg:province":"Lecco",
    "sg:tags":[
        "carpenter's",
        "work",
        "supraregional"
    ],
    "wof:name":"Stie Srl",
    "wof:placetype":"venue"
},
  "geometry": {"coordinates":[9.372403,45.737167],"type":"Point"}
}