{
  "type": "Feature",
  "properties": {
    "iso:country":"IT",
    "sg:address":"26900 Lodi",
    "sg:city":"Lodi",
    "sg:orig_category":"Agenzie D'affari E Servizi Commerciali",
    "sg:phone":"+39 0371 549114",
    "sg:postcode":"26900",
    "sg:province":"Lodi",
    "wof:name":"New Businness Conpany Srl",
    "wof:placetype":"venue"
},
  "geometry": {"coordinates":[9.504045,45.311409],"type":"Point"}
}