{
  "type": "Feature",
  "properties": {
    "addr:full":"00175 Roma Roma Roma 00175",
    "addr:postcode":"00175;00175",
    "iso:country":"IT",
    "sg:address":"00175 Roma",
    "sg:city":"Roma",
    "sg:orig_category":"Animali Domestici - Toeletta",
    "sg:phone":"+39 06 714 0774",
    "sg:postcode":"00175",
    "sg:province":"Roma",
    "wof:name":"Mondo Cane",
    "wof:placetype":"venue"
},
  "geometry": {"coordinates":[12.427363,41.837921],"type":"Point"}
}