{
  "type": "Feature",
  "properties": {
    "iso:country":"IT",
    "sg:address":"10, Via Delle Industrie 30036 Santa Maria Di Sala",
    "sg:city":"Santa Maria di Sala",
    "sg:classifiers":[
        {
            "category":"Food & Beverages",
            "subcategory":"Groceries & Convenience Stores",
            "type":"Retail Goods"
        }
    ],
    "sg:phone":"+39 39041486177",
    "sg:postcode":"30036",
    "sg:province":"Venezia",
    "sg:tags":[
        "product",
        "related"
    ],
    "wof:name":"Bugin (s.r.l.)",
    "wof:placetype":"venue"
},
  "geometry": {"coordinates":[12.112906456,45.5369186401],"type":"Point"}
}