{
  "type": "Feature",
  "properties": {
    "addr:full":"24048 Treviolo Treviolo Bergamo 24048",
    "addr:postcode":"24048;24048",
    "iso:country":"IT",
    "sg:address":"24048 Treviolo",
    "sg:city":"Treviolo",
    "sg:orig_category":"Impianti, Attrezzature E Forniture Sanitarie Ed Ospedaliere",
    "sg:phone":"+39 035 690906",
    "sg:postcode":"24048",
    "sg:province":"Bergamo",
    "wof:name":"Surgi-cal Di Bellio Laura",
    "wof:placetype":"venue"
},
  "geometry": {"coordinates":[9.611899,45.673336],"type":"Point"}
}