{
  "type": "Feature",
  "properties": {
    "iso:country":"IT",
    "sg:address":"21100 Varese",
    "sg:city":"Varese",
    "sg:orig_category":"Non-classified Establishments",
    "sg:phone":"+39 0332 225334",
    "sg:postcode":"21100",
    "sg:province":"Varese",
    "sg:website":"http://www.debortoli.it",
    "wof:name":"De Bortoli Arredamenti Srl",
    "wof:placetype":"venue"
},
  "geometry": {"coordinates":[8.817751,45.836437],"type":"Point"}
}