{
  "type": "Feature",
  "properties": {
    "iso:country":"IT",
    "sg:address":"80022 Arzano",
    "sg:city":"Arzano",
    "sg:orig_category":"Divise Ed Uniformi",
    "sg:phone":"+39 081 731 3112",
    "sg:postcode":"80022",
    "sg:province":"Napoli",
    "wof:name":"Scuotto Industria Manufatti Snc",
    "wof:placetype":"venue"
},
  "geometry": {"coordinates":[14.268666,40.914997],"type":"Point"}
}