{
  "type": "Feature",
  "properties": {
    "addr:full":"20123 Milano Milano Milano 20123",
    "addr:postcode":"20123;20123",
    "iso:country":"IT",
    "sg:address":"20123 Milano",
    "sg:city":"Milano",
    "sg:orig_category":"Accessori Moda D'abbigliamento. Shopping",
    "sg:phone":"+39 02 8940 4896",
    "sg:postcode":"20123",
    "sg:province":"Milano",
    "wof:name":"Colombo Di Stratoti Gregorio",
    "wof:placetype":"venue"
},
  "geometry": {"coordinates":[9.173917,45.457104],"type":"Point"}
}