{
  "type": "Feature",
  "properties": {
    "addr:full":"54, Via Cariati 74100 Taranto Taranto Taranto 74100",
    "addr:postcode":"74100;74100",
    "addr:street":"Via Cariati",
    "iso:country":"IT",
    "sg:address":"54, Via Cariati 74100 Taranto",
    "sg:city":"Taranto",
    "sg:classifiers":[
        {
            "category":"Farming",
            "subcategory":"Livestock Farm",
            "type":"Manufacturing & Wholesale Goods"
        }
    ],
    "sg:phone":"+39 099 471 6110",
    "sg:postcode":"74100",
    "sg:province":"Taranto",
    "sg:tags":[
        "agriculture"
    ],
    "wof:name":"Nuova Taranfish S.r.l.",
    "wof:placetype":"venue"
},
  "geometry": {"coordinates":[17.228769,40.478306],"type":"Point"}
}