{
  "type": "Feature",
  "properties": {
    "addr:full":"157, Via Aurelia Sud 55045 Pietrasanta Pietrasanta Lucca 55045",
    "addr:housenumber":"157",
    "addr:postcode":"55045;55045",
    "addr:street":"Via Aurelia Sud",
    "iso:country":"IT",
    "sg:address":"157, Via Aurelia Sud 55045 Pietrasanta",
    "sg:city":"Pietrasanta",
    "sg:classifiers":[
        {
            "category":"Home & Garden",
            "subcategory":"Home Furnishings",
            "type":"Retail Goods"
        }
    ],
    "sg:phone":"+39 39058421925",
    "sg:postcode":"55045",
    "sg:province":"Lucca",
    "sg:tags":[
        "household"
    ],
    "wof:name":"Finamore Augusto & C.",
    "wof:placetype":"venue"
},
  "geometry": {"coordinates":[10.217743,43.922138],"type":"Point"}
}