{
  "type": "Feature",
  "properties": {
    "iso:country":"IT",
    "sg:address":"26831 Casalmaiocco",
    "sg:city":"Casalmaiocco",
    "sg:orig_category":"Minuterie Metalliche E Ferramenta",
    "sg:phone":"+39 02 9827 0376",
    "sg:postcode":"26831",
    "sg:province":"Lodi",
    "wof:name":"Fratelli Molinari Srl",
    "wof:placetype":"venue"
},
  "geometry": {"coordinates":[9.3590621948,45.3637466431],"type":"Point"}
}