{
  "type": "Feature",
  "properties": {
    "iso:country":"IT",
    "sg:address":"17, Via Tobagi Walter 20143 Milano",
    "sg:city":"Milano",
    "sg:classifiers":[
        {
            "category":"Professional",
            "subcategory":"Computer Services",
            "type":"Services"
        }
    ],
    "sg:phone":"+39 39028914031",
    "sg:postcode":"20143",
    "sg:province":"Milano",
    "sg:tags":[
        "information",
        "technology"
    ],
    "wof:name":"Faber System S.r.l.",
    "wof:placetype":"venue"
},
  "geometry": {"coordinates":[9.126651,45.417774],"type":"Point"}
}