{
  "type": "Feature",
  "properties": {
    "iso:country":"IT",
    "sg:address":"00167 Roma",
    "sg:city":"Roma",
    "sg:orig_category":"Carni, Salumi E Pesci",
    "sg:phone":"+39 06 662 1224",
    "sg:postcode":"00167",
    "sg:province":"Roma",
    "wof:name":"Minutillo Dante",
    "wof:placetype":"venue"
},
  "geometry": {"coordinates":[12.428773,41.900009],"type":"Point"}
}