{
  "type": "Feature",
  "properties": {
    "addr:full":"97015 Modica Modica Ragusa 97015",
    "addr:postcode":"97015;97015",
    "iso:country":"IT",
    "sg:address":"97015 Modica",
    "sg:city":"Modica",
    "sg:orig_category":"Scuole E Servizi Scolastici. Ricerca, Selezione E Formazione Del Personale. Pubblica Amministrazione",
    "sg:phone":"+39 0932 904011",
    "sg:postcode":"97015",
    "sg:province":"Ragusa",
    "wof:name":"Istituto Professionale Alberghiero & Agricoltura E Ambiente",
    "wof:placetype":"venue"
},
  "geometry": {"coordinates":[14.764702,36.844814],"type":"Point"}
}