{
  "type": "Feature",
  "properties": {
    "iso:country":"IT",
    "sg:address":"5, Via Asiago 31030 Castello Di Godego",
    "sg:city":"Castello di Godego",
    "sg:classifiers":[
        {
            "category":"Autos & Motor Vehicles",
            "subcategory":"Automobile Sales",
            "type":"Retail Goods"
        }
    ],
    "sg:phone":"+39 0423 760075",
    "sg:postcode":"31030",
    "sg:province":"Treviso",
    "sg:tags":[
        "motor-cars"
    ],
    "wof:name":"Tecnosir S.r.l.",
    "wof:placetype":"venue"
},
  "geometry": {"coordinates":[11.8557872772,45.6948623657],"type":"Point"}
}