{
  "type": "Feature",
  "properties": {
    "addr:full":"25047 Darfo Boario Terme Darfo Brescia 25047",
    "addr:postcode":"25047;25047",
    "iso:country":"IT",
    "sg:address":"25047 Darfo Boario Terme",
    "sg:city":"Darfo",
    "sg:classifiers":[
        {
            "category":"Arena",
            "subcategory":"Sports Club",
            "type":"Entertainment"
        }
    ],
    "sg:phone":"+39 036 453 2202",
    "sg:postcode":"25047",
    "sg:province":"Brescia",
    "sg:tags":[
        "e",
        "lo",
        "tempo",
        "libero",
        "per",
        "servizi",
        "il"
    ],
    "wof:name":"Giacomelli Simone",
    "wof:placetype":"venue"
},
  "geometry": {"coordinates":[10.185856,45.874592],"type":"Point"}
}