{
  "type": "Feature",
  "properties": {
    "addr:full":"84084 Penta Penta Salerno 84084",
    "addr:postcode":"84084;84084",
    "iso:country":"IT",
    "sg:address":"84084 Penta",
    "sg:city":"Penta",
    "sg:orig_category":"Metalli E Leghe",
    "sg:phone":"+39 089 958180",
    "sg:postcode":"84084",
    "sg:province":"Salerno",
    "wof:name":"Villari Vittorio",
    "wof:placetype":"venue"
},
  "geometry": {"coordinates":[14.7914237976,40.7606086731],"type":"Point"}
}