{
  "type": "Feature",
  "properties": {
    "iso:country":"IT",
    "sg:address":"98066 Patti",
    "sg:city":"Patti",
    "sg:orig_category":"Biliardi Ed Accessori",
    "sg:phone":"+39 0941 562694",
    "sg:postcode":"98066",
    "sg:province":"Messina",
    "wof:name":"Magistro Contenta Maria M.c.m",
    "wof:placetype":"venue"
},
  "geometry": {"coordinates":[14.980865,38.14922],"type":"Point"}
}