{
  "type": "Feature",
  "properties": {
    "addr:full":"39020 Stelvio Tel Bolzano/Bozen 39020",
    "addr:postcode":"39020;tel;39020",
    "addr:street":"Stelvio",
    "iso:country":"IT",
    "sg:address":"39020 Stelvio",
    "sg:city":"Tel",
    "sg:orig_category":"Alberghi",
    "sg:phone":"+39 0473 613021",
    "sg:postcode":"39020",
    "sg:province":"Bolzano/Bozen",
    "sg:website":"http://www.hoteleller.com",
    "wof:name":"Hotel Eller Srl",
    "wof:placetype":"venue"
},
  "geometry": {"coordinates":[11.358005,46.496716],"type":"Point"}
}