{
  "type": "Feature",
  "properties": {
    "addr:full":"20131 Milano Milano Milano 20131",
    "addr:postcode":"20131;20131",
    "iso:country":"IT",
    "sg:address":"20131 Milano",
    "sg:city":"Milano",
    "sg:orig_category":"Telecomunicazioni E Telefonia, Impianti, Apparecchi E Servizi. Acqua, Luce, Gas E Societa' Di Esercizio Pubblico. Servizi Vari Di Interesse Pubblico",
    "sg:phone":"+39 02 236 7903",
    "sg:postcode":"20131",
    "sg:province":"Milano",
    "wof:name":"24 Horas Services Di Bravo Cardenas Henry",
    "wof:placetype":"venue"
},
  "geometry": {"coordinates":[9.229942,45.484535],"type":"Point"}
}