{
  "type": "Feature",
  "properties": {
    "addr:full":"29, Zona Industriale Iii Strada 30030 Fosso' Venezia 30030",
    "addr:housenumber":"29",
    "addr:postcode":"30030;30030",
    "addr:street":"Zona;Strada",
    "iso:country":"IT",
    "sg:address":"29, Zona Industriale Iii Strada 30030 Fosso'",
    "sg:classifiers":[
        {
            "category":"Professional",
            "subcategory":"Business Services",
            "type":"Services"
        }
    ],
    "sg:phone":"+39 041 416 5770",
    "sg:postcode":"30030",
    "sg:province":"Venezia",
    "sg:tags":[
        "advice"
    ],
    "wof:name":"Tucano Macchine (s.r.l.)",
    "wof:placetype":"venue"
},
  "geometry": {"coordinates":[12.338784,45.434338],"type":"Point"}
}