{
  "type": "Feature",
  "properties": {
    "iso:country":"IT",
    "sg:address":"00196 Roma",
    "sg:city":"Roma",
    "sg:orig_category":"Materiali Edili",
    "sg:phone":"+39 06 361 4045",
    "sg:postcode":"00196",
    "sg:province":"Roma",
    "wof:name":"Laterizi Riunite (s.p.a.)",
    "wof:placetype":"venue"
},
  "geometry": {"coordinates":[12.463854,41.927189],"type":"Point"}
}