{
  "type": "Feature",
  "properties": {
    "addr:full":"24060 San Paolo D'argon Bergamo 24060",
    "addr:housenumber":"24060",
    "addr:postcode":"24060",
    "addr:street":"San",
    "iso:country":"IT",
    "sg:address":"24060 San Paolo D'argon",
    "sg:orig_category":"Forniture Per Agricoltura E Zootecnia. Prodotti Chimici Secondari",
    "sg:phone":"+39 035 958406",
    "sg:postcode":"24060",
    "sg:province":"Bergamo",
    "wof:name":"Agrimport (s.r.l.)",
    "wof:placetype":"venue"
},
  "geometry": {"coordinates":[9.7948970795,45.6844062805],"type":"Point"}
}