{
  "type": "Feature",
  "properties": {
    "addr:full":"95128 Catania Catania Catania 95128",
    "addr:postcode":"95128;95128",
    "iso:country":"IT",
    "sg:address":"95128 Catania",
    "sg:city":"Catania",
    "sg:orig_category":"Automazione E Macchine Per Ufficio. Servizi Ausiliari Di Certificati, Riproduzioni, Disegni E Foto",
    "sg:phone":"+39 095 436252",
    "sg:postcode":"95128",
    "sg:province":"Catania",
    "wof:name":"Micron S.p.a.",
    "wof:placetype":"venue"
},
  "geometry": {"coordinates":[15.088243,37.520954],"type":"Point"}
}