{
  "type": "Feature",
  "properties": {
    "iso:country":"IT",
    "sg:address":"Piazza S. Fedele, 4; Milano; 20121",
    "sg:city":"Milano",
    "sg:classifiers":[
        {
            "category":"Banks & Credit Unions",
            "subcategory":"Bank",
            "type":"Services"
        }
    ],
    "sg:phone":"+39 0221731",
    "sg:postcode":"20121",
    "sg:province":"Milano",
    "wof:name":"Credito Artigiano",
    "wof:placetype":"venue"
},
  "geometry": {"coordinates":[9.191258,45.466442],"type":"Point"}
}