{
  "type": "Feature",
  "properties": {
    "iso:country":"IT",
    "sg:address":"55045 Pietrasanta",
    "sg:city":"Pietrasanta",
    "sg:orig_category":"Impianti Elettrici Industriali E Civili - Installazione E Manutenzione",
    "sg:phone":"+39 0584 790643",
    "sg:postcode":"55045",
    "sg:province":"Lucca",
    "wof:name":"Elettromeccanica 2g Srl",
    "wof:placetype":"venue"
},
  "geometry": {"coordinates":[10.229042,43.947212],"type":"Point"}
}