{
  "type": "Feature",
  "properties": {
    "addr:full":"41012 Carpi Carpi Modena 41012",
    "addr:postcode":"41012;41012",
    "iso:country":"IT",
    "sg:address":"41012 Carpi",
    "sg:city":"Carpi",
    "sg:orig_category":"Abbigliamento Esterno, Maglierie E Pelliccerie. Shopping",
    "sg:phone":"+39 059 663925",
    "sg:postcode":"41012",
    "sg:province":"Modena",
    "wof:name":"Maglificio Rosmarie Srl",
    "wof:placetype":"venue"
},
  "geometry": {"coordinates":[10.876288,44.751987],"type":"Point"}
}