{
  "type": "Feature",
  "properties": {
    "addr:full":"52040 Tegoleto AR",
    "addr:postcode":"52040",
    "iso:country":"IT",
    "sg:address":"52040 Tegoleto",
    "sg:orig_category":"Frigotecnica, Apparecchiature E Servizi. Arredi Ed Attrezzature Per Uffici",
    "sg:phone":"+39 0575 497706",
    "sg:province":"AR",
    "wof:name":"Frigomeccanica (s.n.c.)",
    "wof:placetype":"venue"
},
  "geometry": {"coordinates":[11.7845954895,43.3945617676],"type":"Point"}
}