{
  "type": "Feature",
  "properties": {
    "addr:full":"22070 Grandate Grandate Como 22070",
    "addr:postcode":"22070;22070",
    "iso:country":"IT",
    "sg:address":"22070 Grandate",
    "sg:city":"Grandate",
    "sg:orig_category":"Apparecchiature Oleodinamiche",
    "sg:phone":"+39 031 564700",
    "sg:postcode":"22070",
    "sg:province":"Como",
    "wof:name":"R.t.c.",
    "wof:placetype":"venue"
},
  "geometry": {"coordinates":[9.056132,45.768761],"type":"Point"}
}