{
  "type": "Feature",
  "properties": {
    "addr:full":"Via San Donato 83; Bologna; 40127 Bologna Bologna 40127",
    "addr:housenumber":"83",
    "addr:postcode":"40127;40127",
    "addr:street":"Via San Donato",
    "iso:country":"IT",
    "sg:address":"Via San Donato 83; Bologna; 40127",
    "sg:city":"Bologna",
    "sg:classifiers":[
        {
            "category":"Banks & Credit Unions",
            "subcategory":"Bank",
            "type":"Services"
        }
    ],
    "sg:phone":"+39 051 633 2208",
    "sg:postcode":"40127",
    "sg:province":"Bologna",
    "wof:name":"Rolo Banca 1473 Spa",
    "wof:placetype":"venue"
},
  "geometry": {"coordinates":[11.370589,44.504791],"type":"Point"}
}