{
  "type": "Feature",
  "properties": {
    "iso:country":"IT",
    "sg:address":"8, Strada Del Vino 39057 Appiano Sulla Strada Del Vino",
    "sg:city":"Appiano sulla strada del vino",
    "sg:classifiers":[
        {
            "category":"Food & Beverages",
            "subcategory":"Groceries & Convenience Stores",
            "type":"Retail Goods"
        }
    ],
    "sg:phone":"+39 0471 664246",
    "sg:postcode":"39057",
    "sg:province":"Bolzano/Bozen",
    "sg:tags":[
        "drink"
    ],
    "wof:name":"Cantina Produttori Colterenzio Soc.coop.a.r.l.",
    "wof:placetype":"venue"
},
  "geometry": {"coordinates":[11.29442,46.471786],"type":"Point"}
}