{
  "type": "Feature",
  "properties": {
    "iso:country":"IT",
    "sg:address":"24069 Cenate Sotto",
    "sg:city":"Cenate Sotto",
    "sg:orig_category":"Articoli Da Regalo. Arte Ed Artigianato Artistico. Shopping. Regalistica Aziendale",
    "sg:phone":"+39 035 940096",
    "sg:postcode":"24069",
    "sg:province":"Bergamo",
    "wof:name":"Zenoni Giuseppe",
    "wof:placetype":"venue"
},
  "geometry": {"coordinates":[9.827661,45.696636],"type":"Point"}
}