{
  "type": "Feature",
  "properties": {
    "addr:full":"21052 Busto Arsizio Busto Arsizio Varese 21052",
    "addr:postcode":"21052;21052",
    "iso:country":"IT",
    "sg:address":"21052 Busto Arsizio",
    "sg:city":"Busto Arsizio",
    "sg:orig_category":"Macchine, Impianti Ed Attrezzature Per Abbigliamento E Pelletterie",
    "sg:phone":"+39 0331 686333",
    "sg:postcode":"21052",
    "sg:province":"Varese",
    "wof:name":"M.s.p. (s.n.c.)",
    "wof:placetype":"venue"
},
  "geometry": {"coordinates":[8.842774,45.618965],"type":"Point"}
}