{
  "type": "Feature",
  "properties": {
    "iso:country":"IT",
    "sg:address":"1, Via G. Mazzini 21041 Albizzate",
    "sg:city":"Albizzate",
    "sg:classifiers":[
        {
            "category":"Home & Garden",
            "subcategory":"Home Furnishings",
            "type":"Retail Goods"
        }
    ],
    "sg:phone":"+39 0331 993200",
    "sg:postcode":"21041",
    "sg:province":"Varese",
    "sg:tags":[
        "household"
    ],
    "wof:name":"Rossi Di Albizzate (s.p.a.)",
    "wof:placetype":"venue"
},
  "geometry": {"coordinates":[8.828389,45.768631],"type":"Point"}
}