{
  "type": "Feature",
  "properties": {
    "iso:country":"IT",
    "sg:address":"24061 Albano Sant'alessandro",
    "sg:orig_category":"Macchine Ed Impianti Per Edilizia E Lavori Pubblici",
    "sg:phone":"+39 035 581035",
    "sg:postcode":"24061",
    "sg:province":"Bergamo",
    "wof:name":"Costruzioni Meccaniche Quassi (s.n.c.)",
    "wof:placetype":"venue"
},
  "geometry": {"coordinates":[9.746792,45.689964],"type":"Point"}
}