{
  "type": "Feature",
  "properties": {
    "iso:country":"IT",
    "sg:address":"Via E Nardi; Venarotta",
    "sg:classifiers":[
        {
            "category":"Banks & Credit Unions",
            "subcategory":"Bank",
            "type":"Services"
        }
    ],
    "sg:phone":"+39 0736 362597",
    "wof:name":"Banca Di Roma",
    "wof:placetype":"venue"
},
  "geometry": {"coordinates":[13.49434,42.88192],"type":"Point"}
}