{
  "type": "Feature",
  "properties": {
    "iso:country":"IT",
    "sg:address":"Viale Vittorio Veneto 112 13011 Borgosesia",
    "sg:city":"Borgosesia",
    "sg:classifiers":[
        {
            "category":"Community Center",
            "subcategory":"Senior",
            "type":"Public Place"
        }
    ],
    "sg:phone":"+39 0163 22751",
    "sg:postcode":"13011",
    "sg:province":"Vercelli",
    "sg:tags":[
        "die",
        "brass",
        "casting"
    ],
    "wof:name":"Metalfusor",
    "wof:placetype":"venue"
},
  "geometry": {"coordinates":[8.282822,45.71315],"type":"Point"}
}