{
  "type": "Feature",
  "properties": {
    "iso:country":"IT",
    "sg:address":"00138 Roma",
    "sg:city":"Roma",
    "sg:orig_category":"Agenzie Ed Uffici Commerciali",
    "sg:phone":"+39 0688311",
    "sg:postcode":"00138",
    "sg:province":"Roma",
    "sg:website":"http://www.igol.it",
    "wof:name":"Societa' Per L'imprenditorialita' Giovanile Spa",
    "wof:placetype":"venue"
},
  "geometry": {"coordinates":[12.576381,41.876678],"type":"Point"}
}