{
  "type": "Feature",
  "properties": {
    "addr:full":"50133 Firenze Firenze Firenze 50133",
    "addr:postcode":"50133;50133",
    "iso:country":"IT",
    "sg:address":"50133 Firenze",
    "sg:city":"Firenze",
    "sg:orig_category":"Servizi Per Aziende, Manifestazioni E Supporto Agli Scambi Commerciali",
    "sg:phone":"+39 339 446 2588",
    "sg:postcode":"50133",
    "sg:province":"Firenze",
    "wof:name":"Sp Agency Servizi & Spettacoli",
    "wof:placetype":"venue"
},
  "geometry": {"coordinates":[11.270862,43.790886],"type":"Point"}
}