{
  "type": "Feature",
  "properties": {
    "iso:country":"IT",
    "sg:address":"08028 Orosei",
    "sg:city":"Orosei",
    "sg:classifiers":[
        {
            "category":"Home & Garden",
            "subcategory":"Building Materials",
            "type":"Retail Goods"
        }
    ],
    "sg:phone":"+39 0784 98619",
    "sg:postcode":"08028",
    "sg:province":"Nuoro",
    "sg:tags":[
        "stone",
        "similar",
        "marble"
    ],
    "sg:website":"http://www.simg-marmi.com",
    "wof:name":"S.i.m.g. Srl",
    "wof:placetype":"venue"
},
  "geometry": {"coordinates":[9.712121,40.398346],"type":"Point"}
}