{
  "type": "Feature",
  "properties": {
    "iso:country":"IT",
    "sg:address":"1, Via Circonfucense 67056 Luco Dei Marsi",
    "sg:classifiers":[
        {
            "category":"Food & Beverages",
            "subcategory":"Groceries & Convenience Stores",
            "type":"Retail Goods"
        }
    ],
    "sg:phone":"+39 0863 528911",
    "sg:postcode":"67056",
    "sg:province":"L'Aquila",
    "sg:tags":[
        "product",
        "related"
    ],
    "wof:name":"Cooperativa Montebello",
    "wof:placetype":"venue"
},
  "geometry": {"coordinates":[13.4110422134,41.9408531189],"type":"Point"}
}