{
  "type": "Feature",
  "properties": {
    "addr:full":"41100 Modena Modena Modena 41100",
    "addr:postcode":"41100;41100",
    "iso:country":"IT",
    "sg:address":"41100 Modena",
    "sg:city":"Modena",
    "sg:orig_category":"Metalli Non Ferrosi E Leghe",
    "sg:phone":"+39 059 453811",
    "sg:postcode":"41100",
    "sg:province":"Modena",
    "wof:name":"Galvan Tubi Spa",
    "wof:placetype":"venue"
},
  "geometry": {"coordinates":[10.9439992905,44.6720809937],"type":"Point"}
}