{
  "type": "Feature",
  "properties": {
    "iso:country":"IT",
    "sg:address":"Via I Maggio, 2/4 24060 Telgate",
    "sg:city":"Telgate",
    "sg:classifiers":[
        {
            "category":"Shopping",
            "subcategory":"Baby Store",
            "type":"Retail Goods"
        }
    ],
    "sg:phone":"+39 035 831271",
    "sg:postcode":"24060",
    "sg:province":"Bergamo",
    "sg:tags":[
        "babies'",
        "buggy",
        "pram"
    ],
    "sg:website":"www.primisogni.com",
    "wof:name":"Primi Sogni Srl",
    "wof:placetype":"venue"
},
  "geometry": {"coordinates":[9.669952,45.694904],"type":"Point"}
}