{
  "type": "Feature",
  "properties": {
    "addr:full":"10040 Pralormo Pralormo Torino 10040",
    "addr:housenumber":"10040",
    "addr:postcode":"10040",
    "addr:street":"Pralormo Pralormo",
    "iso:country":"IT",
    "sg:address":"10040 Pralormo",
    "sg:city":"Pralormo",
    "sg:orig_category":"Elettrotecnica Industriale, Prodotti E Apparecchiature",
    "sg:phone":"+39 011 948 1813",
    "sg:postcode":"10040",
    "sg:province":"Torino",
    "wof:name":"El.mec Di Mitoli Alberto",
    "wof:placetype":"venue"
},
  "geometry": {"coordinates":[7.9025,44.860798],"type":"Point"}
}