{
  "type": "Feature",
  "properties": {
    "iso:country":"IT",
    "sg:address":"189, Via Massaia Guglielmo Cardinale 90142 Palermo",
    "sg:city":"Palermo",
    "sg:classifiers":[
        {
            "category":"Autos & Motor Vehicles",
            "subcategory":"Boat Sales",
            "type":"Retail Goods"
        }
    ],
    "sg:phone":"+39 39091540564",
    "sg:postcode":"90142",
    "sg:province":"Palermo",
    "wof:name":"Ma.ri.naval.s.r.l.",
    "wof:placetype":"venue"
},
  "geometry": {"coordinates":[13.361376,38.11562],"type":"Point"}
}