{
  "type": "Feature",
  "properties": {
    "addr:full":"138, V. Emanuele Filiberto 00185 Roma Roma Roma 00185",
    "addr:housenumber":"138",
    "addr:postcode":"00185;00185",
    "addr:street":"V. Emanuele Filiberto",
    "iso:country":"IT",
    "sg:address":"138, V. Emanuele Filiberto 00185 Roma",
    "sg:city":"Roma",
    "sg:classifiers":[
        {
            "category":"Communications",
            "subcategory":"Television Station",
            "type":"Services"
        }
    ],
    "sg:phone":"+39 06 7720 5304",
    "sg:postcode":"00185",
    "sg:province":"Roma",
    "sg:tags":[
        "equipment",
        "optical",
        "instrument"
    ],
    "sg:website":"http://www.paginegialle.it/magonicola",
    "wof:name":"Mago Nicola",
    "wof:placetype":"venue"
},
  "geometry": {"coordinates":[12.507721,41.888405],"type":"Point"}
}