{
  "type": "Feature",
  "properties": {
    "addr:full":"52100 Arezzo Arezzo Arezzo 52100",
    "addr:postcode":"52100;52100",
    "iso:country":"IT",
    "sg:address":"52100 Arezzo",
    "sg:city":"Arezzo",
    "sg:orig_category":"Accessori Moda D'abbigliamento",
    "sg:phone":"+39 0575 321082",
    "sg:postcode":"52100",
    "sg:province":"Arezzo",
    "wof:name":"Chimera Gold Snc",
    "wof:placetype":"venue"
},
  "geometry": {"coordinates":[11.865387,43.494888],"type":"Point"}
}