{
  "type": "Feature",
  "properties": {
    "iso:country":"IT",
    "sg:address":"24030 Medolago",
    "sg:city":"Medolago",
    "sg:orig_category":"Macchine Ed Impianti Per Edilizia E Lavori Pubblici. Apparecchiature Ed Attrezzature Meccaniche",
    "sg:phone":"+39 035 493 3373",
    "sg:postcode":"24030",
    "sg:province":"Bergamo",
    "wof:name":"Belli Di Belli E. & C. Snc",
    "wof:placetype":"venue"
},
  "geometry": {"coordinates":[9.505103,45.675678],"type":"Point"}
}