{
  "type": "Feature",
  "properties": {
    "addr:full":"26/a, Via Torquato Tasso 42023 Cadelbosco Di Sopra Reggio Nell'Emilia 42023",
    "addr:housenumber":"26 / a",
    "addr:postcode":"42023;42023",
    "addr:street":"Via Torquato Tasso",
    "iso:country":"IT",
    "sg:address":"26/a, Via Torquato Tasso 42023 Cadelbosco Di Sopra",
    "sg:classifiers":[
        {
            "category":"Manufacturing",
            "subcategory":"Metals",
            "type":"Manufacturing & Wholesale Goods"
        }
    ],
    "sg:phone":"+39 0522 917123",
    "sg:postcode":"42023",
    "sg:province":"Reggio Nell'Emilia",
    "sg:tags":[
        "processing"
    ],
    "wof:name":"Zi.d.e. (s.r.l.)",
    "wof:placetype":"venue"
},
  "geometry": {"coordinates":[10.6020154953,44.7553291321],"type":"Point"}
}