{
  "type": "Feature",
  "properties": {
    "iso:country":"IT",
    "sg:address":"Zona Industriale 223 66034 Lanciano",
    "sg:city":"Lanciano",
    "sg:orig_category":"Traffic Sign Films, Reflective",
    "sg:phone":"+39 0872 7051",
    "sg:postcode":"66034",
    "sg:province":"Chieti",
    "sg:website":"www.sanmarco-icm.com",
    "wof:name":"San Marco Spa",
    "wof:placetype":"venue"
},
  "geometry": {"coordinates":[14.167151,42.351791],"type":"Point"}
}