{
  "type": "Feature",
  "properties": {
    "iso:country":"IT",
    "sg:address":"20122 Milano",
    "sg:city":"Milano",
    "sg:orig_category":"Forniture Per Abbigliamento E Pelletterie",
    "sg:phone":"+39 02 5830 4391",
    "sg:postcode":"20122",
    "sg:province":"Milano",
    "wof:name":"Istituto Artistico Abbigliamento Marangoni (s.r.l.)",
    "wof:placetype":"venue"
},
  "geometry": {"coordinates":[9.1920127869,45.4594116211],"type":"Point"}
}