{
  "type": "Feature",
  "properties": {
    "iso:country":"IT",
    "sg:address":"Loc Bagnaia, 13/2 52100 Arezzo",
    "sg:city":"Arezzo",
    "sg:classifiers":[
        {
            "category":"Shopping",
            "subcategory":"Jewelry",
            "type":"Retail Goods"
        }
    ],
    "sg:phone":"+39 0575 966266",
    "sg:postcode":"52100",
    "sg:province":"Arezzo",
    "sg:tags":[
        "jewellery",
        "gold"
    ],
    "sg:website":"www.primaverapreziosi.com",
    "wof:name":"Primavera Preziosi Di Roberto Burroni & C Snc",
    "wof:placetype":"venue"
},
  "geometry": {"coordinates":[11.863062,43.471203],"type":"Point"}
}