{
  "type": "Feature",
  "properties": {
    "addr:full":"89125 Reggio Calabria RC",
    "addr:postcode":"89125",
    "iso:country":"IT",
    "sg:address":"89125 Reggio Calabria",
    "sg:orig_category":"Pneumatici - Commercio E Riparazione",
    "sg:phone":"+39 0965 28981",
    "sg:province":"RC",
    "wof:name":"Mannino Srl",
    "wof:placetype":"venue"
},
  "geometry": {"coordinates":[15.6478509903,38.1101264954],"type":"Point"}
}