{
  "type": "Feature",
  "properties": {
    "iso:country":"IT",
    "sg:address":"20017 Rho",
    "sg:city":"Rho",
    "sg:orig_category":"Macchine, Impianti Ed Attrezzature Industria Delle Materie Plastiche E Gomma",
    "sg:phone":"+39 02 9390 1166",
    "sg:postcode":"20017",
    "sg:province":"Milano",
    "wof:name":"Pressosud Snc Dei Fratelli Marino",
    "wof:placetype":"venue"
},
  "geometry": {"coordinates":[9.092377,45.525948],"type":"Point"}
}