{
  "type": "Feature",
  "properties": {
    "iso:country":"IT",
    "sg:address":"27020 Zerbolo'",
    "sg:orig_category":"Servizi Per Lo Sport E Il Tempo Libero. Servizi Al Turismo",
    "sg:phone":"+39 0382 818354",
    "sg:postcode":"27020",
    "sg:province":"Pavia",
    "wof:name":"Parco Acquatico Ticino Srl",
    "wof:placetype":"venue"
},
  "geometry": {"coordinates":[9.039779,45.253403],"type":"Point"}
}