{
  "type": "Feature",
  "properties": {
    "iso:country":"IT",
    "sg:address":"20090 Trezzano Sul Naviglio",
    "sg:city":"Trezzano sul Naviglio",
    "sg:orig_category":"Utensili Meccanici E Materiali",
    "sg:phone":"+39 02 4840 0752",
    "sg:postcode":"20090",
    "sg:province":"Milano",
    "wof:name":"Galesi Ossigenoterapia Srl",
    "wof:placetype":"venue"
},
  "geometry": {"coordinates":[9.056388,45.422085],"type":"Point"}
}