{
  "type": "Feature",
  "properties": {
    "iso:country":"IT",
    "sg:address":"95030 Catania",
    "sg:orig_category":"Utensili Meccanici E Materiali",
    "sg:phone":"+39 095 735 7264",
    "sg:postcode":"95030",
    "sg:province":"Catania",
    "wof:name":"Terranova Srl",
    "wof:placetype":"venue"
},
  "geometry": {"coordinates":[15.089929,37.511295],"type":"Point"}
}