{
  "type": "Feature",
  "properties": {
    "iso:country":"IT",
    "sg:address":"42027 Montecchio Emilia",
    "sg:orig_category":"Servizi E Lavori Per Abbigliamento E Pelletterie",
    "sg:phone":"+39 0522 865085",
    "sg:postcode":"42027",
    "sg:province":"Reggio Nell'Emilia",
    "wof:name":"Casotti Bianca & C. S.a.s.",
    "wof:placetype":"venue"
},
  "geometry": {"coordinates":[10.627794,44.696228],"type":"Point"}
}