{
  "type": "Feature",
  "properties": {
    "iso:country":"IT",
    "sg:address":"25020 Offlaga",
    "sg:city":"Offlaga",
    "sg:orig_category":"Prodotti E Manufatti In Materie Plastiche. Forniture Per Attivita' Industriali",
    "sg:phone":"+39 030 979670",
    "sg:postcode":"25020",
    "sg:province":"Brescia",
    "wof:name":"Nova Plastik (s.r.l.)",
    "wof:placetype":"venue"
},
  "geometry": {"coordinates":[10.1211681366,45.2473983765],"type":"Point"}
}