{
  "type": "Feature",
  "properties": {
    "iso:country":"IT",
    "sg:address":"28076 Pogno",
    "sg:city":"Pogno",
    "sg:orig_category":"Arredo Bagno Ed Idrosanitari. Idrosanitari E Accessori. Minuterie Metalliche E Ferramenta",
    "sg:phone":"+39 0322 97207",
    "sg:postcode":"28076",
    "sg:province":"Novara",
    "sg:website":"http://www.rubitor.com",
    "wof:name":"Rubitor Srl",
    "wof:placetype":"venue"
},
  "geometry": {"coordinates":[8.383867,45.754551],"type":"Point"}
}