{
  "type": "Feature",
  "properties": {
    "iso:country":"IT",
    "sg:address":"25123 Brescia",
    "sg:city":"Brescia",
    "sg:orig_category":"Stampi Materie Plastiche E Gomma",
    "sg:phone":"+39 030 362613",
    "sg:postcode":"25123",
    "sg:province":"Brescia",
    "wof:name":"D.f.b. Srl",
    "wof:placetype":"venue"
},
  "geometry": {"coordinates":[10.240805,45.529957],"type":"Point"}
}