{
  "type": "Feature",
  "properties": {
    "iso:country":"IT",
    "sg:address":"06063 Magione",
    "sg:city":"Magione",
    "sg:orig_category":"Automobili E Mezzi Di Trasporto",
    "sg:phone":"+39 075 843741",
    "sg:postcode":"06063",
    "sg:province":"Perugia",
    "wof:name":"B.c.r. Snc Officina Meccanica Di Riparazioni",
    "wof:placetype":"venue"
},
  "geometry": {"coordinates":[12.186145,43.119774],"type":"Point"}
}