{
  "type": "Feature",
  "properties": {
    "iso:country":"IT",
    "sg:address":"20026 Novate Milanese",
    "sg:city":"Novate Milanese",
    "sg:orig_category":"Materiali E Componenti Elettrotecnici",
    "sg:phone":"+39 02 3820 0716",
    "sg:postcode":"20026",
    "sg:province":"Milano",
    "wof:name":"Avel Di Tampanelli Clara",
    "wof:placetype":"venue"
},
  "geometry": {"coordinates":[9.133265,45.534405],"type":"Point"}
}