{
  "type": "Feature",
  "properties": {
    "iso:country":"IT",
    "sg:address":"62100 Macerata",
    "sg:city":"Macerata",
    "sg:orig_category":"Persiane Ed Avvolgibili",
    "sg:phone":"+39 0733 292148",
    "sg:postcode":"62100",
    "sg:province":"Macerata",
    "wof:name":"Ramaccioni Fratelli Snc",
    "wof:placetype":"venue"
},
  "geometry": {"coordinates":[13.4861774445,43.2758293152],"type":"Point"}
}