{
  "type": "Feature",
  "properties": {
    "iso:country":"IT",
    "sg:address":"20124 Milano",
    "sg:city":"Milano",
    "sg:orig_category":"Studi E Consulenze Amministrative, Commerciali E Aziendali. Banche E Servizi Finanziari. Agenzie D'affari E Servizi Commerciali. Consulenze Tecniche, Amministrative E Perizie",
    "sg:phone":"+39 02 2952 3512",
    "sg:postcode":"20124",
    "sg:province":"Milano",
    "wof:name":"R & S Consulting Sas",
    "wof:placetype":"venue"
},
  "geometry": {"coordinates":[9.20244,45.47646],"type":"Point"}
}