{
  "type": "Feature",
  "properties": {
    "iso:country":"IT",
    "sg:address":"10123 Torino",
    "sg:city":"Torino",
    "sg:orig_category":"Servizi Editoriali. Shopping",
    "sg:phone":"+39 011 517 5361",
    "sg:postcode":"10123",
    "sg:province":"Torino",
    "wof:name":"Avignone Rossa Giorgio",
    "wof:placetype":"venue"
},
  "geometry": {"coordinates":[7.592328,45.029629],"type":"Point"}
}