{
  "type": "Feature",
  "properties": {
    "iso:country":"IT",
    "sg:address":"73056 Taurisano",
    "sg:city":"Taurisano",
    "sg:orig_category":"Agricoltura, Orticoltura E Floricoltura",
    "sg:phone":"+39 0833 623187",
    "sg:postcode":"73056",
    "sg:province":"Lecce",
    "wof:name":"Ciullo Francesco",
    "wof:placetype":"venue"
},
  "geometry": {"coordinates":[18.155115,40.011345],"type":"Point"}
}