{
  "type": "Feature",
  "properties": {
    "addr:full":"06059 Todi Todi Perugia 06059",
    "addr:postcode":"06059;06059",
    "iso:country":"IT",
    "sg:address":"06059 Todi",
    "sg:city":"Todi",
    "sg:orig_category":"Persiane Ed Avvolgibili",
    "sg:phone":"+39 075 898 7339",
    "sg:postcode":"06059",
    "sg:province":"Perugia",
    "wof:name":"A.p.i.a.f. Snc",
    "wof:placetype":"venue"
},
  "geometry": {"coordinates":[11.9423513412,43.0714073181],"type":"Point"}
}