{
  "type": "Feature",
  "properties": {
    "addr:full":"10078 Venaria Torino 10078",
    "addr:postcode":"10078;10078",
    "iso:country":"IT",
    "sg:address":"10078 Venaria",
    "sg:orig_category":"Motocicli E Motocarri Accessori E Parti - Vendita Al Dettaglio",
    "sg:phone":"+39 011 452 7462",
    "sg:postcode":"10078",
    "sg:province":"Torino",
    "wof:name":"M.a.r.v. Di Taramino & C. Sas",
    "wof:placetype":"venue"
},
  "geometry": {"coordinates":[7.634806633,45.129070282],"type":"Point"}
}