{
  "type": "Feature",
  "properties": {
    "iso:country":"IT",
    "sg:address":"36071 Arzignano",
    "sg:city":"Arzignano",
    "sg:orig_category":"Calzature, Pelletterie E Pelli",
    "sg:phone":"+39 0444 452446",
    "sg:postcode":"36071",
    "sg:province":"Vicenza",
    "wof:name":"Abipel Di Rancan Ada",
    "wof:placetype":"venue"
},
  "geometry": {"coordinates":[11.316156,45.528141],"type":"Point"}
}