{
  "type": "Feature",
  "properties": {
    "iso:country":"IT",
    "sg:address":"90124 Palermo",
    "sg:city":"Palermo",
    "sg:orig_category":"Impianti, Attrezzature E Forniture Sanitarie Ed Ospedaliere",
    "sg:phone":"+39 091 441260",
    "sg:postcode":"90124",
    "sg:province":"Palermo",
    "wof:name":"Imperato Francesco E Figli Snc",
    "wof:placetype":"venue"
},
  "geometry": {"coordinates":[13.332105,38.119705],"type":"Point"}
}