{
  "type": "Feature",
  "properties": {
    "iso:country":"IT",
    "sg:address":"80048 Sant'anastasia",
    "sg:orig_category":"Servizi E Lavori Per Agricoltura E Zootecnia. Servizi E Lavori Per Edilizia E Lavori Pubblici",
    "sg:phone":"+39 081 897 2900",
    "sg:postcode":"80048",
    "sg:province":"Napoli",
    "sg:website":"http://www.afservizi.it",
    "wof:name":"Af Servizi",
    "wof:placetype":"venue"
},
  "geometry": {"coordinates":[14.389875,40.865025],"type":"Point"}
}