{
  "type": "Feature",
  "properties": {
    "iso:country":"IT",
    "sg:address":"23889 Santa Maria Hoe'",
    "sg:orig_category":"Arredi Ed Attrezzature Per Attivita' Commerciali Ed Artigianali",
    "sg:phone":"+39 039 531 2272",
    "sg:postcode":"23889",
    "sg:province":"Lecco",
    "wof:name":"Expo Srl",
    "wof:placetype":"venue"
},
  "geometry": {"coordinates":[9.330031,45.748985],"type":"Point"}
}