{
  "type": "Feature",
  "properties": {
    "iso:country":"IT",
    "sg:address":"70126 Bari",
    "sg:city":"Bari",
    "sg:orig_category":"Automobili - Commercio",
    "sg:phone":"+39 080 549 1055",
    "sg:postcode":"70126",
    "sg:province":"Bari",
    "sg:website":"http://www.autosanmarco.it",
    "wof:name":"Auto San Marco Srl",
    "wof:placetype":"venue"
},
  "geometry": {"coordinates":[16.761116,40.887756],"type":"Point"}
}