{
  "type": "Feature",
  "properties": {
    "iso:country":"IT",
    "sg:address":"47900 Rimini",
    "sg:city":"Rimini",
    "sg:orig_category":"Abbigliamento Esterno, Maglierie E Pelliccerie. Servizi E Lavori Per Abbigliamento E Pelletterie",
    "sg:phone":"+39 0541 78259",
    "sg:postcode":"47900",
    "sg:province":"Rimini",
    "wof:name":"D.s. Di Serafini Guerrino & C. Snc",
    "wof:placetype":"venue"
},
  "geometry": {"coordinates":[12.552751,44.026459],"type":"Point"}
}