{
  "type": "Feature",
  "properties": {
    "iso:country":"IT",
    "sg:address":"21020 Casale Litta",
    "sg:city":"Casale Litta",
    "sg:orig_category":"Termotecnica E Riscaldamento, Apparecchiature E Servizi",
    "sg:phone":"+39 0332 948070",
    "sg:postcode":"21020",
    "sg:province":"Varese",
    "wof:name":"Bruciatori Helios",
    "wof:placetype":"venue"
},
  "geometry": {"coordinates":[8.732264,45.779449],"type":"Point"}
}