{
  "type": "Feature",
  "properties": {
    "iso:country":"IT",
    "sg:address":"Belgioioso, Pv",
    "sg:classifiers":[
        {
            "category":"Banks & Credit Unions",
            "subcategory":"Bank",
            "type":"Services"
        }
    ],
    "wof:name":"Swift La Hulpe (belgio)",
    "wof:placetype":"venue"
},
  "geometry": {"coordinates":[9.314816,45.159534],"type":"Point"}
}