{
  "type": "Feature",
  "properties": {
    "iso:country":"IT",
    "sg:address":"80121 Napoli",
    "sg:city":"Napoli",
    "sg:orig_category":"Tessuti E Stoffe",
    "sg:phone":"+39 081 414524",
    "sg:postcode":"80121",
    "sg:province":"Napoli",
    "wof:name":"Errico Mario & Carlo Snc",
    "wof:placetype":"venue"
},
  "geometry": {"coordinates":[14.206745,40.906376],"type":"Point"}
}