{
  "type": "Feature",
  "properties": {
    "addr:full":"Via F. Cavallotti 3/n; Genova",
    "addr:housenumber":"3 / n",
    "addr:street":"Via F. Cavallotti",
    "iso:country":"IT",
    "sg:address":"Via F. Cavallotti 3/n; Genova",
    "sg:classifiers":[
        {
            "category":"Banks & Credit Unions",
            "subcategory":"Bank",
            "type":"Services"
        }
    ],
    "sg:phone":"+39 010 377 4647",
    "wof:name":"Banca Di Roma",
    "wof:placetype":"venue"
},
  "geometry": {"coordinates":[8.974902,44.392757],"type":"Point"}
}