{
  "type": "Feature",
  "properties": {
    "iso:country":"IT",
    "sg:address":"34, Via Torino 22079 Villa Guardia",
    "sg:city":"Villa Guardia",
    "sg:classifiers":[
        {
            "category":"Professional",
            "subcategory":"Engineering",
            "type":"Services"
        }
    ],
    "sg:phone":"+39 39031481248",
    "sg:postcode":"22079",
    "sg:province":"Como",
    "sg:tags":[
        "machine",
        "-",
        "mechanical"
    ],
    "wof:name":"M.t.l. Meccanica Tessile Lariana (s.r.l.)",
    "wof:placetype":"venue"
},
  "geometry": {"coordinates":[9.025271,45.765457],"type":"Point"}
}