{
  "type": "Feature",
  "properties": {
    "iso:country":"IT",
    "sg:address":"30174 Mestre",
    "sg:city":"Mestre",
    "sg:orig_category":"Ricambi E Componenti Dei Mezzi Di Trasporto",
    "sg:phone":"+39 041 943149",
    "sg:postcode":"30174",
    "sg:province":"Venezia",
    "wof:name":"Pesce Severino",
    "wof:placetype":"venue"
},
  "geometry": {"coordinates":[12.238779068,45.5287208557],"type":"Point"}
}