{
  "type": "Feature",
  "properties": {
    "addr:full":"84033 Montesano Sulla Marcellana Montesano sulla Marcellana Salerno 84033",
    "addr:housenumber":"sulla marcellana",
    "addr:postcode":"84033;84033",
    "addr:street":"Salerno",
    "iso:country":"IT",
    "sg:address":"84033 Montesano Sulla Marcellana",
    "sg:city":"Montesano sulla Marcellana",
    "sg:orig_category":"Studi E Consulenze Tecniche E Industriali. Servizi E Lavori Per Edilizia E Lavori Pubblici. Professionisti - Studi E Servizi Ed Associazioni Di Interesse Aziendale",
    "sg:phone":"+39 0975 863410",
    "sg:postcode":"84033",
    "sg:province":"Salerno",
    "wof:name":"Teknoglass Di Maniglia Francesco",
    "wof:placetype":"venue"
},
  "geometry": {"coordinates":[15.723381,40.270275],"type":"Point"}
}