{
  "type": "Feature",
  "properties": {
    "iso:country":"IT",
    "sg:address":"62010 Trodica Di Morrovalle",
    "sg:city":"Morrovalle",
    "sg:orig_category":"Macchine Per Cucire - Commercio E Riparazione",
    "sg:phone":"+39 0733 865808",
    "sg:postcode":"62010",
    "sg:province":"Macerata",
    "wof:name":"B.n.f. Di Bonifazi Sergio",
    "wof:placetype":"venue"
},
  "geometry": {"coordinates":[13.589556,43.31752],"type":"Point"}
}