{
  "type": "Feature",
  "properties": {
    "addr:full":"20047 Brugherio Brugherio Milano 20047",
    "addr:postcode":"20047;20047",
    "iso:country":"IT",
    "sg:address":"20047 Brugherio",
    "sg:city":"Brugherio",
    "sg:orig_category":"Elettrodomestici - Riparazione E Vendita Al Dettaglio Di Accessori",
    "sg:phone":"+39 039 208 6806",
    "sg:postcode":"20047",
    "sg:province":"Milano",
    "sg:website":"http://www.candy.it",
    "wof:name":"Gias Srl",
    "wof:placetype":"venue"
},
  "geometry": {"coordinates":[9.170137,45.449856],"type":"Point"}
}