{
  "type": "Feature",
  "properties": {
    "iso:country":"IT",
    "sg:address":"20094 Corsico",
    "sg:city":"Corsico",
    "sg:orig_category":"Professionisti - Studi E Servizi Ed Associazioni Di Interesse Aziendale. Associazioni Ed Organismi Di Interesse Pubblico",
    "sg:phone":"+39 02 440 0966",
    "sg:postcode":"20094",
    "sg:province":"Milano",
    "wof:name":"Club Forza Italia - Corsico",
    "wof:placetype":"venue"
},
  "geometry": {"coordinates":[9.1094150543,45.4391822815],"type":"Point"}
}