{
  "type": "Feature",
  "properties": {
    "iso:country":"IT",
    "sg:address":"09122 Cagliari",
    "sg:city":"Cagliari",
    "sg:orig_category":"Forniture Per Agricoltura E Zootecnia",
    "sg:phone":"+39 070 283396",
    "sg:postcode":"09122",
    "sg:province":"Cagliari",
    "wof:name":"Commerciale Agricola Sarda Di Lanzi Angelo & C. Sas",
    "wof:placetype":"venue"
},
  "geometry": {"coordinates":[9.0997571945,39.2276992798],"type":"Point"}
}