{
  "type": "Feature",
  "properties": {
    "addr:full":"06038 Spello Spello Perugia 06038",
    "addr:postcode":"06038;06038",
    "iso:country":"IT",
    "sg:address":"06038 Spello",
    "sg:city":"Spello",
    "sg:orig_category":"Tessuti E Stoffe",
    "sg:phone":"+39 0742 301557",
    "sg:postcode":"06038",
    "sg:province":"Perugia",
    "wof:name":"Palini Fratelli Snc",
    "wof:placetype":"venue"
},
  "geometry": {"coordinates":[12.656072,43.00119],"type":"Point"}
}