{
  "type": "Feature",
  "properties": {
    "iso:country":"IT",
    "sg:address":"36061 Bassano Del Grappa",
    "sg:city":"Bassano del Grappa",
    "sg:orig_category":"Zootecnia E Pesca, Allevamento Piccoli Animali. Animali Domestici",
    "sg:phone":"+39 0424 525098",
    "sg:postcode":"36061",
    "sg:province":"Vicenza",
    "wof:name":"Mondo Di Miki Snc",
    "wof:placetype":"venue"
},
  "geometry": {"coordinates":[11.730305,45.767864],"type":"Point"}
}