{
  "type": "Feature",
  "properties": {
    "iso:country":"IT",
    "sg:address":"47828 Santarcangelo Di Romagna",
    "sg:orig_category":"Lavorazioni Metalli, Stampaggio E Saldatura",
    "sg:phone":"+39 0541 750898",
    "sg:province":"RN",
    "wof:name":"Italmec Snc Di Zammarchi Gilberto & C.",
    "wof:placetype":"venue"
},
  "geometry": {"coordinates":[12.478151,44.035568],"type":"Point"}
}