{
  "type": "Feature",
  "properties": {
    "iso:country":"IT",
    "sg:address":"Via Calcinate 5 21026 Gavirate",
    "sg:city":"Gavirate",
    "sg:classifiers":[
        {
            "category":"Home & Garden",
            "subcategory":"Furniture",
            "type":"Retail Goods"
        }
    ],
    "sg:phone":"+39 0332 743777",
    "sg:postcode":"21026",
    "sg:province":"Varese",
    "sg:website":"www.rodaonline.com",
    "wof:name":"Roda S.r.l.",
    "wof:placetype":"venue"
},
  "geometry": {"coordinates":[8.748707,45.821995],"type":"Point"}
}