{
  "type": "Feature",
  "properties": {
    "iso:country":"IT",
    "sg:address":"4, Via Siepe Nuova 80027 Frattamaggiore",
    "sg:city":"Frattamaggiore",
    "sg:classifiers":[
        {
            "category":"Professional",
            "subcategory":"Engineering",
            "type":"Services"
        }
    ],
    "sg:phone":"+39 081 880 1448",
    "sg:postcode":"80027",
    "sg:province":"Napoli",
    "sg:tags":[
        "machine",
        "-",
        "mechanical"
    ],
    "wof:name":"Ecolwater Di D'errico Anna & C. Sas",
    "wof:placetype":"venue"
},
  "geometry": {"coordinates":[14.275707,40.930809],"type":"Point"}
}