{
  "type": "Feature",
  "properties": {
    "iso:country":"IT",
    "sg:address":"Via Tosco Romagnola Est, 8/12 56020 San Romano",
    "sg:city":"San Romano",
    "sg:orig_category":"Ladies' Shoes",
    "sg:phone":"+39 0571 467680",
    "sg:postcode":"56020",
    "sg:province":"Pisa",
    "sg:website":"www.simonettarossi.com",
    "wof:name":"Sobucal S.r.l.",
    "wof:placetype":"venue"
},
  "geometry": {"coordinates":[10.396585,43.716137],"type":"Point"}
}