{
  "type": "Feature",
  "properties": {
    "iso:country":"IT",
    "sg:address":"39010 San Pancrazio",
    "sg:city":"San Pancrazio",
    "sg:orig_category":"Pubblica Amministrazione",
    "sg:phone":"+39 0473 787441",
    "sg:postcode":"39010",
    "sg:province":"Bolzano/Bozen",
    "wof:name":"Foerderungsgenossenschaft Ulten G.m.b.h.",
    "wof:placetype":"venue"
},
  "geometry": {"coordinates":[11.0873699188,46.5862770081],"type":"Point"}
}