{
  "type": "Feature",
  "properties": {
    "iso:country":"IT",
    "sg:address":"36050 Bressanvido",
    "sg:city":"Bressanvido",
    "sg:orig_category":"Servizi E Lavori Per Abbigliamento E Pelletterie. Cartotecnica E Servizi. Servizi E Lavori Industria Delle Materie Plastiche",
    "sg:phone":"+39 0444 460186",
    "sg:postcode":"36050",
    "sg:province":"Vicenza",
    "wof:name":"Ad. Tech. S.r.l",
    "wof:placetype":"venue"
},
  "geometry": {"coordinates":[11.648227,45.650536],"type":"Point"}
}