{
  "type": "Feature",
  "properties": {
    "addr:full":"6, Via Lecco 20124 Milano Milano Milano 20124",
    "addr:postcode":"20124;20124",
    "addr:street":"Via Lecco",
    "iso:country":"IT",
    "sg:address":"6, Via Lecco 20124 Milano",
    "sg:city":"Milano",
    "sg:classifiers":[
        {
            "category":"Wholesale",
            "subcategory":"Drugs",
            "type":"Manufacturing & Wholesale Goods"
        }
    ],
    "sg:phone":"+39 02 2952 4653",
    "sg:postcode":"20124",
    "sg:province":"Milano",
    "sg:tags":[
        "chemical",
        "pharmaceutical"
    ],
    "wof:name":"Afroriental Trade Center (s.r.l.)",
    "wof:placetype":"venue"
},
  "geometry": {"coordinates":[9.2039,45.476471],"type":"Point"}
}