{
  "type": "Feature",
  "properties": {
    "iso:country":"IT",
    "sg:address":"20090 Pantigliate",
    "sg:city":"Pantigliate",
    "sg:orig_category":"Non-classified Establishments",
    "sg:phone":"+39 02 906 7043",
    "sg:postcode":"20090",
    "sg:province":"Milano",
    "sg:website":"http://www.bertolesi.it",
    "wof:name":"Bertolesi Fratelli Srl",
    "wof:placetype":"venue"
},
  "geometry": {"coordinates":[9.334264,45.471645],"type":"Point"}
}