{
  "type": "Feature",
  "properties": {
    "iso:country":"IT",
    "sg:address":"Via Dismano 5819 47023 Cesena",
    "sg:city":"Cesena",
    "sg:classifiers":[
        {
            "category":"Banks & Credit Unions",
            "subcategory":"Investment Brokerage",
            "type":"Services"
        }
    ],
    "sg:phone":"+39 0547 319311",
    "sg:postcode":"47023",
    "sg:province":"Forl\u00ec-Cesena",
    "sg:tags":[
        "hole",
        "drilling",
        "deep"
    ],
    "sg:website":"www.trevispa.com",
    "wof:name":"Trevi Spa",
    "wof:placetype":"venue"
},
  "geometry": {"coordinates":[12.2179,44.182991],"type":"Point"}
}