{
  "type": "Feature",
  "properties": {
    "iso:country":"IT",
    "sg:address":"36015 Schio",
    "sg:city":"Schio",
    "sg:orig_category":"Musica",
    "sg:phone":"+39 0445 577350",
    "sg:postcode":"36015",
    "sg:province":"Vicenza",
    "wof:name":"Mc Service Srl",
    "wof:placetype":"venue"
},
  "geometry": {"coordinates":[11.5466823578,45.5719909668],"type":"Point"}
}