{
  "type": "Feature",
  "properties": {
    "addr:full":"Via Fiume 6 21054 Fagnano Olona Fagnano Olona Varese 21054",
    "addr:housenumber":"6",
    "addr:postcode":"21054;21054",
    "addr:street":"Via Fiume",
    "iso:country":"IT",
    "sg:address":"Via Fiume 6 21054 Fagnano Olona",
    "sg:city":"Fagnano Olona",
    "sg:orig_category":"Testing Equipment For Power Electronics",
    "sg:phone":"+39 0331 610102",
    "sg:postcode":"21054",
    "sg:province":"Varese",
    "sg:website":"www.servizitecnologici.it",
    "wof:name":"Servizi Tecnologici Di Bordoni Marco",
    "wof:placetype":"venue"
},
  "geometry": {"coordinates":[8.877222,45.667454],"type":"Point"}
}