{
  "type": "Feature",
  "properties": {
    "iso:country":"IT",
    "sg:address":"21100 Varese",
    "sg:city":"Varese",
    "sg:orig_category":"Ponteggi Per Edilizia",
    "sg:phone":"+39 0332 265097",
    "sg:postcode":"21100",
    "sg:province":"Varese",
    "wof:name":"Puglisi Salvatore",
    "wof:placetype":"venue"
},
  "geometry": {"coordinates":[8.8160705566,45.8321266174],"type":"Point"}
}