{
  "type": "Feature",
  "properties": {
    "iso:country":"IT",
    "sg:address":"5, Via Ceravolo 20090 Pieve Emanuele",
    "sg:city":"Pieve Emanuele",
    "sg:classifiers":[
        {
            "category":"Manufacturing",
            "subcategory":"Metals",
            "type":"Manufacturing & Wholesale Goods"
        }
    ],
    "sg:phone":"+39 02 9072 3801",
    "sg:postcode":"20090",
    "sg:province":"Milano",
    "sg:tags":[
        "processing"
    ],
    "wof:name":"O.m.a.s. (s.n.c.)",
    "wof:placetype":"venue"
},
  "geometry": {"coordinates":[9.1857509613,45.3708724976],"type":"Point"}
}