{
  "type": "Feature",
  "properties": {
    "addr:full":"33100 Udine Udine Udine 33100",
    "addr:postcode":"33100;33100",
    "iso:country":"IT",
    "sg:address":"33100 Udine",
    "sg:city":"Udine",
    "sg:orig_category":"Antifurto",
    "sg:phone":"+39 0432 602469",
    "sg:postcode":"33100",
    "sg:province":"Udine",
    "wof:name":"Italcontrol Telematica P.s.c.",
    "wof:placetype":"venue"
},
  "geometry": {"coordinates":[13.259665,46.026012],"type":"Point"}
}