{
  "type": "Feature",
  "properties": {
    "iso:country":"IT",
    "sg:address":"27, Via Dell' Uliveto 01039 Vignanello",
    "sg:city":"Vignanello",
    "sg:classifiers":[
        {
            "category":"Shopping",
            "subcategory":"Clothing, Apparel, & Fashions",
            "type":"Retail Goods"
        }
    ],
    "sg:phone":"+39 0761 755842",
    "sg:postcode":"01039",
    "sg:province":"Viterbo",
    "sg:tags":[
        "clothes"
    ],
    "wof:name":"Valex Snc Di Olivieri Antonio E Ceccarelli Amelio",
    "wof:placetype":"venue"
},
  "geometry": {"coordinates":[12.287077,42.387081],"type":"Point"}
}