{
  "type": "Feature",
  "properties": {
    "iso:country":"IT",
    "sg:address":"70124 Bari",
    "sg:city":"Bari",
    "sg:orig_category":"Vetro: Prodotti E Lavorazioni",
    "sg:phone":"+39 080 527 7895",
    "sg:postcode":"70124",
    "sg:province":"Bari",
    "wof:name":"Metalpuglia Snc Di Michele E Domenico Colangiuli",
    "wof:placetype":"venue"
},
  "geometry": {"coordinates":[16.887306,41.041389],"type":"Point"}
}