{
  "type": "Feature",
  "properties": {
    "addr:full":"35010 San Giorgio In Bosco San Giorgio in Bosco Padova 35010",
    "addr:housenumber":"35010",
    "addr:postcode":"in bosco;35010",
    "iso:country":"IT",
    "sg:address":"35010 San Giorgio In Bosco",
    "sg:city":"San Giorgio in Bosco",
    "sg:orig_category":"Adesivi",
    "sg:phone":"+39 049 945 0300",
    "sg:postcode":"35010",
    "sg:province":"Padova",
    "wof:name":"Testa & C. Srl",
    "wof:placetype":"venue"
},
  "geometry": {"coordinates":[11.806621,45.59063],"type":"Point"}
}