{
  "type": "Feature",
  "properties": {
    "iso:country":"IT",
    "sg:address":"23, C. Xxii Marzo 20129 Milano",
    "sg:city":"Milano",
    "sg:classifiers":[
        {
            "category":"Wholesale",
            "subcategory":"Drugs",
            "type":"Manufacturing & Wholesale Goods"
        }
    ],
    "sg:phone":"+39 02 7611 5246",
    "sg:postcode":"20129",
    "sg:province":"Milano",
    "sg:tags":[
        "chemical",
        "pharmaceutical"
    ],
    "sg:website":"http://www.paginegialle.it/farmaciaventrini",
    "wof:name":"Farmacia Ventrini",
    "wof:placetype":"venue"
},
  "geometry": {"coordinates":[9.212657,45.472752],"type":"Point"}
}