{
  "type": "Feature",
  "properties": {
    "iso:country":"IT",
    "sg:address":"56124 Pisa",
    "sg:city":"Pisa",
    "sg:orig_category":"Agenzie Viaggi E Turismo",
    "sg:phone":"+39 050 544521",
    "sg:postcode":"56124",
    "sg:province":"Pisa",
    "wof:name":"Co.pi.sa. Soc.coop.r.l.",
    "wof:placetype":"venue"
},
  "geometry": {"coordinates":[10.410302,43.711357],"type":"Point"}
}