{
  "type": "Feature",
  "properties": {
    "iso:country":"IT",
    "sg:address":"10144 Torino",
    "sg:city":"Torino",
    "sg:orig_category":"Abbigliamento Intimo, Calze E Costumi Da Bagno. Shopping",
    "sg:phone":"+39 011 480997",
    "sg:postcode":"10144",
    "sg:province":"Torino",
    "wof:name":"Elda Elegance Intime Di Possetti Lucia & C. Sas",
    "wof:placetype":"venue"
},
  "geometry": {"coordinates":[7.665386,45.082153],"type":"Point"}
}