{
  "type": "Feature",
  "properties": {
    "iso:country":"IT",
    "sg:address":"17, Via Segavecchia 36055 Nove",
    "sg:city":"Nove",
    "sg:classifiers":[
        {
            "category":"Shopping",
            "subcategory":"Crafts & Fabrics",
            "type":"Retail Goods"
        }
    ],
    "sg:phone":"+39 0424 590106",
    "sg:postcode":"36055",
    "sg:province":"Vicenza",
    "sg:tags":[
        "ceramic"
    ],
    "wof:name":"Ahura Per L'arredamento Di Zanardello Ezio Antonio",
    "wof:placetype":"venue"
},
  "geometry": {"coordinates":[11.681607,45.717442],"type":"Point"}
}