{
  "type": "Feature",
  "properties": {
    "addr:full":"26, Via Serassi Carlo 24124 Bergamo Bergamo Bergamo 24124",
    "addr:postcode":"24124;24124",
    "addr:street":"Via Serassi Carlo",
    "iso:country":"IT",
    "sg:address":"26, Via Serassi Carlo 24124 Bergamo",
    "sg:city":"Bergamo",
    "sg:classifiers":[
        {
            "category":"Real Estate",
            "subcategory":"Surveying",
            "type":"Services"
        }
    ],
    "sg:phone":"+39 39035344096",
    "sg:postcode":"24124",
    "sg:province":"Bergamo",
    "sg:tags":[
        "equipment",
        "material",
        "good",
        "-",
        "handling"
    ],
    "wof:name":"Tecnomeccanica Zurcher Spa",
    "wof:placetype":"venue"
},
  "geometry": {"coordinates":[9.669952,45.694904],"type":"Point"}
}