{
  "type": "Feature",
  "properties": {
    "addr:full":"10, Via Palustela 38010 Romeno Romeno Trento 38010",
    "addr:postcode":"38010;38010",
    "addr:street":"Via Palustela",
    "iso:country":"IT",
    "sg:address":"10, Via Palustela 38010 Romeno",
    "sg:city":"Romeno",
    "sg:classifiers":[
        {
            "category":"Professional",
            "subcategory":"Engineering",
            "type":"Services"
        }
    ],
    "sg:phone":"+39 0463 875300",
    "sg:postcode":"38010",
    "sg:province":"Trento",
    "sg:tags":[
        "machine",
        "-",
        "mechanical"
    ],
    "wof:name":"Meccanica Zucal F.lli (s.n.c.)",
    "wof:placetype":"venue"
},
  "geometry": {"coordinates":[11.11531,46.395424],"type":"Point"}
}