{
  "type": "Feature",
  "properties": {
    "iso:country":"IT",
    "sg:address":"24030 Mapello",
    "sg:city":"Mapello",
    "sg:orig_category":"Materiali Semilavorati Metallici",
    "sg:phone":"+39 035 494 5833",
    "sg:postcode":"24030",
    "sg:province":"Bergamo",
    "wof:name":"Siderbergamo Srl",
    "wof:placetype":"venue"
},
  "geometry": {"coordinates":[9.547851,45.708855],"type":"Point"}
}