{
  "type": "Feature",
  "properties": {
    "iso:country":"IT",
    "sg:address":"21019 Somma Lombardo",
    "sg:city":"Somma Lombardo",
    "sg:orig_category":"Articoli Da Regalo. Forniture Per Attivita' Commerciali Ed Artigianali",
    "sg:phone":"+39 0331 256718",
    "sg:postcode":"21019",
    "sg:province":"Varese",
    "wof:name":"Gattoni Antonio",
    "wof:placetype":"venue"
},
  "geometry": {"coordinates":[8.705768,45.683064],"type":"Point"}
}