{
  "type": "Feature",
  "properties": {
    "addr:full":"56025 Pontedera Pontedera Pisa 56025",
    "addr:postcode":"56025;56025",
    "iso:country":"IT",
    "sg:address":"56025 Pontedera",
    "sg:city":"Pontedera",
    "sg:orig_category":"Motori Ed Organi Di Trasmissione. Ricambi E Componenti Dei Mezzi Di Trasporto",
    "sg:phone":"+39 0587 290614",
    "sg:postcode":"56025",
    "sg:province":"Pisa",
    "wof:name":"Egidio Massei Sas Di Massei Giovanni & C.",
    "wof:placetype":"venue"
},
  "geometry": {"coordinates":[10.5931930542,43.6333618164],"type":"Point"}
}