{
  "type": "Feature",
  "properties": {
    "addr:full":"2, Via Quargnasco 13854 Quaregna Quaregna Biella 13854",
    "addr:postcode":"13854;13854",
    "addr:street":"Via Quargnasco",
    "iso:country":"IT",
    "sg:address":"2, Via Quargnasco 13854 Quaregna",
    "sg:city":"Quaregna",
    "sg:classifiers":[
        {
            "category":"Shopping",
            "subcategory":"Crafts & Fabrics",
            "type":"Retail Goods"
        }
    ],
    "sg:phone":"+39 390 159 3698",
    "sg:postcode":"13854",
    "sg:province":"Biella",
    "wof:name":"Filatura Quargnasca (s.r.l.)",
    "wof:placetype":"venue"
},
  "geometry": {"coordinates":[8.1676959991,45.5840568542],"type":"Point"}
}