{
  "type": "Feature",
  "properties": {
    "iso:country":"IT",
    "sg:address":"27039 Sannazzaro De'burgondi",
    "sg:orig_category":"Elettrotecnica Industriale, Prodotti E Apparecchiature. Elettronica Industriale, Prodotti E Apparecchiature",
    "sg:phone":"+39 0382 901026",
    "sg:postcode":"27039",
    "sg:province":"Pavia",
    "wof:name":"Impes - Costruzioni Termotecniche Snc",
    "wof:placetype":"venue"
},
  "geometry": {"coordinates":[8.907419,45.095551],"type":"Point"}
}