{
  "type": "Feature",
  "properties": {
    "iso:country":"IT",
    "sg:address":"40069 Zola Predosa",
    "sg:city":"Zola",
    "sg:orig_category":"Abbigliamento Intimo, Calze E Costumi Da Bagno",
    "sg:phone":"+39 051 754335",
    "sg:postcode":"40069",
    "sg:province":"Bologna",
    "wof:name":"Biotecnica Srl",
    "wof:placetype":"venue"
},
  "geometry": {"coordinates":[11.248984,44.493778],"type":"Point"}
}