{
  "type": "Feature",
  "properties": {
    "iso:country":"IT",
    "sg:address":"Via Palianese Sud 03018 Paliano",
    "sg:city":"Paliano",
    "sg:classifiers":[
        {
            "category":"Home & Garden",
            "subcategory":"Home Furnishings",
            "type":"Retail Goods"
        }
    ],
    "sg:phone":"+39 0775 533121",
    "sg:postcode":"03018",
    "sg:province":"Frosinone",
    "sg:tags":[
        "household"
    ],
    "wof:name":"S.i.a.t.a. Spa",
    "wof:placetype":"venue"
},
  "geometry": {"coordinates":[13.026159,41.78907],"type":"Point"}
}