{
  "type": "Feature",
  "properties": {
    "iso:country":"IT",
    "sg:address":"24067 Sarnico",
    "sg:city":"Sarnico",
    "sg:orig_category":"Hobbistica",
    "sg:phone":"+39 035 912165",
    "sg:postcode":"24067",
    "sg:province":"Bergamo",
    "wof:name":"De Grandi Alessandra",
    "wof:placetype":"venue"
},
  "geometry": {"coordinates":[9.956317,45.667278],"type":"Point"}
}