{
  "type": "Feature",
  "properties": {
    "iso:country":"IT",
    "sg:address":"14, Via Scarpetta Edoardo 00128 Roma",
    "sg:city":"Roma",
    "sg:classifiers":[
        {
            "category":"Autos & Motor Vehicles",
            "subcategory":"Automobile Sales",
            "type":"Retail Goods"
        }
    ],
    "sg:phone":"+39 39065087228",
    "sg:postcode":"00128",
    "sg:province":"Roma",
    "sg:tags":[
        "motor-cars"
    ],
    "wof:name":"Articar (s.r.l.)",
    "wof:placetype":"venue"
},
  "geometry": {"coordinates":[12.4548330307,41.7940940857],"type":"Point"}
}