{
  "type": "Feature",
  "properties": {
    "addr:full":"03035 Fontana Liri Fontana Liri Frosinone 03035",
    "addr:housenumber":"03035",
    "addr:postcode":"03035",
    "addr:street":"Liri",
    "iso:country":"IT",
    "sg:address":"03035 Fontana Liri",
    "sg:city":"Fontana Liri",
    "sg:orig_category":"Servizi Per Lo Sport E Il Tempo Libero. Ristoranti Ed Esercizi Affini. Servizi Ausiliari Di Ristorazione E Di Intrattenimento",
    "sg:phone":"+39 0776 525549",
    "sg:postcode":"03035",
    "sg:province":"Frosinone",
    "wof:name":"Easy Life Soc. Activa",
    "wof:placetype":"venue"
},
  "geometry": {"coordinates":[13.142518,41.742039],"type":"Point"}
}