{
  "type": "Feature",
  "properties": {
    "addr:full":"57123 Livorno Livorno Livorno 57123",
    "addr:postcode":"57123;57123",
    "iso:country":"IT",
    "sg:address":"57123 Livorno",
    "sg:city":"Livorno",
    "sg:orig_category":"Servizi Ausiliari Per Il Trasporto",
    "sg:phone":"+39 0586 219076",
    "sg:postcode":"57123",
    "sg:province":"Livorno",
    "wof:name":"Gest-navi S.r.l.",
    "wof:placetype":"venue"
},
  "geometry": {"coordinates":[10.310501,43.577747],"type":"Point"}
}