{
  "type": "Feature",
  "properties": {
    "addr:full":"24050 Cavernago Cavernago Bergamo 24050",
    "addr:postcode":"24050;24050",
    "iso:country":"IT",
    "sg:address":"24050 Cavernago",
    "sg:city":"Cavernago",
    "sg:orig_category":"Alberghi",
    "sg:phone":"+39 035 840266",
    "sg:postcode":"24050",
    "sg:province":"Bergamo",
    "sg:website":"http://www.hotelgiordano.it",
    "wof:name":"Albergo Giordano Di Re Giovanna E Figli Snc",
    "wof:placetype":"venue"
},
  "geometry": {"coordinates":[9.722903,45.654636],"type":"Point"}
}