{
  "type": "Feature",
  "properties": {
    "addr:full":"Via Dei Lavoratori 20080 Calvignasco Calvignasco Milano 20080",
    "addr:postcode":"20080;20080",
    "addr:street":"Via Dei Lavoratori",
    "iso:country":"IT",
    "sg:address":"Via Dei Lavoratori 20080 Calvignasco",
    "sg:city":"Calvignasco",
    "sg:classifiers":[
        {
            "category":"Manufacturing",
            "subcategory":"Metals",
            "type":"Manufacturing & Wholesale Goods"
        }
    ],
    "sg:phone":"+39 02 9005 9258",
    "sg:postcode":"20080",
    "sg:province":"Milano",
    "sg:tags":[
        "metallurgy",
        "metalworking"
    ],
    "wof:name":"Societa' Italiana Raccordi Tubi Tiranti Spa",
    "wof:placetype":"venue"
},
  "geometry": {"coordinates":[9.028924942,45.3190040588],"type":"Point"}
}