{
  "type": "Feature",
  "properties": {
    "iso:country":"IT",
    "sg:address":"51100 Pistoia",
    "sg:city":"Pistoia",
    "sg:orig_category":"Ospedali E Servizi Sanitari",
    "sg:phone":"+39 0573 367275",
    "sg:postcode":"51100",
    "sg:province":"Pistoia",
    "wof:name":"Carta Mario",
    "wof:placetype":"venue"
},
  "geometry": {"coordinates":[10.913455,43.934925],"type":"Point"}
}