{
  "type": "Feature",
  "properties": {
    "iso:country":"IT",
    "sg:address":"12, Via Fermi Enrico 31048 San Biagio Di Callalta",
    "sg:city":"San Biagio di Callalta",
    "sg:classifiers":[
        {
            "category":"Manufacturing",
            "subcategory":"Rubber & Plastics",
            "type":"Manufacturing & Wholesale Goods"
        }
    ],
    "sg:phone":"+39 0422 792111",
    "sg:postcode":"31048",
    "sg:province":"Treviso",
    "wof:name":"O.r.t. Industria S.r.l.",
    "wof:placetype":"venue"
},
  "geometry": {"coordinates":[12.2919864655,45.6940422058],"type":"Point"}
}