{
  "type": "Feature",
  "properties": {
    "iso:country":"IT",
    "sg:address":"20135 Milano",
    "sg:city":"Milano",
    "sg:orig_category":"Non-classified Establishments",
    "sg:phone":"+39 02 5832 0338",
    "sg:postcode":"20135",
    "sg:province":"Milano",
    "wof:name":"Coltellerie Italiane Zoppis",
    "wof:placetype":"venue"
},
  "geometry": {"coordinates":[9.198786,45.45092],"type":"Point"}
}