{
  "type": "Feature",
  "properties": {
    "iso:country":"IT",
    "sg:address":"51031 Agliana",
    "sg:city":"Agliana",
    "sg:orig_category":"Ristorazione E Locali Pubblici Affini. Ristoranti Ed Esercizi Affini",
    "sg:phone":"+39 0574 675252",
    "sg:postcode":"51031",
    "sg:province":"Pistoia",
    "wof:name":"Orchidea Sas",
    "wof:placetype":"venue"
},
  "geometry": {"coordinates":[10.997658,43.892128],"type":"Point"}
}