{
  "type": "Feature",
  "properties": {
    "iso:country":"IT",
    "sg:address":"10141 Torino",
    "sg:city":"Torino",
    "sg:orig_category":"Servizi E Lavori Per Ecologia E Smaltimento Rifiuti. Macchine E Forniture Per Ecologia E Smaltimento Rifiuti",
    "sg:phone":"+39 011 386498",
    "sg:postcode":"10141",
    "sg:province":"Torino",
    "wof:name":"Ditta M8",
    "wof:placetype":"venue"
},
  "geometry": {"coordinates":[7.64962,45.056835],"type":"Point"}
}