{
  "type": "Feature",
  "properties": {
    "iso:country":"IT",
    "sg:address":"3, Via Giusso G. 80069 Vico Equense",
    "sg:city":"Vico Equense",
    "sg:classifiers":[
        {
            "category":"Wholesale",
            "subcategory":"Machinery & Supplies",
            "type":"Manufacturing & Wholesale Goods"
        }
    ],
    "sg:phone":"+39 081 801 5940",
    "sg:postcode":"80069",
    "sg:province":"Napoli",
    "sg:tags":[
        "equipment",
        "precision"
    ],
    "wof:name":"Lasit Srl",
    "wof:placetype":"venue"
},
  "geometry": {"coordinates":[14.2516355515,40.84009552],"type":"Point"}
}