{
  "type": "Feature",
  "properties": {
    "addr:full":"40129 Bologna Bologna Bologna 40129",
    "addr:postcode":"40129;40129",
    "iso:country":"IT",
    "sg:address":"40129 Bologna",
    "sg:city":"Bologna",
    "sg:orig_category":"Apparecchiature Ed Attrezzature Meccaniche",
    "sg:phone":"+39 051 418 7061",
    "sg:postcode":"40129",
    "sg:province":"Bologna",
    "wof:name":"Tecno Parts Spa",
    "wof:placetype":"venue"
},
  "geometry": {"coordinates":[11.350598,44.537769],"type":"Point"}
}