{
  "type": "Feature",
  "properties": {
    "addr:full":"29, Corso Novara 10078 Venaria Torino 10078",
    "addr:postcode":"10078;10078",
    "addr:street":"Corso Novara",
    "iso:country":"IT",
    "sg:address":"29, Corso Novara 10078 Venaria",
    "sg:classifiers":[
        {
            "category":"Professional",
            "subcategory":"Engineering",
            "type":"Services"
        }
    ],
    "sg:phone":"+39 011 424 6574",
    "sg:postcode":"10078",
    "sg:province":"Torino",
    "sg:tags":[
        "machine",
        "-",
        "mechanical"
    ],
    "wof:name":"Vernettiblina Di Vittorio E Carla Vernetti Blina S",
    "wof:placetype":"venue"
},
  "geometry": {"coordinates":[7.633691,45.114265],"type":"Point"}
}