{
  "type": "Feature",
  "properties": {
    "iso:country":"IT",
    "sg:address":"37137 Verona",
    "sg:city":"Verona",
    "sg:orig_category":"Prodotti Di Base E Forniture Per Industria Alimentare E Bevande. Forniture Per Attivita' Commerciali Ed Artigianali",
    "sg:phone":"+39 045 953860",
    "sg:postcode":"37137",
    "sg:province":"Verona",
    "wof:name":"Idea Service Di Canali Marco",
    "wof:placetype":"venue"
},
  "geometry": {"coordinates":[10.9444417953,45.4154510498],"type":"Point"}
}