{
  "type": "Feature",
  "properties": {
    "addr:full":"21040 Castronno Castronno Varese 21040",
    "addr:postcode":"21040;21040",
    "iso:country":"IT",
    "sg:address":"21040 Castronno",
    "sg:city":"Castronno",
    "sg:orig_category":"Prodotti Chimici Di Base",
    "sg:phone":"+39 0332 893758",
    "sg:postcode":"21040",
    "sg:province":"Varese",
    "sg:website":"http://www.prodottichimiciprofessionali.com",
    "wof:name":"Arialdo Galizzi",
    "wof:placetype":"venue"
},
  "geometry": {"coordinates":[8.8570489883,45.7746162415],"type":"Point"}
}