{
  "type": "Feature",
  "properties": {
    "addr:full":"39011 Lana Lana Bolzano/Bozen 39011",
    "addr:postcode":"39011;39011",
    "iso:country":"IT",
    "sg:address":"39011 Lana",
    "sg:city":"Lana",
    "sg:classifiers":[
        {
            "category":"Home & Garden",
            "subcategory":"Hardware",
            "type":"Retail Goods"
        }
    ],
    "sg:phone":"+39 0473 563300",
    "sg:postcode":"39011",
    "sg:province":"Bolzano/Bozen",
    "wof:name":"Kunstdunger Sas - K.g.",
    "wof:placetype":"venue"
},
  "geometry": {"coordinates":[11.358005,46.496716],"type":"Point"}
}