{
  "type": "Feature",
  "properties": {
    "iso:country":"IT",
    "sg:address":"Via Caduti Liberta, 12; Verres; 11029",
    "sg:city":"Verres",
    "sg:classifiers":[
        {
            "category":"Banks & Credit Unions",
            "subcategory":"Bank",
            "type":"Services"
        }
    ],
    "sg:phone":"+39 0125 920452",
    "sg:postcode":"11029",
    "sg:province":"Aosta",
    "wof:name":"Cassa Di Risparmio Di Torino",
    "wof:placetype":"venue"
},
  "geometry": {"coordinates":[7.689778,45.668835],"type":"Point"}
}