{
  "type": "Feature",
  "properties": {
    "iso:country":"IT",
    "sg:address":"91010 San Vito Lo Capo",
    "sg:city":"San Vito Lo Capo",
    "sg:classifiers":[
        {
            "category":"Travel",
            "subcategory":"Hotels & Motels",
            "type":"Entertainment"
        }
    ],
    "sg:phone":"+39 0923 972444",
    "sg:postcode":"91010",
    "sg:province":"Trapani",
    "sg:tags":[
        "camping",
        "facility"
    ],
    "wof:name":"La Noria Srl",
    "wof:placetype":"venue"
},
  "geometry": {"coordinates":[12.733683,38.174973],"type":"Point"}
}