{
  "type": "Feature",
  "properties": {
    "iso:country":"IT",
    "sg:address":"22030 Montorfano",
    "sg:city":"Montorfano",
    "sg:orig_category":"Non-classified Establishments",
    "sg:phone":"+39 031 553307",
    "sg:postcode":"22030",
    "sg:province":"Como",
    "wof:name":"De Rossi Emilio",
    "wof:placetype":"venue"
},
  "geometry": {"coordinates":[9.164111,45.782799],"type":"Point"}
}