{
  "type": "Feature",
  "properties": {
    "iso:country":"IT",
    "sg:address":"30, Via Fermi Enrico Rovagnasco 20090 Segrate",
    "sg:city":"Segrate",
    "sg:classifiers":[
        {
            "category":"Manufacturing",
            "subcategory":"Lumber",
            "type":"Manufacturing & Wholesale Goods"
        }
    ],
    "sg:phone":"+39 39022138151",
    "sg:postcode":"20090",
    "sg:province":"Milano",
    "sg:tags":[
        "wood"
    ],
    "wof:name":"C.i.m.i (s.p.a.)",
    "wof:placetype":"venue"
},
  "geometry": {"coordinates":[9.274181,45.498203],"type":"Point"}
}