{
  "type": "Feature",
  "properties": {
    "iso:country":"IT",
    "sg:address":"40138 Bologna",
    "sg:city":"Bologna",
    "sg:orig_category":"Etichettatura E Marcatura - Macchine E Sistemi",
    "sg:phone":"+39 051 602 7812",
    "sg:postcode":"40138",
    "sg:province":"Bologna",
    "sg:website":"http://www.globalprintech.it",
    "wof:name":"Global Network Engineering",
    "wof:placetype":"venue"
},
  "geometry": {"coordinates":[11.399781,44.496574],"type":"Point"}
}