{
  "type": "Feature",
  "properties": {
    "iso:country":"IT",
    "sg:address":"Loc Faleri, Km 3,150 01034 Fabrica Di Roma",
    "sg:city":"Fabrica di Roma",
    "sg:classifiers":[
        {
            "category":"Home & Garden",
            "subcategory":"Building Materials",
            "type":"Retail Goods"
        }
    ],
    "sg:phone":"+39 0761 575032",
    "sg:postcode":"01034",
    "sg:province":"Viterbo",
    "sg:tags":[
        "plumbing",
        "ceramic",
        "fixture"
    ],
    "sg:website":"www.faleri.it",
    "wof:name":"Faleri Ceramica Sanitari Srl",
    "wof:placetype":"venue"
},
  "geometry": {"coordinates":[12.104854,42.417381],"type":"Point"}
}