{
  "type": "Feature",
  "properties": {
    "addr:full":"36055 Nove Nove Vicenza 36055",
    "addr:postcode":"36055;36055",
    "iso:country":"IT",
    "sg:address":"36055 Nove",
    "sg:city":"Nove",
    "sg:orig_category":"Macchine E Forniture Per Ecologia E Smaltimento Rifiuti",
    "sg:phone":"+39 0424 592304",
    "sg:postcode":"36055",
    "sg:province":"Vicenza",
    "wof:name":"Ept - Engineering & Consulting Srl",
    "wof:placetype":"venue"
},
  "geometry": {"coordinates":[11.677138,45.711964],"type":"Point"}
}