{
  "type": "Feature",
  "properties": {
    "iso:country":"IT",
    "sg:address":"Via Livelli 53 43010 Polesine Parmense",
    "sg:city":"Polesine Parmense",
    "sg:classifiers":[
        {
            "category":"Building & Trades",
            "subcategory":"Construction",
            "type":"Services"
        }
    ],
    "sg:phone":"+39 0524 96105",
    "sg:postcode":"43010",
    "sg:province":"Parma",
    "sg:tags":[
        "carpenter's",
        "work",
        "supraregional"
    ],
    "wof:name":"O.m.p. Srl",
    "wof:placetype":"venue"
},
  "geometry": {"coordinates":[10.084792,45.018429],"type":"Point"}
}