{
  "type": "Feature",
  "properties": {
    "addr:full":"46100 Mantova Mantova Mantova 46100",
    "addr:postcode":"46100;46100",
    "iso:country":"IT",
    "sg:address":"46100 Mantova",
    "sg:city":"Mantova",
    "sg:orig_category":"Materiali Edili",
    "sg:phone":"+39 0376 381065",
    "sg:postcode":"46100",
    "sg:province":"Mantova",
    "wof:name":"Morselli Dorino & C. Snc",
    "wof:placetype":"venue"
},
  "geometry": {"coordinates":[10.414703,45.222038],"type":"Point"}
}