{
  "type": "Feature",
  "properties": {
    "addr:full":"7, Via Caiani Pietro 50032 Borgo San Lorenzo Borgo San Lorenzo Firenze 50032",
    "addr:postcode":"50032;50032",
    "addr:street":"Via Caiani Pietro;San Lorenzo Borgo San Lorenzo",
    "iso:country":"IT",
    "sg:address":"7, Via Caiani Pietro 50032 Borgo San Lorenzo",
    "sg:city":"Borgo San Lorenzo",
    "sg:classifiers":[
        {
            "category":"Personal",
            "subcategory":"Shoe Repair & Shine",
            "type":"Services"
        }
    ],
    "sg:phone":"+39 055 845 8730",
    "sg:postcode":"50032",
    "sg:province":"Firenze",
    "sg:tags":[
        "leather"
    ],
    "wof:name":"Venturini",
    "wof:placetype":"venue"
},
  "geometry": {"coordinates":[11.406725,43.948181],"type":"Point"}
}