{
  "type": "Feature",
  "properties": {
    "iso:country":"IT",
    "sg:address":"65128 Pescara",
    "sg:city":"Pescara",
    "sg:orig_category":"Forniture Alle Strutture Ricettive. Forniture Per Attivita' Commerciali Ed Artigianali",
    "sg:phone":"+39 085 432 2087",
    "sg:postcode":"65128",
    "sg:province":"Pescara",
    "wof:name":"Fieni's Team Srl",
    "wof:placetype":"venue"
},
  "geometry": {"coordinates":[14.1789398193,42.4346923828],"type":"Point"}
}