{
  "type": "Feature",
  "properties": {
    "iso:country":"IT",
    "sg:address":"00132 Roma",
    "sg:city":"Roma",
    "sg:orig_category":"Imprese Edili",
    "sg:phone":"+39 06 2076 5454",
    "sg:postcode":"00132",
    "sg:province":"Roma",
    "wof:name":"Edil Service 3000",
    "wof:placetype":"venue"
},
  "geometry": {"coordinates":[12.68421,41.863075],"type":"Point"}
}