{
  "type": "Feature",
  "properties": {
    "iso:country":"IT",
    "sg:address":"70125 Bari",
    "sg:city":"Bari",
    "sg:orig_category":"Servizi Per Aziende, Manifestazioni E Supporto Agli Scambi Commerciali",
    "sg:phone":"+39 080 546 1521",
    "sg:postcode":"70125",
    "sg:province":"Bari",
    "sg:website":"http://www.aldotarricone.com",
    "wof:name":"Aldo Tarricone Investigazioni Srl",
    "wof:placetype":"venue"
},
  "geometry": {"coordinates":[16.884878,41.099556],"type":"Point"}
}