{
  "type": "Feature",
  "properties": {
    "iso:country":"IT",
    "sg:address":"62032 Morrovalle",
    "sg:city":"Morro",
    "sg:orig_category":"Cartotecnica E Servizi. Articoli Per Imballaggio E Confezionamento",
    "sg:phone":"+39 0733 866852",
    "sg:postcode":"62032",
    "sg:province":"Macerata",
    "wof:name":"Cartomarche Societ\u00c0 Unipersonale Arl",
    "wof:placetype":"venue"
},
  "geometry": {"coordinates":[13.385315,43.280315],"type":"Point"}
}