{
  "type": "Feature",
  "properties": {
    "iso:country":"IT",
    "sg:address":"38060 Besenello",
    "sg:city":"Besenello",
    "sg:orig_category":"Abbigliamento Esterno, Maglierie E Pelliccerie. Servizi E Lavori Per Abbigliamento E Pelletterie",
    "sg:phone":"+39 0464 834234",
    "sg:postcode":"38060",
    "sg:province":"Trento",
    "sg:website":"http://space.tin.it/economia/ecomper",
    "wof:name":"Modastil Di Martinelli In Comper Ornella",
    "wof:placetype":"venue"
},
  "geometry": {"coordinates":[11.113665,45.943523],"type":"Point"}
}