{
  "type": "Feature",
  "properties": {
    "iso:country":"IT",
    "sg:address":"58010 Sorano",
    "sg:city":"Sorano",
    "sg:orig_category":"Decoratori",
    "sg:phone":"+39 0564 633398",
    "sg:postcode":"58010",
    "sg:province":"Grosseto",
    "wof:name":"Associazione Culturale Studio Pandora",
    "wof:placetype":"venue"
},
  "geometry": {"coordinates":[11.714805603,42.6827507019],"type":"Point"}
}