{
  "type": "Feature",
  "properties": {
    "iso:country":"IT",
    "sg:address":"73014 Gallipoli",
    "sg:city":"Gallipoli",
    "sg:orig_category":"Servizi E Lavori Per Arredamento E Industria Del Legno. Vetro: Prodotti E Lavorazioni",
    "sg:phone":"+39 0833 275257",
    "sg:postcode":"73014",
    "sg:province":"Lecce",
    "wof:name":"Cristal Vetri Di Benvenga Fabrizio",
    "wof:placetype":"venue"
},
  "geometry": {"coordinates":[17.994991,40.061245],"type":"Point"}
}