{
  "type": "Feature",
  "properties": {
    "iso:country":"IT",
    "sg:address":"24067 Sarnico",
    "sg:city":"Sarnico",
    "sg:classifiers":[
        {
            "category":"Professional",
            "subcategory":"Business Services",
            "type":"Services"
        }
    ],
    "sg:phone":"+39 035 924211",
    "sg:postcode":"24067",
    "sg:province":"Bergamo",
    "sg:tags":[
        "support",
        "companies",
        "events",
        "trade"
    ],
    "wof:name":"Sarnico Management Centre",
    "wof:placetype":"venue"
},
  "geometry": {"coordinates":[9.991407,45.676773],"type":"Point"}
}