{
  "type": "Feature",
  "properties": {
    "addr:full":"80125 Napoli Napoli Napoli 80125",
    "addr:housenumber":"80125",
    "addr:postcode":"80125",
    "iso:country":"IT",
    "sg:address":"80125 Napoli",
    "sg:city":"Napoli",
    "sg:orig_category":"Lavorazioni Metalli, Stampaggio E Saldatura",
    "sg:phone":"+39 081 762 9320",
    "sg:postcode":"80125",
    "sg:province":"Napoli",
    "wof:name":"Scognamiglio Antonio Lavori In Acciaio E Metallo",
    "wof:placetype":"venue"
},
  "geometry": {"coordinates":[14.179122,40.843822],"type":"Point"}
}