{
  "type": "Feature",
  "properties": {
    "iso:country":"IT",
    "sg:address":"36015 Schio",
    "sg:city":"Schio",
    "sg:orig_category":"Elettrodomestici. Elettronica Professionale E Di Consumo. Arredi Ed Attrezzature Per Attivita' Commerciali Ed Artigianali. Macchine, Strumenti Ed Apparecchi Per Attivita' Industriali",
    "sg:phone":"+39 0445 578811",
    "sg:postcode":"36015",
    "sg:province":"Vicenza",
    "sg:website":"http://www.imanpack.it",
    "wof:name":"Iman Pack Srl",
    "wof:placetype":"venue"
},
  "geometry": {"coordinates":[11.546574,45.575367],"type":"Point"}
}