{
  "type": "Feature",
  "properties": {
    "iso:country":"IT",
    "sg:address":"24066 Pedrengo",
    "sg:city":"Pedrengo",
    "sg:orig_category":"Articoli Per Imballaggio E Confezionamento. Forniture Per Uffici. Forniture Per Attivita' Commerciali Ed Artigianali",
    "sg:phone":"+39 035 661611",
    "sg:postcode":"24066",
    "sg:province":"Bergamo",
    "wof:name":"Emmeci Srl",
    "wof:placetype":"venue"
},
  "geometry": {"coordinates":[9.73791,45.700481],"type":"Point"}
}