{
  "type": "Feature",
  "properties": {
    "addr:full":"62032 Camerino Camerino Macerata 62032",
    "addr:postcode":"62032;62032",
    "iso:country":"IT",
    "sg:address":"62032 Camerino",
    "sg:city":"Camerino",
    "sg:orig_category":"Impiantistica E Prodotti Tecnologici Per Edilizia",
    "sg:phone":"+39 0737 630882",
    "sg:postcode":"62032",
    "sg:province":"Macerata",
    "wof:name":"Easypark Srl",
    "wof:placetype":"venue"
},
  "geometry": {"coordinates":[13.066685,43.146263],"type":"Point"}
}