{
  "type": "Feature",
  "properties": {
    "iso:country":"IT",
    "sg:address":"16164 Genova",
    "sg:city":"Genova",
    "sg:orig_category":"Vetro: Prodotti E Lavorazioni",
    "sg:phone":"+39 010 713148",
    "sg:postcode":"16164",
    "sg:province":"Genova",
    "wof:name":"Rondanina Vetro Di Rondanina Roberto & C. Snc",
    "wof:placetype":"venue"
},
  "geometry": {"coordinates":[8.903449,44.491497],"type":"Point"}
}