{
  "type": "Feature",
  "properties": {
    "iso:country":"IT",
    "sg:address":"51, Via S. Luca 31038 Paese",
    "sg:city":"Paese",
    "sg:classifiers":[
        {
            "category":"Professional",
            "subcategory":"Engineering",
            "type":"Services"
        }
    ],
    "sg:phone":"+39 390 422 4594",
    "sg:postcode":"31038",
    "sg:province":"Treviso",
    "sg:tags":[
        "machine",
        "-",
        "mechanical"
    ],
    "wof:name":"Generalfilter Italia S.p.a.",
    "wof:placetype":"venue"
},
  "geometry": {"coordinates":[12.153814,45.678627],"type":"Point"}
}