{
  "type": "Feature",
  "properties": {
    "iso:country":"IT",
    "sg:address":"Via Palazzina 24 25124 Brescia",
    "sg:city":"Brescia",
    "sg:classifiers":[
        {
            "category":"Manufacturing",
            "subcategory":"Tools & Machinery",
            "type":"Manufacturing & Wholesale Goods"
        }
    ],
    "sg:phone":"+39 030 349001",
    "sg:postcode":"25124",
    "sg:province":"Brescia",
    "sg:tags":[
        "die",
        "injection",
        "moulding",
        "casting"
    ],
    "sg:website":"www.alplast-dies.it",
    "wof:name":"Al.plast Srl",
    "wof:placetype":"venue"
},
  "geometry": {"coordinates":[11.115941,45.418343],"type":"Point"}
}