{
  "type": "Feature",
  "properties": {
    "addr:full":"Piazza Cavour 1; Cremona; 26100 Cremona Cremona 26100",
    "addr:housenumber":"1",
    "addr:postcode":"26100;26100",
    "addr:street":"Piazza Cavour",
    "iso:country":"IT",
    "sg:address":"Piazza Cavour 1; Cremona; 26100",
    "sg:city":"Cremona",
    "sg:classifiers":[
        {
            "category":"Banks & Credit Unions",
            "subcategory":"Bank",
            "type":"Services"
        }
    ],
    "sg:phone":"+39 0372 31841",
    "sg:postcode":"26100",
    "sg:province":"Cremona",
    "wof:name":"Banca Provinciale Lombarda",
    "wof:placetype":"venue"
},
  "geometry": {"coordinates":[10.023348,45.133938],"type":"Point"}
}