{
  "type": "Feature",
  "properties": {
    "iso:country":"IT",
    "sg:address":"Gall. Principe Di Napoli; Napoli; 80135",
    "sg:city":"Napoli",
    "sg:classifiers":[
        {
            "category":"Banks & Credit Unions",
            "subcategory":"Bank",
            "type":"Services"
        }
    ],
    "sg:phone":"+39 081 340461",
    "sg:postcode":"80135",
    "sg:province":"Napoli",
    "wof:name":"Banco Di Napoli",
    "wof:placetype":"venue"
},
  "geometry": {"coordinates":[14.25034,40.852509],"type":"Point"}
}