{
  "type": "Feature",
  "properties": {
    "iso:country":"IT",
    "sg:address":"40121 Bologna",
    "sg:city":"Bologna",
    "sg:orig_category":"Gioielleria, Oreficeria E Argenteria. Shopping",
    "sg:phone":"+39 051 224271",
    "sg:postcode":"40121",
    "sg:province":"Bologna",
    "wof:name":"Casa Dell'argento",
    "wof:placetype":"venue"
},
  "geometry": {"coordinates":[11.656878,44.977913],"type":"Point"}
}