{
  "type": "Feature",
  "properties": {
    "addr:full":"8, Via Cigliano 50026 San Casciano In Val Di Pesa San Casciano in Val di Pesa Firenze 50026",
    "addr:postcode":"50026;casciano;di pesa;50026",
    "addr:street":"Via Cigliano",
    "iso:country":"IT",
    "sg:address":"8, Via Cigliano 50026 San Casciano In Val Di Pesa",
    "sg:city":"San Casciano in Val di Pesa",
    "sg:classifiers":[
        {
            "category":"Personal",
            "subcategory":"Shoe Repair & Shine",
            "type":"Services"
        }
    ],
    "sg:phone":"+39 39055822213",
    "sg:postcode":"50026",
    "sg:province":"Firenze",
    "sg:tags":[
        "leather"
    ],
    "wof:name":"Calzaturificio L.g.r.",
    "wof:placetype":"venue"
},
  "geometry": {"coordinates":[11.179672,43.637882],"type":"Point"}
}