{
  "type": "Feature",
  "properties": {
    "iso:country":"IT",
    "sg:address":"20133 Milano",
    "sg:city":"Milano",
    "sg:orig_category":"Macchine, Impianti Ed Attrezzature Per Abbigliamento E Pelletterie",
    "sg:phone":"+39 02 7063 0361",
    "sg:postcode":"20133",
    "sg:province":"Milano",
    "wof:name":"New Planet",
    "wof:placetype":"venue"
},
  "geometry": {"coordinates":[9.223974,45.475403],"type":"Point"}
}