{
  "type": "Feature",
  "properties": {
    "iso:country":"IT",
    "sg:address":"3, Via E. Berlinguer 43013 Langhirano",
    "sg:city":"Langhirano",
    "sg:classifiers":[
        {
            "category":"Food & Beverages",
            "subcategory":"Groceries & Convenience Stores",
            "type":"Retail Goods"
        }
    ],
    "sg:phone":"+39 0521 858241",
    "sg:postcode":"43013",
    "sg:province":"Parma",
    "sg:tags":[
        "product",
        "related"
    ],
    "wof:name":"Gli Specialisti Di Angelini (s.p.a.)",
    "wof:placetype":"venue"
},
  "geometry": {"coordinates":[10.2655296326,44.6866264343],"type":"Point"}
}