{
  "type": "Feature",
  "properties": {
    "addr:full":"Via Martiri D' Ungheria 23 35012 Camposampiero Camposampiero Padova 35012",
    "addr:housenumber":"23",
    "addr:postcode":"35012;35012",
    "addr:street":"Via Martiri D ' Ungheria",
    "iso:country":"IT",
    "sg:address":"Via Martiri D' Ungheria 23 35012 Camposampiero",
    "sg:city":"Camposampiero",
    "sg:classifiers":[
        {
            "category":"Manufacturing",
            "subcategory":"Rubber & Plastics",
            "type":"Manufacturing & Wholesale Goods"
        }
    ],
    "sg:phone":"+39 049 930 0220",
    "sg:postcode":"35012",
    "sg:province":"Padova",
    "sg:tags":[
        "material"
    ],
    "sg:website":"www.arcopolimeri.com",
    "wof:name":"Arcopolimeri Srl",
    "wof:placetype":"venue"
},
  "geometry": {"coordinates":[11.9311094284,45.5580444336],"type":"Point"}
}