{
  "type": "Feature",
  "properties": {
    "iso:country":"IT",
    "sg:address":"Borgonuovo 18; Milano; 20121",
    "sg:city":"Milano",
    "sg:classifiers":[
        {
            "category":"Banks & Credit Unions",
            "subcategory":"Bank",
            "type":"Services"
        }
    ],
    "sg:phone":"+39 0263471",
    "sg:postcode":"20121",
    "sg:province":"Milano",
    "wof:name":"Credit Lyonnais Sa",
    "wof:placetype":"venue"
},
  "geometry": {"coordinates":[9.190205,45.471916],"type":"Point"}
}