{
  "type": "Feature",
  "properties": {
    "addr:full":"873, Calle S. Giacomo 30015 Chioggia Chioggia Venezia 30015",
    "addr:housenumber":"873",
    "addr:postcode":"30015;30015",
    "addr:street":"Calle S. Giacomo",
    "iso:country":"IT",
    "sg:address":"873, Calle S. Giacomo 30015 Chioggia",
    "sg:city":"Chioggia",
    "sg:classifiers":[
        {
            "category":"Sports & Exercise",
            "subcategory":"Playing Field",
            "type":"Entertainment"
        }
    ],
    "sg:phone":"+39 39041400148",
    "sg:postcode":"30015",
    "sg:province":"Venezia",
    "sg:tags":[
        "game"
    ],
    "wof:name":"Rossetti Antonio (s.n.c.)",
    "wof:placetype":"venue"
},
  "geometry": {"coordinates":[12.280377,45.21859],"type":"Point"}
}