{
  "type": "Feature",
  "properties": {
    "iso:country":"IT",
    "sg:address":"9, Via Gussalli Luigi 25125 Brescia",
    "sg:city":"Brescia",
    "sg:classifiers":[
        {
            "category":"Professional",
            "subcategory":"Advertising",
            "type":"Services"
        }
    ],
    "sg:phone":"+39 030 358 1510",
    "sg:postcode":"25125",
    "sg:province":"Brescia",
    "sg:tags":[
        "communication",
        "medium"
    ],
    "wof:name":"Onion Spa",
    "wof:placetype":"venue"
},
  "geometry": {"coordinates":[10.222958,45.539829],"type":"Point"}
}