{
  "type": "Feature",
  "properties": {
    "addr:full":"24012 Brembilla Brembilla Bergamo 24012",
    "addr:postcode":"24012;24012",
    "iso:country":"IT",
    "sg:address":"24012 Brembilla",
    "sg:city":"Brembilla",
    "sg:orig_category":"Minuterie - Produzione E Commercio",
    "sg:phone":"+39 0345 98216",
    "sg:postcode":"24012",
    "sg:province":"Bergamo",
    "sg:website":"http://www.gccarminati.it",
    "wof:name":"Gc Carminati Srl",
    "wof:placetype":"venue"
},
  "geometry": {"coordinates":[9.6125659943,45.8186836243],"type":"Point"}
}