{
  "type": "Feature",
  "properties": {
    "iso:country":"IT",
    "sg:address":"25060 Marcheno",
    "sg:city":"Marcheno",
    "sg:orig_category":"Maniglie",
    "sg:phone":"+39 030 896 6033",
    "sg:postcode":"25060",
    "sg:province":"Brescia",
    "sg:website":"http://www.sicma.net",
    "wof:name":"Sicma Maniglie Srl",
    "wof:placetype":"venue"
},
  "geometry": {"coordinates":[10.221043,45.713303],"type":"Point"}
}