{
  "type": "Feature",
  "properties": {
    "iso:country":"IT",
    "sg:address":"20063 Cernusco Sul Naviglio",
    "sg:city":"Cernusco sul Naviglio",
    "sg:orig_category":"Materiali E Componenti Elettrotecnici",
    "sg:postcode":"20063",
    "sg:province":"Milano",
    "wof:name":"Gdt Elettroforniture S.p.a.",
    "wof:placetype":"venue"
},
  "geometry": {"coordinates":[9.289932,45.517666],"type":"Point"}
}