{
  "type": "Feature",
  "properties": {
    "iso:country":"IT",
    "sg:address":"20121 Milano",
    "sg:city":"Milano",
    "sg:orig_category":"Banche E Servizi Finanziari",
    "sg:phone":"+39 02 784670",
    "sg:postcode":"20121",
    "sg:province":"Milano",
    "wof:name":"Banca Ifigest Spa",
    "wof:placetype":"venue"
},
  "geometry": {"coordinates":[9.192014,45.46806],"type":"Point"}
}