{
  "type": "Feature",
  "properties": {
    "iso:country":"IT",
    "sg:address":"4, Via Nenni 40065 Pianoro",
    "sg:city":"Pianoro",
    "sg:classifiers":[
        {
            "category":"Manufacturing",
            "subcategory":"Tools & Machinery",
            "type":"Manufacturing & Wholesale Goods"
        }
    ],
    "sg:phone":"+39 39051775667",
    "sg:postcode":"40065",
    "sg:province":"Bologna",
    "sg:tags":[
        "environment",
        "equipment",
        "-"
    ],
    "wof:name":"Alfarec (s.p.a.)",
    "wof:placetype":"venue"
},
  "geometry": {"coordinates":[11.33748,44.398281],"type":"Point"}
}