{
  "type": "Feature",
  "properties": {
    "addr:full":"81030 Gricignano Di Aversa Gricignano di Aversa Caserta 81030",
    "addr:postcode":"81030;81030",
    "iso:country":"IT",
    "sg:address":"81030 Gricignano Di Aversa",
    "sg:city":"Gricignano di Aversa",
    "sg:orig_category":"Frigotecnica, Apparecchiature E Servizi. Servizi Di Magazzinaggio E Movimentazione",
    "sg:phone":"+39 081 813 2583",
    "sg:postcode":"81030",
    "sg:province":"Caserta",
    "wof:name":"Frigocaserta (s.r.l.)",
    "wof:placetype":"venue"
},
  "geometry": {"coordinates":[14.2428731918,41.0487289429],"type":"Point"}
}