{
  "type": "Feature",
  "properties": {
    "iso:country":"IT",
    "sg:address":"19037 Santo Stefano Magra",
    "sg:orig_category":"Bevande, Vini E Liquori",
    "sg:phone":"+39 0187 630009",
    "sg:postcode":"19037",
    "sg:province":"La Spezia",
    "wof:name":"Battistini Anselmo",
    "wof:placetype":"venue"
},
  "geometry": {"coordinates":[9.9119272232,44.1543693542],"type":"Point"}
}