{
  "type": "Feature",
  "properties": {
    "iso:country":"IT",
    "sg:address":"20124 Milano",
    "sg:city":"Milano",
    "sg:orig_category":"Gioielleria, Oreficeria E Argenteria. Shopping",
    "sg:phone":"+39 02 6749 0309",
    "sg:postcode":"20124",
    "sg:province":"Milano",
    "wof:name":"Artistic International Di Mohammed Islam E C. Sas",
    "wof:placetype":"venue"
},
  "geometry": {"coordinates":[9.211138,45.484653],"type":"Point"}
}