{
  "type": "Feature",
  "properties": {
    "iso:country":"IT",
    "sg:address":"43, Via Elorina 96100 Siracusa",
    "sg:city":"Siracusa",
    "sg:classifiers":[
        {
            "category":"Manufacturing",
            "subcategory":"Glass & Minerals",
            "type":"Manufacturing & Wholesale Goods"
        }
    ],
    "sg:phone":"+39 39093169200",
    "sg:postcode":"96100",
    "sg:province":"Siracusa",
    "wof:name":"Elite Srl",
    "wof:placetype":"venue"
},
  "geometry": {"coordinates":[15.274746,37.064262],"type":"Point"}
}