{
  "type": "Feature",
  "properties": {
    "addr:full":"Via S. Pancrazio Torre Lapillo 73048 Nardo' Lecce 73048",
    "addr:postcode":"73048;73048",
    "addr:street":"Via S. Pancrazio Torre Lapillo;Nardo ' Lecce",
    "iso:country":"IT",
    "sg:address":"Via S. Pancrazio Torre Lapillo 73048 Nardo'",
    "sg:classifiers":[
        {
            "category":"Autos & Motor Vehicles",
            "subcategory":"Boat Sales",
            "type":"Retail Goods"
        }
    ],
    "sg:phone":"+39 0833 566045",
    "sg:postcode":"73048",
    "sg:province":"Lecce",
    "wof:name":"Ilmea (s.r.l.)",
    "wof:placetype":"venue"
},
  "geometry": {"coordinates":[18.174015,40.353291],"type":"Point"}
}