{
  "type": "Feature",
  "properties": {
    "iso:country":"IT",
    "sg:address":"20148 Milano",
    "sg:city":"Milano",
    "sg:orig_category":"Servizi E Lavori Per Abbigliamento E Pelletterie",
    "sg:phone":"+39 02 3926 2156",
    "sg:postcode":"20148",
    "sg:province":"Milano",
    "wof:name":"Amba Parodi Maria",
    "wof:placetype":"venue"
},
  "geometry": {"coordinates":[9.147285,45.482738],"type":"Point"}
}