{
  "type": "Feature",
  "properties": {
    "addr:full":"Via I\u00b0 Maggio,69 - Gariga 29027 Podenzano Podenzano Piacenza 29027",
    "addr:housenumber":"69",
    "addr:postcode":"29027;29027",
    "addr:street":"Via I\u00b0 Maggio",
    "iso:country":"IT",
    "sg:address":"Via I\u00b0 Maggio,69 - Gariga 29027 Podenzano",
    "sg:city":"Podenzano",
    "sg:orig_category":"Dust Removal And Suction Plants For Thermal Oxygen Cutting Installations",
    "sg:phone":"+39 0523 524066",
    "sg:postcode":"29027",
    "sg:province":"Piacenza",
    "wof:name":"Sideros Srl",
    "wof:placetype":"venue"
},
  "geometry": {"coordinates":[9.687683,44.99868],"type":"Point"}
}