{
  "type": "Feature",
  "properties": {
    "addr:full":"40126 Bologna Bologna Bologna 40126",
    "addr:postcode":"40126;40126",
    "iso:country":"IT",
    "sg:address":"40126 Bologna",
    "sg:city":"Bologna",
    "sg:orig_category":"Arredamenti - Vendita Al Dettaglio",
    "sg:phone":"+39 051 421 1636",
    "sg:postcode":"40126",
    "sg:province":"Bologna",
    "sg:website":"http://www.beza.com",
    "wof:name":"Beza Di Atipico Srl",
    "wof:placetype":"venue"
},
  "geometry": {"coordinates":[11.345723,44.499699],"type":"Point"}
}