{
  "type": "Feature",
  "properties": {
    "addr:full":"97100 Ragusa Ragusa Ragusa 97100",
    "addr:postcode":"97100;97100",
    "iso:country":"IT",
    "sg:address":"97100 Ragusa",
    "sg:city":"Ragusa",
    "sg:orig_category":"Studi E Consulenze Tecniche E Industriali. Consulenze Tecniche, Amministrative E Perizie. Professionisti - Studi E Servizi Ed Associazioni Di Interesse Aziendale",
    "sg:phone":"+39 0932 228636",
    "sg:postcode":"97100",
    "sg:province":"Ragusa",
    "wof:name":"Munda Giuseppe",
    "wof:placetype":"venue"
},
  "geometry": {"coordinates":[14.682105,36.912518],"type":"Point"}
}