{
  "type": "Feature",
  "properties": {
    "iso:country":"IT",
    "sg:address":"15030 Villanova Monferrato",
    "sg:city":"Villanova Monferrato",
    "sg:orig_category":"Ricambi E Componenti Dei Mezzi Di Trasporto",
    "sg:phone":"+39 0142 483635",
    "sg:postcode":"15030",
    "sg:province":"Alessandria",
    "sg:website":"http://www.fuorimilano.com/quat-d",
    "wof:name":"Quat-d Di Domenico Dotta",
    "wof:placetype":"venue"
},
  "geometry": {"coordinates":[8.479846,45.182934],"type":"Point"}
}