{
  "type": "Feature",
  "properties": {
    "addr:full":"15100 Alessandria Alessandria Alessandria 15100",
    "addr:postcode":"15100;15100",
    "iso:country":"IT",
    "sg:address":"15100 Alessandria",
    "sg:city":"Alessandria",
    "sg:orig_category":"Automazione E Robotica - Apparecchiature E Componenti",
    "sg:phone":"+39 0131 204411",
    "sg:postcode":"15100",
    "sg:province":"Alessandria",
    "sg:website":"http://www.gefit.com/body.htm",
    "wof:name":"Gefit Spa",
    "wof:placetype":"venue"
},
  "geometry": {"coordinates":[8.624974,44.905861],"type":"Point"}
}