{
  "type": "Feature",
  "properties": {
    "iso:country":"IT",
    "sg:address":"Via All' Idroscalo 16149 Genova",
    "sg:city":"Genova",
    "sg:classifiers":[
        {
            "category":"Parking",
            "subcategory":"Lot",
            "type":"Transportation"
        }
    ],
    "sg:phone":"+39 010 246 2761",
    "sg:postcode":"16149",
    "sg:province":"Genova",
    "sg:tags":[
        "transport",
        "road"
    ],
    "wof:name":"Genoa Marine Services S.r.l.",
    "wof:placetype":"venue"
},
  "geometry": {"coordinates":[8.900524,44.405518],"type":"Point"}
}