{
  "type": "Feature",
  "properties": {
    "iso:country":"IT",
    "sg:address":"Via Tribolina 30 24064 Grumello Del Monte",
    "sg:city":"Grumello del Monte",
    "sg:orig_category":"Shieldings, Electromagnetic",
    "sg:phone":"+39 035 832558",
    "sg:postcode":"24064",
    "sg:province":"Bergamo",
    "sg:website":"www.myshield.it",
    "wof:name":"Castelberg Technologies Srl",
    "wof:placetype":"venue"
},
  "geometry": {"coordinates":[9.883429,45.628574],"type":"Point"}
}