{
  "type": "Feature",
  "properties": {
    "iso:country":"IT",
    "sg:address":"40131 Bologna",
    "sg:city":"Bologna",
    "sg:orig_category":"Prodotti E Manufatti In Materie Plastiche. Servizi E Lavori Industria Delle Materie Plastiche",
    "sg:phone":"+39 051 634 0068",
    "sg:postcode":"40131",
    "sg:province":"Bologna",
    "sg:website":"http://www.franciacatene.it",
    "wof:name":"Francia Srl",
    "wof:placetype":"venue"
},
  "geometry": {"coordinates":[11.3311891556,44.5217132568],"type":"Point"}
}