{
  "type": "Feature",
  "properties": {
    "addr:full":"65017 Penne Penne Pescara 65017",
    "addr:postcode":"65017;65017",
    "iso:country":"IT",
    "sg:address":"65017 Penne",
    "sg:city":"Penne",
    "sg:orig_category":"Birra - Produzione E Commercio",
    "sg:phone":"+39 085 827 9725",
    "sg:postcode":"65017",
    "sg:province":"Pescara",
    "wof:name":"Centro Distribuzione Bevande Srl",
    "wof:placetype":"venue"
},
  "geometry": {"coordinates":[13.9663,42.403248],"type":"Point"}
}