{
  "type": "Feature",
  "properties": {
    "addr:full":"7, Via Mons. Giulio Babolin 35024 Bovolenta Bovolenta Padova 35024",
    "addr:postcode":"35024;35024",
    "addr:street":"Via Mons. Giulio Babolin",
    "iso:country":"IT",
    "sg:address":"7, Via Mons. Giulio Babolin 35024 Bovolenta",
    "sg:city":"Bovolenta",
    "sg:classifiers":[
        {
            "category":"Manufacturing",
            "subcategory":"Metals",
            "type":"Manufacturing & Wholesale Goods"
        }
    ],
    "sg:phone":"+39 049 954 5027",
    "sg:postcode":"35024",
    "sg:province":"Padova",
    "sg:tags":[
        "processing"
    ],
    "wof:name":"Induzione Srl",
    "wof:placetype":"venue"
},
  "geometry": {"coordinates":[11.8765888214,45.4095687866],"type":"Point"}
}