{
  "type": "Feature",
  "properties": {
    "iso:country":"IT",
    "sg:address":"16015 Casella",
    "sg:city":"Casella",
    "sg:orig_category":"Prodotti Vari In Metallo. Articoli Per Imballaggio E Confezionamento",
    "sg:phone":"+39 010 967 0275",
    "sg:postcode":"16015",
    "sg:province":"Genova",
    "wof:name":"L.b.s. Di Lagorio Gianfranco",
    "wof:placetype":"venue"
},
  "geometry": {"coordinates":[9.0037622452,44.5327415466],"type":"Point"}
}