{
  "type": "Feature",
  "properties": {
    "addr:full":"29022 Bobbio Bobbio Piacenza 29022",
    "addr:postcode":"29022;29022",
    "iso:country":"IT",
    "sg:address":"29022 Bobbio",
    "sg:city":"Bobbio",
    "sg:orig_category":"Servizi Ausiliari Per Il Trasporto. Servizi Vari Di Interesse Pubblico",
    "sg:phone":"+39 0523 937127",
    "sg:postcode":"29022",
    "sg:province":"Piacenza",
    "wof:name":"Follini & Rivoli Snc",
    "wof:placetype":"venue"
},
  "geometry": {"coordinates":[9.429183,44.809048],"type":"Point"}
}