{
  "type": "Feature",
  "properties": {
    "iso:country":"IT",
    "sg:address":"10152 Torino",
    "sg:city":"Torino",
    "sg:orig_category":"Calzature, Pelletterie E Pelli",
    "sg:phone":"+39 011 283010",
    "sg:postcode":"10152",
    "sg:province":"Torino",
    "sg:website":"http://www.mtc-abitilavoro.it",
    "wof:name":"M.t.c. Snc Di Massari Alessandro, Corsaro & C.",
    "wof:placetype":"venue"
},
  "geometry": {"coordinates":[7.695158,45.079884],"type":"Point"}
}