{
  "type": "Feature",
  "properties": {
    "iso:country":"IT",
    "sg:address":"00161 Roma",
    "sg:city":"Roma",
    "sg:classifiers":[
        {
            "category":"Health Services",
            "subcategory":"Health Practitioner",
            "type":"Services"
        }
    ],
    "sg:postcode":"00161",
    "sg:province":"Roma",
    "sg:tags":[
        "medici"
    ],
    "wof:name":"Villa Esperia Roma S.p.a.",
    "wof:placetype":"venue"
},
  "geometry": {"coordinates":[12.5135173798,41.9107589722],"type":"Point"}
}