{
  "type": "Feature",
  "properties": {
    "addr:full":"84010 San Valentino Torio San Valentino Torio Salerno 84010",
    "addr:housenumber":"84010;valentino torio",
    "addr:postcode":"valentino torio;84010",
    "addr:street":"San;Salerno",
    "iso:country":"IT",
    "sg:address":"84010 San Valentino Torio",
    "sg:city":"San Valentino Torio",
    "sg:orig_category":"Macchine Ed Impianti Per Edilizia E Lavori Pubblici",
    "sg:phone":"+39 081 955137",
    "sg:postcode":"84010",
    "sg:province":"Salerno",
    "wof:name":"Sama Di Sorrentino Pasquale",
    "wof:placetype":"venue"
},
  "geometry": {"coordinates":[14.602627,40.79694],"type":"Point"}
}