{
  "type": "Feature",
  "properties": {
    "iso:country":"IT",
    "sg:address":"Viale Gramsci 12/14; Pesaro; 61100",
    "sg:city":"Pesaro",
    "sg:classifiers":[
        {
            "category":"Banks & Credit Unions",
            "subcategory":"Bank",
            "type":"Services"
        }
    ],
    "sg:phone":"+39 0721 30581",
    "sg:postcode":"61100",
    "sg:province":"Pesaro E Urbino",
    "wof:name":"Banca Popolare Dell'etruria, E Del Lazio",
    "wof:placetype":"venue"
},
  "geometry": {"coordinates":[12.913523,43.907555],"type":"Point"}
}