{
  "type": "Feature",
  "properties": {
    "addr:full":"22070 Rovello Porro Rovello Porro Como 22070",
    "addr:postcode":"22070;22070",
    "iso:country":"IT",
    "sg:address":"22070 Rovello Porro",
    "sg:city":"Rovello Porro",
    "sg:orig_category":"Lavorazioni Metalli, Stampaggio E Saldatura",
    "sg:postcode":"22070",
    "sg:province":"Como",
    "wof:name":"Tranceria Alberio (s.n.c.)",
    "wof:placetype":"venue"
},
  "geometry": {"coordinates":[9.041134,45.658558],"type":"Point"}
}