{
  "type": "Feature",
  "properties": {
    "iso:country":"IT",
    "sg:address":"16128 Genova",
    "sg:city":"Genova",
    "sg:orig_category":"Forniture E Prodotti Informatici. Forniture Per Uffici",
    "sg:phone":"+39 010 580857",
    "sg:postcode":"16128",
    "sg:province":"Genova",
    "sg:website":"http://www.rbnewage.hypermat.net",
    "wof:name":"Rb New Age Di Bianca Cucchi & C. Snc",
    "wof:placetype":"venue"
},
  "geometry": {"coordinates":[8.938744545,44.4005470276],"type":"Point"}
}