{
  "type": "Feature",
  "properties": {
    "iso:country":"IT",
    "sg:address":"80100 Napoli",
    "sg:orig_category":"Ricerca, Selezione E Formazione Del Personale",
    "sg:phone":"+39 081 750 0859",
    "sg:province":"NA",
    "wof:name":"Team Consulting Srl",
    "wof:placetype":"venue"
},
  "geometry": {"coordinates":[14.282045,40.856991],"type":"Point"}
}