{
  "type": "Feature",
  "properties": {
    "addr:full":"10121 Torino Torino Torino 10121",
    "addr:postcode":"10121;10121",
    "iso:country":"IT",
    "sg:address":"10121 Torino",
    "sg:city":"Torino",
    "sg:orig_category":"Servizi Culturali E Per Lo Spettacolo. Servizi Per Lo Sport E Il Tempo Libero. Servizi Per Aziende, Manifestazioni E Supporto Agli Scambi Commerciali",
    "sg:phone":"+39 011 532692",
    "sg:postcode":"10121",
    "sg:province":"Torino",
    "sg:website":"http://www.divinashock.it",
    "wof:name":"Divina Shock Agency",
    "wof:placetype":"venue"
},
  "geometry": {"coordinates":[7.668562,45.068905],"type":"Point"}
}