{
  "type": "Feature",
  "properties": {
    "addr:full":"2, Via Oberdan G. 40055 Castenaso Castenaso Bologna 40055",
    "addr:postcode":"40055;40055",
    "addr:street":"Via Oberdan G.",
    "iso:country":"IT",
    "sg:address":"2, Via Oberdan G. 40055 Castenaso",
    "sg:city":"Castenaso",
    "sg:classifiers":[
        {
            "category":"Autos & Motor Vehicles",
            "subcategory":"Automobile Sales",
            "type":"Retail Goods"
        }
    ],
    "sg:phone":"+39 39051780018",
    "sg:postcode":"40055",
    "sg:province":"Bologna",
    "sg:tags":[
        "motor-cars"
    ],
    "wof:name":"Autec S.p.a.",
    "wof:placetype":"venue"
},
  "geometry": {"coordinates":[11.4226055145,44.4977416992],"type":"Point"}
}