{
  "type": "Feature",
  "properties": {
    "addr:full":"16121 Genova Genova Genova 16121",
    "addr:postcode":"16121;16121",
    "iso:country":"IT",
    "sg:address":"16121 Genova",
    "sg:city":"Genova",
    "sg:orig_category":"Apparecchi Acustici Per Sordita'",
    "sg:phone":"+39 010 247 4239",
    "sg:postcode":"16121",
    "sg:province":"Genova",
    "sg:website":"http://www.maicobioacustica.com",
    "wof:name":"Maico Bioacustica Snc",
    "wof:placetype":"venue"
},
  "geometry": {"coordinates":[8.939713,44.405628],"type":"Point"}
}