{
  "type": "Feature",
  "properties": {
    "addr:full":"28053 Castelletto Sopra Ticino Castelletto sopra Ticino Novara 28053",
    "addr:postcode":"28053;28053",
    "iso:country":"IT",
    "sg:address":"28053 Castelletto Sopra Ticino",
    "sg:city":"Castelletto sopra Ticino",
    "sg:orig_category":"Vetro: Prodotti E Lavorazioni",
    "sg:phone":"+39 0331 921360",
    "sg:postcode":"28053",
    "sg:province":"Novara",
    "wof:name":"La Modifica Di Rolandi Mario",
    "wof:placetype":"venue"
},
  "geometry": {"coordinates":[8.626179,45.719856],"type":"Point"}
}