{
  "type": "Feature",
  "properties": {
    "iso:country":"IT",
    "sg:address":"Strada Vicinale Del Lionetto 29 10146 Torino",
    "sg:city":"Torino",
    "sg:classifiers":[
        {
            "category":"Manufacturing",
            "subcategory":"Rubber & Plastics",
            "type":"Manufacturing & Wholesale Goods"
        }
    ],
    "sg:phone":"+39 011 779 0617",
    "sg:postcode":"10146",
    "sg:province":"Torino",
    "sg:tags":[
        "joint"
    ],
    "wof:name":"S.a.p.a.t. Sas",
    "wof:placetype":"venue"
},
  "geometry": {"coordinates":[7.686619,45.07056],"type":"Point"}
}