{
  "type": "Feature",
  "properties": {
    "iso:country":"IT",
    "sg:address":"20099 Sesto S. Giovanni",
    "sg:orig_category":"Agenzie Viaggi E Turismo",
    "sg:phone":"+39 02 2247 8571",
    "sg:postcode":"20099",
    "sg:province":"Milano",
    "wof:name":"Ambra Italia Srl",
    "wof:placetype":"venue"
},
  "geometry": {"coordinates":[9.240688,45.534695],"type":"Point"}
}