{
  "type": "Feature",
  "properties": {
    "iso:country":"IT",
    "sg:address":"24069 Trescore Balneario",
    "sg:city":"Trescore Balneario",
    "sg:orig_category":"Utensili Meccanici E Materiali",
    "sg:phone":"+39 035 943636",
    "sg:postcode":"24069",
    "sg:province":"Bergamo",
    "sg:website":"http://www.gloxi.it",
    "wof:name":"Gloxi Italia Srl",
    "wof:placetype":"venue"
},
  "geometry": {"coordinates":[9.847438,45.707226],"type":"Point"}
}