{
  "type": "Feature",
  "properties": {
    "addr:full":"Localita' Canarbino 19032 Lerici Lerici La Spezia 19032",
    "addr:postcode":"19032;19032",
    "addr:street":"Localita ' Canarbino",
    "iso:country":"IT",
    "sg:address":"Localita' Canarbino 19032 Lerici",
    "sg:city":"Lerici",
    "sg:classifiers":[
        {
            "category":"Travel",
            "subcategory":"Travel Agent",
            "type":"Entertainment"
        }
    ],
    "sg:phone":"+39 0187 560764",
    "sg:postcode":"19032",
    "sg:province":"La Spezia",
    "sg:tags":[
        "business"
    ],
    "wof:name":"Trattoria Pin Bon Di Bragazzi Morena",
    "wof:placetype":"venue"
},
  "geometry": {"coordinates":[9.888175,44.095722],"type":"Point"}
}