{
  "type": "Feature",
  "properties": {
    "iso:country":"IT",
    "sg:address":"40, Localita' Arsio 38021 Brez",
    "sg:city":"Brez",
    "sg:classifiers":[
        {
            "category":"Farming",
            "subcategory":"Livestock Farm",
            "type":"Manufacturing & Wholesale Goods"
        }
    ],
    "sg:phone":"+39 0463 874348",
    "sg:postcode":"38021",
    "sg:province":"Trento",
    "sg:tags":[
        "agriculture"
    ],
    "wof:name":"S.a.b.a.c. Soc. Coop.",
    "wof:placetype":"venue"
},
  "geometry": {"coordinates":[11.096387,46.426586],"type":"Point"}
}