{
  "type": "Feature",
  "properties": {
    "iso:country":"IT",
    "sg:address":"24050 Lurano",
    "sg:city":"Lurano",
    "sg:orig_category":"Macchine E Forniture Per Arredamento E Industria Del Legno. Macchine Utensili E Impianti",
    "sg:phone":"+39 035 800782",
    "sg:postcode":"24050",
    "sg:province":"Bergamo",
    "wof:name":"Mec-power Srl",
    "wof:placetype":"venue"
},
  "geometry": {"coordinates":[9.602236,45.591137],"type":"Point"}
}