{
  "type": "Feature",
  "properties": {
    "iso:country":"IT",
    "sg:address":"00144 Roma",
    "sg:city":"Roma",
    "sg:orig_category":"Apparecchi, Attrezzature E Forniture Per Centri Estetici",
    "sg:phone":"+39 06 592 4824",
    "sg:postcode":"00144",
    "sg:province":"Roma",
    "wof:name":"Vitale Sonia",
    "wof:placetype":"venue"
},
  "geometry": {"coordinates":[12.463936,41.832348],"type":"Point"}
}