{
  "type": "Feature",
  "properties": {
    "addr:full":"20093 Cologno Monzese Cologno Monzese Milano 20093",
    "addr:postcode":"20093;20093",
    "iso:country":"IT",
    "sg:address":"20093 Cologno Monzese",
    "sg:city":"Cologno Monzese",
    "sg:orig_category":"Prodotti Chimici Secondari. Medicinali E Prodotti Parafarmaceutici",
    "sg:phone":"+39 0225101",
    "sg:postcode":"20093",
    "sg:province":"Milano",
    "wof:name":"Janssen-cilag S.p.a.",
    "wof:placetype":"venue"
},
  "geometry": {"coordinates":[9.2731714249,45.5342102051],"type":"Point"}
}