{
  "type": "Feature",
  "properties": {
    "iso:country":"IT",
    "sg:address":"07040 Stintino",
    "sg:city":"Stintino",
    "sg:orig_category":"Riparazione Dei Mezzi Di Trasporto. Servizi Ausiliari Dei Mezzi Di Trasporto",
    "sg:phone":"+39 079 523345",
    "sg:postcode":"07040",
    "sg:province":"Sassari",
    "wof:name":"Nautica Benenati Di Nicolino Benenati & C. (s.n.c.)",
    "wof:placetype":"venue"
},
  "geometry": {"coordinates":[8.226574,40.940334],"type":"Point"}
}