{
  "type": "Feature",
  "properties": {
    "iso:country":"IT",
    "sg:address":"20156 Milano",
    "sg:city":"Milano",
    "sg:orig_category":"Servizi E Lavori Per Abbigliamento E Pelletterie",
    "sg:phone":"+39 02 324579",
    "sg:postcode":"20156",
    "sg:province":"Milano",
    "wof:name":"Lavanderia Dry Service",
    "wof:placetype":"venue"
},
  "geometry": {"coordinates":[9.146116,45.494175],"type":"Point"}
}