{
  "type": "Feature",
  "properties": {
    "addr:full":"Via San Martino 7 22070 Castelnuovo Bozzente Castelnuovo Bozzente Como 22070",
    "addr:housenumber":"7;bozzente",
    "addr:postcode":"22070;22070",
    "addr:street":"Via San Martino",
    "iso:country":"IT",
    "sg:address":"Via San Martino 7 22070 Castelnuovo Bozzente",
    "sg:city":"Castelnuovo Bozzente",
    "sg:classifiers":[
        {
            "category":"Building & Trades",
            "subcategory":"Construction",
            "type":"Services"
        }
    ],
    "sg:phone":"+39 031 988476",
    "sg:postcode":"22070",
    "sg:province":"Como",
    "sg:tags":[
        "carpenter's",
        "work",
        "supraregional"
    ],
    "wof:name":"Ferroforma Srl",
    "wof:placetype":"venue"
},
  "geometry": {"coordinates":[8.939444,45.762497],"type":"Point"}
}