{
  "type": "Feature",
  "properties": {
    "addr:full":"00168 Roma Roma Roma 00168",
    "addr:postcode":"00168;00168",
    "iso:country":"IT",
    "sg:address":"00168 Roma",
    "sg:city":"Roma",
    "sg:classifiers":[
        {
            "category":"Health Services",
            "subcategory":"Health Practitioner",
            "type":"Services"
        }
    ],
    "sg:phone":"+39 06 3550 2219",
    "sg:postcode":"00168",
    "sg:province":"Roma",
    "sg:tags":[
        "medici"
    ],
    "wof:name":"Good Living S.r.l.",
    "wof:placetype":"venue"
},
  "geometry": {"coordinates":[12.418636,41.934296],"type":"Point"}
}