{
  "type": "Feature",
  "properties": {
    "iso:country":"IT",
    "sg:address":"00176 Roma",
    "sg:city":"Roma",
    "sg:orig_category":"Servizi Culturali E Per Lo Spettacolo. Arte Ed Artigianato Artistico. Servizi Al Turismo",
    "sg:phone":"+39 06 242 7564",
    "sg:postcode":"00176",
    "sg:province":"Roma",
    "wof:name":"Zeno Arte Srl",
    "wof:placetype":"venue"
},
  "geometry": {"coordinates":[12.537668,41.88372],"type":"Point"}
}