{
  "type": "Feature",
  "properties": {
    "iso:country":"IT",
    "sg:address":"10147 Torino",
    "sg:city":"Torino",
    "sg:orig_category":"Tessuti Arredamento, Tende E Tappeti",
    "sg:phone":"+39 011 295768",
    "sg:postcode":"10147",
    "sg:province":"Torino",
    "wof:name":"Ammirati Vincenzo",
    "wof:placetype":"venue"
},
  "geometry": {"coordinates":[7.678961,45.096855],"type":"Point"}
}