{
  "type": "Feature",
  "properties": {
    "addr:full":"00128 Roma Roma Roma 00128",
    "addr:postcode":"00128;00128",
    "iso:country":"IT",
    "sg:address":"00128 Roma",
    "sg:city":"Roma",
    "sg:orig_category":"Campeggio",
    "sg:phone":"+39 06 508 7912",
    "sg:postcode":"00128",
    "sg:province":"Roma",
    "wof:name":"Bottega Del Campeggiatore Srl",
    "wof:placetype":"venue"
},
  "geometry": {"coordinates":[12.451797,41.791801],"type":"Point"}
}