{
  "type": "Feature",
  "properties": {
    "iso:country":"IT",
    "sg:address":"80147 Napoli",
    "sg:city":"Napoli",
    "sg:orig_category":"Scuole E Servizi Scolastici. Centri Di Estetica E Cosmesi E Servizi. Ricerca, Selezione E Formazione Del Personale",
    "sg:phone":"+39 081 596 4431",
    "sg:postcode":"80147",
    "sg:province":"Napoli",
    "wof:name":"Veneruso Maria Rosaria",
    "wof:placetype":"venue"
},
  "geometry": {"coordinates":[14.206373,40.92894],"type":"Point"}
}