{
  "type": "Feature",
  "properties": {
    "iso:country":"IT",
    "sg:address":"23889 S. Maria Ho\u00e8",
    "sg:orig_category":"Elettricita' Materiali - Produzione",
    "sg:phone":"+39 039 595111",
    "sg:postcode":"23889",
    "sg:province":"Lecco",
    "wof:name":"Giulio Giovenzana Trasformazioni Srl",
    "wof:placetype":"venue"
},
  "geometry": {"coordinates":[9.390071,45.852982],"type":"Point"}
}