{
  "type": "Feature",
  "properties": {
    "iso:country":"IT",
    "sg:address":"25011 Calcinato",
    "sg:city":"Calcinato",
    "sg:orig_category":"Autoscuole",
    "sg:phone":"+39 030 963 6031",
    "sg:postcode":"25011",
    "sg:province":"Brescia",
    "wof:name":"Autoscuola Mori & C. Snc",
    "wof:placetype":"venue"
},
  "geometry": {"coordinates":[10.21676,45.532879],"type":"Point"}
}