{
  "type": "Feature",
  "properties": {
    "iso:country":"IT",
    "sg:address":"03030 Broccostella",
    "sg:city":"Broccostella",
    "sg:orig_category":"Franchising - Servizi E Consulenza",
    "sg:phone":"+39 0776 871600",
    "sg:postcode":"03030",
    "sg:province":"Frosinone",
    "sg:website":"http://www.happyfood.it",
    "wof:name":"Happyfood Corporation Srl",
    "wof:placetype":"venue"
},
  "geometry": {"coordinates":[13.3558101654,41.6406784058],"type":"Point"}
}