{
  "type": "Feature",
  "properties": {
    "iso:country":"IT",
    "sg:address":"Via Paldella 12 47825 Torriana",
    "sg:city":"Torriana",
    "sg:classifiers":[
        {
            "category":"Organizations",
            "subcategory":"Labor Organization",
            "type":"Services"
        }
    ],
    "sg:phone":"+39 0541 675616",
    "sg:postcode":"47825",
    "sg:province":"Rimini",
    "sg:tags":[
        "woodworking",
        "machinery"
    ],
    "sg:website":"www.socomec-snc.com",
    "wof:name":"Socomec Snc",
    "wof:placetype":"venue"
},
  "geometry": {"coordinates":[12.399737,44.000317],"type":"Point"}
}