{
  "type": "Feature",
  "properties": {
    "addr:full":"Via Lambro 47 22045 Lambrugo Lambrugo Como 22045",
    "addr:housenumber":"47",
    "addr:postcode":"22045;22045",
    "addr:street":"Via Lambro",
    "iso:country":"IT",
    "sg:address":"Via Lambro 47 22045 Lambrugo",
    "sg:city":"Lambrugo",
    "sg:classifiers":[
        {
            "category":"Manufacturing",
            "subcategory":"Building Materials",
            "type":"Manufacturing & Wholesale Goods"
        }
    ],
    "sg:phone":"+39 031 608913",
    "sg:postcode":"22045",
    "sg:province":"Como",
    "sg:tags":[
        "polypropylene",
        "pp",
        "fibre"
    ],
    "wof:name":"Gerpa Di Nadia Palmi S.a.s.",
    "wof:placetype":"venue"
},
  "geometry": {"coordinates":[9.2486763,45.7526054382],"type":"Point"}
}