{
  "type": "Feature",
  "properties": {
    "iso:country":"IT",
    "sg:address":"128, Via Naz. Flaminia 61032 Fano",
    "sg:city":"Fano",
    "sg:classifiers":[
        {
            "category":"Shopping",
            "subcategory":"Clothing, Apparel, & Fashions",
            "type":"Retail Goods"
        }
    ],
    "sg:phone":"+39 0721 864322",
    "sg:postcode":"61032",
    "sg:province":"Pesaro E Urbino",
    "sg:tags":[
        "clothes"
    ],
    "wof:name":"Maglificio Gabriella Frattini (s.p.a.)",
    "wof:placetype":"venue"
},
  "geometry": {"coordinates":[12.529803,43.633556],"type":"Point"}
}