{
  "type": "Feature",
  "properties": {
    "addr:full":"Via Roma 62; Limone; 12015 Cuneo 12015",
    "addr:housenumber":"62",
    "addr:postcode":"12015;12015",
    "addr:street":"Via Roma;Limone",
    "iso:country":"IT",
    "sg:address":"Via Roma 62; Limone; 12015",
    "sg:classifiers":[
        {
            "category":"Banks & Credit Unions",
            "subcategory":"Bank",
            "type":"Services"
        }
    ],
    "sg:phone":"+39 0171 92112",
    "sg:postcode":"12015",
    "sg:province":"Cuneo",
    "wof:name":"Cassa Di Risparmio Di Cuneo",
    "wof:placetype":"venue"
},
  "geometry": {"coordinates":[7.576091,44.201004],"type":"Point"}
}