{
  "type": "Feature",
  "properties": {
    "iso:country":"IT",
    "sg:address":"16, Via Mercato Ortofrutticolo 31100 Treviso",
    "sg:city":"Treviso",
    "sg:classifiers":[
        {
            "category":"Food & Beverages",
            "subcategory":"Groceries & Convenience Stores",
            "type":"Retail Goods"
        }
    ],
    "sg:phone":"+39 0422 432820",
    "sg:postcode":"31100",
    "sg:province":"Treviso",
    "sg:tags":[
        "product",
        "related"
    ],
    "wof:name":"Sattin & Camatta (s.r.l.)",
    "wof:placetype":"venue"
},
  "geometry": {"coordinates":[12.2196416855,45.6651000977],"type":"Point"}
}