{
  "type": "Feature",
  "properties": {
    "iso:country":"IT",
    "sg:address":"10067 Vigone",
    "sg:city":"Vigone",
    "sg:orig_category":"Forniture Per Agricoltura E Zootecnia",
    "sg:phone":"+39 011 980 1400",
    "sg:postcode":"10067",
    "sg:province":"Torino",
    "wof:name":"Bessone Arturo",
    "wof:placetype":"venue"
},
  "geometry": {"coordinates":[7.6698637009,44.9892921448],"type":"Point"}
}