{
  "type": "Feature",
  "properties": {
    "iso:country":"IT",
    "sg:address":"22070 Bregnano",
    "sg:city":"Bregnano",
    "sg:orig_category":"Ceramiche E Refrattari - Impianti, Macchine E Materiali",
    "sg:phone":"+39 031 728311",
    "sg:postcode":"22070",
    "sg:province":"Como",
    "sg:website":"http://www.bavelloni.com",
    "wof:name":"Bavelloni Z. Spa",
    "wof:placetype":"venue"
},
  "geometry": {"coordinates":[9.062121,45.708813],"type":"Point"}
}