{
  "type": "Feature",
  "properties": {
    "addr:full":"15076 Ovada Ovada Alessandria 15076",
    "addr:postcode":"15076;15076",
    "iso:country":"IT",
    "sg:address":"15076 Ovada",
    "sg:city":"Ovada",
    "sg:orig_category":"Pompe. Elettrotecnica Industriale, Prodotti E Apparecchiature",
    "sg:phone":"+39 0143 821433",
    "sg:postcode":"15076",
    "sg:province":"Alessandria",
    "wof:name":"Madonna Bruno",
    "wof:placetype":"venue"
},
  "geometry": {"coordinates":[8.637503624,44.6325683594],"type":"Point"}
}