{
  "type": "Feature",
  "properties": {
    "iso:country":"IT",
    "sg:address":"Via G. Matteotti 27 40055 Villanova",
    "sg:city":"Villanova",
    "sg:classifiers":[
        {
            "category":"Health Services",
            "subcategory":"Clinic",
            "type":"Services"
        }
    ],
    "sg:phone":"+39 051 781180",
    "sg:postcode":"40055",
    "sg:province":"Bologna",
    "sg:tags":[
        "dental",
        "chair"
    ],
    "sg:website":"www.cemm.it",
    "wof:name":"C.e.m.m. Costruzioni Elettromeccaniche Medicali Sas",
    "wof:placetype":"venue"
},
  "geometry": {"coordinates":[11.435994,44.499836],"type":"Point"}
}