{
  "type": "Feature",
  "properties": {
    "iso:country":"IT",
    "sg:address":"20146 Milano",
    "sg:city":"Milano",
    "sg:orig_category":"Servizi Editoriali. Pubblicita', Marketing E Comunicazione",
    "sg:phone":"+39 02 477971",
    "sg:postcode":"20146",
    "sg:province":"Milano",
    "wof:name":"Piemme (s.p.a.)",
    "wof:placetype":"venue"
},
  "geometry": {"coordinates":[9.146564,45.455463],"type":"Point"}
}