{
  "type": "Feature",
  "properties": {
    "addr:full":"3, Via Starza 80054 Gragnano Gragnano Napoli 80054",
    "addr:postcode":"80054;80054",
    "addr:street":"Via Starza",
    "iso:country":"IT",
    "sg:address":"3, Via Starza 80054 Gragnano",
    "sg:city":"Gragnano",
    "sg:classifiers":[
        {
            "category":"Parking",
            "subcategory":"Lot",
            "type":"Transportation"
        }
    ],
    "sg:phone":"+39 081 801 2900",
    "sg:postcode":"80054",
    "sg:province":"Napoli",
    "sg:tags":[
        "transport",
        "road"
    ],
    "wof:name":"Cesarano Trasporti Funebri (s.r.l.)",
    "wof:placetype":"venue"
},
  "geometry": {"coordinates":[14.518078,40.697124],"type":"Point"}
}