{
  "type": "Feature",
  "properties": {
    "addr:full":"39, Via Emilia 43010 Fontevivo Fontevivo Parma 43010",
    "addr:postcode":"43010;43010",
    "addr:street":"Via Emilia",
    "iso:country":"IT",
    "sg:address":"39, Via Emilia 43010 Fontevivo",
    "sg:city":"Fontevivo",
    "sg:classifiers":[
        {
            "category":"Shopping",
            "type":"Retail Goods"
        }
    ],
    "sg:phone":"+39 0521 619249",
    "sg:postcode":"43010",
    "sg:province":"Parma",
    "sg:tags":[
        "finished",
        "-",
        "metallic"
    ],
    "wof:name":"G.b.a. Costruzioni (s.r.l.)",
    "wof:placetype":"venue"
},
  "geometry": {"coordinates":[10.208902359,44.8258018494],"type":"Point"}
}