{
  "type": "Feature",
  "properties": {
    "iso:country":"IT",
    "sg:address":"25064 Gussago",
    "sg:city":"Gussago",
    "sg:orig_category":"Prodotti Alimentari. Agricoltura, Orticoltura E Floricoltura",
    "sg:phone":"+39 030 277 0184",
    "sg:postcode":"25064",
    "sg:province":"Brescia",
    "wof:name":"Dolcitalia Funghitalia Di Colombi & C. Snc",
    "wof:placetype":"venue"
},
  "geometry": {"coordinates":[10.1576051712,45.5762748718],"type":"Point"}
}