{
  "type": "Feature",
  "properties": {
    "iso:country":"IT",
    "sg:address":"8, Via Di Giorgio Martini Francesco 74100 Taranto",
    "sg:city":"Taranto",
    "sg:classifiers":[
        {
            "category":"Professional",
            "subcategory":"Engineering",
            "type":"Services"
        }
    ],
    "sg:phone":"+39 099 471 4105",
    "sg:postcode":"74100",
    "sg:province":"Taranto",
    "sg:tags":[
        "machine",
        "-",
        "mechanical"
    ],
    "wof:name":"C.m.i. Sud Srl",
    "wof:placetype":"venue"
},
  "geometry": {"coordinates":[17.240009,40.469238],"type":"Point"}
}