{
  "type": "Feature",
  "properties": {
    "iso:country":"IT",
    "sg:address":"50054 Fucecchio",
    "sg:city":"Fucecchio",
    "sg:classifiers":[
        {
            "category":"Retail",
            "subcategory":"Auto Repair",
            "type":"Services"
        }
    ],
    "sg:phone":"+39 0571 20147",
    "sg:postcode":"50054",
    "sg:province":"Firenze",
    "sg:tags":[
        "articles",
        "product",
        "components",
        "industry",
        "vehicles",
        "rubber",
        "part",
        "spare",
        "motor",
        "works"
    ],
    "wof:name":"Centro Pneus Srl",
    "wof:placetype":"venue"
},
  "geometry": {"coordinates":[10.788723,43.765724],"type":"Point"}
}