{
  "type": "Feature",
  "properties": {
    "iso:country":"IT",
    "sg:address":"50027 Greve In Chianti",
    "sg:city":"Greve in Chianti",
    "sg:orig_category":"Ceramiche Artistiche - Produzione E Ingrosso",
    "sg:phone":"+39 055 854 7305",
    "sg:postcode":"50027",
    "sg:province":"Firenze",
    "wof:name":"La Chimera Di Gheri Massimo & Panconi Simone Snc",
    "wof:placetype":"venue"
},
  "geometry": {"coordinates":[11.298441,43.657433],"type":"Point"}
}