{
  "type": "Feature",
  "properties": {
    "addr:full":"65125 Pescara Pescara Pescara 65125",
    "addr:postcode":"65125;65125",
    "iso:country":"IT",
    "sg:address":"65125 Pescara",
    "sg:city":"Pescara",
    "sg:orig_category":"Cartotecnica E Servizi. Composizione, Stampa E Confezione. Forniture E Prodotti Informatici. Forniture Per Congressi, Fiere E Manifestazioni",
    "sg:phone":"+39 085 75886",
    "sg:postcode":"65125",
    "sg:province":"Pescara",
    "wof:name":"Bold Sas",
    "wof:placetype":"venue"
},
  "geometry": {"coordinates":[14.175657,42.479721],"type":"Point"}
}