{
  "type": "Feature",
  "properties": {
    "iso:country":"IT",
    "sg:address":"03100 Frosinone",
    "sg:city":"Frosinone",
    "sg:orig_category":"Servizi E Lavori Per Edilizia E Lavori Pubblici. Servizi E Lavori Per Ecologia E Smaltimento Rifiuti",
    "sg:phone":"+39 0775 294481",
    "sg:postcode":"03100",
    "sg:province":"Frosinone",
    "wof:name":"Aerospurgo Di Rizzi & C. Snc",
    "wof:placetype":"venue"
},
  "geometry": {"coordinates":[13.347178,41.643112],"type":"Point"}
}