{
  "type": "Feature",
  "properties": {
    "addr:full":"73, Via Valmarana Elena 35133 Padova Padova Padova 35133",
    "addr:postcode":"35133;35133",
    "addr:street":"Via Valmarana Elena",
    "iso:country":"IT",
    "sg:address":"73, Via Valmarana Elena 35133 Padova",
    "sg:city":"Padova",
    "sg:classifiers":[
        {
            "category":"Manufacturing",
            "subcategory":"Wood Products",
            "type":"Manufacturing & Wholesale Goods"
        }
    ],
    "sg:phone":"+39 39049605241",
    "sg:postcode":"35133",
    "sg:province":"Padova",
    "sg:tags":[
        "furniture"
    ],
    "wof:name":"O.v. Ra Di Vigolo Walter (s.n.c.)",
    "wof:placetype":"venue"
},
  "geometry": {"coordinates":[11.844167,45.397499],"type":"Point"}
}