{
  "type": "Feature",
  "properties": {
    "iso:country":"IT",
    "sg:address":"14100 Asti",
    "sg:city":"Asti",
    "sg:orig_category":"Ospedali E Servizi Sanitari",
    "sg:phone":"+39 0141 271214",
    "sg:postcode":"14100",
    "sg:province":"Asti",
    "wof:name":"Casa Di Cura S. Anna Spa",
    "wof:placetype":"venue"
},
  "geometry": {"coordinates":[8.200055,44.937271],"type":"Point"}
}