{
  "type": "Feature",
  "properties": {
    "addr:full":"57, Via Parmesana 36010 Monticello Conte Otto Monticello Conte Otto Vicenza 36010",
    "addr:postcode":"36010;36010",
    "addr:street":"Via Parmesana",
    "iso:country":"IT",
    "sg:address":"57, Via Parmesana 36010 Monticello Conte Otto",
    "sg:city":"Monticello Conte Otto",
    "sg:classifiers":[
        {
            "category":"Shopping",
            "type":"Retail Goods"
        }
    ],
    "sg:phone":"+39 0444 946350",
    "sg:postcode":"36010",
    "sg:province":"Vicenza",
    "sg:tags":[
        "finished",
        "-",
        "metallic"
    ],
    "wof:name":"Officine Meccaniche Zoppelletto S.p.a.",
    "wof:placetype":"venue"
},
  "geometry": {"coordinates":[11.573559761,45.608707428],"type":"Point"}
}