{
  "type": "Feature",
  "properties": {
    "iso:country":"IT",
    "sg:address":"Via Ficora Di Morra S. N. 86079 Venafro",
    "sg:city":"Venafro",
    "sg:classifiers":[
        {
            "category":"Shopping",
            "subcategory":"Crafts & Fabrics",
            "type":"Retail Goods"
        }
    ],
    "sg:phone":"+39 0865 900490",
    "sg:postcode":"86079",
    "sg:province":"Isernia",
    "sg:tags":[
        "textile",
        "machinery",
        "accessory"
    ],
    "sg:website":"www.imatsrl.it",
    "wof:name":"Industria Meridionale Accessori Tessili I.m.a.t. Srl",
    "wof:placetype":"venue"
},
  "geometry": {"coordinates":[14.065169,41.466328],"type":"Point"}
}