{
  "type": "Feature",
  "properties": {
    "addr:full":"5, Via Cilea Francesco 81100 Caserta Caserta Caserta 81100",
    "addr:postcode":"81100;81100",
    "addr:street":"Via Cilea Francesco",
    "iso:country":"IT",
    "sg:address":"5, Via Cilea Francesco 81100 Caserta",
    "sg:city":"Caserta",
    "sg:classifiers":[
        {
            "category":"Manufacturing",
            "subcategory":"Metals",
            "type":"Manufacturing & Wholesale Goods"
        }
    ],
    "sg:phone":"+39 0823 343804",
    "sg:postcode":"81100",
    "sg:province":"Caserta",
    "sg:tags":[
        "metallurgy",
        "metalworking"
    ],
    "wof:name":"Metacarb S.r.l.",
    "wof:placetype":"venue"
},
  "geometry": {"coordinates":[14.3030128479,41.0330581665],"type":"Point"}
}