{
  "type": "Feature",
  "properties": {
    "addr:full":"00165 Roma Roma Roma 00165",
    "addr:postcode":"00165;00165",
    "iso:country":"IT",
    "sg:address":"00165 Roma",
    "sg:city":"Roma",
    "sg:orig_category":"Fisiokinesiterapia",
    "sg:phone":"+39 06 638 1781",
    "sg:postcode":"00165",
    "sg:province":"Roma",
    "wof:name":"Di Giacomo Sergio",
    "wof:placetype":"venue"
},
  "geometry": {"coordinates":[12.4459295273,41.8075065613],"type":"Point"}
}