{
  "type": "Feature",
  "properties": {
    "addr:full":"10072 Caselle Torinese Caselle Torinese Torino 10072",
    "addr:postcode":"10072;10072",
    "iso:country":"IT",
    "sg:address":"10072 Caselle Torinese",
    "sg:city":"Caselle Torinese",
    "sg:orig_category":"Biciclette - Vendita Al Dettaglio E Riparazione",
    "sg:phone":"+39 011 996 8450",
    "sg:postcode":"10072",
    "sg:province":"Torino",
    "wof:name":"Cicli Drigani Di Drigani Livio",
    "wof:placetype":"venue"
},
  "geometry": {"coordinates":[7.699691,45.155518],"type":"Point"}
}