{
  "type": "Feature",
  "properties": {
    "addr:full":"Via Locarno 2 21017 Samarate Samarate Varese 21017",
    "addr:housenumber":"2",
    "addr:postcode":"21017;21017",
    "addr:street":"Via Locarno",
    "iso:country":"IT",
    "sg:address":"Via Locarno 2 21017 Samarate",
    "sg:city":"Samarate",
    "sg:classifiers":[
        {
            "category":"Shopping",
            "subcategory":"Clothing, Apparel, & Fashions",
            "type":"Retail Goods"
        }
    ],
    "sg:phone":"+39 0331 220157",
    "sg:postcode":"21017",
    "sg:province":"Varese",
    "sg:tags":[
        "image",
        "clothing",
        "basic"
    ],
    "sg:website":"www.itmfashion.it",
    "wof:name":"Itm Fashion Srl",
    "wof:placetype":"venue"
},
  "geometry": {"coordinates":[8.788399,45.634518],"type":"Point"}
}