{
  "type": "Feature",
  "properties": {
    "addr:full":"116, Via Vangile 51010 Massa E Cozzile Massa e Cozzile Pistoia 51010",
    "addr:housenumber":"116",
    "addr:postcode":"51010;51010",
    "addr:street":"Via Vangile",
    "iso:country":"IT",
    "sg:address":"116, Via Vangile 51010 Massa E Cozzile",
    "sg:city":"Massa e Cozzile",
    "sg:classifiers":[
        {
            "category":"Professional",
            "subcategory":"Engineering",
            "type":"Services"
        }
    ],
    "sg:phone":"+39 0572 772134",
    "sg:postcode":"51010",
    "sg:province":"Pistoia",
    "sg:tags":[
        "machine",
        "-",
        "mechanical"
    ],
    "wof:name":"O.m.t. S.r.l.",
    "wof:placetype":"venue"
},
  "geometry": {"coordinates":[10.75188,43.896717],"type":"Point"}
}