{
  "type": "Feature",
  "properties": {
    "addr:full":"37136 Verona Verona Verona 37136",
    "addr:postcode":"37136;37136",
    "iso:country":"IT",
    "sg:address":"37136 Verona",
    "sg:city":"Verona",
    "sg:orig_category":"Telecomunicazioni E Telefonia, Impianti, Apparecchi E Servizi",
    "sg:phone":"+39 045 500399",
    "sg:postcode":"37136",
    "sg:province":"Verona",
    "wof:name":"Aemmetel Srl",
    "wof:placetype":"venue"
},
  "geometry": {"coordinates":[10.945527,45.399555],"type":"Point"}
}