{
  "type": "Feature",
  "properties": {
    "addr:full":"Via Resistenza 119 53035 Monteriggioni Monteriggioni Siena 53035",
    "addr:housenumber":"119",
    "addr:postcode":"53035;53035",
    "addr:street":"Via Resistenza",
    "iso:country":"IT",
    "sg:address":"Via Resistenza 119 53035 Monteriggioni",
    "sg:city":"Monteriggioni",
    "sg:classifiers":[
        {
            "category":"Science Facility",
            "type":"Public Place"
        }
    ],
    "sg:phone":"+39 0577 309143",
    "sg:postcode":"53035",
    "sg:province":"Siena",
    "sg:tags":[
        "equipment",
        "analysis"
    ],
    "sg:website":"www.kwkw.it",
    "wof:name":"Kw Apparecchi Scientifici Srl",
    "wof:placetype":"venue"
},
  "geometry": {"coordinates":[11.274549,43.382835],"type":"Point"}
}