{
  "type": "Feature",
  "properties": {
    "iso:country":"IT",
    "sg:address":"20020 Cogliate",
    "sg:city":"Cogliate",
    "sg:orig_category":"Macchine Utensili E Impianti",
    "sg:phone":"+39 02 966 0685",
    "sg:postcode":"20020",
    "sg:province":"Milano",
    "wof:name":"Tresso Luciano",
    "wof:placetype":"venue"
},
  "geometry": {"coordinates":[9.082037,45.644516],"type":"Point"}
}