{
  "type": "Feature",
  "properties": {
    "iso:country":"IT",
    "sg:address":"Via Ghiaia 28 37053 Cerea",
    "sg:city":"Cerea",
    "sg:classifiers":[
        {
            "category":"Bus Stop",
            "subcategory":"None",
            "type":"Transportation"
        }
    ],
    "sg:phone":"+39 0442 375130",
    "sg:postcode":"37053",
    "sg:province":"Verona",
    "sg:tags":[
        "period",
        "furniture"
    ],
    "wof:name":"Real Stil Mobili Srl",
    "wof:placetype":"venue"
},
  "geometry": {"coordinates":[11.2372140884,45.173286438],"type":"Point"}
}