{
  "type": "Feature",
  "properties": {
    "iso:country":"IT",
    "sg:address":"108/e, Via Roma 20060 Cassina De' Pecchi",
    "sg:classifiers":[
        {
            "category":"Professional",
            "subcategory":"Computer Services",
            "type":"Services"
        }
    ],
    "sg:phone":"+39 02 9530 0421",
    "sg:postcode":"20060",
    "sg:province":"Milano",
    "sg:tags":[
        "information",
        "technology"
    ],
    "wof:name":"Software Ag Italia Spa",
    "wof:placetype":"venue"
},
  "geometry": {"coordinates":[9.328653,45.501827],"type":"Point"}
}