{
  "type": "Feature",
  "properties": {
    "addr:full":"36010 Velo D'astico Velo Vicenza 36010",
    "addr:postcode":"36010;36010",
    "iso:country":"IT",
    "sg:address":"36010 Velo D'astico",
    "sg:city":"Velo",
    "sg:orig_category":"Servizi E Lavori Per Ecologia E Smaltimento Rifiuti. Macchine E Forniture Per Ecologia E Smaltimento Rifiuti",
    "sg:phone":"+39 0445 731000",
    "sg:postcode":"36010",
    "sg:province":"Vicenza",
    "sg:website":"http://www.indest.it",
    "wof:name":"Indest Srl",
    "wof:placetype":"venue"
},
  "geometry": {"coordinates":[11.38465,45.79644],"type":"Point"}
}