{
  "type": "Feature",
  "properties": {
    "iso:country":"IT",
    "sg:address":"12, Via M.m. Boiardo 42011 Bagnolo In Piano",
    "sg:classifiers":[
        {
            "category":"Professional",
            "subcategory":"Engineering",
            "type":"Services"
        }
    ],
    "sg:phone":"+39 0522 957017",
    "sg:postcode":"42011",
    "sg:province":"Reggio Nell'Emilia",
    "sg:tags":[
        "machine",
        "-",
        "mechanical"
    ],
    "wof:name":"Lead Time Machining (s.r.l.)",
    "wof:placetype":"venue"
},
  "geometry": {"coordinates":[10.667109,44.757908],"type":"Point"}
}