{
  "type": "Feature",
  "properties": {
    "addr:full":"Via Zalloni 27 40066 Pieve Di Cento Pieve di Cento Bologna 40066",
    "addr:housenumber":"27",
    "addr:postcode":"40066;bologna 40066",
    "addr:street":"Via Zalloni",
    "iso:country":"IT",
    "sg:address":"Via Zalloni 27 40066 Pieve Di Cento",
    "sg:city":"Pieve di Cento",
    "sg:orig_category":"High-voltage Plug-type Connectors",
    "sg:phone":"+39 051 973032",
    "sg:postcode":"40066",
    "sg:province":"Bologna",
    "sg:website":"www.e-p.it",
    "wof:name":"E. P. Produzioni Elettroniche Di Br Egoli Gianpaolo",
    "wof:placetype":"venue"
},
  "geometry": {"coordinates":[11.346481,44.494221],"type":"Point"}
}