{
  "type": "Feature",
  "properties": {
    "iso:country":"IT",
    "sg:address":"50018 Scandicci",
    "sg:city":"Scandicci",
    "sg:orig_category":"Articoli Per Imballaggio E Confezionamento",
    "sg:phone":"+39 055 720528",
    "sg:postcode":"50018",
    "sg:province":"Firenze",
    "wof:name":"Sacchettificio Dessolini Piero",
    "wof:placetype":"venue"
},
  "geometry": {"coordinates":[11.159805,43.766712],"type":"Point"}
}