{
  "type": "Feature",
  "properties": {
    "addr:full":"20121 Milano Milano Milano 20121",
    "addr:postcode":"20121;20121",
    "iso:country":"IT",
    "sg:address":"20121 Milano",
    "sg:city":"Milano",
    "sg:orig_category":"Forniture Per Abbigliamento E Pelletterie",
    "sg:phone":"+39 02 7600 0658",
    "sg:postcode":"20121",
    "sg:province":"Milano",
    "wof:name":"Ortolani (s.n.c.)",
    "wof:placetype":"venue"
},
  "geometry": {"coordinates":[9.1956310272,45.471244812],"type":"Point"}
}