{
  "type": "Feature",
  "properties": {
    "addr:full":"20135 Milano Milano Milano 20135",
    "addr:postcode":"20135;20135",
    "iso:country":"IT",
    "sg:address":"20135 Milano",
    "sg:city":"Milano",
    "sg:orig_category":"Prodotti E Manufatti In Materie Plastiche. Forniture Per Edilizia E Lavori Pubblici. Forniture E Materiali Per Imballaggio E Confezionamento",
    "sg:phone":"+39 02 5990 3767",
    "sg:postcode":"20135",
    "sg:province":"Milano",
    "wof:name":"Tihla Aurora Mihaela",
    "wof:placetype":"venue"
},
  "geometry": {"coordinates":[9.2017345428,45.4693717957],"type":"Point"}
}