{
  "type": "Feature",
  "properties": {
    "iso:country":"IT",
    "sg:address":"C Cobianchi 32; Verbania; 28044",
    "sg:classifiers":[
        {
            "category":"Banks & Credit Unions",
            "subcategory":"Bank",
            "type":"Services"
        }
    ],
    "sg:phone":"+39 0323 403445",
    "wof:name":"Banca Popolare Di Intra Scarl",
    "wof:placetype":"venue"
},
  "geometry": {"coordinates":[8.574607,45.938816],"type":"Point"}
}