{
  "type": "Feature",
  "properties": {
    "iso:country":"IT",
    "sg:address":"03014 Fiuggi",
    "sg:city":"Fiuggi",
    "sg:orig_category":"Tappezzieri In Stoffa E Pelle",
    "sg:phone":"+39 0775 514077",
    "sg:postcode":"03014",
    "sg:province":"Frosinone",
    "wof:name":"Pietrobono Mario - Tappezzeria Artigiana",
    "wof:placetype":"venue"
},
  "geometry": {"coordinates":[13.231723,41.813267],"type":"Point"}
}