{
  "type": "Feature",
  "properties": {
    "addr:full":"Via Rovereto, 1 - Motta 36030 Costabissara Costabissara Vicenza 36030",
    "addr:housenumber":"1",
    "addr:postcode":"36030;36030",
    "addr:street":"Via Rovereto",
    "iso:country":"IT",
    "sg:address":"Via Rovereto, 1 - Motta 36030 Costabissara",
    "sg:city":"Costabissara",
    "sg:classifiers":[
        {
            "category":"Home & Garden",
            "subcategory":"Building Materials",
            "type":"Retail Goods"
        }
    ],
    "sg:phone":"+39 0444 971734",
    "sg:postcode":"36030",
    "sg:province":"Vicenza",
    "sg:tags":[
        "installation",
        "electric"
    ],
    "wof:name":"Elettrica Vicentina Spa",
    "wof:placetype":"venue"
},
  "geometry": {"coordinates":[11.492288,45.604259],"type":"Point"}
}