{
  "type": "Feature",
  "properties": {
    "iso:country":"IT",
    "sg:address":"37036 San Martino Buon Albergo",
    "sg:city":"San Martino Buon Albergo",
    "sg:orig_category":"Lavorazioni Metalli, Stampaggio E Saldatura",
    "sg:phone":"+39 045 990426",
    "sg:postcode":"37036",
    "sg:province":"Verona",
    "wof:name":"O.m.l. Srl",
    "wof:placetype":"venue"
},
  "geometry": {"coordinates":[11.089601,45.417683],"type":"Point"}
}