{
  "type": "Feature",
  "properties": {
    "addr:full":"Via Recanatese 60022 Castelfidardo Castelfidardo Ancona 60022",
    "addr:postcode":"60022;60022",
    "addr:street":"Via Recanatese",
    "iso:country":"IT",
    "sg:address":"Via Recanatese 60022 Castelfidardo",
    "sg:city":"Castelfidardo",
    "sg:classifiers":[
        {
            "category":"Manufacturing",
            "subcategory":"Rubber & Plastics",
            "type":"Manufacturing & Wholesale Goods"
        }
    ],
    "sg:phone":"+39 071 720 6596",
    "sg:postcode":"60022",
    "sg:province":"Ancona",
    "wof:name":"Gimani Di Papa F. & C.snc",
    "wof:placetype":"venue"
},
  "geometry": {"coordinates":[13.5342502594,43.4493789673],"type":"Point"}
}