{
  "type": "Feature",
  "properties": {
    "addr:full":"10098 Rivoli Rivoli Torino 10098",
    "addr:postcode":"10098;10098",
    "iso:country":"IT",
    "sg:address":"10098 Rivoli",
    "sg:city":"Rivoli",
    "sg:orig_category":"Servizi E Lavori Per Arredamento E Industria Del Legno. Servizi Di Magazzinaggio E Movimentazione",
    "sg:phone":"+39 011 956 4493",
    "sg:postcode":"10098",
    "sg:province":"Torino",
    "wof:name":"Cooperativa Ze.da R.l.",
    "wof:placetype":"venue"
},
  "geometry": {"coordinates":[7.669185,45.036247],"type":"Point"}
}