{
  "type": "Feature",
  "properties": {
    "iso:country":"IT",
    "sg:address":"98, Via Matteotti Giacomo 31029 Vittorio Veneto",
    "sg:city":"Vittorio Veneto",
    "sg:classifiers":[
        {
            "category":"Wholesale",
            "subcategory":"Medical Equipment & Supplies",
            "type":"Manufacturing & Wholesale Goods"
        }
    ],
    "sg:phone":"+39 0438 555573",
    "sg:postcode":"31029",
    "sg:province":"Treviso",
    "sg:tags":[
        "-",
        "health",
        "instrument"
    ],
    "wof:name":"Diadent (s.r.l.)",
    "wof:placetype":"venue"
},
  "geometry": {"coordinates":[12.242072,45.666286],"type":"Point"}
}