{
  "type": "Feature",
  "properties": {
    "addr:full":"32, Via Azzi Enrico 31038 Paese Paese Treviso 31038",
    "addr:postcode":"31038;31038",
    "addr:street":"Via Azzi Enrico",
    "iso:country":"IT",
    "sg:address":"32, Via Azzi Enrico 31038 Paese",
    "sg:city":"Paese",
    "sg:classifiers":[
        {
            "category":"Manufacturing",
            "subcategory":"Lumber",
            "type":"Manufacturing & Wholesale Goods"
        }
    ],
    "sg:phone":"+39 0422 431575",
    "sg:postcode":"31038",
    "sg:province":"Treviso",
    "sg:tags":[
        "wood"
    ],
    "wof:name":"Unione Veneta Tranciati (s.r.l.)",
    "wof:placetype":"venue"
},
  "geometry": {"coordinates":[12.192896,45.690689],"type":"Point"}
}