{
  "type": "Feature",
  "properties": {
    "iso:country":"IT",
    "sg:address":"80073 Capri",
    "sg:city":"Capri",
    "sg:orig_category":"Prodotti Alimentari",
    "sg:phone":"+39 081 837 5298",
    "sg:postcode":"80073",
    "sg:province":"Napoli",
    "wof:name":"Un Tocco Di Classe Di Esposito S.",
    "wof:placetype":"venue"
},
  "geometry": {"coordinates":[14.2382259369,40.5538635254],"type":"Point"}
}