{
  "type": "Feature",
  "properties": {
    "iso:country":"IT",
    "sg:address":"31053 Pieve Di Soligo",
    "sg:city":"Pieve di Soligo",
    "sg:orig_category":"Arredamenti E Mobili Professionali. Forniture Per Il Settore Dello Spettacolo",
    "sg:phone":"+39 0438 981358",
    "sg:postcode":"31053",
    "sg:province":"Treviso",
    "wof:name":"Lorenzon Marcello",
    "wof:placetype":"venue"
},
  "geometry": {"coordinates":[12.167367,45.90255],"type":"Point"}
}