{
  "type": "Feature",
  "properties": {
    "iso:country":"IT",
    "sg:address":"19, Via Cerreto 43035 Felino",
    "sg:city":"Felino",
    "sg:classifiers":[
        {
            "category":"Food & Beverages",
            "subcategory":"Groceries & Convenience Stores",
            "type":"Retail Goods"
        }
    ],
    "sg:phone":"+39 0521 835680",
    "sg:postcode":"43035",
    "sg:province":"Parma",
    "sg:tags":[
        "product",
        "related"
    ],
    "wof:name":"Prosciuttificio Cerreto (s.r.l.)",
    "wof:placetype":"venue"
},
  "geometry": {"coordinates":[10.2509527206,44.7043685913],"type":"Point"}
}