{
  "type": "Feature",
  "properties": {
    "iso:country":"IT",
    "sg:address":"41011 Campogalliano",
    "sg:city":"Campogalliano",
    "sg:orig_category":"Macchine E Forniture Per Arredamento E Industria Del Legno. Utensili Meccanici E Materiali",
    "sg:phone":"+39 059 851132",
    "sg:postcode":"41011",
    "sg:province":"Modena",
    "wof:name":"Officina C.m.l. Sas",
    "wof:placetype":"venue"
},
  "geometry": {"coordinates":[10.845345,44.698681],"type":"Point"}
}