{
  "type": "Feature",
  "properties": {
    "addr:full":"39100 Bolzano Bolzano Bolzano/Bozen 39100",
    "addr:postcode":"39100;39100",
    "iso:country":"IT",
    "sg:address":"39100 Bolzano",
    "sg:city":"Bolzano",
    "sg:orig_category":"Mobili - Produzione E Ingrosso",
    "sg:phone":"+39 0471 982256",
    "sg:postcode":"39100",
    "sg:province":"Bolzano/Bozen",
    "wof:name":"Dado Srl - Gmbh",
    "wof:placetype":"venue"
},
  "geometry": {"coordinates":[11.3618354797,46.5006942749],"type":"Point"}
}