{
  "type": "Feature",
  "properties": {
    "addr:full":"10149 Torino Torino Torino 10149",
    "addr:postcode":"10149;10149",
    "iso:country":"IT",
    "sg:address":"10149 Torino",
    "sg:city":"Torino",
    "sg:orig_category":"Forniture Per Uffici",
    "sg:phone":"+39 011 730521",
    "sg:postcode":"10149",
    "sg:province":"Torino",
    "wof:name":"Sacchi Ing. M. Sacchi Srl",
    "wof:placetype":"venue"
},
  "geometry": {"coordinates":[7.6585736275,45.1010665894],"type":"Point"}
}