{
  "type": "Feature",
  "properties": {
    "iso:country":"IT",
    "sg:address":"55020 Diecimo",
    "sg:orig_category":"Macchine, Impianti E Forniture Per Industria Grafica, Cartaria E Cartotecnica",
    "sg:postcode":"55020",
    "sg:province":"Lucca",
    "wof:name":"Italconverting Spa",
    "wof:placetype":"venue"
},
  "geometry": {"coordinates":[10.50852,43.961399],"type":"Point"}
}