{
  "type": "Feature",
  "properties": {
    "addr:full":"00169 Roma Roma Roma 00169",
    "addr:postcode":"00169;00169",
    "iso:country":"IT",
    "sg:address":"00169 Roma",
    "sg:city":"Roma",
    "sg:orig_category":"Scuole E Servizi Scolastici",
    "sg:phone":"+39 06 260622",
    "sg:postcode":"00169",
    "sg:province":"Roma",
    "wof:name":"Scuola Nostra Signora Del Suffragio",
    "wof:placetype":"venue"
},
  "geometry": {"coordinates":[12.593307,41.869179],"type":"Point"}
}