{
  "type": "Feature",
  "properties": {
    "addr:full":"24064 Grumello Del Monte Grumello del Monte Bergamo 24064",
    "addr:postcode":"24064;24064",
    "iso:country":"IT",
    "sg:address":"24064 Grumello Del Monte",
    "sg:city":"Grumello del Monte",
    "sg:classifiers":[
        {
            "category":"Shopping",
            "subcategory":"Jewelry",
            "type":"Retail Goods"
        }
    ],
    "sg:phone":"+39 035 831920",
    "sg:postcode":"24064",
    "sg:province":"Bergamo",
    "sg:tags":[
        "watchmaker",
        "jewelers",
        "gold",
        "silversmith"
    ],
    "sg:website":"http://www.castelplast.it",
    "wof:name":"Castelplast Spa",
    "wof:placetype":"venue"
},
  "geometry": {"coordinates":[9.872783,45.643402],"type":"Point"}
}