{
  "type": "Feature",
  "properties": {
    "addr:full":"2, Via Correnti Cesare 21100 Varese Varese Varese 21100",
    "addr:postcode":"21100;21100",
    "addr:street":"Via Correnti Cesare",
    "iso:country":"IT",
    "sg:address":"2, Via Correnti Cesare 21100 Varese",
    "sg:city":"Varese",
    "sg:classifiers":[
        {
            "category":"Personal",
            "subcategory":"Shoe Repair & Shine",
            "type":"Services"
        }
    ],
    "sg:phone":"+39 0332 811304",
    "sg:postcode":"21100",
    "sg:province":"Varese",
    "sg:tags":[
        "leather"
    ],
    "wof:name":"Valascoli S.r.l.",
    "wof:placetype":"venue"
},
  "geometry": {"coordinates":[8.826385,45.817604],"type":"Point"}
}