{
  "type": "Feature",
  "properties": {
    "iso:country":"IT",
    "sg:address":"20129 Milano",
    "sg:city":"Milano",
    "sg:classifiers":[
        {
            "category":"Health Services",
            "subcategory":"Health Practitioner",
            "type":"Services"
        }
    ],
    "sg:phone":"+39 02 738 4901",
    "sg:postcode":"20129",
    "sg:province":"Milano",
    "sg:tags":[
        "medici"
    ],
    "wof:name":"Casellato Aldo",
    "wof:placetype":"venue"
},
  "geometry": {"coordinates":[9.280231,45.498951],"type":"Point"}
}