{
  "type": "Feature",
  "properties": {
    "iso:country":"IT",
    "sg:address":"20146 Milano",
    "sg:city":"Milano",
    "sg:orig_category":"Impiantistica E Prodotti Tecnologici Per Edilizia. Elettronica Professionale E Di Consumo",
    "sg:phone":"+39 02 423 5133",
    "sg:postcode":"20146",
    "sg:province":"Milano",
    "wof:name":"Marchesi Gianluigi",
    "wof:placetype":"venue"
},
  "geometry": {"coordinates":[9.141349,45.44994],"type":"Point"}
}