{
  "type": "Feature",
  "properties": {
    "iso:country":"IT",
    "sg:address":"52100 Arezzo",
    "sg:city":"Arezzo",
    "sg:orig_category":"Centri Di Estetica E Cosmesi E Servizi",
    "sg:phone":"+39 0575 24615",
    "sg:postcode":"52100",
    "sg:province":"Arezzo",
    "wof:name":"Coiffeur Diffusion Di Robillard Philippe",
    "wof:placetype":"venue"
},
  "geometry": {"coordinates":[11.879035,43.462555],"type":"Point"}
}