{
  "type": "Feature",
  "properties": {
    "addr:full":"16149 Genova Genova Genova 16149",
    "addr:postcode":"16149;16149",
    "iso:country":"IT",
    "sg:address":"16149 Genova",
    "sg:city":"Genova",
    "sg:orig_category":"Macchine E Forniture Per Ecologia E Smaltimento Rifiuti. Forniture Per Attivita' Industriali",
    "sg:phone":"+39 010 465140",
    "sg:postcode":"16149",
    "sg:province":"Genova",
    "wof:name":"Belguardi Srl",
    "wof:placetype":"venue"
},
  "geometry": {"coordinates":[8.888069,44.967991],"type":"Point"}
}