{
  "type": "Feature",
  "properties": {
    "iso:country":"IT",
    "sg:address":"Via Berruti Giuseppe 4/6 10146 Torino",
    "sg:city":"Torino",
    "sg:classifiers":[
        {
            "category":"Home & Garden",
            "subcategory":"Carpets & Floor Coverings",
            "type":"Retail Goods"
        }
    ],
    "sg:phone":"+39 011 712661",
    "sg:postcode":"10146",
    "sg:province":"Torino",
    "sg:tags":[
        "flooring",
        "parquet"
    ],
    "wof:name":"Iozzia Palchetti Snc Di Iozzia & C.",
    "wof:placetype":"venue"
},
  "geometry": {"coordinates":[7.6866188049,45.0705604553],"type":"Point"}
}