{
  "type": "Feature",
  "properties": {
    "iso:country":"IT",
    "sg:address":"42049 Sant'ilario D'enza",
    "sg:orig_category":"Prodotti Vari In Metallo. Articoli Per Imballaggio E Confezionamento",
    "sg:phone":"+39 0522 672712",
    "sg:postcode":"42049",
    "sg:province":"Reggio Nell'Emilia",
    "wof:name":"Bonaretti Giorgio",
    "wof:placetype":"venue"
},
  "geometry": {"coordinates":[10.448800087,44.7266426086],"type":"Point"}
}