{
  "type": "Feature",
  "properties": {
    "iso:country":"IT",
    "sg:address":"236, Via Nazionale 84012 Angri",
    "sg:city":"Angri",
    "sg:classifiers":[
        {
            "category":"Farming",
            "subcategory":"Livestock Farm",
            "type":"Manufacturing & Wholesale Goods"
        }
    ],
    "sg:phone":"+39 39081948366",
    "sg:postcode":"84012",
    "sg:province":"Salerno",
    "sg:tags":[
        "agriculture"
    ],
    "wof:name":"Feger Di Gerardo Ferraioli S.p.a.",
    "wof:placetype":"venue"
},
  "geometry": {"coordinates":[14.574234,40.748489],"type":"Point"}
}