{
  "type": "Feature",
  "properties": {
    "iso:country":"IT",
    "sg:address":"Via Botticelli 12 28010 Briga Novarese",
    "sg:city":"Briga Novarese",
    "sg:orig_category":"Fittings, Valves",
    "sg:phone":"+39 0322 94684",
    "sg:postcode":"28010",
    "sg:province":"Novara",
    "sg:website":"www.bellosta rubinetterie.com",
    "wof:name":"Bellosta Carlo & C. Srl",
    "wof:placetype":"venue"
},
  "geometry": {"coordinates":[8.4488716125,45.7300567627],"type":"Point"}
}