{
  "type": "Feature",
  "properties": {
    "iso:country":"IT",
    "sg:address":"Via Ponte Vecchio, 28 Bis 36034 Malo",
    "sg:city":"Malo",
    "sg:orig_category":"Hardmetals",
    "sg:phone":"+39 0445 602727",
    "sg:postcode":"36034",
    "sg:province":"Vicenza",
    "sg:website":"www.icumtools.it",
    "wof:name":"Icum Italiana Costruzioni Utensileria Meccanica Di Bressan Eugenio & C Snc",
    "wof:placetype":"venue"
},
  "geometry": {"coordinates":[11.540307,45.545906],"type":"Point"}
}