{
  "type": "Feature",
  "properties": {
    "addr:full":"20124 Milano Milano Milano 20124",
    "addr:postcode":"20124;20124",
    "iso:country":"IT",
    "sg:address":"20124 Milano",
    "sg:city":"Milano",
    "sg:orig_category":"Prodotti E Manufatti In Materie Plastiche",
    "sg:phone":"+39 02 655 3141",
    "sg:postcode":"20124",
    "sg:province":"Milano",
    "wof:name":"Vaccarino Plastici Spa",
    "wof:placetype":"venue"
},
  "geometry": {"coordinates":[9.1986932755,45.4794654846],"type":"Point"}
}