{
  "type": "Feature",
  "properties": {
    "addr:full":"32, Viale Delle Industrie 80020 Casavatore Casavatore Napoli 80020",
    "addr:housenumber":"32",
    "addr:postcode":"80020;80020",
    "addr:street":"Viale Delle Industrie",
    "iso:country":"IT",
    "sg:address":"32, Viale Delle Industrie 80020 Casavatore",
    "sg:city":"Casavatore",
    "sg:classifiers":[
        {
            "category":"Manufacturing",
            "subcategory":"Paper Products",
            "type":"Manufacturing & Wholesale Goods"
        }
    ],
    "sg:phone":"+39 081 736 3632",
    "sg:postcode":"80020",
    "sg:province":"Napoli",
    "sg:tags":[
        "cardboard"
    ],
    "wof:name":"La Nuova Linea S.r.l.",
    "wof:placetype":"venue"
},
  "geometry": {"coordinates":[14.2740468979,40.8944969177],"type":"Point"}
}