{
  "type": "Feature",
  "properties": {
    "iso:country":"IT",
    "sg:address":"22063 Cantu'",
    "sg:orig_category":"Tessuti Arredamento - Produzione E Ingrosso",
    "sg:phone":"+39 031 704794",
    "sg:postcode":"22063",
    "sg:province":"Como",
    "wof:name":"Athena Collezioni",
    "wof:placetype":"venue"
},
  "geometry": {"coordinates":[9.127883,45.729912],"type":"Point"}
}