{
  "type": "Feature",
  "properties": {
    "iso:country":"IT",
    "sg:address":"Via Maja 5 21051 Arcisate",
    "sg:city":"Arcisate",
    "sg:classifiers":[
        {
            "category":"Manufacturing",
            "subcategory":"Rubber & Plastics",
            "type":"Manufacturing & Wholesale Goods"
        }
    ],
    "sg:phone":"+39 0332 476011",
    "sg:postcode":"21051",
    "sg:province":"Varese",
    "sg:tags":[
        "working"
    ],
    "sg:website":"www.roechling.it",
    "wof:name":"Roechling Srl",
    "wof:placetype":"venue"
},
  "geometry": {"coordinates":[8.8601493835,45.8519706726],"type":"Point"}
}