{
  "type": "Feature",
  "properties": {
    "addr:full":"00010 Colle Prenestino Roma 00010",
    "addr:postcode":"00010;00010",
    "iso:country":"IT",
    "sg:address":"00010 Colle Prenestino",
    "sg:orig_category":"Petroli, Gas E Combustibili",
    "sg:phone":"+39 06 412 3581",
    "sg:postcode":"00010",
    "sg:province":"Roma",
    "wof:name":"Agip Gas",
    "wof:placetype":"venue"
},
  "geometry": {"coordinates":[12.6355304718,41.9201660156],"type":"Point"}
}