{
  "type": "Feature",
  "properties": {
    "addr:full":"Via Andriano 20 39018 Terlan Bolzano/Bozen 39018",
    "addr:housenumber":"20",
    "addr:postcode":"39018;39018",
    "addr:street":"Via Andriano",
    "iso:country":"IT",
    "sg:address":"Via Andriano 20 39018 Terlan",
    "sg:classifiers":[
        {
            "category":"Health Services",
            "subcategory":"Nursing And Care Facility",
            "type":"Services"
        }
    ],
    "sg:phone":"+39 0471 259000",
    "sg:postcode":"39018",
    "sg:province":"Bolzano/Bozen",
    "sg:tags":[
        "equipment",
        "hospital",
        "clinic",
        "rehabilitation"
    ],
    "wof:name":"Exper Sas",
    "wof:placetype":"venue"
},
  "geometry": {"coordinates":[11.244722,46.530273],"type":"Point"}
}