{
  "type": "Feature",
  "properties": {
    "iso:country":"IT",
    "sg:address":"Contrada Giardinelle 75100 Matera",
    "sg:city":"Matera",
    "sg:classifiers":[
        {
            "category":"Manufacturing",
            "subcategory":"Wood Products",
            "type":"Manufacturing & Wholesale Goods"
        }
    ],
    "sg:phone":"+39 0835 261465",
    "sg:postcode":"75100",
    "sg:province":"Matera",
    "sg:tags":[
        "furniture"
    ],
    "wof:name":"Area Di Olivieri Emanuele E Olivieri Ignazio S.n.c.",
    "wof:placetype":"venue"
},
  "geometry": {"coordinates":[16.564121,40.674011],"type":"Point"}
}