{
  "type": "Feature",
  "properties": {
    "iso:country":"IT",
    "sg:address":"19031 Ameglia",
    "sg:city":"Ameglia",
    "sg:orig_category":"Banche E Servizi Finanziari",
    "sg:phone":"+39 0187 65774",
    "sg:postcode":"19031",
    "sg:province":"La Spezia",
    "wof:name":"Cassa Di Risparmio Della Spezia",
    "wof:placetype":"venue"
},
  "geometry": {"coordinates":[9.983902,44.056183],"type":"Point"}
}