{
  "type": "Feature",
  "properties": {
    "iso:country":"IT",
    "sg:address":"5, Via Vinci Leonardo 04011 Aprilia",
    "sg:city":"Aprilia",
    "sg:classifiers":[
        {
            "category":"Wholesale",
            "subcategory":"Drugs",
            "type":"Manufacturing & Wholesale Goods"
        }
    ],
    "sg:phone":"+39 39069280398",
    "sg:postcode":"04011",
    "sg:province":"Latina",
    "sg:tags":[
        "chemical",
        "pharmaceutical"
    ],
    "wof:name":"Gellini International Srl",
    "wof:placetype":"venue"
},
  "geometry": {"coordinates":[12.9037,41.467598],"type":"Point"}
}