{
  "type": "Feature",
  "properties": {
    "iso:country":"IT",
    "sg:address":"40/42, Via Pineta 51015 Monsummano Terme",
    "sg:city":"Monsummano Terme",
    "sg:classifiers":[
        {
            "category":"Personal",
            "subcategory":"Shoe Repair & Shine",
            "type":"Services"
        }
    ],
    "sg:phone":"+39 39057282666",
    "sg:postcode":"51015",
    "sg:province":"Pistoia",
    "sg:tags":[
        "leather"
    ],
    "wof:name":"Calzaturificio Fratelli Romani (s.p.a.)",
    "wof:placetype":"venue"
},
  "geometry": {"coordinates":[10.819343,43.860485],"type":"Point"}
}