{
  "type": "Feature",
  "properties": {
    "addr:full":"90145 Palermo Palermo Palermo 90145",
    "addr:postcode":"90145;90145",
    "iso:country":"IT",
    "sg:address":"90145 Palermo",
    "sg:city":"Palermo",
    "sg:orig_category":"Utensili Meccanici E Materiali",
    "sg:phone":"+39 091 229951",
    "sg:postcode":"90145",
    "sg:province":"Palermo",
    "wof:name":"Eurocryo Srl",
    "wof:placetype":"venue"
},
  "geometry": {"coordinates":[13.602249,38.018997],"type":"Point"}
}