{
  "type": "Feature",
  "properties": {
    "iso:country":"IT",
    "sg:address":"Via Sotto Monticchio 83048 Montella",
    "sg:city":"Montella",
    "sg:classifiers":[
        {
            "category":"Manufacturing",
            "subcategory":"Lumber",
            "type":"Manufacturing & Wholesale Goods"
        }
    ],
    "sg:phone":"+39 39082761035",
    "sg:postcode":"83048",
    "sg:province":"Avellino",
    "sg:tags":[
        "wood"
    ],
    "wof:name":"De Simone Virgilio",
    "wof:placetype":"venue"
},
  "geometry": {"coordinates":[14.792723,40.914749],"type":"Point"}
}