{
  "type": "Feature",
  "properties": {
    "iso:country":"IT",
    "sg:address":"Via Pindemonte 22 29100 Piacenza",
    "sg:city":"Piacenza",
    "sg:orig_category":"Earthmovers, Bulldozers, Dozers, Wheel Loaders",
    "sg:phone":"+39 0523 593430",
    "sg:postcode":"29100",
    "sg:province":"Piacenza",
    "sg:website":"www.pezzamaserati.com",
    "wof:name":"Pezza E Maserati Snc Macchine Industriali E Agricole",
    "wof:placetype":"venue"
},
  "geometry": {"coordinates":[9.722406,45.044521],"type":"Point"}
}