{
  "type": "Feature",
  "properties": {
    "iso:country":"IT",
    "sg:address":"1, Via Stazione 28053 Castelletto Sopra Ticino",
    "sg:city":"Castelletto sopra Ticino",
    "sg:classifiers":[
        {
            "category":"Professional",
            "subcategory":"Engineering",
            "type":"Services"
        }
    ],
    "sg:phone":"+39 0331 972529",
    "sg:postcode":"28053",
    "sg:province":"Novara",
    "sg:tags":[
        "machine",
        "-",
        "mechanical"
    ],
    "wof:name":"Officine Angelo Sibilia & Figlio (s.p.a.)",
    "wof:placetype":"venue"
},
  "geometry": {"coordinates":[8.638217,45.711578],"type":"Point"}
}