{
  "type": "Feature",
  "properties": {
    "addr:full":"40, Via Bolzaneto 16162 Genova Genova Genova 16162",
    "addr:postcode":"16162;16162",
    "addr:street":"Via Bolzaneto",
    "iso:country":"IT",
    "sg:address":"40, Via Bolzaneto 16162 Genova",
    "sg:city":"Genova",
    "sg:classifiers":[
        {
            "category":"Parking",
            "subcategory":"Lot",
            "type":"Transportation"
        }
    ],
    "sg:phone":"+39 010 745 3527",
    "sg:postcode":"16162",
    "sg:province":"Genova",
    "sg:tags":[
        "transport",
        "road"
    ],
    "wof:name":"Pastorino Angelo Autotrasporti (s.r.l.)",
    "wof:placetype":"venue"
},
  "geometry": {"coordinates":[8.904123,44.456394],"type":"Point"}
}