{
  "type": "Feature",
  "properties": {
    "addr:full":"41100 Modena Modena Modena 41100",
    "addr:postcode":"41100;41100",
    "iso:country":"IT",
    "sg:address":"41100 Modena",
    "sg:city":"Modena",
    "sg:orig_category":"Telecomunicazioni E Telefonia, Impianti, Apparecchi E Servizi",
    "sg:phone":"+39 059 394595",
    "sg:postcode":"41100",
    "sg:province":"Modena",
    "wof:name":"Multimedia Service S.n.c.",
    "wof:placetype":"venue"
},
  "geometry": {"coordinates":[10.919112,44.640472],"type":"Point"}
}