{
  "type": "Feature",
  "properties": {
    "addr:full":"10043 Orbassano Orbassano Torino 10043",
    "addr:postcode":"10043;10043",
    "iso:country":"IT",
    "sg:address":"10043 Orbassano",
    "sg:city":"Orbassano",
    "sg:orig_category":"Distributors: Automatici - Commercio E Gestione",
    "sg:phone":"+39 011 901 1454",
    "sg:postcode":"10043",
    "sg:province":"Torino",
    "sg:website":"http://www.catvending.com",
    "wof:name":"C.a.t. Srl",
    "wof:placetype":"venue"
},
  "geometry": {"coordinates":[7.550007,45.004715],"type":"Point"}
}