{
  "type": "Feature",
  "properties": {
    "addr:full":"21/23, Via Leonardo Da Vinci 20090 Segrate Segrate Milano 20090",
    "addr:housenumber":"21 / 23",
    "addr:postcode":"20090;20090",
    "addr:street":"Via Leonardo Da Vinci",
    "iso:country":"IT",
    "sg:address":"21/23, Via Leonardo Da Vinci 20090 Segrate",
    "sg:city":"Segrate",
    "sg:classifiers":[
        {
            "category":"Utilities",
            "subcategory":"Electric",
            "type":"Services"
        }
    ],
    "sg:phone":"+39 39022134034",
    "sg:postcode":"20090",
    "sg:province":"Milano",
    "sg:tags":[
        "component",
        "electronic"
    ],
    "wof:name":"Federal Trade Spa",
    "wof:placetype":"venue"
},
  "geometry": {"coordinates":[9.280835,45.492172],"type":"Point"}
}