{
  "type": "Feature",
  "properties": {
    "addr:full":"03100 Frosinone Frosinone Frosinone 03100",
    "addr:postcode":"03100;03100",
    "iso:country":"IT",
    "sg:address":"03100 Frosinone",
    "sg:city":"Frosinone",
    "sg:orig_category":"Autocarri",
    "sg:phone":"+39 0775 823015",
    "sg:postcode":"03100",
    "sg:province":"Frosinone",
    "wof:name":"Faag Srl",
    "wof:placetype":"venue"
},
  "geometry": {"coordinates":[13.340167,41.65155],"type":"Point"}
}