{
  "type": "Feature",
  "properties": {
    "iso:country":"IT",
    "sg:address":"20086 Motta Visconti",
    "sg:city":"Motta Visconti",
    "sg:orig_category":"Abbigliamento Intimo, Calze E Costumi Da Bagno. Sport - Articoli E Forniture. Shopping",
    "sg:phone":"+39 02 9000 0482",
    "sg:postcode":"20086",
    "sg:province":"Milano",
    "wof:name":"Barbieri Claudio",
    "wof:placetype":"venue"
},
  "geometry": {"coordinates":[9.190432,45.376583],"type":"Point"}
}