{
  "type": "Feature",
  "properties": {
    "iso:country":"IT",
    "sg:address":"20090 Buccinasco",
    "sg:city":"Buccinasco",
    "sg:orig_category":"Termotecnica E Riscaldamento, Apparecchiature E Servizi",
    "sg:phone":"+39 02 449 1095",
    "sg:postcode":"20090",
    "sg:province":"Milano",
    "wof:name":"C.a.t.i. S.r.l.",
    "wof:placetype":"venue"
},
  "geometry": {"coordinates":[9.105792,45.424637],"type":"Point"}
}