{
  "type": "Feature",
  "properties": {
    "addr:full":"26813 Graffignana Graffignana Lodi 26813",
    "addr:postcode":"26813;26813",
    "iso:country":"IT",
    "sg:address":"26813 Graffignana",
    "sg:city":"Graffignana",
    "sg:orig_category":"Metalli E Leghe",
    "sg:phone":"+39 0371 88674",
    "sg:postcode":"26813",
    "sg:province":"Lodi",
    "wof:name":"Senna Pietro",
    "wof:placetype":"venue"
},
  "geometry": {"coordinates":[9.4582090378,45.1997566223],"type":"Point"}
}