{
  "type": "Feature",
  "properties": {
    "iso:country":"IT",
    "sg:address":"20060 Truccazzano",
    "sg:city":"Albignano",
    "sg:orig_category":"Elettrotecnica Industriale, Prodotti E Apparecchiature",
    "sg:phone":"+39 02 9530 9104",
    "sg:postcode":"20060",
    "sg:province":"Milano",
    "wof:name":"S.a.i. Snc",
    "wof:placetype":"venue"
},
  "geometry": {"coordinates":[9.495101,45.49976],"type":"Point"}
}