{
  "type": "Feature",
  "properties": {
    "iso:country":"IT",
    "sg:address":"Via Emilia Est; Parma",
    "sg:classifiers":[
        {
            "category":"Banks & Credit Unions",
            "subcategory":"Bank",
            "type":"Services"
        }
    ],
    "sg:phone":"+39 0521 244186",
    "wof:name":"Banca San Paolo Di Brescia Spa",
    "wof:placetype":"venue"
},
  "geometry": {"coordinates":[10.348668,44.795677],"type":"Point"}
}