{
  "type": "Feature",
  "properties": {
    "iso:country":"IT",
    "sg:address":"63, Via Pini Tommaso 59100 Prato",
    "sg:city":"Prato",
    "sg:classifiers":[
        {
            "category":"Wholesale",
            "subcategory":"Drugs",
            "type":"Manufacturing & Wholesale Goods"
        }
    ],
    "sg:phone":"+39 0574 595702",
    "sg:postcode":"59100",
    "sg:province":"Prato",
    "sg:tags":[
        "chemical",
        "pharmaceutical"
    ],
    "wof:name":"Agesco (s.r.l.)",
    "wof:placetype":"venue"
},
  "geometry": {"coordinates":[11.096313,43.8797],"type":"Point"}
}