{
  "type": "Feature",
  "properties": {
    "iso:country":"IT",
    "sg:address":"29010 Rottofreno",
    "sg:city":"Rottofreno",
    "sg:orig_category":"Carpenterie Metalliche",
    "sg:phone":"+39 0523 769383",
    "sg:postcode":"29010",
    "sg:province":"Piacenza",
    "wof:name":"Officina Meccanica Scotti Snc Di Scotti Ettore & C.",
    "wof:placetype":"venue"
},
  "geometry": {"coordinates":[9.963435,44.898697],"type":"Point"}
}