{
  "type": "Feature",
  "properties": {
    "iso:country":"IT",
    "sg:address":"4, V. Ponte D'oro 36015 Schio",
    "sg:city":"Schio",
    "sg:classifiers":[
        {
            "category":"Banks & Credit Unions",
            "subcategory":"Investment Brokerage",
            "type":"Services"
        }
    ],
    "sg:phone":"+39 0445 511979",
    "sg:postcode":"36015",
    "sg:province":"Vicenza",
    "sg:tags":[
        "-",
        "transport",
        "related"
    ],
    "sg:website":"http://www.stilservice.com",
    "wof:name":"Stil Service Srl",
    "wof:placetype":"venue"
},
  "geometry": {"coordinates":[11.381783,45.700073],"type":"Point"}
}