{
  "type": "Feature",
  "properties": {
    "iso:country":"IT",
    "sg:address":"71, Via Del Lavoro 40033 Casalecchio Di Reno",
    "sg:city":"Casalecchio di Reno",
    "sg:classifiers":[
        {
            "category":"Wholesale",
            "subcategory":"Drugs",
            "type":"Manufacturing & Wholesale Goods"
        }
    ],
    "sg:phone":"+39 39051595411",
    "sg:postcode":"40033",
    "sg:province":"Bologna",
    "sg:tags":[
        "chemical",
        "pharmaceutical"
    ],
    "wof:name":"Unico La Farmacia Dei Farmacisti Spa",
    "wof:placetype":"venue"
},
  "geometry": {"coordinates":[11.257105,44.488964],"type":"Point"}
}