{
  "type": "Feature",
  "properties": {
    "iso:country":"IT",
    "sg:address":"Via Fatebenefratelli 21; Milan",
    "sg:classifiers":[
        {
            "category":"Travel",
            "subcategory":"Travel Agent",
            "type":"Entertainment"
        }
    ],
    "wof:name":"Hotel Cavour",
    "wof:placetype":"venue"
},
  "geometry": {"coordinates":[9.334486,45.523743],"type":"Point"}
}