{
  "type": "Feature",
  "properties": {
    "iso:country":"IT",
    "sg:address":"Via L. Da Vinci 4 22020 Gironico",
    "sg:city":"Gironico",
    "sg:classifiers":[
        {
            "category":"Retail",
            "subcategory":"Auto Rental",
            "type":"Services"
        }
    ],
    "sg:phone":"+39 031 550020",
    "sg:postcode":"22020",
    "sg:province":"Como",
    "sg:tags":[
        "machine",
        "embossing"
    ],
    "wof:name":"G. Colombo Srl",
    "wof:placetype":"venue"
},
  "geometry": {"coordinates":[9.005651,45.798759],"type":"Point"}
}