{
  "type": "Feature",
  "properties": {
    "iso:country":"IT",
    "sg:address":"80055 Portici",
    "sg:city":"Portici",
    "sg:orig_category":"Motori Ed Organi Di Trasmissione",
    "sg:phone":"+39 081 775 1424",
    "sg:postcode":"80055",
    "sg:province":"Napoli",
    "wof:name":"Poliscotti",
    "wof:placetype":"venue"
},
  "geometry": {"coordinates":[14.3455905914,40.8175354004],"type":"Point"}
}