{
  "type": "Feature",
  "properties": {
    "iso:country":"IT",
    "sg:address":"20030 Senago",
    "sg:city":"Senago",
    "sg:orig_category":"Materiali Edili",
    "sg:phone":"+39 02 998 8461",
    "sg:postcode":"20030",
    "sg:province":"Milano",
    "wof:name":"Crisbar Srl",
    "wof:placetype":"venue"
},
  "geometry": {"coordinates":[9.078749,45.547894],"type":"Point"}
}