{
  "type": "Feature",
  "properties": {
    "addr:full":"93019 Sommatino Sommatino Caltanissetta 93019",
    "addr:postcode":"93019;93019",
    "iso:country":"IT",
    "sg:address":"93019 Sommatino",
    "sg:city":"Sommatino",
    "sg:orig_category":"Studi E Consulenze Tecniche E Industriali. Servizi E Lavori Per Edilizia E Lavori Pubblici. Professionisti - Studi E Servizi Ed Associazioni Di Interesse Aziendale",
    "sg:phone":"+39 0922 873577",
    "sg:postcode":"93019",
    "sg:province":"Caltanissetta",
    "wof:name":"Di Vanni Ing. Vincenzo",
    "wof:placetype":"venue"
},
  "geometry": {"coordinates":[13.995197,37.336048],"type":"Point"}
}