{
  "type": "Feature",
  "properties": {
    "iso:country":"IT",
    "sg:address":"31, Via Dell' Economia 36100 Vicenza",
    "sg:city":"Vicenza",
    "sg:classifiers":[
        {
            "category":"Manufacturing",
            "subcategory":"Rubber & Plastics",
            "type":"Manufacturing & Wholesale Goods"
        }
    ],
    "sg:phone":"+39 0444 291143",
    "sg:postcode":"36100",
    "sg:province":"Vicenza",
    "wof:name":"Charlie Service Srl",
    "wof:placetype":"venue"
},
  "geometry": {"coordinates":[11.526389122,45.5752792358],"type":"Point"}
}