{
  "type": "Feature",
  "properties": {
    "addr:full":"7, Via Della Maggiona 00040 Pomezia Pomezia Roma 00040",
    "addr:postcode":"00040;roma 00040",
    "addr:street":"Via Della Maggiona",
    "iso:country":"IT",
    "sg:address":"7, Via Della Maggiona 00040 Pomezia",
    "sg:city":"Pomezia",
    "sg:classifiers":[
        {
            "category":"Manufacturing",
            "subcategory":"Rubber & Plastics",
            "type":"Manufacturing & Wholesale Goods"
        }
    ],
    "sg:phone":"+39 06 9160 2525",
    "sg:postcode":"00040",
    "sg:province":"Roma",
    "wof:name":"Sp Systema S.r.l.",
    "wof:placetype":"venue"
},
  "geometry": {"coordinates":[12.5233573914,41.6692123413],"type":"Point"}
}