{
  "type": "Feature",
  "properties": {
    "addr:full":"20088 Rosate Rosate Milano 20088",
    "addr:postcode":"20088;20088",
    "iso:country":"IT",
    "sg:address":"20088 Rosate",
    "sg:city":"Rosate",
    "sg:orig_category":"Pubblica Amministrazione",
    "sg:phone":"+39 02 908301",
    "sg:postcode":"20088",
    "sg:province":"Milano",
    "wof:name":"Municipio Di Rosate",
    "wof:placetype":"venue"
},
  "geometry": {"coordinates":[9.2039737701,45.4752655029],"type":"Point"}
}