{
  "type": "Feature",
  "properties": {
    "iso:country":"IT",
    "sg:address":"24040 Lallio",
    "sg:city":"Lallio",
    "sg:orig_category":"Non-classified Establishments",
    "sg:phone":"+39 035 692284",
    "sg:postcode":"24040",
    "sg:province":"Bergamo",
    "wof:name":"Benedetti (s.n.c.)",
    "wof:placetype":"venue"
},
  "geometry": {"coordinates":[9.614531,45.643604],"type":"Point"}
}