{
  "type": "Feature",
  "properties": {
    "addr:full":"47900 Rimini Rimini Rimini 47900",
    "addr:postcode":"47900;47900",
    "iso:country":"IT",
    "sg:address":"47900 Rimini",
    "sg:city":"Rimini",
    "sg:orig_category":"Gallerie D'arte",
    "sg:phone":"+39 0541 393302",
    "sg:postcode":"47900",
    "sg:province":"Rimini",
    "wof:name":"Galleria D'arte Regina Elena Snc",
    "wof:placetype":"venue"
},
  "geometry": {"coordinates":[12.593516,44.055828],"type":"Point"}
}