{
  "type": "Feature",
  "properties": {
    "addr:full":"43100 Parma Moletolo Parma 43100",
    "addr:postcode":"43100;43100",
    "iso:country":"IT",
    "sg:address":"43100 Parma",
    "sg:city":"Moletolo",
    "sg:orig_category":"Legno E Semilavorati",
    "sg:phone":"+39 0521 270723",
    "sg:postcode":"43100",
    "sg:province":"Parma",
    "wof:name":"Carpi Srl",
    "wof:placetype":"venue"
},
  "geometry": {"coordinates":[10.320308,44.830761],"type":"Point"}
}