{
  "type": "Feature",
  "properties": {
    "addr:full":"20090 Pieve Emanuele Pieve Emanuele Milano 20090",
    "addr:postcode":"20090;20090",
    "iso:country":"IT",
    "sg:address":"20090 Pieve Emanuele",
    "sg:city":"Pieve Emanuele",
    "sg:orig_category":"Prodotti Finiti Stampati. Articoli Da Regalo. Arte Ed Artigianato Artistico. Shopping",
    "sg:phone":"+39 02 9042 2258",
    "sg:postcode":"20090",
    "sg:province":"Milano",
    "wof:name":"Arti Grafiche Snc",
    "wof:placetype":"venue"
},
  "geometry": {"coordinates":[9.1930007935,45.3751716614],"type":"Point"}
}