{
  "type": "Feature",
  "properties": {
    "iso:country":"IT",
    "sg:address":"37069 Villafranca Verona",
    "sg:orig_category":"Macchine, Impianti Ed Attrezzature Per Industria Alimentare E Bevande. Macchine E Impianti Per Attivita' Commerciali Ed Artigianali",
    "sg:phone":"+39 045 630 1506",
    "sg:postcode":"37069",
    "sg:province":"Verona",
    "wof:name":"Marana Forni Di Marana Ferdinando",
    "wof:placetype":"venue"
},
  "geometry": {"coordinates":[10.977732,45.409882],"type":"Point"}
}