{
  "type": "Feature",
  "properties": {
    "addr:full":"18, Via Madonnina 25018 Montichiari Montichiari Brescia 25018",
    "addr:postcode":"25018;25018",
    "addr:street":"Via Madonnina",
    "iso:country":"IT",
    "sg:address":"18, Via Madonnina 25018 Montichiari",
    "sg:city":"Montichiari",
    "sg:classifiers":[
        {
            "category":"Shopping",
            "subcategory":"Clothing, Apparel, & Fashions",
            "type":"Retail Goods"
        }
    ],
    "sg:phone":"+39 030 996 2456",
    "sg:postcode":"25018",
    "sg:province":"Brescia",
    "sg:tags":[
        "clothes"
    ],
    "wof:name":"Maglificio Liliana Di Lorenzoni Andrea E C. Snc",
    "wof:placetype":"venue"
},
  "geometry": {"coordinates":[10.398134,45.39777],"type":"Point"}
}