{
  "type": "Feature",
  "properties": {
    "addr:full":"33030 Rive D'arcano Rodeano Udine 33030",
    "addr:postcode":"33030;33030",
    "addr:street":"D'Arcano Rodeano",
    "iso:country":"IT",
    "sg:address":"33030 Rive D'arcano",
    "sg:city":"Rodeano",
    "sg:orig_category":"Stampaggio Gomma",
    "sg:phone":"+39 0432 807195",
    "sg:postcode":"33030",
    "sg:province":"Udine",
    "sg:website":"http://www.artiplastiche.com",
    "wof:name":"Artiplastiche Di Cosolo & C. Snc",
    "wof:placetype":"venue"
},
  "geometry": {"coordinates":[13.017402,46.113449],"type":"Point"}
}