{
  "type": "Feature",
  "properties": {
    "iso:country":"IT",
    "sg:address":"25128 Brescia",
    "sg:city":"Brescia",
    "sg:orig_category":"Sport - Articoli E Forniture",
    "sg:phone":"+39 030 383351",
    "sg:postcode":"25128",
    "sg:province":"Brescia",
    "wof:name":"Armi Renato Luterotti",
    "wof:placetype":"venue"
},
  "geometry": {"coordinates":[10.207205,45.559326],"type":"Point"}
}