{
  "type": "Feature",
  "properties": {
    "iso:country":"IT",
    "sg:address":"00043 Ciampino",
    "sg:city":"Ciampino",
    "sg:orig_category":"Prodotti E Manufatti In Materie Plastiche. Articoli Per Imballaggio E Confezionamento",
    "sg:phone":"+39 06 791 3216",
    "sg:postcode":"00043",
    "sg:province":"Roma",
    "wof:name":"Clai Imballaggi Industriali S R L",
    "wof:placetype":"venue"
},
  "geometry": {"coordinates":[12.5902509689,41.8169174194],"type":"Point"}
}