{
  "type": "Feature",
  "properties": {
    "iso:country":"IT",
    "sg:address":"43022 Tortiano",
    "sg:orig_category":"Prodotti Di Base E Forniture Per Industria Alimentare E Bevande. Carta, Cartone E Prodotti Primari. Forniture Per Attivita' Commerciali Ed Artigianali",
    "sg:phone":"+39 0521 686076",
    "sg:postcode":"43022",
    "sg:province":"Parma",
    "wof:name":"Roccalberti Gianluca",
    "wof:placetype":"venue"
},
  "geometry": {"coordinates":[10.413444519,44.681427002],"type":"Point"}
}