{
  "type": "Feature",
  "properties": {
    "iso:country":"IT",
    "sg:address":"89126 Reggio Calabria",
    "sg:orig_category":"Automatismi Elettrici, Elettronici E Pneumatici",
    "sg:phone":"+39 0965 897485",
    "sg:province":"RC",
    "wof:name":"Cannizzaro Nicola",
    "wof:placetype":"venue"
},
  "geometry": {"coordinates":[15.746854,38.137218],"type":"Point"}
}