{
  "type": "Feature",
  "properties": {
    "iso:country":"IT",
    "sg:address":"50018 Scandicci",
    "sg:city":"Scandicci",
    "sg:orig_category":"Argenterie - Vendita Al Dettaglio",
    "sg:phone":"+39 055 722 1564",
    "sg:postcode":"50018",
    "sg:province":"Firenze",
    "wof:name":"Inter Florence Srl",
    "wof:placetype":"venue"
},
  "geometry": {"coordinates":[11.158982,43.761738],"type":"Point"}
}