{
  "type": "Feature",
  "properties": {
    "addr:full":"50129 Firenze Firenze Firenze 50129",
    "addr:postcode":"50129;50129",
    "iso:country":"IT",
    "sg:address":"50129 Firenze",
    "sg:city":"Firenze",
    "sg:classifiers":[
        {
            "category":"Banks & Credit Unions",
            "subcategory":"Investment Brokerage",
            "type":"Services"
        }
    ],
    "sg:phone":"+39 055 483548",
    "sg:postcode":"50129",
    "sg:province":"Firenze",
    "sg:tags":[
        "parrucchieri",
        "per",
        "donna"
    ],
    "sg:website":"http://www.renatocoiffeur.com",
    "wof:name":"Renato Coiffeur Snc",
    "wof:placetype":"venue"
},
  "geometry": {"coordinates":[10.7479085922,43.8607368469],"type":"Point"}
}