{
  "type": "Feature",
  "properties": {
    "iso:country":"IT",
    "sg:address":"Via Novara 10/d 20013 Magenta",
    "sg:city":"Magenta",
    "sg:classifiers":[
        {
            "category":"Retail",
            "subcategory":"Laundry & Dry Cleaning",
            "type":"Services"
        }
    ],
    "sg:phone":"+39 02 9729 1834",
    "sg:postcode":"20013",
    "sg:province":"Milano",
    "sg:tags":[
        "installation",
        "product",
        "industrial",
        "washing",
        "special"
    ],
    "sg:website":"www.serindgamma.com",
    "wof:name":"Serind Gamma Srl",
    "wof:placetype":"venue"
},
  "geometry": {"coordinates":[8.753222,45.467358],"type":"Point"}
}