{
  "type": "Feature",
  "properties": {
    "addr:full":"23868 Valmadrera Valmadrera Lecco 23868",
    "addr:postcode":"23868;23868",
    "iso:country":"IT",
    "sg:address":"23868 Valmadrera",
    "sg:city":"Valmadrera",
    "sg:orig_category":"Prodotti Chimici Secondari. Macchine, Impianti Ed Attrezzature Industria Chimica. Servizi E Lavori Industria Chimica",
    "sg:phone":"+39 0341 581364",
    "sg:postcode":"23868",
    "sg:province":"Lecco",
    "wof:name":"Aerosol Service Italiana (s.p.a.)",
    "wof:placetype":"venue"
},
  "geometry": {"coordinates":[9.3695173264,45.8541526794],"type":"Point"}
}