{
  "type": "Feature",
  "properties": {
    "iso:country":"IT",
    "sg:address":"10091 Alpignano",
    "sg:city":"Alpignano",
    "sg:classifiers":[
        {
            "category":"Building & Trades",
            "subcategory":"Construction",
            "type":"Services"
        }
    ],
    "sg:phone":"+39 011 968 2769",
    "sg:postcode":"10091",
    "sg:province":"Torino",
    "sg:tags":[
        "industry",
        "work",
        "plastic"
    ],
    "wof:name":"Plastmo Srl",
    "wof:placetype":"venue"
},
  "geometry": {"coordinates":[7.6881713867,45.0292625427],"type":"Point"}
}