{
  "type": "Feature",
  "properties": {
    "iso:country":"IT",
    "sg:address":"4, V. Dell'industria 62010 Treia",
    "sg:city":"Treia",
    "sg:classifiers":[
        {
            "category":"Home & Garden",
            "subcategory":"Home Furnishings",
            "type":"Retail Goods"
        }
    ],
    "sg:phone":"+39 390 733 8401",
    "sg:postcode":"62010",
    "sg:province":"Macerata",
    "sg:tags":[
        "household"
    ],
    "sg:website":"http://www.lubeover.it:ws_end: :mark:ws:http://www.paginegialle.it/cucinelubeoverspa",
    "wof:name":"Lube Over Spa",
    "wof:placetype":"venue"
},
  "geometry": {"coordinates":[13.341947,43.292057],"type":"Point"}
}