{
  "type": "Feature",
  "properties": {
    "iso:country":"IT",
    "sg:address":"10042 Nichelino",
    "sg:city":"Nichelino",
    "sg:orig_category":"Arredo Camera Letto E Complementi. Servizi E Lavori Per Arredamento E Industria Del Legno",
    "sg:phone":"+39 011 621936",
    "sg:postcode":"10042",
    "sg:province":"Torino",
    "wof:name":"Scagliotti Flavio",
    "wof:placetype":"venue"
},
  "geometry": {"coordinates":[7.642891,44.991741],"type":"Point"}
}