{
  "type": "Feature",
  "properties": {
    "iso:country":"IT",
    "sg:address":"20017 Rho",
    "sg:city":"Rho",
    "sg:classifiers":[
        {
            "category":"Health Services",
            "subcategory":"Health Practitioner",
            "type":"Services"
        }
    ],
    "sg:phone":"+39 02 9350 5951",
    "sg:postcode":"20017",
    "sg:province":"Milano",
    "sg:tags":[
        "medici"
    ],
    "wof:name":"Rossi Maurizio",
    "wof:placetype":"venue"
},
  "geometry": {"coordinates":[9.0472135544,45.5295143127],"type":"Point"}
}