{
  "type": "Feature",
  "properties": {
    "iso:country":"IT",
    "sg:address":"Via Roma, 3; Maniago; 33085",
    "sg:city":"Maniago",
    "sg:classifiers":[
        {
            "category":"Banks & Credit Unions",
            "subcategory":"Bank",
            "type":"Services"
        }
    ],
    "sg:phone":"+39 0427 72906",
    "sg:postcode":"33085",
    "sg:province":"Pordenone",
    "wof:name":"Cassa Di Risparmio Di, Udine E Pordenone",
    "wof:placetype":"venue"
},
  "geometry": {"coordinates":[12.707415,46.171642],"type":"Point"}
}