{
  "type": "Feature",
  "properties": {
    "iso:country":"IT",
    "sg:address":"30038 Spinea",
    "sg:city":"Spinea",
    "sg:orig_category":"Servizi Ausiliari Dei Mezzi Di Trasporto",
    "sg:phone":"+39 041 990386",
    "sg:postcode":"30038",
    "sg:province":"Venezia",
    "wof:name":"Gas Metano Spinea (s.a.s.)",
    "wof:placetype":"venue"
},
  "geometry": {"coordinates":[12.142173,45.48822],"type":"Point"}
}