{
  "type": "Feature",
  "properties": {
    "iso:country":"IT",
    "sg:address":"20139 Milano",
    "sg:city":"Milano",
    "sg:orig_category":"Servizi Per Lo Sport E Il Tempo Libero. Servizi Al Turismo",
    "sg:phone":"+39 02 5740 4495",
    "sg:postcode":"20139",
    "sg:province":"Milano",
    "wof:name":"Bowling Corvetto",
    "wof:placetype":"venue"
},
  "geometry": {"coordinates":[9.227516,45.428825],"type":"Point"}
}