{
  "type": "Feature",
  "properties": {
    "addr:full":"8, Corso Spagna 35127 Padova Padova Padova 35127",
    "addr:postcode":"35127;35127",
    "addr:street":"Corso Spagna",
    "iso:country":"IT",
    "sg:address":"8, Corso Spagna 35127 Padova",
    "sg:city":"Padova",
    "sg:classifiers":[
        {
            "category":"Parking",
            "subcategory":"Lot",
            "type":"Transportation"
        }
    ],
    "sg:phone":"+39 049 828 7000",
    "sg:postcode":"35127",
    "sg:province":"Padova",
    "sg:tags":[
        "transport",
        "road"
    ],
    "wof:name":"Gruber Logistics S.p.a.",
    "wof:placetype":"venue"
},
  "geometry": {"coordinates":[11.92522,45.354546],"type":"Point"}
}