{
  "type": "Feature",
  "properties": {
    "addr:full":"23881 Airuno Airuno Lecco 23881",
    "addr:postcode":"23881;23881",
    "iso:country":"IT",
    "sg:address":"23881 Airuno",
    "sg:city":"Airuno",
    "sg:orig_category":"Materiali Semilavorati Metallici",
    "sg:phone":"+39 039 994 3261",
    "sg:postcode":"23881",
    "sg:province":"Lecco",
    "wof:name":"Omas Srl",
    "wof:placetype":"venue"
},
  "geometry": {"coordinates":[9.431012,45.754864],"type":"Point"}
}