{
  "type": "Feature",
  "properties": {
    "addr:full":"39026 Prato Allo Stelvio Prato allo Stelvio Bolzano/Bozen 39026",
    "addr:postcode":"39026;39026",
    "iso:country":"IT",
    "sg:address":"39026 Prato Allo Stelvio",
    "sg:city":"Prato allo Stelvio",
    "sg:orig_category":"Energia Solare Ed Energie Alternative - Impianti E Componenti",
    "sg:phone":"+39 0473 616361",
    "sg:postcode":"39026",
    "sg:province":"Bolzano/Bozen",
    "wof:name":"Walln\u00d6fer Heinrich Franz",
    "wof:placetype":"venue"
},
  "geometry": {"coordinates":[10.581718,46.61665],"type":"Point"}
}