{
  "type": "Feature",
  "properties": {
    "addr:full":"03011 Alatri Alatri Frosinone 03011",
    "addr:postcode":"03011;03011",
    "iso:country":"IT",
    "sg:address":"03011 Alatri",
    "sg:city":"Alatri",
    "sg:orig_category":"Prodotti Chimici Di Base. Forniture Per Attivita' Industriali",
    "sg:phone":"+39 0775 442504",
    "sg:postcode":"03011",
    "sg:province":"Frosinone",
    "wof:name":"Baldassarre Giovanni",
    "wof:placetype":"venue"
},
  "geometry": {"coordinates":[13.3429174423,41.7365989685],"type":"Point"}
}