{
  "type": "Feature",
  "properties": {
    "addr:full":"25013 Carpenedolo Carpenedolo Brescia 25013",
    "addr:postcode":"25013;25013",
    "iso:country":"IT",
    "sg:address":"25013 Carpenedolo",
    "sg:city":"Carpenedolo",
    "sg:classifiers":[
        {
            "category":"Shopping",
            "subcategory":"Clothing, Apparel, & Fashions",
            "type":"Retail Goods"
        }
    ],
    "sg:phone":"+39 030 996 5454",
    "sg:postcode":"25013",
    "sg:province":"Brescia",
    "sg:tags":[
        "activities",
        "goods",
        "supply",
        "leather",
        "commercial",
        "artisan",
        "supplies",
        "clothing"
    ],
    "sg:website":"http://www.pbssoles.it",
    "wof:name":"P.b.s. Srl",
    "wof:placetype":"venue"
},
  "geometry": {"coordinates":[10.424191,45.341812],"type":"Point"}
}