{
  "type": "Feature",
  "properties": {
    "iso:country":"IT",
    "sg:address":"Via Petrarca 44 50041 Calenzano",
    "sg:city":"Calenzano",
    "sg:classifiers":[
        {
            "category":"Food & Beverages",
            "subcategory":"Fruits & Vegetables",
            "type":"Retail Goods"
        }
    ],
    "sg:phone":"+39 055 881 1106",
    "sg:postcode":"50041",
    "sg:province":"Firenze",
    "sg:website":"www.vichi-funghi.it",
    "wof:name":"Vichi Srl",
    "wof:placetype":"venue"
},
  "geometry": {"coordinates":[11.2024698257,43.8259620667],"type":"Point"}
}