{
  "type": "Feature",
  "properties": {
    "iso:country":"IT",
    "sg:address":"46043 Castiglione Stiviere",
    "sg:classifiers":[
        {
            "category":"Parking",
            "subcategory":"Lot",
            "type":"Transportation"
        }
    ],
    "sg:phone":"+39 0376 6781",
    "sg:postcode":"46043",
    "sg:province":"Mantova",
    "sg:tags":[
        "good",
        "shipment",
        "transport"
    ],
    "wof:name":"Bertani Trasporti Spa",
    "wof:placetype":"venue"
},
  "geometry": {"coordinates":[10.795269,45.159779],"type":"Point"}
}