{
  "type": "Feature",
  "properties": {
    "iso:country":"IT",
    "sg:address":"Via Portanova 23 81031 Aversa",
    "sg:city":"Aversa",
    "sg:classifiers":[
        {
            "category":"Shopping",
            "subcategory":"Shoes",
            "type":"Retail Goods"
        }
    ],
    "sg:phone":"+39 081 503 7025",
    "sg:postcode":"81031",
    "sg:province":"Caserta",
    "sg:tags":[
        "men's",
        "boot"
    ],
    "wof:name":"Digi Calzature Sas",
    "wof:placetype":"venue"
},
  "geometry": {"coordinates":[14.3321943283,41.0754165649],"type":"Point"}
}