{
  "type": "Feature",
  "properties": {
    "iso:country":"IT",
    "sg:address":"13871 Verrone",
    "sg:city":"Verrone",
    "sg:orig_category":"Filati - Produzione E Ingrosso",
    "sg:phone":"+39 015 255 8082",
    "sg:postcode":"13871",
    "sg:province":"Biella",
    "wof:name":"Gruppo Tessile Industriale Spa",
    "wof:placetype":"venue"
},
  "geometry": {"coordinates":[8.0977458954,45.5597114563],"type":"Point"}
}