{
  "type": "Feature",
  "properties": {
    "addr:full":"11, Via Cornaggia 20017 Rho Rho Milano 20017",
    "addr:postcode":"20017;20017",
    "addr:street":"Via Cornaggia",
    "iso:country":"IT",
    "sg:address":"11, Via Cornaggia 20017 Rho",
    "sg:city":"Rho",
    "sg:classifiers":[
        {
            "category":"Wholesale",
            "subcategory":"Machinery & Supplies",
            "type":"Manufacturing & Wholesale Goods"
        }
    ],
    "sg:phone":"+39 39029302955",
    "sg:postcode":"20017",
    "sg:province":"Milano",
    "sg:tags":[
        "equipment",
        "-",
        "instrument",
        "measurement"
    ],
    "wof:name":"Corradi",
    "wof:placetype":"venue"
},
  "geometry": {"coordinates":[9.03138,45.530083],"type":"Point"}
}