{
  "type": "Feature",
  "properties": {
    "iso:country":"IT",
    "sg:address":"Viale Al Mare, 78; Casal Borsetti; 48010",
    "sg:city":"Casal Borsetti",
    "sg:classifiers":[
        {
            "category":"Banks & Credit Unions",
            "subcategory":"Bank",
            "type":"Services"
        }
    ],
    "sg:phone":"+39 0544 445103",
    "sg:postcode":"48010",
    "sg:province":"Ravenna",
    "wof:name":"Credito Romagnolo",
    "wof:placetype":"venue"
},
  "geometry": {"coordinates":[12.279901,44.553532],"type":"Point"}
}