{
  "type": "Feature",
  "properties": {
    "addr:full":"00147 Roma Roma Roma 00147",
    "addr:postcode":"00147;00147",
    "iso:country":"IT",
    "sg:address":"00147 Roma",
    "sg:city":"Roma",
    "sg:orig_category":"Publishing Services. Services For Companies, Events, And Support For Trade",
    "sg:phone":"+39 06 519961",
    "sg:postcode":"00147",
    "sg:province":"Roma",
    "sg:website":"http://www.agenziaitalia.it",
    "wof:name":"A.g.i. Agenzia Giornalistica Italia Spa",
    "wof:placetype":"venue"
},
  "geometry": {"coordinates":[12.4961366653,41.8661727905],"type":"Point"}
}