{
  "type": "Feature",
  "properties": {
    "iso:country":"IT",
    "sg:address":"20097 San Donato Milanese",
    "sg:city":"San Donato Milanese",
    "sg:orig_category":"Termotecnica E Riscaldamento, Apparecchiature E Servizi",
    "sg:phone":"+39 02 527 3659",
    "sg:postcode":"20097",
    "sg:province":"Milano",
    "sg:website":"http://www.teknoambiente.it",
    "wof:name":"Tekno Ambiente Srl",
    "wof:placetype":"venue"
},
  "geometry": {"coordinates":[9.272523,45.400745],"type":"Point"}
}