{
  "type": "Feature",
  "properties": {
    "iso:country":"IT",
    "sg:address":"20142 Milano",
    "sg:city":"Milano",
    "sg:orig_category":"Ospedali E Servizi Sanitari",
    "sg:phone":"+39 02 8930 4980",
    "sg:postcode":"20142",
    "sg:province":"Milano",
    "wof:name":"Croce Rossa Italiana/comitato Provinciale Iii Centro Di Mobilitazione",
    "wof:placetype":"venue"
},
  "geometry": {"coordinates":[9.169617,45.4202],"type":"Point"}
}