{
  "type": "Feature",
  "properties": {
    "addr:full":"74100 Taranto Taranto Taranto 74100",
    "addr:postcode":"74100;74100",
    "iso:country":"IT",
    "sg:address":"74100 Taranto",
    "sg:city":"Taranto",
    "sg:orig_category":"Giornali E Riviste - Editori",
    "sg:phone":"+39 099 455 1000",
    "sg:postcode":"74100",
    "sg:province":"Taranto",
    "wof:name":"Pubblicor Piccola Soc. Coop. A R.l.",
    "wof:placetype":"venue"
},
  "geometry": {"coordinates":[17.244928,40.472691],"type":"Point"}
}