{
  "type": "Feature",
  "properties": {
    "iso:country":"IT",
    "sg:address":"62015 Monte S.giusto",
    "sg:orig_category":"Apparecchiature Ed Attrezzature Meccaniche. Forniture E Materiali Per Imballaggio E Confezionamento. Apparecchiature E Sistemi Per Imballaggio E Confezionamento",
    "sg:phone":"+39 0733 539698",
    "sg:postcode":"62015",
    "sg:province":"Macerata",
    "wof:name":"Fustellificio Master Dii Zaccari & Mercuri Snc",
    "wof:placetype":"venue"
},
  "geometry": {"coordinates":[13.456262,43.300747],"type":"Point"}
}