{
  "type": "Feature",
  "properties": {
    "iso:country":"IT",
    "sg:address":"10020 Riva Presso Chieri",
    "sg:city":"Riva presso Chieri",
    "sg:orig_category":"Macchine, Impianti Ed Attrezzature Per Agricoltura E Zootecnia",
    "sg:phone":"+39 011 946 9791",
    "sg:postcode":"10020",
    "sg:province":"Torino",
    "wof:name":"Vittone Mario",
    "wof:placetype":"venue"
},
  "geometry": {"coordinates":[7.868338,45.034912],"type":"Point"}
}