{
  "type": "Feature",
  "properties": {
    "iso:country":"IT",
    "sg:address":"20139 Milano",
    "sg:city":"Milano",
    "sg:orig_category":"Apparecchiature Ed Attrezzature Meccaniche. Ricambi E Componenti Dei Mezzi Di Trasporto",
    "sg:phone":"+39 02 537302",
    "sg:postcode":"20139",
    "sg:province":"Milano",
    "wof:name":"Ammortizzatori A.m. Snc Di Stefano Marchi & C.",
    "wof:placetype":"venue"
},
  "geometry": {"coordinates":[9.202935,45.451721],"type":"Point"}
}