{
  "type": "Feature",
  "properties": {
    "iso:country":"IT",
    "sg:address":"20026 Novate Milanese",
    "sg:city":"Novate Milanese",
    "sg:orig_category":"Prodotti Alimentari",
    "sg:phone":"+39 02 354 2316",
    "sg:postcode":"20026",
    "sg:province":"Milano",
    "wof:name":"Robbiati Alma E Tonolli Lino",
    "wof:placetype":"venue"
},
  "geometry": {"coordinates":[9.1374025345,45.5325622559],"type":"Point"}
}