{
  "type": "Feature",
  "properties": {
    "addr:full":"221/h, Corso Francia 10098 Rivoli Rivoli Torino 10098",
    "addr:housenumber":"221 / h",
    "addr:postcode":"10098;10098",
    "addr:street":"Corso Francia",
    "iso:country":"IT",
    "sg:address":"221/h, Corso Francia 10098 Rivoli",
    "sg:city":"Rivoli",
    "sg:classifiers":[
        {
            "category":"Shopping",
            "type":"Retail Goods"
        }
    ],
    "sg:phone":"+39 011 959 4861",
    "sg:postcode":"10098",
    "sg:province":"Torino",
    "sg:tags":[
        "finished",
        "-",
        "metallic"
    ],
    "wof:name":"Cast Meccanica S.r.l.",
    "wof:placetype":"venue"
},
  "geometry": {"coordinates":[7.5880789757,45.073184967],"type":"Point"}
}