{
  "type": "Feature",
  "properties": {
    "addr:full":"33078 San Vito Tagliamento Pordenone 33078",
    "addr:postcode":"33078;33078",
    "iso:country":"IT",
    "sg:address":"33078 San Vito Tagliamento",
    "sg:orig_category":"Materiali Edili",
    "sg:phone":"+39 0434 858633",
    "sg:postcode":"33078",
    "sg:province":"Pordenone",
    "wof:name":"Euromembrane Spa",
    "wof:placetype":"venue"
},
  "geometry": {"coordinates":[12.710835,46.037888],"type":"Point"}
}