{
  "type": "Feature",
  "properties": {
    "addr:full":"36034 Malo Malo Vicenza 36034",
    "addr:postcode":"36034;36034",
    "iso:country":"IT",
    "sg:address":"36034 Malo",
    "sg:city":"Malo",
    "sg:orig_category":"Carni, Salumi E Pesci. Ristorazione E Locali Pubblici Affini. Shopping",
    "sg:phone":"+39 0445 605408",
    "sg:postcode":"36034",
    "sg:province":"Vicenza",
    "wof:name":"Gastronomia Vergani Snc",
    "wof:placetype":"venue"
},
  "geometry": {"coordinates":[11.41788,45.665546],"type":"Point"}
}