{
  "type": "Feature",
  "properties": {
    "addr:full":"Via Locatelli Antonio 1 37122 Verona Verona Verona 37122",
    "addr:housenumber":"1",
    "addr:postcode":"37122;37122",
    "addr:street":"Via Locatelli Antonio",
    "iso:country":"IT",
    "sg:address":"Via Locatelli Antonio 1 37122 Verona",
    "sg:city":"Verona",
    "sg:classifiers":[
        {
            "category":"Home & Garden",
            "subcategory":"Garden Supply",
            "type":"Retail Goods"
        }
    ],
    "sg:phone":"+39 045 809 9011",
    "sg:postcode":"37122",
    "sg:province":"Verona",
    "sg:tags":[
        "farm",
        "insecticide"
    ],
    "sg:website":"www.consorzioagrariovrvi.com",
    "wof:name":"Consorzio Agrario Di Verona E Vicenza Coop. Arl",
    "wof:placetype":"venue"
},
  "geometry": {"coordinates":[10.991748,45.438366],"type":"Point"}
}