{
  "type": "Feature",
  "properties": {
    "iso:country":"IT",
    "sg:address":"52011 Bibbiena",
    "sg:city":"Bibbiena",
    "sg:orig_category":"Rimorchi Per Automobili",
    "sg:phone":"+39 0575 560067",
    "sg:postcode":"52011",
    "sg:province":"Arezzo",
    "sg:website":"http://www.crescirimorchi.it",
    "wof:name":"Carrozzeria Fratelli Cresci Di Ivo & Silvano Snc",
    "wof:placetype":"venue"
},
  "geometry": {"coordinates":[11.811264,43.725822],"type":"Point"}
}