{
  "type": "Feature",
  "properties": {
    "iso:country":"IT",
    "sg:address":"50121 Firenze",
    "sg:city":"Firenze",
    "sg:orig_category":"Chiese Ed Associazioni Religiose",
    "sg:phone":"+39 055 245252",
    "sg:postcode":"50121",
    "sg:province":"Firenze",
    "wof:name":"Comunita' Ebraica Di Firenze",
    "wof:placetype":"venue"
},
  "geometry": {"coordinates":[11.265472,43.772881],"type":"Point"}
}