{
  "type": "Feature",
  "properties": {
    "addr:full":"2, Via Olgiate Olona 21052 Busto Arsizio Busto Arsizio Varese 21052",
    "addr:postcode":"21052;21052",
    "addr:street":"Via Olgiate Olona",
    "iso:country":"IT",
    "sg:address":"2, Via Olgiate Olona 21052 Busto Arsizio",
    "sg:city":"Busto Arsizio",
    "sg:classifiers":[
        {
            "category":"Home & Garden",
            "subcategory":"Home Furnishings",
            "type":"Retail Goods"
        }
    ],
    "sg:phone":"+39 0331 633552",
    "sg:postcode":"21052",
    "sg:province":"Varese",
    "sg:tags":[
        "household"
    ],
    "wof:name":"Ziprandi Felice (s.n.c.)",
    "wof:placetype":"venue"
},
  "geometry": {"coordinates":[8.865091,45.620975],"type":"Point"}
}