{
  "type": "Feature",
  "properties": {
    "addr:full":"20129 Milano Milano Milano 20129",
    "addr:postcode":"20129;20129",
    "iso:country":"IT",
    "sg:address":"20129 Milano",
    "sg:city":"Milano",
    "sg:orig_category":"Ospedali E Servizi Sanitari",
    "sg:phone":"+39 02 782627",
    "sg:postcode":"20129",
    "sg:province":"Milano",
    "wof:name":"Istituto Di Psicologia Clinica Rocca - Stendoro",
    "wof:placetype":"venue"
},
  "geometry": {"coordinates":[9.20786,45.467869],"type":"Point"}
}