{
  "type": "Feature",
  "properties": {
    "iso:country":"IT",
    "sg:address":"62019 Recanati",
    "sg:city":"Recanati",
    "sg:orig_category":"Servizi E Lavori Per Ecologia E Smaltimento Rifiuti. Servizi Ausiliari Di Analisi, Controllo E Ricerca",
    "sg:phone":"+39 071 757 3136",
    "sg:postcode":"62019",
    "sg:province":"Macerata",
    "sg:website":"http://www.progettoambiente.net",
    "wof:name":"Progetto Ambiente Srl",
    "wof:placetype":"venue"
},
  "geometry": {"coordinates":[13.532124,43.394684],"type":"Point"}
}