{
  "type": "Feature",
  "properties": {
    "addr:full":"Loc Ponte San Quirino 1 33049 San Pietro Al Natisone San Pietro al Natisone Udine 33049",
    "addr:housenumber":"1",
    "addr:postcode":"33049;33049",
    "addr:street":"Loc Ponte San Quirino",
    "iso:country":"IT",
    "sg:address":"Loc Ponte San Quirino 1 33049 San Pietro Al Natisone",
    "sg:city":"San Pietro al Natisone",
    "sg:classifiers":[
        {
            "category":"Bakery",
            "type":"Food & Drink"
        }
    ],
    "sg:phone":"+39 0432 727585",
    "sg:postcode":"33049",
    "sg:province":"Udine",
    "sg:tags":[
        "fresh",
        "pastry",
        "bread"
    ],
    "sg:website":"www.giudittateresa.com",
    "wof:name":"Giuditta Teresa Srl",
    "wof:placetype":"venue"
},
  "geometry": {"coordinates":[13.2307243347,46.0649414062],"type":"Point"}
}