{
  "type": "Feature",
  "properties": {
    "iso:country":"IT",
    "sg:address":"15045 Sale",
    "sg:city":"Sale",
    "sg:orig_category":"Impiantistica E Prodotti Tecnologici Per Edilizia. Elettrotecnica Industriale, Prodotti E Apparecchiature. Elettrotecnica Professionale E Di Consumo",
    "sg:phone":"+39 0131 828339",
    "sg:postcode":"15045",
    "sg:province":"Alessandria",
    "sg:website":"http://www.bononi.it",
    "wof:name":"Bononi Mauro E Claudio Elettrotecnica Ed Informatica Snc",
    "wof:placetype":"venue"
},
  "geometry": {"coordinates":[8.736705,44.954624],"type":"Point"}
}