{
  "type": "Feature",
  "properties": {
    "iso:country":"IT",
    "sg:address":"38068 Rovereto",
    "sg:city":"Rovereto",
    "sg:orig_category":"Carpenterie Metalliche",
    "sg:phone":"+39 0464 423435",
    "sg:postcode":"38068",
    "sg:province":"Trento",
    "wof:name":"Cherotti Riccardo - V.r.s.",
    "wof:placetype":"venue"
},
  "geometry": {"coordinates":[11.025466,45.864994],"type":"Point"}
}