{
  "type": "Feature",
  "properties": {
    "addr:full":"80048 Sant'anastasia Napoli 80048",
    "addr:postcode":"80048;80048",
    "iso:country":"IT",
    "sg:address":"80048 Sant'anastasia",
    "sg:orig_category":"Medici Specialisti - Neurologia E Psichiatria",
    "sg:phone":"+39 338 364 2530",
    "sg:postcode":"80048",
    "sg:province":"Napoli",
    "wof:name":"Ciriello Rita",
    "wof:placetype":"venue"
},
  "geometry": {"coordinates":[14.397167,40.867355],"type":"Point"}
}