{
  "type": "Feature",
  "properties": {
    "iso:country":"IT",
    "sg:address":"20099 Sesto San Giovanni",
    "sg:city":"Sesto San Giovanni",
    "sg:orig_category":"Servizi E Lavori Per Edilizia E Lavori Pubblici. Banche E Servizi Finanziari",
    "sg:phone":"+39 02 240 4451",
    "sg:postcode":"20099",
    "sg:province":"Milano",
    "wof:name":"Timavo Srl",
    "wof:placetype":"venue"
},
  "geometry": {"coordinates":[9.22862,45.541538],"type":"Point"}
}