{
  "type": "Feature",
  "properties": {
    "addr:full":"41, Via Liguria 41012 Carpi Carpi Modena 41012",
    "addr:postcode":"41012;41012",
    "addr:street":"Via Liguria",
    "iso:country":"IT",
    "sg:address":"41, Via Liguria 41012 Carpi",
    "sg:city":"Carpi",
    "sg:classifiers":[
        {
            "category":"Shopping",
            "subcategory":"Clothing, Apparel, & Fashions",
            "type":"Retail Goods"
        }
    ],
    "sg:phone":"+39 39059641564",
    "sg:postcode":"41012",
    "sg:province":"Modena",
    "sg:tags":[
        "clothes"
    ],
    "wof:name":"Vento Vivo (s.r.l.)",
    "wof:placetype":"venue"
},
  "geometry": {"coordinates":[10.88499,44.764259],"type":"Point"}
}