{
  "type": "Feature",
  "properties": {
    "iso:country":"IT",
    "sg:address":"Via Umberto I, 1; Busca; 12022",
    "sg:city":"Busca",
    "sg:classifiers":[
        {
            "category":"Banks & Credit Unions",
            "subcategory":"Bank",
            "type":"Services"
        }
    ],
    "sg:phone":"+39 0171 933056",
    "sg:postcode":"12022",
    "sg:province":"Cuneo",
    "wof:name":"Cassa Di Risparmio Di Torino",
    "wof:placetype":"venue"
},
  "geometry": {"coordinates":[7.477917,44.516041],"type":"Point"}
}