{
  "type": "Feature",
  "properties": {
    "iso:country":"IT",
    "sg:address":"50143 Firenze",
    "sg:city":"Firenze",
    "sg:orig_category":"Servizi E Lavori Industria Della Gomma. Servizi E Lavori Industria Delle Materie Plastiche. Forniture Per Edilizia E Lavori Pubblici",
    "sg:phone":"+39 055 700087",
    "sg:postcode":"50143",
    "sg:province":"Firenze",
    "wof:name":"Uno - Fa Di Favilli Mauro",
    "wof:placetype":"venue"
},
  "geometry": {"coordinates":[11.220776,43.766079],"type":"Point"}
}