{
  "type": "Feature",
  "properties": {
    "iso:country":"IT",
    "sg:address":"20061 Carugate",
    "sg:city":"Carugate",
    "sg:orig_category":"Metalli E Leghe",
    "sg:phone":"+39 02 925 4724",
    "sg:postcode":"20061",
    "sg:province":"Milano",
    "wof:name":"Gkn Sinter Metals S.p.a.",
    "wof:placetype":"venue"
},
  "geometry": {"coordinates":[9.2939100266,45.5442047119],"type":"Point"}
}