{
  "type": "Feature",
  "properties": {
    "iso:country":"IT",
    "sg:address":"Via Tiepolo, 18 Centrospz 31021 Mogliano Veneto",
    "sg:city":"Mogliano Veneto",
    "sg:classifiers":[
        {
            "category":"Ice Cream",
            "type":"Food & Drink"
        }
    ],
    "sg:phone":"+39 041 597 0122",
    "sg:postcode":"31021",
    "sg:province":"Treviso",
    "sg:tags":[
        "article",
        "gift",
        "glass"
    ],
    "wof:name":"V.g. Cristalli D'arte Snc",
    "wof:placetype":"venue"
},
  "geometry": {"coordinates":[12.242072,45.666286],"type":"Point"}
}