{
  "type": "Feature",
  "properties": {
    "iso:country":"IT",
    "sg:address":"14, Via Michelangeli Gualverio 05018 Orvieto",
    "sg:city":"Orvieto",
    "sg:classifiers":[
        {
            "category":"Food & Beverages",
            "subcategory":"Groceries & Convenience Stores",
            "type":"Retail Goods"
        }
    ],
    "sg:phone":"+39 0763 341820",
    "sg:postcode":"05018",
    "sg:province":"Terni",
    "sg:tags":[
        "drink"
    ],
    "wof:name":"Barberani - Azienda Agricola Vallesanta",
    "wof:placetype":"venue"
},
  "geometry": {"coordinates":[12.069637,42.739304],"type":"Point"}
}