{
  "type": "Feature",
  "properties": {
    "addr:full":"35122 Padova Padova Padova 35122",
    "addr:postcode":"35122;35122",
    "iso:country":"IT",
    "sg:address":"35122 Padova",
    "sg:city":"Padova",
    "sg:orig_category":"Medici. Assicurazioni E Servizi Assicurativi. Avvocati, Notai E Servizi Legali. Professionisti - Studi E Servizi Ed Associazioni Di Interesse Aziendale",
    "sg:phone":"+39 049 878 9811",
    "sg:postcode":"35122",
    "sg:province":"Padova",
    "wof:name":"Lonardi Ubaldo",
    "wof:placetype":"venue"
},
  "geometry": {"coordinates":[11.8704309464,45.4003105164],"type":"Point"}
}