{
  "type": "Feature",
  "properties": {
    "iso:country":"IT",
    "sg:address":"Via G. Cesare 11 20029 Turbigo",
    "sg:city":"Turbigo",
    "sg:classifiers":[
        {
            "category":"Military Area",
            "subcategory":"Naval Base",
            "type":"Public Place"
        }
    ],
    "sg:phone":"+39 0331 899175",
    "sg:postcode":"20029",
    "sg:province":"Milano",
    "sg:tags":[
        "pump",
        "acid"
    ],
    "wof:name":"D.m.c. Pompe Snc",
    "wof:placetype":"venue"
},
  "geometry": {"coordinates":[9.188141,45.463688],"type":"Point"}
}