{
  "type": "Feature",
  "properties": {
    "iso:country":"IT",
    "sg:address":"12075 Garessio",
    "sg:city":"Garessio",
    "sg:orig_category":"Forniture Per Edilizia E Lavori Pubblici. Arredi Ed Attrezzature Per Attivita' Commerciali Ed Artigianali. Forniture Per Attivita' Industriali",
    "sg:phone":"+39 0174 803436",
    "sg:postcode":"12075",
    "sg:province":"Cuneo",
    "wof:name":"Sciolfi Aldo - Aessevetro",
    "wof:placetype":"venue"
},
  "geometry": {"coordinates":[8.0136423111,44.2083015442],"type":"Point"}
}