{
  "type": "Feature",
  "properties": {
    "iso:country":"IT",
    "sg:address":"12040 Genola",
    "sg:city":"Genola",
    "sg:orig_category":"Carrozzine E Passeggini Per Bambini",
    "sg:phone":"+39 0172 68567",
    "sg:postcode":"12040",
    "sg:province":"Cuneo",
    "wof:name":"Centro Infanzia E Giochi Srl",
    "wof:placetype":"venue"
},
  "geometry": {"coordinates":[7.660135,44.597454],"type":"Point"}
}