{
  "type": "Feature",
  "properties": {
    "iso:country":"IT",
    "sg:address":"17023 Ceriale",
    "sg:city":"Ceriale",
    "sg:classifiers":[
        {
            "category":"Farming",
            "subcategory":"Berry Farm",
            "type":"Manufacturing & Wholesale Goods"
        }
    ],
    "sg:phone":"+39 0182 990211",
    "sg:postcode":"17023",
    "sg:province":"Savona",
    "sg:tags":[
        "vegetable",
        "growing",
        "flower",
        "agriculture"
    ],
    "wof:name":"Hortacenter",
    "wof:placetype":"venue"
},
  "geometry": {"coordinates":[8.221686,44.080975],"type":"Point"}
}