{
  "type": "Feature",
  "properties": {
    "iso:country":"IT",
    "sg:address":"47/c, Strada Rocca Grimalda 15076 Ovada",
    "sg:city":"Ovada",
    "sg:classifiers":[
        {
            "category":"Manufacturing",
            "subcategory":"Lumber",
            "type":"Manufacturing & Wholesale Goods"
        }
    ],
    "sg:phone":"+39 39014381393",
    "sg:postcode":"15076",
    "sg:province":"Alessandria",
    "sg:tags":[
        "wood"
    ],
    "wof:name":"C.i.l. Soc.coop.r.l.",
    "wof:placetype":"venue"
},
  "geometry": {"coordinates":[8.648533,44.653103],"type":"Point"}
}