{
  "type": "Feature",
  "properties": {
    "iso:country":"IT",
    "sg:address":"20040 Cambiago",
    "sg:city":"Cambiago",
    "sg:orig_category":"Prodotti E Manufatti In Materie Plastiche. Articoli Per Imballaggio E Confezionamento",
    "sg:phone":"+39 02 950 6445",
    "sg:postcode":"20040",
    "sg:province":"Milano",
    "wof:name":"Plastic Glass Srl",
    "wof:placetype":"venue"
},
  "geometry": {"coordinates":[9.4408407211,45.581325531],"type":"Point"}
}