{
  "type": "Feature",
  "properties": {
    "iso:country":"IT",
    "sg:address":"107, Viale Repubblica 22060 Cabiate",
    "sg:city":"Cabiate",
    "sg:classifiers":[
        {
            "category":"Home & Garden",
            "subcategory":"Home Furnishings",
            "type":"Retail Goods"
        }
    ],
    "sg:phone":"+39 39031756212",
    "sg:postcode":"22060",
    "sg:province":"Como",
    "sg:tags":[
        "household"
    ],
    "wof:name":"Pozzoli (s.r.l.)",
    "wof:placetype":"venue"
},
  "geometry": {"coordinates":[9.174486,45.67474],"type":"Point"}
}