{
  "type": "Feature",
  "properties": {
    "addr:full":"00033 Cave Cave Roma 00033",
    "addr:housenumber":"00033",
    "addr:postcode":"00033",
    "addr:street":"Cave Cave Roma",
    "iso:country":"IT",
    "sg:address":"00033 Cave",
    "sg:city":"Cave",
    "sg:orig_category":"Istituti Di Bellezza",
    "sg:phone":"+39 06 950 8252",
    "sg:postcode":"00033",
    "sg:province":"Roma",
    "wof:name":"Linea Futura Di Chialastri Nazareno",
    "wof:placetype":"venue"
},
  "geometry": {"coordinates":[12.499507,41.900536],"type":"Point"}
}