{
  "type": "Feature",
  "properties": {
    "addr:full":"2, Piazza Cavour 22070 Appiano Gentile Appiano Gentile Como 22070",
    "addr:housenumber":"gentile",
    "addr:postcode":"22070;22070",
    "addr:street":"Piazza Cavour",
    "iso:country":"IT",
    "sg:address":"2, Piazza Cavour 22070 Appiano Gentile",
    "sg:city":"Appiano Gentile",
    "sg:classifiers":[
        {
            "category":"Shopping",
            "subcategory":"Crafts & Fabrics",
            "type":"Retail Goods"
        }
    ],
    "sg:phone":"+39 39031972111",
    "sg:postcode":"22070",
    "sg:province":"Como",
    "wof:name":"Ghioldi G. (s.p.a.)",
    "wof:placetype":"venue"
},
  "geometry": {"coordinates":[9.0358791351,45.7660064697],"type":"Point"}
}