{
  "type": "Feature",
  "properties": {
    "iso:country":"IT",
    "sg:address":"Via Trav. Di Francesca Nord 79c 51015 Monsummano Terme",
    "sg:city":"Monsummano Terme",
    "sg:orig_category":"Ladies' Shoes",
    "sg:phone":"+39 0572 51132",
    "sg:postcode":"51015",
    "sg:province":"Pistoia",
    "wof:name":"Calzaturificio Regal Shoes Di Lapardi Massimo",
    "wof:placetype":"venue"
},
  "geometry": {"coordinates":[10.918524,43.932156],"type":"Point"}
}