{
  "type": "Feature",
  "properties": {
    "iso:country":"IT",
    "sg:address":"61025 Montelabbate",
    "sg:city":"Montelabbate",
    "sg:orig_category":"Sedie E Tavoli - Produzione E Ingrosso",
    "sg:phone":"+39 0721 481152",
    "sg:postcode":"61025",
    "sg:province":"Pesaro E Urbino",
    "wof:name":"Mabel Furniture Srl",
    "wof:placetype":"venue"
},
  "geometry": {"coordinates":[12.817792,43.858711],"type":"Point"}
}