{
  "type": "Feature",
  "properties": {
    "addr:full":"36077 Altavilla Vicentina Altavilla Vicentina Vicenza 36077",
    "addr:postcode":"36077;36077",
    "iso:country":"IT",
    "sg:address":"36077 Altavilla Vicentina",
    "sg:city":"Altavilla Vicentina",
    "sg:orig_category":"Servizi Per Aziende, Manifestazioni E Supporto Agli Scambi Commerciali",
    "sg:phone":"+39 0444 370510",
    "sg:postcode":"36077",
    "sg:province":"Vicenza",
    "wof:name":"Pretto Franco",
    "wof:placetype":"venue"
},
  "geometry": {"coordinates":[11.465689,45.519726],"type":"Point"}
}