{
  "type": "Feature",
  "properties": {
    "addr:full":"Via Spinetta 13 28067 Pernate NO",
    "addr:housenumber":"13",
    "addr:postcode":"28067",
    "addr:street":"Via Spinetta",
    "iso:country":"IT",
    "sg:address":"Via Spinetta 13 28067 Pernate",
    "sg:classifiers":[
        {
            "category":"Shopping",
            "subcategory":"Crafts & Fabrics",
            "type":"Retail Goods"
        }
    ],
    "sg:phone":"+39 0321 637081",
    "sg:province":"NO",
    "sg:tags":[
        "ladies'",
        "wear"
    ],
    "wof:name":"Tessitura Di Novara S.p.a.",
    "wof:placetype":"venue"
},
  "geometry": {"coordinates":[8.6763629913,45.4629707336],"type":"Point"}
}