{
  "type": "Feature",
  "properties": {
    "iso:country":"IT",
    "sg:address":"Via Passanti 334 84018 Scafati",
    "sg:city":"Scafati",
    "sg:classifiers":[
        {
            "category":"Restaurant",
            "type":"Food & Drink"
        }
    ],
    "sg:phone":"+39 081 850 8090",
    "sg:postcode":"84018",
    "sg:province":"Salerno",
    "sg:tags":[
        "pasta"
    ],
    "sg:website":"www.pastificiolabor.it",
    "wof:name":"Labor S.r.l.",
    "wof:placetype":"venue"
},
  "geometry": {"coordinates":[14.5097551346,40.7441864014],"type":"Point"}
}