{
  "type": "Feature",
  "properties": {
    "iso:country":"IT",
    "sg:address":"54, Via Statale 25011 Calcinato",
    "sg:city":"Calcinato",
    "sg:classifiers":[
        {
            "category":"Wholesale",
            "subcategory":"Drugs",
            "type":"Manufacturing & Wholesale Goods"
        }
    ],
    "sg:phone":"+39 030 963 7158",
    "sg:postcode":"25011",
    "sg:province":"Brescia",
    "sg:tags":[
        "chemical",
        "pharmaceutical"
    ],
    "wof:name":"Microtool Srl",
    "wof:placetype":"venue"
},
  "geometry": {"coordinates":[10.378634,45.483433],"type":"Point"}
}