{
  "type": "Feature",
  "properties": {
    "iso:country":"IT",
    "sg:address":"12, Via Mascheraio 44100 Ferrara",
    "sg:city":"Ferrara",
    "sg:classifiers":[
        {
            "category":"Professional",
            "subcategory":"Engineering",
            "type":"Services"
        }
    ],
    "sg:phone":"+39 0532 240069",
    "sg:postcode":"44100",
    "sg:province":"Ferrara",
    "sg:tags":[
        "machine",
        "-",
        "mechanical"
    ],
    "wof:name":"Officine Spettoli",
    "wof:placetype":"venue"
},
  "geometry": {"coordinates":[11.62344,44.840496],"type":"Point"}
}