{
  "type": "Feature",
  "properties": {
    "iso:country":"IT",
    "sg:address":"00176 Roma",
    "sg:city":"Roma",
    "sg:orig_category":"Valvole E Apparecchiature Di Misura",
    "sg:phone":"+39 06 701 3545",
    "sg:postcode":"00176",
    "sg:province":"Roma",
    "wof:name":"Silcam Srl.",
    "wof:placetype":"venue"
},
  "geometry": {"coordinates":[12.532671,41.890278],"type":"Point"}
}