{
  "type": "Feature",
  "properties": {
    "iso:country":"IT",
    "sg:address":"Vle Guglielmo Marconi 201 80020 Casavatore",
    "sg:city":"Casavatore",
    "sg:classifiers":[
        {
            "category":"Retail",
            "subcategory":"Repair Shop",
            "type":"Services"
        }
    ],
    "sg:phone":"+39 081 738 3666",
    "sg:postcode":"80020",
    "sg:province":"Napoli",
    "sg:tags":[
        "lamp",
        "part"
    ],
    "sg:website":"www.fratellimarino.it",
    "wof:name":"Am Dei Fratelli Marino Srl",
    "wof:placetype":"venue"
},
  "geometry": {"coordinates":[14.278016,40.895718],"type":"Point"}
}