{
  "type": "Feature",
  "properties": {
    "iso:country":"IT",
    "sg:address":"17100 Savona",
    "sg:city":"Savona",
    "sg:orig_category":"Nautica. Automobili E Mezzi Di Trasporto",
    "sg:phone":"+39 019 881506",
    "sg:postcode":"17100",
    "sg:province":"Savona",
    "wof:name":"Nova Snc",
    "wof:placetype":"venue"
},
  "geometry": {"coordinates":[8.445505,44.283283],"type":"Point"}
}