{
  "type": "Feature",
  "properties": {
    "iso:country":"IT",
    "sg:address":"3, Via Sparate 40011 Anzola Dell'emilia",
    "sg:classifiers":[
        {
            "category":"Farming",
            "subcategory":"Livestock Farm",
            "type":"Manufacturing & Wholesale Goods"
        }
    ],
    "sg:phone":"+39 39051739310",
    "sg:postcode":"40011",
    "sg:province":"Bologna",
    "sg:tags":[
        "agriculture"
    ],
    "wof:name":"Cooperativa Fra Produttori Agricoli - Soc. Coop. (a.r.l.)",
    "wof:placetype":"venue"
},
  "geometry": {"coordinates":[11.156491,44.587601],"type":"Point"}
}