{
  "type": "Feature",
  "properties": {
    "iso:country":"IT",
    "sg:address":"57126 Livorno",
    "sg:city":"Livorno",
    "sg:orig_category":"Termotecnica E Riscaldamento, Apparecchiature E Servizi",
    "sg:phone":"+39 0586 809000",
    "sg:postcode":"57126",
    "sg:province":"Livorno",
    "wof:name":"Marinozzi Geom. Giuseppe",
    "wof:placetype":"venue"
},
  "geometry": {"coordinates":[10.307695,43.542324],"type":"Point"}
}