{
  "type": "Feature",
  "properties": {
    "iso:country":"IT",
    "sg:address":"47, Via Palladio A. 44012 Bondeno",
    "sg:city":"Bondeno",
    "sg:classifiers":[
        {
            "category":"Professional",
            "subcategory":"Engineering",
            "type":"Services"
        }
    ],
    "sg:phone":"+39 0532 897107",
    "sg:postcode":"44012",
    "sg:province":"Ferrara",
    "sg:tags":[
        "machine",
        "-",
        "mechanical"
    ],
    "wof:name":"Eltec Srl",
    "wof:placetype":"venue"
},
  "geometry": {"coordinates":[11.62044,44.837894],"type":"Point"}
}