{
  "type": "Feature",
  "properties": {
    "iso:country":"IT",
    "sg:address":"Via Locatelli 55/a; Villa Di Serio; 24020",
    "sg:city":"Villa di Serio",
    "sg:classifiers":[
        {
            "category":"Banks & Credit Unions",
            "subcategory":"Bank",
            "type":"Services"
        }
    ],
    "sg:phone":"+39 035 661328",
    "sg:postcode":"24020",
    "sg:province":"Bergamo",
    "wof:name":"Credito Bergamasco Spa",
    "wof:placetype":"venue"
},
  "geometry": {"coordinates":[9.733466,45.721531],"type":"Point"}
}