{
  "type": "Feature",
  "properties": {
    "iso:country":"IT",
    "sg:address":"133, Via Edison Alva Thomas 31020 Villorba",
    "sg:city":"Villorba",
    "sg:classifiers":[
        {
            "category":"Professional",
            "subcategory":"Printing & Photocopies",
            "type":"Services"
        }
    ],
    "sg:phone":"+39 0422 919352",
    "sg:postcode":"31020",
    "sg:province":"Treviso",
    "wof:name":"Grafiche Pietrobon (s.r.l.)",
    "wof:placetype":"venue"
},
  "geometry": {"coordinates":[12.2495088577,45.7277679443],"type":"Point"}
}