{
  "type": "Feature",
  "properties": {
    "iso:country":"IT",
    "sg:address":"102, Via Addolorata 62019 Recanati",
    "sg:city":"Recanati",
    "sg:classifiers":[
        {
            "category":"Home & Garden",
            "subcategory":"Home Furnishings",
            "type":"Retail Goods"
        }
    ],
    "sg:phone":"+39 39071980425",
    "sg:postcode":"62019",
    "sg:province":"Macerata",
    "sg:tags":[
        "household"
    ],
    "wof:name":"Falegnameria Electa Di Marconi A. & Carletti M.",
    "wof:placetype":"venue"
},
  "geometry": {"coordinates":[13.456262,43.300747],"type":"Point"}
}