{
  "type": "Feature",
  "properties": {
    "iso:country":"IT",
    "sg:address":"00144 Roma",
    "sg:city":"Roma",
    "sg:classifiers":[
        {
            "category":"Health Services",
            "subcategory":"Health Practitioner",
            "type":"Services"
        }
    ],
    "sg:phone":"+39 06 592 3723",
    "sg:postcode":"00144",
    "sg:province":"Roma",
    "sg:tags":[
        "medici"
    ],
    "wof:name":"Minischetti Giovanni",
    "wof:placetype":"venue"
},
  "geometry": {"coordinates":[12.474485,41.829754],"type":"Point"}
}