{
  "type": "Feature",
  "properties": {
    "iso:country":"IT",
    "sg:address":"35, Via Buia 55100 Lucca",
    "sg:city":"Lucca",
    "sg:classifiers":[
        {
            "category":"Shopping",
            "subcategory":"Jewelry",
            "type":"Retail Goods"
        }
    ],
    "sg:phone":"+39 0583 496002",
    "sg:postcode":"55100",
    "sg:province":"Lucca",
    "sg:tags":[
        "jewellery"
    ],
    "wof:name":"Linea Oro (s.r.l.)",
    "wof:placetype":"venue"
},
  "geometry": {"coordinates":[10.504038,43.843914],"type":"Point"}
}