{
  "type": "Feature",
  "properties": {
    "addr:full":"00119 Roma Roma Roma 00119",
    "addr:postcode":"00119;00119",
    "iso:country":"IT",
    "sg:address":"00119 Roma",
    "sg:city":"Roma",
    "sg:orig_category":"Automazione E Macchine Per Ufficio",
    "sg:phone":"+39 06 5635 2629",
    "sg:postcode":"00119",
    "sg:province":"Roma",
    "wof:name":"Shopping - Line Srl",
    "wof:placetype":"venue"
},
  "geometry": {"coordinates":[12.300567,41.765652],"type":"Point"}
}