{
  "type": "Feature",
  "properties": {
    "iso:country":"IT",
    "sg:address":"26041 Casalmaggiore",
    "sg:city":"Casalbellotto",
    "sg:orig_category":"Utensili Meccanici E Materiali. Forniture Per Attivita' Industriali",
    "sg:phone":"+39 0375 59527",
    "sg:postcode":"26041",
    "sg:province":"Cremona",
    "wof:name":"Carnevali Dino Snc",
    "wof:placetype":"venue"
},
  "geometry": {"coordinates":[10.479156,44.962132],"type":"Point"}
}