{
  "type": "Feature",
  "properties": {
    "iso:country":"IT",
    "sg:address":"Via Roma 15 36040 Torri Di Quartesolo",
    "sg:city":"Torri di Quartesolo",
    "sg:classifiers":[
        {
            "category":"Structure",
            "subcategory":"Office Building",
            "type":"Public Place"
        }
    ],
    "sg:phone":"+39 0444 265800",
    "sg:postcode":"36040",
    "sg:province":"Vicenza",
    "sg:tags":[
        "shelf",
        "system"
    ],
    "sg:website":"www.torri.it",
    "wof:name":"Torri S.p.a.",
    "wof:placetype":"venue"
},
  "geometry": {"coordinates":[11.620742,45.517033],"type":"Point"}
}