{
  "type": "Feature",
  "properties": {
    "iso:country":"IT",
    "sg:address":"20010 Cornaredo",
    "sg:city":"Cornaredo",
    "sg:orig_category":"Utensili Meccanici E Materiali",
    "sg:phone":"+39 02 9356 3102",
    "sg:postcode":"20010",
    "sg:province":"Milano",
    "wof:name":"M.p. Diamant Snc",
    "wof:placetype":"venue"
},
  "geometry": {"coordinates":[9.030807,45.500099],"type":"Point"}
}