{
  "type": "Feature",
  "properties": {
    "iso:country":"IT",
    "sg:address":"23891 Barzano'",
    "sg:orig_category":"Ombrelli Ed Ombrelloni",
    "sg:phone":"+39 039 955655",
    "sg:postcode":"23891",
    "sg:province":"Lecco",
    "sg:website":"http://www.cortimanifattura.it",
    "wof:name":"Manifattura Corti Srl",
    "wof:placetype":"venue"
},
  "geometry": {"coordinates":[9.314531,45.731148],"type":"Point"}
}