{
  "type": "Feature",
  "properties": {
    "iso:country":"IT",
    "sg:address":"50129 Firenze",
    "sg:city":"Firenze",
    "sg:classifiers":[
        {
            "category":"Communications",
            "subcategory":"Film & Video Production",
            "type":"Services"
        }
    ],
    "sg:phone":"+39 055 463 0428",
    "sg:postcode":"50129",
    "sg:province":"Firenze",
    "sg:tags":[
        "certificates",
        "photo",
        "auxiliary",
        "reproduction",
        "drawing"
    ],
    "wof:name":"Insogest Sas",
    "wof:placetype":"venue"
},
  "geometry": {"coordinates":[11.255213,43.78418],"type":"Point"}
}