{
  "type": "Feature",
  "properties": {
    "addr:full":"20137 Milano Milano Milano 20137",
    "addr:postcode":"20137;20137",
    "iso:country":"IT",
    "sg:address":"20137 Milano",
    "sg:city":"Milano",
    "sg:orig_category":"Abbigliamento Esterno, Maglierie E Pelliccerie. Shopping",
    "sg:phone":"+39 02 7012 6926",
    "sg:postcode":"20137",
    "sg:province":"Milano",
    "sg:website":"http://digilander.iol.it/fantasiemariage",
    "wof:name":"Avanzo Massimo - Fantasie Mariage",
    "wof:placetype":"venue"
},
  "geometry": {"coordinates":[9.130579,45.405968],"type":"Point"}
}