{
  "type": "Feature",
  "properties": {
    "addr:full":"43038 Sala Baganza Sala Baganza Parma 43038",
    "addr:housenumber":"baganza",
    "addr:postcode":"43038;43038",
    "addr:street":"Parma",
    "iso:country":"IT",
    "sg:address":"43038 Sala Baganza",
    "sg:city":"Sala Baganza",
    "sg:orig_category":"Imprese Di Costruzioni Civili Ed Industriali",
    "sg:phone":"+39 0521 836350",
    "sg:postcode":"43038",
    "sg:province":"Parma",
    "wof:name":"C.e.t.e.m. (s.n.c.)",
    "wof:placetype":"venue"
},
  "geometry": {"coordinates":[10.232283,44.716385],"type":"Point"}
}