{
  "type": "Feature",
  "properties": {
    "addr:full":"25046 Cazzago San Martino Cazzago San Martino Brescia 25046",
    "addr:postcode":"25046;25046",
    "iso:country":"IT",
    "sg:address":"25046 Cazzago San Martino",
    "sg:city":"Cazzago San Martino",
    "sg:orig_category":"Servizi E Lavori Per Abbigliamento E Pelletterie",
    "sg:phone":"+39 030 775 0605",
    "sg:postcode":"25046",
    "sg:province":"Brescia",
    "wof:name":"Quarantini Gabriella",
    "wof:placetype":"venue"
},
  "geometry": {"coordinates":[10.037611,45.571709],"type":"Point"}
}