{
  "type": "Feature",
  "properties": {
    "addr:full":"33, Via Provinciale 10010 Loranze' Torino 10010",
    "addr:postcode":"10010;10010",
    "addr:street":"Via Provinciale;' Torino",
    "iso:country":"IT",
    "sg:address":"33, Via Provinciale 10010 Loranze'",
    "sg:classifiers":[
        {
            "category":"Utilities",
            "subcategory":"Electric",
            "type":"Services"
        }
    ],
    "sg:phone":"+39 39012553644",
    "sg:postcode":"10010",
    "sg:province":"Torino",
    "sg:tags":[
        "component",
        "electronic"
    ],
    "wof:name":"Argenterie Del Canavese (s.r.l.)",
    "wof:placetype":"venue"
},
  "geometry": {"coordinates":[7.822974,45.442783],"type":"Point"}
}