{
  "type": "Feature",
  "properties": {
    "addr:full":"Via Loc. Crevada 31020 Refrontolo Refrontolo Treviso 31020",
    "addr:postcode":"31020;31020",
    "addr:street":"Via Loc. Crevada",
    "iso:country":"IT",
    "sg:address":"Via Loc. Crevada 31020 Refrontolo",
    "sg:city":"Refrontolo",
    "sg:classifiers":[
        {
            "category":"Autos & Motor Vehicles",
            "subcategory":"Automobile Sales",
            "type":"Retail Goods"
        }
    ],
    "sg:phone":"+39 0438 840281",
    "sg:postcode":"31020",
    "sg:province":"Treviso",
    "sg:tags":[
        "industrial"
    ],
    "wof:name":"Marmitte Zara (s.p.a.)",
    "wof:placetype":"venue"
},
  "geometry": {"coordinates":[12.242072,45.666286],"type":"Point"}
}