{
  "type": "Feature",
  "properties": {
    "iso:country":"IT",
    "sg:address":"41011 Campogalliano",
    "sg:city":"Campogalliano",
    "sg:orig_category":"Hobbistica",
    "sg:phone":"+39 059 525114",
    "sg:postcode":"41011",
    "sg:province":"Modena",
    "wof:name":"Re El Toys Srl",
    "wof:placetype":"venue"
},
  "geometry": {"coordinates":[10.840446,44.696285],"type":"Point"}
}