{
  "type": "Feature",
  "properties": {
    "iso:country":"IT",
    "sg:address":"Via Salemi 36; Mazara; 91026",
    "sg:classifiers":[
        {
            "category":"Banks & Credit Unions",
            "subcategory":"Bank",
            "type":"Services"
        }
    ],
    "sg:phone":"+39 0923 908898",
    "sg:postcode":"91026",
    "sg:province":"Trapani",
    "wof:name":"Credito Italiano Spa",
    "wof:placetype":"venue"
},
  "geometry": {"coordinates":[12.594912,37.654381],"type":"Point"}
}