{
  "type": "Feature",
  "properties": {
    "iso:country":"IT",
    "sg:address":"20050 Lesmo",
    "sg:city":"Lesmo",
    "sg:orig_category":"Assicurazioni",
    "sg:phone":"+39 039 698 0534",
    "sg:postcode":"20050",
    "sg:province":"Milano",
    "wof:name":"Bassignana Federico",
    "wof:placetype":"venue"
},
  "geometry": {"coordinates":[9.306314,45.651344],"type":"Point"}
}