{
  "type": "Feature",
  "properties": {
    "iso:country":"IT",
    "sg:address":"10040 Rivalta Di Torino",
    "sg:city":"Rivalta di Torino",
    "sg:orig_category":"Serramenti Ed Infissi",
    "sg:phone":"+39 011 900 2179",
    "sg:postcode":"10040",
    "sg:province":"Torino",
    "wof:name":"Metal Serramenti 2000 Di Crepaldi Daniele",
    "wof:placetype":"venue"
},
  "geometry": {"coordinates":[7.55243,45.009834],"type":"Point"}
}