{
  "type": "Feature",
  "properties": {
    "iso:country":"IT",
    "sg:address":"20017 Rho",
    "sg:city":"Rho",
    "sg:orig_category":"Articoli Da Regalo. Forniture Per Uffici. Regalistica Aziendale",
    "sg:phone":"+39 02 9390 9580",
    "sg:postcode":"20017",
    "sg:province":"Milano",
    "wof:name":"Inoxcrom Spa",
    "wof:placetype":"venue"
},
  "geometry": {"coordinates":[9.066331,45.526413],"type":"Point"}
}