{
  "type": "Feature",
  "properties": {
    "addr:full":"20133 Milano Milano Milano 20133",
    "addr:postcode":"20133;20133",
    "iso:country":"IT",
    "sg:address":"20133 Milano",
    "sg:city":"Milano",
    "sg:orig_category":"Servizi Editoriali. Professionisti - Studi E Servizi Ed Associazioni Di Interesse Aziendale",
    "sg:phone":"+39 02 7063 0911",
    "sg:postcode":"20133",
    "sg:province":"Milano",
    "wof:name":"Italia Vittorio",
    "wof:placetype":"venue"
},
  "geometry": {"coordinates":[9.23431,45.48048],"type":"Point"}
}