{
  "type": "Feature",
  "properties": {
    "iso:country":"IT",
    "sg:address":"22070 Vertemate Minoprio",
    "sg:city":"Minoprio",
    "sg:orig_category":"Macchine, Impianti Ed Attrezzature Per Abbigliamento E Pelletterie. Apparecchiature Ed Attrezzature Meccaniche. Elettrotecnica Industriale, Prodotti E Apparecchiature",
    "sg:phone":"+39 031 900020",
    "sg:postcode":"22070",
    "sg:province":"Como",
    "wof:name":"Ducap Sas",
    "wof:placetype":"venue"
},
  "geometry": {"coordinates":[9.127478,45.734386],"type":"Point"}
}