{
  "type": "Feature",
  "properties": {
    "iso:country":"IT",
    "sg:address":"26, Via Aporti Ferrante 20127 Milano",
    "sg:city":"Milano",
    "sg:classifiers":[
        {
            "category":"Utilities",
            "subcategory":"Electric",
            "type":"Services"
        }
    ],
    "sg:phone":"+39 390 226 8181",
    "sg:postcode":"20127",
    "sg:province":"Milano",
    "sg:tags":[
        "energy"
    ],
    "wof:name":"Cable And Wireless S.p.a.",
    "wof:placetype":"venue"
},
  "geometry": {"coordinates":[9.210512,45.490391],"type":"Point"}
}