{
  "type": "Feature",
  "properties": {
    "iso:country":"IT",
    "sg:address":"50013 Campi Bisenzio",
    "sg:city":"Campi Bisenzio",
    "sg:orig_category":"Acciaierie E Fonderie",
    "sg:phone":"+39 055 896 0747",
    "sg:postcode":"50013",
    "sg:province":"Firenze",
    "wof:name":"Fonderia Montagna",
    "wof:placetype":"venue"
},
  "geometry": {"coordinates":[11.126132,43.834072],"type":"Point"}
}