{
  "type": "Feature",
  "properties": {
    "iso:country":"IT",
    "sg:address":"15, Via Pace 84096 Montecorvino Rovella",
    "sg:city":"Montecorvino Rovella",
    "sg:classifiers":[
        {
            "category":"Professional",
            "subcategory":"Printing & Photocopies",
            "type":"Services"
        }
    ],
    "sg:phone":"+39 39089867712",
    "sg:postcode":"84096",
    "sg:province":"Salerno",
    "wof:name":"Tipolito L'unione S.r.l. Nio Buong",
    "wof:placetype":"venue"
},
  "geometry": {"coordinates":[14.9784078598,40.6923866272],"type":"Point"}
}