{
  "type": "Feature",
  "properties": {
    "addr:full":"1, Via Pasubio 36066 Sandrigo Sandrigo Vicenza 36066",
    "addr:postcode":"36066;36066",
    "addr:street":"Via Pasubio",
    "iso:country":"IT",
    "sg:address":"1, Via Pasubio 36066 Sandrigo",
    "sg:city":"Sandrigo",
    "sg:classifiers":[
        {
            "category":"Shopping",
            "subcategory":"Jewelry",
            "type":"Retail Goods"
        }
    ],
    "sg:phone":"+39 0444 657344",
    "sg:postcode":"36066",
    "sg:province":"Vicenza",
    "sg:tags":[
        "jewellery"
    ],
    "wof:name":"Auritalia (s.p.a.)",
    "wof:placetype":"venue"
},
  "geometry": {"coordinates":[11.545586,45.639915],"type":"Point"}
}