{
  "type": "Feature",
  "properties": {
    "iso:country":"IT",
    "sg:address":"42015 Correggio",
    "sg:orig_category":"Agenzie D'affari E Servizi Commerciali",
    "sg:phone":"+39 0522 641805",
    "sg:postcode":"42015",
    "sg:province":"Reggio Nell'Emilia",
    "wof:name":"Niji Italiana Spa",
    "wof:placetype":"venue"
},
  "geometry": {"coordinates":[10.247352,44.326279],"type":"Point"}
}