{
  "type": "Feature",
  "properties": {
    "addr:full":"80026 Casoria Casoria Napoli 80026",
    "addr:postcode":"80026;80026",
    "iso:country":"IT",
    "sg:address":"80026 Casoria",
    "sg:city":"Casoria",
    "sg:orig_category":"Materiali Semilavorati Metallici",
    "sg:phone":"+39 081 584 2533",
    "sg:postcode":"80026",
    "sg:province":"Napoli",
    "wof:name":"De Pasquale Ciro",
    "wof:placetype":"venue"
},
  "geometry": {"coordinates":[14.252847,40.882393],"type":"Point"}
}