{
  "type": "Feature",
  "properties": {
    "addr:full":"41026 Pavullo Nel Frignano Pavullo nel Frignano Modena 41026",
    "addr:postcode":"41026;41026",
    "addr:street":"Nel Frignano",
    "iso:country":"IT",
    "sg:address":"41026 Pavullo Nel Frignano",
    "sg:city":"Pavullo nel Frignano",
    "sg:orig_category":"Macchine, Impianti Ed Attrezzature Per Industria Alimentare E Bevande",
    "sg:phone":"+39 0536 21226",
    "sg:postcode":"41026",
    "sg:province":"Modena",
    "wof:name":"Carnevali Lina",
    "wof:placetype":"venue"
},
  "geometry": {"coordinates":[10.833505,44.340073],"type":"Point"}
}