{
  "type": "Feature",
  "properties": {
    "iso:country":"IT",
    "sg:address":"42014 Castellarano",
    "sg:orig_category":"Automazione E Robotica - Apparecchiature E Componenti",
    "sg:phone":"+39 0536 851243",
    "sg:postcode":"42014",
    "sg:province":"Reggio Nell'Emilia",
    "wof:name":"Studio 1 Srl",
    "wof:placetype":"venue"
},
  "geometry": {"coordinates":[10.680349,44.4827],"type":"Point"}
}