{
  "type": "Feature",
  "properties": {
    "addr:full":"15, Via Cinque Giornate Di Milano 59100 Prato Prato Prato 59100",
    "addr:postcode":"59100;59100",
    "addr:street":"Via Cinque Giornate Di Milano",
    "iso:country":"IT",
    "sg:address":"15, Via Cinque Giornate Di Milano 59100 Prato",
    "sg:city":"Prato",
    "sg:classifiers":[
        {
            "category":"Shopping",
            "subcategory":"Clothing, Apparel, & Fashions",
            "type":"Retail Goods"
        }
    ],
    "sg:phone":"+39 0574 622481",
    "sg:postcode":"59100",
    "sg:province":"Prato",
    "sg:tags":[
        "clothes"
    ],
    "wof:name":"Pastacaldi Romano (s.r.l.)",
    "wof:placetype":"venue"
},
  "geometry": {"coordinates":[11.042219,43.86034],"type":"Point"}
}