{
  "type": "Feature",
  "properties": {
    "iso:country":"IT",
    "sg:address":"57025 Piombino",
    "sg:city":"Piombino",
    "sg:orig_category":"Studi E Consulenze Amministrative, Commerciali E Aziendali. Consulenze Tecniche, Amministrative E Perizie. Professionisti - Studi E Servizi Ed Associazioni Di Interesse Aziendale",
    "sg:phone":"+39 0565 221841",
    "sg:postcode":"57025",
    "sg:province":"Livorno",
    "wof:name":"Baggiani Maria Paola",
    "wof:placetype":"venue"
},
  "geometry": {"coordinates":[10.532241,42.924057],"type":"Point"}
}