{
  "type": "Feature",
  "properties": {
    "iso:country":"IT",
    "sg:address":"37057 San Giovanni Lupatoto",
    "sg:city":"San Giovanni Lupatoto",
    "sg:orig_category":"Forniture Per Edilizia E Lavori Pubblici",
    "sg:phone":"+39 045 925 1411",
    "sg:postcode":"37057",
    "sg:province":"Verona",
    "wof:name":"Ricci Mirco",
    "wof:placetype":"venue"
},
  "geometry": {"coordinates":[11.0216226578,45.3803062439],"type":"Point"}
}