{
  "type": "Feature",
  "properties": {
    "iso:country":"IT",
    "sg:address":"Corso Vittorio Emanuele Ii 93, 10100 Turin, To",
    "sg:classifiers":[
        {
            "category":"Banks & Credit Unions",
            "subcategory":"Bank",
            "type":"Services"
        }
    ],
    "wof:name":"La Centrale Dei Bilancri Srl",
    "wof:placetype":"venue"
},
  "geometry": {"coordinates":[7.669452,45.065937],"type":"Point"}
}