{
  "type": "Feature",
  "properties": {
    "iso:country":"IT",
    "sg:address":"21048 Solbiate Arno",
    "sg:city":"Solbiate Arno",
    "sg:orig_category":"Servizi Ausiliari Di Analisi, Controllo E Ricerca",
    "sg:phone":"+39 0331 991317",
    "sg:postcode":"21048",
    "sg:province":"Varese",
    "wof:name":"Ircm Srl",
    "wof:placetype":"venue"
},
  "geometry": {"coordinates":[8.746887,45.778172],"type":"Point"}
}