{
  "type": "Feature",
  "properties": {
    "iso:country":"IT",
    "sg:address":"Via Per Novedrate 123 22066 Mariano Comense",
    "sg:city":"Mariano Comense",
    "sg:classifiers":[
        {
            "category":"Government",
            "subcategory":"Court House",
            "type":"Public Place"
        }
    ],
    "sg:phone":"+39 031 747676",
    "sg:postcode":"22066",
    "sg:province":"Como",
    "sg:tags":[
        "accommodation",
        "furniture"
    ],
    "wof:name":"Ballabio Export Snc",
    "wof:placetype":"venue"
},
  "geometry": {"coordinates":[9.159245,45.704453],"type":"Point"}
}