{
  "type": "Feature",
  "properties": {
    "iso:country":"IT",
    "sg:address":"Piazza Marconi 9 - 12; Nola; 80035",
    "sg:city":"Nola",
    "sg:classifiers":[
        {
            "category":"Banks & Credit Unions",
            "subcategory":"Bank",
            "type":"Services"
        }
    ],
    "sg:phone":"+39 081 822 4111",
    "sg:postcode":"80035",
    "sg:province":"Napoli",
    "wof:name":"Banco Di Napoli Spa",
    "wof:placetype":"venue"
},
  "geometry": {"coordinates":[14.529914,40.92775],"type":"Point"}
}