{
  "type": "Feature",
  "properties": {
    "iso:country":"IT",
    "sg:address":"156, V. Simone Da Corbetta 20011 Corbetta",
    "sg:city":"Corbetta",
    "sg:classifiers":[
        {
            "category":"Manufacturing",
            "subcategory":"Rubber & Plastics",
            "type":"Manufacturing & Wholesale Goods"
        }
    ],
    "sg:phone":"+39 39029721851",
    "sg:postcode":"20011",
    "sg:province":"Milano",
    "sg:website":"http://www.mariolombardini.com:ws_end: :mark:ws:http://www.paginegialle.it/mariolombardini",
    "wof:name":"Lombardini Mario Srl",
    "wof:placetype":"venue"
},
  "geometry": {"coordinates":[8.9120349884,45.4725418091],"type":"Point"}
}