{
  "type": "Feature",
  "properties": {
    "addr:full":"5/a, Via Moretto 31028 Vazzola Vazzola Treviso 31028",
    "addr:housenumber":"5 / a",
    "addr:postcode":"31028;31028",
    "addr:street":"Via Moretto",
    "iso:country":"IT",
    "sg:address":"5/a, Via Moretto 31028 Vazzola",
    "sg:city":"Vazzola",
    "sg:classifiers":[
        {
            "category":"Shopping",
            "subcategory":"Stationery & Office Supplies",
            "type":"Retail Goods"
        }
    ],
    "sg:phone":"+39 0438 441453",
    "sg:postcode":"31028",
    "sg:province":"Treviso",
    "sg:tags":[
        "professional"
    ],
    "wof:name":"Rico & C. Snc",
    "wof:placetype":"venue"
},
  "geometry": {"coordinates":[12.2420721054,45.6662864685],"type":"Point"}
}