{
  "type": "Feature",
  "properties": {
    "addr:full":"00155 Roma Roma Roma 00155",
    "addr:postcode":"00155;00155",
    "iso:country":"IT",
    "sg:address":"00155 Roma",
    "sg:city":"Roma",
    "sg:orig_category":"Prodotti Di Base E Forniture Per Industria Alimentare E Bevande. Macchine, Impianti Ed Attrezzature Per Industria Alimentare E Bevande. Frigotecnica, Apparecchiature E Servizi. Macchine E Impianti Per",
    "sg:phone":"+39 06 218 4396",
    "sg:postcode":"00155",
    "sg:province":"Roma",
    "wof:name":"Frigotermo Romana Di Luigi Corsetti",
    "wof:placetype":"venue"
},
  "geometry": {"coordinates":[12.3758935928,42.1130142212],"type":"Point"}
}