{
  "type": "Feature",
  "properties": {
    "iso:country":"IT",
    "sg:address":"90020 Castellana Sicula",
    "sg:city":"Calcarelli",
    "sg:orig_category":"Servizi E Lavori Per Arredamento E Industria Del Legno. Servizi E Lavori Per Edilizia E Lavori Pubblici",
    "sg:phone":"+39 0921 562525",
    "sg:postcode":"90020",
    "sg:province":"Palermo",
    "wof:name":"Ventimiglia Matteo",
    "wof:placetype":"venue"
},
  "geometry": {"coordinates":[14.043098,37.781857],"type":"Point"}
}