{
  "type": "Feature",
  "properties": {
    "iso:country":"IT",
    "sg:address":"Via Mammianese Nord 47 51017 Pescia",
    "sg:city":"Pescia",
    "sg:classifiers":[
        {
            "category":"Manufacturing",
            "subcategory":"Chemicals & Compounds",
            "type":"Manufacturing & Wholesale Goods"
        }
    ],
    "sg:phone":"+39 0572 476874",
    "sg:postcode":"51017",
    "sg:province":"Pistoia",
    "sg:tags":[
        "base"
    ],
    "sg:website":"www.madras.it",
    "wof:name":"New Madras Srl",
    "wof:placetype":"venue"
},
  "geometry": {"coordinates":[10.691649,43.912922],"type":"Point"}
}