{
  "type": "Feature",
  "properties": {
    "iso:country":"IT",
    "sg:address":"Via Del Perlar 98-98/a 37135 Verona",
    "sg:city":"Verona",
    "sg:classifiers":[
        {
            "category":"Retail",
            "subcategory":"Car Wash",
            "type":"Services"
        }
    ],
    "sg:phone":"+39 045 500855",
    "sg:postcode":"37135",
    "sg:province":"Verona",
    "sg:tags":[
        "machine",
        "metal",
        "stamping",
        "sheet"
    ],
    "sg:website":"www.zape.it",
    "wof:name":"Zape' Spa",
    "wof:placetype":"venue"
},
  "geometry": {"coordinates":[10.968408,45.410362],"type":"Point"}
}