{
  "type": "Feature",
  "properties": {
    "iso:country":"IT",
    "sg:address":"00146 Roma",
    "sg:city":"Roma",
    "sg:orig_category":"Scuole E Servizi Scolastici. Ricerca, Selezione E Formazione Del Personale",
    "sg:phone":"+39 06 559 5300",
    "sg:postcode":"00146",
    "sg:province":"Roma",
    "sg:website":"http://www.jacsonschool.it",
    "wof:name":"Jacson School",
    "wof:placetype":"venue"
},
  "geometry": {"coordinates":[12.468241,41.869984],"type":"Point"}
}