{
  "type": "Feature",
  "properties": {
    "iso:country":"IT",
    "sg:address":"25, Via Capistrano 00173 Roma",
    "sg:city":"Roma",
    "sg:classifiers":[
        {
            "category":"Bars & Pubs",
            "subcategory":"Nightclub",
            "type":"Food & Drink"
        }
    ],
    "sg:phone":"+39 06 7290 1644",
    "sg:postcode":"00173",
    "sg:province":"Roma",
    "sg:tags":[
        "cake",
        "bread"
    ],
    "wof:name":"Piter Pan Di Baretta Giulio S.a.s.",
    "wof:placetype":"venue"
},
  "geometry": {"coordinates":[12.491615,41.863758],"type":"Point"}
}