{
  "type": "Feature",
  "properties": {
    "addr:full":"Via Xx Settembre 31; Torino; 10121 Torino Torino 10121",
    "addr:housenumber":"31",
    "addr:postcode":"10121;10121",
    "addr:street":"Via Xx Settembre",
    "iso:country":"IT",
    "sg:address":"Via Xx Settembre 31; Torino; 10121",
    "sg:city":"Torino",
    "sg:classifiers":[
        {
            "category":"Banks & Credit Unions",
            "subcategory":"Bank",
            "type":"Services"
        }
    ],
    "sg:phone":"+39 0116621",
    "sg:postcode":"10121",
    "sg:province":"Torino",
    "wof:name":"Cassa Di Risparmio Di Torino Spa",
    "wof:placetype":"venue"
},
  "geometry": {"coordinates":[7.394709,45.082336],"type":"Point"}
}