{
  "type": "Feature",
  "properties": {
    "iso:country":"IT",
    "sg:address":"20013 Magenta",
    "sg:city":"Magenta",
    "sg:orig_category":"Automobili E Mezzi Di Trasporto",
    "sg:phone":"+39 02 9729 7294",
    "sg:postcode":"20013",
    "sg:province":"Milano",
    "wof:name":"Giolla Fratelli Snc Di Giolla A. & G.",
    "wof:placetype":"venue"
},
  "geometry": {"coordinates":[9.202418,45.461124],"type":"Point"}
}