{
  "type": "Feature",
  "properties": {
    "iso:country":"IT",
    "sg:address":"74100 Taranto",
    "sg:city":"Taranto",
    "sg:orig_category":"Carboni - Produzione E Commercio",
    "sg:phone":"+39 099 471 1093",
    "sg:postcode":"74100",
    "sg:province":"Taranto",
    "wof:name":"Melle Figlie Di Francesco Srl",
    "wof:placetype":"venue"
},
  "geometry": {"coordinates":[17.227486,40.483143],"type":"Point"}
}