{
  "type": "Feature",
  "properties": {
    "iso:country":"IT",
    "sg:address":"70121 Bari",
    "sg:city":"Bari",
    "sg:orig_category":"Argenterie - Vendita Al Dettaglio",
    "sg:phone":"+39 080 524 4060",
    "sg:postcode":"70121",
    "sg:province":"Bari",
    "wof:name":"Pesce Nicola",
    "wof:placetype":"venue"
},
  "geometry": {"coordinates":[16.871017,41.06279],"type":"Point"}
}