{
  "type": "Feature",
  "properties": {
    "addr:full":"Via Mariotti Umberto 51100 Pistoia Pistoia Pistoia 51100",
    "addr:postcode":"51100;51100",
    "addr:street":"Via Mariotti Umberto",
    "iso:country":"IT",
    "sg:address":"Via Mariotti Umberto 51100 Pistoia",
    "sg:city":"Pistoia",
    "sg:classifiers":[
        {
            "category":"Bars & Pubs",
            "subcategory":"Sports Bar",
            "type":"Food & Drink"
        }
    ],
    "sg:phone":"+39 0573 445 7200",
    "sg:postcode":"51100",
    "sg:province":"Pistoia",
    "sg:tags":[
        "packaging",
        "manufacturing",
        "customized"
    ],
    "sg:website":"www.ricciarellipackaging.com",
    "wof:name":"Ricciarelli Spa",
    "wof:placetype":"venue"
},
  "geometry": {"coordinates":[10.9185237885,43.9321556091],"type":"Point"}
}