{
  "type": "Feature",
  "properties": {
    "iso:country":"IT",
    "sg:address":"Vle Delle Industrie 8 45100 Rovigo",
    "sg:city":"Rovigo",
    "sg:classifiers":[
        {
            "category":"Building & Trades",
            "subcategory":"Construction",
            "type":"Services"
        }
    ],
    "sg:phone":"+39 0425 473111",
    "sg:postcode":"45100",
    "sg:province":"Rovigo",
    "sg:tags":[
        "industry",
        "air-conditioning",
        "system"
    ],
    "wof:name":"Guerrato Spa",
    "wof:placetype":"venue"
},
  "geometry": {"coordinates":[11.768286,45.007301],"type":"Point"}
}