{
  "type": "Feature",
  "properties": {
    "addr:full":"20141 Milano Milano Milano 20141",
    "addr:postcode":"20141;20141",
    "iso:country":"IT",
    "sg:address":"20141 Milano",
    "sg:city":"Milano",
    "sg:orig_category":"Lavorazioni Metalli, Stampaggio E Saldatura",
    "sg:postcode":"20141",
    "sg:province":"Milano",
    "wof:name":"Forgiature Vitali (s.r.l.)",
    "wof:placetype":"venue"
},
  "geometry": {"coordinates":[9.192725,45.440353],"type":"Point"}
}