{
  "type": "Feature",
  "properties": {
    "iso:country":"IT",
    "sg:address":"24, Viale Trento 39100 Bolzano",
    "sg:city":"Bolzano",
    "sg:classifiers":[
        {
            "category":"Communications",
            "subcategory":"Television Station",
            "type":"Services"
        }
    ],
    "sg:phone":"+39 0471 324770",
    "sg:postcode":"39100",
    "sg:province":"Bolzano/Bozen",
    "sg:tags":[
        "audio-visual"
    ],
    "wof:name":"Fidelity S.n.c.",
    "wof:placetype":"venue"
},
  "geometry": {"coordinates":[11.304122,46.479687],"type":"Point"}
}