{
  "type": "Feature",
  "properties": {
    "addr:full":"20070 San Zenone Al Lambro San Zenone al Lambro Milano 20070",
    "addr:housenumber":"20070",
    "addr:postcode":"zenone;lambro;20070",
    "addr:street":"San",
    "iso:country":"IT",
    "sg:address":"20070 San Zenone Al Lambro",
    "sg:city":"San Zenone al Lambro",
    "sg:orig_category":"Arte Ed Artigianato Artistico",
    "sg:phone":"+39 02 9887 0489",
    "sg:postcode":"20070",
    "sg:province":"Milano",
    "wof:name":"Prandini Paolo",
    "wof:placetype":"venue"
},
  "geometry": {"coordinates":[9.359596,45.324039],"type":"Point"}
}