{
  "type": "Feature",
  "properties": {
    "iso:country":"IT",
    "sg:address":"119, Via Pollative 59100 Prato",
    "sg:city":"Prato",
    "sg:classifiers":[
        {
            "category":"Shopping",
            "subcategory":"Crafts & Fabrics",
            "type":"Retail Goods"
        }
    ],
    "sg:phone":"+39 39057451811",
    "sg:postcode":"59100",
    "sg:province":"Prato",
    "wof:name":"Manifattura Igea Spa Filati Per Maglieria",
    "wof:placetype":"venue"
},
  "geometry": {"coordinates":[11.0537071228,43.8567314148],"type":"Point"}
}