{
  "type": "Feature",
  "properties": {
    "iso:country":"IT",
    "sg:address":"Via Monti 424 45025 Fratta Polesine",
    "sg:city":"Fratta Polesine",
    "sg:classifiers":[
        {
            "category":"Food & Beverages",
            "subcategory":"Meat & Fish",
            "type":"Retail Goods"
        }
    ],
    "sg:phone":"+39 0425 668788",
    "sg:postcode":"45025",
    "sg:province":"Rovigo",
    "sg:tags":[
        "fresh"
    ],
    "wof:name":"Bianchini Luciano",
    "wof:placetype":"venue"
},
  "geometry": {"coordinates":[11.6494989395,45.0304832458],"type":"Point"}
}