{
  "type": "Feature",
  "properties": {
    "iso:country":"IT",
    "sg:address":"38, Via Della Giuliana 00195 Roma",
    "sg:city":"Roma",
    "sg:classifiers":[
        {
            "category":"Manufacturing",
            "subcategory":"Printing",
            "type":"Manufacturing & Wholesale Goods"
        }
    ],
    "sg:phone":"+39 39063700163",
    "sg:postcode":"00195",
    "sg:province":"Roma",
    "sg:tags":[
        "publishing"
    ],
    "wof:name":"Promovideo Srl",
    "wof:placetype":"venue"
},
  "geometry": {"coordinates":[12.4544124603,41.9121856689],"type":"Point"}
}