{
  "type": "Feature",
  "properties": {
    "iso:country":"IT",
    "sg:address":"Via Oltrona 28 21020 Barasso",
    "sg:city":"Barasso",
    "sg:classifiers":[
        {
            "category":"Wholesale",
            "subcategory":"Vending Machines",
            "type":"Manufacturing & Wholesale Goods"
        }
    ],
    "sg:phone":"+39 0332 731060",
    "sg:postcode":"21020",
    "sg:province":"Varese",
    "sg:tags":[
        "boring",
        "combined",
        "machines",
        "milling"
    ],
    "sg:website":"www.alesamonti.com",
    "wof:name":"Alesamonti Srl",
    "wof:placetype":"venue"
},
  "geometry": {"coordinates":[8.750409,45.833435],"type":"Point"}
}