{
  "type": "Feature",
  "properties": {
    "addr:full":"15, Via Ferrero C. 10098 Rivoli Rivoli Torino 10098",
    "addr:postcode":"10098;10098",
    "addr:street":"Via Ferrero C.",
    "iso:country":"IT",
    "sg:address":"15, Via Ferrero C. 10098 Rivoli",
    "sg:city":"Rivoli",
    "sg:classifiers":[
        {
            "category":"Shopping",
            "type":"Retail Goods"
        }
    ],
    "sg:phone":"+39 011 957 5131",
    "sg:postcode":"10098",
    "sg:province":"Torino",
    "sg:tags":[
        "finished",
        "-",
        "metallic"
    ],
    "wof:name":"Meccanica Mafaldese Srl",
    "wof:placetype":"venue"
},
  "geometry": {"coordinates":[7.5530982018,45.0628128052],"type":"Point"}
}