{
  "type": "Feature",
  "properties": {
    "iso:country":"IT",
    "sg:address":"Viale Strasburgo, 42; Palermo; 90146",
    "sg:city":"Palermo",
    "sg:classifiers":[
        {
            "category":"Banks & Credit Unions",
            "subcategory":"Bank",
            "type":"Services"
        }
    ],
    "sg:phone":"+39 091 520004",
    "sg:postcode":"90146",
    "sg:province":"Palermo",
    "wof:name":"Banca Di Roma",
    "wof:placetype":"venue"
},
  "geometry": {"coordinates":[13.325377,38.157978],"type":"Point"}
}