{
  "type": "Feature",
  "properties": {
    "addr:full":"20095 Cusano Milanino Cusano Milanino Milano 20095",
    "addr:postcode":"20095;20095",
    "iso:country":"IT",
    "sg:address":"20095 Cusano Milanino",
    "sg:city":"Cusano Milanino",
    "sg:orig_category":"Abbigliamento Esterno, Maglierie E Pelliccerie. Servizi E Lavori Per Abbigliamento E Pelletterie",
    "sg:phone":"+39 02 619 5021",
    "sg:postcode":"20095",
    "sg:province":"Milano",
    "wof:name":"Marelli Riva Luigia",
    "wof:placetype":"venue"
},
  "geometry": {"coordinates":[9.176206,45.54858],"type":"Point"}
}