{
  "type": "Feature",
  "properties": {
    "iso:country":"IT",
    "sg:address":"Zona Industriale 63100 Ascoli Piceno",
    "sg:city":"Ascoli Piceno",
    "sg:orig_category":"Chemical-pharmaceutical Granules",
    "sg:phone":"+39 0736 813913",
    "sg:postcode":"63100",
    "sg:province":"Ascoli Piceno",
    "sg:website":"www.finprojei.com",
    "wof:name":"Finproject-compounds Spa",
    "wof:placetype":"venue"
},
  "geometry": {"coordinates":[13.574977,42.8554],"type":"Point"}
}