{
  "type": "Feature",
  "properties": {
    "iso:country":"IT",
    "sg:address":"Viale Dell' Industria 56022 Castelfranco Di Sotto",
    "sg:city":"Castelfranco di Sotto",
    "sg:classifiers":[
        {
            "category":"Wholesale",
            "subcategory":"Drugs",
            "type":"Manufacturing & Wholesale Goods"
        }
    ],
    "sg:phone":"+39 0571 471313",
    "sg:postcode":"56022",
    "sg:province":"Pisa",
    "sg:tags":[
        "chemical",
        "pharmaceutical"
    ],
    "wof:name":"Dermacolor Srl",
    "wof:placetype":"venue"
},
  "geometry": {"coordinates":[10.7534837723,43.7114677429],"type":"Point"}
}