{
  "type": "Feature",
  "properties": {
    "addr:full":"Via Delle Fonti 393/t 3 59100 Prato Prato Prato 59100",
    "addr:housenumber":"393 / t 3",
    "addr:postcode":"59100;59100",
    "addr:street":"Via Delle Fonti",
    "iso:country":"IT",
    "sg:address":"Via Delle Fonti 393/t 3 59100 Prato",
    "sg:city":"Prato",
    "sg:classifiers":[
        {
            "category":"Shopping",
            "subcategory":"Crafts & Fabrics",
            "type":"Retail Goods"
        }
    ],
    "sg:phone":"+39 0574 597141",
    "sg:postcode":"59100",
    "sg:province":"Prato",
    "sg:tags":[
        "clothing",
        "ladies'",
        "wear",
        "menswear",
        "boys'"
    ],
    "sg:website":"www.inseta.net",
    "wof:name":"Inseta S.r.l.",
    "wof:placetype":"venue"
},
  "geometry": {"coordinates":[11.0963125229,43.879699707],"type":"Point"}
}