{
  "type": "Feature",
  "properties": {
    "iso:country":"IT",
    "sg:address":"Via S.galdino 23851 Galbiate",
    "sg:city":"Galbiate",
    "sg:classifiers":[
        {
            "category":"Professional",
            "subcategory":"Engineering",
            "type":"Services"
        }
    ],
    "sg:phone":"+39 0341 540377",
    "sg:postcode":"23851",
    "sg:province":"Lecco",
    "sg:tags":[
        "machine",
        "-",
        "mechanical"
    ],
    "wof:name":"Giudici Davide & Figli (s.n.c.)",
    "wof:placetype":"venue"
},
  "geometry": {"coordinates":[9.361837,45.820293],"type":"Point"}
}