{
  "type": "Feature",
  "properties": {
    "iso:country":"IT",
    "sg:address":"46040 Monzambano",
    "sg:city":"Monzambano",
    "sg:orig_category":"Macchine Ed Impianti Per Edilizia E Lavori Pubblici",
    "sg:phone":"+39 0376 809301",
    "sg:postcode":"46040",
    "sg:province":"Mantova",
    "wof:name":"Betonrossi Spa",
    "wof:placetype":"venue"
},
  "geometry": {"coordinates":[10.693148,45.387665],"type":"Point"}
}