{
  "type": "Feature",
  "properties": {
    "iso:country":"IT",
    "sg:address":"Via Brescia 145 25039 Travagliato",
    "sg:city":"Travagliato",
    "sg:orig_category":"Bands, Woven",
    "sg:phone":"+39 030 686 5044",
    "sg:postcode":"25039",
    "sg:province":"Brescia",
    "sg:website":"www.tessiturabegni.it",
    "wof:name":"Tessitura Begni Srl",
    "wof:placetype":"venue"
},
  "geometry": {"coordinates":[10.099475,45.520462],"type":"Point"}
}