{
  "type": "Feature",
  "properties": {
    "iso:country":"IT",
    "sg:address":"Via Serra 1 15028 Quattordio",
    "sg:city":"Quattordio",
    "sg:classifiers":[
        {
            "category":"Autos & Motor Vehicles",
            "subcategory":"Automobile Sales",
            "type":"Retail Goods"
        }
    ],
    "sg:phone":"+39 0131 7701",
    "sg:postcode":"15028",
    "sg:province":"Alessandria",
    "sg:tags":[
        "varnish",
        "lacquers"
    ],
    "sg:website":"www.ppg.com",
    "wof:name":"Ppg Industries Italia Srl",
    "wof:placetype":"venue"
},
  "geometry": {"coordinates":[8.388514,44.907005],"type":"Point"}
}