{
  "type": "Feature",
  "properties": {
    "addr:full":"33030 Forgaria Nel Friuli Cornino Udine 33030",
    "addr:postcode":"33030;33030",
    "iso:country":"IT",
    "sg:address":"33030 Forgaria Nel Friuli",
    "sg:city":"Cornino",
    "sg:orig_category":"Impiantistica E Prodotti Tecnologici Per Edilizia",
    "sg:phone":"+39 0427 808584",
    "sg:postcode":"33030",
    "sg:province":"Udine",
    "wof:name":"Legnoluce Srl",
    "wof:placetype":"venue"
},
  "geometry": {"coordinates":[13.014341,46.225182],"type":"Point"}
}