{
  "type": "Feature",
  "properties": {
    "iso:country":"IT",
    "sg:address":"20154 Milano",
    "sg:city":"Milano",
    "sg:orig_category":"Abbigliamento Esterno, Maglierie E Pelliccerie. Servizi E Lavori Per Abbigliamento E Pelletterie",
    "sg:phone":"+39 02 2900 0304",
    "sg:postcode":"20154",
    "sg:province":"Milano",
    "wof:name":"Bruno Antonio",
    "wof:placetype":"venue"
},
  "geometry": {"coordinates":[9.183873,45.482456],"type":"Point"}
}