{
  "type": "Feature",
  "properties": {
    "iso:country":"IT",
    "sg:address":"Via Bruno Buozzi 9 40013 Castel Maggiore",
    "sg:city":"Castel Maggiore",
    "sg:classifiers":[
        {
            "category":"Manufacturing",
            "subcategory":"Paper Products",
            "type":"Manufacturing & Wholesale Goods"
        }
    ],
    "sg:phone":"+39 051 700023",
    "sg:postcode":"40013",
    "sg:province":"Bologna",
    "sg:tags":[
        "descaling"
    ],
    "wof:name":"Acem Azienda Chimica Emiliana Srl",
    "wof:placetype":"venue"
},
  "geometry": {"coordinates":[11.363872,44.559067],"type":"Point"}
}