{
  "type": "Feature",
  "properties": {
    "addr:full":"20052 Monza Monza Milano 20052",
    "addr:postcode":"20052;20052",
    "iso:country":"IT",
    "sg:address":"20052 Monza",
    "sg:city":"Monza",
    "sg:orig_category":"Engineering Societa'",
    "sg:phone":"+39 039 28061",
    "sg:postcode":"20052",
    "sg:province":"Milano",
    "sg:website":"http://www.p-a.it",
    "wof:name":"Project Automation Spa",
    "wof:placetype":"venue"
},
  "geometry": {"coordinates":[9.1942510605,45.5489120483],"type":"Point"}
}