{
  "type": "Feature",
  "properties": {
    "iso:country":"IT",
    "sg:address":"94, Via Golfarelli Innocenzo 47100 Forli'",
    "sg:orig_category":"Miscellaneous Products",
    "sg:phone":"+39 0543 473904",
    "sg:postcode":"47100",
    "sg:province":"Forl\u00ec-Cesena",
    "wof:name":"Sidac S.r.l.",
    "wof:placetype":"venue"
},
  "geometry": {"coordinates":[11.9804611206,43.9947662354],"type":"Point"}
}