{
  "type": "Feature",
  "properties": {
    "iso:country":"IT",
    "sg:address":"95030 Gravina Di Catania",
    "sg:city":"Gravina di Catania",
    "sg:orig_category":"Climatizzazione E Condizionamento, Apparecchiature E Servizi. Accessori Dei Mezzi Di Trasporto",
    "sg:phone":"+39 095 422940",
    "sg:postcode":"95030",
    "sg:province":"Catania",
    "wof:name":"Eliauto Di Prezzavento",
    "wof:placetype":"venue"
},
  "geometry": {"coordinates":[15.05189,37.5583],"type":"Point"}
}