{
  "type": "Feature",
  "properties": {
    "iso:country":"IT",
    "sg:address":"21, Via Diaz Armando 20054 Nova Milanese",
    "sg:city":"Nova Milanese",
    "sg:classifiers":[
        {
            "category":"Shopping",
            "type":"Retail Goods"
        }
    ],
    "sg:phone":"+39 390 362 4931",
    "sg:postcode":"20054",
    "sg:province":"Milano",
    "sg:tags":[
        "finished",
        "-",
        "metallic"
    ],
    "wof:name":"Serrature Meroni S.p.a.",
    "wof:placetype":"venue"
},
  "geometry": {"coordinates":[9.2199401855,45.5504112244],"type":"Point"}
}