{
  "type": "Feature",
  "properties": {
    "iso:country":"IT",
    "sg:address":"16/a, Via Braschi 40069 Zola Predosa",
    "sg:city":"Zola",
    "sg:classifiers":[
        {
            "category":"Professional",
            "subcategory":"Engineering",
            "type":"Services"
        }
    ],
    "sg:phone":"+39 39051751314",
    "sg:postcode":"40069",
    "sg:province":"Bologna",
    "sg:tags":[
        "machine",
        "-",
        "mechanical"
    ],
    "wof:name":"U.p.m. S.r.l.",
    "wof:placetype":"venue"
},
  "geometry": {"coordinates":[11.215776,44.491745],"type":"Point"}
}