{
  "type": "Feature",
  "properties": {
    "iso:country":"IT",
    "sg:address":"20010 Bareggio",
    "sg:city":"Bareggio",
    "sg:orig_category":"Articoli Pulizia",
    "sg:phone":"+39 02 9036 1785",
    "sg:postcode":"20010",
    "sg:province":"Milano",
    "wof:name":"Universal Forniture Di Edoardo Frosi",
    "wof:placetype":"venue"
},
  "geometry": {"coordinates":[9.204,45.454411],"type":"Point"}
}