{
  "type": "Feature",
  "properties": {
    "addr:full":"25014 Castenedolo Castenedolo Brescia 25014",
    "addr:postcode":"25014;25014",
    "iso:country":"IT",
    "sg:address":"25014 Castenedolo",
    "sg:city":"Castenedolo",
    "sg:classifiers":[
        {
            "category":"Banks & Credit Unions",
            "subcategory":"Financial Services",
            "type":"Services"
        }
    ],
    "sg:phone":"+39 030 213 0290",
    "sg:postcode":"25014",
    "sg:province":"Brescia",
    "sg:tags":[
        "articles",
        "product",
        "plastics",
        "industry",
        "work",
        "plastic"
    ],
    "sg:website":"http://www.sirspa.it",
    "wof:name":"S.i.r. Spa",
    "wof:placetype":"venue"
},
  "geometry": {"coordinates":[10.2856149673,45.4820594788],"type":"Point"}
}