{
  "type": "Feature",
  "properties": {
    "iso:country":"IT",
    "sg:address":"31100 Treviso",
    "sg:city":"Treviso",
    "sg:orig_category":"Ricerca, Selezione E Formazione Del Personale",
    "sg:phone":"+39 0422 590510",
    "sg:postcode":"31100",
    "sg:province":"Treviso",
    "wof:name":"Umana Spa",
    "wof:placetype":"venue"
},
  "geometry": {"coordinates":[12.219171,45.674015],"type":"Point"}
}