{
  "type": "Feature",
  "properties": {
    "iso:country":"IT",
    "sg:address":"275, V. Ponte Carolino 81024 Maddalena",
    "sg:classifiers":[
        {
            "category":"Parking",
            "subcategory":"Lot",
            "type":"Transportation"
        }
    ],
    "sg:phone":"+39 0823 203039",
    "sg:postcode":"81024",
    "sg:province":"Caserta",
    "sg:tags":[
        "transport",
        "road"
    ],
    "sg:website":"http://www.paginegialle.it/sanmichele-ce",
    "wof:name":"Onoranze Funebri San Michele Dei F.lli Vanacore",
    "wof:placetype":"venue"
},
  "geometry": {"coordinates":[14.39724,41.039284],"type":"Point"}
}