{
  "type": "Feature",
  "properties": {
    "iso:country":"IT",
    "sg:address":"20149 Milano",
    "sg:city":"Milano",
    "sg:orig_category":"Prodotti Alimentari",
    "sg:phone":"+39 02 468712",
    "sg:postcode":"20149",
    "sg:province":"Milano",
    "wof:name":"Mutti Alessandro Enrico",
    "wof:placetype":"venue"
},
  "geometry": {"coordinates":[9.1473875046,45.4785842896],"type":"Point"}
}