{
  "type": "Feature",
  "properties": {
    "iso:country":"IT",
    "sg:address":"00184 Roma",
    "sg:city":"Roma",
    "sg:orig_category":"Associazioni Ed Organismi Di Interesse Pubblico",
    "sg:phone":"+39 06 474 0279",
    "sg:postcode":"00184",
    "sg:province":"Roma",
    "wof:name":"Anupsa Gruppo Roma",
    "wof:placetype":"venue"
},
  "geometry": {"coordinates":[12.491314,41.859116],"type":"Point"}
}