{
  "type": "Feature",
  "properties": {
    "addr:full":"00198 Roma Roma Roma 00198",
    "addr:postcode":"00198;00198",
    "iso:country":"IT",
    "sg:address":"00198 Roma",
    "sg:city":"Roma",
    "sg:orig_category":"Ricambi E Componenti Dei Mezzi Di Trasporto",
    "sg:phone":"+39 06 855 1363",
    "sg:postcode":"00198",
    "sg:province":"Roma",
    "wof:name":"Cg 67 Di Cerasoli Walter & C. Snc",
    "wof:placetype":"venue"
},
  "geometry": {"coordinates":[12.656899,41.770157],"type":"Point"}
}