{
  "type": "Feature",
  "properties": {
    "addr:full":"51/a, Viale Volta Alessandro 28100 Novara Novara Novara 28100",
    "addr:housenumber":"51 / a",
    "addr:postcode":"28100;28100",
    "addr:street":"Viale Volta Alessandro",
    "iso:country":"IT",
    "sg:address":"51/a, Viale Volta Alessandro 28100 Novara",
    "sg:city":"Novara",
    "sg:classifiers":[
        {
            "category":"Travel",
            "subcategory":"Travel Agent",
            "type":"Entertainment"
        }
    ],
    "sg:phone":"+39 0321 629111",
    "sg:postcode":"28100",
    "sg:province":"Novara",
    "sg:tags":[
        "business"
    ],
    "wof:name":"Novara Esposizioni (s.r.l.)",
    "wof:placetype":"venue"
},
  "geometry": {"coordinates":[8.604989,45.442696],"type":"Point"}
}