{
  "type": "Feature",
  "properties": {
    "iso:country":"IT",
    "sg:address":"24022 Alzano Lombardo",
    "sg:city":"Alzano Lombardo",
    "sg:orig_category":"Carta, Cartone E Prodotti Primari. Forniture E Materiali Per Imballaggio E Confezionamento",
    "sg:phone":"+39 035 412 3028",
    "sg:postcode":"24022",
    "sg:province":"Bergamo",
    "wof:name":"Imbalcart Fiorano Snc",
    "wof:placetype":"venue"
},
  "geometry": {"coordinates":[9.715855,45.749657],"type":"Point"}
}