{
  "type": "Feature",
  "properties": {
    "iso:country":"IT",
    "sg:address":"00196 Roma",
    "sg:city":"Roma",
    "sg:orig_category":"Vetro: Prodotti E Lavorazioni",
    "sg:phone":"+39 06 322 4420",
    "sg:postcode":"00196",
    "sg:province":"Roma",
    "wof:name":"Il Quadro",
    "wof:placetype":"venue"
},
  "geometry": {"coordinates":[12.494854,41.99255],"type":"Point"}
}