{
  "type": "Feature",
  "properties": {
    "iso:country":"IT",
    "sg:address":"Viale Europa, 92; Castellamare Di Stabia; 80053",
    "sg:classifiers":[
        {
            "category":"Banks & Credit Unions",
            "subcategory":"Bank",
            "type":"Services"
        }
    ],
    "sg:phone":"+39 081 870 4666",
    "sg:postcode":"80053",
    "sg:province":"Napoli",
    "wof:name":"Banco Di Roma",
    "wof:placetype":"venue"
},
  "geometry": {"coordinates":[14.489047,40.703056],"type":"Point"}
}