{
  "type": "Feature",
  "properties": {
    "iso:country":"IT",
    "sg:address":"36050 Montorso Vicentino",
    "sg:city":"Montorso Vicentino",
    "sg:orig_category":"Macchine, Impianti Ed Attrezzature Per Abbigliamento E Pelletterie",
    "sg:phone":"+39 0444 685992",
    "sg:postcode":"36050",
    "sg:province":"Vicenza",
    "wof:name":"Tanmac",
    "wof:placetype":"venue"
},
  "geometry": {"coordinates":[11.360212,45.513569],"type":"Point"}
}