{
  "type": "Feature",
  "properties": {
    "addr:full":"44012 Bondeno Bondeno Ferrara 44012",
    "addr:postcode":"44012;44012",
    "iso:country":"IT",
    "sg:address":"44012 Bondeno",
    "sg:city":"Bondeno",
    "sg:orig_category":"Motori Ed Organi Di Trasmissione. Ricambi E Componenti Dei Mezzi Di Trasporto",
    "sg:phone":"+39 0532 897633",
    "sg:postcode":"44012",
    "sg:province":"Ferrara",
    "wof:name":"Bignozzi New Technologies Srl",
    "wof:placetype":"venue"
},
  "geometry": {"coordinates":[11.4055662155,44.8941917419],"type":"Point"}
}