{
  "type": "Feature",
  "properties": {
    "addr:full":"00146 Roma Roma Roma 00146",
    "addr:postcode":"00146;00146",
    "iso:country":"IT",
    "sg:address":"00146 Roma",
    "sg:city":"Roma",
    "sg:orig_category":"Prodotti Finiti Stampati. Servizi Editoriali. Tempo Libero - Articoli E Forniture",
    "sg:phone":"+39 06 557 5937",
    "sg:postcode":"00146",
    "sg:province":"Roma",
    "wof:name":"Systemcart S.r.l.",
    "wof:placetype":"venue"
},
  "geometry": {"coordinates":[12.4660100937,41.8613319397],"type":"Point"}
}