{
  "type": "Feature",
  "properties": {
    "iso:country":"IT",
    "sg:address":"15100 Alessandria",
    "sg:city":"Alessandria",
    "sg:orig_category":"Elettronica Professionale E Di Consumo. Musica. Accessori Dei Mezzi Di Trasporto",
    "sg:phone":"+39 0131 265207",
    "sg:postcode":"15100",
    "sg:province":"Alessandria",
    "wof:name":"Autoradio Service Di Carnassale",
    "wof:placetype":"venue"
},
  "geometry": {"coordinates":[8.637988,44.909374],"type":"Point"}
}