{
  "type": "Feature",
  "properties": {
    "iso:country":"IT",
    "sg:address":"59, Via Emilia Ovest 41013 Castelfranco Emilia",
    "sg:city":"Castelfranco Emilia",
    "sg:classifiers":[
        {
            "category":"Shopping",
            "subcategory":"Clothing, Apparel, & Fashions",
            "type":"Retail Goods"
        }
    ],
    "sg:phone":"+39 39059923837",
    "sg:postcode":"41013",
    "sg:province":"Modena",
    "sg:tags":[
        "clothes"
    ],
    "wof:name":"Biegi (s.r.l.)",
    "wof:placetype":"venue"
},
  "geometry": {"coordinates":[11.036396,44.600483],"type":"Point"}
}