{
  "type": "Feature",
  "properties": {
    "iso:country":"IT",
    "sg:address":"20124 Milano",
    "sg:city":"Milano",
    "sg:orig_category":"Macchine, Impianti E Forniture Per Industria Grafica, Cartaria E Cartotecnica",
    "sg:phone":"+39 02 6671 1248",
    "sg:postcode":"20124",
    "sg:province":"Milano",
    "wof:name":"Impresa Tecnoeditoriale Lombarda Spa",
    "wof:placetype":"venue"
},
  "geometry": {"coordinates":[9.203603,45.483276],"type":"Point"}
}