{
  "type": "Feature",
  "properties": {
    "addr:full":"V.lo Degli Alpini 5 24020 Cene Cene Bergamo 24020",
    "addr:housenumber":"5",
    "addr:postcode":"24020;24020",
    "addr:street":"V.Lo;Alpini",
    "iso:country":"IT",
    "sg:address":"V.lo Degli Alpini 5 24020 Cene",
    "sg:city":"Cene",
    "sg:classifiers":[
        {
            "category":"Wholesale",
            "subcategory":"Machinery & Supplies",
            "type":"Manufacturing & Wholesale Goods"
        }
    ],
    "sg:phone":"+39 0357163",
    "sg:postcode":"24020",
    "sg:province":"Bergamo",
    "sg:tags":[
        "set-up",
        "machine",
        "mill",
        "weaving",
        "equipment"
    ],
    "sg:website":"www.beltrami.it",
    "wof:name":"Beltrami Towelling Spa",
    "wof:placetype":"venue"
},
  "geometry": {"coordinates":[9.669952,45.694904],"type":"Point"}
}