{
  "type": "Feature",
  "properties": {
    "addr:full":"29100 Piacenza Piacenza Piacenza 29100",
    "addr:postcode":"29100;29100",
    "iso:country":"IT",
    "sg:address":"29100 Piacenza",
    "sg:city":"Piacenza",
    "sg:orig_category":"Macchine Ed Impianti Per Edilizia E Lavori Pubblici. Macchine, Strumenti Ed Apparecchi Per Attivita' Industriali",
    "sg:phone":"+39 0523 557331",
    "sg:postcode":"29100",
    "sg:province":"Piacenza",
    "sg:website":"http://www.niccolaipc.com",
    "wof:name":"Niccolai Piergiovanni",
    "wof:placetype":"venue"
},
  "geometry": {"coordinates":[9.720499,45.0341],"type":"Point"}
}