{
  "type": "Feature",
  "properties": {
    "iso:country":"IT",
    "sg:address":"Via Pelosa 100 35010 Borgoricco",
    "sg:city":"Borgoricco",
    "sg:classifiers":[
        {
            "category":"Manufacturing",
            "subcategory":"Building Materials",
            "type":"Manufacturing & Wholesale Goods"
        }
    ],
    "sg:phone":"+39 049 579 8898",
    "sg:postcode":"35010",
    "sg:province":"Padova",
    "sg:tags":[
        "fleece",
        "fabric"
    ],
    "wof:name":"Cimpa Sas Di Gallo Adriano E C",
    "wof:placetype":"venue"
},
  "geometry": {"coordinates":[11.9829673767,45.5409088135],"type":"Point"}
}