{
  "type": "Feature",
  "properties": {
    "iso:country":"IT",
    "sg:address":"97, Via Per Azzano S. Paolo 24050 Grassobbio",
    "sg:city":"Grassobbio",
    "sg:classifiers":[
        {
            "category":"Professional",
            "subcategory":"Printing & Photocopies",
            "type":"Services"
        }
    ],
    "sg:phone":"+39 39035335445",
    "sg:postcode":"24050",
    "sg:province":"Bergamo",
    "wof:name":"Serisystem Srl",
    "wof:placetype":"venue"
},
  "geometry": {"coordinates":[9.6597509384,45.6254959106],"type":"Point"}
}