{
  "type": "Feature",
  "properties": {
    "iso:country":"IT",
    "sg:address":"37019 Peschiera Del Garda",
    "sg:city":"Peschiera del Garda",
    "sg:orig_category":"Pubblica Amministrazione",
    "sg:phone":"+39 045 640 1059",
    "sg:postcode":"37019",
    "sg:province":"Verona",
    "wof:name":"Carabinieri",
    "wof:placetype":"venue"
},
  "geometry": {"coordinates":[10.6688919067,45.4378509521],"type":"Point"}
}