{
  "type": "Feature",
  "properties": {
    "addr:full":"Via Isarco 11 39040 Vahrn Bolzano/Bozen 39040",
    "addr:housenumber":"11",
    "addr:postcode":"39040;39040",
    "addr:street":"Via Isarco",
    "iso:country":"IT",
    "sg:address":"Via Isarco 11 39040 Vahrn",
    "sg:classifiers":[
        {
            "category":"Communications",
            "subcategory":"Film & Video Production",
            "type":"Services"
        }
    ],
    "sg:phone":"+39 0472 836633",
    "sg:postcode":"39040",
    "sg:province":"Bolzano/Bozen",
    "sg:tags":[
        "windows",
        "window",
        "roof",
        "dormer"
    ],
    "sg:website":"www.dachbau.com",
    "wof:name":"Gostner Dachbau Sas",
    "wof:placetype":"venue"
},
  "geometry": {"coordinates":[11.646729,46.739902],"type":"Point"}
}