{
  "type": "Feature",
  "properties": {
    "addr:full":"41100 Modena Modena Modena 41100",
    "addr:postcode":"41100;41100",
    "iso:country":"IT",
    "sg:address":"41100 Modena",
    "sg:city":"Modena",
    "sg:orig_category":"Metalli - Lavorazione Artistica",
    "sg:phone":"+39 059 260012",
    "sg:postcode":"41100",
    "sg:province":"Modena",
    "wof:name":"G.p. Di Pomentale Gianni",
    "wof:placetype":"venue"
},
  "geometry": {"coordinates":[10.9058361053,44.6332473755],"type":"Point"}
}