{
  "type": "Feature",
  "properties": {
    "addr:full":"37138 Verona Verona Verona 37138",
    "addr:postcode":"37138;37138",
    "iso:country":"IT",
    "sg:address":"37138 Verona",
    "sg:city":"Verona",
    "sg:orig_category":"Scuole E Servizi Scolastici. Ricerca, Selezione E Formazione Del Personale",
    "sg:phone":"+39 045 567699",
    "sg:postcode":"37138",
    "sg:province":"Verona",
    "sg:website":"http://www.wallstreetinstitute.com",
    "wof:name":"Wsi Rome Srl",
    "wof:placetype":"venue"
},
  "geometry": {"coordinates":[10.976731,45.437366],"type":"Point"}
}