{
  "type": "Feature",
  "properties": {
    "iso:country":"IT",
    "sg:address":"92100 Agrigento",
    "sg:city":"Agrigento",
    "sg:orig_category":"Imprese Di Costruzioni Civili Ed Industriali",
    "sg:phone":"+39 0922 607094",
    "sg:postcode":"92100",
    "sg:province":"Agrigento",
    "wof:name":"Geosystem Service",
    "wof:placetype":"venue"
},
  "geometry": {"coordinates":[13.623758,37.262157],"type":"Point"}
}