{
  "type": "Feature",
  "properties": {
    "addr:full":"03023 Ceccano Ceccano Frosinone 03023",
    "addr:postcode":"03023;03023",
    "iso:country":"IT",
    "sg:address":"03023 Ceccano",
    "sg:city":"Ceccano",
    "sg:orig_category":"Dolciumi - Produzione",
    "sg:phone":"+39 0775 601446",
    "sg:postcode":"03023",
    "sg:province":"Frosinone",
    "wof:name":"Dolciaria Ceccanese Snc Di Masi Tonino",
    "wof:placetype":"venue"
},
  "geometry": {"coordinates":[13.353925,41.539738],"type":"Point"}
}