{
  "type": "Feature",
  "properties": {
    "iso:country":"IT",
    "sg:address":"Arcella, Via Tiziano; Padova; 35100",
    "sg:classifiers":[
        {
            "category":"Banks & Credit Unions",
            "subcategory":"Bank",
            "type":"Services"
        }
    ],
    "sg:phone":"+39 049 600320",
    "wof:name":"Banca Antoniana",
    "wof:placetype":"venue"
},
  "geometry": {"coordinates":[11.892544,45.425877],"type":"Point"}
}