{
  "type": "Feature",
  "properties": {
    "addr:full":"23813 Cortenova Cortenova Lecco 23813",
    "addr:postcode":"23813;23813",
    "iso:country":"IT",
    "sg:address":"23813 Cortenova",
    "sg:city":"Cortenova",
    "sg:orig_category":"Metalli E Leghe",
    "sg:phone":"+39 0341 901540",
    "sg:postcode":"23813",
    "sg:province":"Lecco",
    "wof:name":"Proferall Srl",
    "wof:placetype":"venue"
},
  "geometry": {"coordinates":[9.3707799911,45.8479194641],"type":"Point"}
}