{
  "type": "Feature",
  "properties": {
    "addr:full":"81050 Pastorano Pastorano Caserta 81050",
    "addr:postcode":"81050;81050",
    "addr:street":"Pastorano Pastorano Caserta",
    "iso:country":"IT",
    "sg:address":"81050 Pastorano",
    "sg:city":"Pastorano",
    "sg:orig_category":"Apparecchiature E Sistemi Per Magazzinaggio E Movimentazione. Servizi Di Magazzinaggio E Movimentazione",
    "sg:phone":"+39 0823 871335",
    "sg:postcode":"81050",
    "sg:province":"Caserta",
    "wof:name":"Velardi Silvano",
    "wof:placetype":"venue"
},
  "geometry": {"coordinates":[14.199241,41.181889],"type":"Point"}
}