{
  "type": "Feature",
  "properties": {
    "addr:full":"22070 Bregnano Bregnano Como 22070",
    "addr:postcode":"22070;22070",
    "iso:country":"IT",
    "sg:address":"22070 Bregnano",
    "sg:city":"Bregnano",
    "sg:orig_category":"Imprese Di Costruzioni Civili Ed Industriali. Servizi Ausiliari Di Sorveglianza, Manutenzione E Pulizia",
    "sg:phone":"+39 031 770454",
    "sg:postcode":"22070",
    "sg:province":"Como",
    "sg:website":"http://www.edilgardenia.it",
    "wof:name":"Edilgardenia Srl",
    "wof:placetype":"venue"
},
  "geometry": {"coordinates":[9.0643,45.697487],"type":"Point"}
}