{
  "type": "Feature",
  "properties": {
    "addr:full":"26013 Crema Crema Cremona 26013",
    "addr:postcode":"26013;26013",
    "iso:country":"IT",
    "sg:address":"26013 Crema",
    "sg:city":"Crema",
    "sg:orig_category":"Elettronica Industriale, Prodotti E Apparecchiature",
    "sg:phone":"+39 0373 890411",
    "sg:postcode":"26013",
    "sg:province":"Cremona",
    "sg:website":"http://www.fresnet.it/aec",
    "wof:name":"A.e.c. Srl Elettronica Industriale",
    "wof:placetype":"venue"
},
  "geometry": {"coordinates":[9.678263,45.369957],"type":"Point"}
}