{
  "type": "Feature",
  "properties": {
    "addr:full":"1, Via I Maggio 30030 Martellago Martellago Venezia 30030",
    "addr:postcode":"30030;30030",
    "addr:street":"Via I Maggio",
    "iso:country":"IT",
    "sg:address":"1, Via I Maggio 30030 Martellago",
    "sg:city":"Martellago",
    "sg:classifiers":[
        {
            "category":"Manufacturing",
            "subcategory":"Metals",
            "type":"Manufacturing & Wholesale Goods"
        }
    ],
    "sg:phone":"+39 041 503 0226",
    "sg:postcode":"30030",
    "sg:province":"Venezia",
    "sg:tags":[
        "processing"
    ],
    "wof:name":"A.c.z. Riviera Torneria S.n.c.",
    "wof:placetype":"venue"
},
  "geometry": {"coordinates":[12.1509637833,45.5173377991],"type":"Point"}
}