{
  "type": "Feature",
  "properties": {
    "iso:country":"IT",
    "sg:address":"13, Via Tribolina 24064 Grumello Del Monte",
    "sg:city":"Grumello del Monte",
    "sg:classifiers":[
        {
            "category":"Shopping",
            "type":"Retail Goods"
        }
    ],
    "sg:phone":"+39 39035832362",
    "sg:postcode":"24064",
    "sg:province":"Bergamo",
    "sg:tags":[
        "finished",
        "-",
        "metallic"
    ],
    "wof:name":"Carpenteria Thema (s.r.l.)",
    "wof:placetype":"venue"
},
  "geometry": {"coordinates":[9.8834285736,45.6285743713],"type":"Point"}
}