{
  "type": "Feature",
  "properties": {
    "addr:full":"90012 Caccamo Caccamo Palermo 90012",
    "addr:postcode":"90012;90012",
    "iso:country":"IT",
    "sg:address":"90012 Caccamo",
    "sg:city":"Caccamo",
    "sg:orig_category":"Macellerie",
    "sg:phone":"+39 091 814 8004",
    "sg:postcode":"90012",
    "sg:province":"Palermo",
    "wof:name":"Carnezzeria Canzone Raimondo",
    "wof:placetype":"venue"
},
  "geometry": {"coordinates":[13.659427,37.874592],"type":"Point"}
}