{
  "type": "Feature",
  "properties": {
    "iso:country":"IT",
    "sg:address":"20131 Milano",
    "sg:city":"Milano",
    "sg:orig_category":"Materiali E Componenti Elettrotecnici. Elettrotecnica Industriale, Prodotti E Apparecchiature",
    "sg:phone":"+39 02 2940 5783",
    "sg:postcode":"20131",
    "sg:province":"Milano",
    "wof:name":"Vernocchi Guido",
    "wof:placetype":"venue"
},
  "geometry": {"coordinates":[9.217329,45.475857],"type":"Point"}
}