{
  "type": "Feature",
  "properties": {
    "iso:country":"IT",
    "sg:address":"00195 Roma",
    "sg:city":"Roma",
    "sg:orig_category":"Pizzerie",
    "sg:phone":"+39 06 3751 6181",
    "sg:postcode":"00195",
    "sg:province":"Roma",
    "wof:name":"Nuova Fiorentina Srl",
    "wof:placetype":"venue"
},
  "geometry": {"coordinates":[12.4630241394,41.9149856567],"type":"Point"}
}