{
  "type": "Feature",
  "properties": {
    "iso:country":"IT",
    "sg:address":"15048 Valenza",
    "sg:city":"Valenza",
    "sg:orig_category":"Esportatori Ed Importatori",
    "sg:phone":"+39 0131 924782",
    "sg:postcode":"15048",
    "sg:province":"Alessandria",
    "wof:name":"Valeria Gioielli Srl",
    "wof:placetype":"venue"
},
  "geometry": {"coordinates":[8.638703,45.007896],"type":"Point"}
}