{
  "type": "Feature",
  "properties": {
    "addr:full":"Via Marconi 34; Mason; 36064 Vicenza 36064",
    "addr:housenumber":"34",
    "addr:postcode":"36064;36064",
    "addr:street":"Via Marconi",
    "iso:country":"IT",
    "sg:address":"Via Marconi 34; Mason; 36064",
    "sg:classifiers":[
        {
            "category":"Banks & Credit Unions",
            "subcategory":"Bank",
            "type":"Services"
        }
    ],
    "sg:phone":"+39 0424 411915",
    "sg:postcode":"36064",
    "sg:province":"Vicenza",
    "wof:name":"Cariverona Banca Spa",
    "wof:placetype":"venue"
},
  "geometry": {"coordinates":[11.606874,45.717659],"type":"Point"}
}