{
  "type": "Feature",
  "properties": {
    "iso:country":"IT",
    "sg:address":"11, Ctr. Valle Cupa 64010 Controguerra",
    "sg:city":"Controguerra",
    "sg:classifiers":[
        {
            "category":"Banks & Credit Unions",
            "subcategory":"Investment Brokerage",
            "type":"Services"
        }
    ],
    "sg:phone":"+39 0861 809922",
    "sg:postcode":"64010",
    "sg:province":"Teramo",
    "sg:tags":[
        "-",
        "transport",
        "related"
    ],
    "sg:website":"http://www.eurofrigor.it:ws_end: :mark:ws:http://www.paginegialle.it/eurofrigor-03",
    "wof:name":"Eurofrigor Srl",
    "wof:placetype":"venue"
},
  "geometry": {"coordinates":[13.698531,42.66127],"type":"Point"}
}