{
  "type": "Feature",
  "properties": {
    "addr:full":"75100 Matera Matera Matera 75100",
    "addr:postcode":"75100;75100",
    "iso:country":"IT",
    "sg:address":"75100 Matera",
    "sg:city":"Matera",
    "sg:orig_category":"Onoranze E Pompe Funebri",
    "sg:phone":"+39 0835 332043",
    "sg:postcode":"75100",
    "sg:province":"Matera",
    "wof:name":"Giasi Emanuele & C. Snc",
    "wof:placetype":"venue"
},
  "geometry": {"coordinates":[16.58198,40.673416],"type":"Point"}
}