{
  "type": "Feature",
  "properties": {
    "addr:full":"58100 Grosseto Grosseto Grosseto 58100",
    "addr:postcode":"58100;58100",
    "iso:country":"IT",
    "sg:address":"58100 Grosseto",
    "sg:city":"Grosseto",
    "sg:classifiers":[
        {
            "category":"Manufacturing",
            "subcategory":"Food",
            "type":"Manufacturing & Wholesale Goods"
        }
    ],
    "sg:phone":"+39 0564 458007",
    "sg:postcode":"58100",
    "sg:province":"Grosseto",
    "sg:tags":[
        "product"
    ],
    "wof:name":"L'alba Tartufi - Vecchia Maremma",
    "wof:placetype":"venue"
},
  "geometry": {"coordinates":[11.1164455414,42.7495117188],"type":"Point"}
}