{
  "type": "Feature",
  "properties": {
    "addr:full":"20020 Cogliate Cogliate Milano 20020",
    "addr:postcode":"20020;20020",
    "iso:country":"IT",
    "sg:address":"20020 Cogliate",
    "sg:city":"Cogliate",
    "sg:orig_category":"Forniture Per Edilizia E Lavori Pubblici",
    "sg:phone":"+39 02 966 1622",
    "sg:postcode":"20020",
    "sg:province":"Milano",
    "sg:website":"http://www.eletecno.com/brm",
    "wof:name":"B.r.m. Snc",
    "wof:placetype":"venue"
},
  "geometry": {"coordinates":[9.082036972,45.6445159912],"type":"Point"}
}