{
  "type": "Feature",
  "properties": {
    "addr:full":"00161 Roma Roma Roma 00161",
    "addr:postcode":"00161;00161",
    "iso:country":"IT",
    "sg:address":"00161 Roma",
    "sg:city":"Roma",
    "sg:classifiers":[
        {
            "category":"Health Services",
            "subcategory":"Health Practitioner",
            "type":"Services"
        }
    ],
    "sg:phone":"+39 06 4424 9350",
    "sg:postcode":"00161",
    "sg:province":"Roma",
    "sg:tags":[
        "medici"
    ],
    "wof:name":"Maimone Silverio",
    "wof:placetype":"venue"
},
  "geometry": {"coordinates":[12.513609,41.911186],"type":"Point"}
}