{
  "type": "Feature",
  "properties": {
    "addr:full":"Via F.lli Lombardi 5 60010 Ostra Vetere Ostra Ancona 60010",
    "addr:housenumber":"5",
    "addr:postcode":"60010;60010",
    "addr:street":"Via F.Lli Lombardi",
    "iso:country":"IT",
    "sg:address":"Via F.lli Lombardi 5 60010 Ostra Vetere",
    "sg:city":"Ostra",
    "sg:orig_category":"Harrows, Cultivators",
    "sg:phone":"+39 071 964182",
    "sg:postcode":"60010",
    "sg:province":"Ancona",
    "wof:name":"Sicma Spa",
    "wof:placetype":"venue"
},
  "geometry": {"coordinates":[13.5187568665,43.6158561707],"type":"Point"}
}