{
  "type": "Feature",
  "properties": {
    "iso:country":"IT",
    "sg:address":"40013 Castel Maggiore",
    "sg:city":"Castel Maggiore",
    "sg:orig_category":"Elettronica Industriale, Prodotti E Apparecchiature",
    "sg:phone":"+39 051 419 8711",
    "sg:postcode":"40013",
    "sg:province":"Bologna",
    "sg:website":"http://www.distar.it",
    "wof:name":"Distar Srl",
    "wof:placetype":"venue"
},
  "geometry": {"coordinates":[11.363301,44.560192],"type":"Point"}
}