{
  "type": "Feature",
  "properties": {
    "iso:country":"IT",
    "sg:address":"37, Via Per Molteno 23848 Oggiono",
    "sg:city":"Oggiono",
    "sg:classifiers":[
        {
            "category":"Autos & Motor Vehicles",
            "subcategory":"Automobile Sales",
            "type":"Retail Goods"
        }
    ],
    "sg:phone":"+39 0341 260198",
    "sg:postcode":"23848",
    "sg:province":"Lecco",
    "sg:tags":[
        "industrial"
    ],
    "wof:name":"Delcar (s.r.l.)",
    "wof:placetype":"venue"
},
  "geometry": {"coordinates":[9.360929,45.806633],"type":"Point"}
}