{
  "type": "Feature",
  "properties": {
    "addr:full":"35010 Vigodarzere Vigodarzere Padova 35010",
    "addr:postcode":"35010;35010",
    "iso:country":"IT",
    "sg:address":"35010 Vigodarzere",
    "sg:city":"Vigodarzere",
    "sg:orig_category":"Macchine Ed Impianti Per Edilizia E Lavori Pubblici",
    "sg:phone":"+39 049 703287",
    "sg:postcode":"35010",
    "sg:province":"Padova",
    "wof:name":"C.a.v. Snc Di Servadio Filippo & C.",
    "wof:placetype":"venue"
},
  "geometry": {"coordinates":[11.894345,45.456604],"type":"Point"}
}