{
  "type": "Feature",
  "properties": {
    "iso:country":"IT",
    "sg:address":"14100 Asti",
    "sg:city":"Asti",
    "sg:orig_category":"Forniture Per Edilizia E Lavori Pubblici. Forniture Industriali Per Prevenzione, Controllo E Sicurezza",
    "sg:phone":"+39 0141 214878",
    "sg:postcode":"14100",
    "sg:province":"Asti",
    "wof:name":"S.p. Di Mario Morlin",
    "wof:placetype":"venue"
},
  "geometry": {"coordinates":[8.2136564255,44.9102401733],"type":"Point"}
}