{
  "type": "Feature",
  "properties": {
    "iso:country":"IT",
    "sg:address":"3, Via Artemide 92100 Agrigento",
    "sg:city":"Agrigento",
    "sg:classifiers":[
        {
            "category":"Professional",
            "subcategory":"Business Services",
            "type":"Services"
        }
    ],
    "sg:phone":"+39 39092225389",
    "sg:postcode":"92100",
    "sg:province":"Agrigento",
    "sg:tags":[
        "advice"
    ],
    "wof:name":"Unione Degli Industriali E Degli Artigiani",
    "wof:placetype":"venue"
},
  "geometry": {"coordinates":[13.598317,37.300171],"type":"Point"}
}