{
  "type": "Feature",
  "properties": {
    "addr:full":"25121 Brescia Brescia Brescia 25121",
    "addr:postcode":"25121;25121",
    "iso:country":"IT",
    "sg:address":"25121 Brescia",
    "sg:city":"Brescia",
    "sg:orig_category":"Pubblica Amministrazione",
    "sg:phone":"+39 030 289 6211",
    "sg:postcode":"25121",
    "sg:province":"Brescia",
    "wof:name":"Uffici Giudiziari",
    "wof:placetype":"venue"
},
  "geometry": {"coordinates":[10.2180624008,45.5325622559],"type":"Point"}
}