{
  "type": "Feature",
  "properties": {
    "addr:full":"24122 Bergamo Bergamo Bergamo 24122",
    "addr:postcode":"24122;24122",
    "iso:country":"IT",
    "sg:address":"24122 Bergamo",
    "sg:city":"Bergamo",
    "sg:orig_category":"Termotecnica E Riscaldamento, Apparecchiature E Servizi",
    "sg:phone":"+39 035 238707",
    "sg:postcode":"24122",
    "sg:province":"Bergamo",
    "wof:name":"Rei",
    "wof:placetype":"venue"
},
  "geometry": {"coordinates":[9.664762,45.688694],"type":"Point"}
}