{
  "type": "Feature",
  "properties": {
    "iso:country":"IT",
    "sg:address":"10040 Druento",
    "sg:city":"Druento",
    "sg:orig_category":"Forniture Per Attivita' Industriali",
    "sg:phone":"+39 011 994 1666",
    "sg:postcode":"10040",
    "sg:province":"Torino",
    "wof:name":"Guarniturificio Brunero Snc",
    "wof:placetype":"venue"
},
  "geometry": {"coordinates":[7.5906476974,45.1272888184],"type":"Point"}
}