{
  "type": "Feature",
  "properties": {
    "addr:full":"Sda Statale 16 70052 Bisceglie Bisceglie Bari 70052",
    "addr:postcode":"70052;70052",
    "iso:country":"IT",
    "sg:address":"Sda Statale 16 70052 Bisceglie",
    "sg:city":"Bisceglie",
    "sg:classifiers":[
        {
            "category":"Food & Beverages",
            "subcategory":"Fruits & Vegetables",
            "type":"Retail Goods"
        }
    ],
    "sg:phone":"+39 080 395 1531",
    "sg:postcode":"70052",
    "sg:province":"Bari",
    "sg:tags":[
        "preserve",
        "cucumber"
    ],
    "sg:website":"www.pumaconserve.it",
    "wof:name":"Puma Conserve S.r.l.",
    "wof:placetype":"venue"
},
  "geometry": {"coordinates":[16.531048,41.220936],"type":"Point"}
}