{
  "type": "Feature",
  "properties": {
    "iso:country":"IT",
    "sg:address":"22, Via Nicolini Padre 35013 Cittadella",
    "sg:city":"Cittadella",
    "sg:classifiers":[
        {
            "category":"Retail",
            "subcategory":"Animal Services",
            "type":"Services"
        }
    ],
    "sg:phone":"+39 049 597 1677",
    "sg:postcode":"35013",
    "sg:province":"Padova",
    "sg:tags":[
        "breeding"
    ],
    "wof:name":"Pro.d.ac. International Snc Di Zanon Ferruccio & C.",
    "wof:placetype":"venue"
},
  "geometry": {"coordinates":[11.876589,45.409569],"type":"Point"}
}