{
  "type": "Feature",
  "properties": {
    "addr:full":"27, Contrada Fiastra 62014 Petriolo Petriolo Macerata 62014",
    "addr:postcode":"62014;62014",
    "addr:street":"Contrada Fiastra",
    "iso:country":"IT",
    "sg:address":"27, Contrada Fiastra 62014 Petriolo",
    "sg:city":"Petriolo",
    "sg:classifiers":[
        {
            "category":"Manufacturing",
            "subcategory":"Metals",
            "type":"Manufacturing & Wholesale Goods"
        }
    ],
    "sg:phone":"+39 0733 550226",
    "sg:postcode":"62014",
    "sg:province":"Macerata",
    "sg:tags":[
        "metallurgy",
        "metalworking"
    ],
    "wof:name":"Metallurgica Centro Italia S.p.a.",
    "wof:placetype":"venue"
},
  "geometry": {"coordinates":[13.4481964111,43.2318344116],"type":"Point"}
}