{
  "type": "Feature",
  "properties": {
    "iso:country":"IT",
    "sg:address":"21010 Besnate",
    "sg:city":"Besnate",
    "sg:orig_category":"Abbigliamento - Produzione E Ingrosso",
    "sg:phone":"+39 0331 274126",
    "sg:postcode":"21010",
    "sg:province":"Varese",
    "wof:name":"Creazioni Bip Bip Srl",
    "wof:placetype":"venue"
},
  "geometry": {"coordinates":[8.762215,45.697262],"type":"Point"}
}