{
  "type": "Feature",
  "properties": {
    "iso:country":"IT",
    "sg:address":"Via Albenga 36a 10098 Rivoli",
    "sg:city":"Rivoli",
    "sg:classifiers":[
        {
            "category":"Train Station",
            "subcategory":"Light Rail",
            "type":"Transportation"
        }
    ],
    "sg:phone":"+39 011 959 7771",
    "sg:postcode":"10098",
    "sg:province":"Torino",
    "sg:tags":[
        "searchlight"
    ],
    "wof:name":"E.l.a. Illuminazioni Di Bertolo Ivo & C Sas",
    "wof:placetype":"venue"
},
  "geometry": {"coordinates":[7.545839,45.065437],"type":"Point"}
}