{
  "type": "Feature",
  "properties": {
    "iso:country":"IT",
    "sg:address":"Via Mattei, 9/21 20050 Ronco Briantino",
    "sg:city":"Ronco Briantino",
    "sg:classifiers":[
        {
            "category":"Banks & Credit Unions",
            "subcategory":"Atm",
            "type":"Services"
        }
    ],
    "sg:phone":"+39 039 607 9047",
    "sg:postcode":"20050",
    "sg:province":"Milano",
    "sg:tags":[
        "steel",
        "frame",
        "bed"
    ],
    "sg:website":"www.stema-zorzetto.com",
    "wof:name":"Stema S.r.l.",
    "wof:placetype":"venue"
},
  "geometry": {"coordinates":[9.417623,45.666698],"type":"Point"}
}