{
  "type": "Feature",
  "properties": {
    "iso:country":"IT",
    "sg:address":"Via S. Giorgio 28041 Arona",
    "sg:city":"Arona",
    "sg:classifiers":[
        {
            "category":"Shopping",
            "subcategory":"Clothing, Apparel, & Fashions",
            "type":"Retail Goods"
        }
    ],
    "sg:phone":"+39 39032246851",
    "sg:postcode":"28041",
    "sg:province":"Novara",
    "sg:tags":[
        "clothes"
    ],
    "wof:name":"Commerciale San Carlo (s.a.s.)",
    "wof:placetype":"venue"
},
  "geometry": {"coordinates":[8.546057,45.746937],"type":"Point"}
}