{
  "type": "Feature",
  "properties": {
    "iso:country":"IT",
    "sg:address":"Piazza Buondelmonti 25; Impruneta; 50023",
    "sg:city":"Impruneta",
    "sg:classifiers":[
        {
            "category":"Banks & Credit Unions",
            "subcategory":"Bank",
            "type":"Services"
        }
    ],
    "sg:phone":"+39 055 201 1032",
    "sg:postcode":"50023",
    "sg:province":"Firenze",
    "wof:name":"Banca Toscana Spa",
    "wof:placetype":"venue"
},
  "geometry": {"coordinates":[11.254595,43.685123],"type":"Point"}
}