{
  "type": "Feature",
  "properties": {
    "iso:country":"IT",
    "sg:address":"Piazza G. Carducci 14/15; Pietrasanta; 55045",
    "sg:city":"Pietrasanta",
    "sg:classifiers":[
        {
            "category":"Banks & Credit Unions",
            "subcategory":"Bank",
            "type":"Services"
        }
    ],
    "sg:phone":"+39 0584 71333",
    "sg:postcode":"55045",
    "sg:province":"Lucca",
    "wof:name":"Banca Toscana Spa",
    "wof:placetype":"venue"
},
  "geometry": {"coordinates":[10.230714,43.956589],"type":"Point"}
}