{
  "type": "Feature",
  "properties": {
    "iso:country":"IT",
    "sg:address":"20032 Cormano",
    "sg:city":"Cormano",
    "sg:orig_category":"Materiali E Componenti Elettrotecnici",
    "sg:phone":"+39 02 6630 6615",
    "sg:postcode":"20032",
    "sg:province":"Milano",
    "wof:name":"F.r.e. Fabbrica Resistenze Elettriche S.a.s. Di G. Berne' & C.",
    "wof:placetype":"venue"
},
  "geometry": {"coordinates":[9.167388,45.536606],"type":"Point"}
}