{
  "type": "Feature",
  "properties": {
    "addr:full":"20017 Rho Rho Milano 20017",
    "addr:postcode":"20017;20017",
    "iso:country":"IT",
    "sg:address":"20017 Rho",
    "sg:city":"Rho",
    "sg:orig_category":"Cinematografia E Radiotelevisione. Pubblicita', Marketing E Comunicazione. Acqua, Luce, Gas E Societa' Di Esercizio Pubblico",
    "sg:phone":"+39 02 931 2191",
    "sg:postcode":"20017",
    "sg:province":"Milano",
    "wof:name":"Ambra Corporation (s.r.l.)",
    "wof:placetype":"venue"
},
  "geometry": {"coordinates":[9.035673,45.525497],"type":"Point"}
}