{
  "type": "Feature",
  "properties": {
    "addr:full":"40, Via S. Francesco A Patria 80019 Qualiano Qualiano Napoli 80019",
    "addr:postcode":"80019;80019",
    "addr:street":"Via S. Francesco A Patria",
    "iso:country":"IT",
    "sg:address":"40, Via S. Francesco A Patria 80019 Qualiano",
    "sg:city":"Qualiano",
    "sg:classifiers":[
        {
            "category":"Manufacturing",
            "subcategory":"Lumber",
            "type":"Manufacturing & Wholesale Goods"
        }
    ],
    "sg:phone":"+39 081 818 4662",
    "sg:postcode":"80019",
    "sg:province":"Napoli",
    "sg:tags":[
        "wood"
    ],
    "wof:name":"Due G. Imballaggi Srl Raffaele",
    "wof:placetype":"venue"
},
  "geometry": {"coordinates":[14.171168,40.923161],"type":"Point"}
}