{
  "type": "Feature",
  "properties": {
    "addr:full":"10135 Torino Torino Torino 10135",
    "addr:postcode":"10135;10135",
    "iso:country":"IT",
    "sg:address":"10135 Torino",
    "sg:city":"Torino",
    "sg:orig_category":"Servizi E Lavori Per Edilizia E Lavori Pubblici",
    "sg:phone":"+39 348 266 5686",
    "sg:postcode":"10135",
    "sg:province":"Torino",
    "wof:name":"Mariano Pugliese",
    "wof:placetype":"venue"
},
  "geometry": {"coordinates":[7.75451,45.094978],"type":"Point"}
}