{
  "type": "Feature",
  "properties": {
    "iso:country":"IT",
    "sg:address":"Via Copernico, 13/15 36057 Arcugnano",
    "sg:city":"Arcugnano",
    "sg:classifiers":[
        {
            "category":"Utilities",
            "subcategory":"Electric",
            "type":"Services"
        }
    ],
    "sg:phone":"+39 0444 289202",
    "sg:postcode":"36057",
    "sg:province":"Vicenza",
    "sg:tags":[
        "furnace"
    ],
    "sg:website":"www.maulesrl.it",
    "wof:name":"Maule Srl",
    "wof:placetype":"venue"
},
  "geometry": {"coordinates":[11.512561,45.51141],"type":"Point"}
}