{
  "type": "Feature",
  "properties": {
    "iso:country":"IT",
    "sg:address":"41100 Modena",
    "sg:city":"Modena",
    "sg:orig_category":"Termotecnica E Riscaldamento, Apparecchiature E Servizi",
    "sg:phone":"+39 059 310724",
    "sg:postcode":"41100",
    "sg:province":"Modena",
    "wof:name":"Guaitoli & Martinelli (s.r.l.)",
    "wof:placetype":"venue"
},
  "geometry": {"coordinates":[11.110543,44.853493],"type":"Point"}
}