{
  "type": "Feature",
  "properties": {
    "addr:full":"50, Via Provinciale 84010 San Valentino Torio San Valentino Torio Salerno 84010",
    "addr:housenumber":"valentino torio",
    "addr:postcode":"84010;valentino torio;84010",
    "addr:street":"Via Provinciale;Salerno",
    "iso:country":"IT",
    "sg:address":"50, Via Provinciale 84010 San Valentino Torio",
    "sg:city":"San Valentino Torio",
    "sg:classifiers":[
        {
            "category":"Manufacturing",
            "subcategory":"Food",
            "type":"Manufacturing & Wholesale Goods"
        }
    ],
    "sg:phone":"+39 081 937 1031",
    "sg:postcode":"84010",
    "sg:province":"Salerno",
    "sg:tags":[
        "equipment",
        "processing",
        "-",
        "machinery"
    ],
    "wof:name":"Tecnocarmec Di Sacchetti E. E Ruggiero G.b. & C. Sas",
    "wof:placetype":"venue"
},
  "geometry": {"coordinates":[14.621213913,40.7869682312],"type":"Point"}
}