{
  "type": "Feature",
  "properties": {
    "iso:country":"IT",
    "sg:address":"15, Via Balzaretti Giuseppe 20133 Milano",
    "sg:city":"Milano",
    "sg:classifiers":[
        {
            "category":"Wholesale",
            "subcategory":"Medical Equipment & Supplies",
            "type":"Manufacturing & Wholesale Goods"
        }
    ],
    "sg:phone":"+39 39022774121",
    "sg:postcode":"20133",
    "sg:province":"Milano",
    "sg:tags":[
        "-",
        "health",
        "instrument"
    ],
    "wof:name":"Sensor Medics Italia Srl",
    "wof:placetype":"venue"
},
  "geometry": {"coordinates":[9.220231,45.477573],"type":"Point"}
}