{
  "type": "Feature",
  "properties": {
    "addr:full":"10042 Nichelino Nichelino Torino 10042",
    "addr:postcode":"10042;10042",
    "iso:country":"IT",
    "sg:address":"10042 Nichelino",
    "sg:city":"Nichelino",
    "sg:orig_category":"Autoveicoli Elettrici",
    "sg:phone":"+39 011 627 9699",
    "sg:postcode":"10042",
    "sg:province":"Torino",
    "wof:name":"New Cab Italia Srl",
    "wof:placetype":"venue"
},
  "geometry": {"coordinates":[7.634185,44.981033],"type":"Point"}
}