{
  "type": "Feature",
  "properties": {
    "iso:country":"IT",
    "sg:address":"20159 Milano",
    "sg:city":"Milano",
    "sg:orig_category":"Erboristerie",
    "sg:phone":"+39 02 6900 7403",
    "sg:postcode":"20159",
    "sg:province":"Milano",
    "wof:name":"Un'isola Verde Srl",
    "wof:placetype":"venue"
},
  "geometry": {"coordinates":[9.187164,45.494179],"type":"Point"}
}