{
  "type": "Feature",
  "properties": {
    "iso:country":"IT",
    "sg:address":"4, Salita S. Remigio 28922 Verbania",
    "sg:city":"Verbania",
    "sg:classifiers":[
        {
            "category":"Travel",
            "subcategory":"Travel Agent",
            "type":"Entertainment"
        }
    ],
    "sg:phone":"+39 0323 556692",
    "sg:postcode":"28922",
    "sg:province":"Verbano-Cusio-Ossola",
    "sg:tags":[
        "business"
    ],
    "wof:name":"Albergo Villa Azalea",
    "wof:placetype":"venue"
},
  "geometry": {"coordinates":[8.272465,46.139969],"type":"Point"}
}