{
  "type": "Feature",
  "properties": {
    "addr:full":"90133 Palermo Palermo Palermo 90133",
    "addr:postcode":"90133;90133",
    "iso:country":"IT",
    "sg:address":"90133 Palermo",
    "sg:city":"Palermo",
    "sg:orig_category":"Universita' Ed Istituti Superiori E Liberi",
    "sg:phone":"+39 091 616 8456",
    "sg:postcode":"90133",
    "sg:province":"Palermo",
    "wof:name":"Cepu Srl",
    "wof:placetype":"venue"
},
  "geometry": {"coordinates":[13.362919,38.112633],"type":"Point"}
}