{
  "type": "Feature",
  "properties": {
    "iso:country":"IT",
    "sg:address":"35017 Piombino Dese",
    "sg:city":"Piombino Dese",
    "sg:orig_category":"Legatorie",
    "sg:phone":"+39 049 936 6788",
    "sg:postcode":"35017",
    "sg:province":"Padova",
    "wof:name":"Nuova Legatoria Artigiana Di Bison Roberto & C. Snc",
    "wof:placetype":"venue"
},
  "geometry": {"coordinates":[11.987937,45.61377],"type":"Point"}
}