{
  "type": "Feature",
  "properties": {
    "iso:country":"IT",
    "sg:address":"84013 Cava De'tirreni",
    "sg:orig_category":"Utensili Meccanici E Materiali",
    "sg:phone":"+39 089 462653",
    "sg:postcode":"84013",
    "sg:province":"Salerno",
    "wof:name":"U.t.i.l. Di Giuseppe Lazzarini Consalvo & C.",
    "wof:placetype":"venue"
},
  "geometry": {"coordinates":[14.693768,40.706985],"type":"Point"}
}