{
  "type": "Feature",
  "properties": {
    "addr:full":"36066 Sandrigo Sandrigo Vicenza 36066",
    "addr:postcode":"36066;36066",
    "iso:country":"IT",
    "sg:address":"36066 Sandrigo",
    "sg:city":"Sandrigo",
    "sg:orig_category":"Macchine E Forniture Per Industria Orafa E Per Orologeria",
    "sg:phone":"+39 0444 659252",
    "sg:postcode":"36066",
    "sg:province":"Vicenza",
    "wof:name":"Pozzato Gimeccanica S.n.c.",
    "wof:placetype":"venue"
},
  "geometry": {"coordinates":[11.553227,45.63829],"type":"Point"}
}