{
  "type": "Feature",
  "properties": {
    "iso:country":"IT",
    "sg:address":"20082 Binasco",
    "sg:city":"Binasco",
    "sg:orig_category":"Arti Grafiche",
    "sg:phone":"+39 02 905 5410",
    "sg:postcode":"20082",
    "sg:province":"Milano",
    "wof:name":"Grafiche Noe' Snc",
    "wof:placetype":"venue"
},
  "geometry": {"coordinates":[9.227492,45.520267],"type":"Point"}
}