{
  "type": "Feature",
  "properties": {
    "iso:country":"IT",
    "sg:address":"Via Vistarino 27010 Copiano",
    "sg:city":"Copiano",
    "sg:classifiers":[
        {
            "category":"Shopping",
            "type":"Retail Goods"
        }
    ],
    "sg:phone":"+39 0382 968730",
    "sg:postcode":"27010",
    "sg:province":"Pavia",
    "sg:tags":[
        "finished",
        "-",
        "metallic"
    ],
    "wof:name":"Officina Vittoria Srl",
    "wof:placetype":"venue"
},
  "geometry": {"coordinates":[9.3193635941,45.1994552612],"type":"Point"}
}