{
  "type": "Feature",
  "properties": {
    "iso:country":"IT",
    "sg:address":"31021 Mogliano Veneto",
    "sg:city":"Mogliano Veneto",
    "sg:orig_category":"Prodotti E Manufatti In Materie Plastiche",
    "sg:phone":"+39 041 593 7036",
    "sg:postcode":"31021",
    "sg:province":"Treviso",
    "sg:website":"http://www.fimar.it",
    "wof:name":"Fimar Snc",
    "wof:placetype":"venue"
},
  "geometry": {"coordinates":[12.260020256,45.5581474304],"type":"Point"}
}