{
  "type": "Feature",
  "properties": {
    "iso:country":"IT",
    "sg:address":"Via Bergamina 20014 Nerviano",
    "sg:city":"Nerviano",
    "sg:classifiers":[
        {
            "category":"Shopping",
            "subcategory":"Computers & Home Electronics",
            "type":"Retail Goods"
        }
    ],
    "sg:phone":"+39 0331 589845",
    "sg:postcode":"20014",
    "sg:province":"Milano",
    "sg:tags":[
        "electronic",
        "electrical",
        "equipment"
    ],
    "wof:name":"E.b. Elettrotecnica S.r.l.",
    "wof:placetype":"venue"
},
  "geometry": {"coordinates":[8.962708,45.557072],"type":"Point"}
}