{
  "type": "Feature",
  "properties": {
    "iso:country":"IT",
    "sg:address":"25037 Pontoglio",
    "sg:city":"Pontoglio",
    "sg:orig_category":"Bevande, Vini E Liquori",
    "sg:phone":"+39 030 737010",
    "sg:postcode":"25037",
    "sg:province":"Brescia",
    "wof:name":"Terzi Giuseppe",
    "wof:placetype":"venue"
},
  "geometry": {"coordinates":[9.859857,45.570213],"type":"Point"}
}