{
  "type": "Feature",
  "properties": {
    "addr:full":"22063 Cantu' Como 22063",
    "addr:postcode":"22063;22063",
    "addr:street":"Cantu ' Como",
    "iso:country":"IT",
    "sg:address":"22063 Cantu'",
    "sg:orig_category":"Scuole E Servizi Scolastici. Ricerca, Selezione E Formazione Del Personale",
    "sg:phone":"+39 031 714020",
    "sg:postcode":"22063",
    "sg:province":"Como",
    "sg:website":"http://www.paginegialle.it/collegiodeamicis",
    "wof:name":"Facec - Collegio Arcivescovile De Amicis",
    "wof:placetype":"venue"
},
  "geometry": {"coordinates":[9.143435,45.737877],"type":"Point"}
}