{
  "type": "Feature",
  "properties": {
    "iso:country":"IT",
    "sg:address":"19, Viale Del Lavoro 37036 San Martino Buon Albergo",
    "sg:city":"San Martino Buon Albergo",
    "sg:classifiers":[
        {
            "category":"Shopping",
            "type":"Retail Goods"
        }
    ],
    "sg:phone":"+39 045 887 7222",
    "sg:postcode":"37036",
    "sg:province":"Verona",
    "sg:tags":[
        "finished",
        "-",
        "metallic"
    ],
    "wof:name":"Conforti S.p.a.",
    "wof:placetype":"venue"
},
  "geometry": {"coordinates":[11.0849075317,45.4171676636],"type":"Point"}
}