{
  "type": "Feature",
  "properties": {
    "iso:country":"IT",
    "sg:address":"43, Via Martina Franca 74012 Crispiano",
    "sg:city":"Crispiano",
    "sg:classifiers":[
        {
            "category":"Shopping",
            "subcategory":"Clothing, Apparel, & Fashions",
            "type":"Retail Goods"
        }
    ],
    "sg:phone":"+39 39099613770",
    "sg:postcode":"74012",
    "sg:province":"Taranto",
    "sg:tags":[
        "clothes"
    ],
    "wof:name":"Ramas Srl",
    "wof:placetype":"venue"
},
  "geometry": {"coordinates":[17.26767,40.530746],"type":"Point"}
}