{
  "type": "Feature",
  "properties": {
    "addr:full":"28857 Santa Maria Maggiore Santa Maria Maggiore Verbano-Cusio-Ossola 28857",
    "addr:postcode":"28857;28857",
    "addr:street":"Maria;Maria",
    "iso:country":"IT",
    "sg:address":"28857 Santa Maria Maggiore",
    "sg:city":"Santa Maria Maggiore",
    "sg:orig_category":"Pubblica Amministrazione",
    "sg:phone":"+39 0324 94763",
    "sg:postcode":"28857",
    "sg:province":"Verbano-Cusio-Ossola",
    "wof:name":"Comunita' Montana Valle Vigezzo",
    "wof:placetype":"venue"
},
  "geometry": {"coordinates":[8.4560661316,46.133682251],"type":"Point"}
}