{
  "type": "Feature",
  "properties": {
    "iso:country":"IT",
    "sg:address":"40053 Bazzano",
    "sg:city":"Bazzano",
    "sg:orig_category":"Sport - Articoli E Forniture",
    "sg:phone":"+39 051 831748",
    "sg:postcode":"40053",
    "sg:province":"Bologna",
    "wof:name":"Pescare' (s.n.c.)",
    "wof:placetype":"venue"
},
  "geometry": {"coordinates":[11.352701,44.543827],"type":"Point"}
}