{
  "type": "Feature",
  "properties": {
    "addr:full":"110, V. Vicenza 36034 Malo Malo Vicenza 36034",
    "addr:housenumber":"110",
    "addr:postcode":"36034;36034",
    "addr:street":"V. Vicenza",
    "iso:country":"IT",
    "sg:address":"110, V. Vicenza 36034 Malo",
    "sg:city":"Malo",
    "sg:classifiers":[
        {
            "category":"Autos & Motor Vehicles",
            "subcategory":"Automobile Sales",
            "type":"Retail Goods"
        }
    ],
    "sg:phone":"+39 0445 581386",
    "sg:postcode":"36034",
    "sg:province":"Vicenza",
    "sg:tags":[
        "motor-cars"
    ],
    "sg:website":"http://www.paginegialle.it/topauto",
    "wof:name":"Top Auto Srl",
    "wof:placetype":"venue"
},
  "geometry": {"coordinates":[11.4309301376,45.6407585144],"type":"Point"}
}