{
  "type": "Feature",
  "properties": {
    "iso:country":"IT",
    "sg:address":"24029 Vertova",
    "sg:city":"Vertova",
    "sg:orig_category":"Elettronica Professionale E Di Consumo. Forniture Per Il Settore Dello Spettacolo. Automazione E Macchine Per Ufficio. Forniture Per Congressi, Fiere E Manifestazioni",
    "sg:phone":"+39 035 712114",
    "sg:postcode":"24029",
    "sg:province":"Bergamo",
    "sg:website":"http://www.eclipsis.it",
    "wof:name":"Eclipsis Di Pedrini Alberto",
    "wof:placetype":"venue"
},
  "geometry": {"coordinates":[9.850272,45.80772],"type":"Point"}
}