{
  "type": "Feature",
  "properties": {
    "iso:country":"IT",
    "sg:address":"20036 Meda",
    "sg:city":"Meda",
    "sg:orig_category":"Macchine Ed Impianti Per Edilizia E Lavori Pubblici",
    "sg:phone":"+39 036 234 1559",
    "sg:postcode":"20036",
    "sg:province":"Milano",
    "wof:name":"Cave Rocca Srl",
    "wof:placetype":"venue"
},
  "geometry": {"coordinates":[9.143373,45.662872],"type":"Point"}
}