{
  "type": "Feature",
  "properties": {
    "iso:country":"IT",
    "sg:address":"07047 Thiesi",
    "sg:city":"Thiesi",
    "sg:orig_category":"Forniture Per Uffici",
    "sg:phone":"+39 079 887 0016",
    "sg:postcode":"07047",
    "sg:province":"Sassari",
    "wof:name":"Kriteriu Snc",
    "wof:placetype":"venue"
},
  "geometry": {"coordinates":[8.649058342,40.5235786438],"type":"Point"}
}