{
  "type": "Feature",
  "properties": {
    "iso:country":"IT",
    "sg:address":"39034 Dobbiaco",
    "sg:city":"Dobbiaco",
    "sg:orig_category":"Alberghi E Strutture Extra Alberghiere. Servizi Per Aziende, Manifestazioni E Supporto Agli Scambi Commerciali",
    "sg:phone":"+39 0474 976151",
    "sg:postcode":"39034",
    "sg:province":"Bolzano/Bozen",
    "sg:website":"http://www.grandhotel-dobbiaco.com",
    "wof:name":"Centro Culturale Grand Hotel Dobbiaco",
    "wof:placetype":"venue"
},
  "geometry": {"coordinates":[11.368299,46.49807],"type":"Point"}
}