{
  "type": "Feature",
  "properties": {
    "iso:country":"IT",
    "sg:address":"30126 Venezia",
    "sg:city":"Venezia",
    "sg:orig_category":"Imprese Di Costruzioni Civili Ed Industriali",
    "sg:phone":"+39 041 526 7918",
    "sg:postcode":"30126",
    "sg:province":"Venezia",
    "wof:name":"Cam Idrografica S.a.s.",
    "wof:placetype":"venue"
},
  "geometry": {"coordinates":[12.367515,45.414833],"type":"Point"}
}