{
  "type": "Feature",
  "properties": {
    "iso:country":"IT",
    "sg:address":"00186 Roma",
    "sg:city":"Roma",
    "sg:orig_category":"Apparecchi, Attrezzature E Forniture Per Centri Estetici",
    "sg:phone":"+39 06 687 3080",
    "sg:postcode":"00186",
    "sg:province":"Roma",
    "wof:name":"Prefetti Bellezza S.r.l.",
    "wof:placetype":"venue"
},
  "geometry": {"coordinates":[12.477009,41.902485],"type":"Point"}
}