{
  "type": "Feature",
  "properties": {
    "iso:country":"IT",
    "sg:address":"10024 Moncalieri",
    "sg:city":"Moncalieri",
    "sg:orig_category":"Arredo Cucina Ed Elettrodomestici. Elettrodomestici",
    "sg:phone":"+39 011 640 8250",
    "sg:postcode":"10024",
    "sg:province":"Torino",
    "wof:name":"Rosy Mobili Srl",
    "wof:placetype":"venue"
},
  "geometry": {"coordinates":[7.671268,45.008663],"type":"Point"}
}