{
  "type": "Feature",
  "properties": {
    "iso:country":"IT",
    "sg:address":"20094 Corsico",
    "sg:city":"Corsico",
    "sg:orig_category":"Elettronica Professionale E Di Consumo. Automazione E Macchine Per Ufficio",
    "sg:phone":"+39 02 4510 8893",
    "sg:postcode":"20094",
    "sg:province":"Milano",
    "wof:name":"Graphos Snc Di Dordoni Mauro & C.",
    "wof:placetype":"venue"
},
  "geometry": {"coordinates":[9.113371,45.433693],"type":"Point"}
}