{
  "type": "Feature",
  "properties": {
    "iso:country":"IT",
    "sg:address":"24122 Bergamo",
    "sg:city":"Bergamo",
    "sg:orig_category":"Non-classified Establishments",
    "sg:phone":"+39 035 221027",
    "sg:postcode":"24122",
    "sg:province":"Bergamo",
    "wof:name":"Oak Srl",
    "wof:placetype":"venue"
},
  "geometry": {"coordinates":[9.521331,45.817902],"type":"Point"}
}