{
  "type": "Feature",
  "properties": {
    "iso:country":"IT",
    "sg:address":"80030 Liveri",
    "sg:city":"Liveri",
    "sg:orig_category":"Prodotti Chimici Di Base. Forniture Per Attivita' Industriali",
    "sg:phone":"+39 081 825 5251",
    "sg:postcode":"80030",
    "sg:province":"Napoli",
    "wof:name":"Nappi Giuseppe",
    "wof:placetype":"venue"
},
  "geometry": {"coordinates":[14.2738771439,40.856628418],"type":"Point"}
}