{
  "type": "Feature",
  "properties": {
    "iso:country":"IT",
    "sg:address":"37139 Verona",
    "sg:city":"Verona",
    "sg:classifiers":[
        {
            "category":"Manufacturing",
            "subcategory":"Tools & Machinery",
            "type":"Manufacturing & Wholesale Goods"
        }
    ],
    "sg:phone":"+39 045 921688",
    "sg:postcode":"37139",
    "sg:province":"Verona",
    "sg:tags":[
        "leather",
        "equipment",
        "goods",
        "clothing"
    ],
    "sg:website":"http://www.pidigi.com",
    "wof:name":"Pidigi Spa",
    "wof:placetype":"venue"
},
  "geometry": {"coordinates":[10.887749,45.450859],"type":"Point"}
}