{
  "type": "Feature",
  "properties": {
    "addr:full":"Via Cigna 110/114 10155 Torino Torino Torino 10155",
    "addr:housenumber":"110 / 114",
    "addr:postcode":"10155;10155",
    "addr:street":"Via Cigna",
    "iso:country":"IT",
    "sg:address":"Via Cigna 110/114 10155 Torino",
    "sg:city":"Torino",
    "sg:orig_category":"Disposal Equipment For The Photo-chemical Industry",
    "sg:phone":"+39 011 244 6111",
    "sg:postcode":"10155",
    "sg:province":"Torino",
    "sg:website":"www.sicme.com",
    "wof:name":"S.i.c.m.e. Spa",
    "wof:placetype":"venue"
},
  "geometry": {"coordinates":[7.685293,45.09166],"type":"Point"}
}