{
  "type": "Feature",
  "properties": {
    "addr:full":"00122 Lido Di Ostia Roma 00122",
    "addr:postcode":"00122;00122",
    "addr:street":"Di Ostia Roma",
    "iso:country":"IT",
    "sg:address":"00122 Lido Di Ostia",
    "sg:orig_category":"Servizi Ausiliari Dei Mezzi Di Trasporto",
    "sg:phone":"+39 06 566 7123",
    "sg:postcode":"00122",
    "sg:province":"Roma",
    "wof:name":"Faenzi Attilia",
    "wof:placetype":"venue"
},
  "geometry": {"coordinates":[12.284636,41.734219],"type":"Point"}
}