{
  "type": "Feature",
  "properties": {
    "iso:country":"IT",
    "sg:address":"00172 Roma",
    "sg:city":"Roma",
    "sg:orig_category":"Autofficine E Centri Assistenza",
    "sg:phone":"+39 06 231 3524",
    "sg:postcode":"00172",
    "sg:province":"Roma",
    "wof:name":"Autofficina D.r.l. Srl",
    "wof:placetype":"venue"
},
  "geometry": {"coordinates":[12.603843,41.866089],"type":"Point"}
}