{
  "type": "Feature",
  "properties": {
    "addr:full":"09030 Elmas Elmas Cagliari 09030",
    "addr:postcode":"09030;09030",
    "iso:country":"IT",
    "sg:address":"09030 Elmas",
    "sg:city":"Elmas",
    "sg:orig_category":"Autorimesse E Parcheggi",
    "sg:phone":"+39 070 291211",
    "sg:postcode":"09030",
    "sg:province":"Cagliari",
    "wof:name":"System Security Service",
    "wof:placetype":"venue"
},
  "geometry": {"coordinates":[9.05813,39.252674],"type":"Point"}
}