{
  "type": "Feature",
  "properties": {
    "iso:country":"IT",
    "sg:address":"10087 Valperga",
    "sg:city":"Valperga",
    "sg:orig_category":"Servizi Per Lo Sport E Il Tempo Libero. Servizi Al Turismo. Acqua, Luce, Gas E Societa' Di Esercizio Pubblico",
    "sg:phone":"+39 0124 659521",
    "sg:postcode":"10087",
    "sg:province":"Torino",
    "wof:name":"Ente Gestine Parchi E Riserve Naturali Del Canavese",
    "wof:placetype":"venue"
},
  "geometry": {"coordinates":[7.674022,45.06641],"type":"Point"}
}