{
  "type": "Feature",
  "properties": {
    "iso:country":"IT",
    "sg:address":"20010 Marcallo Con Casone",
    "sg:city":"Casone",
    "sg:classifiers":[
        {
            "category":"Health Services",
            "subcategory":"Health Practitioner",
            "type":"Services"
        }
    ],
    "sg:phone":"+39 02 976 1905",
    "sg:postcode":"20010",
    "sg:province":"Milano",
    "sg:tags":[
        "medici"
    ],
    "wof:name":"Cucchi Loredana",
    "wof:placetype":"venue"
},
  "geometry": {"coordinates":[8.91035,45.489895],"type":"Point"}
}