{
  "type": "Feature",
  "properties": {
    "addr:full":"00184 Roma Roma Roma 00184",
    "addr:postcode":"00184;00184",
    "iso:country":"IT",
    "sg:address":"00184 Roma",
    "sg:city":"Roma",
    "sg:orig_category":"Scuole E Servizi Scolastici",
    "sg:phone":"+39 06 488 2026",
    "sg:postcode":"00184",
    "sg:province":"Roma",
    "wof:name":"Scuola Privata Istituti Istruzione Media Ed Elementare Parificati",
    "wof:placetype":"venue"
},
  "geometry": {"coordinates":[12.492083,41.895241],"type":"Point"}
}