{
  "type": "Feature",
  "properties": {
    "addr:full":"24029 Vertova Vertova Bergamo 24029",
    "addr:postcode":"24029;24029",
    "iso:country":"IT",
    "sg:address":"24029 Vertova",
    "sg:city":"Vertova",
    "sg:orig_category":"Servizi E Lavori Per Abbigliamento E Pelletterie",
    "sg:phone":"+39 035 711017",
    "sg:postcode":"24029",
    "sg:province":"Bergamo",
    "sg:website":"http://www.gusmini.com",
    "wof:name":"Gusmini S. Lanificio Feltrificio Srl",
    "wof:placetype":"venue"
},
  "geometry": {"coordinates":[9.818562,45.829792],"type":"Point"}
}