{
  "type": "Feature",
  "properties": {
    "iso:country":"IT",
    "sg:address":"63018 Porto Sant'elpidio",
    "sg:orig_category":"Calzature, Pelletterie E Pelli",
    "sg:phone":"+39 0734 997056",
    "sg:postcode":"63018",
    "sg:province":"Ascoli Piceno",
    "sg:website":"http://italiacalzature.com/dati/prod/dati/calz_c2jb044061.html",
    "wof:name":"Calzaturificio Maranesi",
    "wof:placetype":"venue"
},
  "geometry": {"coordinates":[13.749384,43.239349],"type":"Point"}
}