{
  "type": "Feature",
  "properties": {
    "addr:full":"Via Nazionale Appia; Lioni; 83047 Lioni Avellino 83047",
    "addr:postcode":"83047;83047",
    "addr:street":"Via Nazionale Appia Lioni",
    "iso:country":"IT",
    "sg:address":"Via Nazionale Appia; Lioni; 83047",
    "sg:city":"Lioni",
    "sg:classifiers":[
        {
            "category":"Banks & Credit Unions",
            "subcategory":"Bank",
            "type":"Services"
        }
    ],
    "sg:phone":"+39 0827 42154",
    "sg:postcode":"83047",
    "sg:province":"Avellino",
    "wof:name":"Banca Popolare Coop. Di Pescopagano",
    "wof:placetype":"venue"
},
  "geometry": {"coordinates":[15.25447,40.852196],"type":"Point"}
}