{
  "type": "Feature",
  "properties": {
    "addr:full":"40012 Calderara Di Reno Calderara di Reno Bologna 40012",
    "addr:postcode":"40012;40012",
    "iso:country":"IT",
    "sg:address":"40012 Calderara Di Reno",
    "sg:city":"Calderara di Reno",
    "sg:orig_category":"Utensili Meccanici E Materiali. Forniture Per Attivita' Industriali",
    "sg:phone":"+39 051 646 6192",
    "sg:postcode":"40012",
    "sg:province":"Bologna",
    "wof:name":"Claren Cutting Service Snc Di C. Renna & C.",
    "wof:placetype":"venue"
},
  "geometry": {"coordinates":[11.297216,44.5429],"type":"Point"}
}