{
  "type": "Feature",
  "properties": {
    "iso:country":"IT",
    "sg:address":"70051 Barletta",
    "sg:city":"Barletta",
    "sg:orig_category":"Apparecchiature Ed Attrezzature Meccaniche",
    "sg:phone":"+39 0883 510446",
    "sg:postcode":"70051",
    "sg:province":"Bari",
    "wof:name":"Nuova Union Trecciati Snc",
    "wof:placetype":"venue"
},
  "geometry": {"coordinates":[16.069635,41.304806],"type":"Point"}
}