{
  "type": "Feature",
  "properties": {
    "addr:full":"Via Donzelli Da Poneta 50022 Greve In Chianti Greve in Chianti Firenze 50022",
    "addr:postcode":"50022;50022",
    "addr:street":"Via Donzelli Da Poneta",
    "iso:country":"IT",
    "sg:address":"Via Donzelli Da Poneta 50022 Greve In Chianti",
    "sg:city":"Greve in Chianti",
    "sg:classifiers":[
        {
            "category":"Manufacturing",
            "subcategory":"Rubber & Plastics",
            "type":"Manufacturing & Wholesale Goods"
        }
    ],
    "sg:phone":"+39 39055850467",
    "sg:postcode":"50022",
    "sg:province":"Firenze",
    "wof:name":"Sa.de.ro Srl",
    "wof:placetype":"venue"
},
  "geometry": {"coordinates":[11.2623338699,43.6474304199],"type":"Point"}
}