{
  "type": "Feature",
  "properties": {
    "iso:country":"IT",
    "sg:address":"05100 Terni",
    "sg:city":"Terni",
    "sg:orig_category":"Forniture Per Edilizia E Lavori Pubblici. Arredi Ed Attrezzature Per Attivita' Commerciali Ed Artigianali. Forniture Per Attivita' Industriali",
    "sg:phone":"+39 0744 406611",
    "sg:postcode":"05100",
    "sg:province":"Terni",
    "wof:name":"Petrelli Cav. Uff. Attilio",
    "wof:placetype":"venue"
},
  "geometry": {"coordinates":[12.6431722641,42.5707550049],"type":"Point"}
}