{
  "type": "Feature",
  "properties": {
    "iso:country":"IT",
    "sg:address":"19125 La Spezia",
    "sg:orig_category":"Macchine, Impianti Ed Attrezzature Per Industria Alimentare E Bevande. Macchine E Impianti Per Attivita' Commerciali Ed Artigianali",
    "sg:phone":"+39 0187 521006",
    "sg:province":"SP",
    "wof:name":"So.co.li. Di Marcello Rossi E C. Snc",
    "wof:placetype":"venue"
},
  "geometry": {"coordinates":[9.84321,44.122463],"type":"Point"}
}