{
  "type": "Feature",
  "properties": {
    "iso:country":"IT",
    "sg:address":"940/b, Via Prenestina 00155 Roma",
    "sg:city":"Roma",
    "sg:classifiers":[
        {
            "category":"Manufacturing",
            "subcategory":"Metals",
            "type":"Manufacturing & Wholesale Goods"
        }
    ],
    "sg:phone":"+39 39062281996",
    "sg:postcode":"00155",
    "sg:province":"Roma",
    "sg:tags":[
        "metallurgy",
        "metalworking"
    ],
    "wof:name":"Profiltubi (s.a.s.)",
    "wof:placetype":"venue"
},
  "geometry": {"coordinates":[12.8843755722,41.889793396],"type":"Point"}
}