{
  "type": "Feature",
  "properties": {
    "addr:full":"58034 Castell'azzara Selvena Grosseto 58034",
    "addr:postcode":"58034;58034",
    "iso:country":"IT",
    "sg:address":"58034 Castell'azzara",
    "sg:city":"Selvena",
    "sg:orig_category":"Materiali Edili",
    "sg:phone":"+39 0564 951504",
    "sg:postcode":"58034",
    "sg:province":"Grosseto",
    "wof:name":"V.f.di Fortunati Gianni & C. Snc",
    "wof:placetype":"venue"
},
  "geometry": {"coordinates":[11.697824,42.770618],"type":"Point"}
}