{
  "type": "Feature",
  "properties": {
    "addr:full":"37121 Verona Verona Verona 37121",
    "addr:postcode":"37121;37121",
    "iso:country":"IT",
    "sg:address":"37121 Verona",
    "sg:city":"Verona",
    "sg:orig_category":"Agenti D'affari In Mediazione",
    "sg:phone":"+39 045 801 1772",
    "sg:postcode":"37121",
    "sg:province":"Verona",
    "sg:website":"http://www.immobiliarehabitat.it",
    "wof:name":"Habitat Fiorenzato Franco",
    "wof:placetype":"venue"
},
  "geometry": {"coordinates":[10.993498,45.441616],"type":"Point"}
}