{
  "type": "Feature",
  "properties": {
    "iso:country":"IT",
    "sg:address":"34123 Trieste",
    "sg:city":"Trieste",
    "sg:orig_category":"Tourism, Services. Transport, Auxiliary Services",
    "sg:phone":"+39 040 318 2111",
    "sg:postcode":"34123",
    "sg:province":"Trieste",
    "wof:name":"Agenzia Marittima Triestina Srl",
    "wof:placetype":"venue"
},
  "geometry": {"coordinates":[13.759215,45.645462],"type":"Point"}
}