{
  "type": "Feature",
  "properties": {
    "addr:full":"54, Via Alessandrina 27010 Albuzzano Albuzzano Pavia 27010",
    "addr:postcode":"27010;27010",
    "addr:street":"Via Alessandrina",
    "iso:country":"IT",
    "sg:address":"54, Via Alessandrina 27010 Albuzzano",
    "sg:city":"Albuzzano",
    "sg:classifiers":[
        {
            "category":"Professional",
            "subcategory":"Engineering",
            "type":"Services"
        }
    ],
    "sg:phone":"+39 0382 484025",
    "sg:postcode":"27010",
    "sg:province":"Pavia",
    "sg:tags":[
        "machine",
        "-",
        "mechanical"
    ],
    "wof:name":"Costruzioni Meccaniche G.grassi Di Luigi Grassi E",
    "wof:placetype":"venue"
},
  "geometry": {"coordinates":[9.2702455521,45.1875991821],"type":"Point"}
}