{
  "type": "Feature",
  "properties": {
    "addr:full":"11023 Chambave Chambave Aosta 11023",
    "addr:housenumber":"11023",
    "addr:postcode":"11023",
    "addr:street":"Chambave Chambave Aosta",
    "iso:country":"IT",
    "sg:address":"11023 Chambave",
    "sg:city":"Chambave",
    "sg:orig_category":"Agricoltura, Orticoltura E Floricoltura",
    "sg:phone":"+39 0166 546112",
    "sg:postcode":"11023",
    "sg:province":"Aosta",
    "wof:name":"Bancod Eralda Marcella",
    "wof:placetype":"venue"
},
  "geometry": {"coordinates":[7.550218,45.744564],"type":"Point"}
}