{
  "type": "Feature",
  "properties": {
    "iso:country":"IT",
    "sg:address":"27058 Voghera",
    "sg:city":"Voghera",
    "sg:orig_category":"Petroli, Gas E Combustibili",
    "sg:phone":"+39 0383 43878",
    "sg:postcode":"27058",
    "sg:province":"Pavia",
    "wof:name":"Restiani Spa",
    "wof:placetype":"venue"
},
  "geometry": {"coordinates":[9.0118846893,44.999912262],"type":"Point"}
}