{
  "type": "Feature",
  "properties": {
    "addr:full":"21/23, Via Monte Falco 52100 Arezzo Arezzo Arezzo 52100",
    "addr:housenumber":"21 / 23",
    "addr:postcode":"52100;52100",
    "addr:street":"Via Monte Falco",
    "iso:country":"IT",
    "sg:address":"21/23, Via Monte Falco 52100 Arezzo",
    "sg:city":"Arezzo",
    "sg:classifiers":[
        {
            "category":"Shopping",
            "subcategory":"Computers & Home Electronics",
            "type":"Retail Goods"
        }
    ],
    "sg:phone":"+39 0575 302251",
    "sg:postcode":"52100",
    "sg:province":"Arezzo",
    "sg:tags":[
        "electronic",
        "electrical",
        "equipment"
    ],
    "wof:name":"Mantovani Fratelli",
    "wof:placetype":"venue"
},
  "geometry": {"coordinates":[11.873038,43.466282],"type":"Point"}
}