{
  "type": "Feature",
  "properties": {
    "iso:country":"IT",
    "sg:address":"48010 Casola Valsenio",
    "sg:city":"Casola Valsenio",
    "sg:orig_category":"Forniture Per Abbigliamento E Pelletterie",
    "sg:phone":"+39 0546 73027",
    "sg:postcode":"48010",
    "sg:province":"Ravenna",
    "wof:name":"Piuma 02 S.n.c. Di Alpi Luciana & C.",
    "wof:placetype":"venue"
},
  "geometry": {"coordinates":[11.6519098282,44.2423171997],"type":"Point"}
}