{
  "type": "Feature",
  "properties": {
    "iso:country":"IT",
    "sg:address":"20090 Trezzano Sul Naviglio",
    "sg:city":"Trezzano sul Naviglio",
    "sg:orig_category":"Macchine Ed Impianti Per Edilizia E Lavori Pubblici. Macchine Utensili E Impianti",
    "sg:phone":"+39 02 445 4250",
    "sg:postcode":"20090",
    "sg:province":"Milano",
    "wof:name":"Aria Piu' S.r.l.",
    "wof:placetype":"venue"
},
  "geometry": {"coordinates":[9.070732,45.418339],"type":"Point"}
}