{
  "type": "Feature",
  "properties": {
    "addr:full":"Via Col Moschin 16, L-20135 Milan, Mi Milano 20135",
    "addr:housenumber":"16 l-20135",
    "addr:postcode":"20135",
    "addr:street":"Via Col Moschin",
    "iso:country":"IT",
    "sg:address":"Via Col Moschin 16, L-20135 Milan, Mi",
    "sg:classifiers":[
        {
            "category":"Banks & Credit Unions",
            "subcategory":"Bank",
            "type":"Services"
        }
    ],
    "sg:postcode":"20135",
    "sg:province":"Milano",
    "wof:name":"Intesatrade Sim Spa",
    "wof:placetype":"venue"
},
  "geometry": {"coordinates":[9.185498,45.450123],"type":"Point"}
}