{
  "type": "Feature",
  "properties": {
    "iso:country":"IT",
    "sg:address":"06073 Corciano",
    "sg:city":"Corciano",
    "sg:orig_category":"Arredi Ed Attrezzature Per Attivita' Commerciali Ed Artigianali",
    "sg:phone":"+39 075 697 8342",
    "sg:postcode":"06073",
    "sg:province":"Perugia",
    "wof:name":"Grafiche Trotta Perugia Srl",
    "wof:placetype":"venue"
},
  "geometry": {"coordinates":[12.289222,43.109352],"type":"Point"}
}