{
  "type": "Feature",
  "properties": {
    "addr:full":"Via Einstein 6 30036 Santa Maria Di Sala Santa Maria di Sala Venezia 30036",
    "addr:housenumber":"6",
    "addr:postcode":"30036;30036",
    "addr:street":"Via Einstein;Maria",
    "iso:country":"IT",
    "sg:address":"Via Einstein 6 30036 Santa Maria Di Sala",
    "sg:city":"Santa Maria di Sala",
    "sg:orig_category":"Hosiery, Nightwear, Daywear",
    "sg:phone":"+39 041 486444",
    "sg:postcode":"30036",
    "sg:province":"Venezia",
    "wof:name":"Agostini Srl",
    "wof:placetype":"venue"
},
  "geometry": {"coordinates":[12.338784,45.434338],"type":"Point"}
}