{
  "type": "Feature",
  "properties": {
    "iso:country":"IT",
    "sg:address":"224, Via Faentina 48100 Ravenna",
    "sg:city":"Ravenna",
    "sg:classifiers":[
        {
            "category":"Manufacturing",
            "subcategory":"Tools & Machinery",
            "type":"Manufacturing & Wholesale Goods"
        }
    ],
    "sg:phone":"+39 0544 464221",
    "sg:postcode":"48100",
    "sg:province":"Ravenna",
    "sg:tags":[
        "environment",
        "equipment",
        "-"
    ],
    "wof:name":"Agriparadigma (s.r.l.)",
    "wof:placetype":"venue"
},
  "geometry": {"coordinates":[12.225,44.363888],"type":"Point"}
}