{
  "type": "Feature",
  "properties": {
    "iso:country":"IT",
    "sg:address":"Via Vespucci 4 20022 Castano Primo",
    "sg:city":"Castano Primo",
    "sg:classifiers":[
        {
            "category":"Home & Garden",
            "subcategory":"Carpets & Floor Coverings",
            "type":"Retail Goods"
        }
    ],
    "sg:phone":"+39 0331 880528",
    "sg:postcode":"20022",
    "sg:province":"Milano",
    "sg:tags":[
        "animal",
        "skin"
    ],
    "wof:name":"Conceria Everest Di Ruggeri Giovanni",
    "wof:placetype":"venue"
},
  "geometry": {"coordinates":[8.783056,45.547497],"type":"Point"}
}