{
  "type": "Feature",
  "properties": {
    "iso:country":"IT",
    "sg:address":"21010 Cardano Al Campo",
    "sg:city":"Cardano al Campo",
    "sg:orig_category":"Macchine Utensili E Impianti",
    "sg:phone":"+39 0331 732700",
    "sg:postcode":"21010",
    "sg:province":"Varese",
    "wof:name":"Galdabini Cesare (s.p.a.)",
    "wof:placetype":"venue"
},
  "geometry": {"coordinates":[8.760533,45.653027],"type":"Point"}
}