{
  "type": "Feature",
  "properties": {
    "iso:country":"IT",
    "sg:address":"Via Bernocchi, 9; Carcina; 25060",
    "sg:classifiers":[
        {
            "category":"Banks & Credit Unions",
            "subcategory":"Bank",
            "type":"Services"
        }
    ],
    "sg:phone":"+39 030 882333",
    "sg:postcode":"25060",
    "sg:province":"Brescia",
    "wof:name":"Banca Agricola Mantovana",
    "wof:placetype":"venue"
},
  "geometry": {"coordinates":[10.194415,45.641956],"type":"Point"}
}