{
  "type": "Feature",
  "properties": {
    "iso:country":"IT",
    "sg:address":"50144 Firenze",
    "sg:city":"Firenze",
    "sg:orig_category":"Servizi Per Lo Sport E Il Tempo Libero. Ristoranti Ed Esercizi Affini. Servizi Ausiliari Di Ristorazione E Di Intrattenimento",
    "sg:phone":"+39 055 352143",
    "sg:postcode":"50144",
    "sg:province":"Firenze",
    "sg:website":"http://www.rio-grande.it",
    "wof:name":"Rio Grande",
    "wof:placetype":"venue"
},
  "geometry": {"coordinates":[10.747909,43.860737],"type":"Point"}
}