{
  "type": "Feature",
  "properties": {
    "addr:full":"10, Via Costa Andrea 20131 Milano Milano Milano 20131",
    "addr:postcode":"20131;20131",
    "addr:street":"Via Costa Andrea",
    "iso:country":"IT",
    "sg:address":"10, Via Costa Andrea 20131 Milano",
    "sg:city":"Milano",
    "sg:classifiers":[
        {
            "category":"Wholesale",
            "subcategory":"Drugs",
            "type":"Manufacturing & Wholesale Goods"
        }
    ],
    "sg:phone":"+39 39022871277",
    "sg:postcode":"20131",
    "sg:province":"Milano",
    "sg:tags":[
        "chemical",
        "pharmaceutical"
    ],
    "wof:name":"Pharmamec S.a.s. Di Angelo Segalini & C.",
    "wof:placetype":"venue"
},
  "geometry": {"coordinates":[9.220078,45.487068],"type":"Point"}
}