{
  "type": "Feature",
  "properties": {
    "iso:country":"IT",
    "sg:address":"20131 Milano",
    "sg:city":"Milano",
    "sg:orig_category":"Elettronica Professionale E Di Consumo. Tempo Libero - Articoli E Forniture",
    "sg:phone":"+39 02 236 0120",
    "sg:postcode":"20131",
    "sg:province":"Milano",
    "sg:website":"http://www.giablu.com",
    "wof:name":"Gi@blu Di Scavone Cristhian",
    "wof:placetype":"venue"
},
  "geometry": {"coordinates":[9.22359,45.483166],"type":"Point"}
}