{
  "type": "Feature",
  "properties": {
    "iso:country":"IT",
    "sg:address":"74/a, Ca' Pantano 47010 Galeata",
    "sg:city":"Galeata",
    "sg:classifiers":[
        {
            "category":"Professional",
            "subcategory":"Engineering",
            "type":"Services"
        }
    ],
    "sg:phone":"+39 0543 983646",
    "sg:postcode":"47010",
    "sg:province":"Forl\u00ec-Cesena",
    "sg:tags":[
        "machine",
        "-",
        "mechanical"
    ],
    "wof:name":"C.m. Di Mazzoni Mario",
    "wof:placetype":"venue"
},
  "geometry": {"coordinates":[11.980461,43.994766],"type":"Point"}
}