{
  "type": "Feature",
  "properties": {
    "addr:full":"20123 Milano Milano Milano 20123",
    "addr:postcode":"20123;20123",
    "iso:country":"IT",
    "sg:address":"20123 Milano",
    "sg:city":"Milano",
    "sg:orig_category":"Studi E Consulenze Legali E Notarili. Avvocati, Notai E Servizi Legali. Professionisti - Studi E Servizi Ed Associazioni Di Interesse Aziendale",
    "sg:phone":"+39 02 876598",
    "sg:postcode":"20123",
    "sg:province":"Milano",
    "wof:name":"Iannello & Olivares - Notai Associati",
    "wof:placetype":"venue"
},
  "geometry": {"coordinates":[9.18887,45.463268],"type":"Point"}
}