{
  "type": "Feature",
  "properties": {
    "iso:country":"IT",
    "sg:address":"3, Via Dosa 30030 Martellago",
    "sg:city":"Martellago",
    "sg:classifiers":[
        {
            "category":"Manufacturing",
            "subcategory":"Glass & Minerals",
            "type":"Manufacturing & Wholesale Goods"
        }
    ],
    "sg:phone":"+39 39041908920",
    "sg:postcode":"30030",
    "sg:province":"Venezia",
    "wof:name":"Arte Veneziana Arredo (s.n.c.)",
    "wof:placetype":"venue"
},
  "geometry": {"coordinates":[12.192617,45.515808],"type":"Point"}
}