{
  "type": "Feature",
  "properties": {
    "iso:country":"IT",
    "sg:address":"38, Via Sassorosso 41046 Palagano",
    "sg:city":"Palagano",
    "sg:classifiers":[
        {
            "category":"Building & Trades",
            "subcategory":"Construction",
            "type":"Services"
        }
    ],
    "sg:phone":"+39 0536 964225",
    "sg:postcode":"41046",
    "sg:province":"Modena",
    "sg:tags":[
        "work",
        "public"
    ],
    "wof:name":"Stradedil S.r.l.",
    "wof:placetype":"venue"
},
  "geometry": {"coordinates":[10.92522,44.647079],"type":"Point"}
}