{
  "type": "Feature",
  "properties": {
    "addr:full":"20, Via Dell' Artigianato 20041 Agrate Brianza Agrate Brianza Milano 20041",
    "addr:postcode":"20041;20041",
    "addr:street":"Via Dell ' Artigianato",
    "iso:country":"IT",
    "sg:address":"20, Via Dell' Artigianato 20041 Agrate Brianza",
    "sg:city":"Agrate Brianza",
    "sg:classifiers":[
        {
            "category":"Shopping",
            "type":"Retail Goods"
        }
    ],
    "sg:phone":"+39 039 605 8658",
    "sg:postcode":"20041",
    "sg:province":"Milano",
    "sg:tags":[
        "finished",
        "-",
        "metallic"
    ],
    "wof:name":"Angstrom Mecc. (s.n.c.)",
    "wof:placetype":"venue"
},
  "geometry": {"coordinates":[9.3574953079,45.5656929016],"type":"Point"}
}