{
  "type": "Feature",
  "properties": {
    "addr:full":"07100 Sassari Sassari Sassari 07100",
    "addr:postcode":"07100;07100",
    "iso:country":"IT",
    "sg:address":"07100 Sassari",
    "sg:city":"Sassari",
    "sg:orig_category":"Petroli, Gas E Combustibili",
    "sg:phone":"+39 079 270036",
    "sg:postcode":"07100",
    "sg:province":"Sassari",
    "wof:name":"Medea Spa Mediterranea Energia Ambiente",
    "wof:placetype":"venue"
},
  "geometry": {"coordinates":[8.3745718002,40.7555809021],"type":"Point"}
}