{
  "type": "Feature",
  "properties": {
    "iso:country":"IT",
    "sg:address":"116, Via Flavia 34147 Trieste",
    "sg:city":"Trieste",
    "sg:classifiers":[
        {
            "category":"Shopping",
            "subcategory":"Computers & Home Electronics",
            "type":"Retail Goods"
        }
    ],
    "sg:phone":"+39 39040383061",
    "sg:postcode":"34147",
    "sg:province":"Trieste",
    "sg:tags":[
        "electronic",
        "electrical",
        "equipment"
    ],
    "wof:name":"O.c.r.e.m. (s.r.l.)",
    "wof:placetype":"venue"
},
  "geometry": {"coordinates":[13.819425,45.613785],"type":"Point"}
}