{
  "type": "Feature",
  "properties": {
    "addr:full":"27040 Mezzanino Mezzanino Pavia 27040",
    "addr:postcode":"27040;27040",
    "iso:country":"IT",
    "sg:address":"27040 Mezzanino",
    "sg:city":"Mezzanino",
    "sg:orig_category":"Prodotti E Manufatti In Materie Plastiche. Prodotti Cosmetici E Da Toeletta. Forniture Per Attivita' Industriali",
    "sg:phone":"+39 0385 716241",
    "sg:postcode":"27040",
    "sg:province":"Pavia",
    "wof:name":"Panda Di Romagnoli Angelo & C. Snc",
    "wof:placetype":"venue"
},
  "geometry": {"coordinates":[9.2293462753,45.1604270935],"type":"Point"}
}