{
  "type": "Feature",
  "properties": {
    "iso:country":"IT",
    "sg:address":"Via Donzellino 37031 Illasi",
    "sg:city":"Illasi",
    "sg:classifiers":[
        {
            "category":"Shopping",
            "subcategory":"Clothing, Apparel, & Fashions",
            "type":"Retail Goods"
        }
    ],
    "sg:phone":"+39 045 783 4054",
    "sg:postcode":"37031",
    "sg:province":"Verona",
    "sg:tags":[
        "clothing",
        "accessory"
    ],
    "wof:name":"Ombrellificio Grigolini",
    "wof:placetype":"venue"
},
  "geometry": {"coordinates":[11.167814,45.441616],"type":"Point"}
}