{
  "type": "Feature",
  "properties": {
    "iso:country":"IT",
    "sg:address":"10122 Torino",
    "sg:city":"Torino",
    "sg:orig_category":"Orologeria",
    "sg:phone":"+39 011 533504",
    "sg:postcode":"10122",
    "sg:province":"Torino",
    "wof:name":"Jolly Oro Srl",
    "wof:placetype":"venue"
},
  "geometry": {"coordinates":[7.55243,45.009834],"type":"Point"}
}