{
  "type": "Feature",
  "properties": {
    "iso:country":"IT",
    "sg:address":"43, Viale Leonardo Da Vinci 20090 Trezzano Sul Naviglio",
    "sg:city":"Trezzano sul Naviglio",
    "sg:classifiers":[
        {
            "category":"Wholesale",
            "subcategory":"Drugs",
            "type":"Manufacturing & Wholesale Goods"
        }
    ],
    "sg:phone":"+39 390 248 4791",
    "sg:postcode":"20090",
    "sg:province":"Milano",
    "sg:tags":[
        "chemical",
        "pharmaceutical"
    ],
    "wof:name":"Azelis Italia Spa",
    "wof:placetype":"venue"
},
  "geometry": {"coordinates":[9.063527,45.422848],"type":"Point"}
}