{
  "type": "Feature",
  "properties": {
    "addr:full":"24122 Bergamo Bergamo Bergamo 24122",
    "addr:postcode":"24122;24122",
    "iso:country":"IT",
    "sg:address":"24122 Bergamo",
    "sg:city":"Bergamo",
    "sg:orig_category":"Scuole E Servizi Scolastici. Servizi Ausiliari Dei Mezzi Di Trasporto. Ricerca, Selezione E Formazione Del Personale",
    "sg:phone":"+39 035 247370",
    "sg:postcode":"24122",
    "sg:province":"Bergamo",
    "wof:name":"Autoscuola Drago Di Camillo & Daniele Snc",
    "wof:placetype":"venue"
},
  "geometry": {"coordinates":[9.665471,45.689777],"type":"Point"}
}