{
  "type": "Feature",
  "properties": {
    "addr:full":"00187 Roma Roma Roma 00187",
    "addr:postcode":"00187;00187",
    "iso:country":"IT",
    "sg:address":"00187 Roma",
    "sg:city":"Roma",
    "sg:orig_category":"Servizi E Lavori Per Abbigliamento E Pelletterie",
    "sg:phone":"+39 06 3600 2186",
    "sg:postcode":"00187",
    "sg:province":"Roma",
    "wof:name":"De Carlis (s.r.l.)",
    "wof:placetype":"venue"
},
  "geometry": {"coordinates":[12.484528,41.896851],"type":"Point"}
}