{
  "type": "Feature",
  "properties": {
    "iso:country":"IT",
    "sg:address":"Zona Artigianale 6 39040 Vahrn",
    "sg:classifiers":[
        {
            "category":"Bars & Pubs",
            "subcategory":"Nightclub",
            "type":"Food & Drink"
        }
    ],
    "sg:phone":"+39 0472 272601",
    "sg:postcode":"39040",
    "sg:province":"Bolzano/Bozen",
    "sg:tags":[
        "crystal",
        "lamp",
        "chandelier"
    ],
    "sg:website":"www.faustig.ge",
    "wof:name":"Faustig Kurt Sas",
    "wof:placetype":"venue"
},
  "geometry": {"coordinates":[11.652039,46.732529],"type":"Point"}
}