{
  "type": "Feature",
  "properties": {
    "iso:country":"IT",
    "sg:address":"5, Via Andorno 10153 Torino",
    "sg:city":"Torino",
    "sg:classifiers":[
        {
            "category":"Communications",
            "subcategory":"Newspaper",
            "type":"Services"
        }
    ],
    "sg:phone":"+39 011 812 2480",
    "sg:postcode":"10153",
    "sg:province":"Torino",
    "sg:tags":[
        "advertising"
    ],
    "wof:name":"Bonomi (s.n.c.)",
    "wof:placetype":"venue"
},
  "geometry": {"coordinates":[7.711234,45.069626],"type":"Point"}
}