{
  "type": "Feature",
  "properties": {
    "iso:country":"IT",
    "sg:address":"64026 Roseto Degli Abruzzi",
    "sg:city":"Roseto degli Abruzzi",
    "sg:orig_category":"Scuole E Servizi Scolastici",
    "sg:phone":"+39 085 899 5128",
    "sg:postcode":"64026",
    "sg:province":"Teramo",
    "wof:name":"Figlie Di S. Anna",
    "wof:placetype":"venue"
},
  "geometry": {"coordinates":[13.987995,42.677578],"type":"Point"}
}