{
  "type": "Feature",
  "properties": {
    "iso:country":"IT",
    "sg:address":"10139 Torino",
    "sg:city":"Torino",
    "sg:orig_category":"Servizi Di Magazzinaggio E Movimentazione. Servizi Ausiliari Di Sorveglianza, Manutenzione E Pulizia. Servizi Per Aziende, Manifestazioni E Supporto Agli Scambi Commerciali",
    "sg:phone":"+39 011 385 3161",
    "sg:postcode":"10139",
    "sg:province":"Torino",
    "wof:name":"C.s.m. Soc. Coop. A R.l.",
    "wof:placetype":"venue"
},
  "geometry": {"coordinates":[7.642266,45.071144],"type":"Point"}
}