{
  "type": "Feature",
  "properties": {
    "iso:country":"IT",
    "sg:address":"15057 Tortona",
    "sg:city":"Tortona",
    "sg:orig_category":"Agenzie D'affari E Servizi Commerciali. Avvocati, Notai E Servizi Legali. Consulenze Tecniche, Amministrative E Perizie",
    "sg:phone":"+39 0131 866378",
    "sg:postcode":"15057",
    "sg:province":"Alessandria",
    "wof:name":"Dallera Francesco",
    "wof:placetype":"venue"
},
  "geometry": {"coordinates":[8.375333,45.08424],"type":"Point"}
}