{
  "type": "Feature",
  "properties": {
    "iso:country":"IT",
    "sg:address":"00144 Roma",
    "sg:city":"Roma",
    "sg:orig_category":"Abbigliamento Intimo, Calze E Costumi Da Bagno. Sport - Articoli E Forniture. Shopping",
    "sg:phone":"+39 06 5224 4013",
    "sg:postcode":"00144",
    "sg:province":"Roma",
    "wof:name":"G.& G. Italia Srl",
    "wof:placetype":"venue"
},
  "geometry": {"coordinates":[12.438959,41.806042],"type":"Point"}
}