{
  "type": "Feature",
  "properties": {
    "addr:full":"41100 Modena Modena Modena 41100",
    "addr:postcode":"41100;41100",
    "iso:country":"IT",
    "sg:address":"41100 Modena",
    "sg:city":"Modena",
    "sg:orig_category":"Pompe",
    "sg:phone":"+39 059 330091",
    "sg:postcode":"41100",
    "sg:province":"Modena",
    "wof:name":"Oleo Component System (s.r.l.)",
    "wof:placetype":"venue"
},
  "geometry": {"coordinates":[10.880607605,44.6556091309],"type":"Point"}
}