{
  "type": "Feature",
  "properties": {
    "iso:country":"IT",
    "sg:address":"Via Roma 10-14, 16100 Genoa, Ge",
    "sg:classifiers":[
        {
            "category":"Banks & Credit Unions",
            "subcategory":"Bank",
            "type":"Services"
        }
    ],
    "wof:name":"Banca Di Credito Cooperativo Genovese Scrl",
    "wof:placetype":"venue"
},
  "geometry": {"coordinates":[8.936737,44.409405],"type":"Point"}
}