{
  "type": "Feature",
  "properties": {
    "addr:full":"33018 Tarvisio Tarvisio Udine 33018",
    "addr:postcode":"33018;33018",
    "iso:country":"IT",
    "sg:address":"33018 Tarvisio",
    "sg:city":"Tarvisio",
    "sg:orig_category":"Autoaccessori - Produzione",
    "sg:phone":"+39 0428 4171",
    "sg:postcode":"33018",
    "sg:province":"Udine",
    "wof:name":"Weissenfels Spa",
    "wof:placetype":"venue"
},
  "geometry": {"coordinates":[13.553459,46.465477],"type":"Point"}
}