{
  "type": "Feature",
  "properties": {
    "iso:country":"IT",
    "sg:address":"20123 Milano",
    "sg:city":"Milano",
    "sg:orig_category":"Agenzie D'affari E Servizi Commerciali",
    "sg:phone":"+39 02 805 5101",
    "sg:postcode":"20123",
    "sg:province":"Milano",
    "wof:name":"Stuani Piero",
    "wof:placetype":"venue"
},
  "geometry": {"coordinates":[9.185597,45.459797],"type":"Point"}
}