{
  "type": "Feature",
  "properties": {
    "iso:country":"IT",
    "sg:address":"Via Delle Industrie 33050 Pavia Di Udine",
    "sg:city":"Pavia di Udine",
    "sg:classifiers":[
        {
            "category":"Shopping",
            "subcategory":"Stationery & Office Supplies",
            "type":"Retail Goods"
        }
    ],
    "sg:phone":"+39 0432 675839",
    "sg:postcode":"33050",
    "sg:province":"Udine",
    "sg:tags":[
        "professional"
    ],
    "wof:name":"Tecnoemme Snc Di Zanier & C.",
    "wof:placetype":"venue"
},
  "geometry": {"coordinates":[13.2717189789,45.9951438904],"type":"Point"}
}