{
  "type": "Feature",
  "properties": {
    "addr:full":"20081 Abbiategrasso Abbiategrasso Milano 20081",
    "addr:postcode":"20081;20081",
    "iso:country":"IT",
    "sg:address":"20081 Abbiategrasso",
    "sg:city":"Abbiategrasso",
    "sg:orig_category":"Ricambi E Componenti Dei Mezzi Di Trasporto",
    "sg:phone":"+39 02 9496 4672",
    "sg:postcode":"20081",
    "sg:province":"Milano",
    "wof:name":"La Ri-car Srl",
    "wof:placetype":"venue"
},
  "geometry": {"coordinates":[9.234413,45.511501],"type":"Point"}
}