{
  "type": "Feature",
  "properties": {
    "iso:country":"IT",
    "sg:address":"36070 Castelgomberto",
    "sg:city":"Castelgomberto",
    "sg:orig_category":"Forniture Per Agricoltura E Zootecnia. Animali Domestici",
    "sg:phone":"+39 0445 429111",
    "sg:postcode":"36070",
    "sg:province":"Vicenza",
    "sg:website":"http://www.ferplast.com",
    "wof:name":"Ferplast Spa",
    "wof:placetype":"venue"
},
  "geometry": {"coordinates":[11.3967218399,45.5859642029],"type":"Point"}
}