{
  "type": "Feature",
  "properties": {
    "iso:country":"IT",
    "sg:address":"Via Colle Ramole 50023 Impruneta",
    "sg:city":"Impruneta",
    "sg:classifiers":[
        {
            "category":"Professional",
            "subcategory":"Printing & Photocopies",
            "type":"Services"
        }
    ],
    "sg:phone":"+39 055 202 0711",
    "sg:postcode":"50023",
    "sg:province":"Firenze",
    "wof:name":"Studio Leonardo Fotolito (s.r.l.)",
    "wof:placetype":"venue"
},
  "geometry": {"coordinates":[11.2234992981,43.7273101807],"type":"Point"}
}