{
  "type": "Feature",
  "properties": {
    "iso:country":"IT",
    "sg:address":"1, V. E. Mattei 29010 Alseno",
    "sg:city":"Alseno",
    "sg:classifiers":[
        {
            "category":"Real Estate",
            "subcategory":"Surveying",
            "type":"Services"
        }
    ],
    "sg:phone":"+39 0523 945793",
    "sg:postcode":"29010",
    "sg:province":"Piacenza",
    "sg:tags":[
        "equipment",
        "material",
        "good",
        "-",
        "handling"
    ],
    "sg:website":"http://www.clacson.com",
    "wof:name":"Marchelli Tecna Snc",
    "wof:placetype":"venue"
},
  "geometry": {"coordinates":[9.695142,45.053772],"type":"Point"}
}