{
  "type": "Feature",
  "properties": {
    "iso:country":"IT",
    "sg:address":"24060 Cividino",
    "sg:city":"Cividino",
    "sg:orig_category":"Accessori Moda D'abbigliamento",
    "sg:phone":"+39 030 743 8858",
    "sg:postcode":"24060",
    "sg:province":"Bergamo",
    "wof:name":"Pelletterie 2f (s.p.a.)",
    "wof:placetype":"venue"
},
  "geometry": {"coordinates":[9.889883,45.610531],"type":"Point"}
}