{
  "type": "Feature",
  "properties": {
    "addr:full":"31100 Treviso Treviso Treviso 31100",
    "addr:postcode":"31100;31100",
    "iso:country":"IT",
    "sg:address":"31100 Treviso",
    "sg:city":"Treviso",
    "sg:classifiers":[
        {
            "category":"Banks & Credit Unions",
            "subcategory":"Bureau De Change",
            "type":"Services"
        }
    ],
    "sg:phone":"+39 0422 315131",
    "sg:postcode":"31100",
    "sg:province":"Treviso",
    "sg:tags":[
        "services",
        "tourism",
        "public",
        "private",
        "transport"
    ],
    "wof:name":"Aeroporto Di Treviso Spa",
    "wof:placetype":"venue"
},
  "geometry": {"coordinates":[12.20568,45.655323],"type":"Point"}
}