{
  "type": "Feature",
  "properties": {
    "iso:country":"IT",
    "sg:address":"20060 Gessate",
    "sg:city":"Gessate",
    "sg:orig_category":"Macchine, Impianti Ed Attrezzature Industria Chimica. Attrezzature E Forniture Per Officine Riparazione E Servizi Ausiliari",
    "sg:phone":"+39 02 959 2921",
    "sg:postcode":"20060",
    "sg:province":"Milano",
    "wof:name":"Wagner Colora S.r.l.",
    "wof:placetype":"venue"
},
  "geometry": {"coordinates":[9.462349,45.567162],"type":"Point"}
}