{
  "type": "Feature",
  "properties": {
    "iso:country":"IT",
    "sg:address":"10152 Torino",
    "sg:city":"Torino",
    "sg:orig_category":"Materiali Semilavorati Metallici",
    "sg:phone":"+39 011 858222",
    "sg:postcode":"10152",
    "sg:province":"Torino",
    "wof:name":"Simpa Srl",
    "wof:placetype":"venue"
},
  "geometry": {"coordinates":[7.69278,45.080498],"type":"Point"}
}