{
  "type": "Feature",
  "properties": {
    "iso:country":"IT",
    "sg:address":"21052 Busto Arsizio",
    "sg:city":"Busto Arsizio",
    "sg:orig_category":"Cine-foto-ottica. Articoli Medico-sanitari Ed Ortopedici. Impianti, Attrezzature E Forniture Sanitarie Ed Ospedaliere",
    "sg:phone":"+39 0331 635016",
    "sg:postcode":"21052",
    "sg:province":"Varese",
    "wof:name":"Ottica Sonnino Snc Di Pietro Allodi & C.",
    "wof:placetype":"venue"
},
  "geometry": {"coordinates":[8.84347,45.614227],"type":"Point"}
}