{
  "type": "Feature",
  "properties": {
    "iso:country":"IT",
    "sg:address":"Via F. Rubichi, 3; Galatone; 73044",
    "sg:city":"Galatone",
    "sg:classifiers":[
        {
            "category":"Banks & Credit Unions",
            "subcategory":"Bank",
            "type":"Services"
        }
    ],
    "sg:phone":"+39 0833 86733",
    "sg:postcode":"73044",
    "sg:province":"Lecce",
    "wof:name":"Banca Leuzzi & Megha Spa",
    "wof:placetype":"venue"
},
  "geometry": {"coordinates":[18.072887,40.149094],"type":"Point"}
}