{
  "type": "Feature",
  "properties": {
    "iso:country":"IT",
    "sg:address":"Regione Prati E Pescine 113 18011 Arma Di Taggia",
    "sg:classifiers":[
        {
            "category":"Banks & Credit Unions",
            "subcategory":"Financial Services",
            "type":"Services"
        }
    ],
    "sg:phone":"+39 0184 4881",
    "sg:postcode":"18011",
    "sg:province":"Imperia",
    "sg:tags":[
        "wreath",
        "spray",
        "flower"
    ],
    "sg:website":"www.arlottiexport.com",
    "wof:name":"Arlotti Export Srl",
    "wof:placetype":"venue"
},
  "geometry": {"coordinates":[8.0315637589,43.8878936768],"type":"Point"}
}