{
  "type": "Feature",
  "properties": {
    "addr:full":"20017 Rho Rho Milano 20017",
    "addr:postcode":"20017;20017",
    "iso:country":"IT",
    "sg:address":"20017 Rho",
    "sg:city":"Rho",
    "sg:orig_category":"Cartotecnica E Servizi. Articoli Per Imballaggio E Confezionamento",
    "sg:phone":"+39 02 9350 8407",
    "sg:postcode":"20017",
    "sg:province":"Milano",
    "wof:name":"Mascherpa Soluzioni Per L'imballaggio Snc",
    "wof:placetype":"venue"
},
  "geometry": {"coordinates":[9.043291,45.525867],"type":"Point"}
}