{
  "type": "Feature",
  "properties": {
    "iso:country":"IT",
    "sg:address":"19/a, Via Restello 35010 Villa Del Conte",
    "sg:city":"Villa del Conte",
    "sg:classifiers":[
        {
            "category":"Shopping",
            "subcategory":"Clothing, Apparel, & Fashions",
            "type":"Retail Goods"
        }
    ],
    "sg:phone":"+39 049 932 5388",
    "sg:postcode":"35010",
    "sg:province":"Padova",
    "sg:tags":[
        "clothing",
        "accessory"
    ],
    "wof:name":"Co.ba. S.r.l.",
    "wof:placetype":"venue"
},
  "geometry": {"coordinates":[11.876589,45.409569],"type":"Point"}
}