{
  "type": "Feature",
  "properties": {
    "addr:full":"12030 Polonghera Polonghera Cuneo 12030",
    "addr:housenumber":"12030",
    "addr:postcode":"12030",
    "addr:street":"Polonghera Polonghera",
    "iso:country":"IT",
    "sg:address":"12030 Polonghera",
    "sg:city":"Polonghera",
    "sg:orig_category":"Agricoltura, Orticoltura E Floricoltura",
    "sg:phone":"+39 011 974656",
    "sg:postcode":"12030",
    "sg:province":"Cuneo",
    "wof:name":"Rostagno Giuseppe & C. (s.a.s.)",
    "wof:placetype":"venue"
},
  "geometry": {"coordinates":[7.592246,44.804131],"type":"Point"}
}