{
  "type": "Feature",
  "properties": {
    "iso:country":"IT",
    "sg:address":"20019 Settimo Milanese",
    "sg:city":"Settimo Milanese",
    "sg:orig_category":"Forniture Per Agricoltura E Zootecnia. Animali Domestici",
    "sg:phone":"+39 02 3351 2009",
    "sg:postcode":"20019",
    "sg:province":"Milano",
    "sg:website":"http://www.texaspets.it",
    "wof:name":"Texas Pets Srl",
    "wof:placetype":"venue"
},
  "geometry": {"coordinates":[9.0602397919,45.4662895203],"type":"Point"}
}