{
  "type": "Feature",
  "properties": {
    "addr:full":"16, Via De Lai 39100 Bolzano Bolzano Bolzano/Bozen 39100",
    "addr:postcode":"39100;39100",
    "addr:street":"Via De Lai",
    "iso:country":"IT",
    "sg:address":"16, Via De Lai 39100 Bolzano",
    "sg:city":"Bolzano",
    "sg:classifiers":[
        {
            "category":"Professional",
            "subcategory":"Business Services",
            "type":"Services"
        }
    ],
    "sg:phone":"+39 0471 317700",
    "sg:postcode":"39100",
    "sg:province":"Bolzano/Bozen",
    "sg:tags":[
        "advice"
    ],
    "wof:name":"Unione Albergatori E Pubblici Esercenti",
    "wof:placetype":"venue"
},
  "geometry": {"coordinates":[11.328239,46.461643],"type":"Point"}
}