{
  "type": "Feature",
  "properties": {
    "addr:full":"20062 Cassano D'adda Milano 20062",
    "addr:postcode":"20062;20062",
    "iso:country":"IT",
    "sg:address":"20062 Cassano D'adda",
    "sg:orig_category":"Arredo Cucina Ed Elettrodomestici. Elettrodomestici",
    "sg:phone":"+39 036 336 6811",
    "sg:postcode":"20062",
    "sg:province":"Milano",
    "wof:name":"Meg Italia S.r.l.",
    "wof:placetype":"venue"
},
  "geometry": {"coordinates":[9.514461,45.526829],"type":"Point"}
}