{
  "type": "Feature",
  "properties": {
    "addr:full":"24060 Villongo Villongo Bergamo 24060",
    "addr:postcode":"24060;24060",
    "iso:country":"IT",
    "sg:address":"24060 Villongo",
    "sg:city":"Villongo",
    "sg:classifiers":[
        {
            "category":"Wholesale",
            "subcategory":"Machinery & Supplies",
            "type":"Manufacturing & Wholesale Goods"
        }
    ],
    "sg:phone":"+39 035 939211",
    "sg:postcode":"24060",
    "sg:province":"Bergamo",
    "sg:tags":[
        "activities",
        "industrial"
    ],
    "sg:website":"http://www.oldrati.it",
    "wof:name":"Oldrati Spa",
    "wof:placetype":"venue"
},
  "geometry": {"coordinates":[9.721203,45.656593],"type":"Point"}
}