{
  "type": "Feature",
  "properties": {
    "addr:full":"13, Via Lago Di Vico 36015 Schio Schio Vicenza 36015",
    "addr:postcode":"36015;36015",
    "addr:street":"Via Lago Di Vico",
    "iso:country":"IT",
    "sg:address":"13, Via Lago Di Vico 36015 Schio",
    "sg:city":"Schio",
    "sg:classifiers":[
        {
            "category":"Professional",
            "subcategory":"Engineering",
            "type":"Services"
        }
    ],
    "sg:phone":"+39 0445 575122",
    "sg:postcode":"36015",
    "sg:province":"Vicenza",
    "sg:tags":[
        "machine",
        "-",
        "mechanical"
    ],
    "wof:name":"Zimac (s.r.l.)",
    "wof:placetype":"venue"
},
  "geometry": {"coordinates":[11.412992,45.720551],"type":"Point"}
}