{
  "type": "Feature",
  "properties": {
    "iso:country":"IT",
    "sg:address":"62029 Tolentino",
    "sg:city":"Tolentino",
    "sg:orig_category":"Fonderie",
    "sg:phone":"+39 0733 960245",
    "sg:postcode":"62029",
    "sg:province":"Macerata",
    "sg:website":"http://www.metfioretti.it",
    "wof:name":"Metallurgica Fioretti Spa",
    "wof:placetype":"venue"
},
  "geometry": {"coordinates":[13.2894363403,43.2241897583],"type":"Point"}
}