{
  "type": "Feature",
  "properties": {
    "addr:full":"55100 Lucca Lucca Lucca 55100",
    "addr:postcode":"55100;55100",
    "iso:country":"IT",
    "sg:address":"55100 Lucca",
    "sg:city":"Lucca",
    "sg:orig_category":"Automobili E Mezzi Di Trasporto",
    "sg:phone":"+39 0583 998911",
    "sg:postcode":"55100",
    "sg:province":"Lucca",
    "sg:website":"http://www.autolucca.com",
    "wof:name":"Autolucca Spa",
    "wof:placetype":"venue"
},
  "geometry": {"coordinates":[10.53643,43.97134],"type":"Point"}
}