{
  "type": "Feature",
  "properties": {
    "iso:country":"IT",
    "sg:address":"Via Salvemini , 3/5/7 56024 Ponte A Egola",
    "sg:city":"Ponte a egola",
    "sg:classifiers":[
        {
            "category":"Home & Garden",
            "subcategory":"Carpets & Floor Coverings",
            "type":"Retail Goods"
        }
    ],
    "sg:phone":"+39 0571 499527",
    "sg:postcode":"56024",
    "sg:province":"Pisa",
    "sg:tags":[
        "animal",
        "skin"
    ],
    "wof:name":"Conceria Tre M Di Mancini Vivaldo & Vivaldo & C.",
    "wof:placetype":"venue"
},
  "geometry": {"coordinates":[10.396585,43.716137],"type":"Point"}
}