{
  "type": "Feature",
  "properties": {
    "addr:full":"Via Valcesano 86/d 61037 Mondolfo Mondolfo Pesaro E Urbino 61037",
    "addr:housenumber":"86 / d",
    "addr:postcode":"61037;61037",
    "addr:street":"Via Valcesano",
    "iso:country":"IT",
    "sg:address":"Via Valcesano 86/d 61037 Mondolfo",
    "sg:city":"Mondolfo",
    "sg:classifiers":[
        {
            "category":"Landmark",
            "subcategory":"Marketplace",
            "type":"Public Place"
        }
    ],
    "sg:phone":"+39 0721 930130",
    "sg:postcode":"61037",
    "sg:province":"Pesaro E Urbino",
    "sg:tags":[
        "industry",
        "part",
        "bought-in",
        "furniture"
    ],
    "sg:website":"www.profilexport.it",
    "wof:name":"Profil Export Srl",
    "wof:placetype":"venue"
},
  "geometry": {"coordinates":[13.122778,43.749405],"type":"Point"}
}