{
  "type": "Feature",
  "properties": {
    "addr:full":"Via G. Marconi 66050 Roccaspinalveti Roccaspinalveti Chieti 66050",
    "addr:postcode":"66050;66050",
    "addr:street":"Via G. Marconi",
    "iso:country":"IT",
    "sg:address":"Via G. Marconi 66050 Roccaspinalveti",
    "sg:city":"Roccaspinalveti",
    "sg:classifiers":[
        {
            "category":"Shopping",
            "subcategory":"Clothing, Apparel, & Fashions",
            "type":"Retail Goods"
        }
    ],
    "sg:phone":"+39 0873 959170",
    "sg:postcode":"66050",
    "sg:province":"Chieti",
    "sg:tags":[
        "clothes"
    ],
    "wof:name":"Camiceria La Mimosa Soc. Coop A.r.l.",
    "wof:placetype":"venue"
},
  "geometry": {"coordinates":[14.167151,42.351791],"type":"Point"}
}