{
  "type": "Feature",
  "properties": {
    "iso:country":"IT",
    "sg:address":"Via Bibbiena 12/14 50142 Firenze",
    "sg:city":"Firenze",
    "sg:classifiers":[
        {
            "category":"Health Services",
            "subcategory":"Medical Lab",
            "type":"Services"
        }
    ],
    "sg:phone":"+39 055 732511",
    "sg:postcode":"50142",
    "sg:province":"Firenze",
    "sg:tags":[
        "yeast"
    ],
    "sg:website":"www.zeusiba.it",
    "wof:name":"Zeus Industria Biologica Alimentare Spa",
    "wof:placetype":"venue"
},
  "geometry": {"coordinates":[11.199541,43.772507],"type":"Point"}
}