{
  "type": "Feature",
  "properties": {
    "addr:full":"Viale Carlo Sigonio 54; Modena; 41100 Modena Modena 41100",
    "addr:housenumber":"54",
    "addr:postcode":"41100;41100",
    "addr:street":"Viale Carlo Sigonio",
    "iso:country":"IT",
    "sg:address":"Viale Carlo Sigonio 54; Modena; 41100",
    "sg:city":"Modena",
    "sg:classifiers":[
        {
            "category":"Banks & Credit Unions",
            "subcategory":"Bank",
            "type":"Services"
        }
    ],
    "sg:phone":"+39 059 222250",
    "sg:postcode":"41100",
    "sg:province":"Modena",
    "wof:name":"Istituto Bancario, San Paolo Di Torino Spa",
    "wof:placetype":"venue"
},
  "geometry": {"coordinates":[10.919061,44.641876],"type":"Point"}
}