{
  "type": "Feature",
  "properties": {
    "iso:country":"IT",
    "sg:address":"61100 Pesaro",
    "sg:city":"Pesaro",
    "sg:orig_category":"Servizi E Lavori Per Arredamento E Industria Del Legno",
    "sg:phone":"+39 0721 430080",
    "sg:postcode":"61100",
    "sg:province":"Pesaro E Urbino",
    "wof:name":"Sforza Prestige Automotive Veneers S.r.l.",
    "wof:placetype":"venue"
},
  "geometry": {"coordinates":[12.876767,43.903019],"type":"Point"}
}