{
  "type": "Feature",
  "properties": {
    "iso:country":"IT",
    "sg:address":"64020 Castellalto",
    "sg:city":"Castellalto",
    "sg:orig_category":"Prodotti E Manufatti In Materie Plastiche. Articoli Per Imballaggio E Confezionamento",
    "sg:phone":"+39 0861 296017",
    "sg:postcode":"64020",
    "sg:province":"Teramo",
    "sg:website":"http://www.tecnopressonline.it",
    "wof:name":"Tecnopress Srl",
    "wof:placetype":"venue"
},
  "geometry": {"coordinates":[13.8456659317,42.6963272095],"type":"Point"}
}