{
  "type": "Feature",
  "properties": {
    "addr:full":"Via Provinciale 332 55040 Vallecchia Lucca 55040",
    "addr:housenumber":"332",
    "addr:postcode":"55040;55040",
    "addr:street":"Via Provinciale",
    "iso:country":"IT",
    "sg:address":"Via Provinciale 332 55040 Vallecchia",
    "sg:classifiers":[
        {
            "category":"Wholesale",
            "subcategory":"Vending Machines",
            "type":"Manufacturing & Wholesale Goods"
        }
    ],
    "sg:phone":"+39 0584 757075",
    "sg:postcode":"55040",
    "sg:province":"Lucca",
    "sg:tags":[
        "stone",
        "working",
        "machines",
        "others"
    ],
    "sg:website":"www.giorginimaggi.it",
    "wof:name":"Societa' Giorgini Maggi Srl",
    "wof:placetype":"venue"
},
  "geometry": {"coordinates":[10.507994,43.843014],"type":"Point"}
}