{
  "type": "Feature",
  "properties": {
    "iso:country":"IT",
    "sg:address":"91026 Mazara Del Vallo",
    "sg:city":"Mazara del Vallo",
    "sg:orig_category":"Pesci Freschi E Surgelati - Lavorazione E Commercio",
    "sg:phone":"+39 0923 944133",
    "sg:postcode":"91026",
    "sg:province":"Trapani",
    "wof:name":"Medipesca Di A. Misuraca & C. Sas",
    "wof:placetype":"venue"
},
  "geometry": {"coordinates":[12.6445865631,37.7389526367],"type":"Point"}
}