{
  "type": "Feature",
  "properties": {
    "iso:country":"IT",
    "sg:address":"28804 San Bernardino Verbano",
    "sg:city":"San Bernardino Verbano",
    "sg:orig_category":"Termotecnica E Riscaldamento, Apparecchiature E Servizi",
    "sg:phone":"+39 0323 552175",
    "sg:postcode":"28804",
    "sg:province":"Verbano-Cusio-Ossola",
    "wof:name":"Radiatori Tubor Spa",
    "wof:placetype":"venue"
},
  "geometry": {"coordinates":[8.446286,45.997555],"type":"Point"}
}