{
  "type": "Feature",
  "properties": {
    "iso:country":"IT",
    "sg:address":"Via Uccellino, 75/77 44028 Poggio Renatico",
    "sg:city":"Poggio Renatico",
    "sg:orig_category":"Drying Plants For The Food Industry",
    "sg:phone":"+39 0532 829532",
    "sg:postcode":"44028",
    "sg:province":"Ferrara",
    "sg:website":"www.cgm-it.com",
    "wof:name":"Nuova C.g.m. Srl",
    "wof:placetype":"venue"
},
  "geometry": {"coordinates":[11.538477,44.777657],"type":"Point"}
}