{
  "type": "Feature",
  "properties": {
    "iso:country":"IT",
    "sg:address":"4, V. G. Galilei 20040 Burago Molgora",
    "sg:classifiers":[
        {
            "category":"Sports & Exercise",
            "subcategory":"Playing Field",
            "type":"Entertainment"
        }
    ],
    "sg:phone":"+39 390 396 0861",
    "sg:postcode":"20040",
    "sg:province":"Milano",
    "sg:tags":[
        "game"
    ],
    "sg:website":"http://www.bburago.com",
    "wof:name":"Bburago Spa",
    "wof:placetype":"venue"
},
  "geometry": {"coordinates":[9.188141,45.463688],"type":"Point"}
}