{
  "type": "Feature",
  "properties": {
    "addr:full":"35010 Loreggia Loreggia Padova 35010",
    "addr:postcode":"35010;35010",
    "iso:country":"IT",
    "sg:address":"35010 Loreggia",
    "sg:city":"Loreggia",
    "sg:classifiers":[
        {
            "category":"Health Services",
            "subcategory":"Health Practitioner",
            "type":"Services"
        }
    ],
    "sg:phone":"+39 049 930 0307",
    "sg:postcode":"35010",
    "sg:province":"Padova",
    "sg:tags":[
        "medici"
    ],
    "wof:name":"Armato Nino",
    "wof:placetype":"venue"
},
  "geometry": {"coordinates":[11.874359,45.409218],"type":"Point"}
}