{
  "type": "Feature",
  "properties": {
    "iso:country":"IT",
    "sg:address":"21100 Varese",
    "sg:city":"Varese",
    "sg:orig_category":"Scuole E Servizi Scolastici. Ricerca, Selezione E Formazione Del Personale",
    "sg:phone":"+39 800 674 848",
    "sg:postcode":"21100",
    "sg:province":"Varese",
    "wof:name":"Cepu Srl",
    "wof:placetype":"venue"
},
  "geometry": {"coordinates":[8.825439,45.817265],"type":"Point"}
}