{
  "type": "Feature",
  "properties": {
    "addr:full":"20040 Briosco Briosco Milano 20040",
    "addr:postcode":"20040;20040",
    "iso:country":"IT",
    "sg:address":"20040 Briosco",
    "sg:city":"Briosco",
    "sg:orig_category":"Prodotti Finiti Stampati. Forniture E Materiali Per Imballaggio E Confezionamento. Forniture Per Attivita' Commerciali Ed Artigianali",
    "sg:phone":"+39 036 295230",
    "sg:postcode":"20040",
    "sg:province":"Milano",
    "wof:name":"Carta Stampa S.r.l.",
    "wof:placetype":"venue"
},
  "geometry": {"coordinates":[9.2397108078,45.7091560364],"type":"Point"}
}