{
  "type": "Feature",
  "properties": {
    "iso:country":"IT",
    "sg:address":"20125 Milano",
    "sg:city":"Milano",
    "sg:orig_category":"Servizi Editoriali. Professionisti - Studi E Servizi Ed Associazioni Di Interesse Aziendale",
    "sg:phone":"+39 02 668 6206",
    "sg:postcode":"20125",
    "sg:province":"Milano",
    "wof:name":"Ruffelli Renzo",
    "wof:placetype":"venue"
},
  "geometry": {"coordinates":[9.204624,45.501907],"type":"Point"}
}