{
  "type": "Feature",
  "properties": {
    "addr:full":"Vle Antonio Gallus 79 09047 Selargius Selargius Cagliari 09047",
    "addr:housenumber":"79",
    "addr:postcode":"09047;09047",
    "addr:street":"Vle Antonio Gallus",
    "iso:country":"IT",
    "sg:address":"Vle Antonio Gallus 79 09047 Selargius",
    "sg:city":"Selargius",
    "sg:classifiers":[
        {
            "category":"Food & Beverages",
            "subcategory":"Liquor & Beverages",
            "type":"Retail Goods"
        }
    ],
    "sg:phone":"+39 070 842815",
    "sg:postcode":"09047",
    "sg:province":"Cagliari",
    "sg:tags":[
        "wine",
        "italian"
    ],
    "sg:website":"www.meloni-vini.com",
    "wof:name":"Sarda Acque Minerali Sam Spa",
    "wof:placetype":"venue"
},
  "geometry": {"coordinates":[9.169991,39.253876],"type":"Point"}
}