{
  "type": "Feature",
  "properties": {
    "addr:full":"4, Via Diaz Armando 34121 Trieste Trieste Trieste 34121",
    "addr:postcode":"34121;34121",
    "addr:street":"Via Diaz Armando",
    "iso:country":"IT",
    "sg:address":"4, Via Diaz Armando 34121 Trieste",
    "sg:city":"Trieste",
    "sg:classifiers":[
        {
            "category":"Manufacturing",
            "subcategory":"Metals",
            "type":"Manufacturing & Wholesale Goods"
        }
    ],
    "sg:phone":"+39 39040309066",
    "sg:postcode":"34121",
    "sg:province":"Trieste",
    "sg:tags":[
        "metallurgy",
        "metalworking"
    ],
    "wof:name":"Veca Trading (s.r.l.)",
    "wof:placetype":"venue"
},
  "geometry": {"coordinates":[13.7784070969,45.653629303],"type":"Point"}
}