{
  "type": "Feature",
  "properties": {
    "iso:country":"IT",
    "sg:address":"10093 Collegno",
    "sg:city":"Collegno",
    "sg:orig_category":"Abbigliamento Sportivo, Jeans E Casuals - Vendita Al Dettaglio",
    "sg:phone":"+39 011 411 1218",
    "sg:postcode":"10093",
    "sg:province":"Torino",
    "wof:name":"Acquatic Dolphins Snc Di Bevilacqua F. E C.",
    "wof:placetype":"venue"
},
  "geometry": {"coordinates":[7.610179,45.074329],"type":"Point"}
}