{
  "type": "Feature",
  "properties": {
    "iso:country":"IT",
    "sg:address":"2, Via Velinia 02100 Rieti",
    "sg:city":"Rieti",
    "sg:classifiers":[
        {
            "category":"Food & Beverages",
            "subcategory":"Dairy",
            "type":"Retail Goods"
        }
    ],
    "sg:phone":"+39 0746 200249",
    "sg:postcode":"02100",
    "sg:province":"Rieti",
    "sg:tags":[
        "product"
    ],
    "wof:name":"C.la.r. Centrale Latte Rieti Srl",
    "wof:placetype":"venue"
},
  "geometry": {"coordinates":[12.82219,42.398861],"type":"Point"}
}