{
  "type": "Feature",
  "properties": {
    "addr:full":"74014 Laterza Laterza Taranto 74014",
    "addr:postcode":"74014;74014",
    "iso:country":"IT",
    "sg:address":"74014 Laterza",
    "sg:city":"Laterza",
    "sg:orig_category":"Pubblica Amministrazione",
    "sg:phone":"+39 099 829 7911",
    "sg:postcode":"74014",
    "sg:province":"Taranto",
    "wof:name":"Municipio Di Laterza",
    "wof:placetype":"venue"
},
  "geometry": {"coordinates":[16.7942409515,40.6617088318],"type":"Point"}
}