{
  "type": "Feature",
  "properties": {
    "iso:country":"IT",
    "sg:address":"20067 Paullo",
    "sg:city":"Paullo",
    "sg:classifiers":[
        {
            "category":"Health Services",
            "subcategory":"Health Practitioner",
            "type":"Services"
        }
    ],
    "sg:phone":"+39 02 9063 1900",
    "sg:postcode":"20067",
    "sg:province":"Milano",
    "sg:tags":[
        "medici"
    ],
    "wof:name":"Monaja Roberto",
    "wof:placetype":"venue"
},
  "geometry": {"coordinates":[9.1843,45.466667],"type":"Point"}
}