{
  "type": "Feature",
  "properties": {
    "iso:country":"IT",
    "sg:address":"Via Broletto 20, 20121 Milan, Mi",
    "sg:classifiers":[
        {
            "category":"Banks & Credit Unions",
            "subcategory":"Bank",
            "type":"Services"
        }
    ],
    "sg:phone":"+39 0288701",
    "sg:postcode":"20121",
    "sg:province":"Milano",
    "wof:name":"Intesabci Mediocredito Spa",
    "wof:placetype":"venue"
},
  "geometry": {"coordinates":[9.186035,45.466679],"type":"Point"}
}