{
  "type": "Feature",
  "properties": {
    "addr:full":"00055 Ladispoli Ladispoli Roma 00055",
    "addr:postcode":"00055;roma 00055",
    "iso:country":"IT",
    "sg:address":"00055 Ladispoli",
    "sg:city":"Ladispoli",
    "sg:orig_category":"Forniture Per Agricoltura E Zootecnia",
    "sg:phone":"+39 06 991 0230",
    "sg:postcode":"00055",
    "sg:province":"Roma",
    "wof:name":"Agrisem Di Aringoli Piero & C. Snc",
    "wof:placetype":"venue"
},
  "geometry": {"coordinates":[12.4985198975,41.9080352783],"type":"Point"}
}