{
  "type": "Feature",
  "properties": {
    "iso:country":"IT",
    "sg:address":"19/a, Via S. Pio V 40131 Bologna",
    "sg:city":"Bologna",
    "sg:classifiers":[
        {
            "category":"Manufacturing",
            "subcategory":"Printing",
            "type":"Manufacturing & Wholesale Goods"
        }
    ],
    "sg:phone":"+39 39051550487",
    "sg:postcode":"40131",
    "sg:province":"Bologna",
    "sg:tags":[
        "publishing"
    ],
    "wof:name":"Cabicar (s.r.l.)",
    "wof:placetype":"venue"
},
  "geometry": {"coordinates":[11.6568784714,44.9779129028],"type":"Point"}
}