{
  "type": "Feature",
  "properties": {
    "addr:full":"169, Via Granarolo 48018 Faenza Faenza Ravenna 48018",
    "addr:housenumber":"169",
    "addr:postcode":"48018;48018",
    "addr:street":"Via Granarolo",
    "iso:country":"IT",
    "sg:address":"169, Via Granarolo 48018 Faenza",
    "sg:city":"Faenza",
    "sg:classifiers":[
        {
            "category":"Manufacturing",
            "subcategory":"Rubber & Plastics",
            "type":"Manufacturing & Wholesale Goods"
        }
    ],
    "sg:phone":"+39 39054646318",
    "sg:postcode":"48018",
    "sg:province":"Ravenna",
    "wof:name":"Centerplast S.r.l.",
    "wof:placetype":"venue"
},
  "geometry": {"coordinates":[11.8999929428,44.3140945435],"type":"Point"}
}