{
  "type": "Feature",
  "properties": {
    "iso:country":"IT",
    "sg:address":"28, Via Garibaldi 22070 Montano Lucino",
    "sg:city":"Lucino",
    "sg:classifiers":[
        {
            "category":"Shopping",
            "subcategory":"Crafts & Fabrics",
            "type":"Retail Goods"
        }
    ],
    "sg:phone":"+39 39031470180",
    "sg:postcode":"22070",
    "sg:province":"Como",
    "wof:name":"Terragni Fratelli (s.r.l.)",
    "wof:placetype":"venue"
},
  "geometry": {"coordinates":[9.0207052231,45.7951698303],"type":"Point"}
}