{
  "type": "Feature",
  "properties": {
    "addr:full":"Via Sacco E Vanzetti, 103/105 20099 Sesto San Giovanni Sesto San Giovanni Milano 20099",
    "addr:housenumber":"103 / 105",
    "addr:postcode":"20099;20099",
    "addr:street":"Via Sacco E Vanzetti",
    "iso:country":"IT",
    "sg:address":"Via Sacco E Vanzetti, 103/105 20099 Sesto San Giovanni",
    "sg:city":"Sesto San Giovanni",
    "sg:classifiers":[
        {
            "category":"Communications",
            "subcategory":"Film & Video Production",
            "type":"Services"
        }
    ],
    "sg:phone":"+39 02 240 5752",
    "sg:postcode":"20099",
    "sg:province":"Milano",
    "sg:tags":[
        "camera",
        "surveillance"
    ],
    "sg:website":"www.avil.it",
    "wof:name":"Avil Srl",
    "wof:placetype":"venue"
},
  "geometry": {"coordinates":[9.256365,45.529873],"type":"Point"}
}