{
  "type": "Feature",
  "properties": {
    "addr:full":"20047 Brugherio Brugherio Milano 20047",
    "addr:postcode":"20047;20047",
    "iso:country":"IT",
    "sg:address":"20047 Brugherio",
    "sg:city":"Brugherio",
    "sg:classifiers":[
        {
            "category":"Parking",
            "subcategory":"Lot",
            "type":"Transportation"
        }
    ],
    "sg:phone":"+39 039 287 3215",
    "sg:postcode":"20047",
    "sg:province":"Milano",
    "sg:tags":[
        "good",
        "shipment",
        "transport"
    ],
    "wof:name":"Eurotrans Srl",
    "wof:placetype":"venue"
},
  "geometry": {"coordinates":[9.276350975,45.5573234558],"type":"Point"}
}