{
  "type": "Feature",
  "properties": {
    "iso:country":"IT",
    "sg:address":"Via Vittorio Emanuele Orlando 7 95037 San Giovanni La Punta",
    "sg:city":"San Giovanni la Punta",
    "sg:classifiers":[
        {
            "category":"Professional",
            "subcategory":"Computer Services",
            "type":"Services"
        }
    ],
    "sg:phone":"+39 095 741 7411",
    "sg:postcode":"95037",
    "sg:province":"Catania",
    "sg:tags":[
        "telecommunication"
    ],
    "sg:website":"www.antech.it",
    "wof:name":"Antech Spa",
    "wof:placetype":"venue"
},
  "geometry": {"coordinates":[15.099888,37.573498],"type":"Point"}
}