{
  "type": "Feature",
  "properties": {
    "iso:country":"IT",
    "sg:address":"74020 Lizzano",
    "sg:city":"Lizzano",
    "sg:orig_category":"Materiali Edili",
    "sg:phone":"+39 099 955 8245",
    "sg:postcode":"74020",
    "sg:province":"Taranto",
    "wof:name":"Lapesa Saverio",
    "wof:placetype":"venue"
},
  "geometry": {"coordinates":[17.448444,40.392036],"type":"Point"}
}