{
  "type": "Feature",
  "properties": {
    "addr:full":"10152 Torino Torino Torino 10152",
    "addr:postcode":"10152;10152",
    "iso:country":"IT",
    "sg:address":"10152 Torino",
    "sg:city":"Torino",
    "sg:orig_category":"Macchine, Impianti E Forniture Per Industria Grafica, Cartaria E Cartotecnica. Apparecchiature Ed Attrezzature Meccaniche. Automazione E Macchine Per Ufficio",
    "sg:phone":"+39 011 854101",
    "sg:postcode":"10152",
    "sg:province":"Torino",
    "wof:name":"Nuova Etika Piemonte S.n.c.",
    "wof:placetype":"venue"
},
  "geometry": {"coordinates":[7.693638,45.083702],"type":"Point"}
}