{
  "type": "Feature",
  "properties": {
    "iso:country":"IT",
    "sg:address":"36010 Zan\u00e8",
    "sg:orig_category":"Utensili Meccanici E Materiali. Elettrotecnica Industriale, Prodotti E Apparecchiature",
    "sg:phone":"+39 0445 315198",
    "sg:postcode":"36010",
    "sg:province":"Vicenza",
    "wof:name":"Illesi Piero - Elettromeccanica",
    "wof:placetype":"venue"
},
  "geometry": {"coordinates":[11.446404,45.720596],"type":"Point"}
}