{
  "type": "Feature",
  "properties": {
    "iso:country":"IT",
    "sg:address":"51100 Pistoia",
    "sg:city":"Pistoia",
    "sg:orig_category":"Agricoltura - Attrezzi, Prodotti E Forniture",
    "sg:phone":"+39 0573 992211",
    "sg:postcode":"51100",
    "sg:province":"Pistoia",
    "wof:name":"Consorzio Agrario Provinciale Pistoia",
    "wof:placetype":"venue"
},
  "geometry": {"coordinates":[10.909934,43.924294],"type":"Point"}
}