{
  "type": "Feature",
  "properties": {
    "iso:country":"IT",
    "sg:address":"1, Strada S.severa Tolfa 00058 Santa Marinella",
    "sg:city":"Santa Marinella",
    "sg:classifiers":[
        {
            "category":"Communications",
            "subcategory":"Television Station",
            "type":"Services"
        }
    ],
    "sg:phone":"+39 0766 570008",
    "sg:postcode":"00058",
    "sg:province":"Roma",
    "sg:tags":[
        "equipment",
        "optical",
        "instrument"
    ],
    "wof:name":"Cir (s.r.l.)",
    "wof:placetype":"venue"
},
  "geometry": {"coordinates":[12.482325,41.895466],"type":"Point"}
}