{
  "type": "Feature",
  "properties": {
    "iso:country":"IT",
    "sg:address":"38, Via Cellini Benvenuto 59013 Montemurlo",
    "sg:city":"Montemurlo",
    "sg:classifiers":[
        {
            "category":"Shopping",
            "subcategory":"Crafts & Fabrics",
            "type":"Retail Goods"
        }
    ],
    "sg:phone":"+39 0574 652418",
    "sg:postcode":"59013",
    "sg:province":"Prato",
    "wof:name":"Picchi Libertario & C. Snc",
    "wof:placetype":"venue"
},
  "geometry": {"coordinates":[11.058678627,43.9110412598],"type":"Point"}
}