{
  "type": "Feature",
  "properties": {
    "iso:country":"IT",
    "sg:address":"96016 Lentini",
    "sg:city":"Lentini",
    "sg:orig_category":"Marmo, Pietre Ed Affini",
    "sg:phone":"+39 095 783 4537",
    "sg:postcode":"96016",
    "sg:province":"Siracusa",
    "wof:name":"Coral Di Bruno Lucia",
    "wof:placetype":"venue"
},
  "geometry": {"coordinates":[14.996887,37.299431],"type":"Point"}
}