{
  "type": "Feature",
  "properties": {
    "addr:full":"20095 Cusano Milanino Cusano Milanino Milano 20095",
    "addr:postcode":"20095;20095",
    "iso:country":"IT",
    "sg:address":"20095 Cusano Milanino",
    "sg:city":"Cusano Milanino",
    "sg:orig_category":"Pubblica Amministrazione",
    "sg:phone":"+39 02 613 2575",
    "sg:postcode":"20095",
    "sg:province":"Milano",
    "wof:name":"Poste Italiane S.p.a.",
    "wof:placetype":"venue"
},
  "geometry": {"coordinates":[9.1909179688,45.5489425659],"type":"Point"}
}