{
  "type": "Feature",
  "properties": {
    "iso:country":"IT",
    "sg:address":"Piazza Garibaldi, 38; Noci; 70015",
    "sg:city":"Noci",
    "sg:classifiers":[
        {
            "category":"Banks & Credit Unions",
            "subcategory":"Bank",
            "type":"Services"
        }
    ],
    "sg:phone":"+39 080 738966",
    "sg:postcode":"70015",
    "sg:province":"Bari",
    "wof:name":"Banca Popolare Della Murgia",
    "wof:placetype":"venue"
},
  "geometry": {"coordinates":[17.121481,40.796017],"type":"Point"}
}