{
  "type": "Feature",
  "properties": {
    "addr:full":"Localita' Casigliano Campagna 05021 Acquasparta Acquasparta Terni 05021",
    "addr:postcode":"05021;05021",
    "addr:street":"Localita ' Casigliano Campagna",
    "iso:country":"IT",
    "sg:address":"Localita' Casigliano Campagna 05021 Acquasparta",
    "sg:city":"Acquasparta",
    "sg:classifiers":[
        {
            "category":"Autos & Motor Vehicles",
            "subcategory":"Automobile Sales",
            "type":"Retail Goods"
        }
    ],
    "sg:phone":"+39 0744 941114",
    "sg:postcode":"05021",
    "sg:province":"Terni",
    "sg:tags":[
        "motor-cars"
    ],
    "wof:name":"Jolly Bus S.r.l.",
    "wof:placetype":"venue"
},
  "geometry": {"coordinates":[12.535528183,42.6787948608],"type":"Point"}
}