{
  "type": "Feature",
  "properties": {
    "addr:full":"42, Strada Marchionale 46046 Medole Medole Mantova 46046",
    "addr:postcode":"46046;46046",
    "addr:street":"Strada Marchionale",
    "iso:country":"IT",
    "sg:address":"42, Strada Marchionale 46046 Medole",
    "sg:city":"Medole",
    "sg:classifiers":[
        {
            "category":"Manufacturing",
            "subcategory":"Metals",
            "type":"Manufacturing & Wholesale Goods"
        }
    ],
    "sg:phone":"+39 0376 868207",
    "sg:postcode":"46046",
    "sg:province":"Mantova",
    "sg:tags":[
        "processing"
    ],
    "wof:name":"C.v. S.r.l.",
    "wof:placetype":"venue"
},
  "geometry": {"coordinates":[10.5168466568,45.3223342896],"type":"Point"}
}