{
  "type": "Feature",
  "properties": {
    "iso:country":"IT",
    "sg:address":"37010 Brenzone",
    "sg:city":"Brenzone",
    "sg:orig_category":"Scuole E Servizi Scolastici. Servizi Per Lo Sport E Il Tempo Libero",
    "sg:phone":"+39 045 742 0762",
    "sg:postcode":"37010",
    "sg:province":"Verona",
    "wof:name":"Compagnia Delle Derive",
    "wof:placetype":"venue"
},
  "geometry": {"coordinates":[10.768029,45.711136],"type":"Point"}
}