{
  "type": "Feature",
  "properties": {
    "addr:full":"Via G. Grassilli 9 40012 Calderara Di Reno Calderara di Reno Bologna 40012",
    "addr:housenumber":"9",
    "addr:postcode":"40012;40012",
    "addr:street":"Via G. Grassilli",
    "iso:country":"IT",
    "sg:address":"Via G. Grassilli 9 40012 Calderara Di Reno",
    "sg:city":"Calderara di Reno",
    "sg:classifiers":[
        {
            "category":"Wholesale",
            "subcategory":"Machinery & Supplies",
            "type":"Manufacturing & Wholesale Goods"
        }
    ],
    "sg:phone":"+39 051 727309",
    "sg:postcode":"40012",
    "sg:province":"Bologna",
    "sg:tags":[
        "machine",
        "packaging",
        "industry",
        "special"
    ],
    "sg:website":"www.cdvnet.it/d&v",
    "wof:name":"Dalla & Vittorelli Srl",
    "wof:placetype":"venue"
},
  "geometry": {"coordinates":[11.268602,44.539864],"type":"Point"}
}