{
  "type": "Feature",
  "properties": {
    "addr:full":"74100 Taranto Taranto Taranto 74100",
    "addr:postcode":"74100;74100",
    "iso:country":"IT",
    "sg:address":"74100 Taranto",
    "sg:city":"Taranto",
    "sg:orig_category":"Ospedali E Servizi Sanitari. Servizi Ausiliari Di Analisi, Controllo E Ricerca",
    "sg:phone":"+39 099 374045",
    "sg:postcode":"74100",
    "sg:province":"Taranto",
    "wof:name":"Laboratori Chimici Stante",
    "wof:placetype":"venue"
},
  "geometry": {"coordinates":[17.251104,40.458984],"type":"Point"}
}