{
  "type": "Feature",
  "properties": {
    "iso:country":"IT",
    "sg:address":"53045 Acquaviva",
    "sg:city":"Acquaviva",
    "sg:orig_category":"Prodotti Alimentari",
    "sg:phone":"+39 0578 768211",
    "sg:postcode":"53045",
    "sg:province":"Siena",
    "wof:name":"Belloni Stefano",
    "wof:placetype":"venue"
},
  "geometry": {"coordinates":[11.8653144836,43.1150169373],"type":"Point"}
}