{
  "type": "Feature",
  "properties": {
    "iso:country":"IT",
    "sg:address":"84013 Cava De' Tirreni",
    "sg:orig_category":"Cabine Elettriche Di Trasformazione E Comando",
    "sg:phone":"+39 089 444962",
    "sg:postcode":"84013",
    "sg:province":"Salerno",
    "wof:name":"N.s.impianti Snc Di Noviello Antonio & C. Spa",
    "wof:placetype":"venue"
},
  "geometry": {"coordinates":[14.70528,40.716198],"type":"Point"}
}