{
  "type": "Feature",
  "properties": {
    "addr:full":"10123 Torino Torino Torino 10123",
    "addr:postcode":"10123;10123",
    "iso:country":"IT",
    "sg:address":"10123 Torino",
    "sg:city":"Torino",
    "sg:orig_category":"Elettronica Professionale E Di Consumo. Musica",
    "sg:phone":"+39 011 817 3607",
    "sg:postcode":"10123",
    "sg:province":"Torino",
    "wof:name":"Reale Annibale",
    "wof:placetype":"venue"
},
  "geometry": {"coordinates":[7.684424,45.068401],"type":"Point"}
}