{
  "type": "Feature",
  "properties": {
    "iso:country":"IT",
    "sg:address":"00173 Roma",
    "sg:city":"Roma",
    "sg:orig_category":"Prodotti Alimentari",
    "sg:phone":"+39 06 723 3486",
    "sg:postcode":"00173",
    "sg:province":"Roma",
    "wof:name":"Centrali Latte Parmalat (s.p.a.)",
    "wof:placetype":"venue"
},
  "geometry": {"coordinates":[12.6108560562,41.8464813232],"type":"Point"}
}