{
  "type": "Feature",
  "properties": {
    "iso:country":"IT",
    "sg:address":"20159 Milano",
    "sg:city":"Milano",
    "sg:orig_category":"Musica. Shopping",
    "sg:phone":"+39 02 606779",
    "sg:postcode":"20159",
    "sg:province":"Milano",
    "wof:name":"Burdock Di Canulli Flavio",
    "wof:placetype":"venue"
},
  "geometry": {"coordinates":[9.1840190887,45.4961891174],"type":"Point"}
}