{
  "type": "Feature",
  "properties": {
    "addr:full":"20090 Cesano Boscone Cesano Boscone Milano 20090",
    "addr:postcode":"20090;20090",
    "iso:country":"IT",
    "sg:address":"20090 Cesano Boscone",
    "sg:city":"Cesano Boscone",
    "sg:orig_category":"Musica",
    "sg:phone":"+39 02 4586 2060",
    "sg:postcode":"20090",
    "sg:province":"Milano",
    "wof:name":"M.s.m. Master Service Multimedia",
    "wof:placetype":"venue"
},
  "geometry": {"coordinates":[9.0862665176,45.4465751648],"type":"Point"}
}