{
  "type": "Feature",
  "properties": {
    "iso:country":"IT",
    "sg:address":"38077 Ponte Arche",
    "sg:orig_category":"Servizi E Lavori Per Abbigliamento E Pelletterie",
    "sg:phone":"+39 0465 700072",
    "sg:province":"TN",
    "wof:name":"Orange S.a.s.",
    "wof:placetype":"venue"
},
  "geometry": {"coordinates":[-89.474503,36.329498],"type":"Point"}
}