{
  "type": "Feature",
  "properties": {
    "iso:country":"IT",
    "sg:address":"Via Santuario 11 15046 San Salvatore Monferrato",
    "sg:city":"San Salvatore Monferrato",
    "sg:classifiers":[
        {
            "category":"Arena",
            "subcategory":"Bull Ring",
            "type":"Entertainment"
        }
    ],
    "sg:phone":"+39 0131 237015",
    "sg:postcode":"15046",
    "sg:province":"Alessandria",
    "sg:tags":[
        "brooch"
    ],
    "sg:website":"www.dierregioielli.it",
    "wof:name":"Dierre Srl",
    "wof:placetype":"venue"
},
  "geometry": {"coordinates":[8.581863,44.995323],"type":"Point"}
}