{
  "type": "Feature",
  "properties": {
    "addr:full":"32013 Longarone Longarone Belluno 32013",
    "addr:postcode":"32013;32013",
    "iso:country":"IT",
    "sg:address":"32013 Longarone",
    "sg:city":"Longarone",
    "sg:orig_category":"Pubblica Amministrazione",
    "sg:phone":"+39 0437 770416",
    "sg:postcode":"32013",
    "sg:province":"Belluno",
    "wof:name":"Comunita' Montana Cadore Longaronese E Zoldano",
    "wof:placetype":"venue"
},
  "geometry": {"coordinates":[12.3005561829,46.271232605],"type":"Point"}
}