{
  "type": "Feature",
  "properties": {
    "iso:country":"IT",
    "sg:address":"50022 Greve In Chianti",
    "sg:city":"Greve in Chianti",
    "sg:orig_category":"Carpenterie Legno",
    "sg:phone":"+39 055 852002",
    "sg:postcode":"50022",
    "sg:province":"Firenze",
    "wof:name":"Ferruzzi Mario E Carlo Snc",
    "wof:placetype":"venue"
},
  "geometry": {"coordinates":[11.316304,43.543751],"type":"Point"}
}