{
  "type": "Feature",
  "properties": {
    "iso:country":"IT",
    "sg:address":"37038 Soave",
    "sg:city":"Soave",
    "sg:orig_category":"Carta, Cartone E Prodotti Primari",
    "sg:phone":"+39 045 761 4311",
    "sg:postcode":"37038",
    "sg:province":"Verona",
    "wof:name":"Eredi Santarosa Bruno Di Zenari Tiziana & C.",
    "wof:placetype":"venue"
},
  "geometry": {"coordinates":[10.977963,45.413712],"type":"Point"}
}