{
  "type": "Feature",
  "properties": {
    "addr:full":"73100 Lecce Lecce Lecce 73100",
    "addr:postcode":"73100;73100",
    "iso:country":"IT",
    "sg:address":"73100 Lecce",
    "sg:city":"Lecce",
    "sg:orig_category":"Forniture Per Edilizia E Lavori Pubblici",
    "sg:phone":"+39 0832 348682",
    "sg:postcode":"73100",
    "sg:province":"Lecce",
    "wof:name":"Ettore Maglio Srl",
    "wof:placetype":"venue"
},
  "geometry": {"coordinates":[18.1808242798,40.3383979797],"type":"Point"}
}