{
  "type": "Feature",
  "properties": {
    "addr:full":"41013 Castelfranco Emilia Castelfranco Emilia Modena 41013",
    "addr:postcode":"41013;41013",
    "iso:country":"IT",
    "sg:address":"41013 Castelfranco Emilia",
    "sg:city":"Castelfranco Emilia",
    "sg:orig_category":"Prodotti Di Base E Forniture Per Industria Alimentare E Bevande. Forniture E Materiali Per Imballaggio E Confezionamento",
    "sg:phone":"+39 059 925918",
    "sg:postcode":"41013",
    "sg:province":"Modena",
    "wof:name":"Borghi Progetto Enologia Srl",
    "wof:placetype":"venue"
},
  "geometry": {"coordinates":[10.9707860947,44.6378479004],"type":"Point"}
}