{
  "type": "Feature",
  "properties": {
    "addr:full":"33070 Caneva Caneva Pordenone 33070",
    "addr:postcode":"33070;33070",
    "iso:country":"IT",
    "sg:address":"33070 Caneva",
    "sg:city":"Caneva",
    "sg:orig_category":"Lucidatura, Laccatura E Verniciatura Mobili",
    "sg:phone":"+39 0434 79144",
    "sg:postcode":"33070",
    "sg:province":"Pordenone",
    "wof:name":"De Nadai Snc Di De Nadai Mario & C.",
    "wof:placetype":"venue"
},
  "geometry": {"coordinates":[12.50178,46.030571],"type":"Point"}
}