{
  "type": "Feature",
  "properties": {
    "iso:country":"IT",
    "sg:address":"00187 Roma",
    "sg:city":"Roma",
    "sg:orig_category":"Case Editrici",
    "sg:phone":"+39 06 679 3268",
    "sg:postcode":"00187",
    "sg:province":"Roma",
    "sg:website":"http://www.stamperiareale.it",
    "wof:name":"Stamperia Reale Di Roma Srl",
    "wof:placetype":"venue"
},
  "geometry": {"coordinates":[12.485292,41.903042],"type":"Point"}
}