{
  "type": "Feature",
  "properties": {
    "iso:country":"IT",
    "sg:address":"18, Via Cortese E. 80077 Ischia",
    "sg:city":"Ischia",
    "sg:classifiers":[
        {
            "category":"Travel",
            "subcategory":"Travel Agent",
            "type":"Entertainment"
        }
    ],
    "sg:phone":"+39 39081985644",
    "sg:postcode":"80077",
    "sg:province":"Napoli",
    "sg:tags":[
        "business"
    ],
    "wof:name":"Hotel Regina Palace Srl",
    "wof:placetype":"venue"
},
  "geometry": {"coordinates":[13.949284,40.738621],"type":"Point"}
}