{
  "type": "Feature",
  "properties": {
    "iso:country":"IT",
    "sg:address":"80078 Pozzuoli",
    "sg:city":"Pozzuoli",
    "sg:orig_category":"Barche, Canotti Pneumatici E Motoscafi - Vendita Al Dettaglio",
    "sg:phone":"+39 081 303 1258",
    "sg:postcode":"80078",
    "sg:province":"Napoli",
    "wof:name":"Cataboat Snc",
    "wof:placetype":"venue"
},
  "geometry": {"coordinates":[14.120493,40.82687],"type":"Point"}
}