{
  "type": "Feature",
  "properties": {
    "iso:country":"IT",
    "sg:address":"34147 Trieste",
    "sg:city":"Trieste",
    "sg:orig_category":"Lavorazioni Meccaniche E Servizi. Riparazione Dei Mezzi Di Trasporto",
    "sg:phone":"+39 040 281281",
    "sg:postcode":"34147",
    "sg:province":"Trieste",
    "wof:name":"So.co.mar (s.r.l.)",
    "wof:placetype":"venue"
},
  "geometry": {"coordinates":[13.820675,45.613899],"type":"Point"}
}