{
  "type": "Feature",
  "properties": {
    "iso:country":"IT",
    "sg:address":"190, Via B. Sella 13867 Pray",
    "sg:city":"Pray",
    "sg:classifiers":[
        {
            "category":"Shopping",
            "subcategory":"Crafts & Fabrics",
            "type":"Retail Goods"
        }
    ],
    "sg:phone":"+39 39015767464",
    "sg:postcode":"13867",
    "sg:province":"Biella",
    "wof:name":"Eurofil Di Zanello & C. (s.n.c.)",
    "wof:placetype":"venue"
},
  "geometry": {"coordinates":[8.0582695007,45.5628356934],"type":"Point"}
}