{
  "type": "Feature",
  "properties": {
    "iso:country":"IT",
    "sg:address":"87029 Scalea",
    "sg:city":"Scalea",
    "sg:orig_category":"Bestiame - Allevamento E Commercio",
    "sg:phone":"+39 328 633 0599",
    "sg:postcode":"87029",
    "sg:province":"Cosenza",
    "wof:name":"Riccetti Minuccio",
    "wof:placetype":"venue"
},
  "geometry": {"coordinates":[15.799677,39.804295],"type":"Point"}
}