{
  "type": "Feature",
  "properties": {
    "iso:country":"IT",
    "sg:address":"Viale Della Repbblica 28; Paderno Dugnano; 20037",
    "sg:city":"Paderno Dugnano",
    "sg:classifiers":[
        {
            "category":"Banks & Credit Unions",
            "subcategory":"Bank",
            "type":"Services"
        }
    ],
    "sg:phone":"+39 02 918 1844",
    "sg:postcode":"20037",
    "sg:province":"Milano",
    "wof:name":"Istituto Bancario, San Paolo Di Torino Spa",
    "wof:placetype":"venue"
},
  "geometry": {"coordinates":[9.169582,45.570248],"type":"Point"}
}