{
  "type": "Feature",
  "properties": {
    "addr:full":"40054 Budrio Budrio Bologna 40054",
    "addr:postcode":"40054;40054",
    "iso:country":"IT",
    "sg:address":"40054 Budrio",
    "sg:city":"Budrio",
    "sg:orig_category":"Prodotti E Manufatti In Gomma. Forniture Per Attivita' Industriali",
    "sg:phone":"+39 051 803608",
    "sg:postcode":"40054",
    "sg:province":"Bologna",
    "wof:name":"Aercel Srl",
    "wof:placetype":"venue"
},
  "geometry": {"coordinates":[11.3657360077,44.4791908264],"type":"Point"}
}