{
  "type": "Feature",
  "properties": {
    "iso:country":"IT",
    "sg:address":"66054 Vasto",
    "sg:city":"Vasto",
    "sg:orig_category":"Agenzie D'affari E Servizi Commerciali",
    "sg:phone":"+39 0873 801734",
    "sg:postcode":"66054",
    "sg:province":"Chieti",
    "wof:name":"Molino Immobiliare",
    "wof:placetype":"venue"
},
  "geometry": {"coordinates":[14.718911,42.101494],"type":"Point"}
}