{
  "type": "Feature",
  "properties": {
    "iso:country":"IT",
    "sg:address":"20136 Milano",
    "sg:city":"Milano",
    "sg:orig_category":"Termotecnica E Riscaldamento, Apparecchiature E Servizi",
    "sg:phone":"+39 02 8942 3514",
    "sg:postcode":"20136",
    "sg:province":"Milano",
    "wof:name":"Itei Di Mai Linda E C. Sas",
    "wof:placetype":"venue"
},
  "geometry": {"coordinates":[9.181678,45.448624],"type":"Point"}
}