{
  "type": "Feature",
  "properties": {
    "addr:full":"36031 Dueville Dueville Vicenza 36031",
    "addr:postcode":"36031;36031",
    "iso:country":"IT",
    "sg:address":"36031 Dueville",
    "sg:city":"Dueville",
    "sg:orig_category":"Autofficine E Centri Assistenza",
    "sg:phone":"+39 0444 590486",
    "sg:postcode":"36031",
    "sg:province":"Vicenza",
    "wof:name":"C.a.v.i. Carraro Di Carraro G. & C.",
    "wof:placetype":"venue"
},
  "geometry": {"coordinates":[11.576699,45.645542],"type":"Point"}
}