{
  "type": "Feature",
  "properties": {
    "addr:full":"57027 San Vincenzo San Vincenzo Livorno 57027",
    "addr:housenumber":"57027",
    "addr:postcode":"57027",
    "addr:street":"San",
    "iso:country":"IT",
    "sg:address":"57027 San Vincenzo",
    "sg:city":"San Vincenzo",
    "sg:orig_category":"Servizi Per Lo Sport E Il Tempo Libero. Alberghi E Strutture Extra Alberghiere",
    "sg:phone":"+39 0565 706340",
    "sg:postcode":"57027",
    "sg:province":"Livorno",
    "wof:name":"Residence E Stabilimento Balneare La Lanterna",
    "wof:placetype":"venue"
},
  "geometry": {"coordinates":[10.53826,43.087124],"type":"Point"}
}