{
  "type": "Feature",
  "properties": {
    "iso:country":"IT",
    "sg:address":"21020 Casciago",
    "sg:city":"Casciago",
    "sg:orig_category":"Servizi Di Magazzinaggio E Movimentazione",
    "sg:phone":"+39 0332 826023",
    "sg:postcode":"21020",
    "sg:province":"Varese",
    "wof:name":"C.g. Misure Metriche S.n.c. Di Caravati E C.",
    "wof:placetype":"venue"
},
  "geometry": {"coordinates":[8.765385,45.821999],"type":"Point"}
}