{
  "type": "Feature",
  "properties": {
    "iso:country":"IT",
    "sg:address":"43013 Langhirano",
    "sg:city":"Langhirano",
    "sg:classifiers":[
        {
            "category":"Manufacturing",
            "subcategory":"Food",
            "type":"Manufacturing & Wholesale Goods"
        }
    ],
    "sg:phone":"+39 0521 857628",
    "sg:postcode":"43013",
    "sg:province":"Parma",
    "sg:tags":[
        "product"
    ],
    "wof:name":"Soliani Di Soliani Fermo & C. Snc",
    "wof:placetype":"venue"
},
  "geometry": {"coordinates":[10.2996578217,44.8058204651],"type":"Point"}
}