{
  "type": "Feature",
  "properties": {
    "iso:country":"IT",
    "sg:address":"20, Via Dell' Artigianato 63010 Torre San Patrizio",
    "sg:city":"Torre San Patrizio",
    "sg:classifiers":[
        {
            "category":"Personal",
            "subcategory":"Shoe Repair & Shine",
            "type":"Services"
        }
    ],
    "sg:phone":"+39 0734 510701",
    "sg:postcode":"63010",
    "sg:province":"Ascoli Piceno",
    "sg:tags":[
        "leather"
    ],
    "wof:name":"Calzaturificio La Trento Di Cancellieri Simone & C",
    "wof:placetype":"venue"
},
  "geometry": {"coordinates":[13.616323,43.178486],"type":"Point"}
}