{
  "type": "Feature",
  "properties": {
    "addr:full":"145, Vl. Alpago - Loc. Bastia 32015 Puos D'alpago Belluno 32015",
    "addr:housenumber":"145",
    "addr:postcode":"32015;32015",
    "addr:street":"Vl. Alpago Loc. Bastia",
    "iso:country":"IT",
    "sg:address":"145, Vl. Alpago - Loc. Bastia 32015 Puos D'alpago",
    "sg:classifiers":[
        {
            "category":"Manufacturing",
            "subcategory":"Lumber",
            "type":"Manufacturing & Wholesale Goods"
        }
    ],
    "sg:phone":"+39 0437 459448",
    "sg:postcode":"32015",
    "sg:province":"Belluno",
    "sg:tags":[
        "wood"
    ],
    "sg:website":"http://www.echidelpassato.it:ws_end: :mark:ws:http://www.paginegialle.it/echidelpassato",
    "wof:name":"Echi Del Passato Srl",
    "wof:placetype":"venue"
},
  "geometry": {"coordinates":[12.211802,46.151173],"type":"Point"}
}