{
  "type": "Feature",
  "properties": {
    "addr:full":"Via Astesani 43; Milano; 20161 Milano Milano 20161",
    "addr:housenumber":"43",
    "addr:postcode":"20161;20161",
    "addr:street":"Via Astesani",
    "iso:country":"IT",
    "sg:address":"Via Astesani 43; Milano; 20161",
    "sg:city":"Milano",
    "sg:classifiers":[
        {
            "category":"Banks & Credit Unions",
            "subcategory":"Bank",
            "type":"Services"
        }
    ],
    "sg:phone":"+39 02 646 6651",
    "sg:postcode":"20161",
    "sg:province":"Milano",
    "wof:name":"Banca Di Roma",
    "wof:placetype":"venue"
},
  "geometry": {"coordinates":[9.169567,45.520157],"type":"Point"}
}