{
  "type": "Feature",
  "properties": {
    "iso:country":"IT",
    "sg:address":"20154 Milano",
    "sg:city":"Milano",
    "sg:orig_category":"Prodotti Alimentari",
    "sg:phone":"+39 02 349 0681",
    "sg:postcode":"20154",
    "sg:province":"Milano",
    "wof:name":"Bossi Pietro Alberto",
    "wof:placetype":"venue"
},
  "geometry": {"coordinates":[9.1651344299,45.4833259583],"type":"Point"}
}