{
  "type": "Feature",
  "properties": {
    "iso:country":"IT",
    "sg:address":"10022 Carmagnola",
    "sg:city":"Carmagnola",
    "sg:orig_category":"Agricoltura, Orticoltura E Floricoltura",
    "sg:phone":"+39 011 972 3243",
    "sg:postcode":"10022",
    "sg:province":"Torino",
    "wof:name":"Favero Lucia",
    "wof:placetype":"venue"
},
  "geometry": {"coordinates":[7.727388,44.851379],"type":"Point"}
}