{
  "type": "Feature",
  "properties": {
    "iso:country":"IT",
    "sg:address":"Viale Delle Magnolie 1, 38062 Arco, Tn",
    "sg:city":"Arco",
    "sg:classifiers":[
        {
            "category":"Banks & Credit Unions",
            "subcategory":"Bank",
            "type":"Services"
        }
    ],
    "sg:postcode":"38062",
    "sg:province":"Trento",
    "wof:name":"Cassa Rurale Di Arco-garda Trentino-banca Di Credito Cooperativo Scarl",
    "wof:placetype":"venue"
},
  "geometry": {"coordinates":[10.883857,45.91877],"type":"Point"}
}