{
  "type": "Feature",
  "properties": {
    "iso:country":"IT",
    "sg:address":"40121 Bologna",
    "sg:city":"Bologna",
    "sg:classifiers":[
        {
            "category":"Health Services",
            "subcategory":"Health Practitioner",
            "type":"Services"
        }
    ],
    "sg:phone":"+39 051 261416",
    "sg:postcode":"40121",
    "sg:province":"Bologna",
    "sg:tags":[
        "medici"
    ],
    "sg:website":"http://www.zigiotti.it",
    "wof:name":"Prof. Gian Luigi Zigiotti",
    "wof:placetype":"venue"
},
  "geometry": {"coordinates":[11.3398361206,44.5040626526],"type":"Point"}
}