{
  "type": "Feature",
  "properties": {
    "iso:country":"IT",
    "sg:address":"48018 Faenza",
    "sg:city":"Faenza",
    "sg:orig_category":"Elettronica Professionale E Di Consumo. Automazione E Macchine Per Ufficio. Forniture Industriali Per Prevenzione, Controllo E Sicurezza",
    "sg:phone":"+39 0546 622333",
    "sg:postcode":"48018",
    "sg:province":"Ravenna",
    "sg:website":"http://www.tecno-alarm.it",
    "wof:name":"Tecno-alarm Di Lega Claudio & C. Snc",
    "wof:placetype":"venue"
},
  "geometry": {"coordinates":[11.934278,44.384079],"type":"Point"}
}