{
  "type": "Feature",
  "properties": {
    "addr:full":"131, Via Tonale 21100 Varese Varese Varese 21100",
    "addr:housenumber":"131",
    "addr:postcode":"21100;21100",
    "addr:street":"Via Tonale",
    "iso:country":"IT",
    "sg:address":"131, Via Tonale 21100 Varese",
    "sg:city":"Varese",
    "sg:classifiers":[
        {
            "category":"Manufacturing",
            "subcategory":"Rubber & Plastics",
            "type":"Manufacturing & Wholesale Goods"
        }
    ],
    "sg:phone":"+39 0332 333034",
    "sg:postcode":"21100",
    "sg:province":"Varese",
    "wof:name":"Broggini Rag. Vittorio S.r.l.",
    "wof:placetype":"venue"
},
  "geometry": {"coordinates":[8.8482217789,45.8148574829],"type":"Point"}
}