{
  "type": "Feature",
  "properties": {
    "addr:full":"23851 Galbiate Galbiate Lecco 23851",
    "addr:postcode":"23851;23851",
    "iso:country":"IT",
    "sg:address":"23851 Galbiate",
    "sg:city":"Galbiate",
    "sg:orig_category":"Articoli Medico-sanitari Ed Ortopedici",
    "sg:phone":"+39 0341 241011",
    "sg:postcode":"23851",
    "sg:province":"Lecco",
    "sg:website":"http://www.spim.it",
    "wof:name":"Spim Di Bazzoni Roberto",
    "wof:placetype":"venue"
},
  "geometry": {"coordinates":[9.384707,45.817806],"type":"Point"}
}