{
  "type": "Feature",
  "properties": {
    "addr:full":"17024 Finale Ligure Finale Ligure Savona 17024",
    "addr:postcode":"17024;17024",
    "iso:country":"IT",
    "sg:address":"17024 Finale Ligure",
    "sg:city":"Finale Ligure",
    "sg:orig_category":"Agenzie D'affari E Servizi Commerciali",
    "sg:phone":"+39 019 681 6130",
    "sg:postcode":"17024",
    "sg:province":"Savona",
    "sg:website":"http://www.vistamare.it",
    "wof:name":"Vistamare Sas",
    "wof:placetype":"venue"
},
  "geometry": {"coordinates":[8.330545,44.175018],"type":"Point"}
}