{
  "type": "Feature",
  "properties": {
    "iso:country":"IT",
    "sg:address":"Via San Basilio 48, 00187 Rome, Rm",
    "sg:classifiers":[
        {
            "category":"Banks & Credit Unions",
            "subcategory":"Bank",
            "type":"Services"
        }
    ],
    "sg:phone":"+39 039 6488 4380",
    "sg:postcode":"00187",
    "sg:province":"Roma",
    "wof:name":"Bnl Edizioni Srl",
    "wof:placetype":"venue"
},
  "geometry": {"coordinates":[12.490151,41.905308],"type":"Point"}
}