{
  "type": "Feature",
  "properties": {
    "iso:country":"IT",
    "sg:address":"47031 Dogana",
    "sg:orig_category":"Avvocati, Notai E Servizi Legali. Consulenze Tecniche, Amministrative E Perizie",
    "sg:phone":"+39 0549 970830",
    "sg:province":"SM",
    "wof:name":"Brema S.r.l.",
    "wof:placetype":"venue"
},
  "geometry": {"coordinates":[12.48994,43.982136],"type":"Point"}
}