{
  "type": "Feature",
  "properties": {
    "iso:country":"IT",
    "sg:address":"4, Via Villa Poticcio 60022 Castelfidardo",
    "sg:city":"Castelfidardo",
    "sg:classifiers":[
        {
            "category":"Home & Garden",
            "subcategory":"Home Furnishings",
            "type":"Retail Goods"
        }
    ],
    "sg:phone":"+39 071 782 0959",
    "sg:postcode":"60022",
    "sg:province":"Ancona",
    "sg:tags":[
        "household"
    ],
    "wof:name":"Baldoni & Mazzoni",
    "wof:placetype":"venue"
},
  "geometry": {"coordinates":[13.5908746719,43.4505577087],"type":"Point"}
}