{
  "type": "Feature",
  "properties": {
    "iso:country":"IT",
    "sg:address":"Via Sterpi 24 55041 Camaiore",
    "sg:city":"Camaiore",
    "sg:classifiers":[
        {
            "category":"Shopping Center",
            "type":"Public Place"
        }
    ],
    "sg:phone":"+39 0584 984000",
    "sg:postcode":"55041",
    "sg:province":"Lucca",
    "sg:tags":[
        "aluminium",
        "casting"
    ],
    "wof:name":"Oreste Pardini Srl",
    "wof:placetype":"venue"
},
  "geometry": {"coordinates":[10.3047,43.941837],"type":"Point"}
}