{
  "type": "Feature",
  "properties": {
    "iso:country":"IT",
    "sg:address":"Corso Francia 7a; Rivoli; 10098",
    "sg:city":"Rivoli",
    "sg:classifiers":[
        {
            "category":"Banks & Credit Unions",
            "subcategory":"Bank",
            "type":"Services"
        }
    ],
    "sg:phone":"+39 011 953 2343",
    "sg:postcode":"10098",
    "sg:province":"Torino",
    "wof:name":"Creditio Italiano Spa",
    "wof:placetype":"venue"
},
  "geometry": {"coordinates":[7.52064,45.070297],"type":"Point"}
}