{
  "type": "Feature",
  "properties": {
    "addr:full":"90030 Contessa Entellina Contessa Entellina Palermo 90030",
    "addr:postcode":"90030;90030",
    "iso:country":"IT",
    "sg:address":"90030 Contessa Entellina",
    "sg:city":"Contessa Entellina",
    "sg:orig_category":"Pubblica Amministrazione",
    "sg:phone":"+39 091 830 2129",
    "sg:postcode":"90030",
    "sg:province":"Palermo",
    "wof:name":"Carabinieri",
    "wof:placetype":"venue"
},
  "geometry": {"coordinates":[13.1842718124,37.728843689],"type":"Point"}
}