{
  "type": "Feature",
  "properties": {
    "addr:full":"00132 Roma Roma Roma 00132",
    "addr:postcode":"00132;00132",
    "iso:country":"IT",
    "sg:address":"00132 Roma",
    "sg:city":"Roma",
    "sg:orig_category":"Macchine, Impianti Ed Attrezzature Per Agricoltura E Zootecnia. Macchine E Forniture Per Arredamento E Industria Del Legno",
    "sg:phone":"+39 06 2076 2654",
    "sg:postcode":"00132",
    "sg:province":"Roma",
    "wof:name":"Quattrini Di Sandro Quattrini",
    "wof:placetype":"venue"
},
  "geometry": {"coordinates":[12.678832,41.862698],"type":"Point"}
}