{
  "type": "Feature",
  "properties": {
    "addr:full":"10132 Torino Torino Torino 10132",
    "addr:postcode":"10132;10132",
    "iso:country":"IT",
    "sg:address":"10132 Torino",
    "sg:city":"Torino",
    "sg:orig_category":"Utensili Meccanici E Materiali",
    "sg:phone":"+39 011 899 6202",
    "sg:postcode":"10132",
    "sg:province":"Torino",
    "wof:name":"Util-mec",
    "wof:placetype":"venue"
},
  "geometry": {"coordinates":[7.737545,45.070229],"type":"Point"}
}