{
  "type": "Feature",
  "properties": {
    "iso:country":"IT",
    "sg:address":"20137 Milano",
    "sg:city":"Milano",
    "sg:orig_category":"Chiese Ed Associazioni Religiose",
    "sg:phone":"+39 02 711212",
    "sg:postcode":"20137",
    "sg:province":"Milano",
    "wof:name":"Chiesa Cattolica Parrocchiale Preziosissimo Sangue Di N.s.g.c.",
    "wof:placetype":"venue"
},
  "geometry": {"coordinates":[9.192329,45.457504],"type":"Point"}
}