{
  "type": "Feature",
  "properties": {
    "addr:full":"Via Degasperi 32 60020 Agugliano Agugliano Ancona 60020",
    "addr:housenumber":"32",
    "addr:postcode":"60020;60020",
    "addr:street":"Via Degasperi",
    "iso:country":"IT",
    "sg:address":"Via Degasperi 32 60020 Agugliano",
    "sg:city":"Agugliano",
    "sg:classifiers":[
        {
            "category":"Manufacturing",
            "subcategory":"Textiles",
            "type":"Manufacturing & Wholesale Goods"
        }
    ],
    "sg:phone":"+39 071 907447",
    "sg:postcode":"60020",
    "sg:province":"Ancona",
    "sg:tags":[
        "curtain",
        "fabric"
    ],
    "wof:name":"Angeloni Luciana",
    "wof:placetype":"venue"
},
  "geometry": {"coordinates":[13.388594,43.543415],"type":"Point"}
}