{
  "type": "Feature",
  "properties": {
    "iso:country":"IT",
    "sg:address":"00178 Roma",
    "sg:city":"Roma",
    "sg:orig_category":"Articoli Da Regalo. Arte Ed Artigianato Artistico. Shopping",
    "sg:phone":"+39 06 7934 0012",
    "sg:postcode":"00178",
    "sg:province":"Roma",
    "wof:name":"Cortellesi Roberto",
    "wof:placetype":"venue"
},
  "geometry": {"coordinates":[12.558014,41.829327],"type":"Point"}
}