{
  "type": "Feature",
  "properties": {
    "iso:country":"IT",
    "sg:address":"20068 Peschiera Borromeo",
    "sg:city":"Peschiera Borromeo",
    "sg:orig_category":"Servizi E Lavori Per Agricoltura E Zootecnia. Animali Domestici",
    "sg:phone":"+39 02 547 5443",
    "sg:postcode":"20068",
    "sg:province":"Milano",
    "wof:name":"Benanti Rita",
    "wof:placetype":"venue"
},
  "geometry": {"coordinates":[9.311281,45.429543],"type":"Point"}
}