{
  "type": "Feature",
  "properties": {
    "iso:country":"IT",
    "sg:address":"Via Gobetti, 1/3 20090 Buccinasco",
    "sg:city":"Buccinasco",
    "sg:classifiers":[
        {
            "category":"Home & Garden",
            "subcategory":"Hardware",
            "type":"Retail Goods"
        }
    ],
    "sg:phone":"+39 02 4570 0268",
    "sg:postcode":"20090",
    "sg:province":"Milano",
    "sg:tags":[
        "small",
        "ironware",
        "item"
    ],
    "sg:website":"www.derk.it",
    "wof:name":"Derk Spa",
    "wof:placetype":"venue"
},
  "geometry": {"coordinates":[9.084256,45.433983],"type":"Point"}
}