{
  "type": "Feature",
  "properties": {
    "iso:country":"IT",
    "sg:address":"20123 Milano",
    "sg:city":"Milano",
    "sg:orig_category":"Gioielleria, Oreficeria E Argenteria. Shopping",
    "sg:phone":"+39 02 8901 3644",
    "sg:postcode":"20123",
    "sg:province":"Milano",
    "wof:name":"Adamas Srl Di Baccarini Augusto & C.",
    "wof:placetype":"venue"
},
  "geometry": {"coordinates":[9.185324,45.459549],"type":"Point"}
}