{
  "type": "Feature",
  "properties": {
    "addr:full":"3, Strada Passavone 20087 Robecco Sul Naviglio Robecco sul Naviglio Milano 20087",
    "addr:postcode":"20087;20087",
    "addr:street":"Strada Passavone",
    "iso:country":"IT",
    "sg:address":"3, Strada Passavone 20087 Robecco Sul Naviglio",
    "sg:city":"Robecco sul Naviglio",
    "sg:classifiers":[
        {
            "category":"Manufacturing",
            "subcategory":"Rubber & Plastics",
            "type":"Manufacturing & Wholesale Goods"
        }
    ],
    "sg:phone":"+39 39029470972",
    "sg:postcode":"20087",
    "sg:province":"Milano",
    "wof:name":"Apemilano (s.p.a.)",
    "wof:placetype":"venue"
},
  "geometry": {"coordinates":[8.8867845535,45.4286155701],"type":"Point"}
}