{
  "type": "Feature",
  "properties": {
    "iso:country":"IT",
    "sg:address":"23868 Valmadrera",
    "sg:city":"Valmadrera",
    "sg:orig_category":"Lavorazioni Meccaniche E Servizi",
    "sg:phone":"+39 0341 582676",
    "sg:postcode":"23868",
    "sg:province":"Lecco",
    "wof:name":"Spreafico Srl",
    "wof:placetype":"venue"
},
  "geometry": {"coordinates":[9.367928,45.845387],"type":"Point"}
}