{
  "type": "Feature",
  "properties": {
    "iso:country":"IT",
    "sg:address":"50122 Firenze",
    "sg:city":"Firenze",
    "sg:orig_category":"Gioiellerie E Oreficerie - Vendita Al Dettaglio",
    "sg:phone":"+39 055 242983",
    "sg:postcode":"50122",
    "sg:province":"Firenze",
    "sg:website":"http://www.leatherguild.it",
    "wof:name":"The Gold Market",
    "wof:placetype":"venue"
},
  "geometry": {"coordinates":[11.262237,43.768665],"type":"Point"}
}