{
  "type": "Feature",
  "properties": {
    "iso:country":"IT",
    "sg:address":"00015 Monterotondo",
    "sg:city":"Monterotondo",
    "sg:orig_category":"Automazione E Macchine Per Ufficio. Servizi Ausiliari Di Certificati, Riproduzioni, Disegni E Foto",
    "sg:phone":"+39 06 906 9379",
    "sg:postcode":"00015",
    "sg:province":"Roma",
    "wof:name":"Novadata Systems Di Lucentini Fausta E C. Sas",
    "wof:placetype":"venue"
},
  "geometry": {"coordinates":[12.593181,42.080296],"type":"Point"}
}