{
  "type": "Feature",
  "properties": {
    "addr:full":"60026 Numana Numana Ancona 60026",
    "addr:postcode":"60026;60026",
    "iso:country":"IT",
    "sg:address":"60026 Numana",
    "sg:city":"Numana",
    "sg:classifiers":[
        {
            "category":"Travel",
            "subcategory":"Hotels & Motels",
            "type":"Entertainment"
        }
    ],
    "sg:phone":"+39 071 933 0521",
    "sg:postcode":"60026",
    "sg:province":"Ancona",
    "sg:tags":[
        "camping",
        "facility"
    ],
    "sg:website":"http://www.campingriviera.it",
    "wof:name":"Camping Riviera",
    "wof:placetype":"venue"
},
  "geometry": {"coordinates":[13.618908,43.483612],"type":"Point"}
}