{
  "type": "Feature",
  "properties": {
    "iso:country":"IT",
    "sg:address":"06132 Perugia",
    "sg:city":"Perugia",
    "sg:orig_category":"Apparecchiature E Sistemi Per Magazzinaggio E Movimentazione",
    "sg:phone":"+39 075 528 8643",
    "sg:postcode":"06132",
    "sg:province":"Perugia",
    "wof:name":"Consorzio Trasporti Perugia La Freedom Soc.coop.r.l.",
    "wof:placetype":"venue"
},
  "geometry": {"coordinates":[12.357842,43.034187],"type":"Point"}
}