{
  "type": "Feature",
  "properties": {
    "addr:full":"00149 Roma Roma Roma 00149",
    "addr:postcode":"00149;00149",
    "iso:country":"IT",
    "sg:address":"00149 Roma",
    "sg:city":"Roma",
    "sg:orig_category":"Prodotti Alimentari",
    "sg:phone":"+39 06 5528 6150",
    "sg:postcode":"00149",
    "sg:province":"Roma",
    "wof:name":"Soc. S.i.a. Srl",
    "wof:placetype":"venue"
},
  "geometry": {"coordinates":[12.4503211975,41.8556404114],"type":"Point"}
}