{
  "type": "Feature",
  "properties": {
    "iso:country":"IT",
    "sg:address":"20093 Cologno Monzese",
    "sg:city":"Cologno Monzese",
    "sg:orig_category":"Affilatura Strumenti Ed Utensili",
    "sg:phone":"+39 02 253 3375",
    "sg:postcode":"20093",
    "sg:province":"Milano",
    "wof:name":"Vitali Snc Di Vitali Gianpaolo & C.",
    "wof:placetype":"venue"
},
  "geometry": {"coordinates":[9.282738,45.538933],"type":"Point"}
}