{
  "type": "Feature",
  "properties": {
    "addr:full":"Via F. Carrara 121 51015 Monsummano Terme Monsummano Terme Pistoia 51015",
    "addr:housenumber":"121",
    "addr:postcode":"51015;51015",
    "addr:street":"Via F. Carrara",
    "iso:country":"IT",
    "sg:address":"Via F. Carrara 121 51015 Monsummano Terme",
    "sg:city":"Monsummano Terme",
    "sg:classifiers":[
        {
            "category":"Building & Trades",
            "subcategory":"Equipment Rental",
            "type":"Services"
        }
    ],
    "sg:phone":"+39 0572 51465",
    "sg:postcode":"51015",
    "sg:province":"Pistoia",
    "sg:tags":[
        "adhesive",
        "industry",
        "sealant"
    ],
    "sg:website":"www.icad.it",
    "wof:name":"I.c.a.d. Srl",
    "wof:placetype":"venue"
},
  "geometry": {"coordinates":[10.918524,43.932156],"type":"Point"}
}