{
  "type": "Feature",
  "properties": {
    "iso:country":"IT",
    "sg:address":"21026 Gavirate",
    "sg:city":"Gavirate",
    "sg:classifiers":[
        {
            "category":"Health Services",
            "subcategory":"Health Practitioner",
            "type":"Services"
        }
    ],
    "sg:phone":"+39 0332 747167",
    "sg:postcode":"21026",
    "sg:province":"Varese",
    "sg:tags":[
        "medici"
    ],
    "wof:name":"Clerici Giulio",
    "wof:placetype":"venue"
},
  "geometry": {"coordinates":[8.71425,45.840668],"type":"Point"}
}