{
  "type": "Feature",
  "properties": {
    "addr:full":"28100 Novara Novara Novara 28100",
    "addr:postcode":"28100;28100",
    "iso:country":"IT",
    "sg:address":"28100 Novara",
    "sg:city":"Novara",
    "sg:orig_category":"Prodotti Di Base E Forniture Per Industria Alimentare E Bevande",
    "sg:phone":"+39 0321 474327",
    "sg:postcode":"28100",
    "sg:province":"Novara",
    "wof:name":"Uglietti Giulio",
    "wof:placetype":"venue"
},
  "geometry": {"coordinates":[8.6148729324,45.4628143311],"type":"Point"}
}