{
  "type": "Feature",
  "properties": {
    "iso:country":"IT",
    "sg:address":"35020 Saonara",
    "sg:city":"Saonara",
    "sg:orig_category":"Accessori Dei Mezzi Di Trasporto. Riparazione Dei Mezzi Di Trasporto",
    "sg:phone":"+39 049 790895",
    "sg:postcode":"35020",
    "sg:province":"Padova",
    "wof:name":"Tappezzeria Auto Di Conte Gianni",
    "wof:placetype":"venue"
},
  "geometry": {"coordinates":[11.986694,45.360142],"type":"Point"}
}