{
  "type": "Feature",
  "properties": {
    "addr:full":"91026 Mazara Del Vallo Mazara del Vallo Trapani 91026",
    "addr:postcode":"91026;91026",
    "iso:country":"IT",
    "sg:address":"91026 Mazara Del Vallo",
    "sg:city":"Mazara del Vallo",
    "sg:orig_category":"Servizi Ausiliari Per Il Trasporto",
    "sg:phone":"+39 0923 653839",
    "sg:postcode":"91026",
    "sg:province":"Trapani",
    "wof:name":"Lisma Nicolo Maria",
    "wof:placetype":"venue"
},
  "geometry": {"coordinates":[12.579372,37.657013],"type":"Point"}
}