{
  "type": "Feature",
  "properties": {
    "addr:full":"Piazza Roma 10; Grontardo; 26044 Grontardo Cremona 26044",
    "addr:housenumber":"10",
    "addr:postcode":"26044;26044",
    "addr:street":"Piazza Roma",
    "iso:country":"IT",
    "sg:address":"Piazza Roma 10; Grontardo; 26044",
    "sg:city":"Grontardo",
    "sg:classifiers":[
        {
            "category":"Banks & Credit Unions",
            "subcategory":"Bank",
            "type":"Services"
        }
    ],
    "sg:phone":"+39 0372 89126",
    "sg:postcode":"26044",
    "sg:province":"Cremona",
    "wof:name":"Istituto Bancario, San Paolo Di Torino Spa",
    "wof:placetype":"venue"
},
  "geometry": {"coordinates":[10.150827,45.201477],"type":"Point"}
}