{
  "type": "Feature",
  "properties": {
    "addr:full":"24040 Ciserano Ciserano Bergamo 24040",
    "addr:postcode":"24040;24040",
    "iso:country":"IT",
    "sg:address":"24040 Ciserano",
    "sg:city":"Ciserano",
    "sg:orig_category":"Argentatura, Doratura, Platinatura E Rodiatura",
    "sg:phone":"+39 035 884855",
    "sg:postcode":"24040",
    "sg:province":"Bergamo",
    "wof:name":"Superlux Srl",
    "wof:placetype":"venue"
},
  "geometry": {"coordinates":[9.55865,45.582012],"type":"Point"}
}