{
  "type": "Feature",
  "properties": {
    "addr:full":"Via Monfalcone 20010 Arluno Arluno Milano 20010",
    "addr:postcode":"20010;20010",
    "addr:street":"Via Monfalcone",
    "iso:country":"IT",
    "sg:address":"Via Monfalcone 20010 Arluno",
    "sg:city":"Arluno",
    "sg:classifiers":[
        {
            "category":"Manufacturing",
            "subcategory":"Metals",
            "type":"Manufacturing & Wholesale Goods"
        }
    ],
    "sg:phone":"+39 39029017165",
    "sg:postcode":"20010",
    "sg:province":"Milano",
    "sg:tags":[
        "metallurgy",
        "metalworking"
    ],
    "wof:name":"Fonderia F.lli Benzi Snc Di Benzi F.g.a.",
    "wof:placetype":"venue"
},
  "geometry": {"coordinates":[8.9586849213,45.5076789856],"type":"Point"}
}