{
  "type": "Feature",
  "properties": {
    "iso:country":"IT",
    "sg:address":"24061 Albano Sant'alessandro",
    "sg:orig_category":"Manufacturers: Prefabbricati",
    "sg:phone":"+39 035 582200",
    "sg:postcode":"24061",
    "sg:province":"Bergamo",
    "wof:name":"Ghislandi Claudio",
    "wof:placetype":"venue"
},
  "geometry": {"coordinates":[9.766047,45.688522],"type":"Point"}
}