{
  "type": "Feature",
  "properties": {
    "addr:full":"63033 Monte Prandone Centobuchi Ascoli Piceno 63033",
    "addr:housenumber":"63033",
    "addr:postcode":"63033",
    "addr:street":"Monte Prandone Centobuchi",
    "iso:country":"IT",
    "sg:address":"63033 Monte Prandone",
    "sg:city":"Centobuchi",
    "sg:orig_category":"Servizi E Lavori Per Ecologia E Smaltimento Rifiuti",
    "sg:phone":"+39 0735 702999",
    "sg:postcode":"63033",
    "sg:province":"Ascoli Piceno",
    "wof:name":"Recupero 2000 Di Fontana Davide & C. Snc",
    "wof:placetype":"venue"
},
  "geometry": {"coordinates":[13.853148,42.898926],"type":"Point"}
}