{
  "type": "Feature",
  "properties": {
    "addr:full":"50121 Firenze Firenze Firenze 50121",
    "addr:postcode":"50121;50121",
    "iso:country":"IT",
    "sg:address":"50121 Firenze",
    "sg:city":"Firenze",
    "sg:classifiers":[
        {
            "category":"Health Services",
            "subcategory":"Health Practitioner",
            "type":"Services"
        }
    ],
    "sg:phone":"+39 055 247 6236",
    "sg:postcode":"50121",
    "sg:province":"Firenze",
    "sg:tags":[
        "medici"
    ],
    "wof:name":"Capacci Paolo",
    "wof:placetype":"venue"
},
  "geometry": {"coordinates":[11.265472,43.772881],"type":"Point"}
}