{
  "type": "Feature",
  "properties": {
    "addr:full":"Via Molise 24 40060 Osteria Grande Osteria Grande Bologna 40060",
    "addr:housenumber":"24",
    "addr:postcode":"40060;40060",
    "addr:street":"Via Molise;Grande Osteria Grande Bologna",
    "iso:country":"IT",
    "sg:address":"Via Molise 24 40060 Osteria Grande",
    "sg:city":"Osteria Grande",
    "sg:classifiers":[
        {
            "category":"Structure",
            "subcategory":"Warehouse",
            "type":"Public Place"
        }
    ],
    "sg:phone":"+39 051 945852",
    "sg:postcode":"40060",
    "sg:province":"Bologna",
    "sg:tags":[
        "units",
        "automatic",
        "robot",
        "metering"
    ],
    "sg:website":"www.prbpack.com",
    "wof:name":"Prb Packaging Systems Srl",
    "wof:placetype":"venue"
},
  "geometry": {"coordinates":[11.523205,44.435326],"type":"Point"}
}