{
  "type": "Feature",
  "properties": {
    "iso:country":"IT",
    "sg:address":"Via Costeggiola; Zermeghedo; 36050",
    "sg:city":"Zermeghedo",
    "sg:classifiers":[
        {
            "category":"Banks & Credit Unions",
            "subcategory":"Bank",
            "type":"Services"
        }
    ],
    "sg:phone":"+39 0444 484099",
    "sg:postcode":"36050",
    "sg:province":"Vicenza",
    "wof:name":"Banca Popolare Vicentina",
    "wof:placetype":"venue"
},
  "geometry": {"coordinates":[11.371187,45.472885],"type":"Point"}
}