{
  "type": "Feature",
  "properties": {
    "addr:full":"37139 Verona Verona Verona 37139",
    "addr:postcode":"37139;37139",
    "iso:country":"IT",
    "sg:address":"37139 Verona",
    "sg:city":"Verona",
    "sg:classifiers":[
        {
            "category":"Banks & Credit Unions",
            "subcategory":"Atm",
            "type":"Services"
        }
    ],
    "sg:phone":"+39 045 851 1155",
    "sg:postcode":"37139",
    "sg:province":"Verona",
    "sg:tags":[
        "refuse",
        "supply",
        "disposal",
        "environmental",
        "protection",
        "machinery"
    ],
    "wof:name":"Brotto Impianti Snc",
    "wof:placetype":"venue"
},
  "geometry": {"coordinates":[10.901408,45.438122],"type":"Point"}
}