{
  "type": "Feature",
  "properties": {
    "iso:country":"IT",
    "sg:address":"25063 Gardone Val Trompia",
    "sg:city":"Gardone Val Trompia",
    "sg:orig_category":"Automazione E Macchine Per Ufficio. Arredi Ed Attrezzature Per Attivita' Commerciali Ed Artigianali",
    "sg:phone":"+39 030 891 0604",
    "sg:postcode":"25063",
    "sg:province":"Brescia",
    "wof:name":"Serotti Ufficio Di Bettinsoli Martino & C. Snc",
    "wof:placetype":"venue"
},
  "geometry": {"coordinates":[10.168765,45.688896],"type":"Point"}
}