{
  "type": "Feature",
  "properties": {
    "iso:country":"IT",
    "sg:address":"07026 Olbia",
    "sg:city":"Olbia",
    "sg:orig_category":"Elettrotecnica Professionale E Di Consumo. Forniture Per Attivita' Commerciali Ed Artigianali",
    "sg:phone":"+39 0789 50673",
    "sg:postcode":"07026",
    "sg:province":"Olbia-Tempio",
    "wof:name":"Olbia Neon",
    "wof:placetype":"venue"
},
  "geometry": {"coordinates":[9.278559,40.826839],"type":"Point"}
}