{
  "type": "Feature",
  "properties": {
    "addr:full":"50143 Firenze Firenze Firenze 50143",
    "addr:postcode":"50143;50143",
    "iso:country":"IT",
    "sg:address":"50143 Firenze",
    "sg:city":"Firenze",
    "sg:orig_category":"Professionisti - Studi E Servizi Ed Associazioni Di Interesse Aziendale. Associazioni Ed Organismi Di Interesse Pubblico",
    "sg:phone":"+39 055 27051",
    "sg:postcode":"50143",
    "sg:province":"Firenze",
    "wof:name":"Confesercenti Firenze",
    "wof:placetype":"venue"
},
  "geometry": {"coordinates":[10.7479085922,43.8607368469],"type":"Point"}
}