{
  "type": "Feature",
  "properties": {
    "iso:country":"IT",
    "sg:address":"Via Citta Alta 47; Chiusa; 39043",
    "sg:city":"Chiusa",
    "sg:classifiers":[
        {
            "category":"Banks & Credit Unions",
            "subcategory":"Bank",
            "type":"Services"
        }
    ],
    "sg:phone":"+39 0472 846100",
    "sg:postcode":"39043",
    "sg:province":"Bolzano/Bozen",
    "wof:name":"Banca Di Trento E Bolzano Spa",
    "wof:placetype":"venue"
},
  "geometry": {"coordinates":[11.567328,46.641182],"type":"Point"}
}