{
  "type": "Feature",
  "properties": {
    "addr:full":"80045 Pompei Pompei Napoli 80045",
    "addr:housenumber":"80045",
    "addr:postcode":"80045",
    "iso:country":"IT",
    "sg:address":"80045 Pompei",
    "sg:city":"Pompei",
    "sg:orig_category":"Gioielleria, Oreficeria E Argenteria. Shopping",
    "sg:phone":"+39 081 861 2763",
    "sg:postcode":"80045",
    "sg:province":"Napoli",
    "wof:name":"Casa Del Corallo Rosina S.r.l.",
    "wof:placetype":"venue"
},
  "geometry": {"coordinates":[14.4898,40.748131],"type":"Point"}
}