{
  "type": "Feature",
  "properties": {
    "iso:country":"IT",
    "sg:address":"75014 Grassano",
    "sg:city":"Grassano",
    "sg:orig_category":"Materiali Edili",
    "sg:phone":"+39 0835 721685",
    "sg:postcode":"75014",
    "sg:province":"Matera",
    "wof:name":"C.g.s. Lamiere Srl",
    "wof:placetype":"venue"
},
  "geometry": {"coordinates":[16.275751,40.61919],"type":"Point"}
}