{
  "type": "Feature",
  "properties": {
    "iso:country":"IT",
    "sg:address":"79, Via Ragazzi Del 99 20010 San Giorgio Su Legnano",
    "sg:city":"San Giorgio su Legnano",
    "sg:classifiers":[
        {
            "category":"Professional",
            "subcategory":"Engineering",
            "type":"Services"
        }
    ],
    "sg:phone":"+39 0331 402421",
    "sg:postcode":"20010",
    "sg:province":"Milano",
    "sg:tags":[
        "machine",
        "-",
        "mechanical"
    ],
    "wof:name":"Cobelgo Srl",
    "wof:placetype":"venue"
},
  "geometry": {"coordinates":[8.915715,45.569031],"type":"Point"}
}