{
  "type": "Feature",
  "properties": {
    "iso:country":"IT",
    "sg:address":"80040 Poggiomarino",
    "sg:city":"Poggiomarino",
    "sg:orig_category":"Prodotti Alimentari",
    "sg:phone":"+39 081 865 1205",
    "sg:postcode":"80040",
    "sg:province":"Napoli",
    "wof:name":"D'avino Vincenzo E . S.a.s.",
    "wof:placetype":"venue"
},
  "geometry": {"coordinates":[14.2640314102,40.8930625916],"type":"Point"}
}