{
  "type": "Feature",
  "properties": {
    "iso:country":"IT",
    "sg:address":"00068 Rignano Flaminio",
    "sg:city":"Rignano Flaminio",
    "sg:orig_category":"Manufacturers: Prefabbricati",
    "sg:phone":"+39 0761 509096",
    "sg:postcode":"00068",
    "sg:province":"Roma",
    "sg:website":"http://www.italgarden.it",
    "wof:name":"Italgarden Srl",
    "wof:placetype":"venue"
},
  "geometry": {"coordinates":[12.472454,42.191887],"type":"Point"}
}