{
  "type": "Feature",
  "properties": {
    "iso:country":"IT",
    "sg:address":"20156 Milano",
    "sg:city":"Milano",
    "sg:orig_category":"Ospedali E Servizi Sanitari. Servizi Sociali. Associazioni Ed Organismi Di Interesse Pubblico",
    "sg:phone":"+39 02 392 5426",
    "sg:postcode":"20156",
    "sg:province":"Milano",
    "wof:name":"Associazione Comunita' E Famiglia",
    "wof:placetype":"venue"
},
  "geometry": {"coordinates":[9.110395,45.51511],"type":"Point"}
}