{
  "type": "Feature",
  "properties": {
    "iso:country":"IT",
    "sg:address":"55100 Lucca",
    "sg:city":"Lucca",
    "sg:orig_category":"Agricoltura, Orticoltura E Floricoltura",
    "sg:phone":"+39 0583 998115",
    "sg:postcode":"55100",
    "sg:province":"Lucca",
    "sg:website":"http://www.montivivai.com",
    "wof:name":"Montivivai Srl",
    "wof:placetype":"venue"
},
  "geometry": {"coordinates":[10.528715,43.843231],"type":"Point"}
}