{
  "type": "Feature",
  "properties": {
    "iso:country":"IT",
    "sg:address":"23030 Villa Di Tirano",
    "sg:city":"Villa di Tirano",
    "sg:orig_category":"Accessori Dei Mezzi Di Trasporto",
    "sg:phone":"+39 0342 795006",
    "sg:postcode":"23030",
    "sg:province":"Sondrio",
    "wof:name":"Tona Srl",
    "wof:placetype":"venue"
},
  "geometry": {"coordinates":[10.14065,46.205673],"type":"Point"}
}