{
  "type": "Feature",
  "properties": {
    "addr:full":"40062 Molinella Molinella Bologna 40062",
    "addr:postcode":"40062;40062",
    "iso:country":"IT",
    "sg:address":"40062 Molinella",
    "sg:city":"Molinella",
    "sg:orig_category":"Forniture Per Edilizia E Lavori Pubblici",
    "sg:phone":"+39 051 881697",
    "sg:postcode":"40062",
    "sg:province":"Bologna",
    "wof:name":"Centercolor Colorifici Riuniti Srl",
    "wof:placetype":"venue"
},
  "geometry": {"coordinates":[11.3195466995,44.4997062683],"type":"Point"}
}