{
  "type": "Feature",
  "properties": {
    "iso:country":"IT",
    "sg:address":"20024 Garbagnate Milanese",
    "sg:city":"Garbagnate Milanese",
    "sg:orig_category":"Cinematografia E Radiotelevisione. Pubblicita', Marketing E Comunicazione. Acqua, Luce, Gas E Societa' Di Esercizio Pubblico",
    "sg:phone":"+39 02 995 9888",
    "sg:postcode":"20024",
    "sg:province":"Milano",
    "wof:name":"Radio Panda",
    "wof:placetype":"venue"
},
  "geometry": {"coordinates":[9.037493,45.526291],"type":"Point"}
}