{
  "type": "Feature",
  "properties": {
    "iso:country":"IT",
    "sg:address":"15046 San Salvatore Monferrerrato",
    "sg:orig_category":"Materiali Edili",
    "sg:phone":"+39 0131 238257",
    "sg:postcode":"15046",
    "sg:province":"Alessandria",
    "wof:name":"Pasino Di Casalone Piero & C. Snc",
    "wof:placetype":"venue"
},
  "geometry": {"coordinates":[8.567943,44.993748],"type":"Point"}
}