{
  "type": "Feature",
  "properties": {
    "iso:country":"IT",
    "sg:address":"38066 Riva Del Garda",
    "sg:city":"Riva del Garda",
    "sg:orig_category":"Alberghi E Strutture Extra Alberghiere",
    "sg:phone":"+39 0464 521103",
    "sg:postcode":"38066",
    "sg:province":"Trento",
    "sg:website":"http://www.hotelcampagnola.com",
    "wof:name":"Hotel Campagnola",
    "wof:placetype":"venue"
},
  "geometry": {"coordinates":[10.860697,45.903725],"type":"Point"}
}