{
  "type": "Feature",
  "properties": {
    "iso:country":"IT",
    "sg:address":"66100 Chieti",
    "sg:city":"Chieti",
    "sg:classifiers":[
        {
            "category":"Manufacturing",
            "subcategory":"Glass & Minerals",
            "type":"Manufacturing & Wholesale Goods"
        }
    ],
    "sg:phone":"+39 0871 552266",
    "sg:postcode":"66100",
    "sg:province":"Chieti",
    "sg:tags":[
        "paints",
        "varnish",
        "enamel"
    ],
    "sg:website":"http://www.azimutcoatings.com",
    "wof:name":"Azimut Srl",
    "wof:placetype":"venue"
},
  "geometry": {"coordinates":[14.1383638382,42.3814582825],"type":"Point"}
}