{
  "type": "Feature",
  "properties": {
    "iso:country":"IT",
    "sg:address":"16132 Genova",
    "sg:city":"Genova",
    "sg:orig_category":"Imprese Di Costruzioni Civili Ed Industriali",
    "sg:phone":"+39 010 399 3207",
    "sg:postcode":"16132",
    "sg:province":"Genova",
    "wof:name":"Auto Trasporti Guerra",
    "wof:placetype":"venue"
},
  "geometry": {"coordinates":[9.271832,44.535793],"type":"Point"}
}