{
  "type": "Feature",
  "properties": {
    "addr:full":"100, V. Biancospino 50013 Campi Bisenzio Campi Bisenzio Firenze 50013",
    "addr:housenumber":"100",
    "addr:postcode":"50013;50013",
    "addr:street":"V. Biancospino;Bisenzio",
    "iso:country":"IT",
    "sg:address":"100, V. Biancospino 50013 Campi Bisenzio",
    "sg:city":"Campi Bisenzio",
    "sg:classifiers":[
        {
            "category":"Professional",
            "subcategory":"Engineering",
            "type":"Services"
        }
    ],
    "sg:phone":"+39 055 898 6242",
    "sg:postcode":"50013",
    "sg:province":"Firenze",
    "sg:tags":[
        "machine",
        "-",
        "mechanical"
    ],
    "sg:website":"http://www.paginegialle.it/laifirenze",
    "wof:name":"L.a.i.",
    "wof:placetype":"venue"
},
  "geometry": {"coordinates":[11.194315,43.841568],"type":"Point"}
}