{
  "type": "Feature",
  "properties": {
    "iso:country":"IT",
    "sg:address":"24126 Bergamo",
    "sg:city":"Bergamo",
    "sg:orig_category":"Carrozzelle E Poltrone Per Infermi",
    "sg:phone":"+39 035 316677",
    "sg:postcode":"24126",
    "sg:province":"Bergamo",
    "wof:name":"Chi-o-med Srl",
    "wof:placetype":"venue"
},
  "geometry": {"coordinates":[9.655114,45.654369],"type":"Point"}
}