{
  "type": "Feature",
  "properties": {
    "iso:country":"IT",
    "sg:address":"33170 Pordenone",
    "sg:city":"Pordenone",
    "sg:classifiers":[
        {
            "category":"Autos & Motor Vehicles",
            "subcategory":"Automobile Sales",
            "type":"Retail Goods"
        }
    ],
    "sg:phone":"+39 0434 572211",
    "sg:postcode":"33170",
    "sg:province":"Pordenone",
    "sg:tags":[
        "car"
    ],
    "wof:name":"Rimorchi Bertoja Spa",
    "wof:placetype":"venue"
},
  "geometry": {"coordinates":[12.6505422592,45.9269828796],"type":"Point"}
}