{
  "type": "Feature",
  "properties": {
    "iso:country":"IT",
    "sg:address":"Strada 1 - Palazzo F2, 20090 Assago",
    "sg:city":"Assago",
    "sg:classifiers":[
        {
            "category":"Banks & Credit Unions",
            "subcategory":"Financial Services",
            "type":"Services"
        }
    ],
    "sg:phone":"+39 39028922011",
    "sg:postcode":"20090",
    "sg:province":"Milano",
    "sg:tags":[
        "banking",
        "finance",
        "insurance"
    ],
    "wof:name":"Inec Spa",
    "wof:placetype":"venue"
},
  "geometry": {"coordinates":[9.1881408691,45.4636878967],"type":"Point"}
}