{
  "type": "Feature",
  "properties": {
    "iso:country":"IT",
    "sg:address":"20096 Pioltello",
    "sg:city":"Pioltello",
    "sg:orig_category":"Ospedali E Servizi Sanitari. Pubblica Amministrazione. Servizi Sociali",
    "sg:phone":"+39 02 927 3101",
    "sg:postcode":"20096",
    "sg:province":"Milano",
    "wof:name":"Azienda Sanitaria Locale Della Provincia Di Milano 2",
    "wof:placetype":"venue"
},
  "geometry": {"coordinates":[9.328653,45.501827],"type":"Point"}
}