{
  "type": "Feature",
  "properties": {
    "addr:full":"65013 Citt\u00e0 Sant'angelo Pescara 65013",
    "addr:postcode":"65013;65013",
    "iso:country":"IT",
    "sg:address":"65013 Citt\u00e0 Sant'angelo",
    "sg:orig_category":"Macchine, Impianti Ed Attrezzature Per Abbigliamento E Pelletterie. Macchine E Impianti Per Attivita' Commerciali Ed Artigianali",
    "sg:phone":"+39 085 950 0696",
    "sg:postcode":"65013",
    "sg:province":"Pescara",
    "sg:website":"http://www.angeluccidrycenter.it",
    "wof:name":"Angelucci Dry Center Di Catia Angelucci",
    "wof:placetype":"venue"
},
  "geometry": {"coordinates":[14.14239,42.521961],"type":"Point"}
}