{
  "type": "Feature",
  "properties": {
    "addr:full":"Via Tagliamento 5 35030 Tencarola Tencarola Padova 35030",
    "addr:housenumber":"5",
    "addr:postcode":"35030;35030",
    "addr:street":"Via Tagliamento",
    "iso:country":"IT",
    "sg:address":"Via Tagliamento 5 35030 Tencarola",
    "sg:city":"Tencarola",
    "sg:classifiers":[
        {
            "category":"Social Services",
            "subcategory":"Retirement Home",
            "type":"Services"
        }
    ],
    "sg:phone":"+39 049 868 5990",
    "sg:postcode":"35030",
    "sg:province":"Padova",
    "sg:tags":[
        "cutlery",
        "plated",
        "silver"
    ],
    "sg:website":"www.greggio.it",
    "wof:name":"Rino Greggio Argenterie Spa",
    "wof:placetype":"venue"
},
  "geometry": {"coordinates":[11.806222,45.393852],"type":"Point"}
}