{
  "type": "Feature",
  "properties": {
    "iso:country":"IT",
    "sg:address":"Contrada S. Benedetto 92026 Favara",
    "sg:city":"Favara",
    "sg:classifiers":[
        {
            "category":"Food & Beverages",
            "subcategory":"Bakery",
            "type":"Retail Goods"
        }
    ],
    "sg:phone":"+39 0922 441481",
    "sg:postcode":"92026",
    "sg:province":"Agrigento",
    "sg:tags":[
        "grain",
        "cereal"
    ],
    "wof:name":"Centro Distrib.alimentari Srl",
    "wof:placetype":"venue"
},
  "geometry": {"coordinates":[13.619021,37.352001],"type":"Point"}
}