{
  "type": "Feature",
  "properties": {
    "addr:full":"41100 Modena Modena Modena 41100",
    "addr:postcode":"41100;41100",
    "iso:country":"IT",
    "sg:address":"41100 Modena",
    "sg:city":"Modena",
    "sg:orig_category":"Macchine Ed Impianti Per Edilizia E Lavori Pubblici",
    "sg:phone":"+39 059 283584",
    "sg:postcode":"41100",
    "sg:province":"Modena",
    "wof:name":"Washers Srl",
    "wof:placetype":"venue"
},
  "geometry": {"coordinates":[10.925969,44.551601],"type":"Point"}
}