{
  "type": "Feature",
  "properties": {
    "addr:full":"12045 Fossano Fossano Cuneo 12045",
    "addr:postcode":"12045;12045",
    "iso:country":"IT",
    "sg:address":"12045 Fossano",
    "sg:city":"Fossano",
    "sg:orig_category":"Bigiotterie - Vendita Al Dettaglio",
    "sg:phone":"+39 0172 62990",
    "sg:postcode":"12045",
    "sg:province":"Cuneo",
    "wof:name":"Acconciature Mary, Bijoux, Cosmetici Di Bertola Maria",
    "wof:placetype":"venue"
},
  "geometry": {"coordinates":[7.638685,44.443111],"type":"Point"}
}