{
  "type": "Feature",
  "properties": {
    "addr:full":"Via Delle Industrie 16 47824 Poggio Berni Poggio Berni Rimini 47824",
    "addr:housenumber":"16",
    "addr:postcode":"47824;47824",
    "addr:street":"Via Delle Industrie;Berni Poggio Berni",
    "iso:country":"IT",
    "sg:address":"Via Delle Industrie 16 47824 Poggio Berni",
    "sg:city":"Poggio Berni",
    "sg:orig_category":"Fine-dust Protective Clothing, Woven",
    "sg:phone":"+39 0541 627244",
    "sg:postcode":"47824",
    "sg:province":"Rimini",
    "sg:website":"www.lavostrasartoria.it",
    "wof:name":"La Vostra Sartoria Di Casadei Giova Nni & C. Snc",
    "wof:placetype":"venue"
},
  "geometry": {"coordinates":[12.4149465561,44.0493164062],"type":"Point"}
}