{
  "type": "Feature",
  "properties": {
    "addr:full":"60044 Fabriano Fabriano Ancona 60044",
    "addr:postcode":"60044;60044",
    "iso:country":"IT",
    "sg:address":"60044 Fabriano",
    "sg:city":"Fabriano",
    "sg:orig_category":"Prodotti Chimici Di Base. Ospedali E Servizi Sanitari",
    "sg:phone":"+39 0732 71160",
    "sg:postcode":"60044",
    "sg:province":"Ancona",
    "wof:name":"Son Spa",
    "wof:placetype":"venue"
},
  "geometry": {"coordinates":[12.8718891144,43.3512763977],"type":"Point"}
}