{
  "type": "Feature",
  "properties": {
    "iso:country":"IT",
    "sg:address":"20161 Milano",
    "sg:city":"Milano",
    "sg:orig_category":"Prodotti Finiti Stampati. Articoli Da Regalo. Arte Ed Artigianato Artistico. Shopping",
    "sg:phone":"+39 02 6620 3140",
    "sg:postcode":"20161",
    "sg:province":"Milano",
    "wof:name":"La Tavolozza (s.n.c.)",
    "wof:placetype":"venue"
},
  "geometry": {"coordinates":[9.1708402634,45.523651123],"type":"Point"}
}