{
  "type": "Feature",
  "properties": {
    "addr:full":"35010 Curtarolo Curtarolo Padova 35010",
    "addr:postcode":"35010;35010",
    "iso:country":"IT",
    "sg:address":"35010 Curtarolo",
    "sg:city":"Curtarolo",
    "sg:orig_category":"Non-classified Establishments",
    "sg:phone":"+39 049 557388",
    "sg:postcode":"35010",
    "sg:province":"Padova",
    "wof:name":"Borsato Renato",
    "wof:placetype":"venue"
},
  "geometry": {"coordinates":[11.846084,45.511856],"type":"Point"}
}