{
  "type": "Feature",
  "properties": {
    "addr:full":"19/2, Viale Teodorico 20149 Milano Milano Milano 20149",
    "addr:housenumber":"19 / 2",
    "addr:postcode":"20149;20149",
    "addr:street":"Viale Teodorico",
    "iso:country":"IT",
    "sg:address":"19/2, Viale Teodorico 20149 Milano",
    "sg:city":"Milano",
    "sg:classifiers":[
        {
            "category":"Shopping",
            "subcategory":"Gifts & Souvenirs",
            "type":"Retail Goods"
        }
    ],
    "sg:phone":"+39 39023450747",
    "sg:postcode":"20149",
    "sg:province":"Milano",
    "wof:name":"Mtl Italia Srl",
    "wof:placetype":"venue"
},
  "geometry": {"coordinates":[9.155167,45.487263],"type":"Point"}
}