{
  "type": "Feature",
  "properties": {
    "iso:country":"IT",
    "sg:address":"29/a, Via Milano 23899 Robbiate",
    "sg:city":"Robbiate",
    "sg:classifiers":[
        {
            "category":"Manufacturing",
            "subcategory":"Metals",
            "type":"Manufacturing & Wholesale Goods"
        }
    ],
    "sg:phone":"+39 039 928 1133",
    "sg:postcode":"23899",
    "sg:province":"Lecco",
    "sg:tags":[
        "processing"
    ],
    "wof:name":"Arcotronics Hightech Srl",
    "wof:placetype":"venue"
},
  "geometry": {"coordinates":[9.3900709152,45.8529815674],"type":"Point"}
}