{
  "type": "Feature",
  "properties": {
    "addr:full":"31049 Valdobbiadene Valdobbiadene Treviso 31049",
    "addr:postcode":"31049;31049",
    "iso:country":"IT",
    "sg:address":"31049 Valdobbiadene",
    "sg:city":"Valdobbiadene",
    "sg:orig_category":"Abbigliamento Esterno, Maglierie E Pelliccerie. Shopping",
    "sg:phone":"+39 0423 982142",
    "sg:postcode":"31049",
    "sg:province":"Treviso",
    "wof:name":"Possamai Eugenio Maglificio Di Vidor",
    "wof:placetype":"venue"
},
  "geometry": {"coordinates":[12.025048,45.862339],"type":"Point"}
}