{
  "type": "Feature",
  "properties": {
    "iso:country":"IT",
    "sg:address":"89034 Bovalino",
    "sg:city":"Bovalino",
    "sg:orig_category":"Abbigliamento Esterno, Maglierie E Pelliccerie",
    "sg:phone":"+39 0964 679257",
    "sg:postcode":"89034",
    "sg:province":"Reggio Di Calabria",
    "wof:name":"Bruno Sacco S.r.l.",
    "wof:placetype":"venue"
},
  "geometry": {"coordinates":[15.643882,38.186726],"type":"Point"}
}