{
  "type": "Feature",
  "properties": {
    "addr:full":"27, Via Del Lavoro 20040 Usmate Velate Usmate Velate Milano 20040",
    "addr:postcode":"20040;20040",
    "addr:street":"Via Del Lavoro",
    "iso:country":"IT",
    "sg:address":"27, Via Del Lavoro 20040 Usmate Velate",
    "sg:city":"Usmate Velate",
    "sg:classifiers":[
        {
            "category":"Manufacturing",
            "subcategory":"Paper Products",
            "type":"Manufacturing & Wholesale Goods"
        }
    ],
    "sg:phone":"+39 039 682 9483",
    "sg:postcode":"20040",
    "sg:province":"Milano",
    "sg:tags":[
        "cardboard"
    ],
    "wof:name":"Scatolificio Rigamonti Di Rigamonti A. E C.snc",
    "wof:placetype":"venue"
},
  "geometry": {"coordinates":[9.3430204391,45.6422843933],"type":"Point"}
}