{
  "type": "Feature",
  "properties": {
    "iso:country":"IT",
    "sg:address":"43012 Fontanellato",
    "sg:city":"Fontanellato",
    "sg:orig_category":"Bevande, Vini E Liquori",
    "sg:phone":"+39 0521 829811",
    "sg:postcode":"43012",
    "sg:province":"Parma",
    "wof:name":"Boschi Luigi & Figli Spa",
    "wof:placetype":"venue"
},
  "geometry": {"coordinates":[10.204142,44.874084],"type":"Point"}
}