{
  "type": "Feature",
  "properties": {
    "addr:full":"17019 Varazze Varazze Savona 17019",
    "addr:postcode":"17019;17019",
    "iso:country":"IT",
    "sg:address":"17019 Varazze",
    "sg:city":"Varazze",
    "sg:orig_category":"Servizi Culturali E Per Lo Spettacolo. Servizi Al Turismo. Acqua, Luce, Gas E Societa' Di Esercizio Pubblico",
    "sg:phone":"+39 019 930219",
    "sg:postcode":"17019",
    "sg:province":"Savona",
    "wof:name":"Comune",
    "wof:placetype":"venue"
},
  "geometry": {"coordinates":[8.575659,44.359924],"type":"Point"}
}