{
  "type": "Feature",
  "properties": {
    "iso:country":"IT",
    "sg:address":"Via Dell'industria 15/16 36054 Montebello Vicentino",
    "sg:city":"Montebello Vicentino",
    "sg:classifiers":[
        {
            "category":"Shopping",
            "subcategory":"Shoes",
            "type":"Retail Goods"
        }
    ],
    "sg:phone":"+39 0444 440496",
    "sg:postcode":"36054",
    "sg:province":"Vicenza",
    "sg:tags":[
        "leather",
        "chemical",
        "product",
        "industry"
    ],
    "sg:website":"www.chimes.it",
    "wof:name":"Chimes Srl",
    "wof:placetype":"venue"
},
  "geometry": {"coordinates":[11.372439,45.4417],"type":"Point"}
}