{
  "type": "Feature",
  "properties": {
    "addr:full":"8, Via Colombara Bosco 25031 Capriolo Capriolo Brescia 25031",
    "addr:postcode":"25031;25031",
    "addr:street":"Via Colombara Bosco",
    "iso:country":"IT",
    "sg:address":"8, Via Colombara Bosco 25031 Capriolo",
    "sg:city":"Capriolo",
    "sg:classifiers":[
        {
            "category":"Shopping",
            "subcategory":"Stationery & Office Supplies",
            "type":"Retail Goods"
        }
    ],
    "sg:phone":"+39 39030736212",
    "sg:postcode":"25031",
    "sg:province":"Brescia",
    "sg:tags":[
        "professional"
    ],
    "wof:name":"C.s. Arreda S.n.c. Di Zanni Giuseppe E C.",
    "wof:placetype":"venue"
},
  "geometry": {"coordinates":[9.9285383224,45.6250267029],"type":"Point"}
}