{
  "type": "Feature",
  "properties": {
    "iso:country":"IT",
    "sg:address":"Via I Maggio, 93 - Ribis 33010 Reana Del Roiale",
    "sg:city":"Reana del Roiale",
    "sg:classifiers":[
        {
            "category":"Exhibition Hall",
            "type":"Public Place"
        }
    ],
    "sg:phone":"+39 0432 853152",
    "sg:postcode":"33010",
    "sg:province":"Udine",
    "sg:tags":[
        "screen",
        "printing",
        "precision"
    ],
    "sg:website":"www.pertoldi.it",
    "wof:name":"Serigrafia Pertoldi Srl",
    "wof:placetype":"venue"
},
  "geometry": {"coordinates":[13.2307243347,46.0649414062],"type":"Point"}
}