{
  "type": "Feature",
  "properties": {
    "iso:country":"IT",
    "sg:address":"32035 S.giustina",
    "sg:orig_category":"Caminetti, Forni Da Giardino E Barbecues",
    "sg:phone":"+39 0437 888310",
    "sg:postcode":"32035",
    "sg:province":"Belluno",
    "wof:name":"Calorcasa Snc",
    "wof:placetype":"venue"
},
  "geometry": {"coordinates":[12.096933,46.106174],"type":"Point"}
}