{
  "type": "Feature",
  "properties": {
    "iso:country":"IT",
    "sg:address":"36100 Vicenza",
    "sg:city":"Anconetta",
    "sg:orig_category":"Forniture Per Agricoltura E Zootecnia. Animali Domestici",
    "sg:phone":"+39 0444 505489",
    "sg:postcode":"36100",
    "sg:province":"Vicenza",
    "wof:name":"Acquario Magazine Di Bonizzato Roberto & Marchi Lorella Snc",
    "wof:placetype":"venue"
},
  "geometry": {"coordinates":[11.5689268112,45.5664482117],"type":"Point"}
}