{
  "type": "Feature",
  "properties": {
    "addr:full":"37020 Marano Di Valpolicella Marano di Valpolicella Verona 37020",
    "addr:postcode":"37020;37020",
    "iso:country":"IT",
    "sg:address":"37020 Marano Di Valpolicella",
    "sg:city":"Marano di Valpolicella",
    "sg:orig_category":"Forniture Per Edilizia E Lavori Pubblici",
    "sg:phone":"+39 045 770 2231",
    "sg:postcode":"37020",
    "sg:province":"Verona",
    "wof:name":"Tubosider S.r.l.",
    "wof:placetype":"venue"
},
  "geometry": {"coordinates":[10.9391880035,45.5250091553],"type":"Point"}
}