{
  "type": "Feature",
  "properties": {
    "addr:full":"283, Via Delle Fonde 47032 Bertinoro Bertinoro Forl\u00ec-Cesena 47032",
    "addr:housenumber":"283",
    "addr:postcode":"47032;47032",
    "addr:street":"Via Delle Fonde",
    "iso:country":"IT",
    "sg:address":"283, Via Delle Fonde 47032 Bertinoro",
    "sg:city":"Bertinoro",
    "sg:classifiers":[
        {
            "category":"Home & Garden",
            "subcategory":"Home Furnishings",
            "type":"Retail Goods"
        }
    ],
    "sg:phone":"+39 0543 449229",
    "sg:postcode":"47032",
    "sg:province":"Forl\u00ec-Cesena",
    "sg:tags":[
        "household"
    ],
    "wof:name":"Tre Erre (s.p.a.)",
    "wof:placetype":"venue"
},
  "geometry": {"coordinates":[12.167449,44.185993],"type":"Point"}
}