{
  "type": "Feature",
  "properties": {
    "iso:country":"IT",
    "sg:address":"129, Via Emilia Ponente 40133 Bologna",
    "sg:city":"Bologna",
    "sg:classifiers":[
        {
            "category":"Real Estate",
            "subcategory":"Surveying",
            "type":"Services"
        }
    ],
    "sg:phone":"+39 39051315611",
    "sg:postcode":"40133",
    "sg:province":"Bologna",
    "sg:tags":[
        "equipment",
        "material",
        "good",
        "-",
        "handling"
    ],
    "wof:name":"Kone Ascensori Spa",
    "wof:placetype":"venue"
},
  "geometry": {"coordinates":[11.295573,44.508705],"type":"Point"}
}