{
  "type": "Feature",
  "properties": {
    "iso:country":"IT",
    "sg:address":"41011 Campogalliano",
    "sg:city":"Campogalliano",
    "sg:classifiers":[
        {
            "category":"Manufacturing",
            "subcategory":"Glass & Minerals",
            "type":"Manufacturing & Wholesale Goods"
        }
    ],
    "sg:phone":"+39 059 527047",
    "sg:postcode":"41011",
    "sg:province":"Modena",
    "sg:tags":[
        "product",
        "processing"
    ],
    "wof:name":"Futur Glass Srl",
    "wof:placetype":"venue"
},
  "geometry": {"coordinates":[10.846302,44.691643],"type":"Point"}
}