{
  "type": "Feature",
  "properties": {
    "addr:full":"49, Via Leonardo Da Vinci 47021 Bagno Di Romagna Bagno di Romagna Forl\u00ec-Cesena 47021",
    "addr:postcode":"47021;47021",
    "addr:street":"Via Leonardo Da Vinci",
    "iso:country":"IT",
    "sg:address":"49, Via Leonardo Da Vinci 47021 Bagno Di Romagna",
    "sg:city":"Bagno di Romagna",
    "sg:classifiers":[
        {
            "category":"Manufacturing",
            "subcategory":"Metals",
            "type":"Manufacturing & Wholesale Goods"
        }
    ],
    "sg:phone":"+39 0543 918026",
    "sg:postcode":"47021",
    "sg:province":"Forl\u00ec-Cesena",
    "sg:tags":[
        "processing"
    ],
    "wof:name":"Corzani Francesco & C.(s.n.c.)",
    "wof:placetype":"venue"
},
  "geometry": {"coordinates":[11.9781427383,43.8534240723],"type":"Point"}
}