{
  "type": "Feature",
  "properties": {
    "addr:full":"50127 Firenze Firenze Firenze 50127",
    "addr:postcode":"50127;50127",
    "iso:country":"IT",
    "sg:address":"50127 Firenze",
    "sg:city":"Firenze",
    "sg:classifiers":[
        {
            "category":"Professional",
            "subcategory":"Business Services",
            "type":"Services"
        }
    ],
    "sg:phone":"+39 055 437 8490",
    "sg:postcode":"50127",
    "sg:province":"Firenze",
    "sg:tags":[
        "auxiliary",
        "transport"
    ],
    "wof:name":"Carta Aer Rilievi",
    "wof:placetype":"venue"
},
  "geometry": {"coordinates":[11.224044,43.803814],"type":"Point"}
}