{
  "type": "Feature",
  "properties": {
    "iso:country":"IT",
    "sg:address":"39100 Bolzano",
    "sg:city":"Bolzano",
    "sg:orig_category":"Prodotti Chimici Di Base",
    "sg:phone":"+39 0471 978115",
    "sg:postcode":"39100",
    "sg:province":"Bolzano/Bozen",
    "wof:name":"Thaler Srl - Gmbh",
    "wof:placetype":"venue"
},
  "geometry": {"coordinates":[11.3526620865,46.4995918274],"type":"Point"}
}