{
  "type": "Feature",
  "properties": {
    "addr:full":"Via Cassa Di; Genova; 16123 Genova Genova 16123",
    "addr:postcode":"16123;16123",
    "addr:street":"Via Cassa Di Genova",
    "iso:country":"IT",
    "sg:address":"Via Cassa Di; Genova; 16123",
    "sg:city":"Genova",
    "sg:classifiers":[
        {
            "category":"Banks & Credit Unions",
            "subcategory":"Bank",
            "type":"Services"
        }
    ],
    "sg:phone":"+39 010 20911",
    "sg:postcode":"16123",
    "sg:province":"Genova",
    "wof:name":"Cassa Di Risparmio Di Genova, E Imperia",
    "wof:placetype":"venue"
},
  "geometry": {"coordinates":[8.934149,44.408627],"type":"Point"}
}