{
  "type": "Feature",
  "properties": {
    "addr:full":"10125 Torino Torino Torino 10125",
    "addr:postcode":"10125;10125",
    "iso:country":"IT",
    "sg:address":"10125 Torino",
    "sg:city":"Torino",
    "sg:classifiers":[
        {
            "category":"Manufacturing",
            "subcategory":"Leather Goods",
            "type":"Manufacturing & Wholesale Goods"
        }
    ],
    "sg:phone":"+39 011 669 8643",
    "sg:postcode":"10125",
    "sg:province":"Torino",
    "sg:tags":[
        "footwear",
        "skin"
    ],
    "wof:name":"Sales Agency",
    "wof:placetype":"venue"
},
  "geometry": {"coordinates":[7.6810922623,45.0576133728],"type":"Point"}
}