{
  "type": "Feature",
  "properties": {
    "iso:country":"IT",
    "sg:address":"Km. 40.900, Strada St. 131 09025 Sanluri",
    "sg:city":"Sanluri",
    "sg:classifiers":[
        {
            "category":"Farming",
            "subcategory":"Livestock Farm",
            "type":"Manufacturing & Wholesale Goods"
        }
    ],
    "sg:phone":"+39 070 937 1167",
    "sg:postcode":"09025",
    "sg:province":"Medio Campidano",
    "sg:tags":[
        "agriculture"
    ],
    "wof:name":"Consorzio Sardo Cereali",
    "wof:placetype":"venue"
},
  "geometry": {"coordinates":[8.704075,39.531738],"type":"Point"}
}