{
  "type": "Feature",
  "properties": {
    "addr:full":"25070 Casto Casto Brescia 25070",
    "addr:postcode":"25070;25070",
    "iso:country":"IT",
    "sg:address":"25070 Casto",
    "sg:city":"Casto",
    "sg:orig_category":"Acciaierie E Fonderie",
    "sg:phone":"+39 036 588165",
    "sg:postcode":"25070",
    "sg:province":"Brescia",
    "sg:website":"http://www.gsnet.it/fond.pell",
    "wof:name":"Fond Pell Snc Di A. Pellegrini & C.",
    "wof:placetype":"venue"
},
  "geometry": {"coordinates":[10.292157,45.686344],"type":"Point"}
}