{
  "type": "Feature",
  "properties": {
    "iso:country":"IT",
    "sg:address":"23899 Robbiate",
    "sg:city":"Robbiate",
    "sg:orig_category":"Trattamenti Termici E Superficiali Metalli, Galvanotecnica",
    "sg:phone":"+39 039 928 1133",
    "sg:postcode":"23899",
    "sg:province":"Lecco",
    "wof:name":"Aerre Machines Srl",
    "wof:placetype":"venue"
},
  "geometry": {"coordinates":[9.400809,45.692959],"type":"Point"}
}