{
  "type": "Feature",
  "properties": {
    "addr:full":"Via Catalani 45 50050 Cerreto Guidi Cerreto Guidi Firenze 50050",
    "addr:housenumber":"45",
    "addr:postcode":"50050;50050",
    "addr:street":"Via Catalani",
    "iso:country":"IT",
    "sg:address":"Via Catalani 45 50050 Cerreto Guidi",
    "sg:city":"Cerreto Guidi",
    "sg:classifiers":[
        {
            "category":"Train Station",
            "subcategory":"Light Rail",
            "type":"Transportation"
        }
    ],
    "sg:phone":"+39 0571 580101",
    "sg:postcode":"50050",
    "sg:province":"Firenze",
    "sg:tags":[
        "steel",
        "bulk",
        "ibc",
        "container",
        "intermediate"
    ],
    "sg:website":"www.italyexpo.com/vrt",
    "wof:name":"Toscana Inox S.r.l.",
    "wof:placetype":"venue"
},
  "geometry": {"coordinates":[10.881005,43.722481],"type":"Point"}
}