{
  "type": "Feature",
  "properties": {
    "addr:full":"47852 Coriano RN",
    "addr:postcode":"47852",
    "iso:country":"IT",
    "sg:address":"47852 Coriano",
    "sg:orig_category":"Pareti Mobili E Divisorie",
    "sg:phone":"+39 0541 906111",
    "sg:province":"RN",
    "sg:website":"http://www.albiniefontanot.com",
    "wof:name":"Albini & Fontanot Spa",
    "wof:placetype":"venue"
},
  "geometry": {"coordinates":[-87.5587005615,39.1184997559],"type":"Point"}
}