{
  "type": "Feature",
  "properties": {
    "iso:country":"IT",
    "sg:address":"45100 Rovigo",
    "sg:city":"Rovigo",
    "sg:orig_category":"Arredamenti E Mobili Professionali. Complementi Di Arredamento",
    "sg:phone":"+39 0425 24121",
    "sg:postcode":"45100",
    "sg:province":"Rovigo",
    "wof:name":"O.f.f.a.r. Srl",
    "wof:placetype":"venue"
},
  "geometry": {"coordinates":[11.701174,45.049915],"type":"Point"}
}