{
  "type": "Feature",
  "properties": {
    "iso:country":"IT",
    "sg:address":"16, Via S. Giovanni Battista 25030 Pompiano",
    "sg:city":"Pompiano",
    "sg:classifiers":[
        {
            "category":"Farming",
            "subcategory":"Livestock Farm",
            "type":"Manufacturing & Wholesale Goods"
        }
    ],
    "sg:phone":"+39 030 946 0361",
    "sg:postcode":"25030",
    "sg:province":"Brescia",
    "sg:tags":[
        "agriculture"
    ],
    "wof:name":"Cremaschini F.lli S.p.a.",
    "wof:placetype":"venue"
},
  "geometry": {"coordinates":[10.222958,45.539829],"type":"Point"}
}