{
  "type": "Feature",
  "properties": {
    "iso:country":"IT",
    "sg:address":"22060 Figino Serenza",
    "sg:city":"Figino Serenza",
    "sg:orig_category":"Non-classified Establishments",
    "sg:phone":"+39 031 780136",
    "sg:postcode":"22060",
    "sg:province":"Como",
    "sg:website":"http://www.radicemobili.com",
    "wof:name":"Radice Mobili Snc Di Radice Aldo & C.",
    "wof:placetype":"venue"
},
  "geometry": {"coordinates":[9.137767,45.716316],"type":"Point"}
}