{
  "type": "Feature",
  "properties": {
    "iso:country":"IT",
    "sg:address":"53, Piazza Pio Xi 00165 Roma",
    "sg:city":"Roma",
    "sg:classifiers":[
        {
            "category":"Communications",
            "subcategory":"Newspaper",
            "type":"Services"
        }
    ],
    "sg:phone":"+39 39066604811",
    "sg:postcode":"00165",
    "sg:province":"Roma",
    "sg:tags":[
        "advertising"
    ],
    "wof:name":"Roncaglia E Wijkander Roma Srl",
    "wof:placetype":"venue"
},
  "geometry": {"coordinates":[12.437002,41.894211],"type":"Point"}
}