{
  "type": "Feature",
  "properties": {
    "addr:full":"95, Via Circonvallazione 36045 Lonigo Lonigo Vicenza 36045",
    "addr:postcode":"36045;36045",
    "addr:street":"Via Circonvallazione",
    "iso:country":"IT",
    "sg:address":"95, Via Circonvallazione 36045 Lonigo",
    "sg:city":"Lonigo",
    "sg:classifiers":[
        {
            "category":"Wholesale",
            "subcategory":"Drugs",
            "type":"Manufacturing & Wholesale Goods"
        }
    ],
    "sg:phone":"+39 0444 831422",
    "sg:postcode":"36045",
    "sg:province":"Vicenza",
    "sg:tags":[
        "chemical",
        "pharmaceutical"
    ],
    "wof:name":"Loro Fratelli",
    "wof:placetype":"venue"
},
  "geometry": {"coordinates":[11.392275,45.384323],"type":"Point"}
}