{
  "type": "Feature",
  "properties": {
    "iso:country":"IT",
    "sg:address":"52022 Cavriglia",
    "sg:city":"Cavriglia",
    "sg:orig_category":"Trattamenti Termici E Superficiali Metalli, Galvanotecnica",
    "sg:phone":"+39 055 961969",
    "sg:postcode":"52022",
    "sg:province":"Arezzo",
    "wof:name":"F.c. Dei Fratelli Chini Snc",
    "wof:placetype":"venue"
},
  "geometry": {"coordinates":[11.465677,43.569977],"type":"Point"}
}