{
  "type": "Feature",
  "properties": {
    "addr:full":"30, Via Guglielmo Marconi 26046 San Daniele Po San Daniele Po Cremona 26046",
    "addr:postcode":"26046;daniele;26046",
    "addr:street":"Via Guglielmo Marconi;Po",
    "iso:country":"IT",
    "sg:address":"30, Via Guglielmo Marconi 26046 San Daniele Po",
    "sg:city":"San Daniele Po",
    "sg:classifiers":[
        {
            "category":"Professional",
            "subcategory":"Printing & Photocopies",
            "type":"Services"
        }
    ],
    "sg:phone":"+39 39037265645",
    "sg:postcode":"26046",
    "sg:province":"Cremona",
    "wof:name":"Lito - Graf Di Manfredini Fulvia E C. (s.n.c.)",
    "wof:placetype":"venue"
},
  "geometry": {"coordinates":[10.1894626617,45.0620727539],"type":"Point"}
}