{
  "type": "Feature",
  "properties": {
    "iso:country":"IT",
    "sg:address":"80129 Napoli",
    "sg:city":"Napoli",
    "sg:orig_category":"Autoscuole",
    "sg:phone":"+39 081 578 1580",
    "sg:postcode":"80129",
    "sg:province":"Napoli",
    "wof:name":"Autoscuole Isotta",
    "wof:placetype":"venue"
},
  "geometry": {"coordinates":[14.231071,40.848183],"type":"Point"}
}