{
  "type": "Feature",
  "properties": {
    "iso:country":"IT",
    "sg:address":"Allacciante H Zona Industriale 1 66050 San Salvo",
    "sg:city":"San Salvo",
    "sg:classifiers":[
        {
            "category":"Manufacturing",
            "subcategory":"Motor Vehicles & Parts",
            "type":"Manufacturing & Wholesale Goods"
        }
    ],
    "sg:phone":"+39 0873 549345",
    "sg:postcode":"66050",
    "sg:province":"Chieti",
    "sg:tags":[
        "bolts",
        "shaped",
        "component",
        "nuts",
        "dy",
        "carbide",
        "rivets"
    ],
    "sg:website":"www.ilmet-srl.com",
    "wof:name":"Ilmet Srl",
    "wof:placetype":"venue"
},
  "geometry": {"coordinates":[14.167151,42.351791],"type":"Point"}
}