{
  "type": "Feature",
  "properties": {
    "addr:full":"46, Via Dei Cerri 47031 Repubblica Di San Marino SM",
    "addr:postcode":"47031",
    "addr:street":"Via Dei Cerri;Marino",
    "iso:country":"IT",
    "sg:address":"46, Via Dei Cerri 47031 Repubblica Di San Marino",
    "sg:classifiers":[
        {
            "category":"Professional",
            "subcategory":"Engineering",
            "type":"Services"
        }
    ],
    "sg:phone":"+39 0549 904633",
    "sg:province":"SM",
    "sg:tags":[
        "machine",
        "-",
        "mechanical"
    ],
    "wof:name":"Apir Srl",
    "wof:placetype":"venue"
},
  "geometry": {"coordinates":[12.46348,43.970829],"type":"Point"}
}