{
  "type": "Feature",
  "properties": {
    "iso:country":"IT",
    "sg:address":"10148 Torino",
    "sg:city":"Torino",
    "sg:orig_category":"Forniture Per Abbigliamento E Pelletterie",
    "sg:phone":"+39 011 220 0366",
    "sg:postcode":"10148",
    "sg:province":"Torino",
    "wof:name":"Plumex Di Cammilleri C. & C. (s.n.c.)",
    "wof:placetype":"venue"
},
  "geometry": {"coordinates":[7.6829133034,45.1071166992],"type":"Point"}
}