{
  "type": "Feature",
  "properties": {
    "iso:country":"IT",
    "sg:address":"95123 Catania",
    "sg:city":"Catania",
    "sg:orig_category":"Macchine, Impianti Ed Attrezzature Per Abbigliamento E Pelletterie",
    "sg:phone":"+39 095 360372",
    "sg:postcode":"95123",
    "sg:province":"Catania",
    "wof:name":"Di Giovanni Carmelo",
    "wof:placetype":"venue"
},
  "geometry": {"coordinates":[15.068754,37.517979],"type":"Point"}
}