{
  "type": "Feature",
  "properties": {
    "iso:country":"IT",
    "sg:address":"Via Umberto I 133; Oderzo; 30146",
    "sg:classifiers":[
        {
            "category":"Banks & Credit Unions",
            "subcategory":"Bank",
            "type":"Services"
        }
    ],
    "sg:phone":"+39 0422 712515",
    "wof:name":"Cassamaca Spa",
    "wof:placetype":"venue"
},
  "geometry": {"coordinates":[12.494119,45.781105],"type":"Point"}
}