{
  "type": "Feature",
  "properties": {
    "addr:full":"00174 Roma Roma Roma 00174",
    "addr:postcode":"00174;00174",
    "iso:country":"IT",
    "sg:address":"00174 Roma",
    "sg:city":"Roma",
    "sg:orig_category":"Fiorai - Accessori E Forniture",
    "sg:phone":"+39 06 7154 3149",
    "sg:postcode":"00174",
    "sg:province":"Roma",
    "wof:name":"Il Fiore Di Attura Stefania",
    "wof:placetype":"venue"
},
  "geometry": {"coordinates":[12.5609903336,41.8552856445],"type":"Point"}
}