{
  "type": "Feature",
  "properties": {
    "iso:country":"IT",
    "sg:address":"20121 Milano",
    "sg:city":"Milano",
    "sg:orig_category":"Chiese Ed Associazioni Religiose",
    "sg:phone":"+39 02 657 1420",
    "sg:postcode":"20121",
    "sg:province":"Milano",
    "wof:name":"Provincia Di Lombardia S.carlo Borromeo Dei Frati Minori",
    "wof:placetype":"venue"
},
  "geometry": {"coordinates":[9.192266,45.475903],"type":"Point"}
}