{
  "type": "Feature",
  "properties": {
    "iso:country":"IT",
    "sg:address":"93016 Riesi",
    "sg:city":"Riesi",
    "sg:classifiers":[
        {
            "category":"Health Services",
            "subcategory":"Health Practitioner",
            "type":"Services"
        }
    ],
    "sg:phone":"+39 0934 921048",
    "sg:postcode":"93016",
    "sg:province":"Caltanissetta",
    "sg:tags":[
        "medici"
    ],
    "wof:name":"Rindone Felice",
    "wof:placetype":"venue"
},
  "geometry": {"coordinates":[14.0871562958,37.2787628174],"type":"Point"}
}