{
  "type": "Feature",
  "properties": {
    "iso:country":"IT",
    "sg:address":"85029 Venosa",
    "sg:city":"Venosa",
    "sg:orig_category":"Studi E Consulenze Legali E Notarili. Avvocati, Notai E Servizi Legali. Professionisti - Studi E Servizi Ed Associazioni Di Interesse Aziendale",
    "sg:phone":"+39 0972 31989",
    "sg:postcode":"85029",
    "sg:province":"Potenza",
    "wof:name":"Fuccilo Avv. Marisa",
    "wof:placetype":"venue"
},
  "geometry": {"coordinates":[15.813628,40.964138],"type":"Point"}
}