{
  "type": "Feature",
  "properties": {
    "addr:full":"115, Via Ponte A Giogoli 50019 Sesto Fiorentino Ponte a giogoli Firenze 50019",
    "addr:housenumber":"115",
    "addr:postcode":"50019;50019",
    "addr:street":"Via Ponte A Giogoli;Giogoli",
    "iso:country":"IT",
    "sg:address":"115, Via Ponte A Giogoli 50019 Sesto Fiorentino",
    "sg:city":"Ponte a giogoli",
    "sg:classifiers":[
        {
            "category":"Communications",
            "subcategory":"Newspaper",
            "type":"Services"
        }
    ],
    "sg:phone":"+39 39055316853",
    "sg:postcode":"50019",
    "sg:province":"Firenze",
    "sg:tags":[
        "advertising"
    ],
    "wof:name":"Albatros International Graphics (s.r.l.)",
    "wof:placetype":"venue"
},
  "geometry": {"coordinates":[11.187308,43.805256],"type":"Point"}
}