{
  "type": "Feature",
  "properties": {
    "iso:country":"IT",
    "sg:address":"20098 San Giuliano Milanese",
    "sg:city":"San Giuliano Milanese",
    "sg:orig_category":"Cartotecnica E Servizi. Prodotti E Manufatti In Materie Plastiche. Articoli Per Imballaggio E Confezionamento",
    "sg:phone":"+39 02 9828 0020",
    "sg:postcode":"20098",
    "sg:province":"Milano",
    "wof:name":"Facover (s.r.l.)",
    "wof:placetype":"venue"
},
  "geometry": {"coordinates":[9.253379,45.397606],"type":"Point"}
}