{
  "type": "Feature",
  "properties": {
    "iso:country":"IT",
    "sg:address":"63033 Centobuchi",
    "sg:city":"Centobuchi",
    "sg:orig_category":"Forniture E Materiali Per Imballaggio E Confezionamento",
    "sg:phone":"+39 0735 701663",
    "sg:postcode":"63033",
    "sg:province":"Ascoli Piceno",
    "wof:name":"Cip Adriatica S.r.l.",
    "wof:placetype":"venue"
},
  "geometry": {"coordinates":[13.8654937744,42.8989486694],"type":"Point"}
}