{
  "type": "Feature",
  "properties": {
    "addr:full":"Via Calestano 154 43035 Felino Felino Parma 43035",
    "addr:housenumber":"154",
    "addr:postcode":"43035;43035",
    "addr:street":"Via Calestano",
    "iso:country":"IT",
    "sg:address":"Via Calestano 154 43035 Felino",
    "sg:city":"Felino",
    "sg:classifiers":[
        {
            "category":"Food & Beverages",
            "subcategory":"Meat & Fish",
            "type":"Retail Goods"
        }
    ],
    "sg:phone":"+39 0521 830501",
    "sg:postcode":"43035",
    "sg:province":"Parma",
    "sg:tags":[
        "bacon",
        "ham"
    ],
    "wof:name":"Prosciuttificio Del Colle Srl",
    "wof:placetype":"venue"
},
  "geometry": {"coordinates":[10.235165,44.701771],"type":"Point"}
}