{
  "type": "Feature",
  "properties": {
    "addr:full":"20122 Milano Milano Milano 20122",
    "addr:postcode":"20122;20122",
    "iso:country":"IT",
    "sg:address":"20122 Milano",
    "sg:city":"Milano",
    "sg:orig_category":"Macchine, Impianti Ed Attrezzature Per Abbigliamento E Pelletterie",
    "sg:phone":"+39 02 7602 0180",
    "sg:postcode":"20122",
    "sg:province":"Milano",
    "wof:name":"Wolfsbergen Osnabrug Baars Srl",
    "wof:placetype":"venue"
},
  "geometry": {"coordinates":[9.205992,45.464981],"type":"Point"}
}