{
  "type": "Feature",
  "properties": {
    "iso:country":"IT",
    "sg:address":"Via Roma Loc. Grotta 84010 Minori",
    "sg:city":"Minori",
    "sg:classifiers":[
        {
            "category":"Food & Beverages",
            "subcategory":"Fruits & Vegetables",
            "type":"Retail Goods"
        }
    ],
    "sg:phone":"+39 089 851126",
    "sg:postcode":"84010",
    "sg:province":"Salerno",
    "wof:name":"Lemon Sud Srl",
    "wof:placetype":"venue"
},
  "geometry": {"coordinates":[14.765912056,40.6779556274],"type":"Point"}
}