{
  "type": "Feature",
  "properties": {
    "addr:full":"56127 Pisa Pisa Pisa 56127",
    "addr:postcode":"56127;56127",
    "iso:country":"IT",
    "sg:address":"56127 Pisa",
    "sg:city":"Pisa",
    "sg:orig_category":"Universita' Ed Istituti Superiori E Liberi",
    "sg:phone":"+39 050 883111",
    "sg:postcode":"56127",
    "sg:province":"Pisa",
    "sg:website":"http://www.sssup.it",
    "wof:name":"Scuola Superiore Di Studi Universitari E Di Perfezionamento S. Anna",
    "wof:placetype":"venue"
},
  "geometry": {"coordinates":[10.40224,43.721298],"type":"Point"}
}