{
  "type": "Feature",
  "properties": {
    "addr:full":"11, Via Milano 29010 Calendasco Calendasco Piacenza 29010",
    "addr:postcode":"29010;29010",
    "addr:street":"Via Milano",
    "iso:country":"IT",
    "sg:address":"11, Via Milano 29010 Calendasco",
    "sg:city":"Calendasco",
    "sg:classifiers":[
        {
            "category":"Manufacturing",
            "subcategory":"Metals",
            "type":"Manufacturing & Wholesale Goods"
        }
    ],
    "sg:phone":"+39 0523 760575",
    "sg:postcode":"29010",
    "sg:province":"Piacenza",
    "sg:tags":[
        "processing"
    ],
    "wof:name":"Menel & Ambroggi",
    "wof:placetype":"venue"
},
  "geometry": {"coordinates":[9.6281099319,45.0596847534],"type":"Point"}
}