{
  "type": "Feature",
  "properties": {
    "iso:country":"IT",
    "sg:address":"Via Toscana 52 56030 Perignano",
    "sg:classifiers":[
        {
            "category":"Utilities",
            "subcategory":"Natural Gas",
            "type":"Services"
        }
    ],
    "sg:phone":"+39 0587 616385",
    "sg:postcode":"56030",
    "sg:province":"Pisa",
    "sg:tags":[
        "mechanics",
        "precision"
    ],
    "wof:name":"E.t.engineering Technology Srl",
    "wof:placetype":"venue"
},
  "geometry": {"coordinates":[10.3965845108,43.7161369324],"type":"Point"}
}