{
  "type": "Feature",
  "properties": {
    "iso:country":"IT",
    "sg:address":"Via Pomezia, 14 - Porto D'ascoli 63039 San Benedetto Del Tronto",
    "sg:city":"San Benedetto del Tronto",
    "sg:classifiers":[
        {
            "category":"Food & Beverages",
            "subcategory":"Fruits & Vegetables",
            "type":"Retail Goods"
        }
    ],
    "sg:phone":"+39 0735 7541",
    "sg:postcode":"63039",
    "sg:province":"Ascoli Piceno",
    "sg:tags":[
        "frozen"
    ],
    "wof:name":"Soc.coop. Fra Produttori Ortofrutticoli Del Piceno Srl",
    "wof:placetype":"venue"
},
  "geometry": {"coordinates":[13.8958749771,42.9055900574],"type":"Point"}
}