{
  "type": "Feature",
  "properties": {
    "addr:full":"21052 Busto Arsizio Busto Arsizio Varese 21052",
    "addr:postcode":"21052;21052",
    "iso:country":"IT",
    "sg:address":"21052 Busto Arsizio",
    "sg:city":"Busto Arsizio",
    "sg:orig_category":"Materie Plastiche Articoli Tecnici",
    "sg:phone":"+39 0331 324232",
    "sg:postcode":"21052",
    "sg:province":"Varese",
    "wof:name":"Skyline Di Luigi Besnati",
    "wof:placetype":"venue"
},
  "geometry": {"coordinates":[8.845797,45.608871],"type":"Point"}
}