{
  "type": "Feature",
  "properties": {
    "iso:country":"IT",
    "sg:address":"80054 Gragnano",
    "sg:city":"Gragnano",
    "sg:orig_category":"Servizi E Lavori Industria Chimica. Trattamenti Termici E Superficiali Metalli, Galvanotecnica",
    "sg:phone":"+39 081 871 9741",
    "sg:postcode":"80054",
    "sg:province":"Napoli",
    "wof:name":"Airtop Srl",
    "wof:placetype":"venue"
},
  "geometry": {"coordinates":[14.521246,40.68985],"type":"Point"}
}