{
  "type": "Feature",
  "properties": {
    "iso:country":"IT",
    "sg:address":"33087 Pasiano Di Pordenone",
    "sg:city":"Pasiano",
    "sg:orig_category":"Serramenti Ed Infissi. Prodotti Vari In Metallo",
    "sg:phone":"+39 0434 626179",
    "sg:postcode":"33087",
    "sg:province":"Pordenone",
    "sg:website":"http://www.pavarin.it",
    "wof:name":"Pavarin Fratelli Snc",
    "wof:placetype":"venue"
},
  "geometry": {"coordinates":[12.586297,45.844391],"type":"Point"}
}