{
  "type": "Feature",
  "properties": {
    "iso:country":"IT",
    "sg:address":"30175 Mestre",
    "sg:city":"Mestre",
    "sg:orig_category":"Accessori Moda D'abbigliamento. Shopping",
    "sg:phone":"+39 041 951140",
    "sg:postcode":"30175",
    "sg:province":"Venezia",
    "wof:name":"Cappelleria Barbiero Di Barbiero Alessandra E C. (s.a.s.)",
    "wof:placetype":"venue"
},
  "geometry": {"coordinates":[12.240539,45.490822],"type":"Point"}
}