{
  "type": "Feature",
  "properties": {
    "addr:full":"Via Molinetto 4/a; Longastrino; 44014 Longastrino Ferrara 44014",
    "addr:housenumber":"4 / a",
    "addr:postcode":"44014;44014",
    "addr:street":"Via Molinetto;Longastrino",
    "iso:country":"IT",
    "sg:address":"Via Molinetto 4/a; Longastrino; 44014",
    "sg:city":"Longastrino",
    "sg:classifiers":[
        {
            "category":"Banks & Credit Unions",
            "subcategory":"Bank",
            "type":"Services"
        }
    ],
    "sg:phone":"+39 0532 806005",
    "sg:postcode":"44014",
    "sg:province":"Ferrara",
    "wof:name":"Rolo Banca 1473 Spa",
    "wof:placetype":"venue"
},
  "geometry": {"coordinates":[12.008566,44.587833],"type":"Point"}
}