{
  "type": "Feature",
  "properties": {
    "addr:full":"80134 Napoli Napoli Napoli 80134",
    "addr:housenumber":"80134",
    "addr:postcode":"80134",
    "iso:country":"IT",
    "sg:address":"80134 Napoli",
    "sg:city":"Napoli",
    "sg:orig_category":"Ponteggi Per Edilizia",
    "sg:phone":"+39 081 551 4347",
    "sg:postcode":"80134",
    "sg:province":"Napoli",
    "wof:name":"De Chiara Ciro",
    "wof:placetype":"venue"
},
  "geometry": {"coordinates":[14.2482585907,40.8460922241],"type":"Point"}
}