{
  "type": "Feature",
  "properties": {
    "iso:country":"IT",
    "sg:address":"13, V. Delle Valli 10074 Lanzo",
    "sg:classifiers":[
        {
            "category":"Manufacturing",
            "subcategory":"Rubber & Plastics",
            "type":"Manufacturing & Wholesale Goods"
        }
    ],
    "sg:phone":"+39 0123 320471",
    "sg:postcode":"10074",
    "sg:province":"Torino",
    "sg:website":"http://www.thermofibers.it:ws_end: :mark:ws:http://www.paginegialle.it/thfibers",
    "wof:name":"Thermofibers Srl",
    "wof:placetype":"venue"
},
  "geometry": {"coordinates":[7.686619,45.07056],"type":"Point"}
}