{
  "type": "Feature",
  "properties": {
    "iso:country":"IT",
    "sg:address":"80025 Casandrino",
    "sg:city":"Casandrino",
    "sg:orig_category":"Forniture Per Abbigliamento E Pelletterie",
    "sg:phone":"+39 081 505 7483",
    "sg:postcode":"80025",
    "sg:province":"Napoli",
    "wof:name":"Onorato Ciro E Figli S.r.l.",
    "wof:placetype":"venue"
},
  "geometry": {"coordinates":[14.2443284988,40.9160575867],"type":"Point"}
}