{
  "type": "Feature",
  "properties": {
    "iso:country":"IT",
    "sg:address":"20145 Milano",
    "sg:city":"Milano",
    "sg:orig_category":"Servizi E Lavori Per Agricoltura E Zootecnia. Servizi E Lavori Per Ecologia E Smaltimento Rifiuti",
    "sg:phone":"+39 02 485 6131",
    "sg:postcode":"20145",
    "sg:province":"Milano",
    "wof:name":"Consorzio Di Bonifica Est - Ticino Villoresi",
    "wof:placetype":"venue"
},
  "geometry": {"coordinates":[9.166282,45.470844],"type":"Point"}
}