{
  "type": "Feature",
  "properties": {
    "iso:country":"IT",
    "sg:address":"22040 Alzate Brianza",
    "sg:city":"Alzate Brianza",
    "sg:orig_category":"Tempo Libero - Articoli E Forniture. Forniture Per Congressi, Fiere E Manifestazioni. Regalistica Aziendale",
    "sg:phone":"+39 031 619408",
    "sg:postcode":"22040",
    "sg:province":"Como",
    "wof:name":"Publiline Moda E Promozione Srl",
    "wof:placetype":"venue"
},
  "geometry": {"coordinates":[9.183129,45.770798],"type":"Point"}
}