{
  "type": "Feature",
  "properties": {
    "iso:country":"IT",
    "sg:address":"27029 Vigevano",
    "sg:city":"Vigevano",
    "sg:orig_category":"Calzaturifici E Calzolai - Forniture",
    "sg:phone":"+39 0381 344109",
    "sg:postcode":"27029",
    "sg:province":"Pavia",
    "wof:name":"Fustellificio Ellepi Snc Di Lo Presti Luigi E C.",
    "wof:placetype":"venue"
},
  "geometry": {"coordinates":[8.867179,45.303989],"type":"Point"}
}