{
  "type": "Feature",
  "properties": {
    "iso:country":"IT",
    "sg:address":"50, Via Fosse Ardeatine 20020 Busto Garolfo",
    "sg:city":"Busto Garolfo",
    "sg:classifiers":[
        {
            "category":"Professional",
            "subcategory":"Printing & Photocopies",
            "type":"Services"
        }
    ],
    "sg:phone":"+39 0331 569639",
    "sg:postcode":"20020",
    "sg:province":"Milano",
    "wof:name":"Effepi S.r.l.",
    "wof:placetype":"venue"
},
  "geometry": {"coordinates":[8.8955068588,45.5464859009],"type":"Point"}
}