{
  "type": "Feature",
  "properties": {
    "iso:country":"IT",
    "sg:address":"20010 Cornaredo",
    "sg:city":"Cornaredo",
    "sg:orig_category":"Calamite E Magneti Permanenti",
    "sg:phone":"+39 02 9356 9361",
    "sg:postcode":"20010",
    "sg:province":"Milano",
    "wof:name":"R.a.m. Sas",
    "wof:placetype":"venue"
},
  "geometry": {"coordinates":[9.035937,45.484833],"type":"Point"}
}