{
  "type": "Feature",
  "properties": {
    "addr:full":"55043 Lido Di Camaiore LU",
    "addr:postcode":"55043",
    "iso:country":"IT",
    "sg:address":"55043 Lido Di Camaiore",
    "sg:classifiers":[
        {
            "category":"Manufacturing",
            "subcategory":"Building Materials",
            "type":"Manufacturing & Wholesale Goods"
        }
    ],
    "sg:phone":"+39 0584 618855",
    "sg:province":"LU",
    "sg:tags":[
        "semi-finished",
        "wood",
        "products"
    ],
    "wof:name":"Atla Snc",
    "wof:placetype":"venue"
},
  "geometry": {"coordinates":[-92.773003,44.943115],"type":"Point"}
}