{
  "type": "Feature",
  "properties": {
    "iso:country":"IT",
    "sg:address":"21052 Busto Arsizio",
    "sg:city":"Busto Arsizio",
    "sg:orig_category":"Tessuti Arredamento - Vendita Al Dettaglio",
    "sg:phone":"+39 0331 599654",
    "sg:postcode":"21052",
    "sg:province":"Varese",
    "wof:name":"C.f.t. Crespi Filitessuti Srl",
    "wof:placetype":"venue"
},
  "geometry": {"coordinates":[8.840352,45.590649],"type":"Point"}
}