{
  "type": "Feature",
  "properties": {
    "addr:full":"63017 Porto San Giorgio Porto San Giorgio Ascoli Piceno 63017",
    "addr:postcode":"63017;63017",
    "addr:street":"Piceno",
    "iso:country":"IT",
    "sg:address":"63017 Porto San Giorgio",
    "sg:city":"Porto San Giorgio",
    "sg:orig_category":"Climatizzazione E Condizionamento, Apparecchiature E Servizi. Elettrodomestici",
    "sg:phone":"+39 0734 677825",
    "sg:postcode":"63017",
    "sg:province":"Ascoli Piceno",
    "wof:name":"Tecnoclima Snc",
    "wof:placetype":"venue"
},
  "geometry": {"coordinates":[13.79195,43.187519],"type":"Point"}
}