{
  "type": "Feature",
  "properties": {
    "addr:full":"91020 Petrosino Petrosino Trapani 91020",
    "addr:postcode":"91020;91020",
    "iso:country":"IT",
    "sg:address":"91020 Petrosino",
    "sg:city":"Petrosino",
    "sg:classifiers":[
        {
            "category":"Health Services",
            "subcategory":"Health Practitioner",
            "type":"Services"
        }
    ],
    "sg:phone":"+39 0923 985505",
    "sg:postcode":"91020",
    "sg:province":"Trapani",
    "sg:tags":[
        "medici"
    ],
    "wof:name":"Vultaggio Pietro",
    "wof:placetype":"venue"
},
  "geometry": {"coordinates":[12.5011167526,37.7088890076],"type":"Point"}
}