{
  "type": "Feature",
  "properties": {
    "iso:country":"IT",
    "sg:address":"Via Dell'industria 17 33028 Tolmezzo",
    "sg:city":"Tolmezzo",
    "sg:classifiers":[
        {
            "category":"Communications",
            "subcategory":"Film & Video Production",
            "type":"Services"
        }
    ],
    "sg:phone":"+39 0433 4891",
    "sg:postcode":"33028",
    "sg:province":"Udine",
    "sg:tags":[
        "plate",
        "light",
        "car",
        "signal",
        "number",
        "turn",
        "tail",
        "brake",
        "registration"
    ],
    "sg:website":"www.seimaitaliana.it",
    "wof:name":"Seima Italiana Spa",
    "wof:placetype":"venue"
},
  "geometry": {"coordinates":[13.029737,46.390812],"type":"Point"}
}