{
  "type": "Feature",
  "properties": {
    "iso:country":"IT",
    "sg:address":"21029 Vergiate",
    "sg:city":"Vergiate",
    "sg:orig_category":"Accessori Moda D'abbigliamento. Forniture Per Abbigliamento E Pelletterie",
    "sg:phone":"+39 0331 948313",
    "sg:postcode":"21029",
    "sg:province":"Varese",
    "wof:name":"Fiore Agostino",
    "wof:placetype":"venue"
},
  "geometry": {"coordinates":[8.821637,45.82127],"type":"Point"}
}