{
  "type": "Feature",
  "properties": {
    "iso:country":"IT",
    "sg:address":"20159 Milano",
    "sg:city":"Milano",
    "sg:orig_category":"Scuole E Servizi Scolastici. Ricerca, Selezione E Formazione Del Personale. Pubblica Amministrazione",
    "sg:phone":"+39 02 680397",
    "sg:postcode":"20159",
    "sg:province":"Milano",
    "wof:name":"Scuola Media Statale Via Maffucci-pavoni",
    "wof:placetype":"venue"
},
  "geometry": {"coordinates":[9.220072,45.49308],"type":"Point"}
}