{
  "type": "Feature",
  "properties": {
    "iso:country":"IT",
    "sg:address":"Viale Appennino 606/b 47100 Forli'",
    "sg:classifiers":[
        {
            "category":"Building & Trades",
            "subcategory":"Construction",
            "type":"Services"
        }
    ],
    "sg:phone":"+39 0543 86066",
    "sg:postcode":"47100",
    "sg:province":"Forl\u00ec-Cesena",
    "sg:tags":[
        "carpenter's",
        "work",
        "supraregional"
    ],
    "sg:website":"www.rinieri.com",
    "wof:name":"Rinieri Srl",
    "wof:placetype":"venue"
},
  "geometry": {"coordinates":[12.01979,44.172779],"type":"Point"}
}