{
  "type": "Feature",
  "properties": {
    "iso:country":"IT",
    "sg:address":"39100 Bolzano",
    "sg:city":"Bolzano",
    "sg:orig_category":"Banche E Servizi Finanziari",
    "sg:phone":"+39 0471 231111",
    "sg:postcode":"39100",
    "sg:province":"Bolzano/Bozen",
    "sg:website":"http://www.caribz.com",
    "wof:name":"Cassa Di Risparmio Di Bolzano Spa",
    "wof:placetype":"venue"
},
  "geometry": {"coordinates":[11.349211,46.499203],"type":"Point"}
}