{
  "type": "Feature",
  "properties": {
    "iso:country":"IT",
    "sg:address":"21042 Caronno Pertusella",
    "sg:city":"Caronno Pertusella",
    "sg:orig_category":"Campeggio. Automobili E Mezzi Di Trasporto",
    "sg:phone":"+39 02 965 9464",
    "sg:postcode":"21042",
    "sg:province":"Varese",
    "wof:name":"Camping Market Snc",
    "wof:placetype":"venue"
},
  "geometry": {"coordinates":[9.046478,45.592075],"type":"Point"}
}