{
  "type": "Feature",
  "properties": {
    "addr:full":"37021 Valdiporro Verona 37021",
    "addr:postcode":"37021;37021",
    "iso:country":"IT",
    "sg:address":"37021 Valdiporro",
    "sg:orig_category":"Alberghi E Strutture Extra Alberghiere. Ospedali E Servizi Sanitari",
    "sg:phone":"+39 045 705 0145",
    "sg:postcode":"37021",
    "sg:province":"Verona",
    "wof:name":"Casa Soggiorno Alpino Villafranca",
    "wof:placetype":"venue"
},
  "geometry": {"coordinates":[11.053668,45.624771],"type":"Point"}
}