{
  "type": "Feature",
  "properties": {
    "iso:country":"IT",
    "sg:address":"27029 Vigevano",
    "sg:city":"Vigevano",
    "sg:orig_category":"Calzaturifici E Calzolai - Macchine",
    "sg:phone":"+39 0381 345513",
    "sg:postcode":"27029",
    "sg:province":"Pavia",
    "wof:name":"Reces Officina Meccanica Snc",
    "wof:placetype":"venue"
},
  "geometry": {"coordinates":[9.176633,45.196293],"type":"Point"}
}