{
  "type": "Feature",
  "properties": {
    "addr:full":"00144 Roma Roma Roma 00144",
    "addr:postcode":"00144;00144",
    "iso:country":"IT",
    "sg:address":"00144 Roma",
    "sg:city":"Roma",
    "sg:orig_category":"Studi E Consulenze Amministrative, Commerciali E Aziendali. Consulenze Tecniche, Amministrative E Perizie",
    "sg:phone":"+39 06 529 8582",
    "sg:postcode":"00144",
    "sg:province":"Roma",
    "sg:website":"http://www.specialfarma.com",
    "wof:name":"Specialfarma Srl",
    "wof:placetype":"venue"
},
  "geometry": {"coordinates":[12.450677,41.818623],"type":"Point"}
}