{
  "type": "Feature",
  "properties": {
    "addr:full":"Via Alcide De Gasperi 50 52037 Sansepolcro Sansepolcro Arezzo 52037",
    "addr:housenumber":"50",
    "addr:postcode":"52037;52037",
    "addr:street":"Via Alcide De Gasperi",
    "iso:country":"IT",
    "sg:address":"Via Alcide De Gasperi 50 52037 Sansepolcro",
    "sg:city":"Sansepolcro",
    "sg:classifiers":[
        {
            "category":"Banks & Credit Unions",
            "subcategory":"Investment Brokerage",
            "type":"Services"
        }
    ],
    "sg:phone":"+39 0575 720420",
    "sg:postcode":"52037",
    "sg:province":"Arezzo",
    "sg:tags":[
        "casting"
    ],
    "sg:website":"www.fonderiabiagiotti.it",
    "wof:name":"Fonderia Biagiotti Srl",
    "wof:placetype":"venue"
},
  "geometry": {"coordinates":[12.114513,43.554981],"type":"Point"}
}