{
  "type": "Feature",
  "properties": {
    "addr:full":"20080 Basiglio Basiglio Milano 20080",
    "addr:postcode":"20080;20080",
    "iso:country":"IT",
    "sg:address":"20080 Basiglio",
    "sg:city":"Basiglio",
    "sg:orig_category":"Professionisti - Studi E Servizi Ed Associazioni Di Interesse Aziendale. Associazioni Ed Organismi Di Interesse Pubblico",
    "sg:phone":"+39 02 9075 5286",
    "sg:postcode":"20080",
    "sg:province":"Milano",
    "wof:name":"Club Basiglio-forza Italia",
    "wof:placetype":"venue"
},
  "geometry": {"coordinates":[9.1644468307,45.3491897583],"type":"Point"}
}