{
  "type": "Feature",
  "properties": {
    "iso:country":"IT",
    "sg:address":"39042 Bressanone",
    "sg:city":"Bressanone",
    "sg:orig_category":"Accessori Moda D'abbigliamento. Shopping",
    "sg:phone":"+39 0472 200187",
    "sg:postcode":"39042",
    "sg:province":"Bolzano/Bozen",
    "wof:name":"Hutstuebele Ohg Des Michael Pranter Und Der Waltraud Oberkofler",
    "wof:placetype":"venue"
},
  "geometry": {"coordinates":[11.656677,46.718147],"type":"Point"}
}