{
  "type": "Feature",
  "properties": {
    "iso:country":"IT",
    "sg:address":"23827 Lierna",
    "sg:city":"Lierna",
    "sg:orig_category":"Cartotecnica E Servizi. Forniture Per Attivita' Commerciali Ed Artigianali",
    "sg:phone":"+39 0341 740238",
    "sg:postcode":"23827",
    "sg:province":"Lecco",
    "wof:name":"Mea (s.n.c.)",
    "wof:placetype":"venue"
},
  "geometry": {"coordinates":[9.306336,45.957535],"type":"Point"}
}