{
  "type": "Feature",
  "properties": {
    "addr:full":"53036 Poggibonsi Poggibonsi Siena 53036",
    "addr:postcode":"53036;53036",
    "iso:country":"IT",
    "sg:address":"53036 Poggibonsi",
    "sg:city":"Poggibonsi",
    "sg:orig_category":"Arredamenti E Mobili Professionali. Arredi Ed Attrezzature Per Uffici",
    "sg:phone":"+39 0577 988021",
    "sg:postcode":"53036",
    "sg:province":"Siena",
    "sg:website":"http://www.sedex.it",
    "wof:name":"Sedex Srl",
    "wof:placetype":"venue"
},
  "geometry": {"coordinates":[11.106259,43.457352],"type":"Point"}
}