{
  "type": "Feature",
  "properties": {
    "iso:country":"IT",
    "sg:address":"21100 Varese",
    "sg:city":"Varese",
    "sg:orig_category":"Ricerca, Selezione E Formazione Del Personale",
    "sg:phone":"+39 0332 831592",
    "sg:postcode":"21100",
    "sg:province":"Varese",
    "wof:name":"Progetto Lavoro Scarl",
    "wof:placetype":"venue"
},
  "geometry": {"coordinates":[8.831708,45.817516],"type":"Point"}
}