{
  "type": "Feature",
  "properties": {
    "addr:full":"692/a, Via Giacomo Matteotti 51036 Larciano Larciano Pistoia 51036",
    "addr:housenumber":"692 / a",
    "addr:postcode":"51036;51036",
    "addr:street":"Via Giacomo Matteotti",
    "iso:country":"IT",
    "sg:address":"692/a, Via Giacomo Matteotti 51036 Larciano",
    "sg:city":"Larciano",
    "sg:classifiers":[
        {
            "category":"Manufacturing",
            "subcategory":"Rubber & Plastics",
            "type":"Manufacturing & Wholesale Goods"
        }
    ],
    "sg:phone":"+39 0573 838676",
    "sg:postcode":"51036",
    "sg:province":"Pistoia",
    "wof:name":"Plastic Products Srl",
    "wof:placetype":"venue"
},
  "geometry": {"coordinates":[10.9151849747,43.8689804077],"type":"Point"}
}