{
  "type": "Feature",
  "properties": {
    "iso:country":"IT",
    "sg:address":"8, Via Pinturicchio 20060 Mediglia",
    "sg:city":"Mediglia",
    "sg:classifiers":[
        {
            "category":"Wholesale",
            "subcategory":"Machinery & Supplies",
            "type":"Manufacturing & Wholesale Goods"
        }
    ],
    "sg:phone":"+39 02 9068 8001",
    "sg:postcode":"20060",
    "sg:province":"Milano",
    "sg:tags":[
        "equipment",
        "-",
        "instrument",
        "measurement"
    ],
    "wof:name":"Zenith Bilance S.r.l.",
    "wof:placetype":"venue"
},
  "geometry": {"coordinates":[9.366148,45.422943],"type":"Point"}
}