{
  "type": "Feature",
  "properties": {
    "iso:country":"IT",
    "sg:address":"20122 Milano",
    "sg:city":"Milano",
    "sg:orig_category":"Abbigliamento Esterno, Maglierie E Pelliccerie. Shopping",
    "sg:phone":"+39 02 545 4232",
    "sg:postcode":"20122",
    "sg:province":"Milano",
    "wof:name":"Ricci 1965 Di Francesco Ricci & C. S.a.s.",
    "wof:placetype":"venue"
},
  "geometry": {"coordinates":[9.202466,45.46088],"type":"Point"}
}