{
  "type": "Feature",
  "properties": {
    "iso:country":"IT",
    "sg:address":"22070 Grandate",
    "sg:city":"Grandate",
    "sg:orig_category":"Tessuti E Stoffe. Filati E Materie Prime Tessili",
    "sg:phone":"+39 031 455111",
    "sg:postcode":"22070",
    "sg:province":"Como",
    "wof:name":"Clerici Tessuto & C. Spa",
    "wof:placetype":"venue"
},
  "geometry": {"coordinates":[9.060966,45.775661],"type":"Point"}
}