{
  "type": "Feature",
  "properties": {
    "iso:country":"IT",
    "sg:address":"Zona Industriale 3 39052 Caldaro Sulla Strada Del Vino",
    "sg:city":"Caldaro sulla strada del vino",
    "sg:orig_category":"Direct Voltage Converters Dc/dc Converters For Vehicles And Ships",
    "sg:phone":"+39 0471 962255",
    "sg:postcode":"39052",
    "sg:province":"Bolzano/Bozen",
    "sg:website":"www.elektra.it",
    "wof:name":"Elektra Srl",
    "wof:placetype":"venue"
},
  "geometry": {"coordinates":[11.26434,46.460331],"type":"Point"}
}