{
  "type": "Feature",
  "properties": {
    "iso:country":"IT",
    "sg:address":"04012 Cisterna Di Latina",
    "sg:city":"Cisterna di Latina",
    "sg:orig_category":"Sport - Articoli E Forniture",
    "sg:phone":"+39 06 9687 2090",
    "sg:postcode":"04012",
    "sg:province":"Latina",
    "wof:name":"G.d. Sport 2000 Di Grassi Daniele",
    "wof:placetype":"venue"
},
  "geometry": {"coordinates":[12.828477,41.575401],"type":"Point"}
}