{
  "type": "Feature",
  "properties": {
    "iso:country":"IT",
    "sg:address":"Via Del Mare 125 00040 Pomezia",
    "sg:city":"Pomezia",
    "sg:classifiers":[
        {
            "category":"Landmark",
            "subcategory":"Archaeological Site",
            "type":"Public Place"
        }
    ],
    "sg:phone":"+39 06 912491",
    "sg:postcode":"00040",
    "sg:province":"Roma",
    "sg:tags":[
        "reagent",
        "analysis"
    ],
    "wof:name":"Radim Spa",
    "wof:placetype":"venue"
},
  "geometry": {"coordinates":[12.484503,41.655605],"type":"Point"}
}