{
  "type": "Feature",
  "properties": {
    "iso:country":"IT",
    "sg:address":"31015 Conegliano",
    "sg:city":"Conegliano",
    "sg:orig_category":"Cartotecnica E Servizi. Prodotti E Manufatti In Materie Plastiche. Articoli Per Imballaggio E Confezionamento",
    "sg:phone":"+39 0438 451977",
    "sg:postcode":"31015",
    "sg:province":"Treviso",
    "sg:website":"http://www.piqusrl.it",
    "wof:name":"Pi.qu Srl",
    "wof:placetype":"venue"
},
  "geometry": {"coordinates":[12.300653,45.880432],"type":"Point"}
}