{
  "type": "Feature",
  "properties": {
    "iso:country":"IT",
    "sg:address":"00122 Lido Di Ostia",
    "sg:orig_category":"Servizi Per Lo Sport E Il Tempo Libero. Alberghi E Strutture Extra Alberghiere",
    "sg:phone":"+39 06 5647 0652",
    "sg:postcode":"00122",
    "sg:province":"Roma",
    "wof:name":"Nauticlub Castelfusano",
    "wof:placetype":"venue"
},
  "geometry": {"coordinates":[12.328744,41.710743],"type":"Point"}
}