{
  "type": "Feature",
  "properties": {
    "addr:full":"46019 Viadana Viadana Mantova 46019",
    "addr:postcode":"46019;46019",
    "iso:country":"IT",
    "sg:address":"46019 Viadana",
    "sg:city":"Viadana",
    "sg:classifiers":[
        {
            "category":"Home & Garden",
            "subcategory":"Kitchen Supply",
            "type":"Retail Goods"
        }
    ],
    "sg:phone":"+39 0375 785912",
    "sg:postcode":"46019",
    "sg:province":"Mantova",
    "sg:tags":[
        "utensil",
        "houseware"
    ],
    "sg:website":"http://www.mileva.it",
    "wof:name":"Mileva Srl",
    "wof:placetype":"venue"
},
  "geometry": {"coordinates":[10.547641,44.95118],"type":"Point"}
}