{
  "type": "Feature",
  "properties": {
    "iso:country":"IT",
    "sg:address":"Via Piemonte 14 20090 Buccinasco",
    "sg:city":"Buccinasco",
    "sg:orig_category":"Pre-press Machinery",
    "sg:phone":"+39 02 4570 0135",
    "sg:postcode":"20090",
    "sg:province":"Milano",
    "wof:name":"Cappelletti Srl",
    "wof:placetype":"venue"
},
  "geometry": {"coordinates":[9.1186294556,45.4153747559],"type":"Point"}
}