{
  "type": "Feature",
  "properties": {
    "addr:full":"65/e, Via Ghebba 30034 Mira Mira Venezia 30034",
    "addr:housenumber":"65 / e",
    "addr:postcode":"30034;30034",
    "addr:street":"Via Ghebba;Mira Mira Venezia",
    "iso:country":"IT",
    "sg:address":"65/e, Via Ghebba 30034 Mira",
    "sg:city":"Mira",
    "sg:classifiers":[
        {
            "category":"Manufacturing",
            "subcategory":"Metals",
            "type":"Manufacturing & Wholesale Goods"
        }
    ],
    "sg:phone":"+39 041 563 1288",
    "sg:postcode":"30034",
    "sg:province":"Venezia",
    "sg:tags":[
        "metallurgy",
        "metalworking"
    ],
    "wof:name":"Inox Commerciale S.r.l.",
    "wof:placetype":"venue"
},
  "geometry": {"coordinates":[12.1754703522,45.4612808228],"type":"Point"}
}