{
  "type": "Feature",
  "properties": {
    "iso:country":"IT",
    "sg:address":"20097 San Donato Milanese",
    "sg:city":"San Donato Milanese",
    "sg:classifiers":[
        {
            "category":"Health Services",
            "subcategory":"Health Practitioner",
            "type":"Services"
        }
    ],
    "sg:phone":"+39 02 5560 0920",
    "sg:postcode":"20097",
    "sg:province":"Milano",
    "sg:tags":[
        "medici"
    ],
    "wof:name":"Benedetti Fiamma",
    "wof:placetype":"venue"
},
  "geometry": {"coordinates":[9.266017,45.406193],"type":"Point"}
}