{
  "type": "Feature",
  "properties": {
    "iso:country":"IT",
    "sg:address":"14100 Asti",
    "sg:city":"Asti",
    "sg:orig_category":"Prodotti Di Base E Forniture Per Industria Alimentare E Bevande. Vetro: Prodotti E Lavorazioni. Articoli Per Imballaggio E Confezionamento",
    "sg:phone":"+39 0141 212622",
    "sg:postcode":"14100",
    "sg:province":"Asti",
    "wof:name":"Vetrerie Betti S.n.c.",
    "wof:placetype":"venue"
},
  "geometry": {"coordinates":[8.2136564255,44.9102401733],"type":"Point"}
}