{
  "type": "Feature",
  "properties": {
    "addr:full":"6, Via Saba Umberto 41016 Novi Di Modena Novi di Modena Modena 41016",
    "addr:postcode":"41016;41016",
    "addr:street":"Via Saba Umberto",
    "iso:country":"IT",
    "sg:address":"6, Via Saba Umberto 41016 Novi Di Modena",
    "sg:city":"Novi di Modena",
    "sg:classifiers":[
        {
            "category":"Shopping",
            "type":"Retail Goods"
        }
    ],
    "sg:phone":"+39 39059671281",
    "sg:postcode":"41016",
    "sg:province":"Modena",
    "sg:tags":[
        "finished",
        "-",
        "metallic"
    ],
    "wof:name":"Hi-tech Plastic S.n.c.",
    "wof:placetype":"venue"
},
  "geometry": {"coordinates":[10.9252195358,44.6470794678],"type":"Point"}
}