{
  "type": "Feature",
  "properties": {
    "addr:full":"8, Strada Cassiani Liliano Centro Commerciale 61100 Pesaro Pesaro Pesaro E Urbino 61100",
    "addr:postcode":"61100;61100",
    "addr:street":"Strada Cassiani Liliano Centro Commerciale",
    "iso:country":"IT",
    "sg:address":"8, Strada Cassiani Liliano Centro Commerciale 61100 Pesaro",
    "sg:city":"Pesaro",
    "sg:classifiers":[
        {
            "category":"Food & Beverages",
            "subcategory":"Dairy",
            "type":"Retail Goods"
        }
    ],
    "sg:phone":"+39 39072121204",
    "sg:postcode":"61100",
    "sg:province":"Pesaro E Urbino",
    "sg:tags":[
        "product"
    ],
    "wof:name":"Gnassi Walther E Figli Srl",
    "wof:placetype":"venue"
},
  "geometry": {"coordinates":[12.529803,43.633556],"type":"Point"}
}