{
  "type": "Feature",
  "properties": {
    "addr:full":"11, V. Giuseppe Cesare Abba - Molinetto 25080 Mazzano Mazzano Brescia 25080",
    "addr:housenumber":"11",
    "addr:postcode":"25080;25080",
    "addr:street":"V. Giuseppe Cesare Abba Molinetto",
    "iso:country":"IT",
    "sg:address":"11, V. Giuseppe Cesare Abba - Molinetto 25080 Mazzano",
    "sg:city":"Mazzano",
    "sg:classifiers":[
        {
            "category":"Manufacturing",
            "subcategory":"Rubber & Plastics",
            "type":"Manufacturing & Wholesale Goods"
        }
    ],
    "sg:phone":"+39 030 212 1044",
    "sg:postcode":"25080",
    "sg:province":"Brescia",
    "sg:tags":[
        "packaging",
        "material",
        "-"
    ],
    "sg:website":"http://www.poliflex.com:ws_end: :mark:ws:http://www.paginegialle.it/poliflex-01",
    "wof:name":"Poliflex Srl",
    "wof:placetype":"venue"
},
  "geometry": {"coordinates":[10.3673439026,45.5032196045],"type":"Point"}
}