{
  "type": "Feature",
  "properties": {
    "iso:country":"IT",
    "sg:address":"42020 Albinea",
    "sg:orig_category":"Macchine Utensili E Impianti. Elettrotecnica Industriale, Prodotti E Apparecchiature",
    "sg:phone":"+39 0522 597323",
    "sg:postcode":"42020",
    "sg:province":"Reggio Nell'Emilia",
    "wof:name":"Gibertoni Alberto",
    "wof:placetype":"venue"
},
  "geometry": {"coordinates":[10.606624,44.631493],"type":"Point"}
}