{
  "type": "Feature",
  "properties": {
    "iso:country":"IT",
    "sg:address":"Via Gioberti Vincenzo 5 20123 Milano",
    "sg:city":"Milano",
    "sg:classifiers":[
        {
            "category":"Professional",
            "subcategory":"Business Services",
            "type":"Services"
        }
    ],
    "sg:phone":"+39 02 466992",
    "sg:postcode":"20123",
    "sg:province":"Milano",
    "sg:tags":[
        "industrial",
        "export"
    ],
    "wof:name":"Condeco Srl",
    "wof:placetype":"venue"
},
  "geometry": {"coordinates":[9.170375,45.468689],"type":"Point"}
}