{
  "type": "Feature",
  "properties": {
    "iso:country":"IT",
    "sg:address":"30175 Marghera",
    "sg:city":"Marghera",
    "sg:orig_category":"Servizi Ausiliari Di Analisi, Controllo E Ricerca",
    "sg:phone":"+39 041 927570",
    "sg:postcode":"30175",
    "sg:province":"Venezia",
    "wof:name":"Inspections & Consulting S.r.l.",
    "wof:placetype":"venue"
},
  "geometry": {"coordinates":[12.238867,45.470783],"type":"Point"}
}