{
  "type": "Feature",
  "properties": {
    "addr:full":"40122 Bologna Bologna Bologna 40122",
    "addr:postcode":"40122;40122",
    "iso:country":"IT",
    "sg:address":"40122 Bologna",
    "sg:city":"Bologna",
    "sg:orig_category":"Calzature, Pelletterie E Pelli. Shopping",
    "sg:phone":"+39 051 558680",
    "sg:postcode":"40122",
    "sg:province":"Bologna",
    "wof:name":"Calzature Piero Di Grementieri Alfiero & Figlio",
    "wof:placetype":"venue"
},
  "geometry": {"coordinates":[11.333065,44.495472],"type":"Point"}
}