{
  "type": "Feature",
  "properties": {
    "iso:country":"IT",
    "sg:address":"22076 Mozzate",
    "sg:city":"Mozzate",
    "sg:orig_category":"Servizi E Lavori Industria Chimica. Trattamenti Termici E Superficiali Metalli, Galvanotecnica",
    "sg:phone":"+39 0331 832190",
    "sg:postcode":"22076",
    "sg:province":"Como",
    "wof:name":"Sabbiver Srl",
    "wof:placetype":"venue"
},
  "geometry": {"coordinates":[8.952842,45.67194],"type":"Point"}
}