{
  "type": "Feature",
  "properties": {
    "iso:country":"IT",
    "sg:address":"47, Frazione Valdivilla Reg. Rivetti 12058 Santo Stefano Belbo",
    "sg:city":"Santo Stefano Belbo",
    "sg:classifiers":[
        {
            "category":"Food & Beverages",
            "subcategory":"Groceries & Convenience Stores",
            "type":"Retail Goods"
        }
    ],
    "sg:phone":"+39 0141 847149",
    "sg:postcode":"12058",
    "sg:province":"Cuneo",
    "sg:tags":[
        "drink"
    ],
    "wof:name":"Bosio S.r.l.",
    "wof:placetype":"venue"
},
  "geometry": {"coordinates":[7.547111,44.388798],"type":"Point"}
}