{
  "type": "Feature",
  "properties": {
    "addr:full":"Via Turati 16/18; Milan; 20121 Milano 20121",
    "addr:housenumber":"16 / 18",
    "addr:postcode":"20121;20121",
    "addr:street":"Via Turati;Milan",
    "iso:country":"IT",
    "sg:address":"Via Turati 16/18; Milan; 20121",
    "sg:classifiers":[
        {
            "category":"Industrial Area",
            "type":"Public Place"
        }
    ],
    "sg:phone":"+39 390 262 291",
    "sg:postcode":"20121",
    "sg:province":"Milano",
    "sg:tags":[
        "large",
        "private"
    ],
    "sg:website":"www.hdp.it",
    "wof:name":"Holding Di Partecipazioni Industriali S.p.a.",
    "wof:placetype":"venue"
},
  "geometry": {"coordinates":[9.1947174072,45.4749755859],"type":"Point"}
}