{
  "type": "Feature",
  "properties": {
    "iso:country":"IT",
    "sg:address":"00042 Anzio",
    "sg:city":"Anzio",
    "sg:orig_category":"Apparecchiature Elettroniche",
    "sg:phone":"+39 06 987 0938",
    "sg:postcode":"00042",
    "sg:province":"Roma",
    "wof:name":"Micro&systems Srl",
    "wof:placetype":"venue"
},
  "geometry": {"coordinates":[12.463287,41.832565],"type":"Point"}
}