{
  "type": "Feature",
  "properties": {
    "iso:country":"IT",
    "sg:address":"10045 Piossasco",
    "sg:city":"Piossasco",
    "sg:orig_category":"Zootecnia E Pesca, Allevamento Piccoli Animali",
    "sg:phone":"+39 011 906 4210",
    "sg:postcode":"10045",
    "sg:province":"Torino",
    "wof:name":"Fumagalli Andrea",
    "wof:placetype":"venue"
},
  "geometry": {"coordinates":[7.443889,44.991272],"type":"Point"}
}