{
  "type": "Feature",
  "properties": {
    "iso:country":"IT",
    "sg:address":"16123 Genova",
    "sg:city":"Genova",
    "sg:orig_category":"Impiantistica E Prodotti Tecnologici Per Edilizia. Elettrotecnica Professionale E Di Consumo. Telecomunicazioni E Telefonia, Impianti, Apparecchi E Servizi",
    "sg:phone":"+39 010 251 1269",
    "sg:postcode":"16123",
    "sg:province":"Genova",
    "wof:name":"Cuccureddu Snc Di Giorgio Cuccureddu & C.",
    "wof:placetype":"venue"
},
  "geometry": {"coordinates":[8.931434,44.408623],"type":"Point"}
}