{
  "type": "Feature",
  "properties": {
    "addr:full":"10036 Settimo Torinese Settimo Torinese Torino 10036",
    "addr:postcode":"10036;10036",
    "iso:country":"IT",
    "sg:address":"10036 Settimo Torinese",
    "sg:city":"Settimo Torinese",
    "sg:orig_category":"Metalli E Leghe",
    "sg:phone":"+39 011 897 7904",
    "sg:postcode":"10036",
    "sg:province":"Torino",
    "wof:name":"O.m.a.s. Srl",
    "wof:placetype":"venue"
},
  "geometry": {"coordinates":[7.7417068481,45.1420631409],"type":"Point"}
}