{
  "type": "Feature",
  "properties": {
    "addr:full":"Via Pederzana 9 40055 Villanova Villanova Bologna 40055",
    "addr:housenumber":"9",
    "addr:postcode":"40055;40055",
    "addr:street":"Via Pederzana",
    "iso:country":"IT",
    "sg:address":"Via Pederzana 9 40055 Villanova",
    "sg:city":"Villanova",
    "sg:classifiers":[
        {
            "category":"Wholesale",
            "subcategory":"Farm Supplies",
            "type":"Manufacturing & Wholesale Goods"
        }
    ],
    "sg:phone":"+39 051 605 3121",
    "sg:postcode":"40055",
    "sg:province":"Bologna",
    "sg:tags":[
        "agricultural",
        "part",
        "spare",
        "machinery",
        "accessory"
    ],
    "sg:website":"www.impolveratori.it",
    "wof:name":"G.r. Di Gamberini Remo",
    "wof:placetype":"venue"
},
  "geometry": {"coordinates":[11.43271,44.50235],"type":"Point"}
}