{
  "type": "Feature",
  "properties": {
    "iso:country":"IT",
    "sg:address":"84, Via Roviego 30030 Martellago",
    "sg:city":"Martellago",
    "sg:classifiers":[
        {
            "category":"Food & Beverages",
            "subcategory":"Groceries & Convenience Stores",
            "type":"Retail Goods"
        }
    ],
    "sg:phone":"+39 041 503 0661",
    "sg:postcode":"30030",
    "sg:province":"Venezia",
    "sg:tags":[
        "product",
        "related"
    ],
    "wof:name":"Cucina Nostrana Commerciale Srl",
    "wof:placetype":"venue"
},
  "geometry": {"coordinates":[12.1502561569,45.5252761841],"type":"Point"}
}