{
  "type": "Feature",
  "properties": {
    "iso:country":"IT",
    "sg:address":"Via Provinciale Chiantigiana 135/13 50023 Impruneta",
    "sg:city":"Impruneta",
    "sg:classifiers":[
        {
            "category":"Home & Garden",
            "subcategory":"Carpets & Floor Coverings",
            "type":"Retail Goods"
        }
    ],
    "sg:phone":"+39 055 207076",
    "sg:postcode":"50023",
    "sg:province":"Firenze",
    "sg:tags":[
        "tile"
    ],
    "sg:website":"www.sannini.it",
    "wof:name":"Sannini Impruneta Spa",
    "wof:placetype":"venue"
},
  "geometry": {"coordinates":[11.256902,43.768734],"type":"Point"}
}