{
  "type": "Feature",
  "properties": {
    "addr:full":"51010 Margine Coperta Margine Coperta Pistoia 51010",
    "addr:postcode":"51010;51010",
    "addr:street":"Coperta;Coperta",
    "iso:country":"IT",
    "sg:address":"51010 Margine Coperta",
    "sg:city":"Margine Coperta",
    "sg:orig_category":"Macchine, Impianti Ed Attrezzature Industria Chimica",
    "sg:phone":"+39 0572 72230",
    "sg:postcode":"51010",
    "sg:province":"Pistoia",
    "wof:name":"Co.me.v. Srl",
    "wof:placetype":"venue"
},
  "geometry": {"coordinates":[10.75027,43.884373],"type":"Point"}
}