{
  "type": "Feature",
  "properties": {
    "iso:country":"IT",
    "sg:address":"12036 Revello",
    "sg:city":"Revello",
    "sg:orig_category":"Cancelli, Porte E Portoni Automatici E Telecomandati",
    "sg:phone":"+39 0175 259255",
    "sg:postcode":"12036",
    "sg:province":"Cuneo",
    "wof:name":"Testa Fabrizio",
    "wof:placetype":"venue"
},
  "geometry": {"coordinates":[7.550801,44.413197],"type":"Point"}
}