{
  "type": "Feature",
  "properties": {
    "iso:country":"IT",
    "sg:address":"00163 Roma",
    "sg:city":"Roma",
    "sg:orig_category":"Scuole E Servizi Scolastici. Alberghi E Strutture Extra Alberghiere",
    "sg:phone":"+39 06 656651",
    "sg:postcode":"00163",
    "sg:province":"Roma",
    "wof:name":"Citta' Dei Ragazzi",
    "wof:placetype":"venue"
},
  "geometry": {"coordinates":[12.397943,41.86351],"type":"Point"}
}