{
  "type": "Feature",
  "properties": {
    "iso:country":"IT",
    "sg:address":"Via Consolare Valeria 98128 Messina",
    "sg:city":"Messina",
    "sg:classifiers":[
        {
            "category":"Travel",
            "subcategory":"Travel Agent",
            "type":"Entertainment"
        }
    ],
    "sg:phone":"+39 090 292 1002",
    "sg:postcode":"98128",
    "sg:province":"Messina",
    "sg:tags":[
        "business"
    ],
    "wof:name":"Russotti Finance Russfin Spa",
    "wof:placetype":"venue"
},
  "geometry": {"coordinates":[15.524191,38.136784],"type":"Point"}
}