{
  "type": "Feature",
  "properties": {
    "addr:full":"Via I Maggio 22 50053 Empoli Empoli Firenze 50053",
    "addr:housenumber":"22",
    "addr:postcode":"50053;50053",
    "addr:street":"Via I Maggio",
    "iso:country":"IT",
    "sg:address":"Via I Maggio 22 50053 Empoli",
    "sg:city":"Empoli",
    "sg:classifiers":[
        {
            "category":"Government",
            "subcategory":"Post Office",
            "type":"Public Place"
        }
    ],
    "sg:phone":"+39 0571 944404",
    "sg:postcode":"50053",
    "sg:province":"Firenze",
    "sg:tags":[
        "item",
        "household",
        "design"
    ],
    "sg:website":"www.cardini-spa.it",
    "wof:name":"Cardini Raffaello & Gaetano Spa",
    "wof:placetype":"venue"
},
  "geometry": {"coordinates":[11.256902,43.768734],"type":"Point"}
}