{
  "type": "Feature",
  "properties": {
    "iso:country":"IT",
    "sg:address":"Via De' Cattani 69/f 50145 Firenze",
    "sg:city":"Firenze",
    "sg:classifiers":[
        {
            "category":"Autos & Motor Vehicles",
            "subcategory":"Auto Supplies",
            "type":"Retail Goods"
        }
    ],
    "sg:phone":"+39 055 342 7430",
    "sg:postcode":"50145",
    "sg:province":"Firenze",
    "sg:tags":[
        "automobile",
        "part",
        "spare"
    ],
    "wof:name":"S.ar.pi. Srl",
    "wof:placetype":"venue"
},
  "geometry": {"coordinates":[11.256902,43.768734],"type":"Point"}
}