{
  "type": "Feature",
  "properties": {
    "iso:country":"IT",
    "sg:address":"63023 Fermo",
    "sg:city":"Fermo",
    "sg:orig_category":"Termotecnica E Riscaldamento, Apparecchiature E Servizi",
    "sg:phone":"+39 0734 225437",
    "sg:postcode":"63023",
    "sg:province":"Ascoli Piceno",
    "wof:name":"Properzi Secondo",
    "wof:placetype":"venue"
},
  "geometry": {"coordinates":[13.725675,43.16787],"type":"Point"}
}