{
  "type": "Feature",
  "properties": {
    "addr:full":"30020 Marcon Marcon Venezia 30020",
    "addr:postcode":"30020;30020",
    "iso:country":"IT",
    "sg:address":"30020 Marcon",
    "sg:city":"Marcon",
    "sg:orig_category":"Prodotti E Manufatti In Materie Plastiche",
    "sg:phone":"+39 041 456 7361",
    "sg:postcode":"30020",
    "sg:province":"Venezia",
    "wof:name":"Vebel (s.r.l.)",
    "wof:placetype":"venue"
},
  "geometry": {"coordinates":[12.293513298,45.5449066162],"type":"Point"}
}