{
  "type": "Feature",
  "properties": {
    "iso:country":"IT",
    "sg:address":"21/b, Via Al Piano 22100 Como",
    "sg:city":"Como",
    "sg:classifiers":[
        {
            "category":"Wholesale",
            "subcategory":"Drugs",
            "type":"Manufacturing & Wholesale Goods"
        }
    ],
    "sg:phone":"+39 39031590760",
    "sg:postcode":"22100",
    "sg:province":"Como",
    "sg:tags":[
        "chemical",
        "pharmaceutical"
    ],
    "wof:name":"Impresa Belluschi S.n.c.",
    "wof:placetype":"venue"
},
  "geometry": {"coordinates":[9.085456,45.811966],"type":"Point"}
}