{
  "type": "Feature",
  "properties": {
    "iso:country":"IT",
    "sg:address":"37129 Verona",
    "sg:city":"Verona",
    "sg:orig_category":"Articoli Da Regalo. Tempo Libero - Articoli E Forniture. Regalistica Aziendale",
    "sg:phone":"+39 045 800 2991",
    "sg:postcode":"37129",
    "sg:province":"Verona",
    "sg:website":"http://www.cip.it",
    "wof:name":"C.i.p. Di Bonente Marco & C. Sas",
    "wof:placetype":"venue"
},
  "geometry": {"coordinates":[11.013276,45.439316],"type":"Point"}
}