{
  "type": "Feature",
  "properties": {
    "addr:full":"Via Brodolini 3 28865 Crevoladossola Crevoladossola Verbano-Cusio-Ossola 28865",
    "addr:housenumber":"3",
    "addr:postcode":"28865;28865",
    "addr:street":"Via Brodolini",
    "iso:country":"IT",
    "sg:address":"Via Brodolini 3 28865 Crevoladossola",
    "sg:city":"Crevoladossola",
    "sg:classifiers":[
        {
            "category":"Manufacturing",
            "subcategory":"Metals",
            "type":"Manufacturing & Wholesale Goods"
        }
    ],
    "sg:phone":"+39 0324 238760",
    "sg:postcode":"28865",
    "sg:province":"Verbano-Cusio-Ossola",
    "sg:tags":[
        "processing"
    ],
    "wof:name":"Laminatoio Del Sempione Srl",
    "wof:placetype":"venue"
},
  "geometry": {"coordinates":[8.2906341553,46.1322555542],"type":"Point"}
}