{
  "type": "Feature",
  "properties": {
    "addr:full":"89/b, Via Dell' Annunziata 64021 Giulianova Giulianova Teramo 64021",
    "addr:housenumber":"89 / b",
    "addr:postcode":"64021;64021",
    "addr:street":"Via Dell ' Annunziata",
    "iso:country":"IT",
    "sg:address":"89/b, Via Dell' Annunziata 64021 Giulianova",
    "sg:city":"Giulianova",
    "sg:classifiers":[
        {
            "category":"Shopping",
            "subcategory":"Clothing, Apparel, & Fashions",
            "type":"Retail Goods"
        }
    ],
    "sg:phone":"+39 085 800 2245",
    "sg:postcode":"64021",
    "sg:province":"Teramo",
    "sg:tags":[
        "clothes"
    ],
    "wof:name":"Confezioni Sipal S.a.s.",
    "wof:placetype":"venue"
},
  "geometry": {"coordinates":[13.698531,42.66127],"type":"Point"}
}