{
  "type": "Feature",
  "properties": {
    "iso:country":"IT",
    "sg:address":"15048 Valenza",
    "sg:city":"Valenza",
    "sg:orig_category":"Macchine E Forniture Per Industria Orafa E Per Orologeria",
    "sg:phone":"+39 0131 953074",
    "sg:postcode":"15048",
    "sg:province":"Alessandria",
    "wof:name":"Tecno Gold Valenza Snc Di Zaccone & C",
    "wof:placetype":"venue"
},
  "geometry": {"coordinates":[8.636209,45.009483],"type":"Point"}
}