{
  "type": "Feature",
  "properties": {
    "iso:country":"IT",
    "sg:address":"35, Via Ludovisi 00187 Roma",
    "sg:city":"Roma",
    "sg:classifiers":[
        {
            "category":"Shopping",
            "subcategory":"Clothing, Apparel, & Fashions",
            "type":"Retail Goods"
        }
    ],
    "sg:phone":"+39 39064821723",
    "sg:postcode":"00187",
    "sg:province":"Roma",
    "sg:tags":[
        "clothing",
        "accessory"
    ],
    "wof:name":"Renato Balestra Haute Couture S.r.l.",
    "wof:placetype":"venue"
},
  "geometry": {"coordinates":[12.488429,41.906979],"type":"Point"}
}