{
  "type": "Feature",
  "properties": {
    "addr:full":"84098 Pontecagnano Faiano Faiano Salerno 84098",
    "addr:postcode":"84098;84098",
    "iso:country":"IT",
    "sg:address":"84098 Pontecagnano Faiano",
    "sg:city":"Faiano",
    "sg:orig_category":"Forniture Per Agricoltura E Zootecnia. Animali Domestici",
    "sg:phone":"+39 089 849097",
    "sg:postcode":"84098",
    "sg:province":"Salerno",
    "wof:name":"Medivet Di Carlo Clarizia",
    "wof:placetype":"venue"
},
  "geometry": {"coordinates":[14.8804893494,40.6230278015],"type":"Point"}
}