{
  "type": "Feature",
  "properties": {
    "addr:full":"20061 Carugate Carugate Milano 20061",
    "addr:postcode":"20061;20061",
    "addr:street":"Carugate Carugate",
    "iso:country":"IT",
    "sg:address":"20061 Carugate",
    "sg:city":"Carugate",
    "sg:orig_category":"Ospedali E Servizi Sanitari",
    "sg:phone":"+39 02 9215 0344",
    "sg:postcode":"20061",
    "sg:province":"Milano",
    "wof:name":"Croce Bianca Carugate",
    "wof:placetype":"venue"
},
  "geometry": {"coordinates":[9.346452,45.545246],"type":"Point"}
}