{
  "type": "Feature",
  "properties": {
    "iso:country":"IT",
    "sg:address":"36, Via Mattei Enrico 62014 Corridonia",
    "sg:city":"Corridonia",
    "sg:classifiers":[
        {
            "category":"Manufacturing",
            "subcategory":"Textiles",
            "type":"Manufacturing & Wholesale Goods"
        }
    ],
    "sg:phone":"+39 0733 281376",
    "sg:postcode":"62014",
    "sg:province":"Macerata",
    "sg:tags":[
        "leather",
        "raw",
        "material",
        "-"
    ],
    "wof:name":"Fustellificio P.m. S.r.l.",
    "wof:placetype":"venue"
},
  "geometry": {"coordinates":[13.440259,43.289516],"type":"Point"}
}