{
  "type": "Feature",
  "properties": {
    "iso:country":"IT",
    "sg:address":"26, Via Romagna 00187 Roma",
    "sg:city":"Roma",
    "sg:classifiers":[
        {
            "category":"Travel",
            "subcategory":"Travel Agent",
            "type":"Entertainment"
        }
    ],
    "sg:phone":"+39 39064819495",
    "sg:postcode":"00187",
    "sg:province":"Roma",
    "sg:tags":[
        "business"
    ],
    "wof:name":"Food & Beverage S.r.l.",
    "wof:placetype":"venue"
},
  "geometry": {"coordinates":[12.37246,42.13063],"type":"Point"}
}