{
  "type": "Feature",
  "properties": {
    "addr:full":"46042 Castel Goffredo Castel Goffredo Mantova 46042",
    "addr:postcode":"46042;46042",
    "addr:street":"Goffredo",
    "iso:country":"IT",
    "sg:address":"46042 Castel Goffredo",
    "sg:city":"Castel Goffredo",
    "sg:orig_category":"Calze E Collants - Produzione E Ingrosso",
    "sg:phone":"+39 0376 779533",
    "sg:postcode":"46042",
    "sg:province":"Mantova",
    "wof:name":"Calzificio Felice Snc Di Lancellotti & Bandiera",
    "wof:placetype":"venue"
},
  "geometry": {"coordinates":[10.467477,45.284252],"type":"Point"}
}