{
  "type": "Feature",
  "properties": {
    "addr:full":"10155 Torino Torino Torino 10155",
    "addr:postcode":"10155;10155",
    "iso:country":"IT",
    "sg:address":"10155 Torino",
    "sg:city":"Torino",
    "sg:orig_category":"Apparecchiature Ed Attrezzature Meccaniche",
    "sg:phone":"+39 011 245 6811",
    "sg:postcode":"10155",
    "sg:province":"Torino",
    "wof:name":"Dea Tech S.p.a.",
    "wof:placetype":"venue"
},
  "geometry": {"coordinates":[7.685769,45.092342],"type":"Point"}
}