{
  "type": "Feature",
  "properties": {
    "iso:country":"IT",
    "sg:address":"14, Via Guglielmo Marconi 20088 Rosate",
    "sg:city":"Rosate",
    "sg:classifiers":[
        {
            "category":"Manufacturing",
            "subcategory":"Motor Vehicles & Parts",
            "type":"Manufacturing & Wholesale Goods"
        }
    ],
    "sg:phone":"+39 39029058092",
    "sg:postcode":"20088",
    "sg:province":"Milano",
    "sg:tags":[
        "engine"
    ],
    "wof:name":"Ingramec S.r.l.",
    "wof:placetype":"venue"
},
  "geometry": {"coordinates":[9.064705,45.332802],"type":"Point"}
}