{
  "type": "Feature",
  "properties": {
    "iso:country":"IT",
    "sg:address":"18100 Imperia",
    "sg:city":"Imperia",
    "sg:orig_category":"Agenzie Investigative",
    "sg:phone":"+39 0183 297058",
    "sg:postcode":"18100",
    "sg:province":"Imperia",
    "wof:name":"Imperiainform Sas Di R. Sciocchetti",
    "wof:placetype":"venue"
},
  "geometry": {"coordinates":[8.031564,43.887894],"type":"Point"}
}