{
  "type": "Feature",
  "properties": {
    "addr:full":"51100 Pistoia Pistoia Pistoia 51100",
    "addr:postcode":"51100;51100",
    "iso:country":"IT",
    "sg:address":"51100 Pistoia",
    "sg:city":"Pistoia",
    "sg:orig_category":"Pubblicita' - Cartelli, Insegne E Targhe",
    "sg:phone":"+39 0573 33636",
    "sg:postcode":"51100",
    "sg:province":"Pistoia",
    "wof:name":"Multideco Di Barale Luciano & C. Snc",
    "wof:placetype":"venue"
},
  "geometry": {"coordinates":[10.9056482315,43.9335975647],"type":"Point"}
}