{
  "type": "Feature",
  "properties": {
    "addr:full":"Via Bernocchi Antonio 56 25069 Villa Carcina Carcina Brescia 25069",
    "addr:housenumber":"56",
    "addr:postcode":"25069;carcina;25069",
    "addr:street":"Via Bernocchi Antonio",
    "iso:country":"IT",
    "sg:address":"Via Bernocchi Antonio 56 25069 Villa Carcina",
    "sg:city":"Carcina",
    "sg:orig_category":"Fittings, Valves",
    "sg:phone":"+39 030 890 0961",
    "sg:postcode":"25069",
    "sg:province":"Brescia",
    "sg:website":"www.effepirubinetterie.com",
    "wof:name":"Effepi Rubinetterie Srl",
    "wof:placetype":"venue"
},
  "geometry": {"coordinates":[10.2229576111,45.5398292542],"type":"Point"}
}