{
  "type": "Feature",
  "properties": {
    "addr:full":"68, Via Pontarola 35011 Campodarsego Campodarsego Padova 35011",
    "addr:postcode":"35011;35011",
    "addr:street":"Via Pontarola",
    "iso:country":"IT",
    "sg:address":"68, Via Pontarola 35011 Campodarsego",
    "sg:city":"Campodarsego",
    "sg:classifiers":[
        {
            "category":"Professional",
            "subcategory":"Printing & Photocopies",
            "type":"Services"
        }
    ],
    "sg:phone":"+39 049 920 0503",
    "sg:postcode":"35011",
    "sg:province":"Padova",
    "wof:name":"Gruppo Padovana S.r.l.",
    "wof:placetype":"venue"
},
  "geometry": {"coordinates":[11.9158763885,45.4804496765],"type":"Point"}
}