{
  "type": "Feature",
  "properties": {
    "addr:full":"16162 Genova Genova Genova 16162",
    "addr:postcode":"16162;16162",
    "iso:country":"IT",
    "sg:address":"16162 Genova",
    "sg:city":"Genova",
    "sg:classifiers":[
        {
            "category":"Professional",
            "type":"Services"
        }
    ],
    "sg:phone":"+39 010 740 3795",
    "sg:postcode":"16162",
    "sg:province":"Genova",
    "sg:tags":[
        "auxiliary",
        "entertainment",
        "premises",
        "related",
        "catering",
        "public",
        "restaurants"
    ],
    "wof:name":"Cibus Srl",
    "wof:placetype":"venue"
},
  "geometry": {"coordinates":[8.907978,44.460815],"type":"Point"}
}