{
  "type": "Feature",
  "properties": {
    "addr:full":"46, Via Xxiv Maggio 31015 Conegliano Conegliano Treviso 31015",
    "addr:postcode":"31015;31015",
    "addr:street":"Via Xxiv Maggio",
    "iso:country":"IT",
    "sg:address":"46, Via Xxiv Maggio 31015 Conegliano",
    "sg:city":"Conegliano",
    "sg:classifiers":[
        {
            "category":"Sports & Exercise",
            "subcategory":"Playing Field",
            "type":"Entertainment"
        }
    ],
    "sg:phone":"+39 39043832283",
    "sg:postcode":"31015",
    "sg:province":"Treviso",
    "sg:tags":[
        "game"
    ],
    "wof:name":"Tuttobocce",
    "wof:placetype":"venue"
},
  "geometry": {"coordinates":[12.242072,45.666286],"type":"Point"}
}