{
  "type": "Feature",
  "properties": {
    "addr:full":"10141 Torino Torino Torino 10141",
    "addr:postcode":"10141;10141",
    "iso:country":"IT",
    "sg:address":"10141 Torino",
    "sg:city":"Torino",
    "sg:orig_category":"Sport - Articoli E Forniture",
    "sg:phone":"+39 011 385 6430",
    "sg:postcode":"10141",
    "sg:province":"Torino",
    "wof:name":"Armeria Riparazioni G.p.",
    "wof:placetype":"venue"
},
  "geometry": {"coordinates":[7.592778,45.025333],"type":"Point"}
}