{
  "type": "Feature",
  "properties": {
    "iso:country":"IT",
    "sg:address":"6, Contrada Macchia Del Fresco 66015 Fara San Martino",
    "sg:city":"Fara San Martino",
    "sg:classifiers":[
        {
            "category":"Travel",
            "subcategory":"Travel Agent",
            "type":"Entertainment"
        }
    ],
    "sg:phone":"+39 0872 980136",
    "sg:postcode":"66015",
    "sg:province":"Chieti",
    "sg:tags":[
        "business"
    ],
    "wof:name":"Hotel Il Camerlengo",
    "wof:placetype":"venue"
},
  "geometry": {"coordinates":[14.167151,42.351791],"type":"Point"}
}