{
  "type": "Feature",
  "properties": {
    "iso:country":"IT",
    "sg:address":"73050 Salve",
    "sg:city":"Salve",
    "sg:orig_category":"Abbigliamento Esterno, Maglierie E Pelliccerie",
    "sg:phone":"+39 0833 520980",
    "sg:postcode":"73050",
    "sg:province":"Lecce",
    "wof:name":"Confezioni Co.bi Di Conte Biagio",
    "wof:placetype":"venue"
},
  "geometry": {"coordinates":[18.292057,39.862221],"type":"Point"}
}