{
  "type": "Feature",
  "properties": {
    "addr:full":"32, Via Pacinotti Antonio 37135 Verona Verona Verona 37135",
    "addr:postcode":"37135;37135",
    "addr:street":"Via Pacinotti Antonio",
    "iso:country":"IT",
    "sg:address":"32, Via Pacinotti Antonio 37135 Verona",
    "sg:city":"Verona",
    "sg:classifiers":[
        {
            "category":"Manufacturing",
            "subcategory":"Textiles",
            "type":"Manufacturing & Wholesale Goods"
        }
    ],
    "sg:phone":"+39 39045508944",
    "sg:postcode":"37135",
    "sg:province":"Verona",
    "sg:tags":[
        "leather",
        "raw",
        "material",
        "-"
    ],
    "wof:name":"Parma S.r.l.",
    "wof:placetype":"venue"
},
  "geometry": {"coordinates":[10.965893,45.409344],"type":"Point"}
}