{
  "type": "Feature",
  "properties": {
    "iso:country":"IT",
    "sg:address":"74025 Marina Di Ginosa",
    "sg:city":"Ginosa",
    "sg:orig_category":"Pubblica Amministrazione",
    "sg:phone":"+39 099 827 1194",
    "sg:postcode":"74025",
    "sg:province":"Taranto",
    "wof:name":"Forestale Comando Stazione",
    "wof:placetype":"venue"
},
  "geometry": {"coordinates":[16.8864040375,40.4338912964],"type":"Point"}
}