{
  "type": "Feature",
  "properties": {
    "iso:country":"IT",
    "sg:address":"30, Via Guido Rossa 62015 Monte San Giusto",
    "sg:city":"Monte San Giusto",
    "sg:classifiers":[
        {
            "category":"Personal",
            "subcategory":"Shoe Repair & Shine",
            "type":"Services"
        }
    ],
    "sg:phone":"+39 39073353720",
    "sg:postcode":"62015",
    "sg:province":"Macerata",
    "sg:tags":[
        "leather"
    ],
    "wof:name":"Del Papa E C. (s.n.c.)",
    "wof:placetype":"venue"
},
  "geometry": {"coordinates":[13.592466,43.257339],"type":"Point"}
}