{
  "type": "Feature",
  "properties": {
    "iso:country":"IT",
    "sg:address":"Via Lumumba 1 Int. 2 41100 Modena",
    "sg:city":"Modena",
    "sg:classifiers":[
        {
            "category":"Utilities",
            "subcategory":"Natural Gas",
            "type":"Services"
        }
    ],
    "sg:phone":"+39 059 251059",
    "sg:postcode":"41100",
    "sg:province":"Modena",
    "sg:tags":[
        "heater",
        "air"
    ],
    "wof:name":"Officine Natali Srl",
    "wof:placetype":"venue"
},
  "geometry": {"coordinates":[10.961546,44.65704],"type":"Point"}
}