{
  "type": "Feature",
  "properties": {
    "iso:country":"IT",
    "sg:address":"20131 Milano",
    "sg:city":"Milano",
    "sg:orig_category":"Servizi E Lavori Per Abbigliamento E Pelletterie",
    "sg:phone":"+39 02 284 6994",
    "sg:postcode":"20131",
    "sg:province":"Milano",
    "wof:name":"Tintoria Gabriella Di Paolucci Gabriella",
    "wof:placetype":"venue"
},
  "geometry": {"coordinates":[9.224413,45.490406],"type":"Point"}
}