{
  "type": "Feature",
  "properties": {
    "iso:country":"IT",
    "sg:address":"50144 Firenze",
    "sg:city":"Firenze",
    "sg:orig_category":"Servizi E Lavori Per Edilizia E Lavori Pubblici. Consulenze Tecniche, Amministrative E Perizie",
    "sg:phone":"+39 055 366030",
    "sg:postcode":"50144",
    "sg:province":"Firenze",
    "sg:website":"http://www.gfe-em.com",
    "wof:name":"Gfe Energy Management Srl",
    "wof:placetype":"venue"
},
  "geometry": {"coordinates":[11.226877,43.782269],"type":"Point"}
}