{
  "type": "Feature",
  "properties": {
    "addr:full":"19, Via Paleocapa Pietro 17100 Savona Savona Savona 17100",
    "addr:postcode":"17100;17100",
    "addr:street":"Via Paleocapa Pietro",
    "iso:country":"IT",
    "sg:address":"19, Via Paleocapa Pietro 17100 Savona",
    "sg:city":"Savona",
    "sg:classifiers":[
        {
            "category":"Communications",
            "subcategory":"Newspaper",
            "type":"Services"
        }
    ],
    "sg:phone":"+39 39019821705",
    "sg:postcode":"17100",
    "sg:province":"Savona",
    "sg:tags":[
        "advertising"
    ],
    "wof:name":"Publirama S.p.a.",
    "wof:placetype":"venue"
},
  "geometry": {"coordinates":[8.480794,44.308891],"type":"Point"}
}