{
  "type": "Feature",
  "properties": {
    "iso:country":"IT",
    "sg:address":"128/36, Str. Del Drosso 10135 Torino",
    "sg:city":"Torino",
    "sg:classifiers":[
        {
            "category":"Manufacturing",
            "subcategory":"Metals",
            "type":"Manufacturing & Wholesale Goods"
        }
    ],
    "sg:phone":"+39 011 347 2656",
    "sg:postcode":"10135",
    "sg:province":"Torino",
    "sg:tags":[
        "metallurgy",
        "metalworking"
    ],
    "sg:website":"http://www.itas-spa.it",
    "wof:name":"Itas Spa",
    "wof:placetype":"venue"
},
  "geometry": {"coordinates":[7.6135296822,45.0178527832],"type":"Point"}
}