{
  "type": "Feature",
  "properties": {
    "iso:country":"IT",
    "sg:address":"66, V. St. Dei Giovi 22070 Grandate",
    "sg:city":"Grandate",
    "sg:classifiers":[
        {
            "category":"Shopping",
            "subcategory":"Clothing, Apparel, & Fashions",
            "type":"Retail Goods"
        }
    ],
    "sg:phone":"+39 39031399111",
    "sg:postcode":"22070",
    "sg:province":"Como",
    "sg:tags":[
        "clothing",
        "accessory"
    ],
    "sg:website":"http://www.paginegialle.it/guarisco-02",
    "wof:name":"Guarisco Industria Tessile Spa",
    "wof:placetype":"venue"
},
  "geometry": {"coordinates":[9.060573,45.769569],"type":"Point"}
}