{
  "type": "Feature",
  "properties": {
    "iso:country":"IT",
    "sg:address":"10155 Torino",
    "sg:city":"Torino",
    "sg:orig_category":"Fuoristrada Ed Accessori",
    "sg:phone":"+39 011 50065",
    "sg:postcode":"10155",
    "sg:province":"Torino",
    "wof:name":"Capello Pietro",
    "wof:placetype":"venue"
},
  "geometry": {"coordinates":[7.6880064011,45.0913009644],"type":"Point"}
}