{
  "type": "Feature",
  "properties": {
    "iso:country":"IT",
    "sg:address":"3, Via Pascoli Giovanni 60044 Fabriano",
    "sg:city":"Fabriano",
    "sg:classifiers":[
        {
            "category":"Manufacturing",
            "subcategory":"Rubber & Plastics",
            "type":"Manufacturing & Wholesale Goods"
        }
    ],
    "sg:phone":"+39 39073222972",
    "sg:postcode":"60044",
    "sg:province":"Ancona",
    "wof:name":"Mapla (s.p.a.)",
    "wof:placetype":"venue"
},
  "geometry": {"coordinates":[13.5187568665,43.6158561707],"type":"Point"}
}