{
  "type": "Feature",
  "properties": {
    "iso:country":"IT",
    "sg:address":"20, Via Toscana 53036 Poggibonsi",
    "sg:city":"Poggibonsi",
    "sg:classifiers":[
        {
            "category":"Home & Garden",
            "subcategory":"Home Furnishings",
            "type":"Retail Goods"
        }
    ],
    "sg:phone":"+39 0577 980488",
    "sg:postcode":"53036",
    "sg:province":"Siena",
    "sg:tags":[
        "household"
    ],
    "wof:name":"Thesi S.r.l.",
    "wof:placetype":"venue"
},
  "geometry": {"coordinates":[11.22059,43.538055],"type":"Point"}
}