{
  "type": "Feature",
  "properties": {
    "iso:country":"IT",
    "sg:address":"20149 Milano",
    "sg:city":"Milano",
    "sg:orig_category":"Utensili Meccanici E Materiali",
    "sg:phone":"+39 02 4819 3435",
    "sg:postcode":"20149",
    "sg:province":"Milano",
    "wof:name":"Berardi Ennio",
    "wof:placetype":"venue"
},
  "geometry": {"coordinates":[9.147141,45.47842],"type":"Point"}
}