{
  "type": "Feature",
  "properties": {
    "iso:country":"IT",
    "sg:address":"166/1, Via Maccani Ezio 38100 Trento",
    "sg:city":"Trento",
    "sg:classifiers":[
        {
            "category":"Shopping",
            "subcategory":"Computers & Home Electronics",
            "type":"Retail Goods"
        }
    ],
    "sg:phone":"+39 0461 822073",
    "sg:postcode":"38100",
    "sg:province":"Trento",
    "sg:tags":[
        "electronic",
        "electrical",
        "equipment"
    ],
    "wof:name":"Elettro S.e.a. S.n.c.",
    "wof:placetype":"venue"
},
  "geometry": {"coordinates":[11.117148,46.080109],"type":"Point"}
}