{
  "type": "Feature",
  "properties": {
    "iso:country":"IT",
    "sg:address":"41012 Carpi",
    "sg:city":"Carpi",
    "sg:orig_category":"Pubblicita', Marketing E Comunicazione",
    "sg:phone":"+39 059 681545",
    "sg:postcode":"41012",
    "sg:province":"Modena",
    "wof:name":"New Mark Snc",
    "wof:placetype":"venue"
},
  "geometry": {"coordinates":[10.8893194199,44.7835617065],"type":"Point"}
}