{
  "type": "Feature",
  "properties": {
    "iso:country":"IT",
    "sg:address":"20049 Concorezzo",
    "sg:city":"Concorezzo",
    "sg:orig_category":"Utensili Meccanici E Materiali. Forniture Per Attivita' Industriali",
    "sg:postcode":"20049",
    "sg:province":"Milano",
    "wof:name":"A.c.u.m.e. Snc Di Frigerio Giancarlo & C.",
    "wof:placetype":"venue"
},
  "geometry": {"coordinates":[9.323862,45.586708],"type":"Point"}
}