{
  "type": "Feature",
  "properties": {
    "addr:full":"40124 Bologna Bologna Bologna 40124",
    "addr:postcode":"40124;40124",
    "iso:country":"IT",
    "sg:address":"40124 Bologna",
    "sg:city":"Bologna",
    "sg:orig_category":"Forniture Per Uffici",
    "sg:phone":"+39 051 222590",
    "sg:postcode":"40124",
    "sg:province":"Bologna",
    "sg:website":"http://www.sebino.it",
    "wof:name":"Sebino Colori Snc Di Passarini P. Sermasi P. & Osti Vladimiro",
    "wof:placetype":"venue"
},
  "geometry": {"coordinates":[11.3467569351,44.4914665222],"type":"Point"}
}