{
  "type": "Feature",
  "properties": {
    "iso:country":"IT",
    "sg:address":"Via G. Matteotti 112 21015 Lonate Pozzolo",
    "sg:city":"Lonate Pozzolo",
    "sg:classifiers":[
        {
            "category":"Manufacturing",
            "subcategory":"Textiles",
            "type":"Manufacturing & Wholesale Goods"
        }
    ],
    "sg:phone":"+39 0331 660171",
    "sg:postcode":"21015",
    "sg:province":"Varese",
    "sg:tags":[
        "blend"
    ],
    "wof:name":"Fil Tessile S.r.l.",
    "wof:placetype":"venue"
},
  "geometry": {"coordinates":[8.826385,45.817604],"type":"Point"}
}