{
  "type": "Feature",
  "properties": {
    "iso:country":"IT",
    "sg:address":"38066 Riva Del Garda",
    "sg:city":"Riva del Garda",
    "sg:orig_category":"Alberghi",
    "sg:phone":"+39 0464 553581",
    "sg:postcode":"38066",
    "sg:province":"Trento",
    "sg:website":"http://www.grandhotelliberty.it",
    "wof:name":"Grand Hotel Liberty",
    "wof:placetype":"venue"
},
  "geometry": {"coordinates":[10.847095,45.88562],"type":"Point"}
}