{
  "type": "Feature",
  "properties": {
    "iso:country":"IT",
    "sg:address":"20068 Peschiera Borromeo",
    "sg:city":"Peschiera Borromeo",
    "sg:orig_category":"Cartotecnica E Servizi. Composizione, Stampa E Confezione. Servizi E Lavori Industria Delle Materie Plastiche. Servizi Per Imballaggio E Confezionamento",
    "sg:phone":"+39 02 5530 1707",
    "sg:postcode":"20068",
    "sg:province":"Milano",
    "wof:name":"Cedic (s.r.l.)",
    "wof:placetype":"venue"
},
  "geometry": {"coordinates":[9.317017,45.427929],"type":"Point"}
}