{
  "type": "Feature",
  "properties": {
    "iso:country":"IT",
    "sg:address":"97100 Ragusa",
    "sg:city":"Ragusa",
    "sg:orig_category":"Materiali Edili",
    "sg:phone":"+39 0932 251205",
    "sg:postcode":"97100",
    "sg:province":"Ragusa",
    "wof:name":"Iblea Sale Di Borrometi Giuseppe & C. Snc",
    "wof:placetype":"venue"
},
  "geometry": {"coordinates":[14.685569,36.931721],"type":"Point"}
}