{
  "type": "Feature",
  "properties": {
    "addr:full":"38015 Lavis Lavis Trento 38015",
    "addr:postcode":"38015;38015",
    "iso:country":"IT",
    "sg:address":"38015 Lavis",
    "sg:city":"Lavis",
    "sg:orig_category":"Prodotti Chimici Di Base",
    "sg:phone":"+39 0461 249645",
    "sg:postcode":"38015",
    "sg:province":"Trento",
    "wof:name":"Mb4 Distribuzione Srl",
    "wof:placetype":"venue"
},
  "geometry": {"coordinates":[11.0896291733,46.1338920593],"type":"Point"}
}