{
  "type": "Feature",
  "properties": {
    "iso:country":"IT",
    "sg:address":"10024 Moncalieri",
    "sg:city":"Moncalieri",
    "sg:orig_category":"Autodemolizioni",
    "sg:phone":"+39 011 640 9360",
    "sg:postcode":"10024",
    "sg:province":"Torino",
    "wof:name":"Centro Recupero Ecologico Di Costa Bruno",
    "wof:placetype":"venue"
},
  "geometry": {"coordinates":[7.690634,44.995239],"type":"Point"}
}