{
  "type": "Feature",
  "properties": {
    "addr:full":"3, Strada Della Torre 43013 Langhirano Langhirano Parma 43013",
    "addr:postcode":"43013;43013",
    "addr:street":"Strada Della Torre",
    "iso:country":"IT",
    "sg:address":"3, Strada Della Torre 43013 Langhirano",
    "sg:city":"Langhirano",
    "sg:classifiers":[
        {
            "category":"Food & Beverages",
            "subcategory":"Groceries & Convenience Stores",
            "type":"Retail Goods"
        }
    ],
    "sg:phone":"+39 0521 852341",
    "sg:postcode":"43013",
    "sg:province":"Parma",
    "sg:tags":[
        "product",
        "related"
    ],
    "wof:name":"Salumificio La Torre (s.r.l.)",
    "wof:placetype":"venue"
},
  "geometry": {"coordinates":[10.1864557266,44.5395927429],"type":"Point"}
}