{
  "type": "Feature",
  "properties": {
    "addr:full":"Piazza Milano 36; Lido Di Jesolo; Venezia; 30017",
    "addr:housenumber":"36",
    "addr:postcode":"30017",
    "addr:street":"Piazza Milano",
    "iso:country":"IT",
    "sg:address":"Piazza Milano 36; Lido Di Jesolo; Venezia; 30017",
    "sg:classifiers":[
        {
            "category":"Travel",
            "subcategory":"Travel Agent",
            "type":"Entertainment"
        }
    ],
    "sg:phone":"+39 390 421 9728",
    "sg:website":"intrasviaggi.it",
    "wof:name":"Intras Viaggi E Vacanze",
    "wof:placetype":"venue"
},
  "geometry": {"coordinates":[12.671427,45.514072],"type":"Point"}
}