{
  "type": "Feature",
  "properties": {
    "iso:country":"IT",
    "sg:address":"35020 Albignasego",
    "sg:city":"Albignasego",
    "sg:orig_category":"Macchine, Impianti Ed Attrezzature Per Abbigliamento E Pelletterie",
    "sg:phone":"+39 049 862 6808",
    "sg:postcode":"35020",
    "sg:province":"Padova",
    "wof:name":"New Teknik S.r.l.",
    "wof:placetype":"venue"
},
  "geometry": {"coordinates":[11.82767,45.342094],"type":"Point"}
}