{
  "type": "Feature",
  "properties": {
    "addr:full":"64014 Martinsicuro Martinsicuro Teramo 64014",
    "addr:postcode":"64014;64014",
    "iso:country":"IT",
    "sg:address":"64014 Martinsicuro",
    "sg:city":"Martinsicuro",
    "sg:orig_category":"Nautica. Accessori Dei Mezzi Di Trasporto",
    "sg:phone":"+39 0861 762347",
    "sg:postcode":"64014",
    "sg:province":"Teramo",
    "wof:name":"Minnozzi Stefano",
    "wof:placetype":"venue"
},
  "geometry": {"coordinates":[13.917053,42.86697],"type":"Point"}
}