{
  "type": "Feature",
  "properties": {
    "iso:country":"IT",
    "sg:address":"57023 Cecina",
    "sg:city":"Cecina",
    "sg:orig_category":"Utensili Meccanici E Materiali",
    "sg:phone":"+39 0586 662247",
    "sg:postcode":"57023",
    "sg:province":"Livorno",
    "wof:name":"Galassi Nadia",
    "wof:placetype":"venue"
},
  "geometry": {"coordinates":[10.514624,43.32716],"type":"Point"}
}