{
  "type": "Feature",
  "properties": {
    "iso:country":"IT",
    "sg:address":"21057 Olgiate Olona",
    "sg:city":"Olgiate Olona",
    "sg:orig_category":"Abbigliamento Esterno, Maglierie E Pelliccerie",
    "sg:phone":"+39 0331 375760",
    "sg:postcode":"21057",
    "sg:province":"Varese",
    "wof:name":"Confezioni Gemj (s.r.l.)",
    "wof:placetype":"venue"
},
  "geometry": {"coordinates":[8.903342,45.753658],"type":"Point"}
}