{
  "type": "Feature",
  "properties": {
    "iso:country":"IT",
    "sg:address":"25, Viale Del Lavoro 37036 San Martino Buon Albergo",
    "sg:city":"San Martino Buon Albergo",
    "sg:classifiers":[
        {
            "category":"Professional",
            "subcategory":"Engineering",
            "type":"Services"
        }
    ],
    "sg:phone":"+39 39045990078",
    "sg:postcode":"37036",
    "sg:province":"Verona",
    "sg:tags":[
        "machine",
        "-",
        "mechanical"
    ],
    "wof:name":"Dalla Riva G. & Figli (s.n.c.)",
    "wof:placetype":"venue"
},
  "geometry": {"coordinates":[11.091532,45.414051],"type":"Point"}
}