{
  "type": "Feature",
  "properties": {
    "iso:country":"IT",
    "sg:address":"20122 Milano",
    "sg:city":"Milano",
    "sg:orig_category":"Non-classified Establishments",
    "sg:phone":"+39 02 5519 0349",
    "sg:postcode":"20122",
    "sg:province":"Milano",
    "wof:name":"Morandotti Laura",
    "wof:placetype":"venue"
},
  "geometry": {"coordinates":[9.199288,45.456207],"type":"Point"}
}