{
  "type": "Feature",
  "properties": {
    "addr:full":"Km. 27.650, Via Pontina 00040 Pomezia Pomezia Roma 00040",
    "addr:postcode":"00040;roma 00040",
    "addr:street":"Km. 27.650 Via Pontina",
    "iso:country":"IT",
    "sg:address":"Km. 27.650, Via Pontina 00040 Pomezia",
    "sg:city":"Pomezia",
    "sg:classifiers":[
        {
            "category":"Food & Beverages",
            "subcategory":"Groceries & Convenience Stores",
            "type":"Retail Goods"
        }
    ],
    "sg:phone":"+39 39069106911",
    "sg:postcode":"00040",
    "sg:province":"Roma",
    "sg:tags":[
        "product",
        "related"
    ],
    "wof:name":"Ica Sud Spa",
    "wof:placetype":"venue"
},
  "geometry": {"coordinates":[12.4823246002,41.8954658508],"type":"Point"}
}