{
  "type": "Feature",
  "properties": {
    "iso:country":"IT",
    "sg:address":"59016 Poggio A Caiano",
    "sg:city":"Poggio a Caiano",
    "sg:orig_category":"Metalli E Leghe",
    "sg:phone":"+39 055 879 8811",
    "sg:postcode":"59016",
    "sg:province":"Prato",
    "wof:name":"Silly Di Zanirato Liliana",
    "wof:placetype":"venue"
},
  "geometry": {"coordinates":[11.0616760254,43.8099365234],"type":"Point"}
}