{
  "type": "Feature",
  "properties": {
    "iso:country":"IT",
    "sg:address":"20156 Milano",
    "sg:city":"Milano",
    "sg:orig_category":"Forniture Per Attivita' Industriali",
    "sg:phone":"+39 02 3340 0266",
    "sg:postcode":"20156",
    "sg:province":"Milano",
    "sg:website":"http://www.dilanda.it",
    "wof:name":"Dilanda Di Capone Nicola",
    "wof:placetype":"venue"
},
  "geometry": {"coordinates":[9.1481275558,45.4948272705],"type":"Point"}
}