{
  "type": "Feature",
  "properties": {
    "addr:full":"40121 Bologna Bologna Bologna 40121",
    "addr:postcode":"40121;40121",
    "iso:country":"IT",
    "sg:address":"40121 Bologna",
    "sg:city":"Bologna",
    "sg:orig_category":"Filatelia",
    "sg:phone":"+39 051 237480",
    "sg:postcode":"40121",
    "sg:province":"Bologna",
    "wof:name":"Filatelia Riva Reno Snc Di Luciano Morselli & C.",
    "wof:placetype":"venue"
},
  "geometry": {"coordinates":[11.6568784714,44.9779129028],"type":"Point"}
}