{
  "type": "Feature",
  "properties": {
    "addr:full":"44015 Runco Runco Ferrara 44015",
    "addr:postcode":"44015;44015",
    "addr:street":"Runco Ferrara",
    "iso:country":"IT",
    "sg:address":"44015 Runco",
    "sg:city":"Runco",
    "sg:orig_category":"Prodotti E Manufatti In Materie Plastiche",
    "sg:phone":"+39 0532 327133",
    "sg:postcode":"44015",
    "sg:province":"Ferrara",
    "wof:name":"Mazzoni",
    "wof:placetype":"venue"
},
  "geometry": {"coordinates":[11.7768697739,44.727142334],"type":"Point"}
}