{
  "type": "Feature",
  "properties": {
    "iso:country":"IT",
    "sg:address":"12030 Sanfront",
    "sg:city":"Sanfront",
    "sg:orig_category":"Materiali Edili. Forniture Per Attivita' Industriali",
    "sg:phone":"+39 0175 948114",
    "sg:postcode":"12030",
    "sg:province":"Cuneo",
    "wof:name":"Gruppo Teknoquarz (s.p.a.)",
    "wof:placetype":"venue"
},
  "geometry": {"coordinates":[7.322632,44.662952],"type":"Point"}
}