{
  "type": "Feature",
  "properties": {
    "iso:country":"IT",
    "sg:address":"50142 Firenze",
    "sg:city":"Firenze",
    "sg:orig_category":"Forniture Per Abbigliamento E Pelletterie",
    "sg:phone":"+39 055 785406",
    "sg:postcode":"50142",
    "sg:province":"Firenze",
    "wof:name":"Andrea Guarnieri S.r.l.",
    "wof:placetype":"venue"
},
  "geometry": {"coordinates":[10.7479248047,43.6776199341],"type":"Point"}
}