{
  "type": "Feature",
  "properties": {
    "iso:country":"IT",
    "sg:address":"47023 Cesena",
    "sg:city":"Cesena",
    "sg:orig_category":"Scuole E Servizi Scolastici. Ricerca, Selezione E Formazione Del Personale",
    "sg:phone":"+39 0547 612346",
    "sg:postcode":"47023",
    "sg:province":"Forl\u00ec-Cesena",
    "sg:website":"http://www.lordbyron.it",
    "wof:name":"Lord Byron Srl",
    "wof:placetype":"venue"
},
  "geometry": {"coordinates":[11.980461,43.994766],"type":"Point"}
}