{
  "type": "Feature",
  "properties": {
    "iso:country":"IT",
    "sg:address":"59, V. G. Pastore",
    "sg:classifiers":[
        {
            "category":"Shopping",
            "subcategory":"Clothing, Apparel, & Fashions",
            "type":"Retail Goods"
        }
    ],
    "sg:phone":"+39 0541 733778",
    "sg:province":"Viserba47811 Rimini",
    "sg:tags":[
        "clothes"
    ],
    "sg:website":"http://www.promemoriamoda.com",
    "wof:name":"Promemoria Srl",
    "wof:placetype":"venue"
},
  "geometry": {"coordinates":[12.566257,44.06078],"type":"Point"}
}