{
  "type": "Feature",
  "properties": {
    "addr:full":"25/3, V. Andreuzza 33030 Buia Udine 33030",
    "addr:housenumber":"25 / 3 v.",
    "addr:postcode":"33030;33030",
    "addr:street":"Andreuzza",
    "iso:country":"IT",
    "sg:address":"25/3, V. Andreuzza 33030 Buia",
    "sg:classifiers":[
        {
            "category":"Shopping",
            "type":"Retail Goods"
        }
    ],
    "sg:phone":"+39 0432 963440",
    "sg:postcode":"33030",
    "sg:province":"Udine",
    "sg:tags":[
        "finished",
        "-",
        "metallic"
    ],
    "sg:website":"http://www.friulanaflange.it",
    "wof:name":"Friulana Flange Srl",
    "wof:placetype":"venue"
},
  "geometry": {"coordinates":[13.0682983398,46.1840209961],"type":"Point"}
}