{
  "type": "Feature",
  "properties": {
    "iso:country":"IT",
    "sg:address":"44, Via Madonnina 26100 Cremona",
    "sg:city":"Cremona",
    "sg:classifiers":[
        {
            "category":"Professional",
            "subcategory":"Business Services",
            "type":"Services"
        }
    ],
    "sg:phone":"+39 39037236047",
    "sg:postcode":"26100",
    "sg:province":"Cremona",
    "sg:tags":[
        "advice"
    ],
    "wof:name":"Cosmos Italia Srl",
    "wof:placetype":"venue"
},
  "geometry": {"coordinates":[10.034202,45.126217],"type":"Point"}
}