{
  "type": "Feature",
  "properties": {
    "addr:full":"11, Via Vernazzola 27024 Cilavegna Cilavegna Pavia 27024",
    "addr:postcode":"27024;27024",
    "addr:street":"Via Vernazzola",
    "iso:country":"IT",
    "sg:address":"11, Via Vernazzola 27024 Cilavegna",
    "sg:city":"Cilavegna",
    "sg:classifiers":[
        {
            "category":"Personal",
            "subcategory":"Shoe Repair & Shine",
            "type":"Services"
        }
    ],
    "sg:phone":"+39 39038196189",
    "sg:postcode":"27024",
    "sg:province":"Pavia",
    "sg:tags":[
        "leather"
    ],
    "wof:name":"Calzaturificio Pezzana S.r.l.",
    "wof:placetype":"venue"
},
  "geometry": {"coordinates":[8.744326,45.305553],"type":"Point"}
}