{
  "type": "Feature",
  "properties": {
    "iso:country":"IT",
    "sg:address":"73041 Carmiano",
    "sg:city":"Carmiano",
    "sg:orig_category":"Pubblicita', Marketing E Comunicazione",
    "sg:phone":"+39 0832 601537",
    "sg:postcode":"73041",
    "sg:province":"Lecce",
    "wof:name":"Media Service Snc Di Carrozzo Daniele E Quarta Paolo",
    "wof:placetype":"venue"
},
  "geometry": {"coordinates":[18.0361557007,40.3409309387],"type":"Point"}
}