{
  "type": "Feature",
  "properties": {
    "addr:full":"28, Strada Statale 45 Quarto 29020 Gossolengo Gossolengo Piacenza 29020",
    "addr:housenumber":"45",
    "addr:postcode":"29020;29020",
    "addr:street":"Strada Statale",
    "iso:country":"IT",
    "sg:address":"28, Strada Statale 45 Quarto 29020 Gossolengo",
    "sg:city":"Gossolengo",
    "sg:classifiers":[
        {
            "category":"Shopping",
            "subcategory":"Clothing, Apparel, & Fashions",
            "type":"Retail Goods"
        }
    ],
    "sg:phone":"+39 0523 557178",
    "sg:postcode":"29020",
    "sg:province":"Piacenza",
    "sg:tags":[
        "clothes"
    ],
    "wof:name":"Baby Moda Di Soffientini Carla E C. S.a.s.",
    "wof:placetype":"venue"
},
  "geometry": {"coordinates":[9.654645,44.988014],"type":"Point"}
}