{
  "type": "Feature",
  "properties": {
    "addr:full":"25036 Palazzolo Sull'oglio Brescia 25036",
    "addr:postcode":"25036;25036",
    "iso:country":"IT",
    "sg:address":"25036 Palazzolo Sull'oglio",
    "sg:orig_category":"Apparecchiature E Sistemi Per Imballaggio E Confezionamento",
    "sg:phone":"+39 030 740 5711",
    "sg:postcode":"25036",
    "sg:province":"Brescia",
    "wof:name":"Tetra Laval Food Tiromat Spa",
    "wof:placetype":"venue"
},
  "geometry": {"coordinates":[9.878014,45.588829],"type":"Point"}
}