{
  "type": "Feature",
  "properties": {
    "iso:country":"IT",
    "sg:address":"19020 Vezzano Ligure",
    "sg:city":"Ceparana",
    "sg:orig_category":"Bevande, Vini E Liquori",
    "sg:phone":"+39 0187 931261",
    "sg:postcode":"19020",
    "sg:province":"La Spezia",
    "sg:website":"http://www.partesa.it",
    "wof:name":"Partesa Lunezia Srl",
    "wof:placetype":"venue"
},
  "geometry": {"coordinates":[9.875456,44.170643],"type":"Point"}
}