{
  "type": "Feature",
  "properties": {
    "addr:full":"148, Via Limite 50013 Campi Bisenzio Campi Bisenzio Firenze 50013",
    "addr:housenumber":"148",
    "addr:postcode":"50013;50013",
    "addr:street":"Via Limite;Bisenzio",
    "iso:country":"IT",
    "sg:address":"148, Via Limite 50013 Campi Bisenzio",
    "sg:city":"Campi Bisenzio",
    "sg:classifiers":[
        {
            "category":"Shopping",
            "subcategory":"Computers & Home Electronics",
            "type":"Retail Goods"
        }
    ],
    "sg:phone":"+39 39055894881",
    "sg:postcode":"50013",
    "sg:province":"Firenze",
    "sg:tags":[
        "electronic",
        "electrical",
        "equipment"
    ],
    "wof:name":"Dura Lamp Spa",
    "wof:placetype":"venue"
},
  "geometry": {"coordinates":[11.16257,43.83651],"type":"Point"}
}