{
  "type": "Feature",
  "properties": {
    "iso:country":"IT",
    "sg:address":"9, C. Fogazzaro 36100 Vicenza",
    "sg:city":"Vicenza",
    "sg:classifiers":[
        {
            "category":"Sports & Exercise",
            "subcategory":"Playing Field",
            "type":"Entertainment"
        }
    ],
    "sg:phone":"+39 0444 321856",
    "sg:postcode":"36100",
    "sg:province":"Vicenza",
    "sg:tags":[
        "game"
    ],
    "sg:website":"http://www.paginegialle.it/albertoortolani",
    "wof:name":"Ortolani Alberto",
    "wof:placetype":"venue"
},
  "geometry": {"coordinates":[11.543889,45.547386],"type":"Point"}
}