{
  "type": "Feature",
  "properties": {
    "addr:full":"00146 Roma Roma Roma 00146",
    "addr:postcode":"00146;00146",
    "iso:country":"IT",
    "sg:address":"00146 Roma",
    "sg:city":"Roma",
    "sg:orig_category":"Servizi E Lavori Per Abbigliamento E Pelletterie",
    "sg:phone":"+39 06 556 0253",
    "sg:postcode":"00146",
    "sg:province":"Roma",
    "wof:name":"Trebbi Agostina",
    "wof:placetype":"venue"
},
  "geometry": {"coordinates":[12.46963,41.863461],"type":"Point"}
}