{
  "type": "Feature",
  "properties": {
    "addr:full":"41100 Modena Modena Modena 41100",
    "addr:postcode":"41100;41100",
    "iso:country":"IT",
    "sg:address":"41100 Modena",
    "sg:city":"Modena",
    "sg:orig_category":"Automobili E Mezzi Di Trasporto",
    "sg:phone":"+39 059 315015",
    "sg:postcode":"41100",
    "sg:province":"Modena",
    "wof:name":"C.b. Snc Di Bonezzi G. & C.",
    "wof:placetype":"venue"
},
  "geometry": {"coordinates":[10.938402,44.669456],"type":"Point"}
}