{
  "type": "Feature",
  "properties": {
    "addr:full":"85055 Picerno Picerno Potenza 85055",
    "addr:postcode":"85055;85055",
    "iso:country":"IT",
    "sg:address":"85055 Picerno",
    "sg:city":"Picerno",
    "sg:orig_category":"Imprese Di Costruzioni Civili Ed Industriali",
    "sg:phone":"+39 0971 995603",
    "sg:postcode":"85055",
    "sg:province":"Potenza",
    "wof:name":"Co.ge.f. Srl",
    "wof:placetype":"venue"
},
  "geometry": {"coordinates":[15.641246,40.641647],"type":"Point"}
}