{
  "type": "Feature",
  "properties": {
    "iso:country":"IT",
    "sg:address":"23873 Missaglia",
    "sg:city":"Missaglia",
    "sg:orig_category":"Dolciumi E Gelati",
    "sg:phone":"+39 039 920 0691",
    "sg:postcode":"23873",
    "sg:province":"Lecco",
    "wof:name":"Apicoltura Dei Fiori Di Casiraghi Gaudenzio",
    "wof:placetype":"venue"
},
  "geometry": {"coordinates":[9.347558,45.697399],"type":"Point"}
}