{
  "type": "Feature",
  "properties": {
    "iso:country":"IT",
    "sg:address":"97, Via Dei Missaglia 20142 Milano",
    "sg:city":"Milano",
    "sg:classifiers":[
        {
            "category":"Shopping",
            "subcategory":"Clothing, Apparel, & Fashions",
            "type":"Retail Goods"
        }
    ],
    "sg:phone":"+39 39028939111",
    "sg:postcode":"20142",
    "sg:province":"Milano",
    "sg:tags":[
        "clothes"
    ],
    "wof:name":"Puma Italia S.r.l.",
    "wof:placetype":"venue"
},
  "geometry": {"coordinates":[9.174726,45.410095],"type":"Point"}
}