{
  "type": "Feature",
  "properties": {
    "iso:country":"IT",
    "sg:address":"16010 Savignone",
    "sg:city":"Savignone",
    "sg:orig_category":"Pensioni",
    "sg:phone":"+39 010 967 7040",
    "sg:postcode":"16010",
    "sg:province":"Genova",
    "wof:name":"Ristorante Chiara",
    "wof:placetype":"venue"
},
  "geometry": {"coordinates":[8.9884624481,44.5653152466],"type":"Point"}
}