{
  "type": "Feature",
  "properties": {
    "addr:full":"24021 Albino Albino Bergamo 24021",
    "addr:postcode":"24021;24021",
    "iso:country":"IT",
    "sg:address":"24021 Albino",
    "sg:city":"Albino",
    "sg:orig_category":"Macchine, Impianti Ed Attrezzature Per Agricoltura E Zootecnia",
    "sg:phone":"+39 035 752949",
    "sg:postcode":"24021",
    "sg:province":"Bergamo",
    "sg:website":"http://www.carrarairrigazione.com",
    "wof:name":"Carrara Marco - Carrara Irrigazione",
    "wof:placetype":"venue"
},
  "geometry": {"coordinates":[9.736801,45.738033],"type":"Point"}
}