{
  "type": "Feature",
  "properties": {
    "iso:country":"IT",
    "sg:address":"20099 Sesto San Giovanni",
    "sg:city":"Sesto San Giovanni",
    "sg:orig_category":"Climatizzazione E Condizionamento, Apparecchiature E Servizi",
    "sg:phone":"+39 02 240 1751",
    "sg:postcode":"20099",
    "sg:province":"Milano",
    "wof:name":"Aeromeccanica Stranich Spa",
    "wof:placetype":"venue"
},
  "geometry": {"coordinates":[9.260974,45.527172],"type":"Point"}
}