{
  "type": "Feature",
  "properties": {
    "iso:country":"IT",
    "sg:address":"Via Partanna Mondello 46 90147 Palermo",
    "sg:city":"Palermo",
    "sg:classifiers":[
        {
            "category":"Autos & Motor Vehicles",
            "subcategory":"Fuel & Gas Station",
            "type":"Retail Goods"
        }
    ],
    "sg:phone":"+39 091 532740",
    "sg:postcode":"90147",
    "sg:province":"Palermo",
    "sg:tags":[
        "ice-cream",
        "paste",
        "powder"
    ],
    "sg:website":"www.elenka.it",
    "wof:name":"Elenka S.p.a.",
    "wof:placetype":"venue"
},
  "geometry": {"coordinates":[12.941817,37.914299],"type":"Point"}
}