{
  "type": "Feature",
  "properties": {
    "addr:full":"20, Via Dell' Industria 61037 Mondolfo Mondolfo Pesaro E Urbino 61037",
    "addr:postcode":"61037;61037",
    "addr:street":"Via Dell ' Industria",
    "iso:country":"IT",
    "sg:address":"20, Via Dell' Industria 61037 Mondolfo",
    "sg:city":"Mondolfo",
    "sg:classifiers":[
        {
            "category":"Manufacturing",
            "subcategory":"Metals",
            "type":"Manufacturing & Wholesale Goods"
        }
    ],
    "sg:phone":"+39 0721 930248",
    "sg:postcode":"61037",
    "sg:province":"Pesaro E Urbino",
    "sg:tags":[
        "metallurgy",
        "metalworking"
    ],
    "wof:name":"Mondolfo Ferro (s.p.a.)",
    "wof:placetype":"venue"
},
  "geometry": {"coordinates":[13.1057605743,43.7417602539],"type":"Point"}
}