{
  "type": "Feature",
  "properties": {
    "addr:full":"8, Via Genova 41016 Novi Di Modena Novi di Modena Modena 41016",
    "addr:postcode":"41016;41016",
    "addr:street":"Via Genova",
    "iso:country":"IT",
    "sg:address":"8, Via Genova 41016 Novi Di Modena",
    "sg:city":"Novi di Modena",
    "sg:classifiers":[
        {
            "category":"Food & Beverages",
            "subcategory":"Groceries & Convenience Stores",
            "type":"Retail Goods"
        }
    ],
    "sg:phone":"+39 39059677390",
    "sg:postcode":"41016",
    "sg:province":"Modena",
    "sg:tags":[
        "product",
        "related"
    ],
    "wof:name":"Comal Srl",
    "wof:placetype":"venue"
},
  "geometry": {"coordinates":[10.9252195358,44.6470794678],"type":"Point"}
}