{
  "type": "Feature",
  "properties": {
    "addr:full":"12048 Sommariva Del Bosco Sommariva del Bosco Cuneo 12048",
    "addr:postcode":"12048;12048",
    "iso:country":"IT",
    "sg:address":"12048 Sommariva Del Bosco",
    "sg:city":"Sommariva del Bosco",
    "sg:orig_category":"Accessori Dei Mezzi Di Trasporto. Riparazione Dei Mezzi Di Trasporto",
    "sg:phone":"+39 0172 54057",
    "sg:postcode":"12048",
    "sg:province":"Cuneo",
    "wof:name":"Vaula Guido",
    "wof:placetype":"venue"
},
  "geometry": {"coordinates":[7.781394,44.772194],"type":"Point"}
}