{
  "type": "Feature",
  "properties": {
    "iso:country":"IT",
    "sg:address":"Via Verzelloni 14 42015 Correggio",
    "sg:classifiers":[
        {
            "category":"Utilities",
            "subcategory":"Recycling",
            "type":"Services"
        }
    ],
    "sg:phone":"+39 0522 694935",
    "sg:postcode":"42015",
    "sg:province":"Reggio Nell'Emilia",
    "sg:tags":[
        "thermoplastic"
    ],
    "sg:website":"www.2g-r.com",
    "wof:name":"2gr Di Gobbi Luciano E C. Snc",
    "wof:placetype":"venue"
},
  "geometry": {"coordinates":[10.783288,44.760376],"type":"Point"}
}