{
  "type": "Feature",
  "properties": {
    "iso:country":"IT",
    "sg:address":"21054 Fagnano Olona",
    "sg:city":"Fagnano Olona",
    "sg:orig_category":"Condizionamento Aria Impianti - Installazione E Manutenzione",
    "sg:phone":"+39 0331 610903",
    "sg:postcode":"21054",
    "sg:province":"Varese",
    "wof:name":"Termoclima Di Busacca Salvatore",
    "wof:placetype":"venue"
},
  "geometry": {"coordinates":[8.857634,45.667076],"type":"Point"}
}