{
  "type": "Feature",
  "properties": {
    "addr:full":"95025 Aci S. Antonio Catania 95025",
    "addr:postcode":"95025;95025",
    "addr:street":"Aci S.",
    "iso:country":"IT",
    "sg:address":"95025 Aci S. Antonio",
    "sg:orig_category":"Elettronica Professionale E Di Consumo. Automazione E Macchine Per Ufficio. Forniture Industriali Per Prevenzione, Controllo E Sicurezza",
    "sg:phone":"+39 095 702 1159",
    "sg:postcode":"95025",
    "sg:province":"Catania",
    "wof:name":"Electric Service Di Russo Lorenzo",
    "wof:placetype":"venue"
},
  "geometry": {"coordinates":[15.096754,37.506611],"type":"Point"}
}