{
  "type": "Feature",
  "properties": {
    "addr:full":"20149 Milano Milano Milano 20149",
    "addr:postcode":"20149;20149",
    "iso:country":"IT",
    "sg:address":"20149 Milano",
    "sg:city":"Milano",
    "sg:orig_category":"Consulenza Di Direzione Ed Organizzazione Aziendale",
    "sg:phone":"+39 02 469 3701",
    "sg:postcode":"20149",
    "sg:province":"Milano",
    "sg:website":"http://www.isoformazione.it",
    "wof:name":"I.s.o. Srl",
    "wof:placetype":"venue"
},
  "geometry": {"coordinates":[9.148433,45.472786],"type":"Point"}
}