{
  "type": "Feature",
  "properties": {
    "iso:country":"IT",
    "sg:address":"28060 Mandello Vitta",
    "sg:city":"Mandello Vitta",
    "sg:orig_category":"Prodotti Alimentari",
    "sg:phone":"+39 0341 731522",
    "sg:postcode":"28060",
    "sg:province":"Novara",
    "wof:name":"Pasta E Fantasia",
    "wof:placetype":"venue"
},
  "geometry": {"coordinates":[8.4609527588,45.4967422485],"type":"Point"}
}