{
  "type": "Feature",
  "properties": {
    "addr:full":"13856 Vigliano Biellese Vigliano Biellese Biella 13856",
    "addr:postcode":"13856;13856",
    "iso:country":"IT",
    "sg:address":"13856 Vigliano Biellese",
    "sg:city":"Vigliano Biellese",
    "sg:orig_category":"Campionari",
    "sg:phone":"+39 015 812 9908",
    "sg:postcode":"13856",
    "sg:province":"Biella",
    "wof:name":"Erre.bi Cartotecnica Di Ramella E Barbera",
    "wof:placetype":"venue"
},
  "geometry": {"coordinates":[8.125223,45.559258],"type":"Point"}
}