{
  "type": "Feature",
  "properties": {
    "iso:country":"IT",
    "sg:address":"17100 Savona",
    "sg:city":"Savona",
    "sg:orig_category":"Cine-foto-ottica",
    "sg:phone":"+39 019 853123",
    "sg:postcode":"17100",
    "sg:province":"Savona",
    "wof:name":"Foto Market Di Monteleone Simona",
    "wof:placetype":"venue"
},
  "geometry": {"coordinates":[8.429389,44.342548],"type":"Point"}
}