{
  "type": "Feature",
  "properties": {
    "iso:country":"IT",
    "sg:address":"38030 Castello Molina Di Fiemme",
    "sg:city":"Castello Molina di Fiemme",
    "sg:orig_category":"Materiali Edili",
    "sg:phone":"+39 0462 340052",
    "sg:postcode":"38030",
    "sg:province":"Trento",
    "wof:name":"Thaler R. & C. S.p.a.",
    "wof:placetype":"venue"
},
  "geometry": {"coordinates":[11.429472,46.281887],"type":"Point"}
}