{
  "type": "Feature",
  "properties": {
    "iso:country":"IT",
    "sg:address":"30123 Venezia",
    "sg:city":"Dorsoduro",
    "sg:orig_category":"Arte Ed Artigianato Artistico. Scuole E Servizi Scolastici. Servizi Ausiliari Di Analisi, Controllo E Ricerca",
    "sg:phone":"+39 041 241 3752",
    "sg:postcode":"30123",
    "sg:province":"Venezia",
    "wof:name":"Accademia Di Belle Arti",
    "wof:placetype":"venue"
},
  "geometry": {"coordinates":[12.331888,45.429527],"type":"Point"}
}