{
  "type": "Feature",
  "properties": {
    "iso:country":"IT",
    "sg:address":"65022 Bussi Sul Tirino",
    "sg:city":"Bussi sul Tirino",
    "sg:orig_category":"Zootecnia E Pesca, Allevamento Piccoli Animali",
    "sg:phone":"+39 085 980371",
    "sg:postcode":"65022",
    "sg:province":"Pescara",
    "wof:name":"Di Carlo Mariano",
    "wof:placetype":"venue"
},
  "geometry": {"coordinates":[13.824706,42.207672],"type":"Point"}
}