{
  "type": "Feature",
  "properties": {
    "iso:country":"IT",
    "sg:address":"81, Via Schiavonesca 31030 Altivole",
    "sg:city":"Altivole",
    "sg:classifiers":[
        {
            "category":"Home & Garden",
            "subcategory":"Home Furnishings",
            "type":"Retail Goods"
        }
    ],
    "sg:phone":"+39 0423 915557",
    "sg:postcode":"31030",
    "sg:province":"Treviso",
    "sg:tags":[
        "household"
    ],
    "wof:name":"San Marco S.r.l.",
    "wof:placetype":"venue"
},
  "geometry": {"coordinates":[11.9530897141,45.7328224182],"type":"Point"}
}