{
  "type": "Feature",
  "properties": {
    "iso:country":"IT",
    "sg:address":"20154 Milano",
    "sg:city":"Milano",
    "sg:orig_category":"Agenzie D'affari E Servizi Commerciali",
    "sg:phone":"+39 02 317133",
    "sg:postcode":"20154",
    "sg:province":"Milano",
    "wof:name":"Stock Andrea",
    "wof:placetype":"venue"
},
  "geometry": {"coordinates":[9.16655,45.48735],"type":"Point"}
}