{
  "type": "Feature",
  "properties": {
    "addr:full":"1, Zona Industriale 66050 Dogliola Dogliola Chieti 66050",
    "addr:housenumber":"1",
    "addr:postcode":"66050;66050",
    "addr:street":"Zona Industriale",
    "iso:country":"IT",
    "sg:address":"1, Zona Industriale 66050 Dogliola",
    "sg:city":"Dogliola",
    "sg:classifiers":[
        {
            "category":"Shopping",
            "type":"Retail Goods"
        }
    ],
    "sg:phone":"+39 0873 950009",
    "sg:postcode":"66050",
    "sg:province":"Chieti",
    "sg:tags":[
        "finished",
        "-",
        "metallic"
    ],
    "wof:name":"Far - Plast - Casa Srl",
    "wof:placetype":"venue"
},
  "geometry": {"coordinates":[14.1671514511,42.3517913818],"type":"Point"}
}