{
  "type": "Feature",
  "properties": {
    "iso:country":"IT",
    "sg:address":"63039 San Benedetto Del Tronto",
    "sg:city":"San Benedetto del Tronto",
    "sg:classifiers":[
        {
            "category":"Communications",
            "subcategory":"Film & Video Production",
            "type":"Services"
        }
    ],
    "sg:phone":"+39 0735 588390",
    "sg:postcode":"63039",
    "sg:province":"Ascoli Piceno",
    "sg:tags":[
        "supply",
        "cinema",
        "instruments",
        "medical-health",
        "cameras",
        "equipment",
        "orthopedic",
        "products",
        "systems",
        "health",
        "optical",
        "hospital"
    ],
    "wof:name":"Ottica Galilei",
    "wof:placetype":"venue"
},
  "geometry": {"coordinates":[13.629772,42.821072],"type":"Point"}
}