{
  "type": "Feature",
  "properties": {
    "iso:country":"IT",
    "sg:address":"10156 Torino",
    "sg:city":"Torino",
    "sg:orig_category":"Spedizioni Aeree, Marittime E Terrestri",
    "sg:phone":"+39 011 450 0050",
    "sg:postcode":"10156",
    "sg:province":"Torino",
    "sg:website":"http://www.smile-italia.com",
    "wof:name":"S.m.i.l.e Sas Di Amalia Bosio E C.",
    "wof:placetype":"venue"
},
  "geometry": {"coordinates":[7.70615,45.119347],"type":"Point"}
}