{
  "type": "Feature",
  "properties": {
    "addr:full":"112, Frazione Castione Marchesi 43036 Fidenza Castione Marchesi Parma 43036",
    "addr:postcode":"43036;43036",
    "addr:street":"Frazione Castione Marchesi",
    "iso:country":"IT",
    "sg:address":"112, Frazione Castione Marchesi 43036 Fidenza",
    "sg:city":"Castione Marchesi",
    "sg:classifiers":[
        {
            "category":"Manufacturing",
            "subcategory":"Metals",
            "type":"Manufacturing & Wholesale Goods"
        }
    ],
    "sg:phone":"+39 39052467288",
    "sg:postcode":"43036",
    "sg:province":"Parma",
    "sg:tags":[
        "processing"
    ],
    "wof:name":"S.i.c.o.r.t. (s.n.c.)",
    "wof:placetype":"venue"
},
  "geometry": {"coordinates":[10.0409069061,44.9157409668],"type":"Point"}
}