{
  "type": "Feature",
  "properties": {
    "addr:full":"06012 Citt\u00e0 Di Castello Cerbara Perugia 06012",
    "addr:postcode":"06012;06012",
    "iso:country":"IT",
    "sg:address":"06012 Citt\u00e0 Di Castello",
    "sg:city":"Cerbara",
    "sg:classifiers":[
        {
            "category":"Banks & Credit Unions",
            "subcategory":"Atm",
            "type":"Services"
        }
    ],
    "sg:phone":"+39 075 851 2064",
    "sg:postcode":"06012",
    "sg:province":"Perugia",
    "sg:tags":[
        "refuse",
        "supply",
        "disposal",
        "environmental",
        "protection",
        "machinery"
    ],
    "wof:name":"Selena Srl",
    "wof:placetype":"venue"
},
  "geometry": {"coordinates":[12.208383,43.503376],"type":"Point"}
}