{
  "type": "Feature",
  "properties": {
    "iso:country":"IT",
    "sg:address":"29027 Podenzano",
    "sg:city":"Podenzano",
    "sg:orig_category":"Ruote E Cerchioni Per Autoveicoli",
    "sg:phone":"+39 0523 524131",
    "sg:postcode":"29027",
    "sg:province":"Piacenza",
    "wof:name":"Rigeneral Snc Di Costa Luigi E C.",
    "wof:placetype":"venue"
},
  "geometry": {"coordinates":[9.687751,44.998363],"type":"Point"}
}