{
  "type": "Feature",
  "properties": {
    "addr:full":"00054 Fiumicino Fiumicino Roma 00054",
    "addr:postcode":"00054;roma 00054",
    "iso:country":"IT",
    "sg:address":"00054 Fiumicino",
    "sg:city":"Fiumicino",
    "sg:orig_category":"Alberghi E Strutture Extra Alberghiere",
    "sg:phone":"+39 06 652 1659",
    "sg:postcode":"00054",
    "sg:province":"Roma",
    "wof:name":"Traiano 2000 Srl",
    "wof:placetype":"venue"
},
  "geometry": {"coordinates":[12.227221,41.770168],"type":"Point"}
}