{
  "type": "Feature",
  "properties": {
    "addr:full":"Via Legnaghi Corradini 30a 37030 Cazzano Di Tramigna Cazzano di Tramigna Verona 37030",
    "addr:housenumber":"30a",
    "addr:postcode":"37030;37030",
    "addr:street":"Via Legnaghi Corradini;Di Tramigna",
    "iso:country":"IT",
    "sg:address":"Via Legnaghi Corradini 30a 37030 Cazzano Di Tramigna",
    "sg:city":"Cazzano di Tramigna",
    "sg:classifiers":[
        {
            "category":"Winery",
            "type":"Food & Drink"
        }
    ],
    "sg:phone":"+39 045 782 0516",
    "sg:postcode":"37030",
    "sg:province":"Verona",
    "sg:tags":[
        "sparkling",
        "wine"
    ],
    "sg:website":"www.contrispumanti.it",
    "wof:name":"Contri Spumanti Spa",
    "wof:placetype":"venue"
},
  "geometry": {"coordinates":[11.202588,45.474964],"type":"Point"}
}