{
  "type": "Feature",
  "properties": {
    "iso:country":"IT",
    "sg:address":"20084 Lacchiarella",
    "sg:city":"Lacchiarella",
    "sg:orig_category":"Elettrotecnica Professionale E Di Consumo. Forniture Alle Strutture Ricettive. Arredi Ed Attrezzature Per Attivita' Commerciali Ed Artigianali",
    "sg:phone":"+39 02 9003 3249",
    "sg:postcode":"20084",
    "sg:province":"Milano",
    "wof:name":"Cws Italia S.p.a.",
    "wof:placetype":"venue"
},
  "geometry": {"coordinates":[9.148467,45.319118],"type":"Point"}
}