{
  "type": "Feature",
  "properties": {
    "iso:country":"IT",
    "sg:address":"20144 Milano",
    "sg:city":"Milano",
    "sg:orig_category":"Ospedali E Servizi Sanitari. Servizi Sociali. Associazioni Ed Organismi Di Interesse Pubblico",
    "sg:phone":"+39 02 469 9252",
    "sg:postcode":"20144",
    "sg:province":"Milano",
    "wof:name":"S.v.s.s. Servizi Volontariato Sostegno Sociale",
    "wof:placetype":"venue"
},
  "geometry": {"coordinates":[9.158965,45.460163],"type":"Point"}
}