{
  "type": "Feature",
  "properties": {
    "iso:country":"IT",
    "sg:address":"34170 Gorizia",
    "sg:city":"Gorizia",
    "sg:orig_category":"Motori Ed Organi Di Trasmissione",
    "sg:phone":"+39 0481 20425",
    "sg:postcode":"34170",
    "sg:province":"Gorizia",
    "wof:name":"A. Mlakar Srl",
    "wof:placetype":"venue"
},
  "geometry": {"coordinates":[13.5991439819,45.9438247681],"type":"Point"}
}