{
  "type": "Feature",
  "properties": {
    "iso:country":"IT",
    "sg:address":"87100 Cosenza",
    "sg:city":"Cosenza",
    "sg:orig_category":"Assicurazioni",
    "sg:phone":"+39 0984 791532",
    "sg:postcode":"87100",
    "sg:province":"Cosenza",
    "wof:name":"Azzurra Snc",
    "wof:placetype":"venue"
},
  "geometry": {"coordinates":[16.250376,39.294636],"type":"Point"}
}