{
  "type": "Feature",
  "properties": {
    "addr:full":"20159 Milano Milano Milano 20159",
    "addr:postcode":"20159;20159",
    "iso:country":"IT",
    "sg:address":"20159 Milano",
    "sg:city":"Milano",
    "sg:classifiers":[
        {
            "category":"Health Services",
            "subcategory":"Health Practitioner",
            "type":"Services"
        }
    ],
    "sg:phone":"+39 02 688 4017",
    "sg:postcode":"20159",
    "sg:province":"Milano",
    "sg:tags":[
        "medici"
    ],
    "wof:name":"Lureti Gianfranco",
    "wof:placetype":"venue"
},
  "geometry": {"coordinates":[9.191117,45.494087],"type":"Point"}
}