{
  "type": "Feature",
  "properties": {
    "iso:country":"IT",
    "sg:address":"35030 Bastia",
    "sg:city":"Bastia",
    "sg:orig_category":"Prodotti E Manufatti In Gomma",
    "sg:phone":"+39 049 991 0204",
    "sg:postcode":"35030",
    "sg:province":"Padova",
    "wof:name":"Veneta Decalcogomme (s.r.l.)",
    "wof:placetype":"venue"
},
  "geometry": {"coordinates":[11.644944191,45.3825149536],"type":"Point"}
}