{
  "type": "Feature",
  "properties": {
    "iso:country":"IT",
    "sg:address":"00147 Roma",
    "sg:city":"Roma",
    "sg:orig_category":"Amplificazione Sonora",
    "sg:phone":"+39 06 5160 5001",
    "sg:postcode":"00147",
    "sg:province":"Roma",
    "sg:website":"http://www.prosistem.it",
    "wof:name":"Prosistem Srl",
    "wof:placetype":"venue"
},
  "geometry": {"coordinates":[12.499729,41.865833],"type":"Point"}
}