{
  "type": "Feature",
  "properties": {
    "addr:full":"27020 Carbonara Al Ticino Carbonara al Ticino Pavia 27020",
    "addr:housenumber":"ticino",
    "addr:postcode":"27020;27020",
    "iso:country":"IT",
    "sg:address":"27020 Carbonara Al Ticino",
    "sg:city":"Carbonara al Ticino",
    "sg:orig_category":"Prodotti Chimici Di Base. Prodotti Cosmetici E Da Toeletta",
    "sg:phone":"+39 0382 567982",
    "sg:postcode":"27020",
    "sg:province":"Pavia",
    "wof:name":"P.a. Aromatics Srl",
    "wof:placetype":"venue"
},
  "geometry": {"coordinates":[9.0655164719,45.1587944031],"type":"Point"}
}