{
  "type": "Feature",
  "properties": {
    "addr:full":"97100 Ragusa Ragusa Ragusa 97100",
    "addr:postcode":"97100;97100",
    "iso:country":"IT",
    "sg:address":"97100 Ragusa",
    "sg:city":"Ragusa",
    "sg:orig_category":"Ospedali E Servizi Sanitari",
    "sg:phone":"+39 0932 624444",
    "sg:postcode":"97100",
    "sg:province":"Ragusa",
    "wof:name":"Spatuzza Giovanni & C. Snc",
    "wof:placetype":"venue"
},
  "geometry": {"coordinates":[14.737131,36.926693],"type":"Point"}
}