{
  "type": "Feature",
  "properties": {
    "addr:full":"00040 Pomezia Pomezia Roma 00040",
    "addr:postcode":"00040;roma 00040",
    "iso:country":"IT",
    "sg:address":"00040 Pomezia",
    "sg:city":"Pomezia",
    "sg:classifiers":[
        {
            "category":"Manufacturing",
            "subcategory":"Metals",
            "type":"Manufacturing & Wholesale Goods"
        }
    ],
    "sg:phone":"+39 06 912 0192",
    "sg:postcode":"00040",
    "sg:province":"Roma",
    "sg:tags":[
        "ferro"
    ],
    "wof:name":"Sider Pomezia Snc",
    "wof:placetype":"venue"
},
  "geometry": {"coordinates":[12.500784874,41.6832847595],"type":"Point"}
}