{
  "type": "Feature",
  "properties": {
    "iso:country":"IT",
    "sg:address":"28921 Verbania",
    "sg:city":"Verbania",
    "sg:orig_category":"Studi E Consulenze Amministrative, Commerciali E Aziendali. Banche E Servizi Finanziari. Agenzie D'affari E Servizi Commerciali. Consulenze Tecniche, Amministrative E Perizie",
    "sg:phone":"+39 0323 52385",
    "sg:postcode":"28921",
    "sg:province":"Verbano-Cusio-Ossola",
    "sg:website":"http://www.cnavco.it",
    "wof:name":"Cna Artigianato Vco",
    "wof:placetype":"venue"
},
  "geometry": {"coordinates":[8.272465,46.139969],"type":"Point"}
}