{
  "type": "Feature",
  "properties": {
    "iso:country":"IT",
    "sg:address":"18/20, V. Alessandro Volta",
    "sg:classifiers":[
        {
            "category":"Manufacturing",
            "subcategory":"Tools & Machinery",
            "type":"Manufacturing & Wholesale Goods"
        }
    ],
    "sg:phone":"+39 0429 86144",
    "sg:tags":[
        "leather",
        "equipment",
        "goods",
        "clothing"
    ],
    "sg:website":"http://www.technodry.it",
    "wof:name":"Techno-dry Macchine Lavaggio A Secco",
    "wof:placetype":"venue"
},
  "geometry": {"coordinates":[14.2817411423,40.8450622559],"type":"Point"}
}