{
  "type": "Feature",
  "properties": {
    "iso:country":"IT",
    "sg:address":"Via Rezzaia Ii 41 56024 Ponte A Egola",
    "sg:city":"Ponte a egola",
    "sg:orig_category":"Soles, Heels",
    "sg:phone":"+39 0571 485030",
    "sg:postcode":"56024",
    "sg:province":"Pisa",
    "sg:website":"www.guardolificiomambo.com",
    "wof:name":"Guardolificio Mambo Snc Di Bertini",
    "wof:placetype":"venue"
},
  "geometry": {"coordinates":[10.396585,43.716137],"type":"Point"}
}