{
  "type": "Feature",
  "properties": {
    "iso:country":"IT",
    "sg:address":"10095 Grugliasco",
    "sg:city":"Grugliasco",
    "sg:orig_category":"Materiali Edili",
    "sg:phone":"+39 011 314 9028",
    "sg:postcode":"10095",
    "sg:province":"Torino",
    "wof:name":"Beton Group",
    "wof:placetype":"venue"
},
  "geometry": {"coordinates":[7.591261,45.043808],"type":"Point"}
}