{
  "type": "Feature",
  "properties": {
    "addr:full":"20, Via Rescatti Pietro 25010 Brescia Brescia 25010",
    "addr:postcode":"25010;25010",
    "addr:street":"Via Rescatti Pietro",
    "iso:country":"IT",
    "sg:address":"20, Via Rescatti Pietro 25010 Brescia",
    "sg:classifiers":[
        {
            "category":"Retail",
            "subcategory":"Animal Services",
            "type":"Services"
        }
    ],
    "sg:phone":"+39 030 266 7121",
    "sg:postcode":"25010",
    "sg:province":"Brescia",
    "sg:tags":[
        "breeding"
    ],
    "wof:name":"Ce.a.b.",
    "wof:placetype":"venue"
},
  "geometry": {"coordinates":[10.20644,45.492985],"type":"Point"}
}