{
  "type": "Feature",
  "properties": {
    "iso:country":"IT",
    "sg:address":"20021 Bollate",
    "sg:city":"Bollate",
    "sg:orig_category":"Apparecchiature E Sistemi Per Imballaggio E Confezionamento",
    "sg:phone":"+39 02 3326 2265",
    "sg:postcode":"20021",
    "sg:province":"Milano",
    "wof:name":"Rotomac S.r.l.",
    "wof:placetype":"venue"
},
  "geometry": {"coordinates":[9.146313,45.563595],"type":"Point"}
}