{
  "type": "Feature",
  "properties": {
    "iso:country":"IT",
    "sg:address":"00152 Roma",
    "sg:city":"Roma",
    "sg:orig_category":"Servizi E Lavori Per Arredamento E Industria Del Legno. Forniture Per Congressi, Fiere E Manifestazioni. Servizi Per Aziende, Manifestazioni E Supporto Agli Scambi Commerciali",
    "sg:phone":"+39 06 580 0815",
    "sg:postcode":"00152",
    "sg:province":"Roma",
    "sg:website":"http://www.palloncini.it",
    "wof:name":"Balloon Fantasy Srl",
    "wof:placetype":"venue"
},
  "geometry": {"coordinates":[12.4565172195,41.8806419373],"type":"Point"}
}