{
  "type": "Feature",
  "properties": {
    "iso:country":"IT",
    "sg:address":"5, Via Val Di Sandra' 37060 Sona",
    "sg:city":"Sona",
    "sg:classifiers":[
        {
            "category":"Home & Garden",
            "subcategory":"Home Furnishings",
            "type":"Retail Goods"
        }
    ],
    "sg:phone":"+39 045 608 0777",
    "sg:postcode":"37060",
    "sg:province":"Verona",
    "sg:tags":[
        "household"
    ],
    "wof:name":"Euroduto (s.p.a.)",
    "wof:placetype":"venue"
},
  "geometry": {"coordinates":[10.822407,45.438084],"type":"Point"}
}