{
  "type": "Feature",
  "properties": {
    "iso:country":"IT",
    "sg:address":"73017 Sannicola",
    "sg:city":"Sannicola",
    "sg:classifiers":[
        {
            "category":"Building & Trades",
            "subcategory":"Construction",
            "type":"Services"
        }
    ],
    "sg:phone":"+39 0833 231980",
    "sg:postcode":"73017",
    "sg:province":"Lecce",
    "sg:tags":[
        "product",
        "industry",
        "processing",
        "glass",
        "wood",
        "furnishing",
        "works"
    ],
    "wof:name":"Vetreria Ciricugno",
    "wof:placetype":"venue"
},
  "geometry": {"coordinates":[18.0361557007,40.1032981873],"type":"Point"}
}