{
  "type": "Feature",
  "properties": {
    "iso:country":"IT",
    "sg:address":"90039 Villabate",
    "sg:city":"Villabate",
    "sg:orig_category":"Torrefazione Di Caffe' Ed Affini - Lavorazione E Ingrosso",
    "sg:phone":"+39 091 614 0790",
    "sg:postcode":"90039",
    "sg:province":"Palermo",
    "wof:name":"Casa Del Caffe' Dei Fratelli Di Peri Snc",
    "wof:placetype":"venue"
},
  "geometry": {"coordinates":[13.446141,38.077965],"type":"Point"}
}