{
  "type": "Feature",
  "properties": {
    "iso:country":"IT",
    "sg:address":"18, Via Stucchi 22075 Lurate Caccivio",
    "sg:city":"Lurate Caccivio",
    "sg:classifiers":[
        {
            "category":"Real Estate",
            "subcategory":"Architect",
            "type":"Services"
        }
    ],
    "sg:phone":"+39 39031390925",
    "sg:postcode":"22075",
    "sg:province":"Como",
    "sg:tags":[
        "textile",
        "clothing"
    ],
    "wof:name":"Tintoria Fevit (s.n.c.)",
    "wof:placetype":"venue"
},
  "geometry": {"coordinates":[9.00661,45.768272],"type":"Point"}
}