{
  "type": "Feature",
  "properties": {
    "iso:country":"IT",
    "sg:address":"22044 Inverigo",
    "sg:city":"Inverigo",
    "sg:orig_category":"Prodotti E Manufatti In Materie Plastiche",
    "sg:phone":"+39 031 696544",
    "sg:postcode":"22044",
    "sg:province":"Como",
    "wof:name":"Plast Co S.n.c.",
    "wof:placetype":"venue"
},
  "geometry": {"coordinates":[9.2307395935,45.7355957031],"type":"Point"}
}