{
  "type": "Feature",
  "properties": {
    "iso:country":"IT",
    "sg:address":"Via Vittorio Veneto 40/d; Torre Del Greco; 80059",
    "sg:city":"Torre del Greco",
    "sg:classifiers":[
        {
            "category":"Banks & Credit Unions",
            "subcategory":"Bank",
            "type":"Services"
        }
    ],
    "sg:phone":"+39 081 881 1161",
    "sg:postcode":"80059",
    "sg:province":"Napoli",
    "wof:name":"Credito Italiano Spa",
    "wof:placetype":"venue"
},
  "geometry": {"coordinates":[14.36891,40.790855],"type":"Point"}
}