{
  "type": "Feature",
  "properties": {
    "iso:country":"IT",
    "sg:address":"46040 Guidizzolo",
    "sg:city":"Guidizzolo",
    "sg:orig_category":"Apparecchiature E Sistemi Per Magazzinaggio E Movimentazione",
    "sg:phone":"+39 0376 818296",
    "sg:postcode":"46040",
    "sg:province":"Mantova",
    "wof:name":"Cariola Loris",
    "wof:placetype":"venue"
},
  "geometry": {"coordinates":[10.581574,45.321739],"type":"Point"}
}