{
  "type": "Feature",
  "properties": {
    "addr:full":"93012 Gela Gela Caltanissetta 93012",
    "addr:postcode":"93012;93012",
    "iso:country":"IT",
    "sg:address":"93012 Gela",
    "sg:city":"Gela",
    "sg:orig_category":"Pompe. Macchine, Strumenti Ed Apparecchi Per Attivita' Industriali",
    "sg:phone":"+39 0933 912351",
    "sg:postcode":"93012",
    "sg:province":"Caltanissetta",
    "wof:name":"Ce.co.m. Srl",
    "wof:placetype":"venue"
},
  "geometry": {"coordinates":[14.0637350082,37.4883346558],"type":"Point"}
}