{
  "type": "Feature",
  "properties": {
    "iso:country":"IT",
    "sg:address":"90123 Palermo",
    "sg:city":"Palermo",
    "sg:orig_category":"Pubblica Amministrazione",
    "sg:phone":"+39 091 476011",
    "sg:postcode":"90123",
    "sg:province":"Palermo",
    "wof:name":"Comandante Compagnia Mobile Guardia Di Finanza Di Palermo",
    "wof:placetype":"venue"
},
  "geometry": {"coordinates":[13.4431409836,38.0927619934],"type":"Point"}
}