{
  "type": "Feature",
  "properties": {
    "iso:country":"IT",
    "sg:address":"00156 Roma",
    "sg:city":"Roma",
    "sg:orig_category":"Automazione E Macchine Per Ufficio. Servizi Ausiliari Di Certificati, Riproduzioni, Disegni E Foto",
    "sg:phone":"+39 06 415211",
    "sg:postcode":"00156",
    "sg:province":"Roma",
    "sg:website":"http://www.rinaldi-servizi.it",
    "wof:name":"Rinaldo Rinaldi Spa",
    "wof:placetype":"venue"
},
  "geometry": {"coordinates":[12.59771,41.934849],"type":"Point"}
}