{
  "type": "Feature",
  "properties": {
    "addr:full":"80040 Poggiomarino Poggiomarino Napoli 80040",
    "addr:postcode":"80040;80040",
    "iso:country":"IT",
    "sg:address":"80040 Poggiomarino",
    "sg:city":"Poggiomarino",
    "sg:orig_category":"Macchine, Impianti Ed Attrezzature Per Industria Alimentare E Bevande",
    "sg:phone":"+39 081 865 1020",
    "sg:postcode":"80040",
    "sg:province":"Napoli",
    "wof:name":"Bonagura Antonio",
    "wof:placetype":"venue"
},
  "geometry": {"coordinates":[14.540018,40.804241],"type":"Point"}
}