{
  "type": "Feature",
  "properties": {
    "addr:full":"31058 Susegana Susegana Treviso 31058",
    "addr:postcode":"31058;31058",
    "iso:country":"IT",
    "sg:address":"31058 Susegana",
    "sg:city":"Susegana",
    "sg:classifiers":[
        {
            "category":"Manufacturing",
            "subcategory":"Motor Vehicles & Parts",
            "type":"Manufacturing & Wholesale Goods"
        }
    ],
    "sg:phone":"+39 0438 659311",
    "sg:postcode":"31058",
    "sg:province":"Treviso",
    "sg:tags":[
        "drive"
    ],
    "sg:website":"http://www.nuovatrasmissione.com",
    "wof:name":"Nuova Trasmissione Srl",
    "wof:placetype":"venue"
},
  "geometry": {"coordinates":[12.2772531509,45.872833252],"type":"Point"}
}