{
  "type": "Feature",
  "properties": {
    "iso:country":"IT",
    "sg:address":"20155 Milano",
    "sg:city":"Milano",
    "sg:orig_category":"Scuole Private - Elementari",
    "sg:phone":"+39 02 3300 0723",
    "sg:postcode":"20155",
    "sg:province":"Milano",
    "wof:name":"Scuola Elementare Materna A Metodo Montessori",
    "wof:placetype":"venue"
},
  "geometry": {"coordinates":[9.152266,45.492085],"type":"Point"}
}