{
  "type": "Feature",
  "properties": {
    "iso:country":"IT",
    "sg:address":"Corte Campana 10; Lucca; 55100",
    "sg:city":"Lucca",
    "sg:classifiers":[
        {
            "category":"Shopping",
            "subcategory":"Computers & Home Electronics",
            "type":"Retail Goods"
        }
    ],
    "sg:phone":"+39 0583 976635",
    "sg:postcode":"55100",
    "sg:province":"Lucca",
    "sg:tags":[
        "chamber",
        "commerce"
    ],
    "sg:website":"www.lunet.it/enti/cciaa/welcome.html",
    "wof:name":"Lucca Chamber Of Commerce And Industry",
    "wof:placetype":"venue"
},
  "geometry": {"coordinates":[10.50188,43.842495],"type":"Point"}
}