{
  "type": "Feature",
  "properties": {
    "addr:full":"51017 Pescia Pescia Pistoia 51017",
    "addr:postcode":"51017;51017",
    "iso:country":"IT",
    "sg:address":"51017 Pescia",
    "sg:city":"Pescia",
    "sg:orig_category":"Abbigliamento Gestanti E Neonati",
    "sg:phone":"+39 0572 476306",
    "sg:postcode":"51017",
    "sg:province":"Pistoia",
    "wof:name":"Tuttobimbo Di Maffei Lisetta",
    "wof:placetype":"venue"
},
  "geometry": {"coordinates":[10.687972,43.898914],"type":"Point"}
}