{
  "type": "Feature",
  "properties": {
    "iso:country":"IT",
    "sg:address":"Via S. Caterina; Florence",
    "sg:classifiers":[
        {
            "category":"Banks & Credit Unions",
            "subcategory":"Bank",
            "type":"Services"
        }
    ],
    "sg:phone":"+39 055 480763",
    "wof:name":"Cassa Di Risparmio Di Pistoia, E Pescia Spa",
    "wof:placetype":"venue"
},
  "geometry": {"coordinates":[11.256069,43.781605],"type":"Point"}
}