{
  "type": "Feature",
  "properties": {
    "addr:full":"1, V. Levrini 25080 Soiano Del Lago Soiano Brescia 25080",
    "addr:housenumber":"1",
    "addr:postcode":"25080;25080",
    "addr:street":"Levrini",
    "iso:country":"IT",
    "sg:address":"1, V. Levrini 25080 Soiano Del Lago",
    "sg:city":"Soiano",
    "sg:classifiers":[
        {
            "category":"Manufacturing",
            "subcategory":"Rubber & Plastics",
            "type":"Manufacturing & Wholesale Goods"
        }
    ],
    "sg:phone":"+39 036 550 2210",
    "sg:postcode":"25080",
    "sg:province":"Brescia",
    "sg:tags":[
        "packaging",
        "material",
        "-"
    ],
    "sg:website":"http://www.paginegialle.it/plastiline",
    "wof:name":"Nuova Plastiline",
    "wof:placetype":"venue"
},
  "geometry": {"coordinates":[10.4950017929,45.508808136],"type":"Point"}
}