{
  "type": "Feature",
  "properties": {
    "iso:country":"IT",
    "sg:address":"80142 Napoli",
    "sg:city":"Napoli",
    "sg:orig_category":"Gioielleria, Oreficeria E Argenteria",
    "sg:phone":"+39 081 552 6775",
    "sg:postcode":"80142",
    "sg:province":"Napoli",
    "wof:name":"Comegna",
    "wof:placetype":"venue"
},
  "geometry": {"coordinates":[14.258937,40.845287],"type":"Point"}
}