{
  "type": "Feature",
  "properties": {
    "iso:country":"IT",
    "sg:address":"28014 Maggiora",
    "sg:city":"Maggiora",
    "sg:orig_category":"Serramenti Ed Infissi",
    "sg:phone":"+39 0322 87163",
    "sg:postcode":"28014",
    "sg:province":"Novara",
    "wof:name":"Magistrini A. & C. Snc",
    "wof:placetype":"venue"
},
  "geometry": {"coordinates":[8.430306,45.684128],"type":"Point"}
}