{
  "type": "Feature",
  "properties": {
    "iso:country":"IT",
    "sg:address":"Via Palmanova 25 33058 San Giorgio Di Nogaro",
    "sg:city":"San Giorgio di Nogaro",
    "sg:classifiers":[
        {
            "category":"Retail",
            "subcategory":"Repair Shop",
            "type":"Services"
        }
    ],
    "sg:phone":"+39 0431 65353",
    "sg:postcode":"33058",
    "sg:province":"Udine",
    "sg:tags":[
        "workshop",
        "mechanical"
    ],
    "wof:name":"Mavra Srl",
    "wof:placetype":"venue"
},
  "geometry": {"coordinates":[13.20985,45.84095],"type":"Point"}
}