{
  "type": "Feature",
  "properties": {
    "addr:full":"89013 Gioia Tauro Gioia Tauro Reggio Di Calabria 89013",
    "addr:postcode":"89013;89013",
    "iso:country":"IT",
    "sg:address":"89013 Gioia Tauro",
    "sg:city":"Gioia Tauro",
    "sg:orig_category":"Pubblicita', Marketing E Comunicazione",
    "sg:phone":"+39 0966 57986",
    "sg:postcode":"89013",
    "sg:province":"Reggio Di Calabria",
    "sg:website":"http://www.leonardods.it",
    "wof:name":"Leonardo Digital Studio",
    "wof:placetype":"venue"
},
  "geometry": {"coordinates":[15.6501369476,38.1146888733],"type":"Point"}
}