{
  "type": "Feature",
  "properties": {
    "iso:country":"IT",
    "sg:address":"25121 Brescia",
    "sg:city":"Brescia",
    "sg:orig_category":"Servizi Vari Di Interesse Pubblico",
    "sg:phone":"+39 030 294 2185",
    "sg:postcode":"25121",
    "sg:province":"Brescia",
    "wof:name":"Agenzia Matrimoniale Meeting",
    "wof:placetype":"venue"
},
  "geometry": {"coordinates":[10.218922,45.533356],"type":"Point"}
}