{
  "type": "Feature",
  "properties": {
    "iso:country":"IT",
    "sg:address":"55100 Lucca",
    "sg:city":"Lucca",
    "sg:orig_category":"Non-classified Establishments",
    "sg:phone":"+39 0583 343536",
    "sg:postcode":"55100",
    "sg:province":"Lucca",
    "wof:name":"Papeschi Ivano Snc",
    "wof:placetype":"venue"
},
  "geometry": {"coordinates":[10.376962,43.857937],"type":"Point"}
}