{
  "type": "Feature",
  "properties": {
    "iso:country":"IT",
    "sg:address":"26841 Casalpusterlengo",
    "sg:city":"Casalpusterlengo",
    "sg:orig_category":"Argenteria, Oreficeria E Gioielleria - Macchine E Forniture",
    "sg:phone":"+39 0377 912197",
    "sg:postcode":"26841",
    "sg:province":"Lodi",
    "wof:name":"Graficarbo Srl",
    "wof:placetype":"venue"
},
  "geometry": {"coordinates":[9.640527,45.1908],"type":"Point"}
}