{
  "type": "Feature",
  "properties": {
    "iso:country":"IT",
    "sg:address":"15, Via Ferraris Galileo 30038 Spinea",
    "sg:city":"Spinea",
    "sg:classifiers":[
        {
            "category":"Shopping",
            "subcategory":"Computers & Home Electronics",
            "type":"Retail Goods"
        }
    ],
    "sg:phone":"+39 39041990986",
    "sg:postcode":"30038",
    "sg:province":"Venezia",
    "sg:tags":[
        "electronic",
        "electrical",
        "equipment"
    ],
    "wof:name":"Gallo & Da Lio Srl",
    "wof:placetype":"venue"
},
  "geometry": {"coordinates":[12.146115,45.507339],"type":"Point"}
}