{
  "type": "Feature",
  "properties": {
    "iso:country":"IT",
    "sg:address":"Via Selvuzzis 4; Pavia Di Udine; 33050",
    "sg:city":"Pavia di Udine",
    "sg:classifiers":[
        {
            "category":"Banks & Credit Unions",
            "subcategory":"Bank",
            "type":"Services"
        }
    ],
    "sg:phone":"+39 0432 675256",
    "sg:postcode":"33050",
    "sg:province":"Udine",
    "wof:name":"Rolo Banca 1473 Spa",
    "wof:placetype":"venue"
},
  "geometry": {"coordinates":[13.302635,45.989269],"type":"Point"}
}