{
  "type": "Feature",
  "properties": {
    "addr:full":"Via Molino Filo 1 20050 Verano Brianza Verano Brianza Milano 20050",
    "addr:housenumber":"1",
    "addr:postcode":"20050;20050",
    "addr:street":"Via Molino Filo",
    "iso:country":"IT",
    "sg:address":"Via Molino Filo 1 20050 Verano Brianza",
    "sg:city":"Verano Brianza",
    "sg:classifiers":[
        {
            "category":"Manufacturing",
            "subcategory":"Tools & Machinery",
            "type":"Manufacturing & Wholesale Goods"
        }
    ],
    "sg:phone":"+39 036 290 4945",
    "sg:postcode":"20050",
    "sg:province":"Milano",
    "sg:tags":[
        "abrasive"
    ],
    "sg:website":"www.eurokoll.it",
    "wof:name":"Fiocchi Italo & C. S.n.c.",
    "wof:placetype":"venue"
},
  "geometry": {"coordinates":[9.188141,45.463688],"type":"Point"}
}