{
  "type": "Feature",
  "properties": {
    "iso:country":"IT",
    "sg:address":"37138 Verona",
    "sg:city":"Verona",
    "sg:orig_category":"Impiantistica E Prodotti Tecnologici Per Edilizia",
    "sg:phone":"+39 045 572588",
    "sg:postcode":"37138",
    "sg:province":"Verona",
    "wof:name":"Pizzeghella - Stevan",
    "wof:placetype":"venue"
},
  "geometry": {"coordinates":[10.87653,45.350636],"type":"Point"}
}