{
  "type": "Feature",
  "properties": {
    "addr:full":"65, V. I Maggio 29100 Piacenza Piacenza Piacenza 29100",
    "addr:housenumber":"65",
    "addr:postcode":"29100;29100",
    "addr:street":"V. I Maggio",
    "iso:country":"IT",
    "sg:address":"65, V. I Maggio 29100 Piacenza",
    "sg:city":"Piacenza",
    "sg:classifiers":[
        {
            "category":"Shopping",
            "subcategory":"Stationery & Office Supplies",
            "type":"Retail Goods"
        }
    ],
    "sg:phone":"+39 0523 449376",
    "sg:postcode":"29100",
    "sg:province":"Piacenza",
    "sg:tags":[
        "professional"
    ],
    "sg:website":"http://www.centrufficiopc.it",
    "wof:name":"Centrufficio Srl",
    "wof:placetype":"venue"
},
  "geometry": {"coordinates":[9.6624412537,45.0504150391],"type":"Point"}
}