{
  "type": "Feature",
  "properties": {
    "iso:country":"IT",
    "sg:address":"36015 Schio",
    "sg:city":"Schio",
    "sg:orig_category":"Utensili Meccanici E Materiali",
    "sg:phone":"+39 0445 520974",
    "sg:postcode":"36015",
    "sg:province":"Vicenza",
    "wof:name":"Officina Modellisti Pietro Ballico Di Ballico Paolo & C. Sas",
    "wof:placetype":"venue"
},
  "geometry": {"coordinates":[11.346049,45.711227],"type":"Point"}
}