{
  "type": "Feature",
  "properties": {
    "addr:full":"10060 None None Torino 10060",
    "addr:postcode":"10060;10060",
    "iso:country":"IT",
    "sg:address":"10060 None",
    "sg:city":"None",
    "sg:orig_category":"Macchine Utensili E Impianti",
    "sg:phone":"+39 011 986 5771",
    "sg:postcode":"10060",
    "sg:province":"Torino",
    "wof:name":"Corefon International (s.r.l.)",
    "wof:placetype":"venue"
},
  "geometry": {"coordinates":[7.753247,45.092537],"type":"Point"}
}