{
  "type": "Feature",
  "properties": {
    "iso:country":"IT",
    "sg:address":"38051 Borgo Valsugana",
    "sg:city":"Borgo",
    "sg:orig_category":"Pianoforti",
    "sg:phone":"+39 0461 753114",
    "sg:postcode":"38051",
    "sg:province":"Trento",
    "wof:name":"Galvan Romano",
    "wof:placetype":"venue"
},
  "geometry": {"coordinates":[11.4605121613,46.0552787781],"type":"Point"}
}