{
  "type": "Feature",
  "properties": {
    "iso:country":"IT",
    "sg:address":"50018 Scandicci",
    "sg:city":"Scandicci",
    "sg:orig_category":"Serramenti Ed Infissi. Arte Ed Artigianato Artistico. Shopping",
    "sg:phone":"+39 055 731 0687",
    "sg:postcode":"50018",
    "sg:province":"Firenze",
    "sg:website":"http://www.fol.it/artefice",
    "wof:name":"Euro Lamp Art Srl",
    "wof:placetype":"venue"
},
  "geometry": {"coordinates":[11.180319,43.764427],"type":"Point"}
}