{
  "type": "Feature",
  "properties": {
    "iso:country":"IT",
    "sg:address":"10, Via Rodi 24040 Filago",
    "sg:city":"Filago",
    "sg:classifiers":[
        {
            "category":"Professional",
            "subcategory":"Engineering",
            "type":"Services"
        }
    ],
    "sg:phone":"+39 035 493 8971",
    "sg:postcode":"24040",
    "sg:province":"Bergamo",
    "sg:tags":[
        "machine",
        "-",
        "mechanical"
    ],
    "wof:name":"Prosimet S.p.a.",
    "wof:placetype":"venue"
},
  "geometry": {"coordinates":[9.53938,45.639492],"type":"Point"}
}