{
  "type": "Feature",
  "properties": {
    "iso:country":"IT",
    "sg:address":"20149 Milano",
    "sg:city":"Milano",
    "sg:orig_category":"Servizi Ausiliari Dei Mezzi Di Trasporto",
    "sg:phone":"+39 02 407 9633",
    "sg:postcode":"20149",
    "sg:province":"Milano",
    "wof:name":"Marcato Davide",
    "wof:placetype":"venue"
},
  "geometry": {"coordinates":[9.144849,45.470009],"type":"Point"}
}