{
  "type": "Feature",
  "properties": {
    "addr:full":"33084 Cordenons Cordenons Pordenone 33084",
    "addr:postcode":"33084;33084",
    "iso:country":"IT",
    "sg:address":"33084 Cordenons",
    "sg:city":"Cordenons",
    "sg:classifiers":[
        {
            "category":"Travel",
            "subcategory":"Travel Agent",
            "type":"Entertainment"
        }
    ],
    "sg:phone":"+39 0434 580456",
    "sg:postcode":"33084",
    "sg:province":"Pordenone",
    "sg:tags":[
        "operator",
        "tour",
        "tourist"
    ],
    "wof:name":"Noncello Viaggi Srl",
    "wof:placetype":"venue"
},
  "geometry": {"coordinates":[12.707435,45.989044],"type":"Point"}
}