{
  "type": "Feature",
  "properties": {
    "iso:country":"IT",
    "sg:address":"51 Via Piemonte, 00187 Roma",
    "sg:city":"Roma",
    "sg:classifiers":[
        {
            "category":"Banks & Credit Unions",
            "subcategory":"Financial Services",
            "type":"Services"
        }
    ],
    "sg:phone":"+39 390 647 911",
    "sg:postcode":"00187",
    "sg:province":"Roma",
    "sg:tags":[
        "banking",
        "finance",
        "insurance"
    ],
    "wof:name":"Mediocredito Centrale",
    "wof:placetype":"venue"
},
  "geometry": {"coordinates":[12.3729848862,42.1297073364],"type":"Point"}
}