{
  "type": "Feature",
  "properties": {
    "iso:country":"IT",
    "sg:address":"60/c, V. Matteotti 43015 Noceto",
    "sg:city":"Noceto",
    "sg:classifiers":[
        {
            "category":"Sports & Exercise",
            "subcategory":"Playing Field",
            "type":"Entertainment"
        }
    ],
    "sg:phone":"+39 0521 620120",
    "sg:postcode":"43015",
    "sg:province":"Parma",
    "sg:tags":[
        "game"
    ],
    "sg:website":"http://www.footballworldsports.com",
    "wof:name":"Football World",
    "wof:placetype":"venue"
},
  "geometry": {"coordinates":[10.181523,44.814587],"type":"Point"}
}