{
  "type": "Feature",
  "properties": {
    "addr:full":"457, V. Lecco 24030 Pontida Pontida Bergamo 24030",
    "addr:housenumber":"457",
    "addr:postcode":"24030;24030",
    "addr:street":"V. Lecco",
    "iso:country":"IT",
    "sg:address":"457, V. Lecco 24030 Pontida",
    "sg:city":"Pontida",
    "sg:classifiers":[
        {
            "category":"Shopping",
            "subcategory":"Crafts & Fabrics",
            "type":"Retail Goods"
        }
    ],
    "sg:phone":"+39 035 438 5404",
    "sg:postcode":"24030",
    "sg:province":"Bergamo",
    "sg:tags":[
        "ceramic"
    ],
    "sg:website":"http://www.bluestein.it",
    "wof:name":"Bluestein Steel & Stone Srl",
    "wof:placetype":"venue"
},
  "geometry": {"coordinates":[9.506063,45.731621],"type":"Point"}
}