{
  "type": "Feature",
  "properties": {
    "iso:country":"IT",
    "sg:address":"07047 Thiesi",
    "sg:city":"Thiesi",
    "sg:orig_category":"Prodotti Di Base E Forniture Per Industria Alimentare E Bevande",
    "sg:phone":"+39 079 886554",
    "sg:postcode":"07047",
    "sg:province":"Sassari",
    "wof:name":"Fadda Salvatore & C. S.n.c.",
    "wof:placetype":"venue"
},
  "geometry": {"coordinates":[8.649058342,40.5235786438],"type":"Point"}
}