{
  "type": "Feature",
  "properties": {
    "addr:full":"32, Via Marconi Guglielmo 24068 Seriate Seriate Bergamo 24068",
    "addr:postcode":"24068;24068",
    "addr:street":"Via Marconi Guglielmo",
    "iso:country":"IT",
    "sg:address":"32, Via Marconi Guglielmo 24068 Seriate",
    "sg:city":"Seriate",
    "sg:classifiers":[
        {
            "category":"Shopping",
            "type":"Retail Goods"
        }
    ],
    "sg:phone":"+39 39035291234",
    "sg:postcode":"24068",
    "sg:province":"Bergamo",
    "sg:tags":[
        "finished",
        "-",
        "metallic"
    ],
    "wof:name":"Mazzoleni Spa",
    "wof:placetype":"venue"
},
  "geometry": {"coordinates":[9.729886055,45.6791801453],"type":"Point"}
}