{
  "type": "Feature",
  "properties": {
    "iso:country":"IT",
    "sg:address":"06123 Perugia",
    "sg:city":"Perugia",
    "sg:orig_category":"Servizi Editoriali. Shopping",
    "sg:phone":"+39 075 571 6091",
    "sg:postcode":"06123",
    "sg:province":"Perugia",
    "wof:name":"L'antro Libreria",
    "wof:placetype":"venue"
},
  "geometry": {"coordinates":[12.385052,43.116081],"type":"Point"}
}