{
  "type": "Feature",
  "properties": {
    "addr:full":"200, Via Dell' Artigianato 45030 San Martino Di Venezze San Martino di Venezze Rovigo 45030",
    "addr:housenumber":"200",
    "addr:postcode":"45030;45030",
    "addr:street":"Via Dell ' Artigianato",
    "iso:country":"IT",
    "sg:address":"200, Via Dell' Artigianato 45030 San Martino Di Venezze",
    "sg:city":"San Martino di Venezze",
    "sg:classifiers":[
        {
            "category":"Shopping",
            "subcategory":"Clothing, Apparel, & Fashions",
            "type":"Retail Goods"
        }
    ],
    "sg:phone":"+39 39042599488",
    "sg:postcode":"45030",
    "sg:province":"Rovigo",
    "sg:tags":[
        "clothes"
    ],
    "wof:name":"Gifas S.r.l.",
    "wof:placetype":"venue"
},
  "geometry": {"coordinates":[11.891382,45.130035],"type":"Point"}
}