{
  "type": "Feature",
  "properties": {
    "iso:country":"IT",
    "sg:address":"22073 Fino Mornasco",
    "sg:city":"Fino Mornasco",
    "sg:orig_category":"Acciaierie E Fonderie. Arte Ed Artigianato Artistico",
    "sg:phone":"+39 031 927251",
    "sg:postcode":"22073",
    "sg:province":"Como",
    "wof:name":"Fonderia Corti Fabrizio",
    "wof:placetype":"venue"
},
  "geometry": {"coordinates":[9.050485,45.753368],"type":"Point"}
}