{
  "type": "Feature",
  "properties": {
    "iso:country":"IT",
    "sg:address":"00169 Roma",
    "sg:city":"Roma",
    "sg:orig_category":"Frigotecnica, Apparecchiature E Servizi. Forniture Alle Strutture Ricettive",
    "sg:phone":"+39 06 238 9545",
    "sg:postcode":"00169",
    "sg:province":"Roma",
    "wof:name":"Emitec Forni Srl",
    "wof:placetype":"venue"
},
  "geometry": {"coordinates":[12.5643234253,41.8454856873],"type":"Point"}
}