{
  "type": "Feature",
  "properties": {
    "addr:full":"20125 Milano Milano Milano 20125",
    "addr:postcode":"20125;20125",
    "iso:country":"IT",
    "sg:address":"20125 Milano",
    "sg:city":"Milano",
    "sg:orig_category":"Valvole E Apparecchiature Di Misura. Minuterie Metalliche E Ferramenta. Forniture Per Attivita' Industriali",
    "sg:phone":"+39 02 6707 3104",
    "sg:postcode":"20125",
    "sg:province":"Milano",
    "wof:name":"Vignati Fitting Srl",
    "wof:placetype":"venue"
},
  "geometry": {"coordinates":[9.20127,45.495548],"type":"Point"}
}