{
  "type": "Feature",
  "properties": {
    "addr:full":"25018 Montichiari Montichiari Brescia 25018",
    "addr:postcode":"25018;25018",
    "iso:country":"IT",
    "sg:address":"25018 Montichiari",
    "sg:city":"Montichiari",
    "sg:orig_category":"Forniture Per Attivita' Industriali",
    "sg:postcode":"25018",
    "sg:province":"Brescia",
    "wof:name":"Tortelli Francesco",
    "wof:placetype":"venue"
},
  "geometry": {"coordinates":[10.3950681686,45.3992805481],"type":"Point"}
}