{
  "type": "Feature",
  "properties": {
    "iso:country":"IT",
    "sg:address":"70122 Bari",
    "sg:city":"Bari",
    "sg:orig_category":"Macchine, Impianti Ed Attrezzature Per Abbigliamento E Pelletterie",
    "sg:phone":"+39 080 521 6853",
    "sg:postcode":"70122",
    "sg:province":"Bari",
    "wof:name":"Truzzi Dante",
    "wof:placetype":"venue"
},
  "geometry": {"coordinates":[16.869591,41.063461],"type":"Point"}
}