{
  "type": "Feature",
  "properties": {
    "addr:full":"50050 Cerreto Guidi Cerreto Guidi Firenze 50050",
    "addr:postcode":"50050;50050",
    "iso:country":"IT",
    "sg:address":"50050 Cerreto Guidi",
    "sg:city":"Cerreto Guidi",
    "sg:classifiers":[
        {
            "category":"Manufacturing",
            "subcategory":"Leather Goods",
            "type":"Manufacturing & Wholesale Goods"
        }
    ],
    "sg:phone":"+39 0571 581847",
    "sg:postcode":"50050",
    "sg:province":"Firenze",
    "sg:tags":[
        "goods",
        "clothing",
        "supply"
    ],
    "wof:name":"Nuovo Bottonificio Esselle Srl",
    "wof:placetype":"venue"
},
  "geometry": {"coordinates":[10.880807,43.722637],"type":"Point"}
}