{
  "type": "Feature",
  "properties": {
    "addr:full":"40069 Zola Predosa Zola Bologna 40069",
    "addr:postcode":"40069;40069",
    "iso:country":"IT",
    "sg:address":"40069 Zola Predosa",
    "sg:city":"Zola",
    "sg:orig_category":"Forniture Per Attivita' Commerciali Ed Artigianali. Pubblicita', Marketing E Comunicazione",
    "sg:phone":"+39 051 758374",
    "sg:postcode":"40069",
    "sg:province":"Bologna",
    "sg:website":"http://www.acrineon.com",
    "wof:name":"Acrineon Snc Di Scalorbi Giuseppe E Claudio",
    "wof:placetype":"venue"
},
  "geometry": {"coordinates":[11.2343893051,44.5067062378],"type":"Point"}
}