{
  "type": "Feature",
  "properties": {
    "iso:country":"IT",
    "sg:address":"37, Via Bassanese 31044 Montebelluna",
    "sg:city":"Montebelluna",
    "sg:classifiers":[
        {
            "category":"Personal",
            "subcategory":"Shoe Repair & Shine",
            "type":"Services"
        }
    ],
    "sg:phone":"+39 39042322251",
    "sg:postcode":"31044",
    "sg:province":"Treviso",
    "sg:tags":[
        "leather"
    ],
    "wof:name":"Gazziero Strings & Laces S.a.s.",
    "wof:placetype":"venue"
},
  "geometry": {"coordinates":[12.022601,45.77766],"type":"Point"}
}