{
  "type": "Feature",
  "properties": {
    "iso:country":"IT",
    "sg:address":"24040 Stezzano",
    "sg:city":"Stezzano",
    "sg:orig_category":"Tessuti E Stoffe. Filati E Materie Prime Tessili",
    "sg:phone":"+39 035 454 5111",
    "sg:postcode":"24040",
    "sg:province":"Bergamo",
    "wof:name":"Cotonificio Honegger (s.p.a.)",
    "wof:placetype":"venue"
},
  "geometry": {"coordinates":[9.649612,45.649727],"type":"Point"}
}