{
  "type": "Feature",
  "properties": {
    "iso:country":"IT",
    "sg:address":"17015 Celle Ligure",
    "sg:city":"Celle Ligure",
    "sg:orig_category":"Dolciumi E Gelati",
    "sg:phone":"+39 019 993056",
    "sg:postcode":"17015",
    "sg:province":"Savona",
    "wof:name":"Algot Sas",
    "wof:placetype":"venue"
},
  "geometry": {"coordinates":[8.533652,44.348866],"type":"Point"}
}