{
  "type": "Feature",
  "properties": {
    "addr:full":"39, Regione Marcaveri 15020 Murisengo Murisengo Alessandria 15020",
    "addr:housenumber":"39",
    "addr:postcode":"15020;15020",
    "addr:street":"Regione Marcaveri",
    "iso:country":"IT",
    "sg:address":"39, Regione Marcaveri 15020 Murisengo",
    "sg:city":"Murisengo",
    "sg:classifiers":[
        {
            "category":"Professional",
            "subcategory":"Engineering",
            "type":"Services"
        }
    ],
    "sg:phone":"+39 0141 993693",
    "sg:postcode":"15020",
    "sg:province":"Alessandria",
    "sg:tags":[
        "machine",
        "-",
        "mechanical"
    ],
    "wof:name":"S.c.m. Srl",
    "wof:placetype":"venue"
},
  "geometry": {"coordinates":[8.131637,45.081112],"type":"Point"}
}