{
  "type": "Feature",
  "properties": {
    "iso:country":"IT",
    "sg:address":"20136 Milano",
    "sg:city":"Milano",
    "sg:orig_category":"Etichette",
    "sg:phone":"+39 02 8940 3314",
    "sg:postcode":"20136",
    "sg:province":"Milano",
    "wof:name":"Etichettificio Ambrosiano Sas",
    "wof:placetype":"venue"
},
  "geometry": {"coordinates":[9.17821,45.446327],"type":"Point"}
}