{
  "type": "Feature",
  "properties": {
    "iso:country":"IT",
    "sg:address":"26010 Cremosano",
    "sg:city":"Cremosano",
    "sg:orig_category":"Arredamento Parrucchieri Ed Istituti Di Bellezza",
    "sg:phone":"+39 0373 273666",
    "sg:postcode":"26010",
    "sg:province":"Cremona",
    "wof:name":"Vanazzi Service",
    "wof:placetype":"venue"
},
  "geometry": {"coordinates":[9.683226,45.361839],"type":"Point"}
}