{
  "type": "Feature",
  "properties": {
    "iso:country":"IT",
    "sg:address":"20040 Cavenago Di Brianza",
    "sg:city":"Cavenago di Brianza",
    "sg:orig_category":"Cartotecnica E Servizi. Articoli Per Imballaggio E Confezionamento",
    "sg:phone":"+39 02 9533 5141",
    "sg:postcode":"20040",
    "sg:province":"Milano",
    "wof:name":"Tesacom Di Fiammenghi Marcella & C. Snc",
    "wof:placetype":"venue"
},
  "geometry": {"coordinates":[9.414835,45.579563],"type":"Point"}
}