{
  "type": "Feature",
  "properties": {
    "addr:full":"36015 Schio Schio Vicenza 36015",
    "addr:postcode":"36015;36015",
    "iso:country":"IT",
    "sg:address":"36015 Schio",
    "sg:city":"Schio",
    "sg:orig_category":"Macchine Utensili E Impianti",
    "sg:phone":"+39 0445 575791",
    "sg:postcode":"36015",
    "sg:province":"Vicenza",
    "wof:name":"Saco Srl",
    "wof:placetype":"venue"
},
  "geometry": {"coordinates":[11.547974,45.575069],"type":"Point"}
}