{
  "type": "Feature",
  "properties": {
    "iso:country":"IT",
    "sg:address":"Via Noalese 276 30036 Santa Maria Di Sala",
    "sg:city":"Santa Maria di Sala",
    "sg:classifiers":[
        {
            "category":"Manufacturing",
            "subcategory":"Glass & Minerals",
            "type":"Manufacturing & Wholesale Goods"
        }
    ],
    "sg:phone":"+39 041 573 0366",
    "sg:postcode":"30036",
    "sg:province":"Venezia",
    "sg:tags":[
        "crystal",
        "chandelier",
        "pendant"
    ],
    "sg:website":"www.soiva.com",
    "wof:name":"Vetreria Soiva Srl",
    "wof:placetype":"venue"
},
  "geometry": {"coordinates":[12.027896,45.505943],"type":"Point"}
}