{
  "type": "Feature",
  "properties": {
    "addr:full":"23, Via Roma 24020 Gorle Gorle Bergamo 24020",
    "addr:postcode":"24020;24020",
    "addr:street":"Via Roma",
    "iso:country":"IT",
    "sg:address":"23, Via Roma 24020 Gorle",
    "sg:city":"Gorle",
    "sg:classifiers":[
        {
            "category":"Shopping",
            "type":"Retail Goods"
        }
    ],
    "sg:phone":"+39 39035301612",
    "sg:postcode":"24020",
    "sg:province":"Bergamo",
    "sg:tags":[
        "finished",
        "-",
        "metallic"
    ],
    "wof:name":"Panseri S.r.l. Panseri Marco & C.",
    "wof:placetype":"venue"
},
  "geometry": {"coordinates":[9.7353115082,45.7087860107],"type":"Point"}
}