{
  "type": "Feature",
  "properties": {
    "addr:full":"23900 Lecco Lecco Lecco 23900",
    "addr:postcode":"23900;23900",
    "iso:country":"IT",
    "sg:address":"23900 Lecco",
    "sg:city":"Lecco",
    "sg:orig_category":"Ricerca, Selezione E Formazione Del Personale. Pubblica Amministrazione",
    "sg:phone":"+39 0341 287737",
    "sg:postcode":"23900",
    "sg:province":"Lecco",
    "wof:name":"Direzione Provinciale Del Lavoro",
    "wof:placetype":"venue"
},
  "geometry": {"coordinates":[9.395879,45.855572],"type":"Point"}
}