{
  "type": "Feature",
  "properties": {
    "addr:full":"47032 Bertinoro Bertinoro Forl\u00ec-Cesena 47032",
    "addr:postcode":"47032;47032",
    "iso:country":"IT",
    "sg:address":"47032 Bertinoro",
    "sg:city":"Bertinoro",
    "sg:orig_category":"Petroli, Gas E Combustibili",
    "sg:phone":"+39 800 112 277",
    "sg:postcode":"47032",
    "sg:province":"Forl\u00ec-Cesena",
    "wof:name":"Shell Gas Italia Spa",
    "wof:placetype":"venue"
},
  "geometry": {"coordinates":[12.1574659348,44.1731376648],"type":"Point"}
}