{
  "type": "Feature",
  "properties": {
    "iso:country":"IT",
    "sg:address":"1, Strada St. Casale-vercelli 15030 Villanova Monferrato",
    "sg:city":"Villanova Monferrato",
    "sg:classifiers":[
        {
            "category":"Professional",
            "subcategory":"Engineering",
            "type":"Services"
        }
    ],
    "sg:phone":"+39 0142 483878",
    "sg:postcode":"15030",
    "sg:province":"Alessandria",
    "sg:tags":[
        "machine",
        "-",
        "mechanical"
    ],
    "wof:name":"Cerutti Spirito Impianti Srl",
    "wof:placetype":"venue"
},
  "geometry": {"coordinates":[8.616951,44.913216],"type":"Point"}
}