{
  "type": "Feature",
  "properties": {
    "iso:country":"IT",
    "sg:address":"Via Manzoni 3 22060 Cucciago",
    "sg:city":"Cucciago",
    "sg:classifiers":[
        {
            "category":"Government",
            "subcategory":"Court House",
            "type":"Public Place"
        }
    ],
    "sg:phone":"+39 031 725059",
    "sg:postcode":"22060",
    "sg:province":"Como",
    "sg:tags":[
        "accommodation",
        "furniture"
    ],
    "wof:name":"Bomar Di Fratelli Bossi Snc",
    "wof:placetype":"venue"
},
  "geometry": {"coordinates":[9.090621,45.738342],"type":"Point"}
}