{
  "type": "Feature",
  "properties": {
    "iso:country":"IT",
    "sg:address":"00040 Pomezia",
    "sg:city":"Pomezia",
    "sg:orig_category":"Impiantistica E Prodotti Tecnologici Per Edilizia. Climatizzazione E Condizionamento, Apparecchiature E Servizi",
    "sg:phone":"+39 06 9160 1105",
    "sg:postcode":"00040",
    "sg:province":"Roma",
    "wof:name":"Steam",
    "wof:placetype":"venue"
},
  "geometry": {"coordinates":[12.490321,41.683311],"type":"Point"}
}