{
  "type": "Feature",
  "properties": {
    "iso:country":"IT",
    "sg:address":"96012 Avola",
    "sg:city":"Avola",
    "sg:orig_category":"Bagno - Accessori E Mobili",
    "sg:phone":"+39 0931 821022",
    "sg:postcode":"96012",
    "sg:province":"Siracusa",
    "wof:name":"Eredi Di Vaccarisi Michele",
    "wof:placetype":"venue"
},
  "geometry": {"coordinates":[15.175361,36.959656],"type":"Point"}
}