{
  "type": "Feature",
  "properties": {
    "iso:country":"IT",
    "sg:address":"2, Viale Monte Grappa 26027 Rivolta D'adda",
    "sg:classifiers":[
        {
            "category":"Food & Beverages",
            "subcategory":"Bakery",
            "type":"Retail Goods"
        }
    ],
    "sg:phone":"+39 036 337 7111",
    "sg:postcode":"26027",
    "sg:province":"Cremona",
    "sg:tags":[
        "grain",
        "cereal"
    ],
    "wof:name":"Molino Seragni (s.p.a.)",
    "wof:placetype":"venue"
},
  "geometry": {"coordinates":[9.513894,45.468361],"type":"Point"}
}