{
  "type": "Feature",
  "properties": {
    "iso:country":"IT",
    "sg:address":"73100 Lecce",
    "sg:city":"Lecce",
    "sg:orig_category":"Articoli Regalo - Vendita Al Dettaglio",
    "sg:phone":"+39 0832 306604",
    "sg:postcode":"73100",
    "sg:province":"Lecce",
    "wof:name":"Ratta Maria Arcona",
    "wof:placetype":"venue"
},
  "geometry": {"coordinates":[18.17276,40.354111],"type":"Point"}
}