{
  "type": "Feature",
  "properties": {
    "addr:full":"80122 Napoli Napoli Napoli 80122",
    "addr:housenumber":"80122",
    "addr:postcode":"80122",
    "iso:country":"IT",
    "sg:address":"80122 Napoli",
    "sg:city":"Napoli",
    "sg:orig_category":"Medici Specialisti - Chirurgia Plastica E Ricostruttiva",
    "sg:phone":"+39 081 575 7955",
    "sg:postcode":"80122",
    "sg:province":"Napoli",
    "wof:name":"Buonanno D.ssa Maria Sofia",
    "wof:placetype":"venue"
},
  "geometry": {"coordinates":[14.299352,40.903919],"type":"Point"}
}