{
  "type": "Feature",
  "properties": {
    "iso:country":"IT",
    "sg:address":"14, V. E. Fermi 31011 Asolo",
    "sg:city":"Asolo",
    "sg:classifiers":[
        {
            "category":"Sports & Exercise",
            "subcategory":"Playing Field",
            "type":"Entertainment"
        }
    ],
    "sg:phone":"+39 0423 950454",
    "sg:postcode":"31011",
    "sg:province":"Treviso",
    "sg:tags":[
        "game"
    ],
    "sg:website":"http://www.agef.it:ws_end: :mark:ws:http://www.paginegialle.it/agef",
    "wof:name":"Agef Id Srl",
    "wof:placetype":"venue"
},
  "geometry": {"coordinates":[12.242072,45.666286],"type":"Point"}
}