{
  "type": "Feature",
  "properties": {
    "addr:full":"20021 Bollate Bollate Milano 20021",
    "addr:postcode":"20021;20021",
    "iso:country":"IT",
    "sg:address":"20021 Bollate",
    "sg:city":"Bollate",
    "sg:orig_category":"Medici. Assicurazioni E Servizi Assicurativi. Avvocati, Notai E Servizi Legali. Professionisti - Studi E Servizi Ed Associazioni Di Interesse Aziendale",
    "sg:phone":"+39 02 350 1490",
    "sg:postcode":"20021",
    "sg:province":"Milano",
    "wof:name":"Molendini Antonio",
    "wof:placetype":"venue"
},
  "geometry": {"coordinates":[9.1061067581,45.5499382019],"type":"Point"}
}