{
  "type": "Feature",
  "properties": {
    "addr:full":"Contrada Coretto 87046 Montalto Uffugo Montalto Uffugo Cosenza 87046",
    "addr:postcode":"87046;87046",
    "addr:street":"Contrada Coretto",
    "iso:country":"IT",
    "sg:address":"Contrada Coretto 87046 Montalto Uffugo",
    "sg:city":"Montalto Uffugo",
    "sg:classifiers":[
        {
            "category":"Shopping",
            "subcategory":"Computers & Home Electronics",
            "type":"Retail Goods"
        }
    ],
    "sg:phone":"+39 0984 929728",
    "sg:postcode":"87046",
    "sg:province":"Cosenza",
    "sg:tags":[
        "electronic",
        "electrical",
        "equipment"
    ],
    "wof:name":"Dosa Sas Di Domenico Stellato E C.",
    "wof:placetype":"venue"
},
  "geometry": {"coordinates":[16.253809,39.298264],"type":"Point"}
}