{
  "type": "Feature",
  "properties": {
    "iso:country":"IT",
    "sg:address":"227, V. Nazionale Appia 81022 Casagiove",
    "sg:city":"Casagiove",
    "sg:classifiers":[
        {
            "category":"Food & Beverages",
            "subcategory":"Groceries & Convenience Stores",
            "type":"Retail Goods"
        }
    ],
    "sg:phone":"+39 0823 466011",
    "sg:postcode":"81022",
    "sg:province":"Caserta",
    "sg:tags":[
        "product",
        "related"
    ],
    "wof:name":"Olearia Campana Spa - Crom",
    "wof:placetype":"venue"
},
  "geometry": {"coordinates":[14.284734726,41.0753173828],"type":"Point"}
}