{
  "type": "Feature",
  "properties": {
    "iso:country":"IT",
    "sg:address":"31, Via Angelo Canossi 25060 Marcheno",
    "sg:city":"Marcheno",
    "sg:classifiers":[
        {
            "category":"Shopping",
            "type":"Retail Goods"
        }
    ],
    "sg:phone":"+39 030 896 0190",
    "sg:postcode":"25060",
    "sg:province":"Brescia",
    "sg:tags":[
        "finished",
        "-",
        "metallic"
    ],
    "wof:name":"Valbia S.r.l.",
    "wof:placetype":"venue"
},
  "geometry": {"coordinates":[10.2249755859,45.716217041],"type":"Point"}
}