{
  "type": "Feature",
  "properties": {
    "addr:full":"62029 Tolentino Tolentino Macerata 62029",
    "addr:postcode":"62029;62029",
    "iso:country":"IT",
    "sg:address":"62029 Tolentino",
    "sg:city":"Tolentino",
    "sg:orig_category":"Fonderie Alluminio",
    "sg:phone":"+39 0733 971792",
    "sg:postcode":"62029",
    "sg:province":"Macerata",
    "sg:website":"http://www.fometal.it",
    "wof:name":"Fo.metal. Di Nobili A. & Niccolini P. Snc",
    "wof:placetype":"venue"
},
  "geometry": {"coordinates":[13.2894363403,43.2241897583],"type":"Point"}
}