{
  "type": "Feature",
  "properties": {
    "iso:country":"IT",
    "sg:address":"29020 Corte Brugnatella",
    "sg:city":"Corte Brugnatella",
    "sg:orig_category":"Macchine Ed Impianti Per Edilizia E Lavori Pubblici. Impianti E Attrezzature Per Lo Sport E Il Tempo Libero",
    "sg:phone":"+39 0523 939310",
    "sg:postcode":"29020",
    "sg:province":"Piacenza",
    "wof:name":"Grilli Franco",
    "wof:placetype":"venue"
},
  "geometry": {"coordinates":[9.382204,44.712502],"type":"Point"}
}