{
  "type": "Feature",
  "properties": {
    "iso:country":"IT",
    "sg:address":"Via Negrelli, 65/67 20035 Lissone",
    "sg:city":"Lissone",
    "sg:classifiers":[
        {
            "category":"Structure",
            "subcategory":"Office Building",
            "type":"Public Place"
        }
    ],
    "sg:phone":"+39 039 485286",
    "sg:postcode":"20035",
    "sg:province":"Milano",
    "sg:tags":[
        "wall",
        "ceiling",
        "partition",
        "room",
        "clean"
    ],
    "sg:website":"www.parteco.it",
    "wof:name":"Parteco Srl",
    "wof:placetype":"venue"
},
  "geometry": {"coordinates":[9.257936,45.6073],"type":"Point"}
}