{
  "type": "Feature",
  "properties": {
    "iso:country":"IT",
    "sg:address":"46043 Castiglione Delle Stiviere",
    "sg:city":"Castiglione delle Stiviere",
    "sg:orig_category":"Impiantistica E Prodotti Tecnologici Per Edilizia",
    "sg:phone":"+39 0376 944434",
    "sg:postcode":"46043",
    "sg:province":"Mantova",
    "wof:name":"Idealpark Srl",
    "wof:placetype":"venue"
},
  "geometry": {"coordinates":[10.493342,45.387501],"type":"Point"}
}