{
  "type": "Feature",
  "properties": {
    "addr:full":"194/196, Via Xx Settembre 28883 Gravellona Toce Gravellona Toce Verbano-Cusio-Ossola 28883",
    "addr:housenumber":"194 / 196",
    "addr:postcode":"28883;28883",
    "addr:street":"Via Xx Settembre",
    "iso:country":"IT",
    "sg:address":"194/196, Via Xx Settembre 28883 Gravellona Toce",
    "sg:city":"Gravellona Toce",
    "sg:classifiers":[
        {
            "category":"Manufacturing",
            "subcategory":"Motor Vehicles & Parts",
            "type":"Manufacturing & Wholesale Goods"
        }
    ],
    "sg:phone":"+39 39032384863",
    "sg:postcode":"28883",
    "sg:province":"Verbano-Cusio-Ossola",
    "sg:tags":[
        "engine"
    ],
    "wof:name":"Attrezzature F.p.a. S.r.l.",
    "wof:placetype":"venue"
},
  "geometry": {"coordinates":[8.272465,46.139969],"type":"Point"}
}