{
  "type": "Feature",
  "properties": {
    "addr:full":"Via Della Repubblica 105 47039 Savignano Sul Rubicone Savignano sul Rubicone Forl\u00ec-Cesena 47039",
    "addr:housenumber":"105",
    "addr:postcode":"47039;47039",
    "addr:street":"Via Della Repubblica",
    "iso:country":"IT",
    "sg:address":"Via Della Repubblica 105 47039 Savignano Sul Rubicone",
    "sg:city":"Savignano sul Rubicone",
    "sg:orig_category":"Ladies' Knitwear",
    "sg:phone":"+39 0541 945768",
    "sg:postcode":"47039",
    "sg:province":"Forl\u00ec-Cesena",
    "sg:website":"www.gemmazanzani.it",
    "wof:name":"Maglificio Da-ni Di Zanzani Gemma & C. Snc",
    "wof:placetype":"venue"
},
  "geometry": {"coordinates":[12.405804,44.099091],"type":"Point"}
}