{
  "type": "Feature",
  "properties": {
    "iso:country":"IT",
    "sg:address":"30, Viale Giacomo Matteotti 24050 Grassobbio",
    "sg:city":"Grassobbio",
    "sg:classifiers":[
        {
            "category":"Home & Garden",
            "subcategory":"Home Furnishings",
            "type":"Retail Goods"
        }
    ],
    "sg:phone":"+39 39035525040",
    "sg:postcode":"24050",
    "sg:province":"Bergamo",
    "sg:tags":[
        "household"
    ],
    "wof:name":"Imma Di Rudelli Gianandrea & C. (s.a.s.)",
    "wof:placetype":"venue"
},
  "geometry": {"coordinates":[9.721277,45.66235],"type":"Point"}
}