{
  "type": "Feature",
  "properties": {
    "iso:country":"IT",
    "sg:address":"70024 Gravina In Puglia",
    "sg:city":"Gravina in Puglia",
    "sg:orig_category":"Medicinali E Prodotti Parafarmaceutici",
    "sg:phone":"+39 333 742 5817",
    "sg:postcode":"70024",
    "sg:province":"Bari",
    "wof:name":"L'emporio Verde Di Alloggio Pietro",
    "wof:placetype":"venue"
},
  "geometry": {"coordinates":[16.4244880676,40.8201942444],"type":"Point"}
}