{
  "type": "Feature",
  "properties": {
    "iso:country":"IT",
    "sg:address":"4, Via Giovanni Xxiii 40057 Granarolo Dell'emilia",
    "sg:classifiers":[
        {
            "category":"Communications",
            "subcategory":"Newspaper",
            "type":"Services"
        }
    ],
    "sg:phone":"+39 39051767017",
    "sg:postcode":"40057",
    "sg:province":"Bologna",
    "sg:tags":[
        "advertising"
    ],
    "wof:name":"Inglese (s.p.a.)",
    "wof:placetype":"venue"
},
  "geometry": {"coordinates":[11.411285,44.533142],"type":"Point"}
}