{
  "type": "Feature",
  "properties": {
    "iso:country":"IT",
    "sg:address":"Via Pontebbana 33080 Fiume Veneto",
    "sg:city":"Fiume Veneto",
    "sg:classifiers":[
        {
            "category":"Government",
            "subcategory":"Court House",
            "type":"Public Place"
        }
    ],
    "sg:phone":"+39 0434 958958",
    "sg:postcode":"33080",
    "sg:province":"Pordenone",
    "sg:tags":[
        "dredger",
        "cable"
    ],
    "wof:name":"Farid Industrie Spa Torino",
    "wof:placetype":"venue"
},
  "geometry": {"coordinates":[12.714156,45.933537],"type":"Point"}
}