{
  "type": "Feature",
  "properties": {
    "addr:full":"7, Via Dante 20123 Milano Milano Milano 20123",
    "addr:postcode":"20123;20123",
    "addr:street":"Via Dante",
    "iso:country":"IT",
    "sg:address":"7, Via Dante 20123 Milano",
    "sg:city":"Milano",
    "sg:classifiers":[
        {
            "category":"Communications",
            "subcategory":"Newspaper",
            "type":"Services"
        }
    ],
    "sg:phone":"+39 390 280 2021",
    "sg:postcode":"20123",
    "sg:province":"Milano",
    "sg:tags":[
        "advertising"
    ],
    "wof:name":"Euro Rscg Mezzano Costantini Mignani S.r.l.",
    "wof:placetype":"venue"
},
  "geometry": {"coordinates":[9.1843,45.466667],"type":"Point"}
}