{
  "type": "Feature",
  "properties": {
    "iso:country":"IT",
    "sg:address":"00015 Monterotondo",
    "sg:city":"Monterotondo",
    "sg:orig_category":"Servizi E Lavori Per Agricoltura E Zootecnia. Consulenze Tecniche, Amministrative E Perizie",
    "sg:phone":"+39 06 9062 5873",
    "sg:postcode":"00015",
    "sg:province":"Roma",
    "wof:name":"Valeriani Coriolano",
    "wof:placetype":"venue"
},
  "geometry": {"coordinates":[12.62127,42.053421],"type":"Point"}
}