{
  "type": "Feature",
  "properties": {
    "addr:full":"2, Via Cavalieri Di Malta 35038 Torreglia Torreglia Padova 35038",
    "addr:postcode":"35038;35038",
    "addr:street":"Via Cavalieri Di Malta",
    "iso:country":"IT",
    "sg:address":"2, Via Cavalieri Di Malta 35038 Torreglia",
    "sg:city":"Torreglia",
    "sg:classifiers":[
        {
            "category":"Manufacturing",
            "subcategory":"Rubber & Plastics",
            "type":"Manufacturing & Wholesale Goods"
        }
    ],
    "sg:phone":"+39 049 999 8811",
    "sg:postcode":"35038",
    "sg:province":"Padova",
    "wof:name":"Thermoform S.p.a.",
    "wof:placetype":"venue"
},
  "geometry": {"coordinates":[11.7372293472,45.3290214539],"type":"Point"}
}