{
  "type": "Feature",
  "properties": {
    "addr:full":"Km. 11.500, Strada Statale 7 Bis 81030 Teverola Teverola Caserta 81030",
    "addr:housenumber":"7 bis",
    "addr:postcode":"81030;81030",
    "addr:street":"Km.;Strada Statale",
    "iso:country":"IT",
    "sg:address":"Km. 11.500, Strada Statale 7 Bis 81030 Teverola",
    "sg:city":"Teverola",
    "sg:classifiers":[
        {
            "category":"Manufacturing",
            "subcategory":"Metals",
            "type":"Manufacturing & Wholesale Goods"
        }
    ],
    "sg:phone":"+39 081 503 4447",
    "sg:postcode":"81030",
    "sg:province":"Caserta",
    "sg:tags":[
        "processing"
    ],
    "wof:name":"D.sepe E F.lli Srl",
    "wof:placetype":"venue"
},
  "geometry": {"coordinates":[14.3321943283,41.0754165649],"type":"Point"}
}