{
  "type": "Feature",
  "properties": {
    "iso:country":"IT",
    "sg:address":"41100 Modena",
    "sg:city":"Modena",
    "sg:orig_category":"Trattamenti Termici E Superficiali Metalli, Galvanotecnica. Utensili Meccanici E Materiali",
    "sg:phone":"+39 059 333173",
    "sg:postcode":"41100",
    "sg:province":"Modena",
    "wof:name":"F.p.officina Meccanica Srl",
    "wof:placetype":"venue"
},
  "geometry": {"coordinates":[10.943328,44.550243],"type":"Point"}
}