{
  "type": "Feature",
  "properties": {
    "addr:full":"35020 Ponte San Nicolo' Padova 35020",
    "addr:postcode":"35020;35020",
    "addr:street":"Nicolo ' Padova",
    "iso:country":"IT",
    "sg:address":"35020 Ponte San Nicolo'",
    "sg:orig_category":"Indirizzi Commerciali",
    "sg:phone":"+39 049 896 8034",
    "sg:postcode":"35020",
    "sg:province":"Padova",
    "wof:name":"Beep-beep Volantinaggio",
    "wof:placetype":"venue"
},
  "geometry": {"coordinates":[11.93038,45.365978],"type":"Point"}
}