{
  "type": "Feature",
  "properties": {
    "addr:full":"1, Via Pradisopra 39045 Fortezza Fortezza Bolzano/Bozen 39045",
    "addr:postcode":"39045;39045",
    "addr:street":"Via Pradisopra",
    "iso:country":"IT",
    "sg:address":"1, Via Pradisopra 39045 Fortezza",
    "sg:city":"Fortezza",
    "sg:classifiers":[
        {
            "category":"Manufacturing",
            "subcategory":"Lumber",
            "type":"Manufacturing & Wholesale Goods"
        }
    ],
    "sg:phone":"+39 0472 458686",
    "sg:postcode":"39045",
    "sg:province":"Bolzano/Bozen",
    "sg:tags":[
        "wood"
    ],
    "wof:name":"Plunger L. & Figlio (s.p.a.)",
    "wof:placetype":"venue"
},
  "geometry": {"coordinates":[11.358005,46.496716],"type":"Point"}
}