{
  "type": "Feature",
  "properties": {
    "iso:country":"IT",
    "sg:address":"00161 Roma",
    "sg:city":"Roma",
    "sg:orig_category":"Servizi Al Turismo. Ambasciate Ed Enti Internazionali",
    "sg:phone":"+39 06 440 3270",
    "sg:postcode":"00161",
    "sg:province":"Roma",
    "wof:name":"Remenyi Karoly",
    "wof:placetype":"venue"
},
  "geometry": {"coordinates":[12.679593,41.702702],"type":"Point"}
}