{
  "type": "Feature",
  "properties": {
    "iso:country":"IT",
    "sg:address":"39/a, Via Roma 23018 Talamona",
    "sg:city":"Talamona",
    "sg:classifiers":[
        {
            "category":"Shopping",
            "subcategory":"Clothing, Apparel, & Fashions",
            "type":"Retail Goods"
        }
    ],
    "sg:phone":"+39 0342 670267",
    "sg:postcode":"23018",
    "sg:province":"Sondrio",
    "sg:tags":[
        "clothing",
        "accessory"
    ],
    "wof:name":"Fili Di Seta Di Tarca Milena",
    "wof:placetype":"venue"
},
  "geometry": {"coordinates":[9.605898,46.137508],"type":"Point"}
}