{
  "type": "Feature",
  "properties": {
    "iso:country":"IT",
    "sg:address":"25010 Ponte San Marco",
    "sg:classifiers":[
        {
            "category":"Wholesale",
            "subcategory":"Machinery & Supplies",
            "type":"Manufacturing & Wholesale Goods"
        }
    ],
    "sg:phone":"+39 030 996 9977",
    "sg:postcode":"25010",
    "sg:province":"Brescia",
    "sg:tags":[
        "activities",
        "industrial"
    ],
    "sg:website":"http://www.cerabra.it",
    "wof:name":"Cerabra Srl",
    "wof:placetype":"venue"
},
  "geometry": {"coordinates":[10.222958,45.539829],"type":"Point"}
}