{
  "type": "Feature",
  "properties": {
    "iso:country":"IT",
    "sg:address":"41017 Ravarino",
    "sg:city":"Ravarino",
    "sg:orig_category":"Sughero Ed Agglomerati",
    "sg:phone":"+39 059 900117",
    "sg:postcode":"41017",
    "sg:province":"Modena",
    "wof:name":"Marchi Franco Sugherificio Marchi",
    "wof:placetype":"venue"
},
  "geometry": {"coordinates":[11.081429,44.729038],"type":"Point"}
}