{
  "type": "Feature",
  "properties": {
    "iso:country":"IT",
    "sg:address":"10015 Ivrea",
    "sg:city":"Ivrea",
    "sg:orig_category":"Studi E Consulenze Amministrative, Commerciali E Aziendali. Consulenze Tecniche, Amministrative E Perizie",
    "sg:phone":"+39 0125 529250",
    "sg:postcode":"10015",
    "sg:province":"Torino",
    "sg:website":"http://www.elea.it",
    "wof:name":"Elea Spa",
    "wof:placetype":"venue"
},
  "geometry": {"coordinates":[7.995,45.424557],"type":"Point"}
}