{
  "type": "Feature",
  "properties": {
    "iso:country":"IT",
    "sg:address":"Via Barucchella 39 46030 Sustinente",
    "sg:city":"Sustinente",
    "sg:classifiers":[
        {
            "category":"Building & Trades",
            "subcategory":"Construction",
            "type":"Services"
        }
    ],
    "sg:phone":"+39 0386 800320",
    "sg:postcode":"46030",
    "sg:province":"Mantova",
    "sg:tags":[
        "carpenter's",
        "work",
        "supraregional"
    ],
    "wof:name":"O.c.i.s. Snc",
    "wof:placetype":"venue"
},
  "geometry": {"coordinates":[11.028434,45.06739],"type":"Point"}
}