{
  "type": "Feature",
  "properties": {
    "addr:full":"20133 Milano Milano Milano 20133",
    "addr:postcode":"20133;20133",
    "iso:country":"IT",
    "sg:address":"20133 Milano",
    "sg:city":"Milano",
    "sg:classifiers":[
        {
            "category":"Manufacturing",
            "subcategory":"Rubber & Plastics",
            "type":"Manufacturing & Wholesale Goods"
        }
    ],
    "sg:phone":"+39 02 7060 5174",
    "sg:postcode":"20133",
    "sg:province":"Milano",
    "sg:tags":[
        "article",
        "product"
    ],
    "wof:name":"S.d.m. S.c. A R.l.",
    "wof:placetype":"venue"
},
  "geometry": {"coordinates":[9.233176,45.473503],"type":"Point"}
}