{
  "type": "Feature",
  "properties": {
    "iso:country":"IT",
    "sg:address":"95040 Catania",
    "sg:orig_category":"Prodotti Chimici Secondari. Servizi E Lavori Per Ecologia E Smaltimento Rifiuti. Macchine E Forniture Per Ecologia E Smaltimento Rifiuti",
    "sg:phone":"+39 095 422964",
    "sg:postcode":"95040",
    "sg:province":"Catania",
    "wof:name":"Torrisi Domenico",
    "wof:placetype":"venue"
},
  "geometry": {"coordinates":[15.0878343582,37.5024833679],"type":"Point"}
}