{
  "type": "Feature",
  "properties": {
    "iso:country":"IT",
    "sg:address":"53100 Siena",
    "sg:city":"Siena",
    "sg:orig_category":"Associazioni Sindacali E Di Categoria",
    "sg:phone":"+39 0577 2520",
    "sg:postcode":"53100",
    "sg:province":"Siena",
    "sg:website":"http://www.confesercenti.siena.it",
    "wof:name":"Cooperativa Esercenti Senesi A R.l.",
    "wof:placetype":"venue"
},
  "geometry": {"coordinates":[11.345474,43.323696],"type":"Point"}
}