{
  "type": "Feature",
  "properties": {
    "addr:full":"20154 Milano Milano Milano 20154",
    "addr:postcode":"20154;20154",
    "iso:country":"IT",
    "sg:address":"20154 Milano",
    "sg:city":"Milano",
    "sg:orig_category":"Trasporto Pubblico E Privato",
    "sg:phone":"+39 02 655 2349",
    "sg:postcode":"20154",
    "sg:province":"Milano",
    "wof:name":"Taxi",
    "wof:placetype":"venue"
},
  "geometry": {"coordinates":[9.300331,45.487679],"type":"Point"}
}