{
  "type": "Feature",
  "properties": {
    "addr:full":"47020 Longiano Longiano Forl\u00ec-Cesena 47020",
    "addr:postcode":"47020;47020",
    "iso:country":"IT",
    "sg:address":"47020 Longiano",
    "sg:city":"Longiano",
    "sg:orig_category":"Imballaggi - Produzione E Commercio",
    "sg:phone":"+39 0547 56051",
    "sg:postcode":"47020",
    "sg:province":"Forl\u00ec-Cesena",
    "wof:name":"I.c.t.i.a. Snc",
    "wof:placetype":"venue"
},
  "geometry": {"coordinates":[12.199131,44.154163],"type":"Point"}
}