{
  "type": "Feature",
  "properties": {
    "addr:full":"65020 Cugnoli Cugnoli Pescara 65020",
    "addr:postcode":"65020;65020",
    "iso:country":"IT",
    "sg:address":"65020 Cugnoli",
    "sg:city":"Cugnoli",
    "sg:orig_category":"Macchine, Strumenti Ed Apparecchi Per Attivita' Industriali",
    "sg:phone":"+39 085 857 6133",
    "sg:postcode":"65020",
    "sg:province":"Pescara",
    "wof:name":"Restante Nicola",
    "wof:placetype":"venue"
},
  "geometry": {"coordinates":[13.970041,42.294491],"type":"Point"}
}