{
  "type": "Feature",
  "properties": {
    "addr:full":"16121 Genova Genova Genova 16121",
    "addr:postcode":"16121;16121",
    "iso:country":"IT",
    "sg:address":"16121 Genova",
    "sg:city":"Genova",
    "sg:orig_category":"Filati E Materie Prime Tessili",
    "sg:phone":"+39 010 562594",
    "sg:postcode":"16121",
    "sg:province":"Genova",
    "wof:name":"La Fonte Della Lana",
    "wof:placetype":"venue"
},
  "geometry": {"coordinates":[8.943195343,44.4071731567],"type":"Point"}
}