{
  "type": "Feature",
  "properties": {
    "addr:full":"42015 Correggio Reggio Nell'Emilia 42015",
    "addr:postcode":"42015;42015",
    "iso:country":"IT",
    "sg:address":"42015 Correggio",
    "sg:orig_category":"Arredamento Uffici",
    "sg:phone":"+39 0522 692771",
    "sg:postcode":"42015",
    "sg:province":"Reggio Nell'Emilia",
    "wof:name":"Gianni Leoni & C. Snc",
    "wof:placetype":"venue"
},
  "geometry": {"coordinates":[10.776875,44.732365],"type":"Point"}
}