{
  "type": "Feature",
  "properties": {
    "iso:country":"IT",
    "sg:address":"20122 Milano",
    "sg:city":"Milano",
    "sg:orig_category":"Agenzie D'affari E Servizi Commerciali. Avvocati, Notai E Servizi Legali. Consulenze Tecniche, Amministrative E Perizie",
    "sg:phone":"+39 02 546 3641",
    "sg:postcode":"20122",
    "sg:province":"Milano",
    "wof:name":"Societa' Generale Di Rervisione E Certificazione Sas Di Barranco & C.",
    "wof:placetype":"venue"
},
  "geometry": {"coordinates":[9.200259,45.461048],"type":"Point"}
}