{
  "type": "Feature",
  "properties": {
    "addr:full":"12020 Pontechianale Pontechianale Cuneo 12020",
    "addr:housenumber":"12020",
    "addr:postcode":"12020",
    "addr:street":"Pontechianale Pontechianale",
    "iso:country":"IT",
    "sg:address":"12020 Pontechianale",
    "sg:city":"Pontechianale",
    "sg:orig_category":"Servizi Per Lo Sport E Il Tempo Libero. Alberghi E Strutture Extra Alberghiere",
    "sg:phone":"+39 0175 956025",
    "sg:postcode":"12020",
    "sg:province":"Cuneo",
    "wof:name":"Rifugio Gagliardone G. Al Monviso - C.a.i.",
    "wof:placetype":"venue"
},
  "geometry": {"coordinates":[7.035533,44.346863],"type":"Point"}
}