{
  "type": "Feature",
  "properties": {
    "addr:full":"20010 Pregnana Milanese Pregnana Milanese Milano 20010",
    "addr:postcode":"20010;20010",
    "addr:street":"Milanese",
    "iso:country":"IT",
    "sg:address":"20010 Pregnana Milanese",
    "sg:city":"Pregnana Milanese",
    "sg:orig_category":"Prodotti Vari In Metallo. Articoli Per Imballaggio E Confezionamento",
    "sg:phone":"+39 02 9329 0259",
    "sg:postcode":"20010",
    "sg:province":"Milano",
    "wof:name":"Coc Srl",
    "wof:placetype":"venue"
},
  "geometry": {"coordinates":[9.0175905228,45.5161705017],"type":"Point"}
}