{
  "type": "Feature",
  "properties": {
    "addr:full":"31052 Maserada Sul Piave Maserada sul Piave Treviso 31052",
    "addr:postcode":"31052;31052",
    "iso:country":"IT",
    "sg:address":"31052 Maserada Sul Piave",
    "sg:city":"Maserada sul Piave",
    "sg:orig_category":"Macchine E Forniture Per Arredamento E Industria Del Legno. Utensili Meccanici E Materiali",
    "sg:phone":"+39 0422 877184",
    "sg:postcode":"31052",
    "sg:province":"Treviso",
    "wof:name":"Schiavon S.r.l.",
    "wof:placetype":"venue"
},
  "geometry": {"coordinates":[12.288602,45.731949],"type":"Point"}
}