{
  "type": "Feature",
  "properties": {
    "iso:country":"IT",
    "sg:address":"40, V. L. G. Marini 00179 Roma",
    "sg:city":"Roma",
    "sg:classifiers":[
        {
            "category":"Manufacturing",
            "subcategory":"Printing",
            "type":"Manufacturing & Wholesale Goods"
        }
    ],
    "sg:phone":"+39 39067857755",
    "sg:postcode":"00179",
    "sg:province":"Roma",
    "sg:tags":[
        "publishing"
    ],
    "sg:website":"http://www.paginegialle.it/cartonplastex",
    "wof:name":"La Carton Plastex Di Frati Osvalda",
    "wof:placetype":"venue"
},
  "geometry": {"coordinates":[12.5206441879,41.8714675903],"type":"Point"}
}