{
  "type": "Feature",
  "properties": {
    "addr:full":"20129 Milano Milano Milano 20129",
    "addr:postcode":"20129;20129",
    "iso:country":"IT",
    "sg:address":"20129 Milano",
    "sg:city":"Milano",
    "sg:orig_category":"Agricoltura, Orticoltura E Floricoltura. Articoli Da Regalo. Shopping",
    "sg:phone":"+39 02 204 9368",
    "sg:postcode":"20129",
    "sg:province":"Milano",
    "wof:name":"Fiori Fumagalli Sas Di  Angela Fumagalli",
    "wof:placetype":"venue"
},
  "geometry": {"coordinates":[9.206246,45.473938],"type":"Point"}
}