{
  "type": "Feature",
  "properties": {
    "iso:country":"IT",
    "sg:address":"35010 Borgoricco",
    "sg:city":"Borgoricco",
    "sg:orig_category":"Servizi E Lavori Per Agricoltura E Zootecnia",
    "sg:phone":"+39 049 579 8992",
    "sg:postcode":"35010",
    "sg:province":"Padova",
    "wof:name":"Tonello Orlando",
    "wof:placetype":"venue"
},
  "geometry": {"coordinates":[11.942204,45.536278],"type":"Point"}
}