{
  "type": "Feature",
  "properties": {
    "addr:full":"58022 Follonica Follonica Grosseto 58022",
    "addr:postcode":"58022;58022",
    "iso:country":"IT",
    "sg:address":"58022 Follonica",
    "sg:city":"Follonica",
    "sg:orig_category":"Medicinali E Prodotti Parafarmaceutici",
    "sg:phone":"+39 0566 53690",
    "sg:postcode":"58022",
    "sg:province":"Grosseto",
    "wof:name":"Pepe Giuseppe",
    "wof:placetype":"venue"
},
  "geometry": {"coordinates":[11.110701561,42.7811355591],"type":"Point"}
}