{
  "type": "Feature",
  "properties": {
    "iso:country":"IT",
    "sg:address":"70126 Bari",
    "sg:city":"Bari",
    "sg:orig_category":"Ricambi E Componenti Dei Mezzi Di Trasporto",
    "sg:phone":"+39 080 558 0958",
    "sg:postcode":"70126",
    "sg:province":"Bari",
    "wof:name":"Colella Francesco",
    "wof:placetype":"venue"
},
  "geometry": {"coordinates":[16.797693,41.000496],"type":"Point"}
}