{
  "type": "Feature",
  "properties": {
    "iso:country":"IT",
    "sg:address":"25/27, Via Liguria 20090 Pieve Emanuele",
    "sg:city":"Pieve Emanuele",
    "sg:classifiers":[
        {
            "category":"Manufacturing",
            "subcategory":"Metals",
            "type":"Manufacturing & Wholesale Goods"
        }
    ],
    "sg:phone":"+39 02 9072 2301",
    "sg:postcode":"20090",
    "sg:province":"Milano",
    "sg:tags":[
        "processing"
    ],
    "wof:name":"Deco (s.r.l.)",
    "wof:placetype":"venue"
},
  "geometry": {"coordinates":[9.1689586639,45.3742218018],"type":"Point"}
}