{
  "type": "Feature",
  "properties": {
    "addr:full":"10036 Settimo Torinese Settimo Torinese Torino 10036",
    "addr:postcode":"10036;10036",
    "iso:country":"IT",
    "sg:address":"10036 Settimo Torinese",
    "sg:city":"Settimo Torinese",
    "sg:orig_category":"Prodotti E Manufatti In Gomma. Servizi E Lavori Industria Della Gomma. Ricambi E Componenti Dei Mezzi Di Trasporto",
    "sg:phone":"+39 011 89561",
    "sg:postcode":"10036",
    "sg:province":"Torino",
    "wof:name":"Pirelli Pneumatici S.p.a.",
    "wof:placetype":"venue"
},
  "geometry": {"coordinates":[7.7384109497,45.1270942688],"type":"Point"}
}