{
  "type": "Feature",
  "properties": {
    "addr:full":"7, Via Cremona 40066 Pieve Di Cento Pieve di Cento Bologna 40066",
    "addr:postcode":"40066;bologna 40066",
    "addr:street":"Via Cremona",
    "iso:country":"IT",
    "sg:address":"7, Via Cremona 40066 Pieve Di Cento",
    "sg:city":"Pieve di Cento",
    "sg:classifiers":[
        {
            "category":"Professional",
            "subcategory":"Engineering",
            "type":"Services"
        }
    ],
    "sg:phone":"+39 39051975558",
    "sg:postcode":"40066",
    "sg:province":"Bologna",
    "sg:tags":[
        "machine",
        "-",
        "mechanical"
    ],
    "wof:name":"Fratelli Giberti Di Giberti Michele E C. Sas",
    "wof:placetype":"venue"
},
  "geometry": {"coordinates":[11.308828,44.716305],"type":"Point"}
}