{
  "type": "Feature",
  "properties": {
    "iso:country":"IT",
    "sg:address":"Via Barozzo 22075 Lurate Caccivio",
    "sg:city":"Lurate Caccivio",
    "sg:classifiers":[
        {
            "category":"Shopping",
            "subcategory":"Crafts & Fabrics",
            "type":"Retail Goods"
        }
    ],
    "sg:phone":"+39 39031490435",
    "sg:postcode":"22075",
    "sg:province":"Como",
    "wof:name":"Bomotex (s.a.s.)",
    "wof:placetype":"venue"
},
  "geometry": {"coordinates":[8.9928646088,45.7750015259],"type":"Point"}
}