{
  "type": "Feature",
  "properties": {
    "iso:country":"IT",
    "sg:address":"16139 Genova",
    "sg:city":"Genova",
    "sg:orig_category":"Arredo Camera Letto E Complementi. Servizi E Lavori Per Arredamento E Industria Del Legno",
    "sg:phone":"+39 010 883395",
    "sg:postcode":"16139",
    "sg:province":"Genova",
    "wof:name":"Cocchella Ermanno",
    "wof:placetype":"venue"
},
  "geometry": {"coordinates":[8.955012,44.415562],"type":"Point"}
}