{
  "type": "Feature",
  "properties": {
    "iso:country":"IT",
    "sg:address":"117, V. Aterno 66020 S.g. Teatino",
    "sg:classifiers":[
        {
            "category":"Manufacturing",
            "subcategory":"Printing",
            "type":"Manufacturing & Wholesale Goods"
        }
    ],
    "sg:phone":"+39 085 446 0994",
    "sg:postcode":"66020",
    "sg:province":"Chieti",
    "sg:tags":[
        "publishing"
    ],
    "sg:website":"http://www.trimbolieditori.com",
    "wof:name":"New Cards",
    "wof:placetype":"venue"
},
  "geometry": {"coordinates":[14.1619062424,42.4136772156],"type":"Point"}
}