{
  "type": "Feature",
  "properties": {
    "iso:country":"IT",
    "sg:address":"3/b, Localita' Giasbana 34070 San Floriano Del Collio",
    "sg:city":"Giasbana",
    "sg:orig_category":"Miscellaneous Products",
    "sg:phone":"+39 0481 391656",
    "sg:postcode":"34070",
    "sg:province":"Gorizia",
    "wof:name":"Braini",
    "wof:placetype":"venue"
},
  "geometry": {"coordinates":[13.5446166992,45.9625205994],"type":"Point"}
}