{
  "type": "Feature",
  "properties": {
    "addr:full":"74, Via Dell' Indipendenza 40121 Bologna Bologna Bologna 40121",
    "addr:postcode":"40121;40121",
    "addr:street":"Via Dell ' Indipendenza",
    "iso:country":"IT",
    "sg:address":"74, Via Dell' Indipendenza 40121 Bologna",
    "sg:city":"Bologna",
    "sg:classifiers":[
        {
            "category":"Food & Beverages",
            "subcategory":"Groceries & Convenience Stores",
            "type":"Retail Goods"
        }
    ],
    "sg:phone":"+39 39051249590",
    "sg:postcode":"40121",
    "sg:province":"Bologna",
    "sg:tags":[
        "product",
        "related"
    ],
    "wof:name":"Agri 2000 Soc. Coop.r.l.",
    "wof:placetype":"venue"
},
  "geometry": {"coordinates":[11.3449716568,44.5032043457],"type":"Point"}
}