{
  "type": "Feature",
  "properties": {
    "iso:country":"IT",
    "sg:address":"07040 Codrongianos",
    "sg:city":"Codrongianos",
    "sg:orig_category":"Automobili E Mezzi Di Trasporto",
    "sg:phone":"+39 079 435422",
    "sg:postcode":"07040",
    "sg:province":"Sassari",
    "wof:name":"Sabbatini Di Sabbatini Marco Theo (s.a.s.)",
    "wof:placetype":"venue"
},
  "geometry": {"coordinates":[8.680963,40.658463],"type":"Point"}
}