{
  "type": "Feature",
  "properties": {
    "addr:full":"79, Via Cadorna 25027 Quinzano D'oglio Brescia 25027",
    "addr:postcode":"25027;25027",
    "addr:street":"Via Cadorna",
    "iso:country":"IT",
    "sg:address":"79, Via Cadorna 25027 Quinzano D'oglio",
    "sg:classifiers":[
        {
            "category":"Shopping",
            "type":"Retail Goods"
        }
    ],
    "sg:phone":"+39 030 933 6555",
    "sg:postcode":"25027",
    "sg:province":"Brescia",
    "sg:tags":[
        "finished",
        "-",
        "metallic"
    ],
    "wof:name":"Brabantia Italia (s.r.l.)",
    "wof:placetype":"venue"
},
  "geometry": {"coordinates":[10.2229576111,45.5398292542],"type":"Point"}
}