{
  "type": "Feature",
  "properties": {
    "iso:country":"IT",
    "sg:address":"15, Via Lavariano 33050 Mortegliano",
    "sg:city":"Lavariano",
    "sg:classifiers":[
        {
            "category":"Wholesale",
            "subcategory":"Drugs",
            "type":"Manufacturing & Wholesale Goods"
        }
    ],
    "sg:phone":"+39 0432 761801",
    "sg:postcode":"33050",
    "sg:province":"Udine",
    "sg:tags":[
        "chemical",
        "pharmaceutical"
    ],
    "wof:name":"Friulsiir Srl",
    "wof:placetype":"venue"
},
  "geometry": {"coordinates":[13.18272,45.94817],"type":"Point"}
}