{
  "type": "Feature",
  "properties": {
    "addr:full":"20122 Milano Milano Milano 20122",
    "addr:postcode":"20122;20122",
    "iso:country":"IT",
    "sg:address":"20122 Milano",
    "sg:city":"Milano",
    "sg:orig_category":"Cine-foto-ottica",
    "sg:phone":"+39 02 5844 1276",
    "sg:postcode":"20122",
    "sg:province":"Milano",
    "wof:name":"Foto Click S.a.s. Di Marco Dell'uomo & C.",
    "wof:placetype":"venue"
},
  "geometry": {"coordinates":[9.194346,45.452133],"type":"Point"}
}