{
  "type": "Feature",
  "properties": {
    "iso:country":"IT",
    "sg:address":"136, Via Boncore 63014 Montegranaro",
    "sg:city":"Montegranaro",
    "sg:classifiers":[
        {
            "category":"Personal",
            "subcategory":"Shoe Repair & Shine",
            "type":"Services"
        }
    ],
    "sg:phone":"+39 0734 890909",
    "sg:postcode":"63014",
    "sg:province":"Ascoli Piceno",
    "sg:tags":[
        "leather"
    ],
    "wof:name":"Dettagli Srl",
    "wof:placetype":"venue"
},
  "geometry": {"coordinates":[13.626593,43.22551],"type":"Point"}
}