{
  "type": "Feature",
  "properties": {
    "addr:full":"35121 Padova Padova Padova 35121",
    "addr:postcode":"35121;35121",
    "iso:country":"IT",
    "sg:address":"35121 Padova",
    "sg:city":"Padova",
    "sg:orig_category":"Forniture Per Congressi, Fiere E Manifestazioni",
    "sg:phone":"+39 049 875 1723",
    "sg:postcode":"35121",
    "sg:province":"Padova",
    "wof:name":"Parva Favilla Snc",
    "wof:placetype":"venue"
},
  "geometry": {"coordinates":[11.8030347824,45.3608322144],"type":"Point"}
}