{
  "type": "Feature",
  "properties": {
    "addr:full":"28868 Varzo Varzo Verbano-Cusio-Ossola 28868",
    "addr:postcode":"28868;28868",
    "iso:country":"IT",
    "sg:address":"28868 Varzo",
    "sg:city":"Varzo",
    "sg:orig_category":"Servizi Per Lo Sport E Il Tempo Libero. Servizi Al Turismo. Acqua, Luce, Gas E Societa' Di Esercizio Pubblico",
    "sg:phone":"+39 0324 72572",
    "sg:postcode":"28868",
    "sg:province":"Verbano-Cusio-Ossola",
    "wof:name":"Parco Naturale Alpe Veglia",
    "wof:placetype":"venue"
},
  "geometry": {"coordinates":[8.251106,46.206181],"type":"Point"}
}