{
  "type": "Feature",
  "properties": {
    "iso:country":"IT",
    "sg:address":"10038 Verolengo",
    "sg:city":"Verolengo",
    "sg:orig_category":"Dolciumi - Vendita Al Dettaglio",
    "sg:phone":"+39 011 914 9001",
    "sg:postcode":"10038",
    "sg:province":"Torino",
    "wof:name":"Dolciaria Casa Snc",
    "wof:placetype":"venue"
},
  "geometry": {"coordinates":[7.971743,45.189312],"type":"Point"}
}