{
  "type": "Feature",
  "properties": {
    "addr:full":"20124 Milano Milano Milano 20124",
    "addr:postcode":"20124;20124",
    "iso:country":"IT",
    "sg:address":"20124 Milano",
    "sg:city":"Milano",
    "sg:orig_category":"Elettronica Professionale E Di Consumo. Automazione E Macchine Per Ufficio. Forniture Per Congressi, Fiere E Manifestazioni",
    "sg:phone":"+39 02 6671 9287",
    "sg:postcode":"20124",
    "sg:province":"Milano",
    "wof:name":"Universal Spa",
    "wof:placetype":"venue"
},
  "geometry": {"coordinates":[9.201995,45.481731],"type":"Point"}
}