{
  "type": "Feature",
  "properties": {
    "iso:country":"IT",
    "sg:address":"Via Appia Nuova 94; Marino; 00040",
    "sg:city":"Marino",
    "sg:classifiers":[
        {
            "category":"Banks & Credit Unions",
            "subcategory":"Bank",
            "type":"Services"
        }
    ],
    "sg:phone":"+39 06 9354 8030",
    "sg:postcode":"00040",
    "sg:province":"Roma",
    "wof:name":"Ina Banca - Marino Spa",
    "wof:placetype":"venue"
},
  "geometry": {"coordinates":[12.617666,41.765553],"type":"Point"}
}