{
  "type": "Feature",
  "properties": {
    "iso:country":"IT",
    "sg:address":"00151 Roma",
    "sg:city":"Roma",
    "sg:orig_category":"Antenne Radio-televisione",
    "sg:phone":"+39 06 5327 3684",
    "sg:postcode":"00151",
    "sg:province":"Roma",
    "wof:name":"Mcm Sistemi Snc",
    "wof:placetype":"venue"
},
  "geometry": {"coordinates":[12.443931,41.864857],"type":"Point"}
}