{
  "type": "Feature",
  "properties": {
    "addr:full":"90135 Palermo Palermo Palermo 90135",
    "addr:postcode":"90135;90135",
    "iso:country":"IT",
    "sg:address":"90135 Palermo",
    "sg:city":"Palermo",
    "sg:orig_category":"Pubblica Amministrazione",
    "sg:phone":"+39 091 315213",
    "sg:postcode":"90135",
    "sg:province":"Palermo",
    "wof:name":"Guardia Di Finanza/iv Compagnia",
    "wof:placetype":"venue"
},
  "geometry": {"coordinates":[13.3083114624,38.1325378418],"type":"Point"}
}