{
  "type": "Feature",
  "properties": {
    "addr:full":"82020 Pietrelcina Pietrelcina Benevento 82020",
    "addr:postcode":"82020;82020",
    "iso:country":"IT",
    "sg:address":"82020 Pietrelcina",
    "sg:city":"Pietrelcina",
    "sg:orig_category":"Articoli Religiosi",
    "sg:phone":"+39 0824 991800",
    "sg:postcode":"82020",
    "sg:province":"Benevento",
    "wof:name":"Antonio Maturo",
    "wof:placetype":"venue"
},
  "geometry": {"coordinates":[14.846694,41.198006],"type":"Point"}
}