{
  "type": "Feature",
  "properties": {
    "addr:full":"21056 Induno Olona Induno Olona Varese 21056",
    "addr:postcode":"21056;21056",
    "iso:country":"IT",
    "sg:address":"21056 Induno Olona",
    "sg:city":"Induno Olona",
    "sg:orig_category":"Trattamenti Termici E Superficiali Metalli, Galvanotecnica",
    "sg:phone":"+39 0332 200260",
    "sg:postcode":"21056",
    "sg:province":"Varese",
    "wof:name":"Osmal Di Marcantonio Francesco E C. Sas",
    "wof:placetype":"venue"
},
  "geometry": {"coordinates":[8.83438,45.853127],"type":"Point"}
}