{
  "type": "Feature",
  "properties": {
    "iso:country":"IT",
    "sg:address":"Strada Statale 13",
    "sg:city":"Tarcento",
    "sg:classifiers":[
        {
            "category":"Manufacturing",
            "subcategory":"Metals",
            "type":"Manufacturing & Wholesale Goods"
        }
    ],
    "sg:phone":"+39 0432 784723",
    "sg:postcode":"33017",
    "sg:province":"Udine",
    "sg:tags":[
        "blanking",
        "dy"
    ],
    "sg:website":"www.julia.it",
    "wof:name":"Julia Utensili Srl",
    "wof:placetype":"venue"
},
  "geometry": {"coordinates":[13.230724,46.064941],"type":"Point"}
}