{
  "type": "Feature",
  "properties": {
    "addr:full":"80126 Napoli Napoli Napoli 80126",
    "addr:housenumber":"80126",
    "addr:postcode":"80126",
    "iso:country":"IT",
    "sg:address":"80126 Napoli",
    "sg:city":"Napoli",
    "sg:orig_category":"Abbigliamento Esterno, Maglierie E Pelliccerie. Calzature, Pelletterie E Pelli",
    "sg:phone":"+39 081 767 5178",
    "sg:postcode":"80126",
    "sg:province":"Napoli",
    "wof:name":"Fratelli Canonico Borse Snc",
    "wof:placetype":"venue"
},
  "geometry": {"coordinates":[14.198797,40.848099],"type":"Point"}
}