{
  "type": "Feature",
  "properties": {
    "iso:country":"IT",
    "sg:address":"26, Via Dell' Industria 35030 Rubano",
    "sg:city":"Rubano",
    "sg:classifiers":[
        {
            "category":"Manufacturing",
            "subcategory":"Lumber",
            "type":"Manufacturing & Wholesale Goods"
        }
    ],
    "sg:phone":"+39 39049634855",
    "sg:postcode":"35030",
    "sg:province":"Padova",
    "sg:tags":[
        "wood"
    ],
    "wof:name":"Edillegno (s.r.l.)",
    "wof:placetype":"venue"
},
  "geometry": {"coordinates":[11.793263,45.416885],"type":"Point"}
}