{
  "type": "Feature",
  "properties": {
    "addr:full":"25018 Montichiari Montichiari Brescia 25018",
    "addr:postcode":"25018;25018",
    "iso:country":"IT",
    "sg:address":"25018 Montichiari",
    "sg:city":"Montichiari",
    "sg:classifiers":[
        {
            "category":"Home & Garden",
            "subcategory":"Building Materials",
            "type":"Retail Goods"
        }
    ],
    "sg:phone":"+39 030 996 1139",
    "sg:postcode":"25018",
    "sg:province":"Brescia",
    "sg:tags":[
        "window",
        "door",
        "frame"
    ],
    "wof:name":"Serramenti Marella Di Marella Stefano & C. Snc",
    "wof:placetype":"venue"
},
  "geometry": {"coordinates":[10.447775,45.38163],"type":"Point"}
}