{
  "type": "Feature",
  "properties": {
    "iso:country":"IT",
    "sg:address":"46045 Marmirolo",
    "sg:city":"Marmirolo",
    "sg:orig_category":"Studi E Consulenze Amministrative, Commerciali E Aziendali. Consulenze Tecniche, Amministrative E Perizie",
    "sg:phone":"+39 0376 467362",
    "sg:postcode":"46045",
    "sg:province":"Mantova",
    "wof:name":"F & M Consulenti D'azienda Srl",
    "wof:placetype":"venue"
},
  "geometry": {"coordinates":[10.76145,45.213799],"type":"Point"}
}