{
  "type": "Feature",
  "properties": {
    "iso:country":"IT",
    "sg:address":"20124 Milano",
    "sg:city":"Milano",
    "sg:orig_category":"Arti Grafiche",
    "sg:phone":"+39 02 671 4121",
    "sg:postcode":"20124",
    "sg:province":"Milano",
    "sg:website":"http://www.video-team.it",
    "wof:name":"Videoteam Srl",
    "wof:placetype":"venue"
},
  "geometry": {"coordinates":[9.210575,45.486835],"type":"Point"}
}