{
  "type": "Feature",
  "properties": {
    "iso:country":"IT",
    "sg:address":"27029 Vigevano",
    "sg:city":"Vigevano",
    "sg:orig_category":"Abbigliamento Esterno, Maglierie E Pelliccerie. Calzature, Pelletterie E Pelli. Sport - Articoli E Forniture",
    "sg:phone":"+39 0381 42950",
    "sg:postcode":"27029",
    "sg:province":"Pavia",
    "wof:name":"Bellazzi Ambrogio",
    "wof:placetype":"venue"
},
  "geometry": {"coordinates":[8.867567,45.302715],"type":"Point"}
}