{
  "type": "Feature",
  "properties": {
    "addr:full":"25128 Brescia Brescia Brescia 25128",
    "addr:postcode":"25128;25128",
    "iso:country":"IT",
    "sg:address":"25128 Brescia",
    "sg:city":"Brescia",
    "sg:orig_category":"Fotografia Industriale",
    "sg:phone":"+39 030 338 4881",
    "sg:postcode":"25128",
    "sg:province":"Brescia",
    "wof:name":"Sala Paolo - In Immaginabile",
    "wof:placetype":"venue"
},
  "geometry": {"coordinates":[10.220082283,45.5577964783],"type":"Point"}
}