{
  "type": "Feature",
  "properties": {
    "iso:country":"IT",
    "sg:address":"41049 Sassuolo",
    "sg:city":"Sassuolo",
    "sg:orig_category":"Arredo Cucina Ed Elettrodomestici",
    "sg:phone":"+39 0536 802131",
    "sg:postcode":"41049",
    "sg:province":"Modena",
    "wof:name":"Punto Inox (s.r.l.)",
    "wof:placetype":"venue"
},
  "geometry": {"coordinates":[10.801374,44.567097],"type":"Point"}
}