{
  "type": "Feature",
  "properties": {
    "iso:country":"IT",
    "sg:address":"57016 Rosignano Marittimo",
    "sg:city":"Rosignano Marittimo",
    "sg:classifiers":[
        {
            "category":"Manufacturing",
            "subcategory":"Tools & Machinery",
            "type":"Manufacturing & Wholesale Goods"
        }
    ],
    "sg:phone":"+39 0586 769711",
    "sg:postcode":"57016",
    "sg:province":"Livorno",
    "sg:tags":[
        "machining",
        "mechanical"
    ],
    "wof:name":"Siticem Montaggi E Manutenzioni Spa",
    "wof:placetype":"venue"
},
  "geometry": {"coordinates":[10.45645,43.390491],"type":"Point"}
}