{
  "type": "Feature",
  "properties": {
    "addr:full":"Via Roma 79; Ciminna; 90023 Ciminna Palermo 90023",
    "addr:housenumber":"79",
    "addr:postcode":"90023;90023",
    "addr:street":"Via Roma",
    "iso:country":"IT",
    "sg:address":"Via Roma 79; Ciminna; 90023",
    "sg:city":"Ciminna",
    "sg:classifiers":[
        {
            "category":"Banks & Credit Unions",
            "subcategory":"Bank",
            "type":"Services"
        }
    ],
    "sg:phone":"+39 091 820 4415",
    "sg:postcode":"90023",
    "sg:province":"Palermo",
    "wof:name":"Credito Emiliano Spa",
    "wof:placetype":"venue"
},
  "geometry": {"coordinates":[13.560554,37.897469],"type":"Point"}
}