{
  "type": "Feature",
  "properties": {
    "iso:country":"IT",
    "sg:address":"10152 Torino",
    "sg:city":"Torino",
    "sg:orig_category":"Tessuti Arredamento, Tende E Tappeti. Forniture Per Edilizia E Lavori Pubblici",
    "sg:phone":"+39 011 436 2966",
    "sg:postcode":"10152",
    "sg:province":"Torino",
    "wof:name":"Nord Parati",
    "wof:placetype":"venue"
},
  "geometry": {"coordinates":[7.673557,45.083538],"type":"Point"}
}