{
  "type": "Feature",
  "properties": {
    "addr:full":"25133 Brescia Brescia Brescia 25133",
    "addr:postcode":"25133;25133",
    "iso:country":"IT",
    "sg:address":"25133 Brescia",
    "sg:city":"Brescia",
    "sg:orig_category":"Macchine, Impianti Ed Attrezzature Per Abbigliamento E Pelletterie",
    "sg:phone":"+39 030 200 9742",
    "sg:postcode":"25133",
    "sg:province":"Brescia",
    "wof:name":"Ecoimpianti",
    "wof:placetype":"venue"
},
  "geometry": {"coordinates":[10.23481,45.565929],"type":"Point"}
}