{
  "type": "Feature",
  "properties": {
    "addr:full":"27, Via Morosini Don 56022 Castelfranco Di Sotto Castelfranco di Sotto Pisa 56022",
    "addr:postcode":"56022;56022",
    "addr:street":"Via Morosini Don;Di Sotto Pisa",
    "iso:country":"IT",
    "sg:address":"27, Via Morosini Don 56022 Castelfranco Di Sotto",
    "sg:city":"Castelfranco di Sotto",
    "sg:orig_category":"Miscellaneous Products",
    "sg:phone":"+39 0571 489176",
    "sg:postcode":"56022",
    "sg:province":"Pisa",
    "wof:name":"Tacchificio Giove S.n.c.",
    "wof:placetype":"venue"
},
  "geometry": {"coordinates":[10.3965845108,43.7161369324],"type":"Point"}
}