{
  "type": "Feature",
  "properties": {
    "iso:country":"IT",
    "sg:address":"10148 Torino",
    "sg:city":"Torino",
    "sg:orig_category":"Forniture Per Agricoltura E Zootecnia. Animali Domestici",
    "sg:phone":"+39 011 226 3854",
    "sg:postcode":"10148",
    "sg:province":"Torino",
    "wof:name":"Il Supermercato Degli Animali (s.n.c.)",
    "wof:placetype":"venue"
},
  "geometry": {"coordinates":[7.6611356735,45.1098556519],"type":"Point"}
}