{
  "type": "Feature",
  "properties": {
    "addr:full":"52, Via Argentina 86039 Termoli Termoli Campobasso 86039",
    "addr:postcode":"86039;86039",
    "addr:street":"Via Argentina",
    "iso:country":"IT",
    "sg:address":"52, Via Argentina 86039 Termoli",
    "sg:city":"Termoli",
    "sg:classifiers":[
        {
            "category":"Real Estate",
            "subcategory":"Architect",
            "type":"Services"
        }
    ],
    "sg:phone":"+39 0875 701862",
    "sg:postcode":"86039",
    "sg:province":"Campobasso",
    "sg:tags":[
        "textile",
        "clothing"
    ],
    "wof:name":"Gim S.r.l.",
    "wof:placetype":"venue"
},
  "geometry": {"coordinates":[14.983284,41.999672],"type":"Point"}
}