{
  "type": "Feature",
  "properties": {
    "addr:full":"1, Via Montecassino 20021 Bollate Bollate Milano 20021",
    "addr:postcode":"20021;20021",
    "addr:street":"Via Montecassino",
    "iso:country":"IT",
    "sg:address":"1, Via Montecassino 20021 Bollate",
    "sg:city":"Bollate",
    "sg:classifiers":[
        {
            "category":"Professional",
            "subcategory":"Engineering",
            "type":"Services"
        }
    ],
    "sg:phone":"+39 02 3820 0285",
    "sg:postcode":"20021",
    "sg:province":"Milano",
    "sg:tags":[
        "machine",
        "-",
        "mechanical"
    ],
    "wof:name":"Plastimpianti Srl",
    "wof:placetype":"venue"
},
  "geometry": {"coordinates":[9.110689,45.525291],"type":"Point"}
}