{
  "type": "Feature",
  "properties": {
    "addr:full":"00185 Roma Roma Roma 00185",
    "addr:postcode":"00185;00185",
    "iso:country":"IT",
    "sg:address":"00185 Roma",
    "sg:city":"Roma",
    "sg:orig_category":"Bigiotteria - Produzione E Ingrosso",
    "sg:phone":"+39 06 445 3334",
    "sg:postcode":"00185",
    "sg:province":"Roma",
    "wof:name":"Bangla Indian Italian House Snc",
    "wof:placetype":"venue"
},
  "geometry": {"coordinates":[12.501226,41.897285],"type":"Point"}
}