{
  "type": "Feature",
  "properties": {
    "addr:full":"00031 Artena Artena Roma 00031",
    "addr:postcode":"00031;roma 00031",
    "iso:country":"IT",
    "sg:address":"00031 Artena",
    "sg:city":"Artena",
    "sg:orig_category":"Forniture Per Agricoltura E Zootecnia. Prodotti Chimici Secondari",
    "sg:phone":"+39 06 951 6907",
    "sg:postcode":"00031",
    "sg:province":"Roma",
    "wof:name":"Valenzi Luca",
    "wof:placetype":"venue"
},
  "geometry": {"coordinates":[12.9358711243,41.7383270264],"type":"Point"}
}