{
  "type": "Feature",
  "properties": {
    "iso:country":"IT",
    "sg:address":"Ss Statale, 32 Ticinese 12 28040 Varallo Pombia",
    "sg:city":"Varallo Pombia",
    "sg:classifiers":[
        {
            "category":"Wholesale",
            "subcategory":"Chemicals & Plastics",
            "type":"Manufacturing & Wholesale Goods"
        }
    ],
    "sg:phone":"+39 0321 968000",
    "sg:postcode":"28040",
    "sg:province":"Novara",
    "sg:tags":[
        "acrylic",
        "yarn"
    ],
    "sg:website":"www.borgolon.it",
    "wof:name":"Borgolon Spa",
    "wof:placetype":"venue"
},
  "geometry": {"coordinates":[8.618671,45.445084],"type":"Point"}
}