{
  "type": "Feature",
  "properties": {
    "iso:country":"IT",
    "sg:address":"52048 Monte San Savino",
    "sg:city":"Monte San Savino",
    "sg:orig_category":"Accessori Dei Mezzi Di Trasporto",
    "sg:phone":"+39 0575 810209",
    "sg:postcode":"52048",
    "sg:province":"Arezzo",
    "wof:name":"Vamar (s.r.l.)",
    "wof:placetype":"venue"
},
  "geometry": {"coordinates":[11.8555,43.3685],"type":"Point"}
}