{
  "type": "Feature",
  "properties": {
    "iso:country":"IT",
    "sg:address":"08100 Nuoro",
    "sg:city":"Nuoro",
    "sg:orig_category":"Elettricita' Materiali - Ingrosso",
    "sg:phone":"+39 0784 201624",
    "sg:postcode":"08100",
    "sg:province":"Nuoro",
    "wof:name":"B.t.b. Forniture Ed Impianti Elettrici E Tecnologici Di Balloi N.",
    "wof:placetype":"venue"
},
  "geometry": {"coordinates":[9.300736,40.321114],"type":"Point"}
}