{
  "type": "Feature",
  "properties": {
    "iso:country":"IT",
    "sg:address":"06126 Perugia",
    "sg:city":"Perugia",
    "sg:orig_category":"Carta Da Parati - Vendita Al Dettaglio",
    "sg:phone":"+39 075 30619",
    "sg:postcode":"06126",
    "sg:province":"Perugia",
    "wof:name":"Dielle Parati Di Discepoli Luigi",
    "wof:placetype":"venue"
},
  "geometry": {"coordinates":[12.365648,42.866741],"type":"Point"}
}