{
  "type": "Feature",
  "properties": {
    "iso:country":"IT",
    "sg:address":"70014 Conversano",
    "sg:city":"Conversano",
    "sg:orig_category":"Musica",
    "sg:phone":"+39 080 495 2245",
    "sg:postcode":"70014",
    "sg:province":"Bari",
    "wof:name":"Musicanova - Strumenti Musicali",
    "wof:placetype":"venue"
},
  "geometry": {"coordinates":[16.8715896606,41.0044250488],"type":"Point"}
}