{
  "type": "Feature",
  "properties": {
    "addr:full":"25070 Sabbio Chiese Sabbio Chiese Brescia 25070",
    "addr:postcode":"25070;25070",
    "addr:street":"Chiese",
    "iso:country":"IT",
    "sg:address":"25070 Sabbio Chiese",
    "sg:city":"Sabbio Chiese",
    "sg:orig_category":"Trattamenti Termici E Superficiali Metalli, Galvanotecnica",
    "sg:phone":"+39 036 582 6281",
    "sg:postcode":"25070",
    "sg:province":"Brescia",
    "wof:name":"Pulimetal Snc Di Caini E Carli",
    "wof:placetype":"venue"
},
  "geometry": {"coordinates":[10.430076,45.648781],"type":"Point"}
}