{
  "type": "Feature",
  "properties": {
    "iso:country":"IT",
    "sg:address":"Via G. Carducci, 43; Gioia Del Colle; 70023",
    "sg:city":"Gioia del Colle",
    "sg:classifiers":[
        {
            "category":"Banks & Credit Unions",
            "subcategory":"Bank",
            "type":"Services"
        }
    ],
    "sg:phone":"+39 080 830401",
    "sg:postcode":"70023",
    "sg:province":"Bari",
    "wof:name":"Cassa Di Risparmio Di Puglia",
    "wof:placetype":"venue"
},
  "geometry": {"coordinates":[16.918726,40.795219],"type":"Point"}
}