{
  "type": "Feature",
  "properties": {
    "iso:country":"IT",
    "sg:address":"20149 Milano",
    "sg:city":"Milano",
    "sg:orig_category":"Riparazione Dei Mezzi Di Trasporto",
    "sg:phone":"+39 02 481 3221",
    "sg:postcode":"20149",
    "sg:province":"Milano",
    "sg:website":"http://www.driver.it",
    "wof:name":"Fratelli Civeni Di G. & C. Civeni Snc",
    "wof:placetype":"venue"
},
  "geometry": {"coordinates":[9.151852,45.470688],"type":"Point"}
}