{
  "type": "Feature",
  "properties": {
    "iso:country":"IT",
    "sg:address":"63034 Montalto Delle Marche",
    "sg:city":"Montalto delle Marche",
    "sg:orig_category":"Manufacturers: Prefabbricati",
    "sg:phone":"+39 0736 828707",
    "sg:postcode":"63034",
    "sg:province":"Ascoli Piceno",
    "wof:name":"Impresa Edile Felici Marcello",
    "wof:placetype":"venue"
},
  "geometry": {"coordinates":[13.612295,42.99213],"type":"Point"}
}