{
  "type": "Feature",
  "properties": {
    "iso:country":"IT",
    "sg:address":"26100 Cremona",
    "sg:city":"Cremona",
    "sg:orig_category":"Telecomunicazioni E Telefonia, Impianti, Apparecchi E Servizi",
    "sg:phone":"+39 0372 457797",
    "sg:postcode":"26100",
    "sg:province":"Cremona",
    "sg:website":"http://www.paginegialle.it/microtelcr",
    "wof:name":"Microtel Srl",
    "wof:placetype":"venue"
},
  "geometry": {"coordinates":[10.03255,45.140419],"type":"Point"}
}