{
  "type": "Feature",
  "properties": {
    "addr:full":"40069 Zola Predosa Zola Bologna 40069",
    "addr:postcode":"40069;40069",
    "iso:country":"IT",
    "sg:address":"40069 Zola Predosa",
    "sg:city":"Zola",
    "sg:orig_category":"Prodotti Chimici Secondari. Macchine E Forniture Per Ecologia E Smaltimento Rifiuti. Forniture Per Attivita' Industriali",
    "sg:phone":"+39 051 780649",
    "sg:postcode":"40069",
    "sg:province":"Bologna",
    "wof:name":"Compreur Srl",
    "wof:placetype":"venue"
},
  "geometry": {"coordinates":[11.233250618,44.505443573],"type":"Point"}
}