{
  "type": "Feature",
  "properties": {
    "addr:full":"8, Via Cernuschi Enrico 00152 Roma Roma Roma 00152",
    "addr:postcode":"00152;00152",
    "addr:street":"Via Cernuschi Enrico",
    "iso:country":"IT",
    "sg:address":"8, Via Cernuschi Enrico 00152 Roma",
    "sg:city":"Roma",
    "sg:classifiers":[
        {
            "category":"Professional",
            "subcategory":"Printing & Photocopies",
            "type":"Services"
        }
    ],
    "sg:phone":"+39 39065803823",
    "sg:postcode":"00152",
    "sg:province":"Roma",
    "wof:name":"Elettricart Srl",
    "wof:placetype":"venue"
},
  "geometry": {"coordinates":[12.4823246002,41.8954658508],"type":"Point"}
}