{
  "type": "Feature",
  "properties": {
    "iso:country":"IT",
    "sg:address":"Viale E. Mattei 6 60013 Corinaldo",
    "sg:city":"Corinaldo",
    "sg:classifiers":[
        {
            "category":"Communications",
            "subcategory":"Film & Video Production",
            "type":"Services"
        }
    ],
    "sg:phone":"+39 071 67778",
    "sg:postcode":"60013",
    "sg:province":"Ancona",
    "sg:tags":[
        "decorative",
        "mirror"
    ],
    "wof:name":"S.a.r.a. Di Sbrollini, Riccardi, Savelli, Tarsi Snc",
    "wof:placetype":"venue"
},
  "geometry": {"coordinates":[13.518757,43.615856],"type":"Point"}
}