{
  "type": "Feature",
  "properties": {
    "iso:country":"IT",
    "sg:address":"16014 Campomorone",
    "sg:city":"Campomorone",
    "sg:orig_category":"Servizi E Lavori Per Arredamento E Industria Del Legno. Forniture Per Congressi, Fiere E Manifestazioni. Servizi Per Aziende, Manifestazioni E Supporto Agli Scambi Commerciali",
    "sg:phone":"+39 010 726 1383",
    "sg:postcode":"16014",
    "sg:province":"Genova",
    "wof:name":"Casassa Amanda",
    "wof:placetype":"venue"
},
  "geometry": {"coordinates":[8.88448,44.510258],"type":"Point"}
}