{
  "type": "Feature",
  "properties": {
    "addr:full":"64010 Colonnella Colonnella Teramo 64010",
    "addr:postcode":"64010;64010",
    "iso:country":"IT",
    "sg:address":"64010 Colonnella",
    "sg:city":"Colonnella",
    "sg:orig_category":"Cartotecnica E Servizi. Forniture Per Attivita' Commerciali Ed Artigianali",
    "sg:phone":"+39 0861 749562",
    "sg:postcode":"64010",
    "sg:province":"Teramo",
    "wof:name":"Admiral (s.r.l.)",
    "wof:placetype":"venue"
},
  "geometry": {"coordinates":[13.631888,42.600018],"type":"Point"}
}