{
  "type": "Feature",
  "properties": {
    "iso:country":"IT",
    "sg:address":"81100 Caserta",
    "sg:city":"Caserta",
    "sg:orig_category":"Vigilanza E Sorveglianza",
    "sg:phone":"+39 0823 213501",
    "sg:postcode":"81100",
    "sg:province":"Caserta",
    "wof:name":"Istituto Di Vigilanza Soc.coop.r.l. Lavoro E Giustizia",
    "wof:placetype":"venue"
},
  "geometry": {"coordinates":[14.326861,41.068069],"type":"Point"}
}