{
  "type": "Feature",
  "properties": {
    "addr:full":"76, Via Verdi Giuseppe 85024 Lavello Lavello Potenza 85024",
    "addr:postcode":"85024;85024",
    "addr:street":"Via Verdi Giuseppe",
    "iso:country":"IT",
    "sg:address":"76, Via Verdi Giuseppe 85024 Lavello",
    "sg:city":"Lavello",
    "sg:classifiers":[
        {
            "category":"Shopping",
            "subcategory":"Stationery & Office Supplies",
            "type":"Retail Goods"
        }
    ],
    "sg:phone":"+39 39097288730",
    "sg:postcode":"85024",
    "sg:province":"Potenza",
    "sg:tags":[
        "professional"
    ],
    "wof:name":"Novimatic F.lli Napoli S.r.l.",
    "wof:placetype":"venue"
},
  "geometry": {"coordinates":[15.8022212982,40.6372413635],"type":"Point"}
}