{
  "type": "Feature",
  "properties": {
    "iso:country":"IT",
    "sg:address":"35139 Padova",
    "sg:city":"Padova",
    "sg:orig_category":"Accessori Moda D'abbigliamento. Shopping",
    "sg:phone":"+39 049 654173",
    "sg:postcode":"35139",
    "sg:province":"Padova",
    "wof:name":"Cappelleria Modisteria Callegaro & Doriguzzi",
    "wof:placetype":"venue"
},
  "geometry": {"coordinates":[11.865569,45.322815],"type":"Point"}
}