{
  "type": "Feature",
  "properties": {
    "addr:full":"56, Via Dell' Artigianato 40050 Monte San Pietro Monte San Pietro Bologna 40050",
    "addr:postcode":"40050;40050",
    "addr:street":"Via Dell ' Artigianato",
    "iso:country":"IT",
    "sg:address":"56, Via Dell' Artigianato 40050 Monte San Pietro",
    "sg:city":"Monte San Pietro",
    "sg:classifiers":[
        {
            "category":"Bars & Pubs",
            "subcategory":"Nightclub",
            "type":"Food & Drink"
        }
    ],
    "sg:phone":"+39 051 676 1508",
    "sg:postcode":"40050",
    "sg:province":"Bologna",
    "sg:tags":[
        "cake",
        "bread"
    ],
    "wof:name":"Cavallari Giorgio & S.n.c.",
    "wof:placetype":"venue"
},
  "geometry": {"coordinates":[11.077356,44.440647],"type":"Point"}
}