{
  "type": "Feature",
  "properties": {
    "iso:country":"IT",
    "sg:address":"20132 Milano",
    "sg:city":"Milano",
    "sg:orig_category":"Macchine E Forniture Per Ecologia E Smaltimento Rifiuti",
    "sg:phone":"+39 02 282 7968",
    "sg:postcode":"20132",
    "sg:province":"Milano",
    "sg:website":"http://www.nobel-ita.it",
    "wof:name":"Nobel Srl",
    "wof:placetype":"venue"
},
  "geometry": {"coordinates":[9.238062,45.492039],"type":"Point"}
}