{
  "type": "Feature",
  "properties": {
    "addr:full":"95100 Catania CT",
    "addr:postcode":"95100",
    "iso:country":"IT",
    "sg:address":"95100 Catania",
    "sg:orig_category":"Disinfezione, Disinfestazione E Derattizzazione",
    "sg:phone":"+39 095 753 0511",
    "sg:province":"CT",
    "sg:website":"http://www.cataniamultiservizi.it",
    "wof:name":"Catania Multiservizi Spa",
    "wof:placetype":"venue"
},
  "geometry": {"coordinates":[15.109275,37.52224],"type":"Point"}
}