{
  "type": "Feature",
  "properties": {
    "iso:country":"IT",
    "sg:address":"24060 Bagnatica",
    "sg:city":"Bagnatica",
    "sg:orig_category":"Macchine Ed Impianti Per Edilizia E Lavori Pubblici. Apparecchiature E Sistemi Per Magazzinaggio E Movimentazione",
    "sg:phone":"+39 035 684041",
    "sg:postcode":"24060",
    "sg:province":"Bergamo",
    "sg:website":"http://www.instantitalia.it",
    "wof:name":"Nuova Instant Italia Srl",
    "wof:placetype":"venue"
},
  "geometry": {"coordinates":[9.802351,45.675644],"type":"Point"}
}