{
  "type": "Feature",
  "properties": {
    "addr:full":"25068 Sarezzo Sarezzo Brescia 25068",
    "addr:postcode":"25068;25068",
    "iso:country":"IT",
    "sg:address":"25068 Sarezzo",
    "sg:city":"Sarezzo",
    "sg:orig_category":"Servizi E Lavori Per Arredamento E Industria Del Legno. Servizi E Lavori Per Edilizia E Lavori Pubblici",
    "sg:postcode":"25068",
    "sg:province":"Brescia",
    "wof:name":"Tanghetti Fratelli Di Tanghetti Mario E C. S.n.c.",
    "wof:placetype":"venue"
},
  "geometry": {"coordinates":[10.158604,45.668774],"type":"Point"}
}