{
  "type": "Feature",
  "properties": {
    "addr:full":"70018 Rutigliano Rutigliano Bari 70018",
    "addr:postcode":"70018;70018",
    "iso:country":"IT",
    "sg:address":"70018 Rutigliano",
    "sg:city":"Rutigliano",
    "sg:orig_category":"Forniture Per Agricoltura E Zootecnia. Prodotti Chimici Secondari. Macchine E Forniture Per Ecologia E Smaltimento Rifiuti",
    "sg:phone":"+39 080 476 2511",
    "sg:postcode":"70018",
    "sg:province":"Bari",
    "wof:name":"Enoagricola (s.r.l.)",
    "wof:placetype":"venue"
},
  "geometry": {"coordinates":[17.0100803375,41.0080451965],"type":"Point"}
}