{
  "type": "Feature",
  "properties": {
    "addr:full":"8 Viale Matteotti Giacomo, 62012 Civitanova Marche Civitanova Marche Macerata 62012",
    "addr:postcode":"62012;62012",
    "addr:street":"Viale Matteotti Giacomo",
    "iso:country":"IT",
    "sg:address":"8 Viale Matteotti Giacomo, 62012 Civitanova Marche",
    "sg:city":"Civitanova Marche",
    "sg:classifiers":[
        {
            "category":"Banks & Credit Unions",
            "subcategory":"Financial Services",
            "type":"Services"
        }
    ],
    "sg:phone":"+39 390 733 8211",
    "sg:postcode":"62012",
    "sg:province":"Macerata",
    "sg:tags":[
        "banking",
        "finance",
        "insurance"
    ],
    "wof:name":"Banca Di Credito Cooperativo Di Civitanova Marche E Montecosaro",
    "wof:placetype":"venue"
},
  "geometry": {"coordinates":[13.4562616348,43.3007469177],"type":"Point"}
}