{
  "type": "Feature",
  "properties": {
    "iso:country":"IT",
    "sg:address":"21040 Gerenzano",
    "sg:city":"Gerenzano",
    "sg:orig_category":"Automazione E Macchine Per Ufficio. Servizi Ausiliari Di Certificati, Riproduzioni, Disegni E Foto",
    "sg:phone":"+39 02 9648 9114",
    "sg:postcode":"21040",
    "sg:province":"Varese",
    "wof:name":"Dueci S.r.l.",
    "wof:placetype":"venue"
},
  "geometry": {"coordinates":[9.026896,45.621475],"type":"Point"}
}