{
  "type": "Feature",
  "properties": {
    "addr:full":"Via Roma, 38; Torre S. Susanna; 72028 Brindisi 72028",
    "addr:housenumber":"38",
    "addr:postcode":"72028;72028",
    "addr:street":"Via Roma;Susanna",
    "iso:country":"IT",
    "sg:address":"Via Roma, 38; Torre S. Susanna; 72028",
    "sg:classifiers":[
        {
            "category":"Banks & Credit Unions",
            "subcategory":"Bank",
            "type":"Services"
        }
    ],
    "sg:phone":"+39 0831 746083",
    "sg:postcode":"72028",
    "sg:province":"Brindisi",
    "wof:name":"Cassa Di Risparmio Di Puglia",
    "wof:placetype":"venue"
},
  "geometry": {"coordinates":[17.738512,40.464054],"type":"Point"}
}