{
  "type": "Feature",
  "properties": {
    "addr:full":"58100 Grosseto Grosseto Grosseto 58100",
    "addr:postcode":"58100;58100",
    "iso:country":"IT",
    "sg:address":"58100 Grosseto",
    "sg:city":"Grosseto",
    "sg:orig_category":"Arredamento Alberghi",
    "sg:phone":"+39 0564 451693",
    "sg:postcode":"58100",
    "sg:province":"Grosseto",
    "wof:name":"Eurobieffe Srl",
    "wof:placetype":"venue"
},
  "geometry": {"coordinates":[11.097462,42.786148],"type":"Point"}
}