{
  "type": "Feature",
  "properties": {
    "addr:full":"24122 Bergamo Bergamo Bergamo 24122",
    "addr:postcode":"24122;24122",
    "iso:country":"IT",
    "sg:address":"24122 Bergamo",
    "sg:city":"Bergamo",
    "sg:orig_category":"Scuole Di Lingue",
    "sg:phone":"+39 035 218436",
    "sg:postcode":"24122",
    "sg:province":"Bergamo",
    "sg:website":"http://www.centroscolastico.it",
    "wof:name":"Centro Scolastico Bergamo",
    "wof:placetype":"venue"
},
  "geometry": {"coordinates":[9.6659288406,45.6880226135],"type":"Point"}
}