{
  "type": "Feature",
  "properties": {
    "iso:country":"IT",
    "sg:address":"Via Mussa, 21/12 35017 Piombino Dese",
    "sg:city":"Piombino Dese",
    "sg:classifiers":[
        {
            "category":"Banks & Credit Unions",
            "subcategory":"Investment Brokerage",
            "type":"Services"
        }
    ],
    "sg:phone":"+39 049 936 5770",
    "sg:postcode":"35017",
    "sg:province":"Padova",
    "sg:tags":[
        "lamp",
        "chain"
    ],
    "wof:name":"B 4 Srl",
    "wof:placetype":"venue"
},
  "geometry": {"coordinates":[11.986629,45.614914],"type":"Point"}
}