{
  "type": "Feature",
  "properties": {
    "iso:country":"IT",
    "sg:address":"25073 Bovezzo",
    "sg:city":"Bovezzo",
    "sg:orig_category":"Macchine Utensili E Impianti",
    "sg:phone":"+39 030 211 6048",
    "sg:postcode":"25073",
    "sg:province":"Brescia",
    "wof:name":"Fond Forniture Di Marelli Franco",
    "wof:placetype":"venue"
},
  "geometry": {"coordinates":[10.236306,45.594505],"type":"Point"}
}