{
  "type": "Feature",
  "properties": {
    "iso:country":"IT",
    "sg:address":"11, Via Meolde 35017 Piombino Dese",
    "sg:city":"Piombino Dese",
    "sg:classifiers":[
        {
            "category":"Shopping",
            "subcategory":"Computers & Home Electronics",
            "type":"Retail Goods"
        }
    ],
    "sg:phone":"+39 049 936 6697",
    "sg:postcode":"35017",
    "sg:province":"Padova",
    "sg:tags":[
        "electronic",
        "electrical",
        "equipment"
    ],
    "wof:name":"Nuova L.v. Di Fardin Squizzato E C. S.n.c.",
    "wof:placetype":"venue"
},
  "geometry": {"coordinates":[12.002414,45.60936],"type":"Point"}
}