{
  "type": "Feature",
  "properties": {
    "iso:country":"IT",
    "sg:address":"6, Via Monte Cervino 20149 Milano",
    "sg:city":"Milano",
    "sg:classifiers":[
        {
            "category":"Shopping",
            "subcategory":"Gifts & Souvenirs",
            "type":"Retail Goods"
        }
    ],
    "sg:phone":"+39 02 4801 3848",
    "sg:postcode":"20149",
    "sg:province":"Milano",
    "wof:name":"C R F S.r.l.",
    "wof:placetype":"venue"
},
  "geometry": {"coordinates":[9.149873,45.475868],"type":"Point"}
}