{
  "type": "Feature",
  "properties": {
    "iso:country":"IT",
    "sg:address":"86039 Termoli",
    "sg:city":"Termoli",
    "sg:orig_category":"Abbigliamento Esterno, Maglierie E Pelliccerie",
    "sg:phone":"+39 0875 83443",
    "sg:postcode":"86039",
    "sg:province":"Campobasso",
    "wof:name":"C.s.m. Cofezioni Sacre Molise Di Aquilano L.f. & S.",
    "wof:placetype":"venue"
},
  "geometry": {"coordinates":[14.982094,42.00029],"type":"Point"}
}