{
  "type": "Feature",
  "properties": {
    "iso:country":"IT",
    "sg:address":"02100 Rieti",
    "sg:city":"Rieti",
    "sg:orig_category":"Studi E Consulenze Amministrative, Commerciali E Aziendali. Studi E Consulenze Tecniche E Industriali. Consulenze Tecniche, Amministrative E Perizie",
    "sg:phone":"+39 0746 483999",
    "sg:postcode":"02100",
    "sg:province":"Rieti",
    "wof:name":"Biolab - Pic. Soc. Coop. Arl",
    "wof:placetype":"venue"
},
  "geometry": {"coordinates":[12.855318,42.400013],"type":"Point"}
}