{
  "type": "Feature",
  "properties": {
    "iso:country":"IT",
    "sg:address":"24126 Bergamo",
    "sg:city":"Bergamo",
    "sg:orig_category":"Tempo Libero - Articoli E Forniture. Forniture Per Congressi, Fiere E Manifestazioni. Regalistica Aziendale",
    "sg:phone":"+39 035 313257",
    "sg:postcode":"24126",
    "sg:province":"Bergamo",
    "wof:name":"Bianchetti Addobbi Allestimenti Snc",
    "wof:placetype":"venue"
},
  "geometry": {"coordinates":[9.656981,45.673267],"type":"Point"}
}