{
  "type": "Feature",
  "properties": {
    "iso:country":"IT",
    "sg:address":"20070 Dresano",
    "sg:city":"Dresano",
    "sg:orig_category":"Imprese Di Costruzioni Civili Ed Industriali",
    "sg:phone":"+39 02 981 3299",
    "sg:postcode":"20070",
    "sg:province":"Milano",
    "wof:name":"Las Finiture D'interni Sas",
    "wof:placetype":"venue"
},
  "geometry": {"coordinates":[9.005108,45.485126],"type":"Point"}
}