{
  "type": "Feature",
  "properties": {
    "iso:country":"IT",
    "sg:address":"00143 Roma",
    "sg:city":"Roma",
    "sg:orig_category":"Macchine E Forniture Per Arredamento E Industria Del Legno. Forniture Per Edilizia E Lavori Pubblici",
    "sg:phone":"+39 06 501 1500",
    "sg:postcode":"00143",
    "sg:province":"Roma",
    "wof:name":"M.&c. Arredamenti",
    "wof:placetype":"venue"
},
  "geometry": {"coordinates":[12.480967,41.809853],"type":"Point"}
}