{
  "type": "Feature",
  "properties": {
    "iso:country":"IT",
    "sg:address":"00186 Roma",
    "sg:city":"Roma",
    "sg:orig_category":"Abbigliamento Esterno, Maglierie E Pelliccerie. Shopping",
    "sg:phone":"+39 06 686 7670",
    "sg:postcode":"00186",
    "sg:province":"Roma",
    "wof:name":"Baulla' Di Gerbasio Teresa",
    "wof:placetype":"venue"
},
  "geometry": {"coordinates":[12.471581,41.895435],"type":"Point"}
}