{
  "type": "Feature",
  "properties": {
    "addr:full":"55041 Camaiore Camaiore Lucca 55041",
    "addr:postcode":"55041;55041",
    "iso:country":"IT",
    "sg:address":"55041 Camaiore",
    "sg:city":"Camaiore",
    "sg:orig_category":"Prodotti E Manufatti In Materie Plastiche. Forniture Per Attivita' Industriali",
    "sg:phone":"+39 0584 969533",
    "sg:postcode":"55041",
    "sg:province":"Lucca",
    "sg:website":"http://www.reteitalia.it",
    "wof:name":"Versilglas",
    "wof:placetype":"venue"
},
  "geometry": {"coordinates":[10.258890152,43.9065704346],"type":"Point"}
}