{
  "type": "Feature",
  "properties": {
    "addr:full":"20050 Macherio Macherio Milano 20050",
    "addr:postcode":"20050;20050",
    "iso:country":"IT",
    "sg:address":"20050 Macherio",
    "sg:city":"Macherio",
    "sg:orig_category":"Motori Ed Organi Di Trasmissione",
    "sg:phone":"+39 039 201 2046",
    "sg:postcode":"20050",
    "sg:province":"Milano",
    "wof:name":"Fabbrica Catene A Rullo F.lli Fossati Spa",
    "wof:placetype":"venue"
},
  "geometry": {"coordinates":[9.0722637177,45.4190597534],"type":"Point"}
}