{
  "type": "Feature",
  "properties": {
    "iso:country":"IT",
    "sg:address":"24059 Urgnano",
    "sg:city":"Urgnano",
    "sg:classifiers":[
        {
            "category":"Shopping",
            "subcategory":"Bicycles & Sporting Goods",
            "type":"Retail Goods"
        }
    ],
    "sg:phone":"+39 035 891031",
    "sg:postcode":"24059",
    "sg:province":"Bergamo",
    "sg:tags":[
        "e",
        "sport",
        "-",
        "forniture",
        "articoli"
    ],
    "sg:website":"http://www.centro-scarpa.com",
    "wof:name":"Centro Scarpa Urgnano Srl",
    "wof:placetype":"venue"
},
  "geometry": {"coordinates":[9.705009,45.583714],"type":"Point"}
}