{
  "type": "Feature",
  "properties": {
    "iso:country":"IT",
    "sg:address":"70052 Bisceglie",
    "sg:city":"Bisceglie",
    "sg:orig_category":"Autogru - Costruzione E Commercio",
    "sg:phone":"+39 080 392 4003",
    "sg:postcode":"70052",
    "sg:province":"Bari",
    "wof:name":"Euro Rent & Trade Sas",
    "wof:placetype":"venue"
},
  "geometry": {"coordinates":[16.475925,41.210072],"type":"Point"}
}