{
  "type": "Feature",
  "properties": {
    "iso:country":"IT",
    "sg:address":"26100 Cremona",
    "sg:city":"Cremona",
    "sg:orig_category":"Forniture Per Edilizia E Lavori Pubblici",
    "sg:phone":"+39 0372 453366",
    "sg:postcode":"26100",
    "sg:province":"Cremona",
    "sg:website":"http://www.saradini.com",
    "wof:name":"Saradini Spa",
    "wof:placetype":"venue"
},
  "geometry": {"coordinates":[10.0325498581,45.1404190063],"type":"Point"}
}