{
  "type": "Feature",
  "properties": {
    "addr:full":"Via Della Palazzina 45 15100 Alessandria Alessandria Alessandria 15100",
    "addr:housenumber":"45",
    "addr:postcode":"15100;15100",
    "addr:street":"Via Della Palazzina",
    "iso:country":"IT",
    "sg:address":"Via Della Palazzina 45 15100 Alessandria",
    "sg:city":"Alessandria",
    "sg:classifiers":[
        {
            "category":"Shopping",
            "subcategory":"Clothing, Apparel, & Fashions",
            "type":"Retail Goods"
        }
    ],
    "sg:phone":"+39 0131 343987",
    "sg:postcode":"15100",
    "sg:province":"Alessandria",
    "sg:tags":[
        "knitted",
        "knitwear",
        "clothes"
    ],
    "wof:name":"Les Tricots De Francoise",
    "wof:placetype":"venue"
},
  "geometry": {"coordinates":[8.588447,44.898006],"type":"Point"}
}