{
  "type": "Feature",
  "properties": {
    "iso:country":"IT",
    "sg:address":"20082 Binasco",
    "sg:city":"Binasco",
    "sg:orig_category":"Caffe' Crudo E Torrefatto",
    "sg:phone":"+39 02 905 2330",
    "sg:postcode":"20082",
    "sg:province":"Milano",
    "sg:website":"http://www.caffe-bonomi.it",
    "wof:name":"Bonomi Spa",
    "wof:placetype":"venue"
},
  "geometry": {"coordinates":[9.088425,45.334454],"type":"Point"}
}