{
  "type": "Feature",
  "properties": {
    "iso:country":"IT",
    "sg:address":"38100 Trento",
    "sg:city":"Cognola",
    "sg:orig_category":"Elettrotecnica Industriale, Prodotti E Apparecchiature. Elettrotecnica Professionale E Di Consumo",
    "sg:phone":"+39 335 807 8985",
    "sg:postcode":"38100",
    "sg:province":"Trento",
    "wof:name":"Elman Srl",
    "wof:placetype":"venue"
},
  "geometry": {"coordinates":[11.141944,46.076389],"type":"Point"}
}