{
  "type": "Feature",
  "properties": {
    "iso:country":"IT",
    "sg:address":"3, Via S. Francesco D'assisi 20063 Cernusco Sul Naviglio",
    "sg:city":"Cernusco sul Naviglio",
    "sg:classifiers":[
        {
            "category":"Utilities",
            "subcategory":"Electric",
            "type":"Services"
        }
    ],
    "sg:phone":"+39 02 9210 6776",
    "sg:postcode":"20063",
    "sg:province":"Milano",
    "sg:tags":[
        "energy"
    ],
    "wof:name":"Edigas Esercizio Distribuzione Gas S.r.l.",
    "wof:placetype":"venue"
},
  "geometry": {"coordinates":[9.188141,45.463688],"type":"Point"}
}