{
  "type": "Feature",
  "properties": {
    "addr:full":"11020 Gressan Gressan Aosta 11020",
    "addr:postcode":"11020;11020",
    "iso:country":"IT",
    "sg:address":"11020 Gressan",
    "sg:city":"Gressan",
    "sg:classifiers":[
        {
            "category":"Bars & Pubs",
            "subcategory":"Champagne Bar",
            "type":"Food & Drink"
        }
    ],
    "sg:phone":"+39 335 524 816",
    "sg:postcode":"11020",
    "sg:province":"Aosta",
    "sg:tags":[
        "caffe'",
        "e"
    ],
    "wof:name":"Bar Rifugo Chamol\u00c9",
    "wof:placetype":"venue"
},
  "geometry": {"coordinates":[7.309653,45.685692],"type":"Point"}
}