{
  "type": "Feature",
  "properties": {
    "iso:country":"IT",
    "sg:address":"36100 Vicenza",
    "sg:city":"Vicenza",
    "sg:orig_category":"Ammortizzatori",
    "sg:phone":"+39 0444 563855",
    "sg:postcode":"36100",
    "sg:province":"Vicenza",
    "wof:name":"Autoaccessorio Srl",
    "wof:placetype":"venue"
},
  "geometry": {"coordinates":[11.561045,45.53619],"type":"Point"}
}