{
  "type": "Feature",
  "properties": {
    "addr:full":"25040 Malonno Malonno Brescia 25040",
    "addr:postcode":"25040;25040",
    "iso:country":"IT",
    "sg:address":"25040 Malonno",
    "sg:city":"Malonno",
    "sg:orig_category":"Autolinee",
    "sg:phone":"+39 036 463 5583",
    "sg:postcode":"25040",
    "sg:province":"Brescia",
    "wof:name":"Autoservizi Gelmi Sergio & C. Snc",
    "wof:placetype":"venue"
},
  "geometry": {"coordinates":[10.31772,46.121536],"type":"Point"}
}