{
  "type": "Feature",
  "properties": {
    "iso:country":"IT",
    "sg:address":"40122 Bologna",
    "sg:city":"Bologna",
    "sg:orig_category":"Non-classified Establishments",
    "sg:phone":"+39 051 648 6464",
    "sg:postcode":"40122",
    "sg:province":"Bologna",
    "wof:name":"Ugierre Di Ugelmo Giliola",
    "wof:placetype":"venue"
},
  "geometry": {"coordinates":[11.334844,44.496265],"type":"Point"}
}