{
  "type": "Feature",
  "properties": {
    "iso:country":"IT",
    "sg:address":"46010 Curtatone",
    "sg:city":"Curtatone",
    "sg:orig_category":"Forniture Per Agricoltura E Zootecnia",
    "sg:phone":"+39 0376 290104",
    "sg:postcode":"46010",
    "sg:province":"Mantova",
    "wof:name":"Tognazzoni Snc Di Andrea E Alessandro Tognazzoni",
    "wof:placetype":"venue"
},
  "geometry": {"coordinates":[10.7736959457,45.1290168762],"type":"Point"}
}