{
  "type": "Feature",
  "properties": {
    "iso:country":"IT",
    "sg:address":"20123 Milano",
    "sg:city":"Milano",
    "sg:orig_category":"Abbigliamento Esterno, Maglierie E Pelliccerie. Shopping",
    "sg:phone":"+39 02 875500",
    "sg:postcode":"20123",
    "sg:province":"Milano",
    "wof:name":"Nerella Di Faccini Nerella",
    "wof:placetype":"venue"
},
  "geometry": {"coordinates":[9.188869,45.461418],"type":"Point"}
}