{
  "type": "Feature",
  "properties": {
    "iso:country":"IT",
    "sg:address":"22100 Como",
    "sg:city":"Como",
    "sg:classifiers":[
        {
            "category":"Sports & Exercise",
            "subcategory":"Tennis Court",
            "type":"Entertainment"
        }
    ],
    "sg:phone":"+39 031 526404",
    "sg:postcode":"22100",
    "sg:province":"Como",
    "sg:tags":[
        "e",
        "lo",
        "tempo",
        "libero",
        "per",
        "impianti",
        "il",
        "attrezzature"
    ],
    "sg:website":"http://www.venelli.com",
    "wof:name":"Venelli Srl",
    "wof:placetype":"venue"
},
  "geometry": {"coordinates":[9.075348,45.780655],"type":"Point"}
}