{
  "type": "Feature",
  "properties": {
    "addr:full":"33080 Barcis Barcis Pordenone 33080",
    "addr:postcode":"33080;33080",
    "iso:country":"IT",
    "sg:address":"33080 Barcis",
    "sg:city":"Barcis",
    "sg:orig_category":"Pubblica Amministrazione",
    "sg:phone":"+39 0427 764419",
    "sg:postcode":"33080",
    "sg:province":"Pordenone",
    "wof:name":"Comunita' Montana Meduna Cellina",
    "wof:placetype":"venue"
},
  "geometry": {"coordinates":[12.5602083206,46.1914405823],"type":"Point"}
}