{
  "type": "Feature",
  "properties": {
    "iso:country":"IT",
    "sg:address":"34, Via Copernico 44012 Bondeno",
    "sg:city":"Bondeno",
    "sg:classifiers":[
        {
            "category":"Professional",
            "subcategory":"Engineering",
            "type":"Services"
        }
    ],
    "sg:phone":"+39 0532 896232",
    "sg:postcode":"44012",
    "sg:province":"Ferrara",
    "sg:tags":[
        "machine",
        "-",
        "mechanical"
    ],
    "wof:name":"P.c.m.g. Di Grassilli Giancarlo & C Sas",
    "wof:placetype":"venue"
},
  "geometry": {"coordinates":[11.395471,44.93005],"type":"Point"}
}