{
  "type": "Feature",
  "properties": {
    "iso:country":"IT",
    "sg:address":"V.le Dell' Industria 7 20010 Pregnana Milanese",
    "sg:city":"Pregnana Milanese",
    "sg:classifiers":[
        {
            "category":"Building & Trades",
            "subcategory":"Cleaning & Sanitation",
            "type":"Services"
        }
    ],
    "sg:phone":"+39 02 939651",
    "sg:postcode":"20010",
    "sg:province":"Milano",
    "sg:tags":[
        "closure",
        "pharmaceutical",
        "aluminium",
        "industry"
    ],
    "sg:website":"www.helvoetpharma.it",
    "wof:name":"Helvoet Pharma Belgium Nv",
    "wof:placetype":"venue"
},
  "geometry": {"coordinates":[9.007014,45.521526],"type":"Point"}
}