{
  "type": "Feature",
  "properties": {
    "addr:full":"21011 Casorate Sempione Casorate Sempione Varese 21011",
    "addr:postcode":"21011;21011",
    "iso:country":"IT",
    "sg:address":"21011 Casorate Sempione",
    "sg:city":"Casorate Sempione",
    "sg:orig_category":"Forniture Alle Strutture Ricettive. Macchine E Impianti Per Attivita' Commerciali Ed Artigianali",
    "sg:phone":"+39 0331 295269",
    "sg:postcode":"21011",
    "sg:province":"Varese",
    "wof:name":"Victoria Arduino (s.r.l.)",
    "wof:placetype":"venue"
},
  "geometry": {"coordinates":[8.7363204956,45.6724700928],"type":"Point"}
}