{
  "type": "Feature",
  "properties": {
    "iso:country":"IT",
    "sg:address":"84018 Scafati",
    "sg:city":"Scafati",
    "sg:orig_category":"Termotecnica E Riscaldamento, Apparecchiature E Servizi",
    "sg:phone":"+39 081 863 1481",
    "sg:postcode":"84018",
    "sg:province":"Salerno",
    "wof:name":"Termoidrosanitaria Prete Sas",
    "wof:placetype":"venue"
},
  "geometry": {"coordinates":[14.527564,40.749641],"type":"Point"}
}