{
  "type": "Feature",
  "properties": {
    "iso:country":"IT",
    "sg:address":"20121 Milano",
    "sg:city":"Milano",
    "sg:orig_category":"Ristorazione E Locali Pubblici Affini. Ristoranti Ed Esercizi Affini. Servizi Ausiliari Di Ristorazione E Di Intrattenimento",
    "sg:phone":"+39 02 7600 2767",
    "sg:postcode":"20121",
    "sg:province":"Milano",
    "sg:website":"http://www.todine.net/bagutta",
    "wof:name":"Ristorante Bagutta Dei Fratelli Pepori Srl",
    "wof:placetype":"venue"
},
  "geometry": {"coordinates":[9.196468,45.467789],"type":"Point"}
}