{
  "type": "Feature",
  "properties": {
    "iso:country":"IT",
    "sg:address":"84091 Battipaglia",
    "sg:city":"Battipaglia",
    "sg:orig_category":"Carrozzerie Autoveicoli Industriali E Speciali",
    "sg:phone":"+39 0828 346043",
    "sg:postcode":"84091",
    "sg:province":"Salerno",
    "wof:name":"J & Gi International Srl",
    "wof:placetype":"venue"
},
  "geometry": {"coordinates":[14.99165,40.59687],"type":"Point"}
}