{
  "type": "Feature",
  "properties": {
    "iso:country":"IT",
    "sg:address":"3, Piazza S. Paolo 12051 Alba",
    "sg:city":"Alba",
    "sg:classifiers":[
        {
            "category":"Professional",
            "subcategory":"Business Services",
            "type":"Services"
        }
    ],
    "sg:phone":"+39 0173 226611",
    "sg:postcode":"12051",
    "sg:province":"Cuneo",
    "sg:tags":[
        "advice"
    ],
    "wof:name":"Servizi A.c.a. S.r.l.",
    "wof:placetype":"venue"
},
  "geometry": {"coordinates":[7.5471105576,44.38879776],"type":"Point"}
}