{
  "type": "Feature",
  "properties": {
    "iso:country":"IT",
    "sg:address":"20052 Monza",
    "sg:city":"Monza",
    "sg:orig_category":"Servizi Al Turismo. Trasporto Pubblico E Privato. Acqua, Luce, Gas E Societa' Di Esercizio Pubblico",
    "sg:phone":"+39 039 272 0492",
    "sg:postcode":"20052",
    "sg:province":"Milano",
    "wof:name":"T.p.b. -trasporti Pubblici Della Brianza- Spa",
    "wof:placetype":"venue"
},
  "geometry": {"coordinates":[9.27788,45.574421],"type":"Point"}
}