{
  "type": "Feature",
  "properties": {
    "addr:full":"20093 Cologno Monzese Cologno Monzese Milano 20093",
    "addr:postcode":"20093;20093",
    "iso:country":"IT",
    "sg:address":"20093 Cologno Monzese",
    "sg:city":"Cologno Monzese",
    "sg:classifiers":[
        {
            "category":"Manufacturing",
            "subcategory":"Metals",
            "type":"Manufacturing & Wholesale Goods"
        }
    ],
    "sg:phone":"+39 02 254 8421",
    "sg:postcode":"20093",
    "sg:province":"Milano",
    "sg:tags":[
        "forming",
        "working",
        "welding"
    ],
    "wof:name":"Assist-cut Srl",
    "wof:placetype":"venue"
},
  "geometry": {"coordinates":[9.2808990479,45.5400390625],"type":"Point"}
}