{
  "type": "Feature",
  "properties": {
    "iso:country":"IT",
    "sg:address":"11, V. Weingartner 39022 Lagundo",
    "sg:city":"Lagundo",
    "sg:classifiers":[
        {
            "category":"Manufacturing",
            "subcategory":"Food",
            "type":"Manufacturing & Wholesale Goods"
        }
    ],
    "sg:phone":"+39 0473 446246",
    "sg:postcode":"39022",
    "sg:province":"Bolzano/Bozen",
    "sg:tags":[
        "equipment",
        "processing",
        "-",
        "machinery"
    ],
    "sg:website":"http://www.eller.it",
    "wof:name":"Eller Srl",
    "wof:placetype":"venue"
},
  "geometry": {"coordinates":[11.135433197,46.678314209],"type":"Point"}
}