{
  "type": "Feature",
  "properties": {
    "iso:country":"IT",
    "sg:address":"01028 Orte",
    "sg:city":"Orte",
    "sg:orig_category":"Terme",
    "sg:phone":"+39 0761 403066",
    "sg:postcode":"01028",
    "sg:province":"Viterbo",
    "wof:name":"Terme Tourist Di Mandosi Alberto & C. Snc",
    "wof:placetype":"venue"
},
  "geometry": {"coordinates":[12.380755,42.454185],"type":"Point"}
}