{
  "type": "Feature",
  "properties": {
    "iso:country":"IT",
    "sg:address":"7, Via Dei Pradei 22070 Grandate",
    "sg:city":"Grandate",
    "sg:classifiers":[
        {
            "category":"Shopping",
            "subcategory":"Crafts & Fabrics",
            "type":"Retail Goods"
        }
    ],
    "sg:phone":"+39 39031564164",
    "sg:postcode":"22070",
    "sg:province":"Como",
    "wof:name":"Marves (s.r.l.)",
    "wof:placetype":"venue"
},
  "geometry": {"coordinates":[9.051612854,45.7691268921],"type":"Point"}
}