{
  "type": "Feature",
  "properties": {
    "iso:country":"IT",
    "sg:address":"33048 San Giovanni Natisone",
    "sg:orig_category":"Apparecchiature E Sistemi Per Magazzinaggio E Movimentazione. Servizi Di Magazzinaggio E Movimentazione",
    "sg:phone":"+39 0432 756284",
    "sg:postcode":"33048",
    "sg:province":"Udine",
    "sg:website":"http://www.carexpress.it",
    "wof:name":"Car-express Di Cantarutti Sandra & C. Sas",
    "wof:placetype":"venue"
},
  "geometry": {"coordinates":[13.396122,45.975975],"type":"Point"}
}