{
  "type": "Feature",
  "properties": {
    "iso:country":"IT",
    "sg:address":"65129 Pescara",
    "sg:city":"Pescara",
    "sg:orig_category":"Forniture Per Attivita' Commerciali Ed Artigianali. Pubblicita', Marketing E Comunicazione",
    "sg:phone":"+39 085 454 9082",
    "sg:postcode":"65129",
    "sg:province":"Pescara",
    "wof:name":"Adria Neon Di Adriana Di Mascio",
    "wof:placetype":"venue"
},
  "geometry": {"coordinates":[14.2219791412,42.4488525391],"type":"Point"}
}