{
  "type": "Feature",
  "properties": {
    "iso:country":"IT",
    "sg:address":"25080 Calvagese Della Riviera",
    "sg:city":"Calvagese della Riviera",
    "sg:orig_category":"Zootecnia E Pesca, Allevamento Piccoli Animali",
    "sg:phone":"+39 030 601054",
    "sg:postcode":"25080",
    "sg:province":"Brescia",
    "wof:name":"Valovo Di Perini Giuseppe & C. (s.n.c.)",
    "wof:placetype":"venue"
},
  "geometry": {"coordinates":[10.466269,45.521584],"type":"Point"}
}