{
  "type": "Feature",
  "properties": {
    "iso:country":"IT",
    "sg:address":"15067 Novi Ligure",
    "sg:city":"Novi Ligure",
    "sg:orig_category":"Apparecchiature Ed Attrezzature Meccaniche",
    "sg:phone":"+39 0143 78667",
    "sg:postcode":"15067",
    "sg:province":"Alessandria",
    "wof:name":"Sageme 2000 S.a.s.",
    "wof:placetype":"venue"
},
  "geometry": {"coordinates":[8.796452,44.756222],"type":"Point"}
}