{
  "type": "Feature",
  "properties": {
    "iso:country":"IT",
    "sg:address":"10061 Cavour",
    "sg:city":"Cavour",
    "sg:orig_category":"Servizi E Lavori Per Arredamento E Industria Del Legno",
    "sg:phone":"+39 0121 69094",
    "sg:postcode":"10061",
    "sg:province":"Torino",
    "wof:name":"Perassi Legnami Snc",
    "wof:placetype":"venue"
},
  "geometry": {"coordinates":[7.376264,44.793209],"type":"Point"}
}