{
  "type": "Feature",
  "properties": {
    "iso:country":"IT",
    "sg:address":"459, Strada Valli 46011 Acquanegra Sul Chiese",
    "sg:city":"Acquanegra sul Chiese",
    "sg:classifiers":[
        {
            "category":"Sports & Exercise",
            "subcategory":"Playing Field",
            "type":"Entertainment"
        }
    ],
    "sg:phone":"+39 0376 727428",
    "sg:postcode":"46011",
    "sg:province":"Mantova",
    "sg:tags":[
        "game"
    ],
    "wof:name":"Tecno - Cuci Srl",
    "wof:placetype":"venue"
},
  "geometry": {"coordinates":[10.444162,45.16272],"type":"Point"}
}