{
  "type": "Feature",
  "properties": {
    "iso:country":"IT",
    "sg:address":"Via Canonici 61100 Pesaro",
    "sg:city":"Pesaro",
    "sg:classifiers":[
        {
            "category":"Utilities",
            "subcategory":"Electric",
            "type":"Services"
        }
    ],
    "sg:phone":"+39 390 721 6991",
    "sg:postcode":"61100",
    "sg:province":"Pesaro E Urbino",
    "sg:tags":[
        "energy"
    ],
    "wof:name":"Aspes Multiservizi S.p.a.",
    "wof:placetype":"venue"
},
  "geometry": {"coordinates":[12.867797,43.89045],"type":"Point"}
}