{
  "type": "Feature",
  "properties": {
    "iso:country":"IT",
    "sg:address":"7, Via Senofonte 20145 Milano",
    "sg:city":"Milano",
    "sg:classifiers":[
        {
            "category":"Manufacturing",
            "subcategory":"Tools & Machinery",
            "type":"Manufacturing & Wholesale Goods"
        }
    ],
    "sg:phone":"+39 39024984560",
    "sg:postcode":"20145",
    "sg:province":"Milano",
    "sg:tags":[
        "environment",
        "equipment",
        "-"
    ],
    "wof:name":"Daelli S.r.l.",
    "wof:placetype":"venue"
},
  "geometry": {"coordinates":[9.157743,45.475273],"type":"Point"}
}