{
  "type": "Feature",
  "properties": {
    "addr:full":"52026 Pian Di Sc\u00f2 Pian di Sco Arezzo 52026",
    "addr:postcode":"52026;52026",
    "iso:country":"IT",
    "sg:address":"52026 Pian Di Sc\u00f2",
    "sg:city":"Pian di Sco",
    "sg:orig_category":"Apparecchiature Ed Attrezzature Meccaniche. Forniture E Materiali Per Imballaggio E Confezionamento. Apparecchiature E Sistemi Per Imballaggio E Confezionamento",
    "sg:phone":"+39 055 951735",
    "sg:postcode":"52026",
    "sg:province":"Arezzo",
    "wof:name":"Fustellificio Toscano Di Naldini Ugo",
    "wof:placetype":"venue"
},
  "geometry": {"coordinates":[11.489033,43.623913],"type":"Point"}
}