{
  "type": "Feature",
  "properties": {
    "iso:country":"IT",
    "sg:address":"14, Via Macello 10060 Buriasco",
    "sg:city":"Buriasco",
    "sg:classifiers":[
        {
            "category":"Real Estate",
            "subcategory":"Surveying",
            "type":"Services"
        }
    ],
    "sg:phone":"+39 0121 368800",
    "sg:postcode":"10060",
    "sg:province":"Torino",
    "sg:tags":[
        "equipment",
        "material",
        "good",
        "-",
        "handling"
    ],
    "wof:name":"Dema S.p.a.",
    "wof:placetype":"venue"
},
  "geometry": {"coordinates":[7.414187,44.868805],"type":"Point"}
}