{
  "type": "Feature",
  "properties": {
    "iso:country":"IT",
    "sg:address":"Sda San Martino Pizzolano 2 26867 Somaglia",
    "sg:city":"San Martino Pizzolano",
    "sg:classifiers":[
        {
            "category":"Banks & Credit Unions",
            "subcategory":"Investment Brokerage",
            "type":"Services"
        }
    ],
    "sg:phone":"+39 0377 570175",
    "sg:postcode":"26867",
    "sg:province":"Lodi",
    "sg:tags":[
        "electric",
        "intermittent",
        "cranes",
        "elevator",
        "hoisting",
        "equipment",
        "motor"
    ],
    "wof:name":"Motor Lift Srl",
    "wof:placetype":"venue"
},
  "geometry": {"coordinates":[9.609871,45.178825],"type":"Point"}
}