{
  "type": "Feature",
  "properties": {
    "iso:country":"IT",
    "sg:address":"Via Gora Del Pero 43 59100 Prato",
    "sg:city":"Prato",
    "sg:classifiers":[
        {
            "category":"Manufacturing",
            "subcategory":"Textiles",
            "type":"Manufacturing & Wholesale Goods"
        }
    ],
    "sg:phone":"+39 0574 621675",
    "sg:postcode":"59100",
    "sg:province":"Prato",
    "sg:tags":[
        "knitted"
    ],
    "sg:website":"www.timatex.it",
    "wof:name":"Timatex Fabrics Srl",
    "wof:placetype":"venue"
},
  "geometry": {"coordinates":[11.057929,43.856995],"type":"Point"}
}