{
  "type": "Feature",
  "properties": {
    "addr:full":"20146 Milano Milano Milano 20146",
    "addr:postcode":"20146;20146",
    "iso:country":"IT",
    "sg:address":"20146 Milano",
    "sg:city":"Milano",
    "sg:orig_category":"Tempo Libero - Articoli E Forniture. Regalistica Aziendale",
    "sg:phone":"+39 02 4830 1385",
    "sg:postcode":"20146",
    "sg:province":"Milano",
    "wof:name":"Lorca Srl",
    "wof:placetype":"venue"
},
  "geometry": {"coordinates":[9.137342,45.451199],"type":"Point"}
}