{
  "type": "Feature",
  "properties": {
    "addr:full":"10060 None None Torino 10060",
    "addr:postcode":"10060;10060",
    "iso:country":"IT",
    "sg:address":"10060 None",
    "sg:city":"None",
    "sg:orig_category":"Accessori Dei Mezzi Di Trasporto",
    "sg:phone":"+39 011 986 3810",
    "sg:postcode":"10060",
    "sg:province":"Torino",
    "wof:name":"G.t. Granturismo",
    "wof:placetype":"venue"
},
  "geometry": {"coordinates":[7.527526,45.008945],"type":"Point"}
}