{
  "type": "Feature",
  "properties": {
    "iso:country":"IT",
    "sg:address":"70029 Santeramo In Colle",
    "sg:city":"Santeramo in Colle",
    "sg:orig_category":"Macchine, Impianti Ed Attrezzature Per Abbigliamento E Pelletterie",
    "sg:phone":"+39 080 302 2882",
    "sg:postcode":"70029",
    "sg:province":"Bari",
    "wof:name":"Cianciotti Mario",
    "wof:placetype":"venue"
},
  "geometry": {"coordinates":[16.86389,41.127209],"type":"Point"}
}