{
  "type": "Feature",
  "properties": {
    "addr:full":"67063 Oricola L'Aquila 67063",
    "addr:postcode":"67063;l'aquila 67063",
    "iso:country":"IT",
    "sg:address":"67063 Oricola",
    "sg:orig_category":"Accessori Moda D'abbigliamento",
    "sg:phone":"+39 0863 99341",
    "sg:postcode":"67063",
    "sg:province":"L'Aquila",
    "sg:website":"http://www.mondialseta.com",
    "wof:name":"Mondial Seta Srl",
    "wof:placetype":"venue"
},
  "geometry": {"coordinates":[13.431377,41.906658],"type":"Point"}
}