{
  "type": "Feature",
  "properties": {
    "addr:full":"30173 Venezia Mestre Venezia 30173",
    "addr:postcode":"30173;30173",
    "iso:country":"IT",
    "sg:address":"30173 Venezia",
    "sg:city":"Mestre",
    "sg:orig_category":"Nautica. Servizi Per Lo Sport E Il Tempo Libero. Servizi Al Turismo. Servizi Ausiliari Dei Mezzi Di Trasporto",
    "sg:phone":"+39 041 532 8762",
    "sg:postcode":"30173",
    "sg:province":"Venezia",
    "wof:name":"Consorzio Motoscafi S. Giuliano",
    "wof:placetype":"venue"
},
  "geometry": {"coordinates":[12.244107,45.495838],"type":"Point"}
}