{
  "type": "Feature",
  "properties": {
    "iso:country":"IT",
    "sg:address":"Via Dell'industria 74 70051 Barletta",
    "sg:city":"Barletta",
    "sg:classifiers":[
        {
            "category":"Shopping",
            "subcategory":"Shoes",
            "type":"Retail Goods"
        }
    ],
    "sg:phone":"+39 0883 532536",
    "sg:postcode":"70051",
    "sg:province":"Bari",
    "sg:tags":[
        "children's"
    ],
    "wof:name":"Jayne Sport S.r.l.",
    "wof:placetype":"venue"
},
  "geometry": {"coordinates":[16.302851,41.311581],"type":"Point"}
}