{
  "type": "Feature",
  "properties": {
    "iso:country":"IT",
    "sg:address":"Via Enrico Toti 13 04100 Latina",
    "sg:city":"Latina",
    "sg:classifiers":[
        {
            "category":"Government",
            "subcategory":"Court House",
            "type":"Public Place"
        }
    ],
    "sg:phone":"+39 0773 663801",
    "sg:postcode":"04100",
    "sg:province":"Latina",
    "sg:tags":[
        "accommodation",
        "furniture"
    ],
    "wof:name":"Cogeco Di Marisa Tognini & C. Sas",
    "wof:placetype":"venue"
},
  "geometry": {"coordinates":[12.830468,41.564972],"type":"Point"}
}