{
  "type": "Feature",
  "properties": {
    "iso:country":"IT",
    "sg:address":"Ctr Cioffi 84025 Eboli",
    "sg:city":"Eboli",
    "sg:classifiers":[
        {
            "category":"Food & Beverages",
            "subcategory":"Cheese",
            "type":"Retail Goods"
        }
    ],
    "sg:phone":"+39 0828 347060",
    "sg:postcode":"84025",
    "sg:province":"Salerno",
    "sg:tags":[
        "cream"
    ],
    "wof:name":"Casearia Galdi Srl",
    "wof:placetype":"venue"
},
  "geometry": {"coordinates":[14.765912,40.677956],"type":"Point"}
}