{
  "type": "Feature",
  "properties": {
    "iso:country":"IT",
    "sg:address":"50038 Scarperia",
    "sg:city":"Scarperia",
    "sg:orig_category":"Magazzinaggio E Logistica Industriale - Impianti Ed Attrezzature",
    "sg:phone":"+39 055 846542",
    "sg:postcode":"50038",
    "sg:province":"Firenze",
    "sg:website":"http://www.rosss.it",
    "wof:name":"Rosss Dei Fratelli Bettini Snc",
    "wof:placetype":"venue"
},
  "geometry": {"coordinates":[11.320416,44.04398],"type":"Point"}
}