{
  "type": "Feature",
  "properties": {
    "iso:country":"IT",
    "sg:address":"7, Via Fontana 25040 Monticelli Brusati",
    "sg:city":"Monticelli Brusati",
    "sg:classifiers":[
        {
            "category":"Food & Beverages",
            "subcategory":"Groceries & Convenience Stores",
            "type":"Retail Goods"
        }
    ],
    "sg:phone":"+39 39030652661",
    "sg:postcode":"25040",
    "sg:province":"Brescia",
    "sg:tags":[
        "drink"
    ],
    "wof:name":"Antica Cantina Fratta (s.p.a.)",
    "wof:placetype":"venue"
},
  "geometry": {"coordinates":[10.10329,45.623711],"type":"Point"}
}