{
  "type": "Feature",
  "properties": {
    "addr:full":"Via Bastioni 21; Brunico",
    "addr:housenumber":"21",
    "addr:street":"Via Bastioni",
    "iso:country":"IT",
    "sg:address":"Via Bastioni 21; Brunico",
    "sg:classifiers":[
        {
            "category":"Banks & Credit Unions",
            "subcategory":"Bank",
            "type":"Services"
        }
    ],
    "sg:phone":"+39 0474 555892",
    "wof:name":"Cassa Di Risparmio Di Bolzano Spa",
    "wof:placetype":"venue"
},
  "geometry": {"coordinates":[11.93706,46.796215],"type":"Point"}
}