{
  "type": "Feature",
  "properties": {
    "iso:country":"IT",
    "sg:address":"85100 Potenza",
    "sg:city":"Potenza",
    "sg:orig_category":"Banche E Servizi Finanziari",
    "sg:phone":"+39 0971 445509",
    "sg:postcode":"85100",
    "sg:province":"Potenza",
    "wof:name":"Interfin Sas",
    "wof:placetype":"venue"
},
  "geometry": {"coordinates":[15.787437,40.645748],"type":"Point"}
}