{
  "type": "Feature",
  "properties": {
    "addr:full":"50021 Barberino Val D'elsa Firenze 50021",
    "addr:postcode":"50021;50021",
    "addr:street":"Barberino",
    "iso:country":"IT",
    "sg:address":"50021 Barberino Val D'elsa",
    "sg:classifiers":[
        {
            "category":"Wholesale",
            "subcategory":"Machinery & Supplies",
            "type":"Manufacturing & Wholesale Goods"
        }
    ],
    "sg:phone":"+39 055 807 9004",
    "sg:postcode":"50021",
    "sg:province":"Firenze",
    "sg:tags":[
        "product",
        "industrial",
        "equipment",
        "engineering",
        "mechanical",
        "electronic"
    ],
    "wof:name":"S.v.e.m.a. Snc",
    "wof:placetype":"venue"
},
  "geometry": {"coordinates":[11.150411,43.522034],"type":"Point"}
}