{
  "type": "Feature",
  "properties": {
    "addr:full":"40134 Bologna Bologna Bologna 40134",
    "addr:postcode":"40134;40134",
    "iso:country":"IT",
    "sg:address":"40134 Bologna",
    "sg:city":"Bologna",
    "sg:orig_category":"Forniture Per Attivita' Commerciali Ed Artigianali",
    "sg:phone":"+39 051 614 0195",
    "sg:postcode":"40134",
    "sg:province":"Bologna",
    "wof:name":"Armaroli E Bucci Srl",
    "wof:placetype":"venue"
},
  "geometry": {"coordinates":[11.3230600357,44.4955368042],"type":"Point"}
}