{
  "type": "Feature",
  "properties": {
    "addr:full":"Piazza S. Leonardo Da Porto Maurizio 00125 Roma Roma Roma 00125",
    "addr:postcode":"00125;00125",
    "addr:street":"Piazza S. Leonardo Da Porto Maurizio",
    "iso:country":"IT",
    "sg:address":"Piazza S. Leonardo Da Porto Maurizio 00125 Roma",
    "sg:city":"Roma",
    "sg:classifiers":[
        {
            "category":"Shopping",
            "subcategory":"Jewelry",
            "type":"Retail Goods"
        }
    ],
    "sg:phone":"+39 06 5235 2209",
    "sg:postcode":"00125",
    "sg:province":"Roma",
    "sg:tags":[
        "jewellery"
    ],
    "wof:name":"Baroni Gioielli Di Umberto Baroni & C. S.a.s",
    "wof:placetype":"venue"
},
  "geometry": {"coordinates":[12.482325,41.895466],"type":"Point"}
}