{
  "type": "Feature",
  "properties": {
    "iso:country":"IT",
    "sg:address":"Via Milano, 78 - Ospiate 20021 Bollate",
    "sg:city":"Bollate",
    "sg:classifiers":[
        {
            "category":"Home & Garden",
            "subcategory":"Building Materials",
            "type":"Retail Goods"
        }
    ],
    "sg:phone":"+39 02 383341",
    "sg:postcode":"20021",
    "sg:province":"Milano",
    "sg:tags":[
        "industry",
        "chemical-technical",
        "basic"
    ],
    "wof:name":"Rhodia Geronazzo Spa",
    "wof:placetype":"venue"
},
  "geometry": {"coordinates":[9.108963,45.531052],"type":"Point"}
}