{
  "type": "Feature",
  "properties": {
    "iso:country":"IT",
    "sg:address":"13854 Quaregna",
    "sg:city":"Quaregna",
    "sg:orig_category":"Servizi E Lavori Per Abbigliamento E Pelletterie",
    "sg:phone":"+39 015 94941",
    "sg:postcode":"13854",
    "sg:province":"Biella",
    "wof:name":"Tintoria Di Quaregna (s.r.l.)",
    "wof:placetype":"venue"
},
  "geometry": {"coordinates":[8.109231,45.5597],"type":"Point"}
}