{
  "type": "Feature",
  "properties": {
    "iso:country":"IT",
    "sg:address":"Zona Porto Canale 26100 Cremona",
    "sg:city":"Cremona",
    "sg:classifiers":[
        {
            "category":"Manufacturing",
            "subcategory":"Rubber & Plastics",
            "type":"Manufacturing & Wholesale Goods"
        }
    ],
    "sg:phone":"+39 0372 4091",
    "sg:postcode":"26100",
    "sg:province":"Cremona",
    "sg:tags":[
        "pipe",
        "tubes",
        "welded"
    ],
    "sg:website":"www.arvedi.it",
    "wof:name":"Arvedi Tubi Acciai Srl",
    "wof:placetype":"venue"
},
  "geometry": {"coordinates":[10.0261354446,45.1334991455],"type":"Point"}
}