{
  "type": "Feature",
  "properties": {
    "iso:country":"IT",
    "sg:address":"57125 Livorno",
    "sg:city":"Livorno",
    "sg:orig_category":"Forniture Per Abbigliamento E Pelletterie",
    "sg:phone":"+39 0586 880252",
    "sg:postcode":"57125",
    "sg:province":"Livorno",
    "wof:name":"Banchieri Carlo Srl",
    "wof:placetype":"venue"
},
  "geometry": {"coordinates":[10.3158283234,43.5520019531],"type":"Point"}
}