{
  "type": "Feature",
  "properties": {
    "iso:country":"IT",
    "sg:address":"50019 Sesto Fiorentino",
    "sg:city":"Sesto Fiorentino",
    "sg:orig_category":"Servizi Editoriali",
    "sg:phone":"+39 055 311248",
    "sg:postcode":"50019",
    "sg:province":"Firenze",
    "wof:name":"Degl'innocenti Srl",
    "wof:placetype":"venue"
},
  "geometry": {"coordinates":[11.218378,43.837437],"type":"Point"}
}