{
  "type": "Feature",
  "properties": {
    "iso:country":"IT",
    "sg:address":"7, Piazza Matteotti Giacomo 80133 Napoli",
    "sg:city":"Napoli",
    "sg:classifiers":[
        {
            "category":"Wholesale",
            "subcategory":"Machinery & Supplies",
            "type":"Manufacturing & Wholesale Goods"
        }
    ],
    "sg:phone":"+39 081 551 7220",
    "sg:postcode":"80133",
    "sg:province":"Napoli",
    "sg:tags":[
        "equipment",
        "precision"
    ],
    "wof:name":"Sector Group Spa",
    "wof:placetype":"venue"
},
  "geometry": {"coordinates":[14.2506999969,40.8431930542],"type":"Point"}
}