{
  "type": "Feature",
  "properties": {
    "addr:full":"12042 Bra Bra Cuneo 12042",
    "addr:postcode":"12042;12042",
    "iso:country":"IT",
    "sg:address":"12042 Bra",
    "sg:city":"Bra",
    "sg:orig_category":"Termotecnica E Riscaldamento, Apparecchiature E Servizi. Prodotti Vari In Metallo",
    "sg:phone":"+39 0172 430245",
    "sg:postcode":"12042",
    "sg:province":"Cuneo",
    "wof:name":"Clima Service Di Piumatti Elio",
    "wof:placetype":"venue"
},
  "geometry": {"coordinates":[7.62493,44.433804],"type":"Point"}
}