{
  "type": "Feature",
  "properties": {
    "iso:country":"IT",
    "sg:address":"29010 Villanova Sull'arda",
    "sg:city":"Villanova",
    "sg:orig_category":"Macchine, Impianti Ed Attrezzature Industria Chimica. Macchine E Impianti Per Attivita' Commerciali Ed Artigianali",
    "sg:phone":"+39 0523 837855",
    "sg:postcode":"29010",
    "sg:province":"Piacenza",
    "wof:name":"Tizeta (s.r.l.)",
    "wof:placetype":"venue"
},
  "geometry": {"coordinates":[10.007865,45.01646],"type":"Point"}
}