{
  "type": "Feature",
  "properties": {
    "iso:country":"IT",
    "sg:address":"50054 Fucecchio",
    "sg:city":"Fucecchio",
    "sg:orig_category":"Macchine Ufficio - Commercio, Noleggio E Riparazione",
    "sg:phone":"+39 0571 242966",
    "sg:postcode":"50054",
    "sg:province":"Firenze",
    "wof:name":"Micronet Snc Di Crociani Rossano E Stefano Spalladori",
    "wof:placetype":"venue"
},
  "geometry": {"coordinates":[10.788723,43.765724],"type":"Point"}
}