{
  "type": "Feature",
  "properties": {
    "iso:country":"IT",
    "sg:address":"20144 Milano",
    "sg:city":"Milano",
    "sg:orig_category":"Scuole E Servizi Scolastici. Ricerca, Selezione E Formazione Del Personale. Pubblica Amministrazione",
    "sg:phone":"+39 02 481 2076",
    "sg:postcode":"20144",
    "sg:province":"Milano",
    "wof:name":"Scuole Pubbliche Istituti Tecnici Moreschi",
    "wof:placetype":"venue"
},
  "geometry": {"coordinates":[9.164195,45.463966],"type":"Point"}
}