{
  "type": "Feature",
  "properties": {
    "addr:full":"15020 Murisengo Murisengo Alessandria 15020",
    "addr:postcode":"15020;15020",
    "iso:country":"IT",
    "sg:address":"15020 Murisengo",
    "sg:city":"Murisengo",
    "sg:orig_category":"Prodotti Chimici Secondari",
    "sg:phone":"+39 0141 993019",
    "sg:postcode":"15020",
    "sg:province":"Alessandria",
    "wof:name":"Inter.e.m. (s.r.l.)",
    "wof:placetype":"venue"
},
  "geometry": {"coordinates":[8.1495065689,45.0804252625],"type":"Point"}
}