{
  "type": "Feature",
  "properties": {
    "iso:country":"IT",
    "sg:address":"10, Via Bagnolo Belvedere 12032 Barge",
    "sg:city":"Barge",
    "sg:classifiers":[
        {
            "category":"Personal",
            "subcategory":"Shoe Repair & Shine",
            "type":"Services"
        }
    ],
    "sg:phone":"+39 0175 346049",
    "sg:postcode":"12032",
    "sg:province":"Cuneo",
    "sg:tags":[
        "leather"
    ],
    "wof:name":"Selmart Di Martellotto Sebastiano E Figlio (s.n.c.)",
    "wof:placetype":"venue"
},
  "geometry": {"coordinates":[7.32204,44.732414],"type":"Point"}
}