{
  "type": "Feature",
  "properties": {
    "iso:country":"IT",
    "sg:address":"Viale Stazione Prosecco 5/b 34010 Sgonico",
    "sg:city":"Sgonico",
    "sg:classifiers":[
        {
            "category":"Shopping",
            "subcategory":"Mobile Phones",
            "type":"Retail Goods"
        }
    ],
    "sg:phone":"+39 040 419 2111",
    "sg:postcode":"34010",
    "sg:province":"Trieste",
    "sg:tags":[
        "telephone"
    ],
    "sg:website":"www.telit.net",
    "wof:name":"Dai Telecom Spa",
    "wof:placetype":"venue"
},
  "geometry": {"coordinates":[13.7570066452,45.7151527405],"type":"Point"}
}