{
  "type": "Feature",
  "properties": {
    "addr:full":"80123 Napoli Napoli Napoli 80123",
    "addr:housenumber":"80123",
    "addr:postcode":"80123",
    "iso:country":"IT",
    "sg:address":"80123 Napoli",
    "sg:city":"Napoli",
    "sg:orig_category":"Trasporti E Spedizioni Merci",
    "sg:phone":"+39 081 240 3578",
    "sg:postcode":"80123",
    "sg:province":"Napoli",
    "wof:name":"Agenzia Buglione Di Claudio Buglione",
    "wof:placetype":"venue"
},
  "geometry": {"coordinates":[14.221848,40.905849],"type":"Point"}
}