{
  "type": "Feature",
  "properties": {
    "iso:country":"IT",
    "sg:address":"Via Garbini 75 01100 Viterbo",
    "sg:city":"Viterbo",
    "sg:orig_category":"Ladies' Shoes",
    "sg:phone":"+39 0761 27861",
    "sg:postcode":"01100",
    "sg:province":"Viterbo",
    "wof:name":"Fratelli Pietrini Spa",
    "wof:placetype":"venue"
},
  "geometry": {"coordinates":[12.095576,42.437027],"type":"Point"}
}