{
  "type": "Feature",
  "properties": {
    "iso:country":"IT",
    "sg:address":"23, Via Lavoro Zona D/3 15100 Alessandria",
    "sg:city":"Alessandria",
    "sg:classifiers":[
        {
            "category":"Real Estate",
            "subcategory":"Surveying",
            "type":"Services"
        }
    ],
    "sg:phone":"+39 0131 249600",
    "sg:postcode":"15100",
    "sg:province":"Alessandria",
    "sg:tags":[
        "equipment",
        "material",
        "good",
        "-",
        "handling"
    ],
    "wof:name":"Snanol S.r.l.",
    "wof:placetype":"venue"
},
  "geometry": {"coordinates":[8.616951,44.913216],"type":"Point"}
}