{
  "type": "Feature",
  "properties": {
    "iso:country":"IT",
    "sg:address":"12, Via Colonna 31010 Mareno Di Piave",
    "sg:city":"Mareno di Piave",
    "sg:classifiers":[
        {
            "category":"Shopping",
            "subcategory":"Computers & Home Electronics",
            "type":"Retail Goods"
        }
    ],
    "sg:phone":"+39 0438 445056",
    "sg:postcode":"31010",
    "sg:province":"Treviso",
    "sg:tags":[
        "electronic",
        "electrical",
        "equipment"
    ],
    "wof:name":"Elettra 80 (s.r.l.)",
    "wof:placetype":"venue"
},
  "geometry": {"coordinates":[12.314798,45.818588],"type":"Point"}
}