{
  "type": "Feature",
  "properties": {
    "iso:country":"IT",
    "sg:address":"92023 Campobello Di Licata",
    "sg:city":"Campobello di Licata",
    "sg:orig_category":"Disinfezione, Disinfestazione E Derattizzazione",
    "sg:phone":"+39 0922 879690",
    "sg:postcode":"92023",
    "sg:province":"Agrigento",
    "wof:name":"Sicil Eco Srl",
    "wof:placetype":"venue"
},
  "geometry": {"coordinates":[13.920392,37.259445],"type":"Point"}
}