{
  "type": "Feature",
  "properties": {
    "iso:country":"IT",
    "sg:address":"20050 Mezzago",
    "sg:city":"Mezzago",
    "sg:orig_category":"Macchine Utensili E Impianti",
    "sg:phone":"+39 039 602 1358",
    "sg:postcode":"20050",
    "sg:province":"Milano",
    "wof:name":"Dossi Adriano",
    "wof:placetype":"venue"
},
  "geometry": {"coordinates":[9.415168,45.617176],"type":"Point"}
}