{
  "type": "Feature",
  "properties": {
    "iso:country":"IT",
    "sg:address":"50, Via Della Liberta' 06010 Citerna",
    "sg:city":"Citerna",
    "sg:classifiers":[
        {
            "category":"Food & Beverages",
            "subcategory":"Groceries & Convenience Stores",
            "type":"Retail Goods"
        }
    ],
    "sg:phone":"+39 075 859 2831",
    "sg:postcode":"06010",
    "sg:province":"Perugia",
    "sg:tags":[
        "product",
        "related"
    ],
    "wof:name":"Salumificio Valtiberino S.r.l.",
    "wof:placetype":"venue"
},
  "geometry": {"coordinates":[12.1523447037,43.507019043],"type":"Point"}
}