{
  "type": "Feature",
  "properties": {
    "iso:country":"IT",
    "sg:address":"85, V. Amendola 63019 S. Elpidio A Mare",
    "sg:classifiers":[
        {
            "category":"Shopping",
            "subcategory":"Stationery & Office Supplies",
            "type":"Retail Goods"
        }
    ],
    "sg:phone":"+39 0734 871518",
    "sg:postcode":"63019",
    "sg:province":"Ascoli Piceno",
    "sg:tags":[
        "professional"
    ],
    "sg:website":"http://www.estrostands.it",
    "wof:name":"Estro Di Gino Andrenacci",
    "wof:placetype":"venue"
},
  "geometry": {"coordinates":[13.5749769211,42.8554000854],"type":"Point"}
}