{
  "type": "Feature",
  "properties": {
    "addr:full":"80030 Carbonara Di Nola Carbonara di Nola Napoli 80030",
    "addr:housenumber":"di nola",
    "addr:postcode":"80030;80030",
    "iso:country":"IT",
    "sg:address":"80030 Carbonara Di Nola",
    "sg:city":"Carbonara di Nola",
    "sg:orig_category":"Accessori Moda D'abbigliamento",
    "sg:phone":"+39 081 825 4067",
    "sg:postcode":"80030",
    "sg:province":"Napoli",
    "wof:name":"Scala Salvatore",
    "wof:placetype":"venue"
},
  "geometry": {"coordinates":[14.56535,40.88015],"type":"Point"}
}