{
  "type": "Feature",
  "properties": {
    "iso:country":"IT",
    "sg:address":"29, Via Ponte 84086 Roccapiemonte",
    "sg:city":"Roccapiemonte",
    "sg:classifiers":[
        {
            "category":"Professional",
            "subcategory":"Engineering",
            "type":"Services"
        }
    ],
    "sg:phone":"+39 39081931835",
    "sg:postcode":"84086",
    "sg:province":"Salerno",
    "sg:tags":[
        "machine",
        "-",
        "mechanical"
    ],
    "wof:name":"O.m.i.p. (s.r.l.)",
    "wof:placetype":"venue"
},
  "geometry": {"coordinates":[14.611814,40.790649],"type":"Point"}
}