{
  "type": "Feature",
  "properties": {
    "addr:full":"24012 Brembilla Brembilla Bergamo 24012",
    "addr:postcode":"24012;24012",
    "iso:country":"IT",
    "sg:address":"24012 Brembilla",
    "sg:city":"Brembilla",
    "sg:orig_category":"Minuterie Di Precisione",
    "sg:phone":"+39 0345 98829",
    "sg:postcode":"24012",
    "sg:province":"Bergamo",
    "wof:name":"Lidi Snc",
    "wof:placetype":"venue"
},
  "geometry": {"coordinates":[9.5780010223,45.6926765442],"type":"Point"}
}