{
  "type": "Feature",
  "properties": {
    "iso:country":"IT",
    "sg:address":"10036 Settimo Torinese",
    "sg:city":"Settimo Torinese",
    "sg:orig_category":"Penne A Sfera E A Feltro",
    "sg:phone":"+39 011 897 7618",
    "sg:postcode":"10036",
    "sg:province":"Torino",
    "sg:website":"http://www.metalcosrl.it",
    "wof:name":"Metalco Srl",
    "wof:placetype":"venue"
},
  "geometry": {"coordinates":[7.7525167465,45.1503067017],"type":"Point"}
}