{
  "type": "Feature",
  "properties": {
    "addr:full":"Via Dell' Industria 17 61024 Mombaroccio Mombaroccio Pesaro E Urbino 61024",
    "addr:housenumber":"17",
    "addr:postcode":"61024;61024",
    "addr:street":"Via Dell ' Industria",
    "iso:country":"IT",
    "sg:address":"Via Dell' Industria 17 61024 Mombaroccio",
    "sg:city":"Mombaroccio",
    "sg:classifiers":[
        {
            "category":"Home & Garden",
            "subcategory":"Kitchen Supply",
            "type":"Retail Goods"
        }
    ],
    "sg:phone":"+39 0721 470127",
    "sg:postcode":"61024",
    "sg:province":"Pesaro E Urbino",
    "sg:tags":[
        "fitted"
    ],
    "sg:website":"www.piucucine.it",
    "wof:name":"Piu' Cucine Srl",
    "wof:placetype":"venue"
},
  "geometry": {"coordinates":[12.5298032761,43.633556366],"type":"Point"}
}