{
  "type": "Feature",
  "properties": {
    "addr:full":"96, V. Monviso 20024 Garbagnate Milanese Garbagnate Milanese Milano 20024",
    "addr:housenumber":"96",
    "addr:postcode":"20024;20024",
    "addr:street":"V. Monviso",
    "iso:country":"IT",
    "sg:address":"96, V. Monviso 20024 Garbagnate Milanese",
    "sg:city":"Garbagnate Milanese",
    "sg:classifiers":[
        {
            "category":"Shopping",
            "subcategory":"Computers & Home Electronics",
            "type":"Retail Goods"
        }
    ],
    "sg:phone":"+39 39029958801",
    "sg:postcode":"20024",
    "sg:province":"Milano",
    "sg:tags":[
        "electronic",
        "electrical",
        "equipment"
    ],
    "sg:website":"http://www.paginegialle.it/elettro",
    "wof:name":"Elettroimpianti Pelosi",
    "wof:placetype":"venue"
},
  "geometry": {"coordinates":[9.079453,45.556973],"type":"Point"}
}