{
  "type": "Feature",
  "properties": {
    "addr:full":"62017 Porto Recanati Porto Recanati Macerata 62017",
    "addr:housenumber":"62017",
    "addr:postcode":"62017",
    "iso:country":"IT",
    "sg:address":"62017 Porto Recanati",
    "sg:city":"Porto Recanati",
    "sg:orig_category":"Musica",
    "sg:phone":"+39 071 979 8402",
    "sg:postcode":"62017",
    "sg:province":"Macerata",
    "wof:name":"Babbini Ennio",
    "wof:placetype":"venue"
},
  "geometry": {"coordinates":[13.653637886,43.4226379395],"type":"Point"}
}