{
  "type": "Feature",
  "properties": {
    "iso:country":"IT",
    "sg:address":"42100 Reggio Emilia",
    "sg:classifiers":[
        {
            "category":"Health Services",
            "subcategory":"Health Practitioner",
            "type":"Services"
        }
    ],
    "sg:phone":"+39 0522 792420",
    "sg:postcode":"42100",
    "sg:province":"Reggio Nell'Emilia",
    "sg:tags":[
        "medici"
    ],
    "wof:name":"Studio Diagnostico 'raoul Palmer' Srl",
    "wof:placetype":"venue"
},
  "geometry": {"coordinates":[10.6150083542,44.7086830139],"type":"Point"}
}