{
  "type": "Feature",
  "properties": {
    "iso:country":"IT",
    "sg:address":"21052 Busto Arsizio",
    "sg:city":"Busto Arsizio",
    "sg:orig_category":"Lucernari",
    "sg:phone":"+39 0331 683370",
    "sg:postcode":"21052",
    "sg:province":"Varese",
    "wof:name":"Basaglia Geometra Rino",
    "wof:placetype":"venue"
},
  "geometry": {"coordinates":[8.849398,45.619816],"type":"Point"}
}