{
  "type": "Feature",
  "properties": {
    "iso:country":"IT",
    "sg:address":"10122 Torino",
    "sg:city":"Torino",
    "sg:orig_category":"Impiantistica E Prodotti Tecnologici Per Edilizia. Macchine, Strumenti Ed Apparecchi Per Attivita' Industriali",
    "sg:phone":"+39 011 562 8473",
    "sg:postcode":"10122",
    "sg:province":"Torino",
    "wof:name":"Tecnimport S.a.s.",
    "wof:placetype":"venue"
},
  "geometry": {"coordinates":[7.676603,45.071659],"type":"Point"}
}