{
  "type": "Feature",
  "properties": {
    "addr:full":"24050 Cavernago Cavernago Bergamo 24050",
    "addr:postcode":"24050;24050",
    "iso:country":"IT",
    "sg:address":"24050 Cavernago",
    "sg:city":"Cavernago",
    "sg:orig_category":"Prodotti E Manufatti In Materie Plastiche",
    "sg:phone":"+39 035 840075",
    "sg:postcode":"24050",
    "sg:province":"Bergamo",
    "wof:name":"Trafilplastica Bergamasca Di Calesini E C. (s.n.c.)",
    "wof:placetype":"venue"
},
  "geometry": {"coordinates":[9.7635812759,45.6339149475],"type":"Point"}
}