{
  "type": "Feature",
  "properties": {
    "addr:full":"20131 Milano Milano Milano 20131",
    "addr:postcode":"20131;20131",
    "iso:country":"IT",
    "sg:address":"20131 Milano",
    "sg:city":"Milano",
    "sg:orig_category":"Sport - Articoli E Forniture",
    "sg:phone":"+39 02 7063 8086",
    "sg:postcode":"20131",
    "sg:province":"Milano",
    "wof:name":"Armeria Buzzini",
    "wof:placetype":"venue"
},
  "geometry": {"coordinates":[9.235674,45.485161],"type":"Point"}
}