{
  "type": "Feature",
  "properties": {
    "addr:full":"Piazza Italia 12; Acqui Terme; 15011 Acqui Terme Alessandria 15011",
    "addr:housenumber":"12",
    "addr:postcode":"15011;15011",
    "addr:street":"Piazza Italia",
    "iso:country":"IT",
    "sg:address":"Piazza Italia 12; Acqui Terme; 15011",
    "sg:city":"Acqui Terme",
    "sg:classifiers":[
        {
            "category":"Banks & Credit Unions",
            "subcategory":"Bank",
            "type":"Services"
        }
    ],
    "sg:phone":"+39 0144 321533",
    "sg:postcode":"15011",
    "sg:province":"Alessandria",
    "wof:name":"Credito Italiano Spa",
    "wof:placetype":"venue"
},
  "geometry": {"coordinates":[8.469821,44.674568],"type":"Point"}
}