{
  "type": "Feature",
  "properties": {
    "iso:country":"IT",
    "sg:address":"Via Nastrucci 16a 29100 Piacenza",
    "sg:city":"Piacenza",
    "sg:classifiers":[
        {
            "category":"Food & Beverages",
            "subcategory":"Chocolate",
            "type":"Retail Goods"
        }
    ],
    "sg:phone":"+39 0523 57611",
    "sg:postcode":"29100",
    "sg:province":"Piacenza",
    "sg:tags":[
        "export"
    ],
    "sg:website":"www.asisrl.com",
    "wof:name":"Asi Scambi Industriali Srl",
    "wof:placetype":"venue"
},
  "geometry": {"coordinates":[9.7067241669,45.040763855],"type":"Point"}
}