{
  "type": "Feature",
  "properties": {
    "addr:full":"10141 Torino Torino Torino 10141",
    "addr:postcode":"10141;10141",
    "iso:country":"IT",
    "sg:address":"10141 Torino",
    "sg:city":"Torino",
    "sg:orig_category":"Trasporti E Spedizioni Merci",
    "sg:phone":"+39 011 382 2076",
    "sg:postcode":"10141",
    "sg:province":"Torino",
    "wof:name":"Trenitalia Spa Divisone Cargo",
    "wof:placetype":"venue"
},
  "geometry": {"coordinates":[7.657633,45.061344],"type":"Point"}
}