{
  "type": "Feature",
  "properties": {
    "iso:country":"IT",
    "sg:address":"36013 Piovene Rocchette",
    "sg:city":"Piovene Rocchette",
    "sg:orig_category":"Metalli E Leghe",
    "sg:phone":"+39 0445 550485",
    "sg:postcode":"36013",
    "sg:province":"Vicenza",
    "wof:name":"Ronda S.p.a.",
    "wof:placetype":"venue"
},
  "geometry": {"coordinates":[11.4326248169,45.7431640625],"type":"Point"}
}