{
  "type": "Feature",
  "properties": {
    "iso:country":"IT",
    "sg:address":"25020 Pralboino",
    "sg:city":"Pralboino",
    "sg:orig_category":"Istituti Di Bellezza",
    "sg:phone":"+39 030 954604",
    "sg:postcode":"25020",
    "sg:province":"Brescia",
    "wof:name":"Beppe Moda Capelli Di Gobbi G.",
    "wof:placetype":"venue"
},
  "geometry": {"coordinates":[10.218326,45.267109],"type":"Point"}
}