{
  "type": "Feature",
  "properties": {
    "iso:country":"IT",
    "sg:address":"00128 Roma",
    "sg:city":"Roma",
    "sg:classifiers":[
        {
            "category":"Shopping",
            "subcategory":"Bicycles & Sporting Goods",
            "type":"Retail Goods"
        }
    ],
    "sg:phone":"+39 06 508 7912",
    "sg:postcode":"00128",
    "sg:province":"Roma",
    "sg:tags":[
        "e",
        "sport",
        "-",
        "forniture",
        "articoli"
    ],
    "wof:name":"Bottega Del Campeggiatore Srl",
    "wof:placetype":"venue"
},
  "geometry": {"coordinates":[12.451797,41.791801],"type":"Point"}
}