{
  "type": "Feature",
  "properties": {
    "iso:country":"IT",
    "sg:address":"20157 Milano",
    "sg:city":"Milano",
    "sg:orig_category":"Apparecchi, Attrezzature E Forniture Per Centri Estetici. Forniture Per Attivita' Commerciali Ed Artigianali",
    "sg:phone":"+39 02 357 0279",
    "sg:postcode":"20157",
    "sg:province":"Milano",
    "wof:name":"Phs Snc Di Piller E Soffientin",
    "wof:placetype":"venue"
},
  "geometry": {"coordinates":[9.135863,45.514584],"type":"Point"}
}