{
  "type": "Feature",
  "properties": {
    "addr:full":"777, Traversa Marecchia 47822 Santarcangelo Di Romagna Santarcangelo di Romagna Rimini 47822",
    "addr:housenumber":"777",
    "addr:postcode":"47822;47822",
    "addr:street":"Traversa Marecchia",
    "iso:country":"IT",
    "sg:address":"777, Traversa Marecchia 47822 Santarcangelo Di Romagna",
    "sg:city":"Santarcangelo di Romagna",
    "sg:classifiers":[
        {
            "category":"Parking",
            "subcategory":"Lot",
            "type":"Transportation"
        }
    ],
    "sg:phone":"+39 0541 626188",
    "sg:postcode":"47822",
    "sg:province":"Rimini",
    "sg:tags":[
        "transport",
        "road"
    ],
    "wof:name":"Globo Trasporti Scarl",
    "wof:placetype":"venue"
},
  "geometry": {"coordinates":[12.472298,44.031231],"type":"Point"}
}