{
  "type": "Feature",
  "properties": {
    "iso:country":"IT",
    "sg:address":"01030 Vitorchiano",
    "sg:city":"Vitorchiano",
    "sg:orig_category":"Agricoltura - Attrezzi, Prodotti E Forniture",
    "sg:phone":"+39 0761 370292",
    "sg:postcode":"01030",
    "sg:province":"Viterbo",
    "wof:name":"F.a.c.m.a. Di Bellachioma Marcello & C. Snc",
    "wof:placetype":"venue"
},
  "geometry": {"coordinates":[12.17927,42.440834],"type":"Point"}
}