{
  "type": "Feature",
  "properties": {
    "iso:country":"IT",
    "sg:address":"25010 Visano",
    "sg:city":"Visano",
    "sg:orig_category":"Lavorazioni Metalli, Stampaggio E Saldatura",
    "sg:phone":"+39 030 995 8997",
    "sg:postcode":"25010",
    "sg:province":"Brescia",
    "wof:name":"Nuova O.f.a.r (s.p.a.)",
    "wof:placetype":"venue"
},
  "geometry": {"coordinates":[10.373445,45.319389],"type":"Point"}
}