{
  "type": "Feature",
  "properties": {
    "iso:country":"IT",
    "sg:address":"20142 Milano",
    "sg:city":"Milano",
    "sg:orig_category":"Scuole E Servizi Scolastici. Ricerca, Selezione E Formazione Del Personale",
    "sg:phone":"+39 02 8950 6269",
    "sg:postcode":"20142",
    "sg:province":"Milano",
    "sg:website":"http://www.ciamformazione.it",
    "wof:name":"Centro Informatico Addestramento Multimediale",
    "wof:placetype":"venue"
},
  "geometry": {"coordinates":[9.171266,45.441936],"type":"Point"}
}