{
  "type": "Feature",
  "properties": {
    "iso:country":"IT",
    "sg:address":"Fondo Portella Di Mare 90039 Villabate",
    "sg:city":"Villabate",
    "sg:classifiers":[
        {
            "category":"Farming",
            "subcategory":"Livestock Farm",
            "type":"Manufacturing & Wholesale Goods"
        }
    ],
    "sg:phone":"+39 39091492037",
    "sg:postcode":"90039",
    "sg:province":"Palermo",
    "sg:tags":[
        "agriculture"
    ],
    "wof:name":"Sicula Carni (s.p.a.)",
    "wof:placetype":"venue"
},
  "geometry": {"coordinates":[13.445428,38.086525],"type":"Point"}
}