{
  "type": "Feature",
  "properties": {
    "iso:country":"IT",
    "sg:address":"80020 Casavatore",
    "sg:city":"Casavatore",
    "sg:orig_category":"Prodotti E Manufatti In Materie Plastiche",
    "sg:phone":"+39 081 737 3901",
    "sg:postcode":"80020",
    "sg:province":"Napoli",
    "wof:name":"Fratelli Tarantino Di Felice Tarantino & C S.a.s.",
    "wof:placetype":"venue"
},
  "geometry": {"coordinates":[14.2786636353,40.9013328552],"type":"Point"}
}