{
  "type": "Feature",
  "properties": {
    "iso:country":"IT",
    "sg:address":"26010 Dovera",
    "sg:city":"Dovera",
    "sg:orig_category":"Arredi Ed Attrezzature Per Attivita' Commerciali Ed Artigianali",
    "sg:phone":"+39 0373 94194",
    "sg:postcode":"26010",
    "sg:province":"Cremona",
    "wof:name":"L.m.p. Snc",
    "wof:placetype":"venue"
},
  "geometry": {"coordinates":[9.542519,45.366261],"type":"Point"}
}