{
  "type": "Feature",
  "properties": {
    "iso:country":"IT",
    "sg:address":"Ctr. Reuccio 2 62018 Potenza Picena",
    "sg:city":"Potenza Picena",
    "sg:classifiers":[
        {
            "category":"Manufacturing",
            "subcategory":"Rubber & Plastics",
            "type":"Manufacturing & Wholesale Goods"
        }
    ],
    "sg:phone":"+39 0733 671353",
    "sg:postcode":"62018",
    "sg:province":"Macerata",
    "sg:tags":[
        "made",
        "thermoset",
        "part",
        "injection",
        "moulded",
        "thermoplastic"
    ],
    "sg:website":"www.starplast-italy.com",
    "wof:name":"Starplast Srl",
    "wof:placetype":"venue"
},
  "geometry": {"coordinates":[13.456262,43.300747],"type":"Point"}
}