{
  "type": "Feature",
  "properties": {
    "addr:full":"26, Via Roncat 31018 Gaiarine Gaiarine Treviso 31018",
    "addr:postcode":"31018;31018",
    "addr:street":"Via Roncat",
    "iso:country":"IT",
    "sg:address":"26, Via Roncat 31018 Gaiarine",
    "sg:city":"Gaiarine",
    "sg:classifiers":[
        {
            "category":"Home & Garden",
            "subcategory":"Home Furnishings",
            "type":"Retail Goods"
        }
    ],
    "sg:phone":"+39 39043475121",
    "sg:postcode":"31018",
    "sg:province":"Treviso",
    "sg:tags":[
        "household"
    ],
    "wof:name":"Poles (s.r.l.)",
    "wof:placetype":"venue"
},
  "geometry": {"coordinates":[12.513582,45.876453],"type":"Point"}
}