{
  "type": "Feature",
  "properties": {
    "iso:country":"IT",
    "sg:address":"10136 Torino",
    "sg:city":"Torino",
    "sg:orig_category":"Servizi E Lavori Per Edilizia E Lavori Pubblici. Servizi E Lavori Per Ecologia E Smaltimento Rifiuti. Macchine E Forniture Per Ecologia E Smaltimento Rifiuti. Acqua, Luce, Gas E Societa' Di Esercizio ",
    "sg:phone":"+39 011 701178",
    "sg:postcode":"10136",
    "sg:province":"Torino",
    "wof:name":"Associazione Subalpina C.b.o.m.",
    "wof:placetype":"venue"
},
  "geometry": {"coordinates":[7.59119,45.051899],"type":"Point"}
}