{
  "type": "Feature",
  "properties": {
    "iso:country":"IT",
    "sg:address":"16131 Genova",
    "sg:city":"Genova",
    "sg:orig_category":"Gioielleria, Oreficeria E Argenteria. Shopping",
    "sg:phone":"+39 010 388592",
    "sg:postcode":"16131",
    "sg:province":"Genova",
    "wof:name":"Oroshopping Oscar Vita Snc",
    "wof:placetype":"venue"
},
  "geometry": {"coordinates":[8.976386,44.406017],"type":"Point"}
}