{
  "type": "Feature",
  "properties": {
    "addr:full":"23883 Brivio Brivio Lecco 23883",
    "addr:postcode":"23883;23883",
    "iso:country":"IT",
    "sg:address":"23883 Brivio",
    "sg:city":"Brivio",
    "sg:orig_category":"Imballaggio - Macchine",
    "sg:phone":"+39 039 532 0744",
    "sg:postcode":"23883",
    "sg:province":"Lecco",
    "sg:website":"http://www.vacuumpump.it",
    "wof:name":"Vacuum Pump Spa",
    "wof:placetype":"venue"
},
  "geometry": {"coordinates":[9.442229,45.724258],"type":"Point"}
}