{
  "type": "Feature",
  "properties": {
    "addr:full":"36031 Dueville Dueville Vicenza 36031",
    "addr:postcode":"36031;36031",
    "iso:country":"IT",
    "sg:address":"36031 Dueville",
    "sg:city":"Dueville",
    "sg:orig_category":"Impianti Elettrici Industriali E Civili - Installazione E Manutenzione",
    "sg:phone":"+39 0444 590273",
    "sg:postcode":"36031",
    "sg:province":"Vicenza",
    "sg:website":"http://www.2fbattilana.com",
    "wof:name":"2f Di Battilana Armando & C. Snc",
    "wof:placetype":"venue"
},
  "geometry": {"coordinates":[11.573744,45.639603],"type":"Point"}
}