{
  "type": "Feature",
  "properties": {
    "addr:full":"01100 Viterbo Viterbo Viterbo 01100",
    "addr:postcode":"01100;01100",
    "iso:country":"IT",
    "sg:address":"01100 Viterbo",
    "sg:city":"Viterbo",
    "sg:orig_category":"Forniture Per Agricoltura E Zootecnia. Animali Domestici",
    "sg:phone":"+39 0761 223182",
    "sg:postcode":"01100",
    "sg:province":"Viterbo",
    "wof:name":"Pianetanimale",
    "wof:placetype":"venue"
},
  "geometry": {"coordinates":[12.1032934189,42.4374427795],"type":"Point"}
}