{
  "type": "Feature",
  "properties": {
    "iso:country":"IT",
    "sg:address":"520/e, Corso Italia 44043 Mirabello",
    "sg:city":"Mirabello",
    "sg:classifiers":[
        {
            "category":"Wholesale",
            "subcategory":"Machinery & Supplies",
            "type":"Manufacturing & Wholesale Goods"
        }
    ],
    "sg:phone":"+39 0532 846735",
    "sg:postcode":"44043",
    "sg:province":"Ferrara",
    "sg:tags":[
        "-",
        "agriculture",
        "equipment"
    ],
    "wof:name":"Pomac (s.r.l.)",
    "wof:placetype":"venue"
},
  "geometry": {"coordinates":[11.451677,44.819088],"type":"Point"}
}