{
  "type": "Feature",
  "properties": {
    "iso:country":"IT",
    "sg:address":"Viale Del Lavoro 60030 Castelbellino",
    "sg:city":"Castelbellino",
    "sg:classifiers":[
        {
            "category":"Wholesale",
            "subcategory":"Machinery & Supplies",
            "type":"Manufacturing & Wholesale Goods"
        }
    ],
    "sg:phone":"+39 0731 701181",
    "sg:postcode":"60030",
    "sg:province":"Ancona",
    "sg:tags":[
        "-",
        "agriculture",
        "equipment"
    ],
    "wof:name":"Co.r.m.a. Macchine Agricole",
    "wof:placetype":"venue"
},
  "geometry": {"coordinates":[13.166112,43.505066],"type":"Point"}
}