{
  "type": "Feature",
  "properties": {
    "addr:full":"Via Lainate 29 20010 Pogliano Milanese Pogliano Milanese Milano 20010",
    "addr:housenumber":"29",
    "addr:postcode":"20010;20010",
    "addr:street":"Via Lainate",
    "iso:country":"IT",
    "sg:address":"Via Lainate 29 20010 Pogliano Milanese",
    "sg:city":"Pogliano Milanese",
    "sg:classifiers":[
        {
            "category":"Wholesale",
            "subcategory":"Vending Machines",
            "type":"Manufacturing & Wholesale Goods"
        }
    ],
    "sg:phone":"+39 02 939601",
    "sg:postcode":"20010",
    "sg:province":"Milano",
    "sg:tags":[
        "ice",
        "flake"
    ],
    "sg:website":"www.scotsman-ice.it",
    "wof:name":"Frimont Spa",
    "wof:placetype":"venue"
},
  "geometry": {"coordinates":[9.0349740982,45.5093955994],"type":"Point"}
}