{
  "type": "Feature",
  "properties": {
    "addr:full":"00044 Frascati Frascati Roma 00044",
    "addr:postcode":"00044;00044",
    "iso:country":"IT",
    "sg:address":"00044 Frascati",
    "sg:city":"Frascati",
    "sg:orig_category":"Carni, Salumi E Pesci. Zootecnia E Pesca, Allevamento Piccoli Animali",
    "sg:phone":"+39 06 942 0048",
    "sg:postcode":"00044",
    "sg:province":"Roma",
    "wof:name":"Mancini Generoso",
    "wof:placetype":"venue"
},
  "geometry": {"coordinates":[12.673301,41.823296],"type":"Point"}
}