{
  "type": "Feature",
  "properties": {
    "addr:full":"59013 Montemurlo Montemurlo Prato 59013",
    "addr:postcode":"59013;59013",
    "iso:country":"IT",
    "sg:address":"59013 Montemurlo",
    "sg:city":"Montemurlo",
    "sg:orig_category":"Servizi E Lavori Per Abbigliamento E Pelletterie",
    "sg:phone":"+39 0574 683947",
    "sg:postcode":"59013",
    "sg:province":"Prato",
    "wof:name":"Rammendo Irene Di Faella Anna",
    "wof:placetype":"venue"
},
  "geometry": {"coordinates":[11.03046,43.924419],"type":"Point"}
}