{
  "type": "Feature",
  "properties": {
    "iso:country":"IT",
    "sg:address":"20050 Lesmo",
    "sg:city":"Lesmo",
    "sg:orig_category":"Arredi Ed Attrezzature Per Attivita' Commerciali Ed Artigianali",
    "sg:phone":"+39 039 606 4639",
    "sg:postcode":"20050",
    "sg:province":"Milano",
    "wof:name":"Gre Cer Srl",
    "wof:placetype":"venue"
},
  "geometry": {"coordinates":[9.306628,45.650002],"type":"Point"}
}