{
  "type": "Feature",
  "properties": {
    "iso:country":"IT",
    "sg:address":"23851 Galbiate",
    "sg:city":"Galbiate",
    "sg:orig_category":"Serramenti Ed Infissi",
    "sg:phone":"+39 0341 283336",
    "sg:postcode":"23851",
    "sg:province":"Lecco",
    "wof:name":"Arle Di Pessina & C. Snc",
    "wof:placetype":"venue"
},
  "geometry": {"coordinates":[9.392797,45.846462],"type":"Point"}
}