{
  "type": "Feature",
  "properties": {
    "iso:country":"IT",
    "sg:address":"Corso Italia 21; Alleghe; 32022",
    "sg:city":"Alleghe",
    "sg:classifiers":[
        {
            "category":"Banks & Credit Unions",
            "subcategory":"Bank",
            "type":"Services"
        }
    ],
    "sg:phone":"+39 0437 523023",
    "sg:postcode":"32022",
    "sg:province":"Belluno",
    "wof:name":"Cariverona Banca Spa",
    "wof:placetype":"venue"
},
  "geometry": {"coordinates":[12.015998,46.413666],"type":"Point"}
}