{
  "type": "Feature",
  "properties": {
    "iso:country":"IT",
    "sg:address":"20040 Cambiago",
    "sg:city":"Cambiago",
    "sg:orig_category":"Automobili E Mezzi Di Trasporto",
    "sg:phone":"+39 02 950 6418",
    "sg:postcode":"20040",
    "sg:province":"Milano",
    "wof:name":"Mombelli Ezio",
    "wof:placetype":"venue"
},
  "geometry": {"coordinates":[9.446398,45.578434],"type":"Point"}
}