{
  "type": "Feature",
  "properties": {
    "addr:full":"25124 Brescia Brescia Brescia 25124",
    "addr:postcode":"25124;25124",
    "iso:country":"IT",
    "sg:address":"25124 Brescia",
    "sg:city":"Brescia",
    "sg:orig_category":"Materiali Edili",
    "sg:phone":"+39 030 245555",
    "sg:postcode":"25124",
    "sg:province":"Brescia",
    "wof:name":"Minteq Italiana (s.p.a.)",
    "wof:placetype":"venue"
},
  "geometry": {"coordinates":[10.212884,45.528622],"type":"Point"}
}