{
  "type": "Feature",
  "properties": {
    "iso:country":"IT",
    "sg:address":"20149 Milano",
    "sg:city":"Milano",
    "sg:orig_category":"Servizi Per Lo Sport E Il Tempo Libero. Associazioni Ed Organismi Di Interesse Pubblico",
    "sg:phone":"+39 02 498 7699",
    "sg:postcode":"20149",
    "sg:province":"Milano",
    "wof:name":"Associazione Sportiva Junior Milano Pallavolo",
    "wof:placetype":"venue"
},
  "geometry": {"coordinates":[9.145041,45.47382],"type":"Point"}
}