{
  "type": "Feature",
  "properties": {
    "iso:country":"IT",
    "sg:address":"75, Strada Monzambano 46040 Ponti Sul Mincio",
    "sg:city":"Monzambano",
    "sg:classifiers":[
        {
            "category":"Wholesale",
            "subcategory":"Machinery & Supplies",
            "type":"Manufacturing & Wholesale Goods"
        }
    ],
    "sg:phone":"+39 0376 809761",
    "sg:postcode":"46040",
    "sg:province":"Mantova",
    "sg:tags":[
        "-",
        "agriculture",
        "equipment"
    ],
    "wof:name":"C.o.m.t. Di Bazzoli S.r.l.",
    "wof:placetype":"venue"
},
  "geometry": {"coordinates":[10.698556,45.399796],"type":"Point"}
}