{
  "type": "Feature",
  "properties": {
    "addr:full":"41100 Modena Modena Modena 41100",
    "addr:postcode":"41100;41100",
    "iso:country":"IT",
    "sg:address":"41100 Modena",
    "sg:city":"Modena",
    "sg:orig_category":"Estetiste",
    "sg:phone":"+39 059 214278",
    "sg:postcode":"41100",
    "sg:province":"Modena",
    "wof:name":"Estetica A Colori Sas",
    "wof:placetype":"venue"
},
  "geometry": {"coordinates":[10.927654,44.638947],"type":"Point"}
}