{
  "type": "Feature",
  "properties": {
    "iso:country":"IT",
    "sg:address":"83038 Montemiletto",
    "sg:city":"Montemiletto",
    "sg:orig_category":"Lavorazioni Meccaniche E Servizi",
    "sg:phone":"+39 0825 963687",
    "sg:postcode":"83038",
    "sg:province":"Avellino",
    "wof:name":"Palladino Arpino",
    "wof:placetype":"venue"
},
  "geometry": {"coordinates":[14.898175,40.953068],"type":"Point"}
}