{
  "type": "Feature",
  "properties": {
    "iso:country":"IT",
    "sg:address":"67039 Sulmona",
    "sg:orig_category":"Articoli Regalo - Vendita Al Dettaglio",
    "sg:phone":"+39 0864 52213",
    "sg:postcode":"67039",
    "sg:province":"L'Aquila",
    "wof:name":"Cf Creazioni Srl",
    "wof:placetype":"venue"
},
  "geometry": {"coordinates":[13.899222,42.008446],"type":"Point"}
}