{
  "type": "Feature",
  "properties": {
    "iso:country":"IT",
    "sg:address":"13037 Serravalle Sesia",
    "sg:city":"Serravalle Sesia",
    "sg:orig_category":"Macchine, Impianti Ed Attrezzature Per Agricoltura E Zootecnia",
    "sg:phone":"+39 0163 450678",
    "sg:postcode":"13037",
    "sg:province":"Vercelli",
    "wof:name":"L.m.a. S.n.c. Di Greco N. - Mazzone C. & C.",
    "wof:placetype":"venue"
},
  "geometry": {"coordinates":[8.43414,45.325275],"type":"Point"}
}