{
  "type": "Feature",
  "properties": {
    "iso:country":"IT",
    "sg:address":"55012 Capannori",
    "sg:city":"Capannori",
    "sg:orig_category":"Campeggio. Automobili E Mezzi Di Trasporto",
    "sg:phone":"+39 0583 94409",
    "sg:postcode":"55012",
    "sg:province":"Lucca",
    "sg:website":"http://www.bondiolicaravan.it",
    "wof:name":"Bondioli Ernesto",
    "wof:placetype":"venue"
},
  "geometry": {"coordinates":[10.513147,43.811321],"type":"Point"}
}