{
  "type": "Feature",
  "properties": {
    "iso:country":"IT",
    "sg:address":"54100 Massa",
    "sg:city":"Massa",
    "sg:orig_category":"Scuole E Servizi Scolastici",
    "sg:phone":"+39 0585 42684",
    "sg:postcode":"54100",
    "sg:province":"Massa-Carrara",
    "wof:name":"Scuola Magistrale Teresa Vallerga",
    "wof:placetype":"venue"
},
  "geometry": {"coordinates":[10.099769,44.008583],"type":"Point"}
}