{
  "type": "Feature",
  "properties": {
    "iso:country":"IT",
    "sg:address":"59100 Prato",
    "sg:city":"Prato",
    "sg:orig_category":"Facchinaggio, Carico E Scarico Merci, Portabagagli - Servizio",
    "sg:phone":"+39 0574 527724",
    "sg:postcode":"59100",
    "sg:province":"Prato",
    "wof:name":"Centro Servizi C.f.c.",
    "wof:placetype":"venue"
},
  "geometry": {"coordinates":[11.0938081741,43.8780326843],"type":"Point"}
}