{
  "type": "Feature",
  "properties": {
    "addr:full":"40126 Bologna Bologna Bologna 40126",
    "addr:postcode":"40126;40126",
    "iso:country":"IT",
    "sg:address":"40126 Bologna",
    "sg:city":"Bologna",
    "sg:orig_category":"Non-classified Establishments",
    "sg:phone":"+39 051 228645",
    "sg:postcode":"40126",
    "sg:province":"Bologna",
    "wof:name":"Il Cestaio",
    "wof:placetype":"venue"
},
  "geometry": {"coordinates":[11.34729,44.495224],"type":"Point"}
}