{
  "type": "Feature",
  "properties": {
    "iso:country":"IT",
    "sg:address":"Via Oltrona Al Lago 3 21020 Barasso",
    "sg:city":"Barasso",
    "sg:classifiers":[
        {
            "category":"Manufacturing",
            "subcategory":"Paper Products",
            "type":"Manufacturing & Wholesale Goods"
        }
    ],
    "sg:phone":"+39 0332 744131",
    "sg:postcode":"21020",
    "sg:province":"Varese",
    "sg:tags":[
        "plastics",
        "stamped",
        "composite",
        "fibrous",
        "material",
        "pressed",
        "article",
        "embossed",
        "cardboard"
    ],
    "wof:name":"Civelli Gianluigi & C. Snc",
    "wof:placetype":"venue"
},
  "geometry": {"coordinates":[8.750409,45.833435],"type":"Point"}
}