{
  "type": "Feature",
  "properties": {
    "addr:full":"20121 Milano Milano Milano 20121",
    "addr:postcode":"20121;20121",
    "iso:country":"IT",
    "sg:address":"20121 Milano",
    "sg:city":"Milano",
    "sg:orig_category":"Abbigliamento Donna",
    "sg:phone":"+39 02 2906 0969",
    "sg:postcode":"20121",
    "sg:province":"Milano",
    "wof:name":"L'officina Delle Fate",
    "wof:placetype":"venue"
},
  "geometry": {"coordinates":[9.191935,45.471107],"type":"Point"}
}