{
  "type": "Feature",
  "properties": {
    "iso:country":"IT",
    "sg:address":"Viale Pratese 82 50019 Sesto Fiorentino",
    "sg:city":"Sesto Fiorentino",
    "sg:classifiers":[
        {
            "category":"Wholesale",
            "subcategory":"Electrical",
            "type":"Manufacturing & Wholesale Goods"
        }
    ],
    "sg:phone":"+39 055 420 0042",
    "sg:postcode":"50019",
    "sg:province":"Firenze",
    "sg:tags":[
        "component"
    ],
    "wof:name":"Cieffe Srl",
    "wof:placetype":"venue"
},
  "geometry": {"coordinates":[11.186571,43.84161],"type":"Point"}
}