{
  "type": "Feature",
  "properties": {
    "iso:country":"IT",
    "sg:address":"149, Via Torino 00184 Roma",
    "sg:city":"Roma",
    "sg:classifiers":[
        {
            "category":"Travel",
            "subcategory":"Travel Agent",
            "type":"Entertainment"
        }
    ],
    "sg:phone":"+39 39064824828",
    "sg:postcode":"00184",
    "sg:province":"Roma",
    "sg:tags":[
        "business"
    ],
    "wof:name":"Hotel Rex",
    "wof:placetype":"venue"
},
  "geometry": {"coordinates":[12.488592,41.818871],"type":"Point"}
}