{
  "type": "Feature",
  "properties": {
    "iso:country":"IT",
    "sg:address":"20090 Segrate",
    "sg:city":"Segrate",
    "sg:orig_category":"Cartotecnica E Servizi. Forniture Per Attivita' Commerciali Ed Artigianali",
    "sg:phone":"+39 02 213 5045",
    "sg:postcode":"20090",
    "sg:province":"Milano",
    "wof:name":"Tinchelli S.n.c.",
    "wof:placetype":"venue"
},
  "geometry": {"coordinates":[9.301497,45.490143],"type":"Point"}
}