{
  "type": "Feature",
  "properties": {
    "iso:country":"IT",
    "sg:address":"63100 Ascoli Piceno",
    "sg:city":"Ascoli Piceno",
    "sg:orig_category":"Macchine Ed Impianti Per Edilizia E Lavori Pubblici. Elettronica Industriale, Prodotti E Apparecchiature",
    "sg:phone":"+39 0736 252504",
    "sg:postcode":"63100",
    "sg:province":"Ascoli Piceno",
    "wof:name":"Sitea Snc Di Troiani & C.",
    "wof:placetype":"venue"
},
  "geometry": {"coordinates":[13.598843,42.857517],"type":"Point"}
}