{
  "type": "Feature",
  "properties": {
    "iso:country":"IT",
    "sg:address":"98070 Capri Leone",
    "sg:city":"Capri Leone",
    "sg:orig_category":"Impiantistica E Prodotti Tecnologici Per Edilizia. Termotecnica E Riscaldamento, Apparecchiature E Servizi",
    "sg:phone":"+39 0941 958548",
    "sg:postcode":"98070",
    "sg:province":"Messina",
    "wof:name":"Sgro' Carlo",
    "wof:placetype":"venue"
},
  "geometry": {"coordinates":[14.714489,38.109459],"type":"Point"}
}