{
  "type": "Feature",
  "properties": {
    "addr:full":"Via Turati 30/32 20023 Cerro Maggiore Cerro Maggiore Milano 20023",
    "addr:housenumber":"30 / 32",
    "addr:postcode":"20023;20023",
    "addr:street":"Via Turati",
    "iso:country":"IT",
    "sg:address":"Via Turati 30/32 20023 Cerro Maggiore",
    "sg:city":"Cerro Maggiore",
    "sg:orig_category":"Finned Tubes For Heating And Cooling",
    "sg:phone":"+39 0331 517277",
    "sg:postcode":"20023",
    "sg:province":"Milano",
    "wof:name":"Aek Di Galmarini Jacolina & C Snc",
    "wof:placetype":"venue"
},
  "geometry": {"coordinates":[9.1881408691,45.4636878967],"type":"Point"}
}