{
  "type": "Feature",
  "properties": {
    "addr:full":"9, Via Tecnica 23875 Osnago Osnago Lecco 23875",
    "addr:postcode":"23875;23875",
    "addr:street":"Via Tecnica",
    "iso:country":"IT",
    "sg:address":"9, Via Tecnica 23875 Osnago",
    "sg:city":"Osnago",
    "sg:classifiers":[
        {
            "category":"Shopping",
            "type":"Retail Goods"
        }
    ],
    "sg:phone":"+39 39039587491",
    "sg:postcode":"23875",
    "sg:province":"Lecco",
    "sg:tags":[
        "finished",
        "-",
        "metallic"
    ],
    "wof:name":"O.m.g. Di Molgora Gianfranco",
    "wof:placetype":"venue"
},
  "geometry": {"coordinates":[9.3933115005,45.6715354919],"type":"Point"}
}