{
  "type": "Feature",
  "properties": {
    "iso:country":"IT",
    "sg:address":"Via Santeramo 70022 Altamura",
    "sg:city":"Altamura",
    "sg:classifiers":[
        {
            "category":"Home & Garden",
            "subcategory":"Home Furnishings",
            "type":"Retail Goods"
        }
    ],
    "sg:phone":"+39 080 310 1278",
    "sg:postcode":"70022",
    "sg:province":"Bari",
    "sg:tags":[
        "household"
    ],
    "wof:name":"In Salotto Srl",
    "wof:placetype":"venue"
},
  "geometry": {"coordinates":[16.562927,40.826534],"type":"Point"}
}