{
  "type": "Feature",
  "properties": {
    "iso:country":"IT",
    "sg:address":"10100 Torino",
    "sg:orig_category":"Cinematografia E Radiotelevisione. Pubblicita', Marketing E Comunicazione. Acqua, Luce, Gas E Societa' Di Esercizio Pubblico",
    "sg:phone":"+39 0118800",
    "sg:province":"TO",
    "wof:name":"Rai Radiotelevisione Italiana",
    "wof:placetype":"venue"
},
  "geometry": {"coordinates":[7.317979,44.931015],"type":"Point"}
}