{
  "type": "Feature",
  "properties": {
    "addr:full":"33, Via Ii Giugno 36040 Torri Di Quartesolo Torri di Quartesolo Vicenza 36040",
    "addr:postcode":"36040;36040",
    "addr:street":"Via Ii Giugno",
    "iso:country":"IT",
    "sg:address":"33, Via Ii Giugno 36040 Torri Di Quartesolo",
    "sg:city":"Torri di Quartesolo",
    "sg:classifiers":[
        {
            "category":"Shopping",
            "subcategory":"Crafts & Fabrics",
            "type":"Retail Goods"
        }
    ],
    "sg:phone":"+39 0444 582199",
    "sg:postcode":"36040",
    "sg:province":"Vicenza",
    "wof:name":"Sesso Venanzio (s.r.l.)",
    "wof:placetype":"venue"
},
  "geometry": {"coordinates":[11.540307045,45.5459060669],"type":"Point"}
}