{
  "type": "Feature",
  "properties": {
    "addr:full":"20121 Milano Milano Milano 20121",
    "addr:postcode":"20121;20121",
    "iso:country":"IT",
    "sg:address":"20121 Milano",
    "sg:city":"Milano",
    "sg:orig_category":"Prodotti Vari In Metallo",
    "sg:phone":"+39 02 657 0665",
    "sg:postcode":"20121",
    "sg:province":"Milano",
    "wof:name":"Chierichetti Gianni",
    "wof:placetype":"venue"
},
  "geometry": {"coordinates":[9.18841362,45.4786987305],"type":"Point"}
}