{
  "type": "Feature",
  "properties": {
    "iso:country":"IT",
    "sg:address":"95045 Misterbianco",
    "sg:city":"Misterbianco",
    "sg:orig_category":"Acciai Inossidabili - Commercio",
    "sg:phone":"+39 095 476177",
    "sg:postcode":"95045",
    "sg:province":"Catania",
    "wof:name":"C.d.m. Centro Distribuzione Metalli Srl",
    "wof:placetype":"venue"
},
  "geometry": {"coordinates":[15.020676,37.529091],"type":"Point"}
}