{
  "type": "Feature",
  "properties": {
    "iso:country":"IT",
    "sg:address":"20, Via Ajaccio 00198 Roma",
    "sg:city":"Roma",
    "sg:classifiers":[
        {
            "category":"Professional",
            "subcategory":"Advertising",
            "type":"Services"
        }
    ],
    "sg:phone":"+39 06 8535 8424",
    "sg:postcode":"00198",
    "sg:province":"Roma",
    "sg:tags":[
        "communication",
        "medium"
    ],
    "wof:name":"Fandango Srl",
    "wof:placetype":"venue"
},
  "geometry": {"coordinates":[12.509364,41.919128],"type":"Point"}
}