{
  "type": "Feature",
  "properties": {
    "iso:country":"IT",
    "sg:address":"12045 Fossano",
    "sg:city":"Fossano",
    "sg:orig_category":"Macchine Ed Impianti Per Edilizia E Lavori Pubblici",
    "sg:phone":"+39 0172 60928",
    "sg:postcode":"12045",
    "sg:province":"Cuneo",
    "wof:name":"Bongioanni Stampi S.r.l.",
    "wof:placetype":"venue"
},
  "geometry": {"coordinates":[7.747746,44.572037],"type":"Point"}
}