{
  "type": "Feature",
  "properties": {
    "iso:country":"IT",
    "sg:address":"3, Via Della Costetta 16030 Cogorno",
    "sg:city":"Cogorno",
    "sg:classifiers":[
        {
            "category":"Autos & Motor Vehicles",
            "subcategory":"Boat Sales",
            "type":"Retail Goods"
        }
    ],
    "sg:phone":"+39 0185 380227",
    "sg:postcode":"16030",
    "sg:province":"Genova",
    "wof:name":"Ferretto S.n.c.",
    "wof:placetype":"venue"
},
  "geometry": {"coordinates":[9.35259,44.334053],"type":"Point"}
}