{
  "type": "Feature",
  "properties": {
    "iso:country":"IT",
    "sg:address":"53042 Chianciano Terme",
    "sg:city":"Chianciano Terme",
    "sg:orig_category":"Ospedali E Servizi Sanitari",
    "sg:phone":"+39 0578 64169",
    "sg:postcode":"53042",
    "sg:province":"Siena",
    "wof:name":"Giannotti Accordini Giuseppina",
    "wof:placetype":"venue"
},
  "geometry": {"coordinates":[11.820013,43.051834],"type":"Point"}
}