{
  "type": "Feature",
  "properties": {
    "addr:full":"50143 Firenze Firenze Firenze 50143",
    "addr:postcode":"50143;50143",
    "iso:country":"IT",
    "sg:address":"50143 Firenze",
    "sg:city":"Firenze",
    "sg:orig_category":"Informatica - Consulenza E Servizi. Editoria",
    "sg:phone":"+39 055 713988",
    "sg:postcode":"50143",
    "sg:province":"Firenze",
    "sg:website":"http://www.himedia.it",
    "wof:name":"Hypermedia Produzioni Multimediali Srl",
    "wof:placetype":"venue"
},
  "geometry": {"coordinates":[11.127742,43.759525],"type":"Point"}
}