{
  "type": "Feature",
  "properties": {
    "iso:country":"IT",
    "sg:address":"Viale Romagna 14; Milano",
    "sg:classifiers":[
        {
            "category":"Banks & Credit Unions",
            "subcategory":"Bank",
            "type":"Services"
        }
    ],
    "sg:phone":"+39 02 749 0065",
    "wof:name":"Banca Popolare Commercio, E Industria Scarl",
    "wof:placetype":"venue"
},
  "geometry": {"coordinates":[9.224041,45.470028],"type":"Point"}
}