{
  "type": "Feature",
  "properties": {
    "addr:full":"20144 Milano Milano Milano 20144",
    "addr:postcode":"20144;20144",
    "iso:country":"IT",
    "sg:address":"20144 Milano",
    "sg:city":"Milano",
    "sg:orig_category":"Agenzie D'affari E Servizi Commerciali. Avvocati, Notai E Servizi Legali. Consulenze Tecniche, Amministrative E Perizie",
    "sg:phone":"+39 02 498 9816",
    "sg:postcode":"20144",
    "sg:province":"Milano",
    "wof:name":"Elcam Data (s.n.c.)",
    "wof:placetype":"venue"
},
  "geometry": {"coordinates":[9.164396,45.460411],"type":"Point"}
}