{
  "type": "Feature",
  "properties": {
    "iso:country":"IT",
    "sg:address":"20129 Milano",
    "sg:city":"Milano",
    "sg:orig_category":"Servizi Ausiliari Dei Mezzi Di Trasporto",
    "sg:phone":"+39 02 799473",
    "sg:postcode":"20129",
    "sg:province":"Milano",
    "wof:name":"Autorimessa Garage Piave (s.r.l.)",
    "wof:placetype":"venue"
},
  "geometry": {"coordinates":[9.208555,45.470089],"type":"Point"}
}