{
  "type": "Feature",
  "properties": {
    "iso:country":"IT",
    "sg:address":"9, Via Dei Fiori 20080 Zibido San Giacomo",
    "sg:city":"Zibido San Giacomo",
    "sg:classifiers":[
        {
            "category":"Retail",
            "subcategory":"Animal Services",
            "type":"Services"
        }
    ],
    "sg:phone":"+39 02 9000 2855",
    "sg:postcode":"20080",
    "sg:province":"Milano",
    "sg:tags":[
        "breeding"
    ],
    "wof:name":"Studio Prodotti Integrativi",
    "wof:placetype":"venue"
},
  "geometry": {"coordinates":[9.14728,45.401703],"type":"Point"}
}