{
  "type": "Feature",
  "properties": {
    "addr:full":"00173 Roma Roma Roma 00173",
    "addr:postcode":"00173;00173",
    "iso:country":"IT",
    "sg:address":"00173 Roma",
    "sg:city":"Roma",
    "sg:orig_category":"Impiantistica E Prodotti Tecnologici Per Edilizia. Servizi Ausiliari Di Sorveglianza, Manutenzione E Pulizia",
    "sg:phone":"+39 06 723 4808",
    "sg:postcode":"00173",
    "sg:province":"Roma",
    "wof:name":"Progema S.r.l.",
    "wof:placetype":"venue"
},
  "geometry": {"coordinates":[12.614379,41.832401],"type":"Point"}
}