{
  "type": "Feature",
  "properties": {
    "iso:country":"IT",
    "sg:address":"219, Via Adamoli Gelasio 16138 Genova",
    "sg:city":"Genova",
    "sg:classifiers":[
        {
            "category":"Autos & Motor Vehicles",
            "subcategory":"Automobile Sales",
            "type":"Retail Goods"
        }
    ],
    "sg:phone":"+39 010 835 5168",
    "sg:postcode":"16138",
    "sg:province":"Genova",
    "sg:tags":[
        "industrial"
    ],
    "wof:name":"Altra S.p.a.",
    "wof:placetype":"venue"
},
  "geometry": {"coordinates":[8.933989,44.407063],"type":"Point"}
}