{
  "type": "Feature",
  "properties": {
    "iso:country":"IT",
    "sg:address":"93, Corso Buenos Aires 16043 Chiavari",
    "sg:city":"Chiavari",
    "sg:classifiers":[
        {
            "category":"Wholesale",
            "subcategory":"Drugs",
            "type":"Manufacturing & Wholesale Goods"
        }
    ],
    "sg:phone":"+39 0185 363284",
    "sg:postcode":"16043",
    "sg:province":"Genova",
    "sg:tags":[
        "chemical",
        "pharmaceutical"
    ],
    "wof:name":"Chemical Services S.r.l.",
    "wof:placetype":"venue"
},
  "geometry": {"coordinates":[9.312413,44.320362],"type":"Point"}
}