{
  "type": "Feature",
  "properties": {
    "addr:full":"60/1, Via Gandino Giovanni Battista 10148 Torino Torino Torino 10148",
    "addr:housenumber":"60 / 1",
    "addr:postcode":"10148;10148",
    "addr:street":"Via Gandino Giovanni Battista",
    "iso:country":"IT",
    "sg:address":"60/1, Via Gandino Giovanni Battista 10148 Torino",
    "sg:city":"Torino",
    "sg:classifiers":[
        {
            "category":"Shopping",
            "type":"Retail Goods"
        }
    ],
    "sg:phone":"+39 011 225 9806",
    "sg:postcode":"10148",
    "sg:province":"Torino",
    "sg:tags":[
        "finished",
        "-",
        "metallic"
    ],
    "wof:name":"Tecnomolle S.r.l.",
    "wof:placetype":"venue"
},
  "geometry": {"coordinates":[7.6866188049,45.0705604553],"type":"Point"}
}