{
  "type": "Feature",
  "properties": {
    "iso:country":"IT",
    "sg:address":"35124 Padova",
    "sg:city":"Padova",
    "sg:orig_category":"Servizi E Lavori Per Arredamento E Industria Del Legno",
    "sg:phone":"+39 049 686858",
    "sg:postcode":"35124",
    "sg:province":"Padova",
    "wof:name":"Miozzo Rino",
    "wof:placetype":"venue"
},
  "geometry": {"coordinates":[11.889278,45.361393],"type":"Point"}
}