{
  "type": "Feature",
  "properties": {
    "iso:country":"IT",
    "sg:address":"Via Iv Novembre 10 36030 Zugliano",
    "sg:city":"Zugliano",
    "sg:classifiers":[
        {
            "category":"Manufacturing",
            "subcategory":"Electronics",
            "type":"Manufacturing & Wholesale Goods"
        }
    ],
    "sg:phone":"+39 0445 330243",
    "sg:postcode":"36030",
    "sg:province":"Vicenza",
    "sg:tags":[
        "large",
        "machine",
        "industrial",
        "electrical",
        "equipment"
    ],
    "wof:name":"Iotti Remo E C Snc",
    "wof:placetype":"venue"
},
  "geometry": {"coordinates":[11.540307,45.545906],"type":"Point"}
}