{
  "type": "Feature",
  "properties": {
    "iso:country":"IT",
    "sg:address":"14055 Boglietto",
    "sg:city":"Boglietto",
    "sg:orig_category":"Bevande, Vini E Liquori. Servizi E Lavori Per Industria Alimentare E Bevande",
    "sg:phone":"+39 0141 968676",
    "sg:postcode":"14055",
    "sg:province":"Asti",
    "wof:name":"Distilleria Beccaris Elio E Beccaris Carlo & C.s.n.c. Elio",
    "wof:placetype":"venue"
},
  "geometry": {"coordinates":[8.202794,44.76025],"type":"Point"}
}