{
  "type": "Feature",
  "properties": {
    "iso:country":"IT",
    "sg:address":"10143 Torino",
    "sg:city":"Torino",
    "sg:orig_category":"Non-classified Establishments",
    "sg:phone":"+39 011 747088",
    "sg:postcode":"10143",
    "sg:province":"Torino",
    "wof:name":"Ariano Mobili & Divani Sas",
    "wof:placetype":"venue"
},
  "geometry": {"coordinates":[7.539575,45.056698],"type":"Point"}
}