{
  "type": "Feature",
  "properties": {
    "iso:country":"IT",
    "sg:address":"Via Delle Industrie 11 61040 Sant'ippolito",
    "sg:classifiers":[
        {
            "category":"Professional",
            "type":"Services"
        }
    ],
    "sg:phone":"+39 0721 749061",
    "sg:postcode":"61040",
    "sg:province":"Pesaro E Urbino",
    "sg:tags":[
        "mould",
        "construction"
    ],
    "sg:website":"www.galloitaly.com",
    "wof:name":"Gallo Srl",
    "wof:placetype":"venue"
},
  "geometry": {"coordinates":[12.8724727631,43.7039680481],"type":"Point"}
}