{
  "type": "Feature",
  "properties": {
    "addr:full":"Via Roma, 296/298 64014 Martinsicuro Martinsicuro Teramo 64014",
    "addr:housenumber":"296 / 298",
    "addr:postcode":"64014;64014",
    "addr:street":"Via Roma",
    "iso:country":"IT",
    "sg:address":"Via Roma, 296/298 64014 Martinsicuro",
    "sg:city":"Martinsicuro",
    "sg:classifiers":[
        {
            "category":"Food & Beverages",
            "subcategory":"Liquor & Beverages",
            "type":"Retail Goods"
        }
    ],
    "sg:phone":"+39 0861 797530",
    "sg:postcode":"64014",
    "sg:province":"Teramo",
    "sg:tags":[
        "wine",
        "italian"
    ],
    "wof:name":"Frontenac Spa",
    "wof:placetype":"venue"
},
  "geometry": {"coordinates":[13.915452,42.881851],"type":"Point"}
}