{
  "type": "Feature",
  "properties": {
    "iso:country":"IT",
    "sg:address":"Via Galcianese 89/91 59100 Prato",
    "sg:city":"Prato",
    "sg:classifiers":[
        {
            "category":"Shopping",
            "subcategory":"Crafts & Fabrics",
            "type":"Retail Goods"
        }
    ],
    "sg:phone":"+39 0574 42374",
    "sg:postcode":"59100",
    "sg:province":"Prato",
    "sg:tags":[
        "textile",
        "industry"
    ],
    "wof:name":"Nuova Melograno Spa",
    "wof:placetype":"venue"
},
  "geometry": {"coordinates":[11.0734891891,43.8801002502],"type":"Point"}
}