{
  "type": "Feature",
  "properties": {
    "iso:country":"IT",
    "sg:address":"29, Via Statale 10012 Bollengo",
    "sg:city":"Bollengo",
    "sg:classifiers":[
        {
            "category":"Autos & Motor Vehicles",
            "subcategory":"Automobile Sales",
            "type":"Retail Goods"
        }
    ],
    "sg:phone":"+39 0125 675205",
    "sg:postcode":"10012",
    "sg:province":"Torino",
    "sg:tags":[
        "motor-cars"
    ],
    "wof:name":"Val Wagen Ivrea S.r.l.",
    "wof:placetype":"venue"
},
  "geometry": {"coordinates":[7.9412474632,45.4693260193],"type":"Point"}
}