{
  "type": "Feature",
  "properties": {
    "iso:country":"IT",
    "sg:address":"22100 Como",
    "sg:city":"Como",
    "sg:orig_category":"Vetrate Artistiche",
    "sg:phone":"+39 031 521101",
    "sg:postcode":"22100",
    "sg:province":"Como",
    "wof:name":"Giada Di Civitillo Giada",
    "wof:placetype":"venue"
},
  "geometry": {"coordinates":[9.074316,45.785904],"type":"Point"}
}