{
  "type": "Feature",
  "properties": {
    "iso:country":"IT",
    "sg:address":"10123 Torino",
    "sg:city":"Torino",
    "sg:orig_category":"Servizi E Lavori Per Arredamento E Industria Del Legno",
    "sg:phone":"+39 011 812 3368",
    "sg:postcode":"10123",
    "sg:province":"Torino",
    "wof:name":"Antonio E Giorgio D'acci",
    "wof:placetype":"venue"
},
  "geometry": {"coordinates":[7.120077,45.126019],"type":"Point"}
}