{
  "type": "Feature",
  "properties": {
    "addr:full":"40128 Bologna Bologna Bologna 40128",
    "addr:postcode":"40128;40128",
    "iso:country":"IT",
    "sg:address":"40128 Bologna",
    "sg:city":"Bologna",
    "sg:orig_category":"Bevande, Vini E Liquori",
    "sg:phone":"+39 051 327222",
    "sg:postcode":"40128",
    "sg:province":"Bologna",
    "wof:name":"Meotti Giancarlo Sas Di Meotti Roberta & C.",
    "wof:placetype":"venue"
},
  "geometry": {"coordinates":[11.360015,44.536259],"type":"Point"}
}