{
  "type": "Feature",
  "properties": {
    "addr:full":"21023 Besozzo Besozzo Varese 21023",
    "addr:postcode":"21023;21023",
    "iso:country":"IT",
    "sg:address":"21023 Besozzo",
    "sg:city":"Besozzo",
    "sg:orig_category":"Lavorazioni Metalli, Stampaggio E Saldatura",
    "sg:phone":"+39 0332 970563",
    "sg:postcode":"21023",
    "sg:province":"Varese",
    "wof:name":"V2 Components Srl",
    "wof:placetype":"venue"
},
  "geometry": {"coordinates":[8.832591,45.816628],"type":"Point"}
}