{
  "type": "Feature",
  "properties": {
    "addr:full":"69, Via Volta Alessandro 61037 Mondolfo Mondolfo Pesaro E Urbino 61037",
    "addr:postcode":"61037;61037",
    "addr:street":"Via Volta Alessandro",
    "iso:country":"IT",
    "sg:address":"69, Via Volta Alessandro 61037 Mondolfo",
    "sg:city":"Mondolfo",
    "sg:classifiers":[
        {
            "category":"Shopping",
            "subcategory":"Clothing, Apparel, & Fashions",
            "type":"Retail Goods"
        }
    ],
    "sg:phone":"+39 0721 959811",
    "sg:postcode":"61037",
    "sg:province":"Pesaro E Urbino",
    "sg:tags":[
        "clothes"
    ],
    "wof:name":"New Come On F.lli Pelinga S.r.l.",
    "wof:placetype":"venue"
},
  "geometry": {"coordinates":[12.529803,43.633556],"type":"Point"}
}