{
  "type": "Feature",
  "properties": {
    "addr:full":"2, Via Salara 66020 San Giovanni Teatino San Giovanni Teatino Chieti 66020",
    "addr:postcode":"66020;66020",
    "addr:street":"Via Salara",
    "iso:country":"IT",
    "sg:address":"2, Via Salara 66020 San Giovanni Teatino",
    "sg:city":"San Giovanni Teatino",
    "sg:classifiers":[
        {
            "category":"Shopping",
            "subcategory":"Computers & Home Electronics",
            "type":"Retail Goods"
        }
    ],
    "sg:phone":"+39 085 446 0454",
    "sg:postcode":"66020",
    "sg:province":"Chieti",
    "sg:tags":[
        "electronic",
        "electrical",
        "equipment"
    ],
    "wof:name":"Elettrosistemi Srl",
    "wof:placetype":"venue"
},
  "geometry": {"coordinates":[14.167014,42.420704],"type":"Point"}
}