{
  "type": "Feature",
  "properties": {
    "iso:country":"IT",
    "sg:address":"Via Trieste 99 28066 Galliate",
    "sg:city":"Galliate",
    "sg:classifiers":[
        {
            "category":"Banks & Credit Unions",
            "subcategory":"Investment Brokerage",
            "type":"Services"
        }
    ],
    "sg:phone":"+39 0321 860424",
    "sg:postcode":"28066",
    "sg:province":"Novara",
    "sg:tags":[
        "textile",
        "machine"
    ],
    "sg:website":"www.brustio.com",
    "wof:name":"Officina Meccanica Brustio Antonio Srl",
    "wof:placetype":"venue"
},
  "geometry": {"coordinates":[8.701968,45.470528],"type":"Point"}
}