{
  "type": "Feature",
  "properties": {
    "addr:full":"24030 Villa D'adda Bergamo 24030",
    "addr:housenumber":"24030",
    "addr:postcode":"24030",
    "addr:street":"Villa",
    "iso:country":"IT",
    "sg:address":"24030 Villa D'adda",
    "sg:orig_category":"Servizi E Lavori Per Edilizia E Lavori Pubblici. Professionisti - Studi E Servizi Ed Associazioni Di Interesse Aziendale",
    "sg:phone":"+39 035 784850",
    "sg:postcode":"24030",
    "sg:province":"Bergamo",
    "wof:name":"So.ge.tec. Srl",
    "wof:placetype":"venue"
},
  "geometry": {"coordinates":[9.462833,45.715019],"type":"Point"}
}