{
  "type": "Feature",
  "properties": {
    "iso:country":"IT",
    "sg:address":"31023 Resana",
    "sg:city":"Resana",
    "sg:orig_category":"Termotecnica E Riscaldamento, Apparecchiature E Servizi",
    "sg:phone":"+39 0423 737923",
    "sg:postcode":"31023",
    "sg:province":"Treviso",
    "sg:website":"http://www.italianaradiatori.com",
    "wof:name":"Italiana Radiatori Spa",
    "wof:placetype":"venue"
},
  "geometry": {"coordinates":[11.951897,45.67329],"type":"Point"}
}