{
  "type": "Feature",
  "properties": {
    "iso:country":"IT",
    "sg:address":"Via Panagulis 7-z.art. 47010 San Martino In Strada",
    "sg:classifiers":[
        {
            "category":"Manufacturing",
            "subcategory":"Metals",
            "type":"Manufacturing & Wholesale Goods"
        }
    ],
    "sg:phone":"+39 0543 85170",
    "sg:postcode":"47010",
    "sg:province":"Forl\u00ec-Cesena",
    "sg:tags":[
        "processing"
    ],
    "wof:name":"Meccanica Orlandi Srl",
    "wof:placetype":"venue"
},
  "geometry": {"coordinates":[11.9804611206,43.9947662354],"type":"Point"}
}