{
  "type": "Feature",
  "properties": {
    "iso:country":"IT",
    "sg:address":"20093 Cologno Monzese",
    "sg:city":"Cologno Monzese",
    "sg:orig_category":"Dolciumi E Gelati",
    "sg:phone":"+39 02 253 1616",
    "sg:postcode":"20093",
    "sg:province":"Milano",
    "wof:name":"Spicci Antonio",
    "wof:placetype":"venue"
},
  "geometry": {"coordinates":[9.291772,45.530014],"type":"Point"}
}