{
  "type": "Feature",
  "properties": {
    "iso:country":"IT",
    "sg:address":"27, Via Provinciale 26847 Cornovecchio",
    "sg:classifiers":[
        {
            "category":"Food & Beverages",
            "subcategory":"Groceries & Convenience Stores",
            "type":"Retail Goods"
        }
    ],
    "sg:phone":"+39 0377 767057",
    "sg:postcode":"26847",
    "sg:province":"Lodi",
    "sg:tags":[
        "product",
        "related"
    ],
    "wof:name":"Maleo Carni (s.r.l.)",
    "wof:placetype":"venue"
},
  "geometry": {"coordinates":[9.7716264725,45.156036377],"type":"Point"}
}