{
  "type": "Feature",
  "properties": {
    "addr:full":"23887 Olgiate Molgora Olgiate Molgora Lecco 23887",
    "addr:postcode":"23887;23887",
    "iso:country":"IT",
    "sg:address":"23887 Olgiate Molgora",
    "sg:city":"Olgiate Molgora",
    "sg:classifiers":[
        {
            "category":"Shopping",
            "type":"Retail Goods"
        }
    ],
    "sg:phone":"+39 39039507105",
    "sg:postcode":"23887",
    "sg:province":"Lecco",
    "sg:tags":[
        "finished",
        "-",
        "metallic"
    ],
    "wof:name":"Tecnomeccanica Di Fumagalli E Blasi (s.n.c.)",
    "wof:placetype":"venue"
},
  "geometry": {"coordinates":[9.3678731918,45.7697601318],"type":"Point"}
}