{
  "type": "Feature",
  "properties": {
    "addr:full":"20127 Milano Milano Milano 20127",
    "addr:postcode":"20127;20127",
    "iso:country":"IT",
    "sg:address":"20127 Milano",
    "sg:city":"Milano",
    "sg:orig_category":"Servizi Editoriali",
    "sg:phone":"+39 02 289 5181",
    "sg:postcode":"20127",
    "sg:province":"Milano",
    "wof:name":"Zelo Sas Di Zerbi Roberto E Lodola Andrea E C.",
    "wof:placetype":"venue"
},
  "geometry": {"coordinates":[9.219731,45.495937],"type":"Point"}
}