{
  "type": "Feature",
  "properties": {
    "iso:country":"IT",
    "sg:address":"Via Borromei 9, L-20123 Milan, Mi",
    "sg:classifiers":[
        {
            "category":"Banks & Credit Unions",
            "subcategory":"Bank",
            "type":"Services"
        }
    ],
    "sg:phone":"+39 02 721331",
    "sg:postcode":"20123",
    "sg:province":"Milano",
    "wof:name":"Finreme Sim",
    "wof:placetype":"venue"
},
  "geometry": {"coordinates":[9.181909,45.464287],"type":"Point"}
}