{
  "type": "Feature",
  "properties": {
    "addr:full":"39031 Brunico Brunico Bolzano/Bozen 39031",
    "addr:postcode":"39031;39031",
    "iso:country":"IT",
    "sg:address":"39031 Brunico",
    "sg:city":"Brunico",
    "sg:classifiers":[
        {
            "category":"Manufacturing",
            "subcategory":"Metals",
            "type":"Manufacturing & Wholesale Goods"
        }
    ],
    "sg:phone":"+39 0474 551084",
    "sg:postcode":"39031",
    "sg:province":"Bolzano/Bozen",
    "sg:tags":[
        "forming",
        "working",
        "welding"
    ],
    "sg:website":"http://www.auroport.it",
    "wof:name":"Auroport Srl",
    "wof:placetype":"venue"
},
  "geometry": {"coordinates":[11.9258766174,46.7980613708],"type":"Point"}
}