{
  "type": "Feature",
  "properties": {
    "addr:full":"20093 Cologno Monzese Cologno Monzese Milano 20093",
    "addr:postcode":"20093;20093",
    "iso:country":"IT",
    "sg:address":"20093 Cologno Monzese",
    "sg:city":"Cologno Monzese",
    "sg:orig_category":"Servizi Culturali E Per Lo Spettacolo. Servizi Per Lo Sport E Il Tempo Libero. Servizi Per Aziende, Manifestazioni E Supporto Agli Scambi Commerciali",
    "sg:phone":"+39 02 2730 2312",
    "sg:postcode":"20093",
    "sg:province":"Milano",
    "sg:website":"http://www.csc-info.com",
    "wof:name":"Csc Allestimenti Srl",
    "wof:placetype":"venue"
},
  "geometry": {"coordinates":[9.279961,45.537773],"type":"Point"}
}