{
  "type": "Feature",
  "properties": {
    "addr:full":"20041 Agrate Brianza Agrate Brianza Milano 20041",
    "addr:postcode":"20041;20041",
    "iso:country":"IT",
    "sg:address":"20041 Agrate Brianza",
    "sg:city":"Agrate Brianza",
    "sg:orig_category":"Materiali Semilavorati Metallici",
    "sg:phone":"+39 039 689 0175",
    "sg:postcode":"20041",
    "sg:province":"Milano",
    "wof:name":"Colombo Carlo & C. (s.p.a.)",
    "wof:placetype":"venue"
},
  "geometry": {"coordinates":[9.328784,45.570068],"type":"Point"}
}