{
  "type": "Feature",
  "properties": {
    "iso:country":"IT",
    "sg:address":"Garlasco",
    "sg:classifiers":[
        {
            "category":"Banks & Credit Unions",
            "subcategory":"Bank",
            "type":"Services"
        }
    ],
    "sg:phone":"+39 0382 822005",
    "wof:name":"Cassa Di Risparmio, Delle Provincie Lombarde Spa",
    "wof:placetype":"venue"
},
  "geometry": {"coordinates":[8.924851,45.198463],"type":"Point"}
}