{
  "type": "Feature",
  "properties": {
    "addr:full":"Via Stradone 49, Moiano, 06060 Citta' Della Pieve, Pg Perugia 06060",
    "addr:housenumber":"49",
    "addr:postcode":"06060;06060",
    "addr:street":"Via Stradone;' Della Pieve Pg",
    "iso:country":"IT",
    "sg:address":"Via Stradone 49, Moiano, 06060 Citta' Della Pieve, Pg",
    "sg:classifiers":[
        {
            "category":"Banks & Credit Unions",
            "subcategory":"Bank",
            "type":"Services"
        }
    ],
    "sg:postcode":"06060",
    "sg:province":"Perugia",
    "wof:name":"Banca Di Credito Cooperativo Del Trasimeno Scrl",
    "wof:placetype":"venue"
},
  "geometry": {"coordinates":[12.389172,43.110703],"type":"Point"}
}