{
  "type": "Feature",
  "properties": {
    "addr:full":"Via De Gasperi 11, 20061 Carugate, Mi Carugate Milano 20061",
    "addr:housenumber":"11",
    "addr:postcode":"20061;20061",
    "addr:street":"Via De Gasperi;Carugate",
    "iso:country":"IT",
    "sg:address":"Via De Gasperi 11, 20061 Carugate, Mi",
    "sg:city":"Carugate",
    "sg:classifiers":[
        {
            "category":"Banks & Credit Unions",
            "subcategory":"Bank",
            "type":"Services"
        }
    ],
    "sg:phone":"+39 0292741",
    "sg:postcode":"20061",
    "sg:province":"Milano",
    "sg:website":"http://www.bcc.carugate.mi.it",
    "wof:name":"Banca Di Credito Cooperativo Di Carugate Scrl",
    "wof:placetype":"venue"
},
  "geometry": {"coordinates":[9.188141,45.463688],"type":"Point"}
}