{
  "type": "Feature",
  "properties": {
    "iso:country":"IT",
    "sg:address":"20121 Milano",
    "sg:city":"Milano",
    "sg:orig_category":"Case Editrici Musicali",
    "sg:phone":"+39 02 7600 0065",
    "sg:postcode":"20121",
    "sg:province":"Milano",
    "sg:website":"http://www.sonzogno.it",
    "wof:name":"Casa Musicale Sonzogno Sas",
    "wof:placetype":"venue"
},
  "geometry": {"coordinates":[9.193612,45.468826],"type":"Point"}
}