{
  "type": "Feature",
  "properties": {
    "iso:country":"IT",
    "sg:address":"26019 Vailate",
    "sg:city":"Vailate",
    "sg:orig_category":"Macchine, Impianti Ed Attrezzature Per Agricoltura E Zootecnia",
    "sg:phone":"+39 036 384109",
    "sg:postcode":"26019",
    "sg:province":"Cremona",
    "wof:name":"Danelli Fratelli",
    "wof:placetype":"venue"
},
  "geometry": {"coordinates":[9.599451,45.464859],"type":"Point"}
}