{
  "type": "Feature",
  "properties": {
    "iso:country":"IT",
    "sg:address":"21054 Fagnano Olona",
    "sg:city":"Fagnano Olona",
    "sg:orig_category":"Cinematografia E Radiotelevisione. Servizi Per Aziende, Manifestazioni E Supporto Agli Scambi Commerciali",
    "sg:phone":"+39 0331 612048",
    "sg:postcode":"21054",
    "sg:province":"Varese",
    "wof:name":"Studio Fox Sas",
    "wof:placetype":"venue"
},
  "geometry": {"coordinates":[8.851517,45.668266],"type":"Point"}
}