{
  "type": "Feature",
  "properties": {
    "iso:country":"IT",
    "sg:address":"24060 Chiuduno",
    "sg:city":"Chiuduno",
    "sg:classifiers":[
        {
            "category":"Health Services",
            "subcategory":"Health Practitioner",
            "type":"Services"
        }
    ],
    "sg:phone":"+39 035 839288",
    "sg:postcode":"24060",
    "sg:province":"Bergamo",
    "sg:tags":[
        "medici"
    ],
    "wof:name":"Brevi Paolo",
    "wof:placetype":"venue"
},
  "geometry": {"coordinates":[9.853564,45.650242],"type":"Point"}
}