{
  "type": "Feature",
  "properties": {
    "iso:country":"IT",
    "sg:address":"Piazza Mentana 4; Treviglio; 24047",
    "sg:city":"Treviglio",
    "sg:classifiers":[
        {
            "category":"Banks & Credit Unions",
            "subcategory":"Bank",
            "type":"Services"
        }
    ],
    "sg:phone":"+39 036 330 4122",
    "sg:postcode":"24047",
    "sg:province":"Bergamo",
    "wof:name":"Banca Nazionale Del Lavoro Spa",
    "wof:placetype":"venue"
},
  "geometry": {"coordinates":[9.594408,45.523865],"type":"Point"}
}