{
  "type": "Feature",
  "properties": {
    "iso:country":"IT",
    "sg:address":"25040 Corte Franca",
    "sg:city":"Corte Franca",
    "sg:classifiers":[
        {
            "category":"Wholesale",
            "subcategory":"Machinery & Supplies",
            "type":"Manufacturing & Wholesale Goods"
        }
    ],
    "sg:phone":"+39 030 984128",
    "sg:postcode":"25040",
    "sg:province":"Brescia",
    "sg:tags":[
        "component",
        "engineering",
        "material",
        "electrical"
    ],
    "wof:name":"O.m.t. Srl",
    "wof:placetype":"venue"
},
  "geometry": {"coordinates":[9.989232,45.631023],"type":"Point"}
}