{
  "type": "Feature",
  "properties": {
    "iso:country":"IT",
    "sg:address":"10, Via Europa-corsalone 52010 Chiusi Della Verna",
    "sg:city":"Chiusi della Verna",
    "sg:classifiers":[
        {
            "category":"Sports & Exercise",
            "subcategory":"Playing Field",
            "type":"Entertainment"
        }
    ],
    "sg:phone":"+39 0575 511175",
    "sg:postcode":"52010",
    "sg:province":"Arezzo",
    "sg:tags":[
        "game"
    ],
    "wof:name":"Artiflor",
    "wof:placetype":"venue"
},
  "geometry": {"coordinates":[11.83119,43.681564],"type":"Point"}
}