{
  "type": "Feature",
  "properties": {
    "iso:country":"IT",
    "sg:address":"26010 Dovera",
    "sg:city":"Dovera",
    "sg:orig_category":"Macchine, Impianti E Forniture Per Industria Grafica, Cartaria E Cartotecnica. Automazione E Macchine Per Ufficio",
    "sg:phone":"+39 0373 978298",
    "sg:postcode":"26010",
    "sg:province":"Cremona",
    "wof:name":"F.b.f. Service Snc",
    "wof:placetype":"venue"
},
  "geometry": {"coordinates":[9.541052,45.368374],"type":"Point"}
}