{
  "type": "Feature",
  "properties": {
    "iso:country":"IT",
    "sg:address":"80049 Somma Vesuviana",
    "sg:city":"Somma Vesuviana",
    "sg:orig_category":"Prodotti Alimentari. Agricoltura, Orticoltura E Floricoltura",
    "sg:phone":"+39 081 531 8578",
    "sg:postcode":"80049",
    "sg:province":"Napoli",
    "wof:name":"Fratelli Tuorto Sas Di Tuorto Aniello & C.",
    "wof:placetype":"venue"
},
  "geometry": {"coordinates":[14.4289512634,40.8913879395],"type":"Point"}
}