{
  "type": "Feature",
  "properties": {
    "addr:full":"20021 Bollate Bollate Milano 20021",
    "addr:postcode":"20021;20021",
    "iso:country":"IT",
    "sg:address":"20021 Bollate",
    "sg:city":"Bollate",
    "sg:orig_category":"Ospedali E Servizi Sanitari. Servizi Sociali",
    "sg:phone":"+39 02 359 0525",
    "sg:postcode":"20021",
    "sg:province":"Milano",
    "wof:name":"Consultorio Familiare",
    "wof:placetype":"venue"
},
  "geometry": {"coordinates":[9.10631,45.541565],"type":"Point"}
}