{
  "type": "Feature",
  "properties": {
    "addr:full":"62, C. Manzoni 12046 Monta' D'alba Cuneo 12046",
    "addr:housenumber":"62",
    "addr:postcode":"12046 monta;12046",
    "addr:street":"C. Manzoni",
    "iso:country":"IT",
    "sg:address":"62, C. Manzoni 12046 Monta' D'alba",
    "sg:classifiers":[
        {
            "category":"Parking",
            "subcategory":"Lot",
            "type":"Transportation"
        }
    ],
    "sg:phone":"+39 0173 976264",
    "sg:postcode":"12046",
    "sg:province":"Cuneo",
    "sg:tags":[
        "transport",
        "road"
    ],
    "sg:website":"http://www.moronemuratore.com",
    "wof:name":"Morone E Murature Snc",
    "wof:placetype":"venue"
},
  "geometry": {"coordinates":[7.547111,44.388798],"type":"Point"}
}