{
  "type": "Feature",
  "properties": {
    "iso:country":"IT",
    "sg:address":"20036 Meda",
    "sg:city":"Meda",
    "sg:orig_category":"Petroli, Gas E Combustibili. Termotecnica E Riscaldamento, Apparecchiature E Servizi",
    "sg:phone":"+39 036 270471",
    "sg:postcode":"20036",
    "sg:province":"Milano",
    "sg:website":"http://www.ambrogiomoro.it",
    "wof:name":"Ambrogio Moro Spa",
    "wof:placetype":"venue"
},
  "geometry": {"coordinates":[9.2124643326,45.4880142212],"type":"Point"}
}