{
  "type": "Feature",
  "properties": {
    "iso:country":"IT",
    "sg:address":"37050 Belfiore",
    "sg:city":"Belfiore",
    "sg:orig_category":"Macchine, Impianti Ed Attrezzature Per Agricoltura E Zootecnia",
    "sg:phone":"+39 045 613 4311",
    "sg:postcode":"37050",
    "sg:province":"Verona",
    "wof:name":"Storti International Srl",
    "wof:placetype":"venue"
},
  "geometry": {"coordinates":[11.09143,45.515686],"type":"Point"}
}