{
  "type": "Feature",
  "properties": {
    "iso:country":"IT",
    "sg:address":"17043 Carcare",
    "sg:city":"Carcare",
    "sg:orig_category":"Legno E Semilavorati",
    "sg:phone":"+39 019 510411",
    "sg:postcode":"17043",
    "sg:province":"Savona",
    "wof:name":"Segherie Scarrone Srl",
    "wof:placetype":"venue"
},
  "geometry": {"coordinates":[8.311162,44.346897],"type":"Point"}
}