{
  "type": "Feature",
  "properties": {
    "addr:full":"40012 Calderara Di Reno Calderara di Reno Bologna 40012",
    "addr:postcode":"40012;40012",
    "iso:country":"IT",
    "sg:address":"40012 Calderara Di Reno",
    "sg:city":"Calderara di Reno",
    "sg:classifiers":[
        {
            "category":"Manufacturing",
            "subcategory":"Motor Vehicles & Parts",
            "type":"Manufacturing & Wholesale Goods"
        }
    ],
    "sg:phone":"+39 051 725442",
    "sg:postcode":"40012",
    "sg:province":"Bologna",
    "sg:tags":[
        "vehicles",
        "accessory"
    ],
    "sg:website":"http://www.topperformances.com",
    "wof:name":"Motorparts Spa - Top Performances/dr. Racing Parts",
    "wof:placetype":"venue"
},
  "geometry": {"coordinates":[11.2648000717,44.5641174316],"type":"Point"}
}