{
  "type": "Feature",
  "properties": {
    "iso:country":"IT",
    "sg:address":"Via Lecce 7 59013 Montemurlo",
    "sg:city":"Montemurlo",
    "sg:orig_category":"Tricot Fabrics",
    "sg:phone":"+39 0574 720253",
    "sg:postcode":"59013",
    "sg:province":"Prato",
    "wof:name":"Manifattura Tessile Elite Di Piero Liberatori & C. Snc",
    "wof:placetype":"venue"
},
  "geometry": {"coordinates":[11.054747,43.909874],"type":"Point"}
}