{
  "type": "Feature",
  "properties": {
    "iso:country":"IT",
    "sg:address":"20154 Milano",
    "sg:city":"Milano",
    "sg:orig_category":"Forniture Per Uffici. Servizi Vari Di Interesse Pubblico",
    "sg:phone":"+39 02 331 9072",
    "sg:postcode":"20154",
    "sg:province":"Milano",
    "wof:name":"Tabacchi Montello Di Petronzi Katty",
    "wof:placetype":"venue"
},
  "geometry": {"coordinates":[9.1811437607,45.4804115295],"type":"Point"}
}