{
  "type": "Feature",
  "properties": {
    "iso:country":"IT",
    "sg:address":"25030 Rudiano",
    "sg:city":"Rudiano",
    "sg:orig_category":"Agricoltura, Orticoltura E Floricoltura",
    "sg:phone":"+39 030 716535",
    "sg:postcode":"25030",
    "sg:province":"Brescia",
    "wof:name":"Pilotti Chiara",
    "wof:placetype":"venue"
},
  "geometry": {"coordinates":[10.285615,45.482059],"type":"Point"}
}