{
  "type": "Feature",
  "properties": {
    "iso:country":"IT",
    "sg:address":"44047 Sant'agostino",
    "sg:city":"Dosso",
    "sg:orig_category":"Articoli Per Imballaggio E Confezionamento",
    "sg:phone":"+39 0532 848224",
    "sg:postcode":"44047",
    "sg:province":"Ferrara",
    "wof:name":"Cartotecnica Sei Srl",
    "wof:placetype":"venue"
},
  "geometry": {"coordinates":[11.381498,44.796173],"type":"Point"}
}