{
  "type": "Feature",
  "properties": {
    "iso:country":"IT",
    "sg:address":"1, Via M0lino 12030 Envie",
    "sg:city":"Envie",
    "sg:classifiers":[
        {
            "category":"Manufacturing",
            "subcategory":"Rubber & Plastics",
            "type":"Manufacturing & Wholesale Goods"
        }
    ],
    "sg:phone":"+39 0175 278266",
    "sg:postcode":"12030",
    "sg:province":"Cuneo",
    "sg:tags":[
        "packaging",
        "material",
        "-"
    ],
    "wof:name":"Plast Cuneo Sac Di Campeggio Lustri Lorella",
    "wof:placetype":"venue"
},
  "geometry": {"coordinates":[7.5471105576,44.38879776],"type":"Point"}
}