{
  "type": "Feature",
  "properties": {
    "addr:full":"04022 Fondi Fondi Latina 04022",
    "addr:postcode":"04022;04022",
    "iso:country":"IT",
    "sg:address":"04022 Fondi",
    "sg:city":"Fondi",
    "sg:orig_category":"Non-classified Establishments",
    "sg:phone":"+39 0771 500892",
    "sg:postcode":"04022",
    "sg:province":"Latina",
    "wof:name":"Mobil De Santis Srl",
    "wof:placetype":"venue"
},
  "geometry": {"coordinates":[13.240773,41.293541],"type":"Point"}
}