{
  "type": "Feature",
  "properties": {
    "iso:country":"IT",
    "sg:address":"20093 Cologno Monzese",
    "sg:city":"Cologno Monzese",
    "sg:orig_category":"Climatizzazione E Condizionamento, Apparecchiature E Servizi",
    "sg:phone":"+39 02 2730 1358",
    "sg:postcode":"20093",
    "sg:province":"Milano",
    "wof:name":"Air Interclima Sas",
    "wof:placetype":"venue"
},
  "geometry": {"coordinates":[9.287419,45.524223],"type":"Point"}
}