{
  "type": "Feature",
  "properties": {
    "iso:country":"IT",
    "sg:address":"20154 Milano",
    "sg:city":"Milano",
    "sg:orig_category":"Arte Ed Artigianato Artistico",
    "sg:phone":"+39 02 342205",
    "sg:postcode":"20154",
    "sg:province":"Milano",
    "wof:name":"Frangi Reale",
    "wof:placetype":"venue"
},
  "geometry": {"coordinates":[9.169292,45.487896],"type":"Point"}
}