{
  "type": "Feature",
  "properties": {
    "addr:full":"32100 Belluno Belluno Belluno 32100",
    "addr:postcode":"32100;32100",
    "iso:country":"IT",
    "sg:address":"32100 Belluno",
    "sg:city":"Belluno",
    "sg:orig_category":"Apparecchiature Ed Attrezzature Meccaniche",
    "sg:phone":"+39 0437 931252",
    "sg:postcode":"32100",
    "sg:province":"Belluno",
    "wof:name":"Oleomec Srl",
    "wof:placetype":"venue"
},
  "geometry": {"coordinates":[12.249158,46.170296],"type":"Point"}
}