{
  "type": "Feature",
  "properties": {
    "iso:country":"IT",
    "sg:address":"20065 Inzago",
    "sg:city":"Inzago",
    "sg:orig_category":"Forniture E Materiali Per Imballaggio E Confezionamento. Forniture Per Uffici. Forniture Per Attivita' Commerciali Ed Artigianali",
    "sg:phone":"+39 02 954 9681",
    "sg:postcode":"20065",
    "sg:province":"Milano",
    "wof:name":"Ari Di Villa Srl",
    "wof:placetype":"venue"
},
  "geometry": {"coordinates":[9.4771509171,45.5389328003],"type":"Point"}
}