{
  "type": "Feature",
  "properties": {
    "iso:country":"IT",
    "sg:address":"31023 Resana",
    "sg:city":"Resana",
    "sg:orig_category":"Illuminazione - Apparecchiature",
    "sg:phone":"+39 0423 715266",
    "sg:postcode":"31023",
    "sg:province":"Treviso",
    "sg:website":"http://www.lalternativa.com",
    "wof:name":"L'alternativa Srl",
    "wof:placetype":"venue"
},
  "geometry": {"coordinates":[11.968021,45.627796],"type":"Point"}
}