{
  "type": "Feature",
  "properties": {
    "addr:full":"98, Via Casaloldo 46041 Asola Asola Mantova 46041",
    "addr:postcode":"46041;46041",
    "addr:street":"Via Casaloldo",
    "iso:country":"IT",
    "sg:address":"98, Via Casaloldo 46041 Asola",
    "sg:city":"Asola",
    "sg:classifiers":[
        {
            "category":"Autos & Motor Vehicles",
            "subcategory":"Automobile Sales",
            "type":"Retail Goods"
        }
    ],
    "sg:phone":"+39 0376 748114",
    "sg:postcode":"46041",
    "sg:province":"Mantova",
    "sg:tags":[
        "equipment",
        "transport"
    ],
    "wof:name":"Tecno Telai Ciclo S.r.l.",
    "wof:placetype":"venue"
},
  "geometry": {"coordinates":[10.415451,45.221188],"type":"Point"}
}