{
  "type": "Feature",
  "properties": {
    "iso:country":"IT",
    "sg:address":"Corso Ara Di Giove 128; Pedara; 95030",
    "sg:city":"Pedara",
    "sg:classifiers":[
        {
            "category":"Banks & Credit Unions",
            "subcategory":"Bank",
            "type":"Services"
        }
    ],
    "sg:phone":"+39 095 915336",
    "sg:postcode":"95030",
    "sg:province":"Catania",
    "wof:name":"Banca Popolare Di Belpasso",
    "wof:placetype":"venue"
},
  "geometry": {"coordinates":[15.060741,37.618137],"type":"Point"}
}