{
  "type": "Feature",
  "properties": {
    "iso:country":"IT",
    "sg:address":"Piazza Dante 21/22, 20050 Lesmo, Mi",
    "sg:city":"Lesmo",
    "sg:classifiers":[
        {
            "category":"Banks & Credit Unions",
            "subcategory":"Bank",
            "type":"Services"
        }
    ],
    "sg:postcode":"20050",
    "sg:province":"Milano",
    "wof:name":"Banca Di Credito Cooperativo Di Lesmo",
    "wof:placetype":"venue"
},
  "geometry": {"coordinates":[9.308458,45.649986],"type":"Point"}
}