{
  "type": "Feature",
  "properties": {
    "iso:country":"IT",
    "sg:address":"Via Volpina 16 21010 Besnate",
    "sg:city":"Besnate",
    "sg:classifiers":[
        {
            "category":"Wholesale",
            "subcategory":"Furniture",
            "type":"Manufacturing & Wholesale Goods"
        }
    ],
    "sg:phone":"+39 0331 27991",
    "sg:postcode":"21010",
    "sg:province":"Varese",
    "sg:tags":[
        "nonwovens",
        "industry"
    ],
    "wof:name":"Tessutitalia Srl",
    "wof:placetype":"venue"
},
  "geometry": {"coordinates":[8.772309,45.692493],"type":"Point"}
}