{
  "type": "Feature",
  "properties": {
    "iso:country":"IT",
    "sg:address":"39043 Chiusa",
    "sg:city":"Chiusa",
    "sg:orig_category":"Servizi Per Lo Sport E Il Tempo Libero. Alberghi E Strutture Extra Alberghiere",
    "sg:phone":"+39 348 260 8960",
    "sg:postcode":"39043",
    "sg:province":"Bolzano/Bozen",
    "wof:name":"Rifugio St\u00d6ffl H\u00dctte",
    "wof:placetype":"venue"
},
  "geometry": {"coordinates":[11.358005,46.496716],"type":"Point"}
}