{
  "type": "Feature",
  "properties": {
    "iso:country":"IT",
    "sg:address":"Via A. Spazzoli 48 47015 Modigliana",
    "sg:city":"Modigliana",
    "sg:classifiers":[
        {
            "category":"Government",
            "subcategory":"Department Of Motor Vehicles",
            "type":"Public Place"
        }
    ],
    "sg:phone":"+39 0546 941117",
    "sg:postcode":"47015",
    "sg:province":"Forl\u00ec-Cesena",
    "sg:tags":[
        "caterpillar",
        "chassis",
        "excavator"
    ],
    "wof:name":"Macmoter Spa",
    "wof:placetype":"venue"
},
  "geometry": {"coordinates":[11.980461,43.994766],"type":"Point"}
}