{
  "type": "Feature",
  "properties": {
    "addr:full":"40124 Bologna Bologna Bologna 40124",
    "addr:postcode":"40124;40124",
    "iso:country":"IT",
    "sg:address":"40124 Bologna",
    "sg:city":"Bologna",
    "sg:classifiers":[
        {
            "category":"Government",
            "subcategory":"Office",
            "type":"Public Place"
        }
    ],
    "sg:phone":"+39 051 224392",
    "sg:postcode":"40124",
    "sg:province":"Bologna",
    "sg:tags":[
        "e",
        "lo",
        "tempo",
        "libero",
        "per",
        "spettacolo",
        "servizi",
        "culturali",
        "sport",
        "il"
    ],
    "sg:website":"http://www.zingaroclub.com",
    "wof:name":"Zingaro' Soc.coop.r.l.",
    "wof:placetype":"venue"
},
  "geometry": {"coordinates":[11.348382,44.491318],"type":"Point"}
}