{
  "type": "Feature",
  "properties": {
    "addr:full":"Via Quattro Novembre 233 25010 Borgosatollo Borgosatollo Brescia 25010",
    "addr:housenumber":"233",
    "addr:postcode":"25010;25010",
    "addr:street":"Via Quattro Novembre",
    "iso:country":"IT",
    "sg:address":"Via Quattro Novembre 233 25010 Borgosatollo",
    "sg:city":"Borgosatollo",
    "sg:classifiers":[
        {
            "category":"Manufacturing",
            "subcategory":"Textiles",
            "type":"Manufacturing & Wholesale Goods"
        }
    ],
    "sg:phone":"+39 030 641217",
    "sg:postcode":"25010",
    "sg:province":"Brescia",
    "sg:tags":[
        "finishing",
        "roller"
    ],
    "wof:name":"Barra S.r.l.",
    "wof:placetype":"venue"
},
  "geometry": {"coordinates":[10.222958,45.539829],"type":"Point"}
}