{
  "type": "Feature",
  "properties": {
    "iso:country":"IT",
    "sg:address":"20, Contrada Campiglione 63023 Fermo",
    "sg:city":"Campiglione",
    "sg:classifiers":[
        {
            "category":"Personal",
            "subcategory":"Shoe Repair & Shine",
            "type":"Services"
        }
    ],
    "sg:phone":"+39 39073460881",
    "sg:postcode":"63023",
    "sg:province":"Ascoli Piceno",
    "sg:tags":[
        "leather"
    ],
    "wof:name":"Marc Donna Spa",
    "wof:placetype":"venue"
},
  "geometry": {"coordinates":[13.655121,43.170639],"type":"Point"}
}