{
  "type": "Feature",
  "properties": {
    "addr:full":"04012 Cisterna Di Latina Cisterna di Latina Latina 04012",
    "addr:postcode":"04012;04012",
    "iso:country":"IT",
    "sg:address":"04012 Cisterna Di Latina",
    "sg:city":"Cisterna di Latina",
    "sg:orig_category":"Carta E Cartone Ondulato",
    "sg:phone":"+39 06 9687 2005",
    "sg:postcode":"04012",
    "sg:province":"Latina",
    "wof:name":"M.p.s. Recycling",
    "wof:placetype":"venue"
},
  "geometry": {"coordinates":[12.828477,41.575401],"type":"Point"}
}