{
  "type": "Feature",
  "properties": {
    "iso:country":"IT",
    "sg:address":"Via Po 66; Ferrara",
    "sg:classifiers":[
        {
            "category":"Banks & Credit Unions",
            "subcategory":"Bank",
            "type":"Services"
        }
    ],
    "sg:phone":"+39 0532 771980",
    "wof:name":"Cassa Di Risparmio In Bologna Spa",
    "wof:placetype":"venue"
},
  "geometry": {"coordinates":[11.621659,44.835564],"type":"Point"}
}