{
  "type": "Feature",
  "properties": {
    "addr:full":"20095 Cusano Milanino Cusano Milanino Milano 20095",
    "addr:postcode":"20095;20095",
    "iso:country":"IT",
    "sg:address":"20095 Cusano Milanino",
    "sg:city":"Cusano Milanino",
    "sg:orig_category":"Motori Ed Organi Di Trasmissione",
    "sg:phone":"+39 02 6640 0503",
    "sg:postcode":"20095",
    "sg:province":"Milano",
    "wof:name":"Moltrasio Massimo",
    "wof:placetype":"venue"
},
  "geometry": {"coordinates":[9.1849403381,45.5448532104],"type":"Point"}
}