{
  "type": "Feature",
  "properties": {
    "addr:full":"20063 Cernusco Sul Naviglio Cernusco sul Naviglio Milano 20063",
    "addr:postcode":"20063;20063",
    "iso:country":"IT",
    "sg:address":"20063 Cernusco Sul Naviglio",
    "sg:city":"Cernusco sul Naviglio",
    "sg:orig_category":"Materiali Edili",
    "sg:phone":"+39 02 924 2093",
    "sg:postcode":"20063",
    "sg:province":"Milano",
    "wof:name":"Cave Merlini S.p.a.",
    "wof:placetype":"venue"
},
  "geometry": {"coordinates":[9.289932,45.517666],"type":"Point"}
}