{
  "type": "Feature",
  "properties": {
    "addr:full":"54, Via Pasitea 84017 Positano Positano Salerno 84017",
    "addr:postcode":"84017;84017",
    "addr:street":"Via Pasitea",
    "iso:country":"IT",
    "sg:address":"54, Via Pasitea 84017 Positano",
    "sg:city":"Positano",
    "sg:classifiers":[
        {
            "category":"Real Estate",
            "subcategory":"Architect",
            "type":"Services"
        }
    ],
    "sg:phone":"+39 39089811818",
    "sg:postcode":"84017",
    "sg:province":"Salerno",
    "sg:tags":[
        "textile",
        "clothing"
    ],
    "wof:name":"Tutino Rita",
    "wof:placetype":"venue"
},
  "geometry": {"coordinates":[14.482939,40.629292],"type":"Point"}
}