{
  "type": "Feature",
  "properties": {
    "iso:country":"IT",
    "sg:address":"84091 Battipaglia",
    "sg:city":"Battipaglia",
    "sg:orig_category":"Lavorazioni Meccaniche E Servizi",
    "sg:phone":"+39 0828 302001",
    "sg:postcode":"84091",
    "sg:province":"Salerno",
    "wof:name":"Officina Pietrasanta La Folgore Srl",
    "wof:placetype":"venue"
},
  "geometry": {"coordinates":[14.950567,40.593929],"type":"Point"}
}