{
  "type": "Feature",
  "properties": {
    "iso:country":"IT",
    "sg:address":"1, Via Delle Due Porte 20087 Robecco Sul Naviglio",
    "sg:city":"Robecco sul Naviglio",
    "sg:classifiers":[
        {
            "category":"Professional",
            "subcategory":"Engineering",
            "type":"Services"
        }
    ],
    "sg:phone":"+39 39029469821",
    "sg:postcode":"20087",
    "sg:province":"Milano",
    "sg:tags":[
        "machine",
        "-",
        "mechanical"
    ],
    "wof:name":"Strapex S.r.l.",
    "wof:placetype":"venue"
},
  "geometry": {"coordinates":[8.892162,45.42889],"type":"Point"}
}