{
  "type": "Feature",
  "properties": {
    "iso:country":"IT",
    "sg:address":"47900 Rimini",
    "sg:city":"Rimini",
    "sg:orig_category":"Autoradio",
    "sg:phone":"+39 0541 391052",
    "sg:postcode":"47900",
    "sg:province":"Rimini",
    "wof:name":"Centro Servizi Auto",
    "wof:placetype":"venue"
},
  "geometry": {"coordinates":[12.5827,44.061108],"type":"Point"}
}