{
  "type": "Feature",
  "properties": {
    "addr:full":"20128 Milano Milano Milano 20128",
    "addr:postcode":"20128;20128",
    "iso:country":"IT",
    "sg:address":"20128 Milano",
    "sg:city":"Milano",
    "sg:orig_category":"Galvanotecnica",
    "sg:phone":"+39 02 2700 4680",
    "sg:postcode":"20128",
    "sg:province":"Milano",
    "wof:name":"Bertolesi Mauro",
    "wof:placetype":"venue"
},
  "geometry": {"coordinates":[9.225398,45.509415],"type":"Point"}
}