{
  "type": "Feature",
  "properties": {
    "iso:country":"IT",
    "sg:address":"40063 Monghidoro",
    "sg:city":"Monghidoro",
    "sg:orig_category":"Arredamenti - Vendita Al Dettaglio",
    "sg:phone":"+39 051 655 5239",
    "sg:postcode":"40063",
    "sg:province":"Bologna",
    "wof:name":"Mobilificio Naldi Srl",
    "wof:placetype":"venue"
},
  "geometry": {"coordinates":[11.33176,44.221127],"type":"Point"}
}