{
  "type": "Feature",
  "properties": {
    "iso:country":"IT",
    "sg:address":"82, Via Orzinuovi 25125 Brescia",
    "sg:city":"Brescia",
    "sg:classifiers":[
        {
            "category":"Food & Beverages",
            "subcategory":"Groceries & Convenience Stores",
            "type":"Retail Goods"
        }
    ],
    "sg:phone":"+39 030 353 0565",
    "sg:postcode":"25125",
    "sg:province":"Brescia",
    "sg:tags":[
        "product",
        "related"
    ],
    "wof:name":"Arici Savino & C. (s.n.c.)",
    "wof:placetype":"venue"
},
  "geometry": {"coordinates":[10.1763954163,45.532989502],"type":"Point"}
}