{
  "type": "Feature",
  "properties": {
    "iso:country":"IT",
    "sg:address":"Via Oxilia Nino 26 20127 Milano",
    "sg:city":"Milano",
    "sg:orig_category":"Block Bonding Appliances For Bookbinding",
    "sg:phone":"+39 02 2614 8880",
    "sg:postcode":"20127",
    "sg:province":"Milano",
    "sg:website":"www.generalsystem.com",
    "wof:name":"General System Company Srl",
    "wof:placetype":"venue"
},
  "geometry": {"coordinates":[9.213301,45.491489],"type":"Point"}
}