{
  "type": "Feature",
  "properties": {
    "iso:country":"IT",
    "sg:address":"84011 Amalfi",
    "sg:city":"Amalfi",
    "sg:orig_category":"Dolciumi E Gelati",
    "sg:phone":"+39 089 873211",
    "sg:postcode":"84011",
    "sg:province":"Salerno",
    "sg:website":"http://www.positano.starnet.it/cata",
    "wof:name":"C.a.t.a. Soc.coop.r.l.",
    "wof:placetype":"venue"
},
  "geometry": {"coordinates":[14.599497,40.639927],"type":"Point"}
}