{
  "type": "Feature",
  "properties": {
    "addr:full":"53049 Torrita Di Siena Torrita di Siena Siena 53049",
    "addr:postcode":"53049;53049",
    "iso:country":"IT",
    "sg:address":"53049 Torrita Di Siena",
    "sg:city":"Torrita di Siena",
    "sg:orig_category":"Manufacturers: Prefabbricati",
    "sg:phone":"+39 0577 624068",
    "sg:postcode":"53049",
    "sg:province":"Siena",
    "sg:website":"http://www.peruzzi3.it",
    "wof:name":"Peruzzi 3 Srl",
    "wof:placetype":"venue"
},
  "geometry": {"coordinates":[11.782633,43.168102],"type":"Point"}
}