{
  "type": "Feature",
  "properties": {
    "addr:full":"8, Via Montebello 40121 Bologna Bologna Bologna 40121",
    "addr:postcode":"40121;40121",
    "addr:street":"Via Montebello",
    "iso:country":"IT",
    "sg:address":"8, Via Montebello 40121 Bologna",
    "sg:city":"Bologna",
    "sg:classifiers":[
        {
            "category":"Travel",
            "subcategory":"Travel Agent",
            "type":"Entertainment"
        }
    ],
    "sg:phone":"+39 39051249361",
    "sg:postcode":"40121",
    "sg:province":"Bologna",
    "sg:tags":[
        "business"
    ],
    "wof:name":"Albergo Royal Hotel Carlton",
    "wof:placetype":"venue"
},
  "geometry": {"coordinates":[11.342675,44.502571],"type":"Point"}
}