{
  "type": "Feature",
  "properties": {
    "addr:full":"Via Kravogl 6 39100 Bolzano Bolzano Bolzano/Bozen 39100",
    "addr:housenumber":"6",
    "addr:postcode":"39100;39100",
    "addr:street":"Via Kravogl",
    "iso:country":"IT",
    "sg:address":"Via Kravogl 6 39100 Bolzano",
    "sg:city":"Bolzano",
    "sg:orig_category":"Escalators, Moving Stairways, Travelators",
    "sg:phone":"+39 0471 200625",
    "sg:postcode":"39100",
    "sg:province":"Bolzano/Bozen",
    "sg:website":"www.lenzi.it",
    "wof:name":"Lenzi Spa",
    "wof:placetype":"venue"
},
  "geometry": {"coordinates":[11.328239,46.461643],"type":"Point"}
}