{
  "type": "Feature",
  "properties": {
    "iso:country":"IT",
    "sg:address":"Via Pra Delle Vigne 249 21030 Grantola",
    "sg:city":"Grantola",
    "sg:classifiers":[
        {
            "category":"Building & Trades",
            "subcategory":"Pest Control",
            "type":"Services"
        }
    ],
    "sg:phone":"+39 0332 576842",
    "sg:postcode":"21030",
    "sg:province":"Varese",
    "sg:tags":[
        "line",
        "machines",
        "trimming"
    ],
    "sg:website":"www.fassantagostino.it",
    "wof:name":"S.a.s. Santagostini Attrezzature Speciali Di Santagostini Luca",
    "wof:placetype":"venue"
},
  "geometry": {"coordinates":[8.770238,45.950893],"type":"Point"}
}