{
  "type": "Feature",
  "properties": {
    "addr:full":"03040 Ausonia Ausonia Frosinone 03040",
    "addr:postcode":"03040;03040",
    "iso:country":"IT",
    "sg:address":"03040 Ausonia",
    "sg:city":"Ausonia",
    "sg:orig_category":"Agenzie Immobiliari",
    "sg:phone":"+39 0776 952716",
    "sg:postcode":"03040",
    "sg:province":"Frosinone",
    "wof:name":"Edil Castelli Snc",
    "wof:placetype":"venue"
},
  "geometry": {"coordinates":[13.349755,41.631283],"type":"Point"}
}