{
  "type": "Feature",
  "properties": {
    "iso:country":"IT",
    "sg:address":"10093 Collegno",
    "sg:city":"Collegno",
    "sg:orig_category":"Materiali Edili",
    "sg:postcode":"10093",
    "sg:province":"Torino",
    "wof:name":"De Angelis F.lli Di De Angelis Antonio E C. (s.a.s.)",
    "wof:placetype":"venue"
},
  "geometry": {"coordinates":[7.594224,45.078407],"type":"Point"}
}