{
  "type": "Feature",
  "properties": {
    "iso:country":"IT",
    "sg:address":"137, Rione Martiri 83031 Ariano Irpino",
    "sg:city":"Ariano Irpino",
    "sg:classifiers":[
        {
            "category":"Professional",
            "subcategory":"Engineering",
            "type":"Services"
        }
    ],
    "sg:phone":"+39 0825 828873",
    "sg:postcode":"83031",
    "sg:province":"Avellino",
    "sg:tags":[
        "machine",
        "-",
        "mechanical"
    ],
    "wof:name":"Commerciale Scaperrotta Srl",
    "wof:placetype":"venue"
},
  "geometry": {"coordinates":[15.105429,41.16386],"type":"Point"}
}