{
  "type": "Feature",
  "properties": {
    "addr:full":"80059 Torre Del Greco Torre del Greco Napoli 80059",
    "addr:postcode":"80059;80059",
    "iso:country":"IT",
    "sg:address":"80059 Torre Del Greco",
    "sg:city":"Torre del Greco",
    "sg:orig_category":"Banche E Servizi Finanziari",
    "sg:phone":"+39 081 849 3311",
    "sg:postcode":"80059",
    "sg:province":"Napoli",
    "wof:name":"Noto Immobiliare Sas",
    "wof:placetype":"venue"
},
  "geometry": {"coordinates":[14.338956,40.820759],"type":"Point"}
}