{
  "type": "Feature",
  "properties": {
    "iso:country":"IT",
    "sg:address":"70122 Bari",
    "sg:city":"Bari",
    "sg:orig_category":"Servizi Culturali E Per Lo Spettacolo. Cine-foto-ottica",
    "sg:phone":"+39 080 523 2567",
    "sg:postcode":"70122",
    "sg:province":"Bari",
    "wof:name":"Foto Mira Di Garbellano Paolo",
    "wof:placetype":"venue"
},
  "geometry": {"coordinates":[16.8665142059,41.1288604736],"type":"Point"}
}