{
  "type": "Feature",
  "properties": {
    "addr:full":"23, V. Campo Di Maggio21022 Brunello Varese 21022",
    "addr:housenumber":"23",
    "addr:postcode":"21022",
    "addr:street":"V. Campo Di Maggio21022",
    "iso:country":"IT",
    "sg:address":"23, V. Campo Di Maggio21022 Brunello",
    "sg:classifiers":[
        {
            "category":"Manufacturing",
            "subcategory":"Metals",
            "type":"Manufacturing & Wholesale Goods"
        }
    ],
    "sg:phone":"+39 0332 461744",
    "sg:postcode":"21022",
    "sg:province":"Varese",
    "sg:tags":[
        "processing"
    ],
    "sg:website":"http://www.fabriziocarlotto.com",
    "wof:name":"Fabrizio Carlotto Srl",
    "wof:placetype":"venue"
},
  "geometry": {"coordinates":[8.8027267456,45.7680244446],"type":"Point"}
}