{
  "type": "Feature",
  "properties": {
    "iso:country":"IT",
    "sg:address":"46029 Rivarolo Mantovano",
    "sg:city":"Riva",
    "sg:orig_category":"Campeggio. Automobili E Mezzi Di Trasporto",
    "sg:phone":"+39 0376 99590",
    "sg:postcode":"46029",
    "sg:province":"Mantova",
    "sg:website":"http://www.autohome.it",
    "wof:name":"Zifer Di Fercodini & C. Snc",
    "wof:placetype":"venue"
},
  "geometry": {"coordinates":[10.793836,45.148235],"type":"Point"}
}