{
  "type": "Feature",
  "properties": {
    "addr:full":"Zona P.i.p. 70025 Grumo Appula Grumo Appula Bari 70025",
    "addr:postcode":"70025;70025",
    "addr:street":"Zona P.I.P.",
    "iso:country":"IT",
    "sg:address":"Zona P.i.p. 70025 Grumo Appula",
    "sg:city":"Grumo Appula",
    "sg:classifiers":[
        {
            "category":"Food & Beverages",
            "subcategory":"Groceries & Convenience Stores",
            "type":"Retail Goods"
        }
    ],
    "sg:phone":"+39 080623136662",
    "sg:postcode":"70025",
    "sg:province":"Bari",
    "sg:tags":[
        "product",
        "related"
    ],
    "sg:website":"http://www.paginegialle.it/",
    "wof:name":"Frantoio Oleario Palladino Snc",
    "wof:placetype":"venue"
},
  "geometry": {"coordinates":[16.8692913055,41.1260528564],"type":"Point"}
}