{
  "type": "Feature",
  "properties": {
    "iso:country":"IT",
    "sg:address":"49, Via Rimini 59100 Prato",
    "sg:city":"Prato",
    "sg:classifiers":[
        {
            "category":"Shopping",
            "subcategory":"Computers & Home Electronics",
            "type":"Retail Goods"
        }
    ],
    "sg:phone":"+39 0574 607434",
    "sg:postcode":"59100",
    "sg:province":"Prato",
    "sg:tags":[
        "electronic",
        "electrical",
        "equipment"
    ],
    "wof:name":"Co.be. (s.n.c.)",
    "wof:placetype":"venue"
},
  "geometry": {"coordinates":[11.072657,43.877434],"type":"Point"}
}