{
  "type": "Feature",
  "properties": {
    "iso:country":"IT",
    "sg:address":"55100 Lucca",
    "sg:city":"Lucca",
    "sg:orig_category":"Depurazione E Trattamento Delle Acque - Impianti Ed Apparecchi",
    "sg:phone":"+39 0583 331599",
    "sg:postcode":"55100",
    "sg:province":"Lucca",
    "wof:name":"Acquaservice Sas",
    "wof:placetype":"venue"
},
  "geometry": {"coordinates":[10.506303,43.850742],"type":"Point"}
}