{
  "type": "Feature",
  "properties": {
    "addr:full":"50145 Firenze Firenze Firenze 50145",
    "addr:postcode":"50145;50145",
    "iso:country":"IT",
    "sg:address":"50145 Firenze",
    "sg:city":"Firenze",
    "sg:orig_category":"Fonderie",
    "sg:phone":"+39 055 374124",
    "sg:postcode":"50145",
    "sg:province":"Firenze",
    "sg:website":"http://www.artigianamodelli.it",
    "wof:name":"Artigiana Modelli Snc",
    "wof:placetype":"venue"
},
  "geometry": {"coordinates":[11.2145814896,43.7088127136],"type":"Point"}
}