{
  "type": "Feature",
  "properties": {
    "iso:country":"IT",
    "sg:address":"159, Corso Vittorio Emanuele 80059 Torre Del Greco",
    "sg:city":"Torre del Greco",
    "sg:classifiers":[
        {
            "category":"Wholesale",
            "subcategory":"Machinery & Supplies",
            "type":"Manufacturing & Wholesale Goods"
        }
    ],
    "sg:phone":"+39 081 849 6997",
    "sg:postcode":"80059",
    "sg:province":"Napoli",
    "sg:tags":[
        "equipment",
        "-",
        "instrument",
        "measurement"
    ],
    "wof:name":"Carlo Gavazzi Pantec Spa",
    "wof:placetype":"venue"
},
  "geometry": {"coordinates":[14.338956,40.820759],"type":"Point"}
}