{
  "type": "Feature",
  "properties": {
    "iso:country":"IT",
    "sg:address":"41037 Mirandola",
    "sg:city":"Mirandola",
    "sg:orig_category":"Macchine Utensili E Impianti",
    "sg:phone":"+39 0535 22357",
    "sg:postcode":"41037",
    "sg:province":"Modena",
    "wof:name":"Officina Meccanica Romagnoli Srl",
    "wof:placetype":"venue"
},
  "geometry": {"coordinates":[11.08847,44.928791],"type":"Point"}
}