{
  "type": "Feature",
  "properties": {
    "iso:country":"IT",
    "sg:address":"80010 Quarto",
    "sg:city":"Quarto",
    "sg:orig_category":"Elettrotecnica Industriale, Prodotti E Apparecchiature. Impianti, Attrezzature E Forniture Sanitarie Ed Ospedaliere. Forniture Per Attivita' Industriali",
    "sg:phone":"+39 081 876 8433",
    "sg:postcode":"80010",
    "sg:province":"Napoli",
    "sg:website":"http://www.paginegialle.it/angelomoscarino",
    "wof:name":"Moscarino Angelo",
    "wof:placetype":"venue"
},
  "geometry": {"coordinates":[14.133904,40.878086],"type":"Point"}
}