{
  "type": "Feature",
  "properties": {
    "addr:full":"30032 Fiesso D'artico Venezia 30032",
    "addr:postcode":"30032;30032",
    "iso:country":"IT",
    "sg:address":"30032 Fiesso D'artico",
    "sg:orig_category":"Forniture Per Abbigliamento E Pelletterie",
    "sg:phone":"+39 049 502845",
    "sg:postcode":"30032",
    "sg:province":"Venezia",
    "wof:name":"Newplastic S.r.l.",
    "wof:placetype":"venue"
},
  "geometry": {"coordinates":[12.0376939774,45.4219512939],"type":"Point"}
}