{
  "type": "Feature",
  "properties": {
    "iso:country":"IT",
    "sg:address":"24126 Bergamo",
    "sg:city":"Bergamo",
    "sg:orig_category":"Gioielleria, Oreficeria E Argenteria",
    "sg:phone":"+39 035 316537",
    "sg:postcode":"24126",
    "sg:province":"Bergamo",
    "wof:name":"Scanzi Isidoro",
    "wof:placetype":"venue"
},
  "geometry": {"coordinates":[9.657347,45.671482],"type":"Point"}
}