{
  "type": "Feature",
  "properties": {
    "iso:country":"IT",
    "sg:address":"25050 Rodengo Saiano",
    "sg:orig_category":"Macchine Utensili E Impianti",
    "sg:phone":"+39 030 610540",
    "sg:postcode":"25050",
    "sg:province":"Brescia",
    "wof:name":"Sergi S.r.l.",
    "wof:placetype":"venue"
},
  "geometry": {"coordinates":[10.124055,45.577286],"type":"Point"}
}