{
  "type": "Feature",
  "properties": {
    "iso:country":"IT",
    "sg:address":"93016 Riesi",
    "sg:city":"Riesi",
    "sg:orig_category":"Cornici Ed Aste - Vendita Al Dettaglio",
    "sg:phone":"+39 0934 929202",
    "sg:postcode":"93016",
    "sg:province":"Caltanissetta",
    "wof:name":"Novarte Di Giuseppe Ciulla",
    "wof:placetype":"venue"
},
  "geometry": {"coordinates":[14.032127,37.590305],"type":"Point"}
}