{
  "type": "Feature",
  "properties": {
    "iso:country":"IT",
    "sg:address":"28, Via Del Lavoro 20040 Usmate Velate",
    "sg:city":"Usmate Velate",
    "sg:classifiers":[
        {
            "category":"Professional",
            "subcategory":"Engineering",
            "type":"Services"
        }
    ],
    "sg:phone":"+39 039 682 9526",
    "sg:postcode":"20040",
    "sg:province":"Milano",
    "sg:tags":[
        "machine",
        "-",
        "mechanical"
    ],
    "wof:name":"Unimec Produzione Srl",
    "wof:placetype":"venue"
},
  "geometry": {"coordinates":[9.34302,45.642284],"type":"Point"}
}