{
  "type": "Feature",
  "properties": {
    "addr:full":"00144 Roma Roma Roma 00144",
    "addr:postcode":"00144;00144",
    "iso:country":"IT",
    "sg:address":"00144 Roma",
    "sg:city":"Roma",
    "sg:orig_category":"Arredo Cucina Ed Elettrodomestici. Elettrodomestici",
    "sg:phone":"+39 06 5220 7013",
    "sg:postcode":"00144",
    "sg:province":"Roma",
    "wof:name":"Dierre Eur",
    "wof:placetype":"venue"
},
  "geometry": {"coordinates":[12.445815,41.816437],"type":"Point"}
}