{
  "type": "Feature",
  "properties": {
    "addr:full":"15100 Alessandria Alessandria Alessandria 15100",
    "addr:postcode":"15100;15100",
    "iso:country":"IT",
    "sg:address":"15100 Alessandria",
    "sg:city":"Alessandria",
    "sg:orig_category":"Antifurto",
    "sg:phone":"+39 0131 261868",
    "sg:postcode":"15100",
    "sg:province":"Alessandria",
    "sg:website":"http://www.paletta.it",
    "wof:name":"Paletta Luigi",
    "wof:placetype":"venue"
},
  "geometry": {"coordinates":[8.606305,44.914783],"type":"Point"}
}