{
  "type": "Feature",
  "properties": {
    "addr:full":"Viale Giannotti Donato 24 50126 Firenze Firenze Firenze 50126",
    "addr:housenumber":"24",
    "addr:postcode":"50126;50126",
    "addr:street":"Viale Giannotti Donato",
    "iso:country":"IT",
    "sg:address":"Viale Giannotti Donato 24 50126 Firenze",
    "sg:city":"Firenze",
    "sg:classifiers":[
        {
            "category":"Food & Beverages",
            "subcategory":"Meat & Fish",
            "type":"Retail Goods"
        }
    ],
    "sg:phone":"+39 055 681 2148",
    "sg:postcode":"50126",
    "sg:province":"Firenze",
    "sg:website":"www.leonet.it/firms/cata",
    "wof:name":"Cata Inter Trading Srl",
    "wof:placetype":"venue"
},
  "geometry": {"coordinates":[11.256902,43.768734],"type":"Point"}
}