{
  "type": "Feature",
  "properties": {
    "iso:country":"IT",
    "sg:address":"12, Via Traversa Pirazzini 48012 Bagnacavallo",
    "sg:city":"Bagnacavallo",
    "sg:classifiers":[
        {
            "category":"Shopping",
            "subcategory":"Clothing, Apparel, & Fashions",
            "type":"Retail Goods"
        }
    ],
    "sg:phone":"+39 39054561157",
    "sg:postcode":"48012",
    "sg:province":"Ravenna",
    "sg:tags":[
        "clothes"
    ],
    "wof:name":"Maglificio Di Traversara Di Marchetti Sante E C. (s.a.s.)",
    "wof:placetype":"venue"
},
  "geometry": {"coordinates":[12.196571,44.41573],"type":"Point"}
}