{
  "type": "Feature",
  "properties": {
    "addr:full":"20019 Settimo Milanese Settimo Milanese Milano 20019",
    "addr:postcode":"20019;20019",
    "iso:country":"IT",
    "sg:address":"20019 Settimo Milanese",
    "sg:city":"Settimo Milanese",
    "sg:orig_category":"Campeggio",
    "sg:phone":"+39 02 328 5650",
    "sg:postcode":"20019",
    "sg:province":"Milano",
    "wof:name":"Jolly Shop",
    "wof:placetype":"venue"
},
  "geometry": {"coordinates":[9.055924,45.482975],"type":"Point"}
}