{
  "type": "Feature",
  "properties": {
    "iso:country":"IT",
    "sg:address":"Via Bulgaria 16 46042 Castel Goffredo",
    "sg:city":"Castel Goffredo",
    "sg:classifiers":[
        {
            "category":"Communications",
            "subcategory":"Television Station",
            "type":"Services"
        }
    ],
    "sg:phone":"+39 0376 779483",
    "sg:postcode":"46042",
    "sg:province":"Mantova",
    "sg:tags":[
        "discotheque",
        "special",
        "effect"
    ],
    "sg:website":"www.griven.com",
    "wof:name":"Griven Srl",
    "wof:placetype":"venue"
},
  "geometry": {"coordinates":[10.477046,45.282532],"type":"Point"}
}