{
  "type": "Feature",
  "properties": {
    "iso:country":"IT",
    "sg:address":"Via Trieste 8 60033 Chiaravalle",
    "sg:city":"Chiaravalle",
    "sg:classifiers":[
        {
            "category":"Military Area",
            "subcategory":"Armory",
            "type":"Public Place"
        }
    ],
    "sg:phone":"+39 071 948817",
    "sg:postcode":"60033",
    "sg:province":"Ancona",
    "sg:tags":[
        "cartridge"
    ],
    "sg:website":"www.beniarmi.it",
    "wof:name":"F.b. Di Beni Luciano E C. Snc",
    "wof:placetype":"venue"
},
  "geometry": {"coordinates":[13.401649,43.626205],"type":"Point"}
}