{
  "type": "Feature",
  "properties": {
    "iso:country":"IT",
    "sg:address":"157/15, Strada Del Francese 10156 Torino",
    "sg:city":"Torino",
    "sg:classifiers":[
        {
            "category":"Manufacturing",
            "subcategory":"Metals",
            "type":"Manufacturing & Wholesale Goods"
        }
    ],
    "sg:phone":"+39 011 470 1122",
    "sg:postcode":"10156",
    "sg:province":"Torino",
    "sg:tags":[
        "metallurgy",
        "metalworking"
    ],
    "wof:name":"Trafiltecno (s.p.a.)",
    "wof:placetype":"venue"
},
  "geometry": {"coordinates":[7.6729016304,45.131187439],"type":"Point"}
}