{
  "type": "Feature",
  "properties": {
    "iso:country":"IT",
    "sg:address":"27050 Casei Gerola",
    "sg:city":"Casei",
    "sg:orig_category":"Non-classified Establishments",
    "sg:phone":"+39 0383 61480",
    "sg:postcode":"27050",
    "sg:province":"Pavia",
    "wof:name":"Athena Nord Srl",
    "wof:placetype":"venue"
},
  "geometry": {"coordinates":[8.927814,45.00861],"type":"Point"}
}