{
  "type": "Feature",
  "properties": {
    "addr:full":"Via Xxv Luglio 6; Torrebelvicino; 36036 Torrebelvicino Vicenza 36036",
    "addr:housenumber":"6",
    "addr:postcode":"36036;36036",
    "addr:street":"Via Xxv Luglio;Torrebelvicino",
    "iso:country":"IT",
    "sg:address":"Via Xxv Luglio 6; Torrebelvicino; 36036",
    "sg:city":"Torrebelvicino",
    "sg:classifiers":[
        {
            "category":"Banks & Credit Unions",
            "subcategory":"Bank",
            "type":"Services"
        }
    ],
    "sg:phone":"+39 0445 570200",
    "sg:postcode":"36036",
    "sg:province":"Vicenza",
    "wof:name":"Banca Popolare Vicentina",
    "wof:placetype":"venue"
},
  "geometry": {"coordinates":[11.291558,45.71656],"type":"Point"}
}