{
  "type": "Feature",
  "properties": {
    "iso:country":"IT",
    "sg:address":"36027 Rosa'",
    "sg:orig_category":"Scuole E Servizi Scolastici",
    "sg:phone":"+39 0424 582191",
    "sg:postcode":"36027",
    "sg:province":"Vicenza",
    "wof:name":"English International School",
    "wof:placetype":"venue"
},
  "geometry": {"coordinates":[11.768878,45.729294],"type":"Point"}
}