{
  "type": "Feature",
  "properties": {
    "iso:country":"IT",
    "sg:address":"43012 Sanguinaro",
    "sg:orig_category":"Macchine Pulizia Industriale",
    "sg:phone":"+39 0521 825525",
    "sg:postcode":"43012",
    "sg:province":"Parma",
    "sg:website":"http://ecologica.it",
    "wof:name":"Ecologica Spa",
    "wof:placetype":"venue"
},
  "geometry": {"coordinates":[10.317055,44.799595],"type":"Point"}
}