{
  "type": "Feature",
  "properties": {
    "addr:full":"10098 Rivoli Rivoli Torino 10098",
    "addr:postcode":"10098;10098",
    "iso:country":"IT",
    "sg:address":"10098 Rivoli",
    "sg:city":"Rivoli",
    "sg:orig_category":"Forni Industriali",
    "sg:phone":"+39 011 953 2018",
    "sg:postcode":"10098",
    "sg:province":"Torino",
    "wof:name":"Fratelli Buscieti Di Buscieti D. E R. Snc",
    "wof:placetype":"venue"
},
  "geometry": {"coordinates":[7.5032348633,45.0715026855],"type":"Point"}
}