{
  "type": "Feature",
  "properties": {
    "iso:country":"IT",
    "sg:address":"70010 Turi",
    "sg:city":"Turi",
    "sg:classifiers":[
        {
            "category":"Manufacturing",
            "subcategory":"Food",
            "type":"Manufacturing & Wholesale Goods"
        }
    ],
    "sg:phone":"+39 080 891 6362",
    "sg:postcode":"70010",
    "sg:province":"Bari",
    "sg:tags":[
        "product"
    ],
    "wof:name":"Tarall'oro Snc",
    "wof:placetype":"venue"
},
  "geometry": {"coordinates":[16.9482078552,40.8820152283],"type":"Point"}
}