{
  "type": "Feature",
  "properties": {
    "addr:full":"28, Corso Cavallotti Felice 15100 Alessandria Alessandria Alessandria 15100",
    "addr:postcode":"15100;15100",
    "addr:street":"Corso Cavallotti Felice",
    "iso:country":"IT",
    "sg:address":"28, Corso Cavallotti Felice 15100 Alessandria",
    "sg:city":"Alessandria",
    "sg:classifiers":[
        {
            "category":"Shopping",
            "subcategory":"Jewelry",
            "type":"Retail Goods"
        }
    ],
    "sg:phone":"+39 0131 262289",
    "sg:postcode":"15100",
    "sg:province":"Alessandria",
    "sg:tags":[
        "jewellery"
    ],
    "wof:name":"F.i.a.m. S.r.l",
    "wof:placetype":"venue"
},
  "geometry": {"coordinates":[8.607996,44.912167],"type":"Point"}
}