{
  "type": "Feature",
  "properties": {
    "iso:country":"IT",
    "sg:address":"86010 Busso",
    "sg:city":"Busso",
    "sg:orig_category":"Materiali Edili",
    "sg:phone":"+39 0874 348246",
    "sg:postcode":"86010",
    "sg:province":"Campobasso",
    "wof:name":"Romeo Balsamo S.r.l.",
    "wof:placetype":"venue"
},
  "geometry": {"coordinates":[14.562056,41.555168],"type":"Point"}
}