{
  "type": "Feature",
  "properties": {
    "iso:country":"IT",
    "sg:address":"17, Via Calabria 20158 Milano",
    "sg:city":"Milano",
    "sg:classifiers":[
        {
            "category":"Farming",
            "subcategory":"Livestock Farm",
            "type":"Manufacturing & Wholesale Goods"
        }
    ],
    "sg:phone":"+39 02 3932 2062",
    "sg:postcode":"20158",
    "sg:province":"Milano",
    "sg:tags":[
        "agriculture"
    ],
    "wof:name":"Nuova Flesan S.r.l.",
    "wof:placetype":"venue"
},
  "geometry": {"coordinates":[9.169566,45.495541],"type":"Point"}
}