{
  "type": "Feature",
  "properties": {
    "iso:country":"IT",
    "sg:address":"25030 Castel Mella",
    "sg:city":"Castel Mella",
    "sg:classifiers":[
        {
            "category":"Home & Garden",
            "subcategory":"Building Materials",
            "type":"Retail Goods"
        }
    ],
    "sg:phone":"+39 030 358 2433",
    "sg:postcode":"25030",
    "sg:province":"Brescia",
    "sg:tags":[
        "window",
        "door",
        "frame"
    ],
    "sg:website":"http://www.vegallarm.it",
    "wof:name":"Vegallarm Snc Di Bonetti Giulio & Crespi Claudio",
    "wof:placetype":"venue"
},
  "geometry": {"coordinates":[10.147706,45.489117],"type":"Point"}
}