{
  "type": "Feature",
  "properties": {
    "addr:full":"Strada Selvagrossa 36 61010 Tavullia Tavullia Pesaro E Urbino 61010",
    "addr:housenumber":"36",
    "addr:postcode":"61010;61010",
    "addr:street":"Strada Selvagrossa;E Urbino",
    "iso:country":"IT",
    "sg:address":"Strada Selvagrossa 36 61010 Tavullia",
    "sg:city":"Tavullia",
    "sg:classifiers":[
        {
            "category":"Communications",
            "subcategory":"Film & Video Production",
            "type":"Services"
        }
    ],
    "sg:phone":"+39 0721 20031",
    "sg:postcode":"61010",
    "sg:province":"Pesaro E Urbino",
    "sg:tags":[
        "decorative",
        "mirror"
    ],
    "sg:website":"www.ilvaglass.com",
    "wof:name":"Ilva Glass Spa",
    "wof:placetype":"venue"
},
  "geometry": {"coordinates":[12.529803,43.633556],"type":"Point"}
}