{
  "type": "Feature",
  "properties": {
    "iso:country":"IT",
    "sg:address":"51100 Quarrata",
    "sg:orig_category":"Ospedali E Servizi Sanitari",
    "sg:phone":"+39 0573 774518",
    "sg:postcode":"51100",
    "sg:province":"Pistoia",
    "wof:name":"Day Medical Dental",
    "wof:placetype":"venue"
},
  "geometry": {"coordinates":[10.917764,43.906559],"type":"Point"}
}