{
  "type": "Feature",
  "properties": {
    "iso:country":"IT",
    "sg:address":"36015 Schio",
    "sg:city":"Schio",
    "sg:orig_category":"Lavorazioni Metalli, Stampaggio E Saldatura",
    "sg:phone":"+39 0445 576540",
    "sg:postcode":"36015",
    "sg:province":"Vicenza",
    "wof:name":"Aves Srl",
    "wof:placetype":"venue"
},
  "geometry": {"coordinates":[11.362141,45.709492],"type":"Point"}
}