{
  "type": "Feature",
  "properties": {
    "iso:country":"IT",
    "sg:address":"59100 Prato",
    "sg:city":"Prato",
    "sg:orig_category":"Servizi E Lavori Per Abbigliamento E Pelletterie",
    "sg:phone":"+39 0574 811006",
    "sg:postcode":"59100",
    "sg:province":"Prato",
    "wof:name":"Rudytex",
    "wof:placetype":"venue"
},
  "geometry": {"coordinates":[11.03681,43.920544],"type":"Point"}
}