{
  "type": "Feature",
  "properties": {
    "addr:full":"Via Dell' Artigianato 06083 Bastia Umbra Bastia Perugia 06083",
    "addr:postcode":"06083;06083",
    "addr:street":"Via Dell ' Artigianato",
    "iso:country":"IT",
    "sg:address":"Via Dell' Artigianato 06083 Bastia Umbra",
    "sg:city":"Bastia",
    "sg:classifiers":[
        {
            "category":"Wholesale",
            "subcategory":"Chemicals & Plastics",
            "type":"Manufacturing & Wholesale Goods"
        }
    ],
    "sg:phone":"+39 075 800 0655",
    "sg:postcode":"06083",
    "sg:province":"Perugia",
    "sg:tags":[
        "processing",
        "machinery",
        "accessory"
    ],
    "sg:website":"www.torninova.com",
    "wof:name":"Torninova Srl",
    "wof:placetype":"venue"
},
  "geometry": {"coordinates":[12.542338,43.057941],"type":"Point"}
}