{
  "type": "Feature",
  "properties": {
    "addr:full":"44042 Cento Cento Ferrara 44042",
    "addr:postcode":"44042;44042",
    "iso:country":"IT",
    "sg:address":"44042 Cento",
    "sg:city":"Cento",
    "sg:orig_category":"Motori Ed Organi Di Trasmissione. Ricambi E Componenti Dei Mezzi Di Trasporto",
    "sg:phone":"+39 051 683 7511",
    "sg:postcode":"44042",
    "sg:province":"Ferrara",
    "sg:website":"http://www.detroitdiesel.com",
    "wof:name":"Vm Motori Spa A Detroit Diesel Co.",
    "wof:placetype":"venue"
},
  "geometry": {"coordinates":[11.2947473526,44.7400169373],"type":"Point"}
}