{
  "type": "Feature",
  "properties": {
    "iso:country":"IT",
    "sg:address":"37012 Bussolengo",
    "sg:city":"Bussolengo",
    "sg:orig_category":"Forniture Per Abbigliamento E Pelletterie",
    "sg:phone":"+39 045 715 0645",
    "sg:postcode":"37012",
    "sg:province":"Verona",
    "wof:name":"Suolettificio D.m.g. Sport (s.n.c.)",
    "wof:placetype":"venue"
},
  "geometry": {"coordinates":[10.8506412506,45.4657058716],"type":"Point"}
}