{
  "type": "Feature",
  "properties": {
    "iso:country":"IT",
    "sg:address":"43100 Parma",
    "sg:city":"Parma",
    "sg:orig_category":"Servizi E Lavori Per Edilizia E Lavori Pubblici",
    "sg:phone":"+39 0521 252879",
    "sg:postcode":"43100",
    "sg:province":"Parma",
    "wof:name":"Dall'aglio Francesco Casa Pi\u00d9",
    "wof:placetype":"venue"
},
  "geometry": {"coordinates":[10.311707,44.783955],"type":"Point"}
}