{
  "type": "Feature",
  "properties": {
    "addr:full":"43015 Noceto Noceto Parma 43015",
    "addr:postcode":"43015;43015",
    "iso:country":"IT",
    "sg:address":"43015 Noceto",
    "sg:city":"Noceto",
    "sg:classifiers":[
        {
            "category":"Manufacturing",
            "subcategory":"Tools & Machinery",
            "type":"Manufacturing & Wholesale Goods"
        }
    ],
    "sg:phone":"+39 0521 628645",
    "sg:postcode":"43015",
    "sg:province":"Parma",
    "sg:tags":[
        "machining",
        "mechanical"
    ],
    "wof:name":"Ferrari Mario & C. Snc",
    "wof:placetype":"venue"
},
  "geometry": {"coordinates":[10.185301,44.816353],"type":"Point"}
}