{
  "type": "Feature",
  "properties": {
    "addr:full":"57123 Livorno Livorno Livorno 57123",
    "addr:postcode":"57123;57123",
    "iso:country":"IT",
    "sg:address":"57123 Livorno",
    "sg:city":"Livorno",
    "sg:orig_category":"Musica",
    "sg:phone":"+39 0586 899466",
    "sg:postcode":"57123",
    "sg:province":"Livorno",
    "wof:name":"Casa Della Musica - Pietro Napoli",
    "wof:placetype":"venue"
},
  "geometry": {"coordinates":[10.3145074844,43.5517082214],"type":"Point"}
}