{
  "type": "Feature",
  "properties": {
    "addr:full":"56013 Marina Di Pisa PI",
    "addr:postcode":"56013",
    "addr:street":"Di Pisa Pi",
    "iso:country":"IT",
    "sg:address":"56013 Marina Di Pisa",
    "sg:orig_category":"Motori Ed Organi Di Trasmissione. Ricambi E Componenti Dei Mezzi Di Trasporto",
    "sg:phone":"+39 050 36721",
    "sg:province":"PI",
    "wof:name":"Centro Diesel Di Ghelardoni & Benedetti",
    "wof:placetype":"venue"
},
  "geometry": {"coordinates":[-94.1923370361,43.5992355347],"type":"Point"}
}