{
  "type": "Feature",
  "properties": {
    "addr:full":"19/21, Via Divisione Tridentina 24020 Villa Di Serio Villa di Serio Bergamo 24020",
    "addr:housenumber":"19 / 21",
    "addr:postcode":"24020;24020",
    "addr:street":"Via Divisione Tridentina",
    "iso:country":"IT",
    "sg:address":"19/21, Via Divisione Tridentina 24020 Villa Di Serio",
    "sg:city":"Villa di Serio",
    "sg:classifiers":[
        {
            "category":"Professional",
            "subcategory":"Engineering",
            "type":"Services"
        }
    ],
    "sg:phone":"+39 39035668079",
    "sg:postcode":"24020",
    "sg:province":"Bergamo",
    "sg:tags":[
        "machine",
        "-",
        "mechanical"
    ],
    "wof:name":"Promatech S.p.a.",
    "wof:placetype":"venue"
},
  "geometry": {"coordinates":[9.738119,45.725178],"type":"Point"}
}