{
  "type": "Feature",
  "properties": {
    "addr:full":"00185 Roma Roma Roma 00185",
    "addr:postcode":"00185;00185",
    "iso:country":"IT",
    "sg:address":"00185 Roma",
    "sg:city":"Roma",
    "sg:orig_category":"Servizi Culturali E Per Lo Spettacolo. Servizi Al Turismo. Acqua, Luce, Gas E Societa' Di Esercizio Pubblico",
    "sg:phone":"+39 06 4470 3989",
    "sg:postcode":"00185",
    "sg:province":"Roma",
    "wof:name":"Biblioteca Nazionale Centrale Roma",
    "wof:placetype":"venue"
},
  "geometry": {"coordinates":[12.505505,41.906097],"type":"Point"}
}