{
  "type": "Feature",
  "properties": {
    "iso:country":"IT",
    "sg:address":"24021 Albino",
    "sg:city":"Albino",
    "sg:orig_category":"Servizi Per Lo Sport E Il Tempo Libero. Servizi Al Turismo",
    "sg:phone":"+39 035 751408",
    "sg:postcode":"24021",
    "sg:province":"Bergamo",
    "wof:name":"Funivia Albino - Selvino-s.a.b. Autoservizi (s.r.l.)",
    "wof:placetype":"venue"
},
  "geometry": {"coordinates":[9.659244,45.698196],"type":"Point"}
}