{
  "type": "Feature",
  "properties": {
    "iso:country":"IT",
    "sg:address":"20148 Milano",
    "sg:city":"Milano",
    "sg:orig_category":"Forniture Per Attivita' Commerciali Ed Artigianali",
    "sg:phone":"+39 02 4540 9071",
    "sg:postcode":"20148",
    "sg:province":"Milano",
    "wof:name":"Dottincisioni Di Andrea Dotti",
    "wof:placetype":"venue"
},
  "geometry": {"coordinates":[9.1428165436,45.474697113],"type":"Point"}
}