{
  "type": "Feature",
  "properties": {
    "addr:full":"25040 Cividate Camuno Cividate Camuno Brescia 25040",
    "addr:postcode":"25040;25040",
    "iso:country":"IT",
    "sg:address":"25040 Cividate Camuno",
    "sg:city":"Cividate Camuno",
    "sg:orig_category":"Termotecnica E Riscaldamento, Apparecchiature E Servizi",
    "sg:phone":"+39 036 445 6104",
    "sg:postcode":"25040",
    "sg:province":"Brescia",
    "wof:name":"Gosio F.lli Di Gosio Giuseppino & C. Snc",
    "wof:placetype":"venue"
},
  "geometry": {"coordinates":[10.263092,45.943233],"type":"Point"}
}