{
  "type": "Feature",
  "properties": {
    "iso:country":"IT",
    "sg:address":"00010 Roma",
    "sg:classifiers":[
        {
            "category":"Home & Garden",
            "subcategory":"Home Furnishings",
            "type":"Retail Goods"
        }
    ],
    "sg:phone":"+39 06 2242 9206",
    "sg:postcode":"00010",
    "sg:province":"Roma",
    "sg:tags":[
        "bathroom",
        "accessories"
    ],
    "wof:name":"Tecnoarredi Srl",
    "wof:placetype":"venue"
},
  "geometry": {"coordinates":[12.6286029816,41.8918190002],"type":"Point"}
}