{
  "type": "Feature",
  "properties": {
    "iso:country":"IT",
    "sg:address":"47900 Rimini",
    "sg:city":"Rimini",
    "sg:orig_category":"Cucine, Forni E Fornelli Uso Domestico",
    "sg:phone":"+39 0541 727849",
    "sg:postcode":"47900",
    "sg:province":"Rimini",
    "wof:name":"Peppucci Riccardo & C. Sas",
    "wof:placetype":"venue"
},
  "geometry": {"coordinates":[12.507329,44.05061],"type":"Point"}
}