{
  "type": "Feature",
  "properties": {
    "iso:country":"IT",
    "sg:address":"53100 Siena",
    "sg:city":"Siena",
    "sg:orig_category":"Calzature, Pelletterie E Pelli. Shopping",
    "sg:phone":"+39 0577 40015",
    "sg:postcode":"53100",
    "sg:province":"Siena",
    "wof:name":"Franchi Romano",
    "wof:placetype":"venue"
},
  "geometry": {"coordinates":[11.365801,43.31971],"type":"Point"}
}