{
  "type": "Feature",
  "properties": {
    "iso:country":"IT",
    "sg:address":"8, Via Del Freidano 10099 San Mauro Torinese",
    "sg:city":"San Mauro Torinese",
    "sg:classifiers":[
        {
            "category":"Manufacturing",
            "subcategory":"Paper Products",
            "type":"Manufacturing & Wholesale Goods"
        }
    ],
    "sg:phone":"+39 011 223 3111",
    "sg:postcode":"10099",
    "sg:province":"Torino",
    "sg:tags":[
        "cardboard"
    ],
    "wof:name":"Cartiere Burgo S.p.a.",
    "wof:placetype":"venue"
},
  "geometry": {"coordinates":[7.7420887947,45.1110038757],"type":"Point"}
}