{
  "type": "Feature",
  "properties": {
    "addr:full":"12, Via Caduti Del Lavoro 61032 Fano Fano Pesaro E Urbino 61032",
    "addr:postcode":"61032;61032",
    "addr:street":"Via Caduti Del Lavoro",
    "iso:country":"IT",
    "sg:address":"12, Via Caduti Del Lavoro 61032 Fano",
    "sg:city":"Fano",
    "sg:classifiers":[
        {
            "category":"Bars & Pubs",
            "subcategory":"Nightclub",
            "type":"Food & Drink"
        }
    ],
    "sg:phone":"+39 0721 806597",
    "sg:postcode":"61032",
    "sg:province":"Pesaro E Urbino",
    "sg:tags":[
        "cake",
        "bread"
    ],
    "wof:name":"Il Pane (s.r.l.)",
    "wof:placetype":"venue"
},
  "geometry": {"coordinates":[12.529803,43.633556],"type":"Point"}
}