{
  "type": "Feature",
  "properties": {
    "iso:country":"IT",
    "sg:address":"39, Via Valadier 00193 Roma",
    "sg:city":"Roma",
    "sg:classifiers":[
        {
            "category":"Utilities",
            "subcategory":"Telephone",
            "type":"Services"
        }
    ],
    "sg:phone":"+39 39063234449",
    "sg:postcode":"00193",
    "sg:province":"Roma",
    "sg:tags":[
        "telecommunication"
    ],
    "wof:name":"Sim Elettra (s.r.l.)",
    "wof:placetype":"venue"
},
  "geometry": {"coordinates":[12.468155,41.907822],"type":"Point"}
}