{
  "type": "Feature",
  "properties": {
    "iso:country":"IT",
    "sg:address":"25055 Pisogne",
    "sg:city":"Pisogne",
    "sg:orig_category":"Arredo Bagno Ed Idrosanitari. Idrosanitari E Accessori",
    "sg:phone":"+39 036 488 0447",
    "sg:postcode":"25055",
    "sg:province":"Brescia",
    "wof:name":"Rubi Zeta Di Zanardi G. & A. Snc",
    "wof:placetype":"venue"
},
  "geometry": {"coordinates":[10.139048,45.8064],"type":"Point"}
}