{
  "type": "Feature",
  "properties": {
    "iso:country":"IT",
    "sg:address":"Via Rimale 53 43036 Fidenza",
    "sg:city":"Fidenza",
    "sg:orig_category":"Ladies' Trousers Suits, Suits, Jackets, Skirts, And Trousers",
    "sg:phone":"+39 0524 526460",
    "sg:postcode":"43036",
    "sg:province":"Parma",
    "sg:website":"www.pinko.it",
    "wof:name":"Cris Confezioni Srl",
    "wof:placetype":"venue"
},
  "geometry": {"coordinates":[10.023093,44.87944],"type":"Point"}
}