{
  "type": "Feature",
  "properties": {
    "iso:country":"IT",
    "sg:address":"26026 Ferie",
    "sg:orig_category":"Materiali Edili",
    "sg:phone":"+39 0372 727200",
    "sg:postcode":"26026",
    "sg:province":"Cremona",
    "wof:name":"Fornace Edilpadana (s.r.l.)",
    "wof:placetype":"venue"
},
  "geometry": {"coordinates":[9.867204,45.161888],"type":"Point"}
}