{
  "type": "Feature",
  "properties": {
    "addr:full":"Corso Venezia 5; Milano; 20121 Milano Milano 20121",
    "addr:housenumber":"5",
    "addr:postcode":"20121;20121",
    "addr:street":"Corso Venezia",
    "iso:country":"IT",
    "sg:address":"Corso Venezia 5; Milano; 20121",
    "sg:city":"Milano",
    "sg:classifiers":[
        {
            "category":"Banks & Credit Unions",
            "subcategory":"Bank",
            "type":"Services"
        }
    ],
    "sg:phone":"+39 02 7601 4579",
    "sg:postcode":"20121",
    "sg:province":"Milano",
    "wof:name":"Bank Austria Ag",
    "wof:placetype":"venue"
},
  "geometry": {"coordinates":[9.201342,45.470848],"type":"Point"}
}