{
  "type": "Feature",
  "properties": {
    "iso:country":"IT",
    "sg:address":"00147 Roma",
    "sg:city":"Roma",
    "sg:orig_category":"Servizi Per Lo Sport E Il Tempo Libero. Servizi Al Turismo",
    "sg:phone":"+39 06 594 0169",
    "sg:postcode":"00147",
    "sg:province":"Roma",
    "wof:name":"Accademia Del Nuoto",
    "wof:placetype":"venue"
},
  "geometry": {"coordinates":[12.491333,41.848278],"type":"Point"}
}