{
  "type": "Feature",
  "properties": {
    "addr:full":"71011 Apricena Apricena Foggia 71011",
    "addr:postcode":"71011;71011",
    "iso:country":"IT",
    "sg:address":"71011 Apricena",
    "sg:city":"Apricena",
    "sg:orig_category":"Agricoltura - Attrezzi, Prodotti E Forniture",
    "sg:phone":"+39 0882 646032",
    "sg:postcode":"71011",
    "sg:province":"Foggia",
    "wof:name":"Cooperativa Agricola Fra Coltivatori Di Apricena Srl",
    "wof:placetype":"venue"
},
  "geometry": {"coordinates":[15.477108,41.790829],"type":"Point"}
}