{
  "type": "Feature",
  "properties": {
    "iso:country":"IT",
    "sg:address":"4, Via Capparola Sotto 25078 Vestone",
    "sg:city":"Vestone",
    "sg:classifiers":[
        {
            "category":"Manufacturing",
            "subcategory":"Metals",
            "type":"Manufacturing & Wholesale Goods"
        }
    ],
    "sg:phone":"+39 036 587 8011",
    "sg:postcode":"25078",
    "sg:province":"Brescia",
    "sg:tags":[
        "metallurgy",
        "metalworking"
    ],
    "wof:name":"Unidelta Idrosanitaria",
    "wof:placetype":"venue"
},
  "geometry": {"coordinates":[10.4131994247,45.7149887085],"type":"Point"}
}