{
  "type": "Feature",
  "properties": {
    "iso:country":"IT",
    "sg:address":"Via Togliatti 52/a 42020 Montecavolo",
    "sg:classifiers":[
        {
            "category":"Autos & Motor Vehicles",
            "subcategory":"Auto Supplies",
            "type":"Retail Goods"
        }
    ],
    "sg:phone":"+39 0522 250411",
    "sg:postcode":"42020",
    "sg:province":"Reggio Nell'Emilia",
    "sg:tags":[
        "automobile",
        "accessory"
    ],
    "sg:website":"www.autosonik.com",
    "wof:name":"Autosonik Group Srl",
    "wof:placetype":"venue"
},
  "geometry": {"coordinates":[10.567183,44.642696],"type":"Point"}
}