{
  "type": "Feature",
  "properties": {
    "addr:full":"13, Via Canova 36053 Gambellara Gambellara Vicenza 36053",
    "addr:postcode":"36053;36053",
    "addr:street":"Via Canova",
    "iso:country":"IT",
    "sg:address":"13, Via Canova 36053 Gambellara",
    "sg:city":"Gambellara",
    "sg:classifiers":[
        {
            "category":"Manufacturing",
            "subcategory":"Textiles",
            "type":"Manufacturing & Wholesale Goods"
        }
    ],
    "sg:phone":"+39 0444 648649",
    "sg:postcode":"36053",
    "sg:province":"Vicenza",
    "sg:tags":[
        "leather",
        "raw",
        "material",
        "-"
    ],
    "wof:name":"Savoda S.r.l.",
    "wof:placetype":"venue"
},
  "geometry": {"coordinates":[11.3479,45.429852],"type":"Point"}
}