{
  "type": "Feature",
  "properties": {
    "addr:full":"80022 Arzano Arzano Napoli 80022",
    "addr:postcode":"80022;80022",
    "iso:country":"IT",
    "sg:address":"80022 Arzano",
    "sg:city":"Arzano",
    "sg:orig_category":"Agenzie D'affari E Servizi Commerciali",
    "sg:phone":"+39 081 731 0670",
    "sg:postcode":"80022",
    "sg:province":"Napoli",
    "wof:name":"Studio Flegreo Un Srl",
    "wof:placetype":"venue"
},
  "geometry": {"coordinates":[14.265237,40.911655],"type":"Point"}
}