{
  "type": "Feature",
  "properties": {
    "iso:country":"IT",
    "sg:address":"30174 Venezia",
    "sg:city":"Mestre",
    "sg:orig_category":"Alimentare E Conserviera Industria - Macchine",
    "sg:phone":"+39 041 981188",
    "sg:postcode":"30174",
    "sg:province":"Venezia",
    "sg:website":"http://www.avegroup.com",
    "wof:name":"Alta Meccaniche Srl",
    "wof:placetype":"venue"
},
  "geometry": {"coordinates":[12.225021,45.503708],"type":"Point"}
}