{
  "type": "Feature",
  "properties": {
    "iso:country":"IT",
    "sg:address":"70027 Palo Del Colle",
    "sg:city":"Palo del Colle",
    "sg:orig_category":"Articoli Per Imballaggio E Confezionamento. Forniture Per Uffici. Forniture Per Attivita' Commerciali Ed Artigianali",
    "sg:phone":"+39 080 991 1420",
    "sg:postcode":"70027",
    "sg:province":"Bari",
    "wof:name":"Boffoli Vito",
    "wof:placetype":"venue"
},
  "geometry": {"coordinates":[16.696062,41.05899],"type":"Point"}
}