{
  "type": "Feature",
  "properties": {
    "iso:country":"IT",
    "sg:address":"28100 Novara",
    "sg:city":"Novara",
    "sg:orig_category":"Antinfortunistica - Attrezzature Ed Articoli",
    "sg:phone":"+39 0321 339078",
    "sg:postcode":"28100",
    "sg:province":"Novara",
    "wof:name":"Spagnuolo Irene 3s Scuola Sicurezza Sport",
    "wof:placetype":"venue"
},
  "geometry": {"coordinates":[8.616614,45.460354],"type":"Point"}
}