{
  "type": "Feature",
  "properties": {
    "iso:country":"IT",
    "sg:address":"25070 Sabbio Chiese",
    "sg:city":"Sabbio Chiese",
    "sg:orig_category":"Utensili Meccanici E Materiali",
    "sg:phone":"+39 036 589 5621",
    "sg:postcode":"25070",
    "sg:province":"Brescia",
    "wof:name":"Piardi Claudio",
    "wof:placetype":"venue"
},
  "geometry": {"coordinates":[10.431466,45.648319],"type":"Point"}
}