{
  "type": "Feature",
  "properties": {
    "addr:full":"45024 Fiesso Umbertiano Fiesso Umbertiano Rovigo 45024",
    "addr:postcode":"45024;45024",
    "addr:street":"Umbertiano Rovigo",
    "iso:country":"IT",
    "sg:address":"45024 Fiesso Umbertiano",
    "sg:city":"Fiesso Umbertiano",
    "sg:orig_category":"Prodotti E Manufatti In Materie Plastiche",
    "sg:phone":"+39 0425 745511",
    "sg:postcode":"45024",
    "sg:province":"Rovigo",
    "sg:website":"http://www.lareter.it",
    "wof:name":"Lareter Spa",
    "wof:placetype":"venue"
},
  "geometry": {"coordinates":[11.6049022675,44.9598731995],"type":"Point"}
}