{
  "type": "Feature",
  "properties": {
    "iso:country":"IT",
    "sg:address":"98123 Messina",
    "sg:city":"Messina",
    "sg:orig_category":"Prodotti Di Base E Forniture Per Industria Alimentare E Bevande. Prodotti Chimici Di Base",
    "sg:phone":"+39 090 293 5532",
    "sg:postcode":"98123",
    "sg:province":"Messina",
    "wof:name":"Esaflor (s.r.l.)",
    "wof:placetype":"venue"
},
  "geometry": {"coordinates":[15.556101799,38.1807327271],"type":"Point"}
}