{
  "type": "Feature",
  "properties": {
    "iso:country":"IT",
    "sg:address":"Via Edison, 193/195 20019 Settimo Milanese",
    "sg:city":"Settimo Milanese",
    "sg:classifiers":[
        {
            "category":"Banks & Credit Unions",
            "subcategory":"Investment Brokerage",
            "type":"Services"
        }
    ],
    "sg:phone":"+39 02 3350 0288",
    "sg:postcode":"20019",
    "sg:province":"Milano",
    "sg:tags":[
        "filters"
    ],
    "wof:name":"Ballerini Filtrazione Srl",
    "wof:placetype":"venue"
},
  "geometry": {"coordinates":[9.0650424957,45.4644775391],"type":"Point"}
}