{
  "type": "Feature",
  "properties": {
    "addr:full":"Via Xxv Luglio 160 84013 Cava De' Tirreni Salerno 84013",
    "addr:housenumber":"160",
    "addr:postcode":"84013;84013",
    "addr:street":"Via Xxv Luglio",
    "iso:country":"IT",
    "sg:address":"Via Xxv Luglio 160 84013 Cava De' Tirreni",
    "sg:classifiers":[
        {
            "category":"Banks & Credit Unions",
            "subcategory":"Investment Brokerage",
            "type":"Services"
        }
    ],
    "sg:phone":"+39 089 344633",
    "sg:postcode":"84013",
    "sg:province":"Salerno",
    "sg:tags":[
        "stone",
        "lithography"
    ],
    "sg:website":"www.medeaspa.it",
    "wof:name":"Medea Spa",
    "wof:placetype":"venue"
},
  "geometry": {"coordinates":[14.765912,40.677956],"type":"Point"}
}