{
  "type": "Feature",
  "properties": {
    "iso:country":"IT",
    "sg:address":"20030 Bovisio Masciago",
    "sg:city":"Bovisio",
    "sg:orig_category":"Serramenti Ed Infissi",
    "sg:phone":"+39 036 255 9171",
    "sg:postcode":"20030",
    "sg:province":"Milano",
    "sg:website":"http://www.atenaservice.it",
    "wof:name":"Atena Service Srl",
    "wof:placetype":"venue"
},
  "geometry": {"coordinates":[9.146356,45.608803],"type":"Point"}
}