{
  "type": "Feature",
  "properties": {
    "addr:full":"38038 Tesero Tesero Trento 38038",
    "addr:postcode":"38038;38038",
    "iso:country":"IT",
    "sg:address":"38038 Tesero",
    "sg:city":"Tesero",
    "sg:orig_category":"Elettronica Professionale E Di Consumo. Musica",
    "sg:phone":"+39 0462 813071",
    "sg:postcode":"38038",
    "sg:province":"Trento",
    "wof:name":"Delmarco Iginio",
    "wof:placetype":"venue"
},
  "geometry": {"coordinates":[11.507655,46.28952],"type":"Point"}
}