{
  "type": "Feature",
  "properties": {
    "addr:full":"10042 Nichelino Nichelino Torino 10042",
    "addr:postcode":"10042;10042",
    "iso:country":"IT",
    "sg:address":"10042 Nichelino",
    "sg:city":"Nichelino",
    "sg:orig_category":"Forniture Per Edilizia E Lavori Pubblici",
    "sg:phone":"+39 011 624526",
    "sg:postcode":"10042",
    "sg:province":"Torino",
    "sg:website":"http://www.borgatta.com",
    "wof:name":"Borgatta Emilio Srl",
    "wof:placetype":"venue"
},
  "geometry": {"coordinates":[7.638425827,44.9780502319],"type":"Point"}
}