{
  "type": "Feature",
  "properties": {
    "addr:full":"42013 Casalgrande Reggio Nell'Emilia 42013",
    "addr:postcode":"42013;42013",
    "iso:country":"IT",
    "sg:address":"42013 Casalgrande",
    "sg:orig_category":"Ricambi E Componenti Dei Mezzi Di Trasporto",
    "sg:phone":"+39 0522 999179",
    "sg:postcode":"42013",
    "sg:province":"Reggio Nell'Emilia",
    "wof:name":"Old Racing Spare Parts",
    "wof:placetype":"venue"
},
  "geometry": {"coordinates":[10.6277942657,44.6962280273],"type":"Point"}
}