{
  "type": "Feature",
  "properties": {
    "addr:full":"11, Via Cassino D'alberi 20067 Tribiano Tribiano Milano 20067",
    "addr:postcode":"20067;20067",
    "addr:street":"Via Cassino D'Alberi",
    "iso:country":"IT",
    "sg:address":"11, Via Cassino D'alberi 20067 Tribiano",
    "sg:city":"Tribiano",
    "sg:classifiers":[
        {
            "category":"Professional",
            "subcategory":"Engineering",
            "type":"Services"
        }
    ],
    "sg:phone":"+39 02 9063 9967",
    "sg:postcode":"20067",
    "sg:province":"Milano",
    "sg:tags":[
        "machine",
        "-",
        "mechanical"
    ],
    "wof:name":"Nuova Novater S.r.l.",
    "wof:placetype":"venue"
},
  "geometry": {"coordinates":[9.381859,45.409081],"type":"Point"}
}