{
  "type": "Feature",
  "properties": {
    "addr:full":"71016 San Severo San Severo Foggia 71016",
    "addr:housenumber":"71016",
    "addr:postcode":"71016",
    "addr:street":"San Severo",
    "iso:country":"IT",
    "sg:address":"71016 San Severo",
    "sg:city":"San Severo",
    "sg:orig_category":"Agende, Calendari E Rubriche",
    "sg:phone":"+39 0882 335997",
    "sg:postcode":"71016",
    "sg:province":"Foggia",
    "wof:name":"Grafiche Sales Srl",
    "wof:placetype":"venue"
},
  "geometry": {"coordinates":[15.628367,41.316082],"type":"Point"}
}