{
  "type": "Feature",
  "properties": {
    "iso:country":"IT",
    "sg:address":"20122 Milano",
    "sg:city":"Milano",
    "sg:orig_category":"Arredamenti Ed Architettura D'interni",
    "sg:phone":"+39 02 799773",
    "sg:postcode":"20122",
    "sg:province":"Milano",
    "wof:name":"Multiform Srl",
    "wof:placetype":"venue"
},
  "geometry": {"coordinates":[9.196825,45.465469],"type":"Point"}
}