{
  "type": "Feature",
  "properties": {
    "iso:country":"IT",
    "sg:address":"23, Via Quasimodo S. 55023 Borgo A Mozzano",
    "sg:city":"Borgo a Mozzano",
    "sg:classifiers":[
        {
            "category":"Shopping",
            "subcategory":"Gifts & Souvenirs",
            "type":"Retail Goods"
        }
    ],
    "sg:phone":"+39 0583 838618",
    "sg:postcode":"55023",
    "sg:province":"Lucca",
    "wof:name":"La Bottega Del '900 Di Patrizia Caraffi",
    "wof:placetype":"venue"
},
  "geometry": {"coordinates":[10.51089,43.963238],"type":"Point"}
}