{
  "type": "Feature",
  "properties": {
    "addr:full":"10136 Torino Torino Torino 10136",
    "addr:postcode":"10136;10136",
    "iso:country":"IT",
    "sg:address":"10136 Torino",
    "sg:city":"Torino",
    "sg:orig_category":"Impianti, Attrezzature E Forniture Sanitarie Ed Ospedaliere",
    "sg:phone":"+39 011 396481",
    "sg:postcode":"10136",
    "sg:province":"Torino",
    "wof:name":"Absa Di Sartori G. & C. (s.n.c.)",
    "wof:placetype":"venue"
},
  "geometry": {"coordinates":[7.642635,45.049335],"type":"Point"}
}