{
  "type": "Feature",
  "properties": {
    "addr:full":"20083 Bonirola Milano 20083",
    "addr:postcode":"20083;20083",
    "addr:street":"Bonirola",
    "iso:country":"IT",
    "sg:address":"20083 Bonirola",
    "sg:orig_category":"Materiali E Componenti Elettronici",
    "sg:phone":"+39 02 9084 1416",
    "sg:postcode":"20083",
    "sg:province":"Milano",
    "wof:name":"B.f.m. Srl",
    "wof:placetype":"venue"
},
  "geometry": {"coordinates":[9.188141,45.463688],"type":"Point"}
}