{
  "type": "Feature",
  "properties": {
    "iso:country":"IT",
    "sg:address":"97011 Acate",
    "sg:city":"Acate",
    "sg:orig_category":"Automobili E Mezzi Di Trasporto",
    "sg:phone":"+39 0932 874128",
    "sg:postcode":"97011",
    "sg:province":"Ragusa",
    "sg:website":"http://www.citycarweb.com",
    "wof:name":"Citycar Di Pianeta Giovanna",
    "wof:placetype":"venue"
},
  "geometry": {"coordinates":[14.437396,37.016689],"type":"Point"}
}