{
  "type": "Feature",
  "properties": {
    "iso:country":"IT",
    "sg:address":"Via Di Tocqueville 11, 20154 Milan, Mi",
    "sg:classifiers":[
        {
            "category":"Banks & Credit Unions",
            "subcategory":"Bank",
            "type":"Services"
        }
    ],
    "sg:phone":"+39 02 655931",
    "sg:postcode":"20154",
    "sg:province":"Milano",
    "wof:name":"Deutsche Bank Factoring Spa",
    "wof:placetype":"venue"
},
  "geometry": {"coordinates":[9.186823,45.482449],"type":"Point"}
}