{
  "type": "Feature",
  "properties": {
    "iso:country":"IT",
    "sg:address":"98073 Mistretta",
    "sg:city":"Mistretta",
    "sg:orig_category":"Agricoltura, Orticoltura E Floricoltura",
    "sg:phone":"+39 0921 381789",
    "sg:postcode":"98073",
    "sg:province":"Messina",
    "sg:website":"http://www.agricolagiordano.it",
    "wof:name":"Frantoio Oleario Giordano Giuseppe",
    "wof:placetype":"venue"
},
  "geometry": {"coordinates":[14.355916,37.915169],"type":"Point"}
}