{
  "type": "Feature",
  "properties": {
    "addr:full":"00166 Roma Roma Roma 00166",
    "addr:postcode":"00166;00166",
    "iso:country":"IT",
    "sg:address":"00166 Roma",
    "sg:city":"Roma",
    "sg:orig_category":"Scuole E Servizi Scolastici. Centri Di Estetica E Cosmesi E Servizi. Ricerca, Selezione E Formazione Del Personale",
    "sg:phone":"+39 06 624 5554",
    "sg:postcode":"00166",
    "sg:province":"Roma",
    "wof:name":"Fabbri Oriana",
    "wof:placetype":"venue"
},
  "geometry": {"coordinates":[12.716368,41.815659],"type":"Point"}
}