{
  "type": "Feature",
  "properties": {
    "iso:country":"IT",
    "sg:address":"7, V. Delle Industrie 24048 Treviolo",
    "sg:city":"Treviolo",
    "sg:classifiers":[
        {
            "category":"Manufacturing",
            "subcategory":"Metals",
            "type":"Manufacturing & Wholesale Goods"
        }
    ],
    "sg:phone":"+39 39035690102",
    "sg:postcode":"24048",
    "sg:province":"Bergamo",
    "sg:tags":[
        "metallurgy",
        "metalworking"
    ],
    "sg:website":"http://www.marer.it",
    "wof:name":"M.a.r.e.r. Srl",
    "wof:placetype":"venue"
},
  "geometry": {"coordinates":[9.5997209549,45.6686782837],"type":"Point"}
}