{
  "type": "Feature",
  "properties": {
    "addr:full":"16146 Genova Genova Genova 16146",
    "addr:postcode":"16146;16146",
    "iso:country":"IT",
    "sg:address":"16146 Genova",
    "sg:city":"Genova",
    "sg:classifiers":[
        {
            "category":"Banks & Credit Unions",
            "subcategory":"Investment Brokerage",
            "type":"Services"
        }
    ],
    "sg:phone":"+39 010 362 1124",
    "sg:postcode":"16146",
    "sg:province":"Genova",
    "sg:tags":[
        "parrucchieri",
        "per",
        "donna"
    ],
    "wof:name":"Coppola By D'adamo",
    "wof:placetype":"venue"
},
  "geometry": {"coordinates":[8.9714622498,44.3972702026],"type":"Point"}
}