{
  "type": "Feature",
  "properties": {
    "iso:country":"IT",
    "sg:address":"20124 Milano",
    "sg:city":"Milano",
    "sg:orig_category":"Servizi Ausiliari Per Il Trasporto. Agenzie D'affari E Servizi Commerciali",
    "sg:phone":"+39 02 669 4003",
    "sg:postcode":"20124",
    "sg:province":"Milano",
    "wof:name":"Gasmare Srl",
    "wof:placetype":"venue"
},
  "geometry": {"coordinates":[9.202972,45.483746],"type":"Point"}
}