{
  "type": "Feature",
  "properties": {
    "iso:country":"IT",
    "sg:address":"66010 Torrevecchia Teatina",
    "sg:city":"Torrevecchia Teatina",
    "sg:orig_category":"Impiantistica E Prodotti Tecnologici Per Edilizia. Elettronica Professionale E Di Consumo. Accessori Dei Mezzi Di Trasporto. Forniture Industriali Per Prevenzione, Controllo E Sicurezza",
    "sg:phone":"+39 0871 361721",
    "sg:postcode":"66010",
    "sg:province":"Chieti",
    "sg:website":"http://www.2bautomazioni.it",
    "wof:name":"Due B Automazioni Srl",
    "wof:placetype":"venue"
},
  "geometry": {"coordinates":[14.214408,42.383713],"type":"Point"}
}