{
  "type": "Feature",
  "properties": {
    "addr:full":"3/a, Via S. Maria Valle 20123 Milano Milano Milano 20123",
    "addr:housenumber":"3 / a",
    "addr:postcode":"20123;20123",
    "addr:street":"Via S. Maria Valle",
    "iso:country":"IT",
    "sg:address":"3/a, Via S. Maria Valle 20123 Milano",
    "sg:city":"Milano",
    "sg:classifiers":[
        {
            "category":"Shopping",
            "subcategory":"Jewelry",
            "type":"Retail Goods"
        }
    ],
    "sg:phone":"+39 02 8901 0040",
    "sg:postcode":"20123",
    "sg:province":"Milano",
    "sg:tags":[
        "jewellery"
    ],
    "wof:name":"Zamero Bondi Di Israel Josefa",
    "wof:placetype":"venue"
},
  "geometry": {"coordinates":[9.184035,45.460117],"type":"Point"}
}