{
  "type": "Feature",
  "properties": {
    "iso:country":"IT",
    "sg:address":"26020 Agnadello",
    "sg:city":"Agnadello",
    "sg:orig_category":"Servizi E Lavori Per Agricoltura E Zootecnia",
    "sg:phone":"+39 0373 93094",
    "sg:postcode":"26020",
    "sg:province":"Cremona",
    "wof:name":"Rossi Francesco",
    "wof:placetype":"venue"
},
  "geometry": {"coordinates":[10.012727,45.142838],"type":"Point"}
}