{
  "type": "Feature",
  "properties": {
    "iso:country":"IT",
    "sg:address":"80133 Napoli",
    "sg:city":"Napoli",
    "sg:orig_category":"Arredamenti E Mobili Professionali. Impianti, Attrezzature E Forniture Sanitarie Ed Ospedaliere",
    "sg:phone":"+39 081 552 5315",
    "sg:postcode":"80133",
    "sg:province":"Napoli",
    "wof:name":"Rossi R. (s.r.l.)",
    "wof:placetype":"venue"
},
  "geometry": {"coordinates":[14.20492,40.909969],"type":"Point"}
}