{
  "type": "Feature",
  "properties": {
    "iso:country":"IT",
    "sg:address":"139, Viale Della Repubblica 59100 Prato",
    "sg:city":"Prato",
    "sg:orig_category":"Miscellaneous Products",
    "sg:phone":"+39 0574 582246",
    "sg:postcode":"59100",
    "sg:province":"Prato",
    "wof:name":"Masolini Aldo (s.r.l.)",
    "wof:placetype":"venue"
},
  "geometry": {"coordinates":[11.1263513565,43.9359703064],"type":"Point"}
}