{
  "type": "Feature",
  "properties": {
    "iso:country":"IT",
    "sg:address":"19021 Arcola",
    "sg:city":"Arcola",
    "sg:orig_category":"Trasporti E Spedizioni Merci",
    "sg:phone":"+39 0187 562990",
    "sg:postcode":"19021",
    "sg:province":"La Spezia",
    "wof:name":"Spe.de.mar. Srl",
    "wof:placetype":"venue"
},
  "geometry": {"coordinates":[9.887912,44.102432],"type":"Point"}
}