{
  "type": "Feature",
  "properties": {
    "iso:country":"IT",
    "sg:address":"Via Dati 54; Viserba; 47049",
    "sg:classifiers":[
        {
            "category":"Banks & Credit Unions",
            "subcategory":"Bank",
            "type":"Services"
        }
    ],
    "sg:phone":"+39 0541 734564",
    "wof:name":"Rolo Banca 1473 Spa",
    "wof:placetype":"venue"
},
  "geometry": {"coordinates":[12.540524,44.086575],"type":"Point"}
}