{
  "type": "Feature",
  "properties": {
    "addr:full":"31100 Treviso Treviso Treviso 31100",
    "addr:postcode":"31100;31100",
    "iso:country":"IT",
    "sg:address":"31100 Treviso",
    "sg:city":"Treviso",
    "sg:classifiers":[
        {
            "category":"Government",
            "subcategory":"Office",
            "type":"Public Place"
        }
    ],
    "sg:phone":"+39 0422 234861",
    "sg:postcode":"31100",
    "sg:province":"Treviso",
    "sg:tags":[
        "sector",
        "fair",
        "entertainment",
        "supply",
        "non-professional",
        "engineering",
        "congresses",
        "supplies",
        "professional",
        "automation",
        "electronic",
        "events",
        "machines"
    ],
    "wof:name":"Blow Up Audiovisivi Snc Di Coassin",
    "wof:placetype":"venue"
},
  "geometry": {"coordinates":[12.2286100388,45.657409668],"type":"Point"}
}