{
  "type": "Feature",
  "properties": {
    "iso:country":"IT",
    "sg:address":"20138 Milano",
    "sg:city":"Milano",
    "sg:orig_category":"Servizi Ausiliari Per Il Trasporto",
    "sg:phone":"+39 02 756 0476",
    "sg:postcode":"20138",
    "sg:province":"Milano",
    "wof:name":"Air Walser Srl",
    "wof:placetype":"venue"
},
  "geometry": {"coordinates":[9.26141,45.452328],"type":"Point"}
}