{
  "type": "Feature",
  "properties": {
    "addr:full":"36027 Rosa' Vicenza 36027",
    "addr:postcode":"36027;36027",
    "addr:street":"Rosa ' Vicenza",
    "iso:country":"IT",
    "sg:address":"36027 Rosa'",
    "sg:classifiers":[
        {
            "category":"Farming",
            "subcategory":"Fish & Marine Products",
            "type":"Manufacturing & Wholesale Goods"
        }
    ],
    "sg:phone":"+39 0424 581990",
    "sg:postcode":"36027",
    "sg:province":"Vicenza",
    "sg:tags":[
        "packaging",
        "articles",
        "packing",
        "plastics",
        "article"
    ],
    "wof:name":"Sacchettificio Di Rosa' Srl",
    "wof:placetype":"venue"
},
  "geometry": {"coordinates":[11.7820301056,45.7185287476],"type":"Point"}
}