{
  "type": "Feature",
  "properties": {
    "iso:country":"IT",
    "sg:address":"Via Napoli 71100 Foggia",
    "sg:city":"Foggia",
    "sg:classifiers":[
        {
            "category":"Farming",
            "subcategory":"Livestock Farm",
            "type":"Manufacturing & Wholesale Goods"
        }
    ],
    "sg:phone":"+39 0881 750472",
    "sg:postcode":"71100",
    "sg:province":"Foggia",
    "sg:tags":[
        "agriculture"
    ],
    "wof:name":"Co.s.e.me.-compagnia Sementi Elette Meridionali S.r.l.",
    "wof:placetype":"venue"
},
  "geometry": {"coordinates":[15.537906,41.432995],"type":"Point"}
}