{
  "type": "Feature",
  "properties": {
    "iso:country":"IT",
    "sg:address":"27049 Stradella",
    "sg:city":"Stradella",
    "sg:orig_category":"Serramenti Ed Infissi",
    "sg:phone":"+39 0385 246515",
    "sg:postcode":"27049",
    "sg:province":"Pavia",
    "wof:name":"Sami Di Pezone Domenico & Tonsino Salvatore S.n.c.",
    "wof:placetype":"venue"
},
  "geometry": {"coordinates":[9.307333,45.077862],"type":"Point"}
}