{
  "type": "Feature",
  "properties": {
    "iso:country":"IT",
    "sg:address":"22022 Casasco D'intelvi",
    "sg:orig_category":"Alberghi E Strutture Extra Alberghiere. Ospedali E Servizi Sanitari",
    "sg:phone":"+39 031 817988",
    "sg:postcode":"22022",
    "sg:province":"Como",
    "wof:name":"Il Ronco",
    "wof:placetype":"venue"
},
  "geometry": {"coordinates":[9.077765,45.942997],"type":"Point"}
}