{
  "type": "Feature",
  "properties": {
    "addr:full":"57025 Piombino Piombino Livorno 57025",
    "addr:postcode":"57025;57025",
    "iso:country":"IT",
    "sg:address":"57025 Piombino",
    "sg:city":"Piombino",
    "sg:orig_category":"Acque Minerali E Bevande, Naturali E Gassate - Commercio",
    "sg:phone":"+39 0565 49386",
    "sg:postcode":"57025",
    "sg:province":"Livorno",
    "wof:name":"Idam Sas Di Dell'agnello Nico & C.",
    "wof:placetype":"venue"
},
  "geometry": {"coordinates":[10.523568,42.939468],"type":"Point"}
}