{
  "type": "Feature",
  "properties": {
    "addr:full":"24270 Acquasparta TR",
    "addr:postcode":"24270",
    "addr:street":"Acquasparta",
    "iso:country":"IT",
    "sg:address":"24270 Acquasparta",
    "sg:orig_category":"Bottiglie, Fiaschi E Damigiane",
    "sg:phone":"+39 0744 242705",
    "sg:province":"TR",
    "sg:website":"http://www.firenzevetro.com",
    "wof:name":"Firenze Vetro Srl",
    "wof:placetype":"venue"
},
  "geometry": {"coordinates":[-82.247467,36.755268],"type":"Point"}
}