{
  "type": "Feature",
  "properties": {
    "iso:country":"IT",
    "sg:address":"Via Molino Di Sopra 64 37054 Nogara",
    "sg:city":"Nogara",
    "sg:classifiers":[
        {
            "category":"Bars & Pubs",
            "subcategory":"Hookah Bar",
            "type":"Food & Drink"
        }
    ],
    "sg:phone":"+39 0442 539066",
    "sg:postcode":"37054",
    "sg:province":"Verona",
    "sg:tags":[
        "aluminium",
        "tin",
        "bottle"
    ],
    "sg:website":"www.rexam.com",
    "wof:name":"Rexam Beverage Can Italia Srl",
    "wof:placetype":"venue"
},
  "geometry": {"coordinates":[11.051482,45.191486],"type":"Point"}
}