{
  "type": "Feature",
  "properties": {
    "iso:country":"IT",
    "sg:address":"48017 Conselice",
    "sg:city":"Conselice",
    "sg:orig_category":"Forniture Per Uffici",
    "sg:phone":"+39 0545 980512",
    "sg:postcode":"48017",
    "sg:province":"Ravenna",
    "wof:name":"Tuttocarta Snc Di Dal Pozzo Doriano E Frabbi Fabio",
    "wof:placetype":"venue"
},
  "geometry": {"coordinates":[11.8308935165,44.51171875],"type":"Point"}
}