{
  "type": "Feature",
  "properties": {
    "addr:full":"Via Pio Corsi 63; Mizza Monteferrato; 14049 Asti 14049",
    "addr:housenumber":"63",
    "addr:postcode":"14049;14049",
    "addr:street":"Via Pio Corsi;Monteferrato",
    "iso:country":"IT",
    "sg:address":"Via Pio Corsi 63; Mizza Monteferrato; 14049",
    "sg:classifiers":[
        {
            "category":"Banks & Credit Unions",
            "subcategory":"Bank",
            "type":"Services"
        }
    ],
    "sg:phone":"+39 0141 726282",
    "sg:postcode":"14049",
    "sg:province":"Asti",
    "wof:name":"Cariverona Banca Spa",
    "wof:placetype":"venue"
},
  "geometry": {"coordinates":[8.357672,44.773979],"type":"Point"}
}