{
  "type": "Feature",
  "properties": {
    "iso:country":"IT",
    "sg:address":"53024 Montalcino",
    "sg:city":"Montalcino",
    "sg:orig_category":"Ristorazione E Locali Pubblici Affini. Ristoranti Ed Esercizi Affini. Servizi Ausiliari Di Ristorazione E Di Intrattenimento",
    "sg:phone":"+39 0577 847150",
    "sg:postcode":"53024",
    "sg:province":"Siena",
    "sg:website":"http://www.grappoloblu.it",
    "wof:name":"Il Grappolo Blu - Camere Per Turisti",
    "wof:placetype":"venue"
},
  "geometry": {"coordinates":[11.45663,43.042759],"type":"Point"}
}