{
  "type": "Feature",
  "properties": {
    "addr:full":"19016 Monterosso Al Mare Monterosso al Mare La Spezia 19016",
    "addr:postcode":"19016;19016",
    "iso:country":"IT",
    "sg:address":"19016 Monterosso Al Mare",
    "sg:city":"Monterosso al Mare",
    "sg:orig_category":"Alberghi E Strutture Extra Alberghiere",
    "sg:phone":"+39 335 476 804",
    "sg:postcode":"19016",
    "sg:province":"La Spezia",
    "wof:name":"Vidic Agenzia Immobiliare",
    "wof:placetype":"venue"
},
  "geometry": {"coordinates":[9.684386,44.134777],"type":"Point"}
}