{
  "type": "Feature",
  "properties": {
    "addr:full":"80027 Frattamaggiore Frattamaggiore Napoli 80027",
    "addr:postcode":"80027;80027",
    "iso:country":"IT",
    "sg:address":"80027 Frattamaggiore",
    "sg:city":"Frattamaggiore",
    "sg:orig_category":"Nautica. Forniture Per Attivita' Commerciali Ed Artigianali",
    "sg:phone":"+39 081 834 1495",
    "sg:postcode":"80027",
    "sg:province":"Napoli",
    "wof:name":"Capasso Carmine",
    "wof:placetype":"venue"
},
  "geometry": {"coordinates":[14.277716,40.938816],"type":"Point"}
}