{
  "type": "Feature",
  "properties": {
    "iso:country":"IT",
    "sg:address":"31047 Ponte Di Piave",
    "sg:city":"Negrisia",
    "sg:orig_category":"Aziende Agricole",
    "sg:phone":"+39 0422 854607",
    "sg:postcode":"31047",
    "sg:province":"Treviso",
    "wof:name":"Azienda Agricola Lorenzon Antonello",
    "wof:placetype":"venue"
},
  "geometry": {"coordinates":[12.432185,45.734169],"type":"Point"}
}