{
  "type": "Feature",
  "properties": {
    "addr:full":"90144 Palermo Palermo Palermo 90144",
    "addr:postcode":"90144;90144",
    "iso:country":"IT",
    "sg:address":"90144 Palermo",
    "sg:city":"Palermo",
    "sg:orig_category":"Vetro: Prodotti E Lavorazioni. Forniture Industriali Per Prevenzione, Controllo E Sicurezza",
    "sg:phone":"+39 091 625 9469",
    "sg:postcode":"90144",
    "sg:province":"Palermo",
    "wof:name":"La Greca Edmondo",
    "wof:placetype":"venue"
},
  "geometry": {"coordinates":[13.344983,38.13937],"type":"Point"}
}