{
  "type": "Feature",
  "properties": {
    "iso:country":"IT",
    "sg:address":"82, V. Colombo 29100 Piacenza",
    "sg:city":"Piacenza",
    "sg:classifiers":[
        {
            "category":"Bars & Pubs",
            "subcategory":"Nightclub",
            "type":"Food & Drink"
        }
    ],
    "sg:phone":"+39 0523 592648",
    "sg:postcode":"29100",
    "sg:province":"Piacenza",
    "sg:tags":[
        "cake",
        "bread"
    ],
    "sg:website":"http://www.paginegialle.it/panrapetti",
    "wof:name":"Panificio Rapetti",
    "wof:placetype":"venue"
},
  "geometry": {"coordinates":[9.709244,45.045319],"type":"Point"}
}