{
  "type": "Feature",
  "properties": {
    "iso:country":"IT",
    "sg:address":"4, Viale Ventuno Aprile 00162 Roma",
    "sg:city":"Roma",
    "sg:classifiers":[
        {
            "category":"Travel",
            "subcategory":"Travel Agent",
            "type":"Entertainment"
        }
    ],
    "sg:phone":"+39 39068600602",
    "sg:postcode":"00162",
    "sg:province":"Roma",
    "sg:tags":[
        "business"
    ],
    "wof:name":"Lo.an. Spa",
    "wof:placetype":"venue"
},
  "geometry": {"coordinates":[12.482325,41.895466],"type":"Point"}
}