{
  "type": "Feature",
  "properties": {
    "iso:country":"IT",
    "sg:address":"20037 Paderno Dugnano",
    "sg:city":"Paderno Dugnano",
    "sg:orig_category":"Lavorazioni Metalli, Stampaggio E Saldatura",
    "sg:phone":"+39 02 918 1071",
    "sg:postcode":"20037",
    "sg:province":"Milano",
    "wof:name":"Riccardo Santambrogio Forgiatura",
    "wof:placetype":"venue"
},
  "geometry": {"coordinates":[9.160024,45.570141],"type":"Point"}
}