{
  "type": "Feature",
  "properties": {
    "iso:country":"IT",
    "sg:address":"10024 Moncalieri",
    "sg:city":"Moncalieri",
    "sg:orig_category":"Cancelli, Porte E Portoni Automatici E Telecomandati",
    "sg:phone":"+39 011 606 1747",
    "sg:postcode":"10024",
    "sg:province":"Torino",
    "wof:name":"Cam Di Cortini",
    "wof:placetype":"venue"
},
  "geometry": {"coordinates":[7.346722,45.09626],"type":"Point"}
}