{
  "type": "Feature",
  "properties": {
    "iso:country":"IT",
    "sg:address":"90139 Palermo",
    "sg:city":"Palermo",
    "sg:orig_category":"Prodotti Alimentari",
    "sg:phone":"+39 091 581415",
    "sg:postcode":"90139",
    "sg:province":"Palermo",
    "wof:name":"Gargano Rosa",
    "wof:placetype":"venue"
},
  "geometry": {"coordinates":[13.3562908173,38.1288375854],"type":"Point"}
}