{
  "type": "Feature",
  "properties": {
    "iso:country":"IT",
    "sg:address":"25132 Brescia",
    "sg:city":"Brescia",
    "sg:orig_category":"Macchine, Impianti Ed Attrezzature Per Abbigliamento E Pelletterie",
    "sg:phone":"+39 030 373 3349",
    "sg:postcode":"25132",
    "sg:province":"Brescia",
    "wof:name":"B.l.u. Service Srl",
    "wof:placetype":"venue"
},
  "geometry": {"coordinates":[10.161521,45.543995],"type":"Point"}
}