{
  "type": "Feature",
  "properties": {
    "addr:full":"113, Via Roma 50058 Signa Signa Firenze 50058",
    "addr:housenumber":"113",
    "addr:postcode":"50058;50058",
    "addr:street":"Via Roma",
    "iso:country":"IT",
    "sg:address":"113, Via Roma 50058 Signa",
    "sg:city":"Signa",
    "sg:classifiers":[
        {
            "category":"Personal",
            "subcategory":"Shoe Repair & Shine",
            "type":"Services"
        }
    ],
    "sg:phone":"+39 39055875633",
    "sg:postcode":"50058",
    "sg:province":"Firenze",
    "sg:tags":[
        "leather"
    ],
    "wof:name":"Bettini Raffaello (s.r.l.)",
    "wof:placetype":"venue"
},
  "geometry": {"coordinates":[11.133806,43.822876],"type":"Point"}
}