{
  "type": "Feature",
  "properties": {
    "iso:country":"IT",
    "sg:address":"87075 Trebisacce",
    "sg:city":"Trebisacce",
    "sg:orig_category":"Macchine Agricole - Commercio E Riparazione",
    "sg:phone":"+39 0981 51890",
    "sg:postcode":"87075",
    "sg:province":"Cosenza",
    "wof:name":"L'agricola Calabrese Sas Di Osvaldo Filice",
    "wof:placetype":"venue"
},
  "geometry": {"coordinates":[16.517162,39.882526],"type":"Point"}
}