{
  "type": "Feature",
  "properties": {
    "iso:country":"IT",
    "sg:address":"12084 Mondov\u00ec",
    "sg:orig_category":"Porte",
    "sg:phone":"+39 0174 47920",
    "sg:postcode":"12084",
    "sg:province":"Cuneo",
    "sg:website":"http://www.batlegno.com",
    "wof:name":"Bat Legno Snc Di Avagnina Giacomo E C.",
    "wof:placetype":"venue"
},
  "geometry": {"coordinates":[7.8177599907,44.4049758911],"type":"Point"}
}