{
  "type": "Feature",
  "properties": {
    "addr:full":"10040 La Loggia La Loggia Torino 10040",
    "addr:housenumber":"10040",
    "addr:postcode":"10040",
    "addr:street":"La",
    "iso:country":"IT",
    "sg:address":"10040 La Loggia",
    "sg:city":"La Loggia",
    "sg:orig_category":"Utensili Meccanici E Materiali",
    "sg:phone":"+39 011 962 7351",
    "sg:postcode":"10040",
    "sg:province":"Torino",
    "wof:name":"Cargnino Celeste",
    "wof:placetype":"venue"
},
  "geometry": {"coordinates":[7.671617,45.001396],"type":"Point"}
}