{
  "type": "Feature",
  "properties": {
    "iso:country":"IT",
    "sg:address":"43100 Ugozzolo",
    "sg:orig_category":"Macchine Utensili E Impianti",
    "sg:phone":"+39 0521 608080",
    "sg:postcode":"43100",
    "sg:province":"Parma",
    "wof:name":"Saldotecnica (s.r.l.)",
    "wof:placetype":"venue"
},
  "geometry": {"coordinates":[10.371952,44.842129],"type":"Point"}
}