{
  "type": "Feature",
  "properties": {
    "iso:country":"IT",
    "sg:address":"10064 Pinerolo",
    "sg:city":"Pinerolo",
    "sg:orig_category":"Materiali E Componenti Elettronici",
    "sg:phone":"+39 0121 322444",
    "sg:postcode":"10064",
    "sg:province":"Torino",
    "sg:website":"http://www.cazzadori.it",
    "wof:name":"Cazzadori Vittorio",
    "wof:placetype":"venue"
},
  "geometry": {"coordinates":[7.349995,44.885025],"type":"Point"}
}