{
  "type": "Feature",
  "properties": {
    "addr:full":"Zona Industriale 81030 Teverola Teverola Caserta 81030",
    "addr:postcode":"81030;81030",
    "addr:street":"Zona Industriale",
    "iso:country":"IT",
    "sg:address":"Zona Industriale 81030 Teverola",
    "sg:city":"Teverola",
    "sg:classifiers":[
        {
            "category":"Structure",
            "subcategory":"Factory",
            "type":"Public Place"
        }
    ],
    "sg:phone":"+39 081 811 8070",
    "sg:postcode":"81030",
    "sg:province":"Caserta",
    "sg:tags":[
        "complete",
        "installations"
    ],
    "wof:name":"Transime Sud Srl",
    "wof:placetype":"venue"
},
  "geometry": {"coordinates":[14.3321943283,41.0754165649],"type":"Point"}
}