{
  "type": "Feature",
  "properties": {
    "addr:full":"00040 Nemi Nemi Roma 00040",
    "addr:postcode":"00040;roma 00040",
    "iso:country":"IT",
    "sg:address":"00040 Nemi",
    "sg:city":"Nemi",
    "sg:orig_category":"Dolciumi E Gelati",
    "sg:phone":"+39 06 936 8817",
    "sg:postcode":"00040",
    "sg:province":"Roma",
    "wof:name":"Apicoltura Di Gino E Ivo De Sanctis Snc",
    "wof:placetype":"venue"
},
  "geometry": {"coordinates":[12.679378,41.756817],"type":"Point"}
}