{
  "type": "Feature",
  "properties": {
    "iso:country":"IT",
    "sg:address":"18, Via Tezze Di Cornedo 36073 Cornedo Vicentino",
    "sg:city":"Cornedo Vicentino",
    "sg:classifiers":[
        {
            "category":"Shopping",
            "type":"Retail Goods"
        }
    ],
    "sg:phone":"+39 0445 953141",
    "sg:postcode":"36073",
    "sg:province":"Vicenza",
    "sg:tags":[
        "finished",
        "-",
        "metallic"
    ],
    "wof:name":"Co.s.a.p. S.c.a.r.l.",
    "wof:placetype":"venue"
},
  "geometry": {"coordinates":[11.3569803238,45.6101150513],"type":"Point"}
}