{
  "type": "Feature",
  "properties": {
    "iso:country":"IT",
    "sg:address":"57121 Livorno",
    "sg:city":"Livorno",
    "sg:orig_category":"Imprese Di Costruzioni Civili Ed Industriali",
    "sg:phone":"+39 0586 409599",
    "sg:postcode":"57121",
    "sg:province":"Livorno",
    "wof:name":"Cecchi Massimo",
    "wof:placetype":"venue"
},
  "geometry": {"coordinates":[10.340583,43.56361],"type":"Point"}
}