{
  "type": "Feature",
  "properties": {
    "addr:full":"Via De Lai 2, 39100 Bolzano, Bz Bolzano Bolzano/Bozen 39100",
    "addr:housenumber":"2",
    "addr:postcode":"39100;39100",
    "addr:street":"Via De Lai",
    "iso:country":"IT",
    "sg:address":"Via De Lai 2, 39100 Bolzano, Bz",
    "sg:city":"Bolzano",
    "sg:classifiers":[
        {
            "category":"Banks & Credit Unions",
            "subcategory":"Bank",
            "type":"Services"
        }
    ],
    "sg:postcode":"39100",
    "sg:province":"Bolzano/Bozen",
    "wof:name":"Cassa Rurale Di Bolzano Scrl- Raiffeisenkasse Bozen Gmbh",
    "wof:placetype":"venue"
},
  "geometry": {"coordinates":[11.328239,46.461643],"type":"Point"}
}