{
  "type": "Feature",
  "properties": {
    "iso:country":"IT",
    "sg:address":"25080 Padenghe Sul Garda",
    "sg:city":"Padenghe sul Garda",
    "sg:orig_category":"Nastri Carta, Tessuto E Plastica",
    "sg:phone":"+39 030 990 0989",
    "sg:postcode":"25080",
    "sg:province":"Brescia",
    "sg:website":"http://www.combyitalia.it",
    "wof:name":"Comby Italia Srl",
    "wof:placetype":"venue"
},
  "geometry": {"coordinates":[10.503839,45.506386],"type":"Point"}
}