{
  "type": "Feature",
  "properties": {
    "iso:country":"IT",
    "sg:address":"36027 Ros\u00e0",
    "sg:classifiers":[
        {
            "category":"Cinema",
            "subcategory":"Movie Theater",
            "type":"Entertainment"
        }
    ],
    "sg:phone":"+39 0424 85404",
    "sg:postcode":"36027",
    "sg:province":"Vicenza",
    "sg:tags":[
        "bobine"
    ],
    "sg:website":"http://www.parolin.it",
    "wof:name":"Parolin Vittorio Snc",
    "wof:placetype":"venue"
},
  "geometry": {"coordinates":[11.761703,45.72839],"type":"Point"}
}