{
  "type": "Feature",
  "properties": {
    "addr:full":"80142 Napoli Napoli Napoli 80142",
    "addr:housenumber":"80142",
    "addr:postcode":"80142",
    "iso:country":"IT",
    "sg:address":"80142 Napoli",
    "sg:city":"Napoli",
    "sg:orig_category":"Accessori Moda D'abbigliamento. Shopping",
    "sg:phone":"+39 081 269367",
    "sg:postcode":"80142",
    "sg:province":"Napoli",
    "wof:name":"Panico Franca",
    "wof:placetype":"venue"
},
  "geometry": {"coordinates":[14.221219,40.861385],"type":"Point"}
}