{
  "type": "Feature",
  "properties": {
    "iso:country":"IT",
    "sg:address":"12032 Barge",
    "sg:city":"Barge",
    "sg:orig_category":"Caminetti, Forni Da Giardino E Barbecues",
    "sg:phone":"+39 0175 346407",
    "sg:postcode":"12032",
    "sg:province":"Cuneo",
    "wof:name":"Domenino Giuseppe Snc",
    "wof:placetype":"venue"
},
  "geometry": {"coordinates":[7.340854,44.73624],"type":"Point"}
}