{
  "type": "Feature",
  "properties": {
    "addr:full":"00185 Roma Roma Roma 00185",
    "addr:postcode":"00185;00185",
    "iso:country":"IT",
    "sg:address":"00185 Roma",
    "sg:city":"Roma",
    "sg:orig_category":"Ristorazione E Locali Pubblici Affini. Ristoranti Ed Esercizi Affini. Servizi Ausiliari Di Ristorazione E Di Intrattenimento",
    "sg:phone":"+39 06 490617",
    "sg:postcode":"00185",
    "sg:province":"Roma",
    "sg:website":"http://www.programmaitalia.com10/12",
    "wof:name":"Ristorante Pizzeria '10-12' G. Moretti",
    "wof:placetype":"venue"
},
  "geometry": {"coordinates":[12.504059,41.901791],"type":"Point"}
}