{
  "type": "Feature",
  "properties": {
    "iso:country":"IT",
    "sg:address":"30037 Scorze'",
    "sg:classifiers":[
        {
            "category":"Health Services",
            "subcategory":"Health Practitioner",
            "type":"Services"
        }
    ],
    "sg:phone":"+39 041 584 1558",
    "sg:postcode":"30037",
    "sg:province":"Venezia",
    "sg:tags":[
        "medici"
    ],
    "wof:name":"D.s. Medica",
    "wof:placetype":"venue"
},
  "geometry": {"coordinates":[12.155953,45.528606],"type":"Point"}
}