{
  "type": "Feature",
  "properties": {
    "addr:full":"95121 Catania Catania Catania 95121",
    "addr:postcode":"95121;95121",
    "iso:country":"IT",
    "sg:address":"95121 Catania",
    "sg:city":"Catania",
    "sg:orig_category":"Petroli, Gas E Combustibili. Termotecnica E Riscaldamento, Apparecchiature E Servizi",
    "sg:phone":"+39 095 723 0001",
    "sg:postcode":"95121",
    "sg:province":"Catania",
    "sg:website":"http://www.sicilianacarbolio.it",
    "wof:name":"Siciliana Carbolio Spa",
    "wof:placetype":"venue"
},
  "geometry": {"coordinates":[15.0089883804,37.4158554077],"type":"Point"}
}