{
  "type": "Feature",
  "properties": {
    "iso:country":"IT",
    "sg:address":"52100 Arezzo",
    "sg:city":"Arezzo",
    "sg:orig_category":"Pubblica Amministrazione",
    "sg:phone":"+39 0575117",
    "sg:postcode":"52100",
    "sg:province":"Arezzo",
    "wof:name":"Guardia Di Finanza",
    "wof:placetype":"venue"
},
  "geometry": {"coordinates":[11.8788003922,43.4607772827],"type":"Point"}
}