{
  "type": "Feature",
  "properties": {
    "addr:full":"30, Strada Di Serravalle 15067 Novi Ligure Novi Ligure Alessandria 15067",
    "addr:postcode":"15067;15067",
    "addr:street":"Strada Di Serravalle",
    "iso:country":"IT",
    "sg:address":"30, Strada Di Serravalle 15067 Novi Ligure",
    "sg:city":"Novi Ligure",
    "sg:classifiers":[
        {
            "category":"Wholesale",
            "subcategory":"Drugs",
            "type":"Manufacturing & Wholesale Goods"
        }
    ],
    "sg:phone":"+39 0143 743283",
    "sg:postcode":"15067",
    "sg:province":"Alessandria",
    "sg:tags":[
        "chemical",
        "pharmaceutical"
    ],
    "wof:name":"Smurfit Packaging Italia S.p.a.",
    "wof:placetype":"venue"
},
  "geometry": {"coordinates":[8.819156,44.743443],"type":"Point"}
}