{
  "type": "Feature",
  "properties": {
    "addr:full":"Via Matteotti 10 20060 Pessano Con Bornago Ornago Milano 20060",
    "addr:housenumber":"10",
    "addr:postcode":"20060;20060",
    "addr:street":"Via Matteotti",
    "iso:country":"IT",
    "sg:address":"Via Matteotti 10 20060 Pessano Con Bornago",
    "sg:city":"Ornago",
    "sg:orig_category":"Servo Drives",
    "sg:phone":"+39 02 9574 0078",
    "sg:postcode":"20060",
    "sg:province":"Milano",
    "wof:name":"Ele - Fantini Srl",
    "wof:placetype":"venue"
},
  "geometry": {"coordinates":[9.401821,45.564964],"type":"Point"}
}