{
  "type": "Feature",
  "properties": {
    "iso:country":"IT",
    "sg:address":"Via Boccherini 24/2 40033 Casalecchio Di Reno",
    "sg:city":"Casalecchio di Reno",
    "sg:orig_category":"Grain Moisture Measurement Instruments",
    "sg:phone":"+39 051 573235",
    "sg:postcode":"40033",
    "sg:province":"Bologna",
    "sg:website":"www.naelettronica.it",
    "wof:name":"Na Elettronica Snc Di Diamanti Paolo & C",
    "wof:placetype":"venue"
},
  "geometry": {"coordinates":[11.258288,44.479397],"type":"Point"}
}