{
  "type": "Feature",
  "properties": {
    "addr:full":"20025 Legnano Legnano Milano 20025",
    "addr:postcode":"20025;20025",
    "iso:country":"IT",
    "sg:address":"20025 Legnano",
    "sg:city":"Legnano",
    "sg:classifiers":[
        {
            "category":"Professional",
            "subcategory":"Engineering",
            "type":"Services"
        }
    ],
    "sg:phone":"+39 0331 479111",
    "sg:postcode":"20025",
    "sg:province":"Milano",
    "sg:tags":[
        "equipment",
        "product",
        "industrial",
        "electrical"
    ],
    "sg:website":"http://www.abb.com",
    "wof:name":"Abb Trasmissione & Distribuzione Spa Divisione Trasformatori",
    "wof:placetype":"venue"
},
  "geometry": {"coordinates":[9.014976,45.485619],"type":"Point"}
}