{
  "type": "Feature",
  "properties": {
    "iso:country":"IT",
    "sg:address":"41049 Sassuolo",
    "sg:city":"Sassuolo",
    "sg:orig_category":"Ceramiche: Prodotti E Lavorazioni. Forniture Per Attivita' Industriali",
    "sg:phone":"+39 0536 802955",
    "sg:postcode":"41049",
    "sg:province":"Modena",
    "wof:name":"K. Erremme S.r.l.",
    "wof:placetype":"venue"
},
  "geometry": {"coordinates":[10.921174,44.654366],"type":"Point"}
}