{
  "type": "Feature",
  "properties": {
    "iso:country":"IT",
    "sg:address":"09010 Piscinas",
    "sg:orig_category":"Materiali Edili",
    "sg:postcode":"09010",
    "sg:province":"Cagliari",
    "wof:name":"Societa' Sarda Di Bentonite (s.p.a.)",
    "wof:placetype":"venue"
},
  "geometry": {"coordinates":[8.665813,39.077171],"type":"Point"}
}