{
  "type": "Feature",
  "properties": {
    "addr:full":"55049 Viareggio Viareggio Lucca 55049",
    "addr:postcode":"55049;55049",
    "iso:country":"IT",
    "sg:address":"55049 Viareggio",
    "sg:city":"Viareggio",
    "sg:orig_category":"Trasporti E Spedizioni Merci",
    "sg:phone":"+39 0584 48292",
    "sg:postcode":"55049",
    "sg:province":"Lucca",
    "sg:website":"http://www.riviera-express.it",
    "wof:name":"Riviera Express Di Cappelli Massimo",
    "wof:placetype":"venue"
},
  "geometry": {"coordinates":[10.27123,43.851627],"type":"Point"}
}