{
  "type": "Feature",
  "properties": {
    "iso:country":"IT",
    "sg:address":"Via Locatelli Antonio 50 24121 Bergamo",
    "sg:city":"Bergamo",
    "sg:classifiers":[
        {
            "category":"Home & Garden",
            "subcategory":"Carpets & Floor Coverings",
            "type":"Retail Goods"
        }
    ],
    "sg:phone":"+39 035 225362",
    "sg:postcode":"24121",
    "sg:province":"Bergamo",
    "sg:tags":[
        "wall",
        "insulating"
    ],
    "sg:website":"www.edilmontaggi.it",
    "wof:name":"Edil Montaggi Srl",
    "wof:placetype":"venue"
},
  "geometry": {"coordinates":[9.669227,45.698311],"type":"Point"}
}