{
  "type": "Feature",
  "properties": {
    "addr:full":"Via S. Maria Novella 121; Fiano Firenze 50050",
    "addr:housenumber":"121",
    "addr:postcode":"50050",
    "addr:street":"Via S. Maria Novella",
    "iso:country":"IT",
    "sg:address":"Via S. Maria Novella 121; Fiano",
    "sg:classifiers":[
        {
            "category":"Travel",
            "subcategory":"Travel Agent",
            "type":"Entertainment"
        }
    ],
    "sg:phone":"+39 390 571 6695",
    "sg:postcode":"50050",
    "sg:province":"Firenze",
    "wof:name":"Sonesta Castello Di S. Maria Novella",
    "wof:placetype":"venue"
},
  "geometry": {"coordinates":[10.9129,43.554661],"type":"Point"}
}