{
  "type": "Feature",
  "properties": {
    "addr:full":"20010 Vanzago Vanzago Milano 20010",
    "addr:postcode":"20010;20010",
    "iso:country":"IT",
    "sg:address":"20010 Vanzago",
    "sg:city":"Vanzago",
    "sg:orig_category":"Minuterie Metalliche E Ferramenta",
    "sg:phone":"+39 02 9354 0289",
    "sg:postcode":"20010",
    "sg:province":"Milano",
    "wof:name":"Ar.tec Sas Di Malabarba Massimiliano",
    "wof:placetype":"venue"
},
  "geometry": {"coordinates":[9.024312973,45.5065498352],"type":"Point"}
}