{
  "type": "Feature",
  "properties": {
    "iso:country":"IT",
    "sg:address":"20063 Cernusco Sul Naviglio",
    "sg:city":"Cernusco sul Naviglio",
    "sg:orig_category":"Servizi Di Magazzinaggio E Movimentazione",
    "sg:phone":"+39 02 9214 3575",
    "sg:postcode":"20063",
    "sg:province":"Milano",
    "wof:name":"So.ge.ma. Spa",
    "wof:placetype":"venue"
},
  "geometry": {"coordinates":[9.271413,45.521442],"type":"Point"}
}