{
  "type": "Feature",
  "properties": {
    "iso:country":"IT",
    "sg:address":"10095 Grugliasco",
    "sg:city":"Grugliasco",
    "sg:orig_category":"Studi E Consulenze Tecniche E Industriali. Consulenze Tecniche, Amministrative E Perizie",
    "sg:phone":"+39 011 707 1554",
    "sg:postcode":"10095",
    "sg:province":"Torino",
    "sg:website":"http://www.serimscarl.net",
    "wof:name":"Serim - Cenasca Soc.coop.r.l.",
    "wof:placetype":"venue"
},
  "geometry": {"coordinates":[7.625241,45.058384],"type":"Point"}
}