{
  "type": "Feature",
  "properties": {
    "addr:full":"16124 Genova Genova Genova 16124",
    "addr:postcode":"16124;16124",
    "iso:country":"IT",
    "sg:address":"16124 Genova",
    "sg:city":"Genova",
    "sg:orig_category":"Centri Di Estetica E Cosmesi E Servizi. Prodotti Cosmetici E Da Toeletta",
    "sg:phone":"+39 010 247 6889",
    "sg:postcode":"16124",
    "sg:province":"Genova",
    "wof:name":"Ghiorzo Eleonora",
    "wof:placetype":"venue"
},
  "geometry": {"coordinates":[8.929619,44.411659],"type":"Point"}
}