{
  "type": "Feature",
  "properties": {
    "iso:country":"IT",
    "sg:address":"Via Quarantadue Martiri 207 28921 Verbania",
    "sg:city":"Verbania",
    "sg:classifiers":[
        {
            "category":"Professional",
            "subcategory":"Business Services",
            "type":"Services"
        }
    ],
    "sg:phone":"+39 0323 406926",
    "sg:postcode":"28921",
    "sg:province":"Verbano-Cusio-Ossola",
    "sg:tags":[
        "high-precision",
        "mechanic"
    ],
    "sg:website":"www.tc-cardana.com",
    "wof:name":"Tecnologie Costruttive Tc Srl",
    "wof:placetype":"venue"
},
  "geometry": {"coordinates":[8.462587,45.93882],"type":"Point"}
}