{
  "type": "Feature",
  "properties": {
    "addr:full":"6, Via Pontida 63039 San Benedetto Del Tronto San Benedetto del Tronto Ascoli Piceno 63039",
    "addr:postcode":"63039;63039",
    "addr:street":"Via Pontida;Piceno",
    "iso:country":"IT",
    "sg:address":"6, Via Pontida 63039 San Benedetto Del Tronto",
    "sg:city":"San Benedetto del Tronto",
    "sg:classifiers":[
        {
            "category":"Wholesale",
            "subcategory":"Medical Equipment & Supplies",
            "type":"Manufacturing & Wholesale Goods"
        }
    ],
    "sg:phone":"+39 0735 656670",
    "sg:postcode":"63039",
    "sg:province":"Ascoli Piceno",
    "sg:tags":[
        "-",
        "health",
        "instrument"
    ],
    "wof:name":"Tds S.r.l.",
    "wof:placetype":"venue"
},
  "geometry": {"coordinates":[13.896484,42.90012],"type":"Point"}
}