{
  "type": "Feature",
  "properties": {
    "iso:country":"IT",
    "sg:address":"20124 Milano",
    "sg:city":"Milano",
    "sg:orig_category":"Servizi E Lavori Per Agricoltura E Zootecnia",
    "sg:phone":"+39 02 673 3481",
    "sg:postcode":"20124",
    "sg:province":"Milano",
    "wof:name":"Comieco - Consorzio Naz. P.i. Recup.e.i.ric.d.imbal.a Ba.cel.",
    "wof:placetype":"venue"
},
  "geometry": {"coordinates":[9.200092,45.481461],"type":"Point"}
}