{
  "type": "Feature",
  "properties": {
    "iso:country":"IT",
    "sg:address":"Via Arconti 4 21013 Gallarate",
    "sg:city":"Gallarate",
    "sg:classifiers":[
        {
            "category":"Banks & Credit Unions",
            "subcategory":"Financial Services",
            "type":"Services"
        }
    ],
    "sg:phone":"+39 0331 793215",
    "sg:postcode":"21013",
    "sg:province":"Varese",
    "sg:tags":[
        "knitwear",
        "industry",
        "lace"
    ],
    "wof:name":"Ricamificio Carlo Canziani Spa",
    "wof:placetype":"venue"
},
  "geometry": {"coordinates":[8.803926,45.66555],"type":"Point"}
}