{
  "type": "Feature",
  "properties": {
    "iso:country":"IT",
    "sg:address":"348, Corso Moncalieri 10133 Torino",
    "sg:city":"Torino",
    "sg:classifiers":[
        {
            "category":"Farming",
            "subcategory":"Livestock Farm",
            "type":"Manufacturing & Wholesale Goods"
        }
    ],
    "sg:phone":"+39 011 661 4996",
    "sg:postcode":"10133",
    "sg:province":"Torino",
    "sg:tags":[
        "agriculture"
    ],
    "wof:name":"Erba Vivai S.r.l.",
    "wof:placetype":"venue"
},
  "geometry": {"coordinates":[7.694828,45.058914],"type":"Point"}
}