{
  "type": "Feature",
  "properties": {
    "iso:country":"IT",
    "sg:address":"10, Via Solari Andrea 20144 Milano",
    "sg:city":"Milano",
    "sg:classifiers":[
        {
            "category":"Manufacturing",
            "subcategory":"Rubber & Plastics",
            "type":"Manufacturing & Wholesale Goods"
        }
    ],
    "sg:phone":"+39 390 248 0431",
    "sg:postcode":"20144",
    "sg:province":"Milano",
    "sg:tags":[
        "packaging",
        "material",
        "-"
    ],
    "wof:name":"Goglio Luigi-milano S.p.a.",
    "wof:placetype":"venue"
},
  "geometry": {"coordinates":[9.1642560959,45.45570755],"type":"Point"}
}