{
  "type": "Feature",
  "properties": {
    "addr:full":"2, Localita' Cusona 53037 San Gimignano San Gimignano Siena 53037",
    "addr:postcode":"53037;gimignano;53037",
    "addr:street":"Localita ' Cusona;Gimignano Siena",
    "iso:country":"IT",
    "sg:address":"2, Localita' Cusona 53037 San Gimignano",
    "sg:city":"San Gimignano",
    "sg:classifiers":[
        {
            "category":"Manufacturing",
            "subcategory":"Rubber & Plastics",
            "type":"Manufacturing & Wholesale Goods"
        }
    ],
    "sg:phone":"+39 0577 989237",
    "sg:postcode":"53037",
    "sg:province":"Siena",
    "wof:name":"Espansi Tecnici (s.a.s.) Gaggelli Mirco",
    "wof:placetype":"venue"
},
  "geometry": {"coordinates":[11.3305139542,43.3186607361],"type":"Point"}
}