{
  "type": "Feature",
  "properties": {
    "iso:country":"IT",
    "sg:address":"66, Corso Della Giovecca 44100 Ferrara",
    "sg:city":"Ferrara",
    "sg:classifiers":[
        {
            "category":"Shopping",
            "subcategory":"Clothing, Apparel, & Fashions",
            "type":"Retail Goods"
        }
    ],
    "sg:phone":"+39 0532 209091",
    "sg:postcode":"44100",
    "sg:province":"Ferrara",
    "sg:tags":[
        "clothes"
    ],
    "wof:name":"La Cicogna S.r.l",
    "wof:placetype":"venue"
},
  "geometry": {"coordinates":[11.622424,44.836948],"type":"Point"}
}