{
  "type": "Feature",
  "properties": {
    "addr:full":"893, Corso Europa 16148 Genova Genova Genova 16148",
    "addr:postcode":"16148;16148",
    "addr:street":"Corso Europa",
    "iso:country":"IT",
    "sg:address":"893, Corso Europa 16148 Genova",
    "sg:city":"Genova",
    "sg:classifiers":[
        {
            "category":"Professional",
            "subcategory":"Printing & Photocopies",
            "type":"Services"
        }
    ],
    "sg:phone":"+39 39010396373",
    "sg:postcode":"16148",
    "sg:province":"Genova",
    "wof:name":"Tormena Industrie Grafiche (s.r.l.)",
    "wof:placetype":"venue"
},
  "geometry": {"coordinates":[8.9164896011,44.4787330627],"type":"Point"}
}