{
  "type": "Feature",
  "properties": {
    "iso:country":"IT",
    "sg:address":"Strada Statale Brennero-negarine 37029 San Pietro In Cariano",
    "sg:city":"Negarine",
    "sg:classifiers":[
        {
            "category":"Manufacturing",
            "subcategory":"Paper Products",
            "type":"Manufacturing & Wholesale Goods"
        }
    ],
    "sg:phone":"+39 045 772 5460",
    "sg:postcode":"37029",
    "sg:province":"Verona",
    "sg:tags":[
        "cardboard"
    ],
    "wof:name":"Industria Cartotecnica Travagliati (s.p.a.)",
    "wof:placetype":"venue"
},
  "geometry": {"coordinates":[10.9917478561,45.4383659363],"type":"Point"}
}