{
  "type": "Feature",
  "properties": {
    "addr:full":"21047 Saronno Saronno Varese 21047",
    "addr:postcode":"21047;21047",
    "iso:country":"IT",
    "sg:address":"21047 Saronno",
    "sg:city":"Saronno",
    "sg:orig_category":"Macchine, Impianti Ed Attrezzature Industria Chimica",
    "sg:phone":"+39 02 9670 9337",
    "sg:postcode":"21047",
    "sg:province":"Varese",
    "wof:name":"Packaging & Design Srl",
    "wof:placetype":"venue"
},
  "geometry": {"coordinates":[9.033503,45.610226],"type":"Point"}
}