{
  "type": "Feature",
  "properties": {
    "iso:country":"IT",
    "sg:address":"30, Via Boccaserio 26861 Fombio",
    "sg:city":"Fombio",
    "sg:classifiers":[
        {
            "category":"Professional",
            "subcategory":"Engineering",
            "type":"Services"
        }
    ],
    "sg:phone":"+39 39037741551",
    "sg:postcode":"26861",
    "sg:province":"Lodi",
    "sg:tags":[
        "machine",
        "-",
        "mechanical"
    ],
    "wof:name":"Gansow Elektrobau Gmbh-succursale Per L'italia",
    "wof:placetype":"venue"
},
  "geometry": {"coordinates":[9.692995,45.145733],"type":"Point"}
}