{
  "type": "Feature",
  "properties": {
    "iso:country":"IT",
    "sg:address":"56025 Pontedera",
    "sg:city":"Pontedera",
    "sg:orig_category":"Cabine Per Verniciature Industriali",
    "sg:phone":"+39 0587 292803",
    "sg:postcode":"56025",
    "sg:province":"Pisa",
    "wof:name":"Tecnover Di Guidi Leandro",
    "wof:placetype":"venue"
},
  "geometry": {"coordinates":[10.643236,43.64679],"type":"Point"}
}