{
  "type": "Feature",
  "properties": {
    "iso:country":"IT",
    "sg:address":"20122 Milano",
    "sg:city":"Milano",
    "sg:orig_category":"Servizi Culturali E Per Lo Spettacolo. Arte Ed Artigianato Artistico. Servizi Al Turismo",
    "sg:phone":"+39 02 795626",
    "sg:postcode":"20122",
    "sg:province":"Milano",
    "wof:name":"Valeria Belvedere (s.r.l.)",
    "wof:placetype":"venue"
},
  "geometry": {"coordinates":[9.204754,45.469414],"type":"Point"}
}