{
  "type": "Feature",
  "properties": {
    "iso:country":"IT",
    "sg:address":"84013 Cava De'tirreni",
    "sg:orig_category":"Servizi E Lavori Industria Della Gomma",
    "sg:phone":"+39 089 344649",
    "sg:postcode":"84013",
    "sg:province":"Salerno",
    "wof:name":"I.go.mer. S.a.s. Di Apicella Amalia & C.",
    "wof:placetype":"venue"
},
  "geometry": {"coordinates":[14.693768,40.706985],"type":"Point"}
}