{
  "type": "Feature",
  "properties": {
    "addr:full":"28041 Arona Arona Novara 28041",
    "addr:postcode":"28041;28041",
    "iso:country":"IT",
    "sg:address":"28041 Arona",
    "sg:city":"Arona",
    "sg:orig_category":"Studi E Consulenze Legali E Notarili. Avvocati, Notai E Servizi Legali. Professionisti - Studi E Servizi Ed Associazioni Di Interesse Aziendale",
    "sg:phone":"+39 0322 242245",
    "sg:postcode":"28041",
    "sg:province":"Novara",
    "sg:website":"http://www.studioconforti.it",
    "wof:name":"Conforti Avvocato Cesare",
    "wof:placetype":"venue"
},
  "geometry": {"coordinates":[8.559519,45.758911],"type":"Point"}
}