{
  "type": "Feature",
  "properties": {
    "iso:country":"IT",
    "sg:address":"Via Atene 7 43010 Bianconese",
    "sg:city":"Bianconese",
    "sg:classifiers":[
        {
            "category":"Recreation",
            "subcategory":"Fishing",
            "type":"Entertainment"
        }
    ],
    "sg:phone":"+39 0521 618000",
    "sg:postcode":"43010",
    "sg:province":"Parma",
    "sg:tags":[
        "tackle"
    ],
    "sg:website":"www.trabucco.it",
    "wof:name":"Trabucco Fishing Diffusion Srl",
    "wof:placetype":"venue"
},
  "geometry": {"coordinates":[10.2381620407,44.8612632751],"type":"Point"}
}