{
  "type": "Feature",
  "properties": {
    "iso:country":"IT",
    "sg:address":"26010 Salvirola",
    "sg:city":"Salvirola",
    "sg:orig_category":"Servizi Per Aziende, Manifestazioni E Supporto Agli Scambi Commerciali",
    "sg:phone":"+39 0373 72529",
    "sg:postcode":"26010",
    "sg:province":"Cremona",
    "wof:name":"Gaetani Ludovico",
    "wof:placetype":"venue"
},
  "geometry": {"coordinates":[9.777005,45.356369],"type":"Point"}
}