{
  "type": "Feature",
  "properties": {
    "iso:country":"IT",
    "sg:address":"50143 Firenze",
    "sg:city":"Firenze",
    "sg:classifiers":[
        {
            "category":"Health Services",
            "subcategory":"Health Practitioner",
            "type":"Services"
        }
    ],
    "sg:phone":"+39 055 715414",
    "sg:postcode":"50143",
    "sg:province":"Firenze",
    "sg:tags":[
        "medici"
    ],
    "wof:name":"Sambalino Andrea",
    "wof:placetype":"venue"
},
  "geometry": {"coordinates":[11.1760320663,43.7705345154],"type":"Point"}
}