{
  "type": "Feature",
  "properties": {
    "iso:country":"IT",
    "sg:address":"1, Via Leonardo Da Vinci 30033 Noale",
    "sg:city":"Noale",
    "sg:classifiers":[
        {
            "category":"Farming",
            "subcategory":"Livestock Farm",
            "type":"Manufacturing & Wholesale Goods"
        }
    ],
    "sg:phone":"+39 041 589 2111",
    "sg:postcode":"30033",
    "sg:province":"Venezia",
    "sg:tags":[
        "agriculture"
    ],
    "wof:name":"Centro Distribuzione Merci S.r.l.",
    "wof:placetype":"venue"
},
  "geometry": {"coordinates":[12.07518,45.54409],"type":"Point"}
}