{
  "type": "Feature",
  "properties": {
    "iso:country":"IT",
    "sg:address":"37032 Monteforte D'alpone",
    "sg:orig_category":"Prodotti Di Base E Forniture Per Industria Alimentare E Bevande",
    "sg:phone":"+39 045 617 6133",
    "sg:postcode":"37032",
    "sg:province":"Verona",
    "wof:name":"Eco.ver Ecologia Veronese Srl",
    "wof:placetype":"venue"
},
  "geometry": {"coordinates":[11.2954282761,45.4568786621],"type":"Point"}
}