{
  "type": "Feature",
  "properties": {
    "addr:full":"35030 Sarmeola Sarmeola Padova 35030",
    "addr:postcode":"35030;35030",
    "iso:country":"IT",
    "sg:address":"35030 Sarmeola",
    "sg:city":"Sarmeola",
    "sg:orig_category":"Tempo Libero - Articoli E Forniture. Automobili E Mezzi Di Trasporto",
    "sg:phone":"+39 049 634746",
    "sg:postcode":"35030",
    "sg:province":"Padova",
    "wof:name":"Dmp Di Petranzan Paolo E Massimo (s.n.c.)",
    "wof:placetype":"venue"
},
  "geometry": {"coordinates":[11.827386,45.433865],"type":"Point"}
}