{
  "type": "Feature",
  "properties": {
    "addr:full":"22, Via Tezze 36060 Molvena Molvena Vicenza 36060",
    "addr:postcode":"36060;36060",
    "addr:street":"Via Tezze",
    "iso:country":"IT",
    "sg:address":"22, Via Tezze 36060 Molvena",
    "sg:city":"Molvena",
    "sg:classifiers":[
        {
            "category":"Home & Garden",
            "subcategory":"Home Furnishings",
            "type":"Retail Goods"
        }
    ],
    "sg:phone":"+39 0424 471119",
    "sg:postcode":"36060",
    "sg:province":"Vicenza",
    "sg:tags":[
        "household"
    ],
    "wof:name":"Tecno-line S.r.l.",
    "wof:placetype":"venue"
},
  "geometry": {"coordinates":[11.631131,45.726067],"type":"Point"}
}