{
  "type": "Feature",
  "properties": {
    "addr:full":"Piazza M. Maltoni 6; Pontassieve; 50065 Pontassieve Firenze 50065",
    "addr:housenumber":"6",
    "addr:postcode":"50065;50065",
    "addr:street":"Piazza M. Maltoni;Pontassieve",
    "iso:country":"IT",
    "sg:address":"Piazza M. Maltoni 6; Pontassieve; 50065",
    "sg:city":"Pontassieve",
    "sg:classifiers":[
        {
            "category":"Banks & Credit Unions",
            "subcategory":"Bank",
            "type":"Services"
        }
    ],
    "sg:phone":"+39 055 836 7351",
    "sg:postcode":"50065",
    "sg:province":"Firenze",
    "wof:name":"Credito Italiano Spa",
    "wof:placetype":"venue"
},
  "geometry": {"coordinates":[11.432266,43.772369],"type":"Point"}
}