{
  "type": "Feature",
  "properties": {
    "addr:full":"Via D'azeglio Massimo 2 40123 Bologna Bologna Bologna 40123",
    "addr:housenumber":"2",
    "addr:postcode":"40123;40123",
    "addr:street":"Via D'Azeglio Massimo",
    "iso:country":"IT",
    "sg:address":"Via D'azeglio Massimo 2 40123 Bologna",
    "sg:city":"Bologna",
    "sg:classifiers":[
        {
            "category":"Shopping",
            "subcategory":"Crafts & Fabrics",
            "type":"Retail Goods"
        }
    ],
    "sg:phone":"+39 051 231061",
    "sg:postcode":"40123",
    "sg:province":"Bologna",
    "sg:tags":[
        "clothing",
        "ladies'",
        "wear",
        "menswear",
        "boys'"
    ],
    "wof:name":"Manifatture All'orologio Sas",
    "wof:placetype":"venue"
},
  "geometry": {"coordinates":[11.3464813232,44.4942207336],"type":"Point"}
}