{
  "type": "Feature",
  "properties": {
    "iso:country":"IT",
    "sg:address":"40/a, Via Sesia 20089 Rozzano",
    "sg:city":"Rozzano",
    "sg:classifiers":[
        {
            "category":"Bars & Pubs",
            "subcategory":"Nightclub",
            "type":"Food & Drink"
        }
    ],
    "sg:phone":"+39 39028255385",
    "sg:postcode":"20089",
    "sg:province":"Milano",
    "sg:tags":[
        "cake",
        "bread"
    ],
    "wof:name":"Panificio Francese Srl",
    "wof:placetype":"venue"
},
  "geometry": {"coordinates":[9.165067,45.396832],"type":"Point"}
}