{
  "type": "Feature",
  "properties": {
    "addr:full":"Viale Rovereto 47 - 49; Riva Del Garda; 38066 Riva del Garda Trento 38066",
    "addr:housenumber":"47 49",
    "addr:postcode":"38066;38066",
    "addr:street":"Viale Rovereto",
    "iso:country":"IT",
    "sg:address":"Viale Rovereto 47 - 49; Riva Del Garda; 38066",
    "sg:city":"Riva del Garda",
    "sg:classifiers":[
        {
            "category":"Travel",
            "subcategory":"Travel Agent",
            "type":"Entertainment"
        }
    ],
    "sg:phone":"+39 390 464 5888",
    "sg:postcode":"38066",
    "sg:province":"Trento",
    "sg:website":"ilgtravel.com",
    "wof:name":"Italian Leisure Group",
    "wof:placetype":"venue"
},
  "geometry": {"coordinates":[10.854005,45.882206],"type":"Point"}
}