{
  "type": "Feature",
  "properties": {
    "iso:country":"IT",
    "sg:address":"89/a, Via Di Pietra 00186 Roma",
    "sg:city":"Roma",
    "sg:classifiers":[
        {
            "category":"Travel",
            "subcategory":"Travel Agent",
            "type":"Entertainment"
        }
    ],
    "sg:phone":"+39 39066749701",
    "sg:postcode":"00186",
    "sg:province":"Roma",
    "sg:tags":[
        "business"
    ],
    "wof:name":"Albergo Cesari Snc Di Anna Palumbo E Figlie",
    "wof:placetype":"venue"
},
  "geometry": {"coordinates":[12.466496,41.869095],"type":"Point"}
}