{
  "type": "Feature",
  "properties": {
    "addr:full":"91, Via Boncore 63014 Montegranaro Montegranaro Ascoli Piceno 63014",
    "addr:postcode":"63014;63014",
    "addr:street":"Via Boncore",
    "iso:country":"IT",
    "sg:address":"91, Via Boncore 63014 Montegranaro",
    "sg:city":"Montegranaro",
    "sg:classifiers":[
        {
            "category":"Personal",
            "subcategory":"Shoe Repair & Shine",
            "type":"Services"
        }
    ],
    "sg:phone":"+39 39073488443",
    "sg:postcode":"63014",
    "sg:province":"Ascoli Piceno",
    "sg:tags":[
        "leather"
    ],
    "wof:name":"Calzaturificio C.a.m.g. Di Salvatelli A. & M.p. (s.n.c.)",
    "wof:placetype":"venue"
},
  "geometry": {"coordinates":[13.62781,43.223068],"type":"Point"}
}