{
  "type": "Feature",
  "properties": {
    "addr:full":"97019 Vittoria Vittoria Ragusa 97019",
    "addr:postcode":"97019;97019",
    "iso:country":"IT",
    "sg:address":"97019 Vittoria",
    "sg:city":"Vittoria",
    "sg:orig_category":"Agricoltura, Orticoltura E Floricoltura. Articoli Da Regalo",
    "sg:phone":"+39 0932 869447",
    "sg:postcode":"97019",
    "sg:province":"Ragusa",
    "wof:name":"Giombarresi Rosario",
    "wof:placetype":"venue"
},
  "geometry": {"coordinates":[14.536253,36.950069],"type":"Point"}
}