{
  "type": "Feature",
  "properties": {
    "iso:country":"IT",
    "sg:address":"86039 Termoli",
    "sg:city":"Termoli",
    "sg:orig_category":"Petroli, Gas E Combustibili",
    "sg:phone":"+39 0875 752025",
    "sg:postcode":"86039",
    "sg:province":"Campobasso",
    "wof:name":"Di Properzio Commerciale (s.r.l.)",
    "wof:placetype":"venue"
},
  "geometry": {"coordinates":[14.997303009,41.9625778198],"type":"Point"}
}