{
  "type": "Feature",
  "properties": {
    "iso:country":"IT",
    "sg:address":"2, Via Piavesella 31040 Trevignano",
    "sg:city":"Trevignano",
    "sg:classifiers":[
        {
            "category":"Personal",
            "subcategory":"Shoe Repair & Shine",
            "type":"Services"
        }
    ],
    "sg:phone":"+39 0423 670468",
    "sg:postcode":"31040",
    "sg:province":"Treviso",
    "sg:tags":[
        "leather"
    ],
    "wof:name":"Calzaturificio Vendramini (s.r.l.)",
    "wof:placetype":"venue"
},
  "geometry": {"coordinates":[12.122828,45.738689],"type":"Point"}
}