{
  "type": "Feature",
  "properties": {
    "iso:country":"IT",
    "sg:address":"37060 Lugagnano",
    "sg:city":"Lugagnano",
    "sg:orig_category":"Macchine, Impianti Ed Attrezzature Per Abbigliamento E Pelletterie. Macchine E Impianti Per Attivita' Commerciali Ed Artigianali",
    "sg:phone":"+39 045 868 0014",
    "sg:postcode":"37060",
    "sg:province":"Verona",
    "wof:name":"F.i.b.i.r. Di Cerato Riccardo",
    "wof:placetype":"venue"
},
  "geometry": {"coordinates":[10.881265,45.429684],"type":"Point"}
}