{
  "type": "Feature",
  "properties": {
    "addr:full":"10154 Torino Torino Torino 10154",
    "addr:postcode":"10154;10154",
    "iso:country":"IT",
    "sg:address":"10154 Torino",
    "sg:city":"Torino",
    "sg:orig_category":"Servizi E Lavori Per Edilizia E Lavori Pubblici. Consulenze Tecniche, Amministrative E Perizie",
    "sg:phone":"+39 011 242 1925",
    "sg:postcode":"10154",
    "sg:province":"Torino",
    "sg:website":"http://www.rimaprogetti.com",
    "wof:name":"Rima Progetti Srl",
    "wof:placetype":"venue"
},
  "geometry": {"coordinates":[7.708713,45.099701],"type":"Point"}
}