{
  "type": "Feature",
  "properties": {
    "iso:country":"IT",
    "sg:address":"82030 San Salvatore Telesino",
    "sg:city":"San Salvatore Telesino",
    "sg:orig_category":"Distributors: Automatici - Commercio E Gestione",
    "sg:phone":"+39 0824 948533",
    "sg:postcode":"82030",
    "sg:province":"Benevento",
    "wof:name":"Pacelli Trade Sas",
    "wof:placetype":"venue"
},
  "geometry": {"coordinates":[14.497476,41.234959],"type":"Point"}
}