{
  "type": "Feature",
  "properties": {
    "addr:full":"20068 Peschiera Borromeo Peschiera Borromeo Milano 20068",
    "addr:postcode":"20068;20068",
    "iso:country":"IT",
    "sg:address":"20068 Peschiera Borromeo",
    "sg:city":"Peschiera Borromeo",
    "sg:orig_category":"Macchine, Impianti Ed Attrezzature Industria Chimica. Prodotti Vari In Metallo. Articoli Per Imballaggio E Confezionamento",
    "sg:phone":"+39 02 5530 3141",
    "sg:postcode":"20068",
    "sg:province":"Milano",
    "wof:name":"Industrial Trading Spa",
    "wof:placetype":"venue"
},
  "geometry": {"coordinates":[9.289042,45.436001],"type":"Point"}
}