{
  "type": "Feature",
  "properties": {
    "iso:country":"IT",
    "sg:address":"96019 Rosolini",
    "sg:city":"Rosolini",
    "sg:orig_category":"Tempo Libero - Articoli E Forniture. Shopping. Regalistica Aziendale",
    "sg:phone":"+39 0931 856709",
    "sg:postcode":"96019",
    "sg:province":"Siracusa",
    "wof:name":"A. & A. Di Alecci M. E N. Snc",
    "wof:placetype":"venue"
},
  "geometry": {"coordinates":[15.117139,37.098988],"type":"Point"}
}