{
  "type": "Feature",
  "properties": {
    "addr:full":"23851 Galbiate Galbiate Lecco 23851",
    "addr:postcode":"23851;23851",
    "iso:country":"IT",
    "sg:address":"23851 Galbiate",
    "sg:city":"Galbiate",
    "sg:orig_category":"Manufacturers: Prefabbricati",
    "sg:phone":"+39 0341 541375",
    "sg:postcode":"23851",
    "sg:province":"Lecco",
    "wof:name":"Riva Renato",
    "wof:placetype":"venue"
},
  "geometry": {"coordinates":[9.375982,45.819313],"type":"Point"}
}