{
  "type": "Feature",
  "properties": {
    "iso:country":"IT",
    "sg:address":"80050 Santa Maria La Carita'",
    "sg:orig_category":"Abbigliamento Bambini E Ragazzi",
    "sg:phone":"+39 081 871 3599",
    "sg:postcode":"80050",
    "sg:province":"Napoli",
    "wof:name":"Piccolo Lord Di Rosalia Vicedomini",
    "wof:placetype":"venue"
},
  "geometry": {"coordinates":[14.507316,40.709648],"type":"Point"}
}