{
  "type": "Feature",
  "properties": {
    "addr:full":"11020 Champdepraz Champdepraz Aosta 11020",
    "addr:housenumber":"11020",
    "addr:postcode":"11020",
    "addr:street":"Champdepraz Champdepraz Aosta",
    "iso:country":"IT",
    "sg:address":"11020 Champdepraz",
    "sg:city":"Champdepraz",
    "sg:orig_category":"Macchine E Forniture Per Arredamento E Industria Del Legno",
    "sg:phone":"+39 0125 960623",
    "sg:postcode":"11020",
    "sg:province":"Aosta",
    "wof:name":"Mdm Srl",
    "wof:placetype":"venue"
},
  "geometry": {"coordinates":[7.670698,45.685234],"type":"Point"}
}