{
  "type": "Feature",
  "properties": {
    "iso:country":"IT",
    "sg:address":"70027 Palo Del Colle",
    "sg:city":"Palo del Colle",
    "sg:orig_category":"Agricoltura - Attrezzi, Prodotti E Forniture",
    "sg:phone":"+39 080 626091",
    "sg:postcode":"70027",
    "sg:province":"Bari",
    "wof:name":"M. & O. Di Liantonio Francesco",
    "wof:placetype":"venue"
},
  "geometry": {"coordinates":[16.699879,41.05994],"type":"Point"}
}