{
  "type": "Feature",
  "properties": {
    "iso:country":"IT",
    "sg:address":"Via Vincenzo Monti 3 20030 Senago",
    "sg:city":"Senago",
    "sg:classifiers":[
        {
            "category":"Structure",
            "subcategory":"Building",
            "type":"Public Place"
        }
    ],
    "sg:phone":"+39 02 998 9701",
    "sg:postcode":"20030",
    "sg:province":"Milano",
    "sg:tags":[
        "canopy"
    ],
    "sg:website":"www.plastecomilano.com",
    "wof:name":"Plasteco Milano Sas",
    "wof:placetype":"venue"
},
  "geometry": {"coordinates":[9.120188,45.572964],"type":"Point"}
}