{
  "type": "Feature",
  "properties": {
    "iso:country":"IT",
    "sg:address":"Via Iv Novembre 48 25068 Sarezzo",
    "sg:city":"Sarezzo",
    "sg:classifiers":[
        {
            "category":"Bars & Pubs",
            "subcategory":"Gay Bar",
            "type":"Food & Drink"
        }
    ],
    "sg:phone":"+39 030 890 0565",
    "sg:postcode":"25068",
    "sg:province":"Brescia",
    "sg:tags":[
        "tub",
        "accessory",
        "bath"
    ],
    "sg:website":"www.allpe.it",
    "wof:name":"All.pe Srl",
    "wof:placetype":"venue"
},
  "geometry": {"coordinates":[10.222958,45.539829],"type":"Point"}
}