{
  "type": "Feature",
  "properties": {
    "addr:full":"86, Corso Messina 95014 Giarre Giarre Catania 95014",
    "addr:postcode":"95014;95014",
    "addr:street":"Corso Messina",
    "iso:country":"IT",
    "sg:address":"86, Corso Messina 95014 Giarre",
    "sg:city":"Giarre",
    "sg:classifiers":[
        {
            "category":"Farming",
            "subcategory":"Livestock Farm",
            "type":"Manufacturing & Wholesale Goods"
        }
    ],
    "sg:phone":"+39 39095932263",
    "sg:postcode":"95014",
    "sg:province":"Catania",
    "sg:tags":[
        "agriculture"
    ],
    "wof:name":"Indelicato Fratelli (s.r.l.)",
    "wof:placetype":"venue"
},
  "geometry": {"coordinates":[15.292408,37.858902],"type":"Point"}
}