{
  "type": "Feature",
  "properties": {
    "addr:full":"20035 Lissone Lissone Milano 20035",
    "addr:postcode":"20035;20035",
    "iso:country":"IT",
    "sg:address":"20035 Lissone",
    "sg:city":"Lissone",
    "sg:orig_category":"Prodotti E Manufatti In Materie Plastiche",
    "sg:phone":"+39 039 484605",
    "sg:postcode":"20035",
    "sg:province":"Milano",
    "wof:name":"Lagi Di Laterza Giuseppe",
    "wof:placetype":"venue"
},
  "geometry": {"coordinates":[9.1885280609,45.4609527588],"type":"Point"}
}