{
  "type": "Feature",
  "properties": {
    "iso:country":"IT",
    "sg:address":"28868 Trasquera",
    "sg:city":"Trasquera",
    "sg:orig_category":"Forniture Per Edilizia E Lavori Pubblici",
    "sg:phone":"+39 0324 79104",
    "sg:postcode":"28868",
    "sg:province":"Verbano-Cusio-Ossola",
    "wof:name":"Iselle Graniti Snc",
    "wof:placetype":"venue"
},
  "geometry": {"coordinates":[8.1815958023,46.2019577026],"type":"Point"}
}