{
  "type": "Feature",
  "properties": {
    "iso:country":"IT",
    "sg:address":"21040 Caronno Varesino",
    "sg:city":"Caronno Varesino",
    "sg:orig_category":"Lavorazioni Metalli, Stampaggio E Saldatura",
    "sg:phone":"+39 0331 980000",
    "sg:postcode":"21040",
    "sg:province":"Varese",
    "wof:name":"Officina Meccanica Cavallaro Di Cavallaro M. & C. Snc",
    "wof:placetype":"venue"
},
  "geometry": {"coordinates":[8.832815,45.736721],"type":"Point"}
}