{
  "type": "Feature",
  "properties": {
    "iso:country":"IT",
    "sg:address":"20141 Milano",
    "sg:city":"Milano",
    "sg:orig_category":"Registrazione Sonora - Sale Prova",
    "sg:phone":"+39 02 5523 0906",
    "sg:postcode":"20141",
    "sg:province":"Milano",
    "sg:website":"http://www.noisefactory.it",
    "wof:name":"Noise Factory Srl",
    "wof:placetype":"venue"
},
  "geometry": {"coordinates":[9.198511,45.440662],"type":"Point"}
}