{
  "type": "Feature",
  "properties": {
    "addr:full":"81030 Parete Parete Caserta 81030",
    "addr:postcode":"81030;81030",
    "iso:country":"IT",
    "sg:address":"81030 Parete",
    "sg:city":"Parete",
    "sg:orig_category":"Elettronica Professionale E Di Consumo. Tempo Libero - Articoli E Forniture",
    "sg:phone":"+39 335 813 945",
    "sg:postcode":"81030",
    "sg:province":"Caserta",
    "sg:website":"http://virtualand-italia.com",
    "wof:name":"Virtualand Di Di Dona Nicola",
    "wof:placetype":"venue"
},
  "geometry": {"coordinates":[14.1607255936,40.957698822],"type":"Point"}
}