{
  "type": "Feature",
  "properties": {
    "iso:country":"IT",
    "sg:address":"00198 Roma",
    "sg:city":"Roma",
    "sg:orig_category":"Elettrodomestici - Riparazione E Vendita Al Dettaglio Di Accessori",
    "sg:phone":"+39 06 854 0921",
    "sg:postcode":"00198",
    "sg:province":"Roma",
    "sg:website":"http://www.greenpower.it",
    "wof:name":"Green Power Srl",
    "wof:placetype":"venue"
},
  "geometry": {"coordinates":[12.505295,41.918606],"type":"Point"}
}