{
  "type": "Feature",
  "properties": {
    "addr:full":"Via Marcello 24 35011 Campodarsego Campodarsego Padova 35011",
    "addr:housenumber":"24",
    "addr:postcode":"35011;35011",
    "addr:street":"Via Marcello",
    "iso:country":"IT",
    "sg:address":"Via Marcello 24 35011 Campodarsego",
    "sg:city":"Campodarsego",
    "sg:classifiers":[
        {
            "category":"Home & Garden",
            "subcategory":"Building Materials",
            "type":"Retail Goods"
        }
    ],
    "sg:phone":"+39 049 920 0757",
    "sg:postcode":"35011",
    "sg:province":"Padova",
    "sg:tags":[
        "central",
        "heating",
        "boiler"
    ],
    "sg:website":"www.banoeco.com",
    "wof:name":"Bano Srl",
    "wof:placetype":"venue"
},
  "geometry": {"coordinates":[11.901219,45.497921],"type":"Point"}
}