{
  "type": "Feature",
  "properties": {
    "iso:country":"IT",
    "sg:address":"Via Del Progresso 30 23037 Tirano",
    "sg:city":"Tirano",
    "sg:classifiers":[
        {
            "category":"Home & Garden",
            "subcategory":"Hardware",
            "type":"Retail Goods"
        }
    ],
    "sg:phone":"+39 0342 704422",
    "sg:postcode":"23037",
    "sg:province":"Sondrio",
    "sg:tags":[
        "small",
        "ironware",
        "item"
    ],
    "wof:name":"Mec.tir. Snc Di Bellesini Guido & C.",
    "wof:placetype":"venue"
},
  "geometry": {"coordinates":[10.154426,46.208912],"type":"Point"}
}