{
  "type": "Feature",
  "properties": {
    "iso:country":"IT",
    "sg:address":"Piazza Francesco Rossi 5; Arsiero; 36011",
    "sg:city":"Arsiero",
    "sg:classifiers":[
        {
            "category":"Banks & Credit Unions",
            "subcategory":"Bank",
            "type":"Services"
        }
    ],
    "sg:phone":"+39 0445 740331",
    "sg:postcode":"36011",
    "sg:province":"Vicenza",
    "wof:name":"Banco Ambrosiano Veneto Spa",
    "wof:placetype":"venue"
},
  "geometry": {"coordinates":[11.349915,45.803257],"type":"Point"}
}