{
  "type": "Feature",
  "properties": {
    "addr:full":"35010 Vigonza Vigonza Padova 35010",
    "addr:postcode":"35010;35010",
    "iso:country":"IT",
    "sg:address":"35010 Vigonza",
    "sg:city":"Vigonza",
    "sg:orig_category":"Alluminio E Leghe",
    "sg:phone":"+39 049 980 1355",
    "sg:postcode":"35010",
    "sg:province":"Padova",
    "sg:website":"http://www.finalspa.it",
    "wof:name":"Fin.al. Spa",
    "wof:placetype":"venue"
},
  "geometry": {"coordinates":[11.987481,45.418667],"type":"Point"}
}