{
  "type": "Feature",
  "properties": {
    "iso:country":"IT",
    "sg:address":"20017 Rho",
    "sg:city":"Rho",
    "sg:orig_category":"Calzature, Pelletterie E Pelli. Servizi E Lavori Per Abbigliamento E Pelletterie",
    "sg:phone":"+39 02 9350 4344",
    "sg:postcode":"20017",
    "sg:province":"Milano",
    "wof:name":"Minit Italia S.p.a.",
    "wof:placetype":"venue"
},
  "geometry": {"coordinates":[9.140545,45.517998],"type":"Point"}
}