{
  "type": "Feature",
  "properties": {
    "iso:country":"IT",
    "sg:address":"Via Matteotti 160 25014 Castenedolo",
    "sg:city":"Castenedolo",
    "sg:classifiers":[
        {
            "category":"Real Estate",
            "subcategory":"Real Estate Agent",
            "type":"Services"
        }
    ],
    "sg:phone":"+39 030 213555",
    "sg:postcode":"25014",
    "sg:province":"Brescia",
    "sg:tags":[
        "lacquer"
    ],
    "sg:website":"www.franchi-kim.it",
    "wof:name":"Franchi & Kim Industrie Vernici S.p.a",
    "wof:placetype":"venue"
},
  "geometry": {"coordinates":[10.304938,45.466812],"type":"Point"}
}