{
  "type": "Feature",
  "properties": {
    "addr:full":"10042 Nichelino Nichelino Torino 10042",
    "addr:postcode":"10042;10042",
    "iso:country":"IT",
    "sg:address":"10042 Nichelino",
    "sg:city":"Nichelino",
    "sg:orig_category":"Automazione E Macchine Per Ufficio",
    "sg:phone":"+39 011 628 1260",
    "sg:postcode":"10042",
    "sg:province":"Torino",
    "wof:name":"L.b.l. (s.r.l.)",
    "wof:placetype":"venue"
},
  "geometry": {"coordinates":[7.64045,44.975597],"type":"Point"}
}