{
  "type": "Feature",
  "properties": {
    "iso:country":"IT",
    "sg:address":"Via Aeroporto 37066 Sommacampagna",
    "sg:city":"Sommacampagna",
    "sg:classifiers":[
        {
            "category":"Airport",
            "subcategory":"General Aviation",
            "type":"Transportation"
        }
    ],
    "sg:phone":"+39 045 861 9056",
    "sg:postcode":"37066",
    "sg:province":"Verona",
    "sg:tags":[
        "transport",
        "air"
    ],
    "wof:name":"Direzione Circoscrizione Aeroportuale Verona",
    "wof:placetype":"venue"
},
  "geometry": {"coordinates":[10.909619,45.405739],"type":"Point"}
}