{
  "type": "Feature",
  "properties": {
    "addr:full":"98, Alzaia Naviglio Grande 20144 Milano Milano Milano 20144",
    "addr:housenumber":"98",
    "addr:postcode":"20144;20144",
    "addr:street":"Alzaia Naviglio Grande",
    "iso:country":"IT",
    "sg:address":"98, Alzaia Naviglio Grande 20144 Milano",
    "sg:city":"Milano",
    "sg:classifiers":[
        {
            "category":"Manufacturing",
            "subcategory":"Paper Products",
            "type":"Manufacturing & Wholesale Goods"
        }
    ],
    "sg:phone":"+39 02 8940 1071",
    "sg:postcode":"20144",
    "sg:province":"Milano",
    "sg:tags":[
        "cardboard"
    ],
    "wof:name":"Nuova S. Marco (s.r.l.)",
    "wof:placetype":"venue"
},
  "geometry": {"coordinates":[9.1618890762,45.4494285583],"type":"Point"}
}