{
  "type": "Feature",
  "properties": {
    "addr:full":"06059 Todi Pantalla Perugia 06059",
    "addr:postcode":"06059;06059",
    "iso:country":"IT",
    "sg:address":"06059 Todi",
    "sg:city":"Pantalla",
    "sg:orig_category":"Forniture Per Agricoltura E Zootecnia",
    "sg:phone":"+39 075 89571",
    "sg:postcode":"06059",
    "sg:province":"Perugia",
    "wof:name":"3a Parco Tecnologico Agroalimentare Dell'umbria",
    "wof:placetype":"venue"
},
  "geometry": {"coordinates":[12.4003143311,42.8742408752],"type":"Point"}
}