{
  "type": "Feature",
  "properties": {
    "addr:full":"46100 Mantova Mantova Mantova 46100",
    "addr:postcode":"46100;46100",
    "iso:country":"IT",
    "sg:address":"46100 Mantova",
    "sg:city":"Mantova",
    "sg:orig_category":"Agenti Di Cambio E Societa' Di Intermediazione Mobiliare",
    "sg:phone":"+39 0376 325277",
    "sg:postcode":"46100",
    "sg:province":"Mantova",
    "wof:name":"Immobiliare Accademia Di Morbin Walter",
    "wof:placetype":"venue"
},
  "geometry": {"coordinates":[10.7962,45.159161],"type":"Point"}
}