{
  "type": "Feature",
  "properties": {
    "iso:country":"IT",
    "sg:address":"12023 Caraglio",
    "sg:city":"Caraglio",
    "sg:orig_category":"Restauratori D'arte",
    "sg:phone":"+39 0171 610237",
    "sg:postcode":"12023",
    "sg:province":"Cuneo",
    "wof:name":"Vetrina Del Tempo Piccola Soc.coop.r.l.",
    "wof:placetype":"venue"
},
  "geometry": {"coordinates":[7.448953,44.429684],"type":"Point"}
}