{
  "type": "Feature",
  "properties": {
    "addr:full":"50013 San Donnino San Donnino Firenze 50013",
    "addr:postcode":"50013;50013",
    "addr:street":"Donnino",
    "iso:country":"IT",
    "sg:address":"50013 San Donnino",
    "sg:city":"San Donnino",
    "sg:orig_category":"Accessori Dei Mezzi Di Trasporto. Riparazione Dei Mezzi Di Trasporto",
    "sg:phone":"+39 055 899 9359",
    "sg:postcode":"50013",
    "sg:province":"Firenze",
    "wof:name":"Hot Spot",
    "wof:placetype":"venue"
},
  "geometry": {"coordinates":[11.138552,43.792534],"type":"Point"}
}