{
  "type": "Feature",
  "properties": {
    "iso:country":"IT",
    "sg:address":"43/45, Via Artigianato 20083 Gaggiano",
    "sg:city":"Gaggiano",
    "sg:classifiers":[
        {
            "category":"Sports & Exercise",
            "subcategory":"Playing Field",
            "type":"Entertainment"
        }
    ],
    "sg:phone":"+39 39029085702",
    "sg:postcode":"20083",
    "sg:province":"Milano",
    "sg:tags":[
        "game"
    ],
    "wof:name":"Aristel Snc Di Basaldella Luca E Ricotti Piercarlo",
    "wof:placetype":"venue"
},
  "geometry": {"coordinates":[9.090038,45.413029],"type":"Point"}
}