{
  "type": "Feature",
  "properties": {
    "addr:full":"10093 Collegno Collegno Torino 10093",
    "addr:postcode":"10093;10093",
    "iso:country":"IT",
    "sg:address":"10093 Collegno",
    "sg:city":"Collegno",
    "sg:orig_category":"Salotti, Poltrone, Sedie E Tavoli",
    "sg:phone":"+39 011 403 0385",
    "sg:postcode":"10093",
    "sg:province":"Torino",
    "sg:website":"http://www.rostagnosalotti.it",
    "wof:name":"Rostagno Srl",
    "wof:placetype":"venue"
},
  "geometry": {"coordinates":[7.5895,45.073551],"type":"Point"}
}