{
  "type": "Feature",
  "properties": {
    "iso:country":"IT",
    "sg:address":"20144 Milano",
    "sg:city":"Milano",
    "sg:orig_category":"Forniture Per Abbigliamento E Pelletterie",
    "sg:phone":"+39 02 467571",
    "sg:postcode":"20144",
    "sg:province":"Milano",
    "sg:website":"http://www.groz-beckert.com",
    "wof:name":"Groz-beckert Italia Srl",
    "wof:placetype":"venue"
},
  "geometry": {"coordinates":[9.160577774,45.4588890076],"type":"Point"}
}