{
  "type": "Feature",
  "properties": {
    "iso:country":"IT",
    "sg:address":"46100 Mantova",
    "sg:city":"Mantova",
    "sg:orig_category":"Medicali Articoli - Commercio",
    "sg:phone":"+39 0376 321478",
    "sg:postcode":"46100",
    "sg:province":"Mantova",
    "wof:name":"Ortopedia Rosa Sas Di Rosa Walter & C.",
    "wof:placetype":"venue"
},
  "geometry": {"coordinates":[10.789355,45.16383],"type":"Point"}
}