{
  "type": "Feature",
  "properties": {
    "addr:full":"5, Via Josip Ressel 34018 San Dorligo Della Valle San Dorligo della Valle Trieste 34018",
    "addr:postcode":"34018;dorligo della valle san;34018",
    "addr:street":"Via Josip Ressel",
    "iso:country":"IT",
    "sg:address":"5, Via Josip Ressel 34018 San Dorligo Della Valle",
    "sg:city":"San Dorligo della Valle",
    "sg:classifiers":[
        {
            "category":"Professional",
            "subcategory":"Printing & Photocopies",
            "type":"Services"
        }
    ],
    "sg:phone":"+39 040 388 0111",
    "sg:postcode":"34018",
    "sg:province":"Trieste",
    "wof:name":"Editoriale Lloyd S.r.l.",
    "wof:placetype":"venue"
},
  "geometry": {"coordinates":[13.7784070969,45.653629303],"type":"Point"}
}