{
  "type": "Feature",
  "properties": {
    "iso:country":"IT",
    "sg:address":"15, Via Pola 20124 Milano",
    "sg:city":"Milano",
    "sg:classifiers":[
        {
            "category":"Manufacturing",
            "subcategory":"Printing",
            "type":"Manufacturing & Wholesale Goods"
        }
    ],
    "sg:phone":"+39 39026937951",
    "sg:postcode":"20124",
    "sg:province":"Milano",
    "sg:tags":[
        "publishing"
    ],
    "wof:name":"Eris Program S.r.l.",
    "wof:placetype":"venue"
},
  "geometry": {"coordinates":[9.1934347153,45.4889297485],"type":"Point"}
}