{
  "type": "Feature",
  "properties": {
    "addr:full":"96010 Priolo Gargallo Priolo Gargallo Siracusa 96010",
    "addr:postcode":"96010;96010",
    "iso:country":"IT",
    "sg:address":"96010 Priolo Gargallo",
    "sg:city":"Priolo Gargallo",
    "sg:orig_category":"Metalli E Leghe",
    "sg:phone":"+39 0931 761230",
    "sg:postcode":"96010",
    "sg:province":"Siracusa",
    "wof:name":"I.t.s. (s.r.l.)",
    "wof:placetype":"venue"
},
  "geometry": {"coordinates":[15.1881370544,37.1566619873],"type":"Point"}
}