{
  "type": "Feature",
  "properties": {
    "iso:country":"IT",
    "sg:address":"20040 Cambiago",
    "sg:city":"Cambiago",
    "sg:orig_category":"Climatizzazione E Condizionamento, Apparecchiature E Servizi",
    "sg:postcode":"20040",
    "sg:province":"Milano",
    "wof:name":"Cbi Clima (s.p.a.)",
    "wof:placetype":"venue"
},
  "geometry": {"coordinates":[9.42133,45.571743],"type":"Point"}
}