{
  "type": "Feature",
  "properties": {
    "addr:full":"98, V. Occhiobello 45024 Fiesso Umbertiano Fiesso Umbertiano Rovigo 45024",
    "addr:housenumber":"98",
    "addr:postcode":"45024;45024",
    "addr:street":"V. Occhiobello;Umbertiano Rovigo",
    "iso:country":"IT",
    "sg:address":"98, V. Occhiobello 45024 Fiesso Umbertiano",
    "sg:city":"Fiesso Umbertiano",
    "sg:classifiers":[
        {
            "category":"Manufacturing",
            "subcategory":"Rubber & Plastics",
            "type":"Manufacturing & Wholesale Goods"
        }
    ],
    "sg:phone":"+39 0425 745511",
    "sg:postcode":"45024",
    "sg:province":"Rovigo",
    "sg:website":"http://www.lareter.it:ws_end: :mark:ws:http://www.paginegialle.it/lareter",
    "wof:name":"Lareter Spa",
    "wof:placetype":"venue"
},
  "geometry": {"coordinates":[11.6049022675,44.9598731995],"type":"Point"}
}