{
  "type": "Feature",
  "properties": {
    "addr:full":"10, Via Palvotrisia 19030 Castelnuovo Magra La Spezia 19030",
    "addr:postcode":"19030;19030",
    "addr:street":"Via Palvotrisia",
    "iso:country":"IT",
    "sg:address":"10, Via Palvotrisia 19030 Castelnuovo Magra",
    "sg:classifiers":[
        {
            "category":"Professional",
            "subcategory":"Engineering",
            "type":"Services"
        }
    ],
    "sg:phone":"+39 0187 675672",
    "sg:postcode":"19030",
    "sg:province":"La Spezia",
    "sg:tags":[
        "machine",
        "-",
        "mechanical"
    ],
    "wof:name":"Mattioni Spa",
    "wof:placetype":"venue"
},
  "geometry": {"coordinates":[9.829219,44.106735],"type":"Point"}
}