{
  "type": "Feature",
  "properties": {
    "addr:full":"20038 Seregno Seregno Milano 20038",
    "addr:postcode":"20038;20038",
    "iso:country":"IT",
    "sg:address":"20038 Seregno",
    "sg:city":"Seregno",
    "sg:classifiers":[
        {
            "category":"Health Services",
            "subcategory":"Health Practitioner",
            "type":"Services"
        }
    ],
    "sg:phone":"+39 036 223 0142",
    "sg:postcode":"20038",
    "sg:province":"Milano",
    "sg:tags":[
        "medici"
    ],
    "wof:name":"Villa Anna Maria",
    "wof:placetype":"venue"
},
  "geometry": {"coordinates":[9.2014369965,45.6485748291],"type":"Point"}
}