{
  "type": "Feature",
  "properties": {
    "iso:country":"IT",
    "sg:address":"37049 Villa Bartolomea",
    "sg:city":"Villa Bartolomea",
    "sg:orig_category":"Trattamenti Termici E Superficiali Metalli, Galvanotecnica",
    "sg:phone":"+39 0442 659110",
    "sg:postcode":"37049",
    "sg:province":"Verona",
    "wof:name":"Novaplast Srl",
    "wof:placetype":"venue"
},
  "geometry": {"coordinates":[11.357357,45.15086],"type":"Point"}
}