{
  "type": "Feature",
  "properties": {
    "addr:full":"41012 Carpi Carpi Modena 41012",
    "addr:postcode":"41012;41012",
    "iso:country":"IT",
    "sg:address":"41012 Carpi",
    "sg:city":"Carpi",
    "sg:orig_category":"Tessuti E Stoffe",
    "sg:phone":"+39 059 688353",
    "sg:postcode":"41012",
    "sg:province":"Modena",
    "wof:name":"Fulchini Carmelinda",
    "wof:placetype":"venue"
},
  "geometry": {"coordinates":[10.859957,44.789127],"type":"Point"}
}