{
  "type": "Feature",
  "properties": {
    "iso:country":"IT",
    "sg:address":"20138 Milano",
    "sg:city":"Milano",
    "sg:orig_category":"Macchine, Impianti E Forniture Per Industria Grafica, Cartaria E Cartotecnica. Automazione E Macchine Per Ufficio",
    "sg:phone":"+39 02 509 9491",
    "sg:postcode":"20138",
    "sg:province":"Milano",
    "wof:name":"Panasonic S.e.i. Spa",
    "wof:placetype":"venue"
},
  "geometry": {"coordinates":[9.25525,45.453308],"type":"Point"}
}