{
  "type": "Feature",
  "properties": {
    "iso:country":"IT",
    "sg:address":"29, Via Settala Lodovico 20124 Milano",
    "sg:city":"Milano",
    "sg:classifiers":[
        {
            "category":"Professional",
            "subcategory":"Business Services",
            "type":"Services"
        }
    ],
    "sg:phone":"+39 02 2940 4088",
    "sg:postcode":"20124",
    "sg:province":"Milano",
    "sg:tags":[
        "advice"
    ],
    "wof:name":"Teleproject Sistemi (s.r.l.)",
    "wof:placetype":"venue"
},
  "geometry": {"coordinates":[9.20603,45.48045],"type":"Point"}
}