{
  "type": "Feature",
  "properties": {
    "iso:country":"IT",
    "sg:address":"80017 Melito Di Napoli",
    "sg:city":"Melito di Napoli",
    "sg:orig_category":"Antifurto",
    "sg:phone":"+39 081 711 3792",
    "sg:postcode":"80017",
    "sg:province":"Napoli",
    "wof:name":"R.p. Auto Di Riccio Antonio Sas",
    "wof:placetype":"venue"
},
  "geometry": {"coordinates":[14.223927,40.920471],"type":"Point"}
}