{
  "type": "Feature",
  "properties": {
    "iso:country":"IT",
    "sg:address":"31020 Villorba",
    "sg:city":"Villorba",
    "sg:orig_category":"Moquettes",
    "sg:phone":"+39 0422 911270",
    "sg:postcode":"31020",
    "sg:province":"Treviso",
    "wof:name":"Linoleum Moquettes Dorpetti Srl",
    "wof:placetype":"venue"
},
  "geometry": {"coordinates":[12.2498893738,45.7211837769],"type":"Point"}
}