{
  "type": "Feature",
  "properties": {
    "addr:full":"34, C. Trieste 28100 Novara Novara Novara 28100",
    "addr:housenumber":"34",
    "addr:postcode":"28100;28100",
    "addr:street":"C. Trieste",
    "iso:country":"IT",
    "sg:address":"34, C. Trieste 28100 Novara",
    "sg:city":"Novara",
    "sg:classifiers":[
        {
            "category":"Banks & Credit Unions",
            "subcategory":"Investment Brokerage",
            "type":"Services"
        }
    ],
    "sg:phone":"+39 0321 696630",
    "sg:postcode":"28100",
    "sg:province":"Novara",
    "sg:tags":[
        "-",
        "transport",
        "related"
    ],
    "wof:name":"Beya Trasporti",
    "wof:placetype":"venue"
},
  "geometry": {"coordinates":[8.637324,45.448669],"type":"Point"}
}