{
  "type": "Feature",
  "properties": {
    "iso:country":"IT",
    "sg:address":"36060 Romano D'ezzelino",
    "sg:orig_category":"Carta, Cartone E Prodotti Primari. Forniture E Materiali Per Imballaggio E Confezionamento",
    "sg:phone":"+39 0424 32853",
    "sg:postcode":"36060",
    "sg:province":"Vicenza",
    "wof:name":"Ms Srl Di Marcadella & Ferronato",
    "wof:placetype":"venue"
},
  "geometry": {"coordinates":[11.777049,45.779358],"type":"Point"}
}