{
  "type": "Feature",
  "properties": {
    "iso:country":"IT",
    "sg:address":"25030 Trenzano",
    "sg:city":"Trenzano",
    "sg:orig_category":"Macchine E Forniture Per Arredamento E Industria Del Legno",
    "sg:phone":"+39 030 997 4304",
    "sg:postcode":"25030",
    "sg:province":"Brescia",
    "wof:name":"M.r. Utensili Di Morghen R. & C. (s.a.s.)",
    "wof:placetype":"venue"
},
  "geometry": {"coordinates":[10.224246,45.551304],"type":"Point"}
}