{
  "type": "Feature",
  "properties": {
    "iso:country":"IT",
    "sg:address":"06012 Citta'dicastello",
    "sg:city":"Cerbara",
    "sg:orig_category":"Prodotti Finiti Stampati. Forniture E Prodotti Informatici. Forniture Per Uffici",
    "sg:phone":"+39 075 851 1510",
    "sg:postcode":"06012",
    "sg:province":"Perugia",
    "sg:website":"http://www.pasquispa.com",
    "wof:name":"Modul Lama Srl",
    "wof:placetype":"venue"
},
  "geometry": {"coordinates":[12.2319049835,43.4577865601],"type":"Point"}
}