{
  "type": "Feature",
  "properties": {
    "iso:country":"IT",
    "sg:address":"20092 Cinisello Balsamo",
    "sg:city":"Cinisello Balsamo",
    "sg:orig_category":"Cinematografia E Radiotelevisione. Pubblicita', Marketing E Comunicazione. Acqua, Luce, Gas E Societa' Di Esercizio Pubblico",
    "sg:phone":"+39 02 6604 3111",
    "sg:postcode":"20092",
    "sg:province":"Milano",
    "wof:name":"Atena Servizi S.p.a.",
    "wof:placetype":"venue"
},
  "geometry": {"coordinates":[9.239838,45.557796],"type":"Point"}
}