{
  "type": "Feature",
  "properties": {
    "iso:country":"IT",
    "sg:address":"Contrada Serralta 60048 Serra San Quirico",
    "sg:city":"Serra San Quirico",
    "sg:classifiers":[
        {
            "category":"Professional",
            "subcategory":"Engineering",
            "type":"Services"
        }
    ],
    "sg:phone":"+39 0731 880008",
    "sg:postcode":"60048",
    "sg:province":"Ancona",
    "sg:tags":[
        "machine",
        "-",
        "mechanical"
    ],
    "wof:name":"Aria S.r.l.",
    "wof:placetype":"venue"
},
  "geometry": {"coordinates":[13.032554,43.436642],"type":"Point"}
}