{
  "type": "Feature",
  "properties": {
    "addr:full":"60/68, Via Briantina 20038 Seregno Seregno Milano 20038",
    "addr:housenumber":"60 / 68",
    "addr:postcode":"20038;20038",
    "addr:street":"Via Briantina",
    "iso:country":"IT",
    "sg:address":"60/68, Via Briantina 20038 Seregno",
    "sg:city":"Seregno",
    "sg:classifiers":[
        {
            "category":"Shopping",
            "subcategory":"Crafts & Fabrics",
            "type":"Retail Goods"
        }
    ],
    "sg:phone":"+39 036 222 9046",
    "sg:postcode":"20038",
    "sg:province":"Milano",
    "wof:name":"Dell'orto Gianpaolo (s.p.a.)",
    "wof:placetype":"venue"
},
  "geometry": {"coordinates":[9.2129964828,45.65965271],"type":"Point"}
}