{
  "type": "Feature",
  "properties": {
    "iso:country":"IT",
    "sg:address":"30038 Spinea",
    "sg:city":"Spinea",
    "sg:orig_category":"Acciaierie E Fonderie",
    "sg:phone":"+39 041 541 0510",
    "sg:postcode":"30038",
    "sg:province":"Venezia",
    "wof:name":"Fula Snc Di Di Giacomo Orlando & C.",
    "wof:placetype":"venue"
},
  "geometry": {"coordinates":[12.145673,45.506889],"type":"Point"}
}