{
  "type": "Feature",
  "properties": {
    "addr:full":"10099 San Mauro Torinese San Mauro Torinese Torino 10099",
    "addr:housenumber":"10099",
    "addr:postcode":"10099",
    "addr:street":"San",
    "iso:country":"IT",
    "sg:address":"10099 San Mauro Torinese",
    "sg:city":"San Mauro Torinese",
    "sg:orig_category":"Macchine, Impianti Ed Attrezzature Industria Chimica. Attrezzature E Forniture Per Officine Riparazione E Servizi Ausiliari",
    "sg:phone":"+39 011 273 1176",
    "sg:postcode":"10099",
    "sg:province":"Torino",
    "wof:name":"I.m.i. Installazione Manutenzione Impianti (s.r.l.)",
    "wof:placetype":"venue"
},
  "geometry": {"coordinates":[7.741341,45.11639],"type":"Point"}
}