{
  "type": "Feature",
  "properties": {
    "iso:country":"IT",
    "sg:address":"24, Via Cortili Mariani 44039 Tresigallo",
    "sg:city":"Tresigallo",
    "sg:classifiers":[
        {
            "category":"Real Estate",
            "subcategory":"Architect",
            "type":"Services"
        }
    ],
    "sg:phone":"+39 0533 601422",
    "sg:postcode":"44039",
    "sg:province":"Ferrara",
    "sg:tags":[
        "textile",
        "clothing"
    ],
    "wof:name":"Creazioni Mirell",
    "wof:placetype":"venue"
},
  "geometry": {"coordinates":[11.870686,44.809349],"type":"Point"}
}