{
  "type": "Feature",
  "properties": {
    "iso:country":"IT",
    "sg:address":"00192 Roma",
    "sg:city":"Roma",
    "sg:orig_category":"Prodotti Finiti Stampati. Forniture Per Uffici",
    "sg:phone":"+39 06 321 4150",
    "sg:postcode":"00192",
    "sg:province":"Roma",
    "wof:name":"Palombi Fratelli Srl",
    "wof:placetype":"venue"
},
  "geometry": {"coordinates":[12.4651613235,41.9086494446],"type":"Point"}
}