{
  "type": "Feature",
  "properties": {
    "iso:country":"IT",
    "sg:address":"00156 Roma",
    "sg:city":"Roma",
    "sg:orig_category":"Ospedali E Servizi Sanitari",
    "sg:phone":"+39 06 411 4929",
    "sg:postcode":"00156",
    "sg:province":"Roma",
    "wof:name":"Associazione Italiana Della Croce Rossa",
    "wof:placetype":"venue"
},
  "geometry": {"coordinates":[12.501858,41.682476],"type":"Point"}
}