{
  "type": "Feature",
  "properties": {
    "addr:full":"Via Ripamonti Giuseppe 89 20141 Milano Milano Milano 20141",
    "addr:housenumber":"89",
    "addr:postcode":"20141;20141",
    "addr:street":"Via Ripamonti Giuseppe",
    "iso:country":"IT",
    "sg:address":"Via Ripamonti Giuseppe 89 20141 Milano",
    "sg:city":"Milano",
    "sg:classifiers":[
        {
            "category":"Communications",
            "subcategory":"Film & Video Production",
            "type":"Services"
        }
    ],
    "sg:phone":"+39 02 574321",
    "sg:postcode":"20141",
    "sg:province":"Milano",
    "sg:tags":[
        "pvc",
        "chloride",
        "polyvinyl"
    ],
    "wof:name":"Adriaplast Spa",
    "wof:placetype":"venue"
},
  "geometry": {"coordinates":[9.1997108459,45.4418258667],"type":"Point"}
}