{
  "type": "Feature",
  "properties": {
    "addr:full":"3, Via I Maggio 42042 Fabbrico Reggio Nell'Emilia 42042",
    "addr:postcode":"42042;42042",
    "addr:street":"Via I Maggio",
    "iso:country":"IT",
    "sg:address":"3, Via I Maggio 42042 Fabbrico",
    "sg:classifiers":[
        {
            "category":"Professional",
            "subcategory":"Engineering",
            "type":"Services"
        }
    ],
    "sg:phone":"+39 0522 660421",
    "sg:postcode":"42042",
    "sg:province":"Reggio Nell'Emilia",
    "sg:tags":[
        "machine",
        "-",
        "mechanical"
    ],
    "wof:name":"Officina Meccanica Fabbricese",
    "wof:placetype":"venue"
},
  "geometry": {"coordinates":[10.627794,44.696228],"type":"Point"}
}