{
  "type": "Feature",
  "properties": {
    "addr:full":"71030 Mattinata Mattinata Foggia 71030",
    "addr:postcode":"71030;71030",
    "iso:country":"IT",
    "sg:address":"71030 Mattinata",
    "sg:city":"Mattinata",
    "sg:orig_category":"Agenzie Immobiliari",
    "sg:phone":"+39 0884 550292",
    "sg:postcode":"71030",
    "sg:province":"Foggia",
    "wof:name":"Armiento Rafaela",
    "wof:placetype":"venue"
},
  "geometry": {"coordinates":[15.554399,41.465248],"type":"Point"}
}