{
  "type": "Feature",
  "properties": {
    "addr:full":"37060 Mozzecane Mozzecane Verona 37060",
    "addr:postcode":"37060;37060",
    "iso:country":"IT",
    "sg:address":"37060 Mozzecane",
    "sg:city":"Mozzecane",
    "sg:orig_category":"Petroli, Gas E Combustibili",
    "sg:phone":"+39 045 793 0001",
    "sg:postcode":"37060",
    "sg:province":"Verona",
    "wof:name":"Petroli Scaligera Sas",
    "wof:placetype":"venue"
},
  "geometry": {"coordinates":[10.8160324097,45.3073806763],"type":"Point"}
}