{
  "type": "Feature",
  "properties": {
    "iso:country":"IT",
    "sg:address":"00019 Tivoli",
    "sg:city":"Tivoli",
    "sg:orig_category":"Servizi E Lavori Per Edilizia E Lavori Pubblici",
    "sg:phone":"+39 0774 509224",
    "sg:postcode":"00019",
    "sg:province":"Roma",
    "wof:name":"Ce.se.p. Di Guerrini Daniele & Stefanizzi M.t.",
    "wof:placetype":"venue"
},
  "geometry": {"coordinates":[12.76933,41.953609],"type":"Point"}
}