{
  "type": "Feature",
  "properties": {
    "addr:full":"40069 Zola Predosa Zola Bologna 40069",
    "addr:postcode":"40069;40069",
    "iso:country":"IT",
    "sg:address":"40069 Zola Predosa",
    "sg:city":"Zola",
    "sg:orig_category":"Catene E Pignoni",
    "sg:phone":"+39 051 616 7393",
    "sg:postcode":"40069",
    "sg:province":"Bologna",
    "wof:name":"Split Srl",
    "wof:placetype":"venue"
},
  "geometry": {"coordinates":[11.235407,44.501335],"type":"Point"}
}