{
  "type": "Feature",
  "properties": {
    "addr:full":"40017 San Giovanni In Persiceto San Giovanni in Persiceto Bologna 40017",
    "addr:housenumber":"40017",
    "addr:postcode":"40017",
    "iso:country":"IT",
    "sg:address":"40017 San Giovanni In Persiceto",
    "sg:city":"San Giovanni in Persiceto",
    "sg:orig_category":"Avvocati, Notai E Servizi Legali. Consulenze Tecniche, Amministrative E Perizie",
    "sg:phone":"+39 051 681 0196",
    "sg:postcode":"40017",
    "sg:province":"Bologna",
    "wof:name":"Mazzoni Giuseppe",
    "wof:placetype":"venue"
},
  "geometry": {"coordinates":[11.18228,44.645348],"type":"Point"}
}