{
  "type": "Feature",
  "properties": {
    "iso:country":"IT",
    "sg:address":"45, Via Antonello Da Messina 95021 Aci Castello",
    "sg:city":"Aci Castello",
    "sg:classifiers":[
        {
            "category":"Travel",
            "subcategory":"Travel Agent",
            "type":"Entertainment"
        }
    ],
    "sg:phone":"+39 39095271557",
    "sg:postcode":"95021",
    "sg:province":"Catania",
    "sg:tags":[
        "business"
    ],
    "wof:name":"Hotel Sheraton",
    "wof:placetype":"venue"
},
  "geometry": {"coordinates":[15.137272,37.542042],"type":"Point"}
}