{
  "type": "Feature",
  "properties": {
    "iso:country":"IT",
    "sg:address":"132, Via Castelletto Stura 12100 Cuneo",
    "sg:city":"Cuneo",
    "sg:classifiers":[
        {
            "category":"Manufacturing",
            "subcategory":"Tools & Machinery",
            "type":"Manufacturing & Wholesale Goods"
        }
    ],
    "sg:phone":"+39 0171 346435",
    "sg:postcode":"12100",
    "sg:province":"Cuneo",
    "sg:tags":[
        "environment",
        "equipment",
        "-"
    ],
    "wof:name":"Saced (s.r.l.)",
    "wof:placetype":"venue"
},
  "geometry": {"coordinates":[7.570191,44.404709],"type":"Point"}
}