{
  "type": "Feature",
  "properties": {
    "iso:country":"IT",
    "sg:address":"Via Barozzia 2; Formigine",
    "sg:classifiers":[
        {
            "category":"Banks & Credit Unions",
            "subcategory":"Bank",
            "type":"Services"
        }
    ],
    "sg:phone":"+39 059 572494",
    "wof:name":"Banca Agricola Mantovana Scarl",
    "wof:placetype":"venue"
},
  "geometry": {"coordinates":[10.782229,44.539089],"type":"Point"}
}