{
  "type": "Feature",
  "properties": {
    "iso:country":"IT",
    "sg:address":"5, Via Del Caminanz 23842 Bosisio Parini",
    "sg:city":"Bosisio Parini",
    "sg:classifiers":[
        {
            "category":"Shopping",
            "subcategory":"Computers & Home Electronics",
            "type":"Retail Goods"
        }
    ],
    "sg:phone":"+39 39031876290",
    "sg:postcode":"23842",
    "sg:province":"Lecco",
    "sg:tags":[
        "electronic",
        "electrical",
        "equipment"
    ],
    "wof:name":"Motor Press (s.r.l.)",
    "wof:placetype":"venue"
},
  "geometry": {"coordinates":[9.390071,45.852982],"type":"Point"}
}