{
  "type": "Feature",
  "properties": {
    "addr:full":"00043 Ciampino Ciampino Roma 00043",
    "addr:postcode":"00043;roma 00043",
    "iso:country":"IT",
    "sg:address":"00043 Ciampino",
    "sg:city":"Ciampino",
    "sg:orig_category":"Cinematografia E Radiotelevisione. Forniture Per Il Settore Dello Spettacolo",
    "sg:phone":"+39 06 791 0098",
    "sg:postcode":"00043",
    "sg:province":"Roma",
    "wof:name":"Arco Due S.r.l.",
    "wof:placetype":"venue"
},
  "geometry": {"coordinates":[12.598457,41.807446],"type":"Point"}
}