{
  "type": "Feature",
  "properties": {
    "addr:full":"51, Via Roma 25070 Casto Casto Brescia 25070",
    "addr:postcode":"25070;25070",
    "addr:street":"Via Roma",
    "iso:country":"IT",
    "sg:address":"51, Via Roma 25070 Casto",
    "sg:city":"Casto",
    "sg:classifiers":[
        {
            "category":"Manufacturing",
            "subcategory":"Metals",
            "type":"Manufacturing & Wholesale Goods"
        }
    ],
    "sg:phone":"+39 39036588170",
    "sg:postcode":"25070",
    "sg:province":"Brescia",
    "sg:tags":[
        "metallurgy",
        "metalworking"
    ],
    "wof:name":"Stilars Di Gobbi Angelo E Arduino & C. (s.n.c.)",
    "wof:placetype":"venue"
},
  "geometry": {"coordinates":[10.2654790878,45.6506500244],"type":"Point"}
}