{
  "type": "Feature",
  "properties": {
    "addr:full":"35123 Padova Padova Padova 35123",
    "addr:postcode":"35123;35123",
    "iso:country":"IT",
    "sg:address":"35123 Padova",
    "sg:city":"Padova",
    "sg:orig_category":"Ospedali E Servizi Sanitari",
    "sg:phone":"+39 049 822 2711",
    "sg:postcode":"35123",
    "sg:province":"Padova",
    "wof:name":"Casa Di Cura Privata Morgagni",
    "wof:placetype":"venue"
},
  "geometry": {"coordinates":[11.878274,45.397102],"type":"Point"}
}