{
  "type": "Feature",
  "properties": {
    "iso:country":"IT",
    "sg:address":"35127 Padova",
    "sg:city":"Padova",
    "sg:orig_category":"Elettrotecnica Professionale E Di Consumo",
    "sg:postcode":"35127",
    "sg:province":"Padova",
    "wof:name":"Sicom (s.r.l.)",
    "wof:placetype":"venue"
},
  "geometry": {"coordinates":[11.934061,45.387646],"type":"Point"}
}