{
  "type": "Feature",
  "properties": {
    "iso:country":"IT",
    "sg:address":"33077 Sacile",
    "sg:city":"Sacile",
    "sg:orig_category":"Nautica. Automobili E Mezzi Di Trasporto",
    "sg:phone":"+39 0434 780388",
    "sg:postcode":"33077",
    "sg:province":"Pordenone",
    "wof:name":"Spagnol Sandro",
    "wof:placetype":"venue"
},
  "geometry": {"coordinates":[12.487506,45.965412],"type":"Point"}
}