{
  "type": "Feature",
  "properties": {
    "iso:country":"IT",
    "sg:address":"34131 Trieste",
    "sg:city":"Trieste",
    "sg:orig_category":"Servizi Culturali E Per Lo Spettacolo. Servizi Per Lo Sport E Il Tempo Libero. Associazioni Ed Organismi Di Interesse Pubblico",
    "sg:phone":"+39 040 760 0131",
    "sg:postcode":"34131",
    "sg:province":"Trieste",
    "sg:website":"http://www.disciplineorientali.com",
    "wof:name":"Centro Discipline Orientali - Associazione Joytinat",
    "wof:placetype":"venue"
},
  "geometry": {"coordinates":[13.779407,45.647072],"type":"Point"}
}