{
  "type": "Feature",
  "properties": {
    "iso:country":"IT",
    "sg:address":"20052 Monza",
    "sg:city":"Monza",
    "sg:orig_category":"Accessori Moda D'abbigliamento. Shopping",
    "sg:phone":"+39 039 835795",
    "sg:postcode":"20052",
    "sg:province":"Milano",
    "wof:name":"Later Di Mauri Luca & C. (s.n.c.)",
    "wof:placetype":"venue"
},
  "geometry": {"coordinates":[9.231512,45.546074],"type":"Point"}
}