{
  "type": "Feature",
  "properties": {
    "iso:country":"IT",
    "sg:address":"34133 Trieste",
    "sg:city":"Trieste",
    "sg:orig_category":"Ristorazione E Locali Pubblici Affini. Ristoranti Ed Esercizi Affini. Servizi Ausiliari Di Ristorazione E Di Intrattenimento",
    "sg:phone":"+39 040 676 1111",
    "sg:postcode":"34133",
    "sg:province":"Trieste",
    "sg:website":"http://www.desco.it",
    "wof:name":"Desco' Srl",
    "wof:placetype":"venue"
},
  "geometry": {"coordinates":[13.776536,45.653091],"type":"Point"}
}