{
  "type": "Feature",
  "properties": {
    "iso:country":"IT",
    "sg:address":"36/a, Via Torretta 40012 Calderara Di Reno",
    "sg:city":"Calderara di Reno",
    "sg:classifiers":[
        {
            "category":"Manufacturing",
            "subcategory":"Rubber & Plastics",
            "type":"Manufacturing & Wholesale Goods"
        }
    ],
    "sg:phone":"+39 39051728221",
    "sg:postcode":"40012",
    "sg:province":"Bologna",
    "wof:name":"Gi Erre Plastica (s.r.l.)",
    "wof:placetype":"venue"
},
  "geometry": {"coordinates":[11.2669916153,44.5472183228],"type":"Point"}
}