{
  "type": "Feature",
  "properties": {
    "addr:full":"43/45, Via Gessi Lanfranco 48022 Lugo Lugo Ravenna 48022",
    "addr:housenumber":"43 / 45",
    "addr:postcode":"48022;48022",
    "addr:street":"Via Gessi Lanfranco",
    "iso:country":"IT",
    "sg:address":"43/45, Via Gessi Lanfranco 48022 Lugo",
    "sg:city":"Lugo",
    "sg:classifiers":[
        {
            "category":"Utilities",
            "subcategory":"Electric",
            "type":"Services"
        }
    ],
    "sg:phone":"+39 39054532701",
    "sg:postcode":"48022",
    "sg:province":"Ravenna",
    "sg:tags":[
        "component",
        "electronic"
    ],
    "wof:name":"Equitec (s.r.l.)",
    "wof:placetype":"venue"
},
  "geometry": {"coordinates":[12.196571,44.41573],"type":"Point"}
}