{
  "type": "Feature",
  "properties": {
    "addr:full":"00186 Roma Roma Roma 00186",
    "addr:postcode":"00186;00186",
    "iso:country":"IT",
    "sg:address":"00186 Roma",
    "sg:city":"Roma",
    "sg:orig_category":"Prodotti Finiti Stampati. Articoli Da Regalo. Arte Ed Artigianato Artistico. Shopping",
    "sg:phone":"+39 06 361 2322",
    "sg:postcode":"00186",
    "sg:province":"Roma",
    "wof:name":"Trincia Piero",
    "wof:placetype":"venue"
},
  "geometry": {"coordinates":[12.3819799423,41.8176231384],"type":"Point"}
}