{
  "type": "Feature",
  "properties": {
    "iso:country":"IT",
    "sg:address":"23879 Verderio Inferiore",
    "sg:city":"Verderio Inferiore",
    "sg:orig_category":"Servizi E Lavori Industria Della Gomma. Servizi E Lavori Industria Delle Materie Plastiche. Forniture Per Edilizia E Lavori Pubblici",
    "sg:phone":"+39 039 511560",
    "sg:postcode":"23879",
    "sg:province":"Lecco",
    "wof:name":"T G (s.r.l.)",
    "wof:placetype":"venue"
},
  "geometry": {"coordinates":[9.423178,45.67062],"type":"Point"}
}