{
  "type": "Feature",
  "properties": {
    "addr:full":"06084 Bettona Bettona Perugia 06084",
    "addr:postcode":"06084;06084",
    "iso:country":"IT",
    "sg:address":"06084 Bettona",
    "sg:city":"Bettona",
    "sg:orig_category":"Porte",
    "sg:phone":"+39 075 982169",
    "sg:postcode":"06084",
    "sg:province":"Perugia",
    "wof:name":"Artigiana Arredamenti",
    "wof:placetype":"venue"
},
  "geometry": {"coordinates":[12.4904689789,43.050617218],"type":"Point"}
}