{
  "type": "Feature",
  "properties": {
    "iso:country":"IT",
    "sg:address":"64100 Teramo",
    "sg:city":"Teramo",
    "sg:orig_category":"Impiantistica E Prodotti Tecnologici Per Edilizia. Elettrotecnica Industriale, Prodotti E Apparecchiature. Elettrotecnica Professionale E Di Consumo",
    "sg:phone":"+39 8651329589",
    "sg:postcode":"64100",
    "sg:province":"Teramo",
    "wof:name":"So.ca. Srl",
    "wof:placetype":"venue"
},
  "geometry": {"coordinates":[13.70575,42.677277],"type":"Point"}
}