{
  "type": "Feature",
  "properties": {
    "iso:country":"IT",
    "sg:address":"20159 Milano",
    "sg:city":"Milano",
    "sg:orig_category":"Ospedali E Servizi Sanitari",
    "sg:phone":"+39 02 6680 6729",
    "sg:postcode":"20159",
    "sg:province":"Milano",
    "wof:name":"Studio Frassine Pierpaolo - Grisenti Angela E Associati",
    "wof:placetype":"venue"
},
  "geometry": {"coordinates":[9.190457,45.492817],"type":"Point"}
}