{
  "type": "Feature",
  "properties": {
    "iso:country":"IT",
    "sg:address":"10098 Rivoli",
    "sg:city":"Rivoli",
    "sg:orig_category":"Forniture Per Agricoltura E Zootecnia. Animali Domestici",
    "sg:phone":"+39 011 958 0223",
    "sg:postcode":"10098",
    "sg:province":"Torino",
    "wof:name":"Arca Di Noe' Di Roberta Altana",
    "wof:placetype":"venue"
},
  "geometry": {"coordinates":[7.5176157951,45.0691299438],"type":"Point"}
}