{
  "type": "Feature",
  "properties": {
    "addr:full":"36015 Schio Schio Vicenza 36015",
    "addr:postcode":"36015;36015",
    "iso:country":"IT",
    "sg:address":"36015 Schio",
    "sg:city":"Schio",
    "sg:classifiers":[
        {
            "category":"Manufacturing",
            "subcategory":"Tools & Machinery",
            "type":"Manufacturing & Wholesale Goods"
        }
    ],
    "sg:phone":"+39 0445 576407",
    "sg:postcode":"36015",
    "sg:province":"Vicenza",
    "sg:tags":[
        "machining",
        "mechanical"
    ],
    "wof:name":"Map Di Tonello Bruno & C. Snc",
    "wof:placetype":"venue"
},
  "geometry": {"coordinates":[11.5415,45.576401],"type":"Point"}
}