{
  "type": "Feature",
  "properties": {
    "addr:full":"Via Marsala 40, 21013 Gallarate, Va Gallarate Varese 21013",
    "addr:housenumber":"40",
    "addr:postcode":"21013;21013",
    "addr:street":"Via Marsala",
    "iso:country":"IT",
    "sg:address":"Via Marsala 40, 21013 Gallarate, Va",
    "sg:city":"Gallarate",
    "sg:classifiers":[
        {
            "category":"Banks & Credit Unions",
            "subcategory":"Bank",
            "type":"Services"
        }
    ],
    "sg:postcode":"21013",
    "sg:province":"Varese",
    "wof:name":"Banca Popolare Del Ticino Scarl",
    "wof:placetype":"venue"
},
  "geometry": {"coordinates":[8.785422,45.657154],"type":"Point"}
}