{
  "type": "Feature",
  "properties": {
    "addr:full":"43013 Langhirano Langhirano Parma 43013",
    "addr:postcode":"43013;43013",
    "iso:country":"IT",
    "sg:address":"43013 Langhirano",
    "sg:city":"Langhirano",
    "sg:orig_category":"Salumifici E Prosciuttifici",
    "sg:phone":"+39 0521 861329",
    "sg:postcode":"43013",
    "sg:province":"Parma",
    "wof:name":"Piazza Peppino E C. Snc",
    "wof:placetype":"venue"
},
  "geometry": {"coordinates":[10.238578,44.698872],"type":"Point"}
}