{
  "type": "Feature",
  "properties": {
    "iso:country":"IT",
    "sg:address":"2, Via Montello 20051 Limbiate",
    "sg:city":"Limbiate",
    "sg:classifiers":[
        {
            "category":"Manufacturing",
            "subcategory":"Metals",
            "type":"Manufacturing & Wholesale Goods"
        }
    ],
    "sg:phone":"+39 39029960078",
    "sg:postcode":"20051",
    "sg:province":"Milano",
    "sg:tags":[
        "processing"
    ],
    "wof:name":"M & F Mingardi & Ferrara (s.r.l.)",
    "wof:placetype":"venue"
},
  "geometry": {"coordinates":[9.0849695206,45.642780304],"type":"Point"}
}