{
  "type": "Feature",
  "properties": {
    "addr:full":"71100 Foggia Foggia Foggia 71100",
    "addr:postcode":"71100;71100",
    "iso:country":"IT",
    "sg:address":"71100 Foggia",
    "sg:city":"Foggia",
    "sg:orig_category":"Prodotti Chimici Secondari. Macchine E Forniture Per Ecologia E Smaltimento Rifiuti. Forniture Per Attivita' Industriali",
    "sg:phone":"+39 0881 883148",
    "sg:postcode":"71100",
    "sg:province":"Foggia",
    "wof:name":"Eco Clean Di Di Nunno Vincenzo Massimo",
    "wof:placetype":"venue"
},
  "geometry": {"coordinates":[15.5474376678,41.4497947693],"type":"Point"}
}