{
  "type": "Feature",
  "properties": {
    "addr:full":"60015 Falconara Marittima Falconara Marittima Ancona 60015",
    "addr:postcode":"60015;60015",
    "iso:country":"IT",
    "sg:address":"60015 Falconara Marittima",
    "sg:city":"Falconara Marittima",
    "sg:orig_category":"Prodotti E Manufatti In Materie Plastiche",
    "sg:phone":"+39 071 916 2253",
    "sg:postcode":"60015",
    "sg:province":"Ancona",
    "wof:name":"Tekcell Srl",
    "wof:placetype":"venue"
},
  "geometry": {"coordinates":[13.3684196472,43.6138954163],"type":"Point"}
}