{
  "type": "Feature",
  "properties": {
    "addr:full":"20090 Buccinasco Buccinasco Milano 20090",
    "addr:postcode":"20090;20090",
    "iso:country":"IT",
    "sg:address":"20090 Buccinasco",
    "sg:city":"Buccinasco",
    "sg:orig_category":"Servizi E Lavori Per Ecologia E Smaltimento Rifiuti. Forniture Industriali Per Prevenzione, Controllo E Sicurezza",
    "sg:phone":"+39 02 4884 4031",
    "sg:postcode":"20090",
    "sg:province":"Milano",
    "wof:name":"Canevari Giampiero",
    "wof:placetype":"venue"
},
  "geometry": {"coordinates":[9.112965,45.423946],"type":"Point"}
}