{
  "type": "Feature",
  "properties": {
    "iso:country":"IT",
    "sg:address":"37024 Negrar",
    "sg:city":"Negrar",
    "sg:orig_category":"Servizi E Lavori Per Industria Alimentare E Bevande",
    "sg:phone":"+39 045 750 0177",
    "sg:postcode":"37024",
    "sg:province":"Verona",
    "wof:name":"Turri Adelino",
    "wof:placetype":"venue"
},
  "geometry": {"coordinates":[10.948398,45.527061],"type":"Point"}
}