{
  "type": "Feature",
  "properties": {
    "addr:full":"Localita' Zona Industriale 10017 Montanaro Montanaro Torino 10017",
    "addr:postcode":"10017;10017",
    "addr:street":"Localita ' Zona Industriale",
    "iso:country":"IT",
    "sg:address":"Localita' Zona Industriale 10017 Montanaro",
    "sg:city":"Montanaro",
    "sg:classifiers":[
        {
            "category":"Autos & Motor Vehicles",
            "subcategory":"Automobile Sales",
            "type":"Retail Goods"
        }
    ],
    "sg:phone":"+39 011 919 2061",
    "sg:postcode":"10017",
    "sg:province":"Torino",
    "sg:tags":[
        "motor-cars"
    ],
    "wof:name":"R.o.i. Automotive Technology S.r.l.",
    "wof:placetype":"venue"
},
  "geometry": {"coordinates":[7.6866188049,45.0705604553],"type":"Point"}
}