{
  "type": "Feature",
  "properties": {
    "addr:full":"18 Corso Umberto I, 85017 Tolve Tolve Potenza 85017",
    "addr:postcode":"85017;85017",
    "addr:street":"Corso Umberto I",
    "iso:country":"IT",
    "sg:address":"18 Corso Umberto I, 85017 Tolve",
    "sg:city":"Tolve",
    "sg:classifiers":[
        {
            "category":"Banks & Credit Unions",
            "subcategory":"Financial Services",
            "type":"Services"
        }
    ],
    "sg:phone":"+39 0971 737030",
    "sg:postcode":"85017",
    "sg:province":"Potenza",
    "sg:tags":[
        "banking",
        "finance",
        "insurance"
    ],
    "wof:name":"Banca Di Credito Cooperativo Di Tolve",
    "wof:placetype":"venue"
},
  "geometry": {"coordinates":[16.0201511383,40.6962356567],"type":"Point"}
}