{
  "type": "Feature",
  "properties": {
    "iso:country":"IT",
    "sg:address":"Via Giotto 32 20048 Carate Brianza",
    "sg:city":"Carate Brianza",
    "sg:classifiers":[
        {
            "category":"Shopping",
            "subcategory":"Event Tickets",
            "type":"Retail Goods"
        }
    ],
    "sg:phone":"+39 036 290 1288",
    "sg:postcode":"20048",
    "sg:province":"Milano",
    "sg:tags":[
        "billfold"
    ],
    "sg:website":"www.marapelletterie.it",
    "wof:name":"Mara Pelletterie S.r.l.",
    "wof:placetype":"venue"
},
  "geometry": {"coordinates":[9.239662,45.668655],"type":"Point"}
}