{
  "type": "Feature",
  "properties": {
    "addr:full":"25016 Ghedi Ghedi Brescia 25016",
    "addr:postcode":"25016;25016",
    "iso:country":"IT",
    "sg:address":"25016 Ghedi",
    "sg:city":"Ghedi",
    "sg:orig_category":"Carni, Salumi E Pesci",
    "sg:phone":"+39 030 901530",
    "sg:postcode":"25016",
    "sg:province":"Brescia",
    "wof:name":"Macalleria Equina Sajetti Severo",
    "wof:placetype":"venue"
},
  "geometry": {"coordinates":[10.300765,45.469013],"type":"Point"}
}