{
  "type": "Feature",
  "properties": {
    "iso:country":"IT",
    "sg:address":"00187 Roma",
    "sg:city":"Roma",
    "sg:orig_category":"Macchine E Forniture Per Industria Orafa E Per Orologeria",
    "sg:phone":"+39 06 678 1319",
    "sg:postcode":"00187",
    "sg:province":"Roma",
    "wof:name":"Silvestro S.r.l.",
    "wof:placetype":"venue"
},
  "geometry": {"coordinates":[12.481037,41.903522],"type":"Point"}
}