{
  "type": "Feature",
  "properties": {
    "iso:country":"IT",
    "sg:address":"40068 San Lazzaro Di Savena",
    "sg:city":"San Lazzaro",
    "sg:orig_category":"Minuterie Metalliche E Ferramenta",
    "sg:phone":"+39 051 627 1546",
    "sg:postcode":"40068",
    "sg:province":"Bologna",
    "sg:website":"http://www.priorimeccanica.it",
    "wof:name":"Priori Meccanica Srl",
    "wof:placetype":"venue"
},
  "geometry": {"coordinates":[11.4121818542,44.4768638611],"type":"Point"}
}