{
  "type": "Feature",
  "properties": {
    "iso:country":"IT",
    "sg:address":"00154 Roma",
    "sg:city":"Roma",
    "sg:orig_category":"Automobili - Commercio",
    "sg:phone":"+39 06 574 1001",
    "sg:postcode":"00154",
    "sg:province":"Roma",
    "wof:name":"Autocarrozzeria Ziliani Bartolo",
    "wof:placetype":"venue"
},
  "geometry": {"coordinates":[12.477862,41.872375],"type":"Point"}
}