{
  "type": "Feature",
  "properties": {
    "iso:country":"IT",
    "sg:address":"Via Manzoni 7 47852 Cerasolo",
    "sg:classifiers":[
        {
            "category":"Communications",
            "subcategory":"Television Station",
            "type":"Services"
        }
    ],
    "sg:phone":"+39 0541 759068",
    "sg:province":"RN",
    "sg:tags":[
        "casting",
        "special"
    ],
    "wof:name":"Fonderia Morri Di Morri Antonio & C. Snc",
    "wof:placetype":"venue"
},
  "geometry": {"coordinates":[12.53657,43.974739],"type":"Point"}
}