{
  "type": "Feature",
  "properties": {
    "iso:country":"IT",
    "sg:address":"24026 Leffe",
    "sg:city":"Leffe",
    "sg:orig_category":"Accessori Moda D'abbigliamento. Forniture Per Abbigliamento E Pelletterie. Shopping",
    "sg:phone":"+39 035 733766",
    "sg:postcode":"24026",
    "sg:province":"Bergamo",
    "wof:name":"Bazzana Antonio",
    "wof:placetype":"venue"
},
  "geometry": {"coordinates":[9.891716,45.798676],"type":"Point"}
}