{
  "type": "Feature",
  "properties": {
    "addr:full":"Via Aurelia 772 00165 Roma Roma Roma 00165",
    "addr:housenumber":"772",
    "addr:postcode":"00165;00165",
    "addr:street":"Via Aurelia",
    "iso:country":"IT",
    "sg:address":"Via Aurelia 772 00165 Roma",
    "sg:city":"Roma",
    "sg:classifiers":[
        {
            "category":"Wholesale",
            "subcategory":"Electrical",
            "type":"Manufacturing & Wholesale Goods"
        }
    ],
    "sg:phone":"+39 06 6641 6440",
    "sg:postcode":"00165",
    "sg:province":"Roma",
    "sg:tags":[
        "component"
    ],
    "wof:name":"Dme Srl",
    "wof:placetype":"venue"
},
  "geometry": {"coordinates":[12.412415,41.890457],"type":"Point"}
}