{
  "type": "Feature",
  "properties": {
    "addr:full":"95126 Catania Catania Catania 95126",
    "addr:postcode":"95126;95126",
    "iso:country":"IT",
    "sg:address":"95126 Catania",
    "sg:city":"Catania",
    "sg:orig_category":"Biancheria, Telerie E Coperte. Forniture Alle Strutture Ricettive",
    "sg:phone":"+39 095 712 2649",
    "sg:postcode":"95126",
    "sg:province":"Catania",
    "wof:name":"Ditta Tosto Natale",
    "wof:placetype":"venue"
},
  "geometry": {"coordinates":[15.106056,37.530426],"type":"Point"}
}