{
  "type": "Feature",
  "properties": {
    "iso:country":"IT",
    "sg:address":"88040 Gizzeria",
    "sg:city":"Gizzeria",
    "sg:orig_category":"Videogiochi, Flippers E Biliardini - Produzione E Ingrosso",
    "sg:phone":"+39 0968 97149",
    "sg:postcode":"88040",
    "sg:province":"Catanzaro",
    "wof:name":"Barbagallo Francesco",
    "wof:placetype":"venue"
},
  "geometry": {"coordinates":[16.204241,38.98111],"type":"Point"}
}