{
  "type": "Feature",
  "properties": {
    "iso:country":"IT",
    "sg:address":"21, Via Segni 63024 Grottazzolina",
    "sg:city":"Grottazzolina",
    "sg:classifiers":[
        {
            "category":"Food & Beverages",
            "subcategory":"Groceries & Convenience Stores",
            "type":"Retail Goods"
        }
    ],
    "sg:phone":"+39 0734 631372",
    "sg:postcode":"63024",
    "sg:province":"Ascoli Piceno",
    "sg:tags":[
        "product",
        "related"
    ],
    "wof:name":"Bacalini (s.r.l.)",
    "wof:placetype":"venue"
},
  "geometry": {"coordinates":[13.6021242142,43.1158409119],"type":"Point"}
}