{
  "type": "Feature",
  "properties": {
    "addr:full":"9, Via Leopardi Giacomo 20123 Milano Milano Milano 20123",
    "addr:postcode":"20123;20123",
    "addr:street":"Via Leopardi Giacomo",
    "iso:country":"IT",
    "sg:address":"9, Via Leopardi Giacomo 20123 Milano",
    "sg:city":"Milano",
    "sg:classifiers":[
        {
            "category":"Professional",
            "subcategory":"Advertising",
            "type":"Services"
        }
    ],
    "sg:phone":"+39 390 243 8191",
    "sg:postcode":"20123",
    "sg:province":"Milano",
    "sg:tags":[
        "communication",
        "medium"
    ],
    "wof:name":"Kpnqwest Italia Spa",
    "wof:placetype":"venue"
},
  "geometry": {"coordinates":[9.175043,45.467728],"type":"Point"}
}