{
  "type": "Feature",
  "properties": {
    "iso:country":"IT",
    "sg:address":"25038 Rovato",
    "sg:city":"Rovato",
    "sg:orig_category":"Cereali E Granaglie",
    "sg:phone":"+39 030 772 1586",
    "sg:postcode":"25038",
    "sg:province":"Brescia",
    "wof:name":"F.lli Scuri Srl",
    "wof:placetype":"venue"
},
  "geometry": {"coordinates":[10.017149,45.53064],"type":"Point"}
}