{
  "type": "Feature",
  "properties": {
    "iso:country":"IT",
    "sg:address":"58045 Civitella Paganico",
    "sg:city":"Civitella Paganico",
    "sg:classifiers":[
        {
            "category":"Restaurant",
            "type":"Food & Drink"
        }
    ],
    "sg:phone":"+39 0564 905590",
    "sg:postcode":"58045",
    "sg:province":"Grosseto",
    "sg:tags":[
        "auxiliary",
        "entertainment",
        "premises",
        "related",
        "catering",
        "similar",
        "public",
        "restaurants"
    ],
    "sg:website":"http://www.lasteccaia.it",
    "wof:name":"Park Hotel La Steccaia",
    "wof:placetype":"venue"
},
  "geometry": {"coordinates":[11.275053,43.022591],"type":"Point"}
}