{
  "type": "Feature",
  "properties": {
    "iso:country":"IT",
    "sg:address":"39, Viale Murano 47838 Riccione",
    "sg:city":"Riccione",
    "sg:classifiers":[
        {
            "category":"Autos & Motor Vehicles",
            "subcategory":"Boat Sales",
            "type":"Retail Goods"
        }
    ],
    "sg:phone":"+39 0541 660061",
    "sg:postcode":"47838",
    "sg:province":"Rimini",
    "wof:name":"Rimini Sail Srl",
    "wof:placetype":"venue"
},
  "geometry": {"coordinates":[12.613916,43.98756],"type":"Point"}
}