{
  "type": "Feature",
  "properties": {
    "iso:country":"IT",
    "sg:address":"14, Via Isonzo 42020 Quattro Castella",
    "sg:classifiers":[
        {
            "category":"Food & Beverages",
            "subcategory":"Groceries & Convenience Stores",
            "type":"Retail Goods"
        }
    ],
    "sg:phone":"+39 0522 885600",
    "sg:postcode":"42020",
    "sg:province":"Reggio Nell'Emilia",
    "sg:tags":[
        "product",
        "related"
    ],
    "wof:name":"Salumificio Stella (s.r.l.)",
    "wof:placetype":"venue"
},
  "geometry": {"coordinates":[10.5826921463,44.6414222717],"type":"Point"}
}