{
  "type": "Feature",
  "properties": {
    "iso:country":"IT",
    "sg:address":"39057 Appiano Strada Vino",
    "sg:orig_category":"Abbigliamento Esterno, Maglierie E Pelliccerie. Forniture Industriali Per Prevenzione, Controllo E Sicurezza",
    "sg:phone":"+39 0471 664144",
    "sg:postcode":"39057",
    "sg:province":"Bolzano/Bozen",
    "sg:website":"http://www.rosenbauer.co.at",
    "wof:name":"Brandschutz Srl",
    "wof:placetype":"venue"
},
  "geometry": {"coordinates":[11.26434,46.460331],"type":"Point"}
}