{
  "type": "Feature",
  "properties": {
    "iso:country":"IT",
    "sg:address":"3, Via Pessino 21030 Casalzuigno",
    "sg:city":"Casalzuigno",
    "sg:classifiers":[
        {
            "category":"Wholesale",
            "subcategory":"Drugs",
            "type":"Manufacturing & Wholesale Goods"
        }
    ],
    "sg:phone":"+39 0332 650165",
    "sg:postcode":"21030",
    "sg:province":"Varese",
    "sg:tags":[
        "chemical",
        "pharmaceutical"
    ],
    "wof:name":"Chemicount Italiana Di De Rocchi L. & C. (s.n.c.)",
    "wof:placetype":"venue"
},
  "geometry": {"coordinates":[8.713941,45.904247],"type":"Point"}
}