{
  "type": "Feature",
  "properties": {
    "iso:country":"IT",
    "sg:address":"25080 Padenghe Sul Garda",
    "sg:city":"Padenghe sul Garda",
    "sg:orig_category":"Legno E Semilavorati. Materiali Edili",
    "sg:phone":"+39 030 990 7033",
    "sg:postcode":"25080",
    "sg:province":"Brescia",
    "wof:name":"Edilgarda Srl",
    "wof:placetype":"venue"
},
  "geometry": {"coordinates":[10.504643,45.503048],"type":"Point"}
}