{
  "type": "Feature",
  "properties": {
    "addr:full":"1, Via Delle Querce 47842 San Giovanni In Marignano San Giovanni in Marignano Rimini 47842",
    "addr:postcode":"47842;47842",
    "addr:street":"Via Delle Querce;Giovanni In Marignano",
    "iso:country":"IT",
    "sg:address":"1, Via Delle Querce 47842 San Giovanni In Marignano",
    "sg:city":"San Giovanni in Marignano",
    "sg:classifiers":[
        {
            "category":"Shopping",
            "subcategory":"Clothing, Apparel, & Fashions",
            "type":"Retail Goods"
        }
    ],
    "sg:phone":"+39 0541 965211",
    "sg:postcode":"47842",
    "sg:province":"Rimini",
    "sg:tags":[
        "clothes"
    ],
    "wof:name":"Aeffe (s.p.a.)",
    "wof:placetype":"venue"
},
  "geometry": {"coordinates":[12.566257,44.06078],"type":"Point"}
}