{
  "type": "Feature",
  "properties": {
    "addr:full":"00198 Roma Roma Roma 00198",
    "addr:postcode":"00198;00198",
    "iso:country":"IT",
    "sg:address":"00198 Roma",
    "sg:city":"Roma",
    "sg:orig_category":"Ricambi E Componenti Dei Mezzi Di Trasporto",
    "sg:phone":"+39 06 8535 3793",
    "sg:postcode":"00198",
    "sg:province":"Roma",
    "wof:name":"Carburatori Sub Agenzia Weber",
    "wof:placetype":"venue"
},
  "geometry": {"coordinates":[12.492148,41.911823],"type":"Point"}
}