{
  "type": "Feature",
  "properties": {
    "addr:full":"20010 Bareggio Bareggio Milano 20010",
    "addr:postcode":"20010;20010",
    "iso:country":"IT",
    "sg:address":"20010 Bareggio",
    "sg:city":"Bareggio",
    "sg:orig_category":"Professionisti - Studi E Servizi Ed Associazioni Di Interesse Aziendale. Associazioni Ed Organismi Di Interesse Pubblico",
    "sg:phone":"+39 02 9036 2355",
    "sg:postcode":"20010",
    "sg:province":"Milano",
    "wof:name":"P.d.s. Partito Democratico Della Sinistra",
    "wof:placetype":"venue"
},
  "geometry": {"coordinates":[9.0245399475,45.5016593933],"type":"Point"}
}