{
  "type": "Feature",
  "properties": {
    "iso:country":"IT",
    "sg:address":"10123 Torino",
    "sg:city":"Torino",
    "sg:orig_category":"Agenzie D'affari E Servizi Commerciali. Servizi Per Aziende, Manifestazioni E Supporto Agli Scambi Commerciali. Acqua, Luce, Gas E Societa' Di Esercizio Pubblico",
    "sg:phone":"+39 011 57161",
    "sg:postcode":"10123",
    "sg:province":"Torino",
    "sg:website":"http://www.to.camcom.it",
    "wof:name":"Camera Di Commercio Industria Artigianato Agricoltura Di Torino",
    "wof:placetype":"venue"
},
  "geometry": {"coordinates":[7.578641,45.021935],"type":"Point"}
}