{
  "type": "Feature",
  "properties": {
    "iso:country":"IT",
    "sg:address":"16129 Genova",
    "sg:city":"Genova",
    "sg:orig_category":"Abbigliamento Intimo, Calze E Costumi Da Bagno",
    "sg:phone":"+39 010 314841",
    "sg:postcode":"16129",
    "sg:province":"Genova",
    "wof:name":"C.e.d.e.c.",
    "wof:placetype":"venue"
},
  "geometry": {"coordinates":[8.95357,44.403305],"type":"Point"}
}