{
  "type": "Feature",
  "properties": {
    "iso:country":"IT",
    "sg:address":"64021 Giulianova",
    "sg:city":"Giulianova",
    "sg:orig_category":"Agenzie Immobiliari",
    "sg:phone":"+39 085 800 4426",
    "sg:postcode":"64021",
    "sg:province":"Teramo",
    "wof:name":"Studio Valentini Professional Services Euro Immobiliare",
    "wof:placetype":"venue"
},
  "geometry": {"coordinates":[13.963575,42.751778],"type":"Point"}
}