{
  "type": "Feature",
  "properties": {
    "iso:country":"IT",
    "sg:address":"336, Via Tortona 47023 Cesena",
    "sg:city":"Cesena",
    "sg:classifiers":[
        {
            "category":"Parking",
            "subcategory":"Lot",
            "type":"Transportation"
        }
    ],
    "sg:phone":"+39 0547 318082",
    "sg:postcode":"47023",
    "sg:province":"Forl\u00ec-Cesena",
    "sg:tags":[
        "transport",
        "road"
    ],
    "wof:name":"Nisi Autotrasporti Di Nisi Antonio E Terzo S.n.c.",
    "wof:placetype":"venue"
},
  "geometry": {"coordinates":[12.211816,44.188454],"type":"Point"}
}