{
  "type": "Feature",
  "properties": {
    "addr:full":"10095 Grugliasco Grugliasco Torino 10095",
    "addr:postcode":"10095;10095",
    "iso:country":"IT",
    "sg:address":"10095 Grugliasco",
    "sg:city":"Grugliasco",
    "sg:orig_category":"Agende, Calendari E Rubriche",
    "sg:phone":"+39 011 783380",
    "sg:postcode":"10095",
    "sg:province":"Torino",
    "wof:name":"Mangano Cataldo",
    "wof:placetype":"venue"
},
  "geometry": {"coordinates":[7.586734,45.045383],"type":"Point"}
}