{
  "type": "Feature",
  "properties": {
    "iso:country":"IT",
    "sg:address":"00169 Roma",
    "sg:city":"Roma",
    "sg:orig_category":"Abbigliamento Esterno, Maglierie E Pelliccerie",
    "sg:phone":"+39 06 261252",
    "sg:postcode":"00169",
    "sg:province":"Roma",
    "wof:name":"3p Di Puccio Salvatore & Figli Snc",
    "wof:placetype":"venue"
},
  "geometry": {"coordinates":[12.591242,41.870907],"type":"Point"}
}