{
  "type": "Feature",
  "properties": {
    "iso:country":"IT",
    "sg:address":"80144 Napoli",
    "sg:city":"Napoli",
    "sg:orig_category":"Arredo Camera Letto E Complementi",
    "sg:phone":"+39 081 736 8332",
    "sg:postcode":"80144",
    "sg:province":"Napoli",
    "wof:name":"Esposito Guido",
    "wof:placetype":"venue"
},
  "geometry": {"coordinates":[14.280296,40.883812],"type":"Point"}
}