{
  "type": "Feature",
  "properties": {
    "iso:country":"IT",
    "sg:address":"Via Jervis 77, Ivrea, To",
    "sg:classifiers":[
        {
            "category":"Banks & Credit Unions",
            "subcategory":"Bank",
            "type":"Services"
        }
    ],
    "wof:name":"Tecnost Spa",
    "wof:placetype":"venue"
},
  "geometry": {"coordinates":[7.868227,45.456642],"type":"Point"}
}