{
  "type": "Feature",
  "properties": {
    "addr:full":"95041 Caltagirone Caltagirone Catania 95041",
    "addr:postcode":"95041;95041",
    "iso:country":"IT",
    "sg:address":"95041 Caltagirone",
    "sg:city":"Caltagirone",
    "sg:orig_category":"Prodotti Chimici Secondari",
    "sg:phone":"+39 0933 31760",
    "sg:postcode":"95041",
    "sg:province":"Catania",
    "wof:name":"Massarotti Giulio",
    "wof:placetype":"venue"
},
  "geometry": {"coordinates":[14.5084571838,37.2370300293],"type":"Point"}
}