{
  "type": "Feature",
  "properties": {
    "iso:country":"IT",
    "sg:address":"50127 Firenze",
    "sg:city":"Firenze",
    "sg:orig_category":"Macchine E Forniture Per Ecologia E Smaltimento Rifiuti. Elettrodomestici. Forniture Alle Strutture Ricettive. Macchine, Strumenti Ed Apparecchi Per Attivita' Industriali",
    "sg:phone":"+39 055 437 7687",
    "sg:postcode":"50127",
    "sg:province":"Firenze",
    "sg:website":"http://www.cilmas.com",
    "wof:name":"Cilmas Centro Sud Srl - Mirage",
    "wof:placetype":"venue"
},
  "geometry": {"coordinates":[10.747925,43.67762],"type":"Point"}
}