{
  "type": "Feature",
  "properties": {
    "addr:full":"50033 Firenzuola Firenzuola Firenze 50033",
    "addr:postcode":"50033;50033",
    "iso:country":"IT",
    "sg:address":"50033 Firenzuola",
    "sg:city":"Firenzuola",
    "sg:orig_category":"Trasporti E Spedizioni Merci",
    "sg:phone":"+39 055 814 4010",
    "sg:postcode":"50033",
    "sg:province":"Firenze",
    "wof:name":"Consorzio Alta Velocita' Emilia Toscana",
    "wof:placetype":"venue"
},
  "geometry": {"coordinates":[11.365801,44.152103],"type":"Point"}
}