{
  "type": "Feature",
  "properties": {
    "addr:full":"50134 Firenze Firenze Firenze 50134",
    "addr:postcode":"50134;50134",
    "iso:country":"IT",
    "sg:address":"50134 Firenze",
    "sg:city":"Firenze",
    "sg:orig_category":"Persiane Ed Avvolgibili",
    "sg:phone":"+39 055 419447",
    "sg:postcode":"50134",
    "sg:province":"Firenze",
    "sg:website":"http://www.serramentidiscount.com",
    "wof:name":"Serramenti Discount Di Marcelletti Francesco",
    "wof:placetype":"venue"
},
  "geometry": {"coordinates":[11.2452945709,43.7910728455],"type":"Point"}
}