{
  "type": "Feature",
  "properties": {
    "iso:country":"IT",
    "sg:address":"58019 Monte Argentario",
    "sg:city":"Monte Argentario",
    "sg:orig_category":"Nautica. Automobili E Mezzi Di Trasporto",
    "sg:phone":"+39 0564 813685",
    "sg:postcode":"58019",
    "sg:province":"Grosseto",
    "wof:name":"Lunghi Vezio",
    "wof:placetype":"venue"
},
  "geometry": {"coordinates":[11.121688,42.432335],"type":"Point"}
}