{
  "type": "Feature",
  "properties": {
    "addr:full":"7, Viale Europa 37045 Legnago Legnago Verona 37045",
    "addr:postcode":"37045;37045",
    "addr:street":"Viale Europa",
    "iso:country":"IT",
    "sg:address":"7, Viale Europa 37045 Legnago",
    "sg:city":"Legnago",
    "sg:classifiers":[
        {
            "category":"Shopping",
            "subcategory":"Computers & Home Electronics",
            "type":"Retail Goods"
        }
    ],
    "sg:phone":"+39 0442 635811",
    "sg:postcode":"37045",
    "sg:province":"Verona",
    "sg:tags":[
        "electronic",
        "electrical",
        "equipment"
    ],
    "wof:name":"Ups Manufacturing S.r.l.",
    "wof:placetype":"venue"
},
  "geometry": {"coordinates":[11.265868,45.185188],"type":"Point"}
}