{
  "type": "Feature",
  "properties": {
    "addr:full":"13100 Prarolo Vercelli 13100",
    "addr:housenumber":"13100",
    "addr:postcode":"13100",
    "iso:country":"IT",
    "sg:address":"13100 Prarolo",
    "sg:orig_category":"Nettezza Urbana - Servizio",
    "sg:phone":"+39 0161 301095",
    "sg:postcode":"13100",
    "sg:province":"Vercelli",
    "wof:name":"S.p.a.i.c. Sas",
    "wof:placetype":"venue"
},
  "geometry": {"coordinates":[8.477667,45.28096],"type":"Point"}
}