{
  "type": "Feature",
  "properties": {
    "addr:full":"135, Viale Gramsci Antonio 20099 Sesto San Giovanni Sesto San Giovanni Milano 20099",
    "addr:postcode":"20099;20099",
    "addr:street":"Viale Gramsci Antonio",
    "iso:country":"IT",
    "sg:address":"135, Viale Gramsci Antonio 20099 Sesto San Giovanni",
    "sg:city":"Sesto San Giovanni",
    "sg:classifiers":[
        {
            "category":"Banks & Credit Unions",
            "subcategory":"Financial Services",
            "type":"Services"
        }
    ],
    "sg:phone":"+39 39022421317",
    "sg:postcode":"20099",
    "sg:province":"Milano",
    "sg:tags":[
        "banking",
        "finance",
        "insurance"
    ],
    "wof:name":"Consulgest (s.r.l.)",
    "wof:placetype":"venue"
},
  "geometry": {"coordinates":[9.23477,45.537983],"type":"Point"}
}