{
  "type": "Feature",
  "properties": {
    "iso:country":"IT",
    "sg:address":"1, Contrada Paparanza 94019 Valguarnera Caropepe",
    "sg:city":"Valguarnera Caropepe",
    "sg:classifiers":[
        {
            "category":"Shopping",
            "subcategory":"Clothing, Apparel, & Fashions",
            "type":"Retail Goods"
        }
    ],
    "sg:phone":"+39 0935 958800",
    "sg:postcode":"94019",
    "sg:province":"Enna",
    "sg:tags":[
        "clothes"
    ],
    "wof:name":"Dalcos Srl",
    "wof:placetype":"venue"
},
  "geometry": {"coordinates":[14.279706,37.567596],"type":"Point"}
}