{
  "type": "Feature",
  "properties": {
    "iso:country":"IT",
    "sg:address":"00153 Roma",
    "sg:city":"Roma",
    "sg:orig_category":"Impiantistica E Prodotti Tecnologici Per Edilizia",
    "sg:phone":"+39 06 5833 3491",
    "sg:postcode":"00153",
    "sg:province":"Roma",
    "sg:website":"http://www.eltionline.it",
    "wof:name":"E.l.t.i. Srl",
    "wof:placetype":"venue"
},
  "geometry": {"coordinates":[12.468177,41.879585],"type":"Point"}
}