{
  "type": "Feature",
  "properties": {
    "addr:full":"95041 Caltagirone Caltagirone Catania 95041",
    "addr:postcode":"95041;95041",
    "iso:country":"IT",
    "sg:address":"95041 Caltagirone",
    "sg:city":"Caltagirone",
    "sg:orig_category":"Impianti, Attrezzature E Forniture Sanitarie Ed Ospedaliere",
    "sg:phone":"+39 0933 25689",
    "sg:postcode":"95041",
    "sg:province":"Catania",
    "wof:name":"Dynamic Dental Di Monteleone F. & Marchese S. Snc",
    "wof:placetype":"venue"
},
  "geometry": {"coordinates":[14.565707,37.249165],"type":"Point"}
}