{
  "type": "Feature",
  "properties": {
    "iso:country":"IT",
    "sg:address":"116, Via Trani 70051 Barletta",
    "sg:city":"Barletta",
    "sg:classifiers":[
        {
            "category":"Manufacturing",
            "subcategory":"Metals",
            "type":"Manufacturing & Wholesale Goods"
        }
    ],
    "sg:phone":"+39 0883 533298",
    "sg:postcode":"70051",
    "sg:province":"Bari",
    "sg:tags":[
        "metallurgy",
        "metalworking"
    ],
    "wof:name":"Smal Di Losappio A. & C. Sas",
    "wof:placetype":"venue"
},
  "geometry": {"coordinates":[16.316192627,41.306427002],"type":"Point"}
}