{
  "type": "Feature",
  "properties": {
    "iso:country":"IT",
    "sg:address":"20123 Milano",
    "sg:city":"Milano",
    "sg:orig_category":"Servizi Per Aziende, Manifestazioni E Supporto Agli Scambi Commerciali",
    "sg:phone":"+39 02 481 8431",
    "sg:postcode":"20123",
    "sg:province":"Milano",
    "sg:website":"http://www.stelline.it",
    "wof:name":"Stelline Servizi Congressuali Srl",
    "wof:placetype":"venue"
},
  "geometry": {"coordinates":[9.17209,45.465687],"type":"Point"}
}