{
  "type": "Feature",
  "properties": {
    "addr:full":"Via Piemonte ,19/21 20030 Senago Senago Milano 20030",
    "addr:housenumber":"19 / 21",
    "addr:postcode":"20030;20030",
    "addr:street":"Via Piemonte",
    "iso:country":"IT",
    "sg:address":"Via Piemonte ,19/21 20030 Senago",
    "sg:city":"Senago",
    "sg:classifiers":[
        {
            "category":"Professional",
            "subcategory":"Engineering",
            "type":"Services"
        }
    ],
    "sg:phone":"+39 02 9901 0754",
    "sg:postcode":"20030",
    "sg:province":"Milano",
    "sg:tags":[
        "aeronautical",
        "aerospace"
    ],
    "wof:name":"F.i.m.a.c. Spa",
    "wof:placetype":"venue"
},
  "geometry": {"coordinates":[9.138332,45.555084],"type":"Point"}
}