{
  "type": "Feature",
  "properties": {
    "iso:country":"IT",
    "sg:address":"6, Via Signorini 52010 Subbiano",
    "sg:city":"Subbiano",
    "sg:classifiers":[
        {
            "category":"Personal",
            "subcategory":"Shoe Repair & Shine",
            "type":"Services"
        }
    ],
    "sg:phone":"+39 0575 489837",
    "sg:postcode":"52010",
    "sg:province":"Arezzo",
    "sg:tags":[
        "leather"
    ],
    "wof:name":"Calzaturificio Marco",
    "wof:placetype":"venue"
},
  "geometry": {"coordinates":[11.87162,43.583282],"type":"Point"}
}