{
  "type": "Feature",
  "properties": {
    "addr:full":"150, Via Brandizzo 10088 Volpiano Volpiano Torino 10088",
    "addr:housenumber":"150",
    "addr:postcode":"10088;10088",
    "addr:street":"Via Brandizzo",
    "iso:country":"IT",
    "sg:address":"150, Via Brandizzo 10088 Volpiano",
    "sg:city":"Volpiano",
    "sg:classifiers":[
        {
            "category":"Professional",
            "subcategory":"Engineering",
            "type":"Services"
        }
    ],
    "sg:phone":"+39 011 995 2099",
    "sg:postcode":"10088",
    "sg:province":"Torino",
    "sg:tags":[
        "machine",
        "-",
        "mechanical"
    ],
    "wof:name":"Lindab S.r.l.",
    "wof:placetype":"venue"
},
  "geometry": {"coordinates":[7.813622,45.174004],"type":"Point"}
}