{
  "type": "Feature",
  "properties": {
    "iso:country":"IT",
    "sg:address":"106, Via Montello 31053 Pieve Di Soligo",
    "sg:city":"Pieve di Soligo",
    "sg:classifiers":[
        {
            "category":"Home & Garden",
            "subcategory":"Home Furnishings",
            "type":"Retail Goods"
        }
    ],
    "sg:phone":"+39 0438 984511",
    "sg:postcode":"31053",
    "sg:province":"Treviso",
    "sg:tags":[
        "household"
    ],
    "wof:name":"Mobilificio S.michele S.r.l.",
    "wof:placetype":"venue"
},
  "geometry": {"coordinates":[12.170128,45.887718],"type":"Point"}
}