{
  "type": "Feature",
  "properties": {
    "addr:full":"Via Dell' Artigianato 06089 Torgiano Torgiano Perugia 06089",
    "addr:postcode":"06089;06089",
    "addr:street":"Via Dell ' Artigianato",
    "iso:country":"IT",
    "sg:address":"Via Dell' Artigianato 06089 Torgiano",
    "sg:city":"Torgiano",
    "sg:classifiers":[
        {
            "category":"Real Estate",
            "subcategory":"Architect",
            "type":"Services"
        }
    ],
    "sg:phone":"+39 39075982795",
    "sg:postcode":"06089",
    "sg:province":"Perugia",
    "sg:tags":[
        "textile",
        "clothing"
    ],
    "wof:name":"Ima S.r.l.",
    "wof:placetype":"venue"
},
  "geometry": {"coordinates":[12.413292,42.98143],"type":"Point"}
}