{
  "type": "Feature",
  "properties": {
    "iso:country":"IT",
    "sg:address":"20121 Milano",
    "sg:city":"Milano",
    "sg:orig_category":"Tessuti E Stoffe. Tessuti Arredamento, Tende E Tappeti",
    "sg:phone":"+39 02 657 5418",
    "sg:postcode":"20121",
    "sg:province":"Milano",
    "wof:name":"Li.mi. Srl - Lisio Tessuti D'arte",
    "wof:placetype":"venue"
},
  "geometry": {"coordinates":[9.193955,45.471287],"type":"Point"}
}