{
  "type": "Feature",
  "properties": {
    "iso:country":"IT",
    "sg:address":"34170 Gorizia",
    "sg:city":"Gorizia",
    "sg:orig_category":"Apparecchiature E Sistemi Per Magazzinaggio E Movimentazione",
    "sg:phone":"+39 0481 529111",
    "sg:postcode":"34170",
    "sg:province":"Gorizia",
    "wof:name":"Mattia Winkler Srl",
    "wof:placetype":"venue"
},
  "geometry": {"coordinates":[13.599144,45.943825],"type":"Point"}
}