{
  "type": "Feature",
  "properties": {
    "iso:country":"IT",
    "sg:address":"2, Viale Dell' Artigianato 35020 Candiana",
    "sg:city":"Candiana",
    "sg:classifiers":[
        {
            "category":"Home & Garden",
            "subcategory":"Home Furnishings",
            "type":"Retail Goods"
        }
    ],
    "sg:phone":"+39 049 534 9987",
    "sg:postcode":"35020",
    "sg:province":"Padova",
    "sg:tags":[
        "household"
    ],
    "wof:name":"Bica (s.p.a.)",
    "wof:placetype":"venue"
},
  "geometry": {"coordinates":[11.973275,45.21006],"type":"Point"}
}