{
  "type": "Feature",
  "properties": {
    "addr:full":"Via Ponte Lamato 60037 Monte San Vito Monte San Vito Ancona 60037",
    "addr:postcode":"60037;60037",
    "addr:street":"Via Ponte Lamato",
    "iso:country":"IT",
    "sg:address":"Via Ponte Lamato 60037 Monte San Vito",
    "sg:city":"Monte San Vito",
    "sg:classifiers":[
        {
            "category":"Food & Beverages",
            "subcategory":"Groceries & Convenience Stores",
            "type":"Retail Goods"
        }
    ],
    "sg:phone":"+39 071 748 9031",
    "sg:postcode":"60037",
    "sg:province":"Ancona",
    "sg:tags":[
        "product",
        "related"
    ],
    "wof:name":"Salumificio Vito (s.r.l.)",
    "wof:placetype":"venue"
},
  "geometry": {"coordinates":[13.2807445526,43.5916442871],"type":"Point"}
}