{
  "type": "Feature",
  "properties": {
    "iso:country":"IT",
    "sg:address":"51000 Bologna",
    "sg:orig_category":"Servizi Vari Di Interesse Pubblico",
    "sg:phone":"+39 347 931 5755",
    "sg:province":"BO",
    "wof:name":"Mark Centro Studi Astrologici",
    "wof:placetype":"venue"
},
  "geometry": {"coordinates":[11.34516,44.504822],"type":"Point"}
}