{
  "type": "Feature",
  "properties": {
    "addr:full":"25, Strada S. Eusebio 10080 Feletto Feletto Torino 10080",
    "addr:postcode":"10080;10080",
    "addr:street":"Strada S. Eusebio",
    "iso:country":"IT",
    "sg:address":"25, Strada S. Eusebio 10080 Feletto",
    "sg:city":"Feletto",
    "sg:classifiers":[
        {
            "category":"Manufacturing",
            "subcategory":"Textiles",
            "type":"Manufacturing & Wholesale Goods"
        }
    ],
    "sg:phone":"+39 0124 490588",
    "sg:postcode":"10080",
    "sg:province":"Torino",
    "sg:tags":[
        "leather",
        "raw",
        "material",
        "-"
    ],
    "wof:name":"Fer - Co (s.r.l.)",
    "wof:placetype":"venue"
},
  "geometry": {"coordinates":[7.686619,45.07056],"type":"Point"}
}