{
  "type": "Feature",
  "properties": {
    "addr:full":"00186 Roma Roma Roma 00186",
    "addr:postcode":"00186;00186",
    "iso:country":"IT",
    "sg:address":"00186 Roma",
    "sg:city":"Roma",
    "sg:orig_category":"Audiovisivi Filmati, Spot E Multimediali - Realizzazione E Duplicazione",
    "sg:phone":"+39 06 683941",
    "sg:postcode":"00186",
    "sg:province":"Roma",
    "sg:website":"http://www.luxvide.it",
    "wof:name":"Lux Vide Spa Finanziaria Per Iniziative Audiovisive E Telematiche",
    "wof:placetype":"venue"
},
  "geometry": {"coordinates":[12.475321,41.896603],"type":"Point"}
}