{
  "type": "Feature",
  "properties": {
    "iso:country":"IT",
    "sg:address":"20121 Milano",
    "sg:city":"Milano",
    "sg:orig_category":"Ortopedia - Articoli",
    "sg:phone":"+39 02 2900 2750",
    "sg:postcode":"20121",
    "sg:province":"Milano",
    "wof:name":"Ortopedia Porta Nuova Di Antonio Arena",
    "wof:placetype":"venue"
},
  "geometry": {"coordinates":[9.194981,45.472153],"type":"Point"}
}