{
  "type": "Feature",
  "properties": {
    "addr:full":"36, Via Menalca 00155 Roma Roma Roma 00155",
    "addr:postcode":"00155;00155",
    "addr:street":"Via Menalca",
    "iso:country":"IT",
    "sg:address":"36, Via Menalca 00155 Roma",
    "sg:city":"Roma",
    "sg:classifiers":[
        {
            "category":"Professional",
            "subcategory":"Printing & Photocopies",
            "type":"Services"
        }
    ],
    "sg:phone":"+39 39062296191",
    "sg:postcode":"00155",
    "sg:province":"Roma",
    "wof:name":"Graphic Make Print Srl",
    "wof:placetype":"venue"
},
  "geometry": {"coordinates":[12.5834321976,41.9283676147],"type":"Point"}
}