{
  "type": "Feature",
  "properties": {
    "iso:country":"IT",
    "sg:address":"24122 Bergamo",
    "sg:city":"Bergamo",
    "sg:orig_category":"Macchine E Forniture Per Industria Orafa E Per Orologeria",
    "sg:phone":"+39 035 218242",
    "sg:postcode":"24122",
    "sg:province":"Bergamo",
    "wof:name":"Angioletti Cesare (s.r.l.)",
    "wof:placetype":"venue"
},
  "geometry": {"coordinates":[9.664847,45.692387],"type":"Point"}
}