{
  "type": "Feature",
  "properties": {
    "iso:country":"IT",
    "sg:address":"55041 Camaiore",
    "sg:city":"Camaiore",
    "sg:orig_category":"Arredo Cucina Ed Elettrodomestici. Elettrodomestici",
    "sg:phone":"+39 0584 969471",
    "sg:postcode":"55041",
    "sg:province":"Lucca",
    "wof:name":"Bird Sing Srl",
    "wof:placetype":"venue"
},
  "geometry": {"coordinates":[10.2623,43.905895],"type":"Point"}
}