{
  "type": "Feature",
  "properties": {
    "iso:country":"IT",
    "sg:address":"20060 Pessano Con Bornago",
    "sg:city":"Ornago",
    "sg:orig_category":"Assemblaggio Conto Terzi",
    "sg:phone":"+39 02 9574 5370",
    "sg:postcode":"20060",
    "sg:province":"Milano",
    "sg:website":"http://www.mcpacking.com",
    "wof:name":"M.c. Packing Srl",
    "wof:placetype":"venue"
},
  "geometry": {"coordinates":[9.386971,45.551506],"type":"Point"}
}