{
  "type": "Feature",
  "properties": {
    "addr:full":"71100 Foggia Foggia Foggia 71100",
    "addr:postcode":"71100;71100",
    "iso:country":"IT",
    "sg:address":"71100 Foggia",
    "sg:city":"Foggia",
    "sg:orig_category":"Ricambi E Componenti Dei Mezzi Di Trasporto",
    "sg:phone":"+39 0881 568667",
    "sg:postcode":"71100",
    "sg:province":"Foggia",
    "sg:website":"http://www.marchetti.isnet.it",
    "wof:name":"Meccanica Marchetti Snc",
    "wof:placetype":"venue"
},
  "geometry": {"coordinates":[15.547438,41.449795],"type":"Point"}
}