{
  "type": "Feature",
  "properties": {
    "iso:country":"IT",
    "sg:address":"Via Bergognone 27; Milano; 20144",
    "sg:city":"Milano",
    "sg:classifiers":[
        {
            "category":"Banks & Credit Unions",
            "subcategory":"Bank",
            "type":"Services"
        }
    ],
    "sg:phone":"+39 02 5810 7132",
    "sg:postcode":"20144",
    "sg:province":"Milano",
    "wof:name":"Banca Sella Spa",
    "wof:placetype":"venue"
},
  "geometry": {"coordinates":[9.163307,45.454525],"type":"Point"}
}