{
  "type": "Feature",
  "properties": {
    "iso:country":"IT",
    "sg:address":"24030 Brancilione",
    "sg:orig_category":"Servizi E Lavori Per Arredamento E Industria Del Legno",
    "sg:phone":"+39 035 851027",
    "sg:postcode":"24030",
    "sg:province":"Bergamo",
    "wof:name":"Belotti Giovanni",
    "wof:placetype":"venue"
},
  "geometry": {"coordinates":[9.534645,45.826786],"type":"Point"}
}