{
  "type": "Feature",
  "properties": {
    "iso:country":"IT",
    "sg:address":"29, Via Roma 50063 Figline Valdarno",
    "sg:city":"Figline Valdarno",
    "sg:classifiers":[
        {
            "category":"Shopping",
            "subcategory":"Clothing, Apparel, & Fashions",
            "type":"Retail Goods"
        }
    ],
    "sg:phone":"+39 39055953253",
    "sg:postcode":"50063",
    "sg:province":"Firenze",
    "sg:tags":[
        "clothes"
    ],
    "wof:name":"B.n.g. Confezioni (s.r.l.)",
    "wof:placetype":"venue"
},
  "geometry": {"coordinates":[11.470633,43.622025],"type":"Point"}
}