{
  "type": "Feature",
  "properties": {
    "iso:country":"IT",
    "sg:address":"60127 Ancona",
    "sg:city":"Ancona",
    "sg:orig_category":"Servizi Ausiliari Di Sorveglianza, Manutenzione E Pulizia",
    "sg:phone":"+39 071 280 1111",
    "sg:postcode":"60127",
    "sg:province":"Ancona",
    "sg:website":"http://www.",
    "wof:name":"Metronotte Srl",
    "wof:placetype":"venue"
},
  "geometry": {"coordinates":[13.505871,43.593262],"type":"Point"}
}