{
  "type": "Feature",
  "properties": {
    "addr:full":"Piazza Xx Settembre 20; Sarnico; 24067 Sarnico Bergamo 24067",
    "addr:housenumber":"20",
    "addr:postcode":"24067;24067",
    "addr:street":"Piazza Xx Settembre",
    "iso:country":"IT",
    "sg:address":"Piazza Xx Settembre 20; Sarnico; 24067",
    "sg:city":"Sarnico",
    "sg:classifiers":[
        {
            "category":"Banks & Credit Unions",
            "subcategory":"Bank",
            "type":"Services"
        }
    ],
    "sg:phone":"+39 035 910150",
    "sg:postcode":"24067",
    "sg:province":"Bergamo",
    "wof:name":"Banca Popolare Di Bergamo",
    "wof:placetype":"venue"
},
  "geometry": {"coordinates":[9.96854,45.670834],"type":"Point"}
}