{
  "type": "Feature",
  "properties": {
    "addr:full":"Viale Ariosto 2-ang.; Carpi; 41012 Carpi Modena 41012",
    "addr:housenumber":"2-ang",
    "addr:postcode":"41012;41012",
    "addr:street":"Viale Ariosto",
    "iso:country":"IT",
    "sg:address":"Viale Ariosto 2-ang.; Carpi; 41012",
    "sg:city":"Carpi",
    "sg:classifiers":[
        {
            "category":"Banks & Credit Unions",
            "subcategory":"Bank",
            "type":"Services"
        }
    ],
    "sg:phone":"+39 059 651191",
    "sg:postcode":"41012",
    "sg:province":"Modena",
    "wof:name":"Credito Italiano Spa",
    "wof:placetype":"venue"
},
  "geometry": {"coordinates":[10.863265,44.837715],"type":"Point"}
}