{
  "type": "Feature",
  "properties": {
    "addr:full":"37050 San Pietro Di Morubio Bonavicina Verona 37050",
    "addr:housenumber":"37050",
    "addr:postcode":"37050",
    "addr:street":"San Pietro Di Morubio Bonavicina",
    "iso:country":"IT",
    "sg:address":"37050 San Pietro Di Morubio",
    "sg:city":"Bonavicina",
    "sg:orig_category":"Zootecnia E Pesca, Allevamento Piccoli Animali",
    "sg:phone":"+39 045 712 5079",
    "sg:postcode":"37050",
    "sg:province":"Verona",
    "wof:name":"Moretto Oreste",
    "wof:placetype":"venue"
},
  "geometry": {"coordinates":[11.199388,45.231731],"type":"Point"}
}