{
  "type": "Feature",
  "properties": {
    "iso:country":"IT",
    "sg:address":"73044 Galatone",
    "sg:city":"Galatone",
    "sg:orig_category":"Forniture Per Edilizia E Lavori Pubblici. Forniture Industriali Per Prevenzione, Controllo E Sicurezza",
    "sg:phone":"+39 0833 832252",
    "sg:postcode":"73044",
    "sg:province":"Lecce",
    "sg:website":"http://www.nuovafise.it",
    "wof:name":"Nuova Fise Srl",
    "wof:placetype":"venue"
},
  "geometry": {"coordinates":[18.0598659515,40.1391601562],"type":"Point"}
}