{
  "type": "Feature",
  "properties": {
    "addr:full":"Piazza Tre Martiri 11; Pontenure",
    "addr:housenumber":"11",
    "addr:street":"Piazza Tre Martiri",
    "iso:country":"IT",
    "sg:address":"Piazza Tre Martiri 11; Pontenure",
    "sg:classifiers":[
        {
            "category":"Banks & Credit Unions",
            "subcategory":"Bank",
            "type":"Services"
        }
    ],
    "sg:phone":"+39 0523 519941",
    "wof:name":"Cassa Di Risparmio Di Parma, E Piacenza Spa",
    "wof:placetype":"venue"
},
  "geometry": {"coordinates":[9.788608,44.99955],"type":"Point"}
}