{
  "type": "Feature",
  "properties": {
    "addr:full":"31032 Casale Sul Sile Casale sul Sile Treviso 31032",
    "addr:postcode":"31032;31032",
    "iso:country":"IT",
    "sg:address":"31032 Casale Sul Sile",
    "sg:city":"Casale sul Sile",
    "sg:orig_category":"Frigotecnica, Apparecchiature E Servizi. Servizi Di Magazzinaggio E Movimentazione",
    "sg:phone":"+39 0422 788850",
    "sg:postcode":"31032",
    "sg:province":"Treviso",
    "wof:name":"Nobile Silvano & C. S.n.c.",
    "wof:placetype":"venue"
},
  "geometry": {"coordinates":[12.3275899887,45.6060066223],"type":"Point"}
}