{
  "type": "Feature",
  "properties": {
    "iso:country":"IT",
    "sg:address":"17025 Loano",
    "sg:city":"Loano",
    "sg:orig_category":"Carni, Salumi E Pesci",
    "sg:phone":"+39 019 667537",
    "sg:postcode":"17025",
    "sg:province":"Savona",
    "wof:name":"Macelleria Equina",
    "wof:placetype":"venue"
},
  "geometry": {"coordinates":[8.226767,44.154976],"type":"Point"}
}