{
  "type": "Feature",
  "properties": {
    "iso:country":"IT",
    "sg:address":"20149 Milano",
    "sg:city":"Milano",
    "sg:orig_category":"Tempo Libero - Articoli E Forniture. Regalistica Aziendale",
    "sg:phone":"+39 02 436093",
    "sg:postcode":"20149",
    "sg:province":"Milano",
    "wof:name":"Rizzi Eugenio",
    "wof:placetype":"venue"
},
  "geometry": {"coordinates":[9.147885,45.473473],"type":"Point"}
}