{
  "type": "Feature",
  "properties": {
    "iso:country":"IT",
    "sg:address":"4, Via Dell' Industria 40064 Ozzano Dell'emilia",
    "sg:classifiers":[
        {
            "category":"Manufacturing",
            "subcategory":"Rubber & Plastics",
            "type":"Manufacturing & Wholesale Goods"
        }
    ],
    "sg:phone":"+39 39051798059",
    "sg:postcode":"40064",
    "sg:province":"Bologna",
    "wof:name":"Faraoni",
    "wof:placetype":"venue"
},
  "geometry": {"coordinates":[11.4258422852,44.4625930786],"type":"Point"}
}