{
  "type": "Feature",
  "properties": {
    "iso:country":"IT",
    "sg:address":"47020 Longiano",
    "sg:city":"Longiano",
    "sg:orig_category":"Prodotti Alimentari",
    "sg:phone":"+39 0547 651811",
    "sg:postcode":"47020",
    "sg:province":"Forl\u00ec-Cesena",
    "wof:name":"Capor Soc.coop.r.l.",
    "wof:placetype":"venue"
},
  "geometry": {"coordinates":[12.3104658127,44.1127243042],"type":"Point"}
}