{
  "type": "Feature",
  "properties": {
    "addr:full":"21047 Saronno Saronno Varese 21047",
    "addr:postcode":"21047;21047",
    "iso:country":"IT",
    "sg:address":"21047 Saronno",
    "sg:city":"Saronno",
    "sg:orig_category":"Pubblica Amministrazione",
    "sg:phone":"+39 02 9624 8016",
    "sg:postcode":"21047",
    "sg:province":"Varese",
    "wof:name":"Saronno Servizi",
    "wof:placetype":"venue"
},
  "geometry": {"coordinates":[9.0320978165,45.6275520325],"type":"Point"}
}