{
  "type": "Feature",
  "properties": {
    "iso:country":"IT",
    "sg:address":"18, Via Del Lavoro 40010 Sala Bolognese",
    "sg:city":"Sala Bolognese",
    "sg:classifiers":[
        {
            "category":"Professional",
            "subcategory":"Engineering",
            "type":"Services"
        }
    ],
    "sg:phone":"+39 051 681 4566",
    "sg:postcode":"40010",
    "sg:province":"Bologna",
    "sg:tags":[
        "machine",
        "-",
        "mechanical"
    ],
    "wof:name":"Eurocolumbus (s.r.l.)",
    "wof:placetype":"venue"
},
  "geometry": {"coordinates":[11.248199,44.585239],"type":"Point"}
}