{
  "type": "Feature",
  "properties": {
    "iso:country":"IT",
    "sg:address":"29100 Piacenza",
    "sg:city":"Piacenza",
    "sg:orig_category":"Valvole E Apparecchiature Di Misura",
    "sg:phone":"+39 0523 615440",
    "sg:postcode":"29100",
    "sg:province":"Piacenza",
    "wof:name":"Carini Spa",
    "wof:placetype":"venue"
},
  "geometry": {"coordinates":[9.730492,45.030628],"type":"Point"}
}