{
  "type": "Feature",
  "properties": {
    "iso:country":"IT",
    "sg:address":"35020 Casalserugo",
    "sg:city":"Casalserugo",
    "sg:orig_category":"Macchine Utensili E Impianti",
    "sg:phone":"+39 049 874 1074",
    "sg:postcode":"35020",
    "sg:province":"Padova",
    "wof:name":"B.s.e. Di Biasia Silvano & C. Snc",
    "wof:placetype":"venue"
},
  "geometry": {"coordinates":[11.909361,45.318745],"type":"Point"}
}