{
  "type": "Feature",
  "properties": {
    "iso:country":"IT",
    "sg:address":"Piazza Del Popolo 34; Montalcino; 53024",
    "sg:city":"Montalcino",
    "sg:classifiers":[
        {
            "category":"Banks & Credit Unions",
            "subcategory":"Bank",
            "type":"Services"
        }
    ],
    "sg:phone":"+39 0577 848564",
    "sg:postcode":"53024",
    "sg:province":"Siena",
    "wof:name":"Banca Toscana Spa",
    "wof:placetype":"venue"
},
  "geometry": {"coordinates":[11.489865,43.058628],"type":"Point"}
}