{
  "type": "Feature",
  "properties": {
    "iso:country":"IT",
    "sg:address":"04011 Aprilia",
    "sg:city":"Aprilia",
    "sg:orig_category":"Ricambi E Componenti Dei Mezzi Di Trasporto",
    "sg:phone":"+39 06 928 8891",
    "sg:postcode":"04011",
    "sg:province":"Latina",
    "wof:name":"Radiatorista Pattaro Giuseppe",
    "wof:placetype":"venue"
},
  "geometry": {"coordinates":[12.531599,41.598339],"type":"Point"}
}