{
  "type": "Feature",
  "properties": {
    "iso:country":"IT",
    "sg:address":"00177 Roma",
    "sg:city":"Roma",
    "sg:orig_category":"Arredo Camera Letto E Complementi. Servizi E Lavori Per Arredamento E Industria Del Legno",
    "sg:phone":"+39 06 290274",
    "sg:postcode":"00177",
    "sg:province":"Roma",
    "wof:name":"Anticoli Marco & C S.a.s.",
    "wof:placetype":"venue"
},
  "geometry": {"coordinates":[12.884376,41.889793],"type":"Point"}
}