{
  "type": "Feature",
  "properties": {
    "iso:country":"IT",
    "sg:address":"2/c, V. Fontana Matuccia 01033 Civita Castellana",
    "sg:city":"Civita Castellana",
    "sg:classifiers":[
        {
            "category":"Professional",
            "subcategory":"Engineering",
            "type":"Services"
        }
    ],
    "sg:phone":"+39 0761 518228",
    "sg:postcode":"01033",
    "sg:province":"Viterbo",
    "sg:tags":[
        "machine",
        "-",
        "mechanical"
    ],
    "sg:website":"http://www.paginegialle.it/lflineaforni",
    "wof:name":"L.f. Linea Forni Per Ceramica Srl",
    "wof:placetype":"venue"
},
  "geometry": {"coordinates":[12.104854,42.417381],"type":"Point"}
}