{
  "type": "Feature",
  "properties": {
    "iso:country":"IT",
    "sg:address":"Via Provinciale Per Montesano 73039 Tricase",
    "sg:city":"Tricase",
    "sg:classifiers":[
        {
            "category":"Metro Station",
            "type":"Transportation"
        }
    ],
    "sg:phone":"+39 0833 543811",
    "sg:postcode":"73039",
    "sg:province":"Lecce",
    "sg:tags":[
        "ship",
        "boat",
        "special-purpose"
    ],
    "sg:website":"www.sogesta.it",
    "wof:name":"So.ge.sta. Di Giampiero Baviglio Sas",
    "wof:placetype":"venue"
},
  "geometry": {"coordinates":[18.336945,39.977905],"type":"Point"}
}