{
  "type": "Feature",
  "properties": {
    "iso:country":"IT",
    "sg:address":"95045 Misterbianco",
    "sg:city":"Misterbianco",
    "sg:orig_category":"Manufacturers: Prefabbricati",
    "sg:phone":"+39 095 420710",
    "sg:postcode":"95045",
    "sg:province":"Catania",
    "wof:name":"Zuppelli Alfio",
    "wof:placetype":"venue"
},
  "geometry": {"coordinates":[15.094043,37.506508],"type":"Point"}
}