{
  "type": "Feature",
  "properties": {
    "iso:country":"IT",
    "sg:address":"17, Via Reiss Romoli 20019 Settimo Milanese",
    "sg:city":"Settimo Milanese",
    "sg:classifiers":[
        {
            "category":"Manufacturing",
            "subcategory":"Metals",
            "type":"Manufacturing & Wholesale Goods"
        }
    ],
    "sg:phone":"+39 02 3350 1212",
    "sg:postcode":"20019",
    "sg:province":"Milano",
    "sg:tags":[
        "metallurgy",
        "metalworking"
    ],
    "wof:name":"Rothenberger Italiana S.r.l.",
    "wof:placetype":"venue"
},
  "geometry": {"coordinates":[9.0652656555,45.4789810181],"type":"Point"}
}