{
  "type": "Feature",
  "properties": {
    "addr:full":"14100 Asti Asti Asti 14100",
    "addr:postcode":"14100;14100",
    "iso:country":"IT",
    "sg:address":"14100 Asti",
    "sg:city":"Asti",
    "sg:orig_category":"Ascensori - Installazione E Manutenzione",
    "sg:phone":"+39 0141 599120",
    "sg:postcode":"14100",
    "sg:province":"Asti",
    "wof:name":"Benetti Erasmo",
    "wof:placetype":"venue"
},
  "geometry": {"coordinates":[8.255555,45.011044],"type":"Point"}
}