{
  "type": "Feature",
  "properties": {
    "iso:country":"IT",
    "sg:address":"59, Via Alessandrini 42017 Novellara",
    "sg:classifiers":[
        {
            "category":"Professional",
            "subcategory":"Engineering",
            "type":"Services"
        }
    ],
    "sg:phone":"+39 0522 653423",
    "sg:postcode":"42017",
    "sg:province":"Reggio Nell'Emilia",
    "sg:tags":[
        "machine",
        "-",
        "mechanical"
    ],
    "wof:name":"Nuova T.m.r. (s.r.l.)",
    "wof:placetype":"venue"
},
  "geometry": {"coordinates":[10.711212,44.828381],"type":"Point"}
}