{
  "type": "Feature",
  "properties": {
    "iso:country":"IT",
    "sg:address":"6, Via Curie Maria 57023 Cecina",
    "sg:city":"Cecina",
    "sg:orig_category":"Miscellaneous Products",
    "sg:phone":"+39 0586 661215",
    "sg:postcode":"57023",
    "sg:province":"Livorno",
    "wof:name":"Barret (s.r.l.)",
    "wof:placetype":"venue"
},
  "geometry": {"coordinates":[10.308011055,43.5518760681],"type":"Point"}
}