{
  "type": "Feature",
  "properties": {
    "iso:country":"IT",
    "sg:address":"Via S.elia 24a 96010 Cassibile",
    "sg:orig_category":"Fruit Growing, Bio-organic",
    "sg:phone":"+39 0931 718155",
    "sg:postcode":"96010",
    "sg:province":"Siracusa",
    "sg:website":"www.campisitalia.com",
    "wof:name":"Campisi Italia",
    "wof:placetype":"venue"
},
  "geometry": {"coordinates":[15.2078294754,36.9888000488],"type":"Point"}
}