{
  "type": "Feature",
  "properties": {
    "addr:full":"10040 Lein\u00ec Torino 10040",
    "addr:postcode":"10040;10040",
    "iso:country":"IT",
    "sg:address":"10040 Lein\u00ec",
    "sg:classifiers":[
        {
            "category":"Professional",
            "subcategory":"Printing & Photocopies",
            "type":"Services"
        }
    ],
    "sg:phone":"+39 011 998 8733",
    "sg:postcode":"10040",
    "sg:province":"Torino",
    "sg:tags":[
        "publishing",
        "industry",
        "plastic",
        "packaging",
        "packing",
        "setting",
        "services",
        "works"
    ],
    "sg:website":"http://www.verplast.net",
    "wof:name":"Ver Plast Srl",
    "wof:placetype":"venue"
},
  "geometry": {"coordinates":[7.7224230766,45.1769599915],"type":"Point"}
}