{
  "type": "Feature",
  "properties": {
    "iso:country":"IT",
    "sg:address":"18, Via Mercurio 21051 Arcisate",
    "sg:city":"Arcisate",
    "sg:classifiers":[
        {
            "category":"Professional",
            "subcategory":"Engineering",
            "type":"Services"
        }
    ],
    "sg:phone":"+39 0332 473640",
    "sg:postcode":"21051",
    "sg:province":"Varese",
    "sg:tags":[
        "machine",
        "-",
        "mechanical"
    ],
    "wof:name":"Quarta Snc",
    "wof:placetype":"venue"
},
  "geometry": {"coordinates":[8.858287,45.852722],"type":"Point"}
}