{
  "type": "Feature",
  "properties": {
    "addr:full":"10123 Torino Torino Torino 10123",
    "addr:postcode":"10123;10123",
    "iso:country":"IT",
    "sg:address":"10123 Torino",
    "sg:city":"Torino",
    "sg:orig_category":"Lavorazioni Meccaniche E Servizi",
    "sg:phone":"+39 011 812 2151",
    "sg:postcode":"10123",
    "sg:province":"Torino",
    "wof:name":"Ferrazza Bruno",
    "wof:placetype":"venue"
},
  "geometry": {"coordinates":[7.530517,45.013672],"type":"Point"}
}