{
  "type": "Feature",
  "properties": {
    "addr:full":"10144 Torino Torino Torino 10144",
    "addr:postcode":"10144;10144",
    "iso:country":"IT",
    "sg:address":"10144 Torino",
    "sg:city":"Torino",
    "sg:orig_category":"Ospedali E Servizi Sanitari",
    "sg:phone":"+39 011 480827",
    "sg:postcode":"10144",
    "sg:province":"Torino",
    "wof:name":"Cardonnet Philippe Jacques",
    "wof:placetype":"venue"
},
  "geometry": {"coordinates":[7.658909,45.08157],"type":"Point"}
}