{
  "type": "Feature",
  "properties": {
    "addr:full":"13011 Borgosesia Borgosesia Vercelli 13011",
    "addr:postcode":"13011;13011",
    "iso:country":"IT",
    "sg:address":"13011 Borgosesia",
    "sg:city":"Borgosesia",
    "sg:orig_category":"Abbigliamento - Vendita Al Dettaglio",
    "sg:phone":"+39 0163 209068",
    "sg:postcode":"13011",
    "sg:province":"Vercelli",
    "wof:name":"Bike & Car",
    "wof:placetype":"venue"
},
  "geometry": {"coordinates":[8.278535,45.716114],"type":"Point"}
}