{
  "type": "Feature",
  "properties": {
    "iso:country":"IT",
    "sg:address":"Via B. Salara, 48 - Castiglione 48100 Ravenna",
    "sg:city":"Ravenna",
    "sg:classifiers":[
        {
            "category":"Wholesale",
            "subcategory":"Home Furnishings",
            "type":"Manufacturing & Wholesale Goods"
        }
    ],
    "sg:phone":"+39 0544 950573",
    "sg:postcode":"48100",
    "sg:province":"Ravenna",
    "sg:tags":[
        "chair"
    ],
    "sg:website":"www.italsedie.com",
    "wof:name":"Italsedie Di Gridelli Ivo & C. Snc",
    "wof:placetype":"venue"
},
  "geometry": {"coordinates":[12.251078,44.255184],"type":"Point"}
}