{
  "type": "Feature",
  "properties": {
    "iso:country":"IT",
    "sg:address":"30171 Venezia",
    "sg:city":"Venezia",
    "sg:orig_category":"Bullonerie",
    "sg:phone":"+39 041 983150",
    "sg:postcode":"30171",
    "sg:province":"Venezia",
    "wof:name":"Utensilferramenta Morello Snc",
    "wof:placetype":"venue"
},
  "geometry": {"coordinates":[12.417943,45.485203],"type":"Point"}
}