{
  "type": "Feature",
  "properties": {
    "addr:full":"Via Lisbona, 28; 35127 Padua, Italy Padova 35127",
    "addr:housenumber":"28",
    "addr:postcode":"35127;35127",
    "addr:street":"Via Lisbona",
    "iso:country":"IT",
    "sg:address":"Via Lisbona, 28; 35127 Padua, Italy",
    "sg:classifiers":[
        {
            "category":"Industrial Area",
            "type":"Public Place"
        }
    ],
    "sg:phone":"+39 049 828 7311",
    "sg:postcode":"35127",
    "sg:province":"Padova",
    "sg:tags":[
        "large",
        "private"
    ],
    "sg:website":"www.finmek.com",
    "wof:name":"Finmek S.p.a.",
    "wof:placetype":"venue"
},
  "geometry": {"coordinates":[11.946398735,45.3961257935],"type":"Point"}
}