{
  "type": "Feature",
  "properties": {
    "iso:country":"IT",
    "sg:address":"20010 Bernate Ticino",
    "sg:city":"Bernate Ticino",
    "sg:orig_category":"Carta, Cartone E Prodotti Primari",
    "sg:phone":"+39 02 975 4561",
    "sg:postcode":"20010",
    "sg:province":"Milano",
    "wof:name":"C.d.m. Di Pattano Felice E Morandi Natale S.n.c",
    "wof:placetype":"venue"
},
  "geometry": {"coordinates":[8.82813,45.481773],"type":"Point"}
}