{
  "type": "Feature",
  "properties": {
    "iso:country":"IT",
    "sg:address":"Via Europa 174/c 25062 Concesio",
    "sg:city":"Concesio",
    "sg:classifiers":[
        {
            "category":"Shopping",
            "subcategory":"Antiques",
            "type":"Retail Goods"
        }
    ],
    "sg:phone":"+39 030 275 1725",
    "sg:postcode":"25062",
    "sg:province":"Brescia",
    "sg:tags":[
        "arm",
        "artifact"
    ],
    "sg:website":"www.euroarms.net",
    "wof:name":"Euroarms Italia Srl",
    "wof:placetype":"venue"
},
  "geometry": {"coordinates":[10.215918,45.604355],"type":"Point"}
}