{
  "type": "Feature",
  "properties": {
    "iso:country":"IT",
    "sg:address":"31038 Paese",
    "sg:city":"Paese",
    "sg:orig_category":"Depurazione E Trattamento Delle Acque - Impianti Ed Apparecchi",
    "sg:phone":"+39 0422 967411",
    "sg:postcode":"31038",
    "sg:province":"Treviso",
    "wof:name":"Ates Srl",
    "wof:placetype":"venue"
},
  "geometry": {"coordinates":[12.153611,45.720165],"type":"Point"}
}