{
  "type": "Feature",
  "properties": {
    "iso:country":"IT",
    "sg:address":"44042 Cento",
    "sg:city":"Cento",
    "sg:orig_category":"Termotecnica E Riscaldamento, Apparecchiature E Servizi",
    "sg:phone":"+39 051 684 3711",
    "sg:postcode":"44042",
    "sg:province":"Ferrara",
    "sg:website":"http://www.baltur.it",
    "wof:name":"Baltur Spa",
    "wof:placetype":"venue"
},
  "geometry": {"coordinates":[11.294747,44.740017],"type":"Point"}
}