{
  "type": "Feature",
  "properties": {
    "iso:country":"IT",
    "sg:address":"33010 Tavagnacco",
    "sg:city":"Tavagnacco",
    "sg:orig_category":"Termotecnica E Riscaldamento, Apparecchiature E Servizi",
    "sg:phone":"+39 0432 575556",
    "sg:postcode":"33010",
    "sg:province":"Udine",
    "wof:name":"Cozzi Eugenio",
    "wof:placetype":"venue"
},
  "geometry": {"coordinates":[13.220924,46.1133],"type":"Point"}
}