{
  "type": "Feature",
  "properties": {
    "iso:country":"IT",
    "sg:address":"21052 Busto Arsizio",
    "sg:city":"Busto Arsizio",
    "sg:orig_category":"Attrezzature E Forniture Per Officine Riparazione E Servizi Ausiliari",
    "sg:phone":"+39 0331 323510",
    "sg:postcode":"21052",
    "sg:province":"Varese",
    "wof:name":"D.e.c.a. (s.r.l.)",
    "wof:placetype":"venue"
},
  "geometry": {"coordinates":[8.874096,45.615368],"type":"Point"}
}