{
  "type": "Feature",
  "properties": {
    "iso:country":"IT",
    "sg:address":"15/17/19/21, V. Roma 59013 Montemurlo",
    "sg:city":"Montemurlo",
    "sg:classifiers":[
        {
            "category":"Shopping",
            "subcategory":"Crafts & Fabrics",
            "type":"Retail Goods"
        }
    ],
    "sg:phone":"+39 390 574 6851",
    "sg:postcode":"59013",
    "sg:province":"Prato",
    "sg:website":"http://www.pontetorto.it",
    "wof:name":"Lanificio Pontetorto Spa",
    "wof:placetype":"venue"
},
  "geometry": {"coordinates":[11.0036678314,43.9044799805],"type":"Point"}
}