{
  "type": "Feature",
  "properties": {
    "addr:full":"Via Grasselli 19; Milano; 20137 Milano Milano 20137",
    "addr:housenumber":"19",
    "addr:postcode":"20137;20137",
    "addr:street":"Via Grasselli",
    "iso:country":"IT",
    "sg:address":"Via Grasselli 19; Milano; 20137",
    "sg:city":"Milano",
    "sg:classifiers":[
        {
            "category":"Banks & Credit Unions",
            "subcategory":"Bank",
            "type":"Services"
        }
    ],
    "sg:phone":"+39 02 7010 1161",
    "sg:postcode":"20137",
    "sg:province":"Milano",
    "wof:name":"Credito Emiliano Spa",
    "wof:placetype":"venue"
},
  "geometry": {"coordinates":[9.227777,45.462032],"type":"Point"}
}