{
  "type": "Feature",
  "properties": {
    "iso:country":"IT",
    "sg:address":"80025 Casandrino",
    "sg:city":"Casandrino",
    "sg:orig_category":"Macchine Ed Impianti Per Edilizia E Lavori Pubblici",
    "sg:phone":"+39 081 833 3348",
    "sg:postcode":"80025",
    "sg:province":"Napoli",
    "wof:name":"Teksped Srl",
    "wof:placetype":"venue"
},
  "geometry": {"coordinates":[14.239428,40.934174],"type":"Point"}
}