{
  "type": "Feature",
  "properties": {
    "iso:country":"IT",
    "sg:address":"00146 Roma",
    "sg:city":"Roma",
    "sg:orig_category":"Scuole E Servizi Scolastici. Alberghi E Strutture Extra Alberghiere",
    "sg:phone":"+39 06 541 0287",
    "sg:postcode":"00146",
    "sg:province":"Roma",
    "wof:name":"Sa.fi Di Sansonetti Giovanni E C. Snc",
    "wof:placetype":"venue"
},
  "geometry": {"coordinates":[12.474194,41.856983],"type":"Point"}
}