{
  "type": "Feature",
  "properties": {
    "iso:country":"IT",
    "sg:address":"Via Enrico Fermi, 2; Cassina De' Pecchi; Milano; 20060",
    "sg:classifiers":[
        {
            "category":"Industrial Area",
            "type":"Public Place"
        }
    ],
    "sg:phone":"+39 390 295 881",
    "sg:postcode":"20060",
    "sg:province":"Milano",
    "sg:tags":[
        "large",
        "private"
    ],
    "sg:website":"www.sirti.it",
    "wof:name":"Sirti Spa",
    "wof:placetype":"venue"
},
  "geometry": {"coordinates":[9.3203840256,45.4901542664],"type":"Point"}
}