{
  "type": "Feature",
  "properties": {
    "addr:full":"00146 Roma Roma Roma 00146",
    "addr:postcode":"00146;00146",
    "iso:country":"IT",
    "sg:address":"00146 Roma",
    "sg:city":"Roma",
    "sg:orig_category":"Macchine, Impianti Ed Attrezzature Per Abbigliamento E Pelletterie",
    "sg:phone":"+39 06 557 0290",
    "sg:postcode":"00146",
    "sg:province":"Roma",
    "wof:name":"Donati Maria",
    "wof:placetype":"venue"
},
  "geometry": {"coordinates":[12.465476,41.865963],"type":"Point"}
}