{
  "type": "Feature",
  "properties": {
    "addr:full":"20123 Milano Milano Milano 20123",
    "addr:postcode":"20123;20123",
    "iso:country":"IT",
    "sg:address":"20123 Milano",
    "sg:city":"Milano",
    "sg:orig_category":"Non-classified Establishments",
    "sg:phone":"+39 02 8645 2776",
    "sg:postcode":"20123",
    "sg:province":"Milano",
    "wof:name":"Chesi Tranquillo",
    "wof:placetype":"venue"
},
  "geometry": {"coordinates":[9.178719,45.45929],"type":"Point"}
}