{
  "type": "Feature",
  "properties": {
    "addr:full":"Via Dell'industria, 86/88/90 70051 Barletta Barletta Bari 70051",
    "addr:housenumber":"86 / 88 / 90",
    "addr:postcode":"70051;70051",
    "addr:street":"Via Dell'Industria",
    "iso:country":"IT",
    "sg:address":"Via Dell'industria, 86/88/90 70051 Barletta",
    "sg:city":"Barletta",
    "sg:classifiers":[
        {
            "category":"Shopping",
            "subcategory":"Shoes",
            "type":"Retail Goods"
        }
    ],
    "sg:phone":"+39 0883 347566",
    "sg:postcode":"70051",
    "sg:province":"Bari",
    "sg:tags":[
        "children's"
    ],
    "sg:website":"www.mondobabysrl.it",
    "wof:name":"Mondo Baby S.r.l.",
    "wof:placetype":"venue"
},
  "geometry": {"coordinates":[16.869291,41.126053],"type":"Point"}
}