{
  "type": "Feature",
  "properties": {
    "iso:country":"IT",
    "sg:address":"Viale Michelangelo, 2/4/6; Napoli; 80100",
    "sg:classifiers":[
        {
            "category":"Banks & Credit Unions",
            "subcategory":"Bank",
            "type":"Services"
        }
    ],
    "sg:phone":"+39 081 246078",
    "wof:name":"Banca Dei Comuni Vesuviani",
    "wof:placetype":"venue"
},
  "geometry": {"coordinates":[14.270226,40.891644],"type":"Point"}
}