{
  "type": "Feature",
  "properties": {
    "addr:full":"24124 Bergamo Bergamo Bergamo 24124",
    "addr:postcode":"24124;24124",
    "iso:country":"IT",
    "sg:address":"24124 Bergamo",
    "sg:city":"Bergamo",
    "sg:orig_category":"Forniture Per Attivita' Industriali",
    "sg:phone":"+39 035 243094",
    "sg:postcode":"24124",
    "sg:province":"Bergamo",
    "wof:name":"Lanzagomma Snc",
    "wof:placetype":"venue"
},
  "geometry": {"coordinates":[9.6925144196,45.713848114],"type":"Point"}
}