{
  "type": "Feature",
  "properties": {
    "iso:country":"IT",
    "sg:address":"1, Via Molinara 22031 Albavilla",
    "sg:city":"Albavilla",
    "sg:classifiers":[
        {
            "category":"Shopping",
            "subcategory":"Crafts & Fabrics",
            "type":"Retail Goods"
        }
    ],
    "sg:phone":"+39 39031628262",
    "sg:postcode":"22031",
    "sg:province":"Como",
    "wof:name":"Resin 2000 (s.r.l.)",
    "wof:placetype":"venue"
},
  "geometry": {"coordinates":[9.1807489395,45.7904243469],"type":"Point"}
}