{
  "type": "Feature",
  "properties": {
    "iso:country":"IT",
    "sg:address":"22100 Como",
    "sg:city":"Como",
    "sg:orig_category":"Automobili E Mezzi Di Trasporto",
    "sg:phone":"+39 031 521220",
    "sg:postcode":"22100",
    "sg:province":"Como",
    "wof:name":"Garage Rezzonico Giorgio Snc",
    "wof:placetype":"venue"
},
  "geometry": {"coordinates":[9.075999,45.78981],"type":"Point"}
}