{
  "type": "Feature",
  "properties": {
    "iso:country":"IT",
    "sg:address":"10123 Torino",
    "sg:city":"Torino",
    "sg:orig_category":"Telecomunicazioni E Telefonia, Impianti, Apparecchi E Servizi",
    "sg:phone":"+39 011 812 8455",
    "sg:postcode":"10123",
    "sg:province":"Torino",
    "sg:website":"http://www.ilcerchiomagico.it",
    "wof:name":"Infotel Torino Srl",
    "wof:placetype":"venue"
},
  "geometry": {"coordinates":[7.688469,45.059437],"type":"Point"}
}