{
  "type": "Feature",
  "properties": {
    "iso:country":"IT",
    "sg:address":"00142 Roma",
    "sg:city":"Roma",
    "sg:classifiers":[
        {
            "category":"Shopping",
            "subcategory":"Bicycles & Sporting Goods",
            "type":"Retail Goods"
        }
    ],
    "sg:phone":"+39 06 5198 0184",
    "sg:postcode":"00142",
    "sg:province":"Roma",
    "sg:tags":[
        "e",
        "sport",
        "-",
        "forniture",
        "articoli"
    ],
    "sg:website":"http://www.bluedimension.it",
    "wof:name":"Bluedimension Srl",
    "wof:placetype":"venue"
},
  "geometry": {"coordinates":[12.489655,41.833878],"type":"Point"}
}