{
  "type": "Feature",
  "properties": {
    "iso:country":"IT",
    "sg:address":"38, Via Azzi Enrico 31038 Paese",
    "sg:city":"Paese",
    "sg:classifiers":[
        {
            "category":"Shopping",
            "subcategory":"Crafts & Fabrics",
            "type":"Retail Goods"
        }
    ],
    "sg:phone":"+39 390 422 2678",
    "sg:postcode":"31038",
    "sg:province":"Treviso",
    "wof:name":"Idea S.r.l.",
    "wof:placetype":"venue"
},
  "geometry": {"coordinates":[12.1922235489,45.6903839111],"type":"Point"}
}