{
  "type": "Feature",
  "properties": {
    "addr:full":"Via Mazzini 40/42 50050 Gambassi Terme Gambassi Terme Firenze 50050",
    "addr:housenumber":"40 / 42",
    "addr:postcode":"50050;50050",
    "addr:street":"Via Mazzini;Terme",
    "iso:country":"IT",
    "sg:address":"Via Mazzini 40/42 50050 Gambassi Terme",
    "sg:city":"Gambassi Terme",
    "sg:orig_category":"Ladies' Shoes",
    "sg:phone":"+39 0571 665361",
    "sg:postcode":"50050",
    "sg:province":"Firenze",
    "sg:website":"www.zodiaco.it",
    "wof:name":"Calzaturificio Rambo Srl",
    "wof:placetype":"venue"
},
  "geometry": {"coordinates":[11.256902,43.768734],"type":"Point"}
}