{
  "type": "Feature",
  "properties": {
    "iso:country":"IT",
    "sg:address":"Via Bari, 13; Bolzano; 39100",
    "sg:city":"Bolzano",
    "sg:classifiers":[
        {
            "category":"Banks & Credit Unions",
            "subcategory":"Bank",
            "type":"Services"
        }
    ],
    "sg:phone":"+39 0471 204483",
    "sg:postcode":"39100",
    "sg:province":"Bolzano/Bozen",
    "wof:name":"Banca Sella Spa",
    "wof:placetype":"venue"
},
  "geometry": {"coordinates":[11.32506,46.486816],"type":"Point"}
}