{
  "type": "Feature",
  "properties": {
    "iso:country":"IT",
    "sg:address":"5, Via Cristoforo Colombo 36075 Montecchio Maggiore",
    "sg:city":"Montecchio Maggiore",
    "sg:classifiers":[
        {
            "category":"Professional",
            "subcategory":"Engineering",
            "type":"Services"
        }
    ],
    "sg:phone":"+39 0444 705000",
    "sg:postcode":"36075",
    "sg:province":"Vicenza",
    "sg:tags":[
        "machine",
        "-",
        "mechanical"
    ],
    "wof:name":"Dinoil S.r.l.",
    "wof:placetype":"venue"
},
  "geometry": {"coordinates":[11.484472,45.523396],"type":"Point"}
}