{
  "type": "Feature",
  "properties": {
    "iso:country":"IT",
    "sg:address":"35124 Padova",
    "sg:city":"Padova",
    "sg:orig_category":"Arredo Cucina Ed Elettrodomestici. Elettrodomestici",
    "sg:phone":"+39 049 690700",
    "sg:postcode":"35124",
    "sg:province":"Padova",
    "wof:name":"Delta Assistenza Snc",
    "wof:placetype":"venue"
},
  "geometry": {"coordinates":[11.889278,45.361393],"type":"Point"}
}