{
  "type": "Feature",
  "properties": {
    "addr:full":"32032 Feltre Feltre Belluno 32032",
    "addr:postcode":"32032;32032",
    "iso:country":"IT",
    "sg:address":"32032 Feltre",
    "sg:city":"Feltre",
    "sg:orig_category":"Fabbri",
    "sg:phone":"+39 0439 81648",
    "sg:postcode":"32032",
    "sg:province":"Belluno",
    "wof:name":"Zanin Gerardo",
    "wof:placetype":"venue"
},
  "geometry": {"coordinates":[12.0834236145,46.095905304],"type":"Point"}
}