{
  "type": "Feature",
  "properties": {
    "iso:country":"IT",
    "sg:address":"20121 Milano",
    "sg:city":"Milano",
    "sg:orig_category":"Servizi Per Lo Sport E Il Tempo Libero. Servizi Al Turismo",
    "sg:phone":"+39 02 655 4758",
    "sg:postcode":"20121",
    "sg:province":"Milano",
    "wof:name":"Brera Sport Club",
    "wof:placetype":"venue"
},
  "geometry": {"coordinates":[9.184489,45.478905],"type":"Point"}
}