{
  "type": "Feature",
  "properties": {
    "iso:country":"IT",
    "sg:address":"40121 Bologna",
    "sg:city":"Bologna",
    "sg:orig_category":"Medici Specialisti - Chirurgia Plastica E Ricostruttiva",
    "sg:phone":"+39 051 261416",
    "sg:postcode":"40121",
    "sg:province":"Bologna",
    "sg:website":"http://www.zigiotti.it",
    "wof:name":"Prof. Gian Luigi Zigiotti",
    "wof:placetype":"venue"
},
  "geometry": {"coordinates":[11.339836,44.504063],"type":"Point"}
}