{
  "type": "Feature",
  "properties": {
    "iso:country":"IT",
    "sg:address":"Via Del Fosso 2 40066 Pieve Di Cento",
    "sg:city":"Pieve di Cento",
    "sg:classifiers":[
        {
            "category":"Wholesale",
            "subcategory":"Auto Parts",
            "type":"Manufacturing & Wholesale Goods"
        }
    ],
    "sg:phone":"+39 051 973535",
    "sg:postcode":"40066",
    "sg:province":"Bologna",
    "sg:tags":[
        "engine",
        "spare",
        "diesel"
    ],
    "wof:name":"Diesel Parts Srl",
    "wof:placetype":"venue"
},
  "geometry": {"coordinates":[11.314312,44.707977],"type":"Point"}
}