{
  "type": "Feature",
  "properties": {
    "addr:full":"21052 Busto Arsizio Busto Arsizio Varese 21052",
    "addr:postcode":"21052;21052",
    "iso:country":"IT",
    "sg:address":"21052 Busto Arsizio",
    "sg:city":"Busto Arsizio",
    "sg:orig_category":"Petroli, Gas E Combustibili",
    "sg:phone":"+39 0331 275316",
    "sg:postcode":"21052",
    "sg:province":"Varese",
    "wof:name":"Mariel Srl",
    "wof:placetype":"venue"
},
  "geometry": {"coordinates":[8.8483867645,45.6186790466],"type":"Point"}
}