{
  "type": "Feature",
  "properties": {
    "iso:country":"IT",
    "sg:address":"63029 Servigliano",
    "sg:city":"Servigliano",
    "sg:orig_category":"Materiali Edili",
    "sg:phone":"+39 0734 750765",
    "sg:postcode":"63029",
    "sg:province":"Ascoli Piceno",
    "wof:name":"Frolla' Srl",
    "wof:placetype":"venue"
},
  "geometry": {"coordinates":[13.516686,42.882851],"type":"Point"}
}