{
  "type": "Feature",
  "properties": {
    "addr:full":"Via Degli Scavi 18 47100 Forli' Forl\u00ec-Cesena 47100",
    "addr:housenumber":"18",
    "addr:postcode":"47100;47100",
    "addr:street":"Via Degli Scavi;' Forli\u0300-Cesena",
    "iso:country":"IT",
    "sg:address":"Via Degli Scavi 18 47100 Forli'",
    "sg:classifiers":[
        {
            "category":"Building & Trades",
            "subcategory":"Construction",
            "type":"Services"
        }
    ],
    "sg:phone":"+39 0543 721269",
    "sg:postcode":"47100",
    "sg:province":"Forl\u00ec-Cesena",
    "sg:tags":[
        "carpenter's",
        "work",
        "supraregional"
    ],
    "sg:website":"www.sartinisilvano.it",
    "wof:name":"Officina Meccanica Sartini Srl",
    "wof:placetype":"venue"
},
  "geometry": {"coordinates":[12.08558,44.237995],"type":"Point"}
}