{
  "type": "Feature",
  "properties": {
    "iso:country":"IT",
    "sg:address":"16129 Genova",
    "sg:city":"Genova",
    "sg:orig_category":"Nautica. Accessori Dei Mezzi Di Trasporto. Servizi Ausiliari Dei Mezzi Di Trasporto",
    "sg:phone":"+39 010 586771",
    "sg:postcode":"16129",
    "sg:province":"Genova",
    "wof:name":"Sirn Srl",
    "wof:placetype":"venue"
},
  "geometry": {"coordinates":[8.949078,44.395317],"type":"Point"}
}