{
  "type": "Feature",
  "properties": {
    "addr:full":"46010 Campitello Campitello Mantova 46010",
    "addr:postcode":"46010;46010",
    "iso:country":"IT",
    "sg:address":"46010 Campitello",
    "sg:city":"Campitello",
    "sg:orig_category":"Campeggio",
    "sg:phone":"+39 0376 96181",
    "sg:postcode":"46010",
    "sg:province":"Mantova",
    "wof:name":"Bertolani F. & C. (s.n.c.)",
    "wof:placetype":"venue"
},
  "geometry": {"coordinates":[10.602906,45.088036],"type":"Point"}
}