{
  "type": "Feature",
  "properties": {
    "iso:country":"IT",
    "sg:address":"20010 Arluno",
    "sg:city":"Arluno",
    "sg:orig_category":"Materiali E Componenti Elettrotecnici. Elettrotecnica Industriale, Prodotti E Apparecchiature",
    "sg:phone":"+39 02 901 7026",
    "sg:postcode":"20010",
    "sg:province":"Milano",
    "wof:name":"Elettromeccanica F.lli Olgiati Snc Di Olgiati E C.",
    "wof:placetype":"venue"
},
  "geometry": {"coordinates":[9.187151,45.529537],"type":"Point"}
}