{
  "type": "Feature",
  "properties": {
    "iso:country":"IT",
    "sg:address":"25038 Rovato",
    "sg:city":"Rovato",
    "sg:orig_category":"Zootecnia E Pesca, Allevamento Piccoli Animali",
    "sg:phone":"+39 030 773 0768",
    "sg:postcode":"25038",
    "sg:province":"Brescia",
    "wof:name":"Clerici Serafino",
    "wof:placetype":"venue"
},
  "geometry": {"coordinates":[9.614247,45.640415],"type":"Point"}
}