{
  "type": "Feature",
  "properties": {
    "iso:country":"IT",
    "sg:address":"105, Via Inveruno 20020 Busto Garolfo",
    "sg:city":"Busto Garolfo",
    "sg:classifiers":[
        {
            "category":"Shopping",
            "subcategory":"Crafts & Fabrics",
            "type":"Retail Goods"
        }
    ],
    "sg:phone":"+39 0331 537513",
    "sg:postcode":"20020",
    "sg:province":"Milano",
    "wof:name":"Laborotex (s.p.a.)",
    "wof:placetype":"venue"
},
  "geometry": {"coordinates":[8.9147291183,45.4982337952],"type":"Point"}
}