{
  "type": "Feature",
  "properties": {
    "iso:country":"IT",
    "sg:address":"50, V. Monte Cimone 36073 Cornedo Vic.",
    "sg:classifiers":[
        {
            "category":"Shopping",
            "subcategory":"Clothing, Apparel, & Fashions",
            "type":"Retail Goods"
        }
    ],
    "sg:phone":"+39 0445 431499",
    "sg:postcode":"36073",
    "sg:province":"Vicenza",
    "sg:tags":[
        "clothing",
        "accessory"
    ],
    "wof:name":"Dal Maso Camiceria & Abbigliamento",
    "wof:placetype":"venue"
},
  "geometry": {"coordinates":[11.526389,45.575279],"type":"Point"}
}