{
  "type": "Feature",
  "properties": {
    "addr:full":"Via Regione Piemionte 5-z.i. D 1 15068 Pozzolo Formigaro Pozzolo Formigaro Alessandria 15068",
    "addr:housenumber":"5-z.i d 1",
    "addr:postcode":"15068;15068",
    "addr:street":"Via Regione Piemionte",
    "iso:country":"IT",
    "sg:address":"Via Regione Piemionte 5-z.i. D 1 15068 Pozzolo Formigaro",
    "sg:city":"Pozzolo Formigaro",
    "sg:classifiers":[
        {
            "category":"Sports & Exercise",
            "subcategory":"Sports Center",
            "type":"Entertainment"
        }
    ],
    "sg:phone":"+39 0143 318500",
    "sg:postcode":"15068",
    "sg:province":"Alessandria",
    "sg:tags":[
        "billiards",
        "accessory"
    ],
    "sg:website":"www.garlando.it",
    "wof:name":"Garlando Srl",
    "wof:placetype":"venue"
},
  "geometry": {"coordinates":[8.616951,44.913216],"type":"Point"}
}