{
  "type": "Feature",
  "properties": {
    "iso:country":"IT",
    "sg:address":"20037 Paderno Dugnano",
    "sg:city":"Paderno Dugnano",
    "sg:classifiers":[
        {
            "category":"Wholesale",
            "subcategory":"Machinery & Supplies",
            "type":"Manufacturing & Wholesale Goods"
        }
    ],
    "sg:phone":"+39 02 9904 1518",
    "sg:postcode":"20037",
    "sg:province":"Milano",
    "sg:tags":[
        "component",
        "engineering",
        "material",
        "electrical"
    ],
    "wof:name":"Grote & Hartmann Spa",
    "wof:placetype":"venue"
},
  "geometry": {"coordinates":[9.180844,45.560593],"type":"Point"}
}