{
  "type": "Feature",
  "properties": {
    "iso:country":"IT",
    "sg:address":"3, Str. Valiminiers 14019 Villanova D'asti",
    "sg:classifiers":[
        {
            "category":"Shopping",
            "subcategory":"Crafts & Fabrics",
            "type":"Retail Goods"
        }
    ],
    "sg:phone":"+39 0141 946909",
    "sg:postcode":"14019",
    "sg:province":"Asti",
    "sg:website":"http://www.saiatex.it",
    "wof:name":"Saiatex Srl",
    "wof:placetype":"venue"
},
  "geometry": {"coordinates":[8.2068128586,44.9008636475],"type":"Point"}
}