{
  "type": "Feature",
  "properties": {
    "addr:full":"00046 Grottaferrata Grottaferrata Roma 00046",
    "addr:postcode":"00046;roma 00046",
    "iso:country":"IT",
    "sg:address":"00046 Grottaferrata",
    "sg:city":"Grottaferrata",
    "sg:orig_category":"Motori Ed Organi Di Trasmissione. Ricambi E Componenti Dei Mezzi Di Trasporto",
    "sg:phone":"+39 06 9431 5822",
    "sg:postcode":"00046",
    "sg:province":"Roma",
    "wof:name":"Iml Motori Spa",
    "wof:placetype":"venue"
},
  "geometry": {"coordinates":[12.6882638931,41.7796096802],"type":"Point"}
}