{
  "type": "Feature",
  "properties": {
    "addr:full":"00147 Roma Roma Roma 00147",
    "addr:postcode":"00147;00147",
    "iso:country":"IT",
    "sg:address":"00147 Roma",
    "sg:city":"Roma",
    "sg:classifiers":[
        {
            "category":"Shopping",
            "subcategory":"Bicycles & Sporting Goods",
            "type":"Retail Goods"
        }
    ],
    "sg:phone":"+39 06 513 4441",
    "sg:postcode":"00147",
    "sg:province":"Roma",
    "sg:tags":[
        "e",
        "sport",
        "-",
        "forniture",
        "articoli"
    ],
    "sg:website":"http://www.windsurfparadise.com",
    "wof:name":"Windsurf Paradise",
    "wof:placetype":"venue"
},
  "geometry": {"coordinates":[12.496149,41.854675],"type":"Point"}
}