{
  "type": "Feature",
  "properties": {
    "iso:country":"IT",
    "sg:address":"4, Via Massarenti Giuseppe 41100 Modena",
    "sg:city":"Modena",
    "sg:classifiers":[
        {
            "category":"Food & Beverages",
            "subcategory":"Groceries & Convenience Stores",
            "type":"Retail Goods"
        }
    ],
    "sg:phone":"+39 39059312055",
    "sg:postcode":"41100",
    "sg:province":"Modena",
    "sg:tags":[
        "product",
        "related"
    ],
    "wof:name":"Pastificio Zanini S.r.l.",
    "wof:placetype":"venue"
},
  "geometry": {"coordinates":[10.9252195358,44.6470794678],"type":"Point"}
}