{
  "type": "Feature",
  "properties": {
    "iso:country":"IT",
    "sg:address":"80038 Pomigliano D'arco",
    "sg:orig_category":"Arti Grafiche",
    "sg:phone":"+39 081 844 9111",
    "sg:postcode":"80038",
    "sg:province":"Napoli",
    "sg:website":"http://www.paginegialle.it/stampress",
    "wof:name":"Stampress Srl",
    "wof:placetype":"venue"
},
  "geometry": {"coordinates":[14.387204,40.908909],"type":"Point"}
}