{
  "type": "Feature",
  "properties": {
    "iso:country":"IT",
    "sg:address":"86170 Isernia",
    "sg:city":"Isernia",
    "sg:orig_category":"Prodotti Chimici Secondari. Macchine E Forniture Per Ecologia E Smaltimento Rifiuti",
    "sg:phone":"+39 0865 29160",
    "sg:postcode":"86170",
    "sg:province":"Isernia",
    "wof:name":"Issan Di Testa Michele",
    "wof:placetype":"venue"
},
  "geometry": {"coordinates":[14.2047157288,41.5974845886],"type":"Point"}
}