{
  "type": "Feature",
  "properties": {
    "addr:full":"06012 Citt\u00e0 Di Castello Perugia 06012",
    "addr:postcode":"06012;06012",
    "iso:country":"IT",
    "sg:address":"06012 Citt\u00e0 Di Castello",
    "sg:orig_category":"Pubblicita', Marketing E Comunicazione",
    "sg:phone":"+39 075 852 2349",
    "sg:postcode":"06012",
    "sg:province":"Perugia",
    "wof:name":"Agenzia Top Service Di Michetti Claudia",
    "wof:placetype":"venue"
},
  "geometry": {"coordinates":[12.2470359802,43.4497146606],"type":"Point"}
}