{
  "type": "Feature",
  "properties": {
    "iso:country":"IT",
    "sg:address":"8, Via Pezzotti Giovanni 20141 Milano",
    "sg:city":"Milano",
    "sg:classifiers":[
        {
            "category":"Manufacturing",
            "subcategory":"Glass & Minerals",
            "type":"Manufacturing & Wholesale Goods"
        }
    ],
    "sg:phone":"+39 39028464144",
    "sg:postcode":"20141",
    "sg:province":"Milano",
    "wof:name":"Soleko Soft Lens Kontact (s.p.a.)",
    "wof:placetype":"venue"
},
  "geometry": {"coordinates":[9.182977,45.441956],"type":"Point"}
}