{
  "type": "Feature",
  "properties": {
    "addr:full":"09127 Cagliari Cagliari Cagliari 09127",
    "addr:postcode":"09127;09127",
    "iso:country":"IT",
    "sg:address":"09127 Cagliari",
    "sg:city":"Cagliari",
    "sg:orig_category":"Servizi E Lavori Per Abbigliamento E Pelletterie. Scuole E Servizi Scolastici. Ricerca, Selezione E Formazione Del Personale",
    "sg:phone":"+39 070 452 5777",
    "sg:postcode":"09127",
    "sg:province":"Cagliari",
    "wof:name":"Sartoria Piroddi M.rosaria",
    "wof:placetype":"venue"
},
  "geometry": {"coordinates":[9.122096,39.215393],"type":"Point"}
}