{
  "type": "Feature",
  "properties": {
    "iso:country":"IT",
    "sg:address":"7, Via Dante 07047 Thiesi",
    "sg:city":"Thiesi",
    "sg:classifiers":[
        {
            "category":"Manufacturing",
            "subcategory":"Textiles",
            "type":"Manufacturing & Wholesale Goods"
        }
    ],
    "sg:phone":"+39 39079886018",
    "sg:postcode":"07047",
    "sg:province":"Sassari",
    "sg:tags":[
        "leather",
        "raw",
        "material",
        "-"
    ],
    "wof:name":"Cossu Demetrio",
    "wof:placetype":"venue"
},
  "geometry": {"coordinates":[8.71623,40.523281],"type":"Point"}
}