{
  "type": "Feature",
  "properties": {
    "iso:country":"IT",
    "sg:address":"16126 Genova",
    "sg:city":"Genova",
    "sg:orig_category":"Ecologia - Studi Consulenza E Servizi",
    "sg:phone":"+39 010 247 6870",
    "sg:postcode":"16126",
    "sg:province":"Genova",
    "wof:name":"Giuseppe Santoro Sas",
    "wof:placetype":"venue"
},
  "geometry": {"coordinates":[8.909358,44.40567],"type":"Point"}
}