{
  "type": "Feature",
  "properties": {
    "iso:country":"IT",
    "sg:address":"50012 Bagno A Ripoli",
    "sg:city":"Bagno a Ripoli",
    "sg:orig_category":"Articoli Da Regalo. Forniture Per Uffici. Regalistica Aziendale",
    "sg:postcode":"50012",
    "sg:province":"Firenze",
    "wof:name":"Stypen Italia Srl",
    "wof:placetype":"venue"
},
  "geometry": {"coordinates":[11.33176,43.731625],"type":"Point"}
}