{
  "type": "Feature",
  "properties": {
    "iso:country":"IT",
    "sg:address":"50038 Scarperia",
    "sg:city":"Scarperia",
    "sg:orig_category":"Serramenti Ed Infissi",
    "sg:phone":"+39 055 843 0484",
    "sg:postcode":"50038",
    "sg:province":"Firenze",
    "wof:name":"Bi.esse",
    "wof:placetype":"venue"
},
  "geometry": {"coordinates":[11.333281,43.974503],"type":"Point"}
}