{
  "type": "Feature",
  "properties": {
    "iso:country":"IT",
    "sg:address":"41100 Modena",
    "sg:city":"Modena",
    "sg:orig_category":"Ricerca, Selezione E Formazione Del Personale",
    "sg:phone":"+39 059 218615",
    "sg:postcode":"41100",
    "sg:province":"Modena",
    "sg:website":"http://www.studiomai.it",
    "wof:name":"Studio Luciano Mai Srl",
    "wof:placetype":"venue"
},
  "geometry": {"coordinates":[10.926615,44.549637],"type":"Point"}
}