{
  "type": "Feature",
  "properties": {
    "addr:full":"Via Maccalone, 54 - Piangipane 48020 Ravenna Ravenna Ravenna 48020",
    "addr:housenumber":"54",
    "addr:postcode":"48020;48020",
    "addr:street":"Via Maccalone",
    "iso:country":"IT",
    "sg:address":"Via Maccalone, 54 - Piangipane 48020 Ravenna",
    "sg:city":"Ravenna",
    "sg:classifiers":[
        {
            "category":"Home & Garden",
            "subcategory":"Furniture",
            "type":"Retail Goods"
        }
    ],
    "sg:phone":"+39 0544 412911",
    "sg:postcode":"48020",
    "sg:province":"Ravenna",
    "sg:tags":[
        "sheeting"
    ],
    "sg:website":"www.trombinigroup.com",
    "wof:name":"Rafal Spa",
    "wof:placetype":"venue"
},
  "geometry": {"coordinates":[12.2250003815,44.3638877869],"type":"Point"}
}