{
  "type": "Feature",
  "properties": {
    "addr:full":"12022 Busca Busca Cuneo 12022",
    "addr:postcode":"12022;12022",
    "iso:country":"IT",
    "sg:address":"12022 Busca",
    "sg:city":"Busca",
    "sg:orig_category":"Servizi Al Turismo. Trasporto Pubblico E Privato. Acqua, Luce, Gas E Societa' Di Esercizio Pubblico",
    "sg:phone":"+39 0171 945894",
    "sg:postcode":"12022",
    "sg:province":"Cuneo",
    "wof:name":"Ferrara Bus Snc",
    "wof:placetype":"venue"
},
  "geometry": {"coordinates":[7.480089,44.524208],"type":"Point"}
}