{
  "type": "Feature",
  "properties": {
    "iso:country":"IT",
    "sg:address":"80078 Pozzuoli",
    "sg:city":"Pozzuoli",
    "sg:orig_category":"Scuole E Servizi Scolastici",
    "sg:phone":"+39 081 303 2409",
    "sg:postcode":"80078",
    "sg:province":"Napoli",
    "wof:name":"Centro Scolastico Accademia Europea Srl",
    "wof:placetype":"venue"
},
  "geometry": {"coordinates":[14.12804,40.82851],"type":"Point"}
}