{
  "type": "Feature",
  "properties": {
    "iso:country":"IT",
    "sg:address":"00194 Roma",
    "sg:city":"Roma",
    "sg:orig_category":"Servizi Per Lo Sport E Il Tempo Libero. Servizi Al Turismo",
    "sg:phone":"+39 06 334 1003",
    "sg:postcode":"00194",
    "sg:province":"Roma",
    "wof:name":"Ass. Culturale Armonia",
    "wof:placetype":"venue"
},
  "geometry": {"coordinates":[12.464174,41.937759],"type":"Point"}
}