{
  "type": "Feature",
  "properties": {
    "iso:country":"IT",
    "sg:address":"10148 Torino",
    "sg:city":"Torino",
    "sg:orig_category":"Autoclavi",
    "sg:phone":"+39 011 274 5165",
    "sg:postcode":"10148",
    "sg:province":"Torino",
    "wof:name":"I.s.a. Di Marcarelli S.",
    "wof:placetype":"venue"
},
  "geometry": {"coordinates":[7.661009,45.112656],"type":"Point"}
}