{
  "type": "Feature",
  "properties": {
    "iso:country":"IT",
    "sg:address":"10129 Torino",
    "sg:city":"Torino",
    "sg:orig_category":"Prodotti Finiti Stampati. Shopping. Regalistica Aziendale",
    "sg:phone":"+39 011 595404",
    "sg:postcode":"10129",
    "sg:province":"Torino",
    "wof:name":"Bedar (s.a.s.)",
    "wof:placetype":"venue"
},
  "geometry": {"coordinates":[7.5786375999,45.0171546936],"type":"Point"}
}