{
  "type": "Feature",
  "properties": {
    "addr:full":"18/20, Via Degli Stradivari 00153 Roma Roma Roma 00153",
    "addr:housenumber":"18 / 20",
    "addr:postcode":"00153;00153",
    "addr:street":"Via Degli Stradivari",
    "iso:country":"IT",
    "sg:address":"18/20, Via Degli Stradivari 00153 Roma",
    "sg:city":"Roma",
    "sg:classifiers":[
        {
            "category":"Wholesale",
            "subcategory":"Medical Equipment & Supplies",
            "type":"Manufacturing & Wholesale Goods"
        }
    ],
    "sg:phone":"+39 39065897627",
    "sg:postcode":"00153",
    "sg:province":"Roma",
    "sg:tags":[
        "-",
        "health",
        "instrument"
    ],
    "wof:name":"Golden Star Snc",
    "wof:placetype":"venue"
},
  "geometry": {"coordinates":[12.468639,41.87479],"type":"Point"}
}