{
  "type": "Feature",
  "properties": {
    "iso:country":"IT",
    "sg:address":"20069 Vaprio D'adda",
    "sg:orig_category":"Ponteggi Per Edilizia",
    "sg:phone":"+39 02 9098 8251",
    "sg:postcode":"20069",
    "sg:province":"Milano",
    "wof:name":"Lead Srl",
    "wof:placetype":"venue"
},
  "geometry": {"coordinates":[9.5262498856,45.5738754272],"type":"Point"}
}