{
  "type": "Feature",
  "properties": {
    "addr:full":"P. Garibaldi 82 80047 San Giuseppe Vesuviano San Giuseppe Vesuviano Napoli 80047",
    "addr:housenumber":"82",
    "addr:postcode":"80047;80047",
    "addr:street":"P. Garibaldi",
    "iso:country":"IT",
    "sg:address":"P. Garibaldi 82 80047 San Giuseppe Vesuviano",
    "sg:city":"San Giuseppe Vesuviano",
    "sg:classifiers":[
        {
            "category":"Home & Garden",
            "subcategory":"Home Furnishings",
            "type":"Retail Goods"
        }
    ],
    "sg:phone":"+39 081 827 4941",
    "sg:postcode":"80047",
    "sg:province":"Napoli",
    "sg:tags":[
        "textile"
    ],
    "wof:name":"Gianni Annunziata Spa",
    "wof:placetype":"venue"
},
  "geometry": {"coordinates":[14.402272,40.86401],"type":"Point"}
}