{
  "type": "Feature",
  "properties": {
    "addr:full":"20010 Cornaredo Cornaredo Milano 20010",
    "addr:postcode":"20010;20010",
    "iso:country":"IT",
    "sg:address":"20010 Cornaredo",
    "sg:city":"Cornaredo",
    "sg:orig_category":"Macchine, Impianti Ed Attrezzature Industria Chimica. Attrezzature E Forniture Per Officine Riparazione E Servizi Ausiliari",
    "sg:phone":"+39 02 9356 9853",
    "sg:postcode":"20010",
    "sg:province":"Milano",
    "wof:name":"O.f. Di Ocello Franco & Messa Felice Sdf",
    "wof:placetype":"venue"
},
  "geometry": {"coordinates":[9.032395,45.498421],"type":"Point"}
}