{
  "type": "Feature",
  "properties": {
    "iso:country":"IT",
    "sg:address":"Via Liguria 2 24052 Azzano San Paolo",
    "sg:city":"Azzano San Paolo",
    "sg:classifiers":[
        {
            "category":"Manufacturing",
            "subcategory":"Chemicals & Compounds",
            "type":"Manufacturing & Wholesale Goods"
        }
    ],
    "sg:phone":"+39 035 325011",
    "sg:postcode":"24052",
    "sg:province":"Bergamo",
    "sg:tags":[
        "industrial"
    ],
    "sg:website":"www.chtitalia.it",
    "wof:name":"Cht Italia Srl",
    "wof:placetype":"venue"
},
  "geometry": {"coordinates":[9.699065,45.662292],"type":"Point"}
}