{
  "type": "Feature",
  "properties": {
    "addr:full":"19124 La Spezia SP",
    "addr:housenumber":"19124",
    "iso:country":"IT",
    "sg:address":"19124 La Spezia",
    "sg:orig_category":"Pompe",
    "sg:phone":"+39 0187 514284",
    "sg:province":"SP",
    "wof:name":"Sinergo Sas",
    "wof:placetype":"venue"
},
  "geometry": {"coordinates":[9.8250484467,44.1140861511],"type":"Point"}
}