{
  "type": "Feature",
  "properties": {
    "addr:full":"5, Via Montanari 27028 San Martino Siccomario San Martino Siccomario Pavia 27028",
    "addr:postcode":"27028;27028",
    "addr:street":"Via Montanari",
    "iso:country":"IT",
    "sg:address":"5, Via Montanari 27028 San Martino Siccomario",
    "sg:city":"San Martino Siccomario",
    "sg:classifiers":[
        {
            "category":"Professional",
            "subcategory":"Engineering",
            "type":"Services"
        }
    ],
    "sg:phone":"+39 0382 498861",
    "sg:postcode":"27028",
    "sg:province":"Pavia",
    "sg:tags":[
        "machine",
        "-",
        "mechanical"
    ],
    "wof:name":"Fonderia Tipografica Pavese S.r.l.",
    "wof:placetype":"venue"
},
  "geometry": {"coordinates":[9.133587,45.155067],"type":"Point"}
}