{
  "type": "Feature",
  "properties": {
    "addr:full":"Viale Darsena Orientale; Castel Volturno; 81030 Castel Volturno Caserta 81030",
    "addr:postcode":"81030;81030",
    "addr:street":"Viale Darsena",
    "iso:country":"IT",
    "sg:address":"Viale Darsena Orientale; Castel Volturno; 81030",
    "sg:city":"Castel Volturno",
    "sg:classifiers":[
        {
            "category":"Banks & Credit Unions",
            "subcategory":"Bank",
            "type":"Services"
        }
    ],
    "sg:phone":"+39 081 509 4126",
    "sg:postcode":"81030",
    "sg:province":"Caserta",
    "wof:name":"Banco Di Napoli Spa",
    "wof:placetype":"venue"
},
  "geometry": {"coordinates":[13.984654,40.974518],"type":"Point"}
}