{
  "type": "Feature",
  "properties": {
    "addr:full":"Via Henry Dunant 25 46040 Guidizzolo Guidizzolo Mantova 46040",
    "addr:housenumber":"25",
    "addr:postcode":"46040;46040",
    "addr:street":"Via Henry Dunant",
    "iso:country":"IT",
    "sg:address":"Via Henry Dunant 25 46040 Guidizzolo",
    "sg:city":"Guidizzolo",
    "sg:orig_category":"Support Stockings, Support Tights",
    "sg:phone":"+39 0376 818753",
    "sg:postcode":"46040",
    "sg:province":"Mantova",
    "sg:website":"www.laboratoripiazza.it",
    "wof:name":"Laboratori Piazza Di Piazza Dario & C. Snc",
    "wof:placetype":"venue"
},
  "geometry": {"coordinates":[10.564227,45.327572],"type":"Point"}
}