{
  "type": "Feature",
  "properties": {
    "addr:full":"40059 Medicina Medicina Bologna 40059",
    "addr:postcode":"40059;40059",
    "iso:country":"IT",
    "sg:address":"40059 Medicina",
    "sg:city":"Medicina",
    "sg:orig_category":"Biancheria Intima Ed Abbigliamento Intimo - Produzione E Ingrosso",
    "sg:phone":"+39 051 851250",
    "sg:postcode":"40059",
    "sg:province":"Bologna",
    "sg:website":"http://www.creazionianna.com",
    "wof:name":"Rambaldi Anna Maria",
    "wof:placetype":"venue"
},
  "geometry": {"coordinates":[11.366227,44.502678],"type":"Point"}
}