{
  "type": "Feature",
  "properties": {
    "addr:full":"10042 Nichelino Nichelino Torino 10042",
    "addr:postcode":"10042;10042",
    "iso:country":"IT",
    "sg:address":"10042 Nichelino",
    "sg:city":"Nichelino",
    "sg:orig_category":"Campeggio. Accessori Dei Mezzi Di Trasporto",
    "sg:phone":"+39 011 680 9426",
    "sg:postcode":"10042",
    "sg:province":"Torino",
    "wof:name":"Il Telone Srl",
    "wof:placetype":"venue"
},
  "geometry": {"coordinates":[7.621832,44.987347],"type":"Point"}
}