{
  "type": "Feature",
  "properties": {
    "addr:full":"9, Via Circonvallazione Ovest 47900 Rimini Rimini Rimini 47900",
    "addr:postcode":"47900;47900",
    "addr:street":"Via Circonvallazione Ovest",
    "iso:country":"IT",
    "sg:address":"9, Via Circonvallazione Ovest 47900 Rimini",
    "sg:city":"Rimini",
    "sg:classifiers":[
        {
            "category":"Manufacturing",
            "subcategory":"Metals",
            "type":"Manufacturing & Wholesale Goods"
        }
    ],
    "sg:phone":"+39 0541 741567",
    "sg:postcode":"47900",
    "sg:province":"Rimini",
    "sg:tags":[
        "metallurgy",
        "metalworking"
    ],
    "wof:name":"Sicof S.r.l.",
    "wof:placetype":"venue"
},
  "geometry": {"coordinates":[12.5268125534,44.067024231],"type":"Point"}
}