{
  "type": "Feature",
  "properties": {
    "iso:country":"IT",
    "sg:address":"70126 Bari",
    "sg:city":"Bari",
    "sg:orig_category":"Forniture E Prodotti Informatici. Forniture Per Uffici",
    "sg:phone":"+39 080 558 3943",
    "sg:postcode":"70126",
    "sg:province":"Bari",
    "sg:website":"http://www.hssystems.it",
    "wof:name":"H.s. Systems Srl",
    "wof:placetype":"venue"
},
  "geometry": {"coordinates":[16.8789901733,41.1152534485],"type":"Point"}
}