{
  "type": "Feature",
  "properties": {
    "addr:full":"3, Via Enrico Fermi 20040 Burago Di Molgora Burago di Molgora Milano 20040",
    "addr:postcode":"20040;20040",
    "addr:street":"Via Enrico Fermi",
    "iso:country":"IT",
    "sg:address":"3, Via Enrico Fermi 20040 Burago Di Molgora",
    "sg:city":"Burago di Molgora",
    "sg:classifiers":[
        {
            "category":"Professional",
            "subcategory":"Engineering",
            "type":"Services"
        }
    ],
    "sg:phone":"+39 39039625021",
    "sg:postcode":"20040",
    "sg:province":"Milano",
    "sg:tags":[
        "machine",
        "-",
        "mechanical"
    ],
    "wof:name":"Wagner Colora S.r.l.",
    "wof:placetype":"venue"
},
  "geometry": {"coordinates":[9.385162,45.590778],"type":"Point"}
}