{
  "type": "Feature",
  "properties": {
    "addr:full":"37126 Verona Verona Verona 37126",
    "addr:postcode":"37126;37126",
    "iso:country":"IT",
    "sg:address":"37126 Verona",
    "sg:city":"Verona",
    "sg:orig_category":"Cartotecnica E Servizi. Composizione, Stampa E Confezione. Forniture E Prodotti Informatici. Forniture Per Congressi, Fiere E Manifestazioni",
    "sg:phone":"+39 045 834 5082",
    "sg:postcode":"37126",
    "sg:province":"Verona",
    "sg:website":"http://www.bvasystems.it",
    "wof:name":"B.v.a. Systems Snc",
    "wof:placetype":"venue"
},
  "geometry": {"coordinates":[10.988317,45.447773],"type":"Point"}
}