{
  "type": "Feature",
  "properties": {
    "addr:full":"20081 Cassinetta Di Lugagnano Cassinetta di Lugagnano Milano 20081",
    "addr:postcode":"20081;20081",
    "addr:street":"Di Lugagnano",
    "iso:country":"IT",
    "sg:address":"20081 Cassinetta Di Lugagnano",
    "sg:city":"Cassinetta di Lugagnano",
    "sg:orig_category":"Articoli Per Imballaggio E Confezionamento",
    "sg:phone":"+39 02 947 0231",
    "sg:postcode":"20081",
    "sg:province":"Milano",
    "wof:name":"Baralan International (s.p.a.)",
    "wof:placetype":"venue"
},
  "geometry": {"coordinates":[8.909885,45.431976],"type":"Point"}
}