{
  "type": "Feature",
  "properties": {
    "iso:country":"IT",
    "sg:address":"40062 Molinella",
    "sg:city":"Molinella",
    "sg:orig_category":"Acque Minerali E Bevande, Naturali E Gassate - Commercio",
    "sg:phone":"+39 051 690 8611",
    "sg:postcode":"40062",
    "sg:province":"Bologna",
    "wof:name":"Diolaiti Stefano - La Fonte",
    "wof:placetype":"venue"
},
  "geometry": {"coordinates":[11.649801,44.649323],"type":"Point"}
}