{
  "type": "Feature",
  "properties": {
    "iso:country":"IT",
    "sg:address":"20099 Sesto San Giovanni",
    "sg:city":"Sesto San Giovanni",
    "sg:orig_category":"Macchine, Impianti E Forniture Per Industria Grafica, Cartaria E Cartotecnica",
    "sg:phone":"+39 02 262381",
    "sg:postcode":"20099",
    "sg:province":"Milano",
    "wof:name":"Bobst Italiana S.p.a.",
    "wof:placetype":"venue"
},
  "geometry": {"coordinates":[9.25841,45.528767],"type":"Point"}
}