{
  "type": "Feature",
  "properties": {
    "addr:full":"30020 Marcon Marcon Venezia 30020",
    "addr:postcode":"30020;30020",
    "iso:country":"IT",
    "sg:address":"30020 Marcon",
    "sg:city":"Marcon",
    "sg:orig_category":"Prodotti Vari In Metallo. Articoli Per Imballaggio E Confezionamento",
    "sg:phone":"+39 041 595 1025",
    "sg:postcode":"30020",
    "sg:province":"Venezia",
    "wof:name":"Presley Flight-case S.n.c.",
    "wof:placetype":"venue"
},
  "geometry": {"coordinates":[12.2786684036,45.557674408],"type":"Point"}
}