{
  "type": "Feature",
  "properties": {
    "iso:country":"IT",
    "sg:address":"20040 Burago Di Molgora",
    "sg:city":"Burago di Molgora",
    "sg:classifiers":[
        {
            "category":"Shopping",
            "subcategory":"Stationery & Office Supplies",
            "type":"Retail Goods"
        }
    ],
    "sg:phone":"+39 039 68301",
    "sg:postcode":"20040",
    "sg:province":"Milano",
    "sg:tags":[
        "activities",
        "commercial",
        "packaging",
        "packing",
        "materials",
        "artisan",
        "supplies"
    ],
    "wof:name":"Cartongraf Spa",
    "wof:placetype":"venue"
},
  "geometry": {"coordinates":[9.3783512115,45.5963668823],"type":"Point"}
}