{
  "type": "Feature",
  "properties": {
    "addr:full":"73031 Alessano Alessano Lecce 73031",
    "addr:postcode":"73031;73031",
    "iso:country":"IT",
    "sg:address":"73031 Alessano",
    "sg:city":"Alessano",
    "sg:orig_category":"Filati E Materie Prime Tessili",
    "sg:phone":"+39 0833 522081",
    "sg:postcode":"73031",
    "sg:province":"Lecce",
    "wof:name":"Mar.cop. (s.n.c.)",
    "wof:placetype":"venue"
},
  "geometry": {"coordinates":[18.338766098,39.8776054382],"type":"Point"}
}