{
  "type": "Feature",
  "properties": {
    "addr:full":"Via Furlanelli 96 20034 Giussano Giussano Milano 20034",
    "addr:housenumber":"96",
    "addr:postcode":"20034;20034",
    "addr:street":"Via Furlanelli",
    "iso:country":"IT",
    "sg:address":"Via Furlanelli 96 20034 Giussano",
    "sg:city":"Giussano",
    "sg:classifiers":[
        {
            "category":"Home & Garden",
            "subcategory":"Furniture",
            "type":"Retail Goods"
        }
    ],
    "sg:phone":"+39 036 23171",
    "sg:postcode":"20034",
    "sg:province":"Milano",
    "sg:tags":[
        "small",
        "occasional"
    ],
    "sg:website":"www.rimadesio.it",
    "wof:name":"Rimadesio S.p.a.",
    "wof:placetype":"venue"
},
  "geometry": {"coordinates":[9.2138366699,45.6862258911],"type":"Point"}
}