{
  "type": "Feature",
  "properties": {
    "addr:full":"41/a, V. Gargn\u00e0 25078 Vestone Vestone Brescia 25078",
    "addr:housenumber":"41 / a",
    "addr:postcode":"25078;25078",
    "addr:street":"V. Gargna\u0300",
    "iso:country":"IT",
    "sg:address":"41/a, V. Gargn\u00e0 25078 Vestone",
    "sg:city":"Vestone",
    "sg:classifiers":[
        {
            "category":"Shopping",
            "type":"Retail Goods"
        }
    ],
    "sg:phone":"+39 39036581481",
    "sg:postcode":"25078",
    "sg:province":"Brescia",
    "sg:tags":[
        "finished",
        "-",
        "metallic"
    ],
    "sg:website":"http://www.rivadossi.it",
    "wof:name":"Rivadossi Sandro & C. Snc",
    "wof:placetype":"venue"
},
  "geometry": {"coordinates":[10.2229576111,45.5398292542],"type":"Point"}
}