{
  "type": "Feature",
  "properties": {
    "iso:country":"IT",
    "sg:address":"26100 Cremona",
    "sg:city":"Cremona",
    "sg:orig_category":"Acciaierie E Fonderie",
    "sg:phone":"+39 0372 460470",
    "sg:postcode":"26100",
    "sg:province":"Cremona",
    "sg:website":"http://www.boccacci.com",
    "wof:name":"Fonderia Artistica Luigi Boccacci Snc",
    "wof:placetype":"venue"
},
  "geometry": {"coordinates":[10.03255,45.140419],"type":"Point"}
}