{
  "type": "Feature",
  "properties": {
    "addr:full":"1, Via Tagliaferro 13019 Varallo Varallo Vercelli 13019",
    "addr:postcode":"13019;13019",
    "addr:street":"Via Tagliaferro",
    "iso:country":"IT",
    "sg:address":"1, Via Tagliaferro 13019 Varallo",
    "sg:city":"Varallo",
    "sg:classifiers":[
        {
            "category":"Manufacturing",
            "subcategory":"Metals",
            "type":"Manufacturing & Wholesale Goods"
        }
    ],
    "sg:phone":"+39 39016354594",
    "sg:postcode":"13019",
    "sg:province":"Vercelli",
    "sg:tags":[
        "metallurgy",
        "metalworking"
    ],
    "wof:name":"Valfond (s.r.l.)",
    "wof:placetype":"venue"
},
  "geometry": {"coordinates":[8.2742824554,45.7818145752],"type":"Point"}
}