{
  "type": "Feature",
  "properties": {
    "addr:full":"70122 Bari Bari Bari 70122",
    "addr:postcode":"70122;70122",
    "iso:country":"IT",
    "sg:address":"70122 Bari",
    "sg:city":"Bari",
    "sg:orig_category":"Salotti, Poltrone, Sedie E Tavoli",
    "sg:phone":"+39 080 524 4824",
    "sg:postcode":"70122",
    "sg:province":"Bari",
    "wof:name":"Interni & Design Di Scivittaro Roberto",
    "wof:placetype":"venue"
},
  "geometry": {"coordinates":[16.861511,41.122364],"type":"Point"}
}