{
  "type": "Feature",
  "properties": {
    "addr:full":"20048 Carate Brianza Carate Brianza Milano 20048",
    "addr:postcode":"20048;20048",
    "iso:country":"IT",
    "sg:address":"20048 Carate Brianza",
    "sg:city":"Carate Brianza",
    "sg:orig_category":"Impiallacciature",
    "sg:phone":"+39 036 280 5080",
    "sg:postcode":"20048",
    "sg:province":"Milano",
    "wof:name":"Strada Legnami Srl",
    "wof:placetype":"venue"
},
  "geometry": {"coordinates":[9.235467,45.677937],"type":"Point"}
}