{
  "type": "Feature",
  "properties": {
    "addr:full":"90013 Castelbuono Castelbuono Palermo 90013",
    "addr:postcode":"90013;90013",
    "iso:country":"IT",
    "sg:address":"90013 Castelbuono",
    "sg:city":"Castelbuono",
    "sg:orig_category":"Ferramenta - Vendita Al Dettaglio",
    "sg:phone":"+39 0921 671185",
    "sg:postcode":"90013",
    "sg:province":"Palermo",
    "wof:name":"Mazzola Michele",
    "wof:placetype":"venue"
},
  "geometry": {"coordinates":[13.3348321915,38.1383247375],"type":"Point"}
}