{
  "type": "Feature",
  "properties": {
    "iso:country":"IT",
    "sg:address":"2, Via Dei Saraceni 90040 Isola Delle Femmine",
    "sg:city":"Isola delle Femmine",
    "sg:classifiers":[
        {
            "category":"Travel",
            "subcategory":"Travel Agent",
            "type":"Entertainment"
        }
    ],
    "sg:phone":"+39 091 867 1538",
    "sg:postcode":"90040",
    "sg:province":"Palermo",
    "sg:tags":[
        "business"
    ],
    "wof:name":"Sirenetta Holidays Srl",
    "wof:placetype":"venue"
},
  "geometry": {"coordinates":[13.24309,38.190945],"type":"Point"}
}