{
  "type": "Feature",
  "properties": {
    "iso:country":"IT",
    "sg:address":"25068 Sarezzo",
    "sg:city":"Sarezzo",
    "sg:orig_category":"Bagno - Accessori E Mobili",
    "sg:phone":"+39 030 890 0565",
    "sg:postcode":"25068",
    "sg:province":"Brescia",
    "sg:website":"http://www.allpe.it",
    "wof:name":"All.pe. Srl",
    "wof:placetype":"venue"
},
  "geometry": {"coordinates":[10.200973,45.662109],"type":"Point"}
}