{
  "type": "Feature",
  "properties": {
    "addr:full":"22074 Lomazzo Lomazzo Como 22074",
    "addr:postcode":"22074;22074",
    "iso:country":"IT",
    "sg:address":"22074 Lomazzo",
    "sg:city":"Lomazzo",
    "sg:orig_category":"Impianti, Attrezzature E Forniture Sanitarie Ed Ospedaliere",
    "sg:phone":"+39 02 9674 0751",
    "sg:postcode":"22074",
    "sg:province":"Como",
    "sg:website":"http://www.vyncit.com",
    "wof:name":"Vyncit",
    "wof:placetype":"venue"
},
  "geometry": {"coordinates":[9.041722,45.673779],"type":"Point"}
}