{
  "type": "Feature",
  "properties": {
    "addr:full":"Contrada Tiriti' 95040 Motta S. Anastasia Catania 95040",
    "addr:postcode":"95040;95040",
    "addr:street":"Contrada Tiriti '",
    "iso:country":"IT",
    "sg:address":"Contrada Tiriti' 95040 Motta S. Anastasia",
    "sg:classifiers":[
        {
            "category":"Shopping",
            "subcategory":"Gifts & Souvenirs",
            "type":"Retail Goods"
        }
    ],
    "sg:phone":"+39 39095303510",
    "sg:postcode":"95040",
    "sg:province":"Catania",
    "wof:name":"Coimer (s.r.l.)",
    "wof:placetype":"venue"
},
  "geometry": {"coordinates":[14.996686,37.52026],"type":"Point"}
}