{
  "type": "Feature",
  "properties": {
    "addr:full":"58019 Monte Argentario Monte Argentario Grosseto 58019",
    "addr:housenumber":"58019",
    "addr:postcode":"58019",
    "addr:street":"Monte",
    "iso:country":"IT",
    "sg:address":"58019 Monte Argentario",
    "sg:city":"Monte Argentario",
    "sg:orig_category":"Servizi Per Lo Sport E Il Tempo Libero. Servizi Ausiliari Dei Mezzi Di Trasporto",
    "sg:phone":"+39 0564 814780",
    "sg:postcode":"58019",
    "sg:province":"Grosseto",
    "wof:name":"Motonautica Argentario Srl",
    "wof:placetype":"venue"
},
  "geometry": {"coordinates":[11.121688,42.432335],"type":"Point"}
}