{
  "type": "Feature",
  "properties": {
    "iso:country":"IT",
    "sg:address":"23, Via Lemerle Fraz. Voltri 16158 Genova",
    "sg:city":"Genova",
    "sg:classifiers":[
        {
            "category":"Utilities",
            "subcategory":"Telephone",
            "type":"Services"
        }
    ],
    "sg:phone":"+39 010 613 5134",
    "sg:postcode":"16158",
    "sg:province":"Genova",
    "sg:tags":[
        "telecommunication"
    ],
    "wof:name":"Self - Sime",
    "wof:placetype":"venue"
},
  "geometry": {"coordinates":[8.933989,44.407063],"type":"Point"}
}