{
  "type": "Feature",
  "properties": {
    "addr:full":"85057 Tramutola Tramutola Potenza 85057",
    "addr:postcode":"85057;85057",
    "iso:country":"IT",
    "sg:address":"85057 Tramutola",
    "sg:city":"Tramutola",
    "sg:orig_category":"Metalli E Leghe",
    "sg:phone":"+39 0975 354366",
    "sg:postcode":"85057",
    "sg:province":"Potenza",
    "wof:name":"Breda Energia-sesto Industria Spa",
    "wof:placetype":"venue"
},
  "geometry": {"coordinates":[15.7703285217,40.3235397339],"type":"Point"}
}