{
  "type": "Feature",
  "properties": {
    "addr:full":"06126 Perugia Perugia Perugia 06126",
    "addr:postcode":"06126;06126",
    "iso:country":"IT",
    "sg:address":"06126 Perugia",
    "sg:city":"Perugia",
    "sg:orig_category":"Servizi Per Lo Sport E Il Tempo Libero. Ristoranti Ed Esercizi Affini. Servizi Ausiliari Di Ristorazione E Di Intrattenimento",
    "sg:phone":"+39 075 38710",
    "sg:postcode":"06126",
    "sg:province":"Perugia",
    "sg:website":"http://www.darwin.it/etoile",
    "wof:name":"B.r.c. Sas Management",
    "wof:placetype":"venue"
},
  "geometry": {"coordinates":[12.401703,43.063652],"type":"Point"}
}