{
  "type": "Feature",
  "properties": {
    "addr:full":"16, Via Parini Giuseppe 09045 Quartu Sant'elena Cagliari 09045",
    "addr:postcode":"09045;09045",
    "addr:street":"Via Parini Giuseppe",
    "iso:country":"IT",
    "sg:address":"16, Via Parini Giuseppe 09045 Quartu Sant'elena",
    "sg:classifiers":[
        {
            "category":"Professional",
            "subcategory":"Engineering",
            "type":"Services"
        }
    ],
    "sg:phone":"+39 39070821529",
    "sg:postcode":"09045",
    "sg:province":"Cagliari",
    "sg:tags":[
        "machine",
        "-",
        "mechanical"
    ],
    "wof:name":"C.i.e.m. S.r.l.",
    "wof:placetype":"venue"
},
  "geometry": {"coordinates":[9.17779,39.236603],"type":"Point"}
}