{
  "type": "Feature",
  "properties": {
    "iso:country":"IT",
    "sg:address":"Corso L Longhi 35; Moneglia; 16030",
    "sg:city":"Moneglia",
    "sg:classifiers":[
        {
            "category":"Banks & Credit Unions",
            "subcategory":"Bank",
            "type":"Services"
        }
    ],
    "sg:phone":"+39 0185 49666",
    "sg:postcode":"16030",
    "sg:province":"Genova",
    "wof:name":"Banca Carige Spa",
    "wof:placetype":"venue"
},
  "geometry": {"coordinates":[9.489863,44.238819],"type":"Point"}
}