{
  "type": "Feature",
  "properties": {
    "iso:country":"IT",
    "sg:address":"38057 Pergine Valsugana",
    "sg:city":"Pergine Valsugana",
    "sg:orig_category":"Elettronica Professionale E Di Consumo. Automazione E Macchine Per Ufficio. Forniture Per Congressi, Fiere E Manifestazioni",
    "sg:phone":"+39 0461 534266",
    "sg:postcode":"38057",
    "sg:province":"Trento",
    "wof:name":"Giochimpara Di Da Ronch A. & Scmidt M. (s.n.c.)",
    "wof:placetype":"venue"
},
  "geometry": {"coordinates":[11.232936,46.063148],"type":"Point"}
}