{
  "type": "Feature",
  "properties": {
    "iso:country":"IT",
    "sg:address":"20124 Milano",
    "sg:city":"Milano",
    "sg:orig_category":"Servizi E Lavori Per Abbigliamento E Pelletterie",
    "sg:phone":"+39 02 201690",
    "sg:postcode":"20124",
    "sg:province":"Milano",
    "wof:name":"Futura 2000 Di Gogulescu Doina E Medici Annamaria S.d.f",
    "wof:placetype":"venue"
},
  "geometry": {"coordinates":[9.205507,45.477879],"type":"Point"}
}