{
  "type": "Feature",
  "properties": {
    "iso:country":"IT",
    "sg:address":"Corso Della Repubblica 38; Macerata; 62100",
    "sg:city":"Macerata",
    "sg:classifiers":[
        {
            "category":"Banks & Credit Unions",
            "subcategory":"Bank",
            "type":"Services"
        }
    ],
    "sg:phone":"+39 0733 426227",
    "sg:postcode":"62100",
    "sg:province":"Macerata",
    "wof:name":"Istituto Di Credito Fondiario",
    "wof:placetype":"venue"
},
  "geometry": {"coordinates":[13.452343,43.299538],"type":"Point"}
}