{
  "type": "Feature",
  "properties": {
    "iso:country":"IT",
    "sg:address":"44, Viale Pacinotti Antonio 51100 Pistoia",
    "sg:city":"Pistoia",
    "sg:classifiers":[
        {
            "category":"Professional",
            "subcategory":"Printing & Photocopies",
            "type":"Services"
        }
    ],
    "sg:phone":"+39 39057326702",
    "sg:postcode":"51100",
    "sg:province":"Pistoia",
    "wof:name":"Tipografia Artigiana Srl",
    "wof:placetype":"venue"
},
  "geometry": {"coordinates":[10.9185237885,43.9321556091],"type":"Point"}
}