{
  "type": "Feature",
  "properties": {
    "addr:full":"18039 Ventimiglia Ventimiglia Imperia 18039",
    "addr:postcode":"18039;18039",
    "iso:country":"IT",
    "sg:address":"18039 Ventimiglia",
    "sg:city":"Ventimiglia",
    "sg:orig_category":"Pubblica Amministrazione",
    "sg:phone":"+39 0184 250723",
    "sg:postcode":"18039",
    "sg:province":"Imperia",
    "wof:name":"Corpo Forestale Dello Stato Comando Stazione Di Ventimiglia",
    "wof:placetype":"venue"
},
  "geometry": {"coordinates":[8.0008392334,43.8686294556],"type":"Point"}
}