{
  "type": "Feature",
  "properties": {
    "iso:country":"IT",
    "sg:address":"Via Nazionale, N. 239/241 S.s.18 4 84015 Nocera Superiore",
    "sg:city":"Nocera Superiore",
    "sg:classifiers":[
        {
            "category":"Food & Beverages",
            "subcategory":"Fruits & Vegetables",
            "type":"Retail Goods"
        }
    ],
    "sg:phone":"+39 081 935010",
    "sg:postcode":"84015",
    "sg:province":"Salerno",
    "sg:tags":[
        "canned"
    ],
    "wof:name":"Elvea S.r.l.",
    "wof:placetype":"venue"
},
  "geometry": {"coordinates":[14.765912,40.677956],"type":"Point"}
}