{
  "type": "Feature",
  "properties": {
    "addr:full":"9, Viale Dell' Industria 37135 Verona Verona Verona 37135",
    "addr:postcode":"37135;37135",
    "addr:street":"Viale Dell ' Industria",
    "iso:country":"IT",
    "sg:address":"9, Viale Dell' Industria 37135 Verona",
    "sg:city":"Verona",
    "sg:classifiers":[
        {
            "category":"Manufacturing",
            "subcategory":"Food",
            "type":"Manufacturing & Wholesale Goods"
        }
    ],
    "sg:phone":"+39 045 828 9111",
    "sg:postcode":"37135",
    "sg:province":"Verona",
    "sg:tags":[
        "equipment",
        "processing",
        "-",
        "machinery"
    ],
    "wof:name":"Polin Ing. & C. S.p.a.",
    "wof:placetype":"venue"
},
  "geometry": {"coordinates":[10.9824056625,45.4125785828],"type":"Point"}
}