{
  "type": "Feature",
  "properties": {
    "addr:full":"11, Via Bacchiglione 35030 Cervarese Santa Croce Cervarese Santa Croce Padova 35030",
    "addr:postcode":"35030;35030",
    "addr:street":"Via Bacchiglione",
    "iso:country":"IT",
    "sg:address":"11, Via Bacchiglione 35030 Cervarese Santa Croce",
    "sg:city":"Cervarese Santa Croce",
    "sg:classifiers":[
        {
            "category":"Shopping",
            "type":"Retail Goods"
        }
    ],
    "sg:phone":"+39 049 991 5288",
    "sg:postcode":"35030",
    "sg:province":"Padova",
    "sg:tags":[
        "finished",
        "-",
        "metallic"
    ],
    "wof:name":"S.a.f.o.r. (s.r.l.)",
    "wof:placetype":"venue"
},
  "geometry": {"coordinates":[11.6921253204,45.4203681946],"type":"Point"}
}