{
  "type": "Feature",
  "properties": {
    "iso:country":"IT",
    "sg:address":"10026 Santena",
    "sg:city":"Santena",
    "sg:orig_category":"Pubblica Amministrazione",
    "sg:phone":"+39 011 945 4432",
    "sg:postcode":"10026",
    "sg:province":"Torino",
    "wof:name":"Associazione Nazionale Vigili Del Fuoco Volontari",
    "wof:placetype":"venue"
},
  "geometry": {"coordinates":[7.6950268745,45.0981864929],"type":"Point"}
}