{
  "type": "Feature",
  "properties": {
    "addr:full":"1, Via Del Progresso 42015 Correggio Reggio Nell'Emilia 42015",
    "addr:postcode":"42015;42015",
    "addr:street":"Via Del Progresso",
    "iso:country":"IT",
    "sg:address":"1, Via Del Progresso 42015 Correggio",
    "sg:classifiers":[
        {
            "category":"Shopping",
            "type":"Retail Goods"
        }
    ],
    "sg:phone":"+39 0522 637763",
    "sg:postcode":"42015",
    "sg:province":"Reggio Nell'Emilia",
    "sg:tags":[
        "finished",
        "-",
        "metallic"
    ],
    "wof:name":"Modelleria Brambilla S.r.l.",
    "wof:placetype":"venue"
},
  "geometry": {"coordinates":[10.8233661652,44.7714080811],"type":"Point"}
}