{
  "type": "Feature",
  "properties": {
    "addr:full":"20, Via Manzoni 20055 Renate Renate Milano 20055",
    "addr:postcode":"20055;20055",
    "addr:street":"Via Manzoni",
    "iso:country":"IT",
    "sg:address":"20, Via Manzoni 20055 Renate",
    "sg:city":"Renate",
    "sg:classifiers":[
        {
            "category":"Shopping",
            "type":"Retail Goods"
        }
    ],
    "sg:phone":"+39 036 292 5088",
    "sg:postcode":"20055",
    "sg:province":"Milano",
    "sg:tags":[
        "finished",
        "-",
        "metallic"
    ],
    "wof:name":"Siab - Magni Rolando S.r.l.",
    "wof:placetype":"venue"
},
  "geometry": {"coordinates":[9.2856969833,45.728717804],"type":"Point"}
}