{
  "type": "Feature",
  "properties": {
    "iso:country":"IT",
    "sg:address":"37017 Lazise",
    "sg:city":"Lazise",
    "sg:orig_category":"Nautica. Automobili E Mezzi Di Trasporto",
    "sg:phone":"+39 045 759 0098",
    "sg:postcode":"37017",
    "sg:province":"Verona",
    "wof:name":"Nautica Casarola (s.r.l.)",
    "wof:placetype":"venue"
},
  "geometry": {"coordinates":[10.716956,45.485691],"type":"Point"}
}