{
  "type": "Feature",
  "properties": {
    "iso:country":"IT",
    "sg:address":"28021 Borgomanero",
    "sg:city":"Borgomanero",
    "sg:orig_category":"Forniture Per Attivita' Industriali",
    "sg:phone":"+39 0322 846744",
    "sg:postcode":"28021",
    "sg:province":"Novara",
    "wof:name":"Pastore Carmelo Fabrizio & C. Sas",
    "wof:placetype":"venue"
},
  "geometry": {"coordinates":[8.455947876,45.7103614807],"type":"Point"}
}