{
  "type": "Feature",
  "properties": {
    "addr:full":"91025 Marsala Marsala Trapani 91025",
    "addr:postcode":"91025;91025",
    "iso:country":"IT",
    "sg:address":"91025 Marsala",
    "sg:city":"Marsala",
    "sg:orig_category":"Petroli, Gas E Combustibili. Materiali Edili",
    "sg:phone":"+39 0923 741521",
    "sg:postcode":"91025",
    "sg:province":"Trapani",
    "wof:name":"Giacalone Salvatore",
    "wof:placetype":"venue"
},
  "geometry": {"coordinates":[12.5150632858,37.7250137329],"type":"Point"}
}