{
  "type": "Feature",
  "properties": {
    "iso:country":"IT",
    "sg:address":"Via Marconi 2; Porto Santo Stefano; 58019",
    "sg:city":"Porto Santo Stefano",
    "sg:classifiers":[
        {
            "category":"Banks & Credit Unions",
            "subcategory":"Bank",
            "type":"Services"
        }
    ],
    "sg:phone":"+39 0564 818683",
    "sg:postcode":"58019",
    "sg:province":"Grosseto",
    "wof:name":"Banca Toscana Spa",
    "wof:placetype":"venue"
},
  "geometry": {"coordinates":[11.122231,42.433395],"type":"Point"}
}