{
  "type": "Feature",
  "properties": {
    "iso:country":"IT",
    "sg:address":"46, Via Gualco 16165 Genova",
    "sg:city":"Genova",
    "sg:classifiers":[
        {
            "category":"Food & Beverages",
            "subcategory":"Groceries & Convenience Stores",
            "type":"Retail Goods"
        }
    ],
    "sg:phone":"+39 39800812088",
    "sg:postcode":"16165",
    "sg:province":"Genova",
    "sg:tags":[
        "product",
        "related"
    ],
    "wof:name":"So.ge.gross (s.a.s.)",
    "wof:placetype":"venue"
},
  "geometry": {"coordinates":[9.0037021637,44.4460945129],"type":"Point"}
}