{
  "type": "Feature",
  "properties": {
    "addr:full":"61100 Pesaro Pesaro Pesaro E Urbino 61100",
    "addr:postcode":"61100;61100",
    "iso:country":"IT",
    "sg:address":"61100 Pesaro",
    "sg:city":"Pesaro",
    "sg:orig_category":"Poltrone E Divani - Produzione E Ingrosso",
    "sg:phone":"+39 0721 283285",
    "sg:postcode":"61100",
    "sg:province":"Pesaro E Urbino",
    "wof:name":"Ark Linea Mobili Imbottiti Di Amantini Ermes & C. Snc",
    "wof:placetype":"venue"
},
  "geometry": {"coordinates":[12.8575725555,43.8792495728],"type":"Point"}
}