{
  "type": "Feature",
  "properties": {
    "iso:country":"IT",
    "sg:address":"41100 Modena",
    "sg:city":"Modena",
    "sg:orig_category":"Ceramiche Per Pavimenti E Rivestimenti - Produzione E Ingrosso",
    "sg:phone":"+39 059 881411",
    "sg:postcode":"41100",
    "sg:province":"Modena",
    "sg:website":"http://www.poliscer.it",
    "wof:name":"Polis Manifatture Ceramiche Spa",
    "wof:placetype":"venue"
},
  "geometry": {"coordinates":[10.929328,44.642517],"type":"Point"}
}