{
  "type": "Feature",
  "properties": {
    "addr:full":"45, V. I Maggio 20021 Baranzate Di Bollate Baranzate Milano 20021",
    "addr:housenumber":"45",
    "addr:postcode":"20021;20021",
    "addr:street":"V. I Maggio",
    "iso:country":"IT",
    "sg:address":"45, V. I Maggio 20021 Baranzate Di Bollate",
    "sg:city":"Baranzate",
    "sg:classifiers":[
        {
            "category":"Professional",
            "subcategory":"Printing & Photocopies",
            "type":"Services"
        }
    ],
    "sg:phone":"+39 39023822111",
    "sg:postcode":"20021",
    "sg:province":"Milano",
    "sg:website":"http://www.tipolitomaggioni.it",
    "wof:name":"Tipolito Maggioni",
    "wof:placetype":"venue"
},
  "geometry": {"coordinates":[9.1174564362,45.5234069824],"type":"Point"}
}