{
  "type": "Feature",
  "properties": {
    "addr:full":"Piazza Della Liberta 42; Alessandria",
    "addr:housenumber":"42",
    "addr:street":"Piazza Della Liberta",
    "iso:country":"IT",
    "sg:address":"Piazza Della Liberta 42; Alessandria",
    "sg:classifiers":[
        {
            "category":"Banks & Credit Unions",
            "subcategory":"Bank",
            "type":"Services"
        }
    ],
    "sg:phone":"+39 0131 445295",
    "wof:name":"Banca Popolare Di Lodi",
    "wof:placetype":"venue"
},
  "geometry": {"coordinates":[8.615147,44.913227],"type":"Point"}
}