{
  "type": "Feature",
  "properties": {
    "iso:country":"IT",
    "sg:address":"37019 Peschiera Del Garda",
    "sg:city":"Peschiera del Garda",
    "sg:classifiers":[
        {
            "category":"Restaurant",
            "type":"Food & Drink"
        }
    ],
    "sg:phone":"+39 045 755 0279",
    "sg:postcode":"37019",
    "sg:province":"Verona",
    "sg:tags":[
        "auxiliary",
        "entertainment",
        "premises",
        "related",
        "catering",
        "similar",
        "public",
        "restaurants"
    ],
    "wof:name":"Hotel Ristorante Belvedere",
    "wof:placetype":"venue"
},
  "geometry": {"coordinates":[10.657769,45.453434],"type":"Point"}
}