{
  "type": "Feature",
  "properties": {
    "iso:country":"IT",
    "sg:address":"37011 Bardolino",
    "sg:city":"Bardolino",
    "sg:orig_category":"Macchine, Impianti E Forniture Per Industria Grafica, Cartaria E Cartotecnica",
    "sg:phone":"+39 045 721 1200",
    "sg:postcode":"37011",
    "sg:province":"Verona",
    "wof:name":"Papiria (s.r.l.)",
    "wof:placetype":"venue"
},
  "geometry": {"coordinates":[10.727128,45.549782],"type":"Point"}
}