{
  "type": "Feature",
  "properties": {
    "addr:full":"90018 Termini Imerese Termini Imerese Palermo 90018",
    "addr:postcode":"90018;90018",
    "iso:country":"IT",
    "sg:address":"90018 Termini Imerese",
    "sg:city":"Termini Imerese",
    "sg:orig_category":"Motori Fuoribordo",
    "sg:phone":"+39 091 814 6349",
    "sg:postcode":"90018",
    "sg:province":"Palermo",
    "wof:name":"Iuculano Rosario",
    "wof:placetype":"venue"
},
  "geometry": {"coordinates":[13.455780983,38.0676422119],"type":"Point"}
}