{
  "type": "Feature",
  "properties": {
    "iso:country":"IT",
    "sg:address":"24, Via Carducci Giosue' 20123 Milano",
    "sg:city":"Milano",
    "sg:classifiers":[
        {
            "category":"Professional",
            "subcategory":"Engineering",
            "type":"Services"
        }
    ],
    "sg:phone":"+39 390 280 4331",
    "sg:postcode":"20123",
    "sg:province":"Milano",
    "sg:tags":[
        "machine",
        "-",
        "mechanical"
    ],
    "wof:name":"Torcitura Carlo Pessina",
    "wof:placetype":"venue"
},
  "geometry": {"coordinates":[9.174446,45.46384],"type":"Point"}
}