{
  "type": "Feature",
  "properties": {
    "iso:country":"IT",
    "sg:address":"Ctr Masseria Lotto 16 98047 Saponara",
    "sg:city":"Saponara",
    "sg:orig_category":"Earthmovers, Bulldozers, Dozers, Wheel Loaders",
    "sg:phone":"+39 090 336540",
    "sg:postcode":"98047",
    "sg:province":"Messina",
    "wof:name":"Edilmoviter-ricambi Di Battaglia An",
    "wof:placetype":"venue"
},
  "geometry": {"coordinates":[15.555523,38.192333],"type":"Point"}
}