{
  "type": "Feature",
  "properties": {
    "iso:country":"IT",
    "sg:address":"17, Via Delle Regioni 50052 Certaldo",
    "sg:city":"Certaldo",
    "sg:classifiers":[
        {
            "category":"Home & Garden",
            "subcategory":"Home Furnishings",
            "type":"Retail Goods"
        }
    ],
    "sg:phone":"+39 0571 668073",
    "sg:postcode":"50052",
    "sg:province":"Firenze",
    "sg:tags":[
        "household"
    ],
    "wof:name":"Arredospini & C. Srl",
    "wof:placetype":"venue"
},
  "geometry": {"coordinates":[11.030364,43.561401],"type":"Point"}
}