{
  "type": "Feature",
  "properties": {
    "addr:full":"3, Via G. Segusini 32036 Sedico Sedico Belluno 32036",
    "addr:postcode":"32036;32036",
    "addr:street":"Via G. Segusini",
    "iso:country":"IT",
    "sg:address":"3, Via G. Segusini 32036 Sedico",
    "sg:city":"Sedico",
    "sg:classifiers":[
        {
            "category":"Manufacturing",
            "subcategory":"Rubber & Plastics",
            "type":"Manufacturing & Wholesale Goods"
        }
    ],
    "sg:phone":"+39 0437 852421",
    "sg:postcode":"32036",
    "sg:province":"Belluno",
    "wof:name":"M.t.m. S.n.c.",
    "wof:placetype":"venue"
},
  "geometry": {"coordinates":[12.0973215103,46.1009407043],"type":"Point"}
}