{
  "type": "Feature",
  "properties": {
    "addr:full":"92020 S.giovanni Gemini Agrigento 92020",
    "addr:postcode":"92020;92020",
    "iso:country":"IT",
    "sg:address":"92020 S.giovanni Gemini",
    "sg:orig_category":"Forniture Per Edilizia E Lavori Pubblici",
    "sg:phone":"+39 0922 903324",
    "sg:postcode":"92020",
    "sg:province":"Agrigento",
    "wof:name":"Tagliareni Antonio",
    "wof:placetype":"venue"
},
  "geometry": {"coordinates":[13.5769557953,37.3111877441],"type":"Point"}
}