{
  "type": "Feature",
  "properties": {
    "iso:country":"IT",
    "sg:address":"20137 Milano",
    "sg:city":"Milano",
    "sg:orig_category":"Automobili - Commercio",
    "sg:phone":"+39 02 5410 8096",
    "sg:postcode":"20137",
    "sg:province":"Milano",
    "sg:website":"http://www.erremmeauto.it",
    "wof:name":"Erre Emme Auto Srl",
    "wof:placetype":"venue"
},
  "geometry": {"coordinates":[9.22368,45.452866],"type":"Point"}
}