{
  "type": "Feature",
  "properties": {
    "addr:full":"1, Via Alessandro Volta 35037 Teolo Teolo Padova 35037",
    "addr:postcode":"35037;35037",
    "addr:street":"Via Alessandro Volta",
    "iso:country":"IT",
    "sg:address":"1, Via Alessandro Volta 35037 Teolo",
    "sg:city":"Teolo",
    "sg:classifiers":[
        {
            "category":"Food & Beverages",
            "subcategory":"Groceries & Convenience Stores",
            "type":"Retail Goods"
        }
    ],
    "sg:phone":"+39 049 999 8411",
    "sg:postcode":"35037",
    "sg:province":"Padova",
    "sg:tags":[
        "product",
        "related"
    ],
    "wof:name":"Polo S.p.a.",
    "wof:placetype":"venue"
},
  "geometry": {"coordinates":[11.7768182755,45.3437004089],"type":"Point"}
}