{
  "type": "Feature",
  "properties": {
    "iso:country":"IT",
    "sg:address":"Via Delle Colline Livornesi 153 56030 Lari",
    "sg:orig_category":"Hoisiery Goods",
    "sg:phone":"+39 0587 423111",
    "sg:postcode":"56030",
    "sg:province":"Pisa",
    "sg:website":"www.eurimpex.it",
    "wof:name":"Eurimpex S.r.l.",
    "wof:placetype":"venue"
},
  "geometry": {"coordinates":[10.5937776566,43.5689086914],"type":"Point"}
}