{
  "type": "Feature",
  "properties": {
    "iso:country":"IT",
    "sg:address":"Via S. Pieretto 40 55060 Badia Cantignano",
    "sg:city":"Badia Cantignano",
    "sg:classifiers":[
        {
            "category":"Manufacturing",
            "subcategory":"Paper Products",
            "type":"Manufacturing & Wholesale Goods"
        }
    ],
    "sg:phone":"+39 0583 403370",
    "sg:postcode":"55060",
    "sg:province":"Lucca",
    "sg:tags":[
        "adhesive",
        "self-adhesive",
        "labels",
        "label"
    ],
    "sg:website":"www.centrostampa.it",
    "wof:name":"Centro Stampa Spa",
    "wof:placetype":"venue"
},
  "geometry": {"coordinates":[10.504339,43.810997],"type":"Point"}
}