{
  "type": "Feature",
  "properties": {
    "addr:full":"37135 Verona Verona Verona 37135",
    "addr:postcode":"37135;37135",
    "iso:country":"IT",
    "sg:address":"37135 Verona",
    "sg:city":"Verona",
    "sg:orig_category":"Macchine, Impianti Ed Attrezzature Industria Chimica. Attrezzature E Forniture Per Officine Riparazione E Servizi Ausiliari",
    "sg:phone":"+39 045 582872",
    "sg:postcode":"37135",
    "sg:province":"Verona",
    "wof:name":"Marini Nerio (s.n.c.)",
    "wof:placetype":"venue"
},
  "geometry": {"coordinates":[10.97267,45.409519],"type":"Point"}
}