{
  "type": "Feature",
  "properties": {
    "addr:full":"87/b, Via Tenna 63015 Monte Urano Monte Urano Ascoli Piceno 63015",
    "addr:housenumber":"87 / b",
    "addr:postcode":"63015;63015",
    "addr:street":"Via Tenna",
    "iso:country":"IT",
    "sg:address":"87/b, Via Tenna 63015 Monte Urano",
    "sg:city":"Monte Urano",
    "sg:classifiers":[
        {
            "category":"Building & Trades",
            "subcategory":"Construction",
            "type":"Services"
        }
    ],
    "sg:phone":"+39 0734 841808",
    "sg:postcode":"63015",
    "sg:province":"Ascoli Piceno",
    "sg:tags":[
        "work",
        "public"
    ],
    "wof:name":"Steca (s.p.a.)",
    "wof:placetype":"venue"
},
  "geometry": {"coordinates":[13.574977,42.8554],"type":"Point"}
}