{
  "type": "Feature",
  "properties": {
    "addr:full":"4, Via Circonvallazione 15100 Alessandria Alessandria Alessandria 15100",
    "addr:postcode":"15100;15100",
    "addr:street":"Via Circonvallazione",
    "iso:country":"IT",
    "sg:address":"4, Via Circonvallazione 15100 Alessandria",
    "sg:city":"Alessandria",
    "sg:orig_category":"Miscellaneous Products",
    "sg:phone":"+39 0131 618421",
    "sg:postcode":"15100",
    "sg:province":"Alessandria",
    "wof:name":"Marengo Imballaggi (s.r.l.)",
    "wof:placetype":"venue"
},
  "geometry": {"coordinates":[8.7073297501,44.8730278015],"type":"Point"}
}