{
  "type": "Feature",
  "properties": {
    "addr:full":"35018 San Martino Di Lupari San Martino di Lupari Padova 35018",
    "addr:housenumber":"35018",
    "addr:postcode":"di lupari;35018",
    "iso:country":"IT",
    "sg:address":"35018 San Martino Di Lupari",
    "sg:city":"San Martino di Lupari",
    "sg:orig_category":"Macchine, Impianti Ed Attrezzature Per Industria Alimentare E Bevande",
    "sg:phone":"+39 049 595 2200",
    "sg:postcode":"35018",
    "sg:province":"Padova",
    "wof:name":"Antonello Ivano & C. (s.n.c.)",
    "wof:placetype":"venue"
},
  "geometry": {"coordinates":[11.86155,45.644394],"type":"Point"}
}