{
  "type": "Feature",
  "properties": {
    "addr:full":"239, Viale De Gasperi 20010 Marcallo Con Casone Casone Milano 20010",
    "addr:postcode":"20010;20010",
    "addr:street":"Viale De Gasperi",
    "iso:country":"IT",
    "sg:address":"239, Viale De Gasperi 20010 Marcallo Con Casone",
    "sg:city":"Casone",
    "sg:classifiers":[
        {
            "category":"Manufacturing",
            "subcategory":"Paper Products",
            "type":"Manufacturing & Wholesale Goods"
        }
    ],
    "sg:phone":"+39 39029760621",
    "sg:postcode":"20010",
    "sg:province":"Milano",
    "sg:tags":[
        "cardboard"
    ],
    "wof:name":"Cartotecnica Magentina S.n.c.",
    "wof:placetype":"venue"
},
  "geometry": {"coordinates":[8.8698072433,45.4746170044],"type":"Point"}
}