{
  "type": "Feature",
  "properties": {
    "addr:full":"19, Via Giuseppe Bonzanni 24040 Bonate Sopra Bonate Sopra Bergamo 24040",
    "addr:postcode":"24040;24040",
    "addr:street":"Via Giuseppe Bonzanni;Sopra",
    "iso:country":"IT",
    "sg:address":"19, Via Giuseppe Bonzanni 24040 Bonate Sopra",
    "sg:city":"Bonate Sopra",
    "sg:classifiers":[
        {
            "category":"Shopping",
            "type":"Retail Goods"
        }
    ],
    "sg:phone":"+39 39035994341",
    "sg:postcode":"24040",
    "sg:province":"Bergamo",
    "sg:tags":[
        "finished",
        "-",
        "metallic"
    ],
    "wof:name":"Vero & Ceccarelli (s.n.c.)",
    "wof:placetype":"venue"
},
  "geometry": {"coordinates":[9.6699523926,45.6949043274],"type":"Point"}
}