{
  "type": "Feature",
  "properties": {
    "iso:country":"IT",
    "sg:address":"56012 Calcinaia",
    "sg:city":"Calcinaia",
    "sg:orig_category":"Fonderie",
    "sg:phone":"+39 0587 489105",
    "sg:postcode":"56012",
    "sg:province":"Pisa",
    "wof:name":"Meini Piero",
    "wof:placetype":"venue"
},
  "geometry": {"coordinates":[10.640583992,43.6781387329],"type":"Point"}
}