{
  "type": "Feature",
  "properties": {
    "iso:country":"IT",
    "sg:address":"10090 Rosta",
    "sg:city":"Rosta",
    "sg:orig_category":"Apparecchiature E Sistemi Per Magazzinaggio E Movimentazione",
    "sg:phone":"+39 011 956 7876",
    "sg:postcode":"10090",
    "sg:province":"Torino",
    "sg:website":"http://www.cmlcarrelli.com",
    "wof:name":"C.m.l. Snc",
    "wof:placetype":"venue"
},
  "geometry": {"coordinates":[7.466259,45.068909],"type":"Point"}
}