{
  "type": "Feature",
  "properties": {
    "addr:full":"50127 Firenze Firenze Firenze 50127",
    "addr:postcode":"50127;50127",
    "iso:country":"IT",
    "sg:address":"50127 Firenze",
    "sg:city":"Firenze",
    "sg:orig_category":"Non-classified Establishments",
    "sg:phone":"+39 055 453959",
    "sg:postcode":"50127",
    "sg:province":"Firenze",
    "wof:name":"Nuova Cartotecnica 89",
    "wof:placetype":"venue"
},
  "geometry": {"coordinates":[11.225395,43.810513],"type":"Point"}
}