{
  "type": "Feature",
  "properties": {
    "addr:full":"20138 Milano Milano Milano 20138",
    "addr:postcode":"20138;20138",
    "iso:country":"IT",
    "sg:address":"20138 Milano",
    "sg:city":"Milano",
    "sg:orig_category":"Servizi E Lavori Per Industria Alimentare E Bevande. Servizi E Lavori Per Abbigliamento E Pelletterie. Servizi E Lavori Per Arredamento E Industria Del Legno. Servizi Vari Di Interesse Pubblico",
    "sg:phone":"+39 02 506 5200",
    "sg:postcode":"20138",
    "sg:province":"Milano",
    "wof:name":"New Music International S.r.l.",
    "wof:placetype":"venue"
},
  "geometry": {"coordinates":[9.251227,45.453423],"type":"Point"}
}