{
  "type": "Feature",
  "properties": {
    "iso:country":"IT",
    "sg:address":"44100 Ferrara",
    "sg:city":"Ferrara",
    "sg:orig_category":"Articoli Da Regalo. Forniture Per Attivita' Commerciali Ed Artigianali",
    "sg:phone":"+39 0532 464198",
    "sg:postcode":"44100",
    "sg:province":"Ferrara",
    "wof:name":"Omniagross Srl",
    "wof:placetype":"venue"
},
  "geometry": {"coordinates":[11.603436,44.869839],"type":"Point"}
}