{
  "type": "Feature",
  "properties": {
    "addr:full":"80045 Pompei Pompei Napoli 80045",
    "addr:housenumber":"80045",
    "addr:postcode":"80045",
    "iso:country":"IT",
    "sg:address":"80045 Pompei",
    "sg:city":"Pompei",
    "sg:orig_category":"Servizi Culturali E Per Lo Spettacolo. Servizi Per Lo Sport E Il Tempo Libero. Associazioni Ed Organismi Di Interesse Pubblico",
    "sg:phone":"+39 081 850 4746",
    "sg:postcode":"80045",
    "sg:province":"Napoli",
    "wof:name":"Associazione Musicale Le Camenae",
    "wof:placetype":"venue"
},
  "geometry": {"coordinates":[14.505784,40.757622],"type":"Point"}
}