{
  "type": "Feature",
  "properties": {
    "addr:full":"10, Via Crocette 37060 Sona Sona Verona 37060",
    "addr:postcode":"37060;37060",
    "addr:street":"Via Crocette",
    "iso:country":"IT",
    "sg:address":"10, Via Crocette 37060 Sona",
    "sg:city":"Sona",
    "sg:classifiers":[
        {
            "category":"Manufacturing",
            "subcategory":"Rubber & Plastics",
            "type":"Manufacturing & Wholesale Goods"
        }
    ],
    "sg:phone":"+39 045 719 0280",
    "sg:postcode":"37060",
    "sg:province":"Verona",
    "wof:name":"C.i.b. Conservatori Industriali Brevettati (s.r.l.)",
    "wof:placetype":"venue"
},
  "geometry": {"coordinates":[10.9465675354,45.4481468201],"type":"Point"}
}