{
  "type": "Feature",
  "properties": {
    "addr:full":"23855 Pescate Pescate Lecco 23855",
    "addr:postcode":"23855;23855",
    "iso:country":"IT",
    "sg:address":"23855 Pescate",
    "sg:city":"Pescate",
    "sg:orig_category":"Pneumatici - Commercio E Riparazione",
    "sg:phone":"+39 0341 287652",
    "sg:postcode":"23855",
    "sg:province":"Lecco",
    "wof:name":"Sbs Di Parisi Giuseppe",
    "wof:placetype":"venue"
},
  "geometry": {"coordinates":[9.3953514099,45.832069397],"type":"Point"}
}