{
  "type": "Feature",
  "properties": {
    "iso:country":"IT",
    "sg:address":"00152 Roma",
    "sg:city":"Roma",
    "sg:classifiers":[
        {
            "category":"Health Services",
            "subcategory":"Health Practitioner",
            "type":"Services"
        }
    ],
    "sg:phone":"+39 06 588 0363",
    "sg:postcode":"00152",
    "sg:province":"Roma",
    "sg:tags":[
        "medici"
    ],
    "wof:name":"Athena Medici Associati - Lucantoni - Tollemeto",
    "wof:placetype":"venue"
},
  "geometry": {"coordinates":[12.460703,41.880817],"type":"Point"}
}