{
  "type": "Feature",
  "properties": {
    "iso:country":"IT",
    "sg:address":"10138 Torino",
    "sg:city":"Torino",
    "sg:orig_category":"Impiantistica E Prodotti Tecnologici Per Edilizia. Telecomunicazioni E Telefonia, Impianti, Apparecchi E Servizi",
    "sg:phone":"+39 011 434 0025",
    "sg:postcode":"10138",
    "sg:province":"Torino",
    "wof:name":"Euroelettrica Srl",
    "wof:placetype":"venue"
},
  "geometry": {"coordinates":[7.661275,45.071823],"type":"Point"}
}