{
  "type": "Feature",
  "properties": {
    "addr:full":"66, Via Rapisardi Mario 90144 Palermo Palermo Palermo 90144",
    "addr:postcode":"90144;90144",
    "addr:street":"Via Rapisardi Mario",
    "iso:country":"IT",
    "sg:address":"66, Via Rapisardi Mario 90144 Palermo",
    "sg:city":"Palermo",
    "sg:classifiers":[
        {
            "category":"Manufacturing",
            "subcategory":"Tools & Machinery",
            "type":"Manufacturing & Wholesale Goods"
        }
    ],
    "sg:phone":"+39 39091342185",
    "sg:postcode":"90144",
    "sg:province":"Palermo",
    "sg:tags":[
        "environment",
        "equipment",
        "-"
    ],
    "wof:name":"Chibivet S.r.l.",
    "wof:placetype":"venue"
},
  "geometry": {"coordinates":[13.361376,38.11562],"type":"Point"}
}