{
  "type": "Feature",
  "properties": {
    "iso:country":"IT",
    "sg:address":"7, Calle S. Giuseppe 30141 Venezia",
    "sg:city":"Venezia",
    "sg:classifiers":[
        {
            "category":"Manufacturing",
            "subcategory":"Glass & Minerals",
            "type":"Manufacturing & Wholesale Goods"
        }
    ],
    "sg:phone":"+39 39041736960",
    "sg:postcode":"30141",
    "sg:province":"Venezia",
    "wof:name":"Ars Murano (s.r.l.)",
    "wof:placetype":"venue"
},
  "geometry": {"coordinates":[12.354699,45.453114],"type":"Point"}
}