{
  "type": "Feature",
  "properties": {
    "addr:full":"10122 Torino Torino Torino 10122",
    "addr:housenumber":"10122",
    "addr:postcode":"10122",
    "iso:country":"IT",
    "sg:address":"10122 Torino",
    "sg:city":"Torino",
    "sg:orig_category":"Banche E Servizi Finanziari",
    "sg:phone":"+39 011 431 0463",
    "sg:postcode":"10122",
    "sg:province":"Torino",
    "wof:name":"Opera Nazionale Assistenza Orfani Sanitari Italiani",
    "wof:placetype":"venue"
},
  "geometry": {"coordinates":[7.680715,45.073292],"type":"Point"}
}