{
  "type": "Feature",
  "properties": {
    "iso:country":"IT",
    "sg:address":"Corso S. Fedi 33; Pistoia; 51100",
    "sg:city":"Pistoia",
    "sg:classifiers":[
        {
            "category":"Banks & Credit Unions",
            "subcategory":"Bank",
            "type":"Services"
        }
    ],
    "sg:phone":"+39 0573 3773",
    "sg:postcode":"51100",
    "sg:province":"Pistoia",
    "wof:name":"Credito Italiano Spa",
    "wof:placetype":"venue"
},
  "geometry": {"coordinates":[10.916739,43.930744],"type":"Point"}
}