{
  "type": "Feature",
  "properties": {
    "iso:country":"IT",
    "sg:address":"20131 Milano",
    "sg:city":"Milano",
    "sg:orig_category":"Climatizzazione E Condizionamento, Apparecchiature E Servizi",
    "sg:phone":"+39 02 236 0245",
    "sg:postcode":"20131",
    "sg:province":"Milano",
    "wof:name":"Mire S.r.l.",
    "wof:placetype":"venue"
},
  "geometry": {"coordinates":[9.231791,45.487091],"type":"Point"}
}