{
  "type": "Feature",
  "properties": {
    "iso:country":"IT",
    "sg:address":"10147 Torino",
    "sg:city":"Torino",
    "sg:orig_category":"Campeggio. Automobili E Mezzi Di Trasporto",
    "sg:phone":"+39 011 296471",
    "sg:postcode":"10147",
    "sg:province":"Torino",
    "wof:name":"Boutique Dell'auto",
    "wof:placetype":"venue"
},
  "geometry": {"coordinates":[7.676683,45.103016],"type":"Point"}
}