{
  "type": "Feature",
  "properties": {
    "iso:country":"IT",
    "sg:address":"22063 Cantu'",
    "sg:orig_category":"Minuterie Metalliche E Ferramenta",
    "sg:phone":"+39 031 714874",
    "sg:postcode":"22063",
    "sg:province":"Como",
    "wof:name":"Eurocondotte 2000 S.r.l.",
    "wof:placetype":"venue"
},
  "geometry": {"coordinates":[9.0981607437,45.7182884216],"type":"Point"}
}