{
  "type": "Feature",
  "properties": {
    "addr:full":"16128 Genova Genova Genova 16128",
    "addr:postcode":"16128;16128",
    "iso:country":"IT",
    "sg:address":"16128 Genova",
    "sg:city":"Genova",
    "sg:classifiers":[
        {
            "category":"Health Services",
            "subcategory":"Health Practitioner",
            "type":"Services"
        }
    ],
    "sg:phone":"+39 010 564256",
    "sg:postcode":"16128",
    "sg:province":"Genova",
    "sg:tags":[
        "medici"
    ],
    "wof:name":"Vittone Maurizio",
    "wof:placetype":"venue"
},
  "geometry": {"coordinates":[8.9369535446,44.4011611938],"type":"Point"}
}