{
  "type": "Feature",
  "properties": {
    "addr:full":"00159 Roma Roma Roma 00159",
    "addr:postcode":"00159;00159",
    "iso:country":"IT",
    "sg:address":"00159 Roma",
    "sg:city":"Roma",
    "sg:classifiers":[
        {
            "category":"Health Services",
            "subcategory":"Health Practitioner",
            "type":"Services"
        }
    ],
    "sg:phone":"+39 06 4353 4547",
    "sg:postcode":"00159",
    "sg:province":"Roma",
    "sg:tags":[
        "medici"
    ],
    "wof:name":"Iori Maria Antonietta",
    "wof:placetype":"venue"
},
  "geometry": {"coordinates":[12.537059,41.897202],"type":"Point"}
}