{
  "type": "Feature",
  "properties": {
    "iso:country":"IT",
    "sg:address":"10098 Rivoli",
    "sg:city":"Rivoli",
    "sg:orig_category":"Apparecchiature Oleodinamiche",
    "sg:phone":"+39 011 959 8500",
    "sg:postcode":"10098",
    "sg:province":"Torino",
    "wof:name":"Hydrolas Sas Di La Sana Luca E C.",
    "wof:placetype":"venue"
},
  "geometry": {"coordinates":[7.528754,45.060741],"type":"Point"}
}