{
  "type": "Feature",
  "properties": {
    "iso:country":"IT",
    "sg:address":"60, Via Della Produzione 61025 Montelabbate",
    "sg:city":"Montelabbate",
    "sg:classifiers":[
        {
            "category":"Home & Garden",
            "subcategory":"Home Furnishings",
            "type":"Retail Goods"
        }
    ],
    "sg:phone":"+39 0721 482595",
    "sg:postcode":"61025",
    "sg:province":"Pesaro E Urbino",
    "sg:tags":[
        "household"
    ],
    "wof:name":"Fb Mobili Beretta Srl",
    "wof:placetype":"venue"
},
  "geometry": {"coordinates":[12.818842,43.859337],"type":"Point"}
}