{
  "type": "Feature",
  "properties": {
    "addr:full":"41012 Carpi Carpi Modena 41012",
    "addr:postcode":"41012;41012",
    "iso:country":"IT",
    "sg:address":"41012 Carpi",
    "sg:city":"Carpi",
    "sg:classifiers":[
        {
            "category":"Health Services",
            "subcategory":"Health Practitioner",
            "type":"Services"
        }
    ],
    "sg:phone":"+39 059 684141",
    "sg:postcode":"41012",
    "sg:province":"Modena",
    "sg:tags":[
        "medici"
    ],
    "wof:name":"Greco Sergio",
    "wof:placetype":"venue"
},
  "geometry": {"coordinates":[10.897178,44.793327],"type":"Point"}
}