{
  "type": "Feature",
  "properties": {
    "iso:country":"IT",
    "sg:address":"Km. 11.500, Via Flaminia 00188 Roma",
    "sg:city":"Roma",
    "sg:classifiers":[
        {
            "category":"Communications",
            "subcategory":"Television Station",
            "type":"Services"
        }
    ],
    "sg:phone":"+39 06 3362 4240",
    "sg:postcode":"00188",
    "sg:province":"Roma",
    "sg:tags":[
        "audio-visual"
    ],
    "wof:name":"Transvideo Srl",
    "wof:placetype":"venue"
},
  "geometry": {"coordinates":[12.482325,41.895466],"type":"Point"}
}