{
  "type": "Feature",
  "properties": {
    "addr:full":"98123 Messina Messina Messina 98123",
    "addr:postcode":"98123;98123",
    "iso:country":"IT",
    "sg:address":"98123 Messina",
    "sg:city":"Messina",
    "sg:orig_category":"Telecomunicazioni E Telefonia, Impianti, Apparecchi E Servizi",
    "sg:phone":"+39 090 671001",
    "sg:postcode":"98123",
    "sg:province":"Messina",
    "wof:name":"Pam Ufficio (s.r.l.)",
    "wof:placetype":"venue"
},
  "geometry": {"coordinates":[15.551834,38.18309],"type":"Point"}
}