{
  "type": "Feature",
  "properties": {
    "addr:full":"70032 Bitonto Bitonto Bari 70032",
    "addr:postcode":"70032;70032",
    "iso:country":"IT",
    "sg:address":"70032 Bitonto",
    "sg:city":"Bitonto",
    "sg:orig_category":"Prodotti Chimici Secondari. Servizi E Lavori Per Ecologia E Smaltimento Rifiuti. Macchine E Forniture Per Ecologia E Smaltimento Rifiuti",
    "sg:phone":"+39 080 373 9135",
    "sg:postcode":"70032",
    "sg:province":"Bari",
    "wof:name":"Abbattista Angelo Michele",
    "wof:placetype":"venue"
},
  "geometry": {"coordinates":[16.6963691711,41.1015014648],"type":"Point"}
}