{
  "type": "Feature",
  "properties": {
    "iso:country":"IT",
    "sg:address":"Via Corella 31040 Meduna Di Livenza",
    "sg:city":"Meduna di Livenza",
    "sg:classifiers":[
        {
            "category":"Home & Garden",
            "subcategory":"Home Furnishings",
            "type":"Retail Goods"
        }
    ],
    "sg:phone":"+39 0422 865181",
    "sg:postcode":"31040",
    "sg:province":"Treviso",
    "sg:tags":[
        "household"
    ],
    "wof:name":"Top Star Spa",
    "wof:placetype":"venue"
},
  "geometry": {"coordinates":[12.598905,45.826565],"type":"Point"}
}