{
  "type": "Feature",
  "properties": {
    "addr:full":"24064 Grumello Del Monte Grumello del Monte Bergamo 24064",
    "addr:postcode":"24064;24064",
    "iso:country":"IT",
    "sg:address":"24064 Grumello Del Monte",
    "sg:city":"Grumello del Monte",
    "sg:orig_category":"Non-classified Establishments",
    "sg:phone":"+39 035 832098",
    "sg:postcode":"24064",
    "sg:province":"Bergamo",
    "wof:name":"Pa.ve Di Pagani & Vezzoli Snc",
    "wof:placetype":"venue"
},
  "geometry": {"coordinates":[9.872783,45.643402],"type":"Point"}
}