{
  "type": "Feature",
  "properties": {
    "addr:full":"61100 Pesaro Pesaro Pesaro E Urbino 61100",
    "addr:postcode":"61100;61100",
    "iso:country":"IT",
    "sg:address":"61100 Pesaro",
    "sg:city":"Pesaro",
    "sg:orig_category":"Mobili Vimini E Giunco - Produzione E Ingrosso",
    "sg:phone":"+39 0721 283648",
    "sg:postcode":"61100",
    "sg:province":"Pesaro E Urbino",
    "wof:name":"Gasparucci Srl",
    "wof:placetype":"venue"
},
  "geometry": {"coordinates":[12.8634586334,43.88098526],"type":"Point"}
}