{
  "type": "Feature",
  "properties": {
    "iso:country":"IT",
    "sg:address":"Via Faentina 175 50010 Caldine",
    "sg:city":"Caldine",
    "sg:classifiers":[
        {
            "category":"Manufacturing",
            "subcategory":"Furniture",
            "type":"Manufacturing & Wholesale Goods"
        }
    ],
    "sg:phone":"+39 055 549131",
    "sg:postcode":"50010",
    "sg:province":"Firenze",
    "sg:tags":[
        "fabric"
    ],
    "sg:website":"www.fanair.it",
    "wof:name":"Fanair Srl",
    "wof:placetype":"venue"
},
  "geometry": {"coordinates":[11.3049144745,43.8279724121],"type":"Point"}
}