{
  "type": "Feature",
  "properties": {
    "iso:country":"IT",
    "sg:address":"25070 Casto",
    "sg:city":"Casto",
    "sg:orig_category":"Servizi E Lavori Industria Chimica. Riparazione Dei Mezzi Di Trasporto",
    "sg:phone":"+39 036 588116",
    "sg:postcode":"25070",
    "sg:province":"Brescia",
    "wof:name":"F.d.t. Di Freddi Tullio & C. Snc",
    "wof:placetype":"venue"
},
  "geometry": {"coordinates":[10.337612,45.698029],"type":"Point"}
}