{
  "type": "Feature",
  "properties": {
    "addr:full":"16137 Genova Genova Genova 16137",
    "addr:postcode":"16137;16137",
    "iso:country":"IT",
    "sg:address":"16137 Genova",
    "sg:city":"Genova",
    "sg:orig_category":"Macchine E Forniture Per Ecologia E Smaltimento Rifiuti",
    "sg:phone":"+39 010 813628",
    "sg:postcode":"16137",
    "sg:province":"Genova",
    "sg:website":"http://www.controlchemi.it",
    "wof:name":"Controlchemi Srl",
    "wof:placetype":"venue"
},
  "geometry": {"coordinates":[8.950131,44.410751],"type":"Point"}
}