{
  "type": "Feature",
  "properties": {
    "addr:full":"8, Via Circonvallazione 13018 Valduggia Valduggia Vercelli 13018",
    "addr:postcode":"13018;13018",
    "addr:street":"Via Circonvallazione",
    "iso:country":"IT",
    "sg:address":"8, Via Circonvallazione 13018 Valduggia",
    "sg:city":"Valduggia",
    "sg:classifiers":[
        {
            "category":"Manufacturing",
            "subcategory":"Metals",
            "type":"Manufacturing & Wholesale Goods"
        }
    ],
    "sg:phone":"+39 39016347416",
    "sg:postcode":"13018",
    "sg:province":"Vercelli",
    "sg:tags":[
        "processing"
    ],
    "wof:name":"Metalli Pressati (s.r.l.)",
    "wof:placetype":"venue"
},
  "geometry": {"coordinates":[8.3307151794,45.7271537781],"type":"Point"}
}