{
  "type": "Feature",
  "properties": {
    "addr:full":"5, Via Torre Bianca 39042 Bressanone Bressanone Bolzano/Bozen 39042",
    "addr:postcode":"39042;39042",
    "addr:street":"Via Torre Bianca",
    "iso:country":"IT",
    "sg:address":"5, Via Torre Bianca 39042 Bressanone",
    "sg:city":"Bressanone",
    "sg:classifiers":[
        {
            "category":"Manufacturing",
            "subcategory":"Printing",
            "type":"Manufacturing & Wholesale Goods"
        }
    ],
    "sg:phone":"+39 0472 201067",
    "sg:postcode":"39042",
    "sg:province":"Bolzano/Bozen",
    "sg:tags":[
        "publishing"
    ],
    "wof:name":"A. Weger Kg D. Andreas Von Moerl",
    "wof:placetype":"venue"
},
  "geometry": {"coordinates":[11.6576395035,46.7172393799],"type":"Point"}
}