{
  "type": "Feature",
  "properties": {
    "iso:country":"IT",
    "sg:address":"3, Via Don Francesco Longato 31036 Istrana",
    "sg:city":"Istrana",
    "sg:classifiers":[
        {
            "category":"Shopping",
            "subcategory":"Stationery & Office Supplies",
            "type":"Retail Goods"
        }
    ],
    "sg:phone":"+39 0422 832355",
    "sg:postcode":"31036",
    "sg:province":"Treviso",
    "sg:tags":[
        "professional"
    ],
    "wof:name":"Mascagni (s.p.a.)",
    "wof:placetype":"venue"
},
  "geometry": {"coordinates":[12.1064949036,45.6923294067],"type":"Point"}
}