{
  "type": "Feature",
  "properties": {
    "addr:full":"Via Nefetti 10; S. Sofia; 47018 Forl\u00ec-Cesena 47018",
    "addr:housenumber":"10",
    "addr:postcode":"47018;47018",
    "addr:street":"Via Nefetti",
    "iso:country":"IT",
    "sg:address":"Via Nefetti 10; S. Sofia; 47018",
    "sg:classifiers":[
        {
            "category":"Banks & Credit Unions",
            "subcategory":"Bank",
            "type":"Services"
        }
    ],
    "sg:phone":"+39 0543 970125",
    "sg:postcode":"47018",
    "sg:province":"Forl\u00ec-Cesena",
    "wof:name":"Rolo Banca 1473 Spa",
    "wof:placetype":"venue"
},
  "geometry": {"coordinates":[11.907191,43.947918],"type":"Point"}
}