{
  "type": "Feature",
  "properties": {
    "addr:full":"10136 Torino Torino Torino 10136",
    "addr:postcode":"10136;10136",
    "iso:country":"IT",
    "sg:address":"10136 Torino",
    "sg:city":"Torino",
    "sg:orig_category":"Hobbistica",
    "sg:phone":"+39 011 329 1829",
    "sg:postcode":"10136",
    "sg:province":"Torino",
    "wof:name":"Filatelia Cantoni",
    "wof:placetype":"venue"
},
  "geometry": {"coordinates":[7.645542,45.052265],"type":"Point"}
}