{
  "type": "Feature",
  "properties": {
    "addr:full":"20124 Milano Milano Milano 20124",
    "addr:postcode":"20124;20124",
    "iso:country":"IT",
    "sg:address":"20124 Milano",
    "sg:city":"Milano",
    "sg:classifiers":[
        {
            "category":"Health Services",
            "subcategory":"Health Practitioner",
            "type":"Services"
        }
    ],
    "sg:phone":"+39 02 2024 0722",
    "sg:postcode":"20124",
    "sg:province":"Milano",
    "sg:tags":[
        "medici"
    ],
    "wof:name":"New Vision Srl",
    "wof:placetype":"venue"
},
  "geometry": {"coordinates":[9.2109012604,45.4824028015],"type":"Point"}
}