{
  "type": "Feature",
  "properties": {
    "addr:full":"40055 Castenaso Castenaso Bologna 40055",
    "addr:postcode":"40055;40055",
    "iso:country":"IT",
    "sg:address":"40055 Castenaso",
    "sg:city":"Castenaso",
    "sg:orig_category":"Servizi E Lavori Industria Della Gomma",
    "sg:phone":"+39 051 780200",
    "sg:postcode":"40055",
    "sg:province":"Bologna",
    "wof:name":"Boriani Roberto & C. (s.n.c.)",
    "wof:placetype":"venue"
},
  "geometry": {"coordinates":[11.431635,44.500977],"type":"Point"}
}