{
  "type": "Feature",
  "properties": {
    "addr:full":"32, Via Pontebbana 31010 Orsago Orsago Treviso 31010",
    "addr:postcode":"31010;31010",
    "addr:street":"Via Pontebbana",
    "iso:country":"IT",
    "sg:address":"32, Via Pontebbana 31010 Orsago",
    "sg:city":"Orsago",
    "sg:classifiers":[
        {
            "category":"Bars & Pubs",
            "subcategory":"Nightclub",
            "type":"Food & Drink"
        }
    ],
    "sg:phone":"+39 0438 992054",
    "sg:postcode":"31010",
    "sg:province":"Treviso",
    "sg:tags":[
        "cake",
        "bread"
    ],
    "wof:name":"Doria (s.p.a.)",
    "wof:placetype":"venue"
},
  "geometry": {"coordinates":[12.428907,45.938419],"type":"Point"}
}