{
  "type": "Feature",
  "properties": {
    "iso:country":"IT",
    "sg:address":"07026 Olbia",
    "sg:city":"Olbia",
    "sg:classifiers":[
        {
            "category":"Retail",
            "subcategory":"Auto Repair",
            "type":"Services"
        }
    ],
    "sg:phone":"+39 0789 58333",
    "sg:postcode":"07026",
    "sg:province":"Olbia-Tempio",
    "sg:tags":[
        "repairs",
        "vehicles",
        "auxiliary",
        "motor"
    ],
    "wof:name":"Gottardi E Deiana Srl",
    "wof:placetype":"venue"
},
  "geometry": {"coordinates":[9.2785587311,40.826839447],"type":"Point"}
}