{
  "type": "Feature",
  "properties": {
    "iso:country":"IT",
    "sg:address":"18038 Sanremo",
    "sg:orig_category":"Macchine, Impianti Ed Attrezzature Per Agricoltura E Zootecnia",
    "sg:phone":"+39 0184 570333",
    "sg:postcode":"18038",
    "sg:province":"Imperia",
    "wof:name":"Marchetto",
    "wof:placetype":"venue"
},
  "geometry": {"coordinates":[7.768629,43.823009],"type":"Point"}
}