{
  "type": "Feature",
  "properties": {
    "iso:country":"IT",
    "sg:address":"20127 Milano",
    "sg:city":"Milano",
    "sg:orig_category":"Chiese Ed Associazioni Religiose",
    "sg:phone":"+39 02 255 1270",
    "sg:postcode":"20127",
    "sg:province":"Milano",
    "wof:name":"Comunita'islamica Di Milano",
    "wof:placetype":"venue"
},
  "geometry": {"coordinates":[9.222985,45.506668],"type":"Point"}
}