{
  "type": "Feature",
  "properties": {
    "addr:full":"20020 Arese Arese Milano 20020",
    "addr:postcode":"20020;20020",
    "iso:country":"IT",
    "sg:address":"20020 Arese",
    "sg:city":"Arese",
    "sg:orig_category":"Petroli, Gas E Combustibili",
    "sg:phone":"+39 02 934551",
    "sg:postcode":"20020",
    "sg:province":"Milano",
    "wof:name":"Tamoil Italia S.p.a.",
    "wof:placetype":"venue"
},
  "geometry": {"coordinates":[9.0838432312,45.5375022888],"type":"Point"}
}