{
  "type": "Feature",
  "properties": {
    "iso:country":"IT",
    "sg:address":"25020 Gambara",
    "sg:city":"Gambara",
    "sg:orig_category":"Zootecnia E Pesca, Allevamento Piccoli Animali",
    "sg:phone":"+39 030 956306",
    "sg:postcode":"25020",
    "sg:province":"Brescia",
    "wof:name":"Vignoni Alfredo",
    "wof:placetype":"venue"
},
  "geometry": {"coordinates":[10.289611,45.258572],"type":"Point"}
}