{
  "type": "Feature",
  "properties": {
    "addr:full":"508, Viale Casiraghi Fratelli 20099 Sesto San Giovanni Sesto San Giovanni Milano 20099",
    "addr:postcode":"20099;20099",
    "addr:street":"Viale Casiraghi",
    "iso:country":"IT",
    "sg:address":"508, Viale Casiraghi Fratelli 20099 Sesto San Giovanni",
    "sg:city":"Sesto San Giovanni",
    "sg:classifiers":[
        {
            "category":"Food & Beverages",
            "subcategory":"Groceries & Convenience Stores",
            "type":"Retail Goods"
        }
    ],
    "sg:phone":"+39 02 2479 2001",
    "sg:postcode":"20099",
    "sg:province":"Milano",
    "sg:tags":[
        "drink"
    ],
    "wof:name":"Universal Flavors S.r.l.",
    "wof:placetype":"venue"
},
  "geometry": {"coordinates":[9.236985,45.548698],"type":"Point"}
}