{
  "type": "Feature",
  "properties": {
    "iso:country":"IT",
    "sg:address":"37124 Verona",
    "sg:city":"Verona",
    "sg:orig_category":"Macchine, Impianti Ed Attrezzature Per Industria Alimentare E Bevande. Elettrodomestici. Macchine E Impianti Per Attivita' Commerciali Ed Artigianali",
    "sg:phone":"+39 045 834 3434",
    "sg:postcode":"37124",
    "sg:province":"Verona",
    "wof:name":"Fracasso Enzo & Bruno",
    "wof:placetype":"venue"
},
  "geometry": {"coordinates":[10.878034,45.35025],"type":"Point"}
}