{
  "type": "Feature",
  "properties": {
    "addr:full":"53, Corso Cavour 28040 Dormelletto Dormelletto Novara 28040",
    "addr:postcode":"28040;28040",
    "addr:street":"Corso Cavour",
    "iso:country":"IT",
    "sg:address":"53, Corso Cavour 28040 Dormelletto",
    "sg:city":"Dormelletto",
    "sg:classifiers":[
        {
            "category":"Shopping",
            "subcategory":"Clothing, Apparel, & Fashions",
            "type":"Retail Goods"
        }
    ],
    "sg:phone":"+39 0322 497032",
    "sg:postcode":"28040",
    "sg:province":"Novara",
    "sg:tags":[
        "clothes"
    ],
    "wof:name":"Les Lunis Dormello S.p.a.",
    "wof:placetype":"venue"
},
  "geometry": {"coordinates":[8.574223,45.733948],"type":"Point"}
}