{
  "type": "Feature",
  "properties": {
    "iso:country":"IT",
    "sg:address":"35010 Vigodarzere",
    "sg:city":"Vigodarzere",
    "sg:orig_category":"Lavorazioni Metalli, Stampaggio E Saldatura",
    "sg:phone":"+39 049 702066",
    "sg:postcode":"35010",
    "sg:province":"Padova",
    "wof:name":"Rossi Fratelli Snc Di Rossi Gianfranco, Sergio & C.",
    "wof:placetype":"venue"
},
  "geometry": {"coordinates":[11.890347,45.452072],"type":"Point"}
}