{
  "type": "Feature",
  "properties": {
    "iso:country":"IT",
    "sg:address":"89030 Sant'agata Del Bianco",
    "sg:orig_category":"Servizi E Lavori Per Ecologia E Smaltimento Rifiuti. Acqua, Luce, Gas E Societa' Di Esercizio Pubblico",
    "sg:phone":"+39 0964 956188",
    "sg:postcode":"89030",
    "sg:province":"Reggio Di Calabria",
    "wof:name":"Zetaemme Sas Di Maiorana Carmela E C.",
    "wof:placetype":"venue"
},
  "geometry": {"coordinates":[16.082518,38.094242],"type":"Point"}
}