{
  "type": "Feature",
  "properties": {
    "iso:country":"IT",
    "sg:address":"25, Via Cavour 27035 Mede",
    "sg:city":"Mede",
    "sg:classifiers":[
        {
            "category":"Shopping",
            "subcategory":"Jewelry",
            "type":"Retail Goods"
        }
    ],
    "sg:phone":"+39 0384 823271",
    "sg:postcode":"27035",
    "sg:province":"Pavia",
    "sg:tags":[
        "jewellery"
    ],
    "wof:name":"Esse & Bi Di Ballotrini Angelo & C. Snc",
    "wof:placetype":"venue"
},
  "geometry": {"coordinates":[8.738471,45.097721],"type":"Point"}
}