{
  "type": "Feature",
  "properties": {
    "iso:country":"IT",
    "sg:address":"05100 Terni",
    "sg:city":"Terni",
    "sg:classifiers":[
        {
            "category":"Professional",
            "subcategory":"Engineering",
            "type":"Services"
        }
    ],
    "sg:phone":"+39 0744 811145",
    "sg:postcode":"05100",
    "sg:province":"Terni",
    "sg:tags":[
        "component",
        "material",
        "electronic"
    ],
    "wof:name":"Eda Srl",
    "wof:placetype":"venue"
},
  "geometry": {"coordinates":[12.621024,42.553715],"type":"Point"}
}