{
  "type": "Feature",
  "properties": {
    "iso:country":"IT",
    "sg:address":"23/t, C. Promessi Sposi 23900 Lecco",
    "sg:city":"Lecco",
    "sg:classifiers":[
        {
            "category":"Shopping",
            "subcategory":"Gifts & Souvenirs",
            "type":"Retail Goods"
        }
    ],
    "sg:phone":"+39 0341 250095",
    "sg:postcode":"23900",
    "sg:province":"Lecco",
    "sg:website":"http://www.adimat.com",
    "wof:name":"Adimat Srl",
    "wof:placetype":"venue"
},
  "geometry": {"coordinates":[9.405952,45.856491],"type":"Point"}
}