{
  "type": "Feature",
  "properties": {
    "iso:country":"IT",
    "sg:address":"31053 Pieve Di Soligo",
    "sg:city":"Pieve di Soligo",
    "sg:orig_category":"Arredamenti E Mobili Professionali. Arredi Ed Attrezzature Per Uffici",
    "sg:phone":"+39 0438 981034",
    "sg:postcode":"31053",
    "sg:province":"Treviso",
    "sg:website":"http://www.dau.it",
    "wof:name":"Dau Srl",
    "wof:placetype":"venue"
},
  "geometry": {"coordinates":[12.181129,45.907856],"type":"Point"}
}