{
  "type": "Feature",
  "properties": {
    "iso:country":"IT",
    "sg:address":"30174 Venezia",
    "sg:city":"Venezia",
    "sg:orig_category":"Impianti, Attrezzature E Forniture Sanitarie Ed Ospedaliere",
    "sg:phone":"+39 041 504 0983",
    "sg:postcode":"30174",
    "sg:province":"Venezia",
    "wof:name":"Ge Medical System Italia Spa",
    "wof:placetype":"venue"
},
  "geometry": {"coordinates":[12.212565,45.505871],"type":"Point"}
}