{
  "type": "Feature",
  "properties": {
    "iso:country":"IT",
    "sg:address":"20142 Milano",
    "sg:city":"Milano",
    "sg:orig_category":"Motori Ed Organi Di Trasmissione. Ricambi E Componenti Dei Mezzi Di Trasporto",
    "sg:phone":"+39 02 843 6538",
    "sg:postcode":"20142",
    "sg:province":"Milano",
    "wof:name":"Cristina Srl",
    "wof:placetype":"venue"
},
  "geometry": {"coordinates":[9.1721658707,45.4418907166],"type":"Point"}
}