{
  "type": "Feature",
  "properties": {
    "iso:country":"IT",
    "sg:address":"20032 Cormano",
    "sg:city":"Cormano",
    "sg:orig_category":"Manufacturers: Prefabbricati",
    "sg:phone":"+39 02 6630 3236",
    "sg:postcode":"20032",
    "sg:province":"Milano",
    "wof:name":"Lenzini Marmi Snc Di Lenzini Cesare E Giuseppe",
    "wof:placetype":"venue"
},
  "geometry": {"coordinates":[9.164799,45.544655],"type":"Point"}
}