{
  "type": "Feature",
  "properties": {
    "addr:full":"28014 Maggiora Maggiora Novara 28014",
    "addr:postcode":"28014;28014",
    "iso:country":"IT",
    "sg:address":"28014 Maggiora",
    "sg:city":"Maggiora",
    "sg:orig_category":"Prodotti Alimentari",
    "sg:phone":"+39 0322 87175",
    "sg:postcode":"28014",
    "sg:province":"Novara",
    "wof:name":"Fasola Luciano Di Fasola Elio E C. (s.n.c.)",
    "wof:placetype":"venue"
},
  "geometry": {"coordinates":[8.4284543991,45.6866035461],"type":"Point"}
}