{
  "type": "Feature",
  "properties": {
    "iso:country":"IT",
    "sg:address":"94, Via Salaria 00015 Monterotondo",
    "sg:city":"Monterotondo",
    "sg:classifiers":[
        {
            "category":"Home & Garden",
            "subcategory":"Home Furnishings",
            "type":"Retail Goods"
        }
    ],
    "sg:phone":"+39 39069060701",
    "sg:postcode":"00015",
    "sg:province":"Roma",
    "sg:tags":[
        "household"
    ],
    "wof:name":"Secom Segnalini Commerciale S.r.l.",
    "wof:placetype":"venue"
},
  "geometry": {"coordinates":[12.60344,42.073608],"type":"Point"}
}