{
  "type": "Feature",
  "properties": {
    "addr:full":"34016 Trieste Trieste 34016",
    "addr:postcode":"34016;34016",
    "iso:country":"IT",
    "sg:address":"34016 Trieste",
    "sg:orig_category":"Pubblica Amministrazione",
    "sg:phone":"+39 040 215 8448",
    "sg:postcode":"34016",
    "sg:province":"Trieste",
    "wof:name":"Polizia/soccorso Pubblico 113",
    "wof:placetype":"venue"
},
  "geometry": {"coordinates":[13.7733869553,45.6887588501],"type":"Point"}
}