{
  "type": "Feature",
  "properties": {
    "addr:full":"20058 Villasanta Villasanta Milano 20058",
    "addr:postcode":"20058;20058",
    "iso:country":"IT",
    "sg:address":"20058 Villasanta",
    "sg:city":"Villasanta",
    "sg:orig_category":"Filati E Materie Prime Tessili",
    "sg:phone":"+39 039 205 0717",
    "sg:postcode":"20058",
    "sg:province":"Milano",
    "wof:name":"Eredi Di Andreoni Di Colombo Snc",
    "wof:placetype":"venue"
},
  "geometry": {"coordinates":[9.1890802383,45.5303878784],"type":"Point"}
}