{
  "type": "Feature",
  "properties": {
    "iso:country":"IT",
    "sg:address":"89843 Maierato",
    "sg:city":"Maierato",
    "sg:orig_category":"Banche E Servizi Finanziari",
    "sg:phone":"+39 0963 253642",
    "sg:postcode":"89843",
    "sg:province":"Vibo Valentia",
    "wof:name":"Banca Di Credito Cooperativo Di Maierato",
    "wof:placetype":"venue"
},
  "geometry": {"coordinates":[16.14106,38.69511],"type":"Point"}
}