{
  "type": "Feature",
  "properties": {
    "iso:country":"IT",
    "sg:address":"31053 Pieve Di Soligo",
    "sg:city":"Pieve di Soligo",
    "sg:orig_category":"Servizi E Lavori Per Arredamento E Industria Del Legno",
    "sg:phone":"+39 0438 842305",
    "sg:postcode":"31053",
    "sg:province":"Treviso",
    "wof:name":"D.m.f. Impiallacciature Di Dalla Mora Daria & Ferrari Cristina S.n.c.",
    "wof:placetype":"venue"
},
  "geometry": {"coordinates":[12.168167,45.886528],"type":"Point"}
}