{
  "type": "Feature",
  "properties": {
    "iso:country":"IT",
    "sg:address":"2, Vicolo Mulini 21034 Cocquio Trevisago",
    "sg:city":"Cocquio",
    "sg:classifiers":[
        {
            "category":"Manufacturing",
            "subcategory":"Lumber",
            "type":"Manufacturing & Wholesale Goods"
        }
    ],
    "sg:phone":"+39 0332 700110",
    "sg:postcode":"21034",
    "sg:province":"Varese",
    "sg:tags":[
        "wood"
    ],
    "wof:name":"Visconti F.lli",
    "wof:placetype":"venue"
},
  "geometry": {"coordinates":[8.826385,45.817604],"type":"Point"}
}