{
  "type": "Feature",
  "properties": {
    "iso:country":"IT",
    "sg:address":"22/24, Via Sassone Candido 13100 Vercelli",
    "sg:city":"Vercelli",
    "sg:classifiers":[
        {
            "category":"Manufacturing",
            "subcategory":"Printing",
            "type":"Manufacturing & Wholesale Goods"
        }
    ],
    "sg:phone":"+39 0161 294203",
    "sg:postcode":"13100",
    "sg:province":"Vercelli",
    "sg:tags":[
        "publishing"
    ],
    "wof:name":"White Star (s.r.l.)",
    "wof:placetype":"venue"
},
  "geometry": {"coordinates":[8.4263935089,45.3210601807],"type":"Point"}
}