{
  "type": "Feature",
  "properties": {
    "addr:full":"19, Via Uditore 90145 Palermo Palermo Palermo 90145",
    "addr:postcode":"90145;90145",
    "addr:street":"Via Uditore",
    "iso:country":"IT",
    "sg:address":"19, Via Uditore 90145 Palermo",
    "sg:city":"Palermo",
    "sg:classifiers":[
        {
            "category":"Food & Beverages",
            "subcategory":"Bakery",
            "type":"Retail Goods"
        }
    ],
    "sg:phone":"+39 39091228292",
    "sg:postcode":"90145",
    "sg:province":"Palermo",
    "sg:tags":[
        "grain",
        "cereal"
    ],
    "wof:name":"Bonura Molino (s.p.a.)",
    "wof:placetype":"venue"
},
  "geometry": {"coordinates":[13.323884,38.131836],"type":"Point"}
}