{
  "type": "Feature",
  "properties": {
    "iso:country":"IT",
    "sg:address":"21040 Vedano Olona",
    "sg:city":"Vedano Olona",
    "sg:orig_category":"Imprese Pulizia",
    "sg:phone":"+39 0332 402138",
    "sg:postcode":"21040",
    "sg:province":"Varese",
    "wof:name":"Impresa Di Pulizia Euroservizi Italia Srl",
    "wof:placetype":"venue"
},
  "geometry": {"coordinates":[8.892158,45.77338],"type":"Point"}
}