{
  "type": "Feature",
  "properties": {
    "iso:country":"IT",
    "sg:address":"50144 Firenze",
    "sg:city":"Firenze",
    "sg:orig_category":"Forniture Per Edilizia E Lavori Pubblici. Arredi Ed Attrezzature Per Attivita' Commerciali Ed Artigianali. Forniture Per Attivita' Industriali",
    "sg:phone":"+39 055 350497",
    "sg:postcode":"50144",
    "sg:province":"Firenze",
    "sg:website":"http://www.centroscale.it",
    "wof:name":"Centro Scale E Serramenti Srl",
    "wof:placetype":"venue"
},
  "geometry": {"coordinates":[11.2268772125,43.7822685242],"type":"Point"}
}