{
  "type": "Feature",
  "properties": {
    "iso:country":"IT",
    "sg:address":"20089 Rozzano",
    "sg:city":"Rozzano",
    "sg:orig_category":"Prodotti Finiti Stampati. Articoli Da Regalo. Arte Ed Artigianato Artistico. Shopping",
    "sg:phone":"+39 02 5750 0301",
    "sg:postcode":"20089",
    "sg:province":"Milano",
    "wof:name":"Pico Art S.r.l.",
    "wof:placetype":"venue"
},
  "geometry": {"coordinates":[9.1731328964,45.3971824646],"type":"Point"}
}