{
  "type": "Feature",
  "properties": {
    "addr:full":"4, Via Bartolomeo Colleoni 24040 Boltiere Boltiere Bergamo 24040",
    "addr:postcode":"24040;24040",
    "addr:street":"Via Bartolomeo Colleoni",
    "iso:country":"IT",
    "sg:address":"4, Via Bartolomeo Colleoni 24040 Boltiere",
    "sg:city":"Boltiere",
    "sg:classifiers":[
        {
            "category":"Shopping",
            "type":"Retail Goods"
        }
    ],
    "sg:phone":"+39 39035806633",
    "sg:postcode":"24040",
    "sg:province":"Bergamo",
    "sg:tags":[
        "finished",
        "-",
        "metallic"
    ],
    "wof:name":"Attrezzeria Cavalleri (s.r.l.)",
    "wof:placetype":"venue"
},
  "geometry": {"coordinates":[9.5584793091,45.621635437],"type":"Point"}
}