{
  "type": "Feature",
  "properties": {
    "addr:full":"1, Via Gramsci Antonio 20030 Senago Senago Milano 20030",
    "addr:postcode":"20030;20030",
    "addr:street":"Via Gramsci Antonio",
    "iso:country":"IT",
    "sg:address":"1, Via Gramsci Antonio 20030 Senago",
    "sg:city":"Senago",
    "sg:classifiers":[
        {
            "category":"Manufacturing",
            "subcategory":"Tools & Machinery",
            "type":"Manufacturing & Wholesale Goods"
        }
    ],
    "sg:phone":"+39 02 9905 5600",
    "sg:postcode":"20030",
    "sg:province":"Milano",
    "sg:tags":[
        "environment",
        "equipment",
        "-"
    ],
    "wof:name":"Ecolife S.r.l.",
    "wof:placetype":"venue"
},
  "geometry": {"coordinates":[9.165059,45.567741],"type":"Point"}
}