{
  "type": "Feature",
  "properties": {
    "addr:full":"Via Principe Di Piemonte 118/120 80026 Casoria Casoria Napoli 80026",
    "addr:housenumber":"118 / 120",
    "addr:postcode":"80026;80026",
    "addr:street":"Via Principe Di Piemonte",
    "iso:country":"IT",
    "sg:address":"Via Principe Di Piemonte 118/120 80026 Casoria",
    "sg:city":"Casoria",
    "sg:classifiers":[
        {
            "category":"Banks & Credit Unions",
            "subcategory":"Investment Brokerage",
            "type":"Services"
        }
    ],
    "sg:phone":"+39 081 757 2056",
    "sg:postcode":"80026",
    "sg:province":"Napoli",
    "sg:tags":[
        "women's",
        "clothing",
        "accessory"
    ],
    "sg:website":"www.brunomariosnc.com",
    "wof:name":"Bruno Mario Snc",
    "wof:placetype":"venue"
},
  "geometry": {"coordinates":[14.285044,40.906883],"type":"Point"}
}