{
  "type": "Feature",
  "properties": {
    "iso:country":"IT",
    "sg:address":"37121 Verona",
    "sg:city":"Verona",
    "sg:orig_category":"Articoli Da Regalo. Tempo Libero - Articoli E Forniture. Regalistica Aziendale",
    "sg:phone":"+39 045 800 5352",
    "sg:postcode":"37121",
    "sg:province":"Verona",
    "wof:name":"Df Di Franchi Stefano",
    "wof:placetype":"venue"
},
  "geometry": {"coordinates":[10.999986,45.437344],"type":"Point"}
}