{
  "type": "Feature",
  "properties": {
    "iso:country":"IT",
    "sg:address":"50041 Calenzano",
    "sg:city":"Calenzano",
    "sg:orig_category":"Fonderie",
    "sg:phone":"+39 055 883261",
    "sg:postcode":"50041",
    "sg:province":"Firenze",
    "sg:website":"http://www.fonderiepalmieri.it",
    "wof:name":"Fonderie Palmieri Spa",
    "wof:placetype":"venue"
},
  "geometry": {"coordinates":[11.1708269119,43.8459968567],"type":"Point"}
}