{
  "type": "Feature",
  "properties": {
    "addr:full":"03011 Alatri Alatri Frosinone 03011",
    "addr:postcode":"03011;03011",
    "iso:country":"IT",
    "sg:address":"03011 Alatri",
    "sg:city":"Alatri",
    "sg:orig_category":"Manufacturers: Prefabbricati",
    "sg:phone":"+39 0775 409329",
    "sg:postcode":"03011",
    "sg:province":"Frosinone",
    "sg:website":"http://www.modulpav.it",
    "wof:name":"Modulpav Di Addesse Elio & Figli",
    "wof:placetype":"venue"
},
  "geometry": {"coordinates":[13.22325,41.796738],"type":"Point"}
}