{
  "type": "Feature",
  "properties": {
    "iso:country":"IT",
    "sg:address":"35137 Padova",
    "sg:city":"Padova",
    "sg:orig_category":"Climatizzazione E Condizionamento, Apparecchiature E Servizi. Accessori Dei Mezzi Di Trasporto",
    "sg:phone":"+39 049 871 8245",
    "sg:postcode":"35137",
    "sg:province":"Padova",
    "wof:name":"Xtreme Sas",
    "wof:placetype":"venue"
},
  "geometry": {"coordinates":[11.87032,45.414623],"type":"Point"}
}