{
  "type": "Feature",
  "properties": {
    "addr:full":"11, V. Portogallo35127 Padova Padova Padova 35127",
    "addr:housenumber":"11",
    "addr:postcode":"35127",
    "addr:street":"V. Portogallo35127",
    "iso:country":"IT",
    "sg:address":"11, V. Portogallo35127 Padova",
    "sg:city":"Padova",
    "sg:classifiers":[
        {
            "category":"Shopping",
            "subcategory":"Stationery & Office Supplies",
            "type":"Retail Goods"
        }
    ],
    "sg:phone":"+39 39049761885",
    "sg:postcode":"35127",
    "sg:province":"Padova",
    "sg:tags":[
        "professional"
    ],
    "sg:website":"http://www.remiro.it",
    "wof:name":"Remiro S.r.l.",
    "wof:placetype":"venue"
},
  "geometry": {"coordinates":[11.9460525513,45.389415741],"type":"Point"}
}