{
  "type": "Feature",
  "properties": {
    "iso:country":"IT",
    "sg:address":"21040 Uboldo",
    "sg:city":"Uboldo",
    "sg:orig_category":"Arredo Cucina Ed Elettrodomestici. Elettrodomestici",
    "sg:phone":"+39 02 9678 1620",
    "sg:postcode":"21040",
    "sg:province":"Varese",
    "wof:name":"Xmeale Snc Di Sandro Bassi E Cipriano Gennarino",
    "wof:placetype":"venue"
},
  "geometry": {"coordinates":[9.005,45.616261],"type":"Point"}
}