{
  "type": "Feature",
  "properties": {
    "iso:country":"IT",
    "sg:address":"46100 Mantova",
    "sg:city":"Mantova",
    "sg:orig_category":"Assicurazioni E Servizi Assicurativi. Consulenze Tecniche, Amministrative E Perizie",
    "sg:phone":"+39 0376 366309",
    "sg:postcode":"46100",
    "sg:province":"Mantova",
    "wof:name":"Cuzzocrea Marco",
    "wof:placetype":"venue"
},
  "geometry": {"coordinates":[10.791612,45.161064],"type":"Point"}
}