{
  "type": "Feature",
  "properties": {
    "iso:country":"IT",
    "sg:address":"Via Torbada 23 23900 Lecco",
    "sg:city":"Lecco",
    "sg:classifiers":[
        {
            "category":"Home & Garden",
            "subcategory":"Hardware",
            "type":"Retail Goods"
        }
    ],
    "sg:phone":"+39 0341 362456",
    "sg:postcode":"23900",
    "sg:province":"Lecco",
    "sg:tags":[
        "small",
        "ironware",
        "item"
    ],
    "wof:name":"Cattaneo Sas Di Cattaneo Barbara & Stefano",
    "wof:placetype":"venue"
},
  "geometry": {"coordinates":[9.390071,45.852982],"type":"Point"}
}