{
  "type": "Feature",
  "properties": {
    "addr:full":"20129 Milano Milano Milano 20129",
    "addr:postcode":"20129;20129",
    "iso:country":"IT",
    "sg:address":"20129 Milano",
    "sg:city":"Milano",
    "sg:orig_category":"Forniture Per Abbigliamento E Pelletterie",
    "sg:phone":"+39 02 204 9107",
    "sg:postcode":"20129",
    "sg:province":"Milano",
    "wof:name":"Danimarca Piumini Danesi (s.r.l.)",
    "wof:placetype":"venue"
},
  "geometry": {"coordinates":[9.2058582306,45.4745635986],"type":"Point"}
}