{
  "type": "Feature",
  "properties": {
    "iso:country":"IT",
    "sg:address":"1, Via Della Maggiona 00040 Pomezia",
    "sg:city":"Pomezia",
    "sg:classifiers":[
        {
            "category":"Professional",
            "subcategory":"Computer Services",
            "type":"Services"
        }
    ],
    "sg:phone":"+39 39069108232",
    "sg:postcode":"00040",
    "sg:province":"Roma",
    "sg:tags":[
        "information",
        "technology"
    ],
    "wof:name":"A.l.a. Elettronica Srl",
    "wof:placetype":"venue"
},
  "geometry": {"coordinates":[12.523357,41.669212],"type":"Point"}
}