{
  "type": "Feature",
  "properties": {
    "addr:full":"41100 Modena Modena Modena 41100",
    "addr:postcode":"41100;41100",
    "iso:country":"IT",
    "sg:address":"41100 Modena",
    "sg:city":"Modena",
    "sg:orig_category":"Alimentari - Produzione E Ingrosso",
    "sg:phone":"+39 059 353343",
    "sg:postcode":"41100",
    "sg:province":"Modena",
    "sg:website":"http://www.il-mercante.com",
    "wof:name":"Il Mercante Srl",
    "wof:placetype":"venue"
},
  "geometry": {"coordinates":[10.902387,44.633694],"type":"Point"}
}