{
  "type": "Feature",
  "properties": {
    "iso:country":"IT",
    "sg:address":"Via Ca' Dei Lunghi 16 47890 Di Repubblica Di San Marino",
    "sg:classifiers":[
        {
            "category":"Manufacturing",
            "subcategory":"Signs",
            "type":"Manufacturing & Wholesale Goods"
        }
    ],
    "sg:phone":"+39 0549 906122",
    "sg:tags":[
        "engraved"
    ],
    "wof:name":"Koppe Di Pelliccioni Marco",
    "wof:placetype":"venue"
},
  "geometry": {"coordinates":[12.452838,43.950298],"type":"Point"}
}