{
  "type": "Feature",
  "properties": {
    "iso:country":"IT",
    "sg:address":"22100 Como",
    "sg:city":"Como",
    "sg:orig_category":"Materiali E Componenti Elettronici",
    "sg:phone":"+39 031 270777",
    "sg:postcode":"22100",
    "sg:province":"Como",
    "wof:name":"C.a.r.t. (s.n.c.)",
    "wof:placetype":"venue"
},
  "geometry": {"coordinates":[9.088001,45.797684],"type":"Point"}
}