{
  "type": "Feature",
  "properties": {
    "iso:country":"IT",
    "sg:address":"1, Via Fratini 55051 Barga",
    "sg:city":"Barga",
    "sg:classifiers":[
        {
            "category":"Manufacturing",
            "subcategory":"Paper Products",
            "type":"Manufacturing & Wholesale Goods"
        }
    ],
    "sg:phone":"+39 0583 724323",
    "sg:postcode":"55051",
    "sg:province":"Lucca",
    "sg:tags":[
        "cardboard"
    ],
    "wof:name":"Regina Superfrisch (s.r.l.)",
    "wof:placetype":"venue"
},
  "geometry": {"coordinates":[10.5079936981,43.8430137634],"type":"Point"}
}