{
  "type": "Feature",
  "properties": {
    "iso:country":"IT",
    "sg:address":"Viale Minieri 201/203; Telese; 82037",
    "sg:classifiers":[
        {
            "category":"Banks & Credit Unions",
            "subcategory":"Bank",
            "type":"Services"
        }
    ],
    "sg:phone":"+39 0824 941296",
    "sg:postcode":"82037",
    "sg:province":"Benevento",
    "wof:name":"Banco Di Napoli Spa",
    "wof:placetype":"venue"
},
  "geometry": {"coordinates":[14.527724,41.220161],"type":"Point"}
}