{
  "type": "Feature",
  "properties": {
    "iso:country":"IT",
    "sg:address":"36030 Rettorgole",
    "sg:city":"Rettorgole",
    "sg:orig_category":"Macchine, Impianti E Forniture Per Industria Grafica, Cartaria E Cartotecnica. Prodotti Chimici Secondari",
    "sg:phone":"+39 0444 986385",
    "sg:postcode":"36030",
    "sg:province":"Vicenza",
    "wof:name":"Graforama (s.n.c.)",
    "wof:placetype":"venue"
},
  "geometry": {"coordinates":[11.526718,45.584999],"type":"Point"}
}