{
  "type": "Feature",
  "properties": {
    "iso:country":"IT",
    "sg:address":"20154 Milano",
    "sg:city":"Milano",
    "sg:orig_category":"Servizi Editoriali. Professionisti - Studi E Servizi Ed Associazioni Di Interesse Aziendale",
    "sg:phone":"+39 02 349 1939",
    "sg:postcode":"20154",
    "sg:province":"Milano",
    "wof:name":"Pronzato Luisa Emilia",
    "wof:placetype":"venue"
},
  "geometry": {"coordinates":[9.175719,45.481915],"type":"Point"}
}