{
  "type": "Feature",
  "properties": {
    "addr:full":"92024 Canicatt\u00ec Agrigento 92024",
    "addr:postcode":"92024;92024",
    "iso:country":"IT",
    "sg:address":"92024 Canicatt\u00ec",
    "sg:orig_category":"Scuole E Servizi Scolastici. Ricerca, Selezione E Formazione Del Personale",
    "sg:phone":"+39 0922 859722",
    "sg:postcode":"92024",
    "sg:province":"Agrigento",
    "wof:name":"D.p.i. Sas Di Giuliana Angelo & C.",
    "wof:placetype":"venue"
},
  "geometry": {"coordinates":[13.588239,37.310402],"type":"Point"}
}