{
  "type": "Feature",
  "properties": {
    "iso:country":"IT",
    "sg:address":"70026 Modugno",
    "sg:city":"Modugno",
    "sg:orig_category":"Carta, Cartone E Prodotti Primari",
    "sg:phone":"+39 080 532 1809",
    "sg:postcode":"70026",
    "sg:province":"Bari",
    "sg:website":"http://www.recuperipugliesi.it",
    "wof:name":"Recuperi Pugliesi Dei Fratelli Schino Srl",
    "wof:placetype":"venue"
},
  "geometry": {"coordinates":[16.786957,41.091084],"type":"Point"}
}