{
  "type": "Feature",
  "properties": {
    "addr:full":"Via Val Sugana 5/k 16164 Genova Genova Genova 16164",
    "addr:housenumber":"5 / k",
    "addr:postcode":"16164;16164",
    "addr:street":"Via Val Sugana",
    "iso:country":"IT",
    "sg:address":"Via Val Sugana 5/k 16164 Genova",
    "sg:city":"Genova",
    "sg:classifiers":[
        {
            "category":"Banks & Credit Unions",
            "subcategory":"Bureau De Change",
            "type":"Services"
        }
    ],
    "sg:phone":"+39 010 714225",
    "sg:postcode":"16164",
    "sg:province":"Genova",
    "sg:tags":[
        "measuring",
        "instrument",
        "pneumatic"
    ],
    "wof:name":"Promar Srl",
    "wof:placetype":"venue"
},
  "geometry": {"coordinates":[8.9339885712,44.4070625305],"type":"Point"}
}