{
  "type": "Feature",
  "properties": {
    "iso:country":"IT",
    "sg:address":"70052 Bisceglie",
    "sg:city":"Bisceglie",
    "sg:orig_category":"Zootecnia E Pesca, Allevamento Piccoli Animali",
    "sg:phone":"+39 080 395 3518",
    "sg:postcode":"70052",
    "sg:province":"Bari",
    "wof:name":"Panittica Pugliese Srl",
    "wof:placetype":"venue"
},
  "geometry": {"coordinates":[16.526892,41.22263],"type":"Point"}
}