{
  "type": "Feature",
  "properties": {
    "iso:country":"IT",
    "sg:address":"18, Via Graziano Ferdinando 80022 Arzano",
    "sg:city":"Arzano",
    "sg:classifiers":[
        {
            "category":"Personal",
            "subcategory":"Shoe Repair & Shine",
            "type":"Services"
        }
    ],
    "sg:phone":"+39 081 573 5204",
    "sg:postcode":"80022",
    "sg:province":"Napoli",
    "sg:tags":[
        "leather"
    ],
    "wof:name":"Calzaturificio Fifth Avenue Shoes Srl",
    "wof:placetype":"venue"
},
  "geometry": {"coordinates":[14.261055,40.922447],"type":"Point"}
}