{
  "type": "Feature",
  "properties": {
    "iso:country":"IT",
    "sg:address":"Via Milano 66; Cogozzo",
    "sg:classifiers":[
        {
            "category":"Banks & Credit Unions",
            "subcategory":"Bank",
            "type":"Services"
        }
    ],
    "sg:phone":"+39 0375 790181",
    "wof:name":"Cassa Di Risparmio Di Parma, E Piacenza Spa",
    "wof:placetype":"venue"
},
  "geometry": {"coordinates":[10.4984,44.937008],"type":"Point"}
}