{
  "type": "Feature",
  "properties": {
    "iso:country":"IT",
    "sg:address":"30133 Venezia",
    "sg:city":"Giudecca",
    "sg:orig_category":"Tessuti Arredamento, Tende E Tappeti. Forniture Per Edilizia E Lavori Pubblici",
    "sg:phone":"+39 041 277 0415",
    "sg:postcode":"30133",
    "sg:province":"Venezia",
    "wof:name":"Hydromiro'",
    "wof:placetype":"venue"
},
  "geometry": {"coordinates":[12.330659,45.425575],"type":"Point"}
}