{
  "type": "Feature",
  "properties": {
    "addr:full":"Via Acrone 3; Agrigento",
    "addr:housenumber":"3",
    "addr:street":"Via Acrone",
    "iso:country":"IT",
    "sg:address":"Via Acrone 3; Agrigento",
    "sg:classifiers":[
        {
            "category":"Banks & Credit Unions",
            "subcategory":"Bank",
            "type":"Services"
        }
    ],
    "sg:phone":"+39 0922 595665",
    "wof:name":"Banca Di Roma",
    "wof:placetype":"venue"
},
  "geometry": {"coordinates":[13.585291,37.30872],"type":"Point"}
}