{
  "type": "Feature",
  "properties": {
    "iso:country":"IT",
    "sg:address":"59, Via Di Vittorio Giuseppe 43044 Collecchio",
    "sg:city":"Collecchio",
    "sg:classifiers":[
        {
            "category":"Professional",
            "subcategory":"Engineering",
            "type":"Services"
        }
    ],
    "sg:phone":"+39 0521 804273",
    "sg:postcode":"43044",
    "sg:province":"Parma",
    "sg:tags":[
        "machine",
        "-",
        "mechanical"
    ],
    "wof:name":"Gandolfi & Magnani (s.r.l.)",
    "wof:placetype":"venue"
},
  "geometry": {"coordinates":[10.259405,44.77005],"type":"Point"}
}