{
  "type": "Feature",
  "properties": {
    "addr:full":"98144 Messina Messina Messina 98144",
    "addr:postcode":"98144;98144",
    "iso:country":"IT",
    "sg:address":"98144 Messina",
    "sg:city":"Messina",
    "sg:orig_category":"Non-classified Establishments",
    "sg:phone":"+39 090 47948",
    "sg:postcode":"98144",
    "sg:province":"Messina",
    "wof:name":"Nuova Ortopedia Di Verduci Gianfranco & C. Sas",
    "wof:placetype":"venue"
},
  "geometry": {"coordinates":[15.562325,38.21365],"type":"Point"}
}