{
  "type": "Feature",
  "properties": {
    "iso:country":"IT",
    "sg:address":"12100 Cuneo",
    "sg:city":"Cuneo",
    "sg:orig_category":"Apparecchiature E Sistemi Per Magazzinaggio E Movimentazione. Macchine E Impianti Per Attivita' Commerciali Ed Artigianali. Macchine, Strumenti Ed Apparecchi Per Attivita' Industriali",
    "sg:phone":"+39 0171 693079",
    "sg:postcode":"12100",
    "sg:province":"Cuneo",
    "wof:name":"Renaldi Riccardo & C. Snc",
    "wof:placetype":"venue"
},
  "geometry": {"coordinates":[7.544938,44.386387],"type":"Point"}
}