{
  "type": "Feature",
  "properties": {
    "iso:country":"IT",
    "sg:address":"Ca Belfiore 16 23030 Borgonuovo",
    "sg:orig_category":"Lathe Centres, Rotating",
    "sg:phone":"+39 051 846760",
    "sg:postcode":"23030",
    "sg:province":"Sondrio",
    "sg:website":"www.tecnologiefrb.com",
    "wof:name":"Tecnologie F.r.b. Spa",
    "wof:placetype":"venue"
},
  "geometry": {"coordinates":[9.869333,46.171261],"type":"Point"}
}