{
  "type": "Feature",
  "properties": {
    "addr:full":"10, Via Dei Tornielli 28100 Novara Novara Novara 28100",
    "addr:postcode":"28100;28100",
    "addr:street":"Via Dei Tornielli",
    "iso:country":"IT",
    "sg:address":"10, Via Dei Tornielli 28100 Novara",
    "sg:city":"Novara",
    "sg:classifiers":[
        {
            "category":"Professional",
            "subcategory":"Computer Services",
            "type":"Services"
        }
    ],
    "sg:phone":"+39 0321 623200",
    "sg:postcode":"28100",
    "sg:province":"Novara",
    "sg:tags":[
        "information",
        "technology"
    ],
    "wof:name":"E.v.e. Software S.r.l.",
    "wof:placetype":"venue"
},
  "geometry": {"coordinates":[8.623451,45.445438],"type":"Point"}
}