{
  "type": "Feature",
  "properties": {
    "addr:full":"9, Via Coppi 41043 Formigine Formigine Modena 41043",
    "addr:postcode":"41043;41043",
    "addr:street":"Via Coppi",
    "iso:country":"IT",
    "sg:address":"9, Via Coppi 41043 Formigine",
    "sg:city":"Formigine",
    "sg:classifiers":[
        {
            "category":"Professional",
            "subcategory":"Engineering",
            "type":"Services"
        }
    ],
    "sg:phone":"+39 39059552784",
    "sg:postcode":"41043",
    "sg:province":"Modena",
    "sg:tags":[
        "machine",
        "-",
        "mechanical"
    ],
    "wof:name":"P.m.a Srl",
    "wof:placetype":"venue"
},
  "geometry": {"coordinates":[10.935554,44.554535],"type":"Point"}
}