{
  "type": "Feature",
  "properties": {
    "addr:full":"70011 Alberobello Alberobello Bari 70011",
    "addr:postcode":"70011;70011",
    "iso:country":"IT",
    "sg:address":"70011 Alberobello",
    "sg:city":"Alberobello",
    "sg:orig_category":"Prodotti Alimentari",
    "sg:phone":"+39 080 432 2249",
    "sg:postcode":"70011",
    "sg:province":"Bari",
    "sg:website":"http://www.assocobe.it",
    "wof:name":"Assocobe Srl",
    "wof:placetype":"venue"
},
  "geometry": {"coordinates":[17.2415275574,40.7883796692],"type":"Point"}
}