{
  "type": "Feature",
  "properties": {
    "addr:full":"Via Veneto 23 35040 Casale Di Scodosia Casale di Scodosia Padova 35040",
    "addr:housenumber":"23",
    "addr:postcode":"35040;35040",
    "addr:street":"Via Veneto",
    "iso:country":"IT",
    "sg:address":"Via Veneto 23 35040 Casale Di Scodosia",
    "sg:city":"Casale di Scodosia",
    "sg:classifiers":[
        {
            "category":"Manufacturing",
            "subcategory":"Furniture",
            "type":"Manufacturing & Wholesale Goods"
        }
    ],
    "sg:phone":"+39 0429 878350",
    "sg:postcode":"35040",
    "sg:province":"Padova",
    "sg:tags":[
        "solid",
        "wood"
    ],
    "sg:website":"www.emme-zeta.it",
    "wof:name":"Emme-zeta S.n.c. Di Zanolla Giorgio E Martinelli Lorenzo",
    "wof:placetype":"venue"
},
  "geometry": {"coordinates":[11.497603,45.183933],"type":"Point"}
}