{
  "type": "Feature",
  "properties": {
    "iso:country":"IT",
    "sg:address":"52028 Terranuova Bracciolini",
    "sg:city":"Terranuova Bracciolini",
    "sg:orig_category":"Arte Ed Artigianato Artistico",
    "sg:phone":"+39 055 919 9106",
    "sg:postcode":"52028",
    "sg:province":"Arezzo",
    "sg:website":"http://www.brillimetalli.it",
    "wof:name":"Lavorazione Metalli Brilli Snc Di Brilli & C.",
    "wof:placetype":"venue"
},
  "geometry": {"coordinates":[11.593027,43.563049],"type":"Point"}
}