{
  "type": "Feature",
  "properties": {
    "addr:full":"54, Via Tuderte 06054 Fratta Todina Fratta Todina Perugia 06054",
    "addr:postcode":"06054;06054",
    "addr:street":"Via Tuderte",
    "iso:country":"IT",
    "sg:address":"54, Via Tuderte 06054 Fratta Todina",
    "sg:city":"Fratta Todina",
    "sg:classifiers":[
        {
            "category":"Shopping",
            "subcategory":"Clothing, Apparel, & Fashions",
            "type":"Retail Goods"
        }
    ],
    "sg:phone":"+39 075 874 5311",
    "sg:postcode":"06054",
    "sg:province":"Perugia",
    "sg:tags":[
        "clothing",
        "accessory"
    ],
    "wof:name":"G.d.s. Di Cicioni Giuliano",
    "wof:placetype":"venue"
},
  "geometry": {"coordinates":[12.373378,42.852432],"type":"Point"}
}