{
  "type": "Feature",
  "properties": {
    "iso:country":"IT",
    "sg:address":"Via Roma, 22; Cocconato; 14023",
    "sg:city":"Cocconato",
    "sg:classifiers":[
        {
            "category":"Banks & Credit Unions",
            "subcategory":"Bank",
            "type":"Services"
        }
    ],
    "sg:phone":"+39 0141 907054",
    "sg:postcode":"14023",
    "sg:province":"Asti",
    "wof:name":"Banca Popolare Di Novara",
    "wof:placetype":"venue"
},
  "geometry": {"coordinates":[8.039583,45.087002],"type":"Point"}
}