{
  "type": "Feature",
  "properties": {
    "addr:full":"25020 Pavone Del Mella Pavone del Mella Brescia 25020",
    "addr:postcode":"25020;25020",
    "iso:country":"IT",
    "sg:address":"25020 Pavone Del Mella",
    "sg:city":"Pavone del Mella",
    "sg:orig_category":"Zootecnia E Pesca, Allevamento Piccoli Animali",
    "sg:phone":"+39 030 959592",
    "sg:postcode":"25020",
    "sg:province":"Brescia",
    "wof:name":"Morandi Pietro",
    "wof:placetype":"venue"
},
  "geometry": {"coordinates":[10.210838,45.296249],"type":"Point"}
}