{
  "type": "Feature",
  "properties": {
    "iso:country":"IT",
    "sg:address":"5, Via Fornara 21016 Luino",
    "sg:city":"Luino",
    "sg:classifiers":[
        {
            "category":"Professional",
            "subcategory":"Engineering",
            "type":"Services"
        }
    ],
    "sg:phone":"+39 0332 541111",
    "sg:postcode":"21016",
    "sg:province":"Varese",
    "sg:tags":[
        "machine",
        "-",
        "mechanical"
    ],
    "wof:name":"Ratti Michele S.p.a.",
    "wof:placetype":"venue"
},
  "geometry": {"coordinates":[8.72909,45.995098],"type":"Point"}
}