{
  "type": "Feature",
  "properties": {
    "addr:full":"7, V. Partigiani D'italia 43029 Traversetolo Traversetolo Parma 43029",
    "addr:housenumber":"7",
    "addr:postcode":"43029;43029",
    "addr:street":"V. Partigiani D'Italia",
    "iso:country":"IT",
    "sg:address":"7, V. Partigiani D'italia 43029 Traversetolo",
    "sg:city":"Traversetolo",
    "sg:classifiers":[
        {
            "category":"Professional",
            "subcategory":"Engineering",
            "type":"Services"
        }
    ],
    "sg:phone":"+39 0521 341348",
    "sg:postcode":"43029",
    "sg:province":"Parma",
    "sg:tags":[
        "machine",
        "-",
        "mechanical"
    ],
    "sg:website":"http://www.epromsrl:ws_end: :mark:ws:http://www.paginegialle.it/epromsrl",
    "wof:name":"E.pro.m.",
    "wof:placetype":"venue"
},
  "geometry": {"coordinates":[10.303876,44.641018],"type":"Point"}
}