{
  "type": "Feature",
  "properties": {
    "iso:country":"IT",
    "sg:address":"20123 Milano",
    "sg:city":"Milano",
    "sg:orig_category":"Banche E Servizi Finanziari",
    "sg:phone":"+39 02 4801 1088",
    "sg:postcode":"20123",
    "sg:province":"Milano",
    "wof:name":"Studio Uboldi S.a.s. Di Uboldi Vittorio & C.",
    "wof:placetype":"venue"
},
  "geometry": {"coordinates":[9.174264,45.465729],"type":"Point"}
}