{
  "type": "Feature",
  "properties": {
    "iso:country":"IT",
    "sg:address":"84010 Tramonti",
    "sg:city":"Tramonti",
    "sg:orig_category":"Caseifici",
    "sg:phone":"+39 089 876920",
    "sg:postcode":"84010",
    "sg:province":"Salerno",
    "wof:name":"Antica Latteria Di Tramonti Srl",
    "wof:placetype":"venue"
},
  "geometry": {"coordinates":[14.649222,40.693462],"type":"Point"}
}