{
  "type": "Feature",
  "properties": {
    "addr:full":"07020 Palau Palau Olbia-Tempio 07020",
    "addr:postcode":"07020;07020",
    "iso:country":"IT",
    "sg:address":"07020 Palau",
    "sg:city":"Palau",
    "sg:orig_category":"Scuole E Servizi Scolastici. Servizi Per Lo Sport E Il Tempo Libero",
    "sg:phone":"+39 0789 702002",
    "sg:postcode":"07020",
    "sg:province":"Olbia-Tempio",
    "wof:name":"Velamarepiu' S.r.l.",
    "wof:placetype":"venue"
},
  "geometry": {"coordinates":[9.56563,40.909538],"type":"Point"}
}