{
  "type": "Feature",
  "properties": {
    "iso:country":"IT",
    "sg:address":"30021 Caorle",
    "sg:city":"Caorle",
    "sg:orig_category":"Ristorazione E Locali Pubblici Affini. Ristoranti Ed Esercizi Affini. Servizi Ausiliari Di Ristorazione E Di Intrattenimento",
    "sg:phone":"+39 0421 81202",
    "sg:postcode":"30021",
    "sg:province":"Venezia",
    "sg:website":"http://hotelcarinzia.it",
    "wof:name":"Hotel Carinzia",
    "wof:placetype":"venue"
},
  "geometry": {"coordinates":[12.91268,45.648376],"type":"Point"}
}