{
  "type": "Feature",
  "properties": {
    "iso:country":"IT",
    "sg:address":"25027 Quinzano D'oglio",
    "sg:classifiers":[
        {
            "category":"Train Station",
            "subcategory":"Light Rail",
            "type":"Transportation"
        }
    ],
    "sg:phone":"+39 030 933 6587",
    "sg:postcode":"25027",
    "sg:province":"Brescia",
    "sg:tags":[
        "plating",
        "treatments",
        "metals",
        "heat",
        "electroforming",
        "surface"
    ],
    "wof:name":"Valsecchi Giovanni",
    "wof:placetype":"venue"
},
  "geometry": {"coordinates":[9.9925317764,45.3131408691],"type":"Point"}
}