{
  "type": "Feature",
  "properties": {
    "iso:country":"IT",
    "sg:address":"12, Via Tangoni 16030 Casarza Ligure",
    "sg:city":"Casarza Ligure",
    "sg:classifiers":[
        {
            "category":"Manufacturing",
            "subcategory":"Rubber & Plastics",
            "type":"Manufacturing & Wholesale Goods"
        }
    ],
    "sg:phone":"+39 0185 469086",
    "sg:postcode":"16030",
    "sg:province":"Genova",
    "wof:name":"A.m.r. Di Tarditi Giambattista",
    "wof:placetype":"venue"
},
  "geometry": {"coordinates":[9.4563007355,44.2718391418],"type":"Point"}
}