{
  "type": "Feature",
  "properties": {
    "iso:country":"IT",
    "sg:address":"28/r, Via Fiasella Domenico 16121 Genova",
    "sg:city":"Genova",
    "sg:classifiers":[
        {
            "category":"Shopping",
            "subcategory":"Clothing, Apparel, & Fashions",
            "type":"Retail Goods"
        }
    ],
    "sg:phone":"+39 39010561114",
    "sg:postcode":"16121",
    "sg:province":"Genova",
    "sg:tags":[
        "clothes"
    ],
    "wof:name":"Berti (s.r.l.)",
    "wof:placetype":"venue"
},
  "geometry": {"coordinates":[8.933989,44.407063],"type":"Point"}
}