{
  "type": "Feature",
  "properties": {
    "iso:country":"IT",
    "sg:address":"40122 Bologna",
    "sg:city":"Bologna",
    "sg:orig_category":"Servizi E Lavori Per Agricoltura E Zootecnia. Servizi E Lavori Per Ecologia E Smaltimento Rifiuti",
    "sg:phone":"+39 051 649 3527",
    "sg:postcode":"40122",
    "sg:province":"Bologna",
    "wof:name":"Consorzio Della Chiusa Di Casalecchio E Del Canale Di Reno",
    "wof:placetype":"venue"
},
  "geometry": {"coordinates":[11.328602,44.497372],"type":"Point"}
}