{
  "type": "Feature",
  "properties": {
    "iso:country":"IT",
    "sg:address":"104, Via Faleria 63018 Porto Sant'elpidio",
    "sg:classifiers":[
        {
            "category":"Personal",
            "subcategory":"Shoe Repair & Shine",
            "type":"Services"
        }
    ],
    "sg:phone":"+39 0734 997258",
    "sg:postcode":"63018",
    "sg:province":"Ascoli Piceno",
    "sg:tags":[
        "leather"
    ],
    "wof:name":"Calzaturificio Mauro S.r.l.",
    "wof:placetype":"venue"
},
  "geometry": {"coordinates":[13.773438,43.24044],"type":"Point"}
}