{
  "type": "Feature",
  "properties": {
    "iso:country":"IT",
    "sg:address":"13, V. Giabbio 23834 Premana",
    "sg:city":"Premana",
    "sg:classifiers":[
        {
            "category":"Shopping",
            "type":"Retail Goods"
        }
    ],
    "sg:phone":"+39 0341 890377",
    "sg:postcode":"23834",
    "sg:province":"Lecco",
    "sg:tags":[
        "finished",
        "-",
        "metallic"
    ],
    "wof:name":"Premax",
    "wof:placetype":"venue"
},
  "geometry": {"coordinates":[9.4218044281,46.0482521057],"type":"Point"}
}