{
  "type": "Feature",
  "properties": {
    "addr:full":"26, Via Appia 81052 Pignataro Maggiore Pignataro Maggiore Caserta 81052",
    "addr:housenumber":"maggiore",
    "addr:postcode":"81052;81052",
    "addr:street":"Via Appia;Maggiore",
    "iso:country":"IT",
    "sg:address":"26, Via Appia 81052 Pignataro Maggiore",
    "sg:city":"Pignataro Maggiore",
    "sg:classifiers":[
        {
            "category":"Manufacturing",
            "subcategory":"Rubber & Plastics",
            "type":"Manufacturing & Wholesale Goods"
        }
    ],
    "sg:phone":"+39 0823 653137",
    "sg:postcode":"81052",
    "sg:province":"Caserta",
    "wof:name":"Politrasf S.r.l.",
    "wof:placetype":"venue"
},
  "geometry": {"coordinates":[14.3321943283,41.0754165649],"type":"Point"}
}