{
  "type": "Feature",
  "properties": {
    "iso:country":"IT",
    "sg:address":"9, Via Monte Grappa 28017 San Maurizio D'opaglio",
    "sg:classifiers":[
        {
            "category":"Manufacturing",
            "subcategory":"Metals",
            "type":"Manufacturing & Wholesale Goods"
        }
    ],
    "sg:phone":"+39 39032296153",
    "sg:postcode":"28017",
    "sg:province":"Novara",
    "sg:tags":[
        "processing"
    ],
    "wof:name":"Cromature Gioira Giulio (s.r.l.)",
    "wof:placetype":"venue"
},
  "geometry": {"coordinates":[8.395108223,45.7787818909],"type":"Point"}
}