{
  "type": "Feature",
  "properties": {
    "iso:country":"IT",
    "sg:address":"10020 Cambiano",
    "sg:city":"Cambiano",
    "sg:orig_category":"Arredo Cucina Ed Elettrodomestici. Frigotecnica, Apparecchiature E Servizi. Elettrodomestici",
    "sg:phone":"+39 011 945 7210",
    "sg:postcode":"10020",
    "sg:province":"Torino",
    "wof:name":"Salmasi Giovanni",
    "wof:placetype":"venue"
},
  "geometry": {"coordinates":[7.773129,44.969387],"type":"Point"}
}