{
  "type": "Feature",
  "properties": {
    "iso:country":"IT",
    "sg:address":"06129 Perugia",
    "sg:city":"Perugia",
    "sg:orig_category":"Abbigliamento Sportivo - Produzione E Ingrosso",
    "sg:phone":"+39 075 500 9365",
    "sg:postcode":"06129",
    "sg:province":"Perugia",
    "wof:name":"Domauto Snc",
    "wof:placetype":"venue"
},
  "geometry": {"coordinates":[12.368846,43.090847],"type":"Point"}
}