{
  "type": "Feature",
  "properties": {
    "iso:country":"IT",
    "sg:address":"27100 Pavia",
    "sg:city":"Pavia",
    "sg:orig_category":"Automobili E Mezzi Di Trasporto",
    "sg:phone":"+39 0382 26269",
    "sg:postcode":"27100",
    "sg:province":"Pavia",
    "wof:name":"F.lli Maggi Snc",
    "wof:placetype":"venue"
},
  "geometry": {"coordinates":[9.150397,45.17762],"type":"Point"}
}