{
  "type": "Feature",
  "properties": {
    "addr:full":"7, Via Goito 20121 Milano Milano Milano 20121",
    "addr:postcode":"20121;20121",
    "addr:street":"Via Goito",
    "iso:country":"IT",
    "sg:address":"7, Via Goito 20121 Milano",
    "sg:city":"Milano",
    "sg:classifiers":[
        {
            "category":"Professional",
            "subcategory":"Business Services",
            "type":"Services"
        }
    ],
    "sg:phone":"+39 39026597957",
    "sg:postcode":"20121",
    "sg:province":"Milano",
    "sg:tags":[
        "advice"
    ],
    "wof:name":"C.d.m. Castelli Design Milano Srl",
    "wof:placetype":"venue"
},
  "geometry": {"coordinates":[9.189025,45.474392],"type":"Point"}
}