{
  "type": "Feature",
  "properties": {
    "addr:full":"41038 San Felice Sul Panaro San Felice sul Panaro Modena 41038",
    "addr:housenumber":"41038",
    "addr:postcode":"panaro;41038",
    "iso:country":"IT",
    "sg:address":"41038 San Felice Sul Panaro",
    "sg:city":"San Felice sul Panaro",
    "sg:orig_category":"Macchine Ed Impianti Per Edilizia E Lavori Pubblici. Macchine, Strumenti Ed Apparecchi Per Attivita' Industriali",
    "sg:phone":"+39 0535 85438",
    "sg:postcode":"41038",
    "sg:province":"Modena",
    "wof:name":"W.g.s. Snc World Glass Service",
    "wof:placetype":"venue"
},
  "geometry": {"coordinates":[11.113351,44.832611],"type":"Point"}
}