{
  "type": "Feature",
  "properties": {
    "iso:country":"IT",
    "sg:address":"23876 Monticello Brianza",
    "sg:city":"Monticello Brianza",
    "sg:orig_category":"Alimentari - Produzione E Ingrosso",
    "sg:phone":"+39 039 920 6717",
    "sg:postcode":"23876",
    "sg:province":"Lecco",
    "wof:name":"Distrifood Srl",
    "wof:placetype":"venue"
},
  "geometry": {"coordinates":[9.294604,45.71376],"type":"Point"}
}