{
  "type": "Feature",
  "properties": {
    "addr:full":"09070 San Vero Milis Milis Oristano 09070",
    "addr:postcode":"09070;09070",
    "iso:country":"IT",
    "sg:address":"09070 San Vero Milis",
    "sg:city":"Milis",
    "sg:orig_category":"Elettricisti",
    "sg:phone":"+39 0783 53217",
    "sg:postcode":"09070",
    "sg:province":"Oristano",
    "sg:website":"http://www.gtelettrica.it",
    "wof:name":"G.t. Elettrica Snc Di Pinna & Rovere",
    "wof:placetype":"venue"
},
  "geometry": {"coordinates":[8.601506,40.015553],"type":"Point"}
}