{
  "type": "Feature",
  "properties": {
    "addr:full":"78, V. Seregno 20033 Desio Desio Milano 20033",
    "addr:housenumber":"78",
    "addr:postcode":"20033;20033",
    "addr:street":"V. Seregno",
    "iso:country":"IT",
    "sg:address":"78, V. Seregno 20033 Desio",
    "sg:city":"Desio",
    "sg:classifiers":[
        {
            "category":"Home & Garden",
            "subcategory":"Home Furnishings",
            "type":"Retail Goods"
        }
    ],
    "sg:phone":"+39 036 230 2655",
    "sg:postcode":"20033",
    "sg:province":"Milano",
    "sg:tags":[
        "household"
    ],
    "sg:website":"http://www.aeffedesio.it",
    "wof:name":"Aeffe Agostoni",
    "wof:placetype":"venue"
},
  "geometry": {"coordinates":[9.203082,45.625473],"type":"Point"}
}