{
  "type": "Feature",
  "properties": {
    "addr:full":"20124 Milano Milano Milano 20124",
    "addr:postcode":"20124;20124",
    "iso:country":"IT",
    "sg:address":"20124 Milano",
    "sg:city":"Milano",
    "sg:orig_category":"Studi E Consulenze Tecniche E Industriali. Servizi E Lavori Per Edilizia E Lavori Pubblici. Professionisti - Studi E Servizi Ed Associazioni Di Interesse Aziendale",
    "sg:phone":"+39 02 669 6477",
    "sg:postcode":"20124",
    "sg:province":"Milano",
    "sg:website":"http://www.centocase.com",
    "wof:name":"Centocase Servizi Immobiliari",
    "wof:placetype":"venue"
},
  "geometry": {"coordinates":[9.213546,45.485706],"type":"Point"}
}