{
  "type": "Feature",
  "properties": {
    "iso:country":"IT",
    "sg:address":"Via Statale, 15 - Castelbello 39020 Castelbello Ciardes",
    "sg:city":"Castelbello",
    "sg:orig_category":"Rolls",
    "sg:phone":"+39 0473 624399",
    "sg:postcode":"39020",
    "sg:province":"Bolzano/Bozen",
    "wof:name":"Preiss Christine & C. Snc",
    "wof:placetype":"venue"
},
  "geometry": {"coordinates":[10.92479,46.634621],"type":"Point"}
}