{
  "type": "Feature",
  "properties": {
    "addr:full":"62, Via Pannilani 22100 Como Como Como 22100",
    "addr:postcode":"22100;22100",
    "addr:street":"Via Pannilani",
    "iso:country":"IT",
    "sg:address":"62, Via Pannilani 22100 Como",
    "sg:city":"Como",
    "sg:classifiers":[
        {
            "category":"Shopping",
            "subcategory":"Crafts & Fabrics",
            "type":"Retail Goods"
        }
    ],
    "sg:phone":"+39 39031274253",
    "sg:postcode":"22100",
    "sg:province":"Como",
    "wof:name":"Stamperia Frigerio E Cassina (s.r.l.)",
    "wof:placetype":"venue"
},
  "geometry": {"coordinates":[9.1143960953,45.800983429],"type":"Point"}
}