{
  "type": "Feature",
  "properties": {
    "iso:country":"IT",
    "sg:address":"Via Cupa 23 80030 Liveri",
    "sg:city":"Liveri",
    "sg:classifiers":[
        {
            "category":"Home & Garden",
            "subcategory":"Home Furnishings",
            "type":"Retail Goods"
        }
    ],
    "sg:phone":"+39 081 825 5206",
    "sg:postcode":"80030",
    "sg:province":"Napoli",
    "sg:tags":[
        "candle",
        "beeswax"
    ],
    "sg:website":"www.anic-italia.com",
    "wof:name":"Amedeo Nappi Industria Ceraria Srl",
    "wof:placetype":"venue"
},
  "geometry": {"coordinates":[14.564608,40.901901],"type":"Point"}
}