{
  "type": "Feature",
  "properties": {
    "iso:country":"IT",
    "sg:address":"20122 Milano",
    "sg:city":"Milano",
    "sg:orig_category":"Elettronica Professionale E Di Consumo. Tempo Libero - Articoli E Forniture",
    "sg:phone":"+39 02 7600 1828",
    "sg:postcode":"20122",
    "sg:province":"Milano",
    "wof:name":"Gameland Sas Di Pasqua Plati & C.",
    "wof:placetype":"venue"
},
  "geometry": {"coordinates":[9.196948,45.464809],"type":"Point"}
}