{
  "type": "Feature",
  "properties": {
    "iso:country":"IT",
    "sg:address":"38/40, Via Calendone 23887 Olgiate Molgora",
    "sg:city":"Olgiate Molgora",
    "sg:classifiers":[
        {
            "category":"Communications",
            "subcategory":"Television Station",
            "type":"Services"
        }
    ],
    "sg:phone":"+39 039 991 0080",
    "sg:postcode":"23887",
    "sg:province":"Lecco",
    "sg:tags":[
        "equipment",
        "optical",
        "instrument"
    ],
    "wof:name":"Ottica Artigiana Di Colombo Angelo & C. S.n.c.",
    "wof:placetype":"venue"
},
  "geometry": {"coordinates":[9.403895,45.719326],"type":"Point"}
}