{
  "type": "Feature",
  "properties": {
    "iso:country":"IT",
    "sg:address":"97019 Vittoria",
    "sg:city":"Vittoria",
    "sg:orig_category":"Ceramiche Per Pavimenti E Rivestimenti - Vendita Al Dettaglio",
    "sg:phone":"+39 0932 863433",
    "sg:postcode":"97019",
    "sg:province":"Ragusa",
    "wof:name":"Progetto Casa Di Impoco E Giacinti Snc",
    "wof:placetype":"venue"
},
  "geometry": {"coordinates":[14.536572,36.950592],"type":"Point"}
}