{
  "type": "Feature",
  "properties": {
    "iso:country":"IT",
    "sg:address":"Lucca, Lu",
    "sg:classifiers":[
        {
            "category":"Banks & Credit Unions",
            "subcategory":"Bank",
            "type":"Services"
        }
    ],
    "wof:name":"Ducato Spa",
    "wof:placetype":"venue"
},
  "geometry": {"coordinates":[10.507994,43.843014],"type":"Point"}
}