{
  "type": "Feature",
  "properties": {
    "addr:full":"30, Via Como 23807 Merate Merate Lecco 23807",
    "addr:postcode":"23807;23807",
    "addr:street":"Via Como",
    "iso:country":"IT",
    "sg:address":"30, Via Como 23807 Merate",
    "sg:city":"Merate",
    "sg:classifiers":[
        {
            "category":"Manufacturing",
            "subcategory":"Paper Products",
            "type":"Manufacturing & Wholesale Goods"
        }
    ],
    "sg:phone":"+39 039 990 8461",
    "sg:postcode":"23807",
    "sg:province":"Lecco",
    "sg:tags":[
        "cardboard"
    ],
    "wof:name":"Casalini & Viscardi (s.r.l.)",
    "wof:placetype":"venue"
},
  "geometry": {"coordinates":[9.3919839859,45.7310600281],"type":"Point"}
}