{
  "type": "Feature",
  "properties": {
    "addr:full":"21, Viale Moro Aldo 24021 Albino Albino Bergamo 24021",
    "addr:housenumber":"21",
    "addr:postcode":"24021;24021",
    "addr:street":"Viale Moro Aldo",
    "iso:country":"IT",
    "sg:address":"21, Viale Moro Aldo 24021 Albino",
    "sg:city":"Albino",
    "sg:classifiers":[
        {
            "category":"Manufacturing",
            "subcategory":"Metals",
            "type":"Manufacturing & Wholesale Goods"
        }
    ],
    "sg:phone":"+39 39035751350",
    "sg:postcode":"24021",
    "sg:province":"Bergamo",
    "sg:tags":[
        "metallurgy",
        "metalworking"
    ],
    "wof:name":"Fonderia Custall Degli Eredi Di Paolo Vedovati (s.r.l.)",
    "wof:placetype":"venue"
},
  "geometry": {"coordinates":[9.6699523926,45.6949043274],"type":"Point"}
}