{
  "type": "Feature",
  "properties": {
    "addr:full":"70057 Palese Macchie BA",
    "addr:postcode":"70057",
    "addr:street":"Palese",
    "iso:country":"IT",
    "sg:address":"70057 Palese Macchie",
    "sg:classifiers":[
        {
            "category":"Health Services",
            "subcategory":"Health Practitioner",
            "type":"Services"
        }
    ],
    "sg:phone":"+39 080 530 0029",
    "sg:province":"BA",
    "sg:tags":[
        "medici"
    ],
    "wof:name":"Maiorano Vincenzo",
    "wof:placetype":"venue"
},
  "geometry": {"coordinates":[16.883186,41.047287],"type":"Point"}
}