{
  "type": "Feature",
  "properties": {
    "iso:country":"IT",
    "sg:address":"86042 Campomarino",
    "sg:city":"Campomarino",
    "sg:classifiers":[
        {
            "category":"Health Services",
            "subcategory":"Health Practitioner",
            "type":"Services"
        }
    ],
    "sg:phone":"+39 0875 539249",
    "sg:postcode":"86042",
    "sg:province":"Campobasso",
    "sg:tags":[
        "medici"
    ],
    "wof:name":"Dell'orco Rosa Lucia",
    "wof:placetype":"venue"
},
  "geometry": {"coordinates":[15.032839,41.956455],"type":"Point"}
}