{
  "type": "Feature",
  "properties": {
    "iso:country":"IT",
    "sg:address":"51030 Serravalle Pistoiese",
    "sg:city":"Serravalle Pistoiese",
    "sg:orig_category":"Forniture Per Attivita' Industriali",
    "sg:phone":"+39 0573 919140",
    "sg:postcode":"51030",
    "sg:province":"Pistoia",
    "wof:name":"Pulitex Di Cantalupo C.",
    "wof:placetype":"venue"
},
  "geometry": {"coordinates":[10.8220062256,43.8981704712],"type":"Point"}
}