{
  "type": "Feature",
  "properties": {
    "iso:country":"IT",
    "sg:address":"23900 Lecco",
    "sg:city":"Lecco",
    "sg:orig_category":"Galvanotecnica - Impianti, Macchine E Forniture",
    "sg:phone":"+39 0341 250250",
    "sg:postcode":"23900",
    "sg:province":"Lecco",
    "wof:name":"Logaglio Spa",
    "wof:placetype":"venue"
},
  "geometry": {"coordinates":[9.409532,45.858814],"type":"Point"}
}