{
  "type": "Feature",
  "properties": {
    "iso:country":"IT",
    "sg:address":"22036 Erba",
    "sg:city":"Erba",
    "sg:orig_category":"Automobili - Commercio",
    "sg:phone":"+39 031 645959",
    "sg:postcode":"22036",
    "sg:province":"Como",
    "wof:name":"Autocomo Srl - Autorizzato Renault",
    "wof:placetype":"venue"
},
  "geometry": {"coordinates":[9.242135,45.799458],"type":"Point"}
}