{
  "type": "Feature",
  "properties": {
    "iso:country":"IT",
    "sg:address":"10034 Chivasso",
    "sg:city":"Chivasso",
    "sg:orig_category":"Banche E Servizi Finanziari. Acqua, Luce, Gas E Societa' Di Esercizio Pubblico",
    "sg:phone":"+39 011 911 6388",
    "sg:postcode":"10034",
    "sg:province":"Torino",
    "wof:name":"Alessandro Maurizio",
    "wof:placetype":"venue"
},
  "geometry": {"coordinates":[7.677423,45.074982],"type":"Point"}
}