{
  "type": "Feature",
  "properties": {
    "iso:country":"IT",
    "sg:address":"3, V. Pitagora 47100 Forli'",
    "sg:classifiers":[
        {
            "category":"Home & Garden",
            "subcategory":"Home Furnishings",
            "type":"Retail Goods"
        }
    ],
    "sg:phone":"+39 0543 708311",
    "sg:postcode":"47100",
    "sg:province":"Forl\u00ec-Cesena",
    "sg:tags":[
        "household"
    ],
    "sg:website":"http://www.gammarr.it:ws_end: :mark:ws:http://www.paginegialle.it/gammaarr",
    "wof:name":"Gamma Arredamenti International Spa",
    "wof:placetype":"venue"
},
  "geometry": {"coordinates":[11.999903,44.221947],"type":"Point"}
}