{
  "type": "Feature",
  "properties": {
    "iso:country":"IT",
    "sg:address":"30026 Portogruaro",
    "sg:city":"Portogruaro",
    "sg:orig_category":"Forniture Per Attivita' Industriali",
    "sg:phone":"+39 0421 271593",
    "sg:postcode":"30026",
    "sg:province":"Venezia",
    "wof:name":"Zaccheo Gaetano",
    "wof:placetype":"venue"
},
  "geometry": {"coordinates":[12.8713626862,45.7682342529],"type":"Point"}
}