{
  "type": "Feature",
  "properties": {
    "addr:full":"Via Ricci, 21- Alberghi 51017 Pescia Pescia Pistoia 51017",
    "addr:housenumber":"21",
    "addr:postcode":"51017;51017",
    "addr:street":"Via Ricci",
    "iso:country":"IT",
    "sg:address":"Via Ricci, 21- Alberghi 51017 Pescia",
    "sg:city":"Pescia",
    "sg:classifiers":[
        {
            "category":"Farming",
            "subcategory":"Nursery",
            "type":"Manufacturing & Wholesale Goods"
        }
    ],
    "sg:phone":"+39 0572 4910",
    "sg:postcode":"51017",
    "sg:province":"Pistoia",
    "sg:tags":[
        "tree",
        "seedling"
    ],
    "sg:website":"www.santvivai.it",
    "wof:name":"Santoni Eugenio Giovanni S.r.l",
    "wof:placetype":"venue"
},
  "geometry": {"coordinates":[10.696786,43.867722],"type":"Point"}
}