{
  "type": "Feature",
  "properties": {
    "iso:country":"IT",
    "sg:address":"35020 Albignasego",
    "sg:city":"Albignasego",
    "sg:orig_category":"Climatizzazione E Condizionamento, Apparecchiature E Servizi",
    "sg:phone":"+39 049 862 9099",
    "sg:postcode":"35020",
    "sg:province":"Padova",
    "sg:website":"http://www.cuoghi-luigi.it",
    "wof:name":"Cuoghi Luigi Snc",
    "wof:placetype":"venue"
},
  "geometry": {"coordinates":[11.831532,45.344246],"type":"Point"}
}