{
  "type": "Feature",
  "properties": {
    "addr:full":"35020 Albignasego Albignasego Padova 35020",
    "addr:postcode":"35020;35020",
    "iso:country":"IT",
    "sg:address":"35020 Albignasego",
    "sg:city":"Albignasego",
    "sg:orig_category":"Depurazione E Trattamento Delle Acque - Impianti Ed Apparecchi",
    "sg:phone":"+39 049 712424",
    "sg:postcode":"35020",
    "sg:province":"Padova",
    "sg:website":"http://www.mmc.it",
    "wof:name":"Mmc Srl",
    "wof:placetype":"venue"
},
  "geometry": {"coordinates":[11.855717,45.347778],"type":"Point"}
}