{
  "type": "Feature",
  "properties": {
    "iso:country":"IT",
    "sg:address":"20013 Magenta",
    "sg:city":"Magenta",
    "sg:orig_category":"Scuole E Servizi Scolastici. Servizi Per Lo Sport E Il Tempo Libero",
    "sg:phone":"+39 02 9729 0787",
    "sg:postcode":"20013",
    "sg:province":"Milano",
    "wof:name":"Futura Danze",
    "wof:placetype":"venue"
},
  "geometry": {"coordinates":[8.8870620728,45.4529151917],"type":"Point"}
}