{
  "type": "Feature",
  "properties": {
    "iso:country":"IT",
    "sg:address":"31046 Oderzo",
    "sg:city":"Oderzo",
    "sg:orig_category":"Informatica - Consulenza E Servizi. Automazione E Macchine Per Ufficio. Servizi Ausiliari Di Analisi, Controllo E Ricerca. Servizi Per Aziende, Manifestazioni E Supporto Agli Scambi Commerciali",
    "sg:phone":"+39 0422 200611",
    "sg:postcode":"31046",
    "sg:province":"Treviso",
    "sg:website":"http://www.naisoft.it",
    "wof:name":"Nai Srl",
    "wof:placetype":"venue"
},
  "geometry": {"coordinates":[12.492403,45.797562],"type":"Point"}
}