{
  "type": "Feature",
  "properties": {
    "addr:full":"70022 Altamura Altamura Bari 70022",
    "addr:postcode":"70022;70022",
    "iso:country":"IT",
    "sg:address":"70022 Altamura",
    "sg:city":"Altamura",
    "sg:orig_category":"Servizi E Lavori Per Edilizia E Lavori Pubblici. Servizi Ausiliari Di Sorveglianza, Manutenzione E Pulizia",
    "sg:phone":"+39 080 314 6934",
    "sg:postcode":"70022",
    "sg:province":"Bari",
    "wof:name":"Elettrica Tiemme Di Tafuno Massimo",
    "wof:placetype":"venue"
},
  "geometry": {"coordinates":[16.870962,41.125393],"type":"Point"}
}