{
  "type": "Feature",
  "properties": {
    "addr:full":"65, Via Cadorna 22060 Carugo Carugo Como 22060",
    "addr:postcode":"22060;22060",
    "addr:street":"Via Cadorna",
    "iso:country":"IT",
    "sg:address":"65, Via Cadorna 22060 Carugo",
    "sg:city":"Carugo",
    "sg:classifiers":[
        {
            "category":"Home & Garden",
            "subcategory":"Home Furnishings",
            "type":"Retail Goods"
        }
    ],
    "sg:phone":"+39 39031745082",
    "sg:postcode":"22060",
    "sg:province":"Como",
    "sg:tags":[
        "household"
    ],
    "wof:name":"Frigerio Fratelli B. & C. (s.n.c.)",
    "wof:placetype":"venue"
},
  "geometry": {"coordinates":[9.188828,45.705235],"type":"Point"}
}