{
  "type": "Feature",
  "properties": {
    "addr:full":"Via G. Carissimi 26; Rome; 00198 Roma 00198",
    "addr:housenumber":"26",
    "addr:postcode":"00198;00198",
    "addr:street":"Via G. Carissimi",
    "iso:country":"IT",
    "sg:address":"Via G. Carissimi 26; Rome; 00198",
    "sg:classifiers":[
        {
            "category":"Travel",
            "subcategory":"Travel Agent",
            "type":"Entertainment"
        }
    ],
    "sg:phone":"+39 390 685 2101",
    "sg:postcode":"00198",
    "sg:province":"Roma",
    "sg:website":"thecharminghotels.com",
    "wof:name":"The Charming Hotels Of The World",
    "wof:placetype":"venue"
},
  "geometry": {"coordinates":[12.492558,41.919518],"type":"Point"}
}