{
  "type": "Feature",
  "properties": {
    "addr:full":"15048 Valenza Valenza Alessandria 15048",
    "addr:postcode":"15048;15048",
    "iso:country":"IT",
    "sg:address":"15048 Valenza",
    "sg:city":"Valenza",
    "sg:orig_category":"Gioielleria, Oreficeria E Argenteria. Shopping",
    "sg:phone":"+39 0131 951050",
    "sg:postcode":"15048",
    "sg:province":"Alessandria",
    "wof:name":"4c Di Caniggia Massimiliano",
    "wof:placetype":"venue"
},
  "geometry": {"coordinates":[8.618973,44.917297],"type":"Point"}
}