{
  "type": "Feature",
  "properties": {
    "iso:country":"IT",
    "sg:address":"98122 Messina",
    "sg:city":"Messina",
    "sg:orig_category":"Scuole E Servizi Scolastici",
    "sg:phone":"+39 090 774059",
    "sg:postcode":"98122",
    "sg:province":"Messina",
    "wof:name":"Istituto S.brigida",
    "wof:placetype":"venue"
},
  "geometry": {"coordinates":[15.547816,38.192719],"type":"Point"}
}