{
  "type": "Feature",
  "properties": {
    "iso:country":"IT",
    "sg:address":"Lott. Brusada 31057 Silea",
    "sg:city":"Silea",
    "sg:classifiers":[
        {
            "category":"Bars & Pubs",
            "subcategory":"Nightclub",
            "type":"Food & Drink"
        }
    ],
    "sg:phone":"+39 0422 362430",
    "sg:postcode":"31057",
    "sg:province":"Treviso",
    "sg:tags":[
        "cake",
        "bread"
    ],
    "wof:name":"La Cialcon Di Vanin Luigi E Roberto & C. (s.n.c.)",
    "wof:placetype":"venue"
},
  "geometry": {"coordinates":[12.309198,45.650059],"type":"Point"}
}