{
  "type": "Feature",
  "properties": {
    "addr:full":"20121 Milano Milano Milano 20121",
    "addr:postcode":"20121;20121",
    "iso:country":"IT",
    "sg:address":"20121 Milano",
    "sg:city":"Milano",
    "sg:orig_category":"Chiese Ed Associazioni Religiose",
    "sg:phone":"+39 02 2900 2053",
    "sg:postcode":"20121",
    "sg:province":"Milano",
    "wof:name":"Istituto Suore Francescane Missionarie Di Gesu' Bambino",
    "wof:placetype":"venue"
},
  "geometry": {"coordinates":[9.182832,45.478207],"type":"Point"}
}