{
  "type": "Feature",
  "properties": {
    "iso:country":"IT",
    "sg:address":"20141 Milano",
    "sg:city":"Milano",
    "sg:orig_category":"Tempo Libero - Articoli E Forniture. Regalistica Aziendale",
    "sg:phone":"+39 02 846 5941",
    "sg:postcode":"20141",
    "sg:province":"Milano",
    "wof:name":"Maggi Coniature Srl",
    "wof:placetype":"venue"
},
  "geometry": {"coordinates":[9.18986,45.44022],"type":"Point"}
}