{
  "type": "Feature",
  "properties": {
    "addr:full":"Via Ricasoli 60, 53100 Siena, Si Siena Siena 53100",
    "addr:housenumber":"60",
    "addr:postcode":"53100;53100",
    "addr:street":"Via Ricasoli",
    "iso:country":"IT",
    "sg:address":"Via Ricasoli 60, 53100 Siena, Si",
    "sg:city":"Siena",
    "sg:classifiers":[
        {
            "category":"Banks & Credit Unions",
            "subcategory":"Bank",
            "type":"Services"
        }
    ],
    "sg:postcode":"53100",
    "sg:province":"Siena",
    "wof:name":"Consorzio Operativo Gruppo Mps",
    "wof:placetype":"venue"
},
  "geometry": {"coordinates":[11.323449,43.326328],"type":"Point"}
}