{
  "type": "Feature",
  "properties": {
    "iso:country":"IT",
    "sg:address":"Via C Battisti 55 24062 Costa Volpino",
    "sg:city":"Costa Volpino",
    "sg:classifiers":[
        {
            "category":"Manufacturing",
            "subcategory":"Tools & Machinery",
            "type":"Manufacturing & Wholesale Goods"
        }
    ],
    "sg:phone":"+39 035 970403",
    "sg:postcode":"24062",
    "sg:province":"Bergamo",
    "sg:tags":[
        "machine",
        "automation"
    ],
    "sg:website":"www.cblutensileria.com",
    "wof:name":"Cbl Di Bendotti Ivonne Carletto Snc",
    "wof:placetype":"venue"
},
  "geometry": {"coordinates":[9.669952,45.694904],"type":"Point"}
}