{
  "type": "Feature",
  "properties": {
    "iso:country":"IT",
    "sg:address":"47100 Forli'",
    "sg:orig_category":"Laser - Apparecchi E Strumenti",
    "sg:phone":"+39 0543 774383",
    "sg:postcode":"47100",
    "sg:province":"Forl\u00ec-Cesena",
    "wof:name":"B-tec Snc Di Biserna Alessandro E Andrea",
    "wof:placetype":"venue"
},
  "geometry": {"coordinates":[12.051767,44.22871],"type":"Point"}
}