{
  "type": "Feature",
  "properties": {
    "iso:country":"IT",
    "sg:address":"36030 Monte Di Malo",
    "sg:city":"Monte di Malo",
    "sg:orig_category":"Acciai Inossidabili - Lavorazione",
    "sg:phone":"+39 0445 602804",
    "sg:postcode":"36030",
    "sg:province":"Vicenza",
    "wof:name":"Fratelli Casara Snc",
    "wof:placetype":"venue"
},
  "geometry": {"coordinates":[11.424424,45.647194],"type":"Point"}
}