{
  "type": "Feature",
  "properties": {
    "iso:country":"IT",
    "sg:address":"33033 Codroipo",
    "sg:city":"Codroipo",
    "sg:orig_category":"Servizi E Lavori Per Edilizia E Lavori Pubblici. Consulenze Tecniche, Amministrative E Perizie",
    "sg:phone":"+39 0432 905677",
    "sg:postcode":"33033",
    "sg:province":"Udine",
    "wof:name":"Fengineering Snc Di Frappa Ettore & C.",
    "wof:placetype":"venue"
},
  "geometry": {"coordinates":[13.240985,46.057701],"type":"Point"}
}