{
  "type": "Feature",
  "properties": {
    "addr:full":"20090 Segrate Segrate Milano 20090",
    "addr:postcode":"20090;20090",
    "iso:country":"IT",
    "sg:address":"20090 Segrate",
    "sg:city":"Segrate",
    "sg:classifiers":[
        {
            "category":"Banks & Credit Unions",
            "subcategory":"Investment Brokerage",
            "type":"Services"
        }
    ],
    "sg:phone":"+39 02 269191",
    "sg:postcode":"20090",
    "sg:province":"Milano",
    "sg:tags":[
        "packaging",
        "equipment",
        "packing",
        "pumps",
        "system"
    ],
    "sg:website":"http://www.obl.it",
    "wof:name":"Obl Srl",
    "wof:placetype":"venue"
},
  "geometry": {"coordinates":[9.299413681,45.4995384216],"type":"Point"}
}