{
  "type": "Feature",
  "properties": {
    "iso:country":"IT",
    "sg:address":"00183 Roma",
    "sg:city":"Roma",
    "sg:orig_category":"Ristorazione E Locali Pubblici Affini. Ristoranti Ed Esercizi Affini. Servizi Ausiliari Di Ristorazione E Di Intrattenimento",
    "sg:phone":"+39 06 701 6427",
    "sg:postcode":"00183",
    "sg:province":"Roma",
    "sg:website":"http://www.pepero.com",
    "wof:name":"Pepero",
    "wof:placetype":"venue"
},
  "geometry": {"coordinates":[12.515934,41.878654],"type":"Point"}
}