{
  "type": "Feature",
  "properties": {
    "iso:country":"IT",
    "sg:address":"37053 Cerea",
    "sg:city":"Cerea",
    "sg:orig_category":"Non-classified Establishments",
    "sg:phone":"+39 0442 80505",
    "sg:postcode":"37053",
    "sg:province":"Verona",
    "wof:name":"G.t.r. Arredamenti Srl",
    "wof:placetype":"venue"
},
  "geometry": {"coordinates":[11.209105,45.192638],"type":"Point"}
}