{
  "type": "Feature",
  "properties": {
    "iso:country":"IT",
    "sg:address":"22070 Bulgarograsso",
    "sg:city":"Bulgarograsso",
    "sg:orig_category":"Prodotti Chimici Industriali - Produzione",
    "sg:phone":"+39 031 932551",
    "sg:postcode":"22070",
    "sg:province":"Como",
    "wof:name":"Datt Chimica Srl",
    "wof:placetype":"venue"
},
  "geometry": {"coordinates":[9.1211462021,45.803062439],"type":"Point"}
}