{
  "type": "Feature",
  "properties": {
    "addr:full":"33057 Palmanova Palmanova Udine 33057",
    "addr:postcode":"33057;33057",
    "iso:country":"IT",
    "sg:address":"33057 Palmanova",
    "sg:city":"Palmanova",
    "sg:orig_category":"Amianto - Bonifica E Smantellamento",
    "sg:phone":"+39 0432 920562",
    "sg:postcode":"33057",
    "sg:province":"Udine",
    "wof:name":"Impresa Moschioni",
    "wof:placetype":"venue"
},
  "geometry": {"coordinates":[13.237219,46.063656],"type":"Point"}
}