{
  "type": "Feature",
  "properties": {
    "iso:country":"IT",
    "sg:address":"Via Dei Procacci 107/c 52046 Lucignano",
    "sg:city":"Lucignano",
    "sg:classifiers":[
        {
            "category":"Manufacturing",
            "subcategory":"Glass & Minerals",
            "type":"Manufacturing & Wholesale Goods"
        }
    ],
    "sg:phone":"+39 0575 836901",
    "sg:postcode":"52046",
    "sg:province":"Arezzo",
    "sg:tags":[
        "finishing"
    ],
    "wof:name":"Vitrum Vetreria Di Gazzei Luciano",
    "wof:placetype":"venue"
},
  "geometry": {"coordinates":[11.8630619049,43.4712028503],"type":"Point"}
}