{
  "type": "Feature",
  "properties": {
    "addr:full":"13, Via Rivarolo 10080 Ozegna Ozegna Torino 10080",
    "addr:postcode":"10080;10080",
    "addr:street":"Via Rivarolo",
    "iso:country":"IT",
    "sg:address":"13, Via Rivarolo 10080 Ozegna",
    "sg:city":"Ozegna",
    "sg:classifiers":[
        {
            "category":"Manufacturing",
            "subcategory":"Lumber",
            "type":"Manufacturing & Wholesale Goods"
        }
    ],
    "sg:phone":"+39 39012429442",
    "sg:postcode":"10080",
    "sg:province":"Torino",
    "sg:tags":[
        "wood"
    ],
    "wof:name":"P.i.l.e.c. Di Cresto Franco E C. (s.n.c.)",
    "wof:placetype":"venue"
},
  "geometry": {"coordinates":[7.741949,45.346016],"type":"Point"}
}