{
  "type": "Feature",
  "properties": {
    "iso:country":"IT",
    "sg:address":"10078 Venaria",
    "sg:orig_category":"Utensili Meccanici E Materiali",
    "sg:phone":"+39 011 450 9393",
    "sg:postcode":"10078",
    "sg:province":"Torino",
    "wof:name":"B.s.a. Srl",
    "wof:placetype":"venue"
},
  "geometry": {"coordinates":[7.628784,45.113621],"type":"Point"}
}