{
  "type": "Feature",
  "properties": {
    "iso:country":"IT",
    "sg:address":"73030 Tiggiano",
    "sg:city":"Tiggiano",
    "sg:orig_category":"Prodotti E Manufatti In Materie Plastiche. Forniture Per Edilizia E Lavori Pubblici. Forniture E Materiali Per Imballaggio E Confezionamento",
    "sg:phone":"+39 0833 531342",
    "sg:postcode":"73030",
    "sg:province":"Lecce",
    "wof:name":"Polistirolo Sud",
    "wof:placetype":"venue"
},
  "geometry": {"coordinates":[18.3653335571,39.9068870544],"type":"Point"}
}