{
  "type": "Feature",
  "properties": {
    "iso:country":"IT",
    "sg:address":"Via Vittorio Emanuele 86 42020 Albinea",
    "sg:classifiers":[
        {
            "category":"Shopping",
            "subcategory":"Clothing, Apparel, & Fashions",
            "type":"Retail Goods"
        }
    ],
    "sg:phone":"+39 0522 347441",
    "sg:postcode":"42020",
    "sg:province":"Reggio Nell'Emilia",
    "sg:tags":[
        "knitted",
        "knitwear",
        "clothes"
    ],
    "wof:name":"Maglierie Cristina Di Motti Adele",
    "wof:placetype":"venue"
},
  "geometry": {"coordinates":[10.607203,44.638214],"type":"Point"}
}