{
  "type": "Feature",
  "properties": {
    "iso:country":"IT",
    "sg:address":"34148 Trieste",
    "sg:city":"Trieste",
    "sg:classifiers":[
        {
            "category":"Professional",
            "subcategory":"Engineering",
            "type":"Services"
        }
    ],
    "sg:phone":"+39 040 828454",
    "sg:postcode":"34148",
    "sg:province":"Trieste",
    "sg:tags":[
        "activities",
        "industrial",
        "equipment",
        "household",
        "commercial",
        "non-professional",
        "instrument",
        "artisan",
        "appliances",
        "electronic",
        "machines",
        "furnishing"
    ],
    "sg:website":"http://www.silves.it",
    "wof:name":"Silves Di Astrid Lovrinovich",
    "wof:placetype":"venue"
},
  "geometry": {"coordinates":[13.809742,45.620296],"type":"Point"}
}