{
  "type": "Feature",
  "properties": {
    "iso:country":"IT",
    "sg:address":"Km. 19,600, V. Salaria 00138 Roma",
    "sg:city":"Roma",
    "sg:classifiers":[
        {
            "category":"Shopping",
            "subcategory":"Crafts & Fabrics",
            "type":"Retail Goods"
        }
    ],
    "sg:phone":"+39 06 8858 8032",
    "sg:postcode":"00138",
    "sg:province":"Roma",
    "sg:tags":[
        "linen"
    ],
    "wof:name":"Nuova Siret Snc",
    "wof:placetype":"venue"
},
  "geometry": {"coordinates":[12.4978933334,41.9117355347],"type":"Point"}
}