{
  "type": "Feature",
  "properties": {
    "iso:country":"IT",
    "sg:address":"20056 Grezzago",
    "sg:city":"Grezzago",
    "sg:orig_category":"Metalli E Leghe",
    "sg:phone":"+39 02 9096 7267",
    "sg:postcode":"20056",
    "sg:province":"Milano",
    "wof:name":"Metalint Srl",
    "wof:placetype":"venue"
},
  "geometry": {"coordinates":[9.5025234222,45.5864448547],"type":"Point"}
}