{
  "type": "Feature",
  "properties": {
    "addr:full":"50018 Scandicci Scandicci Firenze 50018",
    "addr:postcode":"50018;50018",
    "iso:country":"IT",
    "sg:address":"50018 Scandicci",
    "sg:city":"Scandicci",
    "sg:orig_category":"Macchine, Impianti E Forniture Per Industria Grafica, Cartaria E Cartotecnica",
    "sg:phone":"+39 055 731 1265",
    "sg:postcode":"50018",
    "sg:province":"Firenze",
    "wof:name":"Foldyn - S.r.l",
    "wof:placetype":"venue"
},
  "geometry": {"coordinates":[11.150411,43.730701],"type":"Point"}
}