{
  "type": "Feature",
  "properties": {
    "iso:country":"IT",
    "sg:address":"35139 Padova",
    "sg:city":"Padova",
    "sg:orig_category":"Assicurazioni E Servizi Assicurativi. Consulenze Tecniche, Amministrative E Perizie",
    "sg:phone":"+39 049 875 5890",
    "sg:postcode":"35139",
    "sg:province":"Padova",
    "wof:name":"Assilodi",
    "wof:placetype":"venue"
},
  "geometry": {"coordinates":[11.86744,45.407776],"type":"Point"}
}