{
  "type": "Feature",
  "properties": {
    "addr:full":"Km. 36.400, Via Nazionale Puglie 80013 Casalnuovo Di Napoli Casalnuovo di Napoli Napoli 80013",
    "addr:postcode":"80013;80013",
    "addr:street":"Km. 36.400 Via Nazionale",
    "iso:country":"IT",
    "sg:address":"Km. 36.400, Via Nazionale Puglie 80013 Casalnuovo Di Napoli",
    "sg:city":"Casalnuovo di Napoli",
    "sg:classifiers":[
        {
            "category":"Shopping",
            "subcategory":"Clothing, Apparel, & Fashions",
            "type":"Retail Goods"
        }
    ],
    "sg:phone":"+39 081 842 1259",
    "sg:postcode":"80013",
    "sg:province":"Napoli",
    "sg:tags":[
        "clothing",
        "accessory"
    ],
    "wof:name":"Nuova Erreplasta Srl",
    "wof:placetype":"venue"
},
  "geometry": {"coordinates":[14.251636,40.840096],"type":"Point"}
}