{
  "type": "Feature",
  "properties": {
    "addr:full":"Via Guglielmo Marconi 4 37036 San Martino Buon Albergo San Martino Buon Albergo Verona 37036",
    "addr:housenumber":"4",
    "addr:postcode":"37036;buon albergo;37036",
    "addr:street":"Via Guglielmo Marconi",
    "iso:country":"IT",
    "sg:address":"Via Guglielmo Marconi 4 37036 San Martino Buon Albergo",
    "sg:city":"San Martino Buon Albergo",
    "sg:classifiers":[
        {
            "category":"Wholesale",
            "subcategory":"Home Furnishings",
            "type":"Manufacturing & Wholesale Goods"
        }
    ],
    "sg:phone":"+39 045 995361",
    "sg:postcode":"37036",
    "sg:province":"Verona",
    "sg:tags":[
        "packaging",
        "bag",
        "mean"
    ],
    "wof:name":"Scm Di Marconi Nino",
    "wof:placetype":"venue"
},
  "geometry": {"coordinates":[11.091607,45.420521],"type":"Point"}
}