{
  "type": "Feature",
  "properties": {
    "iso:country":"IT",
    "sg:address":"00134 Roma",
    "sg:city":"Roma",
    "sg:orig_category":"Servizi Ausiliari Dei Mezzi Di Trasporto",
    "sg:phone":"+39 06 7135 3359",
    "sg:postcode":"00134",
    "sg:province":"Roma",
    "wof:name":"Di Rocco Massimiliano",
    "wof:placetype":"venue"
},
  "geometry": {"coordinates":[12.479003,41.862656],"type":"Point"}
}