{
  "type": "Feature",
  "properties": {
    "iso:country":"IT",
    "sg:address":"25065 Lumezzane",
    "sg:city":"Lumezzane",
    "sg:classifiers":[
        {
            "category":"Banks & Credit Unions",
            "subcategory":"Investment Brokerage",
            "type":"Services"
        }
    ],
    "sg:phone":"+39 030 897 1408",
    "sg:postcode":"25065",
    "sg:province":"Brescia",
    "sg:tags":[
        "control",
        "industrial",
        "door",
        "supply",
        "window",
        "safety",
        "frames",
        "prevention"
    ],
    "wof:name":"Mori Snc Di Mori Giacomo & C.",
    "wof:placetype":"venue"
},
  "geometry": {"coordinates":[10.271223,45.641441],"type":"Point"}
}