{
  "type": "Feature",
  "properties": {
    "iso:country":"IT",
    "sg:address":"43036 Fidenza",
    "sg:city":"Fidenza",
    "sg:orig_category":"Lavorazioni Meccaniche E Servizi",
    "sg:phone":"+39 0524 81048",
    "sg:postcode":"43036",
    "sg:province":"Parma",
    "wof:name":"Condomett (s.r.l.)",
    "wof:placetype":"venue"
},
  "geometry": {"coordinates":[10.08419,44.85836],"type":"Point"}
}