{
  "type": "Feature",
  "properties": {
    "iso:country":"IT",
    "sg:address":"30020 Bibione",
    "sg:city":"Bibione",
    "sg:orig_category":"Servizi Per Lo Sport E Il Tempo Libero. Alberghi E Strutture Extra Alberghiere",
    "sg:phone":"+39 0431 43124",
    "sg:postcode":"30020",
    "sg:province":"Venezia",
    "sg:website":"http://www.bibionemare.com",
    "wof:name":"Bibione Mare Spa",
    "wof:placetype":"venue"
},
  "geometry": {"coordinates":[13.009471,45.632656],"type":"Point"}
}