{
  "type": "Feature",
  "properties": {
    "iso:country":"IT",
    "sg:address":"46, Corso Diciotto Agosto 1860 85100 Potenza",
    "sg:city":"Potenza",
    "sg:classifiers":[
        {
            "category":"Travel",
            "subcategory":"Travel Agent",
            "type":"Entertainment"
        }
    ],
    "sg:phone":"+39 0971 410220",
    "sg:postcode":"85100",
    "sg:province":"Potenza",
    "sg:tags":[
        "business"
    ],
    "wof:name":"Grande Albergo S.r.l.",
    "wof:placetype":"venue"
},
  "geometry": {"coordinates":[15.802221,40.637241],"type":"Point"}
}