{
  "type": "Feature",
  "properties": {
    "iso:country":"IT",
    "sg:address":"20068 San Bovio",
    "sg:city":"San bovio",
    "sg:orig_category":"Macchine Utensili E Impianti",
    "sg:phone":"+39 02 753 3657",
    "sg:postcode":"20068",
    "sg:province":"Milano",
    "wof:name":"Lomar Di Lomio Giuseppe",
    "wof:placetype":"venue"
},
  "geometry": {"coordinates":[9.313831,45.461433],"type":"Point"}
}