{
  "type": "Feature",
  "properties": {
    "addr:full":"Via A. Moro 26 31010 Moriago Della Battaglia Moriago della Battaglia Treviso 31010",
    "addr:housenumber":"26",
    "addr:postcode":"31010;31010",
    "addr:street":"Via A. Moro",
    "iso:country":"IT",
    "sg:address":"Via A. Moro 26 31010 Moriago Della Battaglia",
    "sg:city":"Moriago della Battaglia",
    "sg:classifiers":[
        {
            "category":"Manufacturing",
            "subcategory":"Furniture",
            "type":"Manufacturing & Wholesale Goods"
        }
    ],
    "sg:phone":"+39 0438 890411",
    "sg:postcode":"31010",
    "sg:province":"Treviso",
    "sg:tags":[
        "bedroom"
    ],
    "sg:website":"www.doimoarredamenti.it",
    "wof:name":"Doimo Arredamenti Spa",
    "wof:placetype":"venue"
},
  "geometry": {"coordinates":[12.242072,45.666286],"type":"Point"}
}