{
  "type": "Feature",
  "properties": {
    "addr:full":"34079 Staranzano Staranzano Gorizia 34079",
    "addr:postcode":"34079;34079",
    "iso:country":"IT",
    "sg:address":"34079 Staranzano",
    "sg:city":"Staranzano",
    "sg:orig_category":"Servizi Per Lo Sport E Il Tempo Libero. Servizi Al Turismo. Acqua, Luce, Gas E Societa' Di Esercizio Pubblico",
    "sg:phone":"+39 0481 716917",
    "sg:postcode":"34079",
    "sg:province":"Gorizia",
    "wof:name":"Riserva Naturale Regionale 'foce Dell'isonzo'",
    "wof:placetype":"venue"
},
  "geometry": {"coordinates":[13.499454,45.776962],"type":"Point"}
}