{
  "type": "Feature",
  "properties": {
    "iso:country":"IT",
    "sg:address":"46029 Suzzara",
    "sg:city":"Suzzara",
    "sg:orig_category":"Arredamento Negozi E Supermercati",
    "sg:phone":"+39 0376 521800",
    "sg:postcode":"46029",
    "sg:province":"Mantova",
    "sg:website":"http://www.everlasting.it",
    "wof:name":"Everlasting Srl",
    "wof:placetype":"venue"
},
  "geometry": {"coordinates":[10.750845,45.008492],"type":"Point"}
}