{
  "type": "Feature",
  "properties": {
    "iso:country":"IT",
    "sg:address":"24060 Sovere",
    "sg:city":"Sovere",
    "sg:orig_category":"Imprese Di Costruzioni Civili Ed Industriali",
    "sg:phone":"+39 035 979292",
    "sg:postcode":"24060",
    "sg:province":"Bergamo",
    "wof:name":"Immobiliare Verde Casa Srl",
    "wof:placetype":"venue"
},
  "geometry": {"coordinates":[10.028611,45.815952],"type":"Point"}
}