{
  "type": "Feature",
  "properties": {
    "iso:country":"IT",
    "sg:address":"27, Via Portico 24050 Orio Al Serio",
    "sg:city":"Orio al Serio",
    "sg:classifiers":[
        {
            "category":"Professional",
            "subcategory":"Printing & Photocopies",
            "type":"Services"
        }
    ],
    "sg:phone":"+39 39035533160",
    "sg:postcode":"24050",
    "sg:province":"Bergamo",
    "wof:name":"Erre Stampa (s.r.l.)",
    "wof:placetype":"venue"
},
  "geometry": {"coordinates":[9.6856403351,45.6646957397],"type":"Point"}
}