{
  "type": "Feature",
  "properties": {
    "addr:full":"Via Delle Prese Z.i.2 36014 Santorso Santorso Vicenza 36014",
    "addr:housenumber":"z.i.2",
    "addr:postcode":"36014;36014",
    "addr:street":"Via Delle Prese",
    "iso:country":"IT",
    "sg:address":"Via Delle Prese Z.i.2 36014 Santorso",
    "sg:city":"Santorso",
    "sg:classifiers":[
        {
            "category":"Manufacturing",
            "subcategory":"Food",
            "type":"Manufacturing & Wholesale Goods"
        }
    ],
    "sg:phone":"+39 0445 641574",
    "sg:postcode":"36014",
    "sg:province":"Vicenza",
    "sg:tags":[
        "equipment",
        "processing",
        "-",
        "machinery"
    ],
    "wof:name":"Temac Di Dalla Guarda Luciano & C. (s.n.c.)",
    "wof:placetype":"venue"
},
  "geometry": {"coordinates":[11.540307045,45.5459060669],"type":"Point"}
}