{
  "type": "Feature",
  "properties": {
    "iso:country":"IT",
    "sg:address":"98148 Santo Stefano Di Camastra",
    "sg:city":"Santo",
    "sg:classifiers":[
        {
            "category":"Health Services",
            "subcategory":"Health Practitioner",
            "type":"Services"
        }
    ],
    "sg:phone":"+39 0921 339598",
    "sg:postcode":"98148",
    "sg:province":"Messina",
    "sg:tags":[
        "medici"
    ],
    "wof:name":"Centro Siciliano Di Nefrologia E Dialisi S.r.l.",
    "wof:placetype":"venue"
},
  "geometry": {"coordinates":[15.555523,38.192333],"type":"Point"}
}