{
  "type": "Feature",
  "properties": {
    "iso:country":"IT",
    "sg:address":"20138 Milano",
    "sg:city":"Milano",
    "sg:orig_category":"Materie Plastiche - Produzione E Lavorazione",
    "sg:phone":"+39 02 506 2191",
    "sg:postcode":"20138",
    "sg:province":"Milano",
    "wof:name":"Nuovacrill Snc",
    "wof:placetype":"venue"
},
  "geometry": {"coordinates":[9.251227,45.453423],"type":"Point"}
}