{
  "type": "Feature",
  "properties": {
    "iso:country":"IT",
    "sg:address":"80044 Ottaviano",
    "sg:city":"Ottaviano",
    "sg:orig_category":"Agenzie D'affari E Servizi Commerciali",
    "sg:phone":"+39 081 827 9422",
    "sg:postcode":"80044",
    "sg:province":"Napoli",
    "wof:name":"Linea C Di Carbone Vincenzo & C. Sas",
    "wof:placetype":"venue"
},
  "geometry": {"coordinates":[14.478153,40.838894],"type":"Point"}
}