{
  "type": "Feature",
  "properties": {
    "iso:country":"IT",
    "sg:address":"Via Appia Antica 81020 San Nicola La Strada",
    "sg:city":"San Nicola la Strada",
    "sg:classifiers":[
        {
            "category":"Manufacturing",
            "subcategory":"Lumber",
            "type":"Manufacturing & Wholesale Goods"
        }
    ],
    "sg:phone":"+39 0823 421166",
    "sg:postcode":"81020",
    "sg:province":"Caserta",
    "sg:tags":[
        "wood"
    ],
    "wof:name":"Tekno S.r.l.",
    "wof:placetype":"venue"
},
  "geometry": {"coordinates":[14.29914,41.069111],"type":"Point"}
}