{
  "type": "Feature",
  "properties": {
    "iso:country":"IT",
    "sg:address":"130, Via Bonaparte Paolina 55049 Viareggio",
    "sg:city":"Viareggio",
    "sg:classifiers":[
        {
            "category":"Professional",
            "subcategory":"Printing & Photocopies",
            "type":"Services"
        }
    ],
    "sg:phone":"+39 39058449917",
    "sg:postcode":"55049",
    "sg:province":"Lucca",
    "wof:name":"L'eliografica",
    "wof:placetype":"venue"
},
  "geometry": {"coordinates":[10.5079936981,43.8430137634],"type":"Point"}
}