{
  "type": "Feature",
  "properties": {
    "iso:country":"IT",
    "sg:address":"64046 Montorio Al Vomano",
    "sg:city":"Montorio al Vomano",
    "sg:orig_category":"Carpenterie Metalliche",
    "sg:phone":"+39 0861 592740",
    "sg:postcode":"64046",
    "sg:province":"Teramo",
    "wof:name":"Sicurmax Di Polisini Pierino",
    "wof:placetype":"venue"
},
  "geometry": {"coordinates":[13.657068,42.580734],"type":"Point"}
}