{
  "type": "Feature",
  "properties": {
    "iso:country":"IT",
    "sg:address":"02100 Rieti",
    "sg:city":"Rieti",
    "sg:orig_category":"Antifurto",
    "sg:phone":"+39 0746 203175",
    "sg:postcode":"02100",
    "sg:province":"Rieti",
    "wof:name":"Istituto Di Vigilanza Diurna E Nottura - Rieti",
    "wof:placetype":"venue"
},
  "geometry": {"coordinates":[12.85402,42.406013],"type":"Point"}
}