{
  "type": "Feature",
  "properties": {
    "iso:country":"IT",
    "sg:address":"Via Martiri Della Liberta' 15 31025 Santa Lucia Di Piave",
    "sg:city":"Santa Lucia di Piave",
    "sg:orig_category":"Filter Cloths",
    "sg:phone":"+39 0438 460103",
    "sg:postcode":"31025",
    "sg:province":"Treviso",
    "wof:name":"Tessitura Domenico E Riccardo Camerotto Snc",
    "wof:placetype":"venue"
},
  "geometry": {"coordinates":[12.2863321304,45.8498382568],"type":"Point"}
}