{
  "type": "Feature",
  "properties": {
    "iso:country":"IT",
    "sg:address":"Cso Canale 4 12051 Alba",
    "sg:city":"Alba",
    "sg:orig_category":"Turbocompressors",
    "sg:phone":"+39 0173 365111",
    "sg:postcode":"12051",
    "sg:province":"Cuneo",
    "sg:website":"www.fts.it",
    "wof:name":"F.t.s. Spa Ferrero Turbo Service",
    "wof:placetype":"venue"
},
  "geometry": {"coordinates":[7.996425,44.764156],"type":"Point"}
}