{
  "type": "Feature",
  "properties": {
    "addr:full":"Via Torquato Tasso 3 25016 Ghedi Ghedi Brescia 25016",
    "addr:housenumber":"3",
    "addr:postcode":"25016;25016",
    "addr:street":"Via Torquato Tasso",
    "iso:country":"IT",
    "sg:address":"Via Torquato Tasso 3 25016 Ghedi",
    "sg:city":"Ghedi",
    "sg:classifiers":[
        {
            "category":"Shopping",
            "subcategory":"Crafts & Fabrics",
            "type":"Retail Goods"
        }
    ],
    "sg:phone":"+39 030 901351",
    "sg:postcode":"25016",
    "sg:province":"Brescia",
    "sg:tags":[
        "cloth",
        "wall-mounted",
        "drier"
    ],
    "wof:name":"Eureka Meccanica Spa",
    "wof:placetype":"venue"
},
  "geometry": {"coordinates":[10.319157,45.40239],"type":"Point"}
}