{
  "type": "Feature",
  "properties": {
    "iso:country":"IT",
    "sg:address":"09098 Terralba",
    "sg:city":"Terralba",
    "sg:orig_category":"Cine-foto-ottica. Articoli Medico-sanitari Ed Ortopedici",
    "sg:phone":"+39 0783 83456",
    "sg:postcode":"09098",
    "sg:province":"Oristano",
    "wof:name":"Deriu Massimo Ottica",
    "wof:placetype":"venue"
},
  "geometry": {"coordinates":[8.636924,39.720638],"type":"Point"}
}