{
  "type": "Feature",
  "properties": {
    "addr:full":"7, Via Maria Teresa 20123 Milano Milano Milano 20123",
    "addr:postcode":"20123;20123",
    "addr:street":"Via Maria Teresa",
    "iso:country":"IT",
    "sg:address":"7, Via Maria Teresa 20123 Milano",
    "sg:city":"Milano",
    "sg:classifiers":[
        {
            "category":"Manufacturing",
            "subcategory":"Tools & Machinery",
            "type":"Manufacturing & Wholesale Goods"
        }
    ],
    "sg:phone":"+39 02 7201 0274",
    "sg:postcode":"20123",
    "sg:province":"Milano",
    "sg:tags":[
        "environment",
        "equipment",
        "-"
    ],
    "wof:name":"Iss Garavaglia Wash Srl",
    "wof:placetype":"venue"
},
  "geometry": {"coordinates":[9.18137,45.463367],"type":"Point"}
}