{
  "type": "Feature",
  "properties": {
    "iso:country":"IT",
    "sg:address":"47100 Forli'",
    "sg:orig_category":"Lavorazioni Meccaniche E Servizi",
    "sg:phone":"+39 0543 795559",
    "sg:postcode":"47100",
    "sg:province":"Forl\u00ec-Cesena",
    "wof:name":"Edil Capacci Srl",
    "wof:placetype":"venue"
},
  "geometry": {"coordinates":[12.05166,44.035629],"type":"Point"}
}