{
  "type": "Feature",
  "properties": {
    "addr:full":"38066 Riva Del Garda Riva del Garda Trento 38066",
    "addr:postcode":"38066;38066",
    "iso:country":"IT",
    "sg:address":"38066 Riva Del Garda",
    "sg:city":"Riva del Garda",
    "sg:classifiers":[
        {
            "category":"Utilities",
            "subcategory":"Natural Gas",
            "type":"Services"
        }
    ],
    "sg:phone":"+39 0464 521130",
    "sg:postcode":"38066",
    "sg:province":"Trento",
    "sg:tags":[
        "aria",
        "e",
        "compressori"
    ],
    "sg:website":"http://www.paginegialle.it/casarisrl",
    "wof:name":"Casari Luciano E Ezio Srl",
    "wof:placetype":"venue"
},
  "geometry": {"coordinates":[10.854874,45.898983],"type":"Point"}
}