{
  "type": "Feature",
  "properties": {
    "iso:country":"IT",
    "sg:address":"70015 Noci",
    "sg:city":"Noci",
    "sg:orig_category":"Elettrodomestici - Riparazione E Vendita Al Dettaglio Di Accessori",
    "sg:phone":"+39 080 497 7098",
    "sg:postcode":"70015",
    "sg:province":"Bari",
    "wof:name":"Miccolis Giuseppe",
    "wof:placetype":"venue"
},
  "geometry": {"coordinates":[17.122139,40.797047],"type":"Point"}
}