{
  "type": "Feature",
  "properties": {
    "iso:country":"IT",
    "sg:address":"Via Badini 9 40050 Quarto Inferiore",
    "sg:orig_category":"Soles, Heels",
    "sg:phone":"+39 051 767104",
    "sg:postcode":"40050",
    "sg:province":"Bologna",
    "wof:name":"Tecnosuola Srl",
    "wof:placetype":"venue"
},
  "geometry": {"coordinates":[11.415637,44.532841],"type":"Point"}
}