{
  "type": "Feature",
  "properties": {
    "addr:full":"90036 Misilmeri Misilmeri Palermo 90036",
    "addr:postcode":"90036;90036",
    "iso:country":"IT",
    "sg:address":"90036 Misilmeri",
    "sg:city":"Misilmeri",
    "sg:orig_category":"Biancheria, Telerie E Coperte. Forniture Alle Strutture Ricettive",
    "sg:phone":"+39 091 872 3896",
    "sg:postcode":"90036",
    "sg:province":"Palermo",
    "wof:name":"Di Gregorio Onofria",
    "wof:placetype":"venue"
},
  "geometry": {"coordinates":[13.443022,38.028397],"type":"Point"}
}