{
  "type": "Feature",
  "properties": {
    "addr:full":"65122 Pescara Pescara Pescara 65122",
    "addr:postcode":"65122;65122",
    "iso:country":"IT",
    "sg:address":"65122 Pescara",
    "sg:city":"Pescara",
    "sg:orig_category":"Centri Di Estetica E Cosmesi E Servizi. Prodotti Cosmetici E Da Toeletta",
    "sg:phone":"+39 085 421 1154",
    "sg:postcode":"65122",
    "sg:province":"Pescara",
    "wof:name":"Patriarca Marisa",
    "wof:placetype":"venue"
},
  "geometry": {"coordinates":[14.209857,42.468136],"type":"Point"}
}