{
  "type": "Feature",
  "properties": {
    "addr:full":"8, Via Pascoli Giovanni 22063 Cantu' Como 22063",
    "addr:postcode":"22063;22063",
    "addr:street":"Via Pascoli Giovanni;Cantu ' Como",
    "iso:country":"IT",
    "sg:address":"8, Via Pascoli Giovanni 22063 Cantu'",
    "sg:classifiers":[
        {
            "category":"Manufacturing",
            "subcategory":"Metals",
            "type":"Manufacturing & Wholesale Goods"
        }
    ],
    "sg:phone":"+39 39031730702",
    "sg:postcode":"22063",
    "sg:province":"Como",
    "sg:tags":[
        "processing"
    ],
    "wof:name":"Marelli Marco E C. (s.n.c.)",
    "wof:placetype":"venue"
},
  "geometry": {"coordinates":[9.0854558945,45.8119659424],"type":"Point"}
}