{
  "type": "Feature",
  "properties": {
    "iso:country":"IT",
    "sg:address":"285, Via Orsoleto 47824 Poggio Berni",
    "sg:city":"Poggio Berni",
    "sg:classifiers":[
        {
            "category":"Manufacturing",
            "subcategory":"Metals",
            "type":"Manufacturing & Wholesale Goods"
        }
    ],
    "sg:phone":"+39 0541 688189",
    "sg:postcode":"47824",
    "sg:province":"Rimini",
    "sg:tags":[
        "processing"
    ],
    "wof:name":"Bargellini Bruno",
    "wof:placetype":"venue"
},
  "geometry": {"coordinates":[12.4172124863,44.030582428],"type":"Point"}
}