{
  "type": "Feature",
  "properties": {
    "addr:full":"20147 Milano Milano Milano 20147",
    "addr:postcode":"20147;20147",
    "iso:country":"IT",
    "sg:address":"20147 Milano",
    "sg:city":"Milano",
    "sg:orig_category":"Banche E Servizi Finanziari",
    "sg:phone":"+39 02 412 5457",
    "sg:postcode":"20147",
    "sg:province":"Milano",
    "wof:name":"Diners Club Societa' Di Intermediazione Mobiliare Spa",
    "wof:placetype":"venue"
},
  "geometry": {"coordinates":[9.134881,45.459522],"type":"Point"}
}