{
  "type": "Feature",
  "properties": {
    "addr:full":"22017 Menaggio Menaggio Como 22017",
    "addr:postcode":"22017;22017",
    "iso:country":"IT",
    "sg:address":"22017 Menaggio",
    "sg:city":"Menaggio",
    "sg:orig_category":"Prodotti Alimentari",
    "sg:phone":"+39 0344 32371",
    "sg:postcode":"22017",
    "sg:province":"Como",
    "wof:name":"Il Fornaio Dei Fratelli Erba Panificio Snc",
    "wof:placetype":"venue"
},
  "geometry": {"coordinates":[9.2390604019,46.0220336914],"type":"Point"}
}