{
  "type": "Feature",
  "properties": {
    "iso:country":"IT",
    "sg:address":"Strada Statale 142 Biellese 28013 Gattico",
    "sg:city":"Gattico",
    "sg:classifiers":[
        {
            "category":"Home & Garden",
            "subcategory":"Home Furnishings",
            "type":"Retail Goods"
        }
    ],
    "sg:phone":"+39 0322 843078",
    "sg:postcode":"28013",
    "sg:province":"Novara",
    "sg:tags":[
        "household"
    ],
    "wof:name":"C.a.l. Di Gennaro & C.",
    "wof:placetype":"venue"
},
  "geometry": {"coordinates":[8.618671,45.445084],"type":"Point"}
}