{
  "type": "Feature",
  "properties": {
    "iso:country":"IT",
    "sg:address":"Zona Industriale 07030 Muros",
    "sg:classifiers":[
        {
            "category":"Food & Beverages",
            "subcategory":"Dairy",
            "type":"Retail Goods"
        }
    ],
    "sg:phone":"+39 39079345614",
    "sg:postcode":"07030",
    "sg:province":"Olbia-Tempio",
    "sg:tags":[
        "product"
    ],
    "wof:name":"Caseificio 3 L S.r.l.",
    "wof:placetype":"venue"
},
  "geometry": {"coordinates":[9.278559,40.826839],"type":"Point"}
}