{
  "type": "Feature",
  "properties": {
    "addr:full":"Via Degli Alpini 84 36040 Torri Di Quartesolo Torri di Quartesolo Vicenza 36040",
    "addr:housenumber":"84",
    "addr:postcode":"36040;36040",
    "addr:street":"Via Degli Alpini",
    "iso:country":"IT",
    "sg:address":"Via Degli Alpini 84 36040 Torri Di Quartesolo",
    "sg:city":"Torri di Quartesolo",
    "sg:classifiers":[
        {
            "category":"Food & Beverages",
            "subcategory":"Cheese",
            "type":"Retail Goods"
        }
    ],
    "sg:phone":"+39 0444 580193",
    "sg:postcode":"36040",
    "sg:province":"Vicenza",
    "wof:name":"Menzio Dal Porto Srl",
    "wof:placetype":"venue"
},
  "geometry": {"coordinates":[11.6051044464,45.5260734558],"type":"Point"}
}