{
  "type": "Feature",
  "properties": {
    "addr:full":"98066 Patti Patti Messina 98066",
    "addr:postcode":"98066;98066",
    "iso:country":"IT",
    "sg:address":"98066 Patti",
    "sg:city":"Patti",
    "sg:orig_category":"Abbigliamento Esterno, Maglierie E Pelliccerie. Shopping",
    "sg:phone":"+39 328 183 8026",
    "sg:postcode":"98066",
    "sg:province":"Messina",
    "wof:name":"Mangone Giovanni",
    "wof:placetype":"venue"
},
  "geometry": {"coordinates":[15.553612,38.179848],"type":"Point"}
}