{
  "type": "Feature",
  "properties": {
    "iso:country":"IT",
    "sg:address":"25065 Lumezzane",
    "sg:city":"Lumezzane",
    "sg:orig_category":"Non-classified Establishments",
    "sg:phone":"+39 030 828029",
    "sg:postcode":"25065",
    "sg:province":"Brescia",
    "wof:name":"Becchetti Angelo Bal Di Pietro Becchetti & C. (s.n.c.)",
    "wof:placetype":"venue"
},
  "geometry": {"coordinates":[10.213804,45.607109],"type":"Point"}
}