{
  "type": "Feature",
  "properties": {
    "addr:full":"31, Via Montanino 80040 Volla Volla Napoli 80040",
    "addr:postcode":"80040;80040",
    "addr:street":"Via Montanino",
    "iso:country":"IT",
    "sg:address":"31, Via Montanino 80040 Volla",
    "sg:city":"Volla",
    "sg:classifiers":[
        {
            "category":"Manufacturing",
            "subcategory":"Rubber & Plastics",
            "type":"Manufacturing & Wholesale Goods"
        }
    ],
    "sg:phone":"+39 081 773 1165",
    "sg:postcode":"80040",
    "sg:province":"Napoli",
    "wof:name":"Lasla Plastic (s.n.c.)",
    "wof:placetype":"venue"
},
  "geometry": {"coordinates":[14.3484964371,40.8845024109],"type":"Point"}
}