{
  "type": "Feature",
  "properties": {
    "iso:country":"IT",
    "sg:address":"13100 Vercelli",
    "sg:city":"Vercelli",
    "sg:orig_category":"Audiovisivi Filmati, Spot E Multimediali - Realizzazione E Duplicazione",
    "sg:phone":"+39 0161 282111",
    "sg:postcode":"13100",
    "sg:province":"Vercelli",
    "wof:name":"Tecnomovie Di Michele Politi & C. Sas",
    "wof:placetype":"venue"
},
  "geometry": {"coordinates":[8.415515,45.324669],"type":"Point"}
}