{
  "type": "Feature",
  "properties": {
    "iso:country":"IT",
    "sg:address":"Via Giuliani Reginaldo 71/r/b 50141 Firenze",
    "sg:city":"Firenze",
    "sg:classifiers":[
        {
            "category":"Shopping",
            "subcategory":"Beauty & Cosmetics",
            "type":"Retail Goods"
        }
    ],
    "sg:phone":"+39 055 436 8315",
    "sg:postcode":"50141",
    "sg:province":"Firenze",
    "sg:tags":[
        "herbal"
    ],
    "sg:website":"www.smnovella.com",
    "wof:name":"Officina Profumo Farmaceutica Di Santa Maria Novella",
    "wof:placetype":"venue"
},
  "geometry": {"coordinates":[11.256902,43.768734],"type":"Point"}
}