{
  "type": "Feature",
  "properties": {
    "addr:full":"Villa Pisanelli Fraz Lucarelli 53017 Radda In Chianti Lucarelli Siena 53017",
    "addr:postcode":"53017;53017",
    "addr:street":"Fraz Lucarelli",
    "iso:country":"IT",
    "sg:address":"Villa Pisanelli Fraz Lucarelli 53017 Radda In Chianti",
    "sg:city":"Lucarelli",
    "sg:classifiers":[
        {
            "category":"Food & Beverages",
            "subcategory":"Liquor & Beverages",
            "type":"Retail Goods"
        }
    ],
    "sg:phone":"+39 0577 733533",
    "sg:postcode":"53017",
    "sg:province":"Siena",
    "sg:tags":[
        "wine",
        "italian"
    ],
    "sg:website":"www.monterinaldi.it",
    "wof:name":"Agricola Monte Rinaldi Srl",
    "wof:placetype":"venue"
},
  "geometry": {"coordinates":[11.330514,43.318661],"type":"Point"}
}