{
  "type": "Feature",
  "properties": {
    "iso:country":"IT",
    "sg:address":"66022 Fossacesia",
    "sg:city":"Fossacesia",
    "sg:orig_category":"Prodotti Alimentari",
    "sg:phone":"+39 0872 60155",
    "sg:postcode":"66022",
    "sg:province":"Chieti",
    "wof:name":"Ciccocioppo Domenico",
    "wof:placetype":"venue"
},
  "geometry": {"coordinates":[14.4898004532,42.2371788025],"type":"Point"}
}