{
  "type": "Feature",
  "properties": {
    "addr:full":"25020 Flero Flero Brescia 25020",
    "addr:postcode":"25020;25020",
    "iso:country":"IT",
    "sg:address":"25020 Flero",
    "sg:city":"Flero",
    "sg:orig_category":"Elettrodomestici. Forniture Alle Strutture Ricettive",
    "sg:phone":"+39 030 358 1040",
    "sg:postcode":"25020",
    "sg:province":"Brescia",
    "wof:name":"Lombardi Roberto",
    "wof:placetype":"venue"
},
  "geometry": {"coordinates":[10.178717,45.486603],"type":"Point"}
}