{
  "type": "Feature",
  "properties": {
    "addr:full":"10092 Beinasco Beinasco Torino 10092",
    "addr:postcode":"10092;10092",
    "iso:country":"IT",
    "sg:address":"10092 Beinasco",
    "sg:city":"Beinasco",
    "sg:orig_category":"Servizi E Lavori Per Abbigliamento E Pelletterie",
    "sg:phone":"+39 011 397 1053",
    "sg:postcode":"10092",
    "sg:province":"Torino",
    "wof:name":"Airone Blu",
    "wof:placetype":"venue"
},
  "geometry": {"coordinates":[7.58408,45.021675],"type":"Point"}
}