{
  "type": "Feature",
  "properties": {
    "addr:full":"25125 Brescia Brescia Brescia 25125",
    "addr:postcode":"25125;25125",
    "iso:country":"IT",
    "sg:address":"25125 Brescia",
    "sg:city":"Brescia",
    "sg:orig_category":"Dolciumi E Gelati",
    "sg:phone":"+39 030 354 0191",
    "sg:postcode":"25125",
    "sg:province":"Brescia",
    "wof:name":"Api Brescia (soc.coop.r.l.)",
    "wof:placetype":"venue"
},
  "geometry": {"coordinates":[10.193008,45.524353],"type":"Point"}
}