{
  "type": "Feature",
  "properties": {
    "addr:full":"41012 Carpi Carpi Modena 41012",
    "addr:postcode":"41012;41012",
    "iso:country":"IT",
    "sg:address":"41012 Carpi",
    "sg:city":"Carpi",
    "sg:orig_category":"Lavorazioni Metalli, Stampaggio E Saldatura",
    "sg:phone":"+39 059 694081",
    "sg:postcode":"41012",
    "sg:province":"Modena",
    "sg:website":"http://www.arsom.it",
    "wof:name":"Arsom Srl",
    "wof:placetype":"venue"
},
  "geometry": {"coordinates":[10.897784,44.891922],"type":"Point"}
}