{
  "type": "Feature",
  "properties": {
    "addr:full":"65125 Pescara Pescara Pescara 65125",
    "addr:postcode":"65125;65125",
    "iso:country":"IT",
    "sg:address":"65125 Pescara",
    "sg:city":"Pescara",
    "sg:orig_category":"Trasporti E Spedizioni Merci",
    "sg:phone":"+39 085 470701",
    "sg:postcode":"65125",
    "sg:province":"Pescara",
    "sg:website":"http://www.italpad.it",
    "wof:name":"Trasporti Ital-pad Srl",
    "wof:placetype":"venue"
},
  "geometry": {"coordinates":[14.180514,42.491184],"type":"Point"}
}