{
  "type": "Feature",
  "properties": {
    "iso:country":"IT",
    "sg:address":"70125 Bari",
    "sg:city":"Bari",
    "sg:orig_category":"Elaboratori Elettronici",
    "sg:phone":"+39 080 502 5268",
    "sg:postcode":"70125",
    "sg:province":"Bari",
    "wof:name":"Sdp Informatica",
    "wof:placetype":"venue"
},
  "geometry": {"coordinates":[16.876474,41.102619],"type":"Point"}
}