{
  "type": "Feature",
  "properties": {
    "addr:full":"19, Via Pisacane Carlo 10042 Nichelino Nichelino Torino 10042",
    "addr:postcode":"10042;10042",
    "addr:street":"Via Pisacane Carlo",
    "iso:country":"IT",
    "sg:address":"19, Via Pisacane Carlo 10042 Nichelino",
    "sg:city":"Nichelino",
    "sg:classifiers":[
        {
            "category":"Professional",
            "subcategory":"Engineering",
            "type":"Services"
        }
    ],
    "sg:phone":"+39 011 680 9323",
    "sg:postcode":"10042",
    "sg:province":"Torino",
    "sg:tags":[
        "machine",
        "-",
        "mechanical"
    ],
    "wof:name":"Col Giovanni Paolo (s.p.a.)",
    "wof:placetype":"venue"
},
  "geometry": {"coordinates":[7.632926,44.975689],"type":"Point"}
}