{
  "type": "Feature",
  "properties": {
    "addr:full":"41042 Fiorano Modenese Fiorano Modenese Modena 41042",
    "addr:postcode":"41042;41042",
    "iso:country":"IT",
    "sg:address":"41042 Fiorano Modenese",
    "sg:city":"Fiorano Modenese",
    "sg:classifiers":[
        {
            "category":"Retail",
            "subcategory":"Storage",
            "type":"Services"
        }
    ],
    "sg:phone":"+39 0536 920422",
    "sg:postcode":"41042",
    "sg:province":"Modena",
    "sg:tags":[
        "equipment",
        "handling",
        "system"
    ],
    "sg:website":"http://www.cammindustriale.com",
    "wof:name":"Camm Industriale Srl",
    "wof:placetype":"venue"
},
  "geometry": {"coordinates":[10.843236,44.539818],"type":"Point"}
}