{
  "type": "Feature",
  "properties": {
    "iso:country":"IT",
    "sg:address":"3, V. Roma 44035 Formignana",
    "sg:city":"Formignana",
    "sg:classifiers":[
        {
            "category":"Parking",
            "subcategory":"Lot",
            "type":"Transportation"
        }
    ],
    "sg:phone":"+39 39053359232",
    "sg:postcode":"44035",
    "sg:province":"Ferrara",
    "sg:tags":[
        "transport",
        "road"
    ],
    "sg:website":"http://www.paginegialle.it/sanpaolo-06",
    "wof:name":"Onoranze Funebri San Paolo Srl",
    "wof:placetype":"venue"
},
  "geometry": {"coordinates":[11.860353,44.842213],"type":"Point"}
}