{
  "type": "Feature",
  "properties": {
    "addr:full":"13, Via Martini Giovanni Battista 00198 Roma Roma Roma 00198",
    "addr:postcode":"00198;00198",
    "addr:street":"Via Martini Giovanni Battista",
    "iso:country":"IT",
    "sg:address":"13, Via Martini Giovanni Battista 00198 Roma",
    "sg:city":"Roma",
    "sg:classifiers":[
        {
            "category":"Real Estate",
            "subcategory":"Architect",
            "type":"Services"
        }
    ],
    "sg:phone":"+39 06 8530 1580",
    "sg:postcode":"00198",
    "sg:province":"Roma",
    "sg:tags":[
        "textile",
        "clothing"
    ],
    "wof:name":"Xines (s.r.l.)",
    "wof:placetype":"venue"
},
  "geometry": {"coordinates":[12.482325,41.895466],"type":"Point"}
}