{
  "type": "Feature",
  "properties": {
    "addr:full":"55, Via S. Giustina 39057 Appiano Sulla Strada Del Vino Appiano sulla strada del vino Bolzano/Bozen 39057",
    "addr:postcode":"39057;39057",
    "addr:street":"Via S. Giustina;Strada;Sulla Strada Del Vino",
    "iso:country":"IT",
    "sg:address":"55, Via S. Giustina 39057 Appiano Sulla Strada Del Vino",
    "sg:city":"Appiano sulla strada del vino",
    "sg:classifiers":[
        {
            "category":"Shopping",
            "subcategory":"Stationery & Office Supplies",
            "type":"Retail Goods"
        }
    ],
    "sg:phone":"+39 0471 662548",
    "sg:postcode":"39057",
    "sg:province":"Bolzano/Bozen",
    "sg:tags":[
        "professional"
    ],
    "wof:name":"Walcher Friedrich",
    "wof:placetype":"venue"
},
  "geometry": {"coordinates":[11.2539014816,46.470741272],"type":"Point"}
}