{
  "type": "Feature",
  "properties": {
    "addr:full":"Viale Dell'industria 75 37047 San Bonifacio San Bonifacio Verona 37047",
    "addr:housenumber":"75",
    "addr:postcode":"37047;37047",
    "addr:street":"Viale Dell'Industria",
    "iso:country":"IT",
    "sg:address":"Viale Dell'industria 75 37047 San Bonifacio",
    "sg:city":"San Bonifacio",
    "sg:orig_category":"Earthmovers, Bulldozers, Dozers, Wheel Loaders",
    "sg:phone":"+39 045 761 1333",
    "sg:postcode":"37047",
    "sg:province":"Verona",
    "sg:website":"www.perlini.com",
    "wof:name":"Perlini International Spa",
    "wof:placetype":"venue"
},
  "geometry": {"coordinates":[11.303888,45.393406],"type":"Point"}
}