{
  "type": "Feature",
  "properties": {
    "iso:country":"IT",
    "sg:address":"Via Rossin 6 21050 Saltrio",
    "sg:city":"Saltrio",
    "sg:classifiers":[
        {
            "category":"Manufacturing",
            "subcategory":"Building Materials",
            "type":"Manufacturing & Wholesale Goods"
        }
    ],
    "sg:phone":"+39 0332 487427",
    "sg:postcode":"21050",
    "sg:province":"Varese",
    "sg:tags":[
        "sealing",
        "plastic"
    ],
    "sg:website":"www.alfaplastmp.it",
    "wof:name":"Alfa Plast Srl",
    "wof:placetype":"venue"
},
  "geometry": {"coordinates":[8.8774795532,45.8509559631],"type":"Point"}
}