{
  "type": "Feature",
  "properties": {
    "iso:country":"IT",
    "sg:address":"Via S. Egidio 9 60020 Polverigi",
    "sg:city":"Polverigi",
    "sg:orig_category":"Lever Locks",
    "sg:phone":"+39 071 906 4011",
    "sg:postcode":"60020",
    "sg:province":"Ancona",
    "sg:website":"www.sercas.it",
    "wof:name":"Juvel Spa",
    "wof:placetype":"venue"
},
  "geometry": {"coordinates":[13.383789,43.532471],"type":"Point"}
}