{
  "type": "Feature",
  "properties": {
    "addr:full":"95033 Biancavilla Biancavilla Catania 95033",
    "addr:postcode":"95033;95033",
    "iso:country":"IT",
    "sg:address":"95033 Biancavilla",
    "sg:city":"Biancavilla",
    "sg:orig_category":"Vetro: Prodotti E Lavorazioni",
    "sg:phone":"+39 095 688683",
    "sg:postcode":"95033",
    "sg:province":"Catania",
    "wof:name":"O.m.e.c. Srl",
    "wof:placetype":"venue"
},
  "geometry": {"coordinates":[14.903845,37.669163],"type":"Point"}
}