{
  "type": "Feature",
  "properties": {
    "iso:country":"IT",
    "sg:address":"24055 Cologno Al Serio",
    "sg:city":"Cologno al Serio",
    "sg:orig_category":"Imprese Edili",
    "sg:phone":"+39 035 890440",
    "sg:postcode":"24055",
    "sg:province":"Bergamo",
    "wof:name":"Co.g.ed Snc Di Cavalleri Giacomo",
    "wof:placetype":"venue"
},
  "geometry": {"coordinates":[9.70972,45.590031],"type":"Point"}
}