{
  "type": "Feature",
  "properties": {
    "iso:country":"IT",
    "sg:address":"20121 Milano",
    "sg:city":"Milano",
    "sg:orig_category":"Studi E Consulenze Amministrative, Commerciali E Aziendali. Banche E Servizi Finanziari. Agenzie D'affari E Servizi Commerciali. Consulenze Tecniche, Amministrative E Perizie",
    "sg:phone":"+39 02 7600 2142",
    "sg:postcode":"20121",
    "sg:province":"Milano",
    "sg:website":"http://www.studiobrughera.it",
    "wof:name":"Studio Brughera",
    "wof:placetype":"venue"
},
  "geometry": {"coordinates":[9.194436,45.471676],"type":"Point"}
}