{
  "type": "Feature",
  "properties": {
    "addr:full":"20090 Cusago Cusago Milano 20090",
    "addr:postcode":"20090;20090",
    "iso:country":"IT",
    "sg:address":"20090 Cusago",
    "sg:city":"Cusago",
    "sg:orig_category":"Pompe. Macchine, Strumenti Ed Apparecchi Per Attivita' Industriali",
    "sg:phone":"+39 02 903581",
    "sg:postcode":"20090",
    "sg:province":"Milano",
    "sg:website":"http://www.flygt.it",
    "wof:name":"Itt Flygt Spa",
    "wof:placetype":"venue"
},
  "geometry": {"coordinates":[9.0436697006,45.4403152466],"type":"Point"}
}