{
  "type": "Feature",
  "properties": {
    "iso:country":"IT",
    "sg:address":"25127 Brescia",
    "sg:city":"Brescia",
    "sg:orig_category":"Articoli Da Regalo. Tempo Libero - Articoli E Forniture. Regalistica Aziendale",
    "sg:phone":"+39 030 373 9180",
    "sg:postcode":"25127",
    "sg:province":"Brescia",
    "wof:name":"Olimpia 90",
    "wof:placetype":"venue"
},
  "geometry": {"coordinates":[10.18751,45.558346],"type":"Point"}
}