{
  "type": "Feature",
  "properties": {
    "iso:country":"IT",
    "sg:address":"12, Via Del Rame P. Felcino 06077 Perugia",
    "sg:classifiers":[
        {
            "category":"Food & Beverages",
            "subcategory":"Groceries & Convenience Stores",
            "type":"Retail Goods"
        }
    ],
    "sg:phone":"+39 075 691 0448",
    "sg:province":"PG",
    "sg:tags":[
        "product",
        "related"
    ],
    "wof:name":"Il Gastronomo (s.n.c.)",
    "wof:placetype":"venue"
},
  "geometry": {"coordinates":[12.384349823,43.1111907959],"type":"Point"}
}