{
  "type": "Feature",
  "properties": {
    "iso:country":"IT",
    "sg:address":"35020 Tribano",
    "sg:city":"Tribano",
    "sg:orig_category":"Macchine Utensili E Impianti",
    "sg:phone":"+39 049 958 8800",
    "sg:postcode":"35020",
    "sg:province":"Padova",
    "wof:name":"Eurositech Srl",
    "wof:placetype":"venue"
},
  "geometry": {"coordinates":[11.924974,45.354462],"type":"Point"}
}