{
  "type": "Feature",
  "properties": {
    "iso:country":"IT",
    "sg:address":"35020 Candiana",
    "sg:city":"Candiana",
    "sg:orig_category":"Abiti Da Lavoro Ed Indumenti Protettivi",
    "sg:phone":"+39 049 534 9635",
    "sg:postcode":"35020",
    "sg:province":"Padova",
    "wof:name":"Zanellato Stefano",
    "wof:placetype":"venue"
},
  "geometry": {"coordinates":[11.990167,45.222038],"type":"Point"}
}