{
  "type": "Feature",
  "properties": {
    "iso:country":"IT",
    "sg:address":"20144 Milano",
    "sg:city":"Milano",
    "sg:orig_category":"Brevetti D'invenzione - Consulenza Tecnica E Legale",
    "sg:phone":"+39 02 480681",
    "sg:postcode":"20144",
    "sg:province":"Milano",
    "sg:website":"http://www.racheli.it",
    "wof:name":"Racheli & C. Spa",
    "wof:placetype":"venue"
},
  "geometry": {"coordinates":[9.164631,45.465504],"type":"Point"}
}