{
  "type": "Feature",
  "properties": {
    "iso:country":"IT",
    "sg:address":"16138 Genova",
    "sg:city":"Genova",
    "sg:orig_category":"Trasporti E Spedizioni Merci",
    "sg:phone":"+39 010 836 4342",
    "sg:postcode":"16138",
    "sg:province":"Genova",
    "wof:name":"Taurino Pietro",
    "wof:placetype":"venue"
},
  "geometry": {"coordinates":[8.977686,44.460903],"type":"Point"}
}