{
  "type": "Feature",
  "properties": {
    "addr:full":"2, Via Balbo Cesare 13100 Vercelli Vercelli Vercelli 13100",
    "addr:postcode":"13100;13100",
    "addr:street":"Via Balbo Cesare",
    "iso:country":"IT",
    "sg:address":"2, Via Balbo Cesare 13100 Vercelli",
    "sg:city":"Vercelli",
    "sg:classifiers":[
        {
            "category":"Banks & Credit Unions",
            "subcategory":"Investment Brokerage",
            "type":"Services"
        }
    ],
    "sg:phone":"+39 0161 501629",
    "sg:postcode":"13100",
    "sg:province":"Vercelli",
    "sg:tags":[
        "-",
        "transport",
        "related"
    ],
    "wof:name":"Il Poliedro Soc. Coop. A R.l.",
    "wof:placetype":"venue"
},
  "geometry": {"coordinates":[8.420386,45.325073],"type":"Point"}
}