{
  "type": "Feature",
  "properties": {
    "addr:full":"20081 Abbiategrasso Abbiategrasso Milano 20081",
    "addr:postcode":"20081;20081",
    "iso:country":"IT",
    "sg:address":"20081 Abbiategrasso",
    "sg:city":"Abbiategrasso",
    "sg:orig_category":"Hobbistica",
    "sg:phone":"+39 02 946 5459",
    "sg:postcode":"20081",
    "sg:province":"Milano",
    "wof:name":"Rossetto Fiorenzo",
    "wof:placetype":"venue"
},
  "geometry": {"coordinates":[8.876838,45.327805],"type":"Point"}
}