{
  "type": "Feature",
  "properties": {
    "addr:full":"22/3, Via Degli Olmi 61100 Pesaro Pesaro Pesaro E Urbino 61100",
    "addr:housenumber":"22 / 3",
    "addr:postcode":"61100;61100",
    "addr:street":"Via Degli Olmi",
    "iso:country":"IT",
    "sg:address":"22/3, Via Degli Olmi 61100 Pesaro",
    "sg:city":"Pesaro",
    "sg:classifiers":[
        {
            "category":"Sports & Exercise",
            "subcategory":"Playing Field",
            "type":"Entertainment"
        }
    ],
    "sg:phone":"+39 39072124403",
    "sg:postcode":"61100",
    "sg:province":"Pesaro E Urbino",
    "sg:tags":[
        "game"
    ],
    "wof:name":"Bang (s.r.l.)",
    "wof:placetype":"venue"
},
  "geometry": {"coordinates":[12.857526,43.900612],"type":"Point"}
}