{
  "type": "Feature",
  "properties": {
    "iso:country":"IT",
    "sg:address":"20124 Milano",
    "sg:city":"Milano",
    "sg:orig_category":"Petroli, Gas E Combustibili",
    "sg:phone":"+39 02 669 9211",
    "sg:postcode":"20124",
    "sg:province":"Milano",
    "wof:name":"Maxcom Petroli S.r.l.",
    "wof:placetype":"venue"
},
  "geometry": {"coordinates":[9.2157316208,45.4859886169],"type":"Point"}
}