{
  "type": "Feature",
  "properties": {
    "iso:country":"IT",
    "sg:address":"20030 Lentate Sul Seveso",
    "sg:city":"Lentate sul Seveso",
    "sg:orig_category":"Tessuti Arredamento - Produzione E Ingrosso",
    "sg:phone":"+39 036 253101",
    "sg:postcode":"20030",
    "sg:province":"Milano",
    "sg:website":"http://www.edaspa.com/",
    "wof:name":"Enzo Degli Angiuoni Spa",
    "wof:placetype":"venue"
},
  "geometry": {"coordinates":[9.12183,45.678387],"type":"Point"}
}