{
  "type": "Feature",
  "properties": {
    "addr:full":"37039 Tregnago Tregnago Verona 37039",
    "addr:postcode":"37039;37039",
    "iso:country":"IT",
    "sg:address":"37039 Tregnago",
    "sg:city":"Tregnago",
    "sg:orig_category":"Cartotecnica E Servizi. Composizione, Stampa E Confezione. Servizi E Lavori Industria Delle Materie Plastiche. Servizi Per Imballaggio E Confezionamento",
    "sg:phone":"+39 045 650 0353",
    "sg:postcode":"37039",
    "sg:province":"Verona",
    "wof:name":"Cavestro Marco",
    "wof:placetype":"venue"
},
  "geometry": {"coordinates":[11.166781,45.504921],"type":"Point"}
}