{
  "type": "Feature",
  "properties": {
    "addr:full":"Via Castelgoffredo 35 46040 Casaloldo Casaloldo Mantova 46040",
    "addr:housenumber":"35",
    "addr:postcode":"46040;46040",
    "addr:street":"Via Castelgoffredo",
    "iso:country":"IT",
    "sg:address":"Via Castelgoffredo 35 46040 Casaloldo",
    "sg:city":"Casaloldo",
    "sg:orig_category":"Spot Luminaires",
    "sg:phone":"+39 0376 778670",
    "sg:postcode":"46040",
    "sg:province":"Mantova",
    "sg:website":"www.teclumen.it",
    "wof:name":"Teclumen Srl",
    "wof:placetype":"venue"
},
  "geometry": {"coordinates":[10.797698,45.160366],"type":"Point"}
}