{
  "type": "Feature",
  "properties": {
    "iso:country":"IT",
    "sg:address":"80013 Casalnuovo Di Napoli",
    "sg:city":"Casalnuovo di Napoli",
    "sg:orig_category":"Dolciumi E Gelati. Condimenti, Spezie, Infusi E Caffe'",
    "sg:phone":"+39 081 842 3204",
    "sg:postcode":"80013",
    "sg:province":"Napoli",
    "wof:name":"Erizuccheri (s.p.a.)",
    "wof:placetype":"venue"
},
  "geometry": {"coordinates":[14.351871,40.915127],"type":"Point"}
}