{
  "type": "Feature",
  "properties": {
    "iso:country":"IT",
    "sg:address":"Via M. Gioia, 88; Milano; 20125",
    "sg:city":"Milano",
    "sg:classifiers":[
        {
            "category":"Banks & Credit Unions",
            "subcategory":"Bank",
            "type":"Services"
        }
    ],
    "sg:phone":"+39 02 688 4531",
    "sg:postcode":"20125",
    "sg:province":"Milano",
    "wof:name":"Credito Lombardo",
    "wof:placetype":"venue"
},
  "geometry": {"coordinates":[9.203856,45.491814],"type":"Point"}
}