{
  "type": "Feature",
  "properties": {
    "iso:country":"IT",
    "sg:address":"48012 Bagnacavallo",
    "sg:city":"Bagnacavallo",
    "sg:orig_category":"Non-classified Establishments",
    "sg:phone":"+39 0545 60117",
    "sg:postcode":"48012",
    "sg:province":"Ravenna",
    "wof:name":"Ter S.r.l.",
    "wof:placetype":"venue"
},
  "geometry": {"coordinates":[12.009159,44.403648],"type":"Point"}
}