{
  "type": "Feature",
  "properties": {
    "iso:country":"IT",
    "sg:address":"Via Mola Saracena 00065 Fiano Romano",
    "sg:city":"Fiano Romano",
    "sg:classifiers":[
        {
            "category":"Home & Garden",
            "subcategory":"Home Furnishings",
            "type":"Retail Goods"
        }
    ],
    "sg:phone":"+39 0765 455800",
    "sg:postcode":"00065",
    "sg:province":"Roma",
    "sg:tags":[
        "household"
    ],
    "wof:name":"B & B Interiors & Design Srl",
    "wof:placetype":"venue"
},
  "geometry": {"coordinates":[12.588251,42.137417],"type":"Point"}
}