{
  "type": "Feature",
  "properties": {
    "iso:country":"IT",
    "sg:address":"31040 Meduna Di Livenza",
    "sg:city":"Meduna di Livenza",
    "sg:orig_category":"Manufacturers: Prefabbricati",
    "sg:phone":"+39 0422 865044",
    "sg:postcode":"31040",
    "sg:province":"Treviso",
    "sg:website":"http://www.lplsrl.it",
    "wof:name":"L.p.l. Snc",
    "wof:placetype":"venue"
},
  "geometry": {"coordinates":[12.597175,45.825924],"type":"Point"}
}