{
  "type": "Feature",
  "properties": {
    "iso:country":"IT",
    "sg:address":"97/c, Frazione Stazione Portacomaro 14100 Asti",
    "sg:city":"Asti",
    "sg:classifiers":[
        {
            "category":"Shopping",
            "subcategory":"Computers & Home Electronics",
            "type":"Retail Goods"
        }
    ],
    "sg:phone":"+39 0141 476997",
    "sg:postcode":"14100",
    "sg:province":"Asti",
    "sg:tags":[
        "electronic",
        "electrical",
        "equipment"
    ],
    "wof:name":"Abb Servomotors (s.r.l.)",
    "wof:placetype":"venue"
},
  "geometry": {"coordinates":[8.241948,44.928791],"type":"Point"}
}