{
  "type": "Feature",
  "properties": {
    "iso:country":"IT",
    "sg:address":"20122 Milano",
    "sg:city":"Milano",
    "sg:orig_category":"Agenzie D'affari E Servizi Commerciali. Avvocati, Notai E Servizi Legali. Consulenze Tecniche, Amministrative E Perizie",
    "sg:phone":"+39 02 798151",
    "sg:postcode":"20122",
    "sg:province":"Milano",
    "wof:name":"Erre A. Revisori Associati (s.r.l.)",
    "wof:placetype":"venue"
},
  "geometry": {"coordinates":[9.195937,45.462837],"type":"Point"}
}