{
  "type": "Feature",
  "properties": {
    "addr:full":"Via Carlo Cattaneo 90 20035 Lissone Lissone Milano 20035",
    "addr:housenumber":"90",
    "addr:postcode":"20035;20035",
    "addr:street":"Via Carlo Cattaneo",
    "iso:country":"IT",
    "sg:address":"Via Carlo Cattaneo 90 20035 Lissone",
    "sg:city":"Lissone",
    "sg:classifiers":[
        {
            "category":"Organizations",
            "subcategory":"Religious Organization",
            "type":"Services"
        }
    ],
    "sg:phone":"+39 039 24491",
    "sg:postcode":"20035",
    "sg:province":"Milano",
    "sg:tags":[
        "lamp",
        "display",
        "arrangement"
    ],
    "sg:website":"www.sidespa.it",
    "wof:name":"Side S.p.a.",
    "wof:placetype":"venue"
},
  "geometry": {"coordinates":[9.253805,45.614689],"type":"Point"}
}