{
  "type": "Feature",
  "properties": {
    "iso:country":"IT",
    "sg:address":"09028 Sestu",
    "sg:city":"Sestu",
    "sg:classifiers":[
        {
            "category":"Building & Trades",
            "subcategory":"Construction",
            "type":"Services"
        }
    ],
    "sg:phone":"+39 070 22281",
    "sg:postcode":"09028",
    "sg:province":"Cagliari",
    "sg:tags":[
        "activities",
        "industrial",
        "supply",
        "valve",
        "equipment",
        "measurement"
    ],
    "wof:name":"Novati Commerciale Sarda Srl",
    "wof:placetype":"venue"
},
  "geometry": {"coordinates":[9.049545,39.267525],"type":"Point"}
}