{
  "type": "Feature",
  "properties": {
    "addr:full":"10/c, V. C. Goldoni 59100 Prato Prato Prato 59100",
    "addr:housenumber":"10 / c v. c.",
    "addr:postcode":"59100;59100",
    "addr:street":"Goldoni",
    "iso:country":"IT",
    "sg:address":"10/c, V. C. Goldoni 59100 Prato",
    "sg:city":"Prato",
    "sg:classifiers":[
        {
            "category":"Shopping",
            "subcategory":"Crafts & Fabrics",
            "type":"Retail Goods"
        }
    ],
    "sg:phone":"+39 0574 461778",
    "sg:postcode":"59100",
    "sg:province":"Prato",
    "sg:tags":[
        "linen"
    ],
    "sg:website":"http://www.paginegialle.it/chartex",
    "wof:name":"Chartex Sas",
    "wof:placetype":"venue"
},
  "geometry": {"coordinates":[11.1048431396,43.8975524902],"type":"Point"}
}