{
  "type": "Feature",
  "properties": {
    "iso:country":"IT",
    "sg:address":"05100 Terni",
    "sg:city":"Terni",
    "sg:orig_category":"Prodotti Alimentari. Servizi E Lavori Per Industria Alimentare E Bevande",
    "sg:phone":"+39 0744 814305",
    "sg:postcode":"05100",
    "sg:province":"Terni",
    "wof:name":"Interpan Spa - Gruppo Novelli",
    "wof:placetype":"venue"
},
  "geometry": {"coordinates":[12.6040258408,42.553730011],"type":"Point"}
}