{
  "type": "Feature",
  "properties": {
    "iso:country":"IT",
    "sg:address":"Via Bellini Vincenzo 2 10121 Torino",
    "sg:city":"Torino",
    "sg:classifiers":[
        {
            "category":"Structure",
            "subcategory":"Office Building",
            "type":"Public Place"
        }
    ],
    "sg:phone":"+39 011 55461",
    "sg:postcode":"10121",
    "sg:province":"Torino",
    "sg:tags":[
        "construction",
        "apartment"
    ],
    "sg:website":"www.borinicostruzioni.com",
    "wof:name":"Borini Costruzioni Spa",
    "wof:placetype":"venue"
},
  "geometry": {"coordinates":[7.686619,45.07056],"type":"Point"}
}