{
  "type": "Feature",
  "properties": {
    "iso:country":"IT",
    "sg:address":"27058 Voghera",
    "sg:city":"Voghera",
    "sg:orig_category":"Macchine, Impianti Ed Attrezzature Per Agricoltura E Zootecnia",
    "sg:phone":"+39 0383 43797",
    "sg:postcode":"27058",
    "sg:province":"Pavia",
    "wof:name":"Pirini Gianni",
    "wof:placetype":"venue"
},
  "geometry": {"coordinates":[9.205344,45.177235],"type":"Point"}
}