{
  "type": "Feature",
  "properties": {
    "addr:full":"30020 Marcon Marcon Venezia 30020",
    "addr:postcode":"30020;30020",
    "iso:country":"IT",
    "sg:address":"30020 Marcon",
    "sg:city":"Marcon",
    "sg:orig_category":"Arredamenti E Mobili Professionali. Forniture Per Il Settore Dello Spettacolo",
    "sg:phone":"+39 041 456 9494",
    "sg:postcode":"30020",
    "sg:province":"Venezia",
    "wof:name":"Laima Srl",
    "wof:placetype":"venue"
},
  "geometry": {"coordinates":[12.295678,45.546288],"type":"Point"}
}