{
  "type": "Feature",
  "properties": {
    "addr:full":"10144 Torino Torino Torino 10144",
    "addr:postcode":"10144;10144",
    "iso:country":"IT",
    "sg:address":"10144 Torino",
    "sg:city":"Torino",
    "sg:orig_category":"Dolciumi E Gelati",
    "sg:phone":"+39 011 437 1168",
    "sg:postcode":"10144",
    "sg:province":"Torino",
    "sg:website":"http://www.pastiglie-leone.com",
    "wof:name":"Pastiglie Leone Srl",
    "wof:placetype":"venue"
},
  "geometry": {"coordinates":[7.593248,45.096569],"type":"Point"}
}