{
  "type": "Feature",
  "properties": {
    "iso:country":"IT",
    "sg:address":"20093 Cologno Monzese",
    "sg:city":"Cologno Monzese",
    "sg:orig_category":"Cine-foto-ottica",
    "sg:phone":"+39 02 2730 3412",
    "sg:postcode":"20093",
    "sg:province":"Milano",
    "wof:name":"Foto Ottica Picozzi Di Chiola Ferruccio & C. Sas",
    "wof:placetype":"venue"
},
  "geometry": {"coordinates":[9.279291,45.529037],"type":"Point"}
}