{
  "type": "Feature",
  "properties": {
    "addr:full":"Via Roma 61 50060 Londa Londa Firenze 50060",
    "addr:housenumber":"61",
    "addr:postcode":"50060;50060",
    "addr:street":"Via Roma;Londa",
    "iso:country":"IT",
    "sg:address":"Via Roma 61 50060 Londa",
    "sg:city":"Londa",
    "sg:classifiers":[
        {
            "category":"Bars & Pubs",
            "subcategory":"Dive Bar",
            "type":"Food & Drink"
        }
    ],
    "sg:phone":"+39 055 835 1680",
    "sg:postcode":"50060",
    "sg:province":"Firenze",
    "sg:tags":[
        "drinking",
        "tumbler",
        "glasses"
    ],
    "sg:website":"www.aicosalconplast.it",
    "wof:name":"Aicosalconplast Spa",
    "wof:placetype":"venue"
},
  "geometry": {"coordinates":[11.56494,43.86237],"type":"Point"}
}