{
  "type": "Feature",
  "properties": {
    "addr:full":"59100 Prato Prato Prato 59100",
    "addr:postcode":"59100;59100",
    "iso:country":"IT",
    "sg:address":"59100 Prato",
    "sg:city":"Prato",
    "sg:orig_category":"Arredo Camera Letto E Complementi",
    "sg:phone":"+39 0574 570236",
    "sg:postcode":"59100",
    "sg:province":"Prato",
    "sg:website":"http://www.materassiematerassi.it",
    "wof:name":"Materassi E Materassi",
    "wof:placetype":"venue"
},
  "geometry": {"coordinates":[11.106703,43.860168],"type":"Point"}
}