{
  "type": "Feature",
  "properties": {
    "addr:full":"09028 Sestu Sestu Cagliari 09028",
    "addr:postcode":"09028;09028",
    "iso:country":"IT",
    "sg:address":"09028 Sestu",
    "sg:city":"Sestu",
    "sg:orig_category":"Editoria Elettronica E Multimediale",
    "sg:phone":"+39 070 260297",
    "sg:postcode":"09028",
    "sg:province":"Cagliari",
    "wof:name":"C.d.e. Srl",
    "wof:placetype":"venue"
},
  "geometry": {"coordinates":[9.049545,39.267525],"type":"Point"}
}