{
  "type": "Feature",
  "properties": {
    "iso:country":"IT",
    "sg:address":"36050 Bolzano Vicentino",
    "sg:city":"Bolzano Vicentino",
    "sg:classifiers":[
        {
            "category":"Home & Garden",
            "subcategory":"Building Materials",
            "type":"Retail Goods"
        }
    ],
    "sg:phone":"+39 0444 535280",
    "sg:postcode":"36050",
    "sg:province":"Vicenza",
    "sg:tags":[
        "gas",
        "caldaie"
    ],
    "wof:name":"Termotecnica Bigarella Di Bigarella Mauro",
    "wof:placetype":"venue"
},
  "geometry": {"coordinates":[11.596325,45.578594],"type":"Point"}
}