{
  "type": "Feature",
  "properties": {
    "addr:full":"80121 Napoli Napoli Napoli 80121",
    "addr:housenumber":"80121",
    "addr:postcode":"80121",
    "iso:country":"IT",
    "sg:address":"80121 Napoli",
    "sg:city":"Napoli",
    "sg:orig_category":"Centri Di Estetica E Cosmesi E Servizi. Prodotti Cosmetici E Da Toeletta",
    "sg:phone":"+39 081 406444",
    "sg:postcode":"80121",
    "sg:province":"Napoli",
    "wof:name":"Parrucche Ts",
    "wof:placetype":"venue"
},
  "geometry": {"coordinates":[14.238945,40.835785],"type":"Point"}
}