{
  "type": "Feature",
  "properties": {
    "addr:full":"Largo Duca Degli Abruzzi 4, 91013 Calatafimi, Tp Calatafimi Trapani 91013",
    "addr:housenumber":"4",
    "addr:postcode":"91013;91013",
    "addr:street":"Largo Duca Degli Abruzzi",
    "iso:country":"IT",
    "sg:address":"Largo Duca Degli Abruzzi 4, 91013 Calatafimi, Tp",
    "sg:city":"Calatafimi",
    "sg:classifiers":[
        {
            "category":"Banks & Credit Unions",
            "subcategory":"Bank",
            "type":"Services"
        }
    ],
    "sg:postcode":"91013",
    "sg:province":"Trapani",
    "wof:name":"Banca Popolare Di Calatafimi Spa",
    "wof:placetype":"venue"
},
  "geometry": {"coordinates":[12.514634,38.018589],"type":"Point"}
}