{
  "type": "Feature",
  "properties": {
    "iso:country":"IT",
    "sg:address":"Via Roma 15; Cefala Diana; 90030",
    "sg:classifiers":[
        {
            "category":"Banks & Credit Unions",
            "subcategory":"Bank",
            "type":"Services"
        }
    ],
    "sg:phone":"+39 091 820 1112",
    "sg:postcode":"90030",
    "sg:province":"Palermo",
    "wof:name":"Banca Popolare Di Carini",
    "wof:placetype":"venue"
},
  "geometry": {"coordinates":[13.463285,37.914864],"type":"Point"}
}