{
  "type": "Feature",
  "properties": {
    "iso:country":"IT",
    "sg:address":"Via Delle Industrie 14 20050 Mezzago",
    "sg:city":"Mezzago",
    "sg:classifiers":[
        {
            "category":"Manufacturing",
            "subcategory":"Metals",
            "type":"Manufacturing & Wholesale Goods"
        }
    ],
    "sg:phone":"+39 039 602 0314",
    "sg:postcode":"20050",
    "sg:province":"Milano",
    "sg:tags":[
        "perforated",
        "sheet"
    ],
    "wof:name":"Relfo Spa",
    "wof:placetype":"venue"
},
  "geometry": {"coordinates":[9.4286136627,45.6261253357],"type":"Point"}
}