{
  "type": "Feature",
  "properties": {
    "addr:full":"Via Canovetti Cosimo 13 25128 Brescia Brescia Brescia 25128",
    "addr:housenumber":"13",
    "addr:postcode":"25128;25128",
    "addr:street":"Via Canovetti Cosimo",
    "iso:country":"IT",
    "sg:address":"Via Canovetti Cosimo 13 25128 Brescia",
    "sg:city":"Brescia",
    "sg:classifiers":[
        {
            "category":"Banks & Credit Unions",
            "subcategory":"Bank",
            "type":"Services"
        }
    ],
    "sg:phone":"+39 030 39991",
    "sg:postcode":"25128",
    "sg:province":"Brescia",
    "sg:tags":[
        "high",
        "grade",
        "steel"
    ],
    "sg:website":"www.orimartin.it",
    "wof:name":"Ori Martin Spa",
    "wof:placetype":"venue"
},
  "geometry": {"coordinates":[10.222958,45.539829],"type":"Point"}
}