{
  "type": "Feature",
  "properties": {
    "iso:country":"IT",
    "sg:address":"39012 Merano",
    "sg:city":"Merano",
    "sg:orig_category":"Falegnami",
    "sg:phone":"+39 0473 445135",
    "sg:postcode":"39012",
    "sg:province":"Bolzano/Bozen",
    "sg:website":"http://www.albatros.bz.it",
    "wof:name":"Albatros",
    "wof:placetype":"venue"
},
  "geometry": {"coordinates":[11.150683403,46.6689720154],"type":"Point"}
}