{
  "type": "Feature",
  "properties": {
    "addr:full":"00191 Roma Roma Roma 00191",
    "addr:postcode":"00191;00191",
    "iso:country":"IT",
    "sg:address":"00191 Roma",
    "sg:city":"Roma",
    "sg:classifiers":[
        {
            "category":"Professional",
            "subcategory":"Business Services",
            "type":"Services"
        }
    ],
    "sg:phone":"+39 06 333 9381",
    "sg:postcode":"00191",
    "sg:province":"Roma",
    "sg:tags":[
        "support",
        "companies",
        "events",
        "trade"
    ],
    "wof:name":"Studio Fratamico",
    "wof:placetype":"venue"
},
  "geometry": {"coordinates":[12.494854,41.99255],"type":"Point"}
}