{
  "type": "Feature",
  "properties": {
    "iso:country":"IT",
    "sg:address":"00192 Roma",
    "sg:city":"Roma",
    "sg:orig_category":"Associazioni Ed Organismi Di Interesse Pubblico",
    "sg:phone":"+39 06 321 5145",
    "sg:postcode":"00192",
    "sg:province":"Roma",
    "wof:name":"Associazione Nazionale Arma Aeronautica",
    "wof:placetype":"venue"
},
  "geometry": {"coordinates":[12.753295,41.835308],"type":"Point"}
}