{
  "type": "Feature",
  "properties": {
    "iso:country":"IT",
    "sg:address":"98051 Barcellona Pozzo Di Gotto",
    "sg:city":"Barcellona Pozzo di Gotto",
    "sg:orig_category":"Prodotti Alimentari. Agricoltura, Orticoltura E Floricoltura",
    "sg:phone":"+39 090 970 1229",
    "sg:postcode":"98051",
    "sg:province":"Messina",
    "wof:name":"A.p.a.o.m.",
    "wof:placetype":"venue"
},
  "geometry": {"coordinates":[15.2126531601,38.1561508179],"type":"Point"}
}