{
  "type": "Feature",
  "properties": {
    "addr:full":"3, Via Giacosa Giuseppe 20127 Milano Milano Milano 20127",
    "addr:postcode":"20127;20127",
    "addr:street":"Via Giacosa Giuseppe",
    "iso:country":"IT",
    "sg:address":"3, Via Giacosa Giuseppe 20127 Milano",
    "sg:city":"Milano",
    "sg:classifiers":[
        {
            "category":"Food & Beverages",
            "subcategory":"Groceries & Convenience Stores",
            "type":"Retail Goods"
        }
    ],
    "sg:phone":"+39 02 2890 0538",
    "sg:postcode":"20127",
    "sg:province":"Milano",
    "sg:tags":[
        "drink"
    ],
    "wof:name":"Amylum Italia Srl",
    "wof:placetype":"venue"
},
  "geometry": {"coordinates":[9.222918,45.491615],"type":"Point"}
}