{
  "type": "Feature",
  "properties": {
    "addr:full":"33, Via Negrisia 31010 Ormelle Treviso 31010",
    "addr:postcode":"31010;31010",
    "addr:street":"Via Negrisia",
    "iso:country":"IT",
    "sg:address":"33, Via Negrisia 31010 Ormelle",
    "sg:classifiers":[
        {
            "category":"Home & Garden",
            "subcategory":"Home Furnishings",
            "type":"Retail Goods"
        }
    ],
    "sg:phone":"+39 0422 751000",
    "sg:postcode":"31010",
    "sg:province":"Treviso",
    "sg:tags":[
        "household"
    ],
    "wof:name":"Mobil Sprint Srl",
    "wof:placetype":"venue"
},
  "geometry": {"coordinates":[12.418502,45.730377],"type":"Point"}
}