{
  "type": "Feature",
  "properties": {
    "iso:country":"IT",
    "sg:address":"00139 Roma",
    "sg:city":"Roma",
    "sg:orig_category":"Articoli Medico-sanitari Ed Ortopedici",
    "sg:phone":"+39 06 8852 1836",
    "sg:postcode":"00139",
    "sg:province":"Roma",
    "sg:website":"http://www.autonomi.it",
    "wof:name":"Autonomi Srl",
    "wof:placetype":"venue"
},
  "geometry": {"coordinates":[12.518984,41.963387],"type":"Point"}
}