{
  "type": "Feature",
  "properties": {
    "iso:country":"IT",
    "sg:address":"20124 Milano",
    "sg:city":"Milano",
    "sg:orig_category":"Cine-foto-ottica",
    "sg:phone":"+39 02 669 4276",
    "sg:postcode":"20124",
    "sg:province":"Milano",
    "wof:name":"Smaf Spa",
    "wof:placetype":"venue"
},
  "geometry": {"coordinates":[9.198601,45.490528],"type":"Point"}
}