{
  "type": "Feature",
  "properties": {
    "addr:full":"25, Via Gheghi 55012 Capannori Capannori Lucca 55012",
    "addr:postcode":"55012;55012",
    "addr:street":"Via Gheghi",
    "iso:country":"IT",
    "sg:address":"25, Via Gheghi 55012 Capannori",
    "sg:city":"Capannori",
    "sg:classifiers":[
        {
            "category":"Personal",
            "subcategory":"Shoe Repair & Shine",
            "type":"Services"
        }
    ],
    "sg:phone":"+39 0583 928385",
    "sg:postcode":"55012",
    "sg:province":"Lucca",
    "sg:tags":[
        "leather"
    ],
    "wof:name":"Del Prete Amerigo Srl",
    "wof:placetype":"venue"
},
  "geometry": {"coordinates":[10.585398,43.87347],"type":"Point"}
}