{
  "type": "Feature",
  "properties": {
    "iso:country":"IT",
    "sg:address":"Via Roma 2; Altare; 17041",
    "sg:city":"Altare",
    "sg:classifiers":[
        {
            "category":"Banks & Credit Unions",
            "subcategory":"Bank",
            "type":"Services"
        }
    ],
    "sg:phone":"+39 019 584481",
    "sg:postcode":"17041",
    "sg:province":"Savona",
    "wof:name":"Cassa Risparmio Di Savona",
    "wof:placetype":"venue"
},
  "geometry": {"coordinates":[8.341868,44.335239],"type":"Point"}
}