{
  "type": "Feature",
  "properties": {
    "iso:country":"IT",
    "sg:address":"21035 Cunardo",
    "sg:city":"Cunardo",
    "sg:orig_category":"Apparecchiature E Sistemi Per Magazzinaggio E Movimentazione",
    "sg:phone":"+39 0332 716206",
    "sg:postcode":"21035",
    "sg:province":"Varese",
    "wof:name":"Varese Autogr\u00d9 Di Polita Geom. Fabio",
    "wof:placetype":"venue"
},
  "geometry": {"coordinates":[8.807352,45.93502],"type":"Point"}
}