{
  "type": "Feature",
  "properties": {
    "addr:full":"74015 Martina Franca Martina Franca Taranto 74015",
    "addr:housenumber":"74015",
    "addr:postcode":"74015",
    "iso:country":"IT",
    "sg:address":"74015 Martina Franca",
    "sg:city":"Martina Franca",
    "sg:orig_category":"Servizi E Lavori Per Edilizia E Lavori Pubblici. Professionisti - Studi E Servizi Ed Associazioni Di Interesse Aziendale",
    "sg:phone":"+39 080 480 9669",
    "sg:postcode":"74015",
    "sg:province":"Taranto",
    "wof:name":"Stit Gea Engineering Constructions Management Srl",
    "wof:placetype":"venue"
},
  "geometry": {"coordinates":[17.335407,40.699455],"type":"Point"}
}