{
  "type": "Feature",
  "properties": {
    "iso:country":"IT",
    "sg:address":"13900 Biella",
    "sg:city":"Biella",
    "sg:orig_category":"Servizi E Lavori Per Edilizia E Lavori Pubblici. Acqua, Luce, Gas E Societa' Di Esercizio Pubblico",
    "sg:phone":"+39 015 401125",
    "sg:postcode":"13900",
    "sg:province":"Biella",
    "wof:name":"Cordar - Societa'per Il Servizio Idrico Integrato S.p.a.",
    "wof:placetype":"venue"
},
  "geometry": {"coordinates":[8.045113,45.559654],"type":"Point"}
}