{
  "type": "Feature",
  "properties": {
    "addr:full":"61024 Mombaroccio Mombaroccio Pesaro E Urbino 61024",
    "addr:postcode":"61024;61024",
    "iso:country":"IT",
    "sg:address":"61024 Mombaroccio",
    "sg:city":"Mombaroccio",
    "sg:orig_category":"Macchine E Forniture Per Arredamento E Industria Del Legno",
    "sg:phone":"+39 0721 471191",
    "sg:postcode":"61024",
    "sg:province":"Pesaro E Urbino",
    "wof:name":"Zanca Srl",
    "wof:placetype":"venue"
},
  "geometry": {"coordinates":[12.863742,43.816666],"type":"Point"}
}