{
  "type": "Feature",
  "properties": {
    "iso:country":"IT",
    "sg:address":"Via G. Galilei 19 35015 Galliera Veneta",
    "sg:city":"Galliera Veneta",
    "sg:classifiers":[
        {
            "category":"Transit Center",
            "subcategory":"Passenger",
            "type":"Transportation"
        }
    ],
    "sg:phone":"+39 049 596 5097",
    "sg:postcode":"35015",
    "sg:province":"Padova",
    "sg:tags":[
        "rolling",
        "industry",
        "door",
        "doors",
        "sectional"
    ],
    "wof:name":"Sicc S.r.l.",
    "wof:placetype":"venue"
},
  "geometry": {"coordinates":[11.876589,45.409569],"type":"Point"}
}