{
  "type": "Feature",
  "properties": {
    "iso:country":"IT",
    "sg:address":"18033 Camporosso",
    "sg:city":"Camporosso",
    "sg:orig_category":"Automobili E Mezzi Di Trasporto",
    "sg:phone":"+39 0184 255630",
    "sg:postcode":"18033",
    "sg:province":"Imperia",
    "wof:name":"Autofficina Cassini Renato & C.",
    "wof:placetype":"venue"
},
  "geometry": {"coordinates":[7.631943,43.796951],"type":"Point"}
}