{
  "type": "Feature",
  "properties": {
    "iso:country":"IT",
    "sg:address":"Via Valsorda 22040 Alzate Brianza",
    "sg:city":"Alzate Brianza",
    "sg:classifiers":[
        {
            "category":"Shopping",
            "subcategory":"Crafts & Fabrics",
            "type":"Retail Goods"
        }
    ],
    "sg:phone":"+39 39031619945",
    "sg:postcode":"22040",
    "sg:province":"Como",
    "wof:name":"Tessilcrine Di Aldo Valtorta & C. Sas",
    "wof:placetype":"venue"
},
  "geometry": {"coordinates":[9.1924362183,45.7368240356],"type":"Point"}
}