{
  "type": "Feature",
  "properties": {
    "addr:full":"5, Via Del Lavoro 45010 Villadose Villadose Rovigo 45010",
    "addr:postcode":"45010;45010",
    "addr:street":"Via Del Lavoro",
    "iso:country":"IT",
    "sg:address":"5, Via Del Lavoro 45010 Villadose",
    "sg:city":"Villadose",
    "sg:classifiers":[
        {
            "category":"Manufacturing",
            "subcategory":"Metals",
            "type":"Manufacturing & Wholesale Goods"
        }
    ],
    "sg:phone":"+39 0425 405052",
    "sg:postcode":"45010",
    "sg:province":"Rovigo",
    "sg:tags":[
        "metallurgy",
        "metalworking"
    ],
    "wof:name":"Tecnoaccessori Srl",
    "wof:placetype":"venue"
},
  "geometry": {"coordinates":[11.8717708588,45.1266021729],"type":"Point"}
}