{
  "type": "Feature",
  "properties": {
    "iso:country":"IT",
    "sg:address":"81, Via Don Gnocchi 22044 Inverigo",
    "sg:city":"Inverigo",
    "sg:classifiers":[
        {
            "category":"Travel",
            "subcategory":"Travel Agent",
            "type":"Entertainment"
        }
    ],
    "sg:phone":"+39 39031696577",
    "sg:postcode":"22044",
    "sg:province":"Como",
    "sg:tags":[
        "business"
    ],
    "wof:name":"Albergo Ristorante Il Nuovo Crotto Rosa",
    "wof:placetype":"venue"
},
  "geometry": {"coordinates":[9.213522,45.736252],"type":"Point"}
}