{
  "type": "Feature",
  "properties": {
    "addr:full":"Via Ca'dell'orbo 49 40055 Villanova Villanova Bologna 40055",
    "addr:housenumber":"49",
    "addr:postcode":"40055;40055",
    "addr:street":"Via Ca'Dell'Orbo",
    "iso:country":"IT",
    "sg:address":"Via Ca'dell'orbo 49 40055 Villanova",
    "sg:city":"Villanova",
    "sg:classifiers":[
        {
            "category":"Manufacturing",
            "subcategory":"Metals",
            "type":"Manufacturing & Wholesale Goods"
        }
    ],
    "sg:phone":"+39 051 781122",
    "sg:postcode":"40055",
    "sg:province":"Bologna",
    "sg:tags":[
        "machine",
        "sheet",
        "working"
    ],
    "wof:name":"Grandini Meccanica Srl",
    "wof:placetype":"venue"
},
  "geometry": {"coordinates":[11.43843,44.507168],"type":"Point"}
}