{
  "type": "Feature",
  "properties": {
    "iso:country":"IT",
    "sg:address":"90032 Bisacquino",
    "sg:city":"Bisacquino",
    "sg:orig_category":"Termotecnica E Riscaldamento, Apparecchiature E Servizi",
    "sg:phone":"+39 091 835 1955",
    "sg:postcode":"90032",
    "sg:province":"Palermo",
    "wof:name":"De Angeli Denis",
    "wof:placetype":"venue"
},
  "geometry": {"coordinates":[13.258952,37.709839],"type":"Point"}
}