{
  "type": "Feature",
  "properties": {
    "addr:full":"20093 Cologno Monzese Cologno Monzese Milano 20093",
    "addr:postcode":"20093;20093",
    "iso:country":"IT",
    "sg:address":"20093 Cologno Monzese",
    "sg:city":"Cologno Monzese",
    "sg:orig_category":"Prodotti Chimici Di Base. Forniture Per Attivita' Industriali",
    "sg:phone":"+39 02 254 5091",
    "sg:postcode":"20093",
    "sg:province":"Milano",
    "wof:name":"Bz - Eurocolor (s.a.s.)",
    "wof:placetype":"venue"
},
  "geometry": {"coordinates":[9.2648620605,45.534942627],"type":"Point"}
}