{
  "type": "Feature",
  "properties": {
    "iso:country":"IT",
    "sg:address":"53100 Siena",
    "sg:city":"Siena",
    "sg:orig_category":"Centri Di Estetica E Cosmesi E Servizi",
    "sg:phone":"+39 0577 283280",
    "sg:postcode":"53100",
    "sg:province":"Siena",
    "sg:website":"http://www.ilmosaiko.it",
    "wof:name":"Mosaiko Hair Diffusion",
    "wof:placetype":"venue"
},
  "geometry": {"coordinates":[11.330226,43.316666],"type":"Point"}
}