{
  "type": "Feature",
  "properties": {
    "addr:full":"5, Via Lamarmora 27058 Voghera Voghera Pavia 27058",
    "addr:postcode":"27058;27058",
    "addr:street":"Via Lamarmora",
    "iso:country":"IT",
    "sg:address":"5, Via Lamarmora 27058 Voghera",
    "sg:city":"Voghera",
    "sg:classifiers":[
        {
            "category":"Manufacturing",
            "subcategory":"Metals",
            "type":"Manufacturing & Wholesale Goods"
        }
    ],
    "sg:phone":"+39 39038348841",
    "sg:postcode":"27058",
    "sg:province":"Pavia",
    "sg:tags":[
        "metallurgy",
        "metalworking"
    ],
    "wof:name":"Stanley Italia S.r.l.",
    "wof:placetype":"venue"
},
  "geometry": {"coordinates":[9.0169792175,44.9980773926],"type":"Point"}
}