{
  "type": "Feature",
  "properties": {
    "iso:country":"IT",
    "sg:address":"Via Ricordi 32 43011 Busseto",
    "sg:city":"Busseto",
    "sg:orig_category":"Resistors, Electrical",
    "sg:phone":"+39 0524 92460",
    "sg:postcode":"43011",
    "sg:province":"Parma",
    "sg:website":"www.tecnowattsnc.it",
    "wof:name":"Tecnowatt S.n.c.",
    "wof:placetype":"venue"
},
  "geometry": {"coordinates":[10.050588,44.98457],"type":"Point"}
}