{
  "type": "Feature",
  "properties": {
    "iso:country":"IT",
    "sg:address":"20093 Cologno Monzese",
    "sg:city":"Cologno Monzese",
    "sg:orig_category":"Studi E Consulenze Tecniche E Industriali. Assicurazioni E Servizi Assicurativi. Consulenze Tecniche, Amministrative E Perizie",
    "sg:phone":"+39 02 2670 8306",
    "sg:postcode":"20093",
    "sg:province":"Milano",
    "wof:name":"Studio Peritale Ascenzo",
    "wof:placetype":"venue"
},
  "geometry": {"coordinates":[9.278098,45.533524],"type":"Point"}
}