{
  "type": "Feature",
  "properties": {
    "iso:country":"IT",
    "sg:address":"10147 Torino",
    "sg:city":"Torino",
    "sg:orig_category":"Non-classified Establishments",
    "sg:phone":"+39 011 226 1034",
    "sg:postcode":"10147",
    "sg:province":"Torino",
    "wof:name":"Toy Fantasy Di Bagetto G. & C. (s.n.c.)",
    "wof:placetype":"venue"
},
  "geometry": {"coordinates":[7.676558,45.102867],"type":"Point"}
}