{
  "type": "Feature",
  "properties": {
    "iso:country":"IT",
    "sg:address":"00040 Castel Gandolfo",
    "sg:city":"Castel Gandolfo",
    "sg:classifiers":[
        {
            "category":"Sports & Exercise",
            "subcategory":"Tennis Court",
            "type":"Entertainment"
        }
    ],
    "sg:phone":"+39 06 936 0634",
    "sg:postcode":"00040",
    "sg:province":"Roma",
    "sg:tags":[
        "e",
        "lo",
        "tempo",
        "libero",
        "per",
        "impianti",
        "il",
        "attrezzature"
    ],
    "wof:name":"Petriconi Claudio",
    "wof:placetype":"venue"
},
  "geometry": {"coordinates":[12.650542,41.743259],"type":"Point"}
}