{
  "type": "Feature",
  "properties": {
    "iso:country":"IT",
    "sg:address":"Via Passolombardo 26100 Cremona",
    "sg:city":"Cremona",
    "sg:classifiers":[
        {
            "category":"Travel",
            "subcategory":"Travel Agent",
            "type":"Entertainment"
        }
    ],
    "sg:phone":"+39 0372 450490",
    "sg:postcode":"26100",
    "sg:province":"Cremona",
    "sg:tags":[
        "business"
    ],
    "wof:name":"Hermes Hotel",
    "wof:placetype":"venue"
},
  "geometry": {"coordinates":[10.068518,45.140186],"type":"Point"}
}