{
  "type": "Feature",
  "properties": {
    "addr:full":"31053 Pieve Di Soligo Pieve di Soligo Treviso 31053",
    "addr:postcode":"31053;31053",
    "iso:country":"IT",
    "sg:address":"31053 Pieve Di Soligo",
    "sg:city":"Pieve di Soligo",
    "sg:orig_category":"Alberghi E Strutture Extra Alberghiere. Servizi Per Aziende, Manifestazioni E Supporto Agli Scambi Commerciali",
    "sg:phone":"+39 0438 980435",
    "sg:postcode":"31053",
    "sg:province":"Treviso",
    "sg:website":"http://www.nline.it/conta",
    "wof:name":"Hotel Conta' Gestioni Srl",
    "wof:placetype":"venue"
},
  "geometry": {"coordinates":[12.170751,45.903698],"type":"Point"}
}