{
  "type": "Feature",
  "properties": {
    "iso:country":"IT",
    "sg:address":"20026 Novate Milanese",
    "sg:city":"Novate Milanese",
    "sg:orig_category":"Macchine, Impianti Ed Attrezzature Industria Chimica. Pompe",
    "sg:phone":"+39 02 354 1607",
    "sg:postcode":"20026",
    "sg:province":"Milano",
    "wof:name":"C.i. Emme Di Morelli Osvaldo & C. (s.n.c.)",
    "wof:placetype":"venue"
},
  "geometry": {"coordinates":[9.141828,45.533119],"type":"Point"}
}