{
  "type": "Feature",
  "properties": {
    "iso:country":"IT",
    "sg:address":"Via Lamarmora Alfonso 21 20122 Milano",
    "sg:city":"Milano",
    "sg:classifiers":[
        {
            "category":"Shopping",
            "subcategory":"Beauty & Cosmetics",
            "type":"Retail Goods"
        }
    ],
    "sg:phone":"+39 02 5501 1452",
    "sg:postcode":"20122",
    "sg:province":"Milano",
    "sg:tags":[
        "farm",
        "equipment",
        "care",
        "institute",
        "wellness"
    ],
    "sg:website":"www.bielsan.com",
    "wof:name":"Bielsan Srl",
    "wof:placetype":"venue"
},
  "geometry": {"coordinates":[9.199655,45.456703],"type":"Point"}
}