{
  "type": "Feature",
  "properties": {
    "iso:country":"IT",
    "sg:address":"00195 Roma",
    "sg:city":"Roma",
    "sg:orig_category":"Cinematografia E Radiotelevisione. Forniture Per Il Settore Dello Spettacolo",
    "sg:phone":"+39 06 3751 3931",
    "sg:postcode":"00195",
    "sg:province":"Roma",
    "wof:name":"Aries Film (s.r.l.)",
    "wof:placetype":"venue"
},
  "geometry": {"coordinates":[12.462166,41.914528],"type":"Point"}
}