{
  "type": "Feature",
  "properties": {
    "addr:full":"10090 Trana Trana Torino 10090",
    "addr:postcode":"10090;10090",
    "iso:country":"IT",
    "sg:address":"10090 Trana",
    "sg:city":"Trana",
    "sg:classifiers":[
        {
            "category":"Education",
            "subcategory":"Dance Studio",
            "type":"Public Place"
        }
    ],
    "sg:phone":"+39 011 933735",
    "sg:postcode":"10090",
    "sg:province":"Torino",
    "sg:tags":[
        "pallet"
    ],
    "sg:website":"http://www.mgapallets.it",
    "wof:name":"Mga Pallets Srl",
    "wof:placetype":"venue"
},
  "geometry": {"coordinates":[7.4619479179,45.0220069885],"type":"Point"}
}