{
  "type": "Feature",
  "properties": {
    "addr:full":"36072 Chiampo Chiampo Vicenza 36072",
    "addr:postcode":"36072;36072",
    "iso:country":"IT",
    "sg:address":"36072 Chiampo",
    "sg:city":"Chiampo",
    "sg:classifiers":[
        {
            "category":"Manufacturing",
            "subcategory":"Leather Goods",
            "type":"Manufacturing & Wholesale Goods"
        }
    ],
    "sg:phone":"+39 0444 420800",
    "sg:postcode":"36072",
    "sg:province":"Vicenza",
    "sg:tags":[
        "footwear",
        "skin"
    ],
    "sg:website":"http://www.conceriatolio.com",
    "wof:name":"Conceria Tolio Spa",
    "wof:placetype":"venue"
},
  "geometry": {"coordinates":[11.3449888229,45.5177268982],"type":"Point"}
}