{
  "type": "Feature",
  "properties": {
    "iso:country":"IT",
    "sg:address":"Via Provinciale Francesca Sud 167 56022 Castelfranco Di Sotto",
    "sg:city":"Castelfranco di Sotto",
    "sg:classifiers":[
        {
            "category":"Shopping",
            "subcategory":"Shoes",
            "type":"Retail Goods"
        }
    ],
    "sg:phone":"+39 0571 478804",
    "sg:postcode":"56022",
    "sg:province":"Pisa",
    "sg:tags":[
        "wooden",
        "slipper"
    ],
    "sg:website":"www.californiasrl.it",
    "wof:name":"Calzaturificio California Srl",
    "wof:placetype":"venue"
},
  "geometry": {"coordinates":[10.735461,43.698605],"type":"Point"}
}