{
  "type": "Feature",
  "properties": {
    "iso:country":"IT",
    "sg:address":"12, Via Campo Di Pozzo 41038 San Felice Sul Panaro",
    "sg:city":"San Felice sul Panaro",
    "sg:classifiers":[
        {
            "category":"Parking",
            "subcategory":"Lot",
            "type":"Transportation"
        }
    ],
    "sg:phone":"+39 0535 671056",
    "sg:postcode":"41038",
    "sg:province":"Modena",
    "sg:tags":[
        "transport",
        "road"
    ],
    "wof:name":"Picotrans S.r.l.",
    "wof:placetype":"venue"
},
  "geometry": {"coordinates":[11.122303,44.839874],"type":"Point"}
}