{
  "type": "Feature",
  "properties": {
    "iso:country":"IT",
    "sg:address":"Blocco 4.2a Interporto 40010 Bentivoglio",
    "sg:city":"Bentivoglio",
    "sg:classifiers":[
        {
            "category":"Farming",
            "subcategory":"Livestock Farm",
            "type":"Manufacturing & Wholesale Goods"
        }
    ],
    "sg:phone":"+39 051 665 9700",
    "sg:postcode":"40010",
    "sg:province":"Bologna",
    "sg:tags":[
        "agriculture"
    ],
    "wof:name":"Le Quattro Stagioni",
    "wof:placetype":"venue"
},
  "geometry": {"coordinates":[11.346481,44.494221],"type":"Point"}
}