{
  "type": "Feature",
  "properties": {
    "iso:country":"IT",
    "sg:address":"9, Via Campo Gallo 20020 Arese",
    "sg:city":"Arese",
    "sg:classifiers":[
        {
            "category":"Utilities",
            "subcategory":"Telephone",
            "type":"Services"
        }
    ],
    "sg:phone":"+39 39029380875",
    "sg:postcode":"20020",
    "sg:province":"Milano",
    "sg:tags":[
        "telecommunication"
    ],
    "wof:name":"Telesystem (s.r.l.)",
    "wof:placetype":"venue"
},
  "geometry": {"coordinates":[9.08781,45.549232],"type":"Point"}
}