{
  "type": "Feature",
  "properties": {
    "iso:country":"IT",
    "sg:address":"50038 Scarperia",
    "sg:city":"Scarperia",
    "sg:orig_category":"Alberghi E Strutture Extra Alberghiere. Servizi Per Aziende, Manifestazioni E Supporto Agli Scambi Commerciali",
    "sg:phone":"+39 055 840 6012",
    "sg:postcode":"50038",
    "sg:province":"Firenze",
    "wof:name":"Villa Medicea Lo Sprocco",
    "wof:placetype":"venue"
},
  "geometry": {"coordinates":[11.320416,44.04398],"type":"Point"}
}