{
  "type": "Feature",
  "properties": {
    "iso:country":"IT",
    "sg:address":"33070 Vigonovo Di Fontanafredda",
    "sg:classifiers":[
        {
            "category":"Building & Trades",
            "subcategory":"Construction",
            "type":"Services"
        }
    ],
    "sg:phone":"+39 0434 567911",
    "sg:postcode":"33070",
    "sg:province":"Pordenone",
    "sg:tags":[
        "equipment",
        "heat",
        "heating",
        "engineering"
    ],
    "sg:website":"http://www.emmeti.com",
    "wof:name":"Emmeti Spa",
    "wof:placetype":"venue"
},
  "geometry": {"coordinates":[12.710835,46.037888],"type":"Point"}
}