{
  "type": "Feature",
  "properties": {
    "iso:country":"IT",
    "sg:address":"13, Via Milazzo 53045 Montepulciano",
    "sg:city":"Montepulciano",
    "sg:classifiers":[
        {
            "category":"Home & Garden",
            "subcategory":"Home Furnishings",
            "type":"Retail Goods"
        }
    ],
    "sg:phone":"+39 0578 738095",
    "sg:postcode":"53045",
    "sg:province":"Siena",
    "sg:tags":[
        "household"
    ],
    "wof:name":"Neri Iorio E. Ivano",
    "wof:placetype":"venue"
},
  "geometry": {"coordinates":[11.861516,43.136696],"type":"Point"}
}