{
  "type": "Feature",
  "properties": {
    "addr:full":"38068 Rovereto Rovereto Trento 38068",
    "addr:postcode":"38068;38068",
    "iso:country":"IT",
    "sg:address":"38068 Rovereto",
    "sg:city":"Rovereto",
    "sg:orig_category":"Impiantistica E Prodotti Tecnologici Per Edilizia. Termotecnica E Riscaldamento, Apparecchiature E Servizi",
    "sg:phone":"+39 0464 430978",
    "sg:postcode":"38068",
    "sg:province":"Trento",
    "wof:name":"Bruschetti Sandro 'ditta Climatic'",
    "wof:placetype":"venue"
},
  "geometry": {"coordinates":[11.028925,45.868103],"type":"Point"}
}