{
  "type": "Feature",
  "properties": {
    "addr:full":"24040 Bonate Sopra Bonate Sopra Bergamo 24040",
    "addr:postcode":"24040;24040",
    "addr:street":"Sopra",
    "iso:country":"IT",
    "sg:address":"24040 Bonate Sopra",
    "sg:city":"Bonate Sopra",
    "sg:orig_category":"Manufacturers: Prefabbricati",
    "sg:phone":"+39 035 993176",
    "sg:postcode":"24040",
    "sg:province":"Bergamo",
    "wof:name":"Boschini Elio",
    "wof:placetype":"venue"
},
  "geometry": {"coordinates":[9.575091,45.708332],"type":"Point"}
}