{
  "type": "Feature",
  "properties": {
    "addr:full":"33170 Pordenone Pordenone Pordenone 33170",
    "addr:postcode":"33170;33170",
    "iso:country":"IT",
    "sg:address":"33170 Pordenone",
    "sg:city":"Pordenone",
    "sg:orig_category":"Pubblicita' - Cartelli, Insegne E Targhe",
    "sg:phone":"+39 0434 555184",
    "sg:postcode":"33170",
    "sg:province":"Pordenone",
    "wof:name":"Pubblicar Studio Di Bonon Geom. Lucio",
    "wof:placetype":"venue"
},
  "geometry": {"coordinates":[12.6476202011,46.0064811707],"type":"Point"}
}