{
  "type": "Feature",
  "properties": {
    "addr:full":"84013 Cava De' Tirreni Salerno 84013",
    "addr:postcode":"84013;84013",
    "iso:country":"IT",
    "sg:address":"84013 Cava De' Tirreni",
    "sg:orig_category":"Antifurto",
    "sg:phone":"+39 089 466807",
    "sg:postcode":"84013",
    "sg:province":"Salerno",
    "wof:name":"Euroservice Coop.r.l.",
    "wof:placetype":"venue"
},
  "geometry": {"coordinates":[14.705413,40.699829],"type":"Point"}
}