{
  "type": "Feature",
  "properties": {
    "iso:country":"IT",
    "sg:address":"00186 Roma",
    "sg:city":"Roma",
    "sg:orig_category":"Alberghi E Strutture Extra Alberghiere",
    "sg:phone":"+39 06 6880 9278",
    "sg:postcode":"00186",
    "sg:province":"Roma",
    "sg:website":"http://www.travel.it/roma/locandacairoli",
    "wof:name":"Locanda Cairoli",
    "wof:placetype":"venue"
},
  "geometry": {"coordinates":[12.489468,41.85833],"type":"Point"}
}