{
  "type": "Feature",
  "properties": {
    "iso:country":"IT",
    "sg:address":"20036 Meda",
    "sg:city":"Meda",
    "sg:orig_category":"Servizi E Lavori Per Arredamento E Industria Del Legno",
    "sg:phone":"+39 036 234 3359",
    "sg:postcode":"20036",
    "sg:province":"Milano",
    "wof:name":"Cappelli Pietro E Figlio Di Cappelli Giancarlo Ec. S.a.s.",
    "wof:placetype":"venue"
},
  "geometry": {"coordinates":[9.212464,45.488014],"type":"Point"}
}