{
  "type": "Feature",
  "properties": {
    "addr:full":"37014 Castelnuovo Del Garda Castelnuovo del Garda Verona 37014",
    "addr:postcode":"37014;37014",
    "iso:country":"IT",
    "sg:address":"37014 Castelnuovo Del Garda",
    "sg:city":"Castelnuovo del Garda",
    "sg:classifiers":[
        {
            "category":"Restaurant",
            "type":"Food & Drink"
        }
    ],
    "sg:phone":"+39 045 757 0338",
    "sg:postcode":"37014",
    "sg:province":"Verona",
    "sg:tags":[
        "auxiliary",
        "entertainment",
        "premises",
        "related",
        "catering",
        "similar",
        "public",
        "restaurants"
    ],
    "wof:name":"Ra.gen. Hotel Ristorante Pizzeria Lo Scoglio",
    "wof:placetype":"venue"
},
  "geometry": {"coordinates":[10.737102,45.437038],"type":"Point"}
}