{
  "type": "Feature",
  "properties": {
    "addr:full":"Via G. Sirtori 45 20017 Rho Rho Milano 20017",
    "addr:housenumber":"45",
    "addr:postcode":"20017;20017",
    "addr:street":"Via G. Sirtori",
    "iso:country":"IT",
    "sg:address":"Via G. Sirtori 45 20017 Rho",
    "sg:city":"Rho",
    "sg:classifiers":[
        {
            "category":"Train Station",
            "subcategory":"Rail",
            "type":"Transportation"
        }
    ],
    "sg:phone":"+39 02 937521",
    "sg:postcode":"20017",
    "sg:province":"Milano",
    "sg:tags":[
        "packaging",
        "adhesive",
        "tape"
    ],
    "sg:website":"www.boston-tapes.it",
    "wof:name":"Boston Tapes Spa",
    "wof:placetype":"venue"
},
  "geometry": {"coordinates":[9.188141,45.463688],"type":"Point"}
}