{
  "type": "Feature",
  "properties": {
    "iso:country":"IT",
    "sg:address":"Via Fracanzana 10 36054 Montebello Vicentino",
    "sg:city":"Montebello Vicentino",
    "sg:classifiers":[
        {
            "category":"Home & Garden",
            "subcategory":"Carpets & Floor Coverings",
            "type":"Retail Goods"
        }
    ],
    "sg:phone":"+39 0444 644100",
    "sg:postcode":"36054",
    "sg:province":"Vicenza",
    "sg:tags":[
        "animal",
        "skin"
    ],
    "wof:name":"Conceria Cristina Spa",
    "wof:placetype":"venue"
},
  "geometry": {"coordinates":[11.379151,45.446995],"type":"Point"}
}