{
  "type": "Feature",
  "properties": {
    "addr:full":"Via Pascarella Cesare 7 00153 Roma Roma Roma 00153",
    "addr:housenumber":"7",
    "addr:postcode":"00153;00153",
    "addr:street":"Via Pascarella Cesare",
    "iso:country":"IT",
    "sg:address":"Via Pascarella Cesare 7 00153 Roma",
    "sg:city":"Roma",
    "sg:classifiers":[
        {
            "category":"Shopping",
            "subcategory":"Tobacco",
            "type":"Retail Goods"
        }
    ],
    "sg:phone":"+39 0658691",
    "sg:postcode":"00153",
    "sg:province":"Roma",
    "sg:tags":[
        "pipe"
    ],
    "wof:name":"Ati Azienda Tabacchi Italiani Spa",
    "wof:placetype":"venue"
},
  "geometry": {"coordinates":[12.4823246002,41.8954658508],"type":"Point"}
}