{
  "type": "Feature",
  "properties": {
    "iso:country":"IT",
    "sg:address":"35040 Casale Di Scodosia",
    "sg:city":"Casale di Scodosia",
    "sg:orig_category":"Non-classified Establishments",
    "sg:phone":"+39 0429 847680",
    "sg:postcode":"35040",
    "sg:province":"Padova",
    "wof:name":"Moro Loris",
    "wof:placetype":"venue"
},
  "geometry": {"coordinates":[11.495228,45.183838],"type":"Point"}
}