{
  "type": "Feature",
  "properties": {
    "iso:country":"IT",
    "sg:address":"5, Via Zona Pip 83020 Domicella",
    "sg:city":"Domicella",
    "sg:classifiers":[
        {
            "category":"Professional",
            "subcategory":"Printing & Photocopies",
            "type":"Services"
        }
    ],
    "sg:phone":"+39 081 825 4080",
    "sg:postcode":"83020",
    "sg:province":"Avellino",
    "wof:name":"Pubbliluca Sas Di Pandico Antonia E C.",
    "wof:placetype":"venue"
},
  "geometry": {"coordinates":[14.792722702,40.9147491455],"type":"Point"}
}