{
  "type": "Feature",
  "properties": {
    "iso:country":"IT",
    "sg:address":"00139 Roma",
    "sg:city":"Roma",
    "sg:orig_category":"Motori Ed Organi Di Trasmissione. Ricambi E Componenti Dei Mezzi Di Trasporto",
    "sg:phone":"+39 06 8864 0637",
    "sg:postcode":"00139",
    "sg:province":"Roma",
    "wof:name":"Iml Motori S.p.a.",
    "wof:placetype":"venue"
},
  "geometry": {"coordinates":[12.5218572617,41.9490089417],"type":"Point"}
}