{
  "type": "Feature",
  "properties": {
    "addr:full":"97, Via Locana 00166 Roma Roma Roma 00166",
    "addr:postcode":"00166;00166",
    "addr:street":"Via Locana",
    "iso:country":"IT",
    "sg:address":"97, Via Locana 00166 Roma",
    "sg:city":"Roma",
    "sg:classifiers":[
        {
            "category":"Food & Beverages",
            "subcategory":"Dairy",
            "type":"Retail Goods"
        }
    ],
    "sg:phone":"+39 06 6159 7283",
    "sg:postcode":"00166",
    "sg:province":"Roma",
    "sg:tags":[
        "product"
    ],
    "wof:name":"Formaggi Boccea Srl",
    "wof:placetype":"venue"
},
  "geometry": {"coordinates":[12.326264,41.945129],"type":"Point"}
}