{
  "type": "Feature",
  "properties": {
    "addr:full":"Via Dell' Avena Cs.1235 70022 Altamura Altamura Bari 70022",
    "addr:housenumber":"cs.1235",
    "addr:postcode":"70022;70022",
    "addr:street":"Via Dell ' Avena",
    "iso:country":"IT",
    "sg:address":"Via Dell' Avena Cs.1235 70022 Altamura",
    "sg:city":"Altamura",
    "sg:classifiers":[
        {
            "category":"Home & Garden",
            "subcategory":"Home Furnishings",
            "type":"Retail Goods"
        }
    ],
    "sg:phone":"+39 080 311 8825",
    "sg:postcode":"70022",
    "sg:province":"Bari",
    "sg:tags":[
        "household"
    ],
    "wof:name":"Natuzzi Spa",
    "wof:placetype":"venue"
},
  "geometry": {"coordinates":[16.869291,41.126053],"type":"Point"}
}