{
  "type": "Feature",
  "properties": {
    "addr:full":"Via Sodera 66030 Poggiofiorito Poggiofiorito Chieti 66030",
    "addr:postcode":"66030;66030",
    "addr:street":"Via Sodera",
    "iso:country":"IT",
    "sg:address":"Via Sodera 66030 Poggiofiorito",
    "sg:city":"Poggiofiorito",
    "sg:classifiers":[
        {
            "category":"Personal",
            "subcategory":"Shoe Repair & Shine",
            "type":"Services"
        }
    ],
    "sg:phone":"+39 0871 930234",
    "sg:postcode":"66030",
    "sg:province":"Chieti",
    "sg:tags":[
        "leather"
    ],
    "wof:name":"Calzaturificio Card S.r.l.",
    "wof:placetype":"venue"
},
  "geometry": {"coordinates":[14.167151,42.351791],"type":"Point"}
}