{
  "type": "Feature",
  "properties": {
    "addr:full":"70021 Acquaviva Delle Fonti Acquaviva delle Fonti Bari 70021",
    "addr:postcode":"70021;70021",
    "iso:country":"IT",
    "sg:address":"70021 Acquaviva Delle Fonti",
    "sg:city":"Acquaviva delle Fonti",
    "sg:classifiers":[
        {
            "category":"Home & Garden",
            "subcategory":"Building Materials",
            "type":"Retail Goods"
        }
    ],
    "sg:phone":"+39 080 762103",
    "sg:postcode":"70021",
    "sg:province":"Bari",
    "sg:tags":[
        "window",
        "door",
        "frame"
    ],
    "sg:website":"http://www.sidelsrl.com",
    "wof:name":"Si.del. Srl",
    "wof:placetype":"venue"
},
  "geometry": {"coordinates":[16.865452,40.894814],"type":"Point"}
}