{
  "type": "Feature",
  "properties": {
    "addr:full":"384, Strada Provinciale Rivoltana 20090 Rodano Rodano Milano 20090",
    "addr:postcode":"20090;20090",
    "addr:street":"Strada Provinciale Rivoltana",
    "iso:country":"IT",
    "sg:address":"384, Strada Provinciale Rivoltana 20090 Rodano",
    "sg:city":"Rodano",
    "sg:classifiers":[
        {
            "category":"Wholesale",
            "subcategory":"Drugs",
            "type":"Manufacturing & Wholesale Goods"
        }
    ],
    "sg:phone":"+39 390 295 231",
    "sg:postcode":"20090",
    "sg:province":"Milano",
    "sg:tags":[
        "chemical",
        "pharmaceutical"
    ],
    "wof:name":"Antibioticos S.p.a",
    "wof:placetype":"venue"
},
  "geometry": {"coordinates":[9.321723,45.47905],"type":"Point"}
}