{
  "type": "Feature",
  "properties": {
    "addr:full":"37015 Domegliara Domegliara Verona 37015",
    "addr:postcode":"37015;37015",
    "addr:street":"Domegliara",
    "iso:country":"IT",
    "sg:address":"37015 Domegliara",
    "sg:city":"Domegliara",
    "sg:orig_category":"Graniti",
    "sg:phone":"+39 045 686 1417",
    "sg:postcode":"37015",
    "sg:province":"Verona",
    "sg:website":"http://www.coltri.it",
    "wof:name":"Marmi S. Caterina Sas",
    "wof:placetype":"venue"
},
  "geometry": {"coordinates":[10.973013,45.443745],"type":"Point"}
}