{
  "type": "Feature",
  "properties": {
    "iso:country":"IT",
    "sg:address":"25015 Desenzano Del Garda",
    "sg:city":"Desenzano del Garda",
    "sg:orig_category":"Acquari Ornamentali Ed Accessori",
    "sg:phone":"+39 030 991 4209",
    "sg:postcode":"25015",
    "sg:province":"Brescia",
    "wof:name":"L'oasi Acquari Di Boni Raffaello",
    "wof:placetype":"venue"
},
  "geometry": {"coordinates":[10.219965,45.548374],"type":"Point"}
}