{
  "type": "Feature",
  "properties": {
    "addr:full":"4, Via Rubattino Raffaele 20134 Milano Milano Milano 20134",
    "addr:postcode":"20134;20134",
    "addr:street":"Via Rubattino Raffaele",
    "iso:country":"IT",
    "sg:address":"4, Via Rubattino Raffaele 20134 Milano",
    "sg:city":"Milano",
    "sg:classifiers":[
        {
            "category":"Shopping",
            "subcategory":"Crafts & Fabrics",
            "type":"Retail Goods"
        }
    ],
    "sg:phone":"+39 39022154628",
    "sg:postcode":"20134",
    "sg:province":"Milano",
    "sg:tags":[
        "ceramic"
    ],
    "wof:name":"Rosenthal Italia (s.r.l.)",
    "wof:placetype":"venue"
},
  "geometry": {"coordinates":[9.249043,45.476654],"type":"Point"}
}