{
  "type": "Feature",
  "properties": {
    "iso:country":"IT",
    "sg:address":"134, Via Nazionale 36056 Tezze Sul Brenta",
    "sg:city":"Tezze sul Brenta",
    "sg:classifiers":[
        {
            "category":"Parking",
            "subcategory":"Lot",
            "type":"Transportation"
        }
    ],
    "sg:phone":"+39 0424 861025",
    "sg:postcode":"36056",
    "sg:province":"Vicenza",
    "sg:tags":[
        "transport",
        "road"
    ],
    "wof:name":"Campagnolo Trasporti S.r.l.",
    "wof:placetype":"venue"
},
  "geometry": {"coordinates":[11.77204,45.688675],"type":"Point"}
}