{
  "type": "Feature",
  "properties": {
    "addr:full":"50126 Firenze Firenze Firenze 50126",
    "addr:postcode":"50126;50126",
    "iso:country":"IT",
    "sg:address":"50126 Firenze",
    "sg:city":"Firenze",
    "sg:orig_category":"Servizi Per Lo Sport E Il Tempo Libero. Servizi Al Turismo",
    "sg:phone":"+39 055 689618",
    "sg:postcode":"50126",
    "sg:province":"Firenze",
    "sg:website":"http://www.olympusclub.it",
    "wof:name":"Palestra Olympus Club",
    "wof:placetype":"venue"
},
  "geometry": {"coordinates":[11.247304,43.764294],"type":"Point"}
}