{
  "type": "Feature",
  "properties": {
    "iso:country":"IT",
    "sg:address":"Via Romagna 4 20098 Sesto Ulteriano",
    "sg:city":"Sesto Ulteriano",
    "sg:classifiers":[
        {
            "category":"Military Area",
            "subcategory":"Air Force Base",
            "type":"Public Place"
        }
    ],
    "sg:phone":"+39 02 988 0083",
    "sg:postcode":"20098",
    "sg:province":"Milano",
    "sg:tags":[
        "equipment",
        "galvanizing",
        "system",
        "electroplating"
    ],
    "sg:website":"www.progalvano.it",
    "wof:name":"Progalvano Srl",
    "wof:placetype":"venue"
},
  "geometry": {"coordinates":[9.252046,45.398651],"type":"Point"}
}