{
  "type": "Feature",
  "properties": {
    "iso:country":"IT",
    "sg:address":"9, V. E. Mattei 21036 Gemonio",
    "sg:city":"Gemonio",
    "sg:orig_category":"Miscellaneous Products",
    "sg:phone":"+39 0332 608011",
    "sg:postcode":"21036",
    "sg:province":"Varese",
    "sg:website":"http://www.sport-one.com:ws_end: :mark:ws:http://www.paginegialle.it/sportone",
    "wof:name":"Sport-one By Forma Srl",
    "wof:placetype":"venue"
},
  "geometry": {"coordinates":[8.8263845444,45.8176040649],"type":"Point"}
}