{
  "type": "Feature",
  "properties": {
    "iso:country":"IT",
    "sg:address":"28047 Oleggio",
    "sg:city":"Oleggio",
    "sg:orig_category":"Ricambi E Componenti Dei Mezzi Di Trasporto",
    "sg:phone":"+39 0321 922100",
    "sg:postcode":"28047",
    "sg:province":"Novara",
    "wof:name":"Melber S.p.a.",
    "wof:placetype":"venue"
},
  "geometry": {"coordinates":[8.643101,45.590927],"type":"Point"}
}