{
  "type": "Feature",
  "properties": {
    "iso:country":"IT",
    "sg:address":"7, Via Rossini Gioacchino 20010 Bareggio",
    "sg:city":"Bareggio",
    "sg:classifiers":[
        {
            "category":"Wholesale",
            "subcategory":"Machinery & Supplies",
            "type":"Manufacturing & Wholesale Goods"
        }
    ],
    "sg:phone":"+39 02 9036 1286",
    "sg:postcode":"20010",
    "sg:province":"Milano",
    "sg:tags":[
        "equipment",
        "-",
        "instrument",
        "measurement"
    ],
    "wof:name":"Pris Term Srl",
    "wof:placetype":"venue"
},
  "geometry": {"coordinates":[9.048318,45.526184],"type":"Point"}
}