{
  "type": "Feature",
  "properties": {
    "iso:country":"IT",
    "sg:address":"15048 Valenza",
    "sg:city":"Valenza",
    "sg:classifiers":[
        {
            "category":"Health Services",
            "subcategory":"Hospital",
            "type":"Services"
        }
    ],
    "sg:phone":"+39 0131 943114",
    "sg:postcode":"15048",
    "sg:province":"Alessandria",
    "sg:tags":[
        "equipment",
        "systems",
        "supply"
    ],
    "sg:website":"http://www.fraccarivalenza.it",
    "wof:name":"Fraccari Srl",
    "wof:placetype":"venue"
},
  "geometry": {"coordinates":[8.641449,45.019276],"type":"Point"}
}