{
  "type": "Feature",
  "properties": {
    "addr:full":"Via Vitrani Ang. Via Chieffi 64; Barletta; 70051 Barletta Bari 70051",
    "addr:housenumber":"64",
    "addr:postcode":"70051;70051",
    "addr:street":"Via Vitrani Ang. Via Chieffi",
    "iso:country":"IT",
    "sg:address":"Via Vitrani Ang. Via Chieffi 64; Barletta; 70051",
    "sg:city":"Barletta",
    "sg:classifiers":[
        {
            "category":"Banks & Credit Unions",
            "subcategory":"Bank",
            "type":"Services"
        }
    ],
    "sg:phone":"+39 0883 534102",
    "sg:postcode":"70051",
    "sg:province":"Bari",
    "wof:name":"Istituto Bancario, San Paolo Di Torino Spa",
    "wof:placetype":"venue"
},
  "geometry": {"coordinates":[16.287102,41.315632],"type":"Point"}
}