{
  "type": "Feature",
  "properties": {
    "addr:full":"26010 Vaiano Cremasco Vaiano Cremasco Cremona 26010",
    "addr:postcode":"26010;cremasco;26010",
    "iso:country":"IT",
    "sg:address":"26010 Vaiano Cremasco",
    "sg:city":"Vaiano Cremasco",
    "sg:orig_category":"Macchine Utensili E Impianti",
    "sg:postcode":"26010",
    "sg:province":"Cremona",
    "wof:name":"C.m.r. Di Ce' Ettore (s.n.c.)",
    "wof:placetype":"venue"
},
  "geometry": {"coordinates":[9.590398,45.373867],"type":"Point"}
}