{
  "type": "Feature",
  "properties": {
    "iso:country":"IT",
    "sg:address":"41057 Spilamberto",
    "sg:city":"Spilamberto",
    "sg:orig_category":"Automobili - Commercio",
    "sg:phone":"+39 059 783372",
    "sg:postcode":"41057",
    "sg:province":"Modena",
    "wof:name":"Padania Car Center Srl",
    "wof:placetype":"venue"
},
  "geometry": {"coordinates":[11.006822,44.548347],"type":"Point"}
}