{
  "type": "Feature",
  "properties": {
    "iso:country":"IT",
    "sg:address":"46020 Bondeno",
    "sg:orig_category":"Apparecchiature Ed Attrezzature Meccaniche",
    "sg:phone":"+39 0376 54144",
    "sg:postcode":"46020",
    "sg:province":"Mantova",
    "wof:name":"Meclube Srl",
    "wof:placetype":"venue"
},
  "geometry": {"coordinates":[10.797698,45.160366],"type":"Point"}
}