{
  "type": "Feature",
  "properties": {
    "iso:country":"IT",
    "sg:address":"70010 Sammichele Di Bari",
    "sg:city":"Sammichele di Bari",
    "sg:orig_category":"Prodotti Alimentari",
    "sg:phone":"+39 080 891 7662",
    "sg:postcode":"70010",
    "sg:province":"Bari",
    "wof:name":"Morgese Giuseppe",
    "wof:placetype":"venue"
},
  "geometry": {"coordinates":[16.9482803345,40.887512207],"type":"Point"}
}