{
  "type": "Feature",
  "properties": {
    "addr:full":"70013 Castellana Grotte Castellana Grotte Bari 70013",
    "addr:postcode":"70013;70013",
    "iso:country":"IT",
    "sg:address":"70013 Castellana Grotte",
    "sg:city":"Castellana Grotte",
    "sg:orig_category":"Servizi E Lavori Per Arredamento E Industria Del Legno. Arte Ed Artigianato Artistico",
    "sg:phone":"+39 080 496 8681",
    "sg:postcode":"70013",
    "sg:province":"Bari",
    "wof:name":"Palmitessa Paolo & C. Sas",
    "wof:placetype":"venue"
},
  "geometry": {"coordinates":[17.169088,40.884819],"type":"Point"}
}