{
  "type": "Feature",
  "properties": {
    "iso:country":"IT",
    "sg:address":"20144 Milano",
    "sg:city":"Milano",
    "sg:orig_category":"Studi E Consulenze Legali E Notarili. Avvocati, Notai E Servizi Legali. Professionisti - Studi E Servizi Ed Associazioni Di Interesse Aziendale",
    "sg:phone":"+39 02 498 9401",
    "sg:postcode":"20144",
    "sg:province":"Milano",
    "wof:name":"Maienza Dr Nicola",
    "wof:placetype":"venue"
},
  "geometry": {"coordinates":[9.158482,45.45998],"type":"Point"}
}