{
  "type": "Feature",
  "properties": {
    "iso:country":"IT",
    "sg:address":"61032 Fano",
    "sg:city":"Fano",
    "sg:orig_category":"Macchine, Impianti Ed Attrezzature Industria Chimica",
    "sg:phone":"+39 0721 856128",
    "sg:postcode":"61032",
    "sg:province":"Pesaro E Urbino",
    "wof:name":"Euroimpianti Srl",
    "wof:placetype":"venue"
},
  "geometry": {"coordinates":[13.003093,43.785992],"type":"Point"}
}