{
  "type": "Feature",
  "properties": {
    "addr:full":"12060 Farigliano Farigliano Cuneo 12060",
    "addr:housenumber":"12060",
    "addr:postcode":"12060",
    "addr:street":"Farigliano",
    "iso:country":"IT",
    "sg:address":"12060 Farigliano",
    "sg:city":"Farigliano",
    "sg:classifiers":[
        {
            "category":"Education",
            "subcategory":"Dance Studio",
            "type":"Public Place"
        }
    ],
    "sg:phone":"+39 0173 76748",
    "sg:postcode":"12060",
    "sg:province":"Cuneo",
    "sg:tags":[
        "pallet"
    ],
    "wof:name":"Taricco Pallets Srl",
    "wof:placetype":"venue"
},
  "geometry": {"coordinates":[7.9162192345,44.5112380981],"type":"Point"}
}