{
  "type": "Feature",
  "properties": {
    "iso:country":"IT",
    "sg:address":"81025 Marcianise",
    "sg:city":"Marcianise",
    "sg:orig_category":"Prodotti Chimici Secondari. Macchine E Forniture Per Ecologia E Smaltimento Rifiuti. Forniture Per Attivita' Industriali",
    "sg:phone":"+39 0823 821210",
    "sg:postcode":"81025",
    "sg:province":"Caserta",
    "sg:website":"http://www.rea.it",
    "wof:name":"Rea Srl Industria Chimica",
    "wof:placetype":"venue"
},
  "geometry": {"coordinates":[14.2977428436,41.0152359009],"type":"Point"}
}