{
  "type": "Feature",
  "properties": {
    "iso:country":"IT",
    "sg:address":"61030 Tavernelle",
    "sg:city":"Tavernelle",
    "sg:orig_category":"Prodotti Chimici Secondari",
    "sg:phone":"+39 0721 896121",
    "sg:postcode":"61030",
    "sg:province":"Pesaro E Urbino",
    "wof:name":"Gallo (s.r.l.)",
    "wof:placetype":"venue"
},
  "geometry": {"coordinates":[12.8608255386,43.7189445496],"type":"Point"}
}