{
  "type": "Feature",
  "properties": {
    "addr:full":"22060 Carimate Carimate Como 22060",
    "addr:postcode":"22060;22060",
    "iso:country":"IT",
    "sg:address":"22060 Carimate",
    "sg:city":"Carimate",
    "sg:orig_category":"Metalli E Leghe",
    "sg:phone":"+39 031 790893",
    "sg:postcode":"22060",
    "sg:province":"Como",
    "wof:name":"Pelligra Pietro",
    "wof:placetype":"venue"
},
  "geometry": {"coordinates":[9.1289634705,45.7145767212],"type":"Point"}
}