{
  "type": "Feature",
  "properties": {
    "iso:country":"IT",
    "sg:address":"21040 Venegono Inferiore",
    "sg:city":"Venegono Inferiore",
    "sg:orig_category":"Astucci",
    "sg:phone":"+39 0331 864048",
    "sg:postcode":"21040",
    "sg:province":"Varese",
    "wof:name":"Viplarte Snc",
    "wof:placetype":"venue"
},
  "geometry": {"coordinates":[8.890594,45.778862],"type":"Point"}
}