{
  "type": "Feature",
  "properties": {
    "iso:country":"IT",
    "sg:address":"84121 Salerno",
    "sg:city":"Salerno",
    "sg:orig_category":"Trasporti E Spedizioni Merci",
    "sg:phone":"+39 089 230338",
    "sg:postcode":"84121",
    "sg:province":"Salerno",
    "sg:website":"http://www.autori.it",
    "wof:name":"Michele Autori Srl",
    "wof:placetype":"venue"
},
  "geometry": {"coordinates":[14.752823,40.677593],"type":"Point"}
}