{
  "type": "Feature",
  "properties": {
    "addr:full":"26900 Lodi Lodi Lodi 26900",
    "addr:postcode":"26900;26900",
    "iso:country":"IT",
    "sg:address":"26900 Lodi",
    "sg:city":"Lodi",
    "sg:orig_category":"Forniture Per Agricoltura E Zootecnia. Animali Domestici",
    "sg:phone":"+39 0371 438156",
    "sg:postcode":"26900",
    "sg:province":"Lodi",
    "wof:name":"Medivet Srl",
    "wof:placetype":"venue"
},
  "geometry": {"coordinates":[9.5171451569,45.2974700928],"type":"Point"}
}