{
  "type": "Feature",
  "properties": {
    "iso:country":"IT",
    "sg:address":"4, Via San Marco 31031 Caerano Di San Marco",
    "sg:city":"Caerano di San Marco",
    "sg:classifiers":[
        {
            "category":"Shopping",
            "subcategory":"Clothing, Apparel, & Fashions",
            "type":"Retail Goods"
        }
    ],
    "sg:phone":"+39 390 423 6591",
    "sg:postcode":"31031",
    "sg:province":"Treviso",
    "sg:tags":[
        "clothes"
    ],
    "wof:name":"Sanremo Moda Uomo S.p.a.",
    "wof:placetype":"venue"
},
  "geometry": {"coordinates":[12.000619,45.783188],"type":"Point"}
}