{
  "type": "Feature",
  "properties": {
    "addr:full":"00148 Roma Roma Roma 00148",
    "addr:postcode":"00148;00148",
    "iso:country":"IT",
    "sg:address":"00148 Roma",
    "sg:city":"Roma",
    "sg:orig_category":"Animali Domestici - Allevamento E Addestramento",
    "sg:phone":"+39 06 655 3480",
    "sg:postcode":"00148",
    "sg:province":"Roma",
    "wof:name":"Centro Sanitario Cinofilo Srl",
    "wof:placetype":"venue"
},
  "geometry": {"coordinates":[12.418119,41.831593],"type":"Point"}
}