{
  "type": "Feature",
  "properties": {
    "iso:country":"IT",
    "sg:address":"Via Giovanni Xxiii 26-28; Silla; 40040",
    "sg:classifiers":[
        {
            "category":"Banks & Credit Unions",
            "subcategory":"Bank",
            "type":"Services"
        }
    ],
    "sg:phone":"+39 0534 30018",
    "wof:name":"Rolo Banca 1473 Spa",
    "wof:placetype":"venue"
},
  "geometry": {"coordinates":[10.979287,44.180779],"type":"Point"}
}