{
  "type": "Feature",
  "properties": {
    "addr:full":"22100 Como Como Como 22100",
    "addr:postcode":"22100;22100",
    "iso:country":"IT",
    "sg:address":"22100 Como",
    "sg:city":"Como",
    "sg:classifiers":[
        {
            "category":"Shopping",
            "type":"Retail Goods"
        }
    ],
    "sg:phone":"+39 031 260820",
    "sg:postcode":"22100",
    "sg:province":"Como",
    "sg:tags":[
        "letti"
    ],
    "wof:name":"Idea Divaneria",
    "wof:placetype":"venue"
},
  "geometry": {"coordinates":[9.090336,45.796215],"type":"Point"}
}