{
  "type": "Feature",
  "properties": {
    "iso:country":"IT",
    "sg:address":"38035 Moena",
    "sg:city":"Moena",
    "sg:orig_category":"Dolciumi E Gelati",
    "sg:phone":"+39 0462 573149",
    "sg:postcode":"38035",
    "sg:province":"Trento",
    "wof:name":"Hotel Faloria Di Farina Manuel & C. Sas",
    "wof:placetype":"venue"
},
  "geometry": {"coordinates":[11.660217,46.376587],"type":"Point"}
}