{
  "type": "Feature",
  "properties": {
    "iso:country":"IT",
    "sg:address":"24050 Spirano",
    "sg:city":"Spirano",
    "sg:orig_category":"Forniture Per Edilizia E Lavori Pubblici",
    "sg:phone":"+39 035 876 6464",
    "sg:postcode":"24050",
    "sg:province":"Bergamo",
    "wof:name":"Gm Plast Snc Di Azzolari & C.",
    "wof:placetype":"venue"
},
  "geometry": {"coordinates":[9.6622190475,45.5954971313],"type":"Point"}
}