{
  "type": "Feature",
  "properties": {
    "addr:full":"13, V. L. Manara 20058 Villasanta Villasanta Milano 20058",
    "addr:housenumber":"13",
    "addr:postcode":"20058;20058",
    "addr:street":"V. L. Manara",
    "iso:country":"IT",
    "sg:address":"13, V. L. Manara 20058 Villasanta",
    "sg:city":"Villasanta",
    "sg:classifiers":[
        {
            "category":"Autos & Motor Vehicles",
            "subcategory":"Boat Sales",
            "type":"Retail Goods"
        }
    ],
    "sg:phone":"+39 39039302181",
    "sg:postcode":"20058",
    "sg:province":"Milano",
    "sg:website":"http://www.scminox.it",
    "wof:name":"S.c.m. Srl",
    "wof:placetype":"venue"
},
  "geometry": {"coordinates":[9.312387,45.608932],"type":"Point"}
}