{
  "type": "Feature",
  "properties": {
    "iso:country":"IT",
    "sg:address":"30010 Cavallino - Treporti",
    "sg:orig_category":"Zootecnia E Pesca, Allevamento Piccoli Animali",
    "sg:phone":"+39 041 966270",
    "sg:postcode":"30010",
    "sg:province":"Venezia",
    "wof:name":"Valle Sacchetta & Sacchettina (s.a.s.)",
    "wof:placetype":"venue"
},
  "geometry": {"coordinates":[12.495258,45.475262],"type":"Point"}
}