{
  "type": "Feature",
  "properties": {
    "iso:country":"IT",
    "sg:address":"00165 Roma",
    "sg:city":"Roma",
    "sg:orig_category":"Agenzie D'affari E Servizi Commerciali",
    "sg:phone":"+39 06 6813 6185",
    "sg:postcode":"00165",
    "sg:province":"Roma",
    "wof:name":"Topcase Consulenze E Servizi Immobiliari Srl",
    "wof:placetype":"venue"
},
  "geometry": {"coordinates":[12.440924,41.895489],"type":"Point"}
}