{
  "type": "Feature",
  "properties": {
    "addr:full":"Via Fasano 1340 70010 Locorotondo Locorotondo Bari 70010",
    "addr:housenumber":"1340",
    "addr:postcode":"70010;70010",
    "addr:street":"Via Fasano",
    "iso:country":"IT",
    "sg:address":"Via Fasano 1340 70010 Locorotondo",
    "sg:city":"Locorotondo",
    "sg:classifiers":[
        {
            "category":"Home & Garden",
            "subcategory":"Home Furnishings",
            "type":"Retail Goods"
        }
    ],
    "sg:phone":"+39 080 431 1055",
    "sg:postcode":"70010",
    "sg:province":"Bari",
    "sg:tags":[
        "wallpaper"
    ],
    "wof:name":"Serigrafia Guarnieri Di Guarnieri Salvatore",
    "wof:placetype":"venue"
},
  "geometry": {"coordinates":[17.329245,40.760571],"type":"Point"}
}