{
  "type": "Feature",
  "properties": {
    "addr:full":"20121 Milano Milano Milano 20121",
    "addr:postcode":"20121;20121",
    "iso:country":"IT",
    "sg:address":"20121 Milano",
    "sg:city":"Milano",
    "sg:orig_category":"Zootecnia E Pesca, Allevamento Piccoli Animali. Servizi Per Lo Sport E Il Tempo Libero",
    "sg:phone":"+39 02 8699 5434",
    "sg:postcode":"20121",
    "sg:province":"Milano",
    "wof:name":"Gianni - Daniele S.r.l",
    "wof:placetype":"venue"
},
  "geometry": {"coordinates":[9.183307,45.469765],"type":"Point"}
}