{
  "type": "Feature",
  "properties": {
    "iso:country":"IT",
    "sg:address":"3/4, Via J.barozzi 40050 Monteveglio",
    "sg:city":"Monteveglio",
    "sg:classifiers":[
        {
            "category":"Professional",
            "subcategory":"Engineering",
            "type":"Services"
        }
    ],
    "sg:phone":"+39 39051960302",
    "sg:postcode":"40050",
    "sg:province":"Bologna",
    "sg:tags":[
        "machine",
        "-",
        "mechanical"
    ],
    "wof:name":"Pras-matic (s.r.l.)",
    "wof:placetype":"venue"
},
  "geometry": {"coordinates":[11.346481,44.494221],"type":"Point"}
}