{
  "type": "Feature",
  "properties": {
    "addr:full":"60019 Senigallia Senigallia Ancona 60019",
    "addr:postcode":"60019;60019",
    "iso:country":"IT",
    "sg:address":"60019 Senigallia",
    "sg:city":"Senigallia",
    "sg:orig_category":"Impiantistica E Prodotti Tecnologici Per Edilizia. Elettrotecnica Industriale, Prodotti E Apparecchiature",
    "sg:phone":"+39 071 660 9092",
    "sg:postcode":"60019",
    "sg:province":"Ancona",
    "wof:name":"Savini Fabio Savini Luca & C. Snc",
    "wof:placetype":"venue"
},
  "geometry": {"coordinates":[13.197106,43.68961],"type":"Point"}
}