{
  "type": "Feature",
  "properties": {
    "addr:full":"20121 Milano Milano Milano 20121",
    "addr:postcode":"20121;20121",
    "iso:country":"IT",
    "sg:address":"20121 Milano",
    "sg:city":"Milano",
    "sg:orig_category":"Palestre",
    "sg:phone":"+39 02 655 4758",
    "sg:postcode":"20121",
    "sg:province":"Milano",
    "wof:name":"Brera Sport Club",
    "wof:placetype":"venue"
},
  "geometry": {"coordinates":[9.1844892502,45.4789047241],"type":"Point"}
}