{
  "type": "Feature",
  "properties": {
    "addr:full":"24040 Calvenzano Calvenzano Bergamo 24040",
    "addr:postcode":"24040;24040",
    "iso:country":"IT",
    "sg:address":"24040 Calvenzano",
    "sg:city":"Calvenzano",
    "sg:orig_category":"Raccorderie E Valvole Per Industrie Varie",
    "sg:phone":"+39 036 386249",
    "sg:postcode":"24040",
    "sg:province":"Bergamo",
    "wof:name":"Raccordtubi Srl",
    "wof:placetype":"venue"
},
  "geometry": {"coordinates":[9.604839,45.489372],"type":"Point"}
}