{
  "type": "Feature",
  "properties": {
    "iso:country":"IT",
    "sg:address":"10156 Torino",
    "sg:city":"Torino",
    "sg:orig_category":"Imballaggi - Produzione E Commercio",
    "sg:phone":"+39 011 274 2020",
    "sg:postcode":"10156",
    "sg:province":"Torino",
    "wof:name":"Movinpack Snc",
    "wof:placetype":"venue"
},
  "geometry": {"coordinates":[7.70615,45.119347],"type":"Point"}
}