{
  "type": "Feature",
  "properties": {
    "iso:country":"IT",
    "sg:address":"33/35, Via Giovanni Xxiii 56025 Pontedera",
    "sg:city":"Pontedera",
    "sg:classifiers":[
        {
            "category":"Parking",
            "subcategory":"Lot",
            "type":"Transportation"
        }
    ],
    "sg:phone":"+39 0587 484183",
    "sg:postcode":"56025",
    "sg:province":"Pisa",
    "sg:tags":[
        "transport",
        "road"
    ],
    "wof:name":"Parentini Autotrasporti Srl",
    "wof:placetype":"venue"
},
  "geometry": {"coordinates":[10.659641,43.668762],"type":"Point"}
}