{
  "type": "Feature",
  "properties": {
    "iso:country":"IT",
    "sg:address":"6, Viale Europa 93014 Mussomeli",
    "sg:city":"Mussomeli",
    "sg:classifiers":[
        {
            "category":"Building & Trades",
            "subcategory":"Construction",
            "type":"Services"
        }
    ],
    "sg:phone":"+39 0934 993918",
    "sg:postcode":"93014",
    "sg:province":"Caltanissetta",
    "sg:tags":[
        "work",
        "public"
    ],
    "wof:name":"Mingoia & C. Impresa Costruzioni S.r.l.",
    "wof:placetype":"venue"
},
  "geometry": {"coordinates":[13.750776,37.585152],"type":"Point"}
}