{
  "type": "Feature",
  "properties": {
    "addr:full":"25040 Saviore Dell'adamello Brescia 25040",
    "addr:postcode":"25040;25040",
    "iso:country":"IT",
    "sg:address":"25040 Saviore Dell'adamello",
    "sg:orig_category":"Servizi Per Lo Sport E Il Tempo Libero. Servizi Al Turismo. Acqua, Luce, Gas E Societa' Di Esercizio Pubblico",
    "sg:phone":"+39 036 463 4145",
    "sg:postcode":"25040",
    "sg:province":"Brescia",
    "wof:name":"Parco Dell'adamello",
    "wof:placetype":"venue"
},
  "geometry": {"coordinates":[10.39843,46.080654],"type":"Point"}
}