{
  "type": "Feature",
  "properties": {
    "iso:country":"IT",
    "sg:address":"28, Via Stretta 25128 Brescia",
    "sg:city":"Brescia",
    "sg:classifiers":[
        {
            "category":"Professional",
            "subcategory":"Computer Services",
            "type":"Services"
        }
    ],
    "sg:phone":"+39 030 370 2291",
    "sg:postcode":"25128",
    "sg:province":"Brescia",
    "sg:tags":[
        "information",
        "technology"
    ],
    "wof:name":"Ocs S.p.a.",
    "wof:placetype":"venue"
},
  "geometry": {"coordinates":[10.220815,45.561813],"type":"Point"}
}