{
  "type": "Feature",
  "properties": {
    "iso:country":"IT",
    "sg:address":"21057 Olgiate Olona",
    "sg:city":"Olgiate Olona",
    "sg:orig_category":"Macchine, Impianti Ed Attrezzature Per Abbigliamento E Pelletterie",
    "sg:phone":"+39 0331 649668",
    "sg:postcode":"21057",
    "sg:province":"Varese",
    "wof:name":"Meccano Tessile Bustese Snc",
    "wof:placetype":"venue"
},
  "geometry": {"coordinates":[8.881413,45.629898],"type":"Point"}
}