{
  "type": "Feature",
  "properties": {
    "iso:country":"IT",
    "sg:address":"00186 Roma",
    "sg:city":"Roma",
    "sg:orig_category":"Carni, Salumi E Pesci",
    "sg:phone":"+39 06 361 2269",
    "sg:postcode":"00186",
    "sg:province":"Roma",
    "sg:website":"http://www.annibale.com",
    "wof:name":"Annibale",
    "wof:placetype":"venue"
},
  "geometry": {"coordinates":[12.476037,41.908779],"type":"Point"}
}