{
  "type": "Feature",
  "properties": {
    "addr:full":"80011 Acerra Acerra Napoli 80011",
    "addr:postcode":"80011;80011",
    "iso:country":"IT",
    "sg:address":"80011 Acerra",
    "sg:city":"Acerra",
    "sg:orig_category":"Prodotti Di Base E Forniture Per Industria Alimentare E Bevande",
    "sg:phone":"+39 081 520 7156",
    "sg:postcode":"80011",
    "sg:province":"Napoli",
    "wof:name":"Andretta F.lli S.n.c.",
    "wof:placetype":"venue"
},
  "geometry": {"coordinates":[14.3730669022,40.9539031982],"type":"Point"}
}