{
  "type": "Feature",
  "properties": {
    "addr:full":"Regione Pioppeto 12035 Racconigi Racconigi Cuneo 12035",
    "addr:postcode":"12035;12035",
    "addr:street":"Regione Pioppeto",
    "iso:country":"IT",
    "sg:address":"Regione Pioppeto 12035 Racconigi",
    "sg:city":"Racconigi",
    "sg:classifiers":[
        {
            "category":"Manufacturing",
            "subcategory":"Metals",
            "type":"Manufacturing & Wholesale Goods"
        }
    ],
    "sg:phone":"+39 390 172 8021",
    "sg:postcode":"12035",
    "sg:province":"Cuneo",
    "sg:tags":[
        "processing"
    ],
    "wof:name":"Ilva Spa",
    "wof:placetype":"venue"
},
  "geometry": {"coordinates":[7.5471105576,44.38879776],"type":"Point"}
}