{
  "type": "Feature",
  "properties": {
    "iso:country":"IT",
    "sg:address":"11017 Morgex",
    "sg:city":"Morgex",
    "sg:orig_category":"Termotecnica E Riscaldamento, Apparecchiature E Servizi",
    "sg:phone":"+39 0165 809405",
    "sg:postcode":"11017",
    "sg:province":"Aosta",
    "wof:name":"Ditta Papagni Nicola",
    "wof:placetype":"venue"
},
  "geometry": {"coordinates":[7.031984,45.757153],"type":"Point"}
}