{
  "type": "Feature",
  "properties": {
    "addr:full":"20020 Arese Arese Milano 20020",
    "addr:postcode":"20020;20020",
    "iso:country":"IT",
    "sg:address":"20020 Arese",
    "sg:city":"Arese",
    "sg:orig_category":"Agenti D'affari In Mediazione",
    "sg:phone":"+39 02 9358 1477",
    "sg:postcode":"20020",
    "sg:province":"Milano",
    "wof:name":"Buroservice Snc",
    "wof:placetype":"venue"
},
  "geometry": {"coordinates":[9.07469,45.553246],"type":"Point"}
}