{
  "type": "Feature",
  "properties": {
    "iso:country":"IT",
    "sg:address":"40132 Bologna",
    "sg:city":"Bologna",
    "sg:orig_category":"Elettrotecnica Industriale, Prodotti E Apparecchiature",
    "sg:phone":"+39 051 641 6231",
    "sg:postcode":"40132",
    "sg:province":"Bologna",
    "wof:name":"Gi.fa. Trasmissioni Sas",
    "wof:placetype":"venue"
},
  "geometry": {"coordinates":[11.282862,44.515312],"type":"Point"}
}