{
  "type": "Feature",
  "properties": {
    "addr:full":"95041 Caltagirone Caltagirone Catania 95041",
    "addr:postcode":"95041;95041",
    "iso:country":"IT",
    "sg:address":"95041 Caltagirone",
    "sg:city":"Caltagirone",
    "sg:orig_category":"Prodotti Cosmetici E Da Toeletta",
    "sg:phone":"+39 0933 21547",
    "sg:postcode":"95041",
    "sg:province":"Catania",
    "wof:name":"Galvano Salvatore",
    "wof:placetype":"venue"
},
  "geometry": {"coordinates":[14.5189218521,37.2060775757],"type":"Point"}
}