{
  "type": "Feature",
  "properties": {
    "iso:country":"IT",
    "sg:address":"35010 Vigonza",
    "sg:city":"Vigonza",
    "sg:classifiers":[
        {
            "category":"Manufacturing",
            "subcategory":"Tools & Machinery",
            "type":"Manufacturing & Wholesale Goods"
        }
    ],
    "sg:phone":"+39 049 893 0867",
    "sg:postcode":"35010",
    "sg:province":"Padova",
    "sg:tags":[
        "machining",
        "mechanical"
    ],
    "wof:name":"Officina Meccanica Varotto Amedeo Snc",
    "wof:placetype":"venue"
},
  "geometry": {"coordinates":[11.933917,45.400372],"type":"Point"}
}