{
  "type": "Feature",
  "properties": {
    "iso:country":"IT",
    "sg:address":"Loc. Torre Del Parco 14 62022 Castelraimondo",
    "sg:city":"Castelraimondo",
    "sg:classifiers":[
        {
            "category":"Manufacturing",
            "subcategory":"Wood Products",
            "type":"Manufacturing & Wholesale Goods"
        }
    ],
    "sg:phone":"+39 0737 640069",
    "sg:postcode":"62022",
    "sg:province":"Macerata",
    "sg:tags":[
        "genuine",
        "panel"
    ],
    "wof:name":"Iclen Dei Fratelli Cucculelli Snc",
    "wof:placetype":"venue"
},
  "geometry": {"coordinates":[13.456262,43.300747],"type":"Point"}
}