{
  "type": "Feature",
  "properties": {
    "addr:full":"142, Via Stabile Mariano 90139 Palermo Palermo Palermo 90139",
    "addr:housenumber":"142",
    "addr:postcode":"90139;90139",
    "addr:street":"Via Stabile Mariano",
    "iso:country":"IT",
    "sg:address":"142, Via Stabile Mariano 90139 Palermo",
    "sg:city":"Palermo",
    "sg:classifiers":[
        {
            "category":"Manufacturing",
            "subcategory":"Printing",
            "type":"Manufacturing & Wholesale Goods"
        }
    ],
    "sg:phone":"+39 39091324901",
    "sg:postcode":"90139",
    "sg:province":"Palermo",
    "sg:tags":[
        "publishing"
    ],
    "wof:name":"Giornale Il Foglio",
    "wof:placetype":"venue"
},
  "geometry": {"coordinates":[13.3541097641,38.1215553284],"type":"Point"}
}