{
  "type": "Feature",
  "properties": {
    "iso:country":"IT",
    "sg:address":"00148 Roma",
    "sg:city":"Roma",
    "sg:orig_category":"Shopping. Prodotti Cosmetici E Da Toeletta",
    "sg:phone":"+39 06 661680",
    "sg:postcode":"00148",
    "sg:province":"Roma",
    "wof:name":"G.l.e.a.p.",
    "wof:placetype":"venue"
},
  "geometry": {"coordinates":[12.421778,41.863724],"type":"Point"}
}