{
  "type": "Feature",
  "properties": {
    "iso:country":"IT",
    "sg:address":"9, Via Giovanni Xxiii 62100 Macerata",
    "sg:city":"Macerata",
    "sg:classifiers":[
        {
            "category":"Shopping",
            "subcategory":"Computers & Home Electronics",
            "type":"Retail Goods"
        }
    ],
    "sg:phone":"+39 0733 202293",
    "sg:postcode":"62100",
    "sg:province":"Macerata",
    "sg:tags":[
        "electronic",
        "electrical",
        "equipment"
    ],
    "wof:name":"Elettromeccanica Faggiolati S.r.l.",
    "wof:placetype":"venue"
},
  "geometry": {"coordinates":[13.42896,43.260017],"type":"Point"}
}