{
  "type": "Feature",
  "properties": {
    "iso:country":"IT",
    "sg:address":"65121 Pescara",
    "sg:city":"Pescara",
    "sg:orig_category":"Prodotti Di Base E Forniture Per Industria Alimentare E Bevande. Forniture Per Attivita' Commerciali Ed Artigianali",
    "sg:phone":"+39 085 205 8320",
    "sg:postcode":"65121",
    "sg:province":"Pescara",
    "wof:name":"P & D S.r.l.",
    "wof:placetype":"venue"
},
  "geometry": {"coordinates":[14.2432804108,42.4442024231],"type":"Point"}
}