{
  "type": "Feature",
  "properties": {
    "iso:country":"IT",
    "sg:address":"41042 Fiorano Modenese",
    "sg:city":"Fiorano Modenese",
    "sg:classifiers":[
        {
            "category":"Retail",
            "subcategory":"Car Wash",
            "type":"Services"
        }
    ],
    "sg:phone":"+39 0536 920450",
    "sg:postcode":"41042",
    "sg:province":"Modena",
    "sg:tags":[
        "activities",
        "industrial",
        "instrument",
        "machines",
        "equipment"
    ],
    "wof:name":"Zama Sensor Srl",
    "wof:placetype":"venue"
},
  "geometry": {"coordinates":[10.83915,44.538376],"type":"Point"}
}