{
  "type": "Feature",
  "properties": {
    "addr:full":"20090 Opera Opera Milano 20090",
    "addr:postcode":"20090;20090",
    "iso:country":"IT",
    "sg:address":"20090 Opera",
    "sg:city":"Opera",
    "sg:orig_category":"Acciaierie E Fonderie",
    "sg:phone":"+39 02 5760 0189",
    "sg:postcode":"20090",
    "sg:province":"Milano",
    "wof:name":"Fondindustria (s.r.l.)",
    "wof:placetype":"venue"
},
  "geometry": {"coordinates":[9.208113,45.369926],"type":"Point"}
}