{
  "type": "Feature",
  "properties": {
    "iso:country":"IT",
    "sg:address":"57023 Cecina",
    "sg:city":"Cecina",
    "sg:orig_category":"Servizi Per Lo Sport E Il Tempo Libero. Servizi Ausiliari Dei Mezzi Di Trasporto",
    "sg:phone":"+39 0586 620276",
    "sg:postcode":"57023",
    "sg:province":"Livorno",
    "wof:name":"Agenzia Nautica Stella Polare",
    "wof:placetype":"venue"
},
  "geometry": {"coordinates":[10.497967,43.298958],"type":"Point"}
}