{
  "type": "Feature",
  "properties": {
    "iso:country":"IT",
    "sg:address":"Via Berlinguer 1 29020 Gossolengo",
    "sg:city":"Gossolengo",
    "sg:orig_category":"Screw Spindle Pumps",
    "sg:phone":"+39 0523 557623",
    "sg:postcode":"29020",
    "sg:province":"Piacenza",
    "sg:website":"www.settima.it",
    "wof:name":"Settima Meccanica",
    "wof:placetype":"venue"
},
  "geometry": {"coordinates":[9.653687,44.972042],"type":"Point"}
}