{
  "type": "Feature",
  "properties": {
    "iso:country":"IT",
    "sg:address":"Via Bixio 40 Caldebosco Di Sopra 42010 Villarotta",
    "sg:classifiers":[
        {
            "category":"Professional",
            "type":"Services"
        }
    ],
    "sg:phone":"+39 0522 912170",
    "sg:postcode":"42010",
    "sg:province":"Reggio Nell'Emilia",
    "sg:tags":[
        "transport"
    ],
    "sg:website":"www.accorsitrasporti.it",
    "wof:name":"Accorsi Srl",
    "wof:placetype":"venue"
},
  "geometry": {"coordinates":[10.627794,44.696228],"type":"Point"}
}