{
  "type": "Feature",
  "properties": {
    "iso:country":"IT",
    "sg:address":"20052 Monza",
    "sg:city":"Monza",
    "sg:orig_category":"Utensili Meccanici E Materiali",
    "sg:phone":"+39 039 83981",
    "sg:postcode":"20052",
    "sg:province":"Milano",
    "sg:website":"http://www.grupposapio.it",
    "wof:name":"Sapio Produzione Idrogeno Ossigeno Srl",
    "wof:placetype":"venue"
},
  "geometry": {"coordinates":[9.231942,45.546379],"type":"Point"}
}