{
  "type": "Feature",
  "properties": {
    "addr:full":"04020 Santi Cosma E Damiano Santi Cosma e Damiano Latina 04020",
    "addr:postcode":"04020;04020",
    "addr:street":"E;E",
    "iso:country":"IT",
    "sg:address":"04020 Santi Cosma E Damiano",
    "sg:city":"Santi Cosma e Damiano",
    "sg:orig_category":"Metalli E Leghe",
    "sg:phone":"+39 0771 608135",
    "sg:postcode":"04020",
    "sg:province":"Latina",
    "wof:name":"Gambardella Lucio Valerio",
    "wof:placetype":"venue"
},
  "geometry": {"coordinates":[13.8147525787,41.2976875305],"type":"Point"}
}