{
  "type": "Feature",
  "properties": {
    "iso:country":"IT",
    "sg:address":"88046 Lamezia Terme",
    "sg:city":"Lamezia Terme",
    "sg:orig_category":"Autodemolizioni",
    "sg:phone":"+39 0968 411350",
    "sg:postcode":"88046",
    "sg:province":"Catanzaro",
    "sg:website":"http://www.rasauto.com",
    "wof:name":"Rasauto Di Raso Valentino & C. Snc",
    "wof:placetype":"venue"
},
  "geometry": {"coordinates":[16.275751,38.93362],"type":"Point"}
}