{
  "type": "Feature",
  "properties": {
    "iso:country":"IT",
    "sg:address":"Via Osella 7/9 10040 Leini'",
    "sg:classifiers":[
        {
            "category":"Utilities",
            "subcategory":"Cable",
            "type":"Services"
        }
    ],
    "sg:phone":"+39 011 998 6811",
    "sg:postcode":"10040",
    "sg:province":"Torino",
    "sg:tags":[
        "installation",
        "optical",
        "waveguide"
    ],
    "sg:website":"www.htcsrl.com",
    "wof:name":"H.t.c. Srl",
    "wof:placetype":"venue"
},
  "geometry": {"coordinates":[7.728677,45.188461],"type":"Point"}
}