{
  "type": "Feature",
  "properties": {
    "iso:country":"IT",
    "sg:address":"1, Regione Bracalla 12020 Rossana",
    "sg:city":"Rossana",
    "sg:classifiers":[
        {
            "category":"Manufacturing",
            "subcategory":"Metals",
            "type":"Manufacturing & Wholesale Goods"
        }
    ],
    "sg:phone":"+39 39017564409",
    "sg:postcode":"12020",
    "sg:province":"Cuneo",
    "sg:tags":[
        "metallurgy",
        "metalworking"
    ],
    "wof:name":"Ceros (s.p.a.)",
    "wof:placetype":"venue"
},
  "geometry": {"coordinates":[7.5471105576,44.38879776],"type":"Point"}
}