{
  "type": "Feature",
  "properties": {
    "iso:country":"IT",
    "sg:address":"95019 Zafferana Etnea",
    "sg:city":"Zafferana Etnea",
    "sg:orig_category":"Dolciumi E Gelati",
    "sg:postcode":"95019",
    "sg:province":"Catania",
    "wof:name":"Cooperativa Apicultori Etnea",
    "wof:placetype":"venue"
},
  "geometry": {"coordinates":[15.109947,37.687866],"type":"Point"}
}