{
  "type": "Feature",
  "properties": {
    "iso:country":"IT",
    "sg:address":"09047 Selargius",
    "sg:city":"Selargius",
    "sg:orig_category":"Autoscuole",
    "sg:phone":"+39 070 850778",
    "sg:postcode":"09047",
    "sg:province":"Cagliari",
    "wof:name":"Ca.me. Di Melis & C. Sas",
    "wof:placetype":"venue"
},
  "geometry": {"coordinates":[9.165498,39.255684],"type":"Point"}
}