{
  "type": "Feature",
  "properties": {
    "iso:country":"IT",
    "sg:address":"95047 Patern\u00f2",
    "sg:orig_category":"Servizi E Lavori Per Agricoltura E Zootecnia. Imprese Di Costruzioni Civili Ed Industriali",
    "sg:phone":"+39 095 842900",
    "sg:postcode":"95047",
    "sg:province":"Catania",
    "wof:name":"Societ\u00c0 Europea Perforazioni Srl",
    "wof:placetype":"venue"
},
  "geometry": {"coordinates":[14.428165,37.278538],"type":"Point"}
}