{
  "type": "Feature",
  "properties": {
    "addr:full":"02100 Rieti Rieti Rieti 02100",
    "addr:postcode":"02100;02100",
    "iso:country":"IT",
    "sg:address":"02100 Rieti",
    "sg:city":"Rieti",
    "sg:orig_category":"Prodotti Alimentari",
    "sg:phone":"+39 0746 220926",
    "sg:postcode":"02100",
    "sg:province":"Rieti",
    "wof:name":"San Carlo Gruppo Alimentare Spa",
    "wof:placetype":"venue"
},
  "geometry": {"coordinates":[12.9352712631,42.3484268188],"type":"Point"}
}