{
  "type": "Feature",
  "properties": {
    "addr:full":"Via Privata S. Rosa 26816 Ossago Lodigiano Ossago Lodigiano Lodi 26816",
    "addr:housenumber":"lodigiano",
    "addr:postcode":"26816;26816",
    "addr:street":"Via Privata S. Rosa;Lodigiano",
    "iso:country":"IT",
    "sg:address":"Via Privata S. Rosa 26816 Ossago Lodigiano",
    "sg:city":"Ossago Lodigiano",
    "sg:classifiers":[
        {
            "category":"Food & Beverages",
            "subcategory":"Dairy",
            "type":"Retail Goods"
        }
    ],
    "sg:phone":"+39 39037187781",
    "sg:postcode":"26816",
    "sg:province":"Lodi",
    "sg:tags":[
        "product"
    ],
    "wof:name":"Stella Bianca S.p.a.",
    "wof:placetype":"venue"
},
  "geometry": {"coordinates":[9.49785,45.312878],"type":"Point"}
}