{
  "type": "Feature",
  "properties": {
    "iso:country":"IT",
    "sg:address":"Via Laghetto N 34 20050 Macherio",
    "sg:city":"Macherio",
    "sg:orig_category":"Cast Steel Chains",
    "sg:phone":"+39 039 201 2730",
    "sg:postcode":"20050",
    "sg:province":"Milano",
    "sg:website":"www.fossatichains.it",
    "wof:name":"Fratelli Fossati Fabbrica Catenea Rullo Spa",
    "wof:placetype":"venue"
},
  "geometry": {"coordinates":[9.269595,45.643322],"type":"Point"}
}