{
  "type": "Feature",
  "properties": {
    "iso:country":"IT",
    "sg:address":"20081 Abbiategrasso",
    "sg:city":"Abbiategrasso",
    "sg:orig_category":"Servizi Culturali E Per Lo Spettacolo",
    "sg:phone":"+39 02 946 2616",
    "sg:postcode":"20081",
    "sg:province":"Milano",
    "wof:name":"Cinema Al Corso",
    "wof:placetype":"venue"
},
  "geometry": {"coordinates":[8.976087,45.402832],"type":"Point"}
}