{
  "type": "Feature",
  "properties": {
    "addr:full":"Via Pr\u00e8 85 36061 Bassano Del Grappa Bassano del Grappa Vicenza 36061",
    "addr:housenumber":"85",
    "addr:postcode":"36061;36061",
    "addr:street":"Via Pre\u0300",
    "iso:country":"IT",
    "sg:address":"Via Pr\u00e8 85 36061 Bassano Del Grappa",
    "sg:city":"Bassano del Grappa",
    "sg:classifiers":[
        {
            "category":"Manufacturing",
            "subcategory":"Rubber & Plastics",
            "type":"Manufacturing & Wholesale Goods"
        }
    ],
    "sg:phone":"+39 0424 566003",
    "sg:postcode":"36061",
    "sg:province":"Vicenza",
    "sg:tags":[
        "part",
        "pressed"
    ],
    "wof:name":"Sintesi Snc",
    "wof:placetype":"venue"
},
  "geometry": {"coordinates":[11.540307045,45.5459060669],"type":"Point"}
}