{
  "type": "Feature",
  "properties": {
    "iso:country":"IT",
    "sg:address":"36071 Arzignano",
    "sg:city":"Arzignano",
    "sg:orig_category":"Carrelli Elevatori E Trasportatori - Commercio E Noleggio",
    "sg:phone":"+39 0444 673599",
    "sg:postcode":"36071",
    "sg:province":"Vicenza",
    "sg:website":"http://www.bericar.it",
    "wof:name":"Bericar Srl",
    "wof:placetype":"venue"
},
  "geometry": {"coordinates":[11.346683,45.517197],"type":"Point"}
}