{
  "type": "Feature",
  "properties": {
    "addr:full":"16159 Genova Genova Genova 16159",
    "addr:postcode":"16159;16159",
    "iso:country":"IT",
    "sg:address":"16159 Genova",
    "sg:city":"Genova",
    "sg:orig_category":"Prodotti Di Base E Forniture Per Industria Alimentare E Bevande. Macchine, Impianti Ed Attrezzature Per Industria Alimentare E Bevande. Frigotecnica, Apparecchiature E Servizi. Macchine E Impianti Per",
    "sg:phone":"+39 010 419855",
    "sg:postcode":"16159",
    "sg:province":"Genova",
    "wof:name":"Bella Antonello",
    "wof:placetype":"venue"
},
  "geometry": {"coordinates":[8.8900556564,44.4269256592],"type":"Point"}
}