{
  "type": "Feature",
  "properties": {
    "addr:full":"20141 Milano Milano Milano 20141",
    "addr:postcode":"20141;20141",
    "iso:country":"IT",
    "sg:address":"20141 Milano",
    "sg:city":"Milano",
    "sg:orig_category":"Non-classified Establishments",
    "sg:phone":"+39 02 8951 1066",
    "sg:postcode":"20141",
    "sg:province":"Milano",
    "wof:name":"Gennari Paolo",
    "wof:placetype":"venue"
},
  "geometry": {"coordinates":[9.197552,45.43684],"type":"Point"}
}