{
  "type": "Feature",
  "properties": {
    "iso:country":"IT",
    "sg:address":"Via Roma 151 31020 Lancenigo",
    "sg:city":"Lancenigo",
    "sg:classifiers":[
        {
            "category":"Train Station",
            "subcategory":"Light Rail",
            "type":"Transportation"
        }
    ],
    "sg:phone":"+39 0422 6155",
    "sg:postcode":"31020",
    "sg:province":"Treviso",
    "sg:tags":[
        "lighting"
    ],
    "sg:website":"www.lelux.it",
    "wof:name":"Le Lux Spa",
    "wof:placetype":"venue"
},
  "geometry": {"coordinates":[12.255618,45.719898],"type":"Point"}
}