{
  "type": "Feature",
  "properties": {
    "iso:country":"IT",
    "sg:address":"22070 Solbiate",
    "sg:city":"Solbiate",
    "sg:orig_category":"Servizi E Lavori Per Abbigliamento E Pelletterie",
    "sg:phone":"+39 031 800593",
    "sg:postcode":"22070",
    "sg:province":"Como",
    "wof:name":"Taiana Maria",
    "wof:placetype":"venue"
},
  "geometry": {"coordinates":[8.987272,45.801643],"type":"Point"}
}