{
  "type": "Feature",
  "properties": {
    "addr:full":"35018 San Martino Di Lupari San Martino di Lupari Padova 35018",
    "addr:housenumber":"35018",
    "addr:postcode":"di lupari;35018",
    "iso:country":"IT",
    "sg:address":"35018 San Martino Di Lupari",
    "sg:city":"San Martino di Lupari",
    "sg:orig_category":"Ceramiche: Prodotti E Lavorazioni",
    "sg:phone":"+39 049 946 1899",
    "sg:postcode":"35018",
    "sg:province":"Padova",
    "wof:name":"Emmegi Snc Di Marostica Luciano & C.",
    "wof:placetype":"venue"
},
  "geometry": {"coordinates":[11.851705,45.65387],"type":"Point"}
}