{
  "type": "Feature",
  "properties": {
    "iso:country":"IT",
    "sg:address":"41100 Modena",
    "sg:city":"Modena",
    "sg:orig_category":"Arredamenti E Mobili Professionali",
    "sg:phone":"+39 059 345833",
    "sg:postcode":"41100",
    "sg:province":"Modena",
    "wof:name":"Mood Srl",
    "wof:placetype":"venue"
},
  "geometry": {"coordinates":[10.910335,44.638176],"type":"Point"}
}