{
  "type": "Feature",
  "properties": {
    "iso:country":"IT",
    "sg:address":"Contrada Gisira 96011 Augusta",
    "sg:city":"Augusta",
    "sg:classifiers":[
        {
            "category":"Travel",
            "subcategory":"Travel Agent",
            "type":"Entertainment"
        }
    ],
    "sg:phone":"+39 0931 994401",
    "sg:postcode":"96011",
    "sg:province":"Siracusa",
    "sg:tags":[
        "business"
    ],
    "wof:name":"Brucoli Village",
    "wof:placetype":"venue"
},
  "geometry": {"coordinates":[15.28444,37.066483],"type":"Point"}
}