{
  "type": "Feature",
  "properties": {
    "addr:full":"66030 S. Giovanni Teatino Chieti 66030",
    "addr:housenumber":"66030",
    "addr:postcode":"66030",
    "addr:street":"S. Giovanni Teatino",
    "iso:country":"IT",
    "sg:address":"66030 S. Giovanni Teatino",
    "sg:orig_category":"Non-classified Establishments",
    "sg:phone":"+39 085 446 0736",
    "sg:postcode":"66030",
    "sg:province":"Chieti",
    "wof:name":"Ciesseta Srl",
    "wof:placetype":"venue"
},
  "geometry": {"coordinates":[14.180963,42.418926],"type":"Point"}
}