{
  "type": "Feature",
  "properties": {
    "iso:country":"IT",
    "sg:address":"09128 Cagliari",
    "sg:city":"Cagliari",
    "sg:classifiers":[
        {
            "category":"Health Services",
            "subcategory":"Nursing And Care Facility",
            "type":"Services"
        }
    ],
    "sg:phone":"+39 070 494891",
    "sg:postcode":"09128",
    "sg:province":"Cagliari",
    "sg:tags":[
        "case",
        "cura",
        "private",
        "di"
    ],
    "sg:website":"http://www.casadicuravillaelena.it",
    "wof:name":"Casa Di Cura Villa Elena Spa",
    "wof:placetype":"venue"
},
  "geometry": {"coordinates":[9.124368,39.214378],"type":"Point"}
}