{
  "type": "Feature",
  "properties": {
    "iso:country":"IT",
    "sg:address":"64021 Giulianova",
    "sg:city":"Giulianova",
    "sg:orig_category":"Caminetti, Forni Da Giardino E Barbecues",
    "sg:phone":"+39 085 800 6034",
    "sg:postcode":"64021",
    "sg:province":"Teramo",
    "wof:name":"Bioedilizia Srl",
    "wof:placetype":"venue"
},
  "geometry": {"coordinates":[13.956345,42.766514],"type":"Point"}
}