{
  "type": "Feature",
  "properties": {
    "addr:full":"24/c, Viale Gorizia 00198 Roma Roma Roma 00198",
    "addr:housenumber":"24 / c",
    "addr:postcode":"00198;00198",
    "addr:street":"Viale Gorizia",
    "iso:country":"IT",
    "sg:address":"24/c, Viale Gorizia 00198 Roma",
    "sg:city":"Roma",
    "sg:classifiers":[
        {
            "category":"Travel",
            "subcategory":"Travel Agent",
            "type":"Entertainment"
        }
    ],
    "sg:phone":"+39 39068417001",
    "sg:postcode":"00198",
    "sg:province":"Roma",
    "sg:tags":[
        "business"
    ],
    "wof:name":"Fasi Congress Srl",
    "wof:placetype":"venue"
},
  "geometry": {"coordinates":[12.482325,41.895466],"type":"Point"}
}