{
  "type": "Feature",
  "properties": {
    "iso:country":"IT",
    "sg:address":"24019 Zogno",
    "sg:city":"Ambria",
    "sg:orig_category":"Impiantistica E Prodotti Tecnologici Per Edilizia. Elettrotecnica Industriale, Prodotti E Apparecchiature. Elettrotecnica Professionale E Di Consumo",
    "sg:phone":"+39 0345 92646",
    "sg:postcode":"24019",
    "sg:province":"Bergamo",
    "sg:website":"http://www.htaitalia.com",
    "wof:name":"H.t.a. High Technology Application Snc",
    "wof:placetype":"venue"
},
  "geometry": {"coordinates":[9.679437,45.806957],"type":"Point"}
}