{
  "type": "Feature",
  "properties": {
    "addr:full":"10092 Beinasco Beinasco Torino 10092",
    "addr:postcode":"10092;10092",
    "iso:country":"IT",
    "sg:address":"10092 Beinasco",
    "sg:city":"Beinasco",
    "sg:orig_category":"Macchine E Forniture Per Arredamento E Industria Del Legno. Colori, Vernici E Smalti",
    "sg:phone":"+39 011 398 7492",
    "sg:postcode":"10092",
    "sg:province":"Torino",
    "wof:name":"Fornasari Sergio",
    "wof:placetype":"venue"
},
  "geometry": {"coordinates":[7.586665,45.017017],"type":"Point"}
}