{
  "type": "Feature",
  "properties": {
    "addr:full":"20090 Assago Assago Milano 20090",
    "addr:postcode":"20090;20090",
    "addr:street":"Assago",
    "iso:country":"IT",
    "sg:address":"20090 Assago",
    "sg:city":"Assago",
    "sg:classifiers":[
        {
            "category":"Sports & Exercise",
            "subcategory":"Tennis Court",
            "type":"Entertainment"
        }
    ],
    "sg:phone":"+39 02 488 0241",
    "sg:postcode":"20090",
    "sg:province":"Milano",
    "sg:tags":[
        "e",
        "lo",
        "tempo",
        "libero",
        "per",
        "impianti",
        "il",
        "attrezzature"
    ],
    "sg:website":"http://www.nordpiscine.it",
    "wof:name":"Nord Piscine Srl",
    "wof:placetype":"venue"
},
  "geometry": {"coordinates":[9.122567,45.402092],"type":"Point"}
}