{
  "type": "Feature",
  "properties": {
    "addr:full":"Via C\u00e0 Morelli 19/a 31056 Roncade Roncade Treviso 31056",
    "addr:housenumber":"19 / a",
    "addr:postcode":"31056;31056",
    "addr:street":"Via Ca\u0300 Morelli",
    "iso:country":"IT",
    "sg:address":"Via C\u00e0 Morelli 19/a 31056 Roncade",
    "sg:city":"Roncade",
    "sg:classifiers":[
        {
            "category":"Manufacturing",
            "subcategory":"Furniture",
            "type":"Manufacturing & Wholesale Goods"
        }
    ],
    "sg:phone":"+39 0422 707426",
    "sg:postcode":"31056",
    "sg:province":"Treviso",
    "sg:tags":[
        "hinge"
    ],
    "wof:name":"Anselmi & C. Srl",
    "wof:placetype":"venue"
},
  "geometry": {"coordinates":[12.3685007095,45.6369400024],"type":"Point"}
}