{
  "type": "Feature",
  "properties": {
    "iso:country":"IT",
    "sg:address":"80051 Agerola",
    "sg:city":"Agerola",
    "sg:orig_category":"Prodotti Chimici Secondari. Tempo Libero - Articoli E Forniture. Servizi Per Lo Sport E Il Tempo Libero. Servizi Per Aziende, Manifestazioni E Supporto Agli Scambi Commerciali",
    "sg:phone":"+39 081 873 1214",
    "sg:postcode":"80051",
    "sg:province":"Napoli",
    "wof:name":"Medaglia Matteo",
    "wof:placetype":"venue"
},
  "geometry": {"coordinates":[14.5480480194,40.6413230896],"type":"Point"}
}