{
  "type": "Feature",
  "properties": {
    "iso:country":"IT",
    "sg:address":"Palazzo Serbelloni; Milano; 20121",
    "sg:city":"Milano",
    "sg:classifiers":[
        {
            "category":"Banks & Credit Unions",
            "subcategory":"Bank",
            "type":"Services"
        }
    ],
    "sg:phone":"+39 02 7600 4752",
    "sg:postcode":"20121",
    "sg:province":"Milano",
    "wof:name":"Morgan Stanley International Inc.",
    "wof:placetype":"venue"
},
  "geometry": {"coordinates":[9.199658,45.46907],"type":"Point"}
}