{
  "type": "Feature",
  "properties": {
    "addr:full":"5, Via Milano 22070 Luisago Luisago Como 22070",
    "addr:postcode":"22070;22070",
    "addr:street":"Via Milano",
    "iso:country":"IT",
    "sg:address":"5, Via Milano 22070 Luisago",
    "sg:city":"Luisago",
    "sg:classifiers":[
        {
            "category":"Professional",
            "subcategory":"Engineering",
            "type":"Services"
        }
    ],
    "sg:phone":"+39 39031927170",
    "sg:postcode":"22070",
    "sg:province":"Como",
    "sg:tags":[
        "machine",
        "-",
        "mechanical"
    ],
    "wof:name":"Bema (s.r.l.)",
    "wof:placetype":"venue"
},
  "geometry": {"coordinates":[9.059883,45.75679],"type":"Point"}
}