{
  "type": "Feature",
  "properties": {
    "addr:full":"04100 Latina Latina Latina 04100",
    "addr:postcode":"04100;04100",
    "iso:country":"IT",
    "sg:address":"04100 Latina",
    "sg:city":"Latina",
    "sg:orig_category":"Caldaie Riscaldamento",
    "sg:phone":"+39 0773 484762",
    "sg:postcode":"04100",
    "sg:province":"Latina",
    "wof:name":"Centro Termico Srl",
    "wof:placetype":"venue"
},
  "geometry": {"coordinates":[12.90678,41.474716],"type":"Point"}
}