{
  "type": "Feature",
  "properties": {
    "addr:full":"Via Buonarroti 5/7 20050 Triuggio Triuggio Milano 20050",
    "addr:housenumber":"5 / 7",
    "addr:postcode":"20050;20050",
    "addr:street":"Via Buonarroti",
    "iso:country":"IT",
    "sg:address":"Via Buonarroti 5/7 20050 Triuggio",
    "sg:city":"Triuggio",
    "sg:classifiers":[
        {
            "category":"Wholesale",
            "subcategory":"Construction Materials",
            "type":"Manufacturing & Wholesale Goods"
        }
    ],
    "sg:phone":"+39 036 291 8311",
    "sg:postcode":"20050",
    "sg:province":"Milano",
    "sg:tags":[
        "concrete",
        "additive"
    ],
    "wof:name":"Tekna Chem Srl",
    "wof:placetype":"venue"
},
  "geometry": {"coordinates":[9.188141,45.463688],"type":"Point"}
}