{
  "type": "Feature",
  "properties": {
    "iso:country":"IT",
    "sg:address":"17, Via Delle Scalette 51039 Quarrata",
    "sg:city":"Quarrata",
    "sg:classifiers":[
        {
            "category":"Manufacturing",
            "subcategory":"Lumber",
            "type":"Manufacturing & Wholesale Goods"
        }
    ],
    "sg:phone":"+39 0573 737797",
    "sg:postcode":"51039",
    "sg:province":"Pistoia",
    "sg:tags":[
        "wood"
    ],
    "wof:name":"M.t.m. Di Martelli Guido E C. Snc",
    "wof:placetype":"venue"
},
  "geometry": {"coordinates":[10.995354,43.85323],"type":"Point"}
}