{
  "type": "Feature",
  "properties": {
    "addr:full":"12024 Costigliole Saluzzo Costigliole Saluzzo Cuneo 12024",
    "addr:postcode":"12024;12024",
    "iso:country":"IT",
    "sg:address":"12024 Costigliole Saluzzo",
    "sg:city":"Costigliole Saluzzo",
    "sg:orig_category":"Frigotecnica, Apparecchiature E Servizi. Servizi Di Magazzinaggio E Movimentazione",
    "sg:phone":"+39 0175 230471",
    "sg:postcode":"12024",
    "sg:province":"Cuneo",
    "wof:name":"Beoletto Aurelio E Mario S.s.",
    "wof:placetype":"venue"
},
  "geometry": {"coordinates":[7.5462107658,44.5266647339],"type":"Point"}
}