{
  "type": "Feature",
  "properties": {
    "iso:country":"IT",
    "sg:address":"1, Via Fasola 28077 Prato Sesia",
    "sg:city":"Prato Sesia",
    "sg:classifiers":[
        {
            "category":"Food & Beverages",
            "subcategory":"Groceries & Convenience Stores",
            "type":"Retail Goods"
        }
    ],
    "sg:phone":"+39 0163 851172",
    "sg:postcode":"28077",
    "sg:province":"Novara",
    "sg:tags":[
        "product",
        "related"
    ],
    "wof:name":"Pmp Di Bocchese Piermarco & C. S.a.s.",
    "wof:placetype":"venue"
},
  "geometry": {"coordinates":[8.3685855865,45.6530990601],"type":"Point"}
}