{
  "type": "Feature",
  "properties": {
    "iso:country":"IT",
    "sg:address":"24030 Berbenno",
    "sg:city":"Berbenno",
    "sg:orig_category":"Servizi E Lavori Per Arredamento E Industria Del Legno",
    "sg:postcode":"24030",
    "sg:province":"Bergamo",
    "wof:name":"F.lli Todeschini Di Todeschini Marco & C. (s.n.c.)",
    "wof:placetype":"venue"
},
  "geometry": {"coordinates":[9.657463,45.698689],"type":"Point"}
}