{
  "type": "Feature",
  "properties": {
    "iso:country":"IT",
    "sg:address":"22, Cupa Lautrec 80141 Napoli",
    "sg:city":"Napoli",
    "sg:orig_category":"Miscellaneous Products",
    "sg:phone":"+39 081 780 1155",
    "sg:postcode":"80141",
    "sg:province":"Napoli",
    "wof:name":"Strazzullo S.r.l.",
    "wof:placetype":"venue"
},
  "geometry": {"coordinates":[14.2837581635,40.8689155579],"type":"Point"}
}