{
  "type": "Feature",
  "properties": {
    "iso:country":"IT",
    "sg:address":"8, Via Marconi 21020 Bardello",
    "sg:city":"Bardello",
    "sg:classifiers":[
        {
            "category":"Manufacturing",
            "subcategory":"Metals",
            "type":"Manufacturing & Wholesale Goods"
        }
    ],
    "sg:phone":"+39 0332 743644",
    "sg:postcode":"21020",
    "sg:province":"Varese",
    "sg:tags":[
        "processing"
    ],
    "wof:name":"Savens (s.r.l.)",
    "wof:placetype":"venue"
},
  "geometry": {"coordinates":[8.7137079239,45.820350647],"type":"Point"}
}