{
  "type": "Feature",
  "properties": {
    "iso:country":"IT",
    "sg:address":"46030 San Giorgio Di Mantova",
    "sg:city":"San Giorgio di Mantova",
    "sg:orig_category":"Servizi E Lavori Per Agricoltura E Zootecnia",
    "sg:phone":"+39 0376 371582",
    "sg:postcode":"46030",
    "sg:province":"Mantova",
    "wof:name":"Caffini Creonte",
    "wof:placetype":"venue"
},
  "geometry": {"coordinates":[10.871969,45.153164],"type":"Point"}
}