{
  "type": "Feature",
  "properties": {
    "iso:country":"IT",
    "sg:address":"00054 Fiumicino",
    "sg:city":"Fiumicino",
    "sg:orig_category":"Chiese Ed Associazioni Religiose",
    "sg:phone":"+39 06 650 6175",
    "sg:postcode":"00054",
    "sg:province":"Roma",
    "wof:name":"Chiesa Apostolica",
    "wof:placetype":"venue"
},
  "geometry": {"coordinates":[12.232077,41.777271],"type":"Point"}
}