{
  "type": "Feature",
  "properties": {
    "addr:full":"10040 Val Della Torre Val della Torre Torino 10040",
    "addr:postcode":"10040;10040",
    "iso:country":"IT",
    "sg:address":"10040 Val Della Torre",
    "sg:city":"Val della Torre",
    "sg:orig_category":"Forniture Per Edilizia E Lavori Pubblici. Forniture Per Attivita' Industriali",
    "sg:phone":"+39 011 968 9634",
    "sg:postcode":"10040",
    "sg:province":"Torino",
    "wof:name":"Beta Model Di Ursi E Samuelli Snc",
    "wof:placetype":"venue"
},
  "geometry": {"coordinates":[7.4871511459,45.1392860413],"type":"Point"}
}