{
  "type": "Feature",
  "properties": {
    "iso:country":"IT",
    "sg:address":"24050 Covo",
    "sg:city":"Covo",
    "sg:orig_category":"Macchine Movimento Terra",
    "sg:phone":"+39 036 393632",
    "sg:postcode":"24050",
    "sg:province":"Bergamo",
    "wof:name":"Enzo Pesenti Srl",
    "wof:placetype":"venue"
},
  "geometry": {"coordinates":[9.773752,45.501366],"type":"Point"}
}