{
  "type": "Feature",
  "properties": {
    "iso:country":"IT",
    "sg:address":"51017 Pescia",
    "sg:city":"Pescia",
    "sg:orig_category":"Prodotti Di Base E Forniture Per Industria Alimentare E Bevande",
    "sg:phone":"+39 0572 476816",
    "sg:postcode":"51017",
    "sg:province":"Pistoia",
    "wof:name":"Giordano Italo",
    "wof:placetype":"venue"
},
  "geometry": {"coordinates":[10.6852588654,43.9004325867],"type":"Point"}
}