{
  "type": "Feature",
  "properties": {
    "iso:country":"IT",
    "sg:address":"22060 Cabiate",
    "sg:city":"Cabiate",
    "sg:orig_category":"Servizi E Lavori Per Arredamento E Industria Del Legno. Arte Ed Artigianato Artistico",
    "sg:phone":"+39 031 766538",
    "sg:postcode":"22060",
    "sg:province":"Como",
    "wof:name":"Mauri Paolo",
    "wof:placetype":"venue"
},
  "geometry": {"coordinates":[9.057482,45.834496],"type":"Point"}
}