{
  "type": "Feature",
  "properties": {
    "iso:country":"IT",
    "sg:address":"50, Via Mattei 31010 Maser",
    "sg:city":"Maser",
    "sg:classifiers":[
        {
            "category":"Shopping",
            "subcategory":"Clothing, Apparel, & Fashions",
            "type":"Retail Goods"
        }
    ],
    "sg:phone":"+39 0423 925022",
    "sg:postcode":"31010",
    "sg:province":"Treviso",
    "sg:tags":[
        "clothes"
    ],
    "wof:name":"Confezioni Florell S.r.l.",
    "wof:placetype":"venue"
},
  "geometry": {"coordinates":[11.965041,45.792538],"type":"Point"}
}