{
  "type": "Feature",
  "properties": {
    "addr:full":"74100 Taranto Taranto Taranto 74100",
    "addr:postcode":"74100;74100",
    "iso:country":"IT",
    "sg:address":"74100 Taranto",
    "sg:city":"Taranto",
    "sg:orig_category":"Pubblica Amministrazione",
    "sg:phone":"+39 099 739 5111",
    "sg:postcode":"74100",
    "sg:province":"Taranto",
    "wof:name":"Vigili Del Fuoco",
    "wof:placetype":"venue"
},
  "geometry": {"coordinates":[17.2510299683,40.4609489441],"type":"Point"}
}