{
  "type": "Feature",
  "properties": {
    "iso:country":"IT",
    "sg:address":"80141 Napoli",
    "sg:city":"Napoli",
    "sg:orig_category":"Ospedali E Servizi Sanitari",
    "sg:phone":"+39 081 599 3425",
    "sg:postcode":"80141",
    "sg:province":"Napoli",
    "wof:name":"Antismoking Center Sas",
    "wof:placetype":"venue"
},
  "geometry": {"coordinates":[14.26658,40.870995],"type":"Point"}
}