{
  "type": "Feature",
  "properties": {
    "addr:full":"20020 Lainate Lainate Milano 20020",
    "addr:postcode":"20020;20020",
    "iso:country":"IT",
    "sg:address":"20020 Lainate",
    "sg:city":"Lainate",
    "sg:orig_category":"Prodotti Chimici Secondari. Medicinali E Prodotti Parafarmaceutici",
    "sg:phone":"+39 02 937631",
    "sg:postcode":"20020",
    "sg:province":"Milano",
    "wof:name":"Alk Abello' Spa",
    "wof:placetype":"venue"
},
  "geometry": {"coordinates":[9.0403594971,45.5755233765],"type":"Point"}
}