{
  "type": "Feature",
  "properties": {
    "addr:full":"63, Via Vigna 35020 Arzergrande Arzergrande Padova 35020",
    "addr:postcode":"35020;35020",
    "addr:street":"Via Vigna",
    "iso:country":"IT",
    "sg:address":"63, Via Vigna 35020 Arzergrande",
    "sg:city":"Arzergrande",
    "sg:classifiers":[
        {
            "category":"Shopping",
            "subcategory":"Clothing, Apparel, & Fashions",
            "type":"Retail Goods"
        }
    ],
    "sg:phone":"+39 049 580 0517",
    "sg:postcode":"35020",
    "sg:province":"Padova",
    "sg:tags":[
        "clothes"
    ],
    "wof:name":"Confezioni Rosa",
    "wof:placetype":"venue"
},
  "geometry": {"coordinates":[12.036997,45.267876],"type":"Point"}
}