{
  "type": "Feature",
  "properties": {
    "iso:country":"IT",
    "sg:address":"12100 Confreria",
    "sg:city":"Confreria",
    "sg:orig_category":"Ospedali E Servizi Sanitari",
    "sg:phone":"+39 0171 641111",
    "sg:postcode":"12100",
    "sg:province":"Cuneo",
    "wof:name":"Ospedale Carle",
    "wof:placetype":"venue"
},
  "geometry": {"coordinates":[7.518304,44.389744],"type":"Point"}
}