{
  "type": "Feature",
  "properties": {
    "iso:country":"IT",
    "sg:address":"70121 Bari",
    "sg:city":"Bari",
    "sg:orig_category":"Abbigliamento Intimo, Calze E Costumi Da Bagno. Shopping",
    "sg:phone":"+39 080 521 3827",
    "sg:postcode":"70121",
    "sg:province":"Bari",
    "wof:name":"Minerva Sas",
    "wof:placetype":"venue"
},
  "geometry": {"coordinates":[16.868761,41.12381],"type":"Point"}
}