{
  "type": "Feature",
  "properties": {
    "iso:country":"IT",
    "sg:address":"20146 Milano",
    "sg:city":"Milano",
    "sg:orig_category":"Apparecchiature Ed Attrezzature Meccaniche. Elettronica Industriale, Prodotti E Apparecchiature. Impianti, Attrezzature E Forniture Sanitarie Ed Ospedaliere. Apparecchi, Attrezzature E Forniture Per C",
    "sg:phone":"+39 02 4871 3191",
    "sg:postcode":"20146",
    "sg:province":"Milano",
    "wof:name":"Flaser Srl",
    "wof:placetype":"venue"
},
  "geometry": {"coordinates":[9.1432,45.460594],"type":"Point"}
}