{
  "type": "Feature",
  "properties": {
    "iso:country":"IT",
    "sg:address":"Via Bernini 9 80020 Frattaminore",
    "sg:city":"Frattaminore",
    "sg:orig_category":"Ladies' Shoes",
    "sg:phone":"+39 081 890 4111",
    "sg:postcode":"80020",
    "sg:province":"Napoli",
    "wof:name":"Angelo Bervicato Srl",
    "wof:placetype":"venue"
},
  "geometry": {"coordinates":[14.270327,40.958813],"type":"Point"}
}