{
  "type": "Feature",
  "properties": {
    "iso:country":"IT",
    "sg:address":"50065 Pontassieve",
    "sg:city":"Pontassieve",
    "sg:orig_category":"Impiantistica E Prodotti Tecnologici Per Edilizia. Forniture Industriali Per Prevenzione, Controllo E Sicurezza",
    "sg:phone":"+39 055 836 7086",
    "sg:postcode":"50065",
    "sg:province":"Firenze",
    "wof:name":"Ce.v.est. Centro Vendita Estintori Snc",
    "wof:placetype":"venue"
},
  "geometry": {"coordinates":[11.422133,43.773762],"type":"Point"}
}