{
  "type": "Feature",
  "properties": {
    "addr:full":"10155 Torino Torino Torino 10155",
    "addr:postcode":"10155;10155",
    "iso:country":"IT",
    "sg:address":"10155 Torino",
    "sg:city":"Torino",
    "sg:orig_category":"Sale Giochi, Biliardi E Bowlings",
    "sg:phone":"+39 011 248 9618",
    "sg:postcode":"10155",
    "sg:province":"Torino",
    "wof:name":"Fabbrica Bigliardi Fratelli De Agostini Di Mazzei M. & C.",
    "wof:placetype":"venue"
},
  "geometry": {"coordinates":[7.692323,45.090649],"type":"Point"}
}