{
  "type": "Feature",
  "properties": {
    "iso:country":"IT",
    "sg:address":"Viale Dell' Areonautica 80038 Pomigliano D'arco",
    "sg:classifiers":[
        {
            "category":"Utilities",
            "subcategory":"Telephone",
            "type":"Services"
        }
    ],
    "sg:phone":"+39 081 884 1321",
    "sg:postcode":"80038",
    "sg:province":"Napoli",
    "sg:tags":[
        "telecommunication"
    ],
    "wof:name":"V. La Gatta S.r.l.",
    "wof:placetype":"venue"
},
  "geometry": {"coordinates":[14.251636,40.840096],"type":"Point"}
}