{
  "type": "Feature",
  "properties": {
    "addr:full":"30175 Venezia Marghera Venezia 30175",
    "addr:postcode":"30175;30175",
    "iso:country":"IT",
    "sg:address":"30175 Venezia",
    "sg:city":"Marghera",
    "sg:orig_category":"Servizi Al Turismo. Servizi Ausiliari Per Il Trasporto",
    "sg:phone":"+39 041 920686",
    "sg:postcode":"30175",
    "sg:province":"Venezia",
    "wof:name":"Rialto De Pita'",
    "wof:placetype":"venue"
},
  "geometry": {"coordinates":[12.099564,45.451496],"type":"Point"}
}