{
  "type": "Feature",
  "properties": {
    "iso:country":"IT",
    "sg:address":"145, Via Piave 32040 Lozzo Di Cadore",
    "sg:city":"Lozzo di Cadore",
    "sg:classifiers":[
        {
            "category":"Wholesale",
            "subcategory":"Medical Equipment & Supplies",
            "type":"Manufacturing & Wholesale Goods"
        }
    ],
    "sg:phone":"+39 39043576782",
    "sg:postcode":"32040",
    "sg:province":"Belluno",
    "sg:tags":[
        "-",
        "health",
        "instrument"
    ],
    "wof:name":"La Fenice S.r.l.",
    "wof:placetype":"venue"
},
  "geometry": {"coordinates":[12.447614,46.485466],"type":"Point"}
}