{
  "type": "Feature",
  "properties": {
    "addr:full":"16039 Sestri Levante Sestri Levante Genova 16039",
    "addr:postcode":"16039;16039",
    "iso:country":"IT",
    "sg:address":"16039 Sestri Levante",
    "sg:city":"Sestri Levante",
    "sg:orig_category":"Materiali E Componenti Elettrotecnici",
    "sg:phone":"+39 0185 43095",
    "sg:postcode":"16039",
    "sg:province":"Genova",
    "wof:name":"Dielettrica Ligure (s.r.l.)",
    "wof:placetype":"venue"
},
  "geometry": {"coordinates":[9.420201,44.266293],"type":"Point"}
}