{
  "type": "Feature",
  "properties": {
    "iso:country":"IT",
    "sg:address":"Via De Marchi, 30/32 31020 San Vendemiano",
    "sg:city":"San Vendemiano",
    "sg:classifiers":[
        {
            "category":"Home & Garden",
            "subcategory":"Hardware",
            "type":"Retail Goods"
        }
    ],
    "sg:phone":"+39 0438 400132",
    "sg:postcode":"31020",
    "sg:province":"Treviso",
    "sg:tags":[
        "small",
        "ironware",
        "item"
    ],
    "sg:website":"www.sarvo.it",
    "wof:name":"Sarbo Spa",
    "wof:placetype":"venue"
},
  "geometry": {"coordinates":[12.329329,45.903641],"type":"Point"}
}