{
  "type": "Feature",
  "properties": {
    "addr:full":"40128 Bologna Bologna Bologna 40128",
    "addr:postcode":"40128;40128",
    "iso:country":"IT",
    "sg:address":"40128 Bologna",
    "sg:city":"Bologna",
    "sg:orig_category":"Componenti Elettronici",
    "sg:phone":"+39 051 374029",
    "sg:postcode":"40128",
    "sg:province":"Bologna",
    "sg:website":"http://www.ropavittorio.com",
    "wof:name":"Ropa Vittorio & C. Snc",
    "wof:placetype":"venue"
},
  "geometry": {"coordinates":[11.355308,44.508759],"type":"Point"}
}