{
  "type": "Feature",
  "properties": {
    "iso:country":"IT",
    "sg:address":"76/78, Via Della Produzione 61025 Montelabbate",
    "sg:city":"Montelabbate",
    "sg:classifiers":[
        {
            "category":"Home & Garden",
            "subcategory":"Home Furnishings",
            "type":"Retail Goods"
        }
    ],
    "sg:phone":"+39 0721 481144",
    "sg:postcode":"61025",
    "sg:province":"Pesaro E Urbino",
    "sg:tags":[
        "household"
    ],
    "wof:name":"R.t.l. Di Rapa S.r.l.",
    "wof:placetype":"venue"
},
  "geometry": {"coordinates":[12.817565,43.860931],"type":"Point"}
}