{
  "type": "Feature",
  "properties": {
    "iso:country":"IT",
    "sg:address":"13818 Tollegno",
    "sg:city":"Tollegno",
    "sg:orig_category":"Servizi E Lavori Per Edilizia E Lavori Pubblici",
    "sg:phone":"+39 015 242 3038",
    "sg:postcode":"13818",
    "sg:province":"Biella",
    "wof:name":"Magnolo Giuseppe",
    "wof:placetype":"venue"
},
  "geometry": {"coordinates":[8.049818,45.596401],"type":"Point"}
}