{
  "type": "Feature",
  "properties": {
    "addr:full":"56025 Pontedera Pontedera Pisa 56025",
    "addr:postcode":"56025;56025",
    "iso:country":"IT",
    "sg:address":"56025 Pontedera",
    "sg:city":"Pontedera",
    "sg:orig_category":"Tessuti E Stoffe. Filati E Materie Prime Tessili",
    "sg:phone":"+39 0587 290374",
    "sg:postcode":"56025",
    "sg:province":"Pisa",
    "wof:name":"Italtessil",
    "wof:placetype":"venue"
},
  "geometry": {"coordinates":[10.395495,43.719097],"type":"Point"}
}