{
  "type": "Feature",
  "properties": {
    "iso:country":"IT",
    "sg:address":"61, Via Bruni Grimaldi Nicola 84014 Nocera Inferiore",
    "sg:city":"Nocera Inferiore",
    "sg:classifiers":[
        {
            "category":"Professional",
            "subcategory":"Engineering",
            "type":"Services"
        }
    ],
    "sg:phone":"+39 081 517 9670",
    "sg:postcode":"84014",
    "sg:province":"Salerno",
    "sg:tags":[
        "machine",
        "-",
        "mechanical"
    ],
    "wof:name":"Ferrara S.n.c.di G. & G Ferrara",
    "wof:placetype":"venue"
},
  "geometry": {"coordinates":[14.765912,40.677956],"type":"Point"}
}