{
  "type": "Feature",
  "properties": {
    "iso:country":"IT",
    "sg:address":"25039 Travagliato",
    "sg:city":"Travagliato",
    "sg:orig_category":"Zootecnia E Pesca, Allevamento Piccoli Animali",
    "sg:phone":"+39 030 660457",
    "sg:postcode":"25039",
    "sg:province":"Brescia",
    "wof:name":"Foini Bruno",
    "wof:placetype":"venue"
},
  "geometry": {"coordinates":[10.115698,45.564682],"type":"Point"}
}