{
  "type": "Feature",
  "properties": {
    "iso:country":"IT",
    "sg:address":"Piazza Garibaldi, 7; Barge; 12032",
    "sg:city":"Barge",
    "sg:classifiers":[
        {
            "category":"Banks & Credit Unions",
            "subcategory":"Bank",
            "type":"Services"
        }
    ],
    "sg:phone":"+39 0175 36455",
    "sg:postcode":"12032",
    "sg:province":"Cuneo",
    "wof:name":"Cassa Di Risparmio Di Torino",
    "wof:placetype":"venue"
},
  "geometry": {"coordinates":[7.322904,44.725075],"type":"Point"}
}