{
  "type": "Feature",
  "properties": {
    "iso:country":"IT",
    "sg:address":"26100 Cremona",
    "sg:city":"Cremona",
    "sg:orig_category":"Cine-foto-ottica. Shopping",
    "sg:phone":"+39 0372 23407",
    "sg:postcode":"26100",
    "sg:province":"Cremona",
    "wof:name":"Adamo Ed Eva",
    "wof:placetype":"venue"
},
  "geometry": {"coordinates":[10.029757,45.148808],"type":"Point"}
}