{
  "type": "Feature",
  "properties": {
    "addr:full":"10128 Torino Torino Torino 10128",
    "addr:postcode":"10128;10128",
    "iso:country":"IT",
    "sg:address":"10128 Torino",
    "sg:city":"Torino",
    "sg:orig_category":"Audiovisivi Filmati, Spot E Multimediali - Realizzazione E Duplicazione",
    "sg:phone":"+39 011 580 6123",
    "sg:postcode":"10128",
    "sg:province":"Torino",
    "sg:website":"http://www.pulsar.to.it",
    "wof:name":"Pulsar Srl",
    "wof:placetype":"venue"
},
  "geometry": {"coordinates":[7.665637,45.051918],"type":"Point"}
}