{
  "type": "Feature",
  "properties": {
    "iso:country":"IT",
    "sg:address":"31, Via Paolo Braccini 01030 Canepina",
    "sg:city":"Canepina",
    "sg:classifiers":[
        {
            "category":"Shopping",
            "subcategory":"Clothing, Apparel, & Fashions",
            "type":"Retail Goods"
        }
    ],
    "sg:phone":"+39 0761 752279",
    "sg:postcode":"01030",
    "sg:province":"Viterbo",
    "sg:tags":[
        "clothes"
    ],
    "wof:name":"Maglificio Nuovo Secolo Snc Di Bracci Gabriella E Luana",
    "wof:placetype":"venue"
},
  "geometry": {"coordinates":[12.104854,42.417381],"type":"Point"}
}