{
  "type": "Feature",
  "properties": {
    "addr:full":"16, Via Rimembranza 22079 Villa Guardia Villa Guardia Como 22079",
    "addr:housenumber":"guardia",
    "addr:postcode":"22079;22079",
    "addr:street":"Via Rimembranza;Guardia",
    "iso:country":"IT",
    "sg:address":"16, Via Rimembranza 22079 Villa Guardia",
    "sg:city":"Villa Guardia",
    "sg:classifiers":[
        {
            "category":"Food & Beverages",
            "subcategory":"Dairy",
            "type":"Retail Goods"
        }
    ],
    "sg:phone":"+39 39031563333",
    "sg:postcode":"22079",
    "sg:province":"Como",
    "sg:tags":[
        "product"
    ],
    "wof:name":"Carnini (s.p.a.)",
    "wof:placetype":"venue"
},
  "geometry": {"coordinates":[9.02167,45.783039],"type":"Point"}
}