{
  "type": "Feature",
  "properties": {
    "addr:full":"20067 Paullo Paullo Milano 20067",
    "addr:postcode":"20067;20067",
    "iso:country":"IT",
    "sg:address":"20067 Paullo",
    "sg:city":"Paullo",
    "sg:orig_category":"Prodotti Alimentari",
    "sg:phone":"+39 02 906 4341",
    "sg:postcode":"20067",
    "sg:province":"Milano",
    "wof:name":"L'emporio Verde",
    "wof:placetype":"venue"
},
  "geometry": {"coordinates":[9.0052728653,45.4851989746],"type":"Point"}
}