{
  "type": "Feature",
  "properties": {
    "iso:country":"IT",
    "sg:address":"10072 Caselle Torinese",
    "sg:city":"Caselle Torinese",
    "sg:orig_category":"Associazioni Ed Organismi Di Interesse Pubblico",
    "sg:phone":"+39 011 991 4588",
    "sg:postcode":"10072",
    "sg:province":"Torino",
    "wof:name":"Associazione Nazionale Alpini",
    "wof:placetype":"venue"
},
  "geometry": {"coordinates":[7.647851,45.177006],"type":"Point"}
}