{
  "type": "Feature",
  "properties": {
    "iso:country":"IT",
    "sg:address":"35, Via Matteotti Giacomo 20093 Cologno Monzese",
    "sg:city":"Cologno Monzese",
    "sg:classifiers":[
        {
            "category":"Professional",
            "subcategory":"Engineering",
            "type":"Services"
        }
    ],
    "sg:phone":"+39 39022542814",
    "sg:postcode":"20093",
    "sg:province":"Milano",
    "sg:tags":[
        "machine",
        "-",
        "mechanical"
    ],
    "wof:name":"Mentasti G. (s.a.s.)",
    "wof:placetype":"venue"
},
  "geometry": {"coordinates":[9.275654,45.533321],"type":"Point"}
}