{
  "type": "Feature",
  "properties": {
    "iso:country":"IT",
    "sg:address":"3, Via Ferretti 14054 Coazzolo",
    "sg:city":"Coazzolo",
    "sg:classifiers":[
        {
            "category":"Building & Trades",
            "subcategory":"Construction",
            "type":"Services"
        }
    ],
    "sg:phone":"+39 0141 870157",
    "sg:postcode":"14054",
    "sg:province":"Asti",
    "sg:tags":[
        "work",
        "public"
    ],
    "wof:name":"S.f.p. - Societa' Fabbricazione Poliestere (s.r.l.)",
    "wof:placetype":"venue"
},
  "geometry": {"coordinates":[8.153419,44.737667],"type":"Point"}
}