{
  "type": "Feature",
  "properties": {
    "iso:country":"IT",
    "sg:address":"26018 Trigolo",
    "sg:city":"Trigolo",
    "sg:orig_category":"Servizi E Lavori Per Agricoltura E Zootecnia",
    "sg:phone":"+39 0374 370238",
    "sg:postcode":"26018",
    "sg:province":"Cremona",
    "wof:name":"Co.p.a. Trigolese S.c.r.l.",
    "wof:placetype":"venue"
},
  "geometry": {"coordinates":[9.815495,45.331676],"type":"Point"}
}