{
  "type": "Feature",
  "properties": {
    "iso:country":"IT",
    "sg:address":"Stradone Porta Palio 86; Verona; 37122",
    "sg:city":"Verona",
    "sg:classifiers":[
        {
            "category":"Banks & Credit Unions",
            "subcategory":"Bank",
            "type":"Services"
        }
    ],
    "sg:phone":"+39 045 867 2711",
    "sg:postcode":"37122",
    "sg:province":"Verona",
    "wof:name":"Rolo Banca 1473 Spa",
    "wof:placetype":"venue"
},
  "geometry": {"coordinates":[10.980736,45.435677],"type":"Point"}
}