{
  "type": "Feature",
  "properties": {
    "addr:full":"00153 Roma Roma Roma 00153",
    "addr:postcode":"00153;00153",
    "iso:country":"IT",
    "sg:address":"00153 Roma",
    "sg:city":"Roma",
    "sg:orig_category":"Articoli Sportivi - Vendita Al Dettaglio",
    "sg:phone":"+39 06 574 6277",
    "sg:postcode":"00153",
    "sg:province":"Roma",
    "wof:name":"Aleandri Massimo Fabio Emporio Del Pescatore",
    "wof:placetype":"venue"
},
  "geometry": {"coordinates":[12.475321,41.881931],"type":"Point"}
}