{
  "type": "Feature",
  "properties": {
    "addr:full":"Via Salaino Andrea 14 20144 Milano Milano Milano 20144",
    "addr:housenumber":"14",
    "addr:postcode":"20144;20144",
    "addr:street":"Via Salaino Andrea",
    "iso:country":"IT",
    "sg:address":"Via Salaino Andrea 14 20144 Milano",
    "sg:city":"Milano",
    "sg:classifiers":[
        {
            "category":"Shopping",
            "subcategory":"Clothing, Apparel, & Fashions",
            "type":"Retail Goods"
        }
    ],
    "sg:phone":"+39 02 498 0510",
    "sg:postcode":"20144",
    "sg:province":"Milano",
    "sg:tags":[
        "leather",
        "clothing"
    ],
    "wof:name":"A.m.a. Srl",
    "wof:placetype":"venue"
},
  "geometry": {"coordinates":[9.163922,45.457226],"type":"Point"}
}