{
  "type": "Feature",
  "properties": {
    "iso:country":"IT",
    "sg:address":"10098 Rivoli",
    "sg:city":"Rivoli",
    "sg:orig_category":"Prodotti E Manufatti In Gomma. Forniture Per Attivita' Industriali",
    "sg:phone":"+39 011 957 4025",
    "sg:postcode":"10098",
    "sg:province":"Torino",
    "wof:name":"Taurus Sages Srl",
    "wof:placetype":"venue"
},
  "geometry": {"coordinates":[7.5567626953,45.0797729492],"type":"Point"}
}