{
  "type": "Feature",
  "properties": {
    "iso:country":"IT",
    "sg:address":"12, Via Giovanni Xxiii 37051 Bovolone",
    "sg:city":"Bovolone",
    "sg:classifiers":[
        {
            "category":"Home & Garden",
            "subcategory":"Home Furnishings",
            "type":"Retail Goods"
        }
    ],
    "sg:phone":"+39 045 690 1089",
    "sg:postcode":"37051",
    "sg:province":"Verona",
    "sg:tags":[
        "household"
    ],
    "wof:name":"Como' Stil Di Patuzzo Patrizia",
    "wof:placetype":"venue"
},
  "geometry": {"coordinates":[11.129156,45.262409],"type":"Point"}
}