{
  "type": "Feature",
  "properties": {
    "iso:country":"IT",
    "sg:address":"Via Xxi Luglio 5-7-9; Sessa Aurunca; 81037",
    "sg:city":"Sessa Aurunca",
    "sg:classifiers":[
        {
            "category":"Banks & Credit Unions",
            "subcategory":"Bank",
            "type":"Services"
        }
    ],
    "sg:phone":"+39 0823 937800",
    "sg:postcode":"81037",
    "sg:province":"Caserta",
    "wof:name":"Banco Di Napoli Spa",
    "wof:placetype":"venue"
},
  "geometry": {"coordinates":[13.8912,41.253365],"type":"Point"}
}