{
  "type": "Feature",
  "properties": {
    "iso:country":"IT",
    "sg:address":"Sda Per Gambolo' 58 27033 Garbana",
    "sg:city":"Garbana",
    "sg:orig_category":"Aluminium Granules",
    "sg:phone":"+39 0381 640144",
    "sg:postcode":"27033",
    "sg:province":"Pavia",
    "wof:name":"Metalplast Srl",
    "wof:placetype":"venue"
},
  "geometry": {"coordinates":[9.156563,45.185886],"type":"Point"}
}