{
  "type": "Feature",
  "properties": {
    "addr:full":"95047 Paterno' Catania 95047",
    "addr:postcode":"95047;95047",
    "addr:street":"Paterno ' Catania",
    "iso:country":"IT",
    "sg:address":"95047 Paterno'",
    "sg:orig_category":"Ospedali E Servizi Sanitari. Servizi Ausiliari Di Analisi, Controllo E Ricerca",
    "sg:phone":"+39 095 622521",
    "sg:postcode":"95047",
    "sg:province":"Catania",
    "wof:name":"Lab.analisi Biologiche Dott.ssa Guglielmino & C",
    "wof:placetype":"venue"
},
  "geometry": {"coordinates":[14.899157,37.564781],"type":"Point"}
}