{
  "type": "Feature",
  "properties": {
    "iso:country":"IT",
    "sg:address":"60010 Ripe",
    "sg:city":"Ripe",
    "sg:orig_category":"Ospedali E Servizi Sanitari. Centri Di Estetica E Cosmesi E Servizi",
    "sg:phone":"+39 071 795 8820",
    "sg:postcode":"60010",
    "sg:province":"Ancona",
    "wof:name":"Studio Di Podologia Ed Estetica Di Pizzighello Oriella",
    "wof:placetype":"venue"
},
  "geometry": {"coordinates":[13.105245,43.669937],"type":"Point"}
}