{
  "type": "Feature",
  "properties": {
    "addr:full":"31013 Codogne' Treviso 31013",
    "addr:postcode":"31013;31013",
    "addr:street":"Codogne ' Treviso",
    "iso:country":"IT",
    "sg:address":"31013 Codogne'",
    "sg:orig_category":"Materiali E Componenti Elettrotecnici",
    "sg:phone":"+39 0438 470599",
    "sg:postcode":"31013",
    "sg:province":"Treviso",
    "wof:name":"C.s.m. Spa",
    "wof:placetype":"venue"
},
  "geometry": {"coordinates":[12.373667,45.870068],"type":"Point"}
}