{
  "type": "Feature",
  "properties": {
    "addr:full":"00141 Roma Roma Roma 00141",
    "addr:postcode":"00141;00141",
    "iso:country":"IT",
    "sg:address":"00141 Roma",
    "sg:city":"Roma",
    "sg:orig_category":"Automazione E Macchine Per Ufficio",
    "sg:phone":"+39 06 8719 2050",
    "sg:postcode":"00141",
    "sg:province":"Roma",
    "sg:website":"http://www.mfpubblicita.it",
    "wof:name":"M.f. Pubblicita' Srl",
    "wof:placetype":"venue"
},
  "geometry": {"coordinates":[12.523556,41.932568],"type":"Point"}
}