{
  "type": "Feature",
  "properties": {
    "iso:country":"IT",
    "sg:address":"Via Valentini, 10; Prato; 50047",
    "sg:classifiers":[
        {
            "category":"Banks & Credit Unions",
            "subcategory":"Bank",
            "type":"Services"
        }
    ],
    "sg:phone":"+39 0574 491001",
    "wof:name":"Banca Di Roma",
    "wof:placetype":"venue"
},
  "geometry": {"coordinates":[11.101782,43.874538],"type":"Point"}
}