{
  "type": "Feature",
  "properties": {
    "addr:full":"73039 Tricase Tricase Lecce 73039",
    "addr:postcode":"73039;73039",
    "iso:country":"IT",
    "sg:address":"73039 Tricase",
    "sg:city":"Tricase",
    "sg:orig_category":"Candele, Torce A Vento E Fiaccole",
    "sg:phone":"+39 0833 546063",
    "sg:postcode":"73039",
    "sg:province":"Lecce",
    "wof:name":"Cereria Artigiana Di Longo Andrea",
    "wof:placetype":"venue"
},
  "geometry": {"coordinates":[18.368263,39.950245],"type":"Point"}
}