{
  "type": "Feature",
  "properties": {
    "iso:country":"IT",
    "sg:address":"62012 Civitanova Marche",
    "sg:city":"Civitanova Marche",
    "sg:orig_category":"Apparecchiature Oleodinamiche",
    "sg:phone":"+39 0733 895711",
    "sg:postcode":"62012",
    "sg:province":"Macerata",
    "sg:website":"http://www.camozzi.it",
    "wof:name":"Tecnoindustria Pasquali Srl",
    "wof:placetype":"venue"
},
  "geometry": {"coordinates":[13.694167,43.318214],"type":"Point"}
}