{
  "type": "Feature",
  "properties": {
    "iso:country":"IT",
    "sg:address":"20010 Pogliano Milanese",
    "sg:city":"Pogliano Milanese",
    "sg:orig_category":"Prodotti Vari In Metallo. Articoli Per Imballaggio E Confezionamento",
    "sg:phone":"+39 02 934 0821",
    "sg:postcode":"20010",
    "sg:province":"Milano",
    "wof:name":"M.r. Di Mantegazza Massimo E C. Snc",
    "wof:placetype":"venue"
},
  "geometry": {"coordinates":[8.9810085297,45.5369491577],"type":"Point"}
}