{
  "type": "Feature",
  "properties": {
    "iso:country":"IT",
    "sg:address":"50141 Firenze",
    "sg:city":"Firenze",
    "sg:orig_category":"Autonoleggio",
    "sg:phone":"+39 055 437 7906",
    "sg:postcode":"50141",
    "sg:province":"Firenze",
    "sg:website":"http://www.farbus.it",
    "wof:name":"Autonoleggi Far Di Francini Alberto",
    "wof:placetype":"venue"
},
  "geometry": {"coordinates":[10.747909,43.860737],"type":"Point"}
}