{
  "type": "Feature",
  "properties": {
    "iso:country":"IT",
    "sg:address":"2, Via Petrarca Francesco 50041 Calenzano",
    "sg:city":"Calenzano",
    "sg:classifiers":[
        {
            "category":"Manufacturing",
            "subcategory":"Metals",
            "type":"Manufacturing & Wholesale Goods"
        }
    ],
    "sg:phone":"+39 055 887 6704",
    "sg:postcode":"50041",
    "sg:province":"Firenze",
    "sg:tags":[
        "metallurgy",
        "metalworking"
    ],
    "wof:name":"Cavalzani Inox Srl",
    "wof:placetype":"venue"
},
  "geometry": {"coordinates":[11.1244935989,43.8264198303],"type":"Point"}
}