{
  "type": "Feature",
  "properties": {
    "addr:full":"26, Via Torre Verde 38100 Trento Trento Trento 38100",
    "addr:postcode":"38100;38100",
    "addr:street":"Via Torre Verde",
    "iso:country":"IT",
    "sg:address":"26, Via Torre Verde 38100 Trento",
    "sg:city":"Trento",
    "sg:classifiers":[
        {
            "category":"Home & Garden",
            "subcategory":"Home Furnishings",
            "type":"Retail Goods"
        }
    ],
    "sg:phone":"+39 0461 233666",
    "sg:postcode":"38100",
    "sg:province":"Trento",
    "sg:tags":[
        "household"
    ],
    "wof:name":"Magazzini Europa Di Nicolodi Lorenzo & C. (s.a.s.)",
    "wof:placetype":"venue"
},
  "geometry": {"coordinates":[11.123109,46.070812],"type":"Point"}
}