{
  "type": "Feature",
  "properties": {
    "iso:country":"IT",
    "sg:address":"17100 Savona",
    "sg:city":"Savona",
    "sg:orig_category":"Abbigliamento In Pelle - Vendita Al Dettaglio",
    "sg:phone":"+39 019 848 5512",
    "sg:postcode":"17100",
    "sg:province":"Savona",
    "wof:name":"Fashion Art Di Nobile Monica",
    "wof:placetype":"venue"
},
  "geometry": {"coordinates":[8.482619,44.30801],"type":"Point"}
}