{
  "type": "Feature",
  "properties": {
    "addr:full":"Via Arno, 1/3 63023 Fermo Fermo Ascoli Piceno 63023",
    "addr:housenumber":"1 / 3",
    "addr:postcode":"63023;63023",
    "addr:street":"Via Arno;Piceno",
    "iso:country":"IT",
    "sg:address":"Via Arno, 1/3 63023 Fermo",
    "sg:city":"Fermo",
    "sg:classifiers":[
        {
            "category":"Shopping",
            "subcategory":"Shoes",
            "type":"Retail Goods"
        }
    ],
    "sg:phone":"+39 0734 628373",
    "sg:postcode":"63023",
    "sg:province":"Ascoli Piceno",
    "sg:tags":[
        "men's",
        "boot"
    ],
    "wof:name":"G.d.n. Srl",
    "wof:placetype":"venue"
},
  "geometry": {"coordinates":[13.6658229828,43.17993927],"type":"Point"}
}