{
  "type": "Feature",
  "properties": {
    "iso:country":"IT",
    "sg:address":"80022 Arzano",
    "sg:city":"Arzano",
    "sg:orig_category":"Articoli Pulizia",
    "sg:phone":"+39 081 573 2828",
    "sg:postcode":"80022",
    "sg:province":"Napoli",
    "wof:name":"Fatigati Antonio S.r.l.",
    "wof:placetype":"venue"
},
  "geometry": {"coordinates":[14.269459,40.92244],"type":"Point"}
}