{
  "type": "Feature",
  "properties": {
    "addr:full":"92020 Racalmuto Racalmuto Agrigento 92020",
    "addr:postcode":"92020;92020",
    "iso:country":"IT",
    "sg:address":"92020 Racalmuto",
    "sg:city":"Racalmuto",
    "sg:orig_category":"Poltrone E Divani - Produzione E Ingrosso",
    "sg:phone":"+39 0922 942025",
    "sg:postcode":"92020",
    "sg:province":"Agrigento",
    "wof:name":"Poly.ar.tes. Di Rizzo Paolo",
    "wof:placetype":"venue"
},
  "geometry": {"coordinates":[13.7332344055,37.4088020325],"type":"Point"}
}