{
  "type": "Feature",
  "properties": {
    "iso:country":"IT",
    "sg:address":"10156 Torino",
    "sg:city":"Torino",
    "sg:orig_category":"Materiali Semilavorati Metallici",
    "sg:phone":"+39 011 450 0902",
    "sg:postcode":"10156",
    "sg:province":"Torino",
    "wof:name":"Item Srl",
    "wof:placetype":"venue"
},
  "geometry": {"coordinates":[7.70615,45.119347],"type":"Point"}
}