{
  "type": "Feature",
  "properties": {
    "iso:country":"IT",
    "sg:address":"20090 Cusago",
    "sg:city":"Cusago",
    "sg:orig_category":"Abiti Da Lavoro Ed Indumenti Protettivi",
    "sg:phone":"+39 02 9039 0302",
    "sg:postcode":"20090",
    "sg:province":"Milano",
    "sg:website":"http://www.marchesisrl.it",
    "wof:name":"Marchesi Srl",
    "wof:placetype":"venue"
},
  "geometry": {"coordinates":[9.04367,45.440315],"type":"Point"}
}