{
  "type": "Feature",
  "properties": {
    "iso:country":"IT",
    "sg:address":"23010 Fusine",
    "sg:city":"Fusine",
    "sg:orig_category":"Materiali Edili",
    "sg:phone":"+39 0342 493956",
    "sg:postcode":"23010",
    "sg:province":"Sondrio",
    "wof:name":"Valcem Srl",
    "wof:placetype":"venue"
},
  "geometry": {"coordinates":[9.735838,46.149658],"type":"Point"}
}