{
  "type": "Feature",
  "properties": {
    "iso:country":"IT",
    "sg:address":"Loc San Maurizio 13060 Roasio",
    "sg:city":"Roasio",
    "sg:orig_category":"Bakery Improvers",
    "sg:phone":"+39 0163 862004",
    "sg:postcode":"13060",
    "sg:province":"Vercelli",
    "wof:name":"San Rocco Di Eredi Gualino Umberto & Gualino Enzo Snc",
    "wof:placetype":"venue"
},
  "geometry": {"coordinates":[8.426394,45.32106],"type":"Point"}
}