{
  "type": "Feature",
  "properties": {
    "addr:full":"84083 Lanzara Lanzara Salerno 84083",
    "addr:housenumber":"84083",
    "addr:postcode":"84083",
    "addr:street":"Lanzara Lanzara",
    "iso:country":"IT",
    "sg:address":"84083 Lanzara",
    "sg:city":"Lanzara",
    "sg:orig_category":"Materiali Edili",
    "sg:phone":"+39 081 952130",
    "sg:postcode":"84083",
    "sg:province":"Salerno",
    "wof:name":"Villani Calce A. & G. Snc",
    "wof:placetype":"venue"
},
  "geometry": {"coordinates":[14.679222,40.776279],"type":"Point"}
}