{
  "type": "Feature",
  "properties": {
    "iso:country":"IT",
    "sg:address":"28845 Domodossola",
    "sg:city":"Domodossola",
    "sg:classifiers":[
        {
            "category":"Health Services",
            "subcategory":"Health Practitioner",
            "type":"Services"
        }
    ],
    "sg:phone":"+39 0324 242770",
    "sg:postcode":"28845",
    "sg:province":"Verbano-Cusio-Ossola",
    "sg:tags":[
        "medici"
    ],
    "wof:name":"Forum Crisalide",
    "wof:placetype":"venue"
},
  "geometry": {"coordinates":[8.280046,46.118286],"type":"Point"}
}