{
  "type": "Feature",
  "properties": {
    "iso:country":"IT",
    "sg:address":"30123 Venezia",
    "sg:city":"Dorsoduro",
    "sg:classifiers":[
        {
            "category":"Travel",
            "subcategory":"Hotels & Motels",
            "type":"Entertainment"
        }
    ],
    "sg:phone":"+39 041 710896",
    "sg:postcode":"30123",
    "sg:province":"Venezia",
    "sg:tags":[
        "hotels",
        "facility"
    ],
    "wof:name":"Tiziano Snc Di Cristante Nicola & C.",
    "wof:placetype":"venue"
},
  "geometry": {"coordinates":[12.325772,45.435734],"type":"Point"}
}