{
  "type": "Feature",
  "properties": {
    "iso:country":"IT",
    "sg:address":"95018 Riposto",
    "sg:city":"Riposto",
    "sg:orig_category":"Orologeria. Shopping",
    "sg:phone":"+39 095 939946",
    "sg:postcode":"95018",
    "sg:province":"Catania",
    "wof:name":"Cosentino Gioielli Snc Dei Fratelli Sergio E Tullio",
    "wof:placetype":"venue"
},
  "geometry": {"coordinates":[15.049281,37.518906],"type":"Point"}
}