{
  "type": "Feature",
  "properties": {
    "iso:country":"IT",
    "sg:address":"Via Piave 61 31010 Cimadolmo",
    "sg:city":"Cimadolmo",
    "sg:classifiers":[
        {
            "category":"Home & Garden",
            "subcategory":"Hardware",
            "type":"Retail Goods"
        }
    ],
    "sg:phone":"+39 0422 748083",
    "sg:postcode":"31010",
    "sg:province":"Treviso",
    "sg:tags":[
        "small",
        "ironware",
        "item"
    ],
    "wof:name":"New-mec S.r.l.",
    "wof:placetype":"venue"
},
  "geometry": {"coordinates":[12.414665,45.714027],"type":"Point"}
}