{
  "type": "Feature",
  "properties": {
    "addr:full":"55045 Pietrasanta Pietrasanta Lucca 55045",
    "addr:postcode":"55045;55045",
    "iso:country":"IT",
    "sg:address":"55045 Pietrasanta",
    "sg:city":"Pietrasanta",
    "sg:orig_category":"Non-classified Establishments",
    "sg:phone":"+39 0584 742597",
    "sg:postcode":"55045",
    "sg:province":"Lucca",
    "sg:website":"http://www.lapiramidearredamenti.it",
    "wof:name":"Arredamenti La Piramide Di Landi Roberto",
    "wof:placetype":"venue"
},
  "geometry": {"coordinates":[10.211808,43.970535],"type":"Point"}
}