{
  "type": "Feature",
  "properties": {
    "iso:country":"IT",
    "sg:address":"10153 Torino",
    "sg:city":"Torino",
    "sg:orig_category":"Macchine, Impianti Ed Attrezzature Per Abbigliamento E Pelletterie",
    "sg:phone":"+39 011 882961",
    "sg:postcode":"10153",
    "sg:province":"Torino",
    "wof:name":"T.t.t. Ricambi Telai Tessili Torino",
    "wof:placetype":"venue"
},
  "geometry": {"coordinates":[7.710384,45.072193],"type":"Point"}
}