{
  "type": "Feature",
  "properties": {
    "addr:full":"4, Via S. Francesco 20050 Sovico Sovico Milano 20050",
    "addr:postcode":"20050;20050",
    "addr:street":"Via S. Francesco",
    "iso:country":"IT",
    "sg:address":"4, Via S. Francesco 20050 Sovico",
    "sg:city":"Sovico",
    "sg:classifiers":[
        {
            "category":"Shopping",
            "type":"Retail Goods"
        }
    ],
    "sg:phone":"+39 039 201 1571",
    "sg:postcode":"20050",
    "sg:province":"Milano",
    "sg:tags":[
        "finished",
        "-",
        "metallic"
    ],
    "wof:name":"La Esakon (s.r.l.)",
    "wof:placetype":"venue"
},
  "geometry": {"coordinates":[9.1881408691,45.4636878967],"type":"Point"}
}