{
  "type": "Feature",
  "properties": {
    "addr:full":"7, Via Pagani Giuseppe 21047 Saronno Saronno Varese 21047",
    "addr:postcode":"21047;21047",
    "addr:street":"Via Pagani Giuseppe",
    "iso:country":"IT",
    "sg:address":"7, Via Pagani Giuseppe 21047 Saronno",
    "sg:city":"Saronno",
    "sg:classifiers":[
        {
            "category":"Manufacturing",
            "subcategory":"Paper Products",
            "type":"Manufacturing & Wholesale Goods"
        }
    ],
    "sg:phone":"+39 02 9670 0839",
    "sg:postcode":"21047",
    "sg:province":"Varese",
    "sg:tags":[
        "cardboard"
    ],
    "wof:name":"Rossella Etichette (s.r.l.)",
    "wof:placetype":"venue"
},
  "geometry": {"coordinates":[8.8263845444,45.8176040649],"type":"Point"}
}