{
  "type": "Feature",
  "properties": {
    "addr:full":"39, Via Zanardelli Giuseppe 25063 Gardone Val Trompia Gardone Val Trompia Brescia 25063",
    "addr:postcode":"25063;25063",
    "addr:street":"Via Zanardelli Giuseppe",
    "iso:country":"IT",
    "sg:address":"39, Via Zanardelli Giuseppe 25063 Gardone Val Trompia",
    "sg:city":"Gardone Val Trompia",
    "sg:classifiers":[
        {
            "category":"Sports & Exercise",
            "subcategory":"Playing Field",
            "type":"Entertainment"
        }
    ],
    "sg:phone":"+39 030 891 2161",
    "sg:postcode":"25063",
    "sg:province":"Brescia",
    "sg:tags":[
        "game"
    ],
    "wof:name":"Zoli Antonio (s.p.a.)",
    "wof:placetype":"venue"
},
  "geometry": {"coordinates":[10.222958,45.539829],"type":"Point"}
}