{
  "type": "Feature",
  "properties": {
    "iso:country":"IT",
    "sg:address":"16137 Genova",
    "sg:city":"Genova",
    "sg:orig_category":"Automobili E Mezzi Di Trasporto",
    "sg:phone":"+39 010 846 1423",
    "sg:postcode":"16137",
    "sg:province":"Genova",
    "wof:name":"Catturani Francesco",
    "wof:placetype":"venue"
},
  "geometry": {"coordinates":[8.951253,44.409824],"type":"Point"}
}