{
  "type": "Feature",
  "properties": {
    "iso:country":"IT",
    "sg:address":"04100 Latina",
    "sg:city":"Latina",
    "sg:orig_category":"Bigiotteria - Produzione E Ingrosso",
    "sg:phone":"+39 0773 693197",
    "sg:postcode":"04100",
    "sg:province":"Latina",
    "wof:name":"Distribuzione Girardi Di Di Martino Filomena",
    "wof:placetype":"venue"
},
  "geometry": {"coordinates":[12.945737,41.537693],"type":"Point"}
}