{
  "type": "Feature",
  "properties": {
    "addr:full":"97/2, Via Stalingrado 40128 Bologna Bologna Bologna 40128",
    "addr:housenumber":"97 / 2",
    "addr:postcode":"40128;40128",
    "addr:street":"Via Stalingrado",
    "iso:country":"IT",
    "sg:address":"97/2, Via Stalingrado 40128 Bologna",
    "sg:city":"Bologna",
    "sg:classifiers":[
        {
            "category":"Utilities",
            "subcategory":"Telephone",
            "type":"Services"
        }
    ],
    "sg:phone":"+39 051 638 8809",
    "sg:postcode":"40128",
    "sg:province":"Bologna",
    "sg:tags":[
        "telecommunication"
    ],
    "wof:name":"Rete 7 Spa",
    "wof:placetype":"venue"
},
  "geometry": {"coordinates":[11.359689,44.51614],"type":"Point"}
}