{
  "type": "Feature",
  "properties": {
    "iso:country":"IT",
    "sg:address":"10036 Settimo Torinese",
    "sg:city":"Settimo Torinese",
    "sg:orig_category":"Macchine, Impianti E Forniture Per Industria Grafica, Cartaria E Cartotecnica. Prodotti Chimici Secondari",
    "sg:phone":"+39 011 800 5570",
    "sg:postcode":"10036",
    "sg:province":"Torino",
    "sg:website":"http://www.marking.it",
    "wof:name":"Marking Products Srl",
    "wof:placetype":"venue"
},
  "geometry": {"coordinates":[7.747465,45.148266],"type":"Point"}
}