{
  "type": "Feature",
  "properties": {
    "iso:country":"IT",
    "sg:address":"Corso Della Vittoria 1241 21042 Caronno Pertusella",
    "sg:city":"Caronno Pertusella",
    "sg:classifiers":[
        {
            "category":"Farming",
            "subcategory":"Fish & Marine Products",
            "type":"Manufacturing & Wholesale Goods"
        }
    ],
    "sg:phone":"+39 02 966 5111",
    "sg:postcode":"21042",
    "sg:province":"Varese",
    "sg:tags":[
        "technical",
        "rubber",
        "soft",
        "us"
    ],
    "sg:website":"www.mgmgomma.com",
    "wof:name":"M.g.m. Srl",
    "wof:placetype":"venue"
},
  "geometry": {"coordinates":[9.040478,45.605247],"type":"Point"}
}