{
  "type": "Feature",
  "properties": {
    "iso:country":"IT",
    "sg:address":"6, Viale Ranzoni Daniele 20149 Milano",
    "sg:city":"Milano",
    "sg:classifiers":[
        {
            "category":"Shopping",
            "subcategory":"Jewelry",
            "type":"Retail Goods"
        }
    ],
    "sg:phone":"+39 390 243 6224",
    "sg:postcode":"20149",
    "sg:province":"Milano",
    "sg:tags":[
        "jewellery"
    ],
    "wof:name":"Stefal Srl",
    "wof:placetype":"venue"
},
  "geometry": {"coordinates":[9.145852,45.468117],"type":"Point"}
}