{
  "type": "Feature",
  "properties": {
    "addr:full":"1, Viale Dell' Artigianato 36030 San Vito Di Leguzzano San Vito di Leguzzano Vicenza 36030",
    "addr:postcode":"36030;36030",
    "addr:street":"Viale Dell ' Artigianato",
    "iso:country":"IT",
    "sg:address":"1, Viale Dell' Artigianato 36030 San Vito Di Leguzzano",
    "sg:city":"San Vito di Leguzzano",
    "sg:classifiers":[
        {
            "category":"Shopping",
            "subcategory":"Stationery & Office Supplies",
            "type":"Retail Goods"
        }
    ],
    "sg:phone":"+39 0445 519077",
    "sg:postcode":"36030",
    "sg:province":"Vicenza",
    "sg:tags":[
        "professional"
    ],
    "wof:name":"Delta Arredamenti (s.r.l.)",
    "wof:placetype":"venue"
},
  "geometry": {"coordinates":[11.3995733261,45.6851501465],"type":"Point"}
}