{
  "type": "Feature",
  "properties": {
    "addr:full":"7, Via Allende S. 40065 Pianoro Pianoro Bologna 40065",
    "addr:postcode":"40065;40065",
    "addr:street":"Via Allende S.",
    "iso:country":"IT",
    "sg:address":"7, Via Allende S. 40065 Pianoro",
    "sg:city":"Pianoro",
    "sg:classifiers":[
        {
            "category":"Manufacturing",
            "subcategory":"Paper Products",
            "type":"Manufacturing & Wholesale Goods"
        }
    ],
    "sg:phone":"+39 39051777544",
    "sg:postcode":"40065",
    "sg:province":"Bologna",
    "sg:tags":[
        "cardboard"
    ],
    "wof:name":"M.g. (s.p.a.)",
    "wof:placetype":"venue"
},
  "geometry": {"coordinates":[11.3423128128,44.4021949768],"type":"Point"}
}