{
  "type": "Feature",
  "properties": {
    "iso:country":"IT",
    "sg:address":"Via Galvani 23 52100 Arezzo",
    "sg:city":"Arezzo",
    "sg:classifiers":[
        {
            "category":"Shopping",
            "subcategory":"Baby Store",
            "type":"Retail Goods"
        }
    ],
    "sg:phone":"+39 0575 984004",
    "sg:postcode":"52100",
    "sg:province":"Arezzo",
    "sg:tags":[
        "clothing"
    ],
    "wof:name":"Padelli & Scolari Srl",
    "wof:placetype":"venue"
},
  "geometry": {"coordinates":[11.863062,43.471203],"type":"Point"}
}