{
  "type": "Feature",
  "properties": {
    "iso:country":"IT",
    "sg:address":"Via Dell' Olmo 7 36055 Nove",
    "sg:city":"Nove",
    "sg:classifiers":[
        {
            "category":"Professional",
            "subcategory":"Business Services",
            "type":"Services"
        }
    ],
    "sg:phone":"+39 0424 597400",
    "sg:postcode":"36055",
    "sg:province":"Vicenza",
    "sg:tags":[
        "industrial",
        "export"
    ],
    "sg:website":"www.stalam.com",
    "wof:name":"Stalam S.p.a.",
    "wof:placetype":"venue"
},
  "geometry": {"coordinates":[11.672338,45.709522],"type":"Point"}
}