{
  "type": "Feature",
  "properties": {
    "iso:country":"IT",
    "sg:address":"33100 Udine",
    "sg:city":"Udine",
    "sg:classifiers":[
        {
            "category":"Manufacturing",
            "subcategory":"Paper Products",
            "type":"Manufacturing & Wholesale Goods"
        }
    ],
    "sg:phone":"+39 0432 546996",
    "sg:postcode":"33100",
    "sg:province":"Udine",
    "sg:tags":[
        "finished",
        "products",
        "printed",
        "supply"
    ],
    "wof:name":"Gruppo Emporio Grafico Srl",
    "wof:placetype":"venue"
},
  "geometry": {"coordinates":[13.2218818665,46.0728645325],"type":"Point"}
}