{
  "type": "Feature",
  "properties": {
    "iso:country":"IT",
    "sg:address":"00019 Tivoli",
    "sg:city":"Tivoli",
    "sg:orig_category":"Elettronica Professionale E Di Consumo. Musica. Accessori Dei Mezzi Di Trasporto",
    "sg:phone":"+39 0774 531829",
    "sg:postcode":"00019",
    "sg:province":"Roma",
    "wof:name":"Tacconelli Luciano",
    "wof:placetype":"venue"
},
  "geometry": {"coordinates":[12.764785,41.951664],"type":"Point"}
}