{
  "type": "Feature",
  "properties": {
    "iso:country":"IT",
    "sg:address":"20016 Pero",
    "sg:city":"Pero",
    "sg:orig_category":"Ricambi E Componenti Dei Mezzi Di Trasporto",
    "sg:phone":"+39 02 3810 0066",
    "sg:postcode":"20016",
    "sg:province":"Milano",
    "wof:name":"Bracchi Ruote S.r.l.",
    "wof:placetype":"venue"
},
  "geometry": {"coordinates":[9.075945,45.503326],"type":"Point"}
}