{
  "type": "Feature",
  "properties": {
    "addr:full":"66020 San Giovanni Teatino San Giovanni Teatino Chieti 66020",
    "addr:housenumber":"66020",
    "addr:postcode":"66020",
    "addr:street":"San",
    "iso:country":"IT",
    "sg:address":"66020 San Giovanni Teatino",
    "sg:city":"San Giovanni Teatino",
    "sg:orig_category":"Prodotti Di Base E Forniture Per Industria Alimentare E Bevande. Carta, Cartone E Prodotti Primari. Forniture Per Attivita' Commerciali Ed Artigianali",
    "sg:phone":"+39 085 446 0971",
    "sg:postcode":"66020",
    "sg:province":"Chieti",
    "wof:name":"Eurocarta S.a.s. Di Masciovecchio Luciano & C.",
    "wof:placetype":"venue"
},
  "geometry": {"coordinates":[14.1768264771,42.4160919189],"type":"Point"}
}