{
  "type": "Feature",
  "properties": {
    "iso:country":"IT",
    "sg:address":"10095 Grugliasco",
    "sg:city":"Grugliasco",
    "sg:orig_category":"Motori Ed Organi Di Trasmissione",
    "sg:phone":"+39 011 311 0311",
    "sg:postcode":"10095",
    "sg:province":"Torino",
    "wof:name":"Ca. Mor Di Cambareri D. E Moretti M. & C. S.a.s.",
    "wof:placetype":"venue"
},
  "geometry": {"coordinates":[7.6197195053,45.0453147888],"type":"Point"}
}