{
  "type": "Feature",
  "properties": {
    "addr:full":"16030 Casarza Ligure Casarza Ligure Genova 16030",
    "addr:housenumber":"16030",
    "addr:postcode":"16030",
    "addr:street":"Casarza Ligure",
    "iso:country":"IT",
    "sg:address":"16030 Casarza Ligure",
    "sg:city":"Casarza Ligure",
    "sg:orig_category":"Sport - Articoli E Forniture",
    "sg:phone":"+39 0185 46971",
    "sg:postcode":"16030",
    "sg:province":"Genova",
    "wof:name":"Scubapro Europe Srl",
    "wof:placetype":"venue"
},
  "geometry": {"coordinates":[9.456502,44.271893],"type":"Point"}
}