{
  "type": "Feature",
  "properties": {
    "iso:country":"IT",
    "sg:address":"7 Piazza Silvabella, 27036 Mortara",
    "sg:city":"Mortara",
    "sg:classifiers":[
        {
            "category":"Banks & Credit Unions",
            "subcategory":"Financial Services",
            "type":"Services"
        }
    ],
    "sg:phone":"+39 39038493293",
    "sg:postcode":"27036",
    "sg:province":"Pavia",
    "sg:tags":[
        "banking",
        "finance",
        "insurance"
    ],
    "wof:name":"Organizzazione Leasing (srl)",
    "wof:placetype":"venue"
},
  "geometry": {"coordinates":[8.7395792007,45.2525062561],"type":"Point"}
}