{
  "type": "Feature",
  "properties": {
    "addr:full":"14017 Valfenera Valfenera Asti 14017",
    "addr:postcode":"14017;14017",
    "iso:country":"IT",
    "sg:address":"14017 Valfenera",
    "sg:city":"Valfenera",
    "sg:orig_category":"Prodotti Alimentari",
    "sg:phone":"+39 0141 939864",
    "sg:postcode":"14017",
    "sg:province":"Asti",
    "wof:name":"Di Francescantonio Andrea",
    "wof:placetype":"venue"
},
  "geometry": {"coordinates":[7.9649682045,44.8966712952],"type":"Point"}
}