{
  "type": "Feature",
  "properties": {
    "iso:country":"IT",
    "sg:address":"20035 Lissone",
    "sg:city":"Lissone",
    "sg:classifiers":[
        {
            "category":"Bars & Pubs",
            "subcategory":"Champagne Bar",
            "type":"Food & Drink"
        }
    ],
    "sg:phone":"+39 039 214 5303",
    "sg:postcode":"20035",
    "sg:province":"Milano",
    "sg:tags":[
        "caffe'",
        "e"
    ],
    "wof:name":"Famar Snc Di Maristella Arosio E Fabio Limonta",
    "wof:placetype":"venue"
},
  "geometry": {"coordinates":[9.240172,45.62035],"type":"Point"}
}