{
  "type": "Feature",
  "properties": {
    "iso:country":"IT",
    "sg:address":"20063 Cernusco Sul Naviglio",
    "sg:city":"Cernusco sul Naviglio",
    "sg:orig_category":"Termotecnica E Riscaldamento, Apparecchiature E Servizi",
    "sg:phone":"+39 02 924 1176",
    "sg:postcode":"20063",
    "sg:province":"Milano",
    "wof:name":"Termo Scambio Snc Di Ratti Gaetano E Figlio",
    "wof:placetype":"venue"
},
  "geometry": {"coordinates":[9.361538,45.52615],"type":"Point"}
}