{
  "type": "Feature",
  "properties": {
    "addr:full":"42, Via Andrea Palladio 35010 San Giorgio In Bosco San Giorgio in Bosco Padova 35010",
    "addr:postcode":"35010;in bosco;35010",
    "addr:street":"Via Andrea Palladio",
    "iso:country":"IT",
    "sg:address":"42, Via Andrea Palladio 35010 San Giorgio In Bosco",
    "sg:city":"San Giorgio in Bosco",
    "sg:classifiers":[
        {
            "category":"Manufacturing",
            "subcategory":"Rubber & Plastics",
            "type":"Manufacturing & Wholesale Goods"
        }
    ],
    "sg:phone":"+39 049 945 0457",
    "sg:postcode":"35010",
    "sg:province":"Padova",
    "wof:name":"G.m.p. Engineering S.r.l.",
    "wof:placetype":"venue"
},
  "geometry": {"coordinates":[11.8199872971,45.5657348633],"type":"Point"}
}