{
  "type": "Feature",
  "properties": {
    "iso:country":"IT",
    "sg:address":"26 Via S. Teresa, 10121 Torino",
    "sg:city":"Torino",
    "sg:classifiers":[
        {
            "category":"Banks & Credit Unions",
            "subcategory":"Financial Services",
            "type":"Services"
        }
    ],
    "sg:phone":"+39 011 516 0111",
    "sg:postcode":"10121",
    "sg:province":"Torino",
    "sg:tags":[
        "banking",
        "finance",
        "insurance"
    ],
    "wof:name":"Fida Sim Spa",
    "wof:placetype":"venue"
},
  "geometry": {"coordinates":[7.5796356201,45.0229988098],"type":"Point"}
}