{
  "type": "Feature",
  "properties": {
    "iso:country":"IT",
    "sg:address":"22070 Grandate",
    "sg:city":"Grandate",
    "sg:orig_category":"Articoli Per Neonati E Bambini",
    "sg:phone":"+39 031 382111",
    "sg:postcode":"22070",
    "sg:province":"Como",
    "sg:website":"http://www.artsana.com",
    "wof:name":"Artsana Spa",
    "wof:placetype":"venue"
},
  "geometry": {"coordinates":[9.061914,45.766594],"type":"Point"}
}