{
  "type": "Feature",
  "properties": {
    "iso:country":"IT",
    "sg:address":"30030 Olmo",
    "sg:city":"Olmo",
    "sg:orig_category":"Lavorazioni Metalli, Stampaggio E Saldatura",
    "sg:phone":"+39 041 546 0233",
    "sg:postcode":"30030",
    "sg:province":"Venezia",
    "wof:name":"Annoe' Michele",
    "wof:placetype":"venue"
},
  "geometry": {"coordinates":[12.187868,45.512836],"type":"Point"}
}