{
  "type": "Feature",
  "properties": {
    "addr:full":"41037 Mirandola Mirandola Modena 41037",
    "addr:postcode":"41037;41037",
    "iso:country":"IT",
    "sg:address":"41037 Mirandola",
    "sg:city":"Mirandola",
    "sg:orig_category":"Servizi E Lavori Per Ecologia E Smaltimento Rifiuti. Servizi Ausiliari Di Sorveglianza, Manutenzione E Pulizia",
    "sg:phone":"+39 0535 27191",
    "sg:postcode":"41037",
    "sg:province":"Modena",
    "sg:website":"http://www.arcanet.it",
    "wof:name":"Mivebo Soc.coop.r.l.",
    "wof:placetype":"venue"
},
  "geometry": {"coordinates":[10.99646,44.892437],"type":"Point"}
}