{
  "type": "Feature",
  "properties": {
    "iso:country":"IT",
    "sg:address":"Via Ortica 6 20134 Milano",
    "sg:city":"Milano",
    "sg:classifiers":[
        {
            "category":"Manufacturing",
            "subcategory":"Tools & Machinery",
            "type":"Manufacturing & Wholesale Goods"
        }
    ],
    "sg:phone":"+39 02 7611 0157",
    "sg:postcode":"20134",
    "sg:province":"Milano",
    "sg:tags":[
        "pump",
        "seal",
        "mechanical"
    ],
    "sg:website":"www.roten.it",
    "wof:name":"Roten Srl",
    "wof:placetype":"venue"
},
  "geometry": {"coordinates":[9.22013,45.487114],"type":"Point"}
}