{
  "type": "Feature",
  "properties": {
    "addr:full":"46030 Pomponesco Pomponesco Mantova 46030",
    "addr:postcode":"46030;46030",
    "iso:country":"IT",
    "sg:address":"46030 Pomponesco",
    "sg:city":"Pomponesco",
    "sg:orig_category":"Accessori Dei Mezzi Di Trasporto",
    "sg:postcode":"46030",
    "sg:province":"Mantova",
    "wof:name":"Autotime (s.r.l.)",
    "wof:placetype":"venue"
},
  "geometry": {"coordinates":[10.580061,44.933006],"type":"Point"}
}