{
  "type": "Feature",
  "properties": {
    "addr:full":"Via Kennedy 87055 San Giovanni In Fiore San Giovanni in Fiore Cosenza 87055",
    "addr:postcode":"87055;87055",
    "addr:street":"Via Kennedy",
    "iso:country":"IT",
    "sg:address":"Via Kennedy 87055 San Giovanni In Fiore",
    "sg:city":"San Giovanni in Fiore",
    "sg:classifiers":[
        {
            "category":"Building & Trades",
            "subcategory":"Construction",
            "type":"Services"
        }
    ],
    "sg:phone":"+39 0984 970092",
    "sg:postcode":"87055",
    "sg:province":"Cosenza",
    "sg:tags":[
        "work",
        "public"
    ],
    "wof:name":"Luchetta Domenico",
    "wof:placetype":"venue"
},
  "geometry": {"coordinates":[16.69206,39.263412],"type":"Point"}
}