{
  "type": "Feature",
  "properties": {
    "addr:full":"74100 Taranto Taranto Taranto 74100",
    "addr:postcode":"74100;74100",
    "iso:country":"IT",
    "sg:address":"74100 Taranto",
    "sg:city":"Taranto",
    "sg:orig_category":"Abbigliamento Esterno, Maglierie E Pelliccerie. Calzature, Pelletterie E Pelli",
    "sg:phone":"+39 099 459 3881",
    "sg:postcode":"74100",
    "sg:province":"Taranto",
    "wof:name":"Imperatrice Di Rosa Fumarola",
    "wof:placetype":"venue"
},
  "geometry": {"coordinates":[17.240322,40.473591],"type":"Point"}
}