{
  "type": "Feature",
  "properties": {
    "iso:country":"IT",
    "sg:address":"Via Marconi 41 20089 Rozzano",
    "sg:city":"Rozzano",
    "sg:classifiers":[
        {
            "category":"Manufacturing",
            "subcategory":"Rubber & Plastics",
            "type":"Manufacturing & Wholesale Goods"
        }
    ],
    "sg:phone":"+39 02 5750 1557",
    "sg:postcode":"20089",
    "sg:province":"Milano",
    "sg:tags":[
        "overflow",
        "valve",
        "safety",
        "valves"
    ],
    "sg:website":"www.nuovacoi.it",
    "wof:name":"Nuova Coi S.r.l.",
    "wof:placetype":"venue"
},
  "geometry": {"coordinates":[9.168921,45.377979],"type":"Point"}
}