{
  "type": "Feature",
  "properties": {
    "addr:full":"Via Mazzini 14 21040 Oggiona Con Santo Stefano Oggiona Varese 21040",
    "addr:housenumber":"14",
    "addr:postcode":"21040;21040",
    "addr:street":"Via Mazzini",
    "iso:country":"IT",
    "sg:address":"Via Mazzini 14 21040 Oggiona Con Santo Stefano",
    "sg:city":"Oggiona",
    "sg:classifiers":[
        {
            "category":"Shopping",
            "subcategory":"Crafts & Fabrics",
            "type":"Retail Goods"
        }
    ],
    "sg:phone":"+39 0331 217225",
    "sg:postcode":"21040",
    "sg:province":"Varese",
    "sg:tags":[
        "jacquard"
    ],
    "sg:website":"www.santostefanoarno.it",
    "wof:name":"Manifattura Di S. Stefano Arno Srl",
    "wof:placetype":"venue"
},
  "geometry": {"coordinates":[8.80333,45.70232],"type":"Point"}
}