{
  "type": "Feature",
  "properties": {
    "iso:country":"IT",
    "sg:address":"57014 Collesalvetti",
    "sg:city":"Collesalvetti",
    "sg:orig_category":"Ceramiche Per Pavimenti E Rivestimenti - Produzione E Ingrosso",
    "sg:phone":"+39 0586 963907",
    "sg:postcode":"57014",
    "sg:province":"Livorno",
    "wof:name":"Stella Ceramiche Di Veroni Alessio",
    "wof:placetype":"venue"
},
  "geometry": {"coordinates":[10.428418,43.590744],"type":"Point"}
}