{
  "type": "Feature",
  "properties": {
    "addr:full":"00185 Roma Roma Roma 00185",
    "addr:postcode":"00185;00185",
    "iso:country":"IT",
    "sg:address":"00185 Roma",
    "sg:city":"Roma",
    "sg:orig_category":"Cinematografia E Radiotelevisione. Forniture Per Il Settore Dello Spettacolo",
    "sg:phone":"+39 06 446 2662",
    "sg:postcode":"00185",
    "sg:province":"Roma",
    "wof:name":"Sarandrea Bruno",
    "wof:placetype":"venue"
},
  "geometry": {"coordinates":[12.451303,41.852913],"type":"Point"}
}