{
  "type": "Feature",
  "properties": {
    "addr:full":"Piazza Iv Novembre; Pozzolengo; 25010 Pozzolengo Brescia 25010",
    "addr:postcode":"25010;25010",
    "addr:street":"Piazza Iv Novembre",
    "iso:country":"IT",
    "sg:address":"Piazza Iv Novembre; Pozzolengo; 25010",
    "sg:city":"Pozzolengo",
    "sg:classifiers":[
        {
            "category":"Banks & Credit Unions",
            "subcategory":"Bank",
            "type":"Services"
        }
    ],
    "sg:phone":"+39 030 918133",
    "sg:postcode":"25010",
    "sg:province":"Brescia",
    "wof:name":"Banca Agricola Mantovana",
    "wof:placetype":"venue"
},
  "geometry": {"coordinates":[10.627185,45.403179],"type":"Point"}
}