{
  "type": "Feature",
  "properties": {
    "iso:country":"IT",
    "sg:address":"727, C. S. Giovanni 80146 Napoli",
    "sg:city":"Napoli",
    "sg:classifiers":[
        {
            "category":"Manufacturing",
            "subcategory":"Paper Products",
            "type":"Manufacturing & Wholesale Goods"
        }
    ],
    "sg:phone":"+39 39081482028",
    "sg:postcode":"80146",
    "sg:province":"Napoli",
    "sg:tags":[
        "cardboard"
    ],
    "sg:website":"http://www.graficheansa.com",
    "wof:name":"Grafiche An.sa Srl",
    "wof:placetype":"venue"
},
  "geometry": {"coordinates":[14.3154239655,40.8268165588],"type":"Point"}
}