{
  "type": "Feature",
  "properties": {
    "iso:country":"IT",
    "sg:address":"20154 Milano",
    "sg:city":"Milano",
    "sg:orig_category":"Servizi Al Turismo. Ambasciate Ed Enti Internazionali",
    "sg:phone":"+39 02 655 2351",
    "sg:postcode":"20154",
    "sg:province":"Milano",
    "wof:name":"Ambasciata Della Repubblica Popolare Cinese Presso L'italia",
    "wof:placetype":"venue"
},
  "geometry": {"coordinates":[9.183805,45.485031],"type":"Point"}
}