{
  "type": "Feature",
  "properties": {
    "iso:country":"IT",
    "sg:address":"10092 Borgaretto",
    "sg:city":"Borgaretto",
    "sg:orig_category":"Sport - Articoli E Forniture",
    "sg:phone":"+39 011 358 3227",
    "sg:postcode":"10092",
    "sg:province":"Torino",
    "wof:name":"Terenzi Piero",
    "wof:placetype":"venue"
},
  "geometry": {"coordinates":[7.6042,45.00174],"type":"Point"}
}