{
  "type": "Feature",
  "properties": {
    "iso:country":"IT",
    "sg:address":"70059 Trani",
    "sg:city":"Trani",
    "sg:orig_category":"Arredamenti - Produzione E Ingrosso",
    "sg:phone":"+39 0883 587828",
    "sg:postcode":"70059",
    "sg:province":"Bari",
    "wof:name":"Modi Di Paolo & Ippolita Di Cugno Snc",
    "wof:placetype":"venue"
},
  "geometry": {"coordinates":[16.531048,41.220936],"type":"Point"}
}