{
  "type": "Feature",
  "properties": {
    "addr:full":"00165 Roma Roma Roma 00165",
    "addr:postcode":"00165;00165",
    "iso:country":"IT",
    "sg:address":"00165 Roma",
    "sg:city":"Roma",
    "sg:orig_category":"Fodere E Tappeti Per Autoveicoli - Produzione E Ingrosso",
    "sg:phone":"+39 06 636823",
    "sg:postcode":"00165",
    "sg:province":"Roma",
    "wof:name":"Cds Arredamento Per Auto Di Stefano Crocini",
    "wof:placetype":"venue"
},
  "geometry": {"coordinates":[12.4409313202,41.8949813843],"type":"Point"}
}