{
  "type": "Feature",
  "properties": {
    "iso:country":"IT",
    "sg:address":"46040 Gazoldo Degli Ippoliti",
    "sg:city":"Gazoldo degli Ippoliti",
    "sg:orig_category":"Arredo Cucina Ed Elettrodomestici. Elettrodomestici",
    "sg:phone":"+39 0376 657133",
    "sg:postcode":"46040",
    "sg:province":"Mantova",
    "wof:name":"Bergamini Agostino",
    "wof:placetype":"venue"
},
  "geometry": {"coordinates":[10.580482,45.20126],"type":"Point"}
}