{
  "type": "Feature",
  "properties": {
    "addr:full":"65122 Pescara Pescara Pescara 65122",
    "addr:postcode":"65122;65122",
    "iso:country":"IT",
    "sg:address":"65122 Pescara",
    "sg:city":"Pescara",
    "sg:orig_category":"Forniture Per Edilizia E Lavori Pubblici",
    "sg:phone":"+39 085 421 1370",
    "sg:postcode":"65122",
    "sg:province":"Pescara",
    "wof:name":"Eco. Saves Srl",
    "wof:placetype":"venue"
},
  "geometry": {"coordinates":[14.2090415955,42.4719848633],"type":"Point"}
}