{
  "type": "Feature",
  "properties": {
    "iso:country":"IT",
    "sg:address":"22100 Como",
    "sg:city":"Como",
    "sg:orig_category":"Scuole E Servizi Scolastici. Servizi Per Lo Sport E Il Tempo Libero",
    "sg:phone":"+39 031 242656",
    "sg:postcode":"22100",
    "sg:province":"Como",
    "wof:name":"Stiil European Academy Srl",
    "wof:placetype":"venue"
},
  "geometry": {"coordinates":[9.07783,45.811813],"type":"Point"}
}