{
  "type": "Feature",
  "properties": {
    "addr:full":"36050 Bolzano Vicentino Bolzano Vicentino Vicenza 36050",
    "addr:postcode":"36050;36050",
    "iso:country":"IT",
    "sg:address":"36050 Bolzano Vicentino",
    "sg:city":"Bolzano Vicentino",
    "sg:orig_category":"Cartotecnica E Servizi",
    "sg:phone":"+39 0444 350202",
    "sg:postcode":"36050",
    "sg:province":"Vicenza",
    "wof:name":"Cartotecnica Vittoria Snc",
    "wof:placetype":"venue"
},
  "geometry": {"coordinates":[11.635859,45.602436],"type":"Point"}
}