{
  "type": "Feature",
  "properties": {
    "iso:country":"IT",
    "sg:address":"42017 Novellara",
    "sg:orig_category":"Giochi Per Giardini E Parchi",
    "sg:phone":"+39 0522 653274",
    "sg:postcode":"42017",
    "sg:province":"Reggio Nell'Emilia",
    "wof:name":"Omes Di Bonini & Redeghieri Snc",
    "wof:placetype":"venue"
},
  "geometry": {"coordinates":[10.677843,44.76862],"type":"Point"}
}