{
  "type": "Feature",
  "properties": {
    "iso:country":"IT",
    "sg:address":"2, Via Luigi Galvani 25010 San Zeno Naviglio",
    "sg:city":"San Zeno Naviglio",
    "sg:classifiers":[
        {
            "category":"Manufacturing",
            "subcategory":"Metals",
            "type":"Manufacturing & Wholesale Goods"
        }
    ],
    "sg:phone":"+39 030 353 9386",
    "sg:postcode":"25010",
    "sg:province":"Brescia",
    "sg:tags":[
        "metallurgy",
        "metalworking"
    ],
    "wof:name":"Biemme Utensileria Di Precisione Di Belotti C. Snc",
    "wof:placetype":"venue"
},
  "geometry": {"coordinates":[10.2282924652,45.4991798401],"type":"Point"}
}