{
  "type": "Feature",
  "properties": {
    "addr:full":"31020 Villorba Villorba Treviso 31020",
    "addr:postcode":"31020;31020",
    "iso:country":"IT",
    "sg:address":"31020 Villorba",
    "sg:city":"Villorba",
    "sg:orig_category":"Centri Di Estetica E Cosmesi E Servizi",
    "sg:phone":"+39 0422 608982",
    "sg:postcode":"31020",
    "sg:province":"Treviso",
    "wof:name":"Bobbo Andrea",
    "wof:placetype":"venue"
},
  "geometry": {"coordinates":[12.257892,45.711731],"type":"Point"}
}