{
  "type": "Feature",
  "properties": {
    "iso:country":"IT",
    "sg:address":"12100 Cuneo",
    "sg:city":"Cuneo",
    "sg:orig_category":"Automobili E Mezzi Di Trasporto. Riparazione Dei Mezzi Di Trasporto",
    "sg:phone":"+39 0171 694800",
    "sg:postcode":"12100",
    "sg:province":"Cuneo",
    "wof:name":"M.p. Di Moletti Bruno",
    "wof:placetype":"venue"
},
  "geometry": {"coordinates":[7.546389,44.432663],"type":"Point"}
}