{
  "type": "Feature",
  "properties": {
    "iso:country":"IT",
    "sg:address":"Via Costa Andrea 2 20131 Milano",
    "sg:city":"Milano",
    "sg:classifiers":[
        {
            "category":"Wholesale",
            "subcategory":"Vending Machines",
            "type":"Manufacturing & Wholesale Goods"
        }
    ],
    "sg:phone":"+39 02 2611 0603",
    "sg:postcode":"20131",
    "sg:province":"Milano",
    "sg:tags":[
        "ceramic",
        "processing"
    ],
    "wof:name":"Atlas Trading Company Srl",
    "wof:placetype":"venue"
},
  "geometry": {"coordinates":[9.218261,45.48624],"type":"Point"}
}