{
  "type": "Feature",
  "properties": {
    "addr:full":"Via San Lorenzo 164 Zona Industrial 86100 Campobasso Campobasso Campobasso 86100",
    "addr:housenumber":"164",
    "addr:postcode":"86100;86100",
    "addr:street":"Via San Lorenzo;Zona Industrial",
    "iso:country":"IT",
    "sg:address":"Via San Lorenzo 164 Zona Industrial 86100 Campobasso",
    "sg:city":"Campobasso",
    "sg:orig_category":"Ladies' Knitwear",
    "sg:phone":"+39 0874 482507",
    "sg:postcode":"86100",
    "sg:province":"Campobasso",
    "sg:website":"www.lindamaglieria.com",
    "wof:name":"Magor Srl",
    "wof:placetype":"venue"
},
  "geometry": {"coordinates":[14.664799,41.560085],"type":"Point"}
}