{
  "type": "Feature",
  "properties": {
    "iso:country":"IT",
    "sg:address":"60123 Ancona",
    "sg:city":"Ancona",
    "sg:orig_category":"Orologi - Produzione E Commercio",
    "sg:phone":"+39 071 200523",
    "sg:postcode":"60123",
    "sg:province":"Ancona",
    "wof:name":"Gitre Snc",
    "wof:placetype":"venue"
},
  "geometry": {"coordinates":[13.527785,43.618553],"type":"Point"}
}