{
  "type": "Feature",
  "properties": {
    "iso:country":"IT",
    "sg:address":"00047 Marino",
    "sg:city":"Marino",
    "sg:orig_category":"Servizi E Lavori Per Abbigliamento E Pelletterie",
    "sg:phone":"+39 06 938 8141",
    "sg:postcode":"00047",
    "sg:province":"Roma",
    "wof:name":"Nocenzi Pellicceria",
    "wof:placetype":"venue"
},
  "geometry": {"coordinates":[12.675003,41.772881],"type":"Point"}
}