{
  "type": "Feature",
  "properties": {
    "iso:country":"IT",
    "sg:address":"80059 Torre Del Greco",
    "sg:city":"Torre del Greco",
    "sg:orig_category":"Macchine E Forniture Per Industria Orafa E Per Orologeria",
    "sg:phone":"+39 081 881 2540",
    "sg:postcode":"80059",
    "sg:province":"Napoli",
    "wof:name":"M.d.p.l. Snc Di Mileo Giuseppe E Del Peschio Alessandro",
    "wof:placetype":"venue"
},
  "geometry": {"coordinates":[14.37439,40.791618],"type":"Point"}
}