{
  "type": "Feature",
  "properties": {
    "iso:country":"IT",
    "sg:address":"70, Via Albino Luciani 31043 Fontanelle",
    "sg:city":"Fontanelle",
    "sg:classifiers":[
        {
            "category":"Manufacturing",
            "subcategory":"Wood Products",
            "type":"Manufacturing & Wholesale Goods"
        }
    ],
    "sg:phone":"+39 0422 818111",
    "sg:postcode":"31043",
    "sg:province":"Treviso",
    "sg:tags":[
        "furniture"
    ],
    "wof:name":"A.l.f. Uno S.p.a.",
    "wof:placetype":"venue"
},
  "geometry": {"coordinates":[12.482391,45.84787],"type":"Point"}
}