{
  "type": "Feature",
  "properties": {
    "addr:full":"20084 Lacchiarella Lacchiarella Milano 20084",
    "addr:postcode":"20084;20084",
    "iso:country":"IT",
    "sg:address":"20084 Lacchiarella",
    "sg:city":"Lacchiarella",
    "sg:orig_category":"Petroli, Gas E Combustibili",
    "sg:phone":"+39 02 900171",
    "sg:postcode":"20084",
    "sg:province":"Milano",
    "wof:name":"Sigemi Srl",
    "wof:placetype":"venue"
},
  "geometry": {"coordinates":[9.1484670639,45.3191184998],"type":"Point"}
}