{
  "type": "Feature",
  "properties": {
    "addr:full":"16, Via Colombara 37052 Casaleone Casaleone Verona 37052",
    "addr:postcode":"37052;37052",
    "addr:street":"Via Colombara",
    "iso:country":"IT",
    "sg:address":"16, Via Colombara 37052 Casaleone",
    "sg:city":"Casaleone",
    "sg:classifiers":[
        {
            "category":"Farming",
            "subcategory":"Livestock Farm",
            "type":"Manufacturing & Wholesale Goods"
        }
    ],
    "sg:phone":"+39 0442 331613",
    "sg:postcode":"37052",
    "sg:province":"Verona",
    "sg:tags":[
        "agriculture"
    ],
    "wof:name":"Garden House Di Zago Gianpaolo",
    "wof:placetype":"venue"
},
  "geometry": {"coordinates":[11.196163,45.174278],"type":"Point"}
}