{
  "type": "Feature",
  "properties": {
    "iso:country":"IT",
    "sg:address":"33, Via Casale 43035 Felino",
    "sg:city":"Felino",
    "sg:classifiers":[
        {
            "category":"Food & Beverages",
            "subcategory":"Groceries & Convenience Stores",
            "type":"Retail Goods"
        }
    ],
    "sg:phone":"+39 0521 835401",
    "sg:postcode":"43035",
    "sg:province":"Parma",
    "sg:tags":[
        "product",
        "related"
    ],
    "wof:name":"Casale (s.p.a.)",
    "wof:placetype":"venue"
},
  "geometry": {"coordinates":[10.248008728,44.7211685181],"type":"Point"}
}