{
  "type": "Feature",
  "properties": {
    "addr:full":"Via Livenza 7 65010 Spoltore Spoltore Pescara 65010",
    "addr:housenumber":"7",
    "addr:postcode":"65010;65010",
    "addr:street":"Via Livenza",
    "iso:country":"IT",
    "sg:address":"Via Livenza 7 65010 Spoltore",
    "sg:city":"Spoltore",
    "sg:classifiers":[
        {
            "category":"Transit Center",
            "subcategory":"Freight",
            "type":"Transportation"
        }
    ],
    "sg:phone":"+39 085 497 1121",
    "sg:postcode":"65010",
    "sg:province":"Pescara",
    "sg:tags":[
        "elevator"
    ],
    "wof:name":"O.r.e.m. Spa",
    "wof:placetype":"venue"
},
  "geometry": {"coordinates":[14.1725063324,42.4397239685],"type":"Point"}
}