{
  "type": "Feature",
  "properties": {
    "iso:country":"IT",
    "sg:address":"Via Dante Aleghieri 24040 Stezzano",
    "sg:city":"Stezzano",
    "sg:classifiers":[
        {
            "category":"Wholesale",
            "subcategory":"Construction Materials",
            "type":"Manufacturing & Wholesale Goods"
        }
    ],
    "sg:phone":"+39 035 592548",
    "sg:postcode":"24040",
    "sg:province":"Bergamo",
    "sg:tags":[
        "resistance",
        "welding"
    ],
    "sg:website":"www.anarducci.com",
    "wof:name":"A. Narducci Spa",
    "wof:placetype":"venue"
},
  "geometry": {"coordinates":[9.647341,45.640812],"type":"Point"}
}