{
  "type": "Feature",
  "properties": {
    "iso:country":"IT",
    "sg:address":"10064 Pinerolo",
    "sg:city":"Pinerolo",
    "sg:orig_category":"Termotecnica E Riscaldamento, Apparecchiature E Servizi",
    "sg:phone":"+39 0121 374494",
    "sg:postcode":"10064",
    "sg:province":"Torino",
    "wof:name":"Perotti Remo",
    "wof:placetype":"venue"
},
  "geometry": {"coordinates":[7.329496,44.884693],"type":"Point"}
}