{
  "type": "Feature",
  "properties": {
    "addr:full":"Via Galvana 5 43015 Noceto Noceto Parma 43015",
    "addr:housenumber":"5",
    "addr:postcode":"43015;43015",
    "addr:street":"Via Galvana",
    "iso:country":"IT",
    "sg:address":"Via Galvana 5 43015 Noceto",
    "sg:city":"Noceto",
    "sg:classifiers":[
        {
            "category":"Manufacturing",
            "subcategory":"Rubber & Plastics",
            "type":"Manufacturing & Wholesale Goods"
        }
    ],
    "sg:phone":"+39 0521 628641",
    "sg:postcode":"43015",
    "sg:province":"Parma",
    "sg:tags":[
        "material"
    ],
    "sg:website":"www.resital.it",
    "wof:name":"Resital Srl",
    "wof:placetype":"venue"
},
  "geometry": {"coordinates":[10.1530160904,44.8130149841],"type":"Point"}
}