{
  "type": "Feature",
  "properties": {
    "addr:full":"95123 Catania Catania Catania 95123",
    "addr:postcode":"95123;95123",
    "iso:country":"IT",
    "sg:address":"95123 Catania",
    "sg:city":"Catania",
    "sg:orig_category":"Musica. Shopping",
    "sg:phone":"+39 095 356820",
    "sg:postcode":"95123",
    "sg:province":"Catania",
    "wof:name":"Electronic Sistem Service Di Venturelli Andrea",
    "wof:placetype":"venue"
},
  "geometry": {"coordinates":[15.0559959412,37.5077705383],"type":"Point"}
}