{
  "type": "Feature",
  "properties": {
    "iso:country":"IT",
    "sg:address":"20129 Milano",
    "sg:city":"Milano",
    "sg:orig_category":"Agenzie D'affari E Servizi Commerciali",
    "sg:phone":"+39 02 782571",
    "sg:postcode":"20129",
    "sg:province":"Milano",
    "wof:name":"Locomia S.r.l.",
    "wof:placetype":"venue"
},
  "geometry": {"coordinates":[9.206683,45.470226],"type":"Point"}
}