{
  "type": "Feature",
  "properties": {
    "addr:full":"25030 Roncadelle Roncadelle Brescia 25030",
    "addr:postcode":"25030;25030",
    "iso:country":"IT",
    "sg:address":"25030 Roncadelle",
    "sg:city":"Roncadelle",
    "sg:orig_category":"Prodotti E Manufatti In Gomma",
    "sg:phone":"+39 030 258 5009",
    "sg:postcode":"25030",
    "sg:province":"Brescia",
    "wof:name":"Gomma Service Srl",
    "wof:placetype":"venue"
},
  "geometry": {"coordinates":[10.1587562561,45.5276260376],"type":"Point"}
}