{
  "type": "Feature",
  "properties": {
    "addr:full":"21047 Saronno Saronno Varese 21047",
    "addr:postcode":"21047;21047",
    "iso:country":"IT",
    "sg:address":"21047 Saronno",
    "sg:city":"Saronno",
    "sg:orig_category":"Abbigliamento Esterno, Maglierie E Pelliccerie. Calzature, Pelletterie E Pelli. Sport - Articoli E Forniture",
    "sg:phone":"+39 02 960 6523",
    "sg:postcode":"21047",
    "sg:province":"Varese",
    "wof:name":"I.c.p. Italian Chemical Professional",
    "wof:placetype":"venue"
},
  "geometry": {"coordinates":[9.033545,45.610889],"type":"Point"}
}