{
  "type": "Feature",
  "properties": {
    "addr:full":"47017 Rocca San Casciano Rocca San Casciano Forl\u00ec-Cesena 47017",
    "addr:postcode":"47017;47017",
    "addr:street":"Forli\u0300-Cesena",
    "iso:country":"IT",
    "sg:address":"47017 Rocca San Casciano",
    "sg:city":"Rocca San Casciano",
    "sg:orig_category":"Prodotti Vari In Metallo. Articoli Per Imballaggio E Confezionamento",
    "sg:phone":"+39 0543 960477",
    "sg:postcode":"47017",
    "sg:province":"Forl\u00ec-Cesena",
    "wof:name":"Carrel System S.n.c. Di Ginestri Gian Luca & C.",
    "wof:placetype":"venue"
},
  "geometry": {"coordinates":[11.8140954971,44.0443305969],"type":"Point"}
}