{
  "type": "Feature",
  "properties": {
    "iso:country":"IT",
    "sg:address":"18, Viale Caproni Giovanni 38068 Rovereto",
    "sg:city":"Rovereto",
    "sg:classifiers":[
        {
            "category":"Manufacturing",
            "subcategory":"Tools & Machinery",
            "type":"Manufacturing & Wholesale Goods"
        }
    ],
    "sg:phone":"+39 0464 433330",
    "sg:postcode":"38068",
    "sg:province":"Trento",
    "sg:tags":[
        "environment",
        "equipment",
        "-"
    ],
    "wof:name":"Wegher (s.r.l.)",
    "wof:placetype":"venue"
},
  "geometry": {"coordinates":[11.014523,45.864624],"type":"Point"}
}