{
  "type": "Feature",
  "properties": {
    "addr:full":"11, Via Industria 24050 Orio Al Serio Orio al Serio Bergamo 24050",
    "addr:postcode":"24050;24050",
    "addr:street":"Via Industria",
    "iso:country":"IT",
    "sg:address":"11, Via Industria 24050 Orio Al Serio",
    "sg:city":"Orio al Serio",
    "sg:classifiers":[
        {
            "category":"Manufacturing",
            "subcategory":"Glass & Minerals",
            "type":"Manufacturing & Wholesale Goods"
        }
    ],
    "sg:phone":"+39 39035525188",
    "sg:postcode":"24050",
    "sg:province":"Bergamo",
    "wof:name":"Multiglass (s.r.l.)",
    "wof:placetype":"venue"
},
  "geometry": {"coordinates":[9.706095,45.659386],"type":"Point"}
}