{
  "type": "Feature",
  "properties": {
    "addr:full":"15, Via Zancani Camillo 39100 Bolzano Bolzano Bolzano/Bozen 39100",
    "addr:postcode":"39100;39100",
    "addr:street":"Via Zancani Camillo",
    "iso:country":"IT",
    "sg:address":"15, Via Zancani Camillo 39100 Bolzano",
    "sg:city":"Bolzano",
    "sg:classifiers":[
        {
            "category":"Shopping",
            "subcategory":"Crafts & Fabrics",
            "type":"Retail Goods"
        }
    ],
    "sg:phone":"+39 0471 288034",
    "sg:postcode":"39100",
    "sg:province":"Bolzano/Bozen",
    "sg:tags":[
        "ceramic"
    ],
    "wof:name":"Lazzarini & C. S.r.l.",
    "wof:placetype":"venue"
},
  "geometry": {"coordinates":[11.328239,46.461643],"type":"Point"}
}