{
  "type": "Feature",
  "properties": {
    "iso:country":"IT",
    "sg:address":"24, Via Andorra 35127 Padova",
    "sg:city":"Padova",
    "sg:classifiers":[
        {
            "category":"Communications",
            "subcategory":"Television Station",
            "type":"Services"
        }
    ],
    "sg:phone":"+39 049 870 2083",
    "sg:postcode":"35127",
    "sg:province":"Padova",
    "sg:tags":[
        "audio-visual"
    ],
    "wof:name":"Feel S.r.l.",
    "wof:placetype":"venue"
},
  "geometry": {"coordinates":[11.844167,45.397499],"type":"Point"}
}