{
  "type": "Feature",
  "properties": {
    "iso:country":"IT",
    "sg:address":"18, Via Del Fangario 09122 Cagliari",
    "sg:city":"Cagliari",
    "sg:classifiers":[
        {
            "category":"Farming",
            "subcategory":"Livestock Farm",
            "type":"Manufacturing & Wholesale Goods"
        }
    ],
    "sg:phone":"+39 39070290717",
    "sg:postcode":"09122",
    "sg:province":"Cagliari",
    "sg:tags":[
        "agriculture"
    ],
    "wof:name":"Tuttifrutti S.r.l.",
    "wof:placetype":"venue"
},
  "geometry": {"coordinates":[9.093898,39.243023],"type":"Point"}
}