{
  "type": "Feature",
  "properties": {
    "iso:country":"IT",
    "sg:address":"20067 Tribiano",
    "sg:city":"Tribiano",
    "sg:orig_category":"Metalli E Leghe",
    "sg:phone":"+39 02 906 4701",
    "sg:postcode":"20067",
    "sg:province":"Milano",
    "wof:name":"Dede' Renato",
    "wof:placetype":"venue"
},
  "geometry": {"coordinates":[9.3804931641,45.4163627625],"type":"Point"}
}