{
  "type": "Feature",
  "properties": {
    "addr:full":"81025 Marcianise Marcianise Caserta 81025",
    "addr:postcode":"81025;81025",
    "iso:country":"IT",
    "sg:address":"81025 Marcianise",
    "sg:city":"Marcianise",
    "sg:orig_category":"Servizi E Lavori Industria Delle Materie Plastiche",
    "sg:phone":"+39 0823 821495",
    "sg:postcode":"81025",
    "sg:province":"Caserta",
    "sg:website":"http://www.edilplast.com",
    "wof:name":"Edilplast Srl",
    "wof:placetype":"venue"
},
  "geometry": {"coordinates":[14.297743,41.015236],"type":"Point"}
}