{
  "type": "Feature",
  "properties": {
    "iso:country":"IT",
    "sg:address":"05100 Terni",
    "sg:city":"Terni",
    "sg:orig_category":"Ospedali E Servizi Sanitari",
    "sg:phone":"+39 0744 409500",
    "sg:postcode":"05100",
    "sg:province":"Terni",
    "wof:name":"Paoluzzi Leonardo",
    "wof:placetype":"venue"
},
  "geometry": {"coordinates":[12.649158,42.568142],"type":"Point"}
}