{
  "type": "Feature",
  "properties": {
    "addr:full":"5, Via Dante Alighieri 22030 Montorfano Montorfano Como 22030",
    "addr:postcode":"22030;22030",
    "addr:street":"Via Dante Alighieri",
    "iso:country":"IT",
    "sg:address":"5, Via Dante Alighieri 22030 Montorfano",
    "sg:city":"Montorfano",
    "sg:classifiers":[
        {
            "category":"Manufacturing",
            "subcategory":"Rubber & Plastics",
            "type":"Manufacturing & Wholesale Goods"
        }
    ],
    "sg:phone":"+39 39031553263",
    "sg:postcode":"22030",
    "sg:province":"Como",
    "wof:name":"Larioplast",
    "wof:placetype":"venue"
},
  "geometry": {"coordinates":[9.0854558945,45.8119659424],"type":"Point"}
}