{
  "type": "Feature",
  "properties": {
    "iso:country":"IT",
    "sg:address":"20121 Milano",
    "sg:city":"Milano",
    "sg:orig_category":"Studi E Consulenze Amministrative, Commerciali E Aziendali. Consulenze Tecniche, Amministrative E Perizie",
    "sg:phone":"+39 02 290371",
    "sg:postcode":"20121",
    "sg:province":"Milano",
    "wof:name":"Arthur Andersen Spa",
    "wof:placetype":"venue"
},
  "geometry": {"coordinates":[9.195362,45.475655],"type":"Point"}
}