{
  "type": "Feature",
  "properties": {
    "iso:country":"IT",
    "sg:address":"10091 Alpignano",
    "sg:city":"Alpignano",
    "sg:orig_category":"Abbigliamento Esterno, Maglierie E Pelliccerie. Forniture Per Abbigliamento E Pelletterie",
    "sg:phone":"+39 011 967 7489",
    "sg:postcode":"10091",
    "sg:province":"Torino",
    "wof:name":"Pezzalificio Fea & Furini Snc",
    "wof:placetype":"venue"
},
  "geometry": {"coordinates":[7.523935,45.094307],"type":"Point"}
}