{
  "type": "Feature",
  "properties": {
    "iso:country":"IT",
    "sg:address":"74100 Taranto",
    "sg:city":"Taranto",
    "sg:orig_category":"Servizi Culturali E Per Lo Spettacolo. Servizi Per Lo Sport E Il Tempo Libero. Associazioni Ed Organismi Di Interesse Pubblico",
    "sg:phone":"+39 099 375866",
    "sg:postcode":"74100",
    "sg:province":"Taranto",
    "wof:name":"Terrarte Iniziative Per L'ambiente E La Cultura",
    "wof:placetype":"venue"
},
  "geometry": {"coordinates":[17.25869,40.462708],"type":"Point"}
}