{
  "type": "Feature",
  "properties": {
    "iso:country":"IT",
    "sg:address":"19/2, V. Genova 40139 Bologna",
    "sg:city":"Bologna",
    "sg:classifiers":[
        {
            "category":"Shopping",
            "subcategory":"Clothing, Apparel, & Fashions",
            "type":"Retail Goods"
        }
    ],
    "sg:phone":"+39 051 627 2020",
    "sg:postcode":"40139",
    "sg:province":"Bologna",
    "sg:tags":[
        "clothes"
    ],
    "sg:website":"http://www.sartoriateatralealberani.it",
    "wof:name":"Alberani Sartoria Teatrale",
    "wof:placetype":"venue"
},
  "geometry": {"coordinates":[11.393627,44.472214],"type":"Point"}
}