{
  "type": "Feature",
  "properties": {
    "iso:country":"IT",
    "sg:address":"36, Via Del Santo 98124 Messina",
    "sg:city":"Messina",
    "sg:classifiers":[
        {
            "category":"Professional",
            "subcategory":"Engineering",
            "type":"Services"
        }
    ],
    "sg:phone":"+39 39090695456",
    "sg:postcode":"98124",
    "sg:province":"Messina",
    "sg:tags":[
        "machine",
        "-",
        "mechanical"
    ],
    "wof:name":"Piccola Neon Di Ganfi G. & Lattada M.",
    "wof:placetype":"venue"
},
  "geometry": {"coordinates":[15.515157,38.167107],"type":"Point"}
}