{
  "type": "Feature",
  "properties": {
    "iso:country":"IT",
    "sg:address":"Via Matteotti 8b; Cento; 44042",
    "sg:city":"Cento",
    "sg:classifiers":[
        {
            "category":"Banks & Credit Unions",
            "subcategory":"Bank",
            "type":"Services"
        }
    ],
    "sg:phone":"+39 051 683 3111",
    "sg:postcode":"44042",
    "sg:province":"Ferrara",
    "wof:name":"Cassa Di Risparmio Di Cento Spa",
    "wof:placetype":"venue"
},
  "geometry": {"coordinates":[11.28889,44.728218],"type":"Point"}
}