{
  "type": "Feature",
  "properties": {
    "addr:full":"06034 Foligno Foligno Perugia 06034",
    "addr:postcode":"06034;06034",
    "iso:country":"IT",
    "sg:address":"06034 Foligno",
    "sg:city":"Foligno",
    "sg:orig_category":"Imprese Di Costruzioni Civili Ed Industriali",
    "sg:phone":"+39 0742 391111",
    "sg:postcode":"06034",
    "sg:province":"Perugia",
    "wof:name":"Calcestruzzi Costruzioni Metelli Cav. Luigi",
    "wof:placetype":"venue"
},
  "geometry": {"coordinates":[12.724227,42.926266],"type":"Point"}
}