{
  "type": "Feature",
  "properties": {
    "addr:full":"2, Via Delle Azalee 20090 Buccinasco Buccinasco Milano 20090",
    "addr:postcode":"20090;20090",
    "addr:street":"Via Delle Azalee",
    "iso:country":"IT",
    "sg:address":"2, Via Delle Azalee 20090 Buccinasco",
    "sg:city":"Buccinasco",
    "sg:classifiers":[
        {
            "category":"Utilities",
            "subcategory":"Electric",
            "type":"Services"
        }
    ],
    "sg:phone":"+39 390 248 8551",
    "sg:postcode":"20090",
    "sg:province":"Milano",
    "sg:tags":[
        "component",
        "electronic"
    ],
    "wof:name":"Vlm (s.p.a.)",
    "wof:placetype":"venue"
},
  "geometry": {"coordinates":[9.093089,45.414219],"type":"Point"}
}