{
  "type": "Feature",
  "properties": {
    "addr:full":"07024 La Maddalena La Maddalena Olbia-Tempio 07024",
    "addr:housenumber":"07024",
    "addr:postcode":"07024",
    "addr:street":"La Maddalena La",
    "iso:country":"IT",
    "sg:address":"07024 La Maddalena",
    "sg:city":"La Maddalena",
    "sg:orig_category":"Apparecchiature E Sistemi Per Magazzinaggio E Movimentazione",
    "sg:phone":"+39 0789 734056",
    "sg:postcode":"07024",
    "sg:province":"Olbia-Tempio",
    "wof:name":"G.p.d. Edilizia Srl",
    "wof:placetype":"venue"
},
  "geometry": {"coordinates":[9.417273,41.230465],"type":"Point"}
}