{
  "type": "Feature",
  "properties": {
    "iso:country":"IT",
    "sg:address":"296/a, S. Croce 30135 Venezia",
    "sg:city":"Venezia",
    "sg:classifiers":[
        {
            "category":"Parking",
            "subcategory":"Lot",
            "type":"Transportation"
        }
    ],
    "sg:phone":"+39 39041713719",
    "sg:postcode":"30135",
    "sg:province":"Venezia",
    "sg:tags":[
        "transport",
        "road"
    ],
    "sg:website":"http://www.trasbagagli.it",
    "wof:name":"Cooperativa Trasbagagli Venezia",
    "wof:placetype":"venue"
},
  "geometry": {"coordinates":[12.319861,45.437767],"type":"Point"}
}