{
  "type": "Feature",
  "properties": {
    "iso:country":"IT",
    "sg:address":"35030 Vo",
    "sg:orig_category":"Materiali Edili",
    "sg:phone":"+39 049 994 0057",
    "sg:postcode":"35030",
    "sg:province":"Padova",
    "wof:name":"Costruzioni Stradali Martini Silvestro & C. Snc",
    "wof:placetype":"venue"
},
  "geometry": {"coordinates":[11.6425,45.329224],"type":"Point"}
}