{
  "type": "Feature",
  "properties": {
    "iso:country":"IT",
    "sg:address":"37010 Sant'ambrogio Di Valpolicella",
    "sg:orig_category":"Macchine Ed Impianti Per Edilizia E Lavori Pubblici",
    "sg:phone":"+39 045 686 2548",
    "sg:postcode":"37010",
    "sg:province":"Verona",
    "wof:name":"Zed Srl",
    "wof:placetype":"venue"
},
  "geometry": {"coordinates":[10.99311,45.441959],"type":"Point"}
}