{
  "type": "Feature",
  "properties": {
    "addr:full":"Via Trieste 49; Albenga; 17031 Albenga Savona 17031",
    "addr:housenumber":"49",
    "addr:postcode":"17031;17031",
    "addr:street":"Via Trieste",
    "iso:country":"IT",
    "sg:address":"Via Trieste 49; Albenga; 17031",
    "sg:city":"Albenga",
    "sg:classifiers":[
        {
            "category":"Banks & Credit Unions",
            "subcategory":"Bank",
            "type":"Services"
        }
    ],
    "sg:phone":"+39 0182 555026",
    "sg:postcode":"17031",
    "sg:province":"Savona",
    "wof:name":"Banca Nazionale Del Lavoro Spa",
    "wof:placetype":"venue"
},
  "geometry": {"coordinates":[8.217827,44.046963],"type":"Point"}
}