{
  "type": "Feature",
  "properties": {
    "addr:full":"15, Via Brallo 27010 Siziano Siziano Pavia 27010",
    "addr:postcode":"27010;27010",
    "addr:street":"Via Brallo",
    "iso:country":"IT",
    "sg:address":"15, Via Brallo 27010 Siziano",
    "sg:city":"Siziano",
    "sg:classifiers":[
        {
            "category":"Food & Beverages",
            "subcategory":"Groceries & Convenience Stores",
            "type":"Retail Goods"
        }
    ],
    "sg:phone":"+39 0382 678411",
    "sg:postcode":"27010",
    "sg:province":"Pavia",
    "sg:tags":[
        "product",
        "related"
    ],
    "wof:name":"Deligusti Spa",
    "wof:placetype":"venue"
},
  "geometry": {"coordinates":[9.2119283676,45.314163208],"type":"Point"}
}