{
  "type": "Feature",
  "properties": {
    "addr:full":"38027 Mal\u00e8 Trento 38027",
    "addr:postcode":"38027;38027",
    "iso:country":"IT",
    "sg:address":"38027 Mal\u00e8",
    "sg:orig_category":"Serramenti Ed Infissi. Prodotti Vari In Metallo",
    "sg:phone":"+39 0463 900160",
    "sg:postcode":"38027",
    "sg:province":"Trento",
    "wof:name":"Ferramenta Gionta",
    "wof:placetype":"venue"
},
  "geometry": {"coordinates":[10.908605,46.348171],"type":"Point"}
}