{
  "type": "Feature",
  "properties": {
    "addr:full":"18, Via Carmagnola 10040 Pralormo Pralormo Torino 10040",
    "addr:postcode":"10040;10040",
    "addr:street":"Via Carmagnola",
    "iso:country":"IT",
    "sg:address":"18, Via Carmagnola 10040 Pralormo",
    "sg:city":"Pralormo",
    "sg:classifiers":[
        {
            "category":"Wholesale",
            "subcategory":"Drugs",
            "type":"Manufacturing & Wholesale Goods"
        }
    ],
    "sg:phone":"+39 011 948 1309",
    "sg:postcode":"10040",
    "sg:province":"Torino",
    "sg:tags":[
        "chemical",
        "pharmaceutical"
    ],
    "wof:name":"Cauda Strade (s.r.l.)",
    "wof:placetype":"venue"
},
  "geometry": {"coordinates":[7.877115,44.858021],"type":"Point"}
}