{
  "type": "Feature",
  "properties": {
    "addr:full":"Via Industria 19 41100 Modena Modena Modena 41100",
    "addr:housenumber":"19",
    "addr:postcode":"41100;41100",
    "addr:street":"Via Industria",
    "iso:country":"IT",
    "sg:address":"Via Industria 19 41100 Modena",
    "sg:city":"Modena",
    "sg:classifiers":[
        {
            "category":"Wholesale",
            "subcategory":"Plants",
            "type":"Manufacturing & Wholesale Goods"
        }
    ],
    "sg:phone":"+39 059 283557",
    "sg:postcode":"41100",
    "sg:province":"Modena",
    "sg:tags":[
        "machine",
        "industrial",
        "automation"
    ],
    "wof:name":"Faber Srl",
    "wof:placetype":"venue"
},
  "geometry": {"coordinates":[10.92522,44.647079],"type":"Point"}
}