{
  "type": "Feature",
  "properties": {
    "addr:full":"Via Roma 60; Acuto",
    "addr:housenumber":"60",
    "addr:street":"Via Roma",
    "iso:country":"IT",
    "sg:address":"Via Roma 60; Acuto",
    "sg:classifiers":[
        {
            "category":"Banks & Credit Unions",
            "subcategory":"Bank",
            "type":"Services"
        }
    ],
    "sg:phone":"+39 0775 56814",
    "wof:name":"Banca Di Roma",
    "wof:placetype":"venue"
},
  "geometry": {"coordinates":[13.177698,41.792248],"type":"Point"}
}