{
  "type": "Feature",
  "properties": {
    "iso:country":"IT",
    "sg:address":"60027 Osimo",
    "sg:city":"Osimo",
    "sg:orig_category":"Telefoni Cellulari E Radiotelefoni",
    "sg:phone":"+39 071 723 1197",
    "sg:postcode":"60027",
    "sg:province":"Ancona",
    "wof:name":"Stura Di Stura Mario & C. Snc",
    "wof:placetype":"venue"
},
  "geometry": {"coordinates":[13.463523,43.469288],"type":"Point"}
}