{
  "type": "Feature",
  "properties": {
    "addr:full":"80134 Napoli Napoli Napoli 80134",
    "addr:housenumber":"80134",
    "addr:postcode":"80134",
    "iso:country":"IT",
    "sg:address":"80134 Napoli",
    "sg:city":"Napoli",
    "sg:orig_category":"Agenzie Ed Enti Turistici. Consulenze Tecniche, Amministrative E Perizie",
    "sg:phone":"+39 081 781 0026",
    "sg:postcode":"80134",
    "sg:province":"Napoli",
    "wof:name":"Associazione Turistica I Viaggi Del Sottomarino",
    "wof:placetype":"venue"
},
  "geometry": {"coordinates":[14.351406,40.882412],"type":"Point"}
}