{
  "type": "Feature",
  "properties": {
    "iso:country":"IT",
    "sg:address":"27049 Stradella",
    "sg:city":"Stradella",
    "sg:orig_category":"Musica",
    "sg:phone":"+39 0385 40501",
    "sg:postcode":"27049",
    "sg:province":"Pavia",
    "wof:name":"Cagiada Marco",
    "wof:placetype":"venue"
},
  "geometry": {"coordinates":[9.3037624359,45.0740814209],"type":"Point"}
}