{
  "type": "Feature",
  "properties": {
    "iso:country":"IT",
    "sg:address":"Via Buozzi Bruno 26 20097 San Donato Milanese",
    "sg:city":"San Donato Milanese",
    "sg:classifiers":[
        {
            "category":"Recreation",
            "subcategory":"Sailing Club",
            "type":"Entertainment"
        }
    ],
    "sg:phone":"+39 02 5180 0538",
    "sg:postcode":"20097",
    "sg:province":"Milano",
    "sg:tags":[
        "inland",
        "vessel",
        "navigation"
    ],
    "sg:website":"www.lomac.it",
    "wof:name":"Lomac Nautica Srl",
    "wof:placetype":"venue"
},
  "geometry": {"coordinates":[9.258321,45.411835],"type":"Point"}
}