{
  "type": "Feature",
  "properties": {
    "iso:country":"IT",
    "sg:address":"30038 Spinea",
    "sg:city":"Spinea",
    "sg:orig_category":"Non-classified Establishments",
    "sg:phone":"+39 041 994428",
    "sg:postcode":"30038",
    "sg:province":"Venezia",
    "wof:name":"Rustici Faraon Di Faraon Gianni & C. Snc",
    "wof:placetype":"venue"
},
  "geometry": {"coordinates":[12.1455,45.50668],"type":"Point"}
}