{
  "type": "Feature",
  "properties": {
    "iso:country":"IT",
    "sg:address":"80141 Napoli",
    "sg:city":"Napoli",
    "sg:classifiers":[
        {
            "category":"Health Services",
            "subcategory":"Health Practitioner",
            "type":"Services"
        }
    ],
    "sg:phone":"+39 081 298509",
    "sg:postcode":"80141",
    "sg:province":"Napoli",
    "sg:tags":[
        "medici"
    ],
    "wof:name":"Badolati Elio",
    "wof:placetype":"venue"
},
  "geometry": {"coordinates":[14.208664,40.935051],"type":"Point"}
}