{
  "type": "Feature",
  "properties": {
    "addr:full":"Via Corradini 2 42048 Rubiera Reggio Nell'Emilia 42048",
    "addr:housenumber":"2",
    "addr:postcode":"42048;42048",
    "addr:street":"Via Corradini",
    "iso:country":"IT",
    "sg:address":"Via Corradini 2 42048 Rubiera",
    "sg:classifiers":[
        {
            "category":"Utilities",
            "subcategory":"Natural Gas",
            "type":"Services"
        }
    ],
    "sg:phone":"+39 0522 628249",
    "sg:postcode":"42048",
    "sg:province":"Reggio Nell'Emilia",
    "sg:tags":[
        "diaphragm",
        "pump"
    ],
    "sg:website":"www.udor.it",
    "wof:name":"Udor Srl",
    "wof:placetype":"venue"
},
  "geometry": {"coordinates":[10.627794,44.696228],"type":"Point"}
}