{
  "type": "Feature",
  "properties": {
    "addr:full":"10, Via Sonna 23806 Torre De' Busi Lecco 23806",
    "addr:postcode":"23806;de ' busi;23806",
    "addr:street":"Via Sonna",
    "iso:country":"IT",
    "sg:address":"10, Via Sonna 23806 Torre De' Busi",
    "sg:classifiers":[
        {
            "category":"Manufacturing",
            "subcategory":"Metals",
            "type":"Manufacturing & Wholesale Goods"
        }
    ],
    "sg:phone":"+39 39035785050",
    "sg:postcode":"23806",
    "sg:province":"Lecco",
    "sg:tags":[
        "metallurgy",
        "metalworking"
    ],
    "wof:name":"Trafilerie Chioderie Torre De' Busi Di Morandini G. & C.(s.a.s.)",
    "wof:placetype":"venue"
},
  "geometry": {"coordinates":[9.4666318893,45.7760429382],"type":"Point"}
}