{
  "type": "Feature",
  "properties": {
    "iso:country":"IT",
    "sg:address":"20099 Sesto San Giovanni",
    "sg:city":"Sesto San Giovanni",
    "sg:orig_category":"Articoli Pulizia. Macchine E Forniture Per Ecologia E Smaltimento Rifiuti. Forniture Per Attivita' Commerciali Ed Artigianali",
    "sg:phone":"+39 02 240 1275",
    "sg:postcode":"20099",
    "sg:province":"Milano",
    "wof:name":"Paperplast",
    "wof:placetype":"venue"
},
  "geometry": {"coordinates":[9.242583,45.538628],"type":"Point"}
}