{
  "type": "Feature",
  "properties": {
    "iso:country":"IT",
    "sg:address":"20098 San Giuliano Milanese",
    "sg:city":"San Giuliano Milanese",
    "sg:classifiers":[
        {
            "category":"Professional",
            "subcategory":"Engineering",
            "type":"Services"
        }
    ],
    "sg:phone":"+39 02 988 0189",
    "sg:postcode":"20098",
    "sg:province":"Milano",
    "sg:tags":[
        "component",
        "material",
        "electronic"
    ],
    "wof:name":"O & B Elettronica Srl",
    "wof:placetype":"venue"
},
  "geometry": {"coordinates":[9.259433,45.397762],"type":"Point"}
}