{
  "type": "Feature",
  "properties": {
    "iso:country":"IT",
    "sg:address":"40057 Granarolo Emilia",
    "sg:orig_category":"Elettronica Industriale, Prodotti E Apparecchiature",
    "sg:phone":"+39 051 605 6500",
    "sg:postcode":"40057",
    "sg:province":"Bologna",
    "sg:website":"http://www.web.tin.it/iter",
    "wof:name":"I.t.e.r. Srl",
    "wof:placetype":"venue"
},
  "geometry": {"coordinates":[11.439745,44.547112],"type":"Point"}
}