{
  "type": "Feature",
  "properties": {
    "addr:full":"20144 Milano Milano Milano 20144",
    "addr:postcode":"20144;20144",
    "iso:country":"IT",
    "sg:address":"20144 Milano",
    "sg:city":"Milano",
    "sg:orig_category":"Forniture Per Abbigliamento E Pelletterie",
    "sg:phone":"+39 02 498 1679",
    "sg:postcode":"20144",
    "sg:province":"Milano",
    "wof:name":"Ermolli Marco",
    "wof:placetype":"venue"
},
  "geometry": {"coordinates":[9.1624450684,45.4581680298],"type":"Point"}
}