{
  "type": "Feature",
  "properties": {
    "addr:full":"06081 Assisi Assisi Perugia 06081",
    "addr:postcode":"06081;06081",
    "iso:country":"IT",
    "sg:address":"06081 Assisi",
    "sg:city":"Assisi",
    "sg:orig_category":"Servizi E Lavori Per Agricoltura E Zootecnia",
    "sg:phone":"+39 075 806 4257",
    "sg:postcode":"06081",
    "sg:province":"Perugia",
    "wof:name":"Fortini Marcello",
    "wof:placetype":"venue"
},
  "geometry": {"coordinates":[12.652667,43.030315],"type":"Point"}
}