{
  "type": "Feature",
  "properties": {
    "iso:country":"IT",
    "sg:address":"81042 Calvi Risorta",
    "sg:city":"Calvi Risorta",
    "sg:orig_category":"Cancelleria",
    "sg:phone":"+39 0823 652630",
    "sg:postcode":"81042",
    "sg:province":"Caserta",
    "wof:name":"I.de.ma. Snc Di Giacomo Martucci",
    "wof:placetype":"venue"
},
  "geometry": {"coordinates":[14.129298,41.219345],"type":"Point"}
}