{
  "type": "Feature",
  "properties": {
    "iso:country":"IT",
    "sg:address":"20149 Milano",
    "sg:city":"Milano",
    "sg:orig_category":"Cinematografia E Radiotelevisione",
    "sg:phone":"+39 02 4398 1787",
    "sg:postcode":"20149",
    "sg:province":"Milano",
    "wof:name":"Bassano Marco",
    "wof:placetype":"venue"
},
  "geometry": {"coordinates":[9.1497,45.476597],"type":"Point"}
}