{
  "type": "Feature",
  "properties": {
    "iso:country":"IT",
    "sg:address":"Strada St. 275 73030 Surano",
    "sg:city":"Surano",
    "sg:classifiers":[
        {
            "category":"Autos & Motor Vehicles",
            "subcategory":"Boat Sales",
            "type":"Retail Goods"
        }
    ],
    "sg:phone":"+39 0836 936809",
    "sg:postcode":"73030",
    "sg:province":"Lecce",
    "wof:name":"Tecnica Vetroresina Di Longo Giuseppe E F.lli Sas",
    "wof:placetype":"venue"
},
  "geometry": {"coordinates":[18.174015,40.353291],"type":"Point"}
}