{
  "type": "Feature",
  "properties": {
    "addr:full":"20094 Corsico Corsico Milano 20094",
    "addr:postcode":"20094;20094",
    "iso:country":"IT",
    "sg:address":"20094 Corsico",
    "sg:city":"Corsico",
    "sg:orig_category":"Ospedali E Servizi Sanitari. Servizi Sociali",
    "sg:phone":"+39 02 450 1396",
    "sg:postcode":"20094",
    "sg:province":"Milano",
    "wof:name":"Coop. Lotta Contro L'emarginazione Coop. Soc. A Rl",
    "wof:placetype":"venue"
},
  "geometry": {"coordinates":[9.093081,45.439693],"type":"Point"}
}