{
  "type": "Feature",
  "properties": {
    "iso:country":"IT",
    "sg:address":"18100 Imperia",
    "sg:city":"Imperia",
    "sg:orig_category":"Cantieri Navali",
    "sg:phone":"+39 0183 666705",
    "sg:postcode":"18100",
    "sg:province":"Imperia",
    "wof:name":"Imperia Mare Spa",
    "wof:placetype":"venue"
},
  "geometry": {"coordinates":[8.018356,43.877312],"type":"Point"}
}