{
  "type": "Feature",
  "properties": {
    "iso:country":"IT",
    "sg:address":"25071 Agnosine",
    "sg:city":"Agnosine",
    "sg:orig_category":"Trattamenti Termici E Superficiali Metalli, Galvanotecnica",
    "sg:phone":"+39 036 589 6619",
    "sg:postcode":"25071",
    "sg:province":"Brescia",
    "wof:name":"Industria Galvanotecnica Srl",
    "wof:placetype":"venue"
},
  "geometry": {"coordinates":[10.348217,45.639217],"type":"Point"}
}