{
  "type": "Feature",
  "properties": {
    "iso:country":"IT",
    "sg:address":"40037 Sasso Marconi",
    "sg:city":"Sasso Marconi",
    "sg:orig_category":"Autofficine, Gommisti E Autolavaggi - Attrezzature",
    "sg:phone":"+39 051 678 1511",
    "sg:postcode":"40037",
    "sg:province":"Bologna",
    "sg:website":"http://www.ravaglioli.com",
    "wof:name":"Ravaglioli Spa",
    "wof:placetype":"venue"
},
  "geometry": {"coordinates":[11.27292,44.428505],"type":"Point"}
}