{
  "type": "Feature",
  "properties": {
    "iso:country":"IT",
    "sg:address":"04019 Terracina",
    "sg:city":"Terracina",
    "sg:orig_category":"Fognature",
    "sg:phone":"+39 0773 730000",
    "sg:postcode":"04019",
    "sg:province":"Latina",
    "wof:name":"Frattarelli Franco",
    "wof:placetype":"venue"
},
  "geometry": {"coordinates":[13.2129259109,41.2997093201],"type":"Point"}
}