{
  "type": "Feature",
  "properties": {
    "addr:full":"Via Fatebenefratelli ,1/3 24010 Sorisole Sorisole Bergamo 24010",
    "addr:housenumber":"1 / 3",
    "addr:postcode":"24010;24010",
    "addr:street":"Via Fatebenefratelli",
    "iso:country":"IT",
    "sg:address":"Via Fatebenefratelli ,1/3 24010 Sorisole",
    "sg:city":"Sorisole",
    "sg:orig_category":"Hot-water Irrigation Sterilizers",
    "sg:phone":"+39 035 573857",
    "sg:postcode":"24010",
    "sg:province":"Bergamo",
    "sg:website":"www.milestonesrl.com",
    "wof:name":"Milestone Srl",
    "wof:placetype":"venue"
},
  "geometry": {"coordinates":[9.653881,45.735344],"type":"Point"}
}