{
  "type": "Feature",
  "properties": {
    "iso:country":"IT",
    "sg:address":"S.da Vairo Menga 15 14036 Moncalvo",
    "sg:city":"Moncalvo",
    "sg:classifiers":[
        {
            "category":"Manufacturing",
            "subcategory":"Rubber & Plastics",
            "type":"Manufacturing & Wholesale Goods"
        }
    ],
    "sg:phone":"+39 0141 917661",
    "sg:postcode":"14036",
    "sg:province":"Asti",
    "sg:tags":[
        "technical",
        "item",
        "us"
    ],
    "sg:website":"www.dogi.it",
    "wof:name":"Dogi Spa",
    "wof:placetype":"venue"
},
  "geometry": {"coordinates":[8.206813,44.900864],"type":"Point"}
}