{
  "type": "Feature",
  "properties": {
    "iso:country":"IT",
    "sg:address":"16131 Genova",
    "sg:city":"Genova",
    "sg:orig_category":"Servizi E Lavori Per Abbigliamento E Pelletterie",
    "sg:phone":"+39 010 522 1344",
    "sg:postcode":"16131",
    "sg:province":"Genova",
    "wof:name":"Inserra Teresa",
    "wof:placetype":"venue"
},
  "geometry": {"coordinates":[8.970903,44.404881],"type":"Point"}
}