{
  "type": "Feature",
  "properties": {
    "addr:full":"35040 Santa Margherita D'adige Padova 35040",
    "addr:postcode":"35040;35040",
    "iso:country":"IT",
    "sg:address":"35040 Santa Margherita D'adige",
    "sg:orig_category":"Servizi E Lavori Per Abbigliamento E Pelletterie",
    "sg:phone":"+39 0429 86732",
    "sg:postcode":"35040",
    "sg:province":"Padova",
    "wof:name":"Zenoni Cristina",
    "wof:placetype":"venue"
},
  "geometry": {"coordinates":[11.555359,45.213406],"type":"Point"}
}