{
  "type": "Feature",
  "properties": {
    "iso:country":"IT",
    "sg:address":"12, Via Barignani 61100 Pesaro",
    "sg:city":"Pesaro",
    "sg:classifiers":[
        {
            "category":"Professional",
            "subcategory":"Computer Services",
            "type":"Services"
        }
    ],
    "sg:phone":"+39 0721 371080",
    "sg:postcode":"61100",
    "sg:province":"Pesaro E Urbino",
    "sg:tags":[
        "information",
        "technology"
    ],
    "wof:name":"Polo Engineering Srl",
    "wof:placetype":"venue"
},
  "geometry": {"coordinates":[12.911731,43.910698],"type":"Point"}
}