{
  "type": "Feature",
  "properties": {
    "addr:full":"Via Nazionale, 98/a; Altedo; 40051 Altedo Bologna 40051",
    "addr:housenumber":"98 / a",
    "addr:postcode":"40051;40051",
    "addr:street":"Via Nazionale",
    "iso:country":"IT",
    "sg:address":"Via Nazionale, 98/a; Altedo; 40051",
    "sg:city":"Altedo",
    "sg:classifiers":[
        {
            "category":"Banks & Credit Unions",
            "subcategory":"Bank",
            "type":"Services"
        }
    ],
    "sg:phone":"+39 051 871704",
    "sg:postcode":"40051",
    "sg:province":"Bologna",
    "wof:name":"Banco Del Monte",
    "wof:placetype":"venue"
},
  "geometry": {"coordinates":[11.486649,44.664749],"type":"Point"}
}