{
  "type": "Feature",
  "properties": {
    "addr:full":"75, Via Don Maestrini 25020 Flero Flero Brescia 25020",
    "addr:postcode":"25020;25020",
    "addr:street":"Via Don Maestrini",
    "iso:country":"IT",
    "sg:address":"75, Via Don Maestrini 25020 Flero",
    "sg:city":"Flero",
    "sg:classifiers":[
        {
            "category":"Manufacturing",
            "subcategory":"Rubber & Plastics",
            "type":"Manufacturing & Wholesale Goods"
        }
    ],
    "sg:phone":"+39 030 264 0591",
    "sg:postcode":"25020",
    "sg:province":"Brescia",
    "wof:name":"Termoplastica Bresciana (s.r.l.)",
    "wof:placetype":"venue"
},
  "geometry": {"coordinates":[10.1777353287,45.4749526978],"type":"Point"}
}