{
  "type": "Feature",
  "properties": {
    "iso:country":"IT",
    "sg:address":"14, Via Scapacchio' Ovest 35030 Saccolongo",
    "sg:city":"Saccolongo",
    "sg:classifiers":[
        {
            "category":"Shopping",
            "subcategory":"Clothing, Apparel, & Fashions",
            "type":"Retail Goods"
        }
    ],
    "sg:phone":"+39 049 801 5068",
    "sg:postcode":"35030",
    "sg:province":"Padova",
    "sg:tags":[
        "clothes"
    ],
    "wof:name":"Tobaldo",
    "wof:placetype":"venue"
},
  "geometry": {"coordinates":[11.735075,45.409405],"type":"Point"}
}