{
  "type": "Feature",
  "properties": {
    "iso:country":"IT",
    "sg:address":"70037 Ruvo Di Puglia",
    "sg:city":"Ruvo di Puglia",
    "sg:orig_category":"Arredi Ed Attrezzature Per Attivita' Commerciali Ed Artigianali",
    "sg:phone":"+39 080 361 3423",
    "sg:postcode":"70037",
    "sg:province":"Bari",
    "wof:name":"Lovero Allestimenti Srl",
    "wof:placetype":"venue"
},
  "geometry": {"coordinates":[16.464146,41.064796],"type":"Point"}
}