{
  "type": "Feature",
  "properties": {
    "addr:full":"133, Via Trabucco 90146 Palermo Palermo Palermo 90146",
    "addr:housenumber":"133",
    "addr:postcode":"90146;90146",
    "addr:street":"Via Trabucco",
    "iso:country":"IT",
    "sg:address":"133, Via Trabucco 90146 Palermo",
    "sg:city":"Palermo",
    "sg:classifiers":[
        {
            "category":"Manufacturing",
            "subcategory":"Tools & Machinery",
            "type":"Manufacturing & Wholesale Goods"
        }
    ],
    "sg:phone":"+39 091 688 2865",
    "sg:postcode":"90146",
    "sg:province":"Palermo",
    "sg:tags":[
        "environment",
        "equipment",
        "-"
    ],
    "wof:name":"Aertec (s.r.l.)",
    "wof:placetype":"venue"
},
  "geometry": {"coordinates":[13.315532,38.151001],"type":"Point"}
}