{
  "type": "Feature",
  "properties": {
    "iso:country":"IT",
    "sg:address":"59013 Montemurlo",
    "sg:city":"Montemurlo",
    "sg:orig_category":"Apparecchiature E Sistemi Per Magazzinaggio E Movimentazione. Macchine E Impianti Per Attivita' Commerciali Ed Artigianali. Macchine, Strumenti Ed Apparecchi Per Attivita' Industriali",
    "sg:phone":"+39 0574 683459",
    "sg:postcode":"59013",
    "sg:province":"Prato",
    "wof:name":"Cba Di Caciolli Gilberto & C. Sas",
    "wof:placetype":"venue"
},
  "geometry": {"coordinates":[11.026214,43.90551],"type":"Point"}
}