{
  "type": "Feature",
  "properties": {
    "iso:country":"IT",
    "sg:address":"Via Isonzo 21/a 34070 Mossa",
    "sg:city":"Mossa",
    "sg:classifiers":[
        {
            "category":"Food & Beverages",
            "subcategory":"Meat & Fish",
            "type":"Retail Goods"
        }
    ],
    "sg:phone":"+39 0481 380241",
    "sg:postcode":"34070",
    "sg:province":"Gorizia",
    "sg:tags":[
        "bacon",
        "ham"
    ],
    "wof:name":"Wild Srl",
    "wof:placetype":"venue"
},
  "geometry": {"coordinates":[13.548534,45.928867],"type":"Point"}
}