{
  "type": "Feature",
  "properties": {
    "iso:country":"IT",
    "sg:address":"73044 Galatone",
    "sg:city":"Galatone",
    "sg:orig_category":"Forniture Per Attivita' Commerciali Ed Artigianali. Arredi Ed Attrezzature Per Attivita' Commerciali Ed Artigianali",
    "sg:phone":"+39 0833 865878",
    "sg:postcode":"73044",
    "sg:province":"Lecce",
    "wof:name":"Frigo Del Salento Srl",
    "wof:placetype":"venue"
},
  "geometry": {"coordinates":[18.0598659515,40.1391601562],"type":"Point"}
}