{
  "type": "Feature",
  "properties": {
    "iso:country":"IT",
    "sg:address":"66/a, Strada Buffolara 43100 Parma",
    "sg:city":"Parma",
    "sg:orig_category":"Miscellaneous Products",
    "sg:phone":"+39 0521 290222",
    "sg:postcode":"43100",
    "sg:province":"Parma",
    "wof:name":"Clean International Srl",
    "wof:placetype":"venue"
},
  "geometry": {"coordinates":[10.2949199677,44.8232078552],"type":"Point"}
}