{
  "type": "Feature",
  "properties": {
    "iso:country":"IT",
    "sg:address":"21, Via Monselice 20033 Desio",
    "sg:city":"Desio",
    "sg:classifiers":[
        {
            "category":"Shopping",
            "type":"Retail Goods"
        }
    ],
    "sg:phone":"+39 036 262 4093",
    "sg:postcode":"20033",
    "sg:province":"Milano",
    "sg:tags":[
        "finished",
        "-",
        "metallic"
    ],
    "wof:name":"Carbo Sidiam Di Mario Giuseppe E Carlo Cattaneo (s.n.c.)",
    "wof:placetype":"venue"
},
  "geometry": {"coordinates":[9.1914606094,45.6099662781],"type":"Point"}
}