{
  "type": "Feature",
  "properties": {
    "iso:country":"IT",
    "sg:address":"Via Guisti 14; Udine",
    "sg:classifiers":[
        {
            "category":"Banks & Credit Unions",
            "subcategory":"Bank",
            "type":"Services"
        }
    ],
    "sg:phone":"+39 0432 25331",
    "wof:name":"Banca Antoniana, Popolare Veneta Scarl",
    "wof:placetype":"venue"
},
  "geometry": {"coordinates":[13.241263,46.059864],"type":"Point"}
}