{
  "type": "Feature",
  "properties": {
    "iso:country":"IT",
    "sg:address":"55045 Pietrasanta",
    "sg:city":"Pietrasanta",
    "sg:orig_category":"Calzature, Pelletterie E Pelli. Shopping",
    "sg:phone":"+39 0584 283000",
    "sg:postcode":"55045",
    "sg:province":"Lucca",
    "wof:name":"Nova Lampo Snc Di Monari M. & C.",
    "wof:placetype":"venue"
},
  "geometry": {"coordinates":[10.245337,43.938614],"type":"Point"}
}