{
  "type": "Feature",
  "properties": {
    "iso:country":"IT",
    "sg:address":"42100 Reggio Emilia",
    "sg:orig_category":"Musica",
    "sg:phone":"+39 0522 941877",
    "sg:postcode":"42100",
    "sg:province":"Reggio Nell'Emilia",
    "wof:name":"Roxy Hall Snc Di Franceschi Ivan",
    "wof:placetype":"venue"
},
  "geometry": {"coordinates":[10.5535907745,44.7247276306],"type":"Point"}
}