{
  "type": "Feature",
  "properties": {
    "iso:country":"IT",
    "sg:address":"Cascina Belgiardi' 24056 Fontanella",
    "sg:city":"Fontanella",
    "sg:classifiers":[
        {
            "category":"Farming",
            "subcategory":"Livestock Farm",
            "type":"Manufacturing & Wholesale Goods"
        }
    ],
    "sg:phone":"+39 036 399 7249",
    "sg:postcode":"24056",
    "sg:province":"Bergamo",
    "sg:tags":[
        "agriculture"
    ],
    "wof:name":"Azienda Agricola Gattinoni Silvio E Francesco S.s.",
    "wof:placetype":"venue"
},
  "geometry": {"coordinates":[9.669952,45.694904],"type":"Point"}
}