{
  "type": "Feature",
  "properties": {
    "iso:country":"IT",
    "sg:address":"25080 Manerba Del Garda",
    "sg:city":"Manerba del Garda",
    "sg:orig_category":"Carni, Salumi E Pesci. Zootecnia E Pesca, Allevamento Piccoli Animali",
    "sg:phone":"+39 036 567871",
    "sg:postcode":"25080",
    "sg:province":"Brescia",
    "sg:website":"http://www.nordimport.it",
    "wof:name":"Nordimport Spa",
    "wof:placetype":"venue"
},
  "geometry": {"coordinates":[10.516687,45.608604],"type":"Point"}
}