{
  "type": "Feature",
  "properties": {
    "addr:full":"37020 Cerro Veronese Cerro Veronese Verona 37020",
    "addr:housenumber":"37020;veronese",
    "addr:postcode":"37020",
    "addr:street":"Cerro;Cerro",
    "iso:country":"IT",
    "sg:address":"37020 Cerro Veronese",
    "sg:city":"Cerro Veronese",
    "sg:orig_category":"Macchine Ed Impianti Per Edilizia E Lavori Pubblici",
    "sg:phone":"+39 045 708 0855",
    "sg:postcode":"37020",
    "sg:province":"Verona",
    "wof:name":"Elettredile Di Zamperini Stefano & C. Snc",
    "wof:placetype":"venue"
},
  "geometry": {"coordinates":[11.040708,45.575569],"type":"Point"}
}