{
  "type": "Feature",
  "properties": {
    "iso:country":"IT",
    "sg:address":"41100 Modena",
    "sg:city":"Modena",
    "sg:orig_category":"Macchine, Impianti Ed Attrezzature Per Abbigliamento E Pelletterie",
    "sg:phone":"+39 059 333946",
    "sg:postcode":"41100",
    "sg:province":"Modena",
    "wof:name":"Omtex Di Omero Sargenti",
    "wof:placetype":"venue"
},
  "geometry": {"coordinates":[10.942211,44.544682],"type":"Point"}
}