{
  "type": "Feature",
  "properties": {
    "addr:full":"20144 Milano Milano Milano 20144",
    "addr:postcode":"20144;20144",
    "iso:country":"IT",
    "sg:address":"20144 Milano",
    "sg:city":"Milano",
    "sg:orig_category":"Servizi Per Aziende, Manifestazioni E Supporto Agli Scambi Commerciali",
    "sg:phone":"+39 02 837 2796",
    "sg:postcode":"20144",
    "sg:province":"Milano",
    "wof:name":"Paralleli Srl",
    "wof:placetype":"venue"
},
  "geometry": {"coordinates":[9.172211,45.453091],"type":"Point"}
}