{
  "type": "Feature",
  "properties": {
    "addr:full":"16, Via Chiesaccia 40056 Crespellano Crespellano Bologna 40056",
    "addr:postcode":"40056;40056",
    "addr:street":"Via Chiesaccia",
    "iso:country":"IT",
    "sg:address":"16, Via Chiesaccia 40056 Crespellano",
    "sg:city":"Crespellano",
    "sg:classifiers":[
        {
            "category":"Utilities",
            "subcategory":"Telephone",
            "type":"Services"
        }
    ],
    "sg:phone":"+39 39051739304",
    "sg:postcode":"40056",
    "sg:province":"Bologna",
    "sg:tags":[
        "telecommunication"
    ],
    "wof:name":"Istel Telefonia (s.r.l.)",
    "wof:placetype":"venue"
},
  "geometry": {"coordinates":[11.153629,44.557571],"type":"Point"}
}