{
  "type": "Feature",
  "properties": {
    "iso:country":"IT",
    "sg:address":"44, Piazza Chiesa Damiano 57124 Livorno",
    "sg:city":"Livorno",
    "sg:classifiers":[
        {
            "category":"Autos & Motor Vehicles",
            "subcategory":"Automobile Sales",
            "type":"Retail Goods"
        }
    ],
    "sg:phone":"+39 0586 856362",
    "sg:postcode":"57124",
    "sg:province":"Livorno",
    "sg:tags":[
        "motor-cars"
    ],
    "wof:name":"Aica Acam Srl",
    "wof:placetype":"venue"
},
  "geometry": {"coordinates":[10.308011055,43.5518760681],"type":"Point"}
}