{
  "type": "Feature",
  "properties": {
    "iso:country":"IT",
    "sg:address":"Piazza Zumaglini 21; Vercelli; 13100",
    "sg:city":"Vercelli",
    "sg:classifiers":[
        {
            "category":"Banks & Credit Unions",
            "subcategory":"Bank",
            "type":"Services"
        }
    ],
    "sg:phone":"+39 0161 64121",
    "sg:postcode":"13100",
    "sg:province":"Vercelli",
    "wof:name":"Banca Popolare Di Novara",
    "wof:placetype":"venue"
},
  "geometry": {"coordinates":[8.420463,45.324772],"type":"Point"}
}