{
  "type": "Feature",
  "properties": {
    "iso:country":"IT",
    "sg:address":"20146 Milano",
    "sg:city":"Milano",
    "sg:orig_category":"Abbigliamento Esterno, Maglierie E Pelliccerie. Servizi E Lavori Per Abbigliamento E Pelletterie",
    "sg:phone":"+39 02 423 7544",
    "sg:postcode":"20146",
    "sg:province":"Milano",
    "wof:name":"Abissi Di Scoppa Valeria",
    "wof:placetype":"venue"
},
  "geometry": {"coordinates":[9.146099,45.449738],"type":"Point"}
}