{
  "type": "Feature",
  "properties": {
    "addr:full":"Via Roma, 68 40069 Zola Predosa Zola Bologna 40069",
    "addr:housenumber":"68",
    "addr:postcode":"40069;40069",
    "addr:street":"Via Roma",
    "iso:country":"IT",
    "sg:address":"Via Roma, 68 40069 Zola Predosa",
    "sg:city":"Zola",
    "sg:classifiers":[
        {
            "category":"Manufacturing",
            "subcategory":"Rubber & Plastics",
            "type":"Manufacturing & Wholesale Goods"
        }
    ],
    "sg:phone":"+39 051 751100",
    "sg:postcode":"40069",
    "sg:province":"Bologna",
    "sg:tags":[
        "processing"
    ],
    "wof:name":"Plaxtiglass Srl",
    "wof:placetype":"venue"
},
  "geometry": {"coordinates":[11.2472276688,44.4963684082],"type":"Point"}
}