{
  "type": "Feature",
  "properties": {
    "addr:full":"16/1, Via Bastia 48017 Conselice Conselice Ravenna 48017",
    "addr:housenumber":"16 / 1",
    "addr:postcode":"48017;48017",
    "addr:street":"Via Bastia",
    "iso:country":"IT",
    "sg:address":"16/1, Via Bastia 48017 Conselice",
    "sg:city":"Conselice",
    "sg:classifiers":[
        {
            "category":"Food & Beverages",
            "subcategory":"Groceries & Convenience Stores",
            "type":"Retail Goods"
        }
    ],
    "sg:phone":"+39 39054580328",
    "sg:postcode":"48017",
    "sg:province":"Ravenna",
    "sg:tags":[
        "product",
        "related"
    ],
    "wof:name":"Surgital (s.r.l.)",
    "wof:placetype":"venue"
},
  "geometry": {"coordinates":[11.8757514954,44.5698890686],"type":"Point"}
}