{
  "type": "Feature",
  "properties": {
    "iso:country":"IT",
    "sg:address":"15033 Casale Monferrato",
    "sg:city":"Casale Monferrato",
    "sg:orig_category":"Elettrotecnica Professionale E Di Consumo. Forniture Alle Strutture Ricettive. Arredi Ed Attrezzature Per Attivita' Commerciali Ed Artigianali",
    "sg:phone":"+39 0142 76631",
    "sg:postcode":"15033",
    "sg:province":"Alessandria",
    "wof:name":"Detercart Sas",
    "wof:placetype":"venue"
},
  "geometry": {"coordinates":[8.480874,45.122253],"type":"Point"}
}