{
  "type": "Feature",
  "properties": {
    "iso:country":"IT",
    "sg:address":"10043 Orbassano",
    "sg:city":"Orbassano",
    "sg:orig_category":"Trattamenti Termici E Superficiali Metalli, Galvanotecnica",
    "sg:phone":"+39 011 900 3513",
    "sg:postcode":"10043",
    "sg:province":"Torino",
    "wof:name":"O.c.a.t. S.n.c.",
    "wof:placetype":"venue"
},
  "geometry": {"coordinates":[7.58928,45.012573],"type":"Point"}
}