{
  "type": "Feature",
  "properties": {
    "addr:full":"03036 Isola Del Liri Isola del Liri Frosinone 03036",
    "addr:postcode":"03036;03036",
    "iso:country":"IT",
    "sg:address":"03036 Isola Del Liri",
    "sg:city":"Isola del Liri",
    "sg:orig_category":"Ospedali E Servizi Sanitari",
    "sg:phone":"+39 0776 808928",
    "sg:postcode":"03036",
    "sg:province":"Frosinone",
    "wof:name":"Pessia Adalia",
    "wof:placetype":"venue"
},
  "geometry": {"coordinates":[13.569289,41.680222],"type":"Point"}
}