{
  "type": "Feature",
  "properties": {
    "addr:full":"22100 Como Como Como 22100",
    "addr:postcode":"22100;22100",
    "iso:country":"IT",
    "sg:address":"22100 Como",
    "sg:city":"Como",
    "sg:orig_category":"Porte Pieghevoli E Scorrevoli",
    "sg:phone":"+39 031 523640",
    "sg:postcode":"22100",
    "sg:province":"Como",
    "wof:name":"Gattitende",
    "wof:placetype":"venue"
},
  "geometry": {"coordinates":[9.0892829895,45.7885665894],"type":"Point"}
}