{
  "type": "Feature",
  "properties": {
    "iso:country":"IT",
    "sg:address":"20123 Milano",
    "sg:city":"Milano",
    "sg:orig_category":"Ceramiche: Prodotti E Lavorazioni. Articoli Da Regalo. Arte Ed Artigianato Artistico. Shopping",
    "sg:phone":"+39 02 832 2269",
    "sg:postcode":"20123",
    "sg:province":"Milano",
    "sg:website":"http://www.gobbetto.com",
    "wof:name":"Gobbetto Srl",
    "wof:placetype":"venue"
},
  "geometry": {"coordinates":[9.172743,45.459846],"type":"Point"}
}