{
  "type": "Feature",
  "properties": {
    "iso:country":"IT",
    "sg:address":"57, Via Raffaello 31020 San Vendemiano",
    "sg:city":"San Vendemiano",
    "sg:classifiers":[
        {
            "category":"Shopping",
            "subcategory":"Computers & Home Electronics",
            "type":"Retail Goods"
        }
    ],
    "sg:phone":"+39 0438 400053",
    "sg:postcode":"31020",
    "sg:province":"Treviso",
    "sg:tags":[
        "electronic",
        "electrical",
        "equipment"
    ],
    "wof:name":"Neon Lauro Di Piaia Lauro",
    "wof:placetype":"venue"
},
  "geometry": {"coordinates":[12.325205,45.895496],"type":"Point"}
}