{
  "type": "Feature",
  "properties": {
    "iso:country":"IT",
    "sg:address":"25040 Cividate Camuno",
    "sg:city":"Cividate Camuno",
    "sg:orig_category":"Metalli E Leghe",
    "sg:phone":"+39 036 434 0206",
    "sg:postcode":"25040",
    "sg:province":"Brescia",
    "wof:name":"Euro Sider Scalo Spa",
    "wof:placetype":"venue"
},
  "geometry": {"coordinates":[10.2562961578,45.9398231506],"type":"Point"}
}