{
  "type": "Feature",
  "properties": {
    "iso:country":"IT",
    "sg:address":"Piazza S.giovanni 3/a; Busto; 21052",
    "sg:classifiers":[
        {
            "category":"Banks & Credit Unions",
            "subcategory":"Bank",
            "type":"Services"
        }
    ],
    "sg:phone":"+39 0331 392111",
    "sg:postcode":"21052",
    "sg:province":"Varese",
    "wof:name":"Banca Popolare Di Bergamo",
    "wof:placetype":"venue"
},
  "geometry": {"coordinates":[8.851834,45.612026],"type":"Point"}
}