{
  "type": "Feature",
  "properties": {
    "iso:country":"IT",
    "sg:address":"37060 Sona",
    "sg:city":"Lugagnano",
    "sg:orig_category":"Non-classified Establishments",
    "sg:phone":"+39 045 609 0141",
    "sg:postcode":"37060",
    "sg:province":"Verona",
    "wof:name":"Toys Center",
    "wof:placetype":"venue"
},
  "geometry": {"coordinates":[10.864875,45.438786],"type":"Point"}
}