{
  "type": "Feature",
  "properties": {
    "addr:full":"Via Giannessi 55049 Viareggio Viareggio Lucca 55049",
    "addr:postcode":"55049;55049",
    "addr:street":"Via Giannessi",
    "iso:country":"IT",
    "sg:address":"Via Giannessi 55049 Viareggio",
    "sg:city":"Viareggio",
    "sg:classifiers":[
        {
            "category":"Autos & Motor Vehicles",
            "subcategory":"Boat Sales",
            "type":"Retail Goods"
        }
    ],
    "sg:phone":"+39 0584 388192",
    "sg:postcode":"55049",
    "sg:province":"Lucca",
    "wof:name":"C.b.i. Navi Spa",
    "wof:placetype":"venue"
},
  "geometry": {"coordinates":[10.246423,43.860233],"type":"Point"}
}