{
  "type": "Feature",
  "properties": {
    "iso:country":"IT",
    "sg:address":"00142 Roma",
    "sg:city":"Roma",
    "sg:classifiers":[
        {
            "category":"Professional",
            "subcategory":"Management & Consulting",
            "type":"Services"
        }
    ],
    "sg:phone":"+39 199 115 525",
    "sg:postcode":"00142",
    "sg:province":"Roma",
    "sg:tags":[
        "information",
        "communication",
        "marketing",
        "-",
        "advertising",
        "consultant",
        "services",
        "technology"
    ],
    "sg:website":"http://www.mediacon.it",
    "wof:name":"Mediacon Sistemi Informativi Spa",
    "wof:placetype":"venue"
},
  "geometry": {"coordinates":[12.512489,41.832355],"type":"Point"}
}