{
  "type": "Feature",
  "properties": {
    "addr:full":"46029 Suzzara Suzzara Mantova 46029",
    "addr:postcode":"46029;46029",
    "iso:country":"IT",
    "sg:address":"46029 Suzzara",
    "sg:city":"Suzzara",
    "sg:orig_category":"Motori Elettrici E Componenti",
    "sg:phone":"+39 0376 521693",
    "sg:postcode":"46029",
    "sg:province":"Mantova",
    "sg:website":"http://www.nalamotors.com",
    "wof:name":"Nala Motors Srl",
    "wof:placetype":"venue"
},
  "geometry": {"coordinates":[10.7673387527,44.988910675],"type":"Point"}
}