{
  "type": "Feature",
  "properties": {
    "addr:full":"Via Curiel 11 10024 Moncalieri Moncalieri Torino 10024",
    "addr:housenumber":"11",
    "addr:postcode":"10024;10024",
    "addr:street":"Via Curiel",
    "iso:country":"IT",
    "sg:address":"Via Curiel 11 10024 Moncalieri",
    "sg:city":"Moncalieri",
    "sg:classifiers":[
        {
            "category":"Autos & Motor Vehicles",
            "subcategory":"Boat Sales",
            "type":"Retail Goods"
        }
    ],
    "sg:phone":"+39 011 682 9000",
    "sg:postcode":"10024",
    "sg:province":"Torino",
    "sg:tags":[
        "spare",
        "part",
        "commercial",
        "truck"
    ],
    "sg:website":"www.errevi.it",
    "wof:name":"Errevi Spa",
    "wof:placetype":"venue"
},
  "geometry": {"coordinates":[7.669978,44.990913],"type":"Point"}
}