{
  "type": "Feature",
  "properties": {
    "addr:full":"12, Via Dalmazia 25126 Brescia Brescia Brescia 25126",
    "addr:postcode":"25126;25126",
    "addr:street":"Via Dalmazia",
    "iso:country":"IT",
    "sg:address":"12, Via Dalmazia 25126 Brescia",
    "sg:city":"Brescia",
    "sg:classifiers":[
        {
            "category":"Shopping",
            "subcategory":"Clothing, Apparel, & Fashions",
            "type":"Retail Goods"
        }
    ],
    "sg:phone":"+39 030 242 2178",
    "sg:postcode":"25126",
    "sg:province":"Brescia",
    "sg:tags":[
        "clothes"
    ],
    "wof:name":"Prima Donna Di Castellani E C Snc",
    "wof:placetype":"venue"
},
  "geometry": {"coordinates":[10.201517,45.534904],"type":"Point"}
}