{
  "type": "Feature",
  "properties": {
    "addr:full":"33020 Forni Di Sotto Forni di Sotto Udine 33020",
    "addr:postcode":"33020;33020",
    "iso:country":"IT",
    "sg:address":"33020 Forni Di Sotto",
    "sg:city":"Forni di Sotto",
    "sg:orig_category":"Occhiali - Produzione E Ingrosso",
    "sg:phone":"+39 0433 87257",
    "sg:postcode":"33020",
    "sg:province":"Udine",
    "sg:website":"http://www.topstylesnc.it",
    "wof:name":"Topstyle Snc Di Antoniacomi R. & C.",
    "wof:placetype":"venue"
},
  "geometry": {"coordinates":[12.675166,46.395481],"type":"Point"}
}