{
  "type": "Feature",
  "properties": {
    "iso:country":"IT",
    "sg:address":"51011 Borgo A Buggiano",
    "sg:city":"Borgo a buggiano",
    "sg:orig_category":"Agriturismo",
    "sg:phone":"+39 0572 72180",
    "sg:postcode":"51011",
    "sg:province":"Pistoia",
    "sg:website":"http://www.amicidelcolle.it",
    "wof:name":"Agriturismo Amici Del Colle",
    "wof:placetype":"venue"
},
  "geometry": {"coordinates":[10.728024,43.879681],"type":"Point"}
}