{
  "type": "Feature",
  "properties": {
    "iso:country":"IT",
    "sg:address":"16043 Chiavari",
    "sg:city":"Chiavari",
    "sg:orig_category":"Scuole E Servizi Scolastici",
    "sg:phone":"+39 0185 309017",
    "sg:postcode":"16043",
    "sg:province":"Genova",
    "wof:name":"Istituto A. Manzoni",
    "wof:placetype":"venue"
},
  "geometry": {"coordinates":[8.932747,44.411175],"type":"Point"}
}