{
  "type": "Feature",
  "properties": {
    "iso:country":"IT",
    "sg:address":"10070 Corio",
    "sg:city":"Corio",
    "sg:orig_category":"Servizi E Lavori Per Arredamento E Industria Del Legno",
    "sg:phone":"+39 011 928 2103",
    "sg:postcode":"10070",
    "sg:province":"Torino",
    "wof:name":"Baima Besquet Pietro",
    "wof:placetype":"venue"
},
  "geometry": {"coordinates":[7.546268,45.296818],"type":"Point"}
}