{
  "type": "Feature",
  "properties": {
    "iso:country":"IT",
    "sg:address":"09094 Marrubiu",
    "sg:city":"Marrubiu",
    "sg:orig_category":"Elettrotecnica Industriale, Prodotti E Apparecchiature",
    "sg:phone":"+39 0783 858103",
    "sg:postcode":"09094",
    "sg:province":"Oristano",
    "wof:name":"Siber Sardegna Srl",
    "wof:placetype":"venue"
},
  "geometry": {"coordinates":[8.671061,39.769875],"type":"Point"}
}