{
  "type": "Feature",
  "properties": {
    "iso:country":"IT",
    "sg:address":"97019 Vittoria",
    "sg:city":"Vittoria",
    "sg:orig_category":"Consulenza Commerciale E Finanziaria",
    "sg:phone":"+39 0932 981988",
    "sg:postcode":"97019",
    "sg:province":"Ragusa",
    "wof:name":"Creditosereno Picc.soc.coop.r.l.",
    "wof:placetype":"venue"
},
  "geometry": {"coordinates":[14.536748,36.957695],"type":"Point"}
}