{
  "type": "Feature",
  "properties": {
    "iso:country":"IT",
    "sg:address":"20093 Cologno Monzese",
    "sg:city":"Cologno Monzese",
    "sg:orig_category":"Metalli E Leghe",
    "sg:phone":"+39 02 2730 5592",
    "sg:postcode":"20093",
    "sg:province":"Milano",
    "wof:name":"C.r.f. Rottami Metallici Snc",
    "wof:placetype":"venue"
},
  "geometry": {"coordinates":[9.2649345398,45.5332298279],"type":"Point"}
}