{
  "type": "Feature",
  "properties": {
    "iso:country":"IT",
    "sg:address":"70123 Bari",
    "sg:city":"Bari",
    "sg:orig_category":"Servizi Ausiliari Dei Mezzi Di Trasporto",
    "sg:phone":"+39 080 579 4424",
    "sg:postcode":"70123",
    "sg:province":"Bari",
    "wof:name":"Cellamare Vito",
    "wof:placetype":"venue"
},
  "geometry": {"coordinates":[16.848385,41.12624],"type":"Point"}
}