{
  "type": "Feature",
  "properties": {
    "addr:full":"20036 Meda Meda Milano 20036",
    "addr:postcode":"20036;20036",
    "iso:country":"IT",
    "sg:address":"20036 Meda",
    "sg:city":"Meda",
    "sg:orig_category":"Prodotti E Manufatti In Materie Plastiche",
    "sg:phone":"+39 036 234 2773",
    "sg:postcode":"20036",
    "sg:province":"Milano",
    "wof:name":"Medusa Sas",
    "wof:placetype":"venue"
},
  "geometry": {"coordinates":[9.1609268188,45.664894104],"type":"Point"}
}