{
  "type": "Feature",
  "properties": {
    "iso:country":"IT",
    "sg:address":"Via Papini 4 24040 Madone",
    "sg:city":"Madone",
    "sg:classifiers":[
        {
            "category":"Autos & Motor Vehicles",
            "subcategory":"Fuel & Gas Station",
            "type":"Retail Goods"
        }
    ],
    "sg:phone":"+39 035 991229",
    "sg:postcode":"24040",
    "sg:province":"Bergamo",
    "sg:tags":[
        "chemical"
    ],
    "wof:name":"Labor Chimica Di Verdoni Vittorio",
    "wof:placetype":"venue"
},
  "geometry": {"coordinates":[9.553327,45.648354],"type":"Point"}
}