{
  "type": "Feature",
  "properties": {
    "addr:full":"5, V. Sempione 20034 Giussano Giussano Milano 20034",
    "addr:housenumber":"5",
    "addr:postcode":"20034;20034",
    "addr:street":"V. Sempione",
    "iso:country":"IT",
    "sg:address":"5, V. Sempione 20034 Giussano",
    "sg:city":"Giussano",
    "sg:classifiers":[
        {
            "category":"Manufacturing",
            "subcategory":"Rubber & Plastics",
            "type":"Manufacturing & Wholesale Goods"
        }
    ],
    "sg:phone":"+39 036 286 0081",
    "sg:postcode":"20034",
    "sg:province":"Milano",
    "sg:website":"http://www.gci-sas.it:ws_end: :mark:ws:http://www.paginegialle.it/gci",
    "wof:name":"G.c.i. Sas",
    "wof:placetype":"venue"
},
  "geometry": {"coordinates":[9.163868,45.46843],"type":"Point"}
}