{
  "type": "Feature",
  "properties": {
    "iso:country":"IT",
    "sg:address":"1, Via Pacinotti Antonio 20092 Cinisello Balsamo",
    "sg:city":"Cinisello Balsamo",
    "sg:classifiers":[
        {
            "category":"Professional",
            "subcategory":"Printing & Photocopies",
            "type":"Services"
        }
    ],
    "sg:phone":"+39 390 261 7911",
    "sg:postcode":"20092",
    "sg:province":"Milano",
    "wof:name":"Rotocalcografica Italiana S.p.a.",
    "wof:placetype":"venue"
},
  "geometry": {"coordinates":[9.1884269714,45.5303421021],"type":"Point"}
}