{
  "type": "Feature",
  "properties": {
    "addr:full":"23030 Mazzo Di Valtellina Mazzo di Valtellina Sondrio 23030",
    "addr:postcode":"23030;23030",
    "iso:country":"IT",
    "sg:address":"23030 Mazzo Di Valtellina",
    "sg:city":"Mazzo di Valtellina",
    "sg:orig_category":"Bevande, Vini E Liquori",
    "sg:phone":"+39 0342 861346",
    "sg:postcode":"23030",
    "sg:province":"Sondrio",
    "wof:name":"Bibita Srl",
    "wof:placetype":"venue"
},
  "geometry": {"coordinates":[10.258393,46.264584],"type":"Point"}
}