{
  "type": "Feature",
  "properties": {
    "addr:full":"61044 Cantiano Cantiano Pesaro E Urbino 61044",
    "addr:postcode":"61044;61044",
    "iso:country":"IT",
    "sg:address":"61044 Cantiano",
    "sg:city":"Cantiano",
    "sg:orig_category":"Minuterie Metalliche E Ferramenta",
    "sg:phone":"+39 0721 788002",
    "sg:postcode":"61044",
    "sg:province":"Pesaro E Urbino",
    "wof:name":"Piesse Snc Di Perez Miguel Angel E Soriani Elena",
    "wof:placetype":"venue"
},
  "geometry": {"coordinates":[12.6241283417,43.4813804626],"type":"Point"}
}