{
  "type": "Feature",
  "properties": {
    "addr:full":"9, Viale Del Lavoro 37030 Colognola Ai Colli Colognola ai Colli Verona 37030",
    "addr:postcode":"37030;37030",
    "addr:street":"Viale Del Lavoro",
    "iso:country":"IT",
    "sg:address":"9, Viale Del Lavoro 37030 Colognola Ai Colli",
    "sg:city":"Colognola ai Colli",
    "sg:classifiers":[
        {
            "category":"Shopping",
            "subcategory":"Computers & Home Electronics",
            "type":"Retail Goods"
        }
    ],
    "sg:phone":"+39 045 615 9211",
    "sg:postcode":"37030",
    "sg:province":"Verona",
    "sg:tags":[
        "electronic",
        "electrical",
        "equipment"
    ],
    "wof:name":"Prisma Spa",
    "wof:placetype":"venue"
},
  "geometry": {"coordinates":[11.212831,45.382523],"type":"Point"}
}