{
  "type": "Feature",
  "properties": {
    "addr:full":"17, Via Del Fangario 09122 Cagliari Cagliari Cagliari 09122",
    "addr:postcode":"09122;09122",
    "addr:street":"Via Del Fangario",
    "iso:country":"IT",
    "sg:address":"17, Via Del Fangario 09122 Cagliari",
    "sg:city":"Cagliari",
    "sg:classifiers":[
        {
            "category":"Professional",
            "subcategory":"Business Services",
            "type":"Services"
        }
    ],
    "sg:phone":"+39 39070290770",
    "sg:postcode":"09122",
    "sg:province":"Cagliari",
    "sg:tags":[
        "advice"
    ],
    "wof:name":"Emmepi Service S.r.l.",
    "wof:placetype":"venue"
},
  "geometry": {"coordinates":[9.093288,39.242657],"type":"Point"}
}