{
  "type": "Feature",
  "properties": {
    "iso:country":"IT",
    "sg:address":"142/2, Via A. Costa 40065 Pianoro",
    "sg:city":"Pianoro",
    "sg:classifiers":[
        {
            "category":"Manufacturing",
            "subcategory":"Printing",
            "type":"Manufacturing & Wholesale Goods"
        }
    ],
    "sg:phone":"+39 39051743006",
    "sg:postcode":"40065",
    "sg:province":"Bologna",
    "sg:tags":[
        "publishing"
    ],
    "wof:name":"Studio F.m.b. Bologna (s.r.l.)",
    "wof:placetype":"venue"
},
  "geometry": {"coordinates":[11.3525724411,44.4316062927],"type":"Point"}
}