{
  "type": "Feature",
  "properties": {
    "addr:full":"28, Via Ianniello Pasquale 80027 Frattamaggiore Frattamaggiore Napoli 80027",
    "addr:postcode":"80027;80027",
    "addr:street":"Via Ianniello Pasquale",
    "iso:country":"IT",
    "sg:address":"28, Via Ianniello Pasquale 80027 Frattamaggiore",
    "sg:city":"Frattamaggiore",
    "sg:classifiers":[
        {
            "category":"Shopping",
            "subcategory":"Crafts & Fabrics",
            "type":"Retail Goods"
        }
    ],
    "sg:phone":"+39 081 834 1985",
    "sg:postcode":"80027",
    "sg:province":"Napoli",
    "wof:name":"Ifis Spa",
    "wof:placetype":"venue"
},
  "geometry": {"coordinates":[14.2786607742,40.9444999695],"type":"Point"}
}