{
  "type": "Feature",
  "properties": {
    "iso:country":"IT",
    "sg:address":"45027 Pissatola",
    "sg:city":"Pissatola",
    "sg:orig_category":"Prodotti Di Base E Forniture Per Industria Alimentare E Bevande",
    "sg:phone":"+39 0425 701329",
    "sg:postcode":"45027",
    "sg:province":"Rovigo",
    "wof:name":"Tecnostamp S.r.l.",
    "wof:placetype":"venue"
},
  "geometry": {"coordinates":[11.4729814529,45.0493888855],"type":"Point"}
}