{
  "type": "Feature",
  "properties": {
    "iso:country":"IT",
    "sg:address":"00186 Roma",
    "sg:city":"Roma",
    "sg:orig_category":"Argenteria - Lavorazione E Ingrosso",
    "sg:phone":"+39 06 679 5449",
    "sg:postcode":"00186",
    "sg:province":"Roma",
    "wof:name":"Pipa & Cose Srl",
    "wof:placetype":"venue"
},
  "geometry": {"coordinates":[12.470082,41.865734],"type":"Point"}
}