{
  "type": "Feature",
  "properties": {
    "addr:full":"2/c, Via De Gasperi 12040 Govone Govone Cuneo 12040",
    "addr:housenumber":"2 / c",
    "addr:postcode":"12040;12040",
    "addr:street":"Via De Gasperi",
    "iso:country":"IT",
    "sg:address":"2/c, Via De Gasperi 12040 Govone",
    "sg:city":"Govone",
    "sg:classifiers":[
        {
            "category":"Manufacturing",
            "subcategory":"Metals",
            "type":"Manufacturing & Wholesale Goods"
        }
    ],
    "sg:phone":"+39 39017358787",
    "sg:postcode":"12040",
    "sg:province":"Cuneo",
    "sg:tags":[
        "metallurgy",
        "metalworking"
    ],
    "wof:name":"Anaconda S.p.a.",
    "wof:placetype":"venue"
},
  "geometry": {"coordinates":[7.5471105576,44.38879776],"type":"Point"}
}