{
  "type": "Feature",
  "properties": {
    "addr:full":"00197 Roma Roma Roma 00197",
    "addr:postcode":"00197;00197",
    "iso:country":"IT",
    "sg:address":"00197 Roma",
    "sg:city":"Roma",
    "sg:orig_category":"Banche E Servizi Finanziari",
    "sg:phone":"+39 06 8069 0493",
    "sg:postcode":"00197",
    "sg:province":"Roma",
    "wof:name":"Ge.fi Fiduciaria Romana Spa",
    "wof:placetype":"venue"
},
  "geometry": {"coordinates":[12.487312,41.924412],"type":"Point"}
}