{
  "type": "Feature",
  "properties": {
    "addr:full":"25030 Torbole Casaglia Torbole Casaglia Brescia 25030",
    "addr:postcode":"25030;25030",
    "iso:country":"IT",
    "sg:address":"25030 Torbole Casaglia",
    "sg:city":"Torbole Casaglia",
    "sg:orig_category":"Riparazione Dei Mezzi Di Trasporto. Servizi Ausiliari Dei Mezzi Di Trasporto",
    "sg:phone":"+39 030 215 1080",
    "sg:postcode":"25030",
    "sg:province":"Brescia",
    "wof:name":"R.g. Motorsport S.r.l.",
    "wof:placetype":"venue"
},
  "geometry": {"coordinates":[10.135883,45.477154],"type":"Point"}
}