{
  "type": "Feature",
  "properties": {
    "addr:full":"5, Via Prampolini 41043 Formigine Formigine Modena 41043",
    "addr:postcode":"41043;41043",
    "addr:street":"Via Prampolini",
    "iso:country":"IT",
    "sg:address":"5, Via Prampolini 41043 Formigine",
    "sg:city":"Formigine",
    "sg:classifiers":[
        {
            "category":"Manufacturing",
            "subcategory":"Metals",
            "type":"Manufacturing & Wholesale Goods"
        }
    ],
    "sg:phone":"+39 39059556795",
    "sg:postcode":"41043",
    "sg:province":"Modena",
    "sg:tags":[
        "processing"
    ],
    "wof:name":"Fer.gi.mo. (s.n.c.)",
    "wof:placetype":"venue"
},
  "geometry": {"coordinates":[10.8723325729,44.5264816284],"type":"Point"}
}