{
  "type": "Feature",
  "properties": {
    "iso:country":"IT",
    "sg:address":"28077 Prato Sesia",
    "sg:city":"Prato Sesia",
    "sg:orig_category":"Bevande, Vini E Liquori",
    "sg:phone":"+39 0163 850121",
    "sg:postcode":"28077",
    "sg:province":"Novara",
    "wof:name":"Sellmat Srl",
    "wof:placetype":"venue"
},
  "geometry": {"coordinates":[8.357722,45.659885],"type":"Point"}
}