{
  "type": "Feature",
  "properties": {
    "iso:country":"IT",
    "sg:address":"00010 Marcellina",
    "sg:city":"Marcellina",
    "sg:orig_category":"Lavorazioni Metalli, Stampaggio E Saldatura",
    "sg:phone":"+39 0774 425580",
    "sg:postcode":"00010",
    "sg:province":"Roma",
    "sg:website":"http://www.clm.it",
    "wof:name":"C.l.m. Snc Centro Lavorazioni Macchine",
    "wof:placetype":"venue"
},
  "geometry": {"coordinates":[12.799363,42.025253],"type":"Point"}
}