{
  "type": "Feature",
  "properties": {
    "addr:full":"37040 San Gregorio San Gregorio Verona 37040",
    "addr:housenumber":"37040",
    "addr:postcode":"37040",
    "addr:street":"San Gregorio San Gregorio Verona",
    "iso:country":"IT",
    "sg:address":"37040 San Gregorio",
    "sg:city":"San Gregorio",
    "sg:orig_category":"Forniture E Materiali Per Imballaggio E Confezionamento",
    "sg:phone":"+39 0442 47232",
    "sg:postcode":"37040",
    "sg:province":"Verona",
    "wof:name":"Columelli Valentino",
    "wof:placetype":"venue"
},
  "geometry": {"coordinates":[11.3057260513,45.3401184082],"type":"Point"}
}