{
  "type": "Feature",
  "properties": {
    "addr:full":"7, Via Della Cooperazione 37063 Isola Della Scala Isola della Scala Verona 37063",
    "addr:postcode":"37063;37063",
    "addr:street":"Via Della Cooperazione;Scala Verona",
    "iso:country":"IT",
    "sg:address":"7, Via Della Cooperazione 37063 Isola Della Scala",
    "sg:city":"Isola della Scala",
    "sg:classifiers":[
        {
            "category":"Personal",
            "subcategory":"Shoe Repair & Shine",
            "type":"Services"
        }
    ],
    "sg:phone":"+39 045 663 0388",
    "sg:postcode":"37063",
    "sg:province":"Verona",
    "sg:tags":[
        "leather"
    ],
    "wof:name":"Calzaturificio Ilarj (s.r.l.)",
    "wof:placetype":"venue"
},
  "geometry": {"coordinates":[11.00509,45.263237],"type":"Point"}
}