{
  "type": "Feature",
  "properties": {
    "iso:country":"IT",
    "sg:address":"20032 Cormano",
    "sg:city":"Cormano",
    "sg:orig_category":"Carni, Salumi E Pesci",
    "sg:phone":"+39 02 615 0259",
    "sg:postcode":"20032",
    "sg:province":"Milano",
    "wof:name":"Mastrototaro Pietro",
    "wof:placetype":"venue"
},
  "geometry": {"coordinates":[9.150886,45.549397],"type":"Point"}
}