{
  "type": "Feature",
  "properties": {
    "addr:full":"V. Nazionale 7/9/11 Ex 75/77 Meleto 47017 Rocca San Casciano Rocca San Casciano Forl\u00ec-Cesena 47017",
    "addr:housenumber":"7 / 9 / 11 ex 75 / 77",
    "addr:postcode":"47017;47017",
    "addr:street":"Meleto;Forli\u0300-Cesena",
    "iso:country":"IT",
    "sg:address":"V. Nazionale 7/9/11 Ex 75/77 Meleto 47017 Rocca San Casciano",
    "sg:city":"Rocca San Casciano",
    "sg:classifiers":[
        {
            "category":"Shopping",
            "type":"Retail Goods"
        }
    ],
    "sg:phone":"+39 0543 960139",
    "sg:postcode":"47017",
    "sg:province":"Forl\u00ec-Cesena",
    "sg:tags":[
        "finished",
        "-",
        "metallic"
    ],
    "wof:name":"Armetal (s.r.l.)",
    "wof:placetype":"venue"
},
  "geometry": {"coordinates":[11.9804611206,43.9947662354],"type":"Point"}
}