{
  "type": "Feature",
  "properties": {
    "addr:full":"Via Della Ciocca 21026 Gavirate Gavirate Varese 21026",
    "addr:postcode":"21026;21026",
    "addr:street":"Via Della Ciocca",
    "iso:country":"IT",
    "sg:address":"Via Della Ciocca 21026 Gavirate",
    "sg:city":"Gavirate",
    "sg:classifiers":[
        {
            "category":"Shopping",
            "subcategory":"Crafts & Fabrics",
            "type":"Retail Goods"
        }
    ],
    "sg:phone":"+39 0332 743715",
    "sg:postcode":"21026",
    "sg:province":"Varese",
    "wof:name":"Falchi (s.r.l.)",
    "wof:placetype":"venue"
},
  "geometry": {"coordinates":[8.7050199509,45.8414916992],"type":"Point"}
}