{
  "type": "Feature",
  "properties": {
    "addr:full":"20133 Milano Milano Milano 20133",
    "addr:postcode":"20133;20133",
    "iso:country":"IT",
    "sg:address":"20133 Milano",
    "sg:city":"Milano",
    "sg:orig_category":"Servizi Ausiliari Di Analisi, Controllo E Ricerca",
    "sg:phone":"+39 02 701 5091",
    "sg:postcode":"20133",
    "sg:province":"Milano",
    "wof:name":"Procol Srl",
    "wof:placetype":"venue"
},
  "geometry": {"coordinates":[9.233813,45.473484],"type":"Point"}
}