{
  "type": "Feature",
  "properties": {
    "iso:country":"IT",
    "sg:address":"35026 Conselve",
    "sg:city":"Conselve",
    "sg:orig_category":"Architetti - Studi",
    "sg:phone":"+39 049 950 1106",
    "sg:postcode":"35026",
    "sg:province":"Padova",
    "wof:name":"Edilprogettazioni",
    "wof:placetype":"venue"
},
  "geometry": {"coordinates":[11.906807,45.245541],"type":"Point"}
}