{
  "type": "Feature",
  "properties": {
    "addr:full":"14, Via Losa Paolo 10093 Collegno Collegno Torino 10093",
    "addr:postcode":"10093;10093",
    "addr:street":"Via Losa Paolo",
    "iso:country":"IT",
    "sg:address":"14, Via Losa Paolo 10093 Collegno",
    "sg:city":"Collegno",
    "sg:classifiers":[
        {
            "category":"Professional",
            "subcategory":"Engineering",
            "type":"Services"
        }
    ],
    "sg:phone":"+39 011 403 3678",
    "sg:postcode":"10093",
    "sg:province":"Torino",
    "sg:tags":[
        "machine",
        "-",
        "mechanical"
    ],
    "wof:name":"Bilz Fimas (s.p.a.)",
    "wof:placetype":"venue"
},
  "geometry": {"coordinates":[7.590476,45.074829],"type":"Point"}
}