{
  "type": "Feature",
  "properties": {
    "iso:country":"IT",
    "sg:address":"16, Via Martinelli 34015 Muggia",
    "sg:city":"Muggia",
    "sg:classifiers":[
        {
            "category":"Autos & Motor Vehicles",
            "subcategory":"Boat Sales",
            "type":"Retail Goods"
        }
    ],
    "sg:phone":"+39 39040232121",
    "sg:postcode":"34015",
    "sg:province":"Trieste",
    "wof:name":"Arredamenti Civili E Navali Vitrani S.p.a.",
    "wof:placetype":"venue"
},
  "geometry": {"coordinates":[13.80455,45.593903],"type":"Point"}
}