{
  "type": "Feature",
  "properties": {
    "iso:country":"IT",
    "sg:address":"00178 Roma",
    "sg:city":"Roma",
    "sg:orig_category":"Dispositivi Sicurezza E Allarme",
    "sg:phone":"+39 06 7290 1782",
    "sg:postcode":"00178",
    "sg:province":"Roma",
    "wof:name":"Prime Service Srl",
    "wof:placetype":"venue"
},
  "geometry": {"coordinates":[12.575765,41.834484],"type":"Point"}
}