{
  "type": "Feature",
  "properties": {
    "addr:full":"70025 Grumo Appula Grumo Appula Bari 70025",
    "addr:postcode":"70025;70025",
    "iso:country":"IT",
    "sg:address":"70025 Grumo Appula",
    "sg:city":"Grumo Appula",
    "sg:orig_category":"Estetiste",
    "sg:phone":"+39 080 783 9458",
    "sg:postcode":"70025",
    "sg:province":"Bari",
    "wof:name":"Savino Rosa",
    "wof:placetype":"venue"
},
  "geometry": {"coordinates":[16.749126,41.040131],"type":"Point"}
}