{
  "type": "Feature",
  "properties": {
    "iso:country":"IT",
    "sg:address":"Via S. Pietro In Lama 6 73047 Monteroni Di Lecce",
    "sg:city":"Monteroni di Lecce",
    "sg:classifiers":[
        {
            "category":"Food & Beverages",
            "subcategory":"Liquor & Beverages",
            "type":"Retail Goods"
        }
    ],
    "sg:phone":"+39 0832 327182",
    "sg:postcode":"73047",
    "sg:province":"Lecce",
    "sg:tags":[
        "wine",
        "italian"
    ],
    "sg:website":"www.apolloniovini.it",
    "wof:name":"Casa Vinicola Apollonio Srl",
    "wof:placetype":"venue"
},
  "geometry": {"coordinates":[18.156084,40.342037],"type":"Point"}
}