{
  "type": "Feature",
  "properties": {
    "iso:country":"IT",
    "sg:address":"35129 Padova",
    "sg:city":"Padova",
    "sg:orig_category":"Audiovisivi Apparecchi Ed Impianti - Produzione, Commercio E Noleggio",
    "sg:phone":"+39 049 899 0911",
    "sg:postcode":"35129",
    "sg:province":"Padova",
    "sg:website":"http://www.digitalvideoservice.com",
    "wof:name":"Digital Video Service Srl",
    "wof:placetype":"venue"
},
  "geometry": {"coordinates":[11.115941,45.418343],"type":"Point"}
}