{
  "type": "Feature",
  "properties": {
    "iso:country":"IT",
    "sg:address":"21052 Busto Arsizio",
    "sg:city":"Busto Arsizio",
    "sg:orig_category":"Abbigliamento Gestanti E Neonati",
    "sg:phone":"+39 0331 342073",
    "sg:postcode":"21052",
    "sg:province":"Varese",
    "sg:website":"http://www.babyline.it",
    "wof:name":"Minitex Srl",
    "wof:placetype":"venue"
},
  "geometry": {"coordinates":[8.840031,45.597717],"type":"Point"}
}