{
  "type": "Feature",
  "properties": {
    "iso:country":"IT",
    "sg:address":"20146 Milano",
    "sg:city":"Milano",
    "sg:orig_category":"Macchine Ed Impianti Per Edilizia E Lavori Pubblici. Macchine Utensili E Impianti",
    "sg:phone":"+39 02 4895 0084",
    "sg:postcode":"20146",
    "sg:province":"Milano",
    "wof:name":"Nuova Rudeco Srl",
    "wof:placetype":"venue"
},
  "geometry": {"coordinates":[9.14384,45.454079],"type":"Point"}
}