{
  "type": "Feature",
  "properties": {
    "addr:full":"21042 Caronno Pertusella Caronno Pertusella Varese 21042",
    "addr:postcode":"21042;pertusella;21042",
    "addr:street":"Pertusella",
    "iso:country":"IT",
    "sg:address":"21042 Caronno Pertusella",
    "sg:city":"Caronno Pertusella",
    "sg:orig_category":"Abbigliamento Intimo, Calze E Costumi Da Bagno",
    "sg:phone":"+39 02 965 0409",
    "sg:postcode":"21042",
    "sg:province":"Varese",
    "wof:name":"Donzelli Massimo",
    "wof:placetype":"venue"
},
  "geometry": {"coordinates":[9.058083,45.594994],"type":"Point"}
}