{
  "type": "Feature",
  "properties": {
    "iso:country":"IT",
    "sg:address":"90139 Palermo",
    "sg:city":"Palermo",
    "sg:orig_category":"Professionisti - Studi E Servizi Ed Associazioni Di Interesse Aziendale. Associazioni Ed Organismi Di Interesse Pubblico",
    "sg:phone":"+39 091 612 1125",
    "sg:postcode":"90139",
    "sg:province":"Palermo",
    "wof:name":"Italia Lavoro Spa Ufficio Regionale Sicilia",
    "wof:placetype":"venue"
},
  "geometry": {"coordinates":[13.3581314087,38.125289917],"type":"Point"}
}