{
  "type": "Feature",
  "properties": {
    "iso:country":"IT",
    "sg:address":"Zona Artigianale 1 39030 San Giovanni In Valle Aurina",
    "sg:city":"San giovanni in Valle Aurina",
    "sg:classifiers":[
        {
            "category":"Manufacturing",
            "subcategory":"Wood Products",
            "type":"Manufacturing & Wholesale Goods"
        }
    ],
    "sg:phone":"+39 0474 671333",
    "sg:postcode":"39030",
    "sg:province":"Bolzano/Bozen",
    "sg:tags":[
        "made",
        "balcony"
    ],
    "sg:website":"www.ahrntaler.com",
    "wof:name":"Ahrntaler Bauindustrie G.m.b.h - Sr L",
    "wof:placetype":"venue"
},
  "geometry": {"coordinates":[11.358005,46.496716],"type":"Point"}
}