{
  "type": "Feature",
  "properties": {
    "iso:country":"IT",
    "sg:address":"Via Rossini 17 23873 Missaglia",
    "sg:city":"Missaglia",
    "sg:classifiers":[
        {
            "category":"Banks & Credit Unions",
            "subcategory":"Atm",
            "type":"Services"
        }
    ],
    "sg:phone":"+39 039 920 0551",
    "sg:postcode":"23873",
    "sg:province":"Lecco",
    "sg:tags":[
        "link",
        "chain"
    ],
    "sg:website":"www.sircatene.com",
    "wof:name":"Sircatene Spa",
    "wof:placetype":"venue"
},
  "geometry": {"coordinates":[9.390071,45.852982],"type":"Point"}
}