{
  "type": "Feature",
  "properties": {
    "iso:country":"IT",
    "sg:address":"62010 Appignano",
    "sg:city":"Appignano",
    "sg:orig_category":"Riparazione Dei Mezzi Di Trasporto. Servizi Ausiliari Dei Mezzi Di Trasporto",
    "sg:phone":"+39 0733 570018",
    "sg:postcode":"62010",
    "sg:province":"Macerata",
    "wof:name":"Lma Tecnocar Srl",
    "wof:placetype":"venue"
},
  "geometry": {"coordinates":[13.44077,43.301006],"type":"Point"}
}