{
  "type": "Feature",
  "properties": {
    "iso:country":"IT",
    "sg:address":"48018 Faenza",
    "sg:city":"Faenza",
    "sg:orig_category":"Campeggio. Accessori Dei Mezzi Di Trasporto",
    "sg:phone":"+39 0546 646129",
    "sg:postcode":"48018",
    "sg:province":"Ravenna",
    "wof:name":"Tendema Di Denis Magalotti",
    "wof:placetype":"venue"
},
  "geometry": {"coordinates":[11.881554,44.286377],"type":"Point"}
}