{
  "type": "Feature",
  "properties": {
    "addr:full":"Regione Predda Niedda 07100 Sassari Sassari Sassari 07100",
    "addr:postcode":"07100;07100",
    "addr:street":"Regione Predda Niedda",
    "iso:country":"IT",
    "sg:address":"Regione Predda Niedda 07100 Sassari",
    "sg:city":"Sassari",
    "sg:classifiers":[
        {
            "category":"Professional",
            "subcategory":"Advertising",
            "type":"Services"
        }
    ],
    "sg:phone":"+39 39079260501",
    "sg:postcode":"07100",
    "sg:province":"Sassari",
    "sg:tags":[
        "communication",
        "medium"
    ],
    "wof:name":"German C.a.r. (s.r.l.)",
    "wof:placetype":"venue"
},
  "geometry": {"coordinates":[8.553889,40.729443],"type":"Point"}
}