{
  "type": "Feature",
  "properties": {
    "iso:country":"IT",
    "sg:address":"Contrada Piana 82026 Morcone",
    "sg:city":"Morcone",
    "sg:classifiers":[
        {
            "category":"Farming",
            "subcategory":"Livestock Farm",
            "type":"Manufacturing & Wholesale Goods"
        }
    ],
    "sg:phone":"+39 0824 957700",
    "sg:postcode":"82026",
    "sg:province":"Benevento",
    "sg:tags":[
        "agriculture"
    ],
    "wof:name":"Funghi Del Sannio Srl",
    "wof:placetype":"venue"
},
  "geometry": {"coordinates":[14.686857,41.344051],"type":"Point"}
}