{
  "type": "Feature",
  "properties": {
    "iso:country":"IT",
    "sg:address":"40013 Castel Maggiore",
    "sg:city":"Castel Maggiore",
    "sg:orig_category":"Servizi E Lavori Per Arredamento E Industria Del Legno. Servizi Di Magazzinaggio E Movimentazione",
    "sg:phone":"+39 051 701148",
    "sg:postcode":"40013",
    "sg:province":"Bologna",
    "wof:name":"Nuova Sistema Srl",
    "wof:placetype":"venue"
},
  "geometry": {"coordinates":[11.365755,44.559544],"type":"Point"}
}