{
  "type": "Feature",
  "properties": {
    "addr:full":"50013 Campi Bisenzio Campi Bisenzio Firenze 50013",
    "addr:postcode":"50013;50013",
    "addr:street":"Bisenzio",
    "iso:country":"IT",
    "sg:address":"50013 Campi Bisenzio",
    "sg:city":"Campi Bisenzio",
    "sg:orig_category":"Forniture Per Abbigliamento E Pelletterie",
    "sg:phone":"+39 055 896 4490",
    "sg:postcode":"50013",
    "sg:province":"Firenze",
    "wof:name":"Mini-metal Snc",
    "wof:placetype":"venue"
},
  "geometry": {"coordinates":[11.1267490387,43.8064651489],"type":"Point"}
}