{
  "type": "Feature",
  "properties": {
    "addr:full":"10043 Orbassano Orbassano Torino 10043",
    "addr:postcode":"10043;10043",
    "iso:country":"IT",
    "sg:address":"10043 Orbassano",
    "sg:city":"Orbassano",
    "sg:orig_category":"Acquedotti, Gasdotti Ed Oleodotti - Impianti Ed Attrezzature",
    "sg:phone":"+39 011 900 3731",
    "sg:postcode":"10043",
    "sg:province":"Torino",
    "wof:name":"Impresa Sirio Srl",
    "wof:placetype":"venue"
},
  "geometry": {"coordinates":[7.535295,45.005138],"type":"Point"}
}