{
  "type": "Feature",
  "properties": {
    "iso:country":"IT",
    "sg:address":"Via Autostrada, 16/18 21040 Jerago Con Orago",
    "sg:city":"Jerago con Orago",
    "sg:classifiers":[
        {
            "category":"Wholesale",
            "subcategory":"Vending Machines",
            "type":"Manufacturing & Wholesale Goods"
        }
    ],
    "sg:phone":"+39 0331 219455",
    "sg:postcode":"21040",
    "sg:province":"Varese",
    "sg:tags":[
        "casting",
        "miscellaneous",
        "machines"
    ],
    "sg:website":"www.liasa.it",
    "wof:name":"L.i.a.s.a. Spa",
    "wof:placetype":"venue"
},
  "geometry": {"coordinates":[8.806528,45.748672],"type":"Point"}
}