{
  "type": "Feature",
  "properties": {
    "iso:country":"IT",
    "sg:address":"89018 Villa San Giovanni",
    "sg:city":"Villa San Giovanni",
    "sg:orig_category":"Abbigliamento Esterno, Maglierie E Pelliccerie. Servizi E Lavori Per Abbigliamento E Pelletterie",
    "sg:phone":"+39 0965 756168",
    "sg:postcode":"89018",
    "sg:province":"Reggio Di Calabria",
    "wof:name":"Corigliano Pasquale",
    "wof:placetype":"venue"
},
  "geometry": {"coordinates":[15.636119,38.222595],"type":"Point"}
}