{
  "type": "Feature",
  "properties": {
    "addr:full":"06070 Perugia Perugia 06070",
    "addr:postcode":"06070;06070",
    "iso:country":"IT",
    "sg:address":"06070 Perugia",
    "sg:orig_category":"Agenzie D'affari E Servizi Commerciali",
    "sg:phone":"+39 800 117 766",
    "sg:postcode":"06070",
    "sg:province":"Perugia",
    "wof:name":"Pec - Pronto Emergenza Casa Srl",
    "wof:placetype":"venue"
},
  "geometry": {"coordinates":[12.330222,43.052582],"type":"Point"}
}