{
  "type": "Feature",
  "properties": {
    "iso:country":"IT",
    "sg:address":"16158 Genova",
    "sg:city":"Genova",
    "sg:orig_category":"Trasporti E Spedizioni Merci",
    "sg:phone":"+39 010 612 1768",
    "sg:postcode":"16158",
    "sg:province":"Genova",
    "wof:name":"Silt Sistemi Integrati Di Logistica E Trasporti Srl",
    "wof:placetype":"venue"
},
  "geometry": {"coordinates":[8.693069,44.454037],"type":"Point"}
}