{
  "type": "Feature",
  "properties": {
    "iso:country":"IT",
    "sg:address":"30, Via Trentino Alto Adige 41049 Sassuolo",
    "sg:city":"Sassuolo",
    "sg:classifiers":[
        {
            "category":"Professional",
            "subcategory":"Engineering",
            "type":"Services"
        }
    ],
    "sg:phone":"+39 0536 805012",
    "sg:postcode":"41049",
    "sg:province":"Modena",
    "sg:tags":[
        "machine",
        "-",
        "mechanical"
    ],
    "wof:name":"Tecnomeccanica Di Pinelli Anastasi E C. (s.n.c.)",
    "wof:placetype":"venue"
},
  "geometry": {"coordinates":[10.802183,44.563446],"type":"Point"}
}