{
  "type": "Feature",
  "properties": {
    "iso:country":"IT",
    "sg:address":"16129 Genova",
    "sg:city":"Genova",
    "sg:orig_category":"Medici. Assicurazioni E Servizi Assicurativi. Avvocati, Notai E Servizi Legali. Professionisti - Studi E Servizi Ed Associazioni Di Interesse Aziendale",
    "sg:phone":"+39 010 594714",
    "sg:postcode":"16129",
    "sg:province":"Genova",
    "wof:name":"Bruni Gianlorenzo",
    "wof:placetype":"venue"
},
  "geometry": {"coordinates":[8.9507551193,44.4000740051],"type":"Point"}
}