{
  "type": "Feature",
  "properties": {
    "iso:country":"IT",
    "sg:address":"Corso Sempione 38; Milano; 20145",
    "sg:city":"Milano",
    "sg:classifiers":[
        {
            "category":"Banks & Credit Unions",
            "subcategory":"Bank",
            "type":"Services"
        }
    ],
    "sg:phone":"+39 02 3310 3333",
    "sg:postcode":"20145",
    "sg:province":"Milano",
    "wof:name":"Banca Popolare Di Verona",
    "wof:placetype":"venue"
},
  "geometry": {"coordinates":[9.165672,45.481312],"type":"Point"}
}