{
  "type": "Feature",
  "properties": {
    "iso:country":"IT",
    "sg:address":"16033 Lavagna",
    "sg:city":"Lavagna",
    "sg:classifiers":[
        {
            "category":"Health Services",
            "subcategory":"Health Practitioner",
            "type":"Services"
        }
    ],
    "sg:phone":"+39 0185 393862",
    "sg:postcode":"16033",
    "sg:province":"Genova",
    "sg:tags":[
        "medici"
    ],
    "wof:name":"Coriandolo Diego",
    "wof:placetype":"venue"
},
  "geometry": {"coordinates":[9.372858,44.301552],"type":"Point"}
}