{
  "type": "Feature",
  "properties": {
    "addr:full":"31040 Chiarano Chiarano Treviso 31040",
    "addr:postcode":"31040;31040",
    "iso:country":"IT",
    "sg:address":"31040 Chiarano",
    "sg:city":"Chiarano",
    "sg:orig_category":"Prodotti E Manufatti In Materie Plastiche",
    "sg:phone":"+39 0422 746925",
    "sg:postcode":"31040",
    "sg:province":"Treviso",
    "wof:name":"Europlast Srl",
    "wof:placetype":"venue"
},
  "geometry": {"coordinates":[12.4939575195,45.7036972046],"type":"Point"}
}