{
  "type": "Feature",
  "properties": {
    "iso:country":"IT",
    "sg:address":"95021 Aci Castello",
    "sg:city":"Aci Castello",
    "sg:classifiers":[
        {
            "category":"Building & Trades",
            "subcategory":"Locksmith",
            "type":"Services"
        }
    ],
    "sg:phone":"+39 095 711 1386",
    "sg:postcode":"95021",
    "sg:province":"Catania",
    "sg:tags":[
        "livestock",
        "civil",
        "industry",
        "work",
        "breeding",
        "works",
        "agriculture"
    ],
    "wof:name":"Vivai Aronica - Finflora",
    "wof:placetype":"venue"
},
  "geometry": {"coordinates":[15.131743,37.551105],"type":"Point"}
}