{
  "type": "Feature",
  "properties": {
    "iso:country":"IT",
    "sg:address":"12, Via Nazionale 87060 Crosia",
    "sg:city":"Crosia",
    "sg:classifiers":[
        {
            "category":"Autos & Motor Vehicles",
            "subcategory":"Boat Sales",
            "type":"Retail Goods"
        }
    ],
    "sg:phone":"+39 39098343185",
    "sg:postcode":"87060",
    "sg:province":"Cosenza",
    "wof:name":"Euroyachting S.r.l.",
    "wof:placetype":"venue"
},
  "geometry": {"coordinates":[16.775982,39.604542],"type":"Point"}
}