{
  "type": "Feature",
  "properties": {
    "iso:country":"IT",
    "sg:address":"57037 Portoferraio",
    "sg:city":"Portoferraio",
    "sg:orig_category":"Barche, Canotti Pneumatici E Motoscafi - Vendita Al Dettaglio",
    "sg:phone":"+39 0565 916665",
    "sg:postcode":"57037",
    "sg:province":"Livorno",
    "wof:name":"Esaom Cesa Spa",
    "wof:placetype":"venue"
},
  "geometry": {"coordinates":[10.312546,42.810638],"type":"Point"}
}