{
  "type": "Feature",
  "properties": {
    "iso:country":"IT",
    "sg:address":"27049 Stradella",
    "sg:city":"Stradella",
    "sg:orig_category":"Prodotti Di Base E Forniture Per Industria Alimentare E Bevande",
    "sg:phone":"+39 0385 49808",
    "sg:postcode":"27049",
    "sg:province":"Pavia",
    "wof:name":"Veneri Leonardo",
    "wof:placetype":"venue"
},
  "geometry": {"coordinates":[9.3059387207,45.0716896057],"type":"Point"}
}