{
  "type": "Feature",
  "properties": {
    "addr:full":"80047 San Giuseppe Vesuviano Casilli Napoli 80047",
    "addr:postcode":"80047;80047",
    "iso:country":"IT",
    "sg:address":"80047 San Giuseppe Vesuviano",
    "sg:city":"Casilli",
    "sg:orig_category":"Forniture Industriali Per Prevenzione, Controllo E Sicurezza",
    "sg:phone":"+39 081 827 1318",
    "sg:postcode":"80047",
    "sg:province":"Napoli",
    "sg:website":"http://www.tucer.it",
    "wof:name":"Tucer Di Cerciello Giuseppe E C. Snc",
    "wof:placetype":"venue"
},
  "geometry": {"coordinates":[14.503408432,40.826007843],"type":"Point"}
}