{
  "type": "Feature",
  "properties": {
    "iso:country":"IT",
    "sg:address":"2, Via Colombarotto 40026 Imola",
    "sg:city":"Imola",
    "sg:classifiers":[
        {
            "category":"Home & Garden",
            "subcategory":"Home Furnishings",
            "type":"Retail Goods"
        }
    ],
    "sg:phone":"+39 0542 640443",
    "sg:postcode":"40026",
    "sg:province":"Bologna",
    "sg:tags":[
        "household"
    ],
    "wof:name":"Tre Bi S.r.l.",
    "wof:placetype":"venue"
},
  "geometry": {"coordinates":[11.654126,44.398643],"type":"Point"}
}