{
  "type": "Feature",
  "properties": {
    "iso:country":"IT",
    "sg:address":"20017 Rho",
    "sg:city":"Rho",
    "sg:orig_category":"Pubblica Amministrazione",
    "sg:phone":"+39 02 933321",
    "sg:postcode":"20017",
    "sg:province":"Milano",
    "wof:name":"Municipio Di Rho",
    "wof:placetype":"venue"
},
  "geometry": {"coordinates":[9.1007804871,45.5036621094],"type":"Point"}
}