{
  "type": "Feature",
  "properties": {
    "iso:country":"IT",
    "sg:address":"4, Via Dei Templari 33080 San Quirino",
    "sg:city":"San Quirino",
    "sg:classifiers":[
        {
            "category":"Wholesale",
            "subcategory":"Machinery & Supplies",
            "type":"Manufacturing & Wholesale Goods"
        }
    ],
    "sg:phone":"+39 39043491053",
    "sg:postcode":"33080",
    "sg:province":"Pordenone",
    "sg:tags":[
        "-",
        "agriculture",
        "equipment"
    ],
    "wof:name":"Zilli (s.n.c.)",
    "wof:placetype":"venue"
},
  "geometry": {"coordinates":[12.666106,46.018726],"type":"Point"}
}