{
  "type": "Feature",
  "properties": {
    "iso:country":"IT",
    "sg:address":"20063 Cernusco Sul Naviglio",
    "sg:city":"Cernusco sul Naviglio",
    "sg:orig_category":"Nautica. Accessori Dei Mezzi Di Trasporto",
    "sg:phone":"+39 02 9210 2661",
    "sg:postcode":"20063",
    "sg:province":"Milano",
    "wof:name":"Lauterio & Casiraghi Srl",
    "wof:placetype":"venue"
},
  "geometry": {"coordinates":[9.338531,45.502674],"type":"Point"}
}