{
  "type": "Feature",
  "properties": {
    "addr:full":"Via De Ambrosiis 2/4/6 15067 Novi Ligure Novi Ligure Alessandria 15067",
    "addr:housenumber":"2 / 4 / 6",
    "addr:postcode":"15067;15067",
    "addr:street":"Via De Ambrosiis",
    "iso:country":"IT",
    "sg:address":"Via De Ambrosiis 2/4/6 15067 Novi Ligure",
    "sg:city":"Novi Ligure",
    "sg:classifiers":[
        {
            "category":"Shopping",
            "subcategory":"Pharmacy",
            "type":"Retail Goods"
        }
    ],
    "sg:phone":"+39 0143 3131",
    "sg:postcode":"15067",
    "sg:province":"Alessandria",
    "sg:tags":[
        "pharmaceutical"
    ],
    "sg:website":"www.bioindustria.it",
    "wof:name":"Bioindustria L.i.m. Spa",
    "wof:placetype":"venue"
},
  "geometry": {"coordinates":[8.6169509888,44.9132156372],"type":"Point"}
}