{
  "type": "Feature",
  "properties": {
    "addr:full":"24050 Grassobbio Grassobbio Bergamo 24050",
    "addr:postcode":"24050;24050",
    "iso:country":"IT",
    "sg:address":"24050 Grassobbio",
    "sg:city":"Grassobbio",
    "sg:orig_category":"Forniture Alle Strutture Ricettive. Macchine E Impianti Per Attivita' Commerciali Ed Artigianali",
    "sg:phone":"+39 035 452 2093",
    "sg:postcode":"24050",
    "sg:province":"Bergamo",
    "wof:name":"A.c.e.m. Automatic Cappuccno Espresso Machines Srl",
    "wof:placetype":"venue"
},
  "geometry": {"coordinates":[9.7267217636,45.6578140259],"type":"Point"}
}