{
  "type": "Feature",
  "properties": {
    "iso:country":"IT",
    "sg:address":"43, Via Statale 23888 Perego",
    "sg:city":"Perego",
    "sg:classifiers":[
        {
            "category":"Building & Trades",
            "subcategory":"Construction",
            "type":"Services"
        }
    ],
    "sg:phone":"+39 390 395 7608",
    "sg:postcode":"23888",
    "sg:province":"Lecco",
    "sg:tags":[
        "work",
        "public"
    ],
    "wof:name":"Gerosa Giovanni (s.p.a.)",
    "wof:placetype":"venue"
},
  "geometry": {"coordinates":[9.368297,45.737129],"type":"Point"}
}