{
  "type": "Feature",
  "properties": {
    "iso:country":"IT",
    "sg:address":"90015 Cefal\u00f9",
    "sg:orig_category":"Banche Ed Istituti Di Credito E Risparmio",
    "sg:phone":"+39 0921 923956",
    "sg:postcode":"90015",
    "sg:province":"Palermo",
    "wof:name":"Area Banca Spa",
    "wof:placetype":"venue"
},
  "geometry": {"coordinates":[14.018844,38.008415],"type":"Point"}
}