{
  "type": "Feature",
  "properties": {
    "addr:full":"20132 Milano Milano Milano 20132",
    "addr:postcode":"20132;20132",
    "iso:country":"IT",
    "sg:address":"20132 Milano",
    "sg:city":"Milano",
    "sg:orig_category":"Elettrotecnica Industriale, Prodotti E Apparecchiature. Elettronica Industriale, Prodotti E Apparecchiature. Macchine, Strumenti Ed Apparecchi Per Attivita' Industriali",
    "sg:phone":"+39 02 284 7843",
    "sg:postcode":"20132",
    "sg:province":"Milano",
    "wof:name":"3 B Elettronica Di Brioschi Maria Grazia",
    "wof:placetype":"venue"
},
  "geometry": {"coordinates":[9.238615,45.494041],"type":"Point"}
}