{
  "type": "Feature",
  "properties": {
    "iso:country":"IT",
    "sg:address":"20090 Segrate",
    "sg:city":"Segrate",
    "sg:orig_category":"Legno E Semilavorati. Manufatti Edili E Prefabbricati",
    "sg:phone":"+39 02 2692 3021",
    "sg:postcode":"20090",
    "sg:province":"Milano",
    "wof:name":"Farina Sergio",
    "wof:placetype":"venue"
},
  "geometry": {"coordinates":[9.296718,45.48745],"type":"Point"}
}