{
  "type": "Feature",
  "properties": {
    "iso:country":"IT",
    "sg:address":"55025 Coreglia Antelminelli",
    "sg:city":"Coreglia Antelminelli",
    "sg:orig_category":"Materiali Edili",
    "sg:phone":"+39 0583 78488",
    "sg:postcode":"55025",
    "sg:province":"Lucca",
    "wof:name":"Paganucci Marco Pietro",
    "wof:placetype":"venue"
},
  "geometry": {"coordinates":[10.523468,44.060966],"type":"Point"}
}