{
  "type": "Feature",
  "properties": {
    "iso:country":"IT",
    "sg:address":"Via Zona Industriale 83051 Nusco",
    "sg:city":"Nusco",
    "sg:classifiers":[
        {
            "category":"Manufacturing",
            "subcategory":"Metals",
            "type":"Manufacturing & Wholesale Goods"
        }
    ],
    "sg:phone":"+39 0827 607389",
    "sg:postcode":"83051",
    "sg:province":"Avellino",
    "sg:tags":[
        "metallurgy",
        "metalworking"
    ],
    "wof:name":"Rifometal Spa",
    "wof:placetype":"venue"
},
  "geometry": {"coordinates":[14.792722702,40.9147491455],"type":"Point"}
}