{
  "type": "Feature",
  "properties": {
    "iso:country":"IT",
    "sg:address":"Via Liberta 1; Orgiano; 36040",
    "sg:city":"Orgiano",
    "sg:classifiers":[
        {
            "category":"Banks & Credit Unions",
            "subcategory":"Bank",
            "type":"Services"
        }
    ],
    "sg:phone":"+39 0444 874100",
    "sg:postcode":"36040",
    "sg:province":"Vicenza",
    "wof:name":"Banca Popolare Vicentina Scparl",
    "wof:placetype":"venue"
},
  "geometry": {"coordinates":[11.465203,45.349693],"type":"Point"}
}