{
  "type": "Feature",
  "properties": {
    "iso:country":"IT",
    "sg:address":"21052 Busto Arsizio",
    "sg:city":"Busto Arsizio",
    "sg:orig_category":"Arredo Cucina Ed Elettrodomestici. Elettrodomestici",
    "sg:phone":"+39 0331 678930",
    "sg:postcode":"21052",
    "sg:province":"Varese",
    "wof:name":"Brel Elettrica",
    "wof:placetype":"venue"
},
  "geometry": {"coordinates":[8.848387,45.618679],"type":"Point"}
}