{
  "type": "Feature",
  "properties": {
    "iso:country":"IT",
    "sg:address":"20033 Desio",
    "sg:city":"Desio",
    "sg:orig_category":"Impiantistica E Prodotti Tecnologici Per Edilizia. Forniture Industriali Per Prevenzione, Controllo E Sicurezza",
    "sg:phone":"+39 036 262 8059",
    "sg:postcode":"20033",
    "sg:province":"Milano",
    "wof:name":"Silmar Di Cattaneo Maria Rosa",
    "wof:placetype":"venue"
},
  "geometry": {"coordinates":[9.2052,45.636135],"type":"Point"}
}