{
  "type": "Feature",
  "properties": {
    "addr:full":"50121 Firenze Firenze Firenze 50121",
    "addr:postcode":"50121;50121",
    "iso:country":"IT",
    "sg:address":"50121 Firenze",
    "sg:city":"Firenze",
    "sg:classifiers":[
        {
            "category":"Insurance",
            "subcategory":"Insurance Agent",
            "type":"Services"
        }
    ],
    "sg:phone":"+39 055 500 2072",
    "sg:postcode":"50121",
    "sg:province":"Firenze",
    "sg:tags":[
        "factoring"
    ],
    "wof:name":"Credigest Srl",
    "wof:placetype":"venue"
},
  "geometry": {"coordinates":[11.2621040344,43.7805900574],"type":"Point"}
}