{
  "type": "Feature",
  "properties": {
    "addr:full":"00185 Roma Roma Roma 00185",
    "addr:postcode":"00185;00185",
    "iso:country":"IT",
    "sg:address":"00185 Roma",
    "sg:city":"Roma",
    "sg:orig_category":"Apparecchiature E Sistemi Per Magazzinaggio E Movimentazione",
    "sg:phone":"+39 06 490061",
    "sg:postcode":"00185",
    "sg:province":"Roma",
    "wof:name":"Samar",
    "wof:placetype":"venue"
},
  "geometry": {"coordinates":[12.510108,41.898891],"type":"Point"}
}