{
  "type": "Feature",
  "properties": {
    "iso:country":"IT",
    "sg:address":"Via Zurlo; Angri; 84012",
    "sg:city":"Angri",
    "sg:classifiers":[
        {
            "category":"Banks & Credit Unions",
            "subcategory":"Bank",
            "type":"Services"
        }
    ],
    "sg:phone":"+39 081 948022",
    "sg:postcode":"84012",
    "sg:province":"Salerno",
    "wof:name":"Banco Di Napoli Spa",
    "wof:placetype":"venue"
},
  "geometry": {"coordinates":[14.573208,40.739105],"type":"Point"}
}