{
  "type": "Feature",
  "properties": {
    "addr:full":"38038 Tesero Tesero Trento 38038",
    "addr:postcode":"38038;38038",
    "iso:country":"IT",
    "sg:address":"38038 Tesero",
    "sg:city":"Tesero",
    "sg:orig_category":"Servizi E Lavori Per Arredamento E Industria Del Legno. Servizi E Lavori Per Edilizia E Lavori Pubblici",
    "sg:phone":"+39 0462 814359",
    "sg:postcode":"38038",
    "sg:province":"Trento",
    "wof:name":"Falegnameria Sociale 2000 Sas",
    "wof:placetype":"venue"
},
  "geometry": {"coordinates":[11.519054,46.282936],"type":"Point"}
}