{
  "type": "Feature",
  "properties": {
    "iso:country":"IT",
    "sg:address":"Via California 2 23895 Tabiago",
    "sg:city":"Tabiago",
    "sg:classifiers":[
        {
            "category":"Shopping",
            "subcategory":"Clothing, Apparel, & Fashions",
            "type":"Retail Goods"
        }
    ],
    "sg:phone":"+39 031 690621",
    "sg:postcode":"23895",
    "sg:province":"Lecco",
    "sg:tags":[
        "sportswear"
    ],
    "wof:name":"Station Wagon Srl",
    "wof:placetype":"venue"
},
  "geometry": {"coordinates":[9.390071,45.852982],"type":"Point"}
}