{
  "type": "Feature",
  "properties": {
    "iso:country":"IT",
    "sg:address":"Via Pasubio 45 63039 San Benedetto Del Tronto",
    "sg:city":"San Benedetto del Tronto",
    "sg:classifiers":[
        {
            "category":"Utilities",
            "subcategory":"Fuel Oil & Lpg",
            "type":"Services"
        }
    ],
    "sg:phone":"+39 0735 75971",
    "sg:postcode":"63039",
    "sg:province":"Ascoli Piceno",
    "sg:tags":[
        "used",
        "vehicles"
    ],
    "wof:name":"Fimi Spa",
    "wof:placetype":"venue"
},
  "geometry": {"coordinates":[13.895503,42.900276],"type":"Point"}
}