{
  "type": "Feature",
  "properties": {
    "addr:full":"43012 Fontanellato Fontanellato Parma 43012",
    "addr:postcode":"43012;43012",
    "iso:country":"IT",
    "sg:address":"43012 Fontanellato",
    "sg:city":"Fontanellato",
    "sg:orig_category":"Apparecchiature E Sistemi Per Magazzinaggio E Movimentazione",
    "sg:phone":"+39 0524 527518",
    "sg:postcode":"43012",
    "sg:province":"Parma",
    "wof:name":"Amaf Di Fini Domenico",
    "wof:placetype":"venue"
},
  "geometry": {"coordinates":[10.166826,44.892952],"type":"Point"}
}