{
  "type": "Feature",
  "properties": {
    "iso:country":"IT",
    "sg:address":"56029 S.croce Sull'arno",
    "sg:orig_category":"Teloni Impermeabili",
    "sg:phone":"+39 0571 360125",
    "sg:postcode":"56029",
    "sg:province":"Pisa",
    "wof:name":"Di Vita Antonio",
    "wof:placetype":"venue"
},
  "geometry": {"coordinates":[10.396585,43.716137],"type":"Point"}
}