{
  "type": "Feature",
  "properties": {
    "iso:country":"IT",
    "sg:address":"24030 Villa D'adda",
    "sg:orig_category":"Impermeabilizzazioni Edili - Lavori",
    "sg:phone":"+39 035 784652",
    "sg:postcode":"24030",
    "sg:province":"Bergamo",
    "wof:name":"D'ippolito Giuseppe",
    "wof:placetype":"venue"
},
  "geometry": {"coordinates":[9.462833,45.715019],"type":"Point"}
}