{
  "type": "Feature",
  "properties": {
    "iso:country":"IT",
    "sg:address":"18/20, V. Del Paradiso 53100 Siena",
    "sg:city":"Siena",
    "sg:classifiers":[
        {
            "category":"Food & Beverages",
            "subcategory":"Groceries & Convenience Stores",
            "type":"Retail Goods"
        }
    ],
    "sg:phone":"+39 39057748446",
    "sg:postcode":"53100",
    "sg:province":"Siena",
    "sg:tags":[
        "drink"
    ],
    "sg:website":"http://www.cantinadelbrunello.com",
    "wof:name":"Enoteca Cantina Del Brunello",
    "wof:placetype":"venue"
},
  "geometry": {"coordinates":[11.328159,43.320988],"type":"Point"}
}