{
  "type": "Feature",
  "properties": {
    "addr:full":"36075 Montecchio Maggiore Montecchio Maggiore Vicenza 36075",
    "addr:postcode":"36075;36075",
    "iso:country":"IT",
    "sg:address":"36075 Montecchio Maggiore",
    "sg:city":"Montecchio Maggiore",
    "sg:orig_category":"Prodotti E Manufatti In Materie Plastiche. Forniture Per Attivita' Industriali",
    "sg:phone":"+39 0444 696511",
    "sg:postcode":"36075",
    "sg:province":"Vicenza",
    "sg:website":"http://www.plasticanardon.com",
    "wof:name":"Plastica Nardon Spa",
    "wof:placetype":"venue"
},
  "geometry": {"coordinates":[11.4867181778,45.5066452026],"type":"Point"}
}