{
  "type": "Feature",
  "properties": {
    "addr:full":"20123 Milano Milano Milano 20123",
    "addr:postcode":"20123;20123",
    "iso:country":"IT",
    "sg:address":"20123 Milano",
    "sg:city":"Milano",
    "sg:orig_category":"Calzature, Pelletterie E Pelli. Servizi E Lavori Per Abbigliamento E Pelletterie",
    "sg:phone":"+39 02 4800 7941",
    "sg:postcode":"20123",
    "sg:province":"Milano",
    "wof:name":"Fabbri Luigi",
    "wof:placetype":"venue"
},
  "geometry": {"coordinates":[9.166226,45.466],"type":"Point"}
}