{
  "type": "Feature",
  "properties": {
    "addr:full":"22063 Cant\u00f9 Como 22063",
    "addr:postcode":"22063;22063",
    "iso:country":"IT",
    "sg:address":"22063 Cant\u00f9",
    "sg:orig_category":"Minuterie Metalliche E Ferramenta",
    "sg:phone":"+39 031 714817",
    "sg:postcode":"22063",
    "sg:province":"Como",
    "sg:website":"http://www.mionisrl.it",
    "wof:name":"Mioni Srl",
    "wof:placetype":"venue"
},
  "geometry": {"coordinates":[9.1452255249,45.7369346619],"type":"Point"}
}