{
  "type": "Feature",
  "properties": {
    "addr:full":"95126 Catania Catania Catania 95126",
    "addr:postcode":"95126;95126",
    "iso:country":"IT",
    "sg:address":"95126 Catania",
    "sg:city":"Catania",
    "sg:orig_category":"Fotografia - Servizi, Studi, Sviluppo E Stampa",
    "sg:phone":"+39 095 439782",
    "sg:postcode":"95126",
    "sg:province":"Catania",
    "wof:name":"Fotomateriale Ulisse Srl",
    "wof:placetype":"venue"
},
  "geometry": {"coordinates":[15.0958557129,37.5230369568],"type":"Point"}
}