{
  "type": "Feature",
  "properties": {
    "iso:country":"IT",
    "sg:address":"40121 Bologna",
    "sg:city":"Bologna",
    "sg:orig_category":"Cartotecnica E Servizi. Composizione, Stampa E Confezione. Forniture E Prodotti Informatici. Forniture Per Congressi, Fiere E Manifestazioni",
    "sg:phone":"+39 051 296 1233",
    "sg:postcode":"40121",
    "sg:province":"Bologna",
    "wof:name":"Matica System S.r.l.",
    "wof:placetype":"venue"
},
  "geometry": {"coordinates":[11.342785,44.497658],"type":"Point"}
}