{
  "type": "Feature",
  "properties": {
    "iso:country":"IT",
    "sg:address":"20060 Vignate",
    "sg:city":"Vignate",
    "sg:orig_category":"Scuole E Servizi Scolastici",
    "sg:phone":"+39 02 956 6171",
    "sg:postcode":"20060",
    "sg:province":"Milano",
    "wof:name":"Comune Di Vignate",
    "wof:placetype":"venue"
},
  "geometry": {"coordinates":[9.319864,45.481304],"type":"Point"}
}