{
  "type": "Feature",
  "properties": {
    "addr:full":"33/r., Via Balbi 16126 Genova Genova Genova 16126",
    "addr:housenumber":"33 / r.",
    "addr:postcode":"16126;16126",
    "addr:street":"Via Balbi",
    "iso:country":"IT",
    "sg:address":"33/r., Via Balbi 16126 Genova",
    "sg:city":"Genova",
    "sg:classifiers":[
        {
            "category":"Travel",
            "subcategory":"Travel Agent",
            "type":"Entertainment"
        }
    ],
    "sg:phone":"+39 39010261923",
    "sg:postcode":"16126",
    "sg:province":"Genova",
    "sg:tags":[
        "business"
    ],
    "wof:name":"Albergo Vittoria & Orlandini",
    "wof:placetype":"venue"
},
  "geometry": {"coordinates":[8.888069,44.967991],"type":"Point"}
}