{
  "type": "Feature",
  "properties": {
    "addr:full":"Via Cuneo 14 10090 San Bernardo D'ivrea Torino 10090",
    "addr:housenumber":"14",
    "addr:postcode":"10090;10090",
    "addr:street":"Via Cuneo;D'Ivrea",
    "iso:country":"IT",
    "sg:address":"Via Cuneo 14 10090 San Bernardo D'ivrea",
    "sg:orig_category":"Readers And Recorders For Magnetic Cards",
    "sg:phone":"+39 0125 631887",
    "sg:postcode":"10090",
    "sg:province":"Torino",
    "sg:website":"www.emk.it",
    "wof:name":"Emk Srl",
    "wof:placetype":"venue"
},
  "geometry": {"coordinates":[7.686619,45.07056],"type":"Point"}
}