{
  "type": "Feature",
  "properties": {
    "iso:country":"IT",
    "sg:address":"21047 Saronno",
    "sg:city":"Saronno",
    "sg:classifiers":[
        {
            "category":"Health Services",
            "subcategory":"Health Practitioner",
            "type":"Services"
        }
    ],
    "sg:phone":"+39 02 960 6458",
    "sg:postcode":"21047",
    "sg:province":"Varese",
    "sg:tags":[
        "medici"
    ],
    "wof:name":"Morisi Fulvio",
    "wof:placetype":"venue"
},
  "geometry": {"coordinates":[8.889796257,45.7803726196],"type":"Point"}
}