{
  "type": "Feature",
  "properties": {
    "iso:country":"IT",
    "sg:address":"10, Via Manin 21010 Cardano Al Campo",
    "sg:city":"Cardano al Campo",
    "sg:classifiers":[
        {
            "category":"Shopping",
            "subcategory":"Crafts & Fabrics",
            "type":"Retail Goods"
        }
    ],
    "sg:phone":"+39 0331 261794",
    "sg:postcode":"21010",
    "sg:province":"Varese",
    "wof:name":"Tessitura Aspesi Oddone (s.n.c.)",
    "wof:placetype":"venue"
},
  "geometry": {"coordinates":[8.7766466141,45.6439285278],"type":"Point"}
}