{
  "type": "Feature",
  "properties": {
    "addr:full":"31, Via Dante 22060 Carugo Carugo Como 22060",
    "addr:postcode":"22060;22060",
    "addr:street":"Via Dante",
    "iso:country":"IT",
    "sg:address":"31, Via Dante 22060 Carugo",
    "sg:city":"Carugo",
    "sg:classifiers":[
        {
            "category":"Manufacturing",
            "subcategory":"Wood Products",
            "type":"Manufacturing & Wholesale Goods"
        }
    ],
    "sg:phone":"+39 39031746165",
    "sg:postcode":"22060",
    "sg:province":"Como",
    "sg:tags":[
        "furniture"
    ],
    "wof:name":"Fratelli Longoni (s.n.c.)",
    "wof:placetype":"venue"
},
  "geometry": {"coordinates":[9.170269,45.673351],"type":"Point"}
}