{
  "type": "Feature",
  "properties": {
    "iso:country":"IT",
    "sg:address":"06087 Perugia",
    "sg:orig_category":"Studi E Consulenze Amministrative, Commerciali E Aziendali. Studi E Consulenze Tecniche E Industriali. Consulenze Tecniche, Amministrative E Perizie",
    "sg:phone":"+39 075 599 6735",
    "sg:province":"PG",
    "wof:name":"Qualita' X Competere Snc Di Franceschelli & C.",
    "wof:placetype":"venue"
},
  "geometry": {"coordinates":[-72.88690200000001,41.757599],"type":"Point"}
}