{
  "type": "Feature",
  "properties": {
    "iso:country":"IT",
    "sg:address":"Via Tretti 6 36030 Fara Vicentino",
    "sg:city":"Fara Vicentino",
    "sg:classifiers":[
        {
            "category":"Bars & Pubs",
            "subcategory":"Hookah Bar",
            "type":"Food & Drink"
        }
    ],
    "sg:phone":"+39 0445 874883",
    "sg:postcode":"36030",
    "sg:province":"Vicenza",
    "sg:tags":[
        "industry",
        "pump"
    ],
    "sg:website":"www.tecnicapompe.com",
    "wof:name":"Tecnicapompe Zanin Srl",
    "wof:placetype":"venue"
},
  "geometry": {"coordinates":[11.5475206375,45.7132148743],"type":"Point"}
}