{
  "type": "Feature",
  "properties": {
    "iso:country":"IT",
    "sg:address":"12058 Santo Stefano Belbo",
    "sg:city":"Santo Stefano Belbo",
    "sg:orig_category":"Legno E Semilavorati",
    "sg:phone":"+39 0141 844234",
    "sg:postcode":"12058",
    "sg:province":"Cuneo",
    "wof:name":"I.l.a.s. Di Ariano & Careddu Srl",
    "wof:placetype":"venue"
},
  "geometry": {"coordinates":[8.234879,44.712418],"type":"Point"}
}