{
  "type": "Feature",
  "properties": {
    "addr:full":"20152 Milano Milano Milano 20152",
    "addr:postcode":"20152;20152",
    "iso:country":"IT",
    "sg:address":"20152 Milano",
    "sg:city":"Milano",
    "sg:orig_category":"Prodotti Chimici Secondari. Medicinali E Prodotti Parafarmaceutici",
    "sg:phone":"+39 0248381",
    "sg:postcode":"20152",
    "sg:province":"Milano",
    "wof:name":"Pharmacia & Upjohn S.p.a.",
    "wof:placetype":"venue"
},
  "geometry": {"coordinates":[9.0667657852,45.4441375732],"type":"Point"}
}