{
  "type": "Feature",
  "properties": {
    "iso:country":"IT",
    "sg:address":"64021 Giulianova",
    "sg:city":"Giulianova",
    "sg:orig_category":"Non-classified Establishments",
    "sg:phone":"+39 085 800 3623",
    "sg:postcode":"64021",
    "sg:province":"Teramo",
    "wof:name":"Cartachic Di Lesce Stefania",
    "wof:placetype":"venue"
},
  "geometry": {"coordinates":[13.964403,42.754696],"type":"Point"}
}