{
  "type": "Feature",
  "properties": {
    "addr:full":"00176 Roma Roma Roma 00176",
    "addr:postcode":"00176;00176",
    "iso:country":"IT",
    "sg:address":"00176 Roma",
    "sg:city":"Roma",
    "sg:orig_category":"Carni, Salumi E Pesci",
    "sg:phone":"+39 06 242 7847",
    "sg:postcode":"00176",
    "sg:province":"Roma",
    "wof:name":"Adriatica Di Rapone Sergio & C. S.a.s.",
    "wof:placetype":"venue"
},
  "geometry": {"coordinates":[12.538558,41.882801],"type":"Point"}
}