{
  "type": "Feature",
  "properties": {
    "addr:full":"Via R. Lombardi 38 31030 Arcade Arcade Treviso 31030",
    "addr:housenumber":"38",
    "addr:postcode":"31030;31030",
    "addr:street":"Via R. Lombardi",
    "iso:country":"IT",
    "sg:address":"Via R. Lombardi 38 31030 Arcade",
    "sg:city":"Arcade",
    "sg:classifiers":[
        {
            "category":"Building & Trades",
            "subcategory":"Pest Control",
            "type":"Services"
        }
    ],
    "sg:phone":"+39 0422 720248",
    "sg:postcode":"31030",
    "sg:province":"Treviso",
    "sg:tags":[
        "wood",
        "painting",
        "preserving"
    ],
    "wof:name":"Itaca S.r.l.",
    "wof:placetype":"venue"
},
  "geometry": {"coordinates":[12.242072,45.666286],"type":"Point"}
}