{
  "type": "Feature",
  "properties": {
    "iso:country":"IT",
    "sg:address":"80133 Napoli",
    "sg:city":"Napoli",
    "sg:orig_category":"Servizi Ausiliari Dei Mezzi Di Trasporto",
    "sg:phone":"+39 081 552 1232",
    "sg:postcode":"80133",
    "sg:province":"Napoli",
    "wof:name":"Cervantes Srl",
    "wof:placetype":"venue"
},
  "geometry": {"coordinates":[14.283347,40.899681],"type":"Point"}
}