{
  "type": "Feature",
  "properties": {
    "addr:full":"37121 Verona Verona Verona 37121",
    "addr:postcode":"37121;37121",
    "iso:country":"IT",
    "sg:address":"37121 Verona",
    "sg:city":"Verona",
    "sg:orig_category":"Provincia E Servizi Provinciali",
    "sg:phone":"+39 045 808 8611",
    "sg:postcode":"37121",
    "sg:province":"Verona",
    "sg:website":"http://www.provincia.verona.it",
    "wof:name":"Amministrazione Della Provincia Di Verona",
    "wof:placetype":"venue"
},
  "geometry": {"coordinates":[10.9985322952,45.4437675476],"type":"Point"}
}