{
  "type": "Feature",
  "properties": {
    "addr:full":"Via Varese 5 20096 Pioltello Pioltello Milano 20096",
    "addr:housenumber":"5",
    "addr:postcode":"20096;20096",
    "addr:street":"Via Varese",
    "iso:country":"IT",
    "sg:address":"Via Varese 5 20096 Pioltello",
    "sg:city":"Pioltello",
    "sg:classifiers":[
        {
            "category":"Shopping",
            "subcategory":"Bicycles & Sporting Goods",
            "type":"Retail Goods"
        }
    ],
    "sg:phone":"+39 02 926 6023",
    "sg:postcode":"20096",
    "sg:province":"Milano",
    "sg:tags":[
        "accessory"
    ],
    "wof:name":"Silca Srl",
    "wof:placetype":"venue"
},
  "geometry": {"coordinates":[9.318391,45.49688],"type":"Point"}
}