{
  "type": "Feature",
  "properties": {
    "iso:country":"IT",
    "sg:address":"00166 Roma",
    "sg:city":"Roma",
    "sg:orig_category":"Informatica - Consulenza E Servizi. Editoria",
    "sg:phone":"+39 06 624 3002",
    "sg:postcode":"00166",
    "sg:province":"Roma",
    "sg:website":"http://www.edigroup.it",
    "wof:name":"Edigroup Srl",
    "wof:placetype":"venue"
},
  "geometry": {"coordinates":[12.38977,41.9146],"type":"Point"}
}