{
  "type": "Feature",
  "properties": {
    "iso:country":"IT",
    "sg:address":"45, Via Castignoli 29020 Vigolzone",
    "sg:city":"Vigolzone",
    "sg:classifiers":[
        {
            "category":"Shopping",
            "subcategory":"Computers & Home Electronics",
            "type":"Retail Goods"
        }
    ],
    "sg:phone":"+39 0523 879123",
    "sg:postcode":"29020",
    "sg:province":"Piacenza",
    "sg:tags":[
        "electronic",
        "electrical",
        "equipment"
    ],
    "wof:name":"C.e.v.i. (s.r.l.)",
    "wof:placetype":"venue"
},
  "geometry": {"coordinates":[9.665707,44.912189],"type":"Point"}
}