{
  "type": "Feature",
  "properties": {
    "iso:country":"IT",
    "sg:address":"28074 Ghemme",
    "sg:city":"Ghemme",
    "sg:orig_category":"Filati E Materie Prime Tessili",
    "sg:phone":"+39 0163 841184",
    "sg:postcode":"28074",
    "sg:province":"Novara",
    "wof:name":"Ritorcitura Vega Di Staffiere Eliseo & C. - S.n.c.",
    "wof:placetype":"venue"
},
  "geometry": {"coordinates":[8.4180459976,45.5944328308],"type":"Point"}
}