{
  "type": "Feature",
  "properties": {
    "addr:full":"10149 Torino Torino Torino 10149",
    "addr:postcode":"10149;10149",
    "iso:country":"IT",
    "sg:address":"10149 Torino",
    "sg:city":"Torino",
    "sg:orig_category":"Materiali E Componenti Elettrotecnici",
    "sg:phone":"+39 011 221 7522",
    "sg:postcode":"10149",
    "sg:province":"Torino",
    "wof:name":"E.r.m.e.t. (s.r.l.)",
    "wof:placetype":"venue"
},
  "geometry": {"coordinates":[7.659313,45.095539],"type":"Point"}
}