{
  "type": "Feature",
  "properties": {
    "addr:full":"00144 Roma Roma Roma 00144",
    "addr:postcode":"00144;00144",
    "iso:country":"IT",
    "sg:address":"00144 Roma",
    "sg:city":"Roma",
    "sg:orig_category":"Legno E Semilavorati",
    "sg:phone":"+39 06 500 4386",
    "sg:postcode":"00144",
    "sg:province":"Roma",
    "wof:name":"Antonio Alessi Manassero S.a.s - Studio Rappresentanze Industriali",
    "wof:placetype":"venue"
},
  "geometry": {"coordinates":[12.464817,41.815918],"type":"Point"}
}