{
  "type": "Feature",
  "properties": {
    "addr:full":"13836 Cossato Cossato Biella 13836",
    "addr:postcode":"13836;13836",
    "iso:country":"IT",
    "sg:address":"13836 Cossato",
    "sg:city":"Cossato",
    "sg:orig_category":"Termotecnica E Riscaldamento, Apparecchiature E Servizi",
    "sg:phone":"+39 015 93985",
    "sg:postcode":"13836",
    "sg:province":"Biella",
    "wof:name":"Casonato Di Piliarvu S.a.s.",
    "wof:placetype":"venue"
},
  "geometry": {"coordinates":[8.006454,45.51796],"type":"Point"}
}