{
  "type": "Feature",
  "properties": {
    "addr:full":"Via Reggio, 1/bis 41011 Campogalliano Campogalliano Modena 41011",
    "addr:housenumber":"1 / bis",
    "addr:postcode":"41011;41011",
    "addr:street":"Via Reggio",
    "iso:country":"IT",
    "sg:address":"Via Reggio, 1/bis 41011 Campogalliano",
    "sg:city":"Campogalliano",
    "sg:classifiers":[
        {
            "category":"Home & Garden",
            "subcategory":"Home Furnishings",
            "type":"Retail Goods"
        }
    ],
    "sg:phone":"+39 059 526011",
    "sg:postcode":"41011",
    "sg:province":"Modena",
    "sg:tags":[
        "household",
        "ceramic"
    ],
    "wof:name":"Ceramiche Campogalliano Para Spa",
    "wof:placetype":"venue"
},
  "geometry": {"coordinates":[10.92522,44.647079],"type":"Point"}
}