{
  "type": "Feature",
  "properties": {
    "iso:country":"IT",
    "sg:address":"10145 Torino",
    "sg:city":"Torino",
    "sg:orig_category":"Agenzie D'affari E Servizi Commerciali",
    "sg:phone":"+39 011 749 3970",
    "sg:postcode":"10145",
    "sg:province":"Torino",
    "wof:name":"Giallo Snc Di Flavio Freyria Fava E C",
    "wof:placetype":"venue"
},
  "geometry": {"coordinates":[7.120077,45.126019],"type":"Point"}
}