{
  "type": "Feature",
  "properties": {
    "iso:country":"IT",
    "sg:address":"21100 Varese",
    "sg:city":"Varese",
    "sg:orig_category":"Materiali E Componenti Elettrotecnici",
    "sg:phone":"+39 0332 333104",
    "sg:postcode":"21100",
    "sg:province":"Varese",
    "wof:name":"Gravina Vito",
    "wof:placetype":"venue"
},
  "geometry": {"coordinates":[8.849475,45.8167],"type":"Point"}
}