{
  "type": "Feature",
  "properties": {
    "iso:country":"IT",
    "sg:address":"42, Via E. Mattei 35038 Torreglia",
    "sg:city":"Torreglia",
    "sg:classifiers":[
        {
            "category":"Shopping",
            "subcategory":"Stationery & Office Supplies",
            "type":"Retail Goods"
        }
    ],
    "sg:phone":"+39 049 521 1700",
    "sg:postcode":"35038",
    "sg:province":"Padova",
    "sg:tags":[
        "professional"
    ],
    "wof:name":"Arredamenti Campello (s.r.l.)",
    "wof:placetype":"venue"
},
  "geometry": {"coordinates":[11.8765888214,45.4095687866],"type":"Point"}
}