{
  "type": "Feature",
  "properties": {
    "addr:full":"Viale Risorgimento 34 22073 Fino Mornasco Fino Mornasco Como 22073",
    "addr:housenumber":"34",
    "addr:postcode":"22073;22073",
    "addr:street":"Viale Risorgimento",
    "iso:country":"IT",
    "sg:address":"Viale Risorgimento 34 22073 Fino Mornasco",
    "sg:city":"Fino Mornasco",
    "sg:classifiers":[
        {
            "category":"Manufacturing",
            "subcategory":"Rubber & Plastics",
            "type":"Manufacturing & Wholesale Goods"
        }
    ],
    "sg:phone":"+39 031 927205",
    "sg:postcode":"22073",
    "sg:province":"Como",
    "sg:tags":[
        "profile"
    ],
    "wof:name":"Visgomma Srl",
    "wof:placetype":"venue"
},
  "geometry": {"coordinates":[9.045202,45.747391],"type":"Point"}
}