{
  "type": "Feature",
  "properties": {
    "addr:full":"Via S. Carlo 21047 Saronno Saronno Varese 21047",
    "addr:postcode":"21047;21047",
    "addr:street":"Via S. Carlo",
    "iso:country":"IT",
    "sg:address":"Via S. Carlo 21047 Saronno",
    "sg:city":"Saronno",
    "sg:classifiers":[
        {
            "category":"Shopping",
            "subcategory":"Stationery & Office Supplies",
            "type":"Retail Goods"
        }
    ],
    "sg:phone":"+39 39029603020",
    "sg:postcode":"21047",
    "sg:province":"Varese",
    "sg:tags":[
        "professional"
    ],
    "wof:name":"Telaro Luigi E C. (s.a.s.)",
    "wof:placetype":"venue"
},
  "geometry": {"coordinates":[8.8263845444,45.8176040649],"type":"Point"}
}