{
  "type": "Feature",
  "properties": {
    "iso:country":"IT",
    "sg:address":"20038 Seregno",
    "sg:city":"Seregno",
    "sg:orig_category":"Non-classified Establishments",
    "sg:phone":"+39 036 286 2282",
    "sg:postcode":"20038",
    "sg:province":"Milano",
    "wof:name":"La Pigna Mobili Rustici (s.n.c.)",
    "wof:placetype":"venue"
},
  "geometry": {"coordinates":[9.203573,45.651917],"type":"Point"}
}