{
  "type": "Feature",
  "properties": {
    "addr:full":"Via Cremosina 49 28076 Pogno Pogno Novara 28076",
    "addr:housenumber":"49",
    "addr:postcode":"28076;28076",
    "addr:street":"Via Cremosina",
    "iso:country":"IT",
    "sg:address":"Via Cremosina 49 28076 Pogno",
    "sg:city":"Pogno",
    "sg:classifiers":[
        {
            "category":"Government",
            "subcategory":"Fire Station",
            "type":"Public Place"
        }
    ],
    "sg:phone":"+39 0322 97650",
    "sg:postcode":"28076",
    "sg:province":"Novara",
    "sg:tags":[
        "brass",
        "working"
    ],
    "sg:website":"www.denicola.com",
    "wof:name":"De Nicola Fratelli Srl",
    "wof:placetype":"venue"
},
  "geometry": {"coordinates":[8.380914,45.7523],"type":"Point"}
}