{
  "type": "Feature",
  "properties": {
    "addr:full":"38100 Trento Trento Trento 38100",
    "addr:postcode":"38100;38100",
    "iso:country":"IT",
    "sg:address":"38100 Trento",
    "sg:city":"Trento",
    "sg:orig_category":"Abbigliamento Esterno, Maglierie E Pelliccerie",
    "sg:phone":"+39 0461 980156",
    "sg:postcode":"38100",
    "sg:province":"Trento",
    "wof:name":"Faitex Di Asterio Failoni E C. Snc",
    "wof:placetype":"venue"
},
  "geometry": {"coordinates":[11.120996,46.067341],"type":"Point"}
}