{
  "type": "Feature",
  "properties": {
    "iso:country":"IT",
    "sg:address":"59, Via Giovanni Ventitreesimo 23889 Santa Maria Hoe'",
    "sg:classifiers":[
        {
            "category":"Shopping",
            "subcategory":"Computers & Home Electronics",
            "type":"Retail Goods"
        }
    ],
    "sg:phone":"+39 39039595101",
    "sg:postcode":"23889",
    "sg:province":"Lecco",
    "sg:tags":[
        "electronic",
        "electrical",
        "equipment"
    ],
    "wof:name":"Bessel Spa",
    "wof:placetype":"venue"
},
  "geometry": {"coordinates":[9.390071,45.852982],"type":"Point"}
}