{
  "type": "Feature",
  "properties": {
    "addr:full":"67050 Castellafiume L'Aquila 67050",
    "addr:postcode":"67050;l'aquila 67050",
    "iso:country":"IT",
    "sg:address":"67050 Castellafiume",
    "sg:orig_category":"Non-classified Establishments",
    "sg:phone":"+39 0863 54765",
    "sg:postcode":"67050",
    "sg:province":"L'Aquila",
    "wof:name":"Fratelli Lupiani Snc",
    "wof:placetype":"venue"
},
  "geometry": {"coordinates":[13.465017,42.32132],"type":"Point"}
}