{
  "type": "Feature",
  "properties": {
    "iso:country":"IT",
    "sg:address":"22079 Villa Guardia",
    "sg:city":"Villa Guardia",
    "sg:orig_category":"Macchine, Impianti E Forniture Per Industria Grafica, Cartaria E Cartotecnica",
    "sg:phone":"+39 031 481568",
    "sg:postcode":"22079",
    "sg:province":"Como",
    "wof:name":"Amex (s.r.l.)",
    "wof:placetype":"venue"
},
  "geometry": {"coordinates":[9.033619,45.769848],"type":"Point"}
}