{
  "type": "Feature",
  "properties": {
    "addr:full":"40060 Dozza Dozza Bologna 40060",
    "addr:postcode":"40060;40060",
    "iso:country":"IT",
    "sg:address":"40060 Dozza",
    "sg:city":"Dozza",
    "sg:classifiers":[
        {
            "category":"Structure",
            "subcategory":"Factory",
            "type":"Public Place"
        }
    ],
    "sg:phone":"+39 0542 673 5556",
    "sg:postcode":"40060",
    "sg:province":"Bologna",
    "sg:tags":[
        "steelworks",
        "foundry"
    ],
    "sg:website":"http://www.mennacasting.it",
    "wof:name":"Menna Casting Srl",
    "wof:placetype":"venue"
},
  "geometry": {"coordinates":[11.642518,44.382519],"type":"Point"}
}