{
  "type": "Feature",
  "properties": {
    "iso:country":"IT",
    "sg:address":"25050 Passirano",
    "sg:city":"Passirano",
    "sg:orig_category":"Forniture Per Agricoltura E Zootecnia. Forniture Per Attivita' Industriali",
    "sg:phone":"+39 030 685 0308",
    "sg:postcode":"25050",
    "sg:province":"Brescia",
    "wof:name":"Retificio Brixia S.r.l.",
    "wof:placetype":"venue"
},
  "geometry": {"coordinates":[10.2206344604,45.5347290039],"type":"Point"}
}