{
  "type": "Feature",
  "properties": {
    "iso:country":"IT",
    "sg:address":"84, Via Vecchia Comunale 80026 Casoria",
    "sg:city":"Casoria",
    "sg:classifiers":[
        {
            "category":"Manufacturing",
            "subcategory":"Metals",
            "type":"Manufacturing & Wholesale Goods"
        }
    ],
    "sg:phone":"+39 081 759 9188",
    "sg:postcode":"80026",
    "sg:province":"Napoli",
    "sg:tags":[
        "metallurgy",
        "metalworking"
    ],
    "wof:name":"Movisid (s.p.a.)",
    "wof:placetype":"venue"
},
  "geometry": {"coordinates":[14.3294897079,40.9006958008],"type":"Point"}
}