{
  "type": "Feature",
  "properties": {
    "iso:country":"IT",
    "sg:address":"20085 Locate Di Triulzi",
    "sg:city":"Locate di Triulzi",
    "sg:orig_category":"Ospedali E Servizi Sanitari. Servizi Sociali",
    "sg:phone":"+39 02 907 9219",
    "sg:postcode":"20085",
    "sg:province":"Milano",
    "wof:name":"Asl Provincia Di Milano 2",
    "wof:placetype":"venue"
},
  "geometry": {"coordinates":[9.224252,45.359371],"type":"Point"}
}