{
  "type": "Feature",
  "properties": {
    "addr:full":"65, V. Tazio Nuvolari - Carraia55061 Capannori Capannori Lucca 55061",
    "addr:housenumber":"65;carraia55061",
    "addr:postcode":"55061",
    "addr:street":"V. Tazio Nuvolari",
    "iso:country":"IT",
    "sg:address":"65, V. Tazio Nuvolari - Carraia55061 Capannori",
    "sg:city":"Capannori",
    "sg:classifiers":[
        {
            "category":"Manufacturing",
            "subcategory":"Paper Products",
            "type":"Manufacturing & Wholesale Goods"
        }
    ],
    "sg:phone":"+39 390 583 4481",
    "sg:postcode":"55061",
    "sg:province":"Lucca",
    "sg:tags":[
        "cardboard"
    ],
    "sg:website":"http://www.kartogroup.it",
    "wof:name":"Kartogroup Finanziaria Spa",
    "wof:placetype":"venue"
},
  "geometry": {"coordinates":[10.5650014877,43.8235969543],"type":"Point"}
}