{
  "type": "Feature",
  "properties": {
    "iso:country":"IT",
    "sg:address":"62, Via Novara 21052 Busto Arsizio",
    "sg:city":"Busto Arsizio",
    "sg:classifiers":[
        {
            "category":"Shopping",
            "subcategory":"Crafts & Fabrics",
            "type":"Retail Goods"
        }
    ],
    "sg:phone":"+39 0331 350749",
    "sg:postcode":"21052",
    "sg:province":"Varese",
    "sg:tags":[
        "linen"
    ],
    "wof:name":"Parotex S.r.l.",
    "wof:placetype":"venue"
},
  "geometry": {"coordinates":[8.845659256,45.5840797424],"type":"Point"}
}