{
  "type": "Feature",
  "properties": {
    "addr:full":"Via Bormioli Giovanni 60 25134 Brescia Brescia Brescia 25134",
    "addr:housenumber":"60",
    "addr:postcode":"25134;25134",
    "addr:street":"Via Bormioli Giovanni",
    "iso:country":"IT",
    "sg:address":"Via Bormioli Giovanni 60 25134 Brescia",
    "sg:city":"Brescia",
    "sg:classifiers":[
        {
            "category":"Wholesale",
            "subcategory":"Plants",
            "type":"Manufacturing & Wholesale Goods"
        }
    ],
    "sg:phone":"+39 030 369400",
    "sg:postcode":"25134",
    "sg:province":"Brescia",
    "sg:tags":[
        "synthetic",
        "fibre",
        "spinning",
        "yarn"
    ],
    "sg:website":"www.sangiacomo.com",
    "wof:name":"Sangiacomo Spa",
    "wof:placetype":"venue"
},
  "geometry": {"coordinates":[10.222958,45.539829],"type":"Point"}
}