{
  "type": "Feature",
  "properties": {
    "iso:country":"IT",
    "sg:address":"Str.prov.trav. Del Grillo Km 0,500 00060 Castelnuovo Di Porto",
    "sg:city":"Castelnuovo di Porto",
    "sg:classifiers":[
        {
            "category":"Banks & Credit Unions",
            "subcategory":"Investment Brokerage",
            "type":"Services"
        }
    ],
    "sg:phone":"+39 06 907 3455",
    "sg:postcode":"00060",
    "sg:province":"Roma",
    "sg:tags":[
        "product",
        "hair-care"
    ],
    "wof:name":"Bacchara Srl",
    "wof:placetype":"venue"
},
  "geometry": {"coordinates":[12.482325,41.895466],"type":"Point"}
}