{
  "type": "Feature",
  "properties": {
    "iso:country":"IT",
    "sg:address":"58100 Grosseto",
    "sg:city":"Grosseto",
    "sg:orig_category":"Carni, Salumi E Pesci. Zootecnia E Pesca, Allevamento Piccoli Animali",
    "sg:phone":"+39 0564 455618",
    "sg:postcode":"58100",
    "sg:province":"Grosseto",
    "wof:name":"Guadagnoli Marcello Srl",
    "wof:placetype":"venue"
},
  "geometry": {"coordinates":[11.110029,42.774818],"type":"Point"}
}