{
  "type": "Feature",
  "properties": {
    "iso:country":"IT",
    "sg:address":"Via Papa Giovanni Xxiii,; S. Elpidio; 63019",
    "sg:classifiers":[
        {
            "category":"Banks & Credit Unions",
            "subcategory":"Bank",
            "type":"Services"
        }
    ],
    "sg:phone":"+39 0734 859674",
    "sg:postcode":"63019",
    "sg:province":"Ascoli Piceno",
    "wof:name":"Banca Nazionale Dell' Agricoltura",
    "wof:placetype":"venue"
},
  "geometry": {"coordinates":[13.685125,43.23209],"type":"Point"}
}