{
  "type": "Feature",
  "properties": {
    "iso:country":"IT",
    "sg:address":"10146 Torino",
    "sg:city":"Torino",
    "sg:orig_category":"Medici. Assicurazioni E Servizi Assicurativi. Avvocati, Notai E Servizi Legali. Professionisti - Studi E Servizi Ed Associazioni Di Interesse Aziendale",
    "sg:phone":"+39 011 722896",
    "sg:postcode":"10146",
    "sg:province":"Torino",
    "wof:name":"Bottalo Laura",
    "wof:placetype":"venue"
},
  "geometry": {"coordinates":[7.6188807487,45.0804977417],"type":"Point"}
}