{
  "type": "Feature",
  "properties": {
    "addr:full":"20090 Segrate Segrate Milano 20090",
    "addr:postcode":"20090;20090",
    "iso:country":"IT",
    "sg:address":"20090 Segrate",
    "sg:city":"Segrate",
    "sg:orig_category":"Cartotecnica E Servizi. Forniture Per Uffici",
    "sg:phone":"+39 02 213 9972",
    "sg:postcode":"20090",
    "sg:province":"Milano",
    "sg:website":"http://www.labelcart.it",
    "wof:name":"Laberlcart Srl",
    "wof:placetype":"venue"
},
  "geometry": {"coordinates":[9.3001146317,45.4995384216],"type":"Point"}
}