{
  "type": "Feature",
  "properties": {
    "addr:full":"Corso Regina Margherita,; Troia; 71029 Troia Foggia 71029",
    "addr:postcode":"71029;71029",
    "addr:street":"Corso Regina Margherita",
    "iso:country":"IT",
    "sg:address":"Corso Regina Margherita,; Troia; 71029",
    "sg:city":"Troia",
    "sg:classifiers":[
        {
            "category":"Banks & Credit Unions",
            "subcategory":"Bank",
            "type":"Services"
        }
    ],
    "sg:phone":"+39 0881 970106",
    "sg:postcode":"71029",
    "sg:province":"Foggia",
    "wof:name":"Cassa Di Risparmio Di Puglia",
    "wof:placetype":"venue"
},
  "geometry": {"coordinates":[15.309129,41.361538],"type":"Point"}
}