{
  "type": "Feature",
  "properties": {
    "iso:country":"IT",
    "sg:address":"Via Carpi Ravarino 111 41019 Soliera",
    "sg:city":"Soliera",
    "sg:classifiers":[
        {
            "category":"Wholesale",
            "subcategory":"Vending Machines",
            "type":"Manufacturing & Wholesale Goods"
        }
    ],
    "sg:phone":"+39 059 855911",
    "sg:postcode":"41019",
    "sg:province":"Modena",
    "sg:tags":[
        "honing"
    ],
    "sg:website":"www.cblevigatrici.it",
    "wof:name":"C.b.levigatrici Srl",
    "wof:placetype":"venue"
},
  "geometry": {"coordinates":[10.96887,44.751347],"type":"Point"}
}