{
  "type": "Feature",
  "properties": {
    "addr:full":"35020 Albignasego Albignasego Padova 35020",
    "addr:postcode":"35020;35020",
    "iso:country":"IT",
    "sg:address":"35020 Albignasego",
    "sg:city":"Albignasego",
    "sg:orig_category":"Gioielleria, Oreficeria E Argenteria. Articoli Da Regalo. Shopping",
    "sg:phone":"+39 049 862 9094",
    "sg:postcode":"35020",
    "sg:province":"Padova",
    "wof:name":"Zaggia Alessandro",
    "wof:placetype":"venue"
},
  "geometry": {"coordinates":[11.82767,45.342094],"type":"Point"}
}