{
  "type": "Feature",
  "properties": {
    "addr:full":"10138 Torino Torino Torino 10138",
    "addr:housenumber":"10138",
    "addr:postcode":"10138",
    "iso:country":"IT",
    "sg:address":"10138 Torino",
    "sg:city":"Torino",
    "sg:orig_category":"Assicurazioni E Servizi Assicurativi",
    "sg:phone":"+39 011 386259",
    "sg:postcode":"10138",
    "sg:province":"Torino",
    "sg:website":"http://www.cgabroker.it",
    "wof:name":"Cga Broker Srl",
    "wof:placetype":"venue"
},
  "geometry": {"coordinates":[7.651061,45.064198],"type":"Point"}
}