{
  "type": "Feature",
  "properties": {
    "addr:full":"Via Giotto 3 20040 Cambiago Cambiago Milano 20040",
    "addr:housenumber":"3",
    "addr:postcode":"20040;20040",
    "addr:street":"Via Giotto",
    "iso:country":"IT",
    "sg:address":"Via Giotto 3 20040 Cambiago",
    "sg:city":"Cambiago",
    "sg:classifiers":[
        {
            "category":"Manufacturing",
            "subcategory":"Motor Vehicles & Parts",
            "type":"Manufacturing & Wholesale Goods"
        }
    ],
    "sg:phone":"+39 02 950851",
    "sg:postcode":"20040",
    "sg:province":"Milano",
    "sg:tags":[
        "fibreglass",
        "product"
    ],
    "wof:name":"Saint Gobain Ital Tess Spa",
    "wof:placetype":"venue"
},
  "geometry": {"coordinates":[9.3890972137,45.5987243652],"type":"Point"}
}