{
  "type": "Feature",
  "properties": {
    "iso:country":"IT",
    "sg:address":"20038 Seregno",
    "sg:city":"Seregno",
    "sg:orig_category":"Abbigliamento Esterno, Maglierie E Pelliccerie. Forniture Per Abbigliamento E Pelletterie",
    "sg:phone":"+39 036 223 0041",
    "sg:postcode":"20038",
    "sg:province":"Milano",
    "wof:name":"Lanzani Fratelli (s.n.c.)",
    "wof:placetype":"venue"
},
  "geometry": {"coordinates":[9.056032,45.426567],"type":"Point"}
}