{
  "type": "Feature",
  "properties": {
    "iso:country":"IT",
    "sg:address":"60030 Monsano",
    "sg:city":"Monsano",
    "sg:orig_category":"Materiali Semilavorati Metallici",
    "sg:phone":"+39 0731 60104",
    "sg:postcode":"60030",
    "sg:province":"Ancona",
    "wof:name":"G.m. Di Giuliani G. E Manoni S. Snc",
    "wof:placetype":"venue"
},
  "geometry": {"coordinates":[13.291293,43.566574],"type":"Point"}
}