{
  "type": "Feature",
  "properties": {
    "iso:country":"IT",
    "sg:address":"Via Ronchi Sinistro 20b 35017 Piombino Dese",
    "sg:city":"Piombino Dese",
    "sg:classifiers":[
        {
            "category":"Professional",
            "type":"Services"
        }
    ],
    "sg:phone":"+39 049 936 5934",
    "sg:postcode":"35017",
    "sg:province":"Padova",
    "sg:tags":[
        "transport"
    ],
    "wof:name":"Autotrasporti Bertuola S.r.l.",
    "wof:placetype":"venue"
},
  "geometry": {"coordinates":[11.876589,45.409569],"type":"Point"}
}