{
  "type": "Feature",
  "properties": {
    "iso:country":"IT",
    "sg:address":"20154 Milano",
    "sg:city":"Milano",
    "sg:orig_category":"Elettronica Professionale E Di Consumo. Forniture Per Il Settore Dello Spettacolo. Automazione E Macchine Per Ufficio. Forniture Per Congressi, Fiere E Manifestazioni",
    "sg:phone":"+39 02 349 4710",
    "sg:postcode":"20154",
    "sg:province":"Milano",
    "sg:website":"http://www.tecnoesse.it",
    "wof:name":"Tecnoesse Srl",
    "wof:placetype":"venue"
},
  "geometry": {"coordinates":[9.178782,45.482048],"type":"Point"}
}