{
  "type": "Feature",
  "properties": {
    "addr:full":"93, Via Cesare Battisti 31028 Vazzola Vazzola Treviso 31028",
    "addr:postcode":"31028;31028",
    "addr:street":"Via Cesare Battisti",
    "iso:country":"IT",
    "sg:address":"93, Via Cesare Battisti 31028 Vazzola",
    "sg:city":"Vazzola",
    "sg:classifiers":[
        {
            "category":"Professional",
            "subcategory":"Engineering",
            "type":"Services"
        }
    ],
    "sg:phone":"+39 0438 441419",
    "sg:postcode":"31028",
    "sg:province":"Treviso",
    "sg:tags":[
        "machine",
        "-",
        "mechanical"
    ],
    "wof:name":"Europak S.p.a.",
    "wof:placetype":"venue"
},
  "geometry": {"coordinates":[12.385571,45.845886],"type":"Point"}
}