{
  "type": "Feature",
  "properties": {
    "iso:country":"IT",
    "sg:address":"80128 Napoli",
    "sg:city":"Napoli",
    "sg:orig_category":"Associazioni Ed Organismi Di Interesse Pubblico",
    "sg:phone":"+39 081 560 9437",
    "sg:postcode":"80128",
    "sg:province":"Napoli",
    "wof:name":"Idros Di Sorrentino Silvia",
    "wof:placetype":"venue"
},
  "geometry": {"coordinates":[14.225011,40.851192],"type":"Point"}
}