{
  "type": "Feature",
  "properties": {
    "iso:country":"IT",
    "sg:address":"20143 Milano",
    "sg:city":"Milano",
    "sg:orig_category":"Prodotti Alimentari",
    "sg:phone":"+39 02 839 4964",
    "sg:postcode":"20143",
    "sg:province":"Milano",
    "wof:name":"La Latteria Del Naviglio Di Curato Luigi & Tordonato Clemente (s.n.c.)",
    "wof:placetype":"venue"
},
  "geometry": {"coordinates":[9.1752061844,45.4486808777],"type":"Point"}
}