{
  "type": "Feature",
  "properties": {
    "iso:country":"IT",
    "sg:address":"13894 Gaglianico",
    "sg:city":"Gaglianico",
    "sg:orig_category":"Isolanti Termici Ed Acustici - Commercio",
    "sg:phone":"+39 015 602048",
    "sg:postcode":"13894",
    "sg:province":"Biella",
    "wof:name":"Figli Di Ernesto Forzani Snc",
    "wof:placetype":"venue"
},
  "geometry": {"coordinates":[8.08602,45.532768],"type":"Point"}
}