{
  "type": "Feature",
  "properties": {
    "addr:full":"00121 Lido Di Ostia Roma 00121",
    "addr:postcode":"00121;00121",
    "addr:street":"Di Ostia Roma",
    "iso:country":"IT",
    "sg:address":"00121 Lido Di Ostia",
    "sg:orig_category":"Servizi Per Lo Sport E Il Tempo Libero. Alberghi E Strutture Extra Alberghiere",
    "sg:phone":"+39 06 567 2307",
    "sg:postcode":"00121",
    "sg:province":"Roma",
    "wof:name":"Elmi Giuseppe",
    "wof:placetype":"venue"
},
  "geometry": {"coordinates":[12.274699,41.730145],"type":"Point"}
}