{
  "type": "Feature",
  "properties": {
    "iso:country":"IT",
    "sg:address":"53048 Sinalunga",
    "sg:city":"Sinalunga",
    "sg:orig_category":"Autorevisioni Periodiche - Officine Abilitate",
    "sg:phone":"+39 0577 679814",
    "sg:postcode":"53048",
    "sg:province":"Siena",
    "wof:name":"Valdichiana Pneumatici",
    "wof:placetype":"venue"
},
  "geometry": {"coordinates":[11.749298,43.214741],"type":"Point"}
}