{
  "type": "Feature",
  "properties": {
    "iso:country":"IT",
    "sg:address":"20, Via Europa 36020 Pove Del Grappa",
    "sg:city":"Pove del Grappa",
    "sg:classifiers":[
        {
            "category":"Banks & Credit Unions",
            "subcategory":"Investment Brokerage",
            "type":"Services"
        }
    ],
    "sg:phone":"+39 0424 809141",
    "sg:postcode":"36020",
    "sg:province":"Vicenza",
    "sg:tags":[
        "-",
        "transport",
        "related"
    ],
    "wof:name":"Bertin Dino (s.r.l.)",
    "wof:placetype":"venue"
},
  "geometry": {"coordinates":[11.722571,45.795696],"type":"Point"}
}