{
  "type": "Feature",
  "properties": {
    "addr:full":"Via Roma 78; Pregnana Milanese; 20010 Pregnana Milanese Milano 20010",
    "addr:housenumber":"78",
    "addr:postcode":"20010;20010",
    "addr:street":"Via Roma",
    "iso:country":"IT",
    "sg:address":"Via Roma 78; Pregnana Milanese; 20010",
    "sg:city":"Pregnana Milanese",
    "sg:classifiers":[
        {
            "category":"Banks & Credit Unions",
            "subcategory":"Bank",
            "type":"Services"
        }
    ],
    "sg:phone":"+39 02 9329 0986",
    "sg:postcode":"20010",
    "sg:province":"Milano",
    "wof:name":"Istituto Bancario, San Paolo Di Torino Spa",
    "wof:placetype":"venue"
},
  "geometry": {"coordinates":[9.007998,45.516033],"type":"Point"}
}