{
  "type": "Feature",
  "properties": {
    "iso:country":"IT",
    "sg:address":"50059 Vinci",
    "sg:city":"Vinci",
    "sg:orig_category":"Macchine Ed Impianti Per Edilizia E Lavori Pubblici",
    "sg:phone":"+39 0571 7091",
    "sg:postcode":"50059",
    "sg:province":"Firenze",
    "sg:website":"http://www.industriebitossi.com",
    "wof:name":"Industrie Bitossi Spa",
    "wof:placetype":"venue"
},
  "geometry": {"coordinates":[10.941951,43.750912],"type":"Point"}
}