{
  "type": "Feature",
  "properties": {
    "addr:full":"16144 Genova Genova Genova 16144",
    "addr:postcode":"16144;16144",
    "iso:country":"IT",
    "sg:address":"16144 Genova",
    "sg:city":"Genova",
    "sg:orig_category":"Arredo Cucina Ed Elettrodomestici. Elettrodomestici",
    "sg:phone":"+39 010 823557",
    "sg:postcode":"16144",
    "sg:province":"Genova",
    "wof:name":"Bertoni Angelo",
    "wof:placetype":"venue"
},
  "geometry": {"coordinates":[8.98084,44.425488],"type":"Point"}
}