{
  "type": "Feature",
  "properties": {
    "addr:full":"Via Caduti Di Russia 30 35010 Curtarolo Curtarolo Padova 35010",
    "addr:housenumber":"30",
    "addr:postcode":"35010;35010",
    "addr:street":"Via Caduti Di Russia",
    "iso:country":"IT",
    "sg:address":"Via Caduti Di Russia 30 35010 Curtarolo",
    "sg:city":"Curtarolo",
    "sg:orig_category":"Packagings, Flexible",
    "sg:phone":"+39 049 962 0660",
    "sg:postcode":"35010",
    "sg:province":"Padova",
    "sg:website":"www.mach.ws",
    "wof:name":"Mach Srl",
    "wof:placetype":"venue"
},
  "geometry": {"coordinates":[11.8315401077,45.5386047363],"type":"Point"}
}