{
  "type": "Feature",
  "properties": {
    "iso:country":"IT",
    "sg:address":"18, Via De Nicola Enrico 20090 Cesano Boscone",
    "sg:city":"Cesano Boscone",
    "sg:classifiers":[
        {
            "category":"Shopping",
            "subcategory":"Clothing, Apparel, & Fashions",
            "type":"Retail Goods"
        }
    ],
    "sg:phone":"+39 390 245 8871",
    "sg:postcode":"20090",
    "sg:province":"Milano",
    "sg:tags":[
        "clothes"
    ],
    "wof:name":"Gibierre S.p.a.",
    "wof:placetype":"venue"
},
  "geometry": {"coordinates":[9.08823,45.430515],"type":"Point"}
}