{
  "type": "Feature",
  "properties": {
    "iso:country":"IT",
    "sg:address":"110/2, V. Rivera 10040 Almese",
    "sg:city":"Almese",
    "sg:classifiers":[
        {
            "category":"Professional",
            "subcategory":"Engineering",
            "type":"Services"
        }
    ],
    "sg:phone":"+39 011 935 0039",
    "sg:postcode":"10040",
    "sg:province":"Torino",
    "sg:tags":[
        "machine",
        "-",
        "mechanical"
    ],
    "sg:website":"http://www.paginegialle.it/novitaliasrl",
    "wof:name":"Novitalia Srl",
    "wof:placetype":"venue"
},
  "geometry": {"coordinates":[7.415648,45.109417],"type":"Point"}
}