{
  "type": "Feature",
  "properties": {
    "iso:country":"IT",
    "sg:address":"20093 Cologno Monzese",
    "sg:city":"Cologno Monzese",
    "sg:orig_category":"Carta, Cartone E Prodotti Primari. Forniture E Materiali Per Imballaggio E Confezionamento",
    "sg:phone":"+39 02 254 1601",
    "sg:postcode":"20093",
    "sg:province":"Milano",
    "wof:name":"Mercato Della Carta Di Gandolfi Maria & Antonino (s.n.c.)",
    "wof:placetype":"venue"
},
  "geometry": {"coordinates":[9.281298,45.524288],"type":"Point"}
}