{
  "type": "Feature",
  "properties": {
    "addr:full":"23/25, V. Seggio Dei Cavalieri 81043 Capua Capua Caserta 81043",
    "addr:housenumber":"23 / 25",
    "addr:postcode":"81043;81043",
    "addr:street":"Seggio;Cavalieri",
    "iso:country":"IT",
    "sg:address":"23/25, V. Seggio Dei Cavalieri 81043 Capua",
    "sg:city":"Capua",
    "sg:classifiers":[
        {
            "category":"Shopping",
            "subcategory":"Stationery & Office Supplies",
            "type":"Retail Goods"
        }
    ],
    "sg:phone":"+39 0823 620036",
    "sg:postcode":"81043",
    "sg:province":"Caserta",
    "sg:tags":[
        "professional"
    ],
    "sg:website":"http://www.paginegialle.it/informaticacommercio",
    "wof:name":"Informatica Commercio",
    "wof:placetype":"venue"
},
  "geometry": {"coordinates":[14.2134752274,41.1085090637],"type":"Point"}
}