{
  "type": "Feature",
  "properties": {
    "iso:country":"IT",
    "sg:address":"30175 Venezia",
    "sg:city":"Marghera",
    "sg:classifiers":[
        {
            "category":"Utilities",
            "subcategory":"Fuel Oil & Lpg",
            "type":"Services"
        }
    ],
    "sg:phone":"+39 041 257 5411",
    "sg:postcode":"30175",
    "sg:province":"Venezia",
    "sg:tags":[
        "fuels",
        "petroleum",
        "gas",
        "heating",
        "equipment",
        "heat",
        "products",
        "engineering"
    ],
    "sg:website":"http://www.smpetroli.it",
    "wof:name":"San Marco Petroli Spa",
    "wof:placetype":"venue"
},
  "geometry": {"coordinates":[12.2106542587,45.4400520325],"type":"Point"}
}