{
  "type": "Feature",
  "properties": {
    "addr:full":"8, Via Fratelli Canepa 16010 Serra Ricco' Genova 16010",
    "addr:housenumber":"16010",
    "addr:postcode":"ricco ';16010",
    "addr:street":"Via Fratelli Canepa",
    "iso:country":"IT",
    "sg:address":"8, Via Fratelli Canepa 16010 Serra Ricco'",
    "sg:classifiers":[
        {
            "category":"Professional",
            "subcategory":"Engineering",
            "type":"Services"
        }
    ],
    "sg:phone":"+39 39010754111",
    "sg:postcode":"16010",
    "sg:province":"Genova",
    "sg:tags":[
        "machine",
        "-",
        "mechanical"
    ],
    "wof:name":"Lincoln Electric Italia Srl",
    "wof:placetype":"venue"
},
  "geometry": {"coordinates":[8.921258,44.496815],"type":"Point"}
}