{
  "type": "Feature",
  "properties": {
    "iso:country":"IT",
    "sg:address":"44, Via De Amicis Edmondo 10093 Collegno",
    "sg:city":"Collegno",
    "sg:classifiers":[
        {
            "category":"Professional",
            "subcategory":"Engineering",
            "type":"Services"
        }
    ],
    "sg:phone":"+39 390 114 1011",
    "sg:postcode":"10093",
    "sg:province":"Torino",
    "sg:tags":[
        "machine",
        "-",
        "mechanical"
    ],
    "wof:name":"Sandretto Industrie S.p.a.",
    "wof:placetype":"venue"
},
  "geometry": {"coordinates":[7.597748,45.074821],"type":"Point"}
}