{
  "type": "Feature",
  "properties": {
    "iso:country":"IT",
    "sg:address":"41043 Formigine",
    "sg:city":"Formigine",
    "sg:orig_category":"Cromatura E Nichelatura",
    "sg:phone":"+39 059 554145",
    "sg:postcode":"41043",
    "sg:province":"Modena",
    "wof:name":"Zincaturificio M.r. Snc",
    "wof:placetype":"venue"
},
  "geometry": {"coordinates":[10.794604,44.596336],"type":"Point"}
}