{
  "type": "Feature",
  "properties": {
    "addr:full":"16167 Nervi Genova 16167",
    "addr:postcode":"16167;16167",
    "iso:country":"IT",
    "sg:address":"16167 Nervi",
    "sg:orig_category":"Prodotti Finiti Stampati. Forniture E Materiali Per Imballaggio E Confezionamento. Forniture Per Attivita' Commerciali Ed Artigianali",
    "sg:phone":"+39 010 372 5651",
    "sg:postcode":"16167",
    "sg:province":"Genova",
    "wof:name":"Cabona Pietro Sas",
    "wof:placetype":"venue"
},
  "geometry": {"coordinates":[9.0240650177,44.3836669922],"type":"Point"}
}