{
  "type": "Feature",
  "properties": {
    "iso:country":"IT",
    "sg:address":"22070 Cagno",
    "sg:city":"Cagno",
    "sg:orig_category":"Servizi Culturali E Per Lo Spettacolo. Servizi Al Turismo. Acqua, Luce, Gas E Societa' Di Esercizio Pubblico",
    "sg:phone":"+39 031 808526",
    "sg:postcode":"22070",
    "sg:province":"Como",
    "wof:name":"Biblioteca Comunale",
    "wof:placetype":"venue"
},
  "geometry": {"coordinates":[9.057895,45.768291],"type":"Point"}
}