{
  "type": "Feature",
  "properties": {
    "iso:country":"IT",
    "sg:address":"00152 Roma",
    "sg:city":"Roma",
    "sg:orig_category":"Impiantistica E Prodotti Tecnologici Per Edilizia. Elettronica Professionale E Di Consumo",
    "sg:phone":"+39 06 537 0440",
    "sg:postcode":"00152",
    "sg:province":"Roma",
    "wof:name":"Fabietti Roberto",
    "wof:placetype":"venue"
},
  "geometry": {"coordinates":[12.447272,41.8764],"type":"Point"}
}