{
  "type": "Feature",
  "properties": {
    "iso:country":"IT",
    "sg:address":"125, Via Brescia 25039 Travagliato",
    "sg:city":"Travagliato",
    "sg:classifiers":[
        {
            "category":"Manufacturing",
            "subcategory":"Motor Vehicles & Parts",
            "type":"Manufacturing & Wholesale Goods"
        }
    ],
    "sg:phone":"+39 030 686 5018",
    "sg:postcode":"25039",
    "sg:province":"Brescia",
    "sg:tags":[
        "engine"
    ],
    "wof:name":"Longinotti Fratelli (s.p.a.)",
    "wof:placetype":"venue"
},
  "geometry": {"coordinates":[10.099578,45.52034],"type":"Point"}
}