{
  "type": "Feature",
  "properties": {
    "iso:country":"IT",
    "sg:address":"10023 Chieri",
    "sg:city":"Chieri",
    "sg:orig_category":"Carni, Salumi E Pesci",
    "sg:phone":"+39 011 947 2686",
    "sg:postcode":"10023",
    "sg:province":"Torino",
    "wof:name":"Noviello Luigi",
    "wof:placetype":"venue"
},
  "geometry": {"coordinates":[7.957444,45.039791],"type":"Point"}
}