{
  "type": "Feature",
  "properties": {
    "addr:full":"20090 Cesano Boscone Cesano Boscone Milano 20090",
    "addr:postcode":"20090;20090",
    "iso:country":"IT",
    "sg:address":"20090 Cesano Boscone",
    "sg:city":"Cesano Boscone",
    "sg:orig_category":"Servizi Per Lo Sport E Il Tempo Libero. Associazioni Ed Organismi Di Interesse Pubblico",
    "sg:phone":"+39 02 450 1966",
    "sg:postcode":"20090",
    "sg:province":"Milano",
    "wof:name":"Ranning Club Cesanese",
    "wof:placetype":"venue"
},
  "geometry": {"coordinates":[9.083942,45.439877],"type":"Point"}
}