{
  "type": "Feature",
  "properties": {
    "iso:country":"IT",
    "sg:address":"10153 Torino",
    "sg:city":"Torino",
    "sg:orig_category":"Bagno - Accessori E Mobili",
    "sg:phone":"+39 011 286587",
    "sg:postcode":"10153",
    "sg:province":"Torino",
    "wof:name":"L'arte Marmi",
    "wof:placetype":"venue"
},
  "geometry": {"coordinates":[7.711216,45.078678],"type":"Point"}
}