{
  "type": "Feature",
  "properties": {
    "iso:country":"IT",
    "sg:address":"87064 Corigliano Calabro",
    "sg:city":"Corigliano Calabro",
    "sg:orig_category":"Ospedali E Servizi Sanitari",
    "sg:phone":"+39 0983 891843",
    "sg:postcode":"87064",
    "sg:province":"Cosenza",
    "wof:name":"Pubblica Assistenza Di Rocco Domenica",
    "wof:placetype":"venue"
},
  "geometry": {"coordinates":[16.520807,39.591248],"type":"Point"}
}