{
  "type": "Feature",
  "properties": {
    "iso:country":"IT",
    "sg:address":"42048 Rubiera",
    "sg:orig_category":"Termotecnica E Riscaldamento, Apparecchiature E Servizi",
    "sg:phone":"+39 0522 260523",
    "sg:postcode":"42048",
    "sg:province":"Reggio Nell'Emilia",
    "wof:name":"Arrow Line S.r.l.",
    "wof:placetype":"venue"
},
  "geometry": {"coordinates":[10.788323,44.656906],"type":"Point"}
}