{
  "type": "Feature",
  "properties": {
    "iso:country":"IT",
    "sg:address":"20092 Cinisello Balsamo",
    "sg:city":"Cinisello Balsamo",
    "sg:orig_category":"Dolciumi E Gelati",
    "sg:phone":"+39 02 612 2364",
    "sg:postcode":"20092",
    "sg:province":"Milano",
    "wof:name":"Gelati Sala Di Sirtori Enrico",
    "wof:placetype":"venue"
},
  "geometry": {"coordinates":[9.222113,45.548771],"type":"Point"}
}