{
  "type": "Feature",
  "properties": {
    "iso:country":"IT",
    "sg:address":"25036 Palazzolo Sull'oglio",
    "sg:orig_category":"Macchine Utensili E Impianti. Utensili Meccanici E Materiali",
    "sg:phone":"+39 030 730 1804",
    "sg:postcode":"25036",
    "sg:province":"Brescia",
    "wof:name":"Omac Snc Di Piensi A. & Belometti Emilio",
    "wof:placetype":"venue"
},
  "geometry": {"coordinates":[9.891188,45.594101],"type":"Point"}
}