{
  "type": "Feature",
  "properties": {
    "iso:country":"IT",
    "sg:address":"00043 Ciampino",
    "sg:city":"Ciampino",
    "sg:orig_category":"Impiantistica E Prodotti Tecnologici Per Edilizia. Termotecnica E Riscaldamento, Apparecchiature E Servizi",
    "sg:phone":"+39 06 796 2342",
    "sg:postcode":"00043",
    "sg:province":"Roma",
    "wof:name":"S.i.p.c. Srl",
    "wof:placetype":"venue"
},
  "geometry": {"coordinates":[12.609877,41.788696],"type":"Point"}
}