{
  "type": "Feature",
  "properties": {
    "iso:country":"IT",
    "sg:address":"20123 Milano",
    "sg:city":"Milano",
    "sg:orig_category":"Carta, Cartone E Prodotti Primari",
    "sg:phone":"+39 02 481 4006",
    "sg:postcode":"20123",
    "sg:province":"Milano",
    "wof:name":"Incell Srl",
    "wof:placetype":"venue"
},
  "geometry": {"coordinates":[9.174292,45.4678],"type":"Point"}
}