{
  "type": "Feature",
  "properties": {
    "iso:country":"IT",
    "sg:address":"31033 Castelfranco Veneto",
    "sg:city":"Castelfranco Veneto",
    "sg:orig_category":"Imprese Di Costruzioni Civili Ed Industriali",
    "sg:phone":"+39 0423 492821",
    "sg:postcode":"31033",
    "sg:province":"Treviso",
    "wof:name":"Postumia Cave Srl",
    "wof:placetype":"venue"
},
  "geometry": {"coordinates":[11.972846,45.677139],"type":"Point"}
}