{
  "type": "Feature",
  "properties": {
    "addr:full":"53030 Radicondoli Radicondoli Siena 53030",
    "addr:postcode":"53030;53030",
    "iso:country":"IT",
    "sg:address":"53030 Radicondoli",
    "sg:city":"Radicondoli",
    "sg:orig_category":"Agenzie Ed Uffici Commerciali",
    "sg:phone":"+39 0577 790566",
    "sg:postcode":"53030",
    "sg:province":"Siena",
    "wof:name":"Bobi Srl",
    "wof:placetype":"venue"
},
  "geometry": {"coordinates":[11.044801712,43.2614898682],"type":"Point"}
}