{
  "type": "Feature",
  "properties": {
    "iso:country":"IT",
    "sg:address":"20090 Trezzano Sul Naviglio",
    "sg:city":"Trezzano sul Naviglio",
    "sg:orig_category":"Audiovisivi Apparecchi Ed Impianti - Produzione, Commercio E Noleggio",
    "sg:phone":"+39 02 484152",
    "sg:postcode":"20090",
    "sg:province":"Milano",
    "sg:website":"http://www.nec.it/",
    "wof:name":"Nec Italia Srl",
    "wof:placetype":"venue"
},
  "geometry": {"coordinates":[9.061094,45.421906],"type":"Point"}
}