{
  "type": "Feature",
  "properties": {
    "iso:country":"IT",
    "sg:address":"1, Via Cugia Pasquale 09129 Cagliari",
    "sg:city":"Cagliari",
    "sg:classifiers":[
        {
            "category":"Communications",
            "subcategory":"Newspaper",
            "type":"Services"
        }
    ],
    "sg:phone":"+39 39070340741",
    "sg:postcode":"09129",
    "sg:province":"Cagliari",
    "sg:tags":[
        "advertising"
    ],
    "wof:name":"Creative S.a.s.",
    "wof:placetype":"venue"
},
  "geometry": {"coordinates":[9.109228,39.215458],"type":"Point"}
}