{
  "type": "Feature",
  "properties": {
    "iso:country":"IT",
    "sg:address":"34/a, Lungo Mare Del Sole 71043 Manfredonia",
    "sg:city":"Manfredonia",
    "sg:classifiers":[
        {
            "category":"Travel",
            "subcategory":"Travel Agent",
            "type":"Entertainment"
        }
    ],
    "sg:phone":"+39 0884 542843",
    "sg:postcode":"71043",
    "sg:province":"Foggia",
    "sg:tags":[
        "business"
    ],
    "wof:name":"Albergo Hotel Panorama Del Golfo",
    "wof:placetype":"venue"
},
  "geometry": {"coordinates":[15.5447,41.462334],"type":"Point"}
}