{
  "type": "Feature",
  "properties": {
    "addr:full":"51030 Serravalle Pistoiese Serravalle Pistoiese Pistoia 51030",
    "addr:postcode":"51030;51030",
    "iso:country":"IT",
    "sg:address":"51030 Serravalle Pistoiese",
    "sg:city":"Serravalle Pistoiese",
    "sg:orig_category":"Petroli, Gas E Combustibili",
    "sg:phone":"+39 0573 518205",
    "sg:postcode":"51030",
    "sg:province":"Pistoia",
    "wof:name":"Biagioni Gas Srl",
    "wof:placetype":"venue"
},
  "geometry": {"coordinates":[10.844666481,43.9067726135],"type":"Point"}
}