{
  "type": "Feature",
  "properties": {
    "iso:country":"IT",
    "sg:address":"Via Roma 66; Vercurago; 24030",
    "sg:classifiers":[
        {
            "category":"Banks & Credit Unions",
            "subcategory":"Bank",
            "type":"Services"
        }
    ],
    "sg:phone":"+39 0341 421041",
    "sg:postcode":"24030",
    "sg:province":"Bergamo",
    "wof:name":"Banca Popolare Di Lecco Spa",
    "wof:placetype":"venue"
},
  "geometry": {"coordinates":[9.424152,45.81115],"type":"Point"}
}