{
  "type": "Feature",
  "properties": {
    "addr:full":"81020 San Nicola La Strada San Nicola la Strada Caserta 81020",
    "addr:housenumber":"81020",
    "addr:postcode":"81020",
    "addr:street":"Strada Caserta",
    "iso:country":"IT",
    "sg:address":"81020 San Nicola La Strada",
    "sg:city":"San Nicola la Strada",
    "sg:orig_category":"Scuole E Servizi Scolastici. Servizi Per Lo Sport E Il Tempo Libero",
    "sg:phone":"+39 0823 451043",
    "sg:postcode":"81020",
    "sg:province":"Caserta",
    "wof:name":"Drago Animation Laboratory Di Luisa Tortora",
    "wof:placetype":"venue"
},
  "geometry": {"coordinates":[14.329011,41.055424],"type":"Point"}
}