{
  "type": "Feature",
  "properties": {
    "iso:country":"IT",
    "sg:address":"20129 Milano",
    "sg:city":"Milano",
    "sg:orig_category":"Servizi Per Lo Sport E Il Tempo Libero. Servizi Al Turismo",
    "sg:phone":"+39 02 201359",
    "sg:postcode":"20129",
    "sg:province":"Milano",
    "sg:website":"http://www.fisyodinamic.it",
    "wof:name":"Fisiodynamic Sas Di Capuana",
    "wof:placetype":"venue"
},
  "geometry": {"coordinates":[9.214753,45.475777],"type":"Point"}
}