{
  "type": "Feature",
  "properties": {
    "iso:country":"IT",
    "sg:address":"28021 Borgomanero",
    "sg:city":"Borgomanero",
    "sg:orig_category":"Imprese Di Costruzioni Civili Ed Industriali",
    "sg:phone":"+39 0322 82038",
    "sg:postcode":"28021",
    "sg:province":"Novara",
    "wof:name":"Carnelli Mario & C. Snc",
    "wof:placetype":"venue"
},
  "geometry": {"coordinates":[8.464908,45.702545],"type":"Point"}
}