{
  "type": "Feature",
  "properties": {
    "addr:full":"23865 Valbrona Oliveto Lario Oliveto Lario Lecco 23865",
    "addr:postcode":"23865;23865",
    "addr:street":"Lario Oliveto Lario Lecco",
    "iso:country":"IT",
    "sg:address":"23865 Valbrona Oliveto Lario",
    "sg:city":"Oliveto Lario",
    "sg:classifiers":[
        {
            "category":"Health Services",
            "subcategory":"Nursing And Care Facility",
            "type":"Services"
        }
    ],
    "sg:phone":"+39 031 968000",
    "sg:postcode":"23865",
    "sg:province":"Lecco",
    "sg:tags":[
        "case",
        "riposo",
        "di"
    ],
    "wof:name":"San Giorgio - Residenza Per Anziani",
    "wof:placetype":"venue"
},
  "geometry": {"coordinates":[9.390071,45.852982],"type":"Point"}
}