{
  "type": "Feature",
  "properties": {
    "iso:country":"IT",
    "sg:address":"1/5, Frazione Tiveriacco 33030 Maiano",
    "sg:classifiers":[
        {
            "category":"Home & Garden",
            "subcategory":"Home Furnishings",
            "type":"Retail Goods"
        }
    ],
    "sg:phone":"+39 0432 959252",
    "sg:postcode":"33030",
    "sg:province":"Udine",
    "sg:tags":[
        "household"
    ],
    "wof:name":"Mobilsnaidero S.r.l.",
    "wof:placetype":"venue"
},
  "geometry": {"coordinates":[13.054007,46.18552],"type":"Point"}
}