{
  "type": "Feature",
  "properties": {
    "iso:country":"IT",
    "sg:address":"72100 Brindisi",
    "sg:city":"Brindisi",
    "sg:orig_category":"Trasporti E Spedizioni Merci",
    "sg:phone":"+39 0831 411366",
    "sg:postcode":"72100",
    "sg:province":"Brindisi",
    "wof:name":"Transervis Srl",
    "wof:placetype":"venue"
},
  "geometry": {"coordinates":[17.942587,40.66259],"type":"Point"}
}