{
  "type": "Feature",
  "properties": {
    "addr:full":"Vicolo Treviso 2 31040 Trevignano Trevignano Treviso 31040",
    "addr:housenumber":"2",
    "addr:postcode":"31040;31040",
    "addr:street":"Vicolo Treviso",
    "iso:country":"IT",
    "sg:address":"Vicolo Treviso 2 31040 Trevignano",
    "sg:city":"Trevignano",
    "sg:orig_category":"Special-design Formworks",
    "sg:phone":"+39 0423 670225",
    "sg:postcode":"31040",
    "sg:province":"Treviso",
    "wof:name":"Olmet Casseforme Srl",
    "wof:placetype":"venue"
},
  "geometry": {"coordinates":[12.108126,45.749142],"type":"Point"}
}