{
  "type": "Feature",
  "properties": {
    "addr:full":"1, Strada Casale 15040 Frassineto Po Frassineto Po Alessandria 15040",
    "addr:postcode":"15040;15040",
    "addr:street":"Strada Casale;Po",
    "iso:country":"IT",
    "sg:address":"1, Strada Casale 15040 Frassineto Po",
    "sg:city":"Frassineto Po",
    "sg:classifiers":[
        {
            "category":"Real Estate",
            "subcategory":"Surveying",
            "type":"Services"
        }
    ],
    "sg:phone":"+39 0142 482498",
    "sg:postcode":"15040",
    "sg:province":"Alessandria",
    "sg:tags":[
        "equipment",
        "material",
        "good",
        "-",
        "handling"
    ],
    "wof:name":"So.le. (s.r.l.)",
    "wof:placetype":"venue"
},
  "geometry": {"coordinates":[8.551706,45.096077],"type":"Point"}
}