{
  "type": "Feature",
  "properties": {
    "iso:country":"IT",
    "sg:address":"40122 Bologna",
    "sg:city":"Bologna",
    "sg:orig_category":"Assicurazioni",
    "sg:phone":"+39 051 553412",
    "sg:postcode":"40122",
    "sg:province":"Bologna",
    "wof:name":"Cristiani Mirna Assicurazioni Mirna Tagliavini",
    "wof:placetype":"venue"
},
  "geometry": {"coordinates":[11.333976,44.499805],"type":"Point"}
}