{
  "type": "Feature",
  "properties": {
    "iso:country":"IT",
    "sg:address":"26831 Casalmaiocco",
    "sg:city":"Casalmaiocco",
    "sg:orig_category":"Ricambi E Componenti Dei Mezzi Di Trasporto",
    "sg:phone":"+39 02 9826 4006",
    "sg:postcode":"26831",
    "sg:province":"Lodi",
    "wof:name":"Carbomet Srl",
    "wof:placetype":"venue"
},
  "geometry": {"coordinates":[9.36656,45.357796],"type":"Point"}
}