{
  "type": "Feature",
  "properties": {
    "addr:full":"31058 Susegana Susegana Treviso 31058",
    "addr:postcode":"31058;31058",
    "iso:country":"IT",
    "sg:address":"31058 Susegana",
    "sg:city":"Susegana",
    "sg:orig_category":"Forniture Per Attivita' Industriali",
    "sg:phone":"+39 0438 738334",
    "sg:postcode":"31058",
    "sg:province":"Treviso",
    "wof:name":"Bellotto Fratelli (s.n.c.)",
    "wof:placetype":"venue"
},
  "geometry": {"coordinates":[12.2638530731,45.8404083252],"type":"Point"}
}