{
  "type": "Feature",
  "properties": {
    "iso:country":"IT",
    "sg:address":"20050 Sovico",
    "sg:city":"Sovico",
    "sg:orig_category":"Giocattoli E Giochi - Produzione E Ingrosso",
    "sg:phone":"+39 039 201 8402",
    "sg:postcode":"20050",
    "sg:province":"Milano",
    "wof:name":"Villa Giocattoli Srl",
    "wof:placetype":"venue"
},
  "geometry": {"coordinates":[9.260791,45.644905],"type":"Point"}
}