{
  "type": "Feature",
  "properties": {
    "addr:full":"Corso Vittorio; Campagnano Di Roma",
    "addr:street":"Corso Vittorio;Di Roma",
    "iso:country":"IT",
    "sg:address":"Corso Vittorio; Campagnano Di Roma",
    "sg:classifiers":[
        {
            "category":"Banks & Credit Unions",
            "subcategory":"Bank",
            "type":"Services"
        }
    ],
    "sg:phone":"+39 06 904 1735",
    "wof:name":"Banca Di Roma",
    "wof:placetype":"venue"
},
  "geometry": {"coordinates":[12.382,42.13974],"type":"Point"}
}