{
  "type": "Feature",
  "properties": {
    "addr:full":"1, Via Fabbri Paolo 40013 Castel Maggiore Castel Maggiore Bologna 40013",
    "addr:postcode":"40013;40013",
    "addr:street":"Via Fabbri Paolo",
    "iso:country":"IT",
    "sg:address":"1, Via Fabbri Paolo 40013 Castel Maggiore",
    "sg:city":"Castel Maggiore",
    "sg:classifiers":[
        {
            "category":"Wholesale",
            "subcategory":"Drugs",
            "type":"Manufacturing & Wholesale Goods"
        }
    ],
    "sg:phone":"+39 051 419 0611",
    "sg:postcode":"40013",
    "sg:province":"Bologna",
    "sg:tags":[
        "chemical",
        "pharmaceutical"
    ],
    "wof:name":"Tartarini O.m.t. (s.p.a.)",
    "wof:placetype":"venue"
},
  "geometry": {"coordinates":[11.350978,44.554237],"type":"Point"}
}