{
  "type": "Feature",
  "properties": {
    "iso:country":"IT",
    "sg:address":"80142 Napoli",
    "sg:city":"Napoli",
    "sg:orig_category":"Cartotecnica E Servizi. Forniture Per Uffici",
    "sg:phone":"+39 081 283929",
    "sg:postcode":"80142",
    "sg:province":"Napoli",
    "wof:name":"R.g. Di Rositani Gennaro E C. - Snc",
    "wof:placetype":"venue"
},
  "geometry": {"coordinates":[14.277389,40.847008],"type":"Point"}
}