{
  "type": "Feature",
  "properties": {
    "iso:country":"IT",
    "sg:address":"Via Galileo Galilei 10/11, 83030 Venticano, Av",
    "sg:city":"Venticano",
    "sg:classifiers":[
        {
            "category":"Banks & Credit Unions",
            "subcategory":"Bank",
            "type":"Services"
        }
    ],
    "sg:postcode":"83030",
    "sg:province":"Avellino",
    "wof:name":"Cassa Rurale Ed Artigiana Di Venticano Banca Di Credito Cooperativo Scrl",
    "wof:placetype":"venue"
},
  "geometry": {"coordinates":[14.912409,41.046745],"type":"Point"}
}