{
  "type": "Feature",
  "properties": {
    "iso:country":"IT",
    "sg:address":"97019 Vittoria",
    "sg:city":"Vittoria",
    "sg:orig_category":"Alberghi E Strutture Extra Alberghiere",
    "sg:phone":"+39 0932 992990",
    "sg:postcode":"97019",
    "sg:province":"Ragusa",
    "sg:website":"http://www.vittoriaresidence.com",
    "wof:name":"Hotel Vittoria Residence",
    "wof:placetype":"venue"
},
  "geometry": {"coordinates":[14.539851,36.949951],"type":"Point"}
}