{
  "type": "Feature",
  "properties": {
    "addr:full":"Via Pacini, 76; Milano; 20131 Milano Milano 20131",
    "addr:housenumber":"76",
    "addr:postcode":"20131;20131",
    "addr:street":"Via Pacini",
    "iso:country":"IT",
    "sg:address":"Via Pacini, 76; Milano; 20131",
    "sg:city":"Milano",
    "sg:classifiers":[
        {
            "category":"Banks & Credit Unions",
            "subcategory":"Bank",
            "type":"Services"
        }
    ],
    "sg:phone":"+39 02 266 6426",
    "sg:postcode":"20131",
    "sg:province":"Milano",
    "wof:name":"Banco Ambrosiano Veneto Spa",
    "wof:placetype":"venue"
},
  "geometry": {"coordinates":[9.235732,45.484398],"type":"Point"}
}