{
  "type": "Feature",
  "properties": {
    "addr:full":"27028 San Martino Siccomario San Martino Siccomario Pavia 27028",
    "addr:housenumber":"27028",
    "addr:postcode":"27028",
    "addr:street":"San",
    "iso:country":"IT",
    "sg:address":"27028 San Martino Siccomario",
    "sg:city":"San Martino Siccomario",
    "sg:orig_category":"Macchine Ed Impianti Per Edilizia E Lavori Pubblici. Forniture Per Edilizia E Lavori Pubblici",
    "sg:phone":"+39 0382 559597",
    "sg:postcode":"27028",
    "sg:province":"Pavia",
    "wof:name":"Eurocolor",
    "wof:placetype":"venue"
},
  "geometry": {"coordinates":[9.132076,45.165882],"type":"Point"}
}