{
  "type": "Feature",
  "properties": {
    "iso:country":"IT",
    "sg:address":"30/a, Via Grassi Antonio 35129 Padova",
    "sg:city":"Padova",
    "sg:classifiers":[
        {
            "category":"Professional",
            "subcategory":"Printing & Photocopies",
            "type":"Services"
        }
    ],
    "sg:phone":"+39 39049772488",
    "sg:postcode":"35129",
    "sg:province":"Padova",
    "wof:name":"Tipografia Boaretto (s.r.l.)",
    "wof:placetype":"venue"
},
  "geometry": {"coordinates":[11.8441667557,45.3974990845],"type":"Point"}
}