{
  "type": "Feature",
  "properties": {
    "addr:full":"17012 Albissola Marina Albissola Marina Savona 17012",
    "addr:postcode":"17012;17012",
    "iso:country":"IT",
    "sg:address":"17012 Albissola Marina",
    "sg:city":"Albissola Marina",
    "sg:orig_category":"Macchine Utensili E Impianti",
    "sg:phone":"+39 019 480082",
    "sg:postcode":"17012",
    "sg:province":"Savona",
    "wof:name":"Ep Systems S.r.l.",
    "wof:placetype":"venue"
},
  "geometry": {"coordinates":[8.497047,44.337627],"type":"Point"}
}