{
  "type": "Feature",
  "properties": {
    "iso:country":"IT",
    "sg:address":"95127 Catania",
    "sg:city":"Catania",
    "sg:orig_category":"Telecomunicazioni E Telefonia, Impianti, Apparecchi E Servizi",
    "sg:phone":"+39 095 375914",
    "sg:postcode":"95127",
    "sg:province":"Catania",
    "wof:name":"Cartomedia L'ufficio Oggi Di Campochiaro Massimiliano",
    "wof:placetype":"venue"
},
  "geometry": {"coordinates":[15.096818,37.519753],"type":"Point"}
}