{
  "type": "Feature",
  "properties": {
    "iso:country":"IT",
    "sg:address":"24020 Torre Boldone",
    "sg:city":"Torre Boldone",
    "sg:orig_category":"Forniture Per Agricoltura E Zootecnia",
    "sg:phone":"+39 035 341104",
    "sg:postcode":"24020",
    "sg:province":"Bergamo",
    "wof:name":"Bianchi Gino",
    "wof:placetype":"venue"
},
  "geometry": {"coordinates":[9.6962652206,45.7222061157],"type":"Point"}
}