{
  "type": "Feature",
  "properties": {
    "iso:country":"IT",
    "sg:address":"Via Milano, 5 - Luisago 22070 Portichetto",
    "sg:city":"Luisago",
    "sg:orig_category":"Capillary Tube Manufacturing And Working Machines",
    "sg:phone":"+39 031 927170",
    "sg:postcode":"22070",
    "sg:province":"Como",
    "sg:website":"www.mmpoint.it/bema",
    "wof:name":"Bema S.r.l.",
    "wof:placetype":"venue"
},
  "geometry": {"coordinates":[9.059883,45.75679],"type":"Point"}
}