{
  "type": "Feature",
  "properties": {
    "addr:full":"94, V. Roma 26010 Pianengo Pianengo Cremona 26010",
    "addr:housenumber":"94",
    "addr:postcode":"26010;26010",
    "addr:street":"V. Roma",
    "iso:country":"IT",
    "sg:address":"94, V. Roma 26010 Pianengo",
    "sg:city":"Pianengo",
    "sg:classifiers":[
        {
            "category":"Manufacturing",
            "subcategory":"Food",
            "type":"Manufacturing & Wholesale Goods"
        }
    ],
    "sg:phone":"+39 39037374144",
    "sg:postcode":"26010",
    "sg:province":"Cremona",
    "sg:tags":[
        "equipment",
        "processing",
        "-",
        "machinery"
    ],
    "sg:website":"http://www.farck.com",
    "wof:name":"Farck Spa",
    "wof:placetype":"venue"
},
  "geometry": {"coordinates":[9.7132930756,45.434551239],"type":"Point"}
}