{
  "type": "Feature",
  "properties": {
    "iso:country":"IT",
    "sg:address":"Via Gramsci, 16; Biella; 13051",
    "sg:classifiers":[
        {
            "category":"Banks & Credit Unions",
            "subcategory":"Bank",
            "type":"Services"
        }
    ],
    "sg:phone":"+39 015 35081",
    "wof:name":"Cassa Di Risparmio Di Biella",
    "wof:placetype":"venue"
},
  "geometry": {"coordinates":[8.073496,45.538662],"type":"Point"}
}