{
  "type": "Feature",
  "properties": {
    "iso:country":"IT",
    "sg:address":"84128 Salerno",
    "sg:city":"Salerno",
    "sg:orig_category":"Arredo Cucina Ed Elettrodomestici. Elettrodomestici",
    "sg:phone":"+39 089 756700",
    "sg:postcode":"84128",
    "sg:province":"Salerno",
    "sg:website":"http://web.tiscalinet.it/cosma",
    "wof:name":"Cosma Di Costantino Magliulo",
    "wof:placetype":"venue"
},
  "geometry": {"coordinates":[14.791476,40.665726],"type":"Point"}
}