{
  "type": "Feature",
  "properties": {
    "iso:country":"IT",
    "sg:address":"Via Bergamo 26029 Soncino",
    "sg:city":"Soncino",
    "sg:classifiers":[
        {
            "category":"Professional",
            "subcategory":"Printing & Photocopies",
            "type":"Services"
        }
    ],
    "sg:phone":"+39 39037485191",
    "sg:postcode":"26029",
    "sg:province":"Cremona",
    "wof:name":"Sigma Moore Spa",
    "wof:placetype":"venue"
},
  "geometry": {"coordinates":[9.8592853546,45.4174804688],"type":"Point"}
}