{
  "type": "Feature",
  "properties": {
    "iso:country":"IT",
    "sg:address":"20090 Segrate",
    "sg:city":"Segrate",
    "sg:orig_category":"Professionisti - Studi E Servizi Ed Associazioni Di Interesse Aziendale. Associazioni Ed Organismi Di Interesse Pubblico",
    "sg:phone":"+39 02 213 7864",
    "sg:postcode":"20090",
    "sg:province":"Milano",
    "wof:name":"Lega Nazionale Per La Difesa Del Cane",
    "wof:placetype":"venue"
},
  "geometry": {"coordinates":[9.2739725113,45.4845695496],"type":"Point"}
}