{
  "type": "Feature",
  "properties": {
    "iso:country":"IT",
    "sg:address":"98057 Milazzo",
    "sg:city":"Milazzo",
    "sg:orig_category":"Servizi E Lavori Per Agricoltura E Zootecnia. Servizi E Lavori Per Edilizia E Lavori Pubblici",
    "sg:phone":"+39 090 922 2616",
    "sg:postcode":"98057",
    "sg:province":"Messina",
    "wof:name":"Azienda Agricola Verde 2000",
    "wof:placetype":"venue"
},
  "geometry": {"coordinates":[15.237034,38.200718],"type":"Point"}
}