{
  "type": "Feature",
  "properties": {
    "addr:full":"54033 Carrara Avenza Massa-Carrara 54033",
    "addr:postcode":"54033;54033",
    "addr:street":"Avenza",
    "iso:country":"IT",
    "sg:address":"54033 Carrara",
    "sg:city":"Avenza",
    "sg:orig_category":"Servizi E Lavori Per Edilizia E Lavori Pubblici",
    "sg:phone":"+39 0585 857400",
    "sg:postcode":"54033",
    "sg:province":"Massa-Carrara",
    "wof:name":"Cibifarben Snc",
    "wof:placetype":"venue"
},
  "geometry": {"coordinates":[10.072282,44.042919],"type":"Point"}
}