{
  "type": "Feature",
  "properties": {
    "addr:full":"07046 Porto Torres Porto Torres Sassari 07046",
    "addr:housenumber":"07046",
    "addr:postcode":"07046",
    "addr:street":"Porto Torres Porto Torres",
    "iso:country":"IT",
    "sg:address":"07046 Porto Torres",
    "sg:city":"Porto Torres",
    "sg:orig_category":"Acquedotti, Gasdotti Ed Oleodotti - Impianti Ed Attrezzature",
    "sg:phone":"+39 079 516125",
    "sg:postcode":"07046",
    "sg:province":"Sassari",
    "wof:name":"Co.m.i. Srl",
    "wof:placetype":"venue"
},
  "geometry": {"coordinates":[8.341701,40.828373],"type":"Point"}
}