{
  "type": "Feature",
  "properties": {
    "iso:country":"IT",
    "sg:address":"00128 Roma",
    "sg:city":"Roma",
    "sg:classifiers":[
        {
            "category":"Professional",
            "subcategory":"Business Services",
            "type":"Services"
        }
    ],
    "sg:phone":"+39 06 508 7891",
    "sg:postcode":"00128",
    "sg:province":"Roma",
    "sg:tags":[
        "support",
        "companies",
        "events",
        "trade"
    ],
    "sg:website":"http://www.carliproduzioni.it",
    "wof:name":"Carli Produzioni Srl",
    "wof:placetype":"venue"
},
  "geometry": {"coordinates":[12.456924,41.793079],"type":"Point"}
}