{
  "type": "Feature",
  "properties": {
    "addr:full":"Via Del Lavoratore 2/a 44016 San Biagio San Biagio Ferrara 44016",
    "addr:housenumber":"2 / a",
    "addr:postcode":"44016;biagio;44016",
    "addr:street":"Via Del Lavoratore",
    "iso:country":"IT",
    "sg:address":"Via Del Lavoratore 2/a 44016 San Biagio",
    "sg:city":"San Biagio",
    "sg:classifiers":[
        {
            "category":"Professional",
            "type":"Services"
        }
    ],
    "sg:phone":"+39 0532 809650",
    "sg:postcode":"44016",
    "sg:province":"Ferrara",
    "sg:tags":[
        "mould",
        "construction"
    ],
    "sg:website":"www.romplast.it",
    "wof:name":"Romplast Srl",
    "wof:placetype":"venue"
},
  "geometry": {"coordinates":[11.6204395294,44.8378944397],"type":"Point"}
}