{
  "type": "Feature",
  "properties": {
    "addr:full":"20, Via Monza 20064 Gorgonzola Gorgonzola Milano 20064",
    "addr:postcode":"20064;20064",
    "addr:street":"Via Monza",
    "iso:country":"IT",
    "sg:address":"20, Via Monza 20064 Gorgonzola",
    "sg:city":"Gorgonzola",
    "sg:classifiers":[
        {
            "category":"Shopping",
            "type":"Retail Goods"
        }
    ],
    "sg:phone":"+39 02 9530 0946",
    "sg:postcode":"20064",
    "sg:province":"Milano",
    "sg:tags":[
        "finished",
        "-",
        "metallic"
    ],
    "wof:name":"Nuova Ama Attrezzeria Meccanica Affini (s.r.l.)",
    "wof:placetype":"venue"
},
  "geometry": {"coordinates":[9.4309215546,45.5563163757],"type":"Point"}
}