{
  "type": "Feature",
  "properties": {
    "iso:country":"IT",
    "sg:address":"34148 Trieste",
    "sg:city":"Trieste",
    "sg:orig_category":"Prodotti Vari In Metallo",
    "sg:phone":"+39 040 814136",
    "sg:postcode":"34148",
    "sg:province":"Trieste",
    "wof:name":"World Wide Trade Trieste Srl",
    "wof:placetype":"venue"
},
  "geometry": {"coordinates":[13.8151521683,45.6180038452],"type":"Point"}
}