{
  "type": "Feature",
  "properties": {
    "addr:full":"00040 Rocca Priora Rocca Priora Roma 00040",
    "addr:postcode":"00040;00040",
    "iso:country":"IT",
    "sg:address":"00040 Rocca Priora",
    "sg:city":"Rocca Priora",
    "sg:classifiers":[
        {
            "category":"Health Services",
            "subcategory":"Health Practitioner",
            "type":"Services"
        }
    ],
    "sg:phone":"+39 06 947 2119",
    "sg:postcode":"00040",
    "sg:province":"Roma",
    "sg:tags":[
        "medici"
    ],
    "wof:name":"Riccardi Stefano",
    "wof:placetype":"venue"
},
  "geometry": {"coordinates":[12.7606287003,41.792350769],"type":"Point"}
}