{
  "type": "Feature",
  "properties": {
    "iso:country":"IT",
    "sg:address":"Via Firenze 75020 Noca Siri",
    "sg:classifiers":[
        {
            "category":"Science Facility",
            "type":"Public Place"
        }
    ],
    "sg:phone":"+39 0835 536598",
    "sg:postcode":"75020",
    "sg:province":"Matera",
    "sg:tags":[
        "appliance",
        "biomedical"
    ],
    "wof:name":"Tecnofarma S.r.l.",
    "wof:placetype":"venue"
},
  "geometry": {"coordinates":[16.606087,40.668652],"type":"Point"}
}