{
  "type": "Feature",
  "properties": {
    "iso:country":"IT",
    "sg:address":"Via Roma 25023 Gottolengo",
    "sg:city":"Gottolengo",
    "sg:classifiers":[
        {
            "category":"Wholesale",
            "subcategory":"Machinery & Supplies",
            "type":"Manufacturing & Wholesale Goods"
        }
    ],
    "sg:phone":"+39 030 951 7176",
    "sg:postcode":"25023",
    "sg:province":"Brescia",
    "sg:tags":[
        "-",
        "agriculture",
        "equipment"
    ],
    "wof:name":"Damax",
    "wof:placetype":"venue"
},
  "geometry": {"coordinates":[10.268511,45.286053],"type":"Point"}
}