{
  "type": "Feature",
  "properties": {
    "addr:full":"38, Via Buonarroti Michelangelo 20145 Milano Milano Milano 20145",
    "addr:postcode":"20145;20145",
    "addr:street":"Via Buonarroti Michelangelo",
    "iso:country":"IT",
    "sg:address":"38, Via Buonarroti Michelangelo 20145 Milano",
    "sg:city":"Milano",
    "sg:classifiers":[
        {
            "category":"Manufacturing",
            "subcategory":"Printing",
            "type":"Manufacturing & Wholesale Goods"
        }
    ],
    "sg:phone":"+39 02 4800 2877",
    "sg:postcode":"20145",
    "sg:province":"Milano",
    "sg:tags":[
        "publishing"
    ],
    "wof:name":"Sergio Bonelli Editore S.p.a.",
    "wof:placetype":"venue"
},
  "geometry": {"coordinates":[9.1555433273,45.4711036682],"type":"Point"}
}