{
  "type": "Feature",
  "properties": {
    "iso:country":"IT",
    "sg:address":"12037 Saluzzo",
    "sg:city":"Saluzzo",
    "sg:orig_category":"Articoli Funerari",
    "sg:phone":"+39 0175 248469",
    "sg:postcode":"12037",
    "sg:province":"Cuneo",
    "wof:name":"Ellena Snc Autotrasformazioni",
    "wof:placetype":"venue"
},
  "geometry": {"coordinates":[7.49877,44.645824],"type":"Point"}
}