{
  "type": "Feature",
  "properties": {
    "iso:country":"IT",
    "sg:address":"65128 Pescara",
    "sg:city":"Pescara",
    "sg:orig_category":"Prodotti E Manufatti In Gomma. Servizi E Lavori Industria Della Gomma. Ricambi E Componenti Dei Mezzi Di Trasporto",
    "sg:phone":"+39 085 52521",
    "sg:postcode":"65128",
    "sg:province":"Pescara",
    "wof:name":"Taddeo & Ventura Snc",
    "wof:placetype":"venue"
},
  "geometry": {"coordinates":[14.1975717545,42.4453773499],"type":"Point"}
}