{
  "type": "Feature",
  "properties": {
    "addr:full":"04017 San Felice Circeo San Felice Circeo Latina 04017",
    "addr:housenumber":"04017",
    "addr:postcode":"04017",
    "addr:street":"San",
    "iso:country":"IT",
    "sg:address":"04017 San Felice Circeo",
    "sg:city":"San Felice Circeo",
    "sg:orig_category":"Ceramiche Per Pavimenti E Rivestimenti - Vendita Al Dettaglio",
    "sg:phone":"+39 0773 540620",
    "sg:postcode":"04017",
    "sg:province":"Latina",
    "wof:name":"Diva Sas Di Di Cosimo Egidio E C.",
    "wof:placetype":"venue"
},
  "geometry": {"coordinates":[13.095903,41.242325],"type":"Point"}
}