{
  "type": "Feature",
  "properties": {
    "addr:full":"20080 Basiglio Basiglio Milano 20080",
    "addr:postcode":"20080;20080",
    "iso:country":"IT",
    "sg:address":"20080 Basiglio",
    "sg:city":"Basiglio",
    "sg:orig_category":"Ospedali E Servizi Sanitari",
    "sg:phone":"+39 02 9075 4888",
    "sg:postcode":"20080",
    "sg:province":"Milano",
    "wof:name":"Croce Amica Volontari Del Soccorso",
    "wof:placetype":"venue"
},
  "geometry": {"coordinates":[9.16816,45.380779],"type":"Point"}
}