{
  "type": "Feature",
  "properties": {
    "addr:full":"Km. 80.030, Strada St. 98 70026 Modugno Modugno Bari 70026",
    "addr:housenumber":"98",
    "addr:postcode":"70026;70026",
    "addr:street":"Km.;Strada St.",
    "iso:country":"IT",
    "sg:address":"Km. 80.030, Strada St. 98 70026 Modugno",
    "sg:city":"Modugno",
    "sg:classifiers":[
        {
            "category":"Home & Garden",
            "subcategory":"Home Furnishings",
            "type":"Retail Goods"
        }
    ],
    "sg:phone":"+39 080 535 8765",
    "sg:postcode":"70026",
    "sg:province":"Bari",
    "sg:tags":[
        "household"
    ],
    "wof:name":"Leonmobili Dei F.lli Leone (s.n.c.)",
    "wof:placetype":"venue"
},
  "geometry": {"coordinates":[16.869291,41.126053],"type":"Point"}
}