{
  "type": "Feature",
  "properties": {
    "iso:country":"IT",
    "sg:address":"12060 Roreto",
    "sg:orig_category":"Prodotti Chimici Secondari. Macchine E Forniture Per Ecologia E Smaltimento Rifiuti",
    "sg:phone":"+39 0172 423317",
    "sg:postcode":"12060",
    "sg:province":"Cuneo",
    "wof:name":"Team M.d.l. S.r.l.",
    "wof:placetype":"venue"
},
  "geometry": {"coordinates":[7.8549728394,44.6921043396],"type":"Point"}
}