{
  "type": "Feature",
  "properties": {
    "iso:country":"IT",
    "sg:address":"99, Via Monte Leone 21013 Gallarate",
    "sg:city":"Gallarate",
    "sg:classifiers":[
        {
            "category":"Manufacturing",
            "subcategory":"Metals",
            "type":"Manufacturing & Wholesale Goods"
        }
    ],
    "sg:phone":"+39 0331 773773",
    "sg:postcode":"21013",
    "sg:province":"Varese",
    "sg:tags":[
        "metallurgy",
        "metalworking"
    ],
    "wof:name":"Emmevi (s.n.c.)",
    "wof:placetype":"venue"
},
  "geometry": {"coordinates":[8.7620649338,45.6694145203],"type":"Point"}
}