{
  "type": "Feature",
  "properties": {
    "iso:country":"IT",
    "sg:address":"V. Fosso Antico - Centobuchi 63033 Monteprandone",
    "sg:city":"Centobuchi",
    "sg:classifiers":[
        {
            "category":"Food & Beverages",
            "subcategory":"Groceries & Convenience Stores",
            "type":"Retail Goods"
        }
    ],
    "sg:phone":"+39 0735 712801",
    "sg:postcode":"63033",
    "sg:province":"Ascoli Piceno",
    "sg:tags":[
        "product",
        "related"
    ],
    "sg:website":"http://www.adriacoop.com:ws_end: :mark:ws:http://www.paginegialle.it/adriacoopscrl",
    "wof:name":"Adriacoop Scrl",
    "wof:placetype":"venue"
},
  "geometry": {"coordinates":[13.8472099304,42.88722229],"type":"Point"}
}