{
  "type": "Feature",
  "properties": {
    "addr:full":"Via Novella 61022 Colbordolo Colbordolo Pesaro E Urbino 61022",
    "addr:postcode":"61022;61022",
    "addr:street":"Via Novella",
    "iso:country":"IT",
    "sg:address":"Via Novella 61022 Colbordolo",
    "sg:city":"Colbordolo",
    "sg:classifiers":[
        {
            "category":"Home & Garden",
            "subcategory":"Home Furnishings",
            "type":"Retail Goods"
        }
    ],
    "sg:phone":"+39 0721 479221",
    "sg:postcode":"61022",
    "sg:province":"Pesaro E Urbino",
    "sg:tags":[
        "household"
    ],
    "wof:name":"Top Srl",
    "wof:placetype":"venue"
},
  "geometry": {"coordinates":[12.719912,43.837784],"type":"Point"}
}