{
  "type": "Feature",
  "properties": {
    "iso:country":"IT",
    "sg:address":"Via Imolese 50/c 50033 Firenzuola",
    "sg:city":"Firenzuola",
    "sg:classifiers":[
        {
            "category":"Manufacturing",
            "subcategory":"Building Materials",
            "type":"Manufacturing & Wholesale Goods"
        }
    ],
    "sg:phone":"+39 055 819038",
    "sg:postcode":"50033",
    "sg:province":"Firenze",
    "sg:tags":[
        "sandstone",
        "purpose"
    ],
    "sg:website":"www.coopscalpellini.com",
    "wof:name":"Cooperativa Scalpellini Soc. Coop. S.r.l",
    "wof:placetype":"venue"
},
  "geometry": {"coordinates":[11.380777,44.116802],"type":"Point"}
}