{
  "type": "Feature",
  "properties": {
    "iso:country":"IT",
    "sg:address":"57123 Livorno",
    "sg:city":"Livorno",
    "sg:orig_category":"Agenzie Marittime",
    "sg:phone":"+39 0586 895577",
    "sg:postcode":"57123",
    "sg:province":"Livorno",
    "sg:website":"http://www.alemannospedizioni.it",
    "wof:name":"Alemanno & C. Srl",
    "wof:placetype":"venue"
},
  "geometry": {"coordinates":[10.310501,43.577747],"type":"Point"}
}