{
  "type": "Feature",
  "properties": {
    "addr:full":"20099 Sesto San Giovanni Sesto San Giovanni Milano 20099",
    "addr:postcode":"20099;20099",
    "iso:country":"IT",
    "sg:address":"20099 Sesto San Giovanni",
    "sg:city":"Sesto San Giovanni",
    "sg:orig_category":"Trattamenti Termici E Superficiali Metalli, Galvanotecnica",
    "sg:phone":"+39 02 248 9507",
    "sg:postcode":"20099",
    "sg:province":"Milano",
    "wof:name":"Valcamonica Davide",
    "wof:placetype":"venue"
},
  "geometry": {"coordinates":[9.22488,45.524384],"type":"Point"}
}