{
  "type": "Feature",
  "properties": {
    "addr:full":"30010 Campagna Lupia Campagna Lupia Venezia 30010",
    "addr:postcode":"30010;30010",
    "iso:country":"IT",
    "sg:address":"30010 Campagna Lupia",
    "sg:city":"Campagna Lupia",
    "sg:orig_category":"Macchine Ed Impianti Per Edilizia E Lavori Pubblici",
    "sg:phone":"+39 041 460214",
    "sg:postcode":"30010",
    "sg:province":"Venezia",
    "wof:name":"Boldrin Escavazioni Di Geom. Fabio",
    "wof:placetype":"venue"
},
  "geometry": {"coordinates":[12.101007,45.358116],"type":"Point"}
}