{
  "type": "Feature",
  "properties": {
    "iso:country":"IT",
    "sg:address":"00015 Monterotondo",
    "sg:city":"Monterotondo",
    "sg:orig_category":"Elettronica Professionale E Di Consumo. Forniture Per Il Settore Dello Spettacolo. Automazione E Macchine Per Ufficio. Forniture Per Congressi, Fiere E Manifestazioni",
    "sg:phone":"+39 06 9008 5354",
    "sg:postcode":"00015",
    "sg:province":"Roma",
    "wof:name":"Else Snc",
    "wof:placetype":"venue"
},
  "geometry": {"coordinates":[12.584048,42.059841],"type":"Point"}
}