{
  "type": "Feature",
  "properties": {
    "iso:country":"IT",
    "sg:address":"00194 Roma",
    "sg:city":"Roma",
    "sg:orig_category":"Servizi E Lavori Per Edilizia E Lavori Pubblici. Acqua, Luce, Gas E Societa' Di Esercizio Pubblico",
    "sg:phone":"+39 06 320 2671",
    "sg:postcode":"00194",
    "sg:province":"Roma",
    "wof:name":"Acea Distribuzione Spa",
    "wof:placetype":"venue"
},
  "geometry": {"coordinates":[12.453883,41.927349],"type":"Point"}
}