{
  "type": "Feature",
  "properties": {
    "iso:country":"IT",
    "sg:address":"37026 Pescantina",
    "sg:city":"Pescantina",
    "sg:classifiers":[
        {
            "category":"Parking",
            "subcategory":"Lot",
            "type":"Transportation"
        }
    ],
    "sg:phone":"+39 045 715 4966",
    "sg:postcode":"37026",
    "sg:province":"Verona",
    "sg:tags":[
        "good",
        "shipment",
        "transport"
    ],
    "wof:name":"Zaninelli Ernesto",
    "wof:placetype":"venue"
},
  "geometry": {"coordinates":[10.910691,45.480797],"type":"Point"}
}