{
  "type": "Feature",
  "properties": {
    "addr:full":"00192 Roma Roma Roma 00192",
    "addr:postcode":"00192;00192",
    "iso:country":"IT",
    "sg:address":"00192 Roma",
    "sg:city":"Roma",
    "sg:orig_category":"Climatizzazione E Condizionamento, Apparecchiature E Servizi",
    "sg:phone":"+39 06 687 4688",
    "sg:postcode":"00192",
    "sg:province":"Roma",
    "wof:name":"Zerenghi Srl",
    "wof:placetype":"venue"
},
  "geometry": {"coordinates":[12.461996,41.906464],"type":"Point"}
}