{
  "type": "Feature",
  "properties": {
    "iso:country":"IT",
    "sg:address":"80021 Afragola",
    "sg:city":"Afragola",
    "sg:orig_category":"Bevande, Vini E Liquori. Servizi E Lavori Per Industria Alimentare E Bevande",
    "sg:phone":"+39 081 852 6393",
    "sg:postcode":"80021",
    "sg:province":"Napoli",
    "wof:name":"Giugliano Orlando Srl",
    "wof:placetype":"venue"
},
  "geometry": {"coordinates":[14.307114,40.924019],"type":"Point"}
}