{
  "type": "Feature",
  "properties": {
    "addr:full":"2, Via Dalmastro 36030 Lugo Di Vicenza Lugo di Vicenza Vicenza 36030",
    "addr:postcode":"36030;36030",
    "addr:street":"Via Dalmastro",
    "iso:country":"IT",
    "sg:address":"2, Via Dalmastro 36030 Lugo Di Vicenza",
    "sg:city":"Lugo di Vicenza",
    "sg:classifiers":[
        {
            "category":"Manufacturing",
            "subcategory":"Rubber & Plastics",
            "type":"Manufacturing & Wholesale Goods"
        }
    ],
    "sg:phone":"+39 0445 329111",
    "sg:postcode":"36030",
    "sg:province":"Vicenza",
    "sg:tags":[
        "packaging",
        "material",
        "-"
    ],
    "wof:name":"Bp Europack S.p.a.",
    "wof:placetype":"venue"
},
  "geometry": {"coordinates":[11.5258522034,45.7423553467],"type":"Point"}
}