{
  "type": "Feature",
  "properties": {
    "addr:full":"262, Via Nizza 10126 Torino Torino Torino 10126",
    "addr:housenumber":"262",
    "addr:postcode":"10126;10126",
    "addr:street":"Via Nizza",
    "iso:country":"IT",
    "sg:address":"262, Via Nizza 10126 Torino",
    "sg:city":"Torino",
    "sg:classifiers":[
        {
            "category":"Travel",
            "subcategory":"Travel Agent",
            "type":"Entertainment"
        }
    ],
    "sg:phone":"+39 011 664 2000",
    "sg:postcode":"10126",
    "sg:province":"Torino",
    "sg:tags":[
        "business"
    ],
    "wof:name":"Lingotto S.p.a. - Hotel Le Meridien",
    "wof:placetype":"venue"
},
  "geometry": {"coordinates":[7.666979,45.031673],"type":"Point"}
}