{
  "type": "Feature",
  "properties": {
    "addr:full":"Via Milano 14; Busto; 21052 Varese 21052",
    "addr:housenumber":"14",
    "addr:postcode":"21052;21052",
    "addr:street":"Via Milano;Busto",
    "iso:country":"IT",
    "sg:address":"Via Milano 14; Busto; 21052",
    "sg:classifiers":[
        {
            "category":"Banks & Credit Unions",
            "subcategory":"Bank",
            "type":"Services"
        }
    ],
    "sg:phone":"+39 0331 394111",
    "sg:postcode":"21052",
    "sg:province":"Varese",
    "wof:name":"Istituto Bancario, San Paolo Di Torino Spa",
    "wof:placetype":"venue"
},
  "geometry": {"coordinates":[8.854451,45.611912],"type":"Point"}
}