{
  "type": "Feature",
  "properties": {
    "iso:country":"IT",
    "sg:address":"80047 San Giuseppe Vesuviano",
    "sg:city":"San Giuseppe Vesuviano",
    "sg:orig_category":"Abbigliamento - Produzione E Ingrosso",
    "sg:phone":"+39 081 529 6387",
    "sg:postcode":"80047",
    "sg:province":"Napoli",
    "wof:name":"C.p. Moda Srl",
    "wof:placetype":"venue"
},
  "geometry": {"coordinates":[14.491709,40.841099],"type":"Point"}
}