{
  "type": "Feature",
  "properties": {
    "iso:country":"IT",
    "sg:address":"35013 Cittadella",
    "sg:city":"Cittadella",
    "sg:classifiers":[
        {
            "category":"Government",
            "subcategory":"Office",
            "type":"Public Place"
        }
    ],
    "sg:phone":"+39 049 597 5960",
    "sg:postcode":"35013",
    "sg:province":"Padova",
    "sg:tags":[
        "e",
        "lo",
        "tempo",
        "libero",
        "per",
        "spettacolo",
        "servizi",
        "culturali",
        "sport",
        "il"
    ],
    "wof:name":"Orchestra Symphonium Veneta",
    "wof:placetype":"venue"
},
  "geometry": {"coordinates":[11.780816,45.653957],"type":"Point"}
}