{
  "type": "Feature",
  "properties": {
    "addr:full":"Via Del Commercio 35013 Cittadella Cittadella Padova 35013",
    "addr:postcode":"35013;35013",
    "addr:street":"Via Del Commercio",
    "iso:country":"IT",
    "sg:address":"Via Del Commercio 35013 Cittadella",
    "sg:city":"Cittadella",
    "sg:classifiers":[
        {
            "category":"Shopping",
            "subcategory":"Stationery & Office Supplies",
            "type":"Retail Goods"
        }
    ],
    "sg:phone":"+39 049 940 1500",
    "sg:postcode":"35013",
    "sg:province":"Padova",
    "sg:tags":[
        "professional"
    ],
    "wof:name":"Ca' Onorai Interior Design (s.p.a.)",
    "wof:placetype":"venue"
},
  "geometry": {"coordinates":[11.8025245667,45.6613006592],"type":"Point"}
}