{
  "type": "Feature",
  "properties": {
    "addr:full":"35124 Padova Padova Padova 35124",
    "addr:postcode":"35124;35124",
    "iso:country":"IT",
    "sg:address":"35124 Padova",
    "sg:city":"Padova",
    "sg:orig_category":"Pompe. Apparecchiature E Sistemi Per Imballaggio E Confezionamento",
    "sg:phone":"+39 049 680905",
    "sg:postcode":"35124",
    "sg:province":"Padova",
    "wof:name":"Longhini Guido - Longhini Service",
    "wof:placetype":"venue"
},
  "geometry": {"coordinates":[11.8892784119,45.3613929749],"type":"Point"}
}