{
  "type": "Feature",
  "properties": {
    "iso:country":"IT",
    "sg:address":"05018 Orvieto",
    "sg:city":"Orvieto",
    "sg:orig_category":"Arredo Urbano",
    "sg:phone":"+39 0763 302478",
    "sg:postcode":"05018",
    "sg:province":"Terni",
    "wof:name":"G.m.r. Lavorazione Marmi Snc",
    "wof:placetype":"venue"
},
  "geometry": {"coordinates":[12.146723,42.716347],"type":"Point"}
}