{
  "type": "Feature",
  "properties": {
    "iso:country":"IT",
    "sg:address":"40125 Bologna",
    "sg:city":"Bologna",
    "sg:classifiers":[
        {
            "category":"Health Services",
            "subcategory":"Health Practitioner",
            "type":"Services"
        }
    ],
    "sg:phone":"+39 051 230028",
    "sg:postcode":"40125",
    "sg:province":"Bologna",
    "sg:tags":[
        "medici"
    ],
    "wof:name":"Pedrini Oreste",
    "wof:placetype":"venue"
},
  "geometry": {"coordinates":[11.3514690399,44.4917297363],"type":"Point"}
}