{
  "type": "Feature",
  "properties": {
    "addr:full":"97100 Ragusa Ragusa Ragusa 97100",
    "addr:postcode":"97100;97100",
    "iso:country":"IT",
    "sg:address":"97100 Ragusa",
    "sg:city":"Ragusa",
    "sg:orig_category":"Dolciumi E Gelati. Condimenti, Spezie, Infusi E Caffe'",
    "sg:phone":"+39 0932 667420",
    "sg:postcode":"97100",
    "sg:province":"Ragusa",
    "wof:name":"S.f.i.r. Societa' Fondiaria Industriale Romagnola (s.p.a.)",
    "wof:placetype":"venue"
},
  "geometry": {"coordinates":[14.674679,36.882305],"type":"Point"}
}