{
  "type": "Feature",
  "properties": {
    "iso:country":"IT",
    "sg:address":"16, Via De' Berenzani 26100 Cremona",
    "sg:city":"Cremona",
    "sg:classifiers":[
        {
            "category":"Manufacturing",
            "subcategory":"Food",
            "type":"Manufacturing & Wholesale Goods"
        }
    ],
    "sg:phone":"+39 0372 471504",
    "sg:postcode":"26100",
    "sg:province":"Cremona",
    "sg:tags":[
        "equipment",
        "processing",
        "-",
        "machinery"
    ],
    "wof:name":"Scom Inox Di Martini Enrico E Marco (s.n.c.)",
    "wof:placetype":"venue"
},
  "geometry": {"coordinates":[9.98325634,45.1585159302],"type":"Point"}
}