{
  "type": "Feature",
  "properties": {
    "iso:country":"IT",
    "sg:address":"20124 Milano",
    "sg:city":"Milano",
    "sg:orig_category":"Apparecchiature Ed Attrezzature Meccaniche. Forniture E Materiali Per Imballaggio E Confezionamento. Apparecchiature E Sistemi Per Imballaggio E Confezionamento",
    "sg:phone":"+39 02 683964",
    "sg:postcode":"20124",
    "sg:province":"Milano",
    "wof:name":"Cefola Rosina E Grandini Fortunato",
    "wof:placetype":"venue"
},
  "geometry": {"coordinates":[9.191339,45.485649],"type":"Point"}
}