{
  "type": "Feature",
  "properties": {
    "addr:full":"13, Via Stoppani 23875 Osnago Osnago Lecco 23875",
    "addr:postcode":"23875;23875",
    "addr:street":"Via Stoppani",
    "iso:country":"IT",
    "sg:address":"13, Via Stoppani 23875 Osnago",
    "sg:city":"Osnago",
    "sg:classifiers":[
        {
            "category":"Shopping",
            "type":"Retail Goods"
        }
    ],
    "sg:phone":"+39 390 395 8445",
    "sg:postcode":"23875",
    "sg:province":"Lecco",
    "sg:tags":[
        "finished",
        "-",
        "metallic"
    ],
    "wof:name":"Larga (s.p.a.)",
    "wof:placetype":"venue"
},
  "geometry": {"coordinates":[9.3463001251,45.6811828613],"type":"Point"}
}