{
  "type": "Feature",
  "properties": {
    "iso:country":"IT",
    "sg:address":"50, Via Provinciale 23846 Garbagnate Monastero",
    "sg:city":"Garbagnate Monastero",
    "sg:classifiers":[
        {
            "category":"Manufacturing",
            "subcategory":"Rubber & Plastics",
            "type":"Manufacturing & Wholesale Goods"
        }
    ],
    "sg:phone":"+39 39031853440",
    "sg:postcode":"23846",
    "sg:province":"Lecco",
    "wof:name":"Mauri S.p.a.",
    "wof:placetype":"venue"
},
  "geometry": {"coordinates":[9.3383226395,45.7655448914],"type":"Point"}
}