{
  "type": "Feature",
  "properties": {
    "addr:full":"70123 Bari Bari Bari 70123",
    "addr:postcode":"70123;70123",
    "iso:country":"IT",
    "sg:address":"70123 Bari",
    "sg:city":"Bari",
    "sg:orig_category":"Pubblica Amministrazione",
    "sg:phone":"+39 080 585 7611",
    "sg:postcode":"70123",
    "sg:province":"Bari",
    "wof:name":"Polizia Di Stato",
    "wof:placetype":"venue"
},
  "geometry": {"coordinates":[16.8355369568,41.1224975586],"type":"Point"}
}