{
  "type": "Feature",
  "properties": {
    "iso:country":"IT",
    "sg:address":"54100 Massa",
    "sg:city":"Massa",
    "sg:orig_category":"Abbigliamento Esterno, Maglierie E Pelliccerie. Sport - Articoli E Forniture",
    "sg:phone":"+39 0585 255386",
    "sg:postcode":"54100",
    "sg:province":"Massa-Carrara",
    "sg:website":"http://www.quiksilver.com",
    "wof:name":"Haapiti Srl",
    "wof:placetype":"venue"
},
  "geometry": {"coordinates":[10.10463,44.023632],"type":"Point"}
}