{
  "type": "Feature",
  "properties": {
    "iso:country":"IT",
    "sg:address":"50015 Bagno A Ripoli",
    "sg:orig_category":"Frigotecnica, Apparecchiature E Servizi",
    "sg:phone":"+39 055 26351",
    "sg:province":"FI",
    "sg:website":"http://www.mazzanti-srl.it",
    "wof:name":"Mazzanti Srl",
    "wof:placetype":"venue"
},
  "geometry": {"coordinates":[11.2798519135,43.7365722656],"type":"Point"}
}