{
  "type": "Feature",
  "properties": {
    "iso:country":"IT",
    "sg:address":"Km. 22, Str. St. 175 75024 Montescaglioso",
    "sg:city":"Montescaglioso",
    "sg:classifiers":[
        {
            "category":"Food & Beverages",
            "subcategory":"Groceries & Convenience Stores",
            "type":"Retail Goods"
        }
    ],
    "sg:phone":"+39 0835 207902",
    "sg:postcode":"75024",
    "sg:province":"Matera",
    "sg:tags":[
        "product",
        "related"
    ],
    "sg:website":"http://www.frantoiovenezia.com",
    "wof:name":"Oleificio Venezia Srl",
    "wof:placetype":"venue"
},
  "geometry": {"coordinates":[16.606086731,40.6686515808],"type":"Point"}
}