{
  "type": "Feature",
  "properties": {
    "iso:country":"IT",
    "sg:address":"112, Via Marzabotto 30010 Campagna Lupia",
    "sg:city":"Campagna Lupia",
    "sg:classifiers":[
        {
            "category":"Shopping",
            "subcategory":"Clothing, Apparel, & Fashions",
            "type":"Retail Goods"
        }
    ],
    "sg:phone":"+39 041 518 5088",
    "sg:postcode":"30010",
    "sg:province":"Venezia",
    "sg:tags":[
        "clothes"
    ],
    "wof:name":"Europell 2 S.r.l.",
    "wof:placetype":"venue"
},
  "geometry": {"coordinates":[12.127475,45.385632],"type":"Point"}
}