{
  "type": "Feature",
  "properties": {
    "addr:full":"90, Ctr. Piana Di Larino 86035 Larino Larino Campobasso 86035",
    "addr:housenumber":"90",
    "addr:postcode":"86035;86035",
    "addr:street":"Ctr. Piana Di Larino",
    "iso:country":"IT",
    "sg:address":"90, Ctr. Piana Di Larino 86035 Larino",
    "sg:city":"Larino",
    "sg:classifiers":[
        {
            "category":"Manufacturing",
            "subcategory":"Metals",
            "type":"Manufacturing & Wholesale Goods"
        }
    ],
    "sg:phone":"+39 0874 820132",
    "sg:postcode":"86035",
    "sg:province":"Campobasso",
    "sg:tags":[
        "metallurgy",
        "metalworking"
    ],
    "sg:website":"http://www.dimfix.com",
    "wof:name":"Dimfix Srl",
    "wof:placetype":"venue"
},
  "geometry": {"coordinates":[14.6647987366,41.5600852966],"type":"Point"}
}