{
  "type": "Feature",
  "properties": {
    "iso:country":"IT",
    "sg:address":"Via Ticino 20098 San Giuliano Milanese",
    "sg:city":"San Giuliano Milanese",
    "sg:classifiers":[
        {
            "category":"Banks & Credit Unions",
            "subcategory":"Investment Brokerage",
            "type":"Services"
        }
    ],
    "sg:phone":"+39 39029880146",
    "sg:postcode":"20098",
    "sg:province":"Milano",
    "sg:tags":[
        "-",
        "transport",
        "related"
    ],
    "wof:name":"Im.ex. Srl",
    "wof:placetype":"venue"
},
  "geometry": {"coordinates":[9.257214,45.384968],"type":"Point"}
}