{
  "type": "Feature",
  "properties": {
    "addr:full":"63100 Ascoli Piceno Ascoli Piceno Ascoli Piceno 63100",
    "addr:postcode":"63100;63100",
    "iso:country":"IT",
    "sg:address":"63100 Ascoli Piceno",
    "sg:city":"Ascoli Piceno",
    "sg:orig_category":"Pubblica Amministrazione",
    "sg:phone":"+39 0736 255559",
    "sg:postcode":"63100",
    "sg:province":"Ascoli Piceno",
    "wof:name":"Provincia Di Ascoli Piceno",
    "wof:placetype":"venue"
},
  "geometry": {"coordinates":[13.5668306351,42.847530365],"type":"Point"}
}