{
  "type": "Feature",
  "properties": {
    "iso:country":"IT",
    "sg:address":"Via E. Berlinguer 33/37 47034 Forlimpopoli",
    "sg:city":"Forlimpopoli",
    "sg:classifiers":[
        {
            "category":"Autos & Motor Vehicles",
            "subcategory":"Auto Supplies",
            "type":"Retail Goods"
        }
    ],
    "sg:phone":"+39 0543 744999",
    "sg:postcode":"47034",
    "sg:province":"Forl\u00ec-Cesena",
    "sg:tags":[
        "automobile",
        "accessory"
    ],
    "sg:website":"www.spinellisrl.com",
    "wof:name":"Spinelli Srl",
    "wof:placetype":"venue"
},
  "geometry": {"coordinates":[12.116185,44.193489],"type":"Point"}
}