{
  "type": "Feature",
  "properties": {
    "iso:country":"IT",
    "sg:address":"25136 Brescia",
    "sg:city":"Brescia",
    "sg:orig_category":"Prodotti Alimentari",
    "sg:phone":"+39 030 200 0794",
    "sg:postcode":"25136",
    "sg:province":"Brescia",
    "wof:name":"Valledoro S.p.a.",
    "wof:placetype":"venue"
},
  "geometry": {"coordinates":[10.2257175446,45.5767936707],"type":"Point"}
}