{
  "type": "Feature",
  "properties": {
    "addr:full":"00065 Fiano Romano Fiano Romano Roma 00065",
    "addr:postcode":"00065;roma 00065",
    "addr:street":"Romano",
    "iso:country":"IT",
    "sg:address":"00065 Fiano Romano",
    "sg:city":"Fiano Romano",
    "sg:classifiers":[
        {
            "category":"Health Services",
            "subcategory":"Health Practitioner",
            "type":"Services"
        }
    ],
    "sg:phone":"+39 0765 482023",
    "sg:postcode":"00065",
    "sg:province":"Roma",
    "sg:tags":[
        "medici"
    ],
    "wof:name":"Cinque Cm Sas Di Capobianchi M. & C.",
    "wof:placetype":"venue"
},
  "geometry": {"coordinates":[12.588721,42.166096],"type":"Point"}
}