{
  "type": "Feature",
  "properties": {
    "iso:country":"IT",
    "sg:address":"80073 Capri",
    "sg:city":"Capri",
    "sg:orig_category":"Artigianato Tipico",
    "sg:phone":"+39 081 837 0946",
    "sg:postcode":"80073",
    "sg:province":"Napoli",
    "wof:name":"Schettino Lidia",
    "wof:placetype":"venue"
},
  "geometry": {"coordinates":[14.250504,40.902439],"type":"Point"}
}