{
  "type": "Feature",
  "properties": {
    "addr:full":"18038 Sanremo Imperia 18038",
    "addr:postcode":"18038;18038",
    "iso:country":"IT",
    "sg:address":"18038 Sanremo",
    "sg:orig_category":"Serramenti Ed Infissi",
    "sg:phone":"+39 0184 507822",
    "sg:postcode":"18038",
    "sg:province":"Imperia",
    "wof:name":"Ceramiche Spada",
    "wof:placetype":"venue"
},
  "geometry": {"coordinates":[7.7742700577,43.841178894],"type":"Point"}
}