{
  "type": "Feature",
  "properties": {
    "addr:full":"09048 Sinnai Sinnai Cagliari 09048",
    "addr:postcode":"09048;09048",
    "iso:country":"IT",
    "sg:address":"09048 Sinnai",
    "sg:city":"Sinnai",
    "sg:orig_category":"Materiali E Componenti Elettrotecnici",
    "sg:phone":"+39 070 761037",
    "sg:postcode":"09048",
    "sg:province":"Cagliari",
    "wof:name":"Promael",
    "wof:placetype":"venue"
},
  "geometry": {"coordinates":[9.204537,39.305313],"type":"Point"}
}