{
  "type": "Feature",
  "properties": {
    "addr:full":"Piazzale Donatello 2 50132 Firenze Firenze Firenze 50132",
    "addr:housenumber":"2",
    "addr:postcode":"50132;50132",
    "addr:street":"Piazzale Donatello",
    "iso:country":"IT",
    "sg:address":"Piazzale Donatello 2 50132 Firenze",
    "sg:city":"Firenze",
    "sg:orig_category":"Photogrammetric Equipment",
    "sg:phone":"+39 055 246 9026",
    "sg:postcode":"50132",
    "sg:province":"Firenze",
    "sg:website":"www.siscam.it",
    "wof:name":"Siscam Srl",
    "wof:placetype":"venue"
},
  "geometry": {"coordinates":[11.2685165405,43.7779006958],"type":"Point"}
}