{
  "type": "Feature",
  "properties": {
    "iso:country":"IT",
    "sg:address":"37040 Zimella",
    "sg:city":"Zimella",
    "sg:orig_category":"Elettrotecnica",
    "sg:phone":"+39 0442 84587",
    "sg:postcode":"37040",
    "sg:province":"Verona",
    "wof:name":"Bonato Vittorina",
    "wof:placetype":"venue"
},
  "geometry": {"coordinates":[11.38587,45.338966],"type":"Point"}
}