{
  "type": "Feature",
  "properties": {
    "iso:country":"IT",
    "sg:address":"91026 Mazara Del Vallo",
    "sg:city":"Mazara del Vallo",
    "sg:orig_category":"Agenzie Viaggi E Turismo",
    "sg:phone":"+39 0923 944549",
    "sg:postcode":"91026",
    "sg:province":"Trapani",
    "wof:name":"Ser.tur. Srl",
    "wof:placetype":"venue"
},
  "geometry": {"coordinates":[12.644587,37.738953],"type":"Point"}
}