{
  "type": "Feature",
  "properties": {
    "iso:country":"IT",
    "sg:address":"50019 Sesto Fiorentino",
    "sg:city":"Sesto Fiorentino",
    "sg:orig_category":"Forniture Per Abbigliamento E Pelletterie. Forniture Per Attivita' Commerciali Ed Artigianali",
    "sg:phone":"+39 055 340777",
    "sg:postcode":"50019",
    "sg:province":"Firenze",
    "sg:website":"http://www.anteprimaflorence.it",
    "wof:name":"Anteprima Sas",
    "wof:placetype":"venue"
},
  "geometry": {"coordinates":[11.1782627106,43.811504364],"type":"Point"}
}