{
  "type": "Feature",
  "properties": {
    "addr:full":"20129 Milano Milano Milano 20129",
    "addr:postcode":"20129;20129",
    "iso:country":"IT",
    "sg:address":"20129 Milano",
    "sg:city":"Milano",
    "sg:orig_category":"Ospedali E Servizi Sanitari. Servizi Sociali",
    "sg:phone":"+39 02 2614 5609",
    "sg:postcode":"20129",
    "sg:province":"Milano",
    "wof:name":"Associazione Nazionale Difesa Della Fanciullezza Abbandonata E.m.",
    "wof:placetype":"venue"
},
  "geometry": {"coordinates":[9.209865,45.472294],"type":"Point"}
}