{
  "type": "Feature",
  "properties": {
    "addr:full":"Via Aurelia Nord, 75/77/79 58100 Grosseto Grosseto Grosseto 58100",
    "addr:housenumber":"75 / 77 / 79",
    "addr:postcode":"58100;58100",
    "addr:street":"Via Aurelia Nord",
    "iso:country":"IT",
    "sg:address":"Via Aurelia Nord, 75/77/79 58100 Grosseto",
    "sg:city":"Grosseto",
    "sg:classifiers":[
        {
            "category":"Wholesale",
            "subcategory":"Farm Supplies",
            "type":"Manufacturing & Wholesale Goods"
        }
    ],
    "sg:phone":"+39 0564 454564",
    "sg:postcode":"58100",
    "sg:province":"Grosseto",
    "sg:tags":[
        "agricultural",
        "part",
        "spare",
        "machinery",
        "accessory"
    ],
    "sg:website":"www.verma2000.it",
    "wof:name":"Ve.r.ma Sas",
    "wof:placetype":"venue"
},
  "geometry": {"coordinates":[11.112782,42.762859],"type":"Point"}
}