{
  "type": "Feature",
  "properties": {
    "iso:country":"IT",
    "sg:address":"12051 Alba",
    "sg:city":"Alba",
    "sg:orig_category":"Abbigliamento Alta Moda E Stilisti - Boutiques",
    "sg:phone":"+39 0173 441812",
    "sg:postcode":"12051",
    "sg:province":"Cuneo",
    "wof:name":"Caravan Di Barbero Lucia & C. Snc",
    "wof:placetype":"venue"
},
  "geometry": {"coordinates":[8.0247,44.699448],"type":"Point"}
}