{
  "type": "Feature",
  "properties": {
    "iso:country":"IT",
    "sg:address":"34132 Trieste",
    "sg:city":"Trieste",
    "sg:orig_category":"Banche E Servizi Finanziari",
    "sg:phone":"+39 040 364439",
    "sg:postcode":"34132",
    "sg:province":"Trieste",
    "wof:name":"Sussich Francesca",
    "wof:placetype":"venue"
},
  "geometry": {"coordinates":[13.77317,45.656418],"type":"Point"}
}