{
  "type": "Feature",
  "properties": {
    "iso:country":"IT",
    "sg:address":"20020 Arese",
    "sg:city":"Arese",
    "sg:classifiers":[
        {
            "category":"Health Services",
            "subcategory":"Health Practitioner",
            "type":"Services"
        }
    ],
    "sg:phone":"+39 02 938 5239",
    "sg:postcode":"20020",
    "sg:province":"Milano",
    "sg:tags":[
        "medici"
    ],
    "wof:name":"Martini Renato",
    "wof:placetype":"venue"
},
  "geometry": {"coordinates":[9.078381,45.550171],"type":"Point"}
}