{
  "type": "Feature",
  "properties": {
    "addr:full":"Loc Asi Sud 81025 Marcianise Marcianise Caserta 81025",
    "addr:postcode":"81025;81025",
    "addr:street":"Loc Asi Sud",
    "iso:country":"IT",
    "sg:address":"Loc Asi Sud 81025 Marcianise",
    "sg:city":"Marcianise",
    "sg:classifiers":[
        {
            "category":"Structure",
            "subcategory":"Bridge",
            "type":"Public Place"
        }
    ],
    "sg:phone":"+39 0823 513189",
    "sg:postcode":"81025",
    "sg:province":"Caserta",
    "sg:tags":[
        "item",
        "silver"
    ],
    "wof:name":"Fusco Argenti S.r.l.",
    "wof:placetype":"venue"
},
  "geometry": {"coordinates":[14.332194,41.075417],"type":"Point"}
}