{
  "type": "Feature",
  "properties": {
    "iso:country":"IT",
    "sg:address":"5, Via Dei Guasti 20020 Misinto",
    "sg:city":"Misinto",
    "sg:classifiers":[
        {
            "category":"Shopping",
            "subcategory":"Stationery & Office Supplies",
            "type":"Retail Goods"
        }
    ],
    "sg:phone":"+39 02 9632 9503",
    "sg:postcode":"20020",
    "sg:province":"Milano",
    "sg:tags":[
        "professional"
    ],
    "wof:name":"Arredi Spd (s.r.l.)",
    "wof:placetype":"venue"
},
  "geometry": {"coordinates":[9.0882205963,45.6604728699],"type":"Point"}
}