{
  "type": "Feature",
  "properties": {
    "addr:full":"36100 Vicenza Vicenza Vicenza 36100",
    "addr:postcode":"36100;36100",
    "iso:country":"IT",
    "sg:address":"36100 Vicenza",
    "sg:city":"Vicenza",
    "sg:orig_category":"Prodotti Chimici Di Base",
    "sg:phone":"+39 0444 565500",
    "sg:postcode":"36100",
    "sg:province":"Vicenza",
    "sg:website":"http://www.adtech.it",
    "wof:name":"Ad.tech. Srl",
    "wof:placetype":"venue"
},
  "geometry": {"coordinates":[11.4593887329,45.6443901062],"type":"Point"}
}