{
  "type": "Feature",
  "properties": {
    "addr:full":"18, Viale Delle Industrie 20090 Settala Settala Milano 20090",
    "addr:housenumber":"18",
    "addr:postcode":"20090;20090",
    "addr:street":"Viale Delle Industrie",
    "iso:country":"IT",
    "sg:address":"18, Viale Delle Industrie 20090 Settala",
    "sg:city":"Settala",
    "sg:classifiers":[
        {
            "category":"Wholesale",
            "subcategory":"Drugs",
            "type":"Manufacturing & Wholesale Goods"
        }
    ],
    "sg:phone":"+39 02 9537 9236",
    "sg:postcode":"20090",
    "sg:province":"Milano",
    "sg:tags":[
        "chemical",
        "pharmaceutical"
    ],
    "wof:name":"Settala Gas (s.p.a.)",
    "wof:placetype":"venue"
},
  "geometry": {"coordinates":[9.3811531067,45.4538726807],"type":"Point"}
}