{
  "type": "Feature",
  "properties": {
    "iso:country":"IT",
    "sg:address":"20031 Cesano Maderno",
    "sg:city":"Cesano Maderno",
    "sg:orig_category":"Servizi E Lavori Per Arredamento E Industria Del Legno",
    "sg:phone":"+39 036 250 6631",
    "sg:postcode":"20031",
    "sg:province":"Milano",
    "wof:name":"Frigerio Angelo (s.a.s.)",
    "wof:placetype":"venue"
},
  "geometry": {"coordinates":[9.160772,45.635391],"type":"Point"}
}