{
  "type": "Feature",
  "properties": {
    "iso:country":"IT",
    "sg:address":"00185 Roma",
    "sg:city":"Roma",
    "sg:orig_category":"Hobbistica",
    "sg:phone":"+39 06 488 5007",
    "sg:postcode":"00185",
    "sg:province":"Roma",
    "wof:name":"Numismatica Internazionale Srl",
    "wof:placetype":"venue"
},
  "geometry": {"coordinates":[12.500104,41.901051],"type":"Point"}
}