{
  "type": "Feature",
  "properties": {
    "addr:full":"80131 Napoli Napoli Napoli 80131",
    "addr:housenumber":"80131",
    "addr:postcode":"80131",
    "iso:country":"IT",
    "sg:address":"80131 Napoli",
    "sg:city":"Napoli",
    "sg:orig_category":"Fiori E Piante Artificiali - Produzione E Ingrosso",
    "sg:phone":"+39 081 545 5330",
    "sg:postcode":"80131",
    "sg:province":"Napoli",
    "wof:name":"Vela Imp.ex. Srl",
    "wof:placetype":"venue"
},
  "geometry": {"coordinates":[14.2266340256,40.8655853271],"type":"Point"}
}