{
  "type": "Feature",
  "properties": {
    "iso:country":"IT",
    "sg:address":"18, Via Galilei Galileo 25068 Sarezzo",
    "sg:city":"Sarezzo",
    "sg:classifiers":[
        {
            "category":"Manufacturing",
            "subcategory":"Tools & Machinery",
            "type":"Manufacturing & Wholesale Goods"
        }
    ],
    "sg:phone":"+39 39030800890",
    "sg:postcode":"25068",
    "sg:province":"Brescia",
    "sg:tags":[
        "environment",
        "equipment",
        "-"
    ],
    "wof:name":"Inox - Dep Di Perani Aldo Andreino & C. (s.n.c.)",
    "wof:placetype":"venue"
},
  "geometry": {"coordinates":[10.222958,45.539829],"type":"Point"}
}