{
  "type": "Feature",
  "properties": {
    "iso:country":"IT",
    "sg:address":"52, Via Molini 36055 Nove",
    "sg:city":"Nove",
    "sg:classifiers":[
        {
            "category":"Sports & Exercise",
            "subcategory":"Playing Field",
            "type":"Entertainment"
        }
    ],
    "sg:phone":"+39 0424 590098",
    "sg:postcode":"36055",
    "sg:province":"Vicenza",
    "sg:tags":[
        "game"
    ],
    "wof:name":"Ceramiche Olimpica Di Nove Di Bau' Virginio & C. (s.n.c.)",
    "wof:placetype":"venue"
},
  "geometry": {"coordinates":[11.6835,45.729839],"type":"Point"}
}