{
  "type": "Feature",
  "properties": {
    "iso:country":"IT",
    "sg:address":"25080 Padenghe Sul Garda",
    "sg:city":"Padenghe sul Garda",
    "sg:orig_category":"Servizi Ausiliari Dei Mezzi Di Trasporto. Servizi Ausiliari Per Il Trasporto. Acqua, Luce, Gas E Societa' Di Esercizio Pubblico",
    "sg:phone":"+39 030 990 7164",
    "sg:postcode":"25080",
    "sg:province":"Brescia",
    "wof:name":"West Garda Marina (s.r.l.)",
    "wof:placetype":"venue"
},
  "geometry": {"coordinates":[10.510211,45.495918],"type":"Point"}
}