{
  "type": "Feature",
  "properties": {
    "iso:country":"IT",
    "sg:address":"98030 Castel Mola",
    "sg:orig_category":"Alberghi E Strutture Extra Alberghiere",
    "sg:phone":"+39 0942 28027",
    "sg:postcode":"98030",
    "sg:province":"Messina",
    "wof:name":"Elettra Turismo Snc",
    "wof:placetype":"venue"
},
  "geometry": {"coordinates":[15.555523,38.192333],"type":"Point"}
}