{
  "type": "Feature",
  "properties": {
    "iso:country":"IT",
    "sg:address":"90145 Palermo",
    "sg:city":"Palermo",
    "sg:orig_category":"Laminati Plastici - Commercio",
    "sg:phone":"+39 091 681 2362",
    "sg:postcode":"90145",
    "sg:province":"Palermo",
    "wof:name":"Mignosi Vittorio & C. Snc",
    "wof:placetype":"venue"
},
  "geometry": {"coordinates":[13.337765,38.122028],"type":"Point"}
}