{
  "type": "Feature",
  "properties": {
    "iso:country":"IT",
    "sg:address":"06123 Perugia",
    "sg:city":"Perugia",
    "sg:orig_category":"Notai - Studi",
    "sg:phone":"+39 075 572 2319",
    "sg:postcode":"06123",
    "sg:province":"Perugia",
    "wof:name":"Duranti Dott. Filippo",
    "wof:placetype":"venue"
},
  "geometry": {"coordinates":[12.388584,43.111713],"type":"Point"}
}