{
  "type": "Feature",
  "properties": {
    "iso:country":"IT",
    "sg:address":"Via N. Tommaseo 16 20058 Villasanta",
    "sg:city":"Villasanta",
    "sg:classifiers":[
        {
            "category":"Manufacturing",
            "subcategory":"Motor Vehicles & Parts",
            "type":"Manufacturing & Wholesale Goods"
        }
    ],
    "sg:phone":"+39 039 303641",
    "sg:postcode":"20058",
    "sg:province":"Milano",
    "sg:tags":[
        "press",
        "embossing"
    ],
    "sg:website":"www.imvgalli.it",
    "wof:name":"I.m.v. Galli Srl",
    "wof:placetype":"venue"
},
  "geometry": {"coordinates":[9.188141,45.463688],"type":"Point"}
}