{
  "type": "Feature",
  "properties": {
    "iso:country":"IT",
    "sg:address":"27/r, Via Piombelli Sergio 16159 Genova",
    "sg:city":"Genova",
    "sg:classifiers":[
        {
            "category":"Communications",
            "subcategory":"Television Station",
            "type":"Services"
        }
    ],
    "sg:phone":"+39 010 469 5187",
    "sg:postcode":"16159",
    "sg:province":"Genova",
    "sg:tags":[
        "electronic",
        "publishing"
    ],
    "wof:name":"Plasticard Sas",
    "wof:placetype":"venue"
},
  "geometry": {"coordinates":[8.933989,44.407063],"type":"Point"}
}