{
  "type": "Feature",
  "properties": {
    "iso:country":"IT",
    "sg:address":"83017 Rotondi",
    "sg:city":"Rotondi",
    "sg:classifiers":[
        {
            "category":"Manufacturing",
            "subcategory":"Food",
            "type":"Manufacturing & Wholesale Goods"
        }
    ],
    "sg:phone":"+39 0824 831738",
    "sg:postcode":"83017",
    "sg:province":"Avellino",
    "sg:tags":[
        "product"
    ],
    "sg:website":"http://www.dolciariamaja.it",
    "wof:name":"Maja Jpd Srl",
    "wof:placetype":"venue"
},
  "geometry": {"coordinates":[14.5956001282,41.0366706848],"type":"Point"}
}