{
  "type": "Feature",
  "properties": {
    "iso:country":"IT",
    "sg:address":"Contrada Marzone 70043 Monopoli",
    "sg:city":"Monopoli",
    "sg:classifiers":[
        {
            "category":"Autos & Motor Vehicles",
            "subcategory":"Automobile Sales",
            "type":"Retail Goods"
        }
    ],
    "sg:phone":"+39 39080802182",
    "sg:postcode":"70043",
    "sg:province":"Bari",
    "sg:tags":[
        "industrial"
    ],
    "wof:name":"Isar (s.p.a.)",
    "wof:placetype":"venue"
},
  "geometry": {"coordinates":[17.261835,40.9701],"type":"Point"}
}