{
  "type": "Feature",
  "properties": {
    "addr:full":"Via Val Di Setta; Capalle; 50100",
    "addr:postcode":"50100",
    "addr:street":"Via Val Di Setta Capalle",
    "iso:country":"IT",
    "sg:address":"Via Val Di Setta; Capalle; 50100",
    "sg:classifiers":[
        {
            "category":"Banks & Credit Unions",
            "subcategory":"Bank",
            "type":"Services"
        }
    ],
    "sg:phone":"+39 055 895 1371",
    "wof:name":"Cassa Di Risparmio Di Firenze Spa",
    "wof:placetype":"venue"
},
  "geometry": {"coordinates":[11.120959,43.815731],"type":"Point"}
}