{
  "type": "Feature",
  "properties": {
    "addr:full":"66023 Francavilla Al Mare Francavilla al Mare Chieti 66023",
    "addr:postcode":"66023;66023",
    "iso:country":"IT",
    "sg:address":"66023 Francavilla Al Mare",
    "sg:city":"Francavilla al Mare",
    "sg:orig_category":"Prodotti Chimici Secondari. Macchine E Forniture Per Ecologia E Smaltimento Rifiuti. Forniture Per Attivita' Commerciali Ed Artigianali",
    "sg:phone":"+39 085 491 7078",
    "sg:postcode":"66023",
    "sg:province":"Chieti",
    "wof:name":"New Chimmer Srl",
    "wof:placetype":"venue"
},
  "geometry": {"coordinates":[14.2675762177,42.4035110474],"type":"Point"}
}