{
  "type": "Feature",
  "properties": {
    "addr:full":"50018 Casellina Casellina Firenze 50018",
    "addr:postcode":"50018;50018",
    "iso:country":"IT",
    "sg:address":"50018 Casellina",
    "sg:city":"Casellina",
    "sg:orig_category":"Trattamenti Termici E Superficiali Metalli, Galvanotecnica",
    "sg:phone":"+39 055 754779",
    "sg:postcode":"50018",
    "sg:province":"Firenze",
    "wof:name":"Centro Zincatura S.a.s.",
    "wof:placetype":"venue"
},
  "geometry": {"coordinates":[11.165538,43.769669],"type":"Point"}
}