{
  "type": "Feature",
  "properties": {
    "iso:country":"IT",
    "sg:address":"28068 Romentino",
    "sg:city":"Romentino",
    "sg:classifiers":[
        {
            "category":"Wholesale",
            "subcategory":"Chemicals & Plastics",
            "type":"Manufacturing & Wholesale Goods"
        }
    ],
    "sg:phone":"+39 0321 869200",
    "sg:postcode":"28068",
    "sg:province":"Novara",
    "sg:tags":[
        "article",
        "product",
        "plastics"
    ],
    "sg:website":"http://gigimolina.com",
    "wof:name":"Gigi Molina Brevetti Plastici Spa",
    "wof:placetype":"venue"
},
  "geometry": {"coordinates":[8.6186714172,45.4450836182],"type":"Point"}
}