{
  "type": "Feature",
  "properties": {
    "iso:country":"IT",
    "sg:address":"59100 Prato",
    "sg:city":"Prato",
    "sg:classifiers":[
        {
            "category":"Shopping",
            "subcategory":"Clothing, Apparel, & Fashions",
            "type":"Retail Goods"
        }
    ],
    "sg:phone":"+39 0574 583838",
    "sg:postcode":"59100",
    "sg:province":"Prato",
    "sg:tags":[
        "knitwear",
        "furs",
        "clothing"
    ],
    "wof:name":"Perri Tullio",
    "wof:placetype":"venue"
},
  "geometry": {"coordinates":[11.106703,43.860168],"type":"Point"}
}