{
  "type": "Feature",
  "properties": {
    "addr:full":"7, Via Traiano Marco Ulpio 20149 Milano Milano Milano 20149",
    "addr:postcode":"20149;20149",
    "addr:street":"Via Traiano Marco Ulpio",
    "iso:country":"IT",
    "sg:address":"7, Via Traiano Marco Ulpio 20149 Milano",
    "sg:city":"Milano",
    "sg:classifiers":[
        {
            "category":"Professional",
            "subcategory":"Business Services",
            "type":"Services"
        }
    ],
    "sg:phone":"+39 39023456021",
    "sg:postcode":"20149",
    "sg:province":"Milano",
    "sg:tags":[
        "advice"
    ],
    "wof:name":"Istituo Italiano Dei Plastici Srl",
    "wof:placetype":"venue"
},
  "geometry": {"coordinates":[9.152211,45.484913],"type":"Point"}
}