{
  "type": "Feature",
  "properties": {
    "iso:country":"IT",
    "sg:address":"58100 Grosseto",
    "sg:city":"Grosseto",
    "sg:orig_category":"Autofficine E Centri Assistenza",
    "sg:phone":"+39 0564 457374",
    "sg:postcode":"58100",
    "sg:province":"Grosseto",
    "sg:website":"http://www.noleggiocamper.it",
    "wof:name":"Demi & Demi Srl",
    "wof:placetype":"venue"
},
  "geometry": {"coordinates":[11.093631,42.789543],"type":"Point"}
}