{
  "type": "Feature",
  "properties": {
    "iso:country":"IT",
    "sg:address":"Via Principe Pignatelli 13 65010 Vallemare Di Cepagatti",
    "sg:classifiers":[
        {
            "category":"Home & Garden",
            "subcategory":"Building Materials",
            "type":"Retail Goods"
        }
    ],
    "sg:phone":"+39 085 977 1482",
    "sg:postcode":"65010",
    "sg:province":"Pescara",
    "sg:tags":[
        "central",
        "heating",
        "boiler"
    ],
    "sg:website":"www.fontecal.it",
    "wof:name":"Fontecal Spa",
    "wof:placetype":"venue"
},
  "geometry": {"coordinates":[14.214094,42.464825],"type":"Point"}
}