{
  "type": "Feature",
  "properties": {
    "iso:country":"IT",
    "sg:address":"78, Via Golfarelli Innocenzo 47100 Forli'",
    "sg:classifiers":[
        {
            "category":"Manufacturing",
            "subcategory":"Textiles",
            "type":"Manufacturing & Wholesale Goods"
        }
    ],
    "sg:phone":"+39 0543 723361",
    "sg:postcode":"47100",
    "sg:province":"Forl\u00ec-Cesena",
    "sg:tags":[
        "leather",
        "raw",
        "material",
        "-"
    ],
    "wof:name":"Bizzarro S.r.l.",
    "wof:placetype":"venue"
},
  "geometry": {"coordinates":[12.072315,44.222469],"type":"Point"}
}