{
  "type": "Feature",
  "properties": {
    "iso:country":"IT",
    "sg:address":"80121 Napoli",
    "sg:city":"Napoli",
    "sg:orig_category":"Scuole E Servizi Scolastici. Servizi Per Lo Sport E Il Tempo Libero",
    "sg:phone":"+39 081 764 4538",
    "sg:postcode":"80121",
    "sg:province":"Napoli",
    "wof:name":"Nautica Scuola G.bove",
    "wof:placetype":"venue"
},
  "geometry": {"coordinates":[14.171126,40.859722],"type":"Point"}
}