{
  "type": "Feature",
  "properties": {
    "iso:country":"IT",
    "sg:address":"90142 Palermo",
    "sg:city":"Palermo",
    "sg:orig_category":"Agricoltura, Orticoltura E Floricoltura",
    "sg:phone":"+39 091 546784",
    "sg:postcode":"90142",
    "sg:province":"Palermo",
    "wof:name":"Sicari Roberto",
    "wof:placetype":"venue"
},
  "geometry": {"coordinates":[13.360011,38.139481],"type":"Point"}
}