{
  "type": "Feature",
  "properties": {
    "iso:country":"IT",
    "sg:address":"42021 Bibbiano",
    "sg:orig_category":"Impianti, Attrezzature E Forniture Sanitarie Ed Ospedaliere",
    "sg:phone":"+39 0522 875159",
    "sg:postcode":"42021",
    "sg:province":"Reggio Nell'Emilia",
    "wof:name":"Reverberi Srl",
    "wof:placetype":"venue"
},
  "geometry": {"coordinates":[10.465454,44.63623],"type":"Point"}
}