{
  "type": "Feature",
  "properties": {
    "iso:country":"IT",
    "sg:address":"06034 Foligno",
    "sg:city":"Foligno",
    "sg:orig_category":"Forniture Per Attivita' Industriali",
    "sg:phone":"+39 0742 32651",
    "sg:postcode":"06034",
    "sg:province":"Perugia",
    "wof:name":"Dolci Bernardo Srl",
    "wof:placetype":"venue"
},
  "geometry": {"coordinates":[12.7824773788,42.9773864746],"type":"Point"}
}