{
  "type": "Feature",
  "properties": {
    "addr:full":"26020 Palazzo Pignano Palazzo Pignano Cremona 26020",
    "addr:postcode":"26020;pignano;26020",
    "addr:street":"Cremona",
    "iso:country":"IT",
    "sg:address":"26020 Palazzo Pignano",
    "sg:city":"Palazzo Pignano",
    "sg:orig_category":"Elettrotecnica Industriale, Prodotti E Apparecchiature. Ricambi E Componenti Dei Mezzi Di Trasporto",
    "sg:phone":"+39 0373 90212",
    "sg:postcode":"26020",
    "sg:province":"Cremona",
    "wof:name":"Poletti Vincenzo",
    "wof:placetype":"venue"
},
  "geometry": {"coordinates":[9.566518,45.391651],"type":"Point"}
}