{
  "type": "Feature",
  "properties": {
    "iso:country":"IT",
    "sg:address":"16154 Genova",
    "sg:city":"Genova",
    "sg:orig_category":"Scuole E Servizi Scolastici. Ospedali E Servizi Sanitari",
    "sg:phone":"+39 010 600 1950",
    "sg:postcode":"16154",
    "sg:province":"Genova",
    "wof:name":"Azienda Usl 3 Genovese",
    "wof:placetype":"venue"
},
  "geometry": {"coordinates":[8.841789,44.437885],"type":"Point"}
}