{
  "type": "Feature",
  "properties": {
    "addr:full":"20032 Cormano Cormano Milano 20032",
    "addr:postcode":"20032;20032",
    "iso:country":"IT",
    "sg:address":"20032 Cormano",
    "sg:city":"Cormano",
    "sg:orig_category":"Lavorazioni Metalli, Stampaggio E Saldatura",
    "sg:phone":"+39 02 615 2047",
    "sg:postcode":"20032",
    "sg:province":"Milano",
    "wof:name":"Basilico Livio",
    "wof:placetype":"venue"
},
  "geometry": {"coordinates":[9.168343,45.543785],"type":"Point"}
}