{
  "type": "Feature",
  "properties": {
    "iso:country":"IT",
    "sg:address":"16019 Ronco Scrivia",
    "sg:city":"Ronco Scrivia",
    "sg:orig_category":"Servizi Ausiliari Dei Mezzi Di Trasporto. Servizi Ausiliari Per Il Trasporto. Acqua, Luce, Gas E Societa' Di Esercizio Pubblico",
    "sg:phone":"+39 010 965 7023",
    "sg:postcode":"16019",
    "sg:province":"Genova",
    "wof:name":"Autostrade Spa",
    "wof:placetype":"venue"
},
  "geometry": {"coordinates":[8.935574,44.603554],"type":"Point"}
}