{
  "type": "Feature",
  "properties": {
    "iso:country":"IT",
    "sg:address":"14, Via Del Trifoglio 30100 Venezia",
    "sg:classifiers":[
        {
            "category":"Professional",
            "subcategory":"Engineering",
            "type":"Services"
        }
    ],
    "sg:phone":"+39 39041935988",
    "sg:province":"VE",
    "sg:tags":[
        "machine",
        "-",
        "mechanical"
    ],
    "wof:name":"Officine Meccar (s.n.c.)",
    "wof:placetype":"venue"
},
  "geometry": {"coordinates":[12.214753,45.460426],"type":"Point"}
}