{
  "type": "Feature",
  "properties": {
    "iso:country":"IT",
    "sg:address":"Piazza Risorgimento, 31; Cellamare; 70010",
    "sg:city":"Cellamare",
    "sg:classifiers":[
        {
            "category":"Banks & Credit Unions",
            "subcategory":"Bank",
            "type":"Services"
        }
    ],
    "sg:phone":"+39 080 686009",
    "sg:postcode":"70010",
    "sg:province":"Bari",
    "wof:name":"Banca Popolare Di Bari",
    "wof:placetype":"venue"
},
  "geometry": {"coordinates":[16.929443,41.019131],"type":"Point"}
}