{
  "type": "Feature",
  "properties": {
    "addr:full":"Via Roma, 5/7; Pegognaga; 46020 Pegognaga Mantova 46020",
    "addr:housenumber":"5 / 7",
    "addr:postcode":"46020;46020",
    "addr:street":"Via Roma;Pegognaga",
    "iso:country":"IT",
    "sg:address":"Via Roma, 5/7; Pegognaga; 46020",
    "sg:city":"Pegognaga",
    "sg:classifiers":[
        {
            "category":"Banks & Credit Unions",
            "subcategory":"Bank",
            "type":"Services"
        }
    ],
    "sg:phone":"+39 0376 559718",
    "sg:postcode":"46020",
    "sg:province":"Mantova",
    "wof:name":"Banca Agricola Mantovana Scarl",
    "wof:placetype":"venue"
},
  "geometry": {"coordinates":[10.859345,44.996845],"type":"Point"}
}