{
  "type": "Feature",
  "properties": {
    "iso:country":"IT",
    "sg:address":"90100 Palermo",
    "sg:classifiers":[
        {
            "category":"Bars & Pubs",
            "subcategory":"Champagne Bar",
            "type":"Food & Drink"
        }
    ],
    "sg:phone":"+39 091 491413",
    "sg:province":"PA",
    "sg:tags":[
        "caffe'",
        "e"
    ],
    "wof:name":"Di Maria Domenico",
    "wof:placetype":"venue"
},
  "geometry": {"coordinates":[13.35845,38.121311],"type":"Point"}
}