{
  "type": "Feature",
  "properties": {
    "iso:country":"IT",
    "sg:address":"28801 Cossogno",
    "sg:city":"Cossogno",
    "sg:orig_category":"Servizi Per Lo Sport E Il Tempo Libero. Servizi Al Turismo. Acqua, Luce, Gas E Societa' Di Esercizio Pubblico",
    "sg:phone":"+39 0323 468506",
    "sg:postcode":"28801",
    "sg:province":"Verbano-Cusio-Ossola",
    "wof:name":"Ente Parco Nazionale Val Grande",
    "wof:placetype":"venue"
},
  "geometry": {"coordinates":[8.272465,46.139969],"type":"Point"}
}