{
  "type": "Feature",
  "properties": {
    "iso:country":"IT",
    "sg:address":"Via Matteo Civitali, 1; Milan; 20148",
    "sg:classifiers":[
        {
            "category":"Industrial Area",
            "type":"Public Place"
        }
    ],
    "sg:phone":"+39 390 248 7871",
    "sg:postcode":"20148",
    "sg:province":"Milano",
    "sg:tags":[
        "large",
        "private"
    ],
    "sg:website":"www.recordati.it",
    "wof:name":"Recordati S.p.a.",
    "wof:placetype":"venue"
},
  "geometry": {"coordinates":[9.1325588226,45.4722824097],"type":"Point"}
}