{
  "type": "Feature",
  "properties": {
    "iso:country":"IT",
    "sg:address":"97100 Ragusa",
    "sg:city":"Ragusa",
    "sg:orig_category":"Trasporti E Spedizioni Merci",
    "sg:phone":"+39 0932 257098",
    "sg:postcode":"97100",
    "sg:province":"Ragusa",
    "sg:website":"http://www.ibleatir.it",
    "wof:name":"Iblea Tir Spedizioni",
    "wof:placetype":"venue"
},
  "geometry": {"coordinates":[14.682105,36.912518],"type":"Point"}
}