{
  "type": "Feature",
  "properties": {
    "iso:country":"IT",
    "sg:address":"Localita' Levanella 52025 Montevarchi",
    "sg:city":"Levane",
    "sg:classifiers":[
        {
            "category":"Shopping",
            "subcategory":"Clothing, Apparel, & Fashions",
            "type":"Retail Goods"
        }
    ],
    "sg:phone":"+39 055 978 9194",
    "sg:postcode":"52025",
    "sg:province":"Arezzo",
    "sg:tags":[
        "clothes"
    ],
    "wof:name":"Crea (s.r.l.)",
    "wof:placetype":"venue"
},
  "geometry": {"coordinates":[11.594922,43.512966],"type":"Point"}
}