{
  "type": "Feature",
  "properties": {
    "addr:full":"7, Via Tommaso Edison 20090 Cusago Cusago Milano 20090",
    "addr:postcode":"20090;20090",
    "addr:street":"Via Tommaso Edison",
    "iso:country":"IT",
    "sg:address":"7, Via Tommaso Edison 20090 Cusago",
    "sg:city":"Cusago",
    "sg:classifiers":[
        {
            "category":"Home & Garden",
            "subcategory":"Home Furnishings",
            "type":"Retail Goods"
        }
    ],
    "sg:phone":"+39 02 9039 0013",
    "sg:postcode":"20090",
    "sg:province":"Milano",
    "sg:tags":[
        "household"
    ],
    "wof:name":"Rexite",
    "wof:placetype":"venue"
},
  "geometry": {"coordinates":[9.06343,45.420738],"type":"Point"}
}