{
  "type": "Feature",
  "properties": {
    "iso:country":"IT",
    "sg:address":"50062 Dicomano",
    "sg:city":"Dicomano",
    "sg:orig_category":"Servizi Di Magazzinaggio E Movimentazione",
    "sg:phone":"+39 055 838283",
    "sg:postcode":"50062",
    "sg:province":"Firenze",
    "wof:name":"F.f. Di Fabio Ficcoli E C. Sas",
    "wof:placetype":"venue"
},
  "geometry": {"coordinates":[11.216123,43.711266],"type":"Point"}
}