{
  "type": "Feature",
  "properties": {
    "iso:country":"IT",
    "sg:address":"00121 Lido Di Ostia",
    "sg:orig_category":"Ospedali E Servizi Sanitari",
    "sg:phone":"+39 06 569 0967",
    "sg:postcode":"00121",
    "sg:province":"Roma",
    "wof:name":"Studio Di Radiologia E Di Roentgenterapia Lido Di Ostia Srl",
    "wof:placetype":"venue"
},
  "geometry": {"coordinates":[12.274083,41.73312],"type":"Point"}
}