{
  "type": "Feature",
  "properties": {
    "iso:country":"IT",
    "sg:address":"20037 Paderno Dugnano",
    "sg:city":"Paderno Dugnano",
    "sg:orig_category":"Servizi E Lavori Per Industria Alimentare E Bevande",
    "sg:phone":"+39 02 910 6676",
    "sg:postcode":"20037",
    "sg:province":"Milano",
    "wof:name":"Coop. Agricola Di Consumo S. Martino",
    "wof:placetype":"venue"
},
  "geometry": {"coordinates":[9.162052,45.581711],"type":"Point"}
}