{
  "type": "Feature",
  "properties": {
    "addr:full":"21053 Castellanza Castellanza Varese 21053",
    "addr:postcode":"21053;21053",
    "iso:country":"IT",
    "sg:address":"21053 Castellanza",
    "sg:city":"Castellanza",
    "sg:orig_category":"Abbigliamento Intimo, Calze E Costumi Da Bagno",
    "sg:phone":"+39 0331 632807",
    "sg:postcode":"21053",
    "sg:province":"Varese",
    "wof:name":"Castelli Spa",
    "wof:placetype":"venue"
},
  "geometry": {"coordinates":[8.83631,45.809227],"type":"Point"}
}