{
  "type": "Feature",
  "properties": {
    "iso:country":"IT",
    "sg:address":"20144 Milano",
    "sg:city":"Milano",
    "sg:orig_category":"Gioielleria, Oreficeria E Argenteria. Shopping",
    "sg:phone":"+39 02 8940 2087",
    "sg:postcode":"20144",
    "sg:province":"Milano",
    "sg:website":"http://www.pierrebonnet.com",
    "wof:name":"Pierre Bonnet",
    "wof:placetype":"venue"
},
  "geometry": {"coordinates":[9.169401,45.455097],"type":"Point"}
}