{
  "type": "Feature",
  "properties": {
    "addr:full":"Viale Spagna 156 20093 Cologno Monzese Cologno Monzese Milano 20093",
    "addr:housenumber":"156",
    "addr:postcode":"20093;20093",
    "addr:street":"Viale Spagna",
    "iso:country":"IT",
    "sg:address":"Viale Spagna 156 20093 Cologno Monzese",
    "sg:city":"Cologno Monzese",
    "sg:classifiers":[
        {
            "category":"Manufacturing",
            "subcategory":"Chemicals & Compounds",
            "type":"Manufacturing & Wholesale Goods"
        }
    ],
    "sg:phone":"+39 02 254 1731",
    "sg:postcode":"20093",
    "sg:province":"Milano",
    "sg:tags":[
        "chemical-pharmaceutical",
        "industry",
        "material",
        "basic"
    ],
    "wof:name":"Steroid S.p.a.",
    "wof:placetype":"venue"
},
  "geometry": {"coordinates":[9.26615,45.535221],"type":"Point"}
}