{
  "type": "Feature",
  "properties": {
    "iso:country":"IT",
    "sg:address":"16163 Genova",
    "sg:city":"Genova",
    "sg:orig_category":"Disinfezione, Disinfestazione E Derattizzazione",
    "sg:phone":"+39 010 726 1525",
    "sg:postcode":"16163",
    "sg:province":"Genova",
    "sg:website":"http://www.konrad.it",
    "wof:name":"Cambiaso Massimo",
    "wof:placetype":"venue"
},
  "geometry": {"coordinates":[8.916994,44.486153],"type":"Point"}
}