{
  "type": "Feature",
  "properties": {
    "addr:full":"25031 Capriolo Capriolo Brescia 25031",
    "addr:postcode":"25031;25031",
    "iso:country":"IT",
    "sg:address":"25031 Capriolo",
    "sg:city":"Capriolo",
    "sg:orig_category":"Prodotti E Manufatti In Gomma",
    "sg:phone":"+39 030 746 0543",
    "sg:postcode":"25031",
    "sg:province":"Brescia",
    "wof:name":"Cerni - Gom",
    "wof:placetype":"venue"
},
  "geometry": {"coordinates":[9.9338884354,45.642250061],"type":"Point"}
}