{
  "type": "Feature",
  "properties": {
    "addr:full":"25131 Brescia Brescia Brescia 25131",
    "addr:postcode":"25131;25131",
    "iso:country":"IT",
    "sg:address":"25131 Brescia",
    "sg:city":"Brescia",
    "sg:orig_category":"Fotografia Pubblicitaria",
    "sg:phone":"+39 030 358 2133",
    "sg:postcode":"25131",
    "sg:province":"Brescia",
    "sg:website":"http://www.safetyglass.it",
    "wof:name":"Safetyglass Srl",
    "wof:placetype":"venue"
},
  "geometry": {"coordinates":[10.1763372421,45.4894752502],"type":"Point"}
}