{
  "type": "Feature",
  "properties": {
    "addr:full":"37040 Terrazzo Terrazzo Verona 37040",
    "addr:housenumber":"37040",
    "addr:postcode":"37040",
    "iso:country":"IT",
    "sg:address":"37040 Terrazzo",
    "sg:city":"Terrazzo",
    "sg:orig_category":"Accessori Moda D'abbigliamento. Shopping",
    "sg:phone":"+39 0442 94300",
    "sg:postcode":"37040",
    "sg:province":"Verona",
    "wof:name":"Spazian Onorina",
    "wof:placetype":"venue"
},
  "geometry": {"coordinates":[11.396235,45.172619],"type":"Point"}
}