{
  "type": "Feature",
  "properties": {
    "iso:country":"IT",
    "sg:address":"16122 Genova",
    "sg:city":"Genova",
    "sg:orig_category":"Manufacturers: Prefabbricati. Arredi Ed Attrezzature Per Attivita' Commerciali Ed Artigianali",
    "sg:phone":"+39 010 210693",
    "sg:postcode":"16122",
    "sg:province":"Genova",
    "wof:name":"Tecnogamma Di S. Di Muzio",
    "wof:placetype":"venue"
},
  "geometry": {"coordinates":[8.943854,44.413506],"type":"Point"}
}