{
  "type": "Feature",
  "properties": {
    "iso:country":"IT",
    "sg:address":"Via L. Manara, 18/24; Galatone; 73044",
    "sg:city":"Galatone",
    "sg:classifiers":[
        {
            "category":"Banks & Credit Unions",
            "subcategory":"Bank",
            "type":"Services"
        }
    ],
    "sg:phone":"+39 0833 862827",
    "sg:postcode":"73044",
    "sg:province":"Lecce",
    "wof:name":"Banca Popolare Di Lecce",
    "wof:placetype":"venue"
},
  "geometry": {"coordinates":[18.069519,40.145996],"type":"Point"}
}