{
  "type": "Feature",
  "properties": {
    "iso:country":"IT",
    "sg:address":"Sda Geromina Nuova Artigianale 41 33077 Sacile",
    "sg:city":"Sacile",
    "sg:classifiers":[
        {
            "category":"Manufacturing",
            "subcategory":"Wood Products",
            "type":"Manufacturing & Wholesale Goods"
        }
    ],
    "sg:phone":"+39 0434 71730",
    "sg:postcode":"33077",
    "sg:province":"Pordenone",
    "sg:tags":[
        "semi-finished"
    ],
    "sg:website":"www.siatranciati.it",
    "wof:name":"Sia Tranciati Snc",
    "wof:placetype":"venue"
},
  "geometry": {"coordinates":[12.655044,45.96265],"type":"Point"}
}