{
  "type": "Feature",
  "properties": {
    "iso:country":"IT",
    "sg:address":"20122 Milano",
    "sg:city":"Milano",
    "sg:orig_category":"Servizi E Lavori Per Edilizia E Lavori Pubblici. Banche E Servizi Finanziari",
    "sg:phone":"+39 02 8699 5594",
    "sg:postcode":"20122",
    "sg:province":"Milano",
    "wof:name":"Selfimm Srl",
    "wof:placetype":"venue"
},
  "geometry": {"coordinates":[9.193719,45.464611],"type":"Point"}
}