{
  "type": "Feature",
  "properties": {
    "addr:full":"76, Via Vi Strada 36071 Arzignano Arzignano Vicenza 36071",
    "addr:postcode":"36071;36071",
    "addr:street":"Via Vi Strada",
    "iso:country":"IT",
    "sg:address":"76, Via Vi Strada 36071 Arzignano",
    "sg:city":"Arzignano",
    "sg:classifiers":[
        {
            "category":"Manufacturing",
            "subcategory":"Rubber & Plastics",
            "type":"Manufacturing & Wholesale Goods"
        }
    ],
    "sg:phone":"+39 0444 450660",
    "sg:postcode":"36071",
    "sg:province":"Vicenza",
    "wof:name":"Fratelli Virginio (s.r.l.)",
    "wof:placetype":"venue"
},
  "geometry": {"coordinates":[11.540307045,45.5459060669],"type":"Point"}
}