{
  "type": "Feature",
  "properties": {
    "iso:country":"IT",
    "sg:address":"73051 Novoli",
    "sg:city":"Novoli",
    "sg:orig_category":"Arredo Cucina Ed Elettrodomestici. Elettrodomestici",
    "sg:phone":"+39 0832 714479",
    "sg:postcode":"73051",
    "sg:province":"Lecce",
    "wof:name":"L'idea Elettrodomestici Di Fiore Giovanna",
    "wof:placetype":"venue"
},
  "geometry": {"coordinates":[18.046432,40.374405],"type":"Point"}
}