{
  "type": "Feature",
  "properties": {
    "addr:full":"41013 Castelfranco Emilia Castelfranco Emilia Modena 41013",
    "addr:postcode":"41013;41013",
    "iso:country":"IT",
    "sg:address":"41013 Castelfranco Emilia",
    "sg:city":"Castelfranco Emilia",
    "sg:orig_category":"Macchine, Impianti Ed Attrezzature Per Industria Alimentare E Bevande. Apparecchiature E Sistemi Per Imballaggio E Confezionamento",
    "sg:phone":"+39 059 925773",
    "sg:postcode":"41013",
    "sg:province":"Modena",
    "wof:name":"Etra S.r.l.",
    "wof:placetype":"venue"
},
  "geometry": {"coordinates":[11.019956,44.532043],"type":"Point"}
}