{
  "type": "Feature",
  "properties": {
    "iso:country":"IT",
    "sg:address":"49, Via Montebello 27029 Vigevano",
    "sg:city":"Vigevano",
    "sg:classifiers":[
        {
            "category":"Professional",
            "subcategory":"Engineering",
            "type":"Services"
        }
    ],
    "sg:phone":"+39 0381 345976",
    "sg:postcode":"27029",
    "sg:province":"Pavia",
    "sg:tags":[
        "machine",
        "-",
        "mechanical"
    ],
    "wof:name":"I.m.e.c.a. (s.r.l.)",
    "wof:placetype":"venue"
},
  "geometry": {"coordinates":[8.884189,45.31958],"type":"Point"}
}