{
  "type": "Feature",
  "properties": {
    "iso:country":"IT",
    "sg:address":"32020 Lentiai",
    "sg:city":"Lentiai",
    "sg:orig_category":"Arredo Camera Letto E Complementi",
    "sg:phone":"+39 0437 750756",
    "sg:postcode":"32020",
    "sg:province":"Belluno",
    "sg:website":"http://www.flexpiave.com",
    "wof:name":"Flex Piave Snc",
    "wof:placetype":"venue"
},
  "geometry": {"coordinates":[12.012005,46.040668],"type":"Point"}
}