{
  "type": "Feature",
  "properties": {
    "addr:full":"96100 Siracusa Siracusa Siracusa 96100",
    "addr:postcode":"96100;96100",
    "iso:country":"IT",
    "sg:address":"96100 Siracusa",
    "sg:city":"Siracusa",
    "sg:orig_category":"Musica. Shopping",
    "sg:phone":"+39 0931 442774",
    "sg:postcode":"96100",
    "sg:province":"Siracusa",
    "wof:name":"Moscuzza Francesco Sas",
    "wof:placetype":"venue"
},
  "geometry": {"coordinates":[15.2868089676,37.0832443237],"type":"Point"}
}