{
  "type": "Feature",
  "properties": {
    "iso:country":"IT",
    "sg:address":"84084 Fisciano",
    "sg:city":"Fisciano",
    "sg:orig_category":"Articoli Per Imballaggio E Confezionamento. Forniture Per Uffici. Forniture Per Attivita' Commerciali Ed Artigianali",
    "sg:phone":"+39 089 820 1409",
    "sg:postcode":"84084",
    "sg:province":"Salerno",
    "wof:name":"Bioplast Srl Plastica Gambardella Srl",
    "wof:placetype":"venue"
},
  "geometry": {"coordinates":[14.787101,40.774212],"type":"Point"}
}