{
  "type": "Feature",
  "properties": {
    "iso:country":"IT",
    "sg:address":"42, Via Matteotti 35026 Conselve",
    "sg:city":"Conselve",
    "sg:classifiers":[
        {
            "category":"Shopping",
            "subcategory":"Stationery & Office Supplies",
            "type":"Retail Goods"
        }
    ],
    "sg:phone":"+39 049 950 0744",
    "sg:postcode":"35026",
    "sg:province":"Padova",
    "sg:tags":[
        "professional"
    ],
    "wof:name":"Castom Italia Di Bertoli Luca & C. (s.n.c.)",
    "wof:placetype":"venue"
},
  "geometry": {"coordinates":[11.8765888214,45.4095687866],"type":"Point"}
}