{
  "type": "Feature",
  "properties": {
    "iso:country":"IT",
    "sg:address":"25015 Desenzano Del Garda",
    "sg:city":"Desenzano del Garda",
    "sg:orig_category":"Scuole E Servizi Scolastici. Ospedali E Servizi Sanitari",
    "sg:phone":"+39 030 912 1050",
    "sg:postcode":"25015",
    "sg:province":"Brescia",
    "wof:name":"Rossi Marco",
    "wof:placetype":"venue"
},
  "geometry": {"coordinates":[10.542529,45.467461],"type":"Point"}
}