{
  "type": "Feature",
  "properties": {
    "iso:country":"IT",
    "sg:address":"22015 Gravedona",
    "sg:city":"Gravedona",
    "sg:orig_category":"Articoli Per Imballaggio E Confezionamento",
    "sg:phone":"+39 0344 89530",
    "sg:postcode":"22015",
    "sg:province":"Como",
    "sg:website":"http://www.elletiemme.com",
    "wof:name":"Elletiemme Sas",
    "wof:placetype":"venue"
},
  "geometry": {"coordinates":[9.302738,46.143311],"type":"Point"}
}