{
  "type": "Feature",
  "properties": {
    "iso:country":"IT",
    "sg:address":"7/a, V. Ippolito D'este 16121 Genova",
    "sg:city":"Genova",
    "sg:classifiers":[
        {
            "category":"Shopping",
            "subcategory":"Computers & Home Electronics",
            "type":"Retail Goods"
        }
    ],
    "sg:phone":"+39 010 553 8423",
    "sg:postcode":"16121",
    "sg:province":"Genova",
    "sg:tags":[
        "electronic",
        "electrical",
        "equipment"
    ],
    "sg:website":"http://www.procomser.it",
    "wof:name":"Procomser Srl",
    "wof:placetype":"venue"
},
  "geometry": {"coordinates":[8.941264,44.403263],"type":"Point"}
}