{
  "type": "Feature",
  "properties": {
    "iso:country":"IT",
    "sg:address":"17100 Savona",
    "sg:city":"Legino",
    "sg:orig_category":"Frigotecnica, Apparecchiature E Servizi. Forniture Alle Strutture Ricettive",
    "sg:phone":"+39 019 861532",
    "sg:postcode":"17100",
    "sg:province":"Savona",
    "wof:name":"Cavallino & C. Snc",
    "wof:placetype":"venue"
},
  "geometry": {"coordinates":[8.4490642548,44.2967681885],"type":"Point"}
}