{
  "type": "Feature",
  "properties": {
    "addr:full":"Via Provinciale 15 75020 Scanzano Matera 75020",
    "addr:housenumber":"15",
    "addr:postcode":"75020;75020",
    "addr:street":"Via Provinciale",
    "iso:country":"IT",
    "sg:address":"Via Provinciale 15 75020 Scanzano",
    "sg:classifiers":[
        {
            "category":"Food & Beverages",
            "subcategory":"Fruits & Vegetables",
            "type":"Retail Goods"
        }
    ],
    "sg:phone":"+39 0835 953122",
    "sg:postcode":"75020",
    "sg:province":"Matera",
    "sg:website":"www.heraclea.it/nicofruit",
    "wof:name":"Nico Fruit Societa' Cooperativa Agricola R.l.",
    "wof:placetype":"venue"
},
  "geometry": {"coordinates":[16.606086731,40.6686515808],"type":"Point"}
}