{
  "type": "Feature",
  "properties": {
    "iso:country":"IT",
    "sg:address":"00182 Roma",
    "sg:city":"Roma",
    "sg:orig_category":"Impiantistica E Prodotti Tecnologici Per Edilizia. Elettrotecnica Professionale E Di Consumo. Telecomunicazioni E Telefonia, Impianti, Apparecchi E Servizi",
    "sg:phone":"+39 06 7016 5608",
    "sg:postcode":"00182",
    "sg:province":"Roma",
    "sg:website":"http://www.satservice.it",
    "wof:name":"Antonini Enrico",
    "wof:placetype":"venue"
},
  "geometry": {"coordinates":[12.517254,41.886532],"type":"Point"}
}