{
  "type": "Feature",
  "properties": {
    "iso:country":"IT",
    "sg:address":"20061 Carugate",
    "sg:city":"Carugate",
    "sg:orig_category":"Elettromagneti",
    "sg:phone":"+39 02 925 3661",
    "sg:postcode":"20061",
    "sg:province":"Milano",
    "wof:name":"Lomar Di G. Arini Snc",
    "wof:placetype":"venue"
},
  "geometry": {"coordinates":[9.29391,45.544205],"type":"Point"}
}