{
  "type": "Feature",
  "properties": {
    "addr:full":"26041 Casalmaggiore Casalmaggiore Cremona 26041",
    "addr:housenumber":"26041",
    "addr:postcode":"26041",
    "addr:street":"Casalmaggiore Casalmaggiore Cremona",
    "iso:country":"IT",
    "sg:address":"26041 Casalmaggiore",
    "sg:city":"Casalmaggiore",
    "sg:orig_category":"Manufacturers: Prefabbricati",
    "sg:phone":"+39 0375 200515",
    "sg:postcode":"26041",
    "sg:province":"Cremona",
    "wof:name":"Bragapan Srl",
    "wof:placetype":"venue"
},
  "geometry": {"coordinates":[10.434666,44.985706],"type":"Point"}
}