{
  "type": "Feature",
  "properties": {
    "iso:country":"IT",
    "sg:address":"98070 Capri Leone",
    "sg:city":"Capri Leone",
    "sg:orig_category":"Arredo Cucina Ed Elettrodomestici. Frigotecnica, Apparecchiature E Servizi. Elettrodomestici",
    "sg:phone":"+39 0941 950278",
    "sg:postcode":"98070",
    "sg:province":"Messina",
    "wof:name":"Mormimo Franco",
    "wof:placetype":"venue"
},
  "geometry": {"coordinates":[14.712946,38.111542],"type":"Point"}
}