{
  "type": "Feature",
  "properties": {
    "iso:country":"IT",
    "sg:address":"3/c, V. Ungheri - Lippo 40012 Calderara Di Reno",
    "sg:city":"Calderara di Reno",
    "sg:classifiers":[
        {
            "category":"Autos & Motor Vehicles",
            "subcategory":"Automobile Sales",
            "type":"Retail Goods"
        }
    ],
    "sg:phone":"+39 39051726849",
    "sg:postcode":"40012",
    "sg:province":"Bologna",
    "sg:tags":[
        "equipment",
        "transport"
    ],
    "sg:website":"http://www.ferracci.com:ws_end: :mark:ws:http://www.paginegialle.it/ferracci",
    "wof:name":"Fast By Ferracci Europe Srl",
    "wof:placetype":"venue"
},
  "geometry": {"coordinates":[11.303758,44.546211],"type":"Point"}
}