{
  "type": "Feature",
  "properties": {
    "iso:country":"IT",
    "sg:address":"60123 Ancona",
    "sg:city":"Ancona",
    "sg:orig_category":"Articoli Medico-sanitari Ed Ortopedici",
    "sg:phone":"+39 071 31980",
    "sg:postcode":"60123",
    "sg:province":"Ancona",
    "wof:name":"Lamonea Srl",
    "wof:placetype":"venue"
},
  "geometry": {"coordinates":[13.527785,43.618553],"type":"Point"}
}