{
  "type": "Feature",
  "properties": {
    "iso:country":"IT",
    "sg:address":"70123 Bari",
    "sg:city":"Bari",
    "sg:orig_category":"Irrigazione - Impianti",
    "sg:phone":"+39 080 531 3782",
    "sg:postcode":"70123",
    "sg:province":"Bari",
    "wof:name":"Tre Z Plast Srl",
    "wof:placetype":"venue"
},
  "geometry": {"coordinates":[16.803595,41.10799],"type":"Point"}
}