{
  "type": "Feature",
  "properties": {
    "iso:country":"IT",
    "sg:address":"16, Via Kravogl Johann 39100 Bolzano",
    "sg:city":"Bolzano",
    "sg:classifiers":[
        {
            "category":"Manufacturing",
            "subcategory":"Glass & Minerals",
            "type":"Manufacturing & Wholesale Goods"
        }
    ],
    "sg:phone":"+39 0471 200188",
    "sg:postcode":"39100",
    "sg:province":"Bolzano/Bozen",
    "wof:name":"Vetreria Rasom U. & Co. (s.a.s. - K.g.)",
    "wof:placetype":"venue"
},
  "geometry": {"coordinates":[11.328239,46.461643],"type":"Point"}
}