{
  "type": "Feature",
  "properties": {
    "iso:country":"IT",
    "sg:address":"Via Bugatto Giuseppe 34077 Ronchi Dei Legionari",
    "sg:city":"Ronchi dei Legionari",
    "sg:classifiers":[
        {
            "category":"Building & Trades",
            "subcategory":"Construction",
            "type":"Services"
        }
    ],
    "sg:phone":"+39 0481 474140",
    "sg:postcode":"34077",
    "sg:province":"Gorizia",
    "sg:tags":[
        "heat",
        "exchanger"
    ],
    "wof:name":"Roen Est Srl",
    "wof:placetype":"venue"
},
  "geometry": {"coordinates":[13.621546,45.941303],"type":"Point"}
}