{
  "type": "Feature",
  "properties": {
    "iso:country":"IT",
    "sg:address":"00040 Pomezia",
    "sg:city":"Pomezia",
    "sg:orig_category":"Carni, Salumi E Pesci",
    "sg:phone":"+39 06 912 0580",
    "sg:postcode":"00040",
    "sg:province":"Roma",
    "wof:name":"Polleria =pappagone=",
    "wof:placetype":"venue"
},
  "geometry": {"coordinates":[12.500281,41.673222],"type":"Point"}
}