{
  "type": "Feature",
  "properties": {
    "addr:full":"436, Via Colombo Cristoforo 00145 Roma Roma Roma 00145",
    "addr:housenumber":"436",
    "addr:postcode":"00145;00145",
    "addr:street":"Via Colombo Cristoforo",
    "iso:country":"IT",
    "sg:address":"436, Via Colombo Cristoforo 00145 Roma",
    "sg:city":"Roma",
    "sg:classifiers":[
        {
            "category":"Shopping",
            "subcategory":"Computers & Home Electronics",
            "type":"Retail Goods"
        }
    ],
    "sg:phone":"+39 39065964921",
    "sg:postcode":"00145",
    "sg:province":"Roma",
    "sg:tags":[
        "electronic",
        "electrical",
        "equipment"
    ],
    "wof:name":"Sartem Impianti Srl",
    "wof:placetype":"venue"
},
  "geometry": {"coordinates":[12.486008,41.851433],"type":"Point"}
}