{
  "type": "Feature",
  "properties": {
    "addr:full":"19/a, Via Degli Olmi 48018 Faenza Faenza Ravenna 48018",
    "addr:housenumber":"19 / a",
    "addr:postcode":"48018;48018",
    "addr:street":"Via Degli Olmi",
    "iso:country":"IT",
    "sg:address":"19/a, Via Degli Olmi 48018 Faenza",
    "sg:city":"Faenza",
    "sg:classifiers":[
        {
            "category":"Professional",
            "subcategory":"Engineering",
            "type":"Services"
        }
    ],
    "sg:phone":"+39 39054626596",
    "sg:postcode":"48018",
    "sg:province":"Ravenna",
    "sg:tags":[
        "machine",
        "-",
        "mechanical"
    ],
    "wof:name":"R.t.f. S.r.l.",
    "wof:placetype":"venue"
},
  "geometry": {"coordinates":[12.196571,44.41573],"type":"Point"}
}