{
  "type": "Feature",
  "properties": {
    "iso:country":"IT",
    "sg:address":"10128 Torino",
    "sg:city":"Torino",
    "sg:orig_category":"Abbigliamento Esterno, Maglierie E Pelliccerie",
    "sg:phone":"+39 011 568 1989",
    "sg:postcode":"10128",
    "sg:province":"Torino",
    "sg:website":"http://www.carlofiori.com",
    "wof:name":"Carlo Fiori Sas Di Pirollo Stefano",
    "wof:placetype":"venue"
},
  "geometry": {"coordinates":[7.670135,45.058353],"type":"Point"}
}