{
  "type": "Feature",
  "properties": {
    "iso:country":"IT",
    "sg:address":"00197 Roma",
    "sg:city":"Roma",
    "sg:orig_category":"Trasporti E Spedizioni Merci",
    "sg:phone":"+39 06 807 5242",
    "sg:postcode":"00197",
    "sg:province":"Roma",
    "wof:name":"C.e.m.a.t. (s.p.a.)",
    "wof:placetype":"venue"
},
  "geometry": {"coordinates":[12.484475,41.850975],"type":"Point"}
}