{
  "type": "Feature",
  "properties": {
    "iso:country":"IT",
    "sg:address":"Via Crosa 29 28065 Cerano",
    "sg:city":"Cerano",
    "sg:classifiers":[
        {
            "category":"Wholesale",
            "subcategory":"Machinery & Supplies",
            "type":"Manufacturing & Wholesale Goods"
        }
    ],
    "sg:phone":"+39 0321 772233",
    "sg:postcode":"28065",
    "sg:province":"Novara",
    "sg:tags":[
        "pin",
        "clevis"
    ],
    "sg:website":"www.bulloneriausorini.com",
    "wof:name":"Bulloneria Usorini Srl",
    "wof:placetype":"venue"
},
  "geometry": {"coordinates":[8.804802,45.403782],"type":"Point"}
}