{
  "type": "Feature",
  "properties": {
    "addr:full":"00168 Roma Roma Roma 00168",
    "addr:postcode":"00168;00168",
    "iso:country":"IT",
    "sg:address":"00168 Roma",
    "sg:city":"Roma",
    "sg:orig_category":"Macchine, Impianti Ed Attrezzature Per Abbigliamento E Pelletterie",
    "sg:phone":"+39 06 307 1502",
    "sg:postcode":"00168",
    "sg:province":"Roma",
    "wof:name":"Baronetti Antonino",
    "wof:placetype":"venue"
},
  "geometry": {"coordinates":[12.418193,41.945164],"type":"Point"}
}