{
  "type": "Feature",
  "properties": {
    "addr:full":"Loc. Taverne 06073 Corciano Corciano Perugia 06073",
    "addr:postcode":"06073;06073",
    "addr:street":"Taverne",
    "iso:country":"IT",
    "sg:address":"Loc. Taverne 06073 Corciano",
    "sg:city":"Corciano",
    "sg:classifiers":[
        {
            "category":"Manufacturing",
            "subcategory":"Paper Products",
            "type":"Manufacturing & Wholesale Goods"
        }
    ],
    "sg:phone":"+39 075 697 8342",
    "sg:postcode":"06073",
    "sg:province":"Perugia",
    "sg:tags":[
        "cardboard"
    ],
    "sg:website":"http://www.paginegialle.it/graftrott",
    "wof:name":"Grafiche Trotta Perugia Srl",
    "wof:placetype":"venue"
},
  "geometry": {"coordinates":[12.3891716003,43.1107025146],"type":"Point"}
}