{
  "type": "Feature",
  "properties": {
    "iso:country":"IT",
    "sg:address":"31033 Castelfranco Veneto",
    "sg:city":"Castelfranco Veneto",
    "sg:orig_category":"Forniture Per Edilizia E Lavori Pubblici",
    "sg:phone":"+39 0423 472433",
    "sg:postcode":"31033",
    "sg:province":"Treviso",
    "wof:name":"Antonello Angelo E Figlio Snc",
    "wof:placetype":"venue"
},
  "geometry": {"coordinates":[11.9518966675,45.6732902527],"type":"Point"}
}