{
  "type": "Feature",
  "properties": {
    "iso:country":"IT",
    "sg:address":"26/28, V. Roma 42020 Albinea",
    "sg:classifiers":[
        {
            "category":"Professional",
            "subcategory":"Engineering",
            "type":"Services"
        }
    ],
    "sg:phone":"+39 0522 347330",
    "sg:postcode":"42020",
    "sg:province":"Reggio Nell'Emilia",
    "sg:tags":[
        "machine",
        "-",
        "mechanical"
    ],
    "sg:website":"http://www.flexbimec.com:ws_end: :mark:ws:http://www.paginegialle.it/flexbimecinternational",
    "wof:name":"Flexbimec International",
    "wof:placetype":"venue"
},
  "geometry": {"coordinates":[10.599364,44.622787],"type":"Point"}
}