{
  "type": "Feature",
  "properties": {
    "iso:country":"IT",
    "sg:address":"40139 Bologna",
    "sg:city":"Bologna",
    "sg:orig_category":"Termotecnica E Riscaldamento, Apparecchiature E Servizi. Prodotti Vari In Metallo",
    "sg:phone":"+39 051 624 1224",
    "sg:postcode":"40139",
    "sg:province":"Bologna",
    "wof:name":"Landuzzi Di Landuzzi Stefano & C. Snc",
    "wof:placetype":"venue"
},
  "geometry": {"coordinates":[11.38495,44.477982],"type":"Point"}
}