{
  "type": "Feature",
  "properties": {
    "iso:country":"IT",
    "sg:address":"Localita' Foxi 09045 Quartu Sant'elena",
    "sg:classifiers":[
        {
            "category":"Travel",
            "subcategory":"Travel Agent",
            "type":"Entertainment"
        }
    ],
    "sg:phone":"+39 39070890131",
    "sg:postcode":"09045",
    "sg:province":"Cagliari",
    "sg:tags":[
        "business"
    ],
    "wof:name":"Hotel Califfo",
    "wof:placetype":"venue"
},
  "geometry": {"coordinates":[9.203863,39.225899],"type":"Point"}
}