{
  "type": "Feature",
  "properties": {
    "iso:country":"IT",
    "sg:address":"138, Via Di Tor Sapienza 00155 Roma",
    "sg:city":"Roma",
    "sg:classifiers":[
        {
            "category":"Wholesale",
            "subcategory":"Drugs",
            "type":"Manufacturing & Wholesale Goods"
        }
    ],
    "sg:phone":"+39 390 622 7421",
    "sg:postcode":"00155",
    "sg:province":"Roma",
    "sg:tags":[
        "chemical",
        "pharmaceutical"
    ],
    "wof:name":"Polifarma",
    "wof:placetype":"venue"
},
  "geometry": {"coordinates":[12.57191,41.907539],"type":"Point"}
}