{
  "type": "Feature",
  "properties": {
    "iso:country":"IT",
    "sg:address":"Localita' Pian Dei Peschi 53036 Poggibonsi",
    "sg:city":"Poggibonsi",
    "sg:classifiers":[
        {
            "category":"Home & Garden",
            "subcategory":"Home Furnishings",
            "type":"Retail Goods"
        }
    ],
    "sg:phone":"+39 0577 978611",
    "sg:postcode":"53036",
    "sg:province":"Siena",
    "sg:tags":[
        "household"
    ],
    "wof:name":"Aurora Cucine",
    "wof:placetype":"venue"
},
  "geometry": {"coordinates":[11.3305139542,43.3186607361],"type":"Point"}
}