{
  "type": "Feature",
  "properties": {
    "iso:country":"IT",
    "sg:address":"00162 Roma",
    "sg:city":"Roma",
    "sg:orig_category":"Servizi Al Turismo. Trasporto Pubblico E Privato. Acqua, Luce, Gas E Societa' Di Esercizio Pubblico",
    "sg:phone":"+39 06 8621 4491",
    "sg:postcode":"00162",
    "sg:province":"Roma",
    "wof:name":"Societa' Ferrotranviaria Spa",
    "wof:placetype":"venue"
},
  "geometry": {"coordinates":[12.526935,41.905579],"type":"Point"}
}