{
  "type": "Feature",
  "properties": {
    "iso:country":"IT",
    "sg:address":"Udine, Ud",
    "sg:classifiers":[
        {
            "category":"Banks & Credit Unions",
            "subcategory":"Bank",
            "type":"Services"
        }
    ],
    "wof:name":"Fondazione Cassa Di Risparmio Di Udine E Pordenone",
    "wof:placetype":"venue"
},
  "geometry": {"coordinates":[13.230724,46.064941],"type":"Point"}
}