{
  "type": "Feature",
  "properties": {
    "iso:country":"IT",
    "sg:address":"52, Zona Artigianale 39040 Varna",
    "sg:city":"Varna",
    "sg:classifiers":[
        {
            "category":"Manufacturing",
            "subcategory":"Rubber & Plastics",
            "type":"Manufacturing & Wholesale Goods"
        }
    ],
    "sg:phone":"+39 0472 834916",
    "sg:postcode":"39040",
    "sg:province":"Bolzano/Bozen",
    "wof:name":"Dolar S.r.l.",
    "wof:placetype":"venue"
},
  "geometry": {"coordinates":[11.6520385742,46.7325286865],"type":"Point"}
}