{
  "type": "Feature",
  "properties": {
    "addr:full":"41049 Sassuolo Sassuolo Modena 41049",
    "addr:postcode":"41049;41049",
    "iso:country":"IT",
    "sg:address":"41049 Sassuolo",
    "sg:city":"Sassuolo",
    "sg:orig_category":"Calzature, Pelletterie E Pelli",
    "sg:phone":"+39 0536 872868",
    "sg:postcode":"41049",
    "sg:province":"Modena",
    "wof:name":"Braglia F.lli Pellami (s.n.c.)",
    "wof:placetype":"venue"
},
  "geometry": {"coordinates":[10.776622,44.527027],"type":"Point"}
}