{
  "type": "Feature",
  "properties": {
    "iso:country":"IT",
    "sg:address":"63039 San Benedetto Del Tronto",
    "sg:city":"San Benedetto del Tronto",
    "sg:orig_category":"Scuole E Servizi Scolastici",
    "sg:phone":"+39 0735 583282",
    "sg:postcode":"63039",
    "sg:province":"Ascoli Piceno",
    "wof:name":"Suore Di San Giovanni Battista",
    "wof:placetype":"venue"
},
  "geometry": {"coordinates":[13.873803,42.929726],"type":"Point"}
}