{
  "type": "Feature",
  "properties": {
    "iso:country":"IT",
    "sg:address":"16035 Rapallo",
    "sg:city":"Rapallo",
    "sg:orig_category":"Legno E Semilavorati. Macchine E Forniture Per Arredamento E Industria Del Legno. Hobbistica",
    "sg:phone":"+39 0185 55902",
    "sg:postcode":"16035",
    "sg:province":"Genova",
    "wof:name":"Brizzolara Paolo Fai Da Te",
    "wof:placetype":"venue"
},
  "geometry": {"coordinates":[9.223359,44.352001],"type":"Point"}
}