{
  "type": "Feature",
  "properties": {
    "iso:country":"IT",
    "sg:address":"136, V. Nazionale 92024 Canicatt\u00ec",
    "sg:classifiers":[
        {
            "category":"Manufacturing",
            "subcategory":"Printing",
            "type":"Manufacturing & Wholesale Goods"
        }
    ],
    "sg:phone":"+39 0922 832243",
    "sg:postcode":"92024",
    "sg:province":"Agrigento",
    "sg:tags":[
        "publishing"
    ],
    "sg:website":"http://www.paginegialle.it/itcalbum",
    "wof:name":"I.t.c. Album - Trupia Calogero",
    "wof:placetype":"venue"
},
  "geometry": {"coordinates":[13.8522672653,37.3665046692],"type":"Point"}
}