{
  "type": "Feature",
  "properties": {
    "iso:country":"IT",
    "sg:address":"34170 Gorizia",
    "sg:city":"Gorizia",
    "sg:orig_category":"Servizi E Lavori Per Ecologia E Smaltimento Rifiuti. Acqua, Luce, Gas E Societa' Di Esercizio Pubblico",
    "sg:phone":"+39 0481 593111",
    "sg:postcode":"34170",
    "sg:province":"Gorizia",
    "sg:website":"http://www.amg-go.it",
    "wof:name":"Azienda Multiservizi Goriziana - A.m.g. Spa",
    "wof:placetype":"venue"
},
  "geometry": {"coordinates":[13.599144,45.943825],"type":"Point"}
}