{
  "type": "Feature",
  "properties": {
    "addr:full":"Contrada Vallememoria 62019 Recanati Recanati Macerata 62019",
    "addr:postcode":"62019;62019",
    "addr:street":"Contrada Vallememoria",
    "iso:country":"IT",
    "sg:address":"Contrada Vallememoria 62019 Recanati",
    "sg:city":"Recanati",
    "sg:classifiers":[
        {
            "category":"Professional",
            "subcategory":"Engineering",
            "type":"Services"
        }
    ],
    "sg:phone":"+39 071 757 3998",
    "sg:postcode":"62019",
    "sg:province":"Macerata",
    "sg:tags":[
        "machine",
        "-",
        "mechanical"
    ],
    "wof:name":"Castagnari Srl",
    "wof:placetype":"venue"
},
  "geometry": {"coordinates":[13.574934,43.381649],"type":"Point"}
}