{
  "type": "Feature",
  "properties": {
    "addr:full":"25020 Milzano Milzano Brescia 25020",
    "addr:postcode":"25020;25020",
    "iso:country":"IT",
    "sg:address":"25020 Milzano",
    "sg:city":"Milzano",
    "sg:classifiers":[
        {
            "category":"Health Services",
            "subcategory":"Health Practitioner",
            "type":"Services"
        }
    ],
    "sg:phone":"+39 030 952 1112",
    "sg:postcode":"25020",
    "sg:province":"Brescia",
    "sg:tags":[
        "medici"
    ],
    "wof:name":"Sozzi Emilio",
    "wof:placetype":"venue"
},
  "geometry": {"coordinates":[10.2003145218,45.2745361328],"type":"Point"}
}