{
  "type": "Feature",
  "properties": {
    "iso:country":"IT",
    "sg:address":"Via Papa Giovanni Xxiii 16 42020 San Polo D'enza",
    "sg:orig_category":"Heat Insulators, Microporous",
    "sg:phone":"+39 0522 873621",
    "sg:postcode":"42020",
    "sg:province":"Reggio Nell'Emilia",
    "sg:website":"www.fortlan.it",
    "wof:name":"Fortlan Spa",
    "wof:placetype":"venue"
},
  "geometry": {"coordinates":[10.437903,44.634048],"type":"Point"}
}