{
  "type": "Feature",
  "properties": {
    "iso:country":"IT",
    "sg:address":"00145 Roma",
    "sg:city":"Roma",
    "sg:orig_category":"Impianti Elettrici Industriali E Civili - Installazione E Manutenzione",
    "sg:phone":"+39 06 541 4624",
    "sg:postcode":"00145",
    "sg:province":"Roma",
    "wof:name":"Elettromeccanica Cristoforo Colombo Di Franco E Carlo Alberti",
    "wof:placetype":"venue"
},
  "geometry": {"coordinates":[12.486865,41.855198],"type":"Point"}
}