{
  "type": "Feature",
  "properties": {
    "iso:country":"IT",
    "sg:address":"Via P. Educ. 45; Castellamonte; 10081",
    "sg:city":"Castellamonte",
    "sg:classifiers":[
        {
            "category":"Banks & Credit Unions",
            "subcategory":"Bank",
            "type":"Services"
        }
    ],
    "sg:phone":"+39 0124 585130",
    "sg:postcode":"10081",
    "sg:province":"Torino",
    "wof:name":"Banca Popolare Di Novara",
    "wof:placetype":"venue"
},
  "geometry": {"coordinates":[7.712141,45.382954],"type":"Point"}
}