{
  "type": "Feature",
  "properties": {
    "iso:country":"IT",
    "sg:address":"9, Via Piemonte 23018 Talamona",
    "sg:city":"Talamona",
    "sg:classifiers":[
        {
            "category":"Home & Garden",
            "subcategory":"Home Furnishings",
            "type":"Retail Goods"
        }
    ],
    "sg:phone":"+39 0342 610869",
    "sg:postcode":"23018",
    "sg:province":"Sondrio",
    "sg:tags":[
        "household"
    ],
    "wof:name":"Strato S.r.l.",
    "wof:placetype":"venue"
},
  "geometry": {"coordinates":[9.601852,46.13588],"type":"Point"}
}