{
  "type": "Feature",
  "properties": {
    "addr:full":"20135 Milano Milano Milano 20135",
    "addr:postcode":"20135;20135",
    "iso:country":"IT",
    "sg:address":"20135 Milano",
    "sg:city":"Milano",
    "sg:orig_category":"Cine-foto-ottica",
    "sg:phone":"+39 02 5412 1381",
    "sg:postcode":"20135",
    "sg:province":"Milano",
    "wof:name":"Gruppo Bp Srl",
    "wof:placetype":"venue"
},
  "geometry": {"coordinates":[9.1798696518,45.4820709229],"type":"Point"}
}