{
  "type": "Feature",
  "properties": {
    "addr:full":"20142 Milano Milano Milano 20142",
    "addr:postcode":"20142;20142",
    "iso:country":"IT",
    "sg:address":"20142 Milano",
    "sg:city":"Milano",
    "sg:orig_category":"Servizi E Lavori Per Arredamento E Industria Del Legno. Servizi E Lavori Per Edilizia E Lavori Pubblici",
    "sg:phone":"+39 02 813 4926",
    "sg:postcode":"20142",
    "sg:province":"Milano",
    "wof:name":"Borghese Arnaldo",
    "wof:placetype":"venue"
},
  "geometry": {"coordinates":[9.226432,45.488861],"type":"Point"}
}