{
  "type": "Feature",
  "properties": {
    "iso:country":"IT",
    "sg:address":"84028 Serre",
    "sg:city":"Serre",
    "sg:orig_category":"Prodotti Alimentari",
    "sg:phone":"+39 0828 974396",
    "sg:postcode":"84028",
    "sg:province":"Salerno",
    "wof:name":"Caseificio 'la Villanella'",
    "wof:placetype":"venue"
},
  "geometry": {"coordinates":[14.9108915329,40.6314468384],"type":"Point"}
}