{
  "type": "Feature",
  "properties": {
    "iso:country":"IT",
    "sg:address":"Via Vicinale 2743, San Giorgio, 47020 Cesena, Fo",
    "sg:classifiers":[
        {
            "category":"Banks & Credit Unions",
            "subcategory":"Bank",
            "type":"Services"
        }
    ],
    "sg:postcode":"47020",
    "sg:province":"Forl\u00ec-Cesena",
    "wof:name":"Banca Di Credito Cooperativo S. Giorgio Di Cesena",
    "wof:placetype":"venue"
},
  "geometry": {"coordinates":[11.980461,43.994766],"type":"Point"}
}