{
  "type": "Feature",
  "properties": {
    "addr:full":"13045 Gattinara Gattinara Vercelli 13045",
    "addr:housenumber":"13045",
    "addr:postcode":"13045",
    "addr:street":"Gattinara",
    "iso:country":"IT",
    "sg:address":"13045 Gattinara",
    "sg:city":"Gattinara",
    "sg:orig_category":"Serramenti Ed Infissi",
    "sg:phone":"+39 0163 826847",
    "sg:postcode":"13045",
    "sg:province":"Vercelli",
    "sg:website":"http://www.redlegno.com",
    "wof:name":"Red Legno Di Andreoni Sergio",
    "wof:placetype":"venue"
},
  "geometry": {"coordinates":[8.368611,45.618927],"type":"Point"}
}