{
  "type": "Feature",
  "properties": {
    "iso:country":"IT",
    "sg:address":"59100 Prato",
    "sg:city":"Prato",
    "sg:orig_category":"Cancelli, Porte E Portoni Automatici E Telecomandati",
    "sg:phone":"+39 0574 570386",
    "sg:postcode":"59100",
    "sg:province":"Prato",
    "wof:name":"Blindotec Snc Di Mensi Guido",
    "wof:placetype":"venue"
},
  "geometry": {"coordinates":[11.09893,43.870312],"type":"Point"}
}