{
  "type": "Feature",
  "properties": {
    "iso:country":"IT",
    "sg:address":"73010 Lequile",
    "sg:city":"Lequile",
    "sg:orig_category":"Arredo Cucina Ed Elettrodomestici. Elettrodomestici",
    "sg:phone":"+39 0832 261071",
    "sg:postcode":"73010",
    "sg:province":"Lecce",
    "wof:name":"Bit Elettronica Di Belardo Edmondo",
    "wof:placetype":"venue"
},
  "geometry": {"coordinates":[18.143255,40.298973],"type":"Point"}
}