{
  "type": "Feature",
  "properties": {
    "addr:full":"25065 Lumezzane Lumezzane Brescia 25065",
    "addr:postcode":"25065;25065",
    "iso:country":"IT",
    "sg:address":"25065 Lumezzane",
    "sg:city":"Lumezzane",
    "sg:orig_category":"Metalli E Leghe",
    "sg:phone":"+39 030 827542",
    "sg:postcode":"25065",
    "sg:province":"Brescia",
    "wof:name":"M.a.m. Metalli Srl",
    "wof:placetype":"venue"
},
  "geometry": {"coordinates":[10.2212753296,45.6053657532],"type":"Point"}
}