{
  "type": "Feature",
  "properties": {
    "iso:country":"IT",
    "sg:address":"24044 Dalmine",
    "sg:city":"Dalmine",
    "sg:orig_category":"Servizi Ausiliari Di Analisi, Controllo E Ricerca",
    "sg:phone":"+39 035 370336",
    "sg:postcode":"24044",
    "sg:province":"Bergamo",
    "wof:name":"C C T Centro Controlli Tecnici (s.r.l.)",
    "wof:placetype":"venue"
},
  "geometry": {"coordinates":[9.60613,45.647449],"type":"Point"}
}