{
  "type": "Feature",
  "properties": {
    "addr:full":"72021 Francavilla Fontana Francavilla Fontana Brindisi 72021",
    "addr:postcode":"72021;72021",
    "iso:country":"IT",
    "sg:address":"72021 Francavilla Fontana",
    "sg:city":"Francavilla Fontana",
    "sg:orig_category":"Chiese Ed Associazioni Religiose",
    "sg:phone":"+39 0831 812676",
    "sg:postcode":"72021",
    "sg:province":"Brindisi",
    "wof:name":"Parrocchia Ortodossa",
    "wof:placetype":"venue"
},
  "geometry": {"coordinates":[17.587845,40.530899],"type":"Point"}
}