{
  "type": "Feature",
  "properties": {
    "iso:country":"IT",
    "sg:address":"22066 Mariano Comense",
    "sg:city":"Mariano Comense",
    "sg:orig_category":"Servizi E Lavori Per Arredamento E Industria Del Legno. Arte Ed Artigianato Artistico",
    "sg:phone":"+39 031 747120",
    "sg:postcode":"22066",
    "sg:province":"Como",
    "wof:name":"Pellegatta Mario",
    "wof:placetype":"venue"
},
  "geometry": {"coordinates":[9.170578,45.699463],"type":"Point"}
}