{
  "type": "Feature",
  "properties": {
    "addr:full":"20017 Rho Rho Milano 20017",
    "addr:postcode":"20017;20017",
    "iso:country":"IT",
    "sg:address":"20017 Rho",
    "sg:city":"Rho",
    "sg:orig_category":"Motori Ed Organi Di Trasmissione",
    "sg:phone":"+39 02 9350 1135",
    "sg:postcode":"20017",
    "sg:province":"Milano",
    "wof:name":"Gears (s.p.a.)",
    "wof:placetype":"venue"
},
  "geometry": {"coordinates":[9.0511856079,45.5252227783],"type":"Point"}
}