{
  "type": "Feature",
  "properties": {
    "iso:country":"IT",
    "sg:address":"Via Bellaria 61041 Acqualagna",
    "sg:city":"Acqualagna",
    "sg:classifiers":[
        {
            "category":"Shopping",
            "subcategory":"Clothing, Apparel, & Fashions",
            "type":"Retail Goods"
        }
    ],
    "sg:phone":"+39 0721 798879",
    "sg:postcode":"61041",
    "sg:province":"Pesaro E Urbino",
    "sg:tags":[
        "clothes"
    ],
    "wof:name":"Confezioni Treci (s.r.l.)",
    "wof:placetype":"venue"
},
  "geometry": {"coordinates":[12.621964,43.612782],"type":"Point"}
}