{
  "type": "Feature",
  "properties": {
    "iso:country":"IT",
    "sg:address":"20144 Milano",
    "sg:city":"Milano",
    "sg:orig_category":"Trasporti E Spedizioni Merci",
    "sg:phone":"+39 02 485561",
    "sg:postcode":"20144",
    "sg:province":"Milano",
    "sg:website":"http://www.transco.it",
    "wof:name":"Transco Srl",
    "wof:placetype":"venue"
},
  "geometry": {"coordinates":[9.164654,45.466133],"type":"Point"}
}