{
  "type": "Feature",
  "properties": {
    "iso:country":"IT",
    "sg:address":"06034 Foligno",
    "sg:city":"Foligno",
    "sg:orig_category":"Carrozzelle E Poltrone Per Infermi",
    "sg:phone":"+39 0742 22927",
    "sg:postcode":"06034",
    "sg:province":"Perugia",
    "sg:website":"http://www.ormesa.com",
    "wof:name":"Ormesa Di Menichini Luigi & C.",
    "wof:placetype":"venue"
},
  "geometry": {"coordinates":[12.782477,42.977386],"type":"Point"}
}