{
  "type": "Feature",
  "properties": {
    "iso:country":"IT",
    "sg:address":"50127 Firenze",
    "sg:city":"Firenze",
    "sg:classifiers":[
        {
            "category":"Education",
            "subcategory":"School",
            "type":"Public Place"
        }
    ],
    "sg:phone":"+39 055 439 3506",
    "sg:postcode":"50127",
    "sg:province":"Firenze",
    "sg:tags":[
        "small",
        "breeding",
        "livestock",
        "animal",
        "fishing"
    ],
    "wof:name":"Toscana Molluschi Spa",
    "wof:placetype":"venue"
},
  "geometry": {"coordinates":[11.224044,43.803814],"type":"Point"}
}