{
  "type": "Feature",
  "properties": {
    "addr:full":"40068 San Lazzaro Di Savena San Lazzaro Bologna 40068",
    "addr:housenumber":"40068",
    "addr:postcode":"40068",
    "addr:street":"San;San;Bologna",
    "iso:country":"IT",
    "sg:address":"40068 San Lazzaro Di Savena",
    "sg:city":"San Lazzaro",
    "sg:orig_category":"Apparecchiature Ed Attrezzature Meccaniche",
    "sg:phone":"+39 051 625 8101",
    "sg:postcode":"40068",
    "sg:province":"Bologna",
    "wof:name":"Sixten Srl",
    "wof:placetype":"venue"
},
  "geometry": {"coordinates":[11.427596,44.46236],"type":"Point"}
}