{
  "type": "Feature",
  "properties": {
    "iso:country":"IT",
    "sg:address":"83050 San Potito Ultra",
    "sg:city":"San Potito Ultra",
    "sg:orig_category":"Imprese Di Costruzioni Civili Ed Industriali. Servizi E Lavori Per Ecologia E Smaltimento Rifiuti",
    "sg:phone":"+39 0825 981935",
    "sg:postcode":"83050",
    "sg:province":"Avellino",
    "sg:website":"http://www.ecologia2000.it",
    "wof:name":"Eco Global System Srl",
    "wof:placetype":"venue"
},
  "geometry": {"coordinates":[14.872072,40.92889],"type":"Point"}
}