{
  "type": "Feature",
  "properties": {
    "iso:country":"IT",
    "sg:address":"92021 Aragona",
    "sg:city":"Aragona",
    "sg:orig_category":"Servizi E Lavori Per Agricoltura E Zootecnia. Animali Domestici",
    "sg:phone":"+39 0349 282 9993",
    "sg:postcode":"92021",
    "sg:province":"Agrigento",
    "wof:name":"Baldo Ludovico",
    "wof:placetype":"venue"
},
  "geometry": {"coordinates":[13.601546,37.411205],"type":"Point"}
}