{
  "type": "Feature",
  "properties": {
    "addr:full":"20141 Milano Milano Milano 20141",
    "addr:postcode":"20141;20141",
    "iso:country":"IT",
    "sg:address":"20141 Milano",
    "sg:city":"Milano",
    "sg:orig_category":"Fotografia - Servizi, Studi, Sviluppo E Stampa",
    "sg:phone":"+39 02 8951 6808",
    "sg:postcode":"20141",
    "sg:province":"Milano",
    "wof:name":"Foto G. & A. Ranzini Srl",
    "wof:placetype":"venue"
},
  "geometry": {"coordinates":[9.1817436218,45.4397125244],"type":"Point"}
}