{
  "type": "Feature",
  "properties": {
    "iso:country":"IT",
    "sg:address":"50126 Sesto Fiorentino",
    "sg:orig_category":"Cosmetici, Prodotti Di Bellezza E Di Igiene",
    "sg:phone":"+39 055 421 1799",
    "sg:postcode":"50126",
    "sg:province":"Firenze",
    "wof:name":"Derbe Srl",
    "wof:placetype":"venue"
},
  "geometry": {"coordinates":[11.248666,43.771542],"type":"Point"}
}