{
  "type": "Feature",
  "properties": {
    "addr:full":"20056 Trezzo Sull'adda Milano 20056",
    "addr:postcode":"20056;20056",
    "iso:country":"IT",
    "sg:address":"20056 Trezzo Sull'adda",
    "sg:orig_category":"Frigotecnica, Apparecchiature E Servizi. Forniture Alle Strutture Ricettive",
    "sg:phone":"+39 02 9093 8825",
    "sg:postcode":"20056",
    "sg:province":"Milano",
    "wof:name":"O.m.f. Dei Fratelli Furiosi Ernesto & Giuseppe Snc",
    "wof:placetype":"venue"
},
  "geometry": {"coordinates":[9.521314621,45.6070289612],"type":"Point"}
}