{
  "type": "Feature",
  "properties": {
    "iso:country":"IT",
    "sg:address":"22100 Como",
    "sg:city":"Como",
    "sg:orig_category":"Tessuti E Stoffe. Filati E Materie Prime Tessili",
    "sg:phone":"+39 031 261667",
    "sg:postcode":"22100",
    "sg:province":"Como",
    "wof:name":"Texseta S.r.l.",
    "wof:placetype":"venue"
},
  "geometry": {"coordinates":[9.092748,45.799282],"type":"Point"}
}