{
  "type": "Feature",
  "properties": {
    "addr:full":"35030 Selvazzano Dentro Selvazzano Dentro Padova 35030",
    "addr:postcode":"35030;35030",
    "iso:country":"IT",
    "sg:address":"35030 Selvazzano Dentro",
    "sg:city":"Selvazzano Dentro",
    "sg:orig_category":"Accessori Moda D'abbigliamento",
    "sg:phone":"+39 049 868 5520",
    "sg:postcode":"35030",
    "sg:province":"Padova",
    "wof:name":"R.g.z. Di Zuin S. & C. S.n.c.",
    "wof:placetype":"venue"
},
  "geometry": {"coordinates":[11.813714,45.392075],"type":"Point"}
}