{
  "type": "Feature",
  "properties": {
    "addr:full":"22100 Como Como Como 22100",
    "addr:postcode":"22100;22100",
    "iso:country":"IT",
    "sg:address":"22100 Como",
    "sg:city":"Como",
    "sg:orig_category":"Disegno, Grafica E Belle Arti - Articoli",
    "sg:phone":"+39 031 271121",
    "sg:postcode":"22100",
    "sg:province":"Como",
    "wof:name":"La Fototecnica Ballarate Srl",
    "wof:placetype":"venue"
},
  "geometry": {"coordinates":[9.084923,45.80785],"type":"Point"}
}