{
  "type": "Feature",
  "properties": {
    "addr:full":"31010 Ormelle Treviso 31010",
    "addr:postcode":"31010;31010",
    "iso:country":"IT",
    "sg:address":"31010 Ormelle",
    "sg:orig_category":"Materiali Edili",
    "sg:phone":"+39 0422 851118",
    "sg:postcode":"31010",
    "sg:province":"Treviso",
    "wof:name":"Nenzi Geom. Claudio",
    "wof:placetype":"venue"
},
  "geometry": {"coordinates":[12.418502,45.730377],"type":"Point"}
}