{
  "type": "Feature",
  "properties": {
    "addr:full":"20026 Novate Milanese Novate Milanese Milano 20026",
    "addr:postcode":"20026;20026",
    "iso:country":"IT",
    "sg:address":"20026 Novate Milanese",
    "sg:city":"Novate Milanese",
    "sg:classifiers":[
        {
            "category":"Health Services",
            "subcategory":"Health Practitioner",
            "type":"Services"
        }
    ],
    "sg:phone":"+39 02 3820 1713",
    "sg:postcode":"20026",
    "sg:province":"Milano",
    "sg:tags":[
        "medici"
    ],
    "wof:name":"Iudica Francesco",
    "wof:placetype":"venue"
},
  "geometry": {"coordinates":[9.126911,45.53347],"type":"Point"}
}