{
  "type": "Feature",
  "properties": {
    "iso:country":"IT",
    "sg:address":"50127 Firenze",
    "sg:city":"Firenze",
    "sg:classifiers":[
        {
            "category":"Professional",
            "subcategory":"Advertising",
            "type":"Services"
        }
    ],
    "sg:phone":"+39 055 433540",
    "sg:postcode":"50127",
    "sg:province":"Firenze",
    "sg:tags":[
        "marketing",
        "communication"
    ],
    "wof:name":"Ubv Pubblicit\u00c0 Di Biagini Mauro",
    "wof:placetype":"venue"
},
  "geometry": {"coordinates":[11.230584,43.79604],"type":"Point"}
}