{
  "type": "Feature",
  "properties": {
    "addr:full":"09032 Assemini Assemini Cagliari 09032",
    "addr:postcode":"09032;09032",
    "iso:country":"IT",
    "sg:address":"09032 Assemini",
    "sg:city":"Assemini",
    "sg:orig_category":"Materiali Edili",
    "sg:phone":"+39 070 24651",
    "sg:postcode":"09032",
    "sg:province":"Cagliari",
    "wof:name":"Sanac Spa",
    "wof:placetype":"venue"
},
  "geometry": {"coordinates":[9.024555,39.226257],"type":"Point"}
}