{
  "type": "Feature",
  "properties": {
    "addr:full":"35031 Abano Terme Abano Terme Padova 35031",
    "addr:postcode":"35031;35031",
    "iso:country":"IT",
    "sg:address":"35031 Abano Terme",
    "sg:city":"Abano Terme",
    "sg:orig_category":"Alberghi",
    "sg:phone":"+39 049 866 8057",
    "sg:postcode":"35031",
    "sg:province":"Padova",
    "wof:name":"Terme Salus Srl",
    "wof:placetype":"venue"
},
  "geometry": {"coordinates":[11.778817,45.351967],"type":"Point"}
}