{
  "type": "Feature",
  "properties": {
    "iso:country":"IT",
    "sg:address":"45015 Corbola",
    "sg:city":"Corbola",
    "sg:orig_category":"Lavanderie",
    "sg:phone":"+39 0426 950070",
    "sg:postcode":"45015",
    "sg:province":"Rovigo",
    "wof:name":"Tre B Di Braga Claudio & C. Snc",
    "wof:placetype":"venue"
},
  "geometry": {"coordinates":[12.110486,44.998528],"type":"Point"}
}