{
  "type": "Feature",
  "properties": {
    "iso:country":"IT",
    "sg:address":"72100 Brindisi",
    "sg:city":"Brindisi",
    "sg:orig_category":"Impiantistica E Prodotti Tecnologici Per Edilizia. Servizi Ausiliari Di Sorveglianza, Manutenzione E Pulizia",
    "sg:phone":"+39 0831 546985",
    "sg:postcode":"72100",
    "sg:province":"Brindisi",
    "wof:name":"C.o.m.i.n.a. Srl",
    "wof:placetype":"venue"
},
  "geometry": {"coordinates":[17.882084,40.612133],"type":"Point"}
}