{
  "type": "Feature",
  "properties": {
    "addr:full":"47900 Rimini Rimini Rimini 47900",
    "addr:postcode":"47900;47900",
    "iso:country":"IT",
    "sg:address":"47900 Rimini",
    "sg:city":"Rimini",
    "sg:orig_category":"Servizi Per Lo Sport E Il Tempo Libero. Servizi Al Turismo",
    "sg:phone":"+39 0541 372064",
    "sg:postcode":"47900",
    "sg:province":"Rimini",
    "wof:name":"Fiabilandia",
    "wof:placetype":"venue"
},
  "geometry": {"coordinates":[12.609886,44.034248],"type":"Point"}
}