{
  "type": "Feature",
  "properties": {
    "addr:full":"Via R. Perino 49 10080 Busano Busano Torino 10080",
    "addr:housenumber":"49",
    "addr:postcode":"10080;10080",
    "addr:street":"Via R. Perino",
    "iso:country":"IT",
    "sg:address":"Via R. Perino 49 10080 Busano",
    "sg:city":"Busano",
    "sg:classifiers":[
        {
            "category":"Social Services",
            "subcategory":"Job Training",
            "type":"Services"
        }
    ],
    "sg:phone":"+39 0124 479011",
    "sg:postcode":"10080",
    "sg:province":"Torino",
    "sg:tags":[
        "press",
        "hot",
        "stamping"
    ],
    "sg:website":"www.hotroll.it",
    "wof:name":"Hot Roll Srl",
    "wof:placetype":"venue"
},
  "geometry": {"coordinates":[7.686619,45.07056],"type":"Point"}
}