{
  "type": "Feature",
  "properties": {
    "addr:full":"42049 Sant'ilario D'enza Reggio Nell'Emilia 42049",
    "addr:postcode":"42049;42049",
    "iso:country":"IT",
    "sg:address":"42049 Sant'ilario D'enza",
    "sg:orig_category":"Macchine, Impianti E Forniture Per Industria Grafica, Cartaria E Cartotecnica. Automazione E Macchine Per Ufficio",
    "sg:phone":"+39 0522 909876",
    "sg:postcode":"42049",
    "sg:province":"Reggio Nell'Emilia",
    "wof:name":"L.p.g. Line Project Group Sas",
    "wof:placetype":"venue"
},
  "geometry": {"coordinates":[10.478356,44.756016],"type":"Point"}
}