{
  "type": "Feature",
  "properties": {
    "iso:country":"IT",
    "sg:address":"20098 San Giuliano Milanese",
    "sg:city":"San Giuliano Milanese",
    "sg:orig_category":"Servizi Per Lo Sport E Il Tempo Libero. Servizi Vari Di Interesse Pubblico",
    "sg:phone":"+39 02 9824 5555",
    "sg:postcode":"20098",
    "sg:province":"Milano",
    "wof:name":"Agenzia Ippica Paolo Rossi E C. Snc",
    "wof:placetype":"venue"
},
  "geometry": {"coordinates":[9.244863,45.393761],"type":"Point"}
}