{
  "type": "Feature",
  "properties": {
    "iso:country":"IT",
    "sg:address":"76, Via Xx Settembre 21032 Caravate",
    "sg:city":"Caravate",
    "sg:classifiers":[
        {
            "category":"Communications",
            "subcategory":"Television Station",
            "type":"Services"
        }
    ],
    "sg:phone":"+39 0332 601349",
    "sg:postcode":"21032",
    "sg:province":"Varese",
    "sg:tags":[
        "audio-visual"
    ],
    "wof:name":"Marostica",
    "wof:placetype":"venue"
},
  "geometry": {"coordinates":[8.826385,45.817604],"type":"Point"}
}