{
  "type": "Feature",
  "properties": {
    "addr:full":"20146 Milano Milano Milano 20146",
    "addr:postcode":"20146;20146",
    "iso:country":"IT",
    "sg:address":"20146 Milano",
    "sg:city":"Milano",
    "sg:orig_category":"Non-classified Establishments",
    "sg:phone":"+39 02 428136",
    "sg:postcode":"20146",
    "sg:province":"Milano",
    "wof:name":"Il Palanchino S.a.s. Di Pecchi Marco & C.",
    "wof:placetype":"venue"
},
  "geometry": {"coordinates":[9.14784,45.456547],"type":"Point"}
}