{
  "type": "Feature",
  "properties": {
    "iso:country":"IT",
    "sg:address":"25030 Torbole Casaglia",
    "sg:city":"Torbole Casaglia",
    "sg:orig_category":"Macchine, Impianti Ed Attrezzature Per Industria Alimentare E Bevande. Elettrodomestici. Macchine E Impianti Per Attivita' Commerciali Ed Artigianali",
    "sg:phone":"+39 030 265 0828",
    "sg:postcode":"25030",
    "sg:province":"Brescia",
    "wof:name":"Civini Bilance Di Civini Remo & C. Snc",
    "wof:placetype":"venue"
},
  "geometry": {"coordinates":[10.126692,45.518864],"type":"Point"}
}