{
  "type": "Feature",
  "properties": {
    "iso:country":"IT",
    "sg:address":"50056 Capraia E Limite",
    "sg:orig_category":"Calzature - Produzione E Ingrosso",
    "sg:phone":"+39 0571 583610",
    "sg:postcode":"50056",
    "sg:province":"Firenze",
    "sg:website":"http://www.danton-caparrini.it",
    "wof:name":"Danton Srl",
    "wof:placetype":"venue"
},
  "geometry": {"coordinates":[11.192734,43.842072],"type":"Point"}
}