{
  "type": "Feature",
  "properties": {
    "addr:full":"2, Via Duchi D'aosta 33100 Udine Udine Udine 33100",
    "addr:postcode":"33100;33100",
    "addr:street":"Via Duchi D'Aosta",
    "iso:country":"IT",
    "sg:address":"2, Via Duchi D'aosta 33100 Udine",
    "sg:city":"Udine",
    "sg:classifiers":[
        {
            "category":"Utilities",
            "subcategory":"Electric",
            "type":"Services"
        }
    ],
    "sg:phone":"+39 0432 517311",
    "sg:postcode":"33100",
    "sg:province":"Udine",
    "sg:tags":[
        "energy"
    ],
    "wof:name":"Cafc S.p.a.",
    "wof:placetype":"venue"
},
  "geometry": {"coordinates":[13.233174,46.057491],"type":"Point"}
}