{
  "type": "Feature",
  "properties": {
    "addr:full":"26016 Spino D'adda Cremona 26016",
    "addr:postcode":"26016;26016",
    "iso:country":"IT",
    "sg:address":"26016 Spino D'adda",
    "sg:orig_category":"Automobili E Mezzi Di Trasporto",
    "sg:phone":"+39 0373 980696",
    "sg:postcode":"26016",
    "sg:province":"Cremona",
    "wof:name":"Moroni Autoservice (s.r.l.)",
    "wof:placetype":"venue"
},
  "geometry": {"coordinates":[9.474491,45.403347],"type":"Point"}
}