{
  "type": "Feature",
  "properties": {
    "addr:full":"Via Monchio 3 41042 Fiorano Modenese Fiorano Modenese Modena 41042",
    "addr:housenumber":"3",
    "addr:postcode":"41042;41042",
    "addr:street":"Via Monchio",
    "iso:country":"IT",
    "sg:address":"Via Monchio 3 41042 Fiorano Modenese",
    "sg:city":"Fiorano Modenese",
    "sg:classifiers":[
        {
            "category":"Home & Garden",
            "subcategory":"Building Materials",
            "type":"Retail Goods"
        }
    ],
    "sg:phone":"+39 0536 911406",
    "sg:postcode":"41042",
    "sg:province":"Modena",
    "sg:tags":[
        "tile",
        "ceramic"
    ],
    "sg:website":"www.viki-poliedro.it",
    "wof:name":"Viki Ceramiche Artistiche Srl",
    "wof:placetype":"venue"
},
  "geometry": {"coordinates":[10.824517,44.559025],"type":"Point"}
}