{
  "type": "Feature",
  "properties": {
    "iso:country":"IT",
    "sg:address":"36060 Casoni",
    "sg:orig_category":"Macchine Utensili E Impianti",
    "sg:postcode":"36060",
    "sg:province":"Vicenza",
    "wof:name":"Electro Mem",
    "wof:placetype":"venue"
},
  "geometry": {"coordinates":[11.618756,45.48188],"type":"Point"}
}