{
  "type": "Feature",
  "properties": {
    "iso:country":"IT",
    "sg:address":"20020 Arese",
    "sg:city":"Arese",
    "sg:orig_category":"Macchine Ed Impianti Per Edilizia E Lavori Pubblici",
    "sg:phone":"+39 02 9358 2033",
    "sg:postcode":"20020",
    "sg:province":"Milano",
    "wof:name":"Samedil (s.r.l.)",
    "wof:placetype":"venue"
},
  "geometry": {"coordinates":[9.087011,45.536728],"type":"Point"}
}