{
  "type": "Feature",
  "properties": {
    "iso:country":"IT",
    "sg:address":"Via Nazionale 1 24060 Entratico",
    "sg:city":"Entratico",
    "sg:classifiers":[
        {
            "category":"Manufacturing",
            "subcategory":"Lumber",
            "type":"Manufacturing & Wholesale Goods"
        }
    ],
    "sg:phone":"+39 39035942031",
    "sg:postcode":"24060",
    "sg:province":"Bergamo",
    "sg:tags":[
        "wood"
    ],
    "wof:name":"Rivadossi Matteo E Figlio Snc",
    "wof:placetype":"venue"
},
  "geometry": {"coordinates":[9.870362,45.707474],"type":"Point"}
}