{
  "type": "Feature",
  "properties": {
    "iso:country":"IT",
    "sg:address":"16040 San Colombano Certenoli",
    "sg:city":"Ne",
    "sg:orig_category":"Non-classified Establishments",
    "sg:phone":"+39 0185 358328",
    "sg:postcode":"16040",
    "sg:province":"Genova",
    "wof:name":"Casa Del Giunco Di G. Rivara & C. Snc",
    "wof:placetype":"venue"
},
  "geometry": {"coordinates":[9.288045,44.379593],"type":"Point"}
}