{
  "type": "Feature",
  "properties": {
    "addr:full":"45100 Rovigo Rovigo Rovigo 45100",
    "addr:postcode":"45100;45100",
    "iso:country":"IT",
    "sg:address":"45100 Rovigo",
    "sg:city":"Rovigo",
    "sg:orig_category":"Zootecnia E Pesca, Allevamento Piccoli Animali. Servizi Per Lo Sport E Il Tempo Libero",
    "sg:phone":"+39 0425 30130",
    "sg:postcode":"45100",
    "sg:province":"Rovigo",
    "wof:name":"Centro Equitazione 'il Bosco'",
    "wof:placetype":"venue"
},
  "geometry": {"coordinates":[11.814462,45.073788],"type":"Point"}
}