{
  "type": "Feature",
  "properties": {
    "addr:full":"3, Via I Maggio 37069 Villafranca Di Verona Villafranca di Verona Verona 37069",
    "addr:postcode":"37069;37069",
    "addr:street":"Via I Maggio;Verona",
    "iso:country":"IT",
    "sg:address":"3, Via I Maggio 37069 Villafranca Di Verona",
    "sg:city":"Villafranca di Verona",
    "sg:classifiers":[
        {
            "category":"Bars & Pubs",
            "subcategory":"Nightclub",
            "type":"Food & Drink"
        }
    ],
    "sg:phone":"+39 045 630 0662",
    "sg:postcode":"37069",
    "sg:province":"Verona",
    "sg:tags":[
        "cake",
        "bread"
    ],
    "wof:name":"Dalfini (s.p.a.)",
    "wof:placetype":"venue"
},
  "geometry": {"coordinates":[10.95435,45.421623],"type":"Point"}
}