{
  "type": "Feature",
  "properties": {
    "addr:full":"Ponte Doria Andrea 16126 Genova Genova Genova 16126",
    "addr:postcode":"16126;16126",
    "addr:street":"Ponte;Andrea",
    "iso:country":"IT",
    "sg:address":"Ponte Doria Andrea 16126 Genova",
    "sg:city":"Genova",
    "sg:classifiers":[
        {
            "category":"Marine",
            "type":"Transportation"
        }
    ],
    "sg:phone":"+39 010 246 8868",
    "sg:postcode":"16126",
    "sg:province":"Genova",
    "sg:tags":[
        "transport",
        "sea"
    ],
    "wof:name":"Italian Scandinavian Ships Supply Ltd. (s.r.l.)",
    "wof:placetype":"venue"
},
  "geometry": {"coordinates":[8.933989,44.407063],"type":"Point"}
}