{
  "type": "Feature",
  "properties": {
    "iso:country":"IT",
    "sg:address":"104, V. Delle Pantanelle 04011 Aprilia",
    "sg:city":"Aprilia",
    "sg:classifiers":[
        {
            "category":"Manufacturing",
            "subcategory":"Rubber & Plastics",
            "type":"Manufacturing & Wholesale Goods"
        }
    ],
    "sg:phone":"+39 39069253800",
    "sg:postcode":"04011",
    "sg:province":"Latina",
    "sg:tags":[
        "packaging",
        "material",
        "-"
    ],
    "sg:website":"http://www.paginegialle.it/giubileo2000",
    "wof:name":"Giubileo 2000",
    "wof:placetype":"venue"
},
  "geometry": {"coordinates":[12.6933164597,41.5209274292],"type":"Point"}
}