{
  "type": "Feature",
  "properties": {
    "iso:country":"IT",
    "sg:address":"90145 Palermo",
    "sg:city":"Palermo",
    "sg:orig_category":"Impiantistica E Prodotti Tecnologici Per Edilizia. Serramenti Ed Infissi",
    "sg:phone":"+39 091 226244",
    "sg:postcode":"90145",
    "sg:province":"Palermo",
    "sg:website":"http://www.dadotecna.com",
    "wof:name":"Dado Tecna Di Dom\u00c8 Paolo & C. Sas",
    "wof:placetype":"venue"
},
  "geometry": {"coordinates":[13.306756,38.139172],"type":"Point"}
}