{
  "type": "Feature",
  "properties": {
    "addr:full":"10078 Venaria Torino 10078",
    "addr:postcode":"10078;10078",
    "iso:country":"IT",
    "sg:address":"10078 Venaria",
    "sg:orig_category":"Servizi Per Lo Sport E Il Tempo Libero. Servizi Al Turismo. Acqua, Luce, Gas E Societa' Di Esercizio Pubblico",
    "sg:phone":"+39 011 495795",
    "sg:postcode":"10078",
    "sg:province":"Torino",
    "wof:name":"Azienda Regionale Tenuta La Mandria",
    "wof:placetype":"venue"
},
  "geometry": {"coordinates":[7.622236,45.138233],"type":"Point"}
}