{
  "type": "Feature",
  "properties": {
    "iso:country":"IT",
    "sg:address":"50013 Campi Bisenzio",
    "sg:city":"Campi Bisenzio",
    "sg:orig_category":"Attrezzature E Forniture Per Officine Riparazione E Servizi Ausiliari",
    "sg:phone":"+39 055 896 4304",
    "sg:postcode":"50013",
    "sg:province":"Firenze",
    "wof:name":"Autosystem Srl",
    "wof:placetype":"venue"
},
  "geometry": {"coordinates":[11.149591,43.81638],"type":"Point"}
}