{
  "type": "Feature",
  "properties": {
    "addr:full":"1, Via Borghi 22060 Cucciago Cucciago Como 22060",
    "addr:postcode":"22060;22060",
    "addr:street":"Via Borghi",
    "iso:country":"IT",
    "sg:address":"1, Via Borghi 22060 Cucciago",
    "sg:city":"Cucciago",
    "sg:classifiers":[
        {
            "category":"Home & Garden",
            "subcategory":"Home Furnishings",
            "type":"Retail Goods"
        }
    ],
    "sg:phone":"+39 39031787306",
    "sg:postcode":"22060",
    "sg:province":"Como",
    "sg:tags":[
        "household"
    ],
    "wof:name":"Poli L'ottone (s.n.c.)",
    "wof:placetype":"venue"
},
  "geometry": {"coordinates":[9.107701,45.741982],"type":"Point"}
}