{
  "type": "Feature",
  "properties": {
    "addr:full":"174, Strada Statale Romea 30015 Chioggia Chioggia Venezia 30015",
    "addr:postcode":"30015;30015",
    "addr:street":"Strada Statale Romea",
    "iso:country":"IT",
    "sg:address":"174, Strada Statale Romea 30015 Chioggia",
    "sg:city":"Chioggia",
    "sg:classifiers":[
        {
            "category":"Food & Beverages",
            "subcategory":"Groceries & Convenience Stores",
            "type":"Retail Goods"
        }
    ],
    "sg:phone":"+39 041 554 0755",
    "sg:postcode":"30015",
    "sg:province":"Venezia",
    "sg:tags":[
        "product",
        "related"
    ],
    "wof:name":"De A. Mare (s.r.l.)",
    "wof:placetype":"venue"
},
  "geometry": {"coordinates":[12.2359991074,45.2105827332],"type":"Point"}
}