{
  "type": "Feature",
  "properties": {
    "iso:country":"IT",
    "sg:address":"11, Via Callalta 31046 Oderzo",
    "sg:city":"Oderzo",
    "sg:classifiers":[
        {
            "category":"Shopping",
            "type":"Retail Goods"
        }
    ],
    "sg:phone":"+39 0422 852012",
    "sg:postcode":"31046",
    "sg:province":"Treviso",
    "sg:tags":[
        "finished",
        "-",
        "metallic"
    ],
    "wof:name":"Model Stampi S.r.l.",
    "wof:placetype":"venue"
},
  "geometry": {"coordinates":[12.4723844528,45.7428627014],"type":"Point"}
}