{
  "type": "Feature",
  "properties": {
    "addr:full":"84098 Picciola Salerno 84098",
    "addr:postcode":"84098;84098",
    "addr:street":"Picciola",
    "iso:country":"IT",
    "sg:address":"84098 Picciola",
    "sg:orig_category":"Macchine, Impianti Ed Attrezzature Per Abbigliamento E Pelletterie. Macchine E Impianti Per Attivita' Commerciali Ed Artigianali",
    "sg:phone":"+39 089 203144",
    "sg:postcode":"84098",
    "sg:province":"Salerno",
    "wof:name":"Bertolini Srl",
    "wof:placetype":"venue"
},
  "geometry": {"coordinates":[14.765912,40.677956],"type":"Point"}
}