{
  "type": "Feature",
  "properties": {
    "iso:country":"IT",
    "sg:address":"25050 Monte Isola",
    "sg:city":"Monte Isola",
    "sg:orig_category":"Forniture Per Agricoltura E Zootecnia. Forniture Per Attivita' Industriali",
    "sg:phone":"+39 030 982 5217",
    "sg:postcode":"25050",
    "sg:province":"Brescia",
    "wof:name":"Novali Umberto",
    "wof:placetype":"venue"
},
  "geometry": {"coordinates":[10.0809516907,45.7172164917],"type":"Point"}
}