{
  "type": "Feature",
  "properties": {
    "iso:country":"IT",
    "sg:address":"26, Localita' Gambrinus 31020 San Polo Di Piave",
    "sg:city":"San Polo di Piave",
    "sg:classifiers":[
        {
            "category":"Travel",
            "subcategory":"Travel Agent",
            "type":"Entertainment"
        }
    ],
    "sg:phone":"+39 0422 855246",
    "sg:postcode":"31020",
    "sg:province":"Treviso",
    "sg:tags":[
        "business"
    ],
    "wof:name":"Liquorificio Gambrinus",
    "wof:placetype":"venue"
},
  "geometry": {"coordinates":[12.242072,45.666286],"type":"Point"}
}