{
  "type": "Feature",
  "properties": {
    "iso:country":"IT",
    "sg:address":"80076 Lacco Ameno",
    "sg:city":"Lacco Ameno",
    "sg:orig_category":"Ospedali E Servizi Sanitari",
    "sg:phone":"+39 081 994064",
    "sg:postcode":"80076",
    "sg:province":"Napoli",
    "wof:name":"Rispo Nolli Cesarina",
    "wof:placetype":"venue"
},
  "geometry": {"coordinates":[13.890467,40.750431],"type":"Point"}
}