{
  "type": "Feature",
  "properties": {
    "addr:full":"31020 Villorba Villorba Treviso 31020",
    "addr:postcode":"31020;31020",
    "iso:country":"IT",
    "sg:address":"31020 Villorba",
    "sg:city":"Villorba",
    "sg:classifiers":[
        {
            "category":"Manufacturing",
            "subcategory":"Furniture",
            "type":"Manufacturing & Wholesale Goods"
        }
    ],
    "sg:phone":"+39 0422 910291",
    "sg:postcode":"31020",
    "sg:province":"Treviso",
    "sg:tags":[
        "wood",
        "industry",
        "work",
        "furnishing"
    ],
    "wof:name":"Publimarkacommunication Srl",
    "wof:placetype":"venue"
},
  "geometry": {"coordinates":[12.2509450912,45.7285232544],"type":"Point"}
}