{
  "type": "Feature",
  "properties": {
    "addr:full":"17047 Vado Ligure Vado Ligure Savona 17047",
    "addr:postcode":"17047;17047",
    "iso:country":"IT",
    "sg:address":"17047 Vado Ligure",
    "sg:city":"Vado Ligure",
    "sg:orig_category":"Forniture Per Abbigliamento E Pelletterie. Forniture Per Attivita' Commerciali Ed Artigianali",
    "sg:phone":"+39 019 883215",
    "sg:postcode":"17047",
    "sg:province":"Savona",
    "wof:name":"Bolognesi Serafino",
    "wof:placetype":"venue"
},
  "geometry": {"coordinates":[8.4380302429,44.2705078125],"type":"Point"}
}