{
  "type": "Feature",
  "properties": {
    "addr:full":"25, Via Degli Ortolani 33040 Attimis Attimis Udine 33040",
    "addr:postcode":"33040;33040",
    "addr:street":"Via Degli Ortolani",
    "iso:country":"IT",
    "sg:address":"25, Via Degli Ortolani 33040 Attimis",
    "sg:city":"Attimis",
    "sg:classifiers":[
        {
            "category":"Shopping",
            "type":"Retail Goods"
        }
    ],
    "sg:phone":"+39 0432 789899",
    "sg:postcode":"33040",
    "sg:province":"Udine",
    "sg:tags":[
        "finished",
        "-",
        "metallic"
    ],
    "wof:name":"Civitech S.r.l.",
    "wof:placetype":"venue"
},
  "geometry": {"coordinates":[13.2987041473,46.1853904724],"type":"Point"}
}