{
  "type": "Feature",
  "properties": {
    "addr:full":"20020 Solaro Solaro Milano 20020",
    "addr:postcode":"20020;20020",
    "iso:country":"IT",
    "sg:address":"20020 Solaro",
    "sg:city":"Solaro",
    "sg:orig_category":"Pubblica Amministrazione",
    "sg:phone":"+39 02 9679 8017",
    "sg:postcode":"20020",
    "sg:province":"Milano",
    "wof:name":"Carabinieri",
    "wof:placetype":"venue"
},
  "geometry": {"coordinates":[9.0755310059,45.6167526245],"type":"Point"}
}