{
  "type": "Feature",
  "properties": {
    "iso:country":"IT",
    "sg:address":"46, Via Del Redolone 51030 Serravalle Pistoiese",
    "sg:city":"Serravalle Pistoiese",
    "sg:classifiers":[
        {
            "category":"Home & Garden",
            "subcategory":"Home Furnishings",
            "type":"Retail Goods"
        }
    ],
    "sg:phone":"+39 0573 526391",
    "sg:postcode":"51030",
    "sg:province":"Pistoia",
    "sg:tags":[
        "household"
    ],
    "wof:name":"Eurostile Srl",
    "wof:placetype":"venue"
},
  "geometry": {"coordinates":[10.906042,43.884651],"type":"Point"}
}