{
  "type": "Feature",
  "properties": {
    "addr:full":"21013 Gallarate Gallarate Varese 21013",
    "addr:postcode":"21013;21013",
    "iso:country":"IT",
    "sg:address":"21013 Gallarate",
    "sg:city":"Gallarate",
    "sg:orig_category":"Prodotti Finiti Stampati. Forniture E Prodotti Informatici. Forniture Per Uffici",
    "sg:phone":"+39 0331 790380",
    "sg:postcode":"21013",
    "sg:province":"Varese",
    "wof:name":"Q. Print Srl",
    "wof:placetype":"venue"
},
  "geometry": {"coordinates":[8.7980680466,45.6621704102],"type":"Point"}
}