{
  "type": "Feature",
  "properties": {
    "iso:country":"IT",
    "sg:address":"25018 Montichiari",
    "sg:city":"Montichiari",
    "sg:orig_category":"Autogru - Costruzione E Commercio",
    "sg:phone":"+39 030 965 6811",
    "sg:postcode":"25018",
    "sg:province":"Brescia",
    "wof:name":"Cormach Srl",
    "wof:placetype":"venue"
},
  "geometry": {"coordinates":[10.403581,45.390583],"type":"Point"}
}