{
  "type": "Feature",
  "properties": {
    "iso:country":"IT",
    "sg:address":"10148 Torino",
    "sg:city":"Torino",
    "sg:orig_category":"Pompe. Ricambi E Componenti Dei Mezzi Di Trasporto",
    "sg:phone":"+39 011 220 6953",
    "sg:postcode":"10148",
    "sg:province":"Torino",
    "wof:name":"Piardi Di Piardi Mario Giuseppe & C. (s.n.c.)",
    "wof:placetype":"venue"
},
  "geometry": {"coordinates":[7.6912155151,45.1082077026],"type":"Point"}
}