{
  "type": "Feature",
  "properties": {
    "iso:country":"IT",
    "sg:address":"57128 Livorno",
    "sg:city":"Livorno",
    "sg:orig_category":"Abbigliamento Intimo, Calze E Costumi Da Bagno. Sport - Articoli E Forniture. Shopping",
    "sg:phone":"+39 0586 581338",
    "sg:postcode":"57128",
    "sg:province":"Livorno",
    "wof:name":"Overseas Imp. Exp. Company Di Benitez Stella",
    "wof:placetype":"venue"
},
  "geometry": {"coordinates":[10.372248,43.491211],"type":"Point"}
}