{
  "type": "Feature",
  "properties": {
    "addr:full":"65126 Pescara Pescara Pescara 65126",
    "addr:postcode":"65126;65126",
    "iso:country":"IT",
    "sg:address":"65126 Pescara",
    "sg:city":"Pescara",
    "sg:orig_category":"Servizi E Lavori Per Arredamento E Industria Del Legno. Servizi E Lavori Per Edilizia E Lavori Pubblici",
    "sg:phone":"+39 085 451 0746",
    "sg:postcode":"65126",
    "sg:province":"Pescara",
    "wof:name":"Sintonie Di Zinni Achille & C. Sas",
    "wof:placetype":"venue"
},
  "geometry": {"coordinates":[14.22506,42.461456],"type":"Point"}
}