{
  "type": "Feature",
  "properties": {
    "addr:full":"20090 Pieve Emanuele Fizzonasco Milano 20090",
    "addr:postcode":"20090;20090",
    "iso:country":"IT",
    "sg:address":"20090 Pieve Emanuele",
    "sg:city":"Fizzonasco",
    "sg:orig_category":"Forniture E Materiali Per Imballaggio E Confezionamento. Forniture Per Uffici. Forniture Per Attivita' Commerciali Ed Artigianali",
    "sg:phone":"+39 02 9072 2658",
    "sg:postcode":"20090",
    "sg:province":"Milano",
    "sg:website":"http://www.m5biadesivi.it",
    "wof:name":"M5 Biadesivi",
    "wof:placetype":"venue"
},
  "geometry": {"coordinates":[9.202671051,45.3559150696],"type":"Point"}
}