{
  "type": "Feature",
  "properties": {
    "iso:country":"IT",
    "sg:address":"25032 Chiari",
    "sg:city":"Chiari",
    "sg:orig_category":"Macchine, Impianti Ed Attrezzature Per Agricoltura E Zootecnia. Macchine Ed Impianti Per Edilizia E Lavori Pubblici",
    "sg:phone":"+39 030 711582",
    "sg:postcode":"25032",
    "sg:province":"Brescia",
    "sg:website":"http://www.fornoni.it",
    "wof:name":"Fornoni Giancarlo & Figlio Snc",
    "wof:placetype":"venue"
},
  "geometry": {"coordinates":[9.940469,45.539249],"type":"Point"}
}