{
  "type": "Feature",
  "properties": {
    "addr:full":"63, Via Giardini 41042 Fiorano Modenese Fiorano Modenese Modena 41042",
    "addr:postcode":"41042;41042",
    "addr:street":"Via Giardini",
    "iso:country":"IT",
    "sg:address":"63, Via Giardini 41042 Fiorano Modenese",
    "sg:city":"Fiorano Modenese",
    "sg:classifiers":[
        {
            "category":"Manufacturing",
            "subcategory":"Glass & Minerals",
            "type":"Manufacturing & Wholesale Goods"
        }
    ],
    "sg:phone":"+39 0536 920702",
    "sg:postcode":"41042",
    "sg:province":"Modena",
    "sg:tags":[
        "building",
        "material"
    ],
    "wof:name":"Ceramiche Artistiche Biviemme S.r.l.",
    "wof:placetype":"venue"
},
  "geometry": {"coordinates":[10.852856,44.56023],"type":"Point"}
}