{
  "type": "Feature",
  "properties": {
    "iso:country":"IT",
    "sg:address":"80127 Napoli",
    "sg:city":"Napoli",
    "sg:orig_category":"Servizi E Lavori Per Abbigliamento E Pelletterie",
    "sg:phone":"+39 081 714 3391",
    "sg:postcode":"80127",
    "sg:province":"Napoli",
    "wof:name":"Milfur Pellicceria (s.a.s.)",
    "wof:placetype":"venue"
},
  "geometry": {"coordinates":[14.2006,40.914249],"type":"Point"}
}