{
  "type": "Feature",
  "properties": {
    "iso:country":"IT",
    "sg:address":"12030 Caramagna Piemonte",
    "sg:city":"Caramagna Piemonte",
    "sg:orig_category":"Impiantistica E Prodotti Tecnologici Per Edilizia. Telecomunicazioni E Telefonia, Impianti, Apparecchi E Servizi",
    "sg:phone":"+39 0172 89829",
    "sg:postcode":"12030",
    "sg:province":"Cuneo",
    "sg:website":"http://www.essepitelefonia.it",
    "wof:name":"Essepi Telefonia Di Putetto Sandro",
    "wof:placetype":"venue"
},
  "geometry": {"coordinates":[7.73972,44.780193],"type":"Point"}
}