{
  "type": "Feature",
  "properties": {
    "iso:country":"IT",
    "sg:address":"80038 Pomigliano D'arco",
    "sg:classifiers":[
        {
            "category":"Manufacturing",
            "subcategory":"Furniture",
            "type":"Manufacturing & Wholesale Goods"
        }
    ],
    "sg:phone":"+39 081 803 5779",
    "sg:postcode":"80038",
    "sg:province":"Napoli",
    "sg:tags":[
        "wood",
        "industry",
        "work",
        "furnishing"
    ],
    "wof:name":"Arco Arredo Snc Di E. Colombrino & R. Coppola",
    "wof:placetype":"venue"
},
  "geometry": {"coordinates":[14.3969783783,40.9106941223],"type":"Point"}
}