{
  "type": "Feature",
  "properties": {
    "iso:country":"IT",
    "sg:address":"40013 Castel Maggiore",
    "sg:city":"Castel Maggiore",
    "sg:orig_category":"Dolciumi E Gelati",
    "sg:phone":"+39 051 632 8511",
    "sg:postcode":"40013",
    "sg:province":"Bologna",
    "sg:website":"http://www.coind.com",
    "wof:name":"Co. Ind. Soc.coop.r.l.",
    "wof:placetype":"venue"
},
  "geometry": {"coordinates":[11.373261,44.557774],"type":"Point"}
}