{
  "type": "Feature",
  "properties": {
    "addr:full":"22073 Fino Mornasco Fino Mornasco Como 22073",
    "addr:postcode":"22073;22073",
    "iso:country":"IT",
    "sg:address":"22073 Fino Mornasco",
    "sg:city":"Fino Mornasco",
    "sg:orig_category":"Stampa Tessuti",
    "sg:phone":"+39 031 927168",
    "sg:postcode":"22073",
    "sg:province":"Como",
    "wof:name":"Famaprint 1967 Srl",
    "wof:placetype":"venue"
},
  "geometry": {"coordinates":[9.069056,45.743732],"type":"Point"}
}