{
  "type": "Feature",
  "properties": {
    "addr:full":"37023 Grezzana Grezzana Verona 37023",
    "addr:postcode":"37023;37023",
    "iso:country":"IT",
    "sg:address":"37023 Grezzana",
    "sg:city":"Grezzana",
    "sg:classifiers":[
        {
            "category":"Retail",
            "subcategory":"Storage",
            "type":"Services"
        }
    ],
    "sg:phone":"+39 045 907411",
    "sg:postcode":"37023",
    "sg:province":"Verona",
    "sg:tags":[
        "packaging",
        "article",
        "packing"
    ],
    "wof:name":"Albrigi Srl",
    "wof:placetype":"venue"
},
  "geometry": {"coordinates":[11.0051183701,45.540599823],"type":"Point"}
}