{
  "type": "Feature",
  "properties": {
    "addr:full":"52, V. Achille Ventunni 00155 Roma Roma Roma 00155",
    "addr:housenumber":"52",
    "addr:postcode":"00155;00155",
    "addr:street":"V. Achille Ventunni",
    "iso:country":"IT",
    "sg:address":"52, V. Achille Ventunni 00155 Roma",
    "sg:city":"Roma",
    "sg:classifiers":[
        {
            "category":"Manufacturing",
            "subcategory":"Tools & Machinery",
            "type":"Manufacturing & Wholesale Goods"
        }
    ],
    "sg:phone":"+39 39062291800",
    "sg:postcode":"00155",
    "sg:province":"Roma",
    "sg:tags":[
        "environment",
        "equipment",
        "-"
    ],
    "sg:website":"http://www.edilmaco.it",
    "wof:name":"Edil Maco Spa",
    "wof:placetype":"venue"
},
  "geometry": {"coordinates":[12.614077,41.907375],"type":"Point"}
}