{
  "type": "Feature",
  "properties": {
    "iso:country":"IT",
    "sg:address":"40050 Funo",
    "sg:city":"Funo",
    "sg:orig_category":"Macchine, Impianti E Forniture Per Industria Grafica, Cartaria E Cartotecnica",
    "sg:phone":"+39 051 664 7016",
    "sg:postcode":"40050",
    "sg:province":"Bologna",
    "wof:name":"Sericom Italia (s.r.l.)",
    "wof:placetype":"venue"
},
  "geometry": {"coordinates":[11.364887,44.60783],"type":"Point"}
}