{
  "type": "Feature",
  "properties": {
    "iso:country":"IT",
    "sg:address":"70025 Grumo Appula",
    "sg:city":"Grumo Appula",
    "sg:orig_category":"Articoli Da Regalo. Tempo Libero - Articoli E Forniture. Regalistica Aziendale",
    "sg:phone":"+39 080 622740",
    "sg:postcode":"70025",
    "sg:province":"Bari",
    "sg:website":"http://www.antonellistore.com",
    "wof:name":"Antonelli Giuseppe",
    "wof:placetype":"venue"
},
  "geometry": {"coordinates":[16.698214,40.895374],"type":"Point"}
}