{
  "type": "Feature",
  "properties": {
    "addr:full":"87032 Amantea Amantea Cosenza 87032",
    "addr:postcode":"87032;87032",
    "iso:country":"IT",
    "sg:address":"87032 Amantea",
    "sg:city":"Amantea",
    "sg:orig_category":"Mobili - Vendita Al Dettaglio",
    "sg:phone":"+39 0982 426235",
    "sg:postcode":"87032",
    "sg:province":"Cosenza",
    "wof:name":"Bruno Aldo Domus Line",
    "wof:placetype":"venue"
},
  "geometry": {"coordinates":[16.0712814331,39.1334953308],"type":"Point"}
}