{
  "type": "Feature",
  "properties": {
    "addr:full":"Via Mattei 4 28100 Novara Novara Novara 28100",
    "addr:housenumber":"4",
    "addr:postcode":"28100;28100",
    "addr:street":"Mattei",
    "iso:country":"IT",
    "sg:address":"Via Mattei 4 28100 Novara",
    "sg:city":"Novara",
    "sg:classifiers":[
        {
            "category":"Home & Garden",
            "subcategory":"Building Materials",
            "type":"Retail Goods"
        }
    ],
    "sg:phone":"+39 0321 4401",
    "sg:postcode":"28100",
    "sg:province":"Novara",
    "sg:tags":[
        "installation",
        "electric"
    ],
    "sg:website":"www.comoliferrari.it",
    "wof:name":"Comoli, Ferrari & C. S.p.a.",
    "wof:placetype":"venue"
},
  "geometry": {"coordinates":[8.577179,45.425442],"type":"Point"}
}