{
  "type": "Feature",
  "properties": {
    "addr:full":"20145 Milano Milano Milano 20145",
    "addr:postcode":"20145;20145",
    "iso:country":"IT",
    "sg:address":"20145 Milano",
    "sg:city":"Milano",
    "sg:orig_category":"Cesterie Ed Arredamenti In Giunco",
    "sg:phone":"+39 02 481 2377",
    "sg:postcode":"20145",
    "sg:province":"Milano",
    "wof:name":"Mariani Marta",
    "wof:placetype":"venue"
},
  "geometry": {"coordinates":[9.15492,45.466938],"type":"Point"}
}