{
  "type": "Feature",
  "properties": {
    "iso:country":"IT",
    "sg:address":"13, Via Forcella Vincenzo 20144 Milano",
    "sg:city":"Milano",
    "sg:classifiers":[
        {
            "category":"Communications",
            "subcategory":"Newspaper",
            "type":"Services"
        }
    ],
    "sg:phone":"+39 02 8940 1006",
    "sg:postcode":"20144",
    "sg:province":"Milano",
    "sg:tags":[
        "advertising"
    ],
    "wof:name":"Superstudio 13 Intermoda Srl",
    "wof:placetype":"venue"
},
  "geometry": {"coordinates":[9.166862,45.452377],"type":"Point"}
}