{
  "type": "Feature",
  "properties": {
    "iso:country":"IT",
    "sg:address":"52, Via Marconi 41032 Cavezzo",
    "sg:city":"Cavezzo",
    "sg:classifiers":[
        {
            "category":"Wholesale",
            "subcategory":"Machinery & Supplies",
            "type":"Manufacturing & Wholesale Goods"
        }
    ],
    "sg:phone":"+39 39053558324",
    "sg:postcode":"41032",
    "sg:province":"Modena",
    "sg:tags":[
        "-",
        "agriculture",
        "equipment"
    ],
    "wof:name":"Officine Trevisi (s.r.l.)",
    "wof:placetype":"venue"
},
  "geometry": {"coordinates":[10.996694,44.893066],"type":"Point"}
}