{
  "type": "Feature",
  "properties": {
    "addr:full":"70027 Palo Del Colle Palo del Colle Bari 70027",
    "addr:housenumber":"70027",
    "addr:postcode":"70027",
    "addr:street":"Palo",
    "iso:country":"IT",
    "sg:address":"70027 Palo Del Colle",
    "sg:city":"Palo del Colle",
    "sg:orig_category":"Arredo Cucina Ed Elettrodomestici. Climatizzazione E Condizionamento, Apparecchiature E Servizi",
    "sg:phone":"+39 080 624503",
    "sg:postcode":"70027",
    "sg:province":"Bari",
    "sg:website":"http://www.lacriola.it",
    "wof:name":"Lacriola Carlo Srl",
    "wof:placetype":"venue"
},
  "geometry": {"coordinates":[16.664501,41.045094],"type":"Point"}
}