{
  "type": "Feature",
  "properties": {
    "iso:country":"IT",
    "sg:address":"Via Monti Vincenzo 44 20123 Milano",
    "sg:city":"Milano",
    "sg:classifiers":[
        {
            "category":"Manufacturing",
            "subcategory":"Food",
            "type":"Manufacturing & Wholesale Goods"
        }
    ],
    "sg:phone":"+39 02 468441",
    "sg:postcode":"20123",
    "sg:province":"Milano",
    "sg:tags":[
        "industry",
        "additive"
    ],
    "sg:website":"www.savinimilano.com",
    "wof:name":"Savini Claudio E Figli Srl",
    "wof:placetype":"venue"
},
  "geometry": {"coordinates":[9.16919,45.470905],"type":"Point"}
}