{
  "type": "Feature",
  "properties": {
    "iso:country":"IT",
    "sg:address":"24128 Bergamo",
    "sg:city":"Bergamo",
    "sg:orig_category":"Accessori Dei Mezzi Di Trasporto",
    "sg:phone":"+39 035 437 3000",
    "sg:postcode":"24128",
    "sg:province":"Bergamo",
    "sg:website":"http://www.motouno.it",
    "wof:name":"Motouno Service Sas",
    "wof:placetype":"venue"
},
  "geometry": {"coordinates":[9.6561,45.689503],"type":"Point"}
}