{
  "type": "Feature",
  "properties": {
    "iso:country":"IT",
    "sg:address":"98121 Messina",
    "sg:city":"Messina",
    "sg:classifiers":[
        {
            "category":"Building & Trades",
            "subcategory":"Cleaning & Sanitation",
            "type":"Services"
        }
    ],
    "sg:phone":"+39 090 52839",
    "sg:postcode":"98121",
    "sg:province":"Messina",
    "sg:tags":[
        "handling",
        "auxiliary",
        "storage",
        "surveillance",
        "maintenance",
        "services"
    ],
    "wof:name":"Gentile Traslochi",
    "wof:placetype":"venue"
},
  "geometry": {"coordinates":[15.558735,38.20348],"type":"Point"}
}