{
  "type": "Feature",
  "properties": {
    "addr:full":"36073 Cornedo Vicentino Cornedo Vicentino Vicenza 36073",
    "addr:postcode":"36073;36073",
    "addr:street":"Vicentino",
    "iso:country":"IT",
    "sg:address":"36073 Cornedo Vicentino",
    "sg:city":"Cornedo Vicentino",
    "sg:orig_category":"Abbigliamento Esterno, Maglierie E Pelliccerie. Calzature, Pelletterie E Pelli. Sport - Articoli E Forniture",
    "sg:phone":"+39 0445 446748",
    "sg:postcode":"36073",
    "sg:province":"Vicenza",
    "wof:name":"Selleria Equipe S.n.c.",
    "wof:placetype":"venue"
},
  "geometry": {"coordinates":[11.321626,45.618526],"type":"Point"}
}