{
  "type": "Feature",
  "properties": {
    "iso:country":"IT",
    "sg:address":"Via Piave 48 21057 Olgiate Olona",
    "sg:city":"Olgiate Olona",
    "sg:classifiers":[
        {
            "category":"Health Services",
            "subcategory":"Medical Lab",
            "type":"Services"
        }
    ],
    "sg:phone":"+39 0331 640646",
    "sg:postcode":"21057",
    "sg:province":"Varese",
    "sg:tags":[
        "article",
        "disposable"
    ],
    "sg:website":"www.diffuplast.it",
    "wof:name":"Diffuplast Srl",
    "wof:placetype":"venue"
},
  "geometry": {"coordinates":[8.881253,45.626095],"type":"Point"}
}