{
  "type": "Feature",
  "properties": {
    "iso:country":"IT",
    "sg:address":"30122 Venezia",
    "sg:city":"Castello",
    "sg:orig_category":"Articoli Da Regalo. Arte Ed Artigianato Artistico. Shopping",
    "sg:phone":"+39 041 522 7222",
    "sg:postcode":"30122",
    "sg:province":"Venezia",
    "sg:website":"http://space.tin.it/io/crmoschi",
    "wof:name":"Succ.ri A. Santi Fu A. Sas Di Cristiano Moschini & C.",
    "wof:placetype":"venue"
},
  "geometry": {"coordinates":[12.340803,45.437267],"type":"Point"}
}