{
  "type": "Feature",
  "properties": {
    "iso:country":"IT",
    "sg:address":"160, Via Carnia 21100 Varese",
    "sg:city":"Varese",
    "sg:classifiers":[
        {
            "category":"Sports & Exercise",
            "subcategory":"Playing Field",
            "type":"Entertainment"
        }
    ],
    "sg:phone":"+39 0332 261543",
    "sg:postcode":"21100",
    "sg:province":"Varese",
    "sg:tags":[
        "game"
    ],
    "wof:name":"Autotrasporti Venuta",
    "wof:placetype":"venue"
},
  "geometry": {"coordinates":[8.848646,45.80624],"type":"Point"}
}