{
  "type": "Feature",
  "properties": {
    "iso:country":"IT",
    "sg:address":"Via Crocione 3 40127 Bologna",
    "sg:city":"Bologna",
    "sg:classifiers":[
        {
            "category":"Manufacturing",
            "subcategory":"Motor Vehicles & Parts",
            "type":"Manufacturing & Wholesale Goods"
        }
    ],
    "sg:phone":"+39 051 601 2628",
    "sg:postcode":"40127",
    "sg:province":"Bologna",
    "sg:tags":[
        "pipe",
        "exhaust"
    ],
    "sg:website":"www.fratellibastelli.it",
    "wof:name":"Fratelli Bastelli Snc",
    "wof:placetype":"venue"
},
  "geometry": {"coordinates":[11.425448,44.515877],"type":"Point"}
}