{
  "type": "Feature",
  "properties": {
    "addr:full":"41012 Carpi Carpi Modena 41012",
    "addr:postcode":"41012;41012",
    "iso:country":"IT",
    "sg:address":"41012 Carpi",
    "sg:city":"Carpi",
    "sg:orig_category":"Impiantistica E Prodotti Tecnologici Per Edilizia. Elettronica Professionale E Di Consumo. Accessori Dei Mezzi Di Trasporto. Forniture Industriali Per Prevenzione, Controllo E Sicurezza",
    "sg:phone":"+39 059 643555",
    "sg:postcode":"41012",
    "sg:province":"Modena",
    "sg:website":"http://www.centrumsrl.it",
    "wof:name":"Centrum Srl",
    "wof:placetype":"venue"
},
  "geometry": {"coordinates":[10.883014,44.76593],"type":"Point"}
}