{
  "type": "Feature",
  "properties": {
    "addr:full":"20154 Milano Milano Milano 20154",
    "addr:postcode":"20154;20154",
    "iso:country":"IT",
    "sg:address":"20154 Milano",
    "sg:city":"Milano",
    "sg:classifiers":[
        {
            "category":"Education",
            "subcategory":"School",
            "type":"Public Place"
        }
    ],
    "sg:phone":"+39 02 331 3797",
    "sg:postcode":"20154",
    "sg:province":"Milano",
    "sg:tags":[
        "scuole",
        "informatica",
        "di"
    ],
    "wof:name":"Istituto Bramante",
    "wof:placetype":"venue"
},
  "geometry": {"coordinates":[9.180791,45.478645],"type":"Point"}
}