{
  "type": "Feature",
  "properties": {
    "iso:country":"IT",
    "sg:address":"33032 Bertiolo",
    "sg:city":"Bertiolo",
    "sg:orig_category":"Arte Ed Artigianato Artistico",
    "sg:phone":"+39 0432 917080",
    "sg:postcode":"33032",
    "sg:province":"Udine",
    "wof:name":"Malisan Franco & C. Snc",
    "wof:placetype":"venue"
},
  "geometry": {"coordinates":[13.055645,45.950012],"type":"Point"}
}