{
  "type": "Feature",
  "properties": {
    "iso:country":"IT",
    "sg:address":"16 A/b, V. Vittorio Rossi 00133 Roma",
    "sg:city":"Roma",
    "sg:classifiers":[
        {
            "category":"Parking",
            "subcategory":"Lot",
            "type":"Transportation"
        }
    ],
    "sg:phone":"+39 06 2061 8556",
    "sg:postcode":"00133",
    "sg:province":"Roma",
    "sg:tags":[
        "transport",
        "road"
    ],
    "wof:name":"Gemelli Onoranze Funebri",
    "wof:placetype":"venue"
},
  "geometry": {"coordinates":[12.616983,41.868919],"type":"Point"}
}