{
  "type": "Feature",
  "properties": {
    "iso:country":"IT",
    "sg:address":"00142 Roma",
    "sg:city":"Roma",
    "sg:orig_category":"Informatica - Consulenza E Software",
    "sg:phone":"+39 06 504 2586",
    "sg:postcode":"00142",
    "sg:province":"Roma",
    "sg:website":"http://www.polisonlus.it",
    "wof:name":"Polis O.n.l.u.s.",
    "wof:placetype":"venue"
},
  "geometry": {"coordinates":[12.507812,41.838902],"type":"Point"}
}