{
  "type": "Feature",
  "properties": {
    "addr:full":"Loc Vanzelle Via S. Isidoro 37010 Rivoli Veronese Rivoli Veronese Verona 37010",
    "addr:postcode":"37010;37010",
    "addr:street":"Loc Vanzelle Via S. Isidoro",
    "iso:country":"IT",
    "sg:address":"Loc Vanzelle Via S. Isidoro 37010 Rivoli Veronese",
    "sg:city":"Rivoli Veronese",
    "sg:classifiers":[
        {
            "category":"Manufacturing",
            "subcategory":"Paper Products",
            "type":"Manufacturing & Wholesale Goods"
        }
    ],
    "sg:phone":"+39 045 728 1355",
    "sg:postcode":"37010",
    "sg:province":"Verona",
    "sg:tags":[
        "wool",
        "item",
        "made",
        "cardboard",
        "holiday",
        "easter",
        "christmas"
    ],
    "sg:website":"www.hervit.com",
    "wof:name":"Hervit S.r.l.",
    "wof:placetype":"venue"
},
  "geometry": {"coordinates":[10.991748,45.438366],"type":"Point"}
}