{
  "type": "Feature",
  "properties": {
    "addr:full":"95100 Catania CT",
    "addr:postcode":"95100",
    "iso:country":"IT",
    "sg:address":"95100 Catania",
    "sg:orig_category":"Apparecchiature Ed Attrezzature Meccaniche",
    "sg:phone":"+39 095 291860",
    "sg:province":"CT",
    "wof:name":"Tratos Cavi S.p.a.",
    "wof:placetype":"venue"
},
  "geometry": {"coordinates":[15.062149,37.44445],"type":"Point"}
}