{
  "type": "Feature",
  "properties": {
    "addr:full":"Viale Kennedy 97 50038 Scarperia Scarperia Firenze 50038",
    "addr:housenumber":"97",
    "addr:postcode":"50038;50038",
    "addr:street":"Viale Kennedy",
    "iso:country":"IT",
    "sg:address":"Viale Kennedy 97 50038 Scarperia",
    "sg:city":"Scarperia",
    "sg:classifiers":[
        {
            "category":"Structure",
            "subcategory":"Office Building",
            "type":"Public Place"
        }
    ],
    "sg:phone":"+39 055 84001",
    "sg:postcode":"50038",
    "sg:province":"Firenze",
    "sg:tags":[
        "shelf",
        "system"
    ],
    "sg:website":"www.rosss.it",
    "wof:name":"Rosss Spa",
    "wof:placetype":"venue"
},
  "geometry": {"coordinates":[11.256902,43.768734],"type":"Point"}
}