{
  "type": "Feature",
  "properties": {
    "iso:country":"IT",
    "sg:address":"20145 Milano",
    "sg:city":"Milano",
    "sg:orig_category":"Cinematografia E Radiotelevisione",
    "sg:phone":"+39 02 498 7820",
    "sg:postcode":"20145",
    "sg:province":"Milano",
    "wof:name":"Show Biz Visual Comunications Srl",
    "wof:placetype":"venue"
},
  "geometry": {"coordinates":[9.167121,45.475838],"type":"Point"}
}