{
  "type": "Feature",
  "properties": {
    "iso:country":"IT",
    "sg:address":"50041 Calenzano",
    "sg:city":"Calenzano",
    "sg:orig_category":"Non-classified Establishments",
    "sg:phone":"+39 055 887 9038",
    "sg:postcode":"50041",
    "sg:province":"Firenze",
    "wof:name":"3 M Mobili",
    "wof:placetype":"venue"
},
  "geometry": {"coordinates":[11.204296,43.829369],"type":"Point"}
}