{
  "type": "Feature",
  "properties": {
    "addr:full":"16143 Genova Genova Genova 16143",
    "addr:postcode":"16143;16143",
    "iso:country":"IT",
    "sg:address":"16143 Genova",
    "sg:city":"Genova",
    "sg:orig_category":"Macchine, Impianti E Forniture Per Industria Grafica, Cartaria E Cartotecnica. Automazione E Macchine Per Ufficio",
    "sg:phone":"+39 010 511544",
    "sg:postcode":"16143",
    "sg:province":"Genova",
    "sg:website":"http://www.duplicaritalia.com",
    "wof:name":"Dupli C.a.r.",
    "wof:placetype":"venue"
},
  "geometry": {"coordinates":[8.960418,44.407516],"type":"Point"}
}