{
  "type": "Feature",
  "properties": {
    "addr:full":"35010 Vigonza Vigonza Padova 35010",
    "addr:postcode":"35010;35010",
    "iso:country":"IT",
    "sg:address":"35010 Vigonza",
    "sg:city":"Vigonza",
    "sg:orig_category":"Carni, Salumi E Pesci",
    "sg:phone":"+39 049 725596",
    "sg:postcode":"35010",
    "sg:province":"Padova",
    "wof:name":"Macelleria Coppiello Giovanni Snc",
    "wof:placetype":"venue"
},
  "geometry": {"coordinates":[11.982179,45.423492],"type":"Point"}
}