{
  "type": "Feature",
  "properties": {
    "addr:full":"58024 Massa Marittima Massa Marittima Grosseto 58024",
    "addr:postcode":"58024;58024",
    "iso:country":"IT",
    "sg:address":"58024 Massa Marittima",
    "sg:city":"Massa Marittima",
    "sg:orig_category":"Agricoltura, Orticoltura E Floricoltura",
    "sg:phone":"+39 0566 918058",
    "sg:postcode":"58024",
    "sg:province":"Grosseto",
    "wof:name":"Azienda Agrituristica Fiordaliso",
    "wof:placetype":"venue"
},
  "geometry": {"coordinates":[10.9129,43.058014],"type":"Point"}
}