{
  "type": "Feature",
  "properties": {
    "iso:country":"IT",
    "sg:address":"50126 Firenze",
    "sg:city":"Firenze",
    "sg:orig_category":"Trattamenti Termici E Superficiali Metalli, Galvanotecnica",
    "sg:phone":"+39 055 683804",
    "sg:postcode":"50126",
    "sg:province":"Firenze",
    "wof:name":"Galvanica Lepri Di Lepri Silvio",
    "wof:placetype":"venue"
},
  "geometry": {"coordinates":[11.291373,43.759605],"type":"Point"}
}