{
  "type": "Feature",
  "properties": {
    "iso:country":"IT",
    "sg:address":"Via G. Galilei, 22 - Sarmeola 35030 Rubano",
    "sg:city":"Rubano",
    "sg:orig_category":"Needlework Yarns",
    "sg:phone":"+39 049 897 6776",
    "sg:postcode":"35030",
    "sg:province":"Padova",
    "sg:website":"www.ispe.net",
    "wof:name":"Ispe Snc Di Scettri Paolo & C.",
    "wof:placetype":"venue"
},
  "geometry": {"coordinates":[11.805001,45.419422],"type":"Point"}
}