{
  "type": "Feature",
  "properties": {
    "iso:country":"IT",
    "sg:address":"60018 Montemarciano",
    "sg:city":"Lungomare",
    "sg:orig_category":"Bevande, Vini E Liquori. Ristorazione E Locali Pubblici Affini. Ristoranti Ed Esercizi Affini. Servizi Ausiliari Di Ristorazione E Di Intrattenimento",
    "sg:phone":"+39 071 919 8299",
    "sg:postcode":"60018",
    "sg:province":"Ancona",
    "wof:name":"Perry'o Pub Snc",
    "wof:placetype":"venue"
},
  "geometry": {"coordinates":[13.326345,43.604637],"type":"Point"}
}