{
  "type": "Feature",
  "properties": {
    "iso:country":"IT",
    "sg:address":"Via Orlanda 219 30030 Tessera",
    "sg:orig_category":"House And Building Drainage Systems",
    "sg:phone":"+39 041 900600",
    "sg:postcode":"30030",
    "sg:province":"Venezia",
    "sg:website":"www.ittwellpoint.it",
    "wof:name":"Itt Wellpoint Srl",
    "wof:placetype":"venue"
},
  "geometry": {"coordinates":[12.31645,45.497177],"type":"Point"}
}