{
  "type": "Feature",
  "properties": {
    "addr:full":"3, Vicolo Demonte Melchiorre 12030 Cavallermaggiore Cavallermaggiore Cuneo 12030",
    "addr:housenumber":"3",
    "addr:postcode":"12030;12030",
    "addr:street":"Vicolo Demonte Melchiorre",
    "iso:country":"IT",
    "sg:address":"3, Vicolo Demonte Melchiorre 12030 Cavallermaggiore",
    "sg:city":"Cavallermaggiore",
    "sg:classifiers":[
        {
            "category":"Shopping",
            "type":"Retail Goods"
        }
    ],
    "sg:phone":"+39 0172 382570",
    "sg:postcode":"12030",
    "sg:province":"Cuneo",
    "sg:tags":[
        "finished",
        "-",
        "metallic"
    ],
    "wof:name":"Termoigienica S.n.c. Di Monge Luigi E Demichelis",
    "wof:placetype":"venue"
},
  "geometry": {"coordinates":[7.5471105576,44.38879776],"type":"Point"}
}