{
  "type": "Feature",
  "properties": {
    "iso:country":"IT",
    "sg:address":"Via Garza 36/38 25010 Borgosatollo",
    "sg:city":"Borgosatollo",
    "sg:classifiers":[
        {
            "category":"Health Services",
            "subcategory":"Nursing And Care Facility",
            "type":"Services"
        }
    ],
    "sg:phone":"+39 030 270 2957",
    "sg:postcode":"25010",
    "sg:province":"Brescia",
    "sg:tags":[
        "industrial",
        "robot"
    ],
    "sg:website":"www.maicopresse.com",
    "wof:name":"Irobi Srl",
    "wof:placetype":"venue"
},
  "geometry": {"coordinates":[10.256555,45.476776],"type":"Point"}
}