{
  "type": "Feature",
  "properties": {
    "iso:country":"IT",
    "sg:address":"4/bis, Viale Colombo Cristoforo 54033 Carrara",
    "sg:city":"Carrara",
    "sg:classifiers":[
        {
            "category":"Professional",
            "subcategory":"Engineering",
            "type":"Services"
        }
    ],
    "sg:phone":"+39 0585 780857",
    "sg:postcode":"54033",
    "sg:province":"Massa-Carrara",
    "sg:tags":[
        "machine",
        "-",
        "mechanical"
    ],
    "wof:name":"Co.s.m.i.t. A R.l.",
    "wof:placetype":"venue"
},
  "geometry": {"coordinates":[10.039392,44.037632],"type":"Point"}
}