{
  "type": "Feature",
  "properties": {
    "iso:country":"IT",
    "sg:address":"93017 San Cataldo",
    "sg:city":"San Cataldo",
    "sg:orig_category":"Petroli, Gas E Combustibili",
    "sg:phone":"+39 0934 588368",
    "sg:postcode":"93017",
    "sg:province":"Caltanissetta",
    "wof:name":"B.m.idrocarburi S.a.s.",
    "wof:placetype":"venue"
},
  "geometry": {"coordinates":[13.9878911972,37.4896125793],"type":"Point"}
}