{
  "type": "Feature",
  "properties": {
    "iso:country":"IT",
    "sg:address":"23020 Gordona",
    "sg:city":"Gordona",
    "sg:orig_category":"Articoli Sportivi - Produzione E Ingrosso",
    "sg:phone":"+39 0343 42384",
    "sg:postcode":"23020",
    "sg:province":"Sondrio",
    "wof:name":"Sports Rdp Spa Research Developement Production",
    "wof:placetype":"venue"
},
  "geometry": {"coordinates":[9.368489,46.290688],"type":"Point"}
}