{
  "type": "Feature",
  "properties": {
    "addr:full":"3, Via Levanella Scambio 52025 Montevarchi Levane Arezzo 52025",
    "addr:postcode":"52025;52025",
    "addr:street":"Via Levanella Scambio",
    "iso:country":"IT",
    "sg:address":"3, Via Levanella Scambio 52025 Montevarchi",
    "sg:city":"Levane",
    "sg:classifiers":[
        {
            "category":"Personal",
            "subcategory":"Shoe Repair & Shine",
            "type":"Services"
        }
    ],
    "sg:phone":"+39 055 910 3241",
    "sg:postcode":"52025",
    "sg:province":"Arezzo",
    "sg:tags":[
        "leather"
    ],
    "wof:name":"Almatec S.r.l.",
    "wof:placetype":"venue"
},
  "geometry": {"coordinates":[11.8630619049,43.4712028503],"type":"Point"}
}