{
  "type": "Feature",
  "properties": {
    "iso:country":"IT",
    "sg:address":"20129 Milano",
    "sg:city":"Milano",
    "sg:orig_category":"Arredi Ed Attrezzature Per Uffici",
    "sg:phone":"+39 02 236 3624",
    "sg:postcode":"20129",
    "sg:province":"Milano",
    "wof:name":"La Modernissima Di Renato Fundoni & C. (s.a.s.)",
    "wof:placetype":"venue"
},
  "geometry": {"coordinates":[9.222824,45.475842],"type":"Point"}
}