{
  "type": "Feature",
  "properties": {
    "iso:country":"IT",
    "sg:address":"18018 Taggia",
    "sg:city":"Taggia",
    "sg:orig_category":"Macchine, Impianti Ed Attrezzature Per Agricoltura E Zootecnia",
    "sg:phone":"+39 0184 475645",
    "sg:postcode":"18018",
    "sg:province":"Imperia",
    "wof:name":"Rinaldi Vincenzo",
    "wof:placetype":"venue"
},
  "geometry": {"coordinates":[7.851909,43.863148],"type":"Point"}
}