{
  "type": "Feature",
  "properties": {
    "iso:country":"IT",
    "sg:address":"44042 Cento",
    "sg:city":"Cento",
    "sg:orig_category":"Motori Ed Organi Di Trasmissione",
    "sg:phone":"+39 051 901650",
    "sg:postcode":"44042",
    "sg:province":"Ferrara",
    "wof:name":"Ab. Balboni (s.r.l.)",
    "wof:placetype":"venue"
},
  "geometry": {"coordinates":[11.6237888336,44.8316001892],"type":"Point"}
}