{
  "type": "Feature",
  "properties": {
    "iso:country":"IT",
    "sg:address":"20121 Milano",
    "sg:city":"Milano",
    "sg:orig_category":"Hobbistica",
    "sg:phone":"+39 02 877889",
    "sg:postcode":"20121",
    "sg:province":"Milano",
    "wof:name":"La Moneteria Snc",
    "wof:placetype":"venue"
},
  "geometry": {"coordinates":[9.187427,45.466171],"type":"Point"}
}