{
  "type": "Feature",
  "properties": {
    "iso:country":"IT",
    "sg:address":"80028 Grumo Nevano",
    "sg:city":"Grumo Nevano",
    "sg:orig_category":"Materiali Semilavorati Metallici",
    "sg:phone":"+39 081 830 4114",
    "sg:postcode":"80028",
    "sg:province":"Napoli",
    "wof:name":"D.v.p. Di Gennaro F & C Sas",
    "wof:placetype":"venue"
},
  "geometry": {"coordinates":[14.25173,40.937229],"type":"Point"}
}