{
  "type": "Feature",
  "properties": {
    "addr:full":"7, Viale Vecchi Agamennone 48100 Ravenna Ravenna Ravenna 48100",
    "addr:postcode":"48100;48100",
    "addr:street":"Viale Vecchi Agamennone",
    "iso:country":"IT",
    "sg:address":"7, Viale Vecchi Agamennone 48100 Ravenna",
    "sg:city":"Ravenna",
    "sg:classifiers":[
        {
            "category":"Building & Trades",
            "subcategory":"Construction",
            "type":"Services"
        }
    ],
    "sg:phone":"+39 0544 530742",
    "sg:postcode":"48100",
    "sg:province":"Ravenna",
    "sg:tags":[
        "work",
        "public"
    ],
    "wof:name":"Rana Diving & Marine Contractor S.r.l.",
    "wof:placetype":"venue"
},
  "geometry": {"coordinates":[12.279398,44.491093],"type":"Point"}
}