{
  "type": "Feature",
  "properties": {
    "addr:full":"00152 Roma Roma Roma 00152",
    "addr:postcode":"00152;00152",
    "iso:country":"IT",
    "sg:address":"00152 Roma",
    "sg:city":"Roma",
    "sg:orig_category":"Ospedali E Servizi Sanitari",
    "sg:phone":"+39 06 588 1716",
    "sg:postcode":"00152",
    "sg:province":"Roma",
    "wof:name":"Labanalisi Monteverde Srl",
    "wof:placetype":"venue"
},
  "geometry": {"coordinates":[12.461605,41.881798],"type":"Point"}
}