{
  "type": "Feature",
  "properties": {
    "iso:country":"IT",
    "sg:address":"20136 Milano",
    "sg:city":"Milano",
    "sg:orig_category":"Dolciumi E Gelati",
    "sg:phone":"+39 02 8940 6261",
    "sg:postcode":"20136",
    "sg:province":"Milano",
    "wof:name":"La Casa Del Dolce Di Laurenza Mario",
    "wof:placetype":"venue"
},
  "geometry": {"coordinates":[9.182389,45.452152],"type":"Point"}
}