{
  "type": "Feature",
  "properties": {
    "addr:full":"14, Via Giosue' Carducci 20060 Pozzo D'adda Milano 20060",
    "addr:postcode":"20060;20060",
    "addr:street":"Via Giosue ' Carducci",
    "iso:country":"IT",
    "sg:address":"14, Via Giosue' Carducci 20060 Pozzo D'adda",
    "sg:classifiers":[
        {
            "category":"Shopping",
            "type":"Retail Goods"
        }
    ],
    "sg:phone":"+39 02 9096 7227",
    "sg:postcode":"20060",
    "sg:province":"Milano",
    "sg:tags":[
        "finished",
        "-",
        "metallic"
    ],
    "wof:name":"Comir (s.r.l.)",
    "wof:placetype":"venue"
},
  "geometry": {"coordinates":[9.5061454773,45.5748252869],"type":"Point"}
}