{
  "type": "Feature",
  "properties": {
    "iso:country":"IT",
    "sg:address":"42100 Reggio Emilia",
    "sg:classifiers":[
        {
            "category":"Professional",
            "subcategory":"Business Services",
            "type":"Services"
        }
    ],
    "sg:phone":"+39 0522 452735",
    "sg:postcode":"42100",
    "sg:province":"Reggio Nell'Emilia",
    "sg:tags":[
        "support",
        "companies",
        "events",
        "trade"
    ],
    "sg:website":"http://www.cititraduzioni.it",
    "wof:name":"Citi Coop. Italiana Traduttori E Interpreti",
    "wof:placetype":"venue"
},
  "geometry": {"coordinates":[10.633672,44.694695],"type":"Point"}
}