{
  "type": "Feature",
  "properties": {
    "iso:country":"IT",
    "sg:address":"21047 Saronno",
    "sg:city":"Saronno",
    "sg:orig_category":"Ospedali E Servizi Sanitari",
    "sg:phone":"+39 02 962 0669",
    "sg:postcode":"21047",
    "sg:province":"Varese",
    "wof:name":"Negretti Dr. Vittorio",
    "wof:placetype":"venue"
},
  "geometry": {"coordinates":[8.825321,45.783806],"type":"Point"}
}