{
  "type": "Feature",
  "properties": {
    "addr:full":"81024 Maddaloni Maddaloni Caserta 81024",
    "addr:postcode":"81024;81024",
    "iso:country":"IT",
    "sg:address":"81024 Maddaloni",
    "sg:city":"Maddaloni",
    "sg:orig_category":"Forniture Per Edilizia E Lavori Pubblici. Prodotti Vari In Metallo",
    "sg:phone":"+39 0823 401460",
    "sg:postcode":"81024",
    "sg:province":"Caserta",
    "wof:name":"New Pont Ponteggi Tubolari Srl",
    "wof:placetype":"venue"
},
  "geometry": {"coordinates":[14.3771924973,41.0311279297],"type":"Point"}
}