{
  "type": "Feature",
  "properties": {
    "addr:full":"50018 Scandicci Scandicci Firenze 50018",
    "addr:postcode":"50018;50018",
    "iso:country":"IT",
    "sg:address":"50018 Scandicci",
    "sg:city":"Scandicci",
    "sg:orig_category":"Hobbistica",
    "sg:phone":"+39 055 740132",
    "sg:postcode":"50018",
    "sg:province":"Firenze",
    "wof:name":"Lorenzini Ferdinando",
    "wof:placetype":"venue"
},
  "geometry": {"coordinates":[11.150411,43.730701],"type":"Point"}
}