{
  "type": "Feature",
  "properties": {
    "iso:country":"IT",
    "sg:address":"51036 Larciano",
    "sg:city":"Larciano",
    "sg:orig_category":"Tessuti Arredamento, Tende E Tappeti",
    "sg:phone":"+39 0573 83025",
    "sg:postcode":"51036",
    "sg:province":"Pistoia",
    "wof:name":"Home Line Srl",
    "wof:placetype":"venue"
},
  "geometry": {"coordinates":[10.918368,43.928497],"type":"Point"}
}