{
  "type": "Feature",
  "properties": {
    "addr:full":"20129 Milano Milano Milano 20129",
    "addr:postcode":"20129;20129",
    "iso:country":"IT",
    "sg:address":"20129 Milano",
    "sg:city":"Milano",
    "sg:orig_category":"Abbigliamento Esterno, Maglierie E Pelliccerie. Servizi E Lavori Per Abbigliamento E Pelletterie",
    "sg:phone":"+39 02 733766",
    "sg:postcode":"20129",
    "sg:province":"Milano",
    "wof:name":"Cataldo Antonio",
    "wof:placetype":"venue"
},
  "geometry": {"coordinates":[9.272895,45.445187],"type":"Point"}
}