{
  "type": "Feature",
  "properties": {
    "iso:country":"IT",
    "sg:address":"20134 Milano",
    "sg:city":"Milano",
    "sg:orig_category":"Servizi Ausiliari Di Analisi, Controllo E Ricerca",
    "sg:phone":"+39 02 2641 0327",
    "sg:postcode":"20134",
    "sg:province":"Milano",
    "wof:name":"Iris Servizi Cooperativa Di Solidarieta' Sociale A.r.l.",
    "wof:placetype":"venue"
},
  "geometry": {"coordinates":[9.249826,45.490746],"type":"Point"}
}