{
  "type": "Feature",
  "properties": {
    "addr:full":"Corso Vittorio Emanuele 92/100, Palazzo Vallelonga, 80059 Torre Del Greco, Na Torre del Greco Napoli 80059",
    "addr:housenumber":"92 / 100",
    "addr:postcode":"80059;80059",
    "addr:street":"Corso Vittorio Emanuele",
    "iso:country":"IT",
    "sg:address":"Corso Vittorio Emanuele 92/100, Palazzo Vallelonga, 80059 Torre Del Greco, Na",
    "sg:city":"Torre del Greco",
    "sg:classifiers":[
        {
            "category":"Banks & Credit Unions",
            "subcategory":"Bank",
            "type":"Services"
        }
    ],
    "sg:phone":"+39 081 849 2077",
    "sg:postcode":"80059",
    "sg:province":"Napoli",
    "sg:website":"http://www.bcp.it",
    "wof:name":"Banca Di Credito Popolare Torre Del Greco Scrl",
    "wof:placetype":"venue"
},
  "geometry": {"coordinates":[8.833693,40.549484],"type":"Point"}
}