{
  "type": "Feature",
  "properties": {
    "iso:country":"IT",
    "sg:address":"Via Dell' Artigianato 10 35010 Villa Del Conte",
    "sg:city":"Villa del Conte",
    "sg:classifiers":[
        {
            "category":"Banks & Credit Unions",
            "subcategory":"Financial Services",
            "type":"Services"
        }
    ],
    "sg:phone":"+39 049 932 5066",
    "sg:postcode":"35010",
    "sg:province":"Padova",
    "sg:tags":[
        "washing",
        "agents",
        "cleaning",
        "liquid"
    ],
    "wof:name":"Filmop S.r.l.",
    "wof:placetype":"venue"
},
  "geometry": {"coordinates":[11.853516,45.604187],"type":"Point"}
}