{
  "type": "Feature",
  "properties": {
    "iso:country":"IT",
    "sg:address":"03037 Pontecorvo",
    "sg:city":"Pontecorvo",
    "sg:orig_category":"Servizi Ausiliari Per Il Trasporto. Servizi Vari Di Interesse Pubblico",
    "sg:phone":"+39 0776 761076",
    "sg:postcode":"03037",
    "sg:province":"Frosinone",
    "wof:name":"Ruscio Gianpaolo",
    "wof:placetype":"venue"
},
  "geometry": {"coordinates":[13.647848,41.450253],"type":"Point"}
}