{
  "type": "Feature",
  "properties": {
    "addr:full":"36, Via Piave 20016 Pero Pero Milano 20016",
    "addr:postcode":"20016;20016",
    "addr:street":"Via Piave",
    "iso:country":"IT",
    "sg:address":"36, Via Piave 20016 Pero",
    "sg:city":"Pero",
    "sg:classifiers":[
        {
            "category":"Manufacturing",
            "subcategory":"Metals",
            "type":"Manufacturing & Wholesale Goods"
        }
    ],
    "sg:phone":"+39 02 3810 0162",
    "sg:postcode":"20016",
    "sg:province":"Milano",
    "sg:tags":[
        "metallurgy",
        "metalworking"
    ],
    "wof:name":"Venci O.m.m. Di Ing. Claudio Venci",
    "wof:placetype":"venue"
},
  "geometry": {"coordinates":[9.0938596725,45.5095558167],"type":"Point"}
}