{
  "type": "Feature",
  "properties": {
    "iso:country":"IT",
    "sg:address":"25075 Nave",
    "sg:city":"Nave",
    "sg:orig_category":"Materiali Semilavorati Metallici",
    "sg:phone":"+39 030 253 4527",
    "sg:postcode":"25075",
    "sg:province":"Brescia",
    "wof:name":"Profilati Nave (s.p.a.)",
    "wof:placetype":"venue"
},
  "geometry": {"coordinates":[10.269188,45.58408],"type":"Point"}
}