{
  "type": "Feature",
  "properties": {
    "iso:country":"IT",
    "sg:address":"90144 Palermo",
    "sg:city":"Palermo",
    "sg:orig_category":"Scuole E Servizi Scolastici. Centri Di Estetica E Cosmesi E Servizi. Ricerca, Selezione E Formazione Del Personale",
    "sg:phone":"+39 091 518307",
    "sg:postcode":"90144",
    "sg:province":"Palermo",
    "wof:name":"New S.e.m. Soc.coop.r.l.",
    "wof:placetype":"venue"
},
  "geometry": {"coordinates":[13.337127,38.141926],"type":"Point"}
}