{
  "type": "Feature",
  "properties": {
    "iso:country":"IT",
    "sg:address":"17100 Savona",
    "sg:city":"Savona",
    "sg:orig_category":"Frigotecnica, Apparecchiature E Servizi",
    "sg:phone":"+39 019 821945",
    "sg:postcode":"17100",
    "sg:province":"Savona",
    "wof:name":"Sis.t.e.m.i. Sas Di Broccardi & C.",
    "wof:placetype":"venue"
},
  "geometry": {"coordinates":[8.4779911041,44.3035163879],"type":"Point"}
}