{
  "type": "Feature",
  "properties": {
    "iso:country":"IT",
    "sg:address":"659, Via Statale 51039 Quarrata",
    "sg:city":"Quarrata",
    "sg:classifiers":[
        {
            "category":"Shopping",
            "subcategory":"Crafts & Fabrics",
            "type":"Retail Goods"
        }
    ],
    "sg:phone":"+39 0573 744436",
    "sg:postcode":"51039",
    "sg:province":"Pistoia",
    "wof:name":"Dea S.r.l.",
    "wof:placetype":"venue"
},
  "geometry": {"coordinates":[10.9873533249,43.8695983887],"type":"Point"}
}