{
  "type": "Feature",
  "properties": {
    "iso:country":"IT",
    "sg:address":"00146 Roma",
    "sg:city":"Roma",
    "sg:orig_category":"Ospedali E Servizi Sanitari",
    "sg:phone":"+39 06 556 5917",
    "sg:postcode":"00146",
    "sg:province":"Roma",
    "wof:name":"Clinitalia (s.r.l.)",
    "wof:placetype":"venue"
},
  "geometry": {"coordinates":[12.470173,41.863003],"type":"Point"}
}