{
  "type": "Feature",
  "properties": {
    "iso:country":"IT",
    "sg:address":"17, Via Donatello 59016 Poggio A Caiano",
    "sg:city":"Poggio a Caiano",
    "sg:classifiers":[
        {
            "category":"Shopping",
            "subcategory":"Clothing, Apparel, & Fashions",
            "type":"Retail Goods"
        }
    ],
    "sg:phone":"+39 055 879 7537",
    "sg:postcode":"59016",
    "sg:province":"Prato",
    "sg:tags":[
        "clothing",
        "accessory"
    ],
    "wof:name":"Cappellificio Te S.r.l.",
    "wof:placetype":"venue"
},
  "geometry": {"coordinates":[11.060132,43.810059],"type":"Point"}
}