{
  "type": "Feature",
  "properties": {
    "iso:country":"IT",
    "sg:address":"73, Via Calmaor 31020 San Vendemiano",
    "sg:city":"San Vendemiano",
    "sg:classifiers":[
        {
            "category":"Manufacturing",
            "subcategory":"Metals",
            "type":"Manufacturing & Wholesale Goods"
        }
    ],
    "sg:phone":"+39 0438 778097",
    "sg:postcode":"31020",
    "sg:province":"Treviso",
    "sg:tags":[
        "processing"
    ],
    "wof:name":"O.m.s. (s.p.a.)",
    "wof:placetype":"venue"
},
  "geometry": {"coordinates":[12.3596115112,45.8787651062],"type":"Point"}
}