{
  "type": "Feature",
  "properties": {
    "iso:country":"IT",
    "sg:address":"12042 Bra",
    "sg:city":"Bra",
    "sg:orig_category":"Apparecchiature Ed Attrezzature Meccaniche",
    "sg:phone":"+39 0172 413340",
    "sg:postcode":"12042",
    "sg:province":"Cuneo",
    "sg:website":"http://www.industrialfluid.it",
    "wof:name":"Industrial Fluid Control Sas Di Riva Ezio & C.",
    "wof:placetype":"venue"
},
  "geometry": {"coordinates":[7.806885,44.714588],"type":"Point"}
}