{
  "type": "Feature",
  "properties": {
    "addr:full":"41, V. Molino 31057 Silea Silea Treviso 31057",
    "addr:housenumber":"41",
    "addr:postcode":"31057;31057",
    "addr:street":"V. Molino",
    "iso:country":"IT",
    "sg:address":"41, V. Molino 31057 Silea",
    "sg:city":"Silea",
    "sg:classifiers":[
        {
            "category":"Manufacturing",
            "subcategory":"Metals",
            "type":"Manufacturing & Wholesale Goods"
        }
    ],
    "sg:phone":"+39 39042294461",
    "sg:postcode":"31057",
    "sg:province":"Treviso",
    "sg:tags":[
        "processing"
    ],
    "sg:website":"http://www.paginegialle.it/zanatta-01",
    "wof:name":"Torneria In Lastra Zanatta F.",
    "wof:placetype":"venue"
},
  "geometry": {"coordinates":[12.2898836136,45.6541824341],"type":"Point"}
}