{
  "type": "Feature",
  "properties": {
    "addr:full":"165, Via Boito Arrigo 41019 Soliera Soliera Modena 41019",
    "addr:housenumber":"165",
    "addr:postcode":"41019;41019",
    "addr:street":"Via Boito Arrigo",
    "iso:country":"IT",
    "sg:address":"165, Via Boito Arrigo 41019 Soliera",
    "sg:city":"Soliera",
    "sg:classifiers":[
        {
            "category":"Professional",
            "subcategory":"Engineering",
            "type":"Services"
        }
    ],
    "sg:phone":"+39 39059561215",
    "sg:postcode":"41019",
    "sg:province":"Modena",
    "sg:tags":[
        "machine",
        "-",
        "mechanical"
    ],
    "wof:name":"Demar (s.r.l.)",
    "wof:placetype":"venue"
},
  "geometry": {"coordinates":[10.916961,44.72718],"type":"Point"}
}