{
  "type": "Feature",
  "properties": {
    "iso:country":"IT",
    "sg:address":"Strada Comunale Boschi 9 10092 Beinasco",
    "sg:city":"Beinasco",
    "sg:orig_category":"Brake Linings, Industrial",
    "sg:phone":"+39 011 349 0322",
    "sg:postcode":"10092",
    "sg:province":"Torino",
    "wof:name":"Dott. Stefano Linot Srl",
    "wof:placetype":"venue"
},
  "geometry": {"coordinates":[7.573824,45.010803],"type":"Point"}
}