{
  "type": "Feature",
  "properties": {
    "iso:country":"IT",
    "sg:address":"20098 San Giuliano Milanese",
    "sg:city":"San Giuliano Milanese",
    "sg:orig_category":"Elettrotecnica Professionale E Di Consumo",
    "sg:phone":"+39 02 984 9981",
    "sg:postcode":"20098",
    "sg:province":"Milano",
    "wof:name":"Osram Spa Societa' Riunite Osram Edison Clerici",
    "wof:placetype":"venue"
},
  "geometry": {"coordinates":[9.306191,45.380829],"type":"Point"}
}