{
  "type": "Feature",
  "properties": {
    "addr:full":"43030 San Michele Di Tiorre San Michele di Tiorre Parma 43030",
    "addr:housenumber":"43030",
    "addr:postcode":"43030",
    "addr:street":"San",
    "iso:country":"IT",
    "sg:address":"43030 San Michele Di Tiorre",
    "sg:city":"San Michele di Tiorre",
    "sg:orig_category":"Macchine, Impianti Ed Attrezzature Industria Chimica",
    "sg:phone":"+39 0521 336190",
    "sg:postcode":"43030",
    "sg:province":"Parma",
    "wof:name":"Hpm Srl",
    "wof:placetype":"venue"
},
  "geometry": {"coordinates":[10.272431,44.686832],"type":"Point"}
}