{
  "type": "Feature",
  "properties": {
    "addr:full":"Contrada Grotticelli 93100 Caltanissetta Caltanissetta Caltanissetta 93100",
    "addr:postcode":"93100;93100",
    "addr:street":"Contrada Grotticelli",
    "iso:country":"IT",
    "sg:address":"Contrada Grotticelli 93100 Caltanissetta",
    "sg:city":"Caltanissetta",
    "sg:classifiers":[
        {
            "category":"Farming",
            "subcategory":"Livestock Farm",
            "type":"Manufacturing & Wholesale Goods"
        }
    ],
    "sg:phone":"+39 0934 569227",
    "sg:postcode":"93100",
    "sg:province":"Caltanissetta",
    "sg:tags":[
        "agriculture"
    ],
    "wof:name":"Sider Man Snc",
    "wof:placetype":"venue"
},
  "geometry": {"coordinates":[14.06329,37.48991],"type":"Point"}
}