{
  "type": "Feature",
  "properties": {
    "iso:country":"IT",
    "sg:address":"20021 Bollate",
    "sg:city":"Bollate",
    "sg:orig_category":"Chiese Ed Associazioni Religiose",
    "sg:phone":"+39 02 3830 1532",
    "sg:postcode":"20021",
    "sg:province":"Milano",
    "wof:name":"Chiesa Cristiana Evangelica Battista",
    "wof:placetype":"venue"
},
  "geometry": {"coordinates":[9.12249,45.542072],"type":"Point"}
}