{
  "type": "Feature",
  "properties": {
    "iso:country":"IT",
    "sg:address":"43, Via Montello 20038 Seregno",
    "sg:city":"Seregno",
    "sg:classifiers":[
        {
            "category":"Professional",
            "subcategory":"Engineering",
            "type":"Services"
        }
    ],
    "sg:phone":"+39 036 223 9553",
    "sg:postcode":"20038",
    "sg:province":"Milano",
    "sg:tags":[
        "machine",
        "-",
        "mechanical"
    ],
    "wof:name":"Emmezeta Srl",
    "wof:placetype":"venue"
},
  "geometry": {"coordinates":[9.225981,45.649963],"type":"Point"}
}