{
  "type": "Feature",
  "properties": {
    "iso:country":"IT",
    "sg:address":"18, Viale Gramsci 52016 Castel Focognano",
    "sg:city":"Castel Focognano",
    "sg:classifiers":[
        {
            "category":"Professional",
            "subcategory":"Engineering",
            "type":"Services"
        }
    ],
    "sg:phone":"+39 0575 592215",
    "sg:postcode":"52016",
    "sg:province":"Arezzo",
    "sg:tags":[
        "machine",
        "-",
        "mechanical"
    ],
    "wof:name":"C.m.c. (soc. Coop. R.l.)",
    "wof:placetype":"venue"
},
  "geometry": {"coordinates":[11.869274,43.57621],"type":"Point"}
}