{
  "type": "Feature",
  "properties": {
    "addr:full":"50053 Empoli Empoli Firenze 50053",
    "addr:postcode":"50053;50053",
    "iso:country":"IT",
    "sg:address":"50053 Empoli",
    "sg:city":"Empoli",
    "sg:orig_category":"Calzature, Pelletterie E Pelli",
    "sg:phone":"+39 0571 930144",
    "sg:postcode":"50053",
    "sg:province":"Firenze",
    "wof:name":"Almar Di Araneo",
    "wof:placetype":"venue"
},
  "geometry": {"coordinates":[10.946794,43.693741],"type":"Point"}
}