{
  "type": "Feature",
  "properties": {
    "iso:country":"IT",
    "sg:address":"09131 Cagliari",
    "sg:city":"Cagliari",
    "sg:orig_category":"Elettronica Professionale E Di Consumo. Forniture Per Il Settore Dello Spettacolo. Automazione E Macchine Per Ufficio. Forniture Per Congressi, Fiere E Manifestazioni",
    "sg:phone":"+39 070 485477",
    "sg:postcode":"09131",
    "sg:province":"Cagliari",
    "sg:website":"http://www.rossinimusica.it",
    "wof:name":"Rossini Musica Snc Di Rossini & C.",
    "wof:placetype":"venue"
},
  "geometry": {"coordinates":[9.127629,39.232998],"type":"Point"}
}