{
  "type": "Feature",
  "properties": {
    "addr:full":"6, Via Cantarella 36040 Brendola Brendola Vicenza 36040",
    "addr:postcode":"36040;36040",
    "addr:street":"Via Cantarella",
    "iso:country":"IT",
    "sg:address":"6, Via Cantarella 36040 Brendola",
    "sg:city":"Brendola",
    "sg:classifiers":[
        {
            "category":"Shopping",
            "subcategory":"Clothing, Apparel, & Fashions",
            "type":"Retail Goods"
        }
    ],
    "sg:phone":"+39 0444 401131",
    "sg:postcode":"36040",
    "sg:province":"Vicenza",
    "sg:tags":[
        "clothes"
    ],
    "wof:name":"Volcar S.p.a.",
    "wof:placetype":"venue"
},
  "geometry": {"coordinates":[11.445356,45.473835],"type":"Point"}
}