{
  "type": "Feature",
  "properties": {
    "addr:full":"58020 Scarlino Scarlino Grosseto 58020",
    "addr:postcode":"58020;58020",
    "iso:country":"IT",
    "sg:address":"58020 Scarlino",
    "sg:city":"Scarlino",
    "sg:orig_category":"Agenzie Marittime",
    "sg:phone":"+39 338 930 3343",
    "sg:postcode":"58020",
    "sg:province":"Grosseto",
    "wof:name":"Micera Ciro",
    "wof:placetype":"venue"
},
  "geometry": {"coordinates":[10.850567,42.909019],"type":"Point"}
}