{
  "type": "Feature",
  "properties": {
    "iso:country":"IT",
    "sg:address":"20010 Vanzago",
    "sg:city":"Vanzago",
    "sg:orig_category":"Materiali E Componenti Elettrotecnici",
    "sg:phone":"+39 02 9354 8486",
    "sg:postcode":"20010",
    "sg:province":"Milano",
    "wof:name":"Global Security Srl",
    "wof:placetype":"venue"
},
  "geometry": {"coordinates":[8.983696,45.519077],"type":"Point"}
}