{
  "type": "Feature",
  "properties": {
    "iso:country":"IT",
    "sg:address":"04011 Aprilia",
    "sg:city":"Aprilia",
    "sg:orig_category":"Materiali Semilavorati Metallici",
    "sg:phone":"+39 06 927 5772",
    "sg:postcode":"04011",
    "sg:province":"Latina",
    "wof:name":"2 G Sistemi Snc",
    "wof:placetype":"venue"
},
  "geometry": {"coordinates":[12.690533,41.551586],"type":"Point"}
}