{
  "type": "Feature",
  "properties": {
    "addr:full":"60022 Castelfidardo Castelfidardo Ancona 60022",
    "addr:postcode":"60022;60022",
    "iso:country":"IT",
    "sg:address":"60022 Castelfidardo",
    "sg:city":"Castelfidardo",
    "sg:orig_category":"Materiali Semilavorati Metallici",
    "sg:phone":"+39 071 782 1608",
    "sg:postcode":"60022",
    "sg:province":"Ancona",
    "wof:name":"Cooperativa Albanesi A R.l.",
    "wof:placetype":"venue"
},
  "geometry": {"coordinates":[13.53669,43.449963],"type":"Point"}
}