{
  "type": "Feature",
  "properties": {
    "addr:full":"25135 Brescia Brescia Brescia 25135",
    "addr:postcode":"25135;25135",
    "iso:country":"IT",
    "sg:address":"25135 Brescia",
    "sg:city":"Brescia",
    "sg:orig_category":"Pompe. Macchine, Strumenti Ed Apparecchi Per Attivita' Industriali",
    "sg:phone":"+39 030 376 0660",
    "sg:postcode":"25135",
    "sg:province":"Brescia",
    "sg:website":"http://www.silent.it",
    "wof:name":"Silent Di Foresti Giovanni E C. Snc",
    "wof:placetype":"venue"
},
  "geometry": {"coordinates":[10.2805194855,45.4932403564],"type":"Point"}
}