{
  "type": "Feature",
  "properties": {
    "iso:country":"IT",
    "sg:address":"25010 Borgosatollo",
    "sg:city":"Borgosatollo",
    "sg:orig_category":"Arredo Cucina Ed Elettrodomestici. Elettrodomestici",
    "sg:phone":"+39 030 250 1554",
    "sg:postcode":"25010",
    "sg:province":"Brescia",
    "sg:website":"http://www.cadcam-technologies.it",
    "wof:name":"Cad & Cam Technologies Sas",
    "wof:placetype":"venue"
},
  "geometry": {"coordinates":[10.253191,45.479431],"type":"Point"}
}