{
  "type": "Feature",
  "properties": {
    "addr:full":"66, Via Moro Aldo 46019 Viadana Viadana Mantova 46019",
    "addr:postcode":"46019;46019",
    "addr:street":"Via Moro Aldo",
    "iso:country":"IT",
    "sg:address":"66, Via Moro Aldo 46019 Viadana",
    "sg:city":"Viadana",
    "sg:orig_category":"Miscellaneous Products",
    "sg:phone":"+39 39037588179",
    "sg:postcode":"46019",
    "sg:province":"Mantova",
    "wof:name":"Boldrini Amedeo (s.n.c.)",
    "wof:placetype":"venue"
},
  "geometry": {"coordinates":[10.7976980209,45.1603660583],"type":"Point"}
}