{
  "type": "Feature",
  "properties": {
    "addr:full":"Sda Trossi 10b 13871 Verrone Verrone Biella 13871",
    "addr:housenumber":"10b",
    "addr:postcode":"13871;13871",
    "addr:street":"Trossi",
    "iso:country":"IT",
    "sg:address":"Sda Trossi 10b 13871 Verrone",
    "sg:city":"Verrone",
    "sg:classifiers":[
        {
            "category":"Manufacturing",
            "subcategory":"Textiles",
            "type":"Manufacturing & Wholesale Goods"
        }
    ],
    "sg:phone":"+39 015 255 8498",
    "sg:postcode":"13871",
    "sg:province":"Biella",
    "sg:tags":[
        "blended",
        "yarn"
    ],
    "sg:website":"www.sabotex.it",
    "wof:name":"Sabotex 76 Di Benito Boldi & C. S.a.s.",
    "wof:placetype":"venue"
},
  "geometry": {"coordinates":[8.096946,45.559311],"type":"Point"}
}