{
  "type": "Feature",
  "properties": {
    "iso:country":"IT",
    "sg:address":"Via Gasparoli 94; Cassano Magnago; 21012",
    "sg:city":"Cassano Magnago",
    "sg:classifiers":[
        {
            "category":"Banks & Credit Unions",
            "subcategory":"Bank",
            "type":"Services"
        }
    ],
    "sg:phone":"+39 0331 280989",
    "sg:postcode":"21012",
    "sg:province":"Varese",
    "wof:name":"Credito Italiano Spa",
    "wof:placetype":"venue"
},
  "geometry": {"coordinates":[8.834392,45.661808],"type":"Point"}
}