{
  "type": "Feature",
  "properties": {
    "iso:country":"IT",
    "sg:address":"25024 Porzano",
    "sg:city":"Porzano",
    "sg:orig_category":"Legno E Semilavorati",
    "sg:phone":"+39 030 906 7041",
    "sg:postcode":"25024",
    "sg:province":"Brescia",
    "wof:name":"Molinari Angelo",
    "wof:placetype":"venue"
},
  "geometry": {"coordinates":[10.235789,45.530746],"type":"Point"}
}