{
  "type": "Feature",
  "properties": {
    "iso:country":"IT",
    "sg:address":"20060 Vignate",
    "sg:city":"Vignate",
    "sg:orig_category":"Assemblaggio Conto Terzi",
    "sg:phone":"+39 02 9536 4460",
    "sg:postcode":"20060",
    "sg:province":"Milano",
    "wof:name":"Bruno Giuseppe",
    "wof:placetype":"venue"
},
  "geometry": {"coordinates":[9.32622,45.482487],"type":"Point"}
}