{
  "type": "Feature",
  "properties": {
    "iso:country":"IT",
    "sg:address":"20138 Milano",
    "sg:city":"Milano",
    "sg:orig_category":"Lamiere - Commercio",
    "sg:phone":"+39 02 5800 7581",
    "sg:postcode":"20138",
    "sg:province":"Milano",
    "wof:name":"Iron Centro Prodotti Siderurgici Spa",
    "wof:placetype":"venue"
},
  "geometry": {"coordinates":[9.251227,45.453423],"type":"Point"}
}