{
  "type": "Feature",
  "properties": {
    "addr:full":"22100 Como Como Como 22100",
    "addr:postcode":"22100;22100",
    "iso:country":"IT",
    "sg:address":"22100 Como",
    "sg:city":"Como",
    "sg:orig_category":"Profumi - Produzione E Commercio",
    "sg:phone":"+39 031 268190",
    "sg:postcode":"22100",
    "sg:province":"Como",
    "wof:name":"Numeri Srl - Div. Erre - A.",
    "wof:placetype":"venue"
},
  "geometry": {"coordinates":[9.0891170502,45.8043785095],"type":"Point"}
}