{
  "type": "Feature",
  "properties": {
    "addr:full":"25050 Pian Camuno Pian Camuno Brescia 25050",
    "addr:postcode":"25050;25050",
    "iso:country":"IT",
    "sg:address":"25050 Pian Camuno",
    "sg:city":"Pian Camuno",
    "sg:orig_category":"Motori Ed Organi Di Trasmissione",
    "sg:phone":"+39 036 459 0053",
    "sg:postcode":"25050",
    "sg:province":"Brescia",
    "wof:name":"Colosio Erminio",
    "wof:placetype":"venue"
},
  "geometry": {"coordinates":[10.1298828125,45.8358192444],"type":"Point"}
}