{
  "type": "Feature",
  "properties": {
    "addr:full":"10024 Moncalieri Barauda Torino 10024",
    "addr:postcode":"10024;10024",
    "iso:country":"IT",
    "sg:address":"10024 Moncalieri",
    "sg:city":"Barauda",
    "sg:orig_category":"Utensili Meccanici E Materiali",
    "sg:phone":"+39 011 646 7145",
    "sg:postcode":"10024",
    "sg:province":"Torino",
    "wof:name":"Delta Model (s.n.c.)",
    "wof:placetype":"venue"
},
  "geometry": {"coordinates":[7.673458,44.976852],"type":"Point"}
}