{
  "type": "Feature",
  "properties": {
    "iso:country":"IT",
    "sg:address":"90147 Palermo",
    "sg:city":"Palermo",
    "sg:orig_category":"Automobili E Mezzi Di Trasporto",
    "sg:phone":"+39 091 688 1259",
    "sg:postcode":"90147",
    "sg:province":"Palermo",
    "wof:name":"Sira Srl",
    "wof:placetype":"venue"
},
  "geometry": {"coordinates":[13.313894,38.162819],"type":"Point"}
}