{
  "type": "Feature",
  "properties": {
    "iso:country":"IT",
    "sg:address":"20143 Milano",
    "sg:city":"Milano",
    "sg:orig_category":"Arredo Camera Letto E Complementi",
    "sg:phone":"+39 02 813 4552",
    "sg:postcode":"20143",
    "sg:province":"Milano",
    "wof:name":"Asta Barona Il Mercatone Srl",
    "wof:placetype":"venue"
},
  "geometry": {"coordinates":[9.221858,45.457394],"type":"Point"}
}