{
  "type": "Feature",
  "properties": {
    "iso:country":"IT",
    "sg:address":"20094 Corsico",
    "sg:city":"Corsico",
    "sg:orig_category":"Articoli Per Imballaggio E Confezionamento",
    "sg:phone":"+39 02 440 0708",
    "sg:postcode":"20094",
    "sg:province":"Milano",
    "wof:name":"Lineapiu' Di Peviani Claudio",
    "wof:placetype":"venue"
},
  "geometry": {"coordinates":[9.09387,45.432491],"type":"Point"}
}