{
  "type": "Feature",
  "properties": {
    "addr:full":"22070 Grandate Grandate Como 22070",
    "addr:postcode":"22070;22070",
    "iso:country":"IT",
    "sg:address":"22070 Grandate",
    "sg:city":"Grandate",
    "sg:orig_category":"Macchine E Forniture Per Industria Orafa E Per Orologeria",
    "sg:phone":"+39 031 394111",
    "sg:postcode":"22070",
    "sg:province":"Como",
    "wof:name":"Binda I (s.p.a.)",
    "wof:placetype":"venue"
},
  "geometry": {"coordinates":[9.056528,45.772713],"type":"Point"}
}