{
  "type": "Feature",
  "properties": {
    "iso:country":"IT",
    "sg:address":"21, Via Beato Michele Carcano 22070 Bregnano",
    "sg:city":"Bregnano",
    "sg:classifiers":[
        {
            "category":"Wholesale",
            "subcategory":"Drugs",
            "type":"Manufacturing & Wholesale Goods"
        }
    ],
    "sg:phone":"+39 39031722828",
    "sg:postcode":"22070",
    "sg:province":"Como",
    "sg:tags":[
        "chemical",
        "pharmaceutical"
    ],
    "wof:name":"Pezzoli Petroli Srl",
    "wof:placetype":"venue"
},
  "geometry": {"coordinates":[9.057705,45.690956],"type":"Point"}
}