{
  "type": "Feature",
  "properties": {
    "iso:country":"IT",
    "sg:address":"41100 Modena",
    "sg:city":"Modena",
    "sg:orig_category":"Macchine, Impianti Ed Attrezzature Per Abbigliamento E Pelletterie",
    "sg:phone":"+39 059 391237",
    "sg:postcode":"41100",
    "sg:province":"Modena",
    "wof:name":"Fella Giuseppe",
    "wof:placetype":"venue"
},
  "geometry": {"coordinates":[10.938633,44.546932],"type":"Point"}
}