{
  "type": "Feature",
  "properties": {
    "iso:country":"IT",
    "sg:address":"Contrada Torrepalazzo 82030 Torrecuso",
    "sg:city":"Torrecuso",
    "sg:classifiers":[
        {
            "category":"Real Estate",
            "subcategory":"Surveying",
            "type":"Services"
        }
    ],
    "sg:phone":"+39 0824 876770",
    "sg:postcode":"82030",
    "sg:province":"Benevento",
    "sg:tags":[
        "equipment",
        "material",
        "good",
        "-",
        "handling"
    ],
    "wof:name":"Cormas Srl",
    "wof:placetype":"venue"
},
  "geometry": {"coordinates":[14.739593,41.191399],"type":"Point"}
}