{
  "type": "Feature",
  "properties": {
    "iso:country":"IT",
    "sg:address":"21040 Cislago",
    "sg:city":"Cislago",
    "sg:orig_category":"Servizi E Lavori Per Edilizia E Lavori Pubblici. Acqua, Luce, Gas E Societa' Di Esercizio Pubblico",
    "sg:phone":"+39 02 9640 8497",
    "sg:postcode":"21040",
    "sg:province":"Varese",
    "wof:name":"Enel Direz. Trasm. Milano - Staz. Elettrica",
    "wof:placetype":"venue"
},
  "geometry": {"coordinates":[8.863248,45.777733],"type":"Point"}
}