{
  "type": "Feature",
  "properties": {
    "addr:full":"35026 Conselve Conselve Padova 35026",
    "addr:postcode":"35026;35026",
    "iso:country":"IT",
    "sg:address":"35026 Conselve",
    "sg:city":"Conselve",
    "sg:orig_category":"Trattamenti Termici E Superficiali Metalli, Galvanotecnica",
    "sg:phone":"+39 049 950 1197",
    "sg:postcode":"35026",
    "sg:province":"Padova",
    "wof:name":"Barillari Claudio",
    "wof:placetype":"venue"
},
  "geometry": {"coordinates":[11.861733,45.268593],"type":"Point"}
}