{
  "type": "Feature",
  "properties": {
    "iso:country":"IT",
    "sg:address":"21053 Castellanza",
    "sg:city":"Castellanza",
    "sg:orig_category":"Prodotti Di Base E Forniture Per Industria Alimentare E Bevande. Carta, Cartone E Prodotti Primari. Forniture Per Attivita' Commerciali Ed Artigianali",
    "sg:phone":"+39 0331 503578",
    "sg:postcode":"21053",
    "sg:province":"Varese",
    "wof:name":"Romo Giorgio",
    "wof:placetype":"venue"
},
  "geometry": {"coordinates":[8.8358831406,45.8097496033],"type":"Point"}
}