{
  "type": "Feature",
  "properties": {
    "addr:full":"20154 Milano Milano Milano 20154",
    "addr:postcode":"20154;20154",
    "iso:country":"IT",
    "sg:address":"20154 Milano",
    "sg:city":"Milano",
    "sg:orig_category":"Assicurazioni E Servizi Assicurativi",
    "sg:phone":"+39 0262961",
    "sg:postcode":"20154",
    "sg:province":"Milano",
    "sg:website":"http://www.alleanzaassicurazioni.it",
    "wof:name":"Alleanza Assicurazioni Spa",
    "wof:placetype":"venue"
},
  "geometry": {"coordinates":[9.187387,45.483398],"type":"Point"}
}