{
  "type": "Feature",
  "properties": {
    "iso:country":"IT",
    "sg:address":"15, Via Fizzo 82010 Bucciano",
    "sg:city":"Bucciano",
    "sg:classifiers":[
        {
            "category":"Shopping",
            "subcategory":"Clothing, Apparel, & Fashions",
            "type":"Retail Goods"
        }
    ],
    "sg:phone":"+39 0823 713855",
    "sg:postcode":"82010",
    "sg:province":"Benevento",
    "sg:tags":[
        "clothes"
    ],
    "wof:name":"Free Time Srl",
    "wof:placetype":"venue"
},
  "geometry": {"coordinates":[14.612158,41.068684],"type":"Point"}
}