{
  "type": "Feature",
  "properties": {
    "addr:full":"22063 Cantu' Como 22063",
    "addr:postcode":"22063;22063",
    "addr:street":"Cantu ' Como",
    "iso:country":"IT",
    "sg:address":"22063 Cantu'",
    "sg:classifiers":[
        {
            "category":"Health Services",
            "subcategory":"Health Practitioner",
            "type":"Services"
        }
    ],
    "sg:phone":"+39 031 720228",
    "sg:postcode":"22063",
    "sg:province":"Como",
    "sg:tags":[
        "medici"
    ],
    "wof:name":"Scavino Sergio",
    "wof:placetype":"venue"
},
  "geometry": {"coordinates":[9.1302318573,45.749546051],"type":"Point"}
}