{
  "type": "Feature",
  "properties": {
    "iso:country":"IT",
    "sg:address":"20093 Cologno Monzese",
    "sg:city":"Cologno Monzese",
    "sg:orig_category":"Arredamenti E Mobili Professionali. Impianti, Attrezzature E Forniture Sanitarie Ed Ospedaliere",
    "sg:phone":"+39 02 254 2863",
    "sg:postcode":"20093",
    "sg:province":"Milano",
    "wof:name":"L'isola Del Bagno E C. (s.a.s.)",
    "wof:placetype":"venue"
},
  "geometry": {"coordinates":[9.26747,45.547657],"type":"Point"}
}