{
  "type": "Feature",
  "properties": {
    "iso:country":"IT",
    "sg:address":"Via Padova, 1; Udine; 33100",
    "sg:city":"Udine",
    "sg:classifiers":[
        {
            "category":"Banks & Credit Unions",
            "subcategory":"Bank",
            "type":"Services"
        }
    ],
    "sg:phone":"+39 0432 402777",
    "sg:postcode":"33100",
    "sg:province":"Udine",
    "wof:name":"Cassa Di Risparmio Di Udine, E Pordenone",
    "wof:placetype":"venue"
},
  "geometry": {"coordinates":[13.247629,46.030373],"type":"Point"}
}