{
  "type": "Feature",
  "properties": {
    "iso:country":"IT",
    "sg:address":"Via Giacomo Matteotti 145/d 28077 Prato Sesia",
    "sg:city":"Prato Sesia",
    "sg:classifiers":[
        {
            "category":"Building & Trades",
            "subcategory":"Construction",
            "type":"Services"
        }
    ],
    "sg:phone":"+39 0163 852716",
    "sg:postcode":"28077",
    "sg:province":"Novara",
    "sg:tags":[
        "valve"
    ],
    "sg:website":"www.idrosfer.it",
    "wof:name":"Idrosfer Di Negri Roberto & C.s.n.c",
    "wof:placetype":"venue"
},
  "geometry": {"coordinates":[8.358487,45.65913],"type":"Point"}
}