{
  "type": "Feature",
  "properties": {
    "iso:country":"IT",
    "sg:address":"31050 Vedelago",
    "sg:city":"Fanzolo",
    "sg:orig_category":"Impiantistica E Prodotti Tecnologici Per Edilizia. Elettrotecnica Industriale, Prodotti E Apparecchiature",
    "sg:phone":"+39 0423 487141",
    "sg:postcode":"31050",
    "sg:province":"Treviso",
    "wof:name":"Idl Export Srl",
    "wof:placetype":"venue"
},
  "geometry": {"coordinates":[11.986403,45.711243],"type":"Point"}
}