{
  "type": "Feature",
  "properties": {
    "iso:country":"IT",
    "sg:address":"74100 Taranto",
    "sg:city":"Taranto",
    "sg:orig_category":"Arredamenti - Vendita Al Dettaglio",
    "sg:phone":"+39 099 730 4062",
    "sg:postcode":"74100",
    "sg:province":"Taranto",
    "wof:name":"Tessilarredo Srl",
    "wof:placetype":"venue"
},
  "geometry": {"coordinates":[17.263792,40.466282],"type":"Point"}
}