{
  "type": "Feature",
  "properties": {
    "iso:country":"IT",
    "sg:address":"10098 Rivoli",
    "sg:city":"Rivoli",
    "sg:orig_category":"Macchine E Forniture Per Ecologia E Smaltimento Rifiuti. Termotecnica E Riscaldamento, Apparecchiature E Servizi",
    "sg:phone":"+39 011 953 0791",
    "sg:postcode":"10098",
    "sg:province":"Torino",
    "wof:name":"Ardito Srl",
    "wof:placetype":"venue"
},
  "geometry": {"coordinates":[7.517437,45.078655],"type":"Point"}
}