{
  "type": "Feature",
  "properties": {
    "addr:full":"00195 Roma Roma Roma 00195",
    "addr:postcode":"00195;00195",
    "iso:country":"IT",
    "sg:address":"00195 Roma",
    "sg:city":"Roma",
    "sg:orig_category":"Cinematografia E Radiotelevisione. Cine-foto-ottica",
    "sg:phone":"+39 06 324 4252",
    "sg:postcode":"00195",
    "sg:province":"Roma",
    "wof:name":"Cattleya S.r.l.",
    "wof:placetype":"venue"
},
  "geometry": {"coordinates":[12.465898,41.915283],"type":"Point"}
}