{
  "type": "Feature",
  "properties": {
    "addr:full":"82100 Benevento Benevento Benevento 82100",
    "addr:postcode":"82100;82100",
    "iso:country":"IT",
    "sg:address":"82100 Benevento",
    "sg:city":"Benevento",
    "sg:orig_category":"Forniture Per Attivita' Industriali",
    "sg:phone":"+39 0824 357248",
    "sg:postcode":"82100",
    "sg:province":"Benevento",
    "wof:name":"Tools Srl",
    "wof:placetype":"venue"
},
  "geometry": {"coordinates":[14.7754306793,41.1413879395],"type":"Point"}
}