{
  "type": "Feature",
  "properties": {
    "iso:country":"IT",
    "sg:address":"74100 Taranto",
    "sg:city":"Taranto",
    "sg:orig_category":"Studi E Consulenze Amministrative, Commerciali E Aziendali. Studi E Consulenze Tecniche E Industriali. Consulenze Tecniche, Amministrative E Perizie",
    "sg:phone":"+39 099 452 6267",
    "sg:postcode":"74100",
    "sg:province":"Taranto",
    "wof:name":"Smi Invest Srl Agenzia Immobiliare E Finanziaria",
    "wof:placetype":"venue"
},
  "geometry": {"coordinates":[17.503592,40.454437],"type":"Point"}
}