{
  "type": "Feature",
  "properties": {
    "addr:full":"22021 Bellagio Bellagio Como 22021",
    "addr:postcode":"22021;22021",
    "iso:country":"IT",
    "sg:address":"22021 Bellagio",
    "sg:city":"Bellagio",
    "sg:orig_category":"Pompe - Produzione",
    "sg:phone":"+39 031 950242",
    "sg:postcode":"22021",
    "sg:province":"Como",
    "wof:name":"Gilardoni Fratelli Srl",
    "wof:placetype":"venue"
},
  "geometry": {"coordinates":[9.2461643219,45.9641304016],"type":"Point"}
}