{
  "type": "Feature",
  "properties": {
    "iso:country":"IT",
    "sg:address":"80078 Pozzuoli",
    "sg:city":"Pozzuoli",
    "sg:orig_category":"Macchine Ed Impianti Per Edilizia E Lavori Pubblici. Forniture Per Edilizia E Lavori Pubblici",
    "sg:phone":"+39 081 526 5209",
    "sg:postcode":"80078",
    "sg:province":"Napoli",
    "wof:name":"Viesse Srl",
    "wof:placetype":"venue"
},
  "geometry": {"coordinates":[14.120264,40.856792],"type":"Point"}
}