{
  "type": "Feature",
  "properties": {
    "addr:full":"Via Jacopo Linussio 1 33020 Amaro Amaro Udine 33020",
    "addr:housenumber":"1",
    "addr:postcode":"33020;33020",
    "addr:street":"Via Jacopo Linussio",
    "iso:country":"IT",
    "sg:address":"Via Jacopo Linussio 1 33020 Amaro",
    "sg:city":"Amaro",
    "sg:orig_category":"Vascular Protheses",
    "sg:phone":"+39 0433 468376",
    "sg:postcode":"33020",
    "sg:province":"Udine",
    "sg:website":"www.p1h.it",
    "wof:name":"Plan 1 Health S.r.l.",
    "wof:placetype":"venue"
},
  "geometry": {"coordinates":[13.076896,46.370304],"type":"Point"}
}