{
  "type": "Feature",
  "properties": {
    "iso:country":"IT",
    "sg:address":"20154 Milano",
    "sg:city":"Milano",
    "sg:orig_category":"Valvole E Apparecchiature Di Misura. Ricambi E Componenti Dei Mezzi Di Trasporto",
    "sg:phone":"+39 02 314288",
    "sg:postcode":"20154",
    "sg:province":"Milano",
    "wof:name":"A.t.i. C. Europe Srl Advanced Technologies Installation Company",
    "wof:placetype":"venue"
},
  "geometry": {"coordinates":[9.171356,45.488579],"type":"Point"}
}