{
  "type": "Feature",
  "properties": {
    "addr:full":"24050 Calcinate Calcinate Bergamo 24050",
    "addr:postcode":"24050;24050",
    "iso:country":"IT",
    "sg:address":"24050 Calcinate",
    "sg:city":"Calcinate",
    "sg:orig_category":"Legno E Semilavorati. Manufatti Edili E Prefabbricati",
    "sg:phone":"+39 035 442 3384",
    "sg:postcode":"24050",
    "sg:province":"Bergamo",
    "wof:name":"Betapali S.a.s. Di Bonini Teresina",
    "wof:placetype":"venue"
},
  "geometry": {"coordinates":[9.812567,45.620098],"type":"Point"}
}