{
  "type": "Feature",
  "properties": {
    "addr:full":"Via Crispi 1/c; Campobasso; 86100 Campobasso Campobasso 86100",
    "addr:housenumber":"1 / c",
    "addr:postcode":"86100;86100",
    "addr:street":"Via Crispi",
    "iso:country":"IT",
    "sg:address":"Via Crispi 1/c; Campobasso; 86100",
    "sg:city":"Campobasso",
    "sg:classifiers":[
        {
            "category":"Banks & Credit Unions",
            "subcategory":"Bank",
            "type":"Services"
        }
    ],
    "sg:phone":"+39 0874 6691",
    "sg:postcode":"86100",
    "sg:province":"Campobasso",
    "wof:name":"Banca Di Roma",
    "wof:placetype":"venue"
},
  "geometry": {"coordinates":[14.665393,41.56076],"type":"Point"}
}