{
  "type": "Feature",
  "properties": {
    "iso:country":"IT",
    "sg:address":"20131 Milano",
    "sg:city":"Milano",
    "sg:orig_category":"Servizi E Lavori Per Agricoltura E Zootecnia. Animali Domestici",
    "sg:phone":"+39 02 261 9115",
    "sg:postcode":"20131",
    "sg:province":"Milano",
    "wof:name":"Doggy Di Eusebio Giuliana Cesarina",
    "wof:placetype":"venue"
},
  "geometry": {"coordinates":[9.221355,45.489655],"type":"Point"}
}