{
  "type": "Feature",
  "properties": {
    "addr:full":"00151 Roma Roma Roma 00151",
    "addr:postcode":"00151;00151",
    "iso:country":"IT",
    "sg:address":"00151 Roma",
    "sg:city":"Roma",
    "sg:orig_category":"Forniture Per Abbigliamento E Pelletterie",
    "sg:phone":"+39 06 582 7647",
    "sg:postcode":"00151",
    "sg:province":"Roma",
    "wof:name":"La Rosa Creazioni Di Sanna Francesca",
    "wof:placetype":"venue"
},
  "geometry": {"coordinates":[12.4459753036,41.8723564148],"type":"Point"}
}