{
  "type": "Feature",
  "properties": {
    "iso:country":"IT",
    "sg:address":"Via Baracchini Flavio 9 20123 Milano",
    "sg:city":"Milano",
    "sg:classifiers":[
        {
            "category":"Shopping",
            "subcategory":"Jewelry",
            "type":"Retail Goods"
        }
    ],
    "sg:phone":"+39 02 8646 3143",
    "sg:postcode":"20123",
    "sg:province":"Milano",
    "sg:tags":[
        "fashion",
        "jewellery"
    ],
    "wof:name":"Diagonal Srl",
    "wof:placetype":"venue"
},
  "geometry": {"coordinates":[9.1910705566,45.4613876343],"type":"Point"}
}