{
  "type": "Feature",
  "properties": {
    "addr:full":"25030 Coccaglio Coccaglio Brescia 25030",
    "addr:postcode":"25030;25030",
    "iso:country":"IT",
    "sg:address":"25030 Coccaglio",
    "sg:city":"Coccaglio",
    "sg:orig_category":"Articoli Per Imballaggio E Confezionamento",
    "sg:phone":"+39 030 772 1012",
    "sg:postcode":"25030",
    "sg:province":"Brescia",
    "wof:name":"Tubettificio Pedercini (s.r.l.)",
    "wof:placetype":"venue"
},
  "geometry": {"coordinates":[9.956306,45.59914],"type":"Point"}
}