{
  "type": "Feature",
  "properties": {
    "iso:country":"IT",
    "sg:address":"Via Marie Curie 9 50051 Castelfiorentino",
    "sg:city":"Castelfiorentino",
    "sg:classifiers":[
        {
            "category":"Home & Garden",
            "subcategory":"Hardware",
            "type":"Retail Goods"
        }
    ],
    "sg:phone":"+39 0571 61001",
    "sg:postcode":"50051",
    "sg:province":"Firenze",
    "sg:tags":[
        "small",
        "ironware",
        "item"
    ],
    "sg:website":"www.puccioni.com",
    "wof:name":"Puccioni Metallurgica Srl",
    "wof:placetype":"venue"
},
  "geometry": {"coordinates":[10.989837,43.58989],"type":"Point"}
}