{
  "type": "Feature",
  "properties": {
    "iso:country":"IT",
    "sg:address":"35043 Monselice",
    "sg:city":"Monselice",
    "sg:orig_category":"Campeggio",
    "sg:phone":"+39 0429 780948",
    "sg:postcode":"35043",
    "sg:province":"Padova",
    "wof:name":"I.a.c.c. Di Bertin G. E C. (s.n.c.)",
    "wof:placetype":"venue"
},
  "geometry": {"coordinates":[11.656878,44.977913],"type":"Point"}
}