{
  "type": "Feature",
  "properties": {
    "iso:country":"IT",
    "sg:address":"23900 Lecco",
    "sg:city":"Lecco",
    "sg:orig_category":"Ospedali E Servizi Sanitari",
    "sg:phone":"+39 0341 251412",
    "sg:postcode":"23900",
    "sg:province":"Lecco",
    "wof:name":"Antismoking Center",
    "wof:placetype":"venue"
},
  "geometry": {"coordinates":[9.40027,45.865166],"type":"Point"}
}