{
  "type": "Feature",
  "properties": {
    "addr:full":"20016 Pero Pero Milano 20016",
    "addr:postcode":"20016;20016",
    "iso:country":"IT",
    "sg:address":"20016 Pero",
    "sg:city":"Pero",
    "sg:orig_category":"Prodotti Chimici Secondari. Macchine, Impianti Ed Attrezzature Industria Chimica. Servizi E Lavori Industria Chimica",
    "sg:phone":"+39 02 3391 5196",
    "sg:postcode":"20016",
    "sg:province":"Milano",
    "wof:name":"Coster Tecnologie Speciali S.p.a.",
    "wof:placetype":"venue"
},
  "geometry": {"coordinates":[9.087480545,45.4998474121],"type":"Point"}
}