{
  "type": "Feature",
  "properties": {
    "addr:full":"20010 Bareggio Bareggio Milano 20010",
    "addr:postcode":"20010;20010",
    "iso:country":"IT",
    "sg:address":"20010 Bareggio",
    "sg:city":"Bareggio",
    "sg:orig_category":"Forniture Per Attivita' Industriali",
    "sg:phone":"+39 02 9036 1148",
    "sg:postcode":"20010",
    "sg:province":"Milano",
    "wof:name":"A.c.m. Snc",
    "wof:placetype":"venue"
},
  "geometry": {"coordinates":[9.0024557114,45.4766311646],"type":"Point"}
}