{
  "type": "Feature",
  "properties": {
    "iso:country":"IT",
    "sg:address":"3, Via Postiglione Gaetano 70126 Bari",
    "sg:city":"Bari",
    "sg:classifiers":[
        {
            "category":"Communications",
            "subcategory":"Newspaper",
            "type":"Services"
        }
    ],
    "sg:phone":"+39 080 553 1901",
    "sg:postcode":"70126",
    "sg:province":"Bari",
    "sg:tags":[
        "advertising"
    ],
    "wof:name":"Eta Advertising S.n.c.",
    "wof:placetype":"venue"
},
  "geometry": {"coordinates":[16.876621,41.112411],"type":"Point"}
}