{
  "type": "Feature",
  "properties": {
    "iso:country":"IT",
    "sg:address":"10131 Torino",
    "sg:city":"Torino",
    "sg:orig_category":"Videocassette - Vendita E Noleggio",
    "sg:phone":"+39 011 819 7414",
    "sg:postcode":"10131",
    "sg:province":"Torino",
    "wof:name":"Video 23 Di Cicchelli",
    "wof:placetype":"venue"
},
  "geometry": {"coordinates":[7.72157,45.052528],"type":"Point"}
}