{
  "type": "Feature",
  "properties": {
    "addr:full":"94010 Assoro Assoro Enna 94010",
    "addr:postcode":"94010;94010",
    "iso:country":"IT",
    "sg:address":"94010 Assoro",
    "sg:city":"Assoro",
    "sg:orig_category":"Servizi E Lavori Per Agricoltura E Zootecnia. Servizi E Lavori Industria Chimica. Servizi Ausiliari Di Analisi, Controllo E Ricerca",
    "sg:phone":"+39 0935 667314",
    "sg:postcode":"94010",
    "sg:province":"Enna",
    "wof:name":"Montagna Antonio",
    "wof:placetype":"venue"
},
  "geometry": {"coordinates":[14.422998,37.625782],"type":"Point"}
}