{
  "type": "Feature",
  "properties": {
    "iso:country":"IT",
    "sg:address":"10072 Caselle Torinese",
    "sg:city":"Caselle Torinese",
    "sg:orig_category":"Banche E Servizi Finanziari. Acqua, Luce, Gas E Societa' Di Esercizio Pubblico",
    "sg:phone":"+39 011 991 2896",
    "sg:postcode":"10072",
    "sg:province":"Torino",
    "wof:name":"Uniriscossioni S.p.a.",
    "wof:placetype":"venue"
},
  "geometry": {"coordinates":[7.658156,45.146561],"type":"Point"}
}