{
  "type": "Feature",
  "properties": {
    "addr:full":"10, Via Silenzio 80044 Ottaviano Ottaviano Napoli 80044",
    "addr:postcode":"80044;80044",
    "addr:street":"Via Silenzio",
    "iso:country":"IT",
    "sg:address":"10, Via Silenzio 80044 Ottaviano",
    "sg:city":"Ottaviano",
    "sg:classifiers":[
        {
            "category":"Shopping",
            "subcategory":"Clothing, Apparel, & Fashions",
            "type":"Retail Goods"
        }
    ],
    "sg:phone":"+39 081 827 8524",
    "sg:postcode":"80044",
    "sg:province":"Napoli",
    "sg:tags":[
        "clothes"
    ],
    "wof:name":"Lingerie Favola Srl",
    "wof:placetype":"venue"
},
  "geometry": {"coordinates":[14.251636,40.840096],"type":"Point"}
}