{
  "type": "Feature",
  "properties": {
    "iso:country":"IT",
    "sg:address":"2, V. Casa Rossa 40010 Bentivoglio",
    "sg:city":"Bentivoglio",
    "sg:classifiers":[
        {
            "category":"Manufacturing",
            "subcategory":"Metals",
            "type":"Manufacturing & Wholesale Goods"
        }
    ],
    "sg:phone":"+39 39051866311",
    "sg:postcode":"40010",
    "sg:province":"Bologna",
    "sg:tags":[
        "processing"
    ],
    "sg:website":"http://www.sinteris.com:ws_end: :mark:ws:http://www.paginegialle.it/sinteris",
    "wof:name":"Sinteris Srl",
    "wof:placetype":"venue"
},
  "geometry": {"coordinates":[11.6568784714,44.9779129028],"type":"Point"}
}