{
  "type": "Feature",
  "properties": {
    "iso:country":"IT",
    "sg:address":"271, Via Del Lavoro 37050 Angiari",
    "sg:city":"Angiari",
    "sg:classifiers":[
        {
            "category":"Utilities",
            "subcategory":"Electric",
            "type":"Services"
        }
    ],
    "sg:phone":"+39 39044298141",
    "sg:postcode":"37050",
    "sg:province":"Verona",
    "sg:tags":[
        "component",
        "electronic"
    ],
    "wof:name":"P.a.c. Circuiti Stampati S.r.l.",
    "wof:placetype":"venue"
},
  "geometry": {"coordinates":[11.242513,45.226917],"type":"Point"}
}