{
  "type": "Feature",
  "properties": {
    "iso:country":"IT",
    "sg:address":"20060 Pozzo D'adda",
    "sg:orig_category":"Ricambi E Componenti Dei Mezzi Di Trasporto",
    "sg:phone":"+39 02 9096 0755",
    "sg:postcode":"20060",
    "sg:province":"Milano",
    "wof:name":"Radiatori Adda",
    "wof:placetype":"venue"
},
  "geometry": {"coordinates":[9.526577,45.581596],"type":"Point"}
}