{
  "type": "Feature",
  "properties": {
    "iso:country":"IT",
    "sg:address":"80026 Casoria",
    "sg:city":"Casoria",
    "sg:orig_category":"Forni Elettrici Industriali",
    "sg:phone":"+39 081 757 7115",
    "sg:postcode":"80026",
    "sg:province":"Napoli",
    "wof:name":"Tedicon Russo Ferdinando",
    "wof:placetype":"venue"
},
  "geometry": {"coordinates":[14.2896595001,40.9201507568],"type":"Point"}
}