{
  "type": "Feature",
  "properties": {
    "iso:country":"IT",
    "sg:address":"5, Corso Asti 12051 Alba",
    "sg:city":"Alba",
    "sg:classifiers":[
        {
            "category":"Travel",
            "subcategory":"Travel Agent",
            "type":"Entertainment"
        }
    ],
    "sg:phone":"+39 0173 363251",
    "sg:postcode":"12051",
    "sg:province":"Cuneo",
    "sg:tags":[
        "business"
    ],
    "wof:name":"Motel Alba (s.n.c.)",
    "wof:placetype":"venue"
},
  "geometry": {"coordinates":[8.114513,44.781071],"type":"Point"}
}