{
  "type": "Feature",
  "properties": {
    "iso:country":"IT",
    "sg:address":"28/32, V. Pizzi 20141 Milano",
    "sg:city":"Milano",
    "sg:classifiers":[
        {
            "category":"Utilities",
            "subcategory":"Electric",
            "type":"Services"
        }
    ],
    "sg:phone":"+39 02 5521 2193",
    "sg:postcode":"20141",
    "sg:province":"Milano",
    "sg:tags":[
        "component",
        "electronic"
    ],
    "sg:website":"http://www.applicazionivam.com",
    "wof:name":"Applicazioni Vam",
    "wof:placetype":"venue"
},
  "geometry": {"coordinates":[9.202239,45.43697],"type":"Point"}
}