{
  "type": "Feature",
  "properties": {
    "iso:country":"IT",
    "sg:address":"25021 Bagnolo Mella",
    "sg:city":"Bagnolo Mella",
    "sg:orig_category":"Abbigliamento Esterno, Maglierie E Pelliccerie. Shopping",
    "sg:phone":"+39 030 682 1522",
    "sg:postcode":"25021",
    "sg:province":"Brescia",
    "wof:name":"Olivari Giuseppe & C. Snc",
    "wof:placetype":"venue"
},
  "geometry": {"coordinates":[10.168282,45.422047],"type":"Point"}
}