{
  "type": "Feature",
  "properties": {
    "iso:country":"IT",
    "sg:address":"Via Rossini 7 20010 Bareggio",
    "sg:city":"Bareggio",
    "sg:orig_category":"Hourglasses",
    "sg:phone":"+39 02 9036 1286",
    "sg:postcode":"20010",
    "sg:province":"Milano",
    "sg:website":"www.pristerm.it",
    "wof:name":"Pris Term Srl",
    "wof:placetype":"venue"
},
  "geometry": {"coordinates":[9.008228,45.485069],"type":"Point"}
}