{
  "type": "Feature",
  "properties": {
    "iso:country":"IT",
    "sg:address":"Via Monte Cimone 1 36073 Cornedo Vicentino",
    "sg:city":"Cornedo Vicentino",
    "sg:classifiers":[
        {
            "category":"Shopping",
            "subcategory":"Clothing, Apparel, & Fashions",
            "type":"Retail Goods"
        }
    ],
    "sg:phone":"+39 0445 446455",
    "sg:postcode":"36073",
    "sg:province":"Vicenza",
    "sg:tags":[
        "leather",
        "clothing"
    ],
    "wof:name":"I.d. Leather Srl",
    "wof:placetype":"venue"
},
  "geometry": {"coordinates":[11.323265,45.618988],"type":"Point"}
}