{
  "type": "Feature",
  "properties": {
    "iso:country":"IT",
    "sg:address":"22021 Bellagio",
    "sg:city":"Bellagio",
    "sg:orig_category":"Materiali Semilavorati Metallici",
    "sg:phone":"+39 031 951254",
    "sg:postcode":"22021",
    "sg:province":"Como",
    "wof:name":"Locatelli Mario",
    "wof:placetype":"venue"
},
  "geometry": {"coordinates":[9.229726,45.964565],"type":"Point"}
}