{
  "type": "Feature",
  "properties": {
    "addr:full":"24066 Pedrengo Pedrengo Bergamo 24066",
    "addr:postcode":"24066;24066",
    "iso:country":"IT",
    "sg:address":"24066 Pedrengo",
    "sg:city":"Pedrengo",
    "sg:orig_category":"Apparecchiature E Sistemi Per Imballaggio E Confezionamento",
    "sg:phone":"+39 035 667111",
    "sg:postcode":"24066",
    "sg:province":"Bergamo",
    "wof:name":"Reepack S.r.l.",
    "wof:placetype":"venue"
},
  "geometry": {"coordinates":[9.74581,45.692917],"type":"Point"}
}