{
  "type": "Feature",
  "properties": {
    "iso:country":"IT",
    "sg:address":"38045 Civezzano",
    "sg:city":"Civezzano",
    "sg:orig_category":"Gru - Costruzione E Commercio",
    "sg:phone":"+39 0461 858491",
    "sg:postcode":"38045",
    "sg:province":"Trento",
    "wof:name":"Hoist Srl",
    "wof:placetype":"venue"
},
  "geometry": {"coordinates":[11.201654,46.086109],"type":"Point"}
}