{
  "type": "Feature",
  "properties": {
    "iso:country":"IT",
    "sg:address":"09025 Sanluri",
    "sg:city":"Sanluri",
    "sg:orig_category":"Ricambi E Componenti Dei Mezzi Di Trasporto. Riparazione Dei Mezzi Di Trasporto",
    "sg:phone":"+39 070 937 0525",
    "sg:postcode":"09025",
    "sg:province":"Medio Campidano",
    "wof:name":"Eurogas Di Ibba Giovanna",
    "wof:placetype":"venue"
},
  "geometry": {"coordinates":[8.704075,39.531738],"type":"Point"}
}