{
  "type": "Feature",
  "properties": {
    "addr:full":"80045 Pompei Pompei Napoli 80045",
    "addr:housenumber":"80045",
    "addr:postcode":"80045",
    "iso:country":"IT",
    "sg:address":"80045 Pompei",
    "sg:city":"Pompei",
    "sg:orig_category":"Forniture Per Attivita' Commerciali Ed Artigianali. Arredi Ed Attrezzature Per Attivita' Commerciali Ed Artigianali",
    "sg:phone":"+39 081 863 9040",
    "sg:postcode":"80045",
    "sg:province":"Napoli",
    "wof:name":"Fanec Sas Di Ernesto Moraldo",
    "wof:placetype":"venue"
},
  "geometry": {"coordinates":[14.503692627,40.748878479],"type":"Point"}
}