{
  "type": "Feature",
  "properties": {
    "iso:country":"IT",
    "sg:address":"00185 Roma",
    "sg:city":"Roma",
    "sg:orig_category":"Associazioni Ed Istituti Di Previdenza Ed Assistenza",
    "sg:phone":"+39 0677351",
    "sg:postcode":"00185",
    "sg:province":"Roma",
    "sg:website":"http://www.inpdap.it/",
    "wof:name":"Inpdap",
    "wof:placetype":"venue"
},
  "geometry": {"coordinates":[12.510909,41.890839],"type":"Point"}
}