{
  "type": "Feature",
  "properties": {
    "iso:country":"IT",
    "sg:address":"80142 Napoli",
    "sg:city":"Napoli",
    "sg:orig_category":"Servizi Di Magazzinaggio E Movimentazione. Servizi Ausiliari Di Sorveglianza, Manutenzione E Pulizia",
    "sg:phone":"+39 081 554 9665",
    "sg:postcode":"80142",
    "sg:province":"Napoli",
    "wof:name":"Iannario Snc - Traslochi E Trasporti",
    "wof:placetype":"venue"
},
  "geometry": {"coordinates":[14.277389,40.847008],"type":"Point"}
}