{
  "type": "Feature",
  "properties": {
    "iso:country":"IT",
    "sg:address":"19/20, Piazzale Adriatico 48100 Ravenna",
    "sg:city":"Ravenna",
    "sg:classifiers":[
        {
            "category":"Utilities",
            "subcategory":"Telephone",
            "type":"Services"
        }
    ],
    "sg:phone":"+39 0544 531444",
    "sg:postcode":"48100",
    "sg:province":"Ravenna",
    "sg:tags":[
        "telecommunication"
    ],
    "wof:name":"Punto Vela Di Onoranti & C. (s.a.s.)",
    "wof:placetype":"venue"
},
  "geometry": {"coordinates":[12.282997,44.491035],"type":"Point"}
}