{
  "type": "Feature",
  "properties": {
    "iso:country":"IT",
    "sg:address":"34074 Monfalcone",
    "sg:city":"Monfalcone",
    "sg:orig_category":"Nautica. Ricambi E Componenti Dei Mezzi Di Trasporto",
    "sg:phone":"+39 0481 414045",
    "sg:postcode":"34074",
    "sg:province":"Gorizia",
    "wof:name":"Dade Moto Di Urizio Davide",
    "wof:placetype":"venue"
},
  "geometry": {"coordinates":[13.601861,45.925758],"type":"Point"}
}