{
  "type": "Feature",
  "properties": {
    "iso:country":"IT",
    "sg:address":"30175 Venezia",
    "sg:city":"Venezia",
    "sg:orig_category":"Apparecchiature E Sistemi Per Imballaggio E Confezionamento. Apparecchiature E Sistemi Per Magazzinaggio E Movimentazione",
    "sg:postcode":"30175",
    "sg:province":"Venezia",
    "wof:name":"Zuin Autotrasporti (s.r.l.)",
    "wof:placetype":"venue"
},
  "geometry": {"coordinates":[12.283298,45.440845],"type":"Point"}
}