{
  "type": "Feature",
  "properties": {
    "iso:country":"IT",
    "sg:address":"60019 Senigallia",
    "sg:city":"Senigallia",
    "sg:classifiers":[
        {
            "category":"Manufacturing",
            "subcategory":"Food",
            "type":"Manufacturing & Wholesale Goods"
        }
    ],
    "sg:phone":"+39 071 792 6690",
    "sg:postcode":"60019",
    "sg:province":"Ancona",
    "sg:tags":[
        "product"
    ],
    "wof:name":"Tecnopasta Snc",
    "wof:placetype":"venue"
},
  "geometry": {"coordinates":[13.1971063614,43.6896095276],"type":"Point"}
}