{
  "type": "Feature",
  "properties": {
    "addr:full":"00135 Roma Roma Roma 00135",
    "addr:postcode":"00135;00135",
    "iso:country":"IT",
    "sg:address":"00135 Roma",
    "sg:city":"Roma",
    "sg:orig_category":"Macchine E Forniture Per Ecologia E Smaltimento Rifiuti. Termotecnica E Riscaldamento, Apparecchiature E Servizi",
    "sg:phone":"+39 06 3081 2532",
    "sg:postcode":"00135",
    "sg:province":"Roma",
    "wof:name":"I.m.o.c.r.i. Di Musto Marco S.a.s.",
    "wof:placetype":"venue"
},
  "geometry": {"coordinates":[12.402611,41.955288],"type":"Point"}
}