{
  "type": "Feature",
  "properties": {
    "iso:country":"IT",
    "sg:address":"90145 Palermo",
    "sg:city":"Palermo",
    "sg:orig_category":"Frigotecnica, Apparecchiature E Servizi",
    "sg:phone":"+39 091 682 5459",
    "sg:postcode":"90145",
    "sg:province":"Palermo",
    "wof:name":"Cali' Antonino",
    "wof:placetype":"venue"
},
  "geometry": {"coordinates":[13.4844112396,38.0797386169],"type":"Point"}
}