{
  "type": "Feature",
  "properties": {
    "addr:full":"50013 Campi Bisenzio Campi Bisenzio Firenze 50013",
    "addr:postcode":"50013;50013",
    "addr:street":"Bisenzio",
    "iso:country":"IT",
    "sg:address":"50013 Campi Bisenzio",
    "sg:city":"Campi Bisenzio",
    "sg:orig_category":"Accessori Moda D'abbigliamento. Shopping",
    "sg:phone":"+39 055 897 9160",
    "sg:postcode":"50013",
    "sg:province":"Firenze",
    "sg:website":"http://www.da-me.com",
    "wof:name":"Gruppo Dame Srl",
    "wof:placetype":"venue"
},
  "geometry": {"coordinates":[11.119701,43.828533],"type":"Point"}
}