{
  "type": "Feature",
  "properties": {
    "iso:country":"IT",
    "sg:address":"20157 Milano",
    "sg:city":"Milano",
    "sg:orig_category":"Elettrotecnica Industriale, Prodotti E Apparecchiature. Forniture Per Attivita' Commerciali Ed Artigianali",
    "sg:phone":"+39 02 3900 0891",
    "sg:postcode":"20157",
    "sg:province":"Milano",
    "wof:name":"Galaxy Neon Di Ardemagni Arturo & C. (s.n.c.)",
    "wof:placetype":"venue"
},
  "geometry": {"coordinates":[9.135863,45.514584],"type":"Point"}
}