{
  "type": "Feature",
  "properties": {
    "addr:full":"Via Cambiasi Pompeo 6 20131 Milano Milano Milano 20131",
    "addr:housenumber":"6",
    "addr:postcode":"20131;20131",
    "addr:street":"Via Cambiasi Pompeo",
    "iso:country":"IT",
    "sg:address":"Via Cambiasi Pompeo 6 20131 Milano",
    "sg:city":"Milano",
    "sg:orig_category":"Brassi\u00e8re Cups",
    "sg:phone":"+39 02 284 7512",
    "sg:postcode":"20131",
    "sg:province":"Milano",
    "sg:website":"www.gostoli.com",
    "wof:name":"Gostoli Srl",
    "wof:placetype":"venue"
},
  "geometry": {"coordinates":[9.230638,45.489925],"type":"Point"}
}