{
  "type": "Feature",
  "properties": {
    "iso:country":"IT",
    "sg:address":"98124 Messina",
    "sg:city":"Messina",
    "sg:classifiers":[
        {
            "category":"Arena",
            "subcategory":"Sports Club",
            "type":"Entertainment"
        }
    ],
    "sg:phone":"+39 090 693308",
    "sg:postcode":"98124",
    "sg:province":"Messina",
    "sg:tags":[
        "e",
        "lo",
        "tempo",
        "libero",
        "per",
        "servizi",
        "il"
    ],
    "wof:name":"Imbruglia Teresa",
    "wof:placetype":"venue"
},
  "geometry": {"coordinates":[15.548043,38.178825],"type":"Point"}
}