{
  "type": "Feature",
  "properties": {
    "iso:country":"IT",
    "sg:address":"00187 Roma",
    "sg:city":"Roma",
    "sg:orig_category":"Prodotti Alimentari",
    "sg:phone":"+39 06 679 3102",
    "sg:postcode":"00187",
    "sg:province":"Roma",
    "wof:name":"Guerra Antonio",
    "wof:placetype":"venue"
},
  "geometry": {"coordinates":[12.4816169739,41.8410148621],"type":"Point"}
}