{
  "type": "Feature",
  "properties": {
    "addr:full":"1, Via Dell' Artigianato 35010 Campo San Martino Campo San Martino Padova 35010",
    "addr:postcode":"35010;35010",
    "addr:street":"Via Dell ' Artigianato;San",
    "iso:country":"IT",
    "sg:address":"1, Via Dell' Artigianato 35010 Campo San Martino",
    "sg:city":"Campo San Martino",
    "sg:classifiers":[
        {
            "category":"Manufacturing",
            "subcategory":"Paper Products",
            "type":"Manufacturing & Wholesale Goods"
        }
    ],
    "sg:phone":"+39 049 963 0288",
    "sg:postcode":"35010",
    "sg:province":"Padova",
    "sg:tags":[
        "cardboard"
    ],
    "wof:name":"Zetatre Shoppers (s.r.l.)",
    "wof:placetype":"venue"
},
  "geometry": {"coordinates":[11.80119133,45.601020813],"type":"Point"}
}