{
  "type": "Feature",
  "properties": {
    "iso:country":"IT",
    "sg:address":"22070 Rovello Porro",
    "sg:city":"Rovello Porro",
    "sg:orig_category":"Accessori Moda D'abbigliamento. Forniture Per Abbigliamento E Pelletterie. Shopping",
    "sg:phone":"+39 02 9634 3789",
    "sg:postcode":"22070",
    "sg:province":"Como",
    "wof:name":"Clerici Carlo",
    "wof:placetype":"venue"
},
  "geometry": {"coordinates":[9.088211,45.664402],"type":"Point"}
}