{
  "type": "Feature",
  "properties": {
    "iso:country":"IT",
    "sg:address":"00186 Roma",
    "sg:city":"Roma",
    "sg:orig_category":"Gioielleria, Oreficeria E Argenteria",
    "sg:phone":"+39 06 683 2988",
    "sg:postcode":"00186",
    "sg:province":"Roma",
    "wof:name":"Franchi Fausto Maria",
    "wof:placetype":"venue"
},
  "geometry": {"coordinates":[12.475382,41.903248],"type":"Point"}
}