{
  "type": "Feature",
  "properties": {
    "iso:country":"IT",
    "sg:address":"40012 Calderara Di Reno",
    "sg:city":"Calderara di Reno",
    "sg:orig_category":"Forniture Alle Strutture Ricettive. Macchine E Impianti Per Attivita' Commerciali Ed Artigianali",
    "sg:phone":"+39 051 726045",
    "sg:postcode":"40012",
    "sg:province":"Bologna",
    "wof:name":"Vgd Srl Trial Emiliana",
    "wof:placetype":"venue"
},
  "geometry": {"coordinates":[11.3011798859,44.5433082581],"type":"Point"}
}