{
  "type": "Feature",
  "properties": {
    "iso:country":"IT",
    "sg:address":"00040 Montecompatri",
    "sg:city":"Montecompatri",
    "sg:orig_category":"Forniture Per Agricoltura E Zootecnia",
    "sg:phone":"+39 5069476419",
    "sg:postcode":"00040",
    "sg:province":"Roma",
    "wof:name":"Faza Srl",
    "wof:placetype":"venue"
},
  "geometry": {"coordinates":[12.5497074127,41.8774757385],"type":"Point"}
}