{
  "type": "Feature",
  "properties": {
    "addr:full":"Via Amendola 9/g; Bologna; 40121 Bologna Bologna 40121",
    "addr:housenumber":"9 / g",
    "addr:postcode":"40121;40121",
    "addr:street":"Via Amendola",
    "iso:country":"IT",
    "sg:address":"Via Amendola 9/g; Bologna; 40121",
    "sg:city":"Bologna",
    "sg:classifiers":[
        {
            "category":"Banks & Credit Unions",
            "subcategory":"Bank",
            "type":"Services"
        }
    ],
    "sg:phone":"+39 051 254630",
    "sg:postcode":"40121",
    "sg:province":"Bologna",
    "wof:name":"Cassa Di Risparmio Di Rimini Spa",
    "wof:placetype":"venue"
},
  "geometry": {"coordinates":[11.340798,44.503986],"type":"Point"}
}