{
  "type": "Feature",
  "properties": {
    "addr:full":"Pizza S. Allende 1 47824 Poggio Berni Poggio Berni Rimini 47824",
    "addr:housenumber":"1",
    "addr:postcode":"47824;47824",
    "addr:street":"Allende;Berni Poggio Berni",
    "iso:country":"IT",
    "sg:address":"Pizza S. Allende 1 47824 Poggio Berni",
    "sg:city":"Poggio Berni",
    "sg:classifiers":[
        {
            "category":"Professional",
            "subcategory":"Advertising",
            "type":"Services"
        }
    ],
    "sg:phone":"+39 0541 629284",
    "sg:postcode":"47824",
    "sg:province":"Rimini",
    "sg:tags":[
        "table",
        "napkin"
    ],
    "sg:website":"www.personalzucchero.com",
    "wof:name":"Personal Zucchero",
    "wof:placetype":"venue"
},
  "geometry": {"coordinates":[12.405428,44.013222],"type":"Point"}
}