{
  "type": "Feature",
  "properties": {
    "iso:country":"IT",
    "sg:address":"13855 Valdengo",
    "sg:city":"Valdengo",
    "sg:orig_category":"Materiali Edili",
    "sg:phone":"+39 015 882005",
    "sg:postcode":"13855",
    "sg:province":"Biella",
    "wof:name":"Papangelo Salvatore",
    "wof:placetype":"venue"
},
  "geometry": {"coordinates":[8.129636,45.570602],"type":"Point"}
}