{
  "type": "Feature",
  "properties": {
    "addr:full":"00197 Roma Roma Roma 00197",
    "addr:postcode":"00197;00197",
    "iso:country":"IT",
    "sg:address":"00197 Roma",
    "sg:city":"Roma",
    "sg:orig_category":"Materiali E Componenti Elettrotecnici",
    "sg:phone":"+39 06 3265 0332",
    "sg:postcode":"00197",
    "sg:province":"Roma",
    "wof:name":"Afl Telecommunications Europe Limited",
    "wof:placetype":"venue"
},
  "geometry": {"coordinates":[12.474685,41.923962],"type":"Point"}
}