{
  "type": "Feature",
  "properties": {
    "iso:country":"IT",
    "sg:address":"21050 Cairate",
    "sg:city":"Cairate",
    "sg:orig_category":"Oli Alimentari E Frantoi Oleari",
    "sg:phone":"+39 331 360 410",
    "sg:postcode":"21050",
    "sg:province":"Varese",
    "wof:name":"Lepori Snc",
    "wof:placetype":"venue"
},
  "geometry": {"coordinates":[8.87472,45.695934],"type":"Point"}
}