{
  "type": "Feature",
  "properties": {
    "iso:country":"IT",
    "sg:address":"44, Via Olmo 36077 Altavilla Vicentina",
    "sg:city":"Altavilla Vicentina",
    "sg:classifiers":[
        {
            "category":"Manufacturing",
            "subcategory":"Metals",
            "type":"Manufacturing & Wholesale Goods"
        }
    ],
    "sg:phone":"+39 0444 349177",
    "sg:postcode":"36077",
    "sg:province":"Vicenza",
    "sg:tags":[
        "processing"
    ],
    "wof:name":"Tobaldini (s.p.a.)",
    "wof:placetype":"venue"
},
  "geometry": {"coordinates":[11.4870786667,45.5232315063],"type":"Point"}
}