{
  "type": "Feature",
  "properties": {
    "iso:country":"IT",
    "sg:address":"10122 Torino",
    "sg:city":"Torino",
    "sg:orig_category":"Metalli E Leghe",
    "sg:phone":"+39 011 562 2095",
    "sg:postcode":"10122",
    "sg:province":"Torino",
    "wof:name":"Delari (s.r.l.)",
    "wof:placetype":"venue"
},
  "geometry": {"coordinates":[7.6693282127,45.0734291077],"type":"Point"}
}