{
  "type": "Feature",
  "properties": {
    "iso:country":"IT",
    "sg:address":"73100 Lecce",
    "sg:city":"Lecce",
    "sg:orig_category":"Marmo, Pietre Ed Affini",
    "sg:phone":"+39 0832 361564",
    "sg:postcode":"73100",
    "sg:province":"Lecce",
    "wof:name":"O. De Filippi & C. Snc",
    "wof:placetype":"venue"
},
  "geometry": {"coordinates":[18.139355,40.366394],"type":"Point"}
}