{
  "type": "Feature",
  "properties": {
    "iso:country":"IT",
    "sg:address":"50, Via Barberini 00187 Roma",
    "sg:city":"Roma",
    "sg:classifiers":[
        {
            "category":"Banks & Credit Unions",
            "subcategory":"Financial Services",
            "type":"Services"
        }
    ],
    "sg:phone":"+39 39064872192",
    "sg:postcode":"00187",
    "sg:province":"Roma",
    "sg:tags":[
        "banking",
        "finance",
        "insurance"
    ],
    "wof:name":"Cossa & Partners Insurance Brokers Srl",
    "wof:placetype":"venue"
},
  "geometry": {"coordinates":[12.491888,41.904652],"type":"Point"}
}