{
  "type": "Feature",
  "properties": {
    "iso:country":"IT",
    "sg:address":"56021 Cascina",
    "sg:city":"Cascina",
    "sg:orig_category":"Attrezzature E Forniture Per Officine Riparazione E Servizi Ausiliari",
    "sg:phone":"+39 050 704007",
    "sg:postcode":"56021",
    "sg:province":"Pisa",
    "wof:name":"Colortecnica Srl",
    "wof:placetype":"venue"
},
  "geometry": {"coordinates":[10.541594,43.669193],"type":"Point"}
}