{
  "type": "Feature",
  "properties": {
    "addr:full":"Ctr. ' Le Vecchie Ii ' 80040 Striano Striano Napoli 80040",
    "addr:postcode":"80040;80040",
    "addr:street":"Ctr.",
    "iso:country":"IT",
    "sg:address":"Ctr. ' Le Vecchie Ii ' 80040 Striano",
    "sg:city":"Striano",
    "sg:classifiers":[
        {
            "category":"Food & Beverages",
            "subcategory":"Groceries & Convenience Stores",
            "type":"Retail Goods"
        }
    ],
    "sg:phone":"+39 081 827 6963",
    "sg:postcode":"80040",
    "sg:province":"Napoli",
    "sg:tags":[
        "product",
        "related"
    ],
    "sg:website":"http://www.ambrosio.it:ws_end: :mark:ws:http://www.paginegialle.it/ambrosio-09",
    "wof:name":"I.d.a.v. Srl - Ambrosio",
    "wof:placetype":"venue"
},
  "geometry": {"coordinates":[14.2516355515,40.84009552],"type":"Point"}
}