{
  "type": "Feature",
  "properties": {
    "iso:country":"IT",
    "sg:address":"00121 Lido Di Ostia",
    "sg:orig_category":"Carni, Salumi E Pesci",
    "sg:phone":"+39 06 569 6348",
    "sg:postcode":"00121",
    "sg:province":"Roma",
    "wof:name":"Roberti Riccardo",
    "wof:placetype":"venue"
},
  "geometry": {"coordinates":[12.276567,41.733204],"type":"Point"}
}