{
  "type": "Feature",
  "properties": {
    "iso:country":"IT",
    "sg:address":"Localita' Porcarola 24020 Songavazzo",
    "sg:city":"Songavazzo",
    "sg:classifiers":[
        {
            "category":"Manufacturing",
            "subcategory":"Tools & Machinery",
            "type":"Manufacturing & Wholesale Goods"
        }
    ],
    "sg:phone":"+39 39034674866",
    "sg:postcode":"24020",
    "sg:province":"Bergamo",
    "sg:tags":[
        "environment",
        "equipment",
        "-"
    ],
    "wof:name":"Aerotermica Bergamasca Srl",
    "wof:placetype":"venue"
},
  "geometry": {"coordinates":[9.669952,45.694904],"type":"Point"}
}