{
  "type": "Feature",
  "properties": {
    "addr:full":"Via Bragarina 87 19126 La Spezia SP",
    "addr:housenumber":"87",
    "addr:postcode":"19126",
    "addr:street":"Via Bragarina",
    "iso:country":"IT",
    "sg:address":"Via Bragarina 87 19126 La Spezia",
    "sg:classifiers":[
        {
            "category":"Wholesale",
            "subcategory":"Vending Machines",
            "type":"Manufacturing & Wholesale Goods"
        }
    ],
    "sg:phone":"+39 0187 517632",
    "sg:province":"SP",
    "sg:tags":[
        "ceramic",
        "processing"
    ],
    "wof:name":"Fermac Srl",
    "wof:placetype":"venue"
},
  "geometry": {"coordinates":[9.85148,44.11739],"type":"Point"}
}