{
  "type": "Feature",
  "properties": {
    "iso:country":"IT",
    "sg:address":"20010 Cornaredo",
    "sg:city":"Cornaredo",
    "sg:orig_category":"Petroli, Gas E Combustibili",
    "sg:phone":"+39 02 9356 1299",
    "sg:postcode":"20010",
    "sg:province":"Milano",
    "wof:name":"Ci - Effe Chimica (s.r.l.)",
    "wof:placetype":"venue"
},
  "geometry": {"coordinates":[9.0300960541,45.5009727478],"type":"Point"}
}