{
  "type": "Feature",
  "properties": {
    "addr:full":"00159 Roma Roma Roma 00159",
    "addr:postcode":"00159;00159",
    "iso:country":"IT",
    "sg:address":"00159 Roma",
    "sg:city":"Roma",
    "sg:orig_category":"Servizi E Lavori Per Industria Alimentare E Bevande. Servizi E Lavori Per Abbigliamento E Pelletterie. Servizi E Lavori Per Arredamento E Industria Del Legno",
    "sg:phone":"+39 06 4359 7943",
    "sg:postcode":"00159",
    "sg:province":"Roma",
    "wof:name":"Co.mi.d. Srl",
    "wof:placetype":"venue"
},
  "geometry": {"coordinates":[12.549882,41.903042],"type":"Point"}
}