{
  "type": "Feature",
  "properties": {
    "iso:country":"IT",
    "sg:address":"28075 Grignasco",
    "sg:city":"Grignasco",
    "sg:orig_category":"Animali Domestici - Allevamento E Addestramento",
    "sg:phone":"+39 0163 417294",
    "sg:postcode":"28075",
    "sg:province":"Novara",
    "wof:name":"Allevamento Freccia Nera",
    "wof:placetype":"venue"
},
  "geometry": {"coordinates":[8.343779,45.689655],"type":"Point"}
}