{
  "type": "Feature",
  "properties": {
    "iso:country":"IT",
    "sg:address":"62, Corso Trieste 10024 Moncalieri",
    "sg:city":"Moncalieri",
    "sg:classifiers":[
        {
            "category":"Autos & Motor Vehicles",
            "subcategory":"Automobile Sales",
            "type":"Retail Goods"
        }
    ],
    "sg:phone":"+39 39800449922",
    "sg:postcode":"10024",
    "sg:province":"Torino",
    "sg:tags":[
        "motor-cars"
    ],
    "wof:name":"Abrate Tour Srl",
    "wof:placetype":"venue"
},
  "geometry": {"coordinates":[7.672267437,45.007900238],"type":"Point"}
}