{
  "type": "Feature",
  "properties": {
    "iso:country":"IT",
    "sg:address":"29015 Fontana Pradosa",
    "sg:city":"Fontana Pradosa",
    "sg:orig_category":"Servizi E Lavori Per Ecologia E Smaltimento Rifiuti. Termotecnica E Riscaldamento, Apparecchiature E Servizi. Servizi Ausiliari Di Sorveglianza, Manutenzione E Pulizia",
    "sg:phone":"+39 0523 882077",
    "sg:postcode":"29015",
    "sg:province":"Piacenza",
    "wof:name":"Ciceri Daniele",
    "wof:placetype":"venue"
},
  "geometry": {"coordinates":[9.462533,45.062023],"type":"Point"}
}