{
  "type": "Feature",
  "properties": {
    "addr:full":"10124 Torino Torino Torino 10124",
    "addr:postcode":"10124;10124",
    "iso:country":"IT",
    "sg:address":"10124 Torino",
    "sg:city":"Torino",
    "sg:orig_category":"Tempo Libero - Articoli E Forniture. Regalistica Aziendale",
    "sg:phone":"+39 011 812 2137",
    "sg:postcode":"10124",
    "sg:province":"Torino",
    "wof:name":"D.a.s. Snc Di Tredici G. & C.",
    "wof:placetype":"venue"
},
  "geometry": {"coordinates":[7.69216,45.068085],"type":"Point"}
}