{
  "type": "Feature",
  "properties": {
    "iso:country":"IT",
    "sg:address":"41056 Savignano Sul Panaro",
    "sg:city":"Savignano sul Panaro",
    "sg:orig_category":"Cartotecnica E Servizi",
    "sg:phone":"+39 059 796150",
    "sg:postcode":"41056",
    "sg:province":"Modena",
    "sg:website":"http://www.tipolitografiafg.com",
    "wof:name":"Tipolitografia F.g. Di Grandi Lucio & C. Snc",
    "wof:placetype":"venue"
},
  "geometry": {"coordinates":[11.033334,44.470211],"type":"Point"}
}