{
  "type": "Feature",
  "properties": {
    "addr:full":"20123 Milano Milano Milano 20123",
    "addr:postcode":"20123;20123",
    "iso:country":"IT",
    "sg:address":"20123 Milano",
    "sg:city":"Milano",
    "sg:orig_category":"Servizi Culturali E Per Lo Spettacolo. Servizi Al Turismo. Acqua, Luce, Gas E Societa' Di Esercizio Pubblico",
    "sg:phone":"+39 02 805 5882",
    "sg:postcode":"20123",
    "sg:province":"Milano",
    "wof:name":"Coop. Teatro Degli Eguali",
    "wof:placetype":"venue"
},
  "geometry": {"coordinates":[9.177901,45.465885],"type":"Point"}
}