{
  "type": "Feature",
  "properties": {
    "iso:country":"IT",
    "sg:address":"16036 Recco",
    "sg:city":"Recco",
    "sg:orig_category":"Servizi Al Turismo. Trasporto Pubblico E Privato",
    "sg:phone":"+39 0185 730027",
    "sg:postcode":"16036",
    "sg:province":"Genova",
    "wof:name":"Vip Air International Aerotaxi Group Srl",
    "wof:placetype":"venue"
},
  "geometry": {"coordinates":[9.15115,44.366539],"type":"Point"}
}