{
  "type": "Feature",
  "properties": {
    "addr:full":"34147 Trieste Trieste Trieste 34147",
    "addr:postcode":"34147;34147",
    "iso:country":"IT",
    "sg:address":"34147 Trieste",
    "sg:city":"Trieste",
    "sg:orig_category":"Macchine Ed Impianti Per Edilizia E Lavori Pubblici. Forniture Per Edilizia E Lavori Pubblici",
    "sg:phone":"+39 040 827046",
    "sg:postcode":"34147",
    "sg:province":"Trieste",
    "wof:name":"Edilpont Strutture Srl",
    "wof:placetype":"venue"
},
  "geometry": {"coordinates":[13.800245,45.6119],"type":"Point"}
}