{
  "type": "Feature",
  "properties": {
    "iso:country":"IT",
    "sg:address":"50055 Lastra A Signa",
    "sg:city":"Lastra a Signa",
    "sg:classifiers":[
        {
            "category":"Manufacturing",
            "subcategory":"Tools & Machinery",
            "type":"Manufacturing & Wholesale Goods"
        }
    ],
    "sg:phone":"+39 055 872 2176",
    "sg:postcode":"50055",
    "sg:province":"Firenze",
    "sg:tags":[
        "leather",
        "equipment",
        "goods",
        "clothing"
    ],
    "sg:website":"http://www.delvecchia.com",
    "wof:name":"Del Vecchia Spa",
    "wof:placetype":"venue"
},
  "geometry": {"coordinates":[11.123948,43.77174],"type":"Point"}
}