{
  "type": "Feature",
  "properties": {
    "addr:full":"07021 Arzachena Arzachena Olbia-Tempio 07021",
    "addr:postcode":"07021;07021",
    "iso:country":"IT",
    "sg:address":"07021 Arzachena",
    "sg:city":"Arzachena",
    "sg:orig_category":"Prodotti Alimentari",
    "sg:phone":"+39 0789 81356",
    "sg:postcode":"07021",
    "sg:province":"Olbia-Tempio",
    "wof:name":"La Compagnia Dei Mari Del Nord Srl",
    "wof:placetype":"venue"
},
  "geometry": {"coordinates":[9.2785587311,40.826839447],"type":"Point"}
}