{
  "type": "Feature",
  "properties": {
    "addr:full":"45, Via Partisani 47016 Predappio Predappio Forl\u00ec-Cesena 47016",
    "addr:postcode":"47016;47016",
    "addr:street":"Via Partisani",
    "iso:country":"IT",
    "sg:address":"45, Via Partisani 47016 Predappio",
    "sg:city":"Predappio",
    "sg:classifiers":[
        {
            "category":"Manufacturing",
            "subcategory":"Paper Products",
            "type":"Manufacturing & Wholesale Goods"
        }
    ],
    "sg:phone":"+39 0543 940186",
    "sg:postcode":"47016",
    "sg:province":"Forl\u00ec-Cesena",
    "sg:tags":[
        "cardboard"
    ],
    "wof:name":"Scatolificio Ondulato Forlivese",
    "wof:placetype":"venue"
},
  "geometry": {"coordinates":[11.9804611206,43.9947662354],"type":"Point"}
}