{
  "type": "Feature",
  "properties": {
    "iso:country":"IT",
    "sg:address":"47826 Verucchio",
    "sg:city":"Verucchio",
    "sg:orig_category":"Macchine, Impianti Ed Attrezzature Per Industria Alimentare E Bevande",
    "sg:phone":"+39 0541 670576",
    "sg:postcode":"47826",
    "sg:province":"Rimini",
    "wof:name":"Fimar Spa",
    "wof:placetype":"venue"
},
  "geometry": {"coordinates":[12.424109,43.999405],"type":"Point"}
}