{
  "type": "Feature",
  "properties": {
    "addr:full":"34147 Trieste Trieste Trieste 34147",
    "addr:postcode":"34147;34147",
    "iso:country":"IT",
    "sg:address":"34147 Trieste",
    "sg:city":"Trieste",
    "sg:orig_category":"Professionisti - Studi E Servizi Ed Associazioni Di Interesse Aziendale. Associazioni Ed Organismi Di Interesse Pubblico",
    "sg:phone":"+39 040 89881",
    "sg:postcode":"34147",
    "sg:province":"Trieste",
    "sg:website":"http://www.ezit.ts.it/",
    "wof:name":"Ente Per La Zona Industriale Di Trieste",
    "wof:placetype":"venue"
},
  "geometry": {"coordinates":[13.8098716736,45.6166877747],"type":"Point"}
}