{
  "type": "Feature",
  "properties": {
    "iso:country":"IT",
    "sg:address":"20092 Cinisello Balsamo",
    "sg:city":"Cinisello Balsamo",
    "sg:orig_category":"Servizi Culturali E Per Lo Spettacolo. Servizi Al Turismo. Acqua, Luce, Gas E Societa' Di Esercizio Pubblico",
    "sg:phone":"+39 02 6604 9053",
    "sg:postcode":"20092",
    "sg:province":"Milano",
    "wof:name":"Farmacie Comunali",
    "wof:placetype":"venue"
},
  "geometry": {"coordinates":[9.199354,45.550709],"type":"Point"}
}