{
  "type": "Feature",
  "properties": {
    "addr:full":"Via Trieste 33024 Forni Di Sopra Forni di Sopra Udine 33024",
    "addr:postcode":"33024;33024",
    "addr:street":"Via Trieste",
    "iso:country":"IT",
    "sg:address":"Via Trieste 33024 Forni Di Sopra",
    "sg:city":"Forni di Sopra",
    "sg:classifiers":[
        {
            "category":"Home & Garden",
            "subcategory":"Home Furnishings",
            "type":"Retail Goods"
        }
    ],
    "sg:phone":"+39 39043388307",
    "sg:postcode":"33024",
    "sg:province":"Udine",
    "sg:tags":[
        "household"
    ],
    "wof:name":"Legnolandia S.r.l.",
    "wof:placetype":"venue"
},
  "geometry": {"coordinates":[13.230724,46.064941],"type":"Point"}
}