{
  "type": "Feature",
  "properties": {
    "iso:country":"IT",
    "sg:address":"20138 Milano",
    "sg:city":"Milano",
    "sg:orig_category":"Arredamenti E Mobili Professionali. Forniture Per Il Settore Dello Spettacolo",
    "sg:phone":"+39 02 506 2574",
    "sg:postcode":"20138",
    "sg:province":"Milano",
    "wof:name":"Marsilio Amigoni Bruno",
    "wof:placetype":"venue"
},
  "geometry": {"coordinates":[9.251227,45.453423],"type":"Point"}
}