{
  "type": "Feature",
  "properties": {
    "iso:country":"IT",
    "sg:address":"45 Via Toscana, 86100 Campobasso",
    "sg:city":"Campobasso",
    "sg:classifiers":[
        {
            "category":"Banks & Credit Unions",
            "subcategory":"Financial Services",
            "type":"Services"
        }
    ],
    "sg:phone":"+39 0874 481400",
    "sg:postcode":"86100",
    "sg:province":"Campobasso",
    "sg:tags":[
        "banking",
        "finance",
        "insurance"
    ],
    "wof:name":"Credito Molisano (spa)",
    "wof:placetype":"venue"
},
  "geometry": {"coordinates":[14.6762418747,41.5511131287],"type":"Point"}
}