{
  "type": "Feature",
  "properties": {
    "iso:country":"IT",
    "sg:address":"20149 Milano",
    "sg:city":"Milano",
    "sg:orig_category":"Abiti Da Lavoro Ed Indumenti Protettivi",
    "sg:phone":"+39 02 4870 9019",
    "sg:postcode":"20149",
    "sg:province":"Milano",
    "sg:website":"http://www.gruppomanifatture.it",
    "wof:name":"Gruppo Manifatture Srl",
    "wof:placetype":"venue"
},
  "geometry": {"coordinates":[9.145389,45.46854],"type":"Point"}
}