{
  "type": "Feature",
  "properties": {
    "addr:full":"21100 Varese Varese Varese 21100",
    "addr:postcode":"21100;21100",
    "iso:country":"IT",
    "sg:address":"21100 Varese",
    "sg:city":"Varese",
    "sg:orig_category":"Elettronica Industriale, Prodotti E Apparecchiature",
    "sg:phone":"+39 0332 320217",
    "sg:postcode":"21100",
    "sg:province":"Varese",
    "sg:website":"http://www.retel.it",
    "wof:name":"Retel Srl",
    "wof:placetype":"venue"
},
  "geometry": {"coordinates":[8.784389,45.812656],"type":"Point"}
}