{
  "type": "Feature",
  "properties": {
    "addr:full":"20038 Seregno Seregno Milano 20038",
    "addr:postcode":"20038;20038",
    "iso:country":"IT",
    "sg:address":"20038 Seregno",
    "sg:city":"Seregno",
    "sg:orig_category":"Impianti, Attrezzature E Forniture Sanitarie Ed Ospedaliere",
    "sg:phone":"+39 036 232 5709",
    "sg:postcode":"20038",
    "sg:province":"Milano",
    "wof:name":"Rimsa P. Longoni Srl",
    "wof:placetype":"venue"
},
  "geometry": {"coordinates":[9.203573,45.651917],"type":"Point"}
}