{
  "type": "Feature",
  "properties": {
    "addr:full":"80059 Torre Del Greco Torre del Greco Napoli 80059",
    "addr:postcode":"80059;80059",
    "iso:country":"IT",
    "sg:address":"80059 Torre Del Greco",
    "sg:city":"Torre del Greco",
    "sg:orig_category":"Prodotti Alimentari. Servizi E Lavori Per Industria Alimentare E Bevande",
    "sg:phone":"+39 081 847 1164",
    "sg:postcode":"80059",
    "sg:province":"Napoli",
    "wof:name":"Pac Gel Snc",
    "wof:placetype":"venue"
},
  "geometry": {"coordinates":[14.3999252319,40.7787055969],"type":"Point"}
}