{
  "type": "Feature",
  "properties": {
    "iso:country":"IT",
    "sg:address":"Corso Colombo Cristoforo 3 20144 Milano",
    "sg:city":"Milano",
    "sg:orig_category":"Leather Items, Artisans'",
    "sg:phone":"+39 02 8940 4862",
    "sg:postcode":"20144",
    "sg:province":"Milano",
    "wof:name":"Emil Srl",
    "wof:placetype":"venue"
},
  "geometry": {"coordinates":[9.172084,45.454849],"type":"Point"}
}