{
  "type": "Feature",
  "properties": {
    "iso:country":"IT",
    "sg:address":"41043 Formigine",
    "sg:city":"Formigine",
    "sg:orig_category":"Macchine Utensili E Impianti",
    "sg:phone":"+39 059 552342",
    "sg:postcode":"41043",
    "sg:province":"Modena",
    "wof:name":"Sin-mecc Srl",
    "wof:placetype":"venue"
},
  "geometry": {"coordinates":[10.854474,44.559586],"type":"Point"}
}