{
  "type": "Feature",
  "properties": {
    "addr:full":"00043 Ciampino Ciampino Roma 00043",
    "addr:postcode":"00043;roma 00043",
    "iso:country":"IT",
    "sg:address":"00043 Ciampino",
    "sg:city":"Ciampino",
    "sg:orig_category":"Servizi Al Turismo. Trasporto Pubblico E Privato",
    "sg:phone":"+39 06 7934 0533",
    "sg:postcode":"00043",
    "sg:province":"Roma",
    "wof:name":"Panair",
    "wof:placetype":"venue"
},
  "geometry": {"coordinates":[12.590832,41.800388],"type":"Point"}
}