{
  "type": "Feature",
  "properties": {
    "iso:country":"IT",
    "sg:address":"Via P. Nicola, 43/h; Catania; 95100",
    "sg:classifiers":[
        {
            "category":"Banks & Credit Unions",
            "subcategory":"Bank",
            "type":"Services"
        }
    ],
    "sg:phone":"+39 095 375733",
    "wof:name":"Banca Popolare Di Catania",
    "wof:placetype":"venue"
},
  "geometry": {"coordinates":[15.100004,37.52771],"type":"Point"}
}