{
  "type": "Feature",
  "properties": {
    "addr:full":"20021 Bollate Bollate Milano 20021",
    "addr:postcode":"20021;20021",
    "iso:country":"IT",
    "sg:address":"20021 Bollate",
    "sg:city":"Bollate",
    "sg:orig_category":"Forniture Per Attivita' Commerciali Ed Artigianali",
    "sg:phone":"+39 02 350 1240",
    "sg:postcode":"20021",
    "sg:province":"Milano",
    "wof:name":"Vezzola Giampietro",
    "wof:placetype":"venue"
},
  "geometry": {"coordinates":[9.0954780579,45.5422744751],"type":"Point"}
}