{
  "type": "Feature",
  "properties": {
    "iso:country":"IT",
    "sg:address":"15/17, Via Scotellaro Rocco 50064 Incisa Valdarno",
    "sg:classifiers":[
        {
            "category":"Utilities",
            "subcategory":"Electric",
            "type":"Services"
        }
    ],
    "sg:phone":"+39 055 833 5135",
    "sg:postcode":"50064",
    "sg:province":"Firenze",
    "sg:tags":[
        "component",
        "electronic"
    ],
    "wof:name":"L.t. Imet (s.r.l.)",
    "wof:placetype":"venue"
},
  "geometry": {"coordinates":[11.256902,43.768734],"type":"Point"}
}