{
  "type": "Feature",
  "properties": {
    "addr:full":"Via Zenia Ctr. Mezzocampo 95045 Misterbianco Misterbianco Catania 95045",
    "addr:postcode":"95045;95045",
    "addr:street":"Via Zenia Ctr. Mezzocampo",
    "iso:country":"IT",
    "sg:address":"Via Zenia Ctr. Mezzocampo 95045 Misterbianco",
    "sg:city":"Misterbianco",
    "sg:classifiers":[
        {
            "category":"Shopping",
            "subcategory":"Clothing, Apparel, & Fashions",
            "type":"Retail Goods"
        }
    ],
    "sg:phone":"+39 39095475576",
    "sg:postcode":"95045",
    "sg:province":"Catania",
    "sg:tags":[
        "clothes"
    ],
    "wof:name":"Noi Tre S.r.l.",
    "wof:placetype":"venue"
},
  "geometry": {"coordinates":[15.020676,37.529091],"type":"Point"}
}