{
  "type": "Feature",
  "properties": {
    "iso:country":"IT",
    "sg:address":"21042 Caronno Pertusella",
    "sg:city":"Caronno Pertusella",
    "sg:orig_category":"Macchine Utensili E Impianti",
    "sg:phone":"+39 02 9645 1235",
    "sg:postcode":"21042",
    "sg:province":"Varese",
    "wof:name":"Franchi Flavio (s.r.l.)",
    "wof:placetype":"venue"
},
  "geometry": {"coordinates":[9.045978,45.597878],"type":"Point"}
}