{
  "type": "Feature",
  "properties": {
    "iso:country":"IT",
    "sg:address":"29100 Piacenza",
    "sg:city":"Piacenza",
    "sg:orig_category":"Cine-foto-ottica",
    "sg:phone":"+39 0523 456 0891",
    "sg:postcode":"29100",
    "sg:province":"Piacenza",
    "wof:name":"Photo Art Di Lesmo Fiorenzo & C. Snc",
    "wof:placetype":"venue"
},
  "geometry": {"coordinates":[9.683025,45.036476],"type":"Point"}
}