{
  "type": "Feature",
  "properties": {
    "iso:country":"IT",
    "sg:address":"40129 Bologna",
    "sg:city":"Bologna",
    "sg:orig_category":"Chiese Ed Associazioni Religiose",
    "sg:phone":"+39 051 373973",
    "sg:postcode":"40129",
    "sg:province":"Bologna",
    "wof:name":"Radioevangelo",
    "wof:placetype":"venue"
},
  "geometry": {"coordinates":[11.346021,44.512077],"type":"Point"}
}