{
  "type": "Feature",
  "properties": {
    "addr:full":"40123 Bologna Bologna Bologna 40123",
    "addr:postcode":"40123;40123",
    "iso:country":"IT",
    "sg:address":"40123 Bologna",
    "sg:city":"Bologna",
    "sg:classifiers":[
        {
            "category":"Health Services",
            "subcategory":"Health Practitioner",
            "type":"Services"
        }
    ],
    "sg:phone":"+39 051 585413",
    "sg:postcode":"40123",
    "sg:province":"Bologna",
    "sg:tags":[
        "medici"
    ],
    "sg:website":"http://www.studiovignoli.it",
    "wof:name":"Vignoli Maurizio",
    "wof:placetype":"venue"
},
  "geometry": {"coordinates":[11.3345327377,44.4900779724],"type":"Point"}
}