{
  "type": "Feature",
  "properties": {
    "iso:country":"IT",
    "sg:address":"Via Bainsizza, 37/38 20039 Varedo",
    "sg:city":"Varedo",
    "sg:orig_category":"Semi-finished Copper Products",
    "sg:phone":"+39 036 254 4133",
    "sg:postcode":"20039",
    "sg:province":"Milano",
    "sg:website":"www.metalminotti.it",
    "wof:name":"Societa' Metallurgica Minotti Sas",
    "wof:placetype":"venue"
},
  "geometry": {"coordinates":[9.150496,45.598743],"type":"Point"}
}