{
  "type": "Feature",
  "properties": {
    "iso:country":"IT",
    "sg:address":"22073 Fino Mornasco",
    "sg:city":"Fino Mornasco",
    "sg:orig_category":"Depurazione E Trattamento Delle Acque - Impianti Ed Apparecchi",
    "sg:phone":"+39 031 920518",
    "sg:postcode":"22073",
    "sg:province":"Como",
    "wof:name":"Lariana Depur Spa",
    "wof:placetype":"venue"
},
  "geometry": {"coordinates":[9.070178,45.747734],"type":"Point"}
}