{
  "type": "Feature",
  "properties": {
    "iso:country":"IT",
    "sg:address":"00185 Roma",
    "sg:city":"Roma",
    "sg:orig_category":"Petroli, Gas E Combustibili",
    "sg:phone":"+39 06 474 3799",
    "sg:postcode":"00185",
    "sg:province":"Roma",
    "wof:name":"Assocarboni",
    "wof:placetype":"venue"
},
  "geometry": {"coordinates":[12.4960222244,41.9041595459],"type":"Point"}
}