{
  "type": "Feature",
  "properties": {
    "iso:country":"IT",
    "sg:address":"00040 Pomezia",
    "sg:city":"Pomezia",
    "sg:orig_category":"Motori Ed Organi Di Trasmissione",
    "sg:phone":"+39 06 910 7371",
    "sg:postcode":"00040",
    "sg:province":"Roma",
    "wof:name":"Rcm 2000 Srl",
    "wof:placetype":"venue"
},
  "geometry": {"coordinates":[12.4721841812,41.6843948364],"type":"Point"}
}