{
  "type": "Feature",
  "properties": {
    "addr:full":"90147 Palermo Palermo Palermo 90147",
    "addr:postcode":"90147;90147",
    "iso:country":"IT",
    "sg:address":"90147 Palermo",
    "sg:city":"Palermo",
    "sg:orig_category":"Condizionamento Aria Impianti - Installazione E Manutenzione",
    "sg:phone":"+39 091 637 4996",
    "sg:postcode":"90147",
    "sg:province":"Palermo",
    "wof:name":"Alessi Camillo",
    "wof:placetype":"venue"
},
  "geometry": {"coordinates":[13.369758,38.149906],"type":"Point"}
}