{
  "type": "Feature",
  "properties": {
    "addr:full":"20124 Milano Milano Milano 20124",
    "addr:postcode":"20124;20124",
    "iso:country":"IT",
    "sg:address":"20124 Milano",
    "sg:city":"Milano",
    "sg:orig_category":"Valvole E Apparecchiature Di Misura. Forniture Per Attivita' Industriali",
    "sg:phone":"+39 02 2952 1657",
    "sg:postcode":"20124",
    "sg:province":"Milano",
    "wof:name":"Serto Italiana (s.r.l.)",
    "wof:placetype":"venue"
},
  "geometry": {"coordinates":[9.203648,45.47776],"type":"Point"}
}