{
  "type": "Feature",
  "properties": {
    "iso:country":"IT",
    "sg:address":"15076 Ovada",
    "sg:city":"Ovada",
    "sg:orig_category":"Vetro: Prodotti E Lavorazioni. Forniture Industriali Per Prevenzione, Controllo E Sicurezza",
    "sg:phone":"+39 0143 86030",
    "sg:postcode":"15076",
    "sg:province":"Alessandria",
    "wof:name":"Vemar Snc",
    "wof:placetype":"venue"
},
  "geometry": {"coordinates":[8.649537,44.67252],"type":"Point"}
}