{
  "type": "Feature",
  "properties": {
    "addr:full":"Km. 5.500, Via Per Martina Franca 74100 Taranto Taranto Taranto 74100",
    "addr:postcode":"74100;74100",
    "addr:street":"Km. 5.500 Via Per Martina Franca",
    "iso:country":"IT",
    "sg:address":"Km. 5.500, Via Per Martina Franca 74100 Taranto",
    "sg:city":"Taranto",
    "sg:classifiers":[
        {
            "category":"Building & Trades",
            "subcategory":"Construction",
            "type":"Services"
        }
    ],
    "sg:phone":"+39 099 472 3449",
    "sg:postcode":"74100",
    "sg:province":"Taranto",
    "sg:tags":[
        "work",
        "public"
    ],
    "wof:name":"M.a.d. S.r.l.",
    "wof:placetype":"venue"
},
  "geometry": {"coordinates":[17.240009,40.469238],"type":"Point"}
}