{
  "type": "Feature",
  "properties": {
    "iso:country":"IT",
    "sg:address":"20134 Milano",
    "sg:city":"Milano",
    "sg:orig_category":"Impianti, Attrezzature E Forniture Sanitarie Ed Ospedaliere. Macchine, Strumenti Ed Apparecchi Per Attivita' Industriali",
    "sg:phone":"+39 02 212 7131",
    "sg:postcode":"20134",
    "sg:province":"Milano",
    "wof:name":"Bio Optica Milano S.p.a.",
    "wof:placetype":"venue"
},
  "geometry": {"coordinates":[9.24159,45.47551],"type":"Point"}
}