{
  "type": "Feature",
  "properties": {
    "iso:country":"IT",
    "sg:address":"1, Via Zona Industriale 65020 Alanno",
    "sg:city":"Alanno",
    "sg:classifiers":[
        {
            "category":"Wholesale",
            "subcategory":"Machinery & Supplies",
            "type":"Manufacturing & Wholesale Goods"
        }
    ],
    "sg:phone":"+39 390 858 5751",
    "sg:postcode":"65020",
    "sg:province":"Pescara",
    "sg:tags":[
        "equipment",
        "-",
        "instrument",
        "measurement"
    ],
    "wof:name":"Teknoscuola S.r.l.",
    "wof:placetype":"venue"
},
  "geometry": {"coordinates":[14.214094,42.464825],"type":"Point"}
}