{
  "type": "Feature",
  "properties": {
    "iso:country":"IT",
    "sg:address":"13, Via Enrico Mattei 26020 Madignano",
    "sg:city":"Madignano",
    "sg:classifiers":[
        {
            "category":"Professional",
            "subcategory":"Engineering",
            "type":"Services"
        }
    ],
    "sg:phone":"+39 0373 658034",
    "sg:postcode":"26020",
    "sg:province":"Cremona",
    "sg:tags":[
        "machine",
        "-",
        "mechanical"
    ],
    "wof:name":"Adiemme (s.r.l.)",
    "wof:placetype":"venue"
},
  "geometry": {"coordinates":[9.738359,45.333458],"type":"Point"}
}