{
  "type": "Feature",
  "properties": {
    "iso:country":"IT",
    "sg:address":"29, Via Rupe 38017 Mezzolombardo",
    "sg:city":"Mezzolombardo",
    "sg:classifiers":[
        {
            "category":"Manufacturing",
            "subcategory":"Printing",
            "type":"Manufacturing & Wholesale Goods"
        }
    ],
    "sg:phone":"+39 0461 605600",
    "sg:postcode":"38017",
    "sg:province":"Trento",
    "sg:tags":[
        "publishing"
    ],
    "wof:name":"Cartotrentina S.n.c.di Dolzan Franco & C.",
    "wof:placetype":"venue"
},
  "geometry": {"coordinates":[11.0977964401,46.1920433044],"type":"Point"}
}