{
  "type": "Feature",
  "properties": {
    "iso:country":"IT",
    "sg:address":"35040 Urbana",
    "sg:city":"Urbana",
    "sg:classifiers":[
        {
            "category":"Manufacturing",
            "subcategory":"Leather Goods",
            "type":"Manufacturing & Wholesale Goods"
        }
    ],
    "sg:phone":"+39 0429 878173",
    "sg:postcode":"35040",
    "sg:province":"Padova",
    "sg:tags":[
        "goods",
        "clothing",
        "supply"
    ],
    "wof:name":"Biribo' Di Calonego Barbara",
    "wof:placetype":"venue"
},
  "geometry": {"coordinates":[11.429468,45.193802],"type":"Point"}
}