{
  "type": "Feature",
  "properties": {
    "addr:full":"45, Via Querce 30175 Venezia Venezia Venezia 30175",
    "addr:postcode":"30175;30175",
    "addr:street":"Via Querce",
    "iso:country":"IT",
    "sg:address":"45, Via Querce 30175 Venezia",
    "sg:city":"Venezia",
    "sg:classifiers":[
        {
            "category":"Shopping",
            "type":"Retail Goods"
        }
    ],
    "sg:phone":"+39 39041924195",
    "sg:postcode":"30175",
    "sg:province":"Venezia",
    "sg:tags":[
        "finished",
        "-",
        "metallic"
    ],
    "wof:name":"Cooperativa Di Lavoro Nuova Tubital (soc. Coop. R.l.)",
    "wof:placetype":"venue"
},
  "geometry": {"coordinates":[12.3266267776,45.4408950806],"type":"Point"}
}