{
  "type": "Feature",
  "properties": {
    "addr:full":"25011 Calcinato Calcinato Brescia 25011",
    "addr:postcode":"25011;25011",
    "iso:country":"IT",
    "sg:address":"25011 Calcinato",
    "sg:city":"Calcinato",
    "sg:orig_category":"Servizi E Lavori Per Ecologia E Smaltimento Rifiuti",
    "sg:phone":"+39 030 963 6101",
    "sg:postcode":"25011",
    "sg:province":"Brescia",
    "wof:name":"Car-el Snc",
    "wof:placetype":"venue"
},
  "geometry": {"coordinates":[10.393364,45.460384],"type":"Point"}
}