{
  "type": "Feature",
  "properties": {
    "addr:full":"27010 Siziano Siziano Pavia 27010",
    "addr:postcode":"27010;27010",
    "iso:country":"IT",
    "sg:address":"27010 Siziano",
    "sg:city":"Siziano",
    "sg:orig_category":"Arredo Cucina Ed Elettrodomestici. Climatizzazione E Condizionamento, Apparecchiature E Servizi",
    "sg:phone":"+39 0382 610908",
    "sg:postcode":"27010",
    "sg:province":"Pavia",
    "wof:name":"Bio Air Instruments Srl",
    "wof:placetype":"venue"
},
  "geometry": {"coordinates":[9.174642,45.195351],"type":"Point"}
}