{
  "type": "Feature",
  "properties": {
    "iso:country":"IT",
    "sg:address":"41026 Pavullo Nel Frignano",
    "sg:city":"Pavullo nel Frignano",
    "sg:orig_category":"Agenzie D'affari E Servizi Commerciali. Servizi Per Aziende, Manifestazioni E Supporto Agli Scambi Commerciali. Acqua, Luce, Gas E Societa' Di Esercizio Pubblico",
    "sg:phone":"+39 0536 324247",
    "sg:postcode":"41026",
    "sg:province":"Modena",
    "wof:name":"Delegazione Pavullo N/f",
    "wof:placetype":"venue"
},
  "geometry": {"coordinates":[10.834518,44.34129],"type":"Point"}
}