{
  "type": "Feature",
  "properties": {
    "addr:full":"88040 Mango Catanzaro 88040",
    "addr:housenumber":"88040",
    "addr:postcode":"88040",
    "addr:street":"Mango Catanzaro",
    "iso:country":"IT",
    "sg:address":"88040 Mango",
    "sg:classifiers":[
        {
            "category":"Bars & Pubs",
            "subcategory":"Wine Bar",
            "type":"Food & Drink"
        }
    ],
    "sg:phone":"+39 0141 89440",
    "sg:postcode":"88040",
    "sg:province":"Catanzaro",
    "sg:tags":[
        "liqueur",
        "drinks"
    ],
    "wof:name":"Cascina Pian D'or",
    "wof:placetype":"venue"
},
  "geometry": {"coordinates":[16.587679,38.910599],"type":"Point"}
}