{
  "type": "Feature",
  "properties": {
    "addr:full":"6, Viale Dante Alighieri 38057 Pergine Valsugana Pergine Valsugana Trento 38057",
    "addr:postcode":"38057;38057",
    "addr:street":"Viale Dante Alighieri",
    "iso:country":"IT",
    "sg:address":"6, Viale Dante Alighieri 38057 Pergine Valsugana",
    "sg:city":"Pergine Valsugana",
    "sg:classifiers":[
        {
            "category":"Shopping",
            "subcategory":"Crafts & Fabrics",
            "type":"Retail Goods"
        }
    ],
    "sg:phone":"+39 0461 531363",
    "sg:postcode":"38057",
    "sg:province":"Trento",
    "wof:name":"Costa Tendaggi (s.r.l.)",
    "wof:placetype":"venue"
},
  "geometry": {"coordinates":[11.2179002762,45.9944610596],"type":"Point"}
}