{
  "type": "Feature",
  "properties": {
    "iso:country":"IT",
    "sg:address":"Km. 51.100, Via Monti Lepini 04100 Latina",
    "sg:city":"Latina",
    "sg:classifiers":[
        {
            "category":"Professional",
            "subcategory":"Printing & Photocopies",
            "type":"Services"
        }
    ],
    "sg:phone":"+39 0773 610861",
    "sg:postcode":"04100",
    "sg:province":"Latina",
    "wof:name":"Modulgrafica Srl",
    "wof:placetype":"venue"
},
  "geometry": {"coordinates":[12.909444809,41.543056488],"type":"Point"}
}