{
  "type": "Feature",
  "properties": {
    "iso:country":"IT",
    "sg:address":"Localita' Ponte D'assi 06024 Gubbio",
    "sg:city":"Gubbio",
    "sg:classifiers":[
        {
            "category":"Sports & Exercise",
            "subcategory":"Playing Field",
            "type":"Entertainment"
        }
    ],
    "sg:phone":"+39 075 927 2596",
    "sg:postcode":"06024",
    "sg:province":"Perugia",
    "sg:tags":[
        "game"
    ],
    "wof:name":"Acacia Giuseppe S.r.l.",
    "wof:placetype":"venue"
},
  "geometry": {"coordinates":[12.577233,43.310005],"type":"Point"}
}