{
  "type": "Feature",
  "properties": {
    "addr:full":"22/23, Via L. Spallanzani 42024 Castelnovo Di Sotto Reggio Nell'Emilia 42024",
    "addr:housenumber":"22 / 23",
    "addr:postcode":"42024;42024",
    "addr:street":"Via L. Spallanzani",
    "iso:country":"IT",
    "sg:address":"22/23, Via L. Spallanzani 42024 Castelnovo Di Sotto",
    "sg:classifiers":[
        {
            "category":"Shopping",
            "subcategory":"Clothing, Apparel, & Fashions",
            "type":"Retail Goods"
        }
    ],
    "sg:phone":"+39 0522 682134",
    "sg:postcode":"42024",
    "sg:province":"Reggio Nell'Emilia",
    "sg:tags":[
        "clothing",
        "accessory"
    ],
    "wof:name":"Casoli Fratelli (s.n.c.)",
    "wof:placetype":"venue"
},
  "geometry": {"coordinates":[10.566983,44.802135],"type":"Point"}
}