{
  "type": "Feature",
  "properties": {
    "iso:country":"IT",
    "sg:address":"22100 Como",
    "sg:city":"Como",
    "sg:orig_category":"Servizi E Lavori Per Abbigliamento E Pelletterie",
    "sg:phone":"+39 031 264956",
    "sg:postcode":"22100",
    "sg:province":"Como",
    "wof:name":"Anteprima Studio (s.n.c.)",
    "wof:placetype":"venue"
},
  "geometry": {"coordinates":[9.076119,45.810688],"type":"Point"}
}