{
  "type": "Feature",
  "properties": {
    "iso:country":"IT",
    "sg:address":"40040 Gaggio Montano",
    "sg:orig_category":"Forniture Per Uffici. Servizi Vari Di Interesse Pubblico",
    "sg:phone":"+39 0534 30001",
    "sg:province":"BO",
    "wof:name":"Tabaccheria Esse Due",
    "wof:placetype":"venue"
},
  "geometry": {"coordinates":[10.974822998,44.1826667786],"type":"Point"}
}