{
  "type": "Feature",
  "properties": {
    "iso:country":"IT",
    "sg:address":"13100 Vercelli",
    "sg:city":"Vercelli",
    "sg:orig_category":"Frigotecnica, Apparecchiature E Servizi. Forniture Alle Strutture Ricettive",
    "sg:phone":"+39 0161 251961",
    "sg:postcode":"13100",
    "sg:province":"Vercelli",
    "wof:name":"Olivero Giancarlo",
    "wof:placetype":"venue"
},
  "geometry": {"coordinates":[8.4155092239,45.3256835938],"type":"Point"}
}