{
  "type": "Feature",
  "properties": {
    "addr:full":"13878 Candelo Candelo Biella 13878",
    "addr:postcode":"13878;13878",
    "iso:country":"IT",
    "sg:address":"13878 Candelo",
    "sg:city":"Candelo",
    "sg:orig_category":"Filati E Materie Prime Tessili",
    "sg:phone":"+39 015 253 9741",
    "sg:postcode":"13878",
    "sg:province":"Biella",
    "wof:name":"Pozzo Edoardo",
    "wof:placetype":"venue"
},
  "geometry": {"coordinates":[8.1266641617,45.5341720581],"type":"Point"}
}