{
  "type": "Feature",
  "properties": {
    "iso:country":"IT",
    "sg:address":"242, Corso Susa 10098 Rivoli",
    "sg:city":"Rivoli",
    "sg:classifiers":[
        {
            "category":"Professional",
            "subcategory":"Engineering",
            "type":"Services"
        }
    ],
    "sg:phone":"+39 011 956 5611",
    "sg:postcode":"10098",
    "sg:province":"Torino",
    "sg:tags":[
        "machine",
        "-",
        "mechanical"
    ],
    "wof:name":"Husky Italia S.r.l.",
    "wof:placetype":"venue"
},
  "geometry": {"coordinates":[7.519904,45.070522],"type":"Point"}
}