{
  "type": "Feature",
  "properties": {
    "iso:country":"IT",
    "sg:address":"20124 Milano",
    "sg:city":"Milano",
    "sg:orig_category":"Apparecchiature E Sistemi Per Imballaggio E Confezionamento",
    "sg:phone":"+39 02 6749 0127",
    "sg:postcode":"20124",
    "sg:province":"Milano",
    "wof:name":"Ameia Srl",
    "wof:placetype":"venue"
},
  "geometry": {"coordinates":[9.20049,45.480541],"type":"Point"}
}