{
  "type": "Feature",
  "properties": {
    "iso:country":"IT",
    "sg:address":"00199 Roma",
    "sg:city":"Roma",
    "sg:classifiers":[
        {
            "category":"Health Services",
            "subcategory":"Health Practitioner",
            "type":"Services"
        }
    ],
    "sg:phone":"+39 06 860 1775",
    "sg:postcode":"00199",
    "sg:province":"Roma",
    "sg:tags":[
        "medici"
    ],
    "wof:name":"Ciancaglini Giampietro",
    "wof:placetype":"venue"
},
  "geometry": {"coordinates":[12.520494,41.933678],"type":"Point"}
}