{
  "type": "Feature",
  "properties": {
    "iso:country":"IT",
    "sg:address":"31030 Breda Di Piave",
    "sg:city":"Breda di Piave",
    "sg:orig_category":"Edilizia - Attrezzature",
    "sg:phone":"+39 0422 90251",
    "sg:postcode":"31030",
    "sg:province":"Treviso",
    "wof:name":"Turbosol Produzione Spa",
    "wof:placetype":"venue"
},
  "geometry": {"coordinates":[12.315853,45.712719],"type":"Point"}
}