{
  "type": "Feature",
  "properties": {
    "iso:country":"IT",
    "sg:address":"10148 Torino",
    "sg:city":"Torino",
    "sg:orig_category":"Automobili - Commercio",
    "sg:phone":"+39 011 220 2452",
    "sg:postcode":"10148",
    "sg:province":"Torino",
    "wof:name":"Santini Maru'",
    "wof:placetype":"venue"
},
  "geometry": {"coordinates":[7.682946,45.109707],"type":"Point"}
}