{
  "type": "Feature",
  "properties": {
    "addr:full":"15048 Valenza Valenza Alessandria 15048",
    "addr:postcode":"15048;15048",
    "iso:country":"IT",
    "sg:address":"15048 Valenza",
    "sg:city":"Valenza",
    "sg:orig_category":"Gioielleria, Oreficeria E Argenteria. Shopping",
    "sg:phone":"+39 0131 941024",
    "sg:postcode":"15048",
    "sg:province":"Alessandria",
    "sg:website":"http://www.viscontimirco.com",
    "wof:name":"Mirco Visconti Srl",
    "wof:placetype":"venue"
},
  "geometry": {"coordinates":[8.63987,45.009224],"type":"Point"}
}