{
  "type": "Feature",
  "properties": {
    "iso:country":"IT",
    "sg:address":"95014 Giarre",
    "sg:city":"Giarre",
    "sg:orig_category":"Zootecnia E Pesca, Allevamento Piccoli Animali. Animali Domestici",
    "sg:phone":"+39 095 931083",
    "sg:postcode":"95014",
    "sg:province":"Catania",
    "wof:name":"Vanity Dog Di Napoli Graziella Natia",
    "wof:placetype":"venue"
},
  "geometry": {"coordinates":[15.089382,37.510746],"type":"Point"}
}