{
  "type": "Feature",
  "properties": {
    "addr:full":"12, Strada Abetone Brennero Nord 46035 Ostiglia Ostiglia Mantova 46035",
    "addr:postcode":"46035;46035",
    "addr:street":"Strada Abetone Brennero Nord",
    "iso:country":"IT",
    "sg:address":"12, Strada Abetone Brennero Nord 46035 Ostiglia",
    "sg:city":"Ostiglia",
    "sg:classifiers":[
        {
            "category":"Manufacturing",
            "subcategory":"Metals",
            "type":"Manufacturing & Wholesale Goods"
        }
    ],
    "sg:phone":"+39 0386 802940",
    "sg:postcode":"46035",
    "sg:province":"Mantova",
    "sg:tags":[
        "processing"
    ],
    "wof:name":"Gelmi Inox (s.r.l.)",
    "wof:placetype":"venue"
},
  "geometry": {"coordinates":[11.1424341202,45.0939865112],"type":"Point"}
}