{
  "type": "Feature",
  "properties": {
    "iso:country":"IT",
    "sg:address":"25017 Lonato",
    "sg:city":"Lonato",
    "sg:orig_category":"Servizi E Lavori Per Agricoltura E Zootecnia. Servizi E Lavori Per Ecologia E Smaltimento Rifiuti",
    "sg:postcode":"25017",
    "sg:province":"Brescia",
    "wof:name":"Consorzio Di Bonifica Medio Chiese",
    "wof:placetype":"venue"
},
  "geometry": {"coordinates":[10.232502,45.517506],"type":"Point"}
}