{
  "type": "Feature",
  "properties": {
    "iso:country":"IT",
    "sg:address":"20092 Cinisello Balsamo",
    "sg:city":"Cinisello Balsamo",
    "sg:orig_category":"Apparecchiature Ed Attrezzature Meccaniche",
    "sg:phone":"+39 02 6601 4628",
    "sg:postcode":"20092",
    "sg:province":"Milano",
    "sg:website":"http://www.uesseti.com",
    "wof:name":"Uesseti 2000 Srl",
    "wof:placetype":"venue"
},
  "geometry": {"coordinates":[9.214459,45.550907],"type":"Point"}
}