{
  "type": "Feature",
  "properties": {
    "iso:country":"IT",
    "sg:address":"21100 Varese",
    "sg:city":"Varese",
    "sg:orig_category":"Centri Di Estetica E Cosmesi E Servizi",
    "sg:phone":"+39 0332 236366",
    "sg:postcode":"21100",
    "sg:province":"Varese",
    "sg:website":"http://www.hotparty.it",
    "wof:name":"Hot Party",
    "wof:placetype":"venue"
},
  "geometry": {"coordinates":[8.839915,45.852459],"type":"Point"}
}