{
  "type": "Feature",
  "properties": {
    "iso:country":"IT",
    "sg:address":"90145 Palermo",
    "sg:city":"Palermo",
    "sg:orig_category":"Apparecchi, Attrezzature E Forniture Per Centri Estetici",
    "sg:phone":"+39 091 681 6748",
    "sg:postcode":"90145",
    "sg:province":"Palermo",
    "wof:name":"Beauty Market Di Edoardo Bartolone",
    "wof:placetype":"venue"
},
  "geometry": {"coordinates":[13.484411,38.079739],"type":"Point"}
}