{
  "type": "Feature",
  "properties": {
    "iso:country":"IT",
    "sg:address":"10129 Torino",
    "sg:city":"Torino",
    "sg:orig_category":"Prodotti Finiti Stampati. Forniture E Materiali Per Imballaggio E Confezionamento. Forniture Per Attivita' Commerciali Ed Artigianali",
    "sg:phone":"+39 011 591884",
    "sg:postcode":"10129",
    "sg:province":"Torino",
    "wof:name":"Sile",
    "wof:placetype":"venue"
},
  "geometry": {"coordinates":[7.5792469978,45.0265731812],"type":"Point"}
}