{
  "type": "Feature",
  "properties": {
    "iso:country":"IT",
    "sg:address":"21047 Saronno",
    "sg:city":"Saronno",
    "sg:orig_category":"Macchine, Impianti Ed Attrezzature Industria Chimica",
    "sg:phone":"+39 02 960 2727",
    "sg:postcode":"21047",
    "sg:province":"Varese",
    "wof:name":"Italwisad (s.r.l.)",
    "wof:placetype":"venue"
},
  "geometry": {"coordinates":[9.028486,45.624245],"type":"Point"}
}