{
  "type": "Feature",
  "properties": {
    "iso:country":"IT",
    "sg:address":"41, Via Della Costituzione 46010 Curtatone",
    "sg:city":"Curtatone",
    "sg:classifiers":[
        {
            "category":"Food & Beverages",
            "subcategory":"Groceries & Convenience Stores",
            "type":"Retail Goods"
        }
    ],
    "sg:phone":"+39 0376 290228",
    "sg:postcode":"46010",
    "sg:province":"Mantova",
    "sg:tags":[
        "product",
        "related"
    ],
    "wof:name":"Acetificio Mengazzoli Snc Di Mengazzoli Giorgio & C.",
    "wof:placetype":"venue"
},
  "geometry": {"coordinates":[10.770160675,45.130153656],"type":"Point"}
}