{
  "type": "Feature",
  "properties": {
    "iso:country":"IT",
    "sg:address":"20041 Agrate Brianza",
    "sg:city":"Agrate Brianza",
    "sg:orig_category":"Articoli Pulizia. Macchine E Forniture Per Ecologia E Smaltimento Rifiuti. Forniture Per Attivita' Commerciali Ed Artigianali",
    "sg:phone":"+39 039 689 0095",
    "sg:postcode":"20041",
    "sg:province":"Milano",
    "sg:website":"http://www.ledus.it",
    "wof:name":"Le.dus Di Cimmino",
    "wof:placetype":"venue"
},
  "geometry": {"coordinates":[9.353541,45.572975],"type":"Point"}
}