{
  "type": "Feature",
  "properties": {
    "iso:country":"IT",
    "sg:address":"Localita' Porto Conte 07041 Alghero",
    "sg:city":"Alghero",
    "sg:classifiers":[
        {
            "category":"Travel",
            "subcategory":"Travel Agent",
            "type":"Entertainment"
        }
    ],
    "sg:phone":"+39 39079942010",
    "sg:postcode":"07041",
    "sg:province":"Sassari",
    "sg:tags":[
        "business"
    ],
    "wof:name":"New Gest 2000 Srl",
    "wof:placetype":"venue"
},
  "geometry": {"coordinates":[8.558469,40.727165],"type":"Point"}
}