{
  "type": "Feature",
  "properties": {
    "iso:country":"IT",
    "sg:address":"26839 Zelo Buon Persico",
    "sg:city":"Zelo Buon Persico",
    "sg:orig_category":"Elettromagneti",
    "sg:phone":"+39 02 9065 9880",
    "sg:postcode":"26839",
    "sg:province":"Lodi",
    "wof:name":"Euromagneti Srl",
    "wof:placetype":"venue"
},
  "geometry": {"coordinates":[9.435109,45.395168],"type":"Point"}
}