{
  "type": "Feature",
  "properties": {
    "addr:full":"20154 Milano Milano Milano 20154",
    "addr:postcode":"20154;20154",
    "iso:country":"IT",
    "sg:address":"20154 Milano",
    "sg:city":"Milano",
    "sg:orig_category":"Mobili Metallici",
    "sg:phone":"+39 02 316870",
    "sg:postcode":"20154",
    "sg:province":"Milano",
    "wof:name":"Fsm Di Malara Annunziato",
    "wof:placetype":"venue"
},
  "geometry": {"coordinates":[9.1647968292,45.4867324829],"type":"Point"}
}