{
  "type": "Feature",
  "properties": {
    "iso:country":"IT",
    "sg:address":"20025 Legnano",
    "sg:city":"Legnano",
    "sg:orig_category":"Arredamenti E Mobili Professionali. Apparecchi, Attrezzature E Forniture Per Centri Estetici. Arredi Ed Attrezzature Per Attivita' Commerciali Ed Artigianali",
    "sg:phone":"+39 0331 440039",
    "sg:postcode":"20025",
    "sg:province":"Milano",
    "wof:name":"Le Forme Srl",
    "wof:placetype":"venue"
},
  "geometry": {"coordinates":[9.160802,45.565914],"type":"Point"}
}