{
  "type": "Feature",
  "properties": {
    "iso:country":"IT",
    "sg:address":"90141 Palermo",
    "sg:city":"Palermo",
    "sg:orig_category":"Accessori Dei Mezzi Di Trasporto. Riparazione Dei Mezzi Di Trasporto",
    "sg:phone":"+39 091 343618",
    "sg:postcode":"90141",
    "sg:province":"Palermo",
    "wof:name":"Jolly Tappezzeria",
    "wof:placetype":"venue"
},
  "geometry": {"coordinates":[13.345215,38.128757],"type":"Point"}
}