{
  "type": "Feature",
  "properties": {
    "addr:full":"P.a. Riggio, 15; Catenanuova; 94010 Catenanuova Enna 94010",
    "addr:housenumber":"15",
    "addr:postcode":"94010;94010",
    "iso:country":"IT",
    "sg:address":"P.a. Riggio, 15; Catenanuova; 94010",
    "sg:city":"Catenanuova",
    "sg:classifiers":[
        {
            "category":"Banks & Credit Unions",
            "subcategory":"Bank",
            "type":"Services"
        }
    ],
    "sg:phone":"+39 0935 75067",
    "sg:postcode":"94010",
    "sg:province":"Enna",
    "wof:name":"Cassa Rurale Ed Artigiana, La Riscossa",
    "wof:placetype":"venue"
},
  "geometry": {"coordinates":[14.689849,37.567055],"type":"Point"}
}