{
  "type": "Feature",
  "properties": {
    "iso:country":"IT",
    "sg:address":"40068 San Lazzaro Di Savena",
    "sg:city":"San Lazzaro",
    "sg:orig_category":"Elettronica Professionale E Di Consumo. Tempo Libero - Articoli E Forniture",
    "sg:phone":"+39 051 466226",
    "sg:postcode":"40068",
    "sg:province":"Bologna",
    "wof:name":"Cartolibreria Milena Snc",
    "wof:placetype":"venue"
},
  "geometry": {"coordinates":[11.407465,44.468792],"type":"Point"}
}