{
  "type": "Feature",
  "properties": {
    "iso:country":"IT",
    "sg:address":"81055 Santa Maria Capua Vetere",
    "sg:city":"Santa Maria Capua Vetere",
    "sg:orig_category":"Cine-foto-ottica. Articoli Medico-sanitari Ed Ortopedici. Impianti, Attrezzature E Forniture Sanitarie Ed Ospedaliere",
    "sg:phone":"+39 0823 843920",
    "sg:postcode":"81055",
    "sg:province":"Caserta",
    "wof:name":"Ottica Cappabianca",
    "wof:placetype":"venue"
},
  "geometry": {"coordinates":[14.25762,41.082031],"type":"Point"}
}