{
  "type": "Feature",
  "properties": {
    "iso:country":"IT",
    "sg:address":"Via Paolo Borsellino 10 91026 Mazara Del Vallo",
    "sg:city":"Mazara del Vallo",
    "sg:classifiers":[
        {
            "category":"Food & Beverages",
            "subcategory":"Liquor & Beverages",
            "type":"Retail Goods"
        }
    ],
    "sg:phone":"+39 0923 948411",
    "sg:postcode":"91026",
    "sg:province":"Trapani",
    "sg:tags":[
        "wine",
        "italian"
    ],
    "sg:website":"www.vallovin.com",
    "wof:name":"Vallovin S.r.l.",
    "wof:placetype":"venue"
},
  "geometry": {"coordinates":[12.514634,38.018589],"type":"Point"}
}