{
  "type": "Feature",
  "properties": {
    "iso:country":"IT",
    "sg:address":"25033 Cologne",
    "sg:city":"Cologne",
    "sg:orig_category":"Forniture Per Edilizia E Lavori Pubblici. Forniture Per Attivita' Industriali",
    "sg:phone":"+39 030 715588",
    "sg:postcode":"25033",
    "sg:province":"Brescia",
    "wof:name":"Gollini Tiziano",
    "wof:placetype":"venue"
},
  "geometry": {"coordinates":[9.9381132126,45.5757026672],"type":"Point"}
}