{
  "type": "Feature",
  "properties": {
    "iso:country":"IT",
    "sg:address":"31010 Fregona",
    "sg:city":"Fregona",
    "sg:orig_category":"Cancelli, Porte E Portoni Automatici E Telecomandati",
    "sg:phone":"+39 0438 915023",
    "sg:postcode":"31010",
    "sg:province":"Treviso",
    "wof:name":"Poza Di Pocchiesa & Zambon & C. Snc",
    "wof:placetype":"venue"
},
  "geometry": {"coordinates":[12.341278,46.004387],"type":"Point"}
}