{
  "type": "Feature",
  "properties": {
    "addr:full":"42049 S.ilario D'enza Reggio Nell'Emilia 42049",
    "addr:postcode":"42049;d'enza;42049",
    "iso:country":"IT",
    "sg:address":"42049 S.ilario D'enza",
    "sg:orig_category":"Materie Plastiche Rinforzate E Materiali Compositi",
    "sg:phone":"+39 0522 909723",
    "sg:postcode":"42049",
    "sg:province":"Reggio Nell'Emilia",
    "wof:name":"Nuova Nor Plast Di Medici Giorgio & C. Snc",
    "wof:placetype":"venue"
},
  "geometry": {"coordinates":[10.478555,44.754433],"type":"Point"}
}