{
  "type": "Feature",
  "properties": {
    "addr:full":"24121 Bergamo Bergamo Bergamo 24121",
    "addr:postcode":"24121;24121",
    "iso:country":"IT",
    "sg:address":"24121 Bergamo",
    "sg:city":"Bergamo",
    "sg:orig_category":"Servizi E Lavori Per Ecologia E Smaltimento Rifiuti. Servizi Ausiliari Di Sorveglianza, Manutenzione E Pulizia",
    "sg:phone":"+39 035 212011",
    "sg:postcode":"24121",
    "sg:province":"Bergamo",
    "wof:name":"Mocit Snc Di Guazzi Giorgio & C.",
    "wof:placetype":"venue"
},
  "geometry": {"coordinates":[9.673624,45.697548],"type":"Point"}
}