{
  "type": "Feature",
  "properties": {
    "iso:country":"IT",
    "sg:address":"25040 Monticelli Brusati",
    "sg:city":"Monticelli Brusati",
    "sg:orig_category":"Acciai Comuni",
    "sg:phone":"+39 030 653870",
    "sg:postcode":"25040",
    "sg:province":"Brescia",
    "wof:name":"Luigi Scotti",
    "wof:placetype":"venue"
},
  "geometry": {"coordinates":[10.108776,45.596451],"type":"Point"}
}