{
  "type": "Feature",
  "properties": {
    "iso:country":"IT",
    "sg:address":"95122 Catania",
    "sg:city":"Catania",
    "sg:orig_category":"Non-classified Establishments",
    "sg:phone":"+39 095 203423",
    "sg:postcode":"95122",
    "sg:province":"Catania",
    "wof:name":"Grasso Maria",
    "wof:placetype":"venue"
},
  "geometry": {"coordinates":[15.064209,37.497707],"type":"Point"}
}