{
  "type": "Feature",
  "properties": {
    "iso:country":"IT",
    "sg:address":"90143 Palermo",
    "sg:city":"Palermo",
    "sg:orig_category":"Forniture Per Attivita' Industriali",
    "sg:phone":"+39 091 626 2107",
    "sg:postcode":"90143",
    "sg:province":"Palermo",
    "wof:name":"Costantino Anna Rita",
    "wof:placetype":"venue"
},
  "geometry": {"coordinates":[13.3500652313,38.1419754028],"type":"Point"}
}