{
  "type": "Feature",
  "properties": {
    "iso:country":"IT",
    "sg:address":"80078 Pozzuoli",
    "sg:city":"Pozzuoli",
    "sg:classifiers":[
        {
            "category":"Home & Garden",
            "subcategory":"Building Materials",
            "type":"Retail Goods"
        }
    ],
    "sg:phone":"+39 081 526 3101",
    "sg:postcode":"80078",
    "sg:province":"Napoli",
    "sg:tags":[
        "case",
        "bungalow",
        "e",
        "prefabbricate"
    ],
    "wof:name":"De Cristofaro Adele",
    "wof:placetype":"venue"
},
  "geometry": {"coordinates":[14.120218,40.856796],"type":"Point"}
}