{
  "type": "Feature",
  "properties": {
    "iso:country":"IT",
    "sg:address":"14100 Asti",
    "sg:city":"Asti",
    "sg:orig_category":"Macchine, Impianti Ed Attrezzature Per Agricoltura E Zootecnia. Macchine E Forniture Per Arredamento E Industria Del Legno",
    "sg:phone":"+39 0141 30351",
    "sg:postcode":"14100",
    "sg:province":"Asti",
    "wof:name":"Casa Della Motosega Remo",
    "wof:placetype":"venue"
},
  "geometry": {"coordinates":[8.214519,44.883472],"type":"Point"}
}