{
  "type": "Feature",
  "properties": {
    "addr:full":"Via G. Donizetti 22 22032 Albese Como 22032",
    "addr:housenumber":"22",
    "addr:postcode":"22032;22032",
    "addr:street":"Via G. Donizetti",
    "iso:country":"IT",
    "sg:address":"Via G. Donizetti 22 22032 Albese",
    "sg:classifiers":[
        {
            "category":"Retail",
            "subcategory":"Animal Services",
            "type":"Services"
        }
    ],
    "sg:phone":"+39 031 428205",
    "sg:postcode":"22032",
    "sg:province":"Como",
    "sg:tags":[
        "article",
        "veterinary",
        "drug",
        "care"
    ],
    "wof:name":"I & M Bernareggi Di Brazzola Bernareggi Srl",
    "wof:placetype":"venue"
},
  "geometry": {"coordinates":[9.152507,45.795349],"type":"Point"}
}