{
  "type": "Feature",
  "properties": {
    "addr:full":"8, Via Fieschi 16121 Genova Genova Genova 16121",
    "addr:postcode":"16121;16121",
    "addr:street":"Via Fieschi",
    "iso:country":"IT",
    "sg:address":"8, Via Fieschi 16121 Genova",
    "sg:city":"Genova",
    "sg:classifiers":[
        {
            "category":"Marine",
            "type":"Transportation"
        }
    ],
    "sg:phone":"+39 39010531941",
    "sg:postcode":"16121",
    "sg:province":"Genova",
    "sg:tags":[
        "transport",
        "sea"
    ],
    "wof:name":"Enterprise Shipping Agency Srl",
    "wof:placetype":"venue"
},
  "geometry": {"coordinates":[8.936343,44.404846],"type":"Point"}
}