{
  "type": "Feature",
  "properties": {
    "iso:country":"IT",
    "sg:address":"20041 Agrate Brianza",
    "sg:city":"Agrate Brianza",
    "sg:orig_category":"Sport - Articoli E Forniture",
    "sg:phone":"+39 039 650630",
    "sg:postcode":"20041",
    "sg:province":"Milano",
    "wof:name":"Brianfisher (s.n.c.)",
    "wof:placetype":"venue"
},
  "geometry": {"coordinates":[9.354842,45.57996],"type":"Point"}
}