{
  "type": "Feature",
  "properties": {
    "iso:country":"IT",
    "sg:address":"41100 Modena",
    "sg:city":"Modena",
    "sg:orig_category":"Valvole E Apparecchiature Di Misura. Attrezzature E Forniture Per Officine Riparazione E Servizi Ausiliari. Macchine, Strumenti Ed Apparecchi Per Attivita' Industriali",
    "sg:phone":"+39 059 346441",
    "sg:postcode":"41100",
    "sg:province":"Modena",
    "wof:name":"Aep Transducers Srl",
    "wof:placetype":"venue"
},
  "geometry": {"coordinates":[10.914429,44.663944],"type":"Point"}
}