{
  "type": "Feature",
  "properties": {
    "addr:full":"12042 Bra Bra Cuneo 12042",
    "addr:postcode":"12042;12042",
    "iso:country":"IT",
    "sg:address":"12042 Bra",
    "sg:city":"Bra",
    "sg:orig_category":"Scuole E Servizi Scolastici. Ricerca, Selezione E Formazione Del Personale",
    "sg:phone":"+39 0172 413158",
    "sg:postcode":"12042",
    "sg:province":"Cuneo",
    "wof:name":"Istituto Stenografico Commerciale",
    "wof:placetype":"venue"
},
  "geometry": {"coordinates":[7.927277,44.675545],"type":"Point"}
}