{
  "type": "Feature",
  "properties": {
    "addr:full":"62010 Montefano Montefano Macerata 62010",
    "addr:postcode":"62010;62010",
    "addr:street":"Montefano",
    "iso:country":"IT",
    "sg:address":"62010 Montefano",
    "sg:city":"Montefano",
    "sg:orig_category":"Motori Ed Organi Di Trasmissione. Ricambi E Componenti Dei Mezzi Di Trasporto",
    "sg:phone":"+39 0733 850050",
    "sg:postcode":"62010",
    "sg:province":"Macerata",
    "wof:name":"As.m.e. (s.r.l.)",
    "wof:placetype":"venue"
},
  "geometry": {"coordinates":[13.4393892288,43.4122047424],"type":"Point"}
}