{
  "type": "Feature",
  "properties": {
    "addr:full":"Via Agnano Agli Astroni 80125 Napoli Napoli Napoli 80125",
    "addr:postcode":"80125;80125",
    "addr:street":"Via Agnano;Astroni",
    "iso:country":"IT",
    "sg:address":"Via Agnano Agli Astroni 80125 Napoli",
    "sg:city":"Napoli",
    "sg:classifiers":[
        {
            "category":"Travel",
            "subcategory":"Travel Agent",
            "type":"Entertainment"
        }
    ],
    "sg:phone":"+39 081 570 1733",
    "sg:postcode":"80125",
    "sg:province":"Napoli",
    "sg:tags":[
        "business"
    ],
    "wof:name":"Albergo Hotel Delle Terme Di Agnano",
    "wof:placetype":"venue"
},
  "geometry": {"coordinates":[14.251636,40.840096],"type":"Point"}
}