{
  "type": "Feature",
  "properties": {
    "addr:full":"55, Viale Caduti Sul Lavoro 41100 Modena Modena Modena 41100",
    "addr:housenumber":"55",
    "addr:postcode":"41100;41100",
    "addr:street":"Viale Caduti Sul Lavoro",
    "iso:country":"IT",
    "sg:address":"55, Viale Caduti Sul Lavoro 41100 Modena",
    "sg:city":"Modena",
    "sg:classifiers":[
        {
            "category":"Travel",
            "subcategory":"Travel Agent",
            "type":"Entertainment"
        }
    ],
    "sg:phone":"+39 39059582111",
    "sg:postcode":"41100",
    "sg:province":"Modena",
    "sg:tags":[
        "business"
    ],
    "wof:name":"Finifast Srl",
    "wof:placetype":"venue"
},
  "geometry": {"coordinates":[10.970982,44.63068],"type":"Point"}
}