{
  "type": "Feature",
  "properties": {
    "addr:full":"Via Buonarroti 12 51011 Borgo A Buggiano Borgo a buggiano Pistoia 51011",
    "addr:housenumber":"12",
    "addr:postcode":"51011;51011",
    "addr:street":"Via Buonarroti",
    "iso:country":"IT",
    "sg:address":"Via Buonarroti 12 51011 Borgo A Buggiano",
    "sg:city":"Borgo a buggiano",
    "sg:classifiers":[
        {
            "category":"Farming",
            "subcategory":"Nursery",
            "type":"Manufacturing & Wholesale Goods"
        }
    ],
    "sg:phone":"+39 0572 32113",
    "sg:postcode":"51011",
    "sg:province":"Pistoia",
    "sg:tags":[
        "greenhouse"
    ],
    "wof:name":"Gome Agri Srl",
    "wof:placetype":"venue"
},
  "geometry": {"coordinates":[10.918524,43.932156],"type":"Point"}
}