{
  "type": "Feature",
  "properties": {
    "addr:full":"40050 Monterenzio Monterenzio Bologna 40050",
    "addr:postcode":"40050;monterenzio bologna 40050",
    "iso:country":"IT",
    "sg:address":"40050 Monterenzio",
    "sg:city":"Monterenzio",
    "sg:orig_category":"Prodotti Di Base E Forniture Per Industria Alimentare E Bevande. Prodotti Chimici Di Base",
    "sg:phone":"+39 051 920450",
    "sg:postcode":"40050",
    "sg:province":"Bologna",
    "wof:name":"Molino Boschi Srl",
    "wof:placetype":"venue"
},
  "geometry": {"coordinates":[11.3618898392,44.5027389526],"type":"Point"}
}