{
  "type": "Feature",
  "properties": {
    "addr:full":"00040 Pomezia Pomezia Roma 00040",
    "addr:postcode":"00040;roma 00040",
    "iso:country":"IT",
    "sg:address":"00040 Pomezia",
    "sg:city":"Pomezia",
    "sg:orig_category":"Banche E Servizi Finanziari. Acqua, Luce, Gas E Societa' Di Esercizio Pubblico",
    "sg:phone":"+39 06 911 2433",
    "sg:postcode":"00040",
    "sg:province":"Roma",
    "wof:name":"Esattoria Comunale",
    "wof:placetype":"venue"
},
  "geometry": {"coordinates":[12.501709,41.669582],"type":"Point"}
}