{
  "type": "Feature",
  "properties": {
    "iso:country":"IT",
    "sg:address":"9, Via Vittorio Emanuele Iii 35020 Codevigo",
    "sg:city":"Codevigo",
    "sg:classifiers":[
        {
            "category":"Farming",
            "subcategory":"Livestock Farm",
            "type":"Manufacturing & Wholesale Goods"
        }
    ],
    "sg:phone":"+39 049 581 7042",
    "sg:postcode":"35020",
    "sg:province":"Padova",
    "sg:tags":[
        "agriculture"
    ],
    "wof:name":"F.lli Lionello Siro E Claudio Eredi Di Lionello Rainieri Sdf Ereditari",
    "wof:placetype":"venue"
},
  "geometry": {"coordinates":[12.096201,45.268688],"type":"Point"}
}