{
  "type": "Feature",
  "properties": {
    "addr:full":"00010 Roma Roma 00010",
    "addr:postcode":"00010;00010",
    "iso:country":"IT",
    "sg:address":"00010 Roma",
    "sg:orig_category":"Serramenti Ed Infissi",
    "sg:phone":"+39 06 226 0964",
    "sg:postcode":"00010",
    "sg:province":"Roma",
    "wof:name":"Cicetti Costruzioni Metalliche Srl",
    "wof:placetype":"venue"
},
  "geometry": {"coordinates":[12.6805858612,41.9099311829],"type":"Point"}
}