{
  "type": "Feature",
  "properties": {
    "iso:country":"IT",
    "sg:address":"41012 Carpi",
    "sg:city":"Carpi",
    "sg:orig_category":"Impiantistica E Prodotti Tecnologici Per Edilizia. Forniture Industriali Per Prevenzione, Controllo E Sicurezza",
    "sg:phone":"+39 059 622 9364",
    "sg:postcode":"41012",
    "sg:province":"Modena",
    "wof:name":"Zeus Italia Srl",
    "wof:placetype":"venue"
},
  "geometry": {"coordinates":[10.863265,44.837715],"type":"Point"}
}