{
  "type": "Feature",
  "properties": {
    "addr:full":"Via Garibaldi Giuseppe 88837 Petilia Policastro Petilia Policastro Crotone 88837",
    "addr:housenumber":"policastro",
    "addr:postcode":"88837;88837",
    "addr:street":"Via Garibaldi Giuseppe",
    "iso:country":"IT",
    "sg:address":"Via Garibaldi Giuseppe 88837 Petilia Policastro",
    "sg:city":"Petilia Policastro",
    "sg:classifiers":[
        {
            "category":"Food & Beverages",
            "subcategory":"Groceries & Convenience Stores",
            "type":"Retail Goods"
        }
    ],
    "sg:phone":"+39 0962 434882",
    "sg:postcode":"88837",
    "sg:province":"Crotone",
    "sg:tags":[
        "product",
        "related"
    ],
    "wof:name":"Agroalimentare A. &.a. Nicolazzi Snc",
    "wof:placetype":"venue"
},
  "geometry": {"coordinates":[17.12707901,39.0807380676],"type":"Point"}
}