{
  "type": "Feature",
  "properties": {
    "addr:full":"11, Via Piave 20067 Tribiano Tribiano Milano 20067",
    "addr:postcode":"20067;20067",
    "addr:street":"Via Piave",
    "iso:country":"IT",
    "sg:address":"11, Via Piave 20067 Tribiano",
    "sg:city":"Tribiano",
    "sg:classifiers":[
        {
            "category":"Manufacturing",
            "subcategory":"Food",
            "type":"Manufacturing & Wholesale Goods"
        }
    ],
    "sg:phone":"+39 02 9063 1043",
    "sg:postcode":"20067",
    "sg:province":"Milano",
    "sg:tags":[
        "equipment",
        "processing",
        "-",
        "machinery"
    ],
    "wof:name":"Mazzetti Renato Srl Renato",
    "wof:placetype":"venue"
},
  "geometry": {"coordinates":[9.3796663284,45.4144744873],"type":"Point"}
}