{
  "type": "Feature",
  "properties": {
    "addr:full":"10128 Torino Torino Torino 10128",
    "addr:postcode":"10128;10128",
    "iso:country":"IT",
    "sg:address":"10128 Torino",
    "sg:city":"Torino",
    "sg:orig_category":"Pubblica Amministrazione",
    "sg:phone":"+39 011 517 8781",
    "sg:postcode":"10128",
    "sg:province":"Torino",
    "wof:name":"Corpo Forestale Dello Stato",
    "wof:placetype":"venue"
},
  "geometry": {"coordinates":[7.6706352234,45.0627632141],"type":"Point"}
}