{
  "type": "Feature",
  "properties": {
    "addr:full":"35, Localita' S. Zeno 52100 Arezzo Arezzo Arezzo 52100",
    "addr:postcode":"52100;52100",
    "addr:street":"Localita ' S. Zeno",
    "iso:country":"IT",
    "sg:address":"35, Localita' S. Zeno 52100 Arezzo",
    "sg:city":"Arezzo",
    "sg:classifiers":[
        {
            "category":"Shopping",
            "subcategory":"Jewelry",
            "type":"Retail Goods"
        }
    ],
    "sg:phone":"+39 0575 959212",
    "sg:postcode":"52100",
    "sg:province":"Arezzo",
    "sg:tags":[
        "jewellery"
    ],
    "wof:name":"New Trend 2002 Srl",
    "wof:placetype":"venue"
},
  "geometry": {"coordinates":[11.819435,43.462509],"type":"Point"}
}