{
  "type": "Feature",
  "properties": {
    "addr:full":"00145 Roma Roma Roma 00145",
    "addr:postcode":"00145;00145",
    "iso:country":"IT",
    "sg:address":"00145 Roma",
    "sg:city":"Roma",
    "sg:orig_category":"Studi E Consulenze Tecniche E Industriali. Servizi E Lavori Per Edilizia E Lavori Pubblici. Professionisti - Studi E Servizi Ed Associazioni Di Interesse Aziendale",
    "sg:phone":"+39 06 541 3351",
    "sg:postcode":"00145",
    "sg:province":"Roma",
    "wof:name":"Arzilla Tiziano",
    "wof:placetype":"venue"
},
  "geometry": {"coordinates":[12.486008,41.851433],"type":"Point"}
}