{
  "type": "Feature",
  "properties": {
    "iso:country":"IT",
    "sg:address":"38100 Trento",
    "sg:city":"Trento",
    "sg:orig_category":"Impiantistica E Prodotti Tecnologici Per Edilizia. Climatizzazione E Condizionamento, Apparecchiature E Servizi",
    "sg:phone":"+39 0461 950611",
    "sg:postcode":"38100",
    "sg:province":"Trento",
    "sg:website":"http://www.climacenter.com",
    "wof:name":"Climacenter (sovecar2) Snc Di Giglioli Enrico & C.",
    "wof:placetype":"venue"
},
  "geometry": {"coordinates":[11.11063,46.124554],"type":"Point"}
}