{
  "type": "Feature",
  "properties": {
    "iso:country":"IT",
    "sg:address":"22100 Como",
    "sg:city":"Como",
    "sg:classifiers":[
        {
            "category":"Personal",
            "subcategory":"Piercing",
            "type":"Services"
        }
    ],
    "sg:phone":"+39 031 300346",
    "sg:postcode":"22100",
    "sg:province":"Como",
    "sg:tags":[
        "e",
        "tatuaggi"
    ],
    "wof:name":"Tattoo Studio Caldonia By Ivan",
    "wof:placetype":"venue"
},
  "geometry": {"coordinates":[9.092748,45.799282],"type":"Point"}
}