{
  "type": "Feature",
  "properties": {
    "iso:country":"IT",
    "sg:address":"00153 Roma",
    "sg:city":"Roma",
    "sg:orig_category":"Audiovisivi Filmati, Spot E Multimediali - Realizzazione E Duplicazione",
    "sg:phone":"+39 06 6880 8643",
    "sg:postcode":"00153",
    "sg:province":"Roma",
    "wof:name":"Temafilm Di Danilo Tedone",
    "wof:placetype":"venue"
},
  "geometry": {"coordinates":[12.485897,41.879463],"type":"Point"}
}