{
  "type": "Feature",
  "properties": {
    "addr:full":"20144 Milano Milano Milano 20144",
    "addr:postcode":"20144;20144",
    "iso:country":"IT",
    "sg:address":"20144 Milano",
    "sg:city":"Milano",
    "sg:orig_category":"Arredamento Parrucchieri Ed Istituti Di Bellezza",
    "sg:phone":"+39 02 8942 2292",
    "sg:postcode":"20144",
    "sg:province":"Milano",
    "sg:website":"http://www.salonservice.it",
    "wof:name":"Gestione Salon Service Srl",
    "wof:placetype":"venue"
},
  "geometry": {"coordinates":[9.167369,45.45322],"type":"Point"}
}