{
  "type": "Feature",
  "properties": {
    "iso:country":"IT",
    "sg:address":"20122 Milano",
    "sg:city":"Milano",
    "sg:orig_category":"Servizi Ausiliari Di Analisi, Controllo E Ricerca",
    "sg:phone":"+39 02 878441",
    "sg:postcode":"20122",
    "sg:province":"Milano",
    "wof:name":"Il Poliedro",
    "wof:placetype":"venue"
},
  "geometry": {"coordinates":[9.190414,45.46006],"type":"Point"}
}