{
  "type": "Feature",
  "properties": {
    "iso:country":"IT",
    "sg:address":"10, Viale Rimembranze 25050 Pian Camuno",
    "sg:city":"Pian Camuno",
    "sg:classifiers":[
        {
            "category":"Real Estate",
            "subcategory":"Architect",
            "type":"Services"
        }
    ],
    "sg:phone":"+39 036 459 1107",
    "sg:postcode":"25050",
    "sg:province":"Brescia",
    "sg:tags":[
        "textile",
        "clothing"
    ],
    "wof:name":"Cooperativa Camuna Di Confezioni S.c.r.l.",
    "wof:placetype":"venue"
},
  "geometry": {"coordinates":[10.145896,45.844994],"type":"Point"}
}