{
  "type": "Feature",
  "properties": {
    "iso:country":"IT",
    "sg:address":"23816 Barzio",
    "sg:city":"Barzio",
    "sg:orig_category":"Servizi Per Lo Sport E Il Tempo Libero. Alberghi E Strutture Extra Alberghiere",
    "sg:phone":"+39 0341 996353",
    "sg:postcode":"23816",
    "sg:province":"Lecco",
    "wof:name":"Rifugio Sora",
    "wof:placetype":"venue"
},
  "geometry": {"coordinates":[9.491683,45.953484],"type":"Point"}
}