{
  "type": "Feature",
  "properties": {
    "iso:country":"IT",
    "sg:address":"20018 Sedriano",
    "sg:city":"Sedriano",
    "sg:orig_category":"Macchine Ed Impianti Per Edilizia E Lavori Pubblici",
    "sg:phone":"+39 02 902 0310",
    "sg:postcode":"20018",
    "sg:province":"Milano",
    "wof:name":"Gaglio Giuseppe",
    "wof:placetype":"venue"
},
  "geometry": {"coordinates":[9.179182,45.464802],"type":"Point"}
}