{
  "type": "Feature",
  "properties": {
    "iso:country":"IT",
    "sg:address":"80057 Sant'antonio Abate",
    "sg:orig_category":"Carta Da Parati - Vendita Al Dettaglio",
    "sg:phone":"+39 081 879 7116",
    "sg:postcode":"80057",
    "sg:province":"Napoli",
    "wof:name":"Parati E Colori Sas",
    "wof:placetype":"venue"
},
  "geometry": {"coordinates":[14.54148,40.72438],"type":"Point"}
}