{
  "type": "Feature",
  "properties": {
    "iso:country":"IT",
    "sg:address":"20021 Baranzate",
    "sg:city":"Baranzate",
    "sg:orig_category":"Macchine, Impianti Ed Attrezzature Per Agricoltura E Zootecnia. Macchine, Impianti Ed Attrezzature Industria Chimica. Macchine Utensili E Impianti",
    "sg:phone":"+39 02 382 2021",
    "sg:postcode":"20021",
    "sg:province":"Milano",
    "wof:name":"I.s.g. Srl",
    "wof:placetype":"venue"
},
  "geometry": {"coordinates":[9.110268,45.534241],"type":"Point"}
}