{
  "type": "Feature",
  "properties": {
    "iso:country":"IT",
    "sg:address":"60125 Ancona",
    "sg:city":"Ancona",
    "sg:orig_category":"Centri Di Estetica E Cosmesi E Servizi. Prodotti Cosmetici E Da Toeletta",
    "sg:phone":"+39 071 280 1864",
    "sg:postcode":"60125",
    "sg:province":"Ancona",
    "wof:name":"Santarelli Stefano",
    "wof:placetype":"venue"
},
  "geometry": {"coordinates":[13.501762,43.609886],"type":"Point"}
}