{
  "type": "Feature",
  "properties": {
    "iso:country":"IT",
    "sg:address":"67040 Ocre",
    "sg:orig_category":"Dolciumi - Produzione",
    "sg:phone":"+39 0862 67423",
    "sg:postcode":"67040",
    "sg:province":"L'Aquila",
    "wof:name":"Dolci Aveja Di Mariano Calvisi E C. Snc",
    "wof:placetype":"venue"
},
  "geometry": {"coordinates":[13.457708,42.313511],"type":"Point"}
}