{
  "type": "Feature",
  "properties": {
    "iso:country":"IT",
    "sg:address":"20127 Milano",
    "sg:city":"Milano",
    "sg:orig_category":"Cinematografia E Radiotelevisione",
    "sg:phone":"+39 02 261 0481",
    "sg:postcode":"20127",
    "sg:province":"Milano",
    "wof:name":"Milano Produzioni Di Previati Carlo & C. (s.a.s.)",
    "wof:placetype":"venue"
},
  "geometry": {"coordinates":[9.2319984436,45.4977035522],"type":"Point"}
}