{
  "type": "Feature",
  "properties": {
    "addr:full":"25125 Brescia Brescia Brescia 25125",
    "addr:postcode":"25125;25125",
    "iso:country":"IT",
    "sg:address":"25125 Brescia",
    "sg:city":"Brescia",
    "sg:orig_category":"Forniture E Materiali Per Imballaggio E Confezionamento",
    "sg:phone":"+39 030 358 1820",
    "sg:postcode":"25125",
    "sg:province":"Brescia",
    "sg:website":"http://www.paginegialle.it/methrica",
    "wof:name":"Methrica Srl",
    "wof:placetype":"venue"
},
  "geometry": {"coordinates":[10.1658468246,45.5145759583],"type":"Point"}
}