{
  "type": "Feature",
  "properties": {
    "iso:country":"IT",
    "sg:address":"24042 Capriate San Gervasio",
    "sg:city":"Capriate San Gervasio",
    "sg:classifiers":[
        {
            "category":"Health Services",
            "subcategory":"Health Practitioner",
            "type":"Services"
        }
    ],
    "sg:phone":"+39 02 909 1046",
    "sg:postcode":"24042",
    "sg:province":"Bergamo",
    "sg:tags":[
        "medici"
    ],
    "wof:name":"Uberti Dr. Paolo",
    "wof:placetype":"venue"
},
  "geometry": {"coordinates":[9.5251550674,45.620136261],"type":"Point"}
}