{
  "type": "Feature",
  "properties": {
    "iso:country":"IT",
    "sg:address":"03012 Anagni",
    "sg:city":"Anagni",
    "sg:orig_category":"Forniture Per Abbigliamento E Pelletterie. Forniture Per Attivita' Commerciali Ed Artigianali",
    "sg:phone":"+39 0775 769363",
    "sg:postcode":"03012",
    "sg:province":"Frosinone",
    "wof:name":"Datalabel Group Srl",
    "wof:placetype":"venue"
},
  "geometry": {"coordinates":[13.150967598,41.7346305847],"type":"Point"}
}