{
  "type": "Feature",
  "properties": {
    "iso:country":"IT",
    "sg:address":"36071 Arzignano",
    "sg:city":"Arzignano",
    "sg:orig_category":"Prodotti Chimici Di Base",
    "sg:phone":"+39 0444 451600",
    "sg:postcode":"36071",
    "sg:province":"Vicenza",
    "sg:website":"http://www.bomitali.it",
    "wof:name":"Bomitali Luigi & Figli Srl",
    "wof:placetype":"venue"
},
  "geometry": {"coordinates":[11.3352251053,45.5208435059],"type":"Point"}
}