{
  "type": "Feature",
  "properties": {
    "addr:full":"20122 Milano Milano Milano 20122",
    "addr:postcode":"20122;20122",
    "iso:country":"IT",
    "sg:address":"20122 Milano",
    "sg:city":"Milano",
    "sg:orig_category":"Assicurazioni E Servizi Assicurativi",
    "sg:phone":"+39 02 5832 0272",
    "sg:postcode":"20122",
    "sg:province":"Milano",
    "wof:name":"A.i.c. (s.r.l.)",
    "wof:placetype":"venue"
},
  "geometry": {"coordinates":[9.187041,45.455235],"type":"Point"}
}