{
  "type": "Feature",
  "properties": {
    "addr:full":"16162 Genova Genova Genova 16162",
    "addr:postcode":"16162;16162",
    "iso:country":"IT",
    "sg:address":"16162 Genova",
    "sg:city":"Genova",
    "sg:orig_category":"Servizi Per Lo Sport E Il Tempo Libero. Servizi Al Turismo",
    "sg:phone":"+39 010 749 0512",
    "sg:postcode":"16162",
    "sg:province":"Genova",
    "wof:name":"Bouwling Sport Bolzaneto",
    "wof:placetype":"venue"
},
  "geometry": {"coordinates":[8.898944,44.456001],"type":"Point"}
}