{
  "type": "Feature",
  "properties": {
    "iso:country":"IT",
    "sg:address":"Km. 12.200, Via Trani 70033 Corato",
    "sg:city":"Corato",
    "sg:classifiers":[
        {
            "category":"Real Estate",
            "subcategory":"Architect",
            "type":"Services"
        }
    ],
    "sg:phone":"+39 080 872 5087",
    "sg:postcode":"70033",
    "sg:province":"Bari",
    "sg:tags":[
        "textile",
        "clothing"
    ],
    "wof:name":"Texemme Di Musto Maria",
    "wof:placetype":"venue"
},
  "geometry": {"coordinates":[16.869291,41.126053],"type":"Point"}
}