{
  "type": "Feature",
  "properties": {
    "iso:country":"IT",
    "sg:address":"13100 Vercelli",
    "sg:city":"Vercelli",
    "sg:orig_category":"Servizi E Lavori Industria Chimica. Trattamenti Termici E Superficiali Metalli, Galvanotecnica",
    "sg:phone":"+39 0161 259688",
    "sg:postcode":"13100",
    "sg:province":"Vercelli",
    "wof:name":"Portaro Antonio Decorazioni Di Portaro Nicola & C. Snc",
    "wof:placetype":"venue"
},
  "geometry": {"coordinates":[8.428677,45.318104],"type":"Point"}
}