{
  "type": "Feature",
  "properties": {
    "iso:country":"IT",
    "sg:address":"47100 Forli'",
    "sg:orig_category":"Forniture Per Agricoltura E Zootecnia. Animali Domestici",
    "sg:phone":"+39 0543 796464",
    "sg:postcode":"47100",
    "sg:province":"Forl\u00ec-Cesena",
    "wof:name":"Chemifarma Spa",
    "wof:placetype":"venue"
},
  "geometry": {"coordinates":[11.9804611206,43.9947662354],"type":"Point"}
}