{
  "type": "Feature",
  "properties": {
    "iso:country":"IT",
    "sg:address":"Via Blel\u00e9, 35/r 16133 Genova",
    "sg:city":"Genova",
    "sg:classifiers":[
        {
            "category":"Autos & Motor Vehicles",
            "subcategory":"Auto Supplies",
            "type":"Retail Goods"
        }
    ],
    "sg:phone":"+39 010 511830",
    "sg:postcode":"16133",
    "sg:province":"Genova",
    "sg:tags":[
        "automobile",
        "part",
        "spare"
    ],
    "sg:website":"www.far-ricambi.it",
    "wof:name":"F.a.r. Snc",
    "wof:placetype":"venue"
},
  "geometry": {"coordinates":[8.933989,44.407063],"type":"Point"}
}