{
  "type": "Feature",
  "properties": {
    "addr:full":"9, Via Nazionale 64020 Bellante Bellante Teramo 64020",
    "addr:postcode":"64020;64020",
    "addr:street":"Via Nazionale",
    "iso:country":"IT",
    "sg:address":"9, Via Nazionale 64020 Bellante",
    "sg:city":"Bellante",
    "sg:classifiers":[
        {
            "category":"Shopping",
            "subcategory":"Clothing, Apparel, & Fashions",
            "type":"Retail Goods"
        }
    ],
    "sg:phone":"+39 0861 610924",
    "sg:postcode":"64020",
    "sg:province":"Teramo",
    "sg:tags":[
        "clothes"
    ],
    "wof:name":"Cobel Sdf",
    "wof:placetype":"venue"
},
  "geometry": {"coordinates":[13.840571,42.706451],"type":"Point"}
}