{
  "type": "Feature",
  "properties": {
    "addr:full":"20123 Milano Milano Milano 20123",
    "addr:postcode":"20123;20123",
    "iso:country":"IT",
    "sg:address":"20123 Milano",
    "sg:city":"Milano",
    "sg:orig_category":"Pubblica Amministrazione",
    "sg:phone":"+39 02 4800 2256",
    "sg:postcode":"20123",
    "sg:province":"Milano",
    "wof:name":"C.a.m. Centro Ausiliario Per Problemi Minorili",
    "wof:placetype":"venue"
},
  "geometry": {"coordinates":[9.1733493805,45.4690093994],"type":"Point"}
}