{
  "type": "Feature",
  "properties": {
    "iso:country":"IT",
    "sg:address":"40066 Pieve Di Cento",
    "sg:city":"Pieve di Cento",
    "sg:orig_category":"Forniture Industriali Per Prevenzione, Controllo E Sicurezza",
    "sg:phone":"+39 051 975098",
    "sg:postcode":"40066",
    "sg:province":"Bologna",
    "wof:name":"Guantificio Stella Di Banzi P. E S. S.n.c.",
    "wof:placetype":"venue"
},
  "geometry": {"coordinates":[11.3220567703,44.7223091125],"type":"Point"}
}