{
  "type": "Feature",
  "properties": {
    "addr:full":"53034 Colle Di Val D'elsa Siena 53034",
    "addr:postcode":"53034;53034",
    "iso:country":"IT",
    "sg:address":"53034 Colle Di Val D'elsa",
    "sg:orig_category":"Manufacturers: Prefabbricati. Servizi E Lavori Per Ecologia E Smaltimento Rifiuti",
    "sg:phone":"+39 0577 959521",
    "sg:postcode":"53034",
    "sg:province":"Siena",
    "wof:name":"Biagini & Volpini Srl",
    "wof:placetype":"venue"
},
  "geometry": {"coordinates":[11.093808,43.384811],"type":"Point"}
}