{
  "type": "Feature",
  "properties": {
    "iso:country":"IT",
    "sg:address":"20013 Magenta",
    "sg:city":"Magenta",
    "sg:orig_category":"Articoli Medico-sanitari Ed Ortopedici. Impianti, Attrezzature E Forniture Sanitarie Ed Ospedaliere",
    "sg:phone":"+39 02 9729 2350",
    "sg:postcode":"20013",
    "sg:province":"Milano",
    "wof:name":"New Line S.r.l.",
    "wof:placetype":"venue"
},
  "geometry": {"coordinates":[8.871263,45.484722],"type":"Point"}
}