{
  "type": "Feature",
  "properties": {
    "iso:country":"IT",
    "sg:address":"15048 Valenza",
    "sg:city":"Valenza",
    "sg:orig_category":"Gioielleria, Oreficeria E Argenteria",
    "sg:phone":"+39 0131 945755",
    "sg:postcode":"15048",
    "sg:province":"Alessandria",
    "wof:name":"Foress S.n.c.",
    "wof:placetype":"venue"
},
  "geometry": {"coordinates":[8.607464,44.910973],"type":"Point"}
}