{
  "type": "Feature",
  "properties": {
    "iso:country":"IT",
    "sg:address":"29016 Cortemaggiore",
    "sg:city":"Cortemaggiore",
    "sg:orig_category":"Forniture Per Agricoltura E Zootecnia. Prodotti Chimici Secondari",
    "sg:phone":"+39 0523 836991",
    "sg:postcode":"29016",
    "sg:province":"Piacenza",
    "wof:name":"Nazzani Ermanno",
    "wof:placetype":"venue"
},
  "geometry": {"coordinates":[9.9211339951,44.9899406433],"type":"Point"}
}