{
  "type": "Feature",
  "properties": {
    "iso:country":"IT",
    "sg:address":"Via Piave 6 22035 Canzo",
    "sg:city":"Canzo",
    "sg:classifiers":[
        {
            "category":"Military Area",
            "subcategory":"Air Force Base",
            "type":"Public Place"
        }
    ],
    "sg:phone":"+39 031 684320",
    "sg:postcode":"22035",
    "sg:province":"Como",
    "sg:tags":[
        "equipment",
        "galvanizing",
        "system",
        "electroplating"
    ],
    "sg:website":"www.cvkaut.it",
    "wof:name":"Cvk Automazione Industriale Srl",
    "wof:placetype":"venue"
},
  "geometry": {"coordinates":[9.260376,45.842934],"type":"Point"}
}