{
  "type": "Feature",
  "properties": {
    "addr:full":"21012 Cassano Magnago Cassano Magnago Varese 21012",
    "addr:postcode":"21012;21012",
    "iso:country":"IT",
    "sg:address":"21012 Cassano Magnago",
    "sg:city":"Cassano Magnago",
    "sg:orig_category":"Manufacturers: Prefabbricati",
    "sg:phone":"+39 0331 201098",
    "sg:postcode":"21012",
    "sg:province":"Varese",
    "wof:name":"Luvatti E Crugnola Di Luatti Felicee Luvatti Gianstefano S.n.c.",
    "wof:placetype":"venue"
},
  "geometry": {"coordinates":[8.834249,45.66695],"type":"Point"}
}