{
  "type": "Feature",
  "properties": {
    "addr:full":"28, Via Giuseppe Parini 23861 Cesana Brianza Cesana Brianza Lecco 23861",
    "addr:postcode":"23861;brianza;23861",
    "addr:street":"Via Giuseppe Parini",
    "iso:country":"IT",
    "sg:address":"28, Via Giuseppe Parini 23861 Cesana Brianza",
    "sg:city":"Cesana Brianza",
    "sg:classifiers":[
        {
            "category":"Manufacturing",
            "subcategory":"Metals",
            "type":"Manufacturing & Wholesale Goods"
        }
    ],
    "sg:phone":"+39 031 335 8211",
    "sg:postcode":"23861",
    "sg:province":"Lecco",
    "sg:tags":[
        "processing"
    ],
    "wof:name":"Metalfar Prodotti Industriali S.p.a.",
    "wof:placetype":"venue"
},
  "geometry": {"coordinates":[9.3900709152,45.8529815674],"type":"Point"}
}