{
  "type": "Feature",
  "properties": {
    "iso:country":"IT",
    "sg:address":"10128 Torino",
    "sg:city":"Torino",
    "sg:orig_category":"Internet, Telematica E Audiotex - Servizi",
    "sg:phone":"+39 011 548920",
    "sg:postcode":"10128",
    "sg:province":"Torino",
    "wof:name":"A.g.a.s.",
    "wof:placetype":"venue"
},
  "geometry": {"coordinates":[7.670135,45.058353],"type":"Point"}
}