{
  "type": "Feature",
  "properties": {
    "iso:country":"IT",
    "sg:address":"Via Alla Stazione 22060 Carimate",
    "sg:city":"Carimate",
    "sg:classifiers":[
        {
            "category":"Home & Garden",
            "subcategory":"Home Furnishings",
            "type":"Retail Goods"
        }
    ],
    "sg:phone":"+39 39031791256",
    "sg:postcode":"22060",
    "sg:province":"Como",
    "sg:tags":[
        "household"
    ],
    "wof:name":"Valente Srl",
    "wof:placetype":"venue"
},
  "geometry": {"coordinates":[9.109696,45.699116],"type":"Point"}
}