{
  "type": "Feature",
  "properties": {
    "iso:country":"IT",
    "sg:address":"23, Corso Cervi Fratelli 10093 Collegno",
    "sg:city":"Collegno",
    "sg:classifiers":[
        {
            "category":"Bars & Pubs",
            "subcategory":"Nightclub",
            "type":"Food & Drink"
        }
    ],
    "sg:phone":"+39 011 403 1161",
    "sg:postcode":"10093",
    "sg:province":"Torino",
    "sg:tags":[
        "cake",
        "bread"
    ],
    "wof:name":"Grissitalia S.r.l.",
    "wof:placetype":"venue"
},
  "geometry": {"coordinates":[7.587419,45.076866],"type":"Point"}
}