{
  "type": "Feature",
  "properties": {
    "iso:country":"IT",
    "sg:address":"20020 Arconate",
    "sg:city":"Arconate",
    "sg:orig_category":"Forniture Per Attivita' Industriali",
    "sg:phone":"+39 0331 461433",
    "sg:postcode":"20020",
    "sg:province":"Milano",
    "wof:name":"Spazzolificio Bustese",
    "wof:placetype":"venue"
},
  "geometry": {"coordinates":[8.9063396454,45.543548584],"type":"Point"}
}