{
  "type": "Feature",
  "properties": {
    "addr:full":"11020 Champdepraz Champdepraz Aosta 11020",
    "addr:housenumber":"11020",
    "addr:postcode":"11020",
    "addr:street":"Champdepraz Champdepraz Aosta",
    "iso:country":"IT",
    "sg:address":"11020 Champdepraz",
    "sg:city":"Champdepraz",
    "sg:orig_category":"Pompe. Elettrotecnica Industriale, Prodotti E Apparecchiature",
    "sg:phone":"+39 0125 960423",
    "sg:postcode":"11020",
    "sg:province":"Aosta",
    "wof:name":"Pinet Delio",
    "wof:placetype":"venue"
},
  "geometry": {"coordinates":[7.6656150818,45.6859779358],"type":"Point"}
}