{
  "type": "Feature",
  "properties": {
    "addr:full":"39011 Lana Lana Bolzano/Bozen 39011",
    "addr:postcode":"39011;39011",
    "iso:country":"IT",
    "sg:address":"39011 Lana",
    "sg:city":"Lana",
    "sg:orig_category":"Frigotecnica, Apparecchiature E Servizi. Forniture Alle Strutture Ricettive",
    "sg:phone":"+39 0473 561988",
    "sg:postcode":"39011",
    "sg:province":"Bolzano/Bozen",
    "sg:website":"http://www.neutec.it",
    "wof:name":"Neutec Srl",
    "wof:placetype":"venue"
},
  "geometry": {"coordinates":[11.35800457,46.4967155457],"type":"Point"}
}