{
  "type": "Feature",
  "properties": {
    "iso:country":"IT",
    "sg:address":"5, Via S. Francesco D'assisi 22100 Como",
    "sg:city":"Como",
    "sg:classifiers":[
        {
            "category":"Wholesale",
            "subcategory":"Drugs",
            "type":"Manufacturing & Wholesale Goods"
        }
    ],
    "sg:phone":"+39 39031524095",
    "sg:postcode":"22100",
    "sg:province":"Como",
    "sg:tags":[
        "chemical",
        "pharmaceutical"
    ],
    "wof:name":"S.a.l.a.r.s. (s.p.a.)",
    "wof:placetype":"venue"
},
  "geometry": {"coordinates":[9.085456,45.811966],"type":"Point"}
}