{
  "type": "Feature",
  "properties": {
    "iso:country":"IT",
    "sg:address":"Via Libbia 61 52030 Chiassa Superiore",
    "sg:classifiers":[
        {
            "category":"Professional",
            "subcategory":"Detective & Security Services",
            "type":"Services"
        }
    ],
    "sg:phone":"+39 0575 3171",
    "sg:postcode":"52030",
    "sg:province":"Arezzo",
    "sg:tags":[
        "transducer"
    ],
    "sg:website":"www.trafo.it",
    "wof:name":"Tesar Srl",
    "wof:placetype":"venue"
},
  "geometry": {"coordinates":[11.863062,43.471203],"type":"Point"}
}