{
  "type": "Feature",
  "properties": {
    "addr:full":"47, Viale Colonna Vittoria 65127 Pescara Pescara Pescara 65127",
    "addr:housenumber":"47",
    "addr:postcode":"65127;65127",
    "addr:street":"Viale Colonna Vittoria",
    "iso:country":"IT",
    "sg:address":"47, Viale Colonna Vittoria 65127 Pescara",
    "sg:city":"Pescara",
    "sg:classifiers":[
        {
            "category":"Shopping",
            "subcategory":"Crafts & Fabrics",
            "type":"Retail Goods"
        }
    ],
    "sg:phone":"+39 39085690449",
    "sg:postcode":"65127",
    "sg:province":"Pescara",
    "wof:name":"Suaria Domenico Srl",
    "wof:placetype":"venue"
},
  "geometry": {"coordinates":[14.214094162,42.4648246765],"type":"Point"}
}