{
  "type": "Feature",
  "properties": {
    "addr:full":"20040 Cavenago Di Brianza Cavenago di Brianza Milano 20040",
    "addr:postcode":"20040;20040",
    "iso:country":"IT",
    "sg:address":"20040 Cavenago Di Brianza",
    "sg:city":"Cavenago di Brianza",
    "sg:orig_category":"Analisi Chimiche, Industriali E Merceologiche",
    "sg:phone":"+39 02 9533 9204",
    "sg:postcode":"20040",
    "sg:province":"Milano",
    "sg:website":"http://www.qualitystandard.it/home.htm",
    "wof:name":"Logicway Srl",
    "wof:placetype":"venue"
},
  "geometry": {"coordinates":[9.415507,45.579903],"type":"Point"}
}