{
  "type": "Feature",
  "properties": {
    "iso:country":"IT",
    "sg:address":"80143 Napoli",
    "sg:city":"Napoli",
    "sg:orig_category":"Servizi Al Turismo. Centri Di Estetica E Cosmesi E Servizi",
    "sg:phone":"+39 081 750 1618",
    "sg:postcode":"80143",
    "sg:province":"Napoli",
    "wof:name":"Insurance Service Srl",
    "wof:placetype":"venue"
},
  "geometry": {"coordinates":[14.282045,40.856991],"type":"Point"}
}