{
  "type": "Feature",
  "properties": {
    "addr:full":"22, Via Antonio Meucci 30020 Noventa Di Piave Noventa di Piave Venezia 30020",
    "addr:postcode":"30020;30020",
    "addr:street":"Via Antonio Meucci",
    "iso:country":"IT",
    "sg:address":"22, Via Antonio Meucci 30020 Noventa Di Piave",
    "sg:city":"Noventa di Piave",
    "sg:classifiers":[
        {
            "category":"Professional",
            "subcategory":"Engineering",
            "type":"Services"
        }
    ],
    "sg:phone":"+39 0421 309511",
    "sg:postcode":"30020",
    "sg:province":"Venezia",
    "sg:tags":[
        "machine",
        "-",
        "mechanical"
    ],
    "wof:name":"Alstom T & D S.p.a.",
    "wof:placetype":"venue"
},
  "geometry": {"coordinates":[12.533585,45.6749],"type":"Point"}
}