{
  "type": "Feature",
  "properties": {
    "iso:country":"IT",
    "sg:address":"31, Via Astichello 36030 Montecchio Precalcino",
    "sg:city":"Montecchio Precalcino",
    "sg:classifiers":[
        {
            "category":"Shopping",
            "subcategory":"Clothing, Apparel, & Fashions",
            "type":"Retail Goods"
        }
    ],
    "sg:phone":"+39 0445 864520",
    "sg:postcode":"36030",
    "sg:province":"Vicenza",
    "sg:tags":[
        "clothes"
    ],
    "wof:name":"Onelia (s.p.a.)",
    "wof:placetype":"venue"
},
  "geometry": {"coordinates":[11.565047,45.66201],"type":"Point"}
}