{
  "type": "Feature",
  "properties": {
    "addr:full":"52025 Montevarchi Montevarchi Arezzo 52025",
    "addr:postcode":"52025;52025",
    "iso:country":"IT",
    "sg:address":"52025 Montevarchi",
    "sg:city":"Montevarchi",
    "sg:orig_category":"Enoteche E Vendita Vini",
    "sg:phone":"+39 055 983372",
    "sg:postcode":"52025",
    "sg:province":"Arezzo",
    "sg:website":"http://www.frasca.it",
    "wof:name":"Enoteca Fiaschetteria Da I' Frasca",
    "wof:placetype":"venue"
},
  "geometry": {"coordinates":[11.8759508133,43.4736709595],"type":"Point"}
}