{
  "type": "Feature",
  "properties": {
    "iso:country":"IT",
    "sg:address":"33058 San Giorgio Di Nogaro",
    "sg:city":"San Giorgio di Nogaro",
    "sg:orig_category":"Servizi Al Turismo. Servizi Ausiliari Per Il Trasporto",
    "sg:phone":"+39 0431 621362",
    "sg:postcode":"33058",
    "sg:province":"Udine",
    "wof:name":"Friultrans Spa",
    "wof:placetype":"venue"
},
  "geometry": {"coordinates":[13.202553,45.832108],"type":"Point"}
}