{
  "type": "Feature",
  "properties": {
    "iso:country":"IT",
    "sg:address":"32020 Limana",
    "sg:city":"Limana",
    "sg:classifiers":[
        {
            "category":"Manufacturing",
            "subcategory":"Tools & Machinery",
            "type":"Manufacturing & Wholesale Goods"
        }
    ],
    "sg:phone":"+39 0437 967422",
    "sg:postcode":"32020",
    "sg:province":"Belluno",
    "sg:tags":[
        "machining",
        "mechanical"
    ],
    "wof:name":"Tormen Guerrino & C. Snc",
    "wof:placetype":"venue"
},
  "geometry": {"coordinates":[12.156329,46.102066],"type":"Point"}
}