{
  "type": "Feature",
  "properties": {
    "iso:country":"IT",
    "sg:address":"35020 Brugine",
    "sg:city":"Brugine",
    "sg:orig_category":"Arredo Bagno Ed Idrosanitari. Forniture Alle Strutture Ricettive. Apparecchi, Attrezzature E Forniture Per Centri Estetici",
    "sg:phone":"+39 049 973 0456",
    "sg:postcode":"35020",
    "sg:province":"Padova",
    "wof:name":"Ci.se Elettronica Industriale Srl",
    "wof:placetype":"venue"
},
  "geometry": {"coordinates":[11.999573,45.308193],"type":"Point"}
}