{
  "type": "Feature",
  "properties": {
    "iso:country":"IT",
    "sg:address":"90135 Palermo",
    "sg:city":"Palermo",
    "sg:orig_category":"Ricerca, Selezione E Formazione Del Personale. Pubblica Amministrazione",
    "sg:phone":"+39 091 676 5642",
    "sg:postcode":"90135",
    "sg:province":"Palermo",
    "wof:name":"Ente Nazionale Sordomuti",
    "wof:placetype":"venue"
},
  "geometry": {"coordinates":[13.327372,38.12463],"type":"Point"}
}