{
  "type": "Feature",
  "properties": {
    "addr:full":"10144 Torino Torino Torino 10144",
    "addr:postcode":"10144;10144",
    "iso:country":"IT",
    "sg:address":"10144 Torino",
    "sg:city":"Torino",
    "sg:orig_category":"Arredo Camera Letto E Complementi. Servizi E Lavori Per Arredamento E Industria Del Legno",
    "sg:phone":"+39 011 480543",
    "sg:postcode":"10144",
    "sg:province":"Torino",
    "wof:name":"Colombino Mario",
    "wof:placetype":"venue"
},
  "geometry": {"coordinates":[7.546876,45.000244],"type":"Point"}
}