{
  "type": "Feature",
  "properties": {
    "iso:country":"IT",
    "sg:address":"Collecchio, Pr",
    "sg:classifiers":[
        {
            "category":"Banks & Credit Unions",
            "subcategory":"Bank",
            "type":"Services"
        }
    ],
    "wof:name":"Ge Po Spa",
    "wof:placetype":"venue"
},
  "geometry": {"coordinates":[10.216693,44.751808],"type":"Point"}
}