{
  "type": "Feature",
  "properties": {
    "iso:country":"IT",
    "sg:address":"90127 Palermo",
    "sg:city":"Palermo",
    "sg:orig_category":"Prodotti Di Base E Forniture Per Industria Alimentare E Bevande. Forniture Per Attivita' Commerciali Ed Artigianali",
    "sg:phone":"+39 091 616 4463",
    "sg:postcode":"90127",
    "sg:province":"Palermo",
    "wof:name":"Marsala Mariano",
    "wof:placetype":"venue"
},
  "geometry": {"coordinates":[13.3647947311,38.1027488708],"type":"Point"}
}