{
  "type": "Feature",
  "properties": {
    "iso:country":"IT",
    "sg:address":"20030 Senago",
    "sg:city":"Senago",
    "sg:orig_category":"Professionisti - Studi E Servizi Ed Associazioni Di Interesse Aziendale. Associazioni Ed Organismi Di Interesse Pubblico",
    "sg:phone":"+39 02 9948 2016",
    "sg:postcode":"20030",
    "sg:province":"Milano",
    "wof:name":"Partito Democratico Della Sinistra",
    "wof:placetype":"venue"
},
  "geometry": {"coordinates":[9.1174783707,45.5467453003],"type":"Point"}
}