{
  "type": "Feature",
  "properties": {
    "iso:country":"IT",
    "sg:address":"Via Padule 50018 Scandicci",
    "sg:city":"Scandicci",
    "sg:classifiers":[
        {
            "category":"Professional",
            "subcategory":"Engineering",
            "type":"Services"
        }
    ],
    "sg:phone":"+39 39055721060",
    "sg:postcode":"50018",
    "sg:province":"Firenze",
    "sg:tags":[
        "machine",
        "-",
        "mechanical"
    ],
    "wof:name":"Spotti Luigi S.n.c. Luigi",
    "wof:placetype":"venue"
},
  "geometry": {"coordinates":[11.162244,43.76189],"type":"Point"}
}