{
  "type": "Feature",
  "properties": {
    "addr:full":"Via S. Lorenzo 25 36010 Carre' Vicenza 36010",
    "addr:housenumber":"25",
    "addr:postcode":"36010;36010",
    "addr:street":"Via S. Lorenzo;Carre ' Vicenza",
    "iso:country":"IT",
    "sg:address":"Via S. Lorenzo 25 36010 Carre'",
    "sg:classifiers":[
        {
            "category":"Home & Garden",
            "subcategory":"Hardware",
            "type":"Retail Goods"
        }
    ],
    "sg:phone":"+39 0445 382814",
    "sg:postcode":"36010",
    "sg:province":"Vicenza",
    "sg:tags":[
        "component",
        "electronic"
    ],
    "sg:website":"www.lika.it",
    "wof:name":"Elettroinic Snc",
    "wof:placetype":"venue"
},
  "geometry": {"coordinates":[11.540307,45.545906],"type":"Point"}
}