{
  "type": "Feature",
  "properties": {
    "iso:country":"IT",
    "sg:address":"24, Via Zilie Superiori 25012 Calvisano",
    "sg:city":"Calvisano",
    "sg:classifiers":[
        {
            "category":"Farming",
            "subcategory":"Livestock Farm",
            "type":"Manufacturing & Wholesale Goods"
        }
    ],
    "sg:phone":"+39 030 996 8634",
    "sg:postcode":"25012",
    "sg:province":"Brescia",
    "sg:tags":[
        "agriculture"
    ],
    "wof:name":"Zoogamma Spa",
    "wof:placetype":"venue"
},
  "geometry": {"coordinates":[10.330802,45.353073],"type":"Point"}
}