{
  "type": "Feature",
  "properties": {
    "addr:full":"Via Barletta Strada Statale 16 70059 Trani Trani Bari 70059",
    "addr:housenumber":"16",
    "addr:postcode":"70059;70059",
    "addr:street":"Via Barletta Strada Statale",
    "iso:country":"IT",
    "sg:address":"Via Barletta Strada Statale 16 70059 Trani",
    "sg:city":"Trani",
    "sg:orig_category":"Soles, Heels",
    "sg:phone":"+39 0883 586758",
    "sg:postcode":"70059",
    "sg:province":"Bari",
    "sg:website":"www.vanplast.it",
    "wof:name":"Vanplast Srl",
    "wof:placetype":"venue"
},
  "geometry": {"coordinates":[16.869291,41.126053],"type":"Point"}
}