{
  "type": "Feature",
  "properties": {
    "addr:full":"Via Bellini 91 51031 Agliana Agliana Pistoia 51031",
    "addr:housenumber":"91",
    "addr:postcode":"51031;51031",
    "addr:street":"Via Bellini",
    "iso:country":"IT",
    "sg:address":"Via Bellini 91 51031 Agliana",
    "sg:city":"Agliana",
    "sg:orig_category":"Ladies' Knitwear",
    "sg:phone":"+39 0574 711331",
    "sg:postcode":"51031",
    "sg:province":"Pistoia",
    "sg:website":"www.beby.it",
    "wof:name":"Maglificio Beby Srl",
    "wof:placetype":"venue"
},
  "geometry": {"coordinates":[11.002586,43.907856],"type":"Point"}
}