{
  "type": "Feature",
  "properties": {
    "iso:country":"IT",
    "sg:address":"1, Contrada Lazzare 83040 Guardia Lombardi",
    "sg:city":"Guardia Lombardi",
    "sg:classifiers":[
        {
            "category":"Farming",
            "subcategory":"Livestock Farm",
            "type":"Manufacturing & Wholesale Goods"
        }
    ],
    "sg:phone":"+39 39082741689",
    "sg:postcode":"83040",
    "sg:province":"Avellino",
    "sg:tags":[
        "agriculture"
    ],
    "wof:name":"Vivaio Giosue' Bianco",
    "wof:placetype":"venue"
},
  "geometry": {"coordinates":[15.248261,41.011993],"type":"Point"}
}