{
  "type": "Feature",
  "properties": {
    "iso:country":"IT",
    "sg:address":"6, Via Leopardi 20091 Bresso",
    "sg:city":"Bresso",
    "sg:classifiers":[
        {
            "category":"Shopping",
            "subcategory":"Computers & Home Electronics",
            "type":"Retail Goods"
        }
    ],
    "sg:phone":"+39 39026101264",
    "sg:postcode":"20091",
    "sg:province":"Milano",
    "sg:tags":[
        "electronic",
        "electrical",
        "equipment"
    ],
    "wof:name":"C.e.b. (s.r.l.)",
    "wof:placetype":"venue"
},
  "geometry": {"coordinates":[9.199387,45.530354],"type":"Point"}
}