{
  "type": "Feature",
  "properties": {
    "addr:full":"84015 Nocera Superiore Nocera Superiore Salerno 84015",
    "addr:postcode":"84015;84015",
    "iso:country":"IT",
    "sg:address":"84015 Nocera Superiore",
    "sg:city":"Nocera Superiore",
    "sg:orig_category":"Prodotti Vari In Metallo. Articoli Per Imballaggio E Confezionamento",
    "sg:phone":"+39 081 935586",
    "sg:postcode":"84015",
    "sg:province":"Salerno",
    "wof:name":"Carucci Antonio",
    "wof:placetype":"venue"
},
  "geometry": {"coordinates":[14.6762733459,40.7340698242],"type":"Point"}
}