{
  "type": "Feature",
  "properties": {
    "iso:country":"IT",
    "sg:address":"52100 Arezzo",
    "sg:city":"Arezzo",
    "sg:orig_category":"Elettronica Professionale E Di Consumo. Musica. Accessori Dei Mezzi Di Trasporto",
    "sg:phone":"+39 0575 323280",
    "sg:postcode":"52100",
    "sg:province":"Arezzo",
    "wof:name":"Centro Audio Video Di Micheli Marco",
    "wof:placetype":"venue"
},
  "geometry": {"coordinates":[11.715717,43.539738],"type":"Point"}
}