{
  "type": "Feature",
  "properties": {
    "iso:country":"IT",
    "sg:address":"20, Via Sevardi Roberto 42100 Reggio Emilia",
    "sg:classifiers":[
        {
            "category":"Manufacturing",
            "subcategory":"Metals",
            "type":"Manufacturing & Wholesale Goods"
        }
    ],
    "sg:phone":"+39 0522 514757",
    "sg:postcode":"42100",
    "sg:province":"Reggio Nell'Emilia",
    "sg:tags":[
        "metallurgy",
        "metalworking"
    ],
    "wof:name":"Ferval S.r.l.",
    "wof:placetype":"venue"
},
  "geometry": {"coordinates":[10.659157753,44.7399101257],"type":"Point"}
}