{
  "type": "Feature",
  "properties": {
    "iso:country":"IT",
    "sg:address":"37012 Bussolengo",
    "sg:city":"Bussolengo",
    "sg:orig_category":"Marmo, Pietre Ed Affini",
    "sg:phone":"+39 045 150091",
    "sg:postcode":"37012",
    "sg:province":"Verona",
    "wof:name":"Marmi Perusi Srl",
    "wof:placetype":"venue"
},
  "geometry": {"coordinates":[10.860432,45.477245],"type":"Point"}
}