{
  "type": "Feature",
  "properties": {
    "addr:full":"78, Via Colombo Cristoforo 31015 Conegliano Conegliano Treviso 31015",
    "addr:postcode":"31015;31015",
    "addr:street":"Via Colombo Cristoforo",
    "iso:country":"IT",
    "sg:address":"78, Via Colombo Cristoforo 31015 Conegliano",
    "sg:city":"Conegliano",
    "sg:classifiers":[
        {
            "category":"Professional",
            "subcategory":"Business Services",
            "type":"Services"
        }
    ],
    "sg:phone":"+39 39043833165",
    "sg:postcode":"31015",
    "sg:province":"Treviso",
    "sg:tags":[
        "advice"
    ],
    "wof:name":"Ge.i.co.ve. Zoppas (s.r.l.)",
    "wof:placetype":"venue"
},
  "geometry": {"coordinates":[12.242072,45.666286],"type":"Point"}
}