{
  "type": "Feature",
  "properties": {
    "addr:full":"Via Trento 7; Foggia; 71100 Foggia Foggia 71100",
    "addr:housenumber":"7",
    "addr:postcode":"71100;71100",
    "addr:street":"Via Trento",
    "iso:country":"IT",
    "sg:address":"Via Trento 7; Foggia; 71100",
    "sg:city":"Foggia",
    "sg:classifiers":[
        {
            "category":"Banks & Credit Unions",
            "subcategory":"Bank",
            "type":"Services"
        }
    ],
    "sg:phone":"+39 0881 8941",
    "sg:postcode":"71100",
    "sg:province":"Foggia",
    "wof:name":"Cassa Di Risparmio Di Puglia",
    "wof:placetype":"venue"
},
  "geometry": {"coordinates":[15.551675,41.464195],"type":"Point"}
}