{
  "type": "Feature",
  "properties": {
    "iso:country":"IT",
    "sg:address":"Via Tarona 8 43010 Fontevivo",
    "sg:city":"Fontevivo",
    "sg:classifiers":[
        {
            "category":"Manufacturing",
            "subcategory":"Rubber & Plastics",
            "type":"Manufacturing & Wholesale Goods"
        }
    ],
    "sg:phone":"+39 0521 619830",
    "sg:postcode":"43010",
    "sg:province":"Parma",
    "sg:tags":[
        "wear-resistant"
    ],
    "wof:name":"Eurorubber Spa",
    "wof:placetype":"venue"
},
  "geometry": {"coordinates":[10.221577,44.828091],"type":"Point"}
}