{
  "type": "Feature",
  "properties": {
    "addr:full":"09045 Quartu S.elena Cagliari 09045",
    "addr:postcode":"09045;09045",
    "addr:street":"S.Elena Cagliari",
    "iso:country":"IT",
    "sg:address":"09045 Quartu S.elena",
    "sg:orig_category":"Forniture Per Attivita' Commerciali Ed Artigianali. Pubblicita', Marketing E Comunicazione",
    "sg:phone":"+39 070 863 0092",
    "sg:postcode":"09045",
    "sg:province":"Cagliari",
    "sg:website":"http://www.cpk.it",
    "wof:name":"C.p.k. Comunicazioni Pubbliche Srl",
    "wof:placetype":"venue"
},
  "geometry": {"coordinates":[9.1976585388,39.2398757935],"type":"Point"}
}