{
  "type": "Feature",
  "properties": {
    "iso:country":"IT",
    "sg:address":"37051 Bovolone",
    "sg:city":"Bovolone",
    "sg:orig_category":"Non-classified Establishments",
    "sg:phone":"+39 045 694 9122",
    "sg:postcode":"37051",
    "sg:province":"Verona",
    "wof:name":"Battistella Franco & C. (s.n.c.)",
    "wof:placetype":"venue"
},
  "geometry": {"coordinates":[10.980285,45.415653],"type":"Point"}
}