{
  "type": "Feature",
  "properties": {
    "iso:country":"IT",
    "sg:address":"50018 Scandicci",
    "sg:city":"Scandicci",
    "sg:orig_category":"Macchine, Impianti Ed Attrezzature Per Abbigliamento E Pelletterie",
    "sg:phone":"+39 055 72911",
    "sg:postcode":"50018",
    "sg:province":"Firenze",
    "wof:name":"Matec Spa",
    "wof:placetype":"venue"
},
  "geometry": {"coordinates":[11.157829,43.766178],"type":"Point"}
}