{
  "type": "Feature",
  "properties": {
    "addr:full":"53, Via Roma 55027 Gallicano Gallicano Lucca 55027",
    "addr:postcode":"55027;55027",
    "addr:street":"Via Roma",
    "iso:country":"IT",
    "sg:address":"53, Via Roma 55027 Gallicano",
    "sg:city":"Gallicano",
    "sg:classifiers":[
        {
            "category":"Food & Beverages",
            "subcategory":"Groceries & Convenience Stores",
            "type":"Retail Goods"
        }
    ],
    "sg:phone":"+39 0583 730303",
    "sg:postcode":"55027",
    "sg:province":"Lucca",
    "sg:tags":[
        "product",
        "related"
    ],
    "wof:name":"Salumi Della Garfagnana Srl",
    "wof:placetype":"venue"
},
  "geometry": {"coordinates":[10.5227375031,44.0606842041],"type":"Point"}
}