{
  "type": "Feature",
  "properties": {
    "iso:country":"IT",
    "sg:address":"79, Strada Vercelli 13038 Tricerro",
    "sg:city":"Tricerro",
    "sg:classifiers":[
        {
            "category":"Wholesale",
            "subcategory":"Drugs",
            "type":"Manufacturing & Wholesale Goods"
        }
    ],
    "sg:phone":"+39 0161 808601",
    "sg:postcode":"13038",
    "sg:province":"Vercelli",
    "sg:tags":[
        "chemical",
        "pharmaceutical"
    ],
    "wof:name":"Zeta Esse Ti Srl",
    "wof:placetype":"venue"
},
  "geometry": {"coordinates":[8.362558,45.273075],"type":"Point"}
}