{
  "type": "Feature",
  "properties": {
    "addr:full":"21, Via Altivole 31031 Caerano Di San Marco Caerano di San Marco Treviso 31031",
    "addr:postcode":"31031;31031",
    "addr:street":"Via Altivole",
    "iso:country":"IT",
    "sg:address":"21, Via Altivole 31031 Caerano Di San Marco",
    "sg:city":"Caerano di San Marco",
    "sg:classifiers":[
        {
            "category":"Shopping",
            "subcategory":"Crafts & Fabrics",
            "type":"Retail Goods"
        }
    ],
    "sg:phone":"+39 0423 650343",
    "sg:postcode":"31031",
    "sg:province":"Treviso",
    "wof:name":"Stringhificio Gallina Mario (s.n.c.)",
    "wof:placetype":"venue"
},
  "geometry": {"coordinates":[11.9869260788,45.7588233948],"type":"Point"}
}