{
  "type": "Feature",
  "properties": {
    "addr:full":"20021 Bollate Bollate Milano 20021",
    "addr:postcode":"20021;20021",
    "iso:country":"IT",
    "sg:address":"20021 Bollate",
    "sg:city":"Bollate",
    "sg:orig_category":"Forniture Per Uffici",
    "sg:phone":"+39 02 350 6435",
    "sg:postcode":"20021",
    "sg:province":"Milano",
    "wof:name":"Disegnarte Di Boniardi Pietro",
    "wof:placetype":"venue"
},
  "geometry": {"coordinates":[9.1208791733,45.5402030945],"type":"Point"}
}