{
  "type": "Feature",
  "properties": {
    "addr:full":"Via F. Acri, 12; Bologna; 40126 Bologna Bologna 40126",
    "addr:housenumber":"12",
    "addr:postcode":"40126;40126",
    "addr:street":"Via F. Acri",
    "iso:country":"IT",
    "sg:address":"Via F. Acri, 12; Bologna; 40126",
    "sg:city":"Bologna",
    "sg:classifiers":[
        {
            "category":"Banks & Credit Unions",
            "subcategory":"Bank",
            "type":"Services"
        }
    ],
    "sg:phone":"+39 051 265919",
    "sg:postcode":"40126",
    "sg:province":"Bologna",
    "wof:name":"Banca Del Monte",
    "wof:placetype":"venue"
},
  "geometry": {"coordinates":[11.352839,44.495747],"type":"Point"}
}