{
  "type": "Feature",
  "properties": {
    "iso:country":"IT",
    "sg:address":"35020 Correzzola",
    "sg:city":"Correzzola",
    "sg:orig_category":"Campeggio",
    "sg:phone":"+39 049 581 9297",
    "sg:postcode":"35020",
    "sg:province":"Padova",
    "wof:name":"Bica (s.p.a.)",
    "wof:placetype":"venue"
},
  "geometry": {"coordinates":[12.068759,45.236279],"type":"Point"}
}