{
  "type": "Feature",
  "properties": {
    "iso:country":"IT",
    "sg:address":"14, Via Saluzzo 12030 Casalgrasso",
    "sg:city":"Casalgrasso",
    "sg:classifiers":[
        {
            "category":"Shopping",
            "subcategory":"Crafts & Fabrics",
            "type":"Retail Goods"
        }
    ],
    "sg:phone":"+39 39011975880",
    "sg:postcode":"12030",
    "sg:province":"Cuneo",
    "sg:tags":[
        "ceramic"
    ],
    "wof:name":"C4 (s.r.l.)",
    "wof:placetype":"venue"
},
  "geometry": {"coordinates":[7.625476,44.817738],"type":"Point"}
}