{
  "type": "Feature",
  "properties": {
    "addr:full":"130, Via Roma 10060 Roletto Roletto Torino 10060",
    "addr:housenumber":"130",
    "addr:postcode":"10060;10060",
    "addr:street":"Via Roma",
    "iso:country":"IT",
    "sg:address":"130, Via Roma 10060 Roletto",
    "sg:city":"Roletto",
    "sg:classifiers":[
        {
            "category":"Manufacturing",
            "subcategory":"Printing",
            "type":"Manufacturing & Wholesale Goods"
        }
    ],
    "sg:phone":"+39 0121 542744",
    "sg:postcode":"10060",
    "sg:province":"Torino",
    "sg:tags":[
        "publishing"
    ],
    "wof:name":"Con Pak S.p.a.",
    "wof:placetype":"venue"
},
  "geometry": {"coordinates":[7.3460884094,44.917427063],"type":"Point"}
}