{
  "type": "Feature",
  "properties": {
    "iso:country":"IT",
    "sg:address":"16047 Moconesi",
    "sg:city":"Gattorna",
    "sg:classifiers":[
        {
            "category":"Banks & Credit Unions",
            "subcategory":"Atm",
            "type":"Services"
        }
    ],
    "sg:phone":"+39 0185 934410",
    "sg:postcode":"16047",
    "sg:province":"Genova",
    "sg:tags":[
        "shopping",
        "gift",
        "business",
        "leisure",
        "supplies",
        "article"
    ],
    "wof:name":"Basso Luigi Giocattoli Di Basso Massimiliano",
    "wof:placetype":"venue"
},
  "geometry": {"coordinates":[9.18735,44.430611],"type":"Point"}
}