{
  "type": "Feature",
  "properties": {
    "addr:full":"40068 S. Lazzaro Di Savena Bologna 40068",
    "addr:housenumber":"40068",
    "addr:postcode":"40068",
    "addr:street":"S. Lazzaro Di Savena",
    "iso:country":"IT",
    "sg:address":"40068 S. Lazzaro Di Savena",
    "sg:orig_category":"Fonderie Ghisa",
    "sg:phone":"+39 051 462115",
    "sg:postcode":"40068",
    "sg:province":"Bologna",
    "wof:name":"Accorsi Spa",
    "wof:placetype":"venue"
},
  "geometry": {"coordinates":[11.4163007736,44.4766731262],"type":"Point"}
}