{
  "type": "Feature",
  "properties": {
    "iso:country":"IT",
    "sg:address":"09124 Cagliari",
    "sg:city":"Cagliari",
    "sg:orig_category":"Enti Turistici",
    "sg:phone":"+39 070 60231",
    "sg:postcode":"09124",
    "sg:province":"Cagliari",
    "sg:website":"http://www.esit.net.",
    "wof:name":"E.s.i.t.",
    "wof:placetype":"venue"
},
  "geometry": {"coordinates":[9.113797,39.218624],"type":"Point"}
}