{
  "type": "Feature",
  "properties": {
    "addr:full":"20016 Pero Pero Milano 20016",
    "addr:postcode":"20016;20016",
    "iso:country":"IT",
    "sg:address":"20016 Pero",
    "sg:city":"Pero",
    "sg:orig_category":"Pubblicita' Esterna",
    "sg:phone":"+39 02 353 9758",
    "sg:postcode":"20016",
    "sg:province":"Milano",
    "wof:name":"Danisi Gianni",
    "wof:placetype":"venue"
},
  "geometry": {"coordinates":[9.0839853287,45.5055961609],"type":"Point"}
}