{
  "type": "Feature",
  "properties": {
    "addr:full":"110, Borgo S. Anna 12040 Monteu Roero Monteu Roero Cuneo 12040",
    "addr:housenumber":"110",
    "addr:postcode":"12040;12040",
    "addr:street":"Borgo S. Anna",
    "iso:country":"IT",
    "sg:address":"110, Borgo S. Anna 12040 Monteu Roero",
    "sg:city":"Monteu Roero",
    "sg:classifiers":[
        {
            "category":"Manufacturing",
            "subcategory":"Metals",
            "type":"Manufacturing & Wholesale Goods"
        }
    ],
    "sg:phone":"+39 0173 979517",
    "sg:postcode":"12040",
    "sg:province":"Cuneo",
    "sg:tags":[
        "processing"
    ],
    "wof:name":"Roero Meccanica (s.r.l.)",
    "wof:placetype":"venue"
},
  "geometry": {"coordinates":[7.5471105576,44.38879776],"type":"Point"}
}