{
  "type": "Feature",
  "properties": {
    "addr:full":"20037 Paderno Dugnano Paderno Dugnano Milano 20037",
    "addr:postcode":"20037;20037",
    "iso:country":"IT",
    "sg:address":"20037 Paderno Dugnano",
    "sg:city":"Paderno Dugnano",
    "sg:orig_category":"Porte",
    "sg:phone":"+39 02 918 2250",
    "sg:postcode":"20037",
    "sg:province":"Milano",
    "wof:name":"Lavic Sas Di Tacca M.",
    "wof:placetype":"venue"
},
  "geometry": {"coordinates":[9.1823253632,45.5597610474],"type":"Point"}
}