{
  "type": "Feature",
  "properties": {
    "iso:country":"IT",
    "sg:address":"40055 Castenaso",
    "sg:city":"Castenaso",
    "sg:orig_category":"Prodotti Alimentari",
    "sg:phone":"+39 051 780785",
    "sg:postcode":"40055",
    "sg:province":"Bologna",
    "wof:name":"P.f.l. Service Srl",
    "wof:placetype":"venue"
},
  "geometry": {"coordinates":[11.4364595413,44.5011062622],"type":"Point"}
}