{
  "type": "Feature",
  "properties": {
    "addr:full":"1, Via Delle Valli 20042 Albiate Albiate Milano 20042",
    "addr:postcode":"20042;20042",
    "addr:street":"Via Delle Valli",
    "iso:country":"IT",
    "sg:address":"1, Via Delle Valli 20042 Albiate",
    "sg:city":"Albiate",
    "sg:classifiers":[
        {
            "category":"Manufacturing",
            "subcategory":"Rubber & Plastics",
            "type":"Manufacturing & Wholesale Goods"
        }
    ],
    "sg:phone":"+39 036 293 0845",
    "sg:postcode":"20042",
    "sg:province":"Milano",
    "wof:name":"Casting (s.r.l.)",
    "wof:placetype":"venue"
},
  "geometry": {"coordinates":[9.2405967712,45.6441268921],"type":"Point"}
}