{
  "type": "Feature",
  "properties": {
    "addr:full":"Via Venaprana S.n. 86170 Isernia Isernia Isernia 86170",
    "addr:postcode":"86170;86170",
    "addr:street":"Via Venaprana S.N.",
    "iso:country":"IT",
    "sg:address":"Via Venaprana S.n. 86170 Isernia",
    "sg:city":"Isernia",
    "sg:classifiers":[
        {
            "category":"Home & Garden",
            "subcategory":"Building Materials",
            "type":"Retail Goods"
        }
    ],
    "sg:phone":"+39 0865 3273",
    "sg:postcode":"86170",
    "sg:province":"Isernia",
    "sg:tags":[
        "slab",
        "marble"
    ],
    "wof:name":"Sici Marmi E Graniti Srl",
    "wof:placetype":"venue"
},
  "geometry": {"coordinates":[14.183997,41.562099],"type":"Point"}
}