{
  "type": "Feature",
  "properties": {
    "addr:full":"Loc Rivasso 9 12040 Priocca Priocca Cuneo 12040",
    "addr:housenumber":"9",
    "addr:postcode":"12040;12040",
    "addr:street":"Loc Rivasso",
    "iso:country":"IT",
    "sg:address":"Loc Rivasso 9 12040 Priocca",
    "sg:city":"Priocca",
    "sg:classifiers":[
        {
            "category":"Bakery",
            "type":"Food & Drink"
        }
    ],
    "sg:phone":"+39 0173 616355",
    "sg:postcode":"12040",
    "sg:province":"Cuneo",
    "sg:tags":[
        "fresh",
        "pastry",
        "bread"
    ],
    "wof:name":"Artesina S.p.a.",
    "wof:placetype":"venue"
},
  "geometry": {"coordinates":[7.5471105576,44.38879776],"type":"Point"}
}