{
  "type": "Feature",
  "properties": {
    "addr:full":"36100 Vicenza Vicenza Vicenza 36100",
    "addr:postcode":"36100;36100",
    "iso:country":"IT",
    "sg:address":"36100 Vicenza",
    "sg:city":"Vicenza",
    "sg:classifiers":[
        {
            "category":"Professional",
            "subcategory":"Business Services",
            "type":"Services"
        }
    ],
    "sg:phone":"+39 0444 512733",
    "sg:postcode":"36100",
    "sg:province":"Vicenza",
    "sg:tags":[
        "support",
        "companies",
        "events",
        "trade"
    ],
    "sg:website":"http://www.studiocentro.com/scquater.html",
    "wof:name":"Studio Centro Quater",
    "wof:placetype":"venue"
},
  "geometry": {"coordinates":[11.561045,45.53619],"type":"Point"}
}