{
  "type": "Feature",
  "properties": {
    "addr:full":"63020 Piane Di Falerone Falerone Ascoli Piceno 63020",
    "addr:postcode":"63020;63020",
    "iso:country":"IT",
    "sg:address":"63020 Piane Di Falerone",
    "sg:city":"Falerone",
    "sg:orig_category":"Non-classified Establishments",
    "sg:phone":"+39 0734 750068",
    "sg:postcode":"63020",
    "sg:province":"Ascoli Piceno",
    "wof:name":"Fermani Fratelli G. A. & C.",
    "wof:placetype":"venue"
},
  "geometry": {"coordinates":[13.496265,43.097706],"type":"Point"}
}