{
  "type": "Feature",
  "properties": {
    "addr:full":"62/d, V. Angelo Gitti 25060 Marcheno Marcheno Brescia 25060",
    "addr:housenumber":"62 / d",
    "addr:postcode":"25060;25060",
    "addr:street":"V. Angelo Gitti",
    "iso:country":"IT",
    "sg:address":"62/d, V. Angelo Gitti 25060 Marcheno",
    "sg:city":"Marcheno",
    "sg:classifiers":[
        {
            "category":"Manufacturing",
            "subcategory":"Metals",
            "type":"Manufacturing & Wholesale Goods"
        }
    ],
    "sg:phone":"+39 39030861448",
    "sg:postcode":"25060",
    "sg:province":"Brescia",
    "sg:tags":[
        "processing"
    ],
    "sg:website":"http://www.ripaincisioni.com",
    "wof:name":"Incisioni Meccaniche Ri.pa.",
    "wof:placetype":"venue"
},
  "geometry": {"coordinates":[10.2229576111,45.5398292542],"type":"Point"}
}