{
  "type": "Feature",
  "properties": {
    "iso:country":"IT",
    "sg:address":"30, Via Beato Angelico 53036 Poggibonsi",
    "sg:city":"Poggibonsi",
    "sg:classifiers":[
        {
            "category":"Building & Trades",
            "subcategory":"Construction",
            "type":"Services"
        }
    ],
    "sg:phone":"+39 0577 936400",
    "sg:postcode":"53036",
    "sg:province":"Siena",
    "sg:tags":[
        "work",
        "public"
    ],
    "wof:name":"Impresa Masini Srl",
    "wof:placetype":"venue"
},
  "geometry": {"coordinates":[11.143377,43.465534],"type":"Point"}
}