{
  "type": "Feature",
  "properties": {
    "iso:country":"IT",
    "sg:address":"180, Via Oriolo 27058 Voghera",
    "sg:city":"Oriolo",
    "sg:classifiers":[
        {
            "category":"Wholesale",
            "subcategory":"Machinery & Supplies",
            "type":"Manufacturing & Wholesale Goods"
        }
    ],
    "sg:phone":"+39 0383 344811",
    "sg:postcode":"27058",
    "sg:province":"Pavia",
    "sg:tags":[
        "-",
        "agriculture",
        "equipment"
    ],
    "wof:name":"Cifarelli S.p.a.",
    "wof:placetype":"venue"
},
  "geometry": {"coordinates":[9.023457,45.03223],"type":"Point"}
}