{
  "type": "Feature",
  "properties": {
    "iso:country":"IT",
    "sg:address":"2, Via Della Pineta 00048 Nettuno",
    "sg:city":"Nettuno",
    "sg:classifiers":[
        {
            "category":"Manufacturing",
            "subcategory":"Glass & Minerals",
            "type":"Manufacturing & Wholesale Goods"
        }
    ],
    "sg:phone":"+39 39069870793",
    "sg:postcode":"00048",
    "sg:province":"Roma",
    "wof:name":"Caru Aurelio & C Snc",
    "wof:placetype":"venue"
},
  "geometry": {"coordinates":[12.656981,41.506523],"type":"Point"}
}