{
  "type": "Feature",
  "properties": {
    "iso:country":"IT",
    "sg:address":"11012 Cogne",
    "sg:city":"Cogne",
    "sg:orig_category":"Servizi Per Lo Sport E Il Tempo Libero. Alberghi E Strutture Extra Alberghiere",
    "sg:phone":"+39 0165 74310",
    "sg:postcode":"11012",
    "sg:province":"Aosta",
    "wof:name":"Rifugio Sella V. Al Lauson - C.a.i.",
    "wof:placetype":"venue"
},
  "geometry": {"coordinates":[7.360291,45.572033],"type":"Point"}
}