{
  "type": "Feature",
  "properties": {
    "addr:full":"Via Palagetta 31 50013 Campi Bisenzio Campi Bisenzio Firenze 50013",
    "addr:housenumber":"31",
    "addr:postcode":"50013;50013",
    "addr:street":"Via Palagetta;Bisenzio",
    "iso:country":"IT",
    "sg:address":"Via Palagetta 31 50013 Campi Bisenzio",
    "sg:city":"Campi Bisenzio",
    "sg:orig_category":"Fibre Optics Construction Components",
    "sg:phone":"+39 055 898 6235",
    "sg:postcode":"50013",
    "sg:province":"Firenze",
    "sg:website":"www.dga.it",
    "wof:name":"Dga Fibre Ottiche Srl",
    "wof:placetype":"venue"
},
  "geometry": {"coordinates":[11.1437892914,43.8152160645],"type":"Point"}
}