{
  "type": "Feature",
  "properties": {
    "iso:country":"IT",
    "sg:address":"25035 Ospitaletto",
    "sg:city":"Ospitaletto",
    "sg:orig_category":"Pompe",
    "sg:phone":"+39 030 684 8075",
    "sg:postcode":"25035",
    "sg:province":"Brescia",
    "wof:name":"Baldini Srl",
    "wof:placetype":"venue"
},
  "geometry": {"coordinates":[10.1229124069,45.5512580872],"type":"Point"}
}