{
  "type": "Feature",
  "properties": {
    "iso:country":"IT",
    "sg:address":"00179 Roma",
    "sg:city":"Roma",
    "sg:orig_category":"Servizi Ausiliari Dei Mezzi Di Trasporto",
    "sg:phone":"+39 06 788 0710",
    "sg:postcode":"00179",
    "sg:province":"Roma",
    "wof:name":"Romana Recuperi Srl",
    "wof:placetype":"venue"
},
  "geometry": {"coordinates":[12.532521,41.858192],"type":"Point"}
}