{
  "type": "Feature",
  "properties": {
    "iso:country":"IT",
    "sg:address":"25086 Rezzato",
    "sg:city":"Rezzato",
    "sg:orig_category":"Tessuti Arredamento, Tende E Tappeti. Forniture Per Edilizia E Lavori Pubblici",
    "sg:phone":"+39 030 259 2311",
    "sg:postcode":"25086",
    "sg:province":"Brescia",
    "sg:website":"http://www.tempini.it",
    "wof:name":"Tempini Spa",
    "wof:placetype":"venue"
},
  "geometry": {"coordinates":[10.321738,45.50967],"type":"Point"}
}