{
  "type": "Feature",
  "properties": {
    "iso:country":"IT",
    "sg:address":"35040 Boara Pisani",
    "sg:city":"Boara Pisani",
    "sg:orig_category":"Bicchieri, Posate E Piatti In Carta E Plastica",
    "sg:phone":"+39 0425 48245",
    "sg:postcode":"35040",
    "sg:province":"Padova",
    "wof:name":"Borella Srl",
    "wof:placetype":"venue"
},
  "geometry": {"coordinates":[11.78087,45.109776],"type":"Point"}
}