{
  "type": "Feature",
  "properties": {
    "addr:full":"Km. 44, Via S.s. Valdichienti 62034 Muccia Muccia Macerata 62034",
    "addr:postcode":"62034;62034",
    "addr:street":"Km. 44 Via S.S. Valdichienti",
    "iso:country":"IT",
    "sg:address":"Km. 44, Via S.s. Valdichienti 62034 Muccia",
    "sg:city":"Muccia",
    "sg:classifiers":[
        {
            "category":"Food & Beverages",
            "subcategory":"Groceries & Convenience Stores",
            "type":"Retail Goods"
        }
    ],
    "sg:phone":"+39 0737 646355",
    "sg:postcode":"62034",
    "sg:province":"Macerata",
    "sg:tags":[
        "drink"
    ],
    "wof:name":"Bar Ristorante Varnelli",
    "wof:placetype":"venue"
},
  "geometry": {"coordinates":[13.456262,43.300747],"type":"Point"}
}