{
  "type": "Feature",
  "properties": {
    "addr:full":"Via Mazzini 182; Albino; 24021 Albino Bergamo 24021",
    "addr:housenumber":"182",
    "addr:postcode":"24021;24021",
    "addr:street":"Via Mazzini",
    "iso:country":"IT",
    "sg:address":"Via Mazzini 182; Albino; 24021",
    "sg:city":"Albino",
    "sg:classifiers":[
        {
            "category":"Banks & Credit Unions",
            "subcategory":"Bank",
            "type":"Services"
        }
    ],
    "sg:phone":"+39 035 755227",
    "sg:postcode":"24021",
    "sg:province":"Bergamo",
    "wof:name":"Istituto Bancario, San Paolo Di Torino Spa",
    "wof:placetype":"venue"
},
  "geometry": {"coordinates":[9.791871,45.757198],"type":"Point"}
}