{
  "type": "Feature",
  "properties": {
    "iso:country":"IT",
    "sg:address":"10093 Collegno",
    "sg:city":"Collegno",
    "sg:orig_category":"Arredo Cucina Ed Elettrodomestici. Elettrodomestici",
    "sg:phone":"+39 011 411 1282",
    "sg:postcode":"10093",
    "sg:province":"Torino",
    "sg:website":"http://www.arredamenti73.it",
    "wof:name":"Arredamenti 73 Srl",
    "wof:placetype":"venue"
},
  "geometry": {"coordinates":[7.59775,45.073463],"type":"Point"}
}