{
  "type": "Feature",
  "properties": {
    "addr:full":"00146 Roma Roma Roma 00146",
    "addr:postcode":"00146;00146",
    "iso:country":"IT",
    "sg:address":"00146 Roma",
    "sg:city":"Roma",
    "sg:orig_category":"Arredo Bagno Ed Idrosanitari. Complementi Di Arredamento. Vetro: Prodotti E Lavorazioni",
    "sg:phone":"+39 06 558 3342",
    "sg:postcode":"00146",
    "sg:province":"Roma",
    "wof:name":"Idea Bagno Di Maurizio Proietti",
    "wof:placetype":"venue"
},
  "geometry": {"coordinates":[12.472314,41.862247],"type":"Point"}
}