{
  "type": "Feature",
  "properties": {
    "addr:full":"12060 Bastia Mondov\u00ec Cuneo 12060",
    "addr:postcode":"12060;12060",
    "iso:country":"IT",
    "sg:address":"12060 Bastia Mondov\u00ec",
    "sg:orig_category":"Agricoltura, Orticoltura E Floricoltura",
    "sg:phone":"+39 0174 60174",
    "sg:postcode":"12060",
    "sg:province":"Cuneo",
    "wof:name":"Guido Chionetti - Vivai",
    "wof:placetype":"venue"
},
  "geometry": {"coordinates":[7.8956480026,44.44298172],"type":"Point"}
}