{
  "type": "Feature",
  "properties": {
    "addr:full":"35135 Padova Padova Padova 35135",
    "addr:postcode":"35135;35135",
    "iso:country":"IT",
    "sg:address":"35135 Padova",
    "sg:city":"Padova",
    "sg:orig_category":"Petroli, Gas E Combustibili",
    "sg:phone":"+39 049 864 3548",
    "sg:postcode":"35135",
    "sg:province":"Padova",
    "wof:name":"Giacometti Tullio",
    "wof:placetype":"venue"
},
  "geometry": {"coordinates":[11.8691091537,45.444568634],"type":"Point"}
}