{
  "type": "Feature",
  "properties": {
    "iso:country":"IT",
    "sg:address":"Via Don Sturzo 1 56025 Pontedera",
    "sg:city":"Pontedera",
    "sg:classifiers":[
        {
            "category":"Shopping",
            "subcategory":"Clothing, Apparel, & Fashions",
            "type":"Retail Goods"
        }
    ],
    "sg:phone":"+39 0587 484164",
    "sg:postcode":"56025",
    "sg:province":"Pisa",
    "sg:tags":[
        "leather",
        "clothing"
    ],
    "wof:name":"Dibi Pelfur Spa",
    "wof:placetype":"venue"
},
  "geometry": {"coordinates":[10.656816,43.665417],"type":"Point"}
}