{
  "type": "Feature",
  "properties": {
    "addr:full":"8, Via Brodolini Giacomo 60035 Jesi Jesi Ancona 60035",
    "addr:postcode":"60035;60035",
    "addr:street":"Via Brodolini Giacomo",
    "iso:country":"IT",
    "sg:address":"8, Via Brodolini Giacomo 60035 Jesi",
    "sg:city":"Jesi",
    "sg:classifiers":[
        {
            "category":"Shopping",
            "subcategory":"Clothing, Apparel, & Fashions",
            "type":"Retail Goods"
        }
    ],
    "sg:phone":"+39 39073158626",
    "sg:postcode":"60035",
    "sg:province":"Ancona",
    "sg:tags":[
        "clothes"
    ],
    "wof:name":"Pellicceria Fur Mary (s.r.l.)",
    "wof:placetype":"venue"
},
  "geometry": {"coordinates":[13.518757,43.615856],"type":"Point"}
}