{
  "type": "Feature",
  "properties": {
    "iso:country":"IT",
    "sg:address":"92014 Porto Empedocle",
    "sg:city":"Porto Empedocle",
    "sg:orig_category":"Servizi Al Turismo. Servizi Ausiliari Per Il Trasporto",
    "sg:phone":"+39 0922 636685",
    "sg:postcode":"92014",
    "sg:province":"Agrigento",
    "wof:name":"Siremar Agenzia Tricoli & Nuara Srl",
    "wof:placetype":"venue"
},
  "geometry": {"coordinates":[13.527126,37.286598],"type":"Point"}
}