{
  "type": "Feature",
  "properties": {
    "addr:full":"54033 Carrara Carrara Massa-Carrara 54033",
    "addr:postcode":"54033;54033",
    "iso:country":"IT",
    "sg:address":"54033 Carrara",
    "sg:city":"Carrara",
    "sg:orig_category":"Prodotti Di Base E Forniture Per Industria Alimentare E Bevande. Vetro: Prodotti E Lavorazioni. Articoli Per Imballaggio E Confezionamento",
    "sg:phone":"+39 0585 71471",
    "sg:postcode":"54033",
    "sg:province":"Massa-Carrara",
    "wof:name":"Mazzoni Silvia",
    "wof:placetype":"venue"
},
  "geometry": {"coordinates":[10.099395752,44.0799751282],"type":"Point"}
}