{
  "type": "Feature",
  "properties": {
    "iso:country":"IT",
    "sg:address":"37060 Lugagnano",
    "sg:city":"Lugagnano",
    "sg:orig_category":"Scuole E Servizi Scolastici. Servizi Per Lo Sport E Il Tempo Libero",
    "sg:phone":"+39 045 514500",
    "sg:postcode":"37060",
    "sg:province":"Verona",
    "wof:name":"Gruppo Sportivo Lugagnano",
    "wof:placetype":"venue"
},
  "geometry": {"coordinates":[10.878736,45.43364],"type":"Point"}
}