{
  "type": "Feature",
  "properties": {
    "iso:country":"IT",
    "sg:address":"20126 Milano",
    "sg:city":"Milano",
    "sg:orig_category":"Macchine Utensili E Impianti",
    "sg:phone":"+39 02 6610 7177",
    "sg:postcode":"20126",
    "sg:province":"Milano",
    "wof:name":"Siderservizi Srl",
    "wof:placetype":"venue"
},
  "geometry": {"coordinates":[9.218408,45.517422],"type":"Point"}
}