{
  "type": "Feature",
  "properties": {
    "iso:country":"IT",
    "sg:address":"Via Postiglione 16 10024 Moncalieri",
    "sg:city":"Moncalieri",
    "sg:classifiers":[
        {
            "category":"Autos & Motor Vehicles",
            "subcategory":"Auto Supplies",
            "type":"Retail Goods"
        }
    ],
    "sg:phone":"+39 011 689 4413",
    "sg:postcode":"10024",
    "sg:province":"Torino",
    "sg:tags":[
        "interior",
        "covering"
    ],
    "sg:website":"www.mgicoutier.com",
    "wof:name":"Mgi Coutier Italia S.r.l.",
    "wof:placetype":"venue"
},
  "geometry": {"coordinates":[7.722157,44.97525],"type":"Point"}
}