{
  "type": "Feature",
  "properties": {
    "iso:country":"IT",
    "sg:address":"10128 Torino",
    "sg:city":"Torino",
    "sg:orig_category":"Forniture Per Abbigliamento E Pelletterie",
    "sg:phone":"+39 011 562 8992",
    "sg:postcode":"10128",
    "sg:province":"Torino",
    "wof:name":"Ghio Fratelli & Sorelle Sas Di Ghio Gilberto & C.",
    "wof:placetype":"venue"
},
  "geometry": {"coordinates":[7.3751473427,44.8921127319],"type":"Point"}
}