{
  "type": "Feature",
  "properties": {
    "iso:country":"IT",
    "sg:address":"20122 Milano",
    "sg:city":"Milano",
    "sg:classifiers":[
        {
            "category":"Insurance",
            "subcategory":"Insurance Agent",
            "type":"Services"
        }
    ],
    "sg:phone":"+39 0285571",
    "sg:postcode":"20122",
    "sg:province":"Milano",
    "sg:tags":[
        "technical",
        "consultant",
        "services",
        "appraiser",
        "administrative"
    ],
    "sg:website":"http://www.mansutti.it",
    "wof:name":"Mansutti Spa",
    "wof:placetype":"venue"
},
  "geometry": {"coordinates":[9.189918,45.460796],"type":"Point"}
}