{
  "type": "Feature",
  "properties": {
    "addr:full":"10138 Torino Torino Torino 10138",
    "addr:housenumber":"10138",
    "addr:postcode":"10138",
    "iso:country":"IT",
    "sg:address":"10138 Torino",
    "sg:city":"Torino",
    "sg:orig_category":"Tessuti Arredamento, Tende E Tappeti. Forniture Per Edilizia E Lavori Pubblici",
    "sg:phone":"+39 011 385 1428",
    "sg:postcode":"10138",
    "sg:province":"Torino",
    "sg:website":"http://www.flooring.it",
    "wof:name":"Flooring Di Aralla Lorenzo",
    "wof:placetype":"venue"
},
  "geometry": {"coordinates":[7.657862,45.069744],"type":"Point"}
}