{
  "type": "Feature",
  "properties": {
    "iso:country":"IT",
    "sg:address":"20124 Milano",
    "sg:city":"Milano",
    "sg:orig_category":"Prodotti Finiti Stampati. Forniture Per Uffici. Regalistica Aziendale",
    "sg:phone":"+39 02 6671 0409",
    "sg:postcode":"20124",
    "sg:province":"Milano",
    "wof:name":"Nuovo Istituto Italiano D\u2019arti Grafiche Spa",
    "wof:placetype":"venue"
},
  "geometry": {"coordinates":[9.2030649185,45.4833908081],"type":"Point"}
}