{
  "type": "Feature",
  "properties": {
    "addr:full":"22078 Turate Turate Como 22078",
    "addr:postcode":"22078;22078",
    "iso:country":"IT",
    "sg:address":"22078 Turate",
    "sg:city":"Turate",
    "sg:orig_category":"Pompe. Macchine, Strumenti Ed Apparecchi Per Attivita' Industriali",
    "sg:phone":"+39 02 9648 0396",
    "sg:postcode":"22078",
    "sg:province":"Como",
    "wof:name":"Visati Pompe Snc Di Ugolotti A. & C.",
    "wof:placetype":"venue"
},
  "geometry": {"coordinates":[9.0068101883,45.6581459045],"type":"Point"}
}