{
  "type": "Feature",
  "properties": {
    "addr:full":"20027 Rescaldina Rescaldina Milano 20027",
    "addr:postcode":"20027;20027",
    "iso:country":"IT",
    "sg:address":"20027 Rescaldina",
    "sg:city":"Rescaldina",
    "sg:orig_category":"Apparecchiature E Sistemi Per Magazzinaggio E Movimentazione",
    "sg:phone":"+39 0331 576427",
    "sg:postcode":"20027",
    "sg:province":"Milano",
    "wof:name":"Borghi Vincenzo Sas",
    "wof:placetype":"venue"
},
  "geometry": {"coordinates":[8.927608,45.594681],"type":"Point"}
}