{
  "type": "Feature",
  "properties": {
    "iso:country":"IT",
    "sg:address":"73010 Lequile",
    "sg:city":"Lequile",
    "sg:classifiers":[
        {
            "category":"Farming",
            "subcategory":"Berry Farm",
            "type":"Manufacturing & Wholesale Goods"
        }
    ],
    "sg:phone":"+39 0832 261057",
    "sg:postcode":"73010",
    "sg:province":"Lecce",
    "sg:tags":[
        "vegetable",
        "growing",
        "flower",
        "agriculture"
    ],
    "sg:website":"http://www.albertidicatenaya.com",
    "wof:name":"Alberti Di Catenaya Srl",
    "wof:placetype":"venue"
},
  "geometry": {"coordinates":[18.141111,40.306889],"type":"Point"}
}