{
  "type": "Feature",
  "properties": {
    "addr:full":"Localita' Fosso Dei Molini 58054 Scansano Scansano Grosseto 58054",
    "addr:postcode":"58054;58054",
    "addr:street":"Localita ' Fosso Dei Molini",
    "iso:country":"IT",
    "sg:address":"Localita' Fosso Dei Molini 58054 Scansano",
    "sg:city":"Scansano",
    "sg:classifiers":[
        {
            "category":"Food & Beverages",
            "subcategory":"Groceries & Convenience Stores",
            "type":"Retail Goods"
        }
    ],
    "sg:phone":"+39 0564 508006",
    "sg:postcode":"58054",
    "sg:province":"Grosseto",
    "sg:tags":[
        "product",
        "related"
    ],
    "wof:name":"Azienda Agricola Vinoso S.r.l.",
    "wof:placetype":"venue"
},
  "geometry": {"coordinates":[11.1127824783,42.7628593445],"type":"Point"}
}