{
  "type": "Feature",
  "properties": {
    "iso:country":"IT",
    "sg:address":"2, V. Dell'artigianato 35010 Trebaseleghe",
    "sg:city":"Trebaseleghe",
    "sg:classifiers":[
        {
            "category":"Wholesale",
            "subcategory":"Drugs",
            "type":"Manufacturing & Wholesale Goods"
        }
    ],
    "sg:phone":"+39 049 938 5648",
    "sg:postcode":"35010",
    "sg:province":"Padova",
    "sg:tags":[
        "chemical",
        "pharmaceutical"
    ],
    "sg:website":"http://www.kemichal.it:ws_end: :mark:ws:http://www.paginegialle.it/kemichal",
    "wof:name":"Kemichal Srl",
    "wof:placetype":"venue"
},
  "geometry": {"coordinates":[12.049898,45.582504],"type":"Point"}
}