{
  "type": "Feature",
  "properties": {
    "addr:full":"70032 Bitonto Bitonto Bari 70032",
    "addr:postcode":"70032;70032",
    "iso:country":"IT",
    "sg:address":"70032 Bitonto",
    "sg:city":"Bitonto",
    "sg:orig_category":"Articoli Regalo - Vendita Al Dettaglio",
    "sg:phone":"+39 080 371 7363",
    "sg:postcode":"70032",
    "sg:province":"Bari",
    "wof:name":"Vierre Pelletterie Di Visaggi Rita",
    "wof:placetype":"venue"
},
  "geometry": {"coordinates":[16.784348,41.087082],"type":"Point"}
}