{
  "type": "Feature",
  "properties": {
    "iso:country":"IT",
    "sg:address":"Via Perticari, 6/8 47035 Gambettola",
    "sg:city":"Gambettola",
    "sg:classifiers":[
        {
            "category":"Building & Trades",
            "subcategory":"Construction",
            "type":"Services"
        }
    ],
    "sg:phone":"+39 0547 54240",
    "sg:postcode":"47035",
    "sg:province":"Forl\u00ec-Cesena",
    "sg:tags":[
        "agent",
        "waterproofing"
    ],
    "sg:website":"www.isoltema.com",
    "wof:name":"Isoltema Spa",
    "wof:placetype":"venue"
},
  "geometry": {"coordinates":[12.333592,44.108543],"type":"Point"}
}