{
  "type": "Feature",
  "properties": {
    "iso:country":"IT",
    "sg:address":"23020 Montagna In Valtellina",
    "sg:city":"Montagna in Valtellina",
    "sg:orig_category":"Bagno - Accessori E Mobili",
    "sg:phone":"+39 0342 720244",
    "sg:postcode":"23020",
    "sg:province":"Sondrio",
    "wof:name":"Idrotermica Srl",
    "wof:placetype":"venue"
},
  "geometry": {"coordinates":[9.89905,46.169327],"type":"Point"}
}