{
  "type": "Feature",
  "properties": {
    "iso:country":"IT",
    "sg:address":"83027 Mugnano Del Cardinale",
    "sg:city":"Mugnano del Cardinale",
    "sg:orig_category":"Ospedali E Servizi Sanitari",
    "sg:phone":"+39 081 825 7494",
    "sg:postcode":"83027",
    "sg:province":"Avellino",
    "wof:name":"Carotenuto Vincenza",
    "wof:placetype":"venue"
},
  "geometry": {"coordinates":[14.640061,40.941135],"type":"Point"}
}