{
  "type": "Feature",
  "properties": {
    "iso:country":"IT",
    "sg:address":"20080 Zibido S. Giacomo",
    "sg:orig_category":"Tessuti Arredamento, Tende E Tappeti",
    "sg:phone":"+39 02 9009 3605",
    "sg:postcode":"20080",
    "sg:province":"Milano",
    "wof:name":"Due Emme 2 Sas Di Maitti Fabio",
    "wof:placetype":"venue"
},
  "geometry": {"coordinates":[9.134026,45.402866],"type":"Point"}
}