{
  "type": "Feature",
  "properties": {
    "addr:full":"36027 Ros\u00e0 Vicenza 36027",
    "addr:postcode":"36027;36027",
    "iso:country":"IT",
    "sg:address":"36027 Ros\u00e0",
    "sg:orig_category":"Fiori E Piante - Vendita Al Dettaglio",
    "sg:phone":"+39 0424 580666",
    "sg:postcode":"36027",
    "sg:province":"Vicenza",
    "wof:name":"Bisinella Tiberio",
    "wof:placetype":"venue"
},
  "geometry": {"coordinates":[11.5212192535,45.7493476868],"type":"Point"}
}