{
  "type": "Feature",
  "properties": {
    "iso:country":"IT",
    "sg:address":"73013 Galatina",
    "sg:city":"Galatina",
    "sg:orig_category":"Abbigliamento Esterno, Maglierie E Pelliccerie. Shopping",
    "sg:phone":"+39 0836 564807",
    "sg:postcode":"73013",
    "sg:province":"Lecce",
    "wof:name":"Dayana",
    "wof:placetype":"venue"
},
  "geometry": {"coordinates":[18.058245,40.268375],"type":"Point"}
}