{
  "type": "Feature",
  "properties": {
    "addr:full":"07046 Porto Torres Porto Torres Sassari 07046",
    "addr:housenumber":"07046",
    "addr:postcode":"07046",
    "addr:street":"Porto Torres Porto Torres",
    "iso:country":"IT",
    "sg:address":"07046 Porto Torres",
    "sg:city":"Porto Torres",
    "sg:orig_category":"Prodotti Vari In Metallo. Articoli Per Imballaggio E Confezionamento",
    "sg:phone":"+39 079 516044",
    "sg:postcode":"07046",
    "sg:province":"Sassari",
    "wof:name":"Tinteri Antonio",
    "wof:placetype":"venue"
},
  "geometry": {"coordinates":[8.3417005539,40.8283729553],"type":"Point"}
}