{
  "type": "Feature",
  "properties": {
    "addr:full":"199, Via Roma 62100 Macerata Macerata Macerata 62100",
    "addr:housenumber":"199",
    "addr:postcode":"62100;62100",
    "addr:street":"Via Roma",
    "iso:country":"IT",
    "sg:address":"199, Via Roma 62100 Macerata",
    "sg:city":"Macerata",
    "sg:classifiers":[
        {
            "category":"Banks & Credit Unions",
            "subcategory":"Bank",
            "type":"Services"
        }
    ],
    "sg:phone":"+39 0733 367143",
    "sg:postcode":"62100",
    "sg:province":"Macerata",
    "sg:tags":[
        "banking",
        "institution"
    ],
    "wof:name":"Banca 121",
    "wof:placetype":"venue"
},
  "geometry": {"coordinates":[13.43716,43.293842],"type":"Point"}
}