{
  "type": "Feature",
  "properties": {
    "iso:country":"IT",
    "sg:address":"Via Salieri 8 37050 Vallese",
    "sg:city":"Vallese",
    "sg:classifiers":[
        {
            "category":"Military Area",
            "subcategory":"Army Base",
            "type":"Public Place"
        }
    ],
    "sg:phone":"+39 045 713 4633",
    "sg:postcode":"37050",
    "sg:province":"Verona",
    "sg:tags":[
        "safes",
        "room",
        "strong"
    ],
    "sg:website":"www.stahl-srl.com",
    "wof:name":"Stahl Srl",
    "wof:placetype":"venue"
},
  "geometry": {"coordinates":[11.060934,45.348042],"type":"Point"}
}