{
  "type": "Feature",
  "properties": {
    "iso:country":"IT",
    "sg:address":"00187 Roma",
    "sg:city":"Roma",
    "sg:orig_category":"Banche E Servizi Finanziari",
    "sg:phone":"+39 06 482 1521",
    "sg:postcode":"00187",
    "sg:province":"Roma",
    "wof:name":"Fincorp Srl",
    "wof:placetype":"venue"
},
  "geometry": {"coordinates":[12.487872,41.903587],"type":"Point"}
}