{
  "type": "Feature",
  "properties": {
    "addr:full":"148, Via Umbro Casentinese 52011 Bibbiena Bibbiena Arezzo 52011",
    "addr:housenumber":"148",
    "addr:postcode":"52011;52011",
    "addr:street":"Via Umbro Casentinese",
    "iso:country":"IT",
    "sg:address":"148, Via Umbro Casentinese 52011 Bibbiena",
    "sg:city":"Bibbiena",
    "sg:classifiers":[
        {
            "category":"Manufacturing",
            "subcategory":"Lumber",
            "type":"Manufacturing & Wholesale Goods"
        }
    ],
    "sg:phone":"+39 0575 593083",
    "sg:postcode":"52011",
    "sg:province":"Arezzo",
    "sg:tags":[
        "wood"
    ],
    "wof:name":"Conti Dei (s.a.s.)",
    "wof:placetype":"venue"
},
  "geometry": {"coordinates":[11.810882,43.699505],"type":"Point"}
}