{
  "type": "Feature",
  "properties": {
    "addr:full":"Via Enaudi 11/c 40050 Castello D'argile Bologna 40050",
    "addr:housenumber":"11 / c",
    "addr:postcode":"40050;40050",
    "addr:street":"Via Enaudi",
    "iso:country":"IT",
    "sg:address":"Via Enaudi 11/c 40050 Castello D'argile",
    "sg:classifiers":[
        {
            "category":"Manufacturing",
            "subcategory":"Motor Vehicles & Parts",
            "type":"Manufacturing & Wholesale Goods"
        }
    ],
    "sg:phone":"+39 051 977831",
    "sg:postcode":"40050",
    "sg:province":"Bologna",
    "sg:tags":[
        "spare",
        "tractor",
        "accessory"
    ],
    "sg:website":"www.cosibo.it",
    "wof:name":"Cosibo Srl",
    "wof:placetype":"venue"
},
  "geometry": {"coordinates":[11.346481,44.494221],"type":"Point"}
}