{
  "type": "Feature",
  "properties": {
    "iso:country":"IT",
    "sg:address":"Sda Vecchia Di Pinerolo 10045 Piossasco",
    "sg:city":"Piossasco",
    "sg:classifiers":[
        {
            "category":"Utilities",
            "subcategory":"Electric",
            "type":"Services"
        }
    ],
    "sg:phone":"+39 011 904 2132",
    "sg:postcode":"10045",
    "sg:province":"Torino",
    "sg:tags":[
        "transformer"
    ],
    "sg:website":"www.elpitalia.com",
    "wof:name":"Elettromeccanica Piossasco Di Ing. Luparia Alessandro & Figli Snc",
    "wof:placetype":"venue"
},
  "geometry": {"coordinates":[7.502852,44.96077],"type":"Point"}
}