{
  "type": "Feature",
  "properties": {
    "iso:country":"IT",
    "sg:address":"73032 Andrano",
    "sg:city":"Andrano",
    "sg:orig_category":"Cravatte, Sciarpe E Foulards",
    "sg:phone":"+39 0836 969900",
    "sg:postcode":"73032",
    "sg:province":"Lecce",
    "wof:name":"Rogial's Tie Srl",
    "wof:placetype":"venue"
},
  "geometry": {"coordinates":[18.386707,39.98214],"type":"Point"}
}