{
  "type": "Feature",
  "properties": {
    "addr:full":"00185 Roma Roma Roma 00185",
    "addr:postcode":"00185;00185",
    "iso:country":"IT",
    "sg:address":"00185 Roma",
    "sg:city":"Roma",
    "sg:orig_category":"Pratiche E Certificati - Agenzie",
    "sg:phone":"+39 06 446 0300",
    "sg:postcode":"00185",
    "sg:province":"Roma",
    "sg:website":"http://www.prontobollo.it",
    "wof:name":"Prontobollo Srl",
    "wof:placetype":"venue"
},
  "geometry": {"coordinates":[12.509727478,41.8977012634],"type":"Point"}
}