{
  "type": "Feature",
  "properties": {
    "addr:full":"00181 Roma Roma Roma 00181",
    "addr:postcode":"00181;00181",
    "iso:country":"IT",
    "sg:address":"00181 Roma",
    "sg:city":"Roma",
    "sg:classifiers":[
        {
            "category":"Professional",
            "subcategory":"Computer Services",
            "type":"Services"
        }
    ],
    "sg:phone":"+39 06 7834 6516",
    "sg:postcode":"00181",
    "sg:province":"Roma",
    "sg:tags":[
        "decorative",
        "furniture",
        "object",
        "furnishings",
        "furnishing"
    ],
    "sg:website":"http://www.capitolium.net",
    "wof:name":"Capitolium",
    "wof:placetype":"venue"
},
  "geometry": {"coordinates":[12.5326709747,41.8756103516],"type":"Point"}
}