{
  "type": "Feature",
  "properties": {
    "iso:country":"IT",
    "sg:address":"41100 Modena",
    "sg:city":"Modena",
    "sg:classifiers":[
        {
            "category":"Sports & Exercise",
            "subcategory":"Tennis Court",
            "type":"Entertainment"
        }
    ],
    "sg:phone":"+39 059 391710",
    "sg:postcode":"41100",
    "sg:province":"Modena",
    "sg:tags":[
        "e",
        "lo",
        "tempo",
        "libero",
        "per",
        "impianti",
        "il",
        "attrezzature"
    ],
    "wof:name":"I.t.s. Di Salerno Antonio",
    "wof:placetype":"venue"
},
  "geometry": {"coordinates":[10.931299,44.615875],"type":"Point"}
}