{
  "type": "Feature",
  "properties": {
    "addr:full":"24, Via Matteotti Giacomo 20016 Pero Pero Milano 20016",
    "addr:postcode":"20016;20016",
    "addr:street":"Via Matteotti Giacomo",
    "iso:country":"IT",
    "sg:address":"24, Via Matteotti Giacomo 20016 Pero",
    "sg:city":"Pero",
    "sg:classifiers":[
        {
            "category":"Shopping",
            "subcategory":"Clothing, Apparel, & Fashions",
            "type":"Retail Goods"
        }
    ],
    "sg:phone":"+39 39023561430",
    "sg:postcode":"20016",
    "sg:province":"Milano",
    "sg:tags":[
        "clothing",
        "accessory"
    ],
    "wof:name":"D.h.j. Industries (s.r.l.)",
    "wof:placetype":"venue"
},
  "geometry": {"coordinates":[9.067823,45.517712],"type":"Point"}
}