{
  "type": "Feature",
  "properties": {
    "iso:country":"IT",
    "sg:address":"03030 Villa Santa Lucia",
    "sg:city":"Villa Santa Lucia",
    "sg:orig_category":"Materiali Semilavorati Metallici",
    "sg:phone":"+39 0776 465487",
    "sg:postcode":"03030",
    "sg:province":"Frosinone",
    "wof:name":"Di.ma. Di Di Ianne Mauro",
    "wof:placetype":"venue"
},
  "geometry": {"coordinates":[13.783829,41.489105],"type":"Point"}
}