{
  "type": "Feature",
  "properties": {
    "iso:country":"IT",
    "sg:address":"55023 Chifenti",
    "sg:city":"Chifenti",
    "sg:orig_category":"Articoli Da Regalo. Arte Ed Artigianato Artistico. Shopping",
    "sg:phone":"+39 0583 87213",
    "sg:postcode":"55023",
    "sg:province":"Lucca",
    "wof:name":"Presepi Fontanini (s.p.a.)",
    "wof:placetype":"venue"
},
  "geometry": {"coordinates":[10.559871,44.001575],"type":"Point"}
}