{
  "type": "Feature",
  "properties": {
    "iso:country":"IT",
    "sg:address":"10036 Settimo Torinese",
    "sg:city":"Settimo Torinese",
    "sg:orig_category":"Filati E Materie Prime Tessili",
    "sg:phone":"+39 011 895 5444",
    "sg:postcode":"10036",
    "sg:province":"Torino",
    "wof:name":"Franzoso Cinzia",
    "wof:placetype":"venue"
},
  "geometry": {"coordinates":[7.7619457245,45.1351356506],"type":"Point"}
}