{
  "type": "Feature",
  "properties": {
    "iso:country":"IT",
    "sg:address":"58, Via Poggio Secco 59100 Prato",
    "sg:city":"Prato",
    "sg:classifiers":[
        {
            "category":"Travel",
            "subcategory":"Travel Agent",
            "type":"Entertainment"
        }
    ],
    "sg:phone":"+39 0574 595952",
    "sg:postcode":"59100",
    "sg:province":"Prato",
    "sg:tags":[
        "business"
    ],
    "wof:name":"Albergo Villa S.cristina",
    "wof:placetype":"venue"
},
  "geometry": {"coordinates":[11.123646,43.872295],"type":"Point"}
}