{
  "type": "Feature",
  "properties": {
    "iso:country":"IT",
    "sg:address":"20149 Milano",
    "sg:city":"Milano",
    "sg:orig_category":"Servizi Editoriali",
    "sg:phone":"+39 02 462740",
    "sg:postcode":"20149",
    "sg:province":"Milano",
    "wof:name":"Gallo Vincenzo",
    "wof:placetype":"venue"
},
  "geometry": {"coordinates":[9.152101,45.473869],"type":"Point"}
}