{
  "type": "Feature",
  "properties": {
    "addr:full":"06132 Perugia Perugia Perugia 06132",
    "addr:postcode":"06132;06132",
    "iso:country":"IT",
    "sg:address":"06132 Perugia",
    "sg:city":"Perugia",
    "sg:orig_category":"Borse E Borsette - Produzione E Ingrosso",
    "sg:phone":"+39 075 874 3505",
    "sg:postcode":"06132",
    "sg:province":"Perugia",
    "sg:website":"http://www.militarystyle.com",
    "wof:name":"Pelletterie 2 Erre Srl",
    "wof:placetype":"venue"
},
  "geometry": {"coordinates":[12.339735,43.073055],"type":"Point"}
}