{
  "type": "Feature",
  "properties": {
    "iso:country":"IT",
    "sg:address":"64017 Sant'onofrio",
    "sg:orig_category":"Ospedali E Servizi Sanitari",
    "sg:phone":"+39 0861 553139",
    "sg:province":"TE",
    "wof:name":"D'isidoro Dina",
    "wof:placetype":"venue"
},
  "geometry": {"coordinates":[13.718924,42.753185],"type":"Point"}
}