{
  "type": "Feature",
  "properties": {
    "addr:full":"2, Localita' Molino Rastelli 13018 Valduggia Valduggia Vercelli 13018",
    "addr:postcode":"13018;13018",
    "addr:street":"Localita ' Molino Rastelli",
    "iso:country":"IT",
    "sg:address":"2, Localita' Molino Rastelli 13018 Valduggia",
    "sg:city":"Valduggia",
    "sg:classifiers":[
        {
            "category":"Shopping",
            "type":"Retail Goods"
        }
    ],
    "sg:phone":"+39 39016348062",
    "sg:postcode":"13018",
    "sg:province":"Vercelli",
    "sg:tags":[
        "finished",
        "-",
        "metallic"
    ],
    "wof:name":"B.r.v.bonetti Rubinetterie Valduggia S.r.l.",
    "wof:placetype":"venue"
},
  "geometry": {"coordinates":[8.4263935089,45.3210601807],"type":"Point"}
}