{
  "type": "Feature",
  "properties": {
    "iso:country":"IT",
    "sg:address":"20088 Rosate",
    "sg:city":"Rosate",
    "sg:orig_category":"Forniture Per Edilizia E Lavori Pubblici",
    "sg:phone":"+39 02 9087 0340",
    "sg:postcode":"20088",
    "sg:province":"Milano",
    "sg:website":"http://www.2mrsystem.com",
    "wof:name":"2 Mr System Srl",
    "wof:placetype":"venue"
},
  "geometry": {"coordinates":[9.0234746933,45.3533935547],"type":"Point"}
}