{
  "type": "Feature",
  "properties": {
    "iso:country":"IT",
    "sg:address":"46100 Mantova",
    "sg:city":"Mantova",
    "sg:orig_category":"Editoria",
    "sg:phone":"+39 0376 322430",
    "sg:postcode":"46100",
    "sg:province":"Mantova",
    "sg:website":"http://www.sometti.com",
    "wof:name":"Sometti Editoriale",
    "wof:placetype":"venue"
},
  "geometry": {"coordinates":[10.793054,45.159916],"type":"Point"}
}