{
  "type": "Feature",
  "properties": {
    "iso:country":"IT",
    "sg:address":"13, Viale Europa 33050 Pozzuolo Del Friuli",
    "sg:city":"Pozzuolo del Friuli",
    "sg:classifiers":[
        {
            "category":"Professional",
            "subcategory":"Engineering",
            "type":"Services"
        }
    ],
    "sg:phone":"+39 0432 560305",
    "sg:postcode":"33050",
    "sg:province":"Udine",
    "sg:tags":[
        "machine",
        "-",
        "mechanical"
    ],
    "wof:name":"Geatti (s.r.l.)",
    "wof:placetype":"venue"
},
  "geometry": {"coordinates":[13.208711,46.005882],"type":"Point"}
}