{
  "type": "Feature",
  "properties": {
    "addr:full":"20017 Terrazzano Terrazzano Milano 20017",
    "addr:postcode":"20017;terrazzano;20017",
    "iso:country":"IT",
    "sg:address":"20017 Terrazzano",
    "sg:city":"Terrazzano",
    "sg:orig_category":"Materiali Edili",
    "sg:phone":"+39 02 9390 0691",
    "sg:postcode":"20017",
    "sg:province":"Milano",
    "wof:name":"Giussani Giuseppe",
    "wof:placetype":"venue"
},
  "geometry": {"coordinates":[9.06753,45.54108],"type":"Point"}
}