{
  "type": "Feature",
  "properties": {
    "iso:country":"IT",
    "sg:address":"20158 Milano",
    "sg:city":"Milano",
    "sg:orig_category":"Materiali E Componenti Elettrotecnici",
    "sg:phone":"+39 02 3932 0453",
    "sg:postcode":"20158",
    "sg:province":"Milano",
    "wof:name":"Corubolo Silvano",
    "wof:placetype":"venue"
},
  "geometry": {"coordinates":[9.169043,45.500031],"type":"Point"}
}