{
  "type": "Feature",
  "properties": {
    "addr:full":"Via San Gaetano, 113 Motebelluna 31044",
    "addr:housenumber":"113",
    "addr:postcode":"31044",
    "addr:street":"Via San Gaetano",
    "iso:country":"IT",
    "sg:address":"Via San Gaetano, 113",
    "sg:city":"Motebelluna",
    "sg:classifiers":[
        {
            "category":"Professional",
            "subcategory":"Computer Services",
            "type":"Services"
        }
    ],
    "sg:postcode":"31044",
    "sg:tags":[
        "crm",
        "avatar",
        "virtual-assistant",
        "3d-animation",
        "self-service",
        "ivr",
        "text-to-speech",
        "text-to-video"
    ],
    "sg:website":"http://www.h-care.eu",
    "wof:name":"H-care",
    "wof:placetype":"venue"
},
  "geometry": {"coordinates":[12.428383,45.564237],"type":"Point"}
}