{
  "type": "Feature",
  "properties": {
    "iso:country":"IT",
    "sg:address":"14, Via Carducci 34070 Moraro",
    "sg:city":"Moraro",
    "sg:classifiers":[
        {
            "category":"Home & Garden",
            "subcategory":"Home Furnishings",
            "type":"Retail Goods"
        }
    ],
    "sg:phone":"+39 0481 809132",
    "sg:postcode":"34070",
    "sg:province":"Gorizia",
    "sg:tags":[
        "household"
    ],
    "wof:name":"Picotti (s.r.l.)",
    "wof:placetype":"venue"
},
  "geometry": {"coordinates":[13.511025,45.940498],"type":"Point"}
}