{
  "type": "Feature",
  "properties": {
    "addr:full":"20121 Milano Milano Milano 20121",
    "addr:postcode":"20121;20121",
    "iso:country":"IT",
    "sg:address":"20121 Milano",
    "sg:city":"Milano",
    "sg:orig_category":"Professionisti - Studi E Servizi Ed Associazioni Di Interesse Aziendale. Associazioni Ed Organismi Di Interesse Pubblico. Chiese Ed Associazioni Religiose",
    "sg:phone":"+39 02 659 9115",
    "sg:postcode":"20121",
    "sg:province":"Milano",
    "wof:name":"Centro Parrocchiale S. Marco",
    "wof:placetype":"venue"
},
  "geometry": {"coordinates":[9.1878757477,45.4734802246],"type":"Point"}
}