{
  "type": "Feature",
  "properties": {
    "addr:full":"106, Via Della Repubblica 50050 Cerreto Guidi Cerreto Guidi Firenze 50050",
    "addr:housenumber":"106",
    "addr:postcode":"50050;50050",
    "addr:street":"Via Della Repubblica",
    "iso:country":"IT",
    "sg:address":"106, Via Della Repubblica 50050 Cerreto Guidi",
    "sg:city":"Cerreto Guidi",
    "sg:classifiers":[
        {
            "category":"Home & Garden",
            "subcategory":"Home Furnishings",
            "type":"Retail Goods"
        }
    ],
    "sg:phone":"+39 0571 586180",
    "sg:postcode":"50050",
    "sg:province":"Firenze",
    "sg:tags":[
        "household"
    ],
    "wof:name":"Orlandi Bagno Srl",
    "wof:placetype":"venue"
},
  "geometry": {"coordinates":[10.93288,43.720119],"type":"Point"}
}