{
  "type": "Feature",
  "properties": {
    "iso:country":"IT",
    "sg:address":"172, Viale Buozzi Bruno 50013 Campi Bisenzio",
    "sg:city":"Campi Bisenzio",
    "sg:classifiers":[
        {
            "category":"Shopping",
            "subcategory":"Clothing, Apparel, & Fashions",
            "type":"Retail Goods"
        }
    ],
    "sg:phone":"+39 055 896 3306",
    "sg:postcode":"50013",
    "sg:province":"Firenze",
    "sg:tags":[
        "clothes"
    ],
    "wof:name":"Manifatture 7 Bell (s.p.a.)",
    "wof:placetype":"venue"
},
  "geometry": {"coordinates":[11.147247,43.816929],"type":"Point"}
}