{
  "type": "Feature",
  "properties": {
    "addr:full":"46019 Cogozzo Di Viadana Cogozzo Mantova 46019",
    "addr:postcode":"46019;46019",
    "iso:country":"IT",
    "sg:address":"46019 Cogozzo Di Viadana",
    "sg:city":"Cogozzo",
    "sg:orig_category":"Forniture Per Attivita' Industriali",
    "sg:phone":"+39 0375 785892",
    "sg:postcode":"46019",
    "sg:province":"Mantova",
    "sg:website":"http://www.fiorellini.it",
    "wof:name":"Fiorellini Sergio & C. Snc",
    "wof:placetype":"venue"
},
  "geometry": {"coordinates":[10.771944046,45.156665802],"type":"Point"}
}