{
  "type": "Feature",
  "properties": {
    "addr:full":"11029 Verres Verres Aosta 11029",
    "addr:postcode":"11029;11029",
    "iso:country":"IT",
    "sg:address":"11029 Verres",
    "sg:city":"Verres",
    "sg:orig_category":"Pubblica Amministrazione",
    "sg:phone":"+39 0125 920099",
    "sg:postcode":"11029",
    "sg:province":"Aosta",
    "wof:name":"Garderie Pour L'enfance",
    "wof:placetype":"venue"
},
  "geometry": {"coordinates":[7.6916251183,45.6644973755],"type":"Point"}
}