{
  "type": "Feature",
  "properties": {
    "iso:country":"IT",
    "sg:address":"20060 Vignate",
    "sg:city":"Vignate",
    "sg:orig_category":"Tempo Libero - Articoli E Forniture. Regalistica Aziendale",
    "sg:phone":"+39 02 9536 0292",
    "sg:postcode":"20060",
    "sg:province":"Milano",
    "wof:name":"Flash Laser Service Snc",
    "wof:placetype":"venue"
},
  "geometry": {"coordinates":[9.32622,45.482487],"type":"Point"}
}