{
  "type": "Feature",
  "properties": {
    "addr:full":"12037 Saluzzo Saluzzo Cuneo 12037",
    "addr:postcode":"12037;12037",
    "iso:country":"IT",
    "sg:address":"12037 Saluzzo",
    "sg:city":"Saluzzo",
    "sg:orig_category":"Arredamenti - Vendita Al Dettaglio",
    "sg:phone":"+39 0175 42642",
    "sg:postcode":"12037",
    "sg:province":"Cuneo",
    "sg:website":"http://www.pasero.it",
    "wof:name":"Studio D'interni Arredamenti Di Pasero Renzo & C. Snc",
    "wof:placetype":"venue"
},
  "geometry": {"coordinates":[7.498031,44.637787],"type":"Point"}
}