{
  "type": "Feature",
  "properties": {
    "iso:country":"IT",
    "sg:address":"49/51, Corso Quattro Novembre 12058 Santo Stefano Belbo",
    "sg:city":"Santo Stefano Belbo",
    "sg:classifiers":[
        {
            "category":"Manufacturing",
            "subcategory":"Wood Products",
            "type":"Manufacturing & Wholesale Goods"
        }
    ],
    "sg:phone":"+39 0141 844234",
    "sg:postcode":"12058",
    "sg:province":"Cuneo",
    "sg:tags":[
        "furniture"
    ],
    "wof:name":"I.l.a.s. Di Ariano E Careddu (s.r.l.)",
    "wof:placetype":"venue"
},
  "geometry": {"coordinates":[7.547111,44.388798],"type":"Point"}
}