{
  "type": "Feature",
  "properties": {
    "iso:country":"IT",
    "sg:address":"00181 Roma",
    "sg:city":"Roma",
    "sg:orig_category":"Idraulici E Lattonieri",
    "sg:phone":"+39 06 786563",
    "sg:postcode":"00181",
    "sg:province":"Roma",
    "wof:name":"Carinci Paolo",
    "wof:placetype":"venue"
},
  "geometry": {"coordinates":[12.529088,41.872765],"type":"Point"}
}