{
  "type": "Feature",
  "properties": {
    "iso:country":"IT",
    "sg:address":"Via Appia, Km 192,200 81052 Pignataro Maggiore",
    "sg:city":"Pignataro Maggiore",
    "sg:orig_category":"Aluminium Strips, Anodized",
    "sg:phone":"+39 0823 501111",
    "sg:postcode":"81052",
    "sg:province":"Caserta",
    "sg:website":"www.laminazionesottile.com",
    "wof:name":"Italcoat Srl",
    "wof:placetype":"venue"
},
  "geometry": {"coordinates":[14.332194,41.075417],"type":"Point"}
}