{
  "type": "Feature",
  "properties": {
    "addr:full":"29100 Piacenza Piacenza Piacenza 29100",
    "addr:postcode":"29100;29100",
    "iso:country":"IT",
    "sg:address":"29100 Piacenza",
    "sg:city":"Piacenza",
    "sg:orig_category":"Apparecchiature E Sistemi Per Imballaggio E Confezionamento",
    "sg:phone":"+39 0523 590191",
    "sg:postcode":"29100",
    "sg:province":"Piacenza",
    "wof:name":"Tecnopails Snc Di Lavelli Luigi",
    "wof:placetype":"venue"
},
  "geometry": {"coordinates":[9.767375,45.050365],"type":"Point"}
}