{
  "type": "Feature",
  "properties": {
    "iso:country":"IT",
    "sg:address":"95127 Catania",
    "sg:city":"Catania",
    "sg:orig_category":"Cine-foto-ottica. Articoli Medico-sanitari Ed Ortopedici",
    "sg:phone":"+39 095 552200",
    "sg:postcode":"95127",
    "sg:province":"Catania",
    "wof:name":"Di Vita Carmelo",
    "wof:placetype":"venue"
},
  "geometry": {"coordinates":[15.094701,37.520039],"type":"Point"}
}