{
  "type": "Feature",
  "properties": {
    "iso:country":"IT",
    "sg:address":"20145 Milano",
    "sg:city":"Milano",
    "sg:orig_category":"Studi E Consulenze Amministrative, Commerciali E Aziendali. Consulenze Tecniche, Amministrative E Perizie. Professionisti - Studi E Servizi Ed Associazioni Di Interesse Aziendale",
    "sg:phone":"+39 02 3360 8737",
    "sg:postcode":"20145",
    "sg:province":"Milano",
    "wof:name":"Elabora Sas Di A.saini & C.",
    "wof:placetype":"venue"
},
  "geometry": {"coordinates":[9.16838,45.475681],"type":"Point"}
}