{
  "type": "Feature",
  "properties": {
    "addr:full":"Via Lago Di Vico 60 36015 Schio Schio Vicenza 36015",
    "addr:housenumber":"60",
    "addr:postcode":"36015;36015",
    "addr:street":"Via Lago Di Vico",
    "iso:country":"IT",
    "sg:address":"Via Lago Di Vico 60 36015 Schio",
    "sg:city":"Schio",
    "sg:classifiers":[
        {
            "category":"Wholesale",
            "subcategory":"Medical Equipment & Supplies",
            "type":"Manufacturing & Wholesale Goods"
        }
    ],
    "sg:phone":"+39 0445 502011",
    "sg:postcode":"36015",
    "sg:province":"Vicenza",
    "sg:tags":[
        "dispenser"
    ],
    "sg:website":"www.fas.it",
    "wof:name":"Fas International S.p.a",
    "wof:placetype":"venue"
},
  "geometry": {"coordinates":[11.415496,45.717216],"type":"Point"}
}