{
  "type": "Feature",
  "properties": {
    "iso:country":"IT",
    "sg:address":"Via San Michele Del Carso 36 20035 Lissone",
    "sg:city":"Lissone",
    "sg:classifiers":[
        {
            "category":"Shopping",
            "subcategory":"Clothing, Apparel, & Fashions",
            "type":"Retail Goods"
        }
    ],
    "sg:phone":"+39 039 245 9222",
    "sg:postcode":"20035",
    "sg:province":"Milano",
    "sg:tags":[
        "sportswear"
    ],
    "sg:website":"www.silabybrambi.it",
    "wof:name":"Sila By Brambi Srl",
    "wof:placetype":"venue"
},
  "geometry": {"coordinates":[9.168759,45.574451],"type":"Point"}
}