{
  "type": "Feature",
  "properties": {
    "iso:country":"IT",
    "sg:address":"10036 Settimo Torinese",
    "sg:city":"Settimo Torinese",
    "sg:orig_category":"Macchine Ed Impianti Per Edilizia E Lavori Pubblici",
    "sg:phone":"+39 011 802 2211",
    "sg:postcode":"10036",
    "sg:province":"Torino",
    "wof:name":"Compagnia Generale Trattori S.p.a.",
    "wof:placetype":"venue"
},
  "geometry": {"coordinates":[7.742682,45.141811],"type":"Point"}
}