{
  "type": "Feature",
  "properties": {
    "iso:country":"IT",
    "sg:address":"59100 Prato",
    "sg:city":"Prato",
    "sg:orig_category":"Servizi Di Magazzinaggio E Movimentazione",
    "sg:phone":"+39 0574 401147",
    "sg:postcode":"59100",
    "sg:province":"Prato",
    "wof:name":"C.a.r. Service Di Amerini Simone Bartolini Paolo E C. Snc",
    "wof:placetype":"venue"
},
  "geometry": {"coordinates":[11.094441,43.885902],"type":"Point"}
}