{
  "type": "Feature",
  "properties": {
    "iso:country":"IT",
    "sg:address":"3, Via Dell' Elettronica Zona D3 15100 Alessandria",
    "sg:city":"Alessandria",
    "sg:classifiers":[
        {
            "category":"Farming",
            "subcategory":"Livestock Farm",
            "type":"Manufacturing & Wholesale Goods"
        }
    ],
    "sg:phone":"+39 0131 240311",
    "sg:postcode":"15100",
    "sg:province":"Alessandria",
    "sg:tags":[
        "agriculture"
    ],
    "wof:name":"Testore Giuseppe & C. (s.n.c.)",
    "wof:placetype":"venue"
},
  "geometry": {"coordinates":[8.616951,44.913216],"type":"Point"}
}