{
  "type": "Feature",
  "properties": {
    "iso:country":"IT",
    "sg:address":"Viale Borri 50 21053 Castellanza",
    "sg:city":"Castellanza",
    "sg:classifiers":[
        {
            "category":"Home & Garden",
            "subcategory":"Building Materials",
            "type":"Retail Goods"
        }
    ],
    "sg:phone":"+39 0331 679680",
    "sg:postcode":"21053",
    "sg:province":"Varese",
    "sg:tags":[
        "installation",
        "electric"
    ],
    "sg:website":"www.baldisrl.it",
    "wof:name":"Baldi Srl",
    "wof:placetype":"venue"
},
  "geometry": {"coordinates":[8.873945,45.605022],"type":"Point"}
}