{
  "type": "Feature",
  "properties": {
    "iso:country":"IT",
    "sg:address":"70010 Casamassima",
    "sg:city":"Casamassima",
    "sg:classifiers":[
        {
            "category":"Home & Garden",
            "subcategory":"Carpets & Floor Coverings",
            "type":"Retail Goods"
        }
    ],
    "sg:phone":"+39 080 697 0075",
    "sg:postcode":"70010",
    "sg:province":"Bari",
    "sg:tags":[
        "curtain",
        "material",
        "fabric",
        "fabrics",
        "furnishing"
    ],
    "wof:name":"Fratelli Ladisa Srl",
    "wof:placetype":"venue"
},
  "geometry": {"coordinates":[16.9181346893,40.9553070068],"type":"Point"}
}