{
  "type": "Feature",
  "properties": {
    "iso:country":"IT",
    "sg:address":"10121 Torino",
    "sg:city":"Torino",
    "sg:classifiers":[
        {
            "category":"Health Services",
            "subcategory":"Health Practitioner",
            "type":"Services"
        }
    ],
    "sg:phone":"+39 011 566 0433",
    "sg:postcode":"10121",
    "sg:province":"Torino",
    "sg:tags":[
        "medici"
    ],
    "wof:name":"Ferrando Ugo",
    "wof:placetype":"venue"
},
  "geometry": {"coordinates":[7.567674,45.065186],"type":"Point"}
}