{
  "type": "Feature",
  "properties": {
    "iso:country":"IT",
    "sg:address":"44100 Ferrara",
    "sg:city":"Ferrara",
    "sg:orig_category":"Serramenti Ed Infissi",
    "sg:phone":"+39 0532 712683",
    "sg:postcode":"44100",
    "sg:province":"Ferrara",
    "sg:website":"http://www.passarini.it",
    "wof:name":"Passarini Srl",
    "wof:placetype":"venue"
},
  "geometry": {"coordinates":[11.586777,44.806786],"type":"Point"}
}