{
  "type": "Feature",
  "properties": {
    "iso:country":"IT",
    "sg:address":"06124 Perugia",
    "sg:city":"Perugia",
    "sg:orig_category":"Informatica - Consulenza E Servizi. Editoria",
    "sg:phone":"+39 075 500 1468",
    "sg:postcode":"06124",
    "sg:province":"Perugia",
    "sg:website":"http://www.edizionidarte.com",
    "wof:name":"N.d.l. Sas",
    "wof:placetype":"venue"
},
  "geometry": {"coordinates":[12.381737,43.100235],"type":"Point"}
}