{
  "type": "Feature",
  "properties": {
    "addr:full":"20, Via Alessandrini Emilio 20013 Magenta Magenta Milano 20013",
    "addr:postcode":"20013;20013",
    "addr:street":"Via Alessandrini Emilio",
    "iso:country":"IT",
    "sg:address":"20, Via Alessandrini Emilio 20013 Magenta",
    "sg:city":"Magenta",
    "sg:classifiers":[
        {
            "category":"Manufacturing",
            "subcategory":"Metals",
            "type":"Manufacturing & Wholesale Goods"
        }
    ],
    "sg:phone":"+39 39029794353",
    "sg:postcode":"20013",
    "sg:province":"Milano",
    "sg:tags":[
        "metallurgy",
        "metalworking"
    ],
    "wof:name":"Zamapres (s.r.l.)",
    "wof:placetype":"venue"
},
  "geometry": {"coordinates":[9.1881408691,45.4636878967],"type":"Point"}
}