{
  "type": "Feature",
  "properties": {
    "addr:full":"Via Azzi 36 - Castagnole 31044 Castagnole Di Paese Treviso 31044",
    "addr:housenumber":"36",
    "addr:postcode":"31044;31044",
    "addr:street":"Via Azzi",
    "iso:country":"IT",
    "sg:address":"Via Azzi 36 - Castagnole 31044 Castagnole Di Paese",
    "sg:classifiers":[
        {
            "category":"Government",
            "subcategory":"Court House",
            "type":"Public Place"
        }
    ],
    "sg:phone":"+39 0422 438800",
    "sg:postcode":"31044",
    "sg:province":"Treviso",
    "sg:tags":[
        "accommodation",
        "furniture"
    ],
    "sg:website":"www.palluccobellato.it",
    "wof:name":"Pallucco Italia S.p.a.",
    "wof:placetype":"venue"
},
  "geometry": {"coordinates":[12.192446,45.690491],"type":"Point"}
}