{
  "type": "Feature",
  "properties": {
    "iso:country":"IT",
    "sg:address":"37, V. Cesare Battisti 25017 Lonato",
    "sg:city":"Lonato",
    "sg:classifiers":[
        {
            "category":"Autos & Motor Vehicles",
            "subcategory":"Automobile Sales",
            "type":"Retail Goods"
        }
    ],
    "sg:phone":"+39 030 913 3191",
    "sg:postcode":"25017",
    "sg:province":"Brescia",
    "sg:tags":[
        "motor-cars"
    ],
    "sg:website":"http://www.lorenziauto.it",
    "wof:name":"Lorenzi Group Srl",
    "wof:placetype":"venue"
},
  "geometry": {"coordinates":[10.492231369,45.4606552124],"type":"Point"}
}