{
  "type": "Feature",
  "properties": {
    "iso:country":"IT",
    "sg:address":"06038 Spello",
    "sg:city":"Spello",
    "sg:orig_category":"Macchine Ed Impianti Per Edilizia E Lavori Pubblici",
    "sg:phone":"+39 0742 301626",
    "sg:postcode":"06038",
    "sg:province":"Perugia",
    "wof:name":"Ciancaleoni Fausto & C. (s.n.c.)",
    "wof:placetype":"venue"
},
  "geometry": {"coordinates":[12.656072,43.00119],"type":"Point"}
}