{
  "type": "Feature",
  "properties": {
    "iso:country":"IT",
    "sg:address":"14045 Cortiglione",
    "sg:orig_category":"Elettrotecnica Industriale, Prodotti E Apparecchiature",
    "sg:phone":"+39 0141 765390",
    "sg:postcode":"14045",
    "sg:province":"Asti",
    "wof:name":"F.i.r.e. S.r.l.",
    "wof:placetype":"venue"
},
  "geometry": {"coordinates":[8.340138,44.880447],"type":"Point"}
}