{
  "type": "Feature",
  "properties": {
    "addr:full":"33030 Campoformido Campoformido Udine 33030",
    "addr:postcode":"33030;33030",
    "iso:country":"IT",
    "sg:address":"33030 Campoformido",
    "sg:city":"Campoformido",
    "sg:classifiers":[
        {
            "category":"Health Services",
            "subcategory":"Health Practitioner",
            "type":"Services"
        }
    ],
    "sg:phone":"+39 0432 69500",
    "sg:postcode":"33030",
    "sg:province":"Udine",
    "sg:tags":[
        "medici"
    ],
    "wof:name":"Studio Stomatologico Friulano Dei Dr. Mario, Federica & Alberto Fonzar",
    "wof:placetype":"venue"
},
  "geometry": {"coordinates":[13.2018442154,46.039150238],"type":"Point"}
}