{
  "type": "Feature",
  "properties": {
    "iso:country":"IT",
    "sg:address":"19020 Bolano",
    "sg:city":"Bolano",
    "sg:orig_category":"Torrefazione Di Caffe' Ed Affini - Lavorazione E Ingrosso",
    "sg:phone":"+39 0187 933711",
    "sg:postcode":"19020",
    "sg:province":"La Spezia",
    "sg:website":"http://www.italcaffe.it",
    "wof:name":"Italcaffe'",
    "wof:placetype":"venue"
},
  "geometry": {"coordinates":[9.878301,44.166992],"type":"Point"}
}