{
  "type": "Feature",
  "properties": {
    "iso:country":"IT",
    "sg:address":"4, V. Castelvetro 20154 Milano",
    "sg:city":"Milano",
    "sg:classifiers":[
        {
            "category":"Shopping",
            "subcategory":"Stationery & Office Supplies",
            "type":"Retail Goods"
        }
    ],
    "sg:phone":"+39 390 231 1782",
    "sg:postcode":"20154",
    "sg:province":"Milano",
    "sg:tags":[
        "professional"
    ],
    "sg:website":"http://www.archaprogetti.com",
    "wof:name":"Archa Progetti Srl",
    "wof:placetype":"venue"
},
  "geometry": {"coordinates":[9.1628360748,45.4837417603],"type":"Point"}
}