{
  "type": "Feature",
  "properties": {
    "addr:full":"25, Via Ponticelle Tripoli 43022 Montechiarugolo Montechiarugolo Parma 43022",
    "addr:postcode":"43022;43022",
    "addr:street":"Via Ponticelle",
    "iso:country":"IT",
    "sg:address":"25, Via Ponticelle Tripoli 43022 Montechiarugolo",
    "sg:city":"Montechiarugolo",
    "sg:classifiers":[
        {
            "category":"Food & Beverages",
            "subcategory":"Groceries & Convenience Stores",
            "type":"Retail Goods"
        }
    ],
    "sg:phone":"+39 0521 657186",
    "sg:postcode":"43022",
    "sg:province":"Parma",
    "sg:tags":[
        "product",
        "related"
    ],
    "wof:name":"Bertamoni",
    "wof:placetype":"venue"
},
  "geometry": {"coordinates":[10.4177503586,44.724647522],"type":"Point"}
}