{
  "type": "Feature",
  "properties": {
    "addr:full":"5, Viale I Maggio 60020 Sirolo Sirolo Ancona 60020",
    "addr:postcode":"60020;60020",
    "addr:street":"Viale I Maggio",
    "iso:country":"IT",
    "sg:address":"5, Viale I Maggio 60020 Sirolo",
    "sg:city":"Sirolo",
    "sg:classifiers":[
        {
            "category":"Bars & Pubs",
            "subcategory":"Nightclub",
            "type":"Food & Drink"
        }
    ],
    "sg:phone":"+39 071 933 2012",
    "sg:postcode":"60020",
    "sg:province":"Ancona",
    "sg:tags":[
        "cake",
        "bread"
    ],
    "wof:name":"Panificio Aggiornato Del Conero S.r.l.",
    "wof:placetype":"venue"
},
  "geometry": {"coordinates":[13.601489,43.511219],"type":"Point"}
}