{
  "type": "Feature",
  "properties": {
    "iso:country":"IT",
    "sg:address":"20010 Cornaredo",
    "sg:city":"Cornaredo",
    "sg:orig_category":"Termotecnica E Riscaldamento, Apparecchiature E Servizi",
    "sg:phone":"+39 02 9356 1679",
    "sg:postcode":"20010",
    "sg:province":"Milano",
    "wof:name":"Lovato Giuliano",
    "wof:placetype":"venue"
},
  "geometry": {"coordinates":[9.032351,45.503906],"type":"Point"}
}