{
  "type": "Feature",
  "properties": {
    "addr:full":"95127 Catania Catania Catania 95127",
    "addr:postcode":"95127;95127",
    "iso:country":"IT",
    "sg:address":"95127 Catania",
    "sg:city":"Catania",
    "sg:orig_category":"Telecomunicazioni Impianti Ed Apparecchi - Vendita Al Dettaglio",
    "sg:phone":"+39 095 722 3893",
    "sg:postcode":"95127",
    "sg:province":"Catania",
    "sg:website":"http://www.teleglobal.it",
    "wof:name":"Teleglobal Communication Srl",
    "wof:placetype":"venue"
},
  "geometry": {"coordinates":[15.104574,37.5168],"type":"Point"}
}