{
  "type": "Feature",
  "properties": {
    "addr:full":"Via Enrico Fermi 18 30036 Santa Maria Di Sala Santa Maria di Sala Venezia 30036",
    "addr:housenumber":"18",
    "addr:postcode":"30036;30036",
    "addr:street":"Via Enrico Fermi;Maria",
    "iso:country":"IT",
    "sg:address":"Via Enrico Fermi 18 30036 Santa Maria Di Sala",
    "sg:city":"Santa Maria di Sala",
    "sg:classifiers":[
        {
            "category":"Wholesale",
            "subcategory":"Vending Machines",
            "type":"Manufacturing & Wholesale Goods"
        }
    ],
    "sg:phone":"+39 041 486699",
    "sg:postcode":"30036",
    "sg:province":"Venezia",
    "sg:tags":[
        "boring",
        "combined",
        "machines",
        "milling"
    ],
    "sg:website":"www.fptindustrie.com",
    "wof:name":"Fpt Industrie Spa",
    "wof:placetype":"venue"
},
  "geometry": {"coordinates":[12.056946,45.499332],"type":"Point"}
}