{
  "type": "Feature",
  "properties": {
    "iso:country":"IT",
    "sg:address":"41012 Carpi",
    "sg:city":"Carpi",
    "sg:orig_category":"Apparecchiature Pneumatiche Ed Idropneumatiche",
    "sg:phone":"+39 059 698681",
    "sg:postcode":"41012",
    "sg:province":"Modena",
    "sg:website":"http://www.kpm.it",
    "wof:name":"K.p.m. Spa",
    "wof:placetype":"venue"
},
  "geometry": {"coordinates":[10.883286,44.766827],"type":"Point"}
}