{
  "type": "Feature",
  "properties": {
    "iso:country":"IT",
    "sg:address":"20128 Milano",
    "sg:city":"Milano",
    "sg:orig_category":"Scuole E Servizi Scolastici. Ricerca, Selezione E Formazione Del Personale",
    "sg:phone":"+39 02 2700 3948",
    "sg:postcode":"20128",
    "sg:province":"Milano",
    "wof:name":"Rees A. Hugh",
    "wof:placetype":"venue"
},
  "geometry": {"coordinates":[9.232112,45.504974],"type":"Point"}
}