{
  "type": "Feature",
  "properties": {
    "iso:country":"IT",
    "sg:address":"26, Via Prepassa 51017 Pescia",
    "sg:city":"Pescia",
    "sg:classifiers":[
        {
            "category":"Wholesale",
            "subcategory":"Machinery & Supplies",
            "type":"Manufacturing & Wholesale Goods"
        }
    ],
    "sg:phone":"+39 0572 451966",
    "sg:postcode":"51017",
    "sg:province":"Pistoia",
    "sg:tags":[
        "-",
        "agriculture",
        "equipment"
    ],
    "wof:name":"C.m.b. Cotruzioni Meccaniche Braccini",
    "wof:placetype":"venue"
},
  "geometry": {"coordinates":[10.688111,43.882103],"type":"Point"}
}