{
  "type": "Feature",
  "properties": {
    "iso:country":"IT",
    "sg:address":"64, Via Ghisolfa 20010 Cornaredo",
    "sg:city":"Cornaredo",
    "sg:classifiers":[
        {
            "category":"Real Estate",
            "subcategory":"Surveying",
            "type":"Services"
        }
    ],
    "sg:phone":"+39 02 9356 8514",
    "sg:postcode":"20010",
    "sg:province":"Milano",
    "sg:tags":[
        "equipment",
        "material",
        "good",
        "-",
        "handling"
    ],
    "wof:name":"Sea Sistems S.r.l.",
    "wof:placetype":"venue"
},
  "geometry": {"coordinates":[9.032102,45.503117],"type":"Point"}
}