{
  "type": "Feature",
  "properties": {
    "iso:country":"IT",
    "sg:address":"25020 Milzano",
    "sg:city":"Milzano",
    "sg:orig_category":"Arredamenti - Produzione E Ingrosso",
    "sg:phone":"+39 030 952 1196",
    "sg:postcode":"25020",
    "sg:province":"Brescia",
    "wof:name":"Verniciature Industriali Arcobaleno Snc",
    "wof:placetype":"venue"
},
  "geometry": {"coordinates":[10.202912,45.529366],"type":"Point"}
}