{
  "type": "Feature",
  "properties": {
    "iso:country":"IT",
    "sg:address":"70023 Gioia Del Colle",
    "sg:city":"Gioia del Colle",
    "sg:classifiers":[
        {
            "category":"Bars & Pubs",
            "subcategory":"Biergarten",
            "type":"Food & Drink"
        }
    ],
    "sg:phone":"+39 080 348 3014",
    "sg:postcode":"70023",
    "sg:province":"Bari",
    "sg:tags":[
        "birrerie",
        "e"
    ],
    "wof:name":"All'ombra Del Castello Di C. Mancino E V. Losito Snc",
    "wof:placetype":"venue"
},
  "geometry": {"coordinates":[16.888643,40.765903],"type":"Point"}
}