{
  "type": "Feature",
  "properties": {
    "iso:country":"IT",
    "sg:address":"80017 Melito Di Napoli",
    "sg:city":"Melito di Napoli",
    "sg:orig_category":"Macchine Ed Impianti Per Edilizia E Lavori Pubblici. Macchine, Strumenti Ed Apparecchi Per Attivita' Industriali",
    "sg:postcode":"80017",
    "sg:province":"Napoli",
    "wof:name":"La Vitreria",
    "wof:placetype":"venue"
},
  "geometry": {"coordinates":[14.24639,40.916115],"type":"Point"}
}