{
  "type": "Feature",
  "properties": {
    "iso:country":"IT",
    "sg:address":"97100 Ragusa",
    "sg:city":"Ragusa",
    "sg:orig_category":"Abbigliamento - Vendita Al Dettaglio",
    "sg:phone":"+39 0932 220405",
    "sg:postcode":"97100",
    "sg:province":"Ragusa",
    "wof:name":"Biscaldi Modica Giorgia - Eden Moda Jeunesse",
    "wof:placetype":"venue"
},
  "geometry": {"coordinates":[14.730742,36.925213],"type":"Point"}
}