{
  "type": "Feature",
  "properties": {
    "iso:country":"IT",
    "sg:address":"Via Aldo Moro 19 20096 Pioltello",
    "sg:city":"Pioltello",
    "sg:classifiers":[
        {
            "category":"Military Area",
            "subcategory":"Air Force Base",
            "type":"Public Place"
        }
    ],
    "sg:phone":"+39 02 9214 9945",
    "sg:postcode":"20096",
    "sg:province":"Milano",
    "sg:tags":[
        "carbon",
        "activated"
    ],
    "sg:website":"www.comelt.it",
    "wof:name":"Comelt S.r.l.",
    "wof:placetype":"venue"
},
  "geometry": {"coordinates":[9.326269,45.50246],"type":"Point"}
}