{
  "type": "Feature",
  "properties": {
    "iso:country":"IT",
    "sg:address":"Via Porta Antica 55; Cavriana",
    "sg:classifiers":[
        {
            "category":"Banks & Credit Unions",
            "subcategory":"Bank",
            "type":"Services"
        }
    ],
    "sg:phone":"+39 0376 806270",
    "wof:name":"Banca Agricola Mantovana Scarl",
    "wof:placetype":"venue"
},
  "geometry": {"coordinates":[10.598664,45.350494],"type":"Point"}
}