{
  "type": "Feature",
  "properties": {
    "addr:full":"09123 Cagliari Cagliari Cagliari 09123",
    "addr:postcode":"09123;09123",
    "iso:country":"IT",
    "sg:address":"09123 Cagliari",
    "sg:city":"Cagliari",
    "sg:orig_category":"Porti, Darsene E Servizi Portuali",
    "sg:phone":"+39 070 660148",
    "sg:postcode":"09123",
    "sg:province":"Cagliari",
    "wof:name":"Compagnia Lavoratori Portuali Srl",
    "wof:placetype":"venue"
},
  "geometry": {"coordinates":[9.1061124802,39.2137985229],"type":"Point"}
}