{
  "type": "Feature",
  "properties": {
    "addr:full":"2, Via Delle Industrie 30036 Santa Maria Di Sala Santa Maria di Sala Venezia 30036",
    "addr:postcode":"30036;30036",
    "addr:street":"Via Delle Industrie;Maria",
    "iso:country":"IT",
    "sg:address":"2, Via Delle Industrie 30036 Santa Maria Di Sala",
    "sg:city":"Santa Maria di Sala",
    "sg:classifiers":[
        {
            "category":"Wholesale",
            "subcategory":"Drugs",
            "type":"Manufacturing & Wholesale Goods"
        }
    ],
    "sg:phone":"+39 39041486392",
    "sg:postcode":"30036",
    "sg:province":"Venezia",
    "sg:tags":[
        "chemical",
        "pharmaceutical"
    ],
    "wof:name":"Koral (s.r.l.)",
    "wof:placetype":"venue"
},
  "geometry": {"coordinates":[12.016145,45.50832],"type":"Point"}
}