{
  "type": "Feature",
  "properties": {
    "addr:full":"33077 Sacile Sacile Pordenone 33077",
    "addr:postcode":"33077;33077",
    "iso:country":"IT",
    "sg:address":"33077 Sacile",
    "sg:city":"Sacile",
    "sg:orig_category":"Antiquariato",
    "sg:phone":"+39 0434 735792",
    "sg:postcode":"33077",
    "sg:province":"Pordenone",
    "wof:name":"R4 Sas",
    "wof:placetype":"venue"
},
  "geometry": {"coordinates":[12.50069,45.952595],"type":"Point"}
}