{
  "type": "Feature",
  "properties": {
    "iso:country":"IT",
    "sg:address":"8, Via Del Lavoro 22100 Como",
    "sg:city":"Como",
    "sg:classifiers":[
        {
            "category":"Wholesale",
            "subcategory":"Medical Equipment & Supplies",
            "type":"Manufacturing & Wholesale Goods"
        }
    ],
    "sg:phone":"+39 39031525656",
    "sg:postcode":"22100",
    "sg:province":"Como",
    "sg:tags":[
        "-",
        "health",
        "instrument"
    ],
    "wof:name":"Silhouette Italia (s.r.l.)",
    "wof:placetype":"venue"
},
  "geometry": {"coordinates":[9.077864,45.78223],"type":"Point"}
}