{
  "type": "Feature",
  "properties": {
    "addr:full":"Strada Per Amerina 7100 05020 Fornole Terni 05020",
    "addr:housenumber":"7100",
    "addr:postcode":"05020;05020",
    "addr:street":"Strada Per Amerina",
    "iso:country":"IT",
    "sg:address":"Strada Per Amerina 7100 05020 Fornole",
    "sg:classifiers":[
        {
            "category":"Food & Beverages",
            "subcategory":"Liquor & Beverages",
            "type":"Retail Goods"
        }
    ],
    "sg:phone":"+39 0744 989721",
    "sg:postcode":"05020",
    "sg:province":"Terni",
    "sg:tags":[
        "wine",
        "italian"
    ],
    "wof:name":"Cantina Dei Colli Amerini S.c.a.r.l .",
    "wof:placetype":"venue"
},
  "geometry": {"coordinates":[12.646781,42.560219],"type":"Point"}
}