{
  "type": "Feature",
  "properties": {
    "iso:country":"IT",
    "sg:address":"Contrada La Francesca 85028 Rionero In Vulture",
    "sg:city":"Rionero in Vulture",
    "sg:classifiers":[
        {
            "category":"Food & Beverages",
            "subcategory":"Groceries & Convenience Stores",
            "type":"Retail Goods"
        }
    ],
    "sg:phone":"+39 0972 715672",
    "sg:postcode":"85028",
    "sg:province":"Potenza",
    "sg:tags":[
        "drink"
    ],
    "wof:name":"Cutolo Michele & Figli Srl",
    "wof:placetype":"venue"
},
  "geometry": {"coordinates":[15.802221,40.637241],"type":"Point"}
}