{
  "type": "Feature",
  "properties": {
    "addr:full":"11, Via Marconi 10040 Caselette Caselette Torino 10040",
    "addr:postcode":"10040;10040",
    "addr:street":"Via Marconi",
    "iso:country":"IT",
    "sg:address":"11, Via Marconi 10040 Caselette",
    "sg:city":"Caselette",
    "sg:classifiers":[
        {
            "category":"Shopping",
            "type":"Retail Goods"
        }
    ],
    "sg:phone":"+39 011 968 8936",
    "sg:postcode":"10040",
    "sg:province":"Torino",
    "sg:tags":[
        "finished",
        "-",
        "metallic"
    ],
    "wof:name":"Fratelli Zaramella S.n.c",
    "wof:placetype":"venue"
},
  "geometry": {"coordinates":[7.6866188049,45.0705604553],"type":"Point"}
}