{
  "type": "Feature",
  "properties": {
    "iso:country":"IT",
    "sg:address":"47, Via Ludovica 55100 Lucca",
    "sg:city":"Lucca",
    "sg:classifiers":[
        {
            "category":"Wholesale",
            "subcategory":"Drugs",
            "type":"Manufacturing & Wholesale Goods"
        }
    ],
    "sg:phone":"+39 0583 330398",
    "sg:postcode":"55100",
    "sg:province":"Lucca",
    "sg:tags":[
        "chemical",
        "pharmaceutical"
    ],
    "wof:name":"I.t.o. (s.r.l.)",
    "wof:placetype":"venue"
},
  "geometry": {"coordinates":[10.526492,43.910351],"type":"Point"}
}