{
  "type": "Feature",
  "properties": {
    "iso:country":"IT",
    "sg:address":"81024 Maddaloni",
    "sg:city":"Maddaloni",
    "sg:orig_category":"Agenzie Ed Enti Turistici. Consulenze Tecniche, Amministrative E Perizie",
    "sg:phone":"+39 0823 405962",
    "sg:postcode":"81024",
    "sg:province":"Caserta",
    "sg:website":"http://www.dimatteoviaggi.com",
    "wof:name":"Di Matteo Viaggi",
    "wof:placetype":"venue"
},
  "geometry": {"coordinates":[14.383185,41.040375],"type":"Point"}
}