{
  "type": "Feature",
  "properties": {
    "iso:country":"IT",
    "sg:address":"07032 Nulvi",
    "sg:city":"Nulvi",
    "sg:orig_category":"Pubblica Amministrazione",
    "sg:phone":"+39 079 576875",
    "sg:postcode":"07032",
    "sg:province":"Sassari",
    "wof:name":"Ispettorato Ripartimentale Delle Foreste",
    "wof:placetype":"venue"
},
  "geometry": {"coordinates":[8.7430229187,40.7820930481],"type":"Point"}
}