{
  "type": "Feature",
  "properties": {
    "addr:full":"67, Strada Plan Da Tieja 39048 Selva Di Val Gardena Selva Bolzano/Bozen 39048",
    "addr:postcode":"39048;39048",
    "addr:street":"Strada Plan Da Tieja",
    "iso:country":"IT",
    "sg:address":"67, Strada Plan Da Tieja 39048 Selva Di Val Gardena",
    "sg:city":"Selva",
    "sg:classifiers":[
        {
            "category":"Sports & Exercise",
            "subcategory":"Playing Field",
            "type":"Entertainment"
        }
    ],
    "sg:phone":"+39 0471 792233",
    "sg:postcode":"39048",
    "sg:province":"Bolzano/Bozen",
    "sg:tags":[
        "game"
    ],
    "wof:name":"Anri Art S.r.l.",
    "wof:placetype":"venue"
},
  "geometry": {"coordinates":[11.73428,46.560642],"type":"Point"}
}