{
  "type": "Feature",
  "properties": {
    "iso:country":"IT",
    "sg:address":"12062 Cherasco",
    "sg:city":"Cherasco",
    "sg:orig_category":"Termotecnica E Riscaldamento, Apparecchiature E Servizi",
    "sg:phone":"+39 0172 489507",
    "sg:postcode":"12062",
    "sg:province":"Cuneo",
    "wof:name":"M.s. Di Strada Alberto & C. S.a.s.",
    "wof:placetype":"venue"
},
  "geometry": {"coordinates":[7.493925,44.334797],"type":"Point"}
}