{
  "type": "Feature",
  "properties": {
    "iso:country":"IT",
    "sg:address":"73030 Surano",
    "sg:city":"Surano",
    "sg:orig_category":"Graniti",
    "sg:phone":"+39 0836 761685",
    "sg:postcode":"73030",
    "sg:province":"Lecce",
    "wof:name":"La Salentina Marmi Di Bitonti Davide & C. Snc",
    "wof:placetype":"venue"
},
  "geometry": {"coordinates":[18.339754,39.991863],"type":"Point"}
}