{
  "type": "Feature",
  "properties": {
    "addr:full":"12, V. Curiel 20026 Novate Milanese Novate Milanese Milano 20026",
    "addr:housenumber":"12",
    "addr:postcode":"20026;20026",
    "addr:street":"V. Curiel",
    "iso:country":"IT",
    "sg:address":"12, V. Curiel 20026 Novate Milanese",
    "sg:city":"Novate Milanese",
    "sg:classifiers":[
        {
            "category":"Professional",
            "subcategory":"Engineering",
            "type":"Services"
        }
    ],
    "sg:phone":"+39 39023565960",
    "sg:postcode":"20026",
    "sg:province":"Milano",
    "sg:tags":[
        "machine",
        "-",
        "mechanical"
    ],
    "sg:website":"http://www.guarnimac.it:ws_end: :mark:ws:http://www.paginegialle.it/guarnimac",
    "wof:name":"Guarnimac Srl",
    "wof:placetype":"venue"
},
  "geometry": {"coordinates":[9.127819,45.527317],"type":"Point"}
}