{
  "type": "Feature",
  "properties": {
    "addr:full":"21042 Caronno Pertusella Caronno Pertusella Varese 21042",
    "addr:postcode":"21042;pertusella;21042",
    "addr:street":"Pertusella",
    "iso:country":"IT",
    "sg:address":"21042 Caronno Pertusella",
    "sg:city":"Caronno Pertusella",
    "sg:orig_category":"Impiantistica E Prodotti Tecnologici Per Edilizia. Termotecnica E Riscaldamento, Apparecchiature E Servizi",
    "sg:phone":"+39 02 965 8742",
    "sg:postcode":"21042",
    "sg:province":"Varese",
    "wof:name":"Errebi Impianti Gas Di Borsani Raffaele",
    "wof:placetype":"venue"
},
  "geometry": {"coordinates":[9.040473,45.59621],"type":"Point"}
}