{
  "type": "Feature",
  "properties": {
    "addr:full":"00048 Nettuno Nettuno Roma 00048",
    "addr:postcode":"00048;roma 00048",
    "iso:country":"IT",
    "sg:address":"00048 Nettuno",
    "sg:city":"Nettuno",
    "sg:orig_category":"Servizi E Lavori Per Edilizia E Lavori Pubblici. Acqua, Luce, Gas E Societa' Di Esercizio Pubblico",
    "sg:phone":"+39 06 9883 2041",
    "sg:postcode":"00048",
    "sg:province":"Roma",
    "wof:name":"Enel Spa",
    "wof:placetype":"venue"
},
  "geometry": {"coordinates":[12.702022,41.481419],"type":"Point"}
}