{
  "type": "Feature",
  "properties": {
    "addr:full":"20036 Meda Meda Milano 20036",
    "addr:postcode":"20036;20036",
    "iso:country":"IT",
    "sg:address":"20036 Meda",
    "sg:city":"Meda",
    "sg:orig_category":"Trattamenti Termici E Superficiali Metalli, Galvanotecnica",
    "sg:phone":"+39 036 274166",
    "sg:postcode":"20036",
    "sg:province":"Milano",
    "wof:name":"P.m. Di Mariani Alberto E Panzeri Rosy Snc",
    "wof:placetype":"venue"
},
  "geometry": {"coordinates":[9.175211,45.453312],"type":"Point"}
}