{
  "type": "Feature",
  "properties": {
    "addr:full":"34, V. Galilei 20010 Cornaredo Cornaredo Milano 20010",
    "addr:housenumber":"34",
    "addr:postcode":"20010;20010",
    "addr:street":"V. Galilei",
    "iso:country":"IT",
    "sg:address":"34, V. Galilei 20010 Cornaredo",
    "sg:city":"Cornaredo",
    "sg:classifiers":[
        {
            "category":"Shopping",
            "type":"Retail Goods"
        }
    ],
    "sg:phone":"+39 02 9361 3911",
    "sg:postcode":"20010",
    "sg:province":"Milano",
    "sg:tags":[
        "finished",
        "-",
        "metallic"
    ],
    "wof:name":"Fgr Officina Giovanni Radaelli Srl",
    "wof:placetype":"venue"
},
  "geometry": {"coordinates":[9.0359191895,45.4859809875],"type":"Point"}
}