{
  "type": "Feature",
  "properties": {
    "iso:country":"IT",
    "sg:address":"5, Vicolo Cantieri 50056 Capraia E Limite",
    "sg:classifiers":[
        {
            "category":"Shopping",
            "subcategory":"Clothing, Apparel, & Fashions",
            "type":"Retail Goods"
        }
    ],
    "sg:phone":"+39 0571 979328",
    "sg:postcode":"50056",
    "sg:province":"Firenze",
    "sg:tags":[
        "clothes"
    ],
    "wof:name":"Partner - Tex S.a.s.",
    "wof:placetype":"venue"
},
  "geometry": {"coordinates":[11.256902,43.768734],"type":"Point"}
}