{
  "type": "Feature",
  "properties": {
    "iso:country":"IT",
    "sg:address":"3, V. Europa 63020 Monte Vidon Corrado",
    "sg:city":"Monte Vidon Corrado",
    "sg:classifiers":[
        {
            "category":"Shopping",
            "subcategory":"Clothing, Apparel, & Fashions",
            "type":"Retail Goods"
        }
    ],
    "sg:phone":"+39 0734 759413",
    "sg:postcode":"63020",
    "sg:province":"Ascoli Piceno",
    "sg:tags":[
        "clothing",
        "accessory"
    ],
    "sg:website":"http://www.effegi.com",
    "wof:name":"F. & G. Srl",
    "wof:placetype":"venue"
},
  "geometry": {"coordinates":[13.487131,43.120235],"type":"Point"}
}