{
  "type": "Feature",
  "properties": {
    "addr:full":"20020 Arconate Arconate Milano 20020",
    "addr:postcode":"20020;20020",
    "iso:country":"IT",
    "sg:address":"20020 Arconate",
    "sg:city":"Arconate",
    "sg:orig_category":"Prodotti E Manufatti In Materie Plastiche. Articoli Per Imballaggio E Confezionamento",
    "sg:phone":"+39 0331 461218",
    "sg:postcode":"20020",
    "sg:province":"Milano",
    "sg:website":"http://www.callonitex.it",
    "wof:name":"Tessitura Calloni Lino & C. Snc",
    "wof:placetype":"venue"
},
  "geometry": {"coordinates":[8.8479404449,45.5395469666],"type":"Point"}
}