{
  "type": "Feature",
  "properties": {
    "addr:full":"20127 Milano Milano Milano 20127",
    "addr:postcode":"20127;20127",
    "iso:country":"IT",
    "sg:address":"20127 Milano",
    "sg:city":"Milano",
    "sg:orig_category":"Forniture Per Abbigliamento E Pelletterie",
    "sg:phone":"+39 02 284 7073",
    "sg:postcode":"20127",
    "sg:province":"Milano",
    "wof:name":"Miscioscia Rosa",
    "wof:placetype":"venue"
},
  "geometry": {"coordinates":[9.2348871231,45.4998855591],"type":"Point"}
}