{
  "type": "Feature",
  "properties": {
    "iso:country":"IT",
    "sg:address":"Via Spineto 63020 Falerone",
    "sg:city":"Falerone",
    "sg:classifiers":[
        {
            "category":"Professional",
            "subcategory":"Engineering",
            "type":"Services"
        }
    ],
    "sg:phone":"+39 0734 750489",
    "sg:postcode":"63020",
    "sg:province":"Ascoli Piceno",
    "sg:tags":[
        "machine",
        "-",
        "mechanical"
    ],
    "wof:name":"Costruzioni Meccaniche San Marco Di Cippitelli & C. Snc",
    "wof:placetype":"venue"
},
  "geometry": {"coordinates":[13.500969,43.091152],"type":"Point"}
}