{
  "type": "Feature",
  "properties": {
    "iso:country":"IT",
    "sg:address":"38100 Trento",
    "sg:city":"Trento",
    "sg:orig_category":"Autobus, Filobus E Minibus",
    "sg:phone":"+39 0461 993171",
    "sg:postcode":"38100",
    "sg:province":"Trento",
    "wof:name":"Taxibus Soc. Srl",
    "wof:placetype":"venue"
},
  "geometry": {"coordinates":[11.114763,46.108517],"type":"Point"}
}