{
  "type": "Feature",
  "properties": {
    "iso:country":"IT",
    "sg:address":"24030 Palazzago",
    "sg:city":"Palazzago",
    "sg:orig_category":"Forniture Per Agricoltura E Zootecnia",
    "sg:phone":"+39 035 551277",
    "sg:postcode":"24030",
    "sg:province":"Bergamo",
    "wof:name":"C.t.m. (s.a.s.)",
    "wof:placetype":"venue"
},
  "geometry": {"coordinates":[9.5334444046,45.7530250549],"type":"Point"}
}