{
  "type": "Feature",
  "properties": {
    "addr:full":"20144 Milano Milano Milano 20144",
    "addr:postcode":"20144;20144",
    "iso:country":"IT",
    "sg:address":"20144 Milano",
    "sg:city":"Milano",
    "sg:orig_category":"Agenzie D'affari E Servizi Commerciali",
    "sg:phone":"+39 02 466388",
    "sg:postcode":"20144",
    "sg:province":"Milano",
    "wof:name":"Studio Novaresi S.a.s. Di Novaresi Sandra E C.",
    "wof:placetype":"venue"
},
  "geometry": {"coordinates":[9.160935,45.460682],"type":"Point"}
}