{
  "type": "Feature",
  "properties": {
    "addr:full":"25036 Palazzolo Sull'oglio Brescia 25036",
    "addr:postcode":"25036;25036",
    "iso:country":"IT",
    "sg:address":"25036 Palazzolo Sull'oglio",
    "sg:orig_category":"Apparecchiature E Sistemi Per Magazzinaggio E Movimentazione",
    "sg:phone":"+39 030 738 6171",
    "sg:postcode":"25036",
    "sg:province":"Brescia",
    "sg:website":"http://www.aironenoleggi.it",
    "wof:name":"Airone Srl",
    "wof:placetype":"venue"
},
  "geometry": {"coordinates":[9.891188,45.594101],"type":"Point"}
}