{
  "type": "Feature",
  "properties": {
    "addr:full":"24046 Osio Sotto Osio Sotto Bergamo 24046",
    "addr:postcode":"24046;24046",
    "iso:country":"IT",
    "sg:address":"24046 Osio Sotto",
    "sg:city":"Osio Sotto",
    "sg:orig_category":"Telecomunicazioni E Telefonia, Impianti, Apparecchi E Servizi",
    "sg:phone":"+39 035 881128",
    "sg:postcode":"24046",
    "sg:province":"Bergamo",
    "sg:website":"http://www.longhialfredo.it",
    "wof:name":"A.l. Alfredo Longhi Snc Di Longhi A. & C.",
    "wof:placetype":"venue"
},
  "geometry": {"coordinates":[9.587333,45.613022],"type":"Point"}
}