{
  "type": "Feature",
  "properties": {
    "iso:country":"IT",
    "sg:address":"3, Via Caduti 18 Marzo 1945 43019 Soragna",
    "sg:city":"Soragna",
    "sg:classifiers":[
        {
            "category":"Manufacturing",
            "subcategory":"Lumber",
            "type":"Manufacturing & Wholesale Goods"
        }
    ],
    "sg:phone":"+39 0524 597926",
    "sg:postcode":"43019",
    "sg:province":"Parma",
    "sg:tags":[
        "wood"
    ],
    "wof:name":"C.e.im. Packing (s.r.l.)",
    "wof:placetype":"venue"
},
  "geometry": {"coordinates":[10.116984,44.922306],"type":"Point"}
}