{
  "type": "Feature",
  "properties": {
    "iso:country":"IT",
    "sg:address":"56029 S. Croce Sull'arno",
    "sg:orig_category":"Servizi E Lavori Per Abbigliamento E Pelletterie. Arte Ed Artigianato Artistico. Shopping",
    "sg:phone":"+39 0571 34494",
    "sg:postcode":"56029",
    "sg:province":"Pisa",
    "sg:website":"http://www.oliservice.it",
    "wof:name":"Sa.ga.pell. Srl",
    "wof:placetype":"venue"
},
  "geometry": {"coordinates":[10.735492,43.677475],"type":"Point"}
}