{
  "type": "Feature",
  "properties": {
    "addr:full":"16124 Genova Genova Genova 16124",
    "addr:postcode":"16124;16124",
    "iso:country":"IT",
    "sg:address":"16124 Genova",
    "sg:city":"Genova",
    "sg:orig_category":"Valvole E Apparecchiature Di Misura. Forniture Per Attivita' Industriali",
    "sg:phone":"+39 010 247 1728",
    "sg:postcode":"16124",
    "sg:province":"Genova",
    "wof:name":"Ktm Impianti Srl",
    "wof:placetype":"venue"
},
  "geometry": {"coordinates":[8.929543,44.409389],"type":"Point"}
}