{
  "type": "Feature",
  "properties": {
    "addr:full":"10024 Moncalieri Moncalieri Torino 10024",
    "addr:postcode":"10024;10024",
    "iso:country":"IT",
    "sg:address":"10024 Moncalieri",
    "sg:city":"Moncalieri",
    "sg:orig_category":"Prodotti Chimici Secondari. Macchine E Forniture Per Ecologia E Smaltimento Rifiuti",
    "sg:phone":"+39 011 682 9295",
    "sg:postcode":"10024",
    "sg:province":"Torino",
    "sg:website":"http://www.ormatorino.com",
    "wof:name":"Or.ma. Sas Di Mangogna & C.",
    "wof:placetype":"venue"
},
  "geometry": {"coordinates":[7.6699171066,44.9901008606],"type":"Point"}
}