{
  "type": "Feature",
  "properties": {
    "iso:country":"IT",
    "sg:address":"Via Francesca 10 25026 Pontevico",
    "sg:city":"Pontevico",
    "sg:classifiers":[
        {
            "category":"Organizations",
            "subcategory":"Professional Association",
            "type":"Services"
        }
    ],
    "sg:phone":"+39 030 993 0521",
    "sg:postcode":"25026",
    "sg:province":"Brescia",
    "sg:tags":[
        "electrical",
        "systems",
        "electro-planning"
    ],
    "sg:website":"www.roda.it",
    "wof:name":"Roda Spa",
    "wof:placetype":"venue"
},
  "geometry": {"coordinates":[10.110098,45.271164],"type":"Point"}
}