{
  "type": "Feature",
  "properties": {
    "addr:full":"25020 Capriano Del Colle Capriano del Colle Brescia 25020",
    "addr:postcode":"25020;25020",
    "addr:street":"Del Colle",
    "iso:country":"IT",
    "sg:address":"25020 Capriano Del Colle",
    "sg:city":"Capriano del Colle",
    "sg:orig_category":"Utensili - Commercio",
    "sg:phone":"+39 030 974 9009",
    "sg:postcode":"25020",
    "sg:province":"Brescia",
    "wof:name":"Tonoletti Srl",
    "wof:placetype":"venue"
},
  "geometry": {"coordinates":[10.13225,45.475388],"type":"Point"}
}