{
  "type": "Feature",
  "properties": {
    "iso:country":"IT",
    "sg:address":"71036 Lucera",
    "sg:city":"Lucera",
    "sg:orig_category":"Serramenti Ed Infissi",
    "sg:phone":"+39 0881 540060",
    "sg:postcode":"71036",
    "sg:province":"Foggia",
    "wof:name":"R.m.r. Vetreria",
    "wof:placetype":"venue"
},
  "geometry": {"coordinates":[15.543908,41.463463],"type":"Point"}
}