{
  "type": "Feature",
  "properties": {
    "addr:full":"Via Piazzon 94/96; Creazzo",
    "addr:housenumber":"94 / 96",
    "addr:street":"Via Piazzon",
    "iso:country":"IT",
    "sg:address":"Via Piazzon 94/96; Creazzo",
    "sg:classifiers":[
        {
            "category":"Banks & Credit Unions",
            "subcategory":"Bank",
            "type":"Services"
        }
    ],
    "sg:phone":"+39 0444 349696",
    "wof:name":"Banca Antoniana, Popolare Veneta Scarl",
    "wof:placetype":"venue"
},
  "geometry": {"coordinates":[11.493676,45.535595],"type":"Point"}
}