{
  "type": "Feature",
  "properties": {
    "iso:country":"IT",
    "sg:address":"Via Vallancon Nord 55 35045 Ospedaletto Euganeo",
    "sg:city":"Ospedaletto Euganeo",
    "sg:classifiers":[
        {
            "category":"Conference Center",
            "type":"Public Place"
        }
    ],
    "sg:phone":"+39 0429 678411",
    "sg:postcode":"35045",
    "sg:province":"Padova",
    "sg:tags":[
        "plant",
        "stp",
        "treatment",
        "sewage"
    ],
    "sg:website":"www.tecnomil.it",
    "wof:name":"Tecnomil Spa",
    "wof:placetype":"venue"
},
  "geometry": {"coordinates":[11.580151,45.22403],"type":"Point"}
}