{
  "type": "Feature",
  "properties": {
    "iso:country":"IT",
    "sg:address":"57122 Livorno",
    "sg:city":"Livorno",
    "sg:orig_category":"Salotti, Poltrone, Sedie E Tavoli",
    "sg:phone":"+39 0586 884832",
    "sg:postcode":"57122",
    "sg:province":"Livorno",
    "wof:name":"Linea Sedia",
    "wof:placetype":"venue"
},
  "geometry": {"coordinates":[10.31944,43.557213],"type":"Point"}
}