{
  "type": "Feature",
  "properties": {
    "iso:country":"IT",
    "sg:address":"20128 Milano",
    "sg:city":"Milano",
    "sg:orig_category":"Motori Ed Organi Di Trasmissione",
    "sg:phone":"+39 02 2709 3297",
    "sg:postcode":"20128",
    "sg:province":"Milano",
    "sg:website":"http://www.nadella.it",
    "wof:name":"Nadella Spa",
    "wof:placetype":"venue"
},
  "geometry": {"coordinates":[9.2323036194,45.5074081421],"type":"Point"}
}