{
  "type": "Feature",
  "properties": {
    "iso:country":"IT",
    "sg:address":"16, Via Statale 42013 Casalgrande",
    "sg:classifiers":[
        {
            "category":"Professional",
            "subcategory":"Engineering",
            "type":"Services"
        }
    ],
    "sg:phone":"+39 0522 996565",
    "sg:postcode":"42013",
    "sg:province":"Reggio Nell'Emilia",
    "sg:tags":[
        "machine",
        "-",
        "mechanical"
    ],
    "wof:name":"Teknova (s.r.l.)",
    "wof:placetype":"venue"
},
  "geometry": {"coordinates":[10.693129,44.600605],"type":"Point"}
}