{
  "type": "Feature",
  "properties": {
    "addr:full":"10, V. Fornaci 25040 Corte Franca Corte Franca Brescia 25040",
    "addr:housenumber":"10;25040",
    "addr:postcode":"25040",
    "addr:street":"V. Fornaci",
    "iso:country":"IT",
    "sg:address":"10, V. Fornaci 25040 Corte Franca",
    "sg:city":"Corte Franca",
    "sg:classifiers":[
        {
            "category":"Professional",
            "subcategory":"Engineering",
            "type":"Services"
        }
    ],
    "sg:phone":"+39 030 984 7363",
    "sg:postcode":"25040",
    "sg:province":"Brescia",
    "sg:tags":[
        "machine",
        "-",
        "mechanical"
    ],
    "sg:website":"http://www.infoalm.com:ws_end: :mark:ws:http://www.paginegialle.it/almsrl",
    "wof:name":"A.l.m. Srl",
    "wof:placetype":"venue"
},
  "geometry": {"coordinates":[10.018037,45.635208],"type":"Point"}
}