{
  "type": "Feature",
  "properties": {
    "iso:country":"IT",
    "sg:address":"20098 San Giuliano Milanese",
    "sg:city":"San Giuliano Milanese",
    "sg:orig_category":"Macchine, Impianti E Forniture Per Industria Grafica, Cartaria E Cartotecnica",
    "sg:phone":"+39 02 9828 1079",
    "sg:postcode":"20098",
    "sg:province":"Milano",
    "wof:name":"International Expanding Shafts Srl",
    "wof:placetype":"venue"
},
  "geometry": {"coordinates":[9.264573,45.400974],"type":"Point"}
}