{
  "type": "Feature",
  "properties": {
    "addr:full":"Strada Per Gabbricce 13 53035 Monteriggioni Monteriggioni Siena 53035",
    "addr:housenumber":"13",
    "addr:postcode":"53035;53035",
    "addr:street":"Strada Per Gabbricce",
    "iso:country":"IT",
    "sg:address":"Strada Per Gabbricce 13 53035 Monteriggioni",
    "sg:city":"Monteriggioni",
    "sg:classifiers":[
        {
            "category":"Home & Garden",
            "subcategory":"Furniture",
            "type":"Retail Goods"
        }
    ],
    "sg:phone":"+39 0577 304290",
    "sg:postcode":"53035",
    "sg:province":"Siena",
    "sg:tags":[
        "bathroom"
    ],
    "sg:website":"www.lasaidea.com",
    "wof:name":"Lasaidea Spa",
    "wof:placetype":"venue"
},
  "geometry": {"coordinates":[11.330514,43.318661],"type":"Point"}
}