{
  "type": "Feature",
  "properties": {
    "addr:full":"41012 Cortile Cortile Modena 41012",
    "addr:postcode":"41012;41012",
    "addr:street":"Cortile Cortile Modena",
    "iso:country":"IT",
    "sg:address":"41012 Cortile",
    "sg:city":"Cortile",
    "sg:orig_category":"Accessori Moda D'abbigliamento. Shopping",
    "sg:phone":"+39 059 662726",
    "sg:postcode":"41012",
    "sg:province":"Modena",
    "wof:name":"Malavasi Giovanni",
    "wof:placetype":"venue"
},
  "geometry": {"coordinates":[10.969107,44.796124],"type":"Point"}
}