{
  "type": "Feature",
  "properties": {
    "iso:country":"IT",
    "sg:address":"33010 Pagnacco",
    "sg:city":"Pagnacco",
    "sg:orig_category":"Abbigliamento Esterno, Maglierie E Pelliccerie. Calzature, Pelletterie E Pelli. Sport - Articoli E Forniture",
    "sg:phone":"+39 0432 661350",
    "sg:postcode":"33010",
    "sg:province":"Udine",
    "wof:name":"Freschi Riccard",
    "wof:placetype":"venue"
},
  "geometry": {"coordinates":[13.213007,46.102554],"type":"Point"}
}