{
  "type": "Feature",
  "properties": {
    "iso:country":"IT",
    "sg:address":"09012 Capoterra",
    "sg:city":"Capoterra",
    "sg:orig_category":"Marmo, Pietre Ed Affini",
    "sg:phone":"+39 070 720196",
    "sg:postcode":"09012",
    "sg:province":"Cagliari",
    "wof:name":"Cogoni Luciano",
    "wof:placetype":"venue"
},
  "geometry": {"coordinates":[8.990794,39.159882],"type":"Point"}
}