{
  "type": "Feature",
  "properties": {
    "iso:country":"IT",
    "sg:address":"84123 Salerno",
    "sg:city":"Salerno",
    "sg:orig_category":"Assicurazioni E Servizi Assicurativi. Consulenze Tecniche, Amministrative E Perizie",
    "sg:phone":"+39 089 241616",
    "sg:postcode":"84123",
    "sg:province":"Salerno",
    "wof:name":"Prime Consult Sim Spa",
    "wof:placetype":"venue"
},
  "geometry": {"coordinates":[14.769664,40.675774],"type":"Point"}
}