{
  "type": "Feature",
  "properties": {
    "addr:full":"40128 Bologna Bologna Bologna 40128",
    "addr:postcode":"40128;40128",
    "iso:country":"IT",
    "sg:address":"40128 Bologna",
    "sg:city":"Bologna",
    "sg:classifiers":[
        {
            "category":"Professional",
            "subcategory":"Business Services",
            "type":"Services"
        }
    ],
    "sg:phone":"+39 051 362933",
    "sg:postcode":"40128",
    "sg:province":"Bologna",
    "sg:tags":[
        "support",
        "companies",
        "events",
        "trade"
    ],
    "sg:website":"http://www.astonet.it",
    "wof:name":"Vicari Cinzia",
    "wof:placetype":"venue"
},
  "geometry": {"coordinates":[11.349993,44.514412],"type":"Point"}
}