{
  "type": "Feature",
  "properties": {
    "iso:country":"IT",
    "sg:address":"Piazza Dei Mercanti 5; Milano",
    "sg:classifiers":[
        {
            "category":"Banks & Credit Unions",
            "subcategory":"Bank",
            "type":"Services"
        }
    ],
    "sg:phone":"+39 0285081",
    "wof:name":"Banca Popolare Di Lodi",
    "wof:placetype":"venue"
},
  "geometry": {"coordinates":[9.187819,45.464443],"type":"Point"}
}