{
  "type": "Feature",
  "properties": {
    "addr:full":"95047 Paterno' Catania 95047",
    "addr:postcode":"95047;95047",
    "addr:street":"Paterno ' Catania",
    "iso:country":"IT",
    "sg:address":"95047 Paterno'",
    "sg:classifiers":[
        {
            "category":"Health Services",
            "subcategory":"Health Practitioner",
            "type":"Services"
        }
    ],
    "sg:phone":"+39 095 854542",
    "sg:postcode":"95047",
    "sg:province":"Catania",
    "sg:tags":[
        "medici"
    ],
    "wof:name":"Studio Medico Associato Atletes Dr.g.palmisciano",
    "wof:placetype":"venue"
},
  "geometry": {"coordinates":[14.9016075134,37.5613174438],"type":"Point"}
}