{
  "type": "Feature",
  "properties": {
    "iso:country":"IT",
    "sg:address":"95127 Catania",
    "sg:city":"Catania",
    "sg:orig_category":"Prodotti Finiti Stampati. Forniture Per Uffici",
    "sg:phone":"+39 095 387216",
    "sg:postcode":"95127",
    "sg:province":"Catania",
    "wof:name":"Idea Carta Di Indaco Elia",
    "wof:placetype":"venue"
},
  "geometry": {"coordinates":[15.1003513336,37.5185241699],"type":"Point"}
}