{
  "type": "Feature",
  "properties": {
    "iso:country":"IT",
    "sg:address":"Via Colombarotto 1 40026 Imola",
    "sg:city":"Imola",
    "sg:classifiers":[
        {
            "category":"Manufacturing",
            "subcategory":"Rubber & Plastics",
            "type":"Manufacturing & Wholesale Goods"
        }
    ],
    "sg:phone":"+39 0542 640138",
    "sg:postcode":"40026",
    "sg:province":"Bologna",
    "sg:tags":[
        "material"
    ],
    "sg:website":"www.naldivet.it",
    "wof:name":"Naldi Vetroresina Srl",
    "wof:placetype":"venue"
},
  "geometry": {"coordinates":[11.6525630951,44.3993186951],"type":"Point"}
}