{
  "type": "Feature",
  "properties": {
    "iso:country":"IT",
    "sg:address":"Via Quinzano 75 25030 Castelmella",
    "sg:classifiers":[
        {
            "category":"Wholesale",
            "subcategory":"Vending Machines",
            "type":"Manufacturing & Wholesale Goods"
        }
    ],
    "sg:phone":"+39 030 358 3310",
    "sg:postcode":"25030",
    "sg:province":"Brescia",
    "sg:tags":[
        "bending",
        "profile",
        "iron",
        "structural"
    ],
    "sg:website":"www.starbend.it",
    "wof:name":"Star Bend Srl",
    "wof:placetype":"venue"
},
  "geometry": {"coordinates":[10.163651,45.496902],"type":"Point"}
}