{
  "type": "Feature",
  "properties": {
    "iso:country":"IT",
    "sg:address":"15058 Viguzzolo",
    "sg:city":"Viguzzolo",
    "sg:orig_category":"Cartotecnica E Servizi. Prodotti E Manufatti In Materie Plastiche. Articoli Per Imballaggio E Confezionamento",
    "sg:phone":"+39 0131 899294",
    "sg:postcode":"15058",
    "sg:province":"Alessandria",
    "wof:name":"Plastiqua Snc",
    "wof:placetype":"venue"
},
  "geometry": {"coordinates":[8.520532,44.75655],"type":"Point"}
}