{
  "type": "Feature",
  "properties": {
    "addr:full":"4, Via Torquato Tasso 24020 Gorle Gorle Bergamo 24020",
    "addr:postcode":"24020;24020",
    "addr:street":"Via Torquato Tasso",
    "iso:country":"IT",
    "sg:address":"4, Via Torquato Tasso 24020 Gorle",
    "sg:city":"Gorle",
    "sg:classifiers":[
        {
            "category":"Autos & Motor Vehicles",
            "subcategory":"Automobile Sales",
            "type":"Retail Goods"
        }
    ],
    "sg:phone":"+39 39035656888",
    "sg:postcode":"24020",
    "sg:province":"Bergamo",
    "sg:tags":[
        "industrial"
    ],
    "wof:name":"Bergamo Trasmissioni (s.r.l.)",
    "wof:placetype":"venue"
},
  "geometry": {"coordinates":[9.709192,45.705486],"type":"Point"}
}