{
  "type": "Feature",
  "properties": {
    "iso:country":"IT",
    "sg:address":"09126 Cagliari",
    "sg:city":"Cagliari",
    "sg:orig_category":"Lavorazioni Meccaniche E Servizi",
    "sg:phone":"+39 070 306638",
    "sg:postcode":"09126",
    "sg:province":"Cagliari",
    "wof:name":"S.p.i. Snc",
    "wof:placetype":"venue"
},
  "geometry": {"coordinates":[9.1363649368,39.203212738],"type":"Point"}
}