{
  "type": "Feature",
  "properties": {
    "iso:country":"IT",
    "sg:address":"40037 Sasso Marconi",
    "sg:city":"Sasso Marconi",
    "sg:orig_category":"Servizi Per Lo Sport E Il Tempo Libero. Servizi Al Turismo",
    "sg:phone":"+39 051 842805",
    "sg:postcode":"40037",
    "sg:province":"Bologna",
    "wof:name":"Circolo Ippico Valganzole",
    "wof:placetype":"venue"
},
  "geometry": {"coordinates":[11.304977,44.406082],"type":"Point"}
}