{
  "type": "Feature",
  "properties": {
    "addr:full":"Via Marangoni 7 33100 Udine Udine Udine 33100",
    "addr:housenumber":"7",
    "addr:postcode":"33100;33100",
    "addr:street":"Via Marangoni",
    "iso:country":"IT",
    "sg:address":"Via Marangoni 7 33100 Udine",
    "sg:city":"Udine",
    "sg:orig_category":"Brewpub Equipment",
    "sg:phone":"+39 0432 505230",
    "sg:postcode":"33100",
    "sg:province":"Udine",
    "sg:website":"www.cdsudine.it",
    "wof:name":"Cds Di Mulargia G E C Sas",
    "wof:placetype":"venue"
},
  "geometry": {"coordinates":[13.229845,46.055347],"type":"Point"}
}