{
  "type": "Feature",
  "properties": {
    "iso:country":"IT",
    "sg:address":"1, Piazza Giovanni Battista Dall'armi 31044 Montebelluna",
    "sg:city":"Montebelluna",
    "sg:classifiers":[
        {
            "category":"Banks & Credit Unions",
            "subcategory":"Bank",
            "type":"Services"
        }
    ],
    "sg:phone":"+39 39800373797",
    "sg:postcode":"31044",
    "sg:province":"Treviso",
    "sg:tags":[
        "banking",
        "institution"
    ],
    "wof:name":"Veneto Banca S.c.a.r.l.",
    "wof:placetype":"venue"
},
  "geometry": {"coordinates":[12.242072,45.666286],"type":"Point"}
}