{
  "type": "Feature",
  "properties": {
    "iso:country":"IT",
    "sg:address":"20099 Sesto San Giovanni",
    "sg:city":"Sesto San Giovanni",
    "sg:orig_category":"Scuole E Servizi Scolastici. Servizi Per Lo Sport E Il Tempo Libero",
    "sg:phone":"+39 02 240 0881",
    "sg:postcode":"20099",
    "sg:province":"Milano",
    "wof:name":"Nonsolodanza Sas Di Naser Ismail E C.",
    "wof:placetype":"venue"
},
  "geometry": {"coordinates":[9.233284,45.543503],"type":"Point"}
}