{
  "type": "Feature",
  "properties": {
    "addr:full":"Via Maddaloni 95 80134 Napoli Napoli Napoli 80134",
    "addr:housenumber":"95",
    "addr:postcode":"80134;80134",
    "addr:street":"Via Maddaloni",
    "iso:country":"IT",
    "sg:address":"Via Maddaloni 95 80134 Napoli",
    "sg:city":"Napoli",
    "sg:classifiers":[
        {
            "category":"Government",
            "subcategory":"Jail",
            "type":"Public Place"
        }
    ],
    "sg:phone":"+39 081 714 2900",
    "sg:postcode":"80134",
    "sg:province":"Napoli",
    "sg:tags":[
        "planning",
        "designing"
    ],
    "wof:name":"S.t.i.p.e. Spa",
    "wof:placetype":"venue"
},
  "geometry": {"coordinates":[14.2497348785,40.8465766907],"type":"Point"}
}