{
  "type": "Feature",
  "properties": {
    "addr:full":"20145 Milano Milano Milano 20145",
    "addr:postcode":"20145;20145",
    "iso:country":"IT",
    "sg:address":"20145 Milano",
    "sg:city":"Milano",
    "sg:orig_category":"Editoria",
    "sg:phone":"+39 02 498 3002",
    "sg:postcode":"20145",
    "sg:province":"Milano",
    "wof:name":"Euroteam Prod.discografiche Ed.musicali Di Cassano Ferrandi & C. (s.a.s.)",
    "wof:placetype":"venue"
},
  "geometry": {"coordinates":[9.161902,45.476368],"type":"Point"}
}