{
  "type": "Feature",
  "properties": {
    "addr:full":"02046 Magliano Sabina Magliano Sabina Rieti 02046",
    "addr:housenumber":"sabina",
    "addr:postcode":"02046;02046",
    "iso:country":"IT",
    "sg:address":"02046 Magliano Sabina",
    "sg:city":"Magliano Sabina",
    "sg:orig_category":"Ospedali E Servizi Sanitari",
    "sg:phone":"+39 0744 9121",
    "sg:postcode":"02046",
    "sg:province":"Rieti",
    "wof:name":"Ospedale M. Marini",
    "wof:placetype":"venue"
},
  "geometry": {"coordinates":[12.49539,42.364113],"type":"Point"}
}