{
  "type": "Feature",
  "properties": {
    "addr:full":"00043 Ciampino Ciampino Roma 00043",
    "addr:postcode":"00043;roma 00043",
    "iso:country":"IT",
    "sg:address":"00043 Ciampino",
    "sg:city":"Ciampino",
    "sg:classifiers":[
        {
            "category":"Health Services",
            "subcategory":"Health Practitioner",
            "type":"Services"
        }
    ],
    "sg:phone":"+39 06 796 1087",
    "sg:postcode":"00043",
    "sg:province":"Roma",
    "sg:tags":[
        "medici"
    ],
    "wof:name":"Bonomo Alberto",
    "wof:placetype":"venue"
},
  "geometry": {"coordinates":[12.609218,41.796139],"type":"Point"}
}