{
  "type": "Feature",
  "properties": {
    "iso:country":"IT",
    "sg:address":"20128 Milano",
    "sg:city":"Milano",
    "sg:orig_category":"Elettronica Professionale E Di Consumo. Automazione E Macchine Per Ufficio. Forniture Per Congressi, Fiere E Manifestazioni",
    "sg:phone":"+39 02 255 0650",
    "sg:postcode":"20128",
    "sg:province":"Milano",
    "wof:name":"La Favelliana S.n.c. Di G. Varisco & C.",
    "wof:placetype":"venue"
},
  "geometry": {"coordinates":[9.229133,45.51041],"type":"Point"}
}