{
  "type": "Feature",
  "properties": {
    "addr:full":"73100 Lecce Lecce Lecce 73100",
    "addr:postcode":"73100;73100",
    "iso:country":"IT",
    "sg:address":"73100 Lecce",
    "sg:city":"Lecce",
    "sg:orig_category":"Cartotecnica E Servizi. Forniture Per Uffici",
    "sg:phone":"+39 0832 453135",
    "sg:postcode":"73100",
    "sg:province":"Lecce",
    "wof:name":"Samu Srl",
    "wof:placetype":"venue"
},
  "geometry": {"coordinates":[18.187117,40.356552],"type":"Point"}
}