{
  "type": "Feature",
  "properties": {
    "iso:country":"IT",
    "sg:address":"Via Mambretti Antonio 9 20157 Milano",
    "sg:city":"Milano",
    "sg:classifiers":[
        {
            "category":"Wholesale",
            "subcategory":"Auto Parts",
            "type":"Manufacturing & Wholesale Goods"
        }
    ],
    "sg:phone":"+39 02 3900 3125",
    "sg:postcode":"20157",
    "sg:province":"Milano",
    "sg:tags":[
        "engine",
        "spare",
        "diesel"
    ],
    "sg:website":"www.gbmspa.com",
    "wof:name":"Gbm Compagnia Finanziaria Commerciale Spa",
    "wof:placetype":"venue"
},
  "geometry": {"coordinates":[9.203226,45.482468],"type":"Point"}
}