{
  "type": "Feature",
  "properties": {
    "iso:country":"IT",
    "sg:address":"16137 Genova",
    "sg:city":"Genova",
    "sg:orig_category":"Articoli Da Regalo. Hobbistica. Shopping",
    "sg:phone":"+39 010 875917",
    "sg:postcode":"16137",
    "sg:province":"Genova",
    "wof:name":"Valle Laura Lina",
    "wof:placetype":"venue"
},
  "geometry": {"coordinates":[8.951253,44.409824],"type":"Point"}
}