{
  "type": "Feature",
  "properties": {
    "iso:country":"IT",
    "sg:address":"20016 Pero",
    "sg:city":"Pero",
    "sg:orig_category":"Magazzinaggio E Logistica Industriale - Impianti Ed Attrezzature",
    "sg:phone":"+39 02 358 0156",
    "sg:postcode":"20016",
    "sg:province":"Milano",
    "wof:name":"Alma Italia Srl",
    "wof:placetype":"venue"
},
  "geometry": {"coordinates":[9.09489,45.513428],"type":"Point"}
}