{
  "type": "Feature",
  "properties": {
    "iso:country":"IT",
    "sg:address":"00185 Roma",
    "sg:city":"Roma",
    "sg:orig_category":"Elettrotecnica Professionale E Di Consumo. Forniture Per Attivita' Commerciali Ed Artigianali",
    "sg:phone":"+39 06 7049 4987",
    "sg:postcode":"00185",
    "sg:province":"Roma",
    "wof:name":"D.b. Srl",
    "wof:placetype":"venue"
},
  "geometry": {"coordinates":[12.5111083984,41.8875465393],"type":"Point"}
}