{
  "type": "Feature",
  "properties": {
    "addr:full":"20099 Sesto San Giovanni Sesto San Giovanni Milano 20099",
    "addr:postcode":"20099;20099",
    "iso:country":"IT",
    "sg:address":"20099 Sesto San Giovanni",
    "sg:city":"Sesto San Giovanni",
    "sg:orig_category":"Ospedali E Servizi Sanitari. Servizi Sociali",
    "sg:phone":"+39 02 240 4700",
    "sg:postcode":"20099",
    "sg:province":"Milano",
    "wof:name":"Associazione Casa Sunem Onlus",
    "wof:placetype":"venue"
},
  "geometry": {"coordinates":[9.225585,45.533337],"type":"Point"}
}