{
  "type": "Feature",
  "properties": {
    "iso:country":"IT",
    "sg:address":"67010 L'aquila",
    "sg:orig_category":"Macchine, Impianti Ed Attrezzature Per Agricoltura E Zootecnia. Macchine Ed Impianti Per Edilizia E Lavori Pubblici",
    "sg:phone":"+39 0862 445053",
    "sg:postcode":"67010",
    "sg:province":"L'Aquila",
    "wof:name":"Ciancarella Luciano",
    "wof:placetype":"venue"
},
  "geometry": {"coordinates":[13.454921,42.338322],"type":"Point"}
}