{
  "type": "Feature",
  "properties": {
    "addr:full":"Via Adige 66020 San Giovanni Teatino San Giovanni Teatino Chieti 66020",
    "addr:postcode":"66020;66020",
    "addr:street":"Via Adige",
    "iso:country":"IT",
    "sg:address":"Via Adige 66020 San Giovanni Teatino",
    "sg:city":"San Giovanni Teatino",
    "sg:classifiers":[
        {
            "category":"Home & Garden",
            "subcategory":"Home Furnishings",
            "type":"Retail Goods"
        }
    ],
    "sg:phone":"+39 085 446 0456",
    "sg:postcode":"66020",
    "sg:province":"Chieti",
    "sg:tags":[
        "household"
    ],
    "wof:name":"Arredamenti Mammarella Roberto E C. S.r.l.",
    "wof:placetype":"venue"
},
  "geometry": {"coordinates":[14.168201,42.418415],"type":"Point"}
}