{
  "type": "Feature",
  "properties": {
    "iso:country":"IT",
    "sg:address":"Via S. Lucia Superiore 4 84091 Battipaglia",
    "sg:city":"Battipaglia",
    "sg:classifiers":[
        {
            "category":"Farming",
            "subcategory":"Fish & Marine Products",
            "type":"Manufacturing & Wholesale Goods"
        }
    ],
    "sg:phone":"+39 0828 671404",
    "sg:postcode":"84091",
    "sg:province":"Salerno",
    "sg:tags":[
        "herbal",
        "herb"
    ],
    "sg:website":"www.ragogroup.com",
    "wof:name":"Rago Gaetano Azienda Agricola",
    "wof:placetype":"venue"
},
  "geometry": {"coordinates":[14.765912,40.677956],"type":"Point"}
}