{
  "type": "Feature",
  "properties": {
    "addr:full":"55, Via Ponti Ettore 20143 Milano Milano Milano 20143",
    "addr:postcode":"20143;20143",
    "addr:street":"Via Ponti Ettore",
    "iso:country":"IT",
    "sg:address":"55, Via Ponti Ettore 20143 Milano",
    "sg:city":"Milano",
    "sg:classifiers":[
        {
            "category":"Professional",
            "subcategory":"Engineering",
            "type":"Services"
        }
    ],
    "sg:phone":"+39 39028135725",
    "sg:postcode":"20143",
    "sg:province":"Milano",
    "sg:tags":[
        "machine",
        "-",
        "mechanical"
    ],
    "wof:name":"Air Industrie Systemes (s.p.a.)",
    "wof:placetype":"venue"
},
  "geometry": {"coordinates":[9.1561,45.44252],"type":"Point"}
}