{
  "type": "Feature",
  "properties": {
    "iso:country":"IT",
    "sg:address":"00198 Roma",
    "sg:city":"Roma",
    "sg:orig_category":"Studi E Consulenze Legali E Notarili. Avvocati, Notai E Servizi Legali. Professionisti - Studi E Servizi Ed Associazioni Di Interesse Aziendale",
    "sg:phone":"+39 06 841 9669",
    "sg:postcode":"00198",
    "sg:province":"Roma",
    "wof:name":"S & G Servizi",
    "wof:placetype":"venue"
},
  "geometry": {"coordinates":[12.49533,41.924469],"type":"Point"}
}