{
  "type": "Feature",
  "properties": {
    "iso:country":"IT",
    "sg:address":"Via Mascagni 12 22032 Albese",
    "sg:classifiers":[
        {
            "category":"Wholesale",
            "subcategory":"Office Equipment",
            "type":"Manufacturing & Wholesale Goods"
        }
    ],
    "sg:phone":"+39 031 427717",
    "sg:postcode":"22032",
    "sg:province":"Como",
    "sg:tags":[
        "manufacture",
        "cd-rom"
    ],
    "sg:website":"www.meroni.it",
    "wof:name":"Meroni Editrice Snc",
    "wof:placetype":"venue"
},
  "geometry": {"coordinates":[9.154379,45.792263],"type":"Point"}
}