{
  "type": "Feature",
  "properties": {
    "iso:country":"IT",
    "sg:address":"36027 Rosa'",
    "sg:orig_category":"Carni, Salumi E Pesci",
    "sg:phone":"+39 0424 581467",
    "sg:postcode":"36027",
    "sg:province":"Vicenza",
    "wof:name":"Tre.bi Srl",
    "wof:placetype":"venue"
},
  "geometry": {"coordinates":[11.758925,45.725948],"type":"Point"}
}