{
  "type": "Feature",
  "properties": {
    "iso:country":"IT",
    "sg:address":"86100 Campobasso",
    "sg:city":"Campobasso",
    "sg:orig_category":"Servizi Vari Di Interesse Pubblico",
    "sg:phone":"+39 0874 65652",
    "sg:postcode":"86100",
    "sg:province":"Campobasso",
    "wof:name":"Milesi Roberto",
    "wof:placetype":"venue"
},
  "geometry": {"coordinates":[14.670443,41.577084],"type":"Point"}
}