{
  "type": "Feature",
  "properties": {
    "addr:full":"35127 Padova Padova Padova 35127",
    "addr:postcode":"35127;35127",
    "iso:country":"IT",
    "sg:address":"35127 Padova",
    "sg:city":"Padova",
    "sg:orig_category":"Motori Ed Organi Di Trasmissione",
    "sg:phone":"+39 049 870 5277",
    "sg:postcode":"35127",
    "sg:province":"Padova",
    "wof:name":"Ricambi Autotreno Srl",
    "wof:placetype":"venue"
},
  "geometry": {"coordinates":[11.9231367111,45.3534545898],"type":"Point"}
}