{
  "type": "Feature",
  "properties": {
    "addr:full":"50050 Cerreto Guidi Bassa Firenze 50050",
    "addr:postcode":"50050;50050",
    "iso:country":"IT",
    "sg:address":"50050 Cerreto Guidi",
    "sg:city":"Bassa",
    "sg:orig_category":"Prodotti E Manufatti In Materie Plastiche. Articoli Per Imballaggio E Confezionamento",
    "sg:phone":"+39 0571 581070",
    "sg:postcode":"50050",
    "sg:province":"Firenze",
    "wof:name":"Vetroresina Toscana Snc",
    "wof:placetype":"venue"
},
  "geometry": {"coordinates":[10.8812227249,43.7222595215],"type":"Point"}
}