{
  "type": "Feature",
  "properties": {
    "iso:country":"IT",
    "sg:address":"20149 Milano",
    "sg:city":"Milano",
    "sg:orig_category":"Servizi Editoriali. Pubblicita', Marketing E Comunicazione",
    "sg:phone":"+39 02 345 1276",
    "sg:postcode":"20149",
    "sg:province":"Milano",
    "wof:name":"Pubblicando Srl",
    "wof:placetype":"venue"
},
  "geometry": {"coordinates":[9.153391,45.485851],"type":"Point"}
}