{
  "type": "Feature",
  "properties": {
    "iso:country":"IT",
    "sg:address":"50, Via Sicilia 00187 Roma",
    "sg:city":"Roma",
    "sg:classifiers":[
        {
            "category":"Airport",
            "subcategory":"General Aviation",
            "type":"Transportation"
        }
    ],
    "sg:phone":"+39 06 4288 5140",
    "sg:postcode":"00187",
    "sg:province":"Roma",
    "sg:tags":[
        "transport",
        "air"
    ],
    "wof:name":"Ghana Airways Corporation",
    "wof:placetype":"venue"
},
  "geometry": {"coordinates":[12.495403,41.909595],"type":"Point"}
}