{
  "type": "Feature",
  "properties": {
    "iso:country":"IT",
    "sg:address":"179, Corso Marconi 17014 Cairo Montenotte",
    "sg:city":"Cairo Montenotte",
    "sg:classifiers":[
        {
            "category":"Professional",
            "subcategory":"Engineering",
            "type":"Services"
        }
    ],
    "sg:phone":"+39 39019510315",
    "sg:postcode":"17014",
    "sg:province":"Savona",
    "sg:tags":[
        "machine",
        "-",
        "mechanical"
    ],
    "wof:name":"Campini S.n.c.",
    "wof:placetype":"venue"
},
  "geometry": {"coordinates":[8.32546,44.365402],"type":"Point"}
}