{
  "type": "Feature",
  "properties": {
    "addr:full":"00055 Ladispoli Ladispoli Roma 00055",
    "addr:postcode":"00055;roma 00055",
    "iso:country":"IT",
    "sg:address":"00055 Ladispoli",
    "sg:city":"Ladispoli",
    "sg:orig_category":"Ricambi E Componenti Dei Mezzi Di Trasporto",
    "sg:phone":"+39 06 994 8561",
    "sg:postcode":"00055",
    "sg:province":"Roma",
    "wof:name":"C.r.a. Srl",
    "wof:placetype":"venue"
},
  "geometry": {"coordinates":[12.71157,41.975922],"type":"Point"}
}