{
  "type": "Feature",
  "properties": {
    "iso:country":"IT",
    "sg:address":"Via San Benigno 3 20133 Milano",
    "sg:city":"Milano",
    "sg:classifiers":[
        {
            "category":"Building & Trades",
            "subcategory":"Electrical",
            "type":"Services"
        }
    ],
    "sg:phone":"+39 02 7012 2656",
    "sg:postcode":"20133",
    "sg:province":"Milano",
    "sg:tags":[
        "installation",
        "export"
    ],
    "wof:name":"Xonox S.r.l.",
    "wof:placetype":"venue"
},
  "geometry": {"coordinates":[8.39892,45.462345],"type":"Point"}
}