{
  "type": "Feature",
  "properties": {
    "iso:country":"IT",
    "sg:address":"16017 Isola Del Cantone",
    "sg:city":"Isola del Cantone",
    "sg:orig_category":"Acciaierie E Fonderie",
    "sg:phone":"+39 010 963 6041",
    "sg:postcode":"16017",
    "sg:province":"Genova",
    "wof:name":"Fonderie Cavalleri E C. (s.p.a.)",
    "wof:placetype":"venue"
},
  "geometry": {"coordinates":[8.957612,44.642868],"type":"Point"}
}