{
  "type": "Feature",
  "properties": {
    "iso:country":"IT",
    "sg:address":"10134 Torino",
    "sg:city":"Torino",
    "sg:orig_category":"Modellismo",
    "sg:phone":"+39 011 316 1369",
    "sg:postcode":"10134",
    "sg:province":"Torino",
    "wof:name":"Si.te. Di Russo Mario",
    "wof:placetype":"venue"
},
  "geometry": {"coordinates":[7.6596951485,45.0402793884],"type":"Point"}
}