{
  "type": "Feature",
  "properties": {
    "iso:country":"IT",
    "sg:address":"20010 Inveruno",
    "sg:city":"Inveruno",
    "sg:orig_category":"Macchine Utensili E Impianti",
    "sg:phone":"+39 02 9728 9789",
    "sg:postcode":"20010",
    "sg:province":"Milano",
    "wof:name":"Punching Services Di Caccia Laura E C. Snc",
    "wof:placetype":"venue"
},
  "geometry": {"coordinates":[9.204,45.454411],"type":"Point"}
}