{
  "type": "Feature",
  "properties": {
    "iso:country":"IT",
    "sg:address":"1, Localita' Sassonia 28885 Piedimulera",
    "sg:city":"Piedimulera",
    "sg:classifiers":[
        {
            "category":"Real Estate",
            "subcategory":"Architect",
            "type":"Services"
        }
    ],
    "sg:phone":"+39 39032483454",
    "sg:postcode":"28885",
    "sg:province":"Verbano-Cusio-Ossola",
    "sg:tags":[
        "textile",
        "clothing"
    ],
    "wof:name":"Marta Confezioni Srl",
    "wof:placetype":"venue"
},
  "geometry": {"coordinates":[8.272465,46.139969],"type":"Point"}
}