{
  "type": "Feature",
  "properties": {
    "iso:country":"IT",
    "sg:address":"94017 Regalbuto",
    "sg:city":"Regalbuto",
    "sg:orig_category":"Abiti Da Lavoro Ed Indumenti Protettivi",
    "sg:phone":"+39 0935 71144",
    "sg:postcode":"94017",
    "sg:province":"Enna",
    "wof:name":"Milla Srl",
    "wof:placetype":"venue"
},
  "geometry": {"coordinates":[11.282464,45.737144],"type":"Point"}
}