{
  "type": "Feature",
  "properties": {
    "iso:country":"IT",
    "sg:address":"Via Mongibello 101 95032 Belpasso",
    "sg:city":"Belpasso",
    "sg:classifiers":[
        {
            "category":"Bus Stop",
            "subcategory":"None",
            "type":"Transportation"
        }
    ],
    "sg:phone":"+39 095 713 1170",
    "sg:postcode":"95032",
    "sg:province":"Catania",
    "sg:tags":[
        "filter"
    ],
    "sg:website":"www.promes-filtri.it",
    "wof:name":"Promes Srl",
    "wof:placetype":"venue"
},
  "geometry": {"coordinates":[15.0122289658,37.5298347473],"type":"Point"}
}