{
  "type": "Feature",
  "properties": {
    "addr:full":"20040 Busnago Busnago Milano 20040",
    "addr:postcode":"20040;20040",
    "iso:country":"IT",
    "sg:address":"20040 Busnago",
    "sg:city":"Busnago",
    "sg:orig_category":"Forniture Per Attivita' Industriali",
    "sg:postcode":"20040",
    "sg:province":"Milano",
    "wof:name":"Hercules Italia (s.p.a.)",
    "wof:placetype":"venue"
},
  "geometry": {"coordinates":[9.4574785233,45.6024055481],"type":"Point"}
}