{
  "type": "Feature",
  "properties": {
    "addr:full":"20124 Milano Milano Milano 20124",
    "addr:postcode":"20124;20124",
    "iso:country":"IT",
    "sg:address":"20124 Milano",
    "sg:city":"Milano",
    "sg:orig_category":"Macchine, Impianti Ed Attrezzature Per Abbigliamento E Pelletterie",
    "sg:phone":"+39 02 2951 6013",
    "sg:postcode":"20124",
    "sg:province":"Milano",
    "wof:name":"Singer Italia S.p.a.",
    "wof:placetype":"venue"
},
  "geometry": {"coordinates":[9.206568,45.475979],"type":"Point"}
}