{
  "type": "Feature",
  "properties": {
    "iso:country":"IT",
    "sg:address":"16035 Rapallo",
    "sg:city":"Rapallo",
    "sg:orig_category":"Prodotti Cosmetici E Da Toeletta",
    "sg:phone":"+39 0185 263216",
    "sg:postcode":"16035",
    "sg:province":"Genova",
    "wof:name":"Castiglione Salvatore",
    "wof:placetype":"venue"
},
  "geometry": {"coordinates":[9.2231388092,44.3747825623],"type":"Point"}
}