{
  "type": "Feature",
  "properties": {
    "iso:country":"IT",
    "sg:address":"10156 Torino",
    "sg:city":"Torino",
    "sg:orig_category":"Pneumatici - Commercio E Riparazione",
    "sg:phone":"+39 011 273 2420",
    "sg:postcode":"10156",
    "sg:province":"Torino",
    "wof:name":"Montegrosso Francesco & C.",
    "wof:placetype":"venue"
},
  "geometry": {"coordinates":[7.7061495781,45.1193466187],"type":"Point"}
}