{
  "type": "Feature",
  "properties": {
    "iso:country":"IT",
    "sg:address":"1, Piazza Molineri 12038 Savigliano",
    "sg:city":"Savigliano",
    "sg:classifiers":[
        {
            "category":"Wholesale",
            "subcategory":"Machinery & Supplies",
            "type":"Manufacturing & Wholesale Goods"
        }
    ],
    "sg:phone":"+39 0172 716444",
    "sg:postcode":"12038",
    "sg:province":"Cuneo",
    "sg:tags":[
        "-",
        "agriculture",
        "equipment"
    ],
    "wof:name":"Dima Italia S.p.a.",
    "wof:placetype":"venue"
},
  "geometry": {"coordinates":[7.65859,44.646923],"type":"Point"}
}