{
  "type": "Feature",
  "properties": {
    "iso:country":"IT",
    "sg:address":"Via Helsinki 12a 50018 Scandicci",
    "sg:city":"Scandicci",
    "sg:orig_category":"Hoisiery Goods",
    "sg:phone":"+39 055 72181",
    "sg:postcode":"50018",
    "sg:province":"Firenze",
    "wof:name":"Maglificio Fiesole Spa",
    "wof:placetype":"venue"
},
  "geometry": {"coordinates":[11.155666,43.761925],"type":"Point"}
}