{
  "type": "Feature",
  "properties": {
    "iso:country":"IT",
    "sg:address":"06077 Perugia",
    "sg:orig_category":"Trasporti E Spedizioni Merci",
    "sg:phone":"+39 075 591 3921",
    "sg:province":"PG",
    "sg:website":"http://www.robertopaciotti.com",
    "wof:name":"Paciotti Trasporti Sas",
    "wof:placetype":"venue"
},
  "geometry": {"coordinates":[-72.259399,41.993801],"type":"Point"}
}