{
  "type": "Feature",
  "properties": {
    "addr:full":"85025 Melfi Melfi Potenza 85025",
    "addr:postcode":"85025;85025",
    "iso:country":"IT",
    "sg:address":"85025 Melfi",
    "sg:city":"Melfi",
    "sg:orig_category":"Motori Ed Organi Di Trasmissione. Ricambi E Componenti Dei Mezzi Di Trasporto",
    "sg:phone":"+39 0972 78426",
    "sg:postcode":"85025",
    "sg:province":"Potenza",
    "wof:name":"Magneti Marelli S.p.a.direzione Sistemi Di Scarico",
    "wof:placetype":"venue"
},
  "geometry": {"coordinates":[15.6412525177,41.0444831848],"type":"Point"}
}