{
  "type": "Feature",
  "properties": {
    "addr:full":"45021 Badia Polesine Badia Polesine Rovigo 45021",
    "addr:postcode":"45021;45021",
    "iso:country":"IT",
    "sg:address":"45021 Badia Polesine",
    "sg:city":"Badia Polesine",
    "sg:orig_category":"Servizi E Lavori Per Agricoltura E Zootecnia. Servizi Ausiliari Di Analisi, Controllo E Ricerca",
    "sg:phone":"+39 0425 51405",
    "sg:postcode":"45021",
    "sg:province":"Rovigo",
    "wof:name":"Istituto Sperimentale Per La Cerealicoltura",
    "wof:placetype":"venue"
},
  "geometry": {"coordinates":[11.491412,45.09354],"type":"Point"}
}