{
  "type": "Feature",
  "properties": {
    "addr:full":"83, Corso Lodi 20139 Milano Milano Milano 20139",
    "addr:postcode":"20139;20139",
    "addr:street":"Corso Lodi",
    "iso:country":"IT",
    "sg:address":"83, Corso Lodi 20139 Milano",
    "sg:city":"Milano",
    "sg:classifiers":[
        {
            "category":"Shopping",
            "subcategory":"Crafts & Fabrics",
            "type":"Retail Goods"
        }
    ],
    "sg:phone":"+39 02 5521 2494",
    "sg:postcode":"20139",
    "sg:province":"Milano",
    "wof:name":"Corit Soc. Coop. A R.l.",
    "wof:placetype":"venue"
},
  "geometry": {"coordinates":[9.2029352188,45.4517211914],"type":"Point"}
}