{
  "type": "Feature",
  "properties": {
    "iso:country":"IT",
    "sg:address":"Borgata San Grato 1 10080 Oglianico",
    "sg:city":"Oglianico",
    "sg:classifiers":[
        {
            "category":"Manufacturing",
            "subcategory":"Motor Vehicles & Parts",
            "type":"Manufacturing & Wholesale Goods"
        }
    ],
    "sg:phone":"+39 0124 34446",
    "sg:postcode":"10080",
    "sg:province":"Torino",
    "sg:tags":[
        "industry",
        "metallurgical",
        "vendor"
    ],
    "wof:name":"Commec + B.l. S.r.l.",
    "wof:placetype":"venue"
},
  "geometry": {"coordinates":[7.647056,45.327942],"type":"Point"}
}