{
  "type": "Feature",
  "properties": {
    "iso:country":"IT",
    "sg:address":"20068 Peschiera Borromeo",
    "sg:city":"Peschiera Borromeo",
    "sg:classifiers":[
        {
            "category":"Professional",
            "subcategory":"Accounting & Tax Preparation",
            "type":"Services"
        }
    ],
    "sg:phone":"+39 02 5530 3670",
    "sg:postcode":"20068",
    "sg:province":"Milano",
    "sg:tags":[
        "control",
        "climate",
        "equipment",
        "refrigeration",
        "conditioning",
        "services"
    ],
    "wof:name":"Comfrigo Srl",
    "wof:placetype":"venue"
},
  "geometry": {"coordinates":[9.286185,45.429523],"type":"Point"}
}