{
  "type": "Feature",
  "properties": {
    "iso:country":"IT",
    "sg:address":"88, Corso Vincenzo Bellini 95013 Fiumefreddo Di Sicilia",
    "sg:city":"Fiumefreddo di Sicilia",
    "sg:classifiers":[
        {
            "category":"Building & Trades",
            "subcategory":"Construction",
            "type":"Services"
        }
    ],
    "sg:phone":"+39 39095642188",
    "sg:postcode":"95013",
    "sg:province":"Catania",
    "sg:tags":[
        "work",
        "public"
    ],
    "wof:name":"P.p.p. S.r.l.",
    "wof:placetype":"venue"
},
  "geometry": {"coordinates":[15.210939,37.790497],"type":"Point"}
}