{
  "type": "Feature",
  "properties": {
    "addr:full":"10098 Rivoli Rivoli Torino 10098",
    "addr:postcode":"10098;10098",
    "iso:country":"IT",
    "sg:address":"10098 Rivoli",
    "sg:city":"Rivoli",
    "sg:orig_category":"Imprese Pulizia",
    "sg:phone":"+39 011 953 2984",
    "sg:postcode":"10098",
    "sg:province":"Torino",
    "wof:name":"La Dinamica",
    "wof:placetype":"venue"
},
  "geometry": {"coordinates":[7.567812,45.063744],"type":"Point"}
}