{
  "type": "Feature",
  "properties": {
    "iso:country":"IT",
    "sg:address":"15100 Alessandria",
    "sg:city":"Alessandria",
    "sg:orig_category":"Non-classified Establishments",
    "sg:phone":"+39 0131 288231",
    "sg:postcode":"15100",
    "sg:province":"Alessandria",
    "wof:name":"Color Case Di Massarino Federico",
    "wof:placetype":"venue"
},
  "geometry": {"coordinates":[8.71055,44.910763],"type":"Point"}
}