{
  "type": "Feature",
  "properties": {
    "addr:full":"10142 Torino Torino Torino 10142",
    "addr:postcode":"10142;10142",
    "iso:country":"IT",
    "sg:address":"10142 Torino",
    "sg:city":"Torino",
    "sg:orig_category":"Pompe. Ricambi E Componenti Dei Mezzi Di Trasporto",
    "sg:phone":"+39 011 707 0344",
    "sg:postcode":"10142",
    "sg:province":"Torino",
    "wof:name":"Tecnodiesel Torino Sas",
    "wof:placetype":"venue"
},
  "geometry": {"coordinates":[7.6152319908,45.0683174133],"type":"Point"}
}