{
  "type": "Feature",
  "properties": {
    "iso:country":"IT",
    "sg:address":"28, Via Cesare Battisti 52021 Bucine",
    "sg:city":"Bucine",
    "sg:classifiers":[
        {
            "category":"Manufacturing",
            "subcategory":"Metals",
            "type":"Manufacturing & Wholesale Goods"
        }
    ],
    "sg:phone":"+39 055 978 8657",
    "sg:postcode":"52021",
    "sg:province":"Arezzo",
    "sg:tags":[
        "metallurgy",
        "metalworking"
    ],
    "wof:name":"Oro Piu' (s.r.l.)",
    "wof:placetype":"venue"
},
  "geometry": {"coordinates":[11.61328125,43.499294281],"type":"Point"}
}