{
  "type": "Feature",
  "properties": {
    "iso:country":"IT",
    "sg:address":"33048 San Giovanni Al Natisone",
    "sg:city":"San Giovanni al Natisone",
    "sg:orig_category":"Non-classified Establishments",
    "sg:phone":"+39 0432 757533",
    "sg:postcode":"33048",
    "sg:province":"Udine",
    "wof:name":"Essedi Proposte D'arredo Di Pagano Saverio & C. S.a.s.",
    "wof:placetype":"venue"
},
  "geometry": {"coordinates":[13.380242,45.987869],"type":"Point"}
}