{
  "type": "Feature",
  "properties": {
    "iso:country":"IT",
    "sg:address":"00166 Roma",
    "sg:city":"Roma",
    "sg:orig_category":"Forniture Per Attivita' Commerciali Ed Artigianali. Arredi Ed Attrezzature Per Attivita' Commerciali Ed Artigianali",
    "sg:phone":"+39 06 6152 0062",
    "sg:postcode":"00166",
    "sg:province":"Roma",
    "wof:name":"Forum Sport Shop Srl",
    "wof:placetype":"venue"
},
  "geometry": {"coordinates":[12.3825654984,41.8902206421],"type":"Point"}
}