{
  "type": "Feature",
  "properties": {
    "addr:full":"24030 Villa D'adda Bergamo 24030",
    "addr:housenumber":"24030",
    "addr:postcode":"24030",
    "addr:street":"Villa",
    "iso:country":"IT",
    "sg:address":"24030 Villa D'adda",
    "sg:orig_category":"Servizi Ausiliari Di Analisi, Controllo E Ricerca",
    "sg:phone":"+39 035 793383",
    "sg:postcode":"24030",
    "sg:province":"Bergamo",
    "wof:name":"Magneticontrol Sas",
    "wof:placetype":"venue"
},
  "geometry": {"coordinates":[9.4628334045,45.7150192261],"type":"Point"}
}