{
  "type": "Feature",
  "properties": {
    "iso:country":"IT",
    "sg:address":"00023 Arsoli",
    "sg:city":"Arsoli",
    "sg:classifiers":[
        {
            "category":"Wholesale",
            "subcategory":"Machinery & Supplies",
            "type":"Manufacturing & Wholesale Goods"
        }
    ],
    "sg:phone":"+39 0774 920215",
    "sg:postcode":"00023",
    "sg:province":"Roma",
    "sg:tags":[
        "pump"
    ],
    "wof:name":"Seven Seas Sas",
    "wof:placetype":"venue"
},
  "geometry": {"coordinates":[13.0140686035,42.0430717468],"type":"Point"}
}