{
  "type": "Feature",
  "properties": {
    "iso:country":"IT",
    "sg:address":"10125 Torino",
    "sg:city":"Torino",
    "sg:orig_category":"Studi E Consulenze Amministrative, Commerciali E Aziendali. Studi E Consulenze Tecniche E Industriali. Consulenze Tecniche, Amministrative E Perizie",
    "sg:phone":"+39 0116560",
    "sg:postcode":"10125",
    "sg:province":"Torino",
    "sg:website":"http://www.praxi.com",
    "wof:name":"Praxi Spa",
    "wof:placetype":"venue"
},
  "geometry": {"coordinates":[7.687109,45.059597],"type":"Point"}
}