{
  "type": "Feature",
  "properties": {
    "iso:country":"IT",
    "sg:address":"Via Roberto Da Bari 112 70122 Bari",
    "sg:city":"Bari",
    "sg:orig_category":"Laptops",
    "sg:phone":"+39 080 555 9730",
    "sg:postcode":"70122",
    "sg:province":"Bari",
    "sg:website":"www.computerlevanteengineering.com",
    "wof:name":"Computer Levante Engieneering Srl",
    "wof:placetype":"venue"
},
  "geometry": {"coordinates":[16.868299,41.122681],"type":"Point"}
}