{
  "type": "Feature",
  "properties": {
    "addr:full":"20049 Concorezzo Concorezzo Milano 20049",
    "addr:postcode":"20049;20049",
    "iso:country":"IT",
    "sg:address":"20049 Concorezzo",
    "sg:city":"Concorezzo",
    "sg:orig_category":"Prodotti Alimentari",
    "sg:phone":"+39 039 604 2888",
    "sg:postcode":"20049",
    "sg:province":"Milano",
    "wof:name":"Ms Studio Herbalife Distributor",
    "wof:placetype":"venue"
},
  "geometry": {"coordinates":[9.3326759338,45.5842704773],"type":"Point"}
}