{
  "type": "Feature",
  "properties": {
    "addr:full":"10, Via Brescia 28100 Novara Novara Novara 28100",
    "addr:postcode":"28100;28100",
    "addr:street":"Via Brescia",
    "iso:country":"IT",
    "sg:address":"10, Via Brescia 28100 Novara",
    "sg:city":"Novara",
    "sg:classifiers":[
        {
            "category":"Shopping",
            "subcategory":"Clothing, Apparel, & Fashions",
            "type":"Retail Goods"
        }
    ],
    "sg:phone":"+39 0321 451336",
    "sg:postcode":"28100",
    "sg:province":"Novara",
    "sg:tags":[
        "clothes"
    ],
    "wof:name":"Calzificio Ca.bi.fi. - Biancalani (s.p.a.)",
    "wof:placetype":"venue"
},
  "geometry": {"coordinates":[8.597309,45.432579],"type":"Point"}
}