{
  "type": "Feature",
  "properties": {
    "addr:full":"20093 Cologno Monzese Cologno Monzese Milano 20093",
    "addr:postcode":"20093;20093",
    "iso:country":"IT",
    "sg:address":"20093 Cologno Monzese",
    "sg:city":"Cologno Monzese",
    "sg:orig_category":"Campeggio",
    "sg:phone":"+39 02 254 1286",
    "sg:postcode":"20093",
    "sg:province":"Milano",
    "wof:name":"Plastigas Srl",
    "wof:placetype":"venue"
},
  "geometry": {"coordinates":[9.263535,45.538273],"type":"Point"}
}