{
  "type": "Feature",
  "properties": {
    "addr:full":"Contrada Piane S. Andrea 64032 Atri Atri Teramo 64032",
    "addr:postcode":"64032;64032",
    "addr:street":"Contrada Piane S. Andrea",
    "iso:country":"IT",
    "sg:address":"Contrada Piane S. Andrea 64032 Atri",
    "sg:city":"Atri",
    "sg:classifiers":[
        {
            "category":"Sports & Exercise",
            "subcategory":"Playing Field",
            "type":"Entertainment"
        }
    ],
    "sg:phone":"+39 085 878 0094",
    "sg:postcode":"64032",
    "sg:province":"Teramo",
    "sg:tags":[
        "game"
    ],
    "wof:name":"Dimal Flor S.r.l.",
    "wof:placetype":"venue"
},
  "geometry": {"coordinates":[13.698531,42.66127],"type":"Point"}
}