{
  "type": "Feature",
  "properties": {
    "iso:country":"IT",
    "sg:address":"Via Circonvallazione, 33/35 12030 Monasterolo Di Savigliano",
    "sg:city":"Monasterolo di Savigliano",
    "sg:classifiers":[
        {
            "category":"Wholesale",
            "subcategory":"Fruits & Vegetables",
            "type":"Manufacturing & Wholesale Goods"
        }
    ],
    "sg:phone":"+39 0172 388006",
    "sg:postcode":"12030",
    "sg:province":"Cuneo",
    "sg:tags":[
        "product",
        "cereal"
    ],
    "wof:name":"Bertinotti Margherita & C. Sas",
    "wof:placetype":"venue"
},
  "geometry": {"coordinates":[7.620479,44.689526],"type":"Point"}
}