{
  "type": "Feature",
  "properties": {
    "iso:country":"IT",
    "sg:address":"12100 Cuneo",
    "sg:city":"Cuneo",
    "sg:orig_category":"Campeggio. Automobili E Mezzi Di Trasporto",
    "sg:phone":"+39 0171 67800",
    "sg:postcode":"12100",
    "sg:province":"Cuneo",
    "sg:website":"http://www.lussocuneo.com",
    "wof:name":"Lusso Sas Di Lusso Giorgio & C.",
    "wof:placetype":"venue"
},
  "geometry": {"coordinates":[7.540396,44.385609],"type":"Point"}
}