{
  "type": "Feature",
  "properties": {
    "addr:full":"9, Via S. Paolo Della Croce 20060 Liscate Liscate Milano 20060",
    "addr:postcode":"20060;20060",
    "addr:street":"Via S. Paolo Della Croce",
    "iso:country":"IT",
    "sg:address":"9, Via S. Paolo Della Croce 20060 Liscate",
    "sg:city":"Liscate",
    "sg:classifiers":[
        {
            "category":"Manufacturing",
            "subcategory":"Metals",
            "type":"Manufacturing & Wholesale Goods"
        }
    ],
    "sg:phone":"+39 02 9535 1035",
    "sg:postcode":"20060",
    "sg:province":"Milano",
    "sg:tags":[
        "metallurgy",
        "metalworking"
    ],
    "wof:name":"Metalcom Spa",
    "wof:placetype":"venue"
},
  "geometry": {"coordinates":[9.1881408691,45.4636878967],"type":"Point"}
}