{
  "type": "Feature",
  "properties": {
    "iso:country":"IT",
    "sg:address":"Via Emilia 2890; Budrio Di Longiano; 47020",
    "sg:city":"Budrio",
    "sg:classifiers":[
        {
            "category":"Banks & Credit Unions",
            "subcategory":"Bank",
            "type":"Services"
        }
    ],
    "sg:phone":"+39 0547 56054",
    "sg:postcode":"47020",
    "sg:province":"Forl\u00ec-Cesena",
    "wof:name":"Cassa Di Risparmio, Di Cesena Spa",
    "wof:placetype":"venue"
},
  "geometry": {"coordinates":[12.334831,44.104664],"type":"Point"}
}