{
  "type": "Feature",
  "properties": {
    "addr:full":"40068 San Lazzaro Di Savena San Lazzaro Bologna 40068",
    "addr:housenumber":"40068",
    "addr:postcode":"40068",
    "addr:street":"San;San;Bologna",
    "iso:country":"IT",
    "sg:address":"40068 San Lazzaro Di Savena",
    "sg:city":"San Lazzaro",
    "sg:orig_category":"Macchine, Impianti Ed Attrezzature Industria Delle Materie Plastiche E Gomma",
    "sg:phone":"+39 051 625 5095",
    "sg:postcode":"40068",
    "sg:province":"Bologna",
    "sg:website":"http://www.cervellati.it",
    "wof:name":"Cervellati Srl",
    "wof:placetype":"venue"
},
  "geometry": {"coordinates":[11.428304,44.464806],"type":"Point"}
}