{
  "type": "Feature",
  "properties": {
    "addr:full":"Via Maroncelli,4/6 20031 Cesano Maderno Cesano Maderno Milano 20031",
    "addr:housenumber":"4 / 6",
    "addr:postcode":"20031;20031",
    "addr:street":"Via Maroncelli",
    "iso:country":"IT",
    "sg:address":"Via Maroncelli,4/6 20031 Cesano Maderno",
    "sg:city":"Cesano Maderno",
    "sg:classifiers":[
        {
            "category":"Banks & Credit Unions",
            "subcategory":"Investment Brokerage",
            "type":"Services"
        }
    ],
    "sg:phone":"+39 036 250 1008",
    "sg:postcode":"20031",
    "sg:province":"Milano",
    "sg:tags":[
        "machine",
        "woodworking",
        "used",
        "installations"
    ],
    "wof:name":"O.m.e.z. Snc",
    "wof:placetype":"venue"
},
  "geometry": {"coordinates":[9.153186,45.63213],"type":"Point"}
}