{
  "type": "Feature",
  "properties": {
    "iso:country":"IT",
    "sg:address":"76/b, Str. Martinella 43100 Parma",
    "sg:city":"Parma",
    "sg:classifiers":[
        {
            "category":"Shopping",
            "type":"Retail Goods"
        }
    ],
    "sg:phone":"+39 0521 649606",
    "sg:postcode":"43100",
    "sg:province":"Parma",
    "sg:tags":[
        "finished",
        "-",
        "metallic"
    ],
    "sg:website":"http://www.paginegialle.it/logisticaindustriale2001",
    "wof:name":"Logistica Industriale 2001 Srl",
    "wof:placetype":"venue"
},
  "geometry": {"coordinates":[10.3322725296,44.7545394897],"type":"Point"}
}