{
  "type": "Feature",
  "properties": {
    "addr:full":"00125 Roma Roma Roma 00125",
    "addr:postcode":"00125;00125",
    "iso:country":"IT",
    "sg:address":"00125 Roma",
    "sg:city":"Roma",
    "sg:orig_category":"Macchine, Impianti E Forniture Per Industria Grafica, Cartaria E Cartotecnica. Automazione E Macchine Per Ufficio",
    "sg:phone":"+39 06 5231 0486",
    "sg:postcode":"00125",
    "sg:province":"Roma",
    "wof:name":"Am System Srl",
    "wof:placetype":"venue"
},
  "geometry": {"coordinates":[12.352056,41.774883],"type":"Point"}
}