{
  "type": "Feature",
  "properties": {
    "iso:country":"IT",
    "sg:address":"Via Niccoli 74/76 50051 Castelfiorentino",
    "sg:city":"Castelfiorentino",
    "sg:classifiers":[
        {
            "category":"Manufacturing",
            "subcategory":"Glass & Minerals",
            "type":"Manufacturing & Wholesale Goods"
        }
    ],
    "sg:phone":"+39 0571 684319",
    "sg:postcode":"50051",
    "sg:province":"Firenze",
    "sg:tags":[
        "decorative",
        "artistic"
    ],
    "sg:website":"www.ve-ca.it",
    "wof:name":"Ve-ca Srl",
    "wof:placetype":"venue"
},
  "geometry": {"coordinates":[10.959222,43.634804],"type":"Point"}
}