{
  "type": "Feature",
  "properties": {
    "addr:full":"22060 Novedrate Novedrate Como 22060",
    "addr:postcode":"22060;22060",
    "iso:country":"IT",
    "sg:address":"22060 Novedrate",
    "sg:city":"Novedrate",
    "sg:orig_category":"Macchine, Impianti Ed Attrezzature Per Abbigliamento E Pelletterie",
    "sg:phone":"+39 031 789117",
    "sg:postcode":"22060",
    "sg:province":"Como",
    "wof:name":"M.i.l. Srl",
    "wof:placetype":"venue"
},
  "geometry": {"coordinates":[9.119692,45.702858],"type":"Point"}
}