{
  "type": "Feature",
  "properties": {
    "addr:full":"52, Via Ceci Antonio 56125 Pisa Pisa Pisa 56125",
    "addr:postcode":"56125;56125",
    "addr:street":"Via Ceci Antonio",
    "iso:country":"IT",
    "sg:address":"52, Via Ceci Antonio 56125 Pisa",
    "sg:city":"Pisa",
    "sg:classifiers":[
        {
            "category":"Banks & Credit Unions",
            "subcategory":"Bank",
            "type":"Services"
        }
    ],
    "sg:phone":"+39 39050515511",
    "sg:postcode":"56125",
    "sg:province":"Pisa",
    "sg:tags":[
        "banking",
        "institution"
    ],
    "wof:name":"Bipielle Ducato Leasing Spa",
    "wof:placetype":"venue"
},
  "geometry": {"coordinates":[10.396585,43.716137],"type":"Point"}
}