{
  "type": "Feature",
  "properties": {
    "iso:country":"IT",
    "sg:address":"20093 Cologno Monzese",
    "sg:city":"Cologno Monzese",
    "sg:orig_category":"Termotecnica E Riscaldamento, Apparecchiature E Servizi",
    "sg:phone":"+39 02 254 2561",
    "sg:postcode":"20093",
    "sg:province":"Milano",
    "wof:name":"A.b.s. Apparecchiature E Bruciatori Speciali S.r.l.",
    "wof:placetype":"venue"
},
  "geometry": {"coordinates":[9.271304,45.534931],"type":"Point"}
}