{
  "type": "Feature",
  "properties": {
    "addr:full":"Piazzale Bertacchi 26; Sondrio; 23100 Sondrio Sondrio 23100",
    "addr:housenumber":"26",
    "addr:postcode":"23100;23100",
    "addr:street":"Piazzale Bertacchi",
    "iso:country":"IT",
    "sg:address":"Piazzale Bertacchi 26; Sondrio; 23100",
    "sg:city":"Sondrio",
    "sg:classifiers":[
        {
            "category":"Banks & Credit Unions",
            "subcategory":"Bank",
            "type":"Services"
        }
    ],
    "sg:phone":"+39 0342 510234",
    "sg:postcode":"23100",
    "sg:province":"Sondrio",
    "wof:name":"Banca Nazionale Del Lavoro Spa",
    "wof:placetype":"venue"
},
  "geometry": {"coordinates":[9.871941,46.168697],"type":"Point"}
}