{
  "type": "Feature",
  "properties": {
    "addr:full":"Via Venezia 19 21058 Solbiate Olona Solbiate Olona Varese 21058",
    "addr:housenumber":"19",
    "addr:postcode":"21058;21058",
    "addr:street":"Via Venezia",
    "iso:country":"IT",
    "sg:address":"Via Venezia 19 21058 Solbiate Olona",
    "sg:city":"Solbiate Olona",
    "sg:classifiers":[
        {
            "category":"Home & Garden",
            "subcategory":"Carpets & Floor Coverings",
            "type":"Retail Goods"
        }
    ],
    "sg:phone":"+39 0331 376775",
    "sg:postcode":"21058",
    "sg:province":"Varese",
    "sg:tags":[
        "sofa",
        "bed"
    ],
    "sg:website":"www.jocoitalia.it",
    "wof:name":"Joco Italia Srl",
    "wof:placetype":"venue"
},
  "geometry": {"coordinates":[8.88747,45.768719],"type":"Point"}
}