{
  "type": "Feature",
  "properties": {
    "iso:country":"IT",
    "sg:address":"29100 Piacenza",
    "sg:city":"Piacenza",
    "sg:orig_category":"Articoli Per Imballaggio E Confezionamento",
    "sg:phone":"+39 0523 590693",
    "sg:postcode":"29100",
    "sg:province":"Piacenza",
    "wof:name":"C.m.e. Srl",
    "wof:placetype":"venue"
},
  "geometry": {"coordinates":[9.767375,45.050365],"type":"Point"}
}