{
  "type": "Feature",
  "properties": {
    "addr:full":"Piazza Dei Caduti 10; S. Angelo Lodigiano; 20079",
    "addr:housenumber":"10",
    "addr:postcode":"20079",
    "addr:street":"Piazza Dei Caduti;Lodigiano",
    "iso:country":"IT",
    "sg:address":"Piazza Dei Caduti 10; S. Angelo Lodigiano; 20079",
    "sg:classifiers":[
        {
            "category":"Banks & Credit Unions",
            "subcategory":"Bank",
            "type":"Services"
        }
    ],
    "sg:phone":"+39 0371 90224",
    "wof:name":"Cassa Di Risparmio Di Parma, E Piacenza Spa",
    "wof:placetype":"venue"
},
  "geometry": {"coordinates":[9.408691,45.237179],"type":"Point"}
}