{
  "type": "Feature",
  "properties": {
    "addr:full":"41100 Modena Modena Modena 41100",
    "addr:postcode":"41100;41100",
    "iso:country":"IT",
    "sg:address":"41100 Modena",
    "sg:city":"Modena",
    "sg:orig_category":"Associazioni Ed Organismi Di Interesse Pubblico",
    "sg:phone":"+39 059 251900",
    "sg:postcode":"41100",
    "sg:province":"Modena",
    "wof:name":"Infocasa",
    "wof:placetype":"venue"
},
  "geometry": {"coordinates":[10.935596,44.551308],"type":"Point"}
}