{
  "type": "Feature",
  "properties": {
    "iso:country":"IT",
    "sg:address":"07031 Castelsardo",
    "sg:city":"Castelsardo",
    "sg:orig_category":"Ristorazione E Locali Pubblici Affini. Ristoranti Ed Esercizi Affini",
    "sg:phone":"+39 079 470755",
    "sg:postcode":"07031",
    "sg:province":"Sassari",
    "wof:name":"La Guardiola Di Giampaolo Tugulu",
    "wof:placetype":"venue"
},
  "geometry": {"coordinates":[8.713346,40.912788],"type":"Point"}
}