{
  "type": "Feature",
  "properties": {
    "iso:country":"IT",
    "sg:address":"14100 Asti",
    "sg:city":"Asti",
    "sg:classifiers":[
        {
            "category":"Health Services",
            "subcategory":"Health Practitioner",
            "type":"Services"
        }
    ],
    "sg:phone":"+39 0141 219300",
    "sg:postcode":"14100",
    "sg:province":"Asti",
    "sg:tags":[
        "medici"
    ],
    "wof:name":"Imerito Gianfranco",
    "wof:placetype":"venue"
},
  "geometry": {"coordinates":[8.065505,44.837204],"type":"Point"}
}