{
  "type": "Feature",
  "properties": {
    "iso:country":"IT",
    "sg:address":"23, Via Giuseppe Verdi 31052 Maserada Sul Piave",
    "sg:city":"Maserada sul Piave",
    "sg:classifiers":[
        {
            "category":"Shopping",
            "subcategory":"Clothing, Apparel, & Fashions",
            "type":"Retail Goods"
        }
    ],
    "sg:phone":"+39 0422 686144",
    "sg:postcode":"31052",
    "sg:province":"Treviso",
    "sg:tags":[
        "clothes"
    ],
    "wof:name":"Candel Di Agostini Giovanni & C. S.n.c.",
    "wof:placetype":"venue"
},
  "geometry": {"coordinates":[12.378561,45.732891],"type":"Point"}
}