{
  "type": "Feature",
  "properties": {
    "addr:full":"47100 Forli' Forl\u00ec-Cesena 47100",
    "addr:postcode":"47100;47100",
    "addr:street":"Forli ' Forli\u0300-Cesena",
    "iso:country":"IT",
    "sg:address":"47100 Forli'",
    "sg:orig_category":"Pelli E Pellami - Produzione E Commercio",
    "sg:phone":"+39 0543 403217",
    "sg:postcode":"47100",
    "sg:province":"Forl\u00ec-Cesena",
    "wof:name":"Samon Snc",
    "wof:placetype":"venue"
},
  "geometry": {"coordinates":[12.0821781158,44.2048416138],"type":"Point"}
}