{
  "type": "Feature",
  "properties": {
    "iso:country":"IT",
    "sg:address":"Corso Magenta 5/2-cancello 16125 Genova",
    "sg:city":"Genova",
    "sg:classifiers":[
        {
            "category":"Government",
            "subcategory":"Office",
            "type":"Public Place"
        }
    ],
    "sg:phone":"+39 010 815565",
    "sg:postcode":"16125",
    "sg:province":"Genova",
    "sg:tags":[
        "machine",
        "servicing"
    ],
    "sg:website":"www.ufficiodomani.it",
    "wof:name":"Ufficio Domani Srl",
    "wof:placetype":"venue"
},
  "geometry": {"coordinates":[8.933989,44.407063],"type":"Point"}
}