{
  "type": "Feature",
  "properties": {
    "iso:country":"IT",
    "sg:address":"24065 Lovere",
    "sg:city":"Lovere",
    "sg:orig_category":"Acciaierie E Fonderie",
    "sg:phone":"+39 035 983331",
    "sg:postcode":"24065",
    "sg:province":"Bergamo",
    "wof:name":"Lovere Meccanica Ferroviaria Spa",
    "wof:placetype":"venue"
},
  "geometry": {"coordinates":[9.67014,45.691444],"type":"Point"}
}