{
  "type": "Feature",
  "properties": {
    "addr:full":"00152 Roma Roma Roma 00152",
    "addr:postcode":"00152;00152",
    "iso:country":"IT",
    "sg:address":"00152 Roma",
    "sg:city":"Roma",
    "sg:orig_category":"Ceramiche: Prodotti E Lavorazioni",
    "sg:phone":"+39 06 580 6678",
    "sg:postcode":"00152",
    "sg:province":"Roma",
    "sg:website":"http://www.dinepiezarfati.it",
    "wof:name":"Di Nepi & Zarfati Srl",
    "wof:placetype":"venue"
},
  "geometry": {"coordinates":[12.437986,41.872963],"type":"Point"}
}