{
  "type": "Feature",
  "properties": {
    "addr:full":"32036 Sedico Sedico Belluno 32036",
    "addr:postcode":"32036;32036",
    "iso:country":"IT",
    "sg:address":"32036 Sedico",
    "sg:city":"Sedico",
    "sg:orig_category":"Pubblica Amministrazione",
    "sg:phone":"+39 0437 87891",
    "sg:postcode":"32036",
    "sg:province":"Belluno",
    "wof:name":"Ente Parco Nazionale Delle Dolomiti Bellunesi",
    "wof:placetype":"venue"
},
  "geometry": {"coordinates":[12.1327733994,46.1887283325],"type":"Point"}
}