{
  "type": "Feature",
  "properties": {
    "iso:country":"IT",
    "sg:address":"20144 Milano",
    "sg:city":"Milano",
    "sg:classifiers":[
        {
            "category":"Manufacturing",
            "subcategory":"Paper Products",
            "type":"Manufacturing & Wholesale Goods"
        }
    ],
    "sg:phone":"+39 02 5811 2391",
    "sg:postcode":"20144",
    "sg:province":"Milano",
    "sg:tags":[
        "finished",
        "products",
        "printed",
        "supply"
    ],
    "wof:name":"Nashira Sas",
    "wof:placetype":"venue"
},
  "geometry": {"coordinates":[9.1670217514,45.4541244507],"type":"Point"}
}