{
  "type": "Feature",
  "properties": {
    "addr:full":"Via D'acquisto 14 20037 Paderno Dugnano Paderno Dugnano Milano 20037",
    "addr:housenumber":"14",
    "addr:postcode":"20037;20037",
    "addr:street":"Via D'Acquisto",
    "iso:country":"IT",
    "sg:address":"Via D'acquisto 14 20037 Paderno Dugnano",
    "sg:city":"Paderno Dugnano",
    "sg:classifiers":[
        {
            "category":"Industrial Area",
            "type":"Public Place"
        }
    ],
    "sg:phone":"+39 02 910 4726",
    "sg:postcode":"20037",
    "sg:province":"Milano",
    "sg:tags":[
        "ovens",
        "heated",
        "furnace",
        "electrically"
    ],
    "sg:website":"www.sape.it",
    "wof:name":"Sa.pe. Snc",
    "wof:placetype":"venue"
},
  "geometry": {"coordinates":[9.150634,45.558796],"type":"Point"}
}