{
  "type": "Feature",
  "properties": {
    "iso:country":"IT",
    "sg:address":"41030 Rovereto",
    "sg:orig_category":"Macchine, Impianti Ed Attrezzature Per Agricoltura E Zootecnia. Prodotti Vari In Metallo. Apparecchiature E Sistemi Per Magazzinaggio E Movimentazione",
    "sg:phone":"+39 059 673230",
    "sg:postcode":"41030",
    "sg:province":"Modena",
    "wof:name":"Simawa Srl",
    "wof:placetype":"venue"
},
  "geometry": {"coordinates":[10.947672,44.823502],"type":"Point"}
}