{
  "type": "Feature",
  "properties": {
    "iso:country":"IT",
    "sg:address":"Viale Vicenza 56 36071 Arzignano",
    "sg:city":"Arzignano",
    "sg:classifiers":[
        {
            "category":"Home & Garden",
            "subcategory":"Carpets & Floor Coverings",
            "type":"Retail Goods"
        }
    ],
    "sg:phone":"+39 0444 670325",
    "sg:postcode":"36071",
    "sg:province":"Vicenza",
    "sg:tags":[
        "animal",
        "skin"
    ],
    "wof:name":"Alma Conceria Srl",
    "wof:placetype":"venue"
},
  "geometry": {"coordinates":[11.357018,45.513882],"type":"Point"}
}