{
  "type": "Feature",
  "properties": {
    "iso:country":"IT",
    "sg:address":"34, Via Italia 31020 San Vendemiano",
    "sg:city":"San Vendemiano",
    "sg:classifiers":[
        {
            "category":"Shopping",
            "type":"Retail Goods"
        }
    ],
    "sg:phone":"+39 0438 409090",
    "sg:postcode":"31020",
    "sg:province":"Treviso",
    "sg:tags":[
        "finished",
        "-",
        "metallic"
    ],
    "wof:name":"Unitek (s.r.l.)",
    "wof:placetype":"venue"
},
  "geometry": {"coordinates":[12.3305835724,45.8908462524],"type":"Point"}
}