{
  "type": "Feature",
  "properties": {
    "addr:full":"Localita' Marescotta 01039 Vignanello Vignanello Viterbo 01039",
    "addr:postcode":"01039;01039",
    "addr:street":"Localita ' Marescotta",
    "iso:country":"IT",
    "sg:address":"Localita' Marescotta 01039 Vignanello",
    "sg:city":"Vignanello",
    "sg:classifiers":[
        {
            "category":"Shopping",
            "subcategory":"Clothing, Apparel, & Fashions",
            "type":"Retail Goods"
        }
    ],
    "sg:phone":"+39 0761 754022",
    "sg:postcode":"01039",
    "sg:province":"Viterbo",
    "sg:tags":[
        "clothes"
    ],
    "wof:name":"Ceccarelli Giuseppina",
    "wof:placetype":"venue"
},
  "geometry": {"coordinates":[12.104854,42.417381],"type":"Point"}
}