{
  "type": "Feature",
  "properties": {
    "addr:full":"28, Via Dell' Europa 40037 Sasso Marconi Sasso Marconi Bologna 40037",
    "addr:postcode":"40037;40037",
    "addr:street":"Via Dell ' Europa",
    "iso:country":"IT",
    "sg:address":"28, Via Dell' Europa 40037 Sasso Marconi",
    "sg:city":"Sasso Marconi",
    "sg:classifiers":[
        {
            "category":"Manufacturing",
            "subcategory":"Rubber & Plastics",
            "type":"Manufacturing & Wholesale Goods"
        }
    ],
    "sg:phone":"+39 39051841316",
    "sg:postcode":"40037",
    "sg:province":"Bologna",
    "wof:name":"Marconigomma (s.r.l.)",
    "wof:placetype":"venue"
},
  "geometry": {"coordinates":[11.358324,44.445576],"type":"Point"}
}