{
  "type": "Feature",
  "properties": {
    "addr:full":"70125 Bari Bari Bari 70125",
    "addr:postcode":"70125;70125",
    "iso:country":"IT",
    "sg:address":"70125 Bari",
    "sg:city":"Bari",
    "sg:orig_category":"Prodotti Di Base E Forniture Per Industria Alimentare E Bevande. Carta, Cartone E Prodotti Primari. Forniture Per Attivita' Commerciali Ed Artigianali",
    "sg:phone":"+39 080 557 4911",
    "sg:postcode":"70125",
    "sg:province":"Bari",
    "wof:name":"Eddycart Salerno S.r.l.",
    "wof:placetype":"venue"
},
  "geometry": {"coordinates":[16.8664455414,41.0712547302],"type":"Point"}
}