{
  "type": "Feature",
  "properties": {
    "iso:country":"IT",
    "sg:address":"00165 Roma",
    "sg:city":"Roma",
    "sg:orig_category":"Arredamenti E Mobili Professionali. Forniture Alle Strutture Ricettive",
    "sg:phone":"+39 06 638 1104",
    "sg:postcode":"00165",
    "sg:province":"Roma",
    "sg:website":"http://www.mobilnovo.it",
    "wof:name":"Mobilnovo Srl",
    "wof:placetype":"venue"
},
  "geometry": {"coordinates":[12.441384,41.897396],"type":"Point"}
}