{
  "type": "Feature",
  "properties": {
    "iso:country":"IT",
    "sg:address":"23, Via Copernico Nicolo' 41015 Nonantola",
    "sg:city":"Nonantola",
    "sg:classifiers":[
        {
            "category":"Manufacturing",
            "subcategory":"Lumber",
            "type":"Manufacturing & Wholesale Goods"
        }
    ],
    "sg:phone":"+39 39059548213",
    "sg:postcode":"41015",
    "sg:province":"Modena",
    "sg:tags":[
        "wood"
    ],
    "wof:name":"S.c.s. Di Sighinolfi & C. S.n.c.",
    "wof:placetype":"venue"
},
  "geometry": {"coordinates":[11.01228,44.674511],"type":"Point"}
}