{
  "type": "Feature",
  "properties": {
    "iso:country":"IT",
    "sg:address":"40033 Casalecchio Di Reno",
    "sg:city":"Casalecchio di Reno",
    "sg:orig_category":"Elettrotecnica Professionale E Di Consumo. Forniture Per Attivita' Commerciali Ed Artigianali",
    "sg:phone":"+39 051 573292",
    "sg:postcode":"40033",
    "sg:province":"Bologna",
    "wof:name":"Lolli Raffaele Impianti Srl",
    "wof:placetype":"venue"
},
  "geometry": {"coordinates":[11.256915,44.4897],"type":"Point"}
}