{
  "type": "Feature",
  "properties": {
    "iso:country":"IT",
    "sg:address":"42017 Novellara",
    "sg:orig_category":"Lavorazioni Meccaniche E Servizi",
    "sg:phone":"+39 0522 654042",
    "sg:postcode":"42017",
    "sg:province":"Reggio Nell'Emilia",
    "sg:website":"http://www.mini-mec.it",
    "wof:name":"Nuova Mini-mec Srl",
    "wof:placetype":"venue"
},
  "geometry": {"coordinates":[10.627794,44.696228],"type":"Point"}
}