{
  "type": "Feature",
  "properties": {
    "iso:country":"IT",
    "sg:address":"3, Via Lamarmora Alfonso 20122 Milano",
    "sg:city":"Milano",
    "sg:classifiers":[
        {
            "category":"Manufacturing",
            "subcategory":"Printing",
            "type":"Manufacturing & Wholesale Goods"
        }
    ],
    "sg:phone":"+39 02 5990 0041",
    "sg:postcode":"20122",
    "sg:province":"Milano",
    "sg:tags":[
        "publishing"
    ],
    "wof:name":"Edizioni Minerva Medica S.p.a.",
    "wof:placetype":"venue"
},
  "geometry": {"coordinates":[9.1963729858,45.4561691284],"type":"Point"}
}