{
  "type": "Feature",
  "properties": {
    "iso:country":"IT",
    "sg:address":"Via Della Cascina Pontevica 19 25125 Brescia",
    "sg:city":"Brescia",
    "sg:classifiers":[
        {
            "category":"Shopping",
            "subcategory":"Clothing, Apparel, & Fashions",
            "type":"Retail Goods"
        }
    ],
    "sg:phone":"+39 030 216 0245",
    "sg:postcode":"25125",
    "sg:province":"Brescia",
    "sg:tags":[
        "blouse",
        "ladies'",
        "dress"
    ],
    "wof:name":"Eurostock Srl",
    "wof:placetype":"venue"
},
  "geometry": {"coordinates":[10.205729,45.500736],"type":"Point"}
}