{
  "type": "Feature",
  "properties": {
    "iso:country":"IT",
    "sg:address":"C/o Credito Emiliano, Via Emilia S. Pietro 4, 42100 Reggio Emilia, Re",
    "sg:classifiers":[
        {
            "category":"Banks & Credit Unions",
            "subcategory":"Bank",
            "type":"Services"
        }
    ],
    "sg:phone":"+39 0522 4501",
    "sg:postcode":"42100",
    "sg:province":"Reggio Nell'Emilia",
    "wof:name":"Credemholding Spa",
    "wof:placetype":"venue"
},
  "geometry": {"coordinates":[10.627794,44.696228],"type":"Point"}
}