{
  "type": "Feature",
  "properties": {
    "addr:full":"20123 Milano Milano Milano 20123",
    "addr:postcode":"20123;20123",
    "iso:country":"IT",
    "sg:address":"20123 Milano",
    "sg:city":"Milano",
    "sg:classifiers":[
        {
            "category":"Professional",
            "type":"Services"
        }
    ],
    "sg:phone":"+39 02 5810 4325",
    "sg:postcode":"20123",
    "sg:province":"Milano",
    "sg:tags":[
        "auxiliary",
        "entertainment",
        "premises",
        "related",
        "catering",
        "public",
        "restaurants"
    ],
    "sg:website":"http://www.lebiciclette.com",
    "wof:name":"Le Biciclette Ristorante + Art Bar",
    "wof:placetype":"venue"
},
  "geometry": {"coordinates":[9.177441,45.457764],"type":"Point"}
}