{
  "type": "Feature",
  "properties": {
    "iso:country":"IT",
    "sg:address":"10126 Torino",
    "sg:city":"Torino",
    "sg:orig_category":"Consulenza Di Direzione Ed Organizzazione Aziendale",
    "sg:phone":"+39 011 676312",
    "sg:postcode":"10126",
    "sg:province":"Torino",
    "wof:name":"Andros Sas",
    "wof:placetype":"venue"
},
  "geometry": {"coordinates":[7.68159,45.049442],"type":"Point"}
}