{
  "type": "Feature",
  "properties": {
    "iso:country":"IT",
    "sg:address":"73100 Lecce",
    "sg:city":"Lecce",
    "sg:orig_category":"Prodotti Alimentari",
    "sg:phone":"+39 0832 340777",
    "sg:postcode":"73100",
    "sg:province":"Lecce",
    "sg:website":"http://www.salentogourmet.com",
    "wof:name":"Salento Gourmet Di Manzone Giuseppe",
    "wof:placetype":"venue"
},
  "geometry": {"coordinates":[18.1871891022,40.3467979431],"type":"Point"}
}