{
  "type": "Feature",
  "properties": {
    "iso:country":"IT",
    "sg:address":"10139 Torino",
    "sg:city":"Torino",
    "sg:classifiers":[
        {
            "category":"Health Services",
            "subcategory":"Health Practitioner",
            "type":"Services"
        }
    ],
    "sg:phone":"+39 011 336504",
    "sg:postcode":"10139",
    "sg:province":"Torino",
    "sg:tags":[
        "medici"
    ],
    "wof:name":"Peronino Maria Margherita",
    "wof:placetype":"venue"
},
  "geometry": {"coordinates":[7.1200766563,45.1260185242],"type":"Point"}
}