{
  "type": "Feature",
  "properties": {
    "addr:full":"36030 Sarcedo Sarcedo Vicenza 36030",
    "addr:postcode":"36030;36030",
    "iso:country":"IT",
    "sg:address":"36030 Sarcedo",
    "sg:city":"Sarcedo",
    "sg:orig_category":"Non-classified Establishments",
    "sg:phone":"+39 0445 344190",
    "sg:postcode":"36030",
    "sg:province":"Vicenza",
    "sg:website":"http://www.dottus.com",
    "wof:name":"Dottus Sas",
    "wof:placetype":"venue"
},
  "geometry": {"coordinates":[11.530423,45.702778],"type":"Point"}
}