{
  "type": "Feature",
  "properties": {
    "iso:country":"IT",
    "sg:address":"64020 Bellante",
    "sg:city":"Bellante",
    "sg:orig_category":"Borse E Borsette - Produzione E Ingrosso",
    "sg:phone":"+39 0861 610221",
    "sg:postcode":"64020",
    "sg:province":"Teramo",
    "wof:name":"Magis Srl",
    "wof:placetype":"venue"
},
  "geometry": {"coordinates":[13.83957,42.706112],"type":"Point"}
}