{
  "type": "Feature",
  "properties": {
    "addr:full":"25017 Lonato Centenaro Brescia 25017",
    "addr:postcode":"25017;25017",
    "iso:country":"IT",
    "sg:address":"25017 Lonato",
    "sg:city":"Centenaro",
    "sg:classifiers":[
        {
            "category":"Home & Garden",
            "subcategory":"Building Materials",
            "type":"Retail Goods"
        }
    ],
    "sg:phone":"+39 030 910 3028",
    "sg:postcode":"25017",
    "sg:province":"Brescia",
    "sg:tags":[
        "window",
        "door",
        "frame"
    ],
    "wof:name":"Bocchio Fratelli Falegnameria Snc",
    "wof:placetype":"venue"
},
  "geometry": {"coordinates":[10.54802,45.429752],"type":"Point"}
}