{
  "type": "Feature",
  "properties": {
    "iso:country":"IT",
    "sg:address":"C.da Scunchipane 92019 Sciacca",
    "sg:city":"Sciacca",
    "sg:classifiers":[
        {
            "category":"Food & Beverages",
            "subcategory":"Bakery",
            "type":"Retail Goods"
        }
    ],
    "sg:phone":"+39 39092580100",
    "sg:postcode":"92019",
    "sg:province":"Agrigento",
    "sg:tags":[
        "grain",
        "cereal"
    ],
    "wof:name":"Licat Paolo Villa Reale",
    "wof:placetype":"venue"
},
  "geometry": {"coordinates":[13.576956,37.311188],"type":"Point"}
}