{
  "type": "Feature",
  "properties": {
    "iso:country":"IT",
    "sg:address":"48022 Lugo",
    "sg:city":"Lugo",
    "sg:orig_category":"Forniture Per Abbigliamento E Pelletterie",
    "sg:phone":"+39 0545 32053",
    "sg:postcode":"48022",
    "sg:province":"Ravenna",
    "wof:name":"Piumaduemila Di Famularo Nunziatina & C. Snc",
    "wof:placetype":"venue"
},
  "geometry": {"coordinates":[11.9089679718,44.4315376282],"type":"Point"}
}