{
  "type": "Feature",
  "properties": {
    "iso:country":"IT",
    "sg:address":"Str. Statale Alba-bra 201 12069 Santa Vittoria D'alba",
    "sg:orig_category":"Gelatine",
    "sg:phone":"+39 0172 478047",
    "sg:postcode":"12069",
    "sg:province":"Cuneo",
    "sg:website":"www.italgelatine.com",
    "wof:name":"Italgelatine Spa",
    "wof:placetype":"venue"
},
  "geometry": {"coordinates":[7.547111,44.388798],"type":"Point"}
}