{
  "type": "Feature",
  "properties": {
    "iso:country":"IT",
    "sg:address":"20143 Milano",
    "sg:city":"Milano",
    "sg:orig_category":"Telecomunicazioni Impianti Ed Apparecchi - Produzione E Ingrosso",
    "sg:phone":"+39 02 818001",
    "sg:postcode":"20143",
    "sg:province":"Milano",
    "sg:website":"http://www.netengineering.it",
    "wof:name":"Net Engineering Srl",
    "wof:placetype":"venue"
},
  "geometry": {"coordinates":[9.156797,45.444038],"type":"Point"}
}