{
  "type": "Feature",
  "properties": {
    "addr:full":"20121 Milano Milano Milano 20121",
    "addr:postcode":"20121;20121",
    "iso:country":"IT",
    "sg:address":"20121 Milano",
    "sg:city":"Milano",
    "sg:orig_category":"Servizi Editoriali. Servizi Per Aziende, Manifestazioni E Supporto Agli Scambi Commerciali",
    "sg:phone":"+39 02 780488",
    "sg:postcode":"20121",
    "sg:province":"Milano",
    "wof:name":"Associated Press Italia",
    "wof:placetype":"venue"
},
  "geometry": {"coordinates":[9.195591,45.472382],"type":"Point"}
}