{
  "type": "Feature",
  "properties": {
    "iso:country":"IT",
    "sg:address":"91015 Custonaci",
    "sg:city":"Custonaci",
    "sg:orig_category":"Caldaie - Produzione E Commercio",
    "sg:phone":"+39 0923 973399",
    "sg:postcode":"91015",
    "sg:province":"Trapani",
    "wof:name":"Edil Pampalone Di Antonino Pampalone & C. Sas",
    "wof:placetype":"venue"
},
  "geometry": {"coordinates":[12.68909,38.075451],"type":"Point"}
}