{
  "type": "Feature",
  "properties": {
    "addr:full":"51, Via Palazzon 36051 Creazzo Creazzo Vicenza 36051",
    "addr:postcode":"36051;36051",
    "addr:street":"Via Palazzon",
    "iso:country":"IT",
    "sg:address":"51, Via Palazzon 36051 Creazzo",
    "sg:city":"Creazzo",
    "sg:classifiers":[
        {
            "category":"Professional",
            "subcategory":"Engineering",
            "type":"Services"
        }
    ],
    "sg:phone":"+39 0444 520755",
    "sg:postcode":"36051",
    "sg:province":"Vicenza",
    "sg:tags":[
        "machine",
        "-",
        "mechanical"
    ],
    "wof:name":"Massignan G. & Figli (s.n.c.)",
    "wof:placetype":"venue"
},
  "geometry": {"coordinates":[11.494589,45.532364],"type":"Point"}
}