{
  "type": "Feature",
  "properties": {
    "iso:country":"IT",
    "sg:address":"15, Piazza Ruggero Settimo Re 90139 Palermo",
    "sg:city":"Palermo",
    "sg:classifiers":[
        {
            "category":"Travel",
            "subcategory":"Travel Agent",
            "type":"Entertainment"
        }
    ],
    "sg:phone":"+39 39091322777",
    "sg:postcode":"90139",
    "sg:province":"Palermo",
    "sg:tags":[
        "business"
    ],
    "wof:name":"Albergo Politeama Palace Hotel",
    "wof:placetype":"venue"
},
  "geometry": {"coordinates":[13.3613758087,38.1156196594],"type":"Point"}
}