{
  "type": "Feature",
  "properties": {
    "iso:country":"IT",
    "sg:address":"8/10, V. Massimo D'azeglio 20021 Bollate",
    "sg:city":"Bollate",
    "sg:classifiers":[
        {
            "category":"Shopping",
            "type":"Retail Goods"
        }
    ],
    "sg:phone":"+39 39023510741",
    "sg:postcode":"20021",
    "sg:province":"Milano",
    "sg:tags":[
        "finished",
        "-",
        "metallic"
    ],
    "sg:website":"http://www.lorenzon-it.com:ws_end: :mark:ws:http://www.paginegialle.it/lorenzonsrl",
    "wof:name":"Lorenzon & C. Srl",
    "wof:placetype":"venue"
},
  "geometry": {"coordinates":[9.1446352005,45.5468025208],"type":"Point"}
}