{
  "type": "Feature",
  "properties": {
    "iso:country":"IT",
    "sg:address":"Via Campoleone Tenuta 13 04010 Campoleone",
    "sg:classifiers":[
        {
            "category":"Professional",
            "subcategory":"Engineering",
            "type":"Services"
        }
    ],
    "sg:phone":"+39 06 927 8251",
    "sg:postcode":"04010",
    "sg:province":"Latina",
    "sg:tags":[
        "equipment",
        "airport",
        "safety"
    ],
    "sg:website":"www.aviogei.it",
    "wof:name":"Airport Equipment - Aviogei Srl",
    "wof:placetype":"venue"
},
  "geometry": {"coordinates":[12.639915,41.648289],"type":"Point"}
}