{
  "type": "Feature",
  "properties": {
    "iso:country":"IT",
    "sg:address":"81034 Mondragone",
    "sg:city":"Mondragone",
    "sg:orig_category":"Fiori E Piante - Ingrosso",
    "sg:phone":"+39 0823 972935",
    "sg:postcode":"81034",
    "sg:province":"Caserta",
    "wof:name":"Roby Flor Di Iafrancesco Caterina",
    "wof:placetype":"venue"
},
  "geometry": {"coordinates":[14.3560094833,41.0703849792],"type":"Point"}
}