{
  "type": "Feature",
  "properties": {
    "iso:country":"IT",
    "sg:address":"20142 Milano",
    "sg:city":"Milano",
    "sg:orig_category":"Ospedali E Servizi Sanitari",
    "sg:phone":"+39 02 826 5952",
    "sg:postcode":"20142",
    "sg:province":"Milano",
    "wof:name":"Fraternita Di Misericordia",
    "wof:placetype":"venue"
},
  "geometry": {"coordinates":[9.171868,45.412216],"type":"Point"}
}