{
  "type": "Feature",
  "properties": {
    "addr:full":"Via Coppino, 371/373 55049 Viareggio Viareggio Lucca 55049",
    "addr:housenumber":"371 / 373",
    "addr:postcode":"55049;55049",
    "addr:street":"Via Coppino",
    "iso:country":"IT",
    "sg:address":"Via Coppino, 371/373 55049 Viareggio",
    "sg:city":"Viareggio",
    "sg:classifiers":[
        {
            "category":"Banks & Credit Unions",
            "subcategory":"Investment Brokerage",
            "type":"Services"
        }
    ],
    "sg:phone":"+39 0584 384377",
    "sg:postcode":"55049",
    "sg:province":"Lucca",
    "sg:tags":[
        "units",
        "customized",
        "power",
        "supply"
    ],
    "sg:website":"www.cantalupi.it",
    "wof:name":"Cantalupi Srl",
    "wof:placetype":"venue"
},
  "geometry": {"coordinates":[10.2453117371,43.8628730774],"type":"Point"}
}