{
  "type": "Feature",
  "properties": {
    "addr:full":"50028 Tavarnelle Val Di Pesa Sambuca Firenze 50028",
    "addr:postcode":"50028;50028",
    "iso:country":"IT",
    "sg:address":"50028 Tavarnelle Val Di Pesa",
    "sg:city":"Sambuca",
    "sg:orig_category":"Ricambi E Componenti Dei Mezzi Di Trasporto",
    "sg:phone":"+39 055 807 0309",
    "sg:postcode":"50028",
    "sg:province":"Firenze",
    "wof:name":"Carbon Dream Spa",
    "wof:placetype":"venue"
},
  "geometry": {"coordinates":[11.218378,43.553329],"type":"Point"}
}