{
  "type": "Feature",
  "properties": {
    "iso:country":"IT",
    "sg:address":"41058 Vignola",
    "sg:city":"Vignola",
    "sg:orig_category":"Sport - Articoli E Forniture",
    "sg:phone":"+39 059 773144",
    "sg:postcode":"41058",
    "sg:province":"Modena",
    "wof:name":"Venturieri Fratelli (s.n.c.)",
    "wof:placetype":"venue"
},
  "geometry": {"coordinates":[10.991012,44.479],"type":"Point"}
}