{
  "type": "Feature",
  "properties": {
    "iso:country":"IT",
    "sg:address":"24036 Ponte San Pietro",
    "sg:city":"Ponte San Pietro",
    "sg:orig_category":"Centri Di Estetica E Cosmesi E Servizi",
    "sg:phone":"+39 035 617180",
    "sg:postcode":"24036",
    "sg:province":"Bergamo",
    "wof:name":"R.v.p. Snc Di Pesenti Valeriano & Paola",
    "wof:placetype":"venue"
},
  "geometry": {"coordinates":[9.593757,45.711063],"type":"Point"}
}