{
  "type": "Feature",
  "properties": {
    "iso:country":"IT",
    "sg:address":"20021 Bollate",
    "sg:city":"Bollate",
    "sg:orig_category":"Metalli E Leghe",
    "sg:phone":"+39 02 351 2632",
    "sg:postcode":"20021",
    "sg:province":"Milano",
    "wof:name":"Omer Trading Srl",
    "wof:placetype":"venue"
},
  "geometry": {"coordinates":[9.1463127136,45.5635948181],"type":"Point"}
}