{
  "type": "Feature",
  "properties": {
    "iso:country":"IT",
    "sg:address":"35020 Arzergrande",
    "sg:city":"Arzergrande",
    "sg:orig_category":"Forniture Per Attivita' Industriali",
    "sg:phone":"+39 049 580 0214",
    "sg:postcode":"35020",
    "sg:province":"Padova",
    "wof:name":"Grigoletto Francesco",
    "wof:placetype":"venue"
},
  "geometry": {"coordinates":[11.8758926392,45.4006919861],"type":"Point"}
}