{
  "type": "Feature",
  "properties": {
    "iso:country":"IT",
    "sg:address":"04023 Formia",
    "sg:city":"Formia",
    "sg:orig_category":"Animali Domestici - Allevamento E Addestramento",
    "sg:phone":"+39 0771 772606",
    "sg:postcode":"04023",
    "sg:province":"Latina",
    "wof:name":"Alicandro Raffaele Dog'house",
    "wof:placetype":"venue"
},
  "geometry": {"coordinates":[13.591545,41.25103],"type":"Point"}
}