{
  "type": "Feature",
  "properties": {
    "iso:country":"IT",
    "sg:address":"38100 Trento",
    "sg:city":"Trento",
    "sg:orig_category":"Non-classified Establishments",
    "sg:phone":"+39 0461 823571",
    "sg:postcode":"38100",
    "sg:province":"Trento",
    "wof:name":"Giuliani Fabio Falegnameria - Arredamenti Su Misura",
    "wof:placetype":"venue"
},
  "geometry": {"coordinates":[11.123575,46.08083],"type":"Point"}
}