{
  "type": "Feature",
  "properties": {
    "addr:full":"40138 Bologna Bologna Bologna 40138",
    "addr:postcode":"40138;40138",
    "iso:country":"IT",
    "sg:address":"40138 Bologna",
    "sg:city":"Bologna",
    "sg:orig_category":"Utensili Meccanici E Materiali",
    "sg:phone":"+39 051 530220",
    "sg:postcode":"40138",
    "sg:province":"Bologna",
    "wof:name":"C.m.t. Di Tubertini",
    "wof:placetype":"venue"
},
  "geometry": {"coordinates":[11.411795,44.50584],"type":"Point"}
}