{
  "type": "Feature",
  "properties": {
    "iso:country":"IT",
    "sg:address":"73100 Lecce",
    "sg:city":"Lecce",
    "sg:orig_category":"Serramenti Ed Infissi",
    "sg:phone":"+39 0832 304457",
    "sg:postcode":"73100",
    "sg:province":"Lecce",
    "sg:website":"http://www.domoconfort.it",
    "wof:name":"Domoconfort Srl",
    "wof:placetype":"venue"
},
  "geometry": {"coordinates":[18.139355,40.366394],"type":"Point"}
}