{
  "type": "Feature",
  "properties": {
    "addr:full":"33, Contrada Torre Allegra Str. St. 114 95121 Catania Catania Catania 95121",
    "addr:housenumber":"114",
    "addr:postcode":"95121;95121",
    "addr:street":"Contrada Torre Allegra Str. St.",
    "iso:country":"IT",
    "sg:address":"33, Contrada Torre Allegra Str. St. 114 95121 Catania",
    "sg:city":"Catania",
    "sg:classifiers":[
        {
            "category":"Parking",
            "subcategory":"Lot",
            "type":"Transportation"
        }
    ],
    "sg:phone":"+39 39095592311",
    "sg:postcode":"95121",
    "sg:province":"Catania",
    "sg:tags":[
        "transport",
        "road"
    ],
    "wof:name":"Avimec (s.r.l.)",
    "wof:placetype":"venue"
},
  "geometry": {"coordinates":[15.066168,37.467422],"type":"Point"}
}