{
  "type": "Feature",
  "properties": {
    "addr:full":"31029 Vittorio Veneto Vittorio Veneto Treviso 31029",
    "addr:postcode":"31029;31029",
    "iso:country":"IT",
    "sg:address":"31029 Vittorio Veneto",
    "sg:city":"Vittorio Veneto",
    "sg:classifiers":[
        {
            "category":"Home & Garden",
            "subcategory":"Furniture",
            "type":"Retail Goods"
        }
    ],
    "sg:phone":"+39 0438 500162",
    "sg:postcode":"31029",
    "sg:province":"Treviso",
    "sg:tags":[
        "craft",
        "art",
        "furnishing",
        "artistic"
    ],
    "wof:name":"Azzalini & Bedana Snc",
    "wof:placetype":"venue"
},
  "geometry": {"coordinates":[12.3009958267,45.9962387085],"type":"Point"}
}