{
  "type": "Feature",
  "properties": {
    "addr:full":"Viale Margherita 11; Viareggio",
    "addr:housenumber":"11",
    "addr:street":"Viale Margherita",
    "iso:country":"IT",
    "sg:address":"Viale Margherita 11; Viareggio",
    "sg:classifiers":[
        {
            "category":"Travel",
            "subcategory":"Travel Agent",
            "type":"Entertainment"
        }
    ],
    "wof:name":"V.e.t Viaggi E Turismo Dmc",
    "wof:placetype":"venue"
},
  "geometry": {"coordinates":[10.242717,43.868031],"type":"Point"}
}