{
  "type": "Feature",
  "properties": {
    "iso:country":"IT",
    "sg:address":"25075 Nave",
    "sg:city":"Nave",
    "sg:orig_category":"Trattamenti Termici E Superficiali Metalli, Galvanotecnica",
    "sg:postcode":"25075",
    "sg:province":"Brescia",
    "wof:name":"Temponi F.lli (s.r.l.)",
    "wof:placetype":"venue"
},
  "geometry": {"coordinates":[10.271795,45.572643],"type":"Point"}
}