{
  "type": "Feature",
  "properties": {
    "addr:full":"30174 Venezia Mestre Venezia 30174",
    "addr:postcode":"30174;30174",
    "iso:country":"IT",
    "sg:address":"30174 Venezia",
    "sg:city":"Mestre",
    "sg:orig_category":"Condizionamento Aria Impianti - Installazione E Manutenzione",
    "sg:phone":"+39 041 914377",
    "sg:postcode":"30174",
    "sg:province":"Venezia",
    "wof:name":"Frigo 2001 Di Visentin Alfredo",
    "wof:placetype":"venue"
},
  "geometry": {"coordinates":[12.207702,45.486542],"type":"Point"}
}