{
  "type": "Feature",
  "properties": {
    "iso:country":"IT",
    "sg:address":"00181 Roma",
    "sg:city":"Roma",
    "sg:orig_category":"Arredo Camera Letto E Complementi",
    "sg:phone":"+39 06 780 7854",
    "sg:postcode":"00181",
    "sg:province":"Roma",
    "wof:name":"Bezziccheri Danilo",
    "wof:placetype":"venue"
},
  "geometry": {"coordinates":[12.523966,41.878021],"type":"Point"}
}