{
  "type": "Feature",
  "properties": {
    "iso:country":"IT",
    "sg:address":"29100 Piacenza",
    "sg:city":"Piacenza",
    "sg:orig_category":"Tempo Libero - Articoli E Forniture. Shopping. Regalistica Aziendale",
    "sg:phone":"+39 0523 331636",
    "sg:postcode":"29100",
    "sg:province":"Piacenza",
    "wof:name":"Fabbrizio Paolo Unicorn",
    "wof:placetype":"venue"
},
  "geometry": {"coordinates":[9.693119,45.05328],"type":"Point"}
}