{
  "type": "Feature",
  "properties": {
    "addr:full":"29, Via Ingegnoli 20093 Cologno Monzese Cologno Monzese Milano 20093",
    "addr:postcode":"20093;20093",
    "addr:street":"Via Ingegnoli",
    "iso:country":"IT",
    "sg:address":"29, Via Ingegnoli 20093 Cologno Monzese",
    "sg:city":"Cologno Monzese",
    "sg:classifiers":[
        {
            "category":"Professional",
            "subcategory":"Engineering",
            "type":"Services"
        }
    ],
    "sg:phone":"+39 39022542941",
    "sg:postcode":"20093",
    "sg:province":"Milano",
    "sg:tags":[
        "machine",
        "-",
        "mechanical"
    ],
    "wof:name":"Guarnizioni Industriali Tecniche Cristiani - Bisconti S.r.l.",
    "wof:placetype":"venue"
},
  "geometry": {"coordinates":[9.266719,45.520943],"type":"Point"}
}