{
  "type": "Feature",
  "properties": {
    "iso:country":"IT",
    "sg:address":"15100 Alessandria",
    "sg:city":"Alessandria",
    "sg:orig_category":"Studi E Consulenze Tecniche E Industriali. Consulenze Tecniche, Amministrative E Perizie",
    "sg:phone":"+39 0131 387394",
    "sg:postcode":"15100",
    "sg:province":"Alessandria",
    "sg:website":"http://www.tfeng.idp.it",
    "wof:name":"T.f. Engineering Service Sas",
    "wof:placetype":"venue"
},
  "geometry": {"coordinates":[8.734209,44.878841],"type":"Point"}
}