{
  "type": "Feature",
  "properties": {
    "iso:country":"IT",
    "sg:address":"20090 Trezzano Sul Naviglio",
    "sg:city":"Trezzano sul Naviglio",
    "sg:orig_category":"Materiali Edili",
    "sg:phone":"+39 02 4840 7155",
    "sg:postcode":"20090",
    "sg:province":"Milano",
    "wof:name":"Allumitetto Di Santarcangelo Mario E Figli Snc",
    "wof:placetype":"venue"
},
  "geometry": {"coordinates":[9.041488,45.413445],"type":"Point"}
}