{
  "type": "Feature",
  "properties": {
    "addr:full":"12030 Caramagna Piemonte Caramagna Piemonte Cuneo 12030",
    "addr:housenumber":"12030",
    "addr:postcode":"piemonte;12030",
    "addr:street":"Caramagna Piemonte",
    "iso:country":"IT",
    "sg:address":"12030 Caramagna Piemonte",
    "sg:city":"Caramagna Piemonte",
    "sg:orig_category":"Dolciumi E Gelati",
    "sg:phone":"+39 0172 89236",
    "sg:postcode":"12030",
    "sg:province":"Cuneo",
    "wof:name":"Lago Dei Salici Srl",
    "wof:placetype":"venue"
},
  "geometry": {"coordinates":[7.738973,44.780273],"type":"Point"}
}