{
  "type": "Feature",
  "properties": {
    "addr:full":"50050 Cerreto Guidi Cerreto Guidi Firenze 50050",
    "addr:postcode":"50050;50050",
    "iso:country":"IT",
    "sg:address":"50050 Cerreto Guidi",
    "sg:city":"Cerreto Guidi",
    "sg:orig_category":"Nastri Adesivi E Biadesivi",
    "sg:phone":"+39 0571 586215",
    "sg:postcode":"50050",
    "sg:province":"Firenze",
    "wof:name":"Balducci Snc",
    "wof:placetype":"venue"
},
  "geometry": {"coordinates":[10.828827,43.776764],"type":"Point"}
}