{
  "type": "Feature",
  "properties": {
    "addr:full":"Strada Ponte Alto 41100 Modena Modena Modena 41100",
    "addr:postcode":"41100;41100",
    "addr:street":"Strada Ponte Alto",
    "iso:country":"IT",
    "sg:address":"Strada Ponte Alto 41100 Modena",
    "sg:city":"Modena",
    "sg:classifiers":[
        {
            "category":"Wholesale",
            "subcategory":"Machinery & Supplies",
            "type":"Manufacturing & Wholesale Goods"
        }
    ],
    "sg:phone":"+39 39059337385",
    "sg:postcode":"41100",
    "sg:province":"Modena",
    "sg:tags":[
        "-",
        "agriculture",
        "equipment"
    ],
    "wof:name":"Maletti Macchine Agricole (s.p.a.)",
    "wof:placetype":"venue"
},
  "geometry": {"coordinates":[10.887064,44.666595],"type":"Point"}
}