{
  "type": "Feature",
  "properties": {
    "addr:full":"36016 Thiene Thiene Vicenza 36016",
    "addr:postcode":"36016;36016",
    "iso:country":"IT",
    "sg:address":"36016 Thiene",
    "sg:city":"Thiene",
    "sg:orig_category":"Pubblica Amministrazione",
    "sg:phone":"+39 0445 361448",
    "sg:postcode":"36016",
    "sg:province":"Vicenza",
    "wof:name":"Guardia Di Finanza",
    "wof:placetype":"venue"
},
  "geometry": {"coordinates":[11.4778594971,45.7035522461],"type":"Point"}
}