{
  "type": "Feature",
  "properties": {
    "iso:country":"IT",
    "sg:address":"P Xx Settembre 19; Pordenone; 22070",
    "sg:classifiers":[
        {
            "category":"Banks & Credit Unions",
            "subcategory":"Bank",
            "type":"Services"
        }
    ],
    "sg:phone":"+39 0434 521814",
    "sg:postcode":"22070",
    "sg:province":"Como",
    "wof:name":"Banca Popolare Friuladria",
    "wof:placetype":"venue"
},
  "geometry": {"coordinates":[9.000445,45.730194],"type":"Point"}
}