{
  "type": "Feature",
  "properties": {
    "iso:country":"IT",
    "sg:address":"7, Via Vaghera 56020 Montopoli In Val D'arno",
    "sg:city":"Montopoli",
    "sg:classifiers":[
        {
            "category":"Personal",
            "subcategory":"Shoe Repair & Shine",
            "type":"Services"
        }
    ],
    "sg:phone":"+39 0571 448028",
    "sg:postcode":"56020",
    "sg:province":"Pisa",
    "sg:tags":[
        "leather"
    ],
    "wof:name":"Zingoni Counters For Footwear Di Zingoni Olinto &",
    "wof:placetype":"venue"
},
  "geometry": {"coordinates":[10.743713,43.691174],"type":"Point"}
}