{
  "type": "Feature",
  "properties": {
    "addr:full":"1, Via Dell' Industria 35010 Vigodarzere Vigodarzere Padova 35010",
    "addr:postcode":"35010;35010",
    "addr:street":"Via Dell ' Industria",
    "iso:country":"IT",
    "sg:address":"1, Via Dell' Industria 35010 Vigodarzere",
    "sg:city":"Vigodarzere",
    "sg:classifiers":[
        {
            "category":"Shopping",
            "subcategory":"Crafts & Fabrics",
            "type":"Retail Goods"
        }
    ],
    "sg:phone":"+39 049 884 1515",
    "sg:postcode":"35010",
    "sg:province":"Padova",
    "wof:name":"Pro.m.i.tess (s.r.l.)",
    "wof:placetype":"venue"
},
  "geometry": {"coordinates":[11.8567733765,45.484588623],"type":"Point"}
}