{
  "type": "Feature",
  "properties": {
    "iso:country":"IT",
    "sg:address":"24020 Cene",
    "sg:city":"Cene",
    "sg:orig_category":"Forniture Per Abbigliamento E Pelletterie",
    "sg:phone":"+39 035 729308",
    "sg:postcode":"24020",
    "sg:province":"Bergamo",
    "wof:name":"Zappella Stefano",
    "wof:placetype":"venue"
},
  "geometry": {"coordinates":[9.666220665,45.6794509888],"type":"Point"}
}