{
  "type": "Feature",
  "properties": {
    "addr:full":"17, Via Maniago 33080 San Quirino San Quirino Pordenone 33080",
    "addr:postcode":"33080;33080",
    "addr:street":"Via Maniago;Quirino San Quirino",
    "iso:country":"IT",
    "sg:address":"17, Via Maniago 33080 San Quirino",
    "sg:city":"San Quirino",
    "sg:classifiers":[
        {
            "category":"Home & Garden",
            "subcategory":"Home Furnishings",
            "type":"Retail Goods"
        }
    ],
    "sg:phone":"+39 39043491491",
    "sg:postcode":"33080",
    "sg:province":"Pordenone",
    "sg:tags":[
        "household"
    ],
    "wof:name":"L.i.c.ar. (s.p.a.)",
    "wof:placetype":"venue"
},
  "geometry": {"coordinates":[12.645801,45.963257],"type":"Point"}
}