{
  "type": "Feature",
  "properties": {
    "addr:full":"144, Via Loretana 60021 Camerano Camerano Ancona 60021",
    "addr:housenumber":"144",
    "addr:postcode":"60021;60021",
    "addr:street":"Via Loretana",
    "iso:country":"IT",
    "sg:address":"144, Via Loretana 60021 Camerano",
    "sg:city":"Camerano",
    "sg:classifiers":[
        {
            "category":"Shopping",
            "type":"Retail Goods"
        }
    ],
    "sg:phone":"+39 39071731424",
    "sg:postcode":"60021",
    "sg:province":"Ancona",
    "sg:tags":[
        "finished",
        "-",
        "metallic"
    ],
    "wof:name":"Magrini Gilberto",
    "wof:placetype":"venue"
},
  "geometry": {"coordinates":[13.5638942719,43.517036438],"type":"Point"}
}