{
  "type": "Feature",
  "properties": {
    "addr:full":"73055 Racale Racale Lecce 73055",
    "addr:postcode":"73055;73055",
    "iso:country":"IT",
    "sg:address":"73055 Racale",
    "sg:city":"Racale",
    "sg:orig_category":"Macchine, Impianti Ed Attrezzature Per Abbigliamento E Pelletterie",
    "sg:phone":"+39 0833 552962",
    "sg:postcode":"73055",
    "sg:province":"Lecce",
    "wof:name":"Nicchiarico Linea Commercio",
    "wof:placetype":"venue"
},
  "geometry": {"coordinates":[18.065794,39.964466],"type":"Point"}
}