{
  "type": "Feature",
  "properties": {
    "iso:country":"IT",
    "sg:address":"14, Via Torino 36060 Romano D'ezzelino",
    "sg:classifiers":[
        {
            "category":"Shopping",
            "subcategory":"Jewelry",
            "type":"Retail Goods"
        }
    ],
    "sg:phone":"+39 0424 832111",
    "sg:postcode":"36060",
    "sg:province":"Vicenza",
    "sg:tags":[
        "jewellery"
    ],
    "wof:name":"Silmar (s.p.a.)",
    "wof:placetype":"venue"
},
  "geometry": {"coordinates":[11.747301,45.788956],"type":"Point"}
}