{
  "type": "Feature",
  "properties": {
    "iso:country":"IT",
    "sg:address":"27040 Cigognola",
    "sg:city":"Cigognola",
    "sg:orig_category":"Imprese Di Costruzioni Civili Ed Industriali",
    "sg:phone":"+39 0385 250355",
    "sg:postcode":"27040",
    "sg:province":"Pavia",
    "wof:name":"Rego Impianti Di Muresu Giovanni",
    "wof:placetype":"venue"
},
  "geometry": {"coordinates":[9.249537,45.039223],"type":"Point"}
}