{
  "type": "Feature",
  "properties": {
    "iso:country":"IT",
    "sg:address":"22036 Erba",
    "sg:city":"Erba",
    "sg:orig_category":"Lavorazioni Metalli, Stampaggio E Saldatura",
    "sg:phone":"+39 031 641610",
    "sg:postcode":"22036",
    "sg:province":"Como",
    "wof:name":"Faer Srl",
    "wof:placetype":"venue"
},
  "geometry": {"coordinates":[9.246387,45.807148],"type":"Point"}
}