{
  "type": "Feature",
  "properties": {
    "iso:country":"IT",
    "sg:address":"13866 Masserano",
    "sg:city":"Masserano",
    "sg:orig_category":"Antifurto",
    "sg:phone":"+39 015 96021",
    "sg:postcode":"13866",
    "sg:province":"Biella",
    "wof:name":"Elettrotecnica R.b. Errebi Snc",
    "wof:placetype":"venue"
},
  "geometry": {"coordinates":[8.088375,45.577629],"type":"Point"}
}