{
  "type": "Feature",
  "properties": {
    "addr:full":"50018 Scandicci Scandicci Firenze 50018",
    "addr:postcode":"50018;50018",
    "iso:country":"IT",
    "sg:address":"50018 Scandicci",
    "sg:city":"Scandicci",
    "sg:classifiers":[
        {
            "category":"Manufacturing",
            "subcategory":"Leather Goods",
            "type":"Manufacturing & Wholesale Goods"
        }
    ],
    "sg:phone":"+39 055 731 0396",
    "sg:postcode":"50018",
    "sg:province":"Firenze",
    "sg:tags":[
        "footwear",
        "skin"
    ],
    "wof:name":"Pielle Srl",
    "wof:placetype":"venue"
},
  "geometry": {"coordinates":[11.160525322,43.7643013],"type":"Point"}
}