{
  "type": "Feature",
  "properties": {
    "iso:country":"IT",
    "sg:address":"Via Alpi 82 63014 Montegranaro",
    "sg:city":"Montegranaro",
    "sg:orig_category":"Ladies' Shoes",
    "sg:phone":"+39 0734 890236",
    "sg:postcode":"63014",
    "sg:province":"Ascoli Piceno",
    "wof:name":"Tentazione Srl",
    "wof:placetype":"venue"
},
  "geometry": {"coordinates":[13.647058,43.258839],"type":"Point"}
}