{
  "type": "Feature",
  "properties": {
    "addr:full":"28017 San Maurizio D'opaglio Novara 28017",
    "addr:postcode":"28017;28017",
    "iso:country":"IT",
    "sg:address":"28017 San Maurizio D'opaglio",
    "sg:classifiers":[
        {
            "category":"Utilities",
            "subcategory":"Water",
            "type":"Services"
        }
    ],
    "sg:phone":"+39 0322 923111",
    "sg:postcode":"28017",
    "sg:province":"Novara",
    "sg:tags":[
        "equipment",
        "valve",
        "measurement"
    ],
    "sg:website":"http://www.giacomini.com",
    "wof:name":"Giacomini Spa",
    "wof:placetype":"venue"
},
  "geometry": {"coordinates":[8.386818,45.78001],"type":"Point"}
}