{
  "type": "Feature",
  "properties": {
    "iso:country":"IT",
    "sg:address":"14030 Castagnole Monferrato",
    "sg:city":"Castagnole Monferrato",
    "sg:orig_category":"Materiali Edili",
    "sg:phone":"+39 0141 292126",
    "sg:postcode":"14030",
    "sg:province":"Asti",
    "wof:name":"Fornace Di Castagnole Monferrato (s.r.l.)",
    "wof:placetype":"venue"
},
  "geometry": {"coordinates":[8.229481,44.881252],"type":"Point"}
}