{
  "type": "Feature",
  "properties": {
    "iso:country":"IT",
    "sg:address":"98, Via Campo D'arrigo 50131 Firenze",
    "sg:city":"Firenze",
    "sg:classifiers":[
        {
            "category":"Manufacturing",
            "subcategory":"Metals",
            "type":"Manufacturing & Wholesale Goods"
        }
    ],
    "sg:phone":"+39 390 555 7351",
    "sg:postcode":"50131",
    "sg:province":"Firenze",
    "sg:tags":[
        "metallurgy",
        "metalworking"
    ],
    "wof:name":"Ferramenta Cobianchi Spa",
    "wof:placetype":"venue"
},
  "geometry": {"coordinates":[11.274930954,43.7812309265],"type":"Point"}
}