{
  "type": "Feature",
  "properties": {
    "iso:country":"IT",
    "sg:address":"2, Via Pacini Giovanni 20131 Milano",
    "sg:city":"Milano",
    "sg:classifiers":[
        {
            "category":"Manufacturing",
            "subcategory":"Motor Vehicles & Parts",
            "type":"Manufacturing & Wholesale Goods"
        }
    ],
    "sg:phone":"+39 39022664846",
    "sg:postcode":"20131",
    "sg:province":"Milano",
    "sg:tags":[
        "engine"
    ],
    "wof:name":"R.i.s.a.m. (s.r.l.)",
    "wof:placetype":"venue"
},
  "geometry": {"coordinates":[9.224793,45.480614],"type":"Point"}
}