{
  "type": "Feature",
  "properties": {
    "addr:full":"Viale Della Repubblica 40; Lissone; 20035 Lissone Milano 20035",
    "addr:housenumber":"40",
    "addr:postcode":"20035;20035",
    "addr:street":"Viale Della Repubblica",
    "iso:country":"IT",
    "sg:address":"Viale Della Repubblica 40; Lissone; 20035",
    "sg:city":"Lissone",
    "sg:classifiers":[
        {
            "category":"Banks & Credit Unions",
            "subcategory":"Bank",
            "type":"Services"
        }
    ],
    "sg:phone":"+39 02 459030",
    "sg:postcode":"20035",
    "sg:province":"Milano",
    "wof:name":"Banca Di Credito Cooperativo, Di Carate Brianza Scarl",
    "wof:placetype":"venue"
},
  "geometry": {"coordinates":[9.249905,45.608929],"type":"Point"}
}