{
  "type": "Feature",
  "properties": {
    "iso:country":"IT",
    "sg:address":"54, Via Alessandro Volta 20090 Cusago",
    "sg:city":"Cusago",
    "sg:classifiers":[
        {
            "category":"Utilities",
            "subcategory":"Electric",
            "type":"Services"
        }
    ],
    "sg:phone":"+39 390 290 3971",
    "sg:postcode":"20090",
    "sg:province":"Milano",
    "sg:tags":[
        "component",
        "electronic"
    ],
    "wof:name":"Ecc Elettronica S.p.a.",
    "wof:placetype":"venue"
},
  "geometry": {"coordinates":[9.073336,45.476891],"type":"Point"}
}