{
  "type": "Feature",
  "properties": {
    "iso:country":"IT",
    "sg:address":"92014 Porto Empedocle",
    "sg:city":"Porto Empedocle",
    "sg:orig_category":"Automobili E Mezzi Di Trasporto",
    "sg:phone":"+39 0922 632789",
    "sg:postcode":"92014",
    "sg:province":"Agrigento",
    "wof:name":"Maria Officina Costr.ribalt",
    "wof:placetype":"venue"
},
  "geometry": {"coordinates":[13.503208,37.312469],"type":"Point"}
}