{
  "type": "Feature",
  "properties": {
    "addr:full":"8, Via Dell' Artigianato 20053 Muggio' Milano 20053",
    "addr:postcode":"20053;20053",
    "addr:street":"Via Dell ' Artigianato;Muggio ' Milano",
    "iso:country":"IT",
    "sg:address":"8, Via Dell' Artigianato 20053 Muggio'",
    "sg:classifiers":[
        {
            "category":"Shopping",
            "type":"Retail Goods"
        }
    ],
    "sg:phone":"+39 39039796272",
    "sg:postcode":"20053",
    "sg:province":"Milano",
    "sg:tags":[
        "finished",
        "-",
        "metallic"
    ],
    "wof:name":"Chemit (s.r.l.)",
    "wof:placetype":"venue"
},
  "geometry": {"coordinates":[9.233253479,45.5858154297],"type":"Point"}
}