{
  "type": "Feature",
  "properties": {
    "addr:full":"28, Via Divisione Acqui 61100 Pesaro Pesaro Pesaro E Urbino 61100",
    "addr:postcode":"61100;61100",
    "addr:street":"Via Divisione Acqui",
    "iso:country":"IT",
    "sg:address":"28, Via Divisione Acqui 61100 Pesaro",
    "sg:city":"Pesaro",
    "sg:classifiers":[
        {
            "category":"Professional",
            "subcategory":"Printing & Photocopies",
            "type":"Services"
        }
    ],
    "sg:phone":"+39 0721 281983",
    "sg:postcode":"61100",
    "sg:province":"Pesaro E Urbino",
    "wof:name":"General Service Snc Di Pratelli M. & C.",
    "wof:placetype":"venue"
},
  "geometry": {"coordinates":[12.8619346619,43.8839263916],"type":"Point"}
}