{
  "type": "Feature",
  "properties": {
    "iso:country":"IT",
    "sg:address":"00183 Roma",
    "sg:city":"Roma",
    "sg:orig_category":"Calzature, Pelletterie E Pelli",
    "sg:phone":"+39 06 700 8295",
    "sg:postcode":"00183",
    "sg:province":"Roma",
    "wof:name":"Belli Germano",
    "wof:placetype":"venue"
},
  "geometry": {"coordinates":[12.505873,41.882904],"type":"Point"}
}