{
  "type": "Feature",
  "properties": {
    "iso:country":"IT",
    "sg:address":"20048 Carate Brianza",
    "sg:city":"Carate Brianza",
    "sg:orig_category":"Lavorazioni Metalli, Stampaggio E Saldatura",
    "sg:phone":"+39 036 299 1695",
    "sg:postcode":"20048",
    "sg:province":"Milano",
    "wof:name":"Butti Di Butti Carlo & C. Snc",
    "wof:placetype":"venue"
},
  "geometry": {"coordinates":[9.22439,45.668251],"type":"Point"}
}