{
  "type": "Feature",
  "properties": {
    "iso:country":"IT",
    "sg:address":"6, Via Pavone 25023 Gottolengo",
    "sg:city":"Gottolengo",
    "sg:orig_category":"Miscellaneous Products",
    "sg:phone":"+39 030 995 1233",
    "sg:postcode":"25023",
    "sg:province":"Brescia",
    "wof:name":"Gottinghen (s.p.a.)",
    "wof:placetype":"venue"
},
  "geometry": {"coordinates":[10.2667713165,45.2874107361],"type":"Point"}
}