{
  "type": "Feature",
  "properties": {
    "iso:country":"IT",
    "sg:address":"Via Cavour 2/a 30024 Musile Di Piave",
    "sg:city":"Musile di Piave",
    "sg:classifiers":[
        {
            "category":"Bars & Pubs",
            "subcategory":"Champagne Bar",
            "type":"Food & Drink"
        }
    ],
    "sg:phone":"+39 0421 592811",
    "sg:postcode":"30024",
    "sg:province":"Venezia",
    "sg:tags":[
        "table",
        "caf\u00e9"
    ],
    "sg:website":"www.housekit.com",
    "wof:name":"House Kit Furniture S.r.l.",
    "wof:placetype":"venue"
},
  "geometry": {"coordinates":[12.338784,45.434338],"type":"Point"}
}