{
  "type": "Feature",
  "properties": {
    "iso:country":"IT",
    "sg:address":"24069 Trescore Balneario",
    "sg:city":"Trescore Balneario",
    "sg:orig_category":"Servizi E Lavori Industria Chimica",
    "sg:phone":"+39 035 941959",
    "sg:postcode":"24069",
    "sg:province":"Bergamo",
    "wof:name":"Pesenti Fabrizio",
    "wof:placetype":"venue"
},
  "geometry": {"coordinates":[9.841463,45.69249],"type":"Point"}
}