{
  "type": "Feature",
  "properties": {
    "iso:country":"IT",
    "sg:address":"24, Via Guglielmo Marconi 23893 Cassago Brianza",
    "sg:city":"Cassago Brianza",
    "sg:classifiers":[
        {
            "category":"Home & Garden",
            "subcategory":"Home Furnishings",
            "type":"Retail Goods"
        }
    ],
    "sg:phone":"+39 39039921311",
    "sg:postcode":"23893",
    "sg:province":"Lecco",
    "sg:tags":[
        "household"
    ],
    "wof:name":"Enrico Casiraghi S.p.a.",
    "wof:placetype":"venue"
},
  "geometry": {"coordinates":[9.390071,45.852982],"type":"Point"}
}