{
  "type": "Feature",
  "properties": {
    "iso:country":"IT",
    "sg:address":"52100 Arezzo",
    "sg:city":"Arezzo",
    "sg:classifiers":[
        {
            "category":"Health Services",
            "subcategory":"Health Practitioner",
            "type":"Services"
        }
    ],
    "sg:phone":"+39 0575 381690",
    "sg:postcode":"52100",
    "sg:province":"Arezzo",
    "sg:tags":[
        "medici"
    ],
    "wof:name":"Cardini Pier Antonio",
    "wof:placetype":"venue"
},
  "geometry": {"coordinates":[11.855974,43.472115],"type":"Point"}
}