{
  "type": "Feature",
  "properties": {
    "addr:full":"23013 Cosio Valtellino Cosio Valtellino Sondrio 23013",
    "addr:postcode":"23013;23013",
    "iso:country":"IT",
    "sg:address":"23013 Cosio Valtellino",
    "sg:city":"Cosio Valtellino",
    "sg:orig_category":"Dolciumi E Gelati. Condimenti, Spezie, Infusi E Caffe'",
    "sg:phone":"+39 0342 638013",
    "sg:postcode":"23013",
    "sg:province":"Sondrio",
    "wof:name":"Valtellina Zuccheri Di Colli Eugenio E C. Snc",
    "wof:placetype":"venue"
},
  "geometry": {"coordinates":[9.545313,46.131432],"type":"Point"}
}