{
  "type": "Feature",
  "properties": {
    "iso:country":"IT",
    "sg:address":"88, Via De Gasperi 20017 Rho",
    "sg:city":"Rho",
    "sg:classifiers":[
        {
            "category":"Utilities",
            "subcategory":"Electric",
            "type":"Services"
        }
    ],
    "sg:phone":"+39 390 293 3331",
    "sg:postcode":"20017",
    "sg:province":"Milano",
    "sg:tags":[
        "component",
        "electronic"
    ],
    "wof:name":"Klinger Spa",
    "wof:placetype":"venue"
},
  "geometry": {"coordinates":[9.080031,45.52861],"type":"Point"}
}