{
  "type": "Feature",
  "properties": {
    "iso:country":"IT",
    "sg:address":"37043 Castagnaro",
    "sg:city":"Castagnaro",
    "sg:classifiers":[
        {
            "category":"Sports & Exercise",
            "subcategory":"Tennis Court",
            "type":"Entertainment"
        }
    ],
    "sg:phone":"+39 0442 92006",
    "sg:postcode":"37043",
    "sg:province":"Verona",
    "sg:tags":[
        "e",
        "lo",
        "tempo",
        "libero",
        "per",
        "impianti",
        "il",
        "attrezzature"
    ],
    "wof:name":"Luminal Park Di Brenzan Angelo",
    "wof:placetype":"venue"
},
  "geometry": {"coordinates":[11.408874,45.118603],"type":"Point"}
}