{
  "type": "Feature",
  "properties": {
    "addr:full":"63033 Monteprandone Monteprandone Ascoli Piceno 63033",
    "addr:postcode":"63033;63033",
    "iso:country":"IT",
    "sg:address":"63033 Monteprandone",
    "sg:city":"Monteprandone",
    "sg:orig_category":"Forniture Per Attivita' Industriali",
    "sg:phone":"+39 0735 710590",
    "sg:postcode":"63033",
    "sg:province":"Ascoli Piceno",
    "wof:name":"Malavolta Spa",
    "wof:placetype":"venue"
},
  "geometry": {"coordinates":[13.8675823212,42.897228241],"type":"Point"}
}