{
  "type": "Feature",
  "properties": {
    "iso:country":"IT",
    "sg:address":"20081 Abbiategrasso",
    "sg:city":"Abbiategrasso",
    "sg:orig_category":"Agenzie D'affari E Servizi Commerciali",
    "sg:phone":"+39 02 946 6660",
    "sg:postcode":"20081",
    "sg:province":"Milano",
    "wof:name":"Tanca Maurizio",
    "wof:placetype":"venue"
},
  "geometry": {"coordinates":[9.190282,45.499363],"type":"Point"}
}