{
  "type": "Feature",
  "properties": {
    "addr:full":"Km 46,485, S.s. 98 70033 Corato Corato Bari 70033",
    "addr:housenumber":"46,485",
    "addr:postcode":"70033;70033",
    "addr:street":"S.S. 98",
    "iso:country":"IT",
    "sg:address":"Km 46,485, S.s. 98 70033 Corato",
    "sg:city":"Corato",
    "sg:classifiers":[
        {
            "category":"Food & Beverages",
            "subcategory":"Groceries & Convenience Stores",
            "type":"Retail Goods"
        }
    ],
    "sg:phone":"+39 080 872 1821",
    "sg:postcode":"70033",
    "sg:province":"Bari",
    "sg:tags":[
        "product",
        "related"
    ],
    "sg:website":"http://www.granoro.it:ws_end: :mark:ws:http://www.paginegialle.it/granoro",
    "wof:name":"Pastificio Granoro A. Mastromauro",
    "wof:placetype":"venue"
},
  "geometry": {"coordinates":[16.8692913055,41.1260528564],"type":"Point"}
}