{
  "type": "Feature",
  "properties": {
    "iso:country":"IT",
    "sg:address":"16154 Genova",
    "sg:city":"Genova",
    "sg:orig_category":"Servizi E Lavori Per Ecologia E Smaltimento Rifiuti. Arte Ed Artigianato Artistico. Servizi Ausiliari Di Sorveglianza, Manutenzione E Pulizia",
    "sg:phone":"+39 010 651 4334",
    "sg:postcode":"16154",
    "sg:province":"Genova",
    "wof:name":"La Trouvaille",
    "wof:placetype":"venue"
},
  "geometry": {"coordinates":[8.841789,44.437885],"type":"Point"}
}