{
  "type": "Feature",
  "properties": {
    "iso:country":"IT",
    "sg:address":"70031 Andria",
    "sg:city":"Andria",
    "sg:orig_category":"Servizi Per Lo Sport E Il Tempo Libero. Servizi Al Turismo",
    "sg:phone":"+39 0883 557888",
    "sg:postcode":"70031",
    "sg:province":"Bari",
    "wof:name":"L'ottagono Hotel - Ristorante",
    "wof:placetype":"venue"
},
  "geometry": {"coordinates":[16.22868,41.138248],"type":"Point"}
}