{
  "type": "Feature",
  "properties": {
    "iso:country":"IT",
    "sg:address":"Via Fratelli Crbi 30 C; Montecavolo; 42020",
    "sg:classifiers":[
        {
            "category":"Banks & Credit Unions",
            "subcategory":"Bank",
            "type":"Services"
        }
    ],
    "sg:phone":"+39 0522 880058",
    "sg:postcode":"42020",
    "sg:province":"Reggio Nell'Emilia",
    "wof:name":"Credito Emiliano Spa",
    "wof:placetype":"venue"
},
  "geometry": {"coordinates":[10.53674,44.631889],"type":"Point"}
}