{
  "type": "Feature",
  "properties": {
    "iso:country":"IT",
    "sg:address":"20093 Cologno Monzese",
    "sg:city":"Cologno Monzese",
    "sg:orig_category":"Macchine, Impianti Ed Attrezzature Industria Chimica",
    "sg:phone":"+39 02 253 6044",
    "sg:postcode":"20093",
    "sg:province":"Milano",
    "wof:name":"Industrialvetro (s.r.l.)",
    "wof:placetype":"venue"
},
  "geometry": {"coordinates":[9.277932,45.540089],"type":"Point"}
}