{
  "type": "Feature",
  "properties": {
    "addr:full":"03039 Sora Sora Frosinone 03039",
    "addr:housenumber":"03039",
    "addr:postcode":"03039",
    "iso:country":"IT",
    "sg:address":"03039 Sora",
    "sg:city":"Sora",
    "sg:orig_category":"Forniture E Prodotti Informatici. Forniture Per Uffici",
    "sg:phone":"+39 0776 839064",
    "sg:postcode":"03039",
    "sg:province":"Frosinone",
    "wof:name":"Green Company Srl",
    "wof:placetype":"venue"
},
  "geometry": {"coordinates":[13.3551130295,41.6345977783],"type":"Point"}
}