{
  "type": "Feature",
  "properties": {
    "iso:country":"IT",
    "sg:address":"00040 Pomezia",
    "sg:city":"Pomezia",
    "sg:orig_category":"Prodotti E Manufatti In Materie Plastiche",
    "sg:phone":"+39 06 916 1901",
    "sg:postcode":"00040",
    "sg:province":"Roma",
    "wof:name":"Covalca Plastici Srl",
    "wof:placetype":"venue"
},
  "geometry": {"coordinates":[12.5086097717,41.682434082],"type":"Point"}
}