{
  "type": "Feature",
  "properties": {
    "addr:full":"89125 Reggio Calabria RC",
    "addr:postcode":"89125",
    "iso:country":"IT",
    "sg:address":"89125 Reggio Calabria",
    "sg:classifiers":[
        {
            "category":"Shopping",
            "subcategory":"Hobbies, Toys, & Games",
            "type":"Retail Goods"
        }
    ],
    "sg:phone":"+39 0965 331541",
    "sg:province":"RC",
    "sg:tags":[
        "article",
        "sport",
        "supply"
    ],
    "wof:name":"Linea Blu Srl Sport Diving Center",
    "wof:placetype":"venue"
},
  "geometry": {"coordinates":[15.647851,38.110126],"type":"Point"}
}