{
  "type": "Feature",
  "properties": {
    "iso:country":"IT",
    "sg:address":"Via Martin L. King 17 47100 Forli'",
    "sg:classifiers":[
        {
            "category":"Home & Garden",
            "subcategory":"Home Furnishings",
            "type":"Retail Goods"
        }
    ],
    "sg:phone":"+39 0543 83200",
    "sg:postcode":"47100",
    "sg:province":"Forl\u00ec-Cesena",
    "sg:tags":[
        "plate",
        "easter",
        "christmas"
    ],
    "sg:website":"www.flamigni.it",
    "wof:name":"Flamigni Srl",
    "wof:placetype":"venue"
},
  "geometry": {"coordinates":[11.980461,43.994766],"type":"Point"}
}