{
  "type": "Feature",
  "properties": {
    "addr:full":"50050 Galleno Firenze 50050",
    "addr:postcode":"50050;50050",
    "addr:street":"Galleno",
    "iso:country":"IT",
    "sg:address":"50050 Galleno",
    "sg:orig_category":"Calzature, Pelletterie E Pelli",
    "sg:phone":"+39 0571 299839",
    "sg:postcode":"50050",
    "sg:province":"Firenze",
    "wof:name":"Rosania Francesco",
    "wof:placetype":"venue"
},
  "geometry": {"coordinates":[11.243247,43.762333],"type":"Point"}
}