{
  "type": "Feature",
  "properties": {
    "addr:full":"47900 Rimini Rimini Rimini 47900",
    "addr:postcode":"47900;47900",
    "iso:country":"IT",
    "sg:address":"47900 Rimini",
    "sg:city":"Rimini",
    "sg:classifiers":[
        {
            "category":"Shopping",
            "subcategory":"Gifts & Souvenirs",
            "type":"Retail Goods"
        }
    ],
    "sg:phone":"+39 0541 51949",
    "sg:postcode":"47900",
    "sg:province":"Rimini",
    "sg:tags":[
        "gifts",
        "business"
    ],
    "wof:name":"Antica Confetteria",
    "wof:placetype":"venue"
},
  "geometry": {"coordinates":[12.569373,44.060223],"type":"Point"}
}