{
  "type": "Feature",
  "properties": {
    "addr:full":"16147 Genova Genova Genova 16147",
    "addr:postcode":"16147;16147",
    "iso:country":"IT",
    "sg:address":"16147 Genova",
    "sg:city":"Genova",
    "sg:orig_category":"Scuole Di Orientamento, Formazione E Addestramento Professionale",
    "sg:phone":"+39 010 387787",
    "sg:postcode":"16147",
    "sg:province":"Genova",
    "wof:name":"Cnos-fap Liguria",
    "wof:placetype":"venue"
},
  "geometry": {"coordinates":[8.996583,44.396793],"type":"Point"}
}