{
  "type": "Feature",
  "properties": {
    "iso:country":"IT",
    "sg:address":"21050 Marnate",
    "sg:city":"Marnate",
    "sg:orig_category":"Forniture Per Attivita' Industriali",
    "sg:phone":"+39 0331 367245",
    "sg:postcode":"21050",
    "sg:province":"Varese",
    "wof:name":"Sp. In. (s.a.s.)",
    "wof:placetype":"venue"
},
  "geometry": {"coordinates":[8.9220209122,45.6274223328],"type":"Point"}
}