{
  "type": "Feature",
  "properties": {
    "iso:country":"IT",
    "sg:address":"Via Giuseppe Mazzini , 29/37 27031 Candia Lomellina",
    "sg:city":"Candia Lomellina",
    "sg:classifiers":[
        {
            "category":"Communications",
            "subcategory":"Newspaper",
            "type":"Services"
        }
    ],
    "sg:phone":"+39 0384 74558",
    "sg:postcode":"27031",
    "sg:province":"Pavia",
    "sg:tags":[
        "press",
        "printing",
        "rotary"
    ],
    "sg:website":"www.cerutti.com",
    "wof:name":"Componenti Grafici Srl",
    "wof:placetype":"venue"
},
  "geometry": {"coordinates":[9.156563,45.185886],"type":"Point"}
}