{
  "type": "Feature",
  "properties": {
    "iso:country":"IT",
    "sg:address":"25016 Ghedi",
    "sg:city":"Ghedi",
    "sg:orig_category":"Tessuti E Stoffe. Filati E Materie Prime Tessili",
    "sg:phone":"+39 030 905 0398",
    "sg:postcode":"25016",
    "sg:province":"Brescia",
    "wof:name":"Roccatura  Caty  Di Brontesi Nives E Caterina S.n.c.",
    "wof:placetype":"venue"
},
  "geometry": {"coordinates":[10.268217,45.393871],"type":"Point"}
}