{
  "type": "Feature",
  "properties": {
    "iso:country":"IT",
    "sg:address":"55, Via Grumello 24127 Bergamo",
    "sg:city":"Bergamo",
    "sg:classifiers":[
        {
            "category":"Professional",
            "subcategory":"Engineering",
            "type":"Services"
        }
    ],
    "sg:phone":"+39 39035254061",
    "sg:postcode":"24127",
    "sg:province":"Bergamo",
    "sg:tags":[
        "machine",
        "-",
        "mechanical"
    ],
    "wof:name":"Schieppati Arrigo Di Edoardo & G. Franco Schieppati",
    "wof:placetype":"venue"
},
  "geometry": {"coordinates":[9.640421,45.671024],"type":"Point"}
}