{
  "type": "Feature",
  "properties": {
    "iso:country":"IT",
    "sg:address":"00185 Roma",
    "sg:city":"Roma",
    "sg:orig_category":"Scuole Private - Elementari",
    "sg:phone":"+39 06 7049 7241",
    "sg:postcode":"00185",
    "sg:province":"Roma",
    "wof:name":"Istituto Santa Maria",
    "wof:placetype":"venue"
},
  "geometry": {"coordinates":[12.504848,41.889786],"type":"Point"}
}