{
  "type": "Feature",
  "properties": {
    "iso:country":"IT",
    "sg:address":"20123 Milano",
    "sg:city":"Milano",
    "sg:orig_category":"Accessori Moda D'abbigliamento. Forniture Per Abbigliamento E Pelletterie",
    "sg:phone":"+39 02 8645 3143",
    "sg:postcode":"20123",
    "sg:province":"Milano",
    "wof:name":"Mariella Giuseppe",
    "wof:placetype":"venue"
},
  "geometry": {"coordinates":[9.177815,45.459469],"type":"Point"}
}