{
  "type": "Feature",
  "properties": {
    "iso:country":"IT",
    "sg:address":"3, Strada Per Vicolungo 28060 Recetto",
    "sg:city":"Recetto",
    "sg:classifiers":[
        {
            "category":"Parking",
            "subcategory":"Lot",
            "type":"Transportation"
        }
    ],
    "sg:phone":"+39 0321 836613",
    "sg:postcode":"28060",
    "sg:province":"Novara",
    "sg:tags":[
        "transport",
        "road"
    ],
    "wof:name":"T.d.e. International Srl",
    "wof:placetype":"venue"
},
  "geometry": {"coordinates":[8.439581,45.459854],"type":"Point"}
}