{
  "type": "Feature",
  "properties": {
    "addr:full":"20129 Milano Milano Milano 20129",
    "addr:postcode":"20129;20129",
    "iso:country":"IT",
    "sg:address":"20129 Milano",
    "sg:city":"Milano",
    "sg:orig_category":"Calzature, Pelletterie E Pelli. Servizi E Lavori Per Abbigliamento E Pelletterie",
    "sg:phone":"+39 02 733778",
    "sg:postcode":"20129",
    "sg:province":"Milano",
    "wof:name":"Rinnovatrice Moderna (la)",
    "wof:placetype":"venue"
},
  "geometry": {"coordinates":[9.214749,45.468426],"type":"Point"}
}