{
  "type": "Feature",
  "properties": {
    "iso:country":"IT",
    "sg:address":"31040 Nervesa Della Battaglia",
    "sg:city":"Nervesa della Battaglia",
    "sg:orig_category":"Carrozzerie Autoveicoli Industriali E Speciali",
    "sg:phone":"+39 0422 881413",
    "sg:postcode":"31040",
    "sg:province":"Treviso",
    "sg:website":"http://www.pilato-spa.it",
    "wof:name":"Pilato Spa",
    "wof:placetype":"venue"
},
  "geometry": {"coordinates":[12.244755,45.806667],"type":"Point"}
}