{
  "type": "Feature",
  "properties": {
    "iso:country":"IT",
    "sg:address":"Contrada Cucullo 66026 Ortona",
    "sg:city":"Ortona",
    "sg:classifiers":[
        {
            "category":"Food & Beverages",
            "subcategory":"Groceries & Convenience Stores",
            "type":"Retail Goods"
        }
    ],
    "sg:phone":"+39 085 903 1342",
    "sg:postcode":"66026",
    "sg:province":"Chieti",
    "sg:tags":[
        "drink"
    ],
    "wof:name":"Citra Vini",
    "wof:placetype":"venue"
},
  "geometry": {"coordinates":[14.361895,42.306915],"type":"Point"}
}