{
  "type": "Feature",
  "properties": {
    "iso:country":"IT",
    "sg:address":"Via Callano 35 70051 Barletta",
    "sg:city":"Barletta",
    "sg:classifiers":[
        {
            "category":"Shopping",
            "subcategory":"Shoes",
            "type":"Retail Goods"
        }
    ],
    "sg:phone":"+39 0883 332290",
    "sg:postcode":"70051",
    "sg:province":"Bari",
    "sg:tags":[
        "mountaineers'",
        "boots",
        "hiking",
        "trekking"
    ],
    "wof:name":"Dennis Di Desario Vincenzo Ruggiero",
    "wof:placetype":"venue"
},
  "geometry": {"coordinates":[16.2969455719,41.3084907532],"type":"Point"}
}