{
  "type": "Feature",
  "properties": {
    "iso:country":"IT",
    "sg:address":"00186 Roma",
    "sg:city":"Roma",
    "sg:orig_category":"Carni, Salumi E Pesci",
    "sg:phone":"+39 06 6880 1415",
    "sg:postcode":"00186",
    "sg:province":"Roma",
    "wof:name":"Fadda Antonio",
    "wof:placetype":"venue"
},
  "geometry": {"coordinates":[12.474966,41.901775],"type":"Point"}
}