{
  "type": "Feature",
  "properties": {
    "addr:full":"Via Dell Artigianato 16/018 41040 Spezzano Modena 41040",
    "addr:housenumber":"16 / 018",
    "addr:postcode":"41040;41040",
    "addr:street":"Via Dell Artigianato",
    "iso:country":"IT",
    "sg:address":"Via Dell Artigianato 16/018 41040 Spezzano",
    "sg:classifiers":[
        {
            "category":"Shopping",
            "subcategory":"Crafts & Fabrics",
            "type":"Retail Goods"
        }
    ],
    "sg:phone":"+39 0536 843716",
    "sg:postcode":"41040",
    "sg:province":"Modena",
    "sg:tags":[
        "decorative",
        "ceramic",
        "artistic"
    ],
    "sg:website":"www.patriziopini.it",
    "wof:name":"Patrizio Pini Srl Design",
    "wof:placetype":"venue"
},
  "geometry": {"coordinates":[10.855484,44.558525],"type":"Point"}
}