{
  "type": "Feature",
  "properties": {
    "iso:country":"IT",
    "sg:address":"56010 Lugnano",
    "sg:orig_category":"Agenzie D'affari E Servizi Commerciali",
    "sg:phone":"+39 050 702652",
    "sg:postcode":"56010",
    "sg:province":"Pisa",
    "wof:name":"Toti Roberto",
    "wof:placetype":"venue"
},
  "geometry": {"coordinates":[10.547668,43.687294],"type":"Point"}
}