{
  "type": "Feature",
  "properties": {
    "iso:country":"IT",
    "sg:address":"24046 Osio Sotto",
    "sg:city":"Osio Sotto",
    "sg:orig_category":"Manufacturers: Prefabbricati",
    "sg:phone":"+39 035 881050",
    "sg:postcode":"24046",
    "sg:province":"Bergamo",
    "wof:name":"L'arte Funeraria Monumenti",
    "wof:placetype":"venue"
},
  "geometry": {"coordinates":[9.562161,45.584728],"type":"Point"}
}