{
  "type": "Feature",
  "properties": {
    "iso:country":"IT",
    "sg:address":"10091 Alpignano",
    "sg:city":"Alpignano",
    "sg:orig_category":"Servizi E Lavori Per Agricoltura E Zootecnia. Animali Domestici",
    "sg:phone":"+39 011 967 9157",
    "sg:postcode":"10091",
    "sg:province":"Torino",
    "wof:name":"City Dog's Sas Di Buffa Giancarlo & C.",
    "wof:placetype":"venue"
},
  "geometry": {"coordinates":[7.5745892525,45.0684051514],"type":"Point"}
}