{
  "type": "Feature",
  "properties": {
    "iso:country":"IT",
    "sg:address":"10143 Torino",
    "sg:city":"Torino",
    "sg:orig_category":"Forniture Per Edilizia E Lavori Pubblici",
    "sg:phone":"+39 011 776 1745",
    "sg:postcode":"10143",
    "sg:province":"Torino",
    "wof:name":"Minelli Diego",
    "wof:placetype":"venue"
},
  "geometry": {"coordinates":[7.6497721672,45.0836257935],"type":"Point"}
}