{
  "type": "Feature",
  "properties": {
    "addr:full":"20049 Concorezzo Concorezzo Milano 20049",
    "addr:postcode":"20049;20049",
    "iso:country":"IT",
    "sg:address":"20049 Concorezzo",
    "sg:city":"Concorezzo",
    "sg:classifiers":[
        {
            "category":"Banks & Credit Unions",
            "subcategory":"Bank",
            "type":"Services"
        }
    ],
    "sg:phone":"+39 039 604 3346",
    "sg:postcode":"20049",
    "sg:province":"Milano",
    "sg:tags":[
        "services",
        "publishing",
        "supply"
    ],
    "wof:name":"Adolfo Felisati & C. Snc",
    "wof:placetype":"venue"
},
  "geometry": {"coordinates":[9.3254766464,45.5865058899],"type":"Point"}
}