{
  "type": "Feature",
  "properties": {
    "addr:full":"00198 Roma Roma Roma 00198",
    "addr:postcode":"00198;00198",
    "iso:country":"IT",
    "sg:address":"00198 Roma",
    "sg:city":"Roma",
    "sg:orig_category":"Pubblica Amministrazione",
    "sg:phone":"+39 06 855 5360",
    "sg:postcode":"00198",
    "sg:province":"Roma",
    "wof:name":"Caserma Villa Umberto - Reparto A Cavallo",
    "wof:placetype":"venue"
},
  "geometry": {"coordinates":[12.4927244186,41.9163169861],"type":"Point"}
}