{
  "type": "Feature",
  "properties": {
    "iso:country":"IT",
    "sg:address":"Viale Cappuccini, 66034 Lanciano",
    "sg:city":"Lanciano",
    "sg:classifiers":[
        {
            "category":"Banks & Credit Unions",
            "subcategory":"Financial Services",
            "type":"Services"
        }
    ],
    "sg:phone":"+39 390 872 7041",
    "sg:postcode":"66034",
    "sg:province":"Chieti",
    "sg:tags":[
        "banking",
        "finance",
        "insurance"
    ],
    "wof:name":"Banca Popolare Di Lanciano E Sulmona Soccoop Arl",
    "wof:placetype":"venue"
},
  "geometry": {"coordinates":[14.3878736496,42.2269096375],"type":"Point"}
}