{
  "type": "Feature",
  "properties": {
    "addr:full":"20090 Cusago Cusago Milano 20090",
    "addr:postcode":"20090;20090",
    "iso:country":"IT",
    "sg:address":"20090 Cusago",
    "sg:city":"Cusago",
    "sg:orig_category":"Stampi, Maschere E Ferri Da Trancia",
    "sg:phone":"+39 02 9039 0195",
    "sg:postcode":"20090",
    "sg:province":"Milano",
    "wof:name":"Marinoni Giancarlo & C. Snc",
    "wof:placetype":"venue"
},
  "geometry": {"coordinates":[9.04667,45.458546],"type":"Point"}
}