{
  "type": "Feature",
  "properties": {
    "iso:country":"IT",
    "sg:address":"17014 Cairo Montenotte",
    "sg:city":"Cairo Montenotte",
    "sg:orig_category":"Scuole E Servizi Scolastici. Ospedali E Servizi Sanitari",
    "sg:phone":"+39 019 501388",
    "sg:postcode":"17014",
    "sg:province":"Savona",
    "wof:name":"Istituto Attivita' Motorie",
    "wof:placetype":"venue"
},
  "geometry": {"coordinates":[8.319747,44.396843],"type":"Point"}
}