{
  "type": "Feature",
  "properties": {
    "iso:country":"IT",
    "sg:address":"10032 Brandizzo",
    "sg:city":"Brandizzo",
    "sg:orig_category":"Macchine, Impianti Ed Attrezzature Per Abbigliamento E Pelletterie. Macchine E Impianti Per Attivita' Commerciali Ed Artigianali",
    "sg:phone":"+39 011 913 7139",
    "sg:postcode":"10032",
    "sg:province":"Torino",
    "wof:name":"Roselli Pierpaolo",
    "wof:placetype":"venue"
},
  "geometry": {"coordinates":[7.517962,45.068066],"type":"Point"}
}