{
  "type": "Feature",
  "properties": {
    "addr:full":"25, Via B.buozzi 40057 Granarolo Dell'emilia Bologna 40057",
    "addr:postcode":"40057;40057",
    "addr:street":"Via B.Buozzi",
    "iso:country":"IT",
    "sg:address":"25, Via B.buozzi 40057 Granarolo Dell'emilia",
    "sg:classifiers":[
        {
            "category":"Shopping",
            "subcategory":"Stationery & Office Supplies",
            "type":"Retail Goods"
        }
    ],
    "sg:phone":"+39 051 602 0111",
    "sg:postcode":"40057",
    "sg:province":"Bologna",
    "sg:tags":[
        "professional"
    ],
    "wof:name":"Allestimenti Sabatini (s.p.a.)",
    "wof:placetype":"venue"
},
  "geometry": {"coordinates":[11.3920383453,44.5539398193],"type":"Point"}
}