{
  "type": "Feature",
  "properties": {
    "addr:full":"2, Localita' Miralbelloo 61047 San Lorenzo In Campo San Lorenzo in Campo Pesaro E Urbino 61047",
    "addr:postcode":"61047;61047",
    "addr:street":"Localita ' Miralbelloo",
    "iso:country":"IT",
    "sg:address":"2, Localita' Miralbelloo 61047 San Lorenzo In Campo",
    "sg:city":"San Lorenzo in Campo",
    "sg:classifiers":[
        {
            "category":"Real Estate",
            "subcategory":"Architect",
            "type":"Services"
        }
    ],
    "sg:phone":"+39 0721 776782",
    "sg:postcode":"61047",
    "sg:province":"Pesaro E Urbino",
    "sg:tags":[
        "textile",
        "clothing"
    ],
    "wof:name":"Confezioni Futura (s.r.l.)",
    "wof:placetype":"venue"
},
  "geometry": {"coordinates":[12.529803,43.633556],"type":"Point"}
}