{
  "type": "Feature",
  "properties": {
    "iso:country":"IT",
    "sg:address":"Via U. Giordano, 1/13 21010 San Macario",
    "sg:city":"San macario",
    "sg:orig_category":"Mixers For Processing Basic Materials",
    "sg:phone":"+39 0331 707070",
    "sg:postcode":"21010",
    "sg:province":"Varese",
    "sg:website":"www.cacciaeng.com",
    "wof:name":"Caccia Engineering Spa",
    "wof:placetype":"venue"
},
  "geometry": {"coordinates":[8.8263845444,45.8176040649],"type":"Point"}
}