{
  "type": "Feature",
  "properties": {
    "addr:full":"00176 Roma Roma Roma 00176",
    "addr:postcode":"00176;00176",
    "iso:country":"IT",
    "sg:address":"00176 Roma",
    "sg:city":"Roma",
    "sg:orig_category":"Pronto Soccorso",
    "sg:phone":"+39 06 2172 8284",
    "sg:postcode":"00176",
    "sg:province":"Roma",
    "wof:name":"Nova Sanitas 2000 Srl",
    "wof:placetype":"venue"
},
  "geometry": {"coordinates":[12.5397052765,41.8835678101],"type":"Point"}
}