{
  "type": "Feature",
  "properties": {
    "addr:full":"30, Via Mattei Enrico 06016 San Giustino San Giustino Perugia 06016",
    "addr:postcode":"06016;06016",
    "addr:street":"Via Mattei Enrico",
    "iso:country":"IT",
    "sg:address":"30, Via Mattei Enrico 06016 San Giustino",
    "sg:city":"San Giustino",
    "sg:classifiers":[
        {
            "category":"Professional",
            "subcategory":"Printing & Photocopies",
            "type":"Services"
        }
    ],
    "sg:phone":"+39 075 856 0333",
    "sg:postcode":"06016",
    "sg:province":"Perugia",
    "wof:name":"Vimer S.r.l.",
    "wof:placetype":"venue"
},
  "geometry": {"coordinates":[12.3891716003,43.1107025146],"type":"Point"}
}