{
  "type": "Feature",
  "properties": {
    "addr:full":"56029 Santa Croce Sull'arno Pisa 56029",
    "addr:postcode":"56029;56029",
    "iso:country":"IT",
    "sg:address":"56029 Santa Croce Sull'arno",
    "sg:orig_category":"Servizi E Lavori Per Abbigliamento E Pelletterie",
    "sg:phone":"+39 0571 30816",
    "sg:postcode":"56029",
    "sg:province":"Pisa",
    "sg:website":"http://www.italicapelli.it",
    "wof:name":"Italica Pelli Srl",
    "wof:placetype":"venue"
},
  "geometry": {"coordinates":[10.76332,43.71294],"type":"Point"}
}