{
  "type": "Feature",
  "properties": {
    "iso:country":"IT",
    "sg:address":"90141 Palermo",
    "sg:city":"Palermo",
    "sg:orig_category":"Cartolerie",
    "sg:phone":"+39 091 662 2085",
    "sg:postcode":"90141",
    "sg:province":"Palermo",
    "wof:name":"Non Solo Ufficio",
    "wof:placetype":"venue"
},
  "geometry": {"coordinates":[13.353692,38.124439],"type":"Point"}
}