{
  "type": "Feature",
  "properties": {
    "iso:country":"IT",
    "sg:address":"90145 Palermo",
    "sg:city":"Palermo",
    "sg:orig_category":"Pompe. Macchine, Strumenti Ed Apparecchi Per Attivita' Industriali",
    "sg:phone":"+39 091 305442",
    "sg:postcode":"90145",
    "sg:province":"Palermo",
    "wof:name":"Gam Clima Di Motisi Giuseppe & C.",
    "wof:placetype":"venue"
},
  "geometry": {"coordinates":[13.3458166122,38.1256027222],"type":"Point"}
}