{
  "type": "Feature",
  "properties": {
    "addr:full":"25136 Brescia Brescia Brescia 25136",
    "addr:postcode":"25136;25136",
    "iso:country":"IT",
    "sg:address":"25136 Brescia",
    "sg:city":"Brescia",
    "sg:orig_category":"Professionisti - Studi E Servizi Ed Associazioni Di Interesse Aziendale. Associazioni Ed Organismi Di Interesse Pubblico",
    "sg:phone":"+39 030 200 8859",
    "sg:postcode":"25136",
    "sg:province":"Brescia",
    "wof:name":"Federazione Italiana Medici Di Medicina Generale",
    "wof:placetype":"venue"
},
  "geometry": {"coordinates":[10.227725029,45.5830421448],"type":"Point"}
}