{
  "type": "Feature",
  "properties": {
    "iso:country":"IT",
    "sg:address":"38027 Male'",
    "sg:orig_category":"Isolanti Termici Ed Acustici - Commercio",
    "sg:phone":"+39 0463 901608",
    "sg:postcode":"38027",
    "sg:province":"Trento",
    "wof:name":"Vetreria Benedetti Di Benedetti Fulvio",
    "wof:placetype":"venue"
},
  "geometry": {"coordinates":[10.91416,46.349072],"type":"Point"}
}