{
  "type": "Feature",
  "properties": {
    "addr:full":"20030 Senago Senago Milano 20030",
    "addr:postcode":"20030;20030",
    "iso:country":"IT",
    "sg:address":"20030 Senago",
    "sg:city":"Senago",
    "sg:orig_category":"Calzature, Pelletterie E Pelli. Servizi E Lavori Per Abbigliamento E Pelletterie",
    "sg:phone":"+39 02 9948 2314",
    "sg:postcode":"20030",
    "sg:province":"Milano",
    "wof:name":"Pieri Massimo Enrico",
    "wof:placetype":"venue"
},
  "geometry": {"coordinates":[9.163568,45.528141],"type":"Point"}
}