{
  "type": "Feature",
  "properties": {
    "iso:country":"IT",
    "sg:address":"70026 Modugno",
    "sg:city":"Modugno",
    "sg:orig_category":"Macchine Ed Impianti Per Edilizia E Lavori Pubblici. Apparecchiature E Sistemi Per Magazzinaggio E Movimentazione",
    "sg:phone":"+39 080 505 7807",
    "sg:postcode":"70026",
    "sg:province":"Bari",
    "sg:website":"http://www.transpuglia.it",
    "wof:name":"Transpuglia Srl",
    "wof:placetype":"venue"
},
  "geometry": {"coordinates":[16.782442,41.086365],"type":"Point"}
}