{
  "type": "Feature",
  "properties": {
    "addr:full":"Via Virgiliana 44012 Bondeno Bondeno Ferrara 44012",
    "addr:postcode":"44012;44012",
    "addr:street":"Via Virgiliana",
    "iso:country":"IT",
    "sg:address":"Via Virgiliana 44012 Bondeno",
    "sg:city":"Bondeno",
    "sg:classifiers":[
        {
            "category":"Wholesale",
            "subcategory":"Machinery & Supplies",
            "type":"Manufacturing & Wholesale Goods"
        }
    ],
    "sg:phone":"+39 0532 883373",
    "sg:postcode":"44012",
    "sg:province":"Ferrara",
    "sg:tags":[
        "-",
        "agriculture",
        "equipment"
    ],
    "wof:name":"Guaresi (s.p.a.)",
    "wof:placetype":"venue"
},
  "geometry": {"coordinates":[11.47064,44.867485],"type":"Point"}
}