{
  "type": "Feature",
  "properties": {
    "iso:country":"IT",
    "sg:address":"32031 Alano Di Piave",
    "sg:city":"Alano di Piave",
    "sg:orig_category":"Termotecnica E Riscaldamento, Apparecchiature E Servizi",
    "sg:phone":"+39 0439 779141",
    "sg:postcode":"32031",
    "sg:province":"Belluno",
    "wof:name":"Industrie Meccaniche Di Alano (s.r.l.)",
    "wof:placetype":"venue"
},
  "geometry": {"coordinates":[11.921476,45.90987],"type":"Point"}
}