{
  "type": "Feature",
  "properties": {
    "addr:full":"50018 Scandicci - Loc. Badia A Settimo Badia a settimo Firenze 50018",
    "addr:postcode":"50018;50018",
    "addr:street":"Settimo",
    "iso:country":"IT",
    "sg:address":"50018 Scandicci - Loc. Badia A Settimo",
    "sg:city":"Badia a settimo",
    "sg:orig_category":"Ottica Apparecchi E Strumenti - Produzione E Ingrosso",
    "sg:phone":"+39 055 722 1367",
    "sg:postcode":"50018",
    "sg:province":"Firenze",
    "sg:website":"http://www.silo.it",
    "wof:name":"Gestione Silo Srl",
    "wof:placetype":"venue"
},
  "geometry": {"coordinates":[11.150411,43.730701],"type":"Point"}
}