{
  "type": "Feature",
  "properties": {
    "iso:country":"IT",
    "sg:address":"27100 Pavia",
    "sg:city":"Pavia",
    "sg:orig_category":"Scuole E Servizi Scolastici. Servizi Per Lo Sport E Il Tempo Libero",
    "sg:phone":"+39 0382 33528",
    "sg:postcode":"27100",
    "sg:province":"Pavia",
    "wof:name":"Audioshop E.m.p. Di Rossi Giorgio & C. Snc",
    "wof:placetype":"venue"
},
  "geometry": {"coordinates":[9.149671,45.18605],"type":"Point"}
}