{
  "type": "Feature",
  "properties": {
    "iso:country":"IT",
    "sg:address":"10036 Settimo Torinese",
    "sg:city":"Settimo Torinese",
    "sg:orig_category":"Forniture Per Uffici. Regalistica Aziendale",
    "sg:phone":"+39 011 896 2411",
    "sg:postcode":"10036",
    "sg:province":"Torino",
    "wof:name":"Universal Spa",
    "wof:placetype":"venue"
},
  "geometry": {"coordinates":[7.7575273514,45.1483383179],"type":"Point"}
}