{
  "type": "Feature",
  "properties": {
    "iso:country":"IT",
    "sg:address":"00153 Roma",
    "sg:city":"Roma",
    "sg:orig_category":"Professionisti - Studi E Servizi Ed Associazioni Di Interesse Aziendale. Associazioni Ed Organismi Di Interesse Pubblico",
    "sg:phone":"+39 06 574 5120",
    "sg:postcode":"00153",
    "sg:province":"Roma",
    "wof:name":"F.i.e.i. Federitalia Export Import Recognized By W.e.i.o.",
    "wof:placetype":"venue"
},
  "geometry": {"coordinates":[12.4867534637,41.8827438354],"type":"Point"}
}