{
  "type": "Feature",
  "properties": {
    "iso:country":"IT",
    "sg:address":"44/46, Via Sibillini 63018 Porto Sant'elpidio",
    "sg:classifiers":[
        {
            "category":"Personal",
            "subcategory":"Shoe Repair & Shine",
            "type":"Services"
        }
    ],
    "sg:phone":"+39 0734 993967",
    "sg:postcode":"63018",
    "sg:province":"Ascoli Piceno",
    "sg:tags":[
        "leather"
    ],
    "wof:name":"Calzaturificio Chimpanze' Lido",
    "wof:placetype":"venue"
},
  "geometry": {"coordinates":[13.74056,43.24873],"type":"Point"}
}