{
  "type": "Feature",
  "properties": {
    "iso:country":"IT",
    "sg:address":"20026 Novate Milanese",
    "sg:city":"Novate Milanese",
    "sg:orig_category":"Termotecnica E Riscaldamento, Apparecchiature E Servizi. Prodotti Vari In Metallo",
    "sg:phone":"+39 02 354 8805",
    "sg:postcode":"20026",
    "sg:province":"Milano",
    "wof:name":"Peluso Sergio",
    "wof:placetype":"venue"
},
  "geometry": {"coordinates":[9.134332,45.541058],"type":"Point"}
}