{
  "type": "Feature",
  "properties": {
    "addr:full":"20092 Cinisello Balsamo Cinisello Balsamo Milano 20092",
    "addr:postcode":"20092;20092",
    "iso:country":"IT",
    "sg:address":"20092 Cinisello Balsamo",
    "sg:city":"Cinisello Balsamo",
    "sg:orig_category":"Servizi Ausiliari Dei Mezzi Di Trasporto",
    "sg:phone":"+39 02 240 4656",
    "sg:postcode":"20092",
    "sg:province":"Milano",
    "wof:name":"Monaci Ambrogio Luigi",
    "wof:placetype":"venue"
},
  "geometry": {"coordinates":[9.232647,45.547836],"type":"Point"}
}