{
  "type": "Feature",
  "properties": {
    "addr:full":"13836 Cossato Cossato Biella 13836",
    "addr:postcode":"13836;13836",
    "iso:country":"IT",
    "sg:address":"13836 Cossato",
    "sg:city":"Cossato",
    "sg:orig_category":"Servizi E Lavori Per Abbigliamento E Pelletterie",
    "sg:phone":"+39 015 93496",
    "sg:postcode":"13836",
    "sg:province":"Biella",
    "wof:name":"Ramtex - Rammendatura Tessuti",
    "wof:placetype":"venue"
},
  "geometry": {"coordinates":[8.181062,45.544518],"type":"Point"}
}