{
  "type": "Feature",
  "properties": {
    "iso:country":"IT",
    "sg:address":"37123 Verona",
    "sg:city":"Verona",
    "sg:orig_category":"Associazioni Sindacali E Di Categoria",
    "sg:phone":"+39 045 867 4611",
    "sg:postcode":"37123",
    "sg:province":"Verona",
    "wof:name":"C.g.i.l. Camera Del Lavoro",
    "wof:placetype":"venue"
},
  "geometry": {"coordinates":[10.982215,45.437229],"type":"Point"}
}