{
  "type": "Feature",
  "properties": {
    "addr:full":"98121 Messina Messina Messina 98121",
    "addr:postcode":"98121;98121",
    "iso:country":"IT",
    "sg:address":"98121 Messina",
    "sg:city":"Messina",
    "sg:orig_category":"Materiali E Componenti Elettronici",
    "sg:phone":"+39 090 51863",
    "sg:postcode":"98121",
    "sg:province":"Messina",
    "wof:name":"Fancello Bartolomeo",
    "wof:placetype":"venue"
},
  "geometry": {"coordinates":[15.556231,38.206974],"type":"Point"}
}