{
  "type": "Feature",
  "properties": {
    "addr:full":"14100 Asti Asti Asti 14100",
    "addr:postcode":"14100;14100",
    "iso:country":"IT",
    "sg:address":"14100 Asti",
    "sg:city":"Asti",
    "sg:classifiers":[
        {
            "category":"Health Services",
            "subcategory":"Health Practitioner",
            "type":"Services"
        }
    ],
    "sg:phone":"+39 0141 353519",
    "sg:postcode":"14100",
    "sg:province":"Asti",
    "sg:tags":[
        "medici"
    ],
    "wof:name":"Prosio Pier Elio",
    "wof:placetype":"venue"
},
  "geometry": {"coordinates":[8.0675506592,44.8354415894],"type":"Point"}
}