{
  "type": "Feature",
  "properties": {
    "iso:country":"IT",
    "sg:address":"37139 Verona",
    "sg:city":"Verona",
    "sg:orig_category":"Apparecchiature Ed Attrezzature Meccaniche",
    "sg:phone":"+39 045 851 0860",
    "sg:postcode":"37139",
    "sg:province":"Verona",
    "wof:name":"B.t.b. Srl",
    "wof:placetype":"venue"
},
  "geometry": {"coordinates":[10.891172,45.453144],"type":"Point"}
}