{
  "type": "Feature",
  "properties": {
    "iso:country":"IT",
    "sg:address":"37066 Sommacampagna",
    "sg:city":"Sommacampagna",
    "sg:orig_category":"Macchine, Impianti Ed Attrezzature Per Agricoltura E Zootecnia. Prodotti Vari In Metallo. Apparecchiature E Sistemi Per Magazzinaggio E Movimentazione",
    "sg:phone":"+39 045 858 1720",
    "sg:postcode":"37066",
    "sg:province":"Verona",
    "wof:name":"B.s.p. Engineering S.r.l.",
    "wof:placetype":"venue"
},
  "geometry": {"coordinates":[10.890699,45.412811],"type":"Point"}
}