{
  "type": "Feature",
  "properties": {
    "iso:country":"IT",
    "sg:address":"83, V. Libbia 52031 Anghiari",
    "sg:city":"Anghiari",
    "sg:classifiers":[
        {
            "category":"Shopping",
            "subcategory":"Jewelry",
            "type":"Retail Goods"
        }
    ],
    "sg:phone":"+39 0575 788494",
    "sg:postcode":"52031",
    "sg:province":"Arezzo",
    "sg:tags":[
        "jewellery"
    ],
    "sg:website":"http://www.nicolpreziosi.it",
    "wof:name":"Nicol Preziosi 560 Ar",
    "wof:placetype":"venue"
},
  "geometry": {"coordinates":[11.938296,43.551933],"type":"Point"}
}