{
  "type": "Feature",
  "properties": {
    "addr:full":"180, V. Brigata Osoppo - Vigonovo 33074 Fontanafredda Fontanafredda Pordenone 33074",
    "addr:housenumber":"180",
    "addr:postcode":"33074;33074",
    "addr:street":"V. Brigata Osoppo",
    "iso:country":"IT",
    "sg:address":"180, V. Brigata Osoppo - Vigonovo 33074 Fontanafredda",
    "sg:city":"Fontanafredda",
    "sg:classifiers":[
        {
            "category":"Manufacturing",
            "subcategory":"Lumber",
            "type":"Manufacturing & Wholesale Goods"
        }
    ],
    "sg:phone":"+39 39043499194",
    "sg:postcode":"33074",
    "sg:province":"Pordenone",
    "sg:tags":[
        "wood"
    ],
    "sg:website":"http://www.cotimber.com",
    "wof:name":"Cotimber Srl",
    "wof:placetype":"venue"
},
  "geometry": {"coordinates":[12.531343,45.978977],"type":"Point"}
}