{
  "type": "Feature",
  "properties": {
    "iso:country":"IT",
    "sg:address":"18018 Arma Di Taggia",
    "sg:city":"Arma di Taggia",
    "sg:classifiers":[
        {
            "category":"Banks & Credit Unions",
            "subcategory":"Investment Brokerage",
            "type":"Services"
        }
    ],
    "sg:phone":"+39 0184 476275",
    "sg:postcode":"18018",
    "sg:province":"Imperia",
    "sg:tags":[
        "services",
        "various",
        "auxiliary",
        "transport",
        "public"
    ],
    "wof:name":"C.l.i.o.f. Srl",
    "wof:placetype":"venue"
},
  "geometry": {"coordinates":[7.839515,43.874702],"type":"Point"}
}