{
  "type": "Feature",
  "properties": {
    "iso:country":"IT",
    "sg:address":"20030 Barlassina",
    "sg:city":"Barlassina",
    "sg:classifiers":[
        {
            "category":"Shopping",
            "subcategory":"Stationery & Office Supplies",
            "type":"Retail Goods"
        }
    ],
    "sg:phone":"+39 036 256 5906",
    "sg:postcode":"20030",
    "sg:province":"Milano",
    "sg:tags":[
        "equipment",
        "furniture",
        "furnishing",
        "professional"
    ],
    "sg:website":"http://www.vago.com",
    "wof:name":"Vago Forniture Srl",
    "wof:placetype":"venue"
},
  "geometry": {"coordinates":[9.1298828125,45.6565628052],"type":"Point"}
}