{
  "type": "Feature",
  "properties": {
    "iso:country":"IT",
    "sg:address":"40026 Imola",
    "sg:city":"Imola",
    "sg:orig_category":"Elettronica Professionale E Di Consumo. Automazione E Macchine Per Ufficio. Forniture Per Congressi, Fiere E Manifestazioni",
    "sg:phone":"+39 0542 641735",
    "sg:postcode":"40026",
    "sg:province":"Bologna",
    "wof:name":"V.b. Di Baldi Vito E C. (s.n.c.)",
    "wof:placetype":"venue"
},
  "geometry": {"coordinates":[11.73855,44.360035],"type":"Point"}
}