{
  "type": "Feature",
  "properties": {
    "iso:country":"IT",
    "sg:address":"42100 Reggio Emilia",
    "sg:orig_category":"Musica. Shopping",
    "sg:phone":"+39 0522 433785",
    "sg:postcode":"42100",
    "sg:province":"Reggio Nell'Emilia",
    "wof:name":"Discoland Sas Di Paride Bonetta",
    "wof:placetype":"venue"
},
  "geometry": {"coordinates":[10.6283960342,44.6984977722],"type":"Point"}
}