{
  "type": "Feature",
  "properties": {
    "iso:country":"IT",
    "sg:address":"33058 San Giorgio Di Nogaro",
    "sg:city":"San Giorgio di Nogaro",
    "sg:orig_category":"Lavorazioni Meccaniche E Servizi",
    "sg:phone":"+39 0431 65987",
    "sg:postcode":"33058",
    "sg:province":"Udine",
    "wof:name":"Mar.met. Srl",
    "wof:placetype":"venue"
},
  "geometry": {"coordinates":[13.216495,45.83321],"type":"Point"}
}