{
  "type": "Feature",
  "properties": {
    "addr:full":"Via Gioberti Vincenzo 88 10128 Torino Torino Torino 10128",
    "addr:housenumber":"88",
    "addr:postcode":"10128;10128",
    "addr:street":"Via Gioberti Vincenzo",
    "iso:country":"IT",
    "sg:address":"Via Gioberti Vincenzo 88 10128 Torino",
    "sg:city":"Torino",
    "sg:classifiers":[
        {
            "category":"Professional",
            "subcategory":"Business Services",
            "type":"Services"
        }
    ],
    "sg:phone":"+39 011 590680",
    "sg:postcode":"10128",
    "sg:province":"Torino",
    "sg:tags":[
        "import",
        "industrial"
    ],
    "wof:name":"Arcelor Long Commercial Torino Srl",
    "wof:placetype":"venue"
},
  "geometry": {"coordinates":[7.686619,45.07056],"type":"Point"}
}