{
  "type": "Feature",
  "properties": {
    "iso:country":"IT",
    "sg:address":"S. S. 115 Incrocio Marina Di Palma 92020 Palma Di Montechiaro",
    "sg:city":"Palma di Montechiaro",
    "sg:classifiers":[
        {
            "category":"Food & Beverages",
            "subcategory":"Fruits & Vegetables",
            "type":"Retail Goods"
        }
    ],
    "sg:phone":"+39 0922 965396",
    "sg:postcode":"92020",
    "sg:province":"Agrigento",
    "wof:name":"L'ortofrutticola La Palma D'oro Di Mangiavillano Antonino",
    "wof:placetype":"venue"
},
  "geometry": {"coordinates":[13.5769557953,37.3111877441],"type":"Point"}
}