{
  "type": "Feature",
  "properties": {
    "addr:full":"02100 Rieti Rieti Rieti 02100",
    "addr:postcode":"02100;02100",
    "iso:country":"IT",
    "sg:address":"02100 Rieti",
    "sg:city":"Rieti",
    "sg:orig_category":"Studi E Consulenze Legali E Notarili. Avvocati, Notai E Servizi Legali. Professionisti - Studi E Servizi Ed Associazioni Di Interesse Aziendale",
    "sg:phone":"+39 0746 203077",
    "sg:postcode":"02100",
    "sg:province":"Rieti",
    "sg:website":"http://www.palombatruini.it",
    "wof:name":"Truini Palomba Avv. Maria Giuseppina",
    "wof:placetype":"venue"
},
  "geometry": {"coordinates":[12.853925,42.409313],"type":"Point"}
}