{
  "type": "Feature",
  "properties": {
    "addr:full":"20121 Milano Milano Milano 20121",
    "addr:postcode":"20121;20121",
    "iso:country":"IT",
    "sg:address":"20121 Milano",
    "sg:city":"Milano",
    "sg:orig_category":"Servizi Per Aziende, Manifestazioni E Supporto Agli Scambi Commerciali. Ambasciate Ed Enti Internazionali",
    "sg:phone":"+39 02 762951",
    "sg:postcode":"20121",
    "sg:province":"Milano",
    "wof:name":"A.t. Kearney S.p.a.",
    "wof:placetype":"venue"
},
  "geometry": {"coordinates":[9.201565,45.471016],"type":"Point"}
}