{
  "type": "Feature",
  "properties": {
    "addr:full":"1, Via Bosco 35010 Vigonza Vigonza Padova 35010",
    "addr:postcode":"35010;35010",
    "addr:street":"Via Bosco",
    "iso:country":"IT",
    "sg:address":"1, Via Bosco 35010 Vigonza",
    "sg:city":"Vigonza",
    "sg:classifiers":[
        {
            "category":"Shopping",
            "subcategory":"Clothing, Apparel, & Fashions",
            "type":"Retail Goods"
        }
    ],
    "sg:phone":"+39 049 800 5011",
    "sg:postcode":"35010",
    "sg:province":"Padova",
    "sg:tags":[
        "clothes"
    ],
    "wof:name":"Camiceria Scabo (s.r.l.)",
    "wof:placetype":"venue"
},
  "geometry": {"coordinates":[11.938967,45.466213],"type":"Point"}
}