{
  "type": "Feature",
  "properties": {
    "iso:country":"IT",
    "sg:address":"80143 Napoli",
    "sg:city":"Napoli",
    "sg:orig_category":"Servizi E Lavori Per Industria Alimentare E Bevande",
    "sg:phone":"+39 081 200873",
    "sg:postcode":"80143",
    "sg:province":"Napoli",
    "wof:name":"Commiss.campanofrutta Castaldo S.a.s",
    "wof:placetype":"venue"
},
  "geometry": {"coordinates":[14.284961,40.858421],"type":"Point"}
}