{
  "type": "Feature",
  "properties": {
    "iso:country":"IT",
    "sg:address":"60020 Falconara Marittima",
    "sg:orig_category":"Arredo Cucina Ed Elettrodomestici. Elettrodomestici",
    "sg:phone":"+39 071 918 8006",
    "sg:postcode":"60020",
    "sg:province":"Ancona",
    "wof:name":"Andreoni & C. Srl",
    "wof:placetype":"venue"
},
  "geometry": {"coordinates":[13.370046,43.610958],"type":"Point"}
}