{
  "type": "Feature",
  "properties": {
    "addr:full":"16142 Genova Genova Genova 16142",
    "addr:postcode":"16142;16142",
    "iso:country":"IT",
    "sg:address":"16142 Genova",
    "sg:city":"Genova",
    "sg:orig_category":"Forniture Alle Strutture Ricettive. Macchine E Impianti Per Attivita' Commerciali Ed Artigianali",
    "sg:phone":"+39 010 816345",
    "sg:postcode":"16142",
    "sg:province":"Genova",
    "wof:name":"Franegar Sas Di Fraguglia Garbarino & C.",
    "wof:placetype":"venue"
},
  "geometry": {"coordinates":[8.9604177475,44.4215698242],"type":"Point"}
}