{
  "type": "Feature",
  "properties": {
    "addr:full":"10148 Torino Torino Torino 10148",
    "addr:postcode":"10148;10148",
    "iso:country":"IT",
    "sg:address":"10148 Torino",
    "sg:city":"Torino",
    "sg:orig_category":"Distributors: Automatici - Commercio E Gestione",
    "sg:phone":"+39 011 220 1826",
    "sg:postcode":"10148",
    "sg:province":"Torino",
    "sg:website":"http://www.ristormatik.it",
    "wof:name":"Ristor Matik Srl",
    "wof:placetype":"venue"
},
  "geometry": {"coordinates":[7.682576,45.108791],"type":"Point"}
}