{
  "type": "Feature",
  "properties": {
    "addr:full":"22, Via Monti Sibillini 63015 Monte Urano Monte Urano Ascoli Piceno 63015",
    "addr:postcode":"63015;63015",
    "addr:street":"Via Monti Sibillini",
    "iso:country":"IT",
    "sg:address":"22, Via Monti Sibillini 63015 Monte Urano",
    "sg:city":"Monte Urano",
    "sg:classifiers":[
        {
            "category":"Personal",
            "subcategory":"Shoe Repair & Shine",
            "type":"Services"
        }
    ],
    "sg:phone":"+39 0734 842468",
    "sg:postcode":"63015",
    "sg:province":"Ascoli Piceno",
    "sg:tags":[
        "leather"
    ],
    "wof:name":"Termoformati 2000 Di Malaigia Andrea & C. Snc",
    "wof:placetype":"venue"
},
  "geometry": {"coordinates":[13.669399,43.206303],"type":"Point"}
}