{
  "type": "Feature",
  "properties": {
    "addr:full":"84085 Mercato San Severino Mercato San Severino Salerno 84085",
    "addr:postcode":"84085;84085",
    "iso:country":"IT",
    "sg:address":"84085 Mercato San Severino",
    "sg:city":"Mercato San Severino",
    "sg:orig_category":"Legatorie",
    "sg:phone":"+39 089 879108",
    "sg:postcode":"84085",
    "sg:province":"Salerno",
    "wof:name":"Grafiche S. Antonio Sas Di Moriniello F & C.",
    "wof:placetype":"venue"
},
  "geometry": {"coordinates":[14.75483,40.785053],"type":"Point"}
}