{
  "type": "Feature",
  "properties": {
    "iso:country":"IT",
    "sg:address":"Localita' Argentera 08029 Siniscola",
    "sg:city":"Siniscola",
    "sg:classifiers":[
        {
            "category":"Shopping",
            "subcategory":"Clothing, Apparel, & Fashions",
            "type":"Retail Goods"
        }
    ],
    "sg:phone":"+39 0784 877217",
    "sg:postcode":"08029",
    "sg:province":"Nuoro",
    "sg:tags":[
        "clothes"
    ],
    "wof:name":"Calze Ros Mary & Co",
    "wof:placetype":"venue"
},
  "geometry": {"coordinates":[9.330436,40.321007],"type":"Point"}
}