{
  "type": "Feature",
  "properties": {
    "iso:country":"IT",
    "sg:address":"6, Via Cappelletta 15046 San Salvatore Monferrato",
    "sg:city":"San Salvatore Monferrato",
    "sg:classifiers":[
        {
            "category":"Shopping",
            "subcategory":"Jewelry",
            "type":"Retail Goods"
        }
    ],
    "sg:phone":"+39 0131 237315",
    "sg:postcode":"15046",
    "sg:province":"Alessandria",
    "sg:tags":[
        "jewellery"
    ],
    "wof:name":"Stilnovo S.r.l.",
    "wof:placetype":"venue"
},
  "geometry": {"coordinates":[8.563966,44.994347],"type":"Point"}
}