{
  "type": "Feature",
  "properties": {
    "iso:country":"IT",
    "sg:address":"59100 Prato",
    "sg:city":"Prato",
    "sg:orig_category":"Abbigliamento Esterno, Maglierie E Pelliccerie. Calzature, Pelletterie E Pelli",
    "sg:phone":"+39 0574 623708",
    "sg:postcode":"59100",
    "sg:province":"Prato",
    "wof:name":"Fcm Di Franco Messineo E C. Sas",
    "wof:placetype":"venue"
},
  "geometry": {"coordinates":[11.0957,43.882587],"type":"Point"}
}