{
  "type": "Feature",
  "properties": {
    "iso:country":"IT",
    "sg:address":"Via Chellavanna 93 84010 Molina Di Vietri Sul Mare",
    "sg:classifiers":[
        {
            "category":"Manufacturing",
            "subcategory":"Paper Products",
            "type":"Manufacturing & Wholesale Goods"
        }
    ],
    "sg:phone":"+39 089 210221",
    "sg:postcode":"84010",
    "sg:province":"Salerno",
    "sg:tags":[
        "cardboard",
        "package"
    ],
    "sg:website":"www.merikartonvietrese.it",
    "wof:name":"Merikarton Vietrese Srl",
    "wof:placetype":"venue"
},
  "geometry": {"coordinates":[14.717933,40.684166],"type":"Point"}
}