{
  "type": "Feature",
  "properties": {
    "iso:country":"IT",
    "sg:address":"30, Viale Commercio 41012 Carpi",
    "sg:city":"Carpi",
    "sg:classifiers":[
        {
            "category":"Retail",
            "subcategory":"Animal Services",
            "type":"Services"
        }
    ],
    "sg:phone":"+39 39059694042",
    "sg:postcode":"41012",
    "sg:province":"Modena",
    "sg:tags":[
        "breeding"
    ],
    "wof:name":"Filozoo (s.p.a.)",
    "wof:placetype":"venue"
},
  "geometry": {"coordinates":[10.854295,44.78849],"type":"Point"}
}