{
  "type": "Feature",
  "properties": {
    "iso:country":"IT",
    "sg:address":"12060 Bossolasco",
    "sg:city":"Bossolasco",
    "sg:orig_category":"Ricambi E Componenti Dei Mezzi Di Trasporto",
    "sg:phone":"+39 0173 799017",
    "sg:postcode":"12060",
    "sg:province":"Cuneo",
    "wof:name":"Electro-parts S.p.a.",
    "wof:placetype":"venue"
},
  "geometry": {"coordinates":[8.064356,44.540176],"type":"Point"}
}