{
  "type": "Feature",
  "properties": {
    "iso:country":"IT",
    "sg:address":"45100 Rovigo",
    "sg:city":"Rovigo",
    "sg:orig_category":"Automobili E Mezzi Di Trasporto",
    "sg:phone":"+39 0425 34868",
    "sg:postcode":"45100",
    "sg:province":"Rovigo",
    "wof:name":"Due Ruote Snc Di Bedendo Enrico & C.",
    "wof:placetype":"venue"
},
  "geometry": {"coordinates":[11.790097,45.069592],"type":"Point"}
}