{
  "type": "Feature",
  "properties": {
    "addr:full":"00197 Roma Roma Roma 00197",
    "addr:postcode":"00197;00197",
    "iso:country":"IT",
    "sg:address":"00197 Roma",
    "sg:city":"Roma",
    "sg:orig_category":"Forniture Per Agricoltura E Zootecnia. Animali Domestici",
    "sg:phone":"+39 06 807 4650",
    "sg:postcode":"00197",
    "sg:province":"Roma",
    "wof:name":"Per Loro Con Amore Di Iellamo Massimiliano",
    "wof:placetype":"venue"
},
  "geometry": {"coordinates":[12.4925737381,41.9240112305],"type":"Point"}
}