{
  "type": "Feature",
  "properties": {
    "iso:country":"IT",
    "sg:address":"10, Via Dell' Industria 31052 Maserada Sul Piave",
    "sg:city":"Maserada sul Piave",
    "sg:classifiers":[
        {
            "category":"Manufacturing",
            "subcategory":"Metals",
            "type":"Manufacturing & Wholesale Goods"
        }
    ],
    "sg:phone":"+39 0422 877010",
    "sg:postcode":"31052",
    "sg:province":"Treviso",
    "sg:tags":[
        "processing"
    ],
    "wof:name":"R.m. Stampati Metalli S.r.l.",
    "wof:placetype":"venue"
},
  "geometry": {"coordinates":[12.3051347733,45.7621459961],"type":"Point"}
}