{
  "type": "Feature",
  "properties": {
    "iso:country":"IT",
    "sg:address":"107, V. Fabio Filzi 45030 Ceneselli",
    "sg:city":"Ceneselli",
    "sg:classifiers":[
        {
            "category":"Manufacturing",
            "subcategory":"Food",
            "type":"Manufacturing & Wholesale Goods"
        }
    ],
    "sg:phone":"+39 39042588058",
    "sg:postcode":"45030",
    "sg:province":"Rovigo",
    "sg:tags":[
        "equipment",
        "processing",
        "-",
        "machinery"
    ],
    "sg:website":"http://www.polesanagrassi.com",
    "wof:name":"Polesana Grassi Snc",
    "wof:placetype":"venue"
},
  "geometry": {"coordinates":[11.3702421188,45.0141067505],"type":"Point"}
}