{
  "type": "Feature",
  "properties": {
    "iso:country":"IT",
    "sg:address":"20052 Monza",
    "sg:city":"Monza",
    "sg:orig_category":"Gioielleria, Oreficeria E Argenteria",
    "sg:phone":"+39 039 741657",
    "sg:postcode":"20052",
    "sg:province":"Milano",
    "wof:name":"Eterea Srl",
    "wof:placetype":"venue"
},
  "geometry": {"coordinates":[9.181125,45.478111],"type":"Point"}
}