{
  "type": "Feature",
  "properties": {
    "iso:country":"IT",
    "sg:address":"Fondamenta Radi Lorenzo 24 30141 Venezia",
    "sg:city":"Venezia",
    "sg:classifiers":[
        {
            "category":"Professional",
            "subcategory":"Art Services",
            "type":"Services"
        }
    ],
    "sg:phone":"+39 041 739388",
    "sg:postcode":"30141",
    "sg:province":"Venezia",
    "sg:tags":[
        "glass",
        "article"
    ],
    "sg:website":"www.auretoso.it",
    "wof:name":"Aureliano Toso Srl",
    "wof:placetype":"venue"
},
  "geometry": {"coordinates":[12.359614,45.458645],"type":"Point"}
}