{
  "type": "Feature",
  "properties": {
    "iso:country":"IT",
    "sg:address":"22060 Novedrate",
    "sg:city":"Novedrate",
    "sg:orig_category":"Prodotti E Manufatti In Materie Plastiche",
    "sg:phone":"+39 031 791863",
    "sg:postcode":"22060",
    "sg:province":"Como",
    "wof:name":"Tecnipol (s.n.c.)",
    "wof:placetype":"venue"
},
  "geometry": {"coordinates":[9.1280698776,45.696231842],"type":"Point"}
}