{
  "type": "Feature",
  "properties": {
    "iso:country":"IT",
    "sg:address":"22, V. Filippo Turati 22060 Carugo",
    "sg:city":"Carugo",
    "sg:classifiers":[
        {
            "category":"Manufacturing",
            "subcategory":"Metals",
            "type":"Manufacturing & Wholesale Goods"
        }
    ],
    "sg:phone":"+39 39031758428",
    "sg:postcode":"22060",
    "sg:province":"Como",
    "sg:tags":[
        "metallurgy",
        "metalworking"
    ],
    "sg:website":"http://www.paginegialle.it/lanzini",
    "wof:name":"Lanzini Luigi & C. Sas",
    "wof:placetype":"venue"
},
  "geometry": {"coordinates":[9.0854558945,45.8119659424],"type":"Point"}
}