{
  "type": "Feature",
  "properties": {
    "iso:country":"IT",
    "sg:address":"56010 Vicopisano",
    "sg:city":"Vicopisano",
    "sg:orig_category":"Arredamenti E Mobili Professionali. Forniture Alle Strutture Ricettive. Arredi Ed Attrezzature Per Attivita' Commerciali Ed Artigianali",
    "sg:phone":"+39 050 704000",
    "sg:postcode":"56010",
    "sg:province":"Pisa",
    "sg:website":"http://www.arredamentitaglioli.it",
    "wof:name":"Taglioli Arredamenti",
    "wof:placetype":"venue"
},
  "geometry": {"coordinates":[10.533777,43.691277],"type":"Point"}
}