{
  "type": "Feature",
  "properties": {
    "iso:country":"IT",
    "sg:address":"20080 Besate",
    "sg:city":"Besate",
    "sg:orig_category":"Prodotti Alimentari",
    "sg:phone":"+39 02 905 0095",
    "sg:postcode":"20080",
    "sg:province":"Milano",
    "wof:name":"Corotti Lorella",
    "wof:placetype":"venue"
},
  "geometry": {"coordinates":[8.9688415527,45.3120002747],"type":"Point"}
}