{
  "type": "Feature",
  "properties": {
    "iso:country":"IT",
    "sg:address":"25040 Angolo Terme",
    "sg:city":"Angolo Terme",
    "sg:orig_category":"Macchine, Impianti Ed Attrezzature Industria Chimica. Vetro: Prodotti E Lavorazioni",
    "sg:phone":"+39 036 454 8051",
    "sg:postcode":"25040",
    "sg:province":"Brescia",
    "wof:name":"Soffieria Artigiana Di Zanelli B. M. & C. Snc",
    "wof:placetype":"venue"
},
  "geometry": {"coordinates":[10.144483,45.89217],"type":"Point"}
}