{
  "type": "Feature",
  "properties": {
    "addr:full":"20142 Milano Milano Milano 20142",
    "addr:postcode":"20142;20142",
    "iso:country":"IT",
    "sg:address":"20142 Milano",
    "sg:city":"Milano",
    "sg:orig_category":"Prodotti Finiti Stampati. Articoli Da Regalo. Arte Ed Artigianato Artistico. Shopping",
    "sg:phone":"+39 02 846 5274",
    "sg:postcode":"20142",
    "sg:province":"Milano",
    "wof:name":"Centro Arte Mige S.r.l.",
    "wof:placetype":"venue"
},
  "geometry": {"coordinates":[9.1684780121,45.4429931641],"type":"Point"}
}