{
  "type": "Feature",
  "properties": {
    "iso:country":"IT",
    "sg:address":"12031 Bagnolo Piemonte",
    "sg:city":"Bagnolo Piemonte",
    "sg:orig_category":"Macchine, Impianti Ed Attrezzature Per Agricoltura E Zootecnia. Macchine Ed Impianti Per Edilizia E Lavori Pubblici",
    "sg:phone":"+39 0175 348139",
    "sg:postcode":"12031",
    "sg:province":"Cuneo",
    "sg:website":"http://www.picorent.com",
    "wof:name":"Picotto F.lli E C. Snc",
    "wof:placetype":"venue"
},
  "geometry": {"coordinates":[7.316876,44.759411],"type":"Point"}
}