{
  "type": "Feature",
  "properties": {
    "addr:full":"10, Via Solferino 20020 Magnago Magnago Milano 20020",
    "addr:postcode":"20020;20020",
    "addr:street":"Via Solferino",
    "iso:country":"IT",
    "sg:address":"10, Via Solferino 20020 Magnago",
    "sg:city":"Magnago",
    "sg:classifiers":[
        {
            "category":"Shopping",
            "subcategory":"Crafts & Fabrics",
            "type":"Retail Goods"
        }
    ],
    "sg:phone":"+39 0331 658165",
    "sg:postcode":"20020",
    "sg:province":"Milano",
    "wof:name":"Tessitura Giannoni S.p.a.",
    "wof:placetype":"venue"
},
  "geometry": {"coordinates":[8.7996482849,45.5775909424],"type":"Point"}
}