{
  "type": "Feature",
  "properties": {
    "addr:full":"13866 Masserano Masserano Biella 13866",
    "addr:postcode":"13866;13866",
    "addr:street":"Masserano",
    "iso:country":"IT",
    "sg:address":"13866 Masserano",
    "sg:city":"Masserano",
    "sg:orig_category":"Termotecnica E Riscaldamento, Apparecchiature E Servizi",
    "sg:phone":"+39 015 99544",
    "sg:postcode":"13866",
    "sg:province":"Biella",
    "wof:name":"Tonelli Impianti Sas",
    "wof:placetype":"venue"
},
  "geometry": {"coordinates":[8.248465,45.569664],"type":"Point"}
}