{
  "type": "Feature",
  "properties": {
    "addr:full":"Via San Rocco, 12 - Soprazocco 25085 Gavardo Gavardo Brescia 25085",
    "addr:housenumber":"12",
    "addr:postcode":"25085;25085",
    "addr:street":"Via San Rocco",
    "iso:country":"IT",
    "sg:address":"Via San Rocco, 12 - Soprazocco 25085 Gavardo",
    "sg:city":"Gavardo",
    "sg:orig_category":"Ladies' Coats",
    "sg:phone":"+39 036 531881",
    "sg:postcode":"25085",
    "sg:province":"Brescia",
    "wof:name":"Confezioni Benetti Di Benetti Luciano Snc",
    "wof:placetype":"venue"
},
  "geometry": {"coordinates":[10.222958,45.539829],"type":"Point"}
}