{
  "type": "Feature",
  "properties": {
    "iso:country":"IT",
    "sg:address":"1311, Via Emilia Est 41100 Modena",
    "sg:city":"Modena",
    "sg:classifiers":[
        {
            "category":"Autos & Motor Vehicles",
            "subcategory":"Automobile Sales",
            "type":"Retail Goods"
        }
    ],
    "sg:phone":"+39 39059284177",
    "sg:postcode":"41100",
    "sg:province":"Modena",
    "sg:tags":[
        "motor-cars"
    ],
    "wof:name":"Team Autok (s.r.l.)",
    "wof:placetype":"venue"
},
  "geometry": {"coordinates":[10.9365940094,44.6419792175],"type":"Point"}
}