{
  "type": "Feature",
  "properties": {
    "addr:full":"10, Via Stella Alpina 59100 Prato Prato Prato 59100",
    "addr:postcode":"59100;59100",
    "addr:street":"Via Stella Alpina",
    "iso:country":"IT",
    "sg:address":"10, Via Stella Alpina 59100 Prato",
    "sg:city":"Prato",
    "sg:classifiers":[
        {
            "category":"Shopping",
            "subcategory":"Crafts & Fabrics",
            "type":"Retail Goods"
        }
    ],
    "sg:phone":"+39 0574 631043",
    "sg:postcode":"59100",
    "sg:province":"Prato",
    "wof:name":"Lanificio Alba",
    "wof:placetype":"venue"
},
  "geometry": {"coordinates":[11.0838661194,43.8701782227],"type":"Point"}
}