{
  "type": "Feature",
  "properties": {
    "addr:full":"63100 Ripaberarda Ascoli Piceno 63100",
    "addr:postcode":"63100;63100",
    "iso:country":"IT",
    "sg:address":"63100 Ripaberarda",
    "sg:orig_category":"Abbigliamento Sportivo - Produzione E Ingrosso",
    "sg:phone":"+39 0736 825235",
    "sg:postcode":"63100",
    "sg:province":"Ascoli Piceno",
    "wof:name":"Centro Confezioni Srl",
    "wof:placetype":"venue"
},
  "geometry": {"coordinates":[13.599131,42.924961],"type":"Point"}
}