{
  "type": "Feature",
  "properties": {
    "iso:country":"IT",
    "sg:address":"116, Via Bergamo 24047 Treviglio",
    "sg:city":"Treviglio",
    "sg:classifiers":[
        {
            "category":"Home & Garden",
            "subcategory":"Home Furnishings",
            "type":"Retail Goods"
        }
    ],
    "sg:phone":"+39 036 330 9989",
    "sg:postcode":"24047",
    "sg:province":"Bergamo",
    "sg:tags":[
        "household"
    ],
    "wof:name":"Giovanni Scotti Mobili D'arte Di Scotti Giovanni & C. S.a.s.",
    "wof:placetype":"venue"
},
  "geometry": {"coordinates":[9.605867,45.554348],"type":"Point"}
}