{
  "type": "Feature",
  "properties": {
    "iso:country":"IT",
    "sg:address":"17019 Varazze",
    "sg:city":"Varazze",
    "sg:orig_category":"Gioielleria, Oreficeria E Argenteria. Shopping",
    "sg:phone":"+39 019 97421",
    "sg:postcode":"17019",
    "sg:province":"Savona",
    "wof:name":"Ubaldo Fabiola",
    "wof:placetype":"venue"
},
  "geometry": {"coordinates":[8.507175,44.32872],"type":"Point"}
}