{
  "type": "Feature",
  "properties": {
    "iso:country":"IT",
    "sg:address":"00179 Roma",
    "sg:city":"Roma",
    "sg:classifiers":[
        {
            "category":"Shopping",
            "subcategory":"Clothing, Apparel, & Fashions",
            "type":"Retail Goods"
        }
    ],
    "sg:phone":"+39 06 780 0970",
    "sg:postcode":"00179",
    "sg:province":"Roma",
    "sg:tags":[
        "activities",
        "goods",
        "supply",
        "leather",
        "commercial",
        "artisan",
        "supplies",
        "clothing"
    ],
    "wof:name":"Gruppo Intersystem",
    "wof:placetype":"venue"
},
  "geometry": {"coordinates":[12.515463,41.867729],"type":"Point"}
}