{
  "type": "Feature",
  "properties": {
    "addr:full":"Via Damano 1 48024 Massa Lombarda Massa Lombarda Ravenna 48024",
    "addr:housenumber":"1",
    "addr:postcode":"48024;48024",
    "addr:street":"Via Damano",
    "iso:country":"IT",
    "sg:address":"Via Damano 1 48024 Massa Lombarda",
    "sg:city":"Massa Lombarda",
    "sg:classifiers":[
        {
            "category":"Banks & Credit Unions",
            "subcategory":"Investment Brokerage",
            "type":"Services"
        }
    ],
    "sg:phone":"+39 0545 979511",
    "sg:postcode":"48024",
    "sg:province":"Ravenna",
    "sg:tags":[
        "packaging",
        "manufactured",
        "packagings",
        "good",
        "industrial"
    ],
    "sg:website":"www.nespak.com",
    "wof:name":"Nespak Spa",
    "wof:placetype":"venue"
},
  "geometry": {"coordinates":[11.833807,44.457706],"type":"Point"}
}