{
  "type": "Feature",
  "properties": {
    "iso:country":"IT",
    "sg:address":"34, Via Statale 14033 Castell'alfero",
    "sg:classifiers":[
        {
            "category":"Shopping",
            "subcategory":"Computers & Home Electronics",
            "type":"Retail Goods"
        }
    ],
    "sg:phone":"+39 0141 296215",
    "sg:postcode":"14033",
    "sg:province":"Asti",
    "sg:tags":[
        "electronic",
        "electrical",
        "equipment"
    ],
    "wof:name":"G.r.m. S.n.c.",
    "wof:placetype":"venue"
},
  "geometry": {"coordinates":[8.227724,44.976315],"type":"Point"}
}