{
  "type": "Feature",
  "properties": {
    "iso:country":"IT",
    "sg:address":"7, Via Benassi Erio 42100 Reggio Emilia",
    "sg:classifiers":[
        {
            "category":"Manufacturing",
            "subcategory":"Motor Vehicles & Parts",
            "type":"Manufacturing & Wholesale Goods"
        }
    ],
    "sg:phone":"+39 0522 308645",
    "sg:postcode":"42100",
    "sg:province":"Reggio Nell'Emilia",
    "sg:tags":[
        "engine"
    ],
    "wof:name":"F.i.s. (s.r.l.)",
    "wof:placetype":"venue"
},
  "geometry": {"coordinates":[10.598417,44.712406],"type":"Point"}
}