{
  "type": "Feature",
  "properties": {
    "addr:full":"13856 Vigliano Biellese Vigliano Biellese Biella 13856",
    "addr:postcode":"13856;13856",
    "iso:country":"IT",
    "sg:address":"13856 Vigliano Biellese",
    "sg:city":"Vigliano Biellese",
    "sg:orig_category":"Apparecchiature E Sistemi Per Magazzinaggio E Movimentazione. Servizi Di Magazzinaggio E Movimentazione",
    "sg:phone":"+39 015 512390",
    "sg:postcode":"13856",
    "sg:province":"Biella",
    "wof:name":"Boscaro Fratelli Snc",
    "wof:placetype":"venue"
},
  "geometry": {"coordinates":[8.090748,45.562893],"type":"Point"}
}