{
  "type": "Feature",
  "properties": {
    "iso:country":"IT",
    "sg:address":"165, Via Giovanni Xxiii 41012 Carpi",
    "sg:city":"Carpi",
    "sg:classifiers":[
        {
            "category":"Shopping",
            "subcategory":"Clothing, Apparel, & Fashions",
            "type":"Retail Goods"
        }
    ],
    "sg:phone":"+39 39059680203",
    "sg:postcode":"41012",
    "sg:province":"Modena",
    "sg:tags":[
        "clothes"
    ],
    "wof:name":"Zacotex (s.r.l.)",
    "wof:placetype":"venue"
},
  "geometry": {"coordinates":[10.877823,44.798954],"type":"Point"}
}