{
  "type": "Feature",
  "properties": {
    "addr:full":"22010 Gera Lario Gera Lario Como 22010",
    "addr:postcode":"22010;22010",
    "iso:country":"IT",
    "sg:address":"22010 Gera Lario",
    "sg:city":"Gera Lario",
    "sg:orig_category":"Non-classified Establishments",
    "sg:phone":"+39 0344 97137",
    "sg:postcode":"22010",
    "sg:province":"Como",
    "wof:name":"Ligari Ennio",
    "wof:placetype":"venue"
},
  "geometry": {"coordinates":[9.368759,46.172054],"type":"Point"}
}