{
  "type": "Feature",
  "properties": {
    "iso:country":"IT",
    "sg:address":"23845 Costa Masnaga",
    "sg:city":"Costa Masnaga",
    "sg:orig_category":"Tessuti E Stoffe",
    "sg:phone":"+39 031 879182",
    "sg:postcode":"23845",
    "sg:province":"Lecco",
    "wof:name":"Felter Gomma Snc",
    "wof:placetype":"venue"
},
  "geometry": {"coordinates":[9.278841,45.762283],"type":"Point"}
}