{
  "type": "Feature",
  "properties": {
    "addr:full":"62100 Macerata Macerata Macerata 62100",
    "addr:postcode":"62100;62100",
    "iso:country":"IT",
    "sg:address":"62100 Macerata",
    "sg:city":"Macerata",
    "sg:classifiers":[
        {
            "category":"Home & Garden",
            "subcategory":"Household Appliances",
            "type":"Retail Goods"
        }
    ],
    "sg:phone":"+39 0733 292156",
    "sg:postcode":"62100",
    "sg:province":"Macerata",
    "sg:tags":[
        "accommodation",
        "appliances",
        "supply"
    ],
    "wof:name":"Giunchi Forni Snc",
    "wof:placetype":"venue"
},
  "geometry": {"coordinates":[13.486177,43.275829],"type":"Point"}
}