{
  "type": "Feature",
  "properties": {
    "iso:country":"IT",
    "sg:address":"Via Stazione 9a 39010 Gargazon",
    "sg:orig_category":"Apples, Fresh",
    "sg:phone":"+39 0473 292323",
    "sg:postcode":"39010",
    "sg:province":"Bolzano/Bozen",
    "wof:name":"Consorzio Frutticoltori Gargazzone-tesimo Scrl",
    "wof:placetype":"venue"
},
  "geometry": {"coordinates":[11.201276,46.580704],"type":"Point"}
}