{
  "type": "Feature",
  "properties": {
    "iso:country":"IT",
    "sg:address":"56031 Bientina",
    "sg:city":"Bientina",
    "sg:orig_category":"Lavorazioni Meccaniche E Servizi. Servizi Per Imballaggio E Confezionamento",
    "sg:phone":"+39 0587 755420",
    "sg:postcode":"56031",
    "sg:province":"Pisa",
    "wof:name":"A.m.p. Di Pepe Andrea",
    "wof:placetype":"venue"
},
  "geometry": {"coordinates":[10.653444,43.721691],"type":"Point"}
}