{
  "type": "Feature",
  "properties": {
    "iso:country":"IT",
    "sg:address":"12100 Cuneo",
    "sg:city":"Cuneo",
    "sg:orig_category":"Tempo Libero - Articoli E Forniture. Regalistica Aziendale",
    "sg:phone":"+39 0171 692310",
    "sg:postcode":"12100",
    "sg:province":"Cuneo",
    "wof:name":"Muchmore",
    "wof:placetype":"venue"
},
  "geometry": {"coordinates":[7.546389,44.432663],"type":"Point"}
}