{
  "type": "Feature",
  "properties": {
    "addr:full":"Via Del Lavoro 23 50041 Calenzano Calenzano Firenze 50041",
    "addr:housenumber":"23",
    "addr:postcode":"50041;50041",
    "addr:street":"Via Del Lavoro",
    "iso:country":"IT",
    "sg:address":"Via Del Lavoro 23 50041 Calenzano",
    "sg:city":"Calenzano",
    "sg:orig_category":"Ladies' Hats",
    "sg:phone":"+39 055 881 1220",
    "sg:postcode":"50041",
    "sg:province":"Firenze",
    "wof:name":"Cioppi Onorio Srl",
    "wof:placetype":"venue"
},
  "geometry": {"coordinates":[11.136567,43.821903],"type":"Point"}
}