{
  "type": "Feature",
  "properties": {
    "iso:country":"IT",
    "sg:address":"Via Del Lavoro 23 50041 Calenzano",
    "sg:city":"Calenzano",
    "sg:orig_category":"Ladies' Hats",
    "sg:phone":"+39 055 881 1220",
    "sg:postcode":"50041",
    "sg:province":"Firenze",
    "wof:name":"Cioppi Onorio Srl",
    "wof:placetype":"venue"
},
  "geometry": {"coordinates":[11.136567,43.821903],"type":"Point"}
}