{
  "type": "Feature",
  "properties": {
    "iso:country":"IT",
    "sg:address":"67039 Sulmona",
    "sg:orig_category":"Prodotti Chimici Di Base",
    "sg:phone":"+39 0864 50973",
    "sg:postcode":"67039",
    "sg:province":"L'Aquila",
    "wof:name":"Fazi Celestino",
    "wof:placetype":"venue"
},
  "geometry": {"coordinates":[13.9282312393,42.0551147461],"type":"Point"}
}