{
  "type": "Feature",
  "properties": {
    "iso:country":"IT",
    "sg:address":"21013 Gallarate",
    "sg:city":"Gallarate",
    "sg:orig_category":"Insegne Luminose",
    "sg:phone":"+39 0331 795743",
    "sg:postcode":"21013",
    "sg:province":"Varese",
    "sg:website":"http://www.neongallaratese.it",
    "wof:name":"Neon Gallaratese Di Venegoni Carlo & C. Snc",
    "wof:placetype":"venue"
},
  "geometry": {"coordinates":[8.796224,45.665981],"type":"Point"}
}