{
  "type": "Feature",
  "properties": {
    "addr:full":"47, Via Brescia 25014 Castenedolo Castenedolo Brescia 25014",
    "addr:postcode":"25014;25014",
    "addr:street":"Via Brescia",
    "iso:country":"IT",
    "sg:address":"47, Via Brescia 25014 Castenedolo",
    "sg:city":"Castenedolo",
    "sg:classifiers":[
        {
            "category":"Professional",
            "subcategory":"Printing & Photocopies",
            "type":"Services"
        }
    ],
    "sg:phone":"+39 030 213 1128",
    "sg:postcode":"25014",
    "sg:province":"Brescia",
    "wof:name":"C.s. Centro Serigrafico Srl",
    "wof:placetype":"venue"
},
  "geometry": {"coordinates":[10.2846345901,45.4826469421],"type":"Point"}
}