{
  "type": "Feature",
  "properties": {
    "iso:country":"IT",
    "sg:address":"18039 Ventimiglia",
    "sg:city":"Ventimiglia",
    "sg:orig_category":"Prodotti Finiti Stampati. Articoli Da Regalo. Arte Ed Artigianato Artistico. Shopping",
    "sg:phone":"+39 0184 351696",
    "sg:postcode":"18039",
    "sg:province":"Imperia",
    "wof:name":"Risso Cornici Di Zambelli Marina",
    "wof:placetype":"venue"
},
  "geometry": {"coordinates":[7.5463886261,43.8279762268],"type":"Point"}
}