{
  "type": "Feature",
  "properties": {
    "iso:country":"IT",
    "sg:address":"37020 Marano Di Valpolicella",
    "sg:city":"Marano di Valpolicella",
    "sg:orig_category":"Calzature, Pelletterie E Pelli",
    "sg:phone":"+39 045 680 1625",
    "sg:postcode":"37020",
    "sg:province":"Verona",
    "wof:name":"My Way Net Srl",
    "wof:placetype":"venue"
},
  "geometry": {"coordinates":[10.898517,45.512131],"type":"Point"}
}