{
  "type": "Feature",
  "properties": {
    "iso:country":"IT",
    "sg:address":"32032 Feltre",
    "sg:city":"Feltre",
    "sg:orig_category":"Batterie, Accumulatori E Pile - Commercio",
    "sg:phone":"+39 0439 304732",
    "sg:postcode":"32032",
    "sg:province":"Belluno",
    "wof:name":"Ara Srl",
    "wof:placetype":"venue"
},
  "geometry": {"coordinates":[12.181176,46.09782],"type":"Point"}
}