{
  "type": "Feature",
  "properties": {
    "iso:country":"IT",
    "sg:address":"24036 Ponte San Pietro",
    "sg:city":"Ponte San Pietro",
    "sg:orig_category":"Non-classified Establishments",
    "sg:phone":"+39 035 617714",
    "sg:postcode":"24036",
    "sg:province":"Bergamo",
    "wof:name":"Casa Pi\u00d9",
    "wof:placetype":"venue"
},
  "geometry": {"coordinates":[9.586657,45.69606],"type":"Point"}
}