{
  "type": "Feature",
  "properties": {
    "addr:full":"14100 Asti Asti Asti 14100",
    "addr:postcode":"14100;14100",
    "iso:country":"IT",
    "sg:address":"14100 Asti",
    "sg:city":"Asti",
    "sg:classifiers":[
        {
            "category":"Banks & Credit Unions",
            "subcategory":"Investment Brokerage",
            "type":"Services"
        }
    ],
    "sg:phone":"+39 0141 476598",
    "sg:postcode":"14100",
    "sg:province":"Asti",
    "sg:tags":[
        "vehicles",
        "auxiliary",
        "motor"
    ],
    "wof:name":"Zagara Salvatore",
    "wof:placetype":"venue"
},
  "geometry": {"coordinates":[8.2410011292,44.9022026062],"type":"Point"}
}