{
  "type": "Feature",
  "properties": {
    "addr:full":"10129 Torino Torino Torino 10129",
    "addr:postcode":"10129;10129",
    "iso:country":"IT",
    "sg:address":"10129 Torino",
    "sg:city":"Torino",
    "sg:orig_category":"Impianti, Attrezzature E Forniture Sanitarie Ed Ospedaliere",
    "sg:phone":"+39 011 597568",
    "sg:postcode":"10129",
    "sg:province":"Torino",
    "wof:name":"A.c.s. Di Montis Luciano E C. (s.n.c.)",
    "wof:placetype":"venue"
},
  "geometry": {"coordinates":[7.573236,45.059692],"type":"Point"}
}