{
  "type": "Feature",
  "properties": {
    "iso:country":"IT",
    "sg:address":"20090 Trezzano Sul Naviglio",
    "sg:city":"Trezzano sul Naviglio",
    "sg:orig_category":"Pubblicita', Marketing E Comunicazione",
    "sg:phone":"+39 02 4849 0177",
    "sg:postcode":"20090",
    "sg:province":"Milano",
    "sg:website":"http://www.gidolo.it",
    "wof:name":"Gidolo Srl",
    "wof:placetype":"venue"
},
  "geometry": {"coordinates":[9.0859518051,45.4165458679],"type":"Point"}
}