{
  "type": "Feature",
  "properties": {
    "iso:country":"IT",
    "sg:address":"10123 Torino",
    "sg:city":"Torino",
    "sg:orig_category":"Gioiellerie E Oreficerie - Vendita Al Dettaglio",
    "sg:phone":"+39 011 530225",
    "sg:postcode":"10123",
    "sg:province":"Torino",
    "wof:name":"Gioielleria Fasano Sas",
    "wof:placetype":"venue"
},
  "geometry": {"coordinates":[7.57748,45.02277],"type":"Point"}
}