{
  "type": "Feature",
  "properties": {
    "addr:full":"24060 Chiuduno Chiuduno Bergamo 24060",
    "addr:postcode":"24060;24060",
    "iso:country":"IT",
    "sg:address":"24060 Chiuduno",
    "sg:city":"Chiuduno",
    "sg:orig_category":"Dolciumi E Gelati",
    "sg:phone":"+39 035 839494",
    "sg:postcode":"24060",
    "sg:province":"Bergamo",
    "wof:name":"Apicoltura Pratovoglia",
    "wof:placetype":"venue"
},
  "geometry": {"coordinates":[9.819507,45.631851],"type":"Point"}
}