{
  "type": "Feature",
  "properties": {
    "addr:full":"Via Nicolo' Da Legnago 37045 Legnago Legnago Verona 37045",
    "addr:postcode":"37045;37045",
    "addr:street":"Via Nicolo ' Da Legnago",
    "iso:country":"IT",
    "sg:address":"Via Nicolo' Da Legnago 37045 Legnago",
    "sg:city":"Legnago",
    "sg:classifiers":[
        {
            "category":"Home & Garden",
            "subcategory":"Home Furnishings",
            "type":"Retail Goods"
        }
    ],
    "sg:phone":"+39 39044223955",
    "sg:postcode":"37045",
    "sg:province":"Verona",
    "sg:tags":[
        "household"
    ],
    "wof:name":"Arredo 3 (s.n.c.)",
    "wof:placetype":"venue"
},
  "geometry": {"coordinates":[11.338432,45.200233],"type":"Point"}
}