{
  "type": "Feature",
  "properties": {
    "iso:country":"IT",
    "sg:address":"47900 Rimini",
    "sg:city":"Rimini",
    "sg:orig_category":"Agenzie Investigative",
    "sg:phone":"+39 0541 21757",
    "sg:postcode":"47900",
    "sg:province":"Rimini",
    "wof:name":"Centro Servizi Investigativi Di Pala & C. Sas",
    "wof:placetype":"venue"
},
  "geometry": {"coordinates":[12.468081,44.074902],"type":"Point"}
}