{
  "type": "Feature",
  "properties": {
    "addr:full":"59, Via Principessa Maria 07100 Sassari Sassari Sassari 07100",
    "addr:postcode":"07100;07100",
    "addr:street":"Via Principessa Maria",
    "iso:country":"IT",
    "sg:address":"59, Via Principessa Maria 07100 Sassari",
    "sg:city":"Sassari",
    "sg:classifiers":[
        {
            "category":"Manufacturing",
            "subcategory":"Food",
            "type":"Manufacturing & Wholesale Goods"
        }
    ],
    "sg:phone":"+39 39079217421",
    "sg:postcode":"07100",
    "sg:province":"Sassari",
    "sg:tags":[
        "equipment",
        "processing",
        "-",
        "machinery"
    ],
    "wof:name":"Panificio Gran Pane Sechi & Riu S.n.c.",
    "wof:placetype":"venue"
},
  "geometry": {"coordinates":[8.5538892746,40.7294425964],"type":"Point"}
}