{
  "type": "Feature",
  "properties": {
    "iso:country":"IT",
    "sg:address":"96014 Floridia",
    "sg:city":"Floridia",
    "sg:orig_category":"Ospedali E Servizi Sanitari",
    "sg:phone":"+39 0931 941511",
    "sg:postcode":"96014",
    "sg:province":"Siracusa",
    "wof:name":"Laboratorio Analisi Cliniche Biomedica Srl",
    "wof:placetype":"venue"
},
  "geometry": {"coordinates":[15.1463336945,37.083656311],"type":"Point"}
}