{
  "type": "Feature",
  "properties": {
    "iso:country":"IT",
    "sg:address":"50056 Montelupo Fiorentino",
    "sg:city":"Montelupo Fiorentino",
    "sg:orig_category":"Ospedali E Servizi Sanitari",
    "sg:phone":"+39 0571 913290",
    "sg:postcode":"50056",
    "sg:province":"Firenze",
    "wof:name":"Istituto Rossella",
    "wof:placetype":"venue"
},
  "geometry": {"coordinates":[11.016522,43.729237],"type":"Point"}
}