{
  "type": "Feature",
  "properties": {
    "iso:country":"IT",
    "sg:address":"Via Belfiore 32 23900 Lecco",
    "sg:city":"Lecco",
    "sg:classifiers":[
        {
            "category":"Utilities",
            "subcategory":"Cable",
            "type":"Services"
        }
    ],
    "sg:phone":"+39 0341 362622",
    "sg:postcode":"23900",
    "sg:province":"Lecco",
    "sg:tags":[
        "wire",
        "iron"
    ],
    "wof:name":"Metallurgica Tognetti Spa",
    "wof:placetype":"venue"
},
  "geometry": {"coordinates":[9.41074,45.853569],"type":"Point"}
}