{
  "type": "Feature",
  "properties": {
    "addr:full":"Via Degli Orefici, 152 - Blocco 27 40050 Funo Funo Bologna 40050",
    "addr:housenumber":"152 blocco 27",
    "addr:postcode":"40050;40050",
    "addr:street":"Via Degli Orefici",
    "iso:country":"IT",
    "sg:address":"Via Degli Orefici, 152 - Blocco 27 40050 Funo",
    "sg:city":"Funo",
    "sg:classifiers":[
        {
            "category":"Health Services",
            "subcategory":"Nursing And Care Facility",
            "type":"Services"
        }
    ],
    "sg:phone":"+39 051 890 1611",
    "sg:postcode":"40050",
    "sg:province":"Bologna",
    "sg:tags":[
        "electro-medical",
        "apparatus"
    ],
    "sg:website":"www.espansione.it",
    "wof:name":"Espansione Marketing Spa",
    "wof:placetype":"venue"
},
  "geometry": {"coordinates":[11.346481,44.494221],"type":"Point"}
}