{
  "type": "Feature",
  "properties": {
    "iso:country":"IT",
    "sg:address":"Viale Lombardia 310 20047 Brugherio",
    "sg:city":"Brugherio",
    "sg:classifiers":[
        {
            "category":"Shopping",
            "subcategory":"Crafts & Fabrics",
            "type":"Retail Goods"
        }
    ],
    "sg:phone":"+39 039 202 4010",
    "sg:postcode":"20047",
    "sg:province":"Milano",
    "sg:tags":[
        "packaging",
        "material",
        "confectionery",
        "catering"
    ],
    "wof:name":"Musto Tipolitografia Impresa Individuale",
    "wof:placetype":"venue"
},
  "geometry": {"coordinates":[9.2909574509,45.5446128845],"type":"Point"}
}