{
  "type": "Feature",
  "properties": {
    "addr:full":"17, Localita' Marinella 58033 Castel Del Piano Castel del Piano Grosseto 58033",
    "addr:housenumber":"del",
    "addr:postcode":"58033;58033",
    "addr:street":"Localita ' Marinella",
    "iso:country":"IT",
    "sg:address":"17, Localita' Marinella 58033 Castel Del Piano",
    "sg:city":"Castel del Piano",
    "sg:classifiers":[
        {
            "category":"Utilities",
            "subcategory":"Electric",
            "type":"Services"
        }
    ],
    "sg:phone":"+39 0564 956681",
    "sg:postcode":"58033",
    "sg:province":"Grosseto",
    "sg:tags":[
        "component",
        "electronic"
    ],
    "wof:name":"Tosti S.a.s. Tosti Fosco & C.",
    "wof:placetype":"venue"
},
  "geometry": {"coordinates":[11.112782,42.762859],"type":"Point"}
}