{
  "type": "Feature",
  "properties": {
    "iso:country":"IT",
    "sg:address":"12084 Mondov\u00ec",
    "sg:classifiers":[
        {
            "category":"Utilities",
            "subcategory":"Natural Gas",
            "type":"Services"
        }
    ],
    "sg:phone":"+39 0174 44545",
    "sg:postcode":"12084",
    "sg:province":"Cuneo",
    "sg:tags":[
        "alloy",
        "metal"
    ],
    "sg:website":"http://www.infosys.it",
    "wof:name":"C.f.m. Srl",
    "wof:placetype":"venue"
},
  "geometry": {"coordinates":[7.8177599907,44.4049758911],"type":"Point"}
}