{
  "type": "Feature",
  "properties": {
    "addr:full":"35010 Villafranca Padovana Campodoro Padova 35010",
    "addr:postcode":"35010;35010",
    "iso:country":"IT",
    "sg:address":"35010 Villafranca Padovana",
    "sg:city":"Campodoro",
    "sg:orig_category":"Servizi Ausiliari Di Analisi, Controllo E Ricerca",
    "sg:phone":"+39 049 905 0013",
    "sg:postcode":"35010",
    "sg:province":"Padova",
    "wof:name":"S.g.s. Ecologia (s.r.l.)",
    "wof:placetype":"venue"
},
  "geometry": {"coordinates":[11.768288,45.463024],"type":"Point"}
}