{
  "type": "Feature",
  "properties": {
    "iso:country":"IT",
    "sg:address":"00185 Roma",
    "sg:city":"Roma",
    "sg:orig_category":"Pompe. Elettrotecnica Industriale, Prodotti E Apparecchiature",
    "sg:phone":"+39 06 445 4929",
    "sg:postcode":"00185",
    "sg:province":"Roma",
    "wof:name":"Criscio Leonardo",
    "wof:placetype":"venue"
},
  "geometry": {"coordinates":[12.5174760818,41.8980941772],"type":"Point"}
}