{
  "type": "Feature",
  "properties": {
    "addr:full":"31020 Villorba Villorba Treviso 31020",
    "addr:postcode":"31020;31020",
    "iso:country":"IT",
    "sg:address":"31020 Villorba",
    "sg:city":"Villorba",
    "sg:orig_category":"Forniture Per Attivita' Industriali",
    "sg:phone":"+39 0422 608426",
    "sg:postcode":"31020",
    "sg:province":"Treviso",
    "wof:name":"Pneumoil Srl",
    "wof:placetype":"venue"
},
  "geometry": {"coordinates":[12.2600841522,45.7136688232],"type":"Point"}
}