{
  "type": "Feature",
  "properties": {
    "addr:full":"00159 Roma Roma Roma 00159",
    "addr:postcode":"00159;00159",
    "iso:country":"IT",
    "sg:address":"00159 Roma",
    "sg:city":"Roma",
    "sg:orig_category":"Arte Ed Artigianato Artistico",
    "sg:phone":"+39 06 4050 0636",
    "sg:postcode":"00159",
    "sg:province":"Roma",
    "wof:name":"Nena Alfiero",
    "wof:placetype":"venue"
},
  "geometry": {"coordinates":[12.562021,41.911472],"type":"Point"}
}