{
  "type": "Feature",
  "properties": {
    "iso:country":"IT",
    "sg:address":"23807 Merate",
    "sg:city":"Merate",
    "sg:orig_category":"Cartotecnica E Servizi. Forniture Per Attivita' Commerciali Ed Artigianali",
    "sg:phone":"+39 039 990 8867",
    "sg:postcode":"23807",
    "sg:province":"Lecco",
    "wof:name":"Casalini E Viscardi (s.r.l.)",
    "wof:placetype":"venue"
},
  "geometry": {"coordinates":[9.362965,45.84309],"type":"Point"}
}