{
  "type": "Feature",
  "properties": {
    "iso:country":"IT",
    "sg:address":"15053 Castelnuovo Scrivia",
    "sg:city":"Castelnuovo Scrivia",
    "sg:orig_category":"Prodotti Alimentari",
    "sg:phone":"+39 0131 825056",
    "sg:postcode":"15053",
    "sg:province":"Alessandria",
    "wof:name":"Scacheri Azienda Agricola",
    "wof:placetype":"venue"
},
  "geometry": {"coordinates":[8.8665447235,44.9737663269],"type":"Point"}
}