{
  "type": "Feature",
  "properties": {
    "iso:country":"IT",
    "sg:address":"20126 Milano",
    "sg:city":"Milano",
    "sg:orig_category":"Automobili E Mezzi Di Trasporto",
    "sg:phone":"+39 02 2700 3416",
    "sg:postcode":"20126",
    "sg:province":"Milano",
    "wof:name":"Firema Trasporti Spa",
    "wof:placetype":"venue"
},
  "geometry": {"coordinates":[9.22242,45.505512],"type":"Point"}
}