{
  "type": "Feature",
  "properties": {
    "iso:country":"IT",
    "sg:address":"7, Viale Risorgimento 45011 Adria",
    "sg:city":"Adria",
    "sg:classifiers":[
        {
            "category":"Manufacturing",
            "subcategory":"Rubber & Plastics",
            "type":"Manufacturing & Wholesale Goods"
        }
    ],
    "sg:phone":"+39 0426 993185",
    "sg:postcode":"45011",
    "sg:province":"Rovigo",
    "wof:name":"Polychimica Srl",
    "wof:placetype":"venue"
},
  "geometry": {"coordinates":[12.0463905334,45.0580749512],"type":"Point"}
}