{
  "type": "Feature",
  "properties": {
    "iso:country":"IT",
    "sg:address":"00043 Ciampino",
    "sg:city":"Ciampino",
    "sg:orig_category":"Forniture Alberghi, Bar, Ristoranti E Comunita'",
    "sg:phone":"+39 06 790791",
    "sg:postcode":"00043",
    "sg:province":"Roma",
    "wof:name":"Acquario Di Petrucci A.p.m. Snc",
    "wof:placetype":"venue"
},
  "geometry": {"coordinates":[12.591386795,41.8188438416],"type":"Point"}
}