{
  "type": "Feature",
  "properties": {
    "iso:country":"IT",
    "sg:address":"41100 Modena",
    "sg:city":"Modena",
    "sg:orig_category":"Macchine, Impianti Ed Attrezzature Per Agricoltura E Zootecnia",
    "sg:phone":"+39 059 242373",
    "sg:postcode":"41100",
    "sg:province":"Modena",
    "wof:name":"Augusto Sales And Marketing (s.r.l.)",
    "wof:placetype":"venue"
},
  "geometry": {"coordinates":[10.932719,44.639885],"type":"Point"}
}