{
  "type": "Feature",
  "properties": {
    "addr:full":"Via Petrarca 10 24052 Azzano San Paolo Azzano San Paolo Bergamo 24052",
    "addr:housenumber":"10",
    "addr:postcode":"24052;24052",
    "addr:street":"Via Petrarca",
    "iso:country":"IT",
    "sg:address":"Via Petrarca 10 24052 Azzano San Paolo",
    "sg:city":"Azzano San Paolo",
    "sg:classifiers":[
        {
            "category":"Wholesale",
            "subcategory":"Plants",
            "type":"Manufacturing & Wholesale Goods"
        }
    ],
    "sg:phone":"+39 035 596511",
    "sg:postcode":"24052",
    "sg:province":"Bergamo",
    "sg:tags":[
        "machine",
        "industrial",
        "automation"
    ],
    "sg:website":"www.termoele.it",
    "wof:name":"Termoelettronica Spa",
    "wof:placetype":"venue"
},
  "geometry": {"coordinates":[9.664278,45.65694],"type":"Point"}
}