{
  "type": "Feature",
  "properties": {
    "addr:full":"10123 Torino Torino Torino 10123",
    "addr:postcode":"10123;10123",
    "iso:country":"IT",
    "sg:address":"10123 Torino",
    "sg:city":"Torino",
    "sg:orig_category":"Cartotecnica E Servizi. Articoli Per Imballaggio E Confezionamento",
    "sg:phone":"+39 011 817 0232",
    "sg:postcode":"10123",
    "sg:province":"Torino",
    "wof:name":"Dolza Roberto E C. Snc",
    "wof:placetype":"venue"
},
  "geometry": {"coordinates":[7.686757,45.063103],"type":"Point"}
}