{
  "type": "Feature",
  "properties": {
    "addr:full":"53021 Abbadia S.salvatore Siena 53021",
    "addr:postcode":"53021;53021",
    "addr:street":"Abbadia S.Salvatore Siena",
    "iso:country":"IT",
    "sg:address":"53021 Abbadia S.salvatore",
    "sg:orig_category":"Abbigliamento Alta Moda E Stilisti - Boutiques",
    "sg:phone":"+39 0577 540 7092",
    "sg:postcode":"53021",
    "sg:province":"Siena",
    "wof:name":"Verticelli Amedeo",
    "wof:placetype":"venue"
},
  "geometry": {"coordinates":[11.330514,43.318661],"type":"Point"}
}