{
  "type": "Feature",
  "properties": {
    "iso:country":"IT",
    "sg:address":"64024 Notaresco",
    "sg:city":"Notaresco",
    "sg:orig_category":"Lavorazioni Meccaniche E Servizi",
    "sg:phone":"+39 085 855 9093",
    "sg:postcode":"64024",
    "sg:province":"Teramo",
    "wof:name":"Master Pubblicita' Abruzzo",
    "wof:placetype":"venue"
},
  "geometry": {"coordinates":[13.879601,42.665611],"type":"Point"}
}