{
  "type": "Feature",
  "properties": {
    "iso:country":"IT",
    "sg:address":"00141 Roma",
    "sg:city":"Roma",
    "sg:orig_category":"Arredi Ed Attrezzature Per Uffici",
    "sg:phone":"+39 06 810 2966",
    "sg:postcode":"00141",
    "sg:province":"Roma",
    "wof:name":"Tecknoart S R L",
    "wof:placetype":"venue"
},
  "geometry": {"coordinates":[12.515275,41.944511],"type":"Point"}
}