{
  "type": "Feature",
  "properties": {
    "iso:country":"IT",
    "sg:address":"10121 Torino",
    "sg:city":"Torino",
    "sg:orig_category":"Infermieri Ed Assistenza Domiciliare",
    "sg:phone":"+39 011 593310",
    "sg:postcode":"10121",
    "sg:province":"Torino",
    "wof:name":"L'assistenza Srl",
    "wof:placetype":"venue"
},
  "geometry": {"coordinates":[7.6781,45.067207],"type":"Point"}
}