{
  "type": "Feature",
  "properties": {
    "addr:full":"30028 S. Michele Al Tagliamento Venezia 30028",
    "addr:housenumber":"30028",
    "addr:postcode":"30028",
    "addr:street":"S. Michele Al Tagliamento",
    "iso:country":"IT",
    "sg:address":"30028 S. Michele Al Tagliamento",
    "sg:orig_category":"Autonoleggio",
    "sg:phone":"+39 0431 50757",
    "sg:postcode":"30028",
    "sg:province":"Venezia",
    "wof:name":"Carrozzeria 2000 Di Disero' Antonino",
    "wof:placetype":"venue"
},
  "geometry": {"coordinates":[12.982637,45.768372],"type":"Point"}
}