{
  "type": "Feature",
  "properties": {
    "addr:full":"7, Via Per Castelletto Cervo 13836 Cossato Cossato Biella 13836",
    "addr:postcode":"13836;13836",
    "addr:street":"Via Per Castelletto",
    "iso:country":"IT",
    "sg:address":"7, Via Per Castelletto Cervo 13836 Cossato",
    "sg:city":"Cossato",
    "sg:classifiers":[
        {
            "category":"Building & Trades",
            "subcategory":"Construction",
            "type":"Services"
        }
    ],
    "sg:phone":"+39 390 159 4145",
    "sg:postcode":"13836",
    "sg:province":"Biella",
    "sg:tags":[
        "work",
        "public"
    ],
    "wof:name":"Bazzani Fratelli (s.p.a.)",
    "wof:placetype":"venue"
},
  "geometry": {"coordinates":[8.05827,45.562836],"type":"Point"}
}