{
  "type": "Feature",
  "properties": {
    "addr:full":"Via Vittorio Veneto 99 35019 Tombolo Tombolo Padova 35019",
    "addr:housenumber":"99",
    "addr:postcode":"35019;35019",
    "addr:street":"Via Vittorio Veneto",
    "iso:country":"IT",
    "sg:address":"Via Vittorio Veneto 99 35019 Tombolo",
    "sg:city":"Tombolo",
    "sg:classifiers":[
        {
            "category":"Building & Trades",
            "subcategory":"Construction",
            "type":"Services"
        }
    ],
    "sg:phone":"+39 049 947 1284",
    "sg:postcode":"35019",
    "sg:province":"Padova",
    "sg:tags":[
        "development",
        "equipment",
        "husbandry",
        "animal"
    ],
    "wof:name":"Pilotto Evaristo Euromeat",
    "wof:placetype":"venue"
},
  "geometry": {"coordinates":[11.813173,45.644978],"type":"Point"}
}