{
  "type": "Feature",
  "properties": {
    "addr:full":"50055 Lastra A Signa Lastra a Signa Firenze 50055",
    "addr:postcode":"50055;50055",
    "addr:street":"A Signa",
    "iso:country":"IT",
    "sg:address":"50055 Lastra A Signa",
    "sg:city":"Lastra a Signa",
    "sg:orig_category":"Ceramiche: Prodotti E Lavorazioni. Articoli Da Regalo. Arte Ed Artigianato Artistico. Shopping",
    "sg:phone":"+39 055 872 3245",
    "sg:postcode":"50055",
    "sg:province":"Firenze",
    "sg:website":"http://www.ceramichepugi.it",
    "wof:name":"Pugi Ceramiche Di Marco Scopetani",
    "wof:placetype":"venue"
},
  "geometry": {"coordinates":[11.082491,43.73737],"type":"Point"}
}