{
  "type": "Feature",
  "properties": {
    "iso:country":"IT",
    "sg:address":"20148 Milano",
    "sg:city":"Milano",
    "sg:classifiers":[
        {
            "category":"Health Services",
            "subcategory":"Health Practitioner",
            "type":"Services"
        }
    ],
    "sg:phone":"+39 02 481 6914",
    "sg:postcode":"20148",
    "sg:province":"Milano",
    "sg:tags":[
        "medici"
    ],
    "wof:name":"Marastoni Fernando",
    "wof:placetype":"venue"
},
  "geometry": {"coordinates":[9.146994,45.481697],"type":"Point"}
}