{
  "type": "Feature",
  "properties": {
    "iso:country":"IT",
    "sg:address":"74/b, Via Fontanelle 80136 Napoli",
    "sg:city":"Napoli",
    "sg:classifiers":[
        {
            "category":"Personal",
            "subcategory":"Shoe Repair & Shine",
            "type":"Services"
        }
    ],
    "sg:phone":"+39 081 544 4693",
    "sg:postcode":"80136",
    "sg:province":"Napoli",
    "sg:tags":[
        "leather"
    ],
    "wof:name":"Terry Moda S.r.l.",
    "wof:placetype":"venue"
},
  "geometry": {"coordinates":[14.239473,40.858757],"type":"Point"}
}