{
  "type": "Feature",
  "properties": {
    "iso:country":"IT",
    "sg:address":"26046 San Daniele Po",
    "sg:city":"San Daniele Po",
    "sg:orig_category":"Panifici Industriali Ed Artigianali",
    "sg:phone":"+39 0372 65524",
    "sg:postcode":"26046",
    "sg:province":"Cremona",
    "wof:name":"Panificio P.f.m. Manini Snc",
    "wof:placetype":"venue"
},
  "geometry": {"coordinates":[10.1810283661,45.0650558472],"type":"Point"}
}