{
  "type": "Feature",
  "properties": {
    "addr:full":"60035 Jesi Jesi Ancona 60035",
    "addr:postcode":"60035;60035",
    "iso:country":"IT",
    "sg:address":"60035 Jesi",
    "sg:city":"Jesi",
    "sg:orig_category":"Fotoincisioni",
    "sg:phone":"+39 0731 211639",
    "sg:postcode":"60035",
    "sg:province":"Ancona",
    "wof:name":"Litograf Srl",
    "wof:placetype":"venue"
},
  "geometry": {"coordinates":[13.2548046112,43.5223197937],"type":"Point"}
}