{
  "type": "Feature",
  "properties": {
    "iso:country":"IT",
    "sg:address":"00015 Monterotondo",
    "sg:city":"Monterotondo",
    "sg:orig_category":"Trasporti E Spedizioni Merci",
    "sg:phone":"+39 06 906 0560",
    "sg:postcode":"00015",
    "sg:province":"Roma",
    "wof:name":"Safe Watcher Srl",
    "wof:placetype":"venue"
},
  "geometry": {"coordinates":[12.595486,42.076405],"type":"Point"}
}