{
  "type": "Feature",
  "properties": {
    "iso:country":"IT",
    "sg:address":"Via Olivetti 9 10040 Leini'",
    "sg:orig_category":"Rehabilitation Equipment",
    "sg:phone":"+39 011 998 9682",
    "sg:postcode":"10040",
    "sg:province":"Torino",
    "wof:name":"D.e.m. S.a.s.",
    "wof:placetype":"venue"
},
  "geometry": {"coordinates":[7.71093,45.166073],"type":"Point"}
}