{
  "type": "Feature",
  "properties": {
    "addr:full":"23900 Lecco Lecco Lecco 23900",
    "addr:postcode":"23900;23900",
    "iso:country":"IT",
    "sg:address":"23900 Lecco",
    "sg:city":"Lecco",
    "sg:orig_category":"Materiali Semilavorati Metallici",
    "sg:phone":"+39 0341 364009",
    "sg:postcode":"23900",
    "sg:province":"Lecco",
    "wof:name":"Defim (s.r.l.)",
    "wof:placetype":"venue"
},
  "geometry": {"coordinates":[9.401086,45.844986],"type":"Point"}
}