{
  "type": "Feature",
  "properties": {
    "addr:full":"20099 Sesto San Giovanni Sesto San Giovanni Milano 20099",
    "addr:postcode":"20099;20099",
    "iso:country":"IT",
    "sg:address":"20099 Sesto San Giovanni",
    "sg:city":"Sesto San Giovanni",
    "sg:orig_category":"Ferrotranviaria Industria",
    "sg:phone":"+39 0224941",
    "sg:postcode":"20099",
    "sg:province":"Milano",
    "wof:name":"Firema Trasporti Spa",
    "wof:placetype":"venue"
},
  "geometry": {"coordinates":[9.2411403656,45.5298233032],"type":"Point"}
}