{
  "type": "Feature",
  "properties": {
    "addr:full":"16143 Genova Genova Genova 16143",
    "addr:postcode":"16143;16143",
    "iso:country":"IT",
    "sg:address":"16143 Genova",
    "sg:city":"Genova",
    "sg:orig_category":"Articoli Medico-sanitari Ed Ortopedici",
    "sg:phone":"+39 010 529 9866",
    "sg:postcode":"16143",
    "sg:province":"Genova",
    "wof:name":"Cooperativa Sociale 'la Rimessa'",
    "wof:placetype":"venue"
},
  "geometry": {"coordinates":[9.06285,44.428562],"type":"Point"}
}