{
  "type": "Feature",
  "properties": {
    "addr:full":"55023 Borgo A Mozzano Borgo a Mozzano Lucca 55023",
    "addr:housenumber":"mozzano",
    "addr:postcode":"55023;55023",
    "iso:country":"IT",
    "sg:address":"55023 Borgo A Mozzano",
    "sg:city":"Borgo a Mozzano",
    "sg:orig_category":"Pubblica Amministrazione",
    "sg:phone":"+39 0583 88248",
    "sg:postcode":"55023",
    "sg:province":"Lucca",
    "wof:name":"Comunita' Montana Media Valle Del Serchio",
    "wof:placetype":"venue"
},
  "geometry": {"coordinates":[10.5463848114,43.9794807434],"type":"Point"}
}