{
  "type": "Feature",
  "properties": {
    "iso:country":"IT",
    "sg:address":"47032 Bertinoro",
    "sg:city":"Bertinoro",
    "sg:orig_category":"Lucernari",
    "sg:phone":"+39 0543 448235",
    "sg:postcode":"47032",
    "sg:province":"Forl\u00ec-Cesena",
    "wof:name":"Faelux Snc",
    "wof:placetype":"venue"
},
  "geometry": {"coordinates":[12.133515,44.149284],"type":"Point"}
}