{
  "type": "Feature",
  "properties": {
    "iso:country":"IT",
    "sg:address":"28100 Novara",
    "sg:city":"Novara",
    "sg:orig_category":"Elaboratori Elettronici",
    "sg:phone":"+39 0321 397475",
    "sg:postcode":"28100",
    "sg:province":"Novara",
    "sg:website":"http://www.datatronic.it",
    "wof:name":"Datatronic Srl",
    "wof:placetype":"venue"
},
  "geometry": {"coordinates":[8.63791,45.444084],"type":"Point"}
}