{
  "type": "Feature",
  "properties": {
    "addr:full":"09170 Oristano Oristano Oristano 09170",
    "addr:postcode":"09170;09170",
    "iso:country":"IT",
    "sg:address":"09170 Oristano",
    "sg:city":"Oristano",
    "sg:orig_category":"Telecomunicazioni E Telefonia, Impianti, Apparecchi E Servizi",
    "sg:phone":"+39 0783 772079",
    "sg:postcode":"09170",
    "sg:province":"Oristano",
    "wof:name":"Comsystems Di Enrico Bianco",
    "wof:placetype":"venue"
},
  "geometry": {"coordinates":[8.592871,39.908054],"type":"Point"}
}