{
  "type": "Feature",
  "properties": {
    "iso:country":"IT",
    "sg:address":"20094 Corsico",
    "sg:city":"Corsico",
    "sg:orig_category":"Macchine Utensili E Impianti",
    "sg:phone":"+39 02 440 8378",
    "sg:postcode":"20094",
    "sg:province":"Milano",
    "wof:name":"Co.ma.f. Srl",
    "wof:placetype":"venue"
},
  "geometry": {"coordinates":[9.113857,45.434719],"type":"Point"}
}