{
  "type": "Feature",
  "properties": {
    "iso:country":"IT",
    "sg:address":"90139 Palermo",
    "sg:city":"Palermo",
    "sg:orig_category":"Forniture Per Edilizia E Lavori Pubblici",
    "sg:phone":"+39 091 581937",
    "sg:postcode":"90139",
    "sg:province":"Palermo",
    "wof:name":"Edil Special Srl",
    "wof:placetype":"venue"
},
  "geometry": {"coordinates":[13.3572845459,38.1294631958],"type":"Point"}
}