{
  "type": "Feature",
  "properties": {
    "iso:country":"IT",
    "sg:address":"00124 Roma",
    "sg:city":"Roma",
    "sg:orig_category":"Forniture Per Agricoltura E Zootecnia",
    "sg:phone":"+39 06 505 3062",
    "sg:postcode":"00124",
    "sg:province":"Roma",
    "wof:name":"Mangimi Zoo Di Zordani Angelo",
    "wof:placetype":"venue"
},
  "geometry": {"coordinates":[12.3616485596,41.7581367493],"type":"Point"}
}