{
  "type": "Feature",
  "properties": {
    "addr:full":"2, V. Del Lavoro 20083 Gaggiano Gaggiano Milano 20083",
    "addr:housenumber":"2",
    "addr:postcode":"20083;20083",
    "addr:street":"V. Del Lavoro",
    "iso:country":"IT",
    "sg:address":"2, V. Del Lavoro 20083 Gaggiano",
    "sg:city":"Gaggiano",
    "sg:classifiers":[
        {
            "category":"Professional",
            "subcategory":"Engineering",
            "type":"Services"
        }
    ],
    "sg:phone":"+39 39029085882",
    "sg:postcode":"20083",
    "sg:province":"Milano",
    "sg:tags":[
        "machine",
        "-",
        "mechanical"
    ],
    "sg:website":"http://www.carabelli-italy.it",
    "wof:name":"Carabelli Sas",
    "wof:placetype":"venue"
},
  "geometry": {"coordinates":[9.030807,45.386055],"type":"Point"}
}