{
  "type": "Feature",
  "properties": {
    "iso:country":"IT",
    "sg:address":"00161 Roma",
    "sg:city":"Roma",
    "sg:orig_category":"Servizi Vari Di Interesse Pubblico",
    "sg:phone":"+39 06 4423 0082",
    "sg:postcode":"00161",
    "sg:province":"Roma",
    "wof:name":"Crollalanza Aldo - Baby Club",
    "wof:placetype":"venue"
},
  "geometry": {"coordinates":[12.512946,41.910431],"type":"Point"}
}