{
  "type": "Feature",
  "properties": {
    "iso:country":"IT",
    "sg:address":"00199 Roma",
    "sg:city":"Roma",
    "sg:orig_category":"Hobbistica",
    "sg:phone":"+39 06 8621 2275",
    "sg:postcode":"00199",
    "sg:province":"Roma",
    "wof:name":"Mega Srl",
    "wof:placetype":"venue"
},
  "geometry": {"coordinates":[12.516026,41.935246],"type":"Point"}
}