{
  "type": "Feature",
  "properties": {
    "addr:full":"31050 Zenson Di Piave Zenson di Piave Treviso 31050",
    "addr:housenumber":"di piave",
    "addr:postcode":"31050;31050",
    "addr:street":"Di Piave",
    "iso:country":"IT",
    "sg:address":"31050 Zenson Di Piave",
    "sg:city":"Zenson di Piave",
    "sg:orig_category":"Prodotti E Manufatti In Materie Plastiche",
    "sg:phone":"+39 0421 344685",
    "sg:postcode":"31050",
    "sg:province":"Treviso",
    "wof:name":"Color Tech Srl",
    "wof:placetype":"venue"
},
  "geometry": {"coordinates":[12.4817781448,45.6788673401],"type":"Point"}
}