{
  "type": "Feature",
  "properties": {
    "iso:country":"IT",
    "sg:address":"1, Contrada Villa Turri 64100 Teramo",
    "sg:city":"Teramo",
    "sg:classifiers":[
        {
            "category":"Real Estate",
            "subcategory":"Architect",
            "type":"Services"
        }
    ],
    "sg:phone":"+39 0861 586131",
    "sg:postcode":"64100",
    "sg:province":"Teramo",
    "sg:tags":[
        "textile",
        "clothing"
    ],
    "wof:name":"Confezioni Futura Di Monia Di Lorenzo",
    "wof:placetype":"venue"
},
  "geometry": {"coordinates":[13.793177,42.706055],"type":"Point"}
}