{
  "type": "Feature",
  "properties": {
    "iso:country":"IT",
    "sg:address":"43100 Parma",
    "sg:city":"Baganzola",
    "sg:orig_category":"Motori Ed Organi Di Trasmissione",
    "sg:phone":"+39 0521 992200",
    "sg:postcode":"43100",
    "sg:province":"Parma",
    "sg:website":"http://www.fmiparma.it",
    "wof:name":"F.m.i. Franceschi Srl",
    "wof:placetype":"venue"
},
  "geometry": {"coordinates":[10.3092880249,44.8576049805],"type":"Point"}
}