{
  "type": "Feature",
  "properties": {
    "iso:country":"IT",
    "sg:address":"20131 Milano",
    "sg:city":"Milano",
    "sg:classifiers":[
        {
            "category":"Health Services",
            "subcategory":"Health Practitioner",
            "type":"Services"
        }
    ],
    "sg:phone":"+39 02 266 5623",
    "sg:postcode":"20131",
    "sg:province":"Milano",
    "sg:tags":[
        "medici"
    ],
    "wof:name":"Santa Clara Centro Polispecialistico (s.r.l.)",
    "wof:placetype":"venue"
},
  "geometry": {"coordinates":[9.2203025818,45.4803161621],"type":"Point"}
}