{
  "type": "Feature",
  "properties": {
    "addr:full":"67019 Scoppito L'Aquila 67019",
    "addr:postcode":"67019;l'aquila 67019",
    "iso:country":"IT",
    "sg:address":"67019 Scoppito",
    "sg:orig_category":"Palestre",
    "sg:phone":"+39 0862 717335",
    "sg:postcode":"67019",
    "sg:province":"L'Aquila",
    "sg:website":"http://www.ilquadrifogliosport.it",
    "wof:name":"Centro Sportivo Il Quadrifoglio",
    "wof:placetype":"venue"
},
  "geometry": {"coordinates":[13.2878789902,42.3597679138],"type":"Point"}
}