{
  "type": "Feature",
  "properties": {
    "addr:full":"Via Zucchi 3/d 40068 San Lazzaro Di Savena San Lazzaro Bologna 40068",
    "addr:housenumber":"3 / d",
    "addr:postcode":"40068;40068",
    "addr:street":"Via Zucchi;San;Bologna",
    "iso:country":"IT",
    "sg:address":"Via Zucchi 3/d 40068 San Lazzaro Di Savena",
    "sg:city":"San Lazzaro",
    "sg:classifiers":[
        {
            "category":"Bars & Pubs",
            "subcategory":"Wine Bar",
            "type":"Food & Drink"
        }
    ],
    "sg:phone":"+39 051 463305",
    "sg:postcode":"40068",
    "sg:province":"Bologna",
    "sg:tags":[
        "industry",
        "beverage",
        "pump"
    ],
    "sg:website":"www.attenda.it",
    "wof:name":"Ur Di Ugo Rota",
    "wof:placetype":"venue"
},
  "geometry": {"coordinates":[11.4324464798,44.4837188721],"type":"Point"}
}