{
  "type": "Feature",
  "properties": {
    "iso:country":"IT",
    "sg:address":"24059 Urgnano",
    "sg:city":"Urgnano",
    "sg:orig_category":"Canne Fumarie, Ciminiere E Camini",
    "sg:phone":"+39 035 893130",
    "sg:postcode":"24059",
    "sg:province":"Bergamo",
    "wof:name":"Pluvitecnica Srl",
    "wof:placetype":"venue"
},
  "geometry": {"coordinates":[9.69365,45.608105],"type":"Point"}
}