{
  "type": "Feature",
  "properties": {
    "addr:full":"51019 Ponte Buggianese Ponte Buggianese Pistoia 51019",
    "addr:postcode":"51019;51019",
    "iso:country":"IT",
    "sg:address":"51019 Ponte Buggianese",
    "sg:city":"Ponte Buggianese",
    "sg:orig_category":"Antiquariato",
    "sg:phone":"+39 0572 636081",
    "sg:postcode":"51019",
    "sg:province":"Pistoia",
    "wof:name":"Giovanni Falco",
    "wof:placetype":"venue"
},
  "geometry": {"coordinates":[10.748635,43.838127],"type":"Point"}
}