{
  "type": "Feature",
  "properties": {
    "addr:full":"8, Via Serio 24020 Casnigo Casnigo Bergamo 24020",
    "addr:postcode":"24020;24020",
    "addr:street":"Via Serio",
    "iso:country":"IT",
    "sg:address":"8, Via Serio 24020 Casnigo",
    "sg:city":"Casnigo",
    "sg:classifiers":[
        {
            "category":"Shopping",
            "subcategory":"Crafts & Fabrics",
            "type":"Retail Goods"
        }
    ],
    "sg:phone":"+39 39035724172",
    "sg:postcode":"24020",
    "sg:province":"Bergamo",
    "wof:name":"Dell'acqua Srl",
    "wof:placetype":"venue"
},
  "geometry": {"coordinates":[9.8733501434,45.8395729065],"type":"Point"}
}