{
  "type": "Feature",
  "properties": {
    "iso:country":"IT",
    "sg:address":"28100 Novara",
    "sg:city":"Novara",
    "sg:orig_category":"Petroli, Gas E Combustibili. Servizi E Lavori Industria Chimica. Servizi E Lavori Per Edilizia E Lavori Pubblici. Acqua, Luce, Gas E Societa' Di Esercizio Pubblico",
    "sg:phone":"+39 0321 626508",
    "sg:postcode":"28100",
    "sg:province":"Novara",
    "wof:name":"Eneco Srl",
    "wof:placetype":"venue"
},
  "geometry": {"coordinates":[8.6137733459,45.4467544556],"type":"Point"}
}