{
  "type": "Feature",
  "properties": {
    "addr:full":"28040 Dormelletto Dormelletto Novara 28040",
    "addr:postcode":"28040;28040",
    "iso:country":"IT",
    "sg:address":"28040 Dormelletto",
    "sg:city":"Dormelletto",
    "sg:orig_category":"Motori Ed Organi Di Trasmissione",
    "sg:phone":"+39 0322 241593",
    "sg:postcode":"28040",
    "sg:province":"Novara",
    "wof:name":"Lamet Sollevamenti",
    "wof:placetype":"venue"
},
  "geometry": {"coordinates":[8.564663887,45.740272522],"type":"Point"}
}