{
  "type": "Feature",
  "properties": {
    "addr:full":"14100 Asti Asti Asti 14100",
    "addr:postcode":"14100;14100",
    "iso:country":"IT",
    "sg:address":"14100 Asti",
    "sg:city":"Asti",
    "sg:orig_category":"Motori Ed Organi Di Trasmissione. Ricambi E Componenti Dei Mezzi Di Trasporto",
    "sg:phone":"+39 0141 476919",
    "sg:postcode":"14100",
    "sg:province":"Asti",
    "wof:name":"Rigan Srl",
    "wof:placetype":"venue"
},
  "geometry": {"coordinates":[8.2309808731,44.9011611938],"type":"Point"}
}