{
  "type": "Feature",
  "properties": {
    "iso:country":"IT",
    "sg:address":"10152 Torino",
    "sg:city":"Torino",
    "sg:orig_category":"Riscaldamento - Apparecchi E Materiali",
    "sg:phone":"+39 011 248 2333",
    "sg:postcode":"10152",
    "sg:province":"Torino",
    "wof:name":"Allemano Metrology Srl",
    "wof:placetype":"venue"
},
  "geometry": {"coordinates":[7.693828,45.081684],"type":"Point"}
}