{
  "type": "Feature",
  "properties": {
    "addr:full":"Via Marconi 1 30031 Dolo Dolo Venezia 30031",
    "addr:housenumber":"1",
    "addr:postcode":"30031;30031",
    "addr:street":"Via Marconi",
    "iso:country":"IT",
    "sg:address":"Via Marconi 1 30031 Dolo",
    "sg:city":"Dolo",
    "sg:classifiers":[
        {
            "category":"Professional",
            "subcategory":"Advertising",
            "type":"Services"
        }
    ],
    "sg:phone":"+39 041 464032",
    "sg:postcode":"30031",
    "sg:province":"Venezia",
    "sg:tags":[
        "video"
    ],
    "wof:name":"Telex Snc",
    "wof:placetype":"venue"
},
  "geometry": {"coordinates":[11.999568,45.430817],"type":"Point"}
}