{
  "type": "Feature",
  "properties": {
    "iso:country":"IT",
    "sg:address":"20049 Concorezzo",
    "sg:city":"Concorezzo",
    "sg:orig_category":"Macchine, Impianti Ed Attrezzature Industria Chimica. Macchine, Strumenti Ed Apparecchi Per Attivita' Industriali",
    "sg:phone":"+39 039 620 3164",
    "sg:postcode":"20049",
    "sg:province":"Milano",
    "wof:name":"Eccofil Srl",
    "wof:placetype":"venue"
},
  "geometry": {"coordinates":[9.327076,45.590023],"type":"Point"}
}