{
  "type": "Feature",
  "properties": {
    "addr:full":"00124 Roma Roma Roma 00124",
    "addr:postcode":"00124;00124",
    "iso:country":"IT",
    "sg:address":"00124 Roma",
    "sg:city":"Roma",
    "sg:orig_category":"Telecomunicazioni E Telefonia, Impianti, Apparecchi E Servizi",
    "sg:phone":"+39 06 509 0741",
    "sg:postcode":"00124",
    "sg:province":"Roma",
    "wof:name":"El.te. Snc",
    "wof:placetype":"venue"
},
  "geometry": {"coordinates":[12.512669,41.841118],"type":"Point"}
}