{
  "type": "Feature",
  "properties": {
    "iso:country":"IT",
    "sg:address":"1, Contrada Piana Romana 82020 Pietrelcina",
    "sg:city":"Pietrelcina",
    "sg:classifiers":[
        {
            "category":"Personal",
            "subcategory":"Shoe Repair & Shine",
            "type":"Services"
        }
    ],
    "sg:phone":"+39 0824 990013",
    "sg:postcode":"82020",
    "sg:province":"Benevento",
    "sg:tags":[
        "leather"
    ],
    "wof:name":"Strike Sas Di Bianco Olimpia",
    "wof:placetype":"venue"
},
  "geometry": {"coordinates":[14.863058,41.205616],"type":"Point"}
}