{
  "type": "Feature",
  "properties": {
    "iso:country":"IT",
    "sg:address":"00052 Cerveteri",
    "sg:city":"Cerveteri",
    "sg:orig_category":"Servizi Vari Di Interesse Pubblico",
    "sg:phone":"+39 06 994 1540",
    "sg:postcode":"00052",
    "sg:province":"Roma",
    "wof:name":"Baby Club Di Bombelli Barbara & C. S.a.s.",
    "wof:placetype":"venue"
},
  "geometry": {"coordinates":[12.093792,41.99218],"type":"Point"}
}