{
  "type": "Feature",
  "properties": {
    "iso:country":"IT",
    "sg:address":"37136 Verona",
    "sg:city":"Verona",
    "sg:classifiers":[
        {
            "category":"Utilities",
            "subcategory":"Refuse",
            "type":"Services"
        }
    ],
    "sg:phone":"+39 045 581144",
    "sg:postcode":"37136",
    "sg:province":"Verona",
    "sg:tags":[
        "auxiliary",
        "disposal",
        "surveillance",
        "environmental",
        "protection",
        "cleaning",
        "maintenance",
        "works"
    ],
    "wof:name":"Bottari Di Bottari Giovanni & C Sas",
    "wof:placetype":"venue"
},
  "geometry": {"coordinates":[10.960493,45.405819],"type":"Point"}
}