{
  "type": "Feature",
  "properties": {
    "iso:country":"IT",
    "sg:address":"24027 Nembro",
    "sg:city":"Nembro",
    "sg:orig_category":"Materiali Edili. Forniture Per Attivita' Industriali",
    "sg:phone":"+39 035 520751",
    "sg:postcode":"24027",
    "sg:province":"Bergamo",
    "wof:name":"Quarzifera Bergamasca S.r.l.",
    "wof:placetype":"venue"
},
  "geometry": {"coordinates":[9.748814,45.737099],"type":"Point"}
}