{
  "type": "Feature",
  "properties": {
    "addr:full":"90047 Partinico Partinico Palermo 90047",
    "addr:postcode":"90047;90047",
    "iso:country":"IT",
    "sg:address":"90047 Partinico",
    "sg:city":"Partinico",
    "sg:orig_category":"Forniture Per Agricoltura E Zootecnia. Animali Domestici",
    "sg:phone":"+39 091 890 7794",
    "sg:postcode":"90047",
    "sg:province":"Palermo",
    "wof:name":"Farmacia Veterinaria Di Rao Pietro E C. Sas",
    "wof:placetype":"venue"
},
  "geometry": {"coordinates":[13.3200378418,38.1431159973],"type":"Point"}
}