{
  "type": "Feature",
  "properties": {
    "iso:country":"IT",
    "sg:address":"20021 Bollate",
    "sg:city":"Bollate",
    "sg:classifiers":[
        {
            "category":"Health Services",
            "subcategory":"Health Practitioner",
            "type":"Services"
        }
    ],
    "sg:phone":"+39 02 3326 0049",
    "sg:postcode":"20021",
    "sg:province":"Milano",
    "sg:tags":[
        "medici"
    ],
    "wof:name":"Menghini Alberto",
    "wof:placetype":"venue"
},
  "geometry": {"coordinates":[9.138598,45.560822],"type":"Point"}
}