{
  "type": "Feature",
  "properties": {
    "addr:full":"35010 Vigonza Vigonza Padova 35010",
    "addr:postcode":"35010;35010",
    "iso:country":"IT",
    "sg:address":"35010 Vigonza",
    "sg:city":"Vigonza",
    "sg:orig_category":"Servizi E Lavori Per Agricoltura E Zootecnia",
    "sg:phone":"+39 049 646072",
    "sg:postcode":"35010",
    "sg:province":"Padova",
    "wof:name":"Pajetta Mario",
    "wof:placetype":"venue"
},
  "geometry": {"coordinates":[11.990358,45.393764],"type":"Point"}
}