{
  "type": "Feature",
  "properties": {
    "addr:full":"64020 San Nicolo'atordino Teramo 64020",
    "addr:housenumber":"64020",
    "addr:postcode":"64020",
    "addr:street":"San Nicolo'Atordino",
    "iso:country":"IT",
    "sg:address":"64020 San Nicolo'atordino",
    "sg:orig_category":"Motori Ed Organi Di Trasmissione. Ricambi E Componenti Dei Mezzi Di Trasporto",
    "sg:phone":"+39 0861 232045",
    "sg:postcode":"64020",
    "sg:province":"Teramo",
    "wof:name":"Trioneuro Spa",
    "wof:placetype":"venue"
},
  "geometry": {"coordinates":[13.6985311508,42.6612701416],"type":"Point"}
}