{
  "type": "Feature",
  "properties": {
    "addr:full":"4, Via Ciovasso 20121 Milano Milano Milano 20121",
    "addr:postcode":"20121;20121",
    "addr:street":"Via Ciovasso",
    "iso:country":"IT",
    "sg:address":"4, Via Ciovasso 20121 Milano",
    "sg:city":"Milano",
    "sg:classifiers":[
        {
            "category":"Shopping",
            "subcategory":"Gifts & Souvenirs",
            "type":"Retail Goods"
        }
    ],
    "sg:phone":"+39 02 7202 2960",
    "sg:postcode":"20121",
    "sg:province":"Milano",
    "wof:name":"Gipierre S.a.s.",
    "wof:placetype":"venue"
},
  "geometry": {"coordinates":[9.186679,45.469788],"type":"Point"}
}