{
  "type": "Feature",
  "properties": {
    "addr:full":"30121 Venezia Cannaregio Venezia 30121",
    "addr:postcode":"30121;30121",
    "addr:street":"Cannaregio",
    "iso:country":"IT",
    "sg:address":"30121 Venezia",
    "sg:city":"Cannaregio",
    "sg:orig_category":"Trasporto Pubblico E Privato",
    "sg:phone":"+39 041 715787",
    "sg:postcode":"30121",
    "sg:province":"Venezia",
    "sg:website":"http://www.veneziaweb.com/brussaisboat",
    "wof:name":"Brussa Is Boat Di Brussa G. & C. Sas",
    "wof:placetype":"venue"
},
  "geometry": {"coordinates":[12.325556,45.443611],"type":"Point"}
}