{
  "type": "Feature",
  "properties": {
    "addr:full":"00142 Roma Roma Roma 00142",
    "addr:postcode":"00142;00142",
    "iso:country":"IT",
    "sg:address":"00142 Roma",
    "sg:city":"Roma",
    "sg:orig_category":"Macchine E Forniture Per Ecologia E Smaltimento Rifiuti",
    "sg:phone":"+39 06 503 3854",
    "sg:postcode":"00142",
    "sg:province":"Roma",
    "wof:name":"Smeco S.r.l.",
    "wof:placetype":"venue"
},
  "geometry": {"coordinates":[12.494505,41.83144],"type":"Point"}
}