{
  "type": "Feature",
  "properties": {
    "iso:country":"IT",
    "sg:address":"29017 Fiorenzuola D'arda",
    "sg:orig_category":"Giardinaggio - Macchine Ed Attrezzi",
    "sg:phone":"+39 0523 983469",
    "sg:postcode":"29017",
    "sg:province":"Piacenza",
    "wof:name":"Tanzi E Troni & C. Snc",
    "wof:placetype":"venue"
},
  "geometry": {"coordinates":[9.917533,44.921272],"type":"Point"}
}