{
  "type": "Feature",
  "properties": {
    "iso:country":"IT",
    "sg:address":"4/8, Via Depretis Agostino 36100 Vicenza",
    "sg:city":"Vicenza",
    "sg:classifiers":[
        {
            "category":"Shopping",
            "subcategory":"Clothing, Apparel, & Fashions",
            "type":"Retail Goods"
        }
    ],
    "sg:phone":"+39 0444 571999",
    "sg:postcode":"36100",
    "sg:province":"Vicenza",
    "sg:tags":[
        "clothes"
    ],
    "wof:name":"Handy Blues (s.r.l.)",
    "wof:placetype":"venue"
},
  "geometry": {"coordinates":[11.526389,45.575279],"type":"Point"}
}