{
  "type": "Feature",
  "properties": {
    "iso:country":"IT",
    "sg:address":"36015 Schio",
    "sg:city":"Schio",
    "sg:orig_category":"Cartotecnica E Servizi. Forniture Per Attivita' Commerciali Ed Artigianali",
    "sg:phone":"+39 0445 575633",
    "sg:postcode":"36015",
    "sg:province":"Vicenza",
    "wof:name":"Paper Line S.p.a.",
    "wof:placetype":"venue"
},
  "geometry": {"coordinates":[11.542892,45.576706],"type":"Point"}
}