{
  "type": "Feature",
  "properties": {
    "iso:country":"IT",
    "sg:address":"10043 Orbassano",
    "sg:city":"Orbassano",
    "sg:orig_category":"Fonderie",
    "sg:phone":"+39 011 901 7567",
    "sg:postcode":"10043",
    "sg:province":"Torino",
    "wof:name":"De.cio Di De Cio Domenico & C. Snc",
    "wof:placetype":"venue"
},
  "geometry": {"coordinates":[7.5789418221,45.0106582642],"type":"Point"}
}