{
  "type": "Feature",
  "properties": {
    "iso:country":"IT",
    "sg:address":"Via Montelungo 59 20027 Rescaldina",
    "sg:city":"Rescaldina",
    "sg:classifiers":[
        {
            "category":"Banks & Credit Unions",
            "subcategory":"Investment Brokerage",
            "type":"Services"
        }
    ],
    "sg:phone":"+39 0331 576450",
    "sg:postcode":"20027",
    "sg:province":"Milano",
    "sg:tags":[
        "product",
        "hair-care"
    ],
    "sg:website":"www.lisapitalia.com",
    "wof:name":"Lisap Spa",
    "wof:placetype":"venue"
},
  "geometry": {"coordinates":[8.965183,45.613945],"type":"Point"}
}