{
  "type": "Feature",
  "properties": {
    "iso:country":"IT",
    "sg:address":"40068 San Lazzaro Di Savena",
    "sg:city":"San Lazzaro",
    "sg:orig_category":"Non-classified Establishments",
    "sg:phone":"+39 051 482447",
    "sg:postcode":"40068",
    "sg:province":"Bologna",
    "wof:name":"Il Cartiglio Di Masi Paolo",
    "wof:placetype":"venue"
},
  "geometry": {"coordinates":[11.341667,44.377247],"type":"Point"}
}