{
  "type": "Feature",
  "properties": {
    "addr:full":"24036 Ponte San Pietro Ponte San Pietro Bergamo 24036",
    "addr:postcode":"24036;24036",
    "iso:country":"IT",
    "sg:address":"24036 Ponte San Pietro",
    "sg:city":"Ponte San Pietro",
    "sg:orig_category":"Petroli, Gas E Combustibili. Termotecnica E Riscaldamento, Apparecchiature E Servizi",
    "sg:phone":"+39 035 611221",
    "sg:postcode":"24036",
    "sg:province":"Bergamo",
    "wof:name":"Calber Srl",
    "wof:placetype":"venue"
},
  "geometry": {"coordinates":[9.575091362,45.7083320618],"type":"Point"}
}