{
  "type": "Feature",
  "properties": {
    "iso:country":"IT",
    "sg:address":"13, Via Umberto I 64034 Castiglione Messer Raimondo",
    "sg:city":"Castiglione Messer Raimondo",
    "sg:classifiers":[
        {
            "category":"Banks & Credit Unions",
            "subcategory":"Bank",
            "type":"Services"
        }
    ],
    "sg:phone":"+39 0861 990660",
    "sg:postcode":"64034",
    "sg:province":"Teramo",
    "sg:tags":[
        "banking",
        "institution"
    ],
    "wof:name":"Banca Di Credito Cooperativo Castiglione Messer Raimondo E Pianella",
    "wof:placetype":"venue"
},
  "geometry": {"coordinates":[13.87781,42.532753],"type":"Point"}
}