{
  "type": "Feature",
  "properties": {
    "iso:country":"IT",
    "sg:address":"31021 Mogliano Veneto",
    "sg:city":"Mogliano Veneto",
    "sg:orig_category":"Servizi E Lavori Per Edilizia E Lavori Pubblici. Acqua, Luce, Gas E Societa' Di Esercizio Pubblico",
    "sg:phone":"+39 041 590 1995",
    "sg:postcode":"31021",
    "sg:province":"Treviso",
    "wof:name":"Spim Servizi Pubblici Integrati Mogliano (s.p.a.)",
    "wof:placetype":"venue"
},
  "geometry": {"coordinates":[12.233357,45.603714],"type":"Point"}
}