{
  "type": "Feature",
  "properties": {
    "iso:country":"IT",
    "sg:address":"18011 Arma Di Taggia",
    "sg:classifiers":[
        {
            "category":"Health Services",
            "subcategory":"Health Practitioner",
            "type":"Services"
        }
    ],
    "sg:phone":"+39 0184 449024",
    "sg:postcode":"18011",
    "sg:province":"Imperia",
    "sg:tags":[
        "medici"
    ],
    "wof:name":"Vacher Lucien",
    "wof:placetype":"venue"
},
  "geometry": {"coordinates":[7.8286366463,43.9418678284],"type":"Point"}
}