{
  "type": "Feature",
  "properties": {
    "iso:country":"IT",
    "sg:address":"00044 Frascati",
    "sg:city":"Frascati",
    "sg:orig_category":"Servizi Per Lo Sport E Il Tempo Libero. Servizi Vari Di Interesse Pubblico",
    "sg:phone":"+39 06 9401 5032",
    "sg:postcode":"00044",
    "sg:province":"Roma",
    "wof:name":"S.a.i.f.di Cori Carlitto Omero E C. Snc",
    "wof:placetype":"venue"
},
  "geometry": {"coordinates":[12.679217,41.808311],"type":"Point"}
}