{
  "type": "Feature",
  "properties": {
    "iso:country":"IT",
    "sg:address":"3, Corso A. De Gasperi 10070 Robassomero",
    "sg:city":"Robassomero",
    "sg:classifiers":[
        {
            "category":"Manufacturing",
            "subcategory":"Metals",
            "type":"Manufacturing & Wholesale Goods"
        }
    ],
    "sg:phone":"+39 011 924 1113",
    "sg:postcode":"10070",
    "sg:province":"Torino",
    "sg:tags":[
        "metallurgy",
        "metalworking"
    ],
    "wof:name":"Costruzioni Accessori Per Auto Spa",
    "wof:placetype":"venue"
},
  "geometry": {"coordinates":[7.6866188049,45.0705604553],"type":"Point"}
}