{
  "type": "Feature",
  "properties": {
    "iso:country":"IT",
    "sg:address":"50022 Greve In Chianti",
    "sg:city":"Greve in Chianti",
    "sg:orig_category":"Restaurants And Related Public Premises. Sport And Leisure, Services. Hotels And Hotel Facilities. Restaurants And Similar",
    "sg:phone":"+39 055 857 2266",
    "sg:postcode":"50022",
    "sg:province":"Firenze",
    "wof:name":"Locanda Il Gallo",
    "wof:placetype":"venue"
},
  "geometry": {"coordinates":[11.313888,43.63829],"type":"Point"}
}