{
  "type": "Feature",
  "properties": {
    "iso:country":"IT",
    "sg:address":"20095 Cusano Milanino",
    "sg:city":"Cusano Milanino",
    "sg:classifiers":[
        {
            "category":"Health Services",
            "subcategory":"Health Practitioner",
            "type":"Services"
        }
    ],
    "sg:phone":"+39 02 619 9382",
    "sg:postcode":"20095",
    "sg:province":"Milano",
    "sg:tags":[
        "medici"
    ],
    "wof:name":"Fisiomed Center Srl",
    "wof:placetype":"venue"
},
  "geometry": {"coordinates":[9.191217,45.554844],"type":"Point"}
}