{
  "type": "Feature",
  "properties": {
    "iso:country":"IT",
    "sg:address":"00126 Roma",
    "sg:city":"Roma",
    "sg:orig_category":"Armadi Guardaroba",
    "sg:phone":"+39 06 521 9377",
    "sg:postcode":"00126",
    "sg:province":"Roma",
    "sg:website":"http://www.legno-ingegno.it",
    "wof:name":"Legno+ingegno",
    "wof:placetype":"venue"
},
  "geometry": {"coordinates":[12.335497,41.779667],"type":"Point"}
}