{
  "type": "Feature",
  "properties": {
    "iso:country":"IT",
    "sg:address":"38023 Cles",
    "sg:city":"Cles",
    "sg:orig_category":"Acquedotti, Gasdotti Ed Oleodotti - Impianti Ed Attrezzature",
    "sg:phone":"+39 0463 625262",
    "sg:postcode":"38023",
    "sg:province":"Trento",
    "sg:website":"http://www.idroforniture.it",
    "wof:name":"Idroforniture Snc Di Angeli Riccardo & C.",
    "wof:placetype":"venue"
},
  "geometry": {"coordinates":[11.035169,46.356541],"type":"Point"}
}