{
  "type": "Feature",
  "properties": {
    "iso:country":"IT",
    "sg:address":"37050 Angiari",
    "sg:city":"Angiari",
    "sg:orig_category":"Termotecnica E Riscaldamento, Apparecchiature E Servizi",
    "sg:postcode":"37050",
    "sg:province":"Verona",
    "wof:name":"F.b.r. Bruciatori (s.r.l.)",
    "wof:placetype":"venue"
},
  "geometry": {"coordinates":[10.987655,45.448505],"type":"Point"}
}