{
  "type": "Feature",
  "properties": {
    "iso:country":"IT",
    "sg:address":"Corso Garibaldi, 62; Pordenone; 33170",
    "sg:city":"Pordenone",
    "sg:classifiers":[
        {
            "category":"Banks & Credit Unions",
            "subcategory":"Bank",
            "type":"Services"
        }
    ],
    "sg:phone":"+39 0434 28021",
    "sg:postcode":"33170",
    "sg:province":"Pordenone",
    "wof:name":"Banca Nazionale Del Lavoro",
    "wof:placetype":"venue"
},
  "geometry": {"coordinates":[12.65595,45.961308],"type":"Point"}
}