{
  "type": "Feature",
  "properties": {
    "iso:country":"IT",
    "sg:address":"00192 Roma",
    "sg:city":"Roma",
    "sg:orig_category":"Servizi E Lavori Per Abbigliamento E Pelletterie. Cartotecnica E Servizi. Servizi E Lavori Industria Delle Materie Plastiche",
    "sg:phone":"+39 06 3750 0375",
    "sg:postcode":"00192",
    "sg:province":"Roma",
    "wof:name":"Pompameo Sabrina",
    "wof:placetype":"venue"
},
  "geometry": {"coordinates":[12.456837,41.909115],"type":"Point"}
}