{
  "type": "Feature",
  "properties": {
    "addr:full":"113, Via Ferraro 92020 Santo Stefano Quisquina Santo Stefano Quisquina Agrigento 92020",
    "addr:housenumber":"113",
    "addr:postcode":"92020;92020",
    "addr:street":"Via Ferraro",
    "iso:country":"IT",
    "sg:address":"113, Via Ferraro 92020 Santo Stefano Quisquina",
    "sg:city":"Santo Stefano Quisquina",
    "sg:classifiers":[
        {
            "category":"Shopping",
            "subcategory":"Clothing, Apparel, & Fashions",
            "type":"Retail Goods"
        }
    ],
    "sg:phone":"+39 0922 982887",
    "sg:postcode":"92020",
    "sg:province":"Agrigento",
    "sg:tags":[
        "clothes"
    ],
    "wof:name":"Artinpell S.n.c. Di L. & A.ragusa",
    "wof:placetype":"venue"
},
  "geometry": {"coordinates":[13.488954,37.625145],"type":"Point"}
}