{
  "type": "Feature",
  "properties": {
    "iso:country":"IT",
    "sg:address":"25079 Vobarno",
    "sg:city":"Vobarno",
    "sg:orig_category":"Nastri Per Trasportatori Ed Elevatori",
    "sg:phone":"+39 036 582 1122",
    "sg:postcode":"25079",
    "sg:province":"Brescia",
    "wof:name":"Mastrotec Snc Di Alberti Vincenzo E Giovanni Snc",
    "wof:placetype":"venue"
},
  "geometry": {"coordinates":[10.009222,45.424999],"type":"Point"}
}