{
  "type": "Feature",
  "properties": {
    "iso:country":"IT",
    "sg:address":"66015 Fara San Martino",
    "sg:city":"Fara San Martino",
    "sg:orig_category":"Macchine, Impianti Ed Attrezzature Per Industria Alimentare E Bevande",
    "sg:phone":"+39 0872 984192",
    "sg:postcode":"66015",
    "sg:province":"Chieti",
    "wof:name":"La Fara",
    "wof:placetype":"venue"
},
  "geometry": {"coordinates":[14.207025,42.095871],"type":"Point"}
}