{
  "type": "Feature",
  "properties": {
    "iso:country":"IT",
    "sg:address":"15, Via Cappella 81021 Arienzo",
    "sg:city":"Arienzo",
    "sg:classifiers":[
        {
            "category":"Communications",
            "subcategory":"Television Station",
            "type":"Services"
        }
    ],
    "sg:phone":"+39 0823 804260",
    "sg:postcode":"81021",
    "sg:province":"Caserta",
    "sg:tags":[
        "audio-visual"
    ],
    "wof:name":"Videotec Srl",
    "wof:placetype":"venue"
},
  "geometry": {"coordinates":[14.494908,41.029175],"type":"Point"}
}