{
  "type": "Feature",
  "properties": {
    "addr:full":"74, V. Gramsci 47100 Forl\u00ec Forl\u00ec-Cesena 47100",
    "addr:housenumber":"74",
    "addr:postcode":"47100;47100",
    "addr:street":"V. Gramsci",
    "iso:country":"IT",
    "sg:address":"74, V. Gramsci 47100 Forl\u00ec",
    "sg:orig_category":"Miscellaneous Products",
    "sg:phone":"+39 0543 400395",
    "sg:postcode":"47100",
    "sg:province":"Forl\u00ec-Cesena",
    "wof:name":"Pompe Funebri Ravaioli",
    "wof:placetype":"venue"
},
  "geometry": {"coordinates":[12.0591430664,44.2189369202],"type":"Point"}
}