{
  "type": "Feature",
  "properties": {
    "addr:full":"Via Terza Armata 91/93 34170 Gorizia Gorizia Gorizia 34170",
    "addr:housenumber":"91 / 93",
    "addr:postcode":"34170;34170",
    "addr:street":"Via Terza Armata",
    "iso:country":"IT",
    "sg:address":"Via Terza Armata 91/93 34170 Gorizia",
    "sg:city":"Gorizia",
    "sg:classifiers":[
        {
            "category":"Coffee & Tea",
            "type":"Food & Drink"
        }
    ],
    "sg:phone":"+39 0481 522132",
    "sg:postcode":"34170",
    "sg:province":"Gorizia",
    "sg:tags":[
        "roasted"
    ],
    "sg:website":"www.caffegoriziana.com",
    "wof:name":"Torrefazione Goriziana Snc Di Crobe Lorenzo, Rogelja Stefano & C.",
    "wof:placetype":"venue"
},
  "geometry": {"coordinates":[13.62437,45.93034],"type":"Point"}
}