{
  "type": "Feature",
  "properties": {
    "iso:country":"IT",
    "sg:address":"12030 Casalgrasso",
    "sg:city":"Casalgrasso",
    "sg:orig_category":"Macchine Ed Impianti Per Edilizia E Lavori Pubblici",
    "sg:phone":"+39 011 975005",
    "sg:postcode":"12030",
    "sg:province":"Cuneo",
    "wof:name":"M.m.t. Sas",
    "wof:placetype":"venue"
},
  "geometry": {"coordinates":[7.634738,44.82513],"type":"Point"}
}