{
  "type": "Feature",
  "properties": {
    "addr:full":"Via Di Porta Al Borgo 130; Pistoia; 51100 Pistoia Pistoia 51100",
    "addr:housenumber":"130",
    "addr:postcode":"51100;51100",
    "addr:street":"Via Di Porta Al Borgo",
    "iso:country":"IT",
    "sg:address":"Via Di Porta Al Borgo 130; Pistoia; 51100",
    "sg:city":"Pistoia",
    "sg:classifiers":[
        {
            "category":"Banks & Credit Unions",
            "subcategory":"Bank",
            "type":"Services"
        }
    ],
    "sg:phone":"+39 0573 368226",
    "sg:postcode":"51100",
    "sg:province":"Pistoia",
    "wof:name":"Cassa Di Risparmio Di Pistoia, E Pescia",
    "wof:placetype":"venue"
},
  "geometry": {"coordinates":[10.911704,43.936703],"type":"Point"}
}