{
  "type": "Feature",
  "properties": {
    "addr:full":"60027 Osimo Osimo Ancona 60027",
    "addr:postcode":"60027;60027",
    "iso:country":"IT",
    "sg:address":"60027 Osimo",
    "sg:city":"Osimo",
    "sg:orig_category":"Elettrotecnica Industriale, Prodotti E Apparecchiature. Elettronica Industriale, Prodotti E Apparecchiature",
    "sg:phone":"+39 071 713 2758",
    "sg:postcode":"60027",
    "sg:province":"Ancona",
    "sg:website":"http://www.seav.com",
    "wof:name":"Seav Srl",
    "wof:placetype":"venue"
},
  "geometry": {"coordinates":[13.497324,43.496376],"type":"Point"}
}