{
  "type": "Feature",
  "properties": {
    "iso:country":"IT",
    "sg:address":"Piazza Della Marina 65126 Pescara",
    "sg:city":"Pescara",
    "sg:classifiers":[
        {
            "category":"Banks & Credit Unions",
            "subcategory":"Investment Brokerage",
            "type":"Services"
        }
    ],
    "sg:phone":"+39 39085693718",
    "sg:postcode":"65126",
    "sg:province":"Pescara",
    "sg:tags":[
        "-",
        "transport",
        "related"
    ],
    "wof:name":"Stante Spedizioni (s.r.l.)",
    "wof:placetype":"venue"
},
  "geometry": {"coordinates":[14.218844,42.463566],"type":"Point"}
}