{
  "type": "Feature",
  "properties": {
    "iso:country":"IT",
    "sg:address":"20083 Gaggiano",
    "sg:city":"Gaggiano",
    "sg:orig_category":"Macchine, Impianti Ed Attrezzature Per Abbigliamento E Pelletterie",
    "sg:phone":"+39 02 908 6955",
    "sg:postcode":"20083",
    "sg:province":"Milano",
    "wof:name":"Paggi (s.r.l.)",
    "wof:placetype":"venue"
},
  "geometry": {"coordinates":[9.152798,45.478371],"type":"Point"}
}