{
  "type": "Feature",
  "properties": {
    "addr:full":"5, Via Mondovi' 20132 Milano Milano Milano 20132",
    "addr:postcode":"20132;20132",
    "addr:street":"Via Mondovi '",
    "iso:country":"IT",
    "sg:address":"5, Via Mondovi' 20132 Milano",
    "sg:city":"Milano",
    "sg:classifiers":[
        {
            "category":"Sports & Exercise",
            "subcategory":"Playing Field",
            "type":"Entertainment"
        }
    ],
    "sg:phone":"+39 39022590965",
    "sg:postcode":"20132",
    "sg:province":"Milano",
    "sg:tags":[
        "game"
    ],
    "wof:name":"Ripa S.r.l.",
    "wof:placetype":"venue"
},
  "geometry": {"coordinates":[9.241715,45.503323],"type":"Point"}
}