{
  "type": "Feature",
  "properties": {
    "iso:country":"IT",
    "sg:address":"20041 Agrate Brianza",
    "sg:city":"Agrate Brianza",
    "sg:orig_category":"Macchine Ed Impianti Per Edilizia E Lavori Pubblici",
    "sg:phone":"+39 039 660762",
    "sg:postcode":"20041",
    "sg:province":"Milano",
    "sg:website":"http://www.tuttoufficio.it",
    "wof:name":"E.d.c. One By Tuttoufficio",
    "wof:placetype":"venue"
},
  "geometry": {"coordinates":[9.336305,45.574757],"type":"Point"}
}