{
  "type": "Feature",
  "properties": {
    "iso:country":"IT",
    "sg:address":"95131 Catania",
    "sg:city":"Catania",
    "sg:orig_category":"Non-classified Establishments",
    "sg:phone":"+39 095 315176",
    "sg:postcode":"95131",
    "sg:province":"Catania",
    "wof:name":"Mazza Sebastiano",
    "wof:placetype":"venue"
},
  "geometry": {"coordinates":[15.088365,37.51017],"type":"Point"}
}