{
  "type": "Feature",
  "properties": {
    "addr:full":"00187 Roma Roma Roma 00187",
    "addr:postcode":"00187;00187",
    "iso:country":"IT",
    "sg:address":"00187 Roma",
    "sg:city":"Roma",
    "sg:classifiers":[
        {
            "category":"Retail",
            "subcategory":"Auto Repair",
            "type":"Services"
        }
    ],
    "sg:phone":"+39 06 4288 1111",
    "sg:postcode":"00187",
    "sg:province":"Roma",
    "sg:tags":[
        "car",
        "vehicles",
        "motor"
    ],
    "wof:name":"Roma L. & B.",
    "wof:placetype":"venue"
},
  "geometry": {"coordinates":[12.494029,41.908497],"type":"Point"}
}