{
  "type": "Feature",
  "properties": {
    "addr:full":"19, Via Cesare Battisti 24026 Leffe Leffe Bergamo 24026",
    "addr:postcode":"24026;24026",
    "addr:street":"Via Cesare Battisti",
    "iso:country":"IT",
    "sg:address":"19, Via Cesare Battisti 24026 Leffe",
    "sg:city":"Leffe",
    "sg:classifiers":[
        {
            "category":"Shopping",
            "subcategory":"Computers & Home Electronics",
            "type":"Retail Goods"
        }
    ],
    "sg:phone":"+39 39035734347",
    "sg:postcode":"24026",
    "sg:province":"Bergamo",
    "sg:tags":[
        "electronic",
        "electrical",
        "equipment"
    ],
    "wof:name":"Co.el.in. Srl",
    "wof:placetype":"venue"
},
  "geometry": {"coordinates":[9.892919,45.801086],"type":"Point"}
}