{
  "type": "Feature",
  "properties": {
    "addr:full":"37036 San Martino Buon Albergo San Martino Buon Albergo Verona 37036",
    "addr:housenumber":"37036",
    "addr:postcode":"buon albergo;37036",
    "iso:country":"IT",
    "sg:address":"37036 San Martino Buon Albergo",
    "sg:city":"San Martino Buon Albergo",
    "sg:orig_category":"Cooperative Produzione, Lavoro E Servizi",
    "sg:phone":"+39 045 892 1729",
    "sg:postcode":"37036",
    "sg:province":"Verona",
    "sg:website":"http://www.gruppoitalservice.com",
    "wof:name":"Verona Work Soc. Coop. A R.l.",
    "wof:placetype":"venue"
},
  "geometry": {"coordinates":[11.091562,45.414032],"type":"Point"}
}