{
  "type": "Feature",
  "properties": {
    "addr:full":"30031 Dolo Arino Venezia 30031",
    "addr:postcode":"30031;30031",
    "iso:country":"IT",
    "sg:address":"30031 Dolo",
    "sg:city":"Arino",
    "sg:orig_category":"Autogru - Noleggio",
    "sg:phone":"+39 041 411747",
    "sg:postcode":"30031",
    "sg:province":"Venezia",
    "wof:name":"Armando Gobbo Srl",
    "wof:placetype":"venue"
},
  "geometry": {"coordinates":[12.064445,45.440838],"type":"Point"}
}