{
  "type": "Feature",
  "properties": {
    "addr:full":"12 Corso Matteotti Giacomo, 20121 Milano Milano Milano 20121",
    "addr:postcode":"20121;20121",
    "addr:street":"Corso Matteotti Giacomo",
    "iso:country":"IT",
    "sg:address":"12 Corso Matteotti Giacomo, 20121 Milano",
    "sg:city":"Milano",
    "sg:classifiers":[
        {
            "category":"Banks & Credit Unions",
            "subcategory":"Financial Services",
            "type":"Services"
        }
    ],
    "sg:phone":"+39 390 277 661",
    "sg:postcode":"20121",
    "sg:province":"Milano",
    "sg:tags":[
        "banking",
        "finance",
        "insurance"
    ],
    "wof:name":"Cbi Factor Spa",
    "wof:placetype":"venue"
},
  "geometry": {"coordinates":[9.1953296661,45.4669151306],"type":"Point"}
}