{
  "type": "Feature",
  "properties": {
    "addr:full":"00040 Ariccia Ariccia Roma 00040",
    "addr:postcode":"00040;roma 00040",
    "iso:country":"IT",
    "sg:address":"00040 Ariccia",
    "sg:city":"Ariccia",
    "sg:orig_category":"Macchine, Impianti Ed Attrezzature Per Industria Alimentare E Bevande",
    "sg:phone":"+39 06 933 3182",
    "sg:postcode":"00040",
    "sg:province":"Roma",
    "wof:name":"Guastalli Mario",
    "wof:placetype":"venue"
},
  "geometry": {"coordinates":[12.695651,41.734653],"type":"Point"}
}