{
  "type": "Feature",
  "properties": {
    "addr:full":"60125 Ancona Ancona Ancona 60125",
    "addr:postcode":"60125;60125",
    "iso:country":"IT",
    "sg:address":"60125 Ancona",
    "sg:city":"Ancona",
    "sg:orig_category":"Pesci Freschi E Surgelati - Lavorazione E Commercio",
    "sg:phone":"+39 071 201956",
    "sg:postcode":"60125",
    "sg:province":"Ancona",
    "wof:name":"Ancoopesca Spa",
    "wof:placetype":"venue"
},
  "geometry": {"coordinates":[13.4914751053,43.609752655],"type":"Point"}
}