{
  "type": "Feature",
  "properties": {
    "addr:full":"29100 Piacenza Piacenza Piacenza 29100",
    "addr:postcode":"29100;29100",
    "iso:country":"IT",
    "sg:address":"29100 Piacenza",
    "sg:city":"Piacenza",
    "sg:orig_category":"Agenzie D'affari E Servizi Commerciali. Servizi Per Aziende, Manifestazioni E Supporto Agli Scambi Commerciali. Acqua, Luce, Gas E Societa' Di Esercizio Pubblico",
    "sg:phone":"+39 0523 3861",
    "sg:postcode":"29100",
    "sg:province":"Piacenza",
    "wof:name":"Camera Commercio Industria Artigianato Agricoltura",
    "wof:placetype":"venue"
},
  "geometry": {"coordinates":[9.693162,45.052288],"type":"Point"}
}