{
  "type": "Feature",
  "properties": {
    "iso:country":"IT",
    "sg:address":"50018 Scandicci",
    "sg:city":"Scandicci",
    "sg:orig_category":"Vetro: Prodotti E Lavorazioni. Forniture Per Attivita' Industriali",
    "sg:phone":"+39 055 722 1367",
    "sg:postcode":"50018",
    "sg:province":"Firenze",
    "wof:name":"Gestione Silo S.r.l.",
    "wof:placetype":"venue"
},
  "geometry": {"coordinates":[11.141559,43.766376],"type":"Point"}
}