{
  "type": "Feature",
  "properties": {
    "addr:full":"63039 San Benedetto Del Tronto San Benedetto del Tronto Ascoli Piceno 63039",
    "addr:housenumber":"63039",
    "addr:postcode":"63039",
    "addr:street":"San;Piceno",
    "iso:country":"IT",
    "sg:address":"63039 San Benedetto Del Tronto",
    "sg:city":"San Benedetto del Tronto",
    "sg:orig_category":"Facchinaggio, Carico E Scarico Merci, Portabagagli - Servizio",
    "sg:phone":"+39 0735 584232",
    "sg:postcode":"63039",
    "sg:province":"Ascoli Piceno",
    "wof:name":"Cooperativa T.t.f. Arl",
    "wof:placetype":"venue"
},
  "geometry": {"coordinates":[13.8812618256,42.9540939331],"type":"Point"}
}