{
  "type": "Feature",
  "properties": {
    "addr:full":"20127 Milano Milano Milano 20127",
    "addr:postcode":"20127;20127",
    "iso:country":"IT",
    "sg:address":"20127 Milano",
    "sg:city":"Milano",
    "sg:orig_category":"Climatizzazione E Condizionamento, Apparecchiature E Servizi",
    "sg:phone":"+39 02 282 9247",
    "sg:postcode":"20127",
    "sg:province":"Milano",
    "wof:name":"Astair & Co. (s.r.l.)",
    "wof:placetype":"venue"
},
  "geometry": {"coordinates":[9.211169,45.489513],"type":"Point"}
}