{
  "type": "Feature",
  "properties": {
    "iso:country":"IT",
    "sg:address":"80058 Torre Annunziata",
    "sg:city":"Torre Annunziata",
    "sg:orig_category":"Hobbistica",
    "sg:phone":"+39 081 861 5613",
    "sg:postcode":"80058",
    "sg:province":"Napoli",
    "wof:name":"Bergamasco Salvatore",
    "wof:placetype":"venue"
},
  "geometry": {"coordinates":[14.439692,40.757801],"type":"Point"}
}