{
  "type": "Feature",
  "properties": {
    "addr:full":"Via Alessandro Volta, 1; Cenate Sotto; Bergamo; I-24069 Cenate Sotto Bergamo 24069",
    "addr:housenumber":"1;i-24069",
    "addr:postcode":"24069",
    "addr:street":"Via Alessandro Volta;Sotto Bergamo",
    "iso:country":"IT",
    "sg:address":"Via Alessandro Volta, 1; Cenate Sotto; Bergamo; I-24069",
    "sg:city":"Cenate Sotto",
    "sg:classifiers":[
        {
            "category":"Industrial Area",
            "type":"Public Place"
        }
    ],
    "sg:phone":"+39 39035946111",
    "sg:postcode":"24069",
    "sg:province":"Bergamo",
    "sg:tags":[
        "large",
        "private"
    ],
    "sg:website":"www.gewiss.it",
    "wof:name":"Gewiss S.p.a.",
    "wof:placetype":"venue"
},
  "geometry": {"coordinates":[9.7567329407,45.7020530701],"type":"Point"}
}