{
  "type": "Feature",
  "properties": {
    "addr:full":"20122 Milano Milano Milano 20122",
    "addr:postcode":"20122;20122",
    "iso:country":"IT",
    "sg:address":"20122 Milano",
    "sg:city":"Milano",
    "sg:orig_category":"Informatica - Consulenza E Servizi. Automazione E Macchine Per Ufficio. Servizi Ausiliari Di Analisi, Controllo E Ricerca. Servizi Per Aziende, Manifestazioni E Supporto Agli Scambi Commerciali",
    "sg:phone":"+39 02 5518 2169",
    "sg:postcode":"20122",
    "sg:province":"Milano",
    "sg:website":"http://www.achab.it",
    "wof:name":"Achab Srl",
    "wof:placetype":"venue"
},
  "geometry": {"coordinates":[9.196806,45.459793],"type":"Point"}
}