{
  "type": "Feature",
  "properties": {
    "iso:country":"IT",
    "sg:address":"21049 Tradate",
    "sg:city":"Tradate",
    "sg:classifiers":[
        {
            "category":"Manufacturing",
            "subcategory":"Motor Vehicles & Parts",
            "type":"Manufacturing & Wholesale Goods"
        }
    ],
    "sg:phone":"+39 0331 843929",
    "sg:postcode":"21049",
    "sg:province":"Varese",
    "sg:tags":[
        "vehicles",
        "accessory"
    ],
    "wof:name":"M. V. Di Iseppi Claudio",
    "wof:placetype":"venue"
},
  "geometry": {"coordinates":[8.8222732544,45.8241958618],"type":"Point"}
}