{
  "type": "Feature",
  "properties": {
    "addr:full":"80035 Nola Nola Napoli 80035",
    "addr:housenumber":"80035",
    "addr:postcode":"80035",
    "addr:street":"Nola",
    "iso:country":"IT",
    "sg:address":"80035 Nola",
    "sg:city":"Nola",
    "sg:orig_category":"Pompe. Elettrotecnica Industriale, Prodotti E Apparecchiature",
    "sg:phone":"+39 081 821 0114",
    "sg:postcode":"80035",
    "sg:province":"Napoli",
    "wof:name":"Ferrara Giovanni",
    "wof:placetype":"venue"
},
  "geometry": {"coordinates":[14.218000412,40.8874969482],"type":"Point"}
}