{
  "type": "Feature",
  "properties": {
    "addr:full":"10 Piazza Pitagora, 00197 Roma Roma Roma 00197",
    "addr:postcode":"00197;00197",
    "addr:street":"Pitagora",
    "iso:country":"IT",
    "sg:address":"10 Piazza Pitagora, 00197 Roma",
    "sg:city":"Roma",
    "sg:classifiers":[
        {
            "category":"Banks & Credit Unions",
            "subcategory":"Financial Services",
            "type":"Services"
        }
    ],
    "sg:phone":"+39 390 680 8991",
    "sg:postcode":"00197",
    "sg:province":"Roma",
    "sg:tags":[
        "banking",
        "finance",
        "insurance"
    ],
    "wof:name":"Studio Elaborazioni Dati Imposta Valore Aggiunto",
    "wof:placetype":"venue"
},
  "geometry": {"coordinates":[12.4904880524,41.9221305847],"type":"Point"}
}