{
  "type": "Feature",
  "properties": {
    "iso:country":"IT",
    "sg:address":"10122 Torino",
    "sg:city":"Torino",
    "sg:orig_category":"Articoli Da Regalo. Arte Ed Artigianato Artistico. Shopping",
    "sg:phone":"+39 011 436 1336",
    "sg:postcode":"10122",
    "sg:province":"Torino",
    "wof:name":"Centostrade Sas",
    "wof:placetype":"venue"
},
  "geometry": {"coordinates":[7.680715,45.073292],"type":"Point"}
}