{
  "type": "Feature",
  "properties": {
    "addr:full":"41100 Modena Modena Modena 41100",
    "addr:postcode":"41100;41100",
    "iso:country":"IT",
    "sg:address":"41100 Modena",
    "sg:city":"Modena",
    "sg:orig_category":"Macchine, Impianti Ed Attrezzature Per Abbigliamento E Pelletterie",
    "sg:phone":"+39 059 300447",
    "sg:postcode":"41100",
    "sg:province":"Modena",
    "wof:name":"Baraldi Fratelli",
    "wof:placetype":"venue"
},
  "geometry": {"coordinates":[10.944763,44.550903],"type":"Point"}
}