{
  "type": "Feature",
  "properties": {
    "iso:country":"IT",
    "sg:address":"10, Via Malnisce 34070 Savogna D'isonzo",
    "sg:classifiers":[
        {
            "category":"Shopping",
            "type":"Retail Goods"
        }
    ],
    "sg:phone":"+39 0481 882450",
    "sg:postcode":"34070",
    "sg:province":"Gorizia",
    "sg:tags":[
        "finished",
        "-",
        "metallic"
    ],
    "wof:name":"Caudek Lavorazioni Lamiere & C. (s.n.c.)",
    "wof:placetype":"venue"
},
  "geometry": {"coordinates":[13.5743179321,45.8974266052],"type":"Point"}
}