{
  "type": "Feature",
  "properties": {
    "addr:full":"Via Delle Fornaci 98 60044 Fabriano Fabriano Ancona 60044",
    "addr:housenumber":"98",
    "addr:postcode":"60044;60044",
    "addr:street":"Via Delle Fornaci",
    "iso:country":"IT",
    "sg:address":"Via Delle Fornaci 98 60044 Fabriano",
    "sg:city":"Fabriano",
    "sg:classifiers":[
        {
            "category":"Home & Garden",
            "subcategory":"Household Appliances",
            "type":"Retail Goods"
        }
    ],
    "sg:phone":"+39 0732 6931",
    "sg:postcode":"60044",
    "sg:province":"Ancona",
    "sg:tags":[
        "electric"
    ],
    "sg:website":"www.turboair.com",
    "wof:name":"Turboair Spa",
    "wof:placetype":"venue"
},
  "geometry": {"coordinates":[12.902463,43.343136],"type":"Point"}
}