{
  "type": "Feature",
  "properties": {
    "iso:country":"IT",
    "sg:address":"2, Via Collari-renazzo 44042 Cento",
    "sg:city":"Cento",
    "sg:classifiers":[
        {
            "category":"Shopping",
            "subcategory":"Clothing, Apparel, & Fashions",
            "type":"Retail Goods"
        }
    ],
    "sg:phone":"+39 051 685 2511",
    "sg:postcode":"44042",
    "sg:province":"Ferrara",
    "sg:tags":[
        "clothes"
    ],
    "wof:name":"B & B Tricot Maglificio Balboni Srl",
    "wof:placetype":"venue"
},
  "geometry": {"coordinates":[11.275933,44.75349],"type":"Point"}
}