{
  "type": "Feature",
  "properties": {
    "iso:country":"IT",
    "sg:address":"56, Via Labicana 00184 Roma",
    "sg:city":"Roma",
    "sg:classifiers":[
        {
            "category":"Banks & Credit Unions",
            "subcategory":"Investment Brokerage",
            "type":"Services"
        }
    ],
    "sg:phone":"+39 06 7720 9041",
    "sg:postcode":"00184",
    "sg:province":"Roma",
    "sg:tags":[
        "-",
        "transport",
        "related"
    ],
    "wof:name":"Pony Line Srl",
    "wof:placetype":"venue"
},
  "geometry": {"coordinates":[12.500789,41.889416],"type":"Point"}
}