{
  "type": "Feature",
  "properties": {
    "addr:full":"23871 Lomagna Lomagna Lecco 23871",
    "addr:postcode":"23871;23871",
    "iso:country":"IT",
    "sg:address":"23871 Lomagna",
    "sg:city":"Lomagna",
    "sg:classifiers":[
        {
            "category":"Health Services",
            "subcategory":"Health Practitioner",
            "type":"Services"
        }
    ],
    "sg:phone":"+39 039 530 0184",
    "sg:postcode":"23871",
    "sg:province":"Lecco",
    "sg:tags":[
        "medici"
    ],
    "wof:name":"Trezza Lorenzo",
    "wof:placetype":"venue"
},
  "geometry": {"coordinates":[9.380273819,45.6604270935],"type":"Point"}
}