{
  "type": "Feature",
  "properties": {
    "iso:country":"IT",
    "sg:address":"Via Faccin 100 36030 Villaverla",
    "sg:city":"Villaverla",
    "sg:classifiers":[
        {
            "category":"Home & Garden",
            "subcategory":"Garden Supply",
            "type":"Retail Goods"
        }
    ],
    "sg:phone":"+39 0445 855922",
    "sg:postcode":"36030",
    "sg:province":"Vicenza",
    "sg:tags":[
        "planter"
    ],
    "sg:website":"www.iterra.it",
    "wof:name":"Iterra Srl",
    "wof:placetype":"venue"
},
  "geometry": {"coordinates":[11.484503746,45.6502723694],"type":"Point"}
}