{
  "type": "Feature",
  "properties": {
    "iso:country":"IT",
    "sg:address":"50012 Bagno A Ripoli",
    "sg:city":"Antella",
    "sg:orig_category":"Prodotti E Manufatti In Gomma. Forniture Per Attivita' Industriali",
    "sg:phone":"+39 055 620687",
    "sg:postcode":"50012",
    "sg:province":"Firenze",
    "sg:website":"http://www.pianigiani.it",
    "wof:name":"Pianigiani Umberto Srl",
    "wof:placetype":"venue"
},
  "geometry": {"coordinates":[11.3166685104,43.7267990112],"type":"Point"}
}