{
  "type": "Feature",
  "properties": {
    "iso:country":"IT",
    "sg:address":"20, V. Mengarini 00149 Roma",
    "sg:city":"Roma",
    "sg:classifiers":[
        {
            "category":"Shopping",
            "subcategory":"Crafts & Fabrics",
            "type":"Retail Goods"
        }
    ],
    "sg:phone":"+39 39065575249",
    "sg:postcode":"00149",
    "sg:province":"Roma",
    "sg:website":"http://www.cilm.it:ws_end: :mark:ws:http://www.paginegialle.it/cilm",
    "wof:name":"C.i.l.m. Srl",
    "wof:placetype":"venue"
},
  "geometry": {"coordinates":[12.4564762115,41.8636360168],"type":"Point"}
}