{
  "type": "Feature",
  "properties": {
    "iso:country":"IT",
    "sg:address":"20136 Milano",
    "sg:city":"Milano",
    "sg:orig_category":"Pubblica Amministrazione",
    "sg:phone":"+39 02 583821",
    "sg:postcode":"20136",
    "sg:province":"Milano",
    "wof:name":"Provveditorato Agli Studi Di Milano",
    "wof:placetype":"venue"
},
  "geometry": {"coordinates":[9.1982011795,45.4453697205],"type":"Point"}
}