{
  "type": "Feature",
  "properties": {
    "addr:full":"60121 Ancona Ancona Ancona 60121",
    "addr:postcode":"60121;60121",
    "iso:country":"IT",
    "sg:address":"60121 Ancona",
    "sg:city":"Ancona",
    "sg:orig_category":"Servizi Per Aziende, Manifestazioni E Supporto Agli Scambi Commerciali",
    "sg:phone":"+39 071 203456",
    "sg:postcode":"60121",
    "sg:province":"Ancona",
    "sg:website":"http://www.progettocasa-sposi.com",
    "wof:name":"Studio Europa - Fiere Ad Ancona",
    "wof:placetype":"venue"
},
  "geometry": {"coordinates":[13.514827,43.618267],"type":"Point"}
}