{
  "type": "Feature",
  "properties": {
    "iso:country":"IT",
    "sg:address":"Via Delle Scienze 21 20082 Binasco",
    "sg:city":"Binasco",
    "sg:classifiers":[
        {
            "category":"Professional",
            "subcategory":"Computer Services",
            "type":"Services"
        }
    ],
    "sg:phone":"+39 02 905731",
    "sg:postcode":"20082",
    "sg:province":"Milano",
    "sg:tags":[
        "adhesive",
        "printing",
        "self-adhesive",
        "system",
        "label"
    ],
    "sg:website":"www.kfitr.it",
    "wof:name":"Kfi Trading Srl",
    "wof:placetype":"venue"
},
  "geometry": {"coordinates":[9.094501,45.336464],"type":"Point"}
}