{
  "type": "Feature",
  "properties": {
    "iso:country":"IT",
    "sg:address":"67, Corso D'azeglio Massimo 10015 Ivrea",
    "sg:city":"Ivrea",
    "sg:classifiers":[
        {
            "category":"Travel",
            "subcategory":"Travel Agent",
            "type":"Entertainment"
        }
    ],
    "sg:phone":"+39 39012549190",
    "sg:postcode":"10015",
    "sg:province":"Torino",
    "sg:tags":[
        "business"
    ],
    "wof:name":"Fraigna S.r.l.",
    "wof:placetype":"venue"
},
  "geometry": {"coordinates":[7.686619,45.07056],"type":"Point"}
}