{
  "type": "Feature",
  "properties": {
    "iso:country":"IT",
    "sg:address":"31046 Oderzo",
    "sg:city":"Oderzo",
    "sg:classifiers":[
        {
            "category":"Travel",
            "subcategory":"Travel Agent",
            "type":"Entertainment"
        }
    ],
    "sg:phone":"+39 0422 713699",
    "sg:postcode":"31046",
    "sg:province":"Treviso",
    "sg:tags":[
        "operator",
        "tour",
        "tourist"
    ],
    "sg:website":"http://www.cash.it/opitergium/ospit/primhotel/default.htm",
    "wof:name":"Primhotel Citt\u00c0 Di Oderzo - Komogest Srl",
    "wof:placetype":"venue"
},
  "geometry": {"coordinates":[12.499269,45.76228],"type":"Point"}
}