{
  "type": "Feature",
  "properties": {
    "iso:country":"IT",
    "sg:address":"40129 Bologna",
    "sg:city":"Bologna",
    "sg:orig_category":"Prodotti Chimici Di Base. Forniture Per Attivita' Industriali",
    "sg:phone":"+39 051 356326",
    "sg:postcode":"40129",
    "sg:province":"Bologna",
    "wof:name":"Ampacet Italia S.r.l.",
    "wof:placetype":"venue"
},
  "geometry": {"coordinates":[11.3272848129,44.5184516907],"type":"Point"}
}