{
  "type": "Feature",
  "properties": {
    "addr:full":"Via S. Barbara 139/d 48010 Fusignano Fusignano Ravenna 48010",
    "addr:housenumber":"139 / d",
    "addr:postcode":"48010;48010",
    "addr:street":"Via S. Barbara",
    "iso:country":"IT",
    "sg:address":"Via S. Barbara 139/d 48010 Fusignano",
    "sg:city":"Fusignano",
    "sg:classifiers":[
        {
            "category":"Structure",
            "subcategory":"Office Building",
            "type":"Public Place"
        }
    ],
    "sg:phone":"+39 0545 53170",
    "sg:postcode":"48010",
    "sg:province":"Ravenna",
    "sg:tags":[
        "filtering",
        "installation"
    ],
    "sg:website":"www.filmac-fitter.com",
    "wof:name":"Filmac S L Filtration Srl",
    "wof:placetype":"venue"
},
  "geometry": {"coordinates":[11.9557628632,44.465133667],"type":"Point"}
}