{
  "type": "Feature",
  "properties": {
    "addr:full":"43010 Fontevivo Fontevivo Parma 43010",
    "addr:postcode":"43010;43010",
    "iso:country":"IT",
    "sg:address":"43010 Fontevivo",
    "sg:city":"Fontevivo",
    "sg:orig_category":"Materie Plastiche Rinforzate E Materiali Compositi",
    "sg:phone":"+39 0521 610550",
    "sg:postcode":"43010",
    "sg:province":"Parma",
    "wof:name":"Bergamaschi Attilio",
    "wof:placetype":"venue"
},
  "geometry": {"coordinates":[10.176259,44.859871],"type":"Point"}
}