{
  "type": "Feature",
  "properties": {
    "iso:country":"IT",
    "sg:address":"45, Via Roma 57126 Livorno",
    "sg:city":"Livorno",
    "sg:classifiers":[
        {
            "category":"Sports & Exercise",
            "subcategory":"Playing Field",
            "type":"Entertainment"
        }
    ],
    "sg:phone":"+39 0586 808518",
    "sg:postcode":"57126",
    "sg:province":"Livorno",
    "sg:tags":[
        "game"
    ],
    "wof:name":"Guastalla Arte Moderna E Contemporanea Edizioni Graphis Arte",
    "wof:placetype":"venue"
},
  "geometry": {"coordinates":[10.31338,43.543598],"type":"Point"}
}