{
  "type": "Feature",
  "properties": {
    "addr:full":"00155 Roma Roma Roma 00155",
    "addr:postcode":"00155;00155",
    "iso:country":"IT",
    "sg:address":"00155 Roma",
    "sg:city":"Roma",
    "sg:orig_category":"Articoli Da Regalo. Regalistica Aziendale",
    "sg:phone":"+39 06 229 2453",
    "sg:postcode":"00155",
    "sg:province":"Roma",
    "wof:name":"Mirti Paolo",
    "wof:placetype":"venue"
},
  "geometry": {"coordinates":[12.6048288345,41.9123878479],"type":"Point"}
}