{
  "type": "Feature",
  "properties": {
    "addr:full":"92, Viale Colombo Cristoforo 50054 Fucecchio Fucecchio Firenze 50054",
    "addr:housenumber":"92",
    "addr:postcode":"50054;50054",
    "addr:street":"Viale Colombo Cristoforo",
    "iso:country":"IT",
    "sg:address":"92, Viale Colombo Cristoforo 50054 Fucecchio",
    "sg:city":"Fucecchio",
    "sg:classifiers":[
        {
            "category":"Personal",
            "subcategory":"Shoe Repair & Shine",
            "type":"Services"
        }
    ],
    "sg:phone":"+39 0571 261508",
    "sg:postcode":"50054",
    "sg:province":"Firenze",
    "sg:tags":[
        "leather"
    ],
    "wof:name":"Calzaturificio Harris Shoes 1913 S.r.l.",
    "wof:placetype":"venue"
},
  "geometry": {"coordinates":[11.256902,43.768734],"type":"Point"}
}