{
  "type": "Feature",
  "properties": {
    "addr:full":"13, Via Pinerolo 22063 Cantu' Como 22063",
    "addr:postcode":"22063;22063",
    "addr:street":"Via Pinerolo;Cantu ' Como",
    "iso:country":"IT",
    "sg:address":"13, Via Pinerolo 22063 Cantu'",
    "sg:classifiers":[
        {
            "category":"Manufacturing",
            "subcategory":"Rubber & Plastics",
            "type":"Manufacturing & Wholesale Goods"
        }
    ],
    "sg:phone":"+39 39031713726",
    "sg:postcode":"22063",
    "sg:province":"Como",
    "wof:name":"Nuova Premi (s.n.c.)",
    "wof:placetype":"venue"
},
  "geometry": {"coordinates":[9.136007309,45.7279968262],"type":"Point"}
}