{
  "type": "Feature",
  "properties": {
    "iso:country":"IT",
    "sg:address":"20146 Milano",
    "sg:city":"Milano",
    "sg:orig_category":"Macchine, Impianti Ed Attrezzature Industria Delle Materie Plastiche E Gomma",
    "sg:phone":"+39 02 423 4432",
    "sg:postcode":"20146",
    "sg:province":"Milano",
    "wof:name":"Siplast Di Gastone Palmeri",
    "wof:placetype":"venue"
},
  "geometry": {"coordinates":[9.136949,45.450756],"type":"Point"}
}