{
  "type": "Feature",
  "properties": {
    "iso:country":"IT",
    "sg:address":"Via Taranto 73100 Lecce",
    "sg:city":"Lecce",
    "sg:classifiers":[
        {
            "category":"Airport",
            "subcategory":"General Aviation",
            "type":"Transportation"
        }
    ],
    "sg:phone":"+39 0832 331570",
    "sg:postcode":"73100",
    "sg:province":"Lecce",
    "sg:tags":[
        "transport",
        "air"
    ],
    "wof:name":"Trasporti Memmi S.r.l.",
    "wof:placetype":"venue"
},
  "geometry": {"coordinates":[18.143244,40.366081],"type":"Point"}
}