{
  "type": "Feature",
  "properties": {
    "iso:country":"IT",
    "sg:address":"00142 Roma",
    "sg:city":"Roma",
    "sg:orig_category":"Macchine, Impianti Ed Attrezzature Industria Chimica",
    "sg:phone":"+39 06 540 3268",
    "sg:postcode":"00142",
    "sg:province":"Roma",
    "wof:name":"Silea (s.r.l.)",
    "wof:placetype":"venue"
},
  "geometry": {"coordinates":[12.480901,41.84557],"type":"Point"}
}