{
  "type": "Feature",
  "properties": {
    "iso:country":"IT",
    "sg:address":"Stradello Zucchero 5 42045 Luzzara",
    "sg:classifiers":[
        {
            "category":"Manufacturing",
            "subcategory":"Tools & Machinery",
            "type":"Manufacturing & Wholesale Goods"
        }
    ],
    "sg:phone":"+39 0522 976067",
    "sg:postcode":"42045",
    "sg:province":"Reggio Nell'Emilia",
    "sg:website":"www.omalutensilli.it",
    "wof:name":"Omal Officine Meccaniche Artoni Luzzara Snc",
    "wof:placetype":"venue"
},
  "geometry": {"coordinates":[10.627794,44.696228],"type":"Point"}
}