{
  "type": "Feature",
  "properties": {
    "addr:full":"90123 Palermo Palermo Palermo 90123",
    "addr:postcode":"90123;90123",
    "iso:country":"IT",
    "sg:address":"90123 Palermo",
    "sg:city":"Palermo",
    "sg:orig_category":"Abbigliamento Esterno, Maglierie E Pelliccerie. Shopping",
    "sg:phone":"+39 091 472361",
    "sg:postcode":"90123",
    "sg:province":"Palermo",
    "wof:name":"Marago Abbigliamento Di Accardi Agostina",
    "wof:placetype":"venue"
},
  "geometry": {"coordinates":[13.210017,37.974766],"type":"Point"}
}