{
  "type": "Feature",
  "properties": {
    "addr:full":"24128 Bergamo Bergamo Bergamo 24128",
    "addr:postcode":"24128;24128",
    "iso:country":"IT",
    "sg:address":"24128 Bergamo",
    "sg:city":"Bergamo",
    "sg:orig_category":"Articoli Regalo - Vendita Al Dettaglio",
    "sg:phone":"+39 035 525 9402",
    "sg:postcode":"24128",
    "sg:province":"Bergamo",
    "wof:name":"Basta Antonio",
    "wof:placetype":"venue"
},
  "geometry": {"coordinates":[9.656411,45.693035],"type":"Point"}
}