{
  "type": "Feature",
  "properties": {
    "iso:country":"IT",
    "sg:address":"40050 Castello D'argile",
    "sg:orig_category":"Automobili E Mezzi Di Trasporto",
    "sg:phone":"+39 051 686 7144",
    "sg:postcode":"40050",
    "sg:province":"Bologna",
    "wof:name":"F G M Di Fabbri Gino E C. Snc",
    "wof:placetype":"venue"
},
  "geometry": {"coordinates":[11.343594,44.682293],"type":"Point"}
}