{
  "type": "Feature",
  "properties": {
    "iso:country":"IT",
    "sg:address":"1473/a, Dorsoduro 30123 Venezia",
    "sg:city":"Dorsoduro",
    "sg:classifiers":[
        {
            "category":"Marine",
            "type":"Transportation"
        }
    ],
    "sg:phone":"+39 041 271 2511",
    "sg:postcode":"30123",
    "sg:province":"Venezia",
    "sg:tags":[
        "transport",
        "sea"
    ],
    "wof:name":"Tositti & C. S.r.l.",
    "wof:placetype":"venue"
},
  "geometry": {"coordinates":[12.321962,45.431011],"type":"Point"}
}