{
  "type": "Feature",
  "properties": {
    "addr:full":"24020 Scanzorosciate Rosciate Bergamo 24020",
    "addr:postcode":"24020;24020",
    "iso:country":"IT",
    "sg:address":"24020 Scanzorosciate",
    "sg:city":"Rosciate",
    "sg:orig_category":"Arredamenti E Mobili Professionali. Impianti, Attrezzature E Forniture Sanitarie Ed Ospedaliere",
    "sg:phone":"+39 035 661872",
    "sg:postcode":"24020",
    "sg:province":"Bergamo",
    "wof:name":"Ceramiche F.lli Barcella Srl",
    "wof:placetype":"venue"
},
  "geometry": {"coordinates":[9.74865,45.706108],"type":"Point"}
}