{
  "type": "Feature",
  "properties": {
    "addr:full":"41019 Soliera Soliera Modena 41019",
    "addr:postcode":"41019;41019",
    "iso:country":"IT",
    "sg:address":"41019 Soliera",
    "sg:city":"Soliera",
    "sg:classifiers":[
        {
            "category":"Manufacturing",
            "subcategory":"Metals",
            "type":"Manufacturing & Wholesale Goods"
        }
    ],
    "sg:phone":"+39 059 561094",
    "sg:postcode":"41019",
    "sg:province":"Modena",
    "sg:tags":[
        "forming",
        "working",
        "welding"
    ],
    "sg:website":"http://www.icam-inox.com",
    "wof:name":"Icam Inox Srl",
    "wof:placetype":"venue"
},
  "geometry": {"coordinates":[10.8986291885,44.7447624207],"type":"Point"}
}