{
  "type": "Feature",
  "properties": {
    "addr:full":"25, Via Campostino Di Mezzana 59100 Prato Mezzana Prato 59100",
    "addr:postcode":"59100;59100",
    "addr:street":"Via Campostino Di Mezzana",
    "iso:country":"IT",
    "sg:address":"25, Via Campostino Di Mezzana 59100 Prato",
    "sg:city":"Mezzana",
    "sg:classifiers":[
        {
            "category":"Shopping",
            "subcategory":"Crafts & Fabrics",
            "type":"Retail Goods"
        }
    ],
    "sg:phone":"+39 0574 593368",
    "sg:postcode":"59100",
    "sg:province":"Prato",
    "wof:name":"Tessitura Italia Srl",
    "wof:placetype":"venue"
},
  "geometry": {"coordinates":[11.0986394882,43.8542671204],"type":"Point"}
}