{
  "type": "Feature",
  "properties": {
    "iso:country":"IT",
    "sg:address":"40033 Casalecchio Di Reno",
    "sg:city":"Casalecchio di Reno",
    "sg:classifiers":[
        {
            "category":"Shopping",
            "subcategory":"Beauty & Cosmetics",
            "type":"Retail Goods"
        }
    ],
    "sg:phone":"+39 051 619 9440",
    "sg:postcode":"40033",
    "sg:province":"Bologna",
    "sg:tags":[
        "salons",
        "activities",
        "supply",
        "commercial",
        "equipment",
        "artisan",
        "supplies"
    ],
    "sg:website":"http://www.globuspso.com",
    "wof:name":"Globus P.s.o.",
    "wof:placetype":"venue"
},
  "geometry": {"coordinates":[11.291379,44.48793],"type":"Point"}
}