{
  "type": "Feature",
  "properties": {
    "iso:country":"IT",
    "sg:address":"24027 Nembro",
    "sg:city":"Nembro",
    "sg:orig_category":"Arredamento Bar E Ristoranti",
    "sg:phone":"+39 035 470388",
    "sg:postcode":"24027",
    "sg:province":"Bergamo",
    "wof:name":"Dondoni Fabio",
    "wof:placetype":"venue"
},
  "geometry": {"coordinates":[9.722438,45.733078],"type":"Point"}
}