{
  "type": "Feature",
  "properties": {
    "iso:country":"IT",
    "sg:address":"244, Via Napoli 80022 Arzano",
    "sg:city":"Arzano",
    "sg:classifiers":[
        {
            "category":"Personal",
            "subcategory":"Shoe Repair & Shine",
            "type":"Services"
        }
    ],
    "sg:phone":"+39 081 573 4833",
    "sg:postcode":"80022",
    "sg:province":"Napoli",
    "sg:tags":[
        "leather"
    ],
    "wof:name":"Calzaturificio Campanile Fratelli",
    "wof:placetype":"venue"
},
  "geometry": {"coordinates":[14.265368,40.906467],"type":"Point"}
}