{
  "type": "Feature",
  "properties": {
    "iso:country":"IT",
    "sg:address":"09123 Cagliari",
    "sg:city":"Cagliari",
    "sg:orig_category":"Prodotti E Manufatti In Materie Plastiche. Articoli Per Imballaggio E Confezionamento",
    "sg:phone":"+39 070 657813",
    "sg:postcode":"09123",
    "sg:province":"Cagliari",
    "wof:name":"Sardavetroresine Di Ivo Manca",
    "wof:placetype":"venue"
},
  "geometry": {"coordinates":[9.1041154861,39.2206726074],"type":"Point"}
}