{
  "type": "Feature",
  "properties": {
    "iso:country":"IT",
    "sg:address":"11, Via Briga 28045 Invorio",
    "sg:city":"Invorio",
    "sg:classifiers":[
        {
            "category":"Shopping",
            "type":"Retail Goods"
        }
    ],
    "sg:phone":"+39 0322 255420",
    "sg:postcode":"28045",
    "sg:province":"Novara",
    "sg:tags":[
        "finished",
        "-",
        "metallic"
    ],
    "wof:name":"Raccorderie T.a.a. (s.p.a.)",
    "wof:placetype":"venue"
},
  "geometry": {"coordinates":[8.4214992523,45.7438240051],"type":"Point"}
}