{
  "type": "Feature",
  "properties": {
    "iso:country":"IT",
    "sg:address":"27, Via Carlo Cattaneo 12062 Cherasco",
    "sg:city":"Cherasco",
    "sg:classifiers":[
        {
            "category":"Manufacturing",
            "subcategory":"Textiles",
            "type":"Manufacturing & Wholesale Goods"
        }
    ],
    "sg:phone":"+39 0172 499039",
    "sg:postcode":"12062",
    "sg:province":"Cuneo",
    "sg:tags":[
        "leather",
        "raw",
        "material",
        "-"
    ],
    "wof:name":"Nuova Bra Pelli S.n.c.di Fea Domenico E Gullino Franco",
    "wof:placetype":"venue"
},
  "geometry": {"coordinates":[7.830384,44.668232],"type":"Point"}
}