{
  "type": "Feature",
  "properties": {
    "iso:country":"IT",
    "sg:address":"10146 Torino",
    "sg:city":"Torino",
    "sg:orig_category":"Macchine, Impianti E Forniture Per Industria Grafica, Cartaria E Cartotecnica. Automazione E Macchine Per Ufficio",
    "sg:phone":"+39 011 779 0080",
    "sg:postcode":"10146",
    "sg:province":"Torino",
    "wof:name":"G.s. Media S.a.s.",
    "wof:placetype":"venue"
},
  "geometry": {"coordinates":[7.120077,45.126019],"type":"Point"}
}