{
  "type": "Feature",
  "properties": {
    "iso:country":"IT",
    "sg:address":"9, Via Pio X 35010 Santa Giustina In Colle",
    "sg:city":"Santa Giustina in Colle",
    "sg:classifiers":[
        {
            "category":"Professional",
            "subcategory":"Engineering",
            "type":"Services"
        }
    ],
    "sg:phone":"+39 049 579 2100",
    "sg:postcode":"35010",
    "sg:province":"Padova",
    "sg:tags":[
        "machine",
        "-",
        "mechanical"
    ],
    "wof:name":"Brofer S.r.l.",
    "wof:placetype":"venue"
},
  "geometry": {"coordinates":[11.903065,45.576176],"type":"Point"}
}