{
  "type": "Feature",
  "properties": {
    "iso:country":"IT",
    "sg:address":"133, Strada Del Francese 10156 Torino",
    "sg:city":"Torino",
    "sg:classifiers":[
        {
            "category":"Professional",
            "subcategory":"Engineering",
            "type":"Services"
        }
    ],
    "sg:phone":"+39 011 450 8111",
    "sg:postcode":"10156",
    "sg:province":"Torino",
    "sg:tags":[
        "machine",
        "-",
        "mechanical"
    ],
    "wof:name":"Spesso Gaskets Srl",
    "wof:placetype":"venue"
},
  "geometry": {"coordinates":[7.672241,45.134205],"type":"Point"}
}