{
  "type": "Feature",
  "properties": {
    "addr:full":"Viale Monza 1 20127 Milano Milano Milano 20127",
    "addr:housenumber":"1",
    "addr:postcode":"20127;20127",
    "addr:street":"Viale Monza",
    "iso:country":"IT",
    "sg:address":"Viale Monza 1 20127 Milano",
    "sg:city":"Milano",
    "sg:classifiers":[
        {
            "category":"Retail",
            "subcategory":"Emissions Testing",
            "type":"Services"
        }
    ],
    "sg:phone":"+39 02 282 9411",
    "sg:postcode":"20127",
    "sg:province":"Milano",
    "sg:tags":[
        "consumer",
        "good",
        "export"
    ],
    "wof:name":"Incotrade Srl",
    "wof:placetype":"venue"
},
  "geometry": {"coordinates":[9.21692,45.48719],"type":"Point"}
}