{
  "type": "Feature",
  "properties": {
    "iso:country":"IT",
    "sg:address":"18016 San Bartolomeo Al Mare",
    "sg:city":"San Bartolomeo al Mare",
    "sg:orig_category":"Consulenza Agricola E Forestale",
    "sg:phone":"+39 0183 408477",
    "sg:postcode":"18016",
    "sg:province":"Imperia",
    "wof:name":"Quadriservice Snc",
    "wof:placetype":"venue"
},
  "geometry": {"coordinates":[8.104928,43.92115],"type":"Point"}
}