{
  "type": "Feature",
  "properties": {
    "iso:country":"IT",
    "sg:address":"12, Via Molise 36015 Schio",
    "sg:city":"Schio",
    "sg:classifiers":[
        {
            "category":"Manufacturing",
            "subcategory":"Food",
            "type":"Manufacturing & Wholesale Goods"
        }
    ],
    "sg:phone":"+39 0445 576250",
    "sg:postcode":"36015",
    "sg:province":"Vicenza",
    "sg:tags":[
        "equipment",
        "processing",
        "-",
        "machinery"
    ],
    "wof:name":"Mimac Italia (s.r.l.)",
    "wof:placetype":"venue"
},
  "geometry": {"coordinates":[11.39980793,45.7213745117],"type":"Point"}
}