{
  "type": "Feature",
  "properties": {
    "addr:full":"Contrada Piani Bianchi 62029 Tolentino Tolentino Macerata 62029",
    "addr:postcode":"62029;62029",
    "addr:street":"Contrada Piani Bianchi",
    "iso:country":"IT",
    "sg:address":"Contrada Piani Bianchi 62029 Tolentino",
    "sg:city":"Tolentino",
    "sg:classifiers":[
        {
            "category":"Personal",
            "subcategory":"Shoe Repair & Shine",
            "type":"Services"
        }
    ],
    "sg:phone":"+39 0733 973227",
    "sg:postcode":"62029",
    "sg:province":"Macerata",
    "sg:tags":[
        "leather"
    ],
    "wof:name":"Pelletteria Tolloni S.a.s. Di Tolloni Patrizio & C",
    "wof:placetype":"venue"
},
  "geometry": {"coordinates":[13.4562616348,43.3007469177],"type":"Point"}
}