{
  "type": "Feature",
  "properties": {
    "iso:country":"IT",
    "sg:address":"20015 Parabiago",
    "sg:city":"Parabiago",
    "sg:orig_category":"Materiali Semilavorati Metallici. Materiali E Componenti Elettrotecnici",
    "sg:phone":"+39 0331 495031",
    "sg:postcode":"20015",
    "sg:province":"Milano",
    "wof:name":"Tranceria Italiana Lamierini Magnetici (s.r.l.)",
    "wof:placetype":"venue"
},
  "geometry": {"coordinates":[8.958752,45.568439],"type":"Point"}
}