{
  "type": "Feature",
  "properties": {
    "addr:full":"50067 Rignano Sull'arno Firenze 50067",
    "addr:postcode":"50067;50067",
    "iso:country":"IT",
    "sg:address":"50067 Rignano Sull'arno",
    "sg:orig_category":"Restaurants And Related Public Premises. Sport And Leisure, Services. Hotels And Hotel Facilities. Restaurants And Similar",
    "sg:phone":"+39 055 830 5240",
    "sg:postcode":"50067",
    "sg:province":"Firenze",
    "wof:name":"Relais Chiara & Lorenzo",
    "wof:placetype":"venue"
},
  "geometry": {"coordinates":[11.422559,43.7225],"type":"Point"}
}