{
  "type": "Feature",
  "properties": {
    "iso:country":"IT",
    "sg:address":"Via Candini 2 40012 Calderara Di Reno",
    "sg:city":"Calderara di Reno",
    "sg:classifiers":[
        {
            "category":"Professional",
            "subcategory":"Credit Reporting & Collection",
            "type":"Services"
        }
    ],
    "sg:phone":"+39 051 314 7011",
    "sg:postcode":"40012",
    "sg:province":"Bologna",
    "sg:tags":[
        "reader",
        "bar-code"
    ],
    "sg:website":"www.datalogic.it",
    "wof:name":"Datalogic Spa",
    "wof:placetype":"venue"
},
  "geometry": {"coordinates":[11.301712,44.544388],"type":"Point"}
}