{
  "type": "Feature",
  "properties": {
    "iso:country":"IT",
    "sg:address":"Via Casa Perizi 1 42035 Castelnovo Ne' Monti",
    "sg:classifiers":[
        {
            "category":"Home & Garden",
            "subcategory":"Home Furnishings",
            "type":"Retail Goods"
        }
    ],
    "sg:phone":"+39 0522 625111",
    "sg:postcode":"42035",
    "sg:province":"Reggio Nell'Emilia",
    "sg:tags":[
        "household",
        "ceramic"
    ],
    "sg:website":"www.rondinegroup.com",
    "wof:name":"Bismantova Spa",
    "wof:placetype":"venue"
},
  "geometry": {"coordinates":[10.627794,44.696228],"type":"Point"}
}