{
  "type": "Feature",
  "properties": {
    "iso:country":"IT",
    "sg:address":"15, V. Bisbino 22072 Cermenate",
    "sg:city":"Cermenate",
    "sg:classifiers":[
        {
            "category":"Professional",
            "subcategory":"Engineering",
            "type":"Services"
        }
    ],
    "sg:phone":"+39 39031773455",
    "sg:postcode":"22072",
    "sg:province":"Como",
    "sg:tags":[
        "machine",
        "-",
        "mechanical"
    ],
    "sg:website":"http://www.paginegialle.it/omtr",
    "wof:name":"O.m.t.r. Srl Officine Meccaniche",
    "wof:placetype":"venue"
},
  "geometry": {"coordinates":[9.075408,45.703026],"type":"Point"}
}