{
  "type": "Feature",
  "properties": {
    "iso:country":"IT",
    "sg:address":"7/a, Localita' Pianizza Di Sotto 39052 Caldaro Sulla Strada Del Vino",
    "sg:city":"Caldaro sulla strada del vino",
    "sg:classifiers":[
        {
            "category":"Farming",
            "subcategory":"Livestock Farm",
            "type":"Manufacturing & Wholesale Goods"
        }
    ],
    "sg:phone":"+39 0471 963565",
    "sg:postcode":"39052",
    "sg:province":"Bolzano/Bozen",
    "sg:tags":[
        "agriculture"
    ],
    "wof:name":"Perkmann A. Blumen & C. S.n.c.",
    "wof:placetype":"venue"
},
  "geometry": {"coordinates":[11.255459,46.430786],"type":"Point"}
}