{
  "type": "Feature",
  "properties": {
    "iso:country":"IT",
    "sg:address":"94018 Troina",
    "sg:city":"Troina",
    "sg:orig_category":"Ceramiche: Prodotti E Lavorazioni",
    "sg:phone":"+39 0935 654146",
    "sg:postcode":"94018",
    "sg:province":"Enna",
    "wof:name":"Lo Cascio Marmi Di Lo Cascio Enrico",
    "wof:placetype":"venue"
},
  "geometry": {"coordinates":[14.635463,37.755424],"type":"Point"}
}