{
  "type": "Feature",
  "properties": {
    "iso:country":"IT",
    "sg:address":"20123 Milano",
    "sg:city":"Milano",
    "sg:orig_category":"Avvocati - Studi",
    "sg:phone":"+39 02 854231",
    "sg:postcode":"20123",
    "sg:province":"Milano",
    "sg:website":"http://www.ashursts.com",
    "wof:name":"Studio Legale Associato Ad Ashurst Morris Crisp",
    "wof:placetype":"venue"
},
  "geometry": {"coordinates":[9.181848,45.462959],"type":"Point"}
}