{
  "type": "Feature",
  "properties": {
    "iso:country":"IT",
    "sg:address":"20060 Pozzuolo Martesana",
    "sg:city":"Pozzuolo Martesana",
    "sg:orig_category":"Servizi E Lavori Per Arredamento E Industria Del Legno",
    "sg:phone":"+39 02 9535 9185",
    "sg:postcode":"20060",
    "sg:province":"Milano",
    "wof:name":"Cividini Giacomo",
    "wof:placetype":"venue"
},
  "geometry": {"coordinates":[9.151748,45.559765],"type":"Point"}
}