{
  "type": "Feature",
  "properties": {
    "iso:country":"IT",
    "sg:address":"00192 Roma",
    "sg:city":"Roma",
    "sg:orig_category":"Centri Di Estetica E Cosmesi E Servizi. Prodotti Cosmetici E Da Toeletta",
    "sg:phone":"+39 06 3973 8141",
    "sg:postcode":"00192",
    "sg:province":"Roma",
    "wof:name":"Ferrara Alberto",
    "wof:placetype":"venue"
},
  "geometry": {"coordinates":[12.71643,41.815178],"type":"Point"}
}