{
  "type": "Feature",
  "properties": {
    "iso:country":"IT",
    "sg:address":"41, Via Delle Vestali 00181 Roma",
    "sg:city":"Roma",
    "sg:classifiers":[
        {
            "category":"Travel",
            "subcategory":"Travel Agent",
            "type":"Entertainment"
        }
    ],
    "sg:phone":"+39 39067806804",
    "sg:postcode":"00181",
    "sg:province":"Roma",
    "sg:tags":[
        "business"
    ],
    "wof:name":"Ristorante Il Capriolo",
    "wof:placetype":"venue"
},
  "geometry": {"coordinates":[12.528934,41.871765],"type":"Point"}
}