{
  "type": "Feature",
  "properties": {
    "iso:country":"IT",
    "sg:address":"1, Via Magellano F. 06016 San Giustino",
    "sg:city":"San Giustino",
    "sg:classifiers":[
        {
            "category":"Professional",
            "subcategory":"Engineering",
            "type":"Services"
        }
    ],
    "sg:phone":"+39 075 856 0181",
    "sg:postcode":"06016",
    "sg:province":"Perugia",
    "sg:tags":[
        "machine",
        "-",
        "mechanical"
    ],
    "wof:name":"Costruzioni Meccaniche Di Fiorucci E. & C. Snc",
    "wof:placetype":"venue"
},
  "geometry": {"coordinates":[12.389172,43.110703],"type":"Point"}
}