{
  "type": "Feature",
  "properties": {
    "iso:country":"IT",
    "sg:address":"71043 Manfredonia",
    "sg:city":"Manfredonia",
    "sg:classifiers":[
        {
            "category":"Bars & Pubs",
            "subcategory":"Champagne Bar",
            "type":"Food & Drink"
        }
    ],
    "sg:phone":"+39 0884 541428",
    "sg:postcode":"71043",
    "sg:province":"Foggia",
    "sg:tags":[
        "caffe'",
        "e"
    ],
    "wof:name":"Lido Aurora Di Salice Patrizia & C. Sas",
    "wof:placetype":"venue"
},
  "geometry": {"coordinates":[15.895949,41.606819],"type":"Point"}
}