{
  "type": "Feature",
  "properties": {
    "iso:country":"IT",
    "sg:address":"10091 Alpignano",
    "sg:city":"Alpignano",
    "sg:orig_category":"Macchine, Impianti Ed Attrezzature Per Industria Alimentare E Bevande",
    "sg:phone":"+39 011 967 5125",
    "sg:postcode":"10091",
    "sg:province":"Torino",
    "sg:website":"http://www.gbsperforate.it",
    "wof:name":"G.b.s. Lamiere Perforate Snc Di A. Bounous & C.",
    "wof:placetype":"venue"
},
  "geometry": {"coordinates":[7.52488,45.094254],"type":"Point"}
}