{
  "type": "Feature",
  "properties": {
    "iso:country":"IT",
    "sg:address":"20128 Milano",
    "sg:city":"Milano",
    "sg:orig_category":"Nautica Equipaggiamenti E Forniture - Vendita Al Dettaglio",
    "sg:phone":"+39 02 259 0531",
    "sg:postcode":"20128",
    "sg:province":"Milano",
    "sg:website":"http://www.marangonimarine.com",
    "wof:name":"Marangoni & C. Snc",
    "wof:placetype":"venue"
},
  "geometry": {"coordinates":[9.234434,45.507458],"type":"Point"}
}