{
  "type": "Feature",
  "properties": {
    "addr:full":"51036 Larciano Larciano Pistoia 51036",
    "addr:postcode":"51036;51036",
    "iso:country":"IT",
    "sg:address":"51036 Larciano",
    "sg:city":"Larciano",
    "sg:orig_category":"Paste Alimentari - Produzione E Ingrosso",
    "sg:phone":"+39 0573 83016",
    "sg:postcode":"51036",
    "sg:province":"Pistoia",
    "sg:website":"http://www.pastificiomonti.zen.it",
    "wof:name":"Pastificio Monti Di Monti Cesare & C. Snc",
    "wof:placetype":"venue"
},
  "geometry": {"coordinates":[10.9172201157,43.869342804],"type":"Point"}
}