{
  "type": "Feature",
  "properties": {
    "iso:country":"IT",
    "sg:address":"2, Madonna Del Pilastro 29010 Gragnano Trebbiense",
    "sg:city":"Gragnano Trebbiense",
    "sg:classifiers":[
        {
            "category":"Food & Beverages",
            "subcategory":"Bakery",
            "type":"Retail Goods"
        }
    ],
    "sg:phone":"+39 0523 787155",
    "sg:postcode":"29010",
    "sg:province":"Piacenza",
    "sg:tags":[
        "grain",
        "cereal"
    ],
    "sg:website":"http://www.dallagiovanna.it",
    "wof:name":"Molino Dallagiovanna Snc",
    "wof:placetype":"venue"
},
  "geometry": {"coordinates":[9.695142,45.053772],"type":"Point"}
}