{
  "type": "Feature",
  "properties": {
    "iso:country":"IT",
    "sg:address":"12, Via Villanuova 25030 Roccafranca",
    "sg:city":"Roccafranca",
    "sg:classifiers":[
        {
            "category":"Food & Beverages",
            "subcategory":"Dairy",
            "type":"Retail Goods"
        }
    ],
    "sg:phone":"+39 030 709 0123",
    "sg:postcode":"25030",
    "sg:province":"Brescia",
    "sg:tags":[
        "product"
    ],
    "wof:name":"Caseificio Campiotti E C. (s.n.c.)",
    "wof:placetype":"venue"
},
  "geometry": {"coordinates":[9.931717,45.446129],"type":"Point"}
}