{
  "type": "Feature",
  "properties": {
    "iso:country":"IT",
    "sg:address":"35141 Padova",
    "sg:city":"Padova",
    "sg:orig_category":"Servizi Ausiliari Di Certificati, Riproduzioni, Disegni E Foto",
    "sg:phone":"+39 049 871 9670",
    "sg:postcode":"35141",
    "sg:province":"Padova",
    "sg:website":"http://www.airdata-it.com",
    "wof:name":"Air Data Srl",
    "wof:placetype":"venue"
},
  "geometry": {"coordinates":[11.115941,45.418343],"type":"Point"}
}