{
  "type": "Feature",
  "properties": {
    "addr:full":"67044 Cerchio L'Aquila 67044",
    "addr:postcode":"67044;67044",
    "iso:country":"IT",
    "sg:address":"67044 Cerchio",
    "sg:orig_category":"Pirotecnica E Fuochi D'artificio",
    "sg:phone":"+39 0863 78511",
    "sg:postcode":"67044",
    "sg:province":"L'Aquila",
    "wof:name":"Amiconi Graziano & Figli",
    "wof:placetype":"venue"
},
  "geometry": {"coordinates":[13.3641147614,42.5579795837],"type":"Point"}
}