{
  "type": "Feature",
  "properties": {
    "addr:full":"Via Eugubina 40 06022 Fossato Di Vico Fossato di Vico Perugia 06022",
    "addr:housenumber":"40",
    "addr:postcode":"06022;06022",
    "addr:street":"Via Eugubina;Vico Fossato Di Vico",
    "iso:country":"IT",
    "sg:address":"Via Eugubina 40 06022 Fossato Di Vico",
    "sg:city":"Fossato di Vico",
    "sg:classifiers":[
        {
            "category":"Social Services",
            "subcategory":"Job Training",
            "type":"Services"
        }
    ],
    "sg:phone":"+39 075 919621",
    "sg:postcode":"06022",
    "sg:province":"Perugia",
    "sg:tags":[
        "pottery"
    ],
    "sg:website":"www.wald.it",
    "wof:name":"Wald Srl",
    "wof:placetype":"venue"
},
  "geometry": {"coordinates":[12.7373991013,43.2873268127],"type":"Point"}
}