{
  "type": "Feature",
  "properties": {
    "addr:full":"22100 Como Como Como 22100",
    "addr:postcode":"22100;22100",
    "iso:country":"IT",
    "sg:address":"22100 Como",
    "sg:city":"Como",
    "sg:orig_category":"Scuole E Servizi Scolastici. Ricerca, Selezione E Formazione Del Personale",
    "sg:phone":"+39 031 575059",
    "sg:postcode":"22100",
    "sg:province":"Como",
    "sg:website":"http://www.nspeak.com",
    "wof:name":"Newspeak International Language School",
    "wof:placetype":"venue"
},
  "geometry": {"coordinates":[9.072428,45.81205],"type":"Point"}
}