{
  "type": "Feature",
  "properties": {
    "iso:country":"IT",
    "sg:address":"98124 Messina",
    "sg:city":"Messina",
    "sg:orig_category":"Prodotti Di Base E Forniture Per Industria Alimentare E Bevande. Forniture Per Attivita' Commerciali Ed Artigianali",
    "sg:phone":"+39 090 293 1064",
    "sg:postcode":"98124",
    "sg:province":"Messina",
    "wof:name":"Famoso Giovanni",
    "wof:placetype":"venue"
},
  "geometry": {"coordinates":[14.6994533539,38.0937614441],"type":"Point"}
}