{
  "type": "Feature",
  "properties": {
    "iso:country":"IT",
    "sg:address":"Via Roma, 37; Arnesano; 73010",
    "sg:city":"Arnesano",
    "sg:classifiers":[
        {
            "category":"Banks & Credit Unions",
            "subcategory":"Bank",
            "type":"Services"
        }
    ],
    "sg:phone":"+39 0832 627106",
    "sg:postcode":"73010",
    "sg:province":"Lecce",
    "wof:name":"Banca Leuzzi & Megha Spa",
    "wof:placetype":"venue"
},
  "geometry": {"coordinates":[18.093496,40.335453],"type":"Point"}
}