{
  "type": "Feature",
  "properties": {
    "addr:full":"Via Mario Cereda 9, 26027 Rivolta D'adda, Cr Cremona 26027",
    "addr:housenumber":"9",
    "addr:postcode":"26027;26027",
    "addr:street":"Via Mario Cereda;D'Adda Cr Cremona",
    "iso:country":"IT",
    "sg:address":"Via Mario Cereda 9, 26027 Rivolta D'adda, Cr",
    "sg:classifiers":[
        {
            "category":"Banks & Credit Unions",
            "subcategory":"Bank",
            "type":"Services"
        }
    ],
    "sg:postcode":"26027",
    "sg:province":"Cremona",
    "wof:name":"Banca Di Credito Cooperativo Di Rivolta D'adda E Agnadello Scrl",
    "wof:placetype":"venue"
},
  "geometry": {"coordinates":[9.512532,45.470161],"type":"Point"}
}