{
  "type": "Feature",
  "properties": {
    "addr:full":"87067 Rossano Rossano Cosenza 87067",
    "addr:postcode":"87067;87067",
    "iso:country":"IT",
    "sg:address":"87067 Rossano",
    "sg:city":"Rossano",
    "sg:orig_category":"Macchine Ed Impianti Per Edilizia E Lavori Pubblici",
    "sg:phone":"+39 0983 569337",
    "sg:postcode":"87067",
    "sg:province":"Cosenza",
    "wof:name":"Movibeton Srl",
    "wof:placetype":"venue"
},
  "geometry": {"coordinates":[16.06237,39.232037],"type":"Point"}
}