{
  "type": "Feature",
  "properties": {
    "iso:country":"IT",
    "sg:address":"50143 Firenze",
    "sg:city":"Firenze",
    "sg:orig_category":"Cartotecnica E Servizi. Forniture Per Attivita' Commerciali Ed Artigianali",
    "sg:phone":"+39 055 701319",
    "sg:postcode":"50143",
    "sg:province":"Firenze",
    "wof:name":"Progetto Campionario",
    "wof:placetype":"venue"
},
  "geometry": {"coordinates":[11.213449,43.769382],"type":"Point"}
}