{
  "type": "Feature",
  "properties": {
    "iso:country":"IT",
    "sg:address":"00152 Roma",
    "sg:city":"Roma",
    "sg:orig_category":"Automazione E Macchine Per Ufficio. Servizi Ausiliari Di Certificati, Riproduzioni, Disegni E Foto",
    "sg:phone":"+39 06 537 0888",
    "sg:postcode":"00152",
    "sg:province":"Roma",
    "wof:name":"Centro Archivi Multimediali Di Pesapane Riccardo",
    "wof:placetype":"venue"
},
  "geometry": {"coordinates":[12.457878,41.871819],"type":"Point"}
}