{
  "type": "Feature",
  "properties": {
    "addr:full":"18/a, Via Dell' Artigianato 26029 Soncino Soncino Cremona 26029",
    "addr:housenumber":"18 / a",
    "addr:postcode":"26029;26029",
    "addr:street":"Via Dell ' Artigianato",
    "iso:country":"IT",
    "sg:address":"18/a, Via Dell' Artigianato 26029 Soncino",
    "sg:city":"Soncino",
    "sg:classifiers":[
        {
            "category":"Utilities",
            "subcategory":"Electric",
            "type":"Services"
        }
    ],
    "sg:phone":"+39 39037483141",
    "sg:postcode":"26029",
    "sg:province":"Cremona",
    "sg:tags":[
        "component",
        "electronic"
    ],
    "wof:name":"Va.re.l S.r.l.",
    "wof:placetype":"venue"
},
  "geometry": {"coordinates":[10.026135,45.133499],"type":"Point"}
}