{
  "type": "Feature",
  "properties": {
    "addr:full":"40068 S. Lazzaro Di Savena Bologna 40068",
    "addr:housenumber":"40068",
    "addr:postcode":"40068",
    "addr:street":"S. Lazzaro Di Savena",
    "iso:country":"IT",
    "sg:address":"40068 S. Lazzaro Di Savena",
    "sg:orig_category":"Utensili Meccanici E Materiali",
    "sg:phone":"+39 051 625 0511",
    "sg:postcode":"40068",
    "sg:province":"Bologna",
    "wof:name":"Nuova Dari Spa",
    "wof:placetype":"venue"
},
  "geometry": {"coordinates":[11.450566,44.476624],"type":"Point"}
}