{
  "type": "Feature",
  "properties": {
    "iso:country":"IT",
    "sg:address":"80039 Saviano",
    "sg:city":"Saviano",
    "sg:orig_category":"Cornici Ed Aste - Produzione E Ingrosso",
    "sg:phone":"+39 081 511 3302",
    "sg:postcode":"80039",
    "sg:province":"Napoli",
    "wof:name":"Del Genio Osvaldo Mario",
    "wof:placetype":"venue"
},
  "geometry": {"coordinates":[14.511625,40.906776],"type":"Point"}
}