{
  "type": "Feature",
  "properties": {
    "addr:full":"21100 Varese Varese Varese 21100",
    "addr:postcode":"21100;21100",
    "iso:country":"IT",
    "sg:address":"21100 Varese",
    "sg:city":"Varese",
    "sg:orig_category":"Macchine, Impianti Ed Attrezzature Per Abbigliamento E Pelletterie",
    "sg:phone":"+39 0332 334188",
    "sg:postcode":"21100",
    "sg:province":"Varese",
    "wof:name":"Ambrosetti S.n.c. Di Ambrosetti E Luisi",
    "wof:placetype":"venue"
},
  "geometry": {"coordinates":[8.791434,45.8904],"type":"Point"}
}