{
  "type": "Feature",
  "properties": {
    "iso:country":"IT",
    "sg:address":"20056 Grezzago",
    "sg:city":"Grezzago",
    "sg:orig_category":"Arti Grafiche",
    "sg:phone":"+39 02 9093 1601",
    "sg:postcode":"20056",
    "sg:province":"Milano",
    "wof:name":"Modulimpianti Snc Di Carla Innocenti",
    "wof:placetype":"venue"
},
  "geometry": {"coordinates":[9.494187,45.590675],"type":"Point"}
}