{
  "type": "Feature",
  "properties": {
    "addr:full":"6, Piazza Della Repubblica 20090 Segrate Segrate Milano 20090",
    "addr:postcode":"20090;20090",
    "addr:street":"Piazza Della Repubblica",
    "iso:country":"IT",
    "sg:address":"6, Piazza Della Repubblica 20090 Segrate",
    "sg:city":"Segrate",
    "sg:classifiers":[
        {
            "category":"Shopping",
            "subcategory":"Clothing, Apparel, & Fashions",
            "type":"Retail Goods"
        }
    ],
    "sg:phone":"+39 39022133494",
    "sg:postcode":"20090",
    "sg:province":"Milano",
    "sg:tags":[
        "clothes"
    ],
    "wof:name":"Talli' Valentino (s.r.l.)",
    "wof:placetype":"venue"
},
  "geometry": {"coordinates":[9.293642,45.492558],"type":"Point"}
}