{
  "type": "Feature",
  "properties": {
    "addr:full":"Via B. Buozzi 12 20090 Pieve Emanuele Pieve Emanuele Milano 20090",
    "addr:housenumber":"12",
    "addr:postcode":"20090;20090",
    "addr:street":"Via B. Buozzi",
    "iso:country":"IT",
    "sg:address":"Via B. Buozzi 12 20090 Pieve Emanuele",
    "sg:city":"Pieve Emanuele",
    "sg:classifiers":[
        {
            "category":"Home & Garden",
            "subcategory":"Carpets & Floor Coverings",
            "type":"Retail Goods"
        }
    ],
    "sg:phone":"+39 02 907441",
    "sg:postcode":"20090",
    "sg:province":"Milano",
    "sg:tags":[
        "aluminium",
        "foil"
    ],
    "sg:website":"www.alcan.com",
    "wof:name":"Alcan Alluminio Spa",
    "wof:placetype":"venue"
},
  "geometry": {"coordinates":[9.180287,45.37991],"type":"Point"}
}