{
  "type": "Feature",
  "properties": {
    "iso:country":"IT",
    "sg:address":"20121 Milano",
    "sg:city":"Milano",
    "sg:orig_category":"Arte Ed Artigianato Artistico",
    "sg:phone":"+39 02 657 2981",
    "sg:postcode":"20121",
    "sg:province":"Milano",
    "wof:name":"Du Pasquier Nathalie",
    "wof:placetype":"venue"
},
  "geometry": {"coordinates":[9.194981,45.472153],"type":"Point"}
}