{
  "type": "Feature",
  "properties": {
    "addr:full":"12042 Bra Bra Cuneo 12042",
    "addr:postcode":"12042;12042",
    "iso:country":"IT",
    "sg:address":"12042 Bra",
    "sg:city":"Bra",
    "sg:orig_category":"Macchine Ed Impianti Per Edilizia E Lavori Pubblici",
    "sg:phone":"+39 0172 412179",
    "sg:postcode":"12042",
    "sg:province":"Cuneo",
    "wof:name":"Ramondetti Giacomo & Claudio S.n.c.",
    "wof:placetype":"venue"
},
  "geometry": {"coordinates":[7.806885,44.714588],"type":"Point"}
}