{
  "type": "Feature",
  "properties": {
    "addr:full":"45/d, V. Piave20070 Castelnuovo Bocca D'adda Milano 20070",
    "addr:housenumber":"45 / d",
    "addr:postcode":"20070",
    "addr:street":"V. Piave20070",
    "iso:country":"IT",
    "sg:address":"45/d, V. Piave20070 Castelnuovo Bocca D'adda",
    "sg:classifiers":[
        {
            "category":"Manufacturing",
            "subcategory":"Rubber & Plastics",
            "type":"Manufacturing & Wholesale Goods"
        }
    ],
    "sg:phone":"+39 39037760918",
    "sg:postcode":"20070",
    "sg:province":"Milano",
    "sg:tags":[
        "packaging",
        "material",
        "-"
    ],
    "sg:website":"http://www.zibrasnc.com:ws_end: :mark:ws:http://www.paginegialle.it/zibra",
    "wof:name":"Zibra Luciano & C. Snc",
    "wof:placetype":"venue"
},
  "geometry": {"coordinates":[9.1881408691,45.4636878967],"type":"Point"}
}