{
  "type": "Feature",
  "properties": {
    "iso:country":"IT",
    "sg:address":"25126 Ponte S. Marco",
    "sg:orig_category":"Abrasivi",
    "sg:phone":"+39 030 963 6400",
    "sg:postcode":"25126",
    "sg:province":"Brescia",
    "wof:name":"Abratec Snc",
    "wof:placetype":"venue"
},
  "geometry": {"coordinates":[10.222958,45.539829],"type":"Point"}
}