{
  "type": "Feature",
  "properties": {
    "iso:country":"IT",
    "sg:address":"40057 Granarolo Dell'emilia - Quarto",
    "sg:orig_category":"Non-classified Establishments",
    "sg:phone":"+39 051 767043",
    "sg:postcode":"40057",
    "sg:province":"Bologna",
    "wof:name":"E 2 Glass Snc",
    "wof:placetype":"venue"
},
  "geometry": {"coordinates":[11.431458,44.566097],"type":"Point"}
}