{
  "type": "Feature",
  "properties": {
    "iso:country":"IT",
    "sg:address":"Corso Canonico Allamano 11 10095 Grugliasco",
    "sg:city":"Grugliasco",
    "sg:classifiers":[
        {
            "category":"Utilities",
            "subcategory":"Natural Gas",
            "type":"Services"
        }
    ],
    "sg:phone":"+39 011 402 2111",
    "sg:postcode":"10095",
    "sg:province":"Torino",
    "sg:tags":[
        "heater",
        "air"
    ],
    "sg:website":"www.joannes.it",
    "wof:name":"Finterm Spa",
    "wof:placetype":"venue"
},
  "geometry": {"coordinates":[7.600964,45.051693],"type":"Point"}
}