{
  "type": "Feature",
  "properties": {
    "addr:full":"2/b, Viale Italia 25126 Brescia Brescia Brescia 25126",
    "addr:housenumber":"2 / b",
    "addr:postcode":"25126;25126",
    "addr:street":"Viale Italia",
    "iso:country":"IT",
    "sg:address":"2/b, Viale Italia 25126 Brescia",
    "sg:city":"Brescia",
    "sg:classifiers":[
        {
            "category":"Wholesale",
            "subcategory":"Drugs",
            "type":"Manufacturing & Wholesale Goods"
        }
    ],
    "sg:phone":"+39 030 281 7711",
    "sg:postcode":"25126",
    "sg:province":"Brescia",
    "sg:tags":[
        "chemical",
        "pharmaceutical"
    ],
    "wof:name":"Cooperativa Esercenti Farmacia S.c.r.r.l.",
    "wof:placetype":"venue"
},
  "geometry": {"coordinates":[10.18075,45.52071],"type":"Point"}
}