{
  "type": "Feature",
  "properties": {
    "iso:country":"IT",
    "sg:address":"Regione Dota 46 14053 Canelli",
    "sg:city":"Canelli",
    "sg:classifiers":[
        {
            "category":"Winery",
            "type":"Food & Drink"
        }
    ],
    "sg:phone":"+39 0141 823404",
    "sg:postcode":"14053",
    "sg:province":"Asti",
    "sg:tags":[
        "equipment",
        "production",
        "sparkling",
        "wine"
    ],
    "sg:website":"www.fimer.it",
    "wof:name":"Fimer Snc",
    "wof:placetype":"venue"
},
  "geometry": {"coordinates":[8.2920131683,44.7227630615],"type":"Point"}
}