{
  "type": "Feature",
  "properties": {
    "iso:country":"IT",
    "sg:address":"20154 Milano",
    "sg:city":"Milano",
    "sg:orig_category":"Antenne Radio-televisione",
    "sg:phone":"+39 02 3310 3460",
    "sg:postcode":"20154",
    "sg:province":"Milano",
    "wof:name":"Elettro Sistemi Srl",
    "wof:placetype":"venue"
},
  "geometry": {"coordinates":[9.168728,45.482395],"type":"Point"}
}