{
  "type": "Feature",
  "properties": {
    "iso:country":"IT",
    "sg:address":"00199 Roma",
    "sg:city":"Roma",
    "sg:orig_category":"Servizi Editoriali. Pubblicita', Marketing E Comunicazione",
    "sg:phone":"+39 06 8535 6329",
    "sg:postcode":"00199",
    "sg:province":"Roma",
    "wof:name":"De Benedetti Bonaiuto Paola Obiettivo Cento Sas",
    "wof:placetype":"venue"
},
  "geometry": {"coordinates":[12.506704,41.927105],"type":"Point"}
}