{
  "type": "Feature",
  "properties": {
    "iso:country":"IT",
    "sg:address":"25025 Manerbio",
    "sg:city":"Manerbio",
    "sg:orig_category":"Ricerca, Selezione E Formazione Del Personale",
    "sg:phone":"+39 030 993 7820",
    "sg:postcode":"25025",
    "sg:province":"Brescia",
    "wof:name":"Umana Spa",
    "wof:placetype":"venue"
},
  "geometry": {"coordinates":[10.137928,45.356518],"type":"Point"}
}