{
  "type": "Feature",
  "properties": {
    "iso:country":"IT",
    "sg:address":"31030 Bessica",
    "sg:orig_category":"Servizi Vari Di Interesse Pubblico",
    "sg:phone":"+39 0423 470848",
    "sg:postcode":"31030",
    "sg:province":"Treviso",
    "wof:name":"Serraggiotto Giuliano",
    "wof:placetype":"venue"
},
  "geometry": {"coordinates":[12.242072,45.666286],"type":"Point"}
}