{
  "type": "Feature",
  "properties": {
    "iso:country":"IT",
    "sg:address":"Via Regio Parco 91 10036 Settimo Torinese",
    "sg:city":"Settimo Torinese",
    "sg:classifiers":[
        {
            "category":"Building & Trades",
            "subcategory":"Equipment Rental",
            "type":"Services"
        }
    ],
    "sg:phone":"+39 011 895 5873",
    "sg:postcode":"10036",
    "sg:province":"Torino",
    "sg:tags":[
        "anchoring"
    ],
    "sg:website":"www.load-lok.com",
    "wof:name":"Load Lok Italia Srl",
    "wof:placetype":"venue"
},
  "geometry": {"coordinates":[7.748915,45.125084],"type":"Point"}
}