{
  "type": "Feature",
  "properties": {
    "addr:full":"91025 Marsala Marsala Trapani 91025",
    "addr:postcode":"91025;91025",
    "iso:country":"IT",
    "sg:address":"91025 Marsala",
    "sg:city":"Marsala",
    "sg:classifiers":[
        {
            "category":"Shopping",
            "subcategory":"Stationery & Office Supplies",
            "type":"Retail Goods"
        }
    ],
    "sg:phone":"+39 0923 723014",
    "sg:postcode":"91025",
    "sg:province":"Trapani",
    "sg:tags":[
        "activities",
        "articles",
        "commercial",
        "packaging",
        "packing",
        "artisan",
        "supplies"
    ],
    "wof:name":"Italpaper Snc",
    "wof:placetype":"venue"
},
  "geometry": {"coordinates":[12.445016861,37.7869033813],"type":"Point"}
}