{
  "type": "Feature",
  "properties": {
    "iso:country":"IT",
    "sg:address":"Via Verdi 7; Milano; 20121",
    "sg:city":"Milano",
    "sg:classifiers":[
        {
            "category":"Banks & Credit Unions",
            "subcategory":"Bank",
            "type":"Services"
        }
    ],
    "sg:phone":"+39 0285871",
    "sg:postcode":"20121",
    "sg:province":"Milano",
    "wof:name":"Credito Milanese",
    "wof:placetype":"venue"
},
  "geometry": {"coordinates":[9.188523,45.468544],"type":"Point"}
}