{
  "type": "Feature",
  "properties": {
    "iso:country":"IT",
    "sg:address":"38100 Trento",
    "sg:city":"Trento",
    "sg:orig_category":"Banche E Servizi Finanziari",
    "sg:phone":"+39 0461 210666",
    "sg:postcode":"38100",
    "sg:province":"Trento",
    "sg:website":"http://www.poptn.it",
    "wof:name":"Banca Popolare Del Trentino",
    "wof:placetype":"venue"
},
  "geometry": {"coordinates":[11.11546,46.093121],"type":"Point"}
}