{
  "type": "Feature",
  "properties": {
    "iso:country":"IT",
    "sg:address":"48010 Cotignola",
    "sg:city":"Cotignola",
    "sg:orig_category":"Depurazione Scarichi Civili E Industriali - Impianti Ed Apparecchi",
    "sg:phone":"+39 0545 41240",
    "sg:postcode":"48010",
    "sg:province":"Ravenna",
    "sg:website":"http://www.fazzini.com",
    "wof:name":"Filtri Fazzini Srl",
    "wof:placetype":"venue"
},
  "geometry": {"coordinates":[11.997156,44.406876],"type":"Point"}
}