{
  "type": "Feature",
  "properties": {
    "addr:full":"61, Via Teodosio 20131 Milano Milano Milano 20131",
    "addr:postcode":"20131;20131",
    "addr:street":"Via Teodosio",
    "iso:country":"IT",
    "sg:address":"61, Via Teodosio 20131 Milano",
    "sg:city":"Milano",
    "sg:classifiers":[
        {
            "category":"Professional",
            "subcategory":"Engineering",
            "type":"Services"
        }
    ],
    "sg:phone":"+39 02 2611 0122",
    "sg:postcode":"20131",
    "sg:province":"Milano",
    "sg:tags":[
        "machine",
        "-",
        "mechanical"
    ],
    "wof:name":"Mire (s.r.l.)",
    "wof:placetype":"venue"
},
  "geometry": {"coordinates":[9.229874,45.486809],"type":"Point"}
}