{
  "type": "Feature",
  "properties": {
    "addr:full":"28/a, Str. Martinella 43100 Parma Parma Parma 43100",
    "addr:housenumber":"28 / a",
    "addr:postcode":"43100;43100",
    "addr:street":"Str. Martinella",
    "iso:country":"IT",
    "sg:address":"28/a, Str. Martinella 43100 Parma",
    "sg:city":"Parma",
    "sg:classifiers":[
        {
            "category":"Professional",
            "subcategory":"Engineering",
            "type":"Services"
        }
    ],
    "sg:phone":"+39 0521 266211",
    "sg:postcode":"43100",
    "sg:province":"Parma",
    "sg:tags":[
        "machine",
        "-",
        "mechanical"
    ],
    "sg:website":"http://www.motorscan.com",
    "wof:name":"Motorscan Spa",
    "wof:placetype":"venue"
},
  "geometry": {"coordinates":[10.329035,44.763836],"type":"Point"}
}