{
  "type": "Feature",
  "properties": {
    "iso:country":"IT",
    "sg:address":"20146 Milano",
    "sg:city":"Milano",
    "sg:orig_category":"Servizi Per Aziende, Manifestazioni E Supporto Agli Scambi Commerciali",
    "sg:phone":"+39 02 4779 1401",
    "sg:postcode":"20146",
    "sg:province":"Milano",
    "wof:name":"Honegger Gaspare S.r.l.",
    "wof:placetype":"venue"
},
  "geometry": {"coordinates":[9.143507,45.453434],"type":"Point"}
}