{
  "type": "Feature",
  "properties": {
    "addr:full":"296, Frazione Pratrivero 13835 Trivero Pratrivero Biella 13835",
    "addr:postcode":"13835;13835",
    "addr:street":"Frazione Pratrivero;Pratrivero",
    "iso:country":"IT",
    "sg:address":"296, Frazione Pratrivero 13835 Trivero",
    "sg:city":"Pratrivero",
    "sg:classifiers":[
        {
            "category":"Shopping",
            "subcategory":"Crafts & Fabrics",
            "type":"Retail Goods"
        }
    ],
    "sg:phone":"+39 015 738 8855",
    "sg:postcode":"13835",
    "sg:province":"Biella",
    "wof:name":"Vitale Barberis Canonico S.p.a.",
    "wof:placetype":"venue"
},
  "geometry": {"coordinates":[8.1820430756,45.6635704041],"type":"Point"}
}