{
  "type": "Feature",
  "properties": {
    "iso:country":"IT",
    "sg:address":"00100 Roma",
    "sg:orig_category":"Ricambi E Componenti Dei Mezzi Di Trasporto. Riparazione Dei Mezzi Di Trasporto",
    "sg:phone":"+39 06 4120 5591",
    "sg:province":"RM",
    "wof:name":"Futurgas Roma Srl",
    "wof:placetype":"venue"
},
  "geometry": {"coordinates":[12.900314,42.051109],"type":"Point"}
}