{
  "type": "Feature",
  "properties": {
    "addr:full":"30035 Mirano Mirano Venezia 30035",
    "addr:postcode":"30035;30035",
    "iso:country":"IT",
    "sg:address":"30035 Mirano",
    "sg:city":"Mirano",
    "sg:orig_category":"Prodotti Chimici Secondari. Servizi E Lavori Per Ecologia E Smaltimento Rifiuti. Macchine E Forniture Per Ecologia E Smaltimento Rifiuti",
    "sg:phone":"+39 041 570 2830",
    "sg:postcode":"30035",
    "sg:province":"Venezia",
    "wof:name":"System Di Gasparini Gino E C. S.a.s.",
    "wof:placetype":"venue"
},
  "geometry": {"coordinates":[12.1732664108,45.5210266113],"type":"Point"}
}