{
  "type": "Feature",
  "properties": {
    "addr:full":"00051 Allumiere Allumiere Roma 00051",
    "addr:postcode":"00051;roma 00051",
    "iso:country":"IT",
    "sg:address":"00051 Allumiere",
    "sg:city":"Allumiere",
    "sg:orig_category":"Ospedali E Servizi Sanitari",
    "sg:phone":"+39 0766 96057",
    "sg:postcode":"00051",
    "sg:province":"Roma",
    "wof:name":"Fiorelli Maria",
    "wof:placetype":"venue"
},
  "geometry": {"coordinates":[12.498557,41.908802],"type":"Point"}
}