{
  "type": "Feature",
  "properties": {
    "addr:full":"29100 Piacenza Piacenza Piacenza 29100",
    "addr:postcode":"29100;29100",
    "iso:country":"IT",
    "sg:address":"29100 Piacenza",
    "sg:city":"Piacenza",
    "sg:orig_category":"Impiantistica E Prodotti Tecnologici Per Edilizia. Elettronica Professionale E Di Consumo",
    "sg:phone":"+39 0523 458664",
    "sg:postcode":"29100",
    "sg:province":"Piacenza",
    "wof:name":"Colombi Pietro",
    "wof:placetype":"venue"
},
  "geometry": {"coordinates":[9.668804,45.045284],"type":"Point"}
}