{
  "type": "Feature",
  "properties": {
    "iso:country":"IT",
    "sg:address":"26861 Fombio",
    "sg:city":"Fombio",
    "sg:orig_category":"Autoveicoli Industriali",
    "sg:phone":"+39 0377 451137",
    "sg:postcode":"26861",
    "sg:province":"Lodi",
    "wof:name":"Sara C.m. Srl",
    "wof:placetype":"venue"
},
  "geometry": {"coordinates":[9.685147,45.134068],"type":"Point"}
}