{
  "type": "Feature",
  "properties": {
    "iso:country":"IT",
    "sg:address":"25125 Brescia",
    "sg:city":"Brescia",
    "sg:orig_category":"Tessuti Arredamento, Tende E Tappeti. Forniture Per Edilizia E Lavori Pubblici",
    "sg:phone":"+39 030 353 2900",
    "sg:postcode":"25125",
    "sg:province":"Brescia",
    "sg:website":"http://www.calestani.it",
    "wof:name":"Calestani Luigi & C. Snc",
    "wof:placetype":"venue"
},
  "geometry": {"coordinates":[10.196167,45.521873],"type":"Point"}
}