{
  "type": "Feature",
  "properties": {
    "iso:country":"IT",
    "sg:address":"30020 Gruaro",
    "sg:city":"Gruaro",
    "sg:orig_category":"Trasporti E Spedizioni Merci",
    "sg:phone":"+39 0421 760252",
    "sg:postcode":"30020",
    "sg:province":"Venezia",
    "wof:name":"Bartolini Spa",
    "wof:placetype":"venue"
},
  "geometry": {"coordinates":[12.813131,45.797035],"type":"Point"}
}