{
  "type": "Feature",
  "properties": {
    "iso:country":"IT",
    "sg:address":"16134 Genova",
    "sg:city":"Genova",
    "sg:orig_category":"Apparecchi, Attrezzature E Forniture Per Centri Estetici",
    "sg:phone":"+39 010 242 5681",
    "sg:postcode":"16134",
    "sg:province":"Genova",
    "wof:name":"Cibrario Sent Fabio",
    "wof:placetype":"venue"
},
  "geometry": {"coordinates":[8.921477,44.425423],"type":"Point"}
}