{
  "type": "Feature",
  "properties": {
    "iso:country":"IT",
    "sg:address":"54100 Massa",
    "sg:city":"Massa",
    "sg:orig_category":"Petroli, Gas E Combustibili. Servizi E Lavori Industria Chimica",
    "sg:phone":"+39 0585 799311",
    "sg:postcode":"54100",
    "sg:province":"Massa-Carrara",
    "wof:name":"I.g.l.o.m. Italia S.p.a.",
    "wof:placetype":"venue"
},
  "geometry": {"coordinates":[10.1039533615,44.0308685303],"type":"Point"}
}