{
  "type": "Feature",
  "properties": {
    "addr:full":"09170 Oristano Oristano Oristano 09170",
    "addr:postcode":"09170;09170",
    "iso:country":"IT",
    "sg:address":"09170 Oristano",
    "sg:city":"Oristano",
    "sg:orig_category":"Informatica - Consulenza E Software",
    "sg:phone":"+39 0389 274 3328",
    "sg:postcode":"09170",
    "sg:province":"Oristano",
    "sg:website":"http://www.gandgstudio.it",
    "wof:name":"G&g Di Martis Gabriele",
    "wof:placetype":"venue"
},
  "geometry": {"coordinates":[8.584811,39.903931],"type":"Point"}
}