{
  "type": "Feature",
  "properties": {
    "iso:country":"IT",
    "sg:address":"20148 Milano",
    "sg:city":"Milano",
    "sg:orig_category":"Servizi Vari Di Interesse Pubblico",
    "sg:phone":"+39 02 404 1365",
    "sg:postcode":"20148",
    "sg:province":"Milano",
    "wof:name":"Donzi' Francesca",
    "wof:placetype":"venue"
},
  "geometry": {"coordinates":[9.131583,45.470612],"type":"Point"}
}