{
  "type": "Feature",
  "properties": {
    "iso:country":"IT",
    "sg:address":"Via Tommasicchio 1 43013 Langhirano",
    "sg:city":"Langhirano",
    "sg:classifiers":[
        {
            "category":"Wholesale",
            "subcategory":"Plants",
            "type":"Manufacturing & Wholesale Goods"
        }
    ],
    "sg:phone":"+39 0521 858045",
    "sg:postcode":"43013",
    "sg:province":"Parma",
    "sg:tags":[
        "cooling",
        "industrial"
    ],
    "sg:website":"www.cesarerivara.it",
    "wof:name":"Cesare Rivara Srl",
    "wof:placetype":"venue"
},
  "geometry": {"coordinates":[10.329548,44.807865],"type":"Point"}
}