{
  "type": "Feature",
  "properties": {
    "iso:country":"IT",
    "sg:address":"50023 Impruneta",
    "sg:city":"Impruneta",
    "sg:orig_category":"Prodotti Chimici Di Base. Ospedali E Servizi Sanitari",
    "sg:phone":"+39 055 237 3718",
    "sg:postcode":"50023",
    "sg:province":"Firenze",
    "wof:name":"Messer Italia S.p.a",
    "wof:placetype":"venue"
},
  "geometry": {"coordinates":[11.2234992981,43.7273101807],"type":"Point"}
}