{
  "type": "Feature",
  "properties": {
    "addr:full":"Via A Guerrini 14, 48100 Ravenna, Ra Ravenna Ravenna 48100",
    "addr:housenumber":"14",
    "addr:postcode":"48100;48100",
    "addr:street":"Via A Guerrini",
    "iso:country":"IT",
    "sg:address":"Via A Guerrini 14, 48100 Ravenna, Ra",
    "sg:city":"Ravenna",
    "sg:classifiers":[
        {
            "category":"Banks & Credit Unions",
            "subcategory":"Bank",
            "type":"Services"
        }
    ],
    "sg:phone":"+39 0544 540111",
    "sg:postcode":"48100",
    "sg:province":"Ravenna",
    "sg:website":"http://www.bpr.it",
    "wof:name":"Banca Popolare Di Ravenna Spa",
    "wof:placetype":"venue"
},
  "geometry": {"coordinates":[12.225,44.363888],"type":"Point"}
}