{
  "type": "Feature",
  "properties": {
    "iso:country":"IT",
    "sg:address":"Messina; 98100",
    "sg:classifiers":[
        {
            "category":"Shopping",
            "subcategory":"Computers & Home Electronics",
            "type":"Retail Goods"
        }
    ],
    "sg:phone":"+39 39090777211",
    "sg:tags":[
        "chamber",
        "commerce"
    ],
    "wof:name":"Messina Chamber Of Commerce And Industry",
    "wof:placetype":"venue"
},
  "geometry": {"coordinates":[15.494688,38.197247],"type":"Point"}
}