{
  "type": "Feature",
  "properties": {
    "iso:country":"IT",
    "sg:address":"36040 Brendola",
    "sg:city":"Brendola",
    "sg:orig_category":"Prodotti E Manufatti In Materie Plastiche",
    "sg:phone":"+39 0444 400773",
    "sg:postcode":"36040",
    "sg:province":"Vicenza",
    "sg:website":"http://www.resimix.com",
    "wof:name":"Resimix Srl",
    "wof:placetype":"venue"
},
  "geometry": {"coordinates":[11.5396566391,45.5532684326],"type":"Point"}
}