{
  "type": "Feature",
  "properties": {
    "addr:full":"10023 Chieri Chieri Torino 10023",
    "addr:postcode":"10023;10023",
    "iso:country":"IT",
    "sg:address":"10023 Chieri",
    "sg:city":"Chieri",
    "sg:orig_category":"Ospedali E Servizi Sanitari. Pubblica Amministrazione. Servizi Sociali",
    "sg:phone":"+39 011 94291",
    "sg:postcode":"10023",
    "sg:province":"Torino",
    "sg:website":"http://www.regione.piemonte.it/sanita/usl/asl08/index08.htm",
    "wof:name":"Azienda Asl N. 8",
    "wof:placetype":"venue"
},
  "geometry": {"coordinates":[7.772956,45.042301],"type":"Point"}
}