{
  "type": "Feature",
  "properties": {
    "addr:full":"20017 Passirana Passirana Milano 20017",
    "addr:postcode":"20017;20017",
    "addr:street":"Passirana",
    "iso:country":"IT",
    "sg:address":"20017 Passirana",
    "sg:city":"Passirana",
    "sg:orig_category":"Prodotti Chimici Secondari",
    "sg:phone":"+39 02 9350 1943",
    "sg:postcode":"20017",
    "sg:province":"Milano",
    "wof:name":"Chimeko Srl Trade Chimico - Ecologico",
    "wof:placetype":"venue"
},
  "geometry": {"coordinates":[9.0720338821,45.5491828918],"type":"Point"}
}