{
  "type": "Feature",
  "properties": {
    "iso:country":"IT",
    "sg:address":"Via Cesare Battisti, 9; Verona; 37121",
    "sg:city":"Verona",
    "sg:classifiers":[
        {
            "category":"Banks & Credit Unions",
            "subcategory":"Bank",
            "type":"Services"
        }
    ],
    "sg:phone":"+39 045 597622",
    "sg:postcode":"37121",
    "sg:province":"Verona",
    "wof:name":"Banca Agricola Popolare Di Cerea",
    "wof:placetype":"venue"
},
  "geometry": {"coordinates":[10.990856,45.434757],"type":"Point"}
}