{
  "type": "Feature",
  "properties": {
    "addr:full":"50063 Figline Valdarno Figline Valdarno Firenze 50063",
    "addr:postcode":"50063;50063",
    "addr:street":"Valdarno",
    "iso:country":"IT",
    "sg:address":"50063 Figline Valdarno",
    "sg:city":"Figline Valdarno",
    "sg:orig_category":"Macchine, Impianti Ed Attrezzature Industria Chimica",
    "sg:phone":"+39 055 954 4468",
    "sg:postcode":"50063",
    "sg:province":"Firenze",
    "wof:name":"Bureau Maghraby Italia (s.r.l.)",
    "wof:placetype":"venue"
},
  "geometry": {"coordinates":[11.411205,43.619465],"type":"Point"}
}