{
  "type": "Feature",
  "properties": {
    "iso:country":"IT",
    "sg:address":"20051 Limbiate",
    "sg:city":"Limbiate",
    "sg:orig_category":"Macchine Utensili E Impianti",
    "sg:phone":"+39 02 9905 1431",
    "sg:postcode":"20051",
    "sg:province":"Milano",
    "wof:name":"Cavenaghi & Ridolfi (s.p.a.)",
    "wof:placetype":"venue"
},
  "geometry": {"coordinates":[9.1455574036,45.5943069458],"type":"Point"}
}