{
  "type": "Feature",
  "properties": {
    "addr:full":"Via I Maggio 23 37069 Villafranca Di Verona Villafranca di Verona Verona 37069",
    "addr:housenumber":"23",
    "addr:postcode":"37069;37069",
    "addr:street":"Via I Maggio;Verona",
    "iso:country":"IT",
    "sg:address":"Via I Maggio 23 37069 Villafranca Di Verona",
    "sg:city":"Villafranca di Verona",
    "sg:orig_category":"Stone Rubbing And Polishing Machines",
    "sg:phone":"+39 045 790 0322",
    "sg:postcode":"37069",
    "sg:province":"Verona",
    "sg:website":"www.montresor.net",
    "wof:name":"Montresor & C. Srl",
    "wof:placetype":"venue"
},
  "geometry": {"coordinates":[10.886717,45.35104],"type":"Point"}
}