{
  "type": "Feature",
  "properties": {
    "addr:full":"9, Via Di Nanni Dante 97019 Vittoria Vittoria Ragusa 97019",
    "addr:postcode":"97019;97019",
    "addr:street":"Via Di Nanni Dante",
    "iso:country":"IT",
    "sg:address":"9, Via Di Nanni Dante 97019 Vittoria",
    "sg:city":"Vittoria",
    "sg:classifiers":[
        {
            "category":"Farming",
            "subcategory":"Livestock Farm",
            "type":"Manufacturing & Wholesale Goods"
        }
    ],
    "sg:phone":"+39 0932 865147",
    "sg:postcode":"97019",
    "sg:province":"Ragusa",
    "sg:tags":[
        "agriculture"
    ],
    "wof:name":"Eurosicil (s.r.l.)",
    "wof:placetype":"venue"
},
  "geometry": {"coordinates":[14.51892,36.933437],"type":"Point"}
}