{
  "type": "Feature",
  "properties": {
    "iso:country":"IT",
    "sg:address":"36010 Velo D'astico",
    "sg:city":"Seghe",
    "sg:orig_category":"Prodotti E Manufatti In Materie Plastiche",
    "sg:phone":"+39 0445 742166",
    "sg:postcode":"36010",
    "sg:province":"Vicenza",
    "wof:name":"G.m. Di Medici Paolo",
    "wof:placetype":"venue"
},
  "geometry": {"coordinates":[11.3846387863,45.7949981689],"type":"Point"}
}