{
  "type": "Feature",
  "properties": {
    "addr:full":"36077 Altavilla Vicentina Altavilla Vicentina Vicenza 36077",
    "addr:postcode":"36077;36077",
    "iso:country":"IT",
    "sg:address":"36077 Altavilla Vicentina",
    "sg:city":"Altavilla Vicentina",
    "sg:orig_category":"Agenzie Viaggi E Turismo",
    "sg:phone":"+39 348 490 4746",
    "sg:postcode":"36077",
    "sg:province":"Vicenza",
    "sg:website":"http://www.guardaunion.com",
    "wof:name":"Magic Bus Srl",
    "wof:placetype":"venue"
},
  "geometry": {"coordinates":[11.457933,45.511726],"type":"Point"}
}