{
  "type": "Feature",
  "properties": {
    "iso:country":"IT",
    "sg:address":"6, Via Guido Da Como 22100 Como",
    "sg:city":"Como",
    "sg:classifiers":[
        {
            "category":"Parking",
            "subcategory":"Lot",
            "type":"Transportation"
        }
    ],
    "sg:phone":"+39 031 338 8711",
    "sg:postcode":"22100",
    "sg:province":"Como",
    "sg:tags":[
        "transport",
        "road"
    ],
    "wof:name":"Avioservizi Spa",
    "wof:placetype":"venue"
},
  "geometry": {"coordinates":[9.067506,45.784668],"type":"Point"}
}