{
  "type": "Feature",
  "properties": {
    "iso:country":"IT",
    "sg:address":"33050 Gonars",
    "sg:city":"Gonars",
    "sg:orig_category":"Cartotecnica E Servizi. Forniture Per Attivita' Commerciali Ed Artigianali",
    "sg:phone":"+39 0432 992298",
    "sg:postcode":"33050",
    "sg:province":"Udine",
    "wof:name":"Didue",
    "wof:placetype":"venue"
},
  "geometry": {"coordinates":[13.23813,45.896889],"type":"Point"}
}