{
  "type": "Feature",
  "properties": {
    "iso:country":"IT",
    "sg:address":"54, Via Maccalone 48100 Ravenna",
    "sg:city":"Ravenna",
    "sg:classifiers":[
        {
            "category":"Manufacturing",
            "subcategory":"Lumber",
            "type":"Manufacturing & Wholesale Goods"
        }
    ],
    "sg:phone":"+39 39054434675",
    "sg:postcode":"48100",
    "sg:province":"Ravenna",
    "sg:tags":[
        "wood"
    ],
    "wof:name":"Rafal S.p.a.",
    "wof:placetype":"venue"
},
  "geometry": {"coordinates":[12.225,44.363888],"type":"Point"}
}