{
  "type": "Feature",
  "properties": {
    "iso:country":"IT",
    "sg:address":"10, Stradello Romano 41100 Modena",
    "sg:city":"Modena",
    "sg:classifiers":[
        {
            "category":"Professional",
            "subcategory":"Business Services",
            "type":"Services"
        }
    ],
    "sg:phone":"+39 059 286 2211",
    "sg:postcode":"41100",
    "sg:province":"Modena",
    "sg:tags":[
        "advice"
    ],
    "wof:name":"Agenzia D'informazione Aziendale Spa",
    "wof:placetype":"venue"
},
  "geometry": {"coordinates":[10.977831,44.626057],"type":"Point"}
}