{
  "type": "Feature",
  "properties": {
    "iso:country":"IT",
    "sg:address":"Via Sacco E Vanzetti 54 41042 Fiorano Modenese",
    "sg:city":"Fiorano Modenese",
    "sg:orig_category":"Adhesives, Non-combustible",
    "sg:phone":"+39 0536 837111",
    "sg:postcode":"41042",
    "sg:province":"Modena",
    "sg:website":"www.weber-broutin.it",
    "wof:name":"Saint-gobain Weber Spa",
    "wof:placetype":"venue"
},
  "geometry": {"coordinates":[10.820282,44.557816],"type":"Point"}
}