{
  "type": "Feature",
  "properties": {
    "iso:country":"IT",
    "sg:address":"07031 Castelsardo",
    "sg:city":"Castelsardo",
    "sg:orig_category":"Gioielleria, Oreficeria E Argenteria. Shopping",
    "sg:phone":"+39 079 470366",
    "sg:postcode":"07031",
    "sg:province":"Sassari",
    "wof:name":"Sardartis (s.r.l.)",
    "wof:placetype":"venue"
},
  "geometry": {"coordinates":[8.831537,40.847298],"type":"Point"}
}