{
  "type": "Feature",
  "properties": {
    "iso:country":"IT",
    "sg:address":"Piazza Garibaldi 12; Lecco; 22053",
    "sg:classifiers":[
        {
            "category":"Banks & Credit Unions",
            "subcategory":"Bank",
            "type":"Services"
        }
    ],
    "sg:phone":"+39 0341 480111",
    "wof:name":"Banca Popolare Di Lecco",
    "wof:placetype":"venue"
},
  "geometry": {"coordinates":[9.414782,45.801407],"type":"Point"}
}