{
  "type": "Feature",
  "properties": {
    "iso:country":"IT",
    "sg:address":"56035 Lari",
    "sg:city":"Lari",
    "sg:orig_category":"Salotti, Poltrone, Sedie E Tavoli",
    "sg:phone":"+39 0587 616500",
    "sg:postcode":"56035",
    "sg:province":"Pisa",
    "wof:name":"B.m. Style Srl - Mobilificio",
    "wof:placetype":"venue"
},
  "geometry": {"coordinates":[10.593193,43.633362],"type":"Point"}
}