{
  "type": "Feature",
  "properties": {
    "addr:full":"25020 Seniga Seniga Brescia 25020",
    "addr:postcode":"25020;25020",
    "iso:country":"IT",
    "sg:address":"25020 Seniga",
    "sg:city":"Seniga",
    "sg:orig_category":"Trattamenti Termici E Superficiali Metalli, Galvanotecnica",
    "sg:phone":"+39 030 995 5563",
    "sg:postcode":"25020",
    "sg:province":"Brescia",
    "wof:name":"Gatti Ivan",
    "wof:placetype":"venue"
},
  "geometry": {"coordinates":[10.194525,45.555374],"type":"Point"}
}