{
  "type": "Feature",
  "properties": {
    "iso:country":"IT",
    "sg:address":"30100 Venezia",
    "sg:orig_category":"Prodotti Alimentari. Servizi E Lavori Per Industria Alimentare E Bevande",
    "sg:phone":"+39 041 538 4233",
    "sg:province":"VE",
    "wof:name":"Arte Bianca Srl",
    "wof:placetype":"venue"
},
  "geometry": {"coordinates":[12.2147531509,45.4604263306],"type":"Point"}
}