{
  "type": "Feature",
  "properties": {
    "iso:country":"IT",
    "sg:address":"21040 Gerenzano",
    "sg:city":"Gerenzano",
    "sg:orig_category":"Abbigliamento Esterno, Maglierie E Pelliccerie. Shopping",
    "sg:phone":"+39 02 968 8239",
    "sg:postcode":"21040",
    "sg:province":"Varese",
    "wof:name":"Busatto Franco",
    "wof:placetype":"venue"
},
  "geometry": {"coordinates":[8.999471,45.638485],"type":"Point"}
}