{
  "type": "Feature",
  "properties": {
    "iso:country":"IT",
    "sg:address":"25010 Visano",
    "sg:city":"Remedello",
    "sg:orig_category":"Acciaierie E Fonderie",
    "sg:phone":"+39 030 952 9018",
    "sg:postcode":"25010",
    "sg:province":"Brescia",
    "wof:name":"Lumezzane Acciai S.r.l.",
    "wof:placetype":"venue"
},
  "geometry": {"coordinates":[10.419106,45.313747],"type":"Point"}
}