{
  "type": "Feature",
  "properties": {
    "iso:country":"IT",
    "sg:address":"Piazza Cavour; Lenola",
    "sg:classifiers":[
        {
            "category":"Banks & Credit Unions",
            "subcategory":"Bank",
            "type":"Services"
        }
    ],
    "sg:phone":"+39 0771 58020",
    "wof:name":"Banca Popolare Di Fondi",
    "wof:placetype":"venue"
},
  "geometry": {"coordinates":[13.461258,41.409019],"type":"Point"}
}