{
  "type": "Feature",
  "properties": {
    "iso:country":"IT",
    "sg:address":"20048 Carate Brianza",
    "sg:city":"Carate Brianza",
    "sg:orig_category":"Elettronica Industriale, Prodotti E Apparecchiature",
    "sg:phone":"+39 036 291641",
    "sg:postcode":"20048",
    "sg:province":"Milano",
    "sg:website":"http://www.tecnodal.it",
    "wof:name":"Tecnodal Snc",
    "wof:placetype":"venue"
},
  "geometry": {"coordinates":[9.231445,45.671169],"type":"Point"}
}