{
  "type": "Feature",
  "properties": {
    "iso:country":"IT",
    "sg:address":"95129 Catania",
    "sg:city":"Catania",
    "sg:classifiers":[
        {
            "category":"Health Services",
            "subcategory":"Health Practitioner",
            "type":"Services"
        }
    ],
    "sg:phone":"+39 095 446959",
    "sg:postcode":"95129",
    "sg:province":"Catania",
    "sg:tags":[
        "medici"
    ],
    "wof:name":"Studio Di Neuropsichiatria E Psicologia Della Condotta",
    "wof:placetype":"venue"
},
  "geometry": {"coordinates":[15.1010456085,37.5121307373],"type":"Point"}
}