{
  "type": "Feature",
  "properties": {
    "iso:country":"IT",
    "sg:address":"25085 Gavardo",
    "sg:city":"Gavardo",
    "sg:orig_category":"Lavorazioni Metalli, Stampaggio E Saldatura",
    "sg:phone":"+39 036 532525",
    "sg:postcode":"25085",
    "sg:province":"Brescia",
    "wof:name":"Chiodi Alfredo",
    "wof:placetype":"venue"
},
  "geometry": {"coordinates":[10.43902,45.570614],"type":"Point"}
}