{
  "type": "Feature",
  "properties": {
    "addr:full":"20146 Milano Milano Milano 20146",
    "addr:postcode":"20146;20146",
    "iso:country":"IT",
    "sg:address":"20146 Milano",
    "sg:city":"Milano",
    "sg:orig_category":"Abiti Da Lavoro Ed Indumenti Protettivi",
    "sg:phone":"+39 02 4895 1173",
    "sg:postcode":"20146",
    "sg:province":"Milano",
    "wof:name":"Manifattura Fraizzoli & C. Srl",
    "wof:placetype":"venue"
},
  "geometry": {"coordinates":[9.143517,45.44762],"type":"Point"}
}