{
  "type": "Feature",
  "properties": {
    "iso:country":"IT",
    "sg:address":"6, Via Ambrosoli 20090 Rodano",
    "sg:city":"Rodano",
    "sg:classifiers":[
        {
            "category":"Wholesale",
            "subcategory":"Medical Equipment & Supplies",
            "type":"Manufacturing & Wholesale Goods"
        }
    ],
    "sg:phone":"+39 390 295 0541",
    "sg:postcode":"20090",
    "sg:province":"Milano",
    "sg:tags":[
        "-",
        "health",
        "instrument"
    ],
    "wof:name":"Hill - Rom S.p.a.",
    "wof:placetype":"venue"
},
  "geometry": {"coordinates":[9.338659,45.472107],"type":"Point"}
}