{
  "type": "Feature",
  "properties": {
    "iso:country":"IT",
    "sg:address":"70020 Bitritto",
    "sg:city":"Bitritto",
    "sg:orig_category":"Prodotti Alimentari",
    "sg:phone":"+39 080 634750",
    "sg:postcode":"70020",
    "sg:province":"Bari",
    "wof:name":"Valerio Francesco",
    "wof:placetype":"venue"
},
  "geometry": {"coordinates":[16.8287582397,41.0453720093],"type":"Point"}
}