{
  "type": "Feature",
  "properties": {
    "iso:country":"IT",
    "sg:address":"20010 Bareggio",
    "sg:city":"Bareggio",
    "sg:orig_category":"Forniture E Materiali Per Imballaggio E Confezionamento. Forniture Per Uffici. Forniture Per Attivita' Commerciali Ed Artigianali",
    "sg:phone":"+39 02 901 4801",
    "sg:postcode":"20010",
    "sg:province":"Milano",
    "wof:name":"Crc Adesivi",
    "wof:placetype":"venue"
},
  "geometry": {"coordinates":[9.0047264099,45.4856948853],"type":"Point"}
}