{
  "type": "Feature",
  "properties": {
    "addr:full":"70123 Bari Bari Bari 70123",
    "addr:postcode":"70123;70123",
    "iso:country":"IT",
    "sg:address":"70123 Bari",
    "sg:city":"Bari",
    "sg:orig_category":"Valvole E Apparecchiature Di Misura",
    "sg:phone":"+39 080 534 2111",
    "sg:postcode":"70123",
    "sg:province":"Bari",
    "wof:name":"Gasmarkenting (s.r.l.)",
    "wof:placetype":"venue"
},
  "geometry": {"coordinates":[16.873077,41.11805],"type":"Point"}
}