{
  "type": "Feature",
  "properties": {
    "addr:full":"125, Via Comasina 20050 Verano Brianza Verano Brianza Milano 20050",
    "addr:housenumber":"125",
    "addr:postcode":"20050;20050",
    "addr:street":"Via Comasina",
    "iso:country":"IT",
    "sg:address":"125, Via Comasina 20050 Verano Brianza",
    "sg:city":"Verano Brianza",
    "sg:classifiers":[
        {
            "category":"Professional",
            "subcategory":"Engineering",
            "type":"Services"
        }
    ],
    "sg:phone":"+39 036 290 1347",
    "sg:postcode":"20050",
    "sg:province":"Milano",
    "sg:tags":[
        "machine",
        "-",
        "mechanical"
    ],
    "wof:name":"Borgonovo",
    "wof:placetype":"venue"
},
  "geometry": {"coordinates":[9.212132,45.675335],"type":"Point"}
}