{
  "type": "Feature",
  "properties": {
    "iso:country":"IT",
    "sg:address":"34148 Trieste",
    "sg:city":"Trieste",
    "sg:orig_category":"Elettrotecnica Industriale, Prodotti E Apparecchiature. Ricambi E Componenti Dei Mezzi Di Trasporto",
    "sg:phone":"+39 040 281221",
    "sg:postcode":"34148",
    "sg:province":"Trieste",
    "wof:name":"La Nuova Energia S.a.s.",
    "wof:placetype":"venue"
},
  "geometry": {"coordinates":[13.829002,45.618706],"type":"Point"}
}