{
  "type": "Feature",
  "properties": {
    "iso:country":"IT",
    "sg:address":"70026 Modugno",
    "sg:city":"Modugno",
    "sg:orig_category":"Fisiokinesiterapia",
    "sg:phone":"+39 080 535 4914",
    "sg:postcode":"70026",
    "sg:province":"Bari",
    "wof:name":"Fisio Salus Srl",
    "wof:placetype":"venue"
},
  "geometry": {"coordinates":[16.7889518738,41.0876617432],"type":"Point"}
}