{
  "type": "Feature",
  "properties": {
    "iso:country":"IT",
    "sg:address":"20132 Milano",
    "sg:city":"Milano",
    "sg:orig_category":"Carte Plastiche, Magnetiche E Smart - Badges",
    "sg:phone":"+39 02 289 2976",
    "sg:postcode":"20132",
    "sg:province":"Milano",
    "wof:name":"Prisma Informatica Srl",
    "wof:placetype":"venue"
},
  "geometry": {"coordinates":[9.229655,45.494225],"type":"Point"}
}