{
  "type": "Feature",
  "properties": {
    "addr:full":"Via Boldrini 11; Bologna; 40121 Bologna Bologna 40121",
    "addr:housenumber":"11",
    "addr:postcode":"40121;40121",
    "addr:street":"Via Boldrini",
    "iso:country":"IT",
    "sg:address":"Via Boldrini 11; Bologna; 40121",
    "sg:city":"Bologna",
    "sg:classifiers":[
        {
            "category":"Banks & Credit Unions",
            "subcategory":"Bank",
            "type":"Services"
        }
    ],
    "sg:phone":"+39 051 255994",
    "sg:postcode":"40121",
    "sg:province":"Bologna",
    "wof:name":"Banco San Giminiano & San Prospero",
    "wof:placetype":"venue"
},
  "geometry": {"coordinates":[11.339597,44.504765],"type":"Point"}
}