{
  "type": "Feature",
  "properties": {
    "addr:full":"64012 Campli Campli Teramo 64012",
    "addr:postcode":"64012;64012",
    "iso:country":"IT",
    "sg:address":"64012 Campli",
    "sg:city":"Campli",
    "sg:orig_category":"Serramenti Ed Infissi. Prodotti Vari In Metallo",
    "sg:phone":"+39 0861 553434",
    "sg:postcode":"64012",
    "sg:province":"Teramo",
    "wof:name":"Allu System Snc",
    "wof:placetype":"venue"
},
  "geometry": {"coordinates":[13.694167,42.726688],"type":"Point"}
}