{
  "type": "Feature",
  "properties": {
    "addr:full":"10091 Alpignano Alpignano Torino 10091",
    "addr:postcode":"10091;10091",
    "iso:country":"IT",
    "sg:address":"10091 Alpignano",
    "sg:city":"Alpignano",
    "sg:orig_category":"Macchine, Impianti Ed Attrezzature Per Industria Alimentare E Bevande",
    "sg:phone":"+39 011 966 4076",
    "sg:postcode":"10091",
    "sg:province":"Torino",
    "wof:name":"Alitec (s.a.s.)",
    "wof:placetype":"venue"
},
  "geometry": {"coordinates":[7.542398,45.117691],"type":"Point"}
}