{
  "type": "Feature",
  "properties": {
    "addr:full":"8, Via Izzo 80023 Caivano Caivano Napoli 80023",
    "addr:postcode":"80023;80023",
    "addr:street":"Via Izzo",
    "iso:country":"IT",
    "sg:address":"8, Via Izzo 80023 Caivano",
    "sg:city":"Caivano",
    "sg:classifiers":[
        {
            "category":"Personal",
            "subcategory":"Shoe Repair & Shine",
            "type":"Services"
        }
    ],
    "sg:phone":"+39 081 831 9816",
    "sg:postcode":"80023",
    "sg:province":"Napoli",
    "sg:tags":[
        "leather"
    ],
    "wof:name":"Il Guerriero Sas",
    "wof:placetype":"venue"
},
  "geometry": {"coordinates":[14.298512,40.948948],"type":"Point"}
}