{
  "type": "Feature",
  "properties": {
    "iso:country":"IT",
    "sg:address":"41051 Castelnuovo Rangone",
    "sg:city":"Castelnuovo Rangone",
    "sg:orig_category":"Serramenti Ed Infissi. Prodotti Vari In Metallo",
    "sg:phone":"+39 059 536250",
    "sg:postcode":"41051",
    "sg:province":"Modena",
    "sg:website":"http://www.tiemmeserramenti.it",
    "wof:name":"Ti-emme Srl",
    "wof:placetype":"venue"
},
  "geometry": {"coordinates":[10.928713,44.552177],"type":"Point"}
}