{
  "type": "Feature",
  "properties": {
    "iso:country":"IT",
    "sg:address":"20154 Milano",
    "sg:city":"Milano",
    "sg:orig_category":"Professionisti - Studi E Servizi Ed Associazioni Di Interesse Aziendale. Servizi Sociali. Associazioni Ed Organismi Di Interesse Pubblico",
    "sg:phone":"+39 02 331 9942",
    "sg:postcode":"20154",
    "sg:province":"Milano",
    "wof:name":"Esercito Della Salvezza",
    "wof:placetype":"venue"
},
  "geometry": {"coordinates":[9.1730012894,45.4812660217],"type":"Point"}
}