{
  "type": "Feature",
  "properties": {
    "iso:country":"IT",
    "sg:address":"Viale Certosa 218, 20156 Milan, Mi",
    "sg:classifiers":[
        {
            "category":"Banks & Credit Unions",
            "subcategory":"Bank",
            "type":"Services"
        }
    ],
    "sg:postcode":"20156",
    "sg:province":"Milano",
    "wof:name":"Soc Interbancaria Per L'automazione (cedborsa) Spa",
    "wof:placetype":"venue"
},
  "geometry": {"coordinates":[9.151104,45.490414],"type":"Point"}
}