{
  "type": "Feature",
  "properties": {
    "iso:country":"IT",
    "sg:address":"Piazza Della Regione 7; Villagrazia Di Carini; 90040",
    "sg:classifiers":[
        {
            "category":"Banks & Credit Unions",
            "subcategory":"Bank",
            "type":"Services"
        }
    ],
    "sg:phone":"+39 091 867 4978",
    "sg:postcode":"90040",
    "sg:province":"Palermo",
    "wof:name":"Banca Popolare Di Carini",
    "wof:placetype":"venue"
},
  "geometry": {"coordinates":[13.270724,38.084862],"type":"Point"}
}