{
  "type": "Feature",
  "properties": {
    "iso:country":"IT",
    "sg:address":"10, Via Vittorio Veneto 24030 Presezzo",
    "sg:city":"Presezzo",
    "sg:classifiers":[
        {
            "category":"Professional",
            "subcategory":"Engineering",
            "type":"Services"
        }
    ],
    "sg:phone":"+39 39035611454",
    "sg:postcode":"24030",
    "sg:province":"Bergamo",
    "sg:tags":[
        "machine",
        "-",
        "mechanical"
    ],
    "wof:name":"O.m.f.n. Dei F.lli Nani (s.r.l.)",
    "wof:placetype":"venue"
},
  "geometry": {"coordinates":[9.578087,45.693634],"type":"Point"}
}