{
  "type": "Feature",
  "properties": {
    "iso:country":"IT",
    "sg:address":"83030 Manocalzati",
    "sg:city":"Manocalzati",
    "sg:orig_category":"Materiali Semilavorati Metallici",
    "sg:phone":"+39 0825 675454",
    "sg:postcode":"83030",
    "sg:province":"Avellino",
    "wof:name":"Efil Sud S.r.l.",
    "wof:placetype":"venue"
},
  "geometry": {"coordinates":[14.838299,40.953701],"type":"Point"}
}