{
  "type": "Feature",
  "properties": {
    "addr:full":"Via Galileo Galilei 58/60 25020 Poncarale Poncarale Brescia 25020",
    "addr:housenumber":"58 / 60",
    "addr:postcode":"25020;25020",
    "addr:street":"Via Galileo Galilei",
    "iso:country":"IT",
    "sg:address":"Via Galileo Galilei 58/60 25020 Poncarale",
    "sg:city":"Poncarale",
    "sg:classifiers":[
        {
            "category":"Government",
            "subcategory":"Fire Station",
            "type":"Public Place"
        }
    ],
    "sg:phone":"+39 030 264 0134",
    "sg:postcode":"25020",
    "sg:province":"Brescia",
    "sg:tags":[
        "plant",
        "installation",
        "air",
        "ventilation",
        "air-conditioning",
        "treatment"
    ],
    "sg:website":"www.bonomi-eng.it",
    "wof:name":"Bonomi Engineering S.r.l.",
    "wof:placetype":"venue"
},
  "geometry": {"coordinates":[10.201083,45.45533],"type":"Point"}
}