{
  "type": "Feature",
  "properties": {
    "iso:country":"IT",
    "sg:address":"3, Via Meucci 43058 Sorbolo",
    "sg:city":"Sorbolo",
    "sg:classifiers":[
        {
            "category":"Communications",
            "subcategory":"Television Station",
            "type":"Services"
        }
    ],
    "sg:phone":"+39 0521 698901",
    "sg:postcode":"43058",
    "sg:province":"Parma",
    "sg:tags":[
        "audio-visual"
    ],
    "wof:name":"Ital C.i.d.a. (s.p.a.)",
    "wof:placetype":"venue"
},
  "geometry": {"coordinates":[10.447388,44.843929],"type":"Point"}
}