{
  "type": "Feature",
  "properties": {
    "iso:country":"IT",
    "sg:address":"20123 Milano",
    "sg:city":"Milano",
    "sg:orig_category":"Pubblicita', Marketing E Comunicazione",
    "sg:phone":"+39 02 481 5437",
    "sg:postcode":"20123",
    "sg:province":"Milano",
    "wof:name":"Bb Cube Communications S.n.c.",
    "wof:placetype":"venue"
},
  "geometry": {"coordinates":[9.1687498093,45.4656906128],"type":"Point"}
}