{
  "type": "Feature",
  "properties": {
    "iso:country":"IT",
    "sg:address":"58100 Grosseto",
    "sg:city":"Grosseto",
    "sg:orig_category":"Arredo Urbano",
    "sg:phone":"+39 0564 416409",
    "sg:postcode":"58100",
    "sg:province":"Grosseto",
    "wof:name":"F.a.m. Snc",
    "wof:placetype":"venue"
},
  "geometry": {"coordinates":[11.107965,42.745029],"type":"Point"}
}