{
  "type": "Feature",
  "properties": {
    "iso:country":"IT",
    "sg:address":"23846 Garbagnate Monastero",
    "sg:city":"Garbagnate Monastero",
    "sg:orig_category":"Apparecchiature E Sistemi Per Imballaggio E Confezionamento",
    "sg:phone":"+39 031 879811",
    "sg:postcode":"23846",
    "sg:province":"Lecco",
    "wof:name":"Cama 1 Spa",
    "wof:placetype":"venue"
},
  "geometry": {"coordinates":[9.28836,45.770435],"type":"Point"}
}