{
  "type": "Feature",
  "properties": {
    "iso:country":"IT",
    "sg:address":"39, Via Della Resistenza 42018 San Martino In Rio",
    "sg:classifiers":[
        {
            "category":"Wholesale",
            "subcategory":"Machinery & Supplies",
            "type":"Manufacturing & Wholesale Goods"
        }
    ],
    "sg:phone":"+39 0522 698156",
    "sg:postcode":"42018",
    "sg:province":"Reggio Nell'Emilia",
    "sg:tags":[
        "-",
        "agriculture",
        "equipment"
    ],
    "wof:name":"S.e.p. (s.r.l.)",
    "wof:placetype":"venue"
},
  "geometry": {"coordinates":[10.786815,44.738995],"type":"Point"}
}