{
  "type": "Feature",
  "properties": {
    "iso:country":"IT",
    "sg:address":"V Xx Settembre 42/44; Torino; 10121",
    "sg:city":"Torino",
    "sg:classifiers":[
        {
            "category":"Banks & Credit Unions",
            "subcategory":"Bank",
            "type":"Services"
        }
    ],
    "sg:phone":"+39 011 511306",
    "sg:postcode":"10121",
    "sg:province":"Torino",
    "wof:name":"Banca Popolare Di Novara",
    "wof:placetype":"venue"
},
  "geometry": {"coordinates":[7.394709,45.082336],"type":"Point"}
}