{
  "type": "Feature",
  "properties": {
    "addr:full":"20093 Cologno Monzese Cologno Monzese Milano 20093",
    "addr:postcode":"20093;20093",
    "iso:country":"IT",
    "sg:address":"20093 Cologno Monzese",
    "sg:city":"Cologno Monzese",
    "sg:orig_category":"Apparecchiature Ed Attrezzature Meccaniche",
    "sg:phone":"+39 02 254 4045",
    "sg:postcode":"20093",
    "sg:province":"Milano",
    "wof:name":"Toflex Industriale (s.r.l.)",
    "wof:placetype":"venue"
},
  "geometry": {"coordinates":[9.267979,45.524139],"type":"Point"}
}