{
  "type": "Feature",
  "properties": {
    "addr:full":"32030 Quero Quero Belluno 32030",
    "addr:postcode":"32030;32030",
    "iso:country":"IT",
    "sg:address":"32030 Quero",
    "sg:city":"Quero",
    "sg:orig_category":"Occhiali - Produzione E Ingrosso",
    "sg:phone":"+39 0439 788366",
    "sg:postcode":"32030",
    "sg:province":"Belluno",
    "sg:website":"http://www.visard.it",
    "wof:name":"Visard Srl",
    "wof:placetype":"venue"
},
  "geometry": {"coordinates":[11.931723,45.921974],"type":"Point"}
}