{
  "type": "Feature",
  "properties": {
    "iso:country":"IT",
    "sg:address":"12, Via Catagnina 54100 Massa",
    "sg:city":"Massa",
    "sg:classifiers":[
        {
            "category":"Manufacturing",
            "subcategory":"Glass & Minerals",
            "type":"Manufacturing & Wholesale Goods"
        }
    ],
    "sg:phone":"+39 0585 830495",
    "sg:postcode":"54100",
    "sg:province":"Massa-Carrara",
    "wof:name":"B.e.b. Srl Unipersonale",
    "wof:placetype":"venue"
},
  "geometry": {"coordinates":[10.110606,44.036057],"type":"Point"}
}