{
  "type": "Feature",
  "properties": {
    "addr:full":"60033 Chiaravalle Chiaravalle Ancona 60033",
    "addr:postcode":"60033;60033",
    "iso:country":"IT",
    "sg:address":"60033 Chiaravalle",
    "sg:city":"Chiaravalle",
    "sg:orig_category":"Trasporti E Spedizioni Merci",
    "sg:phone":"+39 071 948948",
    "sg:postcode":"60033",
    "sg:province":"Ancona",
    "wof:name":"Mariani Franco",
    "wof:placetype":"venue"
},
  "geometry": {"coordinates":[13.517134,43.618244],"type":"Point"}
}