{
  "type": "Feature",
  "properties": {
    "addr:full":"81036 S.cipriano D'aversa Caserta 81036",
    "addr:postcode":"81036;81036",
    "iso:country":"IT",
    "sg:address":"81036 S.cipriano D'aversa",
    "sg:orig_category":"Arredo Cucina Ed Elettrodomestici. Elettrodomestici",
    "sg:phone":"+39 081 816 4892",
    "sg:postcode":"81036",
    "sg:province":"Caserta",
    "wof:name":"Due D Sas Dei F.lli Del Piano",
    "wof:placetype":"venue"
},
  "geometry": {"coordinates":[14.332194,41.075417],"type":"Point"}
}