{
  "type": "Feature",
  "properties": {
    "addr:full":"64027 S.omero Teramo 64027",
    "addr:postcode":"64027;64027",
    "iso:country":"IT",
    "sg:address":"64027 S.omero",
    "sg:orig_category":"Abbigliamento Esterno, Maglierie E Pelliccerie. Shopping",
    "sg:phone":"+39 0861 818003",
    "sg:postcode":"64027",
    "sg:province":"Teramo",
    "sg:website":"http://www.jonnyq.com",
    "wof:name":"Jonny Q Italia Srl",
    "wof:placetype":"venue"
},
  "geometry": {"coordinates":[13.698531,42.66127],"type":"Point"}
}