{
  "type": "Feature",
  "properties": {
    "iso:country":"IT",
    "sg:address":"56012 Fornacette",
    "sg:city":"Fornacette",
    "sg:orig_category":"Servizi Di Magazzinaggio E Movimentazione",
    "sg:phone":"+39 0587 420665",
    "sg:postcode":"56012",
    "sg:province":"Pisa",
    "wof:name":"Meini Bilance (s.r.l.)",
    "wof:placetype":"venue"
},
  "geometry": {"coordinates":[10.397914,43.710823],"type":"Point"}
}