{
  "type": "Feature",
  "properties": {
    "iso:country":"IT",
    "sg:address":"65121 Pescara",
    "sg:city":"Pescara",
    "sg:orig_category":"Pianoforti",
    "sg:phone":"+39 085 36183",
    "sg:postcode":"65121",
    "sg:province":"Pescara",
    "wof:name":"Ditta Angelo Fabbrini",
    "wof:placetype":"venue"
},
  "geometry": {"coordinates":[14.214887619,42.4663505554],"type":"Point"}
}