{
  "type": "Feature",
  "properties": {
    "iso:country":"IT",
    "sg:address":"12050 Magliano Alfieri",
    "sg:city":"Magliano Alfieri",
    "sg:orig_category":"Abbigliamento Esterno, Maglierie E Pelliccerie",
    "sg:phone":"+39 0173 66612",
    "sg:postcode":"12050",
    "sg:province":"Cuneo",
    "wof:name":"Brands Srl",
    "wof:placetype":"venue"
},
  "geometry": {"coordinates":[8.071259,44.770332],"type":"Point"}
}