{
  "type": "Feature",
  "properties": {
    "iso:country":"IT",
    "sg:address":"37063 Isola Della Scala",
    "sg:city":"Isola della Scala",
    "sg:orig_category":"Servizi E Lavori Per Agricoltura E Zootecnia",
    "sg:postcode":"37063",
    "sg:province":"Verona",
    "wof:name":"Miozzi Vittorio E Giuseppe (s.n.c.)",
    "wof:placetype":"venue"
},
  "geometry": {"coordinates":[11.032325,45.274712],"type":"Point"}
}