{
  "type": "Feature",
  "properties": {
    "iso:country":"IT",
    "sg:address":"30035 Mirano",
    "sg:city":"Mirano",
    "sg:orig_category":"Imprese Di Costruzioni Civili Ed Industriali",
    "sg:phone":"+39 041 570 0969",
    "sg:postcode":"30035",
    "sg:province":"Venezia",
    "sg:website":"http://www.ekos.it",
    "wof:name":"Ekos Italiana Srl",
    "wof:placetype":"venue"
},
  "geometry": {"coordinates":[12.117325,45.476414],"type":"Point"}
}