{
  "type": "Feature",
  "properties": {
    "iso:country":"IT",
    "sg:address":"27029 Vigevano",
    "sg:city":"Vigevano",
    "sg:orig_category":"Prodotti Finiti Stampati. Articoli Da Regalo. Arte Ed Artigianato Artistico. Shopping",
    "sg:phone":"+39 0381 692741",
    "sg:postcode":"27029",
    "sg:province":"Pavia",
    "wof:name":"Stampe Antiche E Libri D'arte Bottigella",
    "wof:placetype":"venue"
},
  "geometry": {"coordinates":[8.8354701996,45.3154907227],"type":"Point"}
}