{
  "type": "Feature",
  "properties": {
    "iso:country":"IT",
    "sg:address":"22070 Bregnano",
    "sg:city":"Bregnano",
    "sg:orig_category":"Carta, Cartone E Prodotti Primari. Forniture E Materiali Per Imballaggio E Confezionamento",
    "sg:phone":"+39 031 774064",
    "sg:postcode":"22070",
    "sg:province":"Como",
    "wof:name":"Imballi Srl",
    "wof:placetype":"venue"
},
  "geometry": {"coordinates":[9.062121,45.708813],"type":"Point"}
}