{
  "type": "Feature",
  "properties": {
    "iso:country":"IT",
    "sg:address":"59100 Prato",
    "sg:city":"Prato",
    "sg:orig_category":"Prodotti E Manufatti In Gomma. Servizi E Lavori Industria Della Gomma. Ricambi E Componenti Dei Mezzi Di Trasporto. Riparazione Dei Mezzi Di Trasporto",
    "sg:phone":"+39 0574 590986",
    "sg:postcode":"59100",
    "sg:province":"Prato",
    "wof:name":"Bartolini Gomme Snc",
    "wof:placetype":"venue"
},
  "geometry": {"coordinates":[11.1089000702,43.8678817749],"type":"Point"}
}