{
  "type": "Feature",
  "properties": {
    "iso:country":"IT",
    "sg:address":"Via Quattro Novembre 2 23807 Merate",
    "sg:city":"Merate",
    "sg:classifiers":[
        {
            "category":"Community Center",
            "subcategory":"Youth",
            "type":"Public Place"
        }
    ],
    "sg:phone":"+39 039 99851",
    "sg:postcode":"23807",
    "sg:province":"Lecco",
    "sg:tags":[
        "steel",
        "section",
        "sections",
        "special"
    ],
    "sg:website":"www.calvi.it",
    "wof:name":"Metallurgica Calvi Spa",
    "wof:placetype":"venue"
},
  "geometry": {"coordinates":[9.390071,45.852982],"type":"Point"}
}