{
  "type": "Feature",
  "properties": {
    "iso:country":"IT",
    "sg:address":"97013 Comiso",
    "sg:city":"Comiso",
    "sg:orig_category":"Forniture Per Edilizia E Lavori Pubblici",
    "sg:phone":"+39 0932 721617",
    "sg:postcode":"97013",
    "sg:province":"Ragusa",
    "wof:name":"Sallemi Giuseppe Restauri",
    "wof:placetype":"venue"
},
  "geometry": {"coordinates":[14.5934886932,36.9401931763],"type":"Point"}
}