{
  "type": "Feature",
  "properties": {
    "iso:country":"IT",
    "sg:address":"35013 Cittadella",
    "sg:city":"Cittadella",
    "sg:orig_category":"Serramenti Ed Infissi",
    "sg:phone":"+39 049 940 1132",
    "sg:postcode":"35013",
    "sg:province":"Padova",
    "wof:name":"Stc (s.r.l.)",
    "wof:placetype":"venue"
},
  "geometry": {"coordinates":[11.786479,45.64093],"type":"Point"}
}