{
  "type": "Feature",
  "properties": {
    "iso:country":"IT",
    "sg:address":"90144 Palermo",
    "sg:city":"Palermo",
    "sg:orig_category":"Cinema And Radio-television. Advertising, Marketing And Communication. Water, Light, Gas And Public Utility Companies",
    "sg:phone":"+39 091 220978",
    "sg:postcode":"90144",
    "sg:province":"Palermo",
    "sg:website":"http://www.dabliuradio.it",
    "wof:name":"W - Dabliu Radio",
    "wof:placetype":"venue"
},
  "geometry": {"coordinates":[13.333428,38.14151],"type":"Point"}
}