{
  "type": "Feature",
  "properties": {
    "addr:full":"73055 Racale Racale Lecce 73055",
    "addr:postcode":"73055;73055",
    "iso:country":"IT",
    "sg:address":"73055 Racale",
    "sg:city":"Racale",
    "sg:orig_category":"Pompe. Macchine, Strumenti Ed Apparecchi Per Attivita' Industriali",
    "sg:phone":"+39 0833 583905",
    "sg:postcode":"73055",
    "sg:province":"Lecce",
    "wof:name":"Idrotech Di Francioso Gianluca",
    "wof:placetype":"venue"
},
  "geometry": {"coordinates":[18.0446929932,40.3471603394],"type":"Point"}
}