{
  "type": "Feature",
  "properties": {
    "addr:full":"10024 Moncalieri Moncalieri Torino 10024",
    "addr:postcode":"10024;10024",
    "iso:country":"IT",
    "sg:address":"10024 Moncalieri",
    "sg:city":"Moncalieri",
    "sg:orig_category":"Riparazione Dei Mezzi Di Trasporto",
    "sg:phone":"+39 011 645616",
    "sg:postcode":"10024",
    "sg:province":"Torino",
    "wof:name":"Autocarrozzeria Bordignon",
    "wof:placetype":"venue"
},
  "geometry": {"coordinates":[7.674047,45.001995],"type":"Point"}
}