{
  "type": "Feature",
  "properties": {
    "iso:country":"IT",
    "sg:address":"09129 Cagliari",
    "sg:city":"Cagliari",
    "sg:orig_category":"Pubblica Amministrazione",
    "sg:phone":"+39 070 402056",
    "sg:postcode":"09129",
    "sg:province":"Cagliari",
    "wof:name":"Ministero Dell'ambiente N.o.e. Carabinieri",
    "wof:placetype":"venue"
},
  "geometry": {"coordinates":[9.1428480148,39.2227783203],"type":"Point"}
}