{
  "type": "Feature",
  "properties": {
    "iso:country":"IT",
    "sg:address":"Via Lombardia 31/33 20098 Sesto Ulteriano",
    "sg:city":"Sesto Ulteriano",
    "sg:classifiers":[
        {
            "category":"Communications",
            "subcategory":"Film & Video Production",
            "type":"Services"
        }
    ],
    "sg:phone":"+39 02 988321",
    "sg:postcode":"20098",
    "sg:province":"Milano",
    "sg:tags":[
        "silicone"
    ],
    "sg:website":"www.dowcorning.com",
    "wof:name":"Dow Corning Spa",
    "wof:placetype":"venue"
},
  "geometry": {"coordinates":[9.253379,45.397606],"type":"Point"}
}