{
  "type": "Feature",
  "properties": {
    "iso:country":"IT",
    "sg:address":"71013 S.giovanni Rotondo",
    "sg:classifiers":[
        {
            "category":"Restaurant",
            "type":"Food & Drink"
        }
    ],
    "sg:phone":"+39 0882 413557",
    "sg:postcode":"71013",
    "sg:province":"Foggia",
    "sg:tags":[
        "auxiliary",
        "entertainment",
        "premises",
        "related",
        "catering",
        "similar",
        "public",
        "restaurants"
    ],
    "sg:website":"http://www.artecotur.it",
    "wof:name":"Bosco Rosso Viaggi Di Arteco.tur",
    "wof:placetype":"venue"
},
  "geometry": {"coordinates":[15.758591,41.673962],"type":"Point"}
}