{
  "type": "Feature",
  "properties": {
    "iso:country":"IT",
    "sg:address":"20146 Milano",
    "sg:city":"Milano",
    "sg:orig_category":"Abbigliamento Intimo, Calze E Costumi Da Bagno",
    "sg:phone":"+39 02 4895 0954",
    "sg:postcode":"20146",
    "sg:province":"Milano",
    "wof:name":"Labate Alfredo",
    "wof:placetype":"venue"
},
  "geometry": {"coordinates":[9.14478,45.452461],"type":"Point"}
}