{
  "type": "Feature",
  "properties": {
    "addr:full":"60/a, Via Della Valverde 37122 Verona Verona Verona 37122",
    "addr:housenumber":"60 / a",
    "addr:postcode":"37122;37122",
    "addr:street":"Via Della Valverde",
    "iso:country":"IT",
    "sg:address":"60/a, Via Della Valverde 37122 Verona",
    "sg:city":"Verona",
    "sg:classifiers":[
        {
            "category":"Shopping",
            "subcategory":"Clothing, Apparel, & Fashions",
            "type":"Retail Goods"
        }
    ],
    "sg:phone":"+39 045 803 4935",
    "sg:postcode":"37122",
    "sg:province":"Verona",
    "sg:tags":[
        "clothes"
    ],
    "wof:name":"Pellicceria Marco & Maria",
    "wof:placetype":"venue"
},
  "geometry": {"coordinates":[10.915559,45.398762],"type":"Point"}
}