{
  "type": "Feature",
  "properties": {
    "iso:country":"IT",
    "sg:address":"12, Via Cima Gogna 32041 Auronzo Di Cadore",
    "sg:city":"Auronzo di Cadore",
    "sg:classifiers":[
        {
            "category":"Home & Garden",
            "subcategory":"Home Furnishings",
            "type":"Retail Goods"
        }
    ],
    "sg:phone":"+39 390 435 9807",
    "sg:postcode":"32041",
    "sg:province":"Belluno",
    "sg:tags":[
        "household"
    ],
    "wof:name":"Metallart (s.r.l.)",
    "wof:placetype":"venue"
},
  "geometry": {"coordinates":[12.21759,46.139965],"type":"Point"}
}