{
  "type": "Feature",
  "properties": {
    "iso:country":"IT",
    "sg:address":"95014 Giarre",
    "sg:city":"Giarre",
    "sg:orig_category":"Scuole E Servizi Scolastici",
    "sg:phone":"+39 095 931527",
    "sg:postcode":"95014",
    "sg:province":"Catania",
    "wof:name":"Istituto Magistrale Don Bosco",
    "wof:placetype":"venue"
},
  "geometry": {"coordinates":[15.178883,37.722687],"type":"Point"}
}