{
  "type": "Feature",
  "properties": {
    "addr:full":"87028 Praia A Mare Praia a Mare Cosenza 87028",
    "addr:postcode":"87028;87028",
    "addr:street":"A",
    "iso:country":"IT",
    "sg:address":"87028 Praia A Mare",
    "sg:city":"Praia a Mare",
    "sg:orig_category":"Elettrotecnica Industriale, Prodotti E Apparecchiature. Ricambi E Componenti Dei Mezzi Di Trasporto",
    "sg:phone":"+39 0985 72427",
    "sg:postcode":"87028",
    "sg:province":"Cosenza",
    "wof:name":"I.m.a. Sas Di Cipro P. & C.",
    "wof:placetype":"venue"
},
  "geometry": {"coordinates":[15.78328,39.889843],"type":"Point"}
}