{
  "type": "Feature",
  "properties": {
    "iso:country":"IT",
    "sg:address":"Via Calabria 33; Cosenza; 87100",
    "sg:city":"Cosenza",
    "sg:classifiers":[
        {
            "category":"Shopping",
            "subcategory":"Computers & Home Electronics",
            "type":"Retail Goods"
        }
    ],
    "sg:phone":"+39 390 984 8151",
    "sg:postcode":"87100",
    "sg:province":"Cosenza",
    "sg:tags":[
        "chamber",
        "commerce"
    ],
    "sg:website":"cs.camcom.it",
    "wof:name":"Cosenza Chamber Of Commerce And Industry",
    "wof:placetype":"venue"
},
  "geometry": {"coordinates":[16.252106,39.29789],"type":"Point"}
}