{
  "type": "Feature",
  "properties": {
    "addr:full":"1, Via Italia 24030 Valbrembo Valbrembo Bergamo 24030",
    "addr:postcode":"24030;24030",
    "addr:street":"Via Italia",
    "iso:country":"IT",
    "sg:address":"1, Via Italia 24030 Valbrembo",
    "sg:city":"Valbrembo",
    "sg:classifiers":[
        {
            "category":"Manufacturing",
            "subcategory":"Metals",
            "type":"Manufacturing & Wholesale Goods"
        }
    ],
    "sg:phone":"+39 035 451 0011",
    "sg:postcode":"24030",
    "sg:province":"Bergamo",
    "sg:tags":[
        "metallurgy",
        "metalworking"
    ],
    "wof:name":"Item (s.r.l.)",
    "wof:placetype":"venue"
},
  "geometry": {"coordinates":[9.6026754379,45.7123451233],"type":"Point"}
}