{
  "type": "Feature",
  "properties": {
    "iso:country":"IT",
    "sg:address":"Via Regina 30; Musso; 22010",
    "sg:city":"Musso",
    "sg:classifiers":[
        {
            "category":"Banks & Credit Unions",
            "subcategory":"Bank",
            "type":"Services"
        }
    ],
    "sg:phone":"+39 0344 82707",
    "sg:postcode":"22010",
    "sg:province":"Como",
    "wof:name":"Istituto Bancario, San Paolo Di Torino Spa",
    "wof:placetype":"venue"
},
  "geometry": {"coordinates":[9.277064,46.109673],"type":"Point"}
}