{
  "type": "Feature",
  "properties": {
    "addr:full":"Via Nazionale 99; Ca De'fabbri",
    "addr:housenumber":"99 ca",
    "addr:street":"Via Nazionale;De'Fabbri",
    "iso:country":"IT",
    "sg:address":"Via Nazionale 99; Ca De'fabbri",
    "sg:classifiers":[
        {
            "category":"Banks & Credit Unions",
            "subcategory":"Bank",
            "type":"Services"
        }
    ],
    "sg:phone":"+39 051 660 5307",
    "wof:name":"Banca Agricola Mantovana Scarl",
    "wof:placetype":"venue"
},
  "geometry": {"coordinates":[11.452899,44.618313],"type":"Point"}
}