{
  "type": "Feature",
  "properties": {
    "iso:country":"IT",
    "sg:address":"27010 Bornasco",
    "sg:city":"Bornasco",
    "sg:classifiers":[
        {
            "category":"Utilities",
            "subcategory":"Refuse",
            "type":"Services"
        }
    ],
    "sg:phone":"+39 0382 955674",
    "sg:postcode":"27010",
    "sg:province":"Pavia",
    "sg:tags":[
        "control",
        "auxiliary",
        "disposal",
        "analysis",
        "research",
        "environmental",
        "protection",
        "works"
    ],
    "wof:name":"Sida Italiana Di Silvia Sartor",
    "wof:placetype":"venue"
},
  "geometry": {"coordinates":[9.140658,44.910488],"type":"Point"}
}