{
  "type": "Feature",
  "properties": {
    "addr:full":"38060 Nago-torbole Trento 38060",
    "addr:postcode":"38060;38060",
    "iso:country":"IT",
    "sg:address":"38060 Nago-torbole",
    "sg:classifiers":[
        {
            "category":"Food & Beverages",
            "subcategory":"Groceries & Convenience Stores",
            "type":"Retail Goods"
        }
    ],
    "sg:phone":"+39 0464 540111",
    "sg:postcode":"38060",
    "sg:province":"Trento",
    "sg:tags":[
        "product",
        "related"
    ],
    "wof:name":"Salumificio Trentino (s.r.l.)",
    "wof:placetype":"venue"
},
  "geometry": {"coordinates":[10.8901691437,45.8782348633],"type":"Point"}
}