{
  "type": "Feature",
  "properties": {
    "iso:country":"IT",
    "sg:address":"Via Cassano D'adda 19 20139 Milano",
    "sg:city":"Milano",
    "sg:classifiers":[
        {
            "category":"Autos & Motor Vehicles",
            "subcategory":"Motorcycle Sales",
            "type":"Retail Goods"
        }
    ],
    "sg:phone":"+39 02 533283",
    "sg:postcode":"20139",
    "sg:province":"Milano",
    "sg:tags":[
        "engine",
        "spare"
    ],
    "sg:website":"www.shoppingclassic.com",
    "wof:name":"Capra And General Sas",
    "wof:placetype":"venue"
},
  "geometry": {"coordinates":[9.211392,45.438068],"type":"Point"}
}