{
  "type": "Feature",
  "properties": {
    "iso:country":"IT",
    "sg:address":"Via Marzabotto 6 20059 Vimercate",
    "sg:city":"Vimercate",
    "sg:orig_category":"Plaiting And Braiding Machines",
    "sg:phone":"+39 039 625111",
    "sg:postcode":"20059",
    "sg:province":"Milano",
    "sg:website":"www.omabraid.com",
    "wof:name":"O.m.a. S.r.l.",
    "wof:placetype":"venue"
},
  "geometry": {"coordinates":[9.3600721359,45.5955276489],"type":"Point"}
}