{
  "type": "Feature",
  "properties": {
    "iso:country":"IT",
    "sg:address":"101, Via Calamandrei Pietro 52100 Arezzo",
    "sg:city":"Arezzo",
    "sg:classifiers":[
        {
            "category":"Manufacturing",
            "subcategory":"Metals",
            "type":"Manufacturing & Wholesale Goods"
        }
    ],
    "sg:phone":"+39 0575 350744",
    "sg:postcode":"52100",
    "sg:province":"Arezzo",
    "sg:tags":[
        "metallurgy",
        "metalworking"
    ],
    "wof:name":"Gold And Silver (s.r.l.)",
    "wof:placetype":"venue"
},
  "geometry": {"coordinates":[11.841676712,43.4614830017],"type":"Point"}
}