{
  "type": "Feature",
  "properties": {
    "addr:full":"25014 Castenedolo Castenedolo Brescia 25014",
    "addr:postcode":"25014;25014",
    "iso:country":"IT",
    "sg:address":"25014 Castenedolo",
    "sg:city":"Castenedolo",
    "sg:orig_category":"Arredo Bagno Ed Idrosanitari. Idrosanitari E Accessori",
    "sg:phone":"+39 030 213 4211",
    "sg:postcode":"25014",
    "sg:province":"Brescia",
    "sg:website":"http://www.bossini.it",
    "wof:name":"Bossini Srl",
    "wof:placetype":"venue"
},
  "geometry": {"coordinates":[10.302215,45.469131],"type":"Point"}
}