{
  "type": "Feature",
  "properties": {
    "addr:full":"46044 Goito Goito Mantova 46044",
    "addr:postcode":"46044;46044",
    "iso:country":"IT",
    "sg:address":"46044 Goito",
    "sg:city":"Goito",
    "sg:orig_category":"Macchine Ed Impianti Per Edilizia E Lavori Pubblici",
    "sg:phone":"+39 0376 604594",
    "sg:postcode":"46044",
    "sg:province":"Mantova",
    "wof:name":"Tarpini Paolo",
    "wof:placetype":"venue"
},
  "geometry": {"coordinates":[10.650032,45.244923],"type":"Point"}
}