{
  "type": "Feature",
  "properties": {
    "addr:full":"Via E. Fermi 48 20019 Settimo Milanese Settimo Milanese Milano 20019",
    "addr:housenumber":"48",
    "addr:postcode":"20019;20019",
    "addr:street":"Via E. Fermi",
    "iso:country":"IT",
    "sg:address":"Via E. Fermi 48 20019 Settimo Milanese",
    "sg:city":"Settimo Milanese",
    "sg:classifiers":[
        {
            "category":"Wholesale",
            "subcategory":"Metals & Minerals",
            "type":"Manufacturing & Wholesale Goods"
        }
    ],
    "sg:phone":"+39 02 328 5775",
    "sg:postcode":"20019",
    "sg:province":"Milano",
    "sg:tags":[
        "machine",
        "sheet",
        "working",
        "strip"
    ],
    "sg:website":"www.servopresse.it",
    "wof:name":"Servopresse S.r.l.",
    "wof:placetype":"venue"
},
  "geometry": {"coordinates":[9.067799,45.480034],"type":"Point"}
}