{
  "type": "Feature",
  "properties": {
    "addr:full":"95030 Nicolosi Nicolosi Catania 95030",
    "addr:postcode":"95030;95030",
    "iso:country":"IT",
    "sg:address":"95030 Nicolosi",
    "sg:city":"Nicolosi",
    "sg:orig_category":"Dolciumi E Gelati",
    "sg:phone":"+39 095 911743",
    "sg:postcode":"95030",
    "sg:province":"Catania",
    "wof:name":"S. Rita",
    "wof:placetype":"venue"
},
  "geometry": {"coordinates":[15.028938,37.592766],"type":"Point"}
}