{
  "type": "Feature",
  "properties": {
    "addr:full":"62, Via Rovadino 25011 Calcinato Calcinato Brescia 25011",
    "addr:postcode":"25011;25011",
    "addr:street":"Via Rovadino",
    "iso:country":"IT",
    "sg:address":"62, Via Rovadino 25011 Calcinato",
    "sg:city":"Calcinato",
    "sg:classifiers":[
        {
            "category":"Shopping",
            "subcategory":"Clothing, Apparel, & Fashions",
            "type":"Retail Goods"
        }
    ],
    "sg:phone":"+39 39030963220",
    "sg:postcode":"25011",
    "sg:province":"Brescia",
    "sg:tags":[
        "clothes"
    ],
    "wof:name":"Maglificio Lella Di Binotti Osvaldo & C. (s.n.c.)",
    "wof:placetype":"venue"
},
  "geometry": {"coordinates":[10.442986,45.460606],"type":"Point"}
}