{
  "type": "Feature",
  "properties": {
    "addr:full":"Via Liguria 2 20098 Sesto Ulteriano Sesto Ulteriano Milano 20098",
    "addr:housenumber":"2",
    "addr:postcode":"20098;20098",
    "addr:street":"Via Liguria",
    "iso:country":"IT",
    "sg:address":"Via Liguria 2 20098 Sesto Ulteriano",
    "sg:city":"Sesto Ulteriano",
    "sg:orig_category":"Cardboard Shelf Trays",
    "sg:phone":"+39 02 988 0008",
    "sg:postcode":"20098",
    "sg:province":"Milano",
    "sg:website":"www.spv.it",
    "wof:name":"S.p.v. Srl",
    "wof:placetype":"venue"
},
  "geometry": {"coordinates":[9.254364,45.397114],"type":"Point"}
}