{
  "type": "Feature",
  "properties": {
    "iso:country":"IT",
    "sg:address":"41100 Modena",
    "sg:city":"Modena",
    "sg:orig_category":"Autobus, Filobus E Minibus",
    "sg:phone":"+39 059 452061",
    "sg:postcode":"41100",
    "sg:province":"Modena",
    "wof:name":"Padane Officine Meccaniche Spa",
    "wof:placetype":"venue"
},
  "geometry": {"coordinates":[10.912465,44.660709],"type":"Point"}
}