{
  "type": "Feature",
  "properties": {
    "addr:full":"33080 Fiume Veneto Fiume Veneto Pordenone 33080",
    "addr:postcode":"33080;33080",
    "iso:country":"IT",
    "sg:address":"33080 Fiume Veneto",
    "sg:city":"Fiume Veneto",
    "sg:orig_category":"Arredo Cucina Ed Elettrodomestici. Climatizzazione E Condizionamento, Apparecchiature E Servizi",
    "sg:phone":"+39 0434 560610",
    "sg:postcode":"33080",
    "sg:province":"Pordenone",
    "wof:name":"Magic Di Biral Cristina E C. (s.n.c.)",
    "wof:placetype":"venue"
},
  "geometry": {"coordinates":[12.726945,45.936237],"type":"Point"}
}