{
  "type": "Feature",
  "properties": {
    "iso:country":"IT",
    "sg:address":"20146 Milano",
    "sg:city":"Milano",
    "sg:orig_category":"Servizi E Lavori Per Abbigliamento E Pelletterie",
    "sg:phone":"+39 02 416397",
    "sg:postcode":"20146",
    "sg:province":"Milano",
    "wof:name":"Tintoria S. Gimignano",
    "wof:placetype":"venue"
},
  "geometry": {"coordinates":[9.136454,45.455967],"type":"Point"}
}