{
  "type": "Feature",
  "properties": {
    "iso:country":"IT",
    "sg:address":"51100 Pistoia",
    "sg:city":"Pistoia",
    "sg:orig_category":"Dolciumi E Gelati",
    "sg:phone":"+39 0573 402797",
    "sg:postcode":"51100",
    "sg:province":"Pistoia",
    "wof:name":"A.v.s Di Gargini S. & C. Snc",
    "wof:placetype":"venue"
},
  "geometry": {"coordinates":[10.89856,43.958435],"type":"Point"}
}