{
  "type": "Feature",
  "properties": {
    "addr:full":"67/d, Via Brolo 25075 Nave Nave Brescia 25075",
    "addr:housenumber":"67 / d",
    "addr:postcode":"25075;25075",
    "addr:street":"Via Brolo",
    "iso:country":"IT",
    "sg:address":"67/d, Via Brolo 25075 Nave",
    "sg:city":"Nave",
    "sg:classifiers":[
        {
            "category":"Shopping",
            "subcategory":"Computers & Home Electronics",
            "type":"Retail Goods"
        }
    ],
    "sg:phone":"+39 030 253 4946",
    "sg:postcode":"25075",
    "sg:province":"Brescia",
    "sg:tags":[
        "electronic",
        "electrical",
        "equipment"
    ],
    "wof:name":"Bombardieri Srl",
    "wof:placetype":"venue"
},
  "geometry": {"coordinates":[10.276157,45.574928],"type":"Point"}
}