{
  "type": "Feature",
  "properties": {
    "iso:country":"IT",
    "sg:address":"25124 San Polo",
    "sg:orig_category":"Dolciumi E Gelati",
    "sg:phone":"+39 030 230 3831",
    "sg:postcode":"25124",
    "sg:province":"Brescia",
    "wof:name":"Pietta Giancarlo",
    "wof:placetype":"venue"
},
  "geometry": {"coordinates":[10.240535,45.512142],"type":"Point"}
}