{
  "type": "Feature",
  "properties": {
    "addr:full":"00040 Ariccia Ariccia Roma 00040",
    "addr:postcode":"00040;roma 00040",
    "iso:country":"IT",
    "sg:address":"00040 Ariccia",
    "sg:city":"Ariccia",
    "sg:orig_category":"Forniture Per Agricoltura E Zootecnia",
    "sg:phone":"+39 06 934 8044",
    "sg:postcode":"00040",
    "sg:province":"Roma",
    "wof:name":"Centro Grassi Ariccia Srl",
    "wof:placetype":"venue"
},
  "geometry": {"coordinates":[12.6751661301,41.7104797363],"type":"Point"}
}