{
  "type": "Feature",
  "properties": {
    "iso:country":"IT",
    "sg:address":"00148 Roma",
    "sg:city":"Roma",
    "sg:orig_category":"Arredamenti Ed Architettura D'interni",
    "sg:phone":"+39 06 6567 0477",
    "sg:postcode":"00148",
    "sg:province":"Roma",
    "wof:name":"Tecnoservice Srl",
    "wof:placetype":"venue"
},
  "geometry": {"coordinates":[12.418671,41.830612],"type":"Point"}
}