{
  "type": "Feature",
  "properties": {
    "addr:full":"40128 Bologna Bologna Bologna 40128",
    "addr:postcode":"40128;40128",
    "iso:country":"IT",
    "sg:address":"40128 Bologna",
    "sg:city":"Bologna",
    "sg:orig_category":"Servizi E Lavori Per Agricoltura E Zootecnia. Servizi Ausiliari Di Analisi, Controllo E Ricerca",
    "sg:phone":"+39 051 705088",
    "sg:postcode":"40128",
    "sg:province":"Bologna",
    "wof:name":"Ist. Naz. Studio E Controllo Tumori B. Ramazzini Scrl",
    "wof:placetype":"venue"
},
  "geometry": {"coordinates":[11.35638,44.54652],"type":"Point"}
}