{
  "type": "Feature",
  "properties": {
    "addr:full":"Via Don Battistoni 1 60035 Jesi Jesi Ancona 60035",
    "addr:housenumber":"1",
    "addr:postcode":"60035;60035",
    "addr:street":"Via Don Battistoni",
    "iso:country":"IT",
    "sg:address":"Via Don Battistoni 1 60035 Jesi",
    "sg:city":"Jesi",
    "sg:orig_category":"Centrifuges For The Food Industry",
    "sg:phone":"+39 0731 231139",
    "sg:postcode":"60035",
    "sg:province":"Ancona",
    "sg:website":"www.pieralisi.it",
    "wof:name":"Gruppo Pieralisi",
    "wof:placetype":"venue"
},
  "geometry": {"coordinates":[13.266004,43.535931],"type":"Point"}
}