{
  "type": "Feature",
  "properties": {
    "iso:country":"IT",
    "sg:address":"00034 Colleferro",
    "sg:city":"Colleferro",
    "sg:orig_category":"Macchine, Impianti Ed Attrezzature Per Agricoltura E Zootecnia",
    "sg:phone":"+39 06 9730 5979",
    "sg:postcode":"00034",
    "sg:province":"Roma",
    "wof:name":"De.mar. Srl - Casazza Marco",
    "wof:placetype":"venue"
},
  "geometry": {"coordinates":[13.001133,41.742126],"type":"Point"}
}