{
  "type": "Feature",
  "properties": {
    "iso:country":"IT",
    "sg:address":"00181 Roma",
    "sg:city":"Roma",
    "sg:orig_category":"Agenzie D'affari E Servizi Commerciali",
    "sg:phone":"+39 06 7814 7089",
    "sg:postcode":"00181",
    "sg:province":"Roma",
    "wof:name":"Adecco Spa - Horeca Centro Sud",
    "wof:placetype":"venue"
},
  "geometry": {"coordinates":[12.43149,41.84409],"type":"Point"}
}