{
  "type": "Feature",
  "properties": {
    "addr:full":"23875 Osnago Osnago Lecco 23875",
    "addr:postcode":"23875;23875",
    "iso:country":"IT",
    "sg:address":"23875 Osnago",
    "sg:city":"Osnago",
    "sg:orig_category":"Salotti, Poltrone, Sedie E Tavoli",
    "sg:phone":"+39 039 587286",
    "sg:postcode":"23875",
    "sg:province":"Lecco",
    "sg:website":"http://www.alidata.it",
    "wof:name":"Fratelli Mandelli Snc",
    "wof:placetype":"venue"
},
  "geometry": {"coordinates":[9.400733,45.692883],"type":"Point"}
}