{
  "type": "Feature",
  "properties": {
    "iso:country":"IT",
    "sg:address":"00156 Roma",
    "sg:city":"Roma",
    "sg:orig_category":"Pubblica Amministrazione",
    "sg:phone":"+39 06 4129 4192",
    "sg:postcode":"00156",
    "sg:province":"Roma",
    "wof:name":"Ente Regionale Di Sviluppo Agrigolo Della Lombardia",
    "wof:placetype":"venue"
},
  "geometry": {"coordinates":[12.6050672531,41.9300003052],"type":"Point"}
}