{
  "type": "Feature",
  "properties": {
    "addr:full":"36030 Monte Di Malo Monte di Malo Vicenza 36030",
    "addr:housenumber":"36030",
    "addr:postcode":"36030",
    "addr:street":"Monte",
    "iso:country":"IT",
    "sg:address":"36030 Monte Di Malo",
    "sg:city":"Monte di Malo",
    "sg:orig_category":"Materiali Edili",
    "sg:phone":"+39 0445 607951",
    "sg:postcode":"36030",
    "sg:province":"Vicenza",
    "wof:name":"C.g.a. Consorzio Gestione Argille",
    "wof:placetype":"venue"
},
  "geometry": {"coordinates":[11.392077,45.654514],"type":"Point"}
}