{
  "type": "Feature",
  "properties": {
    "addr:full":"Via Sacco E Vanzetti 45 41042 Fiorano Modenese Fiorano Modenese Modena 41042",
    "addr:housenumber":"45",
    "addr:postcode":"41042;41042",
    "addr:street":"Via Sacco E Vanzetti",
    "iso:country":"IT",
    "sg:address":"Via Sacco E Vanzetti 45 41042 Fiorano Modenese",
    "sg:city":"Fiorano Modenese",
    "sg:orig_category":"Ceramic Printing Services",
    "sg:phone":"+39 0536 831119",
    "sg:postcode":"41042",
    "sg:province":"Modena",
    "wof:name":"P.s.a. Di Prampolini & C. Snc",
    "wof:placetype":"venue"
},
  "geometry": {"coordinates":[10.820666,44.558735],"type":"Point"}
}