{
  "type": "Feature",
  "properties": {
    "iso:country":"IT",
    "sg:address":"37066 Sommacampagna",
    "sg:city":"Sommacampagna",
    "sg:orig_category":"Ospedali E Servizi Sanitari",
    "sg:phone":"+39 045 515930",
    "sg:postcode":"37066",
    "sg:province":"Verona",
    "wof:name":"Studio Professionisti Chiropratici Associati",
    "wof:placetype":"venue"
},
  "geometry": {"coordinates":[10.845907,45.409306],"type":"Point"}
}