{
  "type": "Feature",
  "properties": {
    "iso:country":"IT",
    "sg:address":"Via Vannucci Pietro 14 25134 Brescia",
    "sg:city":"Brescia",
    "sg:classifiers":[
        {
            "category":"Utilities",
            "subcategory":"Water",
            "type":"Services"
        }
    ],
    "sg:phone":"+39 030 230 4399",
    "sg:postcode":"25134",
    "sg:province":"Brescia",
    "sg:tags":[
        "bevel",
        "gear",
        "motor"
    ],
    "wof:name":"Rossini Ingranaggi Srl",
    "wof:placetype":"venue"
},
  "geometry": {"coordinates":[10.222958,45.539829],"type":"Point"}
}