{
  "type": "Feature",
  "properties": {
    "iso:country":"IT",
    "sg:address":"00187 Roma",
    "sg:city":"Roma",
    "sg:classifiers":[
        {
            "category":"Health Services",
            "subcategory":"Nursing And Care Facility",
            "type":"Services"
        }
    ],
    "sg:phone":"+39 06 482 5151",
    "sg:postcode":"00187",
    "sg:province":"Roma",
    "sg:tags":[
        "case",
        "cura",
        "private",
        "di"
    ],
    "wof:name":"Tosinvest Sanita' Srl",
    "wof:placetype":"venue"
},
  "geometry": {"coordinates":[12.491888,41.904652],"type":"Point"}
}