{
  "type": "Feature",
  "properties": {
    "addr:full":"13886 Viverone Viverone Biella 13886",
    "addr:postcode":"13886;13886",
    "iso:country":"IT",
    "sg:address":"13886 Viverone",
    "sg:city":"Viverone",
    "sg:classifiers":[
        {
            "category":"Bars & Pubs",
            "subcategory":"Champagne Bar",
            "type":"Food & Drink"
        }
    ],
    "sg:phone":"+39 0161 987035",
    "sg:postcode":"13886",
    "sg:province":"Biella",
    "sg:tags":[
        "caffe'",
        "e"
    ],
    "wof:name":"Bar Gelateria Marinella",
    "wof:placetype":"venue"
},
  "geometry": {"coordinates":[8.045958,45.42202],"type":"Point"}
}