{
  "type": "Feature",
  "properties": {
    "addr:full":"Via Edison 2 20040 Burago Di Molgora Burago di Molgora Milano 20040",
    "addr:housenumber":"2",
    "addr:postcode":"20040;20040",
    "addr:street":"Via Edison",
    "iso:country":"IT",
    "sg:address":"Via Edison 2 20040 Burago Di Molgora",
    "sg:city":"Burago di Molgora",
    "sg:classifiers":[
        {
            "category":"Home & Garden",
            "subcategory":"Household Appliances",
            "type":"Retail Goods"
        }
    ],
    "sg:phone":"+39 039 629021",
    "sg:postcode":"20040",
    "sg:province":"Milano",
    "sg:tags":[
        "thermostat"
    ],
    "sg:website":"www.technologygroup.it",
    "wof:name":"T & G S.p.a.",
    "wof:placetype":"venue"
},
  "geometry": {"coordinates":[9.188141,45.463688],"type":"Point"}
}