{
  "type": "Feature",
  "properties": {
    "addr:full":"Localita' Pian Da Lago 32043 Cortina D'ampezzo Belluno 32043",
    "addr:postcode":"32043;32043",
    "addr:street":"Localita ' Pian Da Lago",
    "iso:country":"IT",
    "sg:address":"Localita' Pian Da Lago 32043 Cortina D'ampezzo",
    "sg:classifiers":[
        {
            "category":"Shopping",
            "subcategory":"Clothing, Apparel, & Fashions",
            "type":"Retail Goods"
        }
    ],
    "sg:phone":"+39 390 436 2300",
    "sg:postcode":"32043",
    "sg:province":"Belluno",
    "sg:tags":[
        "clothes"
    ],
    "wof:name":"Dialto Snc",
    "wof:placetype":"venue"
},
  "geometry": {"coordinates":[12.151714,46.509552],"type":"Point"}
}