{
  "type": "Feature",
  "properties": {
    "addr:full":"25050 Provaglio D'iseo Brescia 25050",
    "addr:postcode":"25050;25050",
    "iso:country":"IT",
    "sg:address":"25050 Provaglio D'iseo",
    "sg:orig_category":"Abbigliamento Intimo, Calze E Costumi Da Bagno. Accessori Moda D'abbigliamento",
    "sg:phone":"+39 030 983896",
    "sg:postcode":"25050",
    "sg:province":"Brescia",
    "wof:name":"Martina Abele",
    "wof:placetype":"venue"
},
  "geometry": {"coordinates":[10.042071,45.634613],"type":"Point"}
}