{
  "type": "Feature",
  "properties": {
    "iso:country":"IT",
    "sg:address":"30030 Vigonovo",
    "sg:city":"Vigonovo",
    "sg:orig_category":"Macchine, Impianti Ed Attrezzature Per Industria Alimentare E Bevande. Elettrodomestici. Macchine E Impianti Per Attivita' Commerciali Ed Artigianali",
    "sg:phone":"+39 049 983 1476",
    "sg:postcode":"30030",
    "sg:province":"Venezia",
    "wof:name":"Poletti Lorenzo",
    "wof:placetype":"venue"
},
  "geometry": {"coordinates":[11.998478,45.430702],"type":"Point"}
}