{
  "type": "Feature",
  "properties": {
    "addr:full":"04100 Latina Latina Latina 04100",
    "addr:postcode":"04100;04100",
    "iso:country":"IT",
    "sg:address":"04100 Latina",
    "sg:city":"Latina",
    "sg:orig_category":"Abbigliamento Sportivo, Jeans E Casuals - Vendita Al Dettaglio",
    "sg:phone":"+39 0773 486456",
    "sg:postcode":"04100",
    "sg:province":"Latina",
    "sg:website":"http://www.sport85.it",
    "wof:name":"Sport'85 Srl",
    "wof:placetype":"venue"
},
  "geometry": {"coordinates":[12.876109,41.477413],"type":"Point"}
}