{
  "type": "Feature",
  "properties": {
    "addr:full":"Via Cavour 3 20040 Briosco Briosco Milano 20040",
    "addr:housenumber":"3",
    "addr:postcode":"20040;20040",
    "addr:street":"Via Cavour",
    "iso:country":"IT",
    "sg:address":"Via Cavour 3 20040 Briosco",
    "sg:city":"Briosco",
    "sg:classifiers":[
        {
            "category":"Banks & Credit Unions",
            "subcategory":"Investment Brokerage",
            "type":"Services"
        }
    ],
    "sg:phone":"+39 036 295 8225",
    "sg:postcode":"20040",
    "sg:province":"Milano",
    "sg:tags":[
        "filters"
    ],
    "sg:website":"www.steelworksitalia.com",
    "wof:name":"Micronsep Srl",
    "wof:placetype":"venue"
},
  "geometry": {"coordinates":[9.2370586395,45.7103042603],"type":"Point"}
}