{
  "type": "Feature",
  "properties": {
    "iso:country":"IT",
    "sg:address":"Via Rivale 63 30036 Santa Maria Di Sala",
    "sg:city":"Santa Maria di Sala",
    "sg:classifiers":[
        {
            "category":"Manufacturing",
            "subcategory":"Metals",
            "type":"Manufacturing & Wholesale Goods"
        }
    ],
    "sg:phone":"+39 041 486933",
    "sg:postcode":"30036",
    "sg:province":"Venezia",
    "sg:tags":[
        "mould",
        "aluminium",
        "industry",
        "plastic"
    ],
    "sg:website":"www.comel.it",
    "wof:name":"Comel Snc Di Pellizzaro V.& C",
    "wof:placetype":"venue"
},
  "geometry": {"coordinates":[12.029387,45.455723],"type":"Point"}
}