{
  "type": "Feature",
  "properties": {
    "addr:full":"10020 Cambiano Cambiano Torino 10020",
    "addr:postcode":"10020;10020",
    "iso:country":"IT",
    "sg:address":"10020 Cambiano",
    "sg:city":"Cambiano",
    "sg:orig_category":"Frigotecnica, Apparecchiature E Servizi. Arredi Ed Attrezzature Per Uffici",
    "sg:phone":"+39 011 944 1825",
    "sg:postcode":"10020",
    "sg:province":"Torino",
    "wof:name":"Piovano Gianfranco",
    "wof:placetype":"venue"
},
  "geometry": {"coordinates":[7.7731294632,44.9693870544],"type":"Point"}
}