{
  "type": "Feature",
  "properties": {
    "addr:full":"20037 Paderno Dugnano Paderno Dugnano Milano 20037",
    "addr:postcode":"20037;20037",
    "iso:country":"IT",
    "sg:address":"20037 Paderno Dugnano",
    "sg:city":"Paderno Dugnano",
    "sg:orig_category":"Prodotti E Manufatti In Gomma",
    "sg:phone":"+39 02 910 1520",
    "sg:postcode":"20037",
    "sg:province":"Milano",
    "wof:name":"Zambelli Alcide & Ugo (s.d.f.)",
    "wof:placetype":"venue"
},
  "geometry": {"coordinates":[9.2013778687,45.5587348938],"type":"Point"}
}