{
  "type": "Feature",
  "properties": {
    "iso:country":"IT",
    "sg:address":"95016 Mascali",
    "sg:city":"Mascali",
    "sg:orig_category":"Elettrotecnica Professionale E Di Consumo. Forniture Alle Strutture Ricettive. Arredi Ed Attrezzature Per Attivita' Commerciali Ed Artigianali",
    "sg:phone":"+39 095 969209",
    "sg:postcode":"95016",
    "sg:province":"Catania",
    "wof:name":"C. R. Service Srl",
    "wof:placetype":"venue"
},
  "geometry": {"coordinates":[15.179015,37.803528],"type":"Point"}
}