{
  "type": "Feature",
  "properties": {
    "iso:country":"IT",
    "sg:address":"21018 Sesto Calende",
    "sg:city":"Sesto Calende",
    "sg:orig_category":"Arredamenti - Vendita Al Dettaglio",
    "sg:phone":"+39 0331 924760",
    "sg:postcode":"21018",
    "sg:province":"Varese",
    "wof:name":"Mobili Sala Di Sala Massimo",
    "wof:placetype":"venue"
},
  "geometry": {"coordinates":[8.647105,45.724266],"type":"Point"}
}