{
  "type": "Feature",
  "properties": {
    "addr:full":"37023 Grezzana Grezzana Verona 37023",
    "addr:postcode":"37023;37023",
    "iso:country":"IT",
    "sg:address":"37023 Grezzana",
    "sg:city":"Grezzana",
    "sg:orig_category":"Prodotti Alimentari",
    "sg:phone":"+39 045 865 0327",
    "sg:postcode":"37023",
    "sg:province":"Verona",
    "sg:website":"http://www.saladine.it",
    "wof:name":"Saladine Srl",
    "wof:placetype":"venue"
},
  "geometry": {"coordinates":[11.0033550262,45.5411338806],"type":"Point"}
}