{
  "type": "Feature",
  "properties": {
    "iso:country":"IT",
    "sg:address":"V. Fornaci 25040 Corte Franca",
    "sg:city":"Corte Franca",
    "sg:classifiers":[
        {
            "category":"Professional",
            "subcategory":"Engineering",
            "type":"Services"
        }
    ],
    "sg:phone":"+39 030 988 4298",
    "sg:postcode":"25040",
    "sg:province":"Brescia",
    "sg:tags":[
        "machine",
        "-",
        "mechanical"
    ],
    "sg:website":"http://www.four-emme.com:ws_end: :mark:ws:http://www.paginegialle.it/fouremme",
    "wof:name":"Four-emme Snc",
    "wof:placetype":"venue"
},
  "geometry": {"coordinates":[10.018037,45.635208],"type":"Point"}
}