{
  "type": "Feature",
  "properties": {
    "iso:country":"IT",
    "sg:address":"20017 Rho",
    "sg:city":"Rho",
    "sg:orig_category":"Servizi E Lavori Per Abbigliamento E Pelletterie",
    "sg:phone":"+39 02 930 3108",
    "sg:postcode":"20017",
    "sg:province":"Milano",
    "wof:name":"Leccardi Luigi Maurizio",
    "wof:placetype":"venue"
},
  "geometry": {"coordinates":[9.065959,45.543602],"type":"Point"}
}