{
  "type": "Feature",
  "properties": {
    "iso:country":"IT",
    "sg:address":"20134 Milano",
    "sg:city":"Milano",
    "sg:orig_category":"Apparecchiature E Sistemi Per Magazzinaggio E Movimentazione",
    "sg:phone":"+39 02 215 4211",
    "sg:postcode":"20134",
    "sg:province":"Milano",
    "wof:name":"Traslochi Piola Di Lo Sardo Luca",
    "wof:placetype":"venue"
},
  "geometry": {"coordinates":[9.243004,45.489147],"type":"Point"}
}