{
  "type": "Feature",
  "properties": {
    "addr:full":"30014 Cavarzere Cavarzere Venezia 30014",
    "addr:housenumber":"30014",
    "addr:postcode":"30014",
    "addr:street":"Cavarzere Cavarzere Venezia",
    "iso:country":"IT",
    "sg:address":"30014 Cavarzere",
    "sg:city":"Cavarzere",
    "sg:orig_category":"Forniture Per Agricoltura E Zootecnia. Animali Domestici",
    "sg:phone":"+39 0426 310996",
    "sg:postcode":"30014",
    "sg:province":"Venezia",
    "wof:name":"Essegi S.n.c.",
    "wof:placetype":"venue"
},
  "geometry": {"coordinates":[12.310251236,45.5511283875],"type":"Point"}
}