{
  "type": "Feature",
  "properties": {
    "iso:country":"IT",
    "sg:address":"24060 Sovere",
    "sg:city":"Sovere",
    "sg:orig_category":"Articoli Pulizia. Forniture Per Attivita' Industriali",
    "sg:phone":"+39 035 981177",
    "sg:postcode":"24060",
    "sg:province":"Bergamo",
    "wof:name":"P.d.m. Di Malacrida Gianbattista Angelo & C. (s.n.c.)",
    "wof:placetype":"venue"
},
  "geometry": {"coordinates":[9.935541,45.788876],"type":"Point"}
}