{
  "type": "Feature",
  "properties": {
    "iso:country":"IT",
    "sg:address":"00142 Roma",
    "sg:city":"Roma",
    "sg:orig_category":"Prodotti Finiti Stampati. Shopping. Regalistica Aziendale",
    "sg:phone":"+39 06 5195 6023",
    "sg:postcode":"00142",
    "sg:province":"Roma",
    "wof:name":"La Cornucopia",
    "wof:placetype":"venue"
},
  "geometry": {"coordinates":[12.5040130615,41.8364372253],"type":"Point"}
}