{
  "type": "Feature",
  "properties": {
    "iso:country":"IT",
    "sg:address":"21020 Casale Litta",
    "sg:city":"Casale Litta",
    "sg:orig_category":"Termotecnica E Riscaldamento, Apparecchiature E Servizi",
    "sg:phone":"+39 0332 943111",
    "sg:postcode":"21020",
    "sg:province":"Varese",
    "sg:website":"http://www.prealpipetroli.it",
    "wof:name":"Prealpipetroli Srl",
    "wof:placetype":"venue"
},
  "geometry": {"coordinates":[8.742355,45.754776],"type":"Point"}
}