{
  "type": "Feature",
  "properties": {
    "iso:country":"IT",
    "sg:address":"24100 Bergamo",
    "sg:orig_category":"Lavorazioni Metalli, Stampaggio E Saldatura",
    "sg:phone":"+39 030 743 8910",
    "sg:province":"BG",
    "wof:name":"Sig-mac Srl",
    "wof:placetype":"venue"
},
  "geometry": {"coordinates":[9.891342,45.622124],"type":"Point"}
}