{
  "type": "Feature",
  "properties": {
    "iso:country":"IT",
    "sg:address":"98123 Messina",
    "sg:city":"Messina",
    "sg:orig_category":"Non-classified Establishments",
    "sg:phone":"+39 090 675682",
    "sg:postcode":"98123",
    "sg:province":"Messina",
    "wof:name":"Ceramiche Artigianali Eredi M. Ruggeri Sdf",
    "wof:placetype":"venue"
},
  "geometry": {"coordinates":[15.558221,38.184521],"type":"Point"}
}