{
  "type": "Feature",
  "properties": {
    "iso:country":"IT",
    "sg:address":"71, V. Pisacane 65123 Pescara",
    "sg:city":"Pescara",
    "sg:classifiers":[
        {
            "category":"Utilities",
            "subcategory":"Telephone",
            "type":"Services"
        }
    ],
    "sg:phone":"+39 390 857 4356",
    "sg:postcode":"65123",
    "sg:province":"Pescara",
    "sg:tags":[
        "telecommunication"
    ],
    "sg:website":"http://www.telesis.it",
    "wof:name":"Telesis Srl",
    "wof:placetype":"venue"
},
  "geometry": {"coordinates":[14.196421,42.480396],"type":"Point"}
}