{
  "type": "Feature",
  "properties": {
    "iso:country":"IT",
    "sg:address":"Via Bono Cairoli Adelaide 28 20127 Milano",
    "sg:city":"Milano",
    "sg:classifiers":[
        {
            "category":"Manufacturing",
            "subcategory":"Food",
            "type":"Manufacturing & Wholesale Goods"
        }
    ],
    "sg:phone":"+39 02 2682 7745",
    "sg:postcode":"20127",
    "sg:province":"Milano",
    "sg:tags":[
        "agriculture",
        "industry",
        "installation"
    ],
    "sg:website":"www.pancolini.it",
    "wof:name":"Ing. S. Pancolini Srl",
    "wof:placetype":"venue"
},
  "geometry": {"coordinates":[9.225825,45.500267],"type":"Point"}
}