{
  "type": "Feature",
  "properties": {
    "iso:country":"IT",
    "sg:address":"Via Don Minzoni 108b 42043 Gattatico",
    "sg:classifiers":[
        {
            "category":"Autos & Motor Vehicles",
            "subcategory":"Auto Supplies",
            "type":"Retail Goods"
        }
    ],
    "sg:phone":"+39 0522 671800",
    "sg:postcode":"42043",
    "sg:province":"Reggio Nell'Emilia",
    "sg:tags":[
        "automobile",
        "accessory"
    ],
    "wof:name":"Grossi Snc Di Grossi Lorenza & C.",
    "wof:placetype":"venue"
},
  "geometry": {"coordinates":[10.627794,44.696228],"type":"Point"}
}