{
  "type": "Feature",
  "properties": {
    "iso:country":"IT",
    "sg:address":"61049 Urbania",
    "sg:city":"Urbania",
    "sg:orig_category":"Abbigliamento Esterno, Maglierie E Pelliccerie. Shopping",
    "sg:phone":"+39 0722 319260",
    "sg:postcode":"61049",
    "sg:province":"Pesaro E Urbino",
    "wof:name":"Italian Fashion Spa",
    "wof:placetype":"venue"
},
  "geometry": {"coordinates":[12.484241,43.611721],"type":"Point"}
}