{
  "type": "Feature",
  "properties": {
    "iso:country":"IT",
    "sg:address":"47/a, Via Callalta 31037 Loria",
    "sg:city":"Loria",
    "sg:classifiers":[
        {
            "category":"Manufacturing",
            "subcategory":"Metals",
            "type":"Manufacturing & Wholesale Goods"
        }
    ],
    "sg:phone":"+39 0423 755332",
    "sg:postcode":"31037",
    "sg:province":"Treviso",
    "sg:tags":[
        "metallurgy",
        "metalworking"
    ],
    "wof:name":"International Steel Co. S.p.a.",
    "wof:placetype":"venue"
},
  "geometry": {"coordinates":[12.2420721054,45.6662864685],"type":"Point"}
}