{
  "type": "Feature",
  "properties": {
    "iso:country":"IT",
    "sg:address":"33, Vicolo Emilia Romagna 41049 Sassuolo",
    "sg:city":"Sassuolo",
    "sg:classifiers":[
        {
            "category":"Professional",
            "subcategory":"Engineering",
            "type":"Services"
        }
    ],
    "sg:phone":"+39 0536 804905",
    "sg:postcode":"41049",
    "sg:province":"Modena",
    "sg:tags":[
        "machine",
        "-",
        "mechanical"
    ],
    "wof:name":"Spray Dry (s.r.l.)",
    "wof:placetype":"venue"
},
  "geometry": {"coordinates":[10.794613,44.564491],"type":"Point"}
}