{
  "type": "Feature",
  "properties": {
    "addr:full":"00163 Roma Roma Roma 00163",
    "addr:postcode":"00163;00163",
    "iso:country":"IT",
    "sg:address":"00163 Roma",
    "sg:city":"Roma",
    "sg:classifiers":[
        {
            "category":"Utilities",
            "subcategory":"Refuse",
            "type":"Services"
        }
    ],
    "sg:phone":"+39 06 6577 1249",
    "sg:postcode":"00163",
    "sg:province":"Roma",
    "sg:tags":[
        "auxiliary",
        "disposal",
        "surveillance",
        "environmental",
        "protection",
        "cleaning",
        "maintenance",
        "works"
    ],
    "wof:name":"Petro Service 90 Srl",
    "wof:placetype":"venue"
},
  "geometry": {"coordinates":[12.369645,41.863174],"type":"Point"}
}