{
  "type": "Feature",
  "properties": {
    "iso:country":"IT",
    "sg:address":"91011 Alcamo",
    "sg:city":"Alcamo",
    "sg:orig_category":"Antincendio - Impianti, Attrezzature E Materiali",
    "sg:phone":"+39 0924 514033",
    "sg:postcode":"91011",
    "sg:province":"Trapani",
    "wof:name":"Imet Srl",
    "wof:placetype":"venue"
},
  "geometry": {"coordinates":[12.964372,37.974297],"type":"Point"}
}