{
  "type": "Feature",
  "properties": {
    "iso:country":"IT",
    "sg:address":"33170 Pordenone",
    "sg:city":"Pordenone",
    "sg:orig_category":"Non-classified Establishments",
    "sg:phone":"+39 0434 28577",
    "sg:postcode":"33170",
    "sg:province":"Pordenone",
    "sg:website":"http://www.cantoncolori.com",
    "wof:name":"Ven.co. Srl",
    "wof:placetype":"venue"
},
  "geometry": {"coordinates":[12.613997,45.789448],"type":"Point"}
}