{
  "type": "Feature",
  "properties": {
    "iso:country":"IT",
    "sg:address":"24, Via Beniamino Franklin 41012 Carpi",
    "sg:city":"Carpi",
    "sg:classifiers":[
        {
            "category":"Real Estate",
            "subcategory":"Architect",
            "type":"Services"
        }
    ],
    "sg:phone":"+39 39059645193",
    "sg:postcode":"41012",
    "sg:province":"Modena",
    "sg:tags":[
        "textile",
        "clothing"
    ],
    "wof:name":"Penta Moda Srl",
    "wof:placetype":"venue"
},
  "geometry": {"coordinates":[10.854342,44.780701],"type":"Point"}
}