{
  "type": "Feature",
  "properties": {
    "addr:full":"23, Via Roma 12030 Caramagna Piemonte Caramagna Piemonte Cuneo 12030",
    "addr:postcode":"12030;piemonte;12030",
    "addr:street":"Via Roma;Piemonte",
    "iso:country":"IT",
    "sg:address":"23, Via Roma 12030 Caramagna Piemonte",
    "sg:city":"Caramagna Piemonte",
    "sg:classifiers":[
        {
            "category":"Manufacturing",
            "subcategory":"Rubber & Plastics",
            "type":"Manufacturing & Wholesale Goods"
        }
    ],
    "sg:phone":"+39 0172 829011",
    "sg:postcode":"12030",
    "sg:province":"Cuneo",
    "wof:name":"Lamicolor S.p.a.",
    "wof:placetype":"venue"
},
  "geometry": {"coordinates":[7.7428240776,44.7815246582],"type":"Point"}
}