{
  "type": "Feature",
  "properties": {
    "iso:country":"IT",
    "sg:address":"93012 Gela",
    "sg:city":"Gela",
    "sg:orig_category":"Biancheria Intima Ed Abbigliamento Intimo - Vendita Al Dettaglio",
    "sg:phone":"+39 349 157 3265",
    "sg:postcode":"93012",
    "sg:province":"Caltanissetta",
    "wof:name":"Bilardo Domenico",
    "wof:placetype":"venue"
},
  "geometry": {"coordinates":[14.23258,37.073418],"type":"Point"}
}