{
  "type": "Feature",
  "properties": {
    "iso:country":"IT",
    "sg:address":"06083 Bastia",
    "sg:city":"Bastia",
    "sg:orig_category":"Prodotti Di Base E Forniture Per Industria Alimentare E Bevande",
    "sg:phone":"+39 075 800 2342",
    "sg:postcode":"06083",
    "sg:province":"Perugia",
    "wof:name":"Rossi Tecnocarni S.n.c.",
    "wof:placetype":"venue"
},
  "geometry": {"coordinates":[12.5499696732,43.0658683777],"type":"Point"}
}