{
  "type": "Feature",
  "properties": {
    "iso:country":"IT",
    "sg:address":"00185 Roma",
    "sg:city":"Roma",
    "sg:orig_category":"Forniture Per Agricoltura E Zootecnia. Prodotti Chimici Secondari",
    "sg:phone":"+39 06 480726",
    "sg:postcode":"00185",
    "sg:province":"Roma",
    "wof:name":"Arsol (s.p.a.)",
    "wof:placetype":"venue"
},
  "geometry": {"coordinates":[12.5019054413,41.9056396484],"type":"Point"}
}