{
  "type": "Feature",
  "properties": {
    "iso:country":"IT",
    "sg:address":"00159 Roma",
    "sg:city":"Roma",
    "sg:orig_category":"Etichette",
    "sg:phone":"+39 06 439 0221",
    "sg:postcode":"00159",
    "sg:province":"Roma",
    "sg:website":"http://www.etikaromana.it",
    "wof:name":"Etika Romana Srl",
    "wof:placetype":"venue"
},
  "geometry": {"coordinates":[12.537641,41.905857],"type":"Point"}
}