{
  "type": "Feature",
  "properties": {
    "iso:country":"IT",
    "sg:address":"Via Felice Cavallotti 19 20046 Biassono",
    "sg:city":"Biassono",
    "sg:classifiers":[
        {
            "category":"Banks & Credit Unions",
            "subcategory":"Investment Brokerage",
            "type":"Services"
        }
    ],
    "sg:phone":"+39 039 220041",
    "sg:postcode":"20046",
    "sg:province":"Milano",
    "sg:tags":[
        "table",
        "lamp"
    ],
    "sg:website":"www.album.it",
    "wof:name":"Album Srl",
    "wof:placetype":"venue"
},
  "geometry": {"coordinates":[9.260104,45.629421],"type":"Point"}
}