{
  "type": "Feature",
  "properties": {
    "iso:country":"IT",
    "sg:address":"Via Pitagora 27 35030 Rubano",
    "sg:city":"Rubano",
    "sg:classifiers":[
        {
            "category":"Utilities",
            "subcategory":"Natural Gas",
            "type":"Services"
        }
    ],
    "sg:phone":"+39 049 897 5462",
    "sg:postcode":"35030",
    "sg:province":"Padova",
    "sg:tags":[
        "boiler",
        "central",
        "fired",
        "heating"
    ],
    "sg:website":"www.boldrintech.it",
    "wof:name":"Boldrin Srl",
    "wof:placetype":"venue"
},
  "geometry": {"coordinates":[11.835303,45.418938],"type":"Point"}
}