{
  "type": "Feature",
  "properties": {
    "addr:full":"35010 Carmignano Di Brenta Carmignano di Brenta Padova 35010",
    "addr:postcode":"35010;35010",
    "addr:street":"Di Brenta",
    "iso:country":"IT",
    "sg:address":"35010 Carmignano Di Brenta",
    "sg:city":"Carmignano di Brenta",
    "sg:orig_category":"Medicinali E Prodotti Parafarmaceutici",
    "sg:phone":"+39 049 595 7029",
    "sg:postcode":"35010",
    "sg:province":"Padova",
    "wof:name":"Farmacia Favaro Dr. Franca",
    "wof:placetype":"venue"
},
  "geometry": {"coordinates":[11.7069721222,45.6302261353],"type":"Point"}
}