{
  "type": "Feature",
  "properties": {
    "addr:full":"70044 Polignano A Mare Polignano a Mare Bari 70044",
    "addr:postcode":"70044;70044",
    "iso:country":"IT",
    "sg:address":"70044 Polignano A Mare",
    "sg:city":"Polignano a Mare",
    "sg:orig_category":"Fiori E Piante - Ingrosso",
    "sg:phone":"+39 080 424 7201",
    "sg:postcode":"70044",
    "sg:province":"Bari",
    "wof:name":"Talenti Pasquale",
    "wof:placetype":"venue"
},
  "geometry": {"coordinates":[17.1839027405,40.966835022],"type":"Point"}
}