{
  "type": "Feature",
  "properties": {
    "iso:country":"IT",
    "sg:address":"Via G. Boccaccio 9 42024 Castelnovo Di Sotto",
    "sg:classifiers":[
        {
            "category":"Wholesale",
            "subcategory":"Farm Supplies",
            "type":"Manufacturing & Wholesale Goods"
        }
    ],
    "sg:phone":"+39 0522 682173",
    "sg:postcode":"42024",
    "sg:province":"Reggio Nell'Emilia",
    "sg:tags":[
        "agricultural",
        "part",
        "spare",
        "machinery",
        "accessory"
    ],
    "wof:name":"Officina Meccanica Cucchi S.n.c.",
    "wof:placetype":"venue"
},
  "geometry": {"coordinates":[10.573125,44.796436],"type":"Point"}
}