{
  "type": "Feature",
  "properties": {
    "iso:country":"IT",
    "sg:address":"Via Erba 21 20037 Paderno Dugnano",
    "sg:city":"Paderno Dugnano",
    "sg:classifiers":[
        {
            "category":"Utilities",
            "subcategory":"Natural Gas",
            "type":"Services"
        }
    ],
    "sg:phone":"+39 02 918 5414",
    "sg:postcode":"20037",
    "sg:province":"Milano",
    "sg:tags":[
        "ceiling",
        "lamp"
    ],
    "sg:website":"www.artisticalampadari.it",
    "wof:name":"Artistica Lampadari Snc",
    "wof:placetype":"venue"
},
  "geometry": {"coordinates":[9.190153,45.56889],"type":"Point"}
}