{
  "type": "Feature",
  "properties": {
    "iso:country":"IT",
    "sg:address":"35, Via Firenze 06069 Tuoro Sul Trasimeno",
    "sg:city":"Tuoro sul Trasimeno",
    "sg:classifiers":[
        {
            "category":"Home & Garden",
            "subcategory":"Home Furnishings",
            "type":"Retail Goods"
        }
    ],
    "sg:phone":"+39 39075826239",
    "sg:postcode":"06069",
    "sg:province":"Perugia",
    "sg:tags":[
        "household"
    ],
    "wof:name":"Arreni The Best Di Arreni Maurizio",
    "wof:placetype":"venue"
},
  "geometry": {"coordinates":[12.0625,43.200672],"type":"Point"}
}