{
  "type": "Feature",
  "properties": {
    "iso:country":"IT",
    "sg:address":"15100 Alessandria",
    "sg:city":"Alessandria",
    "sg:orig_category":"Forniture Per Agricoltura E Zootecnia. Animali Domestici",
    "sg:phone":"+39 0131 240973",
    "sg:postcode":"15100",
    "sg:province":"Alessandria",
    "wof:name":"Calcagno Silvia",
    "wof:placetype":"venue"
},
  "geometry": {"coordinates":[8.60846138,44.9021682739],"type":"Point"}
}