{
  "type": "Feature",
  "properties": {
    "iso:country":"IT",
    "sg:address":"36027 Rosa'",
    "sg:orig_category":"Servizi Ausiliari Di Certificati, Riproduzioni, Disegni E Foto",
    "sg:phone":"+39 0424 86173",
    "sg:postcode":"36027",
    "sg:province":"Vicenza",
    "wof:name":"Industrialphoto Sas",
    "wof:placetype":"venue"
},
  "geometry": {"coordinates":[11.761819,45.727962],"type":"Point"}
}