{
  "type": "Feature",
  "properties": {
    "addr:full":"36042 Breganze Breganze Vicenza 36042",
    "addr:postcode":"36042;36042",
    "iso:country":"IT",
    "sg:address":"36042 Breganze",
    "sg:city":"Breganze",
    "sg:orig_category":"Apparecchiature E Sistemi Per Magazzinaggio E Movimentazione",
    "sg:phone":"+39 0445 308096",
    "sg:postcode":"36042",
    "sg:province":"Vicenza",
    "wof:name":"Moro Renato",
    "wof:placetype":"venue"
},
  "geometry": {"coordinates":[11.585725,45.701191],"type":"Point"}
}