{
  "type": "Feature",
  "properties": {
    "addr:full":"10138 Torino Torino Torino 10138",
    "addr:housenumber":"10138",
    "addr:postcode":"10138",
    "iso:country":"IT",
    "sg:address":"10138 Torino",
    "sg:city":"Torino",
    "sg:orig_category":"Minuterie Metalliche E Ferramenta",
    "sg:phone":"+39 011 447 7091",
    "sg:postcode":"10138",
    "sg:province":"Torino",
    "wof:name":"Capella Felice Di Sergio Capella E C. (s.a.s.)",
    "wof:placetype":"venue"
},
  "geometry": {"coordinates":[7.4040775299,45.0849304199],"type":"Point"}
}