{
  "type": "Feature",
  "properties": {
    "iso:country":"IT",
    "sg:address":"23847 Molteno",
    "sg:city":"Molteno",
    "sg:orig_category":"Servizi Ausiliari Di Analisi, Controllo E Ricerca",
    "sg:phone":"+39 031 850026",
    "sg:postcode":"23847",
    "sg:province":"Lecco",
    "wof:name":"D.l.a. S.a.s.",
    "wof:placetype":"venue"
},
  "geometry": {"coordinates":[9.417339,45.830177],"type":"Point"}
}