{
  "type": "Feature",
  "properties": {
    "iso:country":"IT",
    "sg:address":"65020 Rosciano",
    "sg:city":"Rosciano",
    "sg:orig_category":"Servizi E Lavori Per Agricoltura E Zootecnia",
    "sg:phone":"+39 085 850 5171",
    "sg:postcode":"65020",
    "sg:province":"Pescara",
    "wof:name":"Zootecnica Sulpizio S.a.s.",
    "wof:placetype":"venue"
},
  "geometry": {"coordinates":[14.047204,42.32502],"type":"Point"}
}