{
  "type": "Feature",
  "properties": {
    "iso:country":"IT",
    "sg:address":"18038 Sanremo",
    "sg:orig_category":"Petroli, Gas E Combustibili",
    "sg:phone":"+39 0184 573259",
    "sg:postcode":"18038",
    "sg:province":"Imperia",
    "wof:name":"Tommasino Andrea",
    "wof:placetype":"venue"
},
  "geometry": {"coordinates":[7.7741298676,43.8163299561],"type":"Point"}
}