{
  "type": "Feature",
  "properties": {
    "iso:country":"IT",
    "sg:address":"33019 Tricesimo",
    "sg:city":"Tricesimo",
    "sg:orig_category":"Prodotti Alimentari. Shopping",
    "sg:phone":"+39 0432 881744",
    "sg:postcode":"33019",
    "sg:province":"Udine",
    "wof:name":"Savio Franco",
    "wof:placetype":"venue"
},
  "geometry": {"coordinates":[13.2110357285,46.160861969],"type":"Point"}
}