{
  "type": "Feature",
  "properties": {
    "iso:country":"IT",
    "sg:address":"20090 Assago",
    "sg:city":"Assago",
    "sg:orig_category":"Rifiuti Industriali E Speciali Smaltimento E Trattamento - Servizio",
    "sg:phone":"+39 02 4570 2479",
    "sg:postcode":"20090",
    "sg:province":"Milano",
    "wof:name":"Blasotta Giuseppantonio",
    "wof:placetype":"venue"
},
  "geometry": {"coordinates":[9.122666,45.405025],"type":"Point"}
}