{
  "type": "Feature",
  "properties": {
    "iso:country":"IT",
    "sg:address":"89843 Maierato",
    "sg:city":"Maierato",
    "sg:orig_category":"Arredamenti - Vendita Al Dettaglio",
    "sg:phone":"+39 0963 253818",
    "sg:postcode":"89843",
    "sg:province":"Vibo Valentia",
    "wof:name":"Idearredo Di Moschella Antonio",
    "wof:placetype":"venue"
},
  "geometry": {"coordinates":[16.09766,38.67561],"type":"Point"}
}