{
  "type": "Feature",
  "properties": {
    "iso:country":"IT",
    "sg:address":"63020 Monte Giberto",
    "sg:city":"Monte Giberto",
    "sg:orig_category":"Trasporti E Spedizioni Merci",
    "sg:phone":"+39 0734 631895",
    "sg:postcode":"63020",
    "sg:province":"Ascoli Piceno",
    "wof:name":"Concetti Giancarlo Autotrasporti",
    "wof:placetype":"venue"
},
  "geometry": {"coordinates":[13.588907,43.125168],"type":"Point"}
}