{
  "type": "Feature",
  "properties": {
    "addr:full":"36, Via Sbarra 47042 Cesenatico Cesenatico Forl\u00ec-Cesena 47042",
    "addr:postcode":"47042;47042",
    "addr:street":"Via Sbarra",
    "iso:country":"IT",
    "sg:address":"36, Via Sbarra 47042 Cesenatico",
    "sg:city":"Cesenatico",
    "sg:classifiers":[
        {
            "category":"Building & Trades",
            "subcategory":"Construction",
            "type":"Services"
        }
    ],
    "sg:phone":"+39 39054771636",
    "sg:postcode":"47042",
    "sg:province":"Forl\u00ec-Cesena",
    "sg:tags":[
        "work",
        "public"
    ],
    "wof:name":"Ital Games Di Brandinelli Antonio",
    "wof:placetype":"venue"
},
  "geometry": {"coordinates":[12.361233,44.167236],"type":"Point"}
}