{
  "type": "Feature",
  "properties": {
    "iso:country":"IT",
    "sg:address":"00177 Roma",
    "sg:city":"Roma",
    "sg:orig_category":"Articoli Pulizia. Carta, Cartone E Prodotti Primari. Prodotti Cosmetici E Da Toeletta",
    "sg:phone":"+39 06 2440 1243",
    "sg:postcode":"00177",
    "sg:province":"Roma",
    "wof:name":"Paper Comm Di Capozzi Bruno & C.",
    "wof:placetype":"venue"
},
  "geometry": {"coordinates":[12.543642,41.88728],"type":"Point"}
}