{
  "type": "Feature",
  "properties": {
    "addr:full":"00042 Anzio Anzio Roma 00042",
    "addr:postcode":"00042;roma 00042",
    "iso:country":"IT",
    "sg:address":"00042 Anzio",
    "sg:city":"Anzio",
    "sg:orig_category":"Materiali Edili",
    "sg:phone":"+39 06 986 3609",
    "sg:postcode":"00042",
    "sg:province":"Roma",
    "wof:name":"Colonia Luciano",
    "wof:placetype":"venue"
},
  "geometry": {"coordinates":[12.543162,41.950237],"type":"Point"}
}