{
  "type": "Feature",
  "properties": {
    "addr:full":"Via Maiella 73 65010 Spoltore Spoltore Pescara 65010",
    "addr:housenumber":"73",
    "addr:postcode":"65010;65010",
    "addr:street":"Via Maiella",
    "iso:country":"IT",
    "sg:address":"Via Maiella 73 65010 Spoltore",
    "sg:city":"Spoltore",
    "sg:classifiers":[
        {
            "category":"Building & Trades",
            "subcategory":"Plumbing",
            "type":"Services"
        }
    ],
    "sg:phone":"+39 085 497521",
    "sg:postcode":"65010",
    "sg:province":"Pescara",
    "sg:tags":[
        "tank"
    ],
    "sg:website":"www.dizio.it",
    "wof:name":"Di Zio Spa",
    "wof:placetype":"venue"
},
  "geometry": {"coordinates":[14.152276,42.416145],"type":"Point"}
}