{
  "type": "Feature",
  "properties": {
    "iso:country":"IT",
    "sg:address":"64, Via Luigi Einaudi 36040 Brendola",
    "sg:city":"Brendola",
    "sg:classifiers":[
        {
            "category":"Professional",
            "subcategory":"Engineering",
            "type":"Services"
        }
    ],
    "sg:phone":"+39 0444 705811",
    "sg:postcode":"36040",
    "sg:province":"Vicenza",
    "sg:tags":[
        "machine",
        "-",
        "mechanical"
    ],
    "wof:name":"I.m.k.t. S.a.s. Di Dalle Rive Wilma E C.",
    "wof:placetype":"venue"
},
  "geometry": {"coordinates":[11.433217,45.482948],"type":"Point"}
}