{
  "type": "Feature",
  "properties": {
    "iso:country":"IT",
    "sg:address":"40125 Bologna",
    "sg:city":"Bologna",
    "sg:orig_category":"Hobbistica",
    "sg:phone":"+39 051 263433",
    "sg:postcode":"40125",
    "sg:province":"Bologna",
    "wof:name":"Animalia",
    "wof:placetype":"venue"
},
  "geometry": {"coordinates":[11.31211,44.521149],"type":"Point"}
}