{
  "type": "Feature",
  "properties": {
    "iso:country":"IT",
    "sg:address":"20121 Milano",
    "sg:city":"Milano",
    "sg:orig_category":"Musica. Shopping",
    "sg:phone":"+39 02 878831",
    "sg:postcode":"20121",
    "sg:province":"Milano",
    "wof:name":"Mariposa S.r.l.",
    "wof:placetype":"venue"
},
  "geometry": {"coordinates":[9.1918592453,45.4654502869],"type":"Point"}
}