{
  "type": "Feature",
  "properties": {
    "iso:country":"IT",
    "sg:address":"80138 Napoli",
    "sg:city":"Napoli",
    "sg:orig_category":"Arredamenti E Mobili Professionali. Complementi Di Arredamento",
    "sg:phone":"+39 081 420 1162",
    "sg:postcode":"80138",
    "sg:province":"Napoli",
    "wof:name":"Russo Raffaele Arredi E Paramenti Sacri Sas",
    "wof:placetype":"venue"
},
  "geometry": {"coordinates":[14.258491,40.848145],"type":"Point"}
}