{
  "type": "Feature",
  "properties": {
    "iso:country":"IT",
    "sg:address":"Via Colombo Cristoforo 35043 Monselice",
    "sg:city":"Monselice",
    "sg:classifiers":[
        {
            "category":"Personal",
            "subcategory":"Shoe Repair & Shine",
            "type":"Services"
        }
    ],
    "sg:phone":"+39 39042973442",
    "sg:postcode":"35043",
    "sg:province":"Padova",
    "sg:tags":[
        "leather"
    ],
    "wof:name":"Euroborse (s.n.c.)",
    "wof:placetype":"venue"
},
  "geometry": {"coordinates":[11.826052,45.284893],"type":"Point"}
}