{
  "type": "Feature",
  "properties": {
    "addr:full":"10125 Torino Torino Torino 10125",
    "addr:postcode":"10125;10125",
    "iso:country":"IT",
    "sg:address":"10125 Torino",
    "sg:city":"Torino",
    "sg:orig_category":"Non-classified Establishments",
    "sg:phone":"+39 011 669 0599",
    "sg:postcode":"10125",
    "sg:province":"Torino",
    "wof:name":"Tregi' - L'isola Del Bambu'",
    "wof:placetype":"venue"
},
  "geometry": {"coordinates":[7.678753,45.053337],"type":"Point"}
}