{
  "type": "Feature",
  "properties": {
    "addr:full":"20143 Milano Milano Milano 20143",
    "addr:postcode":"20143;20143",
    "iso:country":"IT",
    "sg:address":"20143 Milano",
    "sg:city":"Milano",
    "sg:orig_category":"Arredi Ed Attrezzature Per Attivita' Commerciali Ed Artigianali",
    "sg:phone":"+39 02 8917 0201",
    "sg:postcode":"20143",
    "sg:province":"Milano",
    "wof:name":"Imprint Srl",
    "wof:placetype":"venue"
},
  "geometry": {"coordinates":[9.152709,45.44632],"type":"Point"}
}