{
  "type": "Feature",
  "properties": {
    "addr:full":"57016 Rosignano Marittimo Rosignano Marittimo Livorno 57016",
    "addr:postcode":"57016;57016",
    "iso:country":"IT",
    "sg:address":"57016 Rosignano Marittimo",
    "sg:city":"Rosignano Marittimo",
    "sg:orig_category":"Nautica. Automobili E Mezzi Di Trasporto",
    "sg:phone":"+39 0586 767387",
    "sg:postcode":"57016",
    "sg:province":"Livorno",
    "wof:name":"Gavazzi Luciano",
    "wof:placetype":"venue"
},
  "geometry": {"coordinates":[10.404111,43.411926],"type":"Point"}
}