{
  "type": "Feature",
  "properties": {
    "iso:country":"IT",
    "sg:address":"20123 Milano",
    "sg:city":"Milano",
    "sg:orig_category":"Accessori Moda D'abbigliamento",
    "sg:phone":"+39 02 869 3314",
    "sg:postcode":"20123",
    "sg:province":"Milano",
    "wof:name":"Sacchi Andrea Nello",
    "wof:placetype":"venue"
},
  "geometry": {"coordinates":[9.178845,45.465714],"type":"Point"}
}