{
  "type": "Feature",
  "properties": {
    "iso:country":"IT",
    "sg:address":"171, Via Meldola 47032 Bertinoro",
    "sg:city":"Bertinoro",
    "sg:classifiers":[
        {
            "category":"Farming",
            "subcategory":"Livestock Farm",
            "type":"Manufacturing & Wholesale Goods"
        }
    ],
    "sg:phone":"+39 0543 460737",
    "sg:postcode":"47032",
    "sg:province":"Forl\u00ec-Cesena",
    "sg:tags":[
        "agriculture"
    ],
    "wof:name":"Zoofarm S.r.l.",
    "wof:placetype":"venue"
},
  "geometry": {"coordinates":[12.133515,44.149284],"type":"Point"}
}