{
  "type": "Feature",
  "properties": {
    "iso:country":"IT",
    "sg:address":"Via Vicinale, 2743; Cesena; 47023",
    "sg:city":"Cesena",
    "sg:classifiers":[
        {
            "category":"Banks & Credit Unions",
            "subcategory":"Bank",
            "type":"Services"
        }
    ],
    "sg:phone":"+39 0547 324017",
    "sg:postcode":"47023",
    "sg:province":"Forl\u00ec-Cesena",
    "wof:name":"Cassa Rurale Ed Artigiana",
    "wof:placetype":"venue"
},
  "geometry": {"coordinates":[12.3281,44.123692],"type":"Point"}
}