{
  "type": "Feature",
  "properties": {
    "iso:country":"IT",
    "sg:address":"12060 Castiglione Falletto",
    "sg:city":"Castiglione Falletto",
    "sg:orig_category":"Prodotti Di Base E Forniture Per Industria Alimentare E Bevande",
    "sg:phone":"+39 0173 231929",
    "sg:postcode":"12060",
    "sg:province":"Cuneo",
    "wof:name":"Canta Vincenzo & C. (s.a.s.)",
    "wof:placetype":"venue"
},
  "geometry": {"coordinates":[7.9281620979,44.6754837036],"type":"Point"}
}