{
  "type": "Feature",
  "properties": {
    "iso:country":"IT",
    "sg:address":"40133 Bologna",
    "sg:city":"Bologna",
    "sg:orig_category":"Informatica - Consulenza E Software",
    "sg:phone":"+39 051 658 3011",
    "sg:postcode":"40133",
    "sg:province":"Bologna",
    "sg:website":"http://www.dsnet.it",
    "wof:name":"Ds Logics Srl",
    "wof:placetype":"venue"
},
  "geometry": {"coordinates":[11.304619,44.509567],"type":"Point"}
}