{
  "type": "Feature",
  "properties": {
    "addr:full":"1066, Via Sirene 70044 Polignano A Mare Polignano a Mare Bari 70044",
    "addr:housenumber":"1066",
    "addr:postcode":"70044;70044",
    "addr:street":"Via Sirene",
    "iso:country":"IT",
    "sg:address":"1066, Via Sirene 70044 Polignano A Mare",
    "sg:city":"Polignano a Mare",
    "sg:orig_category":"Miscellaneous Products",
    "sg:phone":"+39 080 424 1070",
    "sg:postcode":"70044",
    "sg:province":"Bari",
    "wof:name":"Fratelli Lamanna S.n.c.",
    "wof:placetype":"venue"
},
  "geometry": {"coordinates":[17.1381702423,41.0377807617],"type":"Point"}
}