{
  "type": "Feature",
  "properties": {
    "iso:country":"IT",
    "sg:address":"48014 Castel Bolognese",
    "sg:city":"Castel Bolognese",
    "sg:orig_category":"Centri Di Estetica E Cosmesi E Servizi",
    "sg:phone":"+39 0546 657008",
    "sg:postcode":"48014",
    "sg:province":"Ravenna",
    "sg:website":"http://www.centrosophia.it",
    "wof:name":"Sophia Srl",
    "wof:placetype":"venue"
},
  "geometry": {"coordinates":[11.802538,44.320408],"type":"Point"}
}