{
  "type": "Feature",
  "properties": {
    "iso:country":"IT",
    "sg:address":"10071 Borgaro Torinese",
    "sg:city":"Borgaro Torinese",
    "sg:orig_category":"Associazioni Ed Organismi Di Interesse Pubblico",
    "sg:phone":"+39 011 470 2244",
    "sg:postcode":"10071",
    "sg:province":"Torino",
    "wof:name":"Associazione Nazionale Alpini",
    "wof:placetype":"venue"
},
  "geometry": {"coordinates":[7.646548,45.152084],"type":"Point"}
}