{
  "type": "Feature",
  "properties": {
    "iso:country":"IT",
    "sg:address":"78, Via Cento 40017 San Giovanni In Persiceto",
    "sg:city":"San Giovanni in Persiceto",
    "sg:classifiers":[
        {
            "category":"Shopping",
            "type":"Retail Goods"
        }
    ],
    "sg:phone":"+39 39051824585",
    "sg:postcode":"40017",
    "sg:province":"Bologna",
    "sg:tags":[
        "finished",
        "-",
        "metallic"
    ],
    "wof:name":"Mollificio G.r. Di Risi S. & Grassilli C. (s.n.c.)",
    "wof:placetype":"venue"
},
  "geometry": {"coordinates":[11.2057590485,44.6645698547],"type":"Point"}
}