{
  "type": "Feature",
  "properties": {
    "iso:country":"IT",
    "sg:address":"20133 Milano",
    "sg:city":"Milano",
    "sg:orig_category":"Scuole E Servizi Scolastici",
    "sg:phone":"+39 02 236 7081",
    "sg:postcode":"20133",
    "sg:province":"Milano",
    "wof:name":"Faes Monforte Scuola Elementare Media Liceo",
    "wof:placetype":"venue"
},
  "geometry": {"coordinates":[9.228016,45.481041],"type":"Point"}
}