{
  "type": "Feature",
  "properties": {
    "iso:country":"IT",
    "sg:address":"871, Via Nomentana 00137 Roma",
    "sg:city":"Roma",
    "sg:classifiers":[
        {
            "category":"Autos & Motor Vehicles",
            "subcategory":"Automobile Sales",
            "type":"Retail Goods"
        }
    ],
    "sg:phone":"+39 06 8689 5960",
    "sg:postcode":"00137",
    "sg:province":"Roma",
    "sg:tags":[
        "motor-cars"
    ],
    "wof:name":"Centro Italia Srl",
    "wof:placetype":"venue"
},
  "geometry": {"coordinates":[12.5535335541,41.9415855408],"type":"Point"}
}