{
  "type": "Feature",
  "properties": {
    "addr:full":"11, Via Monte S.primo 22063 Cantu' Como 22063",
    "addr:postcode":"22063;22063",
    "addr:street":"Via Monte S.Primo;Cantu ' Como",
    "iso:country":"IT",
    "sg:address":"11, Via Monte S.primo 22063 Cantu'",
    "sg:classifiers":[
        {
            "category":"Shopping",
            "subcategory":"Stationery & Office Supplies",
            "type":"Retail Goods"
        }
    ],
    "sg:phone":"+39 39031709910",
    "sg:postcode":"22063",
    "sg:province":"Como",
    "sg:tags":[
        "professional"
    ],
    "wof:name":"Mele Srl",
    "wof:placetype":"venue"
},
  "geometry": {"coordinates":[9.0854558945,45.8119659424],"type":"Point"}
}