{
  "type": "Feature",
  "properties": {
    "addr:full":"26010 Chieve Chieve Cremona 26010",
    "addr:postcode":"26010;26010",
    "iso:country":"IT",
    "sg:address":"26010 Chieve",
    "sg:city":"Chieve",
    "sg:orig_category":"Filtri - Produzione E Commercio",
    "sg:phone":"+39 0373 649595",
    "sg:postcode":"26010",
    "sg:province":"Cremona",
    "wof:name":"Filtri Aria Di Cinzia Marchesi",
    "wof:placetype":"venue"
},
  "geometry": {"coordinates":[9.6175003052,45.3414077759],"type":"Point"}
}