{
  "type": "Feature",
  "properties": {
    "iso:country":"IT",
    "sg:address":"00195 Roma",
    "sg:city":"Roma",
    "sg:orig_category":"Cine-foto-ottica",
    "sg:phone":"+39 06 3973 3473",
    "sg:postcode":"00195",
    "sg:province":"Roma",
    "wof:name":"Studio Eos Fotodesign Sas Di Nanni Tiziana",
    "wof:placetype":"venue"
},
  "geometry": {"coordinates":[12.458121,41.918045],"type":"Point"}
}