{
  "type": "Feature",
  "properties": {
    "iso:country":"IT",
    "sg:address":"31050 Povegliano",
    "sg:city":"Povegliano",
    "sg:orig_category":"Studi E Consulenze Amministrative, Commerciali E Aziendali. Studi E Consulenze Tecniche E Industriali. Consulenze Tecniche, Amministrative E Perizie",
    "sg:phone":"+39 0422 873721",
    "sg:postcode":"31050",
    "sg:province":"Treviso",
    "wof:name":"Creative System Consulting",
    "wof:placetype":"venue"
},
  "geometry": {"coordinates":[12.174593,45.74934],"type":"Point"}
}