{
  "type": "Feature",
  "properties": {
    "addr:full":"Piazza Arciduca; Scena; 39017 Scena Bolzano/Bozen 39017",
    "addr:postcode":"39017;39017",
    "addr:street":"Piazza Arciduca",
    "iso:country":"IT",
    "sg:address":"Piazza Arciduca; Scena; 39017",
    "sg:city":"Scena",
    "sg:classifiers":[
        {
            "category":"Banks & Credit Unions",
            "subcategory":"Bank",
            "type":"Services"
        }
    ],
    "sg:phone":"+39 0473 945520",
    "sg:postcode":"39017",
    "sg:province":"Bolzano/Bozen",
    "wof:name":"Banca Popolare Dell'alto Adige",
    "wof:placetype":"venue"
},
  "geometry": {"coordinates":[11.187205,46.690155],"type":"Point"}
}