{
  "type": "Feature",
  "properties": {
    "addr:full":"11/15/16, Viale Delle Industrie 20020 Arese Arese Milano 20020",
    "addr:housenumber":"11 / 15 / 16",
    "addr:postcode":"20020;20020",
    "addr:street":"Viale Delle Industrie",
    "iso:country":"IT",
    "sg:address":"11/15/16, Viale Delle Industrie 20020 Arese",
    "sg:city":"Arese",
    "sg:classifiers":[
        {
            "category":"Real Estate",
            "subcategory":"Surveying",
            "type":"Services"
        }
    ],
    "sg:phone":"+39 02 9358 3314",
    "sg:postcode":"20020",
    "sg:province":"Milano",
    "sg:tags":[
        "equipment",
        "material",
        "good",
        "-",
        "handling"
    ],
    "wof:name":"Mec - Gru (s.r.l.)",
    "wof:placetype":"venue"
},
  "geometry": {"coordinates":[9.087852,45.535484],"type":"Point"}
}