{
  "type": "Feature",
  "properties": {
    "iso:country":"IT",
    "sg:address":"31015 Conegliano",
    "sg:city":"Conegliano",
    "sg:classifiers":[
        {
            "category":"Banks & Credit Unions",
            "subcategory":"Investment Brokerage",
            "type":"Services"
        }
    ],
    "sg:phone":"+39 0438 450832",
    "sg:postcode":"31015",
    "sg:province":"Treviso",
    "sg:tags":[
        "control",
        "industrial",
        "door",
        "supply",
        "window",
        "safety",
        "frames",
        "prevention"
    ],
    "wof:name":"Kema Srl",
    "wof:placetype":"venue"
},
  "geometry": {"coordinates":[12.225875,45.656288],"type":"Point"}
}