{
  "type": "Feature",
  "properties": {
    "addr:full":"Corso Gua 30; Cologna Veneta; 37044 Cologna Veneta Verona 37044",
    "addr:housenumber":"30",
    "addr:postcode":"37044;37044",
    "addr:street":"Corso Gua",
    "iso:country":"IT",
    "sg:address":"Corso Gua 30; Cologna Veneta; 37044",
    "sg:city":"Cologna Veneta",
    "sg:classifiers":[
        {
            "category":"Banks & Credit Unions",
            "subcategory":"Bank",
            "type":"Services"
        }
    ],
    "sg:phone":"+39 0442 85533",
    "sg:postcode":"37044",
    "sg:province":"Verona",
    "wof:name":"Banco Ambrosiano Veneto Spa",
    "wof:placetype":"venue"
},
  "geometry": {"coordinates":[11.385593,45.310257],"type":"Point"}
}