{
  "type": "Feature",
  "properties": {
    "addr:full":"24021 Albino Albino Bergamo 24021",
    "addr:postcode":"24021;24021",
    "iso:country":"IT",
    "sg:address":"24021 Albino",
    "sg:city":"Albino",
    "sg:orig_category":"Cinema, Cameras, Optical Instruments",
    "sg:phone":"+39 035 760210",
    "sg:postcode":"24021",
    "sg:province":"Bergamo",
    "wof:name":"Ciak Sposi Di Sana Stefano & C. Snc",
    "wof:placetype":"venue"
},
  "geometry": {"coordinates":[9.674421,45.663727],"type":"Point"}
}