{
  "type": "Feature",
  "properties": {
    "iso:country":"IT",
    "sg:address":"40137 Bologna",
    "sg:city":"Bologna",
    "sg:orig_category":"Stands - Progettazione, Allestimento E Noleggio",
    "sg:phone":"+39 051 623 8220",
    "sg:postcode":"40137",
    "sg:province":"Bologna",
    "sg:website":"http://www.aegstand.com",
    "wof:name":"A & G Srl",
    "wof:placetype":"venue"
},
  "geometry": {"coordinates":[11.365417,44.47905],"type":"Point"}
}