{
  "type": "Feature",
  "properties": {
    "iso:country":"IT",
    "sg:address":"Corso Matteotti, 61; Pontedera; 56025",
    "sg:city":"Pontedera",
    "sg:classifiers":[
        {
            "category":"Banks & Credit Unions",
            "subcategory":"Bank",
            "type":"Services"
        }
    ],
    "sg:phone":"+39 0587 53866",
    "sg:postcode":"56025",
    "sg:province":"Pisa",
    "wof:name":"Banco Di Roma",
    "wof:placetype":"venue"
},
  "geometry": {"coordinates":[10.549294,43.676384],"type":"Point"}
}