{
  "type": "Feature",
  "properties": {
    "addr:full":"97016 Pozzallo Pozzallo Ragusa 97016",
    "addr:postcode":"97016;97016",
    "iso:country":"IT",
    "sg:address":"97016 Pozzallo",
    "sg:city":"Pozzallo",
    "sg:classifiers":[
        {
            "category":"Travel",
            "subcategory":"Hotels & Motels",
            "type":"Entertainment"
        }
    ],
    "sg:phone":"+39 0932 958858",
    "sg:postcode":"97016",
    "sg:province":"Ragusa",
    "sg:tags":[
        "hotels",
        "facility"
    ],
    "wof:name":"Hotel Continental",
    "wof:placetype":"venue"
},
  "geometry": {"coordinates":[14.845702,36.726051],"type":"Point"}
}