{
  "type": "Feature",
  "properties": {
    "addr:full":"16126 Genova Genova Genova 16126",
    "addr:postcode":"16126;16126",
    "iso:country":"IT",
    "sg:address":"16126 Genova",
    "sg:city":"Genova",
    "sg:classifiers":[
        {
            "category":"Health Services",
            "subcategory":"Health Practitioner",
            "type":"Services"
        }
    ],
    "sg:phone":"+39 010 265108",
    "sg:postcode":"16126",
    "sg:province":"Genova",
    "sg:tags":[
        "medici"
    ],
    "wof:name":"Rapallo Goffredo",
    "wof:placetype":"venue"
},
  "geometry": {"coordinates":[8.9093580246,44.405670166],"type":"Point"}
}