{
  "type": "Feature",
  "properties": {
    "addr:full":"50031 Barberino Di Mugello Barberino di Mugello Firenze 50031",
    "addr:postcode":"50031;50031",
    "iso:country":"IT",
    "sg:address":"50031 Barberino Di Mugello",
    "sg:city":"Barberino di Mugello",
    "sg:orig_category":"Metalli E Leghe",
    "sg:phone":"+39 055 841107",
    "sg:postcode":"50031",
    "sg:province":"Firenze",
    "sg:website":"http://www.geal.it",
    "wof:name":"Geal Spa",
    "wof:placetype":"venue"
},
  "geometry": {"coordinates":[11.2327003479,43.9918708801],"type":"Point"}
}