{
  "type": "Feature",
  "properties": {
    "addr:full":"20020 Arconate Arconate Milano 20020",
    "addr:postcode":"20020;20020",
    "iso:country":"IT",
    "sg:address":"20020 Arconate",
    "sg:city":"Arconate",
    "sg:classifiers":[
        {
            "category":"Wholesale",
            "subcategory":"Chemicals & Plastics",
            "type":"Manufacturing & Wholesale Goods"
        }
    ],
    "sg:phone":"+39 0331 461218",
    "sg:postcode":"20020",
    "sg:province":"Milano",
    "sg:tags":[
        "article",
        "product",
        "plastics"
    ],
    "sg:website":"http://www.callonitex.it",
    "wof:name":"Tessitura Calloni Lino & C. Snc",
    "wof:placetype":"venue"
},
  "geometry": {"coordinates":[8.8479404449,45.5395469666],"type":"Point"}
}