{
  "type": "Feature",
  "properties": {
    "iso:country":"IT",
    "sg:address":"21047 Saronno",
    "sg:city":"Saronno",
    "sg:orig_category":"Cinematografia E Radiotelevisione. Pubblicita', Marketing E Comunicazione. Acqua, Luce, Gas E Societa' Di Esercizio Pubblico",
    "sg:phone":"+39 02 960 2728",
    "sg:postcode":"21047",
    "sg:province":"Varese",
    "wof:name":"Radiorizzonti (s.r.l.)",
    "wof:placetype":"venue"
},
  "geometry": {"coordinates":[9.037183,45.62566],"type":"Point"}
}