{
  "type": "Feature",
  "properties": {
    "addr:full":"Via Firenze, 46/48; Napoli; 80142 Napoli Napoli 80142",
    "addr:housenumber":"46 / 48",
    "addr:postcode":"80142;80142",
    "addr:street":"Via Firenze",
    "iso:country":"IT",
    "sg:address":"Via Firenze, 46/48; Napoli; 80142",
    "sg:city":"Napoli",
    "sg:classifiers":[
        {
            "category":"Banks & Credit Unions",
            "subcategory":"Bank",
            "type":"Services"
        }
    ],
    "sg:phone":"+39 081 553 8814",
    "sg:postcode":"80142",
    "sg:province":"Napoli",
    "wof:name":"Banco Di Napoli",
    "wof:placetype":"venue"
},
  "geometry": {"coordinates":[14.271423,40.854237],"type":"Point"}
}