{
  "type": "Feature",
  "properties": {
    "iso:country":"IT",
    "sg:address":"25121 Brescia",
    "sg:city":"Brescia",
    "sg:classifiers":[
        {
            "category":"Building & Trades",
            "subcategory":"Construction",
            "type":"Services"
        }
    ],
    "sg:phone":"+39 030 280498",
    "sg:postcode":"25121",
    "sg:province":"Brescia",
    "sg:tags":[
        "art",
        "civil",
        "industry",
        "craft",
        "wood",
        "furnishing",
        "works",
        "artistic"
    ],
    "wof:name":"Elena Allodi",
    "wof:placetype":"venue"
},
  "geometry": {"coordinates":[10.2300205231,45.5371055603],"type":"Point"}
}