{
  "type": "Feature",
  "properties": {
    "iso:country":"IT",
    "sg:address":"1, Via Lorenzetti 61022 Colbordolo",
    "sg:city":"Colbordolo",
    "sg:classifiers":[
        {
            "category":"Home & Garden",
            "subcategory":"Home Furnishings",
            "type":"Retail Goods"
        }
    ],
    "sg:phone":"+39 0721 478397",
    "sg:postcode":"61022",
    "sg:province":"Pesaro E Urbino",
    "sg:tags":[
        "household"
    ],
    "wof:name":"F.ar.mo (s.r.l.)",
    "wof:placetype":"venue"
},
  "geometry": {"coordinates":[12.72503,43.834274],"type":"Point"}
}