{
  "type": "Feature",
  "properties": {
    "addr:full":"20038 Seregno Seregno Milano 20038",
    "addr:postcode":"20038;20038",
    "iso:country":"IT",
    "sg:address":"20038 Seregno",
    "sg:city":"Seregno",
    "sg:orig_category":"Materassi - Produzione E Ingrosso",
    "sg:phone":"+39 036 222 9900",
    "sg:postcode":"20038",
    "sg:province":"Milano",
    "sg:website":"http://www.mambretti.it",
    "wof:name":"Mambretti Reti Di Mambretti Luigi & C. Snc",
    "wof:placetype":"venue"
},
  "geometry": {"coordinates":[9.203573,45.651917],"type":"Point"}
}