{
  "type": "Feature",
  "properties": {
    "iso:country":"IT",
    "sg:address":"80053 Castellammare Di Stabia",
    "sg:city":"Castellammare di Stabia",
    "sg:orig_category":"Servizi E Lavori Industria Della Gomma",
    "sg:phone":"+39 081 871 0535",
    "sg:postcode":"80053",
    "sg:province":"Napoli",
    "wof:name":"Balzano Benito",
    "wof:placetype":"venue"
},
  "geometry": {"coordinates":[14.482836,40.704254],"type":"Point"}
}