{
  "type": "Feature",
  "properties": {
    "addr:full":"Via Dei Faggi 8 47890 Repubblica Di San Marino",
    "addr:housenumber":"8",
    "addr:postcode":"47890",
    "addr:street":"Via Dei Faggi;Marino",
    "iso:country":"IT",
    "sg:address":"Via Dei Faggi 8 47890 Repubblica Di San Marino",
    "sg:classifiers":[
        {
            "category":"Food & Beverages",
            "subcategory":"Chocolate",
            "type":"Retail Goods"
        }
    ],
    "sg:phone":"+39 0549 998046",
    "sg:tags":[
        "candy"
    ],
    "sg:website":"www.internet.sm/liquorificiosanmarino.sm",
    "wof:name":"Liquorificio San Marino Sa",
    "wof:placetype":"venue"
},
  "geometry": {"coordinates":[12.411948,43.902592],"type":"Point"}
}