{
  "type": "Feature",
  "properties": {
    "iso:country":"IT",
    "sg:address":"36077 Altavilla Vicentina",
    "sg:city":"Altavilla Vicentina",
    "sg:orig_category":"Apparecchiature Ed Attrezzature Meccaniche",
    "sg:phone":"+39 0444 370744",
    "sg:postcode":"36077",
    "sg:province":"Vicenza",
    "wof:name":"So.ci.ma Sas",
    "wof:placetype":"venue"
},
  "geometry": {"coordinates":[11.46452,45.519287],"type":"Point"}
}