{
  "type": "Feature",
  "properties": {
    "iso:country":"IT",
    "sg:address":"Via Los Angeles Snc; Assisi; 06088",
    "sg:classifiers":[
        {
            "category":"Banks & Credit Unions",
            "subcategory":"Bank",
            "type":"Services"
        }
    ],
    "sg:phone":"+39 075 804 3370",
    "wof:name":"Banca Nazionale Del Lavoro Spa",
    "wof:placetype":"venue"
},
  "geometry": {"coordinates":[12.566571,43.062851],"type":"Point"}
}