{
  "type": "Feature",
  "properties": {
    "addr:full":"20148 Milano Milano Milano 20148",
    "addr:postcode":"20148;20148",
    "iso:country":"IT",
    "sg:address":"20148 Milano",
    "sg:city":"Milano",
    "sg:classifiers":[
        {
            "category":"Health Services",
            "subcategory":"Health Practitioner",
            "type":"Services"
        }
    ],
    "sg:phone":"+39 02 404 2784",
    "sg:postcode":"20148",
    "sg:province":"Milano",
    "sg:tags":[
        "medici"
    ],
    "wof:name":"Lassini Maria Luisa",
    "wof:placetype":"venue"
},
  "geometry": {"coordinates":[9.1433362961,45.46875],"type":"Point"}
}