{
  "type": "Feature",
  "properties": {
    "addr:full":"1 Piazza Matteotti Giacomo, 06012 Citta' Di Castello Perugia 06012",
    "addr:postcode":"06012 citta;06012",
    "addr:street":"Piazza Matteotti Giacomo",
    "iso:country":"IT",
    "sg:address":"1 Piazza Matteotti Giacomo, 06012 Citta' Di Castello",
    "sg:classifiers":[
        {
            "category":"Banks & Credit Unions",
            "subcategory":"Financial Services",
            "type":"Services"
        }
    ],
    "sg:phone":"+39 390 758 5081",
    "sg:postcode":"06012",
    "sg:province":"Perugia",
    "sg:tags":[
        "banking",
        "finance",
        "insurance"
    ],
    "wof:name":"Cassa Di Risparmio Di Citta Di Castello",
    "wof:placetype":"venue"
},
  "geometry": {"coordinates":[12.3891716003,43.1107025146],"type":"Point"}
}