{
  "type": "Feature",
  "properties": {
    "addr:full":"Via Einaudi Luigi 64 06125 Perugia Perugia Perugia 06125",
    "addr:housenumber":"64",
    "addr:postcode":"06125;06125",
    "addr:street":"Via Einaudi Luigi",
    "iso:country":"IT",
    "sg:address":"Via Einaudi Luigi 64 06125 Perugia",
    "sg:city":"Perugia",
    "sg:classifiers":[
        {
            "category":"Manufacturing",
            "subcategory":"Rubber & Plastics",
            "type":"Manufacturing & Wholesale Goods"
        }
    ],
    "sg:phone":"+39 075 514 9033",
    "sg:postcode":"06125",
    "sg:province":"Perugia",
    "sg:tags":[
        "processing"
    ],
    "wof:name":"Silpa Srl",
    "wof:placetype":"venue"
},
  "geometry": {"coordinates":[12.3891716003,43.1107025146],"type":"Point"}
}