{
  "type": "Feature",
  "properties": {
    "addr:full":"74100 Taranto Taranto Taranto 74100",
    "addr:postcode":"74100;74100",
    "iso:country":"IT",
    "sg:address":"74100 Taranto",
    "sg:city":"Taranto",
    "sg:orig_category":"Assicurazioni E Servizi Assicurativi. Consulenze Tecniche, Amministrative E Perizie",
    "sg:phone":"+39 099 459 1651",
    "sg:postcode":"74100",
    "sg:province":"Taranto",
    "wof:name":"Confitalia Taranto Di Calfapietro Luigi",
    "wof:placetype":"venue"
},
  "geometry": {"coordinates":[17.239473,40.470539],"type":"Point"}
}