{
  "type": "Feature",
  "properties": {
    "iso:country":"IT",
    "sg:address":"Via Cavriana 14 46040 Guidizzolo",
    "sg:city":"Cavriana",
    "sg:classifiers":[
        {
            "category":"Shopping",
            "subcategory":"Crafts & Fabrics",
            "type":"Retail Goods"
        }
    ],
    "sg:phone":"+39 0376 818740",
    "sg:postcode":"46040",
    "sg:province":"Mantova",
    "sg:tags":[
        "synthetic",
        "fabrics",
        "plastic"
    ],
    "wof:name":"Gafitex S.r.l.",
    "wof:placetype":"venue"
},
  "geometry": {"coordinates":[10.5671901703,45.3663215637],"type":"Point"}
}