{
  "type": "Feature",
  "properties": {
    "iso:country":"IT",
    "sg:address":"00153 Roma",
    "sg:city":"Roma",
    "sg:orig_category":"Scuole E Servizi Scolastici",
    "sg:phone":"+39 06 574 1661",
    "sg:postcode":"00153",
    "sg:province":"Roma",
    "wof:name":"Scuola Privata Istituto Magistrale Elena Bettini",
    "wof:placetype":"venue"
},
  "geometry": {"coordinates":[12.476323,41.877609],"type":"Point"}
}