{
  "type": "Feature",
  "properties": {
    "iso:country":"IT",
    "sg:address":"34076 Romans D'isonzo",
    "sg:orig_category":"Prodotti E Manufatti In Materie Plastiche",
    "sg:phone":"+39 0481 908918",
    "sg:postcode":"34076",
    "sg:province":"Gorizia",
    "wof:name":"B. & P. Italia Srl",
    "wof:placetype":"venue"
},
  "geometry": {"coordinates":[13.4094905853,45.840927124],"type":"Point"}
}