{
  "type": "Feature",
  "properties": {
    "iso:country":"IT",
    "sg:address":"31045 Motta Di Livenza",
    "sg:city":"Motta di Livenza",
    "sg:orig_category":"Trasporti E Spedizioni Merci",
    "sg:phone":"+39 0422 860802",
    "sg:postcode":"31045",
    "sg:province":"Treviso",
    "wof:name":"Campagna Renzo",
    "wof:placetype":"venue"
},
  "geometry": {"coordinates":[12.596875,45.769547],"type":"Point"}
}