{
  "type": "Feature",
  "properties": {
    "iso:country":"IT",
    "sg:address":"09122 Cagliari",
    "sg:city":"Cagliari",
    "sg:orig_category":"Macchine, Impianti Ed Attrezzature Industria Chimica. Prodotti Vari In Metallo. Articoli Per Imballaggio E Confezionamento",
    "sg:phone":"+39 070 283635",
    "sg:postcode":"09122",
    "sg:province":"Cagliari",
    "wof:name":"Loddo Francesco",
    "wof:placetype":"venue"
},
  "geometry": {"coordinates":[9.103864,39.235165],"type":"Point"}
}