{
  "type": "Feature",
  "properties": {
    "iso:country":"IT",
    "sg:address":"30, Via Giovanni Pascoli 30020 Quarto D'altino",
    "sg:classifiers":[
        {
            "category":"Shopping",
            "subcategory":"Computers & Home Electronics",
            "type":"Retail Goods"
        }
    ],
    "sg:phone":"+39 390 422 8264",
    "sg:postcode":"30020",
    "sg:province":"Venezia",
    "sg:tags":[
        "electronic",
        "electrical",
        "equipment"
    ],
    "wof:name":"Ditec Spa",
    "wof:placetype":"venue"
},
  "geometry": {"coordinates":[12.352574,45.576351],"type":"Point"}
}