{
  "type": "Feature",
  "properties": {
    "addr:full":"34, Via Di Montramito 55049 Viareggio Viareggio Lucca 55049",
    "addr:postcode":"55049;55049",
    "addr:street":"Via Di Montramito",
    "iso:country":"IT",
    "sg:address":"34, Via Di Montramito 55049 Viareggio",
    "sg:city":"Viareggio",
    "sg:classifiers":[
        {
            "category":"Autos & Motor Vehicles",
            "subcategory":"Boat Sales",
            "type":"Retail Goods"
        }
    ],
    "sg:phone":"+39 0584 944955",
    "sg:postcode":"55049",
    "sg:province":"Lucca",
    "wof:name":"Off Course Srl",
    "wof:placetype":"venue"
},
  "geometry": {"coordinates":[10.302033,43.885288],"type":"Point"}
}