{
  "type": "Feature",
  "properties": {
    "addr:full":"Via Codignola 4 50018 Scandicci Scandicci Firenze 50018",
    "addr:housenumber":"4",
    "addr:postcode":"50018;50018",
    "addr:street":"Via Codignola",
    "iso:country":"IT",
    "sg:address":"Via Codignola 4 50018 Scandicci",
    "sg:city":"Scandicci",
    "sg:classifiers":[
        {
            "category":"Manufacturing",
            "subcategory":"Textiles",
            "type":"Manufacturing & Wholesale Goods"
        }
    ],
    "sg:phone":"+39 055 755220",
    "sg:postcode":"50018",
    "sg:province":"Firenze",
    "sg:tags":[
        "chenille",
        "yarn"
    ],
    "sg:website":"www.luigiboldrini.com",
    "wof:name":"Boldrini Luigi E Figli Spa",
    "wof:placetype":"venue"
},
  "geometry": {"coordinates":[11.168395,43.763382],"type":"Point"}
}