{
  "type": "Feature",
  "properties": {
    "iso:country":"IT",
    "sg:address":"43013 Langhirano",
    "sg:city":"Langhirano",
    "sg:orig_category":"Macchine, Impianti Ed Attrezzature Per Industria Alimentare E Bevande",
    "sg:phone":"+39 0521 852570",
    "sg:postcode":"43013",
    "sg:province":"Parma",
    "wof:name":"Macchine Soncini Alberto Spa",
    "wof:placetype":"venue"
},
  "geometry": {"coordinates":[10.238578,44.698872],"type":"Point"}
}