{
  "type": "Feature",
  "properties": {
    "iso:country":"IT",
    "sg:address":"56021 Cascina",
    "sg:city":"Cascina",
    "sg:orig_category":"Abbigliamento - Vendita Al Dettaglio",
    "sg:phone":"+39 050 741450",
    "sg:postcode":"56021",
    "sg:province":"Pisa",
    "wof:name":"Gabry Moda Market",
    "wof:placetype":"venue"
},
  "geometry": {"coordinates":[10.470207,43.689842],"type":"Point"}
}