{
  "type": "Feature",
  "properties": {
    "iso:country":"IT",
    "sg:address":"6, Viale Mattei 60013 Corinaldo",
    "sg:city":"Corinaldo",
    "sg:classifiers":[
        {
            "category":"Home & Garden",
            "subcategory":"Home Furnishings",
            "type":"Retail Goods"
        }
    ],
    "sg:phone":"+39 390 716 7778",
    "sg:postcode":"60013",
    "sg:province":"Ancona",
    "sg:tags":[
        "household"
    ],
    "wof:name":"S.a.r.a.",
    "wof:placetype":"venue"
},
  "geometry": {"coordinates":[13.070977,43.640266],"type":"Point"}
}