{
  "type": "Feature",
  "properties": {
    "addr:full":"Via Xx Settembre 7 20036 Meda Meda Milano 20036",
    "addr:housenumber":"7",
    "addr:postcode":"20036;20036",
    "addr:street":"Via Xx Settembre",
    "iso:country":"IT",
    "sg:address":"Via Xx Settembre 7 20036 Meda",
    "sg:city":"Meda",
    "sg:classifiers":[
        {
            "category":"Home & Garden",
            "subcategory":"Carpets & Floor Coverings",
            "type":"Retail Goods"
        }
    ],
    "sg:phone":"+39 036 234 3216",
    "sg:postcode":"20036",
    "sg:province":"Milano",
    "sg:tags":[
        "rug",
        "printed"
    ],
    "sg:website":"www.paolalenti.com",
    "wof:name":"Paola Lenti Srl Di Paola Lenti",
    "wof:placetype":"venue"
},
  "geometry": {"coordinates":[9.1881408691,45.4636878967],"type":"Point"}
}