{
  "type": "Feature",
  "properties": {
    "iso:country":"IT",
    "sg:address":"35030 Saccolongo",
    "sg:city":"Saccolongo",
    "sg:orig_category":"Macchine E Forniture Per Arredamento E Industria Del Legno. Colori, Vernici E Smalti",
    "sg:phone":"+39 049 801 5818",
    "sg:postcode":"35030",
    "sg:province":"Padova",
    "wof:name":"B.m. Di Barbiero E Minotti (s.r.l.)",
    "wof:placetype":"venue"
},
  "geometry": {"coordinates":[11.735075,45.409405],"type":"Point"}
}