{
  "type": "Feature",
  "properties": {
    "iso:country":"IT",
    "sg:address":"40057 Granarolo Emilia",
    "sg:orig_category":"Automobili - Elaborazioni",
    "sg:phone":"+39 051 761409",
    "sg:postcode":"40057",
    "sg:province":"Bologna",
    "wof:name":"Gamberini Sergio Officina Elaborazione Auto E Moto",
    "wof:placetype":"venue"
},
  "geometry": {"coordinates":[11.441261,44.549824],"type":"Point"}
}