{
  "type": "Feature",
  "properties": {
    "iso:country":"IT",
    "sg:address":"20122 Milano",
    "sg:city":"Milano",
    "sg:orig_category":"Hobbistica",
    "sg:phone":"+39 02 875780",
    "sg:postcode":"20122",
    "sg:province":"Milano",
    "wof:name":"Lucca Gino Ditta Di G. Baleri",
    "wof:placetype":"venue"
},
  "geometry": {"coordinates":[9.193,45.462151],"type":"Point"}
}