{
  "type": "Feature",
  "properties": {
    "iso:country":"IT",
    "sg:address":"Via Montorso 4a 36071 Arzignano",
    "sg:city":"Arzignano",
    "sg:classifiers":[
        {
            "category":"Manufacturing",
            "subcategory":"Tools & Machinery",
            "type":"Manufacturing & Wholesale Goods"
        }
    ],
    "sg:phone":"+39 0444 473473",
    "sg:postcode":"36071",
    "sg:province":"Vicenza",
    "sg:tags":[
        "tannery"
    ],
    "sg:website":"www.bergiofb.com",
    "wof:name":"Industria Meccanica Bergi Ofb Spa",
    "wof:placetype":"venue"
},
  "geometry": {"coordinates":[11.347034,45.506268],"type":"Point"}
}