{
  "type": "Feature",
  "properties": {
    "iso:country":"IT",
    "sg:address":"07046 Porto Torres",
    "sg:city":"Porto Torres",
    "sg:orig_category":"Chiese Ed Associazioni Religiose",
    "sg:phone":"+39 079 502365",
    "sg:postcode":"07046",
    "sg:province":"Sassari",
    "wof:name":"Radio Vita Nuova",
    "wof:placetype":"venue"
},
  "geometry": {"coordinates":[8.401492,40.835529],"type":"Point"}
}