{
  "type": "Feature",
  "properties": {
    "iso:country":"IT",
    "sg:address":"20125 Milano",
    "sg:city":"Milano",
    "sg:orig_category":"Automazione E Macchine Per Ufficio. Forniture Industriali Per Prevenzione, Controllo E Sicurezza",
    "sg:phone":"+39 02 6900 0483",
    "sg:postcode":"20125",
    "sg:province":"Milano",
    "wof:name":"Ce.si.o. Di Aldo Maiello",
    "wof:placetype":"venue"
},
  "geometry": {"coordinates":[9.196333,45.495358],"type":"Point"}
}