{
  "type": "Feature",
  "properties": {
    "iso:country":"IT",
    "sg:address":"Corso Vittorio Emanuele,; Bitonto; 70032",
    "sg:city":"Bitonto",
    "sg:classifiers":[
        {
            "category":"Banks & Credit Unions",
            "subcategory":"Bank",
            "type":"Services"
        }
    ],
    "sg:phone":"+39 080 618122",
    "sg:postcode":"70032",
    "sg:province":"Bari",
    "wof:name":"Banca Cattolica Popolare",
    "wof:placetype":"venue"
},
  "geometry": {"coordinates":[16.693146,41.109909],"type":"Point"}
}