{
  "type": "Feature",
  "properties": {
    "iso:country":"IT",
    "sg:address":"21013 Gallarate",
    "sg:city":"Gallarate",
    "sg:orig_category":"Macchine, Impianti Ed Attrezzature Per Industria Alimentare E Bevande. Elettrodomestici. Macchine E Impianti Per Attivita' Commerciali Ed Artigianali",
    "sg:phone":"+39 0331 773657",
    "sg:postcode":"21013",
    "sg:province":"Varese",
    "wof:name":"Eurosabo (s.r.l.)",
    "wof:placetype":"venue"
},
  "geometry": {"coordinates":[8.7901,45.683891],"type":"Point"}
}