{
  "type": "Feature",
  "properties": {
    "addr:full":"Via Marconi 96 35027 Noventa Padovana Noventa Padovana Padova 35027",
    "addr:housenumber":"96",
    "addr:postcode":"35027;35027",
    "addr:street":"Via Marconi",
    "iso:country":"IT",
    "sg:address":"Via Marconi 96 35027 Noventa Padovana",
    "sg:city":"Noventa Padovana",
    "sg:classifiers":[
        {
            "category":"Professional",
            "subcategory":"Printing & Photocopies",
            "type":"Services"
        }
    ],
    "sg:phone":"+39 049 625603",
    "sg:postcode":"35027",
    "sg:province":"Padova",
    "sg:tags":[
        "large-format"
    ],
    "wof:name":"Italgraf S.r.l.",
    "wof:placetype":"venue"
},
  "geometry": {"coordinates":[11.96107,45.413204],"type":"Point"}
}