{
  "type": "Feature",
  "properties": {
    "iso:country":"IT",
    "sg:address":"Via Progresso 15 40064 Ozzano Dell'emilia",
    "sg:orig_category":"Packing Machines For Textiles",
    "sg:phone":"+39 051 799226",
    "sg:postcode":"40064",
    "sg:province":"Bologna",
    "wof:name":"G.n.a. Srl",
    "wof:placetype":"venue"
},
  "geometry": {"coordinates":[11.504368782,44.4641075134],"type":"Point"}
}