{
  "type": "Feature",
  "properties": {
    "addr:full":"Via Milano, 233; Vigliano Biellese; 13069",
    "addr:housenumber":"233",
    "addr:postcode":"13069",
    "addr:street":"Via Milano",
    "iso:country":"IT",
    "sg:address":"Via Milano, 233; Vigliano Biellese; 13069",
    "sg:classifiers":[
        {
            "category":"Banks & Credit Unions",
            "subcategory":"Bank",
            "type":"Services"
        }
    ],
    "sg:phone":"+39 015 510608",
    "wof:name":"Banca Sella Spa",
    "wof:placetype":"venue"
},
  "geometry": {"coordinates":[8.110364,45.562214],"type":"Point"}
}