{
  "type": "Feature",
  "properties": {
    "iso:country":"IT",
    "sg:address":"Via Negri 25; Romano D'ezzelino; 36060",
    "sg:classifiers":[
        {
            "category":"Banks & Credit Unions",
            "subcategory":"Bank",
            "type":"Services"
        }
    ],
    "sg:phone":"+39 0424 38145",
    "sg:postcode":"36060",
    "sg:province":"Vicenza",
    "wof:name":"Cariveorna Banca Spa",
    "wof:placetype":"venue"
},
  "geometry": {"coordinates":[11.771769,45.776241],"type":"Point"}
}