{
  "type": "Feature",
  "properties": {
    "iso:country":"IT",
    "sg:address":"50060 Londa",
    "sg:city":"Londa",
    "sg:classifiers":[
        {
            "category":"Restaurant",
            "type":"Food & Drink"
        }
    ],
    "sg:phone":"+39 055 835 4045",
    "sg:postcode":"50060",
    "sg:province":"Firenze",
    "sg:tags":[
        "auxiliary",
        "entertainment",
        "premises",
        "related",
        "catering",
        "similar",
        "public",
        "restaurants"
    ],
    "wof:name":"Il Colonnello Di Zagli Ettore E C. Sas",
    "wof:placetype":"venue"
},
  "geometry": {"coordinates":[11.60487,43.869537],"type":"Point"}
}