{
  "type": "Feature",
  "properties": {
    "iso:country":"IT",
    "sg:address":"63039 San Benedetto Del Tronto",
    "sg:city":"San Benedetto del Tronto",
    "sg:orig_category":"Biancheria, Telerie E Coperte. Forniture Alle Strutture Ricettive",
    "sg:phone":"+39 0735 582488",
    "sg:postcode":"63039",
    "sg:province":"Ascoli Piceno",
    "wof:name":"Centro Tessile San Benedetto Srl",
    "wof:placetype":"venue"
},
  "geometry": {"coordinates":[13.875373,42.960281],"type":"Point"}
}