{
  "type": "Feature",
  "properties": {
    "iso:country":"IT",
    "sg:address":"61033 Fermignano",
    "sg:city":"Fermignano",
    "sg:orig_category":"Non-classified Establishments",
    "sg:phone":"+39 0722 331459",
    "sg:postcode":"61033",
    "sg:province":"Pesaro E Urbino",
    "wof:name":"Ars Mobili Di Antonelli Mario & C. Snc",
    "wof:placetype":"venue"
},
  "geometry": {"coordinates":[12.651205,43.736099],"type":"Point"}
}