{
  "type": "Feature",
  "properties": {
    "iso:country":"IT",
    "sg:address":"Piazza Iv Novembre 11, 26862 Guardamiglio, Lo",
    "sg:city":"Guardamiglio",
    "sg:classifiers":[
        {
            "category":"Banks & Credit Unions",
            "subcategory":"Bank",
            "type":"Services"
        }
    ],
    "sg:postcode":"26862",
    "sg:province":"Lodi",
    "wof:name":"Banca Centropadana-credito Cooperativo Scrl",
    "wof:placetype":"venue"
},
  "geometry": {"coordinates":[9.49785,45.312878],"type":"Point"}
}