{
  "type": "Feature",
  "properties": {
    "iso:country":"IT",
    "sg:address":"25020 Alfianello",
    "sg:city":"Alfianello",
    "sg:orig_category":"Servizi E Lavori Industria Chimica",
    "sg:phone":"+39 030 930 5860",
    "sg:postcode":"25020",
    "sg:province":"Brescia",
    "wof:name":"S.p.v.",
    "wof:placetype":"venue"
},
  "geometry": {"coordinates":[10.138864,45.267422],"type":"Point"}
}