{
  "type": "Feature",
  "properties": {
    "iso:country":"IT",
    "sg:address":"Via Tessare 1 37020 Stallavena",
    "sg:orig_category":"Apparatus, Containers, Tanks, Vessels, And Boilers Of Stainless Steel",
    "sg:phone":"+39 045 865 0250",
    "sg:postcode":"37020",
    "sg:province":"Verona",
    "sg:website":"www.albrigiluigi.com",
    "wof:name":"Albrigi Luigi Srl",
    "wof:placetype":"venue"
},
  "geometry": {"coordinates":[11.003684,45.539955],"type":"Point"}
}