{
  "type": "Feature",
  "properties": {
    "iso:country":"IT",
    "sg:address":"20155 Milano",
    "sg:city":"Milano",
    "sg:orig_category":"Servizi E Lavori Per Ecologia E Smaltimento Rifiuti. Arte Ed Artigianato Artistico. Servizi Ausiliari Di Sorveglianza, Manutenzione E Pulizia",
    "sg:phone":"+39 02 3926 0450",
    "sg:postcode":"20155",
    "sg:province":"Milano",
    "wof:name":"Oggettistica Verde Di Vittori",
    "wof:placetype":"venue"
},
  "geometry": {"coordinates":[9.157006,45.494469],"type":"Point"}
}