{
  "type": "Feature",
  "properties": {
    "iso:country":"IT",
    "sg:address":"Via Giardino, 90 - Carpesica 31029 Vittorio Veneto",
    "sg:city":"Carpesica",
    "sg:classifiers":[
        {
            "category":"Food & Beverages",
            "subcategory":"Liquor & Beverages",
            "type":"Retail Goods"
        }
    ],
    "sg:phone":"+39 0438 920025",
    "sg:postcode":"31029",
    "sg:province":"Treviso",
    "sg:tags":[
        "wine",
        "italian"
    ],
    "sg:website":"www.bellenda.it",
    "wof:name":"Bellenda Di Casagrande Cosmo Umberto Sas",
    "wof:placetype":"venue"
},
  "geometry": {"coordinates":[12.242072,45.666286],"type":"Point"}
}