{
  "type": "Feature",
  "properties": {
    "addr:full":"Via Palladio 36043 Camisano Vicentino Camisano Vicentino Vicenza 36043",
    "addr:postcode":"36043;36043",
    "addr:street":"Via Palladio;Vicentino",
    "iso:country":"IT",
    "sg:address":"Via Palladio 36043 Camisano Vicentino",
    "sg:city":"Camisano Vicentino",
    "sg:classifiers":[
        {
            "category":"Shopping",
            "subcategory":"Jewelry",
            "type":"Retail Goods"
        }
    ],
    "sg:phone":"+39 0444 610219",
    "sg:postcode":"36043",
    "sg:province":"Vicenza",
    "sg:tags":[
        "jewellery"
    ],
    "wof:name":"G.t. Erre",
    "wof:placetype":"venue"
},
  "geometry": {"coordinates":[11.719995,45.524033],"type":"Point"}
}