{
  "type": "Feature",
  "properties": {
    "iso:country":"IT",
    "sg:address":"Via Monte Baldo 22063 Cantu'",
    "sg:classifiers":[
        {
            "category":"Home & Garden",
            "subcategory":"Home Furnishings",
            "type":"Retail Goods"
        }
    ],
    "sg:phone":"+39 39031730482",
    "sg:postcode":"22063",
    "sg:province":"Como",
    "sg:tags":[
        "household"
    ],
    "wof:name":"B. B. M. Di Boschini Marino E Giovanni Snc Lorenzo",
    "wof:placetype":"venue"
},
  "geometry": {"coordinates":[9.164632,45.724808],"type":"Point"}
}