{
  "type": "Feature",
  "properties": {
    "iso:country":"IT",
    "sg:address":"36040 Sarego",
    "sg:city":"Sarego",
    "sg:orig_category":"Lamiere - Produzione",
    "sg:phone":"+39 0444 834455",
    "sg:postcode":"36040",
    "sg:province":"Vicenza",
    "wof:name":"Sidertaglio Lamiere Snc",
    "wof:placetype":"venue"
},
  "geometry": {"coordinates":[11.405072,45.407455],"type":"Point"}
}