{
  "type": "Feature",
  "properties": {
    "iso:country":"IT",
    "sg:address":"56, Strada Provinciale Nola Cicciano 80030 Camposano",
    "sg:city":"Camposano",
    "sg:classifiers":[
        {
            "category":"Farming",
            "subcategory":"Livestock Farm",
            "type":"Manufacturing & Wholesale Goods"
        }
    ],
    "sg:phone":"+39 081 824 8444",
    "sg:postcode":"80030",
    "sg:province":"Napoli",
    "sg:tags":[
        "agriculture"
    ],
    "wof:name":"Tortora Amedeo (s.r.l.)",
    "wof:placetype":"venue"
},
  "geometry": {"coordinates":[14.538394,40.955956],"type":"Point"}
}