{
  "type": "Feature",
  "properties": {
    "iso:country":"IT",
    "sg:address":"10032 Brandizzo",
    "sg:city":"Brandizzo",
    "sg:orig_category":"Forniture Per Agricoltura E Zootecnia. Animali Domestici",
    "sg:phone":"+39 011 913 7265",
    "sg:postcode":"10032",
    "sg:province":"Torino",
    "wof:name":"Onecta (s.r.l.)",
    "wof:placetype":"venue"
},
  "geometry": {"coordinates":[7.8231058121,45.1707077026],"type":"Point"}
}