{
  "type": "Feature",
  "properties": {
    "iso:country":"IT",
    "sg:address":"54033 Carrara",
    "sg:city":"Carrara",
    "sg:orig_category":"Assicurazioni",
    "sg:phone":"+39 0585 70888",
    "sg:postcode":"54033",
    "sg:province":"Massa-Carrara",
    "wof:name":"Vatt Assicurazioni Di Tognarini Gianni & C. Sas",
    "wof:placetype":"venue"
},
  "geometry": {"coordinates":[10.137488,44.033813],"type":"Point"}
}