{
  "type": "Feature",
  "properties": {
    "iso:country":"IT",
    "sg:address":"12, Via Cirillo Domenico 20154 Milano",
    "sg:city":"Milano",
    "sg:classifiers":[
        {
            "category":"Communications",
            "subcategory":"Newspaper",
            "type":"Services"
        }
    ],
    "sg:phone":"+39 02 3493 4716",
    "sg:postcode":"20154",
    "sg:province":"Milano",
    "sg:tags":[
        "advertising"
    ],
    "wof:name":"Matrix Pro Srl",
    "wof:placetype":"venue"
},
  "geometry": {"coordinates":[9.172015,45.477642],"type":"Point"}
}