{
  "type": "Feature",
  "properties": {
    "addr:full":"2, Via Autostrada 24126 Bergamo Bergamo Bergamo 24126",
    "addr:postcode":"24126;24126",
    "addr:street":"Via Autostrada",
    "iso:country":"IT",
    "sg:address":"2, Via Autostrada 24126 Bergamo",
    "sg:city":"Bergamo",
    "sg:classifiers":[
        {
            "category":"Banks & Credit Unions",
            "subcategory":"Investment Brokerage",
            "type":"Services"
        }
    ],
    "sg:phone":"+39 39035318383",
    "sg:postcode":"24126",
    "sg:province":"Bergamo",
    "sg:tags":[
        "-",
        "transport",
        "related"
    ],
    "wof:name":"Italexpress S.r.l.",
    "wof:placetype":"venue"
},
  "geometry": {"coordinates":[9.667692,45.687534],"type":"Point"}
}