{
  "type": "Feature",
  "properties": {
    "iso:country":"IT",
    "sg:address":"21020 Monvalle",
    "sg:city":"Monvalle",
    "sg:orig_category":"Termotecnica E Riscaldamento, Apparecchiature E Servizi",
    "sg:phone":"+39 0332 799744",
    "sg:postcode":"21020",
    "sg:province":"Varese",
    "wof:name":"De.ma Di De Martis E C. Sdf",
    "wof:placetype":"venue"
},
  "geometry": {"coordinates":[8.865533,45.787632],"type":"Point"}
}