{
  "type": "Feature",
  "properties": {
    "iso:country":"IT",
    "sg:address":"17, Z.i. Brodolini 60025 Loreto",
    "sg:city":"Loreto",
    "sg:orig_category":"Miscellaneous Products",
    "sg:phone":"+39 39071978321",
    "sg:postcode":"60025",
    "sg:province":"Ancona",
    "sg:website":"http://www.paginegialle.it/arpaloreto",
    "wof:name":"A.r.p.a. Loreto Srl",
    "wof:placetype":"venue"
},
  "geometry": {"coordinates":[13.5187568665,43.6158561707],"type":"Point"}
}