{
  "type": "Feature",
  "properties": {
    "addr:full":"V. Nazionale 55 25048 Sonico Sonico Brescia 25048",
    "addr:housenumber":"55",
    "addr:postcode":"25048;25048",
    "iso:country":"IT",
    "sg:address":"V. Nazionale 55 25048 Sonico",
    "sg:city":"Sonico",
    "sg:classifiers":[
        {
            "category":"Shopping",
            "type":"Retail Goods"
        }
    ],
    "sg:phone":"+39 39036475460",
    "sg:postcode":"25048",
    "sg:province":"Brescia",
    "sg:tags":[
        "finished",
        "-",
        "metallic"
    ],
    "wof:name":"Moncini Industrie S.r.l.",
    "wof:placetype":"venue"
},
  "geometry": {"coordinates":[10.3455867767,46.1531295776],"type":"Point"}
}