{
  "type": "Feature",
  "properties": {
    "iso:country":"IT",
    "sg:address":"65019 Pianella",
    "sg:city":"Pianella",
    "sg:orig_category":"Materiali Semilavorati Metallici",
    "sg:phone":"+39 085 972 0019",
    "sg:postcode":"65019",
    "sg:province":"Pescara",
    "wof:name":"Intermark Sas",
    "wof:placetype":"venue"
},
  "geometry": {"coordinates":[14.04435,42.398129],"type":"Point"}
}