{
  "type": "Feature",
  "properties": {
    "addr:full":"24060 Brusaporto Brusaporto Bergamo 24060",
    "addr:postcode":"24060;24060",
    "iso:country":"IT",
    "sg:address":"24060 Brusaporto",
    "sg:city":"Brusaporto",
    "sg:orig_category":"Imprese Pulizia",
    "sg:phone":"+39 035 682742",
    "sg:postcode":"24060",
    "sg:province":"Bergamo",
    "wof:name":"Arcobaleno Srl",
    "wof:placetype":"venue"
},
  "geometry": {"coordinates":[9.744646,45.665657],"type":"Point"}
}