{
  "type": "Feature",
  "properties": {
    "iso:country":"IT",
    "sg:address":"00191 Roma",
    "sg:city":"Roma",
    "sg:orig_category":"Arredo Camera Letto E Complementi. Servizi E Lavori Per Arredamento E Industria Del Legno",
    "sg:phone":"+39 06 333 3454",
    "sg:postcode":"00191",
    "sg:province":"Roma",
    "wof:name":"Ferendeles Maria Cristina",
    "wof:placetype":"venue"
},
  "geometry": {"coordinates":[12.467599,41.93713],"type":"Point"}
}