{
  "type": "Feature",
  "properties": {
    "iso:country":"IT",
    "sg:address":"40050 Monteveglio",
    "sg:city":"Monteveglio",
    "sg:orig_category":"Agriturismo",
    "sg:phone":"+39 051 831429",
    "sg:postcode":"40050",
    "sg:province":"Bologna",
    "wof:name":"Agriturismo La Stadira",
    "wof:placetype":"venue"
},
  "geometry": {"coordinates":[11.096516,44.485767],"type":"Point"}
}