{
  "type": "Feature",
  "properties": {
    "iso:country":"IT",
    "sg:address":"97016 Pozzallo",
    "sg:city":"Pozzallo",
    "sg:orig_category":"Servizi Per Lo Sport E Il Tempo Libero. Alberghi E Strutture Extra Alberghiere",
    "sg:phone":"+39 338 977 3033",
    "sg:postcode":"97016",
    "sg:province":"Ragusa",
    "wof:name":"Cuba Libre Di Giunta E Giudice Snc",
    "wof:placetype":"venue"
},
  "geometry": {"coordinates":[14.862974,36.736912],"type":"Point"}
}