{
  "type": "Feature",
  "properties": {
    "addr:full":"16143 Genova Genova Genova 16143",
    "addr:postcode":"16143;16143",
    "iso:country":"IT",
    "sg:address":"16143 Genova",
    "sg:city":"Genova",
    "sg:orig_category":"Elettrotecnica Industriale, Prodotti E Apparecchiature",
    "sg:phone":"+39 010 508103",
    "sg:postcode":"16143",
    "sg:province":"Genova",
    "sg:website":"http://ideeliguri.it/marchioretto.htm",
    "wof:name":"F.a.l. Di Marchioretto",
    "wof:placetype":"venue"
},
  "geometry": {"coordinates":[8.954864,44.406925],"type":"Point"}
}