{
  "type": "Feature",
  "properties": {
    "addr:full":"Cso Italia 500 44043 Mirabello Mirabello Ferrara 44043",
    "addr:housenumber":"500",
    "addr:postcode":"44043;44043",
    "addr:street":"Cso Italia",
    "iso:country":"IT",
    "sg:address":"Cso Italia 500 44043 Mirabello",
    "sg:city":"Mirabello",
    "sg:classifiers":[
        {
            "category":"Autos & Motor Vehicles",
            "subcategory":"Auto Supplies",
            "type":"Retail Goods"
        }
    ],
    "sg:phone":"+39 0532 849852",
    "sg:postcode":"44043",
    "sg:province":"Ferrara",
    "sg:tags":[
        "automobile",
        "accessory"
    ],
    "sg:website":"www.simoniracing.it",
    "wof:name":"Simoni Racing Spa",
    "wof:placetype":"venue"
},
  "geometry": {"coordinates":[11.451192,44.818851],"type":"Point"}
}