{
  "type": "Feature",
  "properties": {
    "iso:country":"IT",
    "sg:address":"92, Via Volta Alessandro 25063 Gardone Val Trompia",
    "sg:city":"Gardone Val Trompia",
    "sg:classifiers":[
        {
            "category":"Sports & Exercise",
            "subcategory":"Playing Field",
            "type":"Entertainment"
        }
    ],
    "sg:phone":"+39 030 891 2087",
    "sg:postcode":"25063",
    "sg:province":"Brescia",
    "sg:tags":[
        "game"
    ],
    "wof:name":"Batan Di Baga L. & C. (s.n.c.)",
    "wof:placetype":"venue"
},
  "geometry": {"coordinates":[10.222958,45.539829],"type":"Point"}
}