{
  "type": "Feature",
  "properties": {
    "addr:full":"13814 Pollone Pollone Biella 13814",
    "addr:postcode":"13814;13814",
    "iso:country":"IT",
    "sg:address":"13814 Pollone",
    "sg:city":"Pollone",
    "sg:orig_category":"Pompe. Ricambi E Componenti Dei Mezzi Di Trasporto",
    "sg:phone":"+39 015 61673",
    "sg:postcode":"13814",
    "sg:province":"Biella",
    "wof:name":"Peretto Claudio Di Peretto Vanni E Roberto (s.n.c.)",
    "wof:placetype":"venue"
},
  "geometry": {"coordinates":[8.0089101791,45.5755996704],"type":"Point"}
}