{
  "type": "Feature",
  "properties": {
    "iso:country":"IT",
    "sg:address":"Via Socrate 1 - Bernate 22070 Casnate",
    "sg:city":"Casnate",
    "sg:classifiers":[
        {
            "category":"Shopping",
            "subcategory":"Clothing, Apparel, & Fashions",
            "type":"Retail Goods"
        }
    ],
    "sg:phone":"+39 031 565102",
    "sg:postcode":"22070",
    "sg:province":"Como",
    "sg:tags":[
        "clothing",
        "fabric"
    ],
    "wof:name":"Idealtex Srl",
    "wof:placetype":"venue"
},
  "geometry": {"coordinates":[9.082746,45.760746],"type":"Point"}
}