{
  "type": "Feature",
  "properties": {
    "iso:country":"IT",
    "sg:address":"00143 Roma",
    "sg:city":"Roma",
    "sg:orig_category":"Materiali Edili",
    "sg:phone":"+39 06 504 1737",
    "sg:postcode":"00143",
    "sg:province":"Roma",
    "wof:name":"Arporo Ardeatina Pozzolana Roma Srl",
    "wof:placetype":"venue"
},
  "geometry": {"coordinates":[12.50766,41.81485],"type":"Point"}
}