{
  "type": "Feature",
  "properties": {
    "iso:country":"IT",
    "sg:address":"37013 Caprino Veronese",
    "sg:city":"Caprino Veronese",
    "sg:orig_category":"Marmo Ed Affini - Lavorazione",
    "sg:phone":"+39 045 620 0896",
    "sg:postcode":"37013",
    "sg:province":"Verona",
    "wof:name":"Cave Vianini Srl",
    "wof:placetype":"venue"
},
  "geometry": {"coordinates":[10.812489,45.610195],"type":"Point"}
}