{
  "type": "Feature",
  "properties": {
    "iso:country":"IT",
    "sg:address":"35030 Saccolongo",
    "sg:city":"Saccolongo",
    "sg:orig_category":"Lavorazioni Metalli, Stampaggio E Saldatura",
    "sg:phone":"+39 049 801 6397",
    "sg:postcode":"35030",
    "sg:province":"Padova",
    "wof:name":"Promec Snc",
    "wof:placetype":"venue"
},
  "geometry": {"coordinates":[11.74714,45.403816],"type":"Point"}
}