{
  "type": "Feature",
  "properties": {
    "iso:country":"IT",
    "sg:address":"10040 Caselette",
    "sg:city":"Caselette",
    "sg:classifiers":[
        {
            "category":"Manufacturing",
            "subcategory":"Tools & Machinery",
            "type":"Manufacturing & Wholesale Goods"
        }
    ],
    "sg:phone":"+39 011 968 7767",
    "sg:postcode":"10040",
    "sg:province":"Torino",
    "sg:tags":[
        "machining",
        "mechanical"
    ],
    "wof:name":"Omicron Srl",
    "wof:placetype":"venue"
},
  "geometry": {"coordinates":[7.673714,45.113964],"type":"Point"}
}