{
  "type": "Feature",
  "properties": {
    "iso:country":"IT",
    "sg:address":"11, Via Piemonte 53036 Poggibonsi",
    "sg:city":"Poggibonsi",
    "sg:classifiers":[
        {
            "category":"Home & Garden",
            "subcategory":"Home Furnishings",
            "type":"Retail Goods"
        }
    ],
    "sg:phone":"+39 0577 988013",
    "sg:postcode":"53036",
    "sg:province":"Siena",
    "sg:tags":[
        "household"
    ],
    "wof:name":"Italspine (s.n.c.)",
    "wof:placetype":"venue"
},
  "geometry": {"coordinates":[11.134553,43.421001],"type":"Point"}
}