{
  "type": "Feature",
  "properties": {
    "addr:full":"50142 Firenze Firenze Firenze 50142",
    "addr:postcode":"50142;50142",
    "iso:country":"IT",
    "sg:address":"50142 Firenze",
    "sg:city":"Firenze",
    "sg:orig_category":"Forniture Per Edilizia E Lavori Pubblici",
    "sg:phone":"+39 055 201 2148",
    "sg:postcode":"50142",
    "sg:province":"Firenze",
    "sg:website":"http://dimg.interfree.it",
    "wof:name":"Di Martino Gianni",
    "wof:placetype":"venue"
},
  "geometry": {"coordinates":[11.208530426,43.7788772583],"type":"Point"}
}