{
  "type": "Feature",
  "properties": {
    "iso:country":"IT",
    "sg:address":"66, V. Dei Colli 31058 Susegana",
    "sg:city":"Susegana",
    "sg:classifiers":[
        {
            "category":"Professional",
            "subcategory":"Engineering",
            "type":"Services"
        }
    ],
    "sg:phone":"+39 0438 450550",
    "sg:postcode":"31058",
    "sg:province":"Treviso",
    "sg:tags":[
        "machine",
        "-",
        "mechanical"
    ],
    "sg:website":"http://www.cmaspa.com:ws_end: :mark:ws:http://www.paginegialle.it/astoria",
    "wof:name":"Astoria - C.m.a. Spa",
    "wof:placetype":"venue"
},
  "geometry": {"coordinates":[12.260715,45.861794],"type":"Point"}
}