{
  "type": "Feature",
  "properties": {
    "addr:full":"61, Via Manzoni Alessandro 80123 Napoli Napoli Napoli 80123",
    "addr:postcode":"80123;80123",
    "addr:street":"Via Manzoni Alessandro",
    "iso:country":"IT",
    "sg:address":"61, Via Manzoni Alessandro 80123 Napoli",
    "sg:city":"Napoli",
    "sg:classifiers":[
        {
            "category":"Wholesale",
            "subcategory":"Drugs",
            "type":"Manufacturing & Wholesale Goods"
        }
    ],
    "sg:phone":"+39 081 714 2843",
    "sg:postcode":"80123",
    "sg:province":"Napoli",
    "sg:tags":[
        "chemical",
        "pharmaceutical"
    ],
    "wof:name":"S.a.i.m. S.r.l.",
    "wof:placetype":"venue"
},
  "geometry": {"coordinates":[14.282479,40.904049],"type":"Point"}
}