{
  "type": "Feature",
  "properties": {
    "iso:country":"IT",
    "sg:address":"12037 Saluzzo",
    "sg:city":"Saluzzo",
    "sg:orig_category":"Prodotti Di Base E Forniture Per Industria Alimentare E Bevande. Carta, Cartone E Prodotti Primari. Forniture Per Attivita' Commerciali Ed Artigianali",
    "sg:phone":"+39 0175 43261",
    "sg:postcode":"12037",
    "sg:province":"Cuneo",
    "wof:name":"Nuova Icas Di Ballario Matteo E C. S.n.c.",
    "wof:placetype":"venue"
},
  "geometry": {"coordinates":[7.4936537743,44.6420555115],"type":"Point"}
}