{
  "type": "Feature",
  "properties": {
    "iso:country":"IT",
    "sg:address":"16, Via Del Candel 32100 Belluno",
    "sg:city":"Belluno",
    "sg:classifiers":[
        {
            "category":"Shopping",
            "type":"Retail Goods"
        }
    ],
    "sg:phone":"+39 0437 931777",
    "sg:postcode":"32100",
    "sg:province":"Belluno",
    "sg:tags":[
        "finished",
        "-",
        "metallic"
    ],
    "wof:name":"Cast Tools S.r.l.",
    "wof:placetype":"venue"
},
  "geometry": {"coordinates":[12.217590332,46.1399650574],"type":"Point"}
}