{
  "type": "Feature",
  "properties": {
    "addr:full":"Viale Del Progresso 37038 Soave Soave Verona 37038",
    "addr:postcode":"37038;37038",
    "addr:street":"Viale Del Progresso",
    "iso:country":"IT",
    "sg:address":"Viale Del Progresso 37038 Soave",
    "sg:city":"Soave",
    "sg:classifiers":[
        {
            "category":"Manufacturing",
            "subcategory":"Metals",
            "type":"Manufacturing & Wholesale Goods"
        }
    ],
    "sg:phone":"+39 045 761 4000",
    "sg:postcode":"37038",
    "sg:province":"Verona",
    "sg:tags":[
        "metallurgy",
        "metalworking"
    ],
    "wof:name":"F.i.z. (s.r.l.)",
    "wof:placetype":"venue"
},
  "geometry": {"coordinates":[11.2388439178,45.4102859497],"type":"Point"}
}