{
  "type": "Feature",
  "properties": {
    "iso:country":"IT",
    "sg:address":"50055 Lastra A Signa",
    "sg:city":"Lastra a Signa",
    "sg:orig_category":"Forniture Per Abbigliamento E Pelletterie",
    "sg:phone":"+39 055 872 3136",
    "sg:postcode":"50055",
    "sg:province":"Firenze",
    "wof:name":"Bolleri Giovanna",
    "wof:placetype":"venue"
},
  "geometry": {"coordinates":[11.12504673,43.8031311035],"type":"Point"}
}