{
  "type": "Feature",
  "properties": {
    "addr:full":"20090 Segrate Segrate Milano 20090",
    "addr:postcode":"20090;20090",
    "iso:country":"IT",
    "sg:address":"20090 Segrate",
    "sg:city":"Segrate",
    "sg:classifiers":[
        {
            "category":"Health Services",
            "subcategory":"Health Practitioner",
            "type":"Services"
        }
    ],
    "sg:phone":"+39 02 2641 4564",
    "sg:postcode":"20090",
    "sg:province":"Milano",
    "sg:tags":[
        "medici"
    ],
    "wof:name":"Rambaldi Renato",
    "wof:placetype":"venue"
},
  "geometry": {"coordinates":[9.2916936874,45.5011444092],"type":"Point"}
}