{
  "type": "Feature",
  "properties": {
    "addr:full":"Via Antonio Gramsci 4 20014 Nerviano Nerviano Milano 20014",
    "addr:housenumber":"4",
    "addr:postcode":"20014;20014",
    "addr:street":"Via Antonio Gramsci",
    "iso:country":"IT",
    "sg:address":"Via Antonio Gramsci 4 20014 Nerviano",
    "sg:city":"Nerviano",
    "sg:classifiers":[
        {
            "category":"Shopping",
            "subcategory":"Pharmacy",
            "type":"Retail Goods"
        }
    ],
    "sg:phone":"+39 0331 587717",
    "sg:postcode":"20014",
    "sg:province":"Milano",
    "sg:tags":[
        "pharmaceutical"
    ],
    "wof:name":"Lampugnani Farmaceutici Spa",
    "wof:placetype":"venue"
},
  "geometry": {"coordinates":[8.9421186447,45.5601501465],"type":"Point"}
}