{
  "type": "Feature",
  "properties": {
    "addr:full":"36063 Marostica Marostica Vicenza 36063",
    "addr:postcode":"36063;36063",
    "iso:country":"IT",
    "sg:address":"36063 Marostica",
    "sg:city":"Marostica",
    "sg:classifiers":[
        {
            "category":"Health Services",
            "subcategory":"Health Practitioner",
            "type":"Services"
        }
    ],
    "sg:phone":"+39 0424 780657",
    "sg:postcode":"36063",
    "sg:province":"Vicenza",
    "sg:tags":[
        "medici"
    ],
    "wof:name":"Bassetto Dr. Bruno",
    "wof:placetype":"venue"
},
  "geometry": {"coordinates":[11.520066,45.530273],"type":"Point"}
}