{
  "type": "Feature",
  "properties": {
    "iso:country":"IT",
    "sg:address":"70125 Bari",
    "sg:city":"Bari",
    "sg:orig_category":"Arredo Camera Letto E Complementi",
    "sg:phone":"+39 080 542 5687",
    "sg:postcode":"70125",
    "sg:province":"Bari",
    "wof:name":"Stea Arredamenti Di Rutigliano Vincenzo",
    "wof:placetype":"venue"
},
  "geometry": {"coordinates":[16.875813,41.003986],"type":"Point"}
}