{
  "type": "Feature",
  "properties": {
    "iso:country":"IT",
    "sg:address":"17024 Finale Ligure",
    "sg:city":"Finale Ligure",
    "sg:orig_category":"Associazioni Tecniche E Socio-economiche",
    "sg:phone":"+39 019 681037",
    "sg:postcode":"17024",
    "sg:province":"Savona",
    "wof:name":"Comunita' Montana Pollupice",
    "wof:placetype":"venue"
},
  "geometry": {"coordinates":[8.345165,44.169987],"type":"Point"}
}