{
  "type": "Feature",
  "properties": {
    "addr:full":"00179 Roma Roma Roma 00179",
    "addr:postcode":"00179;00179",
    "iso:country":"IT",
    "sg:address":"00179 Roma",
    "sg:city":"Roma",
    "sg:orig_category":"Insegne Luminose",
    "sg:phone":"+39 06 789450",
    "sg:postcode":"00179",
    "sg:province":"Roma",
    "wof:name":"Montagna Bruno Pubblicolor",
    "wof:placetype":"venue"
},
  "geometry": {"coordinates":[12.514493,41.870815],"type":"Point"}
}