{
  "type": "Feature",
  "properties": {
    "addr:full":"Via Marsala 345b 51015 Monsummano Terme Monsummano Terme Pistoia 51015",
    "addr:housenumber":"345b",
    "addr:postcode":"51015;51015",
    "addr:street":"Via Marsala",
    "iso:country":"IT",
    "sg:address":"Via Marsala 345b 51015 Monsummano Terme",
    "sg:city":"Monsummano Terme",
    "sg:classifiers":[
        {
            "category":"Manufacturing",
            "subcategory":"Tools & Machinery",
            "type":"Manufacturing & Wholesale Goods"
        }
    ],
    "sg:phone":"+39 0572 952952",
    "sg:postcode":"51015",
    "sg:province":"Pistoia",
    "sg:tags":[
        "making",
        "shoe"
    ],
    "wof:name":"Due Emme Srl",
    "wof:placetype":"venue"
},
  "geometry": {"coordinates":[10.811042,43.858425],"type":"Point"}
}