{
  "type": "Feature",
  "properties": {
    "addr:full":"67051 Avezzano L'Aquila 67051",
    "addr:postcode":"67051;67051",
    "iso:country":"IT",
    "sg:address":"67051 Avezzano",
    "sg:orig_category":"Motori Ed Organi Di Trasmissione. Ricambi E Componenti Dei Mezzi Di Trasporto",
    "sg:phone":"+39 0863 410728",
    "sg:postcode":"67051",
    "sg:province":"L'Aquila",
    "wof:name":"Rif Spa",
    "wof:placetype":"venue"
},
  "geometry": {"coordinates":[13.4066085815,42.3480415344],"type":"Point"}
}