{
  "type": "Feature",
  "properties": {
    "iso:country":"IT",
    "sg:address":"Via Alpiolo 71 28017 San Maurizio D'opaglio",
    "sg:orig_category":"Fittings, Valves",
    "sg:phone":"+39 0322 96246",
    "sg:postcode":"28017",
    "sg:province":"Novara",
    "wof:name":"Fortis Rubinetterie Speciali Srl",
    "wof:placetype":"venue"
},
  "geometry": {"coordinates":[8.4035320282,45.7760505676],"type":"Point"}
}