{
  "type": "Feature",
  "properties": {
    "iso:country":"IT",
    "sg:address":"48010 Godo",
    "sg:orig_category":"Abbigliamento Esterno, Maglierie E Pelliccerie. Forniture Per Abbigliamento E Pelletterie",
    "sg:postcode":"48010",
    "sg:province":"Ravenna",
    "wof:name":"Valeriani Benito Raccolta Di Valeriani Benito & C. S.n.c.",
    "wof:placetype":"venue"
},
  "geometry": {"coordinates":[12.276143,44.481586],"type":"Point"}
}