{
  "type": "Feature",
  "properties": {
    "iso:country":"IT",
    "sg:address":"35031 Abano Terme",
    "sg:city":"Abano Terme",
    "sg:orig_category":"Accessori Moda D'abbigliamento. Forniture Per Abbigliamento E Pelletterie. Shopping",
    "sg:phone":"+39 049 866 9190",
    "sg:postcode":"35031",
    "sg:province":"Padova",
    "wof:name":"Emme Due Di Micheli Ida",
    "wof:placetype":"venue"
},
  "geometry": {"coordinates":[11.779762,45.348301],"type":"Point"}
}