{
  "type": "Feature",
  "properties": {
    "iso:country":"IT",
    "sg:address":"43, V. Calvi 20047 Brugherio",
    "sg:city":"Brugherio",
    "sg:classifiers":[
        {
            "category":"Manufacturing",
            "subcategory":"Metals",
            "type":"Manufacturing & Wholesale Goods"
        }
    ],
    "sg:phone":"+39 39039878799",
    "sg:postcode":"20047",
    "sg:province":"Milano",
    "sg:tags":[
        "processing"
    ],
    "sg:website":"http://www.rettificaturabonaldi.it",
    "wof:name":"Bonaldi Rettificatura",
    "wof:placetype":"venue"
},
  "geometry": {"coordinates":[9.310213089,45.5407447815],"type":"Point"}
}