{
  "type": "Feature",
  "properties": {
    "iso:country":"IT",
    "sg:address":"43100 Parma",
    "sg:city":"Moletolo",
    "sg:orig_category":"Macchine, Impianti Ed Attrezzature Industria Chimica. Vetro: Prodotti E Lavorazioni",
    "sg:phone":"+39 0521 7931",
    "sg:postcode":"43100",
    "sg:province":"Parma",
    "wof:name":"Bormioli Luigi (s.p.a.)",
    "wof:placetype":"venue"
},
  "geometry": {"coordinates":[10.306764,44.838413],"type":"Point"}
}