{
  "type": "Feature",
  "properties": {
    "iso:country":"IT",
    "sg:address":"20134 Milano",
    "sg:city":"Milano",
    "sg:orig_category":"Impiantistica E Prodotti Tecnologici Per Edilizia. Termotecnica E Riscaldamento, Apparecchiature E Servizi",
    "sg:phone":"+39 02 2641 3522",
    "sg:postcode":"20134",
    "sg:province":"Milano",
    "wof:name":"Pmi Impianti (s.r.l.)",
    "wof:placetype":"venue"
},
  "geometry": {"coordinates":[9.237073,45.488705],"type":"Point"}
}