{
  "type": "Feature",
  "properties": {
    "iso:country":"IT",
    "sg:address":"116, V. Vittorio Veneto 60044 Fabriano",
    "sg:city":"Fabriano",
    "sg:classifiers":[
        {
            "category":"Shopping",
            "subcategory":"Computers & Home Electronics",
            "type":"Retail Goods"
        }
    ],
    "sg:phone":"+39 390 732 6901",
    "sg:postcode":"60044",
    "sg:province":"Ancona",
    "sg:tags":[
        "electronic",
        "electrical",
        "equipment"
    ],
    "sg:website":"http://www.a.merloni.it",
    "wof:name":"Antonio Merloni Spa",
    "wof:placetype":"venue"
},
  "geometry": {"coordinates":[12.913619,43.339237],"type":"Point"}
}