{
  "type": "Feature",
  "properties": {
    "iso:country":"IT",
    "sg:address":"21050 Saltrio",
    "sg:city":"Saltrio",
    "sg:orig_category":"Impiantistica E Prodotti Tecnologici Per Edilizia. Elettronica Professionale E Di Consumo",
    "sg:phone":"+39 0332 488494",
    "sg:postcode":"21050",
    "sg:province":"Varese",
    "wof:name":"F.e.b. Elettrica Snc",
    "wof:placetype":"venue"
},
  "geometry": {"coordinates":[8.921741,45.871426],"type":"Point"}
}