{
  "type": "Feature",
  "properties": {
    "iso:country":"IT",
    "sg:address":"20093 Cologno Monzese",
    "sg:city":"Cologno Monzese",
    "sg:orig_category":"Prodotti Alimentari",
    "sg:phone":"+39 02 254 2906",
    "sg:postcode":"20093",
    "sg:province":"Milano",
    "wof:name":"Gassi Antonia",
    "wof:placetype":"venue"
},
  "geometry": {"coordinates":[9.2750167847,45.5400810242],"type":"Point"}
}