{
  "type": "Feature",
  "properties": {
    "iso:country":"IT",
    "sg:address":"25071 Agnosine",
    "sg:city":"Agnosine",
    "sg:orig_category":"Non-classified Establishments",
    "sg:phone":"+39 036 589 6021",
    "sg:postcode":"25071",
    "sg:province":"Brescia",
    "wof:name":"Inoxriv Di Rivadossi Francesco E Figli (s.p.a.)",
    "wof:placetype":"venue"
},
  "geometry": {"coordinates":[10.348217,45.639217],"type":"Point"}
}