{
  "type": "Feature",
  "properties": {
    "iso:country":"IT",
    "sg:address":"10122 Torino",
    "sg:city":"Torino",
    "sg:orig_category":"Ortopedia - Articoli",
    "sg:phone":"+39 011 436 7295",
    "sg:postcode":"10122",
    "sg:province":"Torino",
    "wof:name":"Sanitas Snc Di Deriu E. & C.",
    "wof:placetype":"venue"
},
  "geometry": {"coordinates":[7.678338,45.076416],"type":"Point"}
}