{
  "type": "Feature",
  "properties": {
    "iso:country":"IT",
    "sg:address":"Via A. Volta, 13 - San Michele 51031 Agliana",
    "sg:city":"Agliana",
    "sg:classifiers":[
        {
            "category":"Train Station",
            "subcategory":"Light Rail",
            "type":"Transportation"
        }
    ],
    "sg:phone":"+39 0574 719370",
    "sg:postcode":"51031",
    "sg:province":"Pistoia",
    "sg:tags":[
        "yarn",
        "semi-worsted"
    ],
    "wof:name":"Lanificio Diemmeci Srl",
    "wof:placetype":"venue"
},
  "geometry": {"coordinates":[10.918524,43.932156],"type":"Point"}
}