{
  "type": "Feature",
  "properties": {
    "iso:country":"IT",
    "sg:address":"17, Via Della Cultura 36050 Sovizzo",
    "sg:city":"Sovizzo",
    "sg:classifiers":[
        {
            "category":"Professional",
            "subcategory":"Engineering",
            "type":"Services"
        }
    ],
    "sg:phone":"+39 0444 376245",
    "sg:postcode":"36050",
    "sg:province":"Vicenza",
    "sg:tags":[
        "machine",
        "-",
        "mechanical"
    ],
    "wof:name":"Invimec (s.r.l.)",
    "wof:placetype":"venue"
},
  "geometry": {"coordinates":[11.452816,45.527889],"type":"Point"}
}