{
  "type": "Feature",
  "properties": {
    "iso:country":"IT",
    "sg:address":"Via I Maggio 8 20068 Peschiera Borromeo",
    "sg:city":"Peschiera Borromeo",
    "sg:classifiers":[
        {
            "category":"Wholesale",
            "subcategory":"Plants",
            "type":"Manufacturing & Wholesale Goods"
        }
    ],
    "sg:phone":"+39 02 547 0578",
    "sg:postcode":"20068",
    "sg:province":"Milano",
    "sg:tags":[
        "cooling",
        "industrial"
    ],
    "sg:website":"www.aerfrigor.com",
    "wof:name":"Aerfrigor Srl",
    "wof:placetype":"venue"
},
  "geometry": {"coordinates":[9.277258,45.41666],"type":"Point"}
}