{
  "type": "Feature",
  "properties": {
    "iso:country":"IT",
    "sg:address":"Via Piscina 13 10060 Frossasco",
    "sg:city":"Frossasco",
    "sg:orig_category":"Chipboards",
    "sg:phone":"+39 0121 351211",
    "sg:postcode":"10060",
    "sg:province":"Torino",
    "sg:website":"www.annovati.it",
    "wof:name":"Annovati Spa",
    "wof:placetype":"venue"
},
  "geometry": {"coordinates":[7.379508,44.916534],"type":"Point"}
}