{
  "type": "Feature",
  "properties": {
    "iso:country":"IT",
    "sg:address":"50053 Empoli",
    "sg:city":"Empoli",
    "sg:orig_category":"Autolinee",
    "sg:phone":"+39 0571 590458",
    "sg:postcode":"50053",
    "sg:province":"Firenze",
    "wof:name":"Camion Mercato Srl",
    "wof:placetype":"venue"
},
  "geometry": {"coordinates":[10.965776,43.721287],"type":"Point"}
}