{
  "type": "Feature",
  "properties": {
    "addr:full":"24035 Curno Curno Bergamo 24035",
    "addr:postcode":"24035;24035",
    "iso:country":"IT",
    "sg:address":"24035 Curno",
    "sg:city":"Curno",
    "sg:orig_category":"Antinfortunistica - Attrezzature Ed Articoli",
    "sg:phone":"+39 035 611305",
    "sg:postcode":"24035",
    "sg:province":"Bergamo",
    "wof:name":"Calzature Burini Srl",
    "wof:placetype":"venue"
},
  "geometry": {"coordinates":[9.622209,45.687962],"type":"Point"}
}