{
  "type": "Feature",
  "properties": {
    "addr:full":"57016 Rosignano Solvay Rosignano Solvay Livorno 57016",
    "addr:postcode":"57016;57016",
    "iso:country":"IT",
    "sg:address":"57016 Rosignano Solvay",
    "sg:city":"Rosignano Solvay",
    "sg:orig_category":"Macchine, Impianti E Forniture Per Industria Grafica, Cartaria E Cartotecnica",
    "sg:phone":"+39 0586 764202",
    "sg:postcode":"57016",
    "sg:province":"Livorno",
    "wof:name":"Maccioni E Nardi S.r.l.",
    "wof:placetype":"venue"
},
  "geometry": {"coordinates":[10.465351,43.393841],"type":"Point"}
}