{
  "type": "Feature",
  "properties": {
    "iso:country":"IT",
    "sg:address":"20094 Corsico",
    "sg:city":"Corsico",
    "sg:orig_category":"Prodotti E Manufatti In Materie Plastiche",
    "sg:phone":"+39 02 447 1466",
    "sg:postcode":"20094",
    "sg:province":"Milano",
    "wof:name":"Its - A (s.r.l.)",
    "wof:placetype":"venue"
},
  "geometry": {"coordinates":[9.1168851852,45.4337387085],"type":"Point"}
}