{
  "type": "Feature",
  "properties": {
    "addr:full":"41037 Mirandola Mirandola Modena 41037",
    "addr:postcode":"41037;41037",
    "iso:country":"IT",
    "sg:address":"41037 Mirandola",
    "sg:city":"Mirandola",
    "sg:classifiers":[
        {
            "category":"Health Services",
            "subcategory":"Hospital",
            "type":"Services"
        }
    ],
    "sg:phone":"+39 0535 27252",
    "sg:postcode":"41037",
    "sg:province":"Modena",
    "sg:tags":[
        "equipment",
        "systems",
        "supply"
    ],
    "wof:name":"Probio Srl",
    "wof:placetype":"venue"
},
  "geometry": {"coordinates":[11.08847,44.928791],"type":"Point"}
}