{
  "type": "Feature",
  "properties": {
    "addr:full":"20154 Milano Milano Milano 20154",
    "addr:postcode":"20154;20154",
    "iso:country":"IT",
    "sg:address":"20154 Milano",
    "sg:city":"Milano",
    "sg:orig_category":"Impianti, Attrezzature E Forniture Sanitarie Ed Ospedaliere",
    "sg:phone":"+39 02 331 1634",
    "sg:postcode":"20154",
    "sg:province":"Milano",
    "wof:name":"Selva Bonino U. Srl",
    "wof:placetype":"venue"
},
  "geometry": {"coordinates":[9.179262,45.480484],"type":"Point"}
}