{
  "type": "Feature",
  "properties": {
    "iso:country":"IT",
    "sg:address":"30, Via Corino 20035 Lissone",
    "sg:city":"Lissone",
    "sg:classifiers":[
        {
            "category":"Home & Garden",
            "subcategory":"Home Furnishings",
            "type":"Retail Goods"
        }
    ],
    "sg:phone":"+39 39039480244",
    "sg:postcode":"20035",
    "sg:province":"Milano",
    "sg:tags":[
        "household"
    ],
    "wof:name":"Lineaotto (s.a.s.)",
    "wof:placetype":"venue"
},
  "geometry": {"coordinates":[9.22824,45.613415],"type":"Point"}
}