{
  "type": "Feature",
  "properties": {
    "iso:country":"IT",
    "sg:address":"31020 San Fior",
    "sg:city":"San Fior",
    "sg:orig_category":"Prodotti Alimentari",
    "sg:phone":"+39 0438 260280",
    "sg:postcode":"31020",
    "sg:province":"Treviso",
    "wof:name":"Dal Cin Ginseng Srl",
    "wof:placetype":"venue"
},
  "geometry": {"coordinates":[12.3223361969,45.8911857605],"type":"Point"}
}