{
  "type": "Feature",
  "properties": {
    "addr:full":"31/33, V. Lussemburgo Z.I. Sud49100 Padova",
    "addr:housenumber":"31 / 33;sud49100",
    "addr:street":"V.;Z.I.",
    "iso:country":"IT",
    "sg:address":"31/33, V. Lussemburgo",
    "sg:classifiers":[
        {
            "category":"Autos & Motor Vehicles",
            "subcategory":"Automobile Sales",
            "type":"Retail Goods"
        }
    ],
    "sg:phone":"+39 049 762 1621",
    "sg:province":"Z.I. Sud49100 Padova",
    "sg:tags":[
        "equipment",
        "transport"
    ],
    "sg:website":"http://www.atala.it",
    "wof:name":"Atala Spa",
    "wof:placetype":"venue"
},
  "geometry": {"coordinates":[11.876589,45.409569],"type":"Point"}
}