{
  "type": "Feature",
  "properties": {
    "addr:full":"Via Bovio 14; Banosa Di Puglia; 70053 Bari 70053",
    "addr:housenumber":"14",
    "addr:postcode":"70053;70053",
    "addr:street":"Via Bovio;Puglia",
    "iso:country":"IT",
    "sg:address":"Via Bovio 14; Banosa Di Puglia; 70053",
    "sg:classifiers":[
        {
            "category":"Banks & Credit Unions",
            "subcategory":"Bank",
            "type":"Services"
        }
    ],
    "sg:phone":"+39 0883 611337",
    "sg:postcode":"70053",
    "sg:province":"Bari",
    "wof:name":"Banco Di Napoli Spa",
    "wof:placetype":"venue"
},
  "geometry": {"coordinates":[16.067764,41.222828],"type":"Point"}
}