{
  "type": "Feature",
  "properties": {
    "iso:country":"IT",
    "sg:address":"9, Piazza Piccapietra 16121 Genova",
    "sg:city":"Genova",
    "sg:classifiers":[
        {
            "category":"Marine",
            "type":"Transportation"
        }
    ],
    "sg:phone":"+39 39010539841",
    "sg:postcode":"16121",
    "sg:province":"Genova",
    "sg:tags":[
        "transport",
        "sea"
    ],
    "wof:name":"Cp Ships Agencies Italy Srl",
    "wof:placetype":"venue"
},
  "geometry": {"coordinates":[8.935907,44.408134],"type":"Point"}
}