{
  "type": "Feature",
  "properties": {
    "iso:country":"IT",
    "sg:address":"34, Via Collebeato 25127 Brescia",
    "sg:city":"Brescia",
    "sg:classifiers":[
        {
            "category":"Shopping",
            "subcategory":"Stationery & Office Supplies",
            "type":"Retail Goods"
        }
    ],
    "sg:phone":"+39 39030302781",
    "sg:postcode":"25127",
    "sg:province":"Brescia",
    "sg:tags":[
        "professional"
    ],
    "wof:name":"Societa' Italiana Attrezzature Negozi (s.p.a.)",
    "wof:placetype":"venue"
},
  "geometry": {"coordinates":[10.2092533112,45.5672836304],"type":"Point"}
}