{
  "type": "Feature",
  "properties": {
    "addr:full":"21047 Saronno Saronno Varese 21047",
    "addr:postcode":"21047;21047",
    "iso:country":"IT",
    "sg:address":"21047 Saronno",
    "sg:city":"Saronno",
    "sg:orig_category":"Impiantistica E Prodotti Tecnologici Per Edilizia. Elettrotecnica Professionale E Di Consumo. Telecomunicazioni E Telefonia, Impianti, Apparecchi E Servizi",
    "sg:phone":"+39 02 9670 9085",
    "sg:postcode":"21047",
    "sg:province":"Varese",
    "sg:website":"http://maticautomazioni.it",
    "wof:name":"Matic Srl",
    "wof:placetype":"venue"
},
  "geometry": {"coordinates":[9.047067,45.638943],"type":"Point"}
}