{
  "type": "Feature",
  "properties": {
    "addr:full":"20011 Corbetta Corbetta Milano 20011",
    "addr:postcode":"20011;20011",
    "iso:country":"IT",
    "sg:address":"20011 Corbetta",
    "sg:city":"Corbetta",
    "sg:orig_category":"Depuratori E Depuranti",
    "sg:phone":"+39 02 9727 2162",
    "sg:postcode":"20011",
    "sg:province":"Milano",
    "wof:name":"Biochem Srl",
    "wof:placetype":"venue"
},
  "geometry": {"coordinates":[9.226185,45.507904],"type":"Point"}
}