{
  "type": "Feature",
  "properties": {
    "addr:full":"29, Via Solferino 20020 Ceriano Laghetto Ceriano Laghetto Milano 20020",
    "addr:postcode":"20020;20020",
    "addr:street":"Via Solferino",
    "iso:country":"IT",
    "sg:address":"29, Via Solferino 20020 Ceriano Laghetto",
    "sg:city":"Ceriano Laghetto",
    "sg:classifiers":[
        {
            "category":"Bars & Pubs",
            "subcategory":"Nightclub",
            "type":"Food & Drink"
        }
    ],
    "sg:phone":"+39 02 9670 4386",
    "sg:postcode":"20020",
    "sg:province":"Milano",
    "sg:tags":[
        "cake",
        "bread"
    ],
    "wof:name":"G.r. Lombardi (s.r.l.)",
    "wof:placetype":"venue"
},
  "geometry": {"coordinates":[9.0547,45.631123],"type":"Point"}
}