{
  "type": "Feature",
  "properties": {
    "addr:full":"Via Milano 20 26100 Cremona Cremona Cremona 26100",
    "addr:housenumber":"20",
    "addr:postcode":"26100;26100",
    "addr:street":"Via Milano",
    "iso:country":"IT",
    "sg:address":"Via Milano 20 26100 Cremona",
    "sg:city":"Cremona",
    "sg:classifiers":[
        {
            "category":"Autos & Motor Vehicles",
            "subcategory":"Recreational Vehicle Sales",
            "type":"Retail Goods"
        }
    ],
    "sg:phone":"+39 0372 41901",
    "sg:postcode":"26100",
    "sg:province":"Cremona",
    "sg:tags":[
        "trailer"
    ],
    "sg:website":"www.piacenzarimorchi.it",
    "wof:name":"Piacenza Spa",
    "wof:placetype":"venue"
},
  "geometry": {"coordinates":[9.993817,45.143726],"type":"Point"}
}