{
  "type": "Feature",
  "properties": {
    "addr:full":"4, Localita' Cretaz 11024 Pontey Pontey Aosta 11024",
    "addr:postcode":"11024;11024",
    "addr:street":"Localita ' Cretaz",
    "iso:country":"IT",
    "sg:address":"4, Localita' Cretaz 11024 Pontey",
    "sg:city":"Pontey",
    "sg:classifiers":[
        {
            "category":"Building & Trades",
            "subcategory":"Construction",
            "type":"Services"
        }
    ],
    "sg:phone":"+39 39016630368",
    "sg:postcode":"11024",
    "sg:province":"Aosta",
    "sg:tags":[
        "work",
        "public"
    ],
    "wof:name":"Cos. Mo. Srl",
    "wof:placetype":"venue"
},
  "geometry": {"coordinates":[7.583708,45.73708],"type":"Point"}
}