{
  "type": "Feature",
  "properties": {
    "addr:full":"22100 Como Como Como 22100",
    "addr:postcode":"22100;22100",
    "iso:country":"IT",
    "sg:address":"22100 Como",
    "sg:city":"Como",
    "sg:orig_category":"Autolinee",
    "sg:phone":"+39 031 247111",
    "sg:postcode":"22100",
    "sg:province":"Como",
    "sg:website":"http://www.sptcomo.it",
    "wof:name":"S.p.t. - Soc. Pubblica Trasporti Spa",
    "wof:placetype":"venue"
},
  "geometry": {"coordinates":[9.05248,45.838306],"type":"Point"}
}