{
  "type": "Feature",
  "properties": {
    "addr:full":"20121 Milano Milano Milano 20121",
    "addr:postcode":"20121;20121",
    "iso:country":"IT",
    "sg:address":"20121 Milano",
    "sg:city":"Milano",
    "sg:orig_category":"Pubblicita', Marketing E Comunicazione",
    "sg:phone":"+39 02 782604",
    "sg:postcode":"20121",
    "sg:province":"Milano",
    "sg:website":"http://www.sevenpromotion.it",
    "wof:name":"Seven Promotion Sas",
    "wof:placetype":"venue"
},
  "geometry": {"coordinates":[9.200928688,45.4725837708],"type":"Point"}
}