{
  "type": "Feature",
  "properties": {
    "iso:country":"IT",
    "sg:address":"91100 Trapani",
    "sg:city":"Trapani",
    "sg:orig_category":"Termotecnica E Riscaldamento, Apparecchiature E Servizi",
    "sg:phone":"+39 0923 25825",
    "sg:postcode":"91100",
    "sg:province":"Trapani",
    "wof:name":"Giacalone Salvatore",
    "wof:placetype":"venue"
},
  "geometry": {"coordinates":[12.533182,38.02322],"type":"Point"}
}