{
  "type": "Feature",
  "properties": {
    "addr:full":"25030 Castel Mella Castel Mella Brescia 25030",
    "addr:postcode":"25030;25030",
    "iso:country":"IT",
    "sg:address":"25030 Castel Mella",
    "sg:city":"Castel Mella",
    "sg:orig_category":"Lavorazioni Meccaniche E Servizi",
    "sg:phone":"+39 030 358 1084",
    "sg:postcode":"25030",
    "sg:province":"Brescia",
    "sg:website":"http://www.fedrival.it",
    "wof:name":"Fedrival Di Fedrigo Adriano & C. Snc",
    "wof:placetype":"venue"
},
  "geometry": {"coordinates":[10.15624,45.491356],"type":"Point"}
}