{
  "type": "Feature",
  "properties": {
    "iso:country":"IT",
    "sg:address":"74024 Manduria",
    "sg:city":"Manduria",
    "sg:orig_category":"Mobili Giardini E Terrazzi - Produzione E Ingrosso",
    "sg:phone":"+39 099 979 6172",
    "sg:postcode":"74024",
    "sg:province":"Taranto",
    "wof:name":"Stil Bambu'",
    "wof:placetype":"venue"
},
  "geometry": {"coordinates":[17.6457500458,40.4012413025],"type":"Point"}
}