{
  "type": "Feature",
  "properties": {
    "addr:full":"20162 Milano Milano Milano 20162",
    "addr:postcode":"20162;20162",
    "iso:country":"IT",
    "sg:address":"20162 Milano",
    "sg:city":"Milano",
    "sg:orig_category":"Ospedali E Servizi Sanitari. Servizi Sociali. Associazioni Ed Organismi Di Interesse Pubblico",
    "sg:phone":"+39 02 647 0452",
    "sg:postcode":"20162",
    "sg:province":"Milano",
    "wof:name":"Associazione Salute Donna",
    "wof:placetype":"venue"
},
  "geometry": {"coordinates":[9.296162,45.505367],"type":"Point"}
}