{
  "type": "Feature",
  "properties": {
    "addr:full":"1, Contrada Rivolta Del Re 86039 Termoli Termoli Campobasso 86039",
    "addr:postcode":"86039;86039",
    "addr:street":"Contrada Rivolta Del Re",
    "iso:country":"IT",
    "sg:address":"1, Contrada Rivolta Del Re 86039 Termoli",
    "sg:city":"Termoli",
    "sg:classifiers":[
        {
            "category":"Food & Beverages",
            "subcategory":"Groceries & Convenience Stores",
            "type":"Retail Goods"
        }
    ],
    "sg:phone":"+39 0875 755003",
    "sg:postcode":"86039",
    "sg:province":"Campobasso",
    "sg:tags":[
        "product",
        "related"
    ],
    "wof:name":"Ipagel Srl",
    "wof:placetype":"venue"
},
  "geometry": {"coordinates":[15.005030632,41.9418106079],"type":"Point"}
}