{
  "type": "Feature",
  "properties": {
    "iso:country":"IT",
    "sg:address":"20068 Peschiera Borromeo",
    "sg:city":"Peschiera Borromeo",
    "sg:orig_category":"Forniture Alle Strutture Ricettive. Macchine E Impianti Per Attivita' Commerciali Ed Artigianali",
    "sg:phone":"+39 02 5530 3411",
    "sg:postcode":"20068",
    "sg:province":"Milano",
    "wof:name":"Diego Espresso Di Di Giorgio Giannitto Diego",
    "wof:placetype":"venue"
},
  "geometry": {"coordinates":[9.3170166016,45.4279289246],"type":"Point"}
}