{
  "type": "Feature",
  "properties": {
    "iso:country":"IT",
    "sg:address":"55100 Lucca",
    "sg:city":"Lucca",
    "sg:orig_category":"Ospedali E Servizi Sanitari",
    "sg:phone":"+39 0583 53092",
    "sg:postcode":"55100",
    "sg:province":"Lucca",
    "wof:name":"Nalin Raoul",
    "wof:placetype":"venue"
},
  "geometry": {"coordinates":[10.490099,43.843327],"type":"Point"}
}