{
  "type": "Feature",
  "properties": {
    "addr:full":"20151 Milano Milano Milano 20151",
    "addr:postcode":"20151;20151",
    "iso:country":"IT",
    "sg:address":"20151 Milano",
    "sg:city":"Milano",
    "sg:orig_category":"Professionisti - Studi E Servizi Ed Associazioni Di Interesse Aziendale. Associazioni Ed Organismi Di Interesse Pubblico. Chiese Ed Associazioni Religiose",
    "sg:phone":"+39 02 308 5057",
    "sg:postcode":"20151",
    "sg:province":"Milano",
    "wof:name":"Cooperazione Internazionale",
    "wof:placetype":"venue"
},
  "geometry": {"coordinates":[9.1155824661,45.4877052307],"type":"Point"}
}