{
  "type": "Feature",
  "properties": {
    "iso:country":"IT",
    "sg:address":"80027 Frattamaggiore",
    "sg:city":"Frattamaggiore",
    "sg:orig_category":"Non-classified Establishments",
    "sg:phone":"+39 081 880 6661",
    "sg:postcode":"80027",
    "sg:province":"Napoli",
    "wof:name":"Cesteria Meridionale Snc Del Prete Franco",
    "wof:placetype":"venue"
},
  "geometry": {"coordinates":[14.271726,40.938717],"type":"Point"}
}