{
  "type": "Feature",
  "properties": {
    "iso:country":"IT",
    "sg:address":"20010 Vittuone",
    "sg:city":"Vittuone",
    "sg:orig_category":"Zootecnia E Pesca, Allevamento Piccoli Animali",
    "sg:phone":"+39 02 9011 1063",
    "sg:postcode":"20010",
    "sg:province":"Milano",
    "wof:name":"Avicola 90 (s.r.l.)",
    "wof:placetype":"venue"
},
  "geometry": {"coordinates":[8.943653,45.480858],"type":"Point"}
}