{
  "type": "Feature",
  "properties": {
    "addr:full":"22063 Cantu' Como 22063",
    "addr:postcode":"22063;22063",
    "addr:street":"Cantu ' Como",
    "iso:country":"IT",
    "sg:address":"22063 Cantu'",
    "sg:orig_category":"Metalli E Leghe",
    "sg:phone":"+39 031 732021",
    "sg:postcode":"22063",
    "sg:province":"Como",
    "wof:name":"F.p. Arredi (s.n.c.)",
    "wof:placetype":"venue"
},
  "geometry": {"coordinates":[9.1220083237,45.754447937],"type":"Point"}
}