{
  "type": "Feature",
  "properties": {
    "iso:country":"IT",
    "sg:address":"33100 Udine",
    "sg:city":"Udine",
    "sg:orig_category":"Giornali E Riviste - Editori",
    "sg:phone":"+39 0432 5271",
    "sg:postcode":"33100",
    "sg:province":"Udine",
    "sg:website":"http://www.messaggeroveneto.it",
    "wof:name":"Editoriale Messaggero Veneto",
    "wof:placetype":"venue"
},
  "geometry": {"coordinates":[13.259665,46.026012],"type":"Point"}
}