{
  "type": "Feature",
  "properties": {
    "iso:country":"IT",
    "sg:address":"22060 Carugo",
    "sg:city":"Carugo",
    "sg:classifiers":[
        {
            "category":"Home & Garden",
            "subcategory":"Hardware",
            "type":"Retail Goods"
        }
    ],
    "sg:phone":"+39 031 758428",
    "sg:postcode":"22060",
    "sg:province":"Como",
    "wof:name":"Lanzini Luigi & C. Sas",
    "wof:placetype":"venue"
},
  "geometry": {"coordinates":[9.201219,45.725018],"type":"Point"}
}