{
  "type": "Feature",
  "properties": {
    "iso:country":"IT",
    "sg:address":"62010 Montefano",
    "sg:city":"Montefano",
    "sg:orig_category":"Fonderie Pressofusione",
    "sg:phone":"+39 0733 850102",
    "sg:postcode":"62010",
    "sg:province":"Macerata",
    "wof:name":"A. & C. Snc Di Accattoli Gilberto",
    "wof:placetype":"venue"
},
  "geometry": {"coordinates":[13.4393892288,43.4122047424],"type":"Point"}
}