{
  "type": "Feature",
  "properties": {
    "addr:full":"Via Dante 73 20049 Concorezzo Concorezzo Milano 20049",
    "addr:housenumber":"73",
    "addr:postcode":"20049;20049",
    "addr:street":"Via Dante",
    "iso:country":"IT",
    "sg:address":"Via Dante 73 20049 Concorezzo",
    "sg:city":"Concorezzo",
    "sg:classifiers":[
        {
            "category":"Manufacturing",
            "subcategory":"Chemicals & Compounds",
            "type":"Manufacturing & Wholesale Goods"
        }
    ],
    "sg:phone":"+39 039 604 0220",
    "sg:postcode":"20049",
    "sg:province":"Milano",
    "sg:tags":[
        "industry",
        "plant"
    ],
    "sg:website":"www.biicbianchi.com",
    "wof:name":"Biic Bianchi Spa",
    "wof:placetype":"venue"
},
  "geometry": {"coordinates":[9.1881408691,45.4636878967],"type":"Point"}
}