{
  "type": "Feature",
  "properties": {
    "addr:full":"Via Nazionale 5 84015 Nocera Superiore Nocera Superiore Salerno 84015",
    "addr:housenumber":"5",
    "addr:postcode":"84015;84015",
    "addr:street":"Via Nazionale",
    "iso:country":"IT",
    "sg:address":"Via Nazionale 5 84015 Nocera Superiore",
    "sg:city":"Nocera Superiore",
    "sg:classifiers":[
        {
            "category":"Home & Garden",
            "subcategory":"Carpets & Floor Coverings",
            "type":"Retail Goods"
        }
    ],
    "sg:phone":"+39 081 931011",
    "sg:postcode":"84015",
    "sg:province":"Salerno",
    "sg:tags":[
        "tile",
        "ceramic",
        "printed"
    ],
    "sg:website":"www.francescodemaio.it",
    "wof:name":"Francesco De Maio Ceramica Srl",
    "wof:placetype":"venue"
},
  "geometry": {"coordinates":[14.6838579178,40.7344779968],"type":"Point"}
}