{
  "type": "Feature",
  "properties": {
    "iso:country":"IT",
    "sg:address":"10, V. Volta 24060 San Paolo D'argon",
    "sg:classifiers":[
        {
            "category":"Wholesale",
            "subcategory":"Medical Equipment & Supplies",
            "type":"Manufacturing & Wholesale Goods"
        }
    ],
    "sg:phone":"+39 39035958240",
    "sg:postcode":"24060",
    "sg:province":"Bergamo",
    "sg:tags":[
        "-",
        "health",
        "instrument"
    ],
    "sg:website":"http://www.fiapp.com:ws_end: :mark:ws:http://www.paginegialle.it/fiappinternational",
    "wof:name":"Fiapp International Srl",
    "wof:placetype":"venue"
},
  "geometry": {"coordinates":[9.756733,45.702053],"type":"Point"}
}