{
  "type": "Feature",
  "properties": {
    "addr:full":"09134 Cagliari Cagliari Cagliari 09134",
    "addr:postcode":"09134;09134",
    "iso:country":"IT",
    "sg:address":"09134 Cagliari",
    "sg:city":"Cagliari",
    "sg:orig_category":"Servizi E Lavori Per Abbigliamento E Pelletterie. Scuole E Servizi Scolastici. Ricerca, Selezione E Formazione Del Personale",
    "sg:phone":"+39 070 500931",
    "sg:postcode":"09134",
    "sg:province":"Cagliari",
    "wof:name":"Sartoria Graffi Di Moda Di Farci Cabanu G.",
    "wof:placetype":"venue"
},
  "geometry": {"coordinates":[9.134995,39.24102],"type":"Point"}
}