{
  "type": "Feature",
  "properties": {
    "iso:country":"IT",
    "sg:address":"Via Como 92 20036 Meda",
    "sg:city":"Meda",
    "sg:classifiers":[
        {
            "category":"Shopping",
            "subcategory":"Crafts & Fabrics",
            "type":"Retail Goods"
        }
    ],
    "sg:phone":"+39 036 234 3590",
    "sg:postcode":"20036",
    "sg:province":"Milano",
    "sg:tags":[
        "trade",
        "timber"
    ],
    "sg:website":"www.seralvo.com",
    "wof:name":"Giacomo Seralvo & Figli Spa",
    "wof:placetype":"venue"
},
  "geometry": {"coordinates":[9.161358,45.669048],"type":"Point"}
}