{
  "type": "Feature",
  "properties": {
    "iso:country":"IT",
    "sg:address":"Contrada Pozzo Nuovo 73056 Taurisano",
    "sg:city":"Taurisano",
    "sg:classifiers":[
        {
            "category":"Real Estate",
            "subcategory":"Architect",
            "type":"Services"
        }
    ],
    "sg:phone":"+39 0833 625830",
    "sg:postcode":"73056",
    "sg:province":"Lecce",
    "sg:tags":[
        "textile",
        "clothing"
    ],
    "wof:name":"Melileo S.r.l.",
    "wof:placetype":"venue"
},
  "geometry": {"coordinates":[18.219654,39.944878],"type":"Point"}
}