{
  "type": "Feature",
  "properties": {
    "addr:full":"64, Via Gaeta 00185 Roma Roma Roma 00185",
    "addr:postcode":"00185;00185",
    "addr:street":"Via Gaeta",
    "iso:country":"IT",
    "sg:address":"64, Via Gaeta 00185 Roma",
    "sg:city":"Roma",
    "sg:orig_category":"Miscellaneous Products",
    "sg:phone":"+39 39064441026",
    "sg:postcode":"00185",
    "sg:province":"Roma",
    "wof:name":"Renatovini S.r.l.",
    "wof:placetype":"venue"
},
  "geometry": {"coordinates":[12.5002670288,41.9043807983],"type":"Point"}
}