{
  "type": "Feature",
  "properties": {
    "iso:country":"IT",
    "sg:address":"20084 Lacchiarella",
    "sg:city":"Lacchiarella",
    "sg:orig_category":"Cine-foto-ottica",
    "sg:phone":"+39 02 9007 6140",
    "sg:postcode":"20084",
    "sg:province":"Milano",
    "wof:name":"Tecnifoto (s.n.c.)",
    "wof:placetype":"venue"
},
  "geometry": {"coordinates":[9.136889,45.322853],"type":"Point"}
}