{
  "type": "Feature",
  "properties": {
    "iso:country":"IT",
    "sg:address":"00171 Roma",
    "sg:city":"Roma",
    "sg:orig_category":"Servizi E Lavori Per Arredamento E Industria Del Legno. Arte Ed Artigianato Artistico",
    "sg:phone":"+39 06 218 4479",
    "sg:postcode":"00171",
    "sg:province":"Roma",
    "wof:name":"Spidalieri Paolo",
    "wof:placetype":"venue"
},
  "geometry": {"coordinates":[12.563372,41.888149],"type":"Point"}
}