{
  "type": "Feature",
  "properties": {
    "iso:country":"IT",
    "sg:address":"36061 Bassano Del Grappa",
    "sg:city":"Bassano del Grappa",
    "sg:orig_category":"Macchine, Strumenti Ed Apparecchi Per Attivita' Industriali",
    "sg:phone":"+39 0424 228744",
    "sg:postcode":"36061",
    "sg:province":"Vicenza",
    "wof:name":"Linx Di Bertoncello A. & Salvatico S. Snc",
    "wof:placetype":"venue"
},
  "geometry": {"coordinates":[11.745575,45.752079],"type":"Point"}
}