{
  "type": "Feature",
  "properties": {
    "iso:country":"IT",
    "sg:address":"37135 Verona",
    "sg:city":"Verona",
    "sg:orig_category":"Autofficine E Centri Assistenza",
    "sg:phone":"+39 045 504923",
    "sg:postcode":"37135",
    "sg:province":"Verona",
    "wof:name":"Compri Luciano",
    "wof:placetype":"venue"
},
  "geometry": {"coordinates":[10.974664,45.412758],"type":"Point"}
}