{
  "type": "Feature",
  "properties": {
    "iso:country":"IT",
    "sg:address":"23852 Garlate",
    "sg:city":"Garlate",
    "sg:orig_category":"Apparecchiature Ed Attrezzature Meccaniche",
    "sg:phone":"+39 0341 680017",
    "sg:postcode":"23852",
    "sg:province":"Lecco",
    "wof:name":"Reac Officina Meccanica",
    "wof:placetype":"venue"
},
  "geometry": {"coordinates":[9.401069,45.810478],"type":"Point"}
}