{
  "type": "Feature",
  "properties": {
    "iso:country":"IT",
    "sg:address":"30, Via Brenta 36033 Isola Vicentina",
    "sg:city":"Isola Vicentina",
    "sg:classifiers":[
        {
            "category":"Food & Beverages",
            "subcategory":"Dairy",
            "type":"Retail Goods"
        }
    ],
    "sg:phone":"+39 0444 976944",
    "sg:postcode":"36033",
    "sg:province":"Vicenza",
    "sg:tags":[
        "product"
    ],
    "wof:name":"Caglio Star (s.p.a.)",
    "wof:placetype":"venue"
},
  "geometry": {"coordinates":[11.463975,45.618904],"type":"Point"}
}