{
  "type": "Feature",
  "properties": {
    "iso:country":"IT",
    "sg:address":"61032 Fano",
    "sg:city":"Fano",
    "sg:orig_category":"Ospedali E Servizi Sanitari",
    "sg:phone":"+39 0721 860626",
    "sg:postcode":"61032",
    "sg:province":"Pesaro E Urbino",
    "wof:name":"Ciancamerla Fausta",
    "wof:placetype":"venue"
},
  "geometry": {"coordinates":[13.006179,43.836243],"type":"Point"}
}