{
  "type": "Feature",
  "properties": {
    "iso:country":"IT",
    "sg:address":"41048 Castelvecchio",
    "sg:city":"Castelvecchio",
    "sg:orig_category":"Macchine Ed Impianti Per Edilizia E Lavori Pubblici. Impianti E Attrezzature Per Lo Sport E Il Tempo Libero",
    "sg:phone":"+39 0536 894726",
    "sg:postcode":"41048",
    "sg:province":"Modena",
    "wof:name":"Macchioni Alessandro",
    "wof:placetype":"venue"
},
  "geometry": {"coordinates":[10.672594,44.450233],"type":"Point"}
}