{
  "type": "Feature",
  "properties": {
    "iso:country":"IT",
    "sg:address":"00040 Roma",
    "sg:orig_category":"Forniture Per Attivita' Industriali",
    "sg:phone":"+39 06 7984 8788",
    "sg:postcode":"00040",
    "sg:province":"Roma",
    "wof:name":"Carbone Luigi",
    "wof:placetype":"venue"
},
  "geometry": {"coordinates":[12.5999126434,41.8139419556],"type":"Point"}
}