{
  "type": "Feature",
  "properties": {
    "addr:full":"50068 Rufina Rufina Firenze 50068",
    "addr:postcode":"50068;50068",
    "iso:country":"IT",
    "sg:address":"50068 Rufina",
    "sg:city":"Rufina",
    "sg:orig_category":"Forniture Per Agricoltura E Zootecnia. Prodotti Chimici Secondari. Macchine E Forniture Per Ecologia E Smaltimento Rifiuti",
    "sg:phone":"+39 055 839 7723",
    "sg:postcode":"50068",
    "sg:province":"Firenze",
    "wof:name":"Nocentini Gianni",
    "wof:placetype":"venue"
},
  "geometry": {"coordinates":[11.5361728668,43.8243713379],"type":"Point"}
}