{
  "type": "Feature",
  "properties": {
    "addr:full":"28040 Varallo Pombia Varallo Pombia Novara 28040",
    "addr:postcode":"28040;28040",
    "iso:country":"IT",
    "sg:address":"28040 Varallo Pombia",
    "sg:city":"Varallo Pombia",
    "sg:orig_category":"Articoli Per Imballaggio E Confezionamento",
    "sg:phone":"+39 0321 921110",
    "sg:postcode":"28040",
    "sg:province":"Novara",
    "sg:website":"http://www.verbanofilm.com",
    "wof:name":"Verbano Film Srl",
    "wof:placetype":"venue"
},
  "geometry": {"coordinates":[8.617059,45.673317],"type":"Point"}
}