{
  "type": "Feature",
  "properties": {
    "addr:full":"Via Parco Piaggio 15061 Arquata Scrivia Arquata Scrivia Alessandria 15061",
    "addr:postcode":"15061;15061",
    "addr:street":"Via Parco Piaggio;Scrivia",
    "iso:country":"IT",
    "sg:address":"Via Parco Piaggio 15061 Arquata Scrivia",
    "sg:city":"Arquata Scrivia",
    "sg:classifiers":[
        {
            "category":"Autos & Motor Vehicles",
            "subcategory":"Automobile Sales",
            "type":"Retail Goods"
        }
    ],
    "sg:phone":"+39 0143 667602",
    "sg:postcode":"15061",
    "sg:province":"Alessandria",
    "sg:tags":[
        "equipment",
        "transport"
    ],
    "wof:name":"Officine Di Arquata '96 Srl",
    "wof:placetype":"venue"
},
  "geometry": {"coordinates":[8.616951,44.913216],"type":"Point"}
}