{
  "type": "Feature",
  "properties": {
    "addr:full":"Via Dei Fabrizzio 57 33034 Fagagna Fagagna Udine 33034",
    "addr:housenumber":"57",
    "addr:postcode":"33034;33034",
    "addr:street":"Via Dei Fabrizzio",
    "iso:country":"IT",
    "sg:address":"Via Dei Fabrizzio 57 33034 Fagagna",
    "sg:city":"Fagagna",
    "sg:classifiers":[
        {
            "category":"Shopping",
            "subcategory":"Books",
            "type":"Retail Goods"
        }
    ],
    "sg:phone":"+39 0432 800081",
    "sg:postcode":"33034",
    "sg:province":"Udine",
    "sg:website":"www.magnusedizioni.it",
    "wof:name":"Magnus Edizioni Spa",
    "wof:placetype":"venue"
},
  "geometry": {"coordinates":[13.230724,46.064941],"type":"Point"}
}