{
  "type": "Feature",
  "properties": {
    "addr:full":"43044 Collecchio Collecchio Parma 43044",
    "addr:postcode":"43044;43044",
    "iso:country":"IT",
    "sg:address":"43044 Collecchio",
    "sg:city":"Collecchio",
    "sg:orig_category":"Lavorazioni Metalli, Stampaggio E Saldatura",
    "sg:phone":"+39 0521 805725",
    "sg:postcode":"43044",
    "sg:province":"Parma",
    "wof:name":"Isa Vascelli Srl",
    "wof:placetype":"venue"
},
  "geometry": {"coordinates":[10.211473,44.75758],"type":"Point"}
}