{
  "type": "Feature",
  "properties": {
    "iso:country":"IT",
    "sg:address":"10122 Torino",
    "sg:city":"Torino",
    "sg:orig_category":"Comune E Servizi Comunali",
    "sg:phone":"+39 011 442050",
    "sg:postcode":"10122",
    "sg:province":"Torino",
    "sg:website":"http://www.comune.torino.it",
    "wof:name":"Citt\u00c0 Di Torino - Progetto Speciale Comunicazione",
    "wof:placetype":"venue"
},
  "geometry": {"coordinates":[7.680715,45.073292],"type":"Point"}
}