{
  "type": "Feature",
  "properties": {
    "iso:country":"IT",
    "sg:address":"95126 Catania",
    "sg:city":"Catania",
    "sg:orig_category":"Centri Di Estetica E Cosmesi E Servizi",
    "sg:phone":"+39 095 495377",
    "sg:postcode":"95126",
    "sg:province":"Catania",
    "wof:name":"D & D Di D'agata Daniela",
    "wof:placetype":"venue"
},
  "geometry": {"coordinates":[15.108105,37.527691],"type":"Point"}
}