{
  "type": "Feature",
  "properties": {
    "iso:country":"IT",
    "sg:address":"Corso Nizza 10; Cuneo; 12100",
    "sg:city":"Cuneo",
    "sg:classifiers":[
        {
            "category":"Banks & Credit Unions",
            "subcategory":"Bank",
            "type":"Services"
        }
    ],
    "sg:phone":"+39 0171 55431",
    "sg:postcode":"12100",
    "sg:province":"Cuneo",
    "wof:name":"Banca Nazionale Del Lavoro Spa",
    "wof:placetype":"venue"
},
  "geometry": {"coordinates":[7.546241,44.387947],"type":"Point"}
}