{
  "type": "Feature",
  "properties": {
    "iso:country":"IT",
    "sg:address":"112, Via Trento Trieste Fossalunga 31050 Vedelago",
    "sg:city":"Fossalunga",
    "sg:orig_category":"Miscellaneous Products",
    "sg:phone":"+39 0423 489310",
    "sg:postcode":"31050",
    "sg:province":"Treviso",
    "wof:name":"M.g.m. S.p.a.",
    "wof:placetype":"venue"
},
  "geometry": {"coordinates":[12.057012558,45.6836090088],"type":"Point"}
}