{
  "type": "Feature",
  "properties": {
    "iso:country":"IT",
    "sg:address":"23873 Missaglia",
    "sg:city":"Missaglia",
    "sg:orig_category":"Filati E Materie Prime Tessili",
    "sg:phone":"+39 039 924 1286",
    "sg:postcode":"23873",
    "sg:province":"Lecco",
    "wof:name":"Roccatura Macotex S.a.s. Di Delle Donne C. & C.",
    "wof:placetype":"venue"
},
  "geometry": {"coordinates":[9.3475580215,45.6973991394],"type":"Point"}
}