{
  "type": "Feature",
  "properties": {
    "iso:country":"IT",
    "sg:address":"Via G. Fattori 7 40033 Casalecchio Di Reno",
    "sg:city":"Casalecchio di Reno",
    "sg:classifiers":[
        {
            "category":"Wholesale",
            "subcategory":"Vending Machines",
            "type":"Manufacturing & Wholesale Goods"
        }
    ],
    "sg:phone":"+39 051 613 1930",
    "sg:postcode":"40033",
    "sg:province":"Bologna",
    "sg:tags":[
        "boring",
        "combined",
        "machines",
        "milling"
    ],
    "wof:name":"Su-matic Italia Srl",
    "wof:placetype":"venue"
},
  "geometry": {"coordinates":[11.270576,44.464855],"type":"Point"}
}