{
  "type": "Feature",
  "properties": {
    "iso:country":"IT",
    "sg:address":"Via Trieste, 19; Leporano; 74020",
    "sg:city":"Leporano",
    "sg:classifiers":[
        {
            "category":"Banks & Credit Unions",
            "subcategory":"Bank",
            "type":"Services"
        }
    ],
    "sg:phone":"+39 099 638921",
    "sg:postcode":"74020",
    "sg:province":"Taranto",
    "wof:name":"Cassa Rurale Ed Artigiana",
    "wof:placetype":"venue"
},
  "geometry": {"coordinates":[17.334087,40.384167],"type":"Point"}
}