{
  "type": "Feature",
  "properties": {
    "iso:country":"IT",
    "sg:address":"Via Del Molo 64 19126 La Spezia",
    "sg:orig_category":"Asbestos",
    "sg:phone":"+39 0187 515180",
    "sg:province":"SP",
    "wof:name":"Esse Emme Srl",
    "wof:placetype":"venue"
},
  "geometry": {"coordinates":[9.8545379639,44.1127815247],"type":"Point"}
}