{
  "type": "Feature",
  "properties": {
    "iso:country":"IT",
    "sg:address":"60015 Falconara Marittima",
    "sg:city":"Falconara Marittima",
    "sg:orig_category":"Prodotti Chimici Di Base. Forniture Per Attivita' Industriali",
    "sg:phone":"+39 071 912826",
    "sg:postcode":"60015",
    "sg:province":"Ancona",
    "wof:name":"Barchiesi Nello",
    "wof:placetype":"venue"
},
  "geometry": {"coordinates":[13.3827009201,43.623210907],"type":"Point"}
}