{
  "type": "Feature",
  "properties": {
    "iso:country":"IT",
    "sg:address":"3, Via Gioberti 20090 Trezzano Sul Naviglio",
    "sg:city":"Trezzano sul Naviglio",
    "sg:classifiers":[
        {
            "category":"Manufacturing",
            "subcategory":"Tools & Machinery",
            "type":"Manufacturing & Wholesale Goods"
        }
    ],
    "sg:phone":"+39 02 4840 0626",
    "sg:postcode":"20090",
    "sg:province":"Milano",
    "sg:tags":[
        "environment",
        "equipment",
        "-"
    ],
    "wof:name":"Ats Air Treatment Srl",
    "wof:placetype":"venue"
},
  "geometry": {"coordinates":[9.071378,45.423588],"type":"Point"}
}