{
  "type": "Feature",
  "properties": {
    "iso:country":"IT",
    "sg:address":"30026 Portogruaro",
    "sg:city":"Portogruaro",
    "sg:orig_category":"Fotografia Industriale",
    "sg:phone":"+39 0421 73152",
    "sg:postcode":"30026",
    "sg:province":"Venezia",
    "wof:name":"D'aniello Anna Maria",
    "wof:placetype":"venue"
},
  "geometry": {"coordinates":[12.8574113846,45.7940864563],"type":"Point"}
}