{
  "type": "Feature",
  "properties": {
    "iso:country":"IT",
    "sg:address":"22026 Maslianico",
    "sg:city":"Maslianico",
    "sg:orig_category":"Climatizzazione E Condizionamento, Apparecchiature E Servizi",
    "sg:phone":"+39 031 512656",
    "sg:postcode":"22026",
    "sg:province":"Como",
    "wof:name":"Facchin Antonio",
    "wof:placetype":"venue"
},
  "geometry": {"coordinates":[9.051488,45.840851],"type":"Point"}
}