{
  "type": "Feature",
  "properties": {
    "iso:country":"IT",
    "sg:address":"1, V. Della Meccanica 41018 San Cesario Sul Panato",
    "sg:orig_category":"Miscellaneous Products",
    "sg:phone":"+39 39059952611",
    "sg:postcode":"41018",
    "sg:province":"Modena",
    "sg:website":"http://www.cschiclin.it",
    "wof:name":"Csc",
    "wof:placetype":"venue"
},
  "geometry": {"coordinates":[11.0307807922,44.5905685425],"type":"Point"}
}