{
  "type": "Feature",
  "properties": {
    "iso:country":"IT",
    "sg:address":"87067 Rossano",
    "sg:city":"Rossano",
    "sg:orig_category":"Abbigliamento Esterno, Maglierie E Pelliccerie. Shopping",
    "sg:phone":"+39 0983 513590",
    "sg:postcode":"87067",
    "sg:province":"Cosenza",
    "wof:name":"Gruppo Curia",
    "wof:placetype":"venue"
},
  "geometry": {"coordinates":[16.06237,39.232037],"type":"Point"}
}