{
  "type": "Feature",
  "properties": {
    "iso:country":"IT",
    "sg:address":"36034 Malo",
    "sg:city":"Malo",
    "sg:orig_category":"Mole, Dischi E Lame Abrasive E Diamantate",
    "sg:phone":"+39 0445 580750",
    "sg:postcode":"36034",
    "sg:province":"Vicenza",
    "wof:name":"Italdiamant Spa",
    "wof:placetype":"venue"
},
  "geometry": {"coordinates":[11.4121923447,45.6652259827],"type":"Point"}
}