{
  "type": "Feature",
  "properties": {
    "addr:full":"20136 Milano Milano Milano 20136",
    "addr:postcode":"20136;20136",
    "iso:country":"IT",
    "sg:address":"20136 Milano",
    "sg:city":"Milano",
    "sg:orig_category":"Etichette",
    "sg:phone":"+39 02 837 3415",
    "sg:postcode":"20136",
    "sg:province":"Milano",
    "wof:name":"Italspelta Snc Di Leonetti Michele & C.",
    "wof:placetype":"venue"
},
  "geometry": {"coordinates":[9.179267,45.446823],"type":"Point"}
}