{
  "type": "Feature",
  "properties": {
    "iso:country":"IT",
    "sg:address":"73, Via Sornianese 59100 Prato",
    "sg:city":"Prato",
    "sg:classifiers":[
        {
            "category":"Professional",
            "subcategory":"Engineering",
            "type":"Services"
        }
    ],
    "sg:phone":"+39 0574 663278",
    "sg:postcode":"59100",
    "sg:province":"Prato",
    "sg:tags":[
        "machine",
        "-",
        "mechanical"
    ],
    "wof:name":"Giemme Meccanica Snc",
    "wof:placetype":"venue"
},
  "geometry": {"coordinates":[11.046106,43.882133],"type":"Point"}
}