{
  "type": "Feature",
  "properties": {
    "iso:country":"IT",
    "sg:address":"Via Bastioni Maggiori 15; Bressanone; 39042",
    "sg:city":"Bressanone",
    "sg:classifiers":[
        {
            "category":"Banks & Credit Unions",
            "subcategory":"Bank",
            "type":"Services"
        }
    ],
    "sg:phone":"+39 0472 801515",
    "sg:postcode":"39042",
    "sg:province":"Bolzano/Bozen",
    "wof:name":"Credito Italiano Spa",
    "wof:placetype":"venue"
},
  "geometry": {"coordinates":[11.655529,46.716969],"type":"Point"}
}