{
  "type": "Feature",
  "properties": {
    "addr:full":"50020 Montefiridolfi Montefiridolfi Firenze 50020",
    "addr:postcode":"50020;50020",
    "addr:street":"Montefiridolfi",
    "iso:country":"IT",
    "sg:address":"50020 Montefiridolfi",
    "sg:city":"Montefiridolfi",
    "sg:orig_category":"Agenzie D'affari E Servizi Commerciali",
    "sg:phone":"+39 055 824 4509",
    "sg:postcode":"50020",
    "sg:province":"Firenze",
    "wof:name":"Tricots Consulting Di Mendler M. E C. Snc",
    "wof:placetype":"venue"
},
  "geometry": {"coordinates":[11.186884,43.628063],"type":"Point"}
}