{
  "type": "Feature",
  "properties": {
    "addr:full":"Via Marano 96 33050 Carlino Carlino Udine 33050",
    "addr:housenumber":"96",
    "addr:postcode":"33050;33050",
    "addr:street":"Via Marano",
    "iso:country":"IT",
    "sg:address":"Via Marano 96 33050 Carlino",
    "sg:city":"Carlino",
    "sg:orig_category":"Fish, Frozen",
    "sg:phone":"+39 0431 67921",
    "sg:postcode":"33050",
    "sg:province":"Udine",
    "wof:name":"Friulpesca Srl",
    "wof:placetype":"venue"
},
  "geometry": {"coordinates":[13.1725740433,45.7852783203],"type":"Point"}
}