{
  "type": "Feature",
  "properties": {
    "iso:country":"IT",
    "sg:address":"9, Via Ruvo 70052 Bisceglie",
    "sg:city":"Bisceglie",
    "sg:classifiers":[
        {
            "category":"Shopping",
            "subcategory":"Clothing, Apparel, & Fashions",
            "type":"Retail Goods"
        }
    ],
    "sg:phone":"+39 080 395 8135",
    "sg:postcode":"70052",
    "sg:province":"Bari",
    "sg:tags":[
        "clothes"
    ],
    "wof:name":"Confezioni Lady Grazia",
    "wof:placetype":"venue"
},
  "geometry": {"coordinates":[16.504976,41.231773],"type":"Point"}
}