{
  "type": "Feature",
  "properties": {
    "addr:full":"Via Aldo Moro 24050 Orio Al Serio Orio al Serio Bergamo 24050",
    "addr:postcode":"24050;24050",
    "addr:street":"Via Aldo Moro",
    "iso:country":"IT",
    "sg:address":"Via Aldo Moro 24050 Orio Al Serio",
    "sg:city":"Orio al Serio",
    "sg:classifiers":[
        {
            "category":"Wholesale",
            "subcategory":"Medical Equipment & Supplies",
            "type":"Manufacturing & Wholesale Goods"
        }
    ],
    "sg:phone":"+39 39035526420",
    "sg:postcode":"24050",
    "sg:province":"Bergamo",
    "sg:tags":[
        "-",
        "health",
        "instrument"
    ],
    "wof:name":"Zeta M (s.r.l.)",
    "wof:placetype":"venue"
},
  "geometry": {"coordinates":[9.705609,45.661392],"type":"Point"}
}