{
  "type": "Feature",
  "properties": {
    "addr:full":"43/a, Via Provinciale Nocera Sarno 84014 Nocera Inferiore Nocera Inferiore Salerno 84014",
    "addr:housenumber":"43 / a",
    "addr:postcode":"84014;84014",
    "addr:street":"Via Provinciale Nocera",
    "iso:country":"IT",
    "sg:address":"43/a, Via Provinciale Nocera Sarno 84014 Nocera Inferiore",
    "sg:city":"Nocera Inferiore",
    "sg:classifiers":[
        {
            "category":"Manufacturing",
            "subcategory":"Metals",
            "type":"Manufacturing & Wholesale Goods"
        }
    ],
    "sg:phone":"+39 39081937018",
    "sg:postcode":"84014",
    "sg:province":"Salerno",
    "sg:tags":[
        "metallurgy",
        "metalworking"
    ],
    "wof:name":"Ve.p.r.al. S.r.l.",
    "wof:placetype":"venue"
},
  "geometry": {"coordinates":[14.765912056,40.6779556274],"type":"Point"}
}