{
  "type": "Feature",
  "properties": {
    "iso:country":"IT",
    "sg:address":"Via De Amicis Ang; Conversano; 70014",
    "sg:city":"Conversano",
    "sg:classifiers":[
        {
            "category":"Banks & Credit Unions",
            "subcategory":"Bank",
            "type":"Services"
        }
    ],
    "sg:phone":"+39 080 495 2044",
    "sg:postcode":"70014",
    "sg:province":"Bari",
    "wof:name":"Rolo Banca 1473 Spa",
    "wof:placetype":"venue"
},
  "geometry": {"coordinates":[17.124821,40.966057],"type":"Point"}
}