{
  "type": "Feature",
  "properties": {
    "addr:full":"73011 Alezio Alezio Lecce 73011",
    "addr:postcode":"73011;73011",
    "iso:country":"IT",
    "sg:address":"73011 Alezio",
    "sg:city":"Alezio",
    "sg:orig_category":"Prodotti Alimentari",
    "sg:phone":"+39 0833 283052",
    "sg:postcode":"73011",
    "sg:province":"Lecce",
    "wof:name":"Capursi Pasquale",
    "wof:placetype":"venue"
},
  "geometry": {"coordinates":[18.0657119751,40.0627975464],"type":"Point"}
}