{
  "type": "Feature",
  "properties": {
    "iso:country":"IT",
    "sg:address":"16124 Genova",
    "sg:city":"Genova",
    "sg:orig_category":"Trasporti E Spedizioni Merci",
    "sg:phone":"+39 010 251 8171",
    "sg:postcode":"16124",
    "sg:province":"Genova",
    "sg:website":"http://www.danilo-parodi.com",
    "wof:name":"D. & P. Snc Di Danilo Parodi",
    "wof:placetype":"venue"
},
  "geometry": {"coordinates":[8.975618,44.396839],"type":"Point"}
}