{
  "type": "Feature",
  "properties": {
    "iso:country":"IT",
    "sg:address":"3, Strada Provinciale 47854 Monte Colombo",
    "sg:city":"Monte Colombo",
    "sg:classifiers":[
        {
            "category":"Retail",
            "subcategory":"Animal Services",
            "type":"Services"
        }
    ],
    "sg:phone":"+39 0541 985402",
    "sg:postcode":"47854",
    "sg:province":"Rimini",
    "sg:tags":[
        "breeding"
    ],
    "wof:name":"I.c.m. Industrie Chimiche Minerarie S.p.a.",
    "wof:placetype":"venue"
},
  "geometry": {"coordinates":[12.586713,43.92416],"type":"Point"}
}