{
  "type": "Feature",
  "properties": {
    "iso:country":"IT",
    "sg:address":"51, Via Agarolla 31020 San Polo Di Piave",
    "sg:city":"San Polo di Piave",
    "sg:classifiers":[
        {
            "category":"Home & Garden",
            "subcategory":"Home Furnishings",
            "type":"Retail Goods"
        }
    ],
    "sg:phone":"+39 0422 856624",
    "sg:postcode":"31020",
    "sg:province":"Treviso",
    "sg:tags":[
        "household"
    ],
    "wof:name":"Selene Salotti S.r.l.",
    "wof:placetype":"venue"
},
  "geometry": {"coordinates":[12.391959,45.783646],"type":"Point"}
}