{
  "type": "Feature",
  "properties": {
    "addr:full":"19, Via Gardale Trav. I 25036 Palazzolo Sull'oglio Brescia 25036",
    "addr:postcode":"25036;25036",
    "addr:street":"Via Gardale Trav. I",
    "iso:country":"IT",
    "sg:address":"19, Via Gardale Trav. I 25036 Palazzolo Sull'oglio",
    "sg:classifiers":[
        {
            "category":"Manufacturing",
            "subcategory":"Metals",
            "type":"Manufacturing & Wholesale Goods"
        }
    ],
    "sg:phone":"+39 030 740 1833",
    "sg:postcode":"25036",
    "sg:province":"Brescia",
    "sg:tags":[
        "metallurgy",
        "metalworking"
    ],
    "wof:name":"Fonderie Vignoni Di Vignoni Giulio & C. (s.n.c.)",
    "wof:placetype":"venue"
},
  "geometry": {"coordinates":[10.2229576111,45.5398292542],"type":"Point"}
}