{
  "type": "Feature",
  "properties": {
    "iso:country":"IT",
    "sg:address":"20131 Milano",
    "sg:city":"Milano",
    "sg:orig_category":"Calzature, Pelletterie E Pelli",
    "sg:phone":"+39 02 266 3213",
    "sg:postcode":"20131",
    "sg:province":"Milano",
    "wof:name":"Darifurs Srl",
    "wof:placetype":"venue"
},
  "geometry": {"coordinates":[9.230951,45.483837],"type":"Point"}
}