{
  "type": "Feature",
  "properties": {
    "iso:country":"IT",
    "sg:address":"2/c, Via G. Leopardi 42025 Cavriago",
    "sg:classifiers":[
        {
            "category":"Wholesale",
            "subcategory":"Drugs",
            "type":"Manufacturing & Wholesale Goods"
        }
    ],
    "sg:phone":"+39 0522 576085",
    "sg:postcode":"42025",
    "sg:province":"Reggio Nell'Emilia",
    "sg:tags":[
        "chemical",
        "pharmaceutical"
    ],
    "wof:name":"Eurhema (s.r.l.)",
    "wof:placetype":"venue"
},
  "geometry": {"coordinates":[10.511448,44.695679],"type":"Point"}
}