{
  "type": "Feature",
  "properties": {
    "iso:country":"IT",
    "sg:address":"Via Del Trebbo 1 40013 Castel Maggiore",
    "sg:city":"Castel Maggiore",
    "sg:classifiers":[
        {
            "category":"Bars & Pubs",
            "subcategory":"Wine Bar",
            "type":"Food & Drink"
        }
    ],
    "sg:phone":"+39 051 700604",
    "sg:postcode":"40013",
    "sg:province":"Bologna",
    "sg:tags":[
        "brandy"
    ],
    "sg:website":"www.villazarra.com",
    "wof:name":"Villa Zarri Spa",
    "wof:placetype":"venue"
},
  "geometry": {"coordinates":[11.351789,44.55191],"type":"Point"}
}