{
  "type": "Feature",
  "properties": {
    "iso:country":"IT",
    "sg:address":"20147 Milano",
    "sg:city":"Milano",
    "sg:orig_category":"Elettrotecnica Industriale, Prodotti E Apparecchiature",
    "sg:phone":"+39 02 404 2485",
    "sg:postcode":"20147",
    "sg:province":"Milano",
    "wof:name":"V. & P. Di Dell'aglio Vincenzo",
    "wof:placetype":"venue"
},
  "geometry": {"coordinates":[9.125766,45.456024],"type":"Point"}
}