{
  "type": "Feature",
  "properties": {
    "iso:country":"IT",
    "sg:address":"90036 Misilmeri",
    "sg:city":"Misilmeri",
    "sg:orig_category":"Studi E Consulenze Legali E Notarili. Avvocati, Notai E Servizi Legali. Professionisti - Studi E Servizi Ed Associazioni Di Interesse Aziendale",
    "sg:phone":"+39 091 872 1090",
    "sg:postcode":"90036",
    "sg:province":"Palermo",
    "wof:name":"Studio Notarile Costamante",
    "wof:placetype":"venue"
},
  "geometry": {"coordinates":[13.44863,38.03154],"type":"Point"}
}