{
  "type": "Feature",
  "properties": {
    "iso:country":"IT",
    "sg:address":"2, Via Ungaresca 33070 Brugnera",
    "sg:city":"Brugnera",
    "sg:classifiers":[
        {
            "category":"Manufacturing",
            "subcategory":"Paper Products",
            "type":"Manufacturing & Wholesale Goods"
        }
    ],
    "sg:phone":"+39 0434 623696",
    "sg:postcode":"33070",
    "sg:province":"Pordenone",
    "sg:tags":[
        "cardboard"
    ],
    "wof:name":"Sedie Livenza (s.r.l.)",
    "wof:placetype":"venue"
},
  "geometry": {"coordinates":[12.5345811844,45.9001998901],"type":"Point"}
}