{
  "type": "Feature",
  "properties": {
    "iso:country":"IT",
    "sg:address":"Via Del Corso 63, Rome, Rm",
    "sg:classifiers":[
        {
            "category":"Banks & Credit Unions",
            "subcategory":"Bank",
            "type":"Services"
        }
    ],
    "wof:name":"Beni Stabili",
    "wof:placetype":"venue"
},
  "geometry": {"coordinates":[12.477845,41.907135],"type":"Point"}
}