{
  "type": "Feature",
  "properties": {
    "addr:full":"Via Dei Sabioncelli 24050 Covo Covo Bergamo 24050",
    "addr:postcode":"24050;24050",
    "addr:street":"Via Dei Sabioncelli",
    "iso:country":"IT",
    "sg:address":"Via Dei Sabioncelli 24050 Covo",
    "sg:city":"Covo",
    "sg:classifiers":[
        {
            "category":"Manufacturing",
            "subcategory":"Chemicals & Compounds",
            "type":"Manufacturing & Wholesale Goods"
        }
    ],
    "sg:phone":"+39 036 393 8174",
    "sg:postcode":"24050",
    "sg:province":"Bergamo",
    "sg:tags":[
        "industrial"
    ],
    "wof:name":"Eurokemical Srl",
    "wof:placetype":"venue"
},
  "geometry": {"coordinates":[9.669952,45.694904],"type":"Point"}
}