{
  "type": "Feature",
  "properties": {
    "iso:country":"IT",
    "sg:address":"25128 Brescia",
    "sg:city":"Brescia",
    "sg:orig_category":"Macchine Utensili E Impianti",
    "sg:phone":"+39 030 338 4247",
    "sg:postcode":"25128",
    "sg:province":"Brescia",
    "wof:name":"W.m.t. Srl",
    "wof:placetype":"venue"
},
  "geometry": {"coordinates":[10.227466,45.554096],"type":"Point"}
}