{
  "type": "Feature",
  "properties": {
    "addr:full":"Km. 16.200, Via Caselette 10091 Alpignano Alpignano Torino 10091",
    "addr:postcode":"10091;10091",
    "addr:street":"Km. 16.200 Via Caselette",
    "iso:country":"IT",
    "sg:address":"Km. 16.200, Via Caselette 10091 Alpignano",
    "sg:city":"Alpignano",
    "sg:classifiers":[
        {
            "category":"Shopping",
            "subcategory":"Computers & Home Electronics",
            "type":"Retail Goods"
        }
    ],
    "sg:phone":"+39 390 119 6691",
    "sg:postcode":"10091",
    "sg:province":"Torino",
    "sg:tags":[
        "electronic",
        "electrical",
        "equipment"
    ],
    "wof:name":"Alpignano Lamps S.r.l.",
    "wof:placetype":"venue"
},
  "geometry": {"coordinates":[7.686619,45.07056],"type":"Point"}
}