{
  "type": "Feature",
  "properties": {
    "iso:country":"IT",
    "sg:address":"19/14, Via Rutilia 20141 Milano",
    "sg:city":"Milano",
    "sg:classifiers":[
        {
            "category":"Autos & Motor Vehicles",
            "subcategory":"Automobile Sales",
            "type":"Retail Goods"
        }
    ],
    "sg:phone":"+39 02 5740 4668",
    "sg:postcode":"20141",
    "sg:province":"Milano",
    "sg:tags":[
        "industrial"
    ],
    "wof:name":"Ruotamarket Di Morini Massimo & C. Sas",
    "wof:placetype":"venue"
},
  "geometry": {"coordinates":[9.198322,45.440125],"type":"Point"}
}