{
  "type": "Feature",
  "properties": {
    "iso:country":"IT",
    "sg:address":"45, Viale Tagliamento 41049 Sassuolo",
    "sg:city":"Sassuolo",
    "sg:classifiers":[
        {
            "category":"Communications",
            "subcategory":"Television Station",
            "type":"Services"
        }
    ],
    "sg:phone":"+39 0536 802104",
    "sg:postcode":"41049",
    "sg:province":"Modena",
    "sg:tags":[
        "audio-visual"
    ],
    "wof:name":"Autel (s.r.l.)",
    "wof:placetype":"venue"
},
  "geometry": {"coordinates":[10.805899,44.597446],"type":"Point"}
}