{
  "type": "Feature",
  "properties": {
    "addr:full":"2, V. Marie Curie 39100 Bolzano Bolzano Bolzano/Bozen 39100",
    "addr:housenumber":"2",
    "addr:postcode":"39100;39100",
    "addr:street":"V. Marie Curie",
    "iso:country":"IT",
    "sg:address":"2, V. Marie Curie 39100 Bolzano",
    "sg:city":"Bolzano",
    "sg:classifiers":[
        {
            "category":"Banks & Credit Unions",
            "subcategory":"Investment Brokerage",
            "type":"Services"
        }
    ],
    "sg:phone":"+39 0471 530000",
    "sg:postcode":"39100",
    "sg:province":"Bolzano/Bozen",
    "sg:tags":[
        "-",
        "transport",
        "related"
    ],
    "sg:website":"http://www.fercam.com",
    "wof:name":"Fercam Spa",
    "wof:placetype":"venue"
},
  "geometry": {"coordinates":[11.325057,46.470413],"type":"Point"}
}