{
  "type": "Feature",
  "properties": {
    "iso:country":"IT",
    "sg:address":"Via Eugenio Curiel 6/a 40069 Zola Predosa",
    "sg:city":"Zola",
    "sg:classifiers":[
        {
            "category":"Manufacturing",
            "subcategory":"Motor Vehicles & Parts",
            "type":"Manufacturing & Wholesale Goods"
        }
    ],
    "sg:phone":"+39 051 752404",
    "sg:postcode":"40069",
    "sg:province":"Bologna",
    "sg:tags":[
        "aluminium",
        "processing",
        "sheet"
    ],
    "sg:website":"www.anderlini.it",
    "wof:name":"Anderlini Meccanica Srl",
    "wof:placetype":"venue"
},
  "geometry": {"coordinates":[11.248254,44.495041],"type":"Point"}
}