{
  "type": "Feature",
  "properties": {
    "iso:country":"IT",
    "sg:address":"51, Via Bolzano 39057 Appiano Sulla Strada Del Vino",
    "sg:city":"Appiano sulla strada del vino",
    "sg:classifiers":[
        {
            "category":"Autos & Motor Vehicles",
            "subcategory":"Automobile Sales",
            "type":"Retail Goods"
        }
    ],
    "sg:phone":"+39 0471 633133",
    "sg:postcode":"39057",
    "sg:province":"Bolzano/Bozen",
    "sg:tags":[
        "industrial"
    ],
    "wof:name":"Schwarz Srl",
    "wof:placetype":"venue"
},
  "geometry": {"coordinates":[11.273797,46.474457],"type":"Point"}
}