{
  "type": "Feature",
  "properties": {
    "addr:full":"10023 Chieri Chieri Torino 10023",
    "addr:postcode":"10023;10023",
    "iso:country":"IT",
    "sg:address":"10023 Chieri",
    "sg:city":"Chieri",
    "sg:orig_category":"Servizi E Lavori Per Edilizia E Lavori Pubblici. Servizi E Lavori Per Ecologia E Smaltimento Rifiuti. Macchine E Forniture Per Ecologia E Smaltimento Rifiuti. Acqua, Luce, Gas E Societa' Di Esercizio ",
    "sg:phone":"+39 011 942 4099",
    "sg:postcode":"10023",
    "sg:province":"Torino",
    "wof:name":"Protezione Civile Chieri-volontariato",
    "wof:placetype":"venue"
},
  "geometry": {"coordinates":[7.683528,45.072346],"type":"Point"}
}