{
  "type": "Feature",
  "properties": {
    "iso:country":"IT",
    "sg:address":"25121 Brescia",
    "sg:city":"Brescia",
    "sg:orig_category":"Servizi E Lavori Per Edilizia E Lavori Pubblici. Acqua, Luce, Gas E Societa' Di Esercizio Pubblico",
    "sg:phone":"+39 030 294 2399",
    "sg:postcode":"25121",
    "sg:province":"Brescia",
    "wof:name":"Cosmipel Di Carrozzo Donato E C. Sas",
    "wof:placetype":"venue"
},
  "geometry": {"coordinates":[10.228703,45.535793],"type":"Point"}
}