{
  "type": "Feature",
  "properties": {
    "addr:full":"10022 Carmagnola Carmagnola Torino 10022",
    "addr:postcode":"10022;10022",
    "iso:country":"IT",
    "sg:address":"10022 Carmagnola",
    "sg:city":"Carmagnola",
    "sg:orig_category":"Agricoltura, Orticoltura E Floricoltura",
    "sg:phone":"+39 011 972 3428",
    "sg:postcode":"10022",
    "sg:province":"Torino",
    "wof:name":"Fissore Fertilizzanti Snc",
    "wof:placetype":"venue"
},
  "geometry": {"coordinates":[7.751359,44.812756],"type":"Point"}
}