{
  "type": "Feature",
  "properties": {
    "addr:full":"46010 Gazzuolo Gazzuolo Mantova 46010",
    "addr:postcode":"46010;46010",
    "iso:country":"IT",
    "sg:address":"46010 Gazzuolo",
    "sg:city":"Gazzuolo",
    "sg:orig_category":"Non-classified Establishments",
    "sg:phone":"+39 0376 956023",
    "sg:postcode":"46010",
    "sg:province":"Mantova",
    "wof:name":"Minari Franco E Minari Gino E C. (s.n.c.)",
    "wof:placetype":"venue"
},
  "geometry": {"coordinates":[10.579703,45.065166],"type":"Point"}
}