{
  "type": "Feature",
  "properties": {
    "iso:country":"IT",
    "sg:address":"10093 Collegno",
    "sg:city":"Collegno",
    "sg:orig_category":"Filati E Materie Prime Tessili",
    "sg:phone":"+39 011 780 4228",
    "sg:postcode":"10093",
    "sg:province":"Torino",
    "wof:name":"Macri Antonietta",
    "wof:placetype":"venue"
},
  "geometry": {"coordinates":[7.5803322792,45.072517395],"type":"Point"}
}