{
  "type": "Feature",
  "properties": {
    "addr:full":"38, Via Aquileia 33030 Talmassons Talmassons Udine 33030",
    "addr:postcode":"33030;33030",
    "addr:street":"Via Aquileia",
    "iso:country":"IT",
    "sg:address":"38, Via Aquileia 33030 Talmassons",
    "sg:city":"Talmassons",
    "sg:classifiers":[
        {
            "category":"Home & Garden",
            "subcategory":"Home Furnishings",
            "type":"Retail Goods"
        }
    ],
    "sg:phone":"+39 0432 766027",
    "sg:postcode":"33030",
    "sg:province":"Udine",
    "sg:tags":[
        "household"
    ],
    "wof:name":"Industria Sedie Turello S.r.l.",
    "wof:placetype":"venue"
},
  "geometry": {"coordinates":[13.122529,45.928089],"type":"Point"}
}