{
  "type": "Feature",
  "properties": {
    "addr:full":"00155 Roma Roma Roma 00155",
    "addr:postcode":"00155;00155",
    "iso:country":"IT",
    "sg:address":"00155 Roma",
    "sg:city":"Roma",
    "sg:orig_category":"Forniture Per Edilizia E Lavori Pubblici. Prodotti Vari In Metallo",
    "sg:phone":"+39 06 229 2844",
    "sg:postcode":"00155",
    "sg:province":"Roma",
    "wof:name":"Europont Srl",
    "wof:placetype":"venue"
},
  "geometry": {"coordinates":[12.6140356064,41.9087028503],"type":"Point"}
}