{
  "type": "Feature",
  "properties": {
    "iso:country":"IT",
    "sg:address":"02044 Forano",
    "sg:city":"Forano",
    "sg:classifiers":[
        {
            "category":"Health Services",
            "subcategory":"Health Practitioner",
            "type":"Services"
        }
    ],
    "sg:phone":"+39 0765 570311",
    "sg:postcode":"02044",
    "sg:province":"Rieti",
    "sg:tags":[
        "medici"
    ],
    "wof:name":"Centro Polispecialistico Forano S.r.l.",
    "wof:placetype":"venue"
},
  "geometry": {"coordinates":[12.6044,42.279289],"type":"Point"}
}