{
  "type": "Feature",
  "properties": {
    "iso:country":"IT",
    "sg:address":"66023 Francavilla Al Mare",
    "sg:city":"Francavilla al Mare",
    "sg:orig_category":"Edilizia Materiali - Produzione E Ingrosso",
    "sg:phone":"+39 085 491 0741",
    "sg:postcode":"66023",
    "sg:province":"Chieti",
    "wof:name":"Patricelli Lombardo Sas",
    "wof:placetype":"venue"
},
  "geometry": {"coordinates":[14.262068,42.434921],"type":"Point"}
}