{
  "type": "Feature",
  "properties": {
    "addr:full":"Via Gf Ingrassia 96, 94017 Regalbuto, En Regalbuto Enna 94017",
    "addr:housenumber":"96",
    "addr:postcode":"94017;94017",
    "addr:street":"Via Gf Ingrassia",
    "iso:country":"IT",
    "sg:address":"Via Gf Ingrassia 96, 94017 Regalbuto, En",
    "sg:city":"Regalbuto",
    "sg:classifiers":[
        {
            "category":"Banks & Credit Unions",
            "subcategory":"Bank",
            "type":"Services"
        }
    ],
    "sg:postcode":"94017",
    "sg:province":"Enna",
    "wof:name":"Banca Di Credito Cooperativo La Riscossa Di Regalbuto",
    "wof:placetype":"venue"
},
  "geometry": {"coordinates":[14.279706,37.567596],"type":"Point"}
}