{
  "type": "Feature",
  "properties": {
    "addr:full":"20020 Magnago Magnago Milano 20020",
    "addr:postcode":"20020;20020",
    "iso:country":"IT",
    "sg:address":"20020 Magnago",
    "sg:city":"Magnago",
    "sg:orig_category":"Automobili - Commercio",
    "sg:phone":"+39 0331 659894",
    "sg:postcode":"20020",
    "sg:province":"Milano",
    "sg:website":"http://www.realmotors.it",
    "wof:name":"Real Motors Srl",
    "wof:placetype":"venue"
},
  "geometry": {"coordinates":[9.21031,45.465107],"type":"Point"}
}