{
  "type": "Feature",
  "properties": {
    "iso:country":"IT",
    "sg:address":"74015 Martina Franca",
    "sg:city":"Martina Franca",
    "sg:orig_category":"Abbigliamento - Produzione E Ingrosso",
    "sg:phone":"+39 080 480 7134",
    "sg:postcode":"74015",
    "sg:province":"Taranto",
    "wof:name":"Pellicceria Palazzo Nicola",
    "wof:placetype":"venue"
},
  "geometry": {"coordinates":[17.339006,40.704788],"type":"Point"}
}