{
  "type": "Feature",
  "properties": {
    "addr:full":"20090 Trezzano Sul Naviglio Trezzano sul Naviglio Milano 20090",
    "addr:postcode":"20090;20090",
    "iso:country":"IT",
    "sg:address":"20090 Trezzano Sul Naviglio",
    "sg:city":"Trezzano sul Naviglio",
    "sg:orig_category":"Minuterie - Produzione E Commercio",
    "sg:phone":"+39 02 4846 3627",
    "sg:postcode":"20090",
    "sg:province":"Milano",
    "wof:name":"Dibel Srl",
    "wof:placetype":"venue"
},
  "geometry": {"coordinates":[9.0736560822,45.4196929932],"type":"Point"}
}