{
  "type": "Feature",
  "properties": {
    "iso:country":"IT",
    "sg:address":"16165 Genova",
    "sg:city":"Genova",
    "sg:orig_category":"Illuminazione - Impianti E Materiali",
    "sg:phone":"+39 010 830 9089",
    "sg:postcode":"16165",
    "sg:province":"Genova",
    "wof:name":"Tecnoimpianti Di Alfano Gerolamo",
    "wof:placetype":"venue"
},
  "geometry": {"coordinates":[8.89149,44.408936],"type":"Point"}
}