{
  "type": "Feature",
  "properties": {
    "addr:full":"91026 Mazara Del Vallo Mazara del Vallo Trapani 91026",
    "addr:postcode":"91026;91026",
    "iso:country":"IT",
    "sg:address":"91026 Mazara Del Vallo",
    "sg:city":"Mazara del Vallo",
    "sg:orig_category":"Acciaierie E Fonderie",
    "sg:phone":"+39 0923 941627",
    "sg:postcode":"91026",
    "sg:province":"Trapani",
    "wof:name":"Iscaf Siciliana (s.r.l.)",
    "wof:placetype":"venue"
},
  "geometry": {"coordinates":[12.587575,37.651482],"type":"Point"}
}