{
  "type": "Feature",
  "properties": {
    "iso:country":"IT",
    "sg:address":"09032 Assemini",
    "sg:city":"Assemini",
    "sg:orig_category":"Legno Lavorazione Macchine - Commercio",
    "sg:phone":"+39 070 942116",
    "sg:postcode":"09032",
    "sg:province":"Cagliari",
    "wof:name":"G. Loncini Snc",
    "wof:placetype":"venue"
},
  "geometry": {"coordinates":[9.014565,39.28355],"type":"Point"}
}