{
  "type": "Feature",
  "properties": {
    "iso:country":"IT",
    "sg:address":"52100 Arezzo",
    "sg:city":"Arezzo",
    "sg:orig_category":"Metalli E Leghe",
    "sg:phone":"+39 0575 380608",
    "sg:postcode":"52100",
    "sg:province":"Arezzo",
    "sg:website":"http://www.ekisson.it",
    "wof:name":"Ekisson Srl",
    "wof:placetype":"venue"
},
  "geometry": {"coordinates":[11.8476991653,43.4803695679],"type":"Point"}
}