{
  "type": "Feature",
  "properties": {
    "addr:full":"6, Via Tevere 20020 Cesate Cesate Milano 20020",
    "addr:postcode":"20020;20020",
    "addr:street":"Via Tevere",
    "iso:country":"IT",
    "sg:address":"6, Via Tevere 20020 Cesate",
    "sg:city":"Cesate",
    "sg:classifiers":[
        {
            "category":"Shopping",
            "type":"Retail Goods"
        }
    ],
    "sg:phone":"+39 02 9906 7341",
    "sg:postcode":"20020",
    "sg:province":"Milano",
    "sg:tags":[
        "finished",
        "-",
        "metallic"
    ],
    "wof:name":"C.m.s. (s.r.l.)",
    "wof:placetype":"venue"
},
  "geometry": {"coordinates":[9.0689983368,45.6005592346],"type":"Point"}
}