{
  "type": "Feature",
  "properties": {
    "iso:country":"IT",
    "sg:address":"23883 Brivio",
    "sg:city":"Brivio",
    "sg:orig_category":"Automazione E Robotica - Apparecchiature E Componenti",
    "sg:phone":"+39 039 932 2153",
    "sg:postcode":"23883",
    "sg:province":"Lecco",
    "sg:website":"http://www.effeci.com",
    "wof:name":"Effe.ci. Srl",
    "wof:placetype":"venue"
},
  "geometry": {"coordinates":[9.425315,45.754852],"type":"Point"}
}