{
  "type": "Feature",
  "properties": {
    "addr:full":"39057 Appiano Sulla Strada Del Vino Appiano sulla strada del vino Bolzano/Bozen 39057",
    "addr:postcode":"39057;39057",
    "addr:street":"Strada;Sulla Strada Del Vino",
    "iso:country":"IT",
    "sg:address":"39057 Appiano Sulla Strada Del Vino",
    "sg:city":"Appiano sulla strada del vino",
    "sg:orig_category":"Prodotti Finiti Stampati. Forniture E Prodotti Informatici. Forniture Per Uffici",
    "sg:phone":"+39 0471 663165",
    "sg:postcode":"39057",
    "sg:province":"Bolzano/Bozen",
    "wof:name":"Modulprint Snc Di R. Piemonte",
    "wof:placetype":"venue"
},
  "geometry": {"coordinates":[11.2616682053,46.4497833252],"type":"Point"}
}