{
  "type": "Feature",
  "properties": {
    "addr:full":"24050 Palosco Palosco Bergamo 24050",
    "addr:postcode":"24050;24050",
    "iso:country":"IT",
    "sg:address":"24050 Palosco",
    "sg:city":"Palosco",
    "sg:orig_category":"Materiali Edili",
    "sg:phone":"+39 039 845817",
    "sg:postcode":"24050",
    "sg:province":"Bergamo",
    "wof:name":"Cava Di Palosco Di Tiraboschi Carrara E M.",
    "wof:placetype":"venue"
},
  "geometry": {"coordinates":[9.824031,45.596584],"type":"Point"}
}