{
  "type": "Feature",
  "properties": {
    "iso:country":"IT",
    "sg:address":"65014 Loreto Aprutino",
    "sg:city":"Loreto Aprutino",
    "sg:orig_category":"Agriturismo",
    "sg:phone":"+39 085 497 3100",
    "sg:postcode":"65014",
    "sg:province":"Pescara",
    "sg:website":"http://www.tenutaborgocancelli.com",
    "wof:name":"Tenuta Borgo Cancelli",
    "wof:placetype":"venue"
},
  "geometry": {"coordinates":[13.972414,42.403893],"type":"Point"}
}