{
  "type": "Feature",
  "properties": {
    "iso:country":"IT",
    "sg:address":"35026 Conselve",
    "sg:city":"Conselve",
    "sg:orig_category":"Elettrodomestici. Forniture Alle Strutture Ricettive",
    "sg:phone":"+39 049 950 0555",
    "sg:postcode":"35026",
    "sg:province":"Padova",
    "sg:website":"http://www.atasrl.com",
    "wof:name":"A.t.a. Srl",
    "wof:placetype":"venue"
},
  "geometry": {"coordinates":[11.889959,45.207439],"type":"Point"}
}