{
  "type": "Feature",
  "properties": {
    "iso:country":"IT",
    "sg:address":"21019 Somma Lombardo",
    "sg:city":"Somma Lombardo",
    "sg:orig_category":"Prodotti E Manufatti In Materie Plastiche. Prodotti Cosmetici E Da Toeletta. Forniture Per Attivita' Industriali",
    "sg:phone":"+39 0331 250278",
    "sg:postcode":"21019",
    "sg:province":"Varese",
    "wof:name":"C.s.t. Di De Momi Clara E C. Sas",
    "wof:placetype":"venue"
},
  "geometry": {"coordinates":[8.7042732239,45.676940918],"type":"Point"}
}