{
  "type": "Feature",
  "properties": {
    "iso:country":"IT",
    "sg:address":"Via Cesare Battisti 37 20077 Melegnano",
    "sg:city":"Melegnano",
    "sg:classifiers":[
        {
            "category":"Utilities",
            "subcategory":"Fuel Oil & Lpg",
            "type":"Services"
        }
    ],
    "sg:phone":"+39 02 982051",
    "sg:postcode":"20077",
    "sg:province":"Milano",
    "sg:tags":[
        "transformer",
        "elec",
        "transformers",
        "liquid",
        "immersed",
        "filled"
    ],
    "sg:website":"www.tamini.it",
    "wof:name":"Tamini Trasformatori Srl",
    "wof:placetype":"venue"
},
  "geometry": {"coordinates":[9.329563,45.361298],"type":"Point"}
}