{
  "type": "Feature",
  "properties": {
    "iso:country":"IT",
    "sg:address":"Via Roma; Monte San Biagio",
    "sg:classifiers":[
        {
            "category":"Banks & Credit Unions",
            "subcategory":"Bank",
            "type":"Services"
        }
    ],
    "sg:phone":"+39 0771 56013",
    "wof:name":"Banca Popolare Di Fondi",
    "wof:placetype":"venue"
},
  "geometry": {"coordinates":[13.349076,41.353035],"type":"Point"}
}