{
  "type": "Feature",
  "properties": {
    "iso:country":"IT",
    "sg:address":"Via Piedimonte 54 23868 Valmadrera",
    "sg:city":"Valmadrera",
    "sg:classifiers":[
        {
            "category":"Social Services",
            "subcategory":"Job Training",
            "type":"Services"
        }
    ],
    "sg:phone":"+39 0341 582405",
    "sg:postcode":"23868",
    "sg:province":"Lecco",
    "sg:tags":[
        "machine",
        "pressure",
        "welding"
    ],
    "sg:website":"www.froma.it",
    "wof:name":"Froma Srl",
    "wof:placetype":"venue"
},
  "geometry": {"coordinates":[9.3704204559,45.8476257324],"type":"Point"}
}