{
  "type": "Feature",
  "properties": {
    "iso:country":"IT",
    "sg:address":"17014 Cairo Montenotte",
    "sg:city":"Cairo Montenotte",
    "sg:orig_category":"Articoli Per Neonati E Bambini",
    "sg:phone":"+39 019 504287",
    "sg:postcode":"17014",
    "sg:province":"Savona",
    "sg:website":"http://www.sanitasa-camera.com",
    "wof:name":"Sanitas Di Camera Massimo & C. Sas",
    "wof:placetype":"venue"
},
  "geometry": {"coordinates":[8.319795,44.406944],"type":"Point"}
}