{
  "type": "Feature",
  "properties": {
    "addr:full":"14, Strada Alessandria 15044 Quargnento Quargnento Alessandria 15044",
    "addr:postcode":"15044;15044",
    "addr:street":"Strada Alessandria",
    "iso:country":"IT",
    "sg:address":"14, Strada Alessandria 15044 Quargnento",
    "sg:city":"Quargnento",
    "sg:classifiers":[
        {
            "category":"Shopping",
            "subcategory":"Stationery & Office Supplies",
            "type":"Retail Goods"
        }
    ],
    "sg:phone":"+39 0131 219302",
    "sg:postcode":"15044",
    "sg:province":"Alessandria",
    "sg:tags":[
        "professional"
    ],
    "wof:name":"S.i.c.c.m.a. (s.p.a.)",
    "wof:placetype":"venue"
},
  "geometry": {"coordinates":[8.5047197342,44.9406013489],"type":"Point"}
}