{
  "type": "Feature",
  "properties": {
    "iso:country":"IT",
    "sg:address":"25128 Brescia",
    "sg:city":"Brescia",
    "sg:orig_category":"Arte Ed Artigianato Artistico. Scuole E Servizi Scolastici. Servizi Ausiliari Di Analisi, Controllo E Ricerca",
    "sg:phone":"+39 030 338 5439",
    "sg:postcode":"25128",
    "sg:province":"Brescia",
    "wof:name":"Iannoni Giovanni",
    "wof:placetype":"venue"
},
  "geometry": {"coordinates":[10.221648,45.54884],"type":"Point"}
}