{
  "type": "Feature",
  "properties": {
    "addr:full":"57121 Livorno Livorno Livorno 57121",
    "addr:postcode":"57121;57121",
    "iso:country":"IT",
    "sg:address":"57121 Livorno",
    "sg:city":"Livorno",
    "sg:orig_category":"Cartotecnica E Servizi. Articoli Per Imballaggio E Confezionamento",
    "sg:phone":"+39 0586 409987",
    "sg:postcode":"57121",
    "sg:province":"Livorno",
    "wof:name":"Scatolificio Marinai",
    "wof:placetype":"venue"
},
  "geometry": {"coordinates":[10.340576,43.564495],"type":"Point"}
}