{
  "type": "Feature",
  "properties": {
    "iso:country":"IT",
    "sg:address":"92, Via Piceno Aprutina 63100 Ascoli Piceno",
    "sg:city":"Ascoli Piceno",
    "sg:classifiers":[
        {
            "category":"Wholesale",
            "subcategory":"Machinery & Supplies",
            "type":"Manufacturing & Wholesale Goods"
        }
    ],
    "sg:phone":"+39 0736 342560",
    "sg:postcode":"63100",
    "sg:province":"Ascoli Piceno",
    "sg:tags":[
        "equipment",
        "precision"
    ],
    "wof:name":"Ap Di Antonio Proietti & C. (s.n.c.)",
    "wof:placetype":"venue"
},
  "geometry": {"coordinates":[13.6221103668,42.8435745239],"type":"Point"}
}