{
  "type": "Feature",
  "properties": {
    "addr:full":"20155 Milano Milano Milano 20155",
    "addr:postcode":"20155;20155",
    "iso:country":"IT",
    "sg:address":"20155 Milano",
    "sg:city":"Milano",
    "sg:orig_category":"Studi E Consulenze Tecniche E Industriali. Assicurazioni E Servizi Assicurativi. Consulenze Tecniche, Amministrative E Perizie",
    "sg:phone":"+39 02 3300 2023",
    "sg:postcode":"20155",
    "sg:province":"Milano",
    "wof:name":"Autoperizial Sas Di Marino Stefano E C.",
    "wof:placetype":"venue"
},
  "geometry": {"coordinates":[9.156916,45.493946],"type":"Point"}
}