{
  "type": "Feature",
  "properties": {
    "iso:country":"IT",
    "sg:address":"20096 Seggiano",
    "sg:city":"Seggiano",
    "sg:orig_category":"Macchine, Impianti Ed Attrezzature Industria Chimica",
    "sg:phone":"+39 02 926 7745",
    "sg:postcode":"20096",
    "sg:province":"Milano",
    "wof:name":"Mitis Srl",
    "wof:placetype":"venue"
},
  "geometry": {"coordinates":[9.324005,45.489712],"type":"Point"}
}