{
  "type": "Feature",
  "properties": {
    "iso:country":"IT",
    "sg:address":"65010 Spoltore",
    "sg:city":"Spoltore",
    "sg:orig_category":"Stirerie - Macchine",
    "sg:phone":"+39 085 411242",
    "sg:postcode":"65010",
    "sg:province":"Pescara",
    "wof:name":"De Martino Rappresentanze Sas Di De Martino & C.",
    "wof:placetype":"venue"
},
  "geometry": {"coordinates":[14.18654,42.458286],"type":"Point"}
}