{
  "type": "Feature",
  "properties": {
    "addr:full":"35128 Padova Padova Padova 35128",
    "addr:postcode":"35128;35128",
    "iso:country":"IT",
    "sg:address":"35128 Padova",
    "sg:city":"Padova",
    "sg:orig_category":"Forniture Per Edilizia E Lavori Pubblici",
    "sg:phone":"+39 049 751666",
    "sg:postcode":"35128",
    "sg:province":"Padova",
    "sg:website":"http://www.luise-parati.it",
    "wof:name":"Luise Parati Snc Di Giuseppe Luise & C.",
    "wof:placetype":"venue"
},
  "geometry": {"coordinates":[11.8797225952,45.4013900757],"type":"Point"}
}