{
  "type": "Feature",
  "properties": {
    "addr:full":"Via Verdi 1; Venezia; 30171 Venezia Venezia 30171",
    "addr:housenumber":"1",
    "addr:postcode":"30171;30171",
    "addr:street":"Via Verdi",
    "iso:country":"IT",
    "sg:address":"Via Verdi 1; Venezia; 30171",
    "sg:city":"Venezia",
    "sg:classifiers":[
        {
            "category":"Banks & Credit Unions",
            "subcategory":"Bank",
            "type":"Services"
        }
    ],
    "sg:phone":"+39 041 975855",
    "sg:postcode":"30171",
    "sg:province":"Venezia",
    "wof:name":"Banca Popolare Di Verona",
    "wof:placetype":"venue"
},
  "geometry": {"coordinates":[12.238857,45.492718],"type":"Point"}
}