{
  "type": "Feature",
  "properties": {
    "iso:country":"IT",
    "sg:address":"24064 Grumello Del Monte",
    "sg:city":"Grumello del Monte",
    "sg:orig_category":"Tessuti Arredamento, Tende E Tappeti. Forniture Per Edilizia E Lavori Pubblici",
    "sg:phone":"+39 035 830454",
    "sg:postcode":"24064",
    "sg:province":"Bergamo",
    "wof:name":"Bancora Agostino",
    "wof:placetype":"venue"
},
  "geometry": {"coordinates":[9.872783,45.643402],"type":"Point"}
}