{
  "type": "Feature",
  "properties": {
    "addr:full":"80071 Anacapri Anacapri Napoli 80071",
    "addr:postcode":"80071;80071",
    "iso:country":"IT",
    "sg:address":"80071 Anacapri",
    "sg:city":"Anacapri",
    "sg:orig_category":"Gioielleria, Oreficeria E Argenteria. Shopping",
    "sg:phone":"+39 081 837 1019",
    "sg:postcode":"80071",
    "sg:province":"Napoli",
    "wof:name":"Sirius Di Di Pace Battista Ed Emilia S.n.c.",
    "wof:placetype":"venue"
},
  "geometry": {"coordinates":[14.210528,40.554657],"type":"Point"}
}