{
  "type": "Feature",
  "properties": {
    "iso:country":"IT",
    "sg:address":"51, Via Di Renazzo 44042 Cento",
    "sg:city":"Cento",
    "sg:classifiers":[
        {
            "category":"Shopping",
            "subcategory":"Clothing, Apparel, & Fashions",
            "type":"Retail Goods"
        }
    ],
    "sg:phone":"+39 39051900045",
    "sg:postcode":"44042",
    "sg:province":"Ferrara",
    "sg:tags":[
        "clothes"
    ],
    "wof:name":"Valesani Franco & C. (s.n.c.)",
    "wof:placetype":"venue"
},
  "geometry": {"coordinates":[11.283768,44.761009],"type":"Point"}
}