{
  "type": "Feature",
  "properties": {
    "iso:country":"IT",
    "sg:address":"20040 Carnate",
    "sg:city":"Carnate",
    "sg:orig_category":"Non-classified Establishments",
    "sg:phone":"+39 039 673921",
    "sg:postcode":"20040",
    "sg:province":"Milano",
    "wof:name":"Art's Flowers Di Zardoni Rosanna",
    "wof:placetype":"venue"
},
  "geometry": {"coordinates":[9.376877,45.657269],"type":"Point"}
}