{
  "type": "Feature",
  "properties": {
    "iso:country":"IT",
    "sg:address":"88, Cupa S. Aniello 80146 Napoli",
    "sg:city":"Napoli",
    "sg:classifiers":[
        {
            "category":"Autos & Motor Vehicles",
            "subcategory":"Automobile Sales",
            "type":"Retail Goods"
        }
    ],
    "sg:phone":"+39 39081481317",
    "sg:postcode":"80146",
    "sg:province":"Napoli",
    "sg:tags":[
        "equipment",
        "transport"
    ],
    "wof:name":"Eredi Di Giuseppe Mercuri & C.snc",
    "wof:placetype":"venue"
},
  "geometry": {"coordinates":[14.251636,40.840096],"type":"Point"}
}