{
  "type": "Feature",
  "properties": {
    "iso:country":"IT",
    "sg:address":"24050 Spirano",
    "sg:city":"Spirano",
    "sg:orig_category":"Materiali E Componenti Elettrotecnici",
    "sg:phone":"+39 035 876538",
    "sg:postcode":"24050",
    "sg:province":"Bergamo",
    "wof:name":"La.mo.ter. Srl",
    "wof:placetype":"venue"
},
  "geometry": {"coordinates":[9.698071,45.697445],"type":"Point"}
}