{
  "type": "Feature",
  "properties": {
    "addr:full":"4, Strada Gaione 43100 Parma Gaione Parma 43100",
    "addr:postcode":"43100;43100",
    "addr:street":"Strada Gaione",
    "iso:country":"IT",
    "sg:address":"4, Strada Gaione 43100 Parma",
    "sg:city":"Gaione",
    "sg:classifiers":[
        {
            "category":"Food & Beverages",
            "subcategory":"Groceries & Convenience Stores",
            "type":"Retail Goods"
        }
    ],
    "sg:phone":"+39 0521 648158",
    "sg:postcode":"43100",
    "sg:province":"Parma",
    "sg:tags":[
        "product",
        "related"
    ],
    "wof:name":"Greci Geremia & Figli (s.r.l.)",
    "wof:placetype":"venue"
},
  "geometry": {"coordinates":[10.2949199677,44.8232078552],"type":"Point"}
}