{
  "type": "Feature",
  "properties": {
    "iso:country":"IT",
    "sg:address":"26024 Paderno Ponchielli",
    "sg:city":"Paderno Ponchielli",
    "sg:orig_category":"Apparecchiature E Sistemi Per Magazzinaggio E Movimentazione",
    "sg:phone":"+39 0374 367098",
    "sg:postcode":"26024",
    "sg:province":"Cremona",
    "wof:name":"Ma-sol Srl",
    "wof:placetype":"venue"
},
  "geometry": {"coordinates":[9.932736,45.237362],"type":"Point"}
}