{
  "type": "Feature",
  "properties": {
    "addr:full":"208/sc.a, Via Ascari Alberto 00142 Roma Roma Roma 00142",
    "addr:housenumber":"208",
    "addr:postcode":"00142;00142",
    "addr:street":"Via Ascari Alberto",
    "iso:country":"IT",
    "sg:address":"208/sc.a, Via Ascari Alberto 00142 Roma",
    "sg:city":"Roma",
    "sg:classifiers":[
        {
            "category":"Shopping",
            "subcategory":"Computers & Home Electronics",
            "type":"Retail Goods"
        }
    ],
    "sg:phone":"+39 39065033104",
    "sg:postcode":"00142",
    "sg:province":"Roma",
    "sg:tags":[
        "electronic",
        "electrical",
        "equipment"
    ],
    "wof:name":"Medical System Srl",
    "wof:placetype":"venue"
},
  "geometry": {"coordinates":[12.482325,41.895466],"type":"Point"}
}