{
  "type": "Feature",
  "properties": {
    "iso:country":"IT",
    "sg:address":"23826 Mandello Del Lario",
    "sg:city":"Mandello del Lario",
    "sg:orig_category":"Elettrotecnica Industriale, Prodotti E Apparecchiature. Elettrotecnica Professionale E Di Consumo",
    "sg:phone":"+39 0341 731350",
    "sg:postcode":"23826",
    "sg:province":"Lecco",
    "wof:name":"Tricos Srl",
    "wof:placetype":"venue"
},
  "geometry": {"coordinates":[9.331588,45.914471],"type":"Point"}
}