{
  "type": "Feature",
  "properties": {
    "addr:full":"20, Via Roma 39014 Postal Postal Bolzano/Bozen 39014",
    "addr:postcode":"39014;39014",
    "addr:street":"Via Roma",
    "iso:country":"IT",
    "sg:address":"20, Via Roma 39014 Postal",
    "sg:city":"Postal",
    "sg:classifiers":[
        {
            "category":"Food & Beverages",
            "subcategory":"Groceries & Convenience Stores",
            "type":"Retail Goods"
        }
    ],
    "sg:phone":"+39 0473 292358",
    "sg:postcode":"39014",
    "sg:province":"Bolzano/Bozen",
    "sg:tags":[
        "product",
        "related"
    ],
    "wof:name":"Pfitscher",
    "wof:placetype":"venue"
},
  "geometry": {"coordinates":[11.1946048737,46.6057243347],"type":"Point"}
}