{
  "type": "Feature",
  "properties": {
    "iso:country":"IT",
    "sg:address":"16128 Genova",
    "sg:city":"Genova",
    "sg:orig_category":"Officine Meccaniche Navali",
    "sg:phone":"+39 010 246 1111",
    "sg:postcode":"16128",
    "sg:province":"Genova",
    "sg:website":"http://www.mtd.it",
    "wof:name":"La Meccanica Turbodiesel",
    "wof:placetype":"venue"
},
  "geometry": {"coordinates":[8.936954,44.401161],"type":"Point"}
}