{
  "type": "Feature",
  "properties": {
    "addr:full":"12, V. Pietro Gobetti 20090 Caleppio Di Settala Caleppio Milano 20090",
    "addr:housenumber":"12",
    "addr:postcode":"20090;20090",
    "addr:street":"V. Pietro Gobetti",
    "iso:country":"IT",
    "sg:address":"12, V. Pietro Gobetti 20090 Caleppio Di Settala",
    "sg:city":"Caleppio",
    "sg:classifiers":[
        {
            "category":"Shopping",
            "subcategory":"Crafts & Fabrics",
            "type":"Retail Goods"
        }
    ],
    "sg:phone":"+39 390 295 4171",
    "sg:postcode":"20090",
    "sg:province":"Milano",
    "sg:website":"http://www.cucirinitrestelle.com",
    "wof:name":"Cucirini Tre Stelle Spa",
    "wof:placetype":"venue"
},
  "geometry": {"coordinates":[9.1881408691,45.4636878967],"type":"Point"}
}