{
  "type": "Feature",
  "properties": {
    "addr:full":"Viale Aldo Moro 70; Brindisi; 72100 Brindisi Brindisi 72100",
    "addr:housenumber":"70",
    "addr:postcode":"72100;72100",
    "addr:street":"Viale Aldo Moro",
    "iso:country":"IT",
    "sg:address":"Viale Aldo Moro 70; Brindisi; 72100",
    "sg:city":"Brindisi",
    "sg:classifiers":[
        {
            "category":"Travel",
            "subcategory":"Travel Agent",
            "type":"Entertainment"
        }
    ],
    "sg:phone":"+39 390 831 5828",
    "sg:postcode":"72100",
    "sg:province":"Brindisi",
    "sg:website":"www.bestwestern.com",
    "wof:name":"Best Western Hotel Mediterraneo",
    "wof:placetype":"venue"
},
  "geometry": {"coordinates":[17.931931,40.626556],"type":"Point"}
}