{
  "type": "Feature",
  "properties": {
    "addr:full":"6/r, Via Della Nunziata 17100 Savona Savona Savona 17100",
    "addr:housenumber":"6 / r",
    "addr:postcode":"17100;17100",
    "addr:street":"Via Della Nunziata",
    "iso:country":"IT",
    "sg:address":"6/r, Via Della Nunziata 17100 Savona",
    "sg:city":"Savona",
    "sg:classifiers":[
        {
            "category":"Food & Beverages",
            "subcategory":"Groceries & Convenience Stores",
            "type":"Retail Goods"
        }
    ],
    "sg:phone":"+39 39019264114",
    "sg:postcode":"17100",
    "sg:province":"Savona",
    "sg:tags":[
        "product",
        "related"
    ],
    "wof:name":"Pamfood Srl",
    "wof:placetype":"venue"
},
  "geometry": {"coordinates":[8.4772462845,44.3110694885],"type":"Point"}
}