{
  "type": "Feature",
  "properties": {
    "iso:country":"IT",
    "sg:address":"00040 Pomezia",
    "sg:city":"Pomezia",
    "sg:orig_category":"Attrezzature E Forniture Per Officine Riparazione E Servizi Ausiliari",
    "sg:phone":"+39 06 910 6643",
    "sg:postcode":"00040",
    "sg:province":"Roma",
    "wof:name":"Elettrica Spadaro Di Spadaro Roberto",
    "wof:placetype":"venue"
},
  "geometry": {"coordinates":[12.498468,41.675095],"type":"Point"}
}