{
  "type": "Feature",
  "properties": {
    "addr:full":"43038 Sala Baganza Sala Baganza Parma 43038",
    "addr:housenumber":"baganza",
    "addr:postcode":"43038;43038",
    "addr:street":"Parma",
    "iso:country":"IT",
    "sg:address":"43038 Sala Baganza",
    "sg:city":"Sala Baganza",
    "sg:orig_category":"Autogru - Noleggio",
    "sg:phone":"+39 0521 836760",
    "sg:postcode":"43038",
    "sg:province":"Parma",
    "sg:website":"http://www.emilgru.it",
    "wof:name":"Emilgru Srl",
    "wof:placetype":"venue"
},
  "geometry": {"coordinates":[10.233933,44.716602],"type":"Point"}
}