{
  "type": "Feature",
  "properties": {
    "addr:full":"Via Emilia Romagna 9 35020 Saonara Saonara Padova 35020",
    "addr:housenumber":"9",
    "addr:postcode":"35020;35020",
    "addr:street":"Via Emilia Romagna",
    "iso:country":"IT",
    "sg:address":"Via Emilia Romagna 9 35020 Saonara",
    "sg:city":"Saonara",
    "sg:classifiers":[
        {
            "category":"Health Services",
            "subcategory":"Medical Lab",
            "type":"Services"
        }
    ],
    "sg:phone":"+39 049 879 8101",
    "sg:postcode":"35020",
    "sg:province":"Padova",
    "sg:tags":[
        "laboratory",
        "autoclave"
    ],
    "wof:name":"Officine Sordina S.p.a.",
    "wof:placetype":"venue"
},
  "geometry": {"coordinates":[11.959644,45.378651],"type":"Point"}
}