{
  "type": "Feature",
  "properties": {
    "addr:full":"20129 Milano Milano Milano 20129",
    "addr:postcode":"20129;20129",
    "iso:country":"IT",
    "sg:address":"20129 Milano",
    "sg:city":"Milano",
    "sg:orig_category":"Servizi E Lavori Per Edilizia E Lavori Pubblici. Banche E Servizi Finanziari",
    "sg:phone":"+39 02 2024 1311",
    "sg:postcode":"20129",
    "sg:province":"Milano",
    "wof:name":"Sirli S.r.l.",
    "wof:placetype":"venue"
},
  "geometry": {"coordinates":[9.208783,45.474026],"type":"Point"}
}