{
  "type": "Feature",
  "properties": {
    "addr:full":"Viale Dell' Artigianato 24062 Costa Volpino Costa Volpino Bergamo 24062",
    "addr:housenumber":"volpino",
    "addr:postcode":"24062;24062",
    "addr:street":"Viale Dell ' Artigianato",
    "iso:country":"IT",
    "sg:address":"Viale Dell' Artigianato 24062 Costa Volpino",
    "sg:city":"Costa Volpino",
    "sg:classifiers":[
        {
            "category":"Shopping",
            "type":"Retail Goods"
        }
    ],
    "sg:phone":"+39 39035972479",
    "sg:postcode":"24062",
    "sg:province":"Bergamo",
    "sg:tags":[
        "finished",
        "-",
        "metallic"
    ],
    "wof:name":"Zanardini Giuseppe",
    "wof:placetype":"venue"
},
  "geometry": {"coordinates":[10.1074428558,45.8175544739],"type":"Point"}
}