{
  "type": "Feature",
  "properties": {
    "iso:country":"IT",
    "sg:address":"20047 Brugherio",
    "sg:city":"Brugherio",
    "sg:orig_category":"Prodotti Chimici Secondari. Macchine E Forniture Per Ecologia E Smaltimento Rifiuti",
    "sg:phone":"+39 039 214 2186",
    "sg:postcode":"20047",
    "sg:province":"Milano",
    "wof:name":"Pharma Trade Company Srl",
    "wof:placetype":"venue"
},
  "geometry": {"coordinates":[9.2865600586,45.5485610962],"type":"Point"}
}