{
  "type": "Feature",
  "properties": {
    "iso:country":"IT",
    "sg:address":"8, Via Milano 20020 Ceriano Laghetto",
    "sg:city":"Ceriano Laghetto",
    "sg:classifiers":[
        {
            "category":"Shopping",
            "subcategory":"Stationery & Office Supplies",
            "type":"Retail Goods"
        }
    ],
    "sg:phone":"+39 02 9646 1250",
    "sg:postcode":"20020",
    "sg:province":"Milano",
    "sg:tags":[
        "professional"
    ],
    "wof:name":"Spm Prata Manfrinati Snc",
    "wof:placetype":"venue"
},
  "geometry": {"coordinates":[9.1012039185,45.6294975281],"type":"Point"}
}