{
  "type": "Feature",
  "properties": {
    "iso:country":"IT",
    "sg:address":"65122 Pescara",
    "sg:city":"Pescara",
    "sg:orig_category":"Servizi Ausiliari Di Certificati, Riproduzioni, Disegni E Foto",
    "sg:phone":"+39 085 421 6332",
    "sg:postcode":"65122",
    "sg:province":"Pescara",
    "wof:name":"Studio Sinallagma Sas",
    "wof:placetype":"venue"
},
  "geometry": {"coordinates":[14.209581,42.471947],"type":"Point"}
}