{
  "type": "Feature",
  "properties": {
    "iso:country":"IT",
    "sg:address":"90142 Palermo",
    "sg:city":"Palermo",
    "sg:orig_category":"Impiantistica E Prodotti Tecnologici Per Edilizia. Elettronica Professionale E Di Consumo",
    "sg:phone":"+39 091 637 1523",
    "sg:postcode":"90142",
    "sg:province":"Palermo",
    "wof:name":"Sciacca I. Srl",
    "wof:placetype":"venue"
},
  "geometry": {"coordinates":[13.364264,38.105618],"type":"Point"}
}