{
  "type": "Feature",
  "properties": {
    "addr:full":"61013 Mercatino Conca Mercatino Conca Pesaro E Urbino 61013",
    "addr:postcode":"61013;61013",
    "addr:street":"E Urbino",
    "iso:country":"IT",
    "sg:address":"61013 Mercatino Conca",
    "sg:city":"Mercatino Conca",
    "sg:orig_category":"Prodotti E Manufatti In Materie Plastiche",
    "sg:phone":"+39 0541 971090",
    "sg:postcode":"61013",
    "sg:province":"Pesaro E Urbino",
    "wof:name":"Lazzari Snc Di Lazzari Andrea & C.",
    "wof:placetype":"venue"
},
  "geometry": {"coordinates":[12.4950590134,43.8713531494],"type":"Point"}
}