{
  "type": "Feature",
  "properties": {
    "iso:country":"IT",
    "sg:address":"00191 Roma",
    "sg:city":"Roma",
    "sg:orig_category":"Abbigliamento Intimo, Calze E Costumi Da Bagno. Sport - Articoli E Forniture. Shopping",
    "sg:phone":"+39 06 3630 0873",
    "sg:postcode":"00191",
    "sg:province":"Roma",
    "wof:name":"D.e.d. Di D'ippolito Nadia E D'ippolito Gabriella Snc",
    "wof:placetype":"venue"
},
  "geometry": {"coordinates":[12.467471,41.947327],"type":"Point"}
}