{
  "type": "Feature",
  "properties": {
    "iso:country":"IT",
    "sg:address":"42025 Cavriago",
    "sg:orig_category":"Materie Plastiche - Produzione E Lavorazione",
    "sg:phone":"+39 0522 575781",
    "sg:postcode":"42025",
    "sg:province":"Reggio Nell'Emilia",
    "sg:website":"http://www.tecnoplastica.it",
    "wof:name":"Tecnoplastica Srl Di A. & C.",
    "wof:placetype":"venue"
},
  "geometry": {"coordinates":[10.516124,44.697086],"type":"Point"}
}