{
  "type": "Feature",
  "properties": {
    "addr:full":"28100 Novara Novara Novara 28100",
    "addr:postcode":"28100;28100",
    "iso:country":"IT",
    "sg:address":"28100 Novara",
    "sg:city":"Novara",
    "sg:orig_category":"Biancheria, Telerie E Coperte",
    "sg:phone":"+39 0321 36285",
    "sg:postcode":"28100",
    "sg:province":"Novara",
    "wof:name":"De-co",
    "wof:placetype":"venue"
},
  "geometry": {"coordinates":[8.622065,45.448433],"type":"Point"}
}