{
  "type": "Feature",
  "properties": {
    "iso:country":"IT",
    "sg:address":"00141 Roma",
    "sg:city":"Roma",
    "sg:orig_category":"Servizi E Lavori Per Arredamento E Industria Del Legno. Forniture Per Congressi, Fiere E Manifestazioni. Servizi Per Aziende, Manifestazioni E Supporto Agli Scambi Commerciali",
    "sg:phone":"+39 06 8718 2444",
    "sg:postcode":"00141",
    "sg:province":"Roma",
    "wof:name":"Ditta Accorsi Dino Domenico Di Accorsi Dino Domenico E Bruno S.n.c.",
    "wof:placetype":"venue"
},
  "geometry": {"coordinates":[12.529757,41.940891],"type":"Point"}
}