{
  "type": "Feature",
  "properties": {
    "iso:country":"IT",
    "sg:address":"40128 Bologna",
    "sg:city":"Bologna",
    "sg:orig_category":"Dolciumi E Gelati",
    "sg:phone":"+39 051 353103",
    "sg:postcode":"40128",
    "sg:province":"Bologna",
    "wof:name":"Istituto Nazionale Apicoltura",
    "wof:placetype":"venue"
},
  "geometry": {"coordinates":[11.350011,44.524921],"type":"Point"}
}