{
  "type": "Feature",
  "properties": {
    "iso:country":"IT",
    "sg:address":"20145 Milano",
    "sg:city":"Milano",
    "sg:orig_category":"Servizi E Lavori Per Edilizia E Lavori Pubblici. Banche E Servizi Finanziari",
    "sg:phone":"+39 02 430081",
    "sg:postcode":"20145",
    "sg:province":"Milano",
    "wof:name":"Arch.michele De Lucchi Srl",
    "wof:placetype":"venue"
},
  "geometry": {"coordinates":[9.161365,45.469746],"type":"Point"}
}