{
  "type": "Feature",
  "properties": {
    "addr:full":"3, Via Bragadino Marco Antonio 20144 Milano Milano Milano 20144",
    "addr:postcode":"20144;20144",
    "addr:street":"Via Bragadino Marco Antonio",
    "iso:country":"IT",
    "sg:address":"3, Via Bragadino Marco Antonio 20144 Milano",
    "sg:city":"Milano",
    "sg:classifiers":[
        {
            "category":"Utilities",
            "subcategory":"Telephone",
            "type":"Services"
        }
    ],
    "sg:phone":"+39 02 4800 6239",
    "sg:postcode":"20144",
    "sg:province":"Milano",
    "sg:tags":[
        "telecommunication"
    ],
    "wof:name":"Studio Cinque (s.r.l.)",
    "wof:placetype":"venue"
},
  "geometry": {"coordinates":[9.16775,45.458733],"type":"Point"}
}