{
  "type": "Feature",
  "properties": {
    "addr:full":"14, Via Del Carso 21054 Fagnano Olona Fagnano Olona Varese 21054",
    "addr:postcode":"21054;21054",
    "addr:street":"Via Del Carso",
    "iso:country":"IT",
    "sg:address":"14, Via Del Carso 21054 Fagnano Olona",
    "sg:city":"Fagnano Olona",
    "sg:classifiers":[
        {
            "category":"Manufacturing",
            "subcategory":"Paper Products",
            "type":"Manufacturing & Wholesale Goods"
        }
    ],
    "sg:phone":"+39 0331 617150",
    "sg:postcode":"21054",
    "sg:province":"Varese",
    "sg:tags":[
        "cardboard"
    ],
    "wof:name":"Cartiera Lombarda (s.p.a.)",
    "wof:placetype":"venue"
},
  "geometry": {"coordinates":[8.8263845444,45.8176040649],"type":"Point"}
}