{
  "type": "Feature",
  "properties": {
    "iso:country":"IT",
    "sg:address":"20080 Zibido San Giacomo",
    "sg:city":"Zibido San Giacomo",
    "sg:orig_category":"Materiali E Componenti Elettrotecnici",
    "sg:phone":"+39 02 900281",
    "sg:postcode":"20080",
    "sg:province":"Milano",
    "wof:name":"Legrand Spa",
    "wof:placetype":"venue"
},
  "geometry": {"coordinates":[9.1069,45.36018],"type":"Point"}
}