{
  "type": "Feature",
  "properties": {
    "addr:full":"35030 Selvazzano Dentro Selvazzano Dentro Padova 35030",
    "addr:postcode":"35030;35030",
    "iso:country":"IT",
    "sg:address":"35030 Selvazzano Dentro",
    "sg:city":"Selvazzano Dentro",
    "sg:orig_category":"Forniture Per Abbigliamento E Pelletterie",
    "sg:phone":"+39 049 623645",
    "sg:postcode":"35030",
    "sg:province":"Padova",
    "wof:name":"Pizzo Minuterie Srl",
    "wof:placetype":"venue"
},
  "geometry": {"coordinates":[11.8027086258,45.397644043],"type":"Point"}
}