{
  "type": "Feature",
  "properties": {
    "addr:full":"25086 Rezzato Rezzato Brescia 25086",
    "addr:postcode":"25086;25086",
    "iso:country":"IT",
    "sg:address":"25086 Rezzato",
    "sg:city":"Rezzato",
    "sg:orig_category":"Utensili Meccanici E Materiali",
    "sg:phone":"+39 030 259 2274",
    "sg:postcode":"25086",
    "sg:province":"Brescia",
    "wof:name":"Mareb (s.r.l.)",
    "wof:placetype":"venue"
},
  "geometry": {"coordinates":[10.31174,45.524734],"type":"Point"}
}