{
  "type": "Feature",
  "properties": {
    "iso:country":"IT",
    "sg:address":"4, Via Francia 20093 Cologno Monzese",
    "sg:city":"Cologno Monzese",
    "sg:classifiers":[
        {
            "category":"Manufacturing",
            "subcategory":"Metals",
            "type":"Manufacturing & Wholesale Goods"
        }
    ],
    "sg:phone":"+39 02 2730 5586",
    "sg:postcode":"20093",
    "sg:province":"Milano",
    "sg:tags":[
        "processing"
    ],
    "wof:name":"Impianti Industriali Kolzer Di D'esposito Davide",
    "wof:placetype":"venue"
},
  "geometry": {"coordinates":[9.2660903931,45.5210494995],"type":"Point"}
}