{
  "type": "Feature",
  "properties": {
    "iso:country":"IT",
    "sg:address":"36016 Thiene",
    "sg:city":"Thiene",
    "sg:orig_category":"Macchine Utensili E Impianti",
    "sg:phone":"+39 0445 361256",
    "sg:postcode":"36016",
    "sg:province":"Vicenza",
    "wof:name":"S.i.m.a.s.v. (s.r.l.)",
    "wof:placetype":"venue"
},
  "geometry": {"coordinates":[11.512132,45.705952],"type":"Point"}
}