{
  "type": "Feature",
  "properties": {
    "addr:full":"Via Andrea Doria 4 21012 Cassano Magnago Cassano Magnago Varese 21012",
    "addr:housenumber":"4",
    "addr:postcode":"21012;21012",
    "addr:street":"Via Andrea Doria",
    "iso:country":"IT",
    "sg:address":"Via Andrea Doria 4 21012 Cassano Magnago",
    "sg:city":"Cassano Magnago",
    "sg:classifiers":[
        {
            "category":"Exhibition Hall",
            "type":"Public Place"
        }
    ],
    "sg:phone":"+39 0331 201208",
    "sg:postcode":"21012",
    "sg:province":"Varese",
    "sg:tags":[
        "equipping",
        "sale",
        "room",
        "show"
    ],
    "sg:website":"www.morettidesign.net",
    "wof:name":"Moretti Design Srl",
    "wof:placetype":"venue"
},
  "geometry": {"coordinates":[8.826385,45.817604],"type":"Point"}
}