{
  "type": "Feature",
  "properties": {
    "addr:full":"58100 Grosseto Grosseto Grosseto 58100",
    "addr:postcode":"58100;58100",
    "iso:country":"IT",
    "sg:address":"58100 Grosseto",
    "sg:city":"Grosseto",
    "sg:classifiers":[
        {
            "category":"Banks & Credit Unions",
            "subcategory":"Investment Brokerage",
            "type":"Services"
        }
    ],
    "sg:phone":"+39 0564 491021",
    "sg:postcode":"58100",
    "sg:province":"Grosseto",
    "sg:tags":[
        "parrucchieri",
        "per",
        "donna"
    ],
    "wof:name":"Parrucchiere S & G Doppio Taglio Di Gabriele E Salvatore",
    "wof:placetype":"venue"
},
  "geometry": {"coordinates":[11.0967617035,42.7717514038],"type":"Point"}
}