{
  "type": "Feature",
  "properties": {
    "addr:full":"25, Via M. D'oggiono 23848 Oggiono Oggiono Lecco 23848",
    "addr:postcode":"23848;23848",
    "addr:street":"Via M. D'Oggiono",
    "iso:country":"IT",
    "sg:address":"25, Via M. D'oggiono 23848 Oggiono",
    "sg:city":"Oggiono",
    "sg:classifiers":[
        {
            "category":"Real Estate",
            "subcategory":"Surveying",
            "type":"Services"
        }
    ],
    "sg:phone":"+39 0341 576251",
    "sg:postcode":"23848",
    "sg:province":"Lecco",
    "sg:tags":[
        "equipment",
        "material",
        "good",
        "-",
        "handling"
    ],
    "wof:name":"Colombo Pietro Costruzioni Meccaniche (s.n.c.)",
    "wof:placetype":"venue"
},
  "geometry": {"coordinates":[9.362873,45.790489],"type":"Point"}
}