{
  "type": "Feature",
  "properties": {
    "iso:country":"IT",
    "sg:address":"20040 Bellusco",
    "sg:city":"Bellusco",
    "sg:orig_category":"Frigotecnica, Apparecchiature E Servizi. Arredi Ed Attrezzature Per Uffici",
    "sg:phone":"+39 039 602 0984",
    "sg:postcode":"20040",
    "sg:province":"Milano",
    "wof:name":"Crea Srl",
    "wof:placetype":"venue"
},
  "geometry": {"coordinates":[9.4794397354,45.5793838501],"type":"Point"}
}