{
  "type": "Feature",
  "properties": {
    "iso:country":"IT",
    "sg:address":"64014 Martinsicuro",
    "sg:city":"Martinsicuro",
    "sg:orig_category":"Servizi Ausiliari Per Il Trasporto",
    "sg:phone":"+39 0861 796130",
    "sg:postcode":"64014",
    "sg:province":"Teramo",
    "wof:name":"Tormenti Alfano",
    "wof:placetype":"venue"
},
  "geometry": {"coordinates":[13.9166,42.889671],"type":"Point"}
}