{
  "type": "Feature",
  "properties": {
    "addr:full":"00168 Roma Roma Roma 00168",
    "addr:postcode":"00168;00168",
    "iso:country":"IT",
    "sg:address":"00168 Roma",
    "sg:city":"Roma",
    "sg:orig_category":"Forniture Per Uffici",
    "sg:phone":"+39 06 3550 4677",
    "sg:postcode":"00168",
    "sg:province":"Roma",
    "wof:name":"Caruso Giovanni",
    "wof:placetype":"venue"
},
  "geometry": {"coordinates":[12.4216575623,41.9311065674],"type":"Point"}
}