{
  "type": "Feature",
  "properties": {
    "addr:full":"47032 Bertinoro Bertinoro Forl\u00ec-Cesena 47032",
    "addr:postcode":"47032;47032",
    "iso:country":"IT",
    "sg:address":"47032 Bertinoro",
    "sg:city":"Bertinoro",
    "sg:orig_category":"Prodotti Di Base E Forniture Per Industria Alimentare E Bevande",
    "sg:phone":"+39 0543 449131",
    "sg:postcode":"47032",
    "sg:province":"Forl\u00ec-Cesena",
    "wof:name":"Sandri Giuliano E Gerardo",
    "wof:placetype":"venue"
},
  "geometry": {"coordinates":[12.160656929,44.1697540283],"type":"Point"}
}