{
  "type": "Feature",
  "properties": {
    "iso:country":"IT",
    "sg:address":"28070 Nibbiola",
    "sg:city":"Nibbiola",
    "sg:orig_category":"Servizi Ausiliari Per Il Trasporto. Servizi Vari Di Interesse Pubblico",
    "sg:phone":"+39 0321 84038",
    "sg:postcode":"28070",
    "sg:province":"Novara",
    "wof:name":"Nevi Emanuele",
    "wof:placetype":"venue"
},
  "geometry": {"coordinates":[8.663453,45.374329],"type":"Point"}
}