{
  "type": "Feature",
  "properties": {
    "iso:country":"IT",
    "sg:address":"Via Privata Carriera Rosalba 15 20146 Milano",
    "sg:city":"Milano",
    "sg:classifiers":[
        {
            "category":"Social Services",
            "subcategory":"Child Care",
            "type":"Services"
        }
    ],
    "sg:phone":"+39 02 4895 0287",
    "sg:postcode":"20146",
    "sg:province":"Milano",
    "sg:tags":[
        "lift",
        "maintenance"
    ],
    "wof:name":"Mario E Paolo Bosisio Srl",
    "wof:placetype":"venue"
},
  "geometry": {"coordinates":[9.144137,45.446671],"type":"Point"}
}