{
  "type": "Feature",
  "properties": {
    "addr:full":"00139 Roma Roma Roma 00139",
    "addr:postcode":"00139;00139",
    "iso:country":"IT",
    "sg:address":"00139 Roma",
    "sg:city":"Roma",
    "sg:orig_category":"Ospedali E Servizi Sanitari. Centri Di Estetica E Cosmesi E Servizi",
    "sg:phone":"+39 06 8713 1370",
    "sg:postcode":"00139",
    "sg:province":"Roma",
    "wof:name":"Gregori Luciano",
    "wof:placetype":"venue"
},
  "geometry": {"coordinates":[12.536945,41.971394],"type":"Point"}
}