{
  "type": "Feature",
  "properties": {
    "iso:country":"IT",
    "sg:address":"10, Via Roma 22046 Merone",
    "sg:city":"Merone",
    "sg:classifiers":[
        {
            "category":"Shopping",
            "subcategory":"Crafts & Fabrics",
            "type":"Retail Goods"
        }
    ],
    "sg:phone":"+39 39031650053",
    "sg:postcode":"22046",
    "sg:province":"Como",
    "sg:tags":[
        "linen"
    ],
    "wof:name":"Industria Tessile Gastaldi & C. (s.p.a.)",
    "wof:placetype":"venue"
},
  "geometry": {"coordinates":[9.2242450714,45.7552261353],"type":"Point"}
}