{
  "type": "Feature",
  "properties": {
    "iso:country":"IT",
    "sg:address":"09134 Cagliari",
    "sg:city":"Cagliari",
    "sg:orig_category":"Impiantistica E Prodotti Tecnologici Per Edilizia. Forniture Industriali Per Prevenzione, Controllo E Sicurezza",
    "sg:phone":"+39 070 522125",
    "sg:postcode":"09134",
    "sg:province":"Cagliari",
    "wof:name":"Sardantincendi",
    "wof:placetype":"venue"
},
  "geometry": {"coordinates":[9.126945,39.241695],"type":"Point"}
}