{
  "type": "Feature",
  "properties": {
    "iso:country":"IT",
    "sg:address":"39030 Vandoies",
    "sg:city":"Vandoies",
    "sg:orig_category":"Acquedotti, Gasdotti Ed Oleodotti - Impianti Ed Attrezzature",
    "sg:phone":"+39 0472 869341",
    "sg:postcode":"39030",
    "sg:province":"Bolzano/Bozen",
    "wof:name":"Grubbachbau Sas",
    "wof:placetype":"venue"
},
  "geometry": {"coordinates":[11.72843,46.816105],"type":"Point"}
}