{
  "type": "Feature",
  "properties": {
    "iso:country":"IT",
    "sg:address":"35043 Monselice",
    "sg:city":"Monselice",
    "sg:orig_category":"Elettrotecnica Industriale, Prodotti E Apparecchiature. Elettronica Industriale, Prodotti E Apparecchiature",
    "sg:phone":"+39 0429 780421",
    "sg:postcode":"35043",
    "sg:province":"Padova",
    "sg:website":"http://www.oleodm.com",
    "wof:name":"Oleodinamica O.d.m. Di Salv\u00d2 Lauretta & C. Snc",
    "wof:placetype":"venue"
},
  "geometry": {"coordinates":[11.700944,45.219387],"type":"Point"}
}