{
  "type": "Feature",
  "properties": {
    "iso:country":"IT",
    "sg:address":"60022 Castelfidardo",
    "sg:city":"Castelfidardo",
    "sg:orig_category":"Lavorazioni Metalli, Stampaggio E Saldatura",
    "sg:phone":"+39 071 782 2364",
    "sg:postcode":"60022",
    "sg:province":"Ancona",
    "sg:website":"http://www.sifer.it",
    "wof:name":"Sifer Di Sisti Valentina & C. Snc",
    "wof:placetype":"venue"
},
  "geometry": {"coordinates":[13.539378,43.451351],"type":"Point"}
}