{
  "type": "Feature",
  "properties": {
    "addr:full":"Via S. Maria 32 33050 Bicinicco Bicinicco Udine 33050",
    "addr:housenumber":"32",
    "addr:postcode":"33050;33050",
    "addr:street":"Via S. Maria",
    "iso:country":"IT",
    "sg:address":"Via S. Maria 32 33050 Bicinicco",
    "sg:city":"Bicinicco",
    "sg:orig_category":"Chipboards",
    "sg:phone":"+39 0432 9301",
    "sg:postcode":"33050",
    "sg:province":"Udine",
    "sg:website":"www.bipan.it",
    "wof:name":"Bipan Spa",
    "wof:placetype":"venue"
},
  "geometry": {"coordinates":[13.256546,45.930683],"type":"Point"}
}