{
  "type": "Feature",
  "properties": {
    "iso:country":"IT",
    "sg:address":"27043 Broni",
    "sg:city":"Broni",
    "sg:orig_category":"Centri Di Estetica E Cosmesi E Servizi",
    "sg:phone":"+39 0385 569035",
    "sg:postcode":"27043",
    "sg:province":"Pavia",
    "wof:name":"Sacca' Vincenzo",
    "wof:placetype":"venue"
},
  "geometry": {"coordinates":[9.263463,45.066406],"type":"Point"}
}