{
  "type": "Feature",
  "properties": {
    "iso:country":"IT",
    "sg:address":"39, V. Caberardi 24012 Brembilla",
    "sg:city":"Brembilla",
    "sg:classifiers":[
        {
            "category":"Manufacturing",
            "subcategory":"Metals",
            "type":"Manufacturing & Wholesale Goods"
        }
    ],
    "sg:phone":"+39 39034598235",
    "sg:postcode":"24012",
    "sg:province":"Bergamo",
    "sg:tags":[
        "processing"
    ],
    "sg:website":"http://www.daminelli.com",
    "wof:name":"Daminelli Srl",
    "wof:placetype":"venue"
},
  "geometry": {"coordinates":[9.6038312912,45.8132629395],"type":"Point"}
}