{
  "type": "Feature",
  "properties": {
    "iso:country":"IT",
    "sg:address":"94010 Villarosa",
    "sg:city":"Villarosa",
    "sg:orig_category":"Materiali Edili",
    "sg:phone":"+39 0935 31269",
    "sg:postcode":"94010",
    "sg:province":"Enna",
    "wof:name":"Cotto Aragona Snc",
    "wof:placetype":"venue"
},
  "geometry": {"coordinates":[14.173325,37.586723],"type":"Point"}
}