{
  "type": "Feature",
  "properties": {
    "iso:country":"IT",
    "sg:address":"37052 Casaleone",
    "sg:city":"Casaleone",
    "sg:orig_category":"Sementi E Bulbi",
    "sg:phone":"+39 0442 331600",
    "sg:postcode":"37052",
    "sg:province":"Verona",
    "sg:website":"http://www.esasem.com",
    "wof:name":"Esasem Spa",
    "wof:placetype":"venue"
},
  "geometry": {"coordinates":[11.205403,45.13448],"type":"Point"}
}