{
  "type": "Feature",
  "properties": {
    "iso:country":"IT",
    "sg:address":"55021 Bagni Di Lucca",
    "sg:orig_category":"Ristorazione E Locali Pubblici Affini. Servizi Per Lo Sport E Il Tempo Libero. Alberghi E Strutture Extra Alberghiere. Ristoranti Ed Esercizi Affini",
    "sg:phone":"+39 0583 87983",
    "sg:province":"LU",
    "wof:name":"Azienda Agricola 'belvedere'",
    "wof:placetype":"venue"
},
  "geometry": {"coordinates":[10.558409,44.006767],"type":"Point"}
}