{
  "type": "Feature",
  "properties": {
    "addr:full":"17100 Savona Savona Savona 17100",
    "addr:postcode":"17100;17100",
    "iso:country":"IT",
    "sg:address":"17100 Savona",
    "sg:city":"Savona",
    "sg:classifiers":[
        {
            "category":"Health Services",
            "subcategory":"Health Practitioner",
            "type":"Services"
        }
    ],
    "sg:phone":"+39 019 825708",
    "sg:postcode":"17100",
    "sg:province":"Savona",
    "sg:tags":[
        "medici"
    ],
    "wof:name":"Sciacero Francesco",
    "wof:placetype":"venue"
},
  "geometry": {"coordinates":[8.4293889999,44.3425483704],"type":"Point"}
}