{
  "type": "Feature",
  "properties": {
    "iso:country":"IT",
    "sg:address":"27010 Miradolo Terme",
    "sg:city":"Miradolo Terme",
    "sg:orig_category":"Forniture Per Abbigliamento E Pelletterie",
    "sg:postcode":"27010",
    "sg:province":"Pavia",
    "wof:name":"Albanesi Fabio",
    "wof:placetype":"venue"
},
  "geometry": {"coordinates":[9.4457349777,45.1665267944],"type":"Point"}
}