{
  "type": "Feature",
  "properties": {
    "iso:country":"IT",
    "sg:address":"21019 Somma Lombardo",
    "sg:city":"Somma Lombardo",
    "sg:orig_category":"Macchine, Impianti Ed Attrezzature Per Abbigliamento E Pelletterie",
    "sg:phone":"+39 0331 251530",
    "sg:postcode":"21019",
    "sg:province":"Varese",
    "wof:name":"Zamark S.r.l.",
    "wof:placetype":"venue"
},
  "geometry": {"coordinates":[8.704273,45.676941],"type":"Point"}
}