{
  "type": "Feature",
  "properties": {
    "addr:full":"Via Calabria 11 50052 Certaldo Certaldo Firenze 50052",
    "addr:housenumber":"11",
    "addr:postcode":"50052;50052",
    "addr:street":"Via Calabria",
    "iso:country":"IT",
    "sg:address":"Via Calabria 11 50052 Certaldo",
    "sg:city":"Certaldo",
    "sg:orig_category":"Adhesive Tapes Manufacturing Machines",
    "sg:phone":"+39 0571 668337",
    "sg:postcode":"50052",
    "sg:province":"Firenze",
    "sg:website":"www.nuova-omc.it",
    "wof:name":"Nuova Omc Dei Fratelli Calvetti Snc",
    "wof:placetype":"venue"
},
  "geometry": {"coordinates":[11.031607,43.562214],"type":"Point"}
}