{
  "type": "Feature",
  "properties": {
    "iso:country":"IT",
    "sg:address":"33170 Pordenone",
    "sg:city":"Pordenone",
    "sg:orig_category":"Non-classified Establishments",
    "sg:phone":"+39 0434 571 2041",
    "sg:postcode":"33170",
    "sg:province":"Pordenone",
    "sg:website":"http://www.valcucine.it",
    "wof:name":"Valcucine Spa",
    "wof:placetype":"venue"
},
  "geometry": {"coordinates":[12.650542,45.926983],"type":"Point"}
}