{
  "type": "Feature",
  "properties": {
    "iso:country":"IT",
    "sg:address":"20090 Buccinasco",
    "sg:city":"Buccinasco",
    "sg:orig_category":"Barche, Canotti Pneumatici E Motoscafi - Vendita Al Dettaglio",
    "sg:phone":"+39 02 4884 1626",
    "sg:postcode":"20090",
    "sg:province":"Milano",
    "wof:name":"A.r.c.a. Sas Di Negri & Mezzanzanica",
    "wof:placetype":"venue"
},
  "geometry": {"coordinates":[9.112334,45.433735],"type":"Point"}
}