{
  "type": "Feature",
  "properties": {
    "iso:country":"IT",
    "sg:address":"00179 Roma",
    "sg:city":"Roma",
    "sg:orig_category":"Prodotti Alimentari. Bevande, Vini E Liquori. Medicinali E Prodotti Parafarmaceutici",
    "sg:phone":"+39 06 782 0639",
    "sg:postcode":"00179",
    "sg:province":"Roma",
    "wof:name":"Brancati Raffaele",
    "wof:placetype":"venue"
},
  "geometry": {"coordinates":[12.5334091187,41.8688354492],"type":"Point"}
}