{
  "type": "Feature",
  "properties": {
    "iso:country":"IT",
    "sg:address":"4, Via Di Vittorio 23844 Sirone",
    "sg:city":"Sirone",
    "sg:classifiers":[
        {
            "category":"Professional",
            "subcategory":"Engineering",
            "type":"Services"
        }
    ],
    "sg:phone":"+39 39031852157",
    "sg:postcode":"23844",
    "sg:province":"Lecco",
    "sg:tags":[
        "machine",
        "-",
        "mechanical"
    ],
    "wof:name":"Cos Ma (s.r.l.)",
    "wof:placetype":"venue"
},
  "geometry": {"coordinates":[9.365678,45.791668],"type":"Point"}
}