{
  "type": "Feature",
  "properties": {
    "addr:full":"52025 Montevarchi Montevarchi Arezzo 52025",
    "addr:postcode":"52025;52025",
    "iso:country":"IT",
    "sg:address":"52025 Montevarchi",
    "sg:city":"Montevarchi",
    "sg:orig_category":"Prodotti Alimentari",
    "sg:phone":"+39 055 982391",
    "sg:postcode":"52025",
    "sg:province":"Arezzo",
    "wof:name":"La Bottega Di Vanna",
    "wof:placetype":"venue"
},
  "geometry": {"coordinates":[11.5589103699,43.5000801086],"type":"Point"}
}