{
  "type": "Feature",
  "properties": {
    "iso:country":"IT",
    "sg:address":"Via Dell' Industria 60020 Polverigi",
    "sg:city":"Polverigi",
    "sg:classifiers":[
        {
            "category":"Home & Garden",
            "subcategory":"Home Furnishings",
            "type":"Retail Goods"
        }
    ],
    "sg:phone":"+39 39071906324",
    "sg:postcode":"60020",
    "sg:province":"Ancona",
    "sg:tags":[
        "household"
    ],
    "wof:name":"Inoxa Srl",
    "wof:placetype":"venue"
},
  "geometry": {"coordinates":[13.371237,43.530861],"type":"Point"}
}