{
  "type": "Feature",
  "properties": {
    "addr:full":"Via Ugo Foscolo 83 25016 Ghedi Ghedi Brescia 25016",
    "addr:housenumber":"83",
    "addr:postcode":"25016;25016",
    "addr:street":"Via Ugo Foscolo",
    "iso:country":"IT",
    "sg:address":"Via Ugo Foscolo 83 25016 Ghedi",
    "sg:city":"Ghedi",
    "sg:classifiers":[
        {
            "category":"Wholesale",
            "subcategory":"Machinery & Supplies",
            "type":"Manufacturing & Wholesale Goods"
        }
    ],
    "sg:phone":"+39 030 901631",
    "sg:postcode":"25016",
    "sg:province":"Brescia",
    "sg:tags":[
        "agricultural",
        "equipment"
    ],
    "sg:website":"www.gong.it",
    "wof:name":"Gong Spa",
    "wof:placetype":"venue"
},
  "geometry": {"coordinates":[10.242509,45.481567],"type":"Point"}
}