{
  "type": "Feature",
  "properties": {
    "addr:full":"Via Pisa 61 20093 Cologno Monzese Cologno Monzese Milano 20093",
    "addr:housenumber":"61",
    "addr:postcode":"20093;20093",
    "addr:street":"Via Pisa",
    "iso:country":"IT",
    "sg:address":"Via Pisa 61 20093 Cologno Monzese",
    "sg:city":"Cologno Monzese",
    "sg:classifiers":[
        {
            "category":"Shopping",
            "subcategory":"Beauty & Cosmetics",
            "type":"Retail Goods"
        }
    ],
    "sg:phone":"+39 02 2730 4275",
    "sg:postcode":"20093",
    "sg:province":"Milano",
    "sg:tags":[
        "farm",
        "equipment",
        "care",
        "institute",
        "wellness"
    ],
    "sg:website":"www.biositalia.it",
    "wof:name":"Bios S.r.l.",
    "wof:placetype":"venue"
},
  "geometry": {"coordinates":[9.272047,45.522484],"type":"Point"}
}