{
  "type": "Feature",
  "properties": {
    "iso:country":"IT",
    "sg:address":"19, Via Gorizia 36050 Bolzano Vicentino",
    "sg:city":"Bolzano Vicentino",
    "sg:classifiers":[
        {
            "category":"Manufacturing",
            "subcategory":"Rubber & Plastics",
            "type":"Manufacturing & Wholesale Goods"
        }
    ],
    "sg:phone":"+39 0444 350111",
    "sg:postcode":"36050",
    "sg:province":"Vicenza",
    "wof:name":"Marchetti Pneumatici (s.r.l.)",
    "wof:placetype":"venue"
},
  "geometry": {"coordinates":[11.633188,45.590801],"type":"Point"}
}