{
  "type": "Feature",
  "properties": {
    "addr:full":"6, Via Del Lavoro 31033 Castelfranco Veneto Castelfranco Veneto Treviso 31033",
    "addr:postcode":"31033;31033",
    "addr:street":"Via Del Lavoro",
    "iso:country":"IT",
    "sg:address":"6, Via Del Lavoro 31033 Castelfranco Veneto",
    "sg:city":"Castelfranco Veneto",
    "sg:classifiers":[
        {
            "category":"Wholesale",
            "subcategory":"Machinery & Supplies",
            "type":"Manufacturing & Wholesale Goods"
        }
    ],
    "sg:phone":"+39 0423 738511",
    "sg:postcode":"31033",
    "sg:province":"Treviso",
    "sg:tags":[
        "-",
        "agriculture",
        "equipment"
    ],
    "wof:name":"Castelgarden S.p.a.",
    "wof:placetype":"venue"
},
  "geometry": {"coordinates":[11.964115,45.670643],"type":"Point"}
}