{
  "type": "Feature",
  "properties": {
    "iso:country":"IT",
    "sg:address":"25027 Quinzano D'oglio",
    "sg:classifiers":[
        {
            "category":"Wholesale",
            "subcategory":"Hardware",
            "type":"Manufacturing & Wholesale Goods"
        }
    ],
    "sg:phone":"+39 030 933035",
    "sg:postcode":"25027",
    "sg:province":"Brescia",
    "sg:tags":[
        "activities",
        "industrial",
        "supply",
        "valve",
        "equipment",
        "measurement"
    ],
    "sg:website":"http://www.baronio.it",
    "wof:name":"F.b.q. Baronio Srl",
    "wof:placetype":"venue"
},
  "geometry": {"coordinates":[10.009704,45.31189],"type":"Point"}
}