{
  "type": "Feature",
  "properties": {
    "iso:country":"IT",
    "sg:address":"58100 Grosseto",
    "sg:city":"Grosseto",
    "sg:orig_category":"Attrezzature E Forniture Per Officine Riparazione E Servizi Ausiliari",
    "sg:phone":"+39 0564 415314",
    "sg:postcode":"58100",
    "sg:province":"Grosseto",
    "wof:name":"C.d.e. Centro Distribuzione",
    "wof:placetype":"venue"
},
  "geometry": {"coordinates":[11.114108,42.765507],"type":"Point"}
}