{
  "type": "Feature",
  "properties": {
    "iso:country":"IT",
    "sg:address":"Via A De Gasperi 2; Sordio; 20070",
    "sg:classifiers":[
        {
            "category":"Banks & Credit Unions",
            "subcategory":"Bank",
            "type":"Services"
        }
    ],
    "sg:phone":"+39 02 9826 0514",
    "sg:postcode":"20070",
    "sg:province":"Milano",
    "wof:name":"Istituto Bancario, San Paolo Di Torino Spa",
    "wof:placetype":"venue"
},
  "geometry": {"coordinates":[9.361927,45.3419],"type":"Point"}
}