{
  "type": "Feature",
  "properties": {
    "iso:country":"IT",
    "sg:address":"09040 Guasila",
    "sg:city":"Guasila",
    "sg:orig_category":"Servizi E Lavori Per Edilizia E Lavori Pubblici",
    "sg:phone":"+39 070 980 6862",
    "sg:postcode":"09040",
    "sg:province":"Cagliari",
    "wof:name":"Trexenta Decorazioni",
    "wof:placetype":"venue"
},
  "geometry": {"coordinates":[9.045019,39.563866],"type":"Point"}
}