{
  "type": "Feature",
  "properties": {
    "addr:full":"42015 Correggio Reggio Nell'Emilia 42015",
    "addr:postcode":"42015;42015",
    "iso:country":"IT",
    "sg:address":"42015 Correggio",
    "sg:orig_category":"Manufacturers: Prefabbricati. Prodotti Vari In Metallo",
    "sg:phone":"+39 0522 633123",
    "sg:postcode":"42015",
    "sg:province":"Reggio Nell'Emilia",
    "wof:name":"Greenpipe Srl",
    "wof:placetype":"venue"
},
  "geometry": {"coordinates":[10.792724,44.768467],"type":"Point"}
}