{
  "type": "Feature",
  "properties": {
    "iso:country":"IT",
    "sg:address":"35010 Cadoneghe",
    "sg:city":"Cadoneghe",
    "sg:orig_category":"Macchine E Forniture Per Arredamento E Industria Del Legno. Forniture Per Edilizia E Lavori Pubblici",
    "sg:phone":"+39 049 887 3577",
    "sg:postcode":"35010",
    "sg:province":"Padova",
    "wof:name":"Gabrieli Srl",
    "wof:placetype":"venue"
},
  "geometry": {"coordinates":[11.898566,45.451824],"type":"Point"}
}