{
  "type": "Feature",
  "properties": {
    "iso:country":"IT",
    "sg:address":"59100 Prato",
    "sg:city":"Prato",
    "sg:orig_category":"Abbigliamento Esterno, Maglierie E Pelliccerie. Calzature, Pelletterie E Pelli",
    "sg:phone":"+39 0574 527712",
    "sg:postcode":"59100",
    "sg:province":"Prato",
    "wof:name":"Px Military Store Srl",
    "wof:placetype":"venue"
},
  "geometry": {"coordinates":[11.109426,43.868416],"type":"Point"}
}