{
  "type": "Feature",
  "properties": {
    "iso:country":"IT",
    "sg:address":"24050 Morengo",
    "sg:city":"Morengo",
    "sg:orig_category":"Geometri - Studi",
    "sg:phone":"+39 036 395690",
    "sg:postcode":"24050",
    "sg:province":"Bergamo",
    "wof:name":"Facchetti Geom. Gaudenzio",
    "wof:placetype":"venue"
},
  "geometry": {"coordinates":[9.705302,45.536739],"type":"Point"}
}