{
  "type": "Feature",
  "properties": {
    "iso:country":"IT",
    "sg:address":"36054 Montebello Vicentino",
    "sg:city":"Montebello Vicentino",
    "sg:classifiers":[
        {
            "category":"Retail",
            "subcategory":"Event Space",
            "type":"Services"
        }
    ],
    "sg:phone":"+39 0444 449511",
    "sg:postcode":"36054",
    "sg:province":"Vicenza",
    "sg:tags":[
        "leather",
        "clothing",
        "goods",
        "work"
    ],
    "sg:website":"http://www.montebello-tannery.it",
    "wof:name":"Montebello Conceria Spa",
    "wof:placetype":"venue"
},
  "geometry": {"coordinates":[11.383273,45.458767],"type":"Point"}
}