{
  "type": "Feature",
  "properties": {
    "iso:country":"IT",
    "sg:address":"20092 Cinisello Balsamo",
    "sg:city":"Cinisello Balsamo",
    "sg:orig_category":"Abbigliamento Intimo, Calze E Costumi Da Bagno",
    "sg:phone":"+39 02 612 8104",
    "sg:postcode":"20092",
    "sg:province":"Milano",
    "wof:name":"Dueelle Ingrosso Calze Di Lavista A. E Lapesa A. (s.n.c.)",
    "wof:placetype":"venue"
},
  "geometry": {"coordinates":[9.229849,45.547604],"type":"Point"}
}