{
  "type": "Feature",
  "properties": {
    "iso:country":"IT",
    "sg:address":"26854 Cornegliano Laudense - Lodi",
    "sg:city":"Cornegliano Laudense",
    "sg:orig_category":"Cromatura E Nichelatura",
    "sg:phone":"+39 0371 69381",
    "sg:postcode":"26854",
    "sg:province":"Lodi",
    "sg:website":"http://www.midare.it",
    "wof:name":"Mida Di Pozzi Giorgio",
    "wof:placetype":"venue"
},
  "geometry": {"coordinates":[9.473631,45.288692],"type":"Point"}
}