{
  "type": "Feature",
  "properties": {
    "addr:full":"61020 Lunano Pesaro E Urbino 61020",
    "addr:postcode":"61020;61020",
    "iso:country":"IT",
    "sg:address":"61020 Lunano",
    "sg:orig_category":"Macchine E Forniture Per Arredamento E Industria Del Legno",
    "sg:phone":"+39 0722 70108",
    "sg:postcode":"61020",
    "sg:province":"Pesaro E Urbino",
    "wof:name":"San Girolamo Srl",
    "wof:placetype":"venue"
},
  "geometry": {"coordinates":[12.529803,43.633556],"type":"Point"}
}