{
  "type": "Feature",
  "properties": {
    "iso:country":"IT",
    "sg:address":"10142 Torino",
    "sg:city":"Torino",
    "sg:orig_category":"Accessori Dei Mezzi Di Trasporto. Riparazione Dei Mezzi Di Trasporto",
    "sg:phone":"+39 011 770 7242",
    "sg:postcode":"10142",
    "sg:province":"Torino",
    "wof:name":"S.i.a. Di Vicidomini Francesco & C.",
    "wof:placetype":"venue"
},
  "geometry": {"coordinates":[7.621691,45.063118],"type":"Point"}
}