{
  "type": "Feature",
  "properties": {
    "iso:country":"IT",
    "sg:address":"35020 Saonara",
    "sg:city":"Saonara",
    "sg:orig_category":"Forniture Per Abbigliamento E Pelletterie. Forniture Per Attivita' Commerciali Ed Artigianali",
    "sg:phone":"+39 049 879 0566",
    "sg:postcode":"35020",
    "sg:province":"Padova",
    "wof:name":"Etichettificio Veneto (s.n.c.)",
    "wof:placetype":"venue"
},
  "geometry": {"coordinates":[11.9649362564,45.3812408447],"type":"Point"}
}