{
  "type": "Feature",
  "properties": {
    "addr:full":"00187 Roma Roma Roma 00187",
    "addr:postcode":"00187;00187",
    "iso:country":"IT",
    "sg:address":"00187 Roma",
    "sg:city":"Roma",
    "sg:orig_category":"Calzature, Pelletterie E Pelli. Servizi E Lavori Per Abbigliamento E Pelletterie",
    "sg:phone":"+39 06 474 2474",
    "sg:postcode":"00187",
    "sg:province":"Roma",
    "wof:name":"Reale Alessandro",
    "wof:placetype":"venue"
},
  "geometry": {"coordinates":[12.494669,41.906033],"type":"Point"}
}