{
  "type": "Feature",
  "properties": {
    "iso:country":"IT",
    "sg:address":"22036 Erba",
    "sg:city":"Erba",
    "sg:orig_category":"Non-classified Establishments",
    "sg:phone":"+39 031 640276",
    "sg:postcode":"22036",
    "sg:province":"Como",
    "wof:name":"Ripamonti Giuseppe",
    "wof:placetype":"venue"
},
  "geometry": {"coordinates":[9.038425,45.830288],"type":"Point"}
}