{
  "type": "Feature",
  "properties": {
    "iso:country":"IT",
    "sg:address":"20154 Milano",
    "sg:city":"Milano",
    "sg:orig_category":"Animali Domestici, Articoli Ed Alimenti - Vendita Al Dettaglio",
    "sg:phone":"+39 02 3360 3951",
    "sg:postcode":"20154",
    "sg:province":"Milano",
    "wof:name":"Paro Viviana - Sala Del Cane",
    "wof:placetype":"venue"
},
  "geometry": {"coordinates":[9.177589,45.479176],"type":"Point"}
}