{
  "type": "Feature",
  "properties": {
    "addr:full":"18, Via Poggiali Cristoforo 29100 Piacenza Piacenza Piacenza 29100",
    "addr:postcode":"29100;29100",
    "addr:street":"Via Poggiali Cristoforo",
    "iso:country":"IT",
    "sg:address":"18, Via Poggiali Cristoforo 29100 Piacenza",
    "sg:city":"Piacenza",
    "sg:classifiers":[
        {
            "category":"Banks & Credit Unions",
            "subcategory":"Bank",
            "type":"Services"
        }
    ],
    "sg:phone":"+39 39052354111",
    "sg:postcode":"29100",
    "sg:province":"Piacenza",
    "sg:tags":[
        "banking",
        "institution"
    ],
    "wof:name":"Cassa Di Risparmio Di Parma & Piacenza (s.p.a.)",
    "wof:placetype":"venue"
},
  "geometry": {"coordinates":[9.695142,45.053772],"type":"Point"}
}