{
  "type": "Feature",
  "properties": {
    "iso:country":"IT",
    "sg:address":"57123 Livorno",
    "sg:city":"Livorno",
    "sg:orig_category":"Scuole E Servizi Scolastici",
    "sg:phone":"+39 0586 210120",
    "sg:postcode":"57123",
    "sg:province":"Livorno",
    "wof:name":"Associazione Culturale Vertigo",
    "wof:placetype":"venue"
},
  "geometry": {"coordinates":[10.310501,43.577747],"type":"Point"}
}