{
  "type": "Feature",
  "properties": {
    "iso:country":"IT",
    "sg:address":"Via Del Canneto 25010 Borgosatollo",
    "sg:city":"Borgosatollo",
    "sg:classifiers":[
        {
            "category":"Professional",
            "subcategory":"Engineering",
            "type":"Services"
        }
    ],
    "sg:phone":"+39 030 270 2562",
    "sg:postcode":"25010",
    "sg:province":"Brescia",
    "sg:tags":[
        "machine",
        "-",
        "mechanical"
    ],
    "wof:name":"Pesci Attrezzature (s.r.l.)",
    "wof:placetype":"venue"
},
  "geometry": {"coordinates":[10.250657,45.482632],"type":"Point"}
}