{
  "type": "Feature",
  "properties": {
    "addr:full":"7, Piazzetta Montalcino 50142 Firenze Firenze Firenze 50142",
    "addr:housenumber":"7",
    "addr:postcode":"50142;50142",
    "addr:street":"Piazzetta Montalcino",
    "iso:country":"IT",
    "sg:address":"7, Piazzetta Montalcino 50142 Firenze",
    "sg:city":"Firenze",
    "sg:classifiers":[
        {
            "category":"Shopping",
            "subcategory":"Jewelry",
            "type":"Retail Goods"
        }
    ],
    "sg:phone":"+39 055 732 3082",
    "sg:postcode":"50142",
    "sg:province":"Firenze",
    "sg:tags":[
        "jewellery"
    ],
    "wof:name":"Piccioli",
    "wof:placetype":"venue"
},
  "geometry": {"coordinates":[11.208508,43.770901],"type":"Point"}
}