{
  "type": "Feature",
  "properties": {
    "iso:country":"IT",
    "sg:address":"20097 San Donato Milanese",
    "sg:city":"San Donato Milanese",
    "sg:classifiers":[
        {
            "category":"Shopping",
            "subcategory":"Bicycles & Sporting Goods",
            "type":"Retail Goods"
        }
    ],
    "sg:phone":"+39 02 5570 0257",
    "sg:postcode":"20097",
    "sg:province":"Milano",
    "sg:tags":[
        "tempo",
        "lo",
        "-",
        "libero",
        "per",
        "servizi",
        "forniture",
        "articoli",
        "e",
        "sport",
        "il"
    ],
    "wof:name":"Fulgheri Pesca Sport",
    "wof:placetype":"venue"
},
  "geometry": {"coordinates":[9.253367,45.424278],"type":"Point"}
}