{
  "type": "Feature",
  "properties": {
    "iso:country":"IT",
    "sg:address":"Corso Vitt. Emanuele, 23; Margherita Di Savoia; 71044",
    "sg:city":"Margherita di Savoia",
    "sg:classifiers":[
        {
            "category":"Banks & Credit Unions",
            "subcategory":"Bank",
            "type":"Services"
        }
    ],
    "sg:phone":"+39 0883 754040",
    "sg:postcode":"71044",
    "sg:province":"Foggia",
    "wof:name":"Cassa Di Risparmio Di Puglia",
    "wof:placetype":"venue"
},
  "geometry": {"coordinates":[16.169857,41.352306],"type":"Point"}
}