{
  "type": "Feature",
  "properties": {
    "addr:full":"28, Via Loghetto 24050 Cortenuova Cortenuova Bergamo 24050",
    "addr:postcode":"24050;24050",
    "addr:street":"Via Loghetto",
    "iso:country":"IT",
    "sg:address":"28, Via Loghetto 24050 Cortenuova",
    "sg:city":"Cortenuova",
    "sg:classifiers":[
        {
            "category":"Shopping",
            "subcategory":"Clothing, Apparel, & Fashions",
            "type":"Retail Goods"
        }
    ],
    "sg:phone":"+39 036 390 9139",
    "sg:postcode":"24050",
    "sg:province":"Bergamo",
    "sg:tags":[
        "clothes"
    ],
    "wof:name":"Confezioni Gio - Ade (s.n.c.)",
    "wof:placetype":"venue"
},
  "geometry": {"coordinates":[9.790113,45.539635],"type":"Point"}
}