{
  "type": "Feature",
  "properties": {
    "iso:country":"IT",
    "sg:address":"Via S. Crispino, 1/3 - Mastromarco 51035 Lamporecchio",
    "sg:city":"Lamporecchio",
    "sg:orig_category":"Government-issue Shoes And Boots",
    "sg:phone":"+39 0573 82062",
    "sg:postcode":"51035",
    "sg:province":"Pistoia",
    "sg:website":"www.calzaturieri.it",
    "wof:name":"Calzaturieri Mastromarco Scrl",
    "wof:placetype":"venue"
},
  "geometry": {"coordinates":[10.918524,43.932156],"type":"Point"}
}