{
  "type": "Feature",
  "properties": {
    "iso:country":"IT",
    "sg:address":"17025 Loano",
    "sg:city":"Loano",
    "sg:orig_category":"Accessori Moda D'abbigliamento. Complementi Di Arredamento. Tempo Libero - Articoli E Forniture",
    "sg:phone":"+39 019 668844",
    "sg:postcode":"17025",
    "sg:province":"Savona",
    "wof:name":"Vico",
    "wof:placetype":"venue"
},
  "geometry": {"coordinates":[8.258011,44.128551],"type":"Point"}
}