{
  "type": "Feature",
  "properties": {
    "iso:country":"IT",
    "sg:address":"52, Via Fiumazzo 48022 Lugo",
    "sg:city":"Lugo",
    "sg:classifiers":[
        {
            "category":"Shopping",
            "type":"Retail Goods"
        }
    ],
    "sg:phone":"+39 39054533275",
    "sg:postcode":"48022",
    "sg:province":"Ravenna",
    "sg:tags":[
        "finished",
        "-",
        "metallic"
    ],
    "wof:name":"Sall (s.r.l.)",
    "wof:placetype":"venue"
},
  "geometry": {"coordinates":[11.882686615,44.4592819214],"type":"Point"}
}