{
  "type": "Feature",
  "properties": {
    "addr:full":"1, Via Spineta 84091 Battipaglia Battipaglia Salerno 84091",
    "addr:postcode":"84091;84091",
    "addr:street":"Via Spineta",
    "iso:country":"IT",
    "sg:address":"1, Via Spineta 84091 Battipaglia",
    "sg:city":"Battipaglia",
    "sg:classifiers":[
        {
            "category":"Manufacturing",
            "subcategory":"Rubber & Plastics",
            "type":"Manufacturing & Wholesale Goods"
        }
    ],
    "sg:phone":"+39 0828 673375",
    "sg:postcode":"84091",
    "sg:province":"Salerno",
    "wof:name":"Paif S.p.a.",
    "wof:placetype":"venue"
},
  "geometry": {"coordinates":[14.8897800446,40.5729827881],"type":"Point"}
}