{
  "type": "Feature",
  "properties": {
    "addr:full":"60123 Ancona Ancona Ancona 60123",
    "addr:postcode":"60123;60123",
    "iso:country":"IT",
    "sg:address":"60123 Ancona",
    "sg:city":"Ancona",
    "sg:orig_category":"Prodotti Chimici Secondari. Prodotti Cosmetici E Da Toeletta",
    "sg:phone":"+39 071 31980",
    "sg:postcode":"60123",
    "sg:province":"Ancona",
    "wof:name":"Lamonea Srl",
    "wof:placetype":"venue"
},
  "geometry": {"coordinates":[13.5277853012,43.6185531616],"type":"Point"}
}