{
  "type": "Feature",
  "properties": {
    "iso:country":"IT",
    "sg:address":"43011 Busseto",
    "sg:city":"Busseto",
    "sg:classifiers":[
        {
            "category":"Military Area",
            "subcategory":"Air Force Base",
            "type":"Public Place"
        }
    ],
    "sg:phone":"+39 0524 91164",
    "sg:postcode":"43011",
    "sg:province":"Parma",
    "sg:tags":[
        "cave",
        "e",
        "miniere"
    ],
    "wof:name":"S.e.t.i.f. Srl",
    "wof:placetype":"venue"
},
  "geometry": {"coordinates":[10.0504932404,44.9597320557],"type":"Point"}
}