{
  "type": "Feature",
  "properties": {
    "addr:full":"Via Cadorna, 11/15 22060 Carugo Carugo Como 22060",
    "addr:housenumber":"11 / 15",
    "addr:postcode":"22060;22060",
    "addr:street":"Via Cadorna",
    "iso:country":"IT",
    "sg:address":"Via Cadorna, 11/15 22060 Carugo",
    "sg:city":"Carugo",
    "sg:orig_category":"Furniture, General",
    "sg:phone":"+39 031 762070",
    "sg:postcode":"22060",
    "sg:province":"Como",
    "sg:website":"www.nespoliarredamenti.it",
    "wof:name":"Nespoli Industria Arredamenti Srl",
    "wof:placetype":"venue"
},
  "geometry": {"coordinates":[9.1925783157,45.7087440491],"type":"Point"}
}