{
  "type": "Feature",
  "properties": {
    "iso:country":"IT",
    "sg:address":"35010 Villafranca Padovana",
    "sg:city":"Campodoro",
    "sg:orig_category":"Servizi E Lavori Per Arredamento E Industria Del Legno",
    "sg:phone":"+39 049 905 0034",
    "sg:postcode":"35010",
    "sg:province":"Padova",
    "wof:name":"Nuova Complat Spa",
    "wof:placetype":"venue"
},
  "geometry": {"coordinates":[11.768288,45.463024],"type":"Point"}
}