{
  "type": "Feature",
  "properties": {
    "iso:country":"IT",
    "sg:address":"9, Viale Mengozzi Narciso 53100 Siena",
    "sg:city":"Siena",
    "sg:classifiers":[
        {
            "category":"Wholesale",
            "subcategory":"Drugs",
            "type":"Manufacturing & Wholesale Goods"
        }
    ],
    "sg:phone":"+39 0577 385045",
    "sg:postcode":"53100",
    "sg:province":"Siena",
    "sg:tags":[
        "chemical",
        "pharmaceutical"
    ],
    "wof:name":"Detercom Professional S.r.l.",
    "wof:placetype":"venue"
},
  "geometry": {"coordinates":[11.330514,43.318661],"type":"Point"}
}