{
  "type": "Feature",
  "properties": {
    "iso:country":"IT",
    "sg:address":"Via Petrobelli 11, 25022 Borgo San Giacomo, Bs",
    "sg:city":"Borgo San Giacomo",
    "sg:classifiers":[
        {
            "category":"Banks & Credit Unions",
            "subcategory":"Bank",
            "type":"Services"
        }
    ],
    "sg:postcode":"25022",
    "sg:province":"Brescia",
    "wof:name":"Cassa Rurale Ed Artigiana Di Borgo San Giacomo (brescia)- Scarl Credito Cooperativo",
    "wof:placetype":"venue"
},
  "geometry": {"coordinates":[9.966356,45.350304],"type":"Point"}
}