{
  "type": "Feature",
  "properties": {
    "iso:country":"IT",
    "sg:address":"20017 Rho",
    "sg:city":"Rho",
    "sg:orig_category":"Apparecchi, Attrezzature E Forniture Per Centri Estetici",
    "sg:phone":"+39 02 9390 1244",
    "sg:postcode":"20017",
    "sg:province":"Milano",
    "wof:name":"Newsun (s.r.l.)",
    "wof:placetype":"venue"
},
  "geometry": {"coordinates":[9.083718,45.526047],"type":"Point"}
}