{
  "type": "Feature",
  "properties": {
    "iso:country":"IT",
    "sg:address":"Via Dell' Informatica ,22 - Vigano 20083 Gaggiano",
    "sg:city":"Gaggiano",
    "sg:classifiers":[
        {
            "category":"Manufacturing",
            "subcategory":"Building Materials",
            "type":"Manufacturing & Wholesale Goods"
        }
    ],
    "sg:phone":"+39 02 908 1760",
    "sg:postcode":"20083",
    "sg:province":"Milano",
    "sg:tags":[
        "installation",
        "electrical",
        "explosion-proof"
    ],
    "wof:name":"Kroma Mec Srl",
    "wof:placetype":"venue"
},
  "geometry": {"coordinates":[9.03068,45.381577],"type":"Point"}
}