{
  "type": "Feature",
  "properties": {
    "iso:country":"IT",
    "sg:address":"18, Via Friuli 31057 Silea",
    "sg:city":"Silea",
    "sg:classifiers":[
        {
            "category":"Shopping",
            "subcategory":"Clothing, Apparel, & Fashions",
            "type":"Retail Goods"
        }
    ],
    "sg:phone":"+39 0422 362433",
    "sg:postcode":"31057",
    "sg:province":"Treviso",
    "sg:tags":[
        "clothes"
    ],
    "wof:name":"Dieffe Di Tessari Fiorella & C. S.n.c.",
    "wof:placetype":"venue"
},
  "geometry": {"coordinates":[12.291729,45.659569],"type":"Point"}
}