{
  "type": "Feature",
  "properties": {
    "iso:country":"IT",
    "sg:address":"00166 Roma",
    "sg:city":"Roma",
    "sg:orig_category":"Impiantistica E Prodotti Tecnologici Per Edilizia. Elettronica Professionale E Di Consumo",
    "sg:phone":"+39 06 6654 1541",
    "sg:postcode":"00166",
    "sg:province":"Roma",
    "wof:name":"Cerundolo Salvatore",
    "wof:placetype":"venue"
},
  "geometry": {"coordinates":[12.412865,41.897282],"type":"Point"}
}