{
  "type": "Feature",
  "properties": {
    "addr:full":"20084 Lacchiarella Lacchiarella Milano 20084",
    "addr:postcode":"20084;20084",
    "iso:country":"IT",
    "sg:address":"20084 Lacchiarella",
    "sg:city":"Lacchiarella",
    "sg:orig_category":"Servizi E Lavori Per Agricoltura E Zootecnia. Animali Domestici",
    "sg:phone":"+39 02 900 8550",
    "sg:postcode":"20084",
    "sg:province":"Milano",
    "wof:name":"Penati Valentino",
    "wof:placetype":"venue"
},
  "geometry": {"coordinates":[9.137855,45.36911],"type":"Point"}
}