{
  "type": "Feature",
  "properties": {
    "addr:full":"28924 Verbania Verbania Verbano-Cusio-Ossola 28924",
    "addr:postcode":"28924;28924",
    "iso:country":"IT",
    "sg:address":"28924 Verbania",
    "sg:city":"Verbania",
    "sg:orig_category":"Elettrotecnica Industriale, Prodotti E Apparecchiature",
    "sg:phone":"+39 0323 585511",
    "sg:postcode":"28924",
    "sg:province":"Verbano-Cusio-Ossola",
    "sg:website":"http://www.co-ver.it",
    "wof:name":"Co-ver Energia Srl",
    "wof:placetype":"venue"
},
  "geometry": {"coordinates":[8.499645,45.943306],"type":"Point"}
}