{
  "type": "Feature",
  "properties": {
    "addr:full":"33100 Udine Udine Udine 33100",
    "addr:postcode":"33100;33100",
    "iso:country":"IT",
    "sg:address":"33100 Udine",
    "sg:city":"Udine",
    "sg:orig_category":"Impiantistica E Prodotti Tecnologici Per Edilizia. Elettronica Professionale E Di Consumo",
    "sg:phone":"+39 0432 481710",
    "sg:postcode":"33100",
    "sg:province":"Udine",
    "wof:name":"Cancelli Automatici Srl",
    "wof:placetype":"venue"
},
  "geometry": {"coordinates":[13.221447,46.072475],"type":"Point"}
}