{
  "type": "Feature",
  "properties": {
    "addr:full":"67051 Avezzano L'Aquila 67051",
    "addr:postcode":"67051;67051",
    "iso:country":"IT",
    "sg:address":"67051 Avezzano",
    "sg:orig_category":"Prodotti Alimentari",
    "sg:phone":"+39 0863 38226",
    "sg:postcode":"67051",
    "sg:province":"L'Aquila",
    "wof:name":"Biocca Sabatino",
    "wof:placetype":"venue"
},
  "geometry": {"coordinates":[13.4476833344,42.0411567688],"type":"Point"}
}