{
  "type": "Feature",
  "properties": {
    "addr:full":"Via Della Fangosa 16 50032 Borgo San Lorenzo Borgo San Lorenzo Firenze 50032",
    "addr:housenumber":"16",
    "addr:postcode":"50032;50032",
    "addr:street":"Via Della Fangosa;San Lorenzo Borgo San Lorenzo",
    "iso:country":"IT",
    "sg:address":"Via Della Fangosa 16 50032 Borgo San Lorenzo",
    "sg:city":"Borgo San Lorenzo",
    "sg:classifiers":[
        {
            "category":"Shopping",
            "subcategory":"Gifts & Souvenirs",
            "type":"Retail Goods"
        }
    ],
    "sg:phone":"+39 055 849 6225",
    "sg:postcode":"50032",
    "sg:province":"Firenze",
    "sg:tags":[
        "item"
    ],
    "wof:name":"Europromo Di Paoli Francesca E C. Sas",
    "wof:placetype":"venue"
},
  "geometry": {"coordinates":[11.387724,43.956951],"type":"Point"}
}