{
  "type": "Feature",
  "properties": {
    "iso:country":"IT",
    "sg:address":"22, Via Rossini 40055 Castenaso",
    "sg:city":"Castenaso",
    "sg:classifiers":[
        {
            "category":"Professional",
            "subcategory":"Engineering",
            "type":"Services"
        }
    ],
    "sg:phone":"+39 39051781727",
    "sg:postcode":"40055",
    "sg:province":"Bologna",
    "sg:tags":[
        "machine",
        "-",
        "mechanical"
    ],
    "wof:name":"Iceb Saldatrici (s.r.l.)",
    "wof:placetype":"venue"
},
  "geometry": {"coordinates":[11.439301,44.504726],"type":"Point"}
}