{
  "type": "Feature",
  "properties": {
    "iso:country":"IT",
    "sg:address":"00134 Roma",
    "sg:city":"Roma",
    "sg:orig_category":"Pescherie",
    "sg:phone":"+39 06 7135 6000",
    "sg:postcode":"00134",
    "sg:province":"Roma",
    "wof:name":"Masaniello Ii Srl",
    "wof:placetype":"venue"
},
  "geometry": {"coordinates":[12.5260591507,41.7944717407],"type":"Point"}
}