{
  "type": "Feature",
  "properties": {
    "iso:country":"IT",
    "sg:address":"20041 Agrate Brianza",
    "sg:city":"Agrate Brianza",
    "sg:orig_category":"Materiali Semilavorati Metallici. Materiali E Componenti Elettrotecnici",
    "sg:phone":"+39 039 689 8787",
    "sg:postcode":"20041",
    "sg:province":"Milano",
    "sg:website":"http://www.femag.it",
    "wof:name":"Femag Ferri Magnetici Srl",
    "wof:placetype":"venue"
},
  "geometry": {"coordinates":[9.329562,45.570065],"type":"Point"}
}