{
  "type": "Feature",
  "properties": {
    "iso:country":"IT",
    "sg:address":"09016 Iglesias",
    "sg:city":"Iglesias",
    "sg:orig_category":"Prodotti Chimici Di Base. Prodotti Cosmetici E Da Toeletta",
    "sg:phone":"+39 0781 22242",
    "sg:postcode":"09016",
    "sg:province":"Carbonia-Iglesias",
    "wof:name":"Profumeria =for You=",
    "wof:placetype":"venue"
},
  "geometry": {"coordinates":[8.6446752548,39.2768363953],"type":"Point"}
}