{
  "type": "Feature",
  "properties": {
    "iso:country":"IT",
    "sg:address":"Via Dei Bravi 40 20032 Cormano",
    "sg:city":"Cormano",
    "sg:classifiers":[
        {
            "category":"Shopping",
            "subcategory":"News",
            "type":"Retail Goods"
        }
    ],
    "sg:phone":"+39 02 614 0851",
    "sg:postcode":"20032",
    "sg:province":"Milano",
    "sg:tags":[
        "electromagnet"
    ],
    "sg:website":"www.rele.it",
    "wof:name":"Italiana Rele' Srl",
    "wof:placetype":"venue"
},
  "geometry": {"coordinates":[9.182899,45.538303],"type":"Point"}
}