{
  "type": "Feature",
  "properties": {
    "iso:country":"IT",
    "sg:address":"40043 Marzabotto",
    "sg:city":"Marzabotto",
    "sg:orig_category":"Forniture Per Abbigliamento E Pelletterie",
    "sg:phone":"+39 051 932837",
    "sg:postcode":"40043",
    "sg:province":"Bologna",
    "wof:name":"Tacchificio Monti S.r.l.",
    "wof:placetype":"venue"
},
  "geometry": {"coordinates":[11.1848611832,44.3277816772],"type":"Point"}
}