{
  "type": "Feature",
  "properties": {
    "iso:country":"IT",
    "sg:address":"25080 Prevalle",
    "sg:city":"Prevalle",
    "sg:orig_category":"Officine Meccaniche Di Precisione",
    "sg:phone":"+39 030 603691",
    "sg:postcode":"25080",
    "sg:province":"Brescia",
    "wof:name":"System Stampi Srl",
    "wof:placetype":"venue"
},
  "geometry": {"coordinates":[10.356246,45.501915],"type":"Point"}
}