{
  "type": "Feature",
  "properties": {
    "addr:full":"46030 Virgilio Virgilio Mantova 46030",
    "addr:postcode":"46030;46030",
    "iso:country":"IT",
    "sg:address":"46030 Virgilio",
    "sg:city":"Virgilio",
    "sg:orig_category":"Pizzerie",
    "sg:phone":"+39 0376 280871",
    "sg:postcode":"46030",
    "sg:province":"Mantova",
    "wof:name":"Ristorante Pizzeria La Colonna Di Vitello Ernesto & C. Snc",
    "wof:placetype":"venue"
},
  "geometry": {"coordinates":[10.8049468994,45.1170387268],"type":"Point"}
}