{
  "type": "Feature",
  "properties": {
    "iso:country":"IT",
    "sg:address":"4, V. Ettore Benini 47100 Forli",
    "sg:classifiers":[
        {
            "category":"Autos & Motor Vehicles",
            "subcategory":"Boat Sales",
            "type":"Retail Goods"
        }
    ],
    "sg:phone":"+39 39054384173",
    "sg:postcode":"47100",
    "sg:province":"Forl\u00ec-Cesena",
    "sg:website":"http://www.ccitaly.it:ws_end: :mark:ws:http://www.paginegialle.it/cccortesi",
    "wof:name":"Cc Cortesi E Casadei Srl",
    "wof:placetype":"venue"
},
  "geometry": {"coordinates":[12.012874,44.197208],"type":"Point"}
}