{
  "type": "Feature",
  "properties": {
    "iso:country":"IT",
    "sg:address":"7, Via Del Duca 46030 Serravalle A Po",
    "sg:city":"Serravalle a Po",
    "sg:classifiers":[
        {
            "category":"Shopping",
            "subcategory":"Computers & Home Electronics",
            "type":"Retail Goods"
        }
    ],
    "sg:phone":"+39 0386 840106",
    "sg:postcode":"46030",
    "sg:province":"Mantova",
    "sg:tags":[
        "electronic",
        "electrical",
        "equipment"
    ],
    "wof:name":"Nebeselettrom Snc Di Besitti & C",
    "wof:placetype":"venue"
},
  "geometry": {"coordinates":[11.080284,45.073162],"type":"Point"}
}