{
  "type": "Feature",
  "properties": {
    "addr:full":"90047 Partinico Partinico Palermo 90047",
    "addr:postcode":"90047;90047",
    "iso:country":"IT",
    "sg:address":"90047 Partinico",
    "sg:city":"Partinico",
    "sg:orig_category":"Impiantistica E Prodotti Tecnologici Per Edilizia. Climatizzazione E Condizionamento, Apparecchiature E Servizi",
    "sg:phone":"+39 091 878 3202",
    "sg:postcode":"90047",
    "sg:province":"Palermo",
    "wof:name":"Appresti Salvatore",
    "wof:placetype":"venue"
},
  "geometry": {"coordinates":[13.343388,38.131077],"type":"Point"}
}