{
  "type": "Feature",
  "properties": {
    "addr:full":"24, Via Matteotti 21051 Arcisate Arcisate Varese 21051",
    "addr:postcode":"21051;21051",
    "addr:street":"Via Matteotti",
    "iso:country":"IT",
    "sg:address":"24, Via Matteotti 21051 Arcisate",
    "sg:city":"Arcisate",
    "sg:classifiers":[
        {
            "category":"Shopping",
            "subcategory":"Clothing, Apparel, & Fashions",
            "type":"Retail Goods"
        }
    ],
    "sg:phone":"+39 0332 473752",
    "sg:postcode":"21051",
    "sg:province":"Varese",
    "sg:tags":[
        "clothes"
    ],
    "wof:name":"Gr.an.fur. S.n.c. Di Ancelliero & Grassi",
    "wof:placetype":"venue"
},
  "geometry": {"coordinates":[8.857622,45.85947],"type":"Point"}
}