{
  "type": "Feature",
  "properties": {
    "iso:country":"IT",
    "sg:address":"20049 Concorezzo",
    "sg:city":"Concorezzo",
    "sg:classifiers":[
        {
            "category":"Education",
            "subcategory":"Dance Studio",
            "type":"Public Place"
        }
    ],
    "sg:phone":"+39 02 9210 5872",
    "sg:postcode":"20049",
    "sg:province":"Milano",
    "sg:tags":[
        "pallet"
    ],
    "wof:name":"Mondial Pallets Di Grosso Domenico",
    "wof:placetype":"venue"
},
  "geometry": {"coordinates":[9.3313503265,45.5865478516],"type":"Point"}
}