{
  "type": "Feature",
  "properties": {
    "iso:country":"IT",
    "sg:address":"5, Via Degli Artigiani 46040 Casalmoro",
    "sg:city":"Casalmoro",
    "sg:classifiers":[
        {
            "category":"Shopping",
            "subcategory":"Clothing, Apparel, & Fashions",
            "type":"Retail Goods"
        }
    ],
    "sg:phone":"+39 0376 737161",
    "sg:postcode":"46040",
    "sg:province":"Mantova",
    "sg:tags":[
        "clothes"
    ],
    "wof:name":"Mantova I.t.c. S.r.l.",
    "wof:placetype":"venue"
},
  "geometry": {"coordinates":[10.417248,45.256409],"type":"Point"}
}