{
  "type": "Feature",
  "properties": {
    "iso:country":"IT",
    "sg:address":"39040 Termeno Sulla Strada Del Vino",
    "sg:city":"Termeno sulla strada del vino",
    "sg:orig_category":"Minuterie Metalliche E Ferramenta",
    "sg:phone":"+39 0471 860631",
    "sg:postcode":"39040",
    "sg:province":"Bolzano/Bozen",
    "sg:website":"http://www.bertol.com",
    "wof:name":"Bertol Reinhold",
    "wof:placetype":"venue"
},
  "geometry": {"coordinates":[11.2436275482,46.3426513672],"type":"Point"}
}