{
  "type": "Feature",
  "properties": {
    "iso:country":"IT",
    "sg:address":"22100 Como",
    "sg:city":"Como",
    "sg:orig_category":"Nautica. Ricambi E Componenti Dei Mezzi Di Trasporto",
    "sg:phone":"+39 031 267505",
    "sg:postcode":"22100",
    "sg:province":"Como",
    "wof:name":"Conti Moto Srl",
    "wof:placetype":"venue"
},
  "geometry": {"coordinates":[9.087973,45.797699],"type":"Point"}
}