{
  "type": "Feature",
  "properties": {
    "addr:full":"20063 Cernusco Sul Naviglio Cernusco sul Naviglio Milano 20063",
    "addr:postcode":"20063;20063",
    "iso:country":"IT",
    "sg:address":"20063 Cernusco Sul Naviglio",
    "sg:city":"Cernusco sul Naviglio",
    "sg:orig_category":"Servizi E Lavori Per Edilizia E Lavori Pubblici",
    "sg:phone":"+39 02 924 2036",
    "sg:postcode":"20063",
    "sg:province":"Milano",
    "wof:name":"Colombo Ezio & C.",
    "wof:placetype":"venue"
},
  "geometry": {"coordinates":[9.336107,45.537239],"type":"Point"}
}