{
  "type": "Feature",
  "properties": {
    "iso:country":"IT",
    "sg:address":"41031 Camposanto",
    "sg:city":"Camposanto",
    "sg:orig_category":"Forniture Per Attivita' Commerciali Ed Artigianali. Pubblicita', Marketing E Comunicazione",
    "sg:phone":"+39 0535 88205",
    "sg:postcode":"41031",
    "sg:province":"Modena",
    "wof:name":"Espo Service Srl",
    "wof:placetype":"venue"
},
  "geometry": {"coordinates":[11.1490058899,44.7879066467],"type":"Point"}
}