{
  "type": "Feature",
  "properties": {
    "iso:country":"IT",
    "sg:address":"17, Via T. Edison 42049 Sant'ilario D'enza",
    "sg:classifiers":[
        {
            "category":"Utilities",
            "subcategory":"Electric",
            "type":"Services"
        }
    ],
    "sg:phone":"+39 0522 904011",
    "sg:postcode":"42049",
    "sg:province":"Reggio Nell'Emilia",
    "sg:tags":[
        "component",
        "electronic"
    ],
    "wof:name":"Unielectric S.p.a.",
    "wof:placetype":"venue"
},
  "geometry": {"coordinates":[10.477637,44.75539],"type":"Point"}
}