{
  "type": "Feature",
  "properties": {
    "iso:country":"IT",
    "sg:address":"60127 Ancona",
    "sg:city":"Ancona",
    "sg:orig_category":"Servizi E Lavori Per Edilizia E Lavori Pubblici. Telecomunicazioni E Telefonia, Impianti, Apparecchi E Servizi. Acqua, Luce, Gas E Societa' Di Esercizio Pubblico",
    "sg:phone":"+39 071 207 2475",
    "sg:postcode":"60127",
    "sg:province":"Ancona",
    "sg:website":"http://www.paginegialle.it/choicetlc",
    "wof:name":"Choice Di Sesta Giovanni & C. Sas",
    "wof:placetype":"venue"
},
  "geometry": {"coordinates":[13.507443,43.594421],"type":"Point"}
}