{
  "type": "Feature",
  "properties": {
    "iso:country":"IT",
    "sg:address":"20099 Sesto San Giovanni",
    "sg:city":"Sesto San Giovanni",
    "sg:orig_category":"Riparazione Dei Mezzi Di Trasporto. Servizi Ausiliari Dei Mezzi Di Trasporto",
    "sg:phone":"+39 02 2622 2146",
    "sg:postcode":"20099",
    "sg:province":"Milano",
    "sg:website":"http://www.cpsrevisioni.it",
    "wof:name":"C.p.s. Di Calzolari Franco",
    "wof:placetype":"venue"
},
  "geometry": {"coordinates":[9.25572,45.52858],"type":"Point"}
}