{
  "type": "Feature",
  "properties": {
    "iso:country":"IT",
    "sg:address":"20093 Cologno Monzese",
    "sg:city":"Cologno Monzese",
    "sg:orig_category":"Motori Ed Organi Di Trasmissione. Ricambi E Componenti Dei Mezzi Di Trasporto",
    "sg:phone":"+39 02 2670 8077",
    "sg:postcode":"20093",
    "sg:province":"Milano",
    "wof:name":"Fait International Milano Srl",
    "wof:placetype":"venue"
},
  "geometry": {"coordinates":[9.2639570236,45.5186424255],"type":"Point"}
}