{
  "type": "Feature",
  "properties": {
    "iso:country":"IT",
    "sg:address":"24016 San Pellegrino Terme",
    "sg:city":"San Pellegrino Terme",
    "sg:orig_category":"Acciaierie E Fonderie",
    "sg:phone":"+39 0345 21340",
    "sg:postcode":"24016",
    "sg:province":"Bergamo",
    "wof:name":"Societa' Nordelettrica Sondel (s.p.a.)",
    "wof:placetype":"venue"
},
  "geometry": {"coordinates":[9.670885,45.825974],"type":"Point"}
}