{
  "type": "Feature",
  "properties": {
    "addr:full":"28100 Novara Novara Novara 28100",
    "addr:postcode":"28100;28100",
    "iso:country":"IT",
    "sg:address":"28100 Novara",
    "sg:city":"Novara",
    "sg:orig_category":"Non-classified Establishments",
    "sg:phone":"+39 0321 477107",
    "sg:postcode":"28100",
    "sg:province":"Novara",
    "wof:name":"Toys Center",
    "wof:placetype":"venue"
},
  "geometry": {"coordinates":[8.623774,45.456528],"type":"Point"}
}