{
  "type": "Feature",
  "properties": {
    "addr:full":"80040 Terzigno Terzigno Napoli 80040",
    "addr:postcode":"80040;80040",
    "iso:country":"IT",
    "sg:address":"80040 Terzigno",
    "sg:city":"Terzigno",
    "sg:orig_category":"Abbigliamento Esterno, Maglierie E Pelliccerie",
    "sg:phone":"+39 081 529 7459",
    "sg:postcode":"80040",
    "sg:province":"Napoli",
    "wof:name":"T.jeans Group Srl",
    "wof:placetype":"venue"
},
  "geometry": {"coordinates":[14.485546,40.813847],"type":"Point"}
}