{
  "type": "Feature",
  "properties": {
    "iso:country":"IT",
    "sg:address":"50127 Firenze",
    "sg:city":"Firenze",
    "sg:orig_category":"Servizi Editoriali. Pubblicita', Marketing E Comunicazione",
    "sg:phone":"+39 055 428 9922",
    "sg:postcode":"50127",
    "sg:province":"Firenze",
    "sg:website":"http://www.kidstudio.it",
    "wof:name":"Kidstudio Communications Snc",
    "wof:placetype":"venue"
},
  "geometry": {"coordinates":[11.21629,43.712009],"type":"Point"}
}