{
  "type": "Feature",
  "properties": {
    "iso:country":"IT",
    "sg:address":"50032 Borgo San Lorenzo",
    "sg:city":"Borgo San Lorenzo",
    "sg:orig_category":"Arredo Urbano",
    "sg:phone":"+39 055 845 6648",
    "sg:postcode":"50032",
    "sg:province":"Firenze",
    "wof:name":"Svitavvita Snc",
    "wof:placetype":"venue"
},
  "geometry": {"coordinates":[11.367324,43.960384],"type":"Point"}
}