{
  "type": "Feature",
  "properties": {
    "iso:country":"IT",
    "sg:address":"2, Via Al Confine 23823 Colico",
    "sg:city":"Colico",
    "sg:classifiers":[
        {
            "category":"Airport",
            "subcategory":"General Aviation",
            "type":"Transportation"
        }
    ],
    "sg:phone":"+39 0341 940126",
    "sg:postcode":"23823",
    "sg:province":"Lecco",
    "sg:tags":[
        "transport",
        "air"
    ],
    "wof:name":"Elilario Italia Spa",
    "wof:placetype":"venue"
},
  "geometry": {"coordinates":[9.395745,46.139572],"type":"Point"}
}