{
  "type": "Feature",
  "properties": {
    "iso:country":"IT",
    "sg:address":"66100 San Giovanni Teatino",
    "sg:classifiers":[
        {
            "category":"Banks & Credit Unions",
            "subcategory":"Bank",
            "type":"Services"
        }
    ],
    "sg:phone":"+39 085 446 0159",
    "sg:postcode":"66100",
    "sg:province":"Chieti",
    "sg:tags":[
        "plating",
        "industry",
        "treatments",
        "surface",
        "chemical",
        "heat",
        "electroforming",
        "metals",
        "works"
    ],
    "sg:website":"http://www.ivc.it",
    "wof:name":"I.v.c. Industria Vernici Colori Srl",
    "wof:placetype":"venue"
},
  "geometry": {"coordinates":[14.1692867279,42.4209213257],"type":"Point"}
}