{
  "type": "Feature",
  "properties": {
    "iso:country":"IT",
    "sg:address":"20092 Cinisello Balsamo",
    "sg:city":"Cinisello Balsamo",
    "sg:orig_category":"Materiali E Componenti Elettronici",
    "sg:phone":"+39 02 249 1121",
    "sg:postcode":"20092",
    "sg:province":"Milano",
    "wof:name":"Intersil S.r.l.",
    "wof:placetype":"venue"
},
  "geometry": {"coordinates":[9.215252,45.531631],"type":"Point"}
}