{
  "type": "Feature",
  "properties": {
    "iso:country":"IT",
    "sg:address":"70022 Altamura",
    "sg:city":"Altamura",
    "sg:orig_category":"Arredamenti - Vendita Al Dettaglio",
    "sg:phone":"+39 080 314 0412",
    "sg:postcode":"70022",
    "sg:province":"Bari",
    "sg:website":"http://www.mobilfirma.com",
    "wof:name":"Mobilfirma Del Rag. Tucci Michele",
    "wof:placetype":"venue"
},
  "geometry": {"coordinates":[16.679054,41.182575],"type":"Point"}
}