{
  "type": "Feature",
  "properties": {
    "iso:country":"IT",
    "sg:address":"10072 Caselle Torinese",
    "sg:city":"Caselle Torinese",
    "sg:orig_category":"Trattamenti Termici E Superficiali Metalli, Galvanotecnica",
    "sg:phone":"+39 011 996 9111",
    "sg:postcode":"10072",
    "sg:province":"Torino",
    "wof:name":"S.m.v. Srl",
    "wof:placetype":"venue"
},
  "geometry": {"coordinates":[7.650923,45.184231],"type":"Point"}
}