{
  "type": "Feature",
  "properties": {
    "iso:country":"IT",
    "sg:address":"39, Via Monte Pasubio 36051 Creazzo",
    "sg:city":"Creazzo",
    "sg:classifiers":[
        {
            "category":"Wholesale",
            "subcategory":"Drugs",
            "type":"Manufacturing & Wholesale Goods"
        }
    ],
    "sg:phone":"+39 0444 340530",
    "sg:postcode":"36051",
    "sg:province":"Vicenza",
    "sg:tags":[
        "chemical",
        "pharmaceutical"
    ],
    "wof:name":"Solda' Vladimiro (s.p.a.)",
    "wof:placetype":"venue"
},
  "geometry": {"coordinates":[11.546955,45.562199],"type":"Point"}
}