{
  "type": "Feature",
  "properties": {
    "iso:country":"IT",
    "sg:address":"25014 Castenedolo",
    "sg:city":"Castenedolo",
    "sg:orig_category":"Metalli E Leghe",
    "sg:phone":"+39 030 273 2044",
    "sg:postcode":"25014",
    "sg:province":"Brescia",
    "sg:website":"http://www.lombardaacciai.it",
    "wof:name":"Lombarda Acciai",
    "wof:placetype":"venue"
},
  "geometry": {"coordinates":[10.2830209732,45.4782714844],"type":"Point"}
}