{
  "type": "Feature",
  "properties": {
    "iso:country":"IT",
    "sg:address":"38030 Rover\u00e8 Della Luna",
    "sg:orig_category":"Studi E Consulenze Tecniche E Industriali. Servizi E Lavori Per Edilizia E Lavori Pubblici. Professionisti - Studi E Servizi Ed Associazioni Di Interesse Aziendale",
    "sg:phone":"+39 0461 658604",
    "sg:postcode":"38030",
    "sg:province":"Trento",
    "wof:name":"Ferrari Geom. Antonio",
    "wof:placetype":"venue"
},
  "geometry": {"coordinates":[11.168893,46.249088],"type":"Point"}
}