{
  "type": "Feature",
  "properties": {
    "iso:country":"IT",
    "sg:address":"20089 Rozzano",
    "sg:city":"Rozzano",
    "sg:orig_category":"Motori Ed Organi Di Trasmissione",
    "sg:phone":"+39 02 5750 1557",
    "sg:postcode":"20089",
    "sg:province":"Milano",
    "sg:website":"http://www.nuovacoi.it",
    "wof:name":"Nuova Coi Srl",
    "wof:placetype":"venue"
},
  "geometry": {"coordinates":[9.1689214706,45.3779792786],"type":"Point"}
}