{
  "type": "Feature",
  "properties": {
    "addr:full":"11, Via Dell' Artigianato 33042 Buttrio Buttrio Udine 33042",
    "addr:postcode":"33042;33042",
    "addr:street":"Via Dell ' Artigianato",
    "iso:country":"IT",
    "sg:address":"11, Via Dell' Artigianato 33042 Buttrio",
    "sg:city":"Buttrio",
    "sg:classifiers":[
        {
            "category":"Professional",
            "subcategory":"Engineering",
            "type":"Services"
        }
    ],
    "sg:phone":"+39 0432 674168",
    "sg:postcode":"33042",
    "sg:province":"Udine",
    "sg:tags":[
        "machine",
        "-",
        "mechanical"
    ],
    "wof:name":"Euro.co.met. S.r.l. - Tonello",
    "wof:placetype":"venue"
},
  "geometry": {"coordinates":[13.321419,46.010235],"type":"Point"}
}