{
  "type": "Feature",
  "properties": {
    "iso:country":"IT",
    "sg:address":"10090 San Raffaele Cimena",
    "sg:city":"San Raffaele Cimena",
    "sg:orig_category":"Macchine E Forniture Per Arredamento E Industria Del Legno. Utensili Meccanici E Materiali",
    "sg:phone":"+39 011 981 1390",
    "sg:postcode":"10090",
    "sg:province":"Torino",
    "wof:name":"Olivotto Di Olivotto E. E P. E Sorrentino (s.n.c.)",
    "wof:placetype":"venue"
},
  "geometry": {"coordinates":[7.850482,45.147667],"type":"Point"}
}