{
  "type": "Feature",
  "properties": {
    "iso:country":"IT",
    "sg:address":"20098 San Giuliano Milanese",
    "sg:city":"San Giuliano Milanese",
    "sg:orig_category":"Ricerca, Selezione E Formazione Del Personale",
    "sg:phone":"+39 02 984 3326",
    "sg:postcode":"20098",
    "sg:province":"Milano",
    "wof:name":"Adecco Societa' Di Fornitura Di Lavoro Temporaneo Spa",
    "wof:placetype":"venue"
},
  "geometry": {"coordinates":[9.282633,45.426254],"type":"Point"}
}