{
  "type": "Feature",
  "properties": {
    "iso:country":"IT",
    "sg:address":"60128 Ancona",
    "sg:city":"Ancona",
    "sg:orig_category":"Editing - Agenzie E Studi",
    "sg:phone":"+39 071 283 2011",
    "sg:postcode":"60128",
    "sg:province":"Ancona",
    "wof:name":"Cube3 Digital Design",
    "wof:placetype":"venue"
},
  "geometry": {"coordinates":[13.116407,43.446888],"type":"Point"}
}