{
  "type": "Feature",
  "properties": {
    "iso:country":"IT",
    "sg:address":"22039 Valbrona",
    "sg:city":"Valbrona",
    "sg:orig_category":"Ferramenta - Produzione",
    "sg:phone":"+39 031 660164",
    "sg:postcode":"22039",
    "sg:province":"Como",
    "wof:name":"Fasoli Riccardo Di Fasoli F. & G. Snc",
    "wof:placetype":"venue"
},
  "geometry": {"coordinates":[9.2877368927,45.8703651428],"type":"Point"}
}