{
  "type": "Feature",
  "properties": {
    "iso:country":"IT",
    "sg:address":"14, Via Dell' Artigianato 06083 Bastia",
    "sg:city":"Bastia",
    "sg:classifiers":[
        {
            "category":"Manufacturing",
            "subcategory":"Paper Products",
            "type":"Manufacturing & Wholesale Goods"
        }
    ],
    "sg:phone":"+39 075 800 0824",
    "sg:postcode":"06083",
    "sg:province":"Perugia",
    "sg:tags":[
        "cardboard"
    ],
    "wof:name":"Irm - Italy S.r.l.",
    "wof:placetype":"venue"
},
  "geometry": {"coordinates":[12.5423383713,43.0579414368],"type":"Point"}
}