{
  "type": "Feature",
  "properties": {
    "iso:country":"IT",
    "sg:address":"31, Via Pascoli 31053 Pieve Di Soligo",
    "sg:city":"Pieve di Soligo",
    "sg:classifiers":[
        {
            "category":"Home & Garden",
            "subcategory":"Home Furnishings",
            "type":"Retail Goods"
        }
    ],
    "sg:phone":"+39 39043882928",
    "sg:postcode":"31053",
    "sg:province":"Treviso",
    "sg:tags":[
        "household"
    ],
    "wof:name":"Mobilificio Alba Srl",
    "wof:placetype":"venue"
},
  "geometry": {"coordinates":[12.242072,45.666286],"type":"Point"}
}