{
  "type": "Feature",
  "properties": {
    "addr:full":"59100 Prato Prato Prato 59100",
    "addr:postcode":"59100;59100",
    "iso:country":"IT",
    "sg:address":"59100 Prato",
    "sg:city":"Prato",
    "sg:orig_category":"Filati E Materie Prime Tessili",
    "sg:phone":"+39 0574 624960",
    "sg:postcode":"59100",
    "sg:province":"Prato",
    "wof:name":"Manifattura Filati 3 C Srl",
    "wof:placetype":"venue"
},
  "geometry": {"coordinates":[11.0516138077,43.8616600037],"type":"Point"}
}