{
  "type": "Feature",
  "properties": {
    "iso:country":"IT",
    "sg:address":"38027 Male'",
    "sg:orig_category":"Prodotti Alimentari",
    "sg:phone":"+39 0463 901325",
    "sg:postcode":"38027",
    "sg:province":"Trento",
    "wof:name":"Famiglia Cooperativa Di Male'",
    "wof:placetype":"venue"
},
  "geometry": {"coordinates":[10.9139070511,46.3525009155],"type":"Point"}
}