{
  "type": "Feature",
  "properties": {
    "addr:full":"20095 Cusano Milanino Cusano Milanino Milano 20095",
    "addr:postcode":"20095;20095",
    "iso:country":"IT",
    "sg:address":"20095 Cusano Milanino",
    "sg:city":"Cusano Milanino",
    "sg:orig_category":"Lavorazioni Metalli, Stampaggio E Saldatura",
    "sg:phone":"+39 02 619 6287",
    "sg:postcode":"20095",
    "sg:province":"Milano",
    "wof:name":"Bregoli Maurizio",
    "wof:placetype":"venue"
},
  "geometry": {"coordinates":[9.181405,45.549694],"type":"Point"}
}