{
  "type": "Feature",
  "properties": {
    "iso:country":"IT",
    "sg:address":"25050 Paderno Franciacorta",
    "sg:city":"Paderno Franciacorta",
    "sg:orig_category":"Antinfortunistica - Attrezzature Ed Articoli",
    "sg:phone":"+39 030 685 7565",
    "sg:postcode":"25050",
    "sg:province":"Brescia",
    "sg:website":"http://www.cittadini.it",
    "wof:name":"Cittadini Spa",
    "wof:placetype":"venue"
},
  "geometry": {"coordinates":[10.089183,45.577343],"type":"Point"}
}