{
  "type": "Feature",
  "properties": {
    "iso:country":"IT",
    "sg:address":"18, Via Graffignana 22074 Lomazzo",
    "sg:city":"Lomazzo",
    "sg:classifiers":[
        {
            "category":"Shopping",
            "subcategory":"Crafts & Fabrics",
            "type":"Retail Goods"
        }
    ],
    "sg:phone":"+39 02 9677 9280",
    "sg:postcode":"22074",
    "sg:province":"Como",
    "wof:name":"Tessitura Serica Caslino (s.n.c.)",
    "wof:placetype":"venue"
},
  "geometry": {"coordinates":[9.0344562531,45.7016487122],"type":"Point"}
}