{
  "type": "Feature",
  "properties": {
    "addr:full":"29, V. Trebbia - Zona Industriale Ponte Trebbia 29010 Calendasco Calendasco Piacenza 29010",
    "addr:housenumber":"29",
    "addr:postcode":"29010;29010",
    "addr:street":"V. Trebbia Zona Industriale Ponte Trebbia",
    "iso:country":"IT",
    "sg:address":"29, V. Trebbia - Zona Industriale Ponte Trebbia 29010 Calendasco",
    "sg:city":"Calendasco",
    "sg:classifiers":[
        {
            "category":"Manufacturing",
            "subcategory":"Metals",
            "type":"Manufacturing & Wholesale Goods"
        }
    ],
    "sg:phone":"+39 0523 761811",
    "sg:postcode":"29010",
    "sg:province":"Piacenza",
    "sg:tags":[
        "metallurgy",
        "metalworking"
    ],
    "sg:website":"http://www.petrolraccord.com",
    "wof:name":"Petrol Raccord Spa",
    "wof:placetype":"venue"
},
  "geometry": {"coordinates":[9.6951417923,45.0537719727],"type":"Point"}
}