{
  "type": "Feature",
  "properties": {
    "iso:country":"IT",
    "sg:address":"7, Via Sestriere 10060 Candiolo",
    "sg:city":"Candiolo",
    "sg:classifiers":[
        {
            "category":"Manufacturing",
            "subcategory":"Glass & Minerals",
            "type":"Manufacturing & Wholesale Goods"
        }
    ],
    "sg:phone":"+39 011 962 1221",
    "sg:postcode":"10060",
    "sg:province":"Torino",
    "wof:name":"Soffieria Bertolini (s.p.a.)",
    "wof:placetype":"venue"
},
  "geometry": {"coordinates":[7.623423,44.975182],"type":"Point"}
}