{
  "type": "Feature",
  "properties": {
    "iso:country":"IT",
    "sg:address":"84017 Positano",
    "sg:city":"Positano",
    "sg:classifiers":[
        {
            "category":"Shopping",
            "subcategory":"Clothing, Apparel, & Fashions",
            "type":"Retail Goods"
        }
    ],
    "sg:phone":"+39 089 875919",
    "sg:postcode":"84017",
    "sg:province":"Salerno",
    "sg:tags":[
        "clothing",
        "fur",
        "knitwear"
    ],
    "wof:name":"La Collinetta",
    "wof:placetype":"venue"
},
  "geometry": {"coordinates":[14.4898,40.638832],"type":"Point"}
}