{
  "type": "Feature",
  "properties": {
    "iso:country":"IT",
    "sg:address":"4/6, Via Mariunda 22029 Uggiate Trevano",
    "sg:classifiers":[
        {
            "category":"Shopping",
            "subcategory":"Crafts & Fabrics",
            "type":"Retail Goods"
        }
    ],
    "sg:phone":"+39 39031948948",
    "sg:postcode":"22029",
    "sg:province":"Como",
    "wof:name":"Stamperia Iride (s.r.l.)",
    "wof:placetype":"venue"
},
  "geometry": {"coordinates":[8.9690170288,45.8200721741],"type":"Point"}
}