{
  "type": "Feature",
  "properties": {
    "iso:country":"IT",
    "sg:address":"15, Via Gagini 98122 Messina",
    "sg:city":"Messina",
    "sg:classifiers":[
        {
            "category":"Real Estate",
            "subcategory":"Architect",
            "type":"Services"
        }
    ],
    "sg:phone":"+39 390 905 9080",
    "sg:postcode":"98122",
    "sg:province":"Messina",
    "sg:tags":[
        "textile",
        "clothing"
    ],
    "wof:name":"Margan S.r.l.",
    "wof:placetype":"venue"
},
  "geometry": {"coordinates":[15.551015,38.198853],"type":"Point"}
}