{
  "type": "Feature",
  "properties": {
    "addr:full":"28060 S. Pietro Mosezzo Novara 28060",
    "addr:housenumber":"28060",
    "addr:postcode":"28060",
    "addr:street":"S. Pietro Mosezzo",
    "iso:country":"IT",
    "sg:address":"28060 S. Pietro Mosezzo",
    "sg:orig_category":"Abiti Da Sposa E Cerimonia",
    "sg:phone":"+39 0321 468815",
    "sg:postcode":"28060",
    "sg:province":"Novara",
    "wof:name":"Joy Machines Di Elena Della Fornace",
    "wof:placetype":"venue"
},
  "geometry": {"coordinates":[8.570656,45.450188],"type":"Point"}
}