{
  "type": "Feature",
  "properties": {
    "addr:full":"13900 Biella Biella Biella 13900",
    "addr:postcode":"13900;13900",
    "iso:country":"IT",
    "sg:address":"13900 Biella",
    "sg:city":"Biella",
    "sg:orig_category":"Servizi E Lavori Per Arredamento E Industria Del Legno",
    "sg:phone":"+39 015 32355",
    "sg:postcode":"13900",
    "sg:province":"Biella",
    "wof:name":"Prato Fortunato Legnami Srl",
    "wof:placetype":"venue"
},
  "geometry": {"coordinates":[8.083987,45.567131],"type":"Point"}
}