{
  "type": "Feature",
  "properties": {
    "addr:full":"00010 Roma Roma 00010",
    "addr:postcode":"00010;00010",
    "iso:country":"IT",
    "sg:address":"00010 Roma",
    "sg:orig_category":"Materiali Semilavorati Metallici",
    "sg:phone":"+39 06 2248 4443",
    "sg:postcode":"00010",
    "sg:province":"Roma",
    "wof:name":"F.lli Abate Snc",
    "wof:placetype":"venue"
},
  "geometry": {"coordinates":[12.700839,41.891209],"type":"Point"}
}