{
  "type": "Feature",
  "properties": {
    "addr:full":"20143 Milano Milano Milano 20143",
    "addr:postcode":"20143;20143",
    "iso:country":"IT",
    "sg:address":"20143 Milano",
    "sg:city":"Milano",
    "sg:orig_category":"Servizi E Lavori Per Ecologia E Smaltimento Rifiuti. Servizi Ausiliari Di Analisi, Controllo E Ricerca",
    "sg:phone":"+39 02 813 4784",
    "sg:postcode":"20143",
    "sg:province":"Milano",
    "wof:name":"Tecni.u.m. Sas",
    "wof:placetype":"venue"
},
  "geometry": {"coordinates":[9.148488,45.442276],"type":"Point"}
}