{
  "type": "Feature",
  "properties": {
    "addr:full":"22029 Uggiate Trevano Como 22029",
    "addr:postcode":"22029;22029",
    "addr:street":"Trevano",
    "iso:country":"IT",
    "sg:address":"22029 Uggiate Trevano",
    "sg:orig_category":"Abbigliamento - Vendita Al Dettaglio",
    "sg:phone":"+39 031 809420",
    "sg:postcode":"22029",
    "sg:province":"Como",
    "wof:name":"Thema Sport Di Zambello Eleonora & C. Snc",
    "wof:placetype":"venue"
},
  "geometry": {"coordinates":[9.00318,45.800556],"type":"Point"}
}