{
  "type": "Feature",
  "properties": {
    "iso:country":"IT",
    "sg:address":"2, Via I Maggio 10043 Orbassano",
    "sg:city":"Orbassano",
    "sg:classifiers":[
        {
            "category":"Communications",
            "subcategory":"Television Station",
            "type":"Services"
        }
    ],
    "sg:phone":"+39 011 903 6611",
    "sg:postcode":"10043",
    "sg:province":"Torino",
    "sg:tags":[
        "audio-visual"
    ],
    "wof:name":"Simpesfaip S.p.a.",
    "wof:placetype":"venue"
},
  "geometry": {"coordinates":[7.580275,45.031719],"type":"Point"}
}