{
  "type": "Feature",
  "properties": {
    "iso:country":"IT",
    "sg:address":"20122 Milano",
    "sg:city":"Milano",
    "sg:classifiers":[
        {
            "category":"Health Services",
            "subcategory":"Health Practitioner",
            "type":"Services"
        }
    ],
    "sg:phone":"+39 02 7600 8573",
    "sg:postcode":"20122",
    "sg:province":"Milano",
    "sg:tags":[
        "medici"
    ],
    "wof:name":"Ars Medica Poliambulatorio Sas Di Paduano Guido E C.",
    "wof:placetype":"venue"
},
  "geometry": {"coordinates":[9.198661,45.466408],"type":"Point"}
}