{
  "type": "Feature",
  "properties": {
    "iso:country":"IT",
    "sg:address":"20146 Milano",
    "sg:city":"Milano",
    "sg:orig_category":"Servizi Ausiliari Dei Mezzi Di Trasporto",
    "sg:phone":"+39 02 422 2038",
    "sg:postcode":"20146",
    "sg:province":"Milano",
    "wof:name":"Fiorino Giovanni",
    "wof:placetype":"venue"
},
  "geometry": {"coordinates":[9.149716,45.454128],"type":"Point"}
}