{
  "type": "Feature",
  "properties": {
    "iso:country":"IT",
    "sg:address":"Via La Marmora 42; S. Remo; 18038",
    "sg:classifiers":[
        {
            "category":"Banks & Credit Unions",
            "subcategory":"Bank",
            "type":"Services"
        }
    ],
    "sg:phone":"+39 0184 575150",
    "sg:postcode":"18038",
    "sg:province":"Imperia",
    "wof:name":"Istituto Bancario, San Paolo Di Torino Spa",
    "wof:placetype":"venue"
},
  "geometry": {"coordinates":[7.79535,43.825439],"type":"Point"}
}