{
  "type": "Feature",
  "properties": {
    "iso:country":"IT",
    "sg:address":"63, Via Angeloni Mario 06124 Perugia",
    "sg:city":"Perugia",
    "sg:classifiers":[
        {
            "category":"Farming",
            "subcategory":"Livestock Farm",
            "type":"Manufacturing & Wholesale Goods"
        }
    ],
    "sg:phone":"+39 390 755 0311",
    "sg:postcode":"06124",
    "sg:province":"Perugia",
    "sg:tags":[
        "agriculture"
    ],
    "wof:name":"A.r.u.s.i.a.",
    "wof:placetype":"venue"
},
  "geometry": {"coordinates":[12.378339,43.104813],"type":"Point"}
}