{
  "type": "Feature",
  "properties": {
    "iso:country":"IT",
    "sg:address":"51031 Agliana",
    "sg:city":"Agliana",
    "sg:orig_category":"Biancheria Intima Ed Abbigliamento Intimo - Vendita Al Dettaglio",
    "sg:phone":"+39 0574 718829",
    "sg:postcode":"51031",
    "sg:province":"Pistoia",
    "wof:name":"Ra.ga. Snc",
    "wof:placetype":"venue"
},
  "geometry": {"coordinates":[10.995214,43.901562],"type":"Point"}
}