{
  "type": "Feature",
  "properties": {
    "iso:country":"IT",
    "sg:address":"66034 Lanciano",
    "sg:city":"Lanciano",
    "sg:classifiers":[
        {
            "category":"Health Services",
            "subcategory":"Health Practitioner",
            "type":"Services"
        }
    ],
    "sg:phone":"+39 0872 713779",
    "sg:postcode":"66034",
    "sg:province":"Chieti",
    "sg:tags":[
        "medici"
    ],
    "wof:name":"Fanci Urbano",
    "wof:placetype":"venue"
},
  "geometry": {"coordinates":[14.396766,42.230885],"type":"Point"}
}