{
  "type": "Feature",
  "properties": {
    "addr:full":"20154 Milano Milano Milano 20154",
    "addr:postcode":"20154;20154",
    "iso:country":"IT",
    "sg:address":"20154 Milano",
    "sg:city":"Milano",
    "sg:orig_category":"Professionisti - Studi E Servizi Ed Associazioni Di Interesse Aziendale. Associazioni Ed Organismi Di Interesse Pubblico",
    "sg:phone":"+39 02 349 4785",
    "sg:postcode":"20154",
    "sg:province":"Milano",
    "wof:name":"Associazione Diabetici Della Provincia Di Milano",
    "wof:placetype":"venue"
},
  "geometry": {"coordinates":[9.1663732529,45.4860496521],"type":"Point"}
}