{
  "type": "Feature",
  "properties": {
    "addr:full":"3, Via Mischi G. 29017 Fiorenzuola D'arda Piacenza 29017",
    "addr:postcode":"29017;29017",
    "addr:street":"Via Mischi G.",
    "iso:country":"IT",
    "sg:address":"3, Via Mischi G. 29017 Fiorenzuola D'arda",
    "sg:classifiers":[
        {
            "category":"Farming",
            "subcategory":"Livestock Farm",
            "type":"Manufacturing & Wholesale Goods"
        }
    ],
    "sg:phone":"+39 0523 985711",
    "sg:postcode":"29017",
    "sg:province":"Piacenza",
    "sg:tags":[
        "agriculture"
    ],
    "wof:name":"Consorzio Bacini Piacentini Di Levante",
    "wof:placetype":"venue"
},
  "geometry": {"coordinates":[9.695142,45.053772],"type":"Point"}
}