{
  "type": "Feature",
  "properties": {
    "addr:full":"22/a, Vico Panettieri 80138 Napoli Napoli Napoli 80138",
    "addr:housenumber":"22 / a",
    "addr:postcode":"80138;80138",
    "addr:street":"Vico Panettieri",
    "iso:country":"IT",
    "sg:address":"22/a, Vico Panettieri 80138 Napoli",
    "sg:city":"Napoli",
    "sg:classifiers":[
        {
            "category":"Home & Garden",
            "subcategory":"Home Furnishings",
            "type":"Retail Goods"
        }
    ],
    "sg:phone":"+39 39081266048",
    "sg:postcode":"80138",
    "sg:province":"Napoli",
    "sg:tags":[
        "household"
    ],
    "wof:name":"Icor Sas",
    "wof:placetype":"venue"
},
  "geometry": {"coordinates":[14.251636,40.840096],"type":"Point"}
}