{
  "type": "Feature",
  "properties": {
    "addr:full":"26, Via Poirino 14019 Villanova D'asti Asti 14019",
    "addr:postcode":"14019;14019",
    "addr:street":"Via Poirino",
    "iso:country":"IT",
    "sg:address":"26, Via Poirino 14019 Villanova D'asti",
    "sg:classifiers":[
        {
            "category":"Wholesale",
            "subcategory":"Machinery & Supplies",
            "type":"Manufacturing & Wholesale Goods"
        }
    ],
    "sg:phone":"+39 0141 946527",
    "sg:postcode":"14019",
    "sg:province":"Asti",
    "sg:tags":[
        "-",
        "agriculture",
        "equipment"
    ],
    "wof:name":"Meritano Sas Di Meritano Bruno & C.",
    "wof:placetype":"venue"
},
  "geometry": {"coordinates":[7.907797,44.907063],"type":"Point"}
}