{
  "type": "Feature",
  "properties": {
    "addr:full":"39030 Rasun Anterselva Bolzano/Bozen 39030",
    "addr:postcode":"39030;39030",
    "iso:country":"IT",
    "sg:address":"39030 Rasun Anterselva",
    "sg:orig_category":"Campeggio. Alberghi E Strutture Extra Alberghiere",
    "sg:phone":"+39 0474 492204",
    "sg:postcode":"39030",
    "sg:province":"Bolzano/Bozen",
    "sg:website":"http://www.camping-antholz.com",
    "wof:name":"Camping Antholz",
    "wof:placetype":"venue"
},
  "geometry": {"coordinates":[12.048463,46.779556],"type":"Point"}
}