{
  "type": "Feature",
  "properties": {
    "iso:country":"IT",
    "sg:address":"Via Ludovico Ariosto 17 95014 Giarre",
    "sg:city":"Giarre",
    "sg:classifiers":[
        {
            "category":"Food & Beverages",
            "subcategory":"Liquor & Beverages",
            "type":"Retail Goods"
        }
    ],
    "sg:phone":"+39 095 939650",
    "sg:postcode":"95014",
    "sg:province":"Catania",
    "sg:tags":[
        "wine",
        "italian"
    ],
    "sg:website":"www.russovini.com",
    "wof:name":"Azienda Vinicola Russo Vincenzo .",
    "wof:placetype":"venue"
},
  "geometry": {"coordinates":[15.186746,37.742947],"type":"Point"}
}