{
  "type": "Feature",
  "properties": {
    "addr:full":"20089 Rozzano Rozzano Milano 20089",
    "addr:postcode":"20089;20089",
    "iso:country":"IT",
    "sg:address":"20089 Rozzano",
    "sg:city":"Rozzano",
    "sg:orig_category":"Motori Ed Organi Di Trasmissione. Ricambi E Componenti Dei Mezzi Di Trasporto",
    "sg:phone":"+39 02 5751 2192",
    "sg:postcode":"20089",
    "sg:province":"Milano",
    "wof:name":"Megadyne Service & Distribution S.r.l.",
    "wof:placetype":"venue"
},
  "geometry": {"coordinates":[9.1666612625,45.3934745789],"type":"Point"}
}