{
  "type": "Feature",
  "properties": {
    "iso:country":"IT",
    "sg:address":"10078 Venaria",
    "sg:orig_category":"Tempo Libero - Articoli E Forniture. Automobili E Mezzi Di Trasporto",
    "sg:phone":"+39 011 455 1551",
    "sg:postcode":"10078",
    "sg:province":"Torino",
    "wof:name":"Silver Star",
    "wof:placetype":"venue"
},
  "geometry": {"coordinates":[7.647616,45.115322],"type":"Point"}
}