{
  "type": "Feature",
  "properties": {
    "iso:country":"IT",
    "sg:address":"via Emilia Ponente, 1667",
    "sg:city":"Cesena",
    "sg:classifiers":[
        {
            "category":"Professional",
            "subcategory":"Computer Services",
            "type":"Services"
        }
    ],
    "sg:postcode":"47023",
    "sg:tags":[
        "free-to-play",
        "f2p",
        "game",
        "development",
        "studio",
        "italy",
        "cesena",
        "racing",
        "engine",
        "social",
        "network"
    ],
    "sg:website":"http://www.vaevictis.it",
    "wof:name":"Vae Victis",
    "wof:placetype":"venue"
},
  "geometry": {"coordinates":[12.2091265,44.1480034],"type":"Point"}
}