{
  "type": "Feature",
  "properties": {
    "iso:country":"IT",
    "sg:address":"2, Via Bengasi 21040 Gerenzano",
    "sg:city":"Gerenzano",
    "sg:classifiers":[
        {
            "category":"Manufacturing",
            "subcategory":"Wood Products",
            "type":"Manufacturing & Wholesale Goods"
        }
    ],
    "sg:phone":"+39 39029689047",
    "sg:postcode":"21040",
    "sg:province":"Varese",
    "sg:tags":[
        "furniture"
    ],
    "wof:name":"Franchi Angelo E Figli E C. (s.r.l.)",
    "wof:placetype":"venue"
},
  "geometry": {"coordinates":[8.826385,45.817604],"type":"Point"}
}