{
  "type": "Feature",
  "properties": {
    "addr:full":"16, V. L. Pettin\u00e0 36010 Zan\u00e8 Vicenza 36010",
    "addr:housenumber":"16",
    "addr:postcode":"36010;36010",
    "addr:street":"V. L. Pettina\u0300",
    "iso:country":"IT",
    "sg:address":"16, V. L. Pettin\u00e0 36010 Zan\u00e8",
    "sg:classifiers":[
        {
            "category":"Manufacturing",
            "subcategory":"Rubber & Plastics",
            "type":"Manufacturing & Wholesale Goods"
        }
    ],
    "sg:phone":"+39 0445 316411",
    "sg:postcode":"36010",
    "sg:province":"Vicenza",
    "sg:website":"http://www.boteco.it:ws_end: :mark:ws:http://www.paginegialle.it/boteco",
    "wof:name":"Boteco Spa",
    "wof:placetype":"venue"
},
  "geometry": {"coordinates":[11.540307045,45.5459060669],"type":"Point"}
}