{
  "type": "Feature",
  "properties": {
    "iso:country":"IT",
    "sg:address":"20080 Carpiano",
    "sg:city":"Carpiano",
    "sg:orig_category":"Cartotecnica E Servizi. Forniture Per Attivita' Commerciali Ed Artigianali",
    "sg:phone":"+39 02 9885 5111",
    "sg:postcode":"20080",
    "sg:province":"Milano",
    "wof:name":"3m Italia S.p.a.",
    "wof:placetype":"venue"
},
  "geometry": {"coordinates":[9.271022,45.341419],"type":"Point"}
}