{
  "type": "Feature",
  "properties": {
    "iso:country":"IT",
    "sg:address":"V. G. Nenna 00053 Civitavecchia",
    "sg:city":"Civitavecchia",
    "sg:classifiers":[
        {
            "category":"Sports & Exercise",
            "subcategory":"Playing Field",
            "type":"Entertainment"
        }
    ],
    "sg:phone":"+39 0766 502257",
    "sg:postcode":"00053",
    "sg:province":"Roma",
    "sg:tags":[
        "game"
    ],
    "sg:website":"http://www.asiatradeonline.org",
    "wof:name":"Asia Trade Srl",
    "wof:placetype":"venue"
},
  "geometry": {"coordinates":[12.482325,41.895466],"type":"Point"}
}