{
  "type": "Feature",
  "properties": {
    "iso:country":"IT",
    "sg:address":"43100 Parma",
    "sg:city":"Parma",
    "sg:orig_category":"Forniture Per Attivita' Industriali",
    "sg:phone":"+39 0521 483003",
    "sg:postcode":"43100",
    "sg:province":"Parma",
    "wof:name":"Rekord Abrasivi Sas",
    "wof:placetype":"venue"
},
  "geometry": {"coordinates":[10.3229598999,44.7756004333],"type":"Point"}
}