{
  "type": "Feature",
  "properties": {
    "iso:country":"IT",
    "sg:address":"97100 Ragusa",
    "sg:city":"Ragusa",
    "sg:classifiers":[
        {
            "category":"Professional",
            "type":"Services"
        }
    ],
    "sg:phone":"+39 0932 651403",
    "sg:postcode":"97100",
    "sg:province":"Ragusa",
    "sg:tags":[
        "auxiliary",
        "entertainment",
        "premises",
        "related",
        "catering",
        "public",
        "restaurants"
    ],
    "wof:name":"Ristorante Mediterraneo - Ristor House Sas",
    "wof:placetype":"venue"
},
  "geometry": {"coordinates":[14.524183,36.826019],"type":"Point"}
}