{
  "type": "Feature",
  "properties": {
    "iso:country":"IT",
    "sg:address":"22100 Como",
    "sg:city":"Como",
    "sg:orig_category":"Disegni Per Tessuti",
    "sg:phone":"+39 031 309106",
    "sg:postcode":"22100",
    "sg:province":"Como",
    "wof:name":"Studio 3 Srl",
    "wof:placetype":"venue"
},
  "geometry": {"coordinates":[9.090342,45.813957],"type":"Point"}
}