{
  "type": "Feature",
  "properties": {
    "iso:country":"IT",
    "sg:address":"37012 Bussolengo",
    "sg:city":"Bussolengo",
    "sg:classifiers":[
        {
            "category":"Wholesale",
            "subcategory":"Machinery & Supplies",
            "type":"Manufacturing & Wholesale Goods"
        }
    ],
    "sg:phone":"+39 045 675 2711",
    "sg:postcode":"37012",
    "sg:province":"Verona",
    "sg:tags":[
        "component",
        "engineering",
        "material",
        "electrical"
    ],
    "wof:name":"Matsushita Automation Controls Italia Srl",
    "wof:placetype":"venue"
},
  "geometry": {"coordinates":[10.87465,45.448544],"type":"Point"}
}