{
  "type": "Feature",
  "properties": {
    "addr:full":"06080 Perugia PG",
    "addr:postcode":"06080",
    "addr:street":"Pg",
    "iso:country":"IT",
    "sg:address":"06080 Perugia",
    "sg:classifiers":[
        {
            "category":"Shopping",
            "subcategory":"Crafts & Fabrics",
            "type":"Retail Goods"
        }
    ],
    "sg:phone":"+39 075 599 6044",
    "sg:province":"PG",
    "sg:tags":[
        "decorative",
        "art",
        "furnishings",
        "objects",
        "artistic",
        "crafts"
    ],
    "wof:name":"Imago Grafica Snc",
    "wof:placetype":"venue"
},
  "geometry": {"coordinates":[12.4797945023,43.0860176086],"type":"Point"}
}