{
  "type": "Feature",
  "properties": {
    "iso:country":"IT",
    "sg:address":"19, Via Vittorio Veneto 31040 Chiarano",
    "sg:city":"Chiarano",
    "sg:classifiers":[
        {
            "category":"Manufacturing",
            "subcategory":"Rubber & Plastics",
            "type":"Manufacturing & Wholesale Goods"
        }
    ],
    "sg:phone":"+39 390 422 2030",
    "sg:postcode":"31040",
    "sg:province":"Treviso",
    "wof:name":"Fopan S.p.a.",
    "wof:placetype":"venue"
},
  "geometry": {"coordinates":[12.5655994415,45.7286148071],"type":"Point"}
}