{
  "type": "Feature",
  "properties": {
    "addr:full":"48018 Faenza Faenza Ravenna 48018",
    "addr:postcode":"48018;48018",
    "iso:country":"IT",
    "sg:address":"48018 Faenza",
    "sg:city":"Faenza",
    "sg:orig_category":"Accessori Moda D'abbigliamento. Forniture Per Abbigliamento E Pelletterie",
    "sg:phone":"+39 0546 621619",
    "sg:postcode":"48018",
    "sg:province":"Ravenna",
    "wof:name":"Gladis Creazioni Di Ierpi Gabriella E C. Sas",
    "wof:placetype":"venue"
},
  "geometry": {"coordinates":[12.138917,44.414036],"type":"Point"}
}