{
  "type": "Feature",
  "properties": {
    "addr:full":"74100 Taranto Taranto Taranto 74100",
    "addr:postcode":"74100;74100",
    "iso:country":"IT",
    "sg:address":"74100 Taranto",
    "sg:city":"Taranto",
    "sg:orig_category":"Facchinaggio, Carico E Scarico Merci, Portabagagli - Servizio",
    "sg:phone":"+39 099 453 5111",
    "sg:postcode":"74100",
    "sg:province":"Taranto",
    "wof:name":"Artra Soc.coop.r.l.",
    "wof:placetype":"venue"
},
  "geometry": {"coordinates":[17.2404308319,40.4705543518],"type":"Point"}
}