{
  "type": "Feature",
  "properties": {
    "iso:country":"IT",
    "sg:address":"Via Emilia Levante 200; Castel Bolognese",
    "sg:classifiers":[
        {
            "category":"Banks & Credit Unions",
            "subcategory":"Bank",
            "type":"Services"
        }
    ],
    "sg:phone":"+39 0546 55630",
    "wof:name":"Cassa Di Risparmio Di Imola Spa",
    "wof:placetype":"venue"
},
  "geometry": {"coordinates":[11.812896,44.314327],"type":"Point"}
}