{
  "type": "Feature",
  "properties": {
    "addr:full":"15100 Alessandria Alessandria Alessandria 15100",
    "addr:postcode":"15100;15100",
    "iso:country":"IT",
    "sg:address":"15100 Alessandria",
    "sg:city":"Alessandria",
    "sg:orig_category":"Arredi Ed Attrezzature Per Uffici",
    "sg:phone":"+39 0131 52745",
    "sg:postcode":"15100",
    "sg:province":"Alessandria",
    "wof:name":"Distributori Automatici Di Guarona & Scarabello Snc",
    "wof:placetype":"venue"
},
  "geometry": {"coordinates":[8.627931,44.911236],"type":"Point"}
}