{
  "type": "Feature",
  "properties": {
    "iso:country":"IT",
    "sg:address":"25, V. Ca' Dell'agro 24024 Gandino",
    "sg:city":"Gandino",
    "sg:classifiers":[
        {
            "category":"Shopping",
            "subcategory":"Crafts & Fabrics",
            "type":"Retail Goods"
        }
    ],
    "sg:phone":"+39 39035745002",
    "sg:postcode":"24024",
    "sg:province":"Bergamo",
    "sg:tags":[
        "linen"
    ],
    "sg:website":"http://www.paginegialle.it/lanificiosavoldelli",
    "wof:name":"Lanificio Savoldelli",
    "wof:placetype":"venue"
},
  "geometry": {"coordinates":[9.8967828751,45.8115386963],"type":"Point"}
}