{
  "type": "Feature",
  "properties": {
    "iso:country":"IT",
    "sg:address":"Via Marconi 10 22040 Brenna",
    "sg:city":"Brenna",
    "sg:classifiers":[
        {
            "category":"Government",
            "subcategory":"Court House",
            "type":"Public Place"
        }
    ],
    "sg:phone":"+39 031 797150",
    "sg:postcode":"22040",
    "sg:province":"Como",
    "sg:tags":[
        "accommodation",
        "furniture"
    ],
    "sg:website":"www.gdm-2000.com",
    "wof:name":"Gdm 2000 Srl Guerini Designing Mobili",
    "wof:placetype":"venue"
},
  "geometry": {"coordinates":[9.165406,45.779873],"type":"Point"}
}