{
  "type": "Feature",
  "properties": {
    "addr:full":"26, Via Vincenzo Stefano Breda 35010 Limena Limena Padova 35010",
    "addr:postcode":"35010;35010",
    "addr:street":"Via Vincenzo Stefano",
    "iso:country":"IT",
    "sg:address":"26, Via Vincenzo Stefano Breda 35010 Limena",
    "sg:city":"Limena",
    "sg:classifiers":[
        {
            "category":"Manufacturing",
            "subcategory":"Printing",
            "type":"Manufacturing & Wholesale Goods"
        }
    ],
    "sg:phone":"+39 049 884 0333",
    "sg:postcode":"35010",
    "sg:province":"Padova",
    "sg:tags":[
        "publishing"
    ],
    "wof:name":"Alfe Libri S.r.l.",
    "wof:placetype":"venue"
},
  "geometry": {"coordinates":[11.8485765457,45.4641647339],"type":"Point"}
}