{
  "type": "Feature",
  "properties": {
    "addr:full":"20019 Settimo Milanese Settimo Milanese Milano 20019",
    "addr:postcode":"20019;20019",
    "iso:country":"IT",
    "sg:address":"20019 Settimo Milanese",
    "sg:city":"Settimo Milanese",
    "sg:orig_category":"Bagno - Accessori E Mobili",
    "sg:phone":"+39 02 328 8721",
    "sg:postcode":"20019",
    "sg:province":"Milano",
    "wof:name":"Mobilcrab Srl",
    "wof:placetype":"venue"
},
  "geometry": {"coordinates":[9.066167,45.468361],"type":"Point"}
}