{
  "type": "Feature",
  "properties": {
    "iso:country":"IT",
    "sg:address":"15048 Valenza",
    "sg:city":"Valenza",
    "sg:orig_category":"Gioielleria E Oreficeria - Lavorazione E Ingrosso",
    "sg:phone":"+39 0131 942587",
    "sg:postcode":"15048",
    "sg:province":"Alessandria",
    "wof:name":"Nebbia E Zerbetto Snc Di Nebbia Fabrizio & C.",
    "wof:placetype":"venue"
},
  "geometry": {"coordinates":[8.631977,45.009506],"type":"Point"}
}