{
  "type": "Feature",
  "properties": {
    "addr:full":"23807 Merate Merate Lecco 23807",
    "addr:postcode":"23807;23807",
    "iso:country":"IT",
    "sg:address":"23807 Merate",
    "sg:city":"Merate",
    "sg:orig_category":"Macchine, Impianti Ed Attrezzature Per Agricoltura E Zootecnia",
    "sg:phone":"+39 039 990 2185",
    "sg:postcode":"23807",
    "sg:province":"Lecco",
    "wof:name":"Galbusera Giuseppe Dei Fratelli Galbusera E C.",
    "wof:placetype":"venue"
},
  "geometry": {"coordinates":[9.409127,45.687016],"type":"Point"}
}