{
  "type": "Feature",
  "properties": {
    "addr:full":"45, Via Don Motti 27027 Gropello Cairoli Gropello Cairoli Pavia 27027",
    "addr:postcode":"27027;27027",
    "addr:street":"Via Don Motti",
    "iso:country":"IT",
    "sg:address":"45, Via Don Motti 27027 Gropello Cairoli",
    "sg:city":"Gropello Cairoli",
    "sg:classifiers":[
        {
            "category":"Wholesale",
            "subcategory":"Drugs",
            "type":"Manufacturing & Wholesale Goods"
        }
    ],
    "sg:phone":"+39 0382 814010",
    "sg:postcode":"27027",
    "sg:province":"Pavia",
    "sg:tags":[
        "chemical",
        "pharmaceutical"
    ],
    "wof:name":"Farmabios S.p.a.",
    "wof:placetype":"venue"
},
  "geometry": {"coordinates":[8.999747,45.173298],"type":"Point"}
}