{
  "type": "Feature",
  "properties": {
    "addr:full":"Strada Statale 194 96016 Lentini Lentini Siracusa 96016",
    "addr:housenumber":"194",
    "addr:postcode":"96016;96016",
    "addr:street":"Strada Statale",
    "iso:country":"IT",
    "sg:address":"Strada Statale 194 96016 Lentini",
    "sg:city":"Lentini",
    "sg:classifiers":[
        {
            "category":"Farming",
            "subcategory":"Livestock Farm",
            "type":"Manufacturing & Wholesale Goods"
        }
    ],
    "sg:phone":"+39 39095942522",
    "sg:postcode":"96016",
    "sg:province":"Siracusa",
    "sg:tags":[
        "agriculture"
    ],
    "wof:name":"Assoc.agricola Intercitrus Di Tribulato A.",
    "wof:placetype":"venue"
},
  "geometry": {"coordinates":[15.28444,37.066483],"type":"Point"}
}