{
  "type": "Feature",
  "properties": {
    "iso:country":"IT",
    "sg:address":"48018 Faenza",
    "sg:city":"Faenza",
    "sg:orig_category":"Pompe. Apparecchiature E Sistemi Per Imballaggio E Confezionamento",
    "sg:phone":"+39 0546 46257",
    "sg:postcode":"48018",
    "sg:province":"Ravenna",
    "wof:name":"Lepri Giuseppe",
    "wof:placetype":"venue"
},
  "geometry": {"coordinates":[11.8952980042,44.324382782],"type":"Point"}
}