{
  "type": "Feature",
  "properties": {
    "addr:full":"20050 Triuggio Triuggio Milano 20050",
    "addr:postcode":"20050;20050",
    "iso:country":"IT",
    "sg:address":"20050 Triuggio",
    "sg:city":"Triuggio",
    "sg:orig_category":"Abbigliamento Industria - Forniture Ed Accessori",
    "sg:phone":"+39 036 299 7735",
    "sg:postcode":"20050",
    "sg:province":"Milano",
    "wof:name":"Imtex Srl",
    "wof:placetype":"venue"
},
  "geometry": {"coordinates":[9.273183,45.65654],"type":"Point"}
}