{
  "type": "Feature",
  "properties": {
    "iso:country":"IT",
    "sg:address":"14, Via Carducci Giosue' 20123 Milano",
    "sg:city":"Milano",
    "sg:classifiers":[
        {
            "category":"Communications",
            "subcategory":"Newspaper",
            "type":"Services"
        }
    ],
    "sg:phone":"+39 390 246 7671",
    "sg:postcode":"20123",
    "sg:province":"Milano",
    "sg:tags":[
        "advertising"
    ],
    "wof:name":"Cia Italy Srl",
    "wof:placetype":"venue"
},
  "geometry": {"coordinates":[9.174826,45.464497],"type":"Point"}
}