{
  "type": "Feature",
  "properties": {
    "addr:full":"35, Via Borsellino 25038 Rovato Rovato Brescia 25038",
    "addr:postcode":"25038;25038",
    "addr:street":"Via Borsellino",
    "iso:country":"IT",
    "sg:address":"35, Via Borsellino 25038 Rovato",
    "sg:city":"Rovato",
    "sg:classifiers":[
        {
            "category":"Food & Beverages",
            "subcategory":"Groceries & Convenience Stores",
            "type":"Retail Goods"
        }
    ],
    "sg:phone":"+39 030 770 4444",
    "sg:postcode":"25038",
    "sg:province":"Brescia",
    "sg:tags":[
        "product",
        "related"
    ],
    "wof:name":"Valdigrano Srl Di Flavio Pagani",
    "wof:placetype":"venue"
},
  "geometry": {"coordinates":[10.0088205338,45.5581626892],"type":"Point"}
}