{
  "type": "Feature",
  "properties": {
    "addr:full":"Via Sant'alberto 2 25036 Palazzolo Sull'oglio Brescia 25036",
    "addr:housenumber":"2",
    "addr:postcode":"25036;25036",
    "addr:street":"Via Sant'Alberto",
    "iso:country":"IT",
    "sg:address":"Via Sant'alberto 2 25036 Palazzolo Sull'oglio",
    "sg:classifiers":[
        {
            "category":"Banks & Credit Unions",
            "subcategory":"Investment Brokerage",
            "type":"Services"
        }
    ],
    "sg:phone":"+39 030 73091",
    "sg:postcode":"25036",
    "sg:province":"Brescia",
    "sg:tags":[
        "textile",
        "machine"
    ],
    "sg:website":"www.marzoli.it",
    "wof:name":"Fratelli Marzoli & C. Spa",
    "wof:placetype":"venue"
},
  "geometry": {"coordinates":[10.222958,45.539829],"type":"Point"}
}