{
  "type": "Feature",
  "properties": {
    "iso:country":"IT",
    "sg:address":"Via Passerotta 6 40057 Granarolo Dell'emilia",
    "sg:classifiers":[
        {
            "category":"Military Area",
            "subcategory":"Coast Guard Base",
            "type":"Public Place"
        }
    ],
    "sg:phone":"+39 051 761200",
    "sg:postcode":"40057",
    "sg:province":"Bologna",
    "sg:tags":[
        "gear",
        "rack"
    ],
    "sg:website":"www.matt.it",
    "wof:name":"Mattioli Snc",
    "wof:placetype":"venue"
},
  "geometry": {"coordinates":[11.440987,44.545895],"type":"Point"}
}