{
  "type": "Feature",
  "properties": {
    "addr:full":"Piazza Liberta 8; Monasterolo; 12030 Cuneo 12030",
    "addr:housenumber":"8",
    "addr:postcode":"12030;12030",
    "addr:street":"Piazza Liberta",
    "iso:country":"IT",
    "sg:address":"Piazza Liberta 8; Monasterolo; 12030",
    "sg:classifiers":[
        {
            "category":"Banks & Credit Unions",
            "subcategory":"Bank",
            "type":"Services"
        }
    ],
    "sg:phone":"+39 0172 373143",
    "sg:postcode":"12030",
    "sg:province":"Cuneo",
    "wof:name":"Banca Cassa Di Rispramio, Di Savigliano Spa",
    "wof:placetype":"venue"
},
  "geometry": {"coordinates":[7.620507,44.687084],"type":"Point"}
}