{
  "type": "Feature",
  "properties": {
    "iso:country":"IT",
    "sg:address":"27, Via Dell' Industria 37014 Castelnuovo Del Garda",
    "sg:city":"Castelnuovo del Garda",
    "sg:classifiers":[
        {
            "category":"Personal",
            "subcategory":"Shoe Repair & Shine",
            "type":"Services"
        }
    ],
    "sg:phone":"+39 045 757 0599",
    "sg:postcode":"37014",
    "sg:province":"Verona",
    "sg:tags":[
        "leather"
    ],
    "wof:name":"Ds S.r.l.",
    "wof:placetype":"venue"
},
  "geometry": {"coordinates":[10.761909,45.428055],"type":"Point"}
}