{
  "type": "Feature",
  "properties": {
    "addr:full":"00141 Roma Roma Roma 00141",
    "addr:postcode":"00141;00141",
    "iso:country":"IT",
    "sg:address":"00141 Roma",
    "sg:city":"Roma",
    "sg:orig_category":"Cinematografia E Radiotelevisione",
    "sg:phone":"+39 06 8864 0304",
    "sg:postcode":"00141",
    "sg:province":"Roma",
    "wof:name":"Oxer Srl",
    "wof:placetype":"venue"
},
  "geometry": {"coordinates":[12.52072,41.943577],"type":"Point"}
}