{
  "type": "Feature",
  "properties": {
    "addr:full":"25029 Verolavecchia Verolavecchia Brescia 25029",
    "addr:postcode":"25029;25029",
    "iso:country":"IT",
    "sg:address":"25029 Verolavecchia",
    "sg:city":"Verolavecchia",
    "sg:orig_category":"Carrozzerie Autoveicoli Industriali E Speciali",
    "sg:phone":"+39 030 992 0811",
    "sg:postcode":"25029",
    "sg:province":"Brescia",
    "wof:name":"Extralux Snc Di Ponzio & C.",
    "wof:placetype":"venue"
},
  "geometry": {"coordinates":[10.038509,45.281982],"type":"Point"}
}