{
  "type": "Feature",
  "properties": {
    "iso:country":"IT",
    "sg:address":"20060 Vignate",
    "sg:city":"Vignate",
    "sg:orig_category":"Tessuti E Stoffe. Forniture Per Attivita' Industriali",
    "sg:phone":"+39 02 956 7400",
    "sg:postcode":"20060",
    "sg:province":"Milano",
    "wof:name":"Erresit Srl",
    "wof:placetype":"venue"
},
  "geometry": {"coordinates":[9.153792,45.465057],"type":"Point"}
}