{
  "type": "Feature",
  "properties": {
    "iso:country":"IT",
    "sg:address":"4, Via S. Geminiano 46100 Mantova",
    "sg:city":"Mantova",
    "sg:classifiers":[
        {
            "category":"Manufacturing",
            "subcategory":"Metals",
            "type":"Manufacturing & Wholesale Goods"
        }
    ],
    "sg:phone":"+39 0376 370747",
    "sg:postcode":"46100",
    "sg:province":"Mantova",
    "sg:tags":[
        "metallurgy",
        "metalworking"
    ],
    "wof:name":"Frassine (s.r.l.)",
    "wof:placetype":"venue"
},
  "geometry": {"coordinates":[10.8293905258,45.1603317261],"type":"Point"}
}