{
  "type": "Feature",
  "properties": {
    "addr:full":"36031 Dueville Dueville Vicenza 36031",
    "addr:postcode":"36031;36031",
    "iso:country":"IT",
    "sg:address":"36031 Dueville",
    "sg:city":"Dueville",
    "sg:orig_category":"Pozzi Artesiani - Trivellazione E Manutenzione",
    "sg:phone":"+39 0444 594191",
    "sg:postcode":"36031",
    "sg:province":"Vicenza",
    "wof:name":"Costa Augusto & C. Snc",
    "wof:placetype":"venue"
},
  "geometry": {"coordinates":[11.5500669479,45.636505127],"type":"Point"}
}