{
  "type": "Feature",
  "properties": {
    "addr:full":"12040 Sanfr\u00e8 Cuneo 12040",
    "addr:housenumber":"12040",
    "addr:postcode":"12040",
    "addr:street":"Sanfre\u0300 Cuneo",
    "iso:country":"IT",
    "sg:address":"12040 Sanfr\u00e8",
    "sg:orig_category":"Vetrate Artistiche",
    "sg:phone":"+39 0172 587425",
    "sg:postcode":"12040",
    "sg:province":"Cuneo",
    "wof:name":"Vetrital Di Sansoldo G. E Milanesio C. Snc",
    "wof:placetype":"venue"
},
  "geometry": {"coordinates":[7.53934,44.399136],"type":"Point"}
}