{
  "type": "Feature",
  "properties": {
    "addr:full":"20021 Bollate Bollate Milano 20021",
    "addr:postcode":"20021;20021",
    "iso:country":"IT",
    "sg:address":"20021 Bollate",
    "sg:city":"Bollate",
    "sg:orig_category":"Abbigliamento Esterno, Maglierie E Pelliccerie. Shopping",
    "sg:phone":"+39 02 3326 2217",
    "sg:postcode":"20021",
    "sg:province":"Milano",
    "wof:name":"T.m. Confezioni S.a.s.",
    "wof:placetype":"venue"
},
  "geometry": {"coordinates":[9.141985,45.54937],"type":"Point"}
}