{
  "type": "Feature",
  "properties": {
    "iso:country":"IT",
    "sg:address":"81025 Marcianise",
    "sg:city":"Marcianise",
    "sg:orig_category":"Orologeria",
    "sg:phone":"+39 0823 513140",
    "sg:postcode":"81025",
    "sg:province":"Caserta",
    "wof:name":"Zefiro - Altanus Geneve",
    "wof:placetype":"venue"
},
  "geometry": {"coordinates":[14.297743,41.015236],"type":"Point"}
}