{
  "type": "Feature",
  "properties": {
    "addr:full":"10126 Torino Torino Torino 10126",
    "addr:postcode":"10126;10126",
    "iso:country":"IT",
    "sg:address":"10126 Torino",
    "sg:city":"Torino",
    "sg:orig_category":"Traduttori Ed Interpreti",
    "sg:phone":"+39 011 650 3739",
    "sg:postcode":"10126",
    "sg:province":"Torino",
    "sg:website":"http://www.agenceceg.it",
    "wof:name":"Agence C.e.g.",
    "wof:placetype":"venue"
},
  "geometry": {"coordinates":[7.68159,45.049442],"type":"Point"}
}