{
  "type": "Feature",
  "properties": {
    "addr:full":"9, Via Marche 41049 Sassuolo Sassuolo Modena 41049",
    "addr:postcode":"41049;41049",
    "addr:street":"Via Marche",
    "iso:country":"IT",
    "sg:address":"9, Via Marche 41049 Sassuolo",
    "sg:city":"Sassuolo",
    "sg:classifiers":[
        {
            "category":"Professional",
            "subcategory":"Engineering",
            "type":"Services"
        }
    ],
    "sg:phone":"+39 0536 802117",
    "sg:postcode":"41049",
    "sg:province":"Modena",
    "sg:tags":[
        "machine",
        "-",
        "mechanical"
    ],
    "wof:name":"Camellini Service S.r.l.",
    "wof:placetype":"venue"
},
  "geometry": {"coordinates":[10.801739,44.562408],"type":"Point"}
}