{
  "type": "Feature",
  "properties": {
    "iso:country":"IT",
    "sg:address":"42100 Reggio Emilia",
    "sg:orig_category":"Trattamenti Termici E Superficiali Metalli, Galvanotecnica",
    "sg:phone":"+39 0522 620954",
    "sg:postcode":"42100",
    "sg:province":"Reggio Nell'Emilia",
    "wof:name":"Tartarelli Cosimo - Svm",
    "wof:placetype":"venue"
},
  "geometry": {"coordinates":[10.745181,44.652775],"type":"Point"}
}