{
  "type": "Feature",
  "properties": {
    "iso:country":"IT",
    "sg:address":"Via Bezzera Luigi 20088 Rosate",
    "sg:city":"Rosate",
    "sg:classifiers":[
        {
            "category":"Home & Garden",
            "subcategory":"Home Furnishings",
            "type":"Retail Goods"
        }
    ],
    "sg:phone":"+39 02 9083 4001",
    "sg:postcode":"20088",
    "sg:province":"Milano",
    "sg:tags":[
        "household"
    ],
    "wof:name":"S.c.a.m. S.a.s.",
    "wof:placetype":"venue"
},
  "geometry": {"coordinates":[9.188141,45.463688],"type":"Point"}
}