{
  "type": "Feature",
  "properties": {
    "iso:country":"IT",
    "sg:address":"19126 La Spezia",
    "sg:orig_category":"Riparazione Dei Mezzi Di Trasporto. Servizi Ausiliari Dei Mezzi Di Trasporto",
    "sg:phone":"+39 0187 512746",
    "sg:province":"SP",
    "wof:name":"Esse Emme Srl",
    "wof:placetype":"venue"
},
  "geometry": {"coordinates":[9.854538,44.112782],"type":"Point"}
}