{
  "type": "Feature",
  "properties": {
    "addr:full":"97014 Ispica Ispica Ragusa 97014",
    "addr:postcode":"97014;97014",
    "iso:country":"IT",
    "sg:address":"97014 Ispica",
    "sg:city":"Ispica",
    "sg:orig_category":"Servizi Per Lo Sport E Il Tempo Libero. Servizi Al Turismo",
    "sg:phone":"+39 0932 793433",
    "sg:postcode":"97014",
    "sg:province":"Ragusa",
    "wof:name":"Center Express Di Dimartino A. & Lo Iacono G.s.d.f.",
    "wof:placetype":"venue"
},
  "geometry": {"coordinates":[14.911204,36.785988],"type":"Point"}
}