{
  "type": "Feature",
  "properties": {
    "addr:full":"50122 Firenze Firenze Firenze 50122",
    "addr:postcode":"50122;50122",
    "iso:country":"IT",
    "sg:address":"50122 Firenze",
    "sg:city":"Firenze",
    "sg:orig_category":"Gioielleria, Oreficeria E Argenteria. Shopping",
    "sg:phone":"+39 055 287937",
    "sg:postcode":"50122",
    "sg:province":"Firenze",
    "wof:name":"Ennio Bramanti",
    "wof:placetype":"venue"
},
  "geometry": {"coordinates":[11.256084,43.770569],"type":"Point"}
}