{
  "type": "Feature",
  "properties": {
    "addr:full":"28845 Domodossola Domodossola Verbano-Cusio-Ossola 28845",
    "addr:postcode":"28845;28845",
    "iso:country":"IT",
    "sg:address":"28845 Domodossola",
    "sg:city":"Domodossola",
    "sg:orig_category":"Ferramenta - Ingrosso",
    "sg:phone":"+39 0324 47722",
    "sg:postcode":"28845",
    "sg:province":"Verbano-Cusio-Ossola",
    "wof:name":"Ferramenta L'edilizia Snc",
    "wof:placetype":"venue"
},
  "geometry": {"coordinates":[8.2724647522,46.1399688721],"type":"Point"}
}