{
  "type": "Feature",
  "properties": {
    "addr:full":"52100 Arezzo Arezzo Arezzo 52100",
    "addr:postcode":"52100;52100",
    "iso:country":"IT",
    "sg:address":"52100 Arezzo",
    "sg:city":"Arezzo",
    "sg:orig_category":"Servizi Vari Di Interesse Pubblico",
    "sg:phone":"+39 0575 23111",
    "sg:postcode":"52100",
    "sg:province":"Arezzo",
    "wof:name":"Baby Service S.n.c.",
    "wof:placetype":"venue"
},
  "geometry": {"coordinates":[11.934807,43.432545],"type":"Point"}
}