{
  "type": "Feature",
  "properties": {
    "iso:country":"IT",
    "sg:address":"25060 Cellatica",
    "sg:city":"Cellatica",
    "sg:orig_category":"Materiali Edili",
    "sg:phone":"+39 030 322341",
    "sg:postcode":"25060",
    "sg:province":"Brescia",
    "wof:name":"Societa' Bresciana Refrattari S.r.l.",
    "wof:placetype":"venue"
},
  "geometry": {"coordinates":[10.165646,45.557117],"type":"Point"}
}