{
  "type": "Feature",
  "properties": {
    "addr:full":"217, Via I Maggio 10062 Luserna San Giovanni Luserna Torino 10062",
    "addr:housenumber":"217",
    "addr:postcode":"10062;10062",
    "addr:street":"Via I Maggio",
    "iso:country":"IT",
    "sg:address":"217, Via I Maggio 10062 Luserna San Giovanni",
    "sg:city":"Luserna",
    "sg:classifiers":[
        {
            "category":"Shopping",
            "subcategory":"Clothing, Apparel, & Fashions",
            "type":"Retail Goods"
        }
    ],
    "sg:phone":"+39 0121 909650",
    "sg:postcode":"10062",
    "sg:province":"Torino",
    "sg:tags":[
        "clothes"
    ],
    "wof:name":"Confezioni Nuova Bubel (s.n.c.)",
    "wof:placetype":"venue"
},
  "geometry": {"coordinates":[7.686619,45.07056],"type":"Point"}
}