{
  "type": "Feature",
  "properties": {
    "iso:country":"IT",
    "sg:address":"27040 Pinarolo Po",
    "sg:city":"Pinarolo Po",
    "sg:orig_category":"Abiti Da Lavoro Ed Indumenti Protettivi",
    "sg:phone":"+39 0383 878551",
    "sg:postcode":"27040",
    "sg:province":"Pavia",
    "sg:website":"http://www.lpi-group.it",
    "wof:name":"L.p.i. Di Pirovano Egidio & C. Snc",
    "wof:placetype":"venue"
},
  "geometry": {"coordinates":[9.169472,45.070328],"type":"Point"}
}