{
  "type": "Feature",
  "properties": {
    "iso:country":"IT",
    "sg:address":"20092 Cinisello Balsamo",
    "sg:city":"Cinisello Balsamo",
    "sg:orig_category":"Articoli Da Regalo. Regalistica Aziendale",
    "sg:phone":"+39 02 6129 8441",
    "sg:postcode":"20092",
    "sg:province":"Milano",
    "wof:name":"Foresti Maria Rosa",
    "wof:placetype":"venue"
},
  "geometry": {"coordinates":[9.210021,45.556072],"type":"Point"}
}