{
  "type": "Feature",
  "properties": {
    "iso:country":"IT",
    "sg:address":"53, Via Chiarini Giuseppe 52100 Arezzo",
    "sg:city":"Arezzo",
    "sg:classifiers":[
        {
            "category":"Wholesale",
            "subcategory":"Machinery & Supplies",
            "type":"Manufacturing & Wholesale Goods"
        }
    ],
    "sg:phone":"+39 0575 903434",
    "sg:postcode":"52100",
    "sg:province":"Arezzo",
    "sg:tags":[
        "-",
        "agriculture",
        "equipment"
    ],
    "wof:name":"Bicchi Fratelli (s.r.l.)",
    "wof:placetype":"venue"
},
  "geometry": {"coordinates":[11.863062,43.471203],"type":"Point"}
}