{
  "type": "Feature",
  "properties": {
    "iso:country":"IT",
    "sg:address":"20090 Opera",
    "sg:city":"Opera",
    "sg:orig_category":"Minuterie Metalliche E Ferramenta",
    "sg:phone":"+39 02 5760 3522",
    "sg:postcode":"20090",
    "sg:province":"Milano",
    "wof:name":"Fercal Sas",
    "wof:placetype":"venue"
},
  "geometry": {"coordinates":[9.2043762207,45.3685836792],"type":"Point"}
}