{
  "type": "Feature",
  "properties": {
    "iso:country":"IT",
    "sg:address":"Str. Del Marano 95 47890 Repubblica Di San Marino",
    "sg:classifiers":[
        {
            "category":"Government",
            "subcategory":"Fire Station",
            "type":"Public Place"
        }
    ],
    "sg:phone":"+39 0549 873111",
    "sg:tags":[
        "diffuser",
        "scent",
        "freshener",
        "air"
    ],
    "wof:name":"Laboratorio Chimico - Farmaceutico Sammarinese Sa",
    "wof:placetype":"venue"
},
  "geometry": {"coordinates":[12.506772,43.932026],"type":"Point"}
}