{
  "type": "Feature",
  "properties": {
    "iso:country":"IT",
    "sg:address":"44041 Cento",
    "sg:city":"Casumaro",
    "sg:orig_category":"Prodotti Vari In Metallo. Articoli Per Imballaggio E Confezionamento",
    "sg:phone":"+39 051 684 9636",
    "sg:postcode":"44041",
    "sg:province":"Ferrara",
    "sg:website":"http://www.reno-tech.com",
    "wof:name":"Reno Tech Costruzioni Meccaniche Di Silvio Zizza",
    "wof:placetype":"venue"
},
  "geometry": {"coordinates":[11.3524923325,44.8212928772],"type":"Point"}
}