{
  "type": "Feature",
  "properties": {
    "iso:country":"IT",
    "sg:address":"20025 Legnano",
    "sg:city":"Legnano",
    "sg:orig_category":"Prodotti E Manufatti In Materie Plastiche",
    "sg:phone":"+39 0331 597049",
    "sg:postcode":"20025",
    "sg:province":"Milano",
    "wof:name":"Novachem S.a.s. Di Gatti Fiorella & C.",
    "wof:placetype":"venue"
},
  "geometry": {"coordinates":[8.9029741287,45.593547821],"type":"Point"}
}