{
  "type": "Feature",
  "properties": {
    "iso:country":"IT",
    "sg:address":"6/8, Via Fleming 20092 Cinisello Balsamo",
    "sg:city":"Cinisello Balsamo",
    "sg:classifiers":[
        {
            "category":"Shopping",
            "subcategory":"Computers & Home Electronics",
            "type":"Retail Goods"
        }
    ],
    "sg:phone":"+39 02 6604 7971",
    "sg:postcode":"20092",
    "sg:province":"Milano",
    "sg:tags":[
        "electronic",
        "electrical",
        "equipment"
    ],
    "wof:name":"Sistema Ricambi (s.r.l.)",
    "wof:placetype":"venue"
},
  "geometry": {"coordinates":[9.232257,45.559761],"type":"Point"}
}