{
  "type": "Feature",
  "properties": {
    "iso:country":"IT",
    "sg:address":"20098 San Giuliano Milanese",
    "sg:city":"San Giuliano Milanese",
    "sg:orig_category":"Arte Ed Artigianato Artistico",
    "sg:phone":"+39 02 984 6525",
    "sg:postcode":"20098",
    "sg:province":"Milano",
    "wof:name":"Fabbiani Adelio",
    "wof:placetype":"venue"
},
  "geometry": {"coordinates":[9.291256,45.401318],"type":"Point"}
}