{
  "type": "Feature",
  "properties": {
    "iso:country":"IT",
    "sg:address":"30174 Mestre",
    "sg:city":"Mestre",
    "sg:orig_category":"Nautica. Automobili E Mezzi Di Trasporto",
    "sg:phone":"+39 041 531 2391",
    "sg:postcode":"30174",
    "sg:province":"Venezia",
    "wof:name":"Il Mare Sas",
    "wof:placetype":"venue"
},
  "geometry": {"coordinates":[12.242073,45.483395],"type":"Point"}
}