{
  "type": "Feature",
  "properties": {
    "addr:full":"39, Via Francesco Baracca 31010 Cimadolmo Cimadolmo Treviso 31010",
    "addr:postcode":"31010;31010",
    "addr:street":"Via Francesco Baracca",
    "iso:country":"IT",
    "sg:address":"39, Via Francesco Baracca 31010 Cimadolmo",
    "sg:city":"Cimadolmo",
    "sg:classifiers":[
        {
            "category":"Shopping",
            "subcategory":"Crafts & Fabrics",
            "type":"Retail Goods"
        }
    ],
    "sg:phone":"+39 0422 743016",
    "sg:postcode":"31010",
    "sg:province":"Treviso",
    "wof:name":"La Bottega Del Tendaggio Di Marchi Giancarlo - Roberto & C. (s.n.c.)",
    "wof:placetype":"venue"
},
  "geometry": {"coordinates":[12.3636722565,45.784526825],"type":"Point"}
}