{
  "type": "Feature",
  "properties": {
    "addr:full":"41058 Vignola Vignola Modena 41058",
    "addr:postcode":"41058;41058",
    "iso:country":"IT",
    "sg:address":"41058 Vignola",
    "sg:city":"Vignola",
    "sg:orig_category":"Radiatori Riscaldamento",
    "sg:phone":"+39 059 760160",
    "sg:postcode":"41058",
    "sg:province":"Modena",
    "wof:name":"Nuova M.b.z. Srl",
    "wof:placetype":"venue"
},
  "geometry": {"coordinates":[10.999729,44.496136],"type":"Point"}
}