{
  "type": "Feature",
  "properties": {
    "iso:country":"IT",
    "sg:address":"Via I Maggio, 39/41 25038 Rovato",
    "sg:city":"Rovato",
    "sg:classifiers":[
        {
            "category":"Shopping",
            "subcategory":"Department Store",
            "type":"Retail Goods"
        }
    ],
    "sg:phone":"+39 030 723629",
    "sg:postcode":"25038",
    "sg:province":"Brescia",
    "sg:tags":[
        "linen",
        "bed"
    ],
    "wof:name":"Nobiltex Srl",
    "wof:placetype":"venue"
},
  "geometry": {"coordinates":[10.222958,45.539829],"type":"Point"}
}