{
  "type": "Feature",
  "properties": {
    "addr:full":"Via Carducci Giosue' 2 25126 Brescia Brescia Brescia 25126",
    "addr:housenumber":"2",
    "addr:postcode":"25126;25126",
    "addr:street":"Via;Giosue '",
    "iso:country":"IT",
    "sg:address":"Via Carducci Giosue' 2 25126 Brescia",
    "sg:city":"Brescia",
    "sg:orig_category":"Non-ferrous Metal Scraps",
    "sg:phone":"+39 030 46050",
    "sg:postcode":"25126",
    "sg:province":"Brescia",
    "sg:website":"www.albre.it",
    "wof:name":"Albre Alluminio Bresciano Srl",
    "wof:placetype":"venue"
},
  "geometry": {"coordinates":[10.222958,45.539829],"type":"Point"}
}