{
  "type": "Feature",
  "properties": {
    "addr:full":"24020 Scanzorosciate Rosciate Bergamo 24020",
    "addr:postcode":"24020;24020",
    "iso:country":"IT",
    "sg:address":"24020 Scanzorosciate",
    "sg:city":"Rosciate",
    "sg:orig_category":"Antifurto",
    "sg:phone":"+39 035 657055",
    "sg:postcode":"24020",
    "sg:province":"Bergamo",
    "sg:website":"http://www.sistemidisicurezza.com",
    "wof:name":"Sv Sistemi Di Sicurezza Srl",
    "wof:placetype":"venue"
},
  "geometry": {"coordinates":[9.736278,45.711723],"type":"Point"}
}