{
  "type": "Feature",
  "properties": {
    "iso:country":"IT",
    "sg:address":"12038 Savigliano",
    "sg:city":"Savigliano",
    "sg:orig_category":"Alberghi E Strutture Extra Alberghiere",
    "sg:phone":"+39 0172 726349",
    "sg:postcode":"12038",
    "sg:province":"Cuneo",
    "wof:name":"Motel Cosmera",
    "wof:placetype":"venue"
},
  "geometry": {"coordinates":[7.551993,44.391644],"type":"Point"}
}