{
  "type": "Feature",
  "properties": {
    "iso:country":"IT",
    "sg:address":"98122 Messina",
    "sg:city":"Messina",
    "sg:orig_category":"Motocicli E Motocarri - Commercio E Riparazione",
    "sg:phone":"+39 090 719318",
    "sg:postcode":"98122",
    "sg:province":"Messina",
    "wof:name":"Faranda Maria",
    "wof:placetype":"venue"
},
  "geometry": {"coordinates":[15.5386447906,38.1990470886],"type":"Point"}
}