{
  "type": "Feature",
  "properties": {
    "addr:full":"50145 Firenze Firenze Firenze 50145",
    "addr:postcode":"50145;50145",
    "iso:country":"IT",
    "sg:address":"50145 Firenze",
    "sg:city":"Firenze",
    "sg:orig_category":"Servizi Per Imballaggio E Confezionamento",
    "sg:phone":"+39 055 300150",
    "sg:postcode":"50145",
    "sg:province":"Firenze",
    "sg:website":"http://www.nuovacesat.it",
    "wof:name":"Nuova Cesat Soc.coop.a R.l.",
    "wof:placetype":"venue"
},
  "geometry": {"coordinates":[11.214993,43.711075],"type":"Point"}
}