{
  "type": "Feature",
  "properties": {
    "iso:country":"IT",
    "sg:address":"41100 Modena",
    "sg:city":"Modena",
    "sg:orig_category":"Agenzie D'affari E Servizi Commerciali",
    "sg:phone":"+39 059 356905",
    "sg:postcode":"41100",
    "sg:province":"Modena",
    "wof:name":"Bellani Andrea",
    "wof:placetype":"venue"
},
  "geometry": {"coordinates":[10.975072,44.557484],"type":"Point"}
}