{
  "type": "Feature",
  "properties": {
    "iso:country":"IT",
    "sg:address":"4, Via Candiani 22078 Turate",
    "sg:city":"Turate",
    "sg:classifiers":[
        {
            "category":"Home & Garden",
            "subcategory":"Home Furnishings",
            "type":"Retail Goods"
        }
    ],
    "sg:phone":"+39 39029688209",
    "sg:postcode":"22078",
    "sg:province":"Como",
    "sg:tags":[
        "household"
    ],
    "wof:name":"Fratelli Carnelli S.n.c. Di Carnelli Donato & C.",
    "wof:placetype":"venue"
},
  "geometry": {"coordinates":[9.002285,45.653885],"type":"Point"}
}