{
  "type": "Feature",
  "properties": {
    "addr:full":"25124 Brescia Brescia Brescia 25124",
    "addr:postcode":"25124;25124",
    "iso:country":"IT",
    "sg:address":"25124 Brescia",
    "sg:city":"Brescia",
    "sg:orig_category":"Imprese Di Costruzioni Civili Ed Industriali",
    "sg:phone":"+39 030 222535",
    "sg:postcode":"25124",
    "sg:province":"Brescia",
    "sg:website":"http://www.geoteco.com",
    "wof:name":"Geoteco Srl",
    "wof:placetype":"venue"
},
  "geometry": {"coordinates":[10.211746,45.528088],"type":"Point"}
}