{
  "type": "Feature",
  "properties": {
    "iso:country":"IT",
    "sg:address":"70123 Bari",
    "sg:city":"Bari",
    "sg:orig_category":"Serramenti Ed Infissi. Forniture Industriali Per Prevenzione, Controllo E Sicurezza",
    "sg:phone":"+39 080 574 4380",
    "sg:postcode":"70123",
    "sg:province":"Bari",
    "wof:name":"Casa Delle Chiavi Di Vito De Marzo",
    "wof:placetype":"venue"
},
  "geometry": {"coordinates":[16.858635,41.122471],"type":"Point"}
}