{
  "type": "Feature",
  "properties": {
    "addr:full":"47100 Forl\u00ec Forl\u00ec-Cesena 47100",
    "addr:postcode":"47100;47100",
    "iso:country":"IT",
    "sg:address":"47100 Forl\u00ec",
    "sg:orig_category":"Carni, Salumi E Pesci",
    "sg:phone":"+39 0543 701253",
    "sg:postcode":"47100",
    "sg:province":"Forl\u00ec-Cesena",
    "wof:name":"Macelleria - Gastronomia Di Venti",
    "wof:placetype":"venue"
},
  "geometry": {"coordinates":[12.00258,44.277489],"type":"Point"}
}