{
  "type": "Feature",
  "properties": {
    "iso:country":"IT",
    "sg:address":"20090 Segrate",
    "sg:city":"Segrate",
    "sg:orig_category":"Informatica - Consulenza E Servizi. Pubblicita', Marketing E Comunicazione",
    "sg:phone":"+39 02 7039 8398",
    "sg:postcode":"20090",
    "sg:province":"Milano",
    "sg:website":"http://www.microsoft.com/italy/",
    "wof:name":"Microsoft",
    "wof:placetype":"venue"
},
  "geometry": {"coordinates":[9.28811,45.474987],"type":"Point"}
}