{
  "type": "Feature",
  "properties": {
    "iso:country":"IT",
    "sg:address":"31010 Mareno Di Piave",
    "sg:city":"Mareno di Piave",
    "sg:classifiers":[
        {
            "category":"Shopping",
            "subcategory":"Clothing, Apparel, & Fashions",
            "type":"Retail Goods"
        }
    ],
    "sg:phone":"+39 0438 488186",
    "sg:postcode":"31010",
    "sg:province":"Treviso",
    "sg:tags":[
        "clothing",
        "fur",
        "knitwear"
    ],
    "wof:name":"Alexi's Maglieria",
    "wof:placetype":"venue"
},
  "geometry": {"coordinates":[12.306199,45.819557],"type":"Point"}
}