{
  "type": "Feature",
  "properties": {
    "iso:country":"IT",
    "sg:address":"16042 Carasco",
    "sg:city":"Carasco",
    "sg:orig_category":"Elettronica Professionale E Di Consumo. Forniture Per Il Settore Dello Spettacolo. Automazione E Macchine Per Ufficio. Forniture Per Congressi, Fiere E Manifestazioni",
    "sg:phone":"+39 0185 350081",
    "sg:postcode":"16042",
    "sg:province":"Genova",
    "wof:name":"Artemusica Di Fulvio Fusaro",
    "wof:placetype":"venue"
},
  "geometry": {"coordinates":[9.361758,44.358757],"type":"Point"}
}