{
  "type": "Feature",
  "properties": {
    "addr:full":"157, Strada Corletto 41100 Modena Modena Modena 41100",
    "addr:postcode":"41100;41100",
    "addr:street":"Strada Corletto",
    "iso:country":"IT",
    "sg:address":"157, Strada Corletto 41100 Modena",
    "sg:city":"Modena",
    "sg:classifiers":[
        {
            "category":"Parking",
            "subcategory":"Lot",
            "type":"Transportation"
        }
    ],
    "sg:phone":"+39 39059848652",
    "sg:postcode":"41100",
    "sg:province":"Modena",
    "sg:tags":[
        "transport",
        "road"
    ],
    "wof:name":"Emiliana Traslochi (s.n.c.)",
    "wof:placetype":"venue"
},
  "geometry": {"coordinates":[10.846038,44.632042],"type":"Point"}
}