{
  "type": "Feature",
  "properties": {
    "iso:country":"IT",
    "sg:address":"37, Via Stendardi 70059 Trani",
    "sg:city":"Trani",
    "sg:classifiers":[
        {
            "category":"Personal",
            "subcategory":"Shoe Repair & Shine",
            "type":"Services"
        }
    ],
    "sg:phone":"+39 0883 507945",
    "sg:postcode":"70059",
    "sg:province":"Bari",
    "sg:tags":[
        "leather"
    ],
    "wof:name":"Calzaturificio Top Moda Srl",
    "wof:placetype":"venue"
},
  "geometry": {"coordinates":[16.414734,41.275852],"type":"Point"}
}