{
  "type": "Feature",
  "properties": {
    "iso:country":"IT",
    "sg:address":"55019 Villa Basilica",
    "sg:city":"Villa Basilica",
    "sg:orig_category":"Carta, Cartone E Prodotti Primari. Forniture Per Uffici",
    "sg:phone":"+39 0572 43413",
    "sg:postcode":"55019",
    "sg:province":"Lucca",
    "wof:name":"Cartiera Della Madonnina Spa",
    "wof:placetype":"venue"
},
  "geometry": {"coordinates":[10.653575,43.943363],"type":"Point"}
}