{
  "type": "Feature",
  "properties": {
    "addr:full":"Via Strozzi 41 59013 Montemurlo Montemurlo Prato 59013",
    "addr:housenumber":"41",
    "addr:postcode":"59013;59013",
    "addr:street":"Via Strozzi",
    "iso:country":"IT",
    "sg:address":"Via Strozzi 41 59013 Montemurlo",
    "sg:city":"Montemurlo",
    "sg:orig_category":"Ladies' Coats",
    "sg:phone":"+39 0574 682930",
    "sg:postcode":"59013",
    "sg:province":"Prato",
    "sg:website":"www.verdepiu.it",
    "wof:name":"Verde Piu' Spa",
    "wof:placetype":"venue"
},
  "geometry": {"coordinates":[11.096028,43.885307],"type":"Point"}
}