{
  "type": "Feature",
  "properties": {
    "addr:full":"15, Via Faidana 25065 Lumezzane Lumezzane Brescia 25065",
    "addr:postcode":"25065;25065",
    "addr:street":"Via Faidana",
    "iso:country":"IT",
    "sg:address":"15, Via Faidana 25065 Lumezzane",
    "sg:city":"Lumezzane",
    "sg:classifiers":[
        {
            "category":"Manufacturing",
            "subcategory":"Metals",
            "type":"Manufacturing & Wholesale Goods"
        }
    ],
    "sg:phone":"+39 39030827805",
    "sg:postcode":"25065",
    "sg:province":"Brescia",
    "sg:tags":[
        "processing"
    ],
    "wof:name":"Giulipas Srl",
    "wof:placetype":"venue"
},
  "geometry": {"coordinates":[10.2635469437,45.6446342468],"type":"Point"}
}