{
  "type": "Feature",
  "properties": {
    "iso:country":"IT",
    "sg:address":"84083 Castel San Giorgio",
    "sg:city":"Castel San Giorgio",
    "sg:orig_category":"Bevande, Vini E Liquori",
    "sg:phone":"+39 081 516 1719",
    "sg:postcode":"84083",
    "sg:province":"Salerno",
    "wof:name":"Tecno Forniture Di Russo E Pergamo Snc",
    "wof:placetype":"venue"
},
  "geometry": {"coordinates":[14.709239,40.780251],"type":"Point"}
}