{
  "type": "Feature",
  "properties": {
    "addr:full":"20122 Milano Milano Milano 20122",
    "addr:postcode":"20122;20122",
    "iso:country":"IT",
    "sg:address":"20122 Milano",
    "sg:city":"Milano",
    "sg:orig_category":"Centri Di Estetica E Cosmesi E Servizi",
    "sg:phone":"+39 02 5831 6131",
    "sg:postcode":"20122",
    "sg:province":"Milano",
    "wof:name":"Cataldo Maria Gabriella",
    "wof:placetype":"venue"
},
  "geometry": {"coordinates":[9.192936,45.453568],"type":"Point"}
}