{
  "type": "Feature",
  "properties": {
    "iso:country":"IT",
    "sg:address":"22012 Cernobbio",
    "sg:city":"Cernobbio",
    "sg:orig_category":"Congressi E Conferenze - Sedi E Centri",
    "sg:phone":"+39 0313491",
    "sg:postcode":"22012",
    "sg:province":"Como",
    "sg:website":"http://www.villaerba.it",
    "wof:name":"Villa Erba Spa",
    "wof:placetype":"venue"
},
  "geometry": {"coordinates":[9.073126,45.835636],"type":"Point"}
}