{
  "type": "Feature",
  "properties": {
    "addr:full":"06039 Trevi Trevi Perugia 06039",
    "addr:postcode":"06039;06039",
    "iso:country":"IT",
    "sg:address":"06039 Trevi",
    "sg:city":"Trevi",
    "sg:orig_category":"Funghi E Tartufi",
    "sg:phone":"+39 0742 386000",
    "sg:postcode":"06039",
    "sg:province":"Perugia",
    "wof:name":"Cooperativa Agricola Trevi Arl",
    "wof:placetype":"venue"
},
  "geometry": {"coordinates":[12.7364959717,42.8675880432],"type":"Point"}
}