{
  "type": "Feature",
  "properties": {
    "addr:full":"25127 Brescia Brescia Brescia 25127",
    "addr:postcode":"25127;25127",
    "iso:country":"IT",
    "sg:address":"25127 Brescia",
    "sg:city":"Brescia",
    "sg:orig_category":"Elettrotecnica Industriale, Prodotti E Apparecchiature",
    "sg:phone":"+39 030 311051",
    "sg:postcode":"25127",
    "sg:province":"Brescia",
    "sg:website":"http://www.orsattiathos.it",
    "wof:name":"Orsatti Athos & C. Elettrotecnica Srl",
    "wof:placetype":"venue"
},
  "geometry": {"coordinates":[10.195288,45.557018],"type":"Point"}
}