{
  "type": "Feature",
  "properties": {
    "iso:country":"IT",
    "sg:address":"24050 Spirano",
    "sg:city":"Spirano",
    "sg:orig_category":"Arredamenti E Mobili Professionali. Arredi Ed Attrezzature Per Attivita' Commerciali Ed Artigianali",
    "sg:phone":"+39 035 876432",
    "sg:postcode":"24050",
    "sg:province":"Bergamo",
    "sg:website":"http://www.lamondialarreda.com",
    "wof:name":"La Mondial Arreda Srl",
    "wof:placetype":"venue"
},
  "geometry": {"coordinates":[9.662219,45.595497],"type":"Point"}
}