{
  "type": "Feature",
  "properties": {
    "addr:full":"Via E. Fermi 2/a 62010 Montelupone Montelupone Macerata 62010",
    "addr:housenumber":"2 / a",
    "addr:postcode":"62010;62010",
    "addr:street":"Via E. Fermi",
    "iso:country":"IT",
    "sg:address":"Via E. Fermi 2/a 62010 Montelupone",
    "sg:city":"Montelupone",
    "sg:classifiers":[
        {
            "category":"Manufacturing",
            "subcategory":"Building Materials",
            "type":"Manufacturing & Wholesale Goods"
        }
    ],
    "sg:phone":"+39 0733 225311",
    "sg:postcode":"62010",
    "sg:province":"Macerata",
    "sg:tags":[
        "cement"
    ],
    "sg:website":"www.cementor.com",
    "wof:name":"Cementor Srl",
    "wof:placetype":"venue"
},
  "geometry": {"coordinates":[13.478893,43.356831],"type":"Point"}
}