{
  "type": "Feature",
  "properties": {
    "addr:full":"20089 Rozzano Rozzano Milano 20089",
    "addr:postcode":"20089;20089",
    "iso:country":"IT",
    "sg:address":"20089 Rozzano",
    "sg:city":"Rozzano",
    "sg:orig_category":"Pubblicita', Marketing E Comunicazione",
    "sg:phone":"+39 02 892 5951",
    "sg:postcode":"20089",
    "sg:province":"Milano",
    "sg:website":"http://www.acomunication.com",
    "wof:name":"A.a. Comunication",
    "wof:placetype":"venue"
},
  "geometry": {"coordinates":[9.168964386,45.3800964355],"type":"Point"}
}