{
  "type": "Feature",
  "properties": {
    "addr:full":"59100 Prato Prato Prato 59100",
    "addr:postcode":"59100;59100",
    "iso:country":"IT",
    "sg:address":"59100 Prato",
    "sg:city":"Prato",
    "sg:orig_category":"Forniture Per Abbigliamento E Pelletterie",
    "sg:phone":"+39 0574 814713",
    "sg:postcode":"59100",
    "sg:province":"Prato",
    "wof:name":"Recofibre Srl",
    "wof:placetype":"venue"
},
  "geometry": {"coordinates":[11.0532445908,43.8845558167],"type":"Point"}
}