{
  "type": "Feature",
  "properties": {
    "addr:full":"00155 Roma Roma Roma 00155",
    "addr:postcode":"00155;00155",
    "iso:country":"IT",
    "sg:address":"00155 Roma",
    "sg:city":"Roma",
    "sg:orig_category":"Cartolerie",
    "sg:phone":"+39 06 406 3674",
    "sg:postcode":"00155",
    "sg:province":"Roma",
    "wof:name":"C.t.d. Sas",
    "wof:placetype":"venue"
},
  "geometry": {"coordinates":[12.567016,41.908978],"type":"Point"}
}