{
  "type": "Feature",
  "properties": {
    "iso:country":"IT",
    "sg:address":"00132 Roma",
    "sg:city":"Roma",
    "sg:classifiers":[
        {
            "category":"Utilities",
            "subcategory":"Refuse",
            "type":"Services"
        }
    ],
    "sg:phone":"+39 06 207 3033",
    "sg:postcode":"00132",
    "sg:province":"Roma",
    "sg:tags":[
        "auxiliary",
        "disposal",
        "surveillance",
        "environmental",
        "protection",
        "cleaning",
        "maintenance",
        "works"
    ],
    "wof:name":"Italservizi 2000 Srl",
    "wof:placetype":"venue"
},
  "geometry": {"coordinates":[12.6947,41.863499],"type":"Point"}
}