{
  "type": "Feature",
  "properties": {
    "iso:country":"IT",
    "sg:address":"Via Disciplina 7a 37036 San Martino Buon Albergo",
    "sg:city":"San Martino Buon Albergo",
    "sg:orig_category":"Hoisiery Goods",
    "sg:phone":"+39 045 992500",
    "sg:postcode":"37036",
    "sg:province":"Verona",
    "wof:name":"Piu' Di Ghidoni Giorgio",
    "wof:placetype":"venue"
},
  "geometry": {"coordinates":[11.089754,45.420574],"type":"Point"}
}