{
  "type": "Feature",
  "properties": {
    "addr:full":"25, Via De' Bonomini 41100 Modena Modena Modena 41100",
    "addr:postcode":"41100;41100",
    "addr:street":"Via De ' Bonomini",
    "iso:country":"IT",
    "sg:address":"25, Via De' Bonomini 41100 Modena",
    "sg:city":"Modena",
    "sg:classifiers":[
        {
            "category":"Sports & Exercise",
            "subcategory":"Playing Field",
            "type":"Entertainment"
        }
    ],
    "sg:phone":"+39 39059243404",
    "sg:postcode":"41100",
    "sg:province":"Modena",
    "sg:tags":[
        "game"
    ],
    "wof:name":"Brunetti Marco & C. S.a.s.",
    "wof:placetype":"venue"
},
  "geometry": {"coordinates":[10.934687,44.652851],"type":"Point"}
}