{
  "type": "Feature",
  "properties": {
    "iso:country":"IT",
    "sg:address":"20063 Cernusco Sul Naviglio",
    "sg:city":"Cernusco sul Naviglio",
    "sg:orig_category":"Forniture E Prodotti Informatici. Forniture Per Uffici",
    "sg:phone":"+39 02 9210 1497",
    "sg:postcode":"20063",
    "sg:province":"Milano",
    "wof:name":"Epsilon Computer & Office Srl",
    "wof:placetype":"venue"
},
  "geometry": {"coordinates":[9.3385305405,45.5026741028],"type":"Point"}
}