{
  "type": "Feature",
  "properties": {
    "iso:country":"IT",
    "sg:address":"31040 Paese",
    "sg:orig_category":"Autogru - Noleggio",
    "sg:phone":"+39 0422 483553",
    "sg:postcode":"31040",
    "sg:province":"Treviso",
    "wof:name":"Autotrasporti M.t. Srl",
    "wof:placetype":"venue"
},
  "geometry": {"coordinates":[12.129385,45.735214],"type":"Point"}
}