{
  "type": "Feature",
  "properties": {
    "addr:full":"35011 Campodarsego Campodarsego Padova 35011",
    "addr:postcode":"35011;35011",
    "iso:country":"IT",
    "sg:address":"35011 Campodarsego",
    "sg:city":"Campodarsego",
    "sg:orig_category":"Forniture Per Edilizia E Lavori Pubblici. Forniture Industriali Per Prevenzione, Controllo E Sicurezza",
    "sg:phone":"+39 049 920 0422",
    "sg:postcode":"35011",
    "sg:province":"Padova",
    "wof:name":"A.p.i. Sas Di Dall'aglio & C.",
    "wof:placetype":"venue"
},
  "geometry": {"coordinates":[11.9137172699,45.468536377],"type":"Point"}
}