{
  "type": "Feature",
  "properties": {
    "iso:country":"IT",
    "sg:address":"22100 Como",
    "sg:city":"Como",
    "sg:orig_category":"Macchine Utensili E Impianti",
    "sg:phone":"+39 031 520235",
    "sg:postcode":"22100",
    "sg:province":"Como",
    "wof:name":"C.i.f.e.s. Srl",
    "wof:placetype":"venue"
},
  "geometry": {"coordinates":[9.06769,45.781071],"type":"Point"}
}