{
  "type": "Feature",
  "properties": {
    "addr:full":"20162 Milano Milano Milano 20162",
    "addr:postcode":"20162;20162",
    "iso:country":"IT",
    "sg:address":"20162 Milano",
    "sg:city":"Milano",
    "sg:orig_category":"Servizi E Lavori Per Abbigliamento E Pelletterie",
    "sg:postcode":"20162",
    "sg:province":"Milano",
    "wof:name":"Rosina F.lli (s.p.a.)",
    "wof:placetype":"venue"
},
  "geometry": {"coordinates":[9.1956672668,45.5192680359],"type":"Point"}
}