{
  "type": "Feature",
  "properties": {
    "iso:country":"IT",
    "sg:address":"00146 Roma",
    "sg:city":"Roma",
    "sg:orig_category":"Ospedali E Servizi Sanitari",
    "sg:phone":"+39 06 558 4759",
    "sg:postcode":"00146",
    "sg:province":"Roma",
    "wof:name":"Marino Francesco",
    "wof:placetype":"venue"
},
  "geometry": {"coordinates":[12.473534,41.856564],"type":"Point"}
}