{
  "type": "Feature",
  "properties": {
    "iso:country":"IT",
    "sg:address":"25, Via Liguria 10071 Borgaro Torinese",
    "sg:city":"Borgaro Torinese",
    "sg:classifiers":[
        {
            "category":"Manufacturing",
            "subcategory":"Glass & Minerals",
            "type":"Manufacturing & Wholesale Goods"
        }
    ],
    "sg:phone":"+39 011 407 8311",
    "sg:postcode":"10071",
    "sg:province":"Torino",
    "wof:name":"Cilvea S.p.a.",
    "wof:placetype":"venue"
},
  "geometry": {"coordinates":[7.658708,45.139343],"type":"Point"}
}