{
  "type": "Feature",
  "properties": {
    "iso:country":"IT",
    "sg:address":"42100 Reggio Emilia",
    "sg:orig_category":"Dolciumi E Gelati",
    "sg:phone":"+39 0522 518340",
    "sg:postcode":"42100",
    "sg:province":"Reggio Nell'Emilia",
    "wof:name":"Predolci Srl",
    "wof:placetype":"venue"
},
  "geometry": {"coordinates":[10.652228,44.735054],"type":"Point"}
}