{
  "type": "Feature",
  "properties": {
    "iso:country":"IT",
    "sg:address":"24030 Medolago",
    "sg:city":"Medolago",
    "sg:orig_category":"Servizi E Lavori Per Edilizia E Lavori Pubblici. Acqua, Luce, Gas E Societa' Di Esercizio Pubblico",
    "sg:phone":"+39 035 494 8876",
    "sg:postcode":"24030",
    "sg:province":"Bergamo",
    "wof:name":"S.i.a. Reti S.r.l.",
    "wof:placetype":"venue"
},
  "geometry": {"coordinates":[9.496722,45.669537],"type":"Point"}
}