{
  "type": "Feature",
  "properties": {
    "addr:full":"5/7, Via Primo Maggio 36040 Torri Di Quartesolo Torri di Quartesolo Vicenza 36040",
    "addr:housenumber":"5 / 7",
    "addr:postcode":"36040;36040",
    "addr:street":"Via Primo Maggio",
    "iso:country":"IT",
    "sg:address":"5/7, Via Primo Maggio 36040 Torri Di Quartesolo",
    "sg:city":"Torri di Quartesolo",
    "sg:classifiers":[
        {
            "category":"Wholesale",
            "subcategory":"Machinery & Supplies",
            "type":"Manufacturing & Wholesale Goods"
        }
    ],
    "sg:phone":"+39 0444 580343",
    "sg:postcode":"36040",
    "sg:province":"Vicenza",
    "sg:tags":[
        "-",
        "agriculture",
        "equipment"
    ],
    "wof:name":"Irrigazione Veneta (s.r.l.)",
    "wof:placetype":"venue"
},
  "geometry": {"coordinates":[11.606361,45.517265],"type":"Point"}
}