{
  "type": "Feature",
  "properties": {
    "iso:country":"IT",
    "sg:address":"84025 Eboli",
    "sg:city":"Eboli",
    "sg:orig_category":"Cravatte, Sciarpe E Foulards",
    "sg:phone":"+39 0828 365037",
    "sg:postcode":"84025",
    "sg:province":"Salerno",
    "sg:website":"http://www.dinoventre.it",
    "wof:name":"Euro Confezioni Di Ventrucci Claudino",
    "wof:placetype":"venue"
},
  "geometry": {"coordinates":[14.96225,40.522766],"type":"Point"}
}