{
  "type": "Feature",
  "properties": {
    "addr:full":"4, Via Filippini 61032 Fano Fano Pesaro E Urbino 61032",
    "addr:postcode":"61032;61032",
    "addr:street":"Via Filippini",
    "iso:country":"IT",
    "sg:address":"4, Via Filippini 61032 Fano",
    "sg:city":"Fano",
    "sg:classifiers":[
        {
            "category":"Manufacturing",
            "subcategory":"Metals",
            "type":"Manufacturing & Wholesale Goods"
        }
    ],
    "sg:phone":"+39 39072185681",
    "sg:postcode":"61032",
    "sg:province":"Pesaro E Urbino",
    "sg:tags":[
        "metallurgy",
        "metalworking"
    ],
    "wof:name":"Eurotubi S.r.l.",
    "wof:placetype":"venue"
},
  "geometry": {"coordinates":[13.0091152191,43.792640686],"type":"Point"}
}