{
  "type": "Feature",
  "properties": {
    "iso:country":"IT",
    "sg:address":"12041 Bene Vagienna",
    "sg:city":"Bene Vagienna",
    "sg:orig_category":"Marmo Ed Affini - Lavorazione",
    "sg:phone":"+39 0172 654030",
    "sg:postcode":"12041",
    "sg:province":"Cuneo",
    "wof:name":"Blangetti Michele Mosart Antiqua",
    "wof:placetype":"venue"
},
  "geometry": {"coordinates":[7.81776,44.536259],"type":"Point"}
}