{
  "type": "Feature",
  "properties": {
    "iso:country":"IT",
    "sg:address":"Via Antoniana 35011 Campodarsego",
    "sg:city":"Campodarsego",
    "sg:classifiers":[
        {
            "category":"Wholesale",
            "subcategory":"Machinery & Supplies",
            "type":"Manufacturing & Wholesale Goods"
        }
    ],
    "sg:phone":"+39 049 556 5282",
    "sg:postcode":"35011",
    "sg:province":"Padova",
    "sg:tags":[
        "-",
        "agriculture",
        "equipment"
    ],
    "wof:name":"Gaiani",
    "wof:placetype":"venue"
},
  "geometry": {"coordinates":[11.907006,45.50288],"type":"Point"}
}