{
  "type": "Feature",
  "properties": {
    "addr:full":"26, Via Canova 35015 Galliera Veneta Galliera Veneta Padova 35015",
    "addr:postcode":"35015;35015",
    "addr:street":"Via Canova",
    "iso:country":"IT",
    "sg:address":"26, Via Canova 35015 Galliera Veneta",
    "sg:city":"Galliera Veneta",
    "sg:classifiers":[
        {
            "category":"Shopping",
            "subcategory":"Clothing, Apparel, & Fashions",
            "type":"Retail Goods"
        }
    ],
    "sg:phone":"+39 049 596 5241",
    "sg:postcode":"35015",
    "sg:province":"Padova",
    "sg:tags":[
        "clothes"
    ],
    "wof:name":"Berno",
    "wof:placetype":"venue"
},
  "geometry": {"coordinates":[11.825615,45.672016],"type":"Point"}
}