{
  "type": "Feature",
  "properties": {
    "iso:country":"IT",
    "sg:address":"7, Via Santino E Pompeo Mazzucchelli 21043 Castiglione Olona",
    "sg:city":"Castiglione Olona",
    "sg:classifiers":[
        {
            "category":"Manufacturing",
            "subcategory":"Rubber & Plastics",
            "type":"Manufacturing & Wholesale Goods"
        }
    ],
    "sg:phone":"+39 0331 858989",
    "sg:postcode":"21043",
    "sg:province":"Varese",
    "wof:name":"Sinteco Srl Industria Italiana Plastica",
    "wof:placetype":"venue"
},
  "geometry": {"coordinates":[8.8263845444,45.8176040649],"type":"Point"}
}