{
  "type": "Feature",
  "properties": {
    "iso:country":"IT",
    "sg:address":"19126 La Spezia",
    "sg:orig_category":"Motori Ed Organi Di Trasmissione. Ricambi E Componenti Dei Mezzi Di Trasporto",
    "sg:phone":"+39 0187 511546",
    "sg:province":"SP",
    "wof:name":"C.c.c.u. Sas",
    "wof:placetype":"venue"
},
  "geometry": {"coordinates":[9.8570642471,44.110294342],"type":"Point"}
}