{
  "type": "Feature",
  "properties": {
    "iso:country":"IT",
    "sg:address":"52011 Bibbiena",
    "sg:city":"Bibbiena",
    "sg:orig_category":"Lavorazioni Metalli, Stampaggio E Saldatura",
    "sg:phone":"+39 0575 560231",
    "sg:postcode":"52011",
    "sg:province":"Arezzo",
    "sg:website":"http://www.bendoni.it",
    "wof:name":"Bendoni Inox Srl",
    "wof:placetype":"venue"
},
  "geometry": {"coordinates":[11.811715,43.730755],"type":"Point"}
}