{
  "type": "Feature",
  "properties": {
    "iso:country":"IT",
    "sg:address":"20162 Milano",
    "sg:city":"Milano",
    "sg:orig_category":"Materiali E Componenti Elettrotecnici",
    "sg:phone":"+39 02 642 4633",
    "sg:postcode":"20162",
    "sg:province":"Milano",
    "wof:name":"Officina Elettromeccanica Preti Di Preti Marco",
    "wof:placetype":"venue"
},
  "geometry": {"coordinates":[9.252447,45.529617],"type":"Point"}
}