{
  "type": "Feature",
  "properties": {
    "iso:country":"IT",
    "sg:address":"81100 Caserta",
    "sg:city":"Caserta",
    "sg:orig_category":"Metalli E Leghe",
    "sg:phone":"+39 0823 328821",
    "sg:postcode":"81100",
    "sg:province":"Caserta",
    "wof:name":"Fisac-cgil",
    "wof:placetype":"venue"
},
  "geometry": {"coordinates":[14.328994751,41.0691947937],"type":"Point"}
}