{
  "type": "Feature",
  "properties": {
    "iso:country":"IT",
    "sg:address":"8, Via Maroncelli Pietro 20154 Milano",
    "sg:city":"Milano",
    "sg:classifiers":[
        {
            "category":"Wholesale",
            "subcategory":"Machinery & Supplies",
            "type":"Manufacturing & Wholesale Goods"
        }
    ],
    "sg:phone":"+39 39026590974",
    "sg:postcode":"20154",
    "sg:province":"Milano",
    "sg:tags":[
        "equipment",
        "precision"
    ],
    "wof:name":"Open (s.r.l.)",
    "wof:placetype":"venue"
},
  "geometry": {"coordinates":[9.1836042404,45.4826126099],"type":"Point"}
}