{
  "type": "Feature",
  "properties": {
    "addr:full":"Via Guido Rossa 20 51037 Montale Montale Pistoia 51037",
    "addr:housenumber":"20",
    "addr:postcode":"51037;51037",
    "addr:street":"Via Guido Rossa",
    "iso:country":"IT",
    "sg:address":"Via Guido Rossa 20 51037 Montale",
    "sg:city":"Montale",
    "sg:classifiers":[
        {
            "category":"Shopping",
            "subcategory":"Clothing, Apparel, & Fashions",
            "type":"Retail Goods"
        }
    ],
    "sg:phone":"+39 0573 95851",
    "sg:postcode":"51037",
    "sg:province":"Pistoia",
    "sg:tags":[
        "clothing",
        "fabric"
    ],
    "wof:name":"Master Loom Spa",
    "wof:placetype":"venue"
},
  "geometry": {"coordinates":[11.019257,43.90696],"type":"Point"}
}