{
  "type": "Feature",
  "properties": {
    "addr:full":"35043 Monselice Monselice Padova 35043",
    "addr:postcode":"35043;35043",
    "iso:country":"IT",
    "sg:address":"35043 Monselice",
    "sg:city":"Monselice",
    "sg:orig_category":"Scuole E Servizi Scolastici",
    "sg:phone":"+39 0429 72056",
    "sg:postcode":"35043",
    "sg:province":"Padova",
    "wof:name":"Istituto Sorelle Della Misericordia",
    "wof:placetype":"venue"
},
  "geometry": {"coordinates":[11.745,45.189869],"type":"Point"}
}