{
  "type": "Feature",
  "properties": {
    "addr:full":"Frazione Caseppa 10090 Rivalba Rivalba Torino 10090",
    "addr:postcode":"10090;10090",
    "addr:street":"Frazione Caseppa",
    "iso:country":"IT",
    "sg:address":"Frazione Caseppa 10090 Rivalba",
    "sg:city":"Rivalba",
    "sg:classifiers":[
        {
            "category":"Government",
            "subcategory":"Fire Station",
            "type":"Public Place"
        }
    ],
    "sg:phone":"+39 011 960 4525",
    "sg:postcode":"10090",
    "sg:province":"Torino",
    "sg:tags":[
        "brass",
        "working"
    ],
    "wof:name":"Officine Mecchaniche Di Musso Armando & C. S.a.s",
    "wof:placetype":"venue"
},
  "geometry": {"coordinates":[7.686619,45.07056],"type":"Point"}
}