{
  "type": "Feature",
  "properties": {
    "addr:full":"17, V. Romagna 41053 Maranello Maranello Modena 41053",
    "addr:housenumber":"17",
    "addr:postcode":"41053;41053",
    "addr:street":"V. Romagna",
    "iso:country":"IT",
    "sg:address":"17, V. Romagna 41053 Maranello",
    "sg:city":"Maranello",
    "sg:classifiers":[
        {
            "category":"Professional",
            "subcategory":"Engineering",
            "type":"Services"
        }
    ],
    "sg:phone":"+39 0536 942222",
    "sg:postcode":"41053",
    "sg:province":"Modena",
    "sg:tags":[
        "machine",
        "-",
        "mechanical"
    ],
    "wof:name":"Sertam Srl",
    "wof:placetype":"venue"
},
  "geometry": {"coordinates":[10.877491,44.531876],"type":"Point"}
}