{
  "type": "Feature",
  "properties": {
    "addr:full":"Via Provaglia Bartolomeo 5 40138 Bologna Bologna Bologna 40138",
    "addr:housenumber":"5",
    "addr:postcode":"40138;40138",
    "addr:street":"Via Provaglia Bartolomeo",
    "iso:country":"IT",
    "sg:address":"Via Provaglia Bartolomeo 5 40138 Bologna",
    "sg:city":"Bologna",
    "sg:classifiers":[
        {
            "category":"Ice Cream",
            "type":"Food & Drink"
        }
    ],
    "sg:phone":"+39 051 538818",
    "sg:postcode":"40138",
    "sg:province":"Bologna",
    "sg:tags":[
        "seed",
        "beet",
        "sugar"
    ],
    "sg:website":"www.danisco.com",
    "wof:name":"Danisco Seed Italia Spa",
    "wof:placetype":"venue"
},
  "geometry": {"coordinates":[11.346481,44.494221],"type":"Point"}
}