{
  "type": "Feature",
  "properties": {
    "iso:country":"IT",
    "sg:address":"Via Della Resistenza 1 C; Entracque; 12010",
    "sg:city":"Entracque",
    "sg:classifiers":[
        {
            "category":"Banks & Credit Unions",
            "subcategory":"Bank",
            "type":"Services"
        }
    ],
    "sg:phone":"+39 0171 978148",
    "sg:postcode":"12010",
    "sg:province":"Cuneo",
    "wof:name":"Cassa Di Risparmio Di Cuneo",
    "wof:placetype":"venue"
},
  "geometry": {"coordinates":[7.397345,44.239227],"type":"Point"}
}