{
  "type": "Feature",
  "properties": {
    "addr:full":"24060 Castelli Calepio Castelli Calepio Bergamo 24060",
    "addr:postcode":"24060;24060",
    "iso:country":"IT",
    "sg:address":"24060 Castelli Calepio",
    "sg:city":"Castelli Calepio",
    "sg:orig_category":"Automazione E Macchine Per Ufficio",
    "sg:phone":"+39 035 442 5380",
    "sg:postcode":"24060",
    "sg:province":"Bergamo",
    "wof:name":"Bellotti Di Bellotti & C. Sas",
    "wof:placetype":"venue"
},
  "geometry": {"coordinates":[9.903907,45.638981],"type":"Point"}
}