{
  "type": "Feature",
  "properties": {
    "iso:country":"IT",
    "sg:address":"35010 Borgoricco",
    "sg:city":"Borgoricco",
    "sg:orig_category":"Articoli Pulizia",
    "sg:phone":"+39 049 933 5267",
    "sg:postcode":"35010",
    "sg:province":"Padova",
    "wof:name":"Montagni Fratelli (s.r.l.)",
    "wof:placetype":"venue"
},
  "geometry": {"coordinates":[11.8822803497,45.4047927856],"type":"Point"}
}