{
  "type": "Feature",
  "properties": {
    "addr:full":"130, Via Alcide Degasperi 38023 Cles Cles Trento 38023",
    "addr:housenumber":"130",
    "addr:postcode":"38023;38023",
    "addr:street":"Via Alcide Degasperi",
    "iso:country":"IT",
    "sg:address":"130, Via Alcide Degasperi 38023 Cles",
    "sg:city":"Cles",
    "sg:classifiers":[
        {
            "category":"Shopping",
            "subcategory":"Computers & Home Electronics",
            "type":"Retail Goods"
        }
    ],
    "sg:phone":"+39 0463 422511",
    "sg:postcode":"38023",
    "sg:province":"Trento",
    "sg:tags":[
        "electronic",
        "electrical",
        "equipment"
    ],
    "wof:name":"Art. El Di Odorizzi & C. (s.n.c.)",
    "wof:placetype":"venue"
},
  "geometry": {"coordinates":[11.030467,46.358688],"type":"Point"}
}