{
  "type": "Feature",
  "properties": {
    "addr:full":"31, Via Mascheroni Lorenzo 20145 Milano Milano Milano 20145",
    "addr:postcode":"20145;20145",
    "addr:street":"Via Mascheroni Lorenzo",
    "iso:country":"IT",
    "sg:address":"31, Via Mascheroni Lorenzo 20145 Milano",
    "sg:city":"Milano",
    "sg:classifiers":[
        {
            "category":"Communications",
            "subcategory":"Newspaper",
            "type":"Services"
        }
    ],
    "sg:phone":"+39 02 4800 2014",
    "sg:postcode":"20145",
    "sg:province":"Milano",
    "sg:tags":[
        "advertising"
    ],
    "wof:name":"Open House",
    "wof:placetype":"venue"
},
  "geometry": {"coordinates":[9.163189,45.471645],"type":"Point"}
}