{
  "type": "Feature",
  "properties": {
    "iso:country":"IT",
    "sg:address":"71, Via Milano 20021 Bollate",
    "sg:city":"Bollate",
    "sg:classifiers":[
        {
            "category":"Professional",
            "subcategory":"Printing & Photocopies",
            "type":"Services"
        }
    ],
    "sg:phone":"+39 390 233 3331",
    "sg:postcode":"20021",
    "sg:province":"Milano",
    "wof:name":"Mantegazza Antonio Arti Grafiche Srl",
    "wof:placetype":"venue"
},
  "geometry": {"coordinates":[9.1094408035,45.5306854248],"type":"Point"}
}