{
  "type": "Feature",
  "properties": {
    "addr:full":"199, Vl. S. Concordio Lucca 55100",
    "addr:housenumber":"199",
    "addr:postcode":"55100",
    "addr:street":"Vl. S. Concordio Lucca",
    "iso:country":"IT",
    "sg:address":"199, Vl. S. Concordio",
    "sg:classifiers":[
        {
            "category":"Professional",
            "subcategory":"Engineering",
            "type":"Services"
        }
    ],
    "sg:phone":"+39 39058353442",
    "sg:postcode":"55100",
    "sg:province":"Lucca",
    "sg:tags":[
        "machine",
        "-",
        "mechanical"
    ],
    "sg:website":"http://www.phoenixoml.com",
    "wof:name":"Phoenix O.m.l. Srl",
    "wof:placetype":"venue"
},
  "geometry": {"coordinates":[10.507994,43.843014],"type":"Point"}
}