{
  "type": "Feature",
  "properties": {
    "iso:country":"IT",
    "sg:address":"20132 Milano",
    "sg:city":"Milano",
    "sg:orig_category":"Servizi Ausiliari Dei Mezzi Di Trasporto",
    "sg:phone":"+39 02 261 9156",
    "sg:postcode":"20132",
    "sg:province":"Milano",
    "wof:name":"Garage Padova Snc Di Mazzeo Antonio E C.",
    "wof:placetype":"venue"
},
  "geometry": {"coordinates":[9.233536,45.498825],"type":"Point"}
}