{
  "type": "Feature",
  "properties": {
    "iso:country":"IT",
    "sg:address":"20064 Gorgonzola",
    "sg:city":"Gorgonzola",
    "sg:orig_category":"Abbigliamento Esterno, Maglierie E Pelliccerie. Forniture Industriali Per Prevenzione, Controllo E Sicurezza",
    "sg:phone":"+39 02 9513 8354",
    "sg:postcode":"20064",
    "sg:province":"Milano",
    "sg:website":"http://www.euromicron.it",
    "wof:name":"Mi-gi Srl",
    "wof:placetype":"venue"
},
  "geometry": {"coordinates":[9.077447,45.416939],"type":"Point"}
}