{
  "type": "Feature",
  "properties": {
    "addr:full":"20091 Bresso Bresso Milano 20091",
    "addr:postcode":"20091;20091",
    "iso:country":"IT",
    "sg:address":"20091 Bresso",
    "sg:city":"Bresso",
    "sg:orig_category":"Cromatura E Nichelatura",
    "sg:phone":"+39 02 610 1294",
    "sg:postcode":"20091",
    "sg:province":"Milano",
    "wof:name":"Diamant - Cromo Di G. Di Marino Gramazio M & C Snc",
    "wof:placetype":"venue"
},
  "geometry": {"coordinates":[9.197104,45.536858],"type":"Point"}
}