{
  "type": "Feature",
  "properties": {
    "addr:full":"22036 Erba Erba Como 22036",
    "addr:postcode":"22036;22036",
    "iso:country":"IT",
    "sg:address":"22036 Erba",
    "sg:city":"Erba",
    "sg:orig_category":"Servizi E Lavori Per Agricoltura E Zootecnia",
    "sg:phone":"+39 031 611138",
    "sg:postcode":"22036",
    "sg:province":"Como",
    "wof:name":"Co.f.a.zo. (soc.coop.r.l.)",
    "wof:placetype":"venue"
},
  "geometry": {"coordinates":[9.169209,45.797405],"type":"Point"}
}