{
  "type": "Feature",
  "properties": {
    "iso:country":"IT",
    "sg:address":"88040 Settingiano",
    "sg:city":"Settingiano",
    "sg:orig_category":"Servizi E Lavori Per Arredamento E Industria Del Legno. Servizi E Lavori Per Edilizia E Lavori Pubblici",
    "sg:phone":"+39 0961 998694",
    "sg:postcode":"88040",
    "sg:province":"Catanzaro",
    "sg:website":"http://www.desta.it",
    "wof:name":"Dynamis Srl",
    "wof:placetype":"venue"
},
  "geometry": {"coordinates":[16.532049,38.894169],"type":"Point"}
}