{
  "type": "Feature",
  "properties": {
    "iso:country":"IT",
    "sg:address":"00019 Tivoli",
    "sg:city":"Tivoli",
    "sg:orig_category":"Articoli Per Imballaggio E Confezionamento. Forniture Per Uffici. Forniture Per Attivita' Commerciali Ed Artigianali",
    "sg:phone":"+39 0774 318770",
    "sg:postcode":"00019",
    "sg:province":"Roma",
    "wof:name":"Azienda Artigiani Tagliaferri",
    "wof:placetype":"venue"
},
  "geometry": {"coordinates":[12.787416,41.960182],"type":"Point"}
}