{
  "type": "Feature",
  "properties": {
    "iso:country":"IT",
    "sg:address":"00185 Roma",
    "sg:city":"Roma",
    "sg:orig_category":"Servizi Al Turismo. Trasporto Pubblico E Privato. Acqua, Luce, Gas E Societa' Di Esercizio Pubblico. Pubblica Amministrazione",
    "sg:phone":"+39 06 474 1296",
    "sg:postcode":"00185",
    "sg:province":"Roma",
    "wof:name":"Ferrovie Dell Stato Spa - Ufficio Amministrazione E Contabilita'",
    "wof:placetype":"venue"
},
  "geometry": {"coordinates":[12.502387,41.899258],"type":"Point"}
}