{
  "type": "Feature",
  "properties": {
    "iso:country":"IT",
    "sg:address":"665, Via Em. Ponente 48014 Castel Bolognese",
    "sg:city":"Castel Bolognese",
    "sg:classifiers":[
        {
            "category":"Manufacturing",
            "subcategory":"Rubber & Plastics",
            "type":"Manufacturing & Wholesale Goods"
        }
    ],
    "sg:phone":"+39 0546 656377",
    "sg:postcode":"48014",
    "sg:province":"Ravenna",
    "wof:name":"Vetroresina Senio Di Beltrani Valter",
    "wof:placetype":"venue"
},
  "geometry": {"coordinates":[12.1965713501,44.4157295227],"type":"Point"}
}