{
  "type": "Feature",
  "properties": {
    "addr:full":"37053 Cerea Asparetto Verona 37053",
    "addr:postcode":"37053;37053",
    "iso:country":"IT",
    "sg:address":"37053 Cerea",
    "sg:city":"Asparetto",
    "sg:orig_category":"Ferramenta - Produzione",
    "sg:phone":"+39 0442 83777",
    "sg:postcode":"37053",
    "sg:province":"Verona",
    "wof:name":"Metal Style Srl",
    "wof:placetype":"venue"
},
  "geometry": {"coordinates":[11.1813316345,45.2190093994],"type":"Point"}
}