{
  "type": "Feature",
  "properties": {
    "iso:country":"IT",
    "sg:address":"12074 Cortemilia",
    "sg:city":"Cortemilia",
    "sg:orig_category":"Macchine, Impianti Ed Attrezzature Per Agricoltura E Zootecnia",
    "sg:phone":"+39 0173 81013",
    "sg:postcode":"12074",
    "sg:province":"Cuneo",
    "wof:name":"Giordano Snc Di Giordano Angelo C.",
    "wof:placetype":"venue"
},
  "geometry": {"coordinates":[8.149493,44.437191],"type":"Point"}
}