{
  "type": "Feature",
  "properties": {
    "addr:full":"61032 Fano Bellocchi Pesaro E Urbino 61032",
    "addr:postcode":"61032;61032",
    "iso:country":"IT",
    "sg:address":"61032 Fano",
    "sg:city":"Bellocchi",
    "sg:orig_category":"Imprese Di Costruzioni Civili Ed Industriali",
    "sg:phone":"+39 0721 855650",
    "sg:postcode":"61032",
    "sg:province":"Pesaro E Urbino",
    "sg:website":"http://www.mdue.it",
    "wof:name":"Emmedue Srl",
    "wof:placetype":"venue"
},
  "geometry": {"coordinates":[13.004723,43.78616],"type":"Point"}
}