{
  "type": "Feature",
  "properties": {
    "iso:country":"IT",
    "sg:address":"Localita' Frizzone 55012 Capannori",
    "sg:city":"Capannori",
    "sg:classifiers":[
        {
            "category":"Personal",
            "subcategory":"Shoe Repair & Shine",
            "type":"Services"
        }
    ],
    "sg:phone":"+39 0583 980470",
    "sg:postcode":"55012",
    "sg:province":"Lucca",
    "sg:tags":[
        "leather"
    ],
    "wof:name":"A. Forte (s.r.l.)",
    "wof:placetype":"venue"
},
  "geometry": {"coordinates":[10.597688,43.837914],"type":"Point"}
}