{
  "type": "Feature",
  "properties": {
    "iso:country":"IT",
    "sg:address":"67/69, Via Po 20010 Pregnana Milanese",
    "sg:city":"Pregnana Milanese",
    "sg:classifiers":[
        {
            "category":"Autos & Motor Vehicles",
            "subcategory":"Automobile Sales",
            "type":"Retail Goods"
        }
    ],
    "sg:phone":"+39 02 9359 0903",
    "sg:postcode":"20010",
    "sg:province":"Milano",
    "sg:tags":[
        "equipment",
        "transport"
    ],
    "wof:name":"Big Star (s.r.l.)",
    "wof:placetype":"venue"
},
  "geometry": {"coordinates":[9.012698,45.511944],"type":"Point"}
}