{
  "type": "Feature",
  "properties": {
    "iso:country":"IT",
    "sg:address":"28, Via Tagliamento 23900 Lecco",
    "sg:city":"Lecco",
    "sg:classifiers":[
        {
            "category":"Real Estate",
            "subcategory":"Surveying",
            "type":"Services"
        }
    ],
    "sg:phone":"+39 0341 499730",
    "sg:postcode":"23900",
    "sg:province":"Lecco",
    "sg:tags":[
        "equipment",
        "material",
        "good",
        "-",
        "handling"
    ],
    "wof:name":"Bolis Srl",
    "wof:placetype":"venue"
},
  "geometry": {"coordinates":[9.409434,45.856113],"type":"Point"}
}