{
  "type": "Feature",
  "properties": {
    "addr:full":"20030 Lentate Sul Seveso Lentate sul Seveso Milano 20030",
    "addr:postcode":"20030;20030",
    "iso:country":"IT",
    "sg:address":"20030 Lentate Sul Seveso",
    "sg:city":"Lentate sul Seveso",
    "sg:orig_category":"Pizzerie",
    "sg:phone":"+39 036 254 2408",
    "sg:postcode":"20030",
    "sg:province":"Milano",
    "sg:website":"http://www.ilcastellaccio.it",
    "wof:name":"Il Castellaccio Ristorante",
    "wof:placetype":"venue"
},
  "geometry": {"coordinates":[9.1370706558,45.6658821106],"type":"Point"}
}