{
  "type": "Feature",
  "properties": {
    "addr:full":"32, Corso Vittorio Emanuele Ii 46100 Mantova Mantova Mantova 46100",
    "addr:postcode":"46100;46100",
    "addr:street":"Corso Vittorio Emanuele Ii",
    "iso:country":"IT",
    "sg:address":"32, Corso Vittorio Emanuele Ii 46100 Mantova",
    "sg:city":"Mantova",
    "sg:classifiers":[
        {
            "category":"Banks & Credit Unions",
            "subcategory":"Bank",
            "type":"Services"
        }
    ],
    "sg:phone":"+39 0376 369756",
    "sg:postcode":"46100",
    "sg:province":"Mantova",
    "sg:tags":[
        "banking",
        "institution"
    ],
    "wof:name":"Merchant Leasing International Spa",
    "wof:placetype":"venue"
},
  "geometry": {"coordinates":[10.787139,45.157555],"type":"Point"}
}