{
  "type": "Feature",
  "properties": {
    "iso:country":"IT",
    "sg:address":"04014 Pontinia",
    "sg:city":"Pontinia",
    "sg:orig_category":"Calzature, Pelletterie E Pelli",
    "sg:phone":"+39 0773 851374",
    "sg:postcode":"04014",
    "sg:province":"Latina",
    "wof:name":"Eurostruzzi Sas",
    "wof:placetype":"venue"
},
  "geometry": {"coordinates":[13.116374,41.394905],"type":"Point"}
}