{
  "type": "Feature",
  "properties": {
    "iso:country":"IT",
    "sg:address":"21, Viale Majno Luigi 20122 Milano",
    "sg:city":"Milano",
    "sg:classifiers":[
        {
            "category":"Communications",
            "subcategory":"Newspaper",
            "type":"Services"
        }
    ],
    "sg:phone":"+39 390 276 0521",
    "sg:postcode":"20122",
    "sg:province":"Milano",
    "sg:tags":[
        "advertising"
    ],
    "wof:name":"Impiric S.r.l.",
    "wof:placetype":"venue"
},
  "geometry": {"coordinates":[9.205415,45.4702],"type":"Point"}
}