{
  "type": "Feature",
  "properties": {
    "iso:country":"IT",
    "sg:address":"Via Massarotti 76 26100 Cremona",
    "sg:city":"Cremona",
    "sg:orig_category":"Milling And Mixing Plants For Grain",
    "sg:phone":"+39 0372 4011",
    "sg:postcode":"26100",
    "sg:province":"Cremona",
    "sg:website":"www.ocrimspa.com",
    "wof:name":"Ocrim Spa",
    "wof:placetype":"venue"
},
  "geometry": {"coordinates":[10.0073080063,45.1408691406],"type":"Point"}
}