{
  "type": "Feature",
  "properties": {
    "addr:full":"00039 Zagarolo Zagarolo Roma 00039",
    "addr:postcode":"00039;00039",
    "iso:country":"IT",
    "sg:address":"00039 Zagarolo",
    "sg:city":"Zagarolo",
    "sg:orig_category":"Prodotti Alimentari",
    "sg:phone":"+39 06 957 5294",
    "sg:postcode":"00039",
    "sg:province":"Roma",
    "wof:name":"Pizzi Alberto",
    "wof:placetype":"venue"
},
  "geometry": {"coordinates":[12.8169755936,41.8413887024],"type":"Point"}
}