{
  "type": "Feature",
  "properties": {
    "addr:full":"Via Cantu' 6 27029 Vigevano Vigevano Pavia 27029",
    "addr:housenumber":"6",
    "addr:postcode":"27029;27029",
    "addr:street":"Via Cantu '",
    "iso:country":"IT",
    "sg:address":"Via Cantu' 6 27029 Vigevano",
    "sg:city":"Vigevano",
    "sg:classifiers":[
        {
            "category":"Manufacturing",
            "subcategory":"Tools & Machinery",
            "type":"Manufacturing & Wholesale Goods"
        }
    ],
    "sg:phone":"+39 0381 311955",
    "sg:postcode":"27029",
    "sg:province":"Pavia",
    "sg:tags":[
        "making",
        "shoe"
    ],
    "sg:website":"www.besser.it",
    "wof:name":"Besser Officine Spa",
    "wof:placetype":"venue"
},
  "geometry": {"coordinates":[8.847514,45.308361],"type":"Point"}
}