{
  "type": "Feature",
  "properties": {
    "iso:country":"IT",
    "sg:address":"20090 Segrate",
    "sg:city":"Segrate",
    "sg:orig_category":"Lavorazioni Meccaniche E Servizi. Riparazione Dei Mezzi Di Trasporto",
    "sg:phone":"+39 02 213 1525",
    "sg:postcode":"20090",
    "sg:province":"Milano",
    "wof:name":"Guzzeloni Alessandro",
    "wof:placetype":"venue"
},
  "geometry": {"coordinates":[9.300784,45.48558],"type":"Point"}
}