{
  "type": "Feature",
  "properties": {
    "iso:country":"IT",
    "sg:address":"Via Rota Tetto Canale 12100 Cuneo",
    "sg:city":"Cuneo",
    "sg:classifiers":[
        {
            "category":"Autos & Motor Vehicles",
            "subcategory":"Automobile Sales",
            "type":"Retail Goods"
        }
    ],
    "sg:phone":"+39 0171 402191",
    "sg:postcode":"12100",
    "sg:province":"Cuneo",
    "sg:tags":[
        "industrial"
    ],
    "wof:name":"Omars S.p.a.",
    "wof:placetype":"venue"
},
  "geometry": {"coordinates":[7.547111,44.388798],"type":"Point"}
}