{
  "type": "Feature",
  "properties": {
    "iso:country":"IT",
    "sg:address":"63018 Porto Sant'elpidio",
    "sg:orig_category":"Calzature, Pelletterie E Pelli",
    "sg:phone":"+39 0734 901876",
    "sg:postcode":"63018",
    "sg:province":"Ascoli Piceno",
    "sg:website":"http://www.andreacatini.com",
    "wof:name":"Calzaturificio Andrea Catini",
    "wof:placetype":"venue"
},
  "geometry": {"coordinates":[13.751503,43.266956],"type":"Point"}
}