{
  "type": "Feature",
  "properties": {
    "iso:country":"IT",
    "sg:address":"63018 Porto Sant'elpidio",
    "sg:orig_category":"Calzaturifici E Calzolai - Macchine",
    "sg:phone":"+39 0734 991158",
    "sg:postcode":"63018",
    "sg:province":"Ascoli Piceno",
    "wof:name":"F.lli Carnevali & C. Sas",
    "wof:placetype":"venue"
},
  "geometry": {"coordinates":[13.745511,43.236805],"type":"Point"}
}