{
  "type": "Feature",
  "properties": {
    "iso:country":"IT",
    "sg:address":"Via Tempio Del Cielo 3 00144 Roma",
    "sg:city":"Roma",
    "sg:classifiers":[
        {
            "category":"Food & Beverages",
            "subcategory":"Fruits & Vegetables",
            "type":"Retail Goods"
        }
    ],
    "sg:phone":"+39 06 520831",
    "sg:postcode":"00144",
    "sg:province":"Roma",
    "sg:website":"www.chiquita.com",
    "wof:name":"Chiquita Italia Spa",
    "wof:placetype":"venue"
},
  "geometry": {"coordinates":[12.4332113266,41.8072624207],"type":"Point"}
}