{
  "type": "Feature",
  "properties": {
    "addr:full":"61030 Montefelcino Montefelcino Pesaro E Urbino 61030",
    "addr:postcode":"61030;61030",
    "iso:country":"IT",
    "sg:address":"61030 Montefelcino",
    "sg:city":"Montefelcino",
    "sg:orig_category":"Articoli Per Imballaggio E Confezionamento",
    "sg:phone":"+39 0721 743036",
    "sg:postcode":"61030",
    "sg:province":"Pesaro E Urbino",
    "sg:website":"http://www.grossilamiere.it",
    "wof:name":"Grossi Donata - Lavorazione Lamiere",
    "wof:placetype":"venue"
},
  "geometry": {"coordinates":[12.864567,43.715874],"type":"Point"}
}