{
  "type": "Feature",
  "properties": {
    "addr:full":"61010 Tavullia Tavullia Pesaro E Urbino 61010",
    "addr:postcode":"61010;61010",
    "addr:street":"Tavullia Tavullia Pesaro E Urbino",
    "iso:country":"IT",
    "sg:address":"61010 Tavullia",
    "sg:city":"Tavullia",
    "sg:orig_category":"Bagno - Accessori E Mobili",
    "sg:phone":"+39 0721 476130",
    "sg:postcode":"61010",
    "sg:province":"Pesaro E Urbino",
    "wof:name":"Edildue Di Sbrocca Oscar Snc",
    "wof:placetype":"venue"
},
  "geometry": {"coordinates":[12.561426,43.834869],"type":"Point"}
}