{
  "type": "Feature",
  "properties": {
    "iso:country":"IT",
    "sg:address":"80133 Napoli",
    "sg:city":"Napoli",
    "sg:orig_category":"Riparazione Dei Mezzi Di Trasporto. Servizi Ausiliari Dei Mezzi Di Trasporto",
    "sg:phone":"+39 081 554 3187",
    "sg:postcode":"80133",
    "sg:province":"Napoli",
    "wof:name":"S.i.o.m.i. Srl",
    "wof:placetype":"venue"
},
  "geometry": {"coordinates":[14.255583,40.841072],"type":"Point"}
}