{
  "type": "Feature",
  "properties": {
    "iso:country":"IT",
    "sg:address":"2, Via Del Ricreatorio 34100 Trieste",
    "sg:classifiers":[
        {
            "category":"Banks & Credit Unions",
            "subcategory":"Bank",
            "type":"Services"
        }
    ],
    "sg:phone":"+39 040 214 9111",
    "sg:province":"TS",
    "sg:tags":[
        "banking",
        "institution"
    ],
    "wof:name":"Banca Di Credito Cooperativo Del Carso Soc.coop. A R.l.",
    "wof:placetype":"venue"
},
  "geometry": {"coordinates":[13.76709,45.65065],"type":"Point"}
}