{
  "type": "Feature",
  "properties": {
    "addr:full":"56025 Pontedera Pontedera Pisa 56025",
    "addr:postcode":"56025;56025",
    "iso:country":"IT",
    "sg:address":"56025 Pontedera",
    "sg:city":"Pontedera",
    "sg:classifiers":[
        {
            "category":"Manufacturing",
            "subcategory":"Food",
            "type":"Manufacturing & Wholesale Goods"
        }
    ],
    "sg:phone":"+39 0587 52532",
    "sg:postcode":"56025",
    "sg:province":"Pisa",
    "sg:tags":[
        "product"
    ],
    "sg:website":"http://www.pastificiocaponi.it",
    "wof:name":"Pastificio Caponi Di Caponi Roberto & C. Snc",
    "wof:placetype":"venue"
},
  "geometry": {"coordinates":[10.6759767532,43.643699646],"type":"Point"}
}