{
  "type": "Feature",
  "properties": {
    "iso:country":"IT",
    "sg:address":"16, Via Tevere 66020 San Giovanni Teatino",
    "sg:city":"San Giovanni Teatino",
    "sg:classifiers":[
        {
            "category":"Shopping",
            "subcategory":"Stationery & Office Supplies",
            "type":"Retail Goods"
        }
    ],
    "sg:phone":"+39 085 446 1330",
    "sg:postcode":"66020",
    "sg:province":"Chieti",
    "sg:tags":[
        "professional"
    ],
    "wof:name":"Pan Sas Di De Sanctis Giovanni E Davide",
    "wof:placetype":"venue"
},
  "geometry": {"coordinates":[14.1637382507,42.4083061218],"type":"Point"}
}