{
  "type": "Feature",
  "properties": {
    "addr:full":"34134 Trieste Trieste Trieste 34134",
    "addr:postcode":"34134;34134",
    "iso:country":"IT",
    "sg:address":"34134 Trieste",
    "sg:city":"Trieste",
    "sg:orig_category":"Non-classified Establishments",
    "sg:phone":"+39 040 364096",
    "sg:postcode":"34134",
    "sg:province":"Trieste",
    "wof:name":"Seconda Mano'",
    "wof:placetype":"venue"
},
  "geometry": {"coordinates":[13.776085,45.656651],"type":"Point"}
}