{
  "type": "Feature",
  "properties": {
    "iso:country":"IT",
    "sg:address":"10024 Moncalieri",
    "sg:city":"Moncalieri",
    "sg:orig_category":"Recuperi Industriali Vari",
    "sg:phone":"+39 011 640 6281",
    "sg:postcode":"10024",
    "sg:province":"Torino",
    "sg:website":"http://www.pasquero.com",
    "wof:name":"Pasquero Srl",
    "wof:placetype":"venue"
},
  "geometry": {"coordinates":[7.690634,44.995239],"type":"Point"}
}