{
  "type": "Feature",
  "properties": {
    "iso:country":"IT",
    "sg:address":"00193 Roma",
    "sg:city":"Roma",
    "sg:orig_category":"Medicinali E Prodotti Parafarmaceutici",
    "sg:phone":"+39 06 6880 2237",
    "sg:postcode":"00193",
    "sg:province":"Roma",
    "wof:name":"Nanni Dr. Aldo Farmacia",
    "wof:placetype":"venue"
},
  "geometry": {"coordinates":[12.4636802673,41.9056968689],"type":"Point"}
}