{
  "type": "Feature",
  "properties": {
    "iso:country":"IT",
    "sg:address":"40122 Bologna",
    "sg:city":"Bologna",
    "sg:orig_category":"Trasporti E Spedizioni Merci",
    "sg:phone":"+39 051 524646",
    "sg:postcode":"40122",
    "sg:province":"Bologna",
    "wof:name":"City Express Srl",
    "wof:placetype":"venue"
},
  "geometry": {"coordinates":[11.332065,44.501408],"type":"Point"}
}