{
  "type": "Feature",
  "properties": {
    "iso:country":"IT",
    "sg:address":"57022 Castagneto Carducci",
    "sg:city":"Castagneto Carducci",
    "sg:orig_category":"Riparazione Dei Mezzi Di Trasporto",
    "sg:phone":"+39 0565 775321",
    "sg:postcode":"57022",
    "sg:province":"Livorno",
    "wof:name":"Morelli & Bocelli Snc",
    "wof:placetype":"venue"
},
  "geometry": {"coordinates":[10.597136,43.164669],"type":"Point"}
}