{
  "type": "Feature",
  "properties": {
    "iso:country":"IT",
    "sg:address":"16149 Genova",
    "sg:city":"Genova",
    "sg:orig_category":"Autonoleggio",
    "sg:phone":"+39 010 415236",
    "sg:postcode":"16149",
    "sg:province":"Genova",
    "wof:name":"Frattini Autoservizi Di Frattini Paolo",
    "wof:placetype":"venue"
},
  "geometry": {"coordinates":[8.898611,44.409355],"type":"Point"}
}