{
  "type": "Feature",
  "properties": {
    "iso:country":"IT",
    "sg:address":"20060 Ornago",
    "sg:city":"Ornago",
    "sg:orig_category":"Arredi Ed Attrezzature Per Uffici",
    "sg:phone":"+39 039 601 1160",
    "sg:postcode":"20060",
    "sg:province":"Milano",
    "sg:website":"http://www.milanocaffe.it",
    "wof:name":"Milano Caffe' Sas",
    "wof:placetype":"venue"
},
  "geometry": {"coordinates":[9.423265,45.616161],"type":"Point"}
}