{
  "type": "Feature",
  "properties": {
    "addr:full":"39049 Vipiteno Vipiteno Bolzano/Bozen 39049",
    "addr:postcode":"39049;39049",
    "iso:country":"IT",
    "sg:address":"39049 Vipiteno",
    "sg:city":"Vipiteno",
    "sg:classifiers":[
        {
            "category":"Retail",
            "subcategory":"Veterinary Services",
            "type":"Services"
        }
    ],
    "sg:phone":"+39 0472 723111",
    "sg:postcode":"39049",
    "sg:province":"Bolzano/Bozen",
    "sg:tags":[
        "burro"
    ],
    "sg:website":"http://www.bayernland.it",
    "wof:name":"Bayerland Srl",
    "wof:placetype":"venue"
},
  "geometry": {"coordinates":[11.42881,46.885727],"type":"Point"}
}