{
  "type": "Feature",
  "properties": {
    "iso:country":"IT",
    "sg:address":"66032 Castel Frentano",
    "sg:city":"Castel Frentano",
    "sg:orig_category":"Abiti Da Lavoro Ed Indumenti Protettivi",
    "sg:phone":"+39 0872 569332",
    "sg:postcode":"66032",
    "sg:province":"Chieti",
    "wof:name":"Tecnograf Snc",
    "wof:placetype":"venue"
},
  "geometry": {"coordinates":[14.350098,42.197033],"type":"Point"}
}