{
  "type": "Feature",
  "properties": {
    "addr:full":"Via Bertini 7 47100 Forli' Forl\u00ec-Cesena 47100",
    "addr:housenumber":"7",
    "addr:postcode":"47100;47100",
    "addr:street":"Via Bertini;' Forli\u0300-Cesena",
    "iso:country":"IT",
    "sg:address":"Via Bertini 7 47100 Forli'",
    "sg:classifiers":[
        {
            "category":"Building & Trades",
            "subcategory":"Plumbing",
            "type":"Services"
        }
    ],
    "sg:phone":"+39 0543 722240",
    "sg:postcode":"47100",
    "sg:province":"Forl\u00ec-Cesena",
    "sg:tags":[
        "tank"
    ],
    "sg:website":"www.chiodino.it",
    "wof:name":"Chiodino Amelio & C. Snc",
    "wof:placetype":"venue"
},
  "geometry": {"coordinates":[12.06181,44.222431],"type":"Point"}
}