{
  "type": "Feature",
  "properties": {
    "iso:country":"IT",
    "sg:address":"20068 Peschiera Borromeo",
    "sg:city":"Peschiera Borromeo",
    "sg:orig_category":"Forniture Per Abbigliamento E Pelletterie. Complementi Di Arredamento",
    "sg:phone":"+39 02 5530 0274",
    "sg:postcode":"20068",
    "sg:province":"Milano",
    "wof:name":"D'ambra Passamenerie (s.n.c.)",
    "wof:placetype":"venue"
},
  "geometry": {"coordinates":[9.2871656418,45.438117981],"type":"Point"}
}