{
  "type": "Feature",
  "properties": {
    "addr:full":"03100 Frosinone Frosinone Frosinone 03100",
    "addr:postcode":"03100;03100",
    "iso:country":"IT",
    "sg:address":"03100 Frosinone",
    "sg:city":"Frosinone",
    "sg:orig_category":"Trasporti E Spedizioni Merci",
    "sg:phone":"+39 0775 855341",
    "sg:postcode":"03100",
    "sg:province":"Frosinone",
    "sg:website":"http://www.devellis.it",
    "wof:name":"De Vellis Traslochi Trasporti",
    "wof:placetype":"venue"
},
  "geometry": {"coordinates":[13.344283,41.641834],"type":"Point"}
}