{
  "type": "Feature",
  "properties": {
    "iso:country":"IT",
    "sg:address":"Via Marinaro 47 80025 Casandrino",
    "sg:city":"Casandrino",
    "sg:classifiers":[
        {
            "category":"Shopping",
            "subcategory":"Clothing, Apparel, & Fashions",
            "type":"Retail Goods"
        }
    ],
    "sg:phone":"+39 081 505 5352",
    "sg:postcode":"80025",
    "sg:province":"Napoli",
    "sg:tags":[
        "blouse",
        "ladies'",
        "dress"
    ],
    "sg:website":"www.antonioderrico.com",
    "wof:name":"D.a. Srl",
    "wof:placetype":"venue"
},
  "geometry": {"coordinates":[14.250108,40.928349],"type":"Point"}
}