{
  "type": "Feature",
  "properties": {
    "iso:country":"IT",
    "sg:address":"28047 Oleggio",
    "sg:city":"Oleggio",
    "sg:orig_category":"Servizi E Lavori Per Edilizia E Lavori Pubblici. Servizi Ausiliari Di Sorveglianza, Manutenzione E Pulizia",
    "sg:phone":"+39 0321 960920",
    "sg:postcode":"28047",
    "sg:province":"Novara",
    "wof:name":"Termoidraulica F.lli Spagnoli",
    "wof:placetype":"venue"
},
  "geometry": {"coordinates":[8.635446,45.599129],"type":"Point"}
}