{
  "type": "Feature",
  "properties": {
    "iso:country":"IT",
    "sg:address":"40053 Bazzano",
    "sg:city":"Bazzano",
    "sg:orig_category":"Adesivi",
    "sg:phone":"+39 051 831273",
    "sg:postcode":"40053",
    "sg:province":"Bologna",
    "wof:name":"Benfer Chimica Di Cocchi Ing. Rinaldo Snc Di Giorgio Cocchi",
    "wof:placetype":"venue"
},
  "geometry": {"coordinates":[11.093984,44.506104],"type":"Point"}
}