{
  "type": "Feature",
  "properties": {
    "addr:full":"20035 Lissone Lissone Milano 20035",
    "addr:postcode":"20035;20035",
    "iso:country":"IT",
    "sg:address":"20035 Lissone",
    "sg:city":"Lissone",
    "sg:orig_category":"Prodotti Chimici Di Base",
    "sg:phone":"+39 039 245 9033",
    "sg:postcode":"20035",
    "sg:province":"Milano",
    "wof:name":"S.e.v.e.p. Di Monaci Marcello",
    "wof:placetype":"venue"
},
  "geometry": {"coordinates":[9.2397441864,45.6050682068],"type":"Point"}
}