{
  "type": "Feature",
  "properties": {
    "iso:country":"IT",
    "sg:address":"Via Gora E Barbatole 150/x 51100 Pistoia",
    "sg:city":"Pistoia",
    "sg:classifiers":[
        {
            "category":"Shopping",
            "subcategory":"Department Store",
            "type":"Retail Goods"
        }
    ],
    "sg:phone":"+39 0573 400777",
    "sg:postcode":"51100",
    "sg:province":"Pistoia",
    "sg:tags":[
        "linen",
        "bed"
    ],
    "sg:website":"www.villaflorence.it",
    "wof:name":"Villaflorence Srl",
    "wof:placetype":"venue"
},
  "geometry": {"coordinates":[10.918524,43.932156],"type":"Point"}
}