{
  "type": "Feature",
  "properties": {
    "addr:full":"25014 Castenedolo Castenedolo Brescia 25014",
    "addr:postcode":"25014;25014",
    "iso:country":"IT",
    "sg:address":"25014 Castenedolo",
    "sg:city":"Castenedolo",
    "sg:orig_category":"Abbigliamento Gestanti E Neonati",
    "sg:phone":"+39 030 273 2076",
    "sg:postcode":"25014",
    "sg:province":"Brescia",
    "sg:website":"http://www.babygaia.it",
    "wof:name":"Formentini Cinzia & C. Snc",
    "wof:placetype":"venue"
},
  "geometry": {"coordinates":[10.283542,45.483551],"type":"Point"}
}