{
  "type": "Feature",
  "properties": {
    "addr:full":"23801 Calolziocorte Calolziocorte Lecco 23801",
    "addr:postcode":"23801;23801",
    "iso:country":"IT",
    "sg:address":"23801 Calolziocorte",
    "sg:city":"Calolziocorte",
    "sg:orig_category":"Acciai Inossidabili - Commercio",
    "sg:phone":"+39 0341 641113",
    "sg:postcode":"23801",
    "sg:province":"Lecco",
    "sg:website":"http://www.brambillaspa.it",
    "wof:name":"Trafilerie Brambilla Spa",
    "wof:placetype":"venue"
},
  "geometry": {"coordinates":[9.427165,45.80286],"type":"Point"}
}