{
  "type": "Feature",
  "properties": {
    "iso:country":"IT",
    "sg:address":"Via Vittorio Veneto 119, 00187 Rome, Rm",
    "sg:classifiers":[
        {
            "category":"Banks & Credit Unions",
            "subcategory":"Bank",
            "type":"Services"
        }
    ],
    "sg:phone":"+39 0647021",
    "sg:postcode":"00187",
    "sg:province":"Roma",
    "sg:website":"http://www.bnl.it",
    "wof:name":"Banca Nazionale Del Lavoro Spa",
    "wof:placetype":"venue"
},
  "geometry": {"coordinates":[12.490108,41.906307],"type":"Point"}
}