{
  "type": "Feature",
  "properties": {
    "addr:full":"35, Via Salento 00162 Roma Roma Roma 00162",
    "addr:postcode":"00162;00162",
    "addr:street":"Via Salento",
    "iso:country":"IT",
    "sg:address":"35, Via Salento 00162 Roma",
    "sg:city":"Roma",
    "sg:classifiers":[
        {
            "category":"Manufacturing",
            "subcategory":"Printing",
            "type":"Manufacturing & Wholesale Goods"
        }
    ],
    "sg:phone":"+39 06 4424 2564",
    "sg:postcode":"00162",
    "sg:province":"Roma",
    "sg:tags":[
        "publishing"
    ],
    "wof:name":"A.s.i S.r.l",
    "wof:placetype":"venue"
},
  "geometry": {"coordinates":[12.5244140625,41.9174919128],"type":"Point"}
}