{
  "type": "Feature",
  "properties": {
    "iso:country":"IT",
    "sg:address":"Via Tagliamento 17 23900 Lecco",
    "sg:city":"Lecco",
    "sg:classifiers":[
        {
            "category":"Building & Trades",
            "subcategory":"Construction",
            "type":"Services"
        }
    ],
    "sg:phone":"+39 0341 499191",
    "sg:postcode":"23900",
    "sg:province":"Lecco",
    "sg:tags":[
        "mural"
    ],
    "sg:website":"www.coverline.it",
    "wof:name":"Coverline Srl",
    "wof:placetype":"venue"
},
  "geometry": {"coordinates":[9.4059362411,45.8536682129],"type":"Point"}
}