{
  "type": "Feature",
  "properties": {
    "iso:country":"IT",
    "sg:address":"3, Via Dei Frassini 36100 Vicenza",
    "sg:city":"Vicenza",
    "sg:classifiers":[
        {
            "category":"Manufacturing",
            "subcategory":"Metals",
            "type":"Manufacturing & Wholesale Goods"
        }
    ],
    "sg:phone":"+39 0444 349473",
    "sg:postcode":"36100",
    "sg:province":"Vicenza",
    "sg:tags":[
        "metallurgy",
        "metalworking"
    ],
    "wof:name":"Valinox Italia (s.r.l.)",
    "wof:placetype":"venue"
},
  "geometry": {"coordinates":[11.526389122,45.5752792358],"type":"Point"}
}