{
  "type": "Feature",
  "properties": {
    "iso:country":"IT",
    "sg:address":"Via Lodovica 628 55100 Lucca",
    "sg:city":"Lucca",
    "sg:orig_category":"Ladies' Hats",
    "sg:phone":"+39 0583 57587",
    "sg:postcode":"55100",
    "sg:province":"Lucca",
    "wof:name":"Berrettificio Pal Srl",
    "wof:placetype":"venue"
},
  "geometry": {"coordinates":[10.507994,43.843014],"type":"Point"}
}