{
  "type": "Feature",
  "properties": {
    "iso:country":"IT",
    "sg:address":"Via Dei Seminari 4/a 13900 Biella",
    "sg:city":"Biella",
    "sg:classifiers":[
        {
            "category":"Shopping",
            "subcategory":"Clothing, Apparel, & Fashions",
            "type":"Retail Goods"
        }
    ],
    "sg:phone":"+39 015 848 7111",
    "sg:postcode":"13900",
    "sg:province":"Biella",
    "sg:tags":[
        "lingerie"
    ],
    "wof:name":"Liabel Spa",
    "wof:placetype":"venue"
},
  "geometry": {"coordinates":[8.0582695007,45.5628356934],"type":"Point"}
}