{
  "type": "Feature",
  "properties": {
    "addr:full":"Via Roma 54/a 40069 Zola Predosa Zola Bologna 40069",
    "addr:housenumber":"54 / a",
    "addr:postcode":"40069;40069",
    "addr:street":"Via Roma",
    "iso:country":"IT",
    "sg:address":"Via Roma 54/a 40069 Zola Predosa",
    "sg:city":"Zola",
    "sg:orig_category":"Cylindrical Surface, Contour And Face Shoulder Grinding Machines",
    "sg:phone":"+39 051 298 0211",
    "sg:postcode":"40069",
    "sg:province":"Bologna",
    "sg:website":"www.meccanicanova.com",
    "wof:name":"Meccanica Nova Spa",
    "wof:placetype":"venue"
},
  "geometry": {"coordinates":[11.246904,44.496292],"type":"Point"}
}