{
  "type": "Feature",
  "properties": {
    "iso:country":"IT",
    "sg:address":"20127 Milano",
    "sg:city":"Milano",
    "sg:orig_category":"Servizi Editoriali. Pubblicita', Marketing E Comunicazione",
    "sg:phone":"+39 02 2614 9005",
    "sg:postcode":"20127",
    "sg:province":"Milano",
    "wof:name":"Comunicazioni Giornalistiche Advercoop S.n.c.",
    "wof:placetype":"venue"
},
  "geometry": {"coordinates":[9.21562,45.490871],"type":"Point"}
}