{
  "type": "Feature",
  "properties": {
    "addr:full":"00179 Roma Roma Roma 00179",
    "addr:postcode":"00179;00179",
    "iso:country":"IT",
    "sg:address":"00179 Roma",
    "sg:city":"Roma",
    "sg:orig_category":"Petroli, Gas E Combustibili. Materiali Edili",
    "sg:phone":"+39 06 518931",
    "sg:postcode":"00179",
    "sg:province":"Roma",
    "sg:website":"http://www.maxcom.it",
    "wof:name":"Maxcom Petroli Srl",
    "wof:placetype":"venue"
},
  "geometry": {"coordinates":[12.5084314346,41.8629455566],"type":"Point"}
}