{
  "type": "Feature",
  "properties": {
    "iso:country":"IT",
    "sg:address":"Via L. Da Vinci 8/a 60010 Ripe",
    "sg:city":"Ripe",
    "sg:orig_category":"Menswear, Suits, Trousers, Sports Jackets",
    "sg:phone":"+39 071 795 9330",
    "sg:postcode":"60010",
    "sg:province":"Ancona",
    "wof:name":"Fantasy Studio Srl",
    "wof:placetype":"venue"
},
  "geometry": {"coordinates":[13.5187568665,43.6158561707],"type":"Point"}
}