{
  "type": "Feature",
  "properties": {
    "addr:full":"20122 Milano Milano Milano 20122",
    "addr:postcode":"20122;20122",
    "iso:country":"IT",
    "sg:address":"20122 Milano",
    "sg:city":"Milano",
    "sg:classifiers":[
        {
            "category":"Health Services",
            "subcategory":"Health Practitioner",
            "type":"Services"
        }
    ],
    "sg:phone":"+39 02 5832 0961",
    "sg:postcode":"20122",
    "sg:province":"Milano",
    "sg:tags":[
        "medici"
    ],
    "wof:name":"Oculistica Milanese Sas Della D.ssa Cristina Lonati E C.",
    "wof:placetype":"venue"
},
  "geometry": {"coordinates":[9.195479393,45.4528465271],"type":"Point"}
}