{
  "type": "Feature",
  "properties": {
    "iso:country":"IT",
    "sg:address":"119, Via Bonfadina 25046 Cazzago San Martino",
    "sg:city":"Cazzago San Martino",
    "sg:classifiers":[
        {
            "category":"Manufacturing",
            "subcategory":"Paper Products",
            "type":"Manufacturing & Wholesale Goods"
        }
    ],
    "sg:phone":"+39 030 775 0160",
    "sg:postcode":"25046",
    "sg:province":"Brescia",
    "sg:tags":[
        "cardboard"
    ],
    "wof:name":"Scatolificio Bresciano Di Zanini A. & C. Snc",
    "wof:placetype":"venue"
},
  "geometry": {"coordinates":[10.0334444046,45.5720748901],"type":"Point"}
}