{
  "type": "Feature",
  "properties": {
    "addr:full":"4/6, Via Basse 35010 Campo San Martino Campo San Martino Padova 35010",
    "addr:housenumber":"4 / 6",
    "addr:postcode":"35010;35010",
    "addr:street":"Via Basse;San",
    "iso:country":"IT",
    "sg:address":"4/6, Via Basse 35010 Campo San Martino",
    "sg:city":"Campo San Martino",
    "sg:classifiers":[
        {
            "category":"Shopping",
            "subcategory":"Clothing, Apparel, & Fashions",
            "type":"Retail Goods"
        }
    ],
    "sg:phone":"+39 049 960 0270",
    "sg:postcode":"35010",
    "sg:province":"Padova",
    "sg:tags":[
        "clothing",
        "accessory"
    ],
    "wof:name":"Pastelli (s.n.c.)",
    "wof:placetype":"venue"
},
  "geometry": {"coordinates":[11.115941,45.418343],"type":"Point"}
}