{
  "type": "Feature",
  "properties": {
    "addr:full":"Viale Xvi Giugno 44, 06034 Foligno, Pg Foligno Perugia 06034",
    "addr:housenumber":"44",
    "addr:postcode":"06034;06034",
    "addr:street":"Viale Xvi Giugno;Pg",
    "iso:country":"IT",
    "sg:address":"Viale Xvi Giugno 44, 06034 Foligno, Pg",
    "sg:city":"Foligno",
    "sg:classifiers":[
        {
            "category":"Banks & Credit Unions",
            "subcategory":"Bank",
            "type":"Services"
        }
    ],
    "sg:postcode":"06034",
    "sg:province":"Perugia",
    "wof:name":"Sorit Societ\u00e0 Riscossione Tributi Spa",
    "wof:placetype":"venue"
},
  "geometry": {"coordinates":[12.389172,43.110703],"type":"Point"}
}