{
  "type": "Feature",
  "properties": {
    "iso:country":"IT",
    "sg:address":"21052 Busto Arsizio",
    "sg:city":"Busto Arsizio",
    "sg:orig_category":"Cromatura E Nichelatura",
    "sg:phone":"+39 0331 634465",
    "sg:postcode":"21052",
    "sg:province":"Varese",
    "wof:name":"Cromatura Pozzi & C. Snc",
    "wof:placetype":"venue"
},
  "geometry": {"coordinates":[8.86626,45.605129],"type":"Point"}
}