{
  "type": "Feature",
  "properties": {
    "iso:country":"IT",
    "sg:address":"20094 Corsico",
    "sg:city":"Corsico",
    "sg:orig_category":"Macchine E Forniture Per Ecologia E Smaltimento Rifiuti",
    "sg:phone":"+39 02 4586 9739",
    "sg:postcode":"20094",
    "sg:province":"Milano",
    "wof:name":"L'idealspurghi S.a.s. Di Gallo A. & C.",
    "wof:placetype":"venue"
},
  "geometry": {"coordinates":[9.077039,45.430149],"type":"Point"}
}