{
  "type": "Feature",
  "properties": {
    "addr:full":"37051 Bovolone Bovolone Verona 37051",
    "addr:postcode":"37051;37051",
    "iso:country":"IT",
    "sg:address":"37051 Bovolone",
    "sg:city":"Bovolone",
    "sg:orig_category":"Serramenti Ed Infissi",
    "sg:phone":"+39 045 690 1088",
    "sg:postcode":"37051",
    "sg:province":"Verona",
    "wof:name":"Elettrozeta Di Zamboni Fabiano",
    "wof:placetype":"venue"
},
  "geometry": {"coordinates":[11.109788,45.257645],"type":"Point"}
}