{
  "type": "Feature",
  "properties": {
    "iso:country":"IT",
    "sg:address":"46040 Casalromano",
    "sg:city":"Casalromano",
    "sg:orig_category":"Metalli E Leghe",
    "sg:phone":"+39 0376 76444",
    "sg:postcode":"46040",
    "sg:province":"Mantova",
    "wof:name":"C.i.t.a.c. (s.r.l.)",
    "wof:placetype":"venue"
},
  "geometry": {"coordinates":[10.3656263351,45.196521759],"type":"Point"}
}