{
  "type": "Feature",
  "properties": {
    "iso:country":"IT",
    "sg:address":"40125 Bologna",
    "sg:city":"Bologna",
    "sg:classifiers":[
        {
            "category":"Home & Garden",
            "subcategory":"Home Furnishings",
            "type":"Retail Goods"
        }
    ],
    "sg:phone":"+39 051 648 6009",
    "sg:postcode":"40125",
    "sg:province":"Bologna",
    "sg:tags":[
        "household",
        "appliance",
        "furnishings",
        "kitchen"
    ],
    "wof:name":"Domus D. Srl",
    "wof:placetype":"venue"
},
  "geometry": {"coordinates":[11.3523826599,44.4911308289],"type":"Point"}
}