{
  "type": "Feature",
  "properties": {
    "iso:country":"IT",
    "sg:address":"33040 Pradamano",
    "sg:city":"Pradamano",
    "sg:classifiers":[
        {
            "category":"Farming",
            "subcategory":"Livestock Farm",
            "type":"Manufacturing & Wholesale Goods"
        }
    ],
    "sg:phone":"+39 0432 670133",
    "sg:postcode":"33040",
    "sg:province":"Udine",
    "sg:tags":[
        "equipment",
        "breeding",
        "agriculture",
        "machinery",
        "supply"
    ],
    "wof:name":"Sofim Spa",
    "wof:placetype":"venue"
},
  "geometry": {"coordinates":[13.303778,46.03487],"type":"Point"}
}