{
  "type": "Feature",
  "properties": {
    "iso:country":"IT",
    "sg:address":"20154 Milano",
    "sg:city":"Milano",
    "sg:orig_category":"Impianti, Attrezzature E Forniture Sanitarie Ed Ospedaliere",
    "sg:postcode":"20154",
    "sg:province":"Milano",
    "wof:name":"Ceam Implantologic Di Vitaloni Ambrogio & C. (s.a.s.)",
    "wof:placetype":"venue"
},
  "geometry": {"coordinates":[9.162267,45.485088],"type":"Point"}
}