{
  "type": "Feature",
  "properties": {
    "iso:country":"IT",
    "sg:address":"46100 Mantova",
    "sg:city":"Mantova",
    "sg:orig_category":"Scuole Di Lingue",
    "sg:phone":"+39 0376 269944",
    "sg:postcode":"46100",
    "sg:province":"Mantova",
    "sg:website":"http://www.studio-one-english.com",
    "wof:name":"Studio One Di Margaret Leight",
    "wof:placetype":"venue"
},
  "geometry": {"coordinates":[10.783255,45.146587],"type":"Point"}
}