{
  "type": "Feature",
  "properties": {
    "iso:country":"IT",
    "sg:address":"67055 Gioia Dei Marsi",
    "sg:classifiers":[
        {
            "category":"Restaurant",
            "type":"Food & Drink"
        }
    ],
    "sg:phone":"+39 0863 88111",
    "sg:postcode":"67055",
    "sg:province":"L'Aquila",
    "sg:tags":[
        "auxiliary",
        "entertainment",
        "premises",
        "related",
        "catering",
        "similar",
        "public",
        "restaurants"
    ],
    "wof:name":"Hotel - Ristorante Filippone",
    "wof:placetype":"venue"
},
  "geometry": {"coordinates":[13.699036,41.952091],"type":"Point"}
}