{
  "type": "Feature",
  "properties": {
    "iso:country":"IT",
    "sg:address":"33100 Udine",
    "sg:city":"Udine",
    "sg:orig_category":"Librerie",
    "sg:phone":"+39 0432 299250",
    "sg:postcode":"33100",
    "sg:province":"Udine",
    "wof:name":"Istituto Della Pia Societa' Figlie Di S. Paolo - Apostole Nel Mondo Della Com.ne",
    "wof:placetype":"venue"
},
  "geometry": {"coordinates":[13.240801,46.064381],"type":"Point"}
}