{
  "type": "Feature",
  "properties": {
    "iso:country":"IT",
    "sg:address":"5, V. Dell'incisore 40138 Bologna",
    "sg:city":"Bologna",
    "sg:classifiers":[
        {
            "category":"Shopping",
            "subcategory":"Clothing, Apparel, & Fashions",
            "type":"Retail Goods"
        }
    ],
    "sg:phone":"+39 051 601 3008",
    "sg:postcode":"40138",
    "sg:province":"Bologna",
    "sg:tags":[
        "clothes"
    ],
    "sg:website":"http://www.paginegialle.it/menta",
    "wof:name":"Menta Srl",
    "wof:placetype":"venue"
},
  "geometry": {"coordinates":[11.409968,44.502682],"type":"Point"}
}