{
  "type": "Feature",
  "properties": {
    "iso:country":"IT",
    "sg:address":"118, Via Monferrato 20098 San Giuliano Milanese",
    "sg:city":"San Giuliano Milanese",
    "sg:classifiers":[
        {
            "category":"Wholesale",
            "subcategory":"Drugs",
            "type":"Manufacturing & Wholesale Goods"
        }
    ],
    "sg:phone":"+39 390 298 2111",
    "sg:postcode":"20098",
    "sg:province":"Milano",
    "sg:tags":[
        "chemical",
        "pharmaceutical"
    ],
    "wof:name":"Nitrol Chimica S.r.l.",
    "wof:placetype":"venue"
},
  "geometry": {"coordinates":[9.259009,45.400131],"type":"Point"}
}