{
  "type": "Feature",
  "properties": {
    "iso:country":"IT",
    "sg:address":"20023 Cerro Maggiore",
    "sg:city":"Cerro Maggiore",
    "sg:orig_category":"Articoli Pulizia",
    "sg:phone":"+39 0331 518085",
    "sg:postcode":"20023",
    "sg:province":"Milano",
    "wof:name":"Donati Eraldo",
    "wof:placetype":"venue"
},
  "geometry": {"coordinates":[8.957478,45.587044],"type":"Point"}
}