{
  "type": "Feature",
  "properties": {
    "iso:country":"IT",
    "sg:address":"10073 Cirie'",
    "sg:orig_category":"Legno E Semilavorati",
    "sg:phone":"+39 011 921 0485",
    "sg:postcode":"10073",
    "sg:province":"Torino",
    "wof:name":"Richetta Piero",
    "wof:placetype":"venue"
},
  "geometry": {"coordinates":[7.605832,45.225033],"type":"Point"}
}