{
  "type": "Feature",
  "properties": {
    "iso:country":"IT",
    "sg:address":"70, Via Assisi 00181 Roma",
    "sg:city":"Roma",
    "sg:classifiers":[
        {
            "category":"Shopping",
            "subcategory":"Clothing, Apparel, & Fashions",
            "type":"Retail Goods"
        }
    ],
    "sg:phone":"+39 390 678 6521",
    "sg:postcode":"00181",
    "sg:province":"Roma",
    "sg:tags":[
        "clothes"
    ],
    "wof:name":"M.i.a. Moda Italiana Abbigliamento (s.r.l.)",
    "wof:placetype":"venue"
},
  "geometry": {"coordinates":[12.450279,41.869308],"type":"Point"}
}