{
  "type": "Feature",
  "properties": {
    "iso:country":"IT",
    "sg:address":"21056 Induno Olona",
    "sg:city":"Induno Olona",
    "sg:orig_category":"Macchine, Impianti Ed Attrezzature Per Abbigliamento E Pelletterie",
    "sg:phone":"+39 0332 270511",
    "sg:postcode":"21056",
    "sg:province":"Varese",
    "wof:name":"Mec-mor S.r.l.",
    "wof:placetype":"venue"
},
  "geometry": {"coordinates":[8.84108,45.838722],"type":"Point"}
}