{
  "type": "Feature",
  "properties": {
    "addr:full":"Corso Magenta 85 20123 Milano Milano Milano 20123",
    "addr:housenumber":"85",
    "addr:postcode":"20123;20123",
    "addr:street":"Corso Magenta",
    "iso:country":"IT",
    "sg:address":"Corso Magenta 85 20123 Milano",
    "sg:city":"Milano",
    "sg:classifiers":[
        {
            "category":"Manufacturing",
            "subcategory":"Chemicals & Compounds",
            "type":"Manufacturing & Wholesale Goods"
        }
    ],
    "sg:phone":"+39 02 676161",
    "sg:postcode":"20123",
    "sg:province":"Milano",
    "sg:tags":[
        "product",
        "fur",
        "industry"
    ],
    "sg:website":"www.stoppani.it",
    "wof:name":"Luigi Stoppani Spa",
    "wof:placetype":"venue"
},
  "geometry": {"coordinates":[9.166651,45.465939],"type":"Point"}
}