{
  "type": "Feature",
  "properties": {
    "iso:country":"IT",
    "sg:address":"20123 Milano",
    "sg:city":"Milano",
    "sg:orig_category":"Materiali Semilavorati Metallici",
    "sg:phone":"+39 02 874773",
    "sg:postcode":"20123",
    "sg:province":"Milano",
    "wof:name":"Pirelli Cavi Spa",
    "wof:placetype":"venue"
},
  "geometry": {"coordinates":[9.172138,45.46423],"type":"Point"}
}