{
  "type": "Feature",
  "properties": {
    "addr:full":"80125 Napoli Napoli Napoli 80125",
    "addr:housenumber":"80125",
    "addr:postcode":"80125",
    "iso:country":"IT",
    "sg:address":"80125 Napoli",
    "sg:city":"Napoli",
    "sg:orig_category":"Servizi Al Turismo. Trasporto Pubblico E Privato. Acqua, Luce, Gas E Societa' Di Esercizio Pubblico",
    "sg:phone":"+39 081 735 4111",
    "sg:postcode":"80125",
    "sg:province":"Napoli",
    "wof:name":"Sepsa",
    "wof:placetype":"venue"
},
  "geometry": {"coordinates":[14.211672,40.906437],"type":"Point"}
}