{
  "type": "Feature",
  "properties": {
    "addr:full":"389, Via Litoranea 61037 Mondolfo Mondolfo Pesaro E Urbino 61037",
    "addr:housenumber":"389",
    "addr:postcode":"61037;61037",
    "addr:street":"Via Litoranea",
    "iso:country":"IT",
    "sg:address":"389, Via Litoranea 61037 Mondolfo",
    "sg:city":"Mondolfo",
    "sg:classifiers":[
        {
            "category":"Food & Beverages",
            "subcategory":"Groceries & Convenience Stores",
            "type":"Retail Goods"
        }
    ],
    "sg:phone":"+39 0721 969428",
    "sg:postcode":"61037",
    "sg:province":"Pesaro E Urbino",
    "sg:tags":[
        "product",
        "related"
    ],
    "wof:name":"Azurpesca S.n.c. Di Marchionni Fabio & C.",
    "wof:placetype":"venue"
},
  "geometry": {"coordinates":[13.1626091003,43.7533607483],"type":"Point"}
}