{
  "type": "Feature",
  "properties": {
    "iso:country":"IT",
    "sg:address":"6, Via Dell' Industria 34072 Gradisca D'isonzo",
    "sg:classifiers":[
        {
            "category":"Manufacturing",
            "subcategory":"Tools & Machinery",
            "type":"Manufacturing & Wholesale Goods"
        }
    ],
    "sg:phone":"+39 0481 961524",
    "sg:postcode":"34072",
    "sg:province":"Gorizia",
    "sg:tags":[
        "environment",
        "equipment",
        "-"
    ],
    "wof:name":"Centro Risorse Srl",
    "wof:placetype":"venue"
},
  "geometry": {"coordinates":[13.474898,45.882504],"type":"Point"}
}