{
  "type": "Feature",
  "properties": {
    "iso:country":"IT",
    "sg:address":"00154 Roma",
    "sg:city":"Roma",
    "sg:orig_category":"Attrezzature E Forniture Per Officine Riparazione E Servizi Ausiliari",
    "sg:phone":"+39 06 578 3608",
    "sg:postcode":"00154",
    "sg:province":"Roma",
    "wof:name":"A. C. Camperio Di Va. Cl.",
    "wof:placetype":"venue"
},
  "geometry": {"coordinates":[12.490306,41.868084],"type":"Point"}
}