{
  "type": "Feature",
  "properties": {
    "addr:full":"90133 Palermo Palermo Palermo 90133",
    "addr:postcode":"90133;90133",
    "iso:country":"IT",
    "sg:address":"90133 Palermo",
    "sg:city":"Palermo",
    "sg:orig_category":"Calzature, Pelletterie E Pelli. Servizi E Lavori Per Abbigliamento E Pelletterie",
    "sg:phone":"+39 091 547639",
    "sg:postcode":"90133",
    "sg:province":"Palermo",
    "wof:name":"Gaia Srl",
    "wof:placetype":"venue"
},
  "geometry": {"coordinates":[13.361819,38.120174],"type":"Point"}
}