{
  "type": "Feature",
  "properties": {
    "iso:country":"IT",
    "sg:address":"09125 Cagliari",
    "sg:city":"Cagliari",
    "sg:classifiers":[
        {
            "category":"Health Services",
            "subcategory":"Health Practitioner",
            "type":"Services"
        }
    ],
    "sg:phone":"+39 070 305393",
    "sg:postcode":"09125",
    "sg:province":"Cagliari",
    "sg:tags":[
        "medici"
    ],
    "wof:name":"Mereu Dott. Anna",
    "wof:placetype":"venue"
},
  "geometry": {"coordinates":[9.128157,39.210728],"type":"Point"}
}