{
  "type": "Feature",
  "properties": {
    "iso:country":"IT",
    "sg:address":"95014 Giarre",
    "sg:city":"Giarre",
    "sg:orig_category":"Motori Ed Organi Di Trasmissione. Ricambi E Componenti Dei Mezzi Di Trasporto",
    "sg:phone":"+39 095 933488",
    "sg:postcode":"95014",
    "sg:province":"Catania",
    "wof:name":"Grasso Alfredo",
    "wof:placetype":"venue"
},
  "geometry": {"coordinates":[15.189663887,37.721157074],"type":"Point"}
}