{
  "type": "Feature",
  "properties": {
    "addr:full":"1, Viale Abruzzi 64016 Sant'egidio Alla Vibrata Teramo 64016",
    "addr:postcode":"64016;64016",
    "addr:street":"Viale Abruzzi",
    "iso:country":"IT",
    "sg:address":"1, Viale Abruzzi 64016 Sant'egidio Alla Vibrata",
    "sg:classifiers":[
        {
            "category":"Shopping",
            "subcategory":"Crafts & Fabrics",
            "type":"Retail Goods"
        }
    ],
    "sg:phone":"+39 0861 842290",
    "sg:postcode":"64016",
    "sg:province":"Teramo",
    "wof:name":"Gikappa Srl",
    "wof:placetype":"venue"
},
  "geometry": {"coordinates":[13.7108249664,42.8254051208],"type":"Point"}
}