{
  "type": "Feature",
  "properties": {
    "iso:country":"IT",
    "sg:address":"1, Via Chiesa Damiano 62029 Tolentino",
    "sg:city":"Tolentino",
    "sg:classifiers":[
        {
            "category":"Shopping",
            "subcategory":"Clothing, Apparel, & Fashions",
            "type":"Retail Goods"
        }
    ],
    "sg:phone":"+39 0733 974138",
    "sg:postcode":"62029",
    "sg:province":"Macerata",
    "sg:tags":[
        "clothes"
    ],
    "wof:name":"Creazioni C M S.r.l.",
    "wof:placetype":"venue"
},
  "geometry": {"coordinates":[13.456262,43.300747],"type":"Point"}
}