{
  "type": "Feature",
  "properties": {
    "addr:full":"125, Via Amendola Giovanni 13836 Cossato Cossato Biella 13836",
    "addr:housenumber":"125",
    "addr:postcode":"13836;13836",
    "addr:street":"Via Amendola Giovanni",
    "iso:country":"IT",
    "sg:address":"125, Via Amendola Giovanni 13836 Cossato",
    "sg:city":"Cossato",
    "sg:classifiers":[
        {
            "category":"Shopping",
            "type":"Retail Goods"
        }
    ],
    "sg:phone":"+39 39015980641",
    "sg:postcode":"13836",
    "sg:province":"Biella",
    "sg:tags":[
        "finished",
        "-",
        "metallic"
    ],
    "wof:name":"Italvalvole Di Spadon Oscar & C. (s.a.s.)",
    "wof:placetype":"venue"
},
  "geometry": {"coordinates":[8.0582695007,45.5628356934],"type":"Point"}
}