{
  "type": "Feature",
  "properties": {
    "iso:country":"IT",
    "sg:address":"Via Modigliani 12 20022 Castano Primo",
    "sg:city":"Castano Primo",
    "sg:classifiers":[
        {
            "category":"Utilities",
            "subcategory":"Cable",
            "type":"Services"
        }
    ],
    "sg:phone":"+39 0331 880354",
    "sg:postcode":"20022",
    "sg:province":"Milano",
    "sg:tags":[
        "halogen",
        "lines",
        "free"
    ],
    "sg:website":"www.vibiplast.it",
    "wof:name":"Vibiplast Srl",
    "wof:placetype":"venue"
},
  "geometry": {"coordinates":[8.754724,45.55299],"type":"Point"}
}