{
  "type": "Feature",
  "properties": {
    "iso:country":"IT",
    "sg:address":"25030 Torbole Casaglia",
    "sg:city":"Torbole Casaglia",
    "sg:orig_category":"Manufacturers: Prefabbricati",
    "sg:phone":"+39 030 265 0771",
    "sg:postcode":"25030",
    "sg:province":"Brescia",
    "wof:name":"Edil Scuri Di Scuri Elia & C. Snc",
    "wof:placetype":"venue"
},
  "geometry": {"coordinates":[10.15673,45.532677],"type":"Point"}
}