{
  "type": "Feature",
  "properties": {
    "iso:country":"IT",
    "sg:address":"20128 Milano",
    "sg:city":"Milano",
    "sg:orig_category":"Macchine Utensili E Impianti. Macchine, Strumenti Ed Apparecchi Per Attivita' Industriali",
    "sg:phone":"+39 02 272231",
    "sg:postcode":"20128",
    "sg:province":"Milano",
    "wof:name":"Leybold Vacum Italia Spa",
    "wof:placetype":"venue"
},
  "geometry": {"coordinates":[9.25005,45.511257],"type":"Point"}
}