{
  "type": "Feature",
  "properties": {
    "addr:full":"20149 Milano Milano Milano 20149",
    "addr:postcode":"20149;20149",
    "iso:country":"IT",
    "sg:address":"20149 Milano",
    "sg:city":"Milano",
    "sg:orig_category":"Chiese Ed Associazioni Religiose",
    "sg:phone":"+39 02 498 1506",
    "sg:postcode":"20149",
    "sg:province":"Milano",
    "wof:name":"Prov D It Della Congr Delle Suore Di Nostra Signora Del Cen.",
    "wof:placetype":"venue"
},
  "geometry": {"coordinates":[9.144192,45.474014],"type":"Point"}
}