{
  "type": "Feature",
  "properties": {
    "addr:full":"Via Alberto Parolini 93; Bassano; 360061",
    "addr:housenumber":"93",
    "addr:postcode":"360061",
    "addr:street":"Via Alberto Parolini",
    "iso:country":"IT",
    "sg:address":"Via Alberto Parolini 93; Bassano; 360061",
    "sg:classifiers":[
        {
            "category":"Banks & Credit Unions",
            "subcategory":"Bank",
            "type":"Services"
        }
    ],
    "sg:phone":"+39 0424 515611",
    "wof:name":"Cariverona Banca Spa",
    "wof:placetype":"venue"
},
  "geometry": {"coordinates":[12.405017,43.010548],"type":"Point"}
}