{
  "type": "Feature",
  "properties": {
    "iso:country":"IT",
    "sg:address":"71, Via Cappuccini Vecchi 62014 Corridonia",
    "sg:city":"Corridonia",
    "sg:classifiers":[
        {
            "category":"Personal",
            "subcategory":"Shoe Repair & Shine",
            "type":"Services"
        }
    ],
    "sg:phone":"+39 0733 431386",
    "sg:postcode":"62014",
    "sg:province":"Macerata",
    "sg:tags":[
        "leather"
    ],
    "wof:name":"Greta S.r.l.",
    "wof:placetype":"venue"
},
  "geometry": {"coordinates":[13.487985,43.239246],"type":"Point"}
}