{
  "type": "Feature",
  "properties": {
    "iso:country":"IT",
    "sg:address":"41042 Fiorano Modenese",
    "sg:city":"Fiorano Modenese",
    "sg:orig_category":"Servizi E Lavori Per Arredamento E Industria Del Legno",
    "sg:phone":"+39 0536 921465",
    "sg:postcode":"41042",
    "sg:province":"Modena",
    "wof:name":"Freehand Srl",
    "wof:placetype":"venue"
},
  "geometry": {"coordinates":[10.838421,44.534019],"type":"Point"}
}