{
  "type": "Feature",
  "properties": {
    "iso:country":"IT",
    "sg:address":"10093 Collegno",
    "sg:city":"Collegno",
    "sg:orig_category":"Adesivi",
    "sg:phone":"+39 011 403 4314",
    "sg:postcode":"10093",
    "sg:province":"Torino",
    "wof:name":"Tecnochima Srl",
    "wof:placetype":"venue"
},
  "geometry": {"coordinates":[7.592068,45.073212],"type":"Point"}
}