{
  "type": "Feature",
  "properties": {
    "iso:country":"IT",
    "sg:address":"10, Strada Pradisera 21013 Gallarate",
    "sg:city":"Gallarate",
    "sg:classifiers":[
        {
            "category":"Shopping",
            "subcategory":"Crafts & Fabrics",
            "type":"Retail Goods"
        }
    ],
    "sg:phone":"+39 0331 796550",
    "sg:postcode":"21013",
    "sg:province":"Varese",
    "wof:name":"Tesfan (s.r.l.)",
    "wof:placetype":"venue"
},
  "geometry": {"coordinates":[8.7893104553,45.6753501892],"type":"Point"}
}