{
  "type": "Feature",
  "properties": {
    "iso:country":"IT",
    "sg:address":"Via Verga 14 20020 Lainate",
    "sg:city":"Lainate",
    "sg:classifiers":[
        {
            "category":"Manufacturing",
            "subcategory":"Tools & Machinery",
            "type":"Manufacturing & Wholesale Goods"
        }
    ],
    "sg:phone":"+39 02 937 3484",
    "sg:postcode":"20020",
    "sg:province":"Milano",
    "sg:tags":[
        "machine",
        "special"
    ],
    "wof:name":"Macchine Utensili Tecno Delta Spa",
    "wof:placetype":"venue"
},
  "geometry": {"coordinates":[9.188141,45.463688],"type":"Point"}
}