{
  "type": "Feature",
  "properties": {
    "iso:country":"IT",
    "sg:address":"29, Via Romana 16047 Moconesi",
    "sg:city":"Moconesi",
    "sg:classifiers":[
        {
            "category":"Sports & Exercise",
            "subcategory":"Playing Field",
            "type":"Entertainment"
        }
    ],
    "sg:phone":"+39 0185 934090",
    "sg:postcode":"16047",
    "sg:province":"Genova",
    "sg:tags":[
        "game"
    ],
    "wof:name":"Giobas Snc",
    "wof:placetype":"venue"
},
  "geometry": {"coordinates":[9.183333,44.432018],"type":"Point"}
}