{
  "type": "Feature",
  "properties": {
    "iso:country":"IT",
    "sg:address":"00195 Roma",
    "sg:city":"Roma",
    "sg:orig_category":"Scuole E Servizi Scolastici. Ricerca, Selezione E Formazione Del Personale",
    "sg:phone":"+39 06 321 7869",
    "sg:postcode":"00195",
    "sg:province":"Roma",
    "wof:name":"Centro Studi A. Diaz Srl",
    "wof:placetype":"venue"
},
  "geometry": {"coordinates":[12.466836,41.915264],"type":"Point"}
}