{
  "type": "Feature",
  "properties": {
    "addr:full":"Via Dell' Industria 23854 Olginate Olginate Lecco 23854",
    "addr:postcode":"23854;23854",
    "addr:street":"Via Dell ' Industria",
    "iso:country":"IT",
    "sg:address":"Via Dell' Industria 23854 Olginate",
    "sg:city":"Olginate",
    "sg:classifiers":[
        {
            "category":"Manufacturing",
            "subcategory":"Metals",
            "type":"Manufacturing & Wholesale Goods"
        }
    ],
    "sg:phone":"+39 0341 681165",
    "sg:postcode":"23854",
    "sg:province":"Lecco",
    "sg:tags":[
        "metallurgy",
        "metalworking"
    ],
    "wof:name":"Fonderia Mapelli S.r.l.",
    "wof:placetype":"venue"
},
  "geometry": {"coordinates":[9.42491436,45.7896499634],"type":"Point"}
}