{
  "type": "Feature",
  "properties": {
    "addr:full":"42100 Reggio Emilia Reggio Nell'Emilia 42100",
    "addr:postcode":"42100;42100",
    "iso:country":"IT",
    "sg:address":"42100 Reggio Emilia",
    "sg:orig_category":"Imballaggi In Plastica",
    "sg:phone":"+39 0522 382361",
    "sg:postcode":"42100",
    "sg:province":"Reggio Nell'Emilia",
    "wof:name":"Euroform Srl",
    "wof:placetype":"venue"
},
  "geometry": {"coordinates":[10.591228,44.714584],"type":"Point"}
}