{
  "type": "Feature",
  "properties": {
    "iso:country":"IT",
    "sg:address":"15, Via Dogliani 10152 Torino",
    "sg:city":"Torino",
    "sg:classifiers":[
        {
            "category":"Shopping",
            "subcategory":"Stationery & Office Supplies",
            "type":"Retail Goods"
        }
    ],
    "sg:phone":"+39 39011850235",
    "sg:postcode":"10152",
    "sg:province":"Torino",
    "sg:tags":[
        "professional"
    ],
    "wof:name":"Anteprima S.r.l.",
    "wof:placetype":"venue"
},
  "geometry": {"coordinates":[7.6824631691,45.0881500244],"type":"Point"}
}