{
  "type": "Feature",
  "properties": {
    "iso:country":"IT",
    "sg:address":"22, Via Juglaris 10024 Moncalieri",
    "sg:city":"Moncalieri",
    "sg:classifiers":[
        {
            "category":"Manufacturing",
            "subcategory":"Metals",
            "type":"Manufacturing & Wholesale Goods"
        }
    ],
    "sg:phone":"+39 011 640 5357",
    "sg:postcode":"10024",
    "sg:province":"Torino",
    "sg:tags":[
        "processing"
    ],
    "wof:name":"T.v.p. - Tempera Vuoto Piemonte S.r.l.",
    "wof:placetype":"venue"
},
  "geometry": {"coordinates":[7.6686439514,44.997833252],"type":"Point"}
}