{
  "type": "Feature",
  "properties": {
    "iso:country":"IT",
    "sg:address":"1/c, Via Mattei Enrico 30020 Marcon",
    "sg:city":"Marcon",
    "sg:classifiers":[
        {
            "category":"Wholesale",
            "subcategory":"Machinery & Supplies",
            "type":"Manufacturing & Wholesale Goods"
        }
    ],
    "sg:phone":"+39 041 456 9700",
    "sg:postcode":"30020",
    "sg:province":"Venezia",
    "sg:tags":[
        "equipment",
        "-",
        "instrument",
        "measurement"
    ],
    "wof:name":"Lecroy S.r.l.",
    "wof:placetype":"venue"
},
  "geometry": {"coordinates":[12.338784,45.434338],"type":"Point"}
}