{
  "type": "Feature",
  "properties": {
    "addr:full":"33052 Cervignano Del Friuli Cervignano del Friuli Udine 33052",
    "addr:postcode":"33052;33052",
    "iso:country":"IT",
    "sg:address":"33052 Cervignano Del Friuli",
    "sg:city":"Cervignano del Friuli",
    "sg:orig_category":"Accessori Dei Mezzi Di Trasporto",
    "sg:phone":"+39 0431 30713",
    "sg:postcode":"33052",
    "sg:province":"Udine",
    "wof:name":"Cervignano Gomme Srl",
    "wof:placetype":"venue"
},
  "geometry": {"coordinates":[13.332048,45.832985],"type":"Point"}
}