{
  "type": "Feature",
  "properties": {
    "addr:full":"37060 Sona Lugagnano Verona 37060",
    "addr:postcode":"37060;37060",
    "iso:country":"IT",
    "sg:address":"37060 Sona",
    "sg:city":"Lugagnano",
    "sg:orig_category":"Caravans, Campers, Roulottes E Accessori",
    "sg:phone":"+39 045 514166",
    "sg:postcode":"37060",
    "sg:province":"Verona",
    "wof:name":"Nuova Bicar",
    "wof:placetype":"venue"
},
  "geometry": {"coordinates":[10.887566,45.431572],"type":"Point"}
}