{
  "type": "Feature",
  "properties": {
    "iso:country":"IT",
    "sg:address":"5, Via Ricci Curbastro 48018 Faenza",
    "sg:city":"Faenza",
    "sg:classifiers":[
        {
            "category":"Shopping",
            "subcategory":"Clothing, Apparel, & Fashions",
            "type":"Retail Goods"
        }
    ],
    "sg:phone":"+39 0546 627711",
    "sg:postcode":"48018",
    "sg:province":"Ravenna",
    "sg:tags":[
        "clothes"
    ],
    "wof:name":"Marina Babini Srl",
    "wof:placetype":"venue"
},
  "geometry": {"coordinates":[11.866074,44.299019],"type":"Point"}
}