{
  "type": "Feature",
  "properties": {
    "iso:country":"IT",
    "sg:address":"18100 Imperia",
    "sg:city":"Imperia",
    "sg:orig_category":"Banche E Servizi Finanziari. Acqua, Luce, Gas E Societa' Di Esercizio Pubblico",
    "sg:phone":"+39 0183 297125",
    "sg:postcode":"18100",
    "sg:province":"Imperia",
    "wof:name":"Sestri Spa",
    "wof:placetype":"venue"
},
  "geometry": {"coordinates":[8.040624,43.890873],"type":"Point"}
}