{
  "type": "Feature",
  "properties": {
    "iso:country":"IT",
    "sg:address":"52025 Montevarchi",
    "sg:city":"Montevarchi",
    "sg:orig_category":"Prodotti Chimici Industriali - Commercio",
    "sg:phone":"+39 055 985 0034",
    "sg:postcode":"52025",
    "sg:province":"Arezzo",
    "wof:name":"F.g.m. Trading Srl",
    "wof:placetype":"venue"
},
  "geometry": {"coordinates":[11.5506973267,43.5429878235],"type":"Point"}
}