{
  "type": "Feature",
  "properties": {
    "addr:full":"Via Agucchi, 41/45 40050 Funo Funo Bologna 40050",
    "addr:housenumber":"41 / 45",
    "addr:postcode":"40050;40050",
    "addr:street":"Via Agucchi",
    "iso:country":"IT",
    "sg:address":"Via Agucchi, 41/45 40050 Funo",
    "sg:city":"Funo",
    "sg:classifiers":[
        {
            "category":"Personal",
            "subcategory":"Skin Care",
            "type":"Services"
        }
    ],
    "sg:phone":"+39 051 861415",
    "sg:postcode":"40050",
    "sg:province":"Bologna",
    "sg:tags":[
        "acid-proof",
        "lining"
    ],
    "sg:website":"www.zoccarivestimenti.it",
    "wof:name":"Zocca Officine Meccaniche Srl",
    "wof:placetype":"venue"
},
  "geometry": {"coordinates":[11.360842,44.583748],"type":"Point"}
}