{
  "type": "Feature",
  "properties": {
    "iso:country":"IT",
    "sg:address":"20093 Cologno Monzese",
    "sg:city":"Cologno Monzese",
    "sg:orig_category":"Servizi Editoriali",
    "sg:phone":"+39 02 254 2815",
    "sg:postcode":"20093",
    "sg:province":"Milano",
    "wof:name":"Stimabile Salvatore Roberto",
    "wof:placetype":"venue"
},
  "geometry": {"coordinates":[9.276423,45.528694],"type":"Point"}
}