{
  "type": "Feature",
  "properties": {
    "addr:full":"13, Via Molino 26832 Cervignano D'adda Lodi 26832",
    "addr:postcode":"26832;26832",
    "addr:street":"Via Molino",
    "iso:country":"IT",
    "sg:address":"13, Via Molino 26832 Cervignano D'adda",
    "sg:classifiers":[
        {
            "category":"Shopping",
            "type":"Retail Goods"
        }
    ],
    "sg:phone":"+39 39029813105",
    "sg:postcode":"26832",
    "sg:province":"Lodi",
    "sg:tags":[
        "finished",
        "-",
        "metallic"
    ],
    "wof:name":"Jolly S.r.l.",
    "wof:placetype":"venue"
},
  "geometry": {"coordinates":[9.423283577,45.373714447],"type":"Point"}
}