{
  "type": "Feature",
  "properties": {
    "addr:full":"20021 Bollate Bollate Milano 20021",
    "addr:postcode":"20021;20021",
    "iso:country":"IT",
    "sg:address":"20021 Bollate",
    "sg:city":"Bollate",
    "sg:orig_category":"Pubblica Amministrazione",
    "sg:phone":"+39 02 356 9191",
    "sg:postcode":"20021",
    "sg:province":"Milano",
    "wof:name":"Poste Italiane Spa",
    "wof:placetype":"venue"
},
  "geometry": {"coordinates":[9.1172151566,45.5259857178],"type":"Point"}
}