{
  "type": "Feature",
  "properties": {
    "iso:country":"IT",
    "sg:address":"00040 Ariccia",
    "sg:city":"Ariccia",
    "sg:orig_category":"Prodotti Alimentari",
    "sg:phone":"+39 06 932 4608",
    "sg:postcode":"00040",
    "sg:province":"Roma",
    "wof:name":"Ballerini Ferdinando",
    "wof:placetype":"venue"
},
  "geometry": {"coordinates":[12.6740627289,41.7217025757],"type":"Point"}
}