{
  "type": "Feature",
  "properties": {
    "iso:country":"IT",
    "sg:address":"40/d, Via Delle Industrie 33050 Pavia Di Udine",
    "sg:city":"Pavia di Udine",
    "sg:classifiers":[
        {
            "category":"Utilities",
            "subcategory":"Electric",
            "type":"Services"
        }
    ],
    "sg:phone":"+39 0432 655350",
    "sg:postcode":"33050",
    "sg:province":"Udine",
    "sg:tags":[
        "component",
        "electronic"
    ],
    "wof:name":"Tecnomaster S.p.a.",
    "wof:placetype":"venue"
},
  "geometry": {"coordinates":[13.270295,45.990135],"type":"Point"}
}