{
  "type": "Feature",
  "properties": {
    "iso:country":"IT",
    "sg:address":"20144 Milano",
    "sg:city":"Milano",
    "sg:orig_category":"Calzature, Pelletterie E Pelli",
    "sg:phone":"+39 02 4895 2317",
    "sg:postcode":"20144",
    "sg:province":"Milano",
    "wof:name":"Extravaganza Srl",
    "wof:placetype":"venue"
},
  "geometry": {"coordinates":[9.15662,45.457546],"type":"Point"}
}