{
  "type": "Feature",
  "properties": {
    "iso:country":"IT",
    "sg:address":"95126 Catania",
    "sg:city":"Catania",
    "sg:orig_category":"Prodotti E Manufatti In Materie Plastiche",
    "sg:phone":"+39 095 222214",
    "sg:postcode":"95126",
    "sg:province":"Catania",
    "wof:name":"Aerre Di Romano Antonino",
    "wof:placetype":"venue"
},
  "geometry": {"coordinates":[15.0872001648,37.5297660828],"type":"Point"}
}