{
  "type": "Feature",
  "properties": {
    "iso:country":"IT",
    "sg:address":"20090 Segrate",
    "sg:city":"Segrate",
    "sg:orig_category":"Prodotti Vari In Metallo. Articoli Per Imballaggio E Confezionamento",
    "sg:phone":"+39 02 213 1444",
    "sg:postcode":"20090",
    "sg:province":"Milano",
    "wof:name":"F.i.o.d.o. - Lavorazione Fondi (s.r.l.)",
    "wof:placetype":"venue"
},
  "geometry": {"coordinates":[9.2774896622,45.4963569641],"type":"Point"}
}