{
  "type": "Feature",
  "properties": {
    "iso:country":"IT",
    "sg:address":"83100 Avellino",
    "sg:city":"Avellino",
    "sg:orig_category":"Arredo Bagno Ed Idrosanitari. Complementi Di Arredamento. Vetro: Prodotti E Lavorazioni",
    "sg:phone":"+39 0825 35180",
    "sg:postcode":"83100",
    "sg:province":"Avellino",
    "wof:name":"Cortese Angelo",
    "wof:placetype":"venue"
},
  "geometry": {"coordinates":[14.795842,40.915985],"type":"Point"}
}