{
  "type": "Feature",
  "properties": {
    "iso:country":"IT",
    "sg:address":"12023 Caraglio",
    "sg:city":"Caraglio",
    "sg:orig_category":"Forniture Per Attivita' Industriali. Servizi Ausiliari Di Sorveglianza, Manutenzione E Pulizia",
    "sg:phone":"+39 0171 618835",
    "sg:postcode":"12023",
    "sg:province":"Cuneo",
    "wof:name":"Irec Di Lerda Adriano & C. Snc",
    "wof:placetype":"venue"
},
  "geometry": {"coordinates":[7.3987956047,44.4138183594],"type":"Point"}
}