{
  "type": "Feature",
  "properties": {
    "addr:full":"55, Strada Fantasia 10040 Leini' Torino 10040",
    "addr:postcode":"10040 leini;10040",
    "addr:street":"Strada Fantasia",
    "iso:country":"IT",
    "sg:address":"55, Strada Fantasia 10040 Leini'",
    "sg:classifiers":[
        {
            "category":"Manufacturing",
            "subcategory":"Rubber & Plastics",
            "type":"Manufacturing & Wholesale Goods"
        }
    ],
    "sg:phone":"+39 011 997 4054",
    "sg:postcode":"10040",
    "sg:province":"Torino",
    "wof:name":"Vassoplast (s.n.c.)",
    "wof:placetype":"venue"
},
  "geometry": {"coordinates":[7.7152681351,45.1582107544],"type":"Point"}
}