{
  "type": "Feature",
  "properties": {
    "addr:full":"20014 Nerviano Nerviano Milano 20014",
    "addr:postcode":"20014;20014",
    "iso:country":"IT",
    "sg:address":"20014 Nerviano",
    "sg:city":"Nerviano",
    "sg:classifiers":[
        {
            "category":"Cinema",
            "subcategory":"Movie Theater",
            "type":"Entertainment"
        }
    ],
    "sg:phone":"+39 0331 584289",
    "sg:postcode":"20014",
    "sg:province":"Milano",
    "sg:tags":[
        "bobine"
    ],
    "wof:name":"Florafan Snc",
    "wof:placetype":"venue"
},
  "geometry": {"coordinates":[8.985815,45.555069],"type":"Point"}
}