{
  "type": "Feature",
  "properties": {
    "iso:country":"IT",
    "sg:address":"103, Via Opitergina 33080 Prata Di Pordenone",
    "sg:city":"Prata di Pordenone",
    "sg:classifiers":[
        {
            "category":"Home & Garden",
            "subcategory":"Home Furnishings",
            "type":"Retail Goods"
        }
    ],
    "sg:phone":"+39 0434 620092",
    "sg:postcode":"33080",
    "sg:province":"Pordenone",
    "sg:tags":[
        "household"
    ],
    "wof:name":"Compas Industria Mobili (s.a.s.)",
    "wof:placetype":"venue"
},
  "geometry": {"coordinates":[12.596703,45.895195],"type":"Point"}
}