{
  "type": "Feature",
  "properties": {
    "iso:country":"IT",
    "sg:address":"70010 Casamassima",
    "sg:city":"Casamassima",
    "sg:classifiers":[
        {
            "category":"Personal",
            "subcategory":"Skin Care",
            "type":"Services"
        }
    ],
    "sg:phone":"+39 080 697 0700",
    "sg:postcode":"70010",
    "sg:province":"Bari",
    "sg:tags":[
        "houseware",
        "good",
        "shopping",
        "leather",
        "utensil",
        "skins",
        "footwear",
        "kitchen"
    ],
    "wof:name":"Centroborse Di Barucchelli Anna Sas",
    "wof:placetype":"venue"
},
  "geometry": {"coordinates":[16.9181346893,40.9553070068],"type":"Point"}
}