{
  "type": "Feature",
  "properties": {
    "addr:full":"30174 Venezia Mestre Venezia 30174",
    "addr:postcode":"30174;30174",
    "iso:country":"IT",
    "sg:address":"30174 Venezia",
    "sg:city":"Mestre",
    "sg:orig_category":"Arti Grafiche",
    "sg:phone":"+39 041 961911",
    "sg:postcode":"30174",
    "sg:province":"Venezia",
    "wof:name":"Litostampa Snc Di Alberti, Piccoli & C.",
    "wof:placetype":"venue"
},
  "geometry": {"coordinates":[12.227962,45.503281],"type":"Point"}
}