{
  "type": "Feature",
  "properties": {
    "addr:full":"228, V. P. Veronese 10148 Torino Torino Torino 10148",
    "addr:housenumber":"228",
    "addr:postcode":"10148;10148",
    "addr:street":"V. P. Veronese",
    "iso:country":"IT",
    "sg:address":"228, V. P. Veronese 10148 Torino",
    "sg:city":"Torino",
    "sg:classifiers":[
        {
            "category":"Real Estate",
            "subcategory":"Surveying",
            "type":"Services"
        }
    ],
    "sg:phone":"+39 011 220 7726",
    "sg:postcode":"10148",
    "sg:province":"Torino",
    "sg:tags":[
        "equipment",
        "material",
        "good",
        "-",
        "handling"
    ],
    "sg:website":"http://www.crcricambi.com",
    "wof:name":"Crc Srl",
    "wof:placetype":"venue"
},
  "geometry": {"coordinates":[7.674192,45.109749],"type":"Point"}
}