{
  "type": "Feature",
  "properties": {
    "iso:country":"IT",
    "sg:address":"22, Via Nazioni Unite 24060 Costa Di Mezzate",
    "sg:city":"Costa di Mezzate",
    "sg:classifiers":[
        {
            "category":"Shopping",
            "subcategory":"Clothing, Apparel, & Fashions",
            "type":"Retail Goods"
        }
    ],
    "sg:phone":"+39 39035681240",
    "sg:postcode":"24060",
    "sg:province":"Bergamo",
    "sg:tags":[
        "clothes"
    ],
    "wof:name":"Confezioni Green Teen S.r.l.",
    "wof:placetype":"venue"
},
  "geometry": {"coordinates":[9.805522,45.651478],"type":"Point"}
}