{
  "type": "Feature",
  "properties": {
    "addr:full":"20090 Rodano Rodano Milano 20090",
    "addr:postcode":"20090;20090",
    "iso:country":"IT",
    "sg:address":"20090 Rodano",
    "sg:city":"Rodano",
    "sg:classifiers":[
        {
            "category":"Social Services",
            "subcategory":"Job Training",
            "type":"Services"
        }
    ],
    "sg:phone":"+39 02 9532 8610",
    "sg:postcode":"20090",
    "sg:province":"Milano",
    "sg:tags":[
        "flange"
    ],
    "wof:name":"R.t.i. Srl",
    "wof:placetype":"venue"
},
  "geometry": {"coordinates":[9.338842392,45.4708938599],"type":"Point"}
}