{
  "type": "Feature",
  "properties": {
    "iso:country":"IT",
    "sg:address":"Via Varese 20037 Paderno Dugnano",
    "sg:city":"Paderno Dugnano",
    "sg:classifiers":[
        {
            "category":"Autos & Motor Vehicles",
            "subcategory":"Auto Supplies",
            "type":"Retail Goods"
        }
    ],
    "sg:phone":"+39 02 910 0241",
    "sg:postcode":"20037",
    "sg:province":"Milano",
    "sg:tags":[
        "test",
        "automobile",
        "brake",
        "stand"
    ],
    "wof:name":"Schenck Italia Srl",
    "wof:placetype":"venue"
},
  "geometry": {"coordinates":[9.193069,45.571281],"type":"Point"}
}