{
  "type": "Feature",
  "properties": {
    "iso:country":"IT",
    "sg:address":"34, Via Voldomino 21016 Luino",
    "sg:city":"Luino",
    "sg:classifiers":[
        {
            "category":"Banks & Credit Unions",
            "subcategory":"Investment Brokerage",
            "type":"Services"
        }
    ],
    "sg:phone":"+39 0332 510501",
    "sg:postcode":"21016",
    "sg:province":"Varese",
    "sg:tags":[
        "-",
        "transport",
        "related"
    ],
    "wof:name":"Norfolkline Terminal S.p.a.",
    "wof:placetype":"venue"
},
  "geometry": {"coordinates":[8.743631,45.996082],"type":"Point"}
}