{
  "type": "Feature",
  "properties": {
    "addr:full":"9, Via Barsanti Eugenio 37139 Verona Verona Verona 37139",
    "addr:postcode":"37139;37139",
    "addr:street":"Via Barsanti Eugenio",
    "iso:country":"IT",
    "sg:address":"9, Via Barsanti Eugenio 37139 Verona",
    "sg:city":"Verona",
    "sg:classifiers":[
        {
            "category":"Autos & Motor Vehicles",
            "subcategory":"Automobile Sales",
            "type":"Retail Goods"
        }
    ],
    "sg:phone":"+39 045 851 7711",
    "sg:postcode":"37139",
    "sg:province":"Verona",
    "sg:tags":[
        "industrial"
    ],
    "wof:name":"Japanparts Srl",
    "wof:placetype":"venue"
},
  "geometry": {"coordinates":[10.991748,45.438366],"type":"Point"}
}