{
  "type": "Feature",
  "properties": {
    "iso:country":"IT",
    "sg:address":"95040 Motta Santa Anastasia",
    "sg:orig_category":"Agenzie Di Spettacolo E Di Animazione",
    "sg:phone":"+39 095 303353",
    "sg:postcode":"95040",
    "sg:province":"Catania",
    "wof:name":"Sicil.c.car Srl",
    "wof:placetype":"venue"
},
  "geometry": {"coordinates":[14.5657,37.094334],"type":"Point"}
}