{
  "type": "Feature",
  "properties": {
    "iso:country":"IT",
    "sg:address":"98057 Milazzo",
    "sg:city":"Milazzo",
    "sg:orig_category":"Forniture E Materiali Per Imballaggio E Confezionamento. Forniture Per Uffici. Forniture Per Attivita' Commerciali Ed Artigianali",
    "sg:phone":"+39 090 922 4525",
    "sg:postcode":"98057",
    "sg:province":"Messina",
    "wof:name":"La Rollis Srl",
    "wof:placetype":"venue"
},
  "geometry": {"coordinates":[15.237033844,38.200717926],"type":"Point"}
}