{
  "type": "Feature",
  "properties": {
    "addr:full":"91025 Marsala Marsala Trapani 91025",
    "addr:postcode":"91025;91025",
    "iso:country":"IT",
    "sg:address":"91025 Marsala",
    "sg:city":"Marsala",
    "sg:orig_category":"Prodotti Finiti Stampati. Forniture E Materiali Per Imballaggio E Confezionamento. Forniture Per Attivita' Commerciali Ed Artigianali",
    "sg:phone":"+39 0923 756029",
    "sg:postcode":"91025",
    "sg:province":"Trapani",
    "wof:name":"Marypack Srl",
    "wof:placetype":"venue"
},
  "geometry": {"coordinates":[12.5527505875,37.83253479],"type":"Point"}
}