{
  "type": "Feature",
  "properties": {
    "iso:country":"IT",
    "sg:address":"10125 Torino",
    "sg:city":"Torino",
    "sg:orig_category":"Scuole E Servizi Scolastici. Centri Di Estetica E Cosmesi E Servizi. Ricerca, Selezione E Formazione Del Personale",
    "sg:phone":"+39 011 669 9276",
    "sg:postcode":"10125",
    "sg:province":"Torino",
    "wof:name":"Centro Formazione Professionale Acconciature Femminili Angela (s.n.c.)",
    "wof:placetype":"venue"
},
  "geometry": {"coordinates":[7.677416,45.057991],"type":"Point"}
}