{
  "type": "Feature",
  "properties": {
    "iso:country":"IT",
    "sg:address":"20097 San Donato Milanese",
    "sg:city":"San Donato Milanese",
    "sg:orig_category":"Valvole E Apparecchiature Di Misura. Minuterie Metalliche E Ferramenta. Forniture Per Attivita' Industriali",
    "sg:phone":"+39 02 5162 1300",
    "sg:postcode":"20097",
    "sg:province":"Milano",
    "wof:name":"B.d.m Fluid Trade Srl",
    "wof:placetype":"venue"
},
  "geometry": {"coordinates":[9.263659,45.429562],"type":"Point"}
}