{
  "type": "Feature",
  "properties": {
    "addr:full":"84060 Omignano Omignano Salerno 84060",
    "addr:postcode":"84060;84060",
    "addr:street":"Omignano",
    "iso:country":"IT",
    "sg:address":"84060 Omignano",
    "sg:city":"Omignano",
    "sg:orig_category":"Torrefazione Di Caffe' Ed Affini - Lavorazione E Ingrosso",
    "sg:phone":"+39 0974 64242",
    "sg:postcode":"84060",
    "sg:province":"Salerno",
    "wof:name":"Mokabrasil Srl",
    "wof:placetype":"venue"
},
  "geometry": {"coordinates":[15.085567,40.249016],"type":"Point"}
}