{
  "type": "Feature",
  "properties": {
    "addr:full":"37134 Verona Verona Verona 37134",
    "addr:postcode":"37134;37134",
    "iso:country":"IT",
    "sg:address":"37134 Verona",
    "sg:city":"Verona",
    "sg:orig_category":"Materiali Semilavorati Metallici",
    "sg:phone":"+39 045 826 6107",
    "sg:postcode":"37134",
    "sg:province":"Verona",
    "wof:name":"Ortolani Adelino Srl",
    "wof:placetype":"venue"
},
  "geometry": {"coordinates":[11.00868,45.414845],"type":"Point"}
}