{
  "type": "Feature",
  "properties": {
    "iso:country":"IT",
    "sg:address":"10090 Rosta",
    "sg:city":"Rosta",
    "sg:orig_category":"Apparecchiature Elettroniche",
    "sg:phone":"+39 011 954 0781",
    "sg:postcode":"10090",
    "sg:province":"Torino",
    "sg:website":"http://www.oselin.com",
    "wof:name":"Oselin Albano",
    "wof:placetype":"venue"
},
  "geometry": {"coordinates":[7.477191,45.045101],"type":"Point"}
}