{
  "type": "Feature",
  "properties": {
    "addr:full":"20016 Pero Pero Milano 20016",
    "addr:postcode":"20016;20016",
    "iso:country":"IT",
    "sg:address":"20016 Pero",
    "sg:city":"Pero",
    "sg:orig_category":"Ristorazione E Locali Pubblici Affini. Ristoranti Ed Esercizi Affini",
    "sg:phone":"+39 02 353 5305",
    "sg:postcode":"20016",
    "sg:province":"Milano",
    "wof:name":"Autogrill S.p.a.",
    "wof:placetype":"venue"
},
  "geometry": {"coordinates":[9.061481,45.512276],"type":"Point"}
}