{
  "type": "Feature",
  "properties": {
    "iso:country":"IT",
    "sg:address":"07040 Stintino",
    "sg:city":"Stintino",
    "sg:orig_category":"Frigotecnica, Apparecchiature E Servizi. Servizi Di Magazzinaggio E Movimentazione",
    "sg:phone":"+39 079 523374",
    "sg:postcode":"07040",
    "sg:province":"Sassari",
    "wof:name":"Giovanni Rivieccio & C. Snc",
    "wof:placetype":"venue"
},
  "geometry": {"coordinates":[8.2251501083,40.937122345],"type":"Point"}
}