{
  "type": "Feature",
  "properties": {
    "addr:full":"12042 Bra Bra Cuneo 12042",
    "addr:postcode":"12042;12042",
    "iso:country":"IT",
    "sg:address":"12042 Bra",
    "sg:city":"Bra",
    "sg:orig_category":"Alberghi E Strutture Extra Alberghiere",
    "sg:phone":"+39 0172 44884",
    "sg:postcode":"12042",
    "sg:province":"Cuneo",
    "wof:name":"Sordo Michela",
    "wof:placetype":"venue"
},
  "geometry": {"coordinates":[7.855922,44.696377],"type":"Point"}
}