{
  "type": "Feature",
  "properties": {
    "addr:full":"46018 Sabbioneta Sabbioneta Mantova 46018",
    "addr:postcode":"46018;46018",
    "iso:country":"IT",
    "sg:address":"46018 Sabbioneta",
    "sg:city":"Sabbioneta",
    "sg:orig_category":"Forniture Per Attivita' Industriali",
    "sg:phone":"+39 0375 52698",
    "sg:postcode":"46018",
    "sg:province":"Mantova",
    "sg:website":"http://www.condorpennelli.com",
    "wof:name":"Pennellificio Condor Snc",
    "wof:placetype":"venue"
},
  "geometry": {"coordinates":[10.4858961105,44.9956207275],"type":"Point"}
}