{
  "type": "Feature",
  "properties": {
    "iso:country":"IT",
    "sg:address":"22036 Erba",
    "sg:city":"Erba",
    "sg:orig_category":"Servizi E Lavori Per Abbigliamento E Pelletterie",
    "sg:phone":"+39 031 610739",
    "sg:postcode":"22036",
    "sg:province":"Como",
    "wof:name":"Odone Maria",
    "wof:placetype":"venue"
},
  "geometry": {"coordinates":[9.161435,45.793179],"type":"Point"}
}