{
  "type": "Feature",
  "properties": {
    "iso:country":"IT",
    "sg:address":"80138 Napoli",
    "sg:city":"Napoli",
    "sg:orig_category":"Estetiste",
    "sg:phone":"+39 081 553 9672",
    "sg:postcode":"80138",
    "sg:province":"Napoli",
    "wof:name":"Dibi Center Magia Di Tina Roberto",
    "wof:placetype":"venue"
},
  "geometry": {"coordinates":[14.26172,40.848969],"type":"Point"}
}