{
  "type": "Feature",
  "properties": {
    "addr:full":"21052 Busto Arsizio Busto Arsizio Varese 21052",
    "addr:postcode":"21052;21052",
    "iso:country":"IT",
    "sg:address":"21052 Busto Arsizio",
    "sg:city":"Busto Arsizio",
    "sg:orig_category":"Abbigliamento Esterno, Maglierie E Pelliccerie. Shopping",
    "sg:phone":"+39 0331 633475",
    "sg:postcode":"21052",
    "sg:province":"Varese",
    "wof:name":"Ferrario Snc Di Luigi Ferrario & C.",
    "wof:placetype":"venue"
},
  "geometry": {"coordinates":[8.842607,45.615776],"type":"Point"}
}