{
  "type": "Feature",
  "properties": {
    "addr:full":"18, Via Della Canova 38100 Trento Trento Trento 38100",
    "addr:postcode":"38100;38100",
    "addr:street":"Via Della Canova",
    "iso:country":"IT",
    "sg:address":"18, Via Della Canova 38100 Trento",
    "sg:city":"Trento",
    "sg:classifiers":[
        {
            "category":"Wholesale",
            "subcategory":"Machinery & Supplies",
            "type":"Manufacturing & Wholesale Goods"
        }
    ],
    "sg:phone":"+39 0461 992521",
    "sg:postcode":"38100",
    "sg:province":"Trento",
    "sg:tags":[
        "-",
        "agriculture",
        "equipment"
    ],
    "wof:name":"Odorizzi Ottorino & Figli (s.n.c.)",
    "wof:placetype":"venue"
},
  "geometry": {"coordinates":[11.11021,46.098816],"type":"Point"}
}