{
  "type": "Feature",
  "properties": {
    "addr:full":"15, V. Quattro Passi 41043 Formigine Formigine Modena 41043",
    "addr:housenumber":"15",
    "addr:postcode":"41043;41043",
    "addr:street":"V. Quattro",
    "iso:country":"IT",
    "sg:address":"15, V. Quattro Passi 41043 Formigine",
    "sg:city":"Formigine",
    "sg:classifiers":[
        {
            "category":"Shopping",
            "type":"Retail Goods"
        }
    ],
    "sg:phone":"+39 39059410302",
    "sg:postcode":"41043",
    "sg:province":"Modena",
    "sg:tags":[
        "finished",
        "-",
        "metallic"
    ],
    "sg:website":"http://www.tellurerota.com",
    "wof:name":"Tellure Rota Spa",
    "wof:placetype":"venue"
},
  "geometry": {"coordinates":[10.8515167236,44.5613822937],"type":"Point"}
}