{
  "type": "Feature",
  "properties": {
    "iso:country":"IT",
    "sg:address":"Traversa Iii Saggese 80013 Casalnuovo Di Napoli",
    "sg:city":"Casalnuovo di Napoli",
    "sg:classifiers":[
        {
            "category":"Real Estate",
            "subcategory":"Architect",
            "type":"Services"
        }
    ],
    "sg:phone":"+39 081 522 1960",
    "sg:postcode":"80013",
    "sg:province":"Napoli",
    "sg:tags":[
        "textile",
        "clothing"
    ],
    "wof:name":"2 G Piccolo Angela",
    "wof:placetype":"venue"
},
  "geometry": {"coordinates":[14.359294,40.914467],"type":"Point"}
}