{
  "type": "Feature",
  "properties": {
    "iso:country":"IT",
    "sg:address":"54, V. F. Baracca 30030 Galta Di Vigonovo",
    "sg:city":"Galta",
    "sg:classifiers":[
        {
            "category":"Personal",
            "subcategory":"Shoe Repair & Shine",
            "type":"Services"
        }
    ],
    "sg:phone":"+39 049 983 1983",
    "sg:postcode":"30030",
    "sg:province":"Venezia",
    "sg:tags":[
        "leather"
    ],
    "sg:website":"http://www.paginegialle.it/leosport",
    "wof:name":"Leo Sport",
    "wof:placetype":"venue"
},
  "geometry": {"coordinates":[12.338784,45.434338],"type":"Point"}
}