{
  "type": "Feature",
  "properties": {
    "iso:country":"IT",
    "sg:address":"9, Via Modigliani Amedeo 20092 Cinisello Balsamo",
    "sg:city":"Cinisello Balsamo",
    "sg:classifiers":[
        {
            "category":"Professional",
            "subcategory":"Engineering",
            "type":"Services"
        }
    ],
    "sg:phone":"+39 39026174903",
    "sg:postcode":"20092",
    "sg:province":"Milano",
    "sg:tags":[
        "machine",
        "-",
        "mechanical"
    ],
    "wof:name":"Attrezzeria Meroni (s.r.l.)",
    "wof:placetype":"venue"
},
  "geometry": {"coordinates":[9.201434,45.548569],"type":"Point"}
}