{
  "type": "Feature",
  "properties": {
    "addr:full":"56, Viale Bligny 20136 Milano Milano Milano 20136",
    "addr:housenumber":"56",
    "addr:postcode":"20136;20136",
    "addr:street":"Viale Bligny",
    "iso:country":"IT",
    "sg:address":"56, Viale Bligny 20136 Milano",
    "sg:city":"Milano",
    "sg:classifiers":[
        {
            "category":"Travel",
            "subcategory":"Travel Agent",
            "type":"Entertainment"
        }
    ],
    "sg:phone":"+39 02 5831 8562",
    "sg:postcode":"20136",
    "sg:province":"Milano",
    "sg:tags":[
        "business"
    ],
    "wof:name":"Albergo Liberty",
    "wof:placetype":"venue"
},
  "geometry": {"coordinates":[9.194798,45.450924],"type":"Point"}
}