{
  "type": "Feature",
  "properties": {
    "addr:full":"20052 Monza Monza Milano 20052",
    "addr:postcode":"20052;20052",
    "iso:country":"IT",
    "sg:address":"20052 Monza",
    "sg:city":"Monza",
    "sg:orig_category":"Elettronica Professionale E Di Consumo. Automazione E Macchine Per Ufficio. Forniture Industriali Per Prevenzione, Controllo E Sicurezza",
    "sg:phone":"+39 039 230 4617",
    "sg:postcode":"20052",
    "sg:province":"Milano",
    "sg:website":"http://www.eurocontrolli.com",
    "wof:name":"Eurocontrolli Srl",
    "wof:placetype":"venue"
},
  "geometry": {"coordinates":[9.288399,45.532249],"type":"Point"}
}