{
  "type": "Feature",
  "properties": {
    "addr:full":"22025 Lezzeno Lezzeno Como 22025",
    "addr:postcode":"22025;22025",
    "iso:country":"IT",
    "sg:address":"22025 Lezzeno",
    "sg:city":"Lezzeno",
    "sg:orig_category":"Materiali Semilavorati Metallici",
    "sg:phone":"+39 031 915200",
    "sg:postcode":"22025",
    "sg:province":"Como",
    "wof:name":"Schiavone Alberto",
    "wof:placetype":"venue"
},
  "geometry": {"coordinates":[9.186744,45.944958],"type":"Point"}
}