{
  "type": "Feature",
  "properties": {
    "addr:full":"10122 Torino Torino Torino 10122",
    "addr:housenumber":"10122",
    "addr:postcode":"10122",
    "iso:country":"IT",
    "sg:address":"10122 Torino",
    "sg:city":"Torino",
    "sg:orig_category":"Articoli Da Regalo. Regalistica Aziendale",
    "sg:phone":"+39 011 531764",
    "sg:postcode":"10122",
    "sg:province":"Torino",
    "wof:name":"Bottega Del Natale Di Martolini Sergio",
    "wof:placetype":"venue"
},
  "geometry": {"coordinates":[7.680982,45.071575],"type":"Point"}
}