{
  "type": "Feature",
  "properties": {
    "iso:country":"IT",
    "sg:address":"6, Via Piave 31040 Volpago Del Montello",
    "sg:city":"Volpago del Montello",
    "sg:classifiers":[
        {
            "category":"Personal",
            "subcategory":"Shoe Repair & Shine",
            "type":"Services"
        }
    ],
    "sg:phone":"+39 0423 870058",
    "sg:postcode":"31040",
    "sg:province":"Treviso",
    "sg:tags":[
        "leather"
    ],
    "wof:name":"Calzaturificio Effe Tre (s.r.l.)",
    "wof:placetype":"venue"
},
  "geometry": {"coordinates":[12.110033,45.775658],"type":"Point"}
}