{
  "type": "Feature",
  "properties": {
    "addr:full":"1, Via Della Meccanica 41042 Fiorano Modenese Fiorano Modenese Modena 41042",
    "addr:postcode":"41042;41042",
    "addr:street":"Via Della Meccanica",
    "iso:country":"IT",
    "sg:address":"1, Via Della Meccanica 41042 Fiorano Modenese",
    "sg:city":"Fiorano Modenese",
    "sg:classifiers":[
        {
            "category":"Shopping",
            "subcategory":"Clothing, Apparel, & Fashions",
            "type":"Retail Goods"
        }
    ],
    "sg:phone":"+39 0536 843356",
    "sg:postcode":"41042",
    "sg:province":"Modena",
    "sg:tags":[
        "clothes"
    ],
    "wof:name":"Manicardi Ecologia S.n.c.",
    "wof:placetype":"venue"
},
  "geometry": {"coordinates":[10.839257,44.540035],"type":"Point"}
}