{
  "type": "Feature",
  "properties": {
    "addr:full":"00146 Roma Roma Roma 00146",
    "addr:postcode":"00146;00146",
    "iso:country":"IT",
    "sg:address":"00146 Roma",
    "sg:city":"Roma",
    "sg:orig_category":"Ricambi E Componenti Dei Mezzi Di Trasporto",
    "sg:phone":"+39 06 550 2930",
    "sg:postcode":"00146",
    "sg:province":"Roma",
    "wof:name":"Bastoni Riccardo",
    "wof:placetype":"venue"
},
  "geometry": {"coordinates":[12.463638,41.849285],"type":"Point"}
}