{
  "type": "Feature",
  "properties": {
    "iso:country":"IT",
    "sg:address":"Localita' Pesciola 50051 Castelfiorentino",
    "sg:city":"Castelfiorentino",
    "sg:classifiers":[
        {
            "category":"Home & Garden",
            "subcategory":"Home Furnishings",
            "type":"Retail Goods"
        }
    ],
    "sg:phone":"+39 39057161114",
    "sg:postcode":"50051",
    "sg:province":"Firenze",
    "sg:tags":[
        "household"
    ],
    "wof:name":"Essepiemme Mobili (s.r.l.)",
    "wof:placetype":"venue"
},
  "geometry": {"coordinates":[11.256902,43.768734],"type":"Point"}
}