{
  "type": "Feature",
  "properties": {
    "iso:country":"IT",
    "sg:address":"10154 Torino",
    "sg:city":"Torino",
    "sg:orig_category":"Elettricisti",
    "sg:phone":"+39 011 247 0956",
    "sg:postcode":"10154",
    "sg:province":"Torino",
    "wof:name":"Real Elettrotecnica Sas Di Martoccia & Gruttadauria & C.",
    "wof:placetype":"venue"
},
  "geometry": {"coordinates":[8.39892,45.462345],"type":"Point"}
}