{
  "type": "Feature",
  "properties": {
    "iso:country":"IT",
    "sg:address":"40011 Anzola Dell'emilia",
    "sg:orig_category":"Manufacturers: Prefabbricati. Servizi E Lavori Per Ecologia E Smaltimento Rifiuti",
    "sg:phone":"+39 051 731110",
    "sg:postcode":"40011",
    "sg:province":"Bologna",
    "wof:name":"Venturi Autospurghi Srl",
    "wof:placetype":"venue"
},
  "geometry": {"coordinates":[11.217473,44.551399],"type":"Point"}
}