{
  "type": "Feature",
  "properties": {
    "addr:full":"71042 Cerignola Cerignola Foggia 71042",
    "addr:postcode":"71042;71042",
    "iso:country":"IT",
    "sg:address":"71042 Cerignola",
    "sg:city":"Cerignola",
    "sg:orig_category":"Impiantistica E Prodotti Tecnologici Per Edilizia. Elettrotecnica Industriale, Prodotti E Apparecchiature",
    "sg:phone":"+39 0885 414229",
    "sg:postcode":"71042",
    "sg:province":"Foggia",
    "sg:website":"http://www.lapige.it",
    "wof:name":"La.pi.ge. Dei F.lli Ladogana Srl",
    "wof:placetype":"venue"
},
  "geometry": {"coordinates":[15.92299,41.240726],"type":"Point"}
}