{
  "type": "Feature",
  "properties": {
    "iso:country":"IT",
    "sg:address":"95129 Catania",
    "sg:city":"Catania",
    "sg:classifiers":[
        {
            "category":"Health Services",
            "subcategory":"Nursing And Care Facility",
            "type":"Services"
        }
    ],
    "sg:phone":"+39 095 509457",
    "sg:postcode":"95129",
    "sg:province":"Catania",
    "sg:tags":[
        "case",
        "cura",
        "private",
        "di"
    ],
    "wof:name":"Health Orthopaedics Srl",
    "wof:placetype":"venue"
},
  "geometry": {"coordinates":[15.092015,37.5158],"type":"Point"}
}