{
  "type": "Feature",
  "properties": {
    "iso:country":"IT",
    "sg:address":"00186 Roma",
    "sg:city":"Roma",
    "sg:orig_category":"Accademie",
    "sg:phone":"+39 06 686 4132",
    "sg:postcode":"00186",
    "sg:province":"Roma",
    "sg:website":"http://www.accademiacostumeemoda.it",
    "wof:name":"Accademia Di Costume E Di Moda",
    "wof:placetype":"venue"
},
  "geometry": {"coordinates":[12.468513,41.901146],"type":"Point"}
}