{
  "type": "Feature",
  "properties": {
    "iso:country":"IT",
    "sg:address":"61100 Pesaro",
    "sg:city":"Pesaro",
    "sg:orig_category":"Servizi E Lavori Industria Chimica",
    "sg:phone":"+39 0721 281591",
    "sg:postcode":"61100",
    "sg:province":"Pesaro E Urbino",
    "wof:name":"Carloncini Emilio & C. Snc",
    "wof:placetype":"venue"
},
  "geometry": {"coordinates":[12.874008,43.886642],"type":"Point"}
}