{
  "type": "Feature",
  "properties": {
    "addr:full":"20159 Milano Milano Milano 20159",
    "addr:postcode":"20159;20159",
    "iso:country":"IT",
    "sg:address":"20159 Milano",
    "sg:city":"Milano",
    "sg:orig_category":"Studi E Consulenze Amministrative, Commerciali E Aziendali. Consulenze Tecniche, Amministrative E Perizie. Professionisti - Studi E Servizi Ed Associazioni Di Interesse Aziendale",
    "sg:phone":"+39 02 607 1125",
    "sg:postcode":"20159",
    "sg:province":"Milano",
    "wof:name":"M. & V. Consulting Srl",
    "wof:placetype":"venue"
},
  "geometry": {"coordinates":[9.182116,45.489071],"type":"Point"}
}