{
  "type": "Feature",
  "properties": {
    "addr:full":"24060 Cenate Sopra Cenate Sopra Bergamo 24060",
    "addr:postcode":"24060;24060",
    "addr:street":"Sopra",
    "iso:country":"IT",
    "sg:address":"24060 Cenate Sopra",
    "sg:city":"Cenate Sopra",
    "sg:orig_category":"Scuole E Servizi Scolastici. Ospedali E Servizi Sanitari",
    "sg:phone":"+39 035 956100",
    "sg:postcode":"24060",
    "sg:province":"Bergamo",
    "wof:name":"Societa' Cooperativa L'impronta A R.l.",
    "wof:placetype":"venue"
},
  "geometry": {"coordinates":[9.823736,45.712654],"type":"Point"}
}