{
  "type": "Feature",
  "properties": {
    "addr:full":"07010 Nule Nule Sassari 07010",
    "addr:postcode":"07010;07010",
    "iso:country":"IT",
    "sg:address":"07010 Nule",
    "sg:city":"Nule",
    "sg:orig_category":"Filati E Tessuti - Trattamenti",
    "sg:phone":"+39 079 790860",
    "sg:postcode":"07010",
    "sg:province":"Sassari",
    "sg:website":"http://www.infovacanze.com/crabolu",
    "wof:name":"Tessile Crabolu",
    "wof:placetype":"venue"
},
  "geometry": {"coordinates":[8.5632314682,40.7256698608],"type":"Point"}
}