{
  "type": "Feature",
  "properties": {
    "iso:country":"IT",
    "sg:address":"61, Via Branze 25123 Brescia",
    "sg:city":"Brescia",
    "sg:classifiers":[
        {
            "category":"Travel",
            "subcategory":"Travel Agent",
            "type":"Entertainment"
        }
    ],
    "sg:phone":"+39 39030381528",
    "sg:postcode":"25123",
    "sg:province":"Brescia",
    "sg:tags":[
        "business"
    ],
    "wof:name":"Gruppo Ca' Noa S.p.a.",
    "wof:placetype":"venue"
},
  "geometry": {"coordinates":[10.230113,45.564018],"type":"Point"}
}