{
  "type": "Feature",
  "properties": {
    "iso:country":"IT",
    "sg:address":"36030 Zugliano",
    "sg:city":"Zugliano",
    "sg:classifiers":[
        {
            "category":"Manufacturing",
            "subcategory":"Tools & Machinery",
            "type":"Manufacturing & Wholesale Goods"
        }
    ],
    "sg:phone":"+39 0445 330111",
    "sg:postcode":"36030",
    "sg:province":"Vicenza",
    "sg:tags":[
        "leather",
        "equipment",
        "goods",
        "clothing"
    ],
    "sg:website":"http://www.magnabosco.com",
    "wof:name":"Magnabosco Srl",
    "wof:placetype":"venue"
},
  "geometry": {"coordinates":[11.516881,45.73185],"type":"Point"}
}