{
  "type": "Feature",
  "properties": {
    "addr:full":"00172 Roma Roma Roma 00172",
    "addr:postcode":"00172;00172",
    "iso:country":"IT",
    "sg:address":"00172 Roma",
    "sg:city":"Roma",
    "sg:orig_category":"Minuterie Metalliche E Ferramenta",
    "sg:phone":"+39 06 242 6227",
    "sg:postcode":"00172",
    "sg:province":"Roma",
    "wof:name":"Ferramenta Romano Dolci & C. Snc",
    "wof:placetype":"venue"
},
  "geometry": {"coordinates":[12.5638246536,41.878238678],"type":"Point"}
}