{
  "type": "Feature",
  "properties": {
    "addr:full":"71100 Foggia Foggia Foggia 71100",
    "addr:postcode":"71100;71100",
    "iso:country":"IT",
    "sg:address":"71100 Foggia",
    "sg:city":"Foggia",
    "sg:classifiers":[
        {
            "category":"Sports & Exercise",
            "subcategory":"Tennis Court",
            "type":"Entertainment"
        }
    ],
    "sg:phone":"+39 0881 723870",
    "sg:postcode":"71100",
    "sg:province":"Foggia",
    "sg:tags":[
        "e",
        "lo",
        "tempo",
        "libero",
        "per",
        "impianti",
        "il",
        "attrezzature"
    ],
    "wof:name":"Errede Vito",
    "wof:placetype":"venue"
},
  "geometry": {"coordinates":[15.910334,41.627056],"type":"Point"}
}