{
  "type": "Feature",
  "properties": {
    "addr:full":"40133 Bologna Bologna Bologna 40133",
    "addr:postcode":"40133;40133",
    "iso:country":"IT",
    "sg:address":"40133 Bologna",
    "sg:city":"Bologna",
    "sg:orig_category":"Antincendio - Impianti, Attrezzature E Materiali",
    "sg:phone":"+39 051 384181",
    "sg:postcode":"40133",
    "sg:province":"Bologna",
    "wof:name":"Gi.sa. Snc Di Savoca Aldo & C.",
    "wof:placetype":"venue"
},
  "geometry": {"coordinates":[11.300964,44.506054],"type":"Point"}
}