{
  "type": "Feature",
  "properties": {
    "addr:full":"65126 Pescara Pescara Pescara 65126",
    "addr:postcode":"65126;65126",
    "iso:country":"IT",
    "sg:address":"65126 Pescara",
    "sg:city":"Pescara",
    "sg:orig_category":"Forniture Per Edilizia E Lavori Pubblici",
    "sg:phone":"+39 085 820 6820",
    "sg:postcode":"65126",
    "sg:province":"Pescara",
    "wof:name":"Transact Service Srl",
    "wof:placetype":"venue"
},
  "geometry": {"coordinates":[14.225060463,42.4614562988],"type":"Point"}
}