{
  "type": "Feature",
  "properties": {
    "iso:country":"IT",
    "sg:address":"93016 Riesi",
    "sg:city":"Riesi",
    "sg:orig_category":"Chiese Ed Associazioni Religiose",
    "sg:phone":"+39 0934 920282",
    "sg:postcode":"93016",
    "sg:province":"Caltanissetta",
    "wof:name":"Servizio Cristiano",
    "wof:placetype":"venue"
},
  "geometry": {"coordinates":[14.08936,37.278931],"type":"Point"}
}