{
  "type": "Feature",
  "properties": {
    "addr:full":"Via Arzignano 43 36072 Chiampo Chiampo Vicenza 36072",
    "addr:housenumber":"43",
    "addr:postcode":"36072;36072",
    "addr:street":"Via Arzignano",
    "iso:country":"IT",
    "sg:address":"Via Arzignano 43 36072 Chiampo",
    "sg:city":"Chiampo",
    "sg:classifiers":[
        {
            "category":"Home & Garden",
            "subcategory":"Building Materials",
            "type":"Retail Goods"
        }
    ],
    "sg:phone":"+39 0444 420750",
    "sg:postcode":"36072",
    "sg:province":"Vicenza",
    "sg:tags":[
        "slab",
        "marble"
    ],
    "wof:name":"Pi.ba.marmi S.r.l.",
    "wof:placetype":"venue"
},
  "geometry": {"coordinates":[11.302102,45.534027],"type":"Point"}
}