{
  "type": "Feature",
  "properties": {
    "iso:country":"IT",
    "sg:address":"34139 Trieste",
    "sg:city":"Trieste",
    "sg:orig_category":"Servizi Ausiliari Di Analisi, Controllo E Ricerca",
    "sg:phone":"+39 040 938 0020",
    "sg:postcode":"34139",
    "sg:province":"Trieste",
    "wof:name":"Inspections & Consulting S.r.l.",
    "wof:placetype":"venue"
},
  "geometry": {"coordinates":[13.793214,45.639793],"type":"Point"}
}