{
  "type": "Feature",
  "properties": {
    "iso:country":"IT",
    "sg:address":"Via Maglioleo 68 13900 Biella",
    "sg:city":"Biella",
    "sg:classifiers":[
        {
            "category":"Health Services",
            "subcategory":"Medical Lab",
            "type":"Services"
        }
    ],
    "sg:phone":"+39 015 22278",
    "sg:postcode":"13900",
    "sg:province":"Biella",
    "sg:tags":[
        "appliance",
        "system"
    ],
    "wof:name":"Officina Coppa S.r.l.",
    "wof:placetype":"venue"
},
  "geometry": {"coordinates":[8.073322,45.56559],"type":"Point"}
}