{
  "type": "Feature",
  "properties": {
    "addr:full":"34122 Trieste Trieste Trieste 34122",
    "addr:postcode":"34122;34122",
    "iso:country":"IT",
    "sg:address":"34122 Trieste",
    "sg:city":"Trieste",
    "sg:orig_category":"Consulenza Assicurativa",
    "sg:phone":"+39 040 660810",
    "sg:postcode":"34122",
    "sg:province":"Trieste",
    "wof:name":"Assigest Srl",
    "wof:placetype":"venue"
},
  "geometry": {"coordinates":[13.783402,45.646832],"type":"Point"}
}