{
  "type": "Feature",
  "properties": {
    "addr:full":"31038 Paese Paese Treviso 31038",
    "addr:postcode":"31038;31038",
    "addr:street":"Paese Paese",
    "iso:country":"IT",
    "sg:address":"31038 Paese",
    "sg:city":"Paese",
    "sg:orig_category":"Impiantistica E Prodotti Tecnologici Per Edilizia. Termotecnica E Riscaldamento, Apparecchiature E Servizi",
    "sg:phone":"+39 0422 450246",
    "sg:postcode":"31038",
    "sg:province":"Treviso",
    "wof:name":"Ceron Giorgio Termoidraulica",
    "wof:placetype":"venue"
},
  "geometry": {"coordinates":[12.333777,45.724854],"type":"Point"}
}