{
  "type": "Feature",
  "properties": {
    "addr:full":"70123 Bari Bari Bari 70123",
    "addr:postcode":"70123;70123",
    "iso:country":"IT",
    "sg:address":"70123 Bari",
    "sg:city":"Bari",
    "sg:orig_category":"Macchine Utensili E Impianti",
    "sg:phone":"+39 080 505 6833",
    "sg:postcode":"70123",
    "sg:province":"Bari",
    "wof:name":"Berera Sud S.p.a.",
    "wof:placetype":"venue"
},
  "geometry": {"coordinates":[16.829859,41.043098],"type":"Point"}
}