{
  "type": "Feature",
  "properties": {
    "addr:full":"80147 Napoli Napoli Napoli 80147",
    "addr:postcode":"80147;80147",
    "iso:country":"IT",
    "sg:address":"80147 Napoli",
    "sg:city":"Napoli",
    "sg:orig_category":"Motori Ed Organi Di Trasmissione",
    "sg:phone":"+39 081 752 0171",
    "sg:postcode":"80147",
    "sg:province":"Napoli",
    "sg:website":"http://www.upatsud.it",
    "wof:name":"U.p.a.t. Sud Srl",
    "wof:placetype":"venue"
},
  "geometry": {"coordinates":[14.3438005447,40.8651733398],"type":"Point"}
}