{
  "type": "Feature",
  "properties": {
    "addr:full":"53/55, Via Papa Paolo Vi 25080 Nuvolera Nuvolera Brescia 25080",
    "addr:housenumber":"53 / 55",
    "addr:postcode":"25080;25080",
    "addr:street":"Via Papa Paolo Vi",
    "iso:country":"IT",
    "sg:address":"53/55, Via Papa Paolo Vi 25080 Nuvolera",
    "sg:city":"Nuvolera",
    "sg:classifiers":[
        {
            "category":"Professional",
            "subcategory":"Engineering",
            "type":"Services"
        }
    ],
    "sg:phone":"+39 030 689 7292",
    "sg:postcode":"25080",
    "sg:province":"Brescia",
    "sg:tags":[
        "machine",
        "-",
        "mechanical"
    ],
    "wof:name":"Nocera Precision Tools Di Nocera Eugenio",
    "wof:placetype":"venue"
},
  "geometry": {"coordinates":[10.222958,45.539829],"type":"Point"}
}