{
  "type": "Feature",
  "properties": {
    "addr:full":"73, Via Toti Enrico 31048 San Biagio Di Callalta San Biagio di Callalta Treviso 31048",
    "addr:postcode":"31048;31048",
    "addr:street":"Via Toti Enrico",
    "iso:country":"IT",
    "sg:address":"73, Via Toti Enrico 31048 San Biagio Di Callalta",
    "sg:city":"San Biagio di Callalta",
    "sg:classifiers":[
        {
            "category":"Building & Trades",
            "subcategory":"Construction",
            "type":"Services"
        }
    ],
    "sg:phone":"+39 0422 890200",
    "sg:postcode":"31048",
    "sg:province":"Treviso",
    "sg:tags":[
        "work",
        "public"
    ],
    "wof:name":"Coletto (s.p.a.)",
    "wof:placetype":"venue"
},
  "geometry": {"coordinates":[12.456962,45.706165],"type":"Point"}
}