{
  "type": "Feature",
  "properties": {
    "iso:country":"IT",
    "sg:address":"20131 Milano",
    "sg:city":"Milano",
    "sg:orig_category":"Ospedali E Servizi Sanitari",
    "sg:phone":"+39 02 236 0460",
    "sg:postcode":"20131",
    "sg:province":"Milano",
    "wof:name":"Studio Preda Di M. Pizzochero & C. Sas",
    "wof:placetype":"venue"
},
  "geometry": {"coordinates":[9.229949,45.484344],"type":"Point"}
}