{
  "type": "Feature",
  "properties": {
    "addr:full":"Via G. D'annunzio, 113; Genova; 16121 Genova Genova 16121",
    "addr:housenumber":"113",
    "addr:postcode":"16121;16121",
    "addr:street":"Via G. D'Annunzio",
    "iso:country":"IT",
    "sg:address":"Via G. D'annunzio, 113; Genova; 16121",
    "sg:city":"Genova",
    "sg:classifiers":[
        {
            "category":"Banks & Credit Unions",
            "subcategory":"Bank",
            "type":"Services"
        }
    ],
    "sg:phone":"+39 010 5501 3445",
    "sg:postcode":"16121",
    "sg:province":"Genova",
    "wof:name":"Banco Ambrosiano Veneto Spa",
    "wof:placetype":"venue"
},
  "geometry": {"coordinates":[8.935349,44.404789],"type":"Point"}
}