{
  "type": "Feature",
  "properties": {
    "iso:country":"IT",
    "sg:address":"20091 Bresso",
    "sg:city":"Bresso",
    "sg:orig_category":"Acciaierie E Fonderie",
    "sg:phone":"+39 02 610 0392",
    "sg:postcode":"20091",
    "sg:province":"Milano",
    "wof:name":"Fongaltogi Di Lanzani Alberto & C. S.n.c.",
    "wof:placetype":"venue"
},
  "geometry": {"coordinates":[9.189762,45.53289],"type":"Point"}
}