{
  "type": "Feature",
  "properties": {
    "addr:full":"Via Giovanni Da Procida 10 20149 Milano Milano Milano 20149",
    "addr:housenumber":"10",
    "addr:postcode":"20149;20149",
    "addr:street":"Via Giovanni Da Procida",
    "iso:country":"IT",
    "sg:address":"Via Giovanni Da Procida 10 20149 Milano",
    "sg:city":"Milano",
    "sg:classifiers":[
        {
            "category":"Manufacturing",
            "subcategory":"Chemicals & Compounds",
            "type":"Manufacturing & Wholesale Goods"
        }
    ],
    "sg:phone":"+39 02 3453 7459",
    "sg:postcode":"20149",
    "sg:province":"Milano",
    "sg:tags":[
        "base"
    ],
    "sg:website":"www.alfatrade.net",
    "wof:name":"Alfa Trade Srl",
    "wof:placetype":"venue"
},
  "geometry": {"coordinates":[9.161996,45.4799],"type":"Point"}
}