{
  "type": "Feature",
  "properties": {
    "addr:full":"Via Calabbiana 1 51030 Piteccio Pistoia 51030",
    "addr:housenumber":"1",
    "addr:postcode":"51030;51030",
    "addr:street":"Via Calabbiana",
    "iso:country":"IT",
    "sg:address":"Via Calabbiana 1 51030 Piteccio",
    "sg:classifiers":[
        {
            "category":"Manufacturing",
            "subcategory":"Paper Products",
            "type":"Manufacturing & Wholesale Goods"
        }
    ],
    "sg:phone":"+39 0573 99871",
    "sg:postcode":"51030",
    "sg:province":"Pistoia",
    "sg:tags":[
        "box",
        "folding",
        "uncoated",
        "coated",
        "cardboard"
    ],
    "wof:name":"Cartiera San Felice Spa",
    "wof:placetype":"venue"
},
  "geometry": {"coordinates":[10.8975868225,44.0068473816],"type":"Point"}
}