{
  "type": "Feature",
  "properties": {
    "iso:country":"IT",
    "sg:address":"23900 Lecco",
    "sg:city":"Lecco",
    "sg:orig_category":"Scuole E Servizi Scolastici. Ricerca, Selezione E Formazione Del Personale",
    "sg:phone":"+39 0341 250760",
    "sg:postcode":"23900",
    "sg:province":"Lecco",
    "wof:name":"Istituto A. Volta Srl",
    "wof:placetype":"venue"
},
  "geometry": {"coordinates":[9.406988,45.856987],"type":"Point"}
}