{
  "type": "Feature",
  "properties": {
    "addr:full":"Via Dei Gheghi, 56/58 55018 Segromigno In Monte Segromigno in Monte Lucca 55018",
    "addr:housenumber":"56 / 58",
    "addr:postcode":"55018;55018",
    "addr:street":"Via Dei Gheghi;Lucca",
    "iso:country":"IT",
    "sg:address":"Via Dei Gheghi, 56/58 55018 Segromigno In Monte",
    "sg:city":"Segromigno in Monte",
    "sg:classifiers":[
        {
            "category":"Social Services",
            "subcategory":"Retirement Home",
            "type":"Services"
        }
    ],
    "sg:phone":"+39 0583 927048",
    "sg:postcode":"55018",
    "sg:province":"Lucca",
    "sg:tags":[
        "slipper",
        "house"
    ],
    "sg:website":"www.monolite.biz/marimicheli",
    "wof:name":"Micheli Mario Srl",
    "wof:placetype":"venue"
},
  "geometry": {"coordinates":[10.585891,43.87722],"type":"Point"}
}