{
  "type": "Feature",
  "properties": {
    "addr:full":"Via S. Carlo 74a 10070 San Francesco Al Campo San Francesco al Campo Torino 10070",
    "addr:housenumber":"74a",
    "addr:postcode":"10070;10070",
    "addr:street":"Via S. Carlo;Francesco Al Campo",
    "iso:country":"IT",
    "sg:address":"Via S. Carlo 74a 10070 San Francesco Al Campo",
    "sg:city":"San Francesco al Campo",
    "sg:classifiers":[
        {
            "category":"Utilities",
            "subcategory":"Mobile Phone",
            "type":"Services"
        }
    ],
    "sg:phone":"+39 011 927 6850",
    "sg:postcode":"10070",
    "sg:province":"Torino",
    "sg:tags":[
        "article",
        "promotional"
    ],
    "wof:name":"Pierre Import Sas Di Brescia Pierino & C.",
    "wof:placetype":"venue"
},
  "geometry": {"coordinates":[7.6866188049,45.0705604553],"type":"Point"}
}