{
  "type": "Feature",
  "properties": {
    "addr:full":"22070 Locate Varesino Locate Varesino Como 22070",
    "addr:housenumber":"varesino",
    "addr:postcode":"22070;22070",
    "iso:country":"IT",
    "sg:address":"22070 Locate Varesino",
    "sg:city":"Locate Varesino",
    "sg:orig_category":"Accessori Moda D'abbigliamento. Forniture Per Abbigliamento E Pelletterie",
    "sg:phone":"+39 0331 832670",
    "sg:postcode":"22070",
    "sg:province":"Como",
    "wof:name":"Nova Rampalux Snc Di Franco Ramponi & C.",
    "wof:placetype":"venue"
},
  "geometry": {"coordinates":[8.930966,45.691463],"type":"Point"}
}