{
  "type": "Feature",
  "properties": {
    "iso:country":"IT",
    "sg:address":"98131 Messina",
    "sg:city":"Messina",
    "sg:orig_category":"Arredamenti - Vendita Al Dettaglio",
    "sg:phone":"+39 090 682047",
    "sg:postcode":"98131",
    "sg:province":"Messina",
    "wof:name":"De Salvo Giacomo",
    "wof:placetype":"venue"
},
  "geometry": {"coordinates":[15.524638,38.138466],"type":"Point"}
}