{
  "type": "Feature",
  "properties": {
    "iso:country":"IT",
    "sg:address":"01030 Fabrica Di Roma",
    "sg:classifiers":[
        {
            "category":"Shopping",
            "subcategory":"Stationery & Office Supplies",
            "type":"Retail Goods"
        }
    ],
    "sg:phone":"+39 0761 598219",
    "sg:postcode":"01030",
    "sg:province":"Viterbo",
    "sg:tags":[
        "equipment",
        "furniture",
        "furnishing",
        "professional"
    ],
    "wof:name":"Sbarra Srl",
    "wof:placetype":"venue"
},
  "geometry": {"coordinates":[12.36789608,42.3174362183],"type":"Point"}
}