{
  "type": "Feature",
  "properties": {
    "addr:full":"22/r, Via Dei Martelli 50129 Firenze Firenze Firenze 50129",
    "addr:housenumber":"22 / r",
    "addr:postcode":"50129;50129",
    "addr:street":"Via Dei Martelli",
    "iso:country":"IT",
    "sg:address":"22/r, Via Dei Martelli 50129 Firenze",
    "sg:city":"Firenze",
    "sg:classifiers":[
        {
            "category":"Banks & Credit Unions",
            "subcategory":"Investment Brokerage",
            "type":"Services"
        }
    ],
    "sg:phone":"+39 39055282873",
    "sg:postcode":"50129",
    "sg:province":"Firenze",
    "sg:tags":[
        "-",
        "transport",
        "related"
    ],
    "wof:name":"Gruppo Marzocco Srl",
    "wof:placetype":"venue"
},
  "geometry": {"coordinates":[11.256902,43.768734],"type":"Point"}
}