{
  "type": "Feature",
  "properties": {
    "iso:country":"IT",
    "sg:address":"00139 Roma",
    "sg:city":"Roma",
    "sg:classifiers":[
        {
            "category":"Health Services",
            "subcategory":"Health Practitioner",
            "type":"Services"
        }
    ],
    "sg:phone":"+39 06 8713 2680",
    "sg:postcode":"00139",
    "sg:province":"Roma",
    "sg:tags":[
        "medici"
    ],
    "wof:name":"Centro Medico Svevo S.r.l.",
    "wof:placetype":"venue"
},
  "geometry": {"coordinates":[12.369033,42.115505],"type":"Point"}
}