{
  "type": "Feature",
  "properties": {
    "iso:country":"IT",
    "sg:address":"21040 Gerenzano",
    "sg:city":"Gerenzano",
    "sg:orig_category":"Macchine, Impianti Ed Attrezzature Industria Chimica",
    "sg:phone":"+39 02 968 0564",
    "sg:postcode":"21040",
    "sg:province":"Varese",
    "wof:name":"Sistemi Termici Engineering & Contractor",
    "wof:placetype":"venue"
},
  "geometry": {"coordinates":[8.89446,45.774517],"type":"Point"}
}