{
  "type": "Feature",
  "properties": {
    "iso:country":"IT",
    "sg:address":"40134 Bologna",
    "sg:city":"Bologna",
    "sg:orig_category":"Elettronica Industriale, Prodotti E Apparecchiature",
    "sg:phone":"+39 051 615 3104",
    "sg:postcode":"40134",
    "sg:province":"Bologna",
    "sg:website":"http://www.castorina.bo.it",
    "wof:name":"Castorina Giuseppe",
    "wof:placetype":"venue"
},
  "geometry": {"coordinates":[11.318123,44.492161],"type":"Point"}
}