{
  "type": "Feature",
  "properties": {
    "iso:country":"IT",
    "sg:address":"62012 Civitanova Marche",
    "sg:city":"Civitanova Marche",
    "sg:orig_category":"Abbigliamento Esterno, Maglierie E Pelliccerie. Calzature, Pelletterie E Pelli. Sport - Articoli E Forniture. Shopping",
    "sg:phone":"+39 0733 771541",
    "sg:postcode":"62012",
    "sg:province":"Macerata",
    "wof:name":"Ballando Ballando Sas Di Accorroni Teresa & C.",
    "wof:placetype":"venue"
},
  "geometry": {"coordinates":[13.72895,43.306293],"type":"Point"}
}