{
  "type": "Feature",
  "properties": {
    "iso:country":"IT",
    "sg:address":"Ss Montefeltro, 61/1 61100 Pesaro",
    "sg:city":"Pesaro",
    "sg:classifiers":[
        {
            "category":"Home & Garden",
            "subcategory":"Furniture",
            "type":"Retail Goods"
        }
    ],
    "sg:phone":"+39 0721 21358",
    "sg:postcode":"61100",
    "sg:province":"Pesaro E Urbino",
    "sg:tags":[
        "glass",
        "mirror"
    ],
    "sg:website":"www.vetreriasaraga.it",
    "wof:name":"Vetreria Saraga Di Saraga Mauro E Stefano Snc",
    "wof:placetype":"venue"
},
  "geometry": {"coordinates":[12.5298032761,43.633556366],"type":"Point"}
}