{
  "type": "Feature",
  "properties": {
    "addr:full":"10146 Torino Torino Torino 10146",
    "addr:postcode":"10146;10146",
    "iso:country":"IT",
    "sg:address":"10146 Torino",
    "sg:city":"Torino",
    "sg:orig_category":"Apparecchiature Ed Attrezzature Meccaniche",
    "sg:phone":"+39 011 720467",
    "sg:postcode":"10146",
    "sg:province":"Torino",
    "wof:name":"Allione Alberto",
    "wof:placetype":"venue"
},
  "geometry": {"coordinates":[7.62579,45.080112],"type":"Point"}
}