{
  "type": "Feature",
  "properties": {
    "iso:country":"IT",
    "sg:address":"23900 Lecco",
    "sg:city":"Lecco",
    "sg:orig_category":"Lavorazioni Metalli, Stampaggio E Saldatura",
    "sg:phone":"+39 0341 499200",
    "sg:postcode":"23900",
    "sg:province":"Lecco",
    "wof:name":"Forgiatura Melesi Giuseppe S.n.c.",
    "wof:placetype":"venue"
},
  "geometry": {"coordinates":[9.408464,45.87923],"type":"Point"}
}