{
  "type": "Feature",
  "properties": {
    "addr:full":"66020 San Giovanni Teatino San Giovanni Teatino Chieti 66020",
    "addr:housenumber":"66020",
    "addr:postcode":"66020",
    "addr:street":"San",
    "iso:country":"IT",
    "sg:address":"66020 San Giovanni Teatino",
    "sg:city":"San Giovanni Teatino",
    "sg:orig_category":"Pompe. Elettrotecnica Industriale, Prodotti E Apparecchiature",
    "sg:phone":"+39 085 446 0231",
    "sg:postcode":"66020",
    "sg:province":"Chieti",
    "wof:name":"Lowara (s.p.a.)",
    "wof:placetype":"venue"
},
  "geometry": {"coordinates":[14.1790084839,42.4171218872],"type":"Point"}
}