{
  "type": "Feature",
  "properties": {
    "iso:country":"IT",
    "sg:address":"13011 Borgosesia",
    "sg:city":"Borgosesia",
    "sg:orig_category":"Idrosanitari - Produzione",
    "sg:phone":"+39 0163 23278",
    "sg:postcode":"13011",
    "sg:province":"Vercelli",
    "wof:name":"O.l.a.r. Sas Di Dematteo Stefano & C.",
    "wof:placetype":"venue"
},
  "geometry": {"coordinates":[8.266515,45.716904],"type":"Point"}
}