{
  "type": "Feature",
  "properties": {
    "iso:country":"IT",
    "sg:address":"Via Piemonte, 51/53 56030 Perignano",
    "sg:classifiers":[
        {
            "category":"Manufacturing",
            "subcategory":"Glass & Minerals",
            "type":"Manufacturing & Wholesale Goods"
        }
    ],
    "sg:phone":"+39 0587 616215",
    "sg:postcode":"56030",
    "sg:province":"Pisa",
    "sg:tags":[
        "insulating"
    ],
    "wof:name":"Toncelli Vetri S.r.l.",
    "wof:placetype":"venue"
},
  "geometry": {"coordinates":[10.396585,43.716137],"type":"Point"}
}