{
  "type": "Feature",
  "properties": {
    "addr:full":"23900 Lecco Lecco Lecco 23900",
    "addr:postcode":"23900;23900",
    "iso:country":"IT",
    "sg:address":"23900 Lecco",
    "sg:city":"Lecco",
    "sg:orig_category":"Termotecnica E Riscaldamento, Apparecchiature E Servizi",
    "sg:phone":"+39 0341 364390",
    "sg:postcode":"23900",
    "sg:province":"Lecco",
    "wof:name":"Lecco Termica Di De Francesco Graziano",
    "wof:placetype":"venue"
},
  "geometry": {"coordinates":[9.389099,45.859917],"type":"Point"}
}