{
  "type": "Feature",
  "properties": {
    "iso:country":"IT",
    "sg:address":"14/c, Via Moie 25050 Rodengo Saiano",
    "sg:classifiers":[
        {
            "category":"Professional",
            "subcategory":"Business Services",
            "type":"Services"
        }
    ],
    "sg:phone":"+39 39030611149",
    "sg:postcode":"25050",
    "sg:province":"Brescia",
    "sg:tags":[
        "advice"
    ],
    "wof:name":"Modelleria Ed Animisteria Franciacorta Srl",
    "wof:placetype":"venue"
},
  "geometry": {"coordinates":[10.124055,45.577286],"type":"Point"}
}