{
  "type": "Feature",
  "properties": {
    "addr:full":"38080 Carisolo Carisolo Trento 38080",
    "addr:postcode":"38080;38080",
    "iso:country":"IT",
    "sg:address":"38080 Carisolo",
    "sg:city":"Carisolo",
    "sg:orig_category":"Forniture Per Abbigliamento E Pelletterie",
    "sg:phone":"+39 0465 504103",
    "sg:postcode":"38080",
    "sg:province":"Trento",
    "wof:name":"Valcanover Mirella",
    "wof:placetype":"venue"
},
  "geometry": {"coordinates":[10.7600183487,46.1698684692],"type":"Point"}
}