{
  "type": "Feature",
  "properties": {
    "iso:country":"IT",
    "sg:address":"Viale Sabotino 13 20135 Milano",
    "sg:city":"Milano",
    "sg:classifiers":[
        {
            "category":"Home & Garden",
            "subcategory":"Building Materials",
            "type":"Retail Goods"
        }
    ],
    "sg:phone":"+39 02 5831 8416",
    "sg:postcode":"20135",
    "sg:province":"Milano",
    "sg:tags":[
        "slab",
        "marble"
    ],
    "wof:name":"Marmi Genovesi Srl",
    "wof:placetype":"venue"
},
  "geometry": {"coordinates":[9.198843,45.450947],"type":"Point"}
}