{
  "type": "Feature",
  "properties": {
    "addr:full":"Via Pisa 5/b 36034 Malo Malo Vicenza 36034",
    "addr:housenumber":"5 / b",
    "addr:postcode":"36034;36034",
    "addr:street":"Via Pisa",
    "iso:country":"IT",
    "sg:address":"Via Pisa 5/b 36034 Malo",
    "sg:city":"Malo",
    "sg:classifiers":[
        {
            "category":"Food & Beverages",
            "subcategory":"Fruits & Vegetables",
            "type":"Retail Goods"
        }
    ],
    "sg:phone":"+39 0445 580688",
    "sg:postcode":"36034",
    "sg:province":"Vicenza",
    "sg:tags":[
        "processing",
        "machinery"
    ],
    "sg:website":"www.delfin.it",
    "wof:name":"Delfin Srl",
    "wof:placetype":"venue"
},
  "geometry": {"coordinates":[11.540307045,45.5459060669],"type":"Point"}
}