{
  "type": "Feature",
  "properties": {
    "iso:country":"IT",
    "sg:address":"10023 Chieri",
    "sg:city":"Chieri",
    "sg:orig_category":"Servizi E Lavori Per Abbigliamento E Pelletterie",
    "sg:phone":"+39 011 941 2141",
    "sg:postcode":"10023",
    "sg:province":"Torino",
    "wof:name":"Tinotex Srl",
    "wof:placetype":"venue"
},
  "geometry": {"coordinates":[7.843742,44.956985],"type":"Point"}
}