{
  "type": "Feature",
  "properties": {
    "iso:country":"IT",
    "sg:address":"Viale Matteotti, 89900 Vibo Valentia, Vv",
    "sg:city":"Vibo Valentia",
    "sg:classifiers":[
        {
            "category":"Banks & Credit Unions",
            "subcategory":"Bank",
            "type":"Services"
        }
    ],
    "sg:postcode":"89900",
    "sg:province":"Vibo Valentia",
    "wof:name":"Vibo V Sviluppo Spa",
    "wof:placetype":"venue"
},
  "geometry": {"coordinates":[16.145329,38.697037],"type":"Point"}
}