{
  "type": "Feature",
  "properties": {
    "iso:country":"IT",
    "sg:address":"22070 Senna Comasco",
    "sg:city":"Senna Comasco",
    "sg:orig_category":"Servizi E Lavori Per Edilizia E Lavori Pubblici. Servizi Ausiliari Di Sorveglianza, Manutenzione E Pulizia",
    "sg:phone":"+39 031 560477",
    "sg:postcode":"22070",
    "sg:province":"Como",
    "wof:name":"Di.ca. All Services Srl",
    "wof:placetype":"venue"
},
  "geometry": {"coordinates":[9.109468,45.758823],"type":"Point"}
}