{
  "type": "Feature",
  "properties": {
    "addr:full":"10098 Rivoli Rivoli Torino 10098",
    "addr:postcode":"10098;10098",
    "iso:country":"IT",
    "sg:address":"10098 Rivoli",
    "sg:city":"Rivoli",
    "sg:orig_category":"Isolanti Termici Ed Acustici - Commercio",
    "sg:phone":"+39 011 958 8204",
    "sg:postcode":"10098",
    "sg:province":"Torino",
    "sg:website":"http://www.abtitalia.it",
    "wof:name":"Abt Italia Srl",
    "wof:placetype":"venue"
},
  "geometry": {"coordinates":[7.549222,45.066868],"type":"Point"}
}