{
  "type": "Feature",
  "properties": {
    "addr:full":"30175 Venezia Marghera Venezia 30175",
    "addr:postcode":"30175;30175",
    "iso:country":"IT",
    "sg:address":"30175 Venezia",
    "sg:city":"Marghera",
    "sg:orig_category":"Metalli E Leghe",
    "sg:phone":"+39 041 929055",
    "sg:postcode":"30175",
    "sg:province":"Venezia",
    "wof:name":"Siderurgica Marghera Srl",
    "wof:placetype":"venue"
},
  "geometry": {"coordinates":[12.2245750427,45.4639358521],"type":"Point"}
}