{
  "type": "Feature",
  "properties": {
    "iso:country":"IT",
    "sg:address":"8, Via Don Sturzo 63044 Comunanza",
    "sg:city":"Comunanza",
    "sg:classifiers":[
        {
            "category":"Real Estate",
            "subcategory":"Architect",
            "type":"Services"
        }
    ],
    "sg:phone":"+39 0736 846177",
    "sg:postcode":"63044",
    "sg:province":"Ascoli Piceno",
    "sg:tags":[
        "textile",
        "clothing"
    ],
    "wof:name":"Pant. Com. S.r.l.",
    "wof:placetype":"venue"
},
  "geometry": {"coordinates":[13.574977,42.8554],"type":"Point"}
}