{
  "type": "Feature",
  "properties": {
    "iso:country":"IT",
    "sg:address":"23881 Airuno",
    "sg:city":"Airuno",
    "sg:orig_category":"Materiali Semilavorati Metallici",
    "sg:phone":"+39 039 994 3551",
    "sg:postcode":"23881",
    "sg:province":"Lecco",
    "wof:name":"Omas S.r.l.",
    "wof:placetype":"venue"
},
  "geometry": {"coordinates":[9.420229,45.783531],"type":"Point"}
}