{
  "type": "Feature",
  "properties": {
    "iso:country":"IT",
    "sg:address":"Via Lomelina 16 20090 Buccinasco",
    "sg:city":"Buccinasco",
    "sg:classifiers":[
        {
            "category":"Autos & Motor Vehicles",
            "subcategory":"Auto Supplies",
            "type":"Retail Goods"
        }
    ],
    "sg:phone":"+39 02 4884 3333",
    "sg:postcode":"20090",
    "sg:province":"Milano",
    "sg:tags":[
        "automobile",
        "part",
        "spare"
    ],
    "sg:website":"www.qhitalia.it",
    "wof:name":"Quinton Hazell Italia S.p.a.",
    "wof:placetype":"venue"
},
  "geometry": {"coordinates":[9.123806,45.416069],"type":"Point"}
}