{
  "type": "Feature",
  "properties": {
    "addr:full":"10044 Pianezza Pianezza Torino 10044",
    "addr:postcode":"10044;10044",
    "iso:country":"IT",
    "sg:address":"10044 Pianezza",
    "sg:city":"Pianezza",
    "sg:orig_category":"Materiali E Componenti Elettrotecnici",
    "sg:phone":"+39 011 966 1626",
    "sg:postcode":"10044",
    "sg:province":"Torino",
    "wof:name":"Masterwatt (s.r.l.)",
    "wof:placetype":"venue"
},
  "geometry": {"coordinates":[7.593248,45.096569],"type":"Point"}
}