{
  "type": "Feature",
  "properties": {
    "iso:country":"IT",
    "sg:address":"47, Localita' Ca' Mello 45018 Porto Tolle",
    "sg:city":"Porto Tolle",
    "sg:classifiers":[
        {
            "category":"Real Estate",
            "subcategory":"Architect",
            "type":"Services"
        }
    ],
    "sg:phone":"+39 0426 390330",
    "sg:postcode":"45018",
    "sg:province":"Rovigo",
    "sg:tags":[
        "textile",
        "clothing"
    ],
    "wof:name":"Delta Confezioni S.r.l.",
    "wof:placetype":"venue"
},
  "geometry": {"coordinates":[11.789797,45.070736],"type":"Point"}
}