{
  "type": "Feature",
  "properties": {
    "iso:country":"IT",
    "sg:address":"25064 Gussago",
    "sg:city":"Gussago",
    "sg:orig_category":"Servizi E Lavori Per Agricoltura E Zootecnia. Servizi E Lavori Per Ecologia E Smaltimento Rifiuti. Servizi Ausiliari Di Sorveglianza, Manutenzione E Pulizia",
    "sg:phone":"+39 030 373 2813",
    "sg:postcode":"25064",
    "sg:province":"Brescia",
    "wof:name":"Coven S.r.l.",
    "wof:placetype":"venue"
},
  "geometry": {"coordinates":[10.151052,45.553432],"type":"Point"}
}