{
  "type": "Feature",
  "properties": {
    "iso:country":"IT",
    "sg:address":"18, Via Cristoforo Colombo 35011 Campodarsego",
    "sg:city":"Campodarsego",
    "sg:classifiers":[
        {
            "category":"Professional",
            "subcategory":"Engineering",
            "type":"Services"
        }
    ],
    "sg:phone":"+39 049 920 1965",
    "sg:postcode":"35011",
    "sg:province":"Padova",
    "sg:tags":[
        "machine",
        "-",
        "mechanical"
    ],
    "wof:name":"Volpato S.r.l.",
    "wof:placetype":"venue"
},
  "geometry": {"coordinates":[11.907261,45.485653],"type":"Point"}
}