{
  "type": "Feature",
  "properties": {
    "iso:country":"IT",
    "sg:address":"22063 Cantu'",
    "sg:orig_category":"Lavorazioni Metalli, Stampaggio E Saldatura",
    "sg:phone":"+39 031 716206",
    "sg:postcode":"22063",
    "sg:province":"Como",
    "wof:name":"Gamma 3 S.a.s.",
    "wof:placetype":"venue"
},
  "geometry": {"coordinates":[9.140926,45.72797],"type":"Point"}
}