{
  "type": "Feature",
  "properties": {
    "addr:full":"54100 Massa Massa Massa-Carrara 54100",
    "addr:postcode":"54100;54100",
    "iso:country":"IT",
    "sg:address":"54100 Massa",
    "sg:city":"Massa",
    "sg:orig_category":"Studi E Consulenze Tecniche E Industriali. Servizi E Lavori Per Edilizia E Lavori Pubblici. Professionisti - Studi E Servizi Ed Associazioni Di Interesse Aziendale",
    "sg:phone":"+39 0585 869113",
    "sg:postcode":"54100",
    "sg:province":"Massa-Carrara",
    "wof:name":"Immobiliare Il Gabbiano Di Rifredi Geom. Franco",
    "wof:placetype":"venue"
},
  "geometry": {"coordinates":[10.11906,43.998234],"type":"Point"}
}