{
  "type": "Feature",
  "properties": {
    "iso:country":"IT",
    "sg:address":"20085 Locate Di Triulzi",
    "sg:city":"Locate di Triulzi",
    "sg:orig_category":"Servizi E Lavori Per Arredamento E Industria Del Legno. Servizi E Lavori Per Edilizia E Lavori Pubblici",
    "sg:phone":"+39 02 907 9701",
    "sg:postcode":"20085",
    "sg:province":"Milano",
    "wof:name":"Torzillo Michele",
    "wof:placetype":"venue"
},
  "geometry": {"coordinates":[9.244622,45.395309],"type":"Point"}
}