{
  "type": "Feature",
  "properties": {
    "addr:full":"14/16/18, V. Licinio Murena 00175 Roma Roma Roma 00175",
    "addr:housenumber":"14 / 16 / 18 v. licinio",
    "addr:postcode":"00175;00175",
    "addr:street":"Murena",
    "iso:country":"IT",
    "sg:address":"14/16/18, V. Licinio Murena 00175 Roma",
    "sg:city":"Roma",
    "sg:classifiers":[
        {
            "category":"Home & Garden",
            "subcategory":"Home Furnishings",
            "type":"Retail Goods"
        }
    ],
    "sg:phone":"+39 06 7696 7073",
    "sg:postcode":"00175",
    "sg:province":"Roma",
    "sg:tags":[
        "household"
    ],
    "sg:website":"http://www.cicchetta.it",
    "wof:name":"Cicchetta A.d. Srl",
    "wof:placetype":"venue"
},
  "geometry": {"coordinates":[12.555264,41.861996],"type":"Point"}
}