{
  "type": "Feature",
  "properties": {
    "addr:full":"Via Don Minzoni 2 40018 San Pietro In Casale San Pietro in Casale Bologna 40018",
    "addr:housenumber":"2",
    "addr:postcode":"40018;40018",
    "addr:street":"Via Don Minzoni;Pietro In",
    "iso:country":"IT",
    "sg:address":"Via Don Minzoni 2 40018 San Pietro In Casale",
    "sg:city":"San Pietro in Casale",
    "sg:classifiers":[
        {
            "category":"Banks & Credit Unions",
            "subcategory":"Investment Brokerage",
            "type":"Services"
        }
    ],
    "sg:phone":"+39 051 810456",
    "sg:postcode":"40018",
    "sg:province":"Bologna",
    "sg:tags":[
        "accessory",
        "high-fashion"
    ],
    "sg:website":"www.crimode.com",
    "wof:name":"Cri Mode Di Cristofori Giovanni & C . Snc",
    "wof:placetype":"venue"
},
  "geometry": {"coordinates":[11.316558,44.71384],"type":"Point"}
}