{
  "type": "Feature",
  "properties": {
    "addr:full":"50144 Firenze Firenze Firenze 50144",
    "addr:postcode":"50144;50144",
    "iso:country":"IT",
    "sg:address":"50144 Firenze",
    "sg:city":"Firenze",
    "sg:orig_category":"Studi E Consulenze Amministrative, Commerciali E Aziendali. Consulenze Tecniche, Amministrative E Perizie. Professionisti - Studi E Servizi Ed Associazioni Di Interesse Aziendale",
    "sg:phone":"+39 055 324 5600",
    "sg:postcode":"50144",
    "sg:province":"Firenze",
    "wof:name":"Kutufa' Marcello",
    "wof:placetype":"venue"
},
  "geometry": {"coordinates":[11.234869,43.786633],"type":"Point"}
}