{
  "type": "Feature",
  "properties": {
    "iso:country":"IT",
    "sg:address":"173, Via Forese Macalle' 47018 Santa Sofia",
    "sg:city":"Santa Sofia",
    "sg:classifiers":[
        {
            "category":"Food & Beverages",
            "subcategory":"Bakery",
            "type":"Retail Goods"
        }
    ],
    "sg:phone":"+39 0543 970217",
    "sg:postcode":"47018",
    "sg:province":"Forl\u00ec-Cesena",
    "sg:tags":[
        "grain",
        "cereal"
    ],
    "wof:name":"Agrofertil Soc.coop. A R.l.",
    "wof:placetype":"venue"
},
  "geometry": {"coordinates":[11.980461,43.994766],"type":"Point"}
}