{
  "type": "Feature",
  "properties": {
    "addr:full":"10131 Torino Torino Torino 10131",
    "addr:postcode":"10131;10131",
    "iso:country":"IT",
    "sg:address":"10131 Torino",
    "sg:city":"Torino",
    "sg:orig_category":"Medicinali E Prodotti Parafarmaceutici. Prodotti Cosmetici E Da Toeletta",
    "sg:phone":"+39 011 819 3049",
    "sg:postcode":"10131",
    "sg:province":"Torino",
    "wof:name":"La Recolte Sas",
    "wof:placetype":"venue"
},
  "geometry": {"coordinates":[7.7006435394,45.0625762939],"type":"Point"}
}