{
  "type": "Feature",
  "properties": {
    "iso:country":"IT",
    "sg:address":"35010 Grantorto",
    "sg:city":"Grantorto",
    "sg:orig_category":"Servizi Per Lo Sport E Il Tempo Libero. Ristoranti Ed Esercizi Affini. Servizi Ausiliari Di Ristorazione E Di Intrattenimento",
    "sg:phone":"+39 049 596 0017",
    "sg:postcode":"35010",
    "sg:province":"Padova",
    "wof:name":"Paninoteca Birreria Pub Novecento",
    "wof:placetype":"venue"
},
  "geometry": {"coordinates":[11.875744,45.401489],"type":"Point"}
}