{
  "type": "Feature",
  "properties": {
    "iso:country":"IT",
    "sg:address":"22, Cascina Dallo' 10082 Cuorgne'",
    "sg:classifiers":[
        {
            "category":"Shopping",
            "type":"Retail Goods"
        }
    ],
    "sg:phone":"+39 0124 657058",
    "sg:postcode":"10082",
    "sg:province":"Torino",
    "sg:tags":[
        "finished",
        "-",
        "metallic"
    ],
    "wof:name":"L'elettrometallurgica (s.p.a.)",
    "wof:placetype":"venue"
},
  "geometry": {"coordinates":[7.6606321335,45.385925293],"type":"Point"}
}