{
  "type": "Feature",
  "properties": {
    "iso:country":"IT",
    "sg:address":"37122 Verona",
    "sg:city":"Verona",
    "sg:orig_category":"Macchine, Impianti E Forniture Per Industria Grafica, Cartaria E Cartotecnica. Automazione E Macchine Per Ufficio",
    "sg:phone":"+39 045 800 2529",
    "sg:postcode":"37122",
    "sg:province":"Verona",
    "wof:name":"Office Automation Srl",
    "wof:placetype":"venue"
},
  "geometry": {"coordinates":[10.987656,45.432449],"type":"Point"}
}