{
  "type": "Feature",
  "properties": {
    "iso:country":"IT",
    "sg:address":"Via Dell Unione Europea 35 70051 Barletta",
    "sg:city":"Barletta",
    "sg:classifiers":[
        {
            "category":"Shopping",
            "subcategory":"Shoes",
            "type":"Retail Goods"
        }
    ],
    "sg:phone":"+39 0883 347697",
    "sg:postcode":"70051",
    "sg:province":"Bari",
    "sg:tags":[
        "children's"
    ],
    "wof:name":"Calzaturificio New Rutil Srl",
    "wof:placetype":"venue"
},
  "geometry": {"coordinates":[16.32225,41.306313],"type":"Point"}
}