{
  "type": "Feature",
  "properties": {
    "addr:full":"30174 Mestre Mestre Venezia 30174",
    "addr:postcode":"30174;30174",
    "addr:street":"Mestre Mestre Venezia",
    "iso:country":"IT",
    "sg:address":"30174 Mestre",
    "sg:city":"Mestre",
    "sg:orig_category":"Servizi E Lavori Per Industria Alimentare E Bevande",
    "sg:phone":"+39 041 912043",
    "sg:postcode":"30174",
    "sg:province":"Venezia",
    "wof:name":"Scaggiante Egidio",
    "wof:placetype":"venue"
},
  "geometry": {"coordinates":[12.195189,45.484547],"type":"Point"}
}