{
  "type": "Feature",
  "properties": {
    "iso:country":"IT",
    "sg:address":"20123 Milano",
    "sg:city":"Milano",
    "sg:orig_category":"Abbigliamento Intimo, Calze E Costumi Da Bagno. Sport - Articoli E Forniture. Shopping",
    "sg:phone":"+39 02 877374",
    "sg:postcode":"20123",
    "sg:province":"Milano",
    "wof:name":"Cavadini Cinzia",
    "wof:placetype":"venue"
},
  "geometry": {"coordinates":[9.174826,45.464497],"type":"Point"}
}