{
  "type": "Feature",
  "properties": {
    "addr:full":"316/g, Via Bologna 59100 Prato Prato Prato 59100",
    "addr:housenumber":"316 / g",
    "addr:postcode":"59100;59100",
    "addr:street":"Via Bologna",
    "iso:country":"IT",
    "sg:address":"316/g, Via Bologna 59100 Prato",
    "sg:city":"Prato",
    "sg:classifiers":[
        {
            "category":"Shopping",
            "subcategory":"Crafts & Fabrics",
            "type":"Retail Goods"
        }
    ],
    "sg:phone":"+39 0574 692716",
    "sg:postcode":"59100",
    "sg:province":"Prato",
    "wof:name":"Lanificio U.guarducci (s.r.l.)",
    "wof:placetype":"venue"
},
  "geometry": {"coordinates":[11.1038217545,43.9000053406],"type":"Point"}
}