{
  "type": "Feature",
  "properties": {
    "iso:country":"IT",
    "sg:address":"Via Gramsci, 40/42 21057 Olgiate Olona",
    "sg:city":"Olgiate Olona",
    "sg:classifiers":[
        {
            "category":"Building & Trades",
            "subcategory":"Construction",
            "type":"Services"
        }
    ],
    "sg:phone":"+39 0331 375990",
    "sg:postcode":"21057",
    "sg:province":"Varese",
    "sg:tags":[
        "tool",
        "cutting"
    ],
    "sg:website":"www.polledri.it",
    "wof:name":"Polledri Spa",
    "wof:placetype":"venue"
},
  "geometry": {"coordinates":[8.881757,45.617428],"type":"Point"}
}