{
  "type": "Feature",
  "properties": {
    "iso:country":"IT",
    "sg:address":"37067 Valeggio Sul Mincio",
    "sg:city":"Valeggio sul Mincio",
    "sg:orig_category":"Servizi E Lavori Per Agricoltura E Zootecnia",
    "sg:phone":"+39 045 795 0238",
    "sg:postcode":"37067",
    "sg:province":"Verona",
    "wof:name":"Mezzani Paolino",
    "wof:placetype":"venue"
},
  "geometry": {"coordinates":[10.727598,45.349186],"type":"Point"}
}