{
  "type": "Feature",
  "properties": {
    "iso:country":"IT",
    "sg:address":"25060 Collebeato",
    "sg:city":"Collebeato",
    "sg:orig_category":"Servizi E Lavori Industria Chimica",
    "sg:phone":"+39 030 251 1122",
    "sg:postcode":"25060",
    "sg:province":"Brescia",
    "wof:name":"D.s. Di D'attoma Salvatorelli E C. S.n.c.",
    "wof:placetype":"venue"
},
  "geometry": {"coordinates":[10.215404,45.551018],"type":"Point"}
}