{
  "type": "Feature",
  "properties": {
    "iso:country":"IT",
    "sg:address":"00185 Roma",
    "sg:city":"Roma",
    "sg:orig_category":"Scuole E Servizi Scolastici",
    "sg:phone":"+39 06 474 7451",
    "sg:postcode":"00185",
    "sg:province":"Roma",
    "wof:name":"Societ\u00c0 Di Servizi Snc",
    "wof:placetype":"venue"
},
  "geometry": {"coordinates":[12.500003,41.904224],"type":"Point"}
}