{
  "type": "Feature",
  "properties": {
    "iso:country":"IT",
    "sg:address":"35128 Padova",
    "sg:city":"Padova",
    "sg:orig_category":"Servizi Per Lo Sport E Il Tempo Libero. Associazioni Ed Organismi Di Interesse Pubblico",
    "sg:phone":"+39 049 807 0843",
    "sg:postcode":"35128",
    "sg:province":"Padova",
    "wof:name":"Centro Iperbarico",
    "wof:placetype":"venue"
},
  "geometry": {"coordinates":[11.904662,45.3979],"type":"Point"}
}