{
  "type": "Feature",
  "properties": {
    "iso:country":"IT",
    "sg:address":"Via Per Casaloldo 34 46041 Asola",
    "sg:city":"Asola",
    "sg:orig_category":"Adhesives, Customer-specific",
    "sg:phone":"+39 0376 74704",
    "sg:postcode":"46041",
    "sg:province":"Mantova",
    "wof:name":"Tintoria Manifattura Barbara Spa",
    "wof:placetype":"venue"
},
  "geometry": {"coordinates":[10.4585084915,45.2482376099],"type":"Point"}
}