{
  "type": "Feature",
  "properties": {
    "iso:country":"IT",
    "sg:address":"07100 Sassari",
    "sg:city":"Li punti",
    "sg:orig_category":"Geometri - Studi",
    "sg:phone":"+39 079 395255",
    "sg:postcode":"07100",
    "sg:province":"Sassari",
    "wof:name":"Marzeddu Antonello",
    "wof:placetype":"venue"
},
  "geometry": {"coordinates":[8.520447,40.748501],"type":"Point"}
}