{
  "type": "Feature",
  "properties": {
    "iso:country":"IT",
    "sg:address":"14100 Asti",
    "sg:city":"Asti",
    "sg:orig_category":"Videogiochi, Flippers E Biliardini - Produzione E Ingrosso",
    "sg:phone":"+39 0141 271664",
    "sg:postcode":"14100",
    "sg:province":"Asti",
    "wof:name":"A.ge.a. Di Vegezzi Piero Enrico",
    "wof:placetype":"venue"
},
  "geometry": {"coordinates":[8.220653,44.904789],"type":"Point"}
}