{
  "type": "Feature",
  "properties": {
    "iso:country":"IT",
    "sg:address":"15100 Alessandria",
    "sg:city":"Alessandria",
    "sg:orig_category":"Prodotti E Manufatti In Materie Plastiche",
    "sg:phone":"+39 0131 223504",
    "sg:postcode":"15100",
    "sg:province":"Alessandria",
    "sg:website":"http://www.bussettimazza.com",
    "wof:name":"Bussetti P. Mazza A. & C. Sas",
    "wof:placetype":"venue"
},
  "geometry": {"coordinates":[8.7105503082,44.9107627869],"type":"Point"}
}