{
  "type": "Feature",
  "properties": {
    "addr:full":"6/d, Via Serena 24010 Ponteranica Ponteranica Bergamo 24010",
    "addr:housenumber":"6 / d",
    "addr:postcode":"24010;24010",
    "addr:street":"Via Serena",
    "iso:country":"IT",
    "sg:address":"6/d, Via Serena 24010 Ponteranica",
    "sg:city":"Ponteranica",
    "sg:classifiers":[
        {
            "category":"Professional",
            "subcategory":"Printing & Photocopies",
            "type":"Services"
        }
    ],
    "sg:phone":"+39 39035573268",
    "sg:postcode":"24010",
    "sg:province":"Bergamo",
    "wof:name":"Artigrafiche Mariani & Monti (s.r.l.)",
    "wof:placetype":"venue"
},
  "geometry": {"coordinates":[9.6572780609,45.7207298279],"type":"Point"}
}