{
  "type": "Feature",
  "properties": {
    "addr:full":"24012 Brembilla Brembilla Bergamo 24012",
    "addr:postcode":"24012;24012",
    "iso:country":"IT",
    "sg:address":"24012 Brembilla",
    "sg:city":"Brembilla",
    "sg:orig_category":"Servizi E Lavori Per Arredamento E Industria Del Legno",
    "sg:phone":"+39 0345 98108",
    "sg:postcode":"24012",
    "sg:province":"Bergamo",
    "sg:website":"http://www.fapasalvi.com",
    "wof:name":"F.a.p.a. Salvi Di Salvi Marco",
    "wof:placetype":"venue"
},
  "geometry": {"coordinates":[9.5720930099,45.6935081482],"type":"Point"}
}