{
  "type": "Feature",
  "properties": {
    "iso:country":"IT",
    "sg:address":"20/a, Via Mercalli Giuseppe 43100 Parma",
    "sg:city":"Parma",
    "sg:classifiers":[
        {
            "category":"Manufacturing",
            "subcategory":"Metals",
            "type":"Manufacturing & Wholesale Goods"
        }
    ],
    "sg:phone":"+39 0521 607032",
    "sg:postcode":"43100",
    "sg:province":"Parma",
    "sg:tags":[
        "processing"
    ],
    "wof:name":"Elettrogalvanica Chiari (s.r.l.)",
    "wof:placetype":"venue"
},
  "geometry": {"coordinates":[10.2949199677,44.8232078552],"type":"Point"}
}