{
  "type": "Feature",
  "properties": {
    "iso:country":"IT",
    "sg:address":"Localita' Collacchi 67032 Pescasseroli",
    "sg:classifiers":[
        {
            "category":"Travel",
            "subcategory":"Travel Agent",
            "type":"Entertainment"
        }
    ],
    "sg:phone":"+39 0863 910740",
    "sg:postcode":"67032",
    "sg:province":"L'Aquila",
    "sg:tags":[
        "business"
    ],
    "wof:name":"Hotel Lo Scoiattolo",
    "wof:placetype":"venue"
},
  "geometry": {"coordinates":[13.399934,42.350697],"type":"Point"}
}