{
  "type": "Feature",
  "properties": {
    "iso:country":"IT",
    "sg:address":"30174 Venezia",
    "sg:city":"Mestre",
    "sg:orig_category":"Articoli Medico-sanitari Ed Ortopedici",
    "sg:phone":"+39 041 940061",
    "sg:postcode":"30174",
    "sg:province":"Venezia",
    "wof:name":"Centro Ortopedico Sanitaria 14",
    "wof:placetype":"venue"
},
  "geometry": {"coordinates":[12.229957,45.497963],"type":"Point"}
}