{
  "type": "Feature",
  "properties": {
    "addr:full":"29, Via Lario 20024 Garbagnate Milanese Garbagnate Milanese Milano 20024",
    "addr:postcode":"20024;20024",
    "addr:street":"Via Lario",
    "iso:country":"IT",
    "sg:address":"29, Via Lario 20024 Garbagnate Milanese",
    "sg:city":"Garbagnate Milanese",
    "sg:classifiers":[
        {
            "category":"Manufacturing",
            "subcategory":"Rubber & Plastics",
            "type":"Manufacturing & Wholesale Goods"
        }
    ],
    "sg:phone":"+39 02 9902 6656",
    "sg:postcode":"20024",
    "sg:province":"Milano",
    "wof:name":"Rel",
    "wof:placetype":"venue"
},
  "geometry": {"coordinates":[9.1415290833,45.5563659668],"type":"Point"}
}