{
  "type": "Feature",
  "properties": {
    "iso:country":"IT",
    "sg:address":"00133 Roma",
    "sg:city":"Roma",
    "sg:orig_category":"Servizi E Lavori Per Arredamento E Industria Del Legno",
    "sg:phone":"+39 06 201 6624",
    "sg:postcode":"00133",
    "sg:province":"Roma",
    "wof:name":"Fa.ro S.n.c. Di Zurli F. & Seminara R.",
    "wof:placetype":"venue"
},
  "geometry": {"coordinates":[12.614713,41.879166],"type":"Point"}
}