{
  "type": "Feature",
  "properties": {
    "iso:country":"IT",
    "sg:address":"5, Via Indipendenza 20053 Muggio'",
    "sg:classifiers":[
        {
            "category":"Manufacturing",
            "subcategory":"Metals",
            "type":"Manufacturing & Wholesale Goods"
        }
    ],
    "sg:phone":"+39 39039793213",
    "sg:postcode":"20053",
    "sg:province":"Milano",
    "sg:tags":[
        "processing"
    ],
    "wof:name":"La Nuova Get (s.a.s.)",
    "wof:placetype":"venue"
},
  "geometry": {"coordinates":[9.2077646255,45.5517845154],"type":"Point"}
}