{
  "type": "Feature",
  "properties": {
    "iso:country":"IT",
    "sg:address":"13, Via Dei Gigli 70026 Modugno",
    "sg:city":"Modugno",
    "sg:classifiers":[
        {
            "category":"Wholesale",
            "subcategory":"Machinery & Supplies",
            "type":"Manufacturing & Wholesale Goods"
        }
    ],
    "sg:phone":"+39 080 538 3840",
    "sg:postcode":"70026",
    "sg:province":"Bari",
    "sg:tags":[
        "-",
        "agriculture",
        "equipment"
    ],
    "wof:name":"Hideco Srl",
    "wof:placetype":"venue"
},
  "geometry": {"coordinates":[16.792116,41.104332],"type":"Point"}
}