{
  "type": "Feature",
  "properties": {
    "iso:country":"IT",
    "sg:address":"24060 Telgate",
    "sg:city":"Telgate",
    "sg:orig_category":"Apparecchiature Ed Attrezzature Meccaniche",
    "sg:phone":"+39 035 442 4811",
    "sg:postcode":"24060",
    "sg:province":"Bergamo",
    "sg:website":"http://www.colorfer.it",
    "wof:name":"Color-fer Spa",
    "wof:placetype":"venue"
},
  "geometry": {"coordinates":[9.852834,45.629852],"type":"Point"}
}