{
  "type": "Feature",
  "properties": {
    "iso:country":"IT",
    "sg:address":"20121 Milano",
    "sg:city":"Milano",
    "sg:orig_category":"Studi E Consulenze Amministrative, Commerciali E Aziendali. Banche E Servizi Finanziari. Agenzie D'affari E Servizi Commerciali. Consulenze Tecniche, Amministrative E Perizie",
    "sg:phone":"+39 02 623191",
    "sg:postcode":"20121",
    "sg:province":"Milano",
    "wof:name":"Borioli & Colombo Associati",
    "wof:placetype":"venue"
},
  "geometry": {"coordinates":[9.19244,45.47076],"type":"Point"}
}