{
  "type": "Feature",
  "properties": {
    "iso:country":"IT",
    "sg:address":"24030 Terno D'isola",
    "sg:orig_category":"Zootecnia E Pesca, Allevamento Piccoli Animali",
    "sg:phone":"+39 035 904179",
    "sg:postcode":"24030",
    "sg:province":"Bergamo",
    "wof:name":"Varinelli Mario",
    "wof:placetype":"venue"
},
  "geometry": {"coordinates":[9.537016,45.684422],"type":"Point"}
}