{
  "type": "Feature",
  "properties": {
    "iso:country":"IT",
    "sg:address":"10, Via Genova 80027 Frattamaggiore",
    "sg:city":"Frattamaggiore",
    "sg:classifiers":[
        {
            "category":"Shopping",
            "subcategory":"Clothing, Apparel, & Fashions",
            "type":"Retail Goods"
        }
    ],
    "sg:phone":"+39 081 880 1774",
    "sg:postcode":"80027",
    "sg:province":"Napoli",
    "sg:tags":[
        "clothes"
    ],
    "wof:name":"Paviro Srl",
    "wof:placetype":"venue"
},
  "geometry": {"coordinates":[14.275839,40.935467],"type":"Point"}
}