{
  "type": "Feature",
  "properties": {
    "addr:full":"19, V. Prina 20052 Monza Monza Milano 20052",
    "addr:housenumber":"19",
    "addr:postcode":"20052;20052",
    "addr:street":"V. Prina",
    "iso:country":"IT",
    "sg:address":"19, V. Prina 20052 Monza",
    "sg:city":"Monza",
    "sg:orig_category":"Miscellaneous Products",
    "sg:phone":"+39 39039321956",
    "sg:postcode":"20052",
    "sg:province":"Milano",
    "sg:website":"http://www.ferrari-arrighetti.com",
    "wof:name":"Ferrari & Arrighetti Snc",
    "wof:placetype":"venue"
},
  "geometry": {"coordinates":[9.2672014236,45.587562561],"type":"Point"}
}