{
  "type": "Feature",
  "properties": {
    "addr:full":"16, Via Guglielmo Marconi 31050 Ponzano Veneto Ponzano Veneto Treviso 31050",
    "addr:postcode":"31050;31050",
    "addr:street":"Via Guglielmo Marconi",
    "iso:country":"IT",
    "sg:address":"16, Via Guglielmo Marconi 31050 Ponzano Veneto",
    "sg:city":"Ponzano Veneto",
    "sg:classifiers":[
        {
            "category":"Food & Beverages",
            "subcategory":"Groceries & Convenience Stores",
            "type":"Retail Goods"
        }
    ],
    "sg:phone":"+39 0422 440440",
    "sg:postcode":"31050",
    "sg:province":"Treviso",
    "sg:tags":[
        "drink"
    ],
    "wof:name":"Da Pian Srl",
    "wof:placetype":"venue"
},
  "geometry": {"coordinates":[12.221437,45.70459],"type":"Point"}
}