{
  "type": "Feature",
  "properties": {
    "iso:country":"IT",
    "sg:address":"8, Via Zeni 38068 Rovereto",
    "sg:city":"Rovereto",
    "sg:classifiers":[
        {
            "category":"Professional",
            "subcategory":"Computer Services",
            "type":"Services"
        }
    ],
    "sg:phone":"+39 0464 420852",
    "sg:postcode":"38068",
    "sg:province":"Trento",
    "sg:tags":[
        "information",
        "technology"
    ],
    "wof:name":"Ecosystem Srl",
    "wof:placetype":"venue"
},
  "geometry": {"coordinates":[11.032575,45.889946],"type":"Point"}
}