{
  "type": "Feature",
  "properties": {
    "addr:full":"34016 Trieste Trieste 34016",
    "addr:postcode":"34016;34016",
    "iso:country":"IT",
    "sg:address":"34016 Trieste",
    "sg:orig_category":"Alberghi",
    "sg:phone":"+39 040 922 0163",
    "sg:postcode":"34016",
    "sg:province":"Trieste",
    "wof:name":"Al Tiglio - Pri Lipi",
    "wof:placetype":"venue"
},
  "geometry": {"coordinates":[13.863391,45.641785],"type":"Point"}
}