{
  "type": "Feature",
  "properties": {
    "iso:country":"IT",
    "sg:address":"20093 Cologno Monzese",
    "sg:city":"Cologno Monzese",
    "sg:classifiers":[
        {
            "category":"Health Services",
            "subcategory":"Health Practitioner",
            "type":"Services"
        }
    ],
    "sg:phone":"+39 02 254 7174",
    "sg:postcode":"20093",
    "sg:province":"Milano",
    "sg:tags":[
        "medici"
    ],
    "wof:name":"A.c.s. Ambulatori Clinici Specialistici Di Grimaldi G. & C. Snc",
    "wof:placetype":"venue"
},
  "geometry": {"coordinates":[9.274488,45.520599],"type":"Point"}
}