{
  "type": "Feature",
  "properties": {
    "iso:country":"IT",
    "sg:address":"29100 Piacenza",
    "sg:city":"Piacenza",
    "sg:orig_category":"Traslochi",
    "sg:phone":"+39 0523 711400",
    "sg:postcode":"29100",
    "sg:province":"Piacenza",
    "wof:name":"Casana Trasporti Srl",
    "wof:placetype":"venue"
},
  "geometry": {"coordinates":[9.677814,45.017616],"type":"Point"}
}