{
  "type": "Feature",
  "properties": {
    "iso:country":"IT",
    "sg:address":"23870 Cernusco Lombardone",
    "sg:city":"Cernusco Lombardone",
    "sg:orig_category":"Salumifici E Prosciuttifici",
    "sg:phone":"+39 039 990 9543",
    "sg:postcode":"23870",
    "sg:province":"Lecco",
    "wof:name":"Brivio Salumificio Srl",
    "wof:placetype":"venue"
},
  "geometry": {"coordinates":[9.404634,45.684429],"type":"Point"}
}