{
  "type": "Feature",
  "properties": {
    "addr:full":"21100 Varese Varese Varese 21100",
    "addr:postcode":"21100;21100",
    "iso:country":"IT",
    "sg:address":"21100 Varese",
    "sg:city":"Varese",
    "sg:orig_category":"Centri Di Estetica E Cosmesi E Servizi",
    "sg:phone":"+39 0332 813456",
    "sg:postcode":"21100",
    "sg:province":"Varese",
    "wof:name":"Elianto Srl",
    "wof:placetype":"venue"
},
  "geometry": {"coordinates":[8.839106,45.805923],"type":"Point"}
}