{
  "type": "Feature",
  "properties": {
    "iso:country":"IT",
    "sg:address":"95128 Catania",
    "sg:city":"Catania",
    "sg:orig_category":"Impiantistica E Prodotti Tecnologici Per Edilizia. Orologeria",
    "sg:phone":"+39 095 434676",
    "sg:postcode":"95128",
    "sg:province":"Catania",
    "wof:name":"Lamina Messina Sistemi Srl",
    "wof:placetype":"venue"
},
  "geometry": {"coordinates":[15.083518,37.522221],"type":"Point"}
}