{
  "type": "Feature",
  "properties": {
    "addr:full":"06123 Perugia Perugia Perugia 06123",
    "addr:postcode":"06123;06123",
    "iso:country":"IT",
    "sg:address":"06123 Perugia",
    "sg:city":"Perugia",
    "sg:orig_category":"Cine-foto-ottica. Articoli Medico-sanitari Ed Ortopedici",
    "sg:phone":"+39 075 573 1756",
    "sg:postcode":"06123",
    "sg:province":"Perugia",
    "wof:name":"Bartoccini Di Nebbiai Paolo E C. Sas",
    "wof:placetype":"venue"
},
  "geometry": {"coordinates":[12.388584,43.111713],"type":"Point"}
}