{
  "type": "Feature",
  "properties": {
    "addr:full":"80146 Napoli Napoli Napoli 80146",
    "addr:housenumber":"80146",
    "addr:postcode":"80146",
    "iso:country":"IT",
    "sg:address":"80146 Napoli",
    "sg:city":"Napoli",
    "sg:orig_category":"Petroli, Gas E Combustibili",
    "sg:phone":"+39 081 752 7840",
    "sg:postcode":"80146",
    "sg:province":"Napoli",
    "wof:name":"Miggione Giuseppe",
    "wof:placetype":"venue"
},
  "geometry": {"coordinates":[14.3006515503,40.8391189575],"type":"Point"}
}