{
  "type": "Feature",
  "properties": {
    "iso:country":"IT",
    "sg:address":"37053 Cerea",
    "sg:city":"Cerea",
    "sg:orig_category":"Agricoltura - Attrezzi, Prodotti E Forniture",
    "sg:phone":"+39 0442 35073",
    "sg:postcode":"37053",
    "sg:province":"Verona",
    "wof:name":"S.c.a. Aselogna Sas Di Dani F. E C.",
    "wof:placetype":"venue"
},
  "geometry": {"coordinates":[11.227091,45.189163],"type":"Point"}
}