{
  "type": "Feature",
  "properties": {
    "iso:country":"IT",
    "sg:address":"44042 Cento",
    "sg:city":"Cento",
    "sg:orig_category":"Centri Di Estetica E Cosmesi E Servizi",
    "sg:phone":"+39 051 683 1366",
    "sg:postcode":"44042",
    "sg:province":"Ferrara",
    "wof:name":"Tartari Andrea",
    "wof:placetype":"venue"
},
  "geometry": {"coordinates":[11.477671,44.947525],"type":"Point"}
}