{
  "type": "Feature",
  "properties": {
    "addr:full":"4, Via Romagna 20098 San Giuliano Milanese San Giuliano Milanese Milano 20098",
    "addr:postcode":"20098;20098",
    "addr:street":"Via Romagna",
    "iso:country":"IT",
    "sg:address":"4, Via Romagna 20098 San Giuliano Milanese",
    "sg:city":"San Giuliano Milanese",
    "sg:classifiers":[
        {
            "category":"Professional",
            "subcategory":"Engineering",
            "type":"Services"
        }
    ],
    "sg:phone":"+39 39029881028",
    "sg:postcode":"20098",
    "sg:province":"Milano",
    "sg:tags":[
        "machine",
        "-",
        "mechanical"
    ],
    "wof:name":"Progalvano Di Appiani Pierpaolo & C. (s.a.s.)",
    "wof:placetype":"venue"
},
  "geometry": {"coordinates":[9.252046,45.398651],"type":"Point"}
}