{
  "type": "Feature",
  "properties": {
    "addr:full":"167, Via Della Prata 53048 Sinalunga Sinalunga Siena 53048",
    "addr:housenumber":"167",
    "addr:postcode":"53048;53048",
    "addr:street":"Via Della Prata",
    "iso:country":"IT",
    "sg:address":"167, Via Della Prata 53048 Sinalunga",
    "sg:city":"Sinalunga",
    "sg:classifiers":[
        {
            "category":"Professional",
            "subcategory":"Engineering",
            "type":"Services"
        }
    ],
    "sg:phone":"+39 0577 636058",
    "sg:postcode":"53048",
    "sg:province":"Siena",
    "sg:tags":[
        "machine",
        "-",
        "mechanical"
    ],
    "wof:name":"Esse 5 S.r.l.",
    "wof:placetype":"venue"
},
  "geometry": {"coordinates":[11.751916,43.209793],"type":"Point"}
}