{
  "type": "Feature",
  "properties": {
    "iso:country":"IT",
    "sg:address":"20129 Milano",
    "sg:city":"Milano",
    "sg:orig_category":"Cartotecnica E Servizi. Composizione, Stampa E Confezione. Forniture E Prodotti Informatici. Forniture Per Congressi, Fiere E Manifestazioni",
    "sg:phone":"+39 02 204 6877",
    "sg:postcode":"20129",
    "sg:province":"Milano",
    "wof:name":"Veronese Selvina",
    "wof:placetype":"venue"
},
  "geometry": {"coordinates":[9.211027,45.475975],"type":"Point"}
}