{
  "type": "Feature",
  "properties": {
    "addr:full":"95126 Catania Catania Catania 95126",
    "addr:postcode":"95126;95126",
    "iso:country":"IT",
    "sg:address":"95126 Catania",
    "sg:city":"Catania",
    "sg:orig_category":"Servizi E Lavori Industria Della Gomma",
    "sg:phone":"+39 095 336000",
    "sg:postcode":"95126",
    "sg:province":"Catania",
    "wof:name":"Amore Lorenzo",
    "wof:placetype":"venue"
},
  "geometry": {"coordinates":[15.085518,37.527775],"type":"Point"}
}