{
  "type": "Feature",
  "properties": {
    "addr:full":"95121 Catania Catania Catania 95121",
    "addr:postcode":"95121;95121",
    "iso:country":"IT",
    "sg:address":"95121 Catania",
    "sg:city":"Catania",
    "sg:orig_category":"Trasporti E Spedizioni Merci",
    "sg:phone":"+39 095 592311",
    "sg:postcode":"95121",
    "sg:province":"Catania",
    "wof:name":"Avimec Srl",
    "wof:placetype":"venue"
},
  "geometry": {"coordinates":[15.008988,37.415855],"type":"Point"}
}