{
  "type": "Feature",
  "properties": {
    "iso:country":"IT",
    "sg:address":"Via Del Lavoro, 9/11 37030 Colognola Ai Colli",
    "sg:city":"Colognola ai Colli",
    "sg:classifiers":[
        {
            "category":"Banks & Credit Unions",
            "subcategory":"Investment Brokerage",
            "type":"Services"
        }
    ],
    "sg:phone":"+39 045 615 9211",
    "sg:postcode":"37030",
    "sg:province":"Verona",
    "sg:tags":[
        "lighting",
        "system"
    ],
    "sg:website":"www.prisma-illuminazione.com",
    "wof:name":"Prisma Spa",
    "wof:placetype":"venue"
},
  "geometry": {"coordinates":[11.244623,45.423378],"type":"Point"}
}