{
  "type": "Feature",
  "properties": {
    "addr:full":"60022 Castelfidardo Castelfidardo Ancona 60022",
    "addr:postcode":"60022;60022",
    "iso:country":"IT",
    "sg:address":"60022 Castelfidardo",
    "sg:city":"Castelfidardo",
    "sg:orig_category":"Musica",
    "sg:phone":"+39 071 780973",
    "sg:postcode":"60022",
    "sg:province":"Ancona",
    "wof:name":"O.r.a.",
    "wof:placetype":"venue"
},
  "geometry": {"coordinates":[13.5360546112,43.5228157043],"type":"Point"}
}