{
  "type": "Feature",
  "properties": {
    "iso:country":"IT",
    "sg:address":"25018 Montichiari",
    "sg:city":"Montichiari",
    "sg:orig_category":"Trasporti E Spedizioni Merci",
    "sg:phone":"+39 030 996 0074",
    "sg:postcode":"25018",
    "sg:province":"Brescia",
    "sg:website":"http://www.frt-cse.com",
    "wof:name":"F.r.t. Srl",
    "wof:placetype":"venue"
},
  "geometry": {"coordinates":[10.367213,45.413536],"type":"Point"}
}