{
  "type": "Feature",
  "properties": {
    "iso:country":"IT",
    "sg:address":"60, Via Case Sparse 34070 Savogna D'isonzo",
    "sg:classifiers":[
        {
            "category":"Wholesale",
            "subcategory":"Drugs",
            "type":"Manufacturing & Wholesale Goods"
        }
    ],
    "sg:phone":"+39 0481 882501",
    "sg:postcode":"34070",
    "sg:province":"Gorizia",
    "sg:tags":[
        "chemical",
        "pharmaceutical"
    ],
    "wof:name":"Kemica - Tecnoconvert S.p.a.",
    "wof:placetype":"venue"
},
  "geometry": {"coordinates":[13.598746,45.898891],"type":"Point"}
}