{
  "type": "Feature",
  "properties": {
    "iso:country":"IT",
    "sg:address":"32020 Falcade",
    "sg:city":"Falcade",
    "sg:classifiers":[
        {
            "category":"Travel",
            "subcategory":"Hotels & Motels",
            "type":"Entertainment"
        }
    ],
    "sg:phone":"+39 0437 507311",
    "sg:postcode":"32020",
    "sg:province":"Belluno",
    "sg:tags":[
        "hotels",
        "facility"
    ],
    "wof:name":"Hotel San Giusto - S.i.a.t. Srl",
    "wof:placetype":"venue"
},
  "geometry": {"coordinates":[11.864218,46.353981],"type":"Point"}
}