{
  "type": "Feature",
  "properties": {
    "iso:country":"IT",
    "sg:address":"66041 Atessa",
    "sg:city":"Atessa",
    "sg:orig_category":"Automobili E Mezzi Di Trasporto",
    "sg:phone":"+39 0872 88451",
    "sg:postcode":"66041",
    "sg:province":"Chieti",
    "sg:website":"http://www.mvs.it",
    "wof:name":"Metalmeccanica Val Di Sangro",
    "wof:placetype":"venue"
},
  "geometry": {"coordinates":[14.460685,42.090908],"type":"Point"}
}