{
  "type": "Feature",
  "properties": {
    "iso:country":"IT",
    "sg:address":"38010 Taio",
    "sg:classifiers":[
        {
            "category":"Manufacturing",
            "subcategory":"Tools & Machinery",
            "type":"Manufacturing & Wholesale Goods"
        }
    ],
    "sg:phone":"+39 0463 468733",
    "sg:postcode":"38010",
    "sg:province":"Trento",
    "sg:tags":[
        "machining",
        "mechanical"
    ],
    "sg:website":"http://www.famatec.com",
    "wof:name":"Famatec Srl - Manipolatori Pneumatici",
    "wof:placetype":"venue"
},
  "geometry": {"coordinates":[11.066115,46.323017],"type":"Point"}
}