{
  "type": "Feature",
  "properties": {
    "iso:country":"IT",
    "sg:address":"36042 Breganze",
    "sg:city":"Breganze",
    "sg:orig_category":"Sughero Ed Agglomerati",
    "sg:phone":"+39 0445 873279",
    "sg:postcode":"36042",
    "sg:province":"Vicenza",
    "wof:name":"Sugherificio Bonino Srl",
    "wof:placetype":"venue"
},
  "geometry": {"coordinates":[11.567739,45.684101],"type":"Point"}
}