{
  "type": "Feature",
  "properties": {
    "iso:country":"IT",
    "sg:address":"31020 Villorba",
    "sg:city":"Villorba",
    "sg:orig_category":"Materiali Edili",
    "sg:phone":"+39 0422 608233",
    "sg:postcode":"31020",
    "sg:province":"Treviso",
    "sg:website":"http://www.volteco.it",
    "wof:name":"Volteco Spa",
    "wof:placetype":"venue"
},
  "geometry": {"coordinates":[12.24927,45.724716],"type":"Point"}
}