{
  "type": "Feature",
  "properties": {
    "iso:country":"IT",
    "sg:address":"14042 Calamandrana",
    "sg:city":"Calamandrana",
    "sg:orig_category":"Macchine, Impianti E Forniture Per Industria Grafica, Cartaria E Cartotecnica. Automazione E Macchine Per Ufficio",
    "sg:phone":"+39 0141 769004",
    "sg:postcode":"14042",
    "sg:province":"Asti",
    "wof:name":"Bersano Ezio",
    "wof:placetype":"venue"
},
  "geometry": {"coordinates":[8.326088,44.722195],"type":"Point"}
}