{
  "type": "Feature",
  "properties": {
    "iso:country":"IT",
    "sg:address":"18, Via Palmarina 33048 San Giovanni Al Natisone",
    "sg:city":"San Giovanni al Natisone",
    "sg:classifiers":[
        {
            "category":"Home & Garden",
            "subcategory":"Home Furnishings",
            "type":"Retail Goods"
        }
    ],
    "sg:phone":"+39 0432 756029",
    "sg:postcode":"33048",
    "sg:province":"Udine",
    "sg:tags":[
        "household"
    ],
    "wof:name":"Buiani Due S.r.l.",
    "wof:placetype":"venue"
},
  "geometry": {"coordinates":[13.398038,45.968929],"type":"Point"}
}