{
  "type": "Feature",
  "properties": {
    "addr:full":"70010 Valenzano Casamassima Bari 70010",
    "addr:postcode":"70010;70010",
    "iso:country":"IT",
    "sg:address":"70010 Valenzano",
    "sg:city":"Casamassima",
    "sg:orig_category":"Apparecchiature E Sistemi Per Magazzinaggio E Movimentazione",
    "sg:phone":"+39 080 467 4305",
    "sg:postcode":"70010",
    "sg:province":"Bari",
    "sg:website":"http://www.milanogiovanni.com",
    "wof:name":"Milano Giovanni",
    "wof:placetype":"venue"
},
  "geometry": {"coordinates":[16.887989,41.038113],"type":"Point"}
}