{
  "type": "Feature",
  "properties": {
    "addr:full":"28845 Domodossola Domodossola Verbano-Cusio-Ossola 28845",
    "addr:postcode":"28845;28845",
    "iso:country":"IT",
    "sg:address":"28845 Domodossola",
    "sg:city":"Domodossola",
    "sg:orig_category":"Imbiancatura",
    "sg:phone":"+39 0324 242017",
    "sg:postcode":"28845",
    "sg:province":"Verbano-Cusio-Ossola",
    "wof:name":"Roberti Sas",
    "wof:placetype":"venue"
},
  "geometry": {"coordinates":[8.272465,46.139969],"type":"Point"}
}