{
  "type": "Feature",
  "properties": {
    "iso:country":"IT",
    "sg:address":"59100 Prato",
    "sg:city":"Prato",
    "sg:orig_category":"Prodotti Chimici Di Base. Forniture Per Attivita' Industriali",
    "sg:phone":"+39 0574 630303",
    "sg:postcode":"59100",
    "sg:province":"Prato",
    "sg:website":"http://www.enzobresci.it",
    "wof:name":"Enzobresci Spa",
    "wof:placetype":"venue"
},
  "geometry": {"coordinates":[11.079829216,43.8719520569],"type":"Point"}
}