{
  "type": "Feature",
  "properties": {
    "addr:full":"Via Provinciale 65 24060 Cenate Sopra Cenate Sopra Bergamo 24060",
    "addr:housenumber":"65",
    "addr:postcode":"24060;24060",
    "addr:street":"Via Provinciale;Sopra",
    "iso:country":"IT",
    "sg:address":"Via Provinciale 65 24060 Cenate Sopra",
    "sg:city":"Cenate Sopra",
    "sg:classifiers":[
        {
            "category":"Health Services",
            "subcategory":"Nursing And Care Facility",
            "type":"Services"
        }
    ],
    "sg:phone":"+39 035 957006",
    "sg:postcode":"24060",
    "sg:province":"Bergamo",
    "sg:tags":[
        "industrial",
        "robot"
    ],
    "sg:website":"www.italianarobot.com",
    "wof:name":"Italiana Robot Srl",
    "wof:placetype":"venue"
},
  "geometry": {"coordinates":[9.810163,45.768269],"type":"Point"}
}