{
  "type": "Feature",
  "properties": {
    "iso:country":"IT",
    "sg:address":"24040 Bonate Sopra",
    "sg:city":"Bonate Sopra",
    "sg:orig_category":"Macchine, Impianti Ed Attrezzature Per Industria Alimentare E Bevande. Apparecchiature E Sistemi Per Imballaggio E Confezionamento",
    "sg:phone":"+39 035 494 2582",
    "sg:postcode":"24040",
    "sg:province":"Bergamo",
    "wof:name":"Import Export Bottling Engineering (s.r.l.)",
    "wof:placetype":"venue"
},
  "geometry": {"coordinates":[9.580295,45.680546],"type":"Point"}
}