{
  "type": "Feature",
  "properties": {
    "iso:country":"IT",
    "sg:address":"00185 Roma",
    "sg:city":"Roma",
    "sg:orig_category":"Servizi E Lavori Per Ecologia E Smaltimento Rifiuti. Acqua, Luce, Gas E Societa' Di Esercizio Pubblico",
    "sg:phone":"+39 06 444 0770",
    "sg:postcode":"00185",
    "sg:province":"Roma",
    "wof:name":"A.m.a. Roma",
    "wof:placetype":"venue"
},
  "geometry": {"coordinates":[12.520573,41.899994],"type":"Point"}
}