{
  "type": "Feature",
  "properties": {
    "iso:country":"IT",
    "sg:address":"82100 Benevento",
    "sg:city":"Benevento",
    "sg:orig_category":"Scuole E Servizi Scolastici. Centri Di Estetica E Cosmesi E Servizi. Ricerca, Selezione E Formazione Del Personale",
    "sg:phone":"+39 0824 311464",
    "sg:postcode":"82100",
    "sg:province":"Benevento",
    "wof:name":"Centro Estetico Elite - Scuola Di Formazione Professionale Moriello Srl",
    "wof:placetype":"venue"
},
  "geometry": {"coordinates":[14.794233,41.124485],"type":"Point"}
}