{
  "type": "Feature",
  "properties": {
    "iso:country":"IT",
    "sg:address":"1, Via Salani Eugenio Priamo 50056 Capraia E Limite",
    "sg:classifiers":[
        {
            "category":"Marine",
            "type":"Transportation"
        }
    ],
    "sg:phone":"+39 0571 979111",
    "sg:postcode":"50056",
    "sg:province":"Firenze",
    "sg:tags":[
        "transport",
        "sea"
    ],
    "wof:name":"B.c.s. S.r.l.",
    "wof:placetype":"venue"
},
  "geometry": {"coordinates":[11.256902,43.768734],"type":"Point"}
}