{
  "type": "Feature",
  "properties": {
    "iso:country":"IT",
    "sg:address":"50065 Pontassieve",
    "sg:city":"Molino del Piano",
    "sg:orig_category":"Servizi Culturali E Per Lo Spettacolo. Servizi Per Lo Sport E Il Tempo Libero. Servizi Per Aziende, Manifestazioni E Supporto Agli Scambi Commerciali",
    "sg:phone":"+39 055 836 4412",
    "sg:postcode":"50065",
    "sg:province":"Firenze",
    "wof:name":"Teatrando Snc",
    "wof:placetype":"venue"
},
  "geometry": {"coordinates":[11.40027,43.811447],"type":"Point"}
}