{
  "type": "Feature",
  "properties": {
    "iso:country":"IT",
    "sg:address":"88040 Gizzeria",
    "sg:city":"Gizzeria",
    "sg:orig_category":"Materiali Edili",
    "sg:phone":"+39 0968 466809",
    "sg:postcode":"88040",
    "sg:province":"Catanzaro",
    "wof:name":"Universal Gronda Di Joe De Luca",
    "wof:placetype":"venue"
},
  "geometry": {"coordinates":[16.210003,38.943504],"type":"Point"}
}