{
  "type": "Feature",
  "properties": {
    "addr:full":"Via Galatina 73043 Copertino Copertino Lecce 73043",
    "addr:postcode":"73043;73043",
    "addr:street":"Via Galatina",
    "iso:country":"IT",
    "sg:address":"Via Galatina 73043 Copertino",
    "sg:city":"Copertino",
    "sg:classifiers":[
        {
            "category":"Home & Garden",
            "subcategory":"Home Furnishings",
            "type":"Retail Goods"
        }
    ],
    "sg:phone":"+39 0832 934417",
    "sg:postcode":"73043",
    "sg:province":"Lecce",
    "sg:tags":[
        "household"
    ],
    "wof:name":"Red Moon S.r.l. Mobili Del Salento",
    "wof:placetype":"venue"
},
  "geometry": {"coordinates":[18.058531,40.264786],"type":"Point"}
}