{
  "type": "Feature",
  "properties": {
    "iso:country":"IT",
    "sg:address":"06087 Ponte San Giovanni",
    "sg:classifiers":[
        {
            "category":"Health Services",
            "subcategory":"Health Practitioner",
            "type":"Services"
        }
    ],
    "sg:phone":"+39 075 398599",
    "sg:province":"PG",
    "sg:tags":[
        "medici"
    ],
    "wof:name":"Epidam S.a.s. Di Mayer E Righi",
    "wof:placetype":"venue"
},
  "geometry": {"coordinates":[-72.886902,41.757599],"type":"Point"}
}