{
  "type": "Feature",
  "properties": {
    "iso:country":"IT",
    "sg:address":"41011 Campogalliano",
    "sg:city":"Campogalliano",
    "sg:orig_category":"Macchine Utensili E Impianti",
    "sg:phone":"+39 059 525253",
    "sg:postcode":"41011",
    "sg:province":"Modena",
    "wof:name":"Mec-ind S.r.l.",
    "wof:placetype":"venue"
},
  "geometry": {"coordinates":[10.843895,44.692833],"type":"Point"}
}