{
  "type": "Feature",
  "properties": {
    "iso:country":"IT",
    "sg:address":"108, Via Falterona 52014 Poppi",
    "sg:city":"Poppi",
    "sg:classifiers":[
        {
            "category":"Professional",
            "subcategory":"Engineering",
            "type":"Services"
        }
    ],
    "sg:phone":"+39 0575 550040",
    "sg:postcode":"52014",
    "sg:province":"Arezzo",
    "sg:tags":[
        "machine",
        "-",
        "mechanical"
    ],
    "wof:name":"Officina Metalmeccanica Specializzata O.m.s. (s.r.l.)",
    "wof:placetype":"venue"
},
  "geometry": {"coordinates":[11.745964,43.743748],"type":"Point"}
}