{
  "type": "Feature",
  "properties": {
    "iso:country":"IT",
    "sg:address":"00040 Roma",
    "sg:orig_category":"Macchine Ed Impianti Per Edilizia E Lavori Pubblici. Forniture Per Edilizia E Lavori Pubblici",
    "sg:phone":"+39 06 7980 0087",
    "sg:postcode":"00040",
    "sg:province":"Roma",
    "wof:name":"New Edil 2000 Di Schiavoni Antonello",
    "wof:placetype":"venue"
},
  "geometry": {"coordinates":[12.708748,41.827602],"type":"Point"}
}