{
  "type": "Feature",
  "properties": {
    "iso:country":"IT",
    "sg:address":"40050 Argelato",
    "sg:city":"Argelato",
    "sg:orig_category":"Elettronica Industriale, Prodotti E Apparecchiature",
    "sg:phone":"+39 051 860064",
    "sg:postcode":"40050",
    "sg:province":"Bologna",
    "sg:website":"http://www.ably.it",
    "wof:name":"Ably Srl",
    "wof:placetype":"venue"
},
  "geometry": {"coordinates":[11.367912,44.609722],"type":"Point"}
}