{
  "type": "Feature",
  "properties": {
    "addr:full":"6, Via Giuseppe Garibaldi 23891 Barzano' Lecco 23891",
    "addr:postcode":"23891;23891",
    "addr:street":"Via Giuseppe Garibaldi;Barzano ' Lecco",
    "iso:country":"IT",
    "sg:address":"6, Via Giuseppe Garibaldi 23891 Barzano'",
    "sg:classifiers":[
        {
            "category":"Utilities",
            "subcategory":"Electric",
            "type":"Services"
        }
    ],
    "sg:phone":"+39 039 921 0551",
    "sg:postcode":"23891",
    "sg:province":"Lecco",
    "sg:tags":[
        "component",
        "electronic"
    ],
    "wof:name":"Sacchi Elettronica (s.r.l.)",
    "wof:placetype":"venue"
},
  "geometry": {"coordinates":[9.336033,45.709183],"type":"Point"}
}