{
  "type": "Feature",
  "properties": {
    "addr:full":"21040 Uboldo Uboldo Varese 21040",
    "addr:postcode":"21040;21040",
    "iso:country":"IT",
    "sg:address":"21040 Uboldo",
    "sg:city":"Uboldo",
    "sg:orig_category":"Verniciatura - Impianti E Macchine",
    "sg:phone":"+39 02 9678 2677",
    "sg:postcode":"21040",
    "sg:province":"Varese",
    "wof:name":"Fa.ro. Snc Verniciature Industriali",
    "wof:placetype":"venue"
},
  "geometry": {"coordinates":[8.856109,45.858883],"type":"Point"}
}