{
  "type": "Feature",
  "properties": {
    "addr:full":"Via Santa Maria Fulcorina 1; Milano; 20123 Milano Milano 20123",
    "addr:housenumber":"1",
    "addr:postcode":"20123;20123",
    "addr:street":"Via Santa Maria Fulcorina",
    "iso:country":"IT",
    "sg:address":"Via Santa Maria Fulcorina 1; Milano; 20123",
    "sg:city":"Milano",
    "sg:classifiers":[
        {
            "category":"Banks & Credit Unions",
            "subcategory":"Bank",
            "type":"Services"
        }
    ],
    "sg:phone":"+39 0285541",
    "sg:postcode":"20123",
    "sg:province":"Milano",
    "wof:name":"Banca Popolare Di Sondrio Scarl",
    "wof:placetype":"venue"
},
  "geometry": {"coordinates":[9.183751,45.463593],"type":"Point"}
}