{
  "type": "Feature",
  "properties": {
    "addr:full":"11100 Aosta Aosta Aosta 11100",
    "addr:postcode":"11100;11100",
    "iso:country":"IT",
    "sg:address":"11100 Aosta",
    "sg:city":"Aosta",
    "sg:orig_category":"Studi E Consulenze Amministrative, Commerciali E Aziendali. Studi E Consulenze Tecniche E Industriali. Consulenze Tecniche, Amministrative E Perizie",
    "sg:phone":"+39 0165 361615",
    "sg:postcode":"11100",
    "sg:province":"Aosta",
    "wof:name":"Ansed Snc",
    "wof:placetype":"venue"
},
  "geometry": {"coordinates":[7.313234,45.735001],"type":"Point"}
}