{
  "type": "Feature",
  "properties": {
    "iso:country":"IT",
    "sg:address":"Via Gramsci 202, 40010 Sala Bolognese, Bo",
    "sg:city":"Sala Bolognese",
    "sg:classifiers":[
        {
            "category":"Banks & Credit Unions",
            "subcategory":"Bank",
            "type":"Services"
        }
    ],
    "sg:postcode":"40010",
    "sg:province":"Bologna",
    "wof:name":"Banca Di Credito Cooperativo Di Sala Bolognese (bologna)",
    "wof:placetype":"venue"
},
  "geometry": {"coordinates":[11.267475,44.562317],"type":"Point"}
}