{
  "type": "Feature",
  "properties": {
    "addr:full":"Via Per Olgiate 23883 Brivio Brivio Lecco 23883",
    "addr:postcode":"23883;23883",
    "addr:street":"Via Per Olgiate",
    "iso:country":"IT",
    "sg:address":"Via Per Olgiate 23883 Brivio",
    "sg:city":"Brivio",
    "sg:classifiers":[
        {
            "category":"Professional",
            "subcategory":"Engineering",
            "type":"Services"
        }
    ],
    "sg:phone":"+39 039 532 0744",
    "sg:postcode":"23883",
    "sg:province":"Lecco",
    "sg:tags":[
        "machine",
        "-",
        "mechanical"
    ],
    "wof:name":"Vacuum Pump (s.p.a.)",
    "wof:placetype":"venue"
},
  "geometry": {"coordinates":[9.390071,45.852982],"type":"Point"}
}