{
  "type": "Feature",
  "properties": {
    "addr:full":"124, Via Como 20036 Meda Meda Milano 20036",
    "addr:housenumber":"124",
    "addr:postcode":"20036;20036",
    "addr:street":"Via Como",
    "iso:country":"IT",
    "sg:address":"124, Via Como 20036 Meda",
    "sg:city":"Meda",
    "sg:classifiers":[
        {
            "category":"Manufacturing",
            "subcategory":"Lumber",
            "type":"Manufacturing & Wholesale Goods"
        }
    ],
    "sg:phone":"+39 39036275201",
    "sg:postcode":"20036",
    "sg:province":"Milano",
    "sg:tags":[
        "wood"
    ],
    "wof:name":"S.i.a. Soc. Italiana Accessori Srl",
    "wof:placetype":"venue"
},
  "geometry": {"coordinates":[9.16271,45.671589],"type":"Point"}
}