{
  "type": "Feature",
  "properties": {
    "addr:full":"41, Via Del Fregno 70022 Altamura Altamura Bari 70022",
    "addr:postcode":"70022;70022",
    "addr:street":"Via Del Fregno",
    "iso:country":"IT",
    "sg:address":"41, Via Del Fregno 70022 Altamura",
    "sg:city":"Altamura",
    "sg:classifiers":[
        {
            "category":"Manufacturing",
            "subcategory":"Rubber & Plastics",
            "type":"Manufacturing & Wholesale Goods"
        }
    ],
    "sg:phone":"+39 080 310 1081",
    "sg:postcode":"70022",
    "sg:province":"Bari",
    "wof:name":"Nuova Tedeflex S.r.l.",
    "wof:placetype":"venue"
},
  "geometry": {"coordinates":[16.8692913055,41.1260528564],"type":"Point"}
}