{
  "type": "Feature",
  "properties": {
    "iso:country":"IT",
    "sg:address":"30174 Mestre",
    "sg:city":"Mestre",
    "sg:orig_category":"Servizi Editoriali",
    "sg:phone":"+39 041 950794",
    "sg:postcode":"30174",
    "sg:province":"Venezia",
    "wof:name":"Barnes Massimo",
    "wof:placetype":"venue"
},
  "geometry": {"coordinates":[12.243898,45.496212],"type":"Point"}
}