{
  "type": "Feature",
  "properties": {
    "addr:full":"123/bis, Lungo Dora Firenze 10153 Torino Torino Torino 10153",
    "addr:housenumber":"123 / bis",
    "addr:postcode":"10153;10153",
    "addr:street":"Lungo Dora",
    "iso:country":"IT",
    "sg:address":"123/bis, Lungo Dora Firenze 10153 Torino",
    "sg:city":"Torino",
    "sg:classifiers":[
        {
            "category":"Utilities",
            "subcategory":"Telephone",
            "type":"Services"
        }
    ],
    "sg:phone":"+39 39011858196",
    "sg:postcode":"10153",
    "sg:province":"Torino",
    "sg:tags":[
        "telecommunication"
    ],
    "wof:name":"Giornale Radiotelevisivo Piemonte (s.p.a.)",
    "wof:placetype":"venue"
},
  "geometry": {"coordinates":[7.686619,45.07056],"type":"Point"}
}