{
  "type": "Feature",
  "properties": {
    "iso:country":"IT",
    "sg:address":"50125 Firenze",
    "sg:city":"Firenze",
    "sg:orig_category":"Agenzie D'affari E Servizi Commerciali",
    "sg:phone":"+39 055 234 0688",
    "sg:postcode":"50125",
    "sg:province":"Firenze",
    "wof:name":"Prisma",
    "wof:placetype":"venue"
},
  "geometry": {"coordinates":[11.258047,43.74371],"type":"Point"}
}