{
  "type": "Feature",
  "properties": {
    "iso:country":"IT",
    "sg:address":"13043 Cigliano",
    "sg:city":"Cigliano",
    "sg:orig_category":"Forniture Per Edilizia E Lavori Pubblici",
    "sg:phone":"+39 0161 423167",
    "sg:postcode":"13043",
    "sg:province":"Vercelli",
    "sg:website":"http://www.viglianoedilizia.it",
    "wof:name":"Vigliano Edilizia Sas",
    "wof:placetype":"venue"
},
  "geometry": {"coordinates":[8.3941574097,45.3509788513],"type":"Point"}
}