{
  "type": "Feature",
  "properties": {
    "addr:full":"Via Della Siderurgica 37139 Verona Verona Verona 37139",
    "addr:postcode":"37139;37139",
    "addr:street":"Via Della Siderurgica",
    "iso:country":"IT",
    "sg:address":"Via Della Siderurgica 37139 Verona",
    "sg:city":"Verona",
    "sg:classifiers":[
        {
            "category":"Communications",
            "subcategory":"Film & Video Production",
            "type":"Services"
        }
    ],
    "sg:phone":"+39 045 851 0951",
    "sg:postcode":"37139",
    "sg:province":"Verona",
    "sg:tags":[
        "material",
        "audio-visual"
    ],
    "sg:website":"www.vincenzi.it",
    "wof:name":"Vincenzi & C. Srl",
    "wof:placetype":"venue"
},
  "geometry": {"coordinates":[10.991748,45.438366],"type":"Point"}
}