{
  "type": "Feature",
  "properties": {
    "iso:country":"IT",
    "sg:address":"Ctr Strizzi 23 72100 Brindisi",
    "sg:city":"Brindisi",
    "sg:orig_category":"Tomatoes, Peeled",
    "sg:phone":"+39 0831 519984",
    "sg:postcode":"72100",
    "sg:province":"Brindisi",
    "wof:name":"Ital Prodotti S.a.s. Di Rosato Franco",
    "wof:placetype":"venue"
},
  "geometry": {"coordinates":[17.942587,40.66259],"type":"Point"}
}