{
  "type": "Feature",
  "properties": {
    "iso:country":"IT",
    "sg:address":"95045 Misterbianco",
    "sg:city":"Misterbianco",
    "sg:classifiers":[
        {
            "category":"Home & Garden",
            "subcategory":"Carpets & Floor Coverings",
            "type":"Retail Goods"
        }
    ],
    "sg:phone":"+39 095 516191",
    "sg:postcode":"95045",
    "sg:province":"Catania",
    "sg:tags":[
        "linoleum"
    ],
    "wof:name":"A.k.q. Di Cappadonna Alfredo",
    "wof:placetype":"venue"
},
  "geometry": {"coordinates":[15.046015,37.533508],"type":"Point"}
}