{
  "type": "Feature",
  "properties": {
    "iso:country":"IT",
    "sg:address":"104, Via Provinciale 24021 Albino",
    "sg:city":"Albino",
    "sg:classifiers":[
        {
            "category":"Manufacturing",
            "subcategory":"Metals",
            "type":"Manufacturing & Wholesale Goods"
        }
    ],
    "sg:phone":"+39 39035751508",
    "sg:postcode":"24021",
    "sg:province":"Bergamo",
    "sg:tags":[
        "processing"
    ],
    "wof:name":"Rampinelli (s.p.a.)",
    "wof:placetype":"venue"
},
  "geometry": {"coordinates":[9.7368011475,45.7380332947],"type":"Point"}
}