{
  "type": "Feature",
  "properties": {
    "iso:country":"IT",
    "sg:address":"Via Mappano 10036 Settimo Torinese",
    "sg:city":"Settimo Torinese",
    "sg:classifiers":[
        {
            "category":"Professional",
            "subcategory":"Engineering",
            "type":"Services"
        }
    ],
    "sg:phone":"+39 011 897 7717",
    "sg:postcode":"10036",
    "sg:province":"Torino",
    "sg:tags":[
        "machine",
        "-",
        "mechanical"
    ],
    "wof:name":"Sileco (s.r.l.)",
    "wof:placetype":"venue"
},
  "geometry": {"coordinates":[7.734448,45.145718],"type":"Point"}
}