{
  "type": "Feature",
  "properties": {
    "iso:country":"IT",
    "sg:address":"51031 Agliana",
    "sg:city":"Agliana",
    "sg:orig_category":"Campionari",
    "sg:phone":"+39 0574 712270",
    "sg:postcode":"51031",
    "sg:province":"Pistoia",
    "wof:name":"M.d.l. Campionari Snc",
    "wof:placetype":"venue"
},
  "geometry": {"coordinates":[11.014866,43.902218],"type":"Point"}
}