{
  "type": "Feature",
  "properties": {
    "iso:country":"IT",
    "sg:address":"75, Via Bassanese 31010 Maser",
    "sg:city":"Maser",
    "sg:classifiers":[
        {
            "category":"Food & Beverages",
            "subcategory":"Dairy",
            "type":"Retail Goods"
        }
    ],
    "sg:phone":"+39 0423 923075",
    "sg:postcode":"31010",
    "sg:province":"Treviso",
    "sg:tags":[
        "product"
    ],
    "wof:name":"Basso Sebastiano (s.r.l.)",
    "wof:placetype":"venue"
},
  "geometry": {"coordinates":[11.970532,45.80685],"type":"Point"}
}