{
  "type": "Feature",
  "properties": {
    "iso:country":"IT",
    "sg:address":"Z.i. P.i.p. Loc. Saglieta82020 Paduli",
    "sg:city":"Paduli",
    "sg:classifiers":[
        {
            "category":"Shopping",
            "subcategory":"Computers & Home Electronics",
            "type":"Retail Goods"
        }
    ],
    "sg:phone":"+39 0824 380299",
    "sg:postcode":"82020",
    "sg:province":"Benevento",
    "sg:tags":[
        "electronic",
        "electrical",
        "equipment"
    ],
    "sg:website":"http://www.csabattery.com",
    "wof:name":"C.s.a. Battery",
    "wof:placetype":"venue"
},
  "geometry": {"coordinates":[14.781174,41.130447],"type":"Point"}
}