{
  "type": "Feature",
  "properties": {
    "iso:country":"IT",
    "sg:address":"73100 Lecce",
    "sg:city":"Lecce",
    "sg:orig_category":"Agenzie Immobiliari",
    "sg:phone":"+39 0832 312856",
    "sg:postcode":"73100",
    "sg:province":"Lecce",
    "sg:website":"http://www.paginegialle.it/puntocasa-06",
    "wof:name":"Punto Casa Servizi Immobiliari Integrati Srl",
    "wof:placetype":"venue"
},
  "geometry": {"coordinates":[18.181963,40.354057],"type":"Point"}
}