{
  "type": "Feature",
  "properties": {
    "iso:country":"IT",
    "sg:address":"Piazza Tolomei 11; Siena; 53100",
    "sg:city":"Siena",
    "sg:classifiers":[
        {
            "category":"Banks & Credit Unions",
            "subcategory":"Bank",
            "type":"Services"
        }
    ],
    "sg:phone":"+39 0577 288541",
    "sg:postcode":"53100",
    "sg:province":"Siena",
    "wof:name":"Cassa Di Risparmio Di Firenze Spa",
    "wof:placetype":"venue"
},
  "geometry": {"coordinates":[11.299894,43.335835],"type":"Point"}
}