{
  "type": "Feature",
  "properties": {
    "iso:country":"IT",
    "sg:address":"53/a, Via Di Vittorio 43045 Fornovo Di Taro",
    "sg:city":"Fornovo di Taro",
    "sg:classifiers":[
        {
            "category":"Manufacturing",
            "subcategory":"Metals",
            "type":"Manufacturing & Wholesale Goods"
        }
    ],
    "sg:phone":"+39 39052539152",
    "sg:postcode":"43045",
    "sg:province":"Parma",
    "sg:tags":[
        "processing"
    ],
    "wof:name":"Marimac (s.n.c.)",
    "wof:placetype":"venue"
},
  "geometry": {"coordinates":[10.2282800674,44.7164039612],"type":"Point"}
}