{
  "type": "Feature",
  "properties": {
    "addr:full":"57121 Livorno Livorno Livorno 57121",
    "addr:postcode":"57121;57121",
    "iso:country":"IT",
    "sg:address":"57121 Livorno",
    "sg:city":"Livorno",
    "sg:orig_category":"Acquari Ornamentali Ed Accessori",
    "sg:phone":"+39 0586 410566",
    "sg:postcode":"57121",
    "sg:province":"Livorno",
    "wof:name":"Riccioni Raffaele Habitat Acquari",
    "wof:placetype":"venue"
},
  "geometry": {"coordinates":[10.3565,43.565472],"type":"Point"}
}