{
  "type": "Feature",
  "properties": {
    "iso:country":"IT",
    "sg:address":"21014 Laveno Mombello",
    "sg:city":"Laveno",
    "sg:orig_category":"Arredamenti E Mobili Professionali. Apparecchi, Attrezzature E Forniture Per Centri Estetici. Arredi Ed Attrezzature Per Attivita' Commerciali Ed Artigianali",
    "sg:phone":"+39 0332 626339",
    "sg:postcode":"21014",
    "sg:province":"Varese",
    "wof:name":"Tecno Stile S.r.l.",
    "wof:placetype":"venue"
},
  "geometry": {"coordinates":[8.566189,45.941097],"type":"Point"}
}