{
  "type": "Feature",
  "properties": {
    "iso:country":"IT",
    "sg:address":"45, Via Salvatore Quasimodo 25020 Flero",
    "sg:city":"Flero",
    "sg:classifiers":[
        {
            "category":"Autos & Motor Vehicles",
            "subcategory":"Automobile Sales",
            "type":"Retail Goods"
        }
    ],
    "sg:phone":"+39 030 268 1341",
    "sg:postcode":"25020",
    "sg:province":"Brescia",
    "sg:tags":[
        "equipment",
        "transport"
    ],
    "wof:name":"Gi - Vi (s.r.l.)",
    "wof:placetype":"venue"
},
  "geometry": {"coordinates":[10.161189,45.490177],"type":"Point"}
}