{
  "type": "Feature",
  "properties": {
    "addr:full":"122, Via Scuderlando 37060 Castel D'azzano Azzano Verona 37060",
    "addr:housenumber":"122",
    "addr:postcode":"37060;37060",
    "addr:street":"Via Scuderlando",
    "iso:country":"IT",
    "sg:address":"122, Via Scuderlando 37060 Castel D'azzano",
    "sg:city":"Azzano",
    "sg:classifiers":[
        {
            "category":"Travel",
            "subcategory":"Travel Agent",
            "type":"Entertainment"
        }
    ],
    "sg:phone":"+39 045 852 0932",
    "sg:postcode":"37060",
    "sg:province":"Verona",
    "sg:tags":[
        "business"
    ],
    "wof:name":"Hotel Cristallo",
    "wof:placetype":"venue"
},
  "geometry": {"coordinates":[10.962797,45.368568],"type":"Point"}
}