{
  "type": "Feature",
  "properties": {
    "addr:full":"10058 Sestriere Sestriere Torino 10058",
    "addr:postcode":"10058;10058",
    "iso:country":"IT",
    "sg:address":"10058 Sestriere",
    "sg:city":"Sestriere",
    "sg:orig_category":"Servizi Per Lo Sport E Il Tempo Libero. Servizi Al Turismo",
    "sg:phone":"+39 0122 799411",
    "sg:postcode":"10058",
    "sg:province":"Torino",
    "wof:name":"Sestrieres S.p.a.",
    "wof:placetype":"venue"
},
  "geometry": {"coordinates":[6.887967,44.970013],"type":"Point"}
}