{
  "type": "Feature",
  "properties": {
    "iso:country":"IT",
    "sg:address":"40054 Budrio",
    "sg:city":"Budrio",
    "sg:orig_category":"Macchine, Impianti Ed Attrezzature Per Agricoltura E Zootecnia",
    "sg:phone":"+39 051 800253",
    "sg:postcode":"40054",
    "sg:province":"Bologna",
    "sg:website":"http://www.checchiemagli.com",
    "wof:name":"Checchi & Magli",
    "wof:placetype":"venue"
},
  "geometry": {"coordinates":[11.526902,44.524387],"type":"Point"}
}