{
  "type": "Feature",
  "properties": {
    "addr:full":"10015 Ivrea Ivrea Torino 10015",
    "addr:postcode":"10015;10015",
    "iso:country":"IT",
    "sg:address":"10015 Ivrea",
    "sg:city":"Ivrea",
    "sg:orig_category":"Arredi Ed Attrezzature Per Uffici",
    "sg:phone":"+39 0125 230866",
    "sg:postcode":"10015",
    "sg:province":"Torino",
    "wof:name":"So.ca.d.a. Di Iachi Bonvin & Grosso (s.n.c.)",
    "wof:placetype":"venue"
},
  "geometry": {"coordinates":[7.877191,45.437946],"type":"Point"}
}