{
  "type": "Feature",
  "properties": {
    "iso:country":"IT",
    "sg:address":"10142 Torino",
    "sg:city":"Torino",
    "sg:orig_category":"Arredamenti - Vendita Al Dettaglio",
    "sg:phone":"+39 011 701092",
    "sg:postcode":"10142",
    "sg:province":"Torino",
    "sg:website":"http://www.comerlegno.it",
    "wof:name":"Comerlegno",
    "wof:placetype":"venue"
},
  "geometry": {"coordinates":[7.622406,45.065262],"type":"Point"}
}