{
  "type": "Feature",
  "properties": {
    "iso:country":"IT",
    "sg:address":"95121 Catania",
    "sg:city":"Catania",
    "sg:classifiers":[
        {
            "category":"Education",
            "subcategory":"Vocational School",
            "type":"Public Place"
        }
    ],
    "sg:phone":"+39 095 592014",
    "sg:postcode":"95121",
    "sg:province":"Catania",
    "sg:tags":[
        "product",
        "livestock",
        "chemicals",
        "supplies",
        "breeding",
        "agriculture",
        "secondary"
    ],
    "wof:name":"Eurozolfi Srl",
    "wof:placetype":"venue"
},
  "geometry": {"coordinates":[15.04773,37.494564],"type":"Point"}
}