{
  "type": "Feature",
  "properties": {
    "addr:full":"40059 Medicina Medicina Bologna 40059",
    "addr:postcode":"40059;40059",
    "iso:country":"IT",
    "sg:address":"40059 Medicina",
    "sg:city":"Medicina",
    "sg:orig_category":"Shopping. Prodotti Cosmetici E Da Toeletta",
    "sg:phone":"+39 051 852396",
    "sg:postcode":"40059",
    "sg:province":"Bologna",
    "wof:name":"E.cos. - Ecologia E Cosmesi",
    "wof:placetype":"venue"
},
  "geometry": {"coordinates":[11.644242,44.478725],"type":"Point"}
}