{
  "type": "Feature",
  "properties": {
    "iso:country":"IT",
    "sg:address":"10015 Ivrea",
    "sg:city":"Ivrea",
    "sg:orig_category":"Macchine, Impianti Ed Attrezzature Per Abbigliamento E Pelletterie",
    "sg:phone":"+39 0125 615242",
    "sg:postcode":"10015",
    "sg:province":"Torino",
    "wof:name":"Colombo Sas Di Riviera Ada",
    "wof:placetype":"venue"
},
  "geometry": {"coordinates":[7.761822,45.130444],"type":"Point"}
}