{
  "type": "Feature",
  "properties": {
    "iso:country":"IT",
    "sg:address":"84013 Cava De'tirreni",
    "sg:orig_category":"Agricoltura, Orticoltura E Floricoltura",
    "sg:phone":"+39 089 341612",
    "sg:postcode":"84013",
    "sg:province":"Salerno",
    "wof:name":"Ente Tabacchi Italiani",
    "wof:placetype":"venue"
},
  "geometry": {"coordinates":[14.705554,40.70031],"type":"Point"}
}