{
  "type": "Feature",
  "properties": {
    "iso:country":"IT",
    "sg:address":"27049 Stradella",
    "sg:city":"Stradella",
    "sg:orig_category":"Materiali Semilavorati Metallici",
    "sg:postcode":"27049",
    "sg:province":"Pavia",
    "wof:name":"Pi.ro S.r.l.",
    "wof:placetype":"venue"
},
  "geometry": {"coordinates":[9.304259,45.077358],"type":"Point"}
}