{
  "type": "Feature",
  "properties": {
    "addr:full":"20017 Rho Rho Milano 20017",
    "addr:postcode":"20017;20017",
    "iso:country":"IT",
    "sg:address":"20017 Rho",
    "sg:city":"Rho",
    "sg:orig_category":"Non-classified Establishments",
    "sg:phone":"+39 02 3391 5225",
    "sg:postcode":"20017",
    "sg:province":"Milano",
    "sg:website":"http://www.paginegialle.it/vilmarsrl",
    "wof:name":"Vilmar Srl",
    "wof:placetype":"venue"
},
  "geometry": {"coordinates":[9.080031,45.52861],"type":"Point"}
}