{
  "type": "Feature",
  "properties": {
    "iso:country":"IT",
    "sg:address":"Via F D'aragona 12; Barletta",
    "sg:classifiers":[
        {
            "category":"Banks & Credit Unions",
            "subcategory":"Bank",
            "type":"Services"
        }
    ],
    "sg:phone":"+39 0883 532015",
    "wof:name":"Banco Di Roma",
    "wof:placetype":"venue"
},
  "geometry": {"coordinates":[16.281801,41.318207],"type":"Point"}
}