{
  "type": "Feature",
  "properties": {
    "iso:country":"IT",
    "sg:address":"35021 Agna",
    "sg:city":"Agna",
    "sg:orig_category":"Servizi E Lavori Per Agricoltura E Zootecnia",
    "sg:phone":"+39 049 538 1127",
    "sg:postcode":"35021",
    "sg:province":"Padova",
    "wof:name":"Nardi Fabrizio E Tiziano",
    "wof:placetype":"venue"
},
  "geometry": {"coordinates":[11.947848,45.170094],"type":"Point"}
}