{
  "type": "Feature",
  "properties": {
    "iso:country":"IT",
    "sg:address":"20012 Cuggiono",
    "sg:city":"Cuggiono",
    "sg:orig_category":"Sport - Articoli E Forniture",
    "sg:phone":"+39 02 974035",
    "sg:postcode":"20012",
    "sg:province":"Milano",
    "wof:name":"Beccaglia Angelo",
    "wof:placetype":"venue"
},
  "geometry": {"coordinates":[8.795673,45.50341],"type":"Point"}
}