{
  "type": "Feature",
  "properties": {
    "addr:full":"65013 Citta' S.angelo Pescara 65013",
    "addr:postcode":"65013;65013",
    "iso:country":"IT",
    "sg:address":"65013 Citta' S.angelo",
    "sg:orig_category":"Abbigliamento - Produzione E Ingrosso",
    "sg:phone":"+39 085 950525",
    "sg:postcode":"65013",
    "sg:province":"Pescara",
    "wof:name":"Gelsumini Antonio Carlo",
    "wof:placetype":"venue"
},
  "geometry": {"coordinates":[14.214094,42.464825],"type":"Point"}
}