{
  "type": "Feature",
  "properties": {
    "addr:full":"2, Via P. Mayr 39055 Laives Laives Bolzano/Bozen 39055",
    "addr:postcode":"39055;39055",
    "addr:street":"Via P. Mayr",
    "iso:country":"IT",
    "sg:address":"2, Via P. Mayr 39055 Laives",
    "sg:city":"Laives",
    "sg:classifiers":[
        {
            "category":"Food & Beverages",
            "subcategory":"Groceries & Convenience Stores",
            "type":"Retail Goods"
        }
    ],
    "sg:phone":"+39 0471 954141",
    "sg:postcode":"39055",
    "sg:province":"Bolzano/Bozen",
    "sg:tags":[
        "product",
        "related"
    ],
    "wof:name":"Dallago",
    "wof:placetype":"venue"
},
  "geometry": {"coordinates":[11.3395805359,46.4278106689],"type":"Point"}
}