{
  "type": "Feature",
  "properties": {
    "iso:country":"IT",
    "sg:address":"92017 Sambuca Di Sicilia",
    "sg:city":"Sambuca di Sicilia",
    "sg:orig_category":"Prodotti Chimici Secondari",
    "sg:phone":"+39 0925 941042",
    "sg:postcode":"92017",
    "sg:province":"Agrigento",
    "wof:name":"Di Prima Gaspare",
    "wof:placetype":"venue"
},
  "geometry": {"coordinates":[13.104845047,37.6462059021],"type":"Point"}
}