{
  "type": "Feature",
  "properties": {
    "addr:full":"198, Via Puliche 54100 Massa Massa Massa-Carrara 54100",
    "addr:housenumber":"198",
    "addr:postcode":"54100;54100",
    "addr:street":"Via Puliche",
    "iso:country":"IT",
    "sg:address":"198, Via Puliche 54100 Massa",
    "sg:city":"Massa",
    "sg:classifiers":[
        {
            "category":"Building & Trades",
            "subcategory":"Construction",
            "type":"Services"
        }
    ],
    "sg:phone":"+39 0585 256099",
    "sg:postcode":"54100",
    "sg:province":"Massa-Carrara",
    "sg:tags":[
        "work",
        "public"
    ],
    "wof:name":"D.d.r Costruzioni E Smaltimenti S.r.l.",
    "wof:placetype":"venue"
},
  "geometry": {"coordinates":[10.112231,44.01479],"type":"Point"}
}