{
  "type": "Feature",
  "properties": {
    "iso:country":"IT",
    "sg:address":"25135 Brescia",
    "sg:city":"Brescia",
    "sg:orig_category":"Gioielleria, Oreficeria E Argenteria. Articoli Da Regalo. Shopping",
    "sg:phone":"+39 030 336 5361",
    "sg:postcode":"25135",
    "sg:province":"Brescia",
    "wof:name":"Donegani Fratelli Di Donegani & C. (s.n.c.)",
    "wof:placetype":"venue"
},
  "geometry": {"coordinates":[10.280519,45.49324],"type":"Point"}
}