{
  "type": "Feature",
  "properties": {
    "addr:full":"Via Firenze 1/11; Andria; 70031 Andria Bari 70031",
    "addr:housenumber":"1 / 11",
    "addr:postcode":"70031;70031",
    "addr:street":"Via Firenze",
    "iso:country":"IT",
    "sg:address":"Via Firenze 1/11; Andria; 70031",
    "sg:city":"Andria",
    "sg:classifiers":[
        {
            "category":"Banks & Credit Unions",
            "subcategory":"Bank",
            "type":"Services"
        }
    ],
    "sg:phone":"+39 0883 592325",
    "sg:postcode":"70031",
    "sg:province":"Bari",
    "wof:name":"Banca Popolare Di Puglia, E Basilicata Scarl",
    "wof:placetype":"venue"
},
  "geometry": {"coordinates":[16.300455,41.230099],"type":"Point"}
}