{
  "type": "Feature",
  "properties": {
    "addr:full":"24024 Gandino Gandino Bergamo 24024",
    "addr:postcode":"24024;24024",
    "iso:country":"IT",
    "sg:address":"24024 Gandino",
    "sg:city":"Gandino",
    "sg:classifiers":[
        {
            "category":"Manufacturing",
            "subcategory":"Wood Products",
            "type":"Manufacturing & Wholesale Goods"
        }
    ],
    "sg:phone":"+39 035 745215",
    "sg:postcode":"24024",
    "sg:province":"Bergamo",
    "sg:tags":[
        "industry",
        "machinery",
        "furnishing",
        "supply"
    ],
    "wof:name":"Manifattura Ariete Spa",
    "wof:placetype":"venue"
},
  "geometry": {"coordinates":[9.9077577591,45.8100700378],"type":"Point"}
}