{
  "type": "Feature",
  "properties": {
    "iso:country":"IT",
    "sg:address":"50058 Signa",
    "sg:city":"Signa",
    "sg:orig_category":"Decoratori",
    "sg:phone":"+39 055 873 9876",
    "sg:postcode":"50058",
    "sg:province":"Firenze",
    "wof:name":"Punto Imbiancatura Srl",
    "wof:placetype":"venue"
},
  "geometry": {"coordinates":[11.126222,43.798019],"type":"Point"}
}