{
  "type": "Feature",
  "properties": {
    "iso:country":"IT",
    "sg:address":"25021 Bagnolo Mella",
    "sg:city":"Bagnolo Mella",
    "sg:orig_category":"Abiti Da Lavoro Ed Indumenti Protettivi",
    "sg:phone":"+39 030 682 1860",
    "sg:postcode":"25021",
    "sg:province":"Brescia",
    "sg:website":"http://www.baitecnica.it",
    "wof:name":"Bai Tecnica Srl",
    "wof:placetype":"venue"
},
  "geometry": {"coordinates":[10.182368,45.390373],"type":"Point"}
}