{
  "type": "Feature",
  "properties": {
    "addr:full":"30, Via Piemonte 58022 Follonica Follonica Grosseto 58022",
    "addr:postcode":"58022;58022",
    "addr:street":"Via Piemonte",
    "iso:country":"IT",
    "sg:address":"30, Via Piemonte 58022 Follonica",
    "sg:city":"Follonica",
    "sg:orig_category":"Miscellaneous Products",
    "sg:phone":"+39 39056657278",
    "sg:postcode":"58022",
    "sg:province":"Grosseto",
    "wof:name":"Dive System S.r.l",
    "wof:placetype":"venue"
},
  "geometry": {"coordinates":[10.7690553665,42.9193954468],"type":"Point"}
}