{
  "type": "Feature",
  "properties": {
    "iso:country":"IT",
    "sg:address":"12, Viale Colombo Cristoforo 20090 Trezzano Sul Naviglio",
    "sg:city":"Trezzano sul Naviglio",
    "sg:classifiers":[
        {
            "category":"Manufacturing",
            "subcategory":"Glass & Minerals",
            "type":"Manufacturing & Wholesale Goods"
        }
    ],
    "sg:phone":"+39 02 4840 2766",
    "sg:postcode":"20090",
    "sg:province":"Milano",
    "wof:name":"Vetrerie Bruni Spa",
    "wof:placetype":"venue"
},
  "geometry": {"coordinates":[9.071084,45.425713],"type":"Point"}
}