{
  "type": "Feature",
  "properties": {
    "addr:full":"16042 Carasco Carasco Genova 16042",
    "addr:postcode":"16042;16042",
    "iso:country":"IT",
    "sg:address":"16042 Carasco",
    "sg:city":"Carasco",
    "sg:orig_category":"Automazione E Robotica - Apparecchiature E Componenti",
    "sg:phone":"+39 0185 351840",
    "sg:postcode":"16042",
    "sg:province":"Genova",
    "wof:name":"Nuova Seristudio Di Deiana Roberto",
    "wof:placetype":"venue"
},
  "geometry": {"coordinates":[9.361758,44.358757],"type":"Point"}
}