{
  "type": "Feature",
  "properties": {
    "iso:country":"IT",
    "sg:address":"Via Cardito, 83031 Ariano Irpino, Av",
    "sg:city":"Ariano Irpino",
    "sg:classifiers":[
        {
            "category":"Banks & Credit Unions",
            "subcategory":"Bank",
            "type":"Services"
        }
    ],
    "sg:postcode":"83031",
    "sg:province":"Avellino",
    "wof:name":"Banca Popolare Ariano Valle Ufita Scrl",
    "wof:placetype":"venue"
},
  "geometry": {"coordinates":[15.082317,41.136295],"type":"Point"}
}