{
  "type": "Feature",
  "properties": {
    "iso:country":"IT",
    "sg:address":"20098 San Giuliano Milanese",
    "sg:city":"San Giuliano Milanese",
    "sg:orig_category":"Macchine Utensili E Impianti",
    "sg:phone":"+39 02 984 8577",
    "sg:postcode":"20098",
    "sg:province":"Milano",
    "wof:name":"Commerciale Lem",
    "wof:placetype":"venue"
},
  "geometry": {"coordinates":[9.26124,45.416744],"type":"Point"}
}