{
  "type": "Feature",
  "properties": {
    "iso:country":"IT",
    "sg:address":"50145 Firenze",
    "sg:city":"Firenze",
    "sg:orig_category":"Nautica. Ricambi E Componenti Dei Mezzi Di Trasporto",
    "sg:phone":"+39 055 318972",
    "sg:postcode":"50145",
    "sg:province":"Firenze",
    "sg:website":"http://www.acquasportnautica.it",
    "wof:name":"Acquasport Nautica",
    "wof:placetype":"venue"
},
  "geometry": {"coordinates":[11.195867,43.802845],"type":"Point"}
}