{
  "type": "Feature",
  "properties": {
    "iso:country":"IT",
    "sg:address":"20032 Cormano",
    "sg:city":"Cormano",
    "sg:orig_category":"Utensili Meccanici E Materiali",
    "sg:phone":"+39 02 615 2604",
    "sg:postcode":"20032",
    "sg:province":"Milano",
    "wof:name":"Seal (s.r.l.)",
    "wof:placetype":"venue"
},
  "geometry": {"coordinates":[9.151459,45.549328],"type":"Point"}
}