{
  "type": "Feature",
  "properties": {
    "iso:country":"IT",
    "sg:address":"Via Piave 20036 Meda",
    "sg:city":"Meda",
    "sg:classifiers":[
        {
            "category":"Shopping",
            "subcategory":"Crafts & Fabrics",
            "type":"Retail Goods"
        }
    ],
    "sg:phone":"+39 39036275789",
    "sg:postcode":"20036",
    "sg:province":"Milano",
    "wof:name":"M.t.s. Di De Nova Luigi & C. A Sas",
    "wof:placetype":"venue"
},
  "geometry": {"coordinates":[9.1642503738,45.6551513672],"type":"Point"}
}