{
  "type": "Feature",
  "properties": {
    "addr:full":"21052 Busto Arsizio Busto Arsizio Varese 21052",
    "addr:postcode":"21052;21052",
    "iso:country":"IT",
    "sg:address":"21052 Busto Arsizio",
    "sg:city":"Busto Arsizio",
    "sg:orig_category":"Motori Ed Organi Di Trasmissione",
    "sg:phone":"+39 0331 681797",
    "sg:postcode":"21052",
    "sg:province":"Varese",
    "wof:name":"Gi.di Service S.r.l.",
    "wof:placetype":"venue"
},
  "geometry": {"coordinates":[8.8509073257,45.618927002],"type":"Point"}
}