{
  "type": "Feature",
  "properties": {
    "iso:country":"IT",
    "sg:address":"Via Darwin, 22/13 Int. 59 20019 Settimo Milanese",
    "sg:city":"Settimo Milanese",
    "sg:classifiers":[
        {
            "category":"Manufacturing",
            "subcategory":"Chemicals & Compounds",
            "type":"Manufacturing & Wholesale Goods"
        }
    ],
    "sg:phone":"+39 02 328 8511",
    "sg:postcode":"20019",
    "sg:province":"Milano",
    "sg:tags":[
        "base"
    ],
    "sg:website":"www.urad.it",
    "wof:name":"Urad Snc",
    "wof:placetype":"venue"
},
  "geometry": {"coordinates":[9.058441,45.46381],"type":"Point"}
}