{
  "type": "Feature",
  "properties": {
    "addr:full":"25040 Monticelli Brusati Monticelli Brusati Brescia 25040",
    "addr:postcode":"25040;brusati;25040",
    "addr:street":"Brescia",
    "iso:country":"IT",
    "sg:address":"25040 Monticelli Brusati",
    "sg:city":"Monticelli Brusati",
    "sg:orig_category":"Fonderie Pressofusione",
    "sg:phone":"+39 030 685 0886",
    "sg:postcode":"25040",
    "sg:province":"Brescia",
    "wof:name":"Val Cast Srl",
    "wof:placetype":"venue"
},
  "geometry": {"coordinates":[10.1014318466,45.6358108521],"type":"Point"}
}