{
  "type": "Feature",
  "properties": {
    "iso:country":"IT",
    "sg:address":"21100 Varese",
    "sg:city":"Varese",
    "sg:orig_category":"Telecomunicazioni E Telefonia, Impianti, Apparecchi E Servizi",
    "sg:phone":"+39 0332 286800",
    "sg:postcode":"21100",
    "sg:province":"Varese",
    "wof:name":"E.t.s. Impianti Srl",
    "wof:placetype":"venue"
},
  "geometry": {"coordinates":[8.82146,45.822994],"type":"Point"}
}