{
  "type": "Feature",
  "properties": {
    "addr:full":"83030 Montefredane Arcella Avellino 83030",
    "addr:postcode":"83030;83030",
    "iso:country":"IT",
    "sg:address":"83030 Montefredane",
    "sg:city":"Arcella",
    "sg:orig_category":"Valvole E Apparecchiature Di Misura",
    "sg:phone":"+39 0825 607306",
    "sg:postcode":"83030",
    "sg:province":"Avellino",
    "wof:name":"Giordano Idraulica Snc",
    "wof:placetype":"venue"
},
  "geometry": {"coordinates":[14.827763,40.950302],"type":"Point"}
}