{
  "type": "Feature",
  "properties": {
    "iso:country":"IT",
    "sg:address":"50060 Pelago",
    "sg:city":"Pelago",
    "sg:orig_category":"Servizi E Lavori Per Ecologia E Smaltimento Rifiuti. Servizi Ausiliari Di Sorveglianza, Manutenzione E Pulizia",
    "sg:phone":"+39 055 659 3454",
    "sg:postcode":"50060",
    "sg:province":"Firenze",
    "wof:name":"Berti Di Berti Gisella",
    "wof:placetype":"venue"
},
  "geometry": {"coordinates":[11.444119,43.776566],"type":"Point"}
}