{
  "type": "Feature",
  "properties": {
    "iso:country":"IT",
    "sg:address":"37047 San Bonifacio",
    "sg:city":"San Bonifacio",
    "sg:orig_category":"Servizi Al Turismo. Trasporto Pubblico E Privato. Acqua, Luce, Gas E Societa' Di Esercizio Pubblico",
    "sg:phone":"+39 045 761 0445",
    "sg:postcode":"37047",
    "sg:province":"Verona",
    "wof:name":"Azienda Provinciale Trasporti",
    "wof:placetype":"venue"
},
  "geometry": {"coordinates":[11.283882,45.392498],"type":"Point"}
}