{
  "type": "Feature",
  "properties": {
    "addr:full":"41100 Modena Modena Modena 41100",
    "addr:postcode":"41100;41100",
    "iso:country":"IT",
    "sg:address":"41100 Modena",
    "sg:city":"Modena",
    "sg:orig_category":"Motori Ed Organi Di Trasmissione",
    "sg:phone":"+39 059 30084",
    "sg:postcode":"41100",
    "sg:province":"Modena",
    "wof:name":"Metalcastello Spa",
    "wof:placetype":"venue"
},
  "geometry": {"coordinates":[10.9296503067,44.6459350586],"type":"Point"}
}