{
  "type": "Feature",
  "properties": {
    "iso:country":"IT",
    "sg:address":"10141 Torino",
    "sg:city":"Torino",
    "sg:orig_category":"Impiantistica E Prodotti Tecnologici Per Edilizia. Forniture Industriali Per Prevenzione, Controllo E Sicurezza",
    "sg:phone":"+39 011 337879",
    "sg:postcode":"10141",
    "sg:province":"Torino",
    "wof:name":"Savio Massimo Sas",
    "wof:placetype":"venue"
},
  "geometry": {"coordinates":[7.638512,45.065174],"type":"Point"}
}