{
  "type": "Feature",
  "properties": {
    "iso:country":"IT",
    "sg:address":"31046 Oderzo",
    "sg:city":"Oderzo",
    "sg:orig_category":"Legno E Semilavorati. Materiali Edili",
    "sg:phone":"+39 0422 712460",
    "sg:postcode":"31046",
    "sg:province":"Treviso",
    "wof:name":"Momi Bruno Snc Di Momi Bruno & C.",
    "wof:placetype":"venue"
},
  "geometry": {"coordinates":[12.496923,45.779934],"type":"Point"}
}