{
  "type": "Feature",
  "properties": {
    "addr:full":"6, Via Lombardia 56029 Santa Croce Sull'arno Pisa 56029",
    "addr:postcode":"56029;56029",
    "addr:street":"Via Lombardia",
    "iso:country":"IT",
    "sg:address":"6, Via Lombardia 56029 Santa Croce Sull'arno",
    "sg:classifiers":[
        {
            "category":"Manufacturing",
            "subcategory":"Textiles",
            "type":"Manufacturing & Wholesale Goods"
        }
    ],
    "sg:phone":"+39 0571 367013",
    "sg:postcode":"56029",
    "sg:province":"Pisa",
    "sg:tags":[
        "leather",
        "raw",
        "material",
        "-"
    ],
    "wof:name":"Conceria M B 3 Srl",
    "wof:placetype":"venue"
},
  "geometry": {"coordinates":[10.762089,43.715794],"type":"Point"}
}