{
  "type": "Feature",
  "properties": {
    "iso:country":"IT",
    "sg:address":"58, Via Commercio Quarto 29020 Gossolengo",
    "sg:city":"Gossolengo",
    "sg:classifiers":[
        {
            "category":"Shopping",
            "subcategory":"Clothing, Apparel, & Fashions",
            "type":"Retail Goods"
        }
    ],
    "sg:phone":"+39 0523 557259",
    "sg:postcode":"29020",
    "sg:province":"Piacenza",
    "sg:tags":[
        "clothes"
    ],
    "wof:name":"Galli",
    "wof:placetype":"venue"
},
  "geometry": {"coordinates":[9.669081,44.996311],"type":"Point"}
}