{
  "type": "Feature",
  "properties": {
    "iso:country":"IT",
    "sg:address":"32032 Feltre",
    "sg:city":"Feltre",
    "sg:orig_category":"Forniture Per Attivita' Industriali",
    "sg:phone":"+39 0439 2923",
    "sg:postcode":"32032",
    "sg:province":"Belluno",
    "wof:name":"Fer-com Srl-u.l. Ferut",
    "wof:placetype":"venue"
},
  "geometry": {"coordinates":[11.9114561081,46.0142211914],"type":"Point"}
}