{
  "type": "Feature",
  "properties": {
    "iso:country":"IT",
    "sg:address":"286, Via Tosarelli Bruno 40055 Castenaso",
    "sg:city":"Castenaso",
    "sg:classifiers":[
        {
            "category":"Professional",
            "subcategory":"Engineering",
            "type":"Services"
        }
    ],
    "sg:phone":"+39 39051780238",
    "sg:postcode":"40055",
    "sg:province":"Bologna",
    "sg:tags":[
        "machine",
        "-",
        "mechanical"
    ],
    "wof:name":"Sampingranaggi (s.r.l.)",
    "wof:placetype":"venue"
},
  "geometry": {"coordinates":[11.444955,44.502689],"type":"Point"}
}