{
  "type": "Feature",
  "properties": {
    "iso:country":"IT",
    "sg:address":"47900 Rimini",
    "sg:city":"Rimini",
    "sg:orig_category":"Hobbistica",
    "sg:phone":"+39 0541 382080",
    "sg:postcode":"47900",
    "sg:province":"Rimini",
    "wof:name":"Planetario S.r.l.",
    "wof:placetype":"venue"
},
  "geometry": {"coordinates":[12.591519,44.042473],"type":"Point"}
}