{
  "type": "Feature",
  "properties": {
    "iso:country":"IT",
    "sg:address":"61030 Calcinelli",
    "sg:city":"Calcinelli",
    "sg:orig_category":"Servizi E Lavori Industria Della Gomma. Servizi E Lavori Industria Delle Materie Plastiche. Forniture Per Edilizia E Lavori Pubblici",
    "sg:phone":"+39 0721 895035",
    "sg:postcode":"61030",
    "sg:province":"Pesaro E Urbino",
    "wof:name":"Martini Pierotti Bruna",
    "wof:placetype":"venue"
},
  "geometry": {"coordinates":[12.924518,43.759594],"type":"Point"}
}