{
  "type": "Feature",
  "properties": {
    "addr:full":"06083 Bastia Bastia Perugia 06083",
    "addr:postcode":"06083;06083",
    "iso:country":"IT",
    "sg:address":"06083 Bastia",
    "sg:city":"Bastia",
    "sg:orig_category":"Servizi E Lavori Per Edilizia E Lavori Pubblici. Consulenze Tecniche, Amministrative E Perizie",
    "sg:phone":"+39 075 800 5171",
    "sg:postcode":"06083",
    "sg:province":"Perugia",
    "wof:name":"Bastia Immobiliare Arch\u00c8 Servizi Immobiliari",
    "wof:placetype":"venue"
},
  "geometry": {"coordinates":[12.550882,43.067913],"type":"Point"}
}