{
  "type": "Feature",
  "properties": {
    "iso:country":"IT",
    "sg:address":"46030 Virgilio",
    "sg:city":"Virgilio",
    "sg:orig_category":"Forniture Per Attivita' Industriali",
    "sg:phone":"+39 0376 280492",
    "sg:postcode":"46030",
    "sg:province":"Mantova",
    "wof:name":"Chimicar",
    "wof:placetype":"venue"
},
  "geometry": {"coordinates":[10.7936658859,45.1543121338],"type":"Point"}
}