{
  "type": "Feature",
  "properties": {
    "iso:country":"IT",
    "sg:address":"20121 Milano",
    "sg:city":"Milano",
    "sg:orig_category":"Orologi Di Controllo E Sistemi Di Rilevazione Presenze",
    "sg:phone":"+39 02 659 9562",
    "sg:postcode":"20121",
    "sg:province":"Milano",
    "wof:name":"Villa L. & Figlio Srl",
    "wof:placetype":"venue"
},
  "geometry": {"coordinates":[9.186412,45.475723],"type":"Point"}
}