{
  "type": "Feature",
  "properties": {
    "addr:full":"40068 San Lazzaro Di Savena San Lazzaro Bologna 40068",
    "addr:housenumber":"40068",
    "addr:postcode":"40068",
    "addr:street":"San;San;Bologna",
    "iso:country":"IT",
    "sg:address":"40068 San Lazzaro Di Savena",
    "sg:city":"San Lazzaro",
    "sg:orig_category":"Abbigliamento Intimo, Calze E Costumi Da Bagno. Sport - Articoli E Forniture. Shopping",
    "sg:phone":"+39 051 467447",
    "sg:postcode":"40068",
    "sg:province":"Bologna",
    "wof:name":"Mi.to S.r.l.",
    "wof:placetype":"venue"
},
  "geometry": {"coordinates":[11.416623,44.465328],"type":"Point"}
}