{
  "type": "Feature",
  "properties": {
    "iso:country":"IT",
    "sg:address":"29010 Alseno",
    "sg:city":"Alseno",
    "sg:orig_category":"Prodotti E Manufatti In Gomma. Servizi E Lavori Industria Della Gomma. Ricambi E Componenti Dei Mezzi Di Trasporto",
    "sg:phone":"+39 0523 945026",
    "sg:postcode":"29010",
    "sg:province":"Piacenza",
    "wof:name":"Alseno Gomme Di Baldini E Casarola",
    "wof:placetype":"venue"
},
  "geometry": {"coordinates":[9.9065914154,44.9202728271],"type":"Point"}
}