{
  "type": "Feature",
  "properties": {
    "addr:full":"20010 Casorezzo Casorezzo Milano 20010",
    "addr:postcode":"20010;20010",
    "iso:country":"IT",
    "sg:address":"20010 Casorezzo",
    "sg:city":"Casorezzo",
    "sg:orig_category":"Climatizzazione E Condizionamento, Apparecchiature E Servizi. Elettrodomestici",
    "sg:phone":"+39 02 901 0169",
    "sg:postcode":"20010",
    "sg:province":"Milano",
    "wof:name":"Coram Snc Di Ramorini Renzo & C.",
    "wof:placetype":"venue"
},
  "geometry": {"coordinates":[8.90383,45.521854],"type":"Point"}
}