{
  "type": "Feature",
  "properties": {
    "addr:full":"154, Corso Milano 27029 Vigevano Vigevano Pavia 27029",
    "addr:postcode":"27029;27029",
    "addr:street":"Corso Milano",
    "iso:country":"IT",
    "sg:address":"154, Corso Milano 27029 Vigevano",
    "sg:city":"Vigevano",
    "sg:classifiers":[
        {
            "category":"Personal",
            "subcategory":"Shoe Repair & Shine",
            "type":"Services"
        }
    ],
    "sg:phone":"+39 0381 346491",
    "sg:postcode":"27029",
    "sg:province":"Pavia",
    "sg:tags":[
        "leather"
    ],
    "wof:name":"Boccia Aldo",
    "wof:placetype":"venue"
},
  "geometry": {"coordinates":[8.880337,45.3312],"type":"Point"}
}