{
  "type": "Feature",
  "properties": {
    "iso:country":"IT",
    "sg:address":"Corso Cavour 24; Bari; 70121",
    "sg:city":"Bari",
    "sg:classifiers":[
        {
            "category":"Banks & Credit Unions",
            "subcategory":"Bank",
            "type":"Services"
        }
    ],
    "sg:phone":"+39 080 524 4008",
    "sg:postcode":"70121",
    "sg:province":"Bari",
    "wof:name":"Banca Popolare Di Puglia, E Basilicata Scarl",
    "wof:placetype":"venue"
},
  "geometry": {"coordinates":[16.87266,41.122971],"type":"Point"}
}