{
  "type": "Feature",
  "properties": {
    "addr:full":"88, Via Delle Fornaci 60044 Fabriano Fabriano Ancona 60044",
    "addr:postcode":"60044;60044",
    "addr:street":"Via Delle Fornaci",
    "iso:country":"IT",
    "sg:address":"88, Via Delle Fornaci 60044 Fabriano",
    "sg:city":"Fabriano",
    "sg:classifiers":[
        {
            "category":"Shopping",
            "subcategory":"Clothing, Apparel, & Fashions",
            "type":"Retail Goods"
        }
    ],
    "sg:phone":"+39 0732 627097",
    "sg:postcode":"60044",
    "sg:province":"Ancona",
    "sg:tags":[
        "clothes"
    ],
    "wof:name":"Euroconf S.r.l.",
    "wof:placetype":"venue"
},
  "geometry": {"coordinates":[12.903221,43.345161],"type":"Point"}
}