{
  "type": "Feature",
  "properties": {
    "addr:full":"31, Viale Del Progresso 61029 Urbino Urbino Pesaro E Urbino 61029",
    "addr:housenumber":"31",
    "addr:postcode":"61029;61029",
    "addr:street":"Viale Del Progresso",
    "iso:country":"IT",
    "sg:address":"31, Viale Del Progresso 61029 Urbino",
    "sg:city":"Urbino",
    "sg:classifiers":[
        {
            "category":"Home & Garden",
            "subcategory":"Home Furnishings",
            "type":"Retail Goods"
        }
    ],
    "sg:phone":"+39 39072259238",
    "sg:postcode":"61029",
    "sg:province":"Pesaro E Urbino",
    "sg:tags":[
        "household"
    ],
    "wof:name":"Colocci Piergiogio & Clemente S.n.c.",
    "wof:placetype":"venue"
},
  "geometry": {"coordinates":[12.630026,43.78384],"type":"Point"}
}