{
  "type": "Feature",
  "properties": {
    "iso:country":"IT",
    "sg:address":"24022 Alzano Lombardo",
    "sg:city":"Alzano Lombardo",
    "sg:orig_category":"Agenzie Immobiliari",
    "sg:phone":"+39 035 516552",
    "sg:postcode":"24022",
    "sg:province":"Bergamo",
    "sg:website":"http://www.pentagonoitaliaspa.it",
    "wof:name":"Pentagono Italia Spa",
    "wof:placetype":"venue"
},
  "geometry": {"coordinates":[9.735229,45.737907],"type":"Point"}
}