{
  "type": "Feature",
  "properties": {
    "iso:country":"IT",
    "sg:address":"20131 Milano",
    "sg:city":"Milano",
    "sg:orig_category":"Apparecchiature Elettroniche",
    "sg:phone":"+39 02 261 9193",
    "sg:postcode":"20131",
    "sg:province":"Milano",
    "wof:name":"A.e.s. Sutera",
    "wof:placetype":"venue"
},
  "geometry": {"coordinates":[9.220078,45.487068],"type":"Point"}
}