{
  "type": "Feature",
  "properties": {
    "iso:country":"IT",
    "sg:address":"Via Pucccini 101 59013 Montemurlo",
    "sg:city":"Montemurlo",
    "sg:classifiers":[
        {
            "category":"Shopping",
            "subcategory":"Crafts & Fabrics",
            "type":"Retail Goods"
        }
    ],
    "sg:phone":"+39 0574 682962",
    "sg:postcode":"59013",
    "sg:province":"Prato",
    "sg:tags":[
        "clothing",
        "ladies'",
        "wear",
        "menswear",
        "boys'"
    ],
    "wof:name":"Lanificio Idealtex S.r.l.",
    "wof:placetype":"venue"
},
  "geometry": {"coordinates":[11.023557663,43.9066619873],"type":"Point"}
}