{
  "type": "Feature",
  "properties": {
    "iso:country":"IT",
    "sg:address":"20098 San Giuliano Milanese",
    "sg:city":"San Giuliano Milanese",
    "sg:orig_category":"Macchine Utensili E Impianti",
    "sg:phone":"+39 02 9828 2457",
    "sg:postcode":"20098",
    "sg:province":"Milano",
    "wof:name":"Progalvano Srl",
    "wof:placetype":"venue"
},
  "geometry": {"coordinates":[9.252668,45.401699],"type":"Point"}
}