{
  "type": "Feature",
  "properties": {
    "addr:full":"24, V. Montanaro 10154 Torino Torino Torino 10154",
    "addr:housenumber":"24",
    "addr:postcode":"10154;10154",
    "addr:street":"V. Montanaro",
    "iso:country":"IT",
    "sg:address":"24, V. Montanaro 10154 Torino",
    "sg:city":"Torino",
    "sg:classifiers":[
        {
            "category":"Shopping",
            "subcategory":"Computers & Home Electronics",
            "type":"Retail Goods"
        }
    ],
    "sg:phone":"+39 011 248 5166",
    "sg:postcode":"10154",
    "sg:province":"Torino",
    "sg:tags":[
        "electronic",
        "electrical",
        "equipment"
    ],
    "sg:website":"http://www.paginegialle.it/tesrl-01",
    "wof:name":"T.e. Tecnologie Per L'energia",
    "wof:placetype":"venue"
},
  "geometry": {"coordinates":[7.694506,45.091576],"type":"Point"}
}