{
  "type": "Feature",
  "properties": {
    "iso:country":"IT",
    "sg:address":"Via Volta 5 21040 Oggiona Con Santo Stefano",
    "sg:city":"Oggiona",
    "sg:classifiers":[
        {
            "category":"Manufacturing",
            "subcategory":"Tools & Machinery",
            "type":"Manufacturing & Wholesale Goods"
        }
    ],
    "sg:phone":"+39 0331 217472",
    "sg:postcode":"21040",
    "sg:province":"Varese",
    "sg:tags":[
        "industrial",
        "handheld"
    ],
    "wof:name":"Omma Srl",
    "wof:placetype":"venue"
},
  "geometry": {"coordinates":[8.816747,45.703201],"type":"Point"}
}