{
  "type": "Feature",
  "properties": {
    "iso:country":"IT",
    "sg:address":"06132 Perugia",
    "sg:city":"Perugia",
    "sg:orig_category":"Prodotti Finiti Stampati. Forniture Per Uffici. Regalistica Aziendale",
    "sg:phone":"+39 075 527 1810",
    "sg:postcode":"06132",
    "sg:province":"Perugia",
    "wof:name":"Cartotecnica Perugia Srl",
    "wof:placetype":"venue"
},
  "geometry": {"coordinates":[12.3470458984,43.075050354],"type":"Point"}
}