{
  "type": "Feature",
  "properties": {
    "addr:full":"Regione Sa Stoia 09016 Iglesias Iglesias Carbonia-Iglesias 09016",
    "addr:postcode":"09016;09016",
    "iso:country":"IT",
    "sg:address":"Regione Sa Stoia 09016 Iglesias",
    "sg:city":"Iglesias",
    "sg:classifiers":[
        {
            "category":"Manufacturing",
            "subcategory":"Rubber & Plastics",
            "type":"Manufacturing & Wholesale Goods"
        }
    ],
    "sg:phone":"+39 0781 260057",
    "sg:postcode":"09016",
    "sg:province":"Carbonia-Iglesias",
    "wof:name":"Cardnet Spa",
    "wof:placetype":"venue"
},
  "geometry": {"coordinates":[8.572101593,39.2534675598],"type":"Point"}
}