{
  "type": "Feature",
  "properties": {
    "addr:full":"40122 Bologna Bologna Bologna 40122",
    "addr:postcode":"40122;40122",
    "iso:country":"IT",
    "sg:address":"40122 Bologna",
    "sg:city":"Bologna",
    "sg:orig_category":"Tempo Libero - Articoli E Forniture. Regalistica Aziendale",
    "sg:phone":"+39 051 649 0872",
    "sg:postcode":"40122",
    "sg:province":"Bologna",
    "wof:name":"Evangelisti Giancarla",
    "wof:placetype":"venue"
},
  "geometry": {"coordinates":[11.331529,44.498913],"type":"Point"}
}