{
  "type": "Feature",
  "properties": {
    "iso:country":"IT",
    "sg:address":"89831 Soriano Calabro",
    "sg:city":"Soriano Calabro",
    "sg:orig_category":"Arredamenti - Produzione E Ingrosso",
    "sg:phone":"+39 0963 351766",
    "sg:postcode":"89831",
    "sg:province":"Vibo Valentia",
    "wof:name":"Manila Di Raffaele Francesco",
    "wof:placetype":"venue"
},
  "geometry": {"coordinates":[16.229572,38.597618],"type":"Point"}
}