{
  "type": "Feature",
  "properties": {
    "iso:country":"IT",
    "sg:address":"54033 Carrara",
    "sg:city":"Carrara",
    "sg:orig_category":"Antifurto",
    "sg:phone":"+39 0585 631833",
    "sg:postcode":"54033",
    "sg:province":"Massa-Carrara",
    "wof:name":"Alarm Service",
    "wof:placetype":"venue"
},
  "geometry": {"coordinates":[10.037396,44.039963],"type":"Point"}
}