{
  "type": "Feature",
  "properties": {
    "iso:country":"IT",
    "sg:address":"Via Pantanelli, 3/2 61025 Montelabbate",
    "sg:city":"Montelabbate",
    "sg:classifiers":[
        {
            "category":"Home & Garden",
            "subcategory":"Furniture",
            "type":"Retail Goods"
        }
    ],
    "sg:phone":"+39 0721 491353",
    "sg:postcode":"61025",
    "sg:province":"Pesaro E Urbino",
    "sg:tags":[
        "bathroom"
    ],
    "wof:name":"Dafa Srl",
    "wof:placetype":"venue"
},
  "geometry": {"coordinates":[12.786047,43.857635],"type":"Point"}
}