{
  "type": "Feature",
  "properties": {
    "iso:country":"IT",
    "sg:address":"24033 Calusco D'adda",
    "sg:classifiers":[
        {
            "category":"Wholesale",
            "subcategory":"Chemicals & Plastics",
            "type":"Manufacturing & Wholesale Goods"
        }
    ],
    "sg:phone":"+39 035 436 0026",
    "sg:postcode":"24033",
    "sg:province":"Bergamo",
    "sg:tags":[
        "article",
        "product",
        "plastics"
    ],
    "wof:name":"Giacchetta Snc Di Giacchetta Angelo & C.",
    "wof:placetype":"venue"
},
  "geometry": {"coordinates":[9.4736328125,45.6869544983],"type":"Point"}
}