{
  "type": "Feature",
  "properties": {
    "addr:full":"10148 Torino Torino Torino 10148",
    "addr:postcode":"10148;10148",
    "iso:country":"IT",
    "sg:address":"10148 Torino",
    "sg:city":"Torino",
    "sg:classifiers":[
        {
            "category":"Building & Trades",
            "subcategory":"Construction",
            "type":"Services"
        }
    ],
    "sg:phone":"+39 011 221 7550",
    "sg:postcode":"10148",
    "sg:province":"Torino",
    "sg:tags":[
        "industry",
        "work",
        "plastic"
    ],
    "wof:name":"Savio Plastica Srl",
    "wof:placetype":"venue"
},
  "geometry": {"coordinates":[7.6574254036,45.1092300415],"type":"Point"}
}