{
  "type": "Feature",
  "properties": {
    "addr:full":"25050 Rodengo Saiano Brescia 25050",
    "addr:postcode":"25050;25050",
    "iso:country":"IT",
    "sg:address":"25050 Rodengo Saiano",
    "sg:orig_category":"Ossidazione Anodica",
    "sg:phone":"+39 030 610910",
    "sg:postcode":"25050",
    "sg:province":"Brescia",
    "wof:name":"Ossidal Srl",
    "wof:placetype":"venue"
},
  "geometry": {"coordinates":[10.122003,45.580257],"type":"Point"}
}