{
  "type": "Feature",
  "properties": {
    "iso:country":"IT",
    "sg:address":"80046 San Giorgio A Cremano",
    "sg:city":"San Giorgio a Cremano",
    "sg:classifiers":[
        {
            "category":"Health Services",
            "subcategory":"Nursing And Care Facility",
            "type":"Services"
        }
    ],
    "sg:phone":"+39 081 489907",
    "sg:postcode":"80046",
    "sg:province":"Napoli",
    "sg:tags":[
        "case",
        "cura",
        "private",
        "di"
    ],
    "sg:website":"http://www.clinica-grimaldi.it",
    "wof:name":"So.ges Srl",
    "wof:placetype":"venue"
},
  "geometry": {"coordinates":[14.342153,40.82983],"type":"Point"}
}