{
  "type": "Feature",
  "properties": {
    "iso:country":"IT",
    "sg:address":"Via F. Cervi 24; Cerese; 46030",
    "sg:city":"Cerese",
    "sg:classifiers":[
        {
            "category":"Banks & Credit Unions",
            "subcategory":"Bank",
            "type":"Services"
        }
    ],
    "sg:phone":"+39 0376 280100",
    "sg:postcode":"46030",
    "sg:province":"Mantova",
    "wof:name":"Cassa Risparmio Carpi Spa",
    "wof:placetype":"venue"
},
  "geometry": {"coordinates":[10.791236,45.117588],"type":"Point"}
}