{
  "type": "Feature",
  "properties": {
    "iso:country":"IT",
    "sg:address":"65128 Pescara",
    "sg:city":"Pescara",
    "sg:orig_category":"Ricerca, Selezione E Formazione Del Personale. Pubblica Amministrazione",
    "sg:phone":"+39 085 45391",
    "sg:postcode":"65128",
    "sg:province":"Pescara",
    "wof:name":"Ufficio Provinciale E Regionale Del Lavoro E Della M.o.",
    "wof:placetype":"venue"
},
  "geometry": {"coordinates":[14.02318,42.315868],"type":"Point"}
}