{
  "type": "Feature",
  "properties": {
    "addr:full":"73, V. Ghiarola Vecchia 41042 Fiorano Modenese Fiorano Modenese Modena 41042",
    "addr:housenumber":"73",
    "addr:postcode":"41042;41042",
    "addr:street":"V. Ghiarola Vecchia",
    "iso:country":"IT",
    "sg:address":"73, V. Ghiarola Vecchia 41042 Fiorano Modenese",
    "sg:city":"Fiorano Modenese",
    "sg:classifiers":[
        {
            "category":"Professional",
            "subcategory":"Engineering",
            "type":"Services"
        }
    ],
    "sg:phone":"+39 0536 836111",
    "sg:postcode":"41042",
    "sg:province":"Modena",
    "sg:tags":[
        "machine",
        "-",
        "mechanical"
    ],
    "sg:website":"http://www.system-group.it:ws_end: :mark:ws:http://www.paginegialle.it/systemspa",
    "wof:name":"System Spa",
    "wof:placetype":"venue"
},
  "geometry": {"coordinates":[10.821133,44.550541],"type":"Point"}
}