{
  "type": "Feature",
  "properties": {
    "iso:country":"IT",
    "sg:address":"20081 Abbiategrasso",
    "sg:city":"Abbiategrasso",
    "sg:orig_category":"Prodotti Alimentari. Shopping",
    "sg:phone":"+39 02 946 6902",
    "sg:postcode":"20081",
    "sg:province":"Milano",
    "wof:name":"Radice Anna",
    "wof:placetype":"venue"
},
  "geometry": {"coordinates":[8.8768377304,45.3278045654],"type":"Point"}
}