{
  "type": "Feature",
  "properties": {
    "iso:country":"IT",
    "sg:address":"50136 Firenze",
    "sg:city":"Firenze",
    "sg:orig_category":"Abbigliamento Uomo - Vendita Al Dettaglio",
    "sg:phone":"+39 055 674106",
    "sg:postcode":"50136",
    "sg:province":"Firenze",
    "wof:name":"Marco Borgioli",
    "wof:placetype":"venue"
},
  "geometry": {"coordinates":[11.27812,43.772186],"type":"Point"}
}