{
  "type": "Feature",
  "properties": {
    "addr:full":"20122 Milano Milano Milano 20122",
    "addr:postcode":"20122;20122",
    "iso:country":"IT",
    "sg:address":"20122 Milano",
    "sg:city":"Milano",
    "sg:orig_category":"Musica",
    "sg:phone":"+39 02 725351",
    "sg:postcode":"20122",
    "sg:province":"Milano",
    "wof:name":"Virgin Music Italy S.r.l",
    "wof:placetype":"venue"
},
  "geometry": {"coordinates":[9.1912031174,45.4604415894],"type":"Point"}
}