{
  "type": "Feature",
  "properties": {
    "addr:full":"Via Gobetti 19 21 23 50058 Signa Signa Firenze 50058",
    "addr:housenumber":"19 21 23",
    "addr:postcode":"50058;50058",
    "addr:street":"Via Gobetti",
    "iso:country":"IT",
    "sg:address":"Via Gobetti 19 21 23 50058 Signa",
    "sg:city":"Signa",
    "sg:classifiers":[
        {
            "category":"Home & Garden",
            "subcategory":"Carpets & Floor Coverings",
            "type":"Retail Goods"
        }
    ],
    "sg:phone":"+39 055 876437",
    "sg:postcode":"50058",
    "sg:province":"Firenze",
    "sg:tags":[
        "suction-scrubbing",
        "industrial",
        "single-disc",
        "machine",
        "mac",
        "cleaning",
        "wet",
        "polishing",
        "scrubbers",
        "automatic",
        "machines"
    ],
    "sg:website":"www.duplexitaly.com",
    "wof:name":"Duplex S.r.l.",
    "wof:placetype":"venue"
},
  "geometry": {"coordinates":[11.256901741,43.7687339783],"type":"Point"}
}