{
  "type": "Feature",
  "properties": {
    "iso:country":"IT",
    "sg:address":"33048 San Giovanni Al Natisone",
    "sg:city":"San Giovanni al Natisone",
    "sg:orig_category":"Macchine Utensili E Impianti",
    "sg:phone":"+39 0432 758285",
    "sg:postcode":"33048",
    "sg:province":"Udine",
    "wof:name":"Bucovaz Gianfranco",
    "wof:placetype":"venue"
},
  "geometry": {"coordinates":[13.400945,45.974854],"type":"Point"}
}