{
  "type": "Feature",
  "properties": {
    "iso:country":"IT",
    "sg:address":"39044 Egna",
    "sg:city":"Egna",
    "sg:orig_category":"Impianti, Attrezzature E Forniture Sanitarie Ed Ospedaliere",
    "sg:phone":"+39 0471 826700",
    "sg:postcode":"39044",
    "sg:province":"Bolzano/Bozen",
    "sg:website":"http://www.camina.com",
    "wof:name":"Ca.mi.na Srl",
    "wof:placetype":"venue"
},
  "geometry": {"coordinates":[11.262151,46.31823],"type":"Point"}
}