{
  "type": "Feature",
  "properties": {
    "iso:country":"IT",
    "sg:address":"95018 Riposto",
    "sg:city":"Riposto",
    "sg:orig_category":"Nautica. Automobili E Mezzi Di Trasporto",
    "sg:phone":"+39 095 937825",
    "sg:postcode":"95018",
    "sg:province":"Catania",
    "wof:name":"Tutto Per Motopesca Di Zappulla A.",
    "wof:placetype":"venue"
},
  "geometry": {"coordinates":[15.207612,37.729309],"type":"Point"}
}