{
  "type": "Feature",
  "properties": {
    "addr:full":"Via Del Mare S.n. 73054 Presicce Presicce Lecce 73054",
    "addr:postcode":"73054;73054",
    "addr:street":"Via Del Mare S.N.",
    "iso:country":"IT",
    "sg:address":"Via Del Mare S.n. 73054 Presicce",
    "sg:city":"Presicce",
    "sg:classifiers":[
        {
            "category":"Banks & Credit Unions",
            "subcategory":"Investment Brokerage",
            "type":"Services"
        }
    ],
    "sg:phone":"+39 0833 721964",
    "sg:postcode":"73054",
    "sg:province":"Lecce",
    "sg:tags":[
        "children's",
        "stocking"
    ],
    "wof:name":"Calzificio D'amico Di D'amico Andrea Sas",
    "wof:placetype":"venue"
},
  "geometry": {"coordinates":[18.305964,39.84441],"type":"Point"}
}