{
  "type": "Feature",
  "properties": {
    "addr:full":"Via Livingstone 10 41100 Modena Modena Modena 41100",
    "addr:housenumber":"10",
    "addr:postcode":"41100;41100",
    "addr:street":"Via Livingstone",
    "iso:country":"IT",
    "sg:address":"Via Livingstone 10 41100 Modena",
    "sg:city":"Modena",
    "sg:classifiers":[
        {
            "category":"Banks & Credit Unions",
            "subcategory":"Investment Brokerage",
            "type":"Services"
        }
    ],
    "sg:phone":"+39 059 822321",
    "sg:postcode":"41100",
    "sg:province":"Modena",
    "sg:tags":[
        "equipment",
        "assembly",
        "motor",
        "vehicle"
    ],
    "wof:name":"Modulcar Srl",
    "wof:placetype":"venue"
},
  "geometry": {"coordinates":[10.8851947784,44.6566314697],"type":"Point"}
}