{
  "type": "Feature",
  "properties": {
    "iso:country":"IT",
    "sg:address":"80146 Napoli",
    "sg:city":"Napoli",
    "sg:orig_category":"Forniture Per Uffici",
    "sg:phone":"+39 081 752 9768",
    "sg:postcode":"80146",
    "sg:province":"Napoli",
    "sg:website":"http://www.partenufficio.it",
    "wof:name":"Partenufficio Sas",
    "wof:placetype":"venue"
},
  "geometry": {"coordinates":[14.2954244614,40.8396644592],"type":"Point"}
}