{
  "type": "Feature",
  "properties": {
    "iso:country":"IT",
    "sg:address":"49 Corso Del Rinascimento, 00186 Roma",
    "sg:city":"Roma",
    "sg:classifiers":[
        {
            "category":"Banks & Credit Unions",
            "subcategory":"Financial Services",
            "type":"Services"
        }
    ],
    "sg:phone":"+39 39066896348",
    "sg:postcode":"00186",
    "sg:province":"Roma",
    "sg:tags":[
        "banking",
        "finance",
        "insurance"
    ],
    "wof:name":"Public Affairs Srl",
    "wof:placetype":"venue"
},
  "geometry": {"coordinates":[12.4738883972,41.8987007141],"type":"Point"}
}