{
  "type": "Feature",
  "properties": {
    "addr:full":"Via Tiberina 06053 Deruta Deruta Perugia 06053",
    "addr:postcode":"06053;06053",
    "addr:street":"Via Tiberina",
    "iso:country":"IT",
    "sg:address":"Via Tiberina 06053 Deruta",
    "sg:city":"Deruta",
    "sg:classifiers":[
        {
            "category":"Sports & Exercise",
            "subcategory":"Playing Field",
            "type":"Entertainment"
        }
    ],
    "sg:phone":"+39 075 971 1772",
    "sg:postcode":"06053",
    "sg:province":"Perugia",
    "sg:tags":[
        "game"
    ],
    "wof:name":"Cavallini",
    "wof:placetype":"venue"
},
  "geometry": {"coordinates":[12.423819,42.991371],"type":"Point"}
}