{
  "type": "Feature",
  "properties": {
    "addr:full":"62017 Porto Recanati Porto Recanati Macerata 62017",
    "addr:housenumber":"62017",
    "addr:postcode":"62017",
    "iso:country":"IT",
    "sg:address":"62017 Porto Recanati",
    "sg:city":"Porto Recanati",
    "sg:orig_category":"Prodotti Chimici Di Base",
    "sg:phone":"+39 071 759 0673",
    "sg:postcode":"62017",
    "sg:province":"Macerata",
    "wof:name":"Fratelli Rossi Snc",
    "wof:placetype":"venue"
},
  "geometry": {"coordinates":[13.660367012,43.4334716797],"type":"Point"}
}