{
  "type": "Feature",
  "properties": {
    "iso:country":"IT",
    "sg:address":"12036 Revello",
    "sg:city":"Revello",
    "sg:orig_category":"Servizi Vari Di Interesse Pubblico",
    "sg:phone":"+39 0175 259042",
    "sg:postcode":"12036",
    "sg:province":"Cuneo",
    "wof:name":"Roera Brunella",
    "wof:placetype":"venue"
},
  "geometry": {"coordinates":[7.387973,44.653477],"type":"Point"}
}