{
  "type": "Feature",
  "properties": {
    "addr:full":"44100 Ferrara Ferrara Ferrara 44100",
    "addr:postcode":"44100;44100",
    "iso:country":"IT",
    "sg:address":"44100 Ferrara",
    "sg:city":"Ferrara",
    "sg:orig_category":"Manufacturers: Prefabbricati",
    "sg:phone":"+39 0532 796101",
    "sg:postcode":"44100",
    "sg:province":"Ferrara",
    "wof:name":"Ferrara Service Srl",
    "wof:placetype":"venue"
},
  "geometry": {"coordinates":[11.603532,44.870495],"type":"Point"}
}