{
  "type": "Feature",
  "properties": {
    "iso:country":"IT",
    "sg:address":"20090 Trezzano Sul Naviglio",
    "sg:city":"Trezzano sul Naviglio",
    "sg:orig_category":"Arredo Bagno Ed Idrosanitari. Elettrodomestici",
    "sg:phone":"+39 02 445 5560",
    "sg:postcode":"20090",
    "sg:province":"Milano",
    "wof:name":"Fugas S.p.a.",
    "wof:placetype":"venue"
},
  "geometry": {"coordinates":[9.078523,45.41531],"type":"Point"}
}