{
  "type": "Feature",
  "properties": {
    "iso:country":"IT",
    "sg:address":"20052 Monza",
    "sg:city":"Monza",
    "sg:orig_category":"Apparecchiature E Sistemi Per Imballaggio E Confezionamento. Apparecchiature E Sistemi Per Magazzinaggio E Movimentazione",
    "sg:phone":"+39 039 210 0239",
    "sg:postcode":"20052",
    "sg:province":"Milano",
    "sg:website":"http://www.disis.it",
    "wof:name":"Nuova Disis Srl",
    "wof:placetype":"venue"
},
  "geometry": {"coordinates":[9.247385,45.568596],"type":"Point"}
}