{
  "type": "Feature",
  "properties": {
    "addr:full":"1, Parco Il Baricentro 70010 Casamassima Casamassima Bari 70010",
    "addr:housenumber":"1",
    "addr:postcode":"70010;70010",
    "addr:street":"Parco",
    "iso:country":"IT",
    "sg:address":"1, Parco Il Baricentro 70010 Casamassima",
    "sg:city":"Casamassima",
    "sg:classifiers":[
        {
            "category":"Shopping",
            "subcategory":"Clothing, Apparel, & Fashions",
            "type":"Retail Goods"
        }
    ],
    "sg:phone":"+39 080 697 7343",
    "sg:postcode":"70010",
    "sg:province":"Bari",
    "sg:tags":[
        "clothes"
    ],
    "wof:name":"Cln S.r.l.",
    "wof:placetype":"venue"
},
  "geometry": {"coordinates":[16.869291,41.126053],"type":"Point"}
}