{
  "type": "Feature",
  "properties": {
    "iso:country":"IT",
    "sg:address":"20048 Carate Brianza",
    "sg:city":"Carate Brianza",
    "sg:orig_category":"Petroli, Gas E Combustibili",
    "sg:phone":"+39 036 290 1733",
    "sg:postcode":"20048",
    "sg:province":"Milano",
    "wof:name":"Vergani Paolo",
    "wof:placetype":"venue"
},
  "geometry": {"coordinates":[9.2327756882,45.6751823425],"type":"Point"}
}