{
  "type": "Feature",
  "properties": {
    "iso:country":"IT",
    "sg:address":"223, Via Colombo 21055 Gorla Minore",
    "sg:city":"Gorla Minore",
    "sg:classifiers":[
        {
            "category":"Shopping",
            "subcategory":"Computers & Home Electronics",
            "type":"Retail Goods"
        }
    ],
    "sg:phone":"+39 0331 365327",
    "sg:postcode":"21055",
    "sg:province":"Varese",
    "sg:tags":[
        "electronic",
        "electrical",
        "equipment"
    ],
    "wof:name":"So.va.lux-small Electric Appliances Snc Di Sozzi Gianfranco Emanuele",
    "wof:placetype":"venue"
},
  "geometry": {"coordinates":[8.826385,45.817604],"type":"Point"}
}