{
  "type": "Feature",
  "properties": {
    "addr:full":"95, Via Castellana 30100 Venezia VE",
    "addr:postcode":"30100",
    "addr:street":"Via Castellana;Ve",
    "iso:country":"IT",
    "sg:address":"95, Via Castellana 30100 Venezia",
    "sg:classifiers":[
        {
            "category":"Farming",
            "subcategory":"Livestock Farm",
            "type":"Manufacturing & Wholesale Goods"
        }
    ],
    "sg:phone":"+39 39041988022",
    "sg:province":"VE",
    "sg:tags":[
        "agriculture"
    ],
    "wof:name":"Sgaravatti & C. Sementi (s.p.a.)",
    "wof:placetype":"venue"
},
  "geometry": {"coordinates":[12.214069,45.510914],"type":"Point"}
}