{
  "type": "Feature",
  "properties": {
    "iso:country":"IT",
    "sg:address":"42019 Scandiano",
    "sg:orig_category":"Arredamento Parrucchieri Ed Istituti Di Bellezza",
    "sg:phone":"+39 0522 983139",
    "sg:postcode":"42019",
    "sg:province":"Reggio Nell'Emilia",
    "wof:name":"Creasan Srl",
    "wof:placetype":"venue"
},
  "geometry": {"coordinates":[10.699239,44.600334],"type":"Point"}
}