{
  "type": "Feature",
  "properties": {
    "iso:country":"IT",
    "sg:address":"25036 Palazzolo Sull'oglio",
    "sg:orig_category":"Animali Domestici - Vendita",
    "sg:phone":"+39 030 740 3008",
    "sg:postcode":"25036",
    "sg:province":"Brescia",
    "wof:name":"Shambhala Di Torri Luca & C. Snc",
    "wof:placetype":"venue"
},
  "geometry": {"coordinates":[9.889382,45.595299],"type":"Point"}
}