{
  "type": "Feature",
  "properties": {
    "addr:full":"10090 Rivalba Rivalba Torino 10090",
    "addr:postcode":"10090;10090",
    "iso:country":"IT",
    "sg:address":"10090 Rivalba",
    "sg:city":"Rivalba",
    "sg:orig_category":"Refrattari",
    "sg:phone":"+39 011 960 4513",
    "sg:postcode":"10090",
    "sg:province":"Torino",
    "wof:name":"Fir Di Cacciotto S.",
    "wof:placetype":"venue"
},
  "geometry": {"coordinates":[7.860631,45.120804],"type":"Point"}
}