{
  "type": "Feature",
  "properties": {
    "iso:country":"IT",
    "sg:address":"20090 Assago",
    "sg:city":"Assago",
    "sg:orig_category":"Apparecchi, Attrezzature E Forniture Per Centri Estetici",
    "sg:phone":"+39 02 4570 6335",
    "sg:postcode":"20090",
    "sg:province":"Milano",
    "wof:name":"2g Beauty Communications Srl",
    "wof:placetype":"venue"
},
  "geometry": {"coordinates":[9.127783,45.401855],"type":"Point"}
}