{
  "type": "Feature",
  "properties": {
    "iso:country":"IT",
    "sg:address":"37, Via Danubio 50019 Sesto Fiorentino",
    "sg:city":"Sesto Fiorentino",
    "sg:classifiers":[
        {
            "category":"Shopping",
            "subcategory":"Crafts & Fabrics",
            "type":"Retail Goods"
        }
    ],
    "sg:phone":"+39 39055374632",
    "sg:postcode":"50019",
    "sg:province":"Firenze",
    "wof:name":"Va.ma Commercio Tessuti S.r.l.",
    "wof:placetype":"venue"
},
  "geometry": {"coordinates":[11.1712884903,43.8116874695],"type":"Point"}
}