{
  "type": "Feature",
  "properties": {
    "iso:country":"IT",
    "sg:address":"48, Via Ponte Magno 60034 Cupramontana",
    "sg:city":"Cupramontana",
    "sg:classifiers":[
        {
            "category":"Professional",
            "subcategory":"Engineering",
            "type":"Services"
        }
    ],
    "sg:phone":"+39 0731 703707",
    "sg:postcode":"60034",
    "sg:province":"Ancona",
    "sg:tags":[
        "machine",
        "-",
        "mechanical"
    ],
    "wof:name":"Tecnoattrezzature Di Rossi E Montesi (s.n.c.)",
    "wof:placetype":"venue"
},
  "geometry": {"coordinates":[13.17451,43.477394],"type":"Point"}
}