{
  "type": "Feature",
  "properties": {
    "addr:full":"56123 Pisa Pisa Pisa 56123",
    "addr:postcode":"56123;56123",
    "iso:country":"IT",
    "sg:address":"56123 Pisa",
    "sg:city":"Pisa",
    "sg:orig_category":"Servizi E Lavori Per Ecologia E Smaltimento Rifiuti. Acqua, Luce, Gas E Societa' Di Esercizio Pubblico",
    "sg:phone":"+39 050 843111",
    "sg:postcode":"56123",
    "sg:province":"Pisa",
    "sg:website":"http://www.paginegialle.it/geapisa.it",
    "wof:name":"Gea Azienda Servizi Per L'ambiente",
    "wof:placetype":"venue"
},
  "geometry": {"coordinates":[10.404008,43.723808],"type":"Point"}
}