{
  "type": "Feature",
  "properties": {
    "iso:country":"IT",
    "sg:address":"Piazza F. Meardi 9; Casei Gerola",
    "sg:classifiers":[
        {
            "category":"Banks & Credit Unions",
            "subcategory":"Bank",
            "type":"Services"
        }
    ],
    "sg:phone":"+39 0383 381042",
    "wof:name":"Banca Cassa Di Risparmio, Di Tortona Spa",
    "wof:placetype":"venue"
},
  "geometry": {"coordinates":[8.927066,45.005699],"type":"Point"}
}