{
  "type": "Feature",
  "properties": {
    "iso:country":"IT",
    "sg:address":"Via E. Fermi 5 20090 Buccinasco",
    "sg:city":"Buccinasco",
    "sg:classifiers":[
        {
            "category":"Marine",
            "type":"Transportation"
        }
    ],
    "sg:phone":"+39 02 4570 0206",
    "sg:postcode":"20090",
    "sg:province":"Milano",
    "sg:tags":[
        "diesel",
        "generator"
    ],
    "wof:name":"Saim Spa",
    "wof:placetype":"venue"
},
  "geometry": {"coordinates":[9.127942,45.403309],"type":"Point"}
}