{
  "type": "Feature",
  "properties": {
    "iso:country":"IT",
    "sg:address":"23, Via Bovio Giovanni 21052 Busto Arsizio",
    "sg:city":"Busto Arsizio",
    "sg:classifiers":[
        {
            "category":"Shopping",
            "subcategory":"Crafts & Fabrics",
            "type":"Retail Goods"
        }
    ],
    "sg:phone":"+39 0331 351370",
    "sg:postcode":"21052",
    "sg:province":"Varese",
    "wof:name":"Flem (s.p.a.)",
    "wof:placetype":"venue"
},
  "geometry": {"coordinates":[8.8263845444,45.8176040649],"type":"Point"}
}