{
  "type": "Feature",
  "properties": {
    "iso:country":"IT",
    "sg:address":"61, Via Racconigi 12048 Sommariva Del Bosco",
    "sg:city":"Sommariva del Bosco",
    "sg:classifiers":[
        {
            "category":"Shopping",
            "type":"Retail Goods"
        }
    ],
    "sg:phone":"+39 39017255667",
    "sg:postcode":"12048",
    "sg:province":"Cuneo",
    "sg:tags":[
        "finished",
        "-",
        "metallic"
    ],
    "wof:name":"C.m.s. Di Verre S. & Galata' A. (s.n.c.)",
    "wof:placetype":"venue"
},
  "geometry": {"coordinates":[7.7722802162,44.7723274231],"type":"Point"}
}