{
  "type": "Feature",
  "properties": {
    "iso:country":"IT",
    "sg:address":"56017 San Giuliano Terme",
    "sg:city":"San Giuliano Terme",
    "sg:orig_category":"Impiantistica E Prodotti Tecnologici Per Edilizia. Macchine, Strumenti Ed Apparecchi Per Attivita' Industriali",
    "sg:postcode":"56017",
    "sg:province":"Pisa",
    "wof:name":"Eurotec Pisa (s.r.l.)",
    "wof:placetype":"venue"
},
  "geometry": {"coordinates":[10.365198,43.747925],"type":"Point"}
}