{
  "type": "Feature",
  "properties": {
    "iso:country":"IT",
    "sg:address":"20123 Milano",
    "sg:city":"Milano",
    "sg:orig_category":"Servizi Culturali E Per Lo Spettacolo. Cine-foto-ottica",
    "sg:phone":"+39 02 867935",
    "sg:postcode":"20123",
    "sg:province":"Milano",
    "wof:name":"Focus Video (s.r.l.)",
    "wof:placetype":"venue"
},
  "geometry": {"coordinates":[9.186457634,45.4629669189],"type":"Point"}
}