{
  "type": "Feature",
  "properties": {
    "iso:country":"IT",
    "sg:address":"24, Via Locarno 21040 Sumirago",
    "sg:city":"Sumirago",
    "sg:classifiers":[
        {
            "category":"Shopping",
            "type":"Retail Goods"
        }
    ],
    "sg:phone":"+39 0331 909186",
    "sg:postcode":"21040",
    "sg:province":"Varese",
    "sg:tags":[
        "finished",
        "-",
        "metallic"
    ],
    "wof:name":"Euromicromec S.r.l.",
    "wof:placetype":"venue"
},
  "geometry": {"coordinates":[8.7899618149,45.739818573],"type":"Point"}
}