{
  "type": "Feature",
  "properties": {
    "iso:country":"IT",
    "sg:address":"Via Giacomo Puccini 55016 Porcari",
    "sg:city":"Porcari",
    "sg:orig_category":"Ladies' Shoes",
    "sg:phone":"+39 0583 297169",
    "sg:postcode":"55016",
    "sg:province":"Lucca",
    "wof:name":"Elle Shoes Di Del Prete Anna & C. Snc",
    "wof:placetype":"venue"
},
  "geometry": {"coordinates":[10.604695,43.840576],"type":"Point"}
}