{
  "type": "Feature",
  "properties": {
    "addr:full":"31, Via Armando Diaz 33044 Manzano Manzano Udine 33044",
    "addr:postcode":"33044;33044",
    "addr:street":"Via Armando Diaz",
    "iso:country":"IT",
    "sg:address":"31, Via Armando Diaz 33044 Manzano",
    "sg:city":"Manzano",
    "sg:classifiers":[
        {
            "category":"Professional",
            "subcategory":"Engineering",
            "type":"Services"
        }
    ],
    "sg:phone":"+39 0432 740832",
    "sg:postcode":"33044",
    "sg:province":"Udine",
    "sg:tags":[
        "machine",
        "-",
        "mechanical"
    ],
    "wof:name":"C.a.m.a.m.",
    "wof:placetype":"venue"
},
  "geometry": {"coordinates":[13.364514,45.985744],"type":"Point"}
}