{
  "type": "Feature",
  "properties": {
    "iso:country":"IT",
    "sg:address":"24050 Grassobbio",
    "sg:city":"Grassobbio",
    "sg:orig_category":"Motori Ed Organi Di Trasmissione",
    "sg:phone":"+39 035 335011",
    "sg:postcode":"24050",
    "sg:province":"Bergamo",
    "wof:name":"Varalli",
    "wof:placetype":"venue"
},
  "geometry": {"coordinates":[9.7268362045,45.6591758728],"type":"Point"}
}