{
  "type": "Feature",
  "properties": {
    "addr:full":"46, V. Roma 24067 Sarnico Sarnico Bergamo 24067",
    "addr:housenumber":"46",
    "addr:postcode":"24067;24067",
    "addr:street":"V. Roma",
    "iso:country":"IT",
    "sg:address":"46, V. Roma 24067 Sarnico",
    "sg:city":"Sarnico",
    "sg:classifiers":[
        {
            "category":"Professional",
            "subcategory":"Engineering",
            "type":"Services"
        }
    ],
    "sg:phone":"+39 39035910328",
    "sg:postcode":"24067",
    "sg:province":"Bergamo",
    "sg:tags":[
        "machine",
        "-",
        "mechanical"
    ],
    "sg:website":"http://www.unigasket.it",
    "wof:name":"Unigasket Srl",
    "wof:placetype":"venue"
},
  "geometry": {"coordinates":[9.958923,45.667137],"type":"Point"}
}