{
  "type": "Feature",
  "properties": {
    "iso:country":"IT",
    "sg:address":"95024 Acireale",
    "sg:city":"Acireale",
    "sg:orig_category":"Alimentare E Conserviera Industria - Macchine",
    "sg:phone":"+39 095 877518",
    "sg:postcode":"95024",
    "sg:province":"Catania",
    "wof:name":"C.a.m.a. Srl",
    "wof:placetype":"venue"
},
  "geometry": {"coordinates":[15.160984,37.635765],"type":"Point"}
}