{
  "type": "Feature",
  "properties": {
    "iso:country":"IT",
    "sg:address":"Via A. De Gasperi 32 60021 Camerano",
    "sg:city":"Camerano",
    "sg:orig_category":"Ladies' Knitwear",
    "sg:phone":"+39 071 732440",
    "sg:postcode":"60021",
    "sg:province":"Ancona",
    "sg:website":"www.giorgiograti.it",
    "wof:name":"Giorgio Grati Spa",
    "wof:placetype":"venue"
},
  "geometry": {"coordinates":[13.548501,43.528854],"type":"Point"}
}