{
  "type": "Feature",
  "properties": {
    "addr:full":"20080 Carpiano Carpiano Milano 20080",
    "addr:postcode":"20080;20080",
    "iso:country":"IT",
    "sg:address":"20080 Carpiano",
    "sg:city":"Carpiano",
    "sg:orig_category":"Moquettes",
    "sg:phone":"+39 02 981 5390",
    "sg:postcode":"20080",
    "sg:province":"Milano",
    "wof:name":"Galli Fratelli Snc",
    "wof:placetype":"venue"
},
  "geometry": {"coordinates":[9.2447557449,45.3937530518],"type":"Point"}
}