{
  "type": "Feature",
  "properties": {
    "iso:country":"IT",
    "sg:address":"49, Piazza Del Gesu' 00186 Roma",
    "sg:city":"Roma",
    "sg:classifiers":[
        {
            "category":"Professional",
            "subcategory":"Business Services",
            "type":"Services"
        }
    ],
    "sg:phone":"+39 390 667 671",
    "sg:postcode":"00186",
    "sg:province":"Roma",
    "sg:tags":[
        "advice"
    ],
    "wof:name":"A.b.i.",
    "wof:placetype":"venue"
},
  "geometry": {"coordinates":[12.478869,41.895924],"type":"Point"}
}