{
  "type": "Feature",
  "properties": {
    "iso:country":"IT",
    "sg:address":"43100 Parma",
    "sg:city":"Fontanini",
    "sg:orig_category":"Autofficine, Gommisti E Autolavaggi - Attrezzature",
    "sg:phone":"+39 0521 648713",
    "sg:postcode":"43100",
    "sg:province":"Parma",
    "wof:name":"Sincro Snc",
    "wof:placetype":"venue"
},
  "geometry": {"coordinates":[10.307196,44.758816],"type":"Point"}
}