{
  "type": "Feature",
  "properties": {
    "addr:full":"29/a, Viale Modugno Giorgio 16156 Genova Genova Genova 16156",
    "addr:housenumber":"29 / a",
    "addr:postcode":"16156;16156",
    "addr:street":"Viale Modugno Giorgio",
    "iso:country":"IT",
    "sg:address":"29/a, Viale Modugno Giorgio 16156 Genova",
    "sg:city":"Genova",
    "sg:classifiers":[
        {
            "category":"Manufacturing",
            "subcategory":"Paper Products",
            "type":"Manufacturing & Wholesale Goods"
        }
    ],
    "sg:phone":"+39 010 697 3598",
    "sg:postcode":"16156",
    "sg:province":"Genova",
    "sg:tags":[
        "cardboard"
    ],
    "wof:name":"Cartiera Di Bosco Marengo S.p.a.",
    "wof:placetype":"venue"
},
  "geometry": {"coordinates":[8.9339885712,44.4070625305],"type":"Point"}
}