{
  "type": "Feature",
  "properties": {
    "addr:full":"88, Via Foce 80040 Striano Striano Napoli 80040",
    "addr:postcode":"80040;80040",
    "addr:street":"Via Foce",
    "iso:country":"IT",
    "sg:address":"88, Via Foce 80040 Striano",
    "sg:city":"Striano",
    "sg:classifiers":[
        {
            "category":"Food & Beverages",
            "subcategory":"Groceries & Convenience Stores",
            "type":"Retail Goods"
        }
    ],
    "sg:phone":"+39 081 827 7883",
    "sg:postcode":"80040",
    "sg:province":"Napoli",
    "sg:tags":[
        "product",
        "related"
    ],
    "wof:name":"Strianese Conserve Srl",
    "wof:placetype":"venue"
},
  "geometry": {"coordinates":[14.5806150436,40.8182830811],"type":"Point"}
}