{
  "type": "Feature",
  "properties": {
    "addr:full":"Feldthurnerstra\u00dfe 1b 39042 Brixen Bolzano/Bozen 39042",
    "addr:housenumber":"1b",
    "addr:postcode":"39042;39042",
    "addr:street":"Feldthurnerstrasse",
    "iso:country":"IT",
    "sg:address":"Feldthurnerstra\u00dfe 1b 39042 Brixen",
    "sg:classifiers":[
        {
            "category":"Manufacturing",
            "subcategory":"Tools & Machinery",
            "type":"Manufacturing & Wholesale Goods"
        }
    ],
    "sg:phone":"+39 0472 833944",
    "sg:postcode":"39042",
    "sg:province":"Bolzano/Bozen",
    "sg:tags":[
        "workstation",
        "assembly"
    ],
    "sg:website":"www.nitz.it",
    "wof:name":"Nitz Electronics Gmbh",
    "wof:placetype":"venue"
},
  "geometry": {"coordinates":[11.358005,46.496716],"type":"Point"}
}