{
  "type": "Feature",
  "properties": {
    "iso:country":"IT",
    "sg:address":"00177 Roma",
    "sg:city":"Roma",
    "sg:orig_category":"Macchine E Forniture Per Arredamento E Industria Del Legno",
    "sg:phone":"+39 06 241 9319",
    "sg:postcode":"00177",
    "sg:province":"Roma",
    "wof:name":"Sovema (s.r.l.)",
    "wof:placetype":"venue"
},
  "geometry": {"coordinates":[12.546316,41.878586],"type":"Point"}
}