{
  "type": "Feature",
  "properties": {
    "iso:country":"IT",
    "sg:address":"92, Via Passo Della Volpe 54033 Carrara",
    "sg:city":"Carrara",
    "sg:classifiers":[
        {
            "category":"Wholesale",
            "subcategory":"Drugs",
            "type":"Manufacturing & Wholesale Goods"
        }
    ],
    "sg:phone":"+39 39058555804",
    "sg:postcode":"54033",
    "sg:province":"Massa-Carrara",
    "sg:tags":[
        "chemical",
        "pharmaceutical"
    ],
    "wof:name":"Fratelli Menconi Snc Di Menconi Giuliano E C.",
    "wof:placetype":"venue"
},
  "geometry": {"coordinates":[10.072091,44.042984],"type":"Point"}
}