{
  "type": "Feature",
  "properties": {
    "addr:full":"Via Magenta 79 21052 Busto Arsizio Busto Arsizio Varese 21052",
    "addr:housenumber":"79",
    "addr:postcode":"21052;21052",
    "addr:street":"Via Magenta",
    "iso:country":"IT",
    "sg:address":"Via Magenta 79 21052 Busto Arsizio",
    "sg:city":"Busto Arsizio",
    "sg:classifiers":[
        {
            "category":"Train Station",
            "subcategory":"Rail",
            "type":"Transportation"
        }
    ],
    "sg:phone":"+39 0331 397111",
    "sg:postcode":"21052",
    "sg:province":"Varese",
    "sg:tags":[
        "sheet",
        "bed"
    ],
    "wof:name":"Manifattura Antonio Randi Spa",
    "wof:placetype":"venue"
},
  "geometry": {"coordinates":[8.847075,45.596714],"type":"Point"}
}