{
  "type": "Feature",
  "properties": {
    "addr:full":"1/h, Localita' Vigne 10070 Grosso Grosso Torino 10070",
    "addr:housenumber":"1 / h",
    "addr:postcode":"10070;10070",
    "addr:street":"Localita ' Vigne",
    "iso:country":"IT",
    "sg:address":"1/h, Localita' Vigne 10070 Grosso",
    "sg:city":"Grosso",
    "sg:classifiers":[
        {
            "category":"Professional",
            "subcategory":"Engineering",
            "type":"Services"
        }
    ],
    "sg:phone":"+39 011 926 9766",
    "sg:postcode":"10070",
    "sg:province":"Torino",
    "sg:tags":[
        "machine",
        "-",
        "mechanical"
    ],
    "wof:name":"Tecnomeccanica G.r.w. (s.r.l.)",
    "wof:placetype":"venue"
},
  "geometry": {"coordinates":[7.686619,45.07056],"type":"Point"}
}