{
  "type": "Feature",
  "properties": {
    "iso:country":"IT",
    "sg:address":"24040 Bonate Sotto",
    "sg:city":"Bonate Sotto",
    "sg:orig_category":"Macchine, Impianti Ed Attrezzature Industria Chimica",
    "sg:phone":"+39 035 993796",
    "sg:postcode":"24040",
    "sg:province":"Bergamo",
    "wof:name":"Paganelli Battista",
    "wof:placetype":"venue"
},
  "geometry": {"coordinates":[9.562063,45.662872],"type":"Point"}
}