{
  "type": "Feature",
  "properties": {
    "addr:full":"Via Verdi 22 41018 San Cesario Sul Panaro San Cesario sul Panaro Modena 41018",
    "addr:housenumber":"22",
    "addr:postcode":"41018;cesario;panaro;41018",
    "addr:street":"Via Verdi",
    "iso:country":"IT",
    "sg:address":"Via Verdi 22 41018 San Cesario Sul Panaro",
    "sg:city":"San Cesario sul Panaro",
    "sg:classifiers":[
        {
            "category":"Military Area",
            "subcategory":"Air Force Base",
            "type":"Public Place"
        }
    ],
    "sg:phone":"+39 059 936811",
    "sg:postcode":"41018",
    "sg:province":"Modena",
    "sg:tags":[
        "transmission",
        "line",
        "overhead",
        "accessory"
    ],
    "sg:website":"www.oilsteel.it",
    "wof:name":"Oil & Steel Spa",
    "wof:placetype":"venue"
},
  "geometry": {"coordinates":[11.01827,44.530674],"type":"Point"}
}