{
  "type": "Feature",
  "properties": {
    "iso:country":"IT",
    "sg:address":"35142 Padova",
    "sg:city":"Padova",
    "sg:orig_category":"Trattamenti Termici E Superficiali Metalli, Galvanotecnica",
    "sg:phone":"+39 049 880 1542",
    "sg:postcode":"35142",
    "sg:province":"Padova",
    "wof:name":"Barbiero Mariano",
    "wof:placetype":"venue"
},
  "geometry": {"coordinates":[11.842914,45.386837],"type":"Point"}
}