{
  "type": "Feature",
  "properties": {
    "iso:country":"IT",
    "sg:address":"38038 Tesero",
    "sg:city":"Tesero",
    "sg:classifiers":[
        {
            "category":"Travel",
            "subcategory":"Hotels & Motels",
            "type":"Entertainment"
        }
    ],
    "sg:phone":"+39 0462 814615",
    "sg:postcode":"38038",
    "sg:province":"Trento",
    "sg:tags":[
        "hotels",
        "facility"
    ],
    "wof:name":"Residence Mich Di Mich Luigi",
    "wof:placetype":"venue"
},
  "geometry": {"coordinates":[11.505859,46.304344],"type":"Point"}
}