{
  "type": "Feature",
  "properties": {
    "iso:country":"IT",
    "sg:address":"25013 Carpenedolo",
    "sg:city":"Carpenedolo",
    "sg:orig_category":"Imprese Di Costruzioni Civili Ed Industriali",
    "sg:phone":"+39 030 969495",
    "sg:postcode":"25013",
    "sg:province":"Brescia",
    "wof:name":"Nolli Srl",
    "wof:placetype":"venue"
},
  "geometry": {"coordinates":[10.437586,45.357891],"type":"Point"}
}