{
  "type": "Feature",
  "properties": {
    "iso:country":"IT",
    "sg:address":"00196 Roma",
    "sg:city":"Roma",
    "sg:orig_category":"Servizi Culturali E Per Lo Spettacolo",
    "sg:phone":"+39 06 323 6619",
    "sg:postcode":"00196",
    "sg:province":"Roma",
    "wof:name":"Cinematografo Capitol",
    "wof:placetype":"venue"
},
  "geometry": {"coordinates":[12.466249,41.931099],"type":"Point"}
}