{
  "type": "Feature",
  "properties": {
    "iso:country":"IT",
    "sg:address":"35036 Montegrotto Terme",
    "sg:city":"Montegrotto Terme",
    "sg:orig_category":"Ospedali E Servizi Sanitari",
    "sg:phone":"+39 049 793498",
    "sg:postcode":"35036",
    "sg:province":"Padova",
    "wof:name":"Zamarion Borsato Angela",
    "wof:placetype":"venue"
},
  "geometry": {"coordinates":[11.789288,45.335064],"type":"Point"}
}