{
  "type": "Feature",
  "properties": {
    "iso:country":"IT",
    "sg:address":"25046 Cazzago San Martino",
    "sg:city":"Cazzago San Martino",
    "sg:orig_category":"Apparecchiature Pneumatiche Ed Idropneumatiche",
    "sg:phone":"+39 030 775 9931",
    "sg:postcode":"25046",
    "sg:province":"Brescia",
    "sg:website":"http://www.eurofit.it",
    "wof:name":"Eurofit Srl",
    "wof:placetype":"venue"
},
  "geometry": {"coordinates":[10.05662,45.57209],"type":"Point"}
}