{
  "type": "Feature",
  "properties": {
    "addr:full":"20090 Assago Assago Milano 20090",
    "addr:postcode":"20090;20090",
    "addr:street":"Assago",
    "iso:country":"IT",
    "sg:address":"20090 Assago",
    "sg:city":"Assago",
    "sg:orig_category":"Metalli E Leghe",
    "sg:phone":"+39 02 488 5111",
    "sg:postcode":"20090",
    "sg:province":"Milano",
    "wof:name":"Stanitaliana Spa",
    "wof:placetype":"venue"
},
  "geometry": {"coordinates":[9.1238555908,45.4061965942],"type":"Point"}
}