{
  "type": "Feature",
  "properties": {
    "iso:country":"IT",
    "sg:address":"Via Di Giura Domenico C.commerc. 85100 Potenza",
    "sg:city":"Potenza",
    "sg:classifiers":[
        {
            "category":"Communications",
            "subcategory":"Newspaper",
            "type":"Services"
        }
    ],
    "sg:phone":"+39 0971 441404",
    "sg:postcode":"85100",
    "sg:province":"Potenza",
    "sg:tags":[
        "advertising"
    ],
    "wof:name":"Territorio Spa",
    "wof:placetype":"venue"
},
  "geometry": {"coordinates":[15.802221,40.637241],"type":"Point"}
}