{
  "type": "Feature",
  "properties": {
    "iso:country":"IT",
    "sg:address":"50135 Firenze",
    "sg:city":"Firenze",
    "sg:orig_category":"Prodotti Finiti Stampati. Forniture Per Uffici",
    "sg:phone":"+39 055 610595",
    "sg:postcode":"50135",
    "sg:province":"Firenze",
    "wof:name":"Grafica La Nave",
    "wof:placetype":"venue"
},
  "geometry": {"coordinates":[11.2967739105,43.7719993591],"type":"Point"}
}