{
  "type": "Feature",
  "properties": {
    "addr:full":"35043 Monselice Monselice Padova 35043",
    "addr:postcode":"35043;35043",
    "iso:country":"IT",
    "sg:address":"35043 Monselice",
    "sg:city":"Monselice",
    "sg:orig_category":"Informatica - Consulenza E Servizi. Servizi Ausiliari Di Analisi, Controllo E Ricerca. Servizi Per Aziende, Manifestazioni E Supporto Agli Scambi Commerciali",
    "sg:phone":"+39 0429 787811",
    "sg:postcode":"35043",
    "sg:province":"Padova",
    "wof:name":"C.p.e. Srl",
    "wof:placetype":"venue"
},
  "geometry": {"coordinates":[11.752158,45.230679],"type":"Point"}
}