{
  "type": "Feature",
  "properties": {
    "iso:country":"IT",
    "sg:address":"22100 Como",
    "sg:city":"Como",
    "sg:orig_category":"Servizi E Lavori Per Abbigliamento E Pelletterie",
    "sg:phone":"+39 031 304390",
    "sg:postcode":"22100",
    "sg:province":"Como",
    "wof:name":"Faro Disegni Snc",
    "wof:placetype":"venue"
},
  "geometry": {"coordinates":[9.083964,45.812256],"type":"Point"}
}