{
  "type": "Feature",
  "properties": {
    "iso:country":"IT",
    "sg:address":"Via Francesco Franchi 138 25045 Castegnato",
    "sg:city":"Castegnato",
    "sg:classifiers":[
        {
            "category":"Shopping Center",
            "type":"Public Place"
        }
    ],
    "sg:phone":"+39 030 214 5511",
    "sg:postcode":"25045",
    "sg:province":"Brescia",
    "sg:tags":[
        "aluminium",
        "casting"
    ],
    "sg:website":"www.ghial.it",
    "wof:name":"Ghial Spa",
    "wof:placetype":"venue"
},
  "geometry": {"coordinates":[10.110684,45.55455],"type":"Point"}
}