{
  "type": "Feature",
  "properties": {
    "iso:country":"IT",
    "sg:address":"08025 Oliena",
    "sg:city":"Oliena",
    "sg:orig_category":"Ceramiche: Prodotti E Lavorazioni",
    "sg:phone":"+39 0784 285468",
    "sg:postcode":"08025",
    "sg:province":"Nuoro",
    "wof:name":"Commercial Zeat Srl",
    "wof:placetype":"venue"
},
  "geometry": {"coordinates":[9.404259,40.275208],"type":"Point"}
}