{
  "type": "Feature",
  "properties": {
    "iso:country":"IT",
    "sg:address":"20052 Monza",
    "sg:city":"Monza",
    "sg:orig_category":"Imballaggi - Produzione E Commercio",
    "sg:phone":"+39 039 384743",
    "sg:postcode":"20052",
    "sg:province":"Milano",
    "wof:name":"Mandelli Fratelli Snc",
    "wof:placetype":"venue"
},
  "geometry": {"coordinates":[9.237913,45.44162],"type":"Point"}
}