{
  "type": "Feature",
  "properties": {
    "iso:country":"IT",
    "sg:address":"Via Pietro Zia 13882 Cerrione",
    "sg:city":"Cerrione",
    "sg:classifiers":[
        {
            "category":"Manufacturing",
            "subcategory":"Paper Products",
            "type":"Manufacturing & Wholesale Goods"
        }
    ],
    "sg:phone":"+39 015 258 2111",
    "sg:postcode":"13882",
    "sg:province":"Biella",
    "sg:tags":[
        "cardboard"
    ],
    "wof:name":"De Martiny Bayart Spa",
    "wof:placetype":"venue"
},
  "geometry": {"coordinates":[8.0660362244,45.491027832],"type":"Point"}
}