{
  "type": "Feature",
  "properties": {
    "iso:country":"IT",
    "sg:address":"10024 Moncalieri",
    "sg:city":"Moncalieri",
    "sg:orig_category":"Affilatura Strumenti Ed Utensili",
    "sg:phone":"+39 011 682 9480",
    "sg:postcode":"10024",
    "sg:province":"Torino",
    "wof:name":"C.u.s.p. Di Mardegan Luca",
    "wof:placetype":"venue"
},
  "geometry": {"coordinates":[7.673755,45.000294],"type":"Point"}
}