{
  "type": "Feature",
  "properties": {
    "addr:full":"52, Via Dell' Industria 61100 Pesaro Pesaro Pesaro E Urbino 61100",
    "addr:postcode":"61100;61100",
    "addr:street":"Via Dell ' Industria",
    "iso:country":"IT",
    "sg:address":"52, Via Dell' Industria 61100 Pesaro",
    "sg:city":"Pesaro",
    "sg:classifiers":[
        {
            "category":"Manufacturing",
            "subcategory":"Lumber",
            "type":"Manufacturing & Wholesale Goods"
        }
    ],
    "sg:phone":"+39 0721 482181",
    "sg:postcode":"61100",
    "sg:province":"Pesaro E Urbino",
    "sg:tags":[
        "wood"
    ],
    "wof:name":"Pabe Di Pandolfi & C. Srl",
    "wof:placetype":"venue"
},
  "geometry": {"coordinates":[12.811372,43.861835],"type":"Point"}
}