{
  "type": "Feature",
  "properties": {
    "addr:full":"10090 Sciolze Sciolze Torino 10090",
    "addr:postcode":"10090;10090",
    "iso:country":"IT",
    "sg:address":"10090 Sciolze",
    "sg:city":"Sciolze",
    "sg:orig_category":"Servizi E Lavori Per Industria Alimentare E Bevande",
    "sg:phone":"+39 011 960 3715",
    "sg:postcode":"10090",
    "sg:province":"Torino",
    "wof:name":"Moncalvo Riccardo",
    "wof:placetype":"venue"
},
  "geometry": {"coordinates":[7.881574,45.094223],"type":"Point"}
}