{
  "type": "Feature",
  "properties": {
    "iso:country":"IT",
    "sg:address":"17011 Albisola Superiore",
    "sg:city":"Albisola Superiore",
    "sg:orig_category":"Forniture Per Edilizia E Lavori Pubblici. Prodotti Vari In Metallo",
    "sg:phone":"+39 019 488515",
    "sg:postcode":"17011",
    "sg:province":"Savona",
    "wof:name":"Ma.e.s. Srl",
    "wof:placetype":"venue"
},
  "geometry": {"coordinates":[8.5107126236,44.3425483704],"type":"Point"}
}