{
  "type": "Feature",
  "properties": {
    "addr:full":"10122 Torino Torino Torino 10122",
    "addr:housenumber":"10122",
    "addr:postcode":"10122",
    "iso:country":"IT",
    "sg:address":"10122 Torino",
    "sg:city":"Torino",
    "sg:orig_category":"Non-classified Establishments",
    "sg:phone":"+39 011 436 0707",
    "sg:postcode":"10122",
    "sg:province":"Torino",
    "wof:name":"Tenderini Domenico",
    "wof:placetype":"venue"
},
  "geometry": {"coordinates":[7.680242,45.0769],"type":"Point"}
}