{
  "type": "Feature",
  "properties": {
    "iso:country":"IT",
    "sg:address":"19126 La Spezia",
    "sg:orig_category":"Telecomunicazioni E Telefonia, Impianti, Apparecchi E Servizi",
    "sg:phone":"+39 0187 564562",
    "sg:province":"SP",
    "sg:website":"http://www.omicron.it",
    "wof:name":"Omicron Srl",
    "wof:placetype":"venue"
},
  "geometry": {"coordinates":[9.841598,44.111526],"type":"Point"}
}