{
  "type": "Feature",
  "properties": {
    "iso:country":"IT",
    "sg:address":"13871 Verrone",
    "sg:city":"Verrone",
    "sg:orig_category":"Feltri E Panni",
    "sg:phone":"+39 015 2556 8181",
    "sg:postcode":"13871",
    "sg:province":"Biella",
    "wof:name":"Le Feutre S.a.",
    "wof:placetype":"venue"
},
  "geometry": {"coordinates":[8.0969457626,45.5593109131],"type":"Point"}
}