{
  "type": "Feature",
  "properties": {
    "addr:full":"10090 Buttigliera Alta Buttigliera Alta Torino 10090",
    "addr:postcode":"10090;10090",
    "iso:country":"IT",
    "sg:address":"10090 Buttigliera Alta",
    "sg:city":"Buttigliera Alta",
    "sg:orig_category":"Impiantistica E Prodotti Tecnologici Per Edilizia. Elettrotecnica Industriale, Prodotti E Apparecchiature. Elettrotecnica Professionale E Di Consumo",
    "sg:phone":"+39 011 934 8186",
    "sg:postcode":"10090",
    "sg:province":"Torino",
    "wof:name":"G.t. Impianti Elettrici Di Torta",
    "wof:placetype":"venue"
},
  "geometry": {"coordinates":[7.397664,45.086906],"type":"Point"}
}