{
  "type": "Feature",
  "properties": {
    "iso:country":"IT",
    "sg:address":"03032 Arce",
    "sg:city":"Arce",
    "sg:orig_category":"Antincendio - Impianti, Attrezzature E Materiali",
    "sg:phone":"+39 0776 539072",
    "sg:postcode":"03032",
    "sg:province":"Frosinone",
    "wof:name":"Co.m.i.p. Di Compagnone Eleuterio",
    "wof:placetype":"venue"
},
  "geometry": {"coordinates":[13.572736,41.585091],"type":"Point"}
}