{
  "type": "Feature",
  "properties": {
    "addr:full":"127, Via Penne 66100 Chieti Chieti Chieti 66100",
    "addr:housenumber":"127",
    "addr:postcode":"66100;66100",
    "addr:street":"Via Penne",
    "iso:country":"IT",
    "sg:address":"127, Via Penne 66100 Chieti",
    "sg:city":"Chieti",
    "sg:classifiers":[
        {
            "category":"Shopping",
            "subcategory":"Clothing, Apparel, & Fashions",
            "type":"Retail Goods"
        }
    ],
    "sg:phone":"+39 0871 565620",
    "sg:postcode":"66100",
    "sg:province":"Chieti",
    "sg:tags":[
        "clothes"
    ],
    "wof:name":"Ghost S.r.l.",
    "wof:placetype":"venue"
},
  "geometry": {"coordinates":[14.144359,42.361458],"type":"Point"}
}