{
  "type": "Feature",
  "properties": {
    "iso:country":"IT",
    "sg:address":"36075 Montecchio Maggiore",
    "sg:city":"Montecchio Maggiore",
    "sg:orig_category":"Prodotti E Manufatti In Materie Plastiche. Forniture Per Attivita' Industriali",
    "sg:phone":"+39 0444 699922",
    "sg:postcode":"36075",
    "sg:province":"Vicenza",
    "wof:name":"S.p.t. Di Gatto Srl",
    "wof:placetype":"venue"
},
  "geometry": {"coordinates":[11.4058046341,45.4918365479],"type":"Point"}
}