{
  "type": "Feature",
  "properties": {
    "iso:country":"IT",
    "sg:address":"10024 Moncalieri",
    "sg:city":"Moncalieri",
    "sg:orig_category":"Ricambi E Componenti Dei Mezzi Di Trasporto",
    "sg:phone":"+39 011 606 8250",
    "sg:postcode":"10024",
    "sg:province":"Torino",
    "wof:name":"Gi.bo.di Mastrippolito Domenico",
    "wof:placetype":"venue"
},
  "geometry": {"coordinates":[7.660816,45.015633],"type":"Point"}
}