{
  "type": "Feature",
  "properties": {
    "iso:country":"IT",
    "sg:address":"00044 Frascati",
    "sg:city":"Frascati",
    "sg:orig_category":"Carni, Salumi E Pesci",
    "sg:phone":"+39 06 942 0460",
    "sg:postcode":"00044",
    "sg:province":"Roma",
    "wof:name":"Tardiola Anna Maria",
    "wof:placetype":"venue"
},
  "geometry": {"coordinates":[12.681556,41.808807],"type":"Point"}
}