{
  "type": "Feature",
  "properties": {
    "addr:full":"76/b, Via Redolone 51030 Serravalle Pistoiese Serravalle Pistoiese Pistoia 51030",
    "addr:housenumber":"76 / b",
    "addr:postcode":"51030;51030",
    "addr:street":"Via Redolone",
    "iso:country":"IT",
    "sg:address":"76/b, Via Redolone 51030 Serravalle Pistoiese",
    "sg:city":"Serravalle Pistoiese",
    "sg:classifiers":[
        {
            "category":"Shopping",
            "subcategory":"Crafts & Fabrics",
            "type":"Retail Goods"
        }
    ],
    "sg:phone":"+39 0573 527557",
    "sg:postcode":"51030",
    "sg:province":"Pistoia",
    "wof:name":"Tucci Ilva E Chiti David Snc",
    "wof:placetype":"venue"
},
  "geometry": {"coordinates":[10.9041013718,43.8851394653],"type":"Point"}
}