{
  "type": "Feature",
  "properties": {
    "addr:full":"6, Via Galilei 20090 Assago Assago Milano 20090",
    "addr:postcode":"20090;20090",
    "addr:street":"Via Galilei;Assago",
    "iso:country":"IT",
    "sg:address":"6, Via Galilei 20090 Assago",
    "sg:city":"Assago",
    "sg:classifiers":[
        {
            "category":"Real Estate",
            "subcategory":"Surveying",
            "type":"Services"
        }
    ],
    "sg:phone":"+39 39024880554",
    "sg:postcode":"20090",
    "sg:province":"Milano",
    "sg:tags":[
        "equipment",
        "material",
        "good",
        "-",
        "handling"
    ],
    "wof:name":"Stp (s.r.l.)",
    "wof:placetype":"venue"
},
  "geometry": {"coordinates":[9.1237,45.406204],"type":"Point"}
}