{
  "type": "Feature",
  "properties": {
    "addr:full":"10144 Torino Torino Torino 10144",
    "addr:postcode":"10144;10144",
    "iso:country":"IT",
    "sg:address":"10144 Torino",
    "sg:city":"Torino",
    "sg:orig_category":"Tende Alla Veneziana E Verticali",
    "sg:phone":"+39 011 484377",
    "sg:postcode":"10144",
    "sg:province":"Torino",
    "wof:name":"Ts Tende",
    "wof:placetype":"venue"
},
  "geometry": {"coordinates":[7.661322,45.079601],"type":"Point"}
}