{
  "type": "Feature",
  "properties": {
    "iso:country":"IT",
    "sg:address":"Viale Monza 272 20128 Milano",
    "sg:city":"Milano",
    "sg:orig_category":"Haematological Technology",
    "sg:phone":"+39 02 252091",
    "sg:postcode":"20128",
    "sg:province":"Milano",
    "sg:website":"www.masciabrunelli.it",
    "wof:name":"Biolife Italiana Srl",
    "wof:placetype":"venue"
},
  "geometry": {"coordinates":[9.226134,45.517159],"type":"Point"}
}