{
  "type": "Feature",
  "properties": {
    "addr:full":"1, Via Bonifica Del Tronto 64010 Ancarano Ancarano Teramo 64010",
    "addr:postcode":"64010;64010",
    "addr:street":"Via Bonifica Del Tronto",
    "iso:country":"IT",
    "sg:address":"1, Via Bonifica Del Tronto 64010 Ancarano",
    "sg:city":"Ancarano",
    "sg:classifiers":[
        {
            "category":"Shopping",
            "subcategory":"Computers & Home Electronics",
            "type":"Retail Goods"
        }
    ],
    "sg:phone":"+39 0861 870901",
    "sg:postcode":"64010",
    "sg:province":"Teramo",
    "sg:tags":[
        "electronic",
        "electrical",
        "equipment"
    ],
    "wof:name":"Elettropicena Sud Srl",
    "wof:placetype":"venue"
},
  "geometry": {"coordinates":[13.79407,42.864128],"type":"Point"}
}