{
  "type": "Feature",
  "properties": {
    "iso:country":"IT",
    "sg:address":"70044 Polignano A Mare",
    "sg:city":"Polignano a Mare",
    "sg:orig_category":"Motori Ed Organi Di Trasmissione. Ricambi E Componenti Dei Mezzi Di Trasporto",
    "sg:phone":"+39 080 424 0616",
    "sg:postcode":"70044",
    "sg:province":"Bari",
    "wof:name":"Tatone Vito Officina Meccanica",
    "wof:placetype":"venue"
},
  "geometry": {"coordinates":[17.1839027405,40.966835022],"type":"Point"}
}