{
  "type": "Feature",
  "properties": {
    "iso:country":"IT",
    "sg:address":"2, Localita' Pian D'armi 61026 Piandimeleto",
    "sg:city":"Piandimeleto",
    "sg:classifiers":[
        {
            "category":"Home & Garden",
            "subcategory":"Home Furnishings",
            "type":"Retail Goods"
        }
    ],
    "sg:phone":"+39 0722 721822",
    "sg:postcode":"61026",
    "sg:province":"Pesaro E Urbino",
    "sg:tags":[
        "household"
    ],
    "wof:name":"Sinova S.r.l.",
    "wof:placetype":"venue"
},
  "geometry": {"coordinates":[12.420367,43.725018],"type":"Point"}
}