{
  "type": "Feature",
  "properties": {
    "iso:country":"IT",
    "sg:address":"Via Teodoro Caruel 3 50126 Firenze",
    "sg:city":"Firenze",
    "sg:classifiers":[
        {
            "category":"Bars & Pubs",
            "subcategory":"Nightclub",
            "type":"Food & Drink"
        }
    ],
    "sg:phone":"+39 055 683499",
    "sg:postcode":"50126",
    "sg:province":"Firenze",
    "sg:tags":[
        "lamp",
        "ceramic"
    ],
    "sg:website":"www.ceramichebianchini.it",
    "wof:name":"Arrigo Bianchini Srl",
    "wof:placetype":"venue"
},
  "geometry": {"coordinates":[11.290168,43.753613],"type":"Point"}
}