{
  "type": "Feature",
  "properties": {
    "iso:country":"IT",
    "sg:address":"44040 Marrara",
    "sg:orig_category":"Imprese Di Costruzioni Civili Ed Industriali",
    "sg:phone":"+39 0532 421024",
    "sg:province":"FE",
    "wof:name":"Fergnani Marco",
    "wof:placetype":"venue"
},
  "geometry": {"coordinates":[11.739248,44.787506],"type":"Point"}
}