{
  "type": "Feature",
  "properties": {
    "iso:country":"IT",
    "sg:address":"Via G. Ferrari 21 21047 Saronno",
    "sg:city":"Saronno",
    "sg:classifiers":[
        {
            "category":"Wholesale",
            "subcategory":"Construction Materials",
            "type":"Manufacturing & Wholesale Goods"
        }
    ],
    "sg:phone":"+39 02 9670 1076",
    "sg:postcode":"21047",
    "sg:province":"Varese",
    "sg:tags":[
        "model",
        "architectural"
    ],
    "sg:website":"www.archishop.it",
    "wof:name":"Progest Srl",
    "wof:placetype":"venue"
},
  "geometry": {"coordinates":[8.826385,45.817604],"type":"Point"}
}