{
  "type": "Feature",
  "properties": {
    "iso:country":"IT",
    "sg:address":"Via Nonantolana 970/1 41100 Modena",
    "sg:city":"Modena",
    "sg:classifiers":[
        {
            "category":"Structure",
            "subcategory":"Factory",
            "type":"Public Place"
        }
    ],
    "sg:phone":"+39 059 255 6411",
    "sg:postcode":"41100",
    "sg:province":"Modena",
    "sg:tags":[
        "complete",
        "installations"
    ],
    "wof:name":"Enecolab Srl",
    "wof:placetype":"venue"
},
  "geometry": {"coordinates":[10.9654712677,44.6603431702],"type":"Point"}
}