{
  "type": "Feature",
  "properties": {
    "iso:country":"IT",
    "sg:address":"Via Aldo Lusardi 40, 24040 Calvenzano, Bg",
    "sg:city":"Calvenzano",
    "sg:classifiers":[
        {
            "category":"Banks & Credit Unions",
            "subcategory":"Bank",
            "type":"Services"
        }
    ],
    "sg:postcode":"24040",
    "sg:province":"Bergamo",
    "wof:name":"Banca Di Credito Cooperativo Di Calvenzano",
    "wof:placetype":"venue"
},
  "geometry": {"coordinates":[9.59963,45.494804],"type":"Point"}
}