{
  "type": "Feature",
  "properties": {
    "addr:full":"8, Via Zucchi 20095 Cusano Milanino Cusano Milanino Milano 20095",
    "addr:postcode":"20095;20095",
    "addr:street":"Via Zucchi",
    "iso:country":"IT",
    "sg:address":"8, Via Zucchi 20095 Cusano Milanino",
    "sg:city":"Cusano Milanino",
    "sg:classifiers":[
        {
            "category":"Real Estate",
            "subcategory":"Surveying",
            "type":"Services"
        }
    ],
    "sg:phone":"+39 39026134758",
    "sg:postcode":"20095",
    "sg:province":"Milano",
    "sg:tags":[
        "equipment",
        "material",
        "good",
        "-",
        "handling"
    ],
    "wof:name":"Master Automazione Srl",
    "wof:placetype":"venue"
},
  "geometry": {"coordinates":[9.175249,45.550007],"type":"Point"}
}