{
  "type": "Feature",
  "properties": {
    "iso:country":"IT",
    "sg:address":"1, Via Murari Guglielmo 70123 Bari",
    "sg:city":"Bari",
    "sg:classifiers":[
        {
            "category":"Manufacturing",
            "subcategory":"Food",
            "type":"Manufacturing & Wholesale Goods"
        }
    ],
    "sg:phone":"+39 080 531 4910",
    "sg:postcode":"70123",
    "sg:province":"Bari",
    "sg:tags":[
        "equipment",
        "processing",
        "-",
        "machinery"
    ],
    "wof:name":"Amenduni Nicola (s.p.a.)",
    "wof:placetype":"venue"
},
  "geometry": {"coordinates":[16.8692913055,41.1260528564],"type":"Point"}
}