{
  "type": "Feature",
  "properties": {
    "iso:country":"IT",
    "sg:address":"14100 Asti",
    "sg:city":"Asti",
    "sg:orig_category":"Arredo Cucina Ed Elettrodomestici. Elettrodomestici",
    "sg:phone":"+39 0141 34378",
    "sg:postcode":"14100",
    "sg:province":"Asti",
    "wof:name":"Mara Ricambi Di Magagna P. Carlo & C. Sas",
    "wof:placetype":"venue"
},
  "geometry": {"coordinates":[8.225703,44.942333],"type":"Point"}
}