{
  "type": "Feature",
  "properties": {
    "iso:country":"IT",
    "sg:address":"70124 Bari",
    "sg:city":"Bari",
    "sg:orig_category":"Accessori Dei Mezzi Di Trasporto",
    "sg:phone":"+39 080 561 7788",
    "sg:postcode":"70124",
    "sg:province":"Bari",
    "wof:name":"Il Cruscotto Di Giovanni Dentamaro",
    "wof:placetype":"venue"
},
  "geometry": {"coordinates":[16.847338,41.091347],"type":"Point"}
}