{
  "type": "Feature",
  "properties": {
    "addr:full":"12, Via Monte Grappa 31050 Ponzano Veneto Ponzano Veneto Treviso 31050",
    "addr:postcode":"31050;31050",
    "addr:street":"Via Monte Grappa",
    "iso:country":"IT",
    "sg:address":"12, Via Monte Grappa 31050 Ponzano Veneto",
    "sg:city":"Ponzano Veneto",
    "sg:classifiers":[
        {
            "category":"Professional",
            "subcategory":"Printing & Photocopies",
            "type":"Services"
        }
    ],
    "sg:phone":"+39 0422 967103",
    "sg:postcode":"31050",
    "sg:province":"Treviso",
    "wof:name":"Elleti S.a.s. Di Busatto Tiziana & C.",
    "wof:placetype":"venue"
},
  "geometry": {"coordinates":[12.2334632874,45.6668395996],"type":"Point"}
}