{
  "type": "Feature",
  "properties": {
    "addr:full":"Via Padova Zona Artigianale 64020 Morro D'oro Teramo 64020",
    "addr:postcode":"64020;64020",
    "addr:street":"Via Padova Zona Artigianale",
    "iso:country":"IT",
    "sg:address":"Via Padova Zona Artigianale 64020 Morro D'oro",
    "sg:orig_category":"Radiators, Electric",
    "sg:phone":"+39 085 80401",
    "sg:postcode":"64020",
    "sg:province":"Teramo",
    "sg:website":"www.cordivari.it",
    "wof:name":"Cordivari Srl",
    "wof:placetype":"venue"
},
  "geometry": {"coordinates":[13.698531,42.66127],"type":"Point"}
}