{
  "type": "Feature",
  "properties": {
    "iso:country":"IT",
    "sg:address":"50041 Calenzano",
    "sg:city":"Calenzano",
    "sg:classifiers":[
        {
            "category":"Shopping",
            "subcategory":"Gifts & Souvenirs",
            "type":"Retail Goods"
        }
    ],
    "sg:phone":"+39 055 882 5080",
    "sg:postcode":"50041",
    "sg:province":"Firenze",
    "sg:tags":[
        "gifts",
        "business"
    ],
    "wof:name":"Manifattura Sc3 Snc",
    "wof:placetype":"venue"
},
  "geometry": {"coordinates":[10.747925,43.67762],"type":"Point"}
}