{
  "type": "Feature",
  "properties": {
    "addr:full":"00187 Roma Roma Roma 00187",
    "addr:postcode":"00187;00187",
    "iso:country":"IT",
    "sg:address":"00187 Roma",
    "sg:city":"Roma",
    "sg:orig_category":"Servizi Culturali E Per Lo Spettacolo",
    "sg:phone":"+39 06 481 5820",
    "sg:postcode":"00187",
    "sg:province":"Roma",
    "wof:name":"Italia Cinema Agenzia Per La Promozione Del Cinema Italiano S.r.l.",
    "wof:placetype":"venue"
},
  "geometry": {"coordinates":[12.495072,41.907154],"type":"Point"}
}