{
  "type": "Feature",
  "properties": {
    "addr:full":"V. Spartaco 20135 Milano Milano Milano 20135",
    "addr:postcode":"20135;20135",
    "addr:street":"V. Spartaco",
    "iso:country":"IT",
    "sg:address":"V. Spartaco 20135 Milano",
    "sg:city":"Milano",
    "sg:classifiers":[
        {
            "category":"Manufacturing",
            "subcategory":"Printing",
            "type":"Manufacturing & Wholesale Goods"
        }
    ],
    "sg:phone":"+39 02 5412 2581",
    "sg:postcode":"20135",
    "sg:province":"Milano",
    "sg:tags":[
        "publishing"
    ],
    "sg:website":"http://www.posteritalia.com:ws_end: :mark:ws:http://www.paginegialle.it/posteritalia",
    "wof:name":"Poster Italia",
    "wof:placetype":"venue"
},
  "geometry": {"coordinates":[9.2107667923,45.4584884644],"type":"Point"}
}