{
  "type": "Feature",
  "properties": {
    "iso:country":"IT",
    "sg:address":"00175 Roma",
    "sg:city":"Roma",
    "sg:orig_category":"Ospedali E Servizi Sanitari. Centri Di Estetica E Cosmesi E Servizi",
    "sg:phone":"+39 06 714 1555",
    "sg:postcode":"00175",
    "sg:province":"Roma",
    "wof:name":"Lomuscio Giuseppe",
    "wof:placetype":"venue"
},
  "geometry": {"coordinates":[12.552702,41.863232],"type":"Point"}
}