{
  "type": "Feature",
  "properties": {
    "iso:country":"IT",
    "sg:address":"04014 Pontinia",
    "sg:city":"Pontinia",
    "sg:orig_category":"Vetro: Prodotti E Lavorazioni. Articoli Per Imballaggio E Confezionamento",
    "sg:phone":"+39 0773 853041",
    "sg:postcode":"04014",
    "sg:province":"Latina",
    "wof:name":"Pagliaroli Vetri Srl",
    "wof:placetype":"venue"
},
  "geometry": {"coordinates":[13.147185,41.423885],"type":"Point"}
}