{
  "type": "Feature",
  "properties": {
    "iso:country":"IT",
    "sg:address":"20145 Milano",
    "sg:city":"Milano",
    "sg:orig_category":"Tessuti Arredamento, Tende E Tappeti",
    "sg:phone":"+39 02 466975",
    "sg:postcode":"20145",
    "sg:province":"Milano",
    "wof:name":"Michail Farchad",
    "wof:placetype":"venue"
},
  "geometry": {"coordinates":[9.164303,45.467613],"type":"Point"}
}