{
  "type": "Feature",
  "properties": {
    "iso:country":"IT",
    "sg:address":"Sda Statale 16 Km 629 71010 Poggio Imperiale",
    "sg:city":"Poggio Imperiale",
    "sg:orig_category":"Tomatoes, Peeled",
    "sg:phone":"+39 0882 997979",
    "sg:postcode":"71010",
    "sg:province":"Foggia",
    "wof:name":"Compagnia Generale Agroindustriale Spa",
    "wof:placetype":"venue"
},
  "geometry": {"coordinates":[15.5447,41.462334],"type":"Point"}
}