{
  "type": "Feature",
  "properties": {
    "iso:country":"IT",
    "sg:address":"64028 Silvi Alta",
    "sg:city":"Silvi",
    "sg:orig_category":"Alimentari - Vendita Al Dettaglio",
    "sg:phone":"+39 085 935 4041",
    "sg:postcode":"64028",
    "sg:province":"Teramo",
    "wof:name":"Matilda Produzione Artigianale Di D'apolito Diana",
    "wof:placetype":"venue"
},
  "geometry": {"coordinates":[13.617518,42.593777],"type":"Point"}
}