{
  "type": "Feature",
  "properties": {
    "addr:full":"34072 Gradisca D'isonzo Gorizia 34072",
    "addr:postcode":"34072;34072",
    "iso:country":"IT",
    "sg:address":"34072 Gradisca D'isonzo",
    "sg:orig_category":"Pompe",
    "sg:phone":"+39 0481 99763",
    "sg:postcode":"34072",
    "sg:province":"Gorizia",
    "wof:name":"Olvis Export (s.r.l.)",
    "wof:placetype":"venue"
},
  "geometry": {"coordinates":[13.4975566864,45.8879585266],"type":"Point"}
}