{
  "type": "Feature",
  "properties": {
    "iso:country":"IT",
    "sg:address":"47900 Rimini",
    "sg:city":"Rimini",
    "sg:classifiers":[
        {
            "category":"Health Services",
            "subcategory":"Nursing And Care Facility",
            "type":"Services"
        }
    ],
    "sg:phone":"+39 0541 734127",
    "sg:postcode":"47900",
    "sg:province":"Rimini",
    "sg:tags":[
        "case",
        "riposo",
        "di"
    ],
    "wof:name":"Casa Di Riposo Casa Amica",
    "wof:placetype":"venue"
},
  "geometry": {"coordinates":[12.552751,44.026459],"type":"Point"}
}