{
  "type": "Feature",
  "properties": {
    "iso:country":"IT",
    "sg:address":"20121 Milano",
    "sg:city":"Milano",
    "sg:orig_category":"Banche E Servizi Finanziari",
    "sg:phone":"+39 02 8699 5247",
    "sg:postcode":"20121",
    "sg:province":"Milano",
    "wof:name":"Paradise Srl",
    "wof:placetype":"venue"
},
  "geometry": {"coordinates":[9.191338,45.46521],"type":"Point"}
}