{
  "type": "Feature",
  "properties": {
    "iso:country":"IT",
    "sg:address":"14/8, V. Xx Settembre 16100 Genova",
    "sg:orig_category":"Miscellaneous Products",
    "sg:phone":"+39 010 291 5107",
    "sg:website":"http://www.asef.it",
    "wof:name":"A.se.f.",
    "wof:placetype":"venue"
},
  "geometry": {"coordinates":[8.9399471283,44.4058036804],"type":"Point"}
}