{
  "type": "Feature",
  "properties": {
    "addr:full":"20040 Burago Di Molgora Burago di Molgora Milano 20040",
    "addr:housenumber":"20040",
    "addr:postcode":"20040",
    "addr:street":"Burago",
    "iso:country":"IT",
    "sg:address":"20040 Burago Di Molgora",
    "sg:city":"Burago di Molgora",
    "sg:orig_category":"Tessuti E Stoffe. Forniture Per Attivita' Industriali",
    "sg:phone":"+39 039 608 5788",
    "sg:postcode":"20040",
    "sg:province":"Milano",
    "wof:name":"Ala Tec Srl",
    "wof:placetype":"venue"
},
  "geometry": {"coordinates":[9.384279,45.590801],"type":"Point"}
}