{
  "type": "Feature",
  "properties": {
    "iso:country":"IT",
    "sg:address":"10, Via Corcioni 80044 Ottaviano",
    "sg:city":"Ottaviano",
    "sg:classifiers":[
        {
            "category":"Bars & Pubs",
            "subcategory":"Nightclub",
            "type":"Food & Drink"
        }
    ],
    "sg:phone":"+39 081 528 8024",
    "sg:postcode":"80044",
    "sg:province":"Napoli",
    "sg:tags":[
        "cake",
        "bread"
    ],
    "wof:name":"Dolciaria Acquaviva S.r.l.",
    "wof:placetype":"venue"
},
  "geometry": {"coordinates":[14.491557,40.850594],"type":"Point"}
}