{
  "type": "Feature",
  "properties": {
    "addr:full":"4, Via Antonio Salieri 37050 Oppeano Oppeano Verona 37050",
    "addr:postcode":"37050;37050",
    "addr:street":"Via Antonio Salieri",
    "iso:country":"IT",
    "sg:address":"4, Via Antonio Salieri 37050 Oppeano",
    "sg:city":"Oppeano",
    "sg:classifiers":[
        {
            "category":"Professional",
            "subcategory":"Printing & Photocopies",
            "type":"Services"
        }
    ],
    "sg:phone":"+39 045 699 7555",
    "sg:postcode":"37050",
    "sg:province":"Verona",
    "wof:name":"Plurimetal S.r.l.",
    "wof:placetype":"venue"
},
  "geometry": {"coordinates":[11.0457344055,45.3848762512],"type":"Point"}
}