{
  "type": "Feature",
  "properties": {
    "iso:country":"IT",
    "sg:address":"31040 Portobuffole'",
    "sg:orig_category":"Arredo Camera Letto E Complementi",
    "sg:phone":"+39 0422 850279",
    "sg:postcode":"31040",
    "sg:province":"Treviso",
    "wof:name":"Rialto Arredamenti Srl",
    "wof:placetype":"venue"
},
  "geometry": {"coordinates":[12.536061,45.852345],"type":"Point"}
}