{
  "type": "Feature",
  "properties": {
    "addr:full":"Via Meucci 4 31022 Preganziol Preganziol Treviso 31022",
    "addr:housenumber":"4",
    "addr:postcode":"31022;31022",
    "addr:street":"Via Meucci",
    "iso:country":"IT",
    "sg:address":"Via Meucci 4 31022 Preganziol",
    "sg:city":"Preganziol",
    "sg:orig_category":"Pipe Splitting Equipment",
    "sg:phone":"+39 0422 631411",
    "sg:postcode":"31022",
    "sg:province":"Treviso",
    "wof:name":"Tubes Tech Srl",
    "wof:placetype":"venue"
},
  "geometry": {"coordinates":[12.1774644852,45.6485443115],"type":"Point"}
}