{
  "type": "Feature",
  "properties": {
    "addr:full":"6, Via Trento 25022 Borgo San Giacomo Borgo San Giacomo Brescia 25022",
    "addr:postcode":"25022;25022",
    "addr:street":"Via Trento;Borgo San Giacomo Brescia",
    "iso:country":"IT",
    "sg:address":"6, Via Trento 25022 Borgo San Giacomo",
    "sg:city":"Borgo San Giacomo",
    "sg:classifiers":[
        {
            "category":"Shopping",
            "subcategory":"Clothing, Apparel, & Fashions",
            "type":"Retail Goods"
        }
    ],
    "sg:phone":"+39 39030948142",
    "sg:postcode":"25022",
    "sg:province":"Brescia",
    "sg:tags":[
        "clothes"
    ],
    "wof:name":"Calzificio San Giacomo Di Bertesso Giuseppina & C. S.n.c.",
    "wof:placetype":"venue"
},
  "geometry": {"coordinates":[11.115941,45.418343],"type":"Point"}
}