{
  "type": "Feature",
  "properties": {
    "iso:country":"IT",
    "sg:address":"00136 Roma",
    "sg:city":"Roma",
    "sg:orig_category":"Condizionamento Aria Impianti - Installazione E Manutenzione",
    "sg:phone":"+39 06 3974 9867",
    "sg:postcode":"00136",
    "sg:province":"Roma",
    "wof:name":"Idraulica Via Emo Di Censo Giuseppina",
    "wof:placetype":"venue"
},
  "geometry": {"coordinates":[12.444462,41.903542],"type":"Point"}
}