{
  "type": "Feature",
  "properties": {
    "iso:country":"IT",
    "sg:address":"00144 Roma",
    "sg:city":"Roma",
    "sg:orig_category":"Musica. Shopping",
    "sg:phone":"+39 06 592 3850",
    "sg:postcode":"00144",
    "sg:province":"Roma",
    "wof:name":"Discoteca Il Carillon Srl",
    "wof:placetype":"venue"
},
  "geometry": {"coordinates":[12.4667406082,41.8315467834],"type":"Point"}
}