{
  "type": "Feature",
  "properties": {
    "iso:country":"IT",
    "sg:address":"10, Via Bergamo 26022 Castelverde",
    "sg:city":"Castelverde",
    "sg:classifiers":[
        {
            "category":"Professional",
            "subcategory":"Engineering",
            "type":"Services"
        }
    ],
    "sg:phone":"+39 0372 427597",
    "sg:postcode":"26022",
    "sg:province":"Cremona",
    "sg:tags":[
        "machine",
        "-",
        "mechanical"
    ],
    "wof:name":"Imeco Automazioni Srl",
    "wof:placetype":"venue"
},
  "geometry": {"coordinates":[10.000429,45.183804],"type":"Point"}
}