{
  "type": "Feature",
  "properties": {
    "iso:country":"IT",
    "sg:address":"150, Via Torino 27045 Casteggio",
    "sg:city":"Casteggio",
    "sg:classifiers":[
        {
            "category":"Manufacturing",
            "subcategory":"Food",
            "type":"Manufacturing & Wholesale Goods"
        }
    ],
    "sg:phone":"+39 0383 890232",
    "sg:postcode":"27045",
    "sg:province":"Pavia",
    "sg:tags":[
        "equipment",
        "processing",
        "-",
        "machinery"
    ],
    "wof:name":"Cae (s.p.a.)",
    "wof:placetype":"venue"
},
  "geometry": {"coordinates":[9.1142253876,45.0116157532],"type":"Point"}
}