{
  "type": "Feature",
  "properties": {
    "iso:country":"IT",
    "sg:address":"71049 Trinitapoli",
    "sg:city":"Trinitapoli",
    "sg:orig_category":"Frutta E Verdura - Ingrosso",
    "sg:phone":"+39 0883 630433",
    "sg:postcode":"71049",
    "sg:province":"Foggia",
    "wof:name":"Lamedica Tommaso",
    "wof:placetype":"venue"
},
  "geometry": {"coordinates":[16.0803413391,41.3590278625],"type":"Point"}
}