{
  "type": "Feature",
  "properties": {
    "iso:country":"IT",
    "sg:address":"Via Bengasi 19 70017 Putignano",
    "sg:city":"Putignano",
    "sg:orig_category":"Boys' Clothing",
    "sg:phone":"+39 080 491 1322",
    "sg:postcode":"70017",
    "sg:province":"Bari",
    "wof:name":"Fratelli Totaro Maglificio Mafrat Spa",
    "wof:placetype":"venue"
},
  "geometry": {"coordinates":[17.120663,40.852497],"type":"Point"}
}