{
  "type": "Feature",
  "properties": {
    "iso:country":"IT",
    "sg:address":"41049 Sassuolo",
    "sg:city":"Sassuolo",
    "sg:orig_category":"Pubblica Amministrazione",
    "sg:phone":"+39 0536 818711",
    "sg:postcode":"41049",
    "sg:province":"Modena",
    "wof:name":"Municipio Di Sassuolo",
    "wof:placetype":"venue"
},
  "geometry": {"coordinates":[10.7826042175,44.5404434204],"type":"Point"}
}