{
  "type": "Feature",
  "properties": {
    "iso:country":"IT",
    "sg:address":"12, Via Boccaccio Giovanni 50012 Bagno A Ripoli",
    "sg:city":"Bagno a Ripoli",
    "sg:classifiers":[
        {
            "category":"Personal",
            "subcategory":"Shoe Repair & Shine",
            "type":"Services"
        }
    ],
    "sg:phone":"+39 39055643181",
    "sg:postcode":"50012",
    "sg:province":"Firenze",
    "sg:tags":[
        "leather"
    ],
    "wof:name":"Loma (s.r.l.)",
    "wof:placetype":"venue"
},
  "geometry": {"coordinates":[11.29529,43.73122],"type":"Point"}
}