{
  "type": "Feature",
  "properties": {
    "iso:country":"IT",
    "sg:address":"31, Via Murri Francesco 80022 Arzano",
    "sg:city":"Arzano",
    "sg:classifiers":[
        {
            "category":"Personal",
            "subcategory":"Shoe Repair & Shine",
            "type":"Services"
        }
    ],
    "sg:phone":"+39 081 731 2890",
    "sg:postcode":"80022",
    "sg:province":"Napoli",
    "sg:tags":[
        "leather"
    ],
    "wof:name":"Pancal Donna S.r.l.",
    "wof:placetype":"venue"
},
  "geometry": {"coordinates":[14.271851,40.914883],"type":"Point"}
}