{
  "type": "Feature",
  "properties": {
    "iso:country":"IT",
    "sg:address":"Via Stalingrade 59 A; Bologna; 40100",
    "sg:classifiers":[
        {
            "category":"Banks & Credit Unions",
            "subcategory":"Bank",
            "type":"Services"
        }
    ],
    "sg:phone":"+39 051 374301",
    "wof:name":"Banca Popolare Di Bologna",
    "wof:placetype":"venue"
},
  "geometry": {"coordinates":[11.359783,44.513206],"type":"Point"}
}