{
  "type": "Feature",
  "properties": {
    "iso:country":"IT",
    "sg:address":"40068 San Lazzaro Di Savena",
    "sg:city":"San Lazzaro",
    "sg:orig_category":"Gioielleria, Oreficeria E Argenteria",
    "sg:phone":"+39 051 472451",
    "sg:postcode":"40068",
    "sg:province":"Bologna",
    "sg:website":"http://www.terraenatura.com",
    "wof:name":"Terra E Natura",
    "wof:placetype":"venue"
},
  "geometry": {"coordinates":[11.375804,44.457436],"type":"Point"}
}