{
  "type": "Feature",
  "properties": {
    "iso:country":"IT",
    "sg:address":"31100 Treviso",
    "sg:city":"Treviso",
    "sg:orig_category":"Pneumatici - Commercio E Riparazione",
    "sg:phone":"+39 0422 540940",
    "sg:postcode":"31100",
    "sg:province":"Treviso",
    "wof:name":"Pneumatici Sile Di Falchetto Luciano",
    "wof:placetype":"venue"
},
  "geometry": {"coordinates":[12.1697692871,45.6000938416],"type":"Point"}
}