{
  "type": "Feature",
  "properties": {
    "addr:full":"41012 Carpi Carpi Modena 41012",
    "addr:postcode":"41012;41012",
    "iso:country":"IT",
    "sg:address":"41012 Carpi",
    "sg:city":"Carpi",
    "sg:classifiers":[
        {
            "category":"Banks & Credit Unions",
            "subcategory":"Financial Services",
            "type":"Services"
        }
    ],
    "sg:phone":"+39 059 648111",
    "sg:postcode":"41012",
    "sg:province":"Modena",
    "sg:website":"http://www.crcarpi.it",
    "wof:name":"Cassa Risparmio Carpi Spa",
    "wof:placetype":"venue"
},
  "geometry": {"coordinates":[10.894758,44.794083],"type":"Point"}
}