{
  "type": "Feature",
  "properties": {
    "iso:country":"IT",
    "sg:address":"09037 San Gavino Monreale",
    "sg:city":"San Gavino Monreale",
    "sg:orig_category":"Tappezzieri In Carta",
    "sg:phone":"+39 070 933 9135",
    "sg:postcode":"09037",
    "sg:province":"Medio Campidano",
    "wof:name":"Smile Snc",
    "wof:placetype":"venue"
},
  "geometry": {"coordinates":[8.770147,39.547279],"type":"Point"}
}