{
  "type": "Feature",
  "properties": {
    "addr:full":"Via Roma 89 40012 Calderara Di Reno Calderara di Reno Bologna 40012",
    "addr:housenumber":"89",
    "addr:postcode":"40012;40012",
    "addr:street":"Via Roma",
    "iso:country":"IT",
    "sg:address":"Via Roma 89 40012 Calderara Di Reno",
    "sg:city":"Calderara di Reno",
    "sg:classifiers":[
        {
            "category":"Autos & Motor Vehicles",
            "subcategory":"Auto Supplies",
            "type":"Retail Goods"
        }
    ],
    "sg:phone":"+39 051 727612",
    "sg:postcode":"40012",
    "sg:province":"Bologna",
    "sg:tags":[
        "part",
        "spare",
        "motorcycle",
        "accessory"
    ],
    "wof:name":"Fibreglas G.b Di Ballanti Graziano Snc",
    "wof:placetype":"venue"
},
  "geometry": {"coordinates":[11.2711629868,44.5632858276],"type":"Point"}
}