{
  "type": "Feature",
  "properties": {
    "iso:country":"IT",
    "sg:address":"90011 Bagheria",
    "sg:city":"Bagheria",
    "sg:classifiers":[
        {
            "category":"Health Services",
            "subcategory":"Health Practitioner",
            "type":"Services"
        }
    ],
    "sg:phone":"+39 091 967776",
    "sg:postcode":"90011",
    "sg:province":"Palermo",
    "sg:tags":[
        "medici"
    ],
    "wof:name":"Diagnostica Per Immagini Srl",
    "wof:placetype":"venue"
},
  "geometry": {"coordinates":[13.502089,38.079899],"type":"Point"}
}