{
  "type": "Feature",
  "properties": {
    "iso:country":"IT",
    "sg:address":"80141 Napoli",
    "sg:city":"Napoli",
    "sg:orig_category":"Elettrodomestici - Produzione E Ingrosso",
    "sg:phone":"+39 081 751 2599",
    "sg:postcode":"80141",
    "sg:province":"Napoli",
    "wof:name":"Liguori Srl",
    "wof:placetype":"venue"
},
  "geometry": {"coordinates":[14.26397,40.871151],"type":"Point"}
}