{
  "type": "Feature",
  "properties": {
    "addr:full":"42010 Arceto Reggio Nell'Emilia 42010",
    "addr:postcode":"42010;42010",
    "iso:country":"IT",
    "sg:address":"42010 Arceto",
    "sg:orig_category":"Forniture Per Attivita' Industriali",
    "sg:phone":"+39 0522 980280",
    "sg:postcode":"42010",
    "sg:province":"Reggio Nell'Emilia",
    "wof:name":"Bravi Agr. Giovanni",
    "wof:placetype":"venue"
},
  "geometry": {"coordinates":[10.7233438492,44.6206932068],"type":"Point"}
}