{
  "type": "Feature",
  "properties": {
    "iso:country":"IT",
    "sg:address":"6, Via Giovanni Da Procida 20149 Milano",
    "sg:city":"Milano",
    "sg:classifiers":[
        {
            "category":"Communications",
            "subcategory":"Television Station",
            "type":"Services"
        }
    ],
    "sg:phone":"+39 39023450989",
    "sg:postcode":"20149",
    "sg:province":"Milano",
    "sg:tags":[
        "equipment",
        "optical",
        "instrument"
    ],
    "wof:name":"Voice Systems S.r.l.",
    "wof:placetype":"venue"
},
  "geometry": {"coordinates":[9.162585,45.47945],"type":"Point"}
}