{
  "type": "Feature",
  "properties": {
    "iso:country":"IT",
    "sg:address":"2, Viale Berti Pichat Carlo 40127 Bologna",
    "sg:city":"Bologna",
    "sg:classifiers":[
        {
            "category":"Utilities",
            "subcategory":"Electric",
            "type":"Services"
        }
    ],
    "sg:phone":"+39 39051250277",
    "sg:postcode":"40127",
    "sg:province":"Bologna",
    "sg:tags":[
        "energy"
    ],
    "wof:name":"Circolo Ricreativo Culturale Seabo",
    "wof:placetype":"venue"
},
  "geometry": {"coordinates":[11.346481,44.494221],"type":"Point"}
}