{
  "type": "Feature",
  "properties": {
    "iso:country":"IT",
    "sg:address":"06073 San Mariano",
    "sg:orig_category":"Servizi E Lavori Per Edilizia E Lavori Pubblici. Servizi E Lavori Per Ecologia E Smaltimento Rifiuti. Macchine E Forniture Per Ecologia E Smaltimento Rifiuti. Acqua, Luce, Gas E Societa' Di Esercizio ",
    "sg:postcode":"06073",
    "sg:province":"Perugia",
    "wof:name":"S.g.m. (s.r.l.)",
    "wof:placetype":"venue"
},
  "geometry": {"coordinates":[12.314247,43.095383],"type":"Point"}
}