{
  "type": "Feature",
  "properties": {
    "iso:country":"IT",
    "sg:address":"15048 Valenza",
    "sg:city":"Valenza",
    "sg:orig_category":"Cesellatori Ed Incassatori",
    "sg:phone":"+39 0131 947782",
    "sg:postcode":"15048",
    "sg:province":"Alessandria",
    "sg:website":"http://www.erostylegioielli.it",
    "wof:name":"Erostyle Di Saviolo Fabio",
    "wof:placetype":"venue"
},
  "geometry": {"coordinates":[8.610407,44.914772],"type":"Point"}
}