{
  "type": "Feature",
  "properties": {
    "iso:country":"IT",
    "sg:address":"20020 Arese",
    "sg:city":"Arese",
    "sg:orig_category":"Minuterie Metalliche E Ferramenta",
    "sg:phone":"+39 02 938 1274",
    "sg:postcode":"20020",
    "sg:province":"Milano",
    "wof:name":"Bitifer Di Brusinelli & Testa",
    "wof:placetype":"venue"
},
  "geometry": {"coordinates":[9.0789766312,45.5524559021],"type":"Point"}
}