{
  "type": "Feature",
  "properties": {
    "iso:country":"IT",
    "sg:address":"23851 Galbiate",
    "sg:city":"Galbiate",
    "sg:orig_category":"Frigotecnica, Apparecchiature E Servizi. Forniture Alle Strutture Ricettive",
    "sg:phone":"+39 0341 240110",
    "sg:postcode":"23851",
    "sg:province":"Lecco",
    "wof:name":"Cover Di Perego Giuseppe",
    "wof:placetype":"venue"
},
  "geometry": {"coordinates":[9.3446903229,45.8310546875],"type":"Point"}
}