{
  "type": "Feature",
  "properties": {
    "iso:country":"IT",
    "sg:address":"20098 San Giuliano Milanese",
    "sg:city":"San Giuliano Milanese",
    "sg:orig_category":"Articoli Per Imballaggio E Confezionamento",
    "sg:phone":"+39 02 9828 1604",
    "sg:postcode":"20098",
    "sg:province":"Milano",
    "wof:name":"Nuova Fustameria Rocca Brivio Srl",
    "wof:placetype":"venue"
},
  "geometry": {"coordinates":[9.255579,45.400394],"type":"Point"}
}