{
  "type": "Feature",
  "properties": {
    "iso:country":"IT",
    "sg:address":"Via Nazionale 28 23030 Villa Di Tirano",
    "sg:city":"Villa di Tirano",
    "sg:classifiers":[
        {
            "category":"Wholesale",
            "subcategory":"Drugs",
            "type":"Manufacturing & Wholesale Goods"
        }
    ],
    "sg:phone":"+39 0342 795025",
    "sg:postcode":"23030",
    "sg:province":"Sondrio",
    "sg:tags":[
        "chemical",
        "pharmaceutical"
    ],
    "wof:name":"Liquigas Valtellina S.r.l.",
    "wof:placetype":"venue"
},
  "geometry": {"coordinates":[10.126097,46.192558],"type":"Point"}
}