{
  "type": "Feature",
  "properties": {
    "addr:full":"3, Via Ernesto De Angeli 24028 Ponte Nossa Ponte Nossa Bergamo 24028",
    "addr:postcode":"24028;24028",
    "addr:street":"Via Ernesto De Angeli",
    "iso:country":"IT",
    "sg:address":"3, Via Ernesto De Angeli 24028 Ponte Nossa",
    "sg:city":"Ponte Nossa",
    "sg:classifiers":[
        {
            "category":"Professional",
            "subcategory":"Engineering",
            "type":"Services"
        }
    ],
    "sg:phone":"+39 39035701479",
    "sg:postcode":"24028",
    "sg:province":"Bergamo",
    "sg:tags":[
        "machine",
        "-",
        "mechanical"
    ],
    "wof:name":"Officine Meccaniche Di Ponte Nossa (s.r.l.)",
    "wof:placetype":"venue"
},
  "geometry": {"coordinates":[9.888492,45.868256],"type":"Point"}
}