{
  "type": "Feature",
  "properties": {
    "iso:country":"IT",
    "sg:address":"20092 Cinisello Balsamo",
    "sg:city":"Cinisello Balsamo",
    "sg:orig_category":"Servizi E Lavori Per Industria Alimentare E Bevande",
    "sg:phone":"+39 02 660 7181",
    "sg:postcode":"20092",
    "sg:province":"Milano",
    "wof:name":"Consorzio Cooperative Edificatrici Auprema",
    "wof:placetype":"venue"
},
  "geometry": {"coordinates":[9.219064,45.555416],"type":"Point"}
}