{
  "type": "Feature",
  "properties": {
    "iso:country":"IT",
    "sg:address":"16128 Genova",
    "sg:city":"Genova",
    "sg:orig_category":"Assicurazioni E Servizi Assicurativi",
    "sg:phone":"+39 010 57141",
    "sg:postcode":"16128",
    "sg:province":"Genova",
    "wof:name":"Cambiaso Risso & C. Srl",
    "wof:placetype":"venue"
},
  "geometry": {"coordinates":[8.93939,44.403748],"type":"Point"}
}