{
  "type": "Feature",
  "properties": {
    "addr:full":"10, Via Del Pino 23854 Olginate Olginate Lecco 23854",
    "addr:postcode":"23854;23854",
    "addr:street":"Via Del Pino",
    "iso:country":"IT",
    "sg:address":"10, Via Del Pino 23854 Olginate",
    "sg:city":"Olginate",
    "sg:classifiers":[
        {
            "category":"Shopping",
            "type":"Retail Goods"
        }
    ],
    "sg:phone":"+39 0341 654111",
    "sg:postcode":"23854",
    "sg:province":"Lecco",
    "sg:tags":[
        "finished",
        "-",
        "metallic"
    ],
    "wof:name":"V.a.r.i. S.p.a.",
    "wof:placetype":"venue"
},
  "geometry": {"coordinates":[9.414144516,45.7955703735],"type":"Point"}
}