{
  "type": "Feature",
  "properties": {
    "iso:country":"IT",
    "sg:address":"95125 Catania",
    "sg:city":"Catania",
    "sg:orig_category":"Servizi E Lavori Per Abbigliamento E Pelletterie. Arte Ed Artigianato Artistico. Shopping",
    "sg:phone":"+39 095 446144",
    "sg:postcode":"95125",
    "sg:province":"Catania",
    "wof:name":"Zz Top Di Lanza Concetta",
    "wof:placetype":"venue"
},
  "geometry": {"coordinates":[15.082046,37.534149],"type":"Point"}
}