{
  "type": "Feature",
  "properties": {
    "iso:country":"IT",
    "sg:address":"10156 Torino",
    "sg:city":"Torino",
    "sg:orig_category":"Trattamenti Termici E Superficiali Metalli, Galvanotecnica",
    "sg:phone":"+39 011 223 6763",
    "sg:postcode":"10156",
    "sg:province":"Torino",
    "wof:name":"T.s.t. Tecnologic Sistem Torino S.r.l.",
    "wof:placetype":"venue"
},
  "geometry": {"coordinates":[7.736893,45.135956],"type":"Point"}
}