{
  "type": "Feature",
  "properties": {
    "iso:country":"IT",
    "sg:address":"71019 Vieste",
    "sg:city":"Vieste",
    "sg:orig_category":"Alberghi",
    "sg:phone":"+39 0884 708251",
    "sg:postcode":"71019",
    "sg:province":"Foggia",
    "sg:website":"http://web.tin.it/gruppo_turistico_falcone",
    "wof:name":"Gruppo Turistico Falcone",
    "wof:placetype":"venue"
},
  "geometry": {"coordinates":[16.11105,41.837559],"type":"Point"}
}