{
  "type": "Feature",
  "properties": {
    "addr:full":"150, Viale Leonardo Da Vinci 20090 Trezzano Sul Naviglio Trezzano sul Naviglio Milano 20090",
    "addr:postcode":"20090;20090",
    "addr:street":"Viale Leonardo Da Vinci",
    "iso:country":"IT",
    "sg:address":"150, Viale Leonardo Da Vinci 20090 Trezzano Sul Naviglio",
    "sg:city":"Trezzano sul Naviglio",
    "sg:classifiers":[
        {
            "category":"Manufacturing",
            "subcategory":"Tools & Machinery",
            "type":"Manufacturing & Wholesale Goods"
        }
    ],
    "sg:phone":"+39 39024844931",
    "sg:postcode":"20090",
    "sg:province":"Milano",
    "sg:tags":[
        "environment",
        "equipment",
        "-"
    ],
    "wof:name":"Ciodue Estintori Srl",
    "wof:placetype":"venue"
},
  "geometry": {"coordinates":[9.058637,45.421318],"type":"Point"}
}