{
  "type": "Feature",
  "properties": {
    "iso:country":"IT",
    "sg:address":"10042 Nichelino",
    "sg:city":"Nichelino",
    "sg:orig_category":"Servizi E Lavori Per Edilizia E Lavori Pubblici",
    "sg:phone":"+39 011 605 6021",
    "sg:postcode":"10042",
    "sg:province":"Torino",
    "wof:name":"Essemme Ristrutturazioni Di Saccone Mario",
    "wof:placetype":"venue"
},
  "geometry": {"coordinates":[7.646835,45.002445],"type":"Point"}
}