{
  "type": "Feature",
  "properties": {
    "iso:country":"IT",
    "sg:address":"20017 Rho",
    "sg:city":"Rho",
    "sg:orig_category":"Prodotti Chimici Secondari. Materiali Edili",
    "sg:phone":"+39 02 932 0091",
    "sg:postcode":"20017",
    "sg:province":"Milano",
    "wof:name":"Strazza Giulio (s.p.a.)",
    "wof:placetype":"venue"
},
  "geometry": {"coordinates":[9.047451973,45.513507843],"type":"Point"}
}