{
  "type": "Feature",
  "properties": {
    "iso:country":"IT",
    "sg:address":"20013 Magenta",
    "sg:city":"Magenta",
    "sg:orig_category":"Lame Industriali",
    "sg:phone":"+39 02 9729 7217",
    "sg:postcode":"20013",
    "sg:province":"Milano",
    "wof:name":"Oldani & Portaluppi Srl",
    "wof:placetype":"venue"
},
  "geometry": {"coordinates":[8.88742,45.435925],"type":"Point"}
}