{
  "type": "Feature",
  "properties": {
    "iso:country":"IT",
    "sg:address":"06034 Foligno",
    "sg:city":"Colfiorito",
    "sg:orig_category":"Prodotti Alimentari",
    "sg:phone":"+39 0742 681421",
    "sg:postcode":"06034",
    "sg:province":"Perugia",
    "wof:name":"Caseificio Sociale Colfiorito",
    "wof:placetype":"venue"
},
  "geometry": {"coordinates":[12.8895559311,43.0276679993],"type":"Point"}
}