{
  "type": "Feature",
  "properties": {
    "iso:country":"IT",
    "sg:address":"12080 Roburent",
    "sg:city":"Roburent",
    "sg:orig_category":"Servizi Per Lo Sport E Il Tempo Libero. Servizi Al Turismo",
    "sg:phone":"+39 0174 227054",
    "sg:postcode":"12080",
    "sg:province":"Cuneo",
    "wof:name":"Robur Coop A.r.l.",
    "wof:placetype":"venue"
},
  "geometry": {"coordinates":[7.547111,44.388798],"type":"Point"}
}