{
  "type": "Feature",
  "properties": {
    "iso:country":"IT",
    "sg:address":"80141 Napoli",
    "sg:city":"Napoli",
    "sg:orig_category":"Cartotecnica E Servizi. Forniture Per Uffici",
    "sg:phone":"+39 081 751 0164",
    "sg:postcode":"80141",
    "sg:province":"Napoli",
    "wof:name":"Pelletteria Serretiello Claudio",
    "wof:placetype":"venue"
},
  "geometry": {"coordinates":[14.278638,40.864918],"type":"Point"}
}