{
  "type": "Feature",
  "properties": {
    "addr:full":"37, V. Grandi 48100 Ravenna Ravenna Ravenna 48100",
    "addr:housenumber":"37",
    "addr:postcode":"48100;48100",
    "addr:street":"V. Grandi",
    "iso:country":"IT",
    "sg:address":"37, V. Grandi 48100 Ravenna",
    "sg:city":"Ravenna",
    "sg:classifiers":[
        {
            "category":"Professional",
            "subcategory":"Engineering",
            "type":"Services"
        }
    ],
    "sg:phone":"+39 0544 451513",
    "sg:postcode":"48100",
    "sg:province":"Ravenna",
    "sg:tags":[
        "machine",
        "-",
        "mechanical"
    ],
    "sg:website":"http://www.dalcom.it",
    "wof:name":"Dalcom Srl",
    "wof:placetype":"venue"
},
  "geometry": {"coordinates":[12.211182,44.452049],"type":"Point"}
}