{
  "type": "Feature",
  "properties": {
    "iso:country":"IT",
    "sg:address":"16129 Genova",
    "sg:city":"Genova",
    "sg:orig_category":"Servizi Culturali E Per Lo Spettacolo. Cine-foto-ottica",
    "sg:phone":"+39 010 570 4374",
    "sg:postcode":"16129",
    "sg:province":"Genova",
    "wof:name":"Micro Media Srl",
    "wof:placetype":"venue"
},
  "geometry": {"coordinates":[8.950063,44.403984],"type":"Point"}
}