{
  "type": "Feature",
  "properties": {
    "addr:full":"20135 Milano Milano Milano 20135",
    "addr:postcode":"20135;20135",
    "iso:country":"IT",
    "sg:address":"20135 Milano",
    "sg:city":"Milano",
    "sg:orig_category":"Servizi Di Magazzinaggio E Movimentazione",
    "sg:phone":"+39 02 545 5840",
    "sg:postcode":"20135",
    "sg:province":"Milano",
    "sg:website":"http://www.dedosrl.it",
    "wof:name":"Dedo Srl",
    "wof:placetype":"venue"
},
  "geometry": {"coordinates":[9.149523,45.387794],"type":"Point"}
}