{
  "type": "Feature",
  "properties": {
    "addr:full":"1, Via S. Maria La Carita' 84018 Scafati Scafati Salerno 84018",
    "addr:postcode":"84018;84018",
    "addr:street":"Via S. Maria La Carita '",
    "iso:country":"IT",
    "sg:address":"1, Via S. Maria La Carita' 84018 Scafati",
    "sg:city":"Scafati",
    "sg:classifiers":[
        {
            "category":"Food & Beverages",
            "subcategory":"Groceries & Convenience Stores",
            "type":"Retail Goods"
        }
    ],
    "sg:phone":"+39 081 850 7222",
    "sg:postcode":"84018",
    "sg:province":"Salerno",
    "sg:tags":[
        "product",
        "related"
    ],
    "wof:name":"Ar Industrie Alimentari S.p.a.",
    "wof:placetype":"venue"
},
  "geometry": {"coordinates":[14.5255699158,40.7420959473],"type":"Point"}
}