{
  "type": "Feature",
  "properties": {
    "iso:country":"IT",
    "sg:address":"5, Via Galileo Galilei 28062 Cameri",
    "sg:city":"Cameri",
    "sg:classifiers":[
        {
            "category":"Shopping",
            "subcategory":"Crafts & Fabrics",
            "type":"Retail Goods"
        }
    ],
    "sg:phone":"+39 0321 518899",
    "sg:postcode":"28062",
    "sg:province":"Novara",
    "wof:name":"Bossi S.p.a.",
    "wof:placetype":"venue"
},
  "geometry": {"coordinates":[8.6713352203,45.5001296997],"type":"Point"}
}