{
  "type": "Feature",
  "properties": {
    "iso:country":"IT",
    "sg:address":"40121 Bologna",
    "sg:city":"Bologna",
    "sg:orig_category":"Marketing E Ricerche Di Mercato",
    "sg:phone":"+39 051 422 2001",
    "sg:postcode":"40121",
    "sg:province":"Bologna",
    "sg:website":"http://www.lqitalia.com",
    "wof:name":"L & Q Marketing E Comunicazione Srl",
    "wof:placetype":"venue"
},
  "geometry": {"coordinates":[11.374343,44.483585],"type":"Point"}
}