{
  "type": "Feature",
  "properties": {
    "iso:country":"IT",
    "sg:address":"71, Strada Maestra D'italia 31016 Cordignano",
    "sg:city":"Cordignano",
    "sg:orig_category":"Miscellaneous Products",
    "sg:phone":"+39 0438 992390",
    "sg:postcode":"31016",
    "sg:province":"Treviso",
    "wof:name":"Unitex S.r.l.",
    "wof:placetype":"venue"
},
  "geometry": {"coordinates":[12.4528865814,45.9430580139],"type":"Point"}
}