{
  "type": "Feature",
  "properties": {
    "iso:country":"IT",
    "sg:address":"31010 Mareno Di Piave",
    "sg:city":"Mareno di Piave",
    "sg:orig_category":"Forniture Alle Strutture Ricettive. Macchine E Impianti Per Attivita' Commerciali Ed Artigianali",
    "sg:phone":"+39 0438 492878",
    "sg:postcode":"31010",
    "sg:province":"Treviso",
    "wof:name":"Dal Tio Franco",
    "wof:placetype":"venue"
},
  "geometry": {"coordinates":[12.3347740173,45.8656806946],"type":"Point"}
}