{
  "type": "Feature",
  "properties": {
    "iso:country":"IT",
    "sg:address":"Via Croce 36050 Gambugliano",
    "sg:city":"Gambugliano",
    "sg:classifiers":[
        {
            "category":"Wholesale",
            "subcategory":"Vending Machines",
            "type":"Manufacturing & Wholesale Goods"
        }
    ],
    "sg:phone":"+39 0444 295111",
    "sg:postcode":"36050",
    "sg:province":"Vicenza",
    "sg:tags":[
        "three-phase",
        "motor"
    ],
    "wof:name":"Emg Elettromeccanica Srl",
    "wof:placetype":"venue"
},
  "geometry": {"coordinates":[11.498013,45.602318],"type":"Point"}
}