{
  "type": "Feature",
  "properties": {
    "addr:full":"42010 Arceto Reggio Nell'Emilia 42010",
    "addr:postcode":"42010;42010",
    "iso:country":"IT",
    "sg:address":"42010 Arceto",
    "sg:orig_category":"Attrezzature E Forniture Per Officine Riparazione E Servizi Ausiliari",
    "sg:phone":"+39 0522 980143",
    "sg:postcode":"42010",
    "sg:province":"Reggio Nell'Emilia",
    "wof:name":"Gibel Snc",
    "wof:placetype":"venue"
},
  "geometry": {"coordinates":[10.718665,44.621517],"type":"Point"}
}