{
  "type": "Feature",
  "properties": {
    "iso:country":"IT",
    "sg:address":"7, Via Europa 21040 Morazzone",
    "sg:city":"Morazzone",
    "sg:classifiers":[
        {
            "category":"Professional",
            "subcategory":"Engineering",
            "type":"Services"
        }
    ],
    "sg:phone":"+39 0332 461392",
    "sg:postcode":"21040",
    "sg:province":"Varese",
    "sg:tags":[
        "machine",
        "-",
        "mechanical"
    ],
    "wof:name":"Comeplast Di Cecchinato Ettore & C. S.n.c.",
    "wof:placetype":"venue"
},
  "geometry": {"coordinates":[8.835301,45.760658],"type":"Point"}
}