{
  "type": "Feature",
  "properties": {
    "iso:country":"IT",
    "sg:address":"00155 Roma",
    "sg:city":"Roma",
    "sg:orig_category":"Abbigliamento Esterno, Maglierie E Pelliccerie. Shopping",
    "sg:phone":"+39 06 2275 5252",
    "sg:postcode":"00155",
    "sg:province":"Roma",
    "wof:name":"Vivaldi Srl",
    "wof:placetype":"venue"
},
  "geometry": {"coordinates":[12.884376,41.889793],"type":"Point"}
}