{
  "type": "Feature",
  "properties": {
    "iso:country":"IT",
    "sg:address":"09012 Capoterra",
    "sg:city":"Capoterra",
    "sg:orig_category":"Servizi Per Lo Sport E Il Tempo Libero. Servizi Al Turismo. Servizi Ausiliari Dei Mezzi Di Trasporto. Servizi Ausiliari Per Il Trasporto",
    "sg:phone":"+39 070 720218",
    "sg:postcode":"09012",
    "sg:province":"Cagliari",
    "sg:website":"http://www.tourbaire.com",
    "wof:name":"Tour Baire Snc",
    "wof:placetype":"venue"
},
  "geometry": {"coordinates":[9.01576,39.1502],"type":"Point"}
}