{
  "type": "Feature",
  "properties": {
    "addr:full":"55016 Porcari Porcari Lucca 55016",
    "addr:postcode":"55016;55016",
    "iso:country":"IT",
    "sg:address":"55016 Porcari",
    "sg:city":"Porcari",
    "sg:orig_category":"Scuole E Servizi Scolastici. Servizi Vari Di Interesse Pubblico",
    "sg:phone":"+39 0583 29284",
    "sg:postcode":"55016",
    "sg:province":"Lucca",
    "wof:name":"Cooperativa Insieme Nella Scuola & Dintorni",
    "wof:placetype":"venue"
},
  "geometry": {"coordinates":[10.339598,43.8703],"type":"Point"}
}