{
  "type": "Feature",
  "properties": {
    "iso:country":"IT",
    "sg:address":"60, Via Iv Novembre 23891 Barzano'",
    "sg:classifiers":[
        {
            "category":"Shopping",
            "type":"Retail Goods"
        }
    ],
    "sg:phone":"+39 039 921 1731",
    "sg:postcode":"23891",
    "sg:province":"Lecco",
    "sg:tags":[
        "finished",
        "-",
        "metallic"
    ],
    "wof:name":"Mas Project Due Srl",
    "wof:placetype":"venue"
},
  "geometry": {"coordinates":[9.3900709152,45.8529815674],"type":"Point"}
}