{
  "type": "Feature",
  "properties": {
    "iso:country":"IT",
    "sg:address":"20093 Cologno Monzese",
    "sg:city":"Cologno Monzese",
    "sg:orig_category":"Prodotti Chimici Di Base. Forniture Per Attivita' Industriali",
    "sg:phone":"+39 02 254 3848",
    "sg:postcode":"20093",
    "sg:province":"Milano",
    "wof:name":"Bz - Eurocolor Di Massimo X. & Bozzetti A.maria & C. (s.a.s.)",
    "wof:placetype":"venue"
},
  "geometry": {"coordinates":[9.2648620605,45.534942627],"type":"Point"}
}