{
  "type": "Feature",
  "properties": {
    "iso:country":"IT",
    "sg:address":"20122 Milano",
    "sg:city":"Milano",
    "sg:orig_category":"Abbigliamento Intimo, Calze E Costumi Da Bagno. Articoli Medico-sanitari Ed Ortopedici",
    "sg:phone":"+39 02 7600 3494",
    "sg:postcode":"20122",
    "sg:province":"Milano",
    "wof:name":"Margherita Di Corti F. & C. Sas",
    "wof:placetype":"venue"
},
  "geometry": {"coordinates":[9.196948,45.464809],"type":"Point"}
}