{
  "type": "Feature",
  "properties": {
    "iso:country":"IT",
    "sg:address":"36030 Fara Vicentino",
    "sg:city":"Fara Vicentino",
    "sg:orig_category":"Maglieria - Produzione E Ingrosso",
    "sg:phone":"+39 0445 897431",
    "sg:postcode":"36030",
    "sg:province":"Vicenza",
    "wof:name":"F.lli Borin Snc Di Borin Luca & C.",
    "wof:placetype":"venue"
},
  "geometry": {"coordinates":[11.542616,45.729134],"type":"Point"}
}