{
  "type": "Feature",
  "properties": {
    "iso:country":"IT",
    "sg:address":"Via Boccaccio 73010 Arnesano",
    "sg:city":"Arnesano",
    "sg:classifiers":[
        {
            "category":"Shopping",
            "subcategory":"Clothing, Apparel, & Fashions",
            "type":"Retail Goods"
        }
    ],
    "sg:phone":"+39 0832 324247",
    "sg:postcode":"73010",
    "sg:province":"Lecce",
    "sg:tags":[
        "clothes"
    ],
    "wof:name":"Euroconfezioni Srl",
    "wof:placetype":"venue"
},
  "geometry": {"coordinates":[18.092243,40.347176],"type":"Point"}
}