{
  "type": "Feature",
  "properties": {
    "iso:country":"IT",
    "sg:address":"25013 Carpenedolo",
    "sg:city":"Carpenedolo",
    "sg:orig_category":"Abbigliamento Esterno, Maglierie E Pelliccerie",
    "sg:phone":"+39 030 969 8145",
    "sg:postcode":"25013",
    "sg:province":"Brescia",
    "sg:website":"http://www.ma-ber.it",
    "wof:name":"Maglificio Ma.ber",
    "wof:placetype":"venue"
},
  "geometry": {"coordinates":[10.424191,45.341812],"type":"Point"}
}