{
  "type": "Feature",
  "properties": {
    "iso:country":"IT",
    "sg:address":"Str. Nazionale Per Carpi 1591 41010 Ganaceto",
    "sg:classifiers":[
        {
            "category":"Organizations",
            "subcategory":"Non-profit Organization",
            "type":"Services"
        }
    ],
    "sg:phone":"+39 059 386012",
    "sg:postcode":"41010",
    "sg:province":"Modena",
    "sg:tags":[
        "hospital",
        "waste",
        "system",
        "incineration"
    ],
    "sg:website":"www.ciroldi.it",
    "wof:name":"Ciroldi Spa",
    "wof:placetype":"venue"
},
  "geometry": {"coordinates":[10.8997,44.709724],"type":"Point"}
}