{
  "type": "Feature",
  "properties": {
    "iso:country":"IT",
    "sg:address":"Sda Antica Di Grugliasco, 114/116 10095 Grugliasco",
    "sg:city":"Grugliasco",
    "sg:classifiers":[
        {
            "category":"Health Services",
            "subcategory":"Nursing And Care Facility",
            "type":"Services"
        }
    ],
    "sg:phone":"+39 011 770 5770",
    "sg:postcode":"10095",
    "sg:province":"Torino",
    "sg:tags":[
        "electro-medical",
        "apparatus"
    ],
    "sg:website":"www.lorenzatto.com",
    "wof:name":"Mg Lorenzatto Spa",
    "wof:placetype":"venue"
},
  "geometry": {"coordinates":[7.686619,45.07056],"type":"Point"}
}