{
  "type": "Feature",
  "properties": {
    "addr:full":"37060 Caselle Di Sommacampagna Verona 37060",
    "addr:postcode":"37060;37060",
    "iso:country":"IT",
    "sg:address":"37060 Caselle Di Sommacampagna",
    "sg:orig_category":"Automazione E Macchine Per Ufficio",
    "sg:phone":"+39 045 858 1474",
    "sg:postcode":"37060",
    "sg:province":"Verona",
    "wof:name":"Menini Gianni",
    "wof:placetype":"venue"
},
  "geometry": {"coordinates":[10.897579,45.416161],"type":"Point"}
}