{
  "type": "Feature",
  "properties": {
    "addr:full":"Ctr. Boscopiano Str. Prov. 68 Km. 1 97019 Vittoria Vittoria Ragusa 97019",
    "addr:housenumber":"68",
    "addr:postcode":"97019;97019",
    "addr:street":"Str. Prov.;Km. 1",
    "iso:country":"IT",
    "sg:address":"Ctr. Boscopiano Str. Prov. 68 Km. 1 97019 Vittoria",
    "sg:city":"Vittoria",
    "sg:classifiers":[
        {
            "category":"Food & Beverages",
            "subcategory":"Fruits & Vegetables",
            "type":"Retail Goods"
        }
    ],
    "sg:phone":"+39 0932 861058",
    "sg:postcode":"97019",
    "sg:province":"Ragusa",
    "wof:name":"Nuova Linea Verde Soc. Coop. A R.l.",
    "wof:placetype":"venue"
},
  "geometry": {"coordinates":[14.7285032272,36.9259109497],"type":"Point"}
}