{
  "type": "Feature",
  "properties": {
    "addr:full":"25011 Calcinato Calcinato Brescia 25011",
    "addr:postcode":"25011;25011",
    "iso:country":"IT",
    "sg:address":"25011 Calcinato",
    "sg:city":"Calcinato",
    "sg:orig_category":"Prodotti E Manufatti In Materie Plastiche",
    "sg:phone":"+39 030 996 9168",
    "sg:postcode":"25011",
    "sg:province":"Brescia",
    "wof:name":"Rossetti Umberto",
    "wof:placetype":"venue"
},
  "geometry": {"coordinates":[10.3956031799,45.4584960938],"type":"Point"}
}