{
  "type": "Feature",
  "properties": {
    "iso:country":"IT",
    "sg:address":"34170 Gorizia",
    "sg:city":"Gorizia",
    "sg:orig_category":"Ferramenta - Ingrosso",
    "sg:phone":"+39 0481 535024",
    "sg:postcode":"34170",
    "sg:province":"Gorizia",
    "wof:name":"Fratelli Cantarin Srl",
    "wof:placetype":"venue"
},
  "geometry": {"coordinates":[13.6302928925,45.9478912354],"type":"Point"}
}