{
  "type": "Feature",
  "properties": {
    "iso:country":"IT",
    "sg:address":"00196 Roma",
    "sg:city":"Roma",
    "sg:orig_category":"Articoli Da Regalo. Tempo Libero - Articoli E Forniture. Regalistica Aziendale",
    "sg:phone":"+39 06 8069 2629",
    "sg:postcode":"00196",
    "sg:province":"Roma",
    "wof:name":"Diemme Premiazione Srl",
    "wof:placetype":"venue"
},
  "geometry": {"coordinates":[12.379804,42.076591],"type":"Point"}
}