{
  "type": "Feature",
  "properties": {
    "iso:country":"IT",
    "sg:address":"20092 Cinisello Balsamo",
    "sg:city":"Cinisello Balsamo",
    "sg:orig_category":"Macchine Utensili E Impianti",
    "sg:phone":"+39 02 617 5465",
    "sg:postcode":"20092",
    "sg:province":"Milano",
    "wof:name":"Nuova Tecnolapping Snc",
    "wof:placetype":"venue"
},
  "geometry": {"coordinates":[9.216151,45.567028],"type":"Point"}
}