{
  "type": "Feature",
  "properties": {
    "iso:country":"IT",
    "sg:address":"00048 Nettuno",
    "sg:city":"Nettuno",
    "sg:orig_category":"Scuole E Servizi Scolastici",
    "sg:phone":"+39 06 988 0902",
    "sg:postcode":"00048",
    "sg:province":"Roma",
    "wof:name":"Istituto Parificato =s. Lucia Dei Filippini=",
    "wof:placetype":"venue"
},
  "geometry": {"coordinates":[12.641094,42.032528],"type":"Point"}
}