{
  "type": "Feature",
  "properties": {
    "iso:country":"IT",
    "sg:address":"62019 Recanati",
    "sg:city":"Recanati",
    "sg:orig_category":"Prodotti Vari In Metallo. Articoli Per Imballaggio E Confezionamento",
    "sg:phone":"+39 071 757 0664",
    "sg:postcode":"62019",
    "sg:province":"Macerata",
    "wof:name":"Ecogest Srl",
    "wof:placetype":"venue"
},
  "geometry": {"coordinates":[13.566860199,43.4085235596],"type":"Point"}
}