{
  "type": "Feature",
  "properties": {
    "addr:full":"70126 Bari Bari Bari 70126",
    "addr:postcode":"70126;70126",
    "iso:country":"IT",
    "sg:address":"70126 Bari",
    "sg:city":"Bari",
    "sg:orig_category":"Pubblicita', Marketing E Comunicazione",
    "sg:phone":"+39 080 553 1133",
    "sg:postcode":"70126",
    "sg:province":"Bari",
    "sg:website":"http://www.synergocenter.com",
    "wof:name":"Aet Srl",
    "wof:placetype":"venue"
},
  "geometry": {"coordinates":[16.9181537628,41.0904960632],"type":"Point"}
}