{
  "type": "Feature",
  "properties": {
    "addr:full":"23, Viale Europa 46019 Viadana Viadana Mantova 46019",
    "addr:housenumber":"23",
    "addr:postcode":"46019;46019",
    "addr:street":"Viale Europa",
    "iso:country":"IT",
    "sg:address":"23, Viale Europa 46019 Viadana",
    "sg:city":"Viadana",
    "sg:orig_category":"Miscellaneous Products",
    "sg:phone":"+39 0375 780203",
    "sg:postcode":"46019",
    "sg:province":"Mantova",
    "wof:name":"Arix (s.p.a.)",
    "wof:placetype":"venue"
},
  "geometry": {"coordinates":[10.5007362366,44.9317054749],"type":"Point"}
}