{
  "type": "Feature",
  "properties": {
    "iso:country":"IT",
    "sg:address":"66, Via Puia 33080 Prata Di Pordenone",
    "sg:city":"Prata di Pordenone",
    "sg:classifiers":[
        {
            "category":"Wholesale",
            "subcategory":"Drugs",
            "type":"Manufacturing & Wholesale Goods"
        }
    ],
    "sg:phone":"+39 0434 620620",
    "sg:postcode":"33080",
    "sg:province":"Pordenone",
    "sg:tags":[
        "chemical",
        "pharmaceutical"
    ],
    "wof:name":"Solvepi (s.p.a.)",
    "wof:placetype":"venue"
},
  "geometry": {"coordinates":[12.560739,45.885666],"type":"Point"}
}