{
  "type": "Feature",
  "properties": {
    "iso:country":"IT",
    "sg:address":"37, Via Rubicone 48100 Ravenna",
    "sg:city":"Ravenna",
    "sg:classifiers":[
        {
            "category":"Sports & Exercise",
            "subcategory":"Playing Field",
            "type":"Entertainment"
        }
    ],
    "sg:phone":"+39 39054463422",
    "sg:postcode":"48100",
    "sg:province":"Ravenna",
    "sg:tags":[
        "game"
    ],
    "wof:name":"Erregi Di Re Giorgio",
    "wof:placetype":"venue"
},
  "geometry": {"coordinates":[12.308823,44.292107],"type":"Point"}
}