{
  "type": "Feature",
  "properties": {
    "addr:full":"20037 Paderno Dugnano Paderno Dugnano Milano 20037",
    "addr:postcode":"20037;20037",
    "iso:country":"IT",
    "sg:address":"20037 Paderno Dugnano",
    "sg:city":"Paderno Dugnano",
    "sg:orig_category":"Abrasivi",
    "sg:phone":"+39 02 9182 1001",
    "sg:postcode":"20037",
    "sg:province":"Milano",
    "wof:name":"S.l.f. Abrasivi Srl",
    "wof:placetype":"venue"
},
  "geometry": {"coordinates":[9.181722,45.562313],"type":"Point"}
}