{
  "type": "Feature",
  "properties": {
    "addr:full":"Via Fratelli Rosselli 1/a; Ozieri; 07014 Ozieri Sassari 07014",
    "addr:housenumber":"1 / a",
    "addr:postcode":"07014;07014",
    "addr:street":"Via Fratelli Rosselli;Ozieri",
    "iso:country":"IT",
    "sg:address":"Via Fratelli Rosselli 1/a; Ozieri; 07014",
    "sg:city":"Ozieri",
    "sg:classifiers":[
        {
            "category":"Banks & Credit Unions",
            "subcategory":"Bank",
            "type":"Services"
        }
    ],
    "sg:phone":"+39 079 787541",
    "sg:postcode":"07014",
    "sg:province":"Sassari",
    "wof:name":"Banca Nazionale Del Lavoro Spa",
    "wof:placetype":"venue"
},
  "geometry": {"coordinates":[8.999486,40.58765],"type":"Point"}
}