{
  "type": "Feature",
  "properties": {
    "iso:country":"IT",
    "sg:address":"84131 Salerno",
    "sg:city":"Salerno",
    "sg:orig_category":"Prodotti Di Base E Forniture Per Industria Alimentare E Bevande. Carta, Cartone E Prodotti Primari. Forniture Per Attivita' Commerciali Ed Artigianali",
    "sg:phone":"+39 089 301277",
    "sg:postcode":"84131",
    "sg:province":"Salerno",
    "wof:name":"Carpino Cart Srl",
    "wof:placetype":"venue"
},
  "geometry": {"coordinates":[14.8471956253,40.6421470642],"type":"Point"}
}