{
  "type": "Feature",
  "properties": {
    "iso:country":"IT",
    "sg:address":"20094 Corsico",
    "sg:city":"Corsico",
    "sg:orig_category":"Forniture Per Abbigliamento E Pelletterie",
    "sg:phone":"+39 02 449 1189",
    "sg:postcode":"20094",
    "sg:province":"Milano",
    "wof:name":"Con.mar. S.a.s",
    "wof:placetype":"venue"
},
  "geometry": {"coordinates":[9.1132879257,45.4340896606],"type":"Point"}
}