{
  "type": "Feature",
  "properties": {
    "iso:country":"IT",
    "sg:address":"00161 Roma",
    "sg:city":"Roma",
    "sg:orig_category":"Servizi E Lavori Per Industria Alimentare E Bevande",
    "sg:phone":"+39 06 4424 3604",
    "sg:postcode":"00161",
    "sg:province":"Roma",
    "wof:name":"Galante Ivo",
    "wof:placetype":"venue"
},
  "geometry": {"coordinates":[12.519538,41.90979],"type":"Point"}
}