{
  "type": "Feature",
  "properties": {
    "addr:full":"Via Plutarco 12 20145 Milano Milano Milano 20145",
    "addr:housenumber":"12",
    "addr:postcode":"20145;20145",
    "addr:street":"Via Plutarco",
    "iso:country":"IT",
    "sg:address":"Via Plutarco 12 20145 Milano",
    "sg:city":"Milano",
    "sg:classifiers":[
        {
            "category":"Structure",
            "subcategory":"Public Building",
            "type":"Public Place"
        }
    ],
    "sg:phone":"+39 02 498 1802",
    "sg:postcode":"20145",
    "sg:province":"Milano",
    "sg:tags":[
        "sector",
        "buildings",
        "turnkey"
    ],
    "wof:name":"L'impresa La Casa Costruzioni Srl",
    "wof:placetype":"venue"
},
  "geometry": {"coordinates":[9.1574773788,45.4749107361],"type":"Point"}
}