{
  "type": "Feature",
  "properties": {
    "addr:full":"Viale Del Lavoro 22/i 37036 San Martino Buon Albergo San Martino Buon Albergo Verona 37036",
    "addr:housenumber":"22 / i",
    "addr:postcode":"37036;buon albergo;37036",
    "addr:street":"Viale Del Lavoro",
    "iso:country":"IT",
    "sg:address":"Viale Del Lavoro 22/i 37036 San Martino Buon Albergo",
    "sg:city":"San Martino Buon Albergo",
    "sg:classifiers":[
        {
            "category":"Personal",
            "subcategory":"Shoe Repair & Shine",
            "type":"Services"
        }
    ],
    "sg:phone":"+39 045 878 0393",
    "sg:postcode":"37036",
    "sg:province":"Verona",
    "sg:tags":[
        "health"
    ],
    "sg:website":"www.awonline.net",
    "wof:name":"Awo Di Adamoli Pietro & C. Snc",
    "wof:placetype":"venue"
},
  "geometry": {"coordinates":[11.093755,45.415127],"type":"Point"}
}