{
  "type": "Feature",
  "properties": {
    "addr:full":"20125 Milano Milano Milano 20125",
    "addr:postcode":"20125;20125",
    "iso:country":"IT",
    "sg:address":"20125 Milano",
    "sg:city":"Milano",
    "sg:orig_category":"Arredamenti E Mobili Professionali. Arredi Ed Attrezzature Per Uffici",
    "sg:phone":"+39 02 6707 8350",
    "sg:postcode":"20125",
    "sg:province":"Milano",
    "sg:website":"http://www.gestioneservizi.it",
    "wof:name":"Gestione Servizi Srl",
    "wof:placetype":"venue"
},
  "geometry": {"coordinates":[9.201308,45.495026],"type":"Point"}
}