{
  "type": "Feature",
  "properties": {
    "addr:full":"Via Dell'artigiano 2 40055 Villanova Villanova Bologna 40055",
    "addr:housenumber":"2",
    "addr:postcode":"40055;40055",
    "addr:street":"Via Dell'Artigiano",
    "iso:country":"IT",
    "sg:address":"Via Dell'artigiano 2 40055 Villanova",
    "sg:city":"Villanova",
    "sg:classifiers":[
        {
            "category":"Food & Beverages",
            "subcategory":"Fruits & Vegetables",
            "type":"Retail Goods"
        }
    ],
    "sg:phone":"+39 051 780101",
    "sg:postcode":"40055",
    "sg:province":"Bologna",
    "sg:tags":[
        "machine",
        "packing"
    ],
    "sg:website":"www.tecnomeccanica.bo.it",
    "wof:name":"Tecnomeccanica Srl",
    "wof:placetype":"venue"
},
  "geometry": {"coordinates":[11.4352693558,44.5026359558],"type":"Point"}
}