{
  "type": "Feature",
  "properties": {
    "addr:full":"70019 Triggiano Triggiano Bari 70019",
    "addr:postcode":"70019;70019",
    "iso:country":"IT",
    "sg:address":"70019 Triggiano",
    "sg:city":"Triggiano",
    "sg:orig_category":"Pubblica Amministrazione",
    "sg:phone":"+39 080 468 7880",
    "sg:postcode":"70019",
    "sg:province":"Bari",
    "wof:name":"Carabinieri",
    "wof:placetype":"venue"
},
  "geometry": {"coordinates":[16.9303627014,41.0704574585],"type":"Point"}
}