{
  "type": "Feature",
  "properties": {
    "iso:country":"IT",
    "sg:address":"20038 Seregno",
    "sg:city":"Seregno",
    "sg:orig_category":"Servizi E Lavori Per Arredamento E Industria Del Legno",
    "sg:phone":"+39 036 223 1262",
    "sg:postcode":"20038",
    "sg:province":"Milano",
    "wof:name":"Pellucchi Giuseppe Dei F.lli Pellucchi & C. (s.n.c.)",
    "wof:placetype":"venue"
},
  "geometry": {"coordinates":[9.206349,45.482071],"type":"Point"}
}