{
  "type": "Feature",
  "properties": {
    "addr:full":"46, Via Cairoli 27030 Ottobiano Ottobiano Pavia 27030",
    "addr:postcode":"27030;27030",
    "addr:street":"Via Cairoli",
    "iso:country":"IT",
    "sg:address":"46, Via Cairoli 27030 Ottobiano",
    "sg:city":"Ottobiano",
    "sg:classifiers":[
        {
            "category":"Professional",
            "subcategory":"Engineering",
            "type":"Services"
        }
    ],
    "sg:phone":"+39 39038449544",
    "sg:postcode":"27030",
    "sg:province":"Pavia",
    "sg:tags":[
        "machine",
        "-",
        "mechanical"
    ],
    "wof:name":"Officina Meccanica Forest S.r.l",
    "wof:placetype":"venue"
},
  "geometry": {"coordinates":[8.83436,45.157833],"type":"Point"}
}