{
  "type": "Feature",
  "properties": {
    "addr:full":"00141 Roma Roma Roma 00141",
    "addr:postcode":"00141;00141",
    "iso:country":"IT",
    "sg:address":"00141 Roma",
    "sg:city":"Roma",
    "sg:orig_category":"Abbigliamento Esterno, Maglierie E Pelliccerie",
    "sg:phone":"+39 06 886 3230",
    "sg:postcode":"00141",
    "sg:province":"Roma",
    "wof:name":"Valeriani Anna Maria",
    "wof:placetype":"venue"
},
  "geometry": {"coordinates":[12.517293,41.943409],"type":"Point"}
}