{
  "type": "Feature",
  "properties": {
    "iso:country":"IT",
    "sg:address":"20144 Milano",
    "sg:city":"Milano",
    "sg:orig_category":"Servizi Editoriali. Pubblicita', Marketing E Comunicazione",
    "sg:phone":"+39 02 439 0952",
    "sg:postcode":"20144",
    "sg:province":"Milano",
    "wof:name":"Studio Essecivi S.r.l.",
    "wof:placetype":"venue"
},
  "geometry": {"coordinates":[9.163907,45.459324],"type":"Point"}
}