{
  "type": "Feature",
  "properties": {
    "iso:country":"IT",
    "sg:address":"Via Del Lavoro 37067 Valeggio Sul Mincio",
    "sg:city":"Valeggio sul Mincio",
    "sg:classifiers":[
        {
            "category":"Home & Garden",
            "subcategory":"Home Furnishings",
            "type":"Retail Goods"
        }
    ],
    "sg:phone":"+39 045 637 1110",
    "sg:postcode":"37067",
    "sg:province":"Verona",
    "sg:tags":[
        "household"
    ],
    "wof:name":"La Fablier S.p.a.",
    "wof:placetype":"venue"
},
  "geometry": {"coordinates":[10.74573,45.337223],"type":"Point"}
}