{
  "type": "Feature",
  "properties": {
    "addr:full":"28100 Novara Novara Novara 28100",
    "addr:postcode":"28100;28100",
    "iso:country":"IT",
    "sg:address":"28100 Novara",
    "sg:city":"Novara",
    "sg:orig_category":"Forniture Per Abbigliamento E Pelletterie",
    "sg:phone":"+39 0321 628181",
    "sg:postcode":"28100",
    "sg:province":"Novara",
    "wof:name":"Settembri Srl",
    "wof:placetype":"venue"
},
  "geometry": {"coordinates":[8.6248607635,45.4496803284],"type":"Point"}
}