{
  "type": "Feature",
  "properties": {
    "iso:country":"IT",
    "sg:address":"2, Via Luigi Galvani 22070 Luisago",
    "sg:city":"Luisago",
    "sg:classifiers":[
        {
            "category":"Autos & Motor Vehicles",
            "subcategory":"Boat Sales",
            "type":"Retail Goods"
        }
    ],
    "sg:phone":"+39 39031889866",
    "sg:postcode":"22070",
    "sg:province":"Como",
    "wof:name":"Marlin Boat (s.r.l.)",
    "wof:placetype":"venue"
},
  "geometry": {"coordinates":[9.038338,45.761734],"type":"Point"}
}