{
  "type": "Feature",
  "properties": {
    "addr:full":"90141 Palermo Palermo Palermo 90141",
    "addr:postcode":"90141;90141",
    "iso:country":"IT",
    "sg:address":"90141 Palermo",
    "sg:city":"Palermo",
    "sg:orig_category":"Forniture Per Attivita' Commerciali Ed Artigianali",
    "sg:phone":"+39 091 301906",
    "sg:postcode":"90141",
    "sg:province":"Palermo",
    "wof:name":"Centro Targhe Di Luparello Vincenzo",
    "wof:placetype":"venue"
},
  "geometry": {"coordinates":[13.3462553024,38.1282196045],"type":"Point"}
}