{
  "type": "Feature",
  "properties": {
    "addr:full":"7, Localita' Campagna 32027 Taibon Agordino Taibon Agordino Belluno 32027",
    "addr:postcode":"32027;32027",
    "addr:street":"Localita ' Campagna;Agordino;Agordino",
    "iso:country":"IT",
    "sg:address":"7, Localita' Campagna 32027 Taibon Agordino",
    "sg:city":"Taibon Agordino",
    "sg:classifiers":[
        {
            "category":"Wholesale",
            "subcategory":"Medical Equipment & Supplies",
            "type":"Manufacturing & Wholesale Goods"
        }
    ],
    "sg:phone":"+39 0437 660650",
    "sg:postcode":"32027",
    "sg:province":"Belluno",
    "sg:tags":[
        "-",
        "health",
        "instrument"
    ],
    "wof:name":"Cosmos Di Forcella Cosmo & C. S.n.c.",
    "wof:placetype":"venue"
},
  "geometry": {"coordinates":[12.016109,46.294273],"type":"Point"}
}