{
  "type": "Feature",
  "properties": {
    "iso:country":"IT",
    "sg:address":"28100 Novara",
    "sg:city":"Novara",
    "sg:orig_category":"Petroli, Gas E Combustibili",
    "sg:phone":"+39 0321 625074",
    "sg:postcode":"28100",
    "sg:province":"Novara",
    "wof:name":"Rossari Roberto Sas",
    "wof:placetype":"venue"
},
  "geometry": {"coordinates":[8.6062116623,45.4419593811],"type":"Point"}
}