{
  "type": "Feature",
  "properties": {
    "iso:country":"IT",
    "sg:address":"00179 Roma",
    "sg:city":"Roma",
    "sg:classifiers":[
        {
            "category":"Home & Garden",
            "subcategory":"Home Furnishings",
            "type":"Retail Goods"
        }
    ],
    "sg:phone":"+39 06 7834 7333",
    "sg:postcode":"00179",
    "sg:province":"Roma",
    "sg:tags":[
        "bathroom",
        "accessories"
    ],
    "wof:name":"Teorema Tre Srl",
    "wof:placetype":"venue"
},
  "geometry": {"coordinates":[12.5780220032,41.8090896606],"type":"Point"}
}