{
  "type": "Feature",
  "properties": {
    "iso:country":"IT",
    "sg:address":"20067 Tribiano",
    "sg:city":"Tribiano",
    "sg:orig_category":"Prodotti E Manufatti In Materie Plastiche",
    "sg:phone":"+39 02 9063 2302",
    "sg:postcode":"20067",
    "sg:province":"Milano",
    "wof:name":"Banchieri S.r.l.",
    "wof:placetype":"venue"
},
  "geometry": {"coordinates":[9.3617582321,45.3697967529],"type":"Point"}
}