{
  "type": "Feature",
  "properties": {
    "iso:country":"IT",
    "sg:address":"Corso Vercelli N 332/p 10015 Ivrea",
    "sg:city":"Ivrea",
    "sg:classifiers":[
        {
            "category":"Wholesale",
            "subcategory":"Plants",
            "type":"Manufacturing & Wholesale Goods"
        }
    ],
    "sg:phone":"+39 0125 615350",
    "sg:postcode":"10015",
    "sg:province":"Torino",
    "sg:tags":[
        "machine",
        "industrial",
        "automation"
    ],
    "sg:website":"users.libero.it/ipr/",
    "wof:name":"Ipr Systems Srl",
    "wof:placetype":"venue"
},
  "geometry": {"coordinates":[7.904559,45.469173],"type":"Point"}
}