{
  "type": "Feature",
  "properties": {
    "addr:full":"41, Via Silvio Colli 13811 Andorno Micca Andorno Micca Biella 13811",
    "addr:postcode":"13811;13811",
    "addr:street":"Via Silvio",
    "iso:country":"IT",
    "sg:address":"41, Via Silvio Colli 13811 Andorno Micca",
    "sg:city":"Andorno Micca",
    "sg:classifiers":[
        {
            "category":"Shopping",
            "subcategory":"Crafts & Fabrics",
            "type":"Retail Goods"
        }
    ],
    "sg:phone":"+39 39015473518",
    "sg:postcode":"13811",
    "sg:province":"Biella",
    "wof:name":"Finital S.r.l.",
    "wof:placetype":"venue"
},
  "geometry": {"coordinates":[8.0553455353,45.6014022827],"type":"Point"}
}