{
  "type": "Feature",
  "properties": {
    "iso:country":"IT",
    "sg:address":"47, Via Cairoli Fratelli 20038 Seregno",
    "sg:city":"Seregno",
    "sg:classifiers":[
        {
            "category":"Manufacturing",
            "subcategory":"Tools & Machinery",
            "type":"Manufacturing & Wholesale Goods"
        }
    ],
    "sg:phone":"+39 036 232 6603",
    "sg:postcode":"20038",
    "sg:province":"Milano",
    "sg:tags":[
        "environment",
        "equipment",
        "-"
    ],
    "wof:name":"Depuratori Detroit Srl",
    "wof:placetype":"venue"
},
  "geometry": {"coordinates":[9.188141,45.463688],"type":"Point"}
}