{
  "type": "Feature",
  "properties": {
    "addr:full":"56, Via Cilavegna 27020 Gravellona Lomellina Gravellona Lomellina Pavia 27020",
    "addr:postcode":"27020;27020",
    "addr:street":"Via Cilavegna;Lomellina",
    "iso:country":"IT",
    "sg:address":"56, Via Cilavegna 27020 Gravellona Lomellina",
    "sg:city":"Gravellona Lomellina",
    "sg:classifiers":[
        {
            "category":"Shopping",
            "subcategory":"Clothing, Apparel, & Fashions",
            "type":"Retail Goods"
        }
    ],
    "sg:phone":"+39 0381 650123",
    "sg:postcode":"27020",
    "sg:province":"Pavia",
    "sg:tags":[
        "clothes"
    ],
    "wof:name":"Master (s.r.l.)",
    "wof:placetype":"venue"
},
  "geometry": {"coordinates":[9.156563,45.185886],"type":"Point"}
}