{
  "type": "Feature",
  "properties": {
    "iso:country":"IT",
    "sg:address":"15048 Valenza",
    "sg:city":"Valenza",
    "sg:orig_category":"Gioielleria, Oreficeria E Argenteria",
    "sg:phone":"+39 0131 942021",
    "sg:postcode":"15048",
    "sg:province":"Alessandria",
    "wof:name":"Boris Giuseppe",
    "wof:placetype":"venue"
},
  "geometry": {"coordinates":[8.636843,45.009594],"type":"Point"}
}