{
  "type": "Feature",
  "properties": {
    "iso:country":"IT",
    "sg:address":"98122 Messina",
    "sg:city":"Messina",
    "sg:orig_category":"Apparecchiature E Sistemi Per Magazzinaggio E Movimentazione",
    "sg:phone":"+39 090 718327",
    "sg:postcode":"98122",
    "sg:province":"Messina",
    "wof:name":"Euro Messana Di Sciarrone Serafino",
    "wof:placetype":"venue"
},
  "geometry": {"coordinates":[15.555308,38.188217],"type":"Point"}
}