{
  "type": "Feature",
  "properties": {
    "iso:country":"IT",
    "sg:address":"20090 Cusago",
    "sg:city":"Cusago",
    "sg:orig_category":"Macchine Utensili - Attrezzature E Accessori",
    "sg:phone":"+39 02 901 9943",
    "sg:postcode":"20090",
    "sg:province":"Milano",
    "wof:name":"Tecnoservice Srl",
    "wof:placetype":"venue"
},
  "geometry": {"coordinates":[9.05174,45.437603],"type":"Point"}
}