{
  "type": "Feature",
  "properties": {
    "iso:country":"IT",
    "sg:address":"80123 Napoli",
    "sg:city":"Napoli",
    "sg:orig_category":"Acciaierie E Fonderie. Arte Ed Artigianato Artistico",
    "sg:phone":"+39 081 575 6110",
    "sg:postcode":"80123",
    "sg:province":"Napoli",
    "wof:name":"Delmar (s.n.c.)",
    "wof:placetype":"venue"
},
  "geometry": {"coordinates":[14.192534,40.834789],"type":"Point"}
}