{
  "type": "Feature",
  "properties": {
    "addr:full":"90146 Palermo Palermo Palermo 90146",
    "addr:postcode":"90146;90146",
    "iso:country":"IT",
    "sg:address":"90146 Palermo",
    "sg:city":"Palermo",
    "sg:orig_category":"Arredamenti - Produzione E Ingrosso",
    "sg:phone":"+39 091 688 7459",
    "sg:postcode":"90146",
    "sg:province":"Palermo",
    "wof:name":"Nuovo Centro Vetrine Di G. Cannata & M. Profeta & C. Snc",
    "wof:placetype":"venue"
},
  "geometry": {"coordinates":[13.325377,38.157978],"type":"Point"}
}