{
  "type": "Feature",
  "properties": {
    "addr:full":"20, Via Migliaro 84016 Pagani Pagani Salerno 84016",
    "addr:postcode":"84016;84016",
    "addr:street":"Via Migliaro",
    "iso:country":"IT",
    "sg:address":"20, Via Migliaro 84016 Pagani",
    "sg:city":"Pagani",
    "sg:classifiers":[
        {
            "category":"Manufacturing",
            "subcategory":"Lumber",
            "type":"Manufacturing & Wholesale Goods"
        }
    ],
    "sg:phone":"+39 39081916005",
    "sg:postcode":"84016",
    "sg:province":"Salerno",
    "sg:tags":[
        "wood"
    ],
    "wof:name":"Piscopo S.r.l.",
    "wof:placetype":"venue"
},
  "geometry": {"coordinates":[14.600724,40.737415],"type":"Point"}
}