{
  "type": "Feature",
  "properties": {
    "iso:country":"IT",
    "sg:address":"Strada Statale 315 Km 3,125 01035 Gallese",
    "sg:city":"Gallese",
    "sg:classifiers":[
        {
            "category":"Building & Trades",
            "subcategory":"Cleaning & Sanitation",
            "type":"Services"
        }
    ],
    "sg:phone":"+39 0761 4911",
    "sg:postcode":"01035",
    "sg:province":"Viterbo",
    "sg:tags":[
        "sanitary",
        "facility"
    ],
    "sg:website":"www.gsitaly.it",
    "wof:name":"Gruppo Sanitari Italia Spa",
    "wof:placetype":"venue"
},
  "geometry": {"coordinates":[12.104854,42.417381],"type":"Point"}
}