{
  "type": "Feature",
  "properties": {
    "addr:full":"Via I\u00b0 Maggio, 22/24 40064 Ozzano Dell'emilia Bologna 40064",
    "addr:housenumber":"22 / 24",
    "addr:postcode":"40064;40064",
    "addr:street":"Via I\u00b0 Maggio",
    "iso:country":"IT",
    "sg:address":"Via I\u00b0 Maggio, 22/24 40064 Ozzano Dell'emilia",
    "sg:classifiers":[
        {
            "category":"Manufacturing",
            "subcategory":"Textiles",
            "type":"Manufacturing & Wholesale Goods"
        }
    ],
    "sg:phone":"+39 051 797820",
    "sg:postcode":"40064",
    "sg:province":"Bologna",
    "sg:tags":[
        "dry",
        "detergent",
        "industry",
        "cleaning"
    ],
    "sg:website":"www.alberti-angelo.it",
    "wof:name":"Alberti Angelo",
    "wof:placetype":"venue"
},
  "geometry": {"coordinates":[11.346481,44.494221],"type":"Point"}
}