{
  "type": "Feature",
  "properties": {
    "addr:full":"Via Iv Novembre 18 40061 Minerbio Minerbio Bologna 40061",
    "addr:housenumber":"18",
    "addr:postcode":"40061;minerbio bologna 40061",
    "addr:street":"Via Iv Novembre",
    "iso:country":"IT",
    "sg:address":"Via Iv Novembre 18 40061 Minerbio",
    "sg:city":"Minerbio",
    "sg:orig_category":"Levelling Feet",
    "sg:phone":"+39 051 661 9942",
    "sg:postcode":"40061",
    "sg:province":"Bologna",
    "sg:website":"www.getechsrl.com",
    "wof:name":"Getech Srl",
    "wof:placetype":"venue"
},
  "geometry": {"coordinates":[11.346481,44.494221],"type":"Point"}
}