{
  "type": "Feature",
  "properties": {
    "iso:country":"IT",
    "sg:address":"30173 Mestre",
    "sg:city":"Mestre",
    "sg:orig_category":"Automazione E Macchine Per Ufficio. Servizi Ausiliari Di Certificati, Riproduzioni, Disegni E Foto",
    "sg:phone":"+39 041 535 1090",
    "sg:postcode":"30173",
    "sg:province":"Venezia",
    "wof:name":"Ital\u00ae Archivi Srl",
    "wof:placetype":"venue"
},
  "geometry": {"coordinates":[12.270391,45.493435],"type":"Point"}
}