{
  "type": "Feature",
  "properties": {
    "iso:country":"IT",
    "sg:address":"1714, Via Sant'alberto 40018 San Pietro In Casale",
    "sg:city":"San Pietro in Casale",
    "sg:classifiers":[
        {
            "category":"Professional",
            "subcategory":"Engineering",
            "type":"Services"
        }
    ],
    "sg:phone":"+39 39051811144",
    "sg:postcode":"40018",
    "sg:province":"Bologna",
    "sg:tags":[
        "machine",
        "-",
        "mechanical"
    ],
    "wof:name":"Alaska (s.r.l.)",
    "wof:placetype":"venue"
},
  "geometry": {"coordinates":[11.405679,44.716881],"type":"Point"}
}