{
  "type": "Feature",
  "properties": {
    "addr:full":"Piazza Garibaldi 1; Campitello; 46010 Campitello Mantova 46010",
    "addr:housenumber":"1",
    "addr:postcode":"46010;46010",
    "addr:street":"Piazza Garibaldi;Campitello",
    "iso:country":"IT",
    "sg:address":"Piazza Garibaldi 1; Campitello; 46010",
    "sg:city":"Campitello",
    "sg:classifiers":[
        {
            "category":"Banks & Credit Unions",
            "subcategory":"Bank",
            "type":"Services"
        }
    ],
    "sg:phone":"+39 0376 926282",
    "sg:postcode":"46010",
    "sg:province":"Mantova",
    "wof:name":"Cariverona Banca Spa",
    "wof:placetype":"venue"
},
  "geometry": {"coordinates":[10.583374,45.070004],"type":"Point"}
}