{
  "type": "Feature",
  "properties": {
    "addr:full":"Via S. Marco, 54; Perugia; 06100",
    "addr:housenumber":"54",
    "addr:postcode":"06100",
    "addr:street":"Via S. Marco",
    "iso:country":"IT",
    "sg:address":"Via S. Marco, 54; Perugia; 06100",
    "sg:classifiers":[
        {
            "category":"Banks & Credit Unions",
            "subcategory":"Bank",
            "type":"Services"
        }
    ],
    "sg:phone":"+39 075 43941",
    "wof:name":"Banca D'italia",
    "wof:placetype":"venue"
},
  "geometry": {"coordinates":[12.376619,43.127544],"type":"Point"}
}