{
  "type": "Feature",
  "properties": {
    "iso:country":"IT",
    "sg:address":"Via Tre Bocche 2 25081 Bedizzole",
    "sg:city":"Bedizzole",
    "sg:classifiers":[
        {
            "category":"Utilities",
            "subcategory":"Natural Gas",
            "type":"Services"
        }
    ],
    "sg:phone":"+39 030 674315",
    "sg:postcode":"25081",
    "sg:province":"Brescia",
    "sg:tags":[
        "cylinder",
        "hydraulic"
    ],
    "sg:website":"www.lanuovameccanica.com",
    "wof:name":"La Nuova Meccanica Srl",
    "wof:placetype":"venue"
},
  "geometry": {"coordinates":[10.222958,45.539829],"type":"Point"}
}