{
  "type": "Feature",
  "properties": {
    "addr:full":"41100 Modena Modena Modena 41100",
    "addr:postcode":"41100;41100",
    "iso:country":"IT",
    "sg:address":"41100 Modena",
    "sg:city":"Modena",
    "sg:orig_category":"Macchine, Impianti Ed Attrezzature Per Industria Alimentare E Bevande",
    "sg:phone":"+39 059 363997",
    "sg:postcode":"41100",
    "sg:province":"Modena",
    "wof:name":"Delver S.p.a.",
    "wof:placetype":"venue"
},
  "geometry": {"coordinates":[10.956387,44.636604],"type":"Point"}
}