{
  "type": "Feature",
  "properties": {
    "iso:country":"IT",
    "sg:address":"Via Maestri Del Lavoro 8 62010 Mogliano Marche",
    "sg:city":"Mogliano",
    "sg:orig_category":"Leather Items, Artisans'",
    "sg:phone":"+39 0733 559013",
    "sg:postcode":"62010",
    "sg:province":"Macerata",
    "sg:website":"www.eldatrade.com",
    "wof:name":"Elda Trade Srl",
    "wof:placetype":"venue"
},
  "geometry": {"coordinates":[13.515072,43.200871],"type":"Point"}
}