{
  "type": "Feature",
  "properties": {
    "iso:country":"IT",
    "sg:address":"17, Via Dalmazia 21100 Varese",
    "sg:city":"Varese",
    "sg:classifiers":[
        {
            "category":"Real Estate",
            "subcategory":"Architect",
            "type":"Services"
        }
    ],
    "sg:phone":"+39 0332 336071",
    "sg:postcode":"21100",
    "sg:province":"Varese",
    "sg:tags":[
        "textile",
        "clothing"
    ],
    "wof:name":"Gmv Srl",
    "wof:placetype":"venue"
},
  "geometry": {"coordinates":[8.845953,45.824806],"type":"Point"}
}