{
  "type": "Feature",
  "properties": {
    "addr:full":"80126 Napoli Napoli Napoli 80126",
    "addr:housenumber":"80126",
    "addr:postcode":"80126",
    "iso:country":"IT",
    "sg:address":"80126 Napoli",
    "sg:city":"Napoli",
    "sg:orig_category":"Abbigliamento Esterno, Maglierie E Pelliccerie. Sport - Articoli E Forniture",
    "sg:phone":"+39 081 726 5778",
    "sg:postcode":"80126",
    "sg:province":"Napoli",
    "wof:name":"Daniel's Sport Snc",
    "wof:placetype":"venue"
},
  "geometry": {"coordinates":[14.175491,40.862751],"type":"Point"}
}