{
  "type": "Feature",
  "properties": {
    "addr:full":"04012 Cisterna Di Latina Cisterna di Latina Latina 04012",
    "addr:postcode":"04012;04012",
    "iso:country":"IT",
    "sg:address":"04012 Cisterna Di Latina",
    "sg:city":"Cisterna di Latina",
    "sg:orig_category":"Zootecnia E Pesca, Allevamento Piccoli Animali",
    "sg:phone":"+39 06 968 5000",
    "sg:postcode":"04012",
    "sg:province":"Latina",
    "wof:name":"Nuova Agricoltura Piccola Soc. Coop. Arl",
    "wof:placetype":"venue"
},
  "geometry": {"coordinates":[12.797738,41.503666],"type":"Point"}
}