{
  "type": "Feature",
  "properties": {
    "addr:full":"1, Contrada Molino 60020 Agugliano Agugliano Ancona 60020",
    "addr:postcode":"60020;60020",
    "addr:street":"Contrada Molino",
    "iso:country":"IT",
    "sg:address":"1, Contrada Molino 60020 Agugliano",
    "sg:city":"Agugliano",
    "sg:classifiers":[
        {
            "category":"Shopping",
            "subcategory":"Clothing, Apparel, & Fashions",
            "type":"Retail Goods"
        }
    ],
    "sg:phone":"+39 39071908698",
    "sg:postcode":"60020",
    "sg:province":"Ancona",
    "sg:tags":[
        "clothes"
    ],
    "wof:name":"Zetabi & Bi (s.p.a.)",
    "wof:placetype":"venue"
},
  "geometry": {"coordinates":[13.342372,43.561588],"type":"Point"}
}