{
  "type": "Feature",
  "properties": {
    "addr:full":"10048 Vinovo Vinovo Torino 10048",
    "addr:housenumber":"10048",
    "addr:postcode":"10048",
    "addr:street":"Vinovo",
    "iso:country":"IT",
    "sg:address":"10048 Vinovo",
    "sg:city":"Vinovo",
    "sg:orig_category":"Prodotti Vari In Metallo",
    "sg:phone":"+39 011 965 6020",
    "sg:postcode":"10048",
    "sg:province":"Torino",
    "wof:name":"Robutex Srl",
    "wof:placetype":"venue"
},
  "geometry": {"coordinates":[7.6253991127,44.9775466919],"type":"Point"}
}