{
  "type": "Feature",
  "properties": {
    "addr:full":"00045 Genzano Di Roma Genzano di Roma Roma 00045",
    "addr:postcode":"00045;00045",
    "iso:country":"IT",
    "sg:address":"00045 Genzano Di Roma",
    "sg:city":"Genzano di Roma",
    "sg:orig_category":"Motocicli E Motocarri - Commercio E Riparazione",
    "sg:phone":"+39 06 936 3477",
    "sg:postcode":"00045",
    "sg:province":"Roma",
    "wof:name":"Bianchini Giovanni Centro Ass. Gomme",
    "wof:placetype":"venue"
},
  "geometry": {"coordinates":[12.6962766647,41.693359375],"type":"Point"}
}