{
  "type": "Feature",
  "properties": {
    "addr:full":"10, Via Quaglierini Ettore 57123 Livorno Livorno Livorno 57123",
    "addr:postcode":"57123;57123",
    "addr:street":"Via Quaglierini Ettore",
    "iso:country":"IT",
    "sg:address":"10, Via Quaglierini Ettore 57123 Livorno",
    "sg:city":"Livorno",
    "sg:classifiers":[
        {
            "category":"Shopping",
            "type":"Retail Goods"
        }
    ],
    "sg:phone":"+39 0586 424317",
    "sg:postcode":"57123",
    "sg:province":"Livorno",
    "sg:tags":[
        "finished",
        "-",
        "metallic"
    ],
    "wof:name":"Officine Mec Carpensalda (s.n.c.)",
    "wof:placetype":"venue"
},
  "geometry": {"coordinates":[10.308011055,43.5518760681],"type":"Point"}
}