{
  "type": "Feature",
  "properties": {
    "iso:country":"IT",
    "sg:address":"25050 Paderno Franciacorta",
    "sg:city":"Paderno Franciacorta",
    "sg:orig_category":"Filati Cucirini",
    "sg:phone":"+39 030 685 3001",
    "sg:postcode":"25050",
    "sg:province":"Brescia",
    "wof:name":"Filtec Srl",
    "wof:placetype":"venue"
},
  "geometry": {"coordinates":[10.0858354568,45.5786361694],"type":"Point"}
}