{
  "type": "Feature",
  "properties": {
    "iso:country":"IT",
    "sg:address":"50142 Firenze",
    "sg:city":"Firenze",
    "sg:orig_category":"Medici. Assicurazioni E Servizi Assicurativi. Avvocati, Notai E Servizi Legali. Professionisti - Studi E Servizi Ed Associazioni Di Interesse Aziendale",
    "sg:phone":"+39 055 785631",
    "sg:postcode":"50142",
    "sg:province":"Firenze",
    "wof:name":"Arcieri Aldo",
    "wof:placetype":"venue"
},
  "geometry": {"coordinates":[11.194975853,43.7775154114],"type":"Point"}
}