{
  "type": "Feature",
  "properties": {
    "iso:country":"IT",
    "sg:address":"1, Via W. Tobagi 42025 Cavriago",
    "sg:classifiers":[
        {
            "category":"Farming",
            "subcategory":"Livestock Farm",
            "type":"Manufacturing & Wholesale Goods"
        }
    ],
    "sg:phone":"+39 0522 372378",
    "sg:postcode":"42025",
    "sg:province":"Reggio Nell'Emilia",
    "sg:tags":[
        "agriculture"
    ],
    "wof:name":"Woodline S.r.l.",
    "wof:placetype":"venue"
},
  "geometry": {"coordinates":[10.538112,44.695229],"type":"Point"}
}