{
  "type": "Feature",
  "properties": {
    "iso:country":"IT",
    "sg:address":"00185 Roma",
    "sg:city":"Roma",
    "sg:orig_category":"Banche E Servizi Finanziari",
    "sg:phone":"+39 06 4470 3486",
    "sg:postcode":"00185",
    "sg:province":"Roma",
    "wof:name":"S.r.l.casa Del Turista",
    "wof:placetype":"venue"
},
  "geometry": {"coordinates":[12.501469,41.899746],"type":"Point"}
}