{
  "type": "Feature",
  "properties": {
    "addr:full":"00198 Roma Roma Roma 00198",
    "addr:postcode":"00198;00198",
    "iso:country":"IT",
    "sg:address":"00198 Roma",
    "sg:city":"Roma",
    "sg:orig_category":"Manufacturers: Prefabbricati",
    "sg:phone":"+39 06 855 2379",
    "sg:postcode":"00198",
    "sg:province":"Roma",
    "wof:name":"Stucchi Cecere Di Piacentini Claudio Sas",
    "wof:placetype":"venue"
},
  "geometry": {"coordinates":[12.500676,41.91674],"type":"Point"}
}