{
  "type": "Feature",
  "properties": {
    "addr:full":"40043 Marzabotto Marzabotto Bologna 40043",
    "addr:postcode":"40043;40043",
    "iso:country":"IT",
    "sg:address":"40043 Marzabotto",
    "sg:city":"Marzabotto",
    "sg:orig_category":"Motori Ed Organi Di Trasmissione. Ricambi E Componenti Dei Mezzi Di Trasporto",
    "sg:phone":"+39 051 931276",
    "sg:postcode":"40043",
    "sg:province":"Bologna",
    "wof:name":"Lolli Ceres Srl",
    "wof:placetype":"venue"
},
  "geometry": {"coordinates":[11.408864975,44.5060310364],"type":"Point"}
}