{
  "type": "Feature",
  "properties": {
    "addr:full":"90135 Palermo Palermo Palermo 90135",
    "addr:postcode":"90135;90135",
    "iso:country":"IT",
    "sg:address":"90135 Palermo",
    "sg:city":"Palermo",
    "sg:orig_category":"Materiali Edili",
    "sg:phone":"+39 091 405371",
    "sg:postcode":"90135",
    "sg:province":"Palermo",
    "wof:name":"Lopes Giuseppe",
    "wof:placetype":"venue"
},
  "geometry": {"coordinates":[13.328731,38.116718],"type":"Point"}
}