{
  "type": "Feature",
  "properties": {
    "iso:country":"IT",
    "sg:address":"50041 Calenzano",
    "sg:city":"Calenzano",
    "sg:orig_category":"Prodotti Vari In Metallo. Articoli Per Imballaggio E Confezionamento",
    "sg:phone":"+39 055 887 7133",
    "sg:postcode":"50041",
    "sg:province":"Firenze",
    "wof:name":"Metalcontenitori Srl",
    "wof:placetype":"venue"
},
  "geometry": {"coordinates":[11.1617860794,43.8483314514],"type":"Point"}
}