{
  "type": "Feature",
  "properties": {
    "addr:full":"30121 Venezia Cannaregio Venezia 30121",
    "addr:postcode":"30121;30121",
    "addr:street":"Cannaregio",
    "iso:country":"IT",
    "sg:address":"30121 Venezia",
    "sg:city":"Cannaregio",
    "sg:orig_category":"Prodotti Finiti Stampati. Articoli Da Regalo. Arte Ed Artigianato Artistico. Shopping",
    "sg:phone":"+39 041 710040",
    "sg:postcode":"30121",
    "sg:province":"Venezia",
    "wof:name":"Studio D'arte Vio Di Vio M.",
    "wof:placetype":"venue"
},
  "geometry": {"coordinates":[12.3309459686,45.4434051514],"type":"Point"}
}