{
  "type": "Feature",
  "properties": {
    "iso:country":"IT",
    "sg:address":"125, Via Torino 21042 Caronno Pertusella",
    "sg:city":"Caronno Pertusella",
    "sg:classifiers":[
        {
            "category":"Shopping",
            "subcategory":"Clothing, Apparel, & Fashions",
            "type":"Retail Goods"
        }
    ],
    "sg:phone":"+39 39029657506",
    "sg:postcode":"21042",
    "sg:province":"Varese",
    "sg:tags":[
        "clothes"
    ],
    "wof:name":"Piave Maitex Spa",
    "wof:placetype":"venue"
},
  "geometry": {"coordinates":[9.0522,45.588261],"type":"Point"}
}