{
  "type": "Feature",
  "properties": {
    "addr:full":"Via Malta 26039 Vescovato Vescovato Cremona 26039",
    "addr:postcode":"26039;26039",
    "addr:street":"Via Malta",
    "iso:country":"IT",
    "sg:address":"Via Malta 26039 Vescovato",
    "sg:city":"Vescovato",
    "sg:orig_category":"Slaughter-houses, Abattoirs",
    "sg:phone":"+39 0372 819211",
    "sg:postcode":"26039",
    "sg:province":"Cremona",
    "wof:name":"Cooperativa Produttori Suini Pro Su",
    "wof:placetype":"venue"
},
  "geometry": {"coordinates":[10.158035,45.169537],"type":"Point"}
}