{
  "type": "Feature",
  "properties": {
    "addr:full":"36050 Gambugliano Gambugliano Vicenza 36050",
    "addr:postcode":"36050;36050",
    "iso:country":"IT",
    "sg:address":"36050 Gambugliano",
    "sg:city":"Gambugliano",
    "sg:orig_category":"Metalli E Leghe",
    "sg:phone":"+39 0444 951755",
    "sg:postcode":"36050",
    "sg:province":"Vicenza",
    "wof:name":"Baggio Lavorazione Acciai (s.n.c.)",
    "wof:placetype":"venue"
},
  "geometry": {"coordinates":[11.4397039413,45.5889091492],"type":"Point"}
}