{
  "type": "Feature",
  "properties": {
    "addr:full":"72023 Mesagne Mesagne Brindisi 72023",
    "addr:postcode":"72023;72023",
    "iso:country":"IT",
    "sg:address":"72023 Mesagne",
    "sg:city":"Mesagne",
    "sg:orig_category":"Non-classified Establishments",
    "sg:phone":"+39 0831 735687",
    "sg:postcode":"72023",
    "sg:province":"Brindisi",
    "wof:name":"Il Posto Delle Fragole Di De Leo Desdemona",
    "wof:placetype":"venue"
},
  "geometry": {"coordinates":[17.80759,40.557869],"type":"Point"}
}