{
  "type": "Feature",
  "properties": {
    "iso:country":"IT",
    "sg:address":"35128 Padova",
    "sg:city":"Padova",
    "sg:orig_category":"Medici. Assicurazioni E Servizi Assicurativi. Avvocati, Notai E Servizi Legali. Professionisti - Studi E Servizi Ed Associazioni Di Interesse Aziendale",
    "sg:phone":"+39 049 850377",
    "sg:postcode":"35128",
    "sg:province":"Padova",
    "wof:name":"Gomi (s.r.l.)",
    "wof:placetype":"venue"
},
  "geometry": {"coordinates":[11.9046621323,45.3978996277],"type":"Point"}
}