{
  "type": "Feature",
  "properties": {
    "iso:country":"IT",
    "sg:address":"37066 Sommacampagna",
    "sg:city":"Sommacampagna",
    "sg:orig_category":"Rifiuti Industriali E Speciali Smaltimento E Trattamento - Servizio",
    "sg:phone":"+39 045 790 0948",
    "sg:postcode":"37066",
    "sg:province":"Verona",
    "wof:name":"Benassuti Rottami Sas",
    "wof:placetype":"venue"
},
  "geometry": {"coordinates":[10.726259,45.457371],"type":"Point"}
}