{
  "type": "Feature",
  "properties": {
    "iso:country":"IT",
    "sg:address":"20090 Buccinasco",
    "sg:city":"Buccinasco",
    "sg:orig_category":"Utensili Meccanici E Materiali",
    "sg:phone":"+39 02 4570 8468",
    "sg:postcode":"20090",
    "sg:province":"Milano",
    "wof:name":"S.i.u.d. S.r.l.",
    "wof:placetype":"venue"
},
  "geometry": {"coordinates":[9.116935,45.412636],"type":"Point"}
}