{
  "type": "Feature",
  "properties": {
    "iso:country":"IT",
    "sg:address":"46, Via Serraglio 40026 Imola",
    "sg:city":"Imola",
    "sg:classifiers":[
        {
            "category":"Professional",
            "subcategory":"Engineering",
            "type":"Services"
        }
    ],
    "sg:phone":"+39 0542 640387",
    "sg:postcode":"40026",
    "sg:province":"Bologna",
    "sg:tags":[
        "machine",
        "-",
        "mechanical"
    ],
    "wof:name":"Andalo' Gianni S.r.l.",
    "wof:placetype":"venue"
},
  "geometry": {"coordinates":[11.723058,44.36433],"type":"Point"}
}