{
  "type": "Feature",
  "properties": {
    "iso:country":"IT",
    "sg:address":"1, V. A. Carpen\u00e8 -",
    "sg:city":"Brugnera",
    "sg:classifiers":[
        {
            "category":"Wholesale",
            "subcategory":"Machinery & Supplies",
            "type":"Manufacturing & Wholesale Goods"
        }
    ],
    "sg:phone":"+39 0434 613252",
    "sg:postcode":"33070",
    "sg:province":"Pordenone",
    "sg:tags":[
        "equipment",
        "-",
        "instrument",
        "measurement"
    ],
    "sg:website":"http://www.betaelectronics.it",
    "wof:name":"Beta Electronics Italia Srl",
    "wof:placetype":"venue"
},
  "geometry": {"coordinates":[12.547717,45.911411],"type":"Point"}
}