{
  "type": "Feature",
  "properties": {
    "iso:country":"IT",
    "sg:address":"25, Via Del Boccaccio 00187 Roma",
    "sg:city":"Roma",
    "sg:classifiers":[
        {
            "category":"Travel",
            "subcategory":"Travel Agent",
            "type":"Entertainment"
        }
    ],
    "sg:phone":"+39 39064819626",
    "sg:postcode":"00187",
    "sg:province":"Roma",
    "sg:tags":[
        "business"
    ],
    "wof:name":"Hotel De Petris S.r.l.",
    "wof:placetype":"venue"
},
  "geometry": {"coordinates":[12.48733,41.902451],"type":"Point"}
}