{
  "type": "Feature",
  "properties": {
    "addr:full":"50022 Greve In Chianti Greve in Chianti Firenze 50022",
    "addr:postcode":"50022;50022",
    "iso:country":"IT",
    "sg:address":"50022 Greve In Chianti",
    "sg:city":"Greve in Chianti",
    "sg:orig_category":"Medicinali E Prodotti Parafarmaceutici",
    "sg:phone":"+39 055 854 7368",
    "sg:postcode":"50022",
    "sg:province":"Firenze",
    "wof:name":"Laboratorio Sodini Srl",
    "wof:placetype":"venue"
},
  "geometry": {"coordinates":[11.3220396042,43.6658172607],"type":"Point"}
}