{
  "type": "Feature",
  "properties": {
    "iso:country":"IT",
    "sg:address":"Via Dell' Elettronica 11 37139 Verona",
    "sg:city":"Verona",
    "sg:classifiers":[
        {
            "category":"Professional",
            "subcategory":"Art Services",
            "type":"Services"
        }
    ],
    "sg:phone":"+39 045 818 1444",
    "sg:postcode":"37139",
    "sg:province":"Verona",
    "sg:tags":[
        "catalogue"
    ],
    "wof:name":"Litopat Spa",
    "wof:placetype":"venue"
},
  "geometry": {"coordinates":[10.884894,45.454124],"type":"Point"}
}