{
  "type": "Feature",
  "properties": {
    "addr:full":"7, Via Alfredo Tacca 28010 Pella Pella Novara 28010",
    "addr:postcode":"28010;28010",
    "addr:street":"Via Alfredo Tacca",
    "iso:country":"IT",
    "sg:address":"7, Via Alfredo Tacca 28010 Pella",
    "sg:city":"Pella",
    "sg:classifiers":[
        {
            "category":"Manufacturing",
            "subcategory":"Metals",
            "type":"Manufacturing & Wholesale Goods"
        }
    ],
    "sg:phone":"+39 0322 969152",
    "sg:postcode":"28010",
    "sg:province":"Novara",
    "sg:tags":[
        "processing"
    ],
    "wof:name":"Rizzo F.lli S.n.c.",
    "wof:placetype":"venue"
},
  "geometry": {"coordinates":[8.6186714172,45.4450836182],"type":"Point"}
}