{
  "type": "Feature",
  "properties": {
    "addr:full":"Via Arceviese 60019 Senigallia Senigallia Ancona 60019",
    "addr:postcode":"60019;60019",
    "addr:street":"Via Arceviese",
    "iso:country":"IT",
    "sg:address":"Via Arceviese 60019 Senigallia",
    "sg:city":"Senigallia",
    "sg:classifiers":[
        {
            "category":"Manufacturing",
            "subcategory":"Metals",
            "type":"Manufacturing & Wholesale Goods"
        }
    ],
    "sg:phone":"+39 071 792 6018",
    "sg:postcode":"60019",
    "sg:province":"Ancona",
    "sg:tags":[
        "processing"
    ],
    "wof:name":"Sidermarche S.r.l.",
    "wof:placetype":"venue"
},
  "geometry": {"coordinates":[13.1393871307,43.6304321289],"type":"Point"}
}