{
  "type": "Feature",
  "properties": {
    "addr:full":"1, Via Delle Industrie 24040 Filago Filago Bergamo 24040",
    "addr:postcode":"24040;24040",
    "addr:street":"Via Delle Industrie",
    "iso:country":"IT",
    "sg:address":"1, Via Delle Industrie 24040 Filago",
    "sg:city":"Filago",
    "sg:classifiers":[
        {
            "category":"Retail",
            "subcategory":"Animal Services",
            "type":"Services"
        }
    ],
    "sg:phone":"+39 39035995226",
    "sg:postcode":"24040",
    "sg:province":"Bergamo",
    "sg:tags":[
        "breeding"
    ],
    "wof:name":"Uvigal (s.p.a.)",
    "wof:placetype":"venue"
},
  "geometry": {"coordinates":[9.599721,45.668678],"type":"Point"}
}