{
  "type": "Feature",
  "properties": {
    "iso:country":"IT",
    "sg:address":"28, Via E. Fermi 33058 San Giorgio Di Nogaro",
    "sg:city":"San Giorgio di Nogaro",
    "sg:classifiers":[
        {
            "category":"Shopping",
            "type":"Retail Goods"
        }
    ],
    "sg:phone":"+39 0431 623111",
    "sg:postcode":"33058",
    "sg:province":"Udine",
    "sg:tags":[
        "finished",
        "-",
        "metallic"
    ],
    "wof:name":"Palini & Bertoli Spa",
    "wof:placetype":"venue"
},
  "geometry": {"coordinates":[13.2307243347,46.0649414062],"type":"Point"}
}