{
  "type": "Feature",
  "properties": {
    "addr:full":"Via Circonvallazione Sud 31020 Sernaglia Della Battaglia Sernaglia della Battaglia Treviso 31020",
    "addr:postcode":"31020;31020",
    "addr:street":"Via Circonvallazione Sud",
    "iso:country":"IT",
    "sg:address":"Via Circonvallazione Sud 31020 Sernaglia Della Battaglia",
    "sg:city":"Sernaglia della Battaglia",
    "sg:classifiers":[
        {
            "category":"Home & Garden",
            "subcategory":"Home Furnishings",
            "type":"Retail Goods"
        }
    ],
    "sg:phone":"+39 0438 840549",
    "sg:postcode":"31020",
    "sg:province":"Treviso",
    "sg:tags":[
        "household"
    ],
    "wof:name":"Euromobil (s.p.a.)",
    "wof:placetype":"venue"
},
  "geometry": {"coordinates":[12.242072,45.666286],"type":"Point"}
}