{
  "type": "Feature",
  "properties": {
    "iso:country":"IT",
    "sg:address":"48018 Faenza",
    "sg:city":"Faenza",
    "sg:orig_category":"Enologia Macchine E Prodotti - Vendita Al Dettaglio",
    "sg:phone":"+39 0546 620757",
    "sg:postcode":"48018",
    "sg:province":"Ravenna",
    "wof:name":"F. Lli Tabanelli",
    "wof:placetype":"venue"
},
  "geometry": {"coordinates":[11.896951,44.263058],"type":"Point"}
}