{
  "type": "Feature",
  "properties": {
    "iso:country":"IT",
    "sg:address":"63015 Monte Urano",
    "sg:city":"Monte Urano",
    "sg:orig_category":"Forniture Per Abbigliamento E Pelletterie",
    "sg:phone":"+39 0734 842305",
    "sg:postcode":"63015",
    "sg:province":"Ascoli Piceno",
    "wof:name":"Foder Point Srl",
    "wof:placetype":"venue"
},
  "geometry": {"coordinates":[13.6721839905,43.2048873901],"type":"Point"}
}