{
  "type": "Feature",
  "properties": {
    "iso:country":"IT",
    "sg:address":"20123 Milano",
    "sg:city":"Milano",
    "sg:orig_category":"Avvocati, Notai E Servizi Legali. Consulenze Tecniche, Amministrative E Perizie",
    "sg:phone":"+39 02 869 2442",
    "sg:postcode":"20123",
    "sg:province":"Milano",
    "sg:website":"http://www.modiano.com",
    "wof:name":"Modiano & Associati Spa",
    "wof:placetype":"venue"
},
  "geometry": {"coordinates":[9.181558,45.465714],"type":"Point"}
}