{
  "type": "Feature",
  "properties": {
    "iso:country":"IT",
    "sg:address":"21042 Caronno Pertusella",
    "sg:city":"Caronno Pertusella",
    "sg:orig_category":"Alluminio E Leghe",
    "sg:phone":"+39 02 9645 1333",
    "sg:postcode":"21042",
    "sg:province":"Varese",
    "sg:website":"http://www.profall.com",
    "wof:name":"Profilati Alluminio Srl",
    "wof:placetype":"venue"
},
  "geometry": {"coordinates":[9.040292,45.610878],"type":"Point"}
}