{
  "type": "Feature",
  "properties": {
    "iso:country":"IT",
    "sg:address":"81031 Aversa",
    "sg:city":"Aversa",
    "sg:orig_category":"Arredamenti E Mobili Professionali. Apparecchi, Attrezzature E Forniture Per Centri Estetici. Arredi Ed Attrezzature Per Attivita' Commerciali Ed Artigianali",
    "sg:phone":"+39 081 503 2295",
    "sg:postcode":"81031",
    "sg:province":"Caserta",
    "wof:name":"Fab 4 Di Elvira Portogallo",
    "wof:placetype":"venue"
},
  "geometry": {"coordinates":[14.201299,41.01815],"type":"Point"}
}