{
  "type": "Feature",
  "properties": {
    "addr:full":"71016 San Severo San Severo Foggia 71016",
    "addr:housenumber":"71016",
    "addr:postcode":"71016",
    "addr:street":"San Severo",
    "iso:country":"IT",
    "sg:address":"71016 San Severo",
    "sg:city":"San Severo",
    "sg:orig_category":"Articoli Natalizi",
    "sg:phone":"+39 0882 337455",
    "sg:postcode":"71016",
    "sg:province":"Foggia",
    "sg:website":"http://www.fradasrl.com",
    "wof:name":"Fra.da Srl",
    "wof:placetype":"venue"
},
  "geometry": {"coordinates":[15.430239,41.641582],"type":"Point"}
}