{
  "type": "Feature",
  "properties": {
    "addr:full":"50125 Firenze Firenze Firenze 50125",
    "addr:postcode":"50125;50125",
    "iso:country":"IT",
    "sg:address":"50125 Firenze",
    "sg:city":"Firenze",
    "sg:orig_category":"Servizi Culturali E Per Lo Spettacolo. Arte Ed Artigianato Artistico. Servizi Al Turismo",
    "sg:phone":"+39 055 281756",
    "sg:postcode":"50125",
    "sg:province":"Firenze",
    "sg:website":"http://www.boralevi.com",
    "wof:name":"Boralevi Di Daniele Boralevi",
    "wof:placetype":"venue"
},
  "geometry": {"coordinates":[11.258047,43.74371],"type":"Point"}
}