{
  "type": "Feature",
  "properties": {
    "addr:full":"70, Via Borgosatollo 25010 Montirone Borgosatollo Brescia 25010",
    "addr:postcode":"25010;25010",
    "addr:street":"Via Borgosatollo",
    "iso:country":"IT",
    "sg:address":"70, Via Borgosatollo 25010 Montirone",
    "sg:city":"Borgosatollo",
    "sg:classifiers":[
        {
            "category":"Manufacturing",
            "subcategory":"Paper Products",
            "type":"Manufacturing & Wholesale Goods"
        }
    ],
    "sg:phone":"+39 030 267 7512",
    "sg:postcode":"25010",
    "sg:province":"Brescia",
    "sg:tags":[
        "cardboard"
    ],
    "wof:name":"Daina (s.r.l.)",
    "wof:placetype":"venue"
},
  "geometry": {"coordinates":[10.2340068817,45.4539604187],"type":"Point"}
}