{
  "type": "Feature",
  "properties": {
    "iso:country":"IT",
    "sg:address":"59100 Prato",
    "sg:city":"Prato",
    "sg:orig_category":"Tessuti E Stoffe. Forniture Per Attivita' Industriali",
    "sg:phone":"+39 0574 650022",
    "sg:postcode":"59100",
    "sg:province":"Prato",
    "wof:name":"Ramaspalmati S.r.l.",
    "wof:placetype":"venue"
},
  "geometry": {"coordinates":[11.058562,43.809071],"type":"Point"}
}