{
  "type": "Feature",
  "properties": {
    "addr:full":"20124 Milano Milano Milano 20124",
    "addr:postcode":"20124;20124",
    "iso:country":"IT",
    "sg:address":"20124 Milano",
    "sg:city":"Milano",
    "sg:orig_category":"Editoria",
    "sg:phone":"+39 02 669 6634",
    "sg:postcode":"20124",
    "sg:province":"Milano",
    "wof:name":"Nuova K & K Srl",
    "wof:placetype":"venue"
},
  "geometry": {"coordinates":[9.200512,45.483509],"type":"Point"}
}