{
  "type": "Feature",
  "properties": {
    "iso:country":"IT",
    "sg:address":"Ctr. Vore - Zona Industriale 73040 Melissano",
    "sg:city":"Melissano",
    "sg:classifiers":[
        {
            "category":"Shopping",
            "subcategory":"Crafts & Fabrics",
            "type":"Retail Goods"
        }
    ],
    "sg:phone":"+39 0833 581431",
    "sg:postcode":"73040",
    "sg:province":"Lecce",
    "sg:website":"http://www.paginegialle.it/manifatturaeffeci",
    "wof:name":"Manifattura Effeci Srl",
    "wof:placetype":"venue"
},
  "geometry": {"coordinates":[18.1740150452,40.3532905579],"type":"Point"}
}