{
  "type": "Feature",
  "properties": {
    "iso:country":"IT",
    "sg:address":"84, Viale Delle Industrie 20041 Agrate Brianza",
    "sg:city":"Agrate Brianza",
    "sg:classifiers":[
        {
            "category":"Wholesale",
            "subcategory":"Drugs",
            "type":"Manufacturing & Wholesale Goods"
        }
    ],
    "sg:phone":"+39 390 396 5751",
    "sg:postcode":"20041",
    "sg:province":"Milano",
    "sg:tags":[
        "chemical",
        "pharmaceutical"
    ],
    "wof:name":"Uquifa Italia S.p.a.",
    "wof:placetype":"venue"
},
  "geometry": {"coordinates":[9.349775,45.5662],"type":"Point"}
}