{
  "type": "Feature",
  "properties": {
    "addr:full":"6, V. Tolarolo 43010 Roccabianca Roccabianca Parma 43010",
    "addr:housenumber":"6",
    "addr:postcode":"43010;43010",
    "addr:street":"Tolarolo",
    "iso:country":"IT",
    "sg:address":"6, V. Tolarolo 43010 Roccabianca",
    "sg:city":"Roccabianca",
    "sg:classifiers":[
        {
            "category":"Food & Beverages",
            "subcategory":"Groceries & Convenience Stores",
            "type":"Retail Goods"
        }
    ],
    "sg:phone":"+39 0521 374004",
    "sg:postcode":"43010",
    "sg:province":"Parma",
    "sg:tags":[
        "drink"
    ],
    "sg:website":"http://www.paginegialle.it/faled",
    "wof:name":"Di Castello Faled Distillerie Srl",
    "wof:placetype":"venue"
},
  "geometry": {"coordinates":[10.221578,45.010178],"type":"Point"}
}