{
  "type": "Feature",
  "properties": {
    "addr:full":"48011 Alfonsine Alfonsine Ravenna 48011",
    "addr:postcode":"48011;48011",
    "iso:country":"IT",
    "sg:address":"48011 Alfonsine",
    "sg:city":"Alfonsine",
    "sg:orig_category":"Apparecchiature Ed Attrezzature Meccaniche",
    "sg:phone":"+39 0544 84820",
    "sg:postcode":"48011",
    "sg:province":"Ravenna",
    "wof:name":"Verlicchi S.r.l.",
    "wof:placetype":"venue"
},
  "geometry": {"coordinates":[12.054992,44.498188],"type":"Point"}
}