{
  "type": "Feature",
  "properties": {
    "addr:full":"167, Via Del Brennero 38100 Trento Trento Trento 38100",
    "addr:housenumber":"167",
    "addr:postcode":"38100;38100",
    "addr:street":"Via Del Brennero",
    "iso:country":"IT",
    "sg:address":"167, Via Del Brennero 38100 Trento",
    "sg:city":"Trento",
    "sg:classifiers":[
        {
            "category":"Shopping",
            "subcategory":"Stationery & Office Supplies",
            "type":"Retail Goods"
        }
    ],
    "sg:phone":"+39 0461 821317",
    "sg:postcode":"38100",
    "sg:province":"Trento",
    "sg:tags":[
        "professional"
    ],
    "wof:name":"Tecnostile Interni (s.r.l.)",
    "wof:placetype":"venue"
},
  "geometry": {"coordinates":[11.1115131378,46.0926551819],"type":"Point"}
}