{
  "type": "Feature",
  "properties": {
    "iso:country":"IT",
    "sg:address":"C. So Roma 14/16; Roccamonfina; 81035",
    "sg:city":"Roccamonfina",
    "sg:classifiers":[
        {
            "category":"Banks & Credit Unions",
            "subcategory":"Bank",
            "type":"Services"
        }
    ],
    "sg:phone":"+39 0823 921059",
    "sg:postcode":"81035",
    "sg:province":"Caserta",
    "wof:name":"Banco Di Napoli Spa",
    "wof:placetype":"venue"
},
  "geometry": {"coordinates":[13.98482,41.292206],"type":"Point"}
}