{
  "type": "Feature",
  "properties": {
    "addr:full":"53016 Murlo Murlo Siena 53016",
    "addr:postcode":"53016;53016",
    "iso:country":"IT",
    "sg:address":"53016 Murlo",
    "sg:city":"Murlo",
    "sg:orig_category":"Agriturismo",
    "sg:phone":"+39 0577 814605",
    "sg:postcode":"53016",
    "sg:province":"Siena",
    "sg:website":"http://www.boscodellaspina.it",
    "wof:name":"Bosco Della Spina Srl",
    "wof:placetype":"venue"
},
  "geometry": {"coordinates":[11.365801,43.166851],"type":"Point"}
}