{
  "type": "Feature",
  "properties": {
    "addr:full":"20026 Novate Milanese Novate Milanese Milano 20026",
    "addr:postcode":"20026;20026",
    "iso:country":"IT",
    "sg:address":"20026 Novate Milanese",
    "sg:city":"Novate Milanese",
    "sg:orig_category":"Servizi Vari Di Interesse Pubblico",
    "sg:phone":"+39 02 3910 1439",
    "sg:postcode":"20026",
    "sg:province":"Milano",
    "wof:name":"Crea Srl",
    "wof:placetype":"venue"
},
  "geometry": {"coordinates":[9.141828,45.533119],"type":"Point"}
}