{
  "type": "Feature",
  "properties": {
    "addr:full":"70024 Gravina In Puglia Gravina in Puglia Bari 70024",
    "addr:postcode":"70024;70024",
    "iso:country":"IT",
    "sg:address":"70024 Gravina In Puglia",
    "sg:city":"Gravina in Puglia",
    "sg:orig_category":"Ricambi E Componenti Dei Mezzi Di Trasporto",
    "sg:phone":"+39 080 326 4214",
    "sg:postcode":"70024",
    "sg:province":"Bari",
    "wof:name":"S.e.g. Ricambi (s.r.l.)",
    "wof:placetype":"venue"
},
  "geometry": {"coordinates":[16.430107,40.818031],"type":"Point"}
}