{
  "type": "Feature",
  "properties": {
    "addr:full":"80040 Cercola Cercola Napoli 80040",
    "addr:postcode":"80040;80040",
    "iso:country":"IT",
    "sg:address":"80040 Cercola",
    "sg:city":"Cercola",
    "sg:orig_category":"Colori, Vernici E Smalti - Produzione E Ingrosso",
    "sg:phone":"+39 081 733 1188",
    "sg:postcode":"80040",
    "sg:province":"Napoli",
    "wof:name":"Vernital Spa",
    "wof:placetype":"venue"
},
  "geometry": {"coordinates":[14.350804,40.865398],"type":"Point"}
}