{
  "type": "Feature",
  "properties": {
    "iso:country":"IT",
    "sg:address":"80131 Napoli",
    "sg:city":"Napoli",
    "sg:orig_category":"Forniture Per Attivita' Industriali",
    "sg:phone":"+39 081 577 0315",
    "sg:postcode":"80131",
    "sg:province":"Napoli",
    "sg:website":"http://www.hydroflex.it",
    "wof:name":"Hydroflex Sas",
    "wof:placetype":"venue"
},
  "geometry": {"coordinates":[14.2105283737,40.8628425598],"type":"Point"}
}