{
  "type": "Feature",
  "properties": {
    "addr:full":"20123 Milano Milano Milano 20123",
    "addr:postcode":"20123;20123",
    "iso:country":"IT",
    "sg:address":"20123 Milano",
    "sg:city":"Milano",
    "sg:orig_category":"Professionisti - Studi E Servizi Ed Associazioni Di Interesse Aziendale. Associazioni Ed Organismi Di Interesse Pubblico. Chiese Ed Associazioni Religiose",
    "sg:phone":"+39 02 5831 3651",
    "sg:postcode":"20123",
    "sg:province":"Milano",
    "wof:name":"Federazione Italiana Religiose",
    "wof:placetype":"venue"
},
  "geometry": {"coordinates":[9.1844501495,45.4573020935],"type":"Point"}
}