{
  "type": "Feature",
  "properties": {
    "iso:country":"IT",
    "sg:address":"03013 Ferentino",
    "sg:city":"Ferentino",
    "sg:orig_category":"Utensili Meccanici E Materiali. Forniture Per Attivita' Industriali",
    "sg:phone":"+39 0775 246789",
    "sg:postcode":"03013",
    "sg:province":"Frosinone",
    "wof:name":"Italutensili Di Berretta Maurizio",
    "wof:placetype":"venue"
},
  "geometry": {"coordinates":[13.243263,41.684708],"type":"Point"}
}