{
  "type": "Feature",
  "properties": {
    "iso:country":"IT",
    "sg:address":"10, V. S. Antonio 83020 Quindici",
    "sg:city":"Quindici",
    "sg:classifiers":[
        {
            "category":"Farming",
            "subcategory":"Livestock Farm",
            "type":"Manufacturing & Wholesale Goods"
        }
    ],
    "sg:phone":"+39 081 824 0256",
    "sg:postcode":"83020",
    "sg:province":"Avellino",
    "sg:tags":[
        "agriculture"
    ],
    "sg:website":"http://www.paginegialle.it/santanielloumberto",
    "wof:name":"Fratelli Santaniello Srl",
    "wof:placetype":"venue"
},
  "geometry": {"coordinates":[14.712078,40.891716],"type":"Point"}
}