{
  "type": "Feature",
  "properties": {
    "addr:full":"50041 Calenzano Calenzano Firenze 50041",
    "addr:postcode":"50041;50041",
    "iso:country":"IT",
    "sg:address":"50041 Calenzano",
    "sg:city":"Calenzano",
    "sg:orig_category":"Forniture Per Agricoltura E Zootecnia. Animali Domestici",
    "sg:phone":"+39 055 882 6156",
    "sg:postcode":"50041",
    "sg:province":"Firenze",
    "wof:name":"Paoletti Mangimi",
    "wof:placetype":"venue"
},
  "geometry": {"coordinates":[11.1738777161,43.8421211243],"type":"Point"}
}