{
  "type": "Feature",
  "properties": {
    "iso:country":"IT",
    "sg:address":"15, Via Eridano 44100 Ferrara",
    "sg:city":"Ferrara",
    "sg:classifiers":[
        {
            "category":"Manufacturing",
            "subcategory":"Metals",
            "type":"Manufacturing & Wholesale Goods"
        }
    ],
    "sg:phone":"+39 0532 770420",
    "sg:postcode":"44100",
    "sg:province":"Ferrara",
    "sg:tags":[
        "metallurgy",
        "metalworking"
    ],
    "wof:name":"Elba Di Ferraresi & C. (s.r.l.)",
    "wof:placetype":"venue"
},
  "geometry": {"coordinates":[11.5855083466,44.8538780212],"type":"Point"}
}