{
  "type": "Feature",
  "properties": {
    "addr:full":"Corso Nizza 90; Cuneo; 12100 Cuneo Cuneo 12100",
    "addr:housenumber":"90",
    "addr:postcode":"12100;12100",
    "addr:street":"Corso Nizza",
    "iso:country":"IT",
    "sg:address":"Corso Nizza 90; Cuneo; 12100",
    "sg:city":"Cuneo",
    "sg:classifiers":[
        {
            "category":"Banks & Credit Unions",
            "subcategory":"Bank",
            "type":"Services"
        }
    ],
    "sg:phone":"+39 0171 691910",
    "sg:postcode":"12100",
    "sg:province":"Cuneo",
    "wof:name":"Cassa Di Risparmio Di Savigliano Spa",
    "wof:placetype":"venue"
},
  "geometry": {"coordinates":[7.537561,44.379387],"type":"Point"}
}