{
  "type": "Feature",
  "properties": {
    "iso:country":"IT",
    "sg:address":"04019 Terracina",
    "sg:city":"Terracina",
    "sg:orig_category":"Non-classified Establishments",
    "sg:phone":"+39 0773 705956",
    "sg:postcode":"04019",
    "sg:province":"Latina",
    "wof:name":"Vetreria Europa Srl",
    "wof:placetype":"venue"
},
  "geometry": {"coordinates":[13.043046,41.431461],"type":"Point"}
}