{
  "type": "Feature",
  "properties": {
    "addr:full":"25068 Sarezzo Sarezzo Brescia 25068",
    "addr:postcode":"25068;25068",
    "iso:country":"IT",
    "sg:address":"25068 Sarezzo",
    "sg:city":"Sarezzo",
    "sg:orig_category":"Arredo Bagno Ed Idrosanitari. Idrosanitari E Accessori",
    "sg:phone":"+39 030 802101",
    "sg:postcode":"25068",
    "sg:province":"Brescia",
    "sg:website":"http://www.ibtorbre.it",
    "wof:name":"Ib Torbre Rubinetterie Srl",
    "wof:placetype":"venue"
},
  "geometry": {"coordinates":[10.199898,45.649101],"type":"Point"}
}