{
  "type": "Feature",
  "properties": {
    "iso:country":"IT",
    "sg:address":"20149 Milano",
    "sg:city":"Milano",
    "sg:orig_category":"Prodotti E Manufatti In Materie Plastiche",
    "sg:postcode":"20149",
    "sg:province":"Milano",
    "wof:name":"Omnia (s.r.l.)",
    "wof:placetype":"venue"
},
  "geometry": {"coordinates":[9.1559762955,45.481464386],"type":"Point"}
}