{
  "type": "Feature",
  "properties": {
    "addr:full":"19121 La Spezia SP",
    "addr:housenumber":"19121",
    "iso:country":"IT",
    "sg:address":"19121 La Spezia",
    "sg:orig_category":"Banche E Servizi Finanziari",
    "sg:phone":"+39 0187 773427",
    "sg:province":"SP",
    "wof:name":"Cassa Di Risparmio Della Spezia",
    "wof:placetype":"venue"
},
  "geometry": {"coordinates":[9.819271,44.104679],"type":"Point"}
}