{
  "type": "Feature",
  "properties": {
    "iso:country":"IT",
    "sg:address":"63020 Falerone",
    "sg:city":"Falerone",
    "sg:orig_category":"Arti Grafiche",
    "sg:phone":"+39 0734 710112",
    "sg:postcode":"63020",
    "sg:province":"Ascoli Piceno",
    "wof:name":"Tipografia Menicucci Snc",
    "wof:placetype":"venue"
},
  "geometry": {"coordinates":[13.471705,43.10627],"type":"Point"}
}