{
  "type": "Feature",
  "properties": {
    "iso:country":"IT",
    "sg:address":"20144 Milano",
    "sg:city":"Milano",
    "sg:orig_category":"Minuterie Metalliche E Ferramenta",
    "sg:phone":"+39 02 5810 0572",
    "sg:postcode":"20144",
    "sg:province":"Milano",
    "wof:name":"Vigano' Pietro Snc",
    "wof:placetype":"venue"
},
  "geometry": {"coordinates":[9.1664209366,45.4556312561],"type":"Point"}
}