{
  "type": "Feature",
  "properties": {
    "addr:full":"20, V. Mascagni 22066 Mariano Comense Mariano Comense Como 22066",
    "addr:housenumber":"20",
    "addr:postcode":"22066;22066",
    "addr:street":"V. Mascagni",
    "iso:country":"IT",
    "sg:address":"20, V. Mascagni 22066 Mariano Comense",
    "sg:city":"Mariano Comense",
    "sg:classifiers":[
        {
            "category":"Manufacturing",
            "subcategory":"Lumber",
            "type":"Manufacturing & Wholesale Goods"
        }
    ],
    "sg:phone":"+39 39031746588",
    "sg:postcode":"22066",
    "sg:province":"Como",
    "sg:tags":[
        "wood"
    ],
    "sg:website":"http://www.interplac.com:ws_end: :mark:ws:http://www.paginegialle.it/interplac",
    "wof:name":"Interplac Srl",
    "wof:placetype":"venue"
},
  "geometry": {"coordinates":[9.085456,45.811966],"type":"Point"}
}