{
  "type": "Feature",
  "properties": {
    "iso:country":"IT",
    "sg:address":"36072 Chiampo",
    "sg:city":"Chiampo",
    "sg:orig_category":"Marmo, Pietre Ed Affini",
    "sg:phone":"+39 0444 420302",
    "sg:postcode":"36072",
    "sg:province":"Vicenza",
    "wof:name":"S.i.c.c. Srl",
    "wof:placetype":"venue"
},
  "geometry": {"coordinates":[11.276385,45.54105],"type":"Point"}
}