{
  "type": "Feature",
  "properties": {
    "addr:full":"103, Strada St. Del Santo 35010 Cadoneghe Cadoneghe Padova 35010",
    "addr:postcode":"35010;35010",
    "addr:street":"Strada St. Del Santo",
    "iso:country":"IT",
    "sg:address":"103, Strada St. Del Santo 35010 Cadoneghe",
    "sg:city":"Cadoneghe",
    "sg:classifiers":[
        {
            "category":"Shopping",
            "type":"Retail Goods"
        }
    ],
    "sg:phone":"+39 39049701233",
    "sg:postcode":"35010",
    "sg:province":"Padova",
    "sg:tags":[
        "finished",
        "-",
        "metallic"
    ],
    "wof:name":"I.p.p.i.s. (s.r.l.)",
    "wof:placetype":"venue"
},
  "geometry": {"coordinates":[11.8765888214,45.4095687866],"type":"Point"}
}