{
  "type": "Feature",
  "properties": {
    "iso:country":"IT",
    "sg:address":"88024 Girifalco",
    "sg:city":"Girifalco",
    "sg:orig_category":"Arredo Bagno Ed Idrosanitari. Idrosanitari E Accessori. Minuterie Metalliche E Ferramenta",
    "sg:phone":"+39 0968 748492",
    "sg:postcode":"88024",
    "sg:province":"Catanzaro",
    "wof:name":"L'edilsud Di Marinaro A. & C. Sas",
    "wof:placetype":"venue"
},
  "geometry": {"coordinates":[16.405254,38.80312],"type":"Point"}
}