{
  "type": "Feature",
  "properties": {
    "iso:country":"IT",
    "sg:address":"40040 San Benedetto Val Sambro",
    "sg:orig_category":"Fonderie",
    "sg:phone":"+39 0534 98315",
    "sg:province":"BO",
    "sg:website":"http://www.fmp-spa.it",
    "wof:name":"F.m.p. Spa",
    "wof:placetype":"venue"
},
  "geometry": {"coordinates":[11.215420723,44.1698303223],"type":"Point"}
}