{
  "type": "Feature",
  "properties": {
    "iso:country":"IT",
    "sg:address":"06012 Citt\u00e0 Di Castello",
    "sg:orig_category":"Edilizia - Attrezzature",
    "sg:phone":"+39 075 852 6176",
    "sg:postcode":"06012",
    "sg:province":"Perugia",
    "sg:website":"http://www.edilquattro.com",
    "wof:name":"Edilquattro Srl",
    "wof:placetype":"venue"
},
  "geometry": {"coordinates":[12.253138,43.43763],"type":"Point"}
}