{
  "type": "Feature",
  "properties": {
    "iso:country":"IT",
    "sg:address":"Vicolo Santa Croce 8; Tivoli",
    "sg:classifiers":[
        {
            "category":"Banks & Credit Unions",
            "subcategory":"Bank",
            "type":"Services"
        }
    ],
    "sg:phone":"+39 0774 332510",
    "wof:name":"Banca Di Roma",
    "wof:placetype":"venue"
},
  "geometry": {"coordinates":[12.798164,41.961521],"type":"Point"}
}