{
  "type": "Feature",
  "properties": {
    "iso:country":"IT",
    "sg:address":"33038 San Daniele Del Friuli",
    "sg:city":"San Daniele del Friuli",
    "sg:orig_category":"Prodotti Alimentari",
    "sg:phone":"+39 0432 942994",
    "sg:postcode":"33038",
    "sg:province":"Udine",
    "wof:name":"La Casa Del Prosciutto Snc Di Castellani Caterina E Figlio",
    "wof:placetype":"venue"
},
  "geometry": {"coordinates":[13.2381210327,46.0576210022],"type":"Point"}
}