{
  "type": "Feature",
  "properties": {
    "iso:country":"IT",
    "sg:address":"32, Via Italia 20060 Gessate",
    "sg:city":"Gessate",
    "sg:classifiers":[
        {
            "category":"Wholesale",
            "subcategory":"Machinery & Supplies",
            "type":"Manufacturing & Wholesale Goods"
        }
    ],
    "sg:phone":"+39 02 9578 1144",
    "sg:postcode":"20060",
    "sg:province":"Milano",
    "sg:tags":[
        "equipment",
        "-",
        "instrument",
        "measurement"
    ],
    "wof:name":"Arthermo (s.r.l.)",
    "wof:placetype":"venue"
},
  "geometry": {"coordinates":[9.420921,45.555359],"type":"Point"}
}