{
  "type": "Feature",
  "properties": {
    "iso:country":"IT",
    "sg:address":"10121 Torino",
    "sg:city":"Torino",
    "sg:orig_category":"Macchine, Impianti E Forniture Per Industria Grafica, Cartaria E Cartotecnica. Automazione E Macchine Per Ufficio",
    "sg:phone":"+39 011 561 1206",
    "sg:postcode":"10121",
    "sg:province":"Torino",
    "wof:name":"Bellucci Srl",
    "wof:placetype":"venue"
},
  "geometry": {"coordinates":[7.6781,45.067207],"type":"Point"}
}