{
  "type": "Feature",
  "properties": {
    "iso:country":"IT",
    "sg:address":"36070 Castelgomberto",
    "sg:city":"Castelgomberto",
    "sg:orig_category":"Forniture Per Agricoltura E Zootecnia. Animali Domestici",
    "sg:phone":"+39 0445 940980",
    "sg:postcode":"36070",
    "sg:province":"Vicenza",
    "wof:name":"Nova Food S.r.l.",
    "wof:placetype":"venue"
},
  "geometry": {"coordinates":[11.5221643448,45.5569572449],"type":"Point"}
}