{
  "type": "Feature",
  "properties": {
    "iso:country":"IT",
    "sg:address":"20121 Milano",
    "sg:city":"Milano",
    "sg:orig_category":"Arte Ed Artigianato Artistico. Scuole E Servizi Scolastici. Servizi Ausiliari Di Analisi, Controllo E Ricerca",
    "sg:phone":"+39 02 7600 5071",
    "sg:postcode":"20121",
    "sg:province":"Milano",
    "wof:name":"Accademia Arti Applicate",
    "wof:placetype":"venue"
},
  "geometry": {"coordinates":[9.190015,45.465603],"type":"Point"}
}