{
  "type": "Feature",
  "properties": {
    "iso:country":"IT",
    "sg:address":"Via Rimembranze 7 25012 Calvisano",
    "sg:city":"Calvisano",
    "sg:classifiers":[
        {
            "category":"Autos & Motor Vehicles",
            "subcategory":"Boat Sales",
            "type":"Retail Goods"
        }
    ],
    "sg:phone":"+39 030 996 8132",
    "sg:postcode":"25012",
    "sg:province":"Brescia",
    "sg:tags":[
        "varnish"
    ],
    "sg:website":"www.poli3.it",
    "wof:name":"Poly 3 Srl",
    "wof:placetype":"venue"
},
  "geometry": {"coordinates":[10.348443,45.349258],"type":"Point"}
}