{
  "type": "Feature",
  "properties": {
    "iso:country":"IT",
    "sg:address":"48018 Faenza",
    "sg:city":"Faenza",
    "sg:orig_category":"Salotti, Poltrone, Sedie E Tavoli",
    "sg:phone":"+39 0546 620015",
    "sg:postcode":"48018",
    "sg:province":"Ravenna",
    "sg:website":"http://www.berdonini.it",
    "wof:name":"Berdondini Srl",
    "wof:placetype":"venue"
},
  "geometry": {"coordinates":[11.850488,44.299187],"type":"Point"}
}