{
  "type": "Feature",
  "properties": {
    "addr:full":"56019 Migliarino Migliarino Pisa 56019",
    "addr:postcode":"56019;56019",
    "addr:street":"Migliarino",
    "iso:country":"IT",
    "sg:address":"56019 Migliarino",
    "sg:city":"Migliarino",
    "sg:orig_category":"Arredo Cucina Ed Elettrodomestici. Frigotecnica, Apparecchiature E Servizi. Elettrodomestici",
    "sg:phone":"+39 050 804452",
    "sg:postcode":"56019",
    "sg:province":"Pisa",
    "wof:name":"Giusti Stefano",
    "wof:placetype":"venue"
},
  "geometry": {"coordinates":[10.336577,43.757641],"type":"Point"}
}