{
  "type": "Feature",
  "properties": {
    "addr:full":"6, Via Monte Angiolino 10074 Lanzo Torinese Lanzo Torinese Torino 10074",
    "addr:postcode":"10074;10074",
    "addr:street":"Via Monte Angiolino",
    "iso:country":"IT",
    "sg:address":"6, Via Monte Angiolino 10074 Lanzo Torinese",
    "sg:city":"Lanzo Torinese",
    "sg:classifiers":[
        {
            "category":"Wholesale",
            "subcategory":"Drugs",
            "type":"Manufacturing & Wholesale Goods"
        }
    ],
    "sg:phone":"+39 39012327117",
    "sg:postcode":"10074",
    "sg:province":"Torino",
    "sg:tags":[
        "chemical",
        "pharmaceutical"
    ],
    "wof:name":"Italresine Srl",
    "wof:placetype":"venue"
},
  "geometry": {"coordinates":[7.479612,45.275887],"type":"Point"}
}