{
  "type": "Feature",
  "properties": {
    "addr:full":"00169 Roma Roma Roma 00169",
    "addr:postcode":"00169;00169",
    "iso:country":"IT",
    "sg:address":"00169 Roma",
    "sg:city":"Roma",
    "sg:orig_category":"Dolciumi E Gelati",
    "sg:phone":"+39 06 723 2620",
    "sg:postcode":"00169",
    "sg:province":"Roma",
    "wof:name":"Aliment 90 (s.r.l.)",
    "wof:placetype":"venue"
},
  "geometry": {"coordinates":[12.590051,41.864365],"type":"Point"}
}