{
  "type": "Feature",
  "properties": {
    "addr:full":"12, Via Boccaccio 50060 Pelago Pelago Firenze 50060",
    "addr:postcode":"50060;50060",
    "addr:street":"Via Boccaccio",
    "iso:country":"IT",
    "sg:address":"12, Via Boccaccio 50060 Pelago",
    "sg:city":"Pelago",
    "sg:classifiers":[
        {
            "category":"Personal",
            "subcategory":"Shoe Repair & Shine",
            "type":"Services"
        }
    ],
    "sg:phone":"+39 055 831 4751",
    "sg:postcode":"50060",
    "sg:province":"Firenze",
    "sg:tags":[
        "leather"
    ],
    "wof:name":"Pelletteria Alba",
    "wof:placetype":"venue"
},
  "geometry": {"coordinates":[11.449112,43.78138],"type":"Point"}
}