{
  "type": "Feature",
  "properties": {
    "addr:full":"20145 Milano Milano Milano 20145",
    "addr:postcode":"20145;20145",
    "iso:country":"IT",
    "sg:address":"20145 Milano",
    "sg:city":"Milano",
    "sg:orig_category":"Prodotti E Manufatti In Materie Plastiche",
    "sg:phone":"+39 02 349 0518",
    "sg:postcode":"20145",
    "sg:province":"Milano",
    "wof:name":"V.a.m.p. Srl",
    "wof:placetype":"venue"
},
  "geometry": {"coordinates":[9.1602582932,45.4782524109],"type":"Point"}
}