{
  "type": "Feature",
  "properties": {
    "iso:country":"IT",
    "sg:address":"10149 Torino",
    "sg:city":"Torino",
    "sg:orig_category":"Prodotti Chimici Secondari. Medicinali E Prodotti Parafarmaceutici",
    "sg:phone":"+39 011 737746",
    "sg:postcode":"10149",
    "sg:province":"Torino",
    "wof:name":"Neo - Farma Snc Di Boggia & C.",
    "wof:placetype":"venue"
},
  "geometry": {"coordinates":[7.657705307,45.1011810303],"type":"Point"}
}