{
  "type": "Feature",
  "properties": {
    "iso:country":"IT",
    "sg:address":"30033 Noale",
    "sg:city":"Noale",
    "sg:orig_category":"Servizi E Lavori Per Edilizia E Lavori Pubblici. Banche E Servizi Finanziari",
    "sg:phone":"+39 041 440165",
    "sg:postcode":"30033",
    "sg:province":"Venezia",
    "wof:name":"Edilizia Ragazzo Snc Di Ragazzo Francesco E C.",
    "wof:placetype":"venue"
},
  "geometry": {"coordinates":[12.078292,45.547256],"type":"Point"}
}