{
  "type": "Feature",
  "properties": {
    "iso:country":"IT",
    "sg:address":"Via Rizzoli 6; Bologna; 40125",
    "sg:city":"Bologna",
    "sg:classifiers":[
        {
            "category":"Banks & Credit Unions",
            "subcategory":"Bank",
            "type":"Services"
        }
    ],
    "sg:phone":"+39 051 523524",
    "sg:postcode":"40125",
    "sg:province":"Bologna",
    "wof:name":"Monte Dei Paschi Di Siena",
    "wof:placetype":"venue"
},
  "geometry": {"coordinates":[11.343243,44.494743],"type":"Point"}
}