{
  "type": "Feature",
  "properties": {
    "addr:full":"178, Via Marco Emilio Lepido 40132 Bologna Bologna Bologna 40132",
    "addr:housenumber":"178",
    "addr:postcode":"40132;40132",
    "addr:street":"Via Marco Emilio Lepido",
    "iso:country":"IT",
    "sg:address":"178, Via Marco Emilio Lepido 40132 Bologna",
    "sg:city":"Bologna",
    "sg:classifiers":[
        {
            "category":"Manufacturing",
            "subcategory":"Rubber & Plastics",
            "type":"Manufacturing & Wholesale Goods"
        }
    ],
    "sg:phone":"+39 051 413 1411",
    "sg:postcode":"40132",
    "sg:province":"Bologna",
    "wof:name":"Ssl Healthcare Italia Spa",
    "wof:placetype":"venue"
},
  "geometry": {"coordinates":[11.270086,44.519241],"type":"Point"}
}