{
  "type": "Feature",
  "properties": {
    "iso:country":"IT",
    "sg:address":"12039 Verzuolo",
    "sg:city":"Verzuolo",
    "sg:orig_category":"Termotecnica E Riscaldamento, Apparecchiature E Servizi",
    "sg:phone":"+39 0175 289580",
    "sg:postcode":"12039",
    "sg:province":"Cuneo",
    "wof:name":"C.c.t. Caldereria Costruzioni Termomeccaniche S.r.l.",
    "wof:placetype":"venue"
},
  "geometry": {"coordinates":[7.551807,44.393394],"type":"Point"}
}