{
  "type": "Feature",
  "properties": {
    "iso:country":"IT",
    "sg:address":"Via Spineda 12 31040 Volpago Del Montello",
    "sg:city":"Volpago del Montello",
    "sg:orig_category":"Ladies' Shoes",
    "sg:phone":"+39 0423 8726",
    "sg:postcode":"31040",
    "sg:province":"Treviso",
    "sg:website":"www.garmont.com",
    "wof:name":"Calzaturificio Morlin Srl",
    "wof:placetype":"venue"
},
  "geometry": {"coordinates":[12.102073,45.77824],"type":"Point"}
}