{
  "type": "Feature",
  "properties": {
    "iso:country":"IT",
    "sg:address":"20021 Baranzate",
    "sg:city":"Baranzate",
    "sg:orig_category":"Acciaierie E Fonderie",
    "sg:postcode":"20021",
    "sg:province":"Milano",
    "wof:name":"Metalfond (s.p.a.)",
    "wof:placetype":"venue"
},
  "geometry": {"coordinates":[9.103831,45.526398],"type":"Point"}
}