{
  "type": "Feature",
  "properties": {
    "iso:country":"IT",
    "sg:address":"20129 Milano",
    "sg:city":"Milano",
    "sg:orig_category":"Servizi Ausiliari Dei Mezzi Di Trasporto",
    "sg:phone":"+39 02 201135",
    "sg:postcode":"20129",
    "sg:province":"Milano",
    "wof:name":"Autorimessa Maffio (s.n.c.)",
    "wof:placetype":"venue"
},
  "geometry": {"coordinates":[9.218638,45.476158],"type":"Point"}
}