{
  "type": "Feature",
  "properties": {
    "addr:full":"10, Via Vittorio Veneto 70037 Ruvo Di Puglia Ruvo di Puglia Bari 70037",
    "addr:postcode":"70037;70037",
    "addr:street":"Via Vittorio Veneto",
    "iso:country":"IT",
    "sg:address":"10, Via Vittorio Veneto 70037 Ruvo Di Puglia",
    "sg:city":"Ruvo di Puglia",
    "sg:classifiers":[
        {
            "category":"Shopping",
            "subcategory":"Jewelry",
            "type":"Retail Goods"
        }
    ],
    "sg:phone":"+39 080 362 8285",
    "sg:postcode":"70037",
    "sg:province":"Bari",
    "sg:tags":[
        "jewellery"
    ],
    "wof:name":"Caputi Milena",
    "wof:placetype":"venue"
},
  "geometry": {"coordinates":[16.485199,41.11554],"type":"Point"}
}