{
  "type": "Feature",
  "properties": {
    "addr:full":"28014 Maggiora Maggiora Novara 28014",
    "addr:postcode":"28014;28014",
    "iso:country":"IT",
    "sg:address":"28014 Maggiora",
    "sg:city":"Maggiora",
    "sg:orig_category":"Termotecnica E Riscaldamento, Apparecchiature E Servizi",
    "sg:phone":"+39 0322 87162",
    "sg:postcode":"28014",
    "sg:province":"Novara",
    "wof:name":"Wolden Bruciatori",
    "wof:placetype":"venue"
},
  "geometry": {"coordinates":[8.418377,45.684784],"type":"Point"}
}