{
  "type": "Feature",
  "properties": {
    "iso:country":"IT",
    "sg:address":"20020 Dairago",
    "sg:city":"Dairago",
    "sg:orig_category":"Abbigliamento Esterno, Maglierie E Pelliccerie. Calzature, Pelletterie E Pelli. Sport - Articoli E Forniture. Shopping",
    "sg:phone":"+39 0331 436196",
    "sg:postcode":"20020",
    "sg:province":"Milano",
    "wof:name":"Quick And Slow Di Tedeschi Gioacchino",
    "wof:placetype":"venue"
},
  "geometry": {"coordinates":[8.862543,45.565796],"type":"Point"}
}