{
  "type": "Feature",
  "properties": {
    "iso:country":"IT",
    "sg:address":"70121 Bari",
    "sg:city":"Bari",
    "sg:orig_category":"Abbigliamento Esterno, Maglierie E Pelliccerie",
    "sg:phone":"+39 080 521 3715",
    "sg:postcode":"70121",
    "sg:province":"Bari",
    "wof:name":"La Patriottica Sas",
    "wof:placetype":"venue"
},
  "geometry": {"coordinates":[16.8713,41.124146],"type":"Point"}
}