{
  "type": "Feature",
  "properties": {
    "iso:country":"IT",
    "sg:address":"18, Via Vannucci Pietro 25134 Brescia",
    "sg:city":"Brescia",
    "sg:classifiers":[
        {
            "category":"Professional",
            "subcategory":"Engineering",
            "type":"Services"
        }
    ],
    "sg:phone":"+39 030 230 4773",
    "sg:postcode":"25134",
    "sg:province":"Brescia",
    "sg:tags":[
        "machine",
        "-",
        "mechanical"
    ],
    "wof:name":"Chiaf Fratelli (s.n.c.)",
    "wof:placetype":"venue"
},
  "geometry": {"coordinates":[10.258421,45.514915],"type":"Point"}
}