{
  "type": "Feature",
  "properties": {
    "iso:country":"IT",
    "sg:address":"11028 Valtournenche",
    "sg:city":"Valtournenche",
    "sg:orig_category":"Servizi Per Lo Sport E Il Tempo Libero. Servizi Al Turismo",
    "sg:phone":"+39 0166 92221",
    "sg:postcode":"11028",
    "sg:province":"Aosta",
    "wof:name":"Cime Bianche (s.p.a.)",
    "wof:placetype":"venue"
},
  "geometry": {"coordinates":[7.627372,45.89735],"type":"Point"}
}