{
  "type": "Feature",
  "properties": {
    "iso:country":"IT",
    "sg:address":"00167 Roma",
    "sg:city":"Roma",
    "sg:orig_category":"Dolciumi E Gelati",
    "sg:phone":"+39 06 614 5048",
    "sg:postcode":"00167",
    "sg:province":"Roma",
    "wof:name":"Lucci Cecilia",
    "wof:placetype":"venue"
},
  "geometry": {"coordinates":[12.419884,41.91333],"type":"Point"}
}