{
  "type": "Feature",
  "properties": {
    "iso:country":"IT",
    "sg:address":"109, Via Chiopris 33048 San Giovanni Al Natisone",
    "sg:city":"Chiopris",
    "sg:classifiers":[
        {
            "category":"Home & Garden",
            "subcategory":"Home Furnishings",
            "type":"Retail Goods"
        }
    ],
    "sg:phone":"+39 0432 758023",
    "sg:postcode":"33048",
    "sg:province":"Udine",
    "sg:tags":[
        "household"
    ],
    "wof:name":"Pizzamiglio",
    "wof:placetype":"venue"
},
  "geometry": {"coordinates":[13.396879,45.936253],"type":"Point"}
}