{
  "type": "Feature",
  "properties": {
    "addr:full":"34, Via Di Portovecchio 57025 Piombino Piombino Livorno 57025",
    "addr:postcode":"57025;57025",
    "addr:street":"Via Di Portovecchio",
    "iso:country":"IT",
    "sg:address":"34, Via Di Portovecchio 57025 Piombino",
    "sg:city":"Piombino",
    "sg:classifiers":[
        {
            "category":"Manufacturing",
            "subcategory":"Metals",
            "type":"Manufacturing & Wholesale Goods"
        }
    ],
    "sg:phone":"+39 39056535150",
    "sg:postcode":"57025",
    "sg:province":"Livorno",
    "sg:tags":[
        "processing"
    ],
    "wof:name":"La Magona D'italia Spa",
    "wof:placetype":"venue"
},
  "geometry": {"coordinates":[10.5388212204,42.9343109131],"type":"Point"}
}