{
  "type": "Feature",
  "properties": {
    "iso:country":"IT",
    "sg:address":"22060 Arosio",
    "sg:city":"Arosio",
    "sg:orig_category":"Servizi E Lavori Per Arredamento E Industria Del Legno. Arte Ed Artigianato Artistico",
    "sg:phone":"+39 031 761119",
    "sg:postcode":"22060",
    "sg:province":"Como",
    "wof:name":"Terraneo Fratelli",
    "wof:placetype":"venue"
},
  "geometry": {"coordinates":[9.209241,45.717983],"type":"Point"}
}