{
  "type": "Feature",
  "properties": {
    "addr:full":"19, Via Del Cardine 10080 Bosconero Bosconero Torino 10080",
    "addr:postcode":"10080;10080",
    "addr:street":"Via Del Cardine",
    "iso:country":"IT",
    "sg:address":"19, Via Del Cardine 10080 Bosconero",
    "sg:city":"Bosconero",
    "sg:classifiers":[
        {
            "category":"Manufacturing",
            "subcategory":"Metals",
            "type":"Manufacturing & Wholesale Goods"
        }
    ],
    "sg:phone":"+39 011 988 6174",
    "sg:postcode":"10080",
    "sg:province":"Torino",
    "sg:tags":[
        "metallurgy",
        "metalworking"
    ],
    "wof:name":"Sochi Di Chiarini E C. Snc",
    "wof:placetype":"venue"
},
  "geometry": {"coordinates":[7.7575364113,45.2662811279],"type":"Point"}
}