{
  "type": "Feature",
  "properties": {
    "addr:full":"95014 Giarre Giarre Catania 95014",
    "addr:postcode":"95014;95014",
    "iso:country":"IT",
    "sg:address":"95014 Giarre",
    "sg:city":"Giarre",
    "sg:orig_category":"Medicinali E Prodotti Parafarmaceutici. Prodotti Cosmetici E Da Toeletta",
    "sg:phone":"+39 095 932476",
    "sg:postcode":"95014",
    "sg:province":"Catania",
    "wof:name":"Alch Di D'amore Carmelo",
    "wof:placetype":"venue"
},
  "geometry": {"coordinates":[15.1668329239,37.7233695984],"type":"Point"}
}