{
  "type": "Feature",
  "properties": {
    "iso:country":"IT",
    "sg:address":"20016 Pero",
    "sg:city":"Pero",
    "sg:orig_category":"Elettrotecnica Industriale, Prodotti E Apparecchiature. Impianti, Attrezzature E Forniture Sanitarie Ed Ospedaliere. Forniture Per Attivita' Industriali",
    "sg:phone":"+39 02 339 0433",
    "sg:postcode":"20016",
    "sg:province":"Milano",
    "wof:name":"U.v. Ray Srl",
    "wof:placetype":"venue"
},
  "geometry": {"coordinates":[8.39892,45.462345],"type":"Point"}
}