{
  "type": "Feature",
  "properties": {
    "iso:country":"IT",
    "sg:address":"24040 Bottanuco",
    "sg:city":"Bottanuco",
    "sg:orig_category":"Bandiere E Stendardi",
    "sg:phone":"+39 035 499 2053",
    "sg:postcode":"24040",
    "sg:province":"Bergamo",
    "sg:website":"http://www.studiomirage.it",
    "wof:name":"Mirage Snc Di Balossi Mauro & C.",
    "wof:placetype":"venue"
},
  "geometry": {"coordinates":[9.509463,45.645954],"type":"Point"}
}