{
  "type": "Feature",
  "properties": {
    "addr:full":"35010 Grossa Padova 35010",
    "addr:postcode":"35010;35010",
    "iso:country":"IT",
    "sg:address":"35010 Grossa",
    "sg:orig_category":"Legno E Semilavorati",
    "sg:phone":"+39 049 596 3194",
    "sg:postcode":"35010",
    "sg:province":"Padova",
    "wof:name":"An.pa Di Ceccato Gianpaolo & C. S.a.s.",
    "wof:placetype":"venue"
},
  "geometry": {"coordinates":[11.709914,45.551922],"type":"Point"}
}