{
  "type": "Feature",
  "properties": {
    "iso:country":"IT",
    "sg:address":"52025 Montevarchi",
    "sg:city":"Montevarchi",
    "sg:orig_category":"Modelli Per Sartoria E Abbigliamento",
    "sg:phone":"+39 055 900223",
    "sg:postcode":"52025",
    "sg:province":"Arezzo",
    "sg:website":"http://www.tecnomoda.it",
    "wof:name":"Tecnomoda Di Mazzi Graziella",
    "wof:placetype":"venue"
},
  "geometry": {"coordinates":[11.5589103699,43.5000801086],"type":"Point"}
}