{
  "type": "Feature",
  "properties": {
    "addr:full":"12, Via Gnocchi Don Carlo 20148 Milano Milano Milano 20148",
    "addr:postcode":"20148;20148",
    "addr:street":"Via Gnocchi Don Carlo",
    "iso:country":"IT",
    "sg:address":"12, Via Gnocchi Don Carlo 20148 Milano",
    "sg:city":"Milano",
    "sg:classifiers":[
        {
            "category":"Professional",
            "subcategory":"Engineering",
            "type":"Services"
        }
    ],
    "sg:phone":"+39 02 4009 2188",
    "sg:postcode":"20148",
    "sg:province":"Milano",
    "sg:tags":[
        "machine",
        "-",
        "mechanical"
    ],
    "wof:name":"Lem Graphic International (s.r.l.)",
    "wof:placetype":"venue"
},
  "geometry": {"coordinates":[9.203226,45.482468],"type":"Point"}
}