{
  "type": "Feature",
  "properties": {
    "iso:country":"IT",
    "sg:address":"36077 Altavilla Vicentina",
    "sg:city":"Altavilla Vicentina",
    "sg:orig_category":"Ceramiche Per Pavimenti E Rivestimenti - Vendita Al Dettaglio",
    "sg:phone":"+39 0444 522751",
    "sg:postcode":"36077",
    "sg:province":"Vicenza",
    "wof:name":"Edil 2000 Centro Mosaico",
    "wof:placetype":"venue"
},
  "geometry": {"coordinates":[11.487274,45.519459],"type":"Point"}
}