{
  "type": "Feature",
  "properties": {
    "iso:country":"IT",
    "sg:address":"72100 Brindisi",
    "sg:city":"Brindisi",
    "sg:orig_category":"Trasporti E Spedizioni Merci",
    "sg:phone":"+39 0831 571549",
    "sg:postcode":"72100",
    "sg:province":"Brindisi",
    "wof:name":"Bartolini Spa",
    "wof:placetype":"venue"
},
  "geometry": {"coordinates":[17.950823,40.621315],"type":"Point"}
}