{
  "type": "Feature",
  "properties": {
    "addr:full":"16044 Cicagna Cicagna Genova 16044",
    "addr:postcode":"16044;16044",
    "iso:country":"IT",
    "sg:address":"16044 Cicagna",
    "sg:city":"Cicagna",
    "sg:orig_category":"Prodotti E Manufatti In Materie Plastiche. Forniture Per Edilizia E Lavori Pubblici",
    "sg:phone":"+39 0185 92399",
    "sg:postcode":"16044",
    "sg:province":"Genova",
    "sg:website":"http://www.www.effast.com",
    "wof:name":"Effast Srl",
    "wof:placetype":"venue"
},
  "geometry": {"coordinates":[9.2397603989,44.4062309265],"type":"Point"}
}