{
  "type": "Feature",
  "properties": {
    "addr:full":"20, Via Bovon 31030 Breda Di Piave Breda di Piave Treviso 31030",
    "addr:postcode":"31030;di piave;31030",
    "addr:street":"Via Bovon",
    "iso:country":"IT",
    "sg:address":"20, Via Bovon 31030 Breda Di Piave",
    "sg:city":"Breda di Piave",
    "sg:classifiers":[
        {
            "category":"Shopping",
            "subcategory":"Clothing, Apparel, & Fashions",
            "type":"Retail Goods"
        }
    ],
    "sg:phone":"+39 0422 988132",
    "sg:postcode":"31030",
    "sg:province":"Treviso",
    "sg:tags":[
        "clothes"
    ],
    "wof:name":"Anna E Lei S.n.c. Di Spigariol Anna & C.",
    "wof:placetype":"venue"
},
  "geometry": {"coordinates":[12.387511,45.717697],"type":"Point"}
}