{
  "type": "Feature",
  "properties": {
    "iso:country":"IT",
    "sg:address":"23821 Abbadia Lariana",
    "sg:city":"Abbadia Lariana",
    "sg:orig_category":"Rifiuti Civili, Industriali E Speciali - Impianti, Macchine E Attrezzature",
    "sg:phone":"+39 0341 702330",
    "sg:postcode":"23821",
    "sg:province":"Lecco",
    "sg:website":"http://www.bps-srl.com",
    "wof:name":"Bps Srl",
    "wof:placetype":"venue"
},
  "geometry": {"coordinates":[9.332222,45.90139],"type":"Point"}
}