{
  "type": "Feature",
  "properties": {
    "addr:full":"00187 Roma Roma Roma 00187",
    "addr:postcode":"00187;00187",
    "iso:country":"IT",
    "sg:address":"00187 Roma",
    "sg:city":"Roma",
    "sg:orig_category":"Gioielleria, Oreficeria E Argenteria. Shopping",
    "sg:phone":"+39 06 679 0462",
    "sg:postcode":"00187",
    "sg:province":"Roma",
    "wof:name":"Cimmino Domenico",
    "wof:placetype":"venue"
},
  "geometry": {"coordinates":[12.480123,41.905018],"type":"Point"}
}