{
  "type": "Feature",
  "properties": {
    "iso:country":"IT",
    "sg:address":"65026 Popoli",
    "sg:city":"Popoli",
    "sg:orig_category":"Bevande, Vini E Liquori",
    "sg:phone":"+39 085 98781",
    "sg:postcode":"65026",
    "sg:province":"Pescara",
    "wof:name":"Gran Guizza",
    "wof:placetype":"venue"
},
  "geometry": {"coordinates":[13.83322,42.16959],"type":"Point"}
}