{
  "type": "Feature",
  "properties": {
    "addr:full":"84122 Sant'egidio Del Montalbino Salerno 84122",
    "addr:postcode":"84122;84122",
    "iso:country":"IT",
    "sg:address":"84122 Sant'egidio Del Montalbino",
    "sg:classifiers":[
        {
            "category":"Home & Garden",
            "subcategory":"Building Materials",
            "type":"Retail Goods"
        }
    ],
    "sg:phone":"+39 338 108 4945",
    "sg:postcode":"84122",
    "sg:province":"Salerno",
    "sg:tags":[
        "gas",
        "caldaie"
    ],
    "wof:name":"Coop. Montalbino 86",
    "wof:placetype":"venue"
},
  "geometry": {"coordinates":[14.765912,40.677956],"type":"Point"}
}