{
  "type": "Feature",
  "properties": {
    "addr:full":"5, Via Luciani Papa 96010 Priolo Gargallo Priolo Gargallo Siracusa 96010",
    "addr:postcode":"96010;96010",
    "addr:street":"Via Luciani Papa",
    "iso:country":"IT",
    "sg:address":"5, Via Luciani Papa 96010 Priolo Gargallo",
    "sg:city":"Priolo Gargallo",
    "sg:classifiers":[
        {
            "category":"Shopping",
            "type":"Retail Goods"
        }
    ],
    "sg:phone":"+39 0931 760740",
    "sg:postcode":"96010",
    "sg:province":"Siracusa",
    "sg:tags":[
        "finished",
        "-",
        "metallic"
    ],
    "wof:name":"Edilmeccanica Srl",
    "wof:placetype":"venue"
},
  "geometry": {"coordinates":[15.2844400406,37.0664825439],"type":"Point"}
}