{
  "type": "Feature",
  "properties": {
    "addr:full":"25036 Palazzolo Sull'oglio Brescia 25036",
    "addr:postcode":"25036;25036",
    "iso:country":"IT",
    "sg:address":"25036 Palazzolo Sull'oglio",
    "sg:orig_category":"Prodotti E Manufatti In Materie Plastiche. Forniture Per Edilizia E Lavori Pubblici. Forniture E Materiali Per Imballaggio E Confezionamento",
    "sg:phone":"+39 030 730 1445",
    "sg:postcode":"25036",
    "sg:province":"Brescia",
    "wof:name":"Isomec Srl",
    "wof:placetype":"venue"
},
  "geometry": {"coordinates":[9.8897686005,45.6253890991],"type":"Point"}
}