{
  "type": "Feature",
  "properties": {
    "iso:country":"IT",
    "sg:address":"00040 Lariano",
    "sg:city":"Lariano",
    "sg:orig_category":"Chiese Ed Associazioni Religiose",
    "sg:phone":"+39 06 965 5374",
    "sg:postcode":"00040",
    "sg:province":"Roma",
    "wof:name":"Associazione Testimoni Di Geova Di Velletri E Lariano",
    "wof:placetype":"venue"
},
  "geometry": {"coordinates":[12.8285217285,41.7033042908],"type":"Point"}
}