{
  "type": "Feature",
  "properties": {
    "iso:country":"IT",
    "sg:address":"42015 Correggio",
    "sg:orig_category":"Materie Plastiche Lavorazione - Macchine",
    "sg:phone":"+39 0522 696614",
    "sg:postcode":"42015",
    "sg:province":"Reggio Nell'Emilia",
    "wof:name":"Project Uno Di Manghi Luca & C. Snc",
    "wof:placetype":"venue"
},
  "geometry": {"coordinates":[10.74332,44.700394],"type":"Point"}
}