{
  "type": "Feature",
  "properties": {
    "iso:country":"IT",
    "sg:address":"20154 Milano",
    "sg:city":"Milano",
    "sg:classifiers":[
        {
            "category":"Health Services",
            "subcategory":"Health Practitioner",
            "type":"Services"
        }
    ],
    "sg:phone":"+39 02 331 5480",
    "sg:postcode":"20154",
    "sg:province":"Milano",
    "sg:tags":[
        "medici"
    ],
    "wof:name":"Coniglio Salvatore",
    "wof:placetype":"venue"
},
  "geometry": {"coordinates":[9.168789,45.485416],"type":"Point"}
}