{
  "type": "Feature",
  "properties": {
    "iso:country":"IT",
    "sg:address":"35012 Camposampiero",
    "sg:city":"Camposampiero",
    "sg:orig_category":"Elettricisti",
    "sg:phone":"+39 049 930 2047",
    "sg:postcode":"35012",
    "sg:province":"Padova",
    "wof:name":"Perin Srl",
    "wof:placetype":"venue"
},
  "geometry": {"coordinates":[11.892162,45.420612],"type":"Point"}
}