{
  "type": "Feature",
  "properties": {
    "iso:country":"IT",
    "sg:address":"30126 Alberoni",
    "sg:city":"Alberoni",
    "sg:orig_category":"Alberghi E Strutture Extra Alberghiere. Ospedali E Servizi Sanitari",
    "sg:phone":"+39 041 731047",
    "sg:postcode":"30126",
    "sg:province":"Venezia",
    "wof:name":"Istituto Di Cura S. Camillo",
    "wof:placetype":"venue"
},
  "geometry": {"coordinates":[12.329558,45.358192],"type":"Point"}
}