{
  "type": "Feature",
  "properties": {
    "addr:full":"1, Via Repubblica 25065 Lumezzane Lumezzane Brescia 25065",
    "addr:postcode":"25065;25065",
    "addr:street":"Via Repubblica",
    "iso:country":"IT",
    "sg:address":"1, Via Repubblica 25065 Lumezzane",
    "sg:city":"Lumezzane",
    "sg:classifiers":[
        {
            "category":"Manufacturing",
            "subcategory":"Rubber & Plastics",
            "type":"Manufacturing & Wholesale Goods"
        }
    ],
    "sg:phone":"+39 39030872934",
    "sg:postcode":"25065",
    "sg:province":"Brescia",
    "wof:name":"Aellebi Dei Fratelli Berna (s.n.c.)",
    "wof:placetype":"venue"
},
  "geometry": {"coordinates":[10.2404060364,45.6532363892],"type":"Point"}
}