{
  "type": "Feature",
  "properties": {
    "iso:country":"IT",
    "sg:address":"Via Roma 41; Lecco",
    "sg:classifiers":[
        {
            "category":"Banks & Credit Unions",
            "subcategory":"Bank",
            "type":"Services"
        }
    ],
    "sg:phone":"+39 0341 362720",
    "wof:name":"Credito Valtellinese Scarl",
    "wof:placetype":"venue"
},
  "geometry": {"coordinates":[9.39033,45.853561],"type":"Point"}
}