{
  "type": "Feature",
  "properties": {
    "iso:country":"IT",
    "sg:address":"70124 Bari",
    "sg:city":"Bari",
    "sg:orig_category":"Macchine, Impianti Ed Attrezzature Industria Chimica. Impiantistica E Prodotti Tecnologici Per Edilizia. Impianti, Attrezzature E Forniture Sanitarie Ed Ospedaliere",
    "sg:phone":"+39 080 561 7548",
    "sg:postcode":"70124",
    "sg:province":"Bari",
    "wof:name":"Ferrara Giovanni Srl",
    "wof:placetype":"venue"
},
  "geometry": {"coordinates":[16.863804,41.107811],"type":"Point"}
}