{
  "type": "Feature",
  "properties": {
    "iso:country":"IT",
    "sg:address":"20093 Cologno Monzese",
    "sg:city":"Cologno Monzese",
    "sg:orig_category":"Nautica - Equipaggiamenti",
    "sg:phone":"+39 02 253 3275",
    "sg:postcode":"20093",
    "sg:province":"Milano",
    "sg:website":"http://nauticaled.com",
    "wof:name":"Nautica Led Srl",
    "wof:placetype":"venue"
},
  "geometry": {"coordinates":[9.275867,45.540741],"type":"Point"}
}