{
  "type": "Feature",
  "properties": {
    "addr:full":"90147 Palermo Palermo Palermo 90147",
    "addr:postcode":"90147;90147",
    "iso:country":"IT",
    "sg:address":"90147 Palermo",
    "sg:city":"Palermo",
    "sg:orig_category":"Macchine E Forniture Per Ecologia E Smaltimento Rifiuti",
    "sg:phone":"+39 091 691 1481",
    "sg:postcode":"90147",
    "sg:province":"Palermo",
    "wof:name":"Ecopolis S.r.l.",
    "wof:placetype":"venue"
},
  "geometry": {"coordinates":[13.282984,38.189232],"type":"Point"}
}