{
  "type": "Feature",
  "properties": {
    "addr:full":"89129 Reggio Calabria RC",
    "addr:postcode":"89129",
    "iso:country":"IT",
    "sg:address":"89129 Reggio Calabria",
    "sg:orig_category":"Ceramiche: Prodotti E Lavorazioni",
    "sg:phone":"+39 0965 370884",
    "sg:province":"RC",
    "sg:website":"http://carerefratelli.it",
    "wof:name":"Carere Antonio & Benito",
    "wof:placetype":"venue"
},
  "geometry": {"coordinates":[15.63832,38.082397],"type":"Point"}
}