{
  "type": "Feature",
  "properties": {
    "addr:full":"96100 Siracusa Siracusa Siracusa 96100",
    "addr:postcode":"96100;96100",
    "iso:country":"IT",
    "sg:address":"96100 Siracusa",
    "sg:city":"Siracusa",
    "sg:orig_category":"Macchine Utensili E Impianti",
    "sg:phone":"+39 0931 24327",
    "sg:postcode":"96100",
    "sg:province":"Siracusa",
    "wof:name":"Messina Nunzio",
    "wof:placetype":"venue"
},
  "geometry": {"coordinates":[15.260818,37.061367],"type":"Point"}
}