{
  "type": "Feature",
  "properties": {
    "iso:country":"IT",
    "sg:address":"87036 Rende",
    "sg:city":"Rende",
    "sg:orig_category":"Abbigliamento Esterno, Maglierie E Pelliccerie. Forniture Industriali Per Prevenzione, Controllo E Sicurezza",
    "sg:phone":"+39 0984 403846",
    "sg:postcode":"87036",
    "sg:province":"Cosenza",
    "wof:name":"Dl Confezione Artigianale Di Roberto Amato",
    "wof:placetype":"venue"
},
  "geometry": {"coordinates":[16.238714,39.353756],"type":"Point"}
}