{
  "type": "Feature",
  "properties": {
    "iso:country":"IT",
    "sg:address":"31015 Conegliano",
    "sg:city":"Conegliano",
    "sg:classifiers":[
        {
            "category":"Professional",
            "subcategory":"Business Services",
            "type":"Services"
        }
    ],
    "sg:phone":"+39 0438 64107",
    "sg:postcode":"31015",
    "sg:province":"Treviso",
    "sg:tags":[
        "support",
        "companies",
        "events",
        "trade"
    ],
    "wof:name":"Savic Stuani Adela",
    "wof:placetype":"venue"
},
  "geometry": {"coordinates":[12.300653,45.880432],"type":"Point"}
}