{
  "type": "Feature",
  "properties": {
    "iso:country":"IT",
    "sg:address":"47031 Repubblica Di San Marino",
    "sg:orig_category":"Scuole E Servizi Scolastici. Ricerca, Selezione E Formazione Del Personale",
    "sg:phone":"+39 0549 904133",
    "sg:province":"SM",
    "wof:name":"C.i.d. Corsi Di Insegnamento A Distanza Srl",
    "wof:placetype":"venue"
},
  "geometry": {"coordinates":[12.471645,43.960262],"type":"Point"}
}