{
  "type": "Feature",
  "properties": {
    "iso:country":"IT",
    "sg:address":"90133 Palermo",
    "sg:city":"Palermo",
    "sg:orig_category":"Motocicli E Motocarri - Commercio E Riparazione",
    "sg:phone":"+39 091 611 8475",
    "sg:postcode":"90133",
    "sg:province":"Palermo",
    "wof:name":"Evoluzione Moto Di Arcara Antonino",
    "wof:placetype":"venue"
},
  "geometry": {"coordinates":[13.3659486771,38.1154823303],"type":"Point"}
}