{
  "type": "Feature",
  "properties": {
    "iso:country":"IT",
    "sg:address":"37036 S. Martino Buon Albergo",
    "sg:orig_category":"Filati E Tessuti - Trattamenti",
    "sg:phone":"+39 045 887 1333",
    "sg:postcode":"37036",
    "sg:province":"Verona",
    "wof:name":"Trt Tintoria Resinatura Tessuti Srl",
    "wof:placetype":"venue"
},
  "geometry": {"coordinates":[11.0953454971,45.418258667],"type":"Point"}
}