{
  "type": "Feature",
  "properties": {
    "addr:full":"Via Galileo Ferraris 219; Napoli; 80149",
    "addr:housenumber":"219",
    "addr:postcode":"80149",
    "addr:street":"Via Galileo Ferraris",
    "iso:country":"IT",
    "sg:address":"Via Galileo Ferraris 219; Napoli; 80149",
    "sg:classifiers":[
        {
            "category":"Banks & Credit Unions",
            "subcategory":"Bank",
            "type":"Services"
        }
    ],
    "sg:phone":"+39 081 260765",
    "wof:name":"Banco Di Roma",
    "wof:placetype":"venue"
},
  "geometry": {"coordinates":[14.290721,40.849342],"type":"Point"}
}