{
  "type": "Feature",
  "properties": {
    "iso:country":"IT",
    "sg:address":"33074 Fontanafredda",
    "sg:city":"Fontanafredda",
    "sg:orig_category":"Termotecnica E Riscaldamento, Apparecchiature E Servizi",
    "sg:phone":"+39 0434 567111",
    "sg:postcode":"33074",
    "sg:province":"Pordenone",
    "wof:name":"I.m.a.t. Spa",
    "wof:placetype":"venue"
},
  "geometry": {"coordinates":[12.595577,45.983364],"type":"Point"}
}