{
  "type": "Feature",
  "properties": {
    "addr:full":"10071 Borgaro Torinese Borgaro Torinese Torino 10071",
    "addr:postcode":"10071;10071",
    "iso:country":"IT",
    "sg:address":"10071 Borgaro Torinese",
    "sg:city":"Borgaro Torinese",
    "sg:orig_category":"Prodotti E Manufatti In Materie Plastiche. Servizi E Lavori Industria Delle Materie Plastiche",
    "sg:phone":"+39 011 262 5657",
    "sg:postcode":"10071",
    "sg:province":"Torino",
    "wof:name":"O.g.e.m.p. Di Dalle Vedove Snc",
    "wof:placetype":"venue"
},
  "geometry": {"coordinates":[7.6894340515,45.1338653564],"type":"Point"}
}