{
  "type": "Feature",
  "properties": {
    "iso:country":"IT",
    "sg:address":"56038 Ponsacco",
    "sg:city":"Ponsacco",
    "sg:orig_category":"Servizi E Lavori Per Arredamento E Industria Del Legno",
    "sg:phone":"+39 0587 731630",
    "sg:postcode":"56038",
    "sg:province":"Pisa",
    "sg:website":"http://www.paginegialle.it/gradassi",
    "wof:name":"Gradassi Vasco - Gradassi Mobili",
    "wof:placetype":"venue"
},
  "geometry": {"coordinates":[10.401964,43.717171],"type":"Point"}
}