{
  "type": "Feature",
  "properties": {
    "addr:full":"Via Settola 51031 Agliana Agliana Pistoia 51031",
    "addr:postcode":"51031;51031",
    "addr:street":"Via Settola",
    "iso:country":"IT",
    "sg:address":"Via Settola 51031 Agliana",
    "sg:city":"Agliana",
    "sg:classifiers":[
        {
            "category":"Shopping",
            "subcategory":"Clothing, Apparel, & Fashions",
            "type":"Retail Goods"
        }
    ],
    "sg:phone":"+39 0574 710660",
    "sg:postcode":"51031",
    "sg:province":"Pistoia",
    "sg:tags":[
        "clothes"
    ],
    "wof:name":"Maglificio Valda Spa",
    "wof:placetype":"venue"
},
  "geometry": {"coordinates":[10.989279,43.912647],"type":"Point"}
}