{
  "type": "Feature",
  "properties": {
    "iso:country":"IT",
    "sg:address":"20144 Milano",
    "sg:city":"Milano",
    "sg:orig_category":"Abbigliamento Esterno, Maglierie E Pelliccerie. Shopping",
    "sg:phone":"+39 02 428696",
    "sg:postcode":"20144",
    "sg:province":"Milano",
    "wof:name":"Noblemen",
    "wof:placetype":"venue"
},
  "geometry": {"coordinates":[9.156224,45.453083],"type":"Point"}
}