{
  "type": "Feature",
  "properties": {
    "iso:country":"IT",
    "sg:address":"Via Terracini, 24 - Spedalino 51031 Agliana",
    "sg:city":"Agliana",
    "sg:classifiers":[
        {
            "category":"Shopping",
            "subcategory":"Crafts & Fabrics",
            "type":"Retail Goods"
        }
    ],
    "sg:phone":"+39 0574 711477",
    "sg:postcode":"51031",
    "sg:province":"Pistoia",
    "sg:tags":[
        "polyester"
    ],
    "wof:name":"Lanificio Il Calice Srl",
    "wof:placetype":"venue"
},
  "geometry": {"coordinates":[10.98691082,43.9095344543],"type":"Point"}
}