{
  "type": "Feature",
  "properties": {
    "addr:full":"Via F.genala 17; Soresina; 26015 Soresina Cremona 26015",
    "addr:housenumber":"17",
    "addr:postcode":"26015;26015",
    "addr:street":"Via F.Genala;Soresina",
    "iso:country":"IT",
    "sg:address":"Via F.genala 17; Soresina; 26015",
    "sg:city":"Soresina",
    "sg:classifiers":[
        {
            "category":"Banks & Credit Unions",
            "subcategory":"Bank",
            "type":"Services"
        }
    ],
    "sg:phone":"+39 0374 342064",
    "sg:postcode":"26015",
    "sg:province":"Cremona",
    "wof:name":"Cassa Di Risparmio Di Parma, E Piacenza Spa",
    "wof:placetype":"venue"
},
  "geometry": {"coordinates":[9.854702,45.287151],"type":"Point"}
}