{
  "type": "Feature",
  "properties": {
    "addr:full":"35030 Veggiano Veggiano Padova 35030",
    "addr:postcode":"35030;35030",
    "iso:country":"IT",
    "sg:address":"35030 Veggiano",
    "sg:city":"Veggiano",
    "sg:classifiers":[
        {
            "category":"Home & Garden",
            "subcategory":"Hardware",
            "type":"Retail Goods"
        }
    ],
    "sg:phone":"+39 049 904 8311",
    "sg:postcode":"35030",
    "sg:province":"Padova",
    "sg:website":"http://www.bimecc.it",
    "wof:name":"Bimecc Engineering Spa",
    "wof:placetype":"venue"
},
  "geometry": {"coordinates":[11.115941,45.418343],"type":"Point"}
}