{
  "type": "Feature",
  "properties": {
    "iso:country":"IT",
    "sg:address":"90141 Palermo",
    "sg:city":"Palermo",
    "sg:orig_category":"Gallerie D'arte",
    "sg:phone":"+39 091 625 1736",
    "sg:postcode":"90141",
    "sg:province":"Palermo",
    "wof:name":"Galleria Caravello",
    "wof:placetype":"venue"
},
  "geometry": {"coordinates":[13.350027,38.132931],"type":"Point"}
}