{
  "type": "Feature",
  "properties": {
    "iso:country":"IT",
    "sg:address":"96100 Siracusa",
    "sg:city":"Siracusa",
    "sg:classifiers":[
        {
            "category":"Health Services",
            "subcategory":"Health Practitioner",
            "type":"Services"
        }
    ],
    "sg:phone":"+39 0931 60214",
    "sg:postcode":"96100",
    "sg:province":"Siracusa",
    "sg:tags":[
        "medici"
    ],
    "wof:name":"Scifo Gaetano",
    "wof:placetype":"venue"
},
  "geometry": {"coordinates":[15.2932348251,37.0774459839],"type":"Point"}
}