{
  "type": "Feature",
  "properties": {
    "iso:country":"IT",
    "sg:address":"62027 San Severino Marche",
    "sg:city":"San Severino Marche",
    "sg:orig_category":"Servizi Ausiliari Dei Mezzi Di Trasporto",
    "sg:phone":"+39 0733 633067",
    "sg:postcode":"62027",
    "sg:province":"Macerata",
    "wof:name":"Eurocar Di Flamini Franco & C. Snc",
    "wof:placetype":"venue"
},
  "geometry": {"coordinates":[13.197106,43.273075],"type":"Point"}
}