{
  "type": "Feature",
  "properties": {
    "iso:country":"IT",
    "sg:address":"28, Via Parugiano Di Sotto 59013 Montemurlo",
    "sg:city":"Montemurlo",
    "sg:classifiers":[
        {
            "category":"Wholesale",
            "subcategory":"Drugs",
            "type":"Manufacturing & Wholesale Goods"
        }
    ],
    "sg:phone":"+39 0574 799191",
    "sg:postcode":"59013",
    "sg:province":"Prato",
    "sg:tags":[
        "chemical",
        "pharmaceutical"
    ],
    "wof:name":"Super Glanz (s.p.a.)",
    "wof:placetype":"venue"
},
  "geometry": {"coordinates":[11.041106,43.905479],"type":"Point"}
}