{
  "type": "Feature",
  "properties": {
    "iso:country":"IT",
    "sg:address":"24040 Osio Sopra",
    "sg:city":"Osio Sopra",
    "sg:classifiers":[
        {
            "category":"Wholesale",
            "subcategory":"Home Furnishings",
            "type":"Manufacturing & Wholesale Goods"
        }
    ],
    "sg:phone":"+39 035 500212",
    "sg:postcode":"24040",
    "sg:province":"Bergamo",
    "sg:tags":[
        "household",
        "appliance",
        "furnishings",
        "appliances",
        "kitchen"
    ],
    "sg:website":"http://www.ccagcrotti.com",
    "wof:name":"C.c.a.g. Crotti Srl",
    "wof:placetype":"venue"
},
  "geometry": {"coordinates":[9.5260219574,45.6211471558],"type":"Point"}
}