{
  "type": "Feature",
  "properties": {
    "iso:country":"IT",
    "sg:address":"00176 Roma",
    "sg:city":"Roma",
    "sg:orig_category":"Scuole E Servizi Scolastici",
    "sg:phone":"+39 06 274791",
    "sg:postcode":"00176",
    "sg:province":"Roma",
    "wof:name":"Istituto M. Ss. Assunta",
    "wof:placetype":"venue"
},
  "geometry": {"coordinates":[12.528146,41.886074],"type":"Point"}
}