{
  "type": "Feature",
  "properties": {
    "iso:country":"IT",
    "sg:address":"84123 Salerno",
    "sg:city":"Salerno",
    "sg:orig_category":"Pavimenti Gomma, Linoleum E Plastica",
    "sg:phone":"+39 089 232429",
    "sg:postcode":"84123",
    "sg:province":"Salerno",
    "wof:name":"Casa Della Gomma E Dello Sport",
    "wof:placetype":"venue"
},
  "geometry": {"coordinates":[14.770275116,40.675579071],"type":"Point"}
}