{
  "type": "Feature",
  "properties": {
    "addr:full":"Via Alba 9 10024 Moncalieri Moncalieri Torino 10024",
    "addr:housenumber":"9",
    "addr:postcode":"10024;10024",
    "addr:street":"Via Alba",
    "iso:country":"IT",
    "sg:address":"Via Alba 9 10024 Moncalieri",
    "sg:city":"Moncalieri",
    "sg:classifiers":[
        {
            "category":"Transit Center",
            "subcategory":"Freight",
            "type":"Transportation"
        }
    ],
    "sg:phone":"+39 011 646 7279",
    "sg:postcode":"10024",
    "sg:province":"Torino",
    "sg:tags":[
        "spring",
        "spiral"
    ],
    "sg:website":"www.mollificioitaliano.it",
    "wof:name":"Mollificio Italiano Sas",
    "wof:placetype":"venue"
},
  "geometry": {"coordinates":[7.666874,44.988148],"type":"Point"}
}