{
  "type": "Feature",
  "properties": {
    "addr:full":"Via S.s. N. 10 27040 Bosnasco Bosnasco Pavia 27040",
    "addr:housenumber":"10",
    "addr:postcode":"27040;27040",
    "addr:street":"Via S.S. N.",
    "iso:country":"IT",
    "sg:address":"Via S.s. N. 10 27040 Bosnasco",
    "sg:city":"Bosnasco",
    "sg:classifiers":[
        {
            "category":"Wholesale",
            "subcategory":"Drugs",
            "type":"Manufacturing & Wholesale Goods"
        }
    ],
    "sg:phone":"+39 0385 272247",
    "sg:postcode":"27040",
    "sg:province":"Pavia",
    "sg:tags":[
        "chemical",
        "pharmaceutical"
    ],
    "wof:name":"Kimicar Srl",
    "wof:placetype":"venue"
},
  "geometry": {"coordinates":[9.1565628052,45.1858863831],"type":"Point"}
}