{
  "type": "Feature",
  "properties": {
    "iso:country":"IT",
    "sg:address":"Via Ribes 1 10010 Colleretto Giacosa",
    "sg:city":"Colleretto Giacosa",
    "sg:orig_category":"Toxicology, General",
    "sg:phone":"+39 0125 222111",
    "sg:postcode":"10010",
    "sg:province":"Torino",
    "wof:name":"Istituto Di Ricerche Biomediche Antoine Marxer - Rbm Spa",
    "wof:placetype":"venue"
},
  "geometry": {"coordinates":[7.843995,45.448933],"type":"Point"}
}