{
  "type": "Feature",
  "properties": {
    "iso:country":"IT",
    "sg:address":"20093 Cologno Monzese",
    "sg:city":"Cologno Monzese",
    "sg:orig_category":"Registrazione Sonora - Sale Prova",
    "sg:phone":"+39 02 2539 6194",
    "sg:postcode":"20093",
    "sg:province":"Milano",
    "wof:name":"Vision Srl",
    "wof:placetype":"venue"
},
  "geometry": {"coordinates":[9.2701807022,45.5228996277],"type":"Point"}
}