{
  "type": "Feature",
  "properties": {
    "addr:full":"15, Via S. Vecchia 23868 Valmadrera Valmadrera Lecco 23868",
    "addr:postcode":"23868;23868",
    "addr:street":"Via S. Vecchia",
    "iso:country":"IT",
    "sg:address":"15, Via S. Vecchia 23868 Valmadrera",
    "sg:city":"Valmadrera",
    "sg:classifiers":[
        {
            "category":"Manufacturing",
            "subcategory":"Metals",
            "type":"Manufacturing & Wholesale Goods"
        }
    ],
    "sg:phone":"+39 0341 582165",
    "sg:postcode":"23868",
    "sg:province":"Lecco",
    "sg:tags":[
        "metallurgy",
        "metalworking"
    ],
    "wof:name":"Metalmanzoni (s.p.a.)",
    "wof:placetype":"venue"
},
  "geometry": {"coordinates":[9.3529653549,45.8381690979],"type":"Point"}
}