{
  "type": "Feature",
  "properties": {
    "addr:full":"24127 Bergamo Bergamo Bergamo 24127",
    "addr:postcode":"24127;24127",
    "iso:country":"IT",
    "sg:address":"24127 Bergamo",
    "sg:city":"Bergamo",
    "sg:orig_category":"Servizi E Lavori Industria Della Gomma",
    "sg:phone":"+39 035 255092",
    "sg:postcode":"24127",
    "sg:province":"Bergamo",
    "wof:name":"Frigeni Giovanni",
    "wof:placetype":"venue"
},
  "geometry": {"coordinates":[9.660007,45.688663],"type":"Point"}
}