{
  "type": "Feature",
  "properties": {
    "iso:country":"IT",
    "sg:address":"63100 Ascoli Piceno",
    "sg:city":"Ascoli Piceno",
    "sg:orig_category":"Servizi E Lavori Per Agricoltura E Zootecnia. Servizi Ausiliari Di Analisi, Controllo E Ricerca",
    "sg:phone":"+39 0736 343644",
    "sg:postcode":"63100",
    "sg:province":"Ascoli Piceno",
    "wof:name":"Tecnomarche S.r.l.",
    "wof:placetype":"venue"
},
  "geometry": {"coordinates":[13.636884,42.841957],"type":"Point"}
}