{
  "type": "Feature",
  "properties": {
    "addr:full":"37056 Salizzole Salizzole Verona 37056",
    "addr:postcode":"37056;37056",
    "iso:country":"IT",
    "sg:address":"37056 Salizzole",
    "sg:city":"Salizzole",
    "sg:orig_category":"Prodotti Alimentari",
    "sg:phone":"+39 045 710 2038",
    "sg:postcode":"37056",
    "sg:province":"Verona",
    "wof:name":"Galantini Giuliano",
    "wof:placetype":"venue"
},
  "geometry": {"coordinates":[11.095448494,45.2211074829],"type":"Point"}
}