{
  "type": "Feature",
  "properties": {
    "addr:full":"94, Via Fratta 83029 Solofra Solofra Avellino 83029",
    "addr:postcode":"83029;83029",
    "addr:street":"Via Fratta",
    "iso:country":"IT",
    "sg:address":"94, Via Fratta 83029 Solofra",
    "sg:city":"Solofra",
    "sg:classifiers":[
        {
            "category":"Professional",
            "subcategory":"Engineering",
            "type":"Services"
        }
    ],
    "sg:phone":"+39 0825 535174",
    "sg:postcode":"83029",
    "sg:province":"Avellino",
    "sg:tags":[
        "machine",
        "-",
        "mechanical"
    ],
    "wof:name":"La Elettro Di Del Franco Vincenzo & C.s.n.c.",
    "wof:placetype":"venue"
},
  "geometry": {"coordinates":[14.844357,40.830994],"type":"Point"}
}