{
  "type": "Feature",
  "properties": {
    "addr:full":"22066 Mariano Comense Mariano Comense Como 22066",
    "addr:housenumber":"22066",
    "addr:postcode":"22066",
    "iso:country":"IT",
    "sg:address":"22066 Mariano Comense",
    "sg:city":"Mariano Comense",
    "sg:orig_category":"Macchine E Forniture Per Arredamento E Industria Del Legno. Forniture Per Edilizia E Lavori Pubblici",
    "sg:phone":"+39 031 752019",
    "sg:postcode":"22066",
    "sg:province":"Como",
    "wof:name":"Brianfer (s.r.l.)",
    "wof:placetype":"venue"
},
  "geometry": {"coordinates":[9.186901,45.68198],"type":"Point"}
}