{
  "type": "Feature",
  "properties": {
    "addr:full":"43044 Collecchio Collecchio Parma 43044",
    "addr:postcode":"43044;43044",
    "iso:country":"IT",
    "sg:address":"43044 Collecchio",
    "sg:city":"Collecchio",
    "sg:orig_category":"Prodotti Finiti Stampati. Forniture E Prodotti Informatici. Forniture Per Uffici",
    "sg:phone":"+39 0521 804107",
    "sg:postcode":"43044",
    "sg:province":"Parma",
    "wof:name":"Artegrafica Silva Srl",
    "wof:placetype":"venue"
},
  "geometry": {"coordinates":[10.2165775299,44.7519264221],"type":"Point"}
}