{
  "type": "Feature",
  "properties": {
    "addr:full":"57128 Livorno Livorno Livorno 57128",
    "addr:postcode":"57128;57128",
    "iso:country":"IT",
    "sg:address":"57128 Livorno",
    "sg:city":"Livorno",
    "sg:orig_category":"Impiantistica E Prodotti Tecnologici Per Edilizia. Servizi Ausiliari Di Sorveglianza, Manutenzione E Pulizia",
    "sg:phone":"+39 0586 503105",
    "sg:postcode":"57128",
    "sg:province":"Livorno",
    "wof:name":"Eredi Di Cecchi Vinicio Srl",
    "wof:placetype":"venue"
},
  "geometry": {"coordinates":[10.339977,43.51857],"type":"Point"}
}