{
  "type": "Feature",
  "properties": {
    "iso:country":"IT",
    "sg:address":"Via Rossi 47 25010 Remedello",
    "sg:city":"Remedello",
    "sg:classifiers":[
        {
            "category":"Manufacturing",
            "subcategory":"Printing",
            "type":"Manufacturing & Wholesale Goods"
        }
    ],
    "sg:phone":"+39 030 995 3947",
    "sg:postcode":"25010",
    "sg:province":"Brescia",
    "sg:tags":[
        "plastic"
    ],
    "wof:name":"Uninorm System Srl",
    "wof:placetype":"venue"
},
  "geometry": {"coordinates":[10.3701543808,45.2714157104],"type":"Point"}
}