{
  "type": "Feature",
  "properties": {
    "iso:country":"IT",
    "sg:address":"Via Roma 113 50058 Signa",
    "sg:city":"Signa",
    "sg:classifiers":[
        {
            "category":"Shopping",
            "subcategory":"Crafts & Fabrics",
            "type":"Retail Goods"
        }
    ],
    "sg:phone":"+39 055 875633",
    "sg:postcode":"50058",
    "sg:province":"Firenze",
    "sg:tags":[
        "cloth",
        "glove"
    ],
    "sg:website":"www.bettinifirenze.com",
    "wof:name":"Raffaello Bettini Srl",
    "wof:placetype":"venue"
},
  "geometry": {"coordinates":[11.133806,43.822876],"type":"Point"}
}