{
  "type": "Feature",
  "properties": {
    "iso:country":"IT",
    "sg:address":"19124 La Spezia",
    "sg:classifiers":[
        {
            "category":"Travel",
            "subcategory":"Travel Agent",
            "type":"Entertainment"
        }
    ],
    "sg:phone":"+39 0187 505161",
    "sg:province":"SP",
    "sg:tags":[
        "operator",
        "tour",
        "tourist"
    ],
    "sg:website":"http://www.lorenziniviaggi.it",
    "wof:name":"Lorenzini Agenzia Viaggi E Turismo Srl",
    "wof:placetype":"venue"
},
  "geometry": {"coordinates":[9.825048,44.114086],"type":"Point"}
}