{
  "type": "Feature",
  "properties": {
    "addr:full":"Via Sicilia, 53/55 56030 Perignano Pisa 56030",
    "addr:housenumber":"53 / 55",
    "addr:postcode":"56030;56030",
    "addr:street":"Via Sicilia",
    "iso:country":"IT",
    "sg:address":"Via Sicilia, 53/55 56030 Perignano",
    "sg:classifiers":[
        {
            "category":"Manufacturing",
            "subcategory":"Furniture",
            "type":"Manufacturing & Wholesale Goods"
        }
    ],
    "sg:phone":"+39 0587 616278",
    "sg:postcode":"56030",
    "sg:province":"Pisa",
    "sg:tags":[
        "bedroom"
    ],
    "wof:name":"Ferrettimobili Srl",
    "wof:placetype":"venue"
},
  "geometry": {"coordinates":[10.396585,43.716137],"type":"Point"}
}