{
  "type": "Feature",
  "properties": {
    "addr:full":"33082 Tiezzo Tiezzo Pordenone 33082",
    "addr:postcode":"33082;33082",
    "addr:street":"Tiezzo",
    "iso:country":"IT",
    "sg:address":"33082 Tiezzo",
    "sg:city":"Tiezzo",
    "sg:orig_category":"Materiali Edili",
    "sg:phone":"+39 0434 647233",
    "sg:postcode":"33082",
    "sg:province":"Pordenone",
    "wof:name":"Pre Intonaci",
    "wof:placetype":"venue"
},
  "geometry": {"coordinates":[12.660226,45.895733],"type":"Point"}
}