{
  "type": "Feature",
  "properties": {
    "addr:full":"33070 Brugnera Brugnera Pordenone 33070",
    "addr:postcode":"33070;33070",
    "iso:country":"IT",
    "sg:address":"33070 Brugnera",
    "sg:city":"Brugnera",
    "sg:orig_category":"Imprese Edili",
    "sg:phone":"+39 0434 627021",
    "sg:postcode":"33070",
    "sg:province":"Pordenone",
    "wof:name":"Moras E Bertolo Snc",
    "wof:placetype":"venue"
},
  "geometry": {"coordinates":[12.57238,45.926102],"type":"Point"}
}