{
  "type": "Feature",
  "properties": {
    "iso:country":"IT",
    "sg:address":"20048 Carate Brianza",
    "sg:city":"Carate Brianza",
    "sg:classifiers":[
        {
            "category":"Manufacturing",
            "subcategory":"Leather Goods",
            "type":"Manufacturing & Wholesale Goods"
        }
    ],
    "sg:phone":"+39 036 299 2342",
    "sg:postcode":"20048",
    "sg:province":"Milano",
    "sg:tags":[
        "goods",
        "supply",
        "hospital",
        "equipment",
        "health",
        "systems",
        "supplies",
        "clothing"
    ],
    "wof:name":"Barbiflex Snc",
    "wof:placetype":"venue"
},
  "geometry": {"coordinates":[9.22682,45.670532],"type":"Point"}
}