{
  "type": "Feature",
  "properties": {
    "iso:country":"IT",
    "sg:address":"07046 Porto Torres",
    "sg:city":"Porto Torres",
    "sg:orig_category":"Acciai Inossidabili - Commercio",
    "sg:phone":"+39 079 516362",
    "sg:postcode":"07046",
    "sg:province":"Sassari",
    "wof:name":"Indresa Srl",
    "wof:placetype":"venue"
},
  "geometry": {"coordinates":[8.391155,40.834095],"type":"Point"}
}