{
  "type": "Feature",
  "properties": {
    "addr:full":"44028 Poggio Renatico Poggio Renatico Ferrara 44028",
    "addr:postcode":"44028;44028",
    "iso:country":"IT",
    "sg:address":"44028 Poggio Renatico",
    "sg:city":"Poggio Renatico",
    "sg:orig_category":"Materiali Edili",
    "sg:phone":"+39 0532 829403",
    "sg:postcode":"44028",
    "sg:province":"Ferrara",
    "wof:name":"Calcestruzzi Eurobeton Srl",
    "wof:placetype":"venue"
},
  "geometry": {"coordinates":[11.505774,44.843197],"type":"Point"}
}