{
  "type": "Feature",
  "properties": {
    "addr:full":"43052 Colorno Colorno Parma 43052",
    "addr:postcode":"43052;43052",
    "iso:country":"IT",
    "sg:address":"43052 Colorno",
    "sg:city":"Colorno",
    "sg:orig_category":"Accessori Moda D'abbigliamento. Forniture Per Abbigliamento E Pelletterie",
    "sg:phone":"+39 0521 816248",
    "sg:postcode":"43052",
    "sg:province":"Parma",
    "wof:name":"Turquoise",
    "wof:placetype":"venue"
},
  "geometry": {"coordinates":[10.332565,44.892422],"type":"Point"}
}