{
  "type": "Feature",
  "properties": {
    "iso:country":"IT",
    "sg:address":"Via Rasetti 12 24060 Viadanica",
    "sg:city":"Viadanica",
    "sg:orig_category":"O-rings",
    "sg:phone":"+39 035 928585",
    "sg:postcode":"24060",
    "sg:province":"Bergamo",
    "sg:website":"www.ar-tex.it",
    "wof:name":"Ar-tex Spa",
    "wof:placetype":"venue"
},
  "geometry": {"coordinates":[9.955468,45.689655],"type":"Point"}
}