{
  "type": "Feature",
  "properties": {
    "iso:country":"IT",
    "sg:address":"20090 Assago",
    "sg:city":"Assago",
    "sg:orig_category":"Serramenti Ed Infissi",
    "sg:phone":"+39 02 488 2415",
    "sg:postcode":"20090",
    "sg:province":"Milano",
    "wof:name":"Nuova Isomineral Srl",
    "wof:placetype":"venue"
},
  "geometry": {"coordinates":[9.123772,45.410954],"type":"Point"}
}