{
  "type": "Feature",
  "properties": {
    "iso:country":"IT",
    "sg:address":"31030 Breda Di Piave",
    "sg:city":"Breda di Piave",
    "sg:orig_category":"Marmo, Pietre Ed Affini",
    "sg:phone":"+39 0422 686030",
    "sg:postcode":"31030",
    "sg:province":"Treviso",
    "wof:name":"Meneghel Ado & C. Snc",
    "wof:placetype":"venue"
},
  "geometry": {"coordinates":[12.333777,45.724854],"type":"Point"}
}