{
  "type": "Feature",
  "properties": {
    "iso:country":"IT",
    "sg:address":"90139 Palermo",
    "sg:city":"Palermo",
    "sg:orig_category":"Servizi Vari Di Interesse Pubblico",
    "sg:phone":"+39 091 328433",
    "sg:postcode":"90139",
    "sg:province":"Palermo",
    "sg:website":"http://www.insiemestudiomatrimoniale.it",
    "wof:name":"Insieme Studio Matrimoniale",
    "wof:placetype":"venue"
},
  "geometry": {"coordinates":[13.360102,38.125053],"type":"Point"}
}