{
  "type": "Feature",
  "properties": {
    "iso:country":"IT",
    "sg:address":"20123 Milano",
    "sg:city":"Milano",
    "sg:orig_category":"Biancheria, Telerie E Coperte",
    "sg:phone":"+39 02 8646 0908",
    "sg:postcode":"20123",
    "sg:province":"Milano",
    "wof:name":"Telerie Spadari",
    "wof:placetype":"venue"
},
  "geometry": {"coordinates":[9.186621,45.463928],"type":"Point"}
}