{
  "type": "Feature",
  "properties": {
    "iso:country":"IT",
    "sg:address":"79, Via Brescia 25065 Lumezzane",
    "sg:city":"Lumezzane",
    "sg:classifiers":[
        {
            "category":"Manufacturing",
            "subcategory":"Metals",
            "type":"Manufacturing & Wholesale Goods"
        }
    ],
    "sg:phone":"+39 39030871421",
    "sg:postcode":"25065",
    "sg:province":"Brescia",
    "sg:tags":[
        "metallurgy",
        "metalworking"
    ],
    "wof:name":"P.m.b. Di Bugatti S. E C. (s.n.c.)",
    "wof:placetype":"venue"
},
  "geometry": {"coordinates":[10.2255182266,45.6528053284],"type":"Point"}
}