{
  "type": "Feature",
  "properties": {
    "addr:full":"45, Via Pusterla 25128 Brescia Brescia Brescia 25128",
    "addr:postcode":"25128;25128",
    "addr:street":"Via Pusterla",
    "iso:country":"IT",
    "sg:address":"45, Via Pusterla 25128 Brescia",
    "sg:city":"Brescia",
    "sg:classifiers":[
        {
            "category":"Autos & Motor Vehicles",
            "subcategory":"Automobile Sales",
            "type":"Retail Goods"
        }
    ],
    "sg:phone":"+39 39030305338",
    "sg:postcode":"25128",
    "sg:province":"Brescia",
    "sg:tags":[
        "motor-cars"
    ],
    "wof:name":"Cobra (s.r.l.)",
    "wof:placetype":"venue"
},
  "geometry": {"coordinates":[10.2273435593,45.5444869995],"type":"Point"}
}