{
  "type": "Feature",
  "properties": {
    "iso:country":"IT",
    "sg:address":"12, Via Guglielmo Marconi 20065 Inzago",
    "sg:city":"Inzago",
    "sg:classifiers":[
        {
            "category":"Home & Garden",
            "subcategory":"Home Furnishings",
            "type":"Retail Goods"
        }
    ],
    "sg:phone":"+39 02 9531 4090",
    "sg:postcode":"20065",
    "sg:province":"Milano",
    "sg:tags":[
        "household"
    ],
    "wof:name":"Ar-thema International Srl",
    "wof:placetype":"venue"
},
  "geometry": {"coordinates":[9.536709,45.576473],"type":"Point"}
}