{
  "type": "Feature",
  "properties": {
    "addr:full":"Cso Trieste 53 10024 Moncalieri Moncalieri Torino 10024",
    "addr:housenumber":"53",
    "addr:postcode":"10024;10024",
    "addr:street":"Cso Trieste",
    "iso:country":"IT",
    "sg:address":"Cso Trieste 53 10024 Moncalieri",
    "sg:city":"Moncalieri",
    "sg:classifiers":[
        {
            "category":"Military Area",
            "subcategory":"Army Base",
            "type":"Public Place"
        }
    ],
    "sg:phone":"+39 011 605 5463",
    "sg:postcode":"10024",
    "sg:province":"Torino",
    "sg:tags":[
        "cask",
        "iron"
    ],
    "wof:name":"Sifa S.r.l.",
    "wof:placetype":"venue"
},
  "geometry": {"coordinates":[7.6707,45.009995],"type":"Point"}
}