{
  "type": "Feature",
  "properties": {
    "addr:full":"Via R. Ciancio, 31 - Loc. Fimiani 84080 Lanzara Salerno 84080",
    "addr:housenumber":"31",
    "addr:postcode":"84080;84080",
    "addr:street":"Via R. Ciancio;Loc. Fimiani",
    "iso:country":"IT",
    "sg:address":"Via R. Ciancio, 31 - Loc. Fimiani 84080 Lanzara",
    "sg:classifiers":[
        {
            "category":"Home & Garden",
            "subcategory":"Home Furnishings",
            "type":"Retail Goods"
        }
    ],
    "sg:phone":"+39 081 953 5311",
    "sg:postcode":"84080",
    "sg:province":"Salerno",
    "sg:tags":[
        "plate",
        "black"
    ],
    "wof:name":"Mercantile Acciai S.r.l.",
    "wof:placetype":"venue"
},
  "geometry": {"coordinates":[14.765912,40.677956],"type":"Point"}
}