{
  "type": "Feature",
  "properties": {
    "addr:full":"Via Archi Superiore 98044 San Filippo Del Mela Archi Messina 98044",
    "addr:postcode":"98044;98044",
    "addr:street":"Via Archi Superiore",
    "iso:country":"IT",
    "sg:address":"Via Archi Superiore 98044 San Filippo Del Mela",
    "sg:city":"Archi",
    "sg:classifiers":[
        {
            "category":"Food & Beverages",
            "subcategory":"Groceries & Convenience Stores",
            "type":"Retail Goods"
        }
    ],
    "sg:phone":"+39 090 938 5556",
    "sg:postcode":"98044",
    "sg:province":"Messina",
    "sg:tags":[
        "product",
        "related"
    ],
    "wof:name":"Bucca Olii E Vini Srl",
    "wof:placetype":"venue"
},
  "geometry": {"coordinates":[14.6994533539,38.0937614441],"type":"Point"}
}