{
  "type": "Feature",
  "properties": {
    "iso:country":"IT",
    "sg:address":"31041 Cornuda",
    "sg:city":"Cornuda",
    "sg:orig_category":"Bevande, Vini E Liquori. Shopping",
    "sg:phone":"+39 0423 83317",
    "sg:postcode":"31041",
    "sg:province":"Treviso",
    "wof:name":"Azienda Agricola 'colli Asolani' Di Bedin Enrico & C. Ss",
    "wof:placetype":"venue"
},
  "geometry": {"coordinates":[12.226677,45.655548],"type":"Point"}
}