{
  "type": "Feature",
  "properties": {
    "addr:full":"80131 Napoli Napoli Napoli 80131",
    "addr:housenumber":"80131",
    "addr:postcode":"80131",
    "iso:country":"IT",
    "sg:address":"80131 Napoli",
    "sg:city":"Napoli",
    "sg:orig_category":"Estetiste",
    "sg:phone":"+39 081 592 2929",
    "sg:postcode":"80131",
    "sg:province":"Napoli",
    "wof:name":"Donna In Di Luisa Festa",
    "wof:placetype":"venue"
},
  "geometry": {"coordinates":[14.236187,40.869274],"type":"Point"}
}