{
  "type": "Feature",
  "properties": {
    "iso:country":"IT",
    "sg:address":"20090 Segrate",
    "sg:city":"Segrate",
    "sg:orig_category":"Servizi E Lavori Per Agricoltura E Zootecnia. Animali Domestici",
    "sg:phone":"+39 02 213 2347",
    "sg:postcode":"20090",
    "sg:province":"Milano",
    "wof:name":"Clinica Veterinaria Citta'di Segrate Sas Di Anton Khalil",
    "wof:placetype":"venue"
},
  "geometry": {"coordinates":[9.29609,45.497177],"type":"Point"}
}