{
  "type": "Feature",
  "properties": {
    "iso:country":"IT",
    "sg:address":"35127 Padova",
    "sg:city":"Padova",
    "sg:orig_category":"Prodotti E Manufatti In Gomma. Forniture Per Attivita' Industriali",
    "sg:phone":"+39 049 806 3111",
    "sg:postcode":"35127",
    "sg:province":"Padova",
    "sg:website":"http://www.fischeritalia.it",
    "wof:name":"Fischer Italia Srl",
    "wof:placetype":"venue"
},
  "geometry": {"coordinates":[11.9340610504,45.3876457214],"type":"Point"}
}