{
  "type": "Feature",
  "properties": {
    "iso:country":"IT",
    "sg:address":"Via G. Garibaldi, 123/35 35010 San Pietro In Gu",
    "sg:city":"San Pietro in Gu",
    "sg:classifiers":[
        {
            "category":"Wholesale",
            "subcategory":"Chemicals & Plastics",
            "type":"Manufacturing & Wholesale Goods"
        }
    ],
    "sg:phone":"+39 049 945 5290",
    "sg:postcode":"35010",
    "sg:province":"Padova",
    "sg:tags":[
        "product",
        "disinfectant",
        "cleaning"
    ],
    "wof:name":"Synchem Srl",
    "wof:placetype":"venue"
},
  "geometry": {"coordinates":[11.876589,45.409569],"type":"Point"}
}