{
  "type": "Feature",
  "properties": {
    "iso:country":"IT",
    "sg:address":"21012 Cassano Magnago",
    "sg:city":"Cassano Magnago",
    "sg:orig_category":"Macchine, Impianti Ed Attrezzature Per Abbigliamento E Pelletterie",
    "sg:phone":"+39 0331 201058",
    "sg:postcode":"21012",
    "sg:province":"Varese",
    "wof:name":"Temporiti Srl",
    "wof:placetype":"venue"
},
  "geometry": {"coordinates":[8.824873,45.672413],"type":"Point"}
}