{
  "type": "Feature",
  "properties": {
    "iso:country":"IT",
    "sg:address":"10026 Santena",
    "sg:city":"Santena",
    "sg:orig_category":"Macchine, Impianti Ed Attrezzature Industria Delle Materie Plastiche E Gomma",
    "sg:phone":"+39 011 949 1972",
    "sg:postcode":"10026",
    "sg:province":"Torino",
    "wof:name":"Billion Italia Srl",
    "wof:placetype":"venue"
},
  "geometry": {"coordinates":[7.759223,44.951061],"type":"Point"}
}