{
  "type": "Feature",
  "properties": {
    "iso:country":"IT",
    "sg:address":"26020 Spinadesco",
    "sg:city":"Spinadesco",
    "sg:orig_category":"Macchine, Impianti Ed Attrezzature Per Industria Alimentare E Bevande. Macchine, Impianti Ed Attrezzature Industria Chimica",
    "sg:phone":"+39 0372 492116",
    "sg:postcode":"26020",
    "sg:province":"Cremona",
    "wof:name":"Ardea Srl",
    "wof:placetype":"venue"
},
  "geometry": {"coordinates":[9.939954,45.152641],"type":"Point"}
}