{
  "type": "Feature",
  "properties": {
    "addr:full":"60, V. G. Campagna41010 Cognento Modena 41010",
    "addr:housenumber":"60;campagna41010",
    "addr:postcode":"41010",
    "addr:street":"V. G.",
    "iso:country":"IT",
    "sg:address":"60, V. G. Campagna41010 Cognento",
    "sg:classifiers":[
        {
            "category":"Shopping",
            "subcategory":"Clothing, Apparel, & Fashions",
            "type":"Retail Goods"
        }
    ],
    "sg:phone":"+39 059 292 4911",
    "sg:postcode":"41010",
    "sg:province":"Modena",
    "sg:tags":[
        "clothes"
    ],
    "sg:website":"http://www.intimamoda.it:ws_end: :mark:ws:http://www.paginegialle.it/intimamoda",
    "wof:name":"Intimo Moda Spa",
    "wof:placetype":"venue"
},
  "geometry": {"coordinates":[10.876451,44.638046],"type":"Point"}
}