{
  "type": "Feature",
  "properties": {
    "addr:full":"73048 Nard\u00f2 Lecce 73048",
    "addr:postcode":"73048;73048",
    "iso:country":"IT",
    "sg:address":"73048 Nard\u00f2",
    "sg:classifiers":[
        {
            "category":"Home & Garden",
            "subcategory":"Home Furnishings",
            "type":"Retail Goods"
        }
    ],
    "sg:phone":"+39 0833 578299",
    "sg:postcode":"73048",
    "sg:province":"Lecce",
    "sg:tags":[
        "accessories",
        "bedroom"
    ],
    "wof:name":"Ricamificio Sirio Srl",
    "wof:placetype":"venue"
},
  "geometry": {"coordinates":[17.9768867493,40.2020187378],"type":"Point"}
}