{
  "type": "Feature",
  "properties": {
    "addr:full":"7, Via Dell' Industria 20040 Busnago Busnago Milano 20040",
    "addr:postcode":"20040;20040",
    "addr:street":"Via Dell ' Industria",
    "iso:country":"IT",
    "sg:address":"7, Via Dell' Industria 20040 Busnago",
    "sg:city":"Busnago",
    "sg:classifiers":[
        {
            "category":"Utilities",
            "subcategory":"Electric",
            "type":"Services"
        }
    ],
    "sg:phone":"+39 039 695 7527",
    "sg:postcode":"20040",
    "sg:province":"Milano",
    "sg:tags":[
        "component",
        "electronic"
    ],
    "wof:name":"Ri.p.em. (s.r.l.)",
    "wof:placetype":"venue"
},
  "geometry": {"coordinates":[9.188141,45.463688],"type":"Point"}
}