{
  "type": "Feature",
  "properties": {
    "iso:country":"IT",
    "sg:address":"25080 Molinetto",
    "sg:city":"Molinetto",
    "sg:orig_category":"Gioielleria, Oreficeria E Argenteria. Articoli Da Regalo. Shopping",
    "sg:phone":"+39 030 262 0810",
    "sg:postcode":"25080",
    "sg:province":"Brescia",
    "wof:name":"Artigiana Del Peltro (s.n.c.)",
    "wof:placetype":"venue"
},
  "geometry": {"coordinates":[10.360796,45.502354],"type":"Point"}
}