{
  "type": "Feature",
  "properties": {
    "addr:full":"20, Via Comasinella Di Sotto 20020 Solaro Solaro Milano 20020",
    "addr:postcode":"20020;20020",
    "addr:street":"Via Comasinella Di Sotto",
    "iso:country":"IT",
    "sg:address":"20, Via Comasinella Di Sotto 20020 Solaro",
    "sg:city":"Solaro",
    "sg:classifiers":[
        {
            "category":"Shopping",
            "subcategory":"Computers & Home Electronics",
            "type":"Retail Goods"
        }
    ],
    "sg:phone":"+39 39029657866",
    "sg:postcode":"20020",
    "sg:province":"Milano",
    "sg:tags":[
        "electronic",
        "electrical",
        "equipment"
    ],
    "wof:name":"Agea (s.r.l.)",
    "wof:placetype":"venue"
},
  "geometry": {"coordinates":[9.061958,45.612957],"type":"Point"}
}