{
  "type": "Feature",
  "properties": {
    "addr:full":"20091 Bresso Bresso Milano 20091",
    "addr:postcode":"20091;20091",
    "iso:country":"IT",
    "sg:address":"20091 Bresso",
    "sg:city":"Bresso",
    "sg:orig_category":"Forniture Per Abbigliamento E Pelletterie",
    "sg:phone":"+39 02 610 3064",
    "sg:postcode":"20091",
    "sg:province":"Milano",
    "wof:name":"Fochesato Ottaviana",
    "wof:placetype":"venue"
},
  "geometry": {"coordinates":[9.1932811737,45.5339813232],"type":"Point"}
}