{
  "type": "Feature",
  "properties": {
    "iso:country":"IT",
    "sg:address":"Vle Del Lavoro 22g 37036 San Martino Buon Albergo",
    "sg:city":"San Martino Buon Albergo",
    "sg:classifiers":[
        {
            "category":"Retail",
            "subcategory":"Portrait Studio",
            "type":"Services"
        }
    ],
    "sg:phone":"+39 045 879 9161",
    "sg:postcode":"37036",
    "sg:province":"Verona",
    "sg:tags":[
        "graphic",
        "illustration"
    ],
    "wof:name":"Edigraf Srl",
    "wof:placetype":"venue"
},
  "geometry": {"coordinates":[10.991748,45.438366],"type":"Point"}
}