{
  "type": "Feature",
  "properties": {
    "iso:country":"IT",
    "sg:address":"Lungo Bisagno Istria 14/d/27r 16141 Genova",
    "sg:city":"Genova",
    "sg:classifiers":[
        {
            "category":"Government",
            "subcategory":"Department Of Motor Vehicles",
            "type":"Public Place"
        }
    ],
    "sg:phone":"+39 010 835161",
    "sg:postcode":"16141",
    "sg:province":"Genova",
    "sg:tags":[
        "industrial"
    ],
    "sg:website":"www.phase.it",
    "wof:name":"Phase Motion Control Srl",
    "wof:placetype":"venue"
},
  "geometry": {"coordinates":[8.9502744675,44.4271507263],"type":"Point"}
}