{
  "type": "Feature",
  "properties": {
    "iso:country":"IT",
    "sg:address":"65015 Montesilvano",
    "sg:city":"Montesilvano",
    "sg:orig_category":"Carrozzerie - Forniture",
    "sg:phone":"+39 085 834550",
    "sg:postcode":"65015",
    "sg:province":"Pescara",
    "wof:name":"Masterglass",
    "wof:placetype":"venue"
},
  "geometry": {"coordinates":[14.172975,42.497482],"type":"Point"}
}