{
  "type": "Feature",
  "properties": {
    "addr:full":"92100 Agrigento Agrigento Agrigento 92100",
    "addr:postcode":"92100;92100",
    "iso:country":"IT",
    "sg:address":"92100 Agrigento",
    "sg:city":"Agrigento",
    "sg:orig_category":"Servizi Ausiliari Di Certificati, Riproduzioni, Disegni E Foto",
    "sg:phone":"+39 0922 20676",
    "sg:postcode":"92100",
    "sg:province":"Agrigento",
    "wof:name":"Punturo Michele Studio 33",
    "wof:placetype":"venue"
},
  "geometry": {"coordinates":[13.580095,37.308987],"type":"Point"}
}