{
  "type": "Feature",
  "properties": {
    "iso:country":"IT",
    "sg:address":"7, Via Torino 21050 Cairate",
    "sg:city":"Cairate",
    "sg:classifiers":[
        {
            "category":"Professional",
            "subcategory":"Engineering",
            "type":"Services"
        }
    ],
    "sg:phone":"+39 0331 310260",
    "sg:postcode":"21050",
    "sg:province":"Varese",
    "sg:tags":[
        "machine",
        "-",
        "mechanical"
    ],
    "wof:name":"Saporiti Michele & Figli (s.r.l.)",
    "wof:placetype":"venue"
},
  "geometry": {"coordinates":[8.828611,45.669338],"type":"Point"}
}