{
  "type": "Feature",
  "properties": {
    "iso:country":"IT",
    "sg:address":"Corso Mazzini 121; Gambettola; 47035",
    "sg:city":"Gambettola",
    "sg:classifiers":[
        {
            "category":"Banks & Credit Unions",
            "subcategory":"Bank",
            "type":"Services"
        }
    ],
    "sg:phone":"+39 0547 53155",
    "sg:postcode":"47035",
    "sg:province":"Forl\u00ec-Cesena",
    "wof:name":"Cassa Di Risparmio Di Cesena Spa",
    "wof:placetype":"venue"
},
  "geometry": {"coordinates":[12.338672,44.118332],"type":"Point"}
}