{
  "type": "Feature",
  "properties": {
    "addr:full":"10135 Torino Torino Torino 10135",
    "addr:postcode":"10135;10135",
    "iso:country":"IT",
    "sg:address":"10135 Torino",
    "sg:city":"Torino",
    "sg:orig_category":"Banche E Servizi Finanziari",
    "sg:phone":"+39 011 340 0211",
    "sg:postcode":"10135",
    "sg:province":"Torino",
    "wof:name":"Edilscuola",
    "wof:placetype":"venue"
},
  "geometry": {"coordinates":[7.548742,44.988571],"type":"Point"}
}