{
  "type": "Feature",
  "properties": {
    "iso:country":"IT",
    "sg:address":"80128 Napoli",
    "sg:city":"Napoli",
    "sg:orig_category":"Servizi Culturali E Per Lo Spettacolo. Cine-foto-ottica",
    "sg:phone":"+39 081 560 6521",
    "sg:postcode":"80128",
    "sg:province":"Napoli",
    "wof:name":"Video E Dintorni Sas Di C. Greco & C.",
    "wof:placetype":"venue"
},
  "geometry": {"coordinates":[14.219248,40.849354],"type":"Point"}
}