{
  "type": "Feature",
  "properties": {
    "iso:country":"IT",
    "sg:address":"20146 Milano",
    "sg:city":"Milano",
    "sg:orig_category":"Servizi E Lavori Per Arredamento E Industria Del Legno. Servizi E Lavori Per Edilizia E Lavori Pubblici",
    "sg:phone":"+39 02 474893",
    "sg:postcode":"20146",
    "sg:province":"Milano",
    "wof:name":"Sette Bruno",
    "wof:placetype":"venue"
},
  "geometry": {"coordinates":[9.149186,45.456944],"type":"Point"}
}