{
  "type": "Feature",
  "properties": {
    "iso:country":"IT",
    "sg:address":"63023 Fermo",
    "sg:city":"Fermo",
    "sg:orig_category":"Trattamenti Termici E Superficiali Metalli, Galvanotecnica",
    "sg:phone":"+39 0734 53111",
    "sg:postcode":"63023",
    "sg:province":"Ascoli Piceno",
    "wof:name":"L.o.a. Laboratorio Ossidazione Anodica Snc",
    "wof:placetype":"venue"
},
  "geometry": {"coordinates":[13.574977,42.8554],"type":"Point"}
}