{
  "type": "Feature",
  "properties": {
    "iso:country":"IT",
    "sg:address":"83031 Ariano Irpino",
    "sg:city":"Ariano Irpino",
    "sg:orig_category":"Prodotti E Manufatti In Materie Plastiche",
    "sg:phone":"+39 0825 828638",
    "sg:postcode":"83031",
    "sg:province":"Avellino",
    "wof:name":"Metal - Plastica Di Vitullo Luigi",
    "wof:placetype":"venue"
},
  "geometry": {"coordinates":[15.0751590729,41.1707954407],"type":"Point"}
}