{
  "type": "Feature",
  "properties": {
    "iso:country":"IT",
    "sg:address":"80121 Napoli",
    "sg:city":"Napoli",
    "sg:orig_category":"Servizi Per Aziende, Manifestazioni E Supporto Agli Scambi Commerciali",
    "sg:phone":"+39 081 761 1813",
    "sg:postcode":"80121",
    "sg:province":"Napoli",
    "wof:name":"Bertolini's Hall",
    "wof:placetype":"venue"
},
  "geometry": {"coordinates":[14.268661,40.906223],"type":"Point"}
}