{
  "type": "Feature",
  "properties": {
    "iso:country":"IT",
    "sg:address":"3, Galleria Del Reno 40122 Bologna",
    "sg:city":"Bologna",
    "sg:classifiers":[
        {
            "category":"Farming",
            "subcategory":"Livestock Farm",
            "type":"Manufacturing & Wholesale Goods"
        }
    ],
    "sg:phone":"+39 39051223820",
    "sg:postcode":"40122",
    "sg:province":"Bologna",
    "sg:tags":[
        "agriculture"
    ],
    "wof:name":"Societa' Produttori Sementi (s.p.a.)",
    "wof:placetype":"venue"
},
  "geometry": {"coordinates":[11.339251,44.500195],"type":"Point"}
}