{
  "type": "Feature",
  "properties": {
    "addr:full":"91100 Trapani Trapani Trapani 91100",
    "addr:postcode":"91100;91100",
    "iso:country":"IT",
    "sg:address":"91100 Trapani",
    "sg:city":"Trapani",
    "sg:orig_category":"Apparecchiature Ed Attrezzature Meccaniche",
    "sg:phone":"+39 0923 531008",
    "sg:postcode":"91100",
    "sg:province":"Trapani",
    "wof:name":"Tecno Di Buscaino G.& C.snc.",
    "wof:placetype":"venue"
},
  "geometry": {"coordinates":[12.554167,38.00922],"type":"Point"}
}