{
  "type": "Feature",
  "properties": {
    "iso:country":"IT",
    "sg:address":"25080 Prevalle",
    "sg:city":"Prevalle",
    "sg:orig_category":"Manufacturers: Prefabbricati",
    "sg:phone":"+39 030 603526",
    "sg:postcode":"25080",
    "sg:province":"Brescia",
    "wof:name":"Edilcasa Di Maccarinelli G. & C. Snc",
    "wof:placetype":"venue"
},
  "geometry": {"coordinates":[10.356246,45.501915],"type":"Point"}
}