{
  "type": "Feature",
  "properties": {
    "iso:country":"IT",
    "sg:address":"101, Via Benaco 25081 Bedizzole",
    "sg:city":"Bedizzole",
    "sg:classifiers":[
        {
            "category":"Shopping",
            "subcategory":"Gifts & Souvenirs",
            "type":"Retail Goods"
        }
    ],
    "sg:phone":"+39 030 687 5811",
    "sg:postcode":"25081",
    "sg:province":"Brescia",
    "wof:name":"Aghifug Spa",
    "wof:placetype":"venue"
},
  "geometry": {"coordinates":[10.445722,45.506229],"type":"Point"}
}