{
  "type": "Feature",
  "properties": {
    "iso:country":"IT",
    "sg:address":"62, Via Adriatica 63018 Porto Sant'elpidio",
    "sg:classifiers":[
        {
            "category":"Personal",
            "subcategory":"Shoe Repair & Shine",
            "type":"Services"
        }
    ],
    "sg:phone":"+39 0734 993051",
    "sg:postcode":"63018",
    "sg:province":"Ascoli Piceno",
    "sg:tags":[
        "leather"
    ],
    "wof:name":"Giuliano Venanzi S.r.l.",
    "wof:placetype":"venue"
},
  "geometry": {"coordinates":[13.741467,43.285034],"type":"Point"}
}