{
  "type": "Feature",
  "properties": {
    "iso:country":"IT",
    "sg:address":"Via Toniolo 14 - Binzago 20031 Cesano Maderno",
    "sg:city":"Binzago",
    "sg:classifiers":[
        {
            "category":"Military Area",
            "subcategory":"Air Force Base",
            "type":"Public Place"
        }
    ],
    "sg:phone":"+39 036 255 0322",
    "sg:postcode":"20031",
    "sg:province":"Milano",
    "sg:tags":[
        "equipment",
        "galvanizing",
        "system",
        "electroplating"
    ],
    "wof:name":"Novatec Srl",
    "wof:placetype":"venue"
},
  "geometry": {"coordinates":[9.153353,45.618362],"type":"Point"}
}