{
  "type": "Feature",
  "properties": {
    "addr:full":"00167 Roma Roma Roma 00167",
    "addr:postcode":"00167;00167",
    "iso:country":"IT",
    "sg:address":"00167 Roma",
    "sg:city":"Roma",
    "sg:orig_category":"Prodotti E Manufatti In Gomma",
    "sg:phone":"+39 06 3974 9892",
    "sg:postcode":"00167",
    "sg:province":"Roma",
    "sg:website":"http://www.centromoquettes.com",
    "wof:name":"Centromoquettes Srl",
    "wof:placetype":"venue"
},
  "geometry": {"coordinates":[12.4361724854,41.901676178],"type":"Point"}
}