{
  "type": "Feature",
  "properties": {
    "iso:country":"IT",
    "sg:address":"58100 Grosseto",
    "sg:city":"Grosseto",
    "sg:classifiers":[
        {
            "category":"Food & Beverages",
            "subcategory":"Fruits & Vegetables",
            "type":"Retail Goods"
        }
    ],
    "sg:phone":"+39 0564 458007",
    "sg:postcode":"58100",
    "sg:province":"Grosseto",
    "sg:tags":[
        "growing",
        "agriculture",
        "flower",
        "products"
    ],
    "wof:name":"L'alba Tartufi - Vecchia Maremma",
    "wof:placetype":"venue"
},
  "geometry": {"coordinates":[11.1164455414,42.7495117188],"type":"Point"}
}