{
  "type": "Feature",
  "properties": {
    "iso:country":"IT",
    "sg:address":"90129 Palermo",
    "sg:city":"Palermo",
    "sg:orig_category":"Articoli Medico-sanitari Ed Ortopedici",
    "sg:phone":"+39 091 660 1515",
    "sg:postcode":"90129",
    "sg:province":"Palermo",
    "wof:name":"Otoacustica",
    "wof:placetype":"venue"
},
  "geometry": {"coordinates":[13.339771,38.106873],"type":"Point"}
}