{
  "type": "Feature",
  "properties": {
    "iso:country":"IT",
    "sg:address":"65126 Pescara",
    "sg:city":"Pescara",
    "sg:orig_category":"Impiantistica E Prodotti Tecnologici Per Edilizia",
    "sg:phone":"+39 085 64690",
    "sg:postcode":"65126",
    "sg:province":"Pescara",
    "wof:name":"G.e.a. Srl",
    "wof:placetype":"venue"
},
  "geometry": {"coordinates":[14.224864,42.459774],"type":"Point"}
}