{
  "type": "Feature",
  "properties": {
    "iso:country":"IT",
    "sg:address":"00198 Roma",
    "sg:city":"Roma",
    "sg:orig_category":"Servizi Editoriali. Pubblicita', Marketing E Comunicazione",
    "sg:phone":"+39 06 854 3448",
    "sg:postcode":"00198",
    "sg:province":"Roma",
    "wof:name":"Pubblispe (s.r.l.)",
    "wof:placetype":"venue"
},
  "geometry": {"coordinates":[12.496777,41.912144],"type":"Point"}
}