{
  "type": "Feature",
  "properties": {
    "addr:full":"Via Montecassino, 5/7 40050 Funo Funo Bologna 40050",
    "addr:housenumber":"5 / 7",
    "addr:postcode":"40050;40050",
    "addr:street":"Via Montecassino",
    "iso:country":"IT",
    "sg:address":"Via Montecassino, 5/7 40050 Funo",
    "sg:city":"Funo",
    "sg:classifiers":[
        {
            "category":"Autos & Motor Vehicles",
            "subcategory":"Boat Sales",
            "type":"Retail Goods"
        }
    ],
    "sg:phone":"+39 051 664 6198",
    "sg:postcode":"40050",
    "sg:province":"Bologna",
    "sg:tags":[
        "die",
        "cutting",
        "printing",
        "automatic",
        "machines"
    ],
    "wof:name":"Eurmeccanica Shoes Srl",
    "wof:placetype":"venue"
},
  "geometry": {"coordinates":[11.3661928177,44.6095275879],"type":"Point"}
}