{
  "type": "Feature",
  "properties": {
    "iso:country":"IT",
    "sg:address":"00054 Fiumicino",
    "sg:city":"Fiumicino",
    "sg:orig_category":"Riparazione Dei Mezzi Di Trasporto. Servizi Ausiliari Dei Mezzi Di Trasporto",
    "sg:phone":"+39 06 652 2149",
    "sg:postcode":"00054",
    "sg:province":"Roma",
    "wof:name":"Nautical Technical System Snc.",
    "wof:placetype":"venue"
},
  "geometry": {"coordinates":[12.229798,41.770775],"type":"Point"}
}