{
  "type": "Feature",
  "properties": {
    "addr:full":"15100 Alessandria Alessandria Alessandria 15100",
    "addr:postcode":"15100;15100",
    "iso:country":"IT",
    "sg:address":"15100 Alessandria",
    "sg:city":"Alessandria",
    "sg:orig_category":"Forniture Per Agricoltura E Zootecnia",
    "sg:phone":"+39 0131 226928",
    "sg:postcode":"15100",
    "sg:province":"Alessandria",
    "wof:name":"Agri 2000 Di Gugliada Luciano & C. Snc",
    "wof:placetype":"venue"
},
  "geometry": {"coordinates":[8.6190919876,44.9244766235],"type":"Point"}
}