{
  "type": "Feature",
  "properties": {
    "addr:full":"5/a, Via Salarola 36063 Marostica Marostica Vicenza 36063",
    "addr:housenumber":"5 / a",
    "addr:postcode":"36063;36063",
    "addr:street":"Via Salarola",
    "iso:country":"IT",
    "sg:address":"5/a, Via Salarola 36063 Marostica",
    "sg:city":"Marostica",
    "sg:classifiers":[
        {
            "category":"Home & Garden",
            "subcategory":"Home Furnishings",
            "type":"Retail Goods"
        }
    ],
    "sg:phone":"+39 39042477945",
    "sg:postcode":"36063",
    "sg:province":"Vicenza",
    "sg:tags":[
        "household"
    ],
    "wof:name":"C.b.l. (s.r.l.)",
    "wof:placetype":"venue"
},
  "geometry": {"coordinates":[11.540307,45.545906],"type":"Point"}
}