{
  "type": "Feature",
  "properties": {
    "addr:full":"20066 Melzo Melzo Milano 20066",
    "addr:postcode":"20066;20066",
    "iso:country":"IT",
    "sg:address":"20066 Melzo",
    "sg:city":"Melzo",
    "sg:orig_category":"Prodotti E Manufatti In Materie Plastiche",
    "sg:phone":"+39 02 955 0466",
    "sg:postcode":"20066",
    "sg:province":"Milano",
    "wof:name":"Calvi Srl",
    "wof:placetype":"venue"
},
  "geometry": {"coordinates":[9.2242183685,45.5075569153],"type":"Point"}
}