{
  "type": "Feature",
  "properties": {
    "iso:country":"IT",
    "sg:address":"20143 Milano",
    "sg:city":"Milano",
    "sg:orig_category":"Ristorazione E Locali Pubblici Affini. Ristoranti Ed Esercizi Affini. Servizi Ausiliari Di Ristorazione E Di Intrattenimento",
    "sg:phone":"+39 02 8912 6248",
    "sg:postcode":"20143",
    "sg:province":"Milano",
    "wof:name":"I Furiosi Srl",
    "wof:placetype":"venue"
},
  "geometry": {"coordinates":[9.154993,45.44738],"type":"Point"}
}