{
  "type": "Feature",
  "properties": {
    "iso:country":"IT",
    "sg:address":"24040 Lallio",
    "sg:city":"Lallio",
    "sg:orig_category":"Tessuti Arredamento, Tende E Tappeti",
    "sg:phone":"+39 035 693388",
    "sg:postcode":"24040",
    "sg:province":"Bergamo",
    "wof:name":"Tendaflex Srl",
    "wof:placetype":"venue"
},
  "geometry": {"coordinates":[9.60728,45.634674],"type":"Point"}
}