{
  "type": "Feature",
  "properties": {
    "iso:country":"IT",
    "sg:address":"20154 Milano",
    "sg:city":"Milano",
    "sg:orig_category":"Non-classified Establishments",
    "sg:phone":"+39 02 347885",
    "sg:postcode":"20154",
    "sg:province":"Milano",
    "wof:name":"D.e.c.c.a.",
    "wof:placetype":"venue"
},
  "geometry": {"coordinates":[9.167219,45.481445],"type":"Point"}
}