{
  "type": "Feature",
  "properties": {
    "addr:full":"59, Via Provinciale 24022 Alzano Lombardo Alzano Lombardo Bergamo 24022",
    "addr:postcode":"24022;24022",
    "addr:street":"Via Provinciale",
    "iso:country":"IT",
    "sg:address":"59, Via Provinciale 24022 Alzano Lombardo",
    "sg:city":"Alzano Lombardo",
    "sg:classifiers":[
        {
            "category":"Building & Trades",
            "subcategory":"Construction",
            "type":"Services"
        }
    ],
    "sg:phone":"+39 39035511594",
    "sg:postcode":"24022",
    "sg:province":"Bergamo",
    "sg:tags":[
        "work",
        "public"
    ],
    "wof:name":"Scarpellini (s.p.a.)",
    "wof:placetype":"venue"
},
  "geometry": {"coordinates":[9.731603,45.736835],"type":"Point"}
}