{
  "type": "Feature",
  "properties": {
    "iso:country":"IT",
    "sg:address":"29010 Agazzano",
    "sg:city":"Agazzano",
    "sg:orig_category":"Maneggi E Scuderie Cavalli",
    "sg:phone":"+39 0523 976629",
    "sg:postcode":"29010",
    "sg:province":"Piacenza",
    "wof:name":"Le Merline",
    "wof:placetype":"venue"
},
  "geometry": {"coordinates":[9.519704,44.946739],"type":"Point"}
}