{
  "type": "Feature",
  "properties": {
    "iso:country":"IT",
    "sg:address":"18033 Camporosso",
    "sg:city":"Camporosso",
    "sg:orig_category":"Lavanderie Industriali E Noleggio Biancheria",
    "sg:phone":"+39 0184 252568",
    "sg:postcode":"18033",
    "sg:province":"Imperia",
    "wof:name":"Lavaget Di Giordano & Lituri Snc",
    "wof:placetype":"venue"
},
  "geometry": {"coordinates":[7.631943,43.796951],"type":"Point"}
}