{
  "type": "Feature",
  "properties": {
    "addr:full":"95012 Castiglione Sicilia Catania 95012",
    "addr:postcode":"95012;95012",
    "iso:country":"IT",
    "sg:address":"95012 Castiglione Sicilia",
    "sg:orig_category":"Prodotti Alimentari",
    "sg:phone":"+39 0942 984258",
    "sg:postcode":"95012",
    "sg:province":"Catania",
    "wof:name":"Campione Francesco",
    "wof:placetype":"venue"
},
  "geometry": {"coordinates":[15.08177948,37.5126991272],"type":"Point"}
}