{
  "type": "Feature",
  "properties": {
    "iso:country":"IT",
    "sg:address":"39046 Ortisei",
    "sg:city":"Ortisei",
    "sg:orig_category":"Alberghi",
    "sg:phone":"+39 0471 796171",
    "sg:postcode":"39046",
    "sg:province":"Bolzano/Bozen",
    "sg:website":"http://www.val-gardena.com/hotel/villa-emilia",
    "wof:name":"Hotel Villa Emilia",
    "wof:placetype":"venue"
},
  "geometry": {"coordinates":[11.661343,46.577366],"type":"Point"}
}