{
  "type": "Feature",
  "properties": {
    "addr:full":"20020 Solaro Solaro Milano 20020",
    "addr:postcode":"20020;20020",
    "iso:country":"IT",
    "sg:address":"20020 Solaro",
    "sg:city":"Solaro",
    "sg:orig_category":"Abbigliamento Industria - Macchine Ed Attrezzature",
    "sg:phone":"+39 02 9630 9811",
    "sg:postcode":"20020",
    "sg:province":"Milano",
    "sg:website":"http://www.gerbertechnology.com",
    "wof:name":"Gerber Technology Srl",
    "wof:placetype":"venue"
},
  "geometry": {"coordinates":[9.205008,45.46471],"type":"Point"}
}