{
  "type": "Feature",
  "properties": {
    "addr:full":"37126 Verona Verona Verona 37126",
    "addr:postcode":"37126;37126",
    "iso:country":"IT",
    "sg:address":"37126 Verona",
    "sg:city":"Verona",
    "sg:orig_category":"Ospedali E Servizi Sanitari",
    "sg:phone":"+39 045 918735",
    "sg:postcode":"37126",
    "sg:province":"Verona",
    "sg:website":"http://www.gallieno.it",
    "wof:name":"Analisi Cliniche Gallieno Srl",
    "wof:placetype":"venue"
},
  "geometry": {"coordinates":[10.989206,45.445862],"type":"Point"}
}