{
  "type": "Feature",
  "properties": {
    "iso:country":"IT",
    "sg:address":"Piazza Arti E Mestieri 1, 50026 San Casciano Val Di Pesa, Fi",
    "sg:classifiers":[
        {
            "category":"Banks & Credit Unions",
            "subcategory":"Bank",
            "type":"Services"
        }
    ],
    "sg:postcode":"50026",
    "sg:province":"Firenze",
    "wof:name":"Banca Di Credito Cooperativo Del Chianti Fiorentino",
    "wof:placetype":"venue"
},
  "geometry": {"coordinates":[11.256902,43.768734],"type":"Point"}
}