{
  "type": "Feature",
  "properties": {
    "addr:full":"20043 Arcore Arcore Milano 20043",
    "addr:postcode":"20043;20043",
    "iso:country":"IT",
    "sg:address":"20043 Arcore",
    "sg:city":"Arcore",
    "sg:orig_category":"Forniture Per Abbigliamento E Pelletterie. Forniture E Materiali Per Imballaggio E Confezionamento",
    "sg:phone":"+39 039 614265",
    "sg:postcode":"20043",
    "sg:province":"Milano",
    "wof:name":"Figli Di Daelli Giuseppe S.r.l.",
    "wof:placetype":"venue"
},
  "geometry": {"coordinates":[9.1805763245,45.4775924683],"type":"Point"}
}