{
  "type": "Feature",
  "properties": {
    "iso:country":"IT",
    "sg:address":"10036 Settimo Torinese",
    "sg:city":"Settimo Torinese",
    "sg:orig_category":"Forniture Per Uffici. Regalistica Aziendale",
    "sg:phone":"+39 011 897 7792",
    "sg:postcode":"10036",
    "sg:province":"Torino",
    "wof:name":"Stilo S.n.c. Di Frittella Livio E Pistone Pasqualino",
    "wof:placetype":"venue"
},
  "geometry": {"coordinates":[7.7310681343,45.1461219788],"type":"Point"}
}