{
  "type": "Feature",
  "properties": {
    "iso:country":"IT",
    "sg:address":"62010 Pollenza",
    "sg:city":"Pollenza",
    "sg:orig_category":"Abbigliamento Esterno, Maglierie E Pelliccerie",
    "sg:phone":"+39 0733 549165",
    "sg:postcode":"62010",
    "sg:province":"Macerata",
    "wof:name":"M.a.d.a. Di Damiani Marisa - Giuliano Tricot",
    "wof:placetype":"venue"
},
  "geometry": {"coordinates":[13.361881,43.257549],"type":"Point"}
}