{
  "type": "Feature",
  "properties": {
    "addr:full":"95127 Catania Catania Catania 95127",
    "addr:postcode":"95127;95127",
    "iso:country":"IT",
    "sg:address":"95127 Catania",
    "sg:city":"Catania",
    "sg:orig_category":"Ospedali E Servizi Sanitari",
    "sg:phone":"+39 095 377322",
    "sg:postcode":"95127",
    "sg:province":"Catania",
    "wof:name":"Gecas Srl Gestione Case Di Cura",
    "wof:placetype":"venue"
},
  "geometry": {"coordinates":[15.098997,37.515667],"type":"Point"}
}