{
  "type": "Feature",
  "properties": {
    "addr:full":"11, Via Lungomare 08048 Tortoli' Ogliastra 08048",
    "addr:postcode":"08048;08048",
    "addr:street":"Via Lungomare",
    "iso:country":"IT",
    "sg:address":"11, Via Lungomare 08048 Tortoli'",
    "sg:classifiers":[
        {
            "category":"Professional",
            "subcategory":"Engineering",
            "type":"Services"
        }
    ],
    "sg:phone":"+39 0782 664099",
    "sg:postcode":"08048",
    "sg:province":"Ogliastra",
    "sg:tags":[
        "machine",
        "-",
        "mechanical"
    ],
    "wof:name":"B. Metal Srl",
    "wof:placetype":"venue"
},
  "geometry": {"coordinates":[9.705811,39.935253],"type":"Point"}
}