{
  "type": "Feature",
  "properties": {
    "iso:country":"IT",
    "sg:address":"8, Via Gazzani D. 40012 Calderara Di Reno",
    "sg:city":"Calderara di Reno",
    "sg:classifiers":[
        {
            "category":"Manufacturing",
            "subcategory":"Glass & Minerals",
            "type":"Manufacturing & Wholesale Goods"
        }
    ],
    "sg:phone":"+39 39051727653",
    "sg:postcode":"40012",
    "sg:province":"Bologna",
    "wof:name":"Optovista S.p.a.",
    "wof:placetype":"venue"
},
  "geometry": {"coordinates":[11.269367,44.538082],"type":"Point"}
}