{
  "type": "Feature",
  "properties": {
    "iso:country":"IT",
    "sg:address":"00182 Roma",
    "sg:city":"Roma",
    "sg:orig_category":"Servizi E Lavori Per Abbigliamento E Pelletterie",
    "sg:phone":"+39 06 702 4996",
    "sg:postcode":"00182",
    "sg:province":"Roma",
    "wof:name":"Lindos S.r.l.",
    "wof:placetype":"venue"
},
  "geometry": {"coordinates":[12.516766,41.881756],"type":"Point"}
}