{
  "type": "Feature",
  "properties": {
    "iso:country":"IT",
    "sg:address":"40014 Crevalcore",
    "sg:city":"Crevalcore",
    "sg:orig_category":"Energia Solare Ed Energie Alternative - Impianti E Componenti",
    "sg:phone":"+39 051 680 0544",
    "sg:postcode":"40014",
    "sg:province":"Bologna",
    "wof:name":"Thermomax Italiana Srl",
    "wof:placetype":"venue"
},
  "geometry": {"coordinates":[11.359321,44.505302],"type":"Point"}
}