{
  "type": "Feature",
  "properties": {
    "iso:country":"IT",
    "sg:address":"20058 Villasanta",
    "sg:city":"Villasanta",
    "sg:orig_category":"Termotecnica E Riscaldamento, Apparecchiature E Servizi. Climatizzazione E Condizionamento, Apparecchiature E Servizi",
    "sg:phone":"+39 039 205 0996",
    "sg:postcode":"20058",
    "sg:province":"Milano",
    "wof:name":"Filling Italiana S.r.l.",
    "wof:placetype":"venue"
},
  "geometry": {"coordinates":[9.305615,45.605484],"type":"Point"}
}