{
  "type": "Feature",
  "properties": {
    "iso:country":"IT",
    "sg:address":"Str. Statale 415 Paullese Km, 58 26023 Grumello Cremonese",
    "sg:city":"Grumello cremonese",
    "sg:classifiers":[
        {
            "category":"Banks & Credit Unions",
            "subcategory":"Investment Brokerage",
            "type":"Services"
        }
    ],
    "sg:phone":"+39 0372 70284",
    "sg:postcode":"26023",
    "sg:province":"Cremona",
    "sg:tags":[
        "box",
        "small",
        "folding"
    ],
    "wof:name":"Cartotecnica Ghio Snc",
    "wof:placetype":"venue"
},
  "geometry": {"coordinates":[10.0261354446,45.1334991455],"type":"Point"}
}