{
  "type": "Feature",
  "properties": {
    "iso:country":"IT",
    "sg:address":"321, Via Nazionale 84047 Capaccio",
    "sg:city":"Capaccio",
    "sg:classifiers":[
        {
            "category":"Professional",
            "subcategory":"Engineering",
            "type":"Services"
        }
    ],
    "sg:phone":"+39 0828 871298",
    "sg:postcode":"84047",
    "sg:province":"Salerno",
    "sg:tags":[
        "machine",
        "-",
        "mechanical"
    ],
    "wof:name":"Casa Della Saldatura Srl",
    "wof:placetype":"venue"
},
  "geometry": {"coordinates":[15.012734,40.463215],"type":"Point"}
}