{
  "type": "Feature",
  "properties": {
    "iso:country":"IT",
    "sg:address":"Via Camatte 1 37040 Zimella",
    "sg:city":"Zimella",
    "sg:classifiers":[
        {
            "category":"Real Estate",
            "subcategory":"Real Estate Agent",
            "type":"Services"
        }
    ],
    "sg:phone":"+39 0442 85700",
    "sg:postcode":"37040",
    "sg:province":"Verona",
    "sg:tags":[
        "lacquer"
    ],
    "sg:website":"www.rankover.it",
    "wof:name":"Rankover Spa",
    "wof:placetype":"venue"
},
  "geometry": {"coordinates":[11.361577,45.327606],"type":"Point"}
}