{
  "type": "Feature",
  "properties": {
    "iso:country":"IT",
    "sg:address":"12, Via Bibbiena 50142 Firenze",
    "sg:city":"Firenze",
    "sg:classifiers":[
        {
            "category":"Food & Beverages",
            "subcategory":"Groceries & Convenience Stores",
            "type":"Retail Goods"
        }
    ],
    "sg:phone":"+39 39055732511",
    "sg:postcode":"50142",
    "sg:province":"Firenze",
    "sg:tags":[
        "drink"
    ],
    "wof:name":"Zeus Industria Biologica Alimentare S.p.a.",
    "wof:placetype":"venue"
},
  "geometry": {"coordinates":[11.199541,43.772507],"type":"Point"}
}