{
  "type": "Feature",
  "properties": {
    "iso:country":"IT",
    "sg:address":"41012 Carpi",
    "sg:city":"Carpi",
    "sg:orig_category":"Ospedali E Servizi Sanitari",
    "sg:phone":"+39 059 686945",
    "sg:postcode":"41012",
    "sg:province":"Modena",
    "wof:name":"Pavesi Mantovani Aldina",
    "wof:placetype":"venue"
},
  "geometry": {"coordinates":[10.896285,44.892658],"type":"Point"}
}