{
  "type": "Feature",
  "properties": {
    "addr:full":"30035 Zianigo Zianigo Venezia 30035",
    "addr:postcode":"30035;30035",
    "iso:country":"IT",
    "sg:address":"30035 Zianigo",
    "sg:city":"Zianigo",
    "sg:orig_category":"Servizi E Lavori Per Agricoltura E Zootecnia",
    "sg:phone":"+39 041 570 1329",
    "sg:postcode":"30035",
    "sg:province":"Venezia",
    "wof:name":"Giacomazzo Tarcisio",
    "wof:placetype":"venue"
},
  "geometry": {"coordinates":[12.066671,45.512157],"type":"Point"}
}