{
  "type": "Feature",
  "properties": {
    "iso:country":"IT",
    "sg:address":"61032 Fano",
    "sg:city":"Bellocchi",
    "sg:orig_category":"Legno E Semilavorati",
    "sg:phone":"+39 0721 855147",
    "sg:postcode":"61032",
    "sg:province":"Pesaro E Urbino",
    "sg:website":"http://www.centrodellisolante.com",
    "wof:name":"Centro Dell'isolante Di Onori Fabrizio & C. Sas",
    "wof:placetype":"venue"
},
  "geometry": {"coordinates":[12.997467,43.797623],"type":"Point"}
}