{
  "type": "Feature",
  "properties": {
    "addr:full":"90139 Palermo Palermo Palermo 90139",
    "addr:postcode":"90139;90139",
    "iso:country":"IT",
    "sg:address":"90139 Palermo",
    "sg:city":"Palermo",
    "sg:orig_category":"Massaggi",
    "sg:phone":"+39 091 612 3953",
    "sg:postcode":"90139",
    "sg:province":"Palermo",
    "wof:name":"Iv.ma. Rehabilitation Team Sas",
    "wof:placetype":"venue"
},
  "geometry": {"coordinates":[13.356825,38.127346],"type":"Point"}
}