{
  "type": "Feature",
  "properties": {
    "addr:full":"18010 S. Stefano Al Mare Imperia 18010",
    "addr:housenumber":"18010",
    "addr:postcode":"18010",
    "addr:street":"S. Stefano Al Mare",
    "iso:country":"IT",
    "sg:address":"18010 S. Stefano Al Mare",
    "sg:orig_category":"Nautica. Accessori Dei Mezzi Di Trasporto. Servizi Ausiliari Dei Mezzi Di Trasporto",
    "sg:phone":"+39 0184 487179",
    "sg:postcode":"18010",
    "sg:province":"Imperia",
    "wof:name":"Veleria Viking Di Poppa & C. Snc",
    "wof:placetype":"venue"
},
  "geometry": {"coordinates":[7.828637,43.941868],"type":"Point"}
}