{
  "type": "Feature",
  "properties": {
    "addr:full":"73048 Nard\u00f2 Lecce 73048",
    "addr:postcode":"73048;73048",
    "iso:country":"IT",
    "sg:address":"73048 Nard\u00f2",
    "sg:orig_category":"Manufacturers: Prefabbricati. Idrosanitari E Accessori. Servizi Per Aziende, Manifestazioni E Supporto Agli Scambi Commerciali",
    "sg:phone":"+39 0833 572650",
    "sg:postcode":"73048",
    "sg:province":"Lecce",
    "wof:name":"E.m.i. Ecologia Meridionale Innovativa Di Muci Egidio",
    "wof:placetype":"venue"
},
  "geometry": {"coordinates":[17.996017,40.29446],"type":"Point"}
}