{
  "type": "Feature",
  "properties": {
    "iso:country":"IT",
    "sg:address":"00148 Roma",
    "sg:city":"Roma",
    "sg:classifiers":[
        {
            "category":"Health Services",
            "subcategory":"Dentist",
            "type":"Services"
        }
    ],
    "sg:phone":"+39 06 655951",
    "sg:postcode":"00148",
    "sg:province":"Roma",
    "sg:tags":[
        "hospital"
    ],
    "wof:name":"Villa Sandra Spa",
    "wof:placetype":"venue"
},
  "geometry": {"coordinates":[12.421957,41.849987],"type":"Point"}
}