{
  "type": "Feature",
  "properties": {
    "addr:full":"91017 Pantelleria Pantelleria Trapani 91017",
    "addr:postcode":"91017;91017",
    "iso:country":"IT",
    "sg:address":"91017 Pantelleria",
    "sg:city":"Pantelleria",
    "sg:orig_category":"Ingegneri - Studi",
    "sg:phone":"+39 0923 912520",
    "sg:postcode":"91017",
    "sg:province":"Trapani",
    "wof:name":"Ferrante Ing. Antonello",
    "wof:placetype":"venue"
},
  "geometry": {"coordinates":[12.557287,38.016102],"type":"Point"}
}