{
  "type": "Feature",
  "properties": {
    "iso:country":"IT",
    "sg:address":"Via Cristans 10 33085 Maniago",
    "sg:city":"Maniago",
    "sg:orig_category":"Secateurs, Hedge-clippers, Pruning Shears",
    "sg:phone":"+39 0427 71150",
    "sg:postcode":"33085",
    "sg:province":"Pordenone",
    "sg:website":"www.archman.it",
    "wof:name":"Giovanni Pittau & C. Snc",
    "wof:placetype":"venue"
},
  "geometry": {"coordinates":[12.733773,46.159218],"type":"Point"}
}