{
  "type": "Feature",
  "properties": {
    "iso:country":"IT",
    "sg:address":"47, Via Dell' Artigianato 25039 Travagliato",
    "sg:city":"Travagliato",
    "sg:classifiers":[
        {
            "category":"Shopping",
            "subcategory":"Clothing, Apparel, & Fashions",
            "type":"Retail Goods"
        }
    ],
    "sg:phone":"+39 030 686 3614",
    "sg:postcode":"25039",
    "sg:province":"Brescia",
    "sg:tags":[
        "clothes"
    ],
    "wof:name":"Arcos S.p.a.",
    "wof:placetype":"venue"
},
  "geometry": {"coordinates":[10.126692,45.518864],"type":"Point"}
}