{
  "type": "Feature",
  "properties": {
    "iso:country":"IT",
    "sg:address":"10090 Foglizzo",
    "sg:city":"Foglizzo",
    "sg:orig_category":"Agricoltura, Orticoltura E Floricoltura",
    "sg:phone":"+39 011 988 3542",
    "sg:postcode":"10090",
    "sg:province":"Torino",
    "wof:name":"Bertolino Domenico",
    "wof:placetype":"venue"
},
  "geometry": {"coordinates":[7.569167,45.074329],"type":"Point"}
}