{
  "type": "Feature",
  "properties": {
    "iso:country":"IT",
    "sg:address":"20127 Milano",
    "sg:city":"Milano",
    "sg:orig_category":"Ospedali E Servizi Sanitari",
    "sg:phone":"+39 02 261 9151",
    "sg:postcode":"20127",
    "sg:province":"Milano",
    "wof:name":"Croce S. Rita Associazione Volontaria Di Pronto Soccorso",
    "wof:placetype":"venue"
},
  "geometry": {"coordinates":[9.220678,45.494076],"type":"Point"}
}