{
  "type": "Feature",
  "properties": {
    "iso:country":"IT",
    "sg:address":"31, Via Lungo Chiampo 36054 Montebello Vicentino",
    "sg:city":"Montebello Vicentino",
    "sg:classifiers":[
        {
            "category":"Manufacturing",
            "subcategory":"Textiles",
            "type":"Manufacturing & Wholesale Goods"
        }
    ],
    "sg:phone":"+39 0444 440153",
    "sg:postcode":"36054",
    "sg:province":"Vicenza",
    "sg:tags":[
        "leather",
        "raw",
        "material",
        "-"
    ],
    "wof:name":"Conceria Europa Di Faggiana & Ziggiotti (s.n.c.)",
    "wof:placetype":"venue"
},
  "geometry": {"coordinates":[11.387379,45.465969],"type":"Point"}
}