{
  "type": "Feature",
  "properties": {
    "addr:full":"21052 Busto Arsizio Busto Arsizio Varese 21052",
    "addr:postcode":"21052;21052",
    "iso:country":"IT",
    "sg:address":"21052 Busto Arsizio",
    "sg:city":"Busto Arsizio",
    "sg:orig_category":"Macchine Utensili - Commercio",
    "sg:phone":"+39 0331 632448",
    "sg:postcode":"21052",
    "sg:province":"Varese",
    "wof:name":"B.l. Srl",
    "wof:placetype":"venue"
},
  "geometry": {"coordinates":[8.854794,45.616776],"type":"Point"}
}