{
  "type": "Feature",
  "properties": {
    "iso:country":"IT",
    "sg:address":"31014 Colle Umberto",
    "sg:city":"Colle Umberto",
    "sg:orig_category":"Utensili Meccanici E Materiali",
    "sg:phone":"+39 0438 200152",
    "sg:postcode":"31014",
    "sg:province":"Treviso",
    "wof:name":"Sapio Industrie Srl",
    "wof:placetype":"venue"
},
  "geometry": {"coordinates":[12.322024,45.891487],"type":"Point"}
}