{
  "type": "Feature",
  "properties": {
    "iso:country":"IT",
    "sg:address":"41100 Modena",
    "sg:city":"Modena",
    "sg:orig_category":"Servizi E Lavori Per Abbigliamento E Pelletterie",
    "sg:phone":"+39 059 281227",
    "sg:postcode":"41100",
    "sg:province":"Modena",
    "wof:name":"Lucchi & C. Srl",
    "wof:placetype":"venue"
},
  "geometry": {"coordinates":[10.970762,44.640358],"type":"Point"}
}