{
  "type": "Feature",
  "properties": {
    "iso:country":"IT",
    "sg:address":"53013 Gaiole In Chianti",
    "sg:city":"Gaiole in Chianti",
    "sg:orig_category":"Alberghi E Strutture Extra Alberghiere",
    "sg:phone":"+39 0577 749217",
    "sg:postcode":"53013",
    "sg:province":"Siena",
    "sg:website":"http://www.castellomeleto.it",
    "wof:name":"Castello Di Meleto",
    "wof:placetype":"venue"
},
  "geometry": {"coordinates":[11.411205,43.429482],"type":"Point"}
}