{
  "type": "Feature",
  "properties": {
    "iso:country":"IT",
    "sg:address":"10078 Venaria",
    "sg:orig_category":"Ristoranti",
    "sg:phone":"+39 011 453 0309",
    "sg:postcode":"10078",
    "sg:province":"Torino",
    "wof:name":"Mc Donald's",
    "wof:placetype":"venue"
},
  "geometry": {"coordinates":[7.641111,45.12252],"type":"Point"}
}