{
  "type": "Feature",
  "properties": {
    "addr:full":"24034 Cisano Bergamasco Cisano Bergamasco Bergamo 24034",
    "addr:postcode":"24034;24034",
    "iso:country":"IT",
    "sg:address":"24034 Cisano Bergamasco",
    "sg:city":"Cisano Bergamasco",
    "sg:orig_category":"Macchine, Impianti Ed Attrezzature Per Agricoltura E Zootecnia",
    "sg:phone":"+39 035 781050",
    "sg:postcode":"24034",
    "sg:province":"Bergamo",
    "wof:name":"Bonsaglia Luigi",
    "wof:placetype":"venue"
},
  "geometry": {"coordinates":[9.469285,45.744629],"type":"Point"}
}