{
  "type": "Feature",
  "properties": {
    "iso:country":"IT",
    "sg:address":"55012 Capannori",
    "sg:city":"Capannori",
    "sg:orig_category":"Calzaturifici E Calzolai - Forniture",
    "sg:phone":"+39 0583 407054",
    "sg:postcode":"55012",
    "sg:province":"Lucca",
    "sg:website":"http://www.marcello.it",
    "wof:name":"Calzaturificio Marcello Srl",
    "wof:placetype":"venue"
},
  "geometry": {"coordinates":[10.540193,43.89534],"type":"Point"}
}