{
  "type": "Feature",
  "properties": {
    "iso:country":"IT",
    "sg:address":"18, Strada Del Turchino 15067 Novi Ligure",
    "sg:city":"Novi Ligure",
    "sg:classifiers":[
        {
            "category":"Food & Beverages",
            "subcategory":"Groceries & Convenience Stores",
            "type":"Retail Goods"
        }
    ],
    "sg:phone":"+39 0143 321308",
    "sg:postcode":"15067",
    "sg:province":"Alessandria",
    "sg:tags":[
        "drink"
    ],
    "wof:name":"Partesa Piemonte S.r.l.",
    "wof:placetype":"venue"
},
  "geometry": {"coordinates":[8.76643,44.767017],"type":"Point"}
}