{
  "type": "Feature",
  "properties": {
    "addr:full":"21057 Olgiate Olona Olgiate Olona Varese 21057",
    "addr:postcode":"21057;21057",
    "iso:country":"IT",
    "sg:address":"21057 Olgiate Olona",
    "sg:city":"Olgiate Olona",
    "sg:orig_category":"Servizi Per Aziende, Manifestazioni E Supporto Agli Scambi Commerciali",
    "sg:phone":"+39 0331 643361",
    "sg:postcode":"21057",
    "sg:province":"Varese",
    "wof:name":"Skorpion Investigations Di Romano Renato & C. Sas",
    "wof:placetype":"venue"
},
  "geometry": {"coordinates":[8.881413,45.629898],"type":"Point"}
}