{
  "type": "Feature",
  "properties": {
    "iso:country":"IT",
    "sg:address":"21, Via Pisacane Carlo 15100 Alessandria",
    "sg:city":"Alessandria",
    "sg:classifiers":[
        {
            "category":"Food & Beverages",
            "subcategory":"Dairy",
            "type":"Retail Goods"
        }
    ],
    "sg:phone":"+39 0131 226426",
    "sg:postcode":"15100",
    "sg:province":"Alessandria",
    "sg:tags":[
        "product"
    ],
    "wof:name":"Centro Cooperativa Raccolta Latte (soc.coop.r.l.)",
    "wof:placetype":"venue"
},
  "geometry": {"coordinates":[8.628901,44.913681],"type":"Point"}
}