{
  "type": "Feature",
  "properties": {
    "iso:country":"IT",
    "sg:address":"Via Calcare 1 37030 Badia Calavena",
    "sg:city":"Badia Calavena",
    "sg:classifiers":[
        {
            "category":"Home & Garden",
            "subcategory":"Building Materials",
            "type":"Retail Goods"
        }
    ],
    "sg:phone":"+39 045 781 0680",
    "sg:postcode":"37030",
    "sg:province":"Verona",
    "sg:tags":[
        "slab",
        "marble"
    ],
    "wof:name":"Pavimar Snc Di Gugole Aldo & C.",
    "wof:placetype":"venue"
},
  "geometry": {"coordinates":[11.15381,45.554798],"type":"Point"}
}