{
  "type": "Feature",
  "properties": {
    "addr:full":"100, Via Amendolara 73040 Specchia Specchia Lecce 73040",
    "addr:housenumber":"100",
    "addr:postcode":"73040;73040",
    "addr:street":"Via Amendolara",
    "iso:country":"IT",
    "sg:address":"100, Via Amendolara 73040 Specchia",
    "sg:city":"Specchia",
    "sg:classifiers":[
        {
            "category":"Shopping",
            "subcategory":"Clothing, Apparel, & Fashions",
            "type":"Retail Goods"
        }
    ],
    "sg:phone":"+39 0833 539894",
    "sg:postcode":"73040",
    "sg:province":"Lecce",
    "sg:tags":[
        "clothes"
    ],
    "wof:name":"Calzificio Amendolara Srl",
    "wof:placetype":"venue"
},
  "geometry": {"coordinates":[18.302139,39.937607],"type":"Point"}
}