{
  "type": "Feature",
  "properties": {
    "iso:country":"IT",
    "sg:address":"20081 Abbiategrasso",
    "sg:city":"Abbiategrasso",
    "sg:orig_category":"Forniture Per Edilizia E Lavori Pubblici",
    "sg:phone":"+39 02 9496 8265",
    "sg:postcode":"20081",
    "sg:province":"Milano",
    "wof:name":"Bricolegno Di Maestri Oreste",
    "wof:placetype":"venue"
},
  "geometry": {"coordinates":[8.9198246002,45.3930358887],"type":"Point"}
}