{
  "type": "Feature",
  "properties": {
    "iso:country":"IT",
    "sg:address":"06034 Foligno",
    "sg:city":"Foligno",
    "sg:orig_category":"Lenti A Contatto E Per Occhiali - Produzione E Ingrosso",
    "sg:phone":"+39 0742 356946",
    "sg:postcode":"06034",
    "sg:province":"Perugia",
    "wof:name":"Brunelli Alfredo",
    "wof:placetype":"venue"
},
  "geometry": {"coordinates":[12.702888,42.957958],"type":"Point"}
}