{
  "type": "Feature",
  "properties": {
    "addr:full":"16030 Cogorno Cogorno Genova 16030",
    "addr:housenumber":"16030",
    "addr:postcode":"16030",
    "addr:street":"Cogorno Cogorno Genova",
    "iso:country":"IT",
    "sg:address":"16030 Cogorno",
    "sg:city":"Cogorno",
    "sg:orig_category":"Asfalti, Bitumi Ed Affini",
    "sg:phone":"+39 0185 380719",
    "sg:postcode":"16030",
    "sg:province":"Genova",
    "wof:name":"Em.co.bit. - Tropeano & C. Sas",
    "wof:placetype":"venue"
},
  "geometry": {"coordinates":[9.3656291962,44.3478317261],"type":"Point"}
}