{
  "type": "Feature",
  "properties": {
    "addr:full":"70, Via M. Polo 20083 Gaggiano Gaggiano Milano 20083",
    "addr:postcode":"20083;20083",
    "addr:street":"Via M. Polo",
    "iso:country":"IT",
    "sg:address":"70, Via M. Polo 20083 Gaggiano",
    "sg:city":"Gaggiano",
    "sg:classifiers":[
        {
            "category":"Autos & Motor Vehicles",
            "subcategory":"Automobile Sales",
            "type":"Retail Goods"
        }
    ],
    "sg:phone":"+39 39029081039",
    "sg:postcode":"20083",
    "sg:province":"Milano",
    "sg:tags":[
        "motor-cars"
    ],
    "wof:name":"Sguinzi Pietro (s.p.a.)",
    "wof:placetype":"venue"
},
  "geometry": {"coordinates":[9.0879869461,45.4450531006],"type":"Point"}
}