{
  "type": "Feature",
  "properties": {
    "addr:full":"Via Lega Lombarda 7 24035 Curno Curno Bergamo 24035",
    "addr:housenumber":"7",
    "addr:postcode":"24035;24035",
    "addr:street":"Via Lega Lombarda",
    "iso:country":"IT",
    "sg:address":"Via Lega Lombarda 7 24035 Curno",
    "sg:city":"Curno",
    "sg:classifiers":[
        {
            "category":"Manufacturing",
            "subcategory":"Pottery",
            "type":"Manufacturing & Wholesale Goods"
        }
    ],
    "sg:phone":"+39 035 437 6649",
    "sg:postcode":"24035",
    "sg:province":"Bergamo",
    "sg:tags":[
        "decorative",
        "porcelain"
    ],
    "sg:website":"www.fabarporcellane.it",
    "wof:name":"Fabar Srl",
    "wof:placetype":"venue"
},
  "geometry": {"coordinates":[9.610684,45.683796],"type":"Point"}
}