{
  "type": "Feature",
  "properties": {
    "iso:country":"IT",
    "sg:address":"80134 Napoli",
    "sg:city":"Napoli",
    "sg:orig_category":"Servizi Al Turismo. Centri Di Estetica E Cosmesi E Servizi",
    "sg:phone":"+39 081 551 1291",
    "sg:postcode":"80134",
    "sg:province":"Napoli",
    "wof:name":"Cantiello Antimo",
    "wof:placetype":"venue"
},
  "geometry": {"coordinates":[14.269413,40.91161],"type":"Point"}
}