{
  "type": "Feature",
  "properties": {
    "addr:full":"1, Via Di Vittorio 20060 Vignate Vignate Milano 20060",
    "addr:postcode":"20060;20060",
    "addr:street":"Via Di Vittorio",
    "iso:country":"IT",
    "sg:address":"1, Via Di Vittorio 20060 Vignate",
    "sg:city":"Vignate",
    "sg:classifiers":[
        {
            "category":"Wholesale",
            "subcategory":"Machinery & Supplies",
            "type":"Manufacturing & Wholesale Goods"
        }
    ],
    "sg:phone":"+39 390 295 4581",
    "sg:postcode":"20060",
    "sg:province":"Milano",
    "sg:tags":[
        "-",
        "agriculture",
        "equipment"
    ],
    "wof:name":"John Deere Italiana-sede Italiana Della Deere & Company",
    "wof:placetype":"venue"
},
  "geometry": {"coordinates":[9.332711,45.502911],"type":"Point"}
}