{
  "type": "Feature",
  "properties": {
    "iso:country":"IT",
    "sg:address":"30174 Venezia",
    "sg:city":"Mestre",
    "sg:orig_category":"Utensili Meccanici E Materiali",
    "sg:phone":"+39 041 988255",
    "sg:postcode":"30174",
    "sg:province":"Venezia",
    "sg:website":"http://www.botterluigi.it",
    "wof:name":"Botter Luigi Sas",
    "wof:placetype":"venue"
},
  "geometry": {"coordinates":[12.236166,45.504772],"type":"Point"}
}