{
  "type": "Feature",
  "properties": {
    "addr:full":"70031 Andria Andria Bari 70031",
    "addr:housenumber":"70031",
    "addr:postcode":"70031",
    "iso:country":"IT",
    "sg:address":"70031 Andria",
    "sg:city":"Andria",
    "sg:orig_category":"Tessuti E Stoffe. Filati E Materie Prime Tessili",
    "sg:phone":"+39 0883 550788",
    "sg:postcode":"70031",
    "sg:province":"Bari",
    "wof:name":"Athena Tessile Di Tota Domenica",
    "wof:placetype":"venue"
},
  "geometry": {"coordinates":[16.297255,41.231438],"type":"Point"}
}