{
  "type": "Feature",
  "properties": {
    "iso:country":"IT",
    "sg:address":"10098 Cascine Vica",
    "sg:city":"Cascine vica",
    "sg:orig_category":"Carni, Salumi E Pesci",
    "sg:phone":"+39 011 959 8240",
    "sg:postcode":"10098",
    "sg:province":"Torino",
    "wof:name":"Mattia Michele",
    "wof:placetype":"venue"
},
  "geometry": {"coordinates":[7.579922,45.072704],"type":"Point"}
}