{
  "type": "Feature",
  "properties": {
    "iso:country":"IT",
    "sg:address":"90138 Palermo",
    "sg:city":"Palermo",
    "sg:orig_category":"Automazione E Macchine Per Ufficio. Arredi Ed Attrezzature Per Attivita' Commerciali Ed Artigianali",
    "sg:phone":"+39 091 333619",
    "sg:postcode":"90138",
    "sg:province":"Palermo",
    "wof:name":"A.t.m.u. Di Viola Pietro",
    "wof:placetype":"venue"
},
  "geometry": {"coordinates":[13.348316,38.120705],"type":"Point"}
}