{
  "type": "Feature",
  "properties": {
    "iso:country":"IT",
    "sg:address":"20018 Sedriano",
    "sg:city":"Sedriano",
    "sg:orig_category":"Antincendio - Impianti, Attrezzature E Materiali",
    "sg:phone":"+39 02 9011 0529",
    "sg:postcode":"20018",
    "sg:province":"Milano",
    "sg:website":"http://www.astrasistemiantincendiosrl.it",
    "wof:name":"Astra Sistemi Antincendio",
    "wof:placetype":"venue"
},
  "geometry": {"coordinates":[9.006574,45.473671],"type":"Point"}
}