{
  "type": "Feature",
  "properties": {
    "iso:country":"IT",
    "sg:address":"Via Comunale Vecchia Pesciatina 55012 Capannori",
    "sg:city":"Capannori",
    "sg:classifiers":[
        {
            "category":"Personal",
            "subcategory":"Shoe Repair & Shine",
            "type":"Services"
        }
    ],
    "sg:phone":"+39 0583 962457",
    "sg:postcode":"55012",
    "sg:province":"Lucca",
    "sg:tags":[
        "leather"
    ],
    "wof:name":"Calzaturificio Consuelo Srl",
    "wof:placetype":"venue"
},
  "geometry": {"coordinates":[10.583333,43.833332],"type":"Point"}
}