{
  "type": "Feature",
  "properties": {
    "iso:country":"IT",
    "sg:address":"89, Via Meucci 36057 Arcugnano",
    "sg:city":"Arcugnano",
    "sg:classifiers":[
        {
            "category":"Manufacturing",
            "subcategory":"Metals",
            "type":"Manufacturing & Wholesale Goods"
        }
    ],
    "sg:phone":"+39 0444 288919",
    "sg:postcode":"36057",
    "sg:province":"Vicenza",
    "sg:tags":[
        "metallurgy",
        "metalworking"
    ],
    "wof:name":"Alutecnica S.r.l.",
    "wof:placetype":"venue"
},
  "geometry": {"coordinates":[11.5134000778,45.5083274841],"type":"Point"}
}