{
  "type": "Feature",
  "properties": {
    "iso:country":"IT",
    "sg:address":"62010 Mogliano",
    "sg:city":"Mogliano",
    "sg:orig_category":"Arredamenti - Produzione E Ingrosso",
    "sg:phone":"+39 0733 556679",
    "sg:postcode":"62010",
    "sg:province":"Macerata",
    "wof:name":"I.a.g. Dei F. Lli Frattari",
    "wof:placetype":"venue"
},
  "geometry": {"coordinates":[13.474187,43.183937],"type":"Point"}
}