{
  "type": "Feature",
  "properties": {
    "addr:full":"Piza Collegiata 24; Biancavilla; 95033 Biancavilla Catania 95033",
    "addr:housenumber":"24",
    "addr:postcode":"95033;95033",
    "addr:street":"Collegiata",
    "iso:country":"IT",
    "sg:address":"Piza Collegiata 24; Biancavilla; 95033",
    "sg:city":"Biancavilla",
    "sg:classifiers":[
        {
            "category":"Banks & Credit Unions",
            "subcategory":"Bank",
            "type":"Services"
        }
    ],
    "sg:phone":"+39 095 771 1075",
    "sg:postcode":"95033",
    "sg:province":"Catania",
    "wof:name":"Credito Emiliano Spa",
    "wof:placetype":"venue"
},
  "geometry": {"coordinates":[14.863904,37.645138],"type":"Point"}
}