{
  "type": "Feature",
  "properties": {
    "iso:country":"IT",
    "sg:address":"10092 Beinasco",
    "sg:city":"Beinasco",
    "sg:orig_category":"Minuterie Metalliche E Ferramenta. Forniture Per Attivita' Industriali",
    "sg:phone":"+39 011 349 0586",
    "sg:postcode":"10092",
    "sg:province":"Torino",
    "wof:name":"Fims Snc Di Marchino Andrea E Paola",
    "wof:placetype":"venue"
},
  "geometry": {"coordinates":[7.586956501,45.0284729004],"type":"Point"}
}