{
  "type": "Feature",
  "properties": {
    "iso:country":"IT",
    "sg:address":"60027 Osimo",
    "sg:city":"Osimo",
    "sg:orig_category":"Macchine Utensili E Impianti",
    "sg:phone":"+39 071 710 9291",
    "sg:postcode":"60027",
    "sg:province":"Ancona",
    "sg:website":"http://www.metalplast.it",
    "wof:name":"Metalplast Di Bontempo Daniele",
    "wof:placetype":"venue"
},
  "geometry": {"coordinates":[13.474299,43.467899],"type":"Point"}
}