{
  "type": "Feature",
  "properties": {
    "iso:country":"IT",
    "sg:address":"73044 Galatone",
    "sg:city":"Galatone",
    "sg:orig_category":"Articoli Per Imballaggio E Confezionamento",
    "sg:phone":"+39 0833 861066",
    "sg:postcode":"73044",
    "sg:province":"Lecce",
    "wof:name":"Giuri Gaetano Di Giuri Vito & Fratelli (s.n.c.)",
    "wof:placetype":"venue"
},
  "geometry": {"coordinates":[18.044857,40.347054],"type":"Point"}
}