{
  "type": "Feature",
  "properties": {
    "iso:country":"IT",
    "sg:address":"23100 Sondrio",
    "sg:city":"Sondrio",
    "sg:orig_category":"Agenzie D'affari E Servizi Commerciali. Acqua, Luce, Gas E Societa' Di Esercizio Pubblico",
    "sg:phone":"+39 0342 218860",
    "sg:postcode":"23100",
    "sg:province":"Sondrio",
    "wof:name":"Istituto Vendite Srl",
    "wof:placetype":"venue"
},
  "geometry": {"coordinates":[9.871861,46.168671],"type":"Point"}
}