{
  "type": "Feature",
  "properties": {
    "iso:country":"IT",
    "sg:address":"37053 Cerea",
    "sg:city":"Asparetto",
    "sg:orig_category":"Salotti, Poltrone, Sedie E Tavoli",
    "sg:phone":"+39 0442 83135",
    "sg:postcode":"37053",
    "sg:province":"Verona",
    "wof:name":"Giavoni Adriano",
    "wof:placetype":"venue"
},
  "geometry": {"coordinates":[11.171824,45.21859],"type":"Point"}
}