{
  "type": "Feature",
  "properties": {
    "iso:country":"IT",
    "sg:address":"43044 Collecchio",
    "sg:city":"Collecchio",
    "sg:orig_category":"Lamiere - Lavorazione",
    "sg:phone":"+39 0521 804191",
    "sg:postcode":"43044",
    "sg:province":"Parma",
    "wof:name":"Eurosteel Italia Srl",
    "wof:placetype":"venue"
},
  "geometry": {"coordinates":[10.262858,44.771561],"type":"Point"}
}