{
  "type": "Feature",
  "properties": {
    "iso:country":"IT",
    "sg:address":"20131 Milano",
    "sg:city":"Milano",
    "sg:orig_category":"Studi E Consulenze Tecniche E Industriali. Servizi E Lavori Per Edilizia E Lavori Pubblici. Professionisti - Studi E Servizi Ed Associazioni Di Interesse Aziendale",
    "sg:phone":"+39 02 2611 3518",
    "sg:postcode":"20131",
    "sg:province":"Milano",
    "wof:name":"Moles Geom. Alessandro",
    "wof:placetype":"venue"
},
  "geometry": {"coordinates":[9.219234,45.486542],"type":"Point"}
}