{
  "type": "Feature",
  "properties": {
    "iso:country":"IT",
    "sg:address":"13871 Verrone",
    "sg:city":"Verrone",
    "sg:orig_category":"Tessuti E Stoffe. Filati E Materie Prime Tessili",
    "sg:postcode":"13871",
    "sg:province":"Biella",
    "wof:name":"Filatura Vertex (s.r.l.)",
    "wof:placetype":"venue"
},
  "geometry": {"coordinates":[8.120167,45.504704],"type":"Point"}
}