{
  "type": "Feature",
  "properties": {
    "iso:country":"IT",
    "sg:address":"10/l, V. Campo Di Marte06124 Perugia",
    "sg:city":"Perugia",
    "sg:classifiers":[
        {
            "category":"Shopping",
            "subcategory":"Clothing, Apparel, & Fashions",
            "type":"Retail Goods"
        }
    ],
    "sg:phone":"+39 075 505 6704",
    "sg:postcode":"06124",
    "sg:province":"Perugia",
    "sg:tags":[
        "clothes"
    ],
    "sg:website":"http://www.divertilandia.it",
    "wof:name":"Divertilandia Snc",
    "wof:placetype":"venue"
},
  "geometry": {"coordinates":[12.379078,43.101433],"type":"Point"}
}