{
  "type": "Feature",
  "properties": {
    "iso:country":"IT",
    "sg:address":"Via Chiesa 33; Cerlongo Di Goita",
    "sg:classifiers":[
        {
            "category":"Banks & Credit Unions",
            "subcategory":"Bank",
            "type":"Services"
        }
    ],
    "sg:phone":"+39 0376 687580",
    "wof:name":"Banca Agricola Mantovana Scarl",
    "wof:placetype":"venue"
},
  "geometry": {"coordinates":[10.646283,45.279083],"type":"Point"}
}