{
  "type": "Feature",
  "properties": {
    "addr:full":"262, Localita' Serraglio 53048 Sinalunga Sinalunga Siena 53048",
    "addr:housenumber":"262",
    "addr:postcode":"53048;53048",
    "addr:street":"Localita ' Serraglio",
    "iso:country":"IT",
    "sg:address":"262, Localita' Serraglio 53048 Sinalunga",
    "sg:city":"Sinalunga",
    "sg:classifiers":[
        {
            "category":"Home & Garden",
            "subcategory":"Home Furnishings",
            "type":"Retail Goods"
        }
    ],
    "sg:phone":"+39 0577 632130",
    "sg:postcode":"53048",
    "sg:province":"Siena",
    "sg:tags":[
        "household"
    ],
    "wof:name":"Terrecotte D'arte Snc",
    "wof:placetype":"venue"
},
  "geometry": {"coordinates":[11.330514,43.318661],"type":"Point"}
}