{
  "type": "Feature",
  "properties": {
    "iso:country":"IT",
    "sg:address":"19121 La Spezia",
    "sg:orig_category":"Banche Ed Istituti Di Credito E Risparmio",
    "sg:phone":"+39 0187 773111",
    "sg:province":"SP",
    "sg:website":"http://www.carispe.it",
    "wof:name":"Cassa Di Risparmio Della Spezia",
    "wof:placetype":"venue"
},
  "geometry": {"coordinates":[9.819223,44.104671],"type":"Point"}
}