{
  "type": "Feature",
  "properties": {
    "iso:country":"IT",
    "sg:address":"4, Viale Francia 35020 Ponte San Nicolo'",
    "sg:classifiers":[
        {
            "category":"Shopping",
            "type":"Retail Goods"
        }
    ],
    "sg:phone":"+39 049 896 0313",
    "sg:postcode":"35020",
    "sg:province":"Padova",
    "sg:tags":[
        "finished",
        "-",
        "metallic"
    ],
    "wof:name":"Moulds Pro-tec (s.r.l.)",
    "wof:placetype":"venue"
},
  "geometry": {"coordinates":[11.9240512848,45.3550033569],"type":"Point"}
}