{
  "type": "Feature",
  "properties": {
    "addr:full":"7, Via Artigiani S. Michele 39057 Appiano Sulla Strada Del Vino Appiano sulla strada del vino Bolzano/Bozen 39057",
    "addr:postcode":"39057;39057",
    "addr:street":"Via Artigiani S. Michele;Strada;Sulla Strada Del Vino",
    "iso:country":"IT",
    "sg:address":"7, Via Artigiani S. Michele 39057 Appiano Sulla Strada Del Vino",
    "sg:city":"Appiano sulla strada del vino",
    "sg:classifiers":[
        {
            "category":"Building & Trades",
            "subcategory":"Construction",
            "type":"Services"
        }
    ],
    "sg:phone":"+39 0471 663158",
    "sg:postcode":"39057",
    "sg:province":"Bolzano/Bozen",
    "sg:tags":[
        "work",
        "public"
    ],
    "wof:name":"Sportbau (s.r.l. - G.m.b.h.)",
    "wof:placetype":"venue"
},
  "geometry": {"coordinates":[11.267175,46.461433],"type":"Point"}
}