{
  "type": "Feature",
  "properties": {
    "addr:full":"Km. 26.400, Via Nettunense 04011 Aprilia Aprilia Latina 04011",
    "addr:postcode":"04011;04011",
    "addr:street":"Km. 26.400 Via Nettunense",
    "iso:country":"IT",
    "sg:address":"Km. 26.400, Via Nettunense 04011 Aprilia",
    "sg:city":"Aprilia",
    "sg:classifiers":[
        {
            "category":"Shopping",
            "subcategory":"Stationery & Office Supplies",
            "type":"Retail Goods"
        }
    ],
    "sg:phone":"+39 06 9274 6219",
    "sg:postcode":"04011",
    "sg:province":"Latina",
    "sg:tags":[
        "professional"
    ],
    "wof:name":"Inside International Srl",
    "wof:placetype":"venue"
},
  "geometry": {"coordinates":[12.9036998749,41.4675979614],"type":"Point"}
}