{
  "type": "Feature",
  "properties": {
    "iso:country":"IT",
    "sg:address":"59100 Prato",
    "sg:city":"Prato",
    "sg:orig_category":"Servizi Vari Di Interesse Pubblico",
    "sg:phone":"+39 0574 632415",
    "sg:postcode":"59100",
    "sg:province":"Prato",
    "wof:name":"L'isola Che Non C'e' Di Mariella Menci & C. Snc",
    "wof:placetype":"venue"
},
  "geometry": {"coordinates":[11.125835,43.936611],"type":"Point"}
}