{
  "type": "Feature",
  "properties": {
    "iso:country":"IT",
    "sg:address":"00187 Roma",
    "sg:city":"Roma",
    "sg:orig_category":"Forniture Per Abbigliamento E Pelletterie. Complementi Di Arredamento",
    "sg:phone":"+39 06 679 0561",
    "sg:postcode":"00187",
    "sg:province":"Roma",
    "wof:name":"Micci Giuseppe (s.r.l.)",
    "wof:placetype":"venue"
},
  "geometry": {"coordinates":[12.4801292419,41.9039344788],"type":"Point"}
}