{
  "type": "Feature",
  "properties": {
    "addr:full":"21013 Gallarate Gallarate Varese 21013",
    "addr:postcode":"21013;21013",
    "iso:country":"IT",
    "sg:address":"21013 Gallarate",
    "sg:city":"Gallarate",
    "sg:orig_category":"Arredi Ed Attrezzature Per Uffici",
    "sg:phone":"+39 0331 774844",
    "sg:postcode":"21013",
    "sg:province":"Varese",
    "wof:name":"Blu 3 Gallarate Srl",
    "wof:placetype":"venue"
},
  "geometry": {"coordinates":[8.788728,45.650784],"type":"Point"}
}