{
  "type": "Feature",
  "properties": {
    "addr:full":"18, Via Arcoleo Giorgio 80121 Napoli Napoli Napoli 80121",
    "addr:postcode":"80121;80121",
    "addr:street":"Via Arcoleo Giorgio",
    "iso:country":"IT",
    "sg:address":"18, Via Arcoleo Giorgio 80121 Napoli",
    "sg:city":"Napoli",
    "sg:classifiers":[
        {
            "category":"Autos & Motor Vehicles",
            "subcategory":"Automobile Sales",
            "type":"Retail Goods"
        }
    ],
    "sg:phone":"+39 39800253680",
    "sg:postcode":"80121",
    "sg:province":"Napoli",
    "sg:tags":[
        "motor-cars"
    ],
    "wof:name":"Officine Pelli S.p.a.",
    "wof:placetype":"venue"
},
  "geometry": {"coordinates":[14.2516355515,40.84009552],"type":"Point"}
}