{
  "type": "Feature",
  "properties": {
    "addr:full":"25125 Brescia Brescia Brescia 25125",
    "addr:postcode":"25125;25125",
    "iso:country":"IT",
    "sg:address":"25125 Brescia",
    "sg:city":"Brescia",
    "sg:classifiers":[
        {
            "category":"Shopping",
            "subcategory":"Computers & Home Electronics",
            "type":"Retail Goods"
        }
    ],
    "sg:phone":"+39 030 268 5411",
    "sg:postcode":"25125",
    "sg:province":"Brescia",
    "sg:tags":[
        "personal",
        "ed",
        "accessori"
    ],
    "sg:website":"http://www.stl-it.com",
    "wof:name":"Societa' Telefonica Lombarda Di Leo Carlo & C. Sas",
    "wof:placetype":"venue"
},
  "geometry": {"coordinates":[10.1857709885,45.5203857422],"type":"Point"}
}