{
  "type": "Feature",
  "properties": {
    "iso:country":"IT",
    "sg:address":"98, Via Giovanni Ventitreesimo 23889 Santa Maria Hoe'",
    "sg:classifiers":[
        {
            "category":"Manufacturing",
            "subcategory":"Paper Products",
            "type":"Manufacturing & Wholesale Goods"
        }
    ],
    "sg:phone":"+39 39039570293",
    "sg:postcode":"23889",
    "sg:province":"Lecco",
    "sg:tags":[
        "cardboard"
    ],
    "wof:name":"Scatolificio Samo (s.r.l.)",
    "wof:placetype":"venue"
},
  "geometry": {"coordinates":[9.3900709152,45.8529815674],"type":"Point"}
}