{
  "type": "Feature",
  "properties": {
    "iso:country":"IT",
    "sg:address":"18038 Bussana",
    "sg:city":"Bussana",
    "sg:orig_category":"Macchine, Impianti Ed Attrezzature Per Agricoltura E Zootecnia",
    "sg:postcode":"18038",
    "sg:province":"Imperia",
    "wof:name":"Rodolfi Gaetano",
    "wof:placetype":"venue"
},
  "geometry": {"coordinates":[7.83868,43.83205],"type":"Point"}
}