{
  "type": "Feature",
  "properties": {
    "iso:country":"IT",
    "sg:address":"53040 Cetona",
    "sg:city":"Cetona",
    "sg:orig_category":"Articoli Per Imballaggio E Confezionamento",
    "sg:phone":"+39 0578 237024",
    "sg:postcode":"53040",
    "sg:province":"Siena",
    "wof:name":"Luciano Volpicella",
    "wof:placetype":"venue"
},
  "geometry": {"coordinates":[11.906503,42.966816],"type":"Point"}
}