{
  "type": "Feature",
  "properties": {
    "addr:full":"10146 Torino Torino Torino 10146",
    "addr:postcode":"10146;10146",
    "iso:country":"IT",
    "sg:address":"10146 Torino",
    "sg:city":"Torino",
    "sg:orig_category":"Cine-foto-ottica. Shopping",
    "sg:phone":"+39 011 773 2644",
    "sg:postcode":"10146",
    "sg:province":"Torino",
    "wof:name":"Sexbuster",
    "wof:placetype":"venue"
},
  "geometry": {"coordinates":[7.628252,45.083591],"type":"Point"}
}