{
  "type": "Feature",
  "properties": {
    "iso:country":"IT",
    "sg:address":"10, Via Buozzi 43030 Torrile",
    "sg:classifiers":[
        {
            "category":"Professional",
            "subcategory":"Engineering",
            "type":"Services"
        }
    ],
    "sg:phone":"+39 0521 819221",
    "sg:postcode":"43030",
    "sg:province":"Parma",
    "sg:tags":[
        "machine",
        "-",
        "mechanical"
    ],
    "wof:name":"Spotti Sergio (s.r.l.)",
    "wof:placetype":"venue"
},
  "geometry": {"coordinates":[10.360895,44.891602],"type":"Point"}
}