{
  "type": "Feature",
  "properties": {
    "iso:country":"IT",
    "sg:address":"Via Matteotti 28; Montagnana; 35044",
    "sg:city":"Montagnana",
    "sg:classifiers":[
        {
            "category":"Banks & Credit Unions",
            "subcategory":"Bank",
            "type":"Services"
        }
    ],
    "sg:phone":"+39 0429 81745",
    "sg:postcode":"35044",
    "sg:province":"Padova",
    "wof:name":"Banca Antoniana, Popolare Veneta Scarl",
    "wof:placetype":"venue"
},
  "geometry": {"coordinates":[11.464306,45.233665],"type":"Point"}
}