{
  "type": "Feature",
  "properties": {
    "iso:country":"IT",
    "sg:address":"134, Via Romana Ovest 55016 Porcari",
    "sg:city":"Porcari",
    "sg:classifiers":[
        {
            "category":"Professional",
            "subcategory":"Engineering",
            "type":"Services"
        }
    ],
    "sg:phone":"+39 0583 297171",
    "sg:postcode":"55016",
    "sg:province":"Lucca",
    "sg:tags":[
        "machine",
        "-",
        "mechanical"
    ],
    "wof:name":"A.celli (s.p.a.)",
    "wof:placetype":"venue"
},
  "geometry": {"coordinates":[10.611396,43.851624],"type":"Point"}
}