{
  "type": "Feature",
  "properties": {
    "iso:country":"IT",
    "sg:address":"Via Romana 55015 Montecarlo",
    "sg:city":"Montecarlo",
    "sg:classifiers":[
        {
            "category":"Shopping",
            "subcategory":"Clothing, Apparel, & Fashions",
            "type":"Retail Goods"
        }
    ],
    "sg:phone":"+39 0583 276175",
    "sg:postcode":"55015",
    "sg:province":"Lucca",
    "sg:tags":[
        "clothes"
    ],
    "wof:name":"Turingia",
    "wof:placetype":"venue"
},
  "geometry": {"coordinates":[10.638162,43.830929],"type":"Point"}
}