{
  "type": "Feature",
  "properties": {
    "addr:full":"00044 Frascati Frascati Roma 00044",
    "addr:postcode":"00044;00044",
    "iso:country":"IT",
    "sg:address":"00044 Frascati",
    "sg:city":"Frascati",
    "sg:orig_category":"Fiori E Piante - Vendita Al Dettaglio",
    "sg:phone":"+39 06 940 9296",
    "sg:postcode":"00044",
    "sg:province":"Roma",
    "wof:name":"Magnolia Garden Snc",
    "wof:placetype":"venue"
},
  "geometry": {"coordinates":[12.5137739182,41.8829345703],"type":"Point"}
}