{
  "type": "Feature",
  "properties": {
    "iso:country":"IT",
    "sg:address":"31, Via Mirafiori Gil 10092 Beinasco",
    "sg:city":"Beinasco",
    "sg:classifiers":[
        {
            "category":"Autos & Motor Vehicles",
            "subcategory":"Automobile Sales",
            "type":"Retail Goods"
        }
    ],
    "sg:phone":"+39 011 349 0194",
    "sg:postcode":"10092",
    "sg:province":"Torino",
    "sg:tags":[
        "industrial"
    ],
    "wof:name":"Officine Metallurgiche G. Cornaglia S.p.a.",
    "wof:placetype":"venue"
},
  "geometry": {"coordinates":[7.686619,45.07056],"type":"Point"}
}