{
  "type": "Feature",
  "properties": {
    "addr:full":"20141 Milano Milano Milano 20141",
    "addr:postcode":"20141;20141",
    "iso:country":"IT",
    "sg:address":"20141 Milano",
    "sg:city":"Milano",
    "sg:orig_category":"Arte Ed Artigianato Artistico",
    "sg:phone":"+39 02 846 7433",
    "sg:postcode":"20141",
    "sg:province":"Milano",
    "wof:name":"Micozzi Maria",
    "wof:placetype":"venue"
},
  "geometry": {"coordinates":[9.199751,45.423962],"type":"Point"}
}