{
  "type": "Feature",
  "properties": {
    "iso:country":"IT",
    "sg:address":"41038 San Felice Sul Panaro",
    "sg:city":"San Felice sul Panaro",
    "sg:orig_category":"Forniture Per Attivita' Industriali",
    "sg:phone":"+39 0535 84323",
    "sg:postcode":"41038",
    "sg:province":"Modena",
    "wof:name":"Manfredini Cugini (s.n.c.)",
    "wof:placetype":"venue"
},
  "geometry": {"coordinates":[11.1516485214,44.8472747803],"type":"Point"}
}