{
  "type": "Feature",
  "properties": {
    "addr:full":"50144 Firenze Firenze Firenze 50144",
    "addr:postcode":"50144;50144",
    "iso:country":"IT",
    "sg:address":"50144 Firenze",
    "sg:city":"Firenze",
    "sg:orig_category":"Alberghi E Strutture Extra Alberghiere",
    "sg:phone":"+39 055 321 5114",
    "sg:postcode":"50144",
    "sg:province":"Firenze",
    "wof:name":"Soggiorno 'sogna Firenze' Di Soc. Luck",
    "wof:placetype":"venue"
},
  "geometry": {"coordinates":[11.238214,43.781242],"type":"Point"}
}