{
  "type": "Feature",
  "properties": {
    "iso:country":"IT",
    "sg:address":"11, Via Zanzi 48018 Faenza",
    "sg:city":"Faenza",
    "sg:classifiers":[
        {
            "category":"Shopping",
            "subcategory":"Clothing, Apparel, & Fashions",
            "type":"Retail Goods"
        }
    ],
    "sg:phone":"+39 39054641200",
    "sg:postcode":"48018",
    "sg:province":"Ravenna",
    "sg:tags":[
        "clothes"
    ],
    "wof:name":"Confezioni Cristina",
    "wof:placetype":"venue"
},
  "geometry": {"coordinates":[11.935046,44.386074],"type":"Point"}
}