{
  "type": "Feature",
  "properties": {
    "addr:full":"Via Dell' Artigianato 2 24060 Telgate Telgate Bergamo 24060",
    "addr:housenumber":"2",
    "addr:postcode":"24060;24060",
    "addr:street":"Via Dell ' Artigianato;Telgate",
    "iso:country":"IT",
    "sg:address":"Via Dell' Artigianato 2 24060 Telgate",
    "sg:city":"Telgate",
    "sg:classifiers":[
        {
            "category":"Home & Garden",
            "subcategory":"Furniture",
            "type":"Retail Goods"
        }
    ],
    "sg:phone":"+39 035 831010",
    "sg:postcode":"24060",
    "sg:province":"Bergamo",
    "sg:tags":[
        "solid",
        "children's",
        "made",
        "wood"
    ],
    "sg:website":"www.erlilegno.it",
    "wof:name":"Erli Legno Snc Di E. Erli & C",
    "wof:placetype":"venue"
},
  "geometry": {"coordinates":[9.837865,45.6301],"type":"Point"}
}