{
  "type": "Feature",
  "properties": {
    "iso:country":"IT",
    "sg:address":"121/i, Via Garibaldi G. 45019 Taglio Di Po",
    "sg:city":"Taglio di Po",
    "sg:classifiers":[
        {
            "category":"Shopping",
            "subcategory":"Clothing, Apparel, & Fashions",
            "type":"Retail Goods"
        }
    ],
    "sg:phone":"+39 0426 346505",
    "sg:postcode":"45019",
    "sg:province":"Rovigo",
    "sg:tags":[
        "clothes"
    ],
    "wof:name":"Confezioni Anthea",
    "wof:placetype":"venue"
},
  "geometry": {"coordinates":[11.789797,45.070736],"type":"Point"}
}