{
  "type": "Feature",
  "properties": {
    "iso:country":"IT",
    "sg:address":"00177 Roma",
    "sg:city":"Roma",
    "sg:orig_category":"Abbigliamento Esterno, Maglierie E Pelliccerie",
    "sg:phone":"+39 06 2180 0745",
    "sg:postcode":"00177",
    "sg:province":"Roma",
    "wof:name":"D'apostoli Gianni",
    "wof:placetype":"venue"
},
  "geometry": {"coordinates":[12.558962,41.895847],"type":"Point"}
}