{
  "type": "Feature",
  "properties": {
    "addr:full":"11, Via Delle Rose 36061 Bassano Del Grappa Bassano del Grappa Vicenza 36061",
    "addr:postcode":"36061;36061",
    "addr:street":"Via Delle Rose",
    "iso:country":"IT",
    "sg:address":"11, Via Delle Rose 36061 Bassano Del Grappa",
    "sg:city":"Bassano del Grappa",
    "sg:classifiers":[
        {
            "category":"Professional",
            "subcategory":"Engineering",
            "type":"Services"
        }
    ],
    "sg:phone":"+39 0424 566716",
    "sg:postcode":"36061",
    "sg:province":"Vicenza",
    "sg:tags":[
        "machine",
        "-",
        "mechanical"
    ],
    "wof:name":"C2 Di Cipriani Gian Battista & C. S.a.s.",
    "wof:placetype":"venue"
},
  "geometry": {"coordinates":[11.540307,45.545906],"type":"Point"}
}