{
  "type": "Feature",
  "properties": {
    "iso:country":"IT",
    "sg:address":"20136 Milano",
    "sg:city":"Milano",
    "sg:orig_category":"Servizi Ausiliari Dei Mezzi Di Trasporto",
    "sg:phone":"+39 02 8940 4605",
    "sg:postcode":"20136",
    "sg:province":"Milano",
    "wof:name":"Carrozzeria Rutilia Snc",
    "wof:placetype":"venue"
},
  "geometry": {"coordinates":[9.184147,45.449436],"type":"Point"}
}