{
  "type": "Feature",
  "properties": {
    "addr:full":"53031 Casole D'elsa Siena 53031",
    "addr:postcode":"53031;53031",
    "iso:country":"IT",
    "sg:address":"53031 Casole D'elsa",
    "sg:orig_category":"Mobilieri E Falegnami - Forniture",
    "sg:phone":"+39 0577 925030",
    "sg:postcode":"53031",
    "sg:province":"Siena",
    "wof:name":"Esse Tre Falegnameria Di Renzo Pacini & C. Snc",
    "wof:placetype":"venue"
},
  "geometry": {"coordinates":[11.0485486984,43.3129119873],"type":"Point"}
}