{
  "type": "Feature",
  "properties": {
    "iso:country":"IT",
    "sg:address":"22060 Carugo",
    "sg:city":"Carugo",
    "sg:orig_category":"Arte Ed Artigianato Artistico",
    "sg:phone":"+39 031 758279",
    "sg:postcode":"22060",
    "sg:province":"Como",
    "wof:name":"Alberti Emilio",
    "wof:placetype":"venue"
},
  "geometry": {"coordinates":[9.09196,45.799416],"type":"Point"}
}