{
  "type": "Feature",
  "properties": {
    "iso:country":"IT",
    "sg:address":"00197 Roma",
    "sg:city":"Roma",
    "sg:orig_category":"Arte Ed Artigianato Artistico. Scuole E Servizi Scolastici. Servizi Ausiliari Di Analisi, Controllo E Ricerca",
    "sg:phone":"+39 06 322 2717",
    "sg:postcode":"00197",
    "sg:province":"Roma",
    "wof:name":"Accademia Di Danimarca",
    "wof:placetype":"venue"
},
  "geometry": {"coordinates":[12.478734,41.916866],"type":"Point"}
}