{
  "type": "Feature",
  "properties": {
    "addr:full":"41, Strada Del Confine 36056 Tezze Sul Brenta Tezze sul Brenta Vicenza 36056",
    "addr:postcode":"36056;36056",
    "addr:street":"Strada Del Confine",
    "iso:country":"IT",
    "sg:address":"41, Strada Del Confine 36056 Tezze Sul Brenta",
    "sg:city":"Tezze sul Brenta",
    "sg:classifiers":[
        {
            "category":"Wholesale",
            "subcategory":"Drugs",
            "type":"Manufacturing & Wholesale Goods"
        }
    ],
    "sg:phone":"+39 0424 540883",
    "sg:postcode":"36056",
    "sg:province":"Vicenza",
    "sg:tags":[
        "chemical",
        "pharmaceutical"
    ],
    "wof:name":"Ecopolifix (s.r.l.)",
    "wof:placetype":"venue"
},
  "geometry": {"coordinates":[11.791239,45.691868],"type":"Point"}
}