{
  "type": "Feature",
  "properties": {
    "iso:country":"IT",
    "sg:address":"70123 Bari",
    "sg:city":"Bari",
    "sg:orig_category":"Moduli Continui E Modulistica",
    "sg:phone":"+39 080 531 2955",
    "sg:postcode":"70123",
    "sg:province":"Bari",
    "wof:name":"Italgrafica Sud Srl",
    "wof:placetype":"venue"
},
  "geometry": {"coordinates":[16.8126907349,41.120174408],"type":"Point"}
}