{
  "type": "Feature",
  "properties": {
    "iso:country":"IT",
    "sg:address":"50142 Firenze",
    "sg:city":"Firenze",
    "sg:orig_category":"Antifurto",
    "sg:phone":"+39 055 711617",
    "sg:postcode":"50142",
    "sg:province":"Firenze",
    "wof:name":"Alfatron Snc",
    "wof:placetype":"venue"
},
  "geometry": {"coordinates":[11.219133,43.773705],"type":"Point"}
}