{
  "type": "Feature",
  "properties": {
    "addr:full":"17, Via S. Anna 28881 Casale Corte Cerro Casale Corte Cerro Verbano-Cusio-Ossola 28881",
    "addr:postcode":"28881;28881",
    "addr:street":"Via S. Anna;Corte Cerro Casale Corte Cerro Verbano-Cusio-Ossola",
    "iso:country":"IT",
    "sg:address":"17, Via S. Anna 28881 Casale Corte Cerro",
    "sg:city":"Casale Corte Cerro",
    "sg:classifiers":[
        {
            "category":"Food & Beverages",
            "subcategory":"Groceries & Convenience Stores",
            "type":"Retail Goods"
        }
    ],
    "sg:phone":"+39 39032362575",
    "sg:postcode":"28881",
    "sg:province":"Verbano-Cusio-Ossola",
    "sg:tags":[
        "product",
        "related"
    ],
    "wof:name":"Galli Nino Salumificio (s.p.a.)",
    "wof:placetype":"venue"
},
  "geometry": {"coordinates":[8.2724647522,46.1399688721],"type":"Point"}
}