{
  "type": "Feature",
  "properties": {
    "addr:full":"55012 Capannori Capannori Lucca 55012",
    "addr:postcode":"55012;55012",
    "iso:country":"IT",
    "sg:address":"55012 Capannori",
    "sg:city":"Capannori",
    "sg:orig_category":"Depuratori E Depuranti",
    "sg:phone":"+39 0583 947068",
    "sg:postcode":"55012",
    "sg:province":"Lucca",
    "sg:website":"http://www.ecotoscana2000.it",
    "wof:name":"Ecotoscana 2000 Costruzioni Srl",
    "wof:placetype":"venue"
},
  "geometry": {"coordinates":[10.4987897873,43.8098754883],"type":"Point"}
}