{
  "type": "Feature",
  "properties": {
    "addr:full":"00142 Roma Roma Roma 00142",
    "addr:postcode":"00142;00142",
    "iso:country":"IT",
    "sg:address":"00142 Roma",
    "sg:city":"Roma",
    "sg:orig_category":"Scuole E Servizi Scolastici",
    "sg:phone":"+39 06 503 2382",
    "sg:postcode":"00142",
    "sg:province":"Roma",
    "wof:name":"Istituto Suore Di Nevers",
    "wof:placetype":"venue"
},
  "geometry": {"coordinates":[12.480369,41.830017],"type":"Point"}
}