{
  "type": "Feature",
  "properties": {
    "iso:country":"IT",
    "sg:address":"10042 Nichelino",
    "sg:city":"Nichelino",
    "sg:orig_category":"Studi E Consulenze Tecniche E Industriali. Servizi E Lavori Per Edilizia E Lavori Pubblici. Professionisti - Studi E Servizi Ed Associazioni Di Interesse Aziendale",
    "sg:phone":"+39 011 627 5106",
    "sg:postcode":"10042",
    "sg:province":"Torino",
    "wof:name":"Auno Security Srl",
    "wof:placetype":"venue"
},
  "geometry": {"coordinates":[7.64216,44.975452],"type":"Point"}
}