{
  "type": "Feature",
  "properties": {
    "iso:country":"IT",
    "sg:address":"21100 Varese",
    "sg:city":"Varese",
    "sg:orig_category":"Arredamenti E Mobili Professionali. Apparecchi, Attrezzature E Forniture Per Centri Estetici. Arredi Ed Attrezzature Per Attivita' Commerciali Ed Artigianali",
    "sg:phone":"+39 0332 286641",
    "sg:postcode":"21100",
    "sg:province":"Varese",
    "wof:name":"V2 Cosmetici Snc Di Vida Gianluigi & Raffaella",
    "wof:placetype":"venue"
},
  "geometry": {"coordinates":[8.831484,45.821419],"type":"Point"}
}