{
  "type": "Feature",
  "properties": {
    "iso:country":"IT",
    "sg:address":"25125 Brescia",
    "sg:city":"Brescia",
    "sg:orig_category":"Macchine, Impianti E Forniture Per Industria Grafica, Cartaria E Cartotecnica. Automazione E Macchine Per Ufficio",
    "sg:phone":"+39 030 353 4431",
    "sg:postcode":"25125",
    "sg:province":"Brescia",
    "sg:website":"http://www.progetto6.it",
    "wof:name":"Progetto 6 Srl",
    "wof:placetype":"venue"
},
  "geometry": {"coordinates":[10.180352,45.532616],"type":"Point"}
}