{
  "type": "Feature",
  "properties": {
    "iso:country":"IT",
    "sg:address":"Piazza F. Torre, 83; Benevento; 82100",
    "sg:city":"Benevento",
    "sg:classifiers":[
        {
            "category":"Banks & Credit Unions",
            "subcategory":"Bank",
            "type":"Services"
        }
    ],
    "sg:phone":"+39 0824 21566",
    "sg:postcode":"82100",
    "sg:province":"Benevento",
    "wof:name":"Banco Di Santo Spirito",
    "wof:placetype":"venue"
},
  "geometry": {"coordinates":[14.77892,41.130856],"type":"Point"}
}