{
  "type": "Feature",
  "properties": {
    "addr:full":"5, Via Dei Mille 40121 Bologna Bologna Bologna 40121",
    "addr:postcode":"40121;40121",
    "addr:street":"Via Dei Mille",
    "iso:country":"IT",
    "sg:address":"5, Via Dei Mille 40121 Bologna",
    "sg:city":"Bologna",
    "sg:classifiers":[
        {
            "category":"Shopping",
            "subcategory":"Stationery & Office Supplies",
            "type":"Retail Goods"
        }
    ],
    "sg:phone":"+39 39051240527",
    "sg:postcode":"40121",
    "sg:province":"Bologna",
    "sg:tags":[
        "professional"
    ],
    "wof:name":"Marabini - Baiocchi S.r.l.",
    "wof:placetype":"venue"
},
  "geometry": {"coordinates":[11.34375,44.5013542175],"type":"Point"}
}