{
  "type": "Feature",
  "properties": {
    "addr:full":"38, Via Piave 35030 Selvazzano Dentro Selvazzano Dentro Padova 35030",
    "addr:postcode":"35030;35030",
    "addr:street":"Via Piave",
    "iso:country":"IT",
    "sg:address":"38, Via Piave 35030 Selvazzano Dentro",
    "sg:city":"Selvazzano Dentro",
    "sg:classifiers":[
        {
            "category":"Manufacturing",
            "subcategory":"Metals",
            "type":"Manufacturing & Wholesale Goods"
        }
    ],
    "sg:phone":"+39 049 868 6310",
    "sg:postcode":"35030",
    "sg:province":"Padova",
    "sg:tags":[
        "processing"
    ],
    "wof:name":"Olri (s.r.l.)",
    "wof:placetype":"venue"
},
  "geometry": {"coordinates":[11.8051624298,45.3929138184],"type":"Point"}
}