{
  "type": "Feature",
  "properties": {
    "iso:country":"IT",
    "sg:address":"10141 Torino",
    "sg:city":"Torino",
    "sg:orig_category":"Prodotti Di Base E Forniture Per Industria Alimentare E Bevande. Forniture E Materiali Per Imballaggio E Confezionamento",
    "sg:phone":"+39 011 385 1038",
    "sg:postcode":"10141",
    "sg:province":"Torino",
    "wof:name":"Antoniotto Livio",
    "wof:placetype":"venue"
},
  "geometry": {"coordinates":[7.6465616226,45.0578689575],"type":"Point"}
}