{
  "type": "Feature",
  "properties": {
    "addr:full":"4/b, Via Valle Po 12030 Sanfront Sanfront Cuneo 12030",
    "addr:housenumber":"4 / b",
    "addr:postcode":"12030;12030",
    "addr:street":"Via Valle Po",
    "iso:country":"IT",
    "sg:address":"4/b, Via Valle Po 12030 Sanfront",
    "sg:city":"Sanfront",
    "sg:classifiers":[
        {
            "category":"Manufacturing",
            "subcategory":"Wood Products",
            "type":"Manufacturing & Wholesale Goods"
        }
    ],
    "sg:phone":"+39 0175 948769",
    "sg:postcode":"12030",
    "sg:province":"Cuneo",
    "sg:tags":[
        "furniture"
    ],
    "wof:name":"Falegnameria Boassi Sas Di Boassi Adelchi E C.",
    "wof:placetype":"venue"
},
  "geometry": {"coordinates":[7.547111,44.388798],"type":"Point"}
}