{
  "type": "Feature",
  "properties": {
    "iso:country":"IT",
    "sg:address":"26010 Offanengo",
    "sg:city":"Offanengo",
    "sg:orig_category":"Caldaie - Produzione E Commercio",
    "sg:phone":"+39 0373 780113",
    "sg:postcode":"26010",
    "sg:province":"Cremona",
    "wof:name":"Gruptherm",
    "wof:placetype":"venue"
},
  "geometry": {"coordinates":[9.743834,45.376236],"type":"Point"}
}