{
  "type": "Feature",
  "properties": {
    "iso:country":"IT",
    "sg:address":"20148 Milano",
    "sg:city":"Milano",
    "sg:orig_category":"Macchine, Impianti Ed Attrezzature Industria Delle Materie Plastiche E Gomma",
    "sg:phone":"+39 02 4800 8635",
    "sg:postcode":"20148",
    "sg:province":"Milano",
    "wof:name":"Ram (s.r.l.)",
    "wof:placetype":"venue"
},
  "geometry": {"coordinates":[9.147597,45.479866],"type":"Point"}
}