{
  "type": "Feature",
  "properties": {
    "iso:country":"IT",
    "sg:address":"17047 Vado Ligure",
    "sg:city":"Vado Ligure",
    "sg:orig_category":"Trasporti E Spedizioni Merci",
    "sg:phone":"+39 019 216 0160",
    "sg:postcode":"17047",
    "sg:province":"Savona",
    "wof:name":"Salino Spedizioni Di Salino Tomaso Sas",
    "wof:placetype":"venue"
},
  "geometry": {"coordinates":[8.443275,44.280724],"type":"Point"}
}