{
  "type": "Feature",
  "properties": {
    "iso:country":"IT",
    "sg:address":"80125 Napoli",
    "sg:city":"Napoli",
    "sg:orig_category":"Materiali E Componenti Elettronici",
    "sg:phone":"+39 081 593 0006",
    "sg:postcode":"80125",
    "sg:province":"Napoli",
    "sg:website":"http://www.aepsrl.it",
    "wof:name":"A.e.p. Srl",
    "wof:placetype":"venue"
},
  "geometry": {"coordinates":[14.181599,40.842457],"type":"Point"}
}