{
  "type": "Feature",
  "properties": {
    "iso:country":"IT",
    "sg:address":"63017 Porto San Giorgio",
    "sg:city":"Porto San Giorgio",
    "sg:orig_category":"Forniture Per Attivita' Commerciali Ed Artigianali",
    "sg:phone":"+39 0734 676210",
    "sg:postcode":"63017",
    "sg:province":"Ascoli Piceno",
    "wof:name":"Forgia' Povelio & C. S.n.c.",
    "wof:placetype":"venue"
},
  "geometry": {"coordinates":[13.7888660431,43.1881523132],"type":"Point"}
}