{
  "type": "Feature",
  "properties": {
    "addr:full":"64, Via Cadelsette 37041 Albaredo D'adige Verona 37041",
    "addr:postcode":"37041;37041",
    "addr:street":"Via Cadelsette",
    "iso:country":"IT",
    "sg:address":"64, Via Cadelsette 37041 Albaredo D'adige",
    "sg:classifiers":[
        {
            "category":"Farming",
            "subcategory":"Livestock Farm",
            "type":"Manufacturing & Wholesale Goods"
        }
    ],
    "sg:phone":"+39 045 700 1698",
    "sg:postcode":"37041",
    "sg:province":"Verona",
    "sg:tags":[
        "agriculture"
    ],
    "wof:name":"Bissolo Gabriele S.r.l.",
    "wof:placetype":"venue"
},
  "geometry": {"coordinates":[11.308769,45.307186],"type":"Point"}
}