{
  "type": "Feature",
  "properties": {
    "iso:country":"IT",
    "sg:address":"44030 Ro Ferrarese",
    "sg:city":"Ro",
    "sg:orig_category":"Automobili E Mezzi Di Trasporto",
    "sg:phone":"+39 0532 869903",
    "sg:postcode":"44030",
    "sg:province":"Ferrara",
    "wof:name":"Errepi Auto Di Piva Donatella",
    "wof:placetype":"venue"
},
  "geometry": {"coordinates":[11.742623,44.911167],"type":"Point"}
}