{
  "type": "Feature",
  "properties": {
    "addr:full":"91025 Marsala Marsala Trapani 91025",
    "addr:postcode":"91025;91025",
    "iso:country":"IT",
    "sg:address":"91025 Marsala",
    "sg:city":"Marsala",
    "sg:orig_category":"Agricoltura, Orticoltura E Floricoltura. Articoli Da Regalo. Shopping",
    "sg:phone":"+39 0923 952100",
    "sg:postcode":"91025",
    "sg:province":"Trapani",
    "wof:name":"Casa Del Lilium Di Ragona Antonio & C. Snc",
    "wof:placetype":"venue"
},
  "geometry": {"coordinates":[12.512542,38.017872],"type":"Point"}
}