{
  "type": "Feature",
  "properties": {
    "addr:full":"Via Nettunense Km 13 00040 Ariccia Ariccia Roma 00040",
    "addr:postcode":"00040;roma 00040",
    "addr:street":"Via Nettunense Km 13",
    "iso:country":"IT",
    "sg:address":"Via Nettunense Km 13 00040 Ariccia",
    "sg:city":"Ariccia",
    "sg:classifiers":[
        {
            "category":"Transit Center",
            "subcategory":"Freight",
            "type":"Transportation"
        }
    ],
    "sg:phone":"+39 06 937 4015",
    "sg:postcode":"00040",
    "sg:province":"Roma",
    "sg:tags":[
        "high",
        "lift",
        "truck"
    ],
    "sg:website":"www.sibicar.com",
    "wof:name":"Sibicar Spa",
    "wof:placetype":"venue"
},
  "geometry": {"coordinates":[12.482325,41.895466],"type":"Point"}
}