{
  "type": "Feature",
  "properties": {
    "iso:country":"IT",
    "sg:address":"21041 Albizzate",
    "sg:city":"Albizzate",
    "sg:orig_category":"Calzature, Pelletterie E Pelli",
    "sg:phone":"+39 0331 993491",
    "sg:postcode":"21041",
    "sg:province":"Varese",
    "wof:name":"Bolzoni Enea & C. Snc",
    "wof:placetype":"venue"
},
  "geometry": {"coordinates":[8.826486,45.770313],"type":"Point"}
}