{
  "type": "Feature",
  "properties": {
    "addr:full":"17041 Altare Altare Savona 17041",
    "addr:postcode":"17041;17041",
    "iso:country":"IT",
    "sg:address":"17041 Altare",
    "sg:city":"Altare",
    "sg:orig_category":"Bevande, Vini E Liquori",
    "sg:phone":"+39 019 58256",
    "sg:postcode":"17041",
    "sg:province":"Savona",
    "wof:name":"Terme Vallechiara Spa",
    "wof:placetype":"venue"
},
  "geometry": {"coordinates":[8.332204,44.32737],"type":"Point"}
}