{
  "type": "Feature",
  "properties": {
    "addr:full":"272/1, Via Ripamonti Giuseppe 20141 Milano Milano Milano 20141",
    "addr:housenumber":"272 / 1",
    "addr:postcode":"20141;20141",
    "addr:street":"Via Ripamonti Giuseppe",
    "iso:country":"IT",
    "sg:address":"272/1, Via Ripamonti Giuseppe 20141 Milano",
    "sg:city":"Milano",
    "sg:classifiers":[
        {
            "category":"Professional",
            "subcategory":"Advertising",
            "type":"Services"
        }
    ],
    "sg:phone":"+39 39025398026",
    "sg:postcode":"20141",
    "sg:province":"Milano",
    "sg:tags":[
        "communication",
        "medium"
    ],
    "wof:name":"Multidirect (s.r.l.)",
    "wof:placetype":"venue"
},
  "geometry": {"coordinates":[9.196584,45.451805],"type":"Point"}
}