{
  "type": "Feature",
  "properties": {
    "iso:country":"IT",
    "sg:address":"41049 Sassuolo",
    "sg:city":"Sassuolo",
    "sg:orig_category":"Ceramiche E Refrattari - Impianti, Macchine E Materiali",
    "sg:phone":"+39 0536 801353",
    "sg:postcode":"41049",
    "sg:province":"Modena",
    "wof:name":"Omis Spa",
    "wof:placetype":"venue"
},
  "geometry": {"coordinates":[10.841758,44.586933],"type":"Point"}
}