{
  "type": "Feature",
  "properties": {
    "addr:full":"9, Via Dell' Industria 35044 Montagnana Montagnana Padova 35044",
    "addr:postcode":"35044;35044",
    "addr:street":"Via Dell ' Industria",
    "iso:country":"IT",
    "sg:address":"9, Via Dell' Industria 35044 Montagnana",
    "sg:city":"Montagnana",
    "sg:classifiers":[
        {
            "category":"Shopping",
            "subcategory":"Clothing, Apparel, & Fashions",
            "type":"Retail Goods"
        }
    ],
    "sg:phone":"+39 39042981588",
    "sg:postcode":"35044",
    "sg:province":"Padova",
    "sg:tags":[
        "clothes"
    ],
    "wof:name":"Maglificio Fibo Di Filippi & Bortolini (s.n.c.)",
    "wof:placetype":"venue"
},
  "geometry": {"coordinates":[11.496565,45.225185],"type":"Point"}
}