{
  "type": "Feature",
  "properties": {
    "addr:full":"24060 Grone Grone Bergamo 24060",
    "addr:postcode":"24060;24060",
    "iso:country":"IT",
    "sg:address":"24060 Grone",
    "sg:city":"Grone",
    "sg:orig_category":"Prodotti Alimentari. Agricoltura, Orticoltura E Floricoltura",
    "sg:phone":"+39 035 820450",
    "sg:postcode":"24060",
    "sg:province":"Bergamo",
    "wof:name":"Azienda Agricola Silverfunghi (s.a.s.)",
    "wof:placetype":"venue"
},
  "geometry": {"coordinates":[9.8971624374,45.7187995911],"type":"Point"}
}