{
  "type": "Feature",
  "properties": {
    "addr:full":"20143 Milano Milano Milano 20143",
    "addr:postcode":"20143;20143",
    "iso:country":"IT",
    "sg:address":"20143 Milano",
    "sg:city":"Milano",
    "sg:orig_category":"Apparecchiature Ed Attrezzature Meccaniche. Elettronica Industriale, Prodotti E Apparecchiature",
    "sg:phone":"+39 02 833001",
    "sg:postcode":"20143",
    "sg:province":"Milano",
    "sg:website":"http://www.slb.com/rms/italy",
    "wof:name":"Schlumberger Industries Spa",
    "wof:placetype":"venue"
},
  "geometry": {"coordinates":[9.161645,45.444218],"type":"Point"}
}