{
  "type": "Feature",
  "properties": {
    "iso:country":"IT",
    "sg:address":"12061 Carru'",
    "sg:orig_category":"Macchine, Impianti Ed Attrezzature Per Industria Alimentare E Bevande",
    "sg:phone":"+39 0173 75232",
    "sg:postcode":"12061",
    "sg:province":"Cuneo",
    "wof:name":"Fea Renato",
    "wof:placetype":"venue"
},
  "geometry": {"coordinates":[7.861277,44.477043],"type":"Point"}
}