{
  "type": "Feature",
  "properties": {
    "addr:full":"40026 Imola Imola Bologna 40026",
    "addr:postcode":"40026;40026",
    "iso:country":"IT",
    "sg:address":"40026 Imola",
    "sg:city":"Imola",
    "sg:classifiers":[
        {
            "category":"Travel",
            "subcategory":"Travel Agent",
            "type":"Entertainment"
        }
    ],
    "sg:phone":"+39 0542 22190",
    "sg:postcode":"40026",
    "sg:province":"Bologna",
    "sg:tags":[
        "operator",
        "tour",
        "tourist"
    ],
    "wof:name":"Libreria Di Palazzo Monsignani Srl",
    "wof:placetype":"venue"
},
  "geometry": {"coordinates":[11.750096,44.27681],"type":"Point"}
}