{
  "type": "Feature",
  "properties": {
    "iso:country":"IT",
    "sg:address":"25/a, Via Lanzarini 36060 Romano D'ezzelino",
    "sg:classifiers":[
        {
            "category":"Professional",
            "subcategory":"Printing & Photocopies",
            "type":"Services"
        }
    ],
    "sg:phone":"+39 0424 574285",
    "sg:postcode":"36060",
    "sg:province":"Vicenza",
    "wof:name":"Laboratorio Grafico Bst (s.n.c.)",
    "wof:placetype":"venue"
},
  "geometry": {"coordinates":[11.540307045,45.5459060669],"type":"Point"}
}