{
  "type": "Feature",
  "properties": {
    "addr:full":"30027 San Don\u00e0 Di Piave Venezia 30027",
    "addr:housenumber":"30027",
    "addr:postcode":"30027",
    "iso:country":"IT",
    "sg:address":"30027 San Don\u00e0 Di Piave",
    "sg:orig_category":"Prodotti Chimici Secondari. Macchine E Forniture Per Ecologia E Smaltimento Rifiuti. Forniture Per Attivita' Industriali",
    "sg:phone":"+39 0421 220000",
    "sg:postcode":"30027",
    "sg:province":"Venezia",
    "sg:website":"http://www.sovla.it",
    "wof:name":"Sovla Srl",
    "wof:placetype":"venue"
},
  "geometry": {"coordinates":[12.5935106277,45.6364631653],"type":"Point"}
}