{
  "type": "Feature",
  "properties": {
    "iso:country":"IT",
    "sg:address":"14100 Asti",
    "sg:city":"Asti",
    "sg:orig_category":"Idrosanitari - Commercio",
    "sg:phone":"+39 0141 271633",
    "sg:postcode":"14100",
    "sg:province":"Asti",
    "wof:name":"M.p Mondino Srl",
    "wof:placetype":"venue"
},
  "geometry": {"coordinates":[8.23172,44.903477],"type":"Point"}
}