{
  "type": "Feature",
  "properties": {
    "addr:full":"55012 Capannori Capannori Lucca 55012",
    "addr:postcode":"55012;55012",
    "iso:country":"IT",
    "sg:address":"55012 Capannori",
    "sg:city":"Capannori",
    "sg:orig_category":"Oli Alimentari E Frantoi Oleari",
    "sg:phone":"+39 0583 403400",
    "sg:postcode":"55012",
    "sg:province":"Lucca",
    "wof:name":"Oleificio Frediani & Del Greco Spa",
    "wof:placetype":"venue"
},
  "geometry": {"coordinates":[10.585878,43.841606],"type":"Point"}
}