{
  "type": "Feature",
  "properties": {
    "iso:country":"IT",
    "sg:address":"11/19, Via Semeghini Pio 00155 Roma",
    "sg:city":"Roma",
    "sg:classifiers":[
        {
            "category":"Manufacturing",
            "subcategory":"Rubber & Plastics",
            "type":"Manufacturing & Wholesale Goods"
        }
    ],
    "sg:phone":"+39 39062280686",
    "sg:postcode":"00155",
    "sg:province":"Roma",
    "wof:name":"Luzi Angelo Di Luzi Luigi & C. S.n.c.",
    "wof:placetype":"venue"
},
  "geometry": {"coordinates":[12.4823246002,41.8954658508],"type":"Point"}
}