{
  "type": "Feature",
  "properties": {
    "iso:country":"IT",
    "sg:address":"Frazione Glocchi; Trambileno; 38068",
    "sg:city":"Trambileno",
    "sg:classifiers":[
        {
            "category":"Banks & Credit Unions",
            "subcategory":"Bank",
            "type":"Services"
        }
    ],
    "sg:phone":"+39 0464 88050",
    "sg:postcode":"38068",
    "sg:province":"Trento",
    "wof:name":"Cassa Rurale Di Rovereto",
    "wof:placetype":"venue"
},
  "geometry": {"coordinates":[11.073851,45.866699],"type":"Point"}
}