{
  "type": "Feature",
  "properties": {
    "addr:full":"95047 Patern\u00f2 Catania 95047",
    "addr:postcode":"95047;95047",
    "iso:country":"IT",
    "sg:address":"95047 Patern\u00f2",
    "sg:orig_category":"Lavorazioni Meccaniche E Servizi. Servizi Per Imballaggio E Confezionamento",
    "sg:phone":"+39 095 621434",
    "sg:postcode":"95047",
    "sg:province":"Catania",
    "wof:name":"Jacket Srl",
    "wof:placetype":"venue"
},
  "geometry": {"coordinates":[14.905545,37.567799],"type":"Point"}
}