{
  "type": "Feature",
  "properties": {
    "iso:country":"IT",
    "sg:address":"00015 Monterotondo",
    "sg:city":"Monterotondo",
    "sg:orig_category":"Automazione E Macchine Per Ufficio. Servizi Ausiliari Di Certificati, Riproduzioni, Disegni E Foto",
    "sg:phone":"+39 06 9008 5413",
    "sg:postcode":"00015",
    "sg:province":"Roma",
    "wof:name":"Bucap Srl",
    "wof:placetype":"venue"
},
  "geometry": {"coordinates":[12.601184,42.085663],"type":"Point"}
}