{
  "type": "Feature",
  "properties": {
    "addr:full":"38, Via Diaz 23845 Costa Masnaga Costa Masnaga Lecco 23845",
    "addr:postcode":"23845;masnaga;23845",
    "addr:street":"Via Diaz",
    "iso:country":"IT",
    "sg:address":"38, Via Diaz 23845 Costa Masnaga",
    "sg:city":"Costa Masnaga",
    "sg:classifiers":[
        {
            "category":"Shopping",
            "subcategory":"Crafts & Fabrics",
            "type":"Retail Goods"
        }
    ],
    "sg:phone":"+39 39031855061",
    "sg:postcode":"23845",
    "sg:province":"Lecco",
    "wof:name":"Brenna Edoardo S.r.l.",
    "wof:placetype":"venue"
},
  "geometry": {"coordinates":[9.3900709152,45.8529815674],"type":"Point"}
}