{
  "type": "Feature",
  "properties": {
    "addr:full":"68, Via Brescia 24064 Grumello Del Monte Grumello del Monte Bergamo 24064",
    "addr:postcode":"24064;24064",
    "addr:street":"Via Brescia",
    "iso:country":"IT",
    "sg:address":"68, Via Brescia 24064 Grumello Del Monte",
    "sg:city":"Grumello del Monte",
    "sg:classifiers":[
        {
            "category":"Shopping",
            "subcategory":"Gifts & Souvenirs",
            "type":"Retail Goods"
        }
    ],
    "sg:phone":"+39 39035832662",
    "sg:postcode":"24064",
    "sg:province":"Bergamo",
    "wof:name":"Frase S.r.l.",
    "wof:placetype":"venue"
},
  "geometry": {"coordinates":[9.614247,45.640415],"type":"Point"}
}