{
  "type": "Feature",
  "properties": {
    "iso:country":"IT",
    "sg:address":"20099 Sesto San Giovanni",
    "sg:city":"Sesto San Giovanni",
    "sg:orig_category":"Porte",
    "sg:phone":"+39 02 240 1046",
    "sg:postcode":"20099",
    "sg:province":"Milano",
    "sg:website":"http://www.vailationline.it",
    "wof:name":"Vailati Ivan Roberto",
    "wof:placetype":"venue"
},
  "geometry": {"coordinates":[9.2425832748,45.5386276245],"type":"Point"}
}