{
  "type": "Feature",
  "properties": {
    "addr:full":"65010 Spoltore Spoltore Pescara 65010",
    "addr:postcode":"65010;65010",
    "iso:country":"IT",
    "sg:address":"65010 Spoltore",
    "sg:city":"Spoltore",
    "sg:orig_category":"Pompe. Ricambi E Componenti Dei Mezzi Di Trasporto",
    "sg:phone":"+39 085 411290",
    "sg:postcode":"65010",
    "sg:province":"Pescara",
    "wof:name":"Officina Europa Di Troiano & Bellaspica & C. Snc",
    "wof:placetype":"venue"
},
  "geometry": {"coordinates":[14.1818580627,42.4489402771],"type":"Point"}
}