{
  "type": "Feature",
  "properties": {
    "iso:country":"IT",
    "sg:address":"00186 Roma",
    "sg:city":"Roma",
    "sg:orig_category":"Zootecnia E Pesca, Allevamento Piccoli Animali",
    "sg:phone":"+39 0649661",
    "sg:postcode":"00186",
    "sg:province":"Roma",
    "wof:name":"Unione Nazionale Incremento Razze Equine",
    "wof:placetype":"venue"
},
  "geometry": {"coordinates":[12.475321,41.896603],"type":"Point"}
}