{
  "type": "Feature",
  "properties": {
    "iso:country":"IT",
    "sg:address":"00044 Frascati",
    "sg:city":"Frascati",
    "sg:classifiers":[
        {
            "category":"Health Services",
            "subcategory":"Health Practitioner",
            "type":"Services"
        }
    ],
    "sg:phone":"+39 06 942 4845",
    "sg:postcode":"00044",
    "sg:province":"Roma",
    "sg:tags":[
        "medici"
    ],
    "wof:name":"Diaferia Carlo",
    "wof:placetype":"venue"
},
  "geometry": {"coordinates":[12.673301,41.823296],"type":"Point"}
}