{
  "type": "Feature",
  "properties": {
    "iso:country":"IT",
    "sg:address":"37036 San Martino Buon Albergo",
    "sg:city":"San Martino Buon Albergo",
    "sg:orig_category":"Casseforti E Armadi Blindati",
    "sg:phone":"+39 045 992402",
    "sg:postcode":"37036",
    "sg:province":"Verona",
    "sg:website":"http://www.madinelli.it",
    "wof:name":"Madinelli Srl",
    "wof:placetype":"venue"
},
  "geometry": {"coordinates":[11.110388,45.42004],"type":"Point"}
}