{
  "type": "Feature",
  "properties": {
    "iso:country":"IT",
    "sg:address":"10095 Grugliasco",
    "sg:city":"Grugliasco",
    "sg:orig_category":"Servizi Al Turismo. Trasporto Pubblico E Privato",
    "sg:phone":"+39 011 300 0605",
    "sg:postcode":"10095",
    "sg:province":"Torino",
    "sg:website":"http://www.sadem.it",
    "wof:name":"Sadem Spa",
    "wof:placetype":"venue"
},
  "geometry": {"coordinates":[7.609292,45.034855],"type":"Point"}
}