{
  "type": "Feature",
  "properties": {
    "addr:full":"41100 Modena Modena Modena 41100",
    "addr:postcode":"41100;41100",
    "iso:country":"IT",
    "sg:address":"41100 Modena",
    "sg:city":"Modena",
    "sg:orig_category":"Apparecchiature Ed Attrezzature Meccaniche",
    "sg:phone":"+39 059 252331",
    "sg:postcode":"41100",
    "sg:province":"Modena",
    "sg:website":"http://www.itkitalkrome.com",
    "wof:name":"Italkrome Srl",
    "wof:placetype":"venue"
},
  "geometry": {"coordinates":[10.960762,44.65617],"type":"Point"}
}