{
  "type": "Feature",
  "properties": {
    "iso:country":"IT",
    "sg:address":"55100 Lucca",
    "sg:city":"Lucca",
    "sg:orig_category":"Antinfortunistica - Attrezzature Ed Articoli",
    "sg:phone":"+39 0583 983131",
    "sg:postcode":"55100",
    "sg:province":"Lucca",
    "sg:website":"http://www.tcfactory.it",
    "wof:name":"T & C Factoring Di Barbacci Daniele",
    "wof:placetype":"venue"
},
  "geometry": {"coordinates":[10.54965,43.837326],"type":"Point"}
}