{
  "type": "Feature",
  "properties": {
    "iso:country":"IT",
    "sg:address":"Via Crescenzo Del Monte 25/45, 00153 Rome, Rm",
    "sg:classifiers":[
        {
            "category":"Banks & Credit Unions",
            "subcategory":"Bank",
            "type":"Services"
        }
    ],
    "sg:postcode":"00153",
    "sg:province":"Roma",
    "wof:name":"Artigiancassa-cassa Per Il Credito Alle Imprese Artigiane Spa",
    "wof:placetype":"venue"
},
  "geometry": {"coordinates":[12.46669,41.874405],"type":"Point"}
}