{
  "type": "Feature",
  "properties": {
    "addr:full":"15040 Valle San Bartolomeo Valle San Bartolomeo Alessandria 15040",
    "addr:housenumber":"15040",
    "addr:postcode":"15040",
    "addr:street":"Valle San;Valle",
    "iso:country":"IT",
    "sg:address":"15040 Valle San Bartolomeo",
    "sg:city":"Valle San Bartolomeo",
    "sg:orig_category":"Ospedali E Servizi Sanitari",
    "sg:phone":"+39 0131 59234",
    "sg:postcode":"15040",
    "sg:province":"Alessandria",
    "wof:name":"Zuccotti Capuano Carla",
    "wof:placetype":"venue"
},
  "geometry": {"coordinates":[8.650095,44.954845],"type":"Point"}
}