{
  "type": "Feature",
  "properties": {
    "iso:country":"IT",
    "sg:address":"33044 Manzano",
    "sg:city":"Manzano",
    "sg:orig_category":"Minuterie Metalliche E Ferramenta",
    "sg:phone":"+39 0432 750130",
    "sg:postcode":"33044",
    "sg:province":"Udine",
    "sg:website":"http://www.mmpspa.it",
    "wof:name":"Magazzini Manzanesi Spa",
    "wof:placetype":"venue"
},
  "geometry": {"coordinates":[13.3990268707,45.9870986938],"type":"Point"}
}