{
  "type": "Feature",
  "properties": {
    "addr:full":"Viale Matteotti 31-33; Grosseto; 58100 Grosseto Grosseto 58100",
    "addr:housenumber":"31-33",
    "addr:postcode":"58100;58100",
    "addr:street":"Viale Matteotti",
    "iso:country":"IT",
    "sg:address":"Viale Matteotti 31-33; Grosseto; 58100",
    "sg:city":"Grosseto",
    "sg:classifiers":[
        {
            "category":"Banks & Credit Unions",
            "subcategory":"Bank",
            "type":"Services"
        }
    ],
    "sg:phone":"+39 0564 414193",
    "sg:postcode":"58100",
    "sg:province":"Grosseto",
    "wof:name":"Credito Italiano Spa",
    "wof:placetype":"venue"
},
  "geometry": {"coordinates":[11.110166,42.764282],"type":"Point"}
}