{
  "type": "Feature",
  "properties": {
    "iso:country":"IT",
    "sg:address":"Via Monte Zebio 07020 Palau",
    "sg:city":"Palau",
    "sg:classifiers":[
        {
            "category":"Travel",
            "subcategory":"Travel Agent",
            "type":"Entertainment"
        }
    ],
    "sg:phone":"+39 0789 708468",
    "sg:postcode":"07020",
    "sg:province":"Olbia-Tempio",
    "sg:tags":[
        "business"
    ],
    "wof:name":"Hotel Palau Srl",
    "wof:placetype":"venue"
},
  "geometry": {"coordinates":[9.376289,41.177296],"type":"Point"}
}