{
  "type": "Feature",
  "properties": {
    "iso:country":"IT",
    "sg:address":"31/g, Via Piave 24048 Treviolo",
    "sg:city":"Treviolo",
    "sg:classifiers":[
        {
            "category":"Parking",
            "subcategory":"Lot",
            "type":"Transportation"
        }
    ],
    "sg:phone":"+39 39035691637",
    "sg:postcode":"24048",
    "sg:province":"Bergamo",
    "sg:tags":[
        "transport",
        "road"
    ],
    "wof:name":"Cooperativa Posover A R.l.",
    "wof:placetype":"venue"
},
  "geometry": {"coordinates":[9.630257,45.675449],"type":"Point"}
}