{
  "type": "Feature",
  "properties": {
    "addr:full":"50063 Figline Valdarno Figline Valdarno Firenze 50063",
    "addr:postcode":"50063;50063",
    "addr:street":"Valdarno",
    "iso:country":"IT",
    "sg:address":"50063 Figline Valdarno",
    "sg:city":"Figline Valdarno",
    "sg:classifiers":[
        {
            "category":"Health Services",
            "subcategory":"Health Practitioner",
            "type":"Services"
        }
    ],
    "sg:phone":"+39 055 915 2070",
    "sg:postcode":"50063",
    "sg:province":"Firenze",
    "sg:tags":[
        "medici"
    ],
    "wof:name":"Mugnai Rachele",
    "wof:placetype":"venue"
},
  "geometry": {"coordinates":[11.4703063965,43.6202468872],"type":"Point"}
}