{
  "type": "Feature",
  "properties": {
    "iso:country":"IT",
    "sg:address":"186, Via Etna 95045 Misterbianco",
    "sg:city":"Misterbianco",
    "sg:classifiers":[
        {
            "category":"Food & Beverages",
            "subcategory":"Groceries & Convenience Stores",
            "type":"Retail Goods"
        }
    ],
    "sg:phone":"+39 39095398565",
    "sg:postcode":"95045",
    "sg:province":"Catania",
    "sg:tags":[
        "product",
        "related"
    ],
    "wof:name":"Di. Spec. Siciliana Di Santonocito Lorenzo & C. (s.n.c.)",
    "wof:placetype":"venue"
},
  "geometry": {"coordinates":[15.0355958939,37.5310821533],"type":"Point"}
}