{
  "type": "Feature",
  "properties": {
    "addr:full":"Via Oberdan 8 27029 Vigevano Vigevano Pavia 27029",
    "addr:housenumber":"8",
    "addr:postcode":"27029;27029",
    "addr:street":"Via Oberdan",
    "iso:country":"IT",
    "sg:address":"Via Oberdan 8 27029 Vigevano",
    "sg:city":"Vigevano",
    "sg:classifiers":[
        {
            "category":"Shopping",
            "subcategory":"Shoes",
            "type":"Retail Goods"
        }
    ],
    "sg:phone":"+39 0381 88629",
    "sg:postcode":"27029",
    "sg:province":"Pavia",
    "sg:tags":[
        "men's",
        "boot"
    ],
    "sg:website":"www.saede.it",
    "wof:name":"Sa & De Sas Di Arminio Emma & C.",
    "wof:placetype":"venue"
},
  "geometry": {"coordinates":[9.1565628052,45.1858863831],"type":"Point"}
}