{
  "type": "Feature",
  "properties": {
    "addr:full":"Via Liberta' 121 20020 Lazzate Lazzate Milano 20020",
    "addr:housenumber":"121",
    "addr:postcode":"20020;20020",
    "addr:street":"Via Liberta '",
    "iso:country":"IT",
    "sg:address":"Via Liberta' 121 20020 Lazzate",
    "sg:city":"Lazzate",
    "sg:classifiers":[
        {
            "category":"Wholesale",
            "subcategory":"Furniture",
            "type":"Manufacturing & Wholesale Goods"
        }
    ],
    "sg:phone":"+39 02 9632 0037",
    "sg:postcode":"20020",
    "sg:province":"Milano",
    "sg:tags":[
        "creative"
    ],
    "sg:website":"www.tura.it",
    "wof:name":"Tura - Iniziative Di Arredamento Srl",
    "wof:placetype":"venue"
},
  "geometry": {"coordinates":[9.095922,45.672985],"type":"Point"}
}