{
  "type": "Feature",
  "properties": {
    "iso:country":"IT",
    "sg:address":"40129 Bologna",
    "sg:city":"Bologna",
    "sg:orig_category":"Ricambi E Componenti Dei Mezzi Di Trasporto",
    "sg:phone":"+39 051 321571",
    "sg:postcode":"40129",
    "sg:province":"Bologna",
    "wof:name":"Comel (s.p.a.)",
    "wof:placetype":"venue"
},
  "geometry": {"coordinates":[11.346212,44.535881],"type":"Point"}
}