{
  "type": "Feature",
  "properties": {
    "addr:full":"56028 San Miniato San Miniato Pisa 56028",
    "addr:postcode":"56028;56028",
    "addr:street":"San Miniato San Miniato Pisa",
    "iso:country":"IT",
    "sg:address":"56028 San Miniato",
    "sg:city":"San Miniato",
    "sg:orig_category":"Pelli E Pellami - Produzione E Commercio",
    "sg:phone":"+39 0571 498148",
    "sg:postcode":"56028",
    "sg:province":"Pisa",
    "wof:name":"Francalanci Luca & C Snc",
    "wof:placetype":"venue"
},
  "geometry": {"coordinates":[10.8677253723,43.6729125977],"type":"Point"}
}