{
  "type": "Feature",
  "properties": {
    "iso:country":"IT",
    "sg:address":"30022 Ceggia",
    "sg:city":"Ceggia",
    "sg:orig_category":"Manufacturers: Prefabbricati",
    "sg:phone":"+39 0421 329987",
    "sg:postcode":"30022",
    "sg:province":"Venezia",
    "wof:name":"Italpali S.r.l.",
    "wof:placetype":"venue"
},
  "geometry": {"coordinates":[12.680747,45.731289],"type":"Point"}
}