{
  "type": "Feature",
  "properties": {
    "addr:full":"16129 Genova Genova Genova 16129",
    "addr:postcode":"16129;16129",
    "iso:country":"IT",
    "sg:address":"16129 Genova",
    "sg:city":"Genova",
    "sg:orig_category":"Dolciumi E Gelati",
    "sg:phone":"+39 010 540926",
    "sg:postcode":"16129",
    "sg:province":"Genova",
    "wof:name":"Ballacchino Francesco",
    "wof:placetype":"venue"
},
  "geometry": {"coordinates":[8.948096,44.396812],"type":"Point"}
}