{
  "type": "Feature",
  "properties": {
    "iso:country":"IT",
    "sg:address":"47900 Rimini",
    "sg:city":"Rimini",
    "sg:orig_category":"Ospedali E Servizi Sanitari. Servizi Sociali",
    "sg:phone":"+39 0541 743590",
    "sg:postcode":"47900",
    "sg:province":"Rimini",
    "wof:name":"La Clinique Blu",
    "wof:placetype":"venue"
},
  "geometry": {"coordinates":[12.58075,44.057121],"type":"Point"}
}