{
  "type": "Feature",
  "properties": {
    "iso:country":"IT",
    "sg:address":"Via Aterno Zona Commerciale Dragonara 66020 San Giovanni Teatino",
    "sg:city":"San Giovanni Teatino",
    "sg:classifiers":[
        {
            "category":"Shopping",
            "subcategory":"Computers & Home Electronics",
            "type":"Retail Goods"
        }
    ],
    "sg:phone":"+39 085 446 3060",
    "sg:postcode":"66020",
    "sg:province":"Chieti",
    "sg:tags":[
        "electronic",
        "electrical",
        "equipment"
    ],
    "wof:name":"Comind (s.a.s.)",
    "wof:placetype":"venue"
},
  "geometry": {"coordinates":[14.167151,42.351791],"type":"Point"}
}