{
  "type": "Feature",
  "properties": {
    "addr:full":"20096 Pioltello Pioltello Milano 20096",
    "addr:postcode":"20096;20096",
    "iso:country":"IT",
    "sg:address":"20096 Pioltello",
    "sg:city":"Pioltello",
    "sg:orig_category":"Scuole E Servizi Scolastici. Servizi Vari Di Interesse Pubblico",
    "sg:phone":"+39 02 9210 3697",
    "sg:postcode":"20096",
    "sg:province":"Milano",
    "wof:name":"Municipio",
    "wof:placetype":"venue"
},
  "geometry": {"coordinates":[9.330673,45.503521],"type":"Point"}
}