{
  "type": "Feature",
  "properties": {
    "iso:country":"IT",
    "sg:address":"20159 Milano",
    "sg:city":"Milano",
    "sg:orig_category":"Ristorazione E Locali Pubblici Affini. Ristoranti Ed Esercizi Affini",
    "sg:phone":"+39 02 608 1597",
    "sg:postcode":"20159",
    "sg:province":"Milano",
    "wof:name":"Lo Stuzzichino (s.n.c.)",
    "wof:placetype":"venue"
},
  "geometry": {"coordinates":[9.186219,45.489429],"type":"Point"}
}