{
  "type": "Feature",
  "properties": {
    "addr:full":"Km. 307, Strada Statale Adriatica 16 60100 Ancona AN",
    "addr:housenumber":"16",
    "addr:postcode":"60100",
    "addr:street":"Strada Statale Adriatica",
    "iso:country":"IT",
    "sg:address":"Km. 307, Strada Statale Adriatica 16 60100 Ancona",
    "sg:classifiers":[
        {
            "category":"Bars & Pubs",
            "subcategory":"Nightclub",
            "type":"Food & Drink"
        }
    ],
    "sg:phone":"+39 071 804 7093",
    "sg:province":"AN",
    "sg:tags":[
        "cake",
        "bread"
    ],
    "wof:name":"Giampaoli S.p.a.",
    "wof:placetype":"venue"
},
  "geometry": {"coordinates":[13.508665,43.618198],"type":"Point"}
}