{
  "type": "Feature",
  "properties": {
    "iso:country":"IT",
    "sg:address":"20125 Milano",
    "sg:city":"Milano",
    "sg:orig_category":"Servizi E Lavori Per Edilizia E Lavori Pubblici. Servizi Ausiliari Di Sorveglianza, Manutenzione E Pulizia",
    "sg:phone":"+39 02 6707 6095",
    "sg:postcode":"20125",
    "sg:province":"Milano",
    "wof:name":"Oasi Del Bagno",
    "wof:placetype":"venue"
},
  "geometry": {"coordinates":[9.206995,45.491978],"type":"Point"}
}