{
  "type": "Feature",
  "properties": {
    "addr:full":"38100 Trento Trento Trento 38100",
    "addr:postcode":"38100;38100",
    "iso:country":"IT",
    "sg:address":"38100 Trento",
    "sg:city":"Trento",
    "sg:orig_category":"Articoli Da Regalo. Arte Ed Artigianato Artistico. Shopping",
    "sg:phone":"+39 0461 260308",
    "sg:postcode":"38100",
    "sg:province":"Trento",
    "sg:website":"http://www.tienne.it/orologi",
    "wof:name":"Oreficeria Gold & Silver",
    "wof:placetype":"venue"
},
  "geometry": {"coordinates":[11.12359,46.072586],"type":"Point"}
}