{
  "type": "Feature",
  "properties": {
    "addr:full":"4, Via Trento 53036 Poggibonsi Poggibonsi Siena 53036",
    "addr:postcode":"53036;53036",
    "addr:street":"Via Trento",
    "iso:country":"IT",
    "sg:address":"4, Via Trento 53036 Poggibonsi",
    "sg:city":"Poggibonsi",
    "sg:classifiers":[
        {
            "category":"Manufacturing",
            "subcategory":"Rubber & Plastics",
            "type":"Manufacturing & Wholesale Goods"
        }
    ],
    "sg:phone":"+39 0577 939068",
    "sg:postcode":"53036",
    "sg:province":"Siena",
    "wof:name":"Tosco Espansi Srl",
    "wof:placetype":"venue"
},
  "geometry": {"coordinates":[11.146733284,43.4694671631],"type":"Point"}
}