{
  "type": "Feature",
  "properties": {
    "iso:country":"IT",
    "sg:address":"06063 Magione",
    "sg:city":"Magione",
    "sg:orig_category":"Macchine E Forniture Per Ecologia E Smaltimento Rifiuti",
    "sg:phone":"+39 075 847 2015",
    "sg:postcode":"06063",
    "sg:province":"Perugia",
    "wof:name":"Carbonafta Srl",
    "wof:placetype":"venue"
},
  "geometry": {"coordinates":[12.186145,43.119774],"type":"Point"}
}