{
  "type": "Feature",
  "properties": {
    "iso:country":"IT",
    "sg:address":"75100 Matera",
    "sg:city":"Matera",
    "sg:orig_category":"Macchine Ed Impianti Per Edilizia E Lavori Pubblici. Elettronica Industriale, Prodotti E Apparecchiature",
    "sg:phone":"+39 0835 387751",
    "sg:postcode":"75100",
    "sg:province":"Matera",
    "wof:name":"Sud Signal Srl",
    "wof:placetype":"venue"
},
  "geometry": {"coordinates":[16.573351,40.673241],"type":"Point"}
}