{
  "type": "Feature",
  "properties": {
    "iso:country":"IT",
    "sg:address":"19025 Portovenere",
    "sg:city":"Portovenere",
    "sg:orig_category":"Agenzie Immobiliari",
    "sg:phone":"+39 0187 791343",
    "sg:postcode":"19025",
    "sg:province":"La Spezia",
    "sg:website":"http://lisa.shiny.it/housing/portovenere",
    "wof:name":"Portovenere Immobili Srl",
    "wof:placetype":"venue"
},
  "geometry": {"coordinates":[9.8174362183,44.1081809998],"type":"Point"}
}