{
  "type": "Feature",
  "properties": {
    "addr:full":"19034 Ortonovo Ortonovo La Spezia 19034",
    "addr:postcode":"19034;19034",
    "iso:country":"IT",
    "sg:address":"19034 Ortonovo",
    "sg:city":"Ortonovo",
    "sg:orig_category":"Prodotti Chimici Di Base. Forniture Per Attivita' Industriali",
    "sg:phone":"+39 0187 66712",
    "sg:postcode":"19034",
    "sg:province":"La Spezia",
    "wof:name":"Fidal Srl",
    "wof:placetype":"venue"
},
  "geometry": {"coordinates":[9.901099205,44.1360168457],"type":"Point"}
}