{
  "type": "Feature",
  "properties": {
    "iso:country":"IT",
    "sg:address":"17100 Savona",
    "sg:city":"Savona",
    "sg:orig_category":"Antifurto",
    "sg:phone":"+39 019 813803",
    "sg:postcode":"17100",
    "sg:province":"Savona",
    "wof:name":"Nuova Isat Di Bona Mario",
    "wof:placetype":"venue"
},
  "geometry": {"coordinates":[8.471439,44.301846],"type":"Point"}
}