{
  "type": "Feature",
  "properties": {
    "addr:full":"78, Via Umberto I 42022 Boretto Reggio Nell'Emilia 42022",
    "addr:postcode":"42022;42022",
    "addr:street":"Via Umberto I",
    "iso:country":"IT",
    "sg:address":"78, Via Umberto I 42022 Boretto",
    "sg:classifiers":[
        {
            "category":"Wholesale",
            "subcategory":"Machinery & Supplies",
            "type":"Manufacturing & Wholesale Goods"
        }
    ],
    "sg:phone":"+39 0522 965642",
    "sg:postcode":"42022",
    "sg:province":"Reggio Nell'Emilia",
    "sg:tags":[
        "-",
        "agriculture",
        "equipment"
    ],
    "wof:name":"Carbogreen Di Carboni Renzo",
    "wof:placetype":"venue"
},
  "geometry": {"coordinates":[10.558287,44.905399],"type":"Point"}
}