{
  "type": "Feature",
  "properties": {
    "iso:country":"IT",
    "sg:address":"Via Sesta Strada 45 36071 Arzignano",
    "sg:city":"Arzignano",
    "sg:classifiers":[
        {
            "category":"Manufacturing",
            "subcategory":"Leather Goods",
            "type":"Manufacturing & Wholesale Goods"
        }
    ],
    "sg:phone":"+39 0444 451451",
    "sg:postcode":"36071",
    "sg:province":"Vicenza",
    "sg:tags":[
        "synthetic"
    ],
    "sg:website":"www.spac-spa.it",
    "wof:name":"Spac Spa",
    "wof:placetype":"venue"
},
  "geometry": {"coordinates":[11.36071,45.507133],"type":"Point"}
}