{
  "type": "Feature",
  "properties": {
    "iso:country":"IT",
    "sg:address":"20090 Cusago",
    "sg:city":"Cusago",
    "sg:orig_category":"Arredo Camera Letto E Complementi",
    "sg:phone":"+39 02 901 9903",
    "sg:postcode":"20090",
    "sg:province":"Milano",
    "wof:name":"Corrado Sas Di Quarantotto Corrado Silvana E C.",
    "wof:placetype":"venue"
},
  "geometry": {"coordinates":[9.047132,45.441761],"type":"Point"}
}