{
  "type": "Feature",
  "properties": {
    "iso:country":"IT",
    "sg:address":"18, Vicolo Capagiolo 23893 Cassago Brianza",
    "sg:city":"Cassago Brianza",
    "sg:classifiers":[
        {
            "category":"Real Estate",
            "subcategory":"Surveying",
            "type":"Services"
        }
    ],
    "sg:phone":"+39 39039955934",
    "sg:postcode":"23893",
    "sg:province":"Lecco",
    "sg:tags":[
        "equipment",
        "material",
        "good",
        "-",
        "handling"
    ],
    "wof:name":"Molteni (s.r.l.)",
    "wof:placetype":"venue"
},
  "geometry": {"coordinates":[9.288828,45.738789],"type":"Point"}
}