{
  "type": "Feature",
  "properties": {
    "addr:full":"88040 Serrastretta Serrastretta Catanzaro 88040",
    "addr:postcode":"88040;88040",
    "iso:country":"IT",
    "sg:address":"88040 Serrastretta",
    "sg:city":"Serrastretta",
    "sg:orig_category":"Mobili - Produzione E Ingrosso",
    "sg:phone":"+39 0968 81172",
    "sg:postcode":"88040",
    "sg:province":"Catanzaro",
    "wof:name":"Fazio Donatella La Sedia",
    "wof:placetype":"venue"
},
  "geometry": {"coordinates":[16.4172039032,39.0142211914],"type":"Point"}
}