{
  "type": "Feature",
  "properties": {
    "addr:full":"Via Emilia Levante 288 40068 San Lazzaro Di Savena San Lazzaro Bologna 40068",
    "addr:housenumber":"288",
    "addr:postcode":"40068;40068",
    "addr:street":"Via Emilia Levante;San;Bologna",
    "iso:country":"IT",
    "sg:address":"Via Emilia Levante 288 40068 San Lazzaro Di Savena",
    "sg:city":"San Lazzaro",
    "sg:classifiers":[
        {
            "category":"Social Services",
            "subcategory":"Job Training",
            "type":"Services"
        }
    ],
    "sg:phone":"+39 051 622 6111",
    "sg:postcode":"40068",
    "sg:province":"Bologna",
    "sg:tags":[
        "adhesive",
        "industry",
        "electrical",
        "tape"
    ],
    "sg:website":"www.coveme.com",
    "wof:name":"Coveme Spa",
    "wof:placetype":"venue"
},
  "geometry": {"coordinates":[11.381462,44.48106],"type":"Point"}
}