{
  "type": "Feature",
  "properties": {
    "iso:country":"IT",
    "sg:address":"70051 Barletta",
    "sg:city":"Barletta",
    "sg:orig_category":"Macchine Per Cucire - Commercio E Riparazione",
    "sg:phone":"+39 0883 510221",
    "sg:postcode":"70051",
    "sg:province":"Bari",
    "sg:website":"http://www.crmitalia.org",
    "wof:name":"C.r.m. Di Sfregola Anna Nunzia",
    "wof:placetype":"venue"
},
  "geometry": {"coordinates":[16.737471,41.158783],"type":"Point"}
}