{
  "type": "Feature",
  "properties": {
    "iso:country":"IT",
    "sg:address":"15057 Tortona",
    "sg:city":"Tortona",
    "sg:orig_category":"Articoli Medico-sanitari Ed Ortopedici",
    "sg:phone":"+39 0131 861386",
    "sg:postcode":"15057",
    "sg:province":"Alessandria",
    "wof:name":"Nani Ortopedia Emiliana",
    "wof:placetype":"venue"
},
  "geometry": {"coordinates":[8.957223,44.826965],"type":"Point"}
}