{
  "type": "Feature",
  "properties": {
    "addr:full":"21040 Morazzone Morazzone Varese 21040",
    "addr:postcode":"21040;21040",
    "iso:country":"IT",
    "sg:address":"21040 Morazzone",
    "sg:city":"Morazzone",
    "sg:orig_category":"Calzaturifici E Calzolai - Macchine",
    "sg:phone":"+39 0332 462884",
    "sg:postcode":"21040",
    "sg:province":"Varese",
    "wof:name":"Gesta International Srl",
    "wof:placetype":"venue"
},
  "geometry": {"coordinates":[8.835133,45.76001],"type":"Point"}
}