{
  "type": "Feature",
  "properties": {
    "addr:full":"27050 Torrazza Coste Torrazza Coste Pavia 27050",
    "addr:postcode":"27050;27050",
    "addr:street":"Coste",
    "iso:country":"IT",
    "sg:address":"27050 Torrazza Coste",
    "sg:city":"Torrazza Coste",
    "sg:orig_category":"Frigotecnica, Apparecchiature E Servizi. Climatizzazione E Condizionamento, Apparecchiature E Servizi",
    "sg:phone":"+39 0383 47077",
    "sg:postcode":"27050",
    "sg:province":"Pavia",
    "wof:name":"2 V Refrigerazione Srl",
    "wof:placetype":"venue"
},
  "geometry": {"coordinates":[9.0760269165,44.9881401062],"type":"Point"}
}