{
  "type": "Feature",
  "properties": {
    "addr:full":"11, Via Eridano 26100 Cremona Cremona Cremona 26100",
    "addr:postcode":"26100;26100",
    "addr:street":"Via Eridano",
    "iso:country":"IT",
    "sg:address":"11, Via Eridano 26100 Cremona",
    "sg:city":"Cremona",
    "sg:classifiers":[
        {
            "category":"Autos & Motor Vehicles",
            "subcategory":"Automobile Sales",
            "type":"Retail Goods"
        }
    ],
    "sg:phone":"+39 39037228329",
    "sg:postcode":"26100",
    "sg:province":"Cremona",
    "sg:tags":[
        "motor-cars"
    ],
    "wof:name":"Arcar Spa",
    "wof:placetype":"venue"
},
  "geometry": {"coordinates":[9.9987277985,45.1327896118],"type":"Point"}
}