{
  "type": "Feature",
  "properties": {
    "addr:full":"Via Bivio San Vitale 36075 Montecchio Maggiore Montecchio Maggiore Vicenza 36075",
    "addr:postcode":"36075;36075",
    "addr:street":"Via Bivio San Vitale",
    "iso:country":"IT",
    "sg:address":"Via Bivio San Vitale 36075 Montecchio Maggiore",
    "sg:city":"Montecchio Maggiore",
    "sg:classifiers":[
        {
            "category":"Government",
            "subcategory":"Fire Station",
            "type":"Public Place"
        }
    ],
    "sg:phone":"+39 0444 491744",
    "sg:postcode":"36075",
    "sg:province":"Vicenza",
    "sg:tags":[
        "heating",
        "accessory",
        "ventilation",
        "air conditioning"
    ],
    "sg:website":"www.mutmeccanica.com",
    "wof:name":"Mut Meccanica Tovo Spa",
    "wof:placetype":"venue"
},
  "geometry": {"coordinates":[11.395308,45.510487],"type":"Point"}
}