{
  "type": "Feature",
  "properties": {
    "addr:full":"51100 Pistoia Pistoia Pistoia 51100",
    "addr:postcode":"51100;51100",
    "iso:country":"IT",
    "sg:address":"51100 Pistoia",
    "sg:city":"Pistoia",
    "sg:orig_category":"Animali Domestici - Allevamento E Addestramento",
    "sg:phone":"+39 0573 617542",
    "sg:postcode":"51100",
    "sg:province":"Pistoia",
    "wof:name":"La Badia Di Simone E Carlotta Cappellini Snc",
    "wof:placetype":"venue"
},
  "geometry": {"coordinates":[10.968711,43.909954],"type":"Point"}
}