{
  "type": "Feature",
  "properties": {
    "iso:country":"IT",
    "sg:address":"00131 Roma",
    "sg:city":"Roma",
    "sg:orig_category":"Elettronica Professionale E Di Consumo. Automazione E Macchine Per Ufficio. Forniture Industriali Per Prevenzione, Controllo E Sicurezza",
    "sg:phone":"+39 06 4123 8435",
    "sg:postcode":"00131",
    "sg:province":"Roma",
    "wof:name":"Controlli Sistemi Sicurezza Srl",
    "wof:placetype":"venue"
},
  "geometry": {"coordinates":[12.603024,41.901905],"type":"Point"}
}