{
  "type": "Feature",
  "properties": {
    "addr:full":"80131 Napoli Napoli Napoli 80131",
    "addr:housenumber":"80131",
    "addr:postcode":"80131",
    "iso:country":"IT",
    "sg:address":"80131 Napoli",
    "sg:city":"Napoli",
    "sg:classifiers":[
        {
            "category":"Health Services",
            "subcategory":"Nursing And Care Facility",
            "type":"Services"
        }
    ],
    "sg:phone":"+39 081 587 3808",
    "sg:postcode":"80131",
    "sg:province":"Napoli",
    "sg:tags":[
        "case",
        "cura",
        "private",
        "di"
    ],
    "sg:website":"http://www.villacamaldoli.it",
    "wof:name":"Alma Mater Villa Camaldoli Spa",
    "wof:placetype":"venue"
},
  "geometry": {"coordinates":[14.219233,40.865116],"type":"Point"}
}