{
  "type": "Feature",
  "properties": {
    "iso:country":"IT",
    "sg:address":"20153 Milano",
    "sg:city":"Milano",
    "sg:orig_category":"Macchine E Forniture Per Industria Orafa E Per Orologeria",
    "sg:phone":"+39 02 459 7346",
    "sg:postcode":"20153",
    "sg:province":"Milano",
    "wof:name":"Cucchi E Alfieri Snc Di B.cucchi & M.piera Alfieri",
    "wof:placetype":"venue"
},
  "geometry": {"coordinates":[9.089931,45.480263],"type":"Point"}
}