{
  "type": "Feature",
  "properties": {
    "addr:full":"20099 Sesto San Giovanni Sesto San Giovanni Milano 20099",
    "addr:postcode":"20099;20099",
    "iso:country":"IT",
    "sg:address":"20099 Sesto San Giovanni",
    "sg:city":"Sesto San Giovanni",
    "sg:orig_category":"Macchine, Impianti E Forniture Per Industria Grafica, Cartaria E Cartotecnica",
    "sg:phone":"+39 02 248 5021",
    "sg:postcode":"20099",
    "sg:province":"Milano",
    "wof:name":"Tavolini Bruno",
    "wof:placetype":"venue"
},
  "geometry": {"coordinates":[9.220426,45.536186],"type":"Point"}
}