{
  "type": "Feature",
  "properties": {
    "iso:country":"IT",
    "sg:address":"Via Svincolo Autostr. Reg. Periane 18011 Arma Di Taggia",
    "sg:orig_category":"Earthmovers, Bulldozers, Dozers, Wheel Loaders",
    "sg:phone":"+39 0184 477290",
    "sg:postcode":"18011",
    "sg:province":"Imperia",
    "wof:name":"C.m.i. Srl",
    "wof:placetype":"venue"
},
  "geometry": {"coordinates":[8.031564,43.887894],"type":"Point"}
}