{
  "type": "Feature",
  "properties": {
    "iso:country":"IT",
    "sg:address":"98122 Messina",
    "sg:city":"Messina",
    "sg:classifiers":[
        {
            "category":"Farming",
            "subcategory":"Berry Farm",
            "type":"Manufacturing & Wholesale Goods"
        }
    ],
    "sg:phone":"+39 090 673417",
    "sg:postcode":"98122",
    "sg:province":"Messina",
    "sg:tags":[
        "vegetable",
        "growing",
        "flower",
        "agriculture"
    ],
    "sg:website":"http://www.esportazionesiciliana.com",
    "wof:name":"Esportazione Siciliana Srl",
    "wof:placetype":"venue"
},
  "geometry": {"coordinates":[15.538645,38.199047],"type":"Point"}
}