{
  "type": "Feature",
  "properties": {
    "iso:country":"IT",
    "sg:address":"10148 Torino",
    "sg:city":"Torino",
    "sg:orig_category":"Irrigazione - Impianti",
    "sg:phone":"+39 011 226 1661",
    "sg:postcode":"10148",
    "sg:province":"Torino",
    "wof:name":"Resincondotte Srl",
    "wof:placetype":"venue"
},
  "geometry": {"coordinates":[7.68784,45.112507],"type":"Point"}
}