{
  "type": "Feature",
  "properties": {
    "addr:full":"33034 Fagagna Fagagna Udine 33034",
    "addr:postcode":"33034;33034",
    "iso:country":"IT",
    "sg:address":"33034 Fagagna",
    "sg:city":"Fagagna",
    "sg:classifiers":[
        {
            "category":"Government",
            "subcategory":"Office",
            "type":"Public Place"
        }
    ],
    "sg:phone":"+39 0432 810632",
    "sg:postcode":"33034",
    "sg:province":"Udine",
    "sg:tags":[
        "e",
        "lo",
        "tempo",
        "libero",
        "per",
        "spettacolo",
        "servizi",
        "culturali",
        "sport",
        "il"
    ],
    "wof:name":"Complesso Bandistico Di Fagagna",
    "wof:placetype":"venue"
},
  "geometry": {"coordinates":[13.03699,46.117638],"type":"Point"}
}