{
  "type": "Feature",
  "properties": {
    "iso:country":"IT",
    "sg:address":"18, Via Garibaldi 28076 Pogno",
    "sg:city":"Pogno",
    "sg:classifiers":[
        {
            "category":"Shopping",
            "type":"Retail Goods"
        }
    ],
    "sg:phone":"+39 39032297207",
    "sg:postcode":"28076",
    "sg:province":"Novara",
    "sg:tags":[
        "finished",
        "-",
        "metallic"
    ],
    "wof:name":"Rubitor (s.r.l.)",
    "wof:placetype":"venue"
},
  "geometry": {"coordinates":[8.3838672638,45.7545509338],"type":"Point"}
}