{
  "type": "Feature",
  "properties": {
    "iso:country":"IT",
    "sg:address":"1, Via Pantanelli 61025 Montelabbate",
    "sg:city":"Montelabbate",
    "sg:classifiers":[
        {
            "category":"Home & Garden",
            "subcategory":"Home Furnishings",
            "type":"Retail Goods"
        }
    ],
    "sg:phone":"+39 0721 498600",
    "sg:postcode":"61025",
    "sg:province":"Pesaro E Urbino",
    "sg:tags":[
        "household"
    ],
    "wof:name":"Dafa S.r.l.",
    "wof:placetype":"venue"
},
  "geometry": {"coordinates":[12.785438,43.857155],"type":"Point"}
}