{
  "type": "Feature",
  "properties": {
    "addr:full":"Via Madonna Del Prato 120; Arezzo; 52100 Arezzo Arezzo 52100",
    "addr:housenumber":"120",
    "addr:postcode":"52100;52100",
    "addr:street":"Via Madonna Del Prato",
    "iso:country":"IT",
    "sg:address":"Via Madonna Del Prato 120; Arezzo; 52100",
    "sg:city":"Arezzo",
    "sg:classifiers":[
        {
            "category":"Banks & Credit Unions",
            "subcategory":"Bank",
            "type":"Services"
        }
    ],
    "sg:phone":"+39 0575 379123",
    "sg:postcode":"52100",
    "sg:province":"Arezzo",
    "wof:name":"Banca Commerciale Italiana Spa",
    "wof:placetype":"venue"
},
  "geometry": {"coordinates":[11.878837,43.4627],"type":"Point"}
}