{
  "type": "Feature",
  "properties": {
    "addr:full":"213, Via Varrobbie 41052 Guiglia Guiglia Modena 41052",
    "addr:housenumber":"213",
    "addr:postcode":"41052;41052",
    "addr:street":"Via Varrobbie",
    "iso:country":"IT",
    "sg:address":"213, Via Varrobbie 41052 Guiglia",
    "sg:city":"Guiglia",
    "sg:classifiers":[
        {
            "category":"Food & Beverages",
            "subcategory":"Groceries & Convenience Stores",
            "type":"Retail Goods"
        }
    ],
    "sg:phone":"+39 39059700023",
    "sg:postcode":"41052",
    "sg:province":"Modena",
    "sg:tags":[
        "product",
        "related"
    ],
    "wof:name":"San Geminiano Prosciutti (s.p.a.)",
    "wof:placetype":"venue"
},
  "geometry": {"coordinates":[10.948723793,44.3696670532],"type":"Point"}
}