{
  "type": "Feature",
  "properties": {
    "addr:full":"20143 Milano Milano Milano 20143",
    "addr:postcode":"20143;20143",
    "iso:country":"IT",
    "sg:address":"20143 Milano",
    "sg:city":"Milano",
    "sg:orig_category":"Metalli E Leghe",
    "sg:phone":"+39 02 8912 8655",
    "sg:postcode":"20143",
    "sg:province":"Milano",
    "wof:name":"Miorini Fratelli S.p.a.",
    "wof:placetype":"venue"
},
  "geometry": {"coordinates":[9.1587276459,45.4414100647],"type":"Point"}
}