{
  "type": "Feature",
  "properties": {
    "addr:full":"34122 Trieste Trieste Trieste 34122",
    "addr:postcode":"34122;34122",
    "iso:country":"IT",
    "sg:address":"34122 Trieste",
    "sg:city":"Trieste",
    "sg:orig_category":"Filati E Materie Prime Tessili",
    "sg:phone":"+39 040 771717",
    "sg:postcode":"34122",
    "sg:province":"Trieste",
    "wof:name":"Fonda Silva Sas",
    "wof:placetype":"venue"
},
  "geometry": {"coordinates":[13.7759742737,45.6511497498],"type":"Point"}
}