{
  "type": "Feature",
  "properties": {
    "addr:full":"51100 Pistoia Pistoia Pistoia 51100",
    "addr:postcode":"51100;51100",
    "iso:country":"IT",
    "sg:address":"51100 Pistoia",
    "sg:city":"Pistoia",
    "sg:orig_category":"Frigotecnica, Apparecchiature E Servizi. Forniture Alle Strutture Ricettive",
    "sg:phone":"+39 0573 935005",
    "sg:postcode":"51100",
    "sg:province":"Pistoia",
    "wof:name":"Polar Snc",
    "wof:placetype":"venue"
},
  "geometry": {"coordinates":[10.9347362518,43.9299125671],"type":"Point"}
}