{
  "type": "Feature",
  "properties": {
    "iso:country":"IT",
    "sg:address":"20037 Paderno Dugnano",
    "sg:city":"Paderno Dugnano",
    "sg:orig_category":"Scuole E Servizi Scolastici. Servizi Per Lo Sport E Il Tempo Libero",
    "sg:phone":"+39 02 9904 6574",
    "sg:postcode":"20037",
    "sg:province":"Milano",
    "wof:name":"Paderno - Sub",
    "wof:placetype":"venue"
},
  "geometry": {"coordinates":[9.163235,45.572472],"type":"Point"}
}