{
  "type": "Feature",
  "properties": {
    "iso:country":"IT",
    "sg:address":"35020 Masera' Di Padova",
    "sg:orig_category":"Alimentari - Produzione E Ingrosso",
    "sg:phone":"+39 049 886 0811",
    "sg:postcode":"35020",
    "sg:province":"Padova",
    "wof:name":"F.p. Distribuzione Snc",
    "wof:placetype":"venue"
},
  "geometry": {"coordinates":[11.864272,45.325542],"type":"Point"}
}