{
  "type": "Feature",
  "properties": {
    "iso:country":"IT",
    "sg:address":"22036 Erba",
    "sg:city":"Erba",
    "sg:orig_category":"Chiese Ed Associazioni Religiose",
    "sg:phone":"+39 031 646265",
    "sg:postcode":"22036",
    "sg:province":"Como",
    "wof:name":"Chiesa Di Gesu' Cristo Dei Santi Degli Ultimi Giorni",
    "wof:placetype":"venue"
},
  "geometry": {"coordinates":[9.168669,45.793247],"type":"Point"}
}