{
  "type": "Feature",
  "properties": {
    "iso:country":"IT",
    "sg:address":"19, Viale Kennedy 28021 Borgomanero",
    "sg:city":"Borgomanero",
    "sg:classifiers":[
        {
            "category":"Shopping",
            "subcategory":"Clothing, Apparel, & Fashions",
            "type":"Retail Goods"
        }
    ],
    "sg:phone":"+39 0322 843878",
    "sg:postcode":"28021",
    "sg:province":"Novara",
    "sg:tags":[
        "clothes"
    ],
    "wof:name":"Confezioni Eco S.n.c.",
    "wof:placetype":"venue"
},
  "geometry": {"coordinates":[8.45564,45.70694],"type":"Point"}
}