{
  "type": "Feature",
  "properties": {
    "iso:country":"IT",
    "sg:address":"Via Casale 26 15040 Occimiano",
    "sg:city":"Occimiano",
    "sg:classifiers":[
        {
            "category":"Building & Trades",
            "subcategory":"Plumbing",
            "type":"Services"
        }
    ],
    "sg:phone":"+39 0142 400811",
    "sg:postcode":"15040",
    "sg:province":"Alessandria",
    "sg:tags":[
        "tank"
    ],
    "sg:website":"www.gimartecno.com",
    "wof:name":"Gimar Tecno Srl",
    "wof:placetype":"venue"
},
  "geometry": {"coordinates":[8.500892,45.06498],"type":"Point"}
}