{
  "type": "Feature",
  "properties": {
    "addr:full":"196, Via Flaminia 47900 Rimini Rimini Rimini 47900",
    "addr:housenumber":"196",
    "addr:postcode":"47900;47900",
    "addr:street":"Via Flaminia",
    "iso:country":"IT",
    "sg:address":"196, Via Flaminia 47900 Rimini",
    "sg:city":"Rimini",
    "sg:classifiers":[
        {
            "category":"Bars & Pubs",
            "subcategory":"Nightclub",
            "type":"Food & Drink"
        }
    ],
    "sg:phone":"+39 0541 370616",
    "sg:postcode":"47900",
    "sg:province":"Rimini",
    "sg:tags":[
        "cake",
        "bread"
    ],
    "wof:name":"Fugar Produzione Spa",
    "wof:placetype":"venue"
},
  "geometry": {"coordinates":[12.598984,44.036343],"type":"Point"}
}