{
  "type": "Feature",
  "properties": {
    "iso:country":"IT",
    "sg:address":"247, Via Labriola 59013 Montemurlo",
    "sg:city":"Montemurlo",
    "sg:classifiers":[
        {
            "category":"Shopping",
            "subcategory":"Crafts & Fabrics",
            "type":"Retail Goods"
        }
    ],
    "sg:phone":"+39 0574 721625",
    "sg:postcode":"59013",
    "sg:province":"Prato",
    "wof:name":"Tosco Laniera (s.p.a.)",
    "wof:placetype":"venue"
},
  "geometry": {"coordinates":[11.0506772995,43.904499054],"type":"Point"}
}