{
  "type": "Feature",
  "properties": {
    "iso:country":"IT",
    "sg:address":"Via Imbonati, 15 - Baranzate 20021 Bollate",
    "sg:city":"Baranzate",
    "sg:classifiers":[
        {
            "category":"Communications",
            "subcategory":"Television Station",
            "type":"Services"
        }
    ],
    "sg:phone":"+39 02 356 1202",
    "sg:postcode":"20021",
    "sg:province":"Milano",
    "sg:tags":[
        "work",
        "electronic",
        "electrotechnical",
        "contract",
        "basis"
    ],
    "sg:website":"www.offchiovenda.it",
    "wof:name":"Officine Elettromeccaniche Chiovenda Snc Di Tarrano Adriana E Chivenda Giovanni",
    "wof:placetype":"venue"
},
  "geometry": {"coordinates":[9.118319,45.529728],"type":"Point"}
}