{
  "type": "Feature",
  "properties": {
    "iso:country":"IT",
    "sg:address":"12035 Racconigi",
    "sg:city":"Racconigi",
    "sg:orig_category":"Prodotti E Manufatti In Materie Plastiche",
    "sg:phone":"+39 0172 812111",
    "sg:postcode":"12035",
    "sg:province":"Cuneo",
    "wof:name":"Novaplast Laminati S.p.a.",
    "wof:placetype":"venue"
},
  "geometry": {"coordinates":[7.6942372322,44.773853302],"type":"Point"}
}