{
  "type": "Feature",
  "properties": {
    "iso:country":"IT",
    "sg:address":"Via Fermi 27 34071 Cormons",
    "sg:city":"Cormons",
    "sg:classifiers":[
        {
            "category":"Manufacturing",
            "subcategory":"Leather Goods",
            "type":"Manufacturing & Wholesale Goods"
        }
    ],
    "sg:phone":"+39 0481 637811",
    "sg:postcode":"34071",
    "sg:province":"Gorizia",
    "sg:tags":[
        "synthetic"
    ],
    "wof:name":"Sogetec Spa",
    "wof:placetype":"venue"
},
  "geometry": {"coordinates":[13.621546,45.941303],"type":"Point"}
}