{
  "type": "Feature",
  "properties": {
    "addr:full":"16, V. Vespri Siciliani 20146 Milano Milano Milano 20146",
    "addr:housenumber":"16",
    "addr:postcode":"20146;20146",
    "addr:street":"V. Vespri Siciliani",
    "iso:country":"IT",
    "sg:address":"16, V. Vespri Siciliani 20146 Milano",
    "sg:city":"Milano",
    "sg:classifiers":[
        {
            "category":"Shopping",
            "subcategory":"Gifts & Souvenirs",
            "type":"Retail Goods"
        }
    ],
    "sg:phone":"+39 390 247 3294",
    "sg:postcode":"20146",
    "sg:province":"Milano",
    "sg:website":"http://www.paginegialle.it/crespiec",
    "wof:name":"Crespi & C.",
    "wof:placetype":"venue"
},
  "geometry": {"coordinates":[9.150407,45.453571],"type":"Point"}
}