{
  "type": "Feature",
  "properties": {
    "iso:country":"IT",
    "sg:address":"20090 Segrate",
    "sg:city":"Segrate",
    "sg:orig_category":"Arredi Ed Attrezzature Per Attivita' Commerciali Ed Artigianali",
    "sg:phone":"+39 02 2641 4046",
    "sg:postcode":"20090",
    "sg:province":"Milano",
    "wof:name":"Sistem Di Monferini Stefano & C. (s.n.c.)",
    "wof:placetype":"venue"
},
  "geometry": {"coordinates":[9.291694,45.501144],"type":"Point"}
}