{
  "type": "Feature",
  "properties": {
    "iso:country":"IT",
    "sg:address":"Via Di Piaggia, 2; Lucca; 55100",
    "sg:city":"Lucca",
    "sg:classifiers":[
        {
            "category":"Banks & Credit Unions",
            "subcategory":"Bank",
            "type":"Services"
        }
    ],
    "sg:phone":"+39 0583 42622",
    "sg:postcode":"55100",
    "sg:province":"Lucca",
    "wof:name":"Cassa Di Risparmio Di Lucca",
    "wof:placetype":"venue"
},
  "geometry": {"coordinates":[10.508095,43.840786],"type":"Point"}
}