{
  "type": "Feature",
  "properties": {
    "iso:country":"IT",
    "sg:address":"2755, Via Fossalta 47023 Cesena",
    "sg:city":"Cesena",
    "sg:orig_category":"Miscellaneous Products",
    "sg:phone":"+39 0547 317244",
    "sg:postcode":"47023",
    "sg:province":"Forl\u00ec-Cesena",
    "wof:name":"La Contabilita' (s.r.l.)",
    "wof:placetype":"venue"
},
  "geometry": {"coordinates":[12.2143545151,44.1718559265],"type":"Point"}
}