{
  "type": "Feature",
  "properties": {
    "addr:full":"20138 Milano Milano Milano 20138",
    "addr:postcode":"20138;20138",
    "iso:country":"IT",
    "sg:address":"20138 Milano",
    "sg:city":"Milano",
    "sg:orig_category":"Servizi E Lavori Per Agricoltura E Zootecnia",
    "sg:phone":"+39 02 506 0348",
    "sg:postcode":"20138",
    "sg:province":"Milano",
    "wof:name":"Consorzio Autostazione Merci Di Milano (s.p.a.)",
    "wof:placetype":"venue"
},
  "geometry": {"coordinates":[9.25525,45.453308],"type":"Point"}
}