{
  "type": "Feature",
  "properties": {
    "iso:country":"IT",
    "sg:address":"90135 Palermo",
    "sg:city":"Palermo",
    "sg:orig_category":"Impermeabilizzazioni Edili - Lavori",
    "sg:phone":"+39 380 712 0238",
    "sg:postcode":"90135",
    "sg:province":"Palermo",
    "wof:name":"Giaconia Carmelo Gia.car.",
    "wof:placetype":"venue"
},
  "geometry": {"coordinates":[13.326293,38.118752],"type":"Point"}
}