{
  "type": "Feature",
  "properties": {
    "iso:country":"IT",
    "sg:address":"00149 Roma",
    "sg:city":"Roma",
    "sg:orig_category":"Automobili - Commercio",
    "sg:phone":"+39 06 5527 1101",
    "sg:postcode":"00149",
    "sg:province":"Roma",
    "wof:name":"B. R. Motors Srl",
    "wof:placetype":"venue"
},
  "geometry": {"coordinates":[12.447569,41.857853],"type":"Point"}
}