{
  "type": "Feature",
  "properties": {
    "addr:full":"2, Via Dante Alighieri 35020 Sant'angelo Di Piove Di Sacco Padova 35020",
    "addr:postcode":"35020;35020",
    "addr:street":"Via Dante Alighieri",
    "iso:country":"IT",
    "sg:address":"2, Via Dante Alighieri 35020 Sant'angelo Di Piove Di Sacco",
    "sg:classifiers":[
        {
            "category":"Shopping",
            "subcategory":"Clothing, Apparel, & Fashions",
            "type":"Retail Goods"
        }
    ],
    "sg:phone":"+39 049 970 2433",
    "sg:postcode":"35020",
    "sg:province":"Padova",
    "sg:tags":[
        "clothes"
    ],
    "wof:name":"Sartore",
    "wof:placetype":"venue"
},
  "geometry": {"coordinates":[11.948612,45.318977],"type":"Point"}
}