{
  "type": "Feature",
  "properties": {
    "addr:full":"26, Via Adamello 20010 Bareggio Bareggio Milano 20010",
    "addr:postcode":"20010;20010",
    "addr:street":"Via Adamello",
    "iso:country":"IT",
    "sg:address":"26, Via Adamello 20010 Bareggio",
    "sg:city":"Bareggio",
    "sg:classifiers":[
        {
            "category":"Shopping",
            "type":"Retail Goods"
        }
    ],
    "sg:phone":"+39 39029028618",
    "sg:postcode":"20010",
    "sg:province":"Milano",
    "sg:tags":[
        "finished",
        "-",
        "metallic"
    ],
    "wof:name":"Mollificio Berta Adamo & C. (s.r.l.)",
    "wof:placetype":"venue"
},
  "geometry": {"coordinates":[9.0189800262,45.4844703674],"type":"Point"}
}