{
  "type": "Feature",
  "properties": {
    "iso:country":"IT",
    "sg:address":"25080 Manerba Del Garda",
    "sg:city":"Manerba del Garda",
    "sg:orig_category":"Agenzie Immobiliari",
    "sg:phone":"+39 036 555 1096",
    "sg:postcode":"25080",
    "sg:province":"Brescia",
    "sg:website":"http://www.gardaffare.it",
    "wof:name":"Gardaffare",
    "wof:placetype":"venue"
},
  "geometry": {"coordinates":[10.507059,45.552288],"type":"Point"}
}