{
  "type": "Feature",
  "properties": {
    "addr:full":"33075 Cordovado Cordovado Pordenone 33075",
    "addr:postcode":"33075;33075",
    "iso:country":"IT",
    "sg:address":"33075 Cordovado",
    "sg:city":"Cordovado",
    "sg:orig_category":"Macchine, Impianti Ed Attrezzature Per Agricoltura E Zootecnia",
    "sg:phone":"+39 0434 684508",
    "sg:postcode":"33075",
    "sg:province":"Pordenone",
    "wof:name":"Tecnoterm Snc Di Baccin Eddy E Bravo Giulio",
    "wof:placetype":"venue"
},
  "geometry": {"coordinates":[12.884586,45.850594],"type":"Point"}
}