{
  "type": "Feature",
  "properties": {
    "iso:country":"IT",
    "sg:address":"Fraz Madonna Della Neve 40; Clavesana; 12060",
    "sg:city":"Clavesana",
    "sg:classifiers":[
        {
            "category":"Banks & Credit Unions",
            "subcategory":"Bank",
            "type":"Services"
        }
    ],
    "sg:phone":"+39 0173 790470",
    "sg:postcode":"12060",
    "sg:province":"Cuneo",
    "wof:name":"Banca Di Credito Cooperativo, Di Carru E Del Monregalese Scrl",
    "wof:placetype":"venue"
},
  "geometry": {"coordinates":[7.901754,44.483356],"type":"Point"}
}