{
  "type": "Feature",
  "properties": {
    "iso:country":"IT",
    "sg:address":"22, Via Dell' Artigianato 41030 Bastiglia",
    "sg:city":"Bastiglia",
    "sg:classifiers":[
        {
            "category":"Shopping",
            "subcategory":"Crafts & Fabrics",
            "type":"Retail Goods"
        }
    ],
    "sg:phone":"+39 39059904910",
    "sg:postcode":"41030",
    "sg:province":"Modena",
    "wof:name":"P Macchine S.r.l.",
    "wof:placetype":"venue"
},
  "geometry": {"coordinates":[11.0026807785,44.727180481],"type":"Point"}
}