{
  "type": "Feature",
  "properties": {
    "addr:full":"Via Gaidano 8; Torino; 10137 Torino Torino 10137",
    "addr:housenumber":"8",
    "addr:postcode":"10137;10137",
    "addr:street":"Via Gaidano",
    "iso:country":"IT",
    "sg:address":"Via Gaidano 8; Torino; 10137",
    "sg:city":"Torino",
    "sg:classifiers":[
        {
            "category":"Banks & Credit Unions",
            "subcategory":"Bank",
            "type":"Services"
        }
    ],
    "sg:phone":"+39 011 308 1123",
    "sg:postcode":"10137",
    "sg:province":"Torino",
    "wof:name":"Istituto Bancario, San Paolo Di Torino",
    "wof:placetype":"venue"
},
  "geometry": {"coordinates":[7.628206,45.038799],"type":"Point"}
}