{
  "type": "Feature",
  "properties": {
    "iso:country":"IT",
    "sg:address":"27, Via Ferrari 41043 Formigine",
    "sg:city":"Formigine",
    "sg:classifiers":[
        {
            "category":"Wholesale",
            "subcategory":"Drugs",
            "type":"Manufacturing & Wholesale Goods"
        }
    ],
    "sg:phone":"+39 39059573597",
    "sg:postcode":"41043",
    "sg:province":"Modena",
    "sg:tags":[
        "chemical",
        "pharmaceutical"
    ],
    "wof:name":"Ferro Italia Srl",
    "wof:placetype":"venue"
},
  "geometry": {"coordinates":[10.940673,44.547184],"type":"Point"}
}