{
  "type": "Feature",
  "properties": {
    "addr:full":"25, Via Tevere 51016 Montecatini Terme Pistoia 51016",
    "addr:postcode":"51016;51016",
    "addr:street":"Via Tevere",
    "iso:country":"IT",
    "sg:address":"25, Via Tevere 51016 Montecatini Terme",
    "sg:classifiers":[
        {
            "category":"Manufacturing",
            "subcategory":"Printing",
            "type":"Manufacturing & Wholesale Goods"
        }
    ],
    "sg:phone":"+39 39057292751",
    "sg:postcode":"51016",
    "sg:province":"Pistoia",
    "sg:tags":[
        "publishing"
    ],
    "wof:name":"Kartos Cart. Toscana Montecatini F. E V. Pancioli",
    "wof:placetype":"venue"
},
  "geometry": {"coordinates":[10.7709760666,43.8753623962],"type":"Point"}
}