{
  "type": "Feature",
  "properties": {
    "addr:full":"20056 Trezzo Sull'adda Milano 20056",
    "addr:postcode":"20056;20056",
    "iso:country":"IT",
    "sg:address":"20056 Trezzo Sull'adda",
    "sg:orig_category":"Prodotti E Manufatti In Materie Plastiche",
    "sg:phone":"+39 02 909 0241",
    "sg:postcode":"20056",
    "sg:province":"Milano",
    "wof:name":"Arte Plast Spa",
    "wof:placetype":"venue"
},
  "geometry": {"coordinates":[9.558848381,45.6090049744],"type":"Point"}
}