{
  "type": "Feature",
  "properties": {
    "addr:full":"13039 Trino Trino Vercelli 13039",
    "addr:housenumber":"13039",
    "addr:postcode":"13039",
    "addr:street":"Trino Trino",
    "iso:country":"IT",
    "sg:address":"13039 Trino",
    "sg:city":"Trino",
    "sg:classifiers":[
        {
            "category":"Health Services",
            "subcategory":"Health Practitioner",
            "type":"Services"
        }
    ],
    "sg:phone":"+39 0161 805624",
    "sg:postcode":"13039",
    "sg:province":"Vercelli",
    "sg:tags":[
        "medici"
    ],
    "wof:name":"Francese Fabio",
    "wof:placetype":"venue"
},
  "geometry": {"coordinates":[8.416515,45.324017],"type":"Point"}
}