{
  "type": "Feature",
  "properties": {
    "addr:full":"60030 Maiolati Spontini Maiolati Spontini Ancona 60030",
    "addr:postcode":"60030;60030",
    "iso:country":"IT",
    "sg:address":"60030 Maiolati Spontini",
    "sg:city":"Maiolati Spontini",
    "sg:orig_category":"Carta, Cartone E Prodotti Primari",
    "sg:phone":"+39 0731 703418",
    "sg:postcode":"60030",
    "sg:province":"Ancona",
    "wof:name":"So.ge.nu.s. Spa",
    "wof:placetype":"venue"
},
  "geometry": {"coordinates":[13.146426,43.518204],"type":"Point"}
}