{
  "type": "Feature",
  "properties": {
    "iso:country":"IT",
    "sg:address":"20145 Milano",
    "sg:city":"Milano",
    "sg:orig_category":"Filati E Materie Prime Tessili",
    "sg:phone":"+39 02 498 7741",
    "sg:postcode":"20145",
    "sg:province":"Milano",
    "wof:name":"Castellano & C. (s.n.c.)",
    "wof:placetype":"venue"
},
  "geometry": {"coordinates":[9.1590652466,45.4747314453],"type":"Point"}
}