{
  "type": "Feature",
  "properties": {
    "iso:country":"IT",
    "sg:address":"205, Viale Europa 50126 Firenze",
    "sg:city":"Firenze",
    "sg:classifiers":[
        {
            "category":"Travel",
            "subcategory":"Travel Agent",
            "type":"Entertainment"
        }
    ],
    "sg:phone":"+39 390 556 571",
    "sg:postcode":"50126",
    "sg:province":"Firenze",
    "sg:tags":[
        "business"
    ],
    "wof:name":"Albergo Holiday Inn",
    "wof:placetype":"venue"
},
  "geometry": {"coordinates":[11.174209,43.818306],"type":"Point"}
}