{
  "type": "Feature",
  "properties": {
    "iso:country":"IT",
    "sg:address":"Piazza Alberico 5; Barbiano; 48010",
    "sg:city":"Barbiano",
    "sg:classifiers":[
        {
            "category":"Banks & Credit Unions",
            "subcategory":"Bank",
            "type":"Services"
        }
    ],
    "sg:phone":"+39 0545 78017",
    "sg:postcode":"48010",
    "sg:province":"Ravenna",
    "wof:name":"Cassa Di Risparmio Di Lugo",
    "wof:placetype":"venue"
},
  "geometry": {"coordinates":[11.88461,44.385796],"type":"Point"}
}