{
  "type": "Feature",
  "properties": {
    "iso:country":"IT",
    "sg:address":"18015 Riva Ligure",
    "sg:city":"Riva Ligure",
    "sg:orig_category":"Macchine, Impianti Ed Attrezzature Per Agricoltura E Zootecnia",
    "sg:phone":"+39 0184 485667",
    "sg:postcode":"18015",
    "sg:province":"Imperia",
    "wof:name":"Cantolini Armando",
    "wof:placetype":"venue"
},
  "geometry": {"coordinates":[7.880796,43.838909],"type":"Point"}
}