{
  "type": "Feature",
  "properties": {
    "iso:country":"IT",
    "sg:address":"20127 Milano",
    "sg:city":"Milano",
    "sg:orig_category":"Ospedali E Servizi Sanitari. Servizi Sociali",
    "sg:phone":"+39 02 289 6729",
    "sg:postcode":"20127",
    "sg:province":"Milano",
    "wof:name":"Auser Lombardia",
    "wof:placetype":"venue"
},
  "geometry": {"coordinates":[9.219631,45.490837],"type":"Point"}
}