{
  "type": "Feature",
  "properties": {
    "iso:country":"IT",
    "sg:address":"Via Degli Artigiani 17 38057 Pergine Valsugana",
    "sg:city":"Pergine Valsugana",
    "sg:orig_category":"Felsite Porphyry",
    "sg:phone":"+39 0461 530094",
    "sg:postcode":"38057",
    "sg:province":"Trento",
    "sg:website":"www.colombinispa.it",
    "wof:name":"Colombini Spa",
    "wof:placetype":"venue"
},
  "geometry": {"coordinates":[11.208486557,46.077709198],"type":"Point"}
}