{
  "type": "Feature",
  "properties": {
    "iso:country":"IT",
    "sg:address":"09134 Pirri",
    "sg:orig_category":"Imprese Di Costruzioni Civili Ed Industriali",
    "sg:phone":"+39 070 554230",
    "sg:postcode":"09134",
    "sg:province":"Cagliari",
    "wof:name":"S.i.ge. Societa' Interventi Generali Srl",
    "wof:placetype":"venue"
},
  "geometry": {"coordinates":[9.121664,39.242554],"type":"Point"}
}