{
  "type": "Feature",
  "properties": {
    "iso:country":"IT",
    "sg:address":"84018 Scafati",
    "sg:city":"Scafati",
    "sg:orig_category":"Carta, Cartone E Prodotti Primari. Forniture E Materiali Per Imballaggio E Confezionamento",
    "sg:phone":"+39 081 856 3339",
    "sg:postcode":"84018",
    "sg:province":"Salerno",
    "wof:name":"Cartotecnica Scafatese Di Malafronte & C. Sas",
    "wof:placetype":"venue"
},
  "geometry": {"coordinates":[14.533921,40.759338],"type":"Point"}
}