{
  "type": "Feature",
  "properties": {
    "addr:full":"24042 Capriate San Gervasio Capriate San Gervasio Bergamo 24042",
    "addr:housenumber":"24042",
    "addr:postcode":"24042",
    "addr:street":"Capriate",
    "iso:country":"IT",
    "sg:address":"24042 Capriate San Gervasio",
    "sg:city":"Capriate San Gervasio",
    "sg:orig_category":"Tessuti E Stoffe",
    "sg:phone":"+39 02 9098 0106",
    "sg:postcode":"24042",
    "sg:province":"Bergamo",
    "wof:name":"Fillattice Spa",
    "wof:placetype":"venue"
},
  "geometry": {"coordinates":[9.54681,45.577465],"type":"Point"}
}