{
  "type": "Feature",
  "properties": {
    "iso:country":"IT",
    "sg:address":"40137 Bologna",
    "sg:city":"Bologna",
    "sg:orig_category":"Agenzie Di Spettacolo E Di Animazione",
    "sg:phone":"+39 051 444299",
    "sg:postcode":"40137",
    "sg:province":"Bologna",
    "sg:website":"http://www.artscena.it",
    "wof:name":"Antini La Valle Anna Maria",
    "wof:placetype":"venue"
},
  "geometry": {"coordinates":[11.365088,44.478996],"type":"Point"}
}