{
  "type": "Feature",
  "properties": {
    "iso:country":"IT",
    "sg:address":"21013 Gallarate",
    "sg:city":"Gallarate",
    "sg:orig_category":"Antenne Radio-televisione",
    "sg:phone":"+39 0331 793327",
    "sg:postcode":"21013",
    "sg:province":"Varese",
    "wof:name":"Pioppi Adriano & C. Sas",
    "wof:placetype":"venue"
},
  "geometry": {"coordinates":[8.782642,45.658413],"type":"Point"}
}