{
  "type": "Feature",
  "properties": {
    "iso:country":"IT",
    "sg:address":"25018 Montichiari",
    "sg:city":"Montichiari",
    "sg:orig_category":"Bronzo",
    "sg:phone":"+39 030 962051",
    "sg:postcode":"25018",
    "sg:province":"Brescia",
    "wof:name":"Boa Srl",
    "wof:placetype":"venue"
},
  "geometry": {"coordinates":[10.367213,45.413536],"type":"Point"}
}