{
  "type": "Feature",
  "properties": {
    "iso:country":"IT",
    "sg:address":"6, V. Primo Levi 25018 Montichiari",
    "sg:city":"Montichiari",
    "sg:classifiers":[
        {
            "category":"Autos & Motor Vehicles",
            "subcategory":"Automobile Sales",
            "type":"Retail Goods"
        }
    ],
    "sg:phone":"+39 030 965 4811",
    "sg:postcode":"25018",
    "sg:province":"Brescia",
    "sg:tags":[
        "industrial"
    ],
    "sg:website":"http://www.pezzaioli.it",
    "wof:name":"Carrozzeria Pezzaioli Srl",
    "wof:placetype":"venue"
},
  "geometry": {"coordinates":[10.363299,45.426056],"type":"Point"}
}