{
  "type": "Feature",
  "properties": {
    "iso:country":"IT",
    "sg:address":"24069 Trescore Balneario",
    "sg:city":"Trescore Balneario",
    "sg:orig_category":"Animali Domestici - Allevamento E Addestramento",
    "sg:phone":"+39 035 425 8415",
    "sg:postcode":"24069",
    "sg:province":"Bergamo",
    "wof:name":"Val Del Tiglio Di Sommi Carmela",
    "wof:placetype":"venue"
},
  "geometry": {"coordinates":[9.842226,45.686016],"type":"Point"}
}