{
  "type": "Feature",
  "properties": {
    "iso:country":"IT",
    "sg:address":"20124 Milano",
    "sg:city":"Milano",
    "sg:orig_category":"Valvole E Apparecchiature Di Misura. Attrezzature E Forniture Per Officine Riparazione E Servizi Ausiliari. Macchine, Strumenti Ed Apparecchi Per Attivita' Industriali",
    "sg:phone":"+39 02 669 3535",
    "sg:postcode":"20124",
    "sg:province":"Milano",
    "wof:name":"Digital Test Italia S.r.l.",
    "wof:placetype":"venue"
},
  "geometry": {"coordinates":[9.196966,45.489193],"type":"Point"}
}