{
  "type": "Feature",
  "properties": {
    "iso:country":"IT",
    "sg:address":"Via Della Masolina 22 10040 Piobesi Torinese",
    "sg:city":"Piobesi Torinese",
    "sg:classifiers":[
        {
            "category":"Wholesale",
            "subcategory":"Electrical",
            "type":"Manufacturing & Wholesale Goods"
        }
    ],
    "sg:phone":"+39 011 965 0108",
    "sg:postcode":"10040",
    "sg:province":"Torino",
    "sg:tags":[
        "component"
    ],
    "sg:website":"www.elstarsrl.com",
    "wof:name":"Elstar S.r.l.",
    "wof:placetype":"venue"
},
  "geometry": {"coordinates":[7.624651,44.933666],"type":"Point"}
}