{
  "type": "Feature",
  "properties": {
    "addr:full":"9, Via Vagliasindi Gustavo 95126 Catania Catania Catania 95126",
    "addr:postcode":"95126;95126",
    "addr:street":"Via Vagliasindi Gustavo",
    "iso:country":"IT",
    "sg:address":"9, Via Vagliasindi Gustavo 95126 Catania",
    "sg:city":"Catania",
    "sg:classifiers":[
        {
            "category":"Professional",
            "subcategory":"Printing & Photocopies",
            "type":"Services"
        }
    ],
    "sg:phone":"+39 39095448626",
    "sg:postcode":"95126",
    "sg:province":"Catania",
    "wof:name":"Delta Impianti S.r.l.",
    "wof:placetype":"venue"
},
  "geometry": {"coordinates":[15.0952997208,37.5236473083],"type":"Point"}
}