{
  "type": "Feature",
  "properties": {
    "addr:full":"36043 Camisano Vicentino Camisano Vicentino Vicenza 36043",
    "addr:postcode":"36043;36043",
    "addr:street":"Vicentino",
    "iso:country":"IT",
    "sg:address":"36043 Camisano Vicentino",
    "sg:city":"Camisano Vicentino",
    "sg:orig_category":"Forniture Per Edilizia E Lavori Pubblici",
    "sg:phone":"+39 348 603 9468",
    "sg:postcode":"36043",
    "sg:province":"Vicenza",
    "wof:name":"Paat Di Paccagnella Attilio",
    "wof:placetype":"venue"
},
  "geometry": {"coordinates":[11.652923584,45.5739479065],"type":"Point"}
}