{
  "type": "Feature",
  "properties": {
    "addr:full":"Via Dei Volsci 154 04100 Latina Latina Latina 04100",
    "addr:housenumber":"154",
    "addr:postcode":"04100;04100",
    "addr:street":"Via Dei Volsci",
    "iso:country":"IT",
    "sg:address":"Via Dei Volsci 154 04100 Latina",
    "sg:city":"Latina",
    "sg:classifiers":[
        {
            "category":"Home & Garden",
            "subcategory":"Building Materials",
            "type":"Retail Goods"
        }
    ],
    "sg:phone":"+39 0773 660999",
    "sg:postcode":"04100",
    "sg:province":"Latina",
    "sg:tags":[
        "door",
        "housing",
        "safety"
    ],
    "sg:website":"www.sekat.it",
    "wof:name":"Sekat Srl",
    "wof:placetype":"venue"
},
  "geometry": {"coordinates":[12.909445,41.543056],"type":"Point"}
}