{
  "type": "Feature",
  "properties": {
    "iso:country":"IT",
    "sg:address":"2, Via Vittorio Veneto 35020 Albignasego",
    "sg:city":"Albignasego",
    "sg:classifiers":[
        {
            "category":"Personal",
            "subcategory":"Shoe Repair & Shine",
            "type":"Services"
        }
    ],
    "sg:phone":"+39 39049710336",
    "sg:postcode":"35020",
    "sg:province":"Padova",
    "sg:tags":[
        "leather"
    ],
    "wof:name":"Miramare S.r.l.",
    "wof:placetype":"venue"
},
  "geometry": {"coordinates":[11.865723,45.34837],"type":"Point"}
}