{
  "type": "Feature",
  "properties": {
    "iso:country":"IT",
    "sg:address":"15, Via Lusanna 10087 Valperga",
    "sg:city":"Valperga",
    "sg:classifiers":[
        {
            "category":"Professional",
            "subcategory":"Engineering",
            "type":"Services"
        }
    ],
    "sg:phone":"+39 0124 617305",
    "sg:postcode":"10087",
    "sg:province":"Torino",
    "sg:tags":[
        "machine",
        "-",
        "mechanical"
    ],
    "wof:name":"Italmec",
    "wof:placetype":"venue"
},
  "geometry": {"coordinates":[7.656725,45.377956],"type":"Point"}
}