{
  "type": "Feature",
  "properties": {
    "addr:full":"41100 Modena Modena Modena 41100",
    "addr:postcode":"41100;41100",
    "iso:country":"IT",
    "sg:address":"41100 Modena",
    "sg:city":"Modena",
    "sg:orig_category":"Pubblicita', Marketing E Comunicazione",
    "sg:phone":"+39 059 284330",
    "sg:postcode":"41100",
    "sg:province":"Modena",
    "sg:website":"http://www.gigliotti-group.com",
    "wof:name":"Gigliotti Group Srl",
    "wof:placetype":"venue"
},
  "geometry": {"coordinates":[10.9645795822,44.6305198669],"type":"Point"}
}