{
  "type": "Feature",
  "properties": {
    "iso:country":"IT",
    "sg:address":"Strada Della Selva Grossa 61100 Pesaro",
    "sg:city":"Pesaro",
    "sg:classifiers":[
        {
            "category":"Shopping",
            "subcategory":"Computers & Home Electronics",
            "type":"Retail Goods"
        }
    ],
    "sg:phone":"+39 0721 202850",
    "sg:postcode":"61100",
    "sg:province":"Pesaro E Urbino",
    "sg:tags":[
        "electronic",
        "electrical",
        "equipment"
    ],
    "wof:name":"Cabi Srl",
    "wof:placetype":"venue"
},
  "geometry": {"coordinates":[12.822898,43.883766],"type":"Point"}
}