{
  "type": "Feature",
  "properties": {
    "iso:country":"IT",
    "sg:address":"15067 Novi Ligure",
    "sg:city":"Novi Ligure",
    "sg:classifiers":[
        {
            "category":"Communications",
            "subcategory":"Film & Video Production",
            "type":"Services"
        }
    ],
    "sg:phone":"+39 0143 2731",
    "sg:postcode":"15067",
    "sg:province":"Alessandria",
    "sg:tags":[
        "supply",
        "cinema",
        "instruments",
        "medical-health",
        "cameras",
        "equipment",
        "orthopedic",
        "products",
        "systems",
        "health",
        "optical",
        "hospital"
    ],
    "wof:name":"Pastorelli Ottico - Optometrista Di M. Pastorelli & C. Sas",
    "wof:placetype":"venue"
},
  "geometry": {"coordinates":[8.787167,44.761768],"type":"Point"}
}