{
  "type": "Feature",
  "properties": {
    "addr:full":"37021 Bosco Chiesanuova Bosco Chiesanuova Verona 37021",
    "addr:postcode":"37021;37021",
    "iso:country":"IT",
    "sg:address":"37021 Bosco Chiesanuova",
    "sg:city":"Bosco Chiesanuova",
    "sg:orig_category":"Servizi Per Lo Sport E Il Tempo Libero. Servizi Al Turismo",
    "sg:phone":"+39 045 678 4001",
    "sg:postcode":"37021",
    "sg:province":"Verona",
    "wof:name":"Seggiovia Malga San Giorgio",
    "wof:placetype":"venue"
},
  "geometry": {"coordinates":[11.044022,45.645218],"type":"Point"}
}