{
  "type": "Feature",
  "properties": {
    "iso:country":"IT",
    "sg:address":"20134 Milano",
    "sg:city":"Milano",
    "sg:orig_category":"Servizi E Lavori Industria Chimica. Riparazione Dei Mezzi Di Trasporto",
    "sg:phone":"+39 02 215 1595",
    "sg:postcode":"20134",
    "sg:province":"Milano",
    "sg:website":"http://www.polastri.it",
    "wof:name":"Verniciatura Polastri Srl",
    "wof:placetype":"venue"
},
  "geometry": {"coordinates":[9.247256,45.48185],"type":"Point"}
}