{
  "type": "Feature",
  "properties": {
    "iso:country":"IT",
    "sg:address":"28040 Varallo Pombia",
    "sg:city":"Varallo Pombia",
    "sg:orig_category":"Profilati Ferro E Acciaio",
    "sg:phone":"+39 0321 921231",
    "sg:postcode":"28040",
    "sg:province":"Novara",
    "wof:name":"G.b.n. Profili Speciali Srl",
    "wof:placetype":"venue"
},
  "geometry": {"coordinates":[8.617058754,45.6733169556],"type":"Point"}
}