{
  "type": "Feature",
  "properties": {
    "addr:full":"20, Via Della Commenda 20122 Milano Milano Milano 20122",
    "addr:postcode":"20122;20122",
    "addr:street":"Via Della Commenda",
    "iso:country":"IT",
    "sg:address":"20, Via Della Commenda 20122 Milano",
    "sg:city":"Milano",
    "sg:classifiers":[
        {
            "category":"Shopping",
            "subcategory":"Jewelry",
            "type":"Retail Goods"
        }
    ],
    "sg:phone":"+39 39025511093",
    "sg:postcode":"20122",
    "sg:province":"Milano",
    "sg:tags":[
        "jewellery"
    ],
    "wof:name":"Scarabeo (s.r.l.)",
    "wof:placetype":"venue"
},
  "geometry": {"coordinates":[9.199196,45.456448],"type":"Point"}
}