{
  "type": "Feature",
  "properties": {
    "iso:country":"IT",
    "sg:address":"Via Silvio Pellico 28/1, 65100 Pescara, Pe",
    "sg:classifiers":[
        {
            "category":"Banks & Credit Unions",
            "subcategory":"Bank",
            "type":"Services"
        }
    ],
    "wof:name":"Fira Spa",
    "wof:placetype":"venue"
},
  "geometry": {"coordinates":[14.202839,42.474606],"type":"Point"}
}