{
  "type": "Feature",
  "properties": {
    "iso:country":"IT",
    "sg:address":"21040 Venegono Inferiore",
    "sg:city":"Venegono Inferiore",
    "sg:classifiers":[
        {
            "category":"Building & Trades",
            "subcategory":"Construction",
            "type":"Services"
        }
    ],
    "sg:phone":"+39 0331 866587",
    "sg:postcode":"21040",
    "sg:province":"Varese",
    "sg:tags":[
        "industry",
        "work",
        "plastic"
    ],
    "sg:website":"http://www.emmepiplast.it",
    "wof:name":"Emmepi Plast Srl",
    "wof:placetype":"venue"
},
  "geometry": {"coordinates":[8.9006137848,45.7379150391],"type":"Point"}
}