{
  "type": "Feature",
  "properties": {
    "addr:full":"Via Dottor Adolfo Terzi 16 25080 Nuvolento Nuvolento Brescia 25080",
    "addr:housenumber":"16",
    "addr:postcode":"25080;25080",
    "addr:street":"Via Dottor Adolfo Terzi",
    "iso:country":"IT",
    "sg:address":"Via Dottor Adolfo Terzi 16 25080 Nuvolento",
    "sg:city":"Nuvolento",
    "sg:classifiers":[
        {
            "category":"Bars & Pubs",
            "subcategory":"Sports Bar",
            "type":"Food & Drink"
        }
    ],
    "sg:phone":"+39 030 691487",
    "sg:postcode":"25080",
    "sg:province":"Brescia",
    "sg:tags":[
        "dy",
        "forging"
    ],
    "sg:website":"www.alto.it",
    "wof:name":"Alto Srl",
    "wof:placetype":"venue"
},
  "geometry": {"coordinates":[10.3966913223,45.5456886292],"type":"Point"}
}