{
  "type": "Feature",
  "properties": {
    "iso:country":"IT",
    "sg:address":"7, Via Dell' Industria 47832 San Clemente",
    "sg:city":"San Clemente",
    "sg:classifiers":[
        {
            "category":"Home & Garden",
            "subcategory":"Home Furnishings",
            "type":"Retail Goods"
        }
    ],
    "sg:phone":"+39 0541 987940",
    "sg:postcode":"47832",
    "sg:province":"Rimini",
    "sg:tags":[
        "household"
    ],
    "wof:name":"T.s. Di Tienforti Elvino & C. (s.n.c.)",
    "wof:placetype":"venue"
},
  "geometry": {"coordinates":[12.639709,43.977371],"type":"Point"}
}