{
  "type": "Feature",
  "properties": {
    "iso:country":"IT",
    "sg:address":"00156 Roma",
    "sg:city":"Roma",
    "sg:orig_category":"Servizi Ausiliari Di Analisi, Controllo E Ricerca",
    "sg:phone":"+39 06 411 5109",
    "sg:postcode":"00156",
    "sg:province":"Roma",
    "wof:name":"Laboconsult Srl",
    "wof:placetype":"venue"
},
  "geometry": {"coordinates":[12.583927,41.935448],"type":"Point"}
}