{
  "type": "Feature",
  "properties": {
    "iso:country":"IT",
    "sg:address":"37066 Sommacampagna",
    "sg:city":"Sommacampagna",
    "sg:orig_category":"Prodotti Alimentari. Agricoltura, Orticoltura E Floricoltura",
    "sg:phone":"+39 045 896 0355",
    "sg:postcode":"37066",
    "sg:province":"Verona",
    "wof:name":"Merlini Riccardo S.p.a.",
    "wof:placetype":"venue"
},
  "geometry": {"coordinates":[10.8698587418,45.4502983093],"type":"Point"}
}