{
  "type": "Feature",
  "properties": {
    "iso:country":"IT",
    "sg:address":"88, Via Emilia Est 41013 Castelfranco Emilia",
    "sg:city":"Castelfranco Emilia",
    "sg:classifiers":[
        {
            "category":"Food & Beverages",
            "subcategory":"Dairy",
            "type":"Retail Goods"
        }
    ],
    "sg:phone":"+39 39059924104",
    "sg:postcode":"41013",
    "sg:province":"Modena",
    "sg:tags":[
        "product"
    ],
    "wof:name":"Gra - Com (s.r.l.)",
    "wof:placetype":"venue"
},
  "geometry": {"coordinates":[10.973092,44.626823],"type":"Point"}
}