{
  "type": "Feature",
  "properties": {
    "addr:full":"10156 Torino Torino Torino 10156",
    "addr:postcode":"10156;10156",
    "iso:country":"IT",
    "sg:address":"10156 Torino",
    "sg:city":"Torino",
    "sg:classifiers":[
        {
            "category":"Manufacturing",
            "subcategory":"Tools & Machinery",
            "type":"Manufacturing & Wholesale Goods"
        }
    ],
    "sg:phone":"+39 011 262 9054",
    "sg:postcode":"10156",
    "sg:province":"Torino",
    "sg:tags":[
        "machine",
        "livestock",
        "industry",
        "system",
        "chemical",
        "equipment",
        "breeding",
        "agriculture"
    ],
    "wof:name":"Industrial Service",
    "wof:placetype":"venue"
},
  "geometry": {"coordinates":[7.718673,45.121178],"type":"Point"}
}