{
  "type": "Feature",
  "properties": {
    "iso:country":"IT",
    "sg:address":"50121 Firenze",
    "sg:city":"Firenze",
    "sg:orig_category":"Abbigliamento Esterno, Maglierie E Pelliccerie. Forniture Per Il Settore Dello Spettacolo",
    "sg:phone":"+39 055 247 9742",
    "sg:postcode":"50121",
    "sg:province":"Firenze",
    "wof:name":"Casa D'arte Cerratelli (s.r.l.)",
    "wof:placetype":"venue"
},
  "geometry": {"coordinates":[11.262223,43.774338],"type":"Point"}
}