{
  "type": "Feature",
  "properties": {
    "iso:country":"IT",
    "sg:address":"10098 Rivoli",
    "sg:city":"Rivoli",
    "sg:orig_category":"Aspiratori",
    "sg:phone":"+39 011 959 1601",
    "sg:postcode":"10098",
    "sg:province":"Torino",
    "sg:website":"http://www.savioclima.it",
    "wof:name":"Savio Spa",
    "wof:placetype":"venue"
},
  "geometry": {"coordinates":[7.5552725792,45.0608329773],"type":"Point"}
}