{
  "type": "Feature",
  "properties": {
    "addr:full":"18, Via S. Francesco 45010 Ceregnano Ceregnano Rovigo 45010",
    "addr:postcode":"45010;45010",
    "addr:street":"Via S. Francesco",
    "iso:country":"IT",
    "sg:address":"18, Via S. Francesco 45010 Ceregnano",
    "sg:city":"Ceregnano",
    "sg:classifiers":[
        {
            "category":"Real Estate",
            "subcategory":"Architect",
            "type":"Services"
        }
    ],
    "sg:phone":"+39 0425 937117",
    "sg:postcode":"45010",
    "sg:province":"Rovigo",
    "sg:tags":[
        "textile",
        "clothing"
    ],
    "wof:name":"Confezioni Amalia",
    "wof:placetype":"venue"
},
  "geometry": {"coordinates":[11.904773,45.051788],"type":"Point"}
}