{
  "type": "Feature",
  "properties": {
    "addr:full":"89062 Lazzaro Motta San Giovanni Lazzaro Reggio Di Calabria 89062",
    "addr:postcode":"89062;motta;89062",
    "addr:street":"Lazzaro;San Giovanni Lazzaro",
    "iso:country":"IT",
    "sg:address":"89062 Lazzaro Motta San Giovanni",
    "sg:city":"Lazzaro",
    "sg:orig_category":"Macchine E Forniture Per Ecologia E Smaltimento Rifiuti",
    "sg:phone":"+39 0965 714268",
    "sg:postcode":"89062",
    "sg:province":"Reggio Di Calabria",
    "sg:website":"http://ecoservices.interfree.it",
    "wof:name":"Ecoservices Srl",
    "wof:placetype":"venue"
},
  "geometry": {"coordinates":[15.666759,37.972847],"type":"Point"}
}