{
  "type": "Feature",
  "properties": {
    "iso:country":"IT",
    "sg:address":"Via Gioberti 1 33010 Tavagnacco",
    "sg:city":"Tavagnacco",
    "sg:classifiers":[
        {
            "category":"Military Area",
            "subcategory":"Air Force Base",
            "type":"Public Place"
        }
    ],
    "sg:phone":"+39 0432 571761",
    "sg:postcode":"33010",
    "sg:province":"Udine",
    "sg:tags":[
        "absorption",
        "chiller"
    ],
    "sg:website":"www.satif.it",
    "wof:name":"S.a.t.i.f. Snc",
    "wof:placetype":"venue"
},
  "geometry": {"coordinates":[13.21937,46.100113],"type":"Point"}
}