{
  "type": "Feature",
  "properties": {
    "iso:country":"IT",
    "sg:address":"61025 Montelabbate",
    "sg:city":"Montelabbate",
    "sg:orig_category":"Termotecnica E Riscaldamento, Apparecchiature E Servizi",
    "sg:phone":"+39 0721 498822",
    "sg:postcode":"61025",
    "sg:province":"Pesaro E Urbino",
    "sg:website":"http://www.radiant.it",
    "wof:name":"Radiant Bruciatori Spa",
    "wof:placetype":"venue"
},
  "geometry": {"coordinates":[12.791933,43.861137],"type":"Point"}
}