{
  "type": "Feature",
  "properties": {
    "addr:full":"00192 Roma Roma Roma 00192",
    "addr:postcode":"00192;00192",
    "iso:country":"IT",
    "sg:address":"00192 Roma",
    "sg:city":"Roma",
    "sg:orig_category":"Medici. Assicurazioni E Servizi Assicurativi. Avvocati, Notai E Servizi Legali. Professionisti - Studi E Servizi Ed Associazioni Di Interesse Aziendale",
    "sg:phone":"+39 06 3974 2284",
    "sg:postcode":"00192",
    "sg:province":"Roma",
    "wof:name":"Bartoloni Piero",
    "wof:placetype":"venue"
},
  "geometry": {"coordinates":[12.4564247131,41.9106407166],"type":"Point"}
}