{
  "type": "Feature",
  "properties": {
    "iso:country":"IT",
    "sg:address":"Molo A 30135 Venezia",
    "sg:city":"Venezia",
    "sg:classifiers":[
        {
            "category":"Banks & Credit Unions",
            "subcategory":"Investment Brokerage",
            "type":"Services"
        }
    ],
    "sg:phone":"+39 39041937441",
    "sg:postcode":"30135",
    "sg:province":"Venezia",
    "sg:tags":[
        "-",
        "transport",
        "related"
    ],
    "wof:name":"Tecnospedas Di Bonomo R. E Vespier B. (s.n.c.)",
    "wof:placetype":"venue"
},
  "geometry": {"coordinates":[12.338609,45.434128],"type":"Point"}
}