{
  "type": "Feature",
  "properties": {
    "iso:country":"IT",
    "sg:address":"26012 Castelleone",
    "sg:city":"Castelleone",
    "sg:orig_category":"Prodotti Di Base E Forniture Per Industria Alimentare E Bevande",
    "sg:phone":"+39 0374 359884",
    "sg:postcode":"26012",
    "sg:province":"Cremona",
    "wof:name":"Salvaggio Giovanni",
    "wof:placetype":"venue"
},
  "geometry": {"coordinates":[9.7669229507,45.2865447998],"type":"Point"}
}