{
  "type": "Feature",
  "properties": {
    "iso:country":"IT",
    "sg:address":"Via Pirelli 2 73011 Alezio",
    "sg:city":"Alezio",
    "sg:orig_category":"Ladies' Shoes",
    "sg:phone":"+39 0833 284042",
    "sg:postcode":"73011",
    "sg:province":"Lecce",
    "sg:website":"www.ars-calzature.com",
    "wof:name":"Ars S.r.l. Industria Calzature",
    "wof:placetype":"venue"
},
  "geometry": {"coordinates":[18.052691,40.067108],"type":"Point"}
}