{
  "type": "Feature",
  "properties": {
    "iso:country":"IT",
    "sg:address":"Via Senese 58100 Grosseto",
    "sg:city":"Grosseto",
    "sg:classifiers":[
        {
            "category":"Travel",
            "subcategory":"Travel Agent",
            "type":"Entertainment"
        }
    ],
    "sg:phone":"+39 0564 453833",
    "sg:postcode":"58100",
    "sg:province":"Grosseto",
    "sg:tags":[
        "business"
    ],
    "wof:name":"Hotel Granduca",
    "wof:placetype":"venue"
},
  "geometry": {"coordinates":[11.127049,42.784088],"type":"Point"}
}