{
  "type": "Feature",
  "properties": {
    "addr:full":"00198 Roma Roma Roma 00198",
    "addr:postcode":"00198;00198",
    "iso:country":"IT",
    "sg:address":"00198 Roma",
    "sg:city":"Roma",
    "sg:orig_category":"Servizi Al Turismo. Trasporto Pubblico E Privato. Acqua, Luce, Gas E Societa' Di Esercizio Pubblico. Pubblica Amministrazione",
    "sg:phone":"+39 06 852181",
    "sg:postcode":"00198",
    "sg:province":"Roma",
    "wof:name":"Trenitalia Spa Divisione Cargo",
    "wof:placetype":"venue"
},
  "geometry": {"coordinates":[12.501435,41.911674],"type":"Point"}
}