{
  "type": "Feature",
  "properties": {
    "iso:country":"IT",
    "sg:address":"25, Via Maggiora Guido 14100 Asti",
    "sg:city":"Asti",
    "sg:classifiers":[
        {
            "category":"Banks & Credit Unions",
            "subcategory":"Investment Brokerage",
            "type":"Services"
        }
    ],
    "sg:phone":"+39 0141 274645",
    "sg:postcode":"14100",
    "sg:province":"Asti",
    "sg:tags":[
        "-",
        "transport",
        "related"
    ],
    "wof:name":"Maggiora Guido S.r.l.",
    "wof:placetype":"venue"
},
  "geometry": {"coordinates":[8.206813,44.900864],"type":"Point"}
}