{
  "type": "Feature",
  "properties": {
    "iso:country":"IT",
    "sg:address":"59013 Montemurlo",
    "sg:city":"Montemurlo",
    "sg:orig_category":"Materiali Semilavorati Metallici",
    "sg:phone":"+39 0574 653283",
    "sg:postcode":"59013",
    "sg:province":"Prato",
    "wof:name":"Cipriani Snc Di Cipriani Marco E C.",
    "wof:placetype":"venue"
},
  "geometry": {"coordinates":[11.058475,43.908226],"type":"Point"}
}