{
  "type": "Feature",
  "properties": {
    "iso:country":"IT",
    "sg:address":"70010 Casamassima",
    "sg:city":"Casamassima",
    "sg:orig_category":"Tappeti",
    "sg:phone":"+39 080 697 7257",
    "sg:postcode":"70010",
    "sg:province":"Bari",
    "wof:name":"Safra Di Sarda Francesca Paola",
    "wof:placetype":"venue"
},
  "geometry": {"coordinates":[16.918135,40.955307],"type":"Point"}
}