{
  "type": "Feature",
  "properties": {
    "addr:full":"Via Malpighi Marcello 8 48022 Lugo Lugo Ravenna 48022",
    "addr:housenumber":"8",
    "addr:postcode":"48022;48022",
    "addr:street":"Via Malpighi Marcello",
    "iso:country":"IT",
    "sg:address":"Via Malpighi Marcello 8 48022 Lugo",
    "sg:city":"Lugo",
    "sg:classifiers":[
        {
            "category":"Manufacturing",
            "subcategory":"Tools & Machinery",
            "type":"Manufacturing & Wholesale Goods"
        }
    ],
    "sg:phone":"+39 0545 287665",
    "sg:postcode":"48022",
    "sg:province":"Ravenna",
    "sg:tags":[
        "diamond"
    ],
    "sg:website":"www.diamut.com",
    "wof:name":"Biesse Spa Utensili Unita Produttiv A Diamut",
    "wof:placetype":"venue"
},
  "geometry": {"coordinates":[12.196571,44.41573],"type":"Point"}
}