{
  "type": "Feature",
  "properties": {
    "addr:full":"25034 Orzinuovi Orzinuovi Brescia 25034",
    "addr:postcode":"25034;25034",
    "iso:country":"IT",
    "sg:address":"25034 Orzinuovi",
    "sg:city":"Orzinuovi",
    "sg:orig_category":"Ospedali E Servizi Sanitari",
    "sg:phone":"+39 030 943249",
    "sg:postcode":"25034",
    "sg:province":"Brescia",
    "wof:name":"Neri Patrizio",
    "wof:placetype":"venue"
},
  "geometry": {"coordinates":[9.9281177521,45.4005737305],"type":"Point"}
}