{
  "type": "Feature",
  "properties": {
    "iso:country":"IT",
    "sg:address":"20121 Milano",
    "sg:city":"Milano",
    "sg:orig_category":"Servizi Ausiliari Di Analisi, Controllo E Ricerca",
    "sg:phone":"+39 02 861089",
    "sg:postcode":"20121",
    "sg:province":"Milano",
    "wof:name":"Istituto Superiore Di Sociologia",
    "wof:placetype":"venue"
},
  "geometry": {"coordinates":[9.180479,45.468475],"type":"Point"}
}