{
  "type": "Feature",
  "properties": {
    "iso:country":"IT",
    "sg:address":"Via Boccaccio Sn 73010 Arnesano",
    "sg:city":"Arnesano",
    "sg:classifiers":[
        {
            "category":"Personal",
            "subcategory":"Shoe Repair & Shine",
            "type":"Services"
        }
    ],
    "sg:phone":"+39 0832 321866",
    "sg:postcode":"73010",
    "sg:province":"Lecce",
    "sg:tags":[
        "men's",
        "sock"
    ],
    "wof:name":"Osiris Di Alberani Giuseppe & C. S.n.c.",
    "wof:placetype":"venue"
},
  "geometry": {"coordinates":[18.1740150452,40.3532905579],"type":"Point"}
}