{
  "type": "Feature",
  "properties": {
    "addr:full":"219, Via S. Orsola 25135 Brescia Brescia Brescia 25135",
    "addr:housenumber":"219",
    "addr:postcode":"25135;25135",
    "addr:street":"Via S. Orsola",
    "iso:country":"IT",
    "sg:address":"219, Via S. Orsola 25135 Brescia",
    "sg:city":"Brescia",
    "sg:classifiers":[
        {
            "category":"Shopping",
            "subcategory":"Clothing, Apparel, & Fashions",
            "type":"Retail Goods"
        }
    ],
    "sg:phone":"+39 030 219 0838",
    "sg:postcode":"25135",
    "sg:province":"Brescia",
    "sg:tags":[
        "clothes"
    ],
    "wof:name":"Calzificio Busi Egidio & C. (s.a.s.)",
    "wof:placetype":"venue"
},
  "geometry": {"coordinates":[10.222958,45.539829],"type":"Point"}
}