{
  "type": "Feature",
  "properties": {
    "addr:full":"09034 Villasor Villasor Cagliari 09034",
    "addr:postcode":"09034;09034",
    "iso:country":"IT",
    "sg:address":"09034 Villasor",
    "sg:city":"Villasor",
    "sg:orig_category":"Ferramenta - Vendita Al Dettaglio",
    "sg:phone":"+39 070 964 8977",
    "sg:postcode":"09034",
    "sg:province":"Cagliari",
    "wof:name":"Edil Point Di Feurra Ignazio",
    "wof:placetype":"venue"
},
  "geometry": {"coordinates":[8.9907016754,39.2919006348],"type":"Point"}
}