{
  "type": "Feature",
  "properties": {
    "iso:country":"IT",
    "sg:address":"Via Valle Ponzema Loc. Rolla 16013 Campoligure",
    "sg:classifiers":[
        {
            "category":"Manufacturing",
            "subcategory":"Rubber & Plastics",
            "type":"Manufacturing & Wholesale Goods"
        }
    ],
    "sg:phone":"+39 39010921115",
    "sg:postcode":"16013",
    "sg:province":"Genova",
    "wof:name":"Invat (s.r.l.)",
    "wof:placetype":"venue"
},
  "geometry": {"coordinates":[8.9339885712,44.4070625305],"type":"Point"}
}