{
  "type": "Feature",
  "properties": {
    "iso:country":"IT",
    "sg:address":"Viale Monte Grappa 14 20124 Milano",
    "sg:city":"Milano",
    "sg:orig_category":"Welding Current Generators",
    "sg:phone":"+39 02 2900 3196",
    "sg:postcode":"20124",
    "sg:province":"Milano",
    "sg:website":"www.aetron.it",
    "wof:name":"Aetron Applicazioni Elettroniche Srl",
    "wof:placetype":"venue"
},
  "geometry": {"coordinates":[9.189232,45.480831],"type":"Point"}
}