{
  "type": "Feature",
  "properties": {
    "iso:country":"IT",
    "sg:address":"36015 Schio",
    "sg:city":"Schio",
    "sg:orig_category":"Insegne Luminose",
    "sg:phone":"+39 0445 575357",
    "sg:postcode":"36015",
    "sg:province":"Vicenza",
    "wof:name":"Iltras Snc",
    "wof:placetype":"venue"
},
  "geometry": {"coordinates":[11.54653,45.572327],"type":"Point"}
}