{
  "type": "Feature",
  "properties": {
    "iso:country":"IT",
    "sg:address":"20095 Cusano Milanino",
    "sg:city":"Cusano Milanino",
    "sg:orig_category":"Climatizzazione E Condizionamento, Apparecchiature E Servizi",
    "sg:phone":"+39 02 6640 3282",
    "sg:postcode":"20095",
    "sg:province":"Milano",
    "wof:name":"Emmedue Di Campanelli Adele E Giuseppina",
    "wof:placetype":"venue"
},
  "geometry": {"coordinates":[9.174576,45.552074],"type":"Point"}
}