{
  "type": "Feature",
  "properties": {
    "iso:country":"IT",
    "sg:address":"20151 Milano",
    "sg:city":"Milano",
    "sg:orig_category":"Macchine Utensili E Impianti",
    "sg:phone":"+39 02 3800 2400",
    "sg:postcode":"20151",
    "sg:province":"Milano",
    "wof:name":"Sogemi (s.r.l.)",
    "wof:placetype":"venue"
},
  "geometry": {"coordinates":[9.115582,45.487705],"type":"Point"}
}