{
  "type": "Feature",
  "properties": {
    "iso:country":"IT",
    "sg:address":"25030 Castelcovati",
    "sg:city":"Castelcovati",
    "sg:orig_category":"Saldatura - Materiali",
    "sg:phone":"+39 030 708 0300",
    "sg:postcode":"25030",
    "sg:province":"Brescia",
    "wof:name":"Elletie Sas Di Caccia & C.",
    "wof:placetype":"venue"
},
  "geometry": {"coordinates":[9.946878,45.502613],"type":"Point"}
}