{
  "type": "Feature",
  "properties": {
    "iso:country":"IT",
    "sg:address":"06023 Gualdo Tadino",
    "sg:city":"Gualdo Tadino",
    "sg:orig_category":"Bevande, Vini E Liquori",
    "sg:phone":"+39 075 916143",
    "sg:postcode":"06023",
    "sg:province":"Perugia",
    "wof:name":"Rocchetta (s.p.a.)",
    "wof:placetype":"venue"
},
  "geometry": {"coordinates":[12.794506,43.229343],"type":"Point"}
}