{
  "type": "Feature",
  "properties": {
    "iso:country":"IT",
    "sg:address":"43029 Traversetolo",
    "sg:city":"Mamiano",
    "sg:classifiers":[
        {
            "category":"Home & Garden",
            "subcategory":"Building Materials",
            "type":"Retail Goods"
        }
    ],
    "sg:phone":"+39 0521 848280",
    "sg:postcode":"43029",
    "sg:province":"Parma",
    "sg:tags":[
        "gas",
        "caldaie"
    ],
    "wof:name":"Livraga Franco - Idrogas",
    "wof:placetype":"venue"
},
  "geometry": {"coordinates":[10.345933,44.676895],"type":"Point"}
}