{
  "type": "Feature",
  "properties": {
    "addr:full":"44042 Cento Cento Ferrara 44042",
    "addr:postcode":"44042;44042",
    "iso:country":"IT",
    "sg:address":"44042 Cento",
    "sg:city":"Cento",
    "sg:orig_category":"Manufacturers: Prefabbricati",
    "sg:phone":"+39 051 683 0651",
    "sg:postcode":"44042",
    "sg:province":"Ferrara",
    "wof:name":"Frabetti Carlo Alessandro",
    "wof:placetype":"venue"
},
  "geometry": {"coordinates":[11.276481,44.72921],"type":"Point"}
}