{
  "type": "Feature",
  "properties": {
    "iso:country":"IT",
    "sg:address":"80020 Frattaminore",
    "sg:city":"Frattaminore",
    "sg:orig_category":"Prodotti Alimentari",
    "sg:phone":"+39 081 831 2244",
    "sg:postcode":"80020",
    "sg:province":"Napoli",
    "wof:name":"Sagi Srl",
    "wof:placetype":"venue"
},
  "geometry": {"coordinates":[14.2724733353,40.9327049255],"type":"Point"}
}