{
  "type": "Feature",
  "properties": {
    "iso:country":"IT",
    "sg:address":"35028 Piove Di Sacco",
    "sg:city":"Piove di Sacco",
    "sg:orig_category":"Macchine, Impianti Ed Attrezzature Per Abbigliamento E Pelletterie",
    "sg:phone":"+39 049 584 0617",
    "sg:postcode":"35028",
    "sg:province":"Padova",
    "wof:name":"Atitex",
    "wof:placetype":"venue"
},
  "geometry": {"coordinates":[12.056516,45.290058],"type":"Point"}
}