{
  "type": "Feature",
  "properties": {
    "iso:country":"IT",
    "sg:address":"70019 Triggiano",
    "sg:city":"Triggiano",
    "sg:orig_category":"Magazzini Frigoriferi",
    "sg:phone":"+39 080 549 2752",
    "sg:postcode":"70019",
    "sg:province":"Bari",
    "wof:name":"De-mar Srl",
    "wof:placetype":"venue"
},
  "geometry": {"coordinates":[16.869291,41.126053],"type":"Point"}
}