{
  "type": "Feature",
  "properties": {
    "iso:country":"IT",
    "sg:address":"30121 Venezia",
    "sg:city":"Cannaregio",
    "sg:classifiers":[
        {
            "category":"Banks & Credit Unions",
            "subcategory":"Bureau De Change",
            "type":"Services"
        }
    ],
    "sg:phone":"+39 041 715787",
    "sg:postcode":"30121",
    "sg:province":"Venezia",
    "sg:tags":[
        "auxiliary",
        "vehicles",
        "leisure",
        "services",
        "motor",
        "boats",
        "sport",
        "tourism"
    ],
    "sg:website":"http://www.veneziaweb.com/brussaisboat",
    "wof:name":"Brussa Is Boat Di Brussa G. & C. Sas",
    "wof:placetype":"venue"
},
  "geometry": {"coordinates":[12.325556,45.443611],"type":"Point"}
}