{
  "type": "Feature",
  "properties": {
    "addr:full":"20121 Milano Milano Milano 20121",
    "addr:postcode":"20121;20121",
    "iso:country":"IT",
    "sg:address":"20121 Milano",
    "sg:city":"Milano",
    "sg:orig_category":"Servizi Culturali E Per Lo Spettacolo. Servizi Al Turismo. Acqua, Luce, Gas E Societa' Di Esercizio Pubblico",
    "sg:phone":"+39 02 7621 5001",
    "sg:postcode":"20121",
    "sg:province":"Milano",
    "wof:name":"Fondazione Biblioteca Via Senato",
    "wof:placetype":"venue"
},
  "geometry": {"coordinates":[9.197053,45.470764],"type":"Point"}
}