{
  "type": "Feature",
  "properties": {
    "addr:full":"90146 Palermo Palermo Palermo 90146",
    "addr:postcode":"90146;90146",
    "iso:country":"IT",
    "sg:address":"90146 Palermo",
    "sg:city":"Palermo",
    "sg:orig_category":"Materassi - Vendita Al Dettaglio",
    "sg:phone":"+39 091 516144",
    "sg:postcode":"90146",
    "sg:province":"Palermo",
    "wof:name":"Anello Sergio",
    "wof:placetype":"venue"
},
  "geometry": {"coordinates":[13.329225,38.15213],"type":"Point"}
}