{
  "type": "Feature",
  "properties": {
    "addr:full":"Via Nola 62 80033 Cicciano Cicciano Napoli 80033",
    "addr:housenumber":"62",
    "addr:postcode":"80033;80033",
    "addr:street":"Via Nola",
    "iso:country":"IT",
    "sg:address":"Via Nola 62 80033 Cicciano",
    "sg:city":"Cicciano",
    "sg:classifiers":[
        {
            "category":"Restaurant",
            "type":"Food & Drink"
        }
    ],
    "sg:phone":"+39 081 824 8133",
    "sg:postcode":"80033",
    "sg:province":"Napoli",
    "sg:tags":[
        "pasta"
    ],
    "sg:website":"www.russocicciano.it",
    "wof:name":"Carmine Russo Spa",
    "wof:placetype":"venue"
},
  "geometry": {"coordinates":[14.5652799606,40.9456367493],"type":"Point"}
}