{
  "type": "Feature",
  "properties": {
    "iso:country":"IT",
    "sg:address":"5, Via Nettunense 00040 Castel Gandolfo",
    "sg:city":"Castel Gandolfo",
    "sg:classifiers":[
        {
            "category":"Food & Beverages",
            "subcategory":"Groceries & Convenience Stores",
            "type":"Retail Goods"
        }
    ],
    "sg:phone":"+39 39069314877",
    "sg:postcode":"00040",
    "sg:province":"Roma",
    "sg:tags":[
        "product",
        "related"
    ],
    "wof:name":"Scic Pasta All'uovo",
    "wof:placetype":"venue"
},
  "geometry": {"coordinates":[12.635518074,41.7112922668],"type":"Point"}
}