{
  "type": "Feature",
  "properties": {
    "iso:country":"IT",
    "sg:address":"26841 Casalpusterlengo",
    "sg:city":"Casalpusterlengo",
    "sg:orig_category":"Servizi Ausiliari Dei Mezzi Di Trasporto",
    "sg:phone":"+39 0377 84827",
    "sg:postcode":"26841",
    "sg:province":"Lodi",
    "wof:name":"Fratelli Meazzi Di Pierluigi E Roberto Snc",
    "wof:placetype":"venue"
},
  "geometry": {"coordinates":[9.660354,45.166573],"type":"Point"}
}