{
  "type": "Feature",
  "properties": {
    "addr:full":"20155 Milano Milano Milano 20155",
    "addr:postcode":"20155;20155",
    "iso:country":"IT",
    "sg:address":"20155 Milano",
    "sg:city":"Milano",
    "sg:orig_category":"Abbigliamento Esterno, Maglierie E Pelliccerie",
    "sg:phone":"+39 02 3453 3001",
    "sg:postcode":"20155",
    "sg:province":"Milano",
    "wof:name":"Maglificio Silvana Colombo",
    "wof:placetype":"venue"
},
  "geometry": {"coordinates":[9.164376,45.491192],"type":"Point"}
}