{
  "type": "Feature",
  "properties": {
    "iso:country":"IT",
    "sg:address":"25070 Preseglie",
    "sg:city":"Preseglie",
    "sg:orig_category":"Macchine E Forniture Per Arredamento E Industria Del Legno. Serramenti Ed Infissi. Minuterie Metalliche E Ferramenta",
    "sg:phone":"+39 036 586 0947",
    "sg:postcode":"25070",
    "sg:province":"Brescia",
    "wof:name":"Bon El Di E. Caini E C. (s.n.c.)",
    "wof:placetype":"venue"
},
  "geometry": {"coordinates":[10.381466,45.656071],"type":"Point"}
}