{
  "type": "Feature",
  "properties": {
    "iso:country":"IT",
    "sg:address":"20124 Milano",
    "sg:city":"Milano",
    "sg:classifiers":[
        {
            "category":"Professional",
            "subcategory":"Advertising",
            "type":"Services"
        }
    ],
    "sg:phone":"+39 02 697861",
    "sg:postcode":"20124",
    "sg:province":"Milano",
    "sg:tags":[
        "marketing",
        "communication"
    ],
    "sg:website":"http://www.imshealth.com",
    "wof:name":"Ims Health Spa",
    "wof:placetype":"venue"
},
  "geometry": {"coordinates":[9.196966,45.489193],"type":"Point"}
}