{
  "type": "Feature",
  "properties": {
    "addr:full":"59100 Prato Prato Prato 59100",
    "addr:postcode":"59100;59100",
    "iso:country":"IT",
    "sg:address":"59100 Prato",
    "sg:city":"Prato",
    "sg:orig_category":"Abbigliamento In Pelle - Produzione E Ingrosso",
    "sg:phone":"+39 0574 433695",
    "sg:postcode":"59100",
    "sg:province":"Prato",
    "wof:name":"G.l.a. Group Sas",
    "wof:placetype":"venue"
},
  "geometry": {"coordinates":[11.09396,43.873081],"type":"Point"}
}