{
  "type": "Feature",
  "properties": {
    "iso:country":"IT",
    "sg:address":"20090 Trezzano Sul Naviglio",
    "sg:city":"Trezzano sul Naviglio",
    "sg:orig_category":"Trattamenti Termici Metalli",
    "sg:phone":"+39 02 445 9175",
    "sg:postcode":"20090",
    "sg:province":"Milano",
    "sg:website":"http://www.vacuum.it",
    "wof:name":"Vacuum Spa",
    "wof:placetype":"venue"
},
  "geometry": {"coordinates":[9.04627,45.427235],"type":"Point"}
}