{
  "type": "Feature",
  "properties": {
    "iso:country":"IT",
    "sg:address":"20063 Cernusco Sul Naviglio",
    "sg:city":"Cernusco sul Naviglio",
    "sg:orig_category":"Servizi E Lavori Per Edilizia E Lavori Pubblici. Telecomunicazioni E Telefonia, Impianti, Apparecchi E Servizi. Acqua, Luce, Gas E Societa' Di Esercizio Pubblico",
    "sg:phone":"+39 02 924411",
    "sg:postcode":"20063",
    "sg:province":"Milano",
    "wof:name":"Com.net S.r.l.",
    "wof:placetype":"venue"
},
  "geometry": {"coordinates":[9.326898,45.527588],"type":"Point"}
}