{
  "type": "Feature",
  "properties": {
    "iso:country":"IT",
    "sg:address":"46100 Mantova",
    "sg:city":"Mantova",
    "sg:orig_category":"Casalinghi",
    "sg:phone":"+39 0376 391302",
    "sg:postcode":"46100",
    "sg:province":"Mantova",
    "wof:name":"Fer. Giochi Snc",
    "wof:placetype":"venue"
},
  "geometry": {"coordinates":[10.780667,45.180141],"type":"Point"}
}