{
  "type": "Feature",
  "properties": {
    "iso:country":"IT",
    "sg:address":"179, Via Garibaldi Giuseppe 56124 Pisa",
    "sg:city":"Pisa",
    "sg:classifiers":[
        {
            "category":"Wholesale",
            "subcategory":"Machinery & Supplies",
            "type":"Manufacturing & Wholesale Goods"
        }
    ],
    "sg:phone":"+39 39050598133",
    "sg:postcode":"56124",
    "sg:province":"Pisa",
    "sg:tags":[
        "equipment",
        "-",
        "instrument",
        "measurement"
    ],
    "wof:name":"Biomedica Mangoni Snc",
    "wof:placetype":"venue"
},
  "geometry": {"coordinates":[10.396585,43.716137],"type":"Point"}
}