{
  "type": "Feature",
  "properties": {
    "iso:country":"IT",
    "sg:address":"Localita' Lagoscuro Ceparana 19020 Vezzano Ligure",
    "sg:city":"Ceparana",
    "sg:classifiers":[
        {
            "category":"Manufacturing",
            "subcategory":"Rubber & Plastics",
            "type":"Manufacturing & Wholesale Goods"
        }
    ],
    "sg:phone":"+39 0187 932199",
    "sg:postcode":"19020",
    "sg:province":"La Spezia",
    "wof:name":"L.m.p. (s.n.c.)",
    "wof:placetype":"venue"
},
  "geometry": {"coordinates":[9.8772039413,44.1712760925],"type":"Point"}
}