{
  "type": "Feature",
  "properties": {
    "addr:full":"24047 Treviglio Treviglio Bergamo 24047",
    "addr:postcode":"24047;24047",
    "iso:country":"IT",
    "sg:address":"24047 Treviglio",
    "sg:city":"Treviglio",
    "sg:orig_category":"Serramenti Ed Infissi",
    "sg:phone":"+39 036 330 3956",
    "sg:postcode":"24047",
    "sg:province":"Bergamo",
    "wof:name":"Dimensioni Infissi Snc",
    "wof:placetype":"venue"
},
  "geometry": {"coordinates":[9.597992,45.534607],"type":"Point"}
}