{
  "type": "Feature",
  "properties": {
    "addr:full":"21034 Cocquio Trevisago Cocquio Varese 21034",
    "addr:postcode":"21034;21034",
    "iso:country":"IT",
    "sg:address":"21034 Cocquio Trevisago",
    "sg:city":"Cocquio",
    "sg:orig_category":"Manufacturers: Prefabbricati",
    "sg:phone":"+39 0332 700920",
    "sg:postcode":"21034",
    "sg:province":"Varese",
    "sg:website":"http://www.raffognato.com",
    "wof:name":"Raffognato Luigi & Figlio Geom. Pietro Snc",
    "wof:placetype":"venue"
},
  "geometry": {"coordinates":[8.631948,45.846558],"type":"Point"}
}