{
  "type": "Feature",
  "properties": {
    "iso:country":"IT",
    "sg:address":"19, Via Franco Barbieri 27040 Pinarolo Po",
    "sg:city":"Pinarolo Po",
    "sg:classifiers":[
        {
            "category":"Building & Trades",
            "subcategory":"Construction",
            "type":"Services"
        }
    ],
    "sg:phone":"+39 0383 878647",
    "sg:postcode":"27040",
    "sg:province":"Pavia",
    "sg:tags":[
        "work",
        "public"
    ],
    "wof:name":"Rotoscavi (s.r.l.)",
    "wof:placetype":"venue"
},
  "geometry": {"coordinates":[9.160239,45.063293],"type":"Point"}
}