{
  "type": "Feature",
  "properties": {
    "addr:full":"37020 Volargne Volargne Verona 37020",
    "addr:postcode":"37020;37020",
    "addr:street":"Volargne",
    "iso:country":"IT",
    "sg:address":"37020 Volargne",
    "sg:city":"Volargne",
    "sg:orig_category":"Materiali Edili",
    "sg:phone":"+39 045 686 1050",
    "sg:postcode":"37020",
    "sg:province":"Verona",
    "wof:name":"Villaga Calce S.p.a.",
    "wof:placetype":"venue"
},
  "geometry": {"coordinates":[10.822927,45.54509],"type":"Point"}
}