{
  "type": "Feature",
  "properties": {
    "addr:full":"1, Via Comunale Per Casoni 41027 Pievepelago Pievepelago Modena 41027",
    "addr:postcode":"41027;41027",
    "addr:street":"Via Comunale Per Casoni",
    "iso:country":"IT",
    "sg:address":"1, Via Comunale Per Casoni 41027 Pievepelago",
    "sg:city":"Pievepelago",
    "sg:classifiers":[
        {
            "category":"Shopping",
            "subcategory":"Computers & Home Electronics",
            "type":"Retail Goods"
        }
    ],
    "sg:phone":"+39 39053671108",
    "sg:postcode":"41027",
    "sg:province":"Modena",
    "sg:tags":[
        "electronic",
        "electrical",
        "equipment"
    ],
    "wof:name":"Elettronica Cimone (s.r.l.)",
    "wof:placetype":"venue"
},
  "geometry": {"coordinates":[10.609386,44.216415],"type":"Point"}
}