{
  "type": "Feature",
  "properties": {
    "addr:full":"73019 Trepuzzi Trepuzzi Lecce 73019",
    "addr:postcode":"73019;73019",
    "iso:country":"IT",
    "sg:address":"73019 Trepuzzi",
    "sg:city":"Trepuzzi",
    "sg:orig_category":"Nautica. Automobili E Mezzi Di Trasporto",
    "sg:phone":"+39 347 993 1662",
    "sg:postcode":"73019",
    "sg:province":"Lecce",
    "wof:name":"Projet Di Roberto Gaballo",
    "wof:placetype":"venue"
},
  "geometry": {"coordinates":[18.080673,40.400108],"type":"Point"}
}