{
  "type": "Feature",
  "properties": {
    "iso:country":"IT",
    "sg:address":"00148 Roma",
    "sg:city":"Roma",
    "sg:orig_category":"Chiese Ed Associazioni Religiose",
    "sg:phone":"+39 06 653 0440",
    "sg:postcode":"00148",
    "sg:province":"Roma",
    "wof:name":"Chiesa Di Altri Culti Cristiana Evangelica Peniel",
    "wof:placetype":"venue"
},
  "geometry": {"coordinates":[12.441936,41.841553],"type":"Point"}
}