{
  "type": "Feature",
  "properties": {
    "iso:country":"IT",
    "sg:address":"37139 Verona",
    "sg:city":"Verona",
    "sg:orig_category":"Prodotti E Manufatti In Gomma. Servizi E Lavori Industria Della Gomma. Ricambi E Componenti Dei Mezzi Di Trasporto. Riparazione Dei Mezzi Di Trasporto",
    "sg:phone":"+39 045 851 0796",
    "sg:postcode":"37139",
    "sg:province":"Verona",
    "sg:website":"http://www.sipneus.it",
    "wof:name":"Pneus Biemme Srl",
    "wof:placetype":"venue"
},
  "geometry": {"coordinates":[10.8918819427,45.454208374],"type":"Point"}
}