{
  "type": "Feature",
  "properties": {
    "addr:full":"43100 Parma Parma Parma 43100",
    "addr:postcode":"43100;43100",
    "iso:country":"IT",
    "sg:address":"43100 Parma",
    "sg:city":"Parma",
    "sg:orig_category":"Ricerca, Selezione E Formazione Del Personale",
    "sg:phone":"+39 0521 289755",
    "sg:postcode":"43100",
    "sg:province":"Parma",
    "wof:name":"Selecta Di E. Valla & M. C. Trapani",
    "wof:placetype":"venue"
},
  "geometry": {"coordinates":[10.32296,44.7756],"type":"Point"}
}