{
  "type": "Feature",
  "properties": {
    "addr:full":"5, Via Camillo Cavour 27032 Ferrera Erbognone Ferrera Erbognone Pavia 27032",
    "addr:postcode":"27032;27032",
    "addr:street":"Via Camillo Cavour;Erbognone",
    "iso:country":"IT",
    "sg:address":"5, Via Camillo Cavour 27032 Ferrera Erbognone",
    "sg:city":"Ferrera Erbognone",
    "sg:classifiers":[
        {
            "category":"Farming",
            "subcategory":"Livestock Farm",
            "type":"Manufacturing & Wholesale Goods"
        }
    ],
    "sg:phone":"+39 0382 998995",
    "sg:postcode":"27032",
    "sg:province":"Pavia",
    "sg:tags":[
        "agriculture"
    ],
    "wof:name":"Europea S.p.a.",
    "wof:placetype":"venue"
},
  "geometry": {"coordinates":[9.156563,45.185886],"type":"Point"}
}