{
  "type": "Feature",
  "properties": {
    "iso:country":"IT",
    "sg:address":"27035 Mede",
    "sg:city":"Mede",
    "sg:orig_category":"Distributors: Automatici - Commercio E Gestione",
    "sg:phone":"+39 0384 820633",
    "sg:postcode":"27035",
    "sg:province":"Pavia",
    "wof:name":"Civardi Sas",
    "wof:placetype":"venue"
},
  "geometry": {"coordinates":[8.730096,45.091099],"type":"Point"}
}