{
  "type": "Feature",
  "properties": {
    "addr:full":"40013 Castel Maggiore Castel Maggiore Bologna 40013",
    "addr:postcode":"40013;40013",
    "iso:country":"IT",
    "sg:address":"40013 Castel Maggiore",
    "sg:city":"Castel Maggiore",
    "sg:orig_category":"Cinematografia E Radiotelevisione. Pubblicita', Marketing E Comunicazione. Acqua, Luce, Gas E Societa' Di Esercizio Pubblico",
    "sg:phone":"+39 051 714791",
    "sg:postcode":"40013",
    "sg:province":"Bologna",
    "wof:name":"Gtv Srl",
    "wof:placetype":"venue"
},
  "geometry": {"coordinates":[11.372496,44.56345],"type":"Point"}
}