{
  "type": "Feature",
  "properties": {
    "iso:country":"IT",
    "sg:address":"42, Via Foggia 10152 Torino",
    "sg:city":"Torino",
    "sg:orig_category":"Miscellaneous Products",
    "sg:phone":"+39 390 112 6171",
    "sg:postcode":"10152",
    "sg:province":"Torino",
    "wof:name":"Basic Net S.p.a.",
    "wof:placetype":"venue"
},
  "geometry": {"coordinates":[7.6962189674,45.0790672302],"type":"Point"}
}