{
  "type": "Feature",
  "properties": {
    "addr:full":"Via Dei Tigli 06083 Bastia Bastia Perugia 06083",
    "addr:postcode":"06083;06083",
    "addr:street":"Via Dei Tigli",
    "iso:country":"IT",
    "sg:address":"Via Dei Tigli 06083 Bastia",
    "sg:city":"Bastia",
    "sg:classifiers":[
        {
            "category":"Shopping",
            "subcategory":"Clothing, Apparel, & Fashions",
            "type":"Retail Goods"
        }
    ],
    "sg:phone":"+39 075 801 0734",
    "sg:postcode":"06083",
    "sg:province":"Perugia",
    "sg:tags":[
        "clothes"
    ],
    "wof:name":"Malizia S.r.l.",
    "wof:placetype":"venue"
},
  "geometry": {"coordinates":[12.389172,43.110703],"type":"Point"}
}