{
  "type": "Feature",
  "properties": {
    "iso:country":"IT",
    "sg:address":"13836 Cossato",
    "sg:city":"Cossato",
    "sg:orig_category":"Servizi E Lavori Per Abbigliamento E Pelletterie",
    "sg:phone":"+39 015 93561",
    "sg:postcode":"13836",
    "sg:province":"Biella",
    "wof:name":"Rammendo Giulia Di Paganelli Paola & C. (s.n.c.)",
    "wof:placetype":"venue"
},
  "geometry": {"coordinates":[8.186238,45.576408],"type":"Point"}
}