{
  "type": "Feature",
  "properties": {
    "iso:country":"IT",
    "sg:address":"41031 Camposanto",
    "sg:city":"Camposanto",
    "sg:orig_category":"Articoli Sportivi - Produzione E Ingrosso",
    "sg:phone":"+39 0535666",
    "sg:postcode":"41031",
    "sg:province":"Modena",
    "sg:website":"http://www.centrosr.it",
    "wof:name":"C.s.r. Srl",
    "wof:placetype":"venue"
},
  "geometry": {"coordinates":[11.218376,44.848194],"type":"Point"}
}