{
  "type": "Feature",
  "properties": {
    "addr:full":"87064 Corigliano Calabro Corigliano Calabro Cosenza 87064",
    "addr:postcode":"87064;87064",
    "iso:country":"IT",
    "sg:address":"87064 Corigliano Calabro",
    "sg:city":"Corigliano Calabro",
    "sg:classifiers":[
        {
            "category":"Farming",
            "subcategory":"Farm & Veterinary Services",
            "type":"Manufacturing & Wholesale Goods"
        }
    ],
    "sg:phone":"+39 0983 884431",
    "sg:postcode":"87064",
    "sg:province":"Cosenza",
    "sg:tags":[
        "building",
        "industrial",
        "livestock",
        "residential",
        "industry",
        "breeding",
        "works",
        "agriculture"
    ],
    "wof:name":"Sprovieri Idroelettrica Sas Di Sprovieri Damiano & C.",
    "wof:placetype":"venue"
},
  "geometry": {"coordinates":[16.513344,39.628185],"type":"Point"}
}