{
  "type": "Feature",
  "properties": {
    "iso:country":"IT",
    "sg:address":"21011 Casorate Sempione",
    "sg:city":"Casorate Sempione",
    "sg:orig_category":"Servizi E Lavori Per Abbigliamento E Pelletterie. Scuole E Servizi Scolastici. Ricerca, Selezione E Formazione Del Personale",
    "sg:phone":"+39 0331 767413",
    "sg:postcode":"21011",
    "sg:province":"Varese",
    "wof:name":"Tutino Francesca",
    "wof:placetype":"venue"
},
  "geometry": {"coordinates":[8.7380838394,45.6713485718],"type":"Point"}
}