{
  "type": "Feature",
  "properties": {
    "addr:full":"10, Via Circonvallazione Sud 40062 Molinella Molinella Bologna 40062",
    "addr:postcode":"40062;40062",
    "addr:street":"Via Circonvallazione Sud",
    "iso:country":"IT",
    "sg:address":"10, Via Circonvallazione Sud 40062 Molinella",
    "sg:city":"Molinella",
    "sg:classifiers":[
        {
            "category":"Personal",
            "subcategory":"Shoe Repair & Shine",
            "type":"Services"
        }
    ],
    "sg:phone":"+39 39051880202",
    "sg:postcode":"40062",
    "sg:province":"Bologna",
    "sg:tags":[
        "leather"
    ],
    "wof:name":"Tacchificio Di Molinella (s.r.l.)",
    "wof:placetype":"venue"
},
  "geometry": {"coordinates":[11.668203,44.617001],"type":"Point"}
}