{
  "type": "Feature",
  "properties": {
    "addr:full":"07100 Sassari Sassari Sassari 07100",
    "addr:postcode":"07100;07100",
    "iso:country":"IT",
    "sg:address":"07100 Sassari",
    "sg:city":"Sassari",
    "sg:orig_category":"Manufacturers: Prefabbricati. Arredi Ed Attrezzature Per Attivita' Commerciali Ed Artigianali",
    "sg:phone":"+39 079 260559",
    "sg:postcode":"07100",
    "sg:province":"Sassari",
    "wof:name":"Metal Sistem Sardegna Srl",
    "wof:placetype":"venue"
},
  "geometry": {"coordinates":[8.3745718002,40.7555809021],"type":"Point"}
}