{
  "type": "Feature",
  "properties": {
    "addr:full":"27 Via Carrara Francesco, 00196 Roma Roma Roma 00196",
    "addr:postcode":"00196;00196",
    "addr:street":"Via Carrara Francesco",
    "iso:country":"IT",
    "sg:address":"27 Via Carrara Francesco, 00196 Roma",
    "sg:city":"Roma",
    "sg:classifiers":[
        {
            "category":"Banks & Credit Unions",
            "subcategory":"Financial Services",
            "type":"Services"
        }
    ],
    "sg:phone":"+39 390 632 4981",
    "sg:postcode":"00196",
    "sg:province":"Roma",
    "sg:tags":[
        "banking",
        "finance",
        "insurance"
    ],
    "wof:name":"Istituto Per Il Credito Sportivo",
    "wof:placetype":"venue"
},
  "geometry": {"coordinates":[12.4823246002,41.8954658508],"type":"Point"}
}