{
  "type": "Feature",
  "properties": {
    "iso:country":"IT",
    "sg:address":"26, Via G. Marconi 28019 Suno",
    "sg:city":"Suno",
    "sg:classifiers":[
        {
            "category":"Shopping",
            "subcategory":"Clothing, Apparel, & Fashions",
            "type":"Retail Goods"
        }
    ],
    "sg:phone":"+39 39032285797",
    "sg:postcode":"28019",
    "sg:province":"Novara",
    "sg:tags":[
        "clothes"
    ],
    "wof:name":"Zamar Di Magni Franca & C. (s.n.c.)",
    "wof:placetype":"venue"
},
  "geometry": {"coordinates":[8.544915,45.628937],"type":"Point"}
}