{
  "type": "Feature",
  "properties": {
    "iso:country":"IT",
    "sg:address":"20092 Cinisello Balsamo",
    "sg:city":"Cinisello Balsamo",
    "sg:classifiers":[
        {
            "category":"Health Services",
            "subcategory":"Health Practitioner",
            "type":"Services"
        }
    ],
    "sg:phone":"+39 02 618 5902",
    "sg:postcode":"20092",
    "sg:province":"Milano",
    "sg:tags":[
        "medici"
    ],
    "wof:name":"Lovati Marco",
    "wof:placetype":"venue"
},
  "geometry": {"coordinates":[9.213231,45.555943],"type":"Point"}
}