{
  "type": "Feature",
  "properties": {
    "addr:full":"23, Via Spartaco 20135 Milano Milano Milano 20135",
    "addr:postcode":"20135;20135",
    "addr:street":"Via Spartaco",
    "iso:country":"IT",
    "sg:address":"23, Via Spartaco 20135 Milano",
    "sg:city":"Milano",
    "sg:classifiers":[
        {
            "category":"Shopping",
            "subcategory":"Crafts & Fabrics",
            "type":"Retail Goods"
        }
    ],
    "sg:phone":"+39 02 5518 3182",
    "sg:postcode":"20135",
    "sg:province":"Milano",
    "wof:name":"Canobbio (s.p.a.)",
    "wof:placetype":"venue"
},
  "geometry": {"coordinates":[9.2032260895,45.4824676514],"type":"Point"}
}