{
  "type": "Feature",
  "properties": {
    "iso:country":"IT",
    "sg:address":"08100 Nuoro",
    "sg:city":"Nuoro",
    "sg:orig_category":"Servizi E Lavori Per Edilizia E Lavori Pubblici. Professionisti - Studi E Servizi Ed Associazioni Di Interesse Aziendale",
    "sg:phone":"+39 0784 37612",
    "sg:postcode":"08100",
    "sg:province":"Nuoro",
    "wof:name":"Soiltecnica Srl",
    "wof:placetype":"venue"
},
  "geometry": {"coordinates":[9.330919,40.321762],"type":"Point"}
}