{
  "type": "Feature",
  "properties": {
    "addr:full":"31038 Paese Paese Treviso 31038",
    "addr:postcode":"31038;31038",
    "addr:street":"Paese Paese",
    "iso:country":"IT",
    "sg:address":"31038 Paese",
    "sg:city":"Paese",
    "sg:orig_category":"Forniture Per Edilizia E Lavori Pubblici. Forniture Industriali Per Prevenzione, Controllo E Sicurezza",
    "sg:phone":"+39 0432 452194",
    "sg:postcode":"31038",
    "sg:province":"Treviso",
    "wof:name":"Globus Service Srl",
    "wof:placetype":"venue"
},
  "geometry": {"coordinates":[12.1437330246,45.6755485535],"type":"Point"}
}