{
  "type": "Feature",
  "properties": {
    "iso:country":"IT",
    "sg:address":"Via Barbuggine 115/b; Asparetto; 37050",
    "sg:classifiers":[
        {
            "category":"Banks & Credit Unions",
            "subcategory":"Bank",
            "type":"Services"
        }
    ],
    "sg:phone":"+39 0442 83311",
    "sg:postcode":"37050",
    "sg:province":"Verona",
    "wof:name":"Cariverona Banca Spa",
    "wof:placetype":"venue"
},
  "geometry": {"coordinates":[11.175622,45.212368],"type":"Point"}
}