{
  "type": "Feature",
  "properties": {
    "iso:country":"IT",
    "sg:address":"27100 Pavia",
    "sg:city":"Pavia",
    "sg:orig_category":"Articoli Medico-sanitari Ed Ortopedici",
    "sg:phone":"+39 0382 527952",
    "sg:postcode":"27100",
    "sg:province":"Pavia",
    "wof:name":"Officina Ortopedica Pavese Sas",
    "wof:placetype":"venue"
},
  "geometry": {"coordinates":[9.144313,45.197838],"type":"Point"}
}