{
  "type": "Feature",
  "properties": {
    "iso:country":"IT",
    "sg:address":"16036 Recco",
    "sg:city":"Recco",
    "sg:orig_category":"Servizi Ausiliari Per Il Trasporto. Agenzie D'affari E Servizi Commerciali",
    "sg:phone":"+39 0185 7351",
    "sg:postcode":"16036",
    "sg:province":"Genova",
    "wof:name":"Eco Chartering S.r.l.",
    "wof:placetype":"venue"
},
  "geometry": {"coordinates":[9.135798,44.361877],"type":"Point"}
}