{
  "type": "Feature",
  "properties": {
    "addr:full":"10072 Caselle Torinese Caselle Torinese Torino 10072",
    "addr:postcode":"10072;10072",
    "iso:country":"IT",
    "sg:address":"10072 Caselle Torinese",
    "sg:city":"Caselle Torinese",
    "sg:orig_category":"Arredamento Bar E Ristoranti",
    "sg:phone":"+39 011 996 8944",
    "sg:postcode":"10072",
    "sg:province":"Torino",
    "wof:name":"Vallero Snc",
    "wof:placetype":"venue"
},
  "geometry": {"coordinates":[7.690588,45.163151],"type":"Point"}
}