{
  "type": "Feature",
  "properties": {
    "addr:full":"45020 Giacciano Con Baruchella Baruchella Rovigo 45020",
    "addr:postcode":"45020;45020",
    "addr:street":"Con Baruchella Baruchella",
    "iso:country":"IT",
    "sg:address":"45020 Giacciano Con Baruchella",
    "sg:city":"Baruchella",
    "sg:orig_category":"Agenzie Viaggi E Turismo",
    "sg:phone":"+39 0425 594547",
    "sg:postcode":"45020",
    "sg:province":"Rovigo",
    "wof:name":"Vangadizza Viaggi Di Clipper Viaggi Srl",
    "wof:placetype":"venue"
},
  "geometry": {"coordinates":[11.451407,45.06813],"type":"Point"}
}