{
  "type": "Feature",
  "properties": {
    "iso:country":"IT",
    "sg:address":"31030 Casier",
    "sg:city":"Casier",
    "sg:orig_category":"Trattamenti Termici E Superficiali Metalli, Galvanotecnica",
    "sg:phone":"+39 0422 490197",
    "sg:postcode":"31030",
    "sg:province":"Treviso",
    "wof:name":"Novafigure Snc Di Francesco Corso & C.",
    "wof:placetype":"venue"
},
  "geometry": {"coordinates":[12.263089,45.633438],"type":"Point"}
}