{
  "type": "Feature",
  "properties": {
    "iso:country":"IT",
    "sg:address":"Via Taliercio 2 31010 Ormelle",
    "sg:classifiers":[
        {
            "category":"Manufacturing",
            "subcategory":"Rubber & Plastics",
            "type":"Manufacturing & Wholesale Goods"
        }
    ],
    "sg:phone":"+39 0422 205611",
    "sg:postcode":"31010",
    "sg:province":"Treviso",
    "sg:tags":[
        "material"
    ],
    "sg:website":"www.arredoplast.it",
    "wof:name":"Arredo Plast Spa",
    "wof:placetype":"venue"
},
  "geometry": {"coordinates":[12.2420721054,45.6662864685],"type":"Point"}
}