{
  "type": "Feature",
  "properties": {
    "iso:country":"IT",
    "sg:address":"00153 Roma",
    "sg:city":"Roma",
    "sg:orig_category":"Bevande, Vini E Liquori",
    "sg:phone":"+39 06 580 9753",
    "sg:postcode":"00153",
    "sg:province":"Roma",
    "wof:name":"Meta & Fama Srl",
    "wof:placetype":"venue"
},
  "geometry": {"coordinates":[12.476508,41.888531],"type":"Point"}
}