{
  "type": "Feature",
  "properties": {
    "iso:country":"IT",
    "sg:address":"163, V. Trivellini 25018 Montichiari",
    "sg:city":"Montichiari",
    "sg:classifiers":[
        {
            "category":"Autos & Motor Vehicles",
            "subcategory":"Automobile Sales",
            "type":"Retail Goods"
        }
    ],
    "sg:phone":"+39 030 998 3069",
    "sg:postcode":"25018",
    "sg:province":"Brescia",
    "sg:tags":[
        "industrial"
    ],
    "sg:website":"http://www.paginegialle.it/pezzaioli",
    "wof:name":"Pezzaioli Commerciale Srl",
    "wof:placetype":"venue"
},
  "geometry": {"coordinates":[10.419116,45.384575],"type":"Point"}
}