{
  "type": "Feature",
  "properties": {
    "iso:country":"IT",
    "sg:address":"44020 Goro",
    "sg:city":"Goro",
    "sg:orig_category":"Abbigliamento Esterno, Maglierie E Pelliccerie. Shopping",
    "sg:phone":"+39 0533 996470",
    "sg:postcode":"44020",
    "sg:province":"Ferrara",
    "wof:name":"Mangolini Enzo Walter",
    "wof:placetype":"venue"
},
  "geometry": {"coordinates":[11.76361,44.931171],"type":"Point"}
}