{
  "type": "Feature",
  "properties": {
    "iso:country":"IT",
    "sg:address":"88100 Catanzaro",
    "sg:city":"Catanzaro",
    "sg:orig_category":"Studi E Consulenze Tecniche E Industriali. Servizi E Lavori Per Edilizia E Lavori Pubblici. Professionisti - Studi E Servizi Ed Associazioni Di Interesse Aziendale",
    "sg:phone":"+39 0961 777798",
    "sg:postcode":"88100",
    "sg:province":"Catanzaro",
    "sg:website":"http://www.inteq.it",
    "wof:name":"In.te.q. Srl",
    "wof:placetype":"venue"
},
  "geometry": {"coordinates":[16.568804,38.909935],"type":"Point"}
}