{
  "type": "Feature",
  "properties": {
    "iso:country":"IT",
    "sg:address":"36030 Zugliano",
    "sg:city":"Zugliano",
    "sg:orig_category":"Macchine Utensili E Impianti. Elettrotecnica Industriale, Prodotti E Apparecchiature",
    "sg:phone":"+39 0445 330095",
    "sg:postcode":"36030",
    "sg:province":"Vicenza",
    "wof:name":"Franzan Srl",
    "wof:placetype":"venue"
},
  "geometry": {"coordinates":[11.525,45.730797],"type":"Point"}
}