{
  "type": "Feature",
  "properties": {
    "addr:full":"12, Via Monauni 25030 Coccaglio Coccaglio Brescia 25030",
    "addr:postcode":"25030;25030",
    "addr:street":"Via Monauni",
    "iso:country":"IT",
    "sg:address":"12, Via Monauni 25030 Coccaglio",
    "sg:city":"Coccaglio",
    "sg:classifiers":[
        {
            "category":"Manufacturing",
            "subcategory":"Rubber & Plastics",
            "type":"Manufacturing & Wholesale Goods"
        }
    ],
    "sg:phone":"+39 030 770 3300",
    "sg:postcode":"25030",
    "sg:province":"Brescia",
    "wof:name":"Scab Giardino (s.p.a.)",
    "wof:placetype":"venue"
},
  "geometry": {"coordinates":[9.9793491364,45.5615386963],"type":"Point"}
}