{
  "type": "Feature",
  "properties": {
    "iso:country":"IT",
    "sg:address":"23801 Calolziocorte",
    "sg:city":"Calolziocorte",
    "sg:orig_category":"Servizi E Lavori Per Arredamento E Industria Del Legno. Forniture Per Congressi, Fiere E Manifestazioni. Servizi Per Aziende, Manifestazioni E Supporto Agli Scambi Commerciali",
    "sg:phone":"+39 0341 641696",
    "sg:postcode":"23801",
    "sg:province":"Lecco",
    "wof:name":"Angeli Snc",
    "wof:placetype":"venue"
},
  "geometry": {"coordinates":[9.434072,45.800983],"type":"Point"}
}