{
  "type": "Feature",
  "properties": {
    "iso:country":"IT",
    "sg:address":"00153 Roma",
    "sg:city":"Roma",
    "sg:orig_category":"Manufacturers: Prefabbricati",
    "sg:phone":"+39 06 581 8854",
    "sg:postcode":"00153",
    "sg:province":"Roma",
    "wof:name":"Baiocco Fabrizio",
    "wof:placetype":"venue"
},
  "geometry": {"coordinates":[12.475842,41.889217],"type":"Point"}
}