{
  "type": "Feature",
  "properties": {
    "iso:country":"IT",
    "sg:address":"03013 Ferentino",
    "sg:city":"Ferentino",
    "sg:orig_category":"Metalli E Leghe",
    "sg:phone":"+39 0775 271464",
    "sg:postcode":"03013",
    "sg:province":"Frosinone",
    "wof:name":"M.m.t.",
    "wof:placetype":"venue"
},
  "geometry": {"coordinates":[13.3606500626,41.6305961609],"type":"Point"}
}