{
  "type": "Feature",
  "properties": {
    "iso:country":"IT",
    "sg:address":"70124 Bari",
    "sg:city":"Bari",
    "sg:orig_category":"Impianti, Attrezzature E Forniture Sanitarie Ed Ospedaliere",
    "sg:phone":"+39 080 501 0134",
    "sg:postcode":"70124",
    "sg:province":"Bari",
    "wof:name":"Fotoindustria (s.p.a.)",
    "wof:placetype":"venue"
},
  "geometry": {"coordinates":[16.864202,41.095066],"type":"Point"}
}