{
  "type": "Feature",
  "properties": {
    "iso:country":"IT",
    "sg:address":"15, Via Giovanni Pascoli 31053 Pieve Di Soligo",
    "sg:city":"Pieve di Soligo",
    "sg:classifiers":[
        {
            "category":"Home & Garden",
            "subcategory":"Home Furnishings",
            "type":"Retail Goods"
        }
    ],
    "sg:phone":"+39 0438 840718",
    "sg:postcode":"31053",
    "sg:province":"Treviso",
    "sg:tags":[
        "household"
    ],
    "wof:name":"Clever S.p.a.",
    "wof:placetype":"venue"
},
  "geometry": {"coordinates":[12.163308,45.891617],"type":"Point"}
}