{
  "type": "Feature",
  "properties": {
    "addr:full":"73055 Racale Racale Lecce 73055",
    "addr:postcode":"73055;73055",
    "iso:country":"IT",
    "sg:address":"73055 Racale",
    "sg:city":"Racale",
    "sg:orig_category":"Arredo Urbano",
    "sg:phone":"+39 0833 553817",
    "sg:postcode":"73055",
    "sg:province":"Lecce",
    "wof:name":"Ecoplan Studio",
    "wof:placetype":"venue"
},
  "geometry": {"coordinates":[18.095934,39.958363],"type":"Point"}
}