{
  "type": "Feature",
  "properties": {
    "addr:full":"37049 Villa Bartolomea Villa Bartolomea Verona 37049",
    "addr:housenumber":"37049",
    "addr:postcode":"37049",
    "addr:street":"Villa Bartolomea",
    "iso:country":"IT",
    "sg:address":"37049 Villa Bartolomea",
    "sg:city":"Villa Bartolomea",
    "sg:orig_category":"Bruciatori Nafta, Gasolio E Kerosene - Commercio",
    "sg:phone":"+39 0442 659096",
    "sg:postcode":"37049",
    "sg:province":"Verona",
    "wof:name":"Brama Roberto",
    "wof:placetype":"venue"
},
  "geometry": {"coordinates":[11.355288,45.152039],"type":"Point"}
}