{
  "type": "Feature",
  "properties": {
    "iso:country":"IT",
    "sg:address":"18100 Imperia",
    "sg:city":"Imperia",
    "sg:orig_category":"Servizi Per Lo Sport E Il Tempo Libero. Servizi Ausiliari Dei Mezzi Di Trasporto",
    "sg:phone":"+39 0183 61667",
    "sg:postcode":"18100",
    "sg:province":"Imperia",
    "wof:name":"Agenzia La Rapida",
    "wof:placetype":"venue"
},
  "geometry": {"coordinates":[8.01427,43.876526],"type":"Point"}
}