{
  "type": "Feature",
  "properties": {
    "iso:country":"IT",
    "sg:address":"40033 Casalecchio Di Reno",
    "sg:city":"Casalecchio di Reno",
    "sg:classifiers":[
        {
            "category":"Health Services",
            "subcategory":"Health Practitioner",
            "type":"Services"
        }
    ],
    "sg:phone":"+39 051 577577",
    "sg:postcode":"40033",
    "sg:province":"Bologna",
    "sg:tags":[
        "medici"
    ],
    "wof:name":"Iaquinta Lina",
    "wof:placetype":"venue"
},
  "geometry": {"coordinates":[11.346149,44.504223],"type":"Point"}
}