{
  "type": "Feature",
  "properties": {
    "iso:country":"IT",
    "sg:address":"31029 Vittorio Veneto",
    "sg:city":"Vittorio Veneto",
    "sg:orig_category":"Articoli Da Regalo. Arte Ed Artigianato Artistico. Shopping. Regalistica Aziendale",
    "sg:phone":"+39 0438 554028",
    "sg:postcode":"31029",
    "sg:province":"Treviso",
    "wof:name":"L'atelier Di Maria Rita Faganello",
    "wof:placetype":"venue"
},
  "geometry": {"coordinates":[12.300996,45.996239],"type":"Point"}
}