{
  "type": "Feature",
  "properties": {
    "addr:full":"80100 Napoli NA",
    "addr:postcode":"80100",
    "iso:country":"IT",
    "sg:address":"80100 Napoli",
    "sg:orig_category":"Automobili E Mezzi Di Trasporto",
    "sg:phone":"+39 081 570 0406",
    "sg:province":"NA",
    "wof:name":"Svezia Auto Srl",
    "wof:placetype":"venue"
},
  "geometry": {"coordinates":[14.251636,40.840096],"type":"Point"}
}