{
  "type": "Feature",
  "properties": {
    "addr:full":"29, Via G. Rossa 62015 Monte San Giusto Monte San Giusto Macerata 62015",
    "addr:postcode":"62015;62015",
    "addr:street":"Via G. Rossa",
    "iso:country":"IT",
    "sg:address":"29, Via G. Rossa 62015 Monte San Giusto",
    "sg:city":"Monte San Giusto",
    "sg:classifiers":[
        {
            "category":"Personal",
            "subcategory":"Shoe Repair & Shine",
            "type":"Services"
        }
    ],
    "sg:phone":"+39 0733 837150",
    "sg:postcode":"62015",
    "sg:province":"Macerata",
    "sg:tags":[
        "leather"
    ],
    "wof:name":"Industria Italiana Calzature S.r.l.",
    "wof:placetype":"venue"
},
  "geometry": {"coordinates":[13.456262,43.300747],"type":"Point"}
}