{
  "type": "Feature",
  "properties": {
    "iso:country":"IT",
    "sg:address":"25050 Passirano",
    "sg:city":"Passirano",
    "sg:orig_category":"Suites, Armchairs, Chairs And Tables",
    "sg:phone":"+39 030 685 7568",
    "sg:postcode":"25050",
    "sg:province":"Brescia",
    "sg:website":"http://www.marasrl.it",
    "wof:name":"Mara Srl",
    "wof:placetype":"venue"
},
  "geometry": {"coordinates":[10.079189,45.567432],"type":"Point"}
}