{
  "type": "Feature",
  "properties": {
    "iso:country":"IT",
    "sg:address":"Via G. Puccini, 26/40 20045 Besana In Brianza",
    "sg:city":"Besana in Brianza",
    "sg:classifiers":[
        {
            "category":"Personal",
            "subcategory":"Sauna",
            "type":"Services"
        }
    ],
    "sg:phone":"+39 036 29141",
    "sg:postcode":"20045",
    "sg:province":"Milano",
    "sg:tags":[
        "towel",
        "bathrobes",
        "bath"
    ],
    "sg:website":"www.besanaspugna.com",
    "wof:name":"Manifattura Tessuti Spugna Besana S.p.a.",
    "wof:placetype":"venue"
},
  "geometry": {"coordinates":[9.212464,45.488014],"type":"Point"}
}