{
  "type": "Feature",
  "properties": {
    "iso:country":"IT",
    "sg:address":"15100 Alessandria",
    "sg:city":"Alessandria",
    "sg:orig_category":"Pubblicita', Marketing E Comunicazione",
    "sg:phone":"+39 0131 510097",
    "sg:postcode":"15100",
    "sg:province":"Alessandria",
    "sg:website":"http://www.anteprimaspettacolo.it",
    "wof:name":"Anteprima Spettacolo",
    "wof:placetype":"venue"
},
  "geometry": {"coordinates":[8.7105503082,44.9107627869],"type":"Point"}
}