{
  "type": "Feature",
  "properties": {
    "addr:full":"Via Puccini, 1; 40067 Rastignano, Bologna, Italy Rastignano Bologna 40067",
    "addr:housenumber":"1",
    "addr:postcode":"40067;40067",
    "addr:street":"Via Puccini",
    "iso:country":"IT",
    "sg:address":"Via Puccini, 1; 40067 Rastignano, Bologna, Italy",
    "sg:city":"Rastignano",
    "sg:classifiers":[
        {
            "category":"Industrial Area",
            "type":"Public Place"
        }
    ],
    "sg:phone":"+39 051 620 2111",
    "sg:postcode":"40067",
    "sg:province":"Bologna",
    "sg:tags":[
        "large",
        "private"
    ],
    "sg:website":"www.segafredo.it",
    "wof:name":"Segafredo Zanetti S.p.a.",
    "wof:placetype":"venue"
},
  "geometry": {"coordinates":[11.3500318527,44.4210739136],"type":"Point"}
}