{
  "type": "Feature",
  "properties": {
    "iso:country":"IT",
    "sg:address":"87100 Cosenza",
    "sg:city":"Cosenza",
    "sg:orig_category":"Calzature, Pelletterie E Pelli. Shopping",
    "sg:phone":"+39 0984 76761",
    "sg:postcode":"87100",
    "sg:province":"Cosenza",
    "wof:name":"L'exclusif Di Esposito Adriana",
    "wof:placetype":"venue"
},
  "geometry": {"coordinates":[16.253242,39.295612],"type":"Point"}
}