{
  "type": "Feature",
  "properties": {
    "addr:full":"147, Strada Del Portone 10095 Grugliasco Grugliasco Torino 10095",
    "addr:postcode":"10095;10095",
    "addr:street":"Strada Del Portone",
    "iso:country":"IT",
    "sg:address":"147, Strada Del Portone 10095 Grugliasco",
    "sg:city":"Grugliasco",
    "sg:classifiers":[
        {
            "category":"Professional",
            "subcategory":"Engineering",
            "type":"Services"
        }
    ],
    "sg:phone":"+39 011 314 8333",
    "sg:postcode":"10095",
    "sg:province":"Torino",
    "sg:tags":[
        "machine",
        "-",
        "mechanical"
    ],
    "wof:name":"Sicla S.p.a.",
    "wof:placetype":"venue"
},
  "geometry": {"coordinates":[7.592375,45.042397],"type":"Point"}
}