{
  "type": "Feature",
  "properties": {
    "addr:full":"37, V. Del Progresso 36020 Castegnero Castegnero Vicenza 36020",
    "addr:housenumber":"37",
    "addr:postcode":"36020;36020",
    "addr:street":"V. Del Progresso",
    "iso:country":"IT",
    "sg:address":"37, V. Del Progresso 36020 Castegnero",
    "sg:city":"Castegnero",
    "sg:classifiers":[
        {
            "category":"Autos & Motor Vehicles",
            "subcategory":"Automobile Sales",
            "type":"Retail Goods"
        }
    ],
    "sg:phone":"+39 0444 639377",
    "sg:postcode":"36020",
    "sg:province":"Vicenza",
    "sg:tags":[
        "industrial"
    ],
    "sg:website":"http://www.oml-srl.com:ws_end: :mark:ws:http://www.paginegialle.it/omlsrl",
    "wof:name":"O.m.l. Srl",
    "wof:placetype":"venue"
},
  "geometry": {"coordinates":[11.597124,45.442547],"type":"Point"}
}