{
  "type": "Feature",
  "properties": {
    "iso:country":"IT",
    "sg:address":"20144 Milano",
    "sg:city":"Milano",
    "sg:classifiers":[
        {
            "category":"Health Services",
            "subcategory":"Health Practitioner",
            "type":"Services"
        }
    ],
    "sg:phone":"+39 02 4819 6037",
    "sg:postcode":"20144",
    "sg:province":"Milano",
    "sg:tags":[
        "medici"
    ],
    "wof:name":"Crozafon Philippe",
    "wof:placetype":"venue"
},
  "geometry": {"coordinates":[9.162025,45.459587],"type":"Point"}
}