{
  "type": "Feature",
  "properties": {
    "addr:full":"Via Caduti Sul Lavoro 2; Alife; 81011 Alife Caserta 81011",
    "addr:housenumber":"2",
    "addr:postcode":"81011;81011",
    "addr:street":"Via Caduti Sul Lavoro",
    "iso:country":"IT",
    "sg:address":"Via Caduti Sul Lavoro 2; Alife; 81011",
    "sg:city":"Alife",
    "sg:classifiers":[
        {
            "category":"Banks & Credit Unions",
            "subcategory":"Bank",
            "type":"Services"
        }
    ],
    "sg:phone":"+39 0823 783024",
    "sg:postcode":"81011",
    "sg:province":"Caserta",
    "wof:name":"Banco Di Napoli Spa",
    "wof:placetype":"venue"
},
  "geometry": {"coordinates":[14.336419,41.324898],"type":"Point"}
}