{
  "type": "Feature",
  "properties": {
    "addr:full":"04020 Santi Cosma E Damiano Santi Cosma e Damiano Latina 04020",
    "addr:postcode":"04020;04020",
    "addr:street":"E;E",
    "iso:country":"IT",
    "sg:address":"04020 Santi Cosma E Damiano",
    "sg:city":"Santi Cosma e Damiano",
    "sg:orig_category":"Biancheria, Telerie E Coperte. Forniture Alle Strutture Ricettive",
    "sg:phone":"+39 0771 607464",
    "sg:postcode":"04020",
    "sg:province":"Latina",
    "wof:name":"Cooperativa Sociale Atlandite",
    "wof:placetype":"venue"
},
  "geometry": {"coordinates":[13.816137,41.301277],"type":"Point"}
}