{
  "type": "Feature",
  "properties": {
    "addr:full":"29/a, Via Savoia 00198 Roma Roma Roma 00198",
    "addr:housenumber":"29 / a",
    "addr:postcode":"00198;00198",
    "addr:street":"Via Savoia",
    "iso:country":"IT",
    "sg:address":"29/a, Via Savoia 00198 Roma",
    "sg:city":"Roma",
    "sg:classifiers":[
        {
            "category":"Banks & Credit Unions",
            "subcategory":"Investment Brokerage",
            "type":"Services"
        }
    ],
    "sg:phone":"+39 39068841151",
    "sg:postcode":"00198",
    "sg:province":"Roma",
    "sg:tags":[
        "-",
        "transport",
        "related"
    ],
    "wof:name":"City Cross S.p.a.",
    "wof:placetype":"venue"
},
  "geometry": {"coordinates":[12.482325,41.895466],"type":"Point"}
}