{
  "type": "Feature",
  "properties": {
    "iso:country":"IT",
    "sg:address":"Piazza Castello, 2; Siena; 53025",
    "sg:classifiers":[
        {
            "category":"Banks & Credit Unions",
            "subcategory":"Bank",
            "type":"Services"
        }
    ],
    "sg:phone":"+39 0577 86067",
    "sg:postcode":"53025",
    "sg:province":"Siena",
    "wof:name":"Banca Popolare",
    "wof:placetype":"venue"
},
  "geometry": {"coordinates":[11.804716,43.206371],"type":"Point"}
}