{
  "type": "Feature",
  "properties": {
    "addr:full":"25062 Concesio Concesio Brescia 25062",
    "addr:postcode":"25062;25062",
    "iso:country":"IT",
    "sg:address":"25062 Concesio",
    "sg:city":"Concesio",
    "sg:orig_category":"Utensili Meccanici E Materiali",
    "sg:phone":"+39 030 209 1502",
    "sg:postcode":"25062",
    "sg:province":"Brescia",
    "wof:name":"Gasparini Umberto",
    "wof:placetype":"venue"
},
  "geometry": {"coordinates":[10.224811,45.588097],"type":"Point"}
}