{
  "type": "Feature",
  "properties": {
    "iso:country":"IT",
    "sg:address":"16137 Genova",
    "sg:city":"Genova",
    "sg:orig_category":"Motori Ed Organi Di Trasmissione",
    "sg:phone":"+39 010 837 6410",
    "sg:postcode":"16137",
    "sg:province":"Genova",
    "sg:website":"http://web.tiscalinet.it/fenice2000",
    "wof:name":"Fenice Advanced Technologies & Commercial Services Srl",
    "wof:placetype":"venue"
},
  "geometry": {"coordinates":[8.9512529373,44.4098243713],"type":"Point"}
}