{
  "type": "Feature",
  "properties": {
    "iso:country":"IT",
    "sg:address":"Piazza Zamara 12; Palazzolo Sull'oglio; 25036",
    "sg:classifiers":[
        {
            "category":"Banks & Credit Unions",
            "subcategory":"Bank",
            "type":"Services"
        }
    ],
    "sg:phone":"+39 030 740 2004",
    "sg:postcode":"25036",
    "sg:province":"Brescia",
    "wof:name":"Banca Popolare Di Brescia Scarl",
    "wof:placetype":"venue"
},
  "geometry": {"coordinates":[9.883448,45.598263],"type":"Point"}
}