{
  "type": "Feature",
  "properties": {
    "addr:full":"20026 Novate Milanese Novate Milanese Milano 20026",
    "addr:postcode":"20026;20026",
    "iso:country":"IT",
    "sg:address":"20026 Novate Milanese",
    "sg:city":"Novate Milanese",
    "sg:orig_category":"Fiere, Mostre E Saloni - Allestimento E Servizi",
    "sg:phone":"+39 02 356 1447",
    "sg:postcode":"20026",
    "sg:province":"Milano",
    "wof:name":"Prezioso Leonardo",
    "wof:placetype":"venue"
},
  "geometry": {"coordinates":[9.124671936,45.5293655396],"type":"Point"}
}