{
  "type": "Feature",
  "properties": {
    "addr:full":"Km. 98, Via Pontebbana 33098 Valvasone Valvasone Pordenone 33098",
    "addr:postcode":"33098;33098",
    "addr:street":"Km. 98 Via Pontebbana",
    "iso:country":"IT",
    "sg:address":"Km. 98, Via Pontebbana 33098 Valvasone",
    "sg:city":"Valvasone",
    "sg:classifiers":[
        {
            "category":"Professional",
            "subcategory":"Engineering",
            "type":"Services"
        }
    ],
    "sg:phone":"+39 39043485385",
    "sg:postcode":"33098",
    "sg:province":"Pordenone",
    "sg:tags":[
        "machine",
        "-",
        "mechanical"
    ],
    "wof:name":"Emainox (s.r.l.)",
    "wof:placetype":"venue"
},
  "geometry": {"coordinates":[12.655044,45.96265],"type":"Point"}
}