{
  "type": "Feature",
  "properties": {
    "addr:full":"33100 Udine Udine Udine 33100",
    "addr:postcode":"33100;33100",
    "iso:country":"IT",
    "sg:address":"33100 Udine",
    "sg:city":"Udine",
    "sg:orig_category":"Arredo Cucina Ed Elettrodomestici. Elettrodomestici",
    "sg:phone":"+39 0432 295437",
    "sg:postcode":"33100",
    "sg:province":"Udine",
    "wof:name":"Conz Nadir",
    "wof:placetype":"venue"
},
  "geometry": {"coordinates":[13.247972,46.059017],"type":"Point"}
}