{
  "type": "Feature",
  "properties": {
    "iso:country":"IT",
    "sg:address":"95042 Grammichele",
    "sg:city":"Grammichele",
    "sg:orig_category":"Vetro: Prodotti E Lavorazioni. Forniture Per Attivita' Industriali",
    "sg:phone":"+39 0933 941034",
    "sg:postcode":"95042",
    "sg:province":"Catania",
    "wof:name":"Medico Carmelo",
    "wof:placetype":"venue"
},
  "geometry": {"coordinates":[14.640933,37.216114],"type":"Point"}
}