{
  "type": "Feature",
  "properties": {
    "addr:full":"20048 Carate Brianza Carate Brianza Milano 20048",
    "addr:postcode":"20048;20048",
    "iso:country":"IT",
    "sg:address":"20048 Carate Brianza",
    "sg:city":"Carate Brianza",
    "sg:orig_category":"Ovatte Grezze E Lavorate",
    "sg:phone":"+39 036 299 2342",
    "sg:postcode":"20048",
    "sg:province":"Milano",
    "wof:name":"Barbiflex Snc",
    "wof:placetype":"venue"
},
  "geometry": {"coordinates":[9.22682,45.670532],"type":"Point"}
}