{
  "type": "Feature",
  "properties": {
    "iso:country":"IT",
    "sg:address":"33, Via Campania 41051 Castelnuovo Rangone",
    "sg:city":"Castelnuovo Rangone",
    "sg:classifiers":[
        {
            "category":"Manufacturing",
            "subcategory":"Rubber & Plastics",
            "type":"Manufacturing & Wholesale Goods"
        }
    ],
    "sg:phone":"+39 39059530808",
    "sg:postcode":"41051",
    "sg:province":"Modena",
    "wof:name":"Segno Di De Curtis Lorenzo",
    "wof:placetype":"venue"
},
  "geometry": {"coordinates":[10.911775589,44.5684013367],"type":"Point"}
}