{
  "type": "Feature",
  "properties": {
    "iso:country":"IT",
    "sg:address":"2, Via Piemonte 35020 Due Carrare",
    "sg:city":"Due Carrare",
    "sg:classifiers":[
        {
            "category":"Personal",
            "subcategory":"Shoe Repair & Shine",
            "type":"Services"
        }
    ],
    "sg:phone":"+39 049 529 0122",
    "sg:postcode":"35020",
    "sg:province":"Padova",
    "sg:tags":[
        "leather"
    ],
    "wof:name":"Minucoop (soc.coop.r.l.)",
    "wof:placetype":"venue"
},
  "geometry": {"coordinates":[11.868649,45.352444],"type":"Point"}
}