{
  "type": "Feature",
  "properties": {
    "addr:full":"Strada Statale Belchiaro 47012 Civitella Di Romagna Civitella di Romagna Forl\u00ec-Cesena 47012",
    "addr:postcode":"47012;47012",
    "addr:street":"Strada Statale Belchiaro",
    "iso:country":"IT",
    "sg:address":"Strada Statale Belchiaro 47012 Civitella Di Romagna",
    "sg:city":"Civitella di Romagna",
    "sg:classifiers":[
        {
            "category":"Professional",
            "subcategory":"Engineering",
            "type":"Services"
        }
    ],
    "sg:phone":"+39 0543 983424",
    "sg:postcode":"47012",
    "sg:province":"Forl\u00ec-Cesena",
    "sg:tags":[
        "machine",
        "-",
        "mechanical"
    ],
    "wof:name":"Babbini Fratelli",
    "wof:placetype":"venue"
},
  "geometry": {"coordinates":[11.980461,43.994766],"type":"Point"}
}