{
  "type": "Feature",
  "properties": {
    "addr:full":"10144 Torino Torino Torino 10144",
    "addr:postcode":"10144;10144",
    "iso:country":"IT",
    "sg:address":"10144 Torino",
    "sg:city":"Torino",
    "sg:orig_category":"Forniture Per Attivita' Industriali",
    "sg:phone":"+39 011 473 1553",
    "sg:postcode":"10144",
    "sg:province":"Torino",
    "wof:name":"Abras Abrasivi S.n.c.",
    "wof:placetype":"venue"
},
  "geometry": {"coordinates":[7.6563391685,45.0854797363],"type":"Point"}
}