{
  "type": "Feature",
  "properties": {
    "addr:full":"Via Leonardo Da Vinci 15 35015 Galliera Veneta Galliera Veneta Padova 35015",
    "addr:housenumber":"15",
    "addr:postcode":"35015;35015",
    "addr:street":"Via Leonardo Da Vinci",
    "iso:country":"IT",
    "sg:address":"Via Leonardo Da Vinci 15 35015 Galliera Veneta",
    "sg:city":"Galliera Veneta",
    "sg:classifiers":[
        {
            "category":"Animal Shelter",
            "type":"Public Place"
        }
    ],
    "sg:phone":"+39 049 596 9953",
    "sg:postcode":"35015",
    "sg:province":"Padova",
    "sg:tags":[
        "cage"
    ],
    "sg:website":"www.cifafurgoni.com",
    "wof:name":"Cifa Srl",
    "wof:placetype":"venue"
},
  "geometry": {"coordinates":[11.857697,45.64505],"type":"Point"}
}