{
  "type": "Feature",
  "properties": {
    "iso:country":"IT",
    "sg:address":"21020 Buguggiate",
    "sg:city":"Buguggiate",
    "sg:orig_category":"Macchine, Impianti E Forniture Per Industria Grafica, Cartaria E Cartotecnica. Automazione E Macchine Per Ufficio",
    "sg:phone":"+39 0332 456011",
    "sg:postcode":"21020",
    "sg:province":"Varese",
    "wof:name":"Eprom Srl",
    "wof:placetype":"venue"
},
  "geometry": {"coordinates":[8.79957,45.790642],"type":"Point"}
}