{
  "type": "Feature",
  "properties": {
    "iso:country":"IT",
    "sg:address":"33050 Pozzuolo Del Friuli",
    "sg:city":"Pozzuolo del Friuli",
    "sg:orig_category":"Petroli, Gas E Combustibili. Materiali Edili",
    "sg:phone":"+39 0432 665272",
    "sg:postcode":"33050",
    "sg:province":"Udine",
    "wof:name":"De Cecco Coperture Srl",
    "wof:placetype":"venue"
},
  "geometry": {"coordinates":[13.1994514465,45.9845924377],"type":"Point"}
}