{
  "type": "Feature",
  "properties": {
    "addr:full":"01100 Viterbo Viterbo Viterbo 01100",
    "addr:postcode":"01100;01100",
    "iso:country":"IT",
    "sg:address":"01100 Viterbo",
    "sg:city":"Viterbo",
    "sg:classifiers":[
        {
            "category":"Organizations",
            "subcategory":"Labor Organization",
            "type":"Services"
        }
    ],
    "sg:phone":"+39 0761 304006",
    "sg:postcode":"01100",
    "sg:province":"Viterbo",
    "sg:tags":[
        "food",
        "industry",
        "drink",
        "work"
    ],
    "wof:name":"Molino Profili Giuseppe Sas",
    "wof:placetype":"venue"
},
  "geometry": {"coordinates":[12.0489788055,42.4415359497],"type":"Point"}
}