{
  "type": "Feature",
  "properties": {
    "iso:country":"IT",
    "sg:address":"88046 Lamezia Terme",
    "sg:city":"Lamezia Terme",
    "sg:orig_category":"Frutta E Verdura - Ingrosso",
    "sg:phone":"+39 0968 431000",
    "sg:postcode":"88046",
    "sg:province":"Catanzaro",
    "wof:name":"Macno Fruitts",
    "wof:placetype":"venue"
},
  "geometry": {"coordinates":[16.2894477844,38.9640922546],"type":"Point"}
}