{
  "type": "Feature",
  "properties": {
    "addr:full":"Via A. Volta 9 36057 Arcugnano Arcugnano Vicenza 36057",
    "addr:housenumber":"9",
    "addr:postcode":"36057;36057",
    "addr:street":"Via A. Volta",
    "iso:country":"IT",
    "sg:address":"Via A. Volta 9 36057 Arcugnano",
    "sg:city":"Arcugnano",
    "sg:classifiers":[
        {
            "category":"Health Services",
            "subcategory":"Nursing And Care Facility",
            "type":"Services"
        }
    ],
    "sg:phone":"+39 0444 289200",
    "sg:postcode":"36057",
    "sg:province":"Vicenza",
    "sg:tags":[
        "electro-medical",
        "apparatus"
    ],
    "sg:website":"www.asalaser.com",
    "wof:name":"Asa Srl",
    "wof:placetype":"venue"
},
  "geometry": {"coordinates":[11.510918,45.51123],"type":"Point"}
}