{
  "type": "Feature",
  "properties": {
    "iso:country":"IT",
    "sg:address":"20010 Arluno",
    "sg:city":"Arluno",
    "sg:orig_category":"Riparazione Dei Mezzi Di Trasporto. Servizi Ausiliari Dei Mezzi Di Trasporto",
    "sg:phone":"+39 02 902 5101",
    "sg:postcode":"20010",
    "sg:province":"Milano",
    "wof:name":"Jas Engineering Italia Srl",
    "wof:placetype":"venue"
},
  "geometry": {"coordinates":[9.149752,45.377644],"type":"Point"}
}