{
  "type": "Feature",
  "properties": {
    "iso:country":"IT",
    "sg:address":"10095 Grugliasco",
    "sg:city":"Grugliasco",
    "sg:orig_category":"Utensili Meccanici E Materiali",
    "sg:phone":"+39 011 403 7811",
    "sg:postcode":"10095",
    "sg:province":"Torino",
    "wof:name":"Model-car Snc",
    "wof:placetype":"venue"
},
  "geometry": {"coordinates":[7.601757,45.064682],"type":"Point"}
}