{
  "type": "Feature",
  "properties": {
    "iso:country":"IT",
    "sg:address":"96/98, Viale Indipendenza 62100 Macerata",
    "sg:city":"Macerata",
    "sg:classifiers":[
        {
            "category":"Shopping",
            "subcategory":"Computers & Home Electronics",
            "type":"Retail Goods"
        }
    ],
    "sg:phone":"+39 0733 262236",
    "sg:postcode":"62100",
    "sg:province":"Macerata",
    "sg:tags":[
        "electronic",
        "electrical",
        "equipment"
    ],
    "wof:name":"M.c.m. Di Carbonari S.r.l.",
    "wof:placetype":"venue"
},
  "geometry": {"coordinates":[13.425877,43.296223],"type":"Point"}
}