{
  "type": "Feature",
  "properties": {
    "iso:country":"IT",
    "sg:address":"00189 Roma",
    "sg:city":"Roma",
    "sg:orig_category":"Servizi E Lavori Per Ecologia E Smaltimento Rifiuti. Acqua, Luce, Gas E Societa' Di Esercizio Pubblico",
    "sg:phone":"+39 06 3361 0009",
    "sg:postcode":"00189",
    "sg:province":"Roma",
    "wof:name":"A.m.a. Roma",
    "wof:placetype":"venue"
},
  "geometry": {"coordinates":[12.494854,41.99255],"type":"Point"}
}