{
  "type": "Feature",
  "properties": {
    "addr:full":"72100 Brindisi Brindisi Brindisi 72100",
    "addr:postcode":"72100;72100",
    "iso:country":"IT",
    "sg:address":"72100 Brindisi",
    "sg:city":"Brindisi",
    "sg:orig_category":"Oli Alimentari E Frantoi Oleari",
    "sg:phone":"+39 0831 517315",
    "sg:postcode":"72100",
    "sg:province":"Brindisi",
    "wof:name":"Guarini Liaci Sas",
    "wof:placetype":"venue"
},
  "geometry": {"coordinates":[17.926907,40.634781],"type":"Point"}
}