{
  "type": "Feature",
  "properties": {
    "addr:full":"25033 Cologne Cologne Brescia 25033",
    "addr:postcode":"25033;25033",
    "iso:country":"IT",
    "sg:address":"25033 Cologne",
    "sg:city":"Cologne",
    "sg:orig_category":"Servizi E Lavori Industria Chimica. Trattamenti Termici E Superficiali Metalli, Galvanotecnica",
    "sg:phone":"+39 030 715 6854",
    "sg:postcode":"25033",
    "sg:province":"Brescia",
    "wof:name":"Alghisi Alberto & C. Snc",
    "wof:placetype":"venue"
},
  "geometry": {"coordinates":[10.210238,45.534145],"type":"Point"}
}