{
  "type": "Feature",
  "properties": {
    "iso:country":"IT",
    "sg:address":"44100 Ferrara",
    "sg:city":"Ferrara",
    "sg:orig_category":"Imprese Di Costruzioni Civili Ed Industriali",
    "sg:phone":"+39 0532 206229",
    "sg:postcode":"44100",
    "sg:province":"Ferrara",
    "wof:name":"Silgeo Sas Di Sileo Mariantonietta & C.",
    "wof:placetype":"venue"
},
  "geometry": {"coordinates":[11.624594,44.832333],"type":"Point"}
}