{
  "type": "Feature",
  "properties": {
    "iso:country":"IT",
    "sg:address":"97015 Modica",
    "sg:city":"Modica",
    "sg:orig_category":"Maglierie - Vendita Al Dettaglio",
    "sg:phone":"+39 0932 456002",
    "sg:postcode":"97015",
    "sg:province":"Ragusa",
    "wof:name":"Antonella Corredo Maglieria",
    "wof:placetype":"venue"
},
  "geometry": {"coordinates":[14.765966,36.842911],"type":"Point"}
}