{
  "type": "Feature",
  "properties": {
    "iso:country":"IT",
    "sg:address":"Via Municipio 1, Torchiati, 83026 Montoro Superiore, Av",
    "sg:city":"Montoro Superiore",
    "sg:classifiers":[
        {
            "category":"Banks & Credit Unions",
            "subcategory":"Bank",
            "type":"Services"
        }
    ],
    "sg:postcode":"83026",
    "sg:province":"Avellino",
    "wof:name":"Banca Di Credito Cooperativo Valle Dell 'irno Scrl",
    "wof:placetype":"venue"
},
  "geometry": {"coordinates":[14.802507,40.819168],"type":"Point"}
}