{
  "type": "Feature",
  "properties": {
    "iso:country":"IT",
    "sg:address":"31057 Silea",
    "sg:city":"Silea",
    "sg:orig_category":"Ospedali E Servizi Sanitari",
    "sg:phone":"+39 0422 362891",
    "sg:postcode":"31057",
    "sg:province":"Treviso",
    "wof:name":"Panizzo Dr. Luigi",
    "wof:placetype":"venue"
},
  "geometry": {"coordinates":[12.298195,45.654148],"type":"Point"}
}