{
  "type": "Feature",
  "properties": {
    "iso:country":"IT",
    "sg:address":"55100 Lucca",
    "sg:city":"Lucca",
    "sg:orig_category":"Arredamenti E Mobili Professionali. Arredi Ed Attrezzature Per Uffici",
    "sg:phone":"+39 0583 495566",
    "sg:postcode":"55100",
    "sg:province":"Lucca",
    "wof:name":"Neoarredo Srl",
    "wof:placetype":"venue"
},
  "geometry": {"coordinates":[10.517585,43.840492],"type":"Point"}
}