{
  "type": "Feature",
  "properties": {
    "iso:country":"IT",
    "sg:address":"Via Socrate 2/c 20041 Agrate Brianza",
    "sg:city":"Agrate Brianza",
    "sg:classifiers":[
        {
            "category":"Park",
            "subcategory":"Municipal",
            "type":"Public Place"
        }
    ],
    "sg:phone":"+39 039 605 6769",
    "sg:postcode":"20041",
    "sg:province":"Milano",
    "sg:tags":[
        "waste-water",
        "industrial",
        "treatment"
    ],
    "sg:website":"www.tecnodepur.com",
    "wof:name":"Tecnodepur Srl",
    "wof:placetype":"venue"
},
  "geometry": {"coordinates":[9.3266811371,45.5669403076],"type":"Point"}
}