{
  "type": "Feature",
  "properties": {
    "iso:country":"IT",
    "sg:address":"16, Piazzale Dell' Agricoltura 33100 Udine",
    "sg:city":"Udine",
    "sg:classifiers":[
        {
            "category":"Food & Beverages",
            "subcategory":"Groceries & Convenience Stores",
            "type":"Retail Goods"
        }
    ],
    "sg:phone":"+39 0432 521540",
    "sg:postcode":"33100",
    "sg:province":"Udine",
    "sg:tags":[
        "product",
        "related"
    ],
    "wof:name":"Damiani S.r.l.",
    "wof:placetype":"venue"
},
  "geometry": {"coordinates":[13.2398586273,46.037563324],"type":"Point"}
}