{
  "type": "Feature",
  "properties": {
    "addr:full":"1/b, V. Tezze Di Cereda 36073 Cornedo Vicentino Cereda Vicenza 36073",
    "addr:housenumber":"1 / b v.",
    "addr:postcode":"36073;36073",
    "addr:street":"Tezze;Cereda;Vicentino Cereda",
    "iso:country":"IT",
    "sg:address":"1/b, V. Tezze Di Cereda 36073 Cornedo Vicentino",
    "sg:city":"Cereda",
    "sg:classifiers":[
        {
            "category":"Shopping",
            "type":"Retail Goods"
        }
    ],
    "sg:phone":"+39 0445 951807",
    "sg:postcode":"36073",
    "sg:province":"Vicenza",
    "sg:tags":[
        "finished",
        "-",
        "metallic"
    ],
    "sg:website":"http://www.tessaroferro.it",
    "wof:name":"Tessaro Srl",
    "wof:placetype":"venue"
},
  "geometry": {"coordinates":[11.3940105438,45.5812835693],"type":"Point"}
}