{
  "type": "Feature",
  "properties": {
    "iso:country":"IT",
    "sg:address":"140, Via S. Cassiano 28069 Trecate",
    "sg:city":"Trecate",
    "sg:classifiers":[
        {
            "category":"Wholesale",
            "subcategory":"Drugs",
            "type":"Manufacturing & Wholesale Goods"
        }
    ],
    "sg:phone":"+39 390 321 7981",
    "sg:postcode":"28069",
    "sg:province":"Novara",
    "sg:tags":[
        "chemical",
        "pharmaceutical"
    ],
    "wof:name":"Columbian Carbon Europa (s.r.l.)",
    "wof:placetype":"venue"
},
  "geometry": {"coordinates":[8.768719,45.435467],"type":"Point"}
}