{
  "type": "Feature",
  "properties": {
    "addr:full":"27100 Pavia Pavia Pavia 27100",
    "addr:postcode":"27100;27100",
    "iso:country":"IT",
    "sg:address":"27100 Pavia",
    "sg:city":"Pavia",
    "sg:orig_category":"Servizi E Lavori Per Edilizia E Lavori Pubblici",
    "sg:phone":"+39 0382 471947",
    "sg:postcode":"27100",
    "sg:province":"Pavia",
    "wof:name":"Color Service Snc",
    "wof:placetype":"venue"
},
  "geometry": {"coordinates":[9.08101,45.250931],"type":"Point"}
}