{
  "type": "Feature",
  "properties": {
    "addr:full":"16121 Genova Genova Genova 16121",
    "addr:postcode":"16121;16121",
    "iso:country":"IT",
    "sg:address":"16121 Genova",
    "sg:city":"Genova",
    "sg:orig_category":"Forniture Industriali Per Prevenzione, Controllo E Sicurezza",
    "sg:phone":"+39 010 543463",
    "sg:postcode":"16121",
    "sg:province":"Genova",
    "wof:name":"Emerson & Co. S.r.l.",
    "wof:placetype":"venue"
},
  "geometry": {"coordinates":[8.8880691528,44.9679908752],"type":"Point"}
}