{
  "type": "Feature",
  "properties": {
    "iso:country":"IT",
    "sg:address":"13040 Palazzolo Vercellese",
    "sg:city":"Palazzolo Vercellese",
    "sg:orig_category":"Prodotti Alimentari. Agricoltura, Orticoltura E Floricoltura",
    "sg:phone":"+39 0161 818115",
    "sg:postcode":"13040",
    "sg:province":"Vercelli",
    "wof:name":"Pigino Carlo & Figlio S.n.c.",
    "wof:placetype":"venue"
},
  "geometry": {"coordinates":[8.2308063507,45.185585022],"type":"Point"}
}