{
  "type": "Feature",
  "properties": {
    "addr:full":"10070 Front Front Torino 10070",
    "addr:housenumber":"10070",
    "addr:postcode":"10070",
    "addr:street":"Front Front",
    "iso:country":"IT",
    "sg:address":"10070 Front",
    "sg:city":"Front",
    "sg:orig_category":"Articoli Pulizia",
    "sg:phone":"+39 011 925 1556",
    "sg:postcode":"10070",
    "sg:province":"Torino",
    "wof:name":"Chiavello Francesco",
    "wof:placetype":"venue"
},
  "geometry": {"coordinates":[7.697023,45.268963],"type":"Point"}
}