{
  "type": "Feature",
  "properties": {
    "addr:full":"20037 Paderno Dugnano Paderno Dugnano Milano 20037",
    "addr:postcode":"20037;20037",
    "iso:country":"IT",
    "sg:address":"20037 Paderno Dugnano",
    "sg:city":"Paderno Dugnano",
    "sg:orig_category":"Stampaggio Materie Plastiche",
    "sg:phone":"+39 02 918 6731",
    "sg:postcode":"20037",
    "sg:province":"Milano",
    "wof:name":"Fratelli Maiocchi Di Maiocchi Walter E Luigi Snc",
    "wof:placetype":"venue"
},
  "geometry": {"coordinates":[9.183488,45.563042],"type":"Point"}
}