{
  "type": "Feature",
  "properties": {
    "addr:full":"Via Porte Di Sopra 57 45026 Lendinara Lendinara Rovigo 45026",
    "addr:housenumber":"57",
    "addr:postcode":"45026;45026",
    "addr:street":"Via Porte Di Sopra",
    "iso:country":"IT",
    "sg:address":"Via Porte Di Sopra 57 45026 Lendinara",
    "sg:city":"Lendinara",
    "sg:orig_category":"Fruits, Dried",
    "sg:phone":"+39 0425 601272",
    "sg:postcode":"45026",
    "sg:province":"Rovigo",
    "sg:website":"www.mainardisrl.com",
    "wof:name":"Mainardi Nicola Srl",
    "wof:placetype":"venue"
},
  "geometry": {"coordinates":[11.5884304047,45.0851364136],"type":"Point"}
}