{
  "type": "Feature",
  "properties": {
    "iso:country":"IT",
    "sg:address":"15100 Alessandria",
    "sg:city":"Alessandria",
    "sg:orig_category":"Materiali E Componenti Elettronici",
    "sg:phone":"+39 0131 345061",
    "sg:postcode":"15100",
    "sg:province":"Alessandria",
    "wof:name":"Odicino Giambattista E. C. S.a.s.",
    "wof:placetype":"venue"
},
  "geometry": {"coordinates":[8.605981,44.903831],"type":"Point"}
}