{
  "type": "Feature",
  "properties": {
    "addr:full":"Via Gramsci; Polesella; 45038 Polesella Rovigo 45038",
    "addr:postcode":"45038;45038",
    "addr:street":"Via Gramsci",
    "iso:country":"IT",
    "sg:address":"Via Gramsci; Polesella; 45038",
    "sg:city":"Polesella",
    "sg:classifiers":[
        {
            "category":"Banks & Credit Unions",
            "subcategory":"Bank",
            "type":"Services"
        }
    ],
    "sg:phone":"+39 0425 947018",
    "sg:postcode":"45038",
    "sg:province":"Rovigo",
    "wof:name":"Cassa Rurale Ed Artigiana, S. Apollinare",
    "wof:placetype":"venue"
},
  "geometry": {"coordinates":[11.751038,44.962433],"type":"Point"}
}