{
  "type": "Feature",
  "properties": {
    "addr:full":"19, Via Birago Dalmazio 13100 Vercelli Vercelli Vercelli 13100",
    "addr:postcode":"13100;13100",
    "addr:street":"Via Birago Dalmazio",
    "iso:country":"IT",
    "sg:address":"19, Via Birago Dalmazio 13100 Vercelli",
    "sg:city":"Vercelli",
    "sg:classifiers":[
        {
            "category":"Utilities",
            "subcategory":"Electric",
            "type":"Services"
        }
    ],
    "sg:phone":"+39 0161 212563",
    "sg:postcode":"13100",
    "sg:province":"Vercelli",
    "sg:tags":[
        "electricity"
    ],
    "wof:name":"Tecnogroup Italia S.r.l.",
    "wof:placetype":"venue"
},
  "geometry": {"coordinates":[8.412807,45.331177],"type":"Point"}
}