{
  "type": "Feature",
  "properties": {
    "iso:country":"IT",
    "sg:address":"113, Via Risorgimento 36070 San Pietro Mussolino",
    "sg:city":"San Pietro Mussolino",
    "sg:classifiers":[
        {
            "category":"Manufacturing",
            "subcategory":"Textiles",
            "type":"Manufacturing & Wholesale Goods"
        }
    ],
    "sg:phone":"+39 0444 687751",
    "sg:postcode":"36070",
    "sg:province":"Vicenza",
    "sg:tags":[
        "leather",
        "raw",
        "material",
        "-"
    ],
    "wof:name":"Conceria Rancan S.r.l.",
    "wof:placetype":"venue"
},
  "geometry": {"coordinates":[11.26227,45.578037],"type":"Point"}
}