{
  "type": "Feature",
  "properties": {
    "addr:full":"00065 Fiano Romano Fiano Romano Roma 00065",
    "addr:postcode":"00065;roma 00065",
    "addr:street":"Romano",
    "iso:country":"IT",
    "sg:address":"00065 Fiano Romano",
    "sg:city":"Fiano Romano",
    "sg:orig_category":"Pubblicita' - Cartelli, Insegne E Targhe",
    "sg:phone":"+39 0765 455844",
    "sg:postcode":"00065",
    "sg:province":"Roma",
    "wof:name":"Rb Pubblicita' Srl",
    "wof:placetype":"venue"
},
  "geometry": {"coordinates":[12.5839548111,42.1320991516],"type":"Point"}
}