{
  "type": "Feature",
  "properties": {
    "iso:country":"IT",
    "sg:address":"00185 Roma",
    "sg:city":"Roma",
    "sg:orig_category":"Avvocati, Notai E Servizi Legali. Consulenze Tecniche, Amministrative E Perizie",
    "sg:phone":"+39 06 4782 5222",
    "sg:postcode":"00185",
    "sg:province":"Roma",
    "wof:name":"Bugnion Spa",
    "wof:placetype":"venue"
},
  "geometry": {"coordinates":[12.483696,41.862274],"type":"Point"}
}