{
  "type": "Feature",
  "properties": {
    "iso:country":"IT",
    "sg:address":"Via Falzarego 8 Ospiate Di Bollate 20021 Bollate",
    "sg:city":"Bollate",
    "sg:classifiers":[
        {
            "category":"Wholesale",
            "subcategory":"Electrical",
            "type":"Manufacturing & Wholesale Goods"
        }
    ],
    "sg:phone":"+39 02 383 4151",
    "sg:postcode":"20021",
    "sg:province":"Milano",
    "sg:tags":[
        "component"
    ],
    "wof:name":"L.p.e. Spa",
    "wof:placetype":"venue"
},
  "geometry": {"coordinates":[9.188141,45.463688],"type":"Point"}
}