{
  "type": "Feature",
  "properties": {
    "addr:full":"17100 Savona Savona Savona 17100",
    "addr:postcode":"17100;17100",
    "iso:country":"IT",
    "sg:address":"17100 Savona",
    "sg:city":"Savona",
    "sg:orig_category":"Arredamenti - Vendita Al Dettaglio",
    "sg:phone":"+39 019 822762",
    "sg:postcode":"17100",
    "sg:province":"Savona",
    "wof:name":"Ferrario",
    "wof:placetype":"venue"
},
  "geometry": {"coordinates":[8.479374,44.304451],"type":"Point"}
}