{
  "type": "Feature",
  "properties": {
    "iso:country":"IT",
    "sg:address":"24056 Fontanella",
    "sg:city":"Fontanella",
    "sg:orig_category":"Agricoltura - Attrezzi, Prodotti E Forniture",
    "sg:phone":"+39 036 399 7766",
    "sg:postcode":"24056",
    "sg:province":"Bergamo",
    "wof:name":"Moro Aratri Srl",
    "wof:placetype":"venue"
},
  "geometry": {"coordinates":[9.743472,45.738983],"type":"Point"}
}