{
  "type": "Feature",
  "properties": {
    "iso:country":"IT",
    "sg:address":"35035 Mestrino",
    "sg:city":"Mestrino",
    "sg:orig_category":"Prodotti Chimici Secondari. Servizi E Lavori Per Ecologia E Smaltimento Rifiuti. Macchine E Forniture Per Ecologia E Smaltimento Rifiuti",
    "sg:phone":"+39 049 900 2555",
    "sg:postcode":"35035",
    "sg:province":"Padova",
    "wof:name":"Veronese Natascia",
    "wof:placetype":"venue"
},
  "geometry": {"coordinates":[11.7855997086,45.4302215576],"type":"Point"}
}