{
  "type": "Feature",
  "properties": {
    "addr:full":"28021 Borgomanero Borgomanero Novara 28021",
    "addr:postcode":"28021;28021",
    "iso:country":"IT",
    "sg:address":"28021 Borgomanero",
    "sg:city":"Borgomanero",
    "sg:orig_category":"Ceramiche: Prodotti E Lavorazioni",
    "sg:phone":"+39 0322 846262",
    "sg:postcode":"28021",
    "sg:province":"Novara",
    "wof:name":"Centro Edile Srl",
    "wof:placetype":"venue"
},
  "geometry": {"coordinates":[8.468518,45.704582],"type":"Point"}
}