{
  "type": "Feature",
  "properties": {
    "iso:country":"IT",
    "sg:address":"67, Via Giovanni Niggeler 25031 Capriolo",
    "sg:city":"Capriolo",
    "sg:classifiers":[
        {
            "category":"Shopping",
            "subcategory":"Crafts & Fabrics",
            "type":"Retail Goods"
        }
    ],
    "sg:phone":"+39 39030736386",
    "sg:postcode":"25031",
    "sg:province":"Brescia",
    "wof:name":"Filature Niggeler E Kupfer (s.p.a.)",
    "wof:placetype":"venue"
},
  "geometry": {"coordinates":[9.9329204559,45.6446228027],"type":"Point"}
}