{
  "type": "Feature",
  "properties": {
    "iso:country":"IT",
    "sg:address":"Via Cesare Cantu' 15/c 22031 Albavilla",
    "sg:city":"Albavilla",
    "sg:classifiers":[
        {
            "category":"Building & Trades",
            "subcategory":"Landscaping Services",
            "type":"Services"
        }
    ],
    "sg:phone":"+39 031 626422",
    "sg:postcode":"22031",
    "sg:province":"Como",
    "sg:tags":[
        "equipment",
        "safety"
    ],
    "sg:website":"www.bestidea.it",
    "wof:name":"Bestidea Srl",
    "wof:placetype":"venue"
},
  "geometry": {"coordinates":[9.140602,45.801262],"type":"Point"}
}