{
  "type": "Feature",
  "properties": {
    "iso:country":"IT",
    "sg:address":"62100 Macerata",
    "sg:city":"Macerata",
    "sg:orig_category":"Pompe. Macchine, Strumenti Ed Apparecchi Per Attivita' Industriali",
    "sg:phone":"+39 0733 202293",
    "sg:postcode":"62100",
    "sg:province":"Macerata",
    "wof:name":"Elettromeccanica Faggiolati Srl",
    "wof:placetype":"venue"
},
  "geometry": {"coordinates":[13.4190740585,43.2578315735],"type":"Point"}
}