{
  "type": "Feature",
  "properties": {
    "iso:country":"IT",
    "sg:address":"27029 Vigevano",
    "sg:city":"Vigevano",
    "sg:classifiers":[
        {
            "category":"Manufacturing",
            "subcategory":"Tools & Machinery",
            "type":"Manufacturing & Wholesale Goods"
        }
    ],
    "sg:phone":"+39 0381 84022",
    "sg:postcode":"27029",
    "sg:province":"Pavia",
    "sg:tags":[
        "leather",
        "equipment",
        "goods",
        "clothing"
    ],
    "wof:name":"Officina Meccanica Colli F.g.b. Srl",
    "wof:placetype":"venue"
},
  "geometry": {"coordinates":[8.850045,45.308205],"type":"Point"}
}