{
  "type": "Feature",
  "properties": {
    "iso:country":"IT",
    "sg:address":"20123 Milano",
    "sg:city":"Milano",
    "sg:orig_category":"Servizi Per Aziende, Manifestazioni E Supporto Agli Scambi Commerciali. Ambasciate Ed Enti Internazionali",
    "sg:phone":"+39 02 869 3688",
    "sg:postcode":"20123",
    "sg:province":"Milano",
    "wof:name":"Ambasciata Di Malta Sezione Commerciale",
    "wof:placetype":"venue"
},
  "geometry": {"coordinates":[9.188895,45.461395],"type":"Point"}
}