{
  "type": "Feature",
  "properties": {
    "iso:country":"IT",
    "sg:address":"10143 Torino",
    "sg:city":"Torino",
    "sg:orig_category":"Studi E Consulenze Tecniche E Industriali. Consulenze Tecniche, Amministrative E Perizie",
    "sg:phone":"+39 011 752026",
    "sg:postcode":"10143",
    "sg:province":"Torino",
    "wof:name":"G.e.d.i. Srl",
    "wof:placetype":"venue"
},
  "geometry": {"coordinates":[7.655042,45.085205],"type":"Point"}
}