{
  "type": "Feature",
  "properties": {
    "addr:full":"95030 Sant'agata Li Battiati Catania 95030",
    "addr:postcode":"95030;95030",
    "iso:country":"IT",
    "sg:address":"95030 Sant'agata Li Battiati",
    "sg:orig_category":"Prodotti Di Base E Forniture Per Industria Alimentare E Bevande. Prodotti Chimici Di Base",
    "sg:phone":"+39 095 725 6068",
    "sg:postcode":"95030",
    "sg:province":"Catania",
    "wof:name":"Centro Affari A.d. Di Angelo Davino",
    "wof:placetype":"venue"
},
  "geometry": {"coordinates":[15.0459156036,37.5722084045],"type":"Point"}
}