{
  "type": "Feature",
  "properties": {
    "addr:full":"35031 Abano Terme Abano Terme Padova 35031",
    "addr:postcode":"35031;35031",
    "iso:country":"IT",
    "sg:address":"35031 Abano Terme",
    "sg:city":"Abano Terme",
    "sg:orig_category":"Termotecnica E Riscaldamento, Apparecchiature E Servizi",
    "sg:phone":"+39 049 860 1501",
    "sg:postcode":"35031",
    "sg:province":"Padova",
    "wof:name":"Bademer Tiziano",
    "wof:placetype":"venue"
},
  "geometry": {"coordinates":[11.789186,45.364433],"type":"Point"}
}