{
  "type": "Feature",
  "properties": {
    "iso:country":"IT",
    "sg:address":"20030 Senago",
    "sg:city":"Senago",
    "sg:orig_category":"Dolciumi E Gelati",
    "sg:phone":"+39 02 9981 3035",
    "sg:postcode":"20030",
    "sg:province":"Milano",
    "wof:name":"Cavallaro Francesco",
    "wof:placetype":"venue"
},
  "geometry": {"coordinates":[9.15669,45.571037],"type":"Point"}
}