{
  "type": "Feature",
  "properties": {
    "iso:country":"IT",
    "sg:address":"Via Appia 04012 Cisterna Di Latina",
    "sg:city":"Cisterna di Latina",
    "sg:classifiers":[
        {
            "category":"Home & Garden",
            "subcategory":"Home Furnishings",
            "type":"Retail Goods"
        }
    ],
    "sg:phone":"+39 39069680943",
    "sg:postcode":"04012",
    "sg:province":"Latina",
    "sg:tags":[
        "household"
    ],
    "wof:name":"Legnobagno S.r.l.",
    "wof:placetype":"venue"
},
  "geometry": {"coordinates":[12.867723,41.567429],"type":"Point"}
}