{
  "type": "Feature",
  "properties": {
    "iso:country":"IT",
    "sg:address":"23017 Morbegno",
    "sg:city":"Morbegno",
    "sg:orig_category":"Scuole E Servizi Scolastici. Servizi Per Lo Sport E Il Tempo Libero",
    "sg:phone":"+39 0342 610937",
    "sg:postcode":"23017",
    "sg:province":"Sondrio",
    "wof:name":"Solieri Alga",
    "wof:placetype":"venue"
},
  "geometry": {"coordinates":[9.567037,46.134415],"type":"Point"}
}