{
  "type": "Feature",
  "properties": {
    "iso:country":"IT",
    "sg:address":"40126 Bologna",
    "sg:city":"Bologna",
    "sg:orig_category":"Ristoranti",
    "sg:phone":"+39 051 231576",
    "sg:postcode":"40126",
    "sg:province":"Bologna",
    "wof:name":"Osteria Dell'orsa",
    "wof:placetype":"venue"
},
  "geometry": {"coordinates":[11.349402,44.498432],"type":"Point"}
}