{
  "type": "Feature",
  "properties": {
    "iso:country":"IT",
    "sg:address":"20068 Peschiera Borromeo",
    "sg:city":"Peschiera Borromeo",
    "sg:orig_category":"Lavorazioni Metalli, Stampaggio E Saldatura",
    "sg:phone":"+39 02 547 0579",
    "sg:postcode":"20068",
    "sg:province":"Milano",
    "wof:name":"Recrosio Giusto",
    "wof:placetype":"venue"
},
  "geometry": {"coordinates":[9.303743,45.439217],"type":"Point"}
}