{
  "type": "Feature",
  "properties": {
    "addr:full":"06061 Castiglione Del Lago Castiglione del Lago Perugia 06061",
    "addr:postcode":"06061;06061",
    "iso:country":"IT",
    "sg:address":"06061 Castiglione Del Lago",
    "sg:city":"Castiglione del Lago",
    "sg:orig_category":"Non-classified Establishments",
    "sg:phone":"+39 075 965 9000",
    "sg:postcode":"06061",
    "sg:province":"Perugia",
    "wof:name":"Falegnameria Forconi Antonio E Giuseppe & C. Snc",
    "wof:placetype":"venue"
},
  "geometry": {"coordinates":[12.003296,43.10107],"type":"Point"}
}