{
  "type": "Feature",
  "properties": {
    "iso:country":"IT",
    "sg:address":"105, Via Peveragno 12012 Boves",
    "sg:city":"Boves",
    "sg:classifiers":[
        {
            "category":"Autos & Motor Vehicles",
            "subcategory":"Automobile Sales",
            "type":"Retail Goods"
        }
    ],
    "sg:phone":"+39 0171 388844",
    "sg:postcode":"12012",
    "sg:province":"Cuneo",
    "sg:tags":[
        "motor-cars"
    ],
    "wof:name":"Franchino Motors Di Franchino Valter",
    "wof:placetype":"venue"
},
  "geometry": {"coordinates":[7.56635952,44.332611084],"type":"Point"}
}