{
  "type": "Feature",
  "properties": {
    "iso:country":"IT",
    "sg:address":"37010 Piovezzano",
    "sg:city":"Piovezzano",
    "sg:orig_category":"Agenzie D'affari E Servizi Commerciali",
    "sg:phone":"+39 045 677 0448",
    "sg:postcode":"37010",
    "sg:province":"Verona",
    "wof:name":"Benacus Trading E Servizi Di Rampazzo Walter E C. Sas",
    "wof:placetype":"venue"
},
  "geometry": {"coordinates":[10.797518,45.504086],"type":"Point"}
}