{
  "type": "Feature",
  "properties": {
    "iso:country":"IT",
    "sg:address":"16158 Genova",
    "sg:city":"Genova",
    "sg:orig_category":"Pompe. Elettrotecnica Industriale, Prodotti E Apparecchiature",
    "sg:phone":"+39 010 613 0224",
    "sg:postcode":"16158",
    "sg:province":"Genova",
    "wof:name":"Elpo Srl",
    "wof:placetype":"venue"
},
  "geometry": {"coordinates":[8.739982605,44.431930542],"type":"Point"}
}