{
  "type": "Feature",
  "properties": {
    "iso:country":"IT",
    "sg:address":"20149 Milano",
    "sg:city":"Milano",
    "sg:orig_category":"Forniture Per Abbigliamento E Pelletterie",
    "sg:phone":"+39 02 331 5754",
    "sg:postcode":"20149",
    "sg:province":"Milano",
    "wof:name":"Pozzari Claudio",
    "wof:placetype":"venue"
},
  "geometry": {"coordinates":[9.156085968,45.4835472107],"type":"Point"}
}