{
  "type": "Feature",
  "properties": {
    "iso:country":"IT",
    "sg:address":"Corso Trieste; Caserta; 81100",
    "sg:city":"Caserta",
    "sg:classifiers":[
        {
            "category":"Banks & Credit Unions",
            "subcategory":"Bank",
            "type":"Services"
        }
    ],
    "sg:phone":"+39 0823 321112",
    "sg:postcode":"81100",
    "sg:province":"Caserta",
    "wof:name":"Credito Italiano Spa",
    "wof:placetype":"venue"
},
  "geometry": {"coordinates":[14.336032,41.071873],"type":"Point"}
}