{
  "type": "Feature",
  "properties": {
    "iso:country":"IT",
    "sg:address":"10090 Villarbasse",
    "sg:city":"Villarbasse",
    "sg:orig_category":"Lavorazioni Metalli, Stampaggio E Saldatura",
    "sg:phone":"+39 011 952 8496",
    "sg:postcode":"10090",
    "sg:province":"Torino",
    "wof:name":"Delta Macchine Utensili Snc Di Baldin L. E Santin A.",
    "wof:placetype":"venue"
},
  "geometry": {"coordinates":[7.49611,45.048519],"type":"Point"}
}