{
  "type": "Feature",
  "properties": {
    "iso:country":"IT",
    "sg:address":"Via Privata Maestri Del Lavoro 29 20025 Legnano",
    "sg:city":"Legnano",
    "sg:classifiers":[
        {
            "category":"Shopping",
            "subcategory":"Clothing, Apparel, & Fashions",
            "type":"Retail Goods"
        }
    ],
    "sg:phone":"+39 0331 742711",
    "sg:postcode":"20025",
    "sg:province":"Milano",
    "sg:tags":[
        "fisherman",
        "clothing",
        "angler"
    ],
    "wof:name":"Shimano Italy Fishing Srl",
    "wof:placetype":"venue"
},
  "geometry": {"coordinates":[9.188141,45.463688],"type":"Point"}
}