{
  "type": "Feature",
  "properties": {
    "addr:full":"95128 Catania Catania Catania 95128",
    "addr:postcode":"95128;95128",
    "iso:country":"IT",
    "sg:address":"95128 Catania",
    "sg:city":"Catania",
    "sg:orig_category":"Abbigliamento Alta Moda E Stilisti - Boutiques",
    "sg:phone":"+39 095 504985",
    "sg:postcode":"95128",
    "sg:province":"Catania",
    "wof:name":"Atelier Di Alfonso Zappulla",
    "wof:placetype":"venue"
},
  "geometry": {"coordinates":[15.091979,37.516075],"type":"Point"}
}