{
  "type": "Feature",
  "properties": {
    "addr:full":"14, Contrada Pezzamandra 95045 Misterbianco Misterbianco Catania 95045",
    "addr:postcode":"95045;95045",
    "addr:street":"Contrada Pezzamandra",
    "iso:country":"IT",
    "sg:address":"14, Contrada Pezzamandra 95045 Misterbianco",
    "sg:city":"Misterbianco",
    "sg:classifiers":[
        {
            "category":"Manufacturing",
            "subcategory":"Food",
            "type":"Manufacturing & Wholesale Goods"
        }
    ],
    "sg:phone":"+39 39095483888",
    "sg:postcode":"95045",
    "sg:province":"Catania",
    "sg:tags":[
        "equipment",
        "processing",
        "-",
        "machinery"
    ],
    "wof:name":"Cogemat S.r.l.",
    "wof:placetype":"venue"
},
  "geometry": {"coordinates":[15.0206756592,37.5290908813],"type":"Point"}
}