{
  "type": "Feature",
  "properties": {
    "iso:country":"IT",
    "sg:address":"06019 Umbertide",
    "sg:city":"Umbertide",
    "sg:classifiers":[
        {
            "category":"Government",
            "subcategory":"Office",
            "type":"Public Place"
        }
    ],
    "sg:phone":"+39 075 941 7822",
    "sg:postcode":"06019",
    "sg:province":"Perugia",
    "sg:tags":[
        "e",
        "lo",
        "tempo",
        "libero",
        "per",
        "spettacolo",
        "servizi",
        "culturali",
        "sport",
        "il"
    ],
    "wof:name":"Banda Musicale Cittadina",
    "wof:placetype":"venue"
},
  "geometry": {"coordinates":[12.326642,43.303989],"type":"Point"}
}