{
  "type": "Feature",
  "properties": {
    "iso:country":"IT",
    "sg:address":"26831 Casalmaiocco",
    "sg:city":"Casalmaiocco",
    "sg:orig_category":"Zootecnia E Pesca, Allevamento Piccoli Animali",
    "sg:phone":"+39 02 981 0081",
    "sg:postcode":"26831",
    "sg:province":"Lodi",
    "wof:name":"Boccalari Dante",
    "wof:placetype":"venue"
},
  "geometry": {"coordinates":[9.368587,45.353523],"type":"Point"}
}