{
  "type": "Feature",
  "properties": {
    "addr:full":"Via San Tiziano 54 35010 Trebaseleghe Trebaseleghe Padova 35010",
    "addr:housenumber":"54",
    "addr:postcode":"35010;35010",
    "addr:street":"Via San Tiziano",
    "iso:country":"IT",
    "sg:address":"Via San Tiziano 54 35010 Trebaseleghe",
    "sg:city":"Trebaseleghe",
    "sg:classifiers":[
        {
            "category":"Food & Beverages",
            "subcategory":"Liquor & Beverages",
            "type":"Retail Goods"
        }
    ],
    "sg:phone":"+39 049 579 6492",
    "sg:postcode":"35010",
    "sg:province":"Padova",
    "sg:tags":[
        "wine",
        "italian"
    ],
    "wof:name":"Baia Ermosa S.a.s.",
    "wof:placetype":"venue"
},
  "geometry": {"coordinates":[12.019598,45.578228],"type":"Point"}
}