{
  "type": "Feature",
  "properties": {
    "addr:full":"25018 Montichiari Montichiari Brescia 25018",
    "addr:postcode":"25018;25018",
    "iso:country":"IT",
    "sg:address":"25018 Montichiari",
    "sg:city":"Montichiari",
    "sg:classifiers":[
        {
            "category":"Home & Garden",
            "subcategory":"Home Furnishings",
            "type":"Retail Goods"
        }
    ],
    "sg:phone":"+39 030 996 0845",
    "sg:postcode":"25018",
    "sg:province":"Brescia",
    "sg:tags":[
        "household",
        "appliance",
        "furnishings",
        "kitchen"
    ],
    "wof:name":"Linea Cucine Di Maccarinelli L. E C. Snc",
    "wof:placetype":"venue"
},
  "geometry": {"coordinates":[10.4008789062,45.3938026428],"type":"Point"}
}