{
  "type": "Feature",
  "properties": {
    "iso:country":"IT",
    "sg:address":"20129 Milano",
    "sg:city":"Milano",
    "sg:orig_category":"Carni, Salumi E Pesci",
    "sg:phone":"+39 02 799900",
    "sg:postcode":"20129",
    "sg:province":"Milano",
    "wof:name":"Magni Lorenzo",
    "wof:placetype":"venue"
},
  "geometry": {"coordinates":[9.206733,45.467655],"type":"Point"}
}