{
  "type": "Feature",
  "properties": {
    "addr:full":"00195 Roma Roma Roma 00195",
    "addr:postcode":"00195;00195",
    "iso:country":"IT",
    "sg:address":"00195 Roma",
    "sg:city":"Roma",
    "sg:orig_category":"Infermieri Ed Assistenza Domiciliare",
    "sg:phone":"+39 06 3735 0515",
    "sg:postcode":"00195",
    "sg:province":"Roma",
    "wof:name":"Pelle Lucio",
    "wof:placetype":"venue"
},
  "geometry": {"coordinates":[12.727676,41.826309],"type":"Point"}
}