{
  "type": "Feature",
  "properties": {
    "addr:full":"73012 Campi Salentina Campi Salentina Lecce 73012",
    "addr:postcode":"73012;73012",
    "iso:country":"IT",
    "sg:address":"73012 Campi Salentina",
    "sg:city":"Campi Salentina",
    "sg:orig_category":"Ospedali E Servizi Sanitari",
    "sg:phone":"+39 0832 794362",
    "sg:postcode":"73012",
    "sg:province":"Lecce",
    "wof:name":"Trevisi Aurelio",
    "wof:placetype":"venue"
},
  "geometry": {"coordinates":[18.03879,40.395985],"type":"Point"}
}