{
  "type": "Feature",
  "properties": {
    "addr:full":"20058 Villasanta Villasanta Milano 20058",
    "addr:postcode":"20058;20058",
    "iso:country":"IT",
    "sg:address":"20058 Villasanta",
    "sg:city":"Villasanta",
    "sg:orig_category":"Macchine Utensili E Impianti",
    "sg:phone":"+39 039 302189",
    "sg:postcode":"20058",
    "sg:province":"Milano",
    "wof:name":"Colombo Giovanni Costruzioni Meccaniche (s.n.c.)",
    "wof:placetype":"venue"
},
  "geometry": {"coordinates":[9.149907,45.479897],"type":"Point"}
}