{
  "type": "Feature",
  "properties": {
    "iso:country":"IT",
    "sg:address":"47842 San Giovanni In Marignano",
    "sg:city":"Montalbano",
    "sg:orig_category":"Persiane Ed Avvolgibili",
    "sg:phone":"+39 0541 955505",
    "sg:postcode":"47842",
    "sg:province":"Rimini",
    "wof:name":"Isolcasa Srl",
    "wof:placetype":"venue"
},
  "geometry": {"coordinates":[12.6833333969,43.9613609314],"type":"Point"}
}