{
  "type": "Feature",
  "properties": {
    "addr:full":"1/b, Via Chiusa Pesio 12081 Beinette Beinette Cuneo 12081",
    "addr:housenumber":"1 / b",
    "addr:postcode":"12081;12081",
    "addr:street":"Via Chiusa Pesio",
    "iso:country":"IT",
    "sg:address":"1/b, Via Chiusa Pesio 12081 Beinette",
    "sg:city":"Beinette",
    "sg:classifiers":[
        {
            "category":"Manufacturing",
            "subcategory":"Food",
            "type":"Manufacturing & Wholesale Goods"
        }
    ],
    "sg:phone":"+39 0171 384962",
    "sg:postcode":"12081",
    "sg:province":"Cuneo",
    "sg:tags":[
        "equipment",
        "processing",
        "-",
        "machinery"
    ],
    "wof:name":"Mastof (s.r.l.)",
    "wof:placetype":"venue"
},
  "geometry": {"coordinates":[7.6505746841,44.3593215942],"type":"Point"}
}