{
  "type": "Feature",
  "properties": {
    "iso:country":"IT",
    "sg:address":"20090 Segrate",
    "sg:city":"Segrate",
    "sg:classifiers":[
        {
            "category":"Health Services",
            "subcategory":"Health Practitioner",
            "type":"Services"
        }
    ],
    "sg:phone":"+39 02 213 1192",
    "sg:postcode":"20090",
    "sg:province":"Milano",
    "sg:tags":[
        "medici"
    ],
    "wof:name":"Gattuso Salvino",
    "wof:placetype":"venue"
},
  "geometry": {"coordinates":[9.290705,45.497707],"type":"Point"}
}