{
  "type": "Feature",
  "properties": {
    "addr:full":"54100 Massa Marina di Massa Massa-Carrara 54100",
    "addr:postcode":"54100;54100",
    "addr:street":"Marina;Massa-Carrara",
    "iso:country":"IT",
    "sg:address":"54100 Massa",
    "sg:city":"Marina di Massa",
    "sg:orig_category":"Campeggi, Ostelli E Villaggi Turistici",
    "sg:phone":"+39 0585 780460",
    "sg:postcode":"54100",
    "sg:province":"Massa-Carrara",
    "sg:website":"http://www.campingluna.it",
    "wof:name":"Campeggio Luna",
    "wof:placetype":"venue"
},
  "geometry": {"coordinates":[10.069397,44.027004],"type":"Point"}
}