{
  "type": "Feature",
  "properties": {
    "iso:country":"IT",
    "sg:address":"36031 Dueville",
    "sg:city":"Dueville",
    "sg:orig_category":"Fotoriproduttori E Fotocopiatrici",
    "sg:phone":"+39 0444 593069",
    "sg:postcode":"36031",
    "sg:province":"Vicenza",
    "sg:website":"http://www.paginegialle.it/remaxsolution",
    "wof:name":"Remax Solution Sas",
    "wof:placetype":"venue"
},
  "geometry": {"coordinates":[11.5769004822,45.6396751404],"type":"Point"}
}