{
  "type": "Feature",
  "properties": {
    "addr:full":"20010 Bareggio Bareggio Milano 20010",
    "addr:postcode":"20010;20010",
    "iso:country":"IT",
    "sg:address":"20010 Bareggio",
    "sg:city":"Bareggio",
    "sg:orig_category":"Articoli Da Regalo. Regalistica Aziendale",
    "sg:phone":"+39 02 9036 1190",
    "sg:postcode":"20010",
    "sg:province":"Milano",
    "wof:name":"Lustrosa Srl",
    "wof:placetype":"venue"
},
  "geometry": {"coordinates":[9.003898,45.475731],"type":"Point"}
}