{
  "type": "Feature",
  "properties": {
    "iso:country":"IT",
    "sg:address":"28, Via Archimede 20038 Seregno",
    "sg:city":"Seregno",
    "sg:classifiers":[
        {
            "category":"Parking",
            "subcategory":"Lot",
            "type":"Transportation"
        }
    ],
    "sg:phone":"+39 036 223 0401",
    "sg:postcode":"20038",
    "sg:province":"Milano",
    "sg:tags":[
        "transport",
        "road"
    ],
    "wof:name":"Autotrasporti Marta (s.n.c.)",
    "wof:placetype":"venue"
},
  "geometry": {"coordinates":[9.200424,45.637661],"type":"Point"}
}