{
  "type": "Feature",
  "properties": {
    "addr:full":"62020 Colmurano Colmurano Macerata 62020",
    "addr:postcode":"62020;62020",
    "iso:country":"IT",
    "sg:address":"62020 Colmurano",
    "sg:city":"Colmurano",
    "sg:orig_category":"Abbigliamento Esterno, Maglierie E Pelliccerie",
    "sg:phone":"+39 0733 511133",
    "sg:postcode":"62020",
    "sg:province":"Macerata",
    "wof:name":"Ottaviani Mauro - R.i.m.m. Diffusion Group",
    "wof:placetype":"venue"
},
  "geometry": {"coordinates":[13.155868,43.035725],"type":"Point"}
}