{
  "type": "Feature",
  "properties": {
    "iso:country":"IT",
    "sg:address":"42100 Reggio Emilia",
    "sg:orig_category":"Banche E Servizi Finanziari",
    "sg:phone":"+39 0522 530511",
    "sg:postcode":"42100",
    "sg:province":"Reggio Nell'Emilia",
    "wof:name":"Inno.tecs Spa",
    "wof:placetype":"venue"
},
  "geometry": {"coordinates":[10.632321,44.728573],"type":"Point"}
}