{
  "type": "Feature",
  "properties": {
    "addr:full":"Via I Maggio 22 38060 Besenello Besenello Trento 38060",
    "addr:housenumber":"22",
    "addr:postcode":"38060;38060",
    "addr:street":"Via I Maggio",
    "iso:country":"IT",
    "sg:address":"Via I Maggio 22 38060 Besenello",
    "sg:city":"Besenello",
    "sg:classifiers":[
        {
            "category":"Manufacturing",
            "subcategory":"Tools & Machinery",
            "type":"Manufacturing & Wholesale Goods"
        }
    ],
    "sg:phone":"+39 0464 820005",
    "sg:postcode":"38060",
    "sg:province":"Trento",
    "sg:tags":[
        "wood",
        "working"
    ],
    "wof:name":"G.d.a. S.n.c. Di Adami Oliviero & C .",
    "wof:placetype":"venue"
},
  "geometry": {"coordinates":[11.106471,45.941624],"type":"Point"}
}