{
  "type": "Feature",
  "properties": {
    "addr:full":"40, Viale Toscana 20093 Cologno Monzese Cologno Monzese Milano 20093",
    "addr:housenumber":"40",
    "addr:postcode":"20093;20093",
    "addr:street":"Viale Toscana",
    "iso:country":"IT",
    "sg:address":"40, Viale Toscana 20093 Cologno Monzese",
    "sg:city":"Cologno Monzese",
    "sg:classifiers":[
        {
            "category":"Shopping",
            "subcategory":"Computers & Home Electronics",
            "type":"Retail Goods"
        }
    ],
    "sg:phone":"+39 02 2730 4521",
    "sg:postcode":"20093",
    "sg:province":"Milano",
    "sg:tags":[
        "electronic",
        "electrical",
        "equipment"
    ],
    "wof:name":"We Walter S.r.l.",
    "wof:placetype":"venue"
},
  "geometry": {"coordinates":[9.278468,45.537891],"type":"Point"}
}