{
  "type": "Feature",
  "properties": {
    "iso:country":"IT",
    "sg:address":"27020 Carbonara Al Ticino",
    "sg:city":"Carbonara al Ticino",
    "sg:orig_category":"Lavanderie Industriali E Noleggio Biancheria",
    "sg:phone":"+39 0382 400130",
    "sg:postcode":"27020",
    "sg:province":"Pavia",
    "wof:name":"Bianchi Giordano",
    "wof:placetype":"venue"
},
  "geometry": {"coordinates":[9.06528,45.165302],"type":"Point"}
}