{
  "type": "Feature",
  "properties": {
    "iso:country":"IT",
    "sg:address":"2, Viale Monza 20058 Villasanta",
    "sg:city":"Villasanta",
    "sg:classifiers":[
        {
            "category":"Parking",
            "subcategory":"Lot",
            "type":"Transportation"
        }
    ],
    "sg:phone":"+39 039 205 0888",
    "sg:postcode":"20058",
    "sg:province":"Milano",
    "sg:tags":[
        "transport",
        "road"
    ],
    "wof:name":"Di.pe Srl",
    "wof:placetype":"venue"
},
  "geometry": {"coordinates":[9.308947,45.599499],"type":"Point"}
}