{
  "type": "Feature",
  "properties": {
    "addr:full":"00040 Roma Roma 00040",
    "addr:postcode":"00040;00040",
    "iso:country":"IT",
    "sg:address":"00040 Roma",
    "sg:orig_category":"Alberghi E Strutture Extra Alberghiere. Ospedali E Servizi Sanitari",
    "sg:phone":"+39 06 505 0152",
    "sg:postcode":"00040",
    "sg:province":"Roma",
    "wof:name":"Guazzolini Silvano",
    "wof:placetype":"venue"
},
  "geometry": {"coordinates":[12.500402,41.673164],"type":"Point"}
}