{
  "type": "Feature",
  "properties": {
    "iso:country":"IT",
    "sg:address":"Via Del Tritone 132; Roma; 00187",
    "sg:city":"Roma",
    "sg:classifiers":[
        {
            "category":"Banks & Credit Unions",
            "subcategory":"Bank",
            "type":"Services"
        }
    ],
    "sg:phone":"+39 06 4890 3694",
    "sg:postcode":"00187",
    "sg:province":"Roma",
    "wof:name":"Hsbc Investment Bank Plc",
    "wof:placetype":"venue"
},
  "geometry": {"coordinates":[12.487182,41.903229],"type":"Point"}
}