{
  "type": "Feature",
  "properties": {
    "iso:country":"IT",
    "sg:address":"59, Via Garibaldi Giuseppe 84015 Nocera Superiore",
    "sg:city":"Nocera Superiore",
    "sg:classifiers":[
        {
            "category":"Real Estate",
            "subcategory":"Surveying",
            "type":"Services"
        }
    ],
    "sg:phone":"+39 39081931500",
    "sg:postcode":"84015",
    "sg:province":"Salerno",
    "sg:tags":[
        "equipment",
        "material",
        "good",
        "-",
        "handling"
    ],
    "wof:name":"Inter. Car.snc Di Gaito Pasquale E C.",
    "wof:placetype":"venue"
},
  "geometry": {"coordinates":[14.706748,40.703045],"type":"Point"}
}