{
  "type": "Feature",
  "properties": {
    "addr:full":"Via Emilia E Romagna ,7 - Villatora 35020 Saonara Saonara Padova 35020",
    "addr:housenumber":"7",
    "addr:postcode":"35020;35020",
    "addr:street":"Via Emilia E Romagna",
    "iso:country":"IT",
    "sg:address":"Via Emilia E Romagna ,7 - Villatora 35020 Saonara",
    "sg:city":"Saonara",
    "sg:classifiers":[
        {
            "category":"Shopping",
            "subcategory":"Gifts & Souvenirs",
            "type":"Retail Goods"
        }
    ],
    "sg:phone":"+39 049 640366",
    "sg:postcode":"35020",
    "sg:province":"Padova",
    "sg:tags":[
        "packaging",
        "tin"
    ],
    "sg:website":"www.scatoledueg.it",
    "wof:name":"Scatolificio 2 G Di Giantin Giancarlo & C. Sas",
    "wof:placetype":"venue"
},
  "geometry": {"coordinates":[11.963057,45.378574],"type":"Point"}
}