{
  "type": "Feature",
  "properties": {
    "iso:country":"IT",
    "sg:address":"7, Via Dei Romani 80038 Pomigliano D'arco",
    "sg:classifiers":[
        {
            "category":"Utilities",
            "subcategory":"Electric",
            "type":"Services"
        }
    ],
    "sg:phone":"+39 081 521 3002",
    "sg:postcode":"80038",
    "sg:province":"Napoli",
    "sg:tags":[
        "component",
        "electronic"
    ],
    "wof:name":"L.m.p.sas Di De Michele Anna & C.",
    "wof:placetype":"venue"
},
  "geometry": {"coordinates":[14.383162,40.901642],"type":"Point"}
}