{
  "type": "Feature",
  "properties": {
    "iso:country":"IT",
    "sg:address":"V. Fornello 135 B-c 50013 Campi Bisanzio",
    "sg:classifiers":[
        {
            "category":"Professional",
            "subcategory":"Engineering",
            "type":"Services"
        }
    ],
    "sg:phone":"+39 055 896 9191",
    "sg:postcode":"50013",
    "sg:province":"Firenze",
    "sg:tags":[
        "machine",
        "-",
        "mechanical"
    ],
    "wof:name":"Centro Colori Spa",
    "wof:placetype":"venue"
},
  "geometry": {"coordinates":[11.140724,43.833015],"type":"Point"}
}