{
  "type": "Feature",
  "properties": {
    "addr:full":"43, Via Isolana 37056 Salizzole Salizzole Verona 37056",
    "addr:postcode":"37056;37056",
    "addr:street":"Via Isolana",
    "iso:country":"IT",
    "sg:address":"43, Via Isolana 37056 Salizzole",
    "sg:city":"Salizzole",
    "sg:classifiers":[
        {
            "category":"Food & Beverages",
            "subcategory":"Groceries & Convenience Stores",
            "type":"Retail Goods"
        }
    ],
    "sg:phone":"+39 045 695 4019",
    "sg:postcode":"37056",
    "sg:province":"Verona",
    "sg:tags":[
        "product",
        "related"
    ],
    "wof:name":"Negri F.lli Industria Salumi S.p.a.",
    "wof:placetype":"venue"
},
  "geometry": {"coordinates":[11.1368837357,45.2064590454],"type":"Point"}
}