{
  "type": "Feature",
  "properties": {
    "iso:country":"IT",
    "sg:address":"Via L. Zanussi 16 33070 Brugnera",
    "sg:city":"Brugnera",
    "sg:classifiers":[
        {
            "category":"Manufacturing",
            "subcategory":"Furniture",
            "type":"Manufacturing & Wholesale Goods"
        }
    ],
    "sg:phone":"+39 0434 613333",
    "sg:postcode":"33070",
    "sg:province":"Pordenone",
    "sg:tags":[
        "bedroom"
    ],
    "sg:website":"www.rigomobili.it",
    "wof:name":"Rigo Mobili",
    "wof:placetype":"venue"
},
  "geometry": {"coordinates":[12.551716,45.909431],"type":"Point"}
}