{
  "type": "Feature",
  "properties": {
    "addr:full":"22030 Orsenigo Orsenigo Como 22030",
    "addr:postcode":"22030;22030",
    "iso:country":"IT",
    "sg:address":"22030 Orsenigo",
    "sg:city":"Orsenigo",
    "sg:orig_category":"Segnaletica Stradale",
    "sg:phone":"+39 031 619650",
    "sg:postcode":"22030",
    "sg:province":"Como",
    "sg:website":"http://www.paginegialle.it/cmc",
    "wof:name":"C.m.c. Snc Di Croci Campanelli & C.",
    "wof:placetype":"venue"
},
  "geometry": {"coordinates":[9.124087,45.740204],"type":"Point"}
}