{
  "type": "Feature",
  "properties": {
    "addr:full":"20155 Milano Milano Milano 20155",
    "addr:postcode":"20155;20155",
    "iso:country":"IT",
    "sg:address":"20155 Milano",
    "sg:city":"Milano",
    "sg:orig_category":"Agenzie D'affari E Servizi Commerciali",
    "sg:phone":"+39 02 324795",
    "sg:postcode":"20155",
    "sg:province":"Milano",
    "wof:name":"Gotta Luigi",
    "wof:placetype":"venue"
},
  "geometry": {"coordinates":[9.155767,45.489304],"type":"Point"}
}