{
  "type": "Feature",
  "properties": {
    "addr:full":"Via Treviso 24 31057 Silea Silea Treviso 31057",
    "addr:housenumber":"24",
    "addr:postcode":"31057;31057",
    "addr:street":"Via Treviso",
    "iso:country":"IT",
    "sg:address":"Via Treviso 24 31057 Silea",
    "sg:city":"Silea",
    "sg:classifiers":[
        {
            "category":"Shopping",
            "subcategory":"Baby Store",
            "type":"Retail Goods"
        }
    ],
    "sg:phone":"+39 0422 360318",
    "sg:postcode":"31057",
    "sg:province":"Treviso",
    "sg:tags":[
        "knitted",
        "infant"
    ],
    "sg:website":"www.sabinababy.com",
    "wof:name":"Sabina Sas Di Conte Silvano & C.",
    "wof:placetype":"venue"
},
  "geometry": {"coordinates":[12.28991,45.654152],"type":"Point"}
}