{
  "type": "Feature",
  "properties": {
    "addr:full":"35020 Albignasego Albignasego Padova 35020",
    "addr:postcode":"35020;35020",
    "iso:country":"IT",
    "sg:address":"35020 Albignasego",
    "sg:city":"Albignasego",
    "sg:orig_category":"Pompe. Elettrotecnica Industriale, Prodotti E Apparecchiature",
    "sg:phone":"+39 049 880 6291",
    "sg:postcode":"35020",
    "sg:province":"Padova",
    "wof:name":"Ab. Service Di Giorgetti E Perini S.n.c.",
    "wof:placetype":"venue"
},
  "geometry": {"coordinates":[11.8554887772,45.3695144653],"type":"Point"}
}