{
  "type": "Feature",
  "properties": {
    "iso:country":"IT",
    "sg:address":"24035 Curno",
    "sg:city":"Curno",
    "sg:orig_category":"Arredamenti - Vendita Al Dettaglio",
    "sg:phone":"+39 035 612127",
    "sg:postcode":"24035",
    "sg:province":"Bergamo",
    "wof:name":"F.b. Arredamenti Di Ferrari Luciano",
    "wof:placetype":"venue"
},
  "geometry": {"coordinates":[9.624106,45.68742],"type":"Point"}
}