{
  "type": "Feature",
  "properties": {
    "addr:full":"50122 Firenze Firenze Firenze 50122",
    "addr:postcode":"50122;50122",
    "iso:country":"IT",
    "sg:address":"50122 Firenze",
    "sg:city":"Firenze",
    "sg:orig_category":"Servizi E Lavori Per Abbigliamento E Pelletterie",
    "sg:phone":"+39 055 287095",
    "sg:postcode":"50122",
    "sg:province":"Firenze",
    "wof:name":"Casa Del Rammendo",
    "wof:placetype":"venue"
},
  "geometry": {"coordinates":[11.195163,43.80463],"type":"Point"}
}