{
  "type": "Feature",
  "properties": {
    "iso:country":"IT",
    "sg:address":"Viale Abruzzi 24, 20131 Milan, Mi",
    "sg:classifiers":[
        {
            "category":"Banks & Credit Unions",
            "subcategory":"Bank",
            "type":"Services"
        }
    ],
    "sg:postcode":"20131",
    "sg:province":"Milano",
    "wof:name":"Commercial Union Italia Spa",
    "wof:placetype":"venue"
},
  "geometry": {"coordinates":[9.217299,45.47747],"type":"Point"}
}