{
  "type": "Feature",
  "properties": {
    "iso:country":"IT",
    "sg:address":"48100 Ravenna",
    "sg:city":"Ravenna",
    "sg:classifiers":[
        {
            "category":"Health Services",
            "subcategory":"Nursing And Care Facility",
            "type":"Services"
        }
    ],
    "sg:phone":"+39 0544 458311",
    "sg:postcode":"48100",
    "sg:province":"Ravenna",
    "sg:tags":[
        "case",
        "cura",
        "private",
        "di"
    ],
    "sg:website":"http://www.casadicurasanfrancesco.it",
    "wof:name":"Casa Di Cura San Francesco Srl",
    "wof:placetype":"venue"
},
  "geometry": {"coordinates":[12.224458,44.380314],"type":"Point"}
}