{
  "type": "Feature",
  "properties": {
    "addr:full":"31030 Altivole Altivole Treviso 31030",
    "addr:postcode":"31030;31030",
    "iso:country":"IT",
    "sg:address":"31030 Altivole",
    "sg:city":"Altivole",
    "sg:classifiers":[
        {
            "category":"Sports & Exercise",
            "subcategory":"Sports Center",
            "type":"Entertainment"
        }
    ],
    "sg:phone":"+39 0423 915335",
    "sg:postcode":"31030",
    "sg:province":"Treviso",
    "sg:tags":[
        "knitwear",
        "furs",
        "clothing",
        "article",
        "supply"
    ],
    "sg:website":"http://www.htsforma.com",
    "wof:name":"Hts Srl",
    "wof:placetype":"venue"
},
  "geometry": {"coordinates":[11.984059,45.751762],"type":"Point"}
}