{
  "type": "Feature",
  "properties": {
    "addr:full":"30133 Venezia Giudecca Venezia 30133",
    "addr:postcode":"30133;30133",
    "iso:country":"IT",
    "sg:address":"30133 Venezia",
    "sg:city":"Giudecca",
    "sg:orig_category":"Servizi Per Lo Sport E Il Tempo Libero. Servizi Ausiliari Dei Mezzi Di Trasporto",
    "sg:phone":"+39 041 520 5619",
    "sg:postcode":"30133",
    "sg:province":"Venezia",
    "wof:name":"L'altra Venezia Srl",
    "wof:placetype":"venue"
},
  "geometry": {"coordinates":[12.330659,45.425575],"type":"Point"}
}