{
  "type": "Feature",
  "properties": {
    "iso:country":"IT",
    "sg:address":"14, Via Volta Alessandro 20052 Monza",
    "sg:city":"Monza",
    "sg:classifiers":[
        {
            "category":"Wholesale",
            "subcategory":"Drugs",
            "type":"Manufacturing & Wholesale Goods"
        }
    ],
    "sg:phone":"+39 39039366851",
    "sg:postcode":"20052",
    "sg:province":"Milano",
    "sg:tags":[
        "chemical",
        "pharmaceutical"
    ],
    "wof:name":"Garghentini Giampietro & C. (s.r.l.)",
    "wof:placetype":"venue"
},
  "geometry": {"coordinates":[9.18723,45.53904],"type":"Point"}
}