{
  "type": "Feature",
  "properties": {
    "iso:country":"IT",
    "sg:address":"12030 Caramagna Piemonte",
    "sg:city":"Caramagna Piemonte",
    "sg:orig_category":"Servizi E Lavori Per Abbigliamento E Pelletterie",
    "sg:phone":"+39 0172 89191",
    "sg:postcode":"12030",
    "sg:province":"Cuneo",
    "wof:name":"Ingaramo Maddalena",
    "wof:placetype":"venue"
},
  "geometry": {"coordinates":[7.74017,44.780781],"type":"Point"}
}