{
  "type": "Feature",
  "properties": {
    "iso:country":"IT",
    "sg:address":"20125 Milano",
    "sg:city":"Milano",
    "sg:orig_category":"Odontotecnici - Laboratori",
    "sg:phone":"+39 02 6707 2208",
    "sg:postcode":"20125",
    "sg:province":"Milano",
    "wof:name":"Bellini Giuseppe",
    "wof:placetype":"venue"
},
  "geometry": {"coordinates":[9.20127,45.495548],"type":"Point"}
}