{
  "type": "Feature",
  "properties": {
    "iso:country":"IT",
    "sg:address":"09125 Cagliari",
    "sg:city":"Cagliari",
    "sg:classifiers":[
        {
            "category":"Shopping",
            "subcategory":"Crafts & Fabrics",
            "type":"Retail Goods"
        }
    ],
    "sg:phone":"+39 070 651922",
    "sg:postcode":"09125",
    "sg:province":"Cagliari",
    "sg:tags":[
        "product",
        "art",
        "processing",
        "gifts",
        "artistic",
        "crafts",
        "ceramics"
    ],
    "sg:website":"http://web.tiscalinet.it/treosnc",
    "wof:name":"Tre O Di Oggianu Gianluca & C. Snc",
    "wof:placetype":"venue"
},
  "geometry": {"coordinates":[9.120799,39.213165],"type":"Point"}
}