{
  "type": "Feature",
  "properties": {
    "iso:country":"IT",
    "sg:address":"26010 Monte Cremasco",
    "sg:city":"Monte Cremasco",
    "sg:orig_category":"Imballaggi - Produzione E Commercio",
    "sg:phone":"+39 0373 277006",
    "sg:postcode":"26010",
    "sg:province":"Cremona",
    "wof:name":"Bernocchi Srl",
    "wof:placetype":"venue"
},
  "geometry": {"coordinates":[9.61491,45.360626],"type":"Point"}
}