{
  "type": "Feature",
  "properties": {
    "iso:country":"IT",
    "sg:address":"81022 Casagiove",
    "sg:city":"Casagiove",
    "sg:orig_category":"Catene E Pignoni",
    "sg:phone":"+39 0823 468384",
    "sg:postcode":"81022",
    "sg:province":"Caserta",
    "wof:name":"Centro Distribuzione Cuscinetti Srl",
    "wof:placetype":"venue"
},
  "geometry": {"coordinates":[14.318853,41.076496],"type":"Point"}
}