{
  "type": "Feature",
  "properties": {
    "iso:country":"IT",
    "sg:address":"40033 Casalecchio Di Reno",
    "sg:city":"Casalecchio di Reno",
    "sg:orig_category":"Impiantistica E Prodotti Tecnologici Per Edilizia. Forniture Industriali Per Prevenzione, Controllo E Sicurezza",
    "sg:phone":"+39 051 577812",
    "sg:postcode":"40033",
    "sg:province":"Bologna",
    "sg:website":"http://www.antincendiobolognese.it",
    "wof:name":"Antincendio Bolognese Snc",
    "wof:placetype":"venue"
},
  "geometry": {"coordinates":[11.300316,44.503212],"type":"Point"}
}