{
  "type": "Feature",
  "properties": {
    "iso:country":"IT",
    "sg:address":"45, Via Campania 00187 Roma",
    "sg:city":"Roma",
    "sg:classifiers":[
        {
            "category":"Travel",
            "subcategory":"Travel Agent",
            "type":"Entertainment"
        }
    ],
    "sg:phone":"+39 06 4201 1356",
    "sg:postcode":"00187",
    "sg:province":"Roma",
    "sg:tags":[
        "business"
    ],
    "wof:name":"Il Pomodorino Srl",
    "wof:placetype":"venue"
},
  "geometry": {"coordinates":[12.366143,42.128746],"type":"Point"}
}