{
  "type": "Feature",
  "properties": {
    "addr:full":"20019 Seguro Milano 20019",
    "addr:postcode":"20019;20019",
    "addr:street":"Seguro",
    "iso:country":"IT",
    "sg:address":"20019 Seguro",
    "sg:orig_category":"Prodotti E Manufatti In Materie Plastiche. Forniture E Materiali Per Imballaggio E Confezionamento",
    "sg:phone":"+39 02 3350 1188",
    "sg:postcode":"20019",
    "sg:province":"Milano",
    "wof:name":"Cel - Vil",
    "wof:placetype":"venue"
},
  "geometry": {"coordinates":[9.0625953674,45.4723930359],"type":"Point"}
}