{
  "type": "Feature",
  "properties": {
    "iso:country":"IT",
    "sg:address":"Via Gregor Gasser 2, 39010 Nalles, Bz",
    "sg:city":"Nalles",
    "sg:classifiers":[
        {
            "category":"Banks & Credit Unions",
            "subcategory":"Bank",
            "type":"Services"
        }
    ],
    "sg:postcode":"39010",
    "sg:province":"Bolzano/Bozen",
    "wof:name":"Cassa Raiffeisen Di Nalles Scrl",
    "wof:placetype":"venue"
},
  "geometry": {"coordinates":[11.20311,46.544029],"type":"Point"}
}