{
  "type": "Feature",
  "properties": {
    "iso:country":"IT",
    "sg:address":"Via Boscovich Ruggero 11 20124 Milano",
    "sg:city":"Milano",
    "sg:classifiers":[
        {
            "category":"Shopping",
            "subcategory":"Clothing, Apparel, & Fashions",
            "type":"Retail Goods"
        }
    ],
    "sg:phone":"+39 02 6698 8289",
    "sg:postcode":"20124",
    "sg:province":"Milano",
    "sg:tags":[
        "children's",
        "clothing"
    ],
    "sg:website":"www.calmarini.it",
    "wof:name":"Calmarini Srl",
    "wof:placetype":"venue"
},
  "geometry": {"coordinates":[9.201685,45.482941],"type":"Point"}
}