{
  "type": "Feature",
  "properties": {
    "iso:country":"IT",
    "sg:address":"29100 Piacenza",
    "sg:city":"Piacenza",
    "sg:orig_category":"Apparecchiature Ed Attrezzature Meccaniche. Elettronica Industriale, Prodotti E Apparecchiature. Impianti, Attrezzature E Forniture Sanitarie Ed Ospedaliere. Apparecchi, Attrezzature E Forniture Per C",
    "sg:phone":"+39 0523 579000",
    "sg:postcode":"29100",
    "sg:province":"Piacenza",
    "wof:name":"C.c.r. Medical Srl",
    "wof:placetype":"venue"
},
  "geometry": {"coordinates":[9.736426,45.046082],"type":"Point"}
}