{
  "type": "Feature",
  "properties": {
    "iso:country":"IT",
    "sg:address":"20040 Bellusco",
    "sg:city":"Bellusco",
    "sg:orig_category":"Arredo Bagno Ed Idrosanitari. Complementi Di Arredamento. Vetro: Prodotti E Lavorazioni",
    "sg:phone":"+39 039 684 0839",
    "sg:postcode":"20040",
    "sg:province":"Milano",
    "wof:name":"Radaelli Arnaldo",
    "wof:placetype":"venue"
},
  "geometry": {"coordinates":[9.439644,45.613396],"type":"Point"}
}