{
  "type": "Feature",
  "properties": {
    "iso:country":"IT",
    "sg:address":"35, Via Marmolada 20095 Cusano Milanino",
    "sg:city":"Cusano Milanino",
    "sg:classifiers":[
        {
            "category":"Professional",
            "subcategory":"Engineering",
            "type":"Services"
        }
    ],
    "sg:phone":"+39 02 6640 3096",
    "sg:postcode":"20095",
    "sg:province":"Milano",
    "sg:tags":[
        "machine",
        "-",
        "mechanical"
    ],
    "wof:name":"M.b.m. Srl",
    "wof:placetype":"venue"
},
  "geometry": {"coordinates":[9.171132,45.552761],"type":"Point"}
}