{
  "type": "Feature",
  "properties": {
    "addr:full":"80040 Volla Volla Napoli 80040",
    "addr:postcode":"80040;80040",
    "iso:country":"IT",
    "sg:address":"80040 Volla",
    "sg:city":"Volla",
    "sg:orig_category":"Forniture Per Attivita' Industriali",
    "sg:phone":"+39 081 774 4520",
    "sg:postcode":"80040",
    "sg:province":"Napoli",
    "wof:name":"Vitoltex Di Vitolo Carmela Sas",
    "wof:placetype":"venue"
},
  "geometry": {"coordinates":[14.3475122452,40.8710594177],"type":"Point"}
}