{
  "type": "Feature",
  "properties": {
    "iso:country":"IT",
    "sg:address":"50133 Firenze",
    "sg:city":"Firenze",
    "sg:orig_category":"Servizi E Lavori Per Edilizia E Lavori Pubblici",
    "sg:phone":"+39 055 552 2584",
    "sg:postcode":"50133",
    "sg:province":"Firenze",
    "wof:name":"Gruppo Annex Consorzio Imprese Artigiane",
    "wof:placetype":"venue"
},
  "geometry": {"coordinates":[11.272034,43.793266],"type":"Point"}
}