{
  "type": "Feature",
  "properties": {
    "addr:full":"00185 Roma Roma Roma 00185",
    "addr:postcode":"00185;00185",
    "iso:country":"IT",
    "sg:address":"00185 Roma",
    "sg:city":"Roma",
    "sg:orig_category":"Materiali Semilavorati Metallici",
    "sg:phone":"+39 06 445 1837",
    "sg:postcode":"00185",
    "sg:province":"Roma",
    "wof:name":"Mericone Riccardo",
    "wof:placetype":"venue"
},
  "geometry": {"coordinates":[12.616426,41.723259],"type":"Point"}
}