{
  "type": "Feature",
  "properties": {
    "iso:country":"IT",
    "sg:address":"84085 Mercato S. Severino",
    "sg:city":"Ciorani",
    "sg:orig_category":"Servizi E Lavori Per Arredamento E Industria Del Legno. Forniture Per Congressi, Fiere E Manifestazioni. Servizi Per Aziende, Manifestazioni E Supporto Agli Scambi Commerciali",
    "sg:phone":"+39 089 820319",
    "sg:postcode":"84085",
    "sg:province":"Salerno",
    "wof:name":"De Angelis Gennaro",
    "wof:placetype":"venue"
},
  "geometry": {"coordinates":[14.727675,40.772526],"type":"Point"}
}