{
  "type": "Feature",
  "properties": {
    "addr:full":"07029 Tempio Pausania Tempio Pausania Olbia-Tempio 07029",
    "addr:postcode":"07029;07029",
    "iso:country":"IT",
    "sg:address":"07029 Tempio Pausania",
    "sg:city":"Tempio Pausania",
    "sg:classifiers":[
        {
            "category":"Manufacturing",
            "subcategory":"Wood Products",
            "type":"Manufacturing & Wholesale Goods"
        }
    ],
    "sg:phone":"+39 079 630825",
    "sg:postcode":"07029",
    "sg:province":"Olbia-Tempio",
    "sg:tags":[
        "decorative",
        "building",
        "furnishings",
        "semi-finished",
        "industry",
        "objects",
        "article"
    ],
    "wof:name":"Masu Andrea",
    "wof:placetype":"venue"
},
  "geometry": {"coordinates":[9.1234798431,40.8994483948],"type":"Point"}
}