{
  "type": "Feature",
  "properties": {
    "addr:full":"35011 Campodarsego Campodarsego Padova 35011",
    "addr:postcode":"35011;35011",
    "iso:country":"IT",
    "sg:address":"35011 Campodarsego",
    "sg:city":"Campodarsego",
    "sg:orig_category":"Imprese Di Costruzioni Civili Ed Industriali",
    "sg:phone":"+39 049 556 5869",
    "sg:postcode":"35011",
    "sg:province":"Padova",
    "sg:website":"http://www.kimet.it",
    "wof:name":"Kimet Snc Di Carlini Pietro & C.",
    "wof:placetype":"venue"
},
  "geometry": {"coordinates":[11.893445,45.508625],"type":"Point"}
}