{
  "type": "Feature",
  "properties": {
    "addr:full":"Via Bellini 13 43017 San Secondo Parmense San Secondo Parmense Parma 43017",
    "addr:housenumber":"13;secondo parmense",
    "addr:postcode":"43017;secondo parmense;43017",
    "addr:street":"Via Bellini",
    "iso:country":"IT",
    "sg:address":"Via Bellini 13 43017 San Secondo Parmense",
    "sg:city":"San Secondo Parmense",
    "sg:classifiers":[
        {
            "category":"Bakery",
            "type":"Food & Drink"
        }
    ],
    "sg:phone":"+39 0521 873051",
    "sg:postcode":"43017",
    "sg:province":"Parma",
    "sg:tags":[
        "fresh",
        "pastry",
        "bread"
    ],
    "sg:website":"www.idpsrl.it",
    "wof:name":"Idp Srl",
    "wof:placetype":"venue"
},
  "geometry": {"coordinates":[10.3295478821,44.8078651428],"type":"Point"}
}