{
  "type": "Feature",
  "properties": {
    "iso:country":"IT",
    "sg:address":"38, Via Montello 21040 Caronno Varesino",
    "sg:city":"Caronno Varesino",
    "sg:classifiers":[
        {
            "category":"Manufacturing",
            "subcategory":"Tools & Machinery",
            "type":"Manufacturing & Wholesale Goods"
        }
    ],
    "sg:phone":"+39 0331 981391",
    "sg:postcode":"21040",
    "sg:province":"Varese",
    "sg:tags":[
        "environment",
        "equipment",
        "-"
    ],
    "wof:name":"Impresa Di Pulizie Giuriato Di Giuriato Franco E Guidetti Renata (s.n.c.)",
    "wof:placetype":"venue"
},
  "geometry": {"coordinates":[8.85479,45.776806],"type":"Point"}
}