{
  "type": "Feature",
  "properties": {
    "iso:country":"IT",
    "sg:address":"21, Via Gino Grassi 22030 Lipomo",
    "sg:city":"Lipomo",
    "sg:classifiers":[
        {
            "category":"Shopping",
            "subcategory":"Clothing, Apparel, & Fashions",
            "type":"Retail Goods"
        }
    ],
    "sg:phone":"+39 39031282549",
    "sg:postcode":"22030",
    "sg:province":"Como",
    "sg:tags":[
        "clothes"
    ],
    "wof:name":"Super Sport",
    "wof:placetype":"venue"
},
  "geometry": {"coordinates":[9.112062,45.792648],"type":"Point"}
}