{
  "type": "Feature",
  "properties": {
    "addr:full":"13, Piazza Della Cisterna 53037 San Gimignano San Gimignano Siena 53037",
    "addr:postcode":"53037;gimignano;53037",
    "addr:street":"Piazza Della Cisterna;Gimignano Siena",
    "iso:country":"IT",
    "sg:address":"13, Piazza Della Cisterna 53037 San Gimignano",
    "sg:city":"San Gimignano",
    "sg:classifiers":[
        {
            "category":"Travel",
            "subcategory":"Travel Agent",
            "type":"Entertainment"
        }
    ],
    "sg:phone":"+39 0577 941294",
    "sg:postcode":"53037",
    "sg:province":"Siena",
    "sg:tags":[
        "business"
    ],
    "wof:name":"Albergo Leon Bianco",
    "wof:placetype":"venue"
},
  "geometry": {"coordinates":[11.043531,43.467361],"type":"Point"}
}