{
  "type": "Feature",
  "properties": {
    "iso:country":"IT",
    "sg:address":"25080 Manerba Del Garda",
    "sg:city":"Manerba del Garda",
    "sg:orig_category":"Macchine Utensili E Impianti",
    "sg:postcode":"25080",
    "sg:province":"Brescia",
    "wof:name":"Car.la.s Di Carli Battista",
    "wof:placetype":"venue"
},
  "geometry": {"coordinates":[10.542514,45.544613],"type":"Point"}
}