{
  "type": "Feature",
  "properties": {
    "iso:country":"IT",
    "sg:address":"95124 Catania",
    "sg:city":"Catania",
    "sg:orig_category":"Nautica. Forniture Per Attivita' Commerciali Ed Artigianali",
    "sg:phone":"+39 095 354967",
    "sg:postcode":"95124",
    "sg:province":"Catania",
    "wof:name":"Privitera Salvatore",
    "wof:placetype":"venue"
},
  "geometry": {"coordinates":[15.074743,37.507206],"type":"Point"}
}