{
  "type": "Feature",
  "properties": {
    "iso:country":"IT",
    "sg:address":"20017 Rho",
    "sg:city":"Rho",
    "sg:orig_category":"Stirerie - Servizio Conto Terzi",
    "sg:phone":"+39 02 9390 9206",
    "sg:postcode":"20017",
    "sg:province":"Milano",
    "wof:name":"Stil Stirologistica",
    "wof:placetype":"venue"
},
  "geometry": {"coordinates":[9.084982,45.525616],"type":"Point"}
}