{
  "type": "Feature",
  "properties": {
    "addr:full":"07024 La Maddalena La Maddalena Olbia-Tempio 07024",
    "addr:housenumber":"07024",
    "addr:postcode":"07024",
    "addr:street":"La Maddalena La",
    "iso:country":"IT",
    "sg:address":"07024 La Maddalena",
    "sg:city":"La Maddalena",
    "sg:orig_category":"Servizi E Lavori Per Edilizia E Lavori Pubblici. Servizi Al Turismo",
    "sg:phone":"+39 0789 736560",
    "sg:postcode":"07024",
    "sg:province":"Olbia-Tempio",
    "sg:website":"http://www.agenziailfaro.com",
    "wof:name":"Il Faro Snc Di Emilio Burranca & Figli",
    "wof:placetype":"venue"
},
  "geometry": {"coordinates":[9.417273,41.230465],"type":"Point"}
}