{
  "type": "Feature",
  "properties": {
    "iso:country":"IT",
    "sg:address":"54010 Albiano Magra",
    "sg:orig_category":"Motori Ed Organi Di Trasmissione",
    "sg:phone":"+39 0187 413000",
    "sg:postcode":"54010",
    "sg:province":"Massa-Carrara",
    "wof:name":"Elliott Turbomachinery S.a.",
    "wof:placetype":"venue"
},
  "geometry": {"coordinates":[10.0359659195,44.2214012146],"type":"Point"}
}