{
  "type": "Feature",
  "properties": {
    "iso:country":"IT",
    "sg:address":"20128 Milano",
    "sg:city":"Milano",
    "sg:orig_category":"Forniture Per Uffici",
    "sg:phone":"+39 02 257 3593",
    "sg:postcode":"20128",
    "sg:province":"Milano",
    "wof:name":"Eredi Bresciani Di Vittorio Bresciani & C. Sas",
    "wof:placetype":"venue"
},
  "geometry": {"coordinates":[9.2301025391,45.5092468262],"type":"Point"}
}