{
  "type": "Feature",
  "properties": {
    "iso:country":"IT",
    "sg:address":"28921 Verbania",
    "sg:city":"Verbania",
    "sg:orig_category":"Serramenti Ed Infissi",
    "sg:phone":"+39 0323 402041",
    "sg:postcode":"28921",
    "sg:province":"Verbano-Cusio-Ossola",
    "wof:name":"Pensiltrave Magistri Sas",
    "wof:placetype":"venue"
},
  "geometry": {"coordinates":[8.562985,45.940735],"type":"Point"}
}