{
  "type": "Feature",
  "properties": {
    "iso:country":"IT",
    "sg:address":"163/165, Via Quattro Novembre 21058 Solbiate Olona",
    "sg:city":"Solbiate Olona",
    "sg:classifiers":[
        {
            "category":"Professional",
            "subcategory":"Engineering",
            "type":"Services"
        }
    ],
    "sg:phone":"+39 0331 641680",
    "sg:postcode":"21058",
    "sg:province":"Varese",
    "sg:tags":[
        "machine",
        "-",
        "mechanical"
    ],
    "wof:name":"Rodolfo Comerio Snc",
    "wof:placetype":"venue"
},
  "geometry": {"coordinates":[8.826385,45.817604],"type":"Point"}
}