{
  "type": "Feature",
  "properties": {
    "addr:full":"20064 Gorgonzola Gorgonzola Milano 20064",
    "addr:postcode":"20064;20064",
    "iso:country":"IT",
    "sg:address":"20064 Gorgonzola",
    "sg:city":"Gorgonzola",
    "sg:orig_category":"Forniture Per Agricoltura E Zootecnia",
    "sg:phone":"+39 02 951 5322",
    "sg:postcode":"20064",
    "sg:province":"Milano",
    "wof:name":"Guarneri Adriano",
    "wof:placetype":"venue"
},
  "geometry": {"coordinates":[9.1431922913,45.532043457],"type":"Point"}
}