{
  "type": "Feature",
  "properties": {
    "iso:country":"IT",
    "sg:address":"3, Via P. Mascagni 42018 San Martino In Rio",
    "sg:classifiers":[
        {
            "category":"Wholesale",
            "subcategory":"Machinery & Supplies",
            "type":"Manufacturing & Wholesale Goods"
        }
    ],
    "sg:phone":"+39 0522 646300",
    "sg:postcode":"42018",
    "sg:province":"Reggio Nell'Emilia",
    "sg:tags":[
        "-",
        "agriculture",
        "equipment"
    ],
    "wof:name":"I.s.i. (s.r.l.)",
    "wof:placetype":"venue"
},
  "geometry": {"coordinates":[10.774969,44.731377],"type":"Point"}
}