{
  "type": "Feature",
  "properties": {
    "iso:country":"IT",
    "sg:address":"7, Piazza Tomadini Z.i. 33048 San Giovanni Al Natisone",
    "sg:city":"San Giovanni al Natisone",
    "sg:classifiers":[
        {
            "category":"Professional",
            "subcategory":"Engineering",
            "type":"Services"
        }
    ],
    "sg:phone":"+39 0432 757296",
    "sg:postcode":"33048",
    "sg:province":"Udine",
    "sg:tags":[
        "machine",
        "-",
        "mechanical"
    ],
    "wof:name":"Fermac (s.r.l.)",
    "wof:placetype":"venue"
},
  "geometry": {"coordinates":[13.397373,45.979763],"type":"Point"}
}