{
  "type": "Feature",
  "properties": {
    "addr:full":"21020 Taino Taino Varese 21020",
    "addr:postcode":"21020;21020",
    "iso:country":"IT",
    "sg:address":"21020 Taino",
    "sg:city":"Taino",
    "sg:orig_category":"Agricoltura, Orticoltura E Floricoltura",
    "sg:phone":"+39 0331 957533",
    "sg:postcode":"21020",
    "sg:province":"Varese",
    "wof:name":"Berti Camillo",
    "wof:placetype":"venue"
},
  "geometry": {"coordinates":[8.606118,45.763489],"type":"Point"}
}