{
  "type": "Feature",
  "properties": {
    "iso:country":"IT",
    "sg:address":"24062 Costa Volpino",
    "sg:city":"Costa Volpino",
    "sg:orig_category":"Macchine Utensili E Impianti",
    "sg:phone":"+39 035 988210",
    "sg:postcode":"24062",
    "sg:province":"Bergamo",
    "wof:name":"Forni Industriali Bendotti - Spa",
    "wof:placetype":"venue"
},
  "geometry": {"coordinates":[10.108338,45.832241],"type":"Point"}
}