{
  "type": "Feature",
  "properties": {
    "addr:full":"20026 Novate Milanese Novate Milanese Milano 20026",
    "addr:postcode":"20026;20026",
    "iso:country":"IT",
    "sg:address":"20026 Novate Milanese",
    "sg:city":"Novate Milanese",
    "sg:orig_category":"Servizi E Lavori Industria Chimica. Riparazione Dei Mezzi Di Trasporto",
    "sg:phone":"+39 02 356 7359",
    "sg:postcode":"20026",
    "sg:province":"Milano",
    "wof:name":"Finit Sas",
    "wof:placetype":"venue"
},
  "geometry": {"coordinates":[9.126347,45.527214],"type":"Point"}
}