{
  "type": "Feature",
  "properties": {
    "addr:full":"4, Viale Delle Nazioni 37135 Verona Verona Verona 37135",
    "addr:postcode":"37135;37135",
    "addr:street":"Viale Delle Nazioni",
    "iso:country":"IT",
    "sg:address":"4, Viale Delle Nazioni 37135 Verona",
    "sg:city":"Verona",
    "sg:classifiers":[
        {
            "category":"Banks & Credit Unions",
            "subcategory":"Bank",
            "type":"Services"
        }
    ],
    "sg:phone":"+39 045 827 4111",
    "sg:postcode":"37135",
    "sg:province":"Verona",
    "sg:tags":[
        "banking",
        "institution"
    ],
    "wof:name":"Banco Popolare Di Verona E Novara Scrl",
    "wof:placetype":"venue"
},
  "geometry": {"coordinates":[10.974936,45.404984],"type":"Point"}
}