{
  "type": "Feature",
  "properties": {
    "addr:full":"36030 Zugliano Zugliano Vicenza 36030",
    "addr:postcode":"36030;36030",
    "iso:country":"IT",
    "sg:address":"36030 Zugliano",
    "sg:city":"Zugliano",
    "sg:orig_category":"Macchine, Impianti Ed Attrezzature Per Industria Alimentare E Bevande",
    "sg:phone":"+39 0445 330055",
    "sg:postcode":"36030",
    "sg:province":"Vicenza",
    "wof:name":"Famir S.r.l.",
    "wof:placetype":"venue"
},
  "geometry": {"coordinates":[11.502122,45.716686],"type":"Point"}
}