{
  "type": "Feature",
  "properties": {
    "addr:full":"26866 Sant'angelo Lodigiano Lodi 26866",
    "addr:postcode":"26866;26866",
    "iso:country":"IT",
    "sg:address":"26866 Sant'angelo Lodigiano",
    "sg:orig_category":"Biancheria, Telerie E Coperte",
    "sg:phone":"+39 0371 90464",
    "sg:postcode":"26866",
    "sg:province":"Lodi",
    "wof:name":"Fusari Luigi",
    "wof:placetype":"venue"
},
  "geometry": {"coordinates":[9.409645,45.239204],"type":"Point"}
}