{
  "type": "Feature",
  "properties": {
    "addr:full":"1, Via Ugo Foscolo 21020 Ternate Ternate Varese 21020",
    "addr:postcode":"21020;21020",
    "addr:street":"Via Ugo Foscolo",
    "iso:country":"IT",
    "sg:address":"1, Via Ugo Foscolo 21020 Ternate",
    "sg:city":"Ternate",
    "sg:classifiers":[
        {
            "category":"Shopping",
            "subcategory":"Computers & Home Electronics",
            "type":"Retail Goods"
        }
    ],
    "sg:phone":"+39 0332 961625",
    "sg:postcode":"21020",
    "sg:province":"Varese",
    "sg:tags":[
        "electronic",
        "electrical",
        "equipment"
    ],
    "wof:name":"Duebi S.a.s. Di Bortolotto G. & C.",
    "wof:placetype":"venue"
},
  "geometry": {"coordinates":[8.703675,45.781811],"type":"Point"}
}