{
  "type": "Feature",
  "properties": {
    "iso:country":"IT",
    "sg:address":"42019 Scandiano",
    "sg:orig_category":"Macchine Ed Impianti Per Edilizia E Lavori Pubblici. Apparecchiature Ed Attrezzature Meccaniche",
    "sg:phone":"+39 0522 851279",
    "sg:postcode":"42019",
    "sg:province":"Reggio Nell'Emilia",
    "wof:name":"Venanzetti Vibrazioni Milano (s.r.l.)",
    "wof:placetype":"venue"
},
  "geometry": {"coordinates":[10.694932,44.599297],"type":"Point"}
}