{
  "type": "Feature",
  "properties": {
    "addr:full":"45011 Adria Adria Rovigo 45011",
    "addr:postcode":"45011;45011",
    "iso:country":"IT",
    "sg:address":"45011 Adria",
    "sg:city":"Adria",
    "sg:orig_category":"Lavorazioni Meccaniche E Servizi. Riparazione Dei Mezzi Di Trasporto",
    "sg:phone":"+39 0426 900467",
    "sg:postcode":"45011",
    "sg:province":"Rovigo",
    "sg:website":"http://www.netmarket.it/vittoria",
    "wof:name":"Cantieri Navali Vittoria Spa",
    "wof:placetype":"venue"
},
  "geometry": {"coordinates":[12.056107,45.056396],"type":"Point"}
}