{
  "type": "Feature",
  "properties": {
    "iso:country":"IT",
    "sg:address":"Via Della Repubblica 24064 Grumello Del Monte",
    "sg:city":"Grumello del Monte",
    "sg:classifiers":[
        {
            "category":"Shopping",
            "subcategory":"Jewelry",
            "type":"Retail Goods"
        }
    ],
    "sg:phone":"+39 39035830232",
    "sg:postcode":"24064",
    "sg:province":"Bergamo",
    "sg:tags":[
        "jewellery"
    ],
    "wof:name":"Creazioni Angelo Valli Di Amati Serenella",
    "wof:placetype":"venue"
},
  "geometry": {"coordinates":[9.858374,45.63662],"type":"Point"}
}