{
  "type": "Feature",
  "properties": {
    "iso:country":"IT",
    "sg:address":"22020 Gironico",
    "sg:city":"Gironico",
    "sg:orig_category":"Prodotti Alimentari. Agricoltura, Orticoltura E Floricoltura",
    "sg:phone":"+39 031 440405",
    "sg:postcode":"22020",
    "sg:province":"Como",
    "wof:name":"I Frutti Del Bosco (s.r.l.)",
    "wof:placetype":"venue"
},
  "geometry": {"coordinates":[9.049826622,45.8079185486],"type":"Point"}
}