{
  "type": "Feature",
  "properties": {
    "iso:country":"IT",
    "sg:address":"20049 Concorezzo",
    "sg:city":"Concorezzo",
    "sg:orig_category":"Forniture Per Abbigliamento E Pelletterie. Forniture E Materiali Per Imballaggio E Confezionamento",
    "sg:phone":"+39 039 628091",
    "sg:postcode":"20049",
    "sg:province":"Milano",
    "wof:name":"Mab Spa",
    "wof:placetype":"venue"
},
  "geometry": {"coordinates":[9.3368177414,45.5933952332],"type":"Point"}
}