{
  "type": "Feature",
  "properties": {
    "iso:country":"IT",
    "sg:address":"Via Lutrario 52; Crispano; 80020",
    "sg:city":"Crispano",
    "sg:classifiers":[
        {
            "category":"Banks & Credit Unions",
            "subcategory":"Bank",
            "type":"Services"
        }
    ],
    "sg:phone":"+39 081 834 6876",
    "sg:postcode":"80020",
    "sg:province":"Napoli",
    "wof:name":"Banco Di Napoli Spa",
    "wof:placetype":"venue"
},
  "geometry": {"coordinates":[14.286371,40.952606],"type":"Point"}
}