{
  "type": "Feature",
  "properties": {
    "iso:country":"IT",
    "sg:address":"Via Dagnini 48/d; Bologna; 40137",
    "sg:city":"Bologna",
    "sg:classifiers":[
        {
            "category":"Banks & Credit Unions",
            "subcategory":"Bank",
            "type":"Services"
        }
    ],
    "sg:phone":"+39 051 623 2036",
    "sg:postcode":"40137",
    "sg:province":"Bologna",
    "wof:name":"Rolo Banca 1473 Spa",
    "wof:placetype":"venue"
},
  "geometry": {"coordinates":[11.370486,44.481384],"type":"Point"}
}