{
  "type": "Feature",
  "properties": {
    "iso:country":"IT",
    "sg:address":"40132 Bologna",
    "sg:city":"Bologna",
    "sg:orig_category":"Ospedali E Servizi Sanitari",
    "sg:phone":"+39 051 641 5415",
    "sg:postcode":"40132",
    "sg:province":"Bologna",
    "wof:name":"Acquerello Service Srl",
    "wof:placetype":"venue"
},
  "geometry": {"coordinates":[11.282862,44.515312],"type":"Point"}
}