{
  "type": "Feature",
  "properties": {
    "addr:full":"27, Via Marosticana 31010 Maser Maser Treviso 31010",
    "addr:postcode":"31010;31010",
    "addr:street":"Via Marosticana",
    "iso:country":"IT",
    "sg:address":"27, Via Marosticana 31010 Maser",
    "sg:city":"Maser",
    "sg:classifiers":[
        {
            "category":"Shopping",
            "subcategory":"Clothing, Apparel, & Fashions",
            "type":"Retail Goods"
        }
    ],
    "sg:phone":"+39 39042355004",
    "sg:postcode":"31010",
    "sg:province":"Treviso",
    "sg:tags":[
        "clothes"
    ],
    "wof:name":"Nuova Asolana (soc.coop.r.l.)",
    "wof:placetype":"venue"
},
  "geometry": {"coordinates":[11.962882,45.794518],"type":"Point"}
}