{
  "type": "Feature",
  "properties": {
    "addr:full":"70010 Casamassima Casamassima Bari 70010",
    "addr:postcode":"70010;70010",
    "iso:country":"IT",
    "sg:address":"70010 Casamassima",
    "sg:city":"Casamassima",
    "sg:orig_category":"Articoli Da Regalo. Shopping. Regalistica Aziendale",
    "sg:phone":"+39 080 671836",
    "sg:postcode":"70010",
    "sg:province":"Bari",
    "wof:name":"Orofino Carmela - L'antico 'oggetti D'arte'",
    "wof:placetype":"venue"
},
  "geometry": {"coordinates":[16.888,41.117001],"type":"Point"}
}