{
  "type": "Feature",
  "properties": {
    "addr:full":"95032 Belpasso Belpasso Catania 95032",
    "addr:postcode":"95032;95032",
    "iso:country":"IT",
    "sg:address":"95032 Belpasso",
    "sg:city":"Belpasso",
    "sg:orig_category":"Prodotti Alimentari",
    "sg:phone":"+39 095 791 1711",
    "sg:postcode":"95032",
    "sg:province":"Catania",
    "wof:name":"Ortofresco Srl",
    "wof:placetype":"venue"
},
  "geometry": {"coordinates":[14.8927001953,37.6179199219],"type":"Point"}
}