{
  "type": "Feature",
  "properties": {
    "addr:full":"Via Zona Industriale 64020 Castellalto Castellalto Teramo 64020",
    "addr:postcode":"64020;64020",
    "addr:street":"Via Zona Industriale",
    "iso:country":"IT",
    "sg:address":"Via Zona Industriale 64020 Castellalto",
    "sg:city":"Castellalto",
    "sg:classifiers":[
        {
            "category":"Manufacturing",
            "subcategory":"Rubber & Plastics",
            "type":"Manufacturing & Wholesale Goods"
        }
    ],
    "sg:phone":"+39 39086157472",
    "sg:postcode":"64020",
    "sg:province":"Teramo",
    "sg:tags":[
        "packaging",
        "material",
        "-"
    ],
    "wof:name":"Morgan (s.p.a.)",
    "wof:placetype":"venue"
},
  "geometry": {"coordinates":[13.8473567963,42.7026786804],"type":"Point"}
}