{
  "type": "Feature",
  "properties": {
    "iso:country":"IT",
    "sg:address":"Via Aretina 219 50136 Firenze",
    "sg:city":"Firenze",
    "sg:classifiers":[
        {
            "category":"Professional",
            "subcategory":"Printing & Photocopies",
            "type":"Services"
        }
    ],
    "sg:phone":"+39 055 667123",
    "sg:postcode":"50136",
    "sg:province":"Firenze",
    "sg:tags":[
        "print",
        "periodical"
    ],
    "wof:name":"Mani Srl",
    "wof:placetype":"venue"
},
  "geometry": {"coordinates":[11.293261528,43.7683906555],"type":"Point"}
}