{
  "type": "Feature",
  "properties": {
    "addr:full":"25050 Pian Camuno Pian Camuno Brescia 25050",
    "addr:postcode":"25050;25050",
    "iso:country":"IT",
    "sg:address":"25050 Pian Camuno",
    "sg:city":"Pian Camuno",
    "sg:orig_category":"Macchine, Impianti Ed Attrezzature Per Abbigliamento E Pelletterie",
    "sg:phone":"+39 036 459 0715",
    "sg:postcode":"25050",
    "sg:province":"Brescia",
    "wof:name":"Sygma Srl",
    "wof:placetype":"venue"
},
  "geometry": {"coordinates":[10.135269165,45.8389778137],"type":"Point"}
}