{
  "type": "Feature",
  "properties": {
    "iso:country":"IT",
    "sg:address":"65126 Pescara",
    "sg:city":"Pescara",
    "sg:classifiers":[
        {
            "category":"Shopping",
            "subcategory":"Clothing, Apparel, & Fashions",
            "type":"Retail Goods"
        }
    ],
    "sg:phone":"+39 085 690780",
    "sg:postcode":"65126",
    "sg:province":"Pescara",
    "sg:tags":[
        "knitwear",
        "furs",
        "clothing"
    ],
    "wof:name":"Boutique Buonfiglio Di D'amario Nina",
    "wof:placetype":"venue"
},
  "geometry": {"coordinates":[14.22506,42.461456],"type":"Point"}
}