{
  "type": "Feature",
  "properties": {
    "iso:country":"IT",
    "sg:address":"31100 Treviso",
    "sg:city":"Treviso",
    "sg:orig_category":"Centri Di Estetica E Cosmesi E Servizi",
    "sg:phone":"+39 0422 420744",
    "sg:postcode":"31100",
    "sg:province":"Treviso",
    "wof:name":"Hyper & Hyper Parrucchieri",
    "wof:placetype":"venue"
},
  "geometry": {"coordinates":[12.22861,45.65741],"type":"Point"}
}