{
  "type": "Feature",
  "properties": {
    "addr:full":"62019 Recanati Recanati Macerata 62019",
    "addr:postcode":"62019;62019",
    "iso:country":"IT",
    "sg:address":"62019 Recanati",
    "sg:city":"Recanati",
    "sg:classifiers":[
        {
            "category":"Manufacturing",
            "subcategory":"Food",
            "type":"Manufacturing & Wholesale Goods"
        }
    ],
    "sg:phone":"+39 071 981261",
    "sg:postcode":"62019",
    "sg:province":"Macerata",
    "sg:tags":[
        "product"
    ],
    "wof:name":"D'andrea Giovanni Srl",
    "wof:placetype":"venue"
},
  "geometry": {"coordinates":[13.660367012,43.4334716797],"type":"Point"}
}