{
  "type": "Feature",
  "properties": {
    "iso:country":"IT",
    "sg:address":"95027 San Gregorio Di Catania",
    "sg:city":"San Gregorio di Catania",
    "sg:orig_category":"Consulenza Agricola E Forestale",
    "sg:phone":"+39 095 717 9420",
    "sg:postcode":"95027",
    "sg:province":"Catania",
    "wof:name":"Hortus",
    "wof:placetype":"venue"
},
  "geometry": {"coordinates":[15.110474,37.55315],"type":"Point"}
}