{
  "type": "Feature",
  "properties": {
    "iso:country":"IT",
    "sg:address":"1, Via Lagole 32042 Calalzo Di Cadore",
    "sg:city":"Calalzo di Cadore",
    "sg:classifiers":[
        {
            "category":"Manufacturing",
            "subcategory":"Metals",
            "type":"Manufacturing & Wholesale Goods"
        }
    ],
    "sg:phone":"+39 39043531744",
    "sg:postcode":"32042",
    "sg:province":"Belluno",
    "sg:tags":[
        "metallurgy",
        "metalworking"
    ],
    "wof:name":"Ecma Srl",
    "wof:placetype":"venue"
},
  "geometry": {"coordinates":[12.3866043091,46.4455718994],"type":"Point"}
}