{
  "type": "Feature",
  "properties": {
    "addr:full":"35020 Masera'dipadova Padova 35020",
    "addr:postcode":"35020;35020",
    "iso:country":"IT",
    "sg:address":"35020 Masera'dipadova",
    "sg:orig_category":"Vetro: Prodotti E Lavorazioni. Forniture Per Attivita' Industriali",
    "sg:phone":"+39 049 886 2520",
    "sg:postcode":"35020",
    "sg:province":"Padova",
    "wof:name":"Glass Hi Tech (s.r.l.)",
    "wof:placetype":"venue"
},
  "geometry": {"coordinates":[11.86419,45.320229],"type":"Point"}
}