{
  "type": "Feature",
  "properties": {
    "addr:full":"48018 Faenza Faenza Ravenna 48018",
    "addr:postcode":"48018;48018",
    "iso:country":"IT",
    "sg:address":"48018 Faenza",
    "sg:city":"Faenza",
    "sg:orig_category":"Prodotti Vari In Metallo",
    "sg:phone":"+39 0546 28852",
    "sg:postcode":"48018",
    "sg:province":"Ravenna",
    "wof:name":"Angeli Di Casadio Nerio & C. Snc",
    "wof:placetype":"venue"
},
  "geometry": {"coordinates":[11.9119873047,44.28307724],"type":"Point"}
}