{
  "type": "Feature",
  "properties": {
    "iso:country":"IT",
    "sg:address":"50142 Firenze",
    "sg:city":"Firenze",
    "sg:orig_category":"Elettricisti",
    "sg:phone":"+39 055 736 4701",
    "sg:postcode":"50142",
    "sg:province":"Firenze",
    "sg:website":"http://www.fanfani.it",
    "wof:name":"Fanfani Bandinelli Srl",
    "wof:placetype":"venue"
},
  "geometry": {"coordinates":[10.747925,43.67762],"type":"Point"}
}