{
  "type": "Feature",
  "properties": {
    "iso:country":"IT",
    "sg:address":"80124 Napoli",
    "sg:city":"Napoli",
    "sg:orig_category":"Autolavaggio",
    "sg:phone":"+39 081 230 3281",
    "sg:postcode":"80124",
    "sg:province":"Napoli",
    "wof:name":"Auto Sprint Revisioni E Collaudi",
    "wof:placetype":"venue"
},
  "geometry": {"coordinates":[14.166348,40.813835],"type":"Point"}
}