{
  "type": "Feature",
  "properties": {
    "addr:full":"37050 Oppeano Oppeano Verona 37050",
    "addr:postcode":"37050;37050",
    "iso:country":"IT",
    "sg:address":"37050 Oppeano",
    "sg:city":"Oppeano",
    "sg:orig_category":"Abbigliamento Esterno, Maglierie E Pelliccerie",
    "sg:phone":"+39 045 713 4744",
    "sg:postcode":"37050",
    "sg:province":"Verona",
    "wof:name":"Cereria Zeviana & Ceroscal Srl",
    "wof:placetype":"venue"
},
  "geometry": {"coordinates":[11.05555,45.377125],"type":"Point"}
}