{
  "type": "Feature",
  "properties": {
    "addr:full":"00169 Roma Roma Roma 00169",
    "addr:postcode":"00169;00169",
    "iso:country":"IT",
    "sg:address":"00169 Roma",
    "sg:city":"Roma",
    "sg:orig_category":"Accessori Moda D'abbigliamento. Complementi Di Arredamento. Tempo Libero - Articoli E Forniture",
    "sg:phone":"+39 06 238 9092",
    "sg:postcode":"00169",
    "sg:province":"Roma",
    "wof:name":"Castelnuovo Alessandro",
    "wof:placetype":"venue"
},
  "geometry": {"coordinates":[12.602914,41.873646],"type":"Point"}
}