{
  "type": "Feature",
  "properties": {
    "addr:full":"Via Albare 127b 35017 Piombino Dese Piombino Dese Padova 35017",
    "addr:housenumber":"127b",
    "addr:postcode":"35017;35017",
    "addr:street":"Via Albare",
    "iso:country":"IT",
    "sg:address":"Via Albare 127b 35017 Piombino Dese",
    "sg:city":"Piombino Dese",
    "sg:classifiers":[
        {
            "category":"Professional",
            "subcategory":"Printing & Photocopies",
            "type":"Services"
        }
    ],
    "sg:phone":"+39 049 936 5320",
    "sg:postcode":"35017",
    "sg:province":"Padova",
    "sg:tags":[
        "laboratory",
        "photographic"
    ],
    "sg:website":"www.ditre.com",
    "wof:name":"Ditre Arti Grafiche Srl",
    "wof:placetype":"venue"
},
  "geometry": {"coordinates":[11.8765888214,45.4095687866],"type":"Point"}
}