{
  "type": "Feature",
  "properties": {
    "iso:country":"IT",
    "sg:address":"10144 Torino",
    "sg:city":"Torino",
    "sg:orig_category":"Servizi E Lavori Per Abbigliamento E Pelletterie. Scuole E Servizi Scolastici. Ricerca, Selezione E Formazione Del Personale",
    "sg:phone":"+39 011 473 0088",
    "sg:postcode":"10144",
    "sg:province":"Torino",
    "wof:name":"Masino Liliana",
    "wof:placetype":"venue"
},
  "geometry": {"coordinates":[7.659701,45.081562],"type":"Point"}
}