{
  "type": "Feature",
  "properties": {
    "addr:full":"47020 Longiano Longiano Forl\u00ec-Cesena 47020",
    "addr:postcode":"47020;47020",
    "iso:country":"IT",
    "sg:address":"47020 Longiano",
    "sg:city":"Longiano",
    "sg:orig_category":"Gelateria E Pasticceria Fresca - Macchine E Forniture",
    "sg:phone":"+39 0547 666072",
    "sg:postcode":"47020",
    "sg:province":"Forl\u00ec-Cesena",
    "wof:name":"La Scintilla Di Marchi Marco Sas",
    "wof:placetype":"venue"
},
  "geometry": {"coordinates":[12.386784,44.106529],"type":"Point"}
}