{
  "type": "Feature",
  "properties": {
    "addr:full":"80018 Lucca Napoli 80018",
    "addr:postcode":"80018;80018",
    "iso:country":"IT",
    "sg:address":"80018 Lucca",
    "sg:orig_category":"Cartotecnica - Macchine",
    "sg:phone":"+39 0583 9725",
    "sg:postcode":"80018",
    "sg:province":"Napoli",
    "sg:website":"http://www.fabio-perini.it",
    "wof:name":"Fabio Perini Spa",
    "wof:placetype":"venue"
},
  "geometry": {"coordinates":[14.226567,40.894726],"type":"Point"}
}