{
  "type": "Feature",
  "properties": {
    "addr:full":"00182 Roma Roma Roma 00182",
    "addr:postcode":"00182;00182",
    "iso:country":"IT",
    "sg:address":"00182 Roma",
    "sg:city":"Roma",
    "sg:orig_category":"Forniture Per Edilizia E Lavori Pubblici. Forniture Per Attivita' Industriali",
    "sg:phone":"+39 06 7030 5376",
    "sg:postcode":"00182",
    "sg:province":"Roma",
    "wof:name":"Geraco S.a.s. Di Caraceni Carlo & C.",
    "wof:placetype":"venue"
},
  "geometry": {"coordinates":[12.5191030502,41.8835525513],"type":"Point"}
}