{
  "type": "Feature",
  "properties": {
    "iso:country":"IT",
    "sg:address":"7, Via Dei Prati 10044 Pianezza",
    "sg:city":"Pianezza",
    "sg:classifiers":[
        {
            "category":"Food & Beverages",
            "subcategory":"Groceries & Convenience Stores",
            "type":"Retail Goods"
        }
    ],
    "sg:phone":"+39 011 967 3131",
    "sg:postcode":"10044",
    "sg:province":"Torino",
    "sg:tags":[
        "drink"
    ],
    "wof:name":"Gr Generale Ristorazione (s.r.l.)",
    "wof:placetype":"venue"
},
  "geometry": {"coordinates":[7.623867,45.132248],"type":"Point"}
}