{
  "type": "Feature",
  "properties": {
    "iso:country":"IT",
    "sg:address":"95126 Catania",
    "sg:city":"Catania",
    "sg:orig_category":"Servizi Per Lo Sport E Il Tempo Libero. Servizi Al Turismo",
    "sg:phone":"+39 095 491697",
    "sg:postcode":"95126",
    "sg:province":"Catania",
    "wof:name":"Ds Sport Srl",
    "wof:placetype":"venue"
},
  "geometry": {"coordinates":[15.098433,37.530006],"type":"Point"}
}