{
  "type": "Feature",
  "properties": {
    "addr:full":"21100 Varese Varese Varese 21100",
    "addr:postcode":"21100;21100",
    "iso:country":"IT",
    "sg:address":"21100 Varese",
    "sg:city":"Varese",
    "sg:classifiers":[
        {
            "category":"Health Services",
            "subcategory":"Health Practitioner",
            "type":"Services"
        }
    ],
    "sg:phone":"+39 0332 287868",
    "sg:postcode":"21100",
    "sg:province":"Varese",
    "sg:tags":[
        "medici"
    ],
    "wof:name":"Berti Candida",
    "wof:placetype":"venue"
},
  "geometry": {"coordinates":[8.827611,45.822174],"type":"Point"}
}