{
  "type": "Feature",
  "properties": {
    "iso:country":"IT",
    "sg:address":"42020 Quattro Castella",
    "sg:orig_category":"Clothing, Accessories",
    "sg:phone":"+39 0522 885666",
    "sg:postcode":"42020",
    "sg:province":"Reggio Nell'Emilia",
    "wof:name":"Cravattificio Conti Di Conti & Camellini Snc",
    "wof:placetype":"venue"
},
  "geometry": {"coordinates":[10.575172,44.639183],"type":"Point"}
}