{
  "type": "Feature",
  "properties": {
    "iso:country":"IT",
    "sg:address":"77, Via Cadorna Luigi 20090 Vimodrone",
    "sg:city":"Vimodrone",
    "sg:classifiers":[
        {
            "category":"Shopping",
            "subcategory":"Computers & Home Electronics",
            "type":"Retail Goods"
        }
    ],
    "sg:phone":"+39 39022502576",
    "sg:postcode":"20090",
    "sg:province":"Milano",
    "sg:tags":[
        "electronic",
        "electrical",
        "equipment"
    ],
    "wof:name":"Red Cavi S.p.a.",
    "wof:placetype":"venue"
},
  "geometry": {"coordinates":[9.289877,45.515354],"type":"Point"}
}