{
  "type": "Feature",
  "properties": {
    "addr:full":"58, Via Putignani Nicolo' 70121 Bari Bari Bari 70121",
    "addr:postcode":"70121;70121",
    "addr:street":"Via Putignani Nicolo '",
    "iso:country":"IT",
    "sg:address":"58, Via Putignani Nicolo' 70121 Bari",
    "sg:city":"Bari",
    "sg:classifiers":[
        {
            "category":"Real Estate",
            "subcategory":"Architect",
            "type":"Services"
        }
    ],
    "sg:phone":"+39 080 521 2457",
    "sg:postcode":"70121",
    "sg:province":"Bari",
    "sg:tags":[
        "textile",
        "clothing"
    ],
    "wof:name":"Timurian (s.r.l.)",
    "wof:placetype":"venue"
},
  "geometry": {"coordinates":[16.869291,41.126053],"type":"Point"}
}