{
  "type": "Feature",
  "properties": {
    "iso:country":"IT",
    "sg:address":"40068 San Lazzaro Di Savena",
    "sg:city":"San Lazzaro",
    "sg:orig_category":"Hobbistica",
    "sg:phone":"+39 051 461197",
    "sg:postcode":"40068",
    "sg:province":"Bologna",
    "sg:website":"http://www.sanlazzaro.com/modelplanet",
    "wof:name":"Model Planet Sas Di Giannini Luca & C.",
    "wof:placetype":"venue"
},
  "geometry": {"coordinates":[11.409274,44.465126],"type":"Point"}
}