{
  "type": "Feature",
  "properties": {
    "addr:full":"20021 Bollate Bollate Milano 20021",
    "addr:postcode":"20021;20021",
    "iso:country":"IT",
    "sg:address":"20021 Bollate",
    "sg:city":"Bollate",
    "sg:orig_category":"Servizi E Lavori Per Ecologia E Smaltimento Rifiuti. Forniture Industriali Per Prevenzione, Controllo E Sicurezza",
    "sg:phone":"+39 02 351 0559",
    "sg:postcode":"20021",
    "sg:province":"Milano",
    "wof:name":"2b Resine Srl",
    "wof:placetype":"venue"
},
  "geometry": {"coordinates":[9.146691,45.561996],"type":"Point"}
}