{
  "type": "Feature",
  "properties": {
    "iso:country":"IT",
    "sg:address":"92026 Favara",
    "sg:city":"Favara",
    "sg:orig_category":"Agricoltura, Orticoltura E Floricoltura. Articoli Da Regalo. Shopping",
    "sg:phone":"+39 0922 35983",
    "sg:postcode":"92026",
    "sg:province":"Agrigento",
    "wof:name":"Agenzia Funebre Morreale",
    "wof:placetype":"venue"
},
  "geometry": {"coordinates":[13.662124,37.322052],"type":"Point"}
}