{
  "type": "Feature",
  "properties": {
    "iso:country":"IT",
    "sg:address":"56037 Peccioli",
    "sg:city":"Fabbrica",
    "sg:orig_category":"Cine-foto-ottica",
    "sg:phone":"+39 0587 697147",
    "sg:postcode":"56037",
    "sg:province":"Pisa",
    "sg:website":"http://www.ilfotoamatore.it",
    "wof:name":"Il Fotoamatore Srl",
    "wof:placetype":"venue"
},
  "geometry": {"coordinates":[10.758035,43.507374],"type":"Point"}
}