{
  "type": "Feature",
  "properties": {
    "addr:full":"66051 Cupello Cupello Chieti 66051",
    "addr:postcode":"66051;66051",
    "iso:country":"IT",
    "sg:address":"66051 Cupello",
    "sg:city":"Cupello",
    "sg:classifiers":[
        {
            "category":"Wholesale",
            "subcategory":"Machinery & Supplies",
            "type":"Manufacturing & Wholesale Goods"
        }
    ],
    "sg:phone":"+39 0873 318330",
    "sg:postcode":"66051",
    "sg:province":"Chieti",
    "sg:tags":[
        "product",
        "industrial",
        "equipment",
        "engineering",
        "mechanical",
        "electronic"
    ],
    "sg:website":"http://www.meccanicaengineering.it",
    "wof:name":"Meccanica Engineering Srl",
    "wof:placetype":"venue"
},
  "geometry": {"coordinates":[14.680757,42.066746],"type":"Point"}
}