{
  "type": "Feature",
  "properties": {
    "addr:full":"50, Via Cavour 46043 Castiglione Delle Stiviere Castiglione delle Stiviere Mantova 46043",
    "addr:postcode":"46043;46043",
    "addr:street":"Via Cavour",
    "iso:country":"IT",
    "sg:address":"50, Via Cavour 46043 Castiglione Delle Stiviere",
    "sg:city":"Castiglione delle Stiviere",
    "sg:classifiers":[
        {
            "category":"Wholesale",
            "subcategory":"Drugs",
            "type":"Manufacturing & Wholesale Goods"
        }
    ],
    "sg:phone":"+39 390 376 6371",
    "sg:postcode":"46043",
    "sg:province":"Mantova",
    "sg:tags":[
        "chemical",
        "pharmaceutical"
    ],
    "wof:name":"Huntsman Surface Sciences Italia S.r.l.",
    "wof:placetype":"venue"
},
  "geometry": {"coordinates":[10.797698,45.160366],"type":"Point"}
}