{
  "type": "Feature",
  "properties": {
    "iso:country":"IT",
    "sg:address":"42, Via Provinciale 50037 San Piero A Sieve",
    "sg:city":"San Piero a Sieve",
    "sg:classifiers":[
        {
            "category":"Bars & Pubs",
            "subcategory":"Nightclub",
            "type":"Food & Drink"
        }
    ],
    "sg:phone":"+39 39055848054",
    "sg:postcode":"50037",
    "sg:province":"Firenze",
    "sg:tags":[
        "cake",
        "bread"
    ],
    "wof:name":"Forno Conti Giuliano Srl",
    "wof:placetype":"venue"
},
  "geometry": {"coordinates":[11.32377,43.961231],"type":"Point"}
}