{
  "type": "Feature",
  "properties": {
    "addr:full":"Corso Novara 93 10154 Torino Torino Torino 10154",
    "addr:housenumber":"93",
    "addr:postcode":"10154;10154",
    "addr:street":"Corso Novara",
    "iso:country":"IT",
    "sg:address":"Corso Novara 93 10154 Torino",
    "sg:city":"Torino",
    "sg:classifiers":[
        {
            "category":"Manufacturing",
            "subcategory":"Rubber & Plastics",
            "type":"Manufacturing & Wholesale Goods"
        }
    ],
    "sg:phone":"+39 011 851041",
    "sg:postcode":"10154",
    "sg:province":"Torino",
    "sg:tags":[
        "mould",
        "industry"
    ],
    "wof:name":"Gibin Snc Di Gibin Albino & C.",
    "wof:placetype":"venue"
},
  "geometry": {"coordinates":[8.3989200592,45.4623451233],"type":"Point"}
}