{
  "type": "Feature",
  "properties": {
    "iso:country":"IT",
    "sg:address":"1, Vico Veneto Fr. Fizzonasco 20090 Pieve Emanuele",
    "sg:city":"Fizzonasco",
    "sg:classifiers":[
        {
            "category":"Personal",
            "subcategory":"Shoe Repair & Shine",
            "type":"Services"
        }
    ],
    "sg:phone":"+39 02 9072 5290",
    "sg:postcode":"20090",
    "sg:province":"Milano",
    "sg:tags":[
        "leather"
    ],
    "wof:name":"Kezal (s.r.l.)",
    "wof:placetype":"venue"
},
  "geometry": {"coordinates":[9.188141,45.463688],"type":"Point"}
}