{
  "type": "Feature",
  "properties": {
    "iso:country":"IT",
    "sg:address":"26, Via S. Croce 40122 Bologna",
    "sg:city":"Bologna",
    "sg:classifiers":[
        {
            "category":"Travel",
            "subcategory":"Travel Agent",
            "type":"Entertainment"
        }
    ],
    "sg:phone":"+39 39051523322",
    "sg:postcode":"40122",
    "sg:province":"Bologna",
    "sg:tags":[
        "business"
    ],
    "wof:name":"Albergo Re Enzo",
    "wof:placetype":"venue"
},
  "geometry": {"coordinates":[11.271878,44.50074],"type":"Point"}
}