{
  "type": "Feature",
  "properties": {
    "addr:full":"30030 Martellago Martellago Venezia 30030",
    "addr:postcode":"30030;30030",
    "iso:country":"IT",
    "sg:address":"30030 Martellago",
    "sg:city":"Martellago",
    "sg:orig_category":"Studi E Consulenze Amministrative, Commerciali E Aziendali. Consulenze Tecniche, Amministrative E Perizie",
    "sg:phone":"+39 041 540 3199",
    "sg:postcode":"30030",
    "sg:province":"Venezia",
    "sg:website":"http://www.lisaservizi.it",
    "wof:name":"Lisa Servizi Srl",
    "wof:placetype":"venue"
},
  "geometry": {"coordinates":[12.164495,45.545261],"type":"Point"}
}