{
  "type": "Feature",
  "properties": {
    "iso:country":"IT",
    "sg:address":"25125 Brescia",
    "sg:city":"Brescia",
    "sg:orig_category":"Gioielleria, Oreficeria E Argenteria. Shopping",
    "sg:phone":"+39 030 354 1776",
    "sg:postcode":"25125",
    "sg:province":"Brescia",
    "sg:website":"http://www.zanolli.com",
    "wof:name":"Zanolli A. Spa",
    "wof:placetype":"venue"
},
  "geometry": {"coordinates":[10.182972,45.526886],"type":"Point"}
}