{
  "type": "Feature",
  "properties": {
    "addr:full":"98123 Messina Messina Messina 98123",
    "addr:postcode":"98123;98123",
    "iso:country":"IT",
    "sg:address":"98123 Messina",
    "sg:city":"Messina",
    "sg:orig_category":"Prodotti Di Base E Forniture Per Industria Alimentare E Bevande. Prodotti Chimici Di Base",
    "sg:phone":"+39 090 293 2121",
    "sg:postcode":"98123",
    "sg:province":"Messina",
    "wof:name":"Roberto Antonino & Figli",
    "wof:placetype":"venue"
},
  "geometry": {"coordinates":[15.5548143387,38.1801147461],"type":"Point"}
}