{
  "type": "Feature",
  "properties": {
    "iso:country":"IT",
    "sg:address":"20132 Milano",
    "sg:city":"Milano",
    "sg:orig_category":"Scuole E Servizi Scolastici. Ricerca, Selezione E Formazione Del Personale. Pubblica Amministrazione",
    "sg:phone":"+39 02 282 0786",
    "sg:postcode":"20132",
    "sg:province":"Milano",
    "wof:name":"Istituti Tecnici Industriale E. Molinari",
    "wof:placetype":"venue"
},
  "geometry": {"coordinates":[9.239859,45.496204],"type":"Point"}
}