{
  "type": "Feature",
  "properties": {
    "iso:country":"IT",
    "sg:address":"59015 Carmignano",
    "sg:city":"Carmignano",
    "sg:orig_category":"Ecologia - Studi Consulenza E Servizi",
    "sg:phone":"+39 055 871 8334",
    "sg:postcode":"59015",
    "sg:province":"Prato",
    "sg:website":"http://www.ecorent.it",
    "wof:name":"Ecorent Spa",
    "wof:placetype":"venue"
},
  "geometry": {"coordinates":[11.054593,43.784721],"type":"Point"}
}