{
  "type": "Feature",
  "properties": {
    "addr:full":"47, Via Marconi Guglielmo 31021 Mogliano Veneto Mogliano Veneto Treviso 31021",
    "addr:postcode":"31021;31021",
    "addr:street":"Via Marconi Guglielmo",
    "iso:country":"IT",
    "sg:address":"47, Via Marconi Guglielmo 31021 Mogliano Veneto",
    "sg:city":"Mogliano Veneto",
    "sg:classifiers":[
        {
            "category":"Farming",
            "subcategory":"Livestock Farm",
            "type":"Manufacturing & Wholesale Goods"
        }
    ],
    "sg:phone":"+39 041 590 2470",
    "sg:postcode":"31021",
    "sg:province":"Treviso",
    "sg:tags":[
        "agriculture"
    ],
    "wof:name":"Associazione Produttori Ortofrutticoli Della Marca Trivigiana",
    "wof:placetype":"venue"
},
  "geometry": {"coordinates":[12.164348,45.626915],"type":"Point"}
}