{
  "type": "Feature",
  "properties": {
    "iso:country":"IT",
    "sg:address":"00155 Roma",
    "sg:city":"Roma",
    "sg:orig_category":"Tessuti E Stoffe",
    "sg:phone":"+39 06 228 0459",
    "sg:postcode":"00155",
    "sg:province":"Roma",
    "wof:name":"Rifiniture D'interni Di Tempesta Lionello",
    "wof:placetype":"venue"
},
  "geometry": {"coordinates":[12.584893,41.910336],"type":"Point"}
}