{
  "type": "Feature",
  "properties": {
    "iso:country":"IT",
    "sg:address":"43100 Parma",
    "sg:city":"Parma",
    "sg:orig_category":"Servizi Editoriali. Shopping",
    "sg:phone":"+39 0521 386451",
    "sg:postcode":"43100",
    "sg:province":"Parma",
    "sg:website":"http://www.passatopresente.it",
    "wof:name":"Libreria Di Via N. Bixio",
    "wof:placetype":"venue"
},
  "geometry": {"coordinates":[10.318746,44.796833],"type":"Point"}
}