{
  "type": "Feature",
  "properties": {
    "iso:country":"IT",
    "sg:address":"00061 Anguillara Sabazia",
    "sg:city":"Anguillara Sabazia",
    "sg:orig_category":"Dolciumi E Gelati",
    "sg:phone":"+39 06 996 8500",
    "sg:postcode":"00061",
    "sg:province":"Roma",
    "wof:name":"Boscherini Sonia",
    "wof:placetype":"venue"
},
  "geometry": {"coordinates":[12.271657,42.09145],"type":"Point"}
}