{
  "type": "Feature",
  "properties": {
    "addr:full":"Via Cavour, 79; Trani; 70059 Trani Bari 70059",
    "addr:housenumber":"79",
    "addr:postcode":"70059;70059",
    "addr:street":"Via Cavour",
    "iso:country":"IT",
    "sg:address":"Via Cavour, 79; Trani; 70059",
    "sg:city":"Trani",
    "sg:classifiers":[
        {
            "category":"Banks & Credit Unions",
            "subcategory":"Bank",
            "type":"Services"
        }
    ],
    "sg:phone":"+39 0883 589380",
    "sg:postcode":"70059",
    "sg:province":"Bari",
    "wof:name":"Banco Di Santo Spirito",
    "wof:placetype":"venue"
},
  "geometry": {"coordinates":[16.419727,41.274521],"type":"Point"}
}