{
  "type": "Feature",
  "properties": {
    "addr:full":"10030 Vische Vische Torino 10030",
    "addr:housenumber":"10030",
    "addr:postcode":"10030",
    "addr:street":"Vische Vische",
    "iso:country":"IT",
    "sg:address":"10030 Vische",
    "sg:city":"Vische",
    "sg:orig_category":"Servizi E Lavori Per Agricoltura E Zootecnia. Servizi E Lavori Per Ecologia E Smaltimento Rifiuti",
    "sg:phone":"+39 011 983 7946",
    "sg:postcode":"10030",
    "sg:province":"Torino",
    "wof:name":"Associazione Irrigazione Est Sesia",
    "wof:placetype":"venue"
},
  "geometry": {"coordinates":[7.945944,45.335201],"type":"Point"}
}