{
  "type": "Feature",
  "properties": {
    "iso:country":"IT",
    "sg:address":"10028 Trofarello",
    "sg:city":"Trofarello",
    "sg:orig_category":"Utensili Meccanici E Materiali",
    "sg:phone":"+39 011 648 1237",
    "sg:postcode":"10028",
    "sg:province":"Torino",
    "wof:name":"Aviolamer Srl",
    "wof:placetype":"venue"
},
  "geometry": {"coordinates":[7.727484,44.961952],"type":"Point"}
}