{
  "type": "Feature",
  "properties": {
    "iso:country":"IT",
    "sg:address":"20025 Legnano",
    "sg:city":"Legnano",
    "sg:orig_category":"Macchine Utensili E Impianti",
    "sg:phone":"+39 0331 440112",
    "sg:postcode":"20025",
    "sg:province":"Milano",
    "wof:name":"Colombo Egidio Sas",
    "wof:placetype":"venue"
},
  "geometry": {"coordinates":[9.2725,45.52869],"type":"Point"}
}