{
  "type": "Feature",
  "properties": {
    "addr:full":"43038 Sala Baganza Sala Baganza Parma 43038",
    "addr:housenumber":"baganza",
    "addr:postcode":"43038;43038",
    "addr:street":"Parma",
    "iso:country":"IT",
    "sg:address":"43038 Sala Baganza",
    "sg:city":"Sala Baganza",
    "sg:orig_category":"Macchine, Impianti Ed Attrezzature Per Industria Alimentare E Bevande",
    "sg:phone":"+39 0521 836441",
    "sg:postcode":"43038",
    "sg:province":"Parma",
    "wof:name":"Coppi Impianti Srl",
    "wof:placetype":"venue"
},
  "geometry": {"coordinates":[10.236856,44.723183],"type":"Point"}
}