{
  "type": "Feature",
  "properties": {
    "iso:country":"IT",
    "sg:address":"Via Monte Cervialto 129; Roma; 00139",
    "sg:city":"Roma",
    "sg:classifiers":[
        {
            "category":"Banks & Credit Unions",
            "subcategory":"Bank",
            "type":"Services"
        }
    ],
    "sg:phone":"+39 06 886 0878",
    "sg:postcode":"00139",
    "sg:province":"Roma",
    "wof:name":"Istituto Bancario San Paolo, Di Torino Spa",
    "wof:placetype":"venue"
},
  "geometry": {"coordinates":[12.52335,41.954853],"type":"Point"}
}