{
  "type": "Feature",
  "properties": {
    "iso:country":"IT",
    "sg:address":"20032 Cormano",
    "sg:city":"Cormano",
    "sg:orig_category":"Macchine, Impianti Ed Attrezzature Per Abbigliamento E Pelletterie",
    "sg:phone":"+39 02 6630 5339",
    "sg:postcode":"20032",
    "sg:province":"Milano",
    "wof:name":"A.s. Italia Srl",
    "wof:placetype":"venue"
},
  "geometry": {"coordinates":[9.166234,45.540562],"type":"Point"}
}