{
  "type": "Feature",
  "properties": {
    "iso:country":"IT",
    "sg:address":"50122 Firenze",
    "sg:city":"Firenze",
    "sg:orig_category":"Accademie",
    "sg:phone":"+39 055 214214",
    "sg:postcode":"50122",
    "sg:province":"Firenze",
    "wof:name":"Armonia Hair Academy Sas",
    "wof:placetype":"venue"
},
  "geometry": {"coordinates":[11.256248,43.767994],"type":"Point"}
}