{
  "type": "Feature",
  "properties": {
    "addr:full":"46029 Suzzara Suzzara Mantova 46029",
    "addr:postcode":"46029;46029",
    "iso:country":"IT",
    "sg:address":"46029 Suzzara",
    "sg:city":"Suzzara",
    "sg:orig_category":"Frigoriferi Industriali E Commerciali - Commercio",
    "sg:phone":"+39 0376 535689",
    "sg:postcode":"46029",
    "sg:province":"Mantova",
    "wof:name":"Jigs Service Srl",
    "wof:placetype":"venue"
},
  "geometry": {"coordinates":[10.7508449554,45.0084915161],"type":"Point"}
}