{
  "type": "Feature",
  "properties": {
    "iso:country":"IT",
    "sg:address":"26, Via Emilia Est 42048 Rubiera",
    "sg:classifiers":[
        {
            "category":"Food & Beverages",
            "subcategory":"Groceries & Convenience Stores",
            "type":"Retail Goods"
        }
    ],
    "sg:phone":"+39 0522 626245",
    "sg:postcode":"42048",
    "sg:province":"Reggio Nell'Emilia",
    "sg:tags":[
        "drink"
    ],
    "wof:name":"Vinicola S. Nazaro (s.r.l.)",
    "wof:placetype":"venue"
},
  "geometry": {"coordinates":[10.786415,44.652573],"type":"Point"}
}