{
  "type": "Feature",
  "properties": {
    "addr:full":"Via Delle Industrie 20040 Usmate Velate Usmate Velate Milano 20040",
    "addr:postcode":"20040;20040",
    "addr:street":"Via Delle Industrie",
    "iso:country":"IT",
    "sg:address":"Via Delle Industrie 20040 Usmate Velate",
    "sg:city":"Usmate Velate",
    "sg:classifiers":[
        {
            "category":"Professional",
            "subcategory":"Engineering",
            "type":"Services"
        }
    ],
    "sg:phone":"+39 39039675162",
    "sg:postcode":"20040",
    "sg:province":"Milano",
    "sg:tags":[
        "machine",
        "-",
        "mechanical"
    ],
    "wof:name":"Olivini Srl",
    "wof:placetype":"venue"
},
  "geometry": {"coordinates":[9.343933,45.644005],"type":"Point"}
}