{
  "type": "Feature",
  "properties": {
    "iso:country":"IT",
    "sg:address":"19/a, Via Isola Di Sotto 13011 Borgosesia",
    "sg:city":"Borgosesia",
    "sg:classifiers":[
        {
            "category":"Shopping",
            "subcategory":"Clothing, Apparel, & Fashions",
            "type":"Retail Goods"
        }
    ],
    "sg:phone":"+39 39016325501",
    "sg:postcode":"13011",
    "sg:province":"Vercelli",
    "sg:tags":[
        "clothes"
    ],
    "wof:name":"Fullin Due S.r.l.",
    "wof:placetype":"venue"
},
  "geometry": {"coordinates":[8.426394,45.32106],"type":"Point"}
}