{
  "type": "Feature",
  "properties": {
    "addr:full":"8, Via Cirenei Luigi 20128 Milano Milano Milano 20128",
    "addr:postcode":"20128;20128",
    "addr:street":"Via Cirenei Luigi",
    "iso:country":"IT",
    "sg:address":"8, Via Cirenei Luigi 20128 Milano",
    "sg:city":"Milano",
    "sg:classifiers":[
        {
            "category":"Professional",
            "subcategory":"Engineering",
            "type":"Services"
        }
    ],
    "sg:phone":"+39 02 2700 2211",
    "sg:postcode":"20128",
    "sg:province":"Milano",
    "sg:tags":[
        "machine",
        "-",
        "mechanical"
    ],
    "wof:name":"Ep Srl",
    "wof:placetype":"venue"
},
  "geometry": {"coordinates":[9.229269,45.507824],"type":"Point"}
}