{
  "type": "Feature",
  "properties": {
    "iso:country":"IT",
    "sg:address":"33028 Tolmezzo",
    "sg:city":"Tolmezzo",
    "sg:orig_category":"Servizi E Lavori Industria Della Gomma",
    "sg:phone":"+39 0433 41841",
    "sg:postcode":"33028",
    "sg:province":"Udine",
    "wof:name":"Csat Srl",
    "wof:placetype":"venue"
},
  "geometry": {"coordinates":[13.040964,46.446602],"type":"Point"}
}