{
  "type": "Feature",
  "properties": {
    "iso:country":"IT",
    "sg:address":"22060 Carugo",
    "sg:city":"Carugo",
    "sg:orig_category":"Non-classified Establishments",
    "sg:phone":"+39 031 762400",
    "sg:postcode":"22060",
    "sg:province":"Como",
    "wof:name":"Sintonie Vetri D'arte",
    "wof:placetype":"venue"
},
  "geometry": {"coordinates":[9.20261,45.677994],"type":"Point"}
}