{
  "type": "Feature",
  "properties": {
    "addr:full":"13, Via Vicinale Spadoni 55012 Capannori Capannori Lucca 55012",
    "addr:postcode":"55012;55012",
    "addr:street":"Via Vicinale Spadoni",
    "iso:country":"IT",
    "sg:address":"13, Via Vicinale Spadoni 55012 Capannori",
    "sg:city":"Capannori",
    "sg:classifiers":[
        {
            "category":"Professional",
            "subcategory":"Engineering",
            "type":"Services"
        }
    ],
    "sg:phone":"+39 0583 407480",
    "sg:postcode":"55012",
    "sg:province":"Lucca",
    "sg:tags":[
        "machine",
        "-",
        "mechanical"
    ],
    "wof:name":"Alesa S.n.c.",
    "wof:placetype":"venue"
},
  "geometry": {"coordinates":[10.583333,43.833332],"type":"Point"}
}