{
  "type": "Feature",
  "properties": {
    "iso:country":"IT",
    "sg:address":"13, Via Deppo 32040 Domegge Di Cadore",
    "sg:city":"Domegge di Cadore",
    "sg:classifiers":[
        {
            "category":"Wholesale",
            "subcategory":"Medical Equipment & Supplies",
            "type":"Manufacturing & Wholesale Goods"
        }
    ],
    "sg:phone":"+39 0435 728330",
    "sg:postcode":"32040",
    "sg:province":"Belluno",
    "sg:tags":[
        "-",
        "health",
        "instrument"
    ],
    "wof:name":"Cian",
    "wof:placetype":"venue"
},
  "geometry": {"coordinates":[12.413094,46.461792],"type":"Point"}
}