{
  "type": "Feature",
  "properties": {
    "iso:country":"IT",
    "sg:address":"20152 Milano",
    "sg:city":"Milano",
    "sg:orig_category":"Arredo Cucina Ed Elettrodomestici. Frigotecnica, Apparecchiature E Servizi. Elettrodomestici",
    "sg:phone":"+39 02 4891 1845",
    "sg:postcode":"20152",
    "sg:province":"Milano",
    "wof:name":"Aldrighi Francesco",
    "wof:placetype":"venue"
},
  "geometry": {"coordinates":[9.138498,45.463501],"type":"Point"}
}