{
  "type": "Feature",
  "properties": {
    "addr:full":"6, Via Edison 59015 Carmignano Carmignano Prato 59015",
    "addr:postcode":"59015;59015",
    "addr:street":"Via Edison",
    "iso:country":"IT",
    "sg:address":"6, Via Edison 59015 Carmignano",
    "sg:city":"Carmignano",
    "sg:classifiers":[
        {
            "category":"Shopping",
            "subcategory":"Clothing, Apparel, & Fashions",
            "type":"Retail Goods"
        }
    ],
    "sg:phone":"+39 055 870 5094",
    "sg:postcode":"59015",
    "sg:province":"Prato",
    "sg:tags":[
        "clothes"
    ],
    "wof:name":"Maglificio Gori Snc Di Gori Alessandro & C.",
    "wof:placetype":"venue"
},
  "geometry": {"coordinates":[11.036561,43.833355],"type":"Point"}
}