{
  "type": "Feature",
  "properties": {
    "addr:full":"1, Zona Artigianale 33029 Raveo Raveo Udine 33029",
    "addr:housenumber":"1",
    "addr:postcode":"33029;33029",
    "addr:street":"Zona Artigianale",
    "iso:country":"IT",
    "sg:address":"1, Zona Artigianale 33029 Raveo",
    "sg:city":"Raveo",
    "sg:classifiers":[
        {
            "category":"Wholesale",
            "subcategory":"Medical Equipment & Supplies",
            "type":"Manufacturing & Wholesale Goods"
        }
    ],
    "sg:phone":"+39 0433 746295",
    "sg:postcode":"33029",
    "sg:province":"Udine",
    "sg:tags":[
        "-",
        "health",
        "instrument"
    ],
    "wof:name":"Laboratorio Bs Srl Con Socio Unico",
    "wof:placetype":"venue"
},
  "geometry": {"coordinates":[13.230724,46.064941],"type":"Point"}
}