{
  "type": "Feature",
  "properties": {
    "addr:full":"36071 Arzignano Arzignano Vicenza 36071",
    "addr:postcode":"36071;36071",
    "iso:country":"IT",
    "sg:address":"36071 Arzignano",
    "sg:city":"Arzignano",
    "sg:orig_category":"Agenzie D'affari E Servizi Commerciali",
    "sg:phone":"+39 0444 450035",
    "sg:postcode":"36071",
    "sg:province":"Vicenza",
    "sg:website":"http://www.euroleather.it",
    "wof:name":"Euroleather",
    "wof:placetype":"venue"
},
  "geometry": {"coordinates":[11.513581,45.526112],"type":"Point"}
}