{
  "type": "Feature",
  "properties": {
    "iso:country":"IT",
    "sg:address":"43, Localita' Pian Da Lago 32043 Cortina D'ampezzo",
    "sg:classifiers":[
        {
            "category":"Professional",
            "subcategory":"Engineering",
            "type":"Services"
        }
    ],
    "sg:phone":"+39 0436 867941",
    "sg:postcode":"32043",
    "sg:province":"Belluno",
    "sg:tags":[
        "machine",
        "-",
        "mechanical"
    ],
    "wof:name":"Siorpaes Snc Di Siorpaes Marco & C.",
    "wof:placetype":"venue"
},
  "geometry": {"coordinates":[12.153502,46.509716],"type":"Point"}
}