{
  "type": "Feature",
  "properties": {
    "iso:country":"IT",
    "sg:address":"66, Via Fabio Filzi 31036 Istrana",
    "sg:city":"Istrana",
    "sg:classifiers":[
        {
            "category":"Autos & Motor Vehicles",
            "subcategory":"Automobile Sales",
            "type":"Retail Goods"
        }
    ],
    "sg:phone":"+39 0422 832300",
    "sg:postcode":"31036",
    "sg:province":"Treviso",
    "sg:tags":[
        "equipment",
        "transport"
    ],
    "wof:name":"Axo Sport S.p.a.",
    "wof:placetype":"venue"
},
  "geometry": {"coordinates":[12.094204,45.673557],"type":"Point"}
}