{
  "type": "Feature",
  "properties": {
    "iso:country":"IT",
    "sg:address":"16/b, V. Mattei 25060 Collebeato",
    "sg:city":"Collebeato",
    "sg:classifiers":[
        {
            "category":"Professional",
            "subcategory":"Engineering",
            "type":"Services"
        }
    ],
    "sg:phone":"+39 030 251 1234",
    "sg:postcode":"25060",
    "sg:province":"Brescia",
    "sg:tags":[
        "machine",
        "-",
        "mechanical"
    ],
    "sg:website":"http://www.paginegialle.it/sertom",
    "wof:name":"Sertom Mm Metalforming",
    "wof:placetype":"venue"
},
  "geometry": {"coordinates":[10.211626,45.57655],"type":"Point"}
}