{
  "type": "Feature",
  "properties": {
    "iso:country":"IT",
    "sg:address":"06010 Monte Santa Maria Tiberina",
    "sg:city":"Monte Santa Maria Tiberina",
    "sg:orig_category":"Prodotti Chimici Secondari. Servizi E Lavori Per Ecologia E Smaltimento Rifiuti. Macchine E Forniture Per Ecologia E Smaltimento Rifiuti",
    "sg:phone":"+39 075 857 0105",
    "sg:postcode":"06010",
    "sg:province":"Perugia",
    "wof:name":"Giambi Carlo",
    "wof:placetype":"venue"
},
  "geometry": {"coordinates":[12.1632957458,43.4370536804],"type":"Point"}
}