{
  "type": "Feature",
  "properties": {
    "addr:full":"20121 Milano Milano Milano 20121",
    "addr:postcode":"20121;20121",
    "iso:country":"IT",
    "sg:address":"20121 Milano",
    "sg:city":"Milano",
    "sg:orig_category":"Facchinaggio, Carico E Scarico Merci, Portabagagli - Servizio",
    "sg:phone":"+39 02 659 8071",
    "sg:postcode":"20121",
    "sg:province":"Milano",
    "wof:name":"Cooperativa Di Solidariet\u00c0 Sociale S. Marco",
    "wof:placetype":"venue"
},
  "geometry": {"coordinates":[9.1878757477,45.4734802246],"type":"Point"}
}