{
  "type": "Feature",
  "properties": {
    "addr:full":"6, Via Lazio 36015 Schio Schio Vicenza 36015",
    "addr:postcode":"36015;36015",
    "addr:street":"Via Lazio",
    "iso:country":"IT",
    "sg:address":"6, Via Lazio 36015 Schio",
    "sg:city":"Schio",
    "sg:classifiers":[
        {
            "category":"Shopping",
            "subcategory":"Crafts & Fabrics",
            "type":"Retail Goods"
        }
    ],
    "sg:phone":"+39 0445 675500",
    "sg:postcode":"36015",
    "sg:province":"Vicenza",
    "wof:name":"Lanificio Di Schio Sas Di Jonathan Antony Todhunter",
    "wof:placetype":"venue"
},
  "geometry": {"coordinates":[11.3974542618,45.7212600708],"type":"Point"}
}