{
  "type": "Feature",
  "properties": {
    "iso:country":"IT",
    "sg:address":"34015 Muggia",
    "sg:city":"Muggia",
    "sg:orig_category":"Elettrotecnica Industriale, Prodotti E Apparecchiature. Ricambi E Componenti Dei Mezzi Di Trasporto",
    "sg:phone":"+39 040 232680",
    "sg:postcode":"34015",
    "sg:province":"Trieste",
    "sg:website":"http://www.ricocar.it",
    "wof:name":"Ri.co.car. Snc",
    "wof:placetype":"venue"
},
  "geometry": {"coordinates":[13.767405,45.604198],"type":"Point"}
}