{
  "type": "Feature",
  "properties": {
    "iso:country":"IT",
    "sg:address":"5, V. Dei Campi28050 Vallio Terme",
    "sg:classifiers":[
        {
            "category":"Shopping",
            "subcategory":"Clothing, Apparel, & Fashions",
            "type":"Retail Goods"
        }
    ],
    "sg:phone":"+39 036 537 0025",
    "sg:postcode":"28050",
    "sg:province":"Novara",
    "sg:tags":[
        "clothes"
    ],
    "sg:website":"http://www.lppasini.it",
    "wof:name":"L.p. Di Lazzari L. Pasini M.",
    "wof:placetype":"venue"
},
  "geometry": {"coordinates":[8.618671,45.445084],"type":"Point"}
}