{
  "type": "Feature",
  "properties": {
    "iso:country":"IT",
    "sg:address":"48022 Lugo",
    "sg:city":"Lugo",
    "sg:orig_category":"Mercerie",
    "sg:phone":"+39 0545 26997",
    "sg:postcode":"48022",
    "sg:province":"Ravenna",
    "sg:website":"http://www.scardovi.com",
    "wof:name":"Scardovi Snc Di Scardovi Stefano & C.",
    "wof:placetype":"venue"
},
  "geometry": {"coordinates":[11.8624000549,44.4413871765],"type":"Point"}
}