{
  "type": "Feature",
  "properties": {
    "iso:country":"IT",
    "sg:address":"34, Via Cagnazzi Luca Samuele 70124 Bari",
    "sg:city":"Bari",
    "sg:classifiers":[
        {
            "category":"Professional",
            "subcategory":"Advertising",
            "type":"Services"
        }
    ],
    "sg:phone":"+39 080 501 3811",
    "sg:postcode":"70124",
    "sg:province":"Bari",
    "sg:tags":[
        "communication",
        "medium"
    ],
    "wof:name":"De Giglio F.lli (s.n.c.)",
    "wof:placetype":"venue"
},
  "geometry": {"coordinates":[16.869291,41.126053],"type":"Point"}
}