{
  "type": "Feature",
  "properties": {
    "addr:full":"Via Nazionale 65 62029 Tolentino Tolentino Macerata 62029",
    "addr:housenumber":"65",
    "addr:postcode":"62029;62029",
    "addr:street":"Via Nazionale",
    "iso:country":"IT",
    "sg:address":"Via Nazionale 65 62029 Tolentino",
    "sg:city":"Tolentino",
    "sg:orig_category":"Hoisiery Goods",
    "sg:phone":"+39 0733 971562",
    "sg:postcode":"62029",
    "sg:province":"Macerata",
    "wof:name":"Maglificio Donny & Max Srl",
    "wof:placetype":"venue"
},
  "geometry": {"coordinates":[13.297858,43.211655],"type":"Point"}
}