{
  "type": "Feature",
  "properties": {
    "iso:country":"IT",
    "sg:address":"74100 Taranto",
    "sg:city":"Taranto",
    "sg:classifiers":[
        {
            "category":"Banks & Credit Unions",
            "subcategory":"Investment Brokerage",
            "type":"Services"
        }
    ],
    "sg:phone":"+39 099 735 2067",
    "sg:postcode":"74100",
    "sg:province":"Taranto",
    "sg:tags":[
        "bathing",
        "shopping",
        "underwear",
        "stocking",
        "costumes"
    ],
    "wof:name":"Hibiscus - Calze E Lingerie Di Pizzini Patrizia",
    "wof:placetype":"venue"
},
  "geometry": {"coordinates":[17.261314,40.45813],"type":"Point"}
}