{
  "type": "Feature",
  "properties": {
    "iso:country":"IT",
    "sg:address":"47900 Rimini",
    "sg:city":"Rimini",
    "sg:orig_category":"Accessori Moda D'abbigliamento. Forniture Per Abbigliamento E Pelletterie",
    "sg:phone":"+39 0541 771045",
    "sg:postcode":"47900",
    "sg:province":"Rimini",
    "wof:name":"Mastrolonardo (s.n.c.)",
    "wof:placetype":"venue"
},
  "geometry": {"coordinates":[12.460591,44.072151],"type":"Point"}
}