{
  "type": "Feature",
  "properties": {
    "addr:full":"Via S.margherita 12/14; Milano",
    "addr:housenumber":"12 / 14",
    "addr:street":"Via S.Margherita",
    "iso:country":"IT",
    "sg:address":"Via S.margherita 12/14; Milano",
    "sg:classifiers":[
        {
            "category":"Banks & Credit Unions",
            "subcategory":"Bank",
            "type":"Services"
        }
    ],
    "sg:phone":"+39 0288491",
    "wof:name":"Banco Di Sicilia Spa",
    "wof:placetype":"venue"
},
  "geometry": {"coordinates":[9.188732,45.466259],"type":"Point"}
}