{
  "type": "Feature",
  "properties": {
    "iso:country":"IT",
    "sg:address":"45030 Occhiobello",
    "sg:city":"Occhiobello",
    "sg:orig_category":"Imprese Di Costruzioni Civili Ed Industriali",
    "sg:phone":"+39 0425 750142",
    "sg:postcode":"45030",
    "sg:province":"Rovigo",
    "wof:name":"La Venexiana S.r.l.",
    "wof:placetype":"venue"
},
  "geometry": {"coordinates":[11.572592,44.926533],"type":"Point"}
}