{
  "type": "Feature",
  "properties": {
    "addr:full":"Viale Hanbury 28-ang.; Alassio; 17021 Alassio Savona 17021",
    "addr:housenumber":"28-ang",
    "addr:postcode":"17021;17021",
    "addr:street":"Viale Hanbury",
    "iso:country":"IT",
    "sg:address":"Viale Hanbury 28-ang.; Alassio; 17021",
    "sg:city":"Alassio",
    "sg:classifiers":[
        {
            "category":"Banks & Credit Unions",
            "subcategory":"Bank",
            "type":"Services"
        }
    ],
    "sg:phone":"+39 0182 640137",
    "sg:postcode":"17021",
    "sg:province":"Savona",
    "wof:name":"Credito Italiano Spa",
    "wof:placetype":"venue"
},
  "geometry": {"coordinates":[8.16117,44.017982],"type":"Point"}
}