{
  "type": "Feature",
  "properties": {
    "iso:country":"IT",
    "sg:address":"Via Alla Piana 61 21018 Sesto Calende",
    "sg:city":"Sesto Calende",
    "sg:classifiers":[
        {
            "category":"Utilities",
            "subcategory":"Recycling",
            "type":"Services"
        }
    ],
    "sg:phone":"+39 0331 920724",
    "sg:postcode":"21018",
    "sg:province":"Varese",
    "sg:tags":[
        "plastic"
    ],
    "sg:website":"www.rialti.it",
    "wof:name":"Rialti Srl",
    "wof:placetype":"venue"
},
  "geometry": {"coordinates":[8.640626,45.744156],"type":"Point"}
}