{
  "type": "Feature",
  "properties": {
    "addr:full":"26866 Sant'angelo Lodigiano Lodi 26866",
    "addr:postcode":"26866;26866",
    "iso:country":"IT",
    "sg:address":"26866 Sant'angelo Lodigiano",
    "sg:orig_category":"Prodotti Alimentari",
    "sg:phone":"+39 0371 211263",
    "sg:postcode":"26866",
    "sg:province":"Lodi",
    "wof:name":"Mg Di Garini Mario",
    "wof:placetype":"venue"
},
  "geometry": {"coordinates":[9.4096450806,45.2392044067],"type":"Point"}
}