{
  "type": "Feature",
  "properties": {
    "addr:full":"8, Via Brodolini 40056 Crespellano Crespellano Bologna 40056",
    "addr:postcode":"40056;40056",
    "addr:street":"Via Brodolini",
    "iso:country":"IT",
    "sg:address":"8, Via Brodolini 40056 Crespellano",
    "sg:city":"Crespellano",
    "sg:classifiers":[
        {
            "category":"Communications",
            "subcategory":"Television Station",
            "type":"Services"
        }
    ],
    "sg:phone":"+39 39051969870",
    "sg:postcode":"40056",
    "sg:province":"Bologna",
    "sg:tags":[
        "audio-visual"
    ],
    "wof:name":"A.e.b. S.r.l.",
    "wof:placetype":"venue"
},
  "geometry": {"coordinates":[11.175841,44.518326],"type":"Point"}
}