{
  "type": "Feature",
  "properties": {
    "iso:country":"IT",
    "sg:address":"38068 Rovereto",
    "sg:city":"Rovereto",
    "sg:orig_category":"Apparecchiature Ed Attrezzature Meccaniche. Elettronica Industriale, Prodotti E Apparecchiature",
    "sg:phone":"+39 0464 420456",
    "sg:postcode":"38068",
    "sg:province":"Trento",
    "sg:website":"http://www.elcora.com",
    "wof:name":"Cora Elettroautomazione Srl",
    "wof:placetype":"venue"
},
  "geometry": {"coordinates":[11.025466,45.864994],"type":"Point"}
}