{
  "type": "Feature",
  "properties": {
    "iso:country":"IT",
    "sg:address":"Frazione Mereta 16017 Isola Del Cantone",
    "sg:city":"Isola del Cantone",
    "sg:classifiers":[
        {
            "category":"Real Estate",
            "subcategory":"Surveying",
            "type":"Services"
        }
    ],
    "sg:phone":"+39 010 963 6745",
    "sg:postcode":"16017",
    "sg:province":"Genova",
    "sg:tags":[
        "equipment",
        "material",
        "good",
        "-",
        "handling"
    ],
    "wof:name":"Denios Srl",
    "wof:placetype":"venue"
},
  "geometry": {"coordinates":[8.938999,44.664833],"type":"Point"}
}