{
  "type": "Feature",
  "properties": {
    "iso:country":"IT",
    "sg:address":"25030 Roncadelle",
    "sg:city":"Roncadelle",
    "sg:orig_category":"Gioielleria, Oreficeria E Argenteria. Articoli Da Regalo. Shopping",
    "sg:phone":"+39 030 258 2933",
    "sg:postcode":"25030",
    "sg:province":"Brescia",
    "wof:name":"Romolo Boglioni & Figli S.n.c.",
    "wof:placetype":"venue"
},
  "geometry": {"coordinates":[10.156408,45.532837],"type":"Point"}
}