{
  "type": "Feature",
  "properties": {
    "iso:country":"IT",
    "sg:address":"66026 Ortona",
    "sg:city":"Ortona",
    "sg:orig_category":"Articoli Per Imballaggio E Confezionamento",
    "sg:phone":"+39 085 906 3149",
    "sg:postcode":"66026",
    "sg:province":"Chieti",
    "wof:name":"Bernabeo Antonio",
    "wof:placetype":"venue"
},
  "geometry": {"coordinates":[14.166231,42.345257],"type":"Point"}
}