{
  "type": "Feature",
  "properties": {
    "addr:full":"Via Roma 157, 75010 Gorgoglione, Mt Gorgoglione Matera 75010",
    "addr:housenumber":"157",
    "addr:postcode":"75010;75010",
    "addr:street":"Via Roma;Mt",
    "iso:country":"IT",
    "sg:address":"Via Roma 157, 75010 Gorgoglione, Mt",
    "sg:city":"Gorgoglione",
    "sg:classifiers":[
        {
            "category":"Banks & Credit Unions",
            "subcategory":"Bank",
            "type":"Services"
        }
    ],
    "sg:postcode":"75010",
    "sg:province":"Matera",
    "wof:name":"Banca Di Credito Cooperativo Agri-sauro",
    "wof:placetype":"venue"
},
  "geometry": {"coordinates":[16.144896,40.393635],"type":"Point"}
}