{
  "type": "Feature",
  "properties": {
    "iso:country":"IT",
    "sg:address":"16161 Genova",
    "sg:city":"Genova",
    "sg:orig_category":"Valvole E Apparecchiature Di Misura. Minuterie Metalliche E Ferramenta. Forniture Per Attivita' Industriali",
    "sg:phone":"+39 010 740 6261",
    "sg:postcode":"16161",
    "sg:province":"Genova",
    "wof:name":"I.m.s. (s.r.l.)",
    "wof:placetype":"venue"
},
  "geometry": {"coordinates":[8.887623,44.441998],"type":"Point"}
}