{
  "type": "Feature",
  "properties": {
    "iso:country":"IT",
    "sg:address":"01100 Viterbo",
    "sg:city":"Viterbo",
    "sg:orig_category":"Ferro Battuto",
    "sg:phone":"+39 0761 270945",
    "sg:postcode":"01100",
    "sg:province":"Viterbo",
    "sg:website":"http://www.estroitalia.com",
    "wof:name":"Estro Snc Di Sinibaldi Marco",
    "wof:placetype":"venue"
},
  "geometry": {"coordinates":[12.0924263,42.4462013245],"type":"Point"}
}