{
  "type": "Feature",
  "properties": {
    "addr:full":"62100 Macerata Macerata Macerata 62100",
    "addr:postcode":"62100;62100",
    "iso:country":"IT",
    "sg:address":"62100 Macerata",
    "sg:city":"Macerata",
    "sg:orig_category":"Argenterie - Vendita Al Dettaglio",
    "sg:phone":"+39 0733 230038",
    "sg:postcode":"62100",
    "sg:province":"Macerata",
    "sg:website":"http://www.cartechini.it",
    "wof:name":"Cartechini Argenterie",
    "wof:placetype":"venue"
},
  "geometry": {"coordinates":[13.45229,43.298874],"type":"Point"}
}