{
  "type": "Feature",
  "properties": {
    "addr:full":"6, Via Rossetti Paolo 44042 Cento Cento Ferrara 44042",
    "addr:postcode":"44042;44042",
    "addr:street":"Via Rossetti Paolo",
    "iso:country":"IT",
    "sg:address":"6, Via Rossetti Paolo 44042 Cento",
    "sg:city":"Cento",
    "sg:classifiers":[
        {
            "category":"Manufacturing",
            "subcategory":"Metals",
            "type":"Manufacturing & Wholesale Goods"
        }
    ],
    "sg:phone":"+39 051 684 1183",
    "sg:postcode":"44042",
    "sg:province":"Ferrara",
    "sg:tags":[
        "processing"
    ],
    "wof:name":"Rossi Afro Stamperia A Caldo S.r.l.",
    "wof:placetype":"venue"
},
  "geometry": {"coordinates":[11.6204395294,44.8378944397],"type":"Point"}
}