{
  "type": "Feature",
  "properties": {
    "iso:country":"IT",
    "sg:address":"16164 Genova",
    "sg:city":"Genova",
    "sg:orig_category":"Articoli Da Regalo. Arte Ed Artigianato Artistico. Shopping",
    "sg:phone":"+39 010 711422",
    "sg:postcode":"16164",
    "sg:province":"Genova",
    "wof:name":"Artrade (s.p.a.)",
    "wof:placetype":"venue"
},
  "geometry": {"coordinates":[8.9022,44.493393],"type":"Point"}
}