{
  "type": "Feature",
  "properties": {
    "iso:country":"IT",
    "sg:address":"23/25, Via Di Mezzo S. Giacomo Roncole 41037 Mirandola",
    "sg:city":"Mirandola",
    "sg:classifiers":[
        {
            "category":"Manufacturing",
            "subcategory":"Glass & Minerals",
            "type":"Manufacturing & Wholesale Goods"
        }
    ],
    "sg:phone":"+39 0535 610333",
    "sg:postcode":"41037",
    "sg:province":"Modena",
    "wof:name":"Encaplast (s.r.l.)",
    "wof:placetype":"venue"
},
  "geometry": {"coordinates":[11.009275,44.847816],"type":"Point"}
}