{
  "type": "Feature",
  "properties": {
    "iso:country":"IT",
    "sg:address":"16121 Genova",
    "sg:city":"Genova",
    "sg:orig_category":"Articoli Da Regalo. Regalistica Aziendale",
    "sg:phone":"+39 010 586370",
    "sg:postcode":"16121",
    "sg:province":"Genova",
    "wof:name":"Geit Di Ginocchio E. & C. (s.a.s.)",
    "wof:placetype":"venue"
},
  "geometry": {"coordinates":[8.943141,44.407001],"type":"Point"}
}