{
  "type": "Feature",
  "properties": {
    "addr:full":"00138 Roma Roma Roma 00138",
    "addr:postcode":"00138;00138",
    "iso:country":"IT",
    "sg:address":"00138 Roma",
    "sg:city":"Roma",
    "sg:orig_category":"Chiese Ed Associazioni Religiose",
    "sg:phone":"+39 06 880 2213",
    "sg:postcode":"00138",
    "sg:province":"Roma",
    "wof:name":"Chiesa Di Altri Culti Cristiana Evangelica A.d.i.",
    "wof:placetype":"venue"
},
  "geometry": {"coordinates":[12.51815,41.972862],"type":"Point"}
}