{
  "type": "Feature",
  "properties": {
    "addr:full":"Km. 160, Strada Padana Superiore 20060 Cassina De' Pecchi Milano 20060",
    "addr:postcode":"20060;20060",
    "addr:street":"Strada Padana Superiore",
    "iso:country":"IT",
    "sg:address":"Km. 160, Strada Padana Superiore 20060 Cassina De' Pecchi",
    "sg:orig_category":"Miscellaneous Products",
    "sg:phone":"+39 390 295 2581",
    "sg:postcode":"20060",
    "sg:province":"Milano",
    "wof:name":"Technogenetics S.r.l.",
    "wof:placetype":"venue"
},
  "geometry": {"coordinates":[9.1881408691,45.4636878967],"type":"Point"}
}