{
  "type": "Feature",
  "properties": {
    "iso:country":"IT",
    "sg:address":"31020 Revine Lago",
    "sg:city":"Lago",
    "sg:orig_category":"Prodotti Vari In Metallo",
    "sg:phone":"+39 0438 524061",
    "sg:postcode":"31020",
    "sg:province":"Treviso",
    "wof:name":"Fonderia Ing. Francesco De Poli Di Ettore Marchesin E C. (s.n.c.)",
    "wof:placetype":"venue"
},
  "geometry": {"coordinates":[12.2505922318,45.9951782227],"type":"Point"}
}