{
  "type": "Feature",
  "properties": {
    "iso:country":"IT",
    "sg:address":"Via Kennedy 29 26044 Grontardo",
    "sg:city":"Grontardo",
    "sg:classifiers":[
        {
            "category":"Structure",
            "subcategory":"Office Building",
            "type":"Public Place"
        }
    ],
    "sg:phone":"+39 0372 89170",
    "sg:postcode":"26044",
    "sg:province":"Cremona",
    "sg:tags":[
        "wall",
        "ceiling",
        "partition",
        "room",
        "clean"
    ],
    "sg:website":"www.padanacleanroom.it",
    "wof:name":"Padana Cleanroom Srl",
    "wof:placetype":"venue"
},
  "geometry": {"coordinates":[10.026135,45.133499],"type":"Point"}
}