{
  "type": "Feature",
  "properties": {
    "addr:full":"84087 Sarno Sarno Salerno 84087",
    "addr:postcode":"84087;84087",
    "iso:country":"IT",
    "sg:address":"84087 Sarno",
    "sg:city":"Sarno",
    "sg:classifiers":[
        {
            "category":"Health Services",
            "subcategory":"Health Practitioner",
            "type":"Services"
        }
    ],
    "sg:phone":"+39 081 942887",
    "sg:postcode":"84087",
    "sg:province":"Salerno",
    "sg:tags":[
        "medici"
    ],
    "wof:name":"Rizzo Antonio",
    "wof:placetype":"venue"
},
  "geometry": {"coordinates":[14.6238050461,40.8152351379],"type":"Point"}
}