{
  "type": "Feature",
  "properties": {
    "iso:country":"IT",
    "sg:address":"80, Via Bergamo 20040 Bellusco",
    "sg:city":"Bellusco",
    "sg:classifiers":[
        {
            "category":"Professional",
            "subcategory":"Engineering",
            "type":"Services"
        }
    ],
    "sg:phone":"+39 039 602 2784",
    "sg:postcode":"20040",
    "sg:province":"Milano",
    "sg:tags":[
        "machine",
        "-",
        "mechanical"
    ],
    "wof:name":"Crea (s.r.l.)",
    "wof:placetype":"venue"
},
  "geometry": {"coordinates":[9.428528,45.616306],"type":"Point"}
}