{
  "type": "Feature",
  "properties": {
    "iso:country":"IT",
    "sg:address":"Via Refrecc 184 22030 Lipomo",
    "sg:city":"Lipomo",
    "sg:classifiers":[
        {
            "category":"Transit Center",
            "subcategory":"Freight",
            "type":"Transportation"
        }
    ],
    "sg:phone":"+39 031 555807",
    "sg:postcode":"22030",
    "sg:province":"Como",
    "sg:tags":[
        "necktie"
    ],
    "sg:website":"www.francobassi.com",
    "wof:name":"B B Cravatte S.r.l.",
    "wof:placetype":"venue"
},
  "geometry": {"coordinates":[9.115064,45.798092],"type":"Point"}
}