{
  "type": "Feature",
  "properties": {
    "iso:country":"IT",
    "sg:address":"48/1, Via Faentina Nord 48026 Russi",
    "sg:city":"Russi",
    "sg:classifiers":[
        {
            "category":"Food & Beverages",
            "subcategory":"Groceries & Convenience Stores",
            "type":"Retail Goods"
        }
    ],
    "sg:phone":"+39 0544 582714",
    "sg:postcode":"48026",
    "sg:province":"Ravenna",
    "sg:tags":[
        "drink"
    ],
    "wof:name":"Azienda Vinicola Alla Grotta S.r.l.",
    "wof:placetype":"venue"
},
  "geometry": {"coordinates":[12.032543,44.37558],"type":"Point"}
}