{
  "type": "Feature",
  "properties": {
    "iso:country":"IT",
    "sg:address":"479, Contrada Bosco 91025 Marsala",
    "sg:city":"Marsala",
    "sg:classifiers":[
        {
            "category":"Shopping",
            "type":"Retail Goods"
        }
    ],
    "sg:phone":"+39 0923 995666",
    "sg:postcode":"91025",
    "sg:province":"Trapani",
    "sg:tags":[
        "finished",
        "-",
        "metallic"
    ],
    "wof:name":"Puleo S.r.l.",
    "wof:placetype":"venue"
},
  "geometry": {"coordinates":[12.5089530945,37.8472099304],"type":"Point"}
}