{
  "type": "Feature",
  "properties": {
    "iso:country":"IT",
    "sg:address":"33170 Pordenone",
    "sg:city":"Pordenone",
    "sg:orig_category":"Non-classified Establishments",
    "sg:phone":"+39 0434 361444",
    "sg:postcode":"33170",
    "sg:province":"Pordenone",
    "wof:name":"Legnoplan Srl",
    "wof:placetype":"venue"
},
  "geometry": {"coordinates":[12.646537,45.999832],"type":"Point"}
}