{
  "type": "Feature",
  "properties": {
    "addr:full":"20154 Milano Milano Milano 20154",
    "addr:postcode":"20154;20154",
    "iso:country":"IT",
    "sg:address":"20154 Milano",
    "sg:city":"Milano",
    "sg:orig_category":"Antenne Radio-televisione",
    "sg:phone":"+39 02 349 4140",
    "sg:postcode":"20154",
    "sg:province":"Milano",
    "sg:website":"http://www.antennaclub.it",
    "wof:name":"Antenna Club Srl",
    "wof:placetype":"venue"
},
  "geometry": {"coordinates":[9.164013,45.484505],"type":"Point"}
}