{
  "type": "Feature",
  "properties": {
    "iso:country":"IT",
    "sg:address":"10051 Avigliana",
    "sg:city":"Avigliana",
    "sg:orig_category":"Macchine, Impianti Ed Attrezzature Per Industria Alimentare E Bevande",
    "sg:phone":"+39 011 936 7085",
    "sg:postcode":"10051",
    "sg:province":"Torino",
    "wof:name":"Centro Idea Di Barbera Giuseppe",
    "wof:placetype":"venue"
},
  "geometry": {"coordinates":[7.38916,45.087818],"type":"Point"}
}