{
  "type": "Feature",
  "properties": {
    "addr:full":"09011 Calasetta Calasetta Carbonia-Iglesias 09011",
    "addr:postcode":"09011;09011",
    "iso:country":"IT",
    "sg:address":"09011 Calasetta",
    "sg:city":"Calasetta",
    "sg:orig_category":"Alberghi E Strutture Extra Alberghiere",
    "sg:phone":"+39 0781 88884",
    "sg:postcode":"09011",
    "sg:province":"Carbonia-Iglesias",
    "sg:website":"http://www.keotour.it",
    "wof:name":"Immobiliare Flavia Srl",
    "wof:placetype":"venue"
},
  "geometry": {"coordinates":[8.572101593,39.2534675598],"type":"Point"}
}