{
  "type": "Feature",
  "properties": {
    "iso:country":"IT",
    "sg:address":"10, Via Pertini 26845 Codogno",
    "sg:city":"Codogno",
    "sg:classifiers":[
        {
            "category":"Professional",
            "subcategory":"Engineering",
            "type":"Services"
        }
    ],
    "sg:phone":"+39 39037746661",
    "sg:postcode":"26845",
    "sg:province":"Lodi",
    "sg:tags":[
        "machine",
        "-",
        "mechanical"
    ],
    "wof:name":"Telme S.p.a.",
    "wof:placetype":"venue"
},
  "geometry": {"coordinates":[9.685261,45.156952],"type":"Point"}
}