{
  "type": "Feature",
  "properties": {
    "iso:country":"IT",
    "sg:address":"00155 Roma",
    "sg:city":"Roma",
    "sg:orig_category":"Frigotecnica, Apparecchiature E Servizi. Servizi Di Magazzinaggio E Movimentazione",
    "sg:phone":"+39 06 228 0263",
    "sg:postcode":"00155",
    "sg:province":"Roma",
    "wof:name":"Si.gi. Srl",
    "wof:placetype":"venue"
},
  "geometry": {"coordinates":[12.6068716049,41.898273468],"type":"Point"}
}