{
  "type": "Feature",
  "properties": {
    "iso:country":"IT",
    "sg:address":"42046 Villanova",
    "sg:orig_category":"Macchine Ed Impianti Per Edilizia E Lavori Pubblici",
    "sg:phone":"+39 0522 973348",
    "sg:postcode":"42046",
    "sg:province":"Reggio Nell'Emilia",
    "wof:name":"La Nuova Tecnica (s.n.c.)",
    "wof:placetype":"venue"
},
  "geometry": {"coordinates":[10.736733,44.850487],"type":"Point"}
}