{
  "type": "Feature",
  "properties": {
    "addr:full":"5, Via Privata Angrogna 10139 Torino Torino Torino 10139",
    "addr:postcode":"10139;10139",
    "addr:street":"Via Privata Angrogna",
    "iso:country":"IT",
    "sg:address":"5, Via Privata Angrogna 10139 Torino",
    "sg:city":"Torino",
    "sg:classifiers":[
        {
            "category":"Communications",
            "subcategory":"Newspaper",
            "type":"Services"
        }
    ],
    "sg:phone":"+39 011 771 8183",
    "sg:postcode":"10139",
    "sg:province":"Torino",
    "sg:tags":[
        "advertising"
    ],
    "wof:name":"Medical Communications Srl",
    "wof:placetype":"venue"
},
  "geometry": {"coordinates":[7.686619,45.07056],"type":"Point"}
}