{
  "type": "Feature",
  "properties": {
    "addr:full":"37, Via Leonardo Da Vinci 24043 Caravaggio Caravaggio Bergamo 24043",
    "addr:postcode":"24043;24043",
    "addr:street":"Via Leonardo Da Vinci",
    "iso:country":"IT",
    "sg:address":"37, Via Leonardo Da Vinci 24043 Caravaggio",
    "sg:city":"Caravaggio",
    "sg:orig_category":"Miscellaneous Products",
    "sg:phone":"+39 036 335 0380",
    "sg:postcode":"24043",
    "sg:province":"Bergamo",
    "wof:name":"Pozzi Fratelli (s.r.l.)",
    "wof:placetype":"venue"
},
  "geometry": {"coordinates":[9.5860023499,45.5230064392],"type":"Point"}
}