{
  "type": "Feature",
  "properties": {
    "iso:country":"IT",
    "sg:address":"Via Proventa 130 48018 Faenza",
    "sg:city":"Faenza",
    "sg:classifiers":[
        {
            "category":"Retail",
            "subcategory":"Auto Rental",
            "type":"Services"
        }
    ],
    "sg:phone":"+39 0546 46575",
    "sg:postcode":"48018",
    "sg:province":"Ravenna",
    "sg:tags":[
        "cranes",
        "automobile",
        "crane",
        "salvage",
        "wrecking"
    ],
    "wof:name":"Dms Srl",
    "wof:placetype":"venue"
},
  "geometry": {"coordinates":[11.899097,44.31588],"type":"Point"}
}