{
  "type": "Feature",
  "properties": {
    "iso:country":"IT",
    "sg:address":"Localit\u00e0 Prataroni 01033 Civita Castellana",
    "sg:city":"Civita Castellana",
    "sg:classifiers":[
        {
            "category":"Building & Trades",
            "subcategory":"Plumbing",
            "type":"Services"
        }
    ],
    "sg:phone":"+39 0761 542018",
    "sg:postcode":"01033",
    "sg:province":"Viterbo",
    "sg:tags":[
        "fixture"
    ],
    "sg:website":"www.kerasan.it",
    "wof:name":"Kerasan Srl",
    "wof:placetype":"venue"
},
  "geometry": {"coordinates":[12.1048536301,42.4173812866],"type":"Point"}
}