{
  "type": "Feature",
  "properties": {
    "iso:country":"IT",
    "sg:address":"56122 Pisa",
    "sg:city":"Pisa",
    "sg:orig_category":"Servizi Ausiliari Dei Mezzi Di Trasporto",
    "sg:phone":"+39 050 562203",
    "sg:postcode":"56122",
    "sg:province":"Pisa",
    "wof:name":"Torregas (s.n.c.)",
    "wof:placetype":"venue"
},
  "geometry": {"coordinates":[10.38649,43.731876],"type":"Point"}
}