{
  "type": "Feature",
  "properties": {
    "addr:full":"20132 Milano Milano Milano 20132",
    "addr:postcode":"20132;20132",
    "iso:country":"IT",
    "sg:address":"20132 Milano",
    "sg:city":"Milano",
    "sg:classifiers":[
        {
            "category":"Health Services",
            "subcategory":"Health Practitioner",
            "type":"Services"
        }
    ],
    "sg:phone":"+39 02 215 4739",
    "sg:postcode":"20132",
    "sg:province":"Milano",
    "sg:tags":[
        "medici"
    ],
    "wof:name":"Frosali Laura",
    "wof:placetype":"venue"
},
  "geometry": {"coordinates":[9.237231,45.491287],"type":"Point"}
}