{
  "type": "Feature",
  "properties": {
    "iso:country":"IT",
    "sg:address":"58014 Manciano",
    "sg:city":"Manciano",
    "sg:classifiers":[
        {
            "category":"Travel",
            "subcategory":"Hotels & Motels",
            "type":"Entertainment"
        }
    ],
    "sg:phone":"+39 0564 601182",
    "sg:postcode":"58014",
    "sg:province":"Grosseto",
    "sg:tags":[
        "camping",
        "facility"
    ],
    "wof:name":"Villa Garden Snc",
    "wof:placetype":"venue"
},
  "geometry": {"coordinates":[11.511045,42.67017],"type":"Point"}
}