{
  "type": "Feature",
  "properties": {
    "iso:country":"IT",
    "sg:address":"3/a, V. Macedonia 00179 Roma",
    "sg:city":"Roma",
    "sg:classifiers":[
        {
            "category":"Real Estate",
            "subcategory":"Surveying",
            "type":"Services"
        }
    ],
    "sg:phone":"+39 39067805946",
    "sg:postcode":"00179",
    "sg:province":"Roma",
    "sg:tags":[
        "equipment",
        "material",
        "good",
        "-",
        "handling"
    ],
    "sg:website":"http://www.paginegialle.it/impiantisistemiitalia",
    "wof:name":"Impianti Sistemi Italia",
    "wof:placetype":"venue"
},
  "geometry": {"coordinates":[12.511996,41.873245],"type":"Point"}
}