{
  "type": "Feature",
  "properties": {
    "addr:full":"85100 Potenza Potenza Potenza 85100",
    "addr:postcode":"85100;85100",
    "iso:country":"IT",
    "sg:address":"85100 Potenza",
    "sg:city":"Potenza",
    "sg:orig_category":"Prodotti Di Base E Forniture Per Industria Alimentare E Bevande. Carta, Cartone E Prodotti Primari. Forniture Per Attivita' Commerciali Ed Artigianali",
    "sg:phone":"+39 0971 442750",
    "sg:postcode":"85100",
    "sg:province":"Potenza",
    "wof:name":"Cartoplastica Emmevi Snc",
    "wof:placetype":"venue"
},
  "geometry": {"coordinates":[15.8055467606,40.6464042664],"type":"Point"}
}