{
  "type": "Feature",
  "properties": {
    "iso:country":"IT",
    "sg:address":"16133 Genova",
    "sg:city":"Genova",
    "sg:orig_category":"Trattamenti Termici E Superficiali Metalli, Galvanotecnica",
    "sg:phone":"+39 010 374 2544",
    "sg:postcode":"16133",
    "sg:province":"Genova",
    "wof:name":"Chieppa Antonio",
    "wof:placetype":"venue"
},
  "geometry": {"coordinates":[8.990197,44.411579],"type":"Point"}
}