{
  "type": "Feature",
  "properties": {
    "iso:country":"IT",
    "sg:address":"14034 Castello Di Annone",
    "sg:city":"Castello di Annone",
    "sg:orig_category":"Lavorazioni Meccaniche E Servizi",
    "sg:phone":"+39 0141 401256",
    "sg:postcode":"14034",
    "sg:province":"Asti",
    "sg:website":"http://www.galiziagru.com",
    "wof:name":"Galizia Snc",
    "wof:placetype":"venue"
},
  "geometry": {"coordinates":[8.332096,44.892262],"type":"Point"}
}