{
  "type": "Feature",
  "properties": {
    "addr:full":"98040 Valdina Valdina Messina 98040",
    "addr:postcode":"98040;98040",
    "iso:country":"IT",
    "sg:address":"98040 Valdina",
    "sg:city":"Valdina",
    "sg:orig_category":"Prodotti E Manufatti In Materie Plastiche. Articoli Per Imballaggio E Confezionamento",
    "sg:phone":"+39 090 992 0276",
    "sg:postcode":"98040",
    "sg:province":"Messina",
    "wof:name":"V2s Srl.",
    "wof:placetype":"venue"
},
  "geometry": {"coordinates":[15.360915184,38.2050628662],"type":"Point"}
}