{
  "type": "Feature",
  "properties": {
    "addr:full":"10036 Settimo Torinese Settimo Torinese Torino 10036",
    "addr:postcode":"10036;10036",
    "iso:country":"IT",
    "sg:address":"10036 Settimo Torinese",
    "sg:city":"Settimo Torinese",
    "sg:orig_category":"Motori Ed Organi Di Trasmissione",
    "sg:phone":"+39 011 800 7040",
    "sg:postcode":"10036",
    "sg:province":"Torino",
    "wof:name":"Vibi S.p.a.",
    "wof:placetype":"venue"
},
  "geometry": {"coordinates":[7.7834534645,45.1364974976],"type":"Point"}
}