{
  "type": "Feature",
  "properties": {
    "iso:country":"IT",
    "sg:address":"Via Enrico Fermi 1 20016 Pero",
    "sg:city":"Pero",
    "sg:classifiers":[
        {
            "category":"Taxi",
            "type":"Transportation"
        }
    ],
    "sg:phone":"+39 02 3391 0932",
    "sg:postcode":"20016",
    "sg:province":"Milano",
    "sg:tags":[
        "geared",
        "electric",
        "motor"
    ],
    "sg:website":"www.kenta.it",
    "wof:name":"Kenta Srl",
    "wof:placetype":"venue"
},
  "geometry": {"coordinates":[9.088024,45.503738],"type":"Point"}
}