{
  "type": "Feature",
  "properties": {
    "iso:country":"IT",
    "sg:address":"59100 Prato",
    "sg:city":"Prato",
    "sg:orig_category":"Servizi Ausiliari Di Analisi, Controllo E Ricerca",
    "sg:phone":"+39 0574 639721",
    "sg:postcode":"59100",
    "sg:province":"Prato",
    "wof:name":"T.d.c. Textile Design & Control S.r.l.",
    "wof:placetype":"venue"
},
  "geometry": {"coordinates":[11.076534,43.872814],"type":"Point"}
}