{
  "type": "Feature",
  "properties": {
    "iso:country":"IT",
    "sg:address":"28062 Cameri",
    "sg:city":"Cameri",
    "sg:orig_category":"Forniture Per Edilizia E Lavori Pubblici. Prodotti Vari In Metallo",
    "sg:phone":"+39 0321 518050",
    "sg:postcode":"28062",
    "sg:province":"Novara",
    "wof:name":"Marchetti Fratelli",
    "wof:placetype":"venue"
},
  "geometry": {"coordinates":[8.6619930267,45.4994812012],"type":"Point"}
}