{
  "type": "Feature",
  "properties": {
    "addr:full":"12031 Bagnolo Piemonte Bagnolo Piemonte Cuneo 12031",
    "addr:postcode":"12031;12031",
    "iso:country":"IT",
    "sg:address":"12031 Bagnolo Piemonte",
    "sg:city":"Bagnolo Piemonte",
    "sg:orig_category":"Pubblica Amministrazione",
    "sg:phone":"+39 0175 391121",
    "sg:postcode":"12031",
    "sg:province":"Cuneo",
    "wof:name":"Beriachetto Francesco",
    "wof:placetype":"venue"
},
  "geometry": {"coordinates":[7.27607584,44.7590522766],"type":"Point"}
}