{
  "type": "Feature",
  "properties": {
    "iso:country":"IT",
    "sg:address":"24124 Bergamo",
    "sg:city":"Bergamo",
    "sg:orig_category":"Pittori D'arte E Scenografi - Studi",
    "sg:phone":"+39 035 243196",
    "sg:postcode":"24124",
    "sg:province":"Bergamo",
    "wof:name":"Trovesi Claudia - Blu Lady Snc",
    "wof:placetype":"venue"
},
  "geometry": {"coordinates":[9.6803770065,45.7047615051],"type":"Point"}
}