{
  "type": "Feature",
  "properties": {
    "addr:full":"20092 Cinisello Balsamo Cinisello Balsamo Milano 20092",
    "addr:postcode":"20092;20092",
    "iso:country":"IT",
    "sg:address":"20092 Cinisello Balsamo",
    "sg:city":"Cinisello Balsamo",
    "sg:orig_category":"Pompe",
    "sg:phone":"+39 02 6129 0231",
    "sg:postcode":"20092",
    "sg:province":"Milano",
    "wof:name":"Hawe Italiana (s.r.l.)",
    "wof:placetype":"venue"
},
  "geometry": {"coordinates":[9.2396392822,45.5510978699],"type":"Point"}
}