{
  "type": "Feature",
  "properties": {
    "addr:full":"41012 Carpi Carpi Modena 41012",
    "addr:postcode":"41012;41012",
    "iso:country":"IT",
    "sg:address":"41012 Carpi",
    "sg:city":"Carpi",
    "sg:orig_category":"Abbigliamento Intimo, Calze E Costumi Da Bagno",
    "sg:phone":"+39 059 686210",
    "sg:postcode":"41012",
    "sg:province":"Modena",
    "wof:name":"Ricami N.b.m. Srl",
    "wof:placetype":"venue"
},
  "geometry": {"coordinates":[10.879618,44.801826],"type":"Point"}
}