{
  "type": "Feature",
  "properties": {
    "addr:full":"Via Nazionale 74 33026 Paluzza Paluzza Udine 33026",
    "addr:housenumber":"74",
    "addr:postcode":"33026;33026",
    "addr:street":"Via Nazionale",
    "iso:country":"IT",
    "sg:address":"Via Nazionale 74 33026 Paluzza",
    "sg:city":"Paluzza",
    "sg:classifiers":[
        {
            "category":"Utilities",
            "subcategory":"Mobile Phone",
            "type":"Services"
        }
    ],
    "sg:phone":"+39 0433 775213",
    "sg:postcode":"33026",
    "sg:province":"Udine",
    "sg:tags":[
        "screw",
        "precision"
    ],
    "wof:name":"Viteria Carnica Spa",
    "wof:placetype":"venue"
},
  "geometry": {"coordinates":[13.0056037903,46.581943512],"type":"Point"}
}