{
  "type": "Feature",
  "properties": {
    "iso:country":"IT",
    "sg:address":"Via Briana 8 46020 Bondeno Di Gonzaga",
    "sg:classifiers":[
        {
            "category":"Military Area",
            "subcategory":"Air Force Base",
            "type":"Public Place"
        }
    ],
    "sg:phone":"+39 0376 54534",
    "sg:postcode":"46020",
    "sg:province":"Mantova",
    "sg:tags":[
        "window",
        "skylight",
        "dormer"
    ],
    "sg:website":"www.inlux.it",
    "wof:name":"Inlux S.r.l.",
    "wof:placetype":"venue"
},
  "geometry": {"coordinates":[10.797698,45.160366],"type":"Point"}
}