{
  "type": "Feature",
  "properties": {
    "iso:country":"IT",
    "sg:address":"70123 Bari",
    "sg:city":"Bari",
    "sg:orig_category":"Scuole E Servizi Scolastici. Servizi Per Lo Sport E Il Tempo Libero",
    "sg:phone":"+39 080 574 4778",
    "sg:postcode":"70123",
    "sg:province":"Bari",
    "wof:name":"Autoscuola Universo",
    "wof:placetype":"venue"
},
  "geometry": {"coordinates":[16.847486,41.042629],"type":"Point"}
}