{
  "type": "Feature",
  "properties": {
    "iso:country":"IT",
    "sg:address":"36031 Dueville",
    "sg:city":"Dueville",
    "sg:orig_category":"Macchine E Forniture Per Industria Orafa E Per Orologeria",
    "sg:phone":"+39 0444 595050",
    "sg:postcode":"36031",
    "sg:province":"Vicenza",
    "wof:name":"Gold Stampi Di De Cecchi Stefano & C. Snc",
    "wof:placetype":"venue"
},
  "geometry": {"coordinates":[11.565141,45.611942],"type":"Point"}
}