{
  "type": "Feature",
  "properties": {
    "iso:country":"IT",
    "sg:address":"20090 Opera",
    "sg:city":"Opera",
    "sg:orig_category":"Alimentari - Produzione E Ingrosso",
    "sg:phone":"+39 02 5760 6442",
    "sg:postcode":"20090",
    "sg:province":"Milano",
    "wof:name":"Dc Eurodrinks Srl",
    "wof:placetype":"venue"
},
  "geometry": {"coordinates":[9.225677,45.376812],"type":"Point"}
}