{
  "type": "Feature",
  "properties": {
    "iso:country":"IT",
    "sg:address":"20162 Cusano Milanino",
    "sg:orig_category":"Stampi, Maschere E Ferri Da Trancia",
    "sg:phone":"+39 02 619 8618",
    "sg:postcode":"20162",
    "sg:province":"Milano",
    "wof:name":"Asp Srl",
    "wof:placetype":"venue"
},
  "geometry": {"coordinates":[9.171203,45.554256],"type":"Point"}
}