{
  "type": "Feature",
  "properties": {
    "iso:country":"IT",
    "sg:address":"10156 Torino",
    "sg:city":"Torino",
    "sg:orig_category":"Prodotti Chimici Secondari. Medicinali E Prodotti Parafarmaceutici",
    "sg:phone":"+39 011 273 1702",
    "sg:postcode":"10156",
    "sg:province":"Torino",
    "wof:name":"Teknofarma Spa",
    "wof:placetype":"venue"
},
  "geometry": {"coordinates":[7.3837041855,44.779335022],"type":"Point"}
}