{
  "type": "Feature",
  "properties": {
    "addr:full":"Via Verdi 6, 20121 Milan, Mi Milano 20121",
    "addr:housenumber":"6",
    "addr:postcode":"20121;20121",
    "addr:street":"Via Verdi",
    "iso:country":"IT",
    "sg:address":"Via Verdi 6, 20121 Milan, Mi",
    "sg:classifiers":[
        {
            "category":"Banks & Credit Unions",
            "subcategory":"Bank",
            "type":"Services"
        }
    ],
    "sg:postcode":"20121",
    "sg:province":"Milano",
    "wof:name":"Mercato Impresa Spa",
    "wof:placetype":"venue"
},
  "geometry": {"coordinates":[9.188983,45.468163],"type":"Point"}
}