{
  "type": "Feature",
  "properties": {
    "iso:country":"IT",
    "sg:address":"2/a, Via S.andrea 40050 Castello D'argile",
    "sg:classifiers":[
        {
            "category":"Wholesale",
            "subcategory":"Machinery & Supplies",
            "type":"Manufacturing & Wholesale Goods"
        }
    ],
    "sg:phone":"+39 051 686 7276",
    "sg:postcode":"40050",
    "sg:province":"Bologna",
    "sg:tags":[
        "-",
        "agriculture",
        "equipment"
    ],
    "wof:name":"Orsi Group S.r.l.",
    "wof:placetype":"venue"
},
  "geometry": {"coordinates":[11.346481,44.494221],"type":"Point"}
}