{
  "type": "Feature",
  "properties": {
    "iso:country":"IT",
    "sg:address":"60027 Osimo",
    "sg:city":"Osimo",
    "sg:orig_category":"Apparecchiature E Sistemi Per Magazzinaggio E Movimentazione",
    "sg:phone":"+39 071 710 8660",
    "sg:postcode":"60027",
    "sg:province":"Ancona",
    "wof:name":"Metalsistem Marche Srl",
    "wof:placetype":"venue"
},
  "geometry": {"coordinates":[13.520082,43.574718],"type":"Point"}
}