{
  "type": "Feature",
  "properties": {
    "iso:country":"IT",
    "sg:address":"24126 Bergamo",
    "sg:city":"Bergamo",
    "sg:classifiers":[
        {
            "category":"Health Services",
            "subcategory":"Health Practitioner",
            "type":"Services"
        }
    ],
    "sg:phone":"+39 035 315210",
    "sg:postcode":"24126",
    "sg:province":"Bergamo",
    "sg:tags":[
        "medici"
    ],
    "wof:name":"Rovaris Elena",
    "wof:placetype":"venue"
},
  "geometry": {"coordinates":[9.656867981,45.6731643677],"type":"Point"}
}