{
  "type": "Feature",
  "properties": {
    "addr:full":"41100 Modena Modena Modena 41100",
    "addr:postcode":"41100;41100",
    "iso:country":"IT",
    "sg:address":"41100 Modena",
    "sg:city":"Modena",
    "sg:orig_category":"Imprese Di Costruzioni Civili Ed Industriali",
    "sg:phone":"+39 059 234544",
    "sg:postcode":"41100",
    "sg:province":"Modena",
    "wof:name":"Logickomm S.r.l.",
    "wof:placetype":"venue"
},
  "geometry": {"coordinates":[10.935596,44.551308],"type":"Point"}
}