{
  "type": "Feature",
  "properties": {
    "iso:country":"IT",
    "sg:address":"2, Localita' Palude Di Caldaro 39052 Caldaro Sulla Strada Del Vino",
    "sg:city":"Caldaro sulla strada del vino",
    "sg:classifiers":[
        {
            "category":"Farming",
            "subcategory":"Livestock Farm",
            "type":"Manufacturing & Wholesale Goods"
        }
    ],
    "sg:phone":"+39 0471 810206",
    "sg:postcode":"39052",
    "sg:province":"Bolzano/Bozen",
    "sg:tags":[
        "agriculture"
    ],
    "wof:name":"Consorzio Frutticoltori Caldar0 (soc.coop.r.l.)",
    "wof:placetype":"venue"
},
  "geometry": {"coordinates":[11.358005,46.496716],"type":"Point"}
}