{
  "type": "Feature",
  "properties": {
    "addr:full":"70125 Bari Bari Bari 70125",
    "addr:postcode":"70125;70125",
    "iso:country":"IT",
    "sg:address":"70125 Bari",
    "sg:city":"Bari",
    "sg:orig_category":"Frigotecnica, Apparecchiature E Servizi. Forniture Alle Strutture Ricettive",
    "sg:phone":"+39 080 501 4400",
    "sg:postcode":"70125",
    "sg:province":"Bari",
    "wof:name":"S.a.r.e. Di Michele Tavani",
    "wof:placetype":"venue"
},
  "geometry": {"coordinates":[16.8734874725,41.0937843323],"type":"Point"}
}