{
  "type": "Feature",
  "properties": {
    "addr:full":"06063 Magione Magione Perugia 06063",
    "addr:postcode":"06063;06063",
    "iso:country":"IT",
    "sg:address":"06063 Magione",
    "sg:city":"Magione",
    "sg:orig_category":"Arredamenti E Mobili Professionali. Impianti, Attrezzature E Forniture Sanitarie Ed Ospedaliere",
    "sg:phone":"+39 075 847 9241",
    "sg:postcode":"06063",
    "sg:province":"Perugia",
    "wof:name":"Mobili Gied Snc",
    "wof:placetype":"venue"
},
  "geometry": {"coordinates":[12.166295,43.118057],"type":"Point"}
}