{
  "type": "Feature",
  "properties": {
    "iso:country":"IT",
    "sg:address":"Via Bellini 27 63014 Montegranaro",
    "sg:city":"Montegranaro",
    "sg:classifiers":[
        {
            "category":"Shopping",
            "subcategory":"Shoes",
            "type":"Retail Goods"
        }
    ],
    "sg:phone":"+39 0734 890175",
    "sg:postcode":"63014",
    "sg:province":"Ascoli Piceno",
    "sg:tags":[
        "men's",
        "boot"
    ],
    "sg:website":"www.bavierasrl.it",
    "wof:name":"Calzaturificio Baviera Srl",
    "wof:placetype":"venue"
},
  "geometry": {"coordinates":[13.6278896332,43.2316207886],"type":"Point"}
}