{
  "type": "Feature",
  "properties": {
    "iso:country":"IT",
    "sg:address":"21058 Solbiate Olona",
    "sg:city":"Solbiate Olona",
    "sg:orig_category":"Materie Plastiche Lavorazione - Macchine",
    "sg:phone":"+39 0331 649012",
    "sg:postcode":"21058",
    "sg:province":"Varese",
    "sg:website":"http://www.saldoflex.com",
    "wof:name":"Filippini & Paganini Srl",
    "wof:placetype":"venue"
},
  "geometry": {"coordinates":[8.87587,45.649384],"type":"Point"}
}