{
  "type": "Feature",
  "properties": {
    "iso:country":"IT",
    "sg:address":"40055 Castenaso",
    "sg:city":"Castenaso",
    "sg:orig_category":"Vetro: Prodotti E Lavorazioni. Forniture Industriali Per Prevenzione, Controllo E Sicurezza",
    "sg:phone":"+39 051 782226",
    "sg:postcode":"40055",
    "sg:province":"Bologna",
    "wof:name":"Tecno Securvetro Srl",
    "wof:placetype":"venue"
},
  "geometry": {"coordinates":[11.424398,44.496647],"type":"Point"}
}