{
  "type": "Feature",
  "properties": {
    "addr:full":"30, Via Macchi Giovanni 21100 Varese Varese Varese 21100",
    "addr:postcode":"21100;21100",
    "addr:street":"Via Macchi Giovanni",
    "iso:country":"IT",
    "sg:address":"30, Via Macchi Giovanni 21100 Varese",
    "sg:city":"Varese",
    "sg:classifiers":[
        {
            "category":"Manufacturing",
            "subcategory":"Rubber & Plastics",
            "type":"Manufacturing & Wholesale Goods"
        }
    ],
    "sg:phone":"+39 0332 310100",
    "sg:postcode":"21100",
    "sg:province":"Varese",
    "wof:name":"Sandro Mentasti (s.r.l.)",
    "wof:placetype":"venue"
},
  "geometry": {"coordinates":[8.8263845444,45.8176040649],"type":"Point"}
}