{
  "type": "Feature",
  "properties": {
    "addr:full":"00183 Roma Roma Roma 00183",
    "addr:postcode":"00183;00183",
    "iso:country":"IT",
    "sg:address":"00183 Roma",
    "sg:city":"Roma",
    "sg:orig_category":"Pubblica Amministrazione",
    "sg:phone":"+39 06 7047 4246",
    "sg:postcode":"00183",
    "sg:province":"Roma",
    "wof:name":"Comando Della Capitale",
    "wof:placetype":"venue"
},
  "geometry": {"coordinates":[12.5082931519,41.879524231],"type":"Point"}
}