{
  "type": "Feature",
  "properties": {
    "addr:full":"Via Dei Pizzi 14 25020 Azzano Mella Azzano Mella Brescia 25020",
    "addr:housenumber":"14",
    "addr:postcode":"25020;mella;25020",
    "addr:street":"Via Dei Pizzi",
    "iso:country":"IT",
    "sg:address":"Via Dei Pizzi 14 25020 Azzano Mella",
    "sg:city":"Azzano Mella",
    "sg:classifiers":[
        {
            "category":"Wholesale",
            "subcategory":"Farm Supplies",
            "type":"Manufacturing & Wholesale Goods"
        }
    ],
    "sg:phone":"+39 030 974 7370",
    "sg:postcode":"25020",
    "sg:province":"Brescia",
    "sg:tags":[
        "agricultural",
        "part",
        "spare",
        "machinery",
        "accessory"
    ],
    "wof:name":"Erregibi Di Bonomi Gianmaria & C. Sas",
    "wof:placetype":"venue"
},
  "geometry": {"coordinates":[10.114919,45.455978],"type":"Point"}
}