{
  "type": "Feature",
  "properties": {
    "iso:country":"IT",
    "sg:address":"10056 Oulx",
    "sg:city":"Oulx",
    "sg:orig_category":"Pubblica Amministrazione",
    "sg:phone":"+39 0122 830805",
    "sg:postcode":"10056",
    "sg:province":"Torino",
    "wof:name":"Comunita' Montana Alta Valle Susa",
    "wof:placetype":"venue"
},
  "geometry": {"coordinates":[7.6500520706,45.0649719238],"type":"Point"}
}