{
  "type": "Feature",
  "properties": {
    "iso:country":"IT",
    "sg:address":"Via 4 Novembre 38 23842 Bosisio Parini",
    "sg:city":"Bosisio Parini",
    "sg:classifiers":[
        {
            "category":"Manufacturing",
            "subcategory":"Metals",
            "type":"Manufacturing & Wholesale Goods"
        }
    ],
    "sg:phone":"+39 031 866435",
    "sg:postcode":"23842",
    "sg:province":"Lecco",
    "sg:tags":[
        "machine",
        "cut-off"
    ],
    "wof:name":"Par Met Srl",
    "wof:placetype":"venue"
},
  "geometry": {"coordinates":[9.2928142548,45.8019752502],"type":"Point"}
}