{
  "type": "Feature",
  "properties": {
    "iso:country":"IT",
    "sg:address":"17031 Albenga",
    "sg:city":"Albenga",
    "sg:orig_category":"Acquari Ornamentali Ed Accessori",
    "sg:phone":"+39 0182 555797",
    "sg:postcode":"17031",
    "sg:province":"Savona",
    "wof:name":"Acquanimando",
    "wof:placetype":"venue"
},
  "geometry": {"coordinates":[8.213237,44.053246],"type":"Point"}
}