{
  "type": "Feature",
  "properties": {
    "iso:country":"IT",
    "sg:address":"81100 Caserta",
    "sg:city":"Caserta",
    "sg:orig_category":"Cine-foto-ottica",
    "sg:phone":"+39 0823 361457",
    "sg:postcode":"81100",
    "sg:province":"Caserta",
    "wof:name":"Cristillo Bruno",
    "wof:placetype":"venue"
},
  "geometry": {"coordinates":[14.316046,41.098701],"type":"Point"}
}