{
  "type": "Feature",
  "properties": {
    "addr:full":"21, Via Nazionale 47017 Rocca San Casciano Rocca San Casciano Forl\u00ec-Cesena 47017",
    "addr:postcode":"47017;47017",
    "addr:street":"Via Nazionale;Forli\u0300-Cesena",
    "iso:country":"IT",
    "sg:address":"21, Via Nazionale 47017 Rocca San Casciano",
    "sg:city":"Rocca San Casciano",
    "sg:classifiers":[
        {
            "category":"Professional",
            "subcategory":"Engineering",
            "type":"Services"
        }
    ],
    "sg:phone":"+39 0543 960396",
    "sg:postcode":"47017",
    "sg:province":"Forl\u00ec-Cesena",
    "sg:tags":[
        "machine",
        "-",
        "mechanical"
    ],
    "wof:name":"Art Campenter Srl",
    "wof:placetype":"venue"
},
  "geometry": {"coordinates":[11.824059,44.048218],"type":"Point"}
}