{
  "type": "Feature",
  "properties": {
    "iso:country":"IT",
    "sg:address":"23890 Barzago",
    "sg:city":"Barzago",
    "sg:orig_category":"Attrezzature E Forniture Per Officine Riparazione E Servizi Ausiliari",
    "sg:phone":"+39 031 860976",
    "sg:postcode":"23890",
    "sg:province":"Lecco",
    "wof:name":"Mirkag S.n.c.",
    "wof:placetype":"venue"
},
  "geometry": {"coordinates":[9.387154,45.850735],"type":"Point"}
}