{
  "type": "Feature",
  "properties": {
    "addr:full":"50129 Firenze Firenze Firenze 50129",
    "addr:postcode":"50129;50129",
    "iso:country":"IT",
    "sg:address":"50129 Firenze",
    "sg:city":"Firenze",
    "sg:orig_category":"Agenzie Investigative",
    "sg:phone":"+39 055 283539",
    "sg:postcode":"50129",
    "sg:province":"Firenze",
    "sg:website":"http://www.investigativa.it",
    "wof:name":"L'investigativa",
    "wof:placetype":"venue"
},
  "geometry": {"coordinates":[11.255481,43.773712],"type":"Point"}
}