{
  "type": "Feature",
  "properties": {
    "iso:country":"IT",
    "sg:address":"16043 Chiavari",
    "sg:city":"Chiavari",
    "sg:orig_category":"Agenzie D'affari E Servizi Commerciali. Acqua, Luce, Gas E Societa' Di Esercizio Pubblico",
    "sg:phone":"+39 0185 303044",
    "sg:postcode":"16043",
    "sg:province":"Genova",
    "wof:name":"Casa Delle Aste",
    "wof:placetype":"venue"
},
  "geometry": {"coordinates":[9.32078,44.314911],"type":"Point"}
}