{
  "type": "Feature",
  "properties": {
    "addr:full":"55041 Camaiore Camaiore Lucca 55041",
    "addr:postcode":"55041;55041",
    "iso:country":"IT",
    "sg:address":"55041 Camaiore",
    "sg:city":"Camaiore",
    "sg:classifiers":[
        {
            "category":"Communications",
            "subcategory":"Film & Video Production",
            "type":"Services"
        }
    ],
    "sg:phone":"+39 0584 915442",
    "sg:postcode":"55041",
    "sg:province":"Lucca",
    "sg:tags":[
        "cracker",
        "e",
        "biscotti"
    ],
    "sg:website":"http://www.artebianca.com",
    "wof:name":"Arte Bianca Natura E Tradizione Srl",
    "wof:placetype":"venue"
},
  "geometry": {"coordinates":[10.248645,43.939754],"type":"Point"}
}