{
  "type": "Feature",
  "properties": {
    "addr:full":"Via Del Colle 101 50041 Calenzano Calenzano Firenze 50041",
    "addr:housenumber":"101",
    "addr:postcode":"50041;50041",
    "addr:street":"Via Del Colle",
    "iso:country":"IT",
    "sg:address":"Via Del Colle 101 50041 Calenzano",
    "sg:city":"Calenzano",
    "sg:orig_category":"Fuses",
    "sg:phone":"+39 055 882 6257",
    "sg:postcode":"50041",
    "sg:province":"Firenze",
    "sg:website":"www.italquartz.it",
    "wof:name":"Italquartz S.r.l.",
    "wof:placetype":"venue"
},
  "geometry": {"coordinates":[10.7479085922,43.8607368469],"type":"Point"}
}