{
  "type": "Feature",
  "properties": {
    "addr:full":"50059 Vinci Sovigliana Firenze 50059",
    "addr:postcode":"50059;50059",
    "addr:street":"Sovigliana",
    "iso:country":"IT",
    "sg:address":"50059 Vinci",
    "sg:city":"Sovigliana",
    "sg:orig_category":"Filati E Materie Prime Tessili",
    "sg:phone":"+39 0571 902085",
    "sg:postcode":"50059",
    "sg:province":"Firenze",
    "sg:website":"http://www.piantini.com",
    "wof:name":"Piantini Srl",
    "wof:placetype":"venue"
},
  "geometry": {"coordinates":[10.9346227646,43.7285995483],"type":"Point"}
}