{
  "type": "Feature",
  "properties": {
    "addr:full":"30124 Venezia Venezia Venezia 30124",
    "addr:postcode":"30124;30124",
    "iso:country":"IT",
    "sg:address":"30124 Venezia",
    "sg:city":"Venezia",
    "sg:orig_category":"Accessori Moda D'abbigliamento. Forniture Per Abbigliamento E Pelletterie",
    "sg:phone":"+39 041 520 4433",
    "sg:postcode":"30124",
    "sg:province":"Venezia",
    "wof:name":"Tokatzian",
    "wof:placetype":"venue"
},
  "geometry": {"coordinates":[12.33929,45.433727],"type":"Point"}
}