{
  "type": "Feature",
  "properties": {
    "iso:country":"IT",
    "sg:address":"16126 Genova",
    "sg:city":"Genova",
    "sg:orig_category":"Scuole E Servizi Scolastici. Ricerca, Selezione E Formazione Del Personale. Pubblica Amministrazione",
    "sg:phone":"+39 010 20991",
    "sg:postcode":"16126",
    "sg:province":"Genova",
    "sg:website":"http://www.unige.it",
    "wof:name":"Universita' Degli Studi Di Genova",
    "wof:placetype":"venue"
},
  "geometry": {"coordinates":[8.888069,44.967991],"type":"Point"}
}