{
  "type": "Feature",
  "properties": {
    "iso:country":"IT",
    "sg:address":"55011 Altopascio",
    "sg:city":"Altopascio",
    "sg:orig_category":"Servizi E Lavori Per Ecologia E Smaltimento Rifiuti. Servizi Ausiliari Di Analisi, Controllo E Ricerca",
    "sg:phone":"+39 0589 20484",
    "sg:postcode":"55011",
    "sg:province":"Lucca",
    "sg:website":"http://www.delca.it",
    "wof:name":"Del.ca. Srl",
    "wof:placetype":"venue"
},
  "geometry": {"coordinates":[10.685217,43.812222],"type":"Point"}
}