{
  "type": "Feature",
  "properties": {
    "addr:full":"41100 Modena Modena Modena 41100",
    "addr:postcode":"41100;41100",
    "iso:country":"IT",
    "sg:address":"41100 Modena",
    "sg:city":"Modena",
    "sg:orig_category":"Vetro: Prodotti E Lavorazioni. Forniture Industriali Per Prevenzione, Controllo E Sicurezza",
    "sg:phone":"+39 059 284675",
    "sg:postcode":"41100",
    "sg:province":"Modena",
    "wof:name":"Vetreria Formiginese Srl",
    "wof:placetype":"venue"
},
  "geometry": {"coordinates":[10.963806,44.628319],"type":"Point"}
}