{
  "type": "Feature",
  "properties": {
    "iso:country":"IT",
    "sg:address":"Via Repubblica 8 24060 Castelli Calepio",
    "sg:city":"Castelli Calepio",
    "sg:classifiers":[
        {
            "category":"Real Estate",
            "subcategory":"Real Estate Services",
            "type":"Services"
        }
    ],
    "sg:phone":"+39 030 743 8893",
    "sg:postcode":"24060",
    "sg:province":"Bergamo",
    "sg:tags":[
        "leather",
        "belt"
    ],
    "sg:website":"www.pelletterie2f.it",
    "wof:name":"Pelletterie 2f Spa",
    "wof:placetype":"venue"
},
  "geometry": {"coordinates":[9.669952,45.694904],"type":"Point"}
}