{
  "type": "Feature",
  "properties": {
    "iso:country":"IT",
    "sg:address":"77/1, Via Torino 10040 Druento",
    "sg:city":"Druento",
    "sg:classifiers":[
        {
            "category":"Autos & Motor Vehicles",
            "subcategory":"Automobile Sales",
            "type":"Retail Goods"
        }
    ],
    "sg:phone":"+39 011 984 6501",
    "sg:postcode":"10040",
    "sg:province":"Torino",
    "sg:tags":[
        "industrial"
    ],
    "wof:name":"Lar (s.p.a.)",
    "wof:placetype":"venue"
},
  "geometry": {"coordinates":[7.590741,45.124733],"type":"Point"}
}