{
  "type": "Feature",
  "properties": {
    "addr:full":"33, Via Guglielmo Marconi 46018 Sabbioneta Sabbioneta Mantova 46018",
    "addr:postcode":"46018;46018",
    "addr:street":"Via Guglielmo Marconi",
    "iso:country":"IT",
    "sg:address":"33, Via Guglielmo Marconi 46018 Sabbioneta",
    "sg:city":"Sabbioneta",
    "sg:classifiers":[
        {
            "category":"Real Estate",
            "subcategory":"Surveying",
            "type":"Services"
        }
    ],
    "sg:phone":"+39 0375 254819",
    "sg:postcode":"46018",
    "sg:province":"Mantova",
    "sg:tags":[
        "equipment",
        "material",
        "good",
        "-",
        "handling"
    ],
    "wof:name":"Hs. Marine S.r.l.",
    "wof:placetype":"venue"
},
  "geometry": {"coordinates":[10.53464,45.026073],"type":"Point"}
}