{
  "type": "Feature",
  "properties": {
    "iso:country":"IT",
    "sg:address":"40129 Bologna",
    "sg:city":"Bologna",
    "sg:orig_category":"Raccorderie E Valvole Per Industrie Varie",
    "sg:phone":"+39 051 320457",
    "sg:postcode":"40129",
    "sg:province":"Bologna",
    "wof:name":"Tomaso Ferrario 1885 Snc Di Marina E Mario Monti",
    "wof:placetype":"venue"
},
  "geometry": {"coordinates":[11.351158,44.537628],"type":"Point"}
}