{
  "type": "Feature",
  "properties": {
    "iso:country":"IT",
    "sg:address":"16133 Genova",
    "sg:city":"Genova",
    "sg:classifiers":[
        {
            "category":"Shopping",
            "subcategory":"Bicycles & Sporting Goods",
            "type":"Retail Goods"
        }
    ],
    "sg:phone":"+39 010 396329",
    "sg:postcode":"16133",
    "sg:province":"Genova",
    "sg:tags":[
        "tempo",
        "lo",
        "-",
        "libero",
        "per",
        "servizi",
        "forniture",
        "articoli",
        "e",
        "sport",
        "il"
    ],
    "wof:name":"3 T Sub Di Turri Claudio",
    "wof:placetype":"venue"
},
  "geometry": {"coordinates":[8.98797,44.401794],"type":"Point"}
}