{
  "type": "Feature",
  "properties": {
    "addr:full":"Via Carlo Goldoni, 21/23 20090 Trezzano Sul Naviglio Trezzano sul Naviglio Milano 20090",
    "addr:housenumber":"21 / 23",
    "addr:postcode":"20090;20090",
    "addr:street":"Via Carlo Goldoni",
    "iso:country":"IT",
    "sg:address":"Via Carlo Goldoni, 21/23 20090 Trezzano Sul Naviglio",
    "sg:city":"Trezzano sul Naviglio",
    "sg:classifiers":[
        {
            "category":"Autos & Motor Vehicles",
            "subcategory":"Auto Supplies",
            "type":"Retail Goods"
        }
    ],
    "sg:phone":"+39 02 484371",
    "sg:postcode":"20090",
    "sg:province":"Milano",
    "sg:tags":[
        "automobile",
        "part",
        "spare"
    ],
    "sg:website":"www.electrocar.it",
    "wof:name":"Electrocar Spa",
    "wof:placetype":"venue"
},
  "geometry": {"coordinates":[9.070072,45.429657],"type":"Point"}
}