{
  "type": "Feature",
  "properties": {
    "iso:country":"IT",
    "sg:address":"22100 Como",
    "sg:city":"Como",
    "sg:orig_category":"Servizi E Lavori Per Abbigliamento E Pelletterie",
    "sg:phone":"+39 031 268391",
    "sg:postcode":"22100",
    "sg:province":"Como",
    "wof:name":"Al-over Designs Di Coppola E Peverelli & Co S.n.c.",
    "wof:placetype":"venue"
},
  "geometry": {"coordinates":[9.080854,45.804672],"type":"Point"}
}