{
  "type": "Feature",
  "properties": {
    "iso:country":"IT",
    "sg:address":"44100 Ferrara",
    "sg:city":"Ferrara",
    "sg:orig_category":"Elaborazione Dati - Servizio Conto Terzi",
    "sg:phone":"+39 0532 900989",
    "sg:postcode":"44100",
    "sg:province":"Ferrara",
    "wof:name":"Centro Elaborazione Dati Sas",
    "wof:placetype":"venue"
},
  "geometry": {"coordinates":[11.606179,44.820396],"type":"Point"}
}