{
  "type": "Feature",
  "properties": {
    "addr:full":"Via Salceto 53, 53038 Poggibonsi, Si",
    "addr:housenumber":"53",
    "addr:postcode":"53038",
    "addr:street":"Via Salceto",
    "iso:country":"IT",
    "sg:address":"Via Salceto 53, 53038 Poggibonsi, Si",
    "sg:classifiers":[
        {
            "category":"Banks & Credit Unions",
            "subcategory":"Bank",
            "type":"Services"
        }
    ],
    "sg:phone":"+39 0577 9931",
    "wof:name":"Saped Servizi Spa",
    "wof:placetype":"venue"
},
  "geometry": {"coordinates":[11.153508,43.467922],"type":"Point"}
}