{
  "type": "Feature",
  "properties": {
    "addr:full":"12, Via Figino Ambrogio 20156 Milano Milano Milano 20156",
    "addr:postcode":"20156;20156",
    "addr:street":"Via Figino Ambrogio",
    "iso:country":"IT",
    "sg:address":"12, Via Figino Ambrogio 20156 Milano",
    "sg:city":"Milano",
    "sg:classifiers":[
        {
            "category":"Autos & Motor Vehicles",
            "subcategory":"Automobile Sales",
            "type":"Retail Goods"
        }
    ],
    "sg:phone":"+39 390 232 4441",
    "sg:postcode":"20156",
    "sg:province":"Milano",
    "sg:tags":[
        "industrial"
    ],
    "wof:name":"Krautli Italia Srl",
    "wof:placetype":"venue"
},
  "geometry": {"coordinates":[9.203226,45.482468],"type":"Point"}
}