{
  "type": "Feature",
  "properties": {
    "addr:full":"72, Via Aiaccia - Stagno 57014 Collesalvetti Collesalvetti Livorno 57014",
    "addr:postcode":"57014;57014",
    "addr:street":"Via Aiaccia",
    "iso:country":"IT",
    "sg:address":"72, Via Aiaccia - Stagno 57014 Collesalvetti",
    "sg:city":"Collesalvetti",
    "sg:classifiers":[
        {
            "category":"Manufacturing",
            "subcategory":"Lumber",
            "type":"Manufacturing & Wholesale Goods"
        }
    ],
    "sg:phone":"+39 0586 943440",
    "sg:postcode":"57014",
    "sg:province":"Livorno",
    "sg:tags":[
        "wood"
    ],
    "wof:name":"I.f.a. Industria Fusti Acciaio (s.p.a.)",
    "wof:placetype":"venue"
},
  "geometry": {"coordinates":[10.356906,43.581123],"type":"Point"}
}