{
  "type": "Feature",
  "properties": {
    "iso:country":"IT",
    "sg:address":"90139 Palermo",
    "sg:city":"Palermo",
    "sg:orig_category":"Prodotti Finiti Stampati. Forniture E Prodotti Informatici. Forniture Per Uffici",
    "sg:phone":"+39 091 581254",
    "sg:postcode":"90139",
    "sg:province":"Palermo",
    "sg:website":"http://www.lasiculcarta.it",
    "wof:name":"La Siculcarta Spa",
    "wof:placetype":"venue"
},
  "geometry": {"coordinates":[13.3589925766,38.1285324097],"type":"Point"}
}