{
  "type": "Feature",
  "properties": {
    "iso:country":"IT",
    "sg:address":"25010 Borgosatollo",
    "sg:city":"Borgosatollo",
    "sg:orig_category":"Valvole E Apparecchiature Di Misura. Elettrotecnica Industriale, Prodotti E Apparecchiature",
    "sg:phone":"+39 030 250 0992",
    "sg:postcode":"25010",
    "sg:province":"Brescia",
    "wof:name":"Contermo Pontina Di Grossi Giuseppina & C. (s.n.c.)",
    "wof:placetype":"venue"
},
  "geometry": {"coordinates":[10.244226,45.474648],"type":"Point"}
}