{
  "type": "Feature",
  "properties": {
    "iso:country":"IT",
    "sg:address":"20078 San Colombano Al Lambro",
    "sg:city":"San Colombano al Lambro",
    "sg:orig_category":"Manufacturers: Prefabbricati. Forniture Per Edilizia E Lavori Pubblici",
    "sg:phone":"+39 0371 89055",
    "sg:postcode":"20078",
    "sg:province":"Milano",
    "wof:name":"Futurtek Srl - Divisione Recinzioni",
    "wof:placetype":"venue"
},
  "geometry": {"coordinates":[9.489183,45.172993],"type":"Point"}
}