{
  "type": "Feature",
  "properties": {
    "iso:country":"IT",
    "sg:address":"10141 Torino",
    "sg:city":"Torino",
    "sg:orig_category":"Antenne Radio-televisione",
    "sg:phone":"+39 011 772 4193",
    "sg:postcode":"10141",
    "sg:province":"Torino",
    "wof:name":"Gaatel Di Roda Rosella",
    "wof:placetype":"venue"
},
  "geometry": {"coordinates":[7.619533,45.069187],"type":"Point"}
}