{
  "type": "Feature",
  "properties": {
    "iso:country":"IT",
    "sg:address":"47100 Forli'",
    "sg:orig_category":"Legno Lavorazione Macchine - Produzione",
    "sg:phone":"+39 0543 63232",
    "sg:postcode":"47100",
    "sg:province":"Forl\u00ec-Cesena",
    "wof:name":"Alfamacchine Srl",
    "wof:placetype":"venue"
},
  "geometry": {"coordinates":[12.063612,44.220013],"type":"Point"}
}