{
  "type": "Feature",
  "properties": {
    "addr:full":"50142 Firenze Firenze Firenze 50142",
    "addr:postcode":"50142;50142",
    "iso:country":"IT",
    "sg:address":"50142 Firenze",
    "sg:city":"Firenze",
    "sg:orig_category":"Audiovisivi Apparecchi Ed Impianti - Produzione, Commercio E Noleggio",
    "sg:phone":"+39 055 737 4711",
    "sg:postcode":"50142",
    "sg:province":"Firenze",
    "sg:website":"http://www.natali.it",
    "wof:name":"Natali Multimedia Srl",
    "wof:placetype":"venue"
},
  "geometry": {"coordinates":[10.747925,43.67762],"type":"Point"}
}