{
  "type": "Feature",
  "properties": {
    "iso:country":"IT",
    "sg:address":"31016 Cordignano",
    "sg:city":"Cordignano",
    "sg:orig_category":"Servizi E Lavori Per Edilizia E Lavori Pubblici. Consulenze Tecniche, Amministrative E Perizie",
    "sg:phone":"+39 0438 995300",
    "sg:postcode":"31016",
    "sg:province":"Treviso",
    "wof:name":"Bit Spa",
    "wof:placetype":"venue"
},
  "geometry": {"coordinates":[12.410247,45.947201],"type":"Point"}
}