{
  "type": "Feature",
  "properties": {
    "addr:full":"7/a, Via Bartolomeo Colleoni 24040 Boltiere Boltiere Bergamo 24040",
    "addr:housenumber":"7 / a",
    "addr:postcode":"24040;24040",
    "addr:street":"Via Bartolomeo Colleoni",
    "iso:country":"IT",
    "sg:address":"7/a, Via Bartolomeo Colleoni 24040 Boltiere",
    "sg:city":"Boltiere",
    "sg:classifiers":[
        {
            "category":"Manufacturing",
            "subcategory":"Metals",
            "type":"Manufacturing & Wholesale Goods"
        }
    ],
    "sg:phone":"+39 035 487 6051",
    "sg:postcode":"24040",
    "sg:province":"Bergamo",
    "sg:tags":[
        "processing"
    ],
    "wof:name":"Tibermec (s.p.a.)",
    "wof:placetype":"venue"
},
  "geometry": {"coordinates":[9.6699523926,45.6949043274],"type":"Point"}
}