{
  "type": "Feature",
  "properties": {
    "addr:full":"80067 Sorrento Sorrento Napoli 80067",
    "addr:housenumber":"80067",
    "addr:postcode":"80067",
    "addr:street":"Sorrento Sorrento Napoli",
    "iso:country":"IT",
    "sg:address":"80067 Sorrento",
    "sg:city":"Sorrento",
    "sg:orig_category":"Forniture Per Congressi, Fiere E Manifestazioni",
    "sg:phone":"+39 081 877 3263",
    "sg:postcode":"80067",
    "sg:province":"Napoli",
    "wof:name":"Circolo Dei Forestieri",
    "wof:placetype":"venue"
},
  "geometry": {"coordinates":[14.3743906021,40.6274185181],"type":"Point"}
}