{
  "type": "Feature",
  "properties": {
    "iso:country":"IT",
    "sg:address":"50145 Firenze",
    "sg:city":"Firenze",
    "sg:orig_category":"Servizi Di Magazzinaggio E Movimentazione. Servizi Ausiliari Di Sorveglianza, Manutenzione E Pulizia",
    "sg:phone":"+39 055 30431",
    "sg:postcode":"50145",
    "sg:province":"Firenze",
    "sg:website":"http://www.gruppo-caf.it",
    "wof:name":"C.a.f. Cooperativa Autotrasporti Fiorentini",
    "wof:placetype":"venue"
},
  "geometry": {"coordinates":[11.192209,43.800419],"type":"Point"}
}