{
  "type": "Feature",
  "properties": {
    "iso:country":"IT",
    "sg:address":"Piazza Botero 7, 12041 Bene Vagienna, Cn",
    "sg:city":"Bene Vagienna",
    "sg:classifiers":[
        {
            "category":"Banks & Credit Unions",
            "subcategory":"Bank",
            "type":"Services"
        }
    ],
    "sg:postcode":"12041",
    "sg:province":"Cuneo",
    "wof:name":"Banca Di Credito Cooperativo Di Bene Vagienna (cuneo)",
    "wof:placetype":"venue"
},
  "geometry": {"coordinates":[7.833081,44.54575],"type":"Point"}
}