{
  "type": "Feature",
  "properties": {
    "iso:country":"IT",
    "sg:address":"20093 Cologno Monzese",
    "sg:city":"Cologno Monzese",
    "sg:orig_category":"Macchine, Impianti Ed Attrezzature Per Industria Alimentare E Bevande. Apparecchiature E Sistemi Per Imballaggio E Confezionamento",
    "sg:phone":"+39 02 254 1730",
    "sg:postcode":"20093",
    "sg:province":"Milano",
    "wof:name":"Ocim Srl",
    "wof:placetype":"venue"
},
  "geometry": {"coordinates":[9.267355,45.52404],"type":"Point"}
}