{
  "type": "Feature",
  "properties": {
    "iso:country":"IT",
    "sg:address":"Via Colleoni 5/c 24060 Cividino",
    "sg:city":"Cividino",
    "sg:orig_category":"Valve Packings Of Graphite",
    "sg:phone":"+39 030 743 5465",
    "sg:postcode":"24060",
    "sg:province":"Bergamo",
    "wof:name":"Gasket International Spa",
    "wof:placetype":"venue"
},
  "geometry": {"coordinates":[9.851415,45.6301],"type":"Point"}
}