{
  "type": "Feature",
  "properties": {
    "iso:country":"IT",
    "sg:address":"70043 Monopoli",
    "sg:city":"Monopoli",
    "sg:orig_category":"Legno E Semilavorati",
    "sg:phone":"+39 080 802928",
    "sg:postcode":"70043",
    "sg:province":"Bari",
    "wof:name":"Va.le.sa (s.r.l.)",
    "wof:placetype":"venue"
},
  "geometry": {"coordinates":[17.26664,40.90509],"type":"Point"}
}