{
  "type": "Feature",
  "properties": {
    "addr:full":"116, Via Roma 23808 Vercurago Vercurago Lecco 23808",
    "addr:housenumber":"116",
    "addr:postcode":"23808;23808",
    "addr:street":"Via Roma",
    "iso:country":"IT",
    "sg:address":"116, Via Roma 23808 Vercurago",
    "sg:city":"Vercurago",
    "sg:classifiers":[
        {
            "category":"Bars & Pubs",
            "subcategory":"Nightclub",
            "type":"Food & Drink"
        }
    ],
    "sg:phone":"+39 0341 421838",
    "sg:postcode":"23808",
    "sg:province":"Lecco",
    "sg:tags":[
        "cake",
        "bread"
    ],
    "wof:name":"Pasticceria Del Lario (s.r.l.)",
    "wof:placetype":"venue"
},
  "geometry": {"coordinates":[9.424356,45.807323],"type":"Point"}
}