{
  "type": "Feature",
  "properties": {
    "iso:country":"IT",
    "sg:address":"09047 Selargius",
    "sg:city":"Selargius",
    "sg:orig_category":"Forniture Alle Strutture Ricettive. Macchine E Impianti Per Attivita' Commerciali Ed Artigianali",
    "sg:phone":"+39 070 841934",
    "sg:postcode":"09047",
    "sg:province":"Cagliari",
    "wof:name":"Artigiantecnica Di Sangiovanni & Diana",
    "wof:placetype":"venue"
},
  "geometry": {"coordinates":[9.1589040756,39.2496109009],"type":"Point"}
}