{
  "type": "Feature",
  "properties": {
    "iso:country":"IT",
    "sg:address":"24, Via Dell' Artigianato 61011 Gabicce Mare",
    "sg:city":"Gabicce Mare",
    "sg:classifiers":[
        {
            "category":"Professional",
            "subcategory":"Engineering",
            "type":"Services"
        }
    ],
    "sg:phone":"+39 0541 952924",
    "sg:postcode":"61011",
    "sg:province":"Pesaro E Urbino",
    "sg:tags":[
        "machine",
        "-",
        "mechanical"
    ],
    "wof:name":"O.m.a.g. S.r.l.",
    "wof:placetype":"venue"
},
  "geometry": {"coordinates":[12.772451,43.953297],"type":"Point"}
}