{
  "type": "Feature",
  "properties": {
    "addr:full":"122, Via G. Deledda 46030 Borgoforte Borgoforte Mantova 46030",
    "addr:housenumber":"122",
    "addr:postcode":"46030;46030",
    "addr:street":"Via G. Deledda",
    "iso:country":"IT",
    "sg:address":"122, Via G. Deledda 46030 Borgoforte",
    "sg:city":"Borgoforte",
    "sg:classifiers":[
        {
            "category":"Manufacturing",
            "subcategory":"Paper Products",
            "type":"Manufacturing & Wholesale Goods"
        }
    ],
    "sg:phone":"+39 0376 648587",
    "sg:postcode":"46030",
    "sg:province":"Mantova",
    "sg:tags":[
        "cardboard"
    ],
    "wof:name":"G.e.m. Di Grossi Galeazzo & C. S.n.c.",
    "wof:placetype":"venue"
},
  "geometry": {"coordinates":[10.7462091446,45.12733078],"type":"Point"}
}