{
  "type": "Feature",
  "properties": {
    "iso:country":"IT",
    "sg:address":"20081 Abbiategrasso",
    "sg:city":"Abbiategrasso",
    "sg:orig_category":"Macchine Utensili - Produzione",
    "sg:phone":"+39 02 946 1188",
    "sg:postcode":"20081",
    "sg:province":"Milano",
    "sg:website":"http://www.albacut.it",
    "wof:name":"Alba-cut Srl",
    "wof:placetype":"venue"
},
  "geometry": {"coordinates":[8.919825,45.393036],"type":"Point"}
}