{
  "type": "Feature",
  "properties": {
    "iso:country":"IT",
    "sg:address":"Via S. Maria 20093 Cologno Monzese",
    "sg:city":"Cologno Monzese",
    "sg:classifiers":[
        {
            "category":"Communications",
            "subcategory":"Newspaper",
            "type":"Services"
        }
    ],
    "sg:phone":"+39 39022535641",
    "sg:postcode":"20093",
    "sg:province":"Milano",
    "sg:tags":[
        "advertising"
    ],
    "wof:name":"Publiflor I Pubblicita' Esterna Spa",
    "wof:placetype":"venue"
},
  "geometry": {"coordinates":[9.270423,45.538074],"type":"Point"}
}