{
  "type": "Feature",
  "properties": {
    "iso:country":"IT",
    "sg:address":"70032 Bitonto",
    "sg:city":"Bitonto",
    "sg:orig_category":"Articoli Per Imballaggio E Confezionamento",
    "sg:phone":"+39 080 371 7787",
    "sg:postcode":"70032",
    "sg:province":"Bari",
    "wof:name":"Carton Plast Pugliese Srl",
    "wof:placetype":"venue"
},
  "geometry": {"coordinates":[16.679188,41.132793],"type":"Point"}
}