{
  "type": "Feature",
  "properties": {
    "iso:country":"IT",
    "sg:address":"20090 Pieve Emanuele",
    "sg:city":"Pieve Emanuele",
    "sg:classifiers":[
        {
            "category":"Manufacturing",
            "subcategory":"Glass & Minerals",
            "type":"Manufacturing & Wholesale Goods"
        }
    ],
    "sg:phone":"+39 02 9042 9293",
    "sg:postcode":"20090",
    "sg:province":"Milano",
    "sg:tags":[
        "activities",
        "product",
        "industrial",
        "processing",
        "supply"
    ],
    "wof:name":"Garda Maria Rosa",
    "wof:placetype":"venue"
},
  "geometry": {"coordinates":[9.170377,45.373833],"type":"Point"}
}