{
  "type": "Feature",
  "properties": {
    "addr:full":"1616, Via Nuova Per Pisa Fraz. Massa Pisana 55100 Lucca Lucca Lucca 55100",
    "addr:housenumber":"1616",
    "addr:postcode":"55100;55100",
    "addr:street":"Via Nuova Per Pisa Fraz.;Pisana",
    "iso:country":"IT",
    "sg:address":"1616, Via Nuova Per Pisa Fraz. Massa Pisana 55100 Lucca",
    "sg:city":"Lucca",
    "sg:classifiers":[
        {
            "category":"Travel",
            "subcategory":"Travel Agent",
            "type":"Entertainment"
        }
    ],
    "sg:phone":"+39 0583 370037",
    "sg:postcode":"55100",
    "sg:province":"Lucca",
    "sg:tags":[
        "business"
    ],
    "wof:name":"Albergo Villa La Principessa",
    "wof:placetype":"venue"
},
  "geometry": {"coordinates":[10.507994,43.843014],"type":"Point"}
}