{
  "type": "Feature",
  "properties": {
    "iso:country":"IT",
    "sg:address":"16039 Sestri Levante",
    "sg:city":"Sestri Levante",
    "sg:orig_category":"Servizi E Lavori Per Arredamento E Industria Del Legno",
    "sg:phone":"+39 0185 409174",
    "sg:postcode":"16039",
    "sg:province":"Genova",
    "wof:name":"Sall - Legnami Snc",
    "wof:placetype":"venue"
},
  "geometry": {"coordinates":[9.422827,44.283337],"type":"Point"}
}