{
  "type": "Feature",
  "properties": {
    "iso:country":"IT",
    "sg:address":"12, Via Frassinetto 12040 Genola",
    "sg:city":"Genola",
    "sg:classifiers":[
        {
            "category":"Retail",
            "subcategory":"Animal Services",
            "type":"Services"
        }
    ],
    "sg:phone":"+39 39017268197",
    "sg:postcode":"12040",
    "sg:province":"Cuneo",
    "sg:tags":[
        "breeding"
    ],
    "wof:name":"Rovera",
    "wof:placetype":"venue"
},
  "geometry": {"coordinates":[7.659832,44.599281],"type":"Point"}
}