{
  "type": "Feature",
  "properties": {
    "iso:country":"IT",
    "sg:address":"25080 Prevalle",
    "sg:city":"Prevalle",
    "sg:orig_category":"Carpenterie Metalliche",
    "sg:phone":"+39 030 680 1656",
    "sg:postcode":"25080",
    "sg:province":"Brescia",
    "wof:name":"Rifomet Srl",
    "wof:placetype":"venue"
},
  "geometry": {"coordinates":[10.42207,45.557858],"type":"Point"}
}