{
  "type": "Feature",
  "properties": {
    "addr:full":"40050 Monte San Pietro Monte San Pietro Bologna 40050",
    "addr:housenumber":"40050",
    "addr:postcode":"40050",
    "addr:street":"Monte",
    "iso:country":"IT",
    "sg:address":"40050 Monte San Pietro",
    "sg:city":"Monte San Pietro",
    "sg:orig_category":"Articoli Medico-sanitari Ed Ortopedici. Impianti, Attrezzature E Forniture Sanitarie Ed Ospedaliere",
    "sg:phone":"+39 051 676 2292",
    "sg:postcode":"40050",
    "sg:province":"Bologna",
    "wof:name":"Fm Service S.r.l.",
    "wof:placetype":"venue"
},
  "geometry": {"coordinates":[11.217471,44.535854],"type":"Point"}
}