{
  "type": "Feature",
  "properties": {
    "addr:full":"00174 Roma Roma Roma 00174",
    "addr:postcode":"00174;00174",
    "iso:country":"IT",
    "sg:address":"00174 Roma",
    "sg:city":"Roma",
    "sg:orig_category":"Prodotti Finiti Stampati. Forniture Per Attivita' Commerciali Ed Artigianali",
    "sg:phone":"+39 06 7696 1809",
    "sg:postcode":"00174",
    "sg:province":"Roma",
    "wof:name":"Di Giulio Maurizio",
    "wof:placetype":"venue"
},
  "geometry": {"coordinates":[12.5467271805,41.8625259399],"type":"Point"}
}