{
  "type": "Feature",
  "properties": {
    "addr:full":"19032 Lerici Lerici La Spezia 19032",
    "addr:postcode":"19032;19032",
    "iso:country":"IT",
    "sg:address":"19032 Lerici",
    "sg:city":"Lerici",
    "sg:orig_category":"Nautica. Automobili E Mezzi Di Trasporto",
    "sg:phone":"+39 0187 560019",
    "sg:postcode":"19032",
    "sg:province":"La Spezia",
    "wof:name":"Marina Di Pertusola S.r.l.",
    "wof:placetype":"venue"
},
  "geometry": {"coordinates":[9.767869,44.244793],"type":"Point"}
}