{
  "type": "Feature",
  "properties": {
    "iso:country":"IT",
    "sg:address":"728, Corso Vittorio Veneto 97100 Ragusa",
    "sg:city":"Ragusa",
    "sg:classifiers":[
        {
            "category":"Food & Beverages",
            "subcategory":"Bakery",
            "type":"Retail Goods"
        }
    ],
    "sg:phone":"+39 0932 251254",
    "sg:postcode":"97100",
    "sg:province":"Ragusa",
    "sg:tags":[
        "grain",
        "cereal"
    ],
    "wof:name":"Curiale Vito & Figli",
    "wof:placetype":"venue"
},
  "geometry": {"coordinates":[14.521802,36.825325],"type":"Point"}
}