{
  "type": "Feature",
  "properties": {
    "iso:country":"IT",
    "sg:address":"25071 Agnosine",
    "sg:city":"Agnosine",
    "sg:orig_category":"Macchine E Forniture Per Arredamento E Industria Del Legno. Serramenti Ed Infissi. Minuterie Metalliche E Ferramenta",
    "sg:phone":"+39 036 589 6134",
    "sg:postcode":"25071",
    "sg:province":"Brescia",
    "wof:name":"Seneci Carlo Di Seneci James E C.",
    "wof:placetype":"venue"
},
  "geometry": {"coordinates":[10.351155,45.64996],"type":"Point"}
}