{
  "type": "Feature",
  "properties": {
    "iso:country":"IT",
    "sg:address":"7, Via Dei Platani 22040 Alzate Brianza",
    "sg:city":"Alzate Brianza",
    "sg:classifiers":[
        {
            "category":"Food & Beverages",
            "subcategory":"Bakery",
            "type":"Retail Goods"
        }
    ],
    "sg:phone":"+39 39031630491",
    "sg:postcode":"22040",
    "sg:province":"Como",
    "sg:tags":[
        "grain",
        "cereal"
    ],
    "wof:name":"Molini Lario (s.p.a.)",
    "wof:placetype":"venue"
},
  "geometry": {"coordinates":[9.167118,45.773499],"type":"Point"}
}