{
  "type": "Feature",
  "properties": {
    "addr:full":"7, V. Raffaello 31021 Mogliano Veneto Mogliano Veneto Treviso 31021",
    "addr:housenumber":"7",
    "addr:postcode":"31021;31021",
    "addr:street":"V. Raffaello",
    "iso:country":"IT",
    "sg:address":"7, V. Raffaello 31021 Mogliano Veneto",
    "sg:city":"Mogliano Veneto",
    "sg:classifiers":[
        {
            "category":"Communications",
            "subcategory":"Television Station",
            "type":"Services"
        }
    ],
    "sg:phone":"+39 041 593 7031",
    "sg:postcode":"31021",
    "sg:province":"Treviso",
    "sg:tags":[
        "equipment",
        "optical",
        "instrument"
    ],
    "sg:website":"http://www.pk-digital.it:ws_end: :mark:ws:http://www.paginegialle.it/fotopk",
    "wof:name":"P.k. Photo Know-how",
    "wof:placetype":"venue"
},
  "geometry": {"coordinates":[12.30461,45.587517],"type":"Point"}
}