{
  "type": "Feature",
  "properties": {
    "iso:country":"IT",
    "sg:address":"22, Via Molino 48010 Fusignano",
    "sg:city":"Fusignano",
    "sg:classifiers":[
        {
            "category":"Personal",
            "subcategory":"Shoe Repair & Shine",
            "type":"Services"
        }
    ],
    "sg:phone":"+39 39054552241",
    "sg:postcode":"48010",
    "sg:province":"Ravenna",
    "sg:tags":[
        "leather"
    ],
    "wof:name":"Open Srl",
    "wof:placetype":"venue"
},
  "geometry": {"coordinates":[11.952525,44.469685],"type":"Point"}
}