{
  "type": "Feature",
  "properties": {
    "addr:full":"00010 Roma Roma 00010",
    "addr:postcode":"00010;00010",
    "iso:country":"IT",
    "sg:address":"00010 Roma",
    "sg:orig_category":"Forniture Per Abbigliamento E Pelletterie",
    "sg:phone":"+39 06 226 2811",
    "sg:postcode":"00010",
    "sg:province":"Roma",
    "wof:name":"Petrolati Rosanna E Figlie Snc",
    "wof:placetype":"venue"
},
  "geometry": {"coordinates":[12.3306026459,41.7877922058],"type":"Point"}
}