{
  "type": "Feature",
  "properties": {
    "iso:country":"IT",
    "sg:address":"20124 Milano",
    "sg:city":"Milano",
    "sg:orig_category":"Centri Di Estetica E Cosmesi E Servizi. Prodotti Cosmetici E Da Toeletta",
    "sg:phone":"+39 02 669 1440",
    "sg:postcode":"20124",
    "sg:province":"Milano",
    "wof:name":"Cap Center (s.a.s.)",
    "wof:placetype":"venue"
},
  "geometry": {"coordinates":[9.196957,45.487316],"type":"Point"}
}