{
  "type": "Feature",
  "properties": {
    "iso:country":"IT",
    "sg:address":"25065 Lumezzane",
    "sg:city":"Lumezzane",
    "sg:orig_category":"Utensili Meccanici E Materiali",
    "sg:phone":"+39 030 826816",
    "sg:postcode":"25065",
    "sg:province":"Brescia",
    "wof:name":"Zobbio Floriano & C. Snc",
    "wof:placetype":"venue"
},
  "geometry": {"coordinates":[10.274075,45.653652],"type":"Point"}
}