{
  "type": "Feature",
  "properties": {
    "iso:country":"IT",
    "sg:address":"35010 Campo San Martino",
    "sg:city":"Campo San Martino",
    "sg:orig_category":"Grigliati E Griglie",
    "sg:phone":"+39 049 559 0802",
    "sg:postcode":"35010",
    "sg:province":"Padova",
    "wof:name":"Longo Luciano Snc Di Longo Luciano & C.",
    "wof:placetype":"venue"
},
  "geometry": {"coordinates":[11.810041,45.544746],"type":"Point"}
}