{
  "type": "Feature",
  "properties": {
    "iso:country":"IT",
    "sg:address":"65123 Pescara",
    "sg:city":"Pescara",
    "sg:orig_category":"Servizi E Lavori Per Edilizia E Lavori Pubblici. Servizi E Lavori Per Ecologia E Smaltimento Rifiuti. Macchine E Forniture Per Ecologia E Smaltimento Rifiuti. Acqua, Luce, Gas E Societa' Di Esercizio ",
    "sg:phone":"+39 085 421 3350",
    "sg:postcode":"65123",
    "sg:province":"Pescara",
    "wof:name":"Zuccarini Giuseppe",
    "wof:placetype":"venue"
},
  "geometry": {"coordinates":[14.204006,42.476624],"type":"Point"}
}