{
  "type": "Feature",
  "properties": {
    "iso:country":"IT",
    "sg:address":"20146 Milano",
    "sg:city":"Milano",
    "sg:orig_category":"Modelli E Plastici",
    "sg:phone":"+39 02 4895 0739",
    "sg:postcode":"20146",
    "sg:province":"Milano",
    "wof:name":"Model Snc",
    "wof:placetype":"venue"
},
  "geometry": {"coordinates":[9.1481151581,45.4514541626],"type":"Point"}
}