{
  "type": "Feature",
  "properties": {
    "iso:country":"IT",
    "sg:address":"84013 Cava D\u00e8 Tirreni",
    "sg:orig_category":"Analisi Cliniche - Centri E Laboratori",
    "sg:phone":"+39 089 464280",
    "sg:postcode":"84013",
    "sg:province":"Salerno",
    "wof:name":"Analisi Cliniche Gravagnuolo",
    "wof:placetype":"venue"
},
  "geometry": {"coordinates":[14.705448,40.701687],"type":"Point"}
}