{
  "type": "Feature",
  "properties": {
    "iso:country":"IT",
    "sg:address":"32021 Agordo",
    "sg:city":"Agordo",
    "sg:orig_category":"Occhiali - Produzione E Ingrosso",
    "sg:phone":"+39 0437 63340",
    "sg:postcode":"32021",
    "sg:province":"Belluno",
    "sg:website":"http://www.eyewear.net/occ/dieffe/d",
    "wof:name":"Dieffe Occhiali Agordo Di Favero Giorgio & C. Snc",
    "wof:placetype":"venue"
},
  "geometry": {"coordinates":[12.044903,46.277027],"type":"Point"}
}