{
  "type": "Feature",
  "properties": {
    "iso:country":"IT",
    "sg:address":"00177 Roma",
    "sg:city":"Roma",
    "sg:orig_category":"Termotecnica E Riscaldamento, Apparecchiature E Servizi. Prodotti Vari In Metallo",
    "sg:phone":"+39 06 241 0519",
    "sg:postcode":"00177",
    "sg:province":"Roma",
    "wof:name":"Al.catal Srl",
    "wof:placetype":"venue"
},
  "geometry": {"coordinates":[12.542683,41.876892],"type":"Point"}
}