{
  "type": "Feature",
  "properties": {
    "iso:country":"IT",
    "sg:address":"63014 Montegranaro",
    "sg:city":"Montegranaro",
    "sg:orig_category":"Calzature, Pelletterie E Pelli",
    "sg:phone":"+39 0734 890321",
    "sg:postcode":"63014",
    "sg:province":"Ascoli Piceno",
    "wof:name":"Calzaturificio Mara",
    "wof:placetype":"venue"
},
  "geometry": {"coordinates":[13.575018,42.854923],"type":"Point"}
}