{
  "type": "Feature",
  "properties": {
    "iso:country":"IT",
    "sg:address":"26034 Piadena",
    "sg:city":"Piadena",
    "sg:orig_category":"Mangimi, Foraggi Ed Integratori Zootecnici",
    "sg:phone":"+39 0375 380001",
    "sg:postcode":"26034",
    "sg:province":"Cremona",
    "wof:name":"Z.p.m. Srl",
    "wof:placetype":"venue"
},
  "geometry": {"coordinates":[10.026181,45.13295],"type":"Point"}
}