{
  "type": "Feature",
  "properties": {
    "iso:country":"IT",
    "sg:address":"20135 Milano",
    "sg:city":"Milano",
    "sg:orig_category":"Cinematografia E Radiotelevisione. Cine-foto-ottica",
    "sg:phone":"+39 02 5830 3571",
    "sg:postcode":"20135",
    "sg:province":"Milano",
    "wof:name":"Harem Video Di Amato Maurizio E C. S.a.s.",
    "wof:placetype":"venue"
},
  "geometry": {"coordinates":[9.202509,45.450577],"type":"Point"}
}