{
  "type": "Feature",
  "properties": {
    "iso:country":"IT",
    "sg:address":"160, S.s. Arceviese 60010 Pianello Di Ostra",
    "sg:city":"Ostra",
    "sg:classifiers":[
        {
            "category":"Manufacturing",
            "subcategory":"Rubber & Plastics",
            "type":"Manufacturing & Wholesale Goods"
        }
    ],
    "sg:phone":"+39 39071688686",
    "sg:postcode":"60010",
    "sg:province":"Ancona",
    "sg:tags":[
        "packaging",
        "material",
        "-"
    ],
    "sg:website":"http://www.valmisa.it:ws_end: :mark:ws:http://www.paginegialle.it/plasticavalmisa",
    "wof:name":"Plastica Valmisa Spa",
    "wof:placetype":"venue"
},
  "geometry": {"coordinates":[13.5187568665,43.6158561707],"type":"Point"}
}