{
  "type": "Feature",
  "properties": {
    "iso:country":"IT",
    "sg:address":"1, Via Venezia 35010 Trebaseleghe",
    "sg:city":"Trebaseleghe",
    "sg:classifiers":[
        {
            "category":"Shopping",
            "subcategory":"Clothing, Apparel, & Fashions",
            "type":"Retail Goods"
        }
    ],
    "sg:phone":"+39 049 932 3111",
    "sg:postcode":"35010",
    "sg:province":"Padova",
    "sg:tags":[
        "clothes"
    ],
    "wof:name":"Pepper Industries S.p.a.",
    "wof:placetype":"venue"
},
  "geometry": {"coordinates":[12.053881,45.586647],"type":"Point"}
}