{
  "type": "Feature",
  "properties": {
    "addr:full":"73028 Lecce Lecce 73028",
    "addr:postcode":"73028;73028",
    "iso:country":"IT",
    "sg:address":"73028 Lecce",
    "sg:orig_category":"Assicurazioni",
    "sg:phone":"+39 0832 217849",
    "sg:postcode":"73028",
    "sg:province":"Lecce",
    "wof:name":"Assimoco Agenzie Lecce E Provincia",
    "wof:placetype":"venue"
},
  "geometry": {"coordinates":[18.185089,40.351593],"type":"Point"}
}