{
  "type": "Feature",
  "properties": {
    "iso:country":"IT",
    "sg:address":"64011 Alba Adriatica",
    "sg:city":"Alba Adriatica",
    "sg:orig_category":"Campeggio. Alberghi E Strutture Extra Alberghiere",
    "sg:phone":"+39 0861 713356",
    "sg:postcode":"64011",
    "sg:province":"Teramo",
    "sg:website":"http://www.campingeucaliptus.it",
    "wof:name":"Camping Eucaliptus Di Ruggieri Sante & C. Sas",
    "wof:placetype":"venue"
},
  "geometry": {"coordinates":[13.920199,42.828377],"type":"Point"}
}