{
  "type": "Feature",
  "properties": {
    "iso:country":"IT",
    "sg:address":"50059 Vinci",
    "sg:city":"Vinci",
    "sg:orig_category":"Aspiratori",
    "sg:phone":"+39 0571 508660",
    "sg:postcode":"50059",
    "sg:province":"Firenze",
    "wof:name":"Corme Srl",
    "wof:placetype":"venue"
},
  "geometry": {"coordinates":[10.924196,43.771671],"type":"Point"}
}