{
  "type": "Feature",
  "properties": {
    "addr:full":"94010 Catenanuova Catenanuova Enna 94010",
    "addr:postcode":"94010;94010",
    "iso:country":"IT",
    "sg:address":"94010 Catenanuova",
    "sg:city":"Catenanuova",
    "sg:classifiers":[
        {
            "category":"Health Services",
            "subcategory":"Health Practitioner",
            "type":"Services"
        }
    ],
    "sg:phone":"+39 0935 76394",
    "sg:postcode":"94010",
    "sg:province":"Enna",
    "sg:tags":[
        "medici"
    ],
    "wof:name":"Scaccianoce Salvatore Antonino",
    "wof:placetype":"venue"
},
  "geometry": {"coordinates":[14.6930971146,37.570892334],"type":"Point"}
}