{
  "type": "Feature",
  "properties": {
    "addr:full":"20123 Milano Milano Milano 20123",
    "addr:postcode":"20123;20123",
    "iso:country":"IT",
    "sg:address":"20123 Milano",
    "sg:city":"Milano",
    "sg:orig_category":"Biancheria, Telerie E Coperte",
    "sg:phone":"+39 02 805 3008",
    "sg:postcode":"20123",
    "sg:province":"Milano",
    "wof:name":"Broggi Enrico",
    "wof:placetype":"venue"
},
  "geometry": {"coordinates":[9.189053,45.463284],"type":"Point"}
}