{
  "type": "Feature",
  "properties": {
    "iso:country":"IT",
    "sg:address":"50018 Scandicci",
    "sg:city":"Scandicci",
    "sg:classifiers":[
        {
            "category":"Health Services",
            "subcategory":"Health Practitioner",
            "type":"Services"
        }
    ],
    "sg:phone":"+39 055 250615",
    "sg:postcode":"50018",
    "sg:province":"Firenze",
    "sg:tags":[
        "medici"
    ],
    "wof:name":"Luzzo Pasquale",
    "wof:placetype":"venue"
},
  "geometry": {"coordinates":[11.188883,43.754269],"type":"Point"}
}