{
  "type": "Feature",
  "properties": {
    "iso:country":"IT",
    "sg:address":"57, Via Romana 55015 Montecarlo",
    "sg:city":"Montecarlo",
    "sg:classifiers":[
        {
            "category":"Personal",
            "subcategory":"Shoe Repair & Shine",
            "type":"Services"
        }
    ],
    "sg:phone":"+39 0583 277168",
    "sg:postcode":"55015",
    "sg:province":"Lucca",
    "sg:tags":[
        "leather"
    ],
    "wof:name":"Calzaturificio F.g.",
    "wof:placetype":"venue"
},
  "geometry": {"coordinates":[10.642777,43.829021],"type":"Point"}
}