{
  "type": "Feature",
  "properties": {
    "iso:country":"IT",
    "sg:address":"20092 Cinisello Balsamo",
    "sg:city":"Cinisello Balsamo",
    "sg:orig_category":"Utensili Meccanici E Materiali",
    "sg:phone":"+39 02 612 3777",
    "sg:postcode":"20092",
    "sg:province":"Milano",
    "wof:name":"Costel Srl",
    "wof:placetype":"venue"
},
  "geometry": {"coordinates":[9.247053,45.561531],"type":"Point"}
}