{
  "type": "Feature",
  "properties": {
    "iso:country":"IT",
    "sg:address":"09128 Cagliari",
    "sg:city":"Cagliari",
    "sg:orig_category":"Finanziamenti E Mutui",
    "sg:phone":"+39 070 453140",
    "sg:postcode":"09128",
    "sg:province":"Cagliari",
    "wof:name":"Multi Fin Srl",
    "wof:placetype":"venue"
},
  "geometry": {"coordinates":[9.1243677139,39.2143783569],"type":"Point"}
}