{
  "type": "Feature",
  "properties": {
    "addr:full":"24/b, Traversa Il Crocifisso 59100 Prato Prato Prato 59100",
    "addr:housenumber":"24 / b",
    "addr:postcode":"59100;59100",
    "addr:street":"Crocifisso",
    "iso:country":"IT",
    "sg:address":"24/b, Traversa Il Crocifisso 59100 Prato",
    "sg:city":"Prato",
    "sg:classifiers":[
        {
            "category":"Shopping",
            "subcategory":"Crafts & Fabrics",
            "type":"Retail Goods"
        }
    ],
    "sg:phone":"+39 0574 625415",
    "sg:postcode":"59100",
    "sg:province":"Prato",
    "wof:name":"Menchi Tessuti S.p.a.",
    "wof:placetype":"venue"
},
  "geometry": {"coordinates":[11.0963125229,43.879699707],"type":"Point"}
}