{
  "type": "Feature",
  "properties": {
    "addr:full":"63039 San Benedetto Del Tronto San Benedetto del Tronto Ascoli Piceno 63039",
    "addr:housenumber":"63039",
    "addr:postcode":"63039",
    "addr:street":"San;Piceno",
    "iso:country":"IT",
    "sg:address":"63039 San Benedetto Del Tronto",
    "sg:city":"San Benedetto del Tronto",
    "sg:orig_category":"Elettrotecnica Industriale, Prodotti E Apparecchiature",
    "sg:phone":"+39 0735 583455",
    "sg:postcode":"63039",
    "sg:province":"Ascoli Piceno",
    "wof:name":"Furlanetto International Srl",
    "wof:placetype":"venue"
},
  "geometry": {"coordinates":[13.852541,42.951542],"type":"Point"}
}