{
  "type": "Feature",
  "properties": {
    "iso:country":"IT",
    "sg:address":"41051 Castelnuovo Rangone",
    "sg:city":"Castelnuovo Rangone",
    "sg:orig_category":"Antenne Radio-televisione",
    "sg:phone":"+39 059 538030",
    "sg:postcode":"41051",
    "sg:province":"Modena",
    "wof:name":"Audiocar 2 Snc",
    "wof:placetype":"venue"
},
  "geometry": {"coordinates":[10.939901,44.549385],"type":"Point"}
}