{
  "type": "Feature",
  "properties": {
    "iso:country":"IT",
    "sg:address":"Via Aldo Moro 13; Vallecrosia; 18019",
    "sg:city":"Vallecrosia",
    "sg:classifiers":[
        {
            "category":"Banks & Credit Unions",
            "subcategory":"Bank",
            "type":"Services"
        }
    ],
    "sg:phone":"+39 0184 253070",
    "sg:postcode":"18019",
    "sg:province":"Imperia",
    "wof:name":"Istituto Bancario, San Paolo Di Torino Spa",
    "wof:placetype":"venue"
},
  "geometry": {"coordinates":[7.638105,43.787003],"type":"Point"}
}