{
  "type": "Feature",
  "properties": {
    "iso:country":"IT",
    "sg:address":"47900 Rimini",
    "sg:city":"Rimini",
    "sg:orig_category":"Abbigliamento - Produzione E Ingrosso",
    "sg:phone":"+39 0541 383613",
    "sg:postcode":"47900",
    "sg:province":"Rimini",
    "wof:name":"Marila Srl",
    "wof:placetype":"venue"
},
  "geometry": {"coordinates":[12.546058,44.011654],"type":"Point"}
}