{
  "type": "Feature",
  "properties": {
    "iso:country":"IT",
    "sg:address":"00141 Roma",
    "sg:city":"Roma",
    "sg:orig_category":"Associazioni Artistiche, Culturali E Ricreative",
    "sg:phone":"+39 06 810 7846",
    "sg:postcode":"00141",
    "sg:province":"Roma",
    "wof:name":"Aicai Associazione Italiana Commercianti Artigiani Imprenditori",
    "wof:placetype":"venue"
},
  "geometry": {"coordinates":[12.527699,41.940769],"type":"Point"}
}