{
  "type": "Feature",
  "properties": {
    "iso:country":"IT",
    "sg:address":"20129 Milano",
    "sg:city":"Milano",
    "sg:orig_category":"Abbigliamento Esterno, Maglierie E Pelliccerie. Servizi E Lavori Per Abbigliamento E Pelletterie",
    "sg:phone":"+39 02 784295",
    "sg:postcode":"20129",
    "sg:province":"Milano",
    "wof:name":"Vendola Michele",
    "wof:placetype":"venue"
},
  "geometry": {"coordinates":[9.208532,45.470604],"type":"Point"}
}