{
  "type": "Feature",
  "properties": {
    "iso:country":"IT",
    "sg:address":"93, Via Gramsci Antonio 20037 Paderno Dugnano",
    "sg:city":"Paderno Dugnano",
    "sg:classifiers":[
        {
            "category":"Home & Garden",
            "subcategory":"Home Furnishings",
            "type":"Retail Goods"
        }
    ],
    "sg:phone":"+39 39029184568",
    "sg:postcode":"20037",
    "sg:province":"Milano",
    "sg:tags":[
        "household"
    ],
    "wof:name":"Scaltrini Attilio (s.r.l.)",
    "wof:placetype":"venue"
},
  "geometry": {"coordinates":[9.168834,45.560947],"type":"Point"}
}