{
  "type": "Feature",
  "properties": {
    "iso:country":"IT",
    "sg:address":"22, Via Bravi 35129 Padova",
    "sg:city":"Padova",
    "sg:classifiers":[
        {
            "category":"Shopping",
            "subcategory":"Clothing, Apparel, & Fashions",
            "type":"Retail Goods"
        }
    ],
    "sg:phone":"+39 39049625590",
    "sg:postcode":"35129",
    "sg:province":"Padova",
    "sg:tags":[
        "clothing",
        "accessory"
    ],
    "wof:name":"Agostini Di Gabriele Agostini & C. (s.a.s.)",
    "wof:placetype":"venue"
},
  "geometry": {"coordinates":[11.844167,45.397499],"type":"Point"}
}