{
  "type": "Feature",
  "properties": {
    "addr:full":"68, Via Cesare Battisti 24062 Costa Volpino Costa Volpino Bergamo 24062",
    "addr:housenumber":"volpino",
    "addr:postcode":"24062;24062",
    "addr:street":"Via Cesare Battisti",
    "iso:country":"IT",
    "sg:address":"68, Via Cesare Battisti 24062 Costa Volpino",
    "sg:city":"Costa Volpino",
    "sg:classifiers":[
        {
            "category":"Professional",
            "subcategory":"Engineering",
            "type":"Services"
        }
    ],
    "sg:phone":"+39 39035970322",
    "sg:postcode":"24062",
    "sg:province":"Bergamo",
    "sg:tags":[
        "machine",
        "-",
        "mechanical"
    ],
    "wof:name":"Termotecnica Sebina Di Gelmini & C. (s.n.c.)",
    "wof:placetype":"venue"
},
  "geometry": {"coordinates":[10.106596,45.821201],"type":"Point"}
}