{
  "type": "Feature",
  "properties": {
    "iso:country":"IT",
    "sg:address":"17/b, Via Barontini Ilio 50018 Scandicci",
    "sg:city":"Scandicci",
    "sg:classifiers":[
        {
            "category":"Professional",
            "subcategory":"Engineering",
            "type":"Services"
        }
    ],
    "sg:phone":"+39 39055722091",
    "sg:postcode":"50018",
    "sg:province":"Firenze",
    "sg:tags":[
        "machine",
        "-",
        "mechanical"
    ],
    "wof:name":"Frigel Firenze Srl",
    "wof:placetype":"venue"
},
  "geometry": {"coordinates":[11.135127,43.772083],"type":"Point"}
}