{
  "type": "Feature",
  "properties": {
    "addr:full":"Via Poggi Felice 14 20131 Milano Milano Milano 20131",
    "addr:housenumber":"14",
    "addr:postcode":"20131;20131",
    "addr:street":"Via Poggi Felice",
    "iso:country":"IT",
    "sg:address":"Via Poggi Felice 14 20131 Milano",
    "sg:city":"Milano",
    "sg:classifiers":[
        {
            "category":"Communications",
            "subcategory":"Film & Video Production",
            "type":"Services"
        }
    ],
    "sg:phone":"+39 02 266 6708",
    "sg:postcode":"20131",
    "sg:province":"Milano",
    "sg:tags":[
        "hair",
        "ware"
    ],
    "sg:website":"www.sabbadiniitaly.com",
    "wof:name":"Sabbadini Mauro Srl",
    "wof:placetype":"venue"
},
  "geometry": {"coordinates":[9.228008,45.482967],"type":"Point"}
}