{
  "type": "Feature",
  "properties": {
    "iso:country":"IT",
    "sg:address":"Via Nazionale 61, 43046 Collecchio, Pr",
    "sg:classifiers":[
        {
            "category":"Banks & Credit Unions",
            "subcategory":"Bank",
            "type":"Services"
        }
    ],
    "wof:name":"Cassa Rurale Artigiana Di Ozzano Taro",
    "wof:placetype":"venue"
},
  "geometry": {"coordinates":[10.143631,44.712601],"type":"Point"}
}