{
  "type": "Feature",
  "properties": {
    "iso:country":"IT",
    "sg:address":"24020 Torre Boldone",
    "sg:city":"Torre Boldone",
    "sg:orig_category":"Servizi Editoriali",
    "sg:phone":"+39 035 362026",
    "sg:postcode":"24020",
    "sg:province":"Bergamo",
    "wof:name":"Cuminetti Paolo",
    "wof:placetype":"venue"
},
  "geometry": {"coordinates":[9.7050409317,45.7234344482],"type":"Point"}
}