{
  "type": "Feature",
  "properties": {
    "addr:full":"98071 Capo D'orlando Messina 98071",
    "addr:postcode":"98071;98071",
    "iso:country":"IT",
    "sg:address":"98071 Capo D'orlando",
    "sg:orig_category":"Pubblicita', Marketing E Comunicazione",
    "sg:phone":"+39 0941 913102",
    "sg:postcode":"98071",
    "sg:province":"Messina",
    "sg:website":"http://www.eventipub.it",
    "wof:name":"Eventi Srl",
    "wof:placetype":"venue"
},
  "geometry": {"coordinates":[14.7451868057,38.1568565369],"type":"Point"}
}