{
  "type": "Feature",
  "properties": {
    "iso:country":"IT",
    "sg:address":"46023 Gonzaga",
    "sg:city":"Gonzaga",
    "sg:orig_category":"Zootecnia - Prodotti",
    "sg:phone":"+39 0376 528312",
    "sg:postcode":"46023",
    "sg:province":"Mantova",
    "wof:name":"S.a.a.b. Di Stefanini Antonio & C. Snc",
    "wof:placetype":"venue"
},
  "geometry": {"coordinates":[10.825178,44.95203],"type":"Point"}
}