{
  "type": "Feature",
  "properties": {
    "iso:country":"IT",
    "sg:address":"24010 Ponteranica",
    "sg:city":"Ponteranica",
    "sg:orig_category":"Ceramiche Per Pavimenti E Rivestimenti - Produzione E Ingrosso",
    "sg:phone":"+39 035 412 8050",
    "sg:postcode":"24010",
    "sg:province":"Bergamo",
    "sg:website":"http://www.lopificiobg.it",
    "wof:name":"L'opificio Di Bernacca Nicola",
    "wof:placetype":"venue"
},
  "geometry": {"coordinates":[9.645352,45.722988],"type":"Point"}
}