{
  "type": "Feature",
  "properties": {
    "iso:country":"IT",
    "sg:address":"V. Privata Cartiera 28010 Nebbiuno",
    "sg:city":"Nebbiuno",
    "sg:classifiers":[
        {
            "category":"Manufacturing",
            "subcategory":"Paper Products",
            "type":"Manufacturing & Wholesale Goods"
        }
    ],
    "sg:phone":"+39 39032258103",
    "sg:postcode":"28010",
    "sg:province":"Novara",
    "sg:tags":[
        "cardboard"
    ],
    "sg:website":"http://www.cartieranebbiuno.it:ws_end: :mark:ws:http://www.paginegialle.it/nebbiuno",
    "wof:name":"Cartiera Di Nebbiuno Srl",
    "wof:placetype":"venue"
},
  "geometry": {"coordinates":[8.6186714172,45.4450836182],"type":"Point"}
}