{
  "type": "Feature",
  "properties": {
    "iso:country":"IT",
    "sg:address":"20060 Trezzano Rosa",
    "sg:city":"Trezzano Rosa",
    "sg:orig_category":"Termotecnica E Riscaldamento, Apparecchiature E Servizi",
    "sg:phone":"+39 02 9098 1369",
    "sg:postcode":"20060",
    "sg:province":"Milano",
    "wof:name":"Tre S S.r.l.",
    "wof:placetype":"venue"
},
  "geometry": {"coordinates":[9.473927,45.586823],"type":"Point"}
}