{
  "type": "Feature",
  "properties": {
    "iso:country":"IT",
    "sg:address":"51036 Larciano",
    "sg:city":"Larciano",
    "sg:orig_category":"Articoli Pulizia. Macchine E Forniture Per Ecologia E Smaltimento Rifiuti. Forniture Per Attivita' Commerciali Ed Artigianali",
    "sg:phone":"+39 0573 83264",
    "sg:postcode":"51036",
    "sg:province":"Pistoia",
    "wof:name":"Bonfanti Sauro Snc",
    "wof:placetype":"venue"
},
  "geometry": {"coordinates":[10.879345,43.827415],"type":"Point"}
}