{
  "type": "Feature",
  "properties": {
    "iso:country":"IT",
    "sg:address":"88, Via Giuliani Reginaldo 50141 Firenze",
    "sg:city":"Firenze",
    "sg:classifiers":[
        {
            "category":"Shopping",
            "subcategory":"Clothing, Apparel, & Fashions",
            "type":"Retail Goods"
        }
    ],
    "sg:phone":"+39 39055434442",
    "sg:postcode":"50141",
    "sg:province":"Firenze",
    "sg:tags":[
        "clothing",
        "accessory"
    ],
    "wof:name":"Ema (s.n.c.)",
    "wof:placetype":"venue"
},
  "geometry": {"coordinates":[11.256902,43.768734],"type":"Point"}
}