{
  "type": "Feature",
  "properties": {
    "iso:country":"IT",
    "sg:address":"24122 Bergamo",
    "sg:city":"Bergamo",
    "sg:orig_category":"Impiantistica E Prodotti Tecnologici Per Edilizia",
    "sg:phone":"+39 035 248513",
    "sg:postcode":"24122",
    "sg:province":"Bergamo",
    "sg:website":"http://www.glanzer.it",
    "wof:name":"Glanzer Srl",
    "wof:placetype":"venue"
},
  "geometry": {"coordinates":[9.661957,45.688751],"type":"Point"}
}