{
  "type": "Feature",
  "properties": {
    "iso:country":"IT",
    "sg:address":"5, Via Udine 35035 Mestrino",
    "sg:city":"Mestrino",
    "sg:classifiers":[
        {
            "category":"Manufacturing",
            "subcategory":"Food",
            "type":"Manufacturing & Wholesale Goods"
        }
    ],
    "sg:phone":"+39 049 900 2814",
    "sg:postcode":"35035",
    "sg:province":"Padova",
    "sg:tags":[
        "equipment",
        "processing",
        "-",
        "machinery"
    ],
    "wof:name":"C.i.m. (s.r.l.)",
    "wof:placetype":"venue"
},
  "geometry": {"coordinates":[11.8245124817,45.4548606873],"type":"Point"}
}