{
  "type": "Feature",
  "properties": {
    "iso:country":"IT",
    "sg:address":"04100 Latina",
    "sg:city":"Latina",
    "sg:orig_category":"Pozzi Artesiani - Trivellazione E Manutenzione",
    "sg:phone":"+39 0773 605039",
    "sg:postcode":"04100",
    "sg:province":"Latina",
    "wof:name":"Carini Luigi - Artigiana Pozzi E Palificazioni",
    "wof:placetype":"venue"
},
  "geometry": {"coordinates":[12.8587141037,41.4559707642],"type":"Point"}
}