{
  "type": "Feature",
  "properties": {
    "iso:country":"IT",
    "sg:address":"Via Castel Goffredo 46040 Casaloldo",
    "sg:city":"Casaloldo",
    "sg:classifiers":[
        {
            "category":"Shopping",
            "subcategory":"Computers & Home Electronics",
            "type":"Retail Goods"
        }
    ],
    "sg:phone":"+39 0376 781321",
    "sg:postcode":"46040",
    "sg:province":"Mantova",
    "sg:tags":[
        "electronic",
        "electrical",
        "equipment"
    ],
    "wof:name":"Cappa Di Gandolfini Massimo E C. Snc",
    "wof:placetype":"venue"
},
  "geometry": {"coordinates":[10.477183,45.267574],"type":"Point"}
}