{
  "type": "Feature",
  "properties": {
    "addr:full":"Via Sansovino Andrea 243/65 H 10151 Torino Torino Torino 10151",
    "addr:housenumber":"243 / 65 h",
    "addr:postcode":"10151;10151",
    "addr:street":"Via Sansovino Andrea",
    "iso:country":"IT",
    "sg:address":"Via Sansovino Andrea 243/65 H 10151 Torino",
    "sg:city":"Torino",
    "sg:classifiers":[
        {
            "category":"Marine",
            "type":"Transportation"
        }
    ],
    "sg:phone":"+39 011 739 4754",
    "sg:postcode":"10151",
    "sg:province":"Torino",
    "sg:tags":[
        "diesel",
        "generator"
    ],
    "sg:website":"www.monerk.toolmec.com",
    "wof:name":"Gr Monark Diesel Di G. Bertinetti Sas",
    "wof:placetype":"venue"
},
  "geometry": {"coordinates":[7.686619,45.07056],"type":"Point"}
}