{
  "type": "Feature",
  "properties": {
    "iso:country":"IT",
    "sg:address":"24058 Romano Di Lombardia",
    "sg:city":"Romano di Lombardia",
    "sg:orig_category":"Elettrotecnica Industriale, Prodotti E Apparecchiature. Ricambi E Componenti Dei Mezzi Di Trasporto",
    "sg:phone":"+39 036 390 1981",
    "sg:postcode":"24058",
    "sg:province":"Bergamo",
    "wof:name":"O.m. Impianti Di Maggioni Osvaldo",
    "wof:placetype":"venue"
},
  "geometry": {"coordinates":[9.745404,45.528492],"type":"Point"}
}