{
  "type": "Feature",
  "properties": {
    "iso:country":"IT",
    "sg:address":"Corso Armando Diaz 9, 91026 Mazara Del Vallo, Tp",
    "sg:city":"Mazara del Vallo",
    "sg:classifiers":[
        {
            "category":"Banks & Credit Unions",
            "subcategory":"Bank",
            "type":"Services"
        }
    ],
    "sg:postcode":"91026",
    "sg:province":"Trapani",
    "wof:name":"Banca Commerciale Di Mazara Spa",
    "wof:placetype":"venue"
},
  "geometry": {"coordinates":[12.593633,37.650532],"type":"Point"}
}