{
  "type": "Feature",
  "properties": {
    "iso:country":"IT",
    "sg:address":"25010 Borgosatollo",
    "sg:city":"Borgosatollo",
    "sg:orig_category":"Riparazione Dei Mezzi Di Trasporto",
    "sg:phone":"+39 030 270 1839",
    "sg:postcode":"25010",
    "sg:province":"Brescia",
    "wof:name":"Carrozzeria Cherubini",
    "wof:placetype":"venue"
},
  "geometry": {"coordinates":[10.237979,45.470348],"type":"Point"}
}