{
  "type": "Feature",
  "properties": {
    "addr:full":"41012 Carpi Carpi Modena 41012",
    "addr:postcode":"41012;41012",
    "iso:country":"IT",
    "sg:address":"41012 Carpi",
    "sg:city":"Carpi",
    "sg:orig_category":"Abbigliamento Esterno, Maglierie E Pelliccerie",
    "sg:phone":"+39 059 654699",
    "sg:postcode":"41012",
    "sg:province":"Modena",
    "wof:name":"Gi.3 Srl",
    "wof:placetype":"venue"
},
  "geometry": {"coordinates":[10.884986,44.796265],"type":"Point"}
}