{
  "type": "Feature",
  "properties": {
    "addr:full":"7, Viale Matteotti Giacomo 50121 Firenze Firenze Firenze 50121",
    "addr:postcode":"50121;50121",
    "addr:street":"Viale Matteotti Giacomo",
    "iso:country":"IT",
    "sg:address":"7, Viale Matteotti Giacomo 50121 Firenze",
    "sg:city":"Firenze",
    "sg:classifiers":[
        {
            "category":"Travel",
            "subcategory":"Travel Agent",
            "type":"Entertainment"
        }
    ],
    "sg:phone":"+39 055 500 0631",
    "sg:postcode":"50121",
    "sg:province":"Firenze",
    "sg:tags":[
        "business"
    ],
    "wof:name":"O.i.c. Srl",
    "wof:placetype":"venue"
},
  "geometry": {"coordinates":[11.256902,43.768734],"type":"Point"}
}