{
  "type": "Feature",
  "properties": {
    "addr:full":"4, Via Mulinaccio 56020 Montopoli In Val D'arno Montopoli Pisa 56020",
    "addr:postcode":"56020;56020",
    "addr:street":"Via Mulinaccio;Val D'Arno Montopoli",
    "iso:country":"IT",
    "sg:address":"4, Via Mulinaccio 56020 Montopoli In Val D'arno",
    "sg:city":"Montopoli",
    "sg:classifiers":[
        {
            "category":"Personal",
            "subcategory":"Shoe Repair & Shine",
            "type":"Services"
        }
    ],
    "sg:phone":"+39 0571 459033",
    "sg:postcode":"56020",
    "sg:province":"Pisa",
    "sg:tags":[
        "leather"
    ],
    "wof:name":"Calzaturificio Frangia Shoe' S & C. (s.n.c.)",
    "wof:placetype":"venue"
},
  "geometry": {"coordinates":[10.760815,43.68977],"type":"Point"}
}