{
  "type": "Feature",
  "properties": {
    "iso:country":"IT",
    "sg:address":"37, Via Dandolo 97100 Ragusa",
    "sg:city":"Ragusa",
    "sg:classifiers":[
        {
            "category":"Parking",
            "subcategory":"Lot",
            "type":"Transportation"
        }
    ],
    "sg:phone":"+39 0932 239051",
    "sg:postcode":"97100",
    "sg:province":"Ragusa",
    "sg:tags":[
        "transport",
        "road"
    ],
    "wof:name":"Autotrasporti Tumino Maria Rosa & C. (s.a.s.)",
    "wof:placetype":"venue"
},
  "geometry": {"coordinates":[14.555142,36.78429],"type":"Point"}
}