{
  "type": "Feature",
  "properties": {
    "addr:full":"20063 Cernusco Sul Naviglio Cernusco sul Naviglio Milano 20063",
    "addr:postcode":"20063;20063",
    "iso:country":"IT",
    "sg:address":"20063 Cernusco Sul Naviglio",
    "sg:city":"Cernusco sul Naviglio",
    "sg:orig_category":"Macchine, Impianti E Forniture Per Industria Grafica, Cartaria E Cartotecnica",
    "sg:phone":"+39 02 9210 5800",
    "sg:postcode":"20063",
    "sg:province":"Milano",
    "wof:name":"Terzaghi E De Castiglione",
    "wof:placetype":"venue"
},
  "geometry": {"coordinates":[9.293095,45.493374],"type":"Point"}
}