{
  "type": "Feature",
  "properties": {
    "addr:full":"Via Galvani 39; Bolzano; 39100 Bolzano Bolzano/Bozen 39100",
    "addr:housenumber":"39",
    "addr:postcode":"39100;39100",
    "addr:street":"Via Galvani",
    "iso:country":"IT",
    "sg:address":"Via Galvani 39; Bolzano; 39100",
    "sg:city":"Bolzano",
    "sg:classifiers":[
        {
            "category":"Banks & Credit Unions",
            "subcategory":"Bank",
            "type":"Services"
        }
    ],
    "sg:phone":"+39 0471 935039",
    "sg:postcode":"39100",
    "sg:province":"Bolzano/Bozen",
    "wof:name":"S\u00fcdtiroler Volksbank",
    "wof:placetype":"venue"
},
  "geometry": {"coordinates":[11.329475,46.468937],"type":"Point"}
}