{
  "type": "Feature",
  "properties": {
    "iso:country":"IT",
    "sg:address":"Viale Pola 40; Ostuni; 72017",
    "sg:city":"Ostuni",
    "sg:classifiers":[
        {
            "category":"Banks & Credit Unions",
            "subcategory":"Bank",
            "type":"Services"
        }
    ],
    "sg:phone":"+39 0831 335631",
    "sg:postcode":"72017",
    "sg:province":"Brindisi",
    "wof:name":"Credito Emiliano Spa",
    "wof:placetype":"venue"
},
  "geometry": {"coordinates":[17.57592,40.727192],"type":"Point"}
}