{
  "type": "Feature",
  "properties": {
    "iso:country":"IT",
    "sg:address":"Via Zanardelli 173 25060 Marcheno",
    "sg:city":"Marcheno",
    "sg:classifiers":[
        {
            "category":"Banks & Credit Unions",
            "subcategory":"Investment Brokerage",
            "type":"Services"
        }
    ],
    "sg:phone":"+39 030 861252",
    "sg:postcode":"25060",
    "sg:province":"Brescia",
    "sg:tags":[
        "jig",
        "mechanical",
        "fixture",
        "working",
        "modular"
    ],
    "wof:name":"D'anna Faustino E Giancarlo Sas",
    "wof:placetype":"venue"
},
  "geometry": {"coordinates":[10.2107410431,45.7041625977],"type":"Point"}
}