{
  "type": "Feature",
  "properties": {
    "iso:country":"IT",
    "sg:address":"70014 Conversano",
    "sg:city":"Conversano",
    "sg:orig_category":"Macchine, Impianti Ed Attrezzature Per Agricoltura E Zootecnia. Forniture Per Agricoltura E Zootecnia",
    "sg:phone":"+39 080 495 1005",
    "sg:postcode":"70014",
    "sg:province":"Bari",
    "wof:name":"Agrizootecnica Srl",
    "wof:placetype":"venue"
},
  "geometry": {"coordinates":[17.124821,40.966057],"type":"Point"}
}