{
  "type": "Feature",
  "properties": {
    "addr:full":"Via Rogola 14 23826 Mandello Del Lario Mandello del Lario Lecco 23826",
    "addr:housenumber":"14",
    "addr:postcode":"23826;23826",
    "addr:street":"Via Rogola",
    "iso:country":"IT",
    "sg:address":"Via Rogola 14 23826 Mandello Del Lario",
    "sg:city":"Mandello del Lario",
    "sg:classifiers":[
        {
            "category":"Communications",
            "subcategory":"Film & Video Production",
            "type":"Services"
        }
    ],
    "sg:phone":"+39 0341 739511",
    "sg:postcode":"23826",
    "sg:province":"Lecco",
    "sg:tags":[
        "slitter",
        "rewinders"
    ],
    "wof:name":"Officina Meccanica Del Maglio Spa",
    "wof:placetype":"venue"
},
  "geometry": {"coordinates":[9.3168363571,45.9262542725],"type":"Point"}
}