{
  "type": "Feature",
  "properties": {
    "iso:country":"IT",
    "sg:address":"27, Via Ticino 22073 Fino Mornasco",
    "sg:city":"Fino Mornasco",
    "sg:classifiers":[
        {
            "category":"Shopping",
            "subcategory":"Clothing, Apparel, & Fashions",
            "type":"Retail Goods"
        }
    ],
    "sg:phone":"+39 39031880135",
    "sg:postcode":"22073",
    "sg:province":"Como",
    "sg:tags":[
        "clothing",
        "accessory"
    ],
    "wof:name":"Bottonificio Lariano (s.r.l.)",
    "wof:placetype":"venue"
},
  "geometry": {"coordinates":[9.055985,45.750664],"type":"Point"}
}