{
  "type": "Feature",
  "properties": {
    "iso:country":"IT",
    "sg:address":"00162 Roma",
    "sg:city":"Roma",
    "sg:orig_category":"Abbigliamento Esterno, Maglierie E Pelliccerie",
    "sg:phone":"+39 06 860 5711",
    "sg:postcode":"00162",
    "sg:province":"Roma",
    "wof:name":"Artsana Spa",
    "wof:placetype":"venue"
},
  "geometry": {"coordinates":[12.525181,41.924679],"type":"Point"}
}