{
  "type": "Feature",
  "properties": {
    "iso:country":"IT",
    "sg:address":"20020 Magnago",
    "sg:city":"Magnago",
    "sg:orig_category":"Fonderie Ghisa",
    "sg:phone":"+39 0331 307000",
    "sg:postcode":"20020",
    "sg:province":"Milano",
    "wof:name":"Focrem Spa",
    "wof:placetype":"venue"
},
  "geometry": {"coordinates":[8.8024692535,45.5792541504],"type":"Point"}
}