{
  "type": "Feature",
  "properties": {
    "addr:full":"35135 Padova Padova Padova 35135",
    "addr:postcode":"35135;35135",
    "iso:country":"IT",
    "sg:address":"35135 Padova",
    "sg:city":"Padova",
    "sg:orig_category":"Autogru - Noleggio",
    "sg:phone":"+39 049 605731",
    "sg:postcode":"35135",
    "sg:province":"Padova",
    "sg:website":"http://www.paginegialle.it/italmacer",
    "wof:name":"Italmaceri Snc Di Nicoletto & C.",
    "wof:placetype":"venue"
},
  "geometry": {"coordinates":[11.869109,45.444569],"type":"Point"}
}