{
  "type": "Feature",
  "properties": {
    "iso:country":"IT",
    "sg:address":"34015 Muggia",
    "sg:city":"Muggia",
    "sg:orig_category":"Abbigliamento Sportivo, Jeans E Casuals - Vendita Al Dettaglio",
    "sg:phone":"+39 040 275393",
    "sg:postcode":"34015",
    "sg:province":"Trieste",
    "wof:name":"Luisa Sportswear",
    "wof:placetype":"venue"
},
  "geometry": {"coordinates":[13.768436,45.603916],"type":"Point"}
}