{
  "type": "Feature",
  "properties": {
    "iso:country":"IT",
    "sg:address":"36077 Altavilla Vicentina",
    "sg:city":"Altavilla Vicentina",
    "sg:orig_category":"Metalli E Leghe",
    "sg:phone":"+39 0444 371373",
    "sg:postcode":"36077",
    "sg:province":"Vicenza",
    "wof:name":"Valinox Italia S.r.l.",
    "wof:placetype":"venue"
},
  "geometry": {"coordinates":[11.4521360397,45.507686615],"type":"Point"}
}