{
  "type": "Feature",
  "properties": {
    "iso:country":"IT",
    "sg:address":"00040 Roma",
    "sg:orig_category":"Frigotecnica, Apparecchiature E Servizi. Forniture Alle Strutture Ricettive",
    "sg:phone":"+39 06 7984 5560",
    "sg:postcode":"00040",
    "sg:province":"Roma",
    "sg:website":"http://www.italservice2000.com",
    "wof:name":"Italservice 2000 Srl",
    "wof:placetype":"venue"
},
  "geometry": {"coordinates":[12.6189231873,41.810836792],"type":"Point"}
}