{
  "type": "Feature",
  "properties": {
    "addr:full":"Via Marecchiese 47822 Santarcangelo Di Romagna Santarcangelo di Romagna Rimini 47822",
    "addr:postcode":"47822;47822",
    "addr:street":"Via Marecchiese",
    "iso:country":"IT",
    "sg:address":"Via Marecchiese 47822 Santarcangelo Di Romagna",
    "sg:city":"Santarcangelo di Romagna",
    "sg:classifiers":[
        {
            "category":"Manufacturing",
            "subcategory":"Lumber",
            "type":"Manufacturing & Wholesale Goods"
        }
    ],
    "sg:phone":"+39 0541 750288",
    "sg:postcode":"47822",
    "sg:province":"Rimini",
    "sg:tags":[
        "wood"
    ],
    "wof:name":"Montebelli & Piccari",
    "wof:placetype":"venue"
},
  "geometry": {"coordinates":[12.492471,44.037464],"type":"Point"}
}