{
  "type": "Feature",
  "properties": {
    "addr:full":"1, Strada Bauchieri 14023 Cocconato Cocconato Asti 14023",
    "addr:postcode":"14023;14023",
    "addr:street":"Strada Bauchieri",
    "iso:country":"IT",
    "sg:address":"1, Strada Bauchieri 14023 Cocconato",
    "sg:city":"Cocconato",
    "sg:classifiers":[
        {
            "category":"Shopping",
            "subcategory":"Clothing, Apparel, & Fashions",
            "type":"Retail Goods"
        }
    ],
    "sg:phone":"+39 0141 907555",
    "sg:postcode":"14023",
    "sg:province":"Asti",
    "sg:tags":[
        "clothes"
    ],
    "wof:name":"Conbipel",
    "wof:placetype":"venue"
},
  "geometry": {"coordinates":[8.062721,45.079231],"type":"Point"}
}