{
  "type": "Feature",
  "properties": {
    "addr:full":"Via Della Tecnica, 21/23 36075 Montecchio Maggiore Montecchio Maggiore Vicenza 36075",
    "addr:housenumber":"21 / 23",
    "addr:postcode":"36075;36075",
    "addr:street":"Via Della Tecnica",
    "iso:country":"IT",
    "sg:address":"Via Della Tecnica, 21/23 36075 Montecchio Maggiore",
    "sg:city":"Montecchio Maggiore",
    "sg:classifiers":[
        {
            "category":"Manufacturing",
            "subcategory":"Rubber & Plastics",
            "type":"Manufacturing & Wholesale Goods"
        }
    ],
    "sg:phone":"+39 0444 706311",
    "sg:postcode":"36075",
    "sg:province":"Vicenza",
    "sg:tags":[
        "processing"
    ],
    "sg:website":"www.gamm.com",
    "wof:name":"Gamm Srl",
    "wof:placetype":"venue"
},
  "geometry": {"coordinates":[11.4514255524,45.5237464905],"type":"Point"}
}