{
  "type": "Feature",
  "properties": {
    "addr:full":"20143 Milano Milano Milano 20143",
    "addr:postcode":"20143;20143",
    "iso:country":"IT",
    "sg:address":"20143 Milano",
    "sg:city":"Milano",
    "sg:orig_category":"Materiali Semilavorati Metallici",
    "sg:phone":"+39 02 8915 5314",
    "sg:postcode":"20143",
    "sg:province":"Milano",
    "wof:name":"Tempracciaio Srl",
    "wof:placetype":"venue"
},
  "geometry": {"coordinates":[9.15186,45.443844],"type":"Point"}
}