{
  "type": "Feature",
  "properties": {
    "iso:country":"IT",
    "sg:address":"3, Via Nuova Valassina 23845 Costa Masnaga",
    "sg:city":"Costa Masnaga",
    "sg:classifiers":[
        {
            "category":"Manufacturing",
            "subcategory":"Rubber & Plastics",
            "type":"Manufacturing & Wholesale Goods"
        }
    ],
    "sg:phone":"+39 39031855051",
    "sg:postcode":"23845",
    "sg:province":"Lecco",
    "wof:name":"Puricelli (s.r.l.)",
    "wof:placetype":"venue"
},
  "geometry": {"coordinates":[9.287817955,45.7675704956],"type":"Point"}
}