{
  "type": "Feature",
  "properties": {
    "addr:full":"25034 Orzinuovi Orzinuovi Brescia 25034",
    "addr:postcode":"25034;25034",
    "iso:country":"IT",
    "sg:address":"25034 Orzinuovi",
    "sg:city":"Orzinuovi",
    "sg:orig_category":"Automazione E Macchine Per Ufficio",
    "sg:phone":"+39 030 941792",
    "sg:postcode":"25034",
    "sg:province":"Brescia",
    "wof:name":"Bonzi Palma Aurora",
    "wof:placetype":"venue"
},
  "geometry": {"coordinates":[10.227032,45.522232],"type":"Point"}
}