{
  "type": "Feature",
  "properties": {
    "addr:full":"00047 Marino Marino Roma 00047",
    "addr:postcode":"00047;00047",
    "addr:street":"Marino Roma",
    "iso:country":"IT",
    "sg:address":"00047 Marino",
    "sg:city":"Marino",
    "sg:orig_category":"Scuole E Servizi Scolastici",
    "sg:phone":"+39 06 931 1300",
    "sg:postcode":"00047",
    "sg:province":"Roma",
    "wof:name":"Scuola Elementare",
    "wof:placetype":"venue"
},
  "geometry": {"coordinates":[12.621723,41.744122],"type":"Point"}
}