{
  "type": "Feature",
  "properties": {
    "addr:full":"20123 Milano Milano Milano 20123",
    "addr:postcode":"20123;20123",
    "iso:country":"IT",
    "sg:address":"20123 Milano",
    "sg:city":"Milano",
    "sg:orig_category":"Ospedali E Servizi Sanitari",
    "sg:phone":"+39 02 878200",
    "sg:postcode":"20123",
    "sg:province":"Milano",
    "wof:name":"Adec - Assistenza Dentistica - Cure Odontoiatriche",
    "wof:placetype":"venue"
},
  "geometry": {"coordinates":[9.177111,45.45919],"type":"Point"}
}