{
  "type": "Feature",
  "properties": {
    "iso:country":"IT",
    "sg:address":"16/a, Via Ossaia 52044 Cortona",
    "sg:city":"Cortona",
    "sg:classifiers":[
        {
            "category":"Food & Beverages",
            "subcategory":"Groceries & Convenience Stores",
            "type":"Retail Goods"
        }
    ],
    "sg:phone":"+39 0575 677877",
    "sg:postcode":"52044",
    "sg:province":"Arezzo",
    "sg:tags":[
        "product",
        "related"
    ],
    "wof:name":"Eu - Meat (s.r.l.)",
    "wof:placetype":"venue"
},
  "geometry": {"coordinates":[11.8630619049,43.4712028503],"type":"Point"}
}