{
  "type": "Feature",
  "properties": {
    "addr:full":"50065 Pontassieve Montebonello Firenze 50065",
    "addr:postcode":"50065;50065",
    "addr:street":"Montebonello",
    "iso:country":"IT",
    "sg:address":"50065 Pontassieve",
    "sg:city":"Montebonello",
    "sg:orig_category":"Materiali E Componenti Elettrotecnici. Elettrotecnica Industriale, Prodotti E Apparecchiature",
    "sg:phone":"+39 055 839 7529",
    "sg:postcode":"50065",
    "sg:province":"Firenze",
    "wof:name":"Fashion Lamp Di Dugini Massimo E Dugini Roberto Snc",
    "wof:placetype":"venue"
},
  "geometry": {"coordinates":[11.486668,43.830692],"type":"Point"}
}