{
  "type": "Feature",
  "properties": {
    "iso:country":"IT",
    "sg:address":"37135 Verona",
    "sg:city":"Verona",
    "sg:orig_category":"Prodotti Chimici Secondari",
    "sg:phone":"+39 045 501821",
    "sg:postcode":"37135",
    "sg:province":"Verona",
    "wof:name":"Coversol (s.n.c.)",
    "wof:placetype":"venue"
},
  "geometry": {"coordinates":[10.9832515717,45.4004707336],"type":"Point"}
}