{
  "type": "Feature",
  "properties": {
    "iso:country":"IT",
    "sg:address":"75, Via Pedulla' 16165 Genova",
    "sg:city":"Genova",
    "sg:classifiers":[
        {
            "category":"Building & Trades",
            "subcategory":"Construction",
            "type":"Services"
        }
    ],
    "sg:phone":"+39 010 830 1291",
    "sg:postcode":"16165",
    "sg:province":"Genova",
    "sg:tags":[
        "work",
        "public"
    ],
    "wof:name":"Tagliafico Santo (s.n.c.)",
    "wof:placetype":"venue"
},
  "geometry": {"coordinates":[9.003443,44.446999],"type":"Point"}
}