{
  "type": "Feature",
  "properties": {
    "iso:country":"IT",
    "sg:address":"20090 Assago",
    "sg:city":"Assago",
    "sg:orig_category":"Agenzie D'affari E Servizi Commerciali",
    "sg:phone":"+39 02 825 3902",
    "sg:postcode":"20090",
    "sg:province":"Milano",
    "wof:name":"Uniserve Consorzio Servizi Integrati",
    "wof:placetype":"venue"
},
  "geometry": {"coordinates":[9.148091,45.403061],"type":"Point"}
}