{
  "type": "Feature",
  "properties": {
    "iso:country":"IT",
    "sg:address":"125, Via Roma 30020 Pramaggiore",
    "sg:city":"Pramaggiore",
    "sg:classifiers":[
        {
            "category":"Professional",
            "subcategory":"Engineering",
            "type":"Services"
        }
    ],
    "sg:phone":"+39 0421 799851",
    "sg:postcode":"30020",
    "sg:province":"Venezia",
    "sg:tags":[
        "machine",
        "-",
        "mechanical"
    ],
    "wof:name":"M.v.o. Meccanica (s.r.l.)",
    "wof:placetype":"venue"
},
  "geometry": {"coordinates":[12.749699,45.819988],"type":"Point"}
}