{
  "type": "Feature",
  "properties": {
    "iso:country":"IT",
    "sg:address":"52044 Cortona",
    "sg:city":"Camucia",
    "sg:orig_category":"Prodotti Finiti Stampati. Forniture E Prodotti Informatici. Forniture Per Uffici",
    "sg:phone":"+39 0575 678282",
    "sg:postcode":"52044",
    "sg:province":"Arezzo",
    "wof:name":"Grafiche Calosci Di Calosci Giuseppe & C. Snc",
    "wof:placetype":"venue"
},
  "geometry": {"coordinates":[11.9885835648,43.2438087463],"type":"Point"}
}