{
  "type": "Feature",
  "properties": {
    "iso:country":"IT",
    "sg:address":"Via Nizza 20 37121 Verona",
    "sg:city":"Verona",
    "sg:classifiers":[
        {
            "category":"Banks & Credit Unions",
            "subcategory":"Investment Brokerage",
            "type":"Services"
        }
    ],
    "sg:phone":"+39 045 801 1494",
    "sg:postcode":"37121",
    "sg:province":"Verona",
    "sg:tags":[
        "good",
        "agency",
        "domestic",
        "foreign",
        "raw",
        "materials",
        "broking",
        "machines"
    ],
    "wof:name":"Sicom Italia Societe' Internationale Du Commerce Srl",
    "wof:placetype":"venue"
},
  "geometry": {"coordinates":[11.000377,45.442558],"type":"Point"}
}