{
  "type": "Feature",
  "properties": {
    "iso:country":"IT",
    "sg:address":"86039 Termoli",
    "sg:city":"Termoli",
    "sg:orig_category":"Articoli Da Regalo. Tempo Libero - Articoli E Forniture. Regalistica Aziendale",
    "sg:phone":"+39 0875 703690",
    "sg:postcode":"86039",
    "sg:province":"Campobasso",
    "sg:website":"http://www.bdgsegni.it",
    "wof:name":"Bdg Segni Di De Gregorio Basso Mauro",
    "wof:placetype":"venue"
},
  "geometry": {"coordinates":[14.997303,41.962578],"type":"Point"}
}