{
  "type": "Feature",
  "properties": {
    "addr:full":"00177 Roma Roma Roma 00177",
    "addr:postcode":"00177;00177",
    "iso:country":"IT",
    "sg:address":"00177 Roma",
    "sg:city":"Roma",
    "sg:orig_category":"Carni, Salumi E Pesci",
    "sg:phone":"+39 06 259 3423",
    "sg:postcode":"00177",
    "sg:province":"Roma",
    "wof:name":"Aloisi Daniele",
    "wof:placetype":"venue"
},
  "geometry": {"coordinates":[12.556368,41.896736],"type":"Point"}
}