{
  "type": "Feature",
  "properties": {
    "addr:full":"Vocabolo Mandrelle 06050 Collazzone Collazzone Perugia 06050",
    "addr:postcode":"06050;06050",
    "addr:street":"Vocabolo Mandrelle",
    "iso:country":"IT",
    "sg:address":"Vocabolo Mandrelle 06050 Collazzone",
    "sg:city":"Collazzone",
    "sg:classifiers":[
        {
            "category":"Professional",
            "subcategory":"Printing & Photocopies",
            "type":"Services"
        }
    ],
    "sg:phone":"+39 075 878 8004",
    "sg:postcode":"06050",
    "sg:province":"Perugia",
    "wof:name":"Grilligraf Snc Di Grilli Giancarlo E C.",
    "wof:placetype":"venue"
},
  "geometry": {"coordinates":[12.3891716003,43.1107025146],"type":"Point"}
}