{
  "type": "Feature",
  "properties": {
    "addr:full":"00124 Roma Roma Roma 00124",
    "addr:postcode":"00124;00124",
    "iso:country":"IT",
    "sg:address":"00124 Roma",
    "sg:city":"Roma",
    "sg:classifiers":[
        {
            "category":"Travel",
            "subcategory":"Hotels & Motels",
            "type":"Entertainment"
        }
    ],
    "sg:phone":"+39 06 5091 4880",
    "sg:postcode":"00124",
    "sg:province":"Roma",
    "sg:tags":[
        "hotels",
        "facility"
    ],
    "wof:name":"Il Casale B&b",
    "wof:placetype":"venue"
},
  "geometry": {"coordinates":[12.351558,41.737259],"type":"Point"}
}