{
  "type": "Feature",
  "properties": {
    "iso:country":"IT",
    "sg:address":"35010 Carmignano Di Brenta",
    "sg:city":"Carmignano di Brenta",
    "sg:classifiers":[
        {
            "category":"Shopping",
            "subcategory":"Clothing, Apparel, & Fashions",
            "type":"Retail Goods"
        }
    ],
    "sg:phone":"+39 049 595 7134",
    "sg:postcode":"35010",
    "sg:province":"Padova",
    "sg:tags":[
        "clothing",
        "fur",
        "knitwear"
    ],
    "sg:website":"http://www.lindosconfezioni.com",
    "wof:name":"Lindos Confezioni Srl",
    "wof:placetype":"venue"
},
  "geometry": {"coordinates":[11.706972,45.630226],"type":"Point"}
}