{
  "type": "Feature",
  "properties": {
    "iso:country":"IT",
    "sg:address":"06049 Spoleto",
    "sg:city":"Spoleto",
    "sg:orig_category":"Macchine, Impianti Ed Attrezzature Per Industria Alimentare E Bevande",
    "sg:phone":"+39 0743 223228",
    "sg:postcode":"06049",
    "sg:province":"Perugia",
    "wof:name":"Cooperativa Macellatori Spoleto Soc. Coop. A R.l.",
    "wof:placetype":"venue"
},
  "geometry": {"coordinates":[12.391492,43.100075],"type":"Point"}
}