{
  "type": "Feature",
  "properties": {
    "iso:country":"IT",
    "sg:address":"46041 Asola",
    "sg:city":"Asola",
    "sg:classifiers":[
        {
            "category":"Manufacturing",
            "subcategory":"Furniture",
            "type":"Manufacturing & Wholesale Goods"
        }
    ],
    "sg:phone":"+39 0376 712062",
    "sg:postcode":"46041",
    "sg:province":"Mantova",
    "sg:tags":[
        "wood",
        "industry",
        "work",
        "furnishing"
    ],
    "wof:name":"Piazza Luciano - Artepura",
    "wof:placetype":"venue"
},
  "geometry": {"coordinates":[10.4377231598,45.2173194885],"type":"Point"}
}