{
  "type": "Feature",
  "properties": {
    "iso:country":"IT",
    "sg:address":"15, Via Luigi Galvani 31027 Spresiano",
    "sg:city":"Spresiano",
    "sg:classifiers":[
        {
            "category":"Manufacturing",
            "subcategory":"Tools & Machinery",
            "type":"Manufacturing & Wholesale Goods"
        }
    ],
    "sg:phone":"+39 390 422 7268",
    "sg:postcode":"31027",
    "sg:province":"Treviso",
    "sg:tags":[
        "environment",
        "equipment",
        "-"
    ],
    "wof:name":"Contarina S.p.a.",
    "wof:placetype":"venue"
},
  "geometry": {"coordinates":[12.242072,45.666286],"type":"Point"}
}