{
  "type": "Feature",
  "properties": {
    "iso:country":"IT",
    "sg:address":"Via Cesare Battisti 64 35010 Limena",
    "sg:city":"Limena",
    "sg:classifiers":[
        {
            "category":"Manufacturing",
            "subcategory":"Metals",
            "type":"Manufacturing & Wholesale Goods"
        }
    ],
    "sg:phone":"+39 049 767843",
    "sg:postcode":"35010",
    "sg:province":"Padova",
    "sg:tags":[
        "mould",
        "aluminium",
        "industry",
        "plastic"
    ],
    "wof:name":"Omba Snc",
    "wof:placetype":"venue"
},
  "geometry": {"coordinates":[11.843071,45.467411],"type":"Point"}
}