{
  "type": "Feature",
  "properties": {
    "iso:country":"IT",
    "sg:address":"03011 Alatri",
    "sg:city":"Alatri",
    "sg:orig_category":"Abbigliamento Esterno, Maglierie E Pelliccerie. Forniture Industriali Per Prevenzione, Controllo E Sicurezza",
    "sg:phone":"+39 0775 408929",
    "sg:postcode":"03011",
    "sg:province":"Frosinone",
    "wof:name":"Geval Srl Divisione Antincendio",
    "wof:placetype":"venue"
},
  "geometry": {"coordinates":[13.344282,41.659046],"type":"Point"}
}