{
  "type": "Feature",
  "properties": {
    "iso:country":"IT",
    "sg:address":"4, Via Rivara 10070 Levone",
    "sg:city":"Levone",
    "sg:classifiers":[
        {
            "category":"Professional",
            "subcategory":"Engineering",
            "type":"Services"
        }
    ],
    "sg:phone":"+39 0124 306151",
    "sg:postcode":"10070",
    "sg:province":"Torino",
    "sg:tags":[
        "machine",
        "-",
        "mechanical"
    ],
    "wof:name":"B.p. S.a.s",
    "wof:placetype":"venue"
},
  "geometry": {"coordinates":[7.609336,45.317078],"type":"Point"}
}