{
  "type": "Feature",
  "properties": {
    "iso:country":"IT",
    "sg:address":"191, Localita' Ornellaia-bolgheri 57022 Castagneto Carducci",
    "sg:city":"Bolgheri",
    "sg:classifiers":[
        {
            "category":"Food & Beverages",
            "subcategory":"Groceries & Convenience Stores",
            "type":"Retail Goods"
        }
    ],
    "sg:phone":"+39 39056571811",
    "sg:postcode":"57022",
    "sg:province":"Livorno",
    "sg:tags":[
        "drink"
    ],
    "wof:name":"Ornellaia S.p.a.",
    "wof:placetype":"venue"
},
  "geometry": {"coordinates":[10.308011,43.551876],"type":"Point"}
}