{
  "type": "Feature",
  "properties": {
    "iso:country":"IT",
    "sg:address":"25058 Sulzano",
    "sg:city":"Sulzano",
    "sg:orig_category":"Apparecchiature Ed Attrezzature Meccaniche",
    "sg:phone":"+39 030 985224",
    "sg:postcode":"25058",
    "sg:province":"Brescia",
    "wof:name":"Corderia Bresciana Snc",
    "wof:placetype":"venue"
},
  "geometry": {"coordinates":[10.240464,45.585495],"type":"Point"}
}