{
  "type": "Feature",
  "properties": {
    "iso:country":"IT",
    "sg:address":"129, Via Casalbarbato 43012 Fontanellato",
    "sg:city":"Fontanellato",
    "sg:classifiers":[
        {
            "category":"Professional",
            "subcategory":"Engineering",
            "type":"Services"
        }
    ],
    "sg:phone":"+39 0521 825110",
    "sg:postcode":"43012",
    "sg:province":"Parma",
    "sg:tags":[
        "machine",
        "-",
        "mechanical"
    ],
    "wof:name":"Ghirarduzzi (s.n.c.)",
    "wof:placetype":"venue"
},
  "geometry": {"coordinates":[10.144189,44.865223],"type":"Point"}
}