{
  "type": "Feature",
  "properties": {
    "addr:full":"483, Via Bacchereto 59015 Carmignano Carmignano Prato 59015",
    "addr:housenumber":"483",
    "addr:postcode":"59015;59015",
    "addr:street":"Via Bacchereto",
    "iso:country":"IT",
    "sg:address":"483, Via Bacchereto 59015 Carmignano",
    "sg:city":"Carmignano",
    "sg:classifiers":[
        {
            "category":"Shopping",
            "subcategory":"Clothing, Apparel, & Fashions",
            "type":"Retail Goods"
        }
    ],
    "sg:phone":"+39 055 870 5471",
    "sg:postcode":"59015",
    "sg:province":"Prato",
    "sg:tags":[
        "clothes"
    ],
    "wof:name":"Maglificio Pratesi Gianfranco E Figlie",
    "wof:placetype":"venue"
},
  "geometry": {"coordinates":[11.096313,43.8797],"type":"Point"}
}