{
  "type": "Feature",
  "properties": {
    "iso:country":"IT",
    "sg:address":"Via V. Veneto 45 21010 Golasecca",
    "sg:city":"Golasecca",
    "sg:classifiers":[
        {
            "category":"Arena",
            "subcategory":"Sports Club",
            "type":"Entertainment"
        }
    ],
    "sg:phone":"+39 0331 958506",
    "sg:postcode":"21010",
    "sg:province":"Varese",
    "sg:tags":[
        "slicer"
    ],
    "sg:website":"www.dampa.it",
    "wof:name":"Dampa Srl",
    "wof:placetype":"venue"
},
  "geometry": {"coordinates":[8.826385,45.817604],"type":"Point"}
}