{
  "type": "Feature",
  "properties": {
    "iso:country":"IT",
    "sg:address":"Corso Italia 20020 Vanzaghello",
    "sg:city":"Vanzaghello",
    "sg:classifiers":[
        {
            "category":"Utilities",
            "subcategory":"Electric",
            "type":"Services"
        }
    ],
    "sg:phone":"+39 0331 659965",
    "sg:postcode":"20020",
    "sg:province":"Milano",
    "sg:tags":[
        "component",
        "electronic"
    ],
    "wof:name":"Martignoni Elettrotecnica Srl",
    "wof:placetype":"venue"
},
  "geometry": {"coordinates":[8.792351,45.597187],"type":"Point"}
}