{
  "type": "Feature",
  "properties": {
    "iso:country":"IT",
    "sg:address":"16124 Genova",
    "sg:city":"Genova",
    "sg:orig_category":"Trasporti E Spedizioni Merci",
    "sg:phone":"+39 010 248 8211",
    "sg:postcode":"16124",
    "sg:province":"Genova",
    "sg:website":"http://www.gdtlogistic.com",
    "wof:name":"Gdt Logistic Srl",
    "wof:placetype":"venue"
},
  "geometry": {"coordinates":[8.929835,44.410709],"type":"Point"}
}