{
  "type": "Feature",
  "properties": {
    "addr:full":"07029 Tempio Pausania Tempio Pausania Olbia-Tempio 07029",
    "addr:postcode":"07029;07029",
    "iso:country":"IT",
    "sg:address":"07029 Tempio Pausania",
    "sg:city":"Tempio Pausania",
    "sg:orig_category":"Pubblica Amministrazione",
    "sg:phone":"+39 079 632250",
    "sg:postcode":"07029",
    "sg:province":"Olbia-Tempio",
    "wof:name":"Uffici Giudiziari",
    "wof:placetype":"venue"
},
  "geometry": {"coordinates":[9.1234798431,40.8994483948],"type":"Point"}
}