{
  "type": "Feature",
  "properties": {
    "iso:country":"IT",
    "sg:address":"09170 Oristano",
    "sg:city":"Oristano",
    "sg:orig_category":"Petroli, Gas E Combustibili. Materiali Edili",
    "sg:phone":"+39 0783 359273",
    "sg:postcode":"09170",
    "sg:province":"Oristano",
    "wof:name":"Conglomerati Bituminosi Srl",
    "wof:placetype":"venue"
},
  "geometry": {"coordinates":[8.5916900635,39.9008255005],"type":"Point"}
}