{
  "type": "Feature",
  "properties": {
    "iso:country":"IT",
    "sg:address":"33037 Pasian Di Prato",
    "sg:city":"Pasian di Prato",
    "sg:classifiers":[
        {
            "category":"Wholesale",
            "subcategory":"Auto Parts",
            "type":"Manufacturing & Wholesale Goods"
        }
    ],
    "sg:phone":"+39 0432 400379",
    "sg:postcode":"33037",
    "sg:province":"Udine",
    "sg:tags":[
        "product",
        "industrial",
        "vehicles",
        "component",
        "equipment",
        "engineering",
        "electrical",
        "motor",
        "spare"
    ],
    "wof:name":"Ceconi Roberto",
    "wof:placetype":"venue"
},
  "geometry": {"coordinates":[13.182693,46.089756],"type":"Point"}
}