{
  "type": "Feature",
  "properties": {
    "iso:country":"IT",
    "sg:address":"33084 Cordenons",
    "sg:city":"Cordenons",
    "sg:orig_category":"Autosoccorso",
    "sg:phone":"+39 0434 43552",
    "sg:postcode":"33084",
    "sg:province":"Pordenone",
    "wof:name":"Carrozzeria 'la Meduna' Dei F.lli Gumiero Sas",
    "wof:placetype":"venue"
},
  "geometry": {"coordinates":[12.70466,45.961018],"type":"Point"}
}