{
  "type": "Feature",
  "properties": {
    "addr:full":"70125 Bari Bari Bari 70125",
    "addr:postcode":"70125;70125",
    "iso:country":"IT",
    "sg:address":"70125 Bari",
    "sg:city":"Bari",
    "sg:classifiers":[
        {
            "category":"Education",
            "subcategory":"School",
            "type":"Public Place"
        }
    ],
    "sg:phone":"+39 080 552 1015",
    "sg:postcode":"70125",
    "sg:province":"Bari",
    "sg:tags":[
        "scuole",
        "informatica",
        "di"
    ],
    "sg:website":"http://151.22.151.53",
    "wof:name":"Scuola Tre Dell'ing. Giulio Volpetti",
    "wof:placetype":"venue"
},
  "geometry": {"coordinates":[16.879791,41.088921],"type":"Point"}
}