{
  "type": "Feature",
  "properties": {
    "iso:country":"IT",
    "sg:address":"95036 Randazzo",
    "sg:city":"Randazzo",
    "sg:orig_category":"Emittenti Radiotelevisive",
    "sg:phone":"+39 095 923638",
    "sg:postcode":"95036",
    "sg:province":"Catania",
    "wof:name":"Radio Veronica",
    "wof:placetype":"venue"
},
  "geometry": {"coordinates":[14.943116,37.87709],"type":"Point"}
}