{
  "type": "Feature",
  "properties": {
    "iso:country":"IT",
    "sg:address":"30030 Pianiga",
    "sg:city":"Pianiga",
    "sg:orig_category":"Macchine Utensili - Produzione",
    "sg:phone":"+39 041 519 0346",
    "sg:postcode":"30030",
    "sg:province":"Venezia",
    "wof:name":"Wintech Srl",
    "wof:placetype":"venue"
},
  "geometry": {"coordinates":[11.990739,45.453754],"type":"Point"}
}