{
  "type": "Feature",
  "properties": {
    "iso:country":"IT",
    "sg:address":"80013 Casalnuovo Di Napoli",
    "sg:city":"Casalnuovo di Napoli",
    "sg:orig_category":"Farmacie",
    "sg:phone":"+39 081 842 3601",
    "sg:postcode":"80013",
    "sg:province":"Napoli",
    "wof:name":"Farmacia Cicchelli Dr. Vincenzo",
    "wof:placetype":"venue"
},
  "geometry": {"coordinates":[14.3438205719,40.9121055603],"type":"Point"}
}