{
  "type": "Feature",
  "properties": {
    "iso:country":"IT",
    "sg:address":"41011 Campogalliano",
    "sg:city":"Campogalliano",
    "sg:orig_category":"Macchine, Impianti Ed Attrezzature Per Industria Alimentare E Bevande",
    "sg:phone":"+39 059 527602",
    "sg:postcode":"41011",
    "sg:province":"Modena",
    "wof:name":"Balboni Inox (s.n.c.)",
    "wof:placetype":"venue"
},
  "geometry": {"coordinates":[10.846389,44.694439],"type":"Point"}
}