{
  "type": "Feature",
  "properties": {
    "addr:full":"00040 Pomezia Pomezia Roma 00040",
    "addr:postcode":"00040;roma 00040",
    "iso:country":"IT",
    "sg:address":"00040 Pomezia",
    "sg:city":"Pomezia",
    "sg:orig_category":"Macchine, Impianti Ed Attrezzature Industria Chimica",
    "sg:phone":"+39 06 9162 4014",
    "sg:postcode":"00040",
    "sg:province":"Roma",
    "wof:name":"S.m.a.t. Srl",
    "wof:placetype":"venue"
},
  "geometry": {"coordinates":[12.495704,41.688133],"type":"Point"}
}