{
  "type": "Feature",
  "properties": {
    "iso:country":"IT",
    "sg:address":"53100 Siena",
    "sg:city":"Siena",
    "sg:orig_category":"Prodotti Di Base E Forniture Per Industria Alimentare E Bevande. Carta, Cartone E Prodotti Primari. Forniture Per Attivita' Commerciali Ed Artigianali",
    "sg:phone":"+39 0577 223155",
    "sg:postcode":"53100",
    "sg:province":"Siena",
    "wof:name":"La Cartalimentari",
    "wof:placetype":"venue"
},
  "geometry": {"coordinates":[11.3082447052,43.3139266968],"type":"Point"}
}