{
  "type": "Feature",
  "properties": {
    "iso:country":"IT",
    "sg:address":"64023 Mosciano Sant'angelo",
    "sg:orig_category":"Termotecnica E Riscaldamento, Apparecchiature E Servizi",
    "sg:phone":"+39 085 807 2070",
    "sg:postcode":"64023",
    "sg:province":"Teramo",
    "wof:name":"Metal Com",
    "wof:placetype":"venue"
},
  "geometry": {"coordinates":[13.879601,42.742374],"type":"Point"}
}