{
  "type": "Feature",
  "properties": {
    "addr:full":"20019 Settimo Milanese Settimo Milanese Milano 20019",
    "addr:postcode":"20019;20019",
    "iso:country":"IT",
    "sg:address":"20019 Settimo Milanese",
    "sg:city":"Settimo Milanese",
    "sg:orig_category":"Servizi Ausiliari Dei Mezzi Di Trasporto",
    "sg:phone":"+39 02 3350 1797",
    "sg:postcode":"20019",
    "sg:province":"Milano",
    "wof:name":"Ferwash Sas",
    "wof:placetype":"venue"
},
  "geometry": {"coordinates":[9.056232,45.463234],"type":"Point"}
}