{
  "type": "Feature",
  "properties": {
    "addr:full":"00122 Lido Di Ostia Roma 00122",
    "addr:postcode":"00122;00122",
    "addr:street":"Di Ostia Roma",
    "iso:country":"IT",
    "sg:address":"00122 Lido Di Ostia",
    "sg:orig_category":"Servizi E Lavori Per Abbigliamento E Pelletterie",
    "sg:phone":"+39 06 568 0658",
    "sg:postcode":"00122",
    "sg:province":"Roma",
    "wof:name":"Buonerba Irene",
    "wof:placetype":"venue"
},
  "geometry": {"coordinates":[12.292094,41.732632],"type":"Point"}
}