{
  "type": "Feature",
  "properties": {
    "addr:full":"159, Via Emilia Romagna 47841 Cattolica Cattolica Rimini 47841",
    "addr:housenumber":"159",
    "addr:postcode":"47841;47841",
    "addr:street":"Via Emilia Romagna",
    "iso:country":"IT",
    "sg:address":"159, Via Emilia Romagna 47841 Cattolica",
    "sg:city":"Cattolica",
    "sg:classifiers":[
        {
            "category":"Food & Beverages",
            "subcategory":"Groceries & Convenience Stores",
            "type":"Retail Goods"
        }
    ],
    "sg:phone":"+39 0541 952219",
    "sg:postcode":"47841",
    "sg:province":"Rimini",
    "sg:tags":[
        "product",
        "related"
    ],
    "wof:name":"B. Quadrifoglio 2 Centro Forniture Alimentari",
    "wof:placetype":"venue"
},
  "geometry": {"coordinates":[12.7276754379,43.9638290405],"type":"Point"}
}