{
  "type": "Feature",
  "properties": {
    "iso:country":"IT",
    "sg:address":"20146 Milano",
    "sg:city":"Milano",
    "sg:orig_category":"Servizi E Lavori Per Abbigliamento E Pelletterie",
    "sg:phone":"+39 02 498 6043",
    "sg:postcode":"20146",
    "sg:province":"Milano",
    "wof:name":"Lavasecco Moro Di Moro Cosimo",
    "wof:placetype":"venue"
},
  "geometry": {"coordinates":[9.1546278,45.4583244324],"type":"Point"}
}