{
  "type": "Feature",
  "properties": {
    "iso:country":"IT",
    "sg:address":"20131 Milano",
    "sg:city":"Milano",
    "sg:orig_category":"Pelliccerie",
    "sg:phone":"+39 02 2951 2575",
    "sg:postcode":"20131",
    "sg:province":"Milano",
    "wof:name":"Lualdi Cesare Pellicceria Lualdi",
    "wof:placetype":"venue"
},
  "geometry": {"coordinates":[9.2154026031,45.4844512939],"type":"Point"}
}