{
  "type": "Feature",
  "properties": {
    "iso:country":"IT",
    "sg:address":"00144 Roma",
    "sg:city":"Roma",
    "sg:orig_category":"Banche E Servizi Finanziari",
    "sg:phone":"+39 06 592 4116",
    "sg:postcode":"00144",
    "sg:province":"Roma",
    "wof:name":"Unicredit Factoring Spa",
    "wof:placetype":"venue"
},
  "geometry": {"coordinates":[12.473852,41.836185],"type":"Point"}
}