{
  "type": "Feature",
  "properties": {
    "iso:country":"IT",
    "sg:address":"21055 Gorla Minore",
    "sg:city":"Gorla Minore",
    "sg:orig_category":"Prodotti E Manufatti In Materie Plastiche",
    "sg:phone":"+39 0331 602358",
    "sg:postcode":"21055",
    "sg:province":"Varese",
    "wof:name":"Tecplast (s.r.l.)",
    "wof:placetype":"venue"
},
  "geometry": {"coordinates":[8.8274421692,45.8173522949],"type":"Point"}
}