{
  "type": "Feature",
  "properties": {
    "iso:country":"IT",
    "sg:address":"06059 Todi",
    "sg:city":"Pantalla",
    "sg:classifiers":[
        {
            "category":"Communications",
            "subcategory":"Film & Video Production",
            "type":"Services"
        }
    ],
    "sg:phone":"+39 075 88551",
    "sg:postcode":"06059",
    "sg:province":"Perugia",
    "sg:tags":[
        "semi-finished",
        "materials",
        "metal"
    ],
    "sg:website":"http://www.elcomsystem.it",
    "wof:name":"Elcom System Spa",
    "wof:placetype":"venue"
},
  "geometry": {"coordinates":[12.4003143311,42.8742408752],"type":"Point"}
}