{
  "type": "Feature",
  "properties": {
    "iso:country":"IT",
    "sg:address":"39011 Lana",
    "sg:city":"Lana",
    "sg:orig_category":"Citofoni, Interfonici E Videocitofoni",
    "sg:phone":"+39 0473 559977",
    "sg:postcode":"39011",
    "sg:province":"Bolzano/Bozen",
    "wof:name":"Telmekom Kg - Sas Di Robert Reiterer E Co.",
    "wof:placetype":"venue"
},
  "geometry": {"coordinates":[11.169078,46.612309],"type":"Point"}
}