{
  "type": "Feature",
  "properties": {
    "iso:country":"IT",
    "sg:address":"03023 Ceccano",
    "sg:city":"Ceccano",
    "sg:orig_category":"Macchine, Impianti Ed Attrezzature Industria Chimica",
    "sg:phone":"+39 0775 640106",
    "sg:postcode":"03023",
    "sg:province":"Frosinone",
    "wof:name":"Tecnolchi Srl",
    "wof:placetype":"venue"
},
  "geometry": {"coordinates":[13.296539,41.607273],"type":"Point"}
}