{
  "type": "Feature",
  "properties": {
    "addr:full":"20064 Gorgonzola Gorgonzola Milano 20064",
    "addr:postcode":"20064;20064",
    "iso:country":"IT",
    "sg:address":"20064 Gorgonzola",
    "sg:city":"Gorgonzola",
    "sg:orig_category":"Arti Grafiche",
    "sg:phone":"+39 02 9530 2760",
    "sg:postcode":"20064",
    "sg:province":"Milano",
    "sg:website":"http://space.tin.it/computer/simeschi",
    "wof:name":"Eurografiche Srl",
    "wof:placetype":"venue"
},
  "geometry": {"coordinates":[9.402266,45.523983],"type":"Point"}
}