{
  "type": "Feature",
  "properties": {
    "iso:country":"IT",
    "sg:address":"Via Nazionale 242; Mira; 30034",
    "sg:city":"Mira",
    "sg:classifiers":[
        {
            "category":"Banks & Credit Unions",
            "subcategory":"Bank",
            "type":"Services"
        }
    ],
    "sg:phone":"+39 041 426 5144",
    "sg:postcode":"30034",
    "sg:province":"Venezia",
    "wof:name":"Banca Popolare Vicentina Scparl",
    "wof:placetype":"venue"
},
  "geometry": {"coordinates":[12.131248,45.436619],"type":"Point"}
}