{
  "type": "Feature",
  "properties": {
    "addr:full":"10036 Settimo Torinese Settimo Torinese Torino 10036",
    "addr:postcode":"10036;10036",
    "iso:country":"IT",
    "sg:address":"10036 Settimo Torinese",
    "sg:city":"Settimo Torinese",
    "sg:orig_category":"Prodotti Alimentari",
    "sg:phone":"+39 011 897 7479",
    "sg:postcode":"10036",
    "sg:province":"Torino",
    "wof:name":"Secom Servizio Commerciali Srl",
    "wof:placetype":"venue"
},
  "geometry": {"coordinates":[7.7316241264,45.1461181641],"type":"Point"}
}