{
  "type": "Feature",
  "properties": {
    "iso:country":"IT",
    "sg:address":"3, V. Torricelli 80022 Arzano",
    "sg:city":"Arzano",
    "sg:classifiers":[
        {
            "category":"Manufacturing",
            "subcategory":"Metals",
            "type":"Manufacturing & Wholesale Goods"
        }
    ],
    "sg:phone":"+39 081 573 4358",
    "sg:postcode":"80022",
    "sg:province":"Napoli",
    "sg:tags":[
        "metallurgy",
        "metalworking"
    ],
    "sg:website":"http://www.metallcom.com",
    "wof:name":"Metalltrade Srl",
    "wof:placetype":"venue"
},
  "geometry": {"coordinates":[14.2763185501,40.8921890259],"type":"Point"}
}