{
  "type": "Feature",
  "properties": {
    "addr:full":"Via Cusani 4 20121 Milano Milano Milano 20121",
    "addr:housenumber":"4",
    "addr:postcode":"20121;20121",
    "addr:street":"Via Cusani",
    "iso:country":"IT",
    "sg:address":"Via Cusani 4 20121 Milano",
    "sg:city":"Milano",
    "sg:classifiers":[
        {
            "category":"Wholesale",
            "subcategory":"Books, Periodicals, & Newspapers",
            "type":"Manufacturing & Wholesale Goods"
        }
    ],
    "sg:phone":"+39 02 723311",
    "sg:postcode":"20121",
    "sg:province":"Milano",
    "sg:tags":[
        "publisher",
        "journal"
    ],
    "wof:name":"Casa Editrice Universo Spa",
    "wof:placetype":"venue"
},
  "geometry": {"coordinates":[9.184467,45.468754],"type":"Point"}
}