{
  "type": "Feature",
  "properties": {
    "addr:full":"9, Vicolo Della Fossa 39100 Bolzano Bolzano Bolzano/Bozen 39100",
    "addr:housenumber":"9",
    "addr:postcode":"39100;39100",
    "addr:street":"Vicolo Della Fossa",
    "iso:country":"IT",
    "sg:address":"9, Vicolo Della Fossa 39100 Bolzano",
    "sg:city":"Bolzano",
    "sg:classifiers":[
        {
            "category":"Communications",
            "subcategory":"Television Station",
            "type":"Services"
        }
    ],
    "sg:phone":"+39 0471 289174",
    "sg:postcode":"39100",
    "sg:province":"Bolzano/Bozen",
    "sg:tags":[
        "audio-visual"
    ],
    "wof:name":"Carlin",
    "wof:placetype":"venue"
},
  "geometry": {"coordinates":[11.328239,46.461643],"type":"Point"}
}