{
  "type": "Feature",
  "properties": {
    "iso:country":"IT",
    "sg:address":"10043 Orbassano",
    "sg:city":"Orbassano",
    "sg:orig_category":"Litografie",
    "sg:phone":"+39 011 358 0213",
    "sg:postcode":"10043",
    "sg:province":"Torino",
    "wof:name":"Tre Esse Nastri Snc",
    "wof:placetype":"venue"
},
  "geometry": {"coordinates":[7.547873,45.008419],"type":"Point"}
}