{
  "type": "Feature",
  "properties": {
    "addr:full":"24045 Fara Gera D'adda Bergamo 24045",
    "addr:postcode":"24045;24045",
    "iso:country":"IT",
    "sg:address":"24045 Fara Gera D'adda",
    "sg:orig_category":"Materiali Semilavorati Metallici",
    "sg:phone":"+39 036 339 7508",
    "sg:postcode":"24045",
    "sg:province":"Bergamo",
    "wof:name":"Tecnotaglio Srl",
    "wof:placetype":"venue"
},
  "geometry": {"coordinates":[9.536393,45.558655],"type":"Point"}
}