{
  "type": "Feature",
  "properties": {
    "iso:country":"IT",
    "sg:address":"37135 Verona",
    "sg:city":"Verona",
    "sg:orig_category":"Forni Per Panifici, Pasticcerie E Pizzerie",
    "sg:phone":"+39 045 504885",
    "sg:postcode":"37135",
    "sg:province":"Verona",
    "wof:name":"Fazioni Fratelli Snc",
    "wof:placetype":"venue"
},
  "geometry": {"coordinates":[10.9753131866,45.4106330872],"type":"Point"}
}