{
  "type": "Feature",
  "properties": {
    "iso:country":"IT",
    "sg:address":"31044 Montebelluna",
    "sg:city":"Montebelluna",
    "sg:orig_category":"Tempo Libero - Articoli E Forniture. Automobili E Mezzi Di Trasporto. Riparazione Dei Mezzi Di Trasporto",
    "sg:phone":"+39 0423 22498",
    "sg:postcode":"31044",
    "sg:province":"Treviso",
    "sg:website":"http://www.simonatoweb.it",
    "wof:name":"Simonato Snc Di Simonato Elvio & C.",
    "wof:placetype":"venue"
},
  "geometry": {"coordinates":[12.054277,45.772205],"type":"Point"}
}