{
  "type": "Feature",
  "properties": {
    "iso:country":"IT",
    "sg:address":"7, Via Montegrappa 35010 Santa Giustina In Colle",
    "sg:city":"Santa Giustina in Colle",
    "sg:classifiers":[
        {
            "category":"Home & Garden",
            "subcategory":"Home Furnishings",
            "type":"Retail Goods"
        }
    ],
    "sg:phone":"+39 049 930 0333",
    "sg:postcode":"35010",
    "sg:province":"Padova",
    "sg:tags":[
        "household"
    ],
    "wof:name":"Pavan",
    "wof:placetype":"venue"
},
  "geometry": {"coordinates":[11.890164,45.575867],"type":"Point"}
}