{
  "type": "Feature",
  "properties": {
    "iso:country":"IT",
    "sg:address":"22070 Capiago Intimiano",
    "sg:city":"Capiago",
    "sg:orig_category":"Serramenti Ed Infissi",
    "sg:phone":"+39 031 460034",
    "sg:postcode":"22070",
    "sg:province":"Como",
    "wof:name":"Falegnameria Moras",
    "wof:placetype":"venue"
},
  "geometry": {"coordinates":[9.135012,45.765152],"type":"Point"}
}