{
  "type": "Feature",
  "properties": {
    "iso:country":"IT",
    "sg:address":"11, Via Molinetto 21014 Laveno Mombello",
    "sg:city":"Laveno",
    "sg:classifiers":[
        {
            "category":"Shopping",
            "subcategory":"Crafts & Fabrics",
            "type":"Retail Goods"
        }
    ],
    "sg:phone":"+39 0332 668150",
    "sg:postcode":"21014",
    "sg:province":"Varese",
    "wof:name":"Manifattura Cotoniera Monterosa (s.p.a.)",
    "wof:placetype":"venue"
},
  "geometry": {"coordinates":[8.6278743744,45.9019966125],"type":"Point"}
}