{
  "type": "Feature",
  "properties": {
    "iso:country":"IT",
    "sg:address":"20010 Vittuone",
    "sg:city":"Vittuone",
    "sg:orig_category":"Acciaierie E Fonderie",
    "sg:phone":"+39 02 902 5131",
    "sg:postcode":"20010",
    "sg:province":"Milano",
    "wof:name":"Italian Buttwelding Fittings I.b.f. S.p.a.",
    "wof:placetype":"venue"
},
  "geometry": {"coordinates":[9.071989,45.530949],"type":"Point"}
}