{
  "type": "Feature",
  "properties": {
    "iso:country":"IT",
    "sg:address":"Via Della Ferratella In Laterano 33 00184 Roma",
    "sg:city":"Roma",
    "sg:classifiers":[
        {
            "category":"Juice Bar",
            "subcategory":"None",
            "type":"Food & Drink"
        }
    ],
    "sg:phone":"+39 06 7771 9001",
    "sg:postcode":"00184",
    "sg:province":"Roma",
    "sg:tags":[
        "liquid",
        "paraffin"
    ],
    "sg:website":"www.maxcom.it",
    "wof:name":"Maxcom Petroli Srl",
    "wof:placetype":"venue"
},
  "geometry": {"coordinates":[12.501811,41.883434],"type":"Point"}
}