{
  "type": "Feature",
  "properties": {
    "addr:full":"12030 Casalgrasso Casalgrasso Cuneo 12030",
    "addr:postcode":"12030;12030",
    "iso:country":"IT",
    "sg:address":"12030 Casalgrasso",
    "sg:city":"Casalgrasso",
    "sg:orig_category":"Mangimi, Foraggi Ed Integratori Zootecnici",
    "sg:phone":"+39 011 975823",
    "sg:postcode":"12030",
    "sg:province":"Cuneo",
    "wof:name":"Euroforaggi Sas",
    "wof:placetype":"venue"
},
  "geometry": {"coordinates":[7.593537,44.83004],"type":"Point"}
}