{
  "type": "Feature",
  "properties": {
    "iso:country":"IT",
    "sg:address":"22073 Fino Mornasco",
    "sg:city":"Fino Mornasco",
    "sg:orig_category":"Bevande, Vini E Liquori",
    "sg:phone":"+39 031 928303",
    "sg:postcode":"22073",
    "sg:province":"Como",
    "wof:name":"Lariovini Di Camotti & C.",
    "wof:placetype":"venue"
},
  "geometry": {"coordinates":[9.080585,45.740715],"type":"Point"}
}