{
  "type": "Feature",
  "properties": {
    "addr:full":"21014 Laveno Mombello Laveno Varese 21014",
    "addr:postcode":"21014;21014",
    "iso:country":"IT",
    "sg:address":"21014 Laveno Mombello",
    "sg:city":"Laveno",
    "sg:orig_category":"Nastri Adesivi E Biadesivi",
    "sg:phone":"+39 0332 626189",
    "sg:postcode":"21014",
    "sg:province":"Varese",
    "wof:name":"Walper Di Perteghella Walter",
    "wof:placetype":"venue"
},
  "geometry": {"coordinates":[8.87884,45.860489],"type":"Point"}
}