{
  "type": "Feature",
  "properties": {
    "addr:full":"25125 Brescia Brescia Brescia 25125",
    "addr:postcode":"25125;25125",
    "iso:country":"IT",
    "sg:address":"25125 Brescia",
    "sg:city":"Brescia",
    "sg:orig_category":"Servizi E Lavori Per Arredamento E Industria Del Legno. Servizi Di Magazzinaggio E Movimentazione",
    "sg:phone":"+39 800 900 805",
    "sg:postcode":"25125",
    "sg:province":"Brescia",
    "wof:name":"I Professionisti Del Trasloco",
    "wof:placetype":"venue"
},
  "geometry": {"coordinates":[9.614247,45.640415],"type":"Point"}
}