{
  "type": "Feature",
  "properties": {
    "iso:country":"IT",
    "sg:address":"Via Cassia, 989; Roma",
    "sg:classifiers":[
        {
            "category":"Banks & Credit Unions",
            "subcategory":"Bank",
            "type":"Services"
        }
    ],
    "sg:phone":"+39 06 366 6042",
    "wof:name":"Cassa Di Risparmio Di Roma",
    "wof:placetype":"venue"
},
  "geometry": {"coordinates":[12.430581,41.973083],"type":"Point"}
}