{
  "type": "Feature",
  "properties": {
    "iso:country":"IT",
    "sg:address":"09128 Cagliari",
    "sg:city":"Cagliari",
    "sg:orig_category":"Medici Specialisti - Dermatologia E Malattie Veneree",
    "sg:phone":"+39 070 486288",
    "sg:postcode":"09128",
    "sg:province":"Cagliari",
    "wof:name":"Pirastu Virgilio",
    "wof:placetype":"venue"
},
  "geometry": {"coordinates":[9.124368,39.214378],"type":"Point"}
}