{
  "type": "Feature",
  "properties": {
    "addr:full":"7, Via Venti Settembre 22100 Como Como Como 22100",
    "addr:postcode":"22100;22100",
    "addr:street":"Via Venti Settembre",
    "iso:country":"IT",
    "sg:address":"7, Via Venti Settembre 22100 Como",
    "sg:city":"Como",
    "sg:classifiers":[
        {
            "category":"Shopping",
            "subcategory":"Crafts & Fabrics",
            "type":"Retail Goods"
        }
    ],
    "sg:phone":"+39 39031262210",
    "sg:postcode":"22100",
    "sg:province":"Como",
    "wof:name":"Galetti Srl",
    "wof:placetype":"venue"
},
  "geometry": {"coordinates":[9.0854558945,45.8119659424],"type":"Point"}
}