{
  "type": "Feature",
  "properties": {
    "iso:country":"IT",
    "sg:address":"61020 Sant'angelo In Lizzola",
    "sg:city":"Montecchio",
    "sg:orig_category":"Macchine E Forniture Per Arredamento E Industria Del Legno",
    "sg:phone":"+39 0721 499877",
    "sg:postcode":"61020",
    "sg:province":"Pesaro E Urbino",
    "wof:name":"L. Romani Srl Curvati In Legno",
    "wof:placetype":"venue"
},
  "geometry": {"coordinates":[12.802631,43.826019],"type":"Point"}
}