{
  "type": "Feature",
  "properties": {
    "iso:country":"IT",
    "sg:address":"9/11, Via Luigi Galvani 20090 Assago",
    "sg:city":"Assago",
    "sg:classifiers":[
        {
            "category":"Wholesale",
            "subcategory":"Drugs",
            "type":"Manufacturing & Wholesale Goods"
        }
    ],
    "sg:phone":"+39 02 4884 2603",
    "sg:postcode":"20090",
    "sg:province":"Milano",
    "sg:tags":[
        "chemical",
        "pharmaceutical"
    ],
    "wof:name":"Ridart Srl",
    "wof:placetype":"venue"
},
  "geometry": {"coordinates":[9.119808,45.410217],"type":"Point"}
}