{
  "type": "Feature",
  "properties": {
    "iso:country":"IT",
    "sg:address":"296, Viale Montegrappa 59100 Prato",
    "sg:city":"Prato",
    "sg:classifiers":[
        {
            "category":"Real Estate",
            "subcategory":"Architect",
            "type":"Services"
        }
    ],
    "sg:phone":"+39 0574 596843",
    "sg:postcode":"59100",
    "sg:province":"Prato",
    "sg:tags":[
        "textile",
        "clothing"
    ],
    "wof:name":"L'agenzia International (s.r.l.)",
    "wof:placetype":"venue"
},
  "geometry": {"coordinates":[11.096313,43.8797],"type":"Point"}
}