{
  "type": "Feature",
  "properties": {
    "addr:full":"113, Via Vitt.emanuele Iii 88060 Argusto Argusto Catanzaro 88060",
    "addr:housenumber":"113",
    "addr:postcode":"88060;88060",
    "addr:street":"Via Vitt.Emanuele Iii",
    "iso:country":"IT",
    "sg:address":"113, Via Vitt.emanuele Iii 88060 Argusto",
    "sg:city":"Argusto",
    "sg:classifiers":[
        {
            "category":"Shopping",
            "subcategory":"Clothing, Apparel, & Fashions",
            "type":"Retail Goods"
        }
    ],
    "sg:phone":"+39 39096791092",
    "sg:postcode":"88060",
    "sg:province":"Catanzaro",
    "sg:tags":[
        "clothes"
    ],
    "wof:name":"Barbuto (s.r.l.)",
    "wof:placetype":"venue"
},
  "geometry": {"coordinates":[16.587679,38.910599],"type":"Point"}
}