{
  "type": "Feature",
  "properties": {
    "iso:country":"IT",
    "sg:address":"15100 Alessandria",
    "sg:city":"Alessandria",
    "sg:orig_category":"Professionisti - Studi E Servizi Ed Associazioni Di Interesse Aziendale. Servizi Sociali. Associazioni Ed Organismi Di Interesse Pubblico",
    "sg:phone":"+39 0131 253961",
    "sg:postcode":"15100",
    "sg:province":"Alessandria",
    "sg:website":"http://www.serenassistenza.com",
    "wof:name":"Serenassistenza Italia Srl",
    "wof:placetype":"venue"
},
  "geometry": {"coordinates":[8.6902675629,44.915473938],"type":"Point"}
}