{
  "type": "Feature",
  "properties": {
    "iso:country":"IT",
    "sg:address":"20032 Cormano",
    "sg:city":"Cormano",
    "sg:orig_category":"Impiantistica E Prodotti Tecnologici Per Edilizia. Elettronica Professionale E Di Consumo",
    "sg:phone":"+39 02 6630 5255",
    "sg:postcode":"20032",
    "sg:province":"Milano",
    "wof:name":"A.p. Impianti Sas Di Procopio A. & C.",
    "wof:placetype":"venue"
},
  "geometry": {"coordinates":[9.168825,45.545288],"type":"Point"}
}