{
  "type": "Feature",
  "properties": {
    "addr:full":"33044 Manzano Manzano Udine 33044",
    "addr:postcode":"33044;33044",
    "iso:country":"IT",
    "sg:address":"33044 Manzano",
    "sg:city":"Manzano",
    "sg:classifiers":[
        {
            "category":"Professional",
            "subcategory":"Employment Agencies",
            "type":"Services"
        }
    ],
    "sg:phone":"+39 0432 754158",
    "sg:postcode":"33044",
    "sg:province":"Udine",
    "sg:tags":[
        "activities",
        "commercial",
        "equipment",
        "artisan",
        "supplies",
        "furniture",
        "accommodation",
        "furnishing"
    ],
    "sg:website":"http://www.ellero.it",
    "wof:name":"Ellero Habitat & Contract Srl",
    "wof:placetype":"venue"
},
  "geometry": {"coordinates":[13.3574323654,45.9802398682],"type":"Point"}
}