{
  "type": "Feature",
  "properties": {
    "iso:country":"IT",
    "sg:address":"Via Tevere 18 21043 Castiglione Olona",
    "sg:city":"Castiglione Olona",
    "sg:classifiers":[
        {
            "category":"Manufacturing",
            "subcategory":"Rubber & Plastics",
            "type":"Manufacturing & Wholesale Goods"
        }
    ],
    "sg:phone":"+39 0331 850895",
    "sg:postcode":"21043",
    "sg:province":"Varese",
    "sg:tags":[
        "card"
    ],
    "wof:name":"Itw Ispracontrols Spa",
    "wof:placetype":"venue"
},
  "geometry": {"coordinates":[8.869600296,45.7423057556],"type":"Point"}
}