{
  "type": "Feature",
  "properties": {
    "iso:country":"IT",
    "sg:address":"Via Quintiliano 70031 Andria",
    "sg:city":"Andria",
    "sg:classifiers":[
        {
            "category":"Shopping",
            "subcategory":"Clothing, Apparel, & Fashions",
            "type":"Retail Goods"
        }
    ],
    "sg:phone":"+39 0883 554575",
    "sg:postcode":"70031",
    "sg:province":"Bari",
    "sg:tags":[
        "clothes"
    ],
    "wof:name":"Creazioni Flower Di Raimondi Vincenza",
    "wof:placetype":"venue"
},
  "geometry": {"coordinates":[16.297499,41.23798],"type":"Point"}
}