{
  "type": "Feature",
  "properties": {
    "iso:country":"IT",
    "sg:address":"20089 Rozzano",
    "sg:city":"Rozzano",
    "sg:orig_category":"Apparecchiature Ed Attrezzature Meccaniche",
    "sg:phone":"+39 02 5751 4526",
    "sg:postcode":"20089",
    "sg:province":"Milano",
    "wof:name":"F.r.a.s.s. Sas",
    "wof:placetype":"venue"
},
  "geometry": {"coordinates":[9.168478,45.382587],"type":"Point"}
}