{
  "type": "Feature",
  "properties": {
    "addr:full":"20093 Cologno Monzese Cologno Monzese Milano 20093",
    "addr:postcode":"20093;20093",
    "iso:country":"IT",
    "sg:address":"20093 Cologno Monzese",
    "sg:city":"Cologno Monzese",
    "sg:orig_category":"Servizi E Lavori Industria Chimica. Riparazione Dei Mezzi Di Trasporto",
    "sg:phone":"+39 02 254 2433",
    "sg:postcode":"20093",
    "sg:province":"Milano",
    "wof:name":"Effegi Di Fasson Graziano",
    "wof:placetype":"venue"
},
  "geometry": {"coordinates":[9.267841,45.546398],"type":"Point"}
}