{
  "type": "Feature",
  "properties": {
    "iso:country":"IT",
    "sg:address":"00184 Roma",
    "sg:city":"Roma",
    "sg:orig_category":"Serramenti Ed Infissi. Forniture Industriali Per Prevenzione, Controllo E Sicurezza",
    "sg:phone":"+39 06 679 1908",
    "sg:postcode":"00184",
    "sg:province":"Roma",
    "wof:name":"Giovannoni Enzo",
    "wof:placetype":"venue"
},
  "geometry": {"coordinates":[12.487211,41.894493],"type":"Point"}
}