{
  "type": "Feature",
  "properties": {
    "iso:country":"IT",
    "sg:address":"30, Via Pratelli Norma 58022 Follonica",
    "sg:city":"Follonica",
    "sg:classifiers":[
        {
            "category":"Manufacturing",
            "subcategory":"Glass & Minerals",
            "type":"Manufacturing & Wholesale Goods"
        }
    ],
    "sg:phone":"+39 39056645470",
    "sg:postcode":"58022",
    "sg:province":"Grosseto",
    "wof:name":"Ma Maison Snc Di Buonavita Tiziana E C",
    "wof:placetype":"venue"
},
  "geometry": {"coordinates":[11.112782,42.762859],"type":"Point"}
}