{
  "type": "Feature",
  "properties": {
    "addr:full":"55012 Capannori Capannori Lucca 55012",
    "addr:postcode":"55012;55012",
    "iso:country":"IT",
    "sg:address":"55012 Capannori",
    "sg:city":"Capannori",
    "sg:orig_category":"Cartotecnica E Servizi. Articoli Per Imballaggio E Confezionamento",
    "sg:phone":"+39 0583 98291",
    "sg:postcode":"55012",
    "sg:province":"Lucca",
    "wof:name":"Florenpack Srl",
    "wof:placetype":"venue"
},
  "geometry": {"coordinates":[10.565001,43.823597],"type":"Point"}
}