{
  "type": "Feature",
  "properties": {
    "addr:full":"00060 Canale Monterano Canale Monterano Roma 00060",
    "addr:postcode":"00060;00060",
    "addr:street":"Roma",
    "iso:country":"IT",
    "sg:address":"00060 Canale Monterano",
    "sg:city":"Canale Monterano",
    "sg:orig_category":"Servizi E Lavori Per Edilizia E Lavori Pubblici. Acqua, Luce, Gas E Societa' Di Esercizio Pubblico",
    "sg:phone":"+39 06 996 2225",
    "sg:postcode":"00060",
    "sg:province":"Roma",
    "wof:name":"Enel S.p.a.",
    "wof:placetype":"venue"
},
  "geometry": {"coordinates":[12.068487,42.123886],"type":"Point"}
}