{
  "type": "Feature",
  "properties": {
    "iso:country":"IT",
    "sg:address":"00174 Roma",
    "sg:city":"Roma",
    "sg:orig_category":"Arredo Cucina Ed Elettrodomestici. Elettrodomestici",
    "sg:phone":"+39 06 747 8177",
    "sg:postcode":"00174",
    "sg:province":"Roma",
    "wof:name":"D.el.t.a. Distribuzione Elettrodomestici Televisori Apparecchi Audiovisivi S.r.l.",
    "wof:placetype":"venue"
},
  "geometry": {"coordinates":[12.559963,41.851521],"type":"Point"}
}