{
  "type": "Feature",
  "properties": {
    "iso:country":"IT",
    "sg:address":"30, Via Garibaldi Giuseppe 28066 Galliate",
    "sg:city":"Galliate",
    "sg:classifiers":[
        {
            "category":"Shopping",
            "subcategory":"Crafts & Fabrics",
            "type":"Retail Goods"
        }
    ],
    "sg:phone":"+39 390 321 8081",
    "sg:postcode":"28066",
    "sg:province":"Novara",
    "wof:name":"Standardtela S.p.a.",
    "wof:placetype":"venue"
},
  "geometry": {"coordinates":[8.6937360764,45.4800987244],"type":"Point"}
}