{
  "type": "Feature",
  "properties": {
    "addr:full":"2, Via Garibaldi 14022 Castelnuovo Don Bosco Castelnuovo Don Bosco Asti 14022",
    "addr:postcode":"14022;14022",
    "addr:street":"Via Garibaldi",
    "iso:country":"IT",
    "sg:address":"2, Via Garibaldi 14022 Castelnuovo Don Bosco",
    "sg:city":"Castelnuovo Don Bosco",
    "sg:classifiers":[
        {
            "category":"Autos & Motor Vehicles",
            "subcategory":"Automobile Sales",
            "type":"Retail Goods"
        }
    ],
    "sg:phone":"+39 011 987 6305",
    "sg:postcode":"14022",
    "sg:province":"Asti",
    "sg:tags":[
        "industrial"
    ],
    "wof:name":"Profilcar Di Mosso E Gamba Snc",
    "wof:placetype":"venue"
},
  "geometry": {"coordinates":[7.902309,45.044422],"type":"Point"}
}