{
  "type": "Feature",
  "properties": {
    "iso:country":"IT",
    "sg:address":"56, V. C. Montanari 37060 Mozzecane",
    "sg:city":"Mozzecane",
    "sg:classifiers":[
        {
            "category":"Autos & Motor Vehicles",
            "subcategory":"Automobile Sales",
            "type":"Retail Goods"
        }
    ],
    "sg:phone":"+39 045 634 0289",
    "sg:postcode":"37060",
    "sg:province":"Verona",
    "sg:tags":[
        "industrial"
    ],
    "sg:website":"http://www.centralbus.it",
    "wof:name":"Central Bus Srl",
    "wof:placetype":"venue"
},
  "geometry": {"coordinates":[10.814774,45.305672],"type":"Point"}
}