{
  "type": "Feature",
  "properties": {
    "iso:country":"IT",
    "sg:address":"37022 Fumane",
    "sg:city":"Fumane",
    "sg:orig_category":"Impianti Sportivi E Ricreativi - Esercizio",
    "sg:phone":"+39 045 683 9255",
    "sg:postcode":"37022",
    "sg:province":"Verona",
    "wof:name":"Centro Fumane - Gestione Impianti Sportivi",
    "wof:placetype":"venue"
},
  "geometry": {"coordinates":[10.885118,45.545067],"type":"Point"}
}