{
  "type": "Feature",
  "properties": {
    "iso:country":"IT",
    "sg:address":"Via Maggini 63a, 60127 Ancona, An",
    "sg:city":"Ancona",
    "sg:classifiers":[
        {
            "category":"Banks & Credit Unions",
            "subcategory":"Bank",
            "type":"Services"
        }
    ],
    "sg:postcode":"60127",
    "sg:province":"Ancona",
    "wof:name":"Banca Di Ancona Credito Cooperativo Scrl",
    "wof:placetype":"venue"
},
  "geometry": {"coordinates":[13.50144,43.594151],"type":"Point"}
}