{
  "type": "Feature",
  "properties": {
    "iso:country":"IT",
    "sg:address":"00142 Roma",
    "sg:city":"Roma",
    "sg:orig_category":"Articoli Regalo - Vendita Al Dettaglio",
    "sg:phone":"+39 06 519 1616",
    "sg:postcode":"00142",
    "sg:province":"Roma",
    "wof:name":"Ci.di.idea Di Cinti P. & C. Sas",
    "wof:placetype":"venue"
},
  "geometry": {"coordinates":[12.504013,41.836437],"type":"Point"}
}