{
  "type": "Feature",
  "properties": {
    "addr:full":"10154 Torino Torino Torino 10154",
    "addr:postcode":"10154;10154",
    "iso:country":"IT",
    "sg:address":"10154 Torino",
    "sg:city":"Torino",
    "sg:orig_category":"Autolavaggio",
    "sg:phone":"+39 011 242 2255",
    "sg:postcode":"10154",
    "sg:province":"Torino",
    "wof:name":"Mint Di Alessio Francone",
    "wof:placetype":"venue"
},
  "geometry": {"coordinates":[7.705265,45.095715],"type":"Point"}
}