{
  "type": "Feature",
  "properties": {
    "iso:country":"IT",
    "sg:address":"Via Vico Gian Battista 14 20123 Milano",
    "sg:city":"Milano",
    "sg:classifiers":[
        {
            "category":"Wholesale",
            "subcategory":"Metals & Minerals",
            "type":"Manufacturing & Wholesale Goods"
        }
    ],
    "sg:phone":"+39 02 4801 4650",
    "sg:postcode":"20123",
    "sg:province":"Milano",
    "sg:tags":[
        "non-ferrous"
    ],
    "wof:name":"Leghe E Metalli International Srl",
    "wof:placetype":"venue"
},
  "geometry": {"coordinates":[9.169797,45.461002],"type":"Point"}
}