{
  "type": "Feature",
  "properties": {
    "addr:full":"33082 Azzano Decimo Azzano Decimo Pordenone 33082",
    "addr:postcode":"33082;33082",
    "iso:country":"IT",
    "sg:address":"33082 Azzano Decimo",
    "sg:city":"Azzano Decimo",
    "sg:orig_category":"Prodotti Chimici Di Base",
    "sg:phone":"+39 0434 631246",
    "sg:postcode":"33082",
    "sg:province":"Pordenone",
    "sg:website":"http://www.altur.it",
    "wof:name":"Altur Snc Di Turcatel M. & C.",
    "wof:placetype":"venue"
},
  "geometry": {"coordinates":[12.7131547928,45.8862724304],"type":"Point"}
}