{
  "type": "Feature",
  "properties": {
    "iso:country":"IT",
    "sg:address":"31046 Oderzo",
    "sg:city":"Oderzo",
    "sg:orig_category":"Automobili E Mezzi Di Trasporto",
    "sg:phone":"+39 0422 853939",
    "sg:postcode":"31046",
    "sg:province":"Treviso",
    "sg:website":"http://www.narder.it",
    "wof:name":"Narder Autoveicoli Sas Di Narder",
    "wof:placetype":"venue"
},
  "geometry": {"coordinates":[12.499269,45.76228],"type":"Point"}
}