{
  "type": "Feature",
  "properties": {
    "iso:country":"IT",
    "sg:address":"Km. 17.700, Strada Statale Sannitica 80023 Caivano",
    "sg:city":"Caivano",
    "sg:classifiers":[
        {
            "category":"Manufacturing",
            "subcategory":"Tools & Machinery",
            "type":"Manufacturing & Wholesale Goods"
        }
    ],
    "sg:phone":"+39 081 834 9122",
    "sg:postcode":"80023",
    "sg:province":"Napoli",
    "sg:tags":[
        "environment",
        "equipment",
        "-"
    ],
    "wof:name":"Delta Chimica (s.r.l.)",
    "wof:placetype":"venue"
},
  "geometry": {"coordinates":[14.251636,40.840096],"type":"Point"}
}