{
  "type": "Feature",
  "properties": {
    "iso:country":"IT",
    "sg:address":"14, V. Turati 64028 Silvi",
    "sg:city":"Silvi",
    "sg:classifiers":[
        {
            "category":"Communications",
            "subcategory":"Newspaper",
            "type":"Services"
        }
    ],
    "sg:phone":"+39 085 935 0312",
    "sg:postcode":"64028",
    "sg:province":"Teramo",
    "sg:tags":[
        "advertising"
    ],
    "sg:website":"http://www.paginegialle.it/tutto",
    "wof:name":"Modolo Salvatore",
    "wof:placetype":"venue"
},
  "geometry": {"coordinates":[13.698531,42.66127],"type":"Point"}
}