{
  "type": "Feature",
  "properties": {
    "addr:full":"80010 Quarto Quarto Napoli 80010",
    "addr:postcode":"80010;80010",
    "iso:country":"IT",
    "sg:address":"80010 Quarto",
    "sg:city":"Quarto",
    "sg:orig_category":"Elettronica Professionale E Di Consumo. Automazione E Macchine Per Ufficio. Forniture Industriali Per Prevenzione, Controllo E Sicurezza",
    "sg:phone":"+39 081 806 2758",
    "sg:postcode":"80010",
    "sg:province":"Napoli",
    "sg:website":"http://www.highsecurity.it",
    "wof:name":"Highsecurity Sas Di La Marca Massimiliano",
    "wof:placetype":"venue"
},
  "geometry": {"coordinates":[14.121519,40.877983],"type":"Point"}
}