{
  "type": "Feature",
  "properties": {
    "iso:country":"IT",
    "sg:address":"Via Marconi 70; Casalecchio Di Reno; 40033",
    "sg:city":"Casalecchio di Reno",
    "sg:classifiers":[
        {
            "category":"Banks & Credit Unions",
            "subcategory":"Bank",
            "type":"Services"
        }
    ],
    "sg:phone":"+39 051 613 1315",
    "sg:postcode":"40033",
    "sg:province":"Bologna",
    "wof:name":"Rolo Banca 1473 Spa",
    "wof:placetype":"venue"
},
  "geometry": {"coordinates":[11.276934,44.476536],"type":"Point"}
}