{
  "type": "Feature",
  "properties": {
    "iso:country":"IT",
    "sg:address":"21100 Varese",
    "sg:city":"Varese",
    "sg:orig_category":"Salotti, Poltrone, Sedie E Tavoli",
    "sg:phone":"+39 0332 330375",
    "sg:postcode":"21100",
    "sg:province":"Varese",
    "sg:website":"http://www.arredopiu.net",
    "wof:name":"Arredamenti Piu' Srl",
    "wof:placetype":"venue"
},
  "geometry": {"coordinates":[8.847424,45.815987],"type":"Point"}
}