{
  "type": "Feature",
  "properties": {
    "iso:country":"IT",
    "sg:address":"90141 Palermo",
    "sg:city":"Palermo",
    "sg:orig_category":"Estetiste",
    "sg:phone":"+39 091 348195",
    "sg:postcode":"90141",
    "sg:province":"Palermo",
    "wof:name":"Istituto Rica Di Maria Carollo",
    "wof:placetype":"venue"
},
  "geometry": {"coordinates":[13.338313,38.130833],"type":"Point"}
}