{
  "type": "Feature",
  "properties": {
    "iso:country":"IT",
    "sg:address":"24048 Treviolo",
    "sg:city":"Treviolo",
    "sg:orig_category":"Valvole E Apparecchiature Di Misura",
    "sg:phone":"+39 035 201090",
    "sg:postcode":"24048",
    "sg:province":"Bergamo",
    "wof:name":"I.t.p. Industrial Techno Piping Srl",
    "wof:placetype":"venue"
},
  "geometry": {"coordinates":[9.608239,45.666103],"type":"Point"}
}