{
  "type": "Feature",
  "properties": {
    "addr:full":"24030 Paladina Paladina Bergamo 24030",
    "addr:postcode":"24030;24030",
    "iso:country":"IT",
    "sg:address":"24030 Paladina",
    "sg:city":"Paladina",
    "sg:orig_category":"Lavanderie Industriali E Noleggio Biancheria",
    "sg:phone":"+39 035 637552",
    "sg:postcode":"24030",
    "sg:province":"Bergamo",
    "wof:name":"Dove Il Lavare E' Arte Di Roberti Silverio & Baggi Mirka Snc",
    "wof:placetype":"venue"
},
  "geometry": {"coordinates":[9.60218,45.730049],"type":"Point"}
}