{
  "type": "Feature",
  "properties": {
    "iso:country":"IT",
    "sg:address":"24060 Credaro",
    "sg:city":"Credaro",
    "sg:orig_category":"Forniture Per Attivita' Industriali",
    "sg:phone":"+39 035 935221",
    "sg:postcode":"24060",
    "sg:province":"Bergamo",
    "wof:name":"Cooperativa Labor",
    "wof:placetype":"venue"
},
  "geometry": {"coordinates":[9.6670131683,45.6893234253],"type":"Point"}
}