{
  "type": "Feature",
  "properties": {
    "addr:full":"20036 Meda Meda Milano 20036",
    "addr:postcode":"20036;20036",
    "iso:country":"IT",
    "sg:address":"20036 Meda",
    "sg:city":"Meda",
    "sg:orig_category":"Articoli Per Imballaggio E Confezionamento",
    "sg:phone":"+39 036 234 1484",
    "sg:postcode":"20036",
    "sg:province":"Milano",
    "wof:name":"Gielledue Di Dona' Luigi",
    "wof:placetype":"venue"
},
  "geometry": {"coordinates":[9.13422,45.546768],"type":"Point"}
}