{
  "type": "Feature",
  "properties": {
    "iso:country":"IT",
    "sg:address":"45, Regione Pieve 14018 Villafranca D'asti",
    "sg:classifiers":[
        {
            "category":"Shopping",
            "type":"Retail Goods"
        }
    ],
    "sg:phone":"+39 0141 943110",
    "sg:postcode":"14018",
    "sg:province":"Asti",
    "sg:tags":[
        "finished",
        "-",
        "metallic"
    ],
    "wof:name":"Onni - Stamp (s.r.l.)",
    "wof:placetype":"venue"
},
  "geometry": {"coordinates":[8.0370111465,44.9136123657],"type":"Point"}
}