{
  "type": "Feature",
  "properties": {
    "iso:country":"IT",
    "sg:address":"00132 Roma",
    "sg:city":"Roma",
    "sg:orig_category":"Articoli Pulizia. Carta, Cartone E Prodotti Primari. Prodotti Cosmetici E Da Toeletta",
    "sg:phone":"+39 06 2244 5701",
    "sg:postcode":"00132",
    "sg:province":"Roma",
    "wof:name":"Spark & Spark Italia Srl",
    "wof:placetype":"venue"
},
  "geometry": {"coordinates":[12.664451,41.889587],"type":"Point"}
}