{
  "type": "Feature",
  "properties": {
    "iso:country":"IT",
    "sg:address":"11/a, Via Chioggia 31030 Castello Di Godego",
    "sg:city":"Castello di Godego",
    "sg:classifiers":[
        {
            "category":"Food & Beverages",
            "subcategory":"Groceries & Convenience Stores",
            "type":"Retail Goods"
        }
    ],
    "sg:phone":"+39 0423 760007",
    "sg:postcode":"31030",
    "sg:province":"Treviso",
    "sg:tags":[
        "product",
        "related"
    ],
    "wof:name":"Jolly Sgambaro S.r.l.",
    "wof:placetype":"venue"
},
  "geometry": {"coordinates":[12.2420721054,45.6662864685],"type":"Point"}
}