{
  "type": "Feature",
  "properties": {
    "addr:full":"20125 Milano Milano Milano 20125",
    "addr:postcode":"20125;20125",
    "iso:country":"IT",
    "sg:address":"20125 Milano",
    "sg:city":"Milano",
    "sg:orig_category":"Utensili Meccanici E Materiali",
    "sg:phone":"+39 02 6671 1022",
    "sg:postcode":"20125",
    "sg:province":"Milano",
    "wof:name":"Zinelli S.r.l.",
    "wof:placetype":"venue"
},
  "geometry": {"coordinates":[9.201308,45.495026],"type":"Point"}
}