{
  "type": "Feature",
  "properties": {
    "addr:full":"Via Mestrina 52/54 35030 Veggiano Veggiano Padova 35030",
    "addr:housenumber":"52 / 54",
    "addr:postcode":"35030;35030",
    "addr:street":"Via Mestrina",
    "iso:country":"IT",
    "sg:address":"Via Mestrina 52/54 35030 Veggiano",
    "sg:city":"Veggiano",
    "sg:classifiers":[
        {
            "category":"Home & Garden",
            "subcategory":"Home Furnishings",
            "type":"Retail Goods"
        }
    ],
    "sg:phone":"+39 049 900 0228",
    "sg:postcode":"35030",
    "sg:province":"Padova",
    "sg:tags":[
        "textile"
    ],
    "sg:website":"www.bottaro.it",
    "wof:name":"Bottaro E C. S.r.l.",
    "wof:placetype":"venue"
},
  "geometry": {"coordinates":[11.115941,45.418343],"type":"Point"}
}