{
  "type": "Feature",
  "properties": {
    "iso:country":"IT",
    "sg:address":"29, Via Sabin 20019 Settimo Milanese",
    "sg:city":"Settimo Milanese",
    "sg:classifiers":[
        {
            "category":"Parking",
            "subcategory":"Lot",
            "type":"Transportation"
        }
    ],
    "sg:phone":"+39 39023286101",
    "sg:postcode":"20019",
    "sg:province":"Milano",
    "sg:tags":[
        "transport",
        "road"
    ],
    "wof:name":"Minitransport S R L",
    "wof:placetype":"venue"
},
  "geometry": {"coordinates":[9.066582,45.478741],"type":"Point"}
}