{
  "type": "Feature",
  "properties": {
    "addr:full":"Via Gallesi Giuseppe 30 16163 Genova Genova Genova 16163",
    "addr:housenumber":"30",
    "addr:postcode":"16163;16163",
    "addr:street":"Via Gallesi Giuseppe",
    "iso:country":"IT",
    "sg:address":"Via Gallesi Giuseppe 30 16163 Genova",
    "sg:city":"Genova",
    "sg:classifiers":[
        {
            "category":"Home & Garden",
            "subcategory":"Building Materials",
            "type":"Retail Goods"
        }
    ],
    "sg:phone":"+39 010 712201",
    "sg:postcode":"16163",
    "sg:province":"Genova",
    "sg:tags":[
        "paint",
        "anti-corrosive",
        "lacquer"
    ],
    "wof:name":"Sinco Mec Kolor Spa",
    "wof:placetype":"venue"
},
  "geometry": {"coordinates":[8.933989,44.407063],"type":"Point"}
}