{
  "type": "Feature",
  "properties": {
    "iso:country":"IT",
    "sg:address":"Sda Paiola 2 27010 Cura Carpignano",
    "sg:city":"Cura Carpignano",
    "sg:classifiers":[
        {
            "category":"Building & Trades",
            "subcategory":"Construction",
            "type":"Services"
        }
    ],
    "sg:phone":"+39 0382 483260",
    "sg:postcode":"27010",
    "sg:province":"Pavia",
    "sg:tags":[
        "industrial",
        "demolition"
    ],
    "wof:name":"D.q.s. Srl",
    "wof:placetype":"venue"
},
  "geometry": {"coordinates":[9.218313,45.204433],"type":"Point"}
}