{
  "type": "Feature",
  "properties": {
    "addr:full":"36030 Caldogno Caldogno Vicenza 36030",
    "addr:postcode":"36030;36030",
    "iso:country":"IT",
    "sg:address":"36030 Caldogno",
    "sg:city":"Caldogno",
    "sg:orig_category":"Utensili Meccanici E Materiali",
    "sg:phone":"+39 0444 985560",
    "sg:postcode":"36030",
    "sg:province":"Vicenza",
    "wof:name":"Trevisan Diego",
    "wof:placetype":"venue"
},
  "geometry": {"coordinates":[11.539877,45.600086],"type":"Point"}
}