{
  "type": "Feature",
  "properties": {
    "addr:full":"59013 Montemurlo Montemurlo Prato 59013",
    "addr:postcode":"59013;59013",
    "iso:country":"IT",
    "sg:address":"59013 Montemurlo",
    "sg:city":"Montemurlo",
    "sg:orig_category":"Prodotti Chimici Industriali - Produzione",
    "sg:phone":"+39 0574 682409",
    "sg:postcode":"59013",
    "sg:province":"Prato",
    "wof:name":"Giovanni Re & Figli Srl",
    "wof:placetype":"venue"
},
  "geometry": {"coordinates":[11.028503418,43.9137992859],"type":"Point"}
}