{
  "type": "Feature",
  "properties": {
    "iso:country":"IT",
    "sg:address":"20, Via Rimembranze 22060 Carugo",
    "sg:city":"Carugo",
    "sg:classifiers":[
        {
            "category":"Professional",
            "subcategory":"Engineering",
            "type":"Services"
        }
    ],
    "sg:phone":"+39 39031763201",
    "sg:postcode":"22060",
    "sg:province":"Como",
    "sg:tags":[
        "machine",
        "-",
        "mechanical"
    ],
    "wof:name":"Vigano",
    "wof:placetype":"venue"
},
  "geometry": {"coordinates":[9.19853,45.715195],"type":"Point"}
}