{
  "type": "Feature",
  "properties": {
    "iso:country":"IT",
    "sg:address":"44034 Copparo",
    "sg:city":"Copparo",
    "sg:orig_category":"Macchine Agricole - Produzione",
    "sg:phone":"+39 0532 866866",
    "sg:postcode":"44034",
    "sg:province":"Ferrara",
    "wof:name":"Ferri Srl",
    "wof:placetype":"venue"
},
  "geometry": {"coordinates":[11.772506,44.87851],"type":"Point"}
}