{
  "type": "Feature",
  "properties": {
    "iso:country":"IT",
    "sg:address":"15061 Arquata Scrivia",
    "sg:city":"Arquata Scrivia",
    "sg:orig_category":"Servizi Per Imballaggio E Confezionamento",
    "sg:phone":"+39 0143 635365",
    "sg:postcode":"15061",
    "sg:province":"Alessandria",
    "wof:name":"Top Service Sas Di Bisio S. & C.",
    "wof:placetype":"venue"
},
  "geometry": {"coordinates":[8.887809,44.691528],"type":"Point"}
}