{
  "type": "Feature",
  "properties": {
    "iso:country":"IT",
    "sg:address":"85, Via Ripamonti Giuseppe 20141 Milano",
    "sg:city":"Milano",
    "sg:classifiers":[
        {
            "category":"Utilities",
            "subcategory":"Electric",
            "type":"Services"
        }
    ],
    "sg:phone":"+39 390 257 4711",
    "sg:postcode":"20141",
    "sg:province":"Milano",
    "sg:tags":[
        "energy"
    ],
    "wof:name":"Camuzzi Gazometri (s.p.a.)",
    "wof:placetype":"venue"
},
  "geometry": {"coordinates":[9.199376,45.4431],"type":"Point"}
}