{
  "type": "Feature",
  "properties": {
    "iso:country":"IT",
    "sg:address":"Via Romana 40 28047 Oleggio",
    "sg:city":"Oleggio",
    "sg:orig_category":"Bathing Costumes, Bathing Shorts, Bikinis",
    "sg:phone":"+39 0321 93592",
    "sg:postcode":"28047",
    "sg:province":"Novara",
    "sg:website":"www.ritamare.com",
    "wof:name":"Ritamare Di Mancin & C Snc",
    "wof:placetype":"venue"
},
  "geometry": {"coordinates":[8.641948,45.613407],"type":"Point"}
}