{
  "type": "Feature",
  "properties": {
    "iso:country":"IT",
    "sg:address":"11, Via Cavatigozzi 26028 Sesto Ed Uniti",
    "sg:city":"Sesto ed Uniti",
    "sg:classifiers":[
        {
            "category":"Wholesale",
            "subcategory":"Drugs",
            "type":"Manufacturing & Wholesale Goods"
        }
    ],
    "sg:phone":"+39 0372 710705",
    "sg:postcode":"26028",
    "sg:province":"Cremona",
    "sg:tags":[
        "chemical",
        "pharmaceutical"
    ],
    "wof:name":"Camerini & C. (s.r.l.)",
    "wof:placetype":"venue"
},
  "geometry": {"coordinates":[9.956953,45.156311],"type":"Point"}
}