{
  "type": "Feature",
  "properties": {
    "addr:full":"2, Via Macchine 30175 Venezia Venezia Venezia 30175",
    "addr:postcode":"30175;30175",
    "addr:street":"Via Macchine",
    "iso:country":"IT",
    "sg:address":"2, Via Macchine 30175 Venezia",
    "sg:city":"Venezia",
    "sg:classifiers":[
        {
            "category":"Real Estate",
            "subcategory":"Architect",
            "type":"Services"
        }
    ],
    "sg:phone":"+39 041 509 2111",
    "sg:postcode":"30175",
    "sg:province":"Venezia",
    "sg:tags":[
        "textile",
        "clothing"
    ],
    "wof:name":"Albany International Italia Spa",
    "wof:placetype":"venue"
},
  "geometry": {"coordinates":[12.326627,45.440895],"type":"Point"}
}