{
  "type": "Feature",
  "properties": {
    "addr:full":"50019 Sesto Fiorentino Osmannoro Firenze 50019",
    "addr:postcode":"50019;50019",
    "iso:country":"IT",
    "sg:address":"50019 Sesto Fiorentino",
    "sg:city":"Osmannoro",
    "sg:classifiers":[
        {
            "category":"Manufacturing",
            "subcategory":"Leather Goods",
            "type":"Manufacturing & Wholesale Goods"
        }
    ],
    "sg:phone":"+39 055 301082",
    "sg:postcode":"50019",
    "sg:province":"Firenze",
    "sg:tags":[
        "footwear",
        "skin"
    ],
    "sg:website":"http://www.euro-militaria.com",
    "wof:name":"Euro Srl",
    "wof:placetype":"venue"
},
  "geometry": {"coordinates":[11.168261528,43.8110046387],"type":"Point"}
}