{
  "type": "Feature",
  "properties": {
    "addr:full":"10128 Torino Torino Torino 10128",
    "addr:postcode":"10128;10128",
    "iso:country":"IT",
    "sg:address":"10128 Torino",
    "sg:city":"Torino",
    "sg:orig_category":"Audiovisivi Apparecchi Ed Impianti - Produzione, Commercio E Noleggio",
    "sg:phone":"+39 011 500048",
    "sg:postcode":"10128",
    "sg:province":"Torino",
    "sg:website":"http://www.ovrit.it",
    "wof:name":"Ovrit Video Srl",
    "wof:placetype":"venue"
},
  "geometry": {"coordinates":[7.375147,44.892113],"type":"Point"}
}