{
  "type": "Feature",
  "properties": {
    "addr:full":"13833 Portula Portula Biella 13833",
    "addr:housenumber":"13833",
    "addr:postcode":"13833",
    "addr:street":"Portula Portula",
    "iso:country":"IT",
    "sg:address":"13833 Portula",
    "sg:city":"Portula",
    "sg:orig_category":"Biancheria, Telerie E Coperte. Forniture Alle Strutture Ricettive",
    "sg:phone":"+39 015 787126",
    "sg:postcode":"13833",
    "sg:province":"Biella",
    "wof:name":"Tesshotel",
    "wof:placetype":"venue"
},
  "geometry": {"coordinates":[8.118459,45.705948],"type":"Point"}
}