{
  "type": "Feature",
  "properties": {
    "addr:full":"20092 Cinisello Balsamo Cinisello Balsamo Milano 20092",
    "addr:postcode":"20092;20092",
    "iso:country":"IT",
    "sg:address":"20092 Cinisello Balsamo",
    "sg:city":"Cinisello Balsamo",
    "sg:orig_category":"Servizi E Lavori Per Industria Alimentare E Bevande",
    "sg:phone":"+39 02 6604 7389",
    "sg:postcode":"20092",
    "sg:province":"Milano",
    "wof:name":"Cooperativa La Nostra Casa",
    "wof:placetype":"venue"
},
  "geometry": {"coordinates":[9.17353,45.555565],"type":"Point"}
}