{
  "type": "Feature",
  "properties": {
    "addr:full":"50, Via Palmiro Togliatti 63035 Offida Offida Ascoli Piceno 63035",
    "addr:postcode":"63035;63035",
    "addr:street":"Via Palmiro Togliatti",
    "iso:country":"IT",
    "sg:address":"50, Via Palmiro Togliatti 63035 Offida",
    "sg:city":"Offida",
    "sg:classifiers":[
        {
            "category":"Food & Beverages",
            "subcategory":"Groceries & Convenience Stores",
            "type":"Retail Goods"
        }
    ],
    "sg:phone":"+39 0736 888000",
    "sg:postcode":"63035",
    "sg:province":"Ascoli Piceno",
    "sg:tags":[
        "product",
        "related"
    ],
    "wof:name":"Conserviera Adriatica S.p.a.",
    "wof:placetype":"venue"
},
  "geometry": {"coordinates":[13.7282133102,42.8673706055],"type":"Point"}
}