{
  "type": "Feature",
  "properties": {
    "iso:country":"IT",
    "sg:address":"Via Quitino Sella 16 13856 Vigliano Biellese",
    "sg:city":"Vigliano Biellese",
    "sg:orig_category":"Filters, Active",
    "sg:phone":"+39 015 812 3205",
    "sg:postcode":"13856",
    "sg:province":"Biella",
    "sg:website":"www.altec-italia.it",
    "wof:name":"Altec Italia Srl",
    "wof:placetype":"venue"
},
  "geometry": {"coordinates":[8.0922346115,45.5593452454],"type":"Point"}
}