{
  "type": "Feature",
  "properties": {
    "iso:country":"IT",
    "sg:address":"46100 Mantova",
    "sg:city":"Mantova",
    "sg:orig_category":"Prodotti Chimici Secondari. Servizi E Lavori Per Ecologia E Smaltimento Rifiuti. Macchine E Forniture Per Ecologia E Smaltimento Rifiuti",
    "sg:phone":"+39 0376 321936",
    "sg:postcode":"46100",
    "sg:province":"Mantova",
    "wof:name":"S.c.m. Tecnologie Sas Di Sereni Massimo & C.",
    "wof:placetype":"venue"
},
  "geometry": {"coordinates":[10.79662323,45.1589279175],"type":"Point"}
}