{
  "type": "Feature",
  "properties": {
    "iso:country":"IT",
    "sg:address":"57017 Collesalvetti",
    "sg:city":"Collesalvetti",
    "sg:orig_category":"Anelli E Guarnizioni Di Tenuta E D'arresto",
    "sg:phone":"+39 0586 943666",
    "sg:postcode":"57017",
    "sg:province":"Livorno",
    "wof:name":"Hallite Italia Srl",
    "wof:placetype":"venue"
},
  "geometry": {"coordinates":[10.352402,43.58247],"type":"Point"}
}