{
  "type": "Feature",
  "properties": {
    "iso:country":"IT",
    "sg:address":"20017 Rho",
    "sg:city":"Rho",
    "sg:orig_category":"Elettronica Professionale E Di Consumo. Automazione E Macchine Per Ufficio. Forniture Industriali Per Prevenzione, Controllo E Sicurezza",
    "sg:phone":"+39 02 939 9801",
    "sg:postcode":"20017",
    "sg:province":"Milano",
    "sg:website":"http://www.balconicancelliautomatici.it",
    "wof:name":"Balconi Srl",
    "wof:placetype":"venue"
},
  "geometry": {"coordinates":[9.037736,45.521721],"type":"Point"}
}