{
  "type": "Feature",
  "properties": {
    "iso:country":"IT",
    "sg:address":"24, Via Vincenzo Stefano Breda 35010 Limena",
    "sg:city":"Limena",
    "sg:classifiers":[
        {
            "category":"Autos & Motor Vehicles",
            "subcategory":"Automobile Sales",
            "type":"Retail Goods"
        }
    ],
    "sg:phone":"+39 049 884 1160",
    "sg:postcode":"35010",
    "sg:province":"Padova",
    "sg:tags":[
        "industrial"
    ],
    "wof:name":"Essepi Ricambi S.r.l.",
    "wof:placetype":"venue"
},
  "geometry": {"coordinates":[11.848577,45.464165],"type":"Point"}
}