{
  "type": "Feature",
  "properties": {
    "addr:full":"19126 La Spezia SP",
    "addr:housenumber":"19126",
    "iso:country":"IT",
    "sg:address":"19126 La Spezia",
    "sg:classifiers":[
        {
            "category":"Home & Garden",
            "subcategory":"Furniture",
            "type":"Retail Goods"
        }
    ],
    "sg:phone":"+39 0187 280355",
    "sg:province":"SP",
    "sg:tags":[
        "furnishing"
    ],
    "wof:name":"Nautilus Di Valli Catia",
    "wof:placetype":"venue"
},
  "geometry": {"coordinates":[9.8599328995,44.1075286865],"type":"Point"}
}