{
  "type": "Feature",
  "properties": {
    "addr:full":"88, V. Carducci 86100 Campobasso Campobasso Campobasso 86100",
    "addr:housenumber":"88",
    "addr:postcode":"86100;86100",
    "addr:street":"V. Carducci",
    "iso:country":"IT",
    "sg:address":"88, V. Carducci 86100 Campobasso",
    "sg:city":"Campobasso",
    "sg:classifiers":[
        {
            "category":"Shopping",
            "subcategory":"Jewelry",
            "type":"Retail Goods"
        }
    ],
    "sg:phone":"+39 39087491766",
    "sg:postcode":"86100",
    "sg:province":"Campobasso",
    "sg:tags":[
        "jewellery"
    ],
    "wof:name":"New Line Export Sas",
    "wof:placetype":"venue"
},
  "geometry": {"coordinates":[14.673217,41.54623],"type":"Point"}
}