{
  "type": "Feature",
  "properties": {
    "addr:full":"80, Via Conegliano 31058 Susegana Susegana Treviso 31058",
    "addr:postcode":"31058;31058",
    "addr:street":"Via Conegliano",
    "iso:country":"IT",
    "sg:address":"80, Via Conegliano 31058 Susegana",
    "sg:city":"Susegana",
    "sg:classifiers":[
        {
            "category":"Manufacturing",
            "subcategory":"Wood Products",
            "type":"Manufacturing & Wholesale Goods"
        }
    ],
    "sg:phone":"+39 0438 435222",
    "sg:postcode":"31058",
    "sg:province":"Treviso",
    "sg:tags":[
        "furniture"
    ],
    "wof:name":"Forestale Veneta (s.p.a.)",
    "wof:placetype":"venue"
},
  "geometry": {"coordinates":[12.259966,45.857521],"type":"Point"}
}