{
  "type": "Feature",
  "properties": {
    "iso:country":"IT",
    "sg:address":"10099 San Mauro Torinese",
    "sg:city":"San Mauro Torinese",
    "sg:orig_category":"Motori Ed Organi Di Trasmissione. Ricambi E Componenti Dei Mezzi Di Trasporto",
    "sg:phone":"+39 011 273 5661",
    "sg:postcode":"10099",
    "sg:province":"Torino",
    "wof:name":"Ina Rullini (s.p.a.)",
    "wof:placetype":"venue"
},
  "geometry": {"coordinates":[7.7407751083,45.1163368225],"type":"Point"}
}