{
  "type": "Feature",
  "properties": {
    "iso:country":"IT",
    "sg:address":"28024 Gozzano",
    "sg:city":"Gozzano",
    "sg:orig_category":"Fotografia - Servizi, Studi, Sviluppo E Stampa",
    "sg:phone":"+39 0322 93751",
    "sg:postcode":"28024",
    "sg:province":"Novara",
    "wof:name":"Godi Giuseppe",
    "wof:placetype":"venue"
},
  "geometry": {"coordinates":[8.4375534058,45.7431221008],"type":"Point"}
}