{
  "type": "Feature",
  "properties": {
    "iso:country":"IT",
    "sg:address":"50133 Firenze",
    "sg:city":"Firenze",
    "sg:orig_category":"Agenzie Viaggi E Turismo",
    "sg:phone":"+39 055 552 2182",
    "sg:postcode":"50133",
    "sg:province":"Firenze",
    "wof:name":"Tredici Rosso Viaggi Snc",
    "wof:placetype":"venue"
},
  "geometry": {"coordinates":[11.277887,43.796101],"type":"Point"}
}