{
  "type": "Feature",
  "properties": {
    "addr:full":"89821 Villavallelonga Vallelonga Vibo Valentia 89821",
    "addr:postcode":"89821;89821",
    "addr:street":"Vibo Valentia",
    "iso:country":"IT",
    "sg:address":"89821 Villavallelonga",
    "sg:city":"Vallelonga",
    "sg:orig_category":"Alberghi",
    "sg:phone":"+39 0863 949403",
    "sg:postcode":"89821",
    "sg:province":"Vibo Valentia",
    "sg:website":"http://web.tiscalinet.it/campingvallelonga",
    "wof:name":"Camping Vallelonga",
    "wof:placetype":"venue"
},
  "geometry": {"coordinates":[16.09766,38.67561],"type":"Point"}
}