{
  "type": "Feature",
  "properties": {
    "addr:full":"20062 Cassano D'adda Milano 20062",
    "addr:postcode":"20062;20062",
    "iso:country":"IT",
    "sg:address":"20062 Cassano D'adda",
    "sg:classifiers":[
        {
            "category":"Wholesale",
            "subcategory":"Machinery & Supplies",
            "type":"Manufacturing & Wholesale Goods"
        }
    ],
    "sg:phone":"+39 036 336 1520",
    "sg:postcode":"20062",
    "sg:province":"Milano",
    "sg:tags":[
        "activities",
        "industrial"
    ],
    "wof:name":"Tec Gasket Di Schiavone Claudio",
    "wof:placetype":"venue"
},
  "geometry": {"coordinates":[9.515581,45.53096],"type":"Point"}
}