{
  "type": "Feature",
  "properties": {
    "addr:full":"Via Cavour 7 10070 Robassomero Robassomero Torino 10070",
    "addr:housenumber":"7",
    "addr:postcode":"10070;10070",
    "addr:street":"Via Cavour",
    "iso:country":"IT",
    "sg:address":"Via Cavour 7 10070 Robassomero",
    "sg:city":"Robassomero",
    "sg:orig_category":"Motors, Brushless, Electronically Commutated",
    "sg:phone":"+39 011 924 1201",
    "sg:postcode":"10070",
    "sg:province":"Torino",
    "sg:website":"www.rcv-srl.it",
    "wof:name":"R.c.v. S.r.l.",
    "wof:placetype":"venue"
},
  "geometry": {"coordinates":[7.5887460709,45.1760749817],"type":"Point"}
}