{
  "type": "Feature",
  "properties": {
    "iso:country":"IT",
    "sg:address":"47900 Rimini",
    "sg:city":"Rimini",
    "sg:orig_category":"Hobbistica",
    "sg:phone":"+39 0541 742332",
    "sg:postcode":"47900",
    "sg:province":"Rimini",
    "wof:name":"Elma Di Marchetti E. & C. Snc",
    "wof:placetype":"venue"
},
  "geometry": {"coordinates":[12.578995,44.058655],"type":"Point"}
}