{
  "type": "Feature",
  "properties": {
    "iso:country":"IT",
    "sg:address":"35017 Piombino Dese",
    "sg:city":"Piombino Dese",
    "sg:orig_category":"Lavorazioni Metalli, Stampaggio E Saldatura",
    "sg:phone":"+39 049 936 5225",
    "sg:postcode":"35017",
    "sg:province":"Padova",
    "wof:name":"Libralato Gastone",
    "wof:placetype":"venue"
},
  "geometry": {"coordinates":[12.007536,45.604439],"type":"Point"}
}