{
  "type": "Feature",
  "properties": {
    "iso:country":"IT",
    "sg:address":"Via Spilimbergo 33/35 33034 Fagagna",
    "sg:city":"Fagagna",
    "sg:classifiers":[
        {
            "category":"Professional",
            "subcategory":"Business Services",
            "type":"Services"
        }
    ],
    "sg:phone":"+39 0432 800156",
    "sg:postcode":"33034",
    "sg:province":"Udine",
    "sg:tags":[
        "high-precision",
        "mechanic"
    ],
    "wof:name":"Buttazzoni Cesarino",
    "wof:placetype":"venue"
},
  "geometry": {"coordinates":[13.155867,46.08717],"type":"Point"}
}