{
  "type": "Feature",
  "properties": {
    "iso:country":"IT",
    "sg:address":"20030 Seveso",
    "sg:city":"Seveso",
    "sg:orig_category":"Nautica. Accessori Dei Mezzi Di Trasporto",
    "sg:phone":"+39 036 250 6940",
    "sg:postcode":"20030",
    "sg:province":"Milano",
    "sg:website":"http://www.pepposub.com",
    "wof:name":"Peppo Sub - Gorla Silvia",
    "wof:placetype":"venue"
},
  "geometry": {"coordinates":[9.207305,45.474594],"type":"Point"}
}