{
  "type": "Feature",
  "properties": {
    "iso:country":"IT",
    "sg:address":"21017 Samarate",
    "sg:city":"Samarate",
    "sg:orig_category":"Tessuti Uso Tecnico E Industriale",
    "sg:phone":"+39 0331 234950",
    "sg:postcode":"21017",
    "sg:province":"Varese",
    "wof:name":"Manifil Di Boni Anna Maria E C. Snc",
    "wof:placetype":"venue"
},
  "geometry": {"coordinates":[8.784884,45.618351],"type":"Point"}
}