{
  "type": "Feature",
  "properties": {
    "iso:country":"IT",
    "sg:address":"Via Archimede, 17/19 37036 San Martino Buon Albergo",
    "sg:city":"San Martino Buon Albergo",
    "sg:classifiers":[
        {
            "category":"Shopping",
            "subcategory":"Crafts & Fabrics",
            "type":"Retail Goods"
        }
    ],
    "sg:phone":"+39 045 878 0606",
    "sg:postcode":"37036",
    "sg:province":"Verona",
    "sg:tags":[
        "ladies'",
        "wear"
    ],
    "wof:name":"Sinico Srl",
    "wof:placetype":"venue"
},
  "geometry": {"coordinates":[11.0750656128,45.424156189],"type":"Point"}
}