{
  "type": "Feature",
  "properties": {
    "addr:full":"00185 Roma Roma Roma 00185",
    "addr:postcode":"00185;00185",
    "iso:country":"IT",
    "sg:address":"00185 Roma",
    "sg:city":"Roma",
    "sg:orig_category":"Condizionamento Aria Impianti - Produzione E Commercio",
    "sg:phone":"+39 06 444 1520",
    "sg:postcode":"00185",
    "sg:province":"Roma",
    "wof:name":"Di Massimo Franca",
    "wof:placetype":"venue"
},
  "geometry": {"coordinates":[12.51562,41.899059],"type":"Point"}
}