{
  "type": "Feature",
  "properties": {
    "iso:country":"IT",
    "sg:address":"47031 Repubblica San Marino",
    "sg:orig_category":"Macchine, Impianti Ed Attrezzature Industria Chimica. Macchine, Strumenti Ed Apparecchi Per Attivita' Industriali",
    "sg:phone":"+39 0549 910711",
    "sg:province":"SM",
    "sg:website":"http://www.decaweld.com",
    "wof:name":"Deca S.a.",
    "wof:placetype":"venue"
},
  "geometry": {"coordinates":[-85.168671,39.07534],"type":"Point"}
}