{
  "type": "Feature",
  "properties": {
    "iso:country":"IT",
    "sg:address":"Via Pradellona 60030 Santa Maria Nuova",
    "sg:city":"Santa Maria Nuova",
    "sg:classifiers":[
        {
            "category":"Shopping",
            "subcategory":"Clothing, Apparel, & Fashions",
            "type":"Retail Goods"
        }
    ],
    "sg:phone":"+39 0731 247015",
    "sg:postcode":"60030",
    "sg:province":"Ancona",
    "sg:tags":[
        "clothes"
    ],
    "wof:name":"Conf. G. & G. Srl Societa' Unipersonale",
    "wof:placetype":"venue"
},
  "geometry": {"coordinates":[13.334339,43.476009],"type":"Point"}
}