{
  "type": "Feature",
  "properties": {
    "iso:country":"IT",
    "sg:address":"Ctr Camarro Formeca 91028 Partanna",
    "sg:city":"Partanna",
    "sg:classifiers":[
        {
            "category":"Wholesale",
            "subcategory":"Painting Supplies",
            "type":"Manufacturing & Wholesale Goods"
        }
    ],
    "sg:phone":"+39 0924 87610",
    "sg:postcode":"91028",
    "sg:province":"Trapani",
    "sg:tags":[
        "paint",
        "industrial"
    ],
    "sg:website":"www.atria.it",
    "wof:name":"Colorificio Atria Srl",
    "wof:placetype":"venue"
},
  "geometry": {"coordinates":[12.514634,38.018589],"type":"Point"}
}