{
  "type": "Feature",
  "properties": {
    "addr:full":"20129 Milano Milano Milano 20129",
    "addr:postcode":"20129;20129",
    "iso:country":"IT",
    "sg:address":"20129 Milano",
    "sg:city":"Milano",
    "sg:orig_category":"Serramenti Ed Infissi. Forniture Industriali Per Prevenzione, Controllo E Sicurezza",
    "sg:phone":"+39 02 745219",
    "sg:postcode":"20129",
    "sg:province":"Milano",
    "wof:name":"Monopoli Adriano",
    "wof:placetype":"venue"
},
  "geometry": {"coordinates":[9.212657,45.472752],"type":"Point"}
}