{
  "type": "Feature",
  "properties": {
    "iso:country":"IT",
    "sg:address":"20092 Cinisello Balsamo",
    "sg:city":"Cinisello Balsamo",
    "sg:orig_category":"Servizi Per Lo Sport E Il Tempo Libero. Servizi Al Turismo",
    "sg:phone":"+39 02 6604 5528",
    "sg:postcode":"20092",
    "sg:province":"Milano",
    "wof:name":"Bowling Cinisello S.r.l.",
    "wof:placetype":"venue"
},
  "geometry": {"coordinates":[9.229804,45.547642],"type":"Point"}
}