{
  "type": "Feature",
  "properties": {
    "addr:full":"37135 Verona Verona Verona 37135",
    "addr:postcode":"37135;37135",
    "iso:country":"IT",
    "sg:address":"37135 Verona",
    "sg:city":"Verona",
    "sg:orig_category":"Macchine, Impianti E Forniture Per Industria Grafica, Cartaria E Cartotecnica",
    "sg:phone":"+39 045 502481",
    "sg:postcode":"37135",
    "sg:province":"Verona",
    "wof:name":"Imas Grafica Srl",
    "wof:placetype":"venue"
},
  "geometry": {"coordinates":[10.966032,45.409283],"type":"Point"}
}