{
  "type": "Feature",
  "properties": {
    "iso:country":"IT",
    "sg:address":"20070 San Zenone Al Lambro",
    "sg:city":"San Zenone al Lambro",
    "sg:orig_category":"Studi E Consulenze Tecniche E Industriali. Assicurazioni E Servizi Assicurativi. Consulenze Tecniche, Amministrative E Perizie",
    "sg:phone":"+39 02 9826 0310",
    "sg:postcode":"20070",
    "sg:province":"Milano",
    "wof:name":"Mastronardi Perito Infortunistica Stradale Pietro",
    "wof:placetype":"venue"
},
  "geometry": {"coordinates":[9.125641,45.471767],"type":"Point"}
}