{
  "type": "Feature",
  "properties": {
    "iso:country":"IT",
    "sg:address":"Via Corato 594 70031 Andria",
    "sg:city":"Andria",
    "sg:classifiers":[
        {
            "category":"Utilities",
            "subcategory":"Fuel Oil & Lpg",
            "type":"Services"
        }
    ],
    "sg:phone":"+39 0883 564994",
    "sg:postcode":"70031",
    "sg:province":"Bari",
    "sg:tags":[
        "truck",
        "vehicle"
    ],
    "sg:website":"www.pomosrl.com",
    "wof:name":"Pomo S.r.l.",
    "wof:placetype":"venue"
},
  "geometry": {"coordinates":[16.312813,41.215111],"type":"Point"}
}