{
  "type": "Feature",
  "properties": {
    "iso:country":"IT",
    "sg:address":"34147 Trieste",
    "sg:city":"Trieste",
    "sg:orig_category":"Caffe' Crudo E Torrefatto",
    "sg:phone":"+39 040 280858",
    "sg:postcode":"34147",
    "sg:province":"Trieste",
    "sg:website":"http://www.demus.it",
    "wof:name":"Demus Spa",
    "wof:placetype":"venue"
},
  "geometry": {"coordinates":[13.809872,45.616688],"type":"Point"}
}