{
  "type": "Feature",
  "properties": {
    "iso:country":"IT",
    "sg:address":"20068 Peschiera Borromeo",
    "sg:city":"Peschiera Borromeo",
    "sg:orig_category":"Macchine E Forniture Per Ecologia E Smaltimento Rifiuti. Forniture Per Attivita' Industriali",
    "sg:phone":"+39 02 5530 0732",
    "sg:postcode":"20068",
    "sg:province":"Milano",
    "wof:name":"Ma.in.a. Srl",
    "wof:placetype":"venue"
},
  "geometry": {"coordinates":[9.289042,45.436001],"type":"Point"}
}