{
  "type": "Feature",
  "properties": {
    "iso:country":"IT",
    "sg:address":"55, V. G. Gregoraci 00173 Roma",
    "sg:city":"Roma",
    "sg:classifiers":[
        {
            "category":"Shopping",
            "subcategory":"Stationery & Office Supplies",
            "type":"Retail Goods"
        }
    ],
    "sg:phone":"+39 06 7267 2810",
    "sg:postcode":"00173",
    "sg:province":"Roma",
    "sg:tags":[
        "professional"
    ],
    "sg:website":"http://www.vetrinadesign.it",
    "wof:name":"Vetrina Design Di Marchelli",
    "wof:placetype":"venue"
},
  "geometry": {"coordinates":[12.59790802,41.8432273865],"type":"Point"}
}