{
  "type": "Feature",
  "properties": {
    "iso:country":"IT",
    "sg:address":"20061 Carugate",
    "sg:city":"Carugate",
    "sg:orig_category":"Materiali E Componenti Elettrotecnici",
    "sg:phone":"+39 0292711",
    "sg:postcode":"20061",
    "sg:province":"Milano",
    "sg:website":"http://www.smcitalia.it",
    "wof:name":"Smc Italia Spa",
    "wof:placetype":"venue"
},
  "geometry": {"coordinates":[9.29391,45.544205],"type":"Point"}
}