{
  "type": "Feature",
  "properties": {
    "addr:full":"7, Via Piave 20029 Turbigo Turbigo Milano 20029",
    "addr:postcode":"20029;20029",
    "addr:street":"Via Piave",
    "iso:country":"IT",
    "sg:address":"7, Via Piave 20029 Turbigo",
    "sg:city":"Turbigo",
    "sg:classifiers":[
        {
            "category":"Manufacturing",
            "subcategory":"Textiles",
            "type":"Manufacturing & Wholesale Goods"
        }
    ],
    "sg:phone":"+39 0331 899448",
    "sg:postcode":"20029",
    "sg:province":"Milano",
    "sg:tags":[
        "leather",
        "raw",
        "material",
        "-"
    ],
    "wof:name":"Conceria Cafra (s.r.l.)",
    "wof:placetype":"venue"
},
  "geometry": {"coordinates":[8.730738,45.533161],"type":"Point"}
}