{
  "type": "Feature",
  "properties": {
    "addr:full":"50053 Empoli Empoli Firenze 50053",
    "addr:postcode":"50053;50053",
    "iso:country":"IT",
    "sg:address":"50053 Empoli",
    "sg:city":"Empoli",
    "sg:orig_category":"Pubblicita' - Agenzie Studi",
    "sg:phone":"+39 0571 534938",
    "sg:postcode":"50053",
    "sg:province":"Firenze",
    "wof:name":"Il Caravaggio",
    "wof:placetype":"venue"
},
  "geometry": {"coordinates":[10.94835186,43.7188529968],"type":"Point"}
}