{
  "type": "Feature",
  "properties": {
    "addr:full":"54, Via Del Lavoro 40056 Crespellano Crespellano Bologna 40056",
    "addr:postcode":"40056;40056",
    "addr:street":"Via Del Lavoro",
    "iso:country":"IT",
    "sg:address":"54, Via Del Lavoro 40056 Crespellano",
    "sg:city":"Crespellano",
    "sg:classifiers":[
        {
            "category":"Manufacturing",
            "subcategory":"Lumber",
            "type":"Manufacturing & Wholesale Goods"
        }
    ],
    "sg:phone":"+39 39051733306",
    "sg:postcode":"40056",
    "sg:province":"Bologna",
    "sg:tags":[
        "wood"
    ],
    "wof:name":"Metallegno (s.n.c.)",
    "wof:placetype":"venue"
},
  "geometry": {"coordinates":[11.179232,44.549622],"type":"Point"}
}