{
  "type": "Feature",
  "properties": {
    "iso:country":"IT",
    "sg:address":"23889 Santa Maria Hoe'",
    "sg:orig_category":"Biancheria, Telerie E Coperte. Forniture Alle Strutture Ricettive",
    "sg:phone":"+39 039 531 2028",
    "sg:postcode":"23889",
    "sg:province":"Lecco",
    "wof:name":"Confezioni Zini Srl",
    "wof:placetype":"venue"
},
  "geometry": {"coordinates":[9.426787,45.75758],"type":"Point"}
}