{
  "type": "Feature",
  "properties": {
    "iso:country":"IT",
    "sg:address":"17, Localita' Gerardin 11020 Saint-christophe",
    "sg:city":"Saint-Christophe",
    "sg:classifiers":[
        {
            "category":"Building & Trades",
            "subcategory":"Construction",
            "type":"Services"
        }
    ],
    "sg:phone":"+39 0165 262077",
    "sg:postcode":"11020",
    "sg:province":"Aosta",
    "sg:tags":[
        "work",
        "public"
    ],
    "wof:name":"Gheller Raimondo Sas Fratelloi Gheller",
    "wof:placetype":"venue"
},
  "geometry": {"coordinates":[7.350946,45.743778],"type":"Point"}
}