{
  "type": "Feature",
  "properties": {
    "addr:full":"22036 Erba Erba Como 22036",
    "addr:postcode":"22036;22036",
    "iso:country":"IT",
    "sg:address":"22036 Erba",
    "sg:city":"Erba",
    "sg:orig_category":"Fucinatura",
    "sg:phone":"+39 031 642332",
    "sg:postcode":"22036",
    "sg:province":"Como",
    "wof:name":"Stamperia Resegone Srl",
    "wof:placetype":"venue"
},
  "geometry": {"coordinates":[9.2207365036,45.8029212952],"type":"Point"}
}