{
  "type": "Feature",
  "properties": {
    "addr:full":"53, Via Casamassima 70010 Capurso Capurso Bari 70010",
    "addr:postcode":"70010;70010",
    "addr:street":"Via Casamassima",
    "iso:country":"IT",
    "sg:address":"53, Via Casamassima 70010 Capurso",
    "sg:city":"Capurso",
    "sg:classifiers":[
        {
            "category":"Shopping",
            "subcategory":"Clothing, Apparel, & Fashions",
            "type":"Retail Goods"
        }
    ],
    "sg:phone":"+39 080 455 0327",
    "sg:postcode":"70010",
    "sg:province":"Bari",
    "sg:tags":[
        "clothing",
        "accessory"
    ],
    "wof:name":"Nuova Fil - Tex Srl",
    "wof:placetype":"venue"
},
  "geometry": {"coordinates":[16.888042,41.038048],"type":"Point"}
}