{
  "type": "Feature",
  "properties": {
    "iso:country":"IT",
    "sg:address":"33050 Pozzuolo Del Friuli",
    "sg:city":"Pozzuolo del Friuli",
    "sg:orig_category":"Acciaierie E Fonderie",
    "sg:phone":"+39 0432 613211",
    "sg:postcode":"33050",
    "sg:province":"Udine",
    "wof:name":"Acciaierie Bertoli Safau Spa",
    "wof:placetype":"venue"
},
  "geometry": {"coordinates":[13.237386,46.005566],"type":"Point"}
}