{
  "type": "Feature",
  "properties": {
    "iso:country":"IT",
    "sg:address":"20149 Milano",
    "sg:city":"Milano",
    "sg:classifiers":[
        {
            "category":"Health Services",
            "subcategory":"Health Practitioner",
            "type":"Services"
        }
    ],
    "sg:phone":"+39 02 468825",
    "sg:postcode":"20149",
    "sg:province":"Milano",
    "sg:tags":[
        "medici"
    ],
    "wof:name":"Pozzi Lucia",
    "wof:placetype":"venue"
},
  "geometry": {"coordinates":[9.148733139,45.4731674194],"type":"Point"}
}