{
  "type": "Feature",
  "properties": {
    "iso:country":"IT",
    "sg:address":"10, Via S. Damaso 46046 Medole",
    "sg:city":"Medole",
    "sg:classifiers":[
        {
            "category":"Shopping",
            "subcategory":"Clothing, Apparel, & Fashions",
            "type":"Retail Goods"
        }
    ],
    "sg:phone":"+39 390 376 8671",
    "sg:postcode":"46046",
    "sg:province":"Mantova",
    "sg:tags":[
        "clothes"
    ],
    "wof:name":"Pompea Spa",
    "wof:placetype":"venue"
},
  "geometry": {"coordinates":[10.797698,45.160366],"type":"Point"}
}