{
  "type": "Feature",
  "properties": {
    "iso:country":"IT",
    "sg:address":"Via Balduina 3 42010 Rio Saliceto",
    "sg:classifiers":[
        {
            "category":"Wholesale",
            "subcategory":"Vending Machines",
            "type":"Manufacturing & Wholesale Goods"
        }
    ],
    "sg:phone":"+39 0522 699421",
    "sg:postcode":"42010",
    "sg:province":"Reggio Nell'Emilia",
    "sg:tags":[
        "equipment",
        "street",
        "cleaning"
    ],
    "sg:website":"www.unieco.it",
    "wof:name":"Unieco Costruzioni Meccaniche Srl",
    "wof:placetype":"venue"
},
  "geometry": {"coordinates":[10.820662,44.826431],"type":"Point"}
}