{
  "type": "Feature",
  "properties": {
    "addr:full":"46, Via Bassanese 31044 Montebelluna Montebelluna Treviso 31044",
    "addr:postcode":"31044;31044",
    "addr:street":"Via Bassanese",
    "iso:country":"IT",
    "sg:address":"46, Via Bassanese 31044 Montebelluna",
    "sg:city":"Montebelluna",
    "sg:classifiers":[
        {
            "category":"Manufacturing",
            "subcategory":"Textiles",
            "type":"Manufacturing & Wholesale Goods"
        }
    ],
    "sg:phone":"+39 0423 600560",
    "sg:postcode":"31044",
    "sg:province":"Treviso",
    "sg:tags":[
        "leather",
        "raw",
        "material",
        "-"
    ],
    "wof:name":"Groppo",
    "wof:placetype":"venue"
},
  "geometry": {"coordinates":[12.020353,45.77911],"type":"Point"}
}