{
  "type": "Feature",
  "properties": {
    "addr:full":"Via Don Minzoni, 23/33; Roges; 87036 Roges Cosenza 87036",
    "addr:housenumber":"23 / 33",
    "addr:postcode":"87036;87036",
    "addr:street":"Via Don Minzoni;Roges",
    "iso:country":"IT",
    "sg:address":"Via Don Minzoni, 23/33; Roges; 87036",
    "sg:city":"Roges",
    "sg:classifiers":[
        {
            "category":"Banks & Credit Unions",
            "subcategory":"Bank",
            "type":"Services"
        }
    ],
    "sg:phone":"+39 0984 462644",
    "sg:postcode":"87036",
    "sg:province":"Cosenza",
    "wof:name":"Banca Nazionale Del Lavoro",
    "wof:placetype":"venue"
},
  "geometry": {"coordinates":[16.216913,39.357628],"type":"Point"}
}