{
  "type": "Feature",
  "properties": {
    "addr:full":"29100 Piacenza Piacenza Piacenza 29100",
    "addr:postcode":"29100;29100",
    "iso:country":"IT",
    "sg:address":"29100 Piacenza",
    "sg:city":"Piacenza",
    "sg:orig_category":"Cartotecnica E Servizi. Forniture Per Uffici",
    "sg:phone":"+39 0523 590799",
    "sg:postcode":"29100",
    "sg:province":"Piacenza",
    "wof:name":"Grafica Maserati Snc",
    "wof:placetype":"venue"
},
  "geometry": {"coordinates":[9.728547,45.051823],"type":"Point"}
}