{
  "type": "Feature",
  "properties": {
    "iso:country":"IT",
    "sg:address":"00177 Roma",
    "sg:city":"Roma",
    "sg:orig_category":"Cinematografia E Radiotelevisione. Pubblicita', Marketing E Comunicazione",
    "sg:phone":"+39 06 2440 7238",
    "sg:postcode":"00177",
    "sg:province":"Roma",
    "sg:website":"http://www.tograaudiopro.com",
    "wof:name":"Togra Snc Di Antonio Grande & C.",
    "wof:placetype":"venue"
},
  "geometry": {"coordinates":[12.543642,41.88728],"type":"Point"}
}