{
  "type": "Feature",
  "properties": {
    "addr:full":"Via Caduti Del Lavoro 34 25082 Botticino Sera Botticino Brescia 25082",
    "addr:housenumber":"34",
    "addr:postcode":"25082;25082",
    "addr:street":"Via Caduti Del Lavoro",
    "iso:country":"IT",
    "sg:address":"Via Caduti Del Lavoro 34 25082 Botticino Sera",
    "sg:city":"Botticino",
    "sg:classifiers":[
        {
            "category":"Manufacturing",
            "subcategory":"Rubber & Plastics",
            "type":"Manufacturing & Wholesale Goods"
        }
    ],
    "sg:phone":"+39 030 269 1194",
    "sg:postcode":"25082",
    "sg:province":"Brescia",
    "sg:tags":[
        "bags",
        "polyethylene",
        "sack",
        "bag"
    ],
    "wof:name":"Servo-tex Di Biemmi Antonio",
    "wof:placetype":"venue"
},
  "geometry": {"coordinates":[10.3114099503,45.5288734436],"type":"Point"}
}