{
  "type": "Feature",
  "properties": {
    "iso:country":"IT",
    "sg:address":"Viale Martiri Via Fani 70055 Minervino Murge",
    "sg:city":"Minervino Murge",
    "sg:classifiers":[
        {
            "category":"Shopping",
            "subcategory":"Clothing, Apparel, & Fashions",
            "type":"Retail Goods"
        }
    ],
    "sg:phone":"+39 0883 694257",
    "sg:postcode":"70055",
    "sg:province":"Bari",
    "sg:tags":[
        "clothes"
    ],
    "wof:name":"Fapel (s.n.c.)",
    "wof:placetype":"venue"
},
  "geometry": {"coordinates":[16.084383,41.07703],"type":"Point"}
}