{
  "type": "Feature",
  "properties": {
    "iso:country":"IT",
    "sg:address":"89900 Vibo Valentia",
    "sg:city":"Vibo Valentia",
    "sg:orig_category":"Macchine Ed Impianti Per Edilizia E Lavori Pubblici. Elettronica Industriale, Prodotti E Apparecchiature",
    "sg:phone":"+39 0963 577721",
    "sg:postcode":"89900",
    "sg:province":"Vibo Valentia",
    "wof:name":"Semafori Controlli Automazione Elettronica S.c.a.e. Spa",
    "wof:placetype":"venue"
},
  "geometry": {"coordinates":[16.116837,38.710964],"type":"Point"}
}