{
  "type": "Feature",
  "properties": {
    "addr:full":"2, Via Dell' Industria 24052 Azzano San Paolo Azzano San Paolo Bergamo 24052",
    "addr:postcode":"24052;24052",
    "addr:street":"Via Dell ' Industria",
    "iso:country":"IT",
    "sg:address":"2, Via Dell' Industria 24052 Azzano San Paolo",
    "sg:city":"Azzano San Paolo",
    "sg:classifiers":[
        {
            "category":"Wholesale",
            "subcategory":"Drugs",
            "type":"Manufacturing & Wholesale Goods"
        }
    ],
    "sg:phone":"+39 39035530019",
    "sg:postcode":"24052",
    "sg:province":"Bergamo",
    "sg:tags":[
        "chemical",
        "pharmaceutical"
    ],
    "wof:name":"Astra Vernici Srl",
    "wof:placetype":"venue"
},
  "geometry": {"coordinates":[9.673593,45.667751],"type":"Point"}
}