{
  "type": "Feature",
  "properties": {
    "iso:country":"IT",
    "sg:address":"Via S. Cristoforo 36 40064 Ozzano Dell'emilia",
    "sg:classifiers":[
        {
            "category":"Manufacturing",
            "subcategory":"Rubber & Plastics",
            "type":"Manufacturing & Wholesale Goods"
        }
    ],
    "sg:phone":"+39 051 799759",
    "sg:postcode":"40064",
    "sg:province":"Bologna",
    "sg:tags":[
        "joint"
    ],
    "sg:website":"www.mpgomma.com",
    "wof:name":"M.p. Industria Della Gomma Srl",
    "wof:placetype":"venue"
},
  "geometry": {"coordinates":[11.346481,44.494221],"type":"Point"}
}