{
  "type": "Feature",
  "properties": {
    "iso:country":"IT",
    "sg:address":"25017 Lonato",
    "sg:city":"Lonato",
    "sg:orig_category":"Consulenze Speciali",
    "sg:phone":"+39 030 991 9012",
    "sg:postcode":"25017",
    "sg:province":"Brescia",
    "wof:name":"Bazzoli P.i. Alberto",
    "wof:placetype":"venue"
},
  "geometry": {"coordinates":[10.48619,45.462898],"type":"Point"}
}