{
  "type": "Feature",
  "properties": {
    "addr:full":"20133 Milano Milano Milano 20133",
    "addr:postcode":"20133;20133",
    "iso:country":"IT",
    "sg:address":"20133 Milano",
    "sg:city":"Milano",
    "sg:orig_category":"Abbigliamento Esterno, Maglierie E Pelliccerie. Servizi E Lavori Per Abbigliamento E Pelletterie",
    "sg:phone":"+39 02 236 7085",
    "sg:postcode":"20133",
    "sg:province":"Milano",
    "wof:name":"Monti Antonio",
    "wof:placetype":"venue"
},
  "geometry": {"coordinates":[9.232064,45.482002],"type":"Point"}
}