{
  "type": "Feature",
  "properties": {
    "iso:country":"IT",
    "sg:address":"54/a, Via Vittorio Veneto 00187 Roma",
    "sg:city":"Roma",
    "sg:classifiers":[
        {
            "category":"Airport",
            "subcategory":"General Aviation",
            "type":"Transportation"
        }
    ],
    "sg:phone":"+39 39064882680",
    "sg:postcode":"00187",
    "sg:province":"Roma",
    "sg:tags":[
        "transport",
        "air"
    ],
    "wof:name":"Linee Aeree Polacche - Polish Airlines",
    "wof:placetype":"venue"
},
  "geometry": {"coordinates":[12.4468,42.105164],"type":"Point"}
}