{
  "type": "Feature",
  "properties": {
    "iso:country":"IT",
    "sg:address":"33030 Buia",
    "sg:orig_category":"Banche E Servizi Finanziari",
    "sg:phone":"+39 0432 964375",
    "sg:postcode":"33030",
    "sg:province":"Udine",
    "wof:name":"Fin-de Srl",
    "wof:placetype":"venue"
},
  "geometry": {"coordinates":[13.131496,46.207909],"type":"Point"}
}