{
  "type": "Feature",
  "properties": {
    "iso:country":"IT",
    "sg:address":"00178 Roma",
    "sg:city":"Roma",
    "sg:classifiers":[
        {
            "category":"Government",
            "subcategory":"Office",
            "type":"Public Place"
        }
    ],
    "sg:phone":"+39 06 718 8103",
    "sg:postcode":"00178",
    "sg:province":"Roma",
    "sg:tags":[
        "sector",
        "fair",
        "entertainment",
        "supply",
        "non-professional",
        "engineering",
        "congresses",
        "supplies",
        "professional",
        "automation",
        "electronic",
        "events",
        "machines"
    ],
    "wof:name":"Full Screen Srl",
    "wof:placetype":"venue"
},
  "geometry": {"coordinates":[12.5643234253,41.8454856873],"type":"Point"}
}