{
  "type": "Feature",
  "properties": {
    "addr:full":"1, Via Calendoni 23885 Calco Calco Lecco 23885",
    "addr:postcode":"23885;23885",
    "addr:street":"Via Calendoni",
    "iso:country":"IT",
    "sg:address":"1, Via Calendoni 23885 Calco",
    "sg:city":"Calco",
    "sg:classifiers":[
        {
            "category":"Shopping",
            "type":"Retail Goods"
        }
    ],
    "sg:phone":"+39 39039508551",
    "sg:postcode":"23885",
    "sg:province":"Lecco",
    "sg:tags":[
        "finished",
        "-",
        "metallic"
    ],
    "wof:name":"Fumagalli Srl",
    "wof:placetype":"venue"
},
  "geometry": {"coordinates":[9.408121109,45.723941803],"type":"Point"}
}