{
  "type": "Feature",
  "properties": {
    "iso:country":"IT",
    "sg:address":"5, V. Degli Artigiani",
    "sg:city":"Ginestra fiorentina",
    "sg:classifiers":[
        {
            "category":"Real Estate",
            "subcategory":"Architect",
            "type":"Services"
        }
    ],
    "sg:phone":"+39 055 871 3806",
    "sg:postcode":"50055",
    "sg:province":"Firenze",
    "sg:tags":[
        "textile",
        "clothing"
    ],
    "sg:website":"http://www.b2btogether.it:ws_end: :mark:ws:http://www.paginegialle.it/together",
    "wof:name":"Together Srl",
    "wof:placetype":"venue"
},
  "geometry": {"coordinates":[11.256902,43.768734],"type":"Point"}
}