{
  "type": "Feature",
  "properties": {
    "addr:full":"Fondo Valle Bradano Km 15,00 75022 Irsina Irsina Matera 75022",
    "addr:housenumber":"15,00",
    "addr:postcode":"75022;75022",
    "addr:street":"Fondo Valle Bradano Km",
    "iso:country":"IT",
    "sg:address":"Fondo Valle Bradano Km 15,00 75022 Irsina",
    "sg:city":"Irsina",
    "sg:classifiers":[
        {
            "category":"Wholesale",
            "subcategory":"Drugs",
            "type":"Manufacturing & Wholesale Goods"
        }
    ],
    "sg:phone":"+39 0835 517991",
    "sg:postcode":"75022",
    "sg:province":"Matera",
    "sg:tags":[
        "chemical",
        "pharmaceutical"
    ],
    "wof:name":"Sud Officinale Coop. Agricola S.r.l.",
    "wof:placetype":"venue"
},
  "geometry": {"coordinates":[16.606087,40.668652],"type":"Point"}
}