{
  "type": "Feature",
  "properties": {
    "addr:full":"66100 Chieti Chieti Chieti 66100",
    "addr:postcode":"66100;66100",
    "iso:country":"IT",
    "sg:address":"66100 Chieti",
    "sg:city":"Chieti",
    "sg:orig_category":"Scuole E Servizi Scolastici",
    "sg:phone":"+39 0871 330263",
    "sg:postcode":"66100",
    "sg:province":"Chieti",
    "wof:name":"Cooperativa Abruzzese Del Laboratorio Teatrale D'arte",
    "wof:placetype":"venue"
},
  "geometry": {"coordinates":[14.16847,42.350361],"type":"Point"}
}