{
  "type": "Feature",
  "properties": {
    "iso:country":"IT",
    "sg:address":"Vle Lombardia 63/a 22063 Cantu'",
    "sg:classifiers":[
        {
            "category":"Bus Stop",
            "subcategory":"None",
            "type":"Transportation"
        }
    ],
    "sg:phone":"+39 031 732938",
    "sg:postcode":"22063",
    "sg:province":"Como",
    "sg:tags":[
        "period",
        "furniture"
    ],
    "sg:website":"www.mice.net",
    "wof:name":"Mice Di Rugiano Domenico E C. Snc",
    "wof:placetype":"venue"
},
  "geometry": {"coordinates":[9.1269578934,45.7409934998],"type":"Point"}
}