{
  "type": "Feature",
  "properties": {
    "addr:full":"25063 Gardone Val Trompia Gardone Val Trompia Brescia 25063",
    "addr:postcode":"25063;25063",
    "iso:country":"IT",
    "sg:address":"25063 Gardone Val Trompia",
    "sg:city":"Gardone Val Trompia",
    "sg:orig_category":"Armi E Munizioni - Produzione E Ingrosso",
    "sg:phone":"+39 030 891 5000",
    "sg:postcode":"25063",
    "sg:province":"Brescia",
    "sg:website":"http://www.davide-pedersoli.com",
    "wof:name":"Pedersoli Davide & C. Snc",
    "wof:placetype":"venue"
},
  "geometry": {"coordinates":[10.187927,45.677982],"type":"Point"}
}