{
  "type": "Feature",
  "properties": {
    "iso:country":"IT",
    "sg:address":"36100 Vicenza",
    "sg:city":"Vicenza",
    "sg:orig_category":"Pubblicita', Marketing E Comunicazione",
    "sg:phone":"+39 0444 276101",
    "sg:postcode":"36100",
    "sg:province":"Vicenza",
    "wof:name":"Studio Bicego Srl",
    "wof:placetype":"venue"
},
  "geometry": {"coordinates":[11.4936761856,45.5355949402],"type":"Point"}
}