{
  "type": "Feature",
  "properties": {
    "addr:full":"Via Monte Grappa 12; Osio Sotto; 24046 Osio Sotto Bergamo 24046",
    "addr:housenumber":"12",
    "addr:postcode":"24046;24046",
    "addr:street":"Via Monte Grappa",
    "iso:country":"IT",
    "sg:address":"Via Monte Grappa 12; Osio Sotto; 24046",
    "sg:city":"Osio Sotto",
    "sg:classifiers":[
        {
            "category":"Banks & Credit Unions",
            "subcategory":"Bank",
            "type":"Services"
        }
    ],
    "sg:phone":"+39 035 881844",
    "sg:postcode":"24046",
    "sg:province":"Bergamo",
    "wof:name":"Banca Popolare Di Sondrio Scarl",
    "wof:placetype":"venue"
},
  "geometry": {"coordinates":[9.594275,45.614342],"type":"Point"}
}