{
  "type": "Feature",
  "properties": {
    "addr:full":"00171 Roma Roma Roma 00171",
    "addr:postcode":"00171;00171",
    "iso:country":"IT",
    "sg:address":"00171 Roma",
    "sg:city":"Roma",
    "sg:orig_category":"Prodotti Alimentari",
    "sg:phone":"+39 06 215 6230",
    "sg:postcode":"00171",
    "sg:province":"Roma",
    "wof:name":"Parsi Stefano",
    "wof:placetype":"venue"
},
  "geometry": {"coordinates":[12.5641794205,41.8911590576],"type":"Point"}
}