{
  "type": "Feature",
  "properties": {
    "iso:country":"IT",
    "sg:address":"45100 Rovigo",
    "sg:city":"Rovigo",
    "sg:orig_category":"Articoli Per Imballaggio E Confezionamento",
    "sg:phone":"+39 0425 403111",
    "sg:postcode":"45100",
    "sg:province":"Rovigo",
    "sg:website":"http://www.siccspa.it",
    "wof:name":"Sicc Spa",
    "wof:placetype":"venue"
},
  "geometry": {"coordinates":[11.788043,45.051949],"type":"Point"}
}