{
  "type": "Feature",
  "properties": {
    "iso:country":"IT",
    "sg:address":"3, Strada Privata Lamarmora 28062 Cameri",
    "sg:city":"Cameri",
    "sg:classifiers":[
        {
            "category":"Retail",
            "subcategory":"Animal Services",
            "type":"Services"
        }
    ],
    "sg:phone":"+39 0321 519805",
    "sg:postcode":"28062",
    "sg:province":"Novara",
    "sg:tags":[
        "breeding"
    ],
    "wof:name":"Industrie Salustrid Rocky S.r.l.",
    "wof:placetype":"venue"
},
  "geometry": {"coordinates":[8.669309,45.496574],"type":"Point"}
}