{
  "type": "Feature",
  "properties": {
    "iso:country":"IT",
    "sg:address":"80040 San Sebastiano Al Vesuvio",
    "sg:city":"San Sebastiano al Vesuvio",
    "sg:orig_category":"Abbigliamento Esterno, Maglierie E Pelliccerie. Forniture Per Abbigliamento E Pelletterie",
    "sg:phone":"+39 081 574 2547",
    "sg:postcode":"80040",
    "sg:province":"Napoli",
    "wof:name":"Ascione Giuseppe",
    "wof:placetype":"venue"
},
  "geometry": {"coordinates":[14.368611,40.84565],"type":"Point"}
}