{
  "type": "Feature",
  "properties": {
    "iso:country":"IT",
    "sg:address":"25, Via Dei Mille 27058 Voghera",
    "sg:city":"Voghera",
    "sg:classifiers":[
        {
            "category":"Autos & Motor Vehicles",
            "subcategory":"Automobile Sales",
            "type":"Retail Goods"
        }
    ],
    "sg:phone":"+39 0383 212422",
    "sg:postcode":"27058",
    "sg:province":"Pavia",
    "sg:tags":[
        "industrial"
    ],
    "wof:name":"F.a.r.a.m. (s.p.a.)",
    "wof:placetype":"venue"
},
  "geometry": {"coordinates":[8.999272,44.994167],"type":"Point"}
}