{
  "type": "Feature",
  "properties": {
    "addr:full":"16128 Genova Genova Genova 16128",
    "addr:postcode":"16128;16128",
    "iso:country":"IT",
    "sg:address":"16128 Genova",
    "sg:city":"Genova",
    "sg:orig_category":"Impiantistica E Prodotti Tecnologici Per Edilizia",
    "sg:phone":"+39 010 251 8616",
    "sg:postcode":"16128",
    "sg:province":"Genova",
    "wof:name":"Coop. Custodia Automobili",
    "wof:placetype":"venue"
},
  "geometry": {"coordinates":[8.925174,44.407818],"type":"Point"}
}