{
  "type": "Feature",
  "properties": {
    "iso:country":"IT",
    "sg:address":"24/bis, Via Condove 10050 Borgone Susa",
    "sg:city":"Borgone Susa",
    "sg:classifiers":[
        {
            "category":"Professional",
            "subcategory":"Engineering",
            "type":"Services"
        }
    ],
    "sg:phone":"+39 011 964 5424",
    "sg:postcode":"10050",
    "sg:province":"Torino",
    "sg:tags":[
        "machine",
        "-",
        "mechanical"
    ],
    "wof:name":"Sacmo Srl A Socio Unico",
    "wof:placetype":"venue"
},
  "geometry": {"coordinates":[7.120077,45.126019],"type":"Point"}
}