{
  "type": "Feature",
  "properties": {
    "iso:country":"IT",
    "sg:address":"49/c, Zona Industriale 52043 Castiglion Fiorentino",
    "sg:city":"Castiglion Fiorentino",
    "sg:classifiers":[
        {
            "category":"Personal",
            "subcategory":"Shoe Repair & Shine",
            "type":"Services"
        }
    ],
    "sg:phone":"+39 0575 653066",
    "sg:postcode":"52043",
    "sg:province":"Arezzo",
    "sg:tags":[
        "leather"
    ],
    "wof:name":"Calzaturificio Celini (s.r.l.)",
    "wof:placetype":"venue"
},
  "geometry": {"coordinates":[11.863062,43.471203],"type":"Point"}
}