{
  "type": "Feature",
  "properties": {
    "iso:country":"IT",
    "sg:address":"48100 Ravenna",
    "sg:city":"Ravenna",
    "sg:orig_category":"Servizi Ausiliari Per Il Trasporto",
    "sg:phone":"+39 0544 436437",
    "sg:postcode":"48100",
    "sg:province":"Ravenna",
    "wof:name":"Iron Service (s.r.l.)",
    "wof:placetype":"venue"
},
  "geometry": {"coordinates":[12.18221,44.397228],"type":"Point"}
}