{
  "type": "Feature",
  "properties": {
    "iso:country":"IT",
    "sg:address":"42, Via Statale N.12 41036 Medolla",
    "sg:city":"Medolla",
    "sg:classifiers":[
        {
            "category":"Shopping",
            "subcategory":"Clothing, Apparel, & Fashions",
            "type":"Retail Goods"
        }
    ],
    "sg:phone":"+39 39053553281",
    "sg:postcode":"41036",
    "sg:province":"Modena",
    "sg:tags":[
        "clothes"
    ],
    "wof:name":"Monica Maglieria Srl",
    "wof:placetype":"venue"
},
  "geometry": {"coordinates":[11.059778,44.854713],"type":"Point"}
}