{
  "type": "Feature",
  "properties": {
    "addr:full":"Via Borghisani 9/13 26035 Pieve San Giacomo Pieve San Giacomo Cremona 26035",
    "addr:housenumber":"9 / 13",
    "addr:postcode":"26035;26035",
    "addr:street":"Via Borghisani;San Giacomo Cremona",
    "iso:country":"IT",
    "sg:address":"Via Borghisani 9/13 26035 Pieve San Giacomo",
    "sg:city":"Pieve San Giacomo",
    "sg:classifiers":[
        {
            "category":"Manufacturing",
            "subcategory":"Glass & Minerals",
            "type":"Manufacturing & Wholesale Goods"
        }
    ],
    "sg:phone":"+39 0372 64173",
    "sg:postcode":"26035",
    "sg:province":"Cremona",
    "sg:tags":[
        "machine",
        "tool",
        "working"
    ],
    "wof:name":"Stefiglass International Srl",
    "wof:placetype":"venue"
},
  "geometry": {"coordinates":[10.191221,45.135101],"type":"Point"}
}