{
  "type": "Feature",
  "properties": {
    "addr:full":"00172 Roma Roma Roma 00172",
    "addr:postcode":"00172;00172",
    "iso:country":"IT",
    "sg:address":"00172 Roma",
    "sg:city":"Roma",
    "sg:orig_category":"Arredo Camera Letto E Complementi. Servizi E Lavori Per Arredamento E Industria Del Legno",
    "sg:phone":"+39 06 230 7082",
    "sg:postcode":"00172",
    "sg:province":"Roma",
    "wof:name":"Leonardi Giancarlo",
    "wof:placetype":"venue"
},
  "geometry": {"coordinates":[12.580029,41.872047],"type":"Point"}
}