{
  "type": "Feature",
  "properties": {
    "iso:country":"IT",
    "sg:address":"37010 Cavaion Veronese",
    "sg:city":"Cavaion Veronese",
    "sg:orig_category":"Prodotti E Manufatti In Materie Plastiche",
    "sg:phone":"+39 045 723 5177",
    "sg:postcode":"37010",
    "sg:province":"Verona",
    "wof:name":"Orna Iplast Spa",
    "wof:placetype":"venue"
},
  "geometry": {"coordinates":[10.7527751923,45.5218544006],"type":"Point"}
}