{
  "type": "Feature",
  "properties": {
    "iso:country":"IT",
    "sg:address":"Via Dei Canneti 1 22030 Montorfano",
    "sg:city":"Montorfano",
    "sg:classifiers":[
        {
            "category":"Animal Shelter",
            "type":"Public Place"
        }
    ],
    "sg:phone":"+39 031 200289",
    "sg:postcode":"22030",
    "sg:province":"Como",
    "sg:tags":[
        "cage"
    ],
    "sg:website":"www.eurogabbie.it",
    "wof:name":"Eurogabbie Srl",
    "wof:placetype":"venue"
},
  "geometry": {"coordinates":[9.149663,45.783318],"type":"Point"}
}