{
  "type": "Feature",
  "properties": {
    "addr:full":"20060 Pessano Con Bornago Ornago Milano 20060",
    "addr:postcode":"20060;20060",
    "iso:country":"IT",
    "sg:address":"20060 Pessano Con Bornago",
    "sg:city":"Ornago",
    "sg:orig_category":"Prodotti E Manufatti In Materie Plastiche",
    "sg:phone":"+39 02 9574 5616",
    "sg:postcode":"20060",
    "sg:province":"Milano",
    "wof:name":"Biplast Di Barazzetta Ivano",
    "wof:placetype":"venue"
},
  "geometry": {"coordinates":[9.38697052,45.5515060425],"type":"Point"}
}