{
  "type": "Feature",
  "properties": {
    "addr:full":"125, Via Carducci Giosue' 20099 Sesto San Giovanni Sesto San Giovanni Milano 20099",
    "addr:housenumber":"125",
    "addr:postcode":"20099;20099",
    "addr:street":"Via Carducci Giosue '",
    "iso:country":"IT",
    "sg:address":"125, Via Carducci Giosue' 20099 Sesto San Giovanni",
    "sg:city":"Sesto San Giovanni",
    "sg:classifiers":[
        {
            "category":"Wholesale",
            "subcategory":"Machinery & Supplies",
            "type":"Manufacturing & Wholesale Goods"
        }
    ],
    "sg:phone":"+39 390 226 2971",
    "sg:postcode":"20099",
    "sg:province":"Milano",
    "sg:tags":[
        "equipment",
        "-",
        "instrument",
        "measurement"
    ],
    "wof:name":"Invensys Systems Italia Spa",
    "wof:placetype":"venue"
},
  "geometry": {"coordinates":[9.221711,45.531471],"type":"Point"}
}