{
  "type": "Feature",
  "properties": {
    "iso:country":"IT",
    "sg:address":"43100 Parma",
    "sg:city":"Parma",
    "sg:orig_category":"Pneumatici - Commercio E Riparazione",
    "sg:phone":"+39 0521 240032",
    "sg:postcode":"43100",
    "sg:province":"Parma",
    "wof:name":"Balestrieri Clinio",
    "wof:placetype":"venue"
},
  "geometry": {"coordinates":[10.3486680984,44.7956771851],"type":"Point"}
}