{
  "type": "Feature",
  "properties": {
    "iso:country":"IT",
    "sg:address":"Via Mazza 18; Ottiglio; 15038",
    "sg:city":"Ottiglio",
    "sg:classifiers":[
        {
            "category":"Banks & Credit Unions",
            "subcategory":"Bank",
            "type":"Services"
        }
    ],
    "sg:phone":"+39 0142 921482",
    "sg:postcode":"15038",
    "sg:province":"Alessandria",
    "wof:name":"Istituto Bancario, San Paolo Di Torino Spa",
    "wof:placetype":"venue"
},
  "geometry": {"coordinates":[8.341118,45.054913],"type":"Point"}
}