{
  "type": "Feature",
  "properties": {
    "addr:full":"2/2, V. Zago 40128 Bologna Bologna Bologna 40128",
    "addr:housenumber":"2 / 2 v.",
    "addr:postcode":"40128;40128",
    "addr:street":"Zago",
    "iso:country":"IT",
    "sg:address":"2/2, V. Zago 40128 Bologna",
    "sg:city":"Bologna",
    "sg:classifiers":[
        {
            "category":"Manufacturing",
            "subcategory":"Rubber & Plastics",
            "type":"Manufacturing & Wholesale Goods"
        }
    ],
    "sg:phone":"+39 051 415 3911",
    "sg:postcode":"40128",
    "sg:province":"Bologna",
    "wof:name":"Bertolini Divisione Plastiche Srl",
    "wof:placetype":"venue"
},
  "geometry": {"coordinates":[11.3548440933,44.5060997009],"type":"Point"}
}