{
  "type": "Feature",
  "properties": {
    "addr:full":"73017 Sannicola Sannicola Lecce 73017",
    "addr:postcode":"73017;73017",
    "iso:country":"IT",
    "sg:address":"73017 Sannicola",
    "sg:city":"Sannicola",
    "sg:orig_category":"Macchine, Impianti E Forniture Per Industria Grafica, Cartaria E Cartotecnica. Automazione E Macchine Per Ufficio",
    "sg:phone":"+39 0833 232409",
    "sg:postcode":"73017",
    "sg:province":"Lecce",
    "wof:name":"Gidef Snc Di Giovanni De Filippo & C.",
    "wof:placetype":"venue"
},
  "geometry": {"coordinates":[18.064869,40.092808],"type":"Point"}
}