{
  "type": "Feature",
  "properties": {
    "iso:country":"IT",
    "sg:address":"10126 Torino",
    "sg:city":"Torino",
    "sg:orig_category":"Idrosanitari - Commercio",
    "sg:phone":"+39 011 664 7561",
    "sg:postcode":"10126",
    "sg:province":"Torino",
    "wof:name":"Bais Di Beatrice Snc",
    "wof:placetype":"venue"
},
  "geometry": {"coordinates":[7.575251,45.063297],"type":"Point"}
}