{
  "type": "Feature",
  "properties": {
    "addr:full":"42020 Ciano D'enza Reggio Nell'Emilia 42020",
    "addr:postcode":"42020;42020",
    "addr:street":"D'Enza",
    "iso:country":"IT",
    "sg:address":"42020 Ciano D'enza",
    "sg:orig_category":"Non-classified Establishments",
    "sg:phone":"+39 0522 872208",
    "sg:postcode":"42020",
    "sg:province":"Reggio Nell'Emilia",
    "wof:name":"Bamboo Line",
    "wof:placetype":"venue"
},
  "geometry": {"coordinates":[10.456407547,44.5764083862],"type":"Point"}
}