{
  "type": "Feature",
  "properties": {
    "addr:full":"19038 Sarzana Sarzana La Spezia 19038",
    "addr:postcode":"19038;19038",
    "iso:country":"IT",
    "sg:address":"19038 Sarzana",
    "sg:city":"Sarzana",
    "sg:orig_category":"Servizi E Lavori Per Ecologia E Smaltimento Rifiuti. Termotecnica E Riscaldamento, Apparecchiature E Servizi. Servizi Ausiliari Di Sorveglianza, Manutenzione E Pulizia",
    "sg:phone":"+39 0187 691036",
    "sg:postcode":"19038",
    "sg:province":"La Spezia",
    "wof:name":"Castellini Errico",
    "wof:placetype":"venue"
},
  "geometry": {"coordinates":[9.962835,44.104794],"type":"Point"}
}