{
  "type": "Feature",
  "properties": {
    "iso:country":"IT",
    "sg:address":"22015 Gravedona",
    "sg:city":"Gravedona",
    "sg:orig_category":"Petroli, Gas E Combustibili",
    "sg:phone":"+39 0344 85330",
    "sg:postcode":"22015",
    "sg:province":"Como",
    "wof:name":"Motti Prodotti Petroliferi Snc",
    "wof:placetype":"venue"
},
  "geometry": {"coordinates":[9.3043270111,46.1420822144],"type":"Point"}
}