{
  "type": "Feature",
  "properties": {
    "iso:country":"IT",
    "sg:address":"60127 Ancona",
    "sg:city":"Ancona",
    "sg:orig_category":"Servizi Al Turismo. Servizi Ausiliari Dei Mezzi Di Trasporto. Servizi Ausiliari Per Il Trasporto. Acqua, Luce, Gas E Societa' Di Esercizio Pubblico",
    "sg:phone":"+39 071 280 1924",
    "sg:postcode":"60127",
    "sg:province":"Ancona",
    "wof:name":"I.e.c.e. Sas",
    "wof:placetype":"venue"
},
  "geometry": {"coordinates":[13.503717,43.592644],"type":"Point"}
}