{
  "type": "Feature",
  "properties": {
    "iso:country":"IT",
    "sg:address":"60035 Jesi",
    "sg:city":"Jesi",
    "sg:orig_category":"Agenzie Ed Enti Turistici. Acqua, Luce, Gas E Societa' Di Esercizio Pubblico",
    "sg:phone":"+39 0731 5381",
    "sg:postcode":"60035",
    "sg:province":"Ancona",
    "sg:website":"http://www.comune.jesi.it",
    "wof:name":"Comune Di Jesi",
    "wof:placetype":"venue"
},
  "geometry": {"coordinates":[13.254805,43.52232],"type":"Point"}
}