{
  "type": "Feature",
  "properties": {
    "iso:country":"IT",
    "sg:address":"48, Via Alighieri 60021 Camerano",
    "sg:city":"Camerano",
    "sg:classifiers":[
        {
            "category":"Wholesale",
            "subcategory":"Drugs",
            "type":"Manufacturing & Wholesale Goods"
        }
    ],
    "sg:phone":"+39 39071731452",
    "sg:postcode":"60021",
    "sg:province":"Ancona",
    "sg:tags":[
        "chemical",
        "pharmaceutical"
    ],
    "wof:name":"Springoil S.r.l.",
    "wof:placetype":"venue"
},
  "geometry": {"coordinates":[13.528869,43.515747],"type":"Point"}
}