{
  "type": "Feature",
  "properties": {
    "iso:country":"IT",
    "sg:address":"169, Via Trevigiana 31020 Sernaglia Della Battaglia",
    "sg:city":"Sernaglia della Battaglia",
    "sg:classifiers":[
        {
            "category":"Shopping",
            "subcategory":"Clothing, Apparel, & Fashions",
            "type":"Retail Goods"
        }
    ],
    "sg:phone":"+39 0438 966248",
    "sg:postcode":"31020",
    "sg:province":"Treviso",
    "sg:tags":[
        "clothes"
    ],
    "wof:name":"Confezioni 2ag Di Filippi P. & C. (s.n.c.)",
    "wof:placetype":"venue"
},
  "geometry": {"coordinates":[12.139413,45.871128],"type":"Point"}
}