{
  "type": "Feature",
  "properties": {
    "iso:country":"IT",
    "sg:address":"20159 Milano",
    "sg:city":"Milano",
    "sg:orig_category":"Ristorazione E Locali Pubblici Affini. Ristoranti Ed Esercizi Affini",
    "sg:phone":"+39 02 6900 0245",
    "sg:postcode":"20159",
    "sg:province":"Milano",
    "wof:name":"Taj Mahal Sas Di Qasim Shahzad & C.",
    "wof:placetype":"venue"
},
  "geometry": {"coordinates":[9.188176,45.489048],"type":"Point"}
}