{
  "type": "Feature",
  "properties": {
    "iso:country":"IT",
    "sg:address":"20090 Vimodrone",
    "sg:city":"Vimodrone",
    "sg:orig_category":"Servizi E Lavori Per Industria Alimentare E Bevande. Servizi E Lavori Per Abbigliamento E Pelletterie. Servizi E Lavori Per Arredamento E Industria Del Legno. Servizi Vari Di Interesse Pubblico",
    "sg:phone":"+39 02 2500 7092",
    "sg:postcode":"20090",
    "sg:province":"Milano",
    "wof:name":"Rs Components Spa",
    "wof:placetype":"venue"
},
  "geometry": {"coordinates":[9.301821,45.516483],"type":"Point"}
}