{
  "type": "Feature",
  "properties": {
    "addr:full":"35028 Piove Di Sacco Piove di Sacco Padova 35028",
    "addr:postcode":"35028;35028",
    "iso:country":"IT",
    "sg:address":"35028 Piove Di Sacco",
    "sg:city":"Piove di Sacco",
    "sg:orig_category":"Elettrodomestici. Elettronica Professionale E Di Consumo. Arredi Ed Attrezzature Per Attivita' Commerciali Ed Artigianali. Macchine, Strumenti Ed Apparecchi Per Attivita' Industriali",
    "sg:phone":"+39 049 970 4330",
    "sg:postcode":"35028",
    "sg:province":"Padova",
    "wof:name":"Mezzalana Snc",
    "wof:placetype":"venue"
},
  "geometry": {"coordinates":[12.057671,45.291767],"type":"Point"}
}