{
  "type": "Feature",
  "properties": {
    "addr:full":"20123 Milano Milano Milano 20123",
    "addr:postcode":"20123;20123",
    "iso:country":"IT",
    "sg:address":"20123 Milano",
    "sg:city":"Milano",
    "sg:orig_category":"Scuole E Servizi Scolastici",
    "sg:phone":"+39 02 8940 3482",
    "sg:postcode":"20123",
    "sg:province":"Milano",
    "wof:name":"Studium S. Orsola Srl",
    "wof:placetype":"venue"
},
  "geometry": {"coordinates":[9.179179,45.455715],"type":"Point"}
}