{
  "type": "Feature",
  "properties": {
    "addr:full":"Via Europa 27010 Filighera Filighera Pavia 27010",
    "addr:postcode":"27010;27010",
    "addr:street":"Via Europa",
    "iso:country":"IT",
    "sg:address":"Via Europa 27010 Filighera",
    "sg:city":"Filighera",
    "sg:classifiers":[
        {
            "category":"Manufacturing",
            "subcategory":"Metals",
            "type":"Manufacturing & Wholesale Goods"
        }
    ],
    "sg:phone":"+39 0382 960350",
    "sg:postcode":"27010",
    "sg:province":"Pavia",
    "sg:tags":[
        "metallurgy",
        "metalworking"
    ],
    "wof:name":"M.m.t. Di Mangiarotti B. (s.n.c.)",
    "wof:placetype":"venue"
},
  "geometry": {"coordinates":[9.1565628052,45.1858863831],"type":"Point"}
}