{
  "type": "Feature",
  "properties": {
    "addr:full":"Via Petrarca, 31; Como; 22100 Como Como 22100",
    "addr:housenumber":"31",
    "addr:postcode":"22100;22100",
    "addr:street":"Via Petrarca",
    "iso:country":"IT",
    "sg:address":"Via Petrarca, 31; Como; 22100",
    "sg:city":"Como",
    "sg:classifiers":[
        {
            "category":"Banks & Credit Unions",
            "subcategory":"Bank",
            "type":"Services"
        }
    ],
    "sg:phone":"+39 031 270039",
    "sg:postcode":"22100",
    "sg:province":"Como",
    "wof:name":"Banco Ambrosiano Veneto Spa",
    "wof:placetype":"venue"
},
  "geometry": {"coordinates":[9.094132,45.807304],"type":"Point"}
}