{
  "type": "Feature",
  "properties": {
    "iso:country":"IT",
    "sg:address":"12025 Dronero",
    "sg:city":"Dronero",
    "sg:classifiers":[
        {
            "category":"Coffee & Tea",
            "type":"Food & Drink"
        }
    ],
    "sg:phone":"+39 0171 918232",
    "sg:postcode":"12025",
    "sg:province":"Cuneo",
    "sg:tags":[
        "cioccolato",
        "cacao",
        "e"
    ],
    "wof:name":"Filc Snc",
    "wof:placetype":"venue"
},
  "geometry": {"coordinates":[7.352519,44.466721],"type":"Point"}
}