{
  "type": "Feature",
  "properties": {
    "iso:country":"IT",
    "sg:address":"95024 Acireale",
    "sg:city":"Acireale",
    "sg:orig_category":"Colle E Paste Adesive",
    "sg:phone":"+39 095 763 3011",
    "sg:postcode":"95024",
    "sg:province":"Catania",
    "wof:name":"Michele Messina Rappresentanze",
    "wof:placetype":"venue"
},
  "geometry": {"coordinates":[15.134873,37.561001],"type":"Point"}
}