{
  "type": "Feature",
  "properties": {
    "iso:country":"IT",
    "sg:address":"16, Via Della Centa 31040 Segusino",
    "sg:city":"Segusino",
    "sg:classifiers":[
        {
            "category":"Wholesale",
            "subcategory":"Medical Equipment & Supplies",
            "type":"Manufacturing & Wholesale Goods"
        }
    ],
    "sg:phone":"+39 0423 979759",
    "sg:postcode":"31040",
    "sg:province":"Treviso",
    "sg:tags":[
        "-",
        "health",
        "instrument"
    ],
    "wof:name":"2m Decori S.r.l.",
    "wof:placetype":"venue"
},
  "geometry": {"coordinates":[11.953197,45.909428],"type":"Point"}
}