{
  "type": "Feature",
  "properties": {
    "addr:full":"25030 Coccaglio Coccaglio Brescia 25030",
    "addr:postcode":"25030;25030",
    "iso:country":"IT",
    "sg:address":"25030 Coccaglio",
    "sg:city":"Coccaglio",
    "sg:orig_category":"Macchine Utensili E Impianti",
    "sg:phone":"+39 030 772 1850",
    "sg:postcode":"25030",
    "sg:province":"Brescia",
    "sg:website":"http://www.deantoni.it",
    "wof:name":"Dan Di De Antoni Srl",
    "wof:placetype":"venue"
},
  "geometry": {"coordinates":[9.975315,45.565647],"type":"Point"}
}