{
  "type": "Feature",
  "properties": {
    "addr:full":"25011 Calcinato Calcinato Brescia 25011",
    "addr:postcode":"25011;25011",
    "iso:country":"IT",
    "sg:address":"25011 Calcinato",
    "sg:city":"Calcinato",
    "sg:classifiers":[
        {
            "category":"Manufacturing",
            "subcategory":"Rubber & Plastics",
            "type":"Manufacturing & Wholesale Goods"
        }
    ],
    "sg:phone":"+39 030 963586",
    "sg:postcode":"25011",
    "sg:province":"Brescia",
    "sg:tags":[
        "equipment",
        "industry",
        "machinery"
    ],
    "wof:name":"Abate Basilio & C. Snc",
    "wof:placetype":"venue"
},
  "geometry": {"coordinates":[10.3956031799,45.4584960938],"type":"Point"}
}