{
  "type": "Feature",
  "properties": {
    "addr:full":"Via Fontana Rossa 11 24058 Romano Di Lombardia Romano di Lombardia Bergamo 24058",
    "addr:housenumber":"11",
    "addr:postcode":"24058;24058",
    "addr:street":"Via Fontana Rossa",
    "iso:country":"IT",
    "sg:address":"Via Fontana Rossa 11 24058 Romano Di Lombardia",
    "sg:city":"Romano di Lombardia",
    "sg:classifiers":[
        {
            "category":"Shopping",
            "subcategory":"Hobbies, Toys, & Games",
            "type":"Retail Goods"
        }
    ],
    "sg:phone":"+39 036 391 2282",
    "sg:postcode":"24058",
    "sg:province":"Bergamo",
    "sg:tags":[
        "equipment",
        "machining",
        "mechanical"
    ],
    "wof:name":"Officina Meccanica Romanese Di Forlani Marino E Plebani Romano Snc",
    "wof:placetype":"venue"
},
  "geometry": {"coordinates":[9.745536,45.528431],"type":"Point"}
}