{
  "type": "Feature",
  "properties": {
    "addr:full":"18/22, V. Dei Pioppi 59100 Prato Prato Prato 59100",
    "addr:housenumber":"18 / 22",
    "addr:postcode":"59100;59100",
    "addr:street":"V. Dei Pioppi",
    "iso:country":"IT",
    "sg:address":"18/22, V. Dei Pioppi 59100 Prato",
    "sg:city":"Prato",
    "sg:classifiers":[
        {
            "category":"Shopping",
            "subcategory":"Crafts & Fabrics",
            "type":"Retail Goods"
        }
    ],
    "sg:phone":"+39 39057454811",
    "sg:postcode":"59100",
    "sg:province":"Prato",
    "wof:name":"Texmoda Srl",
    "wof:placetype":"venue"
},
  "geometry": {"coordinates":[11.0793399811,43.8732070923],"type":"Point"}
}