{
  "type": "Feature",
  "properties": {
    "addr:full":"Via Roma 179 20037 Paderno Dugnano Paderno Dugnano Milano 20037",
    "addr:housenumber":"179",
    "addr:postcode":"20037;20037",
    "addr:street":"Via Roma",
    "iso:country":"IT",
    "sg:address":"Via Roma 179 20037 Paderno Dugnano",
    "sg:city":"Paderno Dugnano",
    "sg:classifiers":[
        {
            "category":"Manufacturing",
            "subcategory":"Metals",
            "type":"Manufacturing & Wholesale Goods"
        }
    ],
    "sg:phone":"+39 0291881",
    "sg:postcode":"20037",
    "sg:province":"Milano",
    "sg:tags":[
        "preparation",
        "precious",
        "products"
    ],
    "sg:website":"www.metallipreziosispa.com",
    "wof:name":"Metalli Preziosi S.p.a.",
    "wof:placetype":"venue"
},
  "geometry": {"coordinates":[9.1592273712,45.5629997253],"type":"Point"}
}