{
  "type": "Feature",
  "properties": {
    "addr:full":"11, Via Dei Chiosi 20040 Cavenago Di Brianza Cavenago di Brianza Milano 20040",
    "addr:postcode":"20040;20040",
    "addr:street":"Via Dei Chiosi",
    "iso:country":"IT",
    "sg:address":"11, Via Dei Chiosi 20040 Cavenago Di Brianza",
    "sg:city":"Cavenago di Brianza",
    "sg:classifiers":[
        {
            "category":"Autos & Motor Vehicles",
            "subcategory":"Automobile Sales",
            "type":"Retail Goods"
        }
    ],
    "sg:phone":"+39 39029501497",
    "sg:postcode":"20040",
    "sg:province":"Milano",
    "sg:tags":[
        "equipment",
        "transport"
    ],
    "wof:name":"Cicli Regina Di Romagna Di Cavallucci Elisa & C. Snc",
    "wof:placetype":"venue"
},
  "geometry": {"coordinates":[9.41249,45.579975],"type":"Point"}
}