{
  "type": "Feature",
  "properties": {
    "iso:country":"IT",
    "sg:address":"36040 Brendola",
    "sg:city":"Brendola",
    "sg:orig_category":"Servizi E Lavori Per Arredamento E Industria Del Legno",
    "sg:phone":"+39 0444 400233",
    "sg:postcode":"36040",
    "sg:province":"Vicenza",
    "wof:name":"Studio Associato Cartesio Di Gaio V. E Squaquara M.",
    "wof:placetype":"venue"
},
  "geometry": {"coordinates":[11.448119,45.510704],"type":"Point"}
}