{
  "type": "Feature",
  "properties": {
    "addr:full":"20090 Opera Opera Milano 20090",
    "addr:postcode":"20090;20090",
    "iso:country":"IT",
    "sg:address":"20090 Opera",
    "sg:city":"Opera",
    "sg:classifiers":[
        {
            "category":"Health Services",
            "subcategory":"Health Practitioner",
            "type":"Services"
        }
    ],
    "sg:phone":"+39 02 5760 5686",
    "sg:postcode":"20090",
    "sg:province":"Milano",
    "sg:tags":[
        "medici"
    ],
    "wof:name":"Scicchitano Maria Rosa",
    "wof:placetype":"venue"
},
  "geometry": {"coordinates":[9.209728241,45.3769035339],"type":"Point"}
}