{
  "type": "Feature",
  "properties": {
    "iso:country":"IT",
    "sg:address":"00186 Roma",
    "sg:city":"Roma",
    "sg:orig_category":"Telefoni Cellulari E Radiotelefoni",
    "sg:phone":"+39 06 6880 8342",
    "sg:postcode":"00186",
    "sg:province":"Roma",
    "wof:name":"Alfacom Srl",
    "wof:placetype":"venue"
},
  "geometry": {"coordinates":[12.474972,41.901672],"type":"Point"}
}