{
  "type": "Feature",
  "properties": {
    "iso:country":"IT",
    "sg:address":"70010 Valenzano",
    "sg:city":"Casamassima",
    "sg:classifiers":[
        {
            "category":"Communications",
            "subcategory":"Film & Video Production",
            "type":"Services"
        }
    ],
    "sg:phone":"+39 080 467 5468",
    "sg:postcode":"70010",
    "sg:province":"Bari",
    "sg:tags":[
        "cinema",
        "support",
        "companies",
        "trade",
        "radio-television",
        "events"
    ],
    "wof:name":"Videoland Srl",
    "wof:placetype":"venue"
},
  "geometry": {"coordinates":[16.885927,41.041077],"type":"Point"}
}