{
  "type": "Feature",
  "properties": {
    "iso:country":"IT",
    "sg:address":"93100 Caltanissetta",
    "sg:city":"Caltanissetta",
    "sg:orig_category":"Telecomunicazioni E Telefonia, Impianti, Apparecchi E Servizi",
    "sg:phone":"+39 0934 25992",
    "sg:postcode":"93100",
    "sg:province":"Caltanissetta",
    "wof:name":"Russotti Elettronica",
    "wof:placetype":"venue"
},
  "geometry": {"coordinates":[13.884119,37.486771],"type":"Point"}
}