{
  "type": "Feature",
  "properties": {
    "iso:country":"IT",
    "sg:address":"80124 Napoli",
    "sg:city":"Napoli",
    "sg:orig_category":"Scuole E Servizi Scolastici. Ricerca, Selezione E Formazione Del Personale",
    "sg:phone":"+39 081 570 1945",
    "sg:postcode":"80124",
    "sg:province":"Napoli",
    "wof:name":"Istituto Flegreo Di Stenodattilografia",
    "wof:placetype":"venue"
},
  "geometry": {"coordinates":[14.166627,40.819248],"type":"Point"}
}