{
  "type": "Feature",
  "properties": {
    "addr:full":"21052 Busto Arsizio Busto Arsizio Varese 21052",
    "addr:postcode":"21052;21052",
    "iso:country":"IT",
    "sg:address":"21052 Busto Arsizio",
    "sg:city":"Busto Arsizio",
    "sg:orig_category":"Pompe. Macchine, Strumenti Ed Apparecchi Per Attivita' Industriali",
    "sg:phone":"+39 0331 635300",
    "sg:postcode":"21052",
    "sg:province":"Varese",
    "sg:website":"http://www.idropres.com",
    "wof:name":"Idropres Srl",
    "wof:placetype":"venue"
},
  "geometry": {"coordinates":[8.8457965851,45.60887146],"type":"Point"}
}