{
  "type": "Feature",
  "properties": {
    "iso:country":"IT",
    "sg:address":"10022 Carmagnola",
    "sg:city":"Carmagnola",
    "sg:orig_category":"Materiali Semilavorati Metallici",
    "sg:phone":"+39 011 971 2166",
    "sg:postcode":"10022",
    "sg:province":"Torino",
    "wof:name":"Omnifer Srl",
    "wof:placetype":"venue"
},
  "geometry": {"coordinates":[7.837262,44.925686],"type":"Point"}
}