{
  "type": "Feature",
  "properties": {
    "addr:full":"23030 Livigno Livigno Sondrio 23030",
    "addr:postcode":"23030;23030",
    "iso:country":"IT",
    "sg:address":"23030 Livigno",
    "sg:city":"Livigno",
    "sg:orig_category":"Metalli E Leghe",
    "sg:phone":"+39 0342 997708",
    "sg:postcode":"23030",
    "sg:province":"Sondrio",
    "wof:name":"Longa Angelo",
    "wof:placetype":"venue"
},
  "geometry": {"coordinates":[10.1386098862,46.5490379333],"type":"Point"}
}