{
  "type": "Feature",
  "properties": {
    "iso:country":"IT",
    "sg:address":"Via Medici 128 /po Box 5; S. Agata Militello; 98076",
    "sg:classifiers":[
        {
            "category":"Banks & Credit Unions",
            "subcategory":"Bank",
            "type":"Services"
        }
    ],
    "sg:phone":"+39 0941 7251",
    "sg:postcode":"98076",
    "sg:province":"Messina",
    "wof:name":"Banco Di Sicilia Spa",
    "wof:placetype":"venue"
},
  "geometry": {"coordinates":[14.636631,38.068752],"type":"Point"}
}