{
  "type": "Feature",
  "properties": {
    "iso:country":"IT",
    "sg:address":"25019 Sirmione",
    "sg:city":"Sirmione",
    "sg:orig_category":"Carni, Salumi E Pesci. Zootecnia E Pesca, Allevamento Piccoli Animali",
    "sg:phone":"+39 030 919 6061",
    "sg:postcode":"25019",
    "sg:province":"Brescia",
    "wof:name":"Nuova Zeta 3 Di Zarantonello Michela E Bolzoni Michele Snc",
    "wof:placetype":"venue"
},
  "geometry": {"coordinates":[10.620686,45.451248],"type":"Point"}
}