{
  "type": "Feature",
  "properties": {
    "addr:full":"Via Castelli Romani 00040 Pomezia Pomezia Roma 00040",
    "addr:postcode":"00040;roma 00040",
    "addr:street":"Via Castelli",
    "iso:country":"IT",
    "sg:address":"Via Castelli Romani 00040 Pomezia",
    "sg:city":"Pomezia",
    "sg:classifiers":[
        {
            "category":"Professional",
            "subcategory":"Engineering",
            "type":"Services"
        }
    ],
    "sg:phone":"+39 39069122327",
    "sg:postcode":"00040",
    "sg:province":"Roma",
    "sg:tags":[
        "machine",
        "-",
        "mechanical"
    ],
    "wof:name":"Eurofrigo (s.p.a.)",
    "wof:placetype":"venue"
},
  "geometry": {"coordinates":[12.50861,41.682434],"type":"Point"}
}