{
  "type": "Feature",
  "properties": {
    "iso:country":"IT",
    "sg:address":"24, Via Sauro Nazario 80132 Napoli",
    "sg:city":"Napoli",
    "sg:classifiers":[
        {
            "category":"Travel",
            "subcategory":"Travel Agent",
            "type":"Entertainment"
        }
    ],
    "sg:phone":"+39 081 764 7589",
    "sg:postcode":"80132",
    "sg:province":"Napoli",
    "sg:tags":[
        "business"
    ],
    "wof:name":"Albergo Miramare",
    "wof:placetype":"venue"
},
  "geometry": {"coordinates":[14.301881,40.91441],"type":"Point"}
}