{
  "type": "Feature",
  "properties": {
    "addr:full":"1, Via Provinciale Della Rocca 66030 Santa Maria Imbaro Santa Maria Imbaro Chieti 66030",
    "addr:postcode":"66030;66030",
    "addr:street":"Via Provinciale Della Rocca;Imbaro",
    "iso:country":"IT",
    "sg:address":"1, Via Provinciale Della Rocca 66030 Santa Maria Imbaro",
    "sg:city":"Santa Maria Imbaro",
    "sg:classifiers":[
        {
            "category":"Food & Beverages",
            "subcategory":"Groceries & Convenience Stores",
            "type":"Retail Goods"
        }
    ],
    "sg:phone":"+39 0872 579041",
    "sg:postcode":"66030",
    "sg:province":"Chieti",
    "sg:tags":[
        "product",
        "related"
    ],
    "wof:name":"Pace Srl",
    "wof:placetype":"venue"
},
  "geometry": {"coordinates":[14.4329538345,42.2183952332],"type":"Point"}
}