{
  "type": "Feature",
  "properties": {
    "addr:full":"20098 San Giuliano Milanese San Giuliano Milanese Milano 20098",
    "addr:housenumber":"20098",
    "addr:postcode":"20098",
    "addr:street":"San",
    "iso:country":"IT",
    "sg:address":"20098 San Giuliano Milanese",
    "sg:city":"San Giuliano Milanese",
    "sg:classifiers":[
        {
            "category":"Health Services",
            "subcategory":"Health Practitioner",
            "type":"Services"
        }
    ],
    "sg:phone":"+39 02 9849 1225",
    "sg:postcode":"20098",
    "sg:province":"Milano",
    "sg:tags":[
        "medici"
    ],
    "wof:name":"Bacchioni Antonio Maria",
    "wof:placetype":"venue"
},
  "geometry": {"coordinates":[9.26548,45.406586],"type":"Point"}
}