{
  "type": "Feature",
  "properties": {
    "addr:full":"52100 Arezzo Arezzo Arezzo 52100",
    "addr:postcode":"52100;52100",
    "iso:country":"IT",
    "sg:address":"52100 Arezzo",
    "sg:city":"Arezzo",
    "sg:orig_category":"Macchine E Forniture Per Industria Orafa E Per Orologeria",
    "sg:phone":"+39 0575 300319",
    "sg:postcode":"52100",
    "sg:province":"Arezzo",
    "wof:name":"Cibiemme Stampi Snc",
    "wof:placetype":"venue"
},
  "geometry": {"coordinates":[11.8492765427,43.4617996216],"type":"Point"}
}