{
  "type": "Feature",
  "properties": {
    "addr:full":"Via Trani 220/c 70051 Barletta Barletta Bari 70051",
    "addr:housenumber":"220 / c",
    "addr:postcode":"70051;70051",
    "addr:street":"Via Trani",
    "iso:country":"IT",
    "sg:address":"Via Trani 220/c 70051 Barletta",
    "sg:city":"Barletta",
    "sg:orig_category":"Ladies' Trousers Suits, Suits, Jackets, Skirts, And Trousers",
    "sg:phone":"+39 0883 536770",
    "sg:postcode":"70051",
    "sg:province":"Bari",
    "wof:name":"Daddy S.r.l.",
    "wof:placetype":"venue"
},
  "geometry": {"coordinates":[16.323286,41.302814],"type":"Point"}
}