{
  "type": "Feature",
  "properties": {
    "addr:full":"Via Dei Rovedi 35/37 20010 Pregnana Milanese Pregnana Milanese Milano 20010",
    "addr:housenumber":"35 / 37",
    "addr:postcode":"20010;20010",
    "addr:street":"Via Dei Rovedi;Milanese",
    "iso:country":"IT",
    "sg:address":"Via Dei Rovedi 35/37 20010 Pregnana Milanese",
    "sg:city":"Pregnana Milanese",
    "sg:classifiers":[
        {
            "category":"Building & Trades",
            "subcategory":"Plumbing",
            "type":"Services"
        }
    ],
    "sg:phone":"+39 02 9329 0259",
    "sg:postcode":"20010",
    "sg:province":"Milano",
    "sg:tags":[
        "tank"
    ],
    "sg:website":"www.cocsrl.com",
    "wof:name":"Coc Srl",
    "wof:placetype":"venue"
},
  "geometry": {"coordinates":[9.017566,45.515171],"type":"Point"}
}