{
  "type": "Feature",
  "properties": {
    "iso:country":"IT",
    "sg:address":"Via G. Matteotti 117 24069 Trescore Balneario",
    "sg:city":"Trescore Balneario",
    "sg:classifiers":[
        {
            "category":"Building & Trades",
            "subcategory":"Construction",
            "type":"Services"
        }
    ],
    "sg:phone":"+39 035 940445",
    "sg:postcode":"24069",
    "sg:province":"Bergamo",
    "sg:tags":[
        "valve"
    ],
    "sg:website":"www.gemels.it",
    "wof:name":"Gemels Srl Di Facchinetti Giovanni & Marco",
    "wof:placetype":"venue"
},
  "geometry": {"coordinates":[9.669952,45.694904],"type":"Point"}
}