{
  "type": "Feature",
  "properties": {
    "iso:country":"IT",
    "sg:address":"Via Dell' Artigianato 9 35010 Saletto Di Vigodarzere",
    "sg:city":"Saletto di Vigodarzere",
    "sg:classifiers":[
        {
            "category":"Real Estate",
            "subcategory":"Real Estate Services",
            "type":"Services"
        }
    ],
    "sg:phone":"+39 049 767717",
    "sg:postcode":"35010",
    "sg:province":"Padova",
    "sg:tags":[
        "leather",
        "belt"
    ],
    "wof:name":"Cinturificio G. & G. Snc Di Gastaldello Giulio & C.",
    "wof:placetype":"venue"
},
  "geometry": {"coordinates":[11.497663,45.226299],"type":"Point"}
}