{
  "type": "Feature",
  "properties": {
    "addr:full":"101, Via Marconi 09045 Quartu Sant'elena Cagliari 09045",
    "addr:housenumber":"101",
    "addr:postcode":"09045;09045",
    "addr:street":"Via Marconi",
    "iso:country":"IT",
    "sg:address":"101, Via Marconi 09045 Quartu Sant'elena",
    "sg:classifiers":[
        {
            "category":"Shopping",
            "subcategory":"Stationery & Office Supplies",
            "type":"Retail Goods"
        }
    ],
    "sg:phone":"+39 39070885739",
    "sg:postcode":"09045",
    "sg:province":"Cagliari",
    "sg:tags":[
        "professional"
    ],
    "wof:name":"Franz Mobili (s.r.l.)",
    "wof:placetype":"venue"
},
  "geometry": {"coordinates":[9.1888074875,39.2440948486],"type":"Point"}
}