{
  "type": "Feature",
  "properties": {
    "iso:country":"IT",
    "sg:address":"45039 Stienta",
    "sg:city":"Stienta",
    "sg:orig_category":"Forniture Per Abbigliamento E Pelletterie",
    "sg:phone":"+39 0425 746169",
    "sg:postcode":"45039",
    "sg:province":"Rovigo",
    "wof:name":"Carto Moda",
    "wof:placetype":"venue"
},
  "geometry": {"coordinates":[11.5478868484,44.949092865],"type":"Point"}
}