{
  "type": "Feature",
  "properties": {
    "addr:full":"Via Terraglioni 42/b 36030 Montecchio Precalcino Montecchio Precalcino Vicenza 36030",
    "addr:housenumber":"42 / b",
    "addr:postcode":"36030;36030",
    "addr:street":"Via Terraglioni",
    "iso:country":"IT",
    "sg:address":"Via Terraglioni 42/b 36030 Montecchio Precalcino",
    "sg:city":"Montecchio Precalcino",
    "sg:classifiers":[
        {
            "category":"Donuts",
            "subcategory":"None",
            "type":"Food & Drink"
        }
    ],
    "sg:phone":"+39 0445 864300",
    "sg:postcode":"36030",
    "sg:province":"Vicenza",
    "sg:tags":[
        "dry",
        "sand"
    ],
    "wof:name":"Martini Sabbie Industriali Spa",
    "wof:placetype":"venue"
},
  "geometry": {"coordinates":[11.540307,45.545906],"type":"Point"}
}