{
  "type": "Feature",
  "properties": {
    "iso:country":"IT",
    "sg:address":"Via Roma 85/95, 87100 Cosenza, Cs",
    "sg:city":"Cosenza",
    "sg:classifiers":[
        {
            "category":"Banks & Credit Unions",
            "subcategory":"Bank",
            "type":"Services"
        }
    ],
    "sg:postcode":"87100",
    "sg:province":"Cosenza",
    "wof:name":"Banca Popolare Di Calabria Spa",
    "wof:placetype":"venue"
},
  "geometry": {"coordinates":[16.249765,39.30048],"type":"Point"}
}