{
  "type": "Feature",
  "properties": {
    "addr:full":"1, Via Argine 42022 Boretto Reggio Nell'Emilia 42022",
    "addr:postcode":"42022;42022",
    "addr:street":"Via Argine",
    "iso:country":"IT",
    "sg:address":"1, Via Argine 42022 Boretto",
    "sg:classifiers":[
        {
            "category":"Building & Trades",
            "subcategory":"Construction",
            "type":"Services"
        }
    ],
    "sg:phone":"+39 0522 964505",
    "sg:postcode":"42022",
    "sg:province":"Reggio Nell'Emilia",
    "sg:tags":[
        "work",
        "public"
    ],
    "wof:name":"Flu.mar. Srl",
    "wof:placetype":"venue"
},
  "geometry": {"coordinates":[10.627794,44.696228],"type":"Point"}
}