{
  "type": "Feature",
  "properties": {
    "addr:full":"Via Galassia 61-prato; Frabosa; 12083 Cuneo 12083",
    "addr:housenumber":"61-prato frabosa",
    "addr:postcode":"12083;12083",
    "addr:street":"Via Galassia",
    "iso:country":"IT",
    "sg:address":"Via Galassia 61-prato; Frabosa; 12083",
    "sg:classifiers":[
        {
            "category":"Banks & Credit Unions",
            "subcategory":"Bank",
            "type":"Services"
        }
    ],
    "sg:phone":"+39 0174 334143",
    "sg:postcode":"12083",
    "sg:province":"Cuneo",
    "wof:name":"Cassa Di Risparmio Di Cuneo",
    "wof:placetype":"venue"
},
  "geometry": {"coordinates":[7.782151,44.255817],"type":"Point"}
}