{
  "type": "Feature",
  "properties": {
    "addr:full":"29/a, Via Edolo 20125 Milano Milano Milano 20125",
    "addr:housenumber":"29 / a",
    "addr:postcode":"20125;20125",
    "addr:street":"Via Edolo",
    "iso:country":"IT",
    "sg:address":"29/a, Via Edolo 20125 Milano",
    "sg:city":"Milano",
    "sg:classifiers":[
        {
            "category":"Shopping",
            "subcategory":"Computers & Home Electronics",
            "type":"Retail Goods"
        }
    ],
    "sg:phone":"+39 39026690926",
    "sg:postcode":"20125",
    "sg:province":"Milano",
    "sg:tags":[
        "electronic",
        "electrical",
        "equipment"
    ],
    "wof:name":"Icardi",
    "wof:placetype":"venue"
},
  "geometry": {"coordinates":[9.207009,45.493992],"type":"Point"}
}