{
  "type": "Feature",
  "properties": {
    "iso:country":"IT",
    "sg:address":"22100 Como",
    "sg:city":"Como",
    "sg:orig_category":"Macchine Ed Impianti Per Edilizia E Lavori Pubblici. Apparecchiature E Sistemi Per Magazzinaggio E Movimentazione",
    "sg:phone":"+39 031 522222",
    "sg:postcode":"22100",
    "sg:province":"Como",
    "sg:website":"http://www.ballerini.it",
    "wof:name":"Ballerini Riccardo",
    "wof:placetype":"venue"
},
  "geometry": {"coordinates":[9.096155,45.778881],"type":"Point"}
}