{
  "type": "Feature",
  "properties": {
    "iso:country":"IT",
    "sg:address":"Via I\u00b0 Maggio 7 40011 Anzola Dell'emilia",
    "sg:classifiers":[
        {
            "category":"Professional",
            "subcategory":"Art Services",
            "type":"Services"
        }
    ],
    "sg:phone":"+39 051 731394",
    "sg:postcode":"40011",
    "sg:province":"Bologna",
    "sg:tags":[
        "stand",
        "construction",
        "exhibition",
        "fair",
        "trade"
    ],
    "wof:name":"Mas Modulo",
    "wof:placetype":"venue"
},
  "geometry": {"coordinates":[11.218939,44.533741],"type":"Point"}
}