{
  "type": "Feature",
  "properties": {
    "iso:country":"IT",
    "sg:address":"41100 Modena",
    "sg:city":"Modena",
    "sg:orig_category":"Anelli E Guarnizioni Di Tenuta E D'arresto",
    "sg:phone":"+39 059 366470",
    "sg:postcode":"41100",
    "sg:province":"Modena",
    "sg:website":"http://www.utensilcuscinetti.com",
    "wof:name":"Utensilcuscinetti Srl",
    "wof:placetype":"venue"
},
  "geometry": {"coordinates":[10.936594,44.641979],"type":"Point"}
}