{
  "type": "Feature",
  "properties": {
    "addr:full":"90, Via Giovanni Amendola 51010 Uzzano Uzzano Pistoia 51010",
    "addr:postcode":"51010;51010",
    "addr:street":"Via Giovanni Amendola",
    "iso:country":"IT",
    "sg:address":"90, Via Giovanni Amendola 51010 Uzzano",
    "sg:city":"Uzzano",
    "sg:classifiers":[
        {
            "category":"Professional",
            "subcategory":"Engineering",
            "type":"Services"
        }
    ],
    "sg:phone":"+39 0572 444224",
    "sg:postcode":"51010",
    "sg:province":"Pistoia",
    "sg:tags":[
        "machine",
        "-",
        "mechanical"
    ],
    "wof:name":"Tre Esse Impianti S.r.l.",
    "wof:placetype":"venue"
},
  "geometry": {"coordinates":[10.918524,43.932156],"type":"Point"}
}