{
  "type": "Feature",
  "properties": {
    "addr:full":"Via I Maggio 17/3 40044 PONTECCHIO MARCONI",
    "addr:housenumber":"17 / 3",
    "addr:postcode":"40044",
    "addr:street":"Via I Maggio;Marconi",
    "iso:country":"IT",
    "sg:address":"Via I Maggio",
    "sg:classifiers":[
        {
            "category":"Wholesale",
            "subcategory":"Vending Machines",
            "type":"Manufacturing & Wholesale Goods"
        }
    ],
    "sg:phone":"+39 051 675 2396",
    "sg:province":"17/3 40044 PONTECCHIO MARCONI",
    "sg:tags":[
        "honing"
    ],
    "sg:website":"www.marpolsrl.com",
    "wof:name":"Marpol F.r. Srl",
    "wof:placetype":"venue"
},
  "geometry": {"coordinates":[11.270953,44.424328],"type":"Point"}
}