{
  "type": "Feature",
  "properties": {
    "iso:country":"IT",
    "sg:address":"00135 Roma",
    "sg:city":"Roma",
    "sg:orig_category":"Ospedali E Servizi Sanitari. Servizi Sociali. Associazioni Ed Organismi Di Interesse Pubblico",
    "sg:phone":"+39 06 3068 3448",
    "sg:postcode":"00135",
    "sg:province":"Roma",
    "wof:name":"Cooperativa Sociale Azzurra '84 R.l.",
    "wof:placetype":"venue"
},
  "geometry": {"coordinates":[12.420864,41.949001],"type":"Point"}
}