{
  "type": "Feature",
  "properties": {
    "iso:country":"IT",
    "sg:address":"70122 Bari",
    "sg:city":"Bari",
    "sg:orig_category":"Tende E Tendaggi",
    "sg:phone":"+39 080 521 1644",
    "sg:postcode":"70122",
    "sg:province":"Bari",
    "wof:name":"Viterbo Gaetano",
    "wof:placetype":"venue"
},
  "geometry": {"coordinates":[16.86648,41.124516],"type":"Point"}
}