{
  "type": "Feature",
  "properties": {
    "iso:country":"IT",
    "sg:address":"31013 Codogne'",
    "sg:city":"Cimetta",
    "sg:classifiers":[
        {
            "category":"Utilities",
            "subcategory":"Natural Gas",
            "type":"Services"
        }
    ],
    "sg:phone":"+39 0438 470220",
    "sg:postcode":"31013",
    "sg:province":"Treviso",
    "sg:tags":[
        "alloy",
        "metal"
    ],
    "wof:name":"Anodica Trevigiana Srl",
    "wof:placetype":"venue"
},
  "geometry": {"coordinates":[12.407500267,45.8587608337],"type":"Point"}
}