{
  "type": "Feature",
  "properties": {
    "iso:country":"IT",
    "sg:address":"52025 Montevarchi",
    "sg:city":"Montevarchi",
    "sg:orig_category":"Servizi Vari Di Interesse Pubblico",
    "sg:phone":"+39 055 901308",
    "sg:postcode":"52025",
    "sg:province":"Arezzo",
    "wof:name":"Benefit Di Gobbi Marta",
    "wof:placetype":"venue"
},
  "geometry": {"coordinates":[11.55891,43.50008],"type":"Point"}
}