{
  "type": "Feature",
  "properties": {
    "iso:country":"IT",
    "sg:address":"25065 Lumezzane",
    "sg:city":"Lumezzane",
    "sg:orig_category":"Lavorazioni Metalli, Stampaggio E Saldatura",
    "sg:phone":"+39 030 871153",
    "sg:postcode":"25065",
    "sg:province":"Brescia",
    "sg:website":"http://www.lumetel.it/mgmori",
    "wof:name":"M.g. F.lli Mori Di Mori Massimo & C. Snc",
    "wof:placetype":"venue"
},
  "geometry": {"coordinates":[10.215416,45.606354],"type":"Point"}
}