{
  "type": "Feature",
  "properties": {
    "iso:country":"IT",
    "sg:address":"2, Via Della Croce 00187 Roma",
    "sg:city":"Roma",
    "sg:classifiers":[
        {
            "category":"Shopping",
            "subcategory":"Clothing, Apparel, & Fashions",
            "type":"Retail Goods"
        }
    ],
    "sg:phone":"+39 39066990036",
    "sg:postcode":"00187",
    "sg:province":"Roma",
    "sg:tags":[
        "clothes"
    ],
    "wof:name":"Lancetti Creazioni Srl",
    "wof:placetype":"venue"
},
  "geometry": {"coordinates":[12.42871,41.845947],"type":"Point"}
}