{
  "type": "Feature",
  "properties": {
    "addr:full":"91, Via Monte Bianco 41042 Fiorano Modenese Fiorano Modenese Modena 41042",
    "addr:postcode":"41042;41042",
    "addr:street":"Via Monte Bianco",
    "iso:country":"IT",
    "sg:address":"91, Via Monte Bianco 41042 Fiorano Modenese",
    "sg:city":"Fiorano Modenese",
    "sg:classifiers":[
        {
            "category":"Shopping",
            "subcategory":"Crafts & Fabrics",
            "type":"Retail Goods"
        }
    ],
    "sg:phone":"+39 0536 921321",
    "sg:postcode":"41042",
    "sg:province":"Modena",
    "sg:tags":[
        "ceramic"
    ],
    "wof:name":"Rising Ricerca S.r.l.",
    "wof:placetype":"venue"
},
  "geometry": {"coordinates":[10.856943,44.550175],"type":"Point"}
}