{
  "type": "Feature",
  "properties": {
    "iso:country":"IT",
    "sg:address":"25040 Esine",
    "sg:city":"Esine",
    "sg:orig_category":"Caffe' Crudo E Torrefatto",
    "sg:phone":"+39 036 436 0661",
    "sg:postcode":"25040",
    "sg:province":"Brescia",
    "wof:name":"T.m. Srl Torrefazione Dei F.lli Morandini & C.",
    "wof:placetype":"venue"
},
  "geometry": {"coordinates":[10.236397,45.916485],"type":"Point"}
}