{
  "type": "Feature",
  "properties": {
    "iso:country":"IT",
    "sg:address":"252/b, V. Campana 80078 Pozzuoli",
    "sg:city":"Pozzuoli",
    "sg:classifiers":[
        {
            "category":"Wholesale",
            "subcategory":"Machinery & Supplies",
            "type":"Manufacturing & Wholesale Goods"
        }
    ],
    "sg:phone":"+39 081 526 5240",
    "sg:postcode":"80078",
    "sg:province":"Napoli",
    "sg:tags":[
        "equipment",
        "precision"
    ],
    "sg:website":"http://www.laserevent.it",
    "wof:name":"Laserevent Srl.",
    "wof:placetype":"venue"
},
  "geometry": {"coordinates":[14.1202640533,40.85679245],"type":"Point"}
}