{
  "type": "Feature",
  "properties": {
    "iso:country":"IT",
    "sg:address":"4/f, Regione Dota 14053 Canelli",
    "sg:city":"Canelli",
    "sg:classifiers":[
        {
            "category":"Professional",
            "subcategory":"Engineering",
            "type":"Services"
        }
    ],
    "sg:phone":"+39 0141 822924",
    "sg:postcode":"14053",
    "sg:province":"Asti",
    "sg:tags":[
        "machine",
        "-",
        "mechanical"
    ],
    "wof:name":"C.b.m. Sas Di Barosio Sergio & C.",
    "wof:placetype":"venue"
},
  "geometry": {"coordinates":[8.291972,44.721157],"type":"Point"}
}