{
  "type": "Feature",
  "properties": {
    "iso:country":"IT",
    "sg:address":"7, Via Santorre Di Santarosa 47900 Rimini",
    "sg:city":"Rimini",
    "sg:classifiers":[
        {
            "category":"Autos & Motor Vehicles",
            "subcategory":"Automobile Sales",
            "type":"Retail Goods"
        }
    ],
    "sg:phone":"+39 0541 374009",
    "sg:postcode":"47900",
    "sg:province":"Rimini",
    "sg:tags":[
        "motor-cars"
    ],
    "wof:name":"A.s. Auto Srl",
    "wof:placetype":"venue"
},
  "geometry": {"coordinates":[12.5662565231,44.0607795715],"type":"Point"}
}