{
  "type": "Feature",
  "properties": {
    "iso:country":"IT",
    "sg:address":"Via S Martino 1; Morbegno; 23017",
    "sg:city":"Morbegno",
    "sg:classifiers":[
        {
            "category":"Banks & Credit Unions",
            "subcategory":"Bank",
            "type":"Services"
        }
    ],
    "sg:phone":"+39 0342 614858",
    "sg:postcode":"23017",
    "sg:province":"Sondrio",
    "wof:name":"Istituto Bancario, San Paolo Di Torino Spa",
    "wof:placetype":"venue"
},
  "geometry": {"coordinates":[9.580547,46.133049],"type":"Point"}
}