{
  "type": "Feature",
  "properties": {
    "addr:full":"00043 Ciampino Ciampino Roma 00043",
    "addr:postcode":"00043;roma 00043",
    "iso:country":"IT",
    "sg:address":"00043 Ciampino",
    "sg:city":"Ciampino",
    "sg:orig_category":"Telecomunicazioni E Telefonia, Impianti, Apparecchi E Servizi",
    "sg:phone":"+39 06 7936 5480",
    "sg:postcode":"00043",
    "sg:province":"Roma",
    "wof:name":"Wellcomm Engineering Srl",
    "wof:placetype":"venue"
},
  "geometry": {"coordinates":[12.6078,41.794151],"type":"Point"}
}