{
  "type": "Feature",
  "properties": {
    "iso:country":"IT",
    "sg:address":"15076 Ovada",
    "sg:city":"Ovada",
    "sg:orig_category":"Trasporto Pubblico E Privato",
    "sg:phone":"+39 0143 86547",
    "sg:postcode":"15076",
    "sg:province":"Alessandria",
    "wof:name":"Onoranze Funebri Mandirola Di Scarsi Paolo & C. Sas",
    "wof:placetype":"venue"
},
  "geometry": {"coordinates":[8.560508,44.921642],"type":"Point"}
}