{
  "type": "Feature",
  "properties": {
    "addr:full":"41036 Medolla Medolla Modena 41036",
    "addr:postcode":"41036;41036",
    "iso:country":"IT",
    "sg:address":"41036 Medolla",
    "sg:city":"Medolla",
    "sg:orig_category":"Macchine, Impianti Ed Attrezzature Per Industria Alimentare E Bevande",
    "sg:phone":"+39 0535 51288",
    "sg:postcode":"41036",
    "sg:province":"Modena",
    "wof:name":"Irrigarden Di Facchini Claudio",
    "wof:placetype":"venue"
},
  "geometry": {"coordinates":[11.055879,44.839542],"type":"Point"}
}