{
  "type": "Feature",
  "properties": {
    "addr:full":"54033 Carrara Avenza Massa-Carrara 54033",
    "addr:postcode":"54033;54033",
    "addr:street":"Avenza",
    "iso:country":"IT",
    "sg:address":"54033 Carrara",
    "sg:city":"Avenza",
    "sg:orig_category":"Graniti",
    "sg:phone":"+39 0585 858494",
    "sg:postcode":"54033",
    "sg:province":"Massa-Carrara",
    "sg:website":"http://www.furrer.it",
    "wof:name":"Furrer Spa",
    "wof:placetype":"venue"
},
  "geometry": {"coordinates":[10.051919,44.048927],"type":"Point"}
}