{
  "type": "Feature",
  "properties": {
    "iso:country":"IT",
    "sg:address":"Piazza Piebiscito, 2; Gioia Del Colle; 70023",
    "sg:city":"Gioia del Colle",
    "sg:classifiers":[
        {
            "category":"Banks & Credit Unions",
            "subcategory":"Bank",
            "type":"Services"
        }
    ],
    "sg:phone":"+39 080 834335",
    "sg:postcode":"70023",
    "sg:province":"Bari",
    "wof:name":"Banca Popolare Della Murgia",
    "wof:placetype":"venue"
},
  "geometry": {"coordinates":[16.92136,40.798615],"type":"Point"}
}