{
  "type": "Feature",
  "properties": {
    "addr:full":"12042 Bra Bra Cuneo 12042",
    "addr:postcode":"12042;12042",
    "iso:country":"IT",
    "sg:address":"12042 Bra",
    "sg:city":"Bra",
    "sg:orig_category":"Carni, Salumi E Pesci",
    "sg:phone":"+39 0172 44325",
    "sg:postcode":"12042",
    "sg:province":"Cuneo",
    "wof:name":"Alberti Livio",
    "wof:placetype":"venue"
},
  "geometry": {"coordinates":[7.854847,44.69128],"type":"Point"}
}