{
  "type": "Feature",
  "properties": {
    "iso:country":"IT",
    "sg:address":"20134 Milano",
    "sg:city":"Milano",
    "sg:orig_category":"Tempo Libero - Articoli E Forniture. Regalistica Aziendale",
    "sg:phone":"+39 02 215 2313",
    "sg:postcode":"20134",
    "sg:province":"Milano",
    "wof:name":"Mattel S.r.l.",
    "wof:placetype":"venue"
},
  "geometry": {"coordinates":[9.237222,45.486671],"type":"Point"}
}