{
  "type": "Feature",
  "properties": {
    "iso:country":"IT",
    "sg:address":"19125 La Spezia",
    "sg:orig_category":"Arredamenti - Vendita Al Dettaglio",
    "sg:phone":"+39 0187 504150",
    "sg:province":"SP",
    "sg:website":"http://www.marlettoarredamento.it",
    "wof:name":"Mobilificio Marletto Sas",
    "wof:placetype":"venue"
},
  "geometry": {"coordinates":[9.842874,44.122574],"type":"Point"}
}