{
  "type": "Feature",
  "properties": {
    "iso:country":"IT",
    "sg:address":"20131 Milano",
    "sg:city":"Milano",
    "sg:classifiers":[
        {
            "category":"Health Services",
            "subcategory":"Health Practitioner",
            "type":"Services"
        }
    ],
    "sg:phone":"+39 02 2940 3530",
    "sg:postcode":"20131",
    "sg:province":"Milano",
    "sg:tags":[
        "medici"
    ],
    "wof:name":"Ceriani Dr. Maria Teresa",
    "wof:placetype":"venue"
},
  "geometry": {"coordinates":[9.21729,45.478104],"type":"Point"}
}