{
  "type": "Feature",
  "properties": {
    "iso:country":"IT",
    "sg:address":"50144 Firenze",
    "sg:city":"Firenze",
    "sg:orig_category":"Prodotti Chimici Di Base",
    "sg:phone":"+39 055 352917",
    "sg:postcode":"50144",
    "sg:province":"Firenze",
    "wof:name":"Laborchimica Sas",
    "wof:placetype":"venue"
},
  "geometry": {"coordinates":[10.9478149414,43.7793884277],"type":"Point"}
}