{
  "type": "Feature",
  "properties": {
    "iso:country":"IT",
    "sg:address":"Loc Saragiolo 58054 Scansano",
    "sg:city":"Scansano",
    "sg:classifiers":[
        {
            "category":"Food & Beverages",
            "subcategory":"Liquor & Beverages",
            "type":"Retail Goods"
        }
    ],
    "sg:phone":"+39 0564 507288",
    "sg:postcode":"58054",
    "sg:province":"Grosseto",
    "sg:tags":[
        "wine",
        "italian"
    ],
    "sg:website":"www.cantinadelmurellino.it",
    "wof:name":"Cantina Coop.va Del Morellino Di Scansano Srl",
    "wof:placetype":"venue"
},
  "geometry": {"coordinates":[11.112782,42.762859],"type":"Point"}
}