{
  "type": "Feature",
  "properties": {
    "iso:country":"IT",
    "sg:address":"36066 Sandrigo",
    "sg:city":"Sandrigo",
    "sg:orig_category":"Macchine, Impianti E Forniture Per Industria Grafica, Cartaria E Cartotecnica",
    "sg:phone":"+39 0444 461444",
    "sg:postcode":"36066",
    "sg:province":"Vicenza",
    "sg:website":"http://www.isotex.it",
    "wof:name":"Nuova Isotex Spa",
    "wof:placetype":"venue"
},
  "geometry": {"coordinates":[11.5504,45.632317],"type":"Point"}
}