{
  "type": "Feature",
  "properties": {
    "iso:country":"IT",
    "sg:address":"2, Via Degli Imbriani 20158 Milano",
    "sg:city":"Milano",
    "sg:classifiers":[
        {
            "category":"Autos & Motor Vehicles",
            "subcategory":"Automobile Sales",
            "type":"Retail Goods"
        }
    ],
    "sg:phone":"+39 02 3932 3375",
    "sg:postcode":"20158",
    "sg:province":"Milano",
    "sg:tags":[
        "motor-cars"
    ],
    "wof:name":"Autocarman (s.r.l.)",
    "wof:placetype":"venue"
},
  "geometry": {"coordinates":[9.1709566116,45.4969520569],"type":"Point"}
}