{
  "type": "Feature",
  "properties": {
    "iso:country":"IT",
    "sg:address":"Contrada Poggio Rotondo 95046 Palagonia",
    "sg:city":"Palagonia",
    "sg:classifiers":[
        {
            "category":"Farming",
            "subcategory":"Livestock Farm",
            "type":"Manufacturing & Wholesale Goods"
        }
    ],
    "sg:phone":"+39 095 795 4591",
    "sg:postcode":"95046",
    "sg:province":"Catania",
    "sg:tags":[
        "agriculture"
    ],
    "wof:name":"Ortofrutta Vitale S.r.l.",
    "wof:placetype":"venue"
},
  "geometry": {"coordinates":[14.744907,37.33083],"type":"Point"}
}