{
  "type": "Feature",
  "properties": {
    "addr:full":"60035 Jesi Jesi Ancona 60035",
    "addr:postcode":"60035;60035",
    "iso:country":"IT",
    "sg:address":"60035 Jesi",
    "sg:city":"Jesi",
    "sg:orig_category":"Pompe",
    "sg:phone":"+39 0731 605724",
    "sg:postcode":"60035",
    "sg:province":"Ancona",
    "wof:name":"Possanzini (s.r.l.)",
    "wof:placetype":"venue"
},
  "geometry": {"coordinates":[13.2792367935,43.5415840149],"type":"Point"}
}