{
  "type": "Feature",
  "properties": {
    "iso:country":"IT",
    "sg:address":"21100 Varese",
    "sg:city":"Varese",
    "sg:orig_category":"Cine-foto-ottica",
    "sg:phone":"+39 0332 234378",
    "sg:postcode":"21100",
    "sg:province":"Varese",
    "wof:name":"Tenderini Sergio - Atelier Di Fotografia",
    "wof:placetype":"venue"
},
  "geometry": {"coordinates":[8.829791,45.821014],"type":"Point"}
}