{
  "type": "Feature",
  "properties": {
    "iso:country":"IT",
    "sg:address":"Vle Industria 24060 Castelli Calepio",
    "sg:city":"Castelli Calepio",
    "sg:classifiers":[
        {
            "category":"Professional",
            "subcategory":"Engineering",
            "type":"Services"
        }
    ],
    "sg:phone":"+39 035 442 5360",
    "sg:postcode":"24060",
    "sg:province":"Bergamo",
    "sg:tags":[
        "plating",
        "chromium"
    ],
    "sg:website":"www.castelcrom.it/",
    "wof:name":"Castelcrom Srl",
    "wof:placetype":"venue"
},
  "geometry": {"coordinates":[9.669952,45.694904],"type":"Point"}
}