{
  "type": "Feature",
  "properties": {
    "iso:country":"IT",
    "sg:address":"23873 Missaglia",
    "sg:city":"Missaglia",
    "sg:orig_category":"Motori Ed Organi Di Trasmissione",
    "sg:phone":"+39 039 920 0423",
    "sg:postcode":"23873",
    "sg:province":"Lecco",
    "wof:name":"Sircatene S.p.a.",
    "wof:placetype":"venue"
},
  "geometry": {"coordinates":[9.4148025513,45.8356628418],"type":"Point"}
}