{
  "type": "Feature",
  "properties": {
    "iso:country":"IT",
    "sg:address":"00136 Roma",
    "sg:city":"Roma",
    "sg:orig_category":"Condizionatori Aria - Commercio",
    "sg:phone":"+39 06 3542 0649",
    "sg:postcode":"00136",
    "sg:province":"Roma",
    "wof:name":"Expert R.t.e. Color Srl",
    "wof:placetype":"venue"
},
  "geometry": {"coordinates":[12.445798,41.923347],"type":"Point"}
}