{
  "type": "Feature",
  "properties": {
    "iso:country":"IT",
    "sg:address":"Via Borgovico 138 22100 Como",
    "sg:city":"Como",
    "sg:classifiers":[
        {
            "category":"Banks & Credit Unions",
            "subcategory":"Investment Brokerage",
            "type":"Services"
        }
    ],
    "sg:phone":"+39 031 574400",
    "sg:postcode":"22100",
    "sg:province":"Como",
    "sg:tags":[
        "accessory",
        "high-fashion"
    ],
    "sg:website":"www.paninidue.com",
    "wof:name":"Gerardo Panini Spa",
    "wof:placetype":"venue"
},
  "geometry": {"coordinates":[9.085456,45.811966],"type":"Point"}
}