{
  "type": "Feature",
  "properties": {
    "iso:country":"IT",
    "sg:address":"20052 Monza",
    "sg:city":"Monza",
    "sg:orig_category":"Elettrodomestici Accessori E Parti - Produzione E Ingrosso",
    "sg:phone":"+39 039 832696",
    "sg:postcode":"20052",
    "sg:province":"Milano",
    "sg:website":"http://www.marotrec.it",
    "wof:name":"Marotrec Snc Di M. Galbarini & C.",
    "wof:placetype":"venue"
},
  "geometry": {"coordinates":[9.27788,45.574421],"type":"Point"}
}