{
  "type": "Feature",
  "properties": {
    "iso:country":"IT",
    "sg:address":"41038 San Felice Sul Panaro",
    "sg:city":"San Felice sul Panaro",
    "sg:orig_category":"Trattamenti Termici E Superficiali Metalli, Galvanotecnica",
    "sg:phone":"+39 0535 86411",
    "sg:postcode":"41038",
    "sg:province":"Modena",
    "wof:name":"Smaltiflex (s.p.a.)",
    "wof:placetype":"venue"
},
  "geometry": {"coordinates":[11.11744,44.834057],"type":"Point"}
}