{
  "type": "Feature",
  "properties": {
    "iso:country":"IT",
    "sg:address":"10138 Torino",
    "sg:city":"Torino",
    "sg:orig_category":"Cine-foto-ottica. Articoli Medico-sanitari Ed Ortopedici",
    "sg:phone":"+39 011 758963",
    "sg:postcode":"10138",
    "sg:province":"Torino",
    "wof:name":"Rikcars's (s.n.c.)",
    "wof:placetype":"venue"
},
  "geometry": {"coordinates":[7.646844,45.070194],"type":"Point"}
}