{
  "type": "Feature",
  "properties": {
    "iso:country":"IT",
    "sg:address":"07041 Alghero",
    "sg:city":"Alghero",
    "sg:orig_category":"Oli Alimentari E Frantoi Oleari",
    "sg:phone":"+39 079 951597",
    "sg:postcode":"07041",
    "sg:province":"Sassari",
    "wof:name":"Antica Compagnia Olearia Sarda Di Fois A. G.",
    "wof:placetype":"venue"
},
  "geometry": {"coordinates":[8.381725,40.650681],"type":"Point"}
}