{
  "type": "Feature",
  "properties": {
    "iso:country":"IT",
    "sg:address":"25124 Brescia",
    "sg:city":"Brescia",
    "sg:orig_category":"Studi E Consulenze Amministrative, Commerciali E Aziendali. Banche E Servizi Finanziari. Agenzie D'affari E Servizi Commerciali. Consulenze Tecniche, Amministrative E Perizie",
    "sg:phone":"+39 030 242 7785",
    "sg:postcode":"25124",
    "sg:province":"Brescia",
    "sg:website":"http://www.globalita.com",
    "wof:name":"Global.ita Srl",
    "wof:placetype":"venue"
},
  "geometry": {"coordinates":[10.215641,45.525333],"type":"Point"}
}