{
  "type": "Feature",
  "properties": {
    "iso:country":"IT",
    "sg:address":"25135 Brescia",
    "sg:city":"Brescia",
    "sg:orig_category":"Servizi E Lavori Per Edilizia E Lavori Pubblici. Servizi E Lavori Per Ecologia E Smaltimento Rifiuti. Macchine E Forniture Per Ecologia E Smaltimento Rifiuti. Acqua, Luce, Gas E Societa' Di Esercizio ",
    "sg:phone":"+39 030 231 2191",
    "sg:postcode":"25135",
    "sg:province":"Brescia",
    "wof:name":"Gruppo Val Carobbio",
    "wof:placetype":"venue"
},
  "geometry": {"coordinates":[10.258636,45.523624],"type":"Point"}
}