{
  "type": "Feature",
  "properties": {
    "iso:country":"IT",
    "sg:address":"11026 Pont Saint Martin",
    "sg:orig_category":"Lavorazioni Meccaniche E Servizi. Servizi Per Imballaggio E Confezionamento",
    "sg:phone":"+39 0125 809007",
    "sg:postcode":"11026",
    "sg:province":"Aosta",
    "wof:name":"Service 2000 Soc.coop.r.l.",
    "wof:placetype":"venue"
},
  "geometry": {"coordinates":[7.788478,45.593369],"type":"Point"}
}