{
  "type": "Feature",
  "properties": {
    "iso:country":"IT",
    "sg:address":"80141 Napoli",
    "sg:city":"Napoli",
    "sg:orig_category":"Automobili E Mezzi Di Trasporto",
    "sg:phone":"+39 081 599 1905",
    "sg:postcode":"80141",
    "sg:province":"Napoli",
    "sg:website":"http://www.bellanauto.com",
    "wof:name":"Bellanauto Srl",
    "wof:placetype":"venue"
},
  "geometry": {"coordinates":[14.367335,40.933609],"type":"Point"}
}