{
  "type": "Feature",
  "properties": {
    "addr:full":"10, Via Del Commercio 56034 Casciana Terme Casciana Terme Pisa 56034",
    "addr:postcode":"56034;56034",
    "addr:street":"Via Del Commercio",
    "iso:country":"IT",
    "sg:address":"10, Via Del Commercio 56034 Casciana Terme",
    "sg:city":"Casciana Terme",
    "sg:classifiers":[
        {
            "category":"Shopping",
            "subcategory":"Crafts & Fabrics",
            "type":"Retail Goods"
        }
    ],
    "sg:phone":"+39 0587 645229",
    "sg:postcode":"56034",
    "sg:province":"Pisa",
    "sg:tags":[
        "ceramic"
    ],
    "wof:name":"Gazzarrini Fratelli (s.a.s.)",
    "wof:placetype":"venue"
},
  "geometry": {"coordinates":[10.621223,43.52832],"type":"Point"}
}