{
  "type": "Feature",
  "properties": {
    "iso:country":"IT",
    "sg:address":"Via Palmiro Togliatti 27051 Cava Manara",
    "sg:city":"Cava Manara",
    "sg:classifiers":[
        {
            "category":"Wholesale",
            "subcategory":"Medical Equipment & Supplies",
            "type":"Manufacturing & Wholesale Goods"
        }
    ],
    "sg:phone":"+39 0382 552882",
    "sg:postcode":"27051",
    "sg:province":"Pavia",
    "sg:tags":[
        "-",
        "health",
        "instrument"
    ],
    "wof:name":"Medrad Italia S.r.l.",
    "wof:placetype":"venue"
},
  "geometry": {"coordinates":[9.133402,45.158817],"type":"Point"}
}