{
  "type": "Feature",
  "properties": {
    "iso:country":"IT",
    "sg:address":"36031 Dueville",
    "sg:city":"Dueville",
    "sg:orig_category":"Batterie, Accumulatori E Pile - Commercio",
    "sg:phone":"+39 0444 593207",
    "sg:postcode":"36031",
    "sg:province":"Vicenza",
    "wof:name":"Pe. De. Oil Group Srl",
    "wof:placetype":"venue"
},
  "geometry": {"coordinates":[11.572045,45.62674],"type":"Point"}
}