{
  "type": "Feature",
  "properties": {
    "iso:country":"IT",
    "sg:address":"49, Via Nazionale 17037 Ortovero",
    "sg:city":"Ortovero",
    "sg:classifiers":[
        {
            "category":"Farming",
            "subcategory":"Livestock Farm",
            "type":"Manufacturing & Wholesale Goods"
        }
    ],
    "sg:phone":"+39 0182 559853",
    "sg:postcode":"17037",
    "sg:province":"Savona",
    "sg:tags":[
        "agriculture"
    ],
    "wof:name":"Porcella Enzo",
    "wof:placetype":"venue"
},
  "geometry": {"coordinates":[8.064485,44.055748],"type":"Point"}
}