{
  "type": "Feature",
  "properties": {
    "iso:country":"IT",
    "sg:address":"20129 Milano",
    "sg:city":"Milano",
    "sg:classifiers":[
        {
            "category":"Building & Trades",
            "subcategory":"Construction",
            "type":"Services"
        }
    ],
    "sg:phone":"+39 02 2953 4610",
    "sg:postcode":"20129",
    "sg:province":"Milano",
    "sg:tags":[
        "equipment",
        "heat",
        "heating",
        "engineering"
    ],
    "wof:name":"Aqa Srl",
    "wof:placetype":"venue"
},
  "geometry": {"coordinates":[9.206401,45.473087],"type":"Point"}
}