{
  "type": "Feature",
  "properties": {
    "iso:country":"IT",
    "sg:address":"20010 Cornaredo",
    "sg:city":"Cornaredo",
    "sg:orig_category":"Professionisti - Studi E Servizi Ed Associazioni Di Interesse Aziendale. Associazioni Ed Organismi Di Interesse Pubblico",
    "sg:phone":"+39 02 9356 5324",
    "sg:postcode":"20010",
    "sg:province":"Milano",
    "wof:name":"Lega Nord",
    "wof:placetype":"venue"
},
  "geometry": {"coordinates":[9.0180702209,45.4813461304],"type":"Point"}
}