{
  "type": "Feature",
  "properties": {
    "iso:country":"IT",
    "sg:address":"Cagliari, Ca",
    "sg:classifiers":[
        {
            "category":"Banks & Credit Unions",
            "subcategory":"Bank",
            "type":"Services"
        }
    ],
    "wof:name":"Villaservice",
    "wof:placetype":"venue"
},
  "geometry": {"coordinates":[9.109228,39.215458],"type":"Point"}
}