{
  "type": "Feature",
  "properties": {
    "addr:full":"20035 Lissone Lissone Milano 20035",
    "addr:postcode":"20035;20035",
    "iso:country":"IT",
    "sg:address":"20035 Lissone",
    "sg:city":"Lissone",
    "sg:orig_category":"Forniture Per Abbigliamento E Pelletterie",
    "sg:phone":"+39 039 481825",
    "sg:postcode":"20035",
    "sg:province":"Milano",
    "wof:name":"Faiss Model Di Molteni Alessia",
    "wof:placetype":"venue"
},
  "geometry": {"coordinates":[9.2401723862,45.620349884],"type":"Point"}
}