{
  "type": "Feature",
  "properties": {
    "iso:country":"IT",
    "sg:address":"28060 San Pietro Mosezzo",
    "sg:city":"San Pietro Mosezzo",
    "sg:orig_category":"Prodotti Alimentari",
    "sg:phone":"+39 0321 468551",
    "sg:postcode":"28060",
    "sg:province":"Novara",
    "wof:name":"Pai (s.p.a.)",
    "wof:placetype":"venue"
},
  "geometry": {"coordinates":[8.5570964813,45.455909729],"type":"Point"}
}