{
  "type": "Feature",
  "properties": {
    "iso:country":"IT",
    "sg:address":"22074 Lomazzo",
    "sg:city":"Lomazzo",
    "sg:orig_category":"Arte Ed Artigianato Artistico",
    "sg:phone":"+39 02 9637 0565",
    "sg:postcode":"22074",
    "sg:province":"Como",
    "wof:name":"Somaini Francesco",
    "wof:placetype":"venue"
},
  "geometry": {"coordinates":[9.022512,45.701065],"type":"Point"}
}