{
  "type": "Feature",
  "properties": {
    "iso:country":"IT",
    "sg:address":"Contrada Fontanavecchia 258 86100 Campobasso",
    "sg:city":"Campobasso",
    "sg:classifiers":[
        {
            "category":"Food & Beverages",
            "subcategory":"Specialty",
            "type":"Retail Goods"
        }
    ],
    "sg:phone":"+39 0874 90245",
    "sg:postcode":"86100",
    "sg:province":"Campobasso",
    "sg:tags":[
        "olive-oil"
    ],
    "sg:website":"www.colavita.it",
    "wof:name":"Oleifici Colavita Spa",
    "wof:placetype":"venue"
},
  "geometry": {"coordinates":[14.664799,41.560085],"type":"Point"}
}