{
  "type": "Feature",
  "properties": {
    "addr:full":"29, Via Monte Grappa 00015 Monterotondo Monterotondo Roma 00015",
    "addr:postcode":"00015;roma 00015",
    "addr:street":"Via Monte Grappa",
    "iso:country":"IT",
    "sg:address":"29, Via Monte Grappa 00015 Monterotondo",
    "sg:city":"Monterotondo",
    "sg:classifiers":[
        {
            "category":"Shopping",
            "subcategory":"Crafts & Fabrics",
            "type":"Retail Goods"
        }
    ],
    "sg:phone":"+39 39069004508",
    "sg:postcode":"00015",
    "sg:province":"Roma",
    "wof:name":"Nuovo Canapificio Centro Meridionale Srl",
    "wof:placetype":"venue"
},
  "geometry": {"coordinates":[12.5761241913,42.0563926697],"type":"Point"}
}