{
  "type": "Feature",
  "properties": {
    "iso:country":"IT",
    "sg:address":"80010 Quarto",
    "sg:city":"Quarto",
    "sg:orig_category":"Asfalti, Bitumi Ed Affini",
    "sg:phone":"+39 081 876 6778",
    "sg:postcode":"80010",
    "sg:province":"Napoli",
    "wof:name":"Remartino Bruno",
    "wof:placetype":"venue"
},
  "geometry": {"coordinates":[14.140315,40.877815],"type":"Point"}
}