{
  "type": "Feature",
  "properties": {
    "addr:full":"20094 Corsico Corsico Milano 20094",
    "addr:postcode":"20094;20094",
    "iso:country":"IT",
    "sg:address":"20094 Corsico",
    "sg:city":"Corsico",
    "sg:orig_category":"Prodotti Alimentari",
    "sg:phone":"+39 02 447 3046",
    "sg:postcode":"20094",
    "sg:province":"Milano",
    "wof:name":"Martello Alessandrina",
    "wof:placetype":"venue"
},
  "geometry": {"coordinates":[9.1160430908,45.4328651428],"type":"Point"}
}