{
  "type": "Feature",
  "properties": {
    "iso:country":"IT",
    "sg:address":"00123 Roma",
    "sg:city":"Roma",
    "sg:orig_category":"Servizi E Lavori Per Edilizia E Lavori Pubblici. Acqua, Luce, Gas E Societa' Di Esercizio Pubblico",
    "sg:phone":"+39 06 304 6460",
    "sg:postcode":"00123",
    "sg:province":"Roma",
    "wof:name":"Enel",
    "wof:placetype":"venue"
},
  "geometry": {"coordinates":[12.323482,42.02309],"type":"Point"}
}