{
  "type": "Feature",
  "properties": {
    "iso:country":"IT",
    "sg:address":"Via Trento Trieste 19 36050 Zermeghedo",
    "sg:city":"Zermeghedo",
    "sg:orig_category":"Hide Tanning Tools",
    "sg:phone":"+39 0444 685575",
    "sg:postcode":"36050",
    "sg:province":"Vicenza",
    "sg:website":"www.nardisandro.com",
    "wof:name":"Sandro Nardi Impresa Individuale",
    "wof:placetype":"venue"
},
  "geometry": {"coordinates":[11.369022,45.476433],"type":"Point"}
}