{
  "type": "Feature",
  "properties": {
    "iso:country":"IT",
    "sg:address":"10050 Borgone Susa",
    "sg:city":"Borgone Susa",
    "sg:orig_category":"Non-classified Establishments",
    "sg:phone":"+39 011 964 5360",
    "sg:postcode":"10050",
    "sg:province":"Torino",
    "wof:name":"Carnino Ernesto",
    "wof:placetype":"venue"
},
  "geometry": {"coordinates":[7.676765,45.056751],"type":"Point"}
}