{
  "type": "Feature",
  "properties": {
    "addr:full":"21, V. Gitti 25060 Marcheno Valtrompia Marcheno Brescia 25060",
    "addr:housenumber":"21",
    "addr:postcode":"25060;25060",
    "addr:street":"V. Gitti",
    "iso:country":"IT",
    "sg:address":"21, V. Gitti 25060 Marcheno Valtrompia",
    "sg:city":"Marcheno",
    "sg:classifiers":[
        {
            "category":"Shopping",
            "type":"Retail Goods"
        }
    ],
    "sg:phone":"+39 030 896 0112",
    "sg:postcode":"25060",
    "sg:province":"Brescia",
    "sg:tags":[
        "finished",
        "-",
        "metallic"
    ],
    "sg:website":"http://www.tecnica-srl.com:ws_end: :mark:ws:http://www.paginegialle.it/tecnicasrl-01",
    "wof:name":"Tecnica Srl",
    "wof:placetype":"venue"
},
  "geometry": {"coordinates":[10.2125997543,45.7017250061],"type":"Point"}
}