{
  "type": "Feature",
  "properties": {
    "addr:full":"07020 Aglientu Aglientu Olbia-Tempio 07020",
    "addr:housenumber":"07020",
    "addr:postcode":"07020",
    "addr:street":"Aglientu Aglientu Olbia-Tempio",
    "iso:country":"IT",
    "sg:address":"07020 Aglientu",
    "sg:city":"Aglientu",
    "sg:orig_category":"Agenzie Immobiliari",
    "sg:phone":"+39 079 655053",
    "sg:postcode":"07020",
    "sg:province":"Olbia-Tempio",
    "wof:name":"Tiesse Edilizia Snc",
    "wof:placetype":"venue"
},
  "geometry": {"coordinates":[9.185748,41.163517],"type":"Point"}
}