{
  "type": "Feature",
  "properties": {
    "iso:country":"IT",
    "sg:address":"51015 Monsummano Terme",
    "sg:city":"Monsummano Terme",
    "sg:orig_category":"Calzature - Produzione E Ingrosso",
    "sg:phone":"+39 0572 95611",
    "sg:postcode":"51015",
    "sg:province":"Pistoia",
    "sg:website":"http://www.gregor.it",
    "wof:name":"Gregor Srl",
    "wof:placetype":"venue"
},
  "geometry": {"coordinates":[10.80619,43.868244],"type":"Point"}
}