{
  "type": "Feature",
  "properties": {
    "iso:country":"IT",
    "sg:address":"59013 Montemurlo",
    "sg:city":"Montemurlo",
    "sg:orig_category":"Abbigliamento Esterno, Maglierie E Pelliccerie. Forniture Per Abbigliamento E Pelletterie",
    "sg:phone":"+39 0574 682724",
    "sg:postcode":"59013",
    "sg:province":"Prato",
    "wof:name":"Gepi Snc Di Indelli Giuseppe & C.",
    "wof:placetype":"venue"
},
  "geometry": {"coordinates":[11.027933,43.904713],"type":"Point"}
}