{
  "type": "Feature",
  "properties": {
    "iso:country":"IT",
    "sg:address":"25050 Zone",
    "sg:city":"Zone",
    "sg:orig_category":"Servizi Per Lo Sport E Il Tempo Libero. Alberghi E Strutture Extra Alberghiere",
    "sg:phone":"+39 030 987 0990",
    "sg:postcode":"25050",
    "sg:province":"Brescia",
    "wof:name":"Berardi Flavio",
    "wof:placetype":"venue"
},
  "geometry": {"coordinates":[10.21396,45.524174],"type":"Point"}
}