{
  "type": "Feature",
  "properties": {
    "addr:full":"20128 Milano Milano Milano 20128",
    "addr:postcode":"20128;20128",
    "iso:country":"IT",
    "sg:address":"20128 Milano",
    "sg:city":"Milano",
    "sg:orig_category":"Agenzie Di Spettacolo E Di Animazione",
    "sg:phone":"+39 0227225",
    "sg:postcode":"20128",
    "sg:province":"Milano",
    "sg:website":"http://www.mas.it",
    "wof:name":"Mas Srl",
    "wof:placetype":"venue"
},
  "geometry": {"coordinates":[9.237911,45.507656],"type":"Point"}
}