{
  "type": "Feature",
  "properties": {
    "addr:full":"00040 Montecompatri Montecompatri Roma 00040",
    "addr:postcode":"00040;roma 00040",
    "iso:country":"IT",
    "sg:address":"00040 Montecompatri",
    "sg:city":"Montecompatri",
    "sg:orig_category":"Servizi E Lavori Per Edilizia E Lavori Pubblici. Acqua, Luce, Gas E Societa' Di Esercizio Pubblico",
    "sg:phone":"+39 06 947 6035",
    "sg:postcode":"00040",
    "sg:province":"Roma",
    "wof:name":"Acea Ato2 Spa",
    "wof:placetype":"venue"
},
  "geometry": {"coordinates":[12.711316,41.885487],"type":"Point"}
}