{
  "type": "Feature",
  "properties": {
    "iso:country":"IT",
    "sg:address":"5, Viale Restelli Francesco 20124 Milano",
    "sg:city":"Milano",
    "sg:classifiers":[
        {
            "category":"Manufacturing",
            "subcategory":"Metals",
            "type":"Manufacturing & Wholesale Goods"
        }
    ],
    "sg:phone":"+39 390 266 8931",
    "sg:postcode":"20124",
    "sg:province":"Milano",
    "sg:tags":[
        "metallurgy",
        "metalworking"
    ],
    "wof:name":"Pechiney Italia (s.p.a.)",
    "wof:placetype":"venue"
},
  "geometry": {"coordinates":[9.1956167221,45.4883995056],"type":"Point"}
}