{
  "type": "Feature",
  "properties": {
    "iso:country":"IT",
    "sg:address":"11, Scali Del Corso 57123 Livorno",
    "sg:city":"Livorno",
    "sg:classifiers":[
        {
            "category":"Banks & Credit Unions",
            "subcategory":"Investment Brokerage",
            "type":"Services"
        }
    ],
    "sg:phone":"+39 0586 892072",
    "sg:postcode":"57123",
    "sg:province":"Livorno",
    "sg:tags":[
        "-",
        "transport",
        "related"
    ],
    "wof:name":"Cosmos (s.a.s.)",
    "wof:placetype":"venue"
},
  "geometry": {"coordinates":[10.304885,43.547741],"type":"Point"}
}