{
  "type": "Feature",
  "properties": {
    "addr:full":"Via Montello 2; Avezzano",
    "addr:housenumber":"2",
    "addr:street":"Via Montello",
    "iso:country":"IT",
    "sg:address":"Via Montello 2; Avezzano",
    "sg:classifiers":[
        {
            "category":"Banks & Credit Unions",
            "subcategory":"Bank",
            "type":"Services"
        }
    ],
    "sg:phone":"+39 0863 412936",
    "wof:name":"Banca Di Roma",
    "wof:placetype":"venue"
},
  "geometry": {"coordinates":[13.429268,42.037708],"type":"Point"}
}