{
  "type": "Feature",
  "properties": {
    "addr:full":"37, Via Giovanni Xxiii 20090 Rodano Rodano Milano 20090",
    "addr:postcode":"20090;20090",
    "addr:street":"Via Giovanni Xxiii",
    "iso:country":"IT",
    "sg:address":"37, Via Giovanni Xxiii 20090 Rodano",
    "sg:city":"Rodano",
    "sg:classifiers":[
        {
            "category":"Manufacturing",
            "subcategory":"Paper Products",
            "type":"Manufacturing & Wholesale Goods"
        }
    ],
    "sg:phone":"+39 02 9532 0920",
    "sg:postcode":"20090",
    "sg:province":"Milano",
    "sg:tags":[
        "cardboard"
    ],
    "wof:name":"Reno De Medici S.p.a.",
    "wof:placetype":"venue"
},
  "geometry": {"coordinates":[9.3334655762,45.4730033875],"type":"Point"}
}