{
  "type": "Feature",
  "properties": {
    "iso:country":"IT",
    "sg:address":"Via G.carducci 5; Udine; 33100",
    "sg:city":"Udine",
    "sg:classifiers":[
        {
            "category":"Banks & Credit Unions",
            "subcategory":"Bank",
            "type":"Services"
        }
    ],
    "sg:phone":"+39 0432 504349",
    "sg:postcode":"33100",
    "sg:province":"Udine",
    "wof:name":"Cassa Di Risparmio, Delle Provincie Lombarde Spa",
    "wof:placetype":"venue"
},
  "geometry": {"coordinates":[13.240194,46.05933],"type":"Point"}
}