{
  "type": "Feature",
  "properties": {
    "addr:full":"17, Via Moncalieri 10029 Villastellone Villastellone Torino 10029",
    "addr:postcode":"10029;10029",
    "addr:street":"Via Moncalieri",
    "iso:country":"IT",
    "sg:address":"17, Via Moncalieri 10029 Villastellone",
    "sg:city":"Villastellone",
    "sg:classifiers":[
        {
            "category":"Manufacturing",
            "subcategory":"Metals",
            "type":"Manufacturing & Wholesale Goods"
        }
    ],
    "sg:phone":"+39 011 961 0638",
    "sg:postcode":"10029",
    "sg:province":"Torino",
    "sg:tags":[
        "metallurgy",
        "metalworking"
    ],
    "wof:name":"Edil La Fer (s.n.c.)",
    "wof:placetype":"venue"
},
  "geometry": {"coordinates":[7.7223305702,44.9362068176],"type":"Point"}
}