{
  "type": "Feature",
  "properties": {
    "iso:country":"IT",
    "sg:address":"43100 Parma",
    "sg:city":"Parma",
    "sg:orig_category":"Macchine, Impianti Ed Attrezzature Per Industria Alimentare E Bevande. Apparecchiature E Sistemi Per Imballaggio E Confezionamento",
    "sg:phone":"+39 0521 272855",
    "sg:postcode":"43100",
    "sg:province":"Parma",
    "wof:name":"Logics & Controls Snc",
    "wof:placetype":"venue"
},
  "geometry": {"coordinates":[10.356587,44.811222],"type":"Point"}
}