{
  "type": "Feature",
  "properties": {
    "iso:country":"IT",
    "sg:address":"42/a, Via S. Egidio 33074 Fontanafredda",
    "sg:city":"Fontanafredda",
    "sg:classifiers":[
        {
            "category":"Real Estate",
            "subcategory":"Surveying",
            "type":"Services"
        }
    ],
    "sg:phone":"+39 0434 997580",
    "sg:postcode":"33074",
    "sg:province":"Pordenone",
    "sg:tags":[
        "equipment",
        "material",
        "good",
        "-",
        "handling"
    ],
    "wof:name":"Gru Comedil S.p.a.",
    "wof:placetype":"venue"
},
  "geometry": {"coordinates":[12.655044,45.96265],"type":"Point"}
}