{
  "type": "Feature",
  "properties": {
    "iso:country":"IT",
    "sg:address":"00144 Roma",
    "sg:city":"Roma",
    "sg:orig_category":"Copisterie",
    "sg:phone":"+39 06 5422 1753",
    "sg:postcode":"00144",
    "sg:province":"Roma",
    "wof:name":"Mitam Srl",
    "wof:placetype":"venue"
},
  "geometry": {"coordinates":[12.463812,41.83379],"type":"Point"}
}