{
  "type": "Feature",
  "properties": {
    "addr:full":"50129 Firenze Firenze Firenze 50129",
    "addr:postcode":"50129;50129",
    "iso:country":"IT",
    "sg:address":"50129 Firenze",
    "sg:city":"Firenze",
    "sg:orig_category":"Abbigliamento Industria - Forniture Ed Accessori",
    "sg:phone":"+39 055 411874",
    "sg:postcode":"50129",
    "sg:province":"Firenze",
    "wof:name":"Creazioni Meucci Snc",
    "wof:placetype":"venue"
},
  "geometry": {"coordinates":[10.747925,43.67762],"type":"Point"}
}