{
  "type": "Feature",
  "properties": {
    "iso:country":"IT",
    "sg:address":"Via Giuseppe Parini 28064 Sillavengo",
    "sg:city":"Sillavengo",
    "sg:classifiers":[
        {
            "category":"Shopping",
            "subcategory":"Clothing, Apparel, & Fashions",
            "type":"Retail Goods"
        }
    ],
    "sg:phone":"+39 0321 824180",
    "sg:postcode":"28064",
    "sg:province":"Novara",
    "sg:tags":[
        "clothes"
    ],
    "wof:name":"S.d.m. Maglierie S.r.l.",
    "wof:placetype":"venue"
},
  "geometry": {"coordinates":[8.436523,45.523674],"type":"Point"}
}