{
  "type": "Feature",
  "properties": {
    "addr:full":"36015 Schio Schio Vicenza 36015",
    "addr:postcode":"36015;36015",
    "iso:country":"IT",
    "sg:address":"36015 Schio",
    "sg:city":"Schio",
    "sg:orig_category":"Archiviazione Documenti - Servizio",
    "sg:phone":"+39 0445 577350",
    "sg:postcode":"36015",
    "sg:province":"Vicenza",
    "wof:name":"Mc Service Srl",
    "wof:placetype":"venue"
},
  "geometry": {"coordinates":[11.546682,45.571991],"type":"Point"}
}