{
  "type": "Feature",
  "properties": {
    "addr:full":"25065 Lumezzane Lumezzane Brescia 25065",
    "addr:postcode":"25065;25065",
    "iso:country":"IT",
    "sg:address":"25065 Lumezzane",
    "sg:city":"Lumezzane",
    "sg:orig_category":"Acciaierie E Fonderie",
    "sg:phone":"+39 030 871421",
    "sg:postcode":"25065",
    "sg:province":"Brescia",
    "wof:name":"Pmb Di Bugatti S. & C. Snc",
    "wof:placetype":"venue"
},
  "geometry": {"coordinates":[10.225518,45.652805],"type":"Point"}
}