{
  "type": "Feature",
  "properties": {
    "iso:country":"IT",
    "sg:address":"21046 Malnate",
    "sg:city":"Malnate",
    "sg:orig_category":"Fotografia - Servizi, Studi, Sviluppo E Stampa",
    "sg:phone":"+39 0332 425397",
    "sg:postcode":"21046",
    "sg:province":"Varese",
    "wof:name":"Il Diaframma Di Ghisi Pietro Giorgio",
    "wof:placetype":"venue"
},
  "geometry": {"coordinates":[8.8785486221,45.8006858826],"type":"Point"}
}