{
  "type": "Feature",
  "properties": {
    "iso:country":"IT",
    "sg:address":"45, Via Gramsci Antonio 20032 Cormano",
    "sg:city":"Cormano",
    "sg:classifiers":[
        {
            "category":"Shopping",
            "subcategory":"Computers & Home Electronics",
            "type":"Retail Goods"
        }
    ],
    "sg:phone":"+39 02 6630 0740",
    "sg:postcode":"20032",
    "sg:province":"Milano",
    "sg:tags":[
        "electronic",
        "electrical",
        "equipment"
    ],
    "wof:name":"Plexiform (s.r.l.)",
    "wof:placetype":"venue"
},
  "geometry": {"coordinates":[9.167365,45.539234],"type":"Point"}
}