{
  "type": "Feature",
  "properties": {
    "addr:full":"65013 Citt\u00e0 Sant'angelo Pescara 65013",
    "addr:postcode":"65013;65013",
    "iso:country":"IT",
    "sg:address":"65013 Citt\u00e0 Sant'angelo",
    "sg:orig_category":"Apparecchiature E Sistemi Per Magazzinaggio E Movimentazione",
    "sg:phone":"+39 085 950 6197",
    "sg:postcode":"65013",
    "sg:province":"Pescara",
    "sg:website":"http://www.coprikompatt.com",
    "wof:name":"Coprikompatt Srl",
    "wof:placetype":"venue"
},
  "geometry": {"coordinates":[14.14081,42.524681],"type":"Point"}
}