{
  "type": "Feature",
  "properties": {
    "addr:full":"50136 Firenze Firenze Firenze 50136",
    "addr:postcode":"50136;50136",
    "iso:country":"IT",
    "sg:address":"50136 Firenze",
    "sg:city":"Firenze",
    "sg:orig_category":"Vigilanza E Sorveglianza",
    "sg:phone":"+39 055 23591",
    "sg:postcode":"50136",
    "sg:province":"Firenze",
    "sg:website":"http://www.argo-fi.com",
    "wof:name":"Argo Soc.coop.r.l.",
    "wof:placetype":"venue"
},
  "geometry": {"coordinates":[11.29915,43.766804],"type":"Point"}
}