{
  "type": "Feature",
  "properties": {
    "addr:full":"50124 Sieci Firenze 50124",
    "addr:postcode":"50124;50124",
    "addr:street":"Sieci",
    "iso:country":"IT",
    "sg:address":"50124 Sieci",
    "sg:orig_category":"Animali Domestici, Articoli Ed Alimenti - Vendita Al Dettaglio",
    "sg:phone":"+39 055 832 8774",
    "sg:postcode":"50124",
    "sg:province":"Firenze",
    "wof:name":"Ci.m.a.zoo. Di Cinelli",
    "wof:placetype":"venue"
},
  "geometry": {"coordinates":[11.256902,43.768734],"type":"Point"}
}