{
  "type": "Feature",
  "properties": {
    "addr:full":"66100 Chieti Chieti Chieti 66100",
    "addr:postcode":"66100;66100",
    "iso:country":"IT",
    "sg:address":"66100 Chieti",
    "sg:city":"Chieti",
    "sg:orig_category":"Elaboratori Elettronici",
    "sg:phone":"+39 0871 552599",
    "sg:postcode":"66100",
    "sg:province":"Chieti",
    "wof:name":"Omnibus",
    "wof:placetype":"venue"
},
  "geometry": {"coordinates":[14.158225,42.361412],"type":"Point"}
}