{
  "type": "Feature",
  "properties": {
    "iso:country":"IT",
    "sg:address":"24040 Madone",
    "sg:city":"Madone",
    "sg:orig_category":"Materiali Semilavorati Metallici",
    "sg:phone":"+39 035 994420",
    "sg:postcode":"24040",
    "sg:province":"Bergamo",
    "wof:name":"S.i.t.i.m. Di Facchinetti Antonio & C. Sas",
    "wof:placetype":"venue"
},
  "geometry": {"coordinates":[9.549462,45.650681],"type":"Point"}
}