{
  "type": "Feature",
  "properties": {
    "addr:full":"60, Viale Giacomo Matteotti 89021 Cinquefrondi Cinquefrondi Reggio Di Calabria 89021",
    "addr:housenumber":"60",
    "addr:postcode":"89021;89021",
    "addr:street":"Viale Giacomo Matteotti",
    "iso:country":"IT",
    "sg:address":"60, Viale Giacomo Matteotti 89021 Cinquefrondi",
    "sg:city":"Cinquefrondi",
    "sg:classifiers":[
        {
            "category":"Communications",
            "subcategory":"Television Station",
            "type":"Services"
        }
    ],
    "sg:phone":"+39 0966 931987",
    "sg:postcode":"89021",
    "sg:province":"Reggio Di Calabria",
    "sg:tags":[
        "audio-visual"
    ],
    "wof:name":"Mammola",
    "wof:placetype":"venue"
},
  "geometry": {"coordinates":[15.650137,38.114689],"type":"Point"}
}