{
  "type": "Feature",
  "properties": {
    "iso:country":"IT",
    "sg:address":"Corso Italia 70; Vignola; 41058",
    "sg:city":"Vignola",
    "sg:classifiers":[
        {
            "category":"Banks & Credit Unions",
            "subcategory":"Bank",
            "type":"Services"
        }
    ],
    "sg:phone":"+39 059 760855",
    "sg:postcode":"41058",
    "sg:province":"Modena",
    "wof:name":"Cassa Di Risparmio Di Vignola Spa",
    "wof:placetype":"venue"
},
  "geometry": {"coordinates":[11.010445,44.478168],"type":"Point"}
}