{
  "type": "Feature",
  "properties": {
    "iso:country":"IT",
    "sg:address":"15, Corso Inghilterra 12084 Mondovi'",
    "sg:classifiers":[
        {
            "category":"Professional",
            "subcategory":"Engineering",
            "type":"Services"
        }
    ],
    "sg:phone":"+39 0174 560611",
    "sg:postcode":"12084",
    "sg:province":"Cuneo",
    "sg:tags":[
        "machine",
        "-",
        "mechanical"
    ],
    "wof:name":"Sial-s.p.a.",
    "wof:placetype":"venue"
},
  "geometry": {"coordinates":[7.817162,44.412178],"type":"Point"}
}