{
  "type": "Feature",
  "properties": {
    "addr:full":"Via Marchesane 36061 Bassano Del Grappa Bassano del Grappa Vicenza 36061",
    "addr:postcode":"36061;36061",
    "addr:street":"Via Marchesane",
    "iso:country":"IT",
    "sg:address":"Via Marchesane 36061 Bassano Del Grappa",
    "sg:city":"Bassano del Grappa",
    "sg:classifiers":[
        {
            "category":"Manufacturing",
            "subcategory":"Paper Products",
            "type":"Manufacturing & Wholesale Goods"
        }
    ],
    "sg:phone":"+39 0424 500106",
    "sg:postcode":"36061",
    "sg:province":"Vicenza",
    "sg:tags":[
        "cardboard"
    ],
    "wof:name":"Selmar Srl",
    "wof:placetype":"venue"
},
  "geometry": {"coordinates":[11.6975421906,45.7478752136],"type":"Point"}
}