{
  "type": "Feature",
  "properties": {
    "iso:country":"IT",
    "sg:address":"41011 Campogalliano",
    "sg:city":"Campogalliano",
    "sg:orig_category":"Trasporti E Spedizioni Merci",
    "sg:phone":"+39 059 525252",
    "sg:postcode":"41011",
    "sg:province":"Modena",
    "sg:website":"http://www.sdm.mo.it",
    "wof:name":"Sdm Srl",
    "wof:placetype":"venue"
},
  "geometry": {"coordinates":[10.853719,44.687786],"type":"Point"}
}