{
  "type": "Feature",
  "properties": {
    "iso:country":"IT",
    "sg:address":"Via Maniago 99 33085 Maniago",
    "sg:city":"Maniago",
    "sg:classifiers":[
        {
            "category":"Wholesale",
            "subcategory":"Office Equipment",
            "type":"Manufacturing & Wholesale Goods"
        }
    ],
    "sg:phone":"+39 0427 71561",
    "sg:postcode":"33085",
    "sg:province":"Pordenone",
    "sg:tags":[
        "dental"
    ],
    "sg:website":"www.dentag.com",
    "wof:name":"Den.tag Srl",
    "wof:placetype":"venue"
},
  "geometry": {"coordinates":[12.736802,46.154251],"type":"Point"}
}