{
  "type": "Feature",
  "properties": {
    "iso:country":"IT",
    "sg:address":"40128 Bologna",
    "sg:city":"Bologna",
    "sg:orig_category":"Parrucche E Toupets - Produzione E Ingrosso",
    "sg:phone":"+39 051 327184",
    "sg:postcode":"40128",
    "sg:province":"Bologna",
    "wof:name":"Fair Fashion Di Barbone Loretta & C. Snc",
    "wof:placetype":"venue"
},
  "geometry": {"coordinates":[11.3411569595,44.518901825],"type":"Point"}
}