{
  "type": "Feature",
  "properties": {
    "addr:full":"22063 Cantu' Como 22063",
    "addr:postcode":"22063;22063",
    "addr:street":"Cantu ' Como",
    "iso:country":"IT",
    "sg:address":"22063 Cantu'",
    "sg:orig_category":"Tappezzieri - Forniture",
    "sg:phone":"+39 031 714677",
    "sg:postcode":"22063",
    "sg:province":"Como",
    "wof:name":"Lini & Lini Snc",
    "wof:placetype":"venue"
},
  "geometry": {"coordinates":[9.073638,45.765316],"type":"Point"}
}