{
  "type": "Feature",
  "properties": {
    "addr:full":"88842 Cutro Cutro Crotone 88842",
    "addr:postcode":"88842;88842",
    "iso:country":"IT",
    "sg:address":"88842 Cutro",
    "sg:city":"Cutro",
    "sg:orig_category":"Serramenti Ed Infissi",
    "sg:phone":"+39 0962 774035",
    "sg:postcode":"88842",
    "sg:province":"Crotone",
    "wof:name":"Ottobrini Antonio",
    "wof:placetype":"venue"
},
  "geometry": {"coordinates":[16.983086,38.992771],"type":"Point"}
}