{
  "type": "Feature",
  "properties": {
    "iso:country":"IT",
    "sg:address":"10156 Torino",
    "sg:city":"Torino",
    "sg:orig_category":"Fonderie Bronzo, Ottone E Rame",
    "sg:phone":"+39 011 262 1726",
    "sg:postcode":"10156",
    "sg:province":"Torino",
    "sg:website":"http://www.arischiappa.it",
    "wof:name":"A.r.i.s. Chiappa",
    "wof:placetype":"venue"
},
  "geometry": {"coordinates":[7.7186727524,45.1211776733],"type":"Point"}
}