{
  "type": "Feature",
  "properties": {
    "addr:full":"80144 Napoli Napoli Napoli 80144",
    "addr:housenumber":"80144",
    "addr:postcode":"80144",
    "iso:country":"IT",
    "sg:address":"80144 Napoli",
    "sg:city":"Napoli",
    "sg:orig_category":"Vetro: Prodotti E Lavorazioni",
    "sg:phone":"+39 081 780 1218",
    "sg:postcode":"80144",
    "sg:province":"Napoli",
    "wof:name":"Antica Vetreria Napoletana Di Barbato Francesco",
    "wof:placetype":"venue"
},
  "geometry": {"coordinates":[14.278188,40.875961],"type":"Point"}
}