{
  "type": "Feature",
  "properties": {
    "addr:full":"4, Via Kennedy 25019 Sirmione Sirmione Brescia 25019",
    "addr:postcode":"25019;25019",
    "addr:street":"Via Kennedy",
    "iso:country":"IT",
    "sg:address":"4, Via Kennedy 25019 Sirmione",
    "sg:city":"Sirmione",
    "sg:classifiers":[
        {
            "category":"Food & Beverages",
            "subcategory":"Groceries & Convenience Stores",
            "type":"Retail Goods"
        }
    ],
    "sg:phone":"+39 030 919 6074",
    "sg:postcode":"25019",
    "sg:province":"Brescia",
    "sg:tags":[
        "product",
        "related"
    ],
    "wof:name":"Garda Pesca Di Broglia Umberto & C. S.n.c.",
    "wof:placetype":"venue"
},
  "geometry": {"coordinates":[10.2229576111,45.5398292542],"type":"Point"}
}