{
  "type": "Feature",
  "properties": {
    "addr:full":"Ple Cappella Moreri , 1/3 10060 Bricherasio Bricherasio Torino 10060",
    "addr:housenumber":"1 / 3",
    "addr:postcode":"10060;10060",
    "addr:street":"Ple;Moreri",
    "iso:country":"IT",
    "sg:address":"Ple Cappella Moreri , 1/3 10060 Bricherasio",
    "sg:city":"Bricherasio",
    "sg:classifiers":[
        {
            "category":"Autos & Motor Vehicles",
            "subcategory":"Fuel & Gas Station",
            "type":"Retail Goods"
        }
    ],
    "sg:phone":"+39 0121 598872",
    "sg:postcode":"10060",
    "sg:province":"Torino",
    "sg:tags":[
        "machine",
        "injection",
        "moulding",
        "elastomer",
        "thermoplastic"
    ],
    "wof:name":"Sicav Sas Di Militerni E C",
    "wof:placetype":"venue"
},
  "geometry": {"coordinates":[7.686619,45.07056],"type":"Point"}
}