{
  "type": "Feature",
  "properties": {
    "iso:country":"IT",
    "sg:address":"60127 Ancona",
    "sg:city":"Ancona",
    "sg:orig_category":"Biancheria Intima Ed Abbigliamento Intimo - Produzione E Ingrosso",
    "sg:phone":"+39 071 897606",
    "sg:postcode":"60127",
    "sg:province":"Ancona",
    "wof:name":"Milotex Srl",
    "wof:placetype":"venue"
},
  "geometry": {"coordinates":[13.500317,43.590004],"type":"Point"}
}