{
  "type": "Feature",
  "properties": {
    "addr:full":"4, Via Dei Laghi 61030 Saltara Saltara Pesaro E Urbino 61030",
    "addr:postcode":"61030;61030",
    "addr:street":"Via Dei Laghi",
    "iso:country":"IT",
    "sg:address":"4, Via Dei Laghi 61030 Saltara",
    "sg:city":"Saltara",
    "sg:classifiers":[
        {
            "category":"Shopping",
            "subcategory":"Stationery & Office Supplies",
            "type":"Retail Goods"
        }
    ],
    "sg:phone":"+39 0721 894217",
    "sg:postcode":"61030",
    "sg:province":"Pesaro E Urbino",
    "sg:tags":[
        "professional"
    ],
    "wof:name":"Panicali Srl",
    "wof:placetype":"venue"
},
  "geometry": {"coordinates":[12.5298032761,43.633556366],"type":"Point"}
}