{
  "type": "Feature",
  "properties": {
    "iso:country":"IT",
    "sg:address":"00041 Albano Laziale",
    "sg:city":"Albano Laziale",
    "sg:orig_category":"Ospedali E Servizi Sanitari",
    "sg:phone":"+39 06 932 4661",
    "sg:postcode":"00041",
    "sg:province":"Roma",
    "wof:name":"Ospedale Regina Apostolorum",
    "wof:placetype":"venue"
},
  "geometry": {"coordinates":[12.663136,41.730637],"type":"Point"}
}