{
  "type": "Feature",
  "properties": {
    "iso:country":"IT",
    "sg:address":"20060 Cassina De'pecchi",
    "sg:orig_category":"Articoli Medico-sanitari Ed Ortopedici. Impianti, Attrezzature E Forniture Sanitarie Ed Ospedaliere",
    "sg:phone":"+39 02 952581",
    "sg:postcode":"20060",
    "sg:province":"Milano",
    "wof:name":"Technogenetics S.r.l.",
    "wof:placetype":"venue"
},
  "geometry": {"coordinates":[9.365531,45.519764],"type":"Point"}
}