{
  "type": "Feature",
  "properties": {
    "iso:country":"IT",
    "sg:address":"Via Ettore Ara 1 13100 Vercelli",
    "sg:city":"Vercelli",
    "sg:classifiers":[
        {
            "category":"Shopping",
            "subcategory":"Clothing, Apparel, & Fashions",
            "type":"Retail Goods"
        }
    ],
    "sg:phone":"+39 0161 227211",
    "sg:postcode":"13100",
    "sg:province":"Vercelli",
    "sg:tags":[
        "clothing",
        "fabric"
    ],
    "sg:website":"www.tmieurope.it",
    "wof:name":"T.m.i. Europe S.p.a.",
    "wof:placetype":"venue"
},
  "geometry": {"coordinates":[8.405355,45.301765],"type":"Point"}
}