{
  "type": "Feature",
  "properties": {
    "iso:country":"IT",
    "sg:address":"6, Via Uruguay 35127 Padova",
    "sg:city":"Padova",
    "sg:classifiers":[
        {
            "category":"Manufacturing",
            "subcategory":"Glass & Minerals",
            "type":"Manufacturing & Wholesale Goods"
        }
    ],
    "sg:phone":"+39 39800310099",
    "sg:postcode":"35127",
    "sg:province":"Padova",
    "wof:name":"Optilens Italia Srl",
    "wof:placetype":"venue"
},
  "geometry": {"coordinates":[11.844167,45.397499],"type":"Point"}
}