{
  "type": "Feature",
  "properties": {
    "iso:country":"IT",
    "sg:address":"Piazza Repubblica 4; Novi Ligure; 15067",
    "sg:city":"Novi Ligure",
    "sg:classifiers":[
        {
            "category":"Banks & Credit Unions",
            "subcategory":"Bank",
            "type":"Services"
        }
    ],
    "sg:phone":"+39 0143 7701",
    "sg:postcode":"15067",
    "sg:province":"Alessandria",
    "wof:name":"Istituto Bancario, San Paolo Di Torino Spa",
    "wof:placetype":"venue"
},
  "geometry": {"coordinates":[8.785678,44.762192],"type":"Point"}
}