{
  "type": "Feature",
  "properties": {
    "iso:country":"IT",
    "sg:address":"Piazzale Del Lavoro 29 21044 Cavaria Con Premezzo",
    "sg:city":"Cavaria con Premezzo",
    "sg:classifiers":[
        {
            "category":"Manufacturing",
            "subcategory":"Printing",
            "type":"Manufacturing & Wholesale Goods"
        }
    ],
    "sg:phone":"+39 0331 218717",
    "sg:postcode":"21044",
    "sg:province":"Varese",
    "sg:tags":[
        "machine",
        "transfer",
        "fabric"
    ],
    "sg:website":"www.ets-group.it",
    "wof:name":"Ets Engineering Transfer System S.r.l.",
    "wof:placetype":"venue"
},
  "geometry": {"coordinates":[8.806344986,45.6865501404],"type":"Point"}
}