{
  "type": "Feature",
  "properties": {
    "iso:country":"IT",
    "sg:address":"10098 Rivoli",
    "sg:city":"Rivoli",
    "sg:orig_category":"Acquari Ornamentali Ed Accessori",
    "sg:phone":"+39 011 958 0858",
    "sg:postcode":"10098",
    "sg:province":"Torino",
    "wof:name":"Zoomania",
    "wof:placetype":"venue"
},
  "geometry": {"coordinates":[7.120077,45.126019],"type":"Point"}
}