{
  "type": "Feature",
  "properties": {
    "iso:country":"IT",
    "sg:address":"84131 Salerno",
    "sg:city":"Salerno",
    "sg:orig_category":"Arredamenti E Mobili Professionali. Complementi Di Arredamento",
    "sg:phone":"+39 089 303010",
    "sg:postcode":"84131",
    "sg:province":"Salerno",
    "sg:website":"http://www.giannattasiosistemiecampane.it",
    "wof:name":"Giannattasio Giuseppe",
    "wof:placetype":"venue"
},
  "geometry": {"coordinates":[14.850812,40.642475],"type":"Point"}
}