{
  "type": "Feature",
  "properties": {
    "iso:country":"IT",
    "sg:address":"67068 Scurcola Marsicana",
    "sg:orig_category":"Onoranze E Pompe Funebri",
    "sg:phone":"+39 0863 561089",
    "sg:postcode":"67068",
    "sg:province":"L'Aquila",
    "wof:name":"Falcone Di Proietti Massimiliano",
    "wof:placetype":"venue"
},
  "geometry": {"coordinates":[13.400043,42.350849],"type":"Point"}
}