{
  "type": "Feature",
  "properties": {
    "addr:full":"S. Lucia, 62010 Pollenza Pollenza Macerata 62010",
    "addr:postcode":"62010;62010",
    "iso:country":"IT",
    "sg:address":"S. Lucia, 62010 Pollenza",
    "sg:city":"Pollenza",
    "sg:classifiers":[
        {
            "category":"Shopping",
            "subcategory":"Event Tickets",
            "type":"Retail Goods"
        }
    ],
    "sg:phone":"+39 0733 203655",
    "sg:postcode":"62010",
    "sg:province":"Macerata",
    "sg:tags":[
        "billfold"
    ],
    "sg:website":"www.stephennewline.it",
    "wof:name":"Stephen New Line Srl",
    "wof:placetype":"venue"
},
  "geometry": {"coordinates":[13.364151,43.243484],"type":"Point"}
}