{
  "type": "Feature",
  "properties": {
    "iso:country":"IT",
    "sg:address":"36071 Arzignano",
    "sg:city":"Arzignano",
    "sg:orig_category":"Articoli Da Regalo. Tempo Libero - Articoli E Forniture. Regalistica Aziendale",
    "sg:phone":"+39 0444 674333",
    "sg:postcode":"36071",
    "sg:province":"Vicenza",
    "wof:name":"Centro Cliche's Di Gobbo Giuseppe & C. Snc",
    "wof:placetype":"venue"
},
  "geometry": {"coordinates":[11.522244,45.594025],"type":"Point"}
}