{
  "type": "Feature",
  "properties": {
    "addr:full":"20136 Milano Milano Milano 20136",
    "addr:postcode":"20136;20136",
    "iso:country":"IT",
    "sg:address":"20136 Milano",
    "sg:city":"Milano",
    "sg:orig_category":"Calzature, Pelletterie E Pelli. Servizi E Lavori Per Abbigliamento E Pelletterie",
    "sg:phone":"+39 02 8940 3416",
    "sg:postcode":"20136",
    "sg:province":"Milano",
    "wof:name":"Longhitano Alfio",
    "wof:placetype":"venue"
},
  "geometry": {"coordinates":[9.180321,45.446384],"type":"Point"}
}