{
  "type": "Feature",
  "properties": {
    "iso:country":"IT",
    "sg:address":"93017 San Cataldo",
    "sg:city":"San Cataldo",
    "sg:orig_category":"Materiali Edili",
    "sg:phone":"+39 0934 569005",
    "sg:postcode":"93017",
    "sg:province":"Caltanissetta",
    "wof:name":"Aspia Srl",
    "wof:placetype":"venue"
},
  "geometry": {"coordinates":[13.926,37.498505],"type":"Point"}
}