{
  "type": "Feature",
  "properties": {
    "addr:full":"00195 Roma Roma Roma 00195",
    "addr:postcode":"00195;00195",
    "iso:country":"IT",
    "sg:address":"00195 Roma",
    "sg:city":"Roma",
    "sg:classifiers":[
        {
            "category":"Travel",
            "subcategory":"Hotels & Motels",
            "type":"Entertainment"
        }
    ],
    "sg:phone":"+39 06 322 3100",
    "sg:postcode":"00195",
    "sg:province":"Roma",
    "sg:tags":[
        "hotels",
        "facility"
    ],
    "wof:name":"Residence Prati Srl",
    "wof:placetype":"venue"
},
  "geometry": {"coordinates":[12.467943,41.916569],"type":"Point"}
}