{
  "type": "Feature",
  "properties": {
    "iso:country":"IT",
    "sg:address":"20090 Assago",
    "sg:city":"Assago",
    "sg:orig_category":"Macchine Ed Impianti Per Edilizia E Lavori Pubblici. Macchine Utensili E Impianti",
    "sg:phone":"+39 02 4884 0350",
    "sg:postcode":"20090",
    "sg:province":"Milano",
    "wof:name":"Lampugnani Sabbiatrici S.r.l.",
    "wof:placetype":"venue"
},
  "geometry": {"coordinates":[9.118649,45.409805],"type":"Point"}
}