{
  "type": "Feature",
  "properties": {
    "iso:country":"IT",
    "sg:address":"35030 Rubano",
    "sg:city":"Rubano",
    "sg:classifiers":[
        {
            "category":"Health Services",
            "subcategory":"Health Practitioner",
            "type":"Services"
        }
    ],
    "sg:phone":"+39 049 633036",
    "sg:postcode":"35030",
    "sg:province":"Padova",
    "sg:tags":[
        "medici"
    ],
    "wof:name":"Mino Antonietta",
    "wof:placetype":"venue"
},
  "geometry": {"coordinates":[11.808296,45.42189],"type":"Point"}
}