{
  "type": "Feature",
  "properties": {
    "iso:country":"IT",
    "sg:address":"12055 Diano D'alba",
    "sg:city":"Ricca",
    "sg:orig_category":"Macchine Utensili E Impianti",
    "sg:phone":"+39 0173 612569",
    "sg:postcode":"12055",
    "sg:province":"Cuneo",
    "wof:name":"F.d.m. Snc Di Carlo Fontanone & C.",
    "wof:placetype":"venue"
},
  "geometry": {"coordinates":[8.049047,44.653957],"type":"Point"}
}