{
  "type": "Feature",
  "properties": {
    "addr:full":"60127 Ancona Ancona Ancona 60127",
    "addr:postcode":"60127;60127",
    "iso:country":"IT",
    "sg:address":"60127 Ancona",
    "sg:city":"Ancona",
    "sg:classifiers":[
        {
            "category":"Banks & Credit Unions",
            "subcategory":"Investment Brokerage",
            "type":"Services"
        }
    ],
    "sg:phone":"+39 071 82766",
    "sg:postcode":"60127",
    "sg:province":"Ancona",
    "sg:tags":[
        "vehicles",
        "auxiliary",
        "motor"
    ],
    "wof:name":"Autocarrozzeria Barbini Di Barbini Giacomo & Simone Snc",
    "wof:placetype":"venue"
},
  "geometry": {"coordinates":[13.5028762817,43.5967750549],"type":"Point"}
}