{
  "type": "Feature",
  "properties": {
    "addr:full":"31020 San Vendemiano San Vendemiano Treviso 31020",
    "addr:housenumber":"31020;vendemiano",
    "addr:postcode":"vendemiano;31020",
    "addr:street":"San",
    "iso:country":"IT",
    "sg:address":"31020 San Vendemiano",
    "sg:city":"San Vendemiano",
    "sg:classifiers":[
        {
            "category":"Home & Garden",
            "subcategory":"Home Furnishings",
            "type":"Retail Goods"
        }
    ],
    "sg:phone":"+39 0438 409411",
    "sg:postcode":"31020",
    "sg:province":"Treviso",
    "sg:tags":[
        "decorative",
        "handling",
        "furnishings",
        "storage",
        "system",
        "equipment",
        "objects"
    ],
    "sg:website":"http://www.dieffebi.com",
    "wof:name":"Dieffebi Srl",
    "wof:placetype":"venue"
},
  "geometry": {"coordinates":[12.3516597748,45.8867416382],"type":"Point"}
}