{
  "type": "Feature",
  "properties": {
    "addr:full":"00196 Roma Roma Roma 00196",
    "addr:postcode":"00196;00196",
    "iso:country":"IT",
    "sg:address":"00196 Roma",
    "sg:city":"Roma",
    "sg:orig_category":"Universita' Ed Istituti Superiori E Liberi",
    "sg:phone":"+39 06 320 3842",
    "sg:postcode":"00196",
    "sg:province":"Roma",
    "sg:website":"http://www.universitalia.net",
    "wof:name":"Universitalia Srl",
    "wof:placetype":"venue"
},
  "geometry": {"coordinates":[12.494854,41.99255],"type":"Point"}
}