{
  "type": "Feature",
  "properties": {
    "iso:country":"IT",
    "sg:address":"39040 Ora",
    "sg:city":"Naz",
    "sg:orig_category":"Cartotecnica E Servizi. Forniture Per Uffici",
    "sg:phone":"+39 0471 810992",
    "sg:postcode":"39040",
    "sg:province":"Bolzano/Bozen",
    "sg:website":"http://www.kompass-italia.it",
    "wof:name":"A. Leimgruber & Co. O.h.g.",
    "wof:placetype":"venue"
},
  "geometry": {"coordinates":[11.304829,46.348751],"type":"Point"}
}