{
  "type": "Feature",
  "properties": {
    "addr:full":"20090 Segrate Segrate Milano 20090",
    "addr:postcode":"20090;20090",
    "iso:country":"IT",
    "sg:address":"20090 Segrate",
    "sg:city":"Segrate",
    "sg:orig_category":"Sport - Articoli E Forniture",
    "sg:phone":"+39 02 213 7715",
    "sg:postcode":"20090",
    "sg:province":"Milano",
    "wof:name":"Vigano' Claudio",
    "wof:placetype":"venue"
},
  "geometry": {"coordinates":[9.285477,45.51561],"type":"Point"}
}