{
  "type": "Feature",
  "properties": {
    "iso:country":"IT",
    "sg:address":"8, Via Pioppo 41012 Carpi",
    "sg:city":"Carpi",
    "sg:classifiers":[
        {
            "category":"Shopping",
            "subcategory":"Clothing, Apparel, & Fashions",
            "type":"Retail Goods"
        }
    ],
    "sg:phone":"+39 39059652323",
    "sg:postcode":"41012",
    "sg:province":"Modena",
    "sg:tags":[
        "clothes"
    ],
    "wof:name":"Donna Collection Srl",
    "wof:placetype":"venue"
},
  "geometry": {"coordinates":[10.915253,44.808758],"type":"Point"}
}