{
  "type": "Feature",
  "properties": {
    "iso:country":"IT",
    "sg:address":"50018 Badia A Settimo",
    "sg:city":"Badia a settimo",
    "sg:orig_category":"Agenzie D'affari E Servizi Commerciali",
    "sg:phone":"+39 055 731 0567",
    "sg:postcode":"50018",
    "sg:province":"Firenze",
    "wof:name":"Intersystem Srl",
    "wof:placetype":"venue"
},
  "geometry": {"coordinates":[11.145966,43.77594],"type":"Point"}
}