{
  "type": "Feature",
  "properties": {
    "iso:country":"IT",
    "sg:address":"Viale Parini; Trestina",
    "sg:classifiers":[
        {
            "category":"Banks & Credit Unions",
            "subcategory":"Bank",
            "type":"Services"
        }
    ],
    "sg:phone":"+39 075 854127",
    "wof:name":"Cassa Di Risparmio, Di Citta Di Castello Spa",
    "wof:placetype":"venue"
},
  "geometry": {"coordinates":[12.237233,43.365635],"type":"Point"}
}