{
  "type": "Feature",
  "properties": {
    "addr:full":"20090 Segrate Segrate Milano 20090",
    "addr:postcode":"20090;20090",
    "iso:country":"IT",
    "sg:address":"20090 Segrate",
    "sg:city":"Segrate",
    "sg:orig_category":"Forniture Per Uffici. Servizi Vari Di Interesse Pubblico",
    "sg:phone":"+39 02 213 5795",
    "sg:postcode":"20090",
    "sg:province":"Milano",
    "wof:name":"Jackpot",
    "wof:placetype":"venue"
},
  "geometry": {"coordinates":[9.2704696655,45.4825210571],"type":"Point"}
}