{
  "type": "Feature",
  "properties": {
    "iso:country":"IT",
    "sg:address":"10098 Rivoli",
    "sg:city":"Rivoli",
    "sg:orig_category":"Studi E Consulenze Amministrative, Commerciali E Aziendali. Consulenze Tecniche, Amministrative E Perizie. Professionisti - Studi E Servizi Ed Associazioni Di Interesse Aziendale",
    "sg:phone":"+39 011 958 6705",
    "sg:postcode":"10098",
    "sg:province":"Torino",
    "wof:name":"Olocco Andrea",
    "wof:placetype":"venue"
},
  "geometry": {"coordinates":[7.519159,45.067104],"type":"Point"}
}