{
  "type": "Feature",
  "properties": {
    "iso:country":"IT",
    "sg:address":"56126 Pisa",
    "sg:city":"Pisa",
    "sg:orig_category":"Agenzie Ed Enti Turistici. Acqua, Luce, Gas E Societa' Di Esercizio Pubblico",
    "sg:phone":"+39 050 830253",
    "sg:postcode":"56126",
    "sg:province":"Pisa",
    "sg:website":"http://www.pisae.com",
    "wof:name":"Consorzio Turistico Dell'area Pisana",
    "wof:placetype":"venue"
},
  "geometry": {"coordinates":[10.356113,43.589172],"type":"Point"}
}