{
  "type": "Feature",
  "properties": {
    "iso:country":"IT",
    "sg:address":"00185 Roma",
    "sg:city":"Roma",
    "sg:orig_category":"Universita' Ed Istituti Superiori E Liberi",
    "sg:phone":"+39 06 490979",
    "sg:postcode":"00185",
    "sg:province":"Roma",
    "wof:name":"Istituto Simonelli Di La Monica Luigi",
    "wof:placetype":"venue"
},
  "geometry": {"coordinates":[12.511382,41.900963],"type":"Point"}
}