{
  "type": "Feature",
  "properties": {
    "addr:full":"Via Industriale Traversa Prima 2 25060 Cellatica Cellatica Brescia 25060",
    "addr:housenumber":"2",
    "addr:postcode":"25060;25060",
    "addr:street":"Via Industriale Traversa Prima",
    "iso:country":"IT",
    "sg:address":"Via Industriale Traversa Prima 2 25060 Cellatica",
    "sg:city":"Cellatica",
    "sg:classifiers":[
        {
            "category":"Banks & Credit Unions",
            "subcategory":"Investment Brokerage",
            "type":"Services"
        }
    ],
    "sg:phone":"+39 030 312300",
    "sg:postcode":"25060",
    "sg:province":"Brescia",
    "sg:tags":[
        "packaging",
        "films",
        "film",
        "laminated"
    ],
    "sg:website":"www.faitplast.com",
    "wof:name":"Fait Plast S.p.a",
    "wof:placetype":"venue"
},
  "geometry": {"coordinates":[10.168255806,45.5590171814],"type":"Point"}
}