{
  "type": "Feature",
  "properties": {
    "addr:full":"Via Medici Del Vascello 20 10040 Druento Druento Torino 10040",
    "addr:housenumber":"20",
    "addr:postcode":"10040;10040",
    "addr:street":"Via Medici Del Vascello",
    "iso:country":"IT",
    "sg:address":"Via Medici Del Vascello 20 10040 Druento",
    "sg:city":"Druento",
    "sg:classifiers":[
        {
            "category":"Shopping",
            "subcategory":"Computers & Home Electronics",
            "type":"Retail Goods"
        }
    ],
    "sg:phone":"+39 011 994 4111",
    "sg:postcode":"10040",
    "sg:province":"Torino",
    "sg:tags":[
        "tube",
        "manipulation"
    ],
    "sg:website":"www.bstubi.com",
    "wof:name":"B.s. Spa",
    "wof:placetype":"venue"
},
  "geometry": {"coordinates":[7.631052,45.131958],"type":"Point"}
}