{
  "type": "Feature",
  "properties": {
    "iso:country":"IT",
    "sg:address":"28100 Novara",
    "sg:city":"Novara",
    "sg:orig_category":"Servizi Vari Di Interesse Pubblico",
    "sg:phone":"+39 0321 391187",
    "sg:postcode":"28100",
    "sg:province":"Novara",
    "wof:name":"Giocabimbi S.n.c. Di Minigozzi Sara E Binotti Patrizia",
    "wof:placetype":"venue"
},
  "geometry": {"coordinates":[8.609694,45.446812],"type":"Point"}
}