{
  "type": "Feature",
  "properties": {
    "iso:country":"IT",
    "sg:address":"18, Via Dell' Agricoltura 00065 Fiano Romano",
    "sg:city":"Fiano Romano",
    "sg:classifiers":[
        {
            "category":"Shopping",
            "subcategory":"Crafts & Fabrics",
            "type":"Retail Goods"
        }
    ],
    "sg:phone":"+39 390 765 4081",
    "sg:postcode":"00065",
    "sg:province":"Roma",
    "wof:name":"Set Soc.europa Tessile Spa",
    "wof:placetype":"venue"
},
  "geometry": {"coordinates":[12.5850610733,42.1354293823],"type":"Point"}
}