{
  "type": "Feature",
  "properties": {
    "iso:country":"IT",
    "sg:address":"35020 Codevigo",
    "sg:city":"Codevigo",
    "sg:orig_category":"Prodotti E Manufatti In Gomma. Servizi E Lavori Industria Della Gomma. Ricambi E Componenti Dei Mezzi Di Trasporto. Riparazione Dei Mezzi Di Trasporto",
    "sg:phone":"+39 049 970 5524",
    "sg:postcode":"35020",
    "sg:province":"Padova",
    "wof:name":"Autofficina Gf Car Di Ferrara Gianfranco",
    "wof:placetype":"venue"
},
  "geometry": {"coordinates":[12.0997037888,45.267665863],"type":"Point"}
}