{
  "type": "Feature",
  "properties": {
    "iso:country":"IT",
    "sg:address":"45, Via Dei Giovi 00141 Roma",
    "sg:city":"Roma",
    "sg:classifiers":[
        {
            "category":"Utilities",
            "subcategory":"Telephone",
            "type":"Services"
        }
    ],
    "sg:phone":"+39 39068174550",
    "sg:postcode":"00141",
    "sg:province":"Roma",
    "sg:tags":[
        "telecommunication"
    ],
    "wof:name":"Sotel Srl",
    "wof:placetype":"venue"
},
  "geometry": {"coordinates":[12.534695,41.942726],"type":"Point"}
}