{
  "type": "Feature",
  "properties": {
    "iso:country":"IT",
    "sg:address":"00136 Roma",
    "sg:city":"Roma",
    "sg:orig_category":"Cinematografia E Radiotelevisione",
    "sg:phone":"+39 06 3540 3621",
    "sg:postcode":"00136",
    "sg:province":"Roma",
    "wof:name":"Multimedia Network Srl",
    "wof:placetype":"venue"
},
  "geometry": {"coordinates":[12.446886,41.927017],"type":"Point"}
}