{
  "type": "Feature",
  "properties": {
    "iso:country":"IT",
    "sg:address":"7, Via Venezia Giulia 20157 Milano",
    "sg:city":"Milano",
    "sg:classifiers":[
        {
            "category":"Professional",
            "subcategory":"Engineering",
            "type":"Services"
        }
    ],
    "sg:phone":"+39 39023909181",
    "sg:postcode":"20157",
    "sg:province":"Milano",
    "sg:tags":[
        "machine",
        "-",
        "mechanical"
    ],
    "wof:name":"Ocmi S.p.a.",
    "wof:placetype":"venue"
},
  "geometry": {"coordinates":[9.279292,45.485474],"type":"Point"}
}