{
  "type": "Feature",
  "properties": {
    "addr:full":"24021 Albino Albino Bergamo 24021",
    "addr:postcode":"24021;24021",
    "iso:country":"IT",
    "sg:address":"24021 Albino",
    "sg:city":"Albino",
    "sg:orig_category":"Forniture Per Abbigliamento E Pelletterie. Complementi Di Arredamento",
    "sg:phone":"+39 035 752012",
    "sg:postcode":"24021",
    "sg:province":"Bergamo",
    "wof:name":"Tonin Domenico",
    "wof:placetype":"venue"
},
  "geometry": {"coordinates":[9.7316246033,45.7368431091],"type":"Point"}
}