{
  "type": "Feature",
  "properties": {
    "addr:full":"Via Roma 19; Mozzecane; 37060 Mozzecane Verona 37060",
    "addr:housenumber":"19",
    "addr:postcode":"37060;37060",
    "addr:street":"Via Roma",
    "iso:country":"IT",
    "sg:address":"Via Roma 19; Mozzecane; 37060",
    "sg:city":"Mozzecane",
    "sg:classifiers":[
        {
            "category":"Banks & Credit Unions",
            "subcategory":"Bank",
            "type":"Services"
        }
    ],
    "sg:phone":"+39 045 634 0300",
    "sg:postcode":"37060",
    "sg:province":"Verona",
    "wof:name":"Cariverona Banca Spa",
    "wof:placetype":"venue"
},
  "geometry": {"coordinates":[10.812549,45.302559],"type":"Point"}
}