{
  "type": "Feature",
  "properties": {
    "addr:full":"Km. 1.500, Strada Statale 5 Bis Loc Vasche Di Pianola 67100 L'aquila L'Aquila 67100",
    "addr:housenumber":"5 bis",
    "addr:postcode":"67100;67100",
    "addr:street":"Km. 1.500 Strada Statale",
    "iso:country":"IT",
    "sg:address":"Km. 1.500, Strada Statale 5 Bis Loc Vasche Di Pianola 67100 L'aquila",
    "sg:classifiers":[
        {
            "category":"Autos & Motor Vehicles",
            "subcategory":"Automobile Sales",
            "type":"Retail Goods"
        }
    ],
    "sg:phone":"+39 39086262831",
    "sg:postcode":"67100",
    "sg:province":"L'Aquila",
    "sg:tags":[
        "industrial"
    ],
    "wof:name":"Centrogas",
    "wof:placetype":"venue"
},
  "geometry": {"coordinates":[13.389962,42.354004],"type":"Point"}
}