{
  "type": "Feature",
  "properties": {
    "addr:full":"28047 Oleggio Oleggio Novara 28047",
    "addr:postcode":"28047;28047",
    "iso:country":"IT",
    "sg:address":"28047 Oleggio",
    "sg:city":"Oleggio",
    "sg:orig_category":"Agenzie D'affari E Servizi Commerciali. Servizi Per Aziende, Manifestazioni E Supporto Agli Scambi Commerciali",
    "sg:phone":"+39 0321 93040",
    "sg:postcode":"28047",
    "sg:province":"Novara",
    "wof:name":"Studio E.d. Sas",
    "wof:placetype":"venue"
},
  "geometry": {"coordinates":[8.637972,45.599876],"type":"Point"}
}