{
  "type": "Feature",
  "properties": {
    "addr:full":"16153 Genova Genova Genova 16153",
    "addr:housenumber":"16153",
    "addr:postcode":"16153",
    "iso:country":"IT",
    "sg:address":"16153 Genova",
    "sg:city":"Genova",
    "sg:orig_category":"Articoli Medico-sanitari Ed Ortopedici",
    "sg:phone":"+39 010 604 0640",
    "sg:postcode":"16153",
    "sg:province":"Genova",
    "wof:name":"Gain Sonic Hearing Snc Di Cadenasso L. & C.",
    "wof:placetype":"venue"
},
  "geometry": {"coordinates":[8.854483,44.425083],"type":"Point"}
}