{
  "type": "Feature",
  "properties": {
    "iso:country":"IT",
    "sg:address":"00185 Roma",
    "sg:city":"Roma",
    "sg:orig_category":"Cinematografia E Radiotelevisione. Cine-foto-ottica",
    "sg:phone":"+39 06 445 6836",
    "sg:postcode":"00185",
    "sg:province":"Roma",
    "wof:name":"Bene Carmela",
    "wof:placetype":"venue"
},
  "geometry": {"coordinates":[12.441454,41.861263],"type":"Point"}
}