{
  "type": "Feature",
  "properties": {
    "iso:country":"IT",
    "sg:address":"95121 Catania",
    "sg:city":"Catania",
    "sg:orig_category":"Petroli, Gas E Combustibili",
    "sg:phone":"+39 095 340288",
    "sg:postcode":"95121",
    "sg:province":"Catania",
    "wof:name":"Salva' Birbante Carmela",
    "wof:placetype":"venue"
},
  "geometry": {"coordinates":[15.0814247131,37.493144989],"type":"Point"}
}