{
  "type": "Feature",
  "properties": {
    "iso:country":"IT",
    "sg:address":"Via Decima Strada 1/d 36071 Arzignano",
    "sg:city":"Arzignano",
    "sg:classifiers":[
        {
            "category":"Banks & Credit Unions",
            "subcategory":"Investment Brokerage",
            "type":"Services"
        }
    ],
    "sg:phone":"+39 0444 673640",
    "sg:postcode":"36071",
    "sg:province":"Vicenza",
    "sg:tags":[
        "axial-flow",
        "pump"
    ],
    "wof:name":"S.m.i.e. Pompe Srl",
    "wof:placetype":"venue"
},
  "geometry": {"coordinates":[11.540307,45.545906],"type":"Point"}
}