{
  "type": "Feature",
  "properties": {
    "iso:country":"IT",
    "sg:address":"93, Via Trifogli 36010 Zane'",
    "sg:classifiers":[
        {
            "category":"Utilities",
            "subcategory":"Electric",
            "type":"Services"
        }
    ],
    "sg:phone":"+39 0445 314180",
    "sg:postcode":"36010",
    "sg:province":"Vicenza",
    "sg:tags":[
        "component",
        "electronic"
    ],
    "wof:name":"Filp - Fabbrica Isolanti E Laminati (s.p.a.)",
    "wof:placetype":"venue"
},
  "geometry": {"coordinates":[11.43551,45.71796],"type":"Point"}
}