{
  "type": "Feature",
  "properties": {
    "iso:country":"IT",
    "sg:address":"87073 Oriolo",
    "sg:city":"Oriolo",
    "sg:orig_category":"Materiali E Componenti Elettrotecnici",
    "sg:phone":"+39 0981 930036",
    "sg:postcode":"87073",
    "sg:province":"Cosenza",
    "wof:name":"Di Leo Pasquale",
    "wof:placetype":"venue"
},
  "geometry": {"coordinates":[16.447817,40.053532],"type":"Point"}
}