{
  "type": "Feature",
  "properties": {
    "addr:full":"Via Molinazzo 21 16044 Cicagna Cicagna Genova 16044",
    "addr:housenumber":"21",
    "addr:postcode":"16044;16044",
    "addr:street":"Via Molinazzo",
    "iso:country":"IT",
    "sg:address":"Via Molinazzo 21 16044 Cicagna",
    "sg:city":"Cicagna",
    "sg:classifiers":[
        {
            "category":"Home & Garden",
            "subcategory":"Carpets & Floor Coverings",
            "type":"Retail Goods"
        }
    ],
    "sg:phone":"+39 0185 929983",
    "sg:postcode":"16044",
    "sg:province":"Genova",
    "sg:tags":[
        "slate",
        "flooring"
    ],
    "sg:website":"www.ac-ardesia.com",
    "wof:name":"Cuneo Angiolino & C.",
    "wof:placetype":"venue"
},
  "geometry": {"coordinates":[9.242629,44.402233],"type":"Point"}
}