{
  "type": "Feature",
  "properties": {
    "iso:country":"IT",
    "sg:address":"00048 Nettuno",
    "sg:city":"Nettuno",
    "sg:orig_category":"Servizi Per Lo Sport E Il Tempo Libero. Servizi Ausiliari Dei Mezzi Di Trasporto",
    "sg:phone":"+39 06 988 8346",
    "sg:postcode":"00048",
    "sg:province":"Roma",
    "wof:name":"Veritiero Gianfranco",
    "wof:placetype":"venue"
},
  "geometry": {"coordinates":[12.60807,42.052834],"type":"Point"}
}