{
  "type": "Feature",
  "properties": {
    "iso:country":"IT",
    "sg:address":"18012 Bordighera",
    "sg:city":"Bordighera",
    "sg:orig_category":"Macchine, Impianti Ed Attrezzature Per Agricoltura E Zootecnia",
    "sg:phone":"+39 0184 253501",
    "sg:postcode":"18012",
    "sg:province":"Imperia",
    "wof:name":"Cocchi Di Cocchi Dante & C. Snc",
    "wof:placetype":"venue"
},
  "geometry": {"coordinates":[7.659552,43.793728],"type":"Point"}
}