{
  "type": "Feature",
  "properties": {
    "addr:full":"10051 Avigliana Avigliana Torino 10051",
    "addr:postcode":"10051;10051",
    "iso:country":"IT",
    "sg:address":"10051 Avigliana",
    "sg:city":"Avigliana",
    "sg:orig_category":"Gelati - Produzione E Commercio",
    "sg:phone":"+39 011 936 7615",
    "sg:postcode":"10051",
    "sg:province":"Torino",
    "wof:name":"D.a.d.o. Srl",
    "wof:placetype":"venue"
},
  "geometry": {"coordinates":[7.393842,45.088768],"type":"Point"}
}