{
  "type": "Feature",
  "properties": {
    "addr:full":"51039 Quarrata Quarrata Pistoia 51039",
    "addr:postcode":"51039;51039",
    "iso:country":"IT",
    "sg:address":"51039 Quarrata",
    "sg:city":"Quarrata",
    "sg:orig_category":"Prodotti E Manufatti In Materie Plastiche",
    "sg:phone":"+39 0573 743071",
    "sg:postcode":"51039",
    "sg:province":"Pistoia",
    "wof:name":"Forme Di Fiammerighi M.",
    "wof:placetype":"venue"
},
  "geometry": {"coordinates":[10.9727325439,43.8815078735],"type":"Point"}
}