{
  "type": "Feature",
  "properties": {
    "addr:full":"30, Via Santa Caterina 20010 Arluno Arluno Milano 20010",
    "addr:postcode":"20010;20010",
    "addr:street":"Via Santa Caterina",
    "iso:country":"IT",
    "sg:address":"30, Via Santa Caterina 20010 Arluno",
    "sg:city":"Arluno",
    "sg:classifiers":[
        {
            "category":"Shopping",
            "subcategory":"Crafts & Fabrics",
            "type":"Retail Goods"
        }
    ],
    "sg:phone":"+39 39029017278",
    "sg:postcode":"20010",
    "sg:province":"Milano",
    "wof:name":"Chiaramonte Lane S.r.l.",
    "wof:placetype":"venue"
},
  "geometry": {"coordinates":[9.1881408691,45.4636878967],"type":"Point"}
}