{
  "type": "Feature",
  "properties": {
    "addr:full":"Via Giovanbattista Tiepolo 44020 Ostellato Ostellato Ferrara 44020",
    "addr:postcode":"44020;44020",
    "addr:street":"Via Giovanbattista Tiepolo",
    "iso:country":"IT",
    "sg:address":"Via Giovanbattista Tiepolo 44020 Ostellato",
    "sg:city":"Ostellato",
    "sg:classifiers":[
        {
            "category":"Food & Beverages",
            "subcategory":"Groceries & Convenience Stores",
            "type":"Retail Goods"
        }
    ],
    "sg:phone":"+39 39053357254",
    "sg:postcode":"44020",
    "sg:province":"Ferrara",
    "sg:tags":[
        "product",
        "related"
    ],
    "wof:name":"Nuova Marinalco (s.p.a.)",
    "wof:placetype":"venue"
},
  "geometry": {"coordinates":[11.6204395294,44.8378944397],"type":"Point"}
}