{
  "type": "Feature",
  "properties": {
    "addr:full":"19, Via Costituzione 42015 Correggio Reggio Nell'Emilia 42015",
    "addr:postcode":"42015;42015",
    "addr:street":"Via Costituzione",
    "iso:country":"IT",
    "sg:address":"19, Via Costituzione 42015 Correggio",
    "sg:classifiers":[
        {
            "category":"Shopping",
            "subcategory":"Clothing, Apparel, & Fashions",
            "type":"Retail Goods"
        }
    ],
    "sg:phone":"+39 0522 740011",
    "sg:postcode":"42015",
    "sg:province":"Reggio Nell'Emilia",
    "sg:tags":[
        "clothes"
    ],
    "wof:name":"Marex (s.r.l.)",
    "wof:placetype":"venue"
},
  "geometry": {"coordinates":[10.824916,44.772419],"type":"Point"}
}