{
  "type": "Feature",
  "properties": {
    "addr:full":"66/a, Via Milano 25064 Gussago Gussago Brescia 25064",
    "addr:housenumber":"66 / a",
    "addr:postcode":"25064;25064",
    "iso:country":"IT",
    "sg:address":"66/a, Via Milano 25064 Gussago",
    "sg:city":"Gussago",
    "sg:classifiers":[
        {
            "category":"Manufacturing",
            "subcategory":"Rubber & Plastics",
            "type":"Manufacturing & Wholesale Goods"
        }
    ],
    "sg:phone":"+39 030 241 0444",
    "sg:postcode":"25064",
    "sg:province":"Brescia",
    "wof:name":"Vinilgomma (s.r.l.)",
    "wof:placetype":"venue"
},
  "geometry": {"coordinates":[10.1426782608,45.5494422913],"type":"Point"}
}