{
  "type": "Feature",
  "properties": {
    "addr:full":"35010 Capriccio Padova 35010",
    "addr:postcode":"35010;35010",
    "iso:country":"IT",
    "sg:address":"35010 Capriccio",
    "sg:orig_category":"Articoli Da Regalo. Tempo Libero - Articoli E Forniture. Regalistica Aziendale",
    "sg:phone":"+39 049 503416",
    "sg:postcode":"35010",
    "sg:province":"Padova",
    "wof:name":"Bovo Vinicio",
    "wof:placetype":"venue"
},
  "geometry": {"coordinates":[11.992533,45.416218],"type":"Point"}
}