{
  "type": "Feature",
  "properties": {
    "iso:country":"IT",
    "sg:address":"131, Via Bollitora Interna 41012 Carpi",
    "sg:city":"Carpi",
    "sg:classifiers":[
        {
            "category":"Shopping",
            "subcategory":"Clothing, Apparel, & Fashions",
            "type":"Retail Goods"
        }
    ],
    "sg:phone":"+39 39059697232",
    "sg:postcode":"41012",
    "sg:province":"Modena",
    "sg:tags":[
        "clothes"
    ],
    "wof:name":"Fga Maglierie (s.r.l.)",
    "wof:placetype":"venue"
},
  "geometry": {"coordinates":[10.862018,44.762531],"type":"Point"}
}