{
  "type": "Feature",
  "properties": {
    "iso:country":"IT",
    "sg:address":"90039 Villabate",
    "sg:city":"Villabate",
    "sg:orig_category":"Forniture Per Agricoltura E Zootecnia. Prodotti Chimici Secondari. Macchine E Forniture Per Ecologia E Smaltimento Rifiuti",
    "sg:phone":"+39 091 614 2089",
    "sg:postcode":"90039",
    "sg:province":"Palermo",
    "wof:name":"Agri Edil Di Caracausi F.sco",
    "wof:placetype":"venue"
},
  "geometry": {"coordinates":[13.4455499649,38.0754585266],"type":"Point"}
}