{
  "type": "Feature",
  "properties": {
    "iso:country":"IT",
    "sg:address":"18, Calata Ospedaletto 80133 Napoli",
    "sg:city":"Napoli",
    "sg:classifiers":[
        {
            "category":"Communications",
            "subcategory":"Newspaper",
            "type":"Services"
        }
    ],
    "sg:phone":"+39 081 552 4525",
    "sg:postcode":"80133",
    "sg:province":"Napoli",
    "sg:tags":[
        "advertising"
    ],
    "wof:name":"Ennestudio Srl",
    "wof:placetype":"venue"
},
  "geometry": {"coordinates":[14.252831,40.842922],"type":"Point"}
}