{
  "type": "Feature",
  "properties": {
    "iso:country":"IT",
    "sg:address":"33048 San Giovanni Al Natisone",
    "sg:city":"San Giovanni al Natisone",
    "sg:orig_category":"Minuterie Metalliche E Ferramenta",
    "sg:phone":"+39 0432 747911",
    "sg:postcode":"33048",
    "sg:province":"Udine",
    "sg:website":"http://www.friulsider.com",
    "wof:name":"Friulsider Spa",
    "wof:placetype":"venue"
},
  "geometry": {"coordinates":[13.3747816086,45.9852027893],"type":"Point"}
}