{
  "type": "Feature",
  "properties": {
    "iso:country":"IT",
    "sg:address":"00040 Pomezia",
    "sg:city":"Pomezia",
    "sg:orig_category":"Canne Fumarie, Ciminiere E Camini",
    "sg:phone":"+39 06 9162 4041",
    "sg:postcode":"00040",
    "sg:province":"Roma",
    "wof:name":"Air Tecno Di Maurizio Garofalo",
    "wof:placetype":"venue"
},
  "geometry": {"coordinates":[12.485349,41.672112],"type":"Point"}
}