{
  "type": "Feature",
  "properties": {
    "iso:country":"IT",
    "sg:address":"35010 Limena",
    "sg:city":"Limena",
    "sg:orig_category":"Materiali Edili",
    "sg:phone":"+39 049 884 8133",
    "sg:postcode":"35010",
    "sg:province":"Padova",
    "sg:website":"http://www.space.tin.it/economia/reborto",
    "wof:name":"Bemor Srl",
    "wof:placetype":"venue"
},
  "geometry": {"coordinates":[11.849442,45.461281],"type":"Point"}
}