{
  "type": "Feature",
  "properties": {
    "addr:full":"39100 Bolzano Bolzano Bolzano/Bozen 39100",
    "addr:postcode":"39100;39100",
    "iso:country":"IT",
    "sg:address":"39100 Bolzano",
    "sg:city":"Bolzano",
    "sg:orig_category":"Forniture Uffici",
    "sg:phone":"+39 0471 204680",
    "sg:postcode":"39100",
    "sg:province":"Bolzano/Bozen",
    "sg:website":"http://www.ram-tronix.com",
    "wof:name":"Ram Tronix Srl",
    "wof:placetype":"venue"
},
  "geometry": {"coordinates":[11.35800457,46.4967155457],"type":"Point"}
}