{
  "type": "Feature",
  "properties": {
    "iso:country":"IT",
    "sg:address":"24060 Telgate",
    "sg:city":"Telgate",
    "sg:orig_category":"Serramenti Ed Infissi",
    "sg:phone":"+39 035 830408",
    "sg:postcode":"24060",
    "sg:province":"Bergamo",
    "wof:name":"Seraplastic Snc Di Barcella & C.",
    "wof:placetype":"venue"
},
  "geometry": {"coordinates":[9.852834,45.629852],"type":"Point"}
}