{
  "type": "Feature",
  "properties": {
    "addr:full":"9, Via Galilei Galileo 21019 Somma Lombardo Somma Lombardo Varese 21019",
    "addr:postcode":"21019;21019",
    "addr:street":"Via Galilei Galileo",
    "iso:country":"IT",
    "sg:address":"9, Via Galilei Galileo 21019 Somma Lombardo",
    "sg:city":"Somma Lombardo",
    "sg:classifiers":[
        {
            "category":"Professional",
            "subcategory":"Engineering",
            "type":"Services"
        }
    ],
    "sg:phone":"+39 0331 256510",
    "sg:postcode":"21019",
    "sg:province":"Varese",
    "sg:tags":[
        "machine",
        "-",
        "mechanical"
    ],
    "wof:name":"Zamark S.r.l.",
    "wof:placetype":"venue"
},
  "geometry": {"coordinates":[8.826385,45.817604],"type":"Point"}
}