{
  "type": "Feature",
  "properties": {
    "addr:full":"07031 Castelsardo Castelsardo Sassari 07031",
    "addr:postcode":"07031;07031",
    "iso:country":"IT",
    "sg:address":"07031 Castelsardo",
    "sg:city":"Castelsardo",
    "sg:orig_category":"Cine-foto-ottica. Articoli Medico-sanitari Ed Ortopedici. Impianti, Attrezzature E Forniture Sanitarie Ed Ospedaliere",
    "sg:phone":"+39 079 471534",
    "sg:postcode":"07031",
    "sg:province":"Sassari",
    "wof:name":"Portas Srl",
    "wof:placetype":"venue"
},
  "geometry": {"coordinates":[8.712146,40.914253],"type":"Point"}
}