{
  "type": "Feature",
  "properties": {
    "addr:full":"Via Dante Alighieri 4 25032 Chiari Chiari Brescia 25032",
    "addr:housenumber":"4",
    "addr:postcode":"25032;25032",
    "addr:street":"Via Dante Alighieri",
    "iso:country":"IT",
    "sg:address":"Via Dante Alighieri 4 25032 Chiari",
    "sg:city":"Chiari",
    "sg:classifiers":[
        {
            "category":"Sports & Exercise",
            "subcategory":"Bicycle Rental",
            "type":"Entertainment"
        }
    ],
    "sg:phone":"+39 030 700 0851",
    "sg:postcode":"25032",
    "sg:province":"Brescia",
    "sg:tags":[
        "boot",
        "shoes",
        "leisure"
    ],
    "sg:website":"www.brasilen.it",
    "wof:name":"Calzaturificio Brasilen Srl",
    "wof:placetype":"venue"
},
  "geometry": {"coordinates":[9.944932,45.497452],"type":"Point"}
}