{
  "type": "Feature",
  "properties": {
    "addr:full":"00144 Roma Roma Roma 00144",
    "addr:postcode":"00144;00144",
    "iso:country":"IT",
    "sg:address":"00144 Roma",
    "sg:city":"Roma",
    "sg:orig_category":"Attrezzature E Forniture Per Officine Riparazione E Servizi Ausiliari",
    "sg:phone":"+39 06 529 0301",
    "sg:postcode":"00144",
    "sg:province":"Roma",
    "wof:name":"Baldoncini Mauro",
    "wof:placetype":"venue"
},
  "geometry": {"coordinates":[12.451169,41.830936],"type":"Point"}
}