{
  "type": "Feature",
  "properties": {
    "addr:full":"17, V. Marco Polo 35020 Albignasego Albignasego Padova 35020",
    "addr:housenumber":"17",
    "addr:postcode":"35020;35020",
    "addr:street":"V. Marco Polo",
    "iso:country":"IT",
    "sg:address":"17, V. Marco Polo 35020 Albignasego",
    "sg:city":"Albignasego",
    "sg:classifiers":[
        {
            "category":"Real Estate",
            "subcategory":"Surveying",
            "type":"Services"
        }
    ],
    "sg:phone":"+39 39049681093",
    "sg:postcode":"35020",
    "sg:province":"Padova",
    "sg:tags":[
        "equipment",
        "material",
        "good",
        "-",
        "handling"
    ],
    "sg:website":"http://www.perontecnici.it:ws_end: :mark:ws:http://www.paginegialle.it/perontecnici",
    "wof:name":"Perontecnici Srl",
    "wof:placetype":"venue"
},
  "geometry": {"coordinates":[11.849739,45.370411],"type":"Point"}
}