{
  "type": "Feature",
  "properties": {
    "addr:full":"30032 Fiesso D'artico Venezia 30032",
    "addr:postcode":"30032;30032",
    "iso:country":"IT",
    "sg:address":"30032 Fiesso D'artico",
    "sg:orig_category":"Manufacturers: Prefabbricati",
    "sg:phone":"+39 049 989 9111",
    "sg:postcode":"30032",
    "sg:province":"Venezia",
    "wof:name":"Metalmeccanica Fracasso Spa",
    "wof:placetype":"venue"
},
  "geometry": {"coordinates":[12.031389,45.419823],"type":"Point"}
}