{
  "type": "Feature",
  "properties": {
    "iso:country":"IT",
    "sg:address":"35125 Padova",
    "sg:city":"Padova",
    "sg:orig_category":"Servizi Ausiliari Dei Mezzi Di Trasporto",
    "sg:phone":"+39 049 880 4774",
    "sg:postcode":"35125",
    "sg:province":"Padova",
    "wof:name":"Metano Padova Sas Di Grigoletto Roberto & C.",
    "wof:placetype":"venue"
},
  "geometry": {"coordinates":[11.872622,45.369099],"type":"Point"}
}