{
  "type": "Feature",
  "properties": {
    "iso:country":"IT",
    "sg:address":"00055 Ladispoli",
    "sg:city":"Ladispoli",
    "sg:orig_category":"Materiali Semilavorati Metallici",
    "sg:phone":"+39 06 994 9431",
    "sg:postcode":"00055",
    "sg:province":"Roma",
    "wof:name":"Tecnometalli Snc Di Pompei Maria Silvia",
    "wof:placetype":"venue"
},
  "geometry": {"coordinates":[12.096443,41.970081],"type":"Point"}
}