{
  "type": "Feature",
  "properties": {
    "iso:country":"IT",
    "sg:address":"10138 Torino",
    "sg:city":"Torino",
    "sg:orig_category":"Apparecchiature E Sistemi Per Magazzinaggio E Movimentazione",
    "sg:phone":"+39 011 433 2192",
    "sg:postcode":"10138",
    "sg:province":"Torino",
    "wof:name":"Gozzelino - Pazzagli Di Pazzagli Giuseppe",
    "wof:placetype":"venue"
},
  "geometry": {"coordinates":[7.657862,45.069744],"type":"Point"}
}