{
  "type": "Feature",
  "properties": {
    "addr:full":"52028 Terranuova Bracciolini Terranuova Bracciolini Arezzo 52028",
    "addr:postcode":"52028;52028",
    "iso:country":"IT",
    "sg:address":"52028 Terranuova Bracciolini",
    "sg:city":"Terranuova Bracciolini",
    "sg:orig_category":"Autoveicoli Industriali",
    "sg:phone":"+39 055 919431",
    "sg:postcode":"52028",
    "sg:province":"Arezzo",
    "sg:website":"http://www.resti.it",
    "wof:name":"Resti Spa",
    "wof:placetype":"venue"
},
  "geometry": {"coordinates":[11.555784,43.551159],"type":"Point"}
}