{
  "type": "Feature",
  "properties": {
    "addr:full":"59013 Montemurlo Montemurlo Prato 59013",
    "addr:postcode":"59013;59013",
    "iso:country":"IT",
    "sg:address":"59013 Montemurlo",
    "sg:city":"Montemurlo",
    "sg:classifiers":[
        {
            "category":"Manufacturing",
            "subcategory":"Textiles",
            "type":"Manufacturing & Wholesale Goods"
        }
    ],
    "sg:phone":"+39 0574 651215",
    "sg:postcode":"59013",
    "sg:province":"Prato",
    "sg:tags":[
        "raw",
        "material",
        "yarn",
        "textiles"
    ],
    "wof:name":"S.d.e. Di Ascione Luigi & C. Sas",
    "wof:placetype":"venue"
},
  "geometry": {"coordinates":[11.054902,43.909931],"type":"Point"}
}