{
  "type": "Feature",
  "properties": {
    "addr:full":"65126 Pescara Pescara Pescara 65126",
    "addr:postcode":"65126;65126",
    "iso:country":"IT",
    "sg:address":"65126 Pescara",
    "sg:city":"Pescara",
    "sg:orig_category":"Servizi Culturali E Per Lo Spettacolo. Servizi Per Lo Sport E Il Tempo Libero. Associazioni Ed Organismi Di Interesse Pubblico",
    "sg:phone":"+39 085 454 9553",
    "sg:postcode":"65126",
    "sg:province":"Pescara",
    "sg:website":"http://www.forwardaics.com",
    "wof:name":"Associazione Forward (affiliata A.i.c.s.)",
    "wof:placetype":"venue"
},
  "geometry": {"coordinates":[14.22506,42.461456],"type":"Point"}
}