{
  "type": "Feature",
  "properties": {
    "iso:country":"IT",
    "sg:address":"27029 Vigevano",
    "sg:city":"Vigevano",
    "sg:orig_category":"Bagno - Accessori E Mobili",
    "sg:phone":"+39 0381 319285",
    "sg:postcode":"27029",
    "sg:province":"Pavia",
    "wof:name":"Superedil Snc",
    "wof:placetype":"venue"
},
  "geometry": {"coordinates":[9.064801,45.227512],"type":"Point"}
}