{
  "type": "Feature",
  "properties": {
    "iso:country":"IT",
    "sg:address":"30033 Noale",
    "sg:city":"Noale",
    "sg:orig_category":"Servizi E Lavori Per Edilizia E Lavori Pubblici. Consulenze Tecniche, Amministrative E Perizie",
    "sg:phone":"+39 041 580 2181",
    "sg:postcode":"30033",
    "sg:province":"Venezia",
    "sg:website":"http://www.design-and-consulting.it",
    "wof:name":"D & C - Design And Consulting Srl",
    "wof:placetype":"venue"
},
  "geometry": {"coordinates":[12.062837,45.560242],"type":"Point"}
}