{
  "type": "Feature",
  "properties": {
    "addr:full":"72021 Francavilla Fontana Francavilla Fontana Brindisi 72021",
    "addr:postcode":"72021;72021",
    "iso:country":"IT",
    "sg:address":"72021 Francavilla Fontana",
    "sg:city":"Francavilla Fontana",
    "sg:orig_category":"Forniture Per Agricoltura E Zootecnia",
    "sg:phone":"+39 0831 899498",
    "sg:postcode":"72021",
    "sg:province":"Brindisi",
    "wof:name":"Azienda Agricola S. Croce Di Leogrande Giacomo",
    "wof:placetype":"venue"
},
  "geometry": {"coordinates":[17.5505161285,40.5462265015],"type":"Point"}
}