{
  "type": "Feature",
  "properties": {
    "iso:country":"IT",
    "sg:address":"72, Via Molina 20060 Vignate",
    "sg:city":"Vignate",
    "sg:classifiers":[
        {
            "category":"Manufacturing",
            "subcategory":"Rubber & Plastics",
            "type":"Manufacturing & Wholesale Goods"
        }
    ],
    "sg:phone":"+39 39029560107",
    "sg:postcode":"20060",
    "sg:province":"Milano",
    "wof:name":"O.m.p. S.r.l.",
    "wof:placetype":"venue"
},
  "geometry": {"coordinates":[9.3854379654,45.5031166077],"type":"Point"}
}