{
  "type": "Feature",
  "properties": {
    "iso:country":"IT",
    "sg:address":"72, Via Roma 37054 Nogara",
    "sg:city":"Nogara",
    "sg:classifiers":[
        {
            "category":"Utilities",
            "subcategory":"Telephone",
            "type":"Services"
        }
    ],
    "sg:phone":"+39 0442 510467",
    "sg:postcode":"37054",
    "sg:province":"Verona",
    "sg:tags":[
        "telecommunication"
    ],
    "wof:name":"Sir.tel Snc Di Gallini Adriano & C.",
    "wof:placetype":"venue"
},
  "geometry": {"coordinates":[11.06153,45.176273],"type":"Point"}
}