{
  "type": "Feature",
  "properties": {
    "iso:country":"IT",
    "sg:address":"52025 Montevarchi",
    "sg:city":"Montevarchi",
    "sg:orig_category":"Macchine Utensili E Impianti. Apparecchiature Ed Attrezzature Meccaniche",
    "sg:phone":"+39 055 910 2447",
    "sg:postcode":"52025",
    "sg:province":"Arezzo",
    "sg:website":"http://www.paginegialle.it/serenipaolo",
    "wof:name":"Officina Meccanica Di Sereni Paolo",
    "wof:placetype":"venue"
},
  "geometry": {"coordinates":[11.55891,43.50008],"type":"Point"}
}