{
  "type": "Feature",
  "properties": {
    "addr:full":"22063 Cant\u00f9 Como 22063",
    "addr:postcode":"22063;22063",
    "iso:country":"IT",
    "sg:address":"22063 Cant\u00f9",
    "sg:orig_category":"Arredamenti - Produzione E Ingrosso",
    "sg:phone":"+39 031 732868",
    "sg:postcode":"22063",
    "sg:province":"Como",
    "sg:website":"http://www.cappellettiluigi.com",
    "wof:name":"Cappelletti Luigi & C. Snc",
    "wof:placetype":"venue"
},
  "geometry": {"coordinates":[9.141179,45.724323],"type":"Point"}
}