{
  "type": "Feature",
  "properties": {
    "addr:full":"110, Via Lauretana - Camucia 52044 Cortona Camucia Arezzo 52044",
    "addr:housenumber":"110",
    "addr:postcode":"52044;52044",
    "addr:street":"Via Lauretana Camucia",
    "iso:country":"IT",
    "sg:address":"110, Via Lauretana - Camucia 52044 Cortona",
    "sg:city":"Camucia",
    "sg:classifiers":[
        {
            "category":"Retail",
            "subcategory":"Animal Services",
            "type":"Services"
        }
    ],
    "sg:phone":"+39 0575 630292",
    "sg:postcode":"52044",
    "sg:province":"Arezzo",
    "sg:tags":[
        "breeding"
    ],
    "wof:name":"Turini Romeo Di Turini Vincenzo & C. Snc",
    "wof:placetype":"venue"
},
  "geometry": {"coordinates":[11.974833,43.26001],"type":"Point"}
}