{
  "type": "Feature",
  "properties": {
    "addr:full":"36, Via Postumia 31050 Ponzano Veneto Ponzano Veneto Treviso 31050",
    "addr:postcode":"31050;31050",
    "addr:street":"Via Postumia",
    "iso:country":"IT",
    "sg:address":"36, Via Postumia 31050 Ponzano Veneto",
    "sg:city":"Ponzano Veneto",
    "sg:classifiers":[
        {
            "category":"Food & Beverages",
            "subcategory":"Groceries & Convenience Stores",
            "type":"Retail Goods"
        }
    ],
    "sg:phone":"+39 0422 440101",
    "sg:postcode":"31050",
    "sg:province":"Treviso",
    "sg:tags":[
        "product",
        "related"
    ],
    "wof:name":"Salumificio Di Cornuda S.p.a.",
    "wof:placetype":"venue"
},
  "geometry": {"coordinates":[12.1994695663,45.7270355225],"type":"Point"}
}