{
  "type": "Feature",
  "properties": {
    "addr:full":"97015 Modica Modica Ragusa 97015",
    "addr:postcode":"97015;97015",
    "iso:country":"IT",
    "sg:address":"97015 Modica",
    "sg:city":"Modica",
    "sg:orig_category":"Fiorai - Accessori E Forniture",
    "sg:phone":"+39 0932 762703",
    "sg:postcode":"97015",
    "sg:province":"Ragusa",
    "wof:name":"Verdelli Rosaria",
    "wof:placetype":"venue"
},
  "geometry": {"coordinates":[14.7710351944,36.8417129517],"type":"Point"}
}