{
  "type": "Feature",
  "properties": {
    "addr:full":"30, V. Della Colombana 20078 S. Colombano Al Lambro Milano 20078",
    "addr:housenumber":"30",
    "addr:postcode":"20078;20078",
    "addr:street":"V. Della Colombana;Lambro",
    "iso:country":"IT",
    "sg:address":"30, V. Della Colombana 20078 S. Colombano Al Lambro",
    "sg:classifiers":[
        {
            "category":"Professional",
            "subcategory":"Engineering",
            "type":"Services"
        }
    ],
    "sg:phone":"+39 39037189055",
    "sg:postcode":"20078",
    "sg:province":"Milano",
    "sg:tags":[
        "machine",
        "-",
        "mechanical"
    ],
    "sg:website":"http://www.futurtek.it:ws_end: :mark:ws:http://www.paginegialle.it/futurtek-forni",
    "wof:name":"Futurtek Srl",
    "wof:placetype":"venue"
},
  "geometry": {"coordinates":[9.188141,45.463688],"type":"Point"}
}