{
  "type": "Feature",
  "properties": {
    "iso:country":"IT",
    "sg:address":"17, Via Antonio Carpene' 33070 Brugnera",
    "sg:city":"Brugnera",
    "sg:classifiers":[
        {
            "category":"Home & Garden",
            "subcategory":"Home Furnishings",
            "type":"Retail Goods"
        }
    ],
    "sg:phone":"+39 0434 624920",
    "sg:postcode":"33070",
    "sg:province":"Pordenone",
    "sg:tags":[
        "household"
    ],
    "wof:name":"Compab S.r.l.",
    "wof:placetype":"venue"
},
  "geometry": {"coordinates":[12.551538,45.91407],"type":"Point"}
}