{
  "type": "Feature",
  "properties": {
    "iso:country":"IT",
    "sg:address":"46, Via Masini A. 40069 Zola Predosa",
    "sg:city":"Zola",
    "sg:classifiers":[
        {
            "category":"Professional",
            "subcategory":"Advertising",
            "type":"Services"
        }
    ],
    "sg:phone":"+39 39051750247",
    "sg:postcode":"40069",
    "sg:province":"Bologna",
    "sg:tags":[
        "communication",
        "medium"
    ],
    "wof:name":"Palazzo Albergati (s.p.a.)",
    "wof:placetype":"venue"
},
  "geometry": {"coordinates":[11.221393,44.512066],"type":"Point"}
}