{
  "type": "Feature",
  "properties": {
    "addr:full":"33, Via Ca' Nova Zampieri 37057 San Giovanni Lupatoto San Giovanni Lupatoto Verona 37057",
    "addr:postcode":"37057;37057",
    "addr:street":"Via Ca ' Nova Zampieri;Verona",
    "iso:country":"IT",
    "sg:address":"33, Via Ca' Nova Zampieri 37057 San Giovanni Lupatoto",
    "sg:city":"San Giovanni Lupatoto",
    "sg:classifiers":[
        {
            "category":"Food & Beverages",
            "subcategory":"Groceries & Convenience Stores",
            "type":"Retail Goods"
        }
    ],
    "sg:phone":"+39 045 877 8502",
    "sg:postcode":"37057",
    "sg:province":"Verona",
    "sg:tags":[
        "product",
        "related"
    ],
    "wof:name":"Gama S.p.a.",
    "wof:placetype":"venue"
},
  "geometry": {"coordinates":[11.0181865692,45.3914756775],"type":"Point"}
}