{
  "type": "Feature",
  "properties": {
    "iso:country":"IT",
    "sg:address":"51017 Pescia",
    "sg:city":"Pescia",
    "sg:orig_category":"Articoli Regalo - Produzione E Ingrosso",
    "sg:phone":"+39 0572 400045",
    "sg:postcode":"51017",
    "sg:province":"Pistoia",
    "wof:name":"Gli Antichi Mestieri Soc. Coop. Arl",
    "wof:placetype":"venue"
},
  "geometry": {"coordinates":[10.698516,43.944355],"type":"Point"}
}