{
  "type": "Feature",
  "properties": {
    "addr:full":"2, Vicolo Salvo D'acquisto 24050 Grassobbio Grassobbio Bergamo 24050",
    "addr:housenumber":"2",
    "addr:postcode":"24050;24050",
    "addr:street":"Vicolo Salvo D'Acquisto",
    "iso:country":"IT",
    "sg:address":"2, Vicolo Salvo D'acquisto 24050 Grassobbio",
    "sg:city":"Grassobbio",
    "sg:classifiers":[
        {
            "category":"Wholesale",
            "subcategory":"Drugs",
            "type":"Manufacturing & Wholesale Goods"
        }
    ],
    "sg:phone":"+39 035 424 2111",
    "sg:postcode":"24050",
    "sg:province":"Bergamo",
    "sg:tags":[
        "chemical",
        "pharmaceutical"
    ],
    "wof:name":"Allegrini - Spa",
    "wof:placetype":"venue"
},
  "geometry": {"coordinates":[9.713706,45.65984],"type":"Point"}
}