{
  "type": "Feature",
  "properties": {
    "iso:country":"IT",
    "sg:address":"15, Via Perosi Don Lorenzo 50018 Scandicci",
    "sg:city":"Scandicci",
    "sg:classifiers":[
        {
            "category":"Home & Garden",
            "subcategory":"Home Furnishings",
            "type":"Retail Goods"
        }
    ],
    "sg:phone":"+39 39055756031",
    "sg:postcode":"50018",
    "sg:province":"Firenze",
    "sg:tags":[
        "household"
    ],
    "wof:name":"Chelini (s.p.a.)",
    "wof:placetype":"venue"
},
  "geometry": {"coordinates":[11.173036,43.758507],"type":"Point"}
}