{
  "type": "Feature",
  "properties": {
    "iso:country":"IT",
    "sg:address":"01100 Viterbo",
    "sg:city":"Viterbo",
    "sg:orig_category":"Banche E Servizi Finanziari",
    "sg:phone":"+39 0761 3111",
    "sg:postcode":"01100",
    "sg:province":"Viterbo",
    "sg:website":"http://www.carivit.it",
    "wof:name":"Cassa Di Risparmio Della Provincia Di Viterbo Spa",
    "wof:placetype":"venue"
},
  "geometry": {"coordinates":[12.048979,42.441536],"type":"Point"}
}