{
  "type": "Feature",
  "properties": {
    "iso:country":"IT",
    "sg:address":"39032 Campo Tures",
    "sg:city":"Campo Tures",
    "sg:orig_category":"Manufacturers: Prefabbricati",
    "sg:phone":"+39 0474 678570",
    "sg:postcode":"39032",
    "sg:province":"Bolzano/Bozen",
    "sg:website":"http://www.innerbichler.com",
    "wof:name":"Innerbichler Srl",
    "wof:placetype":"venue"
},
  "geometry": {"coordinates":[12.064618,46.948662],"type":"Point"}
}