{
  "type": "Feature",
  "properties": {
    "addr:full":"10026 Santena Santena Torino 10026",
    "addr:housenumber":"10026",
    "addr:postcode":"10026",
    "addr:street":"Santena Santena",
    "iso:country":"IT",
    "sg:address":"10026 Santena",
    "sg:city":"Santena",
    "sg:orig_category":"Forniture E Materiali Per Imballaggio E Confezionamento. Forniture Per Uffici. Forniture Per Attivita' Commerciali Ed Artigianali",
    "sg:phone":"+39 011 945 4227",
    "sg:postcode":"10026",
    "sg:province":"Torino",
    "wof:name":"Mapi Sas Di Autelli Paolo & C.",
    "wof:placetype":"venue"
},
  "geometry": {"coordinates":[7.4164075851,44.8698692322],"type":"Point"}
}