{
  "type": "Feature",
  "properties": {
    "addr:full":"15, Via Dell' Artigianato 41018 San Cesario Sul Panaro San Cesario sul Panaro Modena 41018",
    "addr:postcode":"41018;cesario;panaro;41018",
    "addr:street":"Via Dell ' Artigianato",
    "iso:country":"IT",
    "sg:address":"15, Via Dell' Artigianato 41018 San Cesario Sul Panaro",
    "sg:city":"San Cesario sul Panaro",
    "sg:classifiers":[
        {
            "category":"Manufacturing",
            "subcategory":"Lumber",
            "type":"Manufacturing & Wholesale Goods"
        }
    ],
    "sg:phone":"+39 39059920010",
    "sg:postcode":"41018",
    "sg:province":"Modena",
    "sg:tags":[
        "wood"
    ],
    "wof:name":"Tecnoprimaf Srl",
    "wof:placetype":"venue"
},
  "geometry": {"coordinates":[11.028806,44.59029],"type":"Point"}
}