{
  "type": "Feature",
  "properties": {
    "iso:country":"IT",
    "sg:address":"41, Via Forti Sergio 00144 Roma",
    "sg:city":"Roma",
    "sg:classifiers":[
        {
            "category":"Manufacturing",
            "subcategory":"Metals",
            "type":"Manufacturing & Wholesale Goods"
        }
    ],
    "sg:phone":"+39 39065292713",
    "sg:postcode":"00144",
    "sg:province":"Roma",
    "sg:tags":[
        "metallurgy",
        "metalworking"
    ],
    "wof:name":"Fisher-rosemount Srl",
    "wof:placetype":"venue"
},
  "geometry": {"coordinates":[12.4467067719,41.8066329956],"type":"Point"}
}