{
  "type": "Feature",
  "properties": {
    "iso:country":"IT",
    "sg:address":"1, Via Magellano F. 06016 San Giustino",
    "sg:city":"San Giustino",
    "sg:classifiers":[
        {
            "category":"Shopping",
            "type":"Retail Goods"
        }
    ],
    "sg:phone":"+39 075 856 0439",
    "sg:postcode":"06016",
    "sg:province":"Perugia",
    "sg:tags":[
        "finished",
        "-",
        "metallic"
    ],
    "wof:name":"Italstampi S.r.l.",
    "wof:placetype":"venue"
},
  "geometry": {"coordinates":[12.3891716003,43.1107025146],"type":"Point"}
}