{
  "type": "Feature",
  "properties": {
    "iso:country":"IT",
    "sg:address":"20091 Bresso",
    "sg:city":"Bresso",
    "sg:orig_category":"Lavorazioni Meccaniche E Servizi",
    "sg:phone":"+39 02 610 1720",
    "sg:postcode":"20091",
    "sg:province":"Milano",
    "wof:name":"La Rettifica Di Galli Carlo",
    "wof:placetype":"venue"
},
  "geometry": {"coordinates":[9.197104,45.536858],"type":"Point"}
}