{
  "type": "Feature",
  "properties": {
    "iso:country":"IT",
    "sg:address":"80014 Giugliano In Campania",
    "sg:city":"Giugliano in Campania",
    "sg:orig_category":"Materiali Semilavorati Metallici",
    "sg:phone":"+39 081 506 7140",
    "sg:postcode":"80014",
    "sg:province":"Napoli",
    "wof:name":"Iodice Agostino",
    "wof:placetype":"venue"
},
  "geometry": {"coordinates":[14.208086,40.940353],"type":"Point"}
}