{
  "type": "Feature",
  "properties": {
    "addr:full":"V. Migliorati - San Sisto 06123 Perugia Perugia Perugia 06123",
    "addr:postcode":"06123;06123",
    "addr:street":"San Sisto",
    "iso:country":"IT",
    "sg:address":"V. Migliorati - San Sisto 06123 Perugia",
    "sg:city":"Perugia",
    "sg:classifiers":[
        {
            "category":"Parking",
            "subcategory":"Lot",
            "type":"Transportation"
        }
    ],
    "sg:phone":"+39 075 528 8643",
    "sg:postcode":"06123",
    "sg:province":"Perugia",
    "sg:tags":[
        "transport",
        "road"
    ],
    "sg:website":"http://www.lafreedom.com",
    "wof:name":"Autotrasporti La Freedom",
    "wof:placetype":"venue"
},
  "geometry": {"coordinates":[12.385052,43.116081],"type":"Point"}
}