{
  "type": "Feature",
  "properties": {
    "addr:full":"20030 Senago Senago Milano 20030",
    "addr:postcode":"20030;20030",
    "iso:country":"IT",
    "sg:address":"20030 Senago",
    "sg:city":"Senago",
    "sg:orig_category":"Prodotti E Manufatti In Materie Plastiche. Servizi E Lavori Industria Delle Materie Plastiche",
    "sg:phone":"+39 02 998 9701",
    "sg:postcode":"20030",
    "sg:province":"Milano",
    "sg:website":"http://www.plastecomilano.com",
    "wof:name":"Plasteco Milano Sas",
    "wof:placetype":"venue"
},
  "geometry": {"coordinates":[9.0596017838,45.4239654541],"type":"Point"}
}