{
  "type": "Feature",
  "properties": {
    "iso:country":"IT",
    "sg:address":"20123 Milano",
    "sg:city":"Milano",
    "sg:orig_category":"Dentisti Medici Chirurghi Ed Odontoiatri",
    "sg:phone":"+39 02 469 1049",
    "sg:postcode":"20123",
    "sg:province":"Milano",
    "wof:name":"Ambulatorio Odontoiatrico Di Feo Dr. Alberto",
    "wof:placetype":"venue"
},
  "geometry": {"coordinates":[9.174111,45.461628],"type":"Point"}
}