{
  "type": "Feature",
  "properties": {
    "iso:country":"IT",
    "sg:address":"50054 Fucecchio",
    "sg:city":"Fucecchio",
    "sg:orig_category":"Arredamenti - Produzione E Ingrosso",
    "sg:phone":"+39 0571 20746",
    "sg:postcode":"50054",
    "sg:province":"Firenze",
    "wof:name":"Settesoldi Tappezzeria",
    "wof:placetype":"venue"
},
  "geometry": {"coordinates":[10.788723,43.765724],"type":"Point"}
}