{
  "type": "Feature",
  "properties": {
    "addr:full":"8, Via G. Nosari 24024 Gandino Gandino Bergamo 24024",
    "addr:postcode":"24024;24024",
    "addr:street":"Via G. Nosari",
    "iso:country":"IT",
    "sg:address":"8, Via G. Nosari 24024 Gandino",
    "sg:city":"Gandino",
    "sg:classifiers":[
        {
            "category":"Shopping",
            "subcategory":"Crafts & Fabrics",
            "type":"Retail Goods"
        }
    ],
    "sg:phone":"+39 39035745177",
    "sg:postcode":"24024",
    "sg:province":"Bergamo",
    "wof:name":"Lafitex S.n.c. Di Presti & C.",
    "wof:placetype":"venue"
},
  "geometry": {"coordinates":[9.8941345215,45.810256958],"type":"Point"}
}