{
  "type": "Feature",
  "properties": {
    "addr:full":"15, Via Tiziano 20032 Cormano Cormano Milano 20032",
    "addr:postcode":"20032;20032",
    "addr:street":"Via Tiziano",
    "iso:country":"IT",
    "sg:address":"15, Via Tiziano 20032 Cormano",
    "sg:city":"Cormano",
    "sg:classifiers":[
        {
            "category":"Wholesale",
            "subcategory":"Drugs",
            "type":"Manufacturing & Wholesale Goods"
        }
    ],
    "sg:phone":"+39 02 6630 2148",
    "sg:postcode":"20032",
    "sg:province":"Milano",
    "sg:tags":[
        "chemical",
        "pharmaceutical"
    ],
    "wof:name":"Kemikos (s.r.l.)",
    "wof:placetype":"venue"
},
  "geometry": {"coordinates":[9.156647,45.550266],"type":"Point"}
}