{
  "type": "Feature",
  "properties": {
    "iso:country":"IT",
    "sg:address":"31033 Castelfranco Veneto",
    "sg:city":"Castelfranco Veneto",
    "sg:orig_category":"Elettronica Professionale E Di Consumo. Automazione E Macchine Per Ufficio",
    "sg:phone":"+39 0423 492921",
    "sg:postcode":"31033",
    "sg:province":"Treviso",
    "wof:name":"Drigo Sas",
    "wof:placetype":"venue"
},
  "geometry": {"coordinates":[11.936238,45.669506],"type":"Point"}
}