{
  "type": "Feature",
  "properties": {
    "iso:country":"IT",
    "sg:address":"37131 Verona",
    "sg:city":"Verona",
    "sg:orig_category":"Forniture Per Agricoltura E Zootecnia",
    "sg:phone":"+39 045 892 1533",
    "sg:postcode":"37131",
    "sg:province":"Verona",
    "wof:name":"Tosi Paola",
    "wof:placetype":"venue"
},
  "geometry": {"coordinates":[11.0337715149,45.4370727539],"type":"Point"}
}