{
  "type": "Feature",
  "properties": {
    "addr:full":"84081 Baronissi Baronissi Salerno 84081",
    "addr:postcode":"84081;84081",
    "iso:country":"IT",
    "sg:address":"84081 Baronissi",
    "sg:city":"Baronissi",
    "sg:orig_category":"Serramenti Ed Infissi. Arte Ed Artigianato Artistico. Shopping",
    "sg:phone":"+39 089 953024",
    "sg:postcode":"84081",
    "sg:province":"Salerno",
    "sg:website":"http://www.designwindows.com",
    "wof:name":"Design Serramenti Srl",
    "wof:placetype":"venue"
},
  "geometry": {"coordinates":[14.781265,40.740265],"type":"Point"}
}