{
  "type": "Feature",
  "properties": {
    "iso:country":"IT",
    "sg:address":"7/a, Via Dell' Artigianato 40064 Ozzano Dell'emilia",
    "sg:classifiers":[
        {
            "category":"Shopping",
            "subcategory":"Clothing, Apparel, & Fashions",
            "type":"Retail Goods"
        }
    ],
    "sg:phone":"+39 39051796721",
    "sg:postcode":"40064",
    "sg:province":"Bologna",
    "sg:tags":[
        "clothes"
    ],
    "wof:name":"Confezioni Madamar Srl",
    "wof:placetype":"venue"
},
  "geometry": {"coordinates":[11.346481,44.494221],"type":"Point"}
}