{
  "type": "Feature",
  "properties": {
    "iso:country":"IT",
    "sg:address":"00159 Roma",
    "sg:city":"Roma",
    "sg:orig_category":"Non-classified Establishments",
    "sg:phone":"+39 06 439 3564",
    "sg:postcode":"00159",
    "sg:province":"Roma",
    "wof:name":"Il Mondo Del Mobile",
    "wof:placetype":"venue"
},
  "geometry": {"coordinates":[12.573743,41.925472],"type":"Point"}
}