{
  "type": "Feature",
  "properties": {
    "iso:country":"IT",
    "sg:address":"30036 Santa Maria Di Sala",
    "sg:city":"Santa Maria di Sala",
    "sg:orig_category":"Servizi E Lavori Industria Chimica",
    "sg:phone":"+39 041 487527",
    "sg:postcode":"30036",
    "sg:province":"Venezia",
    "wof:name":"Gi.m.m.a.c. Di Spolaore Giorgio & C. Snc",
    "wof:placetype":"venue"
},
  "geometry": {"coordinates":[12.017888,45.506691],"type":"Point"}
}