{
  "type": "Feature",
  "properties": {
    "addr:full":"Via F. Bruni, 26/28 - Z.i. Taccoli 62027 San Severino Marche San Severino Marche Macerata 62027",
    "addr:housenumber":"26 / 28",
    "addr:postcode":"62027;marche san;62027",
    "addr:street":"Via F. Bruni;Z.I. Taccoli",
    "iso:country":"IT",
    "sg:address":"Via F. Bruni, 26/28 - Z.i. Taccoli 62027 San Severino Marche",
    "sg:city":"San Severino Marche",
    "sg:orig_category":"Production Lines For Sheet Metal Working",
    "sg:phone":"+39 0733 645101",
    "sg:postcode":"62027",
    "sg:province":"Macerata",
    "sg:website":"www.tecno-promec.it/tecnoprofilatrici",
    "wof:name":"Tecnoprofilatrici Di Trombetti & C. Sas",
    "wof:placetype":"venue"
},
  "geometry": {"coordinates":[13.4562616348,43.3007469177],"type":"Point"}
}