{
  "type": "Feature",
  "properties": {
    "iso:country":"IT",
    "sg:address":"20020 Lainate",
    "sg:city":"Lainate",
    "sg:orig_category":"Metalli E Leghe",
    "sg:phone":"+39 02 9355 0506",
    "sg:postcode":"20020",
    "sg:province":"Milano",
    "wof:name":"M.& F. S.n.c.",
    "wof:placetype":"venue"
},
  "geometry": {"coordinates":[9.076374054,45.5445709229],"type":"Point"}
}