{
  "type": "Feature",
  "properties": {
    "addr:full":"10122 Torino Torino Torino 10122",
    "addr:housenumber":"10122",
    "addr:postcode":"10122",
    "iso:country":"IT",
    "sg:address":"10122 Torino",
    "sg:city":"Torino",
    "sg:orig_category":"Assicurazioni E Servizi Assicurativi. Consulenze Tecniche, Amministrative E Perizie",
    "sg:phone":"+39 011 959 3619",
    "sg:postcode":"10122",
    "sg:province":"Torino",
    "wof:name":"C.i.s.l. Unione Sindacale Territoriale",
    "wof:placetype":"venue"
},
  "geometry": {"coordinates":[7.676596,45.073357],"type":"Point"}
}