{
  "type": "Feature",
  "properties": {
    "iso:country":"IT",
    "sg:address":"122, Strada Cipata 46100 Mantova",
    "sg:city":"Mantova",
    "sg:classifiers":[
        {
            "category":"Parking",
            "subcategory":"Lot",
            "type":"Transportation"
        }
    ],
    "sg:phone":"+39 0376 273011",
    "sg:postcode":"46100",
    "sg:province":"Mantova",
    "sg:tags":[
        "transport",
        "road"
    ],
    "wof:name":"Gam Gruppo Autocisterne Mantova",
    "wof:placetype":"venue"
},
  "geometry": {"coordinates":[10.819442,45.156334],"type":"Point"}
}