{
  "type": "Feature",
  "properties": {
    "addr:full":"16161 Genova Genova Genova 16161",
    "addr:housenumber":"16161",
    "addr:postcode":"16161",
    "iso:country":"IT",
    "sg:address":"16161 Genova",
    "sg:city":"Genova",
    "sg:orig_category":"Servizi Ausiliari Dei Mezzi Di Trasporto",
    "sg:phone":"+39 010 651 7225",
    "sg:postcode":"16161",
    "sg:province":"Genova",
    "wof:name":"Automobilgas",
    "wof:placetype":"venue"
},
  "geometry": {"coordinates":[8.900267,44.433949],"type":"Point"}
}