{
  "type": "Feature",
  "properties": {
    "iso:country":"IT",
    "sg:address":"20149 Milano",
    "sg:city":"Milano",
    "sg:orig_category":"Apparecchiature Ed Attrezzature Meccaniche",
    "sg:phone":"+39 02 3310 5845",
    "sg:postcode":"20149",
    "sg:province":"Milano",
    "wof:name":"Oleo Tecno Dinamica Srl",
    "wof:placetype":"venue"
},
  "geometry": {"coordinates":[9.159434,45.485035],"type":"Point"}
}