{
  "type": "Feature",
  "properties": {
    "addr:full":"114, Via Cibrario Luigi 10143 Torino Torino Torino 10143",
    "addr:housenumber":"114",
    "addr:postcode":"10143;10143",
    "addr:street":"Via Cibrario Luigi",
    "iso:country":"IT",
    "sg:address":"114, Via Cibrario Luigi 10143 Torino",
    "sg:city":"Torino",
    "sg:orig_category":"Miscellaneous Products",
    "sg:phone":"+39 39011759864",
    "sg:postcode":"10143",
    "sg:province":"Torino",
    "wof:name":"Agef Di Greco Antonio E C. (s.n.c.)",
    "wof:placetype":"venue"
},
  "geometry": {"coordinates":[7.6866188049,45.0705604553],"type":"Point"}
}