{
  "type": "Feature",
  "properties": {
    "addr:full":"Piazza Sartori 1; Longarone; 32013 Longarone Belluno 32013",
    "addr:housenumber":"1",
    "addr:postcode":"32013;32013",
    "addr:street":"Piazza Sartori",
    "iso:country":"IT",
    "sg:address":"Piazza Sartori 1; Longarone; 32013",
    "sg:city":"Longarone",
    "sg:classifiers":[
        {
            "category":"Banks & Credit Unions",
            "subcategory":"Bank",
            "type":"Services"
        }
    ],
    "sg:phone":"+39 0437 770111",
    "sg:postcode":"32013",
    "sg:province":"Belluno",
    "wof:name":"Banco Ambrosiano Veneto Spa",
    "wof:placetype":"venue"
},
  "geometry": {"coordinates":[12.299561,46.269291],"type":"Point"}
}