{
  "type": "Feature",
  "properties": {
    "iso:country":"IT",
    "sg:address":"Via Aldo San Lorenzo 31 15020 San Giorgio Monferrato",
    "sg:city":"San Giorgio",
    "sg:classifiers":[
        {
            "category":"Manufacturing",
            "subcategory":"Wood Products",
            "type":"Manufacturing & Wholesale Goods"
        }
    ],
    "sg:postcode":"15020",
    "sg:province":"Alessandria",
    "sg:tags":[
        "insulating",
        "board"
    ],
    "wof:name":"Pannelli Isolanti Srl",
    "wof:placetype":"venue"
},
  "geometry": {"coordinates":[8.616951,44.913216],"type":"Point"}
}