{
  "type": "Feature",
  "properties": {
    "addr:full":"92016 Ribera Ribera Agrigento 92016",
    "addr:postcode":"92016;92016",
    "iso:country":"IT",
    "sg:address":"92016 Ribera",
    "sg:city":"Ribera",
    "sg:orig_category":"Macchine Edili E Stradali - Commercio, Noleggio E Riparazione",
    "sg:phone":"+39 0925 544544",
    "sg:postcode":"92016",
    "sg:province":"Agrigento",
    "sg:website":"http://www.amesonline.it",
    "wof:name":"A Mes Snc Di G. Salvato & C.",
    "wof:placetype":"venue"
},
  "geometry": {"coordinates":[13.258855,37.495865],"type":"Point"}
}