{
  "type": "Feature",
  "properties": {
    "iso:country":"IT",
    "sg:address":"Arnad - Frazione Levieux 11020 Arnad",
    "sg:city":"Arnad",
    "sg:classifiers":[
        {
            "category":"Structure",
            "subcategory":"Office Building",
            "type":"Public Place"
        }
    ],
    "sg:phone":"+39 0125 968611",
    "sg:postcode":"11020",
    "sg:province":"Aosta",
    "sg:tags":[
        "equipment",
        "alarm",
        "installation",
        "system"
    ],
    "sg:website":"www.gps-standard.com",
    "wof:name":"Gps Standard Spa",
    "wof:placetype":"venue"
},
  "geometry": {"coordinates":[7.717496,45.64645],"type":"Point"}
}