{
  "type": "Feature",
  "properties": {
    "iso:country":"IT",
    "sg:address":"35027 Noventa Padovana",
    "sg:city":"Noventa Padovana",
    "sg:classifiers":[
        {
            "category":"Health Services",
            "subcategory":"Health Practitioner",
            "type":"Services"
        }
    ],
    "sg:phone":"+39 049 980 1059",
    "sg:postcode":"35027",
    "sg:province":"Padova",
    "sg:tags":[
        "medici"
    ],
    "wof:name":"Zebellin Giuliano",
    "wof:placetype":"venue"
},
  "geometry": {"coordinates":[11.8932466507,45.4108200073],"type":"Point"}
}