{
  "type": "Feature",
  "properties": {
    "iso:country":"IT",
    "sg:address":"25014 Castenedolo",
    "sg:city":"Castenedolo",
    "sg:orig_category":"Utensili Meccanici E Materiali",
    "sg:phone":"+39 030 273 3182",
    "sg:postcode":"25014",
    "sg:province":"Brescia",
    "wof:name":"Cosio Danilo",
    "wof:placetype":"venue"
},
  "geometry": {"coordinates":[10.292426,45.466812],"type":"Point"}
}