{
  "type": "Feature",
  "properties": {
    "addr:full":"26, Strada Vicinale Della Trinita' 74015 Martina Franca Martina Franca Taranto 74015",
    "addr:postcode":"74015;74015",
    "addr:street":"Strada Vicinale Della Trinita '",
    "iso:country":"IT",
    "sg:address":"26, Strada Vicinale Della Trinita' 74015 Martina Franca",
    "sg:city":"Martina Franca",
    "sg:classifiers":[
        {
            "category":"Shopping",
            "subcategory":"Crafts & Fabrics",
            "type":"Retail Goods"
        }
    ],
    "sg:phone":"+39 080 485 7175",
    "sg:postcode":"74015",
    "sg:province":"Taranto",
    "wof:name":"Confezioni Lerario (s.r.l.)",
    "wof:placetype":"venue"
},
  "geometry": {"coordinates":[17.2400093079,40.4692382812],"type":"Point"}
}