{
  "type": "Feature",
  "properties": {
    "iso:country":"IT",
    "sg:address":"Via Europa Unita 6 24030 Valbrembo",
    "sg:city":"Valbrembo",
    "sg:classifiers":[
        {
            "category":"Building & Trades",
            "subcategory":"Electrical",
            "type":"Services"
        }
    ],
    "sg:phone":"+39 035 528032",
    "sg:postcode":"24030",
    "sg:province":"Bergamo",
    "sg:tags":[
        "tool",
        "high-quality"
    ],
    "sg:website":"www.azfius.it",
    "wof:name":"A.z. F.i.u.s. Spa",
    "wof:placetype":"venue"
},
  "geometry": {"coordinates":[9.601133,45.716274],"type":"Point"}
}