{
  "type": "Feature",
  "properties": {
    "iso:country":"IT",
    "sg:address":"12, Via S. Rocco 25026 Pontevico",
    "sg:city":"Pontevico",
    "sg:classifiers":[
        {
            "category":"Manufacturing",
            "subcategory":"Metals",
            "type":"Manufacturing & Wholesale Goods"
        }
    ],
    "sg:phone":"+39 030 993 0290",
    "sg:postcode":"25026",
    "sg:province":"Brescia",
    "sg:tags":[
        "metallurgy",
        "metalworking"
    ],
    "wof:name":"Sidermariotti (s.r.l.)",
    "wof:placetype":"venue"
},
  "geometry": {"coordinates":[10.1211681366,45.2473983765],"type":"Point"}
}