{
  "type": "Feature",
  "properties": {
    "addr:full":"Piazza San Luca 22; Padola; 32040 Padola Belluno 32040",
    "addr:housenumber":"22",
    "addr:postcode":"32040;32040",
    "addr:street":"Piazza San Luca",
    "iso:country":"IT",
    "sg:address":"Piazza San Luca 22; Padola; 32040",
    "sg:city":"Padola",
    "sg:classifiers":[
        {
            "category":"Banks & Credit Unions",
            "subcategory":"Bank",
            "type":"Services"
        }
    ],
    "sg:phone":"+39 0435 470103",
    "sg:postcode":"32040",
    "sg:province":"Belluno",
    "wof:name":"Banca Popolare Dell'alto Adige",
    "wof:placetype":"venue"
},
  "geometry": {"coordinates":[12.479335,46.601795],"type":"Point"}
}