{
  "type": "Feature",
  "properties": {
    "iso:country":"IT",
    "sg:address":"00156 Roma",
    "sg:city":"Roma",
    "sg:orig_category":"Climatizzazione E Condizionamento, Apparecchiature E Servizi. Accessori Dei Mezzi Di Trasporto",
    "sg:phone":"+39 06 4121 9336",
    "sg:postcode":"00156",
    "sg:province":"Roma",
    "wof:name":"Ellera Massimo",
    "wof:placetype":"venue"
},
  "geometry": {"coordinates":[12.574864,41.939217],"type":"Point"}
}