{
  "type": "Feature",
  "properties": {
    "addr:full":"20133 Milano Milano Milano 20133",
    "addr:postcode":"20133;20133",
    "iso:country":"IT",
    "sg:address":"20133 Milano",
    "sg:city":"Milano",
    "sg:orig_category":"Prodotti Alimentari",
    "sg:phone":"+39 02 730330",
    "sg:postcode":"20133",
    "sg:province":"Milano",
    "wof:name":"Valente Nicola",
    "wof:placetype":"venue"
},
  "geometry": {"coordinates":[9.2296924591,45.471370697],"type":"Point"}
}