{
  "type": "Feature",
  "properties": {
    "addr:full":"12, Via Crescenzio 00193 Roma Roma Roma 00193",
    "addr:postcode":"00193;00193",
    "addr:street":"Via Crescenzio",
    "iso:country":"IT",
    "sg:address":"12, Via Crescenzio 00193 Roma",
    "sg:city":"Roma",
    "sg:classifiers":[
        {
            "category":"Banks & Credit Unions",
            "subcategory":"Financial Services",
            "type":"Services"
        }
    ],
    "sg:phone":"+39 390 668 8121",
    "sg:postcode":"00193",
    "sg:province":"Roma",
    "sg:tags":[
        "banking",
        "finance",
        "insurance"
    ],
    "wof:name":"Societa Italiana Cauzioni-assicurazioni E Riassicurazioni Spa",
    "wof:placetype":"venue"
},
  "geometry": {"coordinates":[12.466527,41.905533],"type":"Point"}
}