{
  "type": "Feature",
  "properties": {
    "iso:country":"IT",
    "sg:address":"61030 Isola Del Piano",
    "sg:city":"Isola del Piano",
    "sg:orig_category":"Macchine, Impianti Ed Attrezzature Per Agricoltura E Zootecnia. Macchine, Impianti Ed Attrezzature Industria Chimica. Macchine Utensili E Impianti",
    "sg:phone":"+39 0721 720256",
    "sg:postcode":"61030",
    "sg:province":"Pesaro E Urbino",
    "wof:name":"Aroph Spagiria Di Di Paoli Marisa",
    "wof:placetype":"venue"
},
  "geometry": {"coordinates":[12.784307,43.737923],"type":"Point"}
}