{
  "type": "Feature",
  "properties": {
    "iso:country":"IT",
    "sg:address":"53045 Montepulciano",
    "sg:city":"Montepulciano",
    "sg:orig_category":"Autofficine E Centri Assistenza",
    "sg:phone":"+39 0578 716795",
    "sg:postcode":"53045",
    "sg:province":"Siena",
    "wof:name":"Autofficina Franchetti Natale",
    "wof:placetype":"venue"
},
  "geometry": {"coordinates":[11.783209,43.094265],"type":"Point"}
}