{
  "type": "Feature",
  "properties": {
    "iso:country":"IT",
    "sg:address":"37015 Domegliara",
    "sg:city":"Domegliara",
    "sg:orig_category":"Utensili Meccanici E Materiali",
    "sg:phone":"+39 045 686 0656",
    "sg:postcode":"37015",
    "sg:province":"Verona",
    "wof:name":"Dives S.r.l.",
    "wof:placetype":"venue"
},
  "geometry": {"coordinates":[11.12674,45.30611],"type":"Point"}
}