{
  "type": "Feature",
  "properties": {
    "iso:country":"IT",
    "sg:address":"Via C. Battisti 57; Foligno; 06034",
    "sg:city":"Foligno",
    "sg:classifiers":[
        {
            "category":"Banks & Credit Unions",
            "subcategory":"Bank",
            "type":"Services"
        }
    ],
    "sg:phone":"+39 0742 352355",
    "sg:postcode":"06034",
    "sg:province":"Perugia",
    "wof:name":"Credito Italiano Spa",
    "wof:placetype":"venue"
},
  "geometry": {"coordinates":[12.709198,42.955807],"type":"Point"}
}