{
  "type": "Feature",
  "properties": {
    "iso:country":"IT",
    "sg:address":"84091 Battipaglia",
    "sg:city":"Battipaglia",
    "sg:orig_category":"Prodotti Alimentari",
    "sg:phone":"+39 0828 300336",
    "sg:postcode":"84091",
    "sg:province":"Salerno",
    "wof:name":"Caseificio Jemma",
    "wof:placetype":"venue"
},
  "geometry": {"coordinates":[14.7631416321,40.6771125793],"type":"Point"}
}