{
  "type": "Feature",
  "properties": {
    "addr:full":"43030 Torrile Parma 43030",
    "addr:postcode":"43030;43030",
    "iso:country":"IT",
    "sg:address":"43030 Torrile",
    "sg:orig_category":"Carpenterie Metalliche",
    "sg:phone":"+39 0521 813509",
    "sg:postcode":"43030",
    "sg:province":"Parma",
    "wof:name":"Ecam Snc Di Campanini Arvedo & C.",
    "wof:placetype":"venue"
},
  "geometry": {"coordinates":[10.329548,44.807865],"type":"Point"}
}