{
  "type": "Feature",
  "properties": {
    "addr:full":"9/11, Via Fermi E. 35010 Cadoneghe Cadoneghe Padova 35010",
    "addr:housenumber":"9 / 11",
    "addr:postcode":"35010;35010",
    "addr:street":"Via Fermi E.",
    "iso:country":"IT",
    "sg:address":"9/11, Via Fermi E. 35010 Cadoneghe",
    "sg:city":"Cadoneghe",
    "sg:classifiers":[
        {
            "category":"Shopping",
            "subcategory":"Crafts & Fabrics",
            "type":"Retail Goods"
        }
    ],
    "sg:phone":"+39 049 887 2828",
    "sg:postcode":"35010",
    "sg:province":"Padova",
    "wof:name":"Aurim (s.p.a.)",
    "wof:placetype":"venue"
},
  "geometry": {"coordinates":[11.8997144699,45.4722709656],"type":"Point"}
}