{
  "type": "Feature",
  "properties": {
    "addr:full":"20131 Milano Milano Milano 20131",
    "addr:postcode":"20131;20131",
    "iso:country":"IT",
    "sg:address":"20131 Milano",
    "sg:city":"Milano",
    "sg:orig_category":"Prodotti Chimici Di Base",
    "sg:phone":"+39 02 706 4191",
    "sg:postcode":"20131",
    "sg:province":"Milano",
    "wof:name":"R. Dona' S.p.a.",
    "wof:placetype":"venue"
},
  "geometry": {"coordinates":[9.2264738083,45.4828491211],"type":"Point"}
}