{
  "type": "Feature",
  "properties": {
    "iso:country":"IT",
    "sg:address":"01030 Carbognano",
    "sg:city":"Carbognano",
    "sg:orig_category":"Prodotti Di Base E Forniture Per Industria Alimentare E Bevande. Forniture Per Attivita' Commerciali Ed Artigianali",
    "sg:phone":"+39 0761 613102",
    "sg:postcode":"01030",
    "sg:province":"Viterbo",
    "wof:name":"Orlandi Alberto",
    "wof:placetype":"venue"
},
  "geometry": {"coordinates":[12.2433481216,42.3722419739],"type":"Point"}
}