{
  "type": "Feature",
  "properties": {
    "iso:country":"IT",
    "sg:address":"Via Leonardo Da Vinci 8 27036 Mortara",
    "sg:city":"Mortara",
    "sg:classifiers":[
        {
            "category":"Manufacturing",
            "subcategory":"Rubber & Plastics",
            "type":"Manufacturing & Wholesale Goods"
        }
    ],
    "sg:phone":"+39 0384 2031",
    "sg:postcode":"27036",
    "sg:province":"Pavia",
    "sg:tags":[
        "ab",
        "styrene",
        "butadiene",
        "foil",
        "slab",
        "acrylonitrile"
    ],
    "sg:website":"www.sitsrl.it",
    "wof:name":"Sit Societa' Industria Truciolari Srl",
    "wof:placetype":"venue"
},
  "geometry": {"coordinates":[8.687793,45.234989],"type":"Point"}
}