{
  "type": "Feature",
  "properties": {
    "addr:full":"93, Via Cervi Fratelli 22066 Mariano Comense Mariano Comense Como 22066",
    "addr:postcode":"22066;22066",
    "addr:street":"Via Cervi",
    "iso:country":"IT",
    "sg:address":"93, Via Cervi Fratelli 22066 Mariano Comense",
    "sg:city":"Mariano Comense",
    "sg:classifiers":[
        {
            "category":"Manufacturing",
            "subcategory":"Rubber & Plastics",
            "type":"Manufacturing & Wholesale Goods"
        }
    ],
    "sg:phone":"+39 39031746665",
    "sg:postcode":"22066",
    "sg:province":"Como",
    "sg:tags":[
        "packaging",
        "material",
        "-"
    ],
    "wof:name":"T.p.s. Di Ballabio Giuliano & C. (s.n.c.)",
    "wof:placetype":"venue"
},
  "geometry": {"coordinates":[9.0854558945,45.8119659424],"type":"Point"}
}