{
  "type": "Feature",
  "properties": {
    "iso:country":"IT",
    "sg:address":"27041 Casanova Lonati",
    "sg:city":"Casanova Lonati",
    "sg:orig_category":"Minuterie Metalliche E Ferramenta",
    "sg:phone":"+39 0385 57237",
    "sg:postcode":"27041",
    "sg:province":"Pavia",
    "wof:name":"Off. Meccanica Micron 77 Snc",
    "wof:placetype":"venue"
},
  "geometry": {"coordinates":[9.2145366669,45.0954818726],"type":"Point"}
}