{
  "type": "Feature",
  "properties": {
    "addr:full":"00040 Pomezia Pomezia Roma 00040",
    "addr:postcode":"00040;roma 00040",
    "iso:country":"IT",
    "sg:address":"00040 Pomezia",
    "sg:city":"Pomezia",
    "sg:orig_category":"Macchine, Impianti Ed Attrezzature Per Abbigliamento E Pelletterie",
    "sg:phone":"+39 06 910 4333",
    "sg:postcode":"00040",
    "sg:province":"Roma",
    "wof:name":"Gallace Maria Rosaria - Magimac '90",
    "wof:placetype":"venue"
},
  "geometry": {"coordinates":[12.498818,41.674484],"type":"Point"}
}