{
  "type": "Feature",
  "properties": {
    "addr:full":"46100 Mantova Mantova Mantova 46100",
    "addr:postcode":"46100;46100",
    "iso:country":"IT",
    "sg:address":"46100 Mantova",
    "sg:city":"Mantova",
    "sg:orig_category":"Professionisti - Studi E Servizi Ed Associazioni Di Interesse Aziendale. Associazioni Ed Organismi Di Interesse Pubblico",
    "sg:phone":"+39 0376 2361",
    "sg:postcode":"46100",
    "sg:province":"Mantova",
    "sg:website":"http://www.mn.confartigianato.it",
    "wof:name":"Upaservizi Srl",
    "wof:placetype":"venue"
},
  "geometry": {"coordinates":[10.7855978012,45.1589126587],"type":"Point"}
}