{
  "type": "Feature",
  "properties": {
    "addr:full":"24047 Treviglio Treviglio Bergamo 24047",
    "addr:postcode":"24047;24047",
    "iso:country":"IT",
    "sg:address":"24047 Treviglio",
    "sg:city":"Treviglio",
    "sg:orig_category":"Prodotti E Manufatti In Materie Plastiche",
    "sg:phone":"+39 036 348485",
    "sg:postcode":"24047",
    "sg:province":"Bergamo",
    "wof:name":"Barba Salvatore",
    "wof:placetype":"venue"
},
  "geometry": {"coordinates":[9.5972414017,45.5326766968],"type":"Point"}
}