{
  "type": "Feature",
  "properties": {
    "addr:full":"09033 Decimomannu Decimomannu Cagliari 09033",
    "addr:postcode":"09033;09033",
    "iso:country":"IT",
    "sg:address":"09033 Decimomannu",
    "sg:city":"Decimomannu",
    "sg:orig_category":"Pubblica Amministrazione",
    "sg:phone":"+39 070 966 0149",
    "sg:postcode":"09033",
    "sg:province":"Cagliari",
    "wof:name":"Pretura",
    "wof:placetype":"venue"
},
  "geometry": {"coordinates":[9.0052604675,39.2876205444],"type":"Point"}
}