{
  "type": "Feature",
  "properties": {
    "iso:country":"IT",
    "sg:address":"Via Cesare Balbo 35",
    "sg:city":"Rome",
    "sg:classifiers":[
        {
            "category":"Professional",
            "subcategory":"Management & Consulting",
            "type":"Services"
        }
    ],
    "sg:postcode":"00184",
    "sg:tags":[
        "web-advertising",
        "web-2-0",
        "social-web",
        "web-consultancy",
        "search-engine-marketing",
        "sem",
        "seo",
        "search-engine-optimization",
        "web-agency",
        "internet-advertising",
        "affiliation-networks",
        "affiliation-platforms",
        "mobile-advertising",
        "display-advertising",
        "classifieds",
        "unso"
    ],
    "sg:website":"http://www.digitalrevenew.com",
    "wof:name":"Digital ReveNew",
    "wof:placetype":"venue"
},
  "geometry": {"coordinates":[12.4941336,41.8975813],"type":"Point"}
}