{
  "type": "Feature",
  "properties": {
    "iso:country":"IT",
    "sg:address":"16043 Chiavari",
    "sg:city":"Chiavari",
    "sg:classifiers":[
        {
            "category":"Health Services",
            "subcategory":"Health Practitioner",
            "type":"Services"
        }
    ],
    "sg:phone":"+39 0185 307697",
    "sg:postcode":"16043",
    "sg:province":"Genova",
    "sg:tags":[
        "medici"
    ],
    "wof:name":"Sambuceti Dino",
    "wof:placetype":"venue"
},
  "geometry": {"coordinates":[9.3173742294,44.324886322],"type":"Point"}
}