{
  "type": "Feature",
  "properties": {
    "addr:full":"20144 Milano Milano Milano 20144",
    "addr:postcode":"20144;20144",
    "iso:country":"IT",
    "sg:address":"20144 Milano",
    "sg:city":"Milano",
    "sg:orig_category":"Minuterie Metalliche E Ferramenta. Ricambi E Componenti Dei Mezzi Di Trasporto",
    "sg:phone":"+39 02 422 2727",
    "sg:postcode":"20144",
    "sg:province":"Milano",
    "wof:name":"De Felice Balestre Di De Felice Franco",
    "wof:placetype":"venue"
},
  "geometry": {"coordinates":[9.171579361,45.4545516968],"type":"Point"}
}