{
  "type": "Feature",
  "properties": {
    "addr:full":"00197 Roma Roma Roma 00197",
    "addr:postcode":"00197;00197",
    "iso:country":"IT",
    "sg:address":"00197 Roma",
    "sg:city":"Roma",
    "sg:orig_category":"Servizi E Lavori Per Abbigliamento E Pelletterie",
    "sg:phone":"+39 06 807 0294",
    "sg:postcode":"00197",
    "sg:province":"Roma",
    "wof:name":"Orlo Rapido Snc Di Massimo Palombo E Maria Teresa Piscitelli",
    "wof:placetype":"venue"
},
  "geometry": {"coordinates":[12.487104,41.922569],"type":"Point"}
}