{
  "type": "Feature",
  "properties": {
    "iso:country":"IT",
    "sg:address":"80139 Napoli",
    "sg:city":"Napoli",
    "sg:orig_category":"Arredamento Negozi E Supermercati",
    "sg:phone":"+39 081 451020",
    "sg:postcode":"80139",
    "sg:province":"Napoli",
    "wof:name":"Centroarredi System Snc",
    "wof:placetype":"venue"
},
  "geometry": {"coordinates":[14.264305,40.854851],"type":"Point"}
}