{
  "type": "Feature",
  "properties": {
    "iso:country":"IT",
    "sg:address":"23841 Annone Di Brianza",
    "sg:city":"Annone di Brianza",
    "sg:orig_category":"Prodotti Di Base E Forniture Per Industria Alimentare E Bevande. Carta, Cartone E Prodotti Primari. Forniture Per Attivita' Commerciali Ed Artigianali",
    "sg:phone":"+39 0341 577760",
    "sg:postcode":"23841",
    "sg:province":"Lecco",
    "wof:name":"Gerry Cart",
    "wof:placetype":"venue"
},
  "geometry": {"coordinates":[9.3793258667,45.816368103],"type":"Point"}
}