{
  "type": "Feature",
  "properties": {
    "addr:full":"27, Via Giovanni Pascoli 30020 Quarto D'altino Venezia 30020",
    "addr:postcode":"30020;30020",
    "addr:street":"Via Giovanni Pascoli",
    "iso:country":"IT",
    "sg:address":"27, Via Giovanni Pascoli 30020 Quarto D'altino",
    "sg:classifiers":[
        {
            "category":"Sports & Exercise",
            "subcategory":"Playing Field",
            "type":"Entertainment"
        }
    ],
    "sg:phone":"+39 0422 825521",
    "sg:postcode":"30020",
    "sg:province":"Venezia",
    "sg:tags":[
        "game"
    ],
    "wof:name":"La Bottega Veneziana (s.r.l.)",
    "wof:placetype":"venue"
},
  "geometry": {"coordinates":[12.351291,45.573418],"type":"Point"}
}