{
  "type": "Feature",
  "properties": {
    "addr:full":"25039 Travagliato Travagliato Brescia 25039",
    "addr:postcode":"25039;25039",
    "iso:country":"IT",
    "sg:address":"25039 Travagliato",
    "sg:city":"Travagliato",
    "sg:orig_category":"Servizi E Lavori Per Industria Alimentare E Bevande",
    "sg:phone":"+39 030 660425",
    "sg:postcode":"25039",
    "sg:province":"Brescia",
    "wof:name":"Marchetti Giuseppe",
    "wof:placetype":"venue"
},
  "geometry": {"coordinates":[10.0862,45.524521],"type":"Point"}
}