{
  "type": "Feature",
  "properties": {
    "addr:full":"2/b, Via Crocifisso 70126 Bari Bari Bari 70126",
    "addr:housenumber":"2 / b",
    "addr:postcode":"70126;70126",
    "addr:street":"Via Crocifisso",
    "iso:country":"IT",
    "sg:address":"2/b, Via Crocifisso 70126 Bari",
    "sg:city":"Bari",
    "sg:classifiers":[
        {
            "category":"Manufacturing",
            "subcategory":"Rubber & Plastics",
            "type":"Manufacturing & Wholesale Goods"
        }
    ],
    "sg:phone":"+39 080 546 8316",
    "sg:postcode":"70126",
    "sg:province":"Bari",
    "wof:name":"Sbs Srl",
    "wof:placetype":"venue"
},
  "geometry": {"coordinates":[16.8704891205,41.0706558228],"type":"Point"}
}