{
  "type": "Feature",
  "properties": {
    "iso:country":"IT",
    "sg:address":"90039 Villabate",
    "sg:city":"Villabate",
    "sg:orig_category":"Petroli, Gas E Combustibili. Termotecnica E Riscaldamento, Apparecchiature E Servizi",
    "sg:phone":"+39 091 490417",
    "sg:postcode":"90039",
    "sg:province":"Palermo",
    "wof:name":"Gical",
    "wof:placetype":"venue"
},
  "geometry": {"coordinates":[13.4425067902,38.0793609619],"type":"Point"}
}