{
  "type": "Feature",
  "properties": {
    "addr:full":"Piazza Di S. Vittore 3, 38010 Taio, Tn Trento 38010",
    "addr:housenumber":"3",
    "addr:postcode":"38010;38010",
    "addr:street":"Piazza Di S. Vittore;Trento",
    "iso:country":"IT",
    "sg:address":"Piazza Di S. Vittore 3, 38010 Taio, Tn",
    "sg:classifiers":[
        {
            "category":"Banks & Credit Unions",
            "subcategory":"Bank",
            "type":"Services"
        }
    ],
    "sg:postcode":"38010",
    "sg:province":"Trento",
    "wof:name":"Cassa Rurale D'anaunia-banca Di Credito Cooperativo Scrl",
    "wof:placetype":"venue"
},
  "geometry": {"coordinates":[11.066191,46.320633],"type":"Point"}
}