{
  "type": "Feature",
  "properties": {
    "iso:country":"IT",
    "sg:address":"Via Garibaldi Giuseppe 83 20054 Nova Milanese",
    "sg:city":"Nova Milanese",
    "sg:classifiers":[
        {
            "category":"Bars & Pubs",
            "subcategory":"Sports Bar",
            "type":"Food & Drink"
        }
    ],
    "sg:phone":"+39 036 236 8357",
    "sg:postcode":"20054",
    "sg:province":"Milano",
    "sg:tags":[
        "dy",
        "forging"
    ],
    "sg:website":"www.mmoi.it",
    "wof:name":"M.moi Srl",
    "wof:placetype":"venue"
},
  "geometry": {"coordinates":[9.2079868317,45.5555915833],"type":"Point"}
}