{
  "type": "Feature",
  "properties": {
    "iso:country":"IT",
    "sg:address":"103, Via Garibaldi 12060 Grinzane Cavour",
    "sg:city":"Grinzane Cavour",
    "sg:classifiers":[
        {
            "category":"Banks & Credit Unions",
            "subcategory":"Bank",
            "type":"Services"
        }
    ],
    "sg:phone":"+39 0173 230511",
    "sg:postcode":"12060",
    "sg:province":"Cuneo",
    "sg:tags":[
        "banking",
        "institution"
    ],
    "wof:name":"Banca Di Credito Cooperativo Di Alba Langhe E Roero S.c.r.l.",
    "wof:placetype":"venue"
},
  "geometry": {"coordinates":[7.98071,44.656212],"type":"Point"}
}