{
  "type": "Feature",
  "properties": {
    "iso:country":"IT",
    "sg:address":"20056 Trezzo Sull'adda",
    "sg:orig_category":"Abbigliamento - Produzione E Ingrosso",
    "sg:phone":"+39 02 909 0202",
    "sg:postcode":"20056",
    "sg:province":"Milano",
    "wof:name":"Stecol Flex Srl",
    "wof:placetype":"venue"
},
  "geometry": {"coordinates":[9.521315,45.607029],"type":"Point"}
}