{
  "type": "Feature",
  "properties": {
    "iso:country":"IT",
    "sg:address":"Via Piave 76 20020 Cogliate",
    "sg:city":"Cogliate",
    "sg:orig_category":"Forced-air Ovens For The Industry",
    "sg:phone":"+39 02 966 1742",
    "sg:postcode":"20020",
    "sg:province":"Milano",
    "wof:name":"Fire-tech Engineering S.r.l.",
    "wof:placetype":"venue"
},
  "geometry": {"coordinates":[9.0885839462,45.6428833008],"type":"Point"}
}