{
  "type": "Feature",
  "properties": {
    "iso:country":"IT",
    "sg:address":"Via Circonvallazione Sud 55 26010 Offanengo",
    "sg:city":"Offanengo",
    "sg:classifiers":[
        {
            "category":"Manufacturing",
            "subcategory":"Tools & Machinery",
            "type":"Manufacturing & Wholesale Goods"
        }
    ],
    "sg:phone":"+39 0373 780380",
    "sg:postcode":"26010",
    "sg:province":"Cremona",
    "sg:tags":[
        "binder",
        "rivet"
    ],
    "sg:website":"www.iml.it",
    "wof:name":"Iml S.r.l.",
    "wof:placetype":"venue"
},
  "geometry": {"coordinates":[9.743834,45.376236],"type":"Point"}
}