{
  "type": "Feature",
  "properties": {
    "iso:country":"IT",
    "sg:address":"14, Via Rota Fratelli 24129 Bergamo",
    "sg:city":"Bergamo",
    "sg:classifiers":[
        {
            "category":"Shopping",
            "subcategory":"Crafts & Fabrics",
            "type":"Retail Goods"
        }
    ],
    "sg:phone":"+39 39035251004",
    "sg:postcode":"24129",
    "sg:province":"Bergamo",
    "wof:name":"Tintoria Orobica Srl",
    "wof:placetype":"venue"
},
  "geometry": {"coordinates":[9.6316671371,45.6940994263],"type":"Point"}
}