{
  "type": "Feature",
  "properties": {
    "addr:full":"50123 Firenze Firenze Firenze 50123",
    "addr:postcode":"50123;50123",
    "iso:country":"IT",
    "sg:address":"50123 Firenze",
    "sg:city":"Firenze",
    "sg:orig_category":"Elettronica Professionale E Di Consumo. Forniture Per Il Settore Dello Spettacolo. Automazione E Macchine Per Ufficio. Forniture Per Congressi, Fiere E Manifestazioni",
    "sg:phone":"+39 055 287082",
    "sg:postcode":"50123",
    "sg:province":"Firenze",
    "sg:website":"http://www.tecnoconference.it",
    "wof:name":"Tecnoconference Srl",
    "wof:placetype":"venue"
},
  "geometry": {"coordinates":[11.250348,43.77903],"type":"Point"}
}