{
  "type": "Feature",
  "properties": {
    "iso:country":"IT",
    "sg:address":"10155 Torino",
    "sg:city":"Torino",
    "sg:orig_category":"Tessuti E Stoffe. Tessuti Arredamento, Tende E Tappeti",
    "sg:phone":"+39 011 812 7801",
    "sg:postcode":"10155",
    "sg:province":"Torino",
    "sg:website":"http://www.avigdor.it",
    "wof:name":"Avigdor Spa",
    "wof:placetype":"venue"
},
  "geometry": {"coordinates":[7.530517,45.013672],"type":"Point"}
}