{
  "type": "Feature",
  "properties": {
    "addr:full":"56/58, V. Roma 09040 Serdiana Serdiana Cagliari 09040",
    "addr:housenumber":"56 / 58 v.",
    "addr:postcode":"09040;09040",
    "addr:street":"Roma",
    "iso:country":"IT",
    "sg:address":"56/58, V. Roma 09040 Serdiana",
    "sg:city":"Serdiana",
    "sg:classifiers":[
        {
            "category":"Food & Beverages",
            "subcategory":"Groceries & Convenience Stores",
            "type":"Retail Goods"
        }
    ],
    "sg:phone":"+39 39070740606",
    "sg:postcode":"09040",
    "sg:province":"Cagliari",
    "sg:tags":[
        "drink"
    ],
    "sg:website":"http://www.cantine-argiolas.it:ws_end: :mark:ws:http://www.paginegialle.it/cantineargiolas",
    "wof:name":"Argiolas Spa",
    "wof:placetype":"venue"
},
  "geometry": {"coordinates":[9.156958,39.372047],"type":"Point"}
}