{
  "type": "Feature",
  "properties": {
    "iso:country":"IT",
    "sg:address":"41042 Fiorano Modenese",
    "sg:city":"Fiorano Modenese",
    "sg:orig_category":"Ceramiche Per Pavimenti E Rivestimenti - Produzione E Ingrosso",
    "sg:phone":"+39 0536 816311",
    "sg:postcode":"41042",
    "sg:province":"Modena",
    "sg:website":"http://www.edilgres-sirio.it",
    "wof:name":"Edilgres Sirio Industrie Fincuoghi Spa",
    "wof:placetype":"venue"
},
  "geometry": {"coordinates":[10.821133,44.550541],"type":"Point"}
}