{
  "type": "Feature",
  "properties": {
    "addr:full":"40050 Monteveglio Monteveglio Bologna 40050",
    "addr:postcode":"40050;40050",
    "iso:country":"IT",
    "sg:address":"40050 Monteveglio",
    "sg:city":"Monteveglio",
    "sg:orig_category":"Forniture Uffici",
    "sg:phone":"+39 051 960670",
    "sg:postcode":"40050",
    "sg:province":"Bologna",
    "wof:name":"A.c.t. Srl",
    "wof:placetype":"venue"
},
  "geometry": {"coordinates":[11.1018733978,44.4716682434],"type":"Point"}
}