{
  "type": "Feature",
  "properties": {
    "iso:country":"IT",
    "sg:address":"47023 Cesena",
    "sg:city":"Cesena",
    "sg:orig_category":"Elettronica Professionale E Di Consumo. Musica. Accessori Dei Mezzi Di Trasporto",
    "sg:phone":"+39 0547 384070",
    "sg:postcode":"47023",
    "sg:province":"Forl\u00ec-Cesena",
    "wof:name":"E.m.e. Snc",
    "wof:placetype":"venue"
},
  "geometry": {"coordinates":[12.139989,44.181221],"type":"Point"}
}