{
  "type": "Feature",
  "properties": {
    "addr:full":"25075 Nave Nave Brescia 25075",
    "addr:postcode":"25075;25075",
    "iso:country":"IT",
    "sg:address":"25075 Nave",
    "sg:city":"Nave",
    "sg:orig_category":"Marmo, Pietre Ed Affini",
    "sg:phone":"+39 030 253 0051",
    "sg:postcode":"25075",
    "sg:province":"Brescia",
    "wof:name":"Granit Marmi Snc Di Bresciani & C.",
    "wof:placetype":"venue"
},
  "geometry": {"coordinates":[10.297388,45.581795],"type":"Point"}
}