{
  "type": "Feature",
  "properties": {
    "addr:full":"65/67, Via Per Solbiate 21040 Oggiona Con Santo Stefano Oggiona Varese 21040",
    "addr:housenumber":"65 / 67",
    "addr:postcode":"21040;21040",
    "addr:street":"Via Per Solbiate",
    "iso:country":"IT",
    "sg:address":"65/67, Via Per Solbiate 21040 Oggiona Con Santo Stefano",
    "sg:city":"Oggiona",
    "sg:classifiers":[
        {
            "category":"Manufacturing",
            "subcategory":"Metals",
            "type":"Manufacturing & Wholesale Goods"
        }
    ],
    "sg:phone":"+39 0331 735398",
    "sg:postcode":"21040",
    "sg:province":"Varese",
    "sg:tags":[
        "processing"
    ],
    "wof:name":"Marini Pulitura Metalli S.n.c.",
    "wof:placetype":"venue"
},
  "geometry": {"coordinates":[8.8129358292,45.7076835632],"type":"Point"}
}