{
  "type": "Feature",
  "properties": {
    "iso:country":"IT",
    "sg:address":"103, Via Lecce 73010 Surbo",
    "sg:city":"Lecce",
    "sg:classifiers":[
        {
            "category":"Real Estate",
            "subcategory":"Architect",
            "type":"Services"
        }
    ],
    "sg:phone":"+39 0832 363032",
    "sg:postcode":"73010",
    "sg:province":"Lecce",
    "sg:tags":[
        "textile",
        "clothing"
    ],
    "wof:name":"Lucy Mode S.r.l.",
    "wof:placetype":"venue"
},
  "geometry": {"coordinates":[18.132048,40.389877],"type":"Point"}
}