{
  "type": "Feature",
  "properties": {
    "addr:full":"35010 Villanova Di Camposampiero Villanova Padova 35010",
    "addr:postcode":"35010;35010",
    "iso:country":"IT",
    "sg:address":"35010 Villanova Di Camposampiero",
    "sg:city":"Villanova",
    "sg:orig_category":"Macchine, Impianti Ed Attrezzature Per Agricoltura E Zootecnia",
    "sg:phone":"+39 049 922 0355",
    "sg:postcode":"35010",
    "sg:province":"Padova",
    "wof:name":"Frascati Verginio",
    "wof:placetype":"venue"
},
  "geometry": {"coordinates":[11.9159,45.467968],"type":"Point"}
}