{
  "type": "Feature",
  "properties": {
    "iso:country":"IT",
    "sg:address":"00184 Roma",
    "sg:city":"Roma",
    "sg:orig_category":"Automobili E Mezzi Di Trasporto",
    "sg:phone":"+39 06 709 6362",
    "sg:postcode":"00184",
    "sg:province":"Roma",
    "wof:name":"Anzano Angelo",
    "wof:placetype":"venue"
},
  "geometry": {"coordinates":[12.495102,41.888779],"type":"Point"}
}