{
  "type": "Feature",
  "properties": {
    "addr:full":"Guano Lucca Lucca 55100",
    "addr:postcode":"55100",
    "iso:country":"IT",
    "sg:address":"Guano",
    "sg:city":"Lucca",
    "sg:orig_category":"Christmas Tree Ornaments, Brass",
    "sg:phone":"+39 0583 403430",
    "sg:postcode":"55100",
    "sg:province":"Lucca",
    "sg:website":"www.ilrustico.it",
    "wof:name":"Il Rustico Spa",
    "wof:placetype":"venue"
},
  "geometry": {"coordinates":[10.5062,43.837399],"type":"Point"}
}