{
  "type": "Feature",
  "properties": {
    "iso:country":"IT",
    "sg:address":"04100 Latina",
    "sg:city":"Latina",
    "sg:orig_category":"Pompe. Apparecchiature E Sistemi Per Imballaggio E Confezionamento",
    "sg:phone":"+39 0773 241836",
    "sg:postcode":"04100",
    "sg:province":"Latina",
    "wof:name":"Prominent Italiana S.r.l.",
    "wof:placetype":"venue"
},
  "geometry": {"coordinates":[12.9250411987,41.4622764587],"type":"Point"}
}