{
  "type": "Feature",
  "properties": {
    "addr:full":"1, Via Unita' D'italia 28100 Novara Novara Novara 28100",
    "addr:postcode":"28100;28100",
    "addr:street":"Via Unita ' D'Italia",
    "iso:country":"IT",
    "sg:address":"1, Via Unita' D'italia 28100 Novara",
    "sg:city":"Novara",
    "sg:classifiers":[
        {
            "category":"Shopping",
            "type":"Retail Goods"
        }
    ],
    "sg:phone":"+39 0321 473351",
    "sg:postcode":"28100",
    "sg:province":"Novara",
    "sg:tags":[
        "finished",
        "-",
        "metallic"
    ],
    "wof:name":"Rubinetterie Stella (s.p.a.)",
    "wof:placetype":"venue"
},
  "geometry": {"coordinates":[8.625582695,45.4603118896],"type":"Point"}
}