{
  "type": "Feature",
  "properties": {
    "addr:full":"83029 Solofra Solofra Avellino 83029",
    "addr:postcode":"83029;83029",
    "iso:country":"IT",
    "sg:address":"83029 Solofra",
    "sg:city":"Solofra",
    "sg:orig_category":"Agenzie Ed Enti Turistici. Consulenze Tecniche, Amministrative E Perizie",
    "sg:phone":"+39 0825 536060",
    "sg:postcode":"83029",
    "sg:province":"Avellino",
    "wof:name":"Planisfero Srl",
    "wof:placetype":"venue"
},
  "geometry": {"coordinates":[14.829493,40.838696],"type":"Point"}
}