{
  "type": "Feature",
  "properties": {
    "iso:country":"IT",
    "sg:address":"36030 Villaverla",
    "sg:city":"Villaverla",
    "sg:orig_category":"Alimentare E Conserviera Industria - Macchine",
    "sg:phone":"+39 0445 350250",
    "sg:postcode":"36030",
    "sg:province":"Vicenza",
    "wof:name":"La Prestigiosa Srl",
    "wof:placetype":"venue"
},
  "geometry": {"coordinates":[11.567254,45.60717],"type":"Point"}
}