{
  "type": "Feature",
  "properties": {
    "addr:full":"6, Via Cherubini Francesco 20145 Milano Milano Milano 20145",
    "addr:postcode":"20145;20145",
    "addr:street":"Via Cherubini Francesco",
    "iso:country":"IT",
    "sg:address":"6, Via Cherubini Francesco 20145 Milano",
    "sg:city":"Milano",
    "sg:classifiers":[
        {
            "category":"Professional",
            "subcategory":"Advertising",
            "type":"Services"
        }
    ],
    "sg:phone":"+39 02 4801 4945",
    "sg:postcode":"20145",
    "sg:province":"Milano",
    "sg:tags":[
        "communication",
        "medium"
    ],
    "wof:name":"Angelicum Film Srl",
    "wof:placetype":"venue"
},
  "geometry": {"coordinates":[9.159645,45.46703],"type":"Point"}
}