{
  "type": "Feature",
  "properties": {
    "addr:full":"70122 Bari Bari Bari 70122",
    "addr:postcode":"70122;70122",
    "iso:country":"IT",
    "sg:address":"70122 Bari",
    "sg:city":"Bari",
    "sg:orig_category":"Servizi Per Aziende, Manifestazioni E Supporto Agli Scambi Commerciali",
    "sg:phone":"+39 080 521 2769",
    "sg:postcode":"70122",
    "sg:province":"Bari",
    "wof:name":"Ap Investigazioni Di A. Piepoli",
    "wof:placetype":"venue"
},
  "geometry": {"coordinates":[16.864901,41.123745],"type":"Point"}
}