{
  "type": "Feature",
  "properties": {
    "addr:full":"24/b, Via Caduti Del Lavoro 60131 Ancona Ancona Ancona 60131",
    "addr:housenumber":"24 / b",
    "addr:postcode":"60131;60131",
    "addr:street":"Via Caduti Del Lavoro",
    "iso:country":"IT",
    "sg:address":"24/b, Via Caduti Del Lavoro 60131 Ancona",
    "sg:city":"Ancona",
    "sg:classifiers":[
        {
            "category":"Manufacturing",
            "subcategory":"Metals",
            "type":"Manufacturing & Wholesale Goods"
        }
    ],
    "sg:phone":"+39 071 286 1464",
    "sg:postcode":"60131",
    "sg:province":"Ancona",
    "sg:tags":[
        "metallurgy",
        "metalworking"
    ],
    "wof:name":"Vuesse S.r.l.",
    "wof:placetype":"venue"
},
  "geometry": {"coordinates":[13.5187568665,43.6158561707],"type":"Point"}
}