{
  "type": "Feature",
  "properties": {
    "iso:country":"IT",
    "sg:address":"3, Via Marconi 40011 Anzola Dell'emilia",
    "sg:classifiers":[
        {
            "category":"Professional",
            "subcategory":"Engineering",
            "type":"Services"
        }
    ],
    "sg:phone":"+39 39051732652",
    "sg:postcode":"40011",
    "sg:province":"Bologna",
    "sg:tags":[
        "machine",
        "-",
        "mechanical"
    ],
    "wof:name":"Emanuel S.r.l.",
    "wof:placetype":"venue"
},
  "geometry": {"coordinates":[11.222641,44.490631],"type":"Point"}
}