{
  "type": "Feature",
  "properties": {
    "iso:country":"IT",
    "sg:address":"Via Dell' Aeronautica 7 24035 Curno",
    "sg:city":"Curno",
    "sg:classifiers":[
        {
            "category":"Manufacturing",
            "subcategory":"Musical Instruments",
            "type":"Manufacturing & Wholesale Goods"
        }
    ],
    "sg:phone":"+39 035 612023",
    "sg:postcode":"24035",
    "sg:province":"Bergamo",
    "sg:tags":[
        "instruments",
        "drawing"
    ],
    "sg:website":"www.morgantino.it",
    "wof:name":"Morgantina Snc Di Puccio & Pesenti",
    "wof:placetype":"venue"
},
  "geometry": {"coordinates":[9.61878,45.693779],"type":"Point"}
}