{
  "type": "Feature",
  "properties": {
    "iso:country":"IT",
    "sg:address":"Via Papini Giovanni 12/a 40128 Bologna",
    "sg:city":"Bologna",
    "sg:classifiers":[
        {
            "category":"Banks & Credit Unions",
            "subcategory":"Investment Brokerage",
            "type":"Services"
        }
    ],
    "sg:phone":"+39 051 322188",
    "sg:postcode":"40128",
    "sg:province":"Bologna",
    "sg:tags":[
        "door",
        "panel"
    ],
    "sg:website":"www.plastinds.com",
    "wof:name":"Plastind's Co. Srl",
    "wof:placetype":"venue"
},
  "geometry": {"coordinates":[11.346481,44.494221],"type":"Point"}
}