{
  "type": "Feature",
  "properties": {
    "addr:full":"90134 Palermo Palermo Palermo 90134",
    "addr:postcode":"90134;90134",
    "iso:country":"IT",
    "sg:address":"90134 Palermo",
    "sg:city":"Palermo",
    "sg:orig_category":"Forniture Per Abbigliamento E Pelletterie",
    "sg:phone":"+39 091 583523",
    "sg:postcode":"90134",
    "sg:province":"Palermo",
    "wof:name":"Sciacchitano Ferdinando",
    "wof:placetype":"venue"
},
  "geometry": {"coordinates":[13.3572845459,38.1138877869],"type":"Point"}
}