{
  "type": "Feature",
  "properties": {
    "iso:country":"IT",
    "sg:address":"10143 Torino",
    "sg:city":"Torino",
    "sg:orig_category":"Valvole E Apparecchiature Di Misura",
    "sg:phone":"+39 011 740932",
    "sg:postcode":"10143",
    "sg:province":"Torino",
    "wof:name":"La.s.a.t.",
    "wof:placetype":"venue"
},
  "geometry": {"coordinates":[7.652743,45.081829],"type":"Point"}
}