{
  "type": "Feature",
  "properties": {
    "iso:country":"IT",
    "sg:address":"S. S. 131, Km 62 09095 Mogoro",
    "sg:city":"Mogoro",
    "sg:classifiers":[
        {
            "category":"Food & Beverages",
            "subcategory":"Liquor & Beverages",
            "type":"Retail Goods"
        }
    ],
    "sg:phone":"+39 0783 990285",
    "sg:postcode":"09095",
    "sg:province":"Oristano",
    "sg:tags":[
        "wine",
        "italian"
    ],
    "wof:name":"Societa' Cooperativa Cantina Sociale Il Nuraghe Arl",
    "wof:placetype":"venue"
},
  "geometry": {"coordinates":[8.596333,39.905273],"type":"Point"}
}