{
  "type": "Feature",
  "properties": {
    "iso:country":"IT",
    "sg:address":"Via Roma 48; Domegge Di Cadore; 32040",
    "sg:city":"Domegge di Cadore",
    "sg:classifiers":[
        {
            "category":"Banks & Credit Unions",
            "subcategory":"Bank",
            "type":"Services"
        }
    ],
    "sg:phone":"+39 0435 520016",
    "sg:postcode":"32040",
    "sg:province":"Belluno",
    "wof:name":"Banca Popolare Dell'alto Adige",
    "wof:placetype":"venue"
},
  "geometry": {"coordinates":[12.416532,46.460426],"type":"Point"}
}