{
  "type": "Feature",
  "properties": {
    "iso:country":"IT",
    "sg:address":"00148 Roma",
    "sg:city":"Roma",
    "sg:orig_category":"Magazzinaggio E Logistica Industriale - Servizio Conto Terzi",
    "sg:phone":"+39 06 653 3228",
    "sg:postcode":"00148",
    "sg:province":"Roma",
    "sg:website":"http://www.brumat.it",
    "wof:name":"Brumat & Co. Srl",
    "wof:placetype":"venue"
},
  "geometry": {"coordinates":[12.436018,41.829967],"type":"Point"}
}