{
  "type": "Feature",
  "properties": {
    "iso:country":"IT",
    "sg:address":"50145 Firenze",
    "sg:city":"Firenze",
    "sg:orig_category":"Gioielleria, Oreficeria E Argenteria",
    "sg:phone":"+39 055 310519",
    "sg:postcode":"50145",
    "sg:province":"Firenze",
    "wof:name":"Foglia Argenteria",
    "wof:placetype":"venue"
},
  "geometry": {"coordinates":[11.163575,43.793423],"type":"Point"}
}