{
  "type": "Feature",
  "properties": {
    "addr:full":"V. Delle Caserme 65127 Pescara Pescara Pescara 65127",
    "addr:postcode":"65127;65127",
    "addr:street":"V. Delle Caserme",
    "iso:country":"IT",
    "sg:address":"V. Delle Caserme 65127 Pescara",
    "sg:city":"Pescara",
    "sg:orig_category":"Miscellaneous Products",
    "sg:phone":"+39 39085690333",
    "sg:postcode":"65127",
    "sg:province":"Pescara",
    "sg:website":"http://www.deflorentiis.it",
    "wof:name":"De Florentiis Dei Fratelli De Florentiis Snc",
    "wof:placetype":"venue"
},
  "geometry": {"coordinates":[14.2123527527,42.4616508484],"type":"Point"}
}