{
  "type": "Feature",
  "properties": {
    "iso:country":"IT",
    "sg:address":"66, Via Cesare Battisti 12030 Caramagna Piemonte",
    "sg:city":"Caramagna Piemonte",
    "sg:classifiers":[
        {
            "category":"Manufacturing",
            "subcategory":"Metals",
            "type":"Manufacturing & Wholesale Goods"
        }
    ],
    "sg:phone":"+39 39017289062",
    "sg:postcode":"12030",
    "sg:province":"Cuneo",
    "sg:tags":[
        "processing"
    ],
    "wof:name":"Golden Car Di Festa A. & C. (s.r.l.)",
    "wof:placetype":"venue"
},
  "geometry": {"coordinates":[7.7363796234,44.7822952271],"type":"Point"}
}