{
  "type": "Feature",
  "properties": {
    "iso:country":"IT",
    "sg:address":"28100 Novara",
    "sg:city":"Novara",
    "sg:orig_category":"Formaggi E Latticini - Produzione E Ingrosso",
    "sg:phone":"+39 0321 691890",
    "sg:postcode":"28100",
    "sg:province":"Novara",
    "wof:name":"Invernizzi Gisberto Francesco E Figlia Srl",
    "wof:placetype":"venue"
},
  "geometry": {"coordinates":[8.63671875,45.4545211792],"type":"Point"}
}