{
  "type": "Feature",
  "properties": {
    "addr:full":"36014 Santorso Santorso Vicenza 36014",
    "addr:postcode":"36014;36014",
    "iso:country":"IT",
    "sg:address":"36014 Santorso",
    "sg:city":"Santorso",
    "sg:orig_category":"Macchine E Forniture Per Ecologia E Smaltimento Rifiuti",
    "sg:phone":"+39 0445 540232",
    "sg:postcode":"36014",
    "sg:province":"Vicenza",
    "wof:name":"Seital Srl",
    "wof:placetype":"venue"
},
  "geometry": {"coordinates":[11.390187,45.724678],"type":"Point"}
}