{
  "type": "Feature",
  "properties": {
    "addr:full":"Via Lombroso Cesare 54 20137 Milano Milano Milano 20137",
    "addr:housenumber":"54",
    "addr:postcode":"20137;20137",
    "addr:street":"Via Lombroso Cesare",
    "iso:country":"IT",
    "sg:address":"Via Lombroso Cesare 54 20137 Milano",
    "sg:city":"Milano",
    "sg:classifiers":[
        {
            "category":"Food & Beverages",
            "subcategory":"Fruits & Vegetables",
            "type":"Retail Goods"
        }
    ],
    "sg:phone":"+39 02 5501 5888",
    "sg:postcode":"20137",
    "sg:province":"Milano",
    "sg:website":"www.sintal.it",
    "wof:name":"Sintal Srl",
    "wof:placetype":"venue"
},
  "geometry": {"coordinates":[9.2032260895,45.4824676514],"type":"Point"}
}