{
  "type": "Feature",
  "properties": {
    "addr:full":"19038 Sarzana Sarzana La Spezia 19038",
    "addr:postcode":"19038;19038",
    "iso:country":"IT",
    "sg:address":"19038 Sarzana",
    "sg:city":"Sarzana",
    "sg:orig_category":"Lucidatura, Laccatura E Verniciatura Mobili",
    "sg:phone":"+39 338 598 5550",
    "sg:postcode":"19038",
    "sg:province":"La Spezia",
    "wof:name":"Badiale Alessandro",
    "wof:placetype":"venue"
},
  "geometry": {"coordinates":[9.844668,44.121727],"type":"Point"}
}