{
  "type": "Feature",
  "properties": {
    "iso:country":"IT",
    "sg:address":"10155 Torino",
    "sg:city":"Torino",
    "sg:orig_category":"Marketing E Ricerche Di Mercato",
    "sg:phone":"+39 011 24561",
    "sg:postcode":"10155",
    "sg:province":"Torino",
    "sg:website":"http://www.rmctorino.com",
    "wof:name":"R.m.c. Ricerca Marketing Comunicazione Srl",
    "wof:placetype":"venue"
},
  "geometry": {"coordinates":[7.682322,45.089886],"type":"Point"}
}