{
  "type": "Feature",
  "properties": {
    "iso:country":"IT",
    "sg:address":"Via S. Croce 165 47032 Capocolle",
    "sg:city":"Capocolle",
    "sg:classifiers":[
        {
            "category":"Communications",
            "subcategory":"Film & Video Production",
            "type":"Services"
        }
    ],
    "sg:phone":"+39 0543 449019",
    "sg:postcode":"47032",
    "sg:province":"Forl\u00ec-Cesena",
    "sg:tags":[
        "windows",
        "window",
        "roof",
        "dormer"
    ],
    "sg:website":"www.wierer.it",
    "wof:name":"Lafarge Roofing Spa",
    "wof:placetype":"venue"
},
  "geometry": {"coordinates":[12.175734,44.188656],"type":"Point"}
}