{
  "type": "Feature",
  "properties": {
    "iso:country":"IT",
    "sg:address":"89012 Delianuova",
    "sg:city":"Delianuova",
    "sg:orig_category":"Medicinali E Prodotti Parafarmaceutici. Prodotti Cosmetici E Da Toeletta",
    "sg:phone":"+39 0966 963914",
    "sg:postcode":"89012",
    "sg:province":"Reggio Di Calabria",
    "wof:name":"Api Reggina Soc.coop.r.l.",
    "wof:placetype":"venue"
},
  "geometry": {"coordinates":[15.6501369476,38.1146888733],"type":"Point"}
}