{
  "type": "Feature",
  "properties": {
    "addr:full":"98, Via S. Martino 28066 Galliate Galliate Novara 28066",
    "addr:postcode":"28066;28066",
    "addr:street":"Via S. Martino",
    "iso:country":"IT",
    "sg:address":"98, Via S. Martino 28066 Galliate",
    "sg:city":"Galliate",
    "sg:classifiers":[
        {
            "category":"Shopping",
            "subcategory":"Crafts & Fabrics",
            "type":"Retail Goods"
        }
    ],
    "sg:phone":"+39 0321 861331",
    "sg:postcode":"28066",
    "sg:province":"Novara",
    "wof:name":"Tessitura Belletti (s.p.a.)",
    "wof:placetype":"venue"
},
  "geometry": {"coordinates":[8.7047576904,45.4803848267],"type":"Point"}
}