{
  "type": "Feature",
  "properties": {
    "addr:full":"13, V. O. Raimondo 00173 Roma Roma Roma 00173",
    "addr:housenumber":"13",
    "addr:postcode":"00173;00173",
    "addr:street":"V. O. Raimondo",
    "iso:country":"IT",
    "sg:address":"13, V. O. Raimondo 00173 Roma",
    "sg:city":"Roma",
    "sg:classifiers":[
        {
            "category":"Manufacturing",
            "subcategory":"Metals",
            "type":"Manufacturing & Wholesale Goods"
        }
    ],
    "sg:phone":"+39 067235383835",
    "sg:postcode":"00173",
    "sg:province":"Roma",
    "sg:tags":[
        "metallurgy",
        "metalworking"
    ],
    "sg:website":"http://www.comi-tec.it",
    "wof:name":"Comitec Sas",
    "wof:placetype":"venue"
},
  "geometry": {"coordinates":[12.5979623795,41.849445343],"type":"Point"}
}