{
  "type": "Feature",
  "properties": {
    "iso:country":"IT",
    "sg:address":"Via Privata Angelo Pasin 1 20090 Buccinasco",
    "sg:city":"Buccinasco",
    "sg:classifiers":[
        {
            "category":"Building & Trades",
            "subcategory":"Construction",
            "type":"Services"
        }
    ],
    "sg:phone":"+39 02 447 1186",
    "sg:postcode":"20090",
    "sg:province":"Milano",
    "sg:tags":[
        "granite",
        "working"
    ],
    "wof:name":"Fratelli Pasin Sas",
    "wof:placetype":"venue"
},
  "geometry": {"coordinates":[9.188141,45.463688],"type":"Point"}
}