{
  "type": "Feature",
  "properties": {
    "iso:country":"IT",
    "sg:address":"1, Piazza S. Maria Beltrade 20123 Milano",
    "sg:city":"Milano",
    "sg:classifiers":[
        {
            "category":"Manufacturing",
            "subcategory":"Glass & Minerals",
            "type":"Manufacturing & Wholesale Goods"
        }
    ],
    "sg:phone":"+39 02 7200 3303",
    "sg:postcode":"20123",
    "sg:province":"Milano",
    "wof:name":"Salmoiraghi & Vigano' Spa",
    "wof:placetype":"venue"
},
  "geometry": {"coordinates":[9.186563,45.462772],"type":"Point"}
}