{
  "type": "Feature",
  "properties": {
    "iso:country":"IT",
    "sg:address":"35028 Piove Di Sacco",
    "sg:city":"Piove di Sacco",
    "sg:orig_category":"Macchine, Impianti Ed Attrezzature Per Industria Alimentare E Bevande. Elettrodomestici. Macchine E Impianti Per Attivita' Commerciali Ed Artigianali",
    "sg:phone":"+39 049 970 4330",
    "sg:postcode":"35028",
    "sg:province":"Padova",
    "wof:name":"Mezzalana Snc",
    "wof:placetype":"venue"
},
  "geometry": {"coordinates":[12.057671,45.291767],"type":"Point"}
}