{
  "type": "Feature",
  "properties": {
    "iso:country":"IT",
    "sg:address":"20144 Milano",
    "sg:city":"Milano",
    "sg:orig_category":"Impianti, Attrezzature E Forniture Sanitarie Ed Ospedaliere",
    "sg:phone":"+39 02 498 4771",
    "sg:postcode":"20144",
    "sg:province":"Milano",
    "wof:name":"Ravelli S.p.a.",
    "wof:placetype":"venue"
},
  "geometry": {"coordinates":[9.164237,45.457462],"type":"Point"}
}