{
  "type": "Feature",
  "properties": {
    "iso:country":"IT",
    "sg:address":"66, Via Per Montorfano 22032 Albese Con Cassano",
    "sg:city":"Albese con Cassano",
    "sg:classifiers":[
        {
            "category":"Sports & Exercise",
            "subcategory":"Playing Field",
            "type":"Entertainment"
        }
    ],
    "sg:phone":"+39 39031428125",
    "sg:postcode":"22032",
    "sg:province":"Como",
    "sg:tags":[
        "game"
    ],
    "wof:name":"Italbaby Srl",
    "wof:placetype":"venue"
},
  "geometry": {"coordinates":[9.137424,45.77002],"type":"Point"}
}