{
  "type": "Feature",
  "properties": {
    "iso:country":"IT",
    "sg:address":"Via Comolli 15 21051 Arcisate",
    "sg:city":"Arcisate",
    "sg:classifiers":[
        {
            "category":"Ice Cream",
            "type":"Food & Drink"
        }
    ],
    "sg:phone":"+39 0332 475200",
    "sg:postcode":"21051",
    "sg:province":"Varese",
    "sg:tags":[
        "beverages",
        "alcoholic"
    ],
    "wof:name":"T & C Varese Srl",
    "wof:placetype":"venue"
},
  "geometry": {"coordinates":[8.882912,45.860378],"type":"Point"}
}