{
  "type": "Feature",
  "properties": {
    "iso:country":"IT",
    "sg:address":"43, Via Toscana 56035 Lari",
    "sg:city":"Lari",
    "sg:classifiers":[
        {
            "category":"Home & Garden",
            "subcategory":"Home Furnishings",
            "type":"Retail Goods"
        }
    ],
    "sg:phone":"+39 0587 616271",
    "sg:postcode":"56035",
    "sg:province":"Pisa",
    "sg:tags":[
        "household"
    ],
    "wof:name":"S.t.m. S.r.l.",
    "wof:placetype":"venue"
},
  "geometry": {"coordinates":[10.5847,43.587799],"type":"Point"}
}