{
  "type": "Feature",
  "properties": {
    "iso:country":"IT",
    "sg:address":"98122 Messina",
    "sg:city":"Messina",
    "sg:orig_category":"Macchine, Impianti Ed Attrezzature Per Industria Alimentare E Bevande",
    "sg:phone":"+39 090 671337",
    "sg:postcode":"98122",
    "sg:province":"Messina",
    "wof:name":"Cieffe S.r.l.",
    "wof:placetype":"venue"
},
  "geometry": {"coordinates":[15.548932,38.190598],"type":"Point"}
}