{
  "type": "Feature",
  "properties": {
    "iso:country":"IT",
    "sg:address":"12, Via Tiberio Claudio Felice 84131 Salerno",
    "sg:city":"Salerno",
    "sg:classifiers":[
        {
            "category":"Sports & Exercise",
            "subcategory":"Playing Field",
            "type":"Entertainment"
        }
    ],
    "sg:phone":"+39 39089301072",
    "sg:postcode":"84131",
    "sg:province":"Salerno",
    "sg:tags":[
        "game"
    ],
    "wof:name":"Centro Restauri Gallo G. E Fiorillo V. Snc",
    "wof:placetype":"venue"
},
  "geometry": {"coordinates":[14.845303,40.640366],"type":"Point"}
}