{
  "type": "Feature",
  "properties": {
    "iso:country":"IT",
    "sg:address":"3, V. Pastore 20056 Trezzo Sull'adda",
    "sg:classifiers":[
        {
            "category":"Wholesale",
            "subcategory":"Drugs",
            "type":"Manufacturing & Wholesale Goods"
        }
    ],
    "sg:phone":"+39 390 290 9941",
    "sg:postcode":"20056",
    "sg:province":"Milano",
    "sg:tags":[
        "chemical",
        "pharmaceutical"
    ],
    "sg:website":"http://www.respharma.com",
    "wof:name":"Res Pharma Srl",
    "wof:placetype":"venue"
},
  "geometry": {"coordinates":[9.508074,45.593475],"type":"Point"}
}