{
  "type": "Feature",
  "properties": {
    "iso:country":"IT",
    "sg:address":"20010 Pogliano Milanese",
    "sg:city":"Pogliano Milanese",
    "sg:orig_category":"Apparecchiature E Sistemi Per Imballaggio E Confezionamento",
    "sg:phone":"+39 02 9354 9442",
    "sg:postcode":"20010",
    "sg:province":"Milano",
    "wof:name":"Italdibipack Center Srl",
    "wof:placetype":"venue"
},
  "geometry": {"coordinates":[9.018787,45.510147],"type":"Point"}
}