{
  "type": "Feature",
  "properties": {
    "iso:country":"IT",
    "sg:address":"33078 San Vito Al Tagliamento",
    "sg:city":"San Vito al Tagliamento",
    "sg:classifiers":[
        {
            "category":"Health Services",
            "subcategory":"Health Practitioner",
            "type":"Services"
        }
    ],
    "sg:phone":"+39 0434 81464",
    "sg:postcode":"33078",
    "sg:province":"Pordenone",
    "sg:tags":[
        "medici"
    ],
    "wof:name":"Plaino Dr. Renzo Amb. Plaino Dott. Renzo",
    "wof:placetype":"venue"
},
  "geometry": {"coordinates":[12.8547544479,45.9147911072],"type":"Point"}
}