{
  "type": "Feature",
  "properties": {
    "iso:country":"IT",
    "sg:address":"92100 Agrigento",
    "sg:city":"Agrigento",
    "sg:orig_category":"Ristorazione E Locali Pubblici Affini. Ristoranti Ed Esercizi Affini. Servizi Ausiliari Di Ristorazione E Di Intrattenimento",
    "sg:phone":"+39 0922 403110",
    "sg:postcode":"92100",
    "sg:province":"Agrigento",
    "wof:name":"Ristorante Trattoria Dei Templi",
    "wof:placetype":"venue"
},
  "geometry": {"coordinates":[13.596735,37.299736],"type":"Point"}
}