{
  "type": "Feature",
  "properties": {
    "addr:full":"Via Torbiera 380 55054 Massarosa Massarosa Lucca 55054",
    "addr:housenumber":"380",
    "addr:postcode":"55054;55054",
    "addr:street":"Via Torbiera",
    "iso:country":"IT",
    "sg:address":"Via Torbiera 380 55054 Massarosa",
    "sg:city":"Massarosa",
    "sg:classifiers":[
        {
            "category":"Organizations",
            "subcategory":"Professional Association",
            "type":"Services"
        }
    ],
    "sg:phone":"+39 0584 940675",
    "sg:postcode":"55054",
    "sg:province":"Lucca",
    "sg:tags":[
        "preparation",
        "sand",
        "gravel",
        "plant"
    ],
    "wof:name":"Cedital Srl",
    "wof:placetype":"venue"
},
  "geometry": {"coordinates":[10.507994,43.843014],"type":"Point"}
}