{
  "type": "Feature",
  "properties": {
    "addr:full":"30125 Venezia Venezia Venezia 30125",
    "addr:postcode":"30125;30125",
    "iso:country":"IT",
    "sg:address":"30125 Venezia",
    "sg:city":"Venezia",
    "sg:orig_category":"Ricerca Scientifica - Istituti",
    "sg:phone":"+39 041 521 6811",
    "sg:postcode":"30125",
    "sg:province":"Venezia",
    "wof:name":"Istituto Per Lo Studio Della Dinamica E Delle Grandi Masse",
    "wof:placetype":"venue"
},
  "geometry": {"coordinates":[12.331525,45.437138],"type":"Point"}
}