{
  "type": "Feature",
  "properties": {
    "iso:country":"IT",
    "sg:address":"24064 Grumello Del Monte",
    "sg:city":"Grumello del Monte",
    "sg:orig_category":"Filati E Tessuti - Trattamenti",
    "sg:phone":"+39 035 830731",
    "sg:postcode":"24064",
    "sg:province":"Bergamo",
    "wof:name":"Ritorcitura F. Lli Rossi",
    "wof:placetype":"venue"
},
  "geometry": {"coordinates":[9.8727827072,45.6434020996],"type":"Point"}
}