{
  "type": "Feature",
  "properties": {
    "addr:full":"20145 Milano Milano Milano 20145",
    "addr:postcode":"20145;20145",
    "iso:country":"IT",
    "sg:address":"20145 Milano",
    "sg:city":"Milano",
    "sg:orig_category":"Pubblicita', Marketing E Comunicazione",
    "sg:phone":"+39 02 433403",
    "sg:postcode":"20145",
    "sg:province":"Milano",
    "wof:name":"C.l.p. (s.r.l.)",
    "wof:placetype":"venue"
},
  "geometry": {"coordinates":[9.1555433273,45.4711036682],"type":"Point"}
}