{
  "type": "Feature",
  "properties": {
    "iso:country":"IT",
    "sg:address":"35014 Fontaniva",
    "sg:city":"Fontaniva",
    "sg:orig_category":"Brunitura Metalli",
    "sg:phone":"+39 049 940 1254",
    "sg:postcode":"35014",
    "sg:province":"Padova",
    "wof:name":"Fabrigalvanica Snc",
    "wof:placetype":"venue"
},
  "geometry": {"coordinates":[11.779621,45.624577],"type":"Point"}
}