{
  "type": "Feature",
  "properties": {
    "addr:full":"Via Germania 3 35127 Padova Padova Padova 35127",
    "addr:housenumber":"3",
    "addr:postcode":"35127;35127",
    "addr:street":"Via Germania",
    "iso:country":"IT",
    "sg:address":"Via Germania 3 35127 Padova",
    "sg:city":"Padova",
    "sg:classifiers":[
        {
            "category":"Wholesale",
            "subcategory":"Plants",
            "type":"Manufacturing & Wholesale Goods"
        }
    ],
    "sg:phone":"+39 049 870 1420",
    "sg:postcode":"35127",
    "sg:province":"Padova",
    "sg:tags":[
        "machine",
        "industrial",
        "automation"
    ],
    "wof:name":"General Fluidi S.r.l.",
    "wof:placetype":"venue"
},
  "geometry": {"coordinates":[11.956558,45.39777],"type":"Point"}
}