{
  "type": "Feature",
  "properties": {
    "iso:country":"IT",
    "sg:address":"20147 Milano",
    "sg:city":"Milano",
    "sg:orig_category":"Scuole E Servizi Scolastici. Ricerca, Selezione E Formazione Del Personale. Pubblica Amministrazione",
    "sg:phone":"+39 02 412 1284",
    "sg:postcode":"20147",
    "sg:province":"Milano",
    "wof:name":"Liceo Scientifico Statale Guglielmo Marconi",
    "wof:placetype":"venue"
},
  "geometry": {"coordinates":[9.13341,45.450943],"type":"Point"}
}