{
  "type": "Feature",
  "properties": {
    "iso:country":"IT",
    "sg:address":"10149 Torino",
    "sg:city":"Torino",
    "sg:orig_category":"Climatizzazione E Condizionamento, Apparecchiature E Servizi",
    "sg:phone":"+39 011 739 7490",
    "sg:postcode":"10149",
    "sg:province":"Torino",
    "sg:website":"http://www.tecnoclima.it",
    "wof:name":"Tecnoclima Snc",
    "wof:placetype":"venue"
},
  "geometry": {"coordinates":[7.5468759537,44.9986000061],"type":"Point"}
}