{
  "type": "Feature",
  "properties": {
    "iso:country":"IT",
    "sg:address":"20159 Milano",
    "sg:city":"Milano",
    "sg:orig_category":"Agenzie D'affari E Servizi Commerciali",
    "sg:phone":"+39 02 689 6821",
    "sg:postcode":"20159",
    "sg:province":"Milano",
    "wof:name":"Sa.pie Caribe Srl",
    "wof:placetype":"venue"
},
  "geometry": {"coordinates":[9.189491,45.490356],"type":"Point"}
}