{
  "type": "Feature",
  "properties": {
    "iso:country":"IT",
    "sg:address":"Via Fernando Santi 15 20056 Trezzo Sull'adda",
    "sg:classifiers":[
        {
            "category":"Professional",
            "subcategory":"Printing & Photocopies",
            "type":"Services"
        }
    ],
    "sg:phone":"+39 02 9096 1300",
    "sg:postcode":"20056",
    "sg:province":"Milano",
    "sg:tags":[
        "paper"
    ],
    "wof:name":"Fabra Srl",
    "wof:placetype":"venue"
},
  "geometry": {"coordinates":[9.1881408691,45.4636878967],"type":"Point"}
}