{
  "type": "Feature",
  "properties": {
    "addr:full":"40128 Bologna Bologna Bologna 40128",
    "addr:postcode":"40128;40128",
    "iso:country":"IT",
    "sg:address":"40128 Bologna",
    "sg:city":"Bologna",
    "sg:orig_category":"Forniture Per Congressi, Fiere E Manifestazioni",
    "sg:phone":"+39 051 250700",
    "sg:postcode":"40128",
    "sg:province":"Bologna",
    "sg:website":"http://www.ocsaservice.it",
    "wof:name":"Ocsa Di Andriani Marcello",
    "wof:placetype":"venue"
},
  "geometry": {"coordinates":[11.3539113998,44.5042190552],"type":"Point"}
}