{
  "type": "Feature",
  "properties": {
    "iso:country":"IT",
    "sg:address":"00040 Larino",
    "sg:orig_category":"Bevande, Vini E Liquori. Agricoltura, Orticoltura E Floricoltura",
    "sg:phone":"+39 06 9649 8746",
    "sg:postcode":"00040",
    "sg:province":"Roma",
    "wof:name":"Casa Vinicola Carpineto",
    "wof:placetype":"venue"
},
  "geometry": {"coordinates":[12.776632,41.692722],"type":"Point"}
}