{
  "type": "Feature",
  "properties": {
    "iso:country":"IT",
    "sg:address":"20019 Settimo Milanese",
    "sg:city":"Settimo Milanese",
    "sg:orig_category":"Manufacturers: Prefabbricati",
    "sg:phone":"+39 02 4892 0088",
    "sg:postcode":"20019",
    "sg:province":"Milano",
    "wof:name":"Ovoidaltubi S.r.l.",
    "wof:placetype":"venue"
},
  "geometry": {"coordinates":[9.06771,45.466381],"type":"Point"}
}