{
  "type": "Feature",
  "properties": {
    "addr:full":"20020 Lainate Lainate Milano 20020",
    "addr:postcode":"20020;20020",
    "iso:country":"IT",
    "sg:address":"20020 Lainate",
    "sg:city":"Lainate",
    "sg:orig_category":"Macchine, Impianti Ed Attrezzature Per Industria Alimentare E Bevande. Elettrodomestici. Macchine E Impianti Per Attivita' Commerciali Ed Artigianali",
    "sg:phone":"+39 02 937 0856",
    "sg:postcode":"20020",
    "sg:province":"Milano",
    "wof:name":"A B M Company Srl",
    "wof:placetype":"venue"
},
  "geometry": {"coordinates":[9.017671,45.568913],"type":"Point"}
}