{
  "type": "Feature",
  "properties": {
    "iso:country":"IT",
    "sg:address":"95045 Misterbianco",
    "sg:city":"Misterbianco",
    "sg:orig_category":"Scuole E Servizi Scolastici. Servizi Ausiliari Dei Mezzi Di Trasporto. Ricerca, Selezione E Formazione Del Personale",
    "sg:phone":"+39 095 476290",
    "sg:postcode":"95045",
    "sg:province":"Catania",
    "wof:name":"Airone Srl",
    "wof:placetype":"venue"
},
  "geometry": {"coordinates":[15.039638,37.522762],"type":"Point"}
}