{
  "type": "Feature",
  "properties": {
    "addr:full":"80142 Napoli Napoli Napoli 80142",
    "addr:housenumber":"80142",
    "addr:postcode":"80142",
    "iso:country":"IT",
    "sg:address":"80142 Napoli",
    "sg:city":"Napoli",
    "sg:orig_category":"Serramenti Ed Infissi. Forniture Industriali Per Prevenzione, Controllo E Sicurezza",
    "sg:phone":"+39 081 553 4390",
    "sg:postcode":"80142",
    "sg:province":"Napoli",
    "wof:name":"Fabio D'angeli Dal 1900 L'arte Di Forgiare Il Ferro",
    "wof:placetype":"venue"
},
  "geometry": {"coordinates":[14.275831,40.847092],"type":"Point"}
}