{
  "type": "Feature",
  "properties": {
    "addr:full":"43013 Langhirano Langhirano Parma 43013",
    "addr:postcode":"43013;43013",
    "iso:country":"IT",
    "sg:address":"43013 Langhirano",
    "sg:city":"Langhirano",
    "sg:orig_category":"Lucidatura, Laccatura E Verniciatura Mobili",
    "sg:phone":"+39 0521 637591",
    "sg:postcode":"43013",
    "sg:province":"Parma",
    "wof:name":"Chiari Dino",
    "wof:placetype":"venue"
},
  "geometry": {"coordinates":[10.290889,44.683029],"type":"Point"}
}