{
  "type": "Feature",
  "properties": {
    "iso:country":"IT",
    "sg:address":"13043 Cigliano",
    "sg:city":"Cigliano",
    "sg:orig_category":"Impiantistica E Prodotti Tecnologici Per Edilizia. Serramenti Ed Infissi",
    "sg:phone":"+39 0161 423914",
    "sg:postcode":"13043",
    "sg:province":"Vercelli",
    "wof:name":"Emmevi Di D'efilippo Giovanni",
    "wof:placetype":"venue"
},
  "geometry": {"coordinates":[8.029381,45.310539],"type":"Point"}
}