{
  "type": "Feature",
  "properties": {
    "addr:full":"Via Mortella Z 62 66030 Poggiofiorito Poggiofiorito Chieti 66030",
    "addr:housenumber":"z 62",
    "addr:postcode":"66030;66030",
    "addr:street":"Via Mortella",
    "iso:country":"IT",
    "sg:address":"Via Mortella Z 62 66030 Poggiofiorito",
    "sg:city":"Poggiofiorito",
    "sg:classifiers":[
        {
            "category":"Wholesale",
            "subcategory":"Farm Supplies",
            "type":"Manufacturing & Wholesale Goods"
        }
    ],
    "sg:phone":"+39 0871 938850",
    "sg:postcode":"66030",
    "sg:province":"Chieti",
    "sg:tags":[
        "agricultural",
        "part",
        "spare",
        "machinery",
        "accessory"
    ],
    "sg:website":"www.leomarsrl.it",
    "wof:name":"Leomar S.r.l.",
    "wof:placetype":"venue"
},
  "geometry": {"coordinates":[14.167151,42.351791],"type":"Point"}
}