{
  "type": "Feature",
  "properties": {
    "addr:full":"35040 Masi Masi Padova 35040",
    "addr:postcode":"35040;35040",
    "iso:country":"IT",
    "sg:address":"35040 Masi",
    "sg:city":"Masi",
    "sg:orig_category":"Non-classified Establishments",
    "sg:phone":"+39 0425 51994",
    "sg:postcode":"35040",
    "sg:province":"Padova",
    "wof:name":"Fratelli Casarotti",
    "wof:placetype":"venue"
},
  "geometry": {"coordinates":[11.453396,45.126137],"type":"Point"}
}