{
  "type": "Feature",
  "properties": {
    "iso:country":"IT",
    "sg:address":"41100 Modena",
    "sg:city":"Modena",
    "sg:orig_category":"Manufacturers: Prefabbricati",
    "sg:phone":"+39 059 282761",
    "sg:postcode":"41100",
    "sg:province":"Modena",
    "sg:website":"http://www.commercio-modenese.com/mazzoni",
    "wof:name":"Mazzoni Marco & C. Snc",
    "wof:placetype":"venue"
},
  "geometry": {"coordinates":[10.91836,44.639408],"type":"Point"}
}