{
  "type": "Feature",
  "properties": {
    "iso:country":"IT",
    "sg:address":"20123 Milano",
    "sg:city":"Milano",
    "sg:classifiers":[
        {
            "category":"Professional",
            "subcategory":"Management & Consulting",
            "type":"Services"
        }
    ],
    "sg:phone":"+39 02 8940 0415",
    "sg:postcode":"20123",
    "sg:province":"Milano",
    "sg:tags":[
        "building",
        "industrial",
        "business",
        "consultants",
        "technical",
        "worker",
        "industry",
        "-",
        "civil",
        "consultant",
        "works"
    ],
    "wof:name":"Barbara Gnecchi Design",
    "wof:placetype":"venue"
},
  "geometry": {"coordinates":[9.174685,45.460003],"type":"Point"}
}