{
  "type": "Feature",
  "properties": {
    "iso:country":"IT",
    "sg:address":"11020 Donnas",
    "sg:city":"Donnas",
    "sg:orig_category":"Acciaierie E Fonderie",
    "sg:phone":"+39 0125 807179",
    "sg:postcode":"11020",
    "sg:province":"Aosta",
    "wof:name":"Siderurgica Ferrero Spa",
    "wof:placetype":"venue"
},
  "geometry": {"coordinates":[7.774363,45.602901],"type":"Point"}
}