{
  "type": "Feature",
  "properties": {
    "iso:country":"IT",
    "sg:address":"20063 Cernusco Naviglio",
    "sg:orig_category":"Arredamenti - Vendita Al Dettaglio",
    "sg:phone":"+39 02 924 5415",
    "sg:postcode":"20063",
    "sg:province":"Milano",
    "wof:name":"Guzzi Arredamenti Snc",
    "wof:placetype":"venue"
},
  "geometry": {"coordinates":[9.203141,45.433544],"type":"Point"}
}