{
  "type": "Feature",
  "properties": {
    "iso:country":"IT",
    "sg:address":"6, V. San Lazzaro40064 Ozzano Dell'emilia",
    "sg:classifiers":[
        {
            "category":"Food & Beverages",
            "subcategory":"Groceries & Convenience Stores",
            "type":"Retail Goods"
        }
    ],
    "sg:phone":"+39 051 499 8511",
    "sg:postcode":"40064",
    "sg:province":"Bologna",
    "sg:tags":[
        "product",
        "related"
    ],
    "sg:website":"http://www.cannamela.it",
    "wof:name":"Cannamela",
    "wof:placetype":"venue"
},
  "geometry": {"coordinates":[11.435962677,44.4602432251],"type":"Point"}
}