{
  "type": "Feature",
  "properties": {
    "iso:country":"IT",
    "sg:address":"25064 Gussago",
    "sg:city":"Gussago",
    "sg:orig_category":"Articoli Per Imballaggio E Confezionamento",
    "sg:phone":"+39 030 373 3900",
    "sg:postcode":"25064",
    "sg:province":"Brescia",
    "wof:name":"La Aspo Politirolo - Imballaggi",
    "wof:placetype":"venue"
},
  "geometry": {"coordinates":[10.155796,45.558613],"type":"Point"}
}