{
  "type": "Feature",
  "properties": {
    "iso:country":"IT",
    "sg:address":"50055 Lastra A Signa",
    "sg:city":"Lastra a Signa",
    "sg:orig_category":"Macchine, Impianti Ed Attrezzature Per Abbigliamento E Pelletterie",
    "sg:phone":"+39 055 872 2640",
    "sg:postcode":"50055",
    "sg:province":"Firenze",
    "wof:name":"Nistri Alessandro",
    "wof:placetype":"venue"
},
  "geometry": {"coordinates":[11.113353,43.768433],"type":"Point"}
}