{
  "type": "Feature",
  "properties": {
    "iso:country":"IT",
    "sg:address":"24058 Romano Di Lombardia",
    "sg:city":"Romano di Lombardia",
    "sg:orig_category":"Pulitura E Lucidatura Metalli",
    "sg:phone":"+39 036 390 2640",
    "sg:postcode":"24058",
    "sg:province":"Bergamo",
    "wof:name":"Itala Di Fasolini Giuseppe",
    "wof:placetype":"venue"
},
  "geometry": {"coordinates":[9.7394628525,45.5261192322],"type":"Point"}
}