{
  "type": "Feature",
  "properties": {
    "iso:country":"IT",
    "sg:address":"50121 Firenze",
    "sg:city":"Firenze",
    "sg:classifiers":[
        {
            "category":"Professional",
            "subcategory":"Printing & Photocopies",
            "type":"Services"
        }
    ],
    "sg:phone":"+39 055 218361",
    "sg:postcode":"50121",
    "sg:province":"Firenze",
    "sg:tags":[
        "auxiliary",
        "photo",
        "packaging",
        "setting",
        "reproduction",
        "certificates",
        "drawing"
    ],
    "wof:name":"Macyf Sas Copisteria La Brunelleschi",
    "wof:placetype":"venue"
},
  "geometry": {"coordinates":[11.25896,43.774532],"type":"Point"}
}