{
  "type": "Feature",
  "properties": {
    "addr:full":"Via Pestalozza Alessandro 16 20131 Milano Milano Milano 20131",
    "addr:housenumber":"16",
    "addr:postcode":"20131;20131",
    "addr:street":"Via Pestalozza Alessandro",
    "iso:country":"IT",
    "sg:address":"Via Pestalozza Alessandro 16 20131 Milano",
    "sg:city":"Milano",
    "sg:classifiers":[
        {
            "category":"Manufacturing",
            "subcategory":"Food",
            "type":"Manufacturing & Wholesale Goods"
        }
    ],
    "sg:phone":"+39 02 236 5453",
    "sg:postcode":"20131",
    "sg:province":"Milano",
    "sg:tags":[
        "raw",
        "material"
    ],
    "sg:website":"www.variati.it",
    "wof:name":"Variati & Co. Spa",
    "wof:placetype":"venue"
},
  "geometry": {"coordinates":[9.2226963043,45.4822311401],"type":"Point"}
}