{
  "type": "Feature",
  "properties": {
    "iso:country":"IT",
    "sg:address":"23843 Dolzago",
    "sg:city":"Dolzago",
    "sg:orig_category":"Espositori, Displays E Articoli Pubblicitari Punto Vendita",
    "sg:phone":"+39 0341 451365",
    "sg:postcode":"23843",
    "sg:province":"Lecco",
    "wof:name":"Galbiati Giacomo",
    "wof:placetype":"venue"
},
  "geometry": {"coordinates":[9.3704938889,45.8485984802],"type":"Point"}
}