{
  "type": "Feature",
  "properties": {
    "iso:country":"IT",
    "sg:address":"15, Viale Lido 28838 Stresa",
    "sg:city":"Stresa",
    "sg:classifiers":[
        {
            "category":"Travel",
            "subcategory":"Travel Agent",
            "type":"Entertainment"
        }
    ],
    "sg:phone":"+39 39032333611",
    "sg:postcode":"28838",
    "sg:province":"Verbano-Cusio-Ossola",
    "sg:tags":[
        "business"
    ],
    "wof:name":"Albergo Lido La Perla Nera",
    "wof:placetype":"venue"
},
  "geometry": {"coordinates":[8.523303,45.889885],"type":"Point"}
}