{
  "type": "Feature",
  "properties": {
    "addr:full":"93100 Caltanissetta Caltanissetta Caltanissetta 93100",
    "addr:postcode":"93100;93100",
    "iso:country":"IT",
    "sg:address":"93100 Caltanissetta",
    "sg:city":"Caltanissetta",
    "sg:orig_category":"Lavoro Interinale E Temporaneo",
    "sg:phone":"+39 800 225 168",
    "sg:postcode":"93100",
    "sg:province":"Caltanissetta",
    "wof:name":"Fincoop Soc.coop.r.l.",
    "wof:placetype":"venue"
},
  "geometry": {"coordinates":[14.046629,37.494469],"type":"Point"}
}