{
  "type": "Feature",
  "properties": {
    "iso:country":"IT",
    "sg:address":"16, Strada Fonte Blancio 10062 Luserna San Giovanni",
    "sg:city":"Luserna",
    "sg:classifiers":[
        {
            "category":"Building & Trades",
            "subcategory":"Construction",
            "type":"Services"
        }
    ],
    "sg:phone":"+39 0121 954502",
    "sg:postcode":"10062",
    "sg:province":"Torino",
    "sg:tags":[
        "work",
        "public"
    ],
    "wof:name":"De Luca",
    "wof:placetype":"venue"
},
  "geometry": {"coordinates":[7.686619,45.07056],"type":"Point"}
}