{
  "type": "Feature",
  "properties": {
    "iso:country":"IT",
    "sg:address":"98050 Terme Vigliatore",
    "sg:city":"Terme Vigliatore",
    "sg:orig_category":"Bevande, Vini E Liquori",
    "sg:phone":"+39 090 978 2613",
    "sg:postcode":"98050",
    "sg:province":"Messina",
    "wof:name":"Ciappazzi Srl",
    "wof:placetype":"venue"
},
  "geometry": {"coordinates":[15.169819,38.136757],"type":"Point"}
}