{
  "type": "Feature",
  "properties": {
    "iso:country":"IT",
    "sg:address":"20094 Corsico",
    "sg:city":"Corsico",
    "sg:orig_category":"Metalli E Leghe",
    "sg:phone":"+39 02 450 2478",
    "sg:postcode":"20094",
    "sg:province":"Milano",
    "wof:name":"Metal Rottami Di Seccia Michele E Giacinto & C. Snc",
    "wof:placetype":"venue"
},
  "geometry": {"coordinates":[9.0843000412,45.4290428162],"type":"Point"}
}