{
  "type": "Feature",
  "properties": {
    "iso:country":"IT",
    "sg:address":"00181 Roma",
    "sg:city":"Roma",
    "sg:orig_category":"Scuole E Servizi Scolastici. Alberghi E Strutture Extra Alberghiere",
    "sg:phone":"+39 06 782 7154",
    "sg:postcode":"00181",
    "sg:province":"Roma",
    "wof:name":"Collegio Preziosissimo Sangue",
    "wof:placetype":"venue"
},
  "geometry": {"coordinates":[12.527661,41.879421],"type":"Point"}
}