{
  "type": "Feature",
  "properties": {
    "iso:country":"IT",
    "sg:address":"96100 Siracusa",
    "sg:city":"Siracusa",
    "sg:orig_category":"Elettrotecnica Industriale, Prodotti E Apparecchiature. Ricambi E Componenti Dei Mezzi Di Trasporto",
    "sg:phone":"+39 0931 783703",
    "sg:postcode":"96100",
    "sg:province":"Siracusa",
    "wof:name":"Il Modulo S.r.l.",
    "wof:placetype":"venue"
},
  "geometry": {"coordinates":[15.293245,37.09071],"type":"Point"}
}