{
  "type": "Feature",
  "properties": {
    "addr:full":"00192 Roma Roma Roma 00192",
    "addr:postcode":"00192;00192",
    "iso:country":"IT",
    "sg:address":"00192 Roma",
    "sg:city":"Roma",
    "sg:orig_category":"Prodotti Alimentari",
    "sg:phone":"+39 06 3974 3503",
    "sg:postcode":"00192",
    "sg:province":"Roma",
    "wof:name":"Visalli Michele",
    "wof:placetype":"venue"
},
  "geometry": {"coordinates":[12.4536762238,41.8604125977],"type":"Point"}
}