{
  "type": "Feature",
  "properties": {
    "iso:country":"IT",
    "sg:address":"95045 Misterbianco",
    "sg:city":"Misterbianco",
    "sg:orig_category":"Caffe' Crudo E Torrefatto",
    "sg:phone":"+39 095 399198",
    "sg:postcode":"95045",
    "sg:province":"Catania",
    "wof:name":"Santonocito Antonio",
    "wof:placetype":"venue"
},
  "geometry": {"coordinates":[15.029149,37.533287],"type":"Point"}
}