{
  "type": "Feature",
  "properties": {
    "iso:country":"IT",
    "sg:address":"36050 Sovizzo",
    "sg:city":"Sovizzo",
    "sg:orig_category":"Rifiuti Industriali E Speciali Smaltimento E Trattamento - Servizio",
    "sg:phone":"+39 0444 536418",
    "sg:postcode":"36050",
    "sg:province":"Vicenza",
    "wof:name":"Ra.me.ve.ca. Di Colombara Stefano",
    "wof:placetype":"venue"
},
  "geometry": {"coordinates":[11.45908,45.531307],"type":"Point"}
}