{
  "type": "Feature",
  "properties": {
    "addr:full":"38/a, Via S. Pietro 16035 Rapallo Rapallo Genova 16035",
    "addr:housenumber":"38 / a",
    "addr:postcode":"16035;16035",
    "addr:street":"Via S. Pietro",
    "iso:country":"IT",
    "sg:address":"38/a, Via S. Pietro 16035 Rapallo",
    "sg:city":"Rapallo",
    "sg:classifiers":[
        {
            "category":"Food & Beverages",
            "subcategory":"Groceries & Convenience Stores",
            "type":"Retail Goods"
        }
    ],
    "sg:phone":"+39 0185 261271",
    "sg:postcode":"16035",
    "sg:province":"Genova",
    "sg:tags":[
        "product",
        "related"
    ],
    "wof:name":"Articom Srl",
    "wof:placetype":"venue"
},
  "geometry": {"coordinates":[8.9339885712,44.4070625305],"type":"Point"}
}