{
  "type": "Feature",
  "properties": {
    "iso:country":"IT",
    "sg:address":"20148 Milano",
    "sg:city":"Milano",
    "sg:orig_category":"Servizi Di Magazzinaggio E Movimentazione",
    "sg:phone":"+39 02 4007 2530",
    "sg:postcode":"20148",
    "sg:province":"Milano",
    "wof:name":"Verga Cinzia",
    "wof:placetype":"venue"
},
  "geometry": {"coordinates":[9.142954,45.468929],"type":"Point"}
}