{
  "type": "Feature",
  "properties": {
    "addr:full":"44, Via Braccio Da Montone 00176 Roma Roma Roma 00176",
    "addr:postcode":"00176;00176",
    "addr:street":"Via Braccio Da Montone",
    "iso:country":"IT",
    "sg:address":"44, Via Braccio Da Montone 00176 Roma",
    "sg:city":"Roma",
    "sg:classifiers":[
        {
            "category":"Manufacturing",
            "subcategory":"Tools & Machinery",
            "type":"Manufacturing & Wholesale Goods"
        }
    ],
    "sg:phone":"+39 390 627 2478",
    "sg:postcode":"00176",
    "sg:province":"Roma",
    "sg:tags":[
        "environment",
        "equipment",
        "-"
    ],
    "wof:name":"Carazzi Srl",
    "wof:placetype":"venue"
},
  "geometry": {"coordinates":[12.529521,41.889263],"type":"Point"}
}