{
  "type": "Feature",
  "properties": {
    "iso:country":"IT",
    "sg:address":"00047 Marino",
    "sg:city":"Marino",
    "sg:orig_category":"Servizi E Lavori Per Industria Alimentare E Bevande. Servizi E Lavori Per Abbigliamento E Pelletterie. Servizi E Lavori Per Arredamento E Industria Del Legno",
    "sg:phone":"+39 06 9354 6220",
    "sg:postcode":"00047",
    "sg:province":"Roma",
    "wof:name":"Caucci Market",
    "wof:placetype":"venue"
},
  "geometry": {"coordinates":[12.600633,41.772827],"type":"Point"}
}