{
  "type": "Feature",
  "properties": {
    "iso:country":"IT",
    "sg:address":"684/686, Via Appia 04026 Minturno",
    "sg:city":"Minturno",
    "sg:classifiers":[
        {
            "category":"Bars & Pubs",
            "subcategory":"Nightclub",
            "type":"Food & Drink"
        }
    ],
    "sg:phone":"+39 0771 682656",
    "sg:postcode":"04026",
    "sg:province":"Latina",
    "sg:tags":[
        "cake",
        "bread"
    ],
    "wof:name":"Pasticceria Morelli S.r.l.",
    "wof:placetype":"venue"
},
  "geometry": {"coordinates":[13.719818,41.2537],"type":"Point"}
}