{
  "type": "Feature",
  "properties": {
    "iso:country":"IT",
    "sg:address":"Via Cavour 167 25082 Botticino Sera",
    "sg:city":"Botticino",
    "sg:classifiers":[
        {
            "category":"Professional",
            "subcategory":"Printing & Photocopies",
            "type":"Services"
        }
    ],
    "sg:phone":"+39 030 269 1454",
    "sg:postcode":"25082",
    "sg:province":"Brescia",
    "sg:tags":[
        "box",
        "machine",
        "cardboard"
    ],
    "sg:website":"www.bragasnc.com",
    "wof:name":"Braga Snc Di Braga Fabio & C.",
    "wof:placetype":"venue"
},
  "geometry": {"coordinates":[10.296351,45.529324],"type":"Point"}
}