{
  "type": "Feature",
  "properties": {
    "iso:country":"IT",
    "sg:address":"08015 Macomer",
    "sg:city":"Macomer",
    "sg:orig_category":"Prodotti E Manufatti In Materie Plastiche. Articoli Per Imballaggio E Confezionamento",
    "sg:phone":"+39 0785 749058",
    "sg:postcode":"08015",
    "sg:province":"Nuoro",
    "wof:name":"Termosarda Di Ruggio Heros",
    "wof:placetype":"venue"
},
  "geometry": {"coordinates":[9.3289690018,40.3284416199],"type":"Point"}
}