{
  "type": "Feature",
  "properties": {
    "addr:full":"Via Croce 39; Brescia; 25121 Brescia Brescia 25121",
    "addr:housenumber":"39",
    "addr:postcode":"25121;25121",
    "addr:street":"Via Croce",
    "iso:country":"IT",
    "sg:address":"Via Croce 39; Brescia; 25121",
    "sg:city":"Brescia",
    "sg:classifiers":[
        {
            "category":"Banks & Credit Unions",
            "subcategory":"Bank",
            "type":"Services"
        }
    ],
    "sg:phone":"+39 030 45454",
    "sg:postcode":"25121",
    "sg:province":"Brescia",
    "wof:name":"Banca Nazionale Del Lavoro",
    "wof:placetype":"venue"
},
  "geometry": {"coordinates":[10.219849,45.534664],"type":"Point"}
}