{
  "type": "Feature",
  "properties": {
    "iso:country":"IT",
    "sg:address":"36056 Tezze Sul Brenta",
    "sg:city":"Tezze sul Brenta",
    "sg:classifiers":[
        {
            "category":"Home & Garden",
            "subcategory":"Home Furnishings",
            "type":"Retail Goods"
        }
    ],
    "sg:phone":"+39 0424 89128",
    "sg:postcode":"36056",
    "sg:province":"Vicenza",
    "sg:tags":[
        "professional",
        "furniture",
        "accommodation",
        "supply"
    ],
    "wof:name":"L'arte Nel Legno Di Marsan Simone",
    "wof:placetype":"venue"
},
  "geometry": {"coordinates":[11.7391967773,45.6853561401],"type":"Point"}
}