{
  "type": "Feature",
  "properties": {
    "addr:full":"1, Fondamenta Serenella 30141 Venezia Venezia Venezia 30141",
    "addr:housenumber":"1",
    "addr:postcode":"30141;30141",
    "addr:street":"Fondamenta Serenella",
    "iso:country":"IT",
    "sg:address":"1, Fondamenta Serenella 30141 Venezia",
    "sg:city":"Venezia",
    "sg:classifiers":[
        {
            "category":"Manufacturing",
            "subcategory":"Glass & Minerals",
            "type":"Manufacturing & Wholesale Goods"
        }
    ],
    "sg:phone":"+39 041 527 5294",
    "sg:postcode":"30141",
    "sg:province":"Venezia",
    "wof:name":"Serenella Arte",
    "wof:placetype":"venue"
},
  "geometry": {"coordinates":[12.347938,45.451591],"type":"Point"}
}