{
  "type": "Feature",
  "properties": {
    "iso:country":"IT",
    "sg:address":"17014 Cairo Montenotte",
    "sg:city":"Cairo Montenotte",
    "sg:orig_category":"Arredamenti E Mobili Professionali",
    "sg:phone":"+39 019 504153",
    "sg:postcode":"17014",
    "sg:province":"Savona",
    "wof:name":"Nuova Metallegno Snc",
    "wof:placetype":"venue"
},
  "geometry": {"coordinates":[8.275796,44.413139],"type":"Point"}
}