{
  "type": "Feature",
  "properties": {
    "iso:country":"IT",
    "sg:address":"12030 Cavallermaggiore",
    "sg:city":"Cavallermaggiore",
    "sg:orig_category":"Forniture Per Attivita' Industriali",
    "sg:phone":"+39 0172 382894",
    "sg:postcode":"12030",
    "sg:province":"Cuneo",
    "wof:name":"Onda Blu Di Cometto Fabio & C. Snc",
    "wof:placetype":"venue"
},
  "geometry": {"coordinates":[7.522600174,44.374797821],"type":"Point"}
}