{
  "type": "Feature",
  "properties": {
    "iso:country":"IT",
    "sg:address":"40128 Bologna",
    "sg:city":"Bologna",
    "sg:orig_category":"Articoli Per Imballaggio E Confezionamento",
    "sg:phone":"+39 051 638 9629",
    "sg:postcode":"40128",
    "sg:province":"Bologna",
    "wof:name":"Casa Della Gomma Srl",
    "wof:placetype":"venue"
},
  "geometry": {"coordinates":[11.358258,44.538193],"type":"Point"}
}