{
  "type": "Feature",
  "properties": {
    "iso:country":"IT",
    "sg:address":"147, Via Villa 30010 Campolongo Maggiore",
    "sg:city":"Campolongo Maggiore",
    "sg:classifiers":[
        {
            "category":"Banks & Credit Unions",
            "subcategory":"Bank",
            "type":"Services"
        }
    ],
    "sg:phone":"+39 049 972 5499",
    "sg:postcode":"30010",
    "sg:province":"Venezia",
    "sg:tags":[
        "banking",
        "institution"
    ],
    "wof:name":"Banco Di Credito Cooperativo Del Veneziano (soc.coop.r.l.)",
    "wof:placetype":"venue"
},
  "geometry": {"coordinates":[12.070092,45.33799],"type":"Point"}
}