{
  "type": "Feature",
  "properties": {
    "addr:full":"98123 Messina Messina Messina 98123",
    "addr:postcode":"98123;98123",
    "iso:country":"IT",
    "sg:address":"98123 Messina",
    "sg:city":"Messina",
    "sg:classifiers":[
        {
            "category":"Shopping",
            "subcategory":"Computers & Home Electronics",
            "type":"Retail Goods"
        }
    ],
    "sg:phone":"+39 090 673345",
    "sg:postcode":"98123",
    "sg:province":"Messina",
    "sg:tags":[
        "vendita",
        "personal",
        "ed",
        "-",
        "al",
        "dettaglio",
        "accessori"
    ],
    "wof:name":"Cali' Marina",
    "wof:placetype":"venue"
},
  "geometry": {"coordinates":[15.5518341064,38.18309021],"type":"Point"}
}