{
  "type": "Feature",
  "properties": {
    "addr:full":"90144 Palermo Palermo Palermo 90144",
    "addr:postcode":"90144;90144",
    "iso:country":"IT",
    "sg:address":"90144 Palermo",
    "sg:city":"Palermo",
    "sg:orig_category":"Scuole Private - Tecniche",
    "sg:phone":"+39 091 309724",
    "sg:postcode":"90144",
    "sg:province":"Palermo",
    "wof:name":"Pitti Gaetano Centro Europeo D'orientamento",
    "wof:placetype":"venue"
},
  "geometry": {"coordinates":[13.366579,38.106636],"type":"Point"}
}