{
  "type": "Feature",
  "properties": {
    "iso:country":"IT",
    "sg:address":"20052 Monza",
    "sg:city":"Monza",
    "sg:orig_category":"Studi E Consulenze Tecniche E Industriali. Consulenze Tecniche, Amministrative E Perizie",
    "sg:phone":"+39 039 23971",
    "sg:postcode":"20052",
    "sg:province":"Milano",
    "sg:website":"http://www.cam-monza.com",
    "wof:name":"C.a.m. Centro Analisi Monza",
    "wof:placetype":"venue"
},
  "geometry": {"coordinates":[9.277356,45.534306],"type":"Point"}
}