{
  "type": "Feature",
  "properties": {
    "iso:country":"IT",
    "sg:address":"51021 Abetone",
    "sg:city":"Abetone",
    "sg:orig_category":"Ristorazione E Locali Pubblici Affini. Ristoranti Ed Esercizi Affini. Servizi Ausiliari Di Ristorazione E Di Intrattenimento",
    "sg:phone":"+39 0573 607064",
    "sg:postcode":"51021",
    "sg:province":"Pistoia",
    "sg:website":"http://www.chiarofonte.it",
    "wof:name":"Hotel Chiarofonte",
    "wof:placetype":"venue"
},
  "geometry": {"coordinates":[10.650924,44.153946],"type":"Point"}
}