{
  "type": "Feature",
  "properties": {
    "addr:full":"7, Via Galileo Galilei 22070 Guanzate Guanzate Como 22070",
    "addr:postcode":"22070;22070",
    "addr:street":"Via Galileo Galilei",
    "iso:country":"IT",
    "sg:address":"7, Via Galileo Galilei 22070 Guanzate",
    "sg:city":"Guanzate",
    "sg:classifiers":[
        {
            "category":"Autos & Motor Vehicles",
            "subcategory":"Automobile Sales",
            "type":"Retail Goods"
        }
    ],
    "sg:phone":"+39 031 352 9061",
    "sg:postcode":"22070",
    "sg:province":"Como",
    "sg:tags":[
        "motor-cars"
    ],
    "wof:name":"Dimatec Spa",
    "wof:placetype":"venue"
},
  "geometry": {"coordinates":[9.034116745,45.7646903992],"type":"Point"}
}