{
  "type": "Feature",
  "properties": {
    "addr:full":"00138 Roma Roma Roma 00138",
    "addr:postcode":"00138;00138",
    "iso:country":"IT",
    "sg:address":"00138 Roma",
    "sg:city":"Roma",
    "sg:orig_category":"Manufacturers: Prefabbricati. Idrosanitari E Accessori. Servizi Per Aziende, Manifestazioni E Supporto Agli Scambi Commerciali",
    "sg:phone":"+39 06 881 3796",
    "sg:postcode":"00138",
    "sg:province":"Roma",
    "wof:name":"Socrates Cooperativa Sociale Arl",
    "wof:placetype":"venue"
},
  "geometry": {"coordinates":[12.514935,41.972008],"type":"Point"}
}