{
  "type": "Feature",
  "properties": {
    "iso:country":"IT",
    "sg:address":"00138 Roma",
    "sg:city":"Roma",
    "sg:orig_category":"Servizi Ausiliari Dei Mezzi Di Trasporto",
    "sg:phone":"+39 06 888 9880",
    "sg:postcode":"00138",
    "sg:province":"Roma",
    "wof:name":"Metano Salaria Di Tibuzzi Manuela",
    "wof:placetype":"venue"
},
  "geometry": {"coordinates":[12.509851,42.008747],"type":"Point"}
}