{
  "type": "Feature",
  "properties": {
    "addr:full":"20149 Milano Milano Milano 20149",
    "addr:postcode":"20149;20149",
    "iso:country":"IT",
    "sg:address":"20149 Milano",
    "sg:city":"Milano",
    "sg:orig_category":"Depurazione E Trattamento Delle Acque - Impianti Ed Apparecchi",
    "sg:phone":"+39 02 3300 0100",
    "sg:postcode":"20149",
    "sg:province":"Milano",
    "sg:website":"http://www.utenti.tripod.it/tecnoeco/index.html",
    "wof:name":"Tecnoeco Srl",
    "wof:placetype":"venue"
},
  "geometry": {"coordinates":[9.154992,45.488316],"type":"Point"}
}