{
  "type": "Feature",
  "properties": {
    "iso:country":"IT",
    "sg:address":"Via Delle Bianchette 5 36030 Sarcedo",
    "sg:city":"Sarcedo",
    "sg:classifiers":[
        {
            "category":"Manufacturing",
            "subcategory":"Metals",
            "type":"Manufacturing & Wholesale Goods"
        }
    ],
    "sg:phone":"+39 0445 360133",
    "sg:postcode":"36030",
    "sg:province":"Vicenza",
    "sg:tags":[
        "die",
        "aluminium",
        "casting"
    ],
    "sg:website":"www.metalfond.com",
    "wof:name":"Metalfond Srl",
    "wof:placetype":"venue"
},
  "geometry": {"coordinates":[11.502191,45.705585],"type":"Point"}
}