{
  "type": "Feature",
  "properties": {
    "addr:full":"45, Via Cipro 47023 Cesena Cesena Forl\u00ec-Cesena 47023",
    "addr:postcode":"47023;47023",
    "addr:street":"Via Cipro",
    "iso:country":"IT",
    "sg:address":"45, Via Cipro 47023 Cesena",
    "sg:city":"Cesena",
    "sg:classifiers":[
        {
            "category":"Manufacturing",
            "subcategory":"Rubber & Plastics",
            "type":"Manufacturing & Wholesale Goods"
        }
    ],
    "sg:phone":"+39 0547 382511",
    "sg:postcode":"47023",
    "sg:province":"Forl\u00ec-Cesena",
    "wof:name":"Pneus Gommaria Di G. Turci & C. (s.a.s.)",
    "wof:placetype":"venue"
},
  "geometry": {"coordinates":[12.243714,44.153896],"type":"Point"}
}