{
  "type": "Feature",
  "properties": {
    "iso:country":"IT",
    "sg:address":"89861 Tropea",
    "sg:city":"Tropea",
    "sg:orig_category":"Autonoleggio",
    "sg:phone":"+39 0963 61615",
    "sg:postcode":"89861",
    "sg:province":"Vibo Valentia",
    "wof:name":"Autonoleggio Di Costa Pietro",
    "wof:placetype":"venue"
},
  "geometry": {"coordinates":[16.09766,38.67561],"type":"Point"}
}