{
  "type": "Feature",
  "properties": {
    "iso:country":"IT",
    "sg:address":"20064 Gorgonzola",
    "sg:city":"Gorgonzola",
    "sg:orig_category":"Abbigliamento Esterno, Maglierie E Pelliccerie",
    "sg:phone":"+39 02 951 5593",
    "sg:postcode":"20064",
    "sg:province":"Milano",
    "wof:name":"Miri (s.r.l.)",
    "wof:placetype":"venue"
},
  "geometry": {"coordinates":[9.206923,45.470066],"type":"Point"}
}