{
  "type": "Feature",
  "properties": {
    "iso:country":"IT",
    "sg:address":"40010 Galliera",
    "sg:orig_category":"Materie Plastiche Lavorazione - Macchine",
    "sg:phone":"+39 051 815516",
    "sg:postcode":"40010",
    "sg:province":"Bologna",
    "wof:name":"Fratelli Francia Snc Di Gabriele Francia & C.",
    "wof:placetype":"venue"
},
  "geometry": {"coordinates":[11.346481,44.494221],"type":"Point"}
}