{
  "type": "Feature",
  "properties": {
    "iso:country":"IT",
    "sg:address":"20021 Bollate",
    "sg:city":"Bollate",
    "sg:orig_category":"Macchine, Impianti Ed Attrezzature Per Industria Alimentare E Bevande. Macchine E Impianti Per Attivita' Commerciali Ed Artigianali",
    "sg:phone":"+39 02 350 2658",
    "sg:postcode":"20021",
    "sg:province":"Milano",
    "wof:name":"Arte Del Pane S.n.c. Di Deserra Mario E Giovanna",
    "wof:placetype":"venue"
},
  "geometry": {"coordinates":[9.143235,45.534023],"type":"Point"}
}