{
  "type": "Feature",
  "properties": {
    "addr:full":"24065 Lovere Lovere Bergamo 24065",
    "addr:postcode":"24065;24065",
    "iso:country":"IT",
    "sg:address":"24065 Lovere",
    "sg:city":"Lovere",
    "sg:orig_category":"Servizi E Lavori Per Ecologia E Smaltimento Rifiuti. Arte Ed Artigianato Artistico. Servizi Ausiliari Di Sorveglianza, Manutenzione E Pulizia",
    "sg:phone":"+39 035 962878",
    "sg:postcode":"24065",
    "sg:province":"Bergamo",
    "wof:name":"Cucinotta Letteria",
    "wof:placetype":"venue"
},
  "geometry": {"coordinates":[10.077584,45.818077],"type":"Point"}
}