{
  "type": "Feature",
  "properties": {
    "iso:country":"IT",
    "sg:address":"40138 Bologna",
    "sg:city":"Bologna",
    "sg:orig_category":"Nidi D'infanzia",
    "sg:phone":"+39 051 309024",
    "sg:postcode":"40138",
    "sg:province":"Bologna",
    "wof:name":"Paedo Srl",
    "wof:placetype":"venue"
},
  "geometry": {"coordinates":[11.398565,44.499325],"type":"Point"}
}