{
  "type": "Feature",
  "properties": {
    "iso:country":"IT",
    "sg:address":"Strada Di Sabbioni 05100 Terni",
    "sg:city":"Terni",
    "sg:classifiers":[
        {
            "category":"Parking",
            "subcategory":"Lot",
            "type":"Transportation"
        }
    ],
    "sg:phone":"+39 0744 813661",
    "sg:postcode":"05100",
    "sg:province":"Terni",
    "sg:tags":[
        "transport",
        "road"
    ],
    "wof:name":"C.u.a.m. (s.r.l.)",
    "wof:placetype":"venue"
},
  "geometry": {"coordinates":[12.625197,42.572308],"type":"Point"}
}