{
  "type": "Feature",
  "properties": {
    "iso:country":"IT",
    "sg:address":"22063 Cantu'",
    "sg:orig_category":"Accessori Moda D'abbigliamento. Forniture Per Abbigliamento E Pelletterie",
    "sg:phone":"+39 031 714533",
    "sg:postcode":"22063",
    "sg:province":"Como",
    "wof:name":"Molteni Genoeffa (s.n.c.)",
    "wof:placetype":"venue"
},
  "geometry": {"coordinates":[9.12682,45.740433],"type":"Point"}
}