{
  "type": "Feature",
  "properties": {
    "iso:country":"IT",
    "sg:address":"20132 Milano",
    "sg:city":"Milano",
    "sg:orig_category":"Servizi Culturali E Per Lo Spettacolo. Servizi Al Turismo. Acqua, Luce, Gas E Societa' Di Esercizio Pubblico",
    "sg:phone":"+39 02 272 2151",
    "sg:postcode":"20132",
    "sg:province":"Milano",
    "wof:name":"Teatro 3 Srl",
    "wof:placetype":"venue"
},
  "geometry": {"coordinates":[9.247232,45.50774],"type":"Point"}
}