{
  "type": "Feature",
  "properties": {
    "iso:country":"IT",
    "sg:address":"70032 Bitonto",
    "sg:city":"Bitonto",
    "sg:orig_category":"Abbigliamento Esterno, Maglierie E Pelliccerie",
    "sg:phone":"+39 080 374 8041",
    "sg:postcode":"70032",
    "sg:province":"Bari",
    "wof:name":"Esselle Di Schiavino Vito",
    "wof:placetype":"venue"
},
  "geometry": {"coordinates":[16.593765,41.075172],"type":"Point"}
}