{
  "type": "Feature",
  "properties": {
    "addr:full":"55100 Meati Lucca 55100",
    "addr:postcode":"55100;55100",
    "iso:country":"IT",
    "sg:address":"55100 Meati",
    "sg:orig_category":"Servizi Al Turismo. Trasporto Pubblico E Privato",
    "sg:phone":"+39 0583 511162",
    "sg:postcode":"55100",
    "sg:province":"Lucca",
    "wof:name":"Delta",
    "wof:placetype":"venue"
},
  "geometry": {"coordinates":[10.44832,43.832058],"type":"Point"}
}