{
  "type": "Feature",
  "properties": {
    "addr:full":"21053 Castellanza Castellanza Varese 21053",
    "addr:postcode":"21053;21053",
    "iso:country":"IT",
    "sg:address":"21053 Castellanza",
    "sg:city":"Castellanza",
    "sg:orig_category":"Valvole E Apparecchiature Di Misura. Minuterie Metalliche E Ferramenta. Forniture Per Attivita' Industriali",
    "sg:phone":"+39 0331 503550",
    "sg:postcode":"21053",
    "sg:province":"Varese",
    "wof:name":"Tre Ci Italia Srl",
    "wof:placetype":"venue"
},
  "geometry": {"coordinates":[8.893489,45.796673],"type":"Point"}
}