{
  "type": "Feature",
  "properties": {
    "iso:country":"IT",
    "sg:address":"21040 Sumirago",
    "sg:city":"Sumirago",
    "sg:orig_category":"Prodotti Chimici Di Base",
    "sg:phone":"+39 0331 909070",
    "sg:postcode":"21040",
    "sg:province":"Varese",
    "wof:name":"Silma Chimica Snc",
    "wof:placetype":"venue"
},
  "geometry": {"coordinates":[8.7870225906,45.7576904297],"type":"Point"}
}