{
  "type": "Feature",
  "properties": {
    "iso:country":"IT",
    "sg:address":"10, Via Pagano Mario 20090 Trezzano Sul Naviglio",
    "sg:city":"Trezzano sul Naviglio",
    "sg:classifiers":[
        {
            "category":"Manufacturing",
            "subcategory":"Metals",
            "type":"Manufacturing & Wholesale Goods"
        }
    ],
    "sg:phone":"+39 39024459175",
    "sg:postcode":"20090",
    "sg:province":"Milano",
    "sg:tags":[
        "processing"
    ],
    "wof:name":"Vacuum (s.p.a.)",
    "wof:placetype":"venue"
},
  "geometry": {"coordinates":[9.0462703705,45.4272346497],"type":"Point"}
}