{
  "type": "Feature",
  "properties": {
    "iso:country":"IT",
    "sg:address":"12/b, Piazza Giolitti 51036 Larciano",
    "sg:city":"Larciano",
    "sg:classifiers":[
        {
            "category":"Food & Beverages",
            "subcategory":"Dairy",
            "type":"Retail Goods"
        }
    ],
    "sg:phone":"+39 39057384571",
    "sg:postcode":"51036",
    "sg:province":"Pistoia",
    "sg:tags":[
        "product"
    ],
    "wof:name":"C.d.f. Toscana Spa",
    "wof:placetype":"venue"
},
  "geometry": {"coordinates":[10.918524,43.932156],"type":"Point"}
}