{
  "type": "Feature",
  "properties": {
    "addr:full":"20122 Milano Milano Milano 20122",
    "addr:postcode":"20122;20122",
    "iso:country":"IT",
    "sg:address":"20122 Milano",
    "sg:city":"Milano",
    "sg:orig_category":"Chiese Ed Associazioni Religiose",
    "sg:phone":"+39 02 5830 5965",
    "sg:postcode":"20122",
    "sg:province":"Milano",
    "wof:name":"Suore Di Carita'",
    "wof:placetype":"venue"
},
  "geometry": {"coordinates":[9.19033,45.454494],"type":"Point"}
}