{
  "type": "Feature",
  "properties": {
    "iso:country":"IT",
    "sg:address":"20153 Milano",
    "sg:city":"Milano",
    "sg:orig_category":"Forniture Per Congressi, Fiere E Manifestazioni",
    "sg:phone":"+39 02 4820 1151",
    "sg:postcode":"20153",
    "sg:province":"Milano",
    "sg:website":"http://www.audiover.it",
    "wof:name":"Audiover Srl",
    "wof:placetype":"venue"
},
  "geometry": {"coordinates":[9.1507587433,45.4618453979],"type":"Point"}
}