{
  "type": "Feature",
  "properties": {
    "iso:country":"IT",
    "sg:address":"80046 San Giorgio A Cremano",
    "sg:city":"San Giorgio a Cremano",
    "sg:orig_category":"Forniture Per Abbigliamento E Pelletterie",
    "sg:phone":"+39 081 470822",
    "sg:postcode":"80046",
    "sg:province":"Napoli",
    "wof:name":"Mattei Maurizio",
    "wof:placetype":"venue"
},
  "geometry": {"coordinates":[14.3366279602,40.830532074],"type":"Point"}
}