{
  "type": "Feature",
  "properties": {
    "addr:full":"00152 Roma Roma Roma 00152",
    "addr:postcode":"00152;00152",
    "iso:country":"IT",
    "sg:address":"00152 Roma",
    "sg:city":"Roma",
    "sg:orig_category":"Prodotti Alimentari",
    "sg:phone":"+39 06 582 7633",
    "sg:postcode":"00152",
    "sg:province":"Roma",
    "wof:name":"Giovannetti Sandro",
    "wof:placetype":"venue"
},
  "geometry": {"coordinates":[12.4450302124,41.8636741638],"type":"Point"}
}