{
  "type": "Feature",
  "properties": {
    "addr:full":"126, Viale Testi Fulvio 20092 Cinisello Balsamo Cinisello Balsamo Milano 20092",
    "addr:postcode":"20092;20092",
    "addr:street":"Viale Testi Fulvio",
    "iso:country":"IT",
    "sg:address":"126, Viale Testi Fulvio 20092 Cinisello Balsamo",
    "sg:city":"Cinisello Balsamo",
    "sg:classifiers":[
        {
            "category":"Utilities",
            "subcategory":"Electric",
            "type":"Services"
        }
    ],
    "sg:phone":"+39 39022479161",
    "sg:postcode":"20092",
    "sg:province":"Milano",
    "sg:tags":[
        "component",
        "electronic"
    ],
    "wof:name":"Litton Precision Products (s.p.a.)",
    "wof:placetype":"venue"
},
  "geometry": {"coordinates":[9.215252,45.531631],"type":"Point"}
}