{
  "type": "Feature",
  "properties": {
    "iso:country":"IT",
    "sg:address":"20146 Milano",
    "sg:city":"Milano",
    "sg:orig_category":"Caccia E Pesca Articoli, Attrezzature Ed Abbigliamento - Vendita Al Dettaglio",
    "sg:phone":"+39 02 4870 2805",
    "sg:postcode":"20146",
    "sg:province":"Milano",
    "wof:name":"Spi Nautica Di Petrilli Pasquale",
    "wof:placetype":"venue"
},
  "geometry": {"coordinates":[9.137004,45.463581],"type":"Point"}
}