{
  "type": "Feature",
  "properties": {
    "iso:country":"IT",
    "sg:address":"50142 Firenze",
    "sg:city":"Firenze",
    "sg:orig_category":"Campeggio. Automobili E Mezzi Di Trasporto",
    "sg:phone":"+39 055 755018",
    "sg:postcode":"50142",
    "sg:province":"Firenze",
    "sg:website":"http://www.campermania.com",
    "wof:name":"Camper Mania Di Palazzi Fabrizio",
    "wof:placetype":"venue"
},
  "geometry": {"coordinates":[11.176032,43.770535],"type":"Point"}
}