{
  "type": "Feature",
  "properties": {
    "iso:country":"IT",
    "sg:address":"15057 Tortona",
    "sg:city":"Tortona",
    "sg:orig_category":"Ospedali E Servizi Sanitari",
    "sg:phone":"+39 0131 40645",
    "sg:postcode":"15057",
    "sg:province":"Alessandria",
    "wof:name":"Bios Soc.coop.r.l.",
    "wof:placetype":"venue"
},
  "geometry": {"coordinates":[8.868261,44.897999],"type":"Point"}
}