{
  "type": "Feature",
  "properties": {
    "iso:country":"IT",
    "sg:address":"20121 Milano",
    "sg:city":"Milano",
    "sg:orig_category":"Professionisti - Studi E Servizi Ed Associazioni Di Interesse Aziendale. Associazioni Ed Organismi Di Interesse Pubblico",
    "sg:phone":"+39 02 874932",
    "sg:postcode":"20121",
    "sg:province":"Milano",
    "wof:name":"Fondazione Internazionale Menarini",
    "wof:placetype":"venue"
},
  "geometry": {"coordinates":[9.1872301102,45.4705314636],"type":"Point"}
}