{
  "type": "Feature",
  "properties": {
    "iso:country":"IT",
    "sg:address":"10122 Torino",
    "sg:city":"Torino",
    "sg:classifiers":[
        {
            "category":"Health Services",
            "subcategory":"Health Practitioner",
            "type":"Services"
        }
    ],
    "sg:phone":"+39 011 539413",
    "sg:postcode":"10122",
    "sg:province":"Torino",
    "sg:tags":[
        "medici"
    ],
    "wof:name":"Spiga Graziella",
    "wof:placetype":"venue"
},
  "geometry": {"coordinates":[7.6801872253,45.0704727173],"type":"Point"}
}