{
  "type": "Feature",
  "properties": {
    "iso:country":"IT",
    "sg:address":"41056 Savignano Sul Panaro",
    "sg:city":"Savignano sul Panaro",
    "sg:orig_category":"Forniture Per Agricoltura E Zootecnia. Prodotti Chimici Secondari. Macchine E Forniture Per Ecologia E Smaltimento Rifiuti",
    "sg:phone":"+39 059 796284",
    "sg:postcode":"41056",
    "sg:province":"Modena",
    "wof:name":"Agri - Verde Garagnani (s.r.l.)",
    "wof:placetype":"venue"
},
  "geometry": {"coordinates":[10.9952049255,44.4556884766],"type":"Point"}
}