{
  "type": "Feature",
  "properties": {
    "iso:country":"IT",
    "sg:address":"Corso G.matteotti 12/14; Latina; 04100",
    "sg:city":"Latina",
    "sg:classifiers":[
        {
            "category":"Banks & Credit Unions",
            "subcategory":"Bank",
            "type":"Services"
        }
    ],
    "sg:phone":"+39 0773 489981",
    "sg:postcode":"04100",
    "sg:province":"Latina",
    "wof:name":"Banco Di Santo Spirito",
    "wof:placetype":"venue"
},
  "geometry": {"coordinates":[12.90652,41.471336],"type":"Point"}
}