{
  "type": "Feature",
  "properties": {
    "iso:country":"IT",
    "sg:address":"Localita' Prarayer 2 11020 Saint-marcel",
    "sg:city":"Saint-Marcel",
    "sg:classifiers":[
        {
            "category":"Food & Beverages",
            "subcategory":"Bakery",
            "type":"Retail Goods"
        }
    ],
    "sg:phone":"+39 0165 768929",
    "sg:postcode":"11020",
    "sg:province":"Aosta",
    "sg:tags":[
        "grain",
        "cereal"
    ],
    "wof:name":"Valby Berti & Yeuillaz Snc",
    "wof:placetype":"venue"
},
  "geometry": {"coordinates":[7.429902,45.730591],"type":"Point"}
}