{
  "type": "Feature",
  "properties": {
    "iso:country":"IT",
    "sg:address":"70032 Bitonto",
    "sg:city":"Bitonto",
    "sg:orig_category":"Materiali Edili",
    "sg:phone":"+39 080 374 3471",
    "sg:postcode":"70032",
    "sg:province":"Bari",
    "wof:name":"Bitoncalce Snc",
    "wof:placetype":"venue"
},
  "geometry": {"coordinates":[16.679188,41.132793],"type":"Point"}
}