{
  "type": "Feature",
  "properties": {
    "iso:country":"IT",
    "sg:address":"31018 Gaiarine",
    "sg:city":"Albina",
    "sg:orig_category":"Macchine E Forniture Per Arredamento E Industria Del Legno",
    "sg:phone":"+39 0434 7571",
    "sg:postcode":"31018",
    "sg:province":"Treviso",
    "wof:name":"Nicos Spa",
    "wof:placetype":"venue"
},
  "geometry": {"coordinates":[12.511917,45.882782],"type":"Point"}
}