{
  "type": "Feature",
  "properties": {
    "addr:full":"10128 Torino Torino Torino 10128",
    "addr:postcode":"10128;10128",
    "iso:country":"IT",
    "sg:address":"10128 Torino",
    "sg:city":"Torino",
    "sg:classifiers":[
        {
            "category":"Health Services",
            "subcategory":"Health Practitioner",
            "type":"Services"
        }
    ],
    "sg:phone":"+39 011 581 7126",
    "sg:postcode":"10128",
    "sg:province":"Torino",
    "sg:tags":[
        "medici"
    ],
    "wof:name":"Bianchi Silvio",
    "wof:placetype":"venue"
},
  "geometry": {"coordinates":[7.664783,45.055252],"type":"Point"}
}