{
  "type": "Feature",
  "properties": {
    "addr:full":"Vle Olimpico 5 80025 Casandrino Casandrino Napoli 80025",
    "addr:housenumber":"5",
    "addr:postcode":"80025;80025",
    "addr:street":"Vle Olimpico",
    "iso:country":"IT",
    "sg:address":"Vle Olimpico 5 80025 Casandrino",
    "sg:city":"Casandrino",
    "sg:orig_category":"Ladies' Shoes",
    "sg:phone":"+39 081 505 5589",
    "sg:postcode":"80025",
    "sg:province":"Napoli",
    "sg:website":"www.calpierre.it",
    "wof:name":"Calpierre S.r.l.",
    "wof:placetype":"venue"
},
  "geometry": {"coordinates":[14.251082,40.924858],"type":"Point"}
}