{
  "type": "Feature",
  "properties": {
    "addr:full":"4, Via Rimini 21050 Cairate Cairate Varese 21050",
    "addr:postcode":"21050;21050",
    "addr:street":"Via Rimini",
    "iso:country":"IT",
    "sg:address":"4, Via Rimini 21050 Cairate",
    "sg:city":"Cairate",
    "sg:classifiers":[
        {
            "category":"Manufacturing",
            "subcategory":"Paper Products",
            "type":"Manufacturing & Wholesale Goods"
        }
    ],
    "sg:phone":"+39 0331 360188",
    "sg:postcode":"21050",
    "sg:province":"Varese",
    "sg:tags":[
        "cardboard"
    ],
    "wof:name":"Ala (s.r.l.)",
    "wof:placetype":"venue"
},
  "geometry": {"coordinates":[8.8687591553,45.6823043823],"type":"Point"}
}