{
  "type": "Feature",
  "properties": {
    "iso:country":"IT",
    "sg:address":"20142 Milano",
    "sg:city":"Milano",
    "sg:orig_category":"Abbigliamento Intimo, Calze E Costumi Da Bagno. Articoli Medico-sanitari Ed Ortopedici",
    "sg:phone":"+39 02 846 5869",
    "sg:postcode":"20142",
    "sg:province":"Milano",
    "wof:name":"Fratelli Elli M.& R.(s.r.l.)",
    "wof:placetype":"venue"
},
  "geometry": {"coordinates":[9.171894,45.441895],"type":"Point"}
}