{
  "type": "Feature",
  "properties": {
    "addr:full":"79, Localita' Montalpero 52026 Pian Di Sco Pian di Sco Arezzo 52026",
    "addr:postcode":"52026;52026",
    "addr:street":"Localita ' Montalpero",
    "iso:country":"IT",
    "sg:address":"79, Localita' Montalpero 52026 Pian Di Sco",
    "sg:city":"Pian di Sco",
    "sg:classifiers":[
        {
            "category":"Manufacturing",
            "subcategory":"Metals",
            "type":"Manufacturing & Wholesale Goods"
        }
    ],
    "sg:phone":"+39 39055965634",
    "sg:postcode":"52026",
    "sg:province":"Arezzo",
    "sg:tags":[
        "processing"
    ],
    "wof:name":"Biesse Galvanica S.r.l.",
    "wof:placetype":"venue"
},
  "geometry": {"coordinates":[11.4989328384,43.6158370972],"type":"Point"}
}