{
  "type": "Feature",
  "properties": {
    "iso:country":"IT",
    "sg:address":"25011 Calcinato",
    "sg:city":"Calcinato",
    "sg:orig_category":"Arredamento Alberghi",
    "sg:phone":"+39 030 963147",
    "sg:postcode":"25011",
    "sg:province":"Brescia",
    "wof:name":"Classik Arredo Snc",
    "wof:placetype":"venue"
},
  "geometry": {"coordinates":[10.394577,45.477306],"type":"Point"}
}