{
  "type": "Feature",
  "properties": {
    "iso:country":"IT",
    "sg:address":"20052 Monza",
    "sg:city":"Monza",
    "sg:orig_category":"Accessori Moda D'abbigliamento",
    "sg:phone":"+39 039 200 1856",
    "sg:postcode":"20052",
    "sg:province":"Milano",
    "sg:website":"http://www.fradan.net",
    "wof:name":"Fradan Snc",
    "wof:placetype":"venue"
},
  "geometry": {"coordinates":[9.273341,45.537621],"type":"Point"}
}