{
  "type": "Feature",
  "properties": {
    "iso:country":"IT",
    "sg:address":"31040 Levada Di Pederobba",
    "sg:city":"Pederobba",
    "sg:orig_category":"Articoli Medico-sanitari Ed Ortopedici",
    "sg:phone":"+39 0423 648246",
    "sg:postcode":"31040",
    "sg:province":"Treviso",
    "wof:name":"Manifattura Di Bigolino Srl",
    "wof:placetype":"venue"
},
  "geometry": {"coordinates":[11.954953,45.877998],"type":"Point"}
}