{
  "type": "Feature",
  "properties": {
    "iso:country":"IT",
    "sg:address":"81020 San Nicola La Strada",
    "sg:city":"San Nicola la Strada",
    "sg:orig_category":"Prodotti Chimici Secondari. Macchine E Forniture Per Ecologia E Smaltimento Rifiuti. Forniture Per Attivita' Industriali",
    "sg:phone":"+39 0823 452055",
    "sg:postcode":"81020",
    "sg:province":"Caserta",
    "wof:name":"D&c Service",
    "wof:placetype":"venue"
},
  "geometry": {"coordinates":[14.3323707581,41.0528144836],"type":"Point"}
}