{
  "type": "Feature",
  "properties": {
    "addr:full":"12050 Guarene Guarene Cuneo 12050",
    "addr:housenumber":"12050",
    "addr:postcode":"12050",
    "addr:street":"Guarene",
    "iso:country":"IT",
    "sg:address":"12050 Guarene",
    "sg:city":"Guarene",
    "sg:orig_category":"Petroli, Gas E Combustibili",
    "sg:phone":"+39 0173 366496",
    "sg:postcode":"12050",
    "sg:province":"Cuneo",
    "wof:name":"Restiani Spa",
    "wof:placetype":"venue"
},
  "geometry": {"coordinates":[8.0416984558,44.7249717712],"type":"Point"}
}