{
  "type": "Feature",
  "properties": {
    "iso:country":"IT",
    "sg:address":"10060 Frossasco",
    "sg:city":"Frossasco",
    "sg:orig_category":"Salotti, Poltrone, Sedie E Tavoli",
    "sg:phone":"+39 0121 352865",
    "sg:postcode":"10060",
    "sg:province":"Torino",
    "wof:name":"Mobilimercato Srl",
    "wof:placetype":"venue"
},
  "geometry": {"coordinates":[7.364475,44.916859],"type":"Point"}
}