{
  "type": "Feature",
  "properties": {
    "iso:country":"IT",
    "sg:address":"41012 Carpi",
    "sg:city":"Carpi",
    "sg:classifiers":[
        {
            "category":"Shopping",
            "subcategory":"Clothing, Apparel, & Fashions",
            "type":"Retail Goods"
        }
    ],
    "sg:phone":"+39 059 686617",
    "sg:postcode":"41012",
    "sg:province":"Modena",
    "sg:tags":[
        "knitwear",
        "furs",
        "clothing"
    ],
    "wof:name":"Creazioni Midal Snc",
    "wof:placetype":"venue"
},
  "geometry": {"coordinates":[10.889363,44.792583],"type":"Point"}
}