{
  "type": "Feature",
  "properties": {
    "addr:full":"20090 Trezzano Sul Naviglio Trezzano sul Naviglio Milano 20090",
    "addr:postcode":"20090;20090",
    "iso:country":"IT",
    "sg:address":"20090 Trezzano Sul Naviglio",
    "sg:city":"Trezzano sul Naviglio",
    "sg:orig_category":"Materiali E Componenti Elettrotecnici",
    "sg:phone":"+39 02 445 9628",
    "sg:postcode":"20090",
    "sg:province":"Milano",
    "wof:name":"Legrand S.p.a.",
    "wof:placetype":"venue"
},
  "geometry": {"coordinates":[9.047612,45.427395],"type":"Point"}
}