{
  "type": "Feature",
  "properties": {
    "iso:country":"IT",
    "sg:address":"24122 Bergamo",
    "sg:city":"Bergamo",
    "sg:orig_category":"Ceramiche: Prodotti E Lavorazioni. Forniture Per Attivita' Industriali",
    "sg:phone":"+39 035 212560",
    "sg:postcode":"24122",
    "sg:province":"Bergamo",
    "wof:name":"Arte Mediterranea",
    "wof:placetype":"venue"
},
  "geometry": {"coordinates":[9.707167,45.690708],"type":"Point"}
}