{
  "type": "Feature",
  "properties": {
    "iso:country":"IT",
    "sg:address":"37010 Costermano",
    "sg:city":"Costermano",
    "sg:orig_category":"Ospedali E Servizi Sanitari",
    "sg:phone":"+39 045 720 0012",
    "sg:postcode":"37010",
    "sg:province":"Verona",
    "wof:name":"Bianchi Bendinelli Elvira",
    "wof:placetype":"venue"
},
  "geometry": {"coordinates":[10.73935,45.587063],"type":"Point"}
}