{
  "type": "Feature",
  "properties": {
    "addr:full":"Via Visconti Alex 4/6 20151 Milano Milano Milano 20151",
    "addr:housenumber":"4 / 6",
    "addr:postcode":"20151;20151",
    "addr:street":"Via Visconti Alex",
    "iso:country":"IT",
    "sg:address":"Via Visconti Alex 4/6 20151 Milano",
    "sg:city":"Milano",
    "sg:classifiers":[
        {
            "category":"Government",
            "subcategory":"Office",
            "type":"Public Place"
        }
    ],
    "sg:phone":"+39 02 353 8026",
    "sg:postcode":"20151",
    "sg:province":"Milano",
    "sg:tags":[
        "planning"
    ],
    "sg:website":"www.aercoplan.it",
    "wof:name":"Aer Coplan Srl",
    "wof:placetype":"venue"
},
  "geometry": {"coordinates":[9.203226,45.482468],"type":"Point"}
}