{
  "type": "Feature",
  "properties": {
    "iso:country":"IT",
    "sg:address":"37057 San Giovanni Lupatoto",
    "sg:city":"San Giovanni Lupatoto",
    "sg:orig_category":"Materiali Semilavorati Metallici",
    "sg:phone":"+39 045 828 3811",
    "sg:postcode":"37057",
    "sg:province":"Verona",
    "wof:name":"Beza Srl",
    "wof:placetype":"venue"
},
  "geometry": {"coordinates":[11.016679,45.394787],"type":"Point"}
}