{
  "type": "Feature",
  "properties": {
    "addr:full":"23822 Bellano Bellano Lecco 23822",
    "addr:postcode":"23822;23822",
    "iso:country":"IT",
    "sg:address":"23822 Bellano",
    "sg:city":"Bellano",
    "sg:orig_category":"Tessuti E Stoffe",
    "sg:phone":"+39 0341 820182",
    "sg:postcode":"23822",
    "sg:province":"Lecco",
    "wof:name":"Lazzari Adriano",
    "wof:placetype":"venue"
},
  "geometry": {"coordinates":[9.303487,46.041527],"type":"Point"}
}