{
  "type": "Feature",
  "properties": {
    "iso:country":"IT",
    "sg:address":"Loc S. Zeno Strada 56b 52100 Arezzo",
    "sg:city":"Arezzo",
    "sg:orig_category":"Non-classified Establishments",
    "sg:phone":"+39 0575 959090",
    "sg:postcode":"52100",
    "sg:province":"Arezzo",
    "sg:website":"www.arezzochains.com",
    "wof:name":"Arezzo Chains Srl",
    "wof:placetype":"venue"
},
  "geometry": {"coordinates":[11.863062,43.471203],"type":"Point"}
}