{
  "type": "Feature",
  "properties": {
    "iso:country":"IT",
    "sg:address":"00165 Roma",
    "sg:city":"Roma",
    "sg:orig_category":"Prodotti Alimentari",
    "sg:phone":"+39 06 3938 8773",
    "sg:postcode":"00165",
    "sg:province":"Roma",
    "sg:website":"http://www.dibal.com",
    "wof:name":"Dibal Italia Srl",
    "wof:placetype":"venue"
},
  "geometry": {"coordinates":[12.4423856735,41.9002876282],"type":"Point"}
}