{
  "type": "Feature",
  "properties": {
    "addr:full":"Corso Garibaldi 111/113; Valenza; 15048 Valenza Alessandria 15048",
    "addr:housenumber":"111 / 113",
    "addr:postcode":"15048;15048",
    "addr:street":"Corso Garibaldi;Valenza",
    "iso:country":"IT",
    "sg:address":"Corso Garibaldi 111/113; Valenza; 15048",
    "sg:city":"Valenza",
    "sg:classifiers":[
        {
            "category":"Banks & Credit Unions",
            "subcategory":"Bank",
            "type":"Services"
        }
    ],
    "sg:phone":"+39 0131 921111",
    "sg:postcode":"15048",
    "sg:province":"Alessandria",
    "wof:name":"Istituto Bancario, San Paolo Di Torino Spa",
    "wof:placetype":"venue"
},
  "geometry": {"coordinates":[8.643903,45.011799],"type":"Point"}
}