{
  "type": "Feature",
  "properties": {
    "addr:full":"Via Nazionale 35 23030 Chiuro Chiuro Sondrio 23030",
    "addr:housenumber":"35",
    "addr:postcode":"23030;23030",
    "addr:street":"Via Nazionale",
    "iso:country":"IT",
    "sg:address":"Via Nazionale 35 23030 Chiuro",
    "sg:city":"Chiuro",
    "sg:classifiers":[
        {
            "category":"Government",
            "subcategory":"Court House",
            "type":"Public Place"
        }
    ],
    "sg:phone":"+39 0342 482329",
    "sg:postcode":"23030",
    "sg:province":"Sondrio",
    "sg:tags":[
        "accommodation",
        "furniture"
    ],
    "sg:website":"www.folini.com",
    "wof:name":"Folini Arredamenti S.r.l.",
    "wof:placetype":"venue"
},
  "geometry": {"coordinates":[10.000202,46.164715],"type":"Point"}
}