{
  "type": "Feature",
  "properties": {
    "iso:country":"IT",
    "sg:address":"100, Via Araldi Antonio 41100 Modena",
    "sg:city":"Modena",
    "sg:classifiers":[
        {
            "category":"Manufacturing",
            "subcategory":"Food",
            "type":"Manufacturing & Wholesale Goods"
        }
    ],
    "sg:phone":"+39 39059374402",
    "sg:postcode":"41100",
    "sg:province":"Modena",
    "sg:tags":[
        "equipment",
        "processing",
        "-",
        "machinery"
    ],
    "wof:name":"Officine Roncaglia (s.p.a.)",
    "wof:placetype":"venue"
},
  "geometry": {"coordinates":[10.9252195358,44.6470794678],"type":"Point"}
}