{
  "type": "Feature",
  "properties": {
    "addr:full":"18100 Imperia Imperia Imperia 18100",
    "addr:postcode":"18100;18100",
    "iso:country":"IT",
    "sg:address":"18100 Imperia",
    "sg:city":"Imperia",
    "sg:orig_category":"Servizi E Lavori Per Abbigliamento E Pelletterie",
    "sg:phone":"+39 0183 291683",
    "sg:postcode":"18100",
    "sg:province":"Imperia",
    "wof:name":"Ardoino Feola Pellicce",
    "wof:placetype":"venue"
},
  "geometry": {"coordinates":[8.064083,43.912491],"type":"Point"}
}