{
  "type": "Feature",
  "properties": {
    "iso:country":"IT",
    "sg:address":"00185 Roma",
    "sg:city":"Roma",
    "sg:orig_category":"Scuole E Servizi Scolastici. Ospedali E Servizi Sanitari",
    "sg:phone":"+39 06 7720 2869",
    "sg:postcode":"00185",
    "sg:province":"Roma",
    "wof:name":"Istituto Carlo Amore Srl",
    "wof:placetype":"venue"
},
  "geometry": {"coordinates":[12.44056,41.776463],"type":"Point"}
}