{
  "type": "Feature",
  "properties": {
    "addr:full":"3, Via Banfi 20025 Legnano Legnano Milano 20025",
    "addr:postcode":"20025;20025",
    "addr:street":"Via Banfi",
    "iso:country":"IT",
    "sg:address":"3, Via Banfi 20025 Legnano",
    "sg:city":"Legnano",
    "sg:classifiers":[
        {
            "category":"Shopping",
            "type":"Retail Goods"
        }
    ],
    "sg:phone":"+39 0331 455162",
    "sg:postcode":"20025",
    "sg:province":"Milano",
    "sg:tags":[
        "finished",
        "-",
        "metallic"
    ],
    "wof:name":"A.f.t. - Advanced Flow Technology Srl",
    "wof:placetype":"venue"
},
  "geometry": {"coordinates":[8.9171867371,45.5925559998],"type":"Point"}
}