{
  "type": "Feature",
  "properties": {
    "iso:country":"IT",
    "sg:address":"32/34, V. Industria - Povolaro",
    "sg:city":"Dueville",
    "sg:classifiers":[
        {
            "category":"Retail",
            "subcategory":"Animal Services",
            "type":"Services"
        }
    ],
    "sg:phone":"+39 0444 360100",
    "sg:postcode":"36031",
    "sg:province":"Vicenza",
    "sg:tags":[
        "breeding"
    ],
    "sg:website":"http://www.askoll.it",
    "wof:name":"Askoll Due Spa",
    "wof:placetype":"venue"
},
  "geometry": {"coordinates":[11.569678,45.619286],"type":"Point"}
}