{
  "type": "Feature",
  "properties": {
    "addr:full":"09028 Sestu Sestu Cagliari 09028",
    "addr:postcode":"09028;09028",
    "iso:country":"IT",
    "sg:address":"09028 Sestu",
    "sg:city":"Sestu",
    "sg:orig_category":"Servizi E Lavori Per Industria Alimentare E Bevande",
    "sg:phone":"+39 070 230016",
    "sg:postcode":"09028",
    "sg:province":"Cagliari",
    "wof:name":"Mercato Agroalimentare Della Sardegna S.p.a.",
    "wof:placetype":"venue"
},
  "geometry": {"coordinates":[9.087178,39.301407],"type":"Point"}
}