{
  "type": "Feature",
  "properties": {
    "addr:full":"26020 Agnadello Agnadello Cremona 26020",
    "addr:postcode":"26020;26020",
    "iso:country":"IT",
    "sg:address":"26020 Agnadello",
    "sg:city":"Agnadello",
    "sg:orig_category":"Macchine, Impianti Ed Attrezzature Per Industria Alimentare E Bevande",
    "sg:phone":"+39 0373 936004",
    "sg:postcode":"26020",
    "sg:province":"Cremona",
    "wof:name":"D&vi Inox Srl",
    "wof:placetype":"venue"
},
  "geometry": {"coordinates":[9.558129,45.445316],"type":"Point"}
}