{
  "type": "Feature",
  "properties": {
    "iso:country":"IT",
    "sg:address":"20124 Milano",
    "sg:city":"Milano",
    "sg:orig_category":"Ristorazione E Locali Pubblici Affini. Ristoranti Ed Esercizi Affini. Servizi Ausiliari Di Ristorazione E Di Intrattenimento",
    "sg:phone":"+39 02 670 0479",
    "sg:postcode":"20124",
    "sg:province":"Milano",
    "wof:name":"Il Treno, Arte E Diletto Club",
    "wof:placetype":"venue"
},
  "geometry": {"coordinates":[9.20075,45.481361],"type":"Point"}
}