{
  "type": "Feature",
  "properties": {
    "addr:full":"20090 Buccinasco Buccinasco Milano 20090",
    "addr:postcode":"20090;20090",
    "iso:country":"IT",
    "sg:address":"20090 Buccinasco",
    "sg:city":"Buccinasco",
    "sg:orig_category":"Minuterie Metalliche E Ferramenta",
    "sg:phone":"+39 02 488 0289",
    "sg:postcode":"20090",
    "sg:province":"Milano",
    "sg:website":"http://www.imacomponentistica.it",
    "wof:name":"Ima Componentistica Srl",
    "wof:placetype":"venue"
},
  "geometry": {"coordinates":[9.1086139679,45.4221038818],"type":"Point"}
}