{
  "type": "Feature",
  "properties": {
    "addr:full":"87064 Corigliano Calabro Corigliano Calabro Cosenza 87064",
    "addr:postcode":"87064;87064",
    "iso:country":"IT",
    "sg:address":"87064 Corigliano Calabro",
    "sg:city":"Corigliano Calabro",
    "sg:orig_category":"Arredo Cucina Ed Elettrodomestici",
    "sg:phone":"+39 0983 851305",
    "sg:postcode":"87064",
    "sg:province":"Cosenza",
    "sg:website":"http://www.ladycucine.it",
    "wof:name":"Lady Srl",
    "wof:placetype":"venue"
},
  "geometry": {"coordinates":[16.511271,39.627613],"type":"Point"}
}