{
  "type": "Feature",
  "properties": {
    "addr:full":"00197 Roma Roma Roma 00197",
    "addr:postcode":"00197;00197",
    "iso:country":"IT",
    "sg:address":"00197 Roma",
    "sg:city":"Roma",
    "sg:orig_category":"Servizi Al Turismo. Ambasciate Ed Enti Internazionali",
    "sg:phone":"+39 06 807 0072",
    "sg:postcode":"00197",
    "sg:province":"Roma",
    "wof:name":"Ambasciata Presso Lo Stato Italiano San Marino (repubblica)",
    "wof:placetype":"venue"
},
  "geometry": {"coordinates":[12.491475,41.929695],"type":"Point"}
}