{
  "type": "Feature",
  "properties": {
    "addr:full":"40, Via Campania 20090 Pieve Emanuele Pieve Emanuele Milano 20090",
    "addr:postcode":"20090;20090",
    "addr:street":"Via Campania",
    "iso:country":"IT",
    "sg:address":"40, Via Campania 20090 Pieve Emanuele",
    "sg:city":"Pieve Emanuele",
    "sg:classifiers":[
        {
            "category":"Shopping",
            "subcategory":"Computers & Home Electronics",
            "type":"Retail Goods"
        }
    ],
    "sg:phone":"+39 02 9042 0039",
    "sg:postcode":"20090",
    "sg:province":"Milano",
    "sg:tags":[
        "electronic",
        "electrical",
        "equipment"
    ],
    "wof:name":"Coel Motori S.r.l.",
    "wof:placetype":"venue"
},
  "geometry": {"coordinates":[9.176364,45.375111],"type":"Point"}
}