{
  "type": "Feature",
  "properties": {
    "iso:country":"IT",
    "sg:address":"83100 Avellino",
    "sg:city":"Avellino",
    "sg:classifiers":[
        {
            "category":"Health Services",
            "subcategory":"Hospital",
            "type":"Services"
        }
    ],
    "sg:phone":"+39 0825 781515",
    "sg:postcode":"83100",
    "sg:province":"Avellino",
    "sg:tags":[
        "supply",
        "medical-health",
        "equipment",
        "orthopedic",
        "products",
        "systems"
    ],
    "wof:name":"Ks Italia Sas",
    "wof:placetype":"venue"
},
  "geometry": {"coordinates":[14.858926,40.827499],"type":"Point"}
}