{
  "type": "Feature",
  "properties": {
    "addr:full":"Via Pier Santi Mattarella 10 36043 Camisano Vicentino Camisano Vicentino Vicenza 36043",
    "addr:housenumber":"10",
    "addr:postcode":"36043;36043",
    "addr:street":"Via Pier Santi Mattarella;Vicentino",
    "iso:country":"IT",
    "sg:address":"Via Pier Santi Mattarella 10 36043 Camisano Vicentino",
    "sg:city":"Camisano Vicentino",
    "sg:classifiers":[
        {
            "category":"Wholesale",
            "subcategory":"Vending Machines",
            "type":"Manufacturing & Wholesale Goods"
        }
    ],
    "sg:phone":"+39 0444 411093",
    "sg:postcode":"36043",
    "sg:province":"Vicenza",
    "sg:tags":[
        "ceramic",
        "processing"
    ],
    "wof:name":"Csc Srl",
    "wof:placetype":"venue"
},
  "geometry": {"coordinates":[11.526389122,45.5752792358],"type":"Point"}
}