{
  "type": "Feature",
  "properties": {
    "iso:country":"IT",
    "sg:address":"80132 Napoli",
    "sg:city":"Napoli",
    "sg:orig_category":"Editoria",
    "sg:phone":"+39 081 417452",
    "sg:postcode":"80132",
    "sg:province":"Napoli",
    "sg:website":"http://www.lacanzonetta.it",
    "wof:name":"La Canzonetta Snc",
    "wof:placetype":"venue"
},
  "geometry": {"coordinates":[14.246861,40.834728],"type":"Point"}
}