{
  "type": "Feature",
  "properties": {
    "iso:country":"IT",
    "sg:address":"70013 Castellana Grotte",
    "sg:city":"Castellana Grotte",
    "sg:orig_category":"Autoveicoli Industriali",
    "sg:phone":"+39 080 496 5384",
    "sg:postcode":"70013",
    "sg:province":"Bari",
    "wof:name":"Pollicelli Allestimenti Veicoli Industriali",
    "wof:placetype":"venue"
},
  "geometry": {"coordinates":[17.068308,40.850853],"type":"Point"}
}