{
  "type": "Feature",
  "properties": {
    "addr:full":"20123 Milano Milano Milano 20123",
    "addr:postcode":"20123;20123",
    "iso:country":"IT",
    "sg:address":"20123 Milano",
    "sg:city":"Milano",
    "sg:orig_category":"Cancelleria",
    "sg:phone":"+39 02 832 1030",
    "sg:postcode":"20123",
    "sg:province":"Milano",
    "wof:name":"Sodiat Sas",
    "wof:placetype":"venue"
},
  "geometry": {"coordinates":[9.173729,45.461334],"type":"Point"}
}