{
  "type": "Feature",
  "properties": {
    "addr:full":"70124 Bari Bari Bari 70124",
    "addr:postcode":"70124;70124",
    "iso:country":"IT",
    "sg:address":"70124 Bari",
    "sg:city":"Bari",
    "sg:orig_category":"Apparecchiature E Sistemi Per Magazzinaggio E Movimentazione",
    "sg:phone":"+39 080 504 1044",
    "sg:postcode":"70124",
    "sg:province":"Bari",
    "wof:name":"Elevatori Srl",
    "wof:placetype":"venue"
},
  "geometry": {"coordinates":[16.859587,41.096497],"type":"Point"}
}