{
  "type": "Feature",
  "properties": {
    "addr:full":"20095 Cusano Milanino Cusano Milanino Milano 20095",
    "addr:postcode":"20095;20095",
    "iso:country":"IT",
    "sg:address":"20095 Cusano Milanino",
    "sg:city":"Cusano Milanino",
    "sg:orig_category":"Autogru - Noleggio",
    "sg:phone":"+39 02 6640 1058",
    "sg:postcode":"20095",
    "sg:province":"Milano",
    "sg:website":"http://www.tarabelloni.it",
    "wof:name":"Tarabelloni Marino",
    "wof:placetype":"venue"
},
  "geometry": {"coordinates":[9.179644,45.558048],"type":"Point"}
}