{
  "type": "Feature",
  "properties": {
    "iso:country":"IT",
    "sg:address":"06012 Citt\u00e0 Di Castello",
    "sg:classifiers":[
        {
            "category":"Banks & Credit Unions",
            "subcategory":"Investment Brokerage",
            "type":"Services"
        }
    ],
    "sg:phone":"+39 075 855 3285",
    "sg:postcode":"06012",
    "sg:province":"Perugia",
    "sg:tags":[
        "services",
        "various",
        "auxiliary",
        "transport",
        "public"
    ],
    "wof:name":"Campriani Mario",
    "wof:placetype":"venue"
},
  "geometry": {"coordinates":[12.23891,43.458618],"type":"Point"}
}