{
  "type": "Feature",
  "properties": {
    "iso:country":"IT",
    "sg:address":"12043 Canale",
    "sg:city":"Canale",
    "sg:orig_category":"Arredamenti - Vendita Al Dettaglio",
    "sg:phone":"+39 0173 979251",
    "sg:postcode":"12043",
    "sg:province":"Cuneo",
    "wof:name":"M.i.m. Masoero & Icardi Snc",
    "wof:placetype":"venue"
},
  "geometry": {"coordinates":[7.996784,44.76437],"type":"Point"}
}