{
  "type": "Feature",
  "properties": {
    "addr:full":"91019 Valderice Valderice Trapani 91019",
    "addr:postcode":"91019;91019",
    "iso:country":"IT",
    "sg:address":"91019 Valderice",
    "sg:city":"Valderice",
    "sg:orig_category":"Banche Ed Istituti Di Credito E Risparmio",
    "sg:phone":"+39 0923 833655",
    "sg:postcode":"91019",
    "sg:province":"Trapani",
    "wof:name":"Banca Di Credito Cooperativo Ericina Di Valderice",
    "wof:placetype":"venue"
},
  "geometry": {"coordinates":[12.612322,38.03688],"type":"Point"}
}