{
  "type": "Feature",
  "properties": {
    "addr:full":"20, Via S. G. Bosco 90044 Carini Carini Palermo 90044",
    "addr:postcode":"90044;90044",
    "addr:street":"Via S. G. Bosco",
    "iso:country":"IT",
    "sg:address":"20, Via S. G. Bosco 90044 Carini",
    "sg:city":"Carini",
    "sg:classifiers":[
        {
            "category":"Food & Beverages",
            "subcategory":"Groceries & Convenience Stores",
            "type":"Retail Goods"
        }
    ],
    "sg:phone":"+39 091 866 8070",
    "sg:postcode":"90044",
    "sg:province":"Palermo",
    "sg:tags":[
        "product",
        "related"
    ],
    "wof:name":"Maza Promotion Di Zimbardo Angelo S.a.s.",
    "wof:placetype":"venue"
},
  "geometry": {"coordinates":[13.2467327118,38.1954956055],"type":"Point"}
}