{
  "type": "Feature",
  "properties": {
    "addr:full":"00187 Roma Roma Roma 00187",
    "addr:postcode":"00187;00187",
    "iso:country":"IT",
    "sg:address":"00187 Roma",
    "sg:city":"Roma",
    "sg:orig_category":"Articoli Da Regalo. Tempo Libero - Articoli E Forniture. Regalistica Aziendale",
    "sg:phone":"+39 06 4201 1064",
    "sg:postcode":"00187",
    "sg:province":"Roma",
    "wof:name":"Johnson Stefano Stabilimento",
    "wof:placetype":"venue"
},
  "geometry": {"coordinates":[12.369829,42.12936],"type":"Point"}
}