{
  "type": "Feature",
  "properties": {
    "addr:full":"03013 Ferentino Ferentino Frosinone 03013",
    "addr:postcode":"03013;03013",
    "iso:country":"IT",
    "sg:address":"03013 Ferentino",
    "sg:city":"Ferentino",
    "sg:orig_category":"Carta Da Parati - Produzione E Ingrosso",
    "sg:phone":"+39 0775 39381",
    "sg:postcode":"03013",
    "sg:province":"Frosinone",
    "sg:website":"http://www.plastisudsrl.it",
    "wof:name":"Plastisud Italia Group Srl",
    "wof:placetype":"venue"
},
  "geometry": {"coordinates":[13.636078,41.542042],"type":"Point"}
}