{
  "type": "Feature",
  "properties": {
    "iso:country":"IT",
    "sg:address":"21, Via Puglie 41012 Carpi",
    "sg:city":"Carpi",
    "sg:classifiers":[
        {
            "category":"Professional",
            "subcategory":"Engineering",
            "type":"Services"
        }
    ],
    "sg:phone":"+39 39059695785",
    "sg:postcode":"41012",
    "sg:province":"Modena",
    "sg:tags":[
        "machine",
        "-",
        "mechanical"
    ],
    "wof:name":"G.m.c. Macchine (s.r.l.)",
    "wof:placetype":"venue"
},
  "geometry": {"coordinates":[10.883416,44.767017],"type":"Point"}
}