{
  "type": "Feature",
  "properties": {
    "iso:country":"IT",
    "sg:address":"20123 Milano",
    "sg:city":"Milano",
    "sg:orig_category":"Agenzie D'affari E Servizi Commerciali",
    "sg:phone":"+39 02 433521",
    "sg:postcode":"20123",
    "sg:province":"Milano",
    "wof:name":"Gl Trade Italia S.r.l.",
    "wof:placetype":"venue"
},
  "geometry": {"coordinates":[9.168196,45.471649],"type":"Point"}
}