{
  "type": "Feature",
  "properties": {
    "iso:country":"IT",
    "sg:address":"424/29, C. Giulio Cesare 10156 Torino",
    "sg:city":"Torino",
    "sg:classifiers":[
        {
            "category":"Professional",
            "subcategory":"Engineering",
            "type":"Services"
        }
    ],
    "sg:phone":"+39 011 222 1111",
    "sg:postcode":"10156",
    "sg:province":"Torino",
    "sg:tags":[
        "machine",
        "-",
        "mechanical"
    ],
    "wof:name":"Gamfior Spa",
    "wof:placetype":"venue"
},
  "geometry": {"coordinates":[7.700382,45.103035],"type":"Point"}
}