{
  "type": "Feature",
  "properties": {
    "iso:country":"IT",
    "sg:address":"00023 Arsoli",
    "sg:city":"Arsoli",
    "sg:orig_category":"Pompe. Macchine, Strumenti Ed Apparecchi Per Attivita' Industriali",
    "sg:phone":"+39 0774 920215",
    "sg:postcode":"00023",
    "sg:province":"Roma",
    "wof:name":"Seven Seas Sas",
    "wof:placetype":"venue"
},
  "geometry": {"coordinates":[13.0140686035,42.0430717468],"type":"Point"}
}