{
  "type": "Feature",
  "properties": {
    "addr:full":"25081 Bedizzole Bedizzole Brescia 25081",
    "addr:postcode":"25081;25081",
    "iso:country":"IT",
    "sg:address":"25081 Bedizzole",
    "sg:city":"Bedizzole",
    "sg:orig_category":"Macchine, Impianti Ed Attrezzature Industria Chimica. Pompe",
    "sg:phone":"+39 030 687 1184",
    "sg:postcode":"25081",
    "sg:province":"Brescia",
    "sg:website":"http://www.watson-marlow.com./watso",
    "wof:name":"Watson-marlow Srl",
    "wof:placetype":"venue"
},
  "geometry": {"coordinates":[10.409131,45.495335],"type":"Point"}
}