{
  "type": "Feature",
  "properties": {
    "addr:full":"26900 Lodi Lodi Lodi 26900",
    "addr:postcode":"26900;26900",
    "iso:country":"IT",
    "sg:address":"26900 Lodi",
    "sg:city":"Lodi",
    "sg:orig_category":"Arredo Camera Letto E Complementi",
    "sg:phone":"+39 0371 412822",
    "sg:postcode":"26900",
    "sg:province":"Lodi",
    "wof:name":"Federflex",
    "wof:placetype":"venue"
},
  "geometry": {"coordinates":[9.500079,45.321766],"type":"Point"}
}