{
  "type": "Feature",
  "properties": {
    "addr:full":"20, V. San Domenico 20010 Bareggio Bareggio Milano 20010",
    "addr:housenumber":"20",
    "addr:postcode":"20010;20010",
    "addr:street":"V. San",
    "iso:country":"IT",
    "sg:address":"20, V. San Domenico 20010 Bareggio",
    "sg:city":"Bareggio",
    "sg:classifiers":[
        {
            "category":"Professional",
            "subcategory":"Engineering",
            "type":"Services"
        }
    ],
    "sg:phone":"+39 39029028496",
    "sg:postcode":"20010",
    "sg:province":"Milano",
    "sg:tags":[
        "machine",
        "-",
        "mechanical"
    ],
    "sg:website":"http://www.syntech.it",
    "wof:name":"Syntech Engineering Srl",
    "wof:placetype":"venue"
},
  "geometry": {"coordinates":[9.00004,45.488518],"type":"Point"}
}