{
  "type": "Feature",
  "properties": {
    "iso:country":"IT",
    "sg:address":"80078 Pozzuoli",
    "sg:city":"Pozzuoli",
    "sg:orig_category":"Prodotti Chimici Secondari. Materiali Edili",
    "sg:phone":"+39 081 526 9668",
    "sg:postcode":"80078",
    "sg:province":"Napoli",
    "wof:name":"Indek Srl",
    "wof:placetype":"venue"
},
  "geometry": {"coordinates":[14.120218277,40.8567962646],"type":"Point"}
}