{
  "type": "Feature",
  "properties": {
    "addr:full":"55019 Villa Basilica Villa Basilica Lucca 55019",
    "addr:housenumber":"55019",
    "addr:postcode":"55019",
    "addr:street":"Villa",
    "iso:country":"IT",
    "sg:address":"55019 Villa Basilica",
    "sg:city":"Villa Basilica",
    "sg:orig_category":"Macchine, Impianti E Forniture Per Industria Grafica, Cartaria E Cartotecnica",
    "sg:phone":"+39 0572 43067",
    "sg:postcode":"55019",
    "sg:province":"Lucca",
    "wof:name":"Officina Meccanica Recard Spa",
    "wof:placetype":"venue"
},
  "geometry": {"coordinates":[10.630917,43.950718],"type":"Point"}
}