{
  "type": "Feature",
  "properties": {
    "iso:country":"IT",
    "sg:address":"16, Via Puglie 20098 San Giuliano Milanese",
    "sg:city":"San Giuliano Milanese",
    "sg:classifiers":[
        {
            "category":"Banks & Credit Unions",
            "subcategory":"Investment Brokerage",
            "type":"Services"
        }
    ],
    "sg:phone":"+39 02 9828 9290",
    "sg:postcode":"20098",
    "sg:province":"Milano",
    "sg:tags":[
        "-",
        "transport",
        "related"
    ],
    "wof:name":"Carreras Italia Srl",
    "wof:placetype":"venue"
},
  "geometry": {"coordinates":[9.250021,45.395851],"type":"Point"}
}