{
  "type": "Feature",
  "properties": {
    "iso:country":"IT",
    "sg:address":"22036 Erba",
    "sg:city":"Erba",
    "sg:orig_category":"Macchine, Impianti Ed Attrezzature Per Abbigliamento E Pelletterie",
    "sg:phone":"+39 031 642328",
    "sg:postcode":"22036",
    "sg:province":"Como",
    "wof:name":"Colmatex",
    "wof:placetype":"venue"
},
  "geometry": {"coordinates":[9.248809,45.81271],"type":"Point"}
}