{
  "type": "Feature",
  "properties": {
    "addr:full":"34, V. Ferdinando Ughelli00179 Roma Roma Roma 00179",
    "addr:housenumber":"34;ughelli00179",
    "addr:postcode":"00179",
    "addr:street":"V. Ferdinando",
    "iso:country":"IT",
    "sg:address":"34, V. Ferdinando Ughelli00179 Roma",
    "sg:city":"Roma",
    "sg:classifiers":[
        {
            "category":"Autos & Motor Vehicles",
            "subcategory":"Automobile Sales",
            "type":"Retail Goods"
        }
    ],
    "sg:phone":"+39 39067887212",
    "sg:postcode":"00179",
    "sg:province":"Roma",
    "sg:tags":[
        "motor-cars"
    ],
    "sg:website":"http://www.paginegialle.it/autobiemmesrl",
    "wof:name":"Autobiemme Srl",
    "wof:placetype":"venue"
},
  "geometry": {"coordinates":[12.5166301727,41.8705062866],"type":"Point"}
}