{
  "type": "Feature",
  "properties": {
    "iso:country":"IT",
    "sg:address":"7/c, Via Di Mezzo Ai Piani 39100 Bolzano",
    "sg:city":"Bolzano",
    "sg:classifiers":[
        {
            "category":"Travel",
            "subcategory":"Travel Agent",
            "type":"Entertainment"
        }
    ],
    "sg:phone":"+39 0471 324030",
    "sg:postcode":"39100",
    "sg:province":"Bolzano/Bozen",
    "sg:tags":[
        "business"
    ],
    "wof:name":"3 P Elettronica S.r.l.",
    "wof:placetype":"venue"
},
  "geometry": {"coordinates":[11.328239,46.461643],"type":"Point"}
}