{
  "type": "Feature",
  "properties": {
    "iso:country":"IT",
    "sg:address":"83024 Monteforte Irpino",
    "sg:city":"Monteforte Irpino",
    "sg:orig_category":"Lavorazioni Meccaniche E Servizi",
    "sg:phone":"+39 0825 681451",
    "sg:postcode":"83024",
    "sg:province":"Avellino",
    "wof:name":"Auto Star Srl",
    "wof:placetype":"venue"
},
  "geometry": {"coordinates":[14.699599,40.899506],"type":"Point"}
}