{
  "type": "Feature",
  "properties": {
    "addr:full":"00040 Pomezia Pomezia Roma 00040",
    "addr:postcode":"00040;roma 00040",
    "iso:country":"IT",
    "sg:address":"00040 Pomezia",
    "sg:city":"Pomezia",
    "sg:orig_category":"Cinematografia E Radiotelevisione. Forniture Per Il Settore Dello Spettacolo",
    "sg:phone":"+39 06 9160 4003",
    "sg:postcode":"00040",
    "sg:province":"Roma",
    "wof:name":"Technicolor",
    "wof:placetype":"venue"
},
  "geometry": {"coordinates":[12.534824,41.673595],"type":"Point"}
}