{
  "type": "Feature",
  "properties": {
    "iso:country":"IT",
    "sg:address":"16129 Genova",
    "sg:city":"Genova",
    "sg:orig_category":"Valvole E Apparecchiature Di Misura",
    "sg:phone":"+39 010 564561",
    "sg:postcode":"16129",
    "sg:province":"Genova",
    "wof:name":"Idrometrica",
    "wof:placetype":"venue"
},
  "geometry": {"coordinates":[8.949579,44.404076],"type":"Point"}
}