{
  "type": "Feature",
  "properties": {
    "iso:country":"IT",
    "sg:address":"38, Via Oltre Brenta 35027 Noventa Padovana",
    "sg:city":"Noventa Padovana",
    "sg:classifiers":[
        {
            "category":"Shopping",
            "subcategory":"Clothing, Apparel, & Fashions",
            "type":"Retail Goods"
        }
    ],
    "sg:phone":"+39 049 980 1282",
    "sg:postcode":"35027",
    "sg:province":"Padova",
    "sg:tags":[
        "clothes"
    ],
    "wof:name":"Chino Trade Agency (s.r.l.)",
    "wof:placetype":"venue"
},
  "geometry": {"coordinates":[12.002361,45.410988],"type":"Point"}
}