{
  "type": "Feature",
  "properties": {
    "addr:full":"42, Via Alba Cortemilia 12055 Diano D'alba Cuneo 12055",
    "addr:postcode":"12055;12055",
    "addr:street":"Via Alba",
    "iso:country":"IT",
    "sg:address":"42, Via Alba Cortemilia 12055 Diano D'alba",
    "sg:classifiers":[
        {
            "category":"Building & Trades",
            "subcategory":"Construction",
            "type":"Services"
        }
    ],
    "sg:phone":"+39 0173 290064",
    "sg:postcode":"12055",
    "sg:province":"Cuneo",
    "sg:tags":[
        "work",
        "public"
    ],
    "wof:name":"Arienti S.r.l.",
    "wof:placetype":"venue"
},
  "geometry": {"coordinates":[8.042427,44.668182],"type":"Point"}
}