{
  "type": "Feature",
  "properties": {
    "addr:full":"20121 Milano Milano Milano 20121",
    "addr:postcode":"20121;20121",
    "iso:country":"IT",
    "sg:address":"20121 Milano",
    "sg:city":"Milano",
    "sg:orig_category":"Studi E Consulenze Legali E Notarili. Avvocati, Notai E Servizi Legali. Professionisti - Studi E Servizi Ed Associazioni Di Interesse Aziendale",
    "sg:phone":"+39 02 794319",
    "sg:postcode":"20121",
    "sg:province":"Milano",
    "wof:name":"Albini Anna",
    "wof:placetype":"venue"
},
  "geometry": {"coordinates":[9.196643,45.471111],"type":"Point"}
}