{
  "type": "Feature",
  "properties": {
    "iso:country":"IT",
    "sg:address":"20069 Vaprio D'adda",
    "sg:orig_category":"Macchine, Impianti Ed Attrezzature Industria Chimica. Vetro: Prodotti E Lavorazioni",
    "sg:phone":"+39 02 909 4088",
    "sg:postcode":"20069",
    "sg:province":"Milano",
    "wof:name":"Penati Soffieria",
    "wof:placetype":"venue"
},
  "geometry": {"coordinates":[9.531033,45.579647],"type":"Point"}
}