{
  "type": "Feature",
  "properties": {
    "iso:country":"IT",
    "sg:address":"76, Via Sant'antonio 45010 Ceregnano",
    "sg:city":"Ceregnano",
    "sg:classifiers":[
        {
            "category":"Autos & Motor Vehicles",
            "subcategory":"Automobile Sales",
            "type":"Retail Goods"
        }
    ],
    "sg:phone":"+39 0425 937525",
    "sg:postcode":"45010",
    "sg:province":"Rovigo",
    "sg:tags":[
        "motor-cars"
    ],
    "wof:name":"Eredi Rossini Luigino & C. S.n.c.",
    "wof:placetype":"venue"
},
  "geometry": {"coordinates":[11.7880191803,45.0470542908],"type":"Point"}
}