{
  "type": "Feature",
  "properties": {
    "iso:country":"IT",
    "sg:address":"90147 Palermo",
    "sg:city":"Palermo",
    "sg:orig_category":"Macchine E Forniture Per Ecologia E Smaltimento Rifiuti. Macchine, Strumenti Ed Apparecchi Per Attivita' Industriali",
    "sg:phone":"+39 091 679 0143",
    "sg:postcode":"90147",
    "sg:province":"Palermo",
    "sg:website":"http://www.vericael.com",
    "wof:name":"Ve.ri.ca.el. Srl",
    "wof:placetype":"venue"
},
  "geometry": {"coordinates":[13.313894,38.162819],"type":"Point"}
}