{
  "type": "Feature",
  "properties": {
    "iso:country":"IT",
    "sg:address":"28, Piazza Croce Benedetto 15048 Valenza",
    "sg:city":"Valenza",
    "sg:classifiers":[
        {
            "category":"Shopping",
            "subcategory":"Jewelry",
            "type":"Retail Goods"
        }
    ],
    "sg:phone":"+39 0131 953064",
    "sg:postcode":"15048",
    "sg:province":"Alessandria",
    "sg:tags":[
        "jewellery"
    ],
    "wof:name":"Lo Galbo Giovanni Battista S.a.s.",
    "wof:placetype":"venue"
},
  "geometry": {"coordinates":[8.636889,45.006092],"type":"Point"}
}