{
  "type": "Feature",
  "properties": {
    "iso:country":"IT",
    "sg:address":"50018 Scandicci",
    "sg:city":"Scandicci",
    "sg:classifiers":[
        {
            "category":"Home & Garden",
            "subcategory":"Furniture",
            "type":"Retail Goods"
        }
    ],
    "sg:phone":"+39 055 735 0517",
    "sg:postcode":"50018",
    "sg:province":"Firenze",
    "sg:tags":[
        "furnishing"
    ],
    "sg:website":"http://www.fornituresedie.com",
    "wof:name":"Forniture Sedie Di Lucia Bardini & C. Snc",
    "wof:placetype":"venue"
},
  "geometry": {"coordinates":[11.1778650284,43.7614440918],"type":"Point"}
}