{
  "type": "Feature",
  "properties": {
    "addr:full":"19, Via Rubens Pietro 20148 Milano Milano Milano 20148",
    "addr:postcode":"20148;20148",
    "addr:street":"Via Rubens Pietro",
    "iso:country":"IT",
    "sg:address":"19, Via Rubens Pietro 20148 Milano",
    "sg:city":"Milano",
    "sg:classifiers":[
        {
            "category":"Professional",
            "subcategory":"Business Services",
            "type":"Services"
        }
    ],
    "sg:phone":"+39 02 4007 4919",
    "sg:postcode":"20148",
    "sg:province":"Milano",
    "sg:tags":[
        "advice"
    ],
    "wof:name":"Alcam (s.r.l.)",
    "wof:placetype":"venue"
},
  "geometry": {"coordinates":[9.143208,45.467232],"type":"Point"}
}