{
  "type": "Feature",
  "properties": {
    "iso:country":"IT",
    "sg:address":"48017 Conselice",
    "sg:city":"Conselice",
    "sg:classifiers":[
        {
            "category":"Health Services",
            "subcategory":"Health Practitioner",
            "type":"Services"
        }
    ],
    "sg:phone":"+39 0545 85295",
    "sg:postcode":"48017",
    "sg:province":"Ravenna",
    "sg:tags":[
        "medici"
    ],
    "wof:name":"Cioni Roberto",
    "wof:placetype":"venue"
},
  "geometry": {"coordinates":[11.829643,44.509811],"type":"Point"}
}