{
  "type": "Feature",
  "properties": {
    "addr:full":"46/9, V. Muratori20137 Milano Milano Milano 20137",
    "addr:housenumber":"46 / 9 v. muratori20137",
    "addr:postcode":"20137",
    "iso:country":"IT",
    "sg:address":"46/9, V. Muratori20137 Milano",
    "sg:city":"Milano",
    "sg:classifiers":[
        {
            "category":"Professional",
            "subcategory":"Engineering",
            "type":"Services"
        }
    ],
    "sg:phone":"+39 39025513514",
    "sg:postcode":"20137",
    "sg:province":"Milano",
    "sg:tags":[
        "machine",
        "-",
        "mechanical"
    ],
    "sg:website":"http://www.luxelettromeccanica.com:ws_end: :mark:ws:http://www.paginegialle.it/luxit",
    "wof:name":"Lux Elettromeccanica Srl",
    "wof:placetype":"venue"
},
  "geometry": {"coordinates":[9.211082,45.450462],"type":"Point"}
}