{
  "type": "Feature",
  "properties": {
    "iso:country":"IT",
    "sg:address":"50063 Figline Valdarno",
    "sg:city":"Figline Valdarno",
    "sg:orig_category":"Piscine Ed Accessori - Costruzione E Manutenzione",
    "sg:phone":"+39 055 953606",
    "sg:postcode":"50063",
    "sg:province":"Firenze",
    "sg:website":"http://www.edenblu.it/acquasport",
    "wof:name":"Acqua Sport Srl",
    "wof:placetype":"venue"
},
  "geometry": {"coordinates":[11.4545459747,43.6389961243],"type":"Point"}
}