{
  "type": "Feature",
  "properties": {
    "iso:country":"IT",
    "sg:address":"59013 Montemurlo",
    "sg:city":"Montemurlo",
    "sg:orig_category":"Tessuti E Stoffe",
    "sg:phone":"+39 0574 650454",
    "sg:postcode":"59013",
    "sg:province":"Prato",
    "wof:name":"Gruppo Produzione Maglia Srl",
    "wof:placetype":"venue"
},
  "geometry": {"coordinates":[11.055368,43.908806],"type":"Point"}
}