{
  "type": "Feature",
  "properties": {
    "iso:country":"IT",
    "sg:address":"Vai Roma 20; Sossano; 36040",
    "sg:city":"Sossano",
    "sg:classifiers":[
        {
            "category":"Banks & Credit Unions",
            "subcategory":"Bank",
            "type":"Services"
        }
    ],
    "sg:phone":"+39 0444 888406",
    "sg:postcode":"36040",
    "sg:province":"Vicenza",
    "wof:name":"Banca Popolare Vicentina",
    "wof:placetype":"venue"
},
  "geometry": {"coordinates":[11.507097,45.357014],"type":"Point"}
}