{
  "type": "Feature",
  "properties": {
    "addr:full":"00153 Roma Roma Roma 00153",
    "addr:postcode":"00153;00153",
    "iso:country":"IT",
    "sg:address":"00153 Roma",
    "sg:city":"Roma",
    "sg:orig_category":"Petroli, Gas E Combustibili",
    "sg:phone":"+39 06 580 3208",
    "sg:postcode":"00153",
    "sg:province":"Roma",
    "wof:name":"Angelini Ascenzo",
    "wof:placetype":"venue"
},
  "geometry": {"coordinates":[12.4755649567,41.8889503479],"type":"Point"}
}