{
  "type": "Feature",
  "properties": {
    "iso:country":"IT",
    "sg:address":"Via Statale Dei Giovi 11b; Grandate; 22070",
    "sg:city":"Grandate",
    "sg:classifiers":[
        {
            "category":"Banks & Credit Unions",
            "subcategory":"Bank",
            "type":"Services"
        }
    ],
    "sg:phone":"+39 031 450595",
    "sg:postcode":"22070",
    "sg:province":"Como",
    "wof:name":"Banca Popolare Di Lecco",
    "wof:placetype":"venue"
},
  "geometry": {"coordinates":[9.054238,45.762001],"type":"Point"}
}