{
  "type": "Feature",
  "properties": {
    "iso:country":"IT",
    "sg:address":"24022 Alzano Lombardo",
    "sg:city":"Alzano Lombardo",
    "sg:orig_category":"Imprese Di Costruzioni Civili Ed Industriali",
    "sg:phone":"+39 035 412 3268",
    "sg:postcode":"24022",
    "sg:province":"Bergamo",
    "sg:website":"http://www.stal.it",
    "wof:name":"S.t.a.l. Srl",
    "wof:placetype":"venue"
},
  "geometry": {"coordinates":[9.722414,45.731781],"type":"Point"}
}