{
  "type": "Feature",
  "properties": {
    "addr:full":"01010 Gradoli Gradoli Viterbo 01010",
    "addr:postcode":"01010;01010",
    "iso:country":"IT",
    "sg:address":"01010 Gradoli",
    "sg:city":"Gradoli",
    "sg:orig_category":"Forniture Per Attivita' Commerciali Ed Artigianali. Forniture Per Attivita' Industriali",
    "sg:phone":"+39 0761 456823",
    "sg:postcode":"01010",
    "sg:province":"Viterbo",
    "wof:name":"Restauro Mobili Il Tarlo",
    "wof:placetype":"venue"
},
  "geometry": {"coordinates":[11.8559627533,42.6445388794],"type":"Point"}
}