{
  "type": "Feature",
  "properties": {
    "iso:country":"IT",
    "sg:address":"26032 Ostiano",
    "sg:city":"Ostiano",
    "sg:orig_category":"Abbigliamento Intimo, Calze E Costumi Da Bagno. Accessori Moda D'abbigliamento",
    "sg:phone":"+39 0372 856330",
    "sg:postcode":"26032",
    "sg:province":"Cremona",
    "wof:name":"Nicost Di Posio Aldo & C. S.n.c.",
    "wof:placetype":"venue"
},
  "geometry": {"coordinates":[9.992465,45.150684],"type":"Point"}
}