{
  "type": "Feature",
  "properties": {
    "iso:country":"IT",
    "sg:address":"20092 Cinisello Balsamo",
    "sg:city":"Cinisello Balsamo",
    "sg:orig_category":"Telecomunicazioni Impianti Ed Apparecchi - Produzione E Ingrosso",
    "sg:phone":"+39 02 660331",
    "sg:postcode":"20092",
    "sg:province":"Milano",
    "wof:name":"Et Srl",
    "wof:placetype":"venue"
},
  "geometry": {"coordinates":[9.224998,45.547836],"type":"Point"}
}