{
  "type": "Feature",
  "properties": {
    "iso:country":"IT",
    "sg:address":"25122 Brescia",
    "sg:city":"Brescia",
    "sg:orig_category":"Servizi Culturali E Per Lo Spettacolo. Servizi Al Turismo. Acqua, Luce, Gas E Societa' Di Esercizio Pubblico",
    "sg:phone":"+39 030 280010",
    "sg:postcode":"25122",
    "sg:province":"Brescia",
    "wof:name":"Associazione Culturale L'immagine",
    "wof:placetype":"venue"
},
  "geometry": {"coordinates":[10.208939,45.547958],"type":"Point"}
}