{
  "type": "Feature",
  "properties": {
    "iso:country":"IT",
    "sg:address":"57033 Marciana Marina",
    "sg:city":"Marciana Marina",
    "sg:orig_category":"Macchine, Impianti Ed Attrezzature Per Industria Alimentare E Bevande",
    "sg:phone":"+39 0565 99514",
    "sg:postcode":"57033",
    "sg:province":"Livorno",
    "wof:name":"Rapanelli Paolo",
    "wof:placetype":"venue"
},
  "geometry": {"coordinates":[10.187135,42.802845],"type":"Point"}
}