{
  "type": "Feature",
  "properties": {
    "iso:country":"IT",
    "sg:address":"74016 Massafra",
    "sg:city":"Massafra",
    "sg:orig_category":"Forniture Per Attivita' Commerciali Ed Artigianali. Arredi Ed Attrezzature Per Attivita' Commerciali Ed Artigianali",
    "sg:phone":"+39 099 880 5940",
    "sg:postcode":"74016",
    "sg:province":"Taranto",
    "wof:name":"Bello Fernando Antonio",
    "wof:placetype":"venue"
},
  "geometry": {"coordinates":[17.120470047,40.5884628296],"type":"Point"}
}