{
  "type": "Feature",
  "properties": {
    "iso:country":"IT",
    "sg:address":"30034 Mira",
    "sg:city":"Gambarare",
    "sg:orig_category":"Riparazione Dei Mezzi Di Trasporto",
    "sg:phone":"+39 041 567 6120",
    "sg:postcode":"30034",
    "sg:province":"Venezia",
    "wof:name":"Carrozzeria Romea Snc",
    "wof:placetype":"venue"
},
  "geometry": {"coordinates":[12.145895,45.408855],"type":"Point"}
}