{
  "type": "Feature",
  "properties": {
    "addr:full":"00128 Roma Roma Roma 00128",
    "addr:postcode":"00128;00128",
    "iso:country":"IT",
    "sg:address":"00128 Roma",
    "sg:city":"Roma",
    "sg:classifiers":[
        {
            "category":"Home & Garden",
            "subcategory":"Home Furnishings",
            "type":"Retail Goods"
        }
    ],
    "sg:phone":"+39 06 508 7891",
    "sg:postcode":"00128",
    "sg:province":"Roma",
    "sg:tags":[
        "professional",
        "furniture",
        "accommodation",
        "supply"
    ],
    "sg:website":"http://www.carliproduzioni.it",
    "wof:name":"Carli Produzioni Srl",
    "wof:placetype":"venue"
},
  "geometry": {"coordinates":[12.4569244385,41.7930793762],"type":"Point"}
}