{
  "type": "Feature",
  "properties": {
    "addr:full":"21026 Gavirate Gavirate Varese 21026",
    "addr:postcode":"21026;21026",
    "iso:country":"IT",
    "sg:address":"21026 Gavirate",
    "sg:city":"Gavirate",
    "sg:orig_category":"Macchine, Strumenti Ed Apparecchi Per Attivita' Industriali",
    "sg:phone":"+39 0332 748311",
    "sg:postcode":"21026",
    "sg:province":"Varese",
    "wof:name":"Abb Astra Contatori Srl",
    "wof:placetype":"venue"
},
  "geometry": {"coordinates":[8.705285,45.840393],"type":"Point"}
}