{
  "type": "Feature",
  "properties": {
    "iso:country":"IT",
    "sg:address":"13100 Vercelli",
    "sg:city":"Vercelli",
    "sg:orig_category":"Articoli Per Imballaggio E Confezionamento",
    "sg:phone":"+39 0161 393381",
    "sg:postcode":"13100",
    "sg:province":"Vercelli",
    "wof:name":"Saccheria Guala Roberto & C. S.n.c.",
    "wof:placetype":"venue"
},
  "geometry": {"coordinates":[8.397749,45.30368],"type":"Point"}
}