{
  "type": "Feature",
  "properties": {
    "iso:country":"IT",
    "sg:address":"00165 Roma",
    "sg:city":"Roma",
    "sg:orig_category":"Agenzie D'affari E Servizi Commerciali. Acqua, Luce, Gas E Societa' Di Esercizio Pubblico",
    "sg:phone":"+39 06 637 4269",
    "sg:postcode":"00165",
    "sg:province":"Roma",
    "wof:name":"Istituto Vendite Giudiziarie",
    "wof:placetype":"venue"
},
  "geometry": {"coordinates":[12.45043,41.894634],"type":"Point"}
}