{
  "type": "Feature",
  "properties": {
    "iso:country":"IT",
    "sg:address":"28065 Cerano",
    "sg:city":"Cerano",
    "sg:orig_category":"Prodotti Alimentari. Agricoltura, Orticoltura E Floricoltura",
    "sg:phone":"+39 0321 728113",
    "sg:postcode":"28065",
    "sg:province":"Novara",
    "wof:name":"Riseria F.lli Dughi (s.n.c.)",
    "wof:placetype":"venue"
},
  "geometry": {"coordinates":[8.8013029099,45.3999443054],"type":"Point"}
}