{
  "type": "Feature",
  "properties": {
    "iso:country":"IT",
    "sg:address":"13836 Cossato",
    "sg:city":"Cossato",
    "sg:orig_category":"Servizi E Lavori Per Edilizia E Lavori Pubblici",
    "sg:phone":"+39 015 925041",
    "sg:postcode":"13836",
    "sg:province":"Biella",
    "wof:name":"Troiano Vincenzo",
    "wof:placetype":"venue"
},
  "geometry": {"coordinates":[8.130657,45.595497],"type":"Point"}
}