{
  "type": "Feature",
  "properties": {
    "addr:full":"24, Strada Sant'eusebio 10080 Feletto Feletto Torino 10080",
    "addr:postcode":"10080;10080",
    "addr:street":"Strada Sant'Eusebio",
    "iso:country":"IT",
    "sg:address":"24, Strada Sant'eusebio 10080 Feletto",
    "sg:city":"Feletto",
    "sg:classifiers":[
        {
            "category":"Real Estate",
            "subcategory":"Surveying",
            "type":"Services"
        }
    ],
    "sg:phone":"+39 0124 490035",
    "sg:postcode":"10080",
    "sg:province":"Torino",
    "sg:tags":[
        "equipment",
        "material",
        "good",
        "-",
        "handling"
    ],
    "wof:name":"Bena (s.n.c.)",
    "wof:placetype":"venue"
},
  "geometry": {"coordinates":[7.743615,45.293758],"type":"Point"}
}