{
  "type": "Feature",
  "properties": {
    "addr:full":"25075 Nave Nave Brescia 25075",
    "addr:postcode":"25075;25075",
    "iso:country":"IT",
    "sg:address":"25075 Nave",
    "sg:city":"Nave",
    "sg:orig_category":"Lavorazioni Metalli, Stampaggio E Saldatura",
    "sg:phone":"+39 030 253 4030",
    "sg:postcode":"25075",
    "sg:province":"Brescia",
    "wof:name":"Rovati Ugo",
    "wof:placetype":"venue"
},
  "geometry": {"coordinates":[10.274633,45.580399],"type":"Point"}
}