{
  "type": "Feature",
  "properties": {
    "addr:full":"41058 Vignola Vignola Modena 41058",
    "addr:postcode":"41058;41058",
    "iso:country":"IT",
    "sg:address":"41058 Vignola",
    "sg:city":"Vignola",
    "sg:orig_category":"Valvole E Apparecchiature Di Misura",
    "sg:phone":"+39 059 770 0411",
    "sg:postcode":"41058",
    "sg:province":"Modena",
    "sg:website":"http://www.davidbrownhydraulics.com",
    "wof:name":"David Brown Hydraulics Italia Srl",
    "wof:placetype":"venue"
},
  "geometry": {"coordinates":[11.002486,44.496532],"type":"Point"}
}