{
  "type": "Feature",
  "properties": {
    "iso:country":"IT",
    "sg:address":"25125 Brescia",
    "sg:city":"Brescia",
    "sg:classifiers":[
        {
            "category":"Shopping",
            "subcategory":"Clothing, Apparel, & Fashions",
            "type":"Retail Goods"
        }
    ],
    "sg:phone":"+39 030 354 3568",
    "sg:postcode":"25125",
    "sg:province":"Brescia",
    "sg:tags":[
        "knitwear",
        "furs",
        "clothing"
    ],
    "wof:name":"Duemme Moda Di Mella Marco & C. Snc",
    "wof:placetype":"venue"
},
  "geometry": {"coordinates":[10.179272,45.532501],"type":"Point"}
}