{
  "type": "Feature",
  "properties": {
    "iso:country":"IT",
    "sg:address":"20146 Milano",
    "sg:city":"Milano",
    "sg:orig_category":"Impianti, Attrezzature E Forniture Sanitarie Ed Ospedaliere",
    "sg:phone":"+39 02 481 2934",
    "sg:postcode":"20146",
    "sg:province":"Milano",
    "wof:name":"Diadent S.r.l.",
    "wof:placetype":"venue"
},
  "geometry": {"coordinates":[9.151431,45.462524],"type":"Point"}
}