{
  "type": "Feature",
  "properties": {
    "addr:full":"Via Crevada 67 31020 Refrontolo Refrontolo Treviso 31020",
    "addr:housenumber":"67",
    "addr:postcode":"31020;31020",
    "addr:street":"Via Crevada",
    "iso:country":"IT",
    "sg:address":"Via Crevada 67 31020 Refrontolo",
    "sg:city":"Refrontolo",
    "sg:classifiers":[
        {
            "category":"Manufacturing",
            "subcategory":"Motor Vehicles & Parts",
            "type":"Manufacturing & Wholesale Goods"
        }
    ],
    "sg:phone":"+39 0438 840281",
    "sg:postcode":"31020",
    "sg:province":"Treviso",
    "sg:tags":[
        "sound",
        "silencer",
        "absorbers"
    ],
    "sg:website":"www.marmittezara.com",
    "wof:name":"Marmitte Zara Spa",
    "wof:placetype":"venue"
},
  "geometry": {"coordinates":[12.230441,45.876987],"type":"Point"}
}