{
  "type": "Feature",
  "properties": {
    "iso:country":"IT",
    "sg:address":"80126 Napoli",
    "sg:city":"Napoli",
    "sg:orig_category":"Materiali Semilavorati Metallici",
    "sg:phone":"+39 081 766 2951",
    "sg:postcode":"80126",
    "sg:province":"Napoli",
    "wof:name":"Correale Achille",
    "wof:placetype":"venue"
},
  "geometry": {"coordinates":[14.197961,40.837917],"type":"Point"}
}