{
  "type": "Feature",
  "properties": {
    "addr:full":"33100 Udine Udine Udine 33100",
    "addr:postcode":"33100;33100",
    "iso:country":"IT",
    "sg:address":"33100 Udine",
    "sg:city":"Udine",
    "sg:orig_category":"Agenzie D'affari E Servizi Commerciali",
    "sg:phone":"+39 0432 511505",
    "sg:postcode":"33100",
    "sg:province":"Udine",
    "wof:name":"Studio Citta' Di Milano S.a.s.",
    "wof:placetype":"venue"
},
  "geometry": {"coordinates":[13.230532,46.06543],"type":"Point"}
}