{
  "type": "Feature",
  "properties": {
    "addr:full":"00152 Roma Roma Roma 00152",
    "addr:postcode":"00152;00152",
    "iso:country":"IT",
    "sg:address":"00152 Roma",
    "sg:city":"Roma",
    "sg:orig_category":"Prodotti Finiti Stampati. Forniture E Materiali Per Imballaggio E Confezionamento. Forniture Per Attivita' Commerciali Ed Artigianali",
    "sg:phone":"+39 06 581 6535",
    "sg:postcode":"00152",
    "sg:province":"Roma",
    "wof:name":"Paper Bags Srl",
    "wof:placetype":"venue"
},
  "geometry": {"coordinates":[12.4586009979,41.8836364746],"type":"Point"}
}