{
  "type": "Feature",
  "properties": {
    "iso:country":"IT",
    "sg:address":"10098 Rivoli",
    "sg:city":"Rivoli",
    "sg:orig_category":"Motori Ed Organi Di Trasmissione",
    "sg:phone":"+39 011 959 4134",
    "sg:postcode":"10098",
    "sg:province":"Torino",
    "wof:name":"Litens Automotive Srl",
    "wof:placetype":"venue"
},
  "geometry": {"coordinates":[7.5457348824,45.0598144531],"type":"Point"}
}