{
  "type": "Feature",
  "properties": {
    "iso:country":"IT",
    "sg:address":"Via Giacomo Puccini 24 55016 Porcari",
    "sg:city":"Porcari",
    "sg:classifiers":[
        {
            "category":"Manufacturing",
            "subcategory":"Paper Products",
            "type":"Manufacturing & Wholesale Goods"
        }
    ],
    "sg:phone":"+39 0583 295798",
    "sg:postcode":"55016",
    "sg:province":"Lucca",
    "sg:tags":[
        "table",
        "cellulose",
        "napkin"
    ],
    "sg:website":"www.deni.it",
    "wof:name":"Deni S.r.l.",
    "wof:placetype":"venue"
},
  "geometry": {"coordinates":[10.6046953201,43.8405761719],"type":"Point"}
}