{
  "type": "Feature",
  "properties": {
    "iso:country":"IT",
    "sg:address":"20097 San Donato Milanese",
    "sg:city":"San Donato Milanese",
    "sg:orig_category":"Carni, Salumi E Pesci",
    "sg:phone":"+39 02 510606",
    "sg:postcode":"20097",
    "sg:province":"Milano",
    "wof:name":"Gianenrico Mapelli S.p.a.",
    "wof:placetype":"venue"
},
  "geometry": {"coordinates":[9.267803,45.41843],"type":"Point"}
}