{
  "type": "Feature",
  "properties": {
    "iso:country":"IT",
    "sg:address":"24020 Rovetta",
    "sg:city":"Rovetta",
    "sg:orig_category":"Abbigliamento Esterno, Maglierie E Pelliccerie",
    "sg:phone":"+39 0346 74411",
    "sg:postcode":"24020",
    "sg:province":"Bergamo",
    "wof:name":"Biemme Sport",
    "wof:placetype":"venue"
},
  "geometry": {"coordinates":[9.973419,45.878891],"type":"Point"}
}