{
  "type": "Feature",
  "properties": {
    "iso:country":"IT",
    "sg:address":"02100 Rieti",
    "sg:city":"Rieti",
    "sg:orig_category":"Forniture E Prodotti Informatici. Forniture Per Uffici",
    "sg:phone":"+39 0746 271062",
    "sg:postcode":"02100",
    "sg:province":"Rieti",
    "wof:name":"C.g.s. Rieti Computer Graphic Systems",
    "wof:placetype":"venue"
},
  "geometry": {"coordinates":[12.8572406769,42.3995819092],"type":"Point"}
}