{
  "type": "Feature",
  "properties": {
    "addr:full":"Cso Sempione 43 21052 Busto Arsizio Busto Arsizio Varese 21052",
    "addr:housenumber":"43",
    "addr:postcode":"21052;21052",
    "addr:street":"Cso Sempione",
    "iso:country":"IT",
    "sg:address":"Cso Sempione 43 21052 Busto Arsizio",
    "sg:city":"Busto Arsizio",
    "sg:classifiers":[
        {
            "category":"Communications",
            "subcategory":"Radio Station",
            "type":"Services"
        }
    ],
    "sg:phone":"+39 0331 302828",
    "sg:postcode":"21052",
    "sg:province":"Varese",
    "sg:tags":[
        "pumping"
    ],
    "sg:website":"www.iteco.net",
    "wof:name":"Gis Grupp Srl",
    "wof:placetype":"venue"
},
  "geometry": {"coordinates":[8.8263845444,45.8176040649],"type":"Point"}
}