{
  "type": "Feature",
  "properties": {
    "iso:country":"IT",
    "sg:address":"40055 Castenaso",
    "sg:city":"Castenaso",
    "sg:orig_category":"Forniture Ospedaliere",
    "sg:phone":"+39 051 605 0300",
    "sg:postcode":"40055",
    "sg:province":"Bologna",
    "sg:website":"http://www.hospimed.it",
    "wof:name":"Hospimed Srl",
    "wof:placetype":"venue"
},
  "geometry": {"coordinates":[11.4552183151,44.507610321],"type":"Point"}
}