{
  "type": "Feature",
  "properties": {
    "addr:full":"46040 Solferino Solferino Mantova 46040",
    "addr:postcode":"46040;46040",
    "iso:country":"IT",
    "sg:address":"46040 Solferino",
    "sg:city":"Solferino",
    "sg:orig_category":"Prodotti E Manufatti In Materie Plastiche",
    "sg:phone":"+39 0376 893408",
    "sg:postcode":"46040",
    "sg:province":"Mantova",
    "wof:name":"Green Plast Srl",
    "wof:placetype":"venue"
},
  "geometry": {"coordinates":[10.5540485382,45.3633346558],"type":"Point"}
}