{
  "type": "Feature",
  "properties": {
    "iso:country":"IT",
    "sg:address":"20127 Milano",
    "sg:city":"Milano",
    "sg:orig_category":"Utensili Meccanici E Materiali",
    "sg:phone":"+39 02 282 7847",
    "sg:postcode":"20127",
    "sg:province":"Milano",
    "wof:name":"C.v.m. Srl",
    "wof:placetype":"venue"
},
  "geometry": {"coordinates":[9.213748,45.493698],"type":"Point"}
}