{
  "type": "Feature",
  "properties": {
    "iso:country":"IT",
    "sg:address":"47100 Forl\u00ec",
    "sg:orig_category":"Fonderie Artistiche",
    "sg:phone":"+39 0543 84338",
    "sg:postcode":"47100",
    "sg:province":"Forl\u00ec-Cesena",
    "wof:name":"Forli' Oro Snc",
    "wof:placetype":"venue"
},
  "geometry": {"coordinates":[12.0132331848,44.1972503662],"type":"Point"}
}