{
  "type": "Feature",
  "properties": {
    "addr:full":"15100 Alessandria Alessandria Alessandria 15100",
    "addr:postcode":"15100;15100",
    "iso:country":"IT",
    "sg:address":"15100 Alessandria",
    "sg:city":"Alessandria",
    "sg:orig_category":"Prodotti Di Base E Forniture Per Industria Alimentare E Bevande. Forniture E Materiali Per Imballaggio E Confezionamento",
    "sg:phone":"+39 0131 618376",
    "sg:postcode":"15100",
    "sg:province":"Alessandria",
    "wof:name":"Sugherificio Maino Di Giovanni Nicola Maino",
    "wof:placetype":"venue"
},
  "geometry": {"coordinates":[8.6883687973,44.8830528259],"type":"Point"}
}