{
  "type": "Feature",
  "properties": {
    "iso:country":"IT",
    "sg:address":"91026 Mazara Del Vallo",
    "sg:city":"Mazara del Vallo",
    "sg:orig_category":"Ospedali E Servizi Sanitari",
    "sg:phone":"+39 0923 908893",
    "sg:postcode":"91026",
    "sg:province":"Trapani",
    "wof:name":"Gianfortuna Maria",
    "wof:placetype":"venue"
},
  "geometry": {"coordinates":[12.600866,37.658058],"type":"Point"}
}