{
  "type": "Feature",
  "properties": {
    "iso:country":"IT",
    "sg:address":"Corso Como 15, 20154 Milan, Mi",
    "sg:classifiers":[
        {
            "category":"Banks & Credit Unions",
            "subcategory":"Bank",
            "type":"Services"
        }
    ],
    "sg:postcode":"20154",
    "sg:province":"Milano",
    "wof:name":"Banca Idea Spa",
    "wof:placetype":"venue"
},
  "geometry": {"coordinates":[9.187499,45.483223],"type":"Point"}
}