{
  "type": "Feature",
  "properties": {
    "iso:country":"IT",
    "sg:address":"20131 Milano",
    "sg:city":"Milano",
    "sg:orig_category":"Petroli, Gas E Combustibili. Servizi E Lavori Industria Chimica. Servizi E Lavori Per Edilizia E Lavori Pubblici. Acqua, Luce, Gas E Societa' Di Esercizio Pubblico",
    "sg:phone":"+39 02 2024 0753",
    "sg:postcode":"20131",
    "sg:province":"Milano",
    "wof:name":"Compagnia Generale Impianti Metano S.p.a.",
    "wof:placetype":"venue"
},
  "geometry": {"coordinates":[9.2156972885,45.4846382141],"type":"Point"}
}