{
  "type": "Feature",
  "properties": {
    "iso:country":"IT",
    "sg:address":"26010 Offanengo",
    "sg:city":"Offanengo",
    "sg:orig_category":"Abbigliamento Esterno, Maglierie E Pelliccerie. Calzature, Pelletterie E Pelli. Sport - Articoli E Forniture",
    "sg:phone":"+39 0373 780259",
    "sg:postcode":"26010",
    "sg:province":"Cremona",
    "wof:name":"Vailati Antonio & C. S.n.c.",
    "wof:placetype":"venue"
},
  "geometry": {"coordinates":[9.732641,45.376957],"type":"Point"}
}