{
  "type": "Feature",
  "properties": {
    "addr:full":"65121 Pescara Pescara Pescara 65121",
    "addr:postcode":"65121;65121",
    "iso:country":"IT",
    "sg:address":"65121 Pescara",
    "sg:city":"Pescara",
    "sg:orig_category":"Non-classified Establishments",
    "sg:phone":"+39 085 299153",
    "sg:postcode":"65121",
    "sg:province":"Pescara",
    "wof:name":"Virtual Service Srl",
    "wof:placetype":"venue"
},
  "geometry": {"coordinates":[14.213725,42.466022],"type":"Point"}
}