{
  "type": "Feature",
  "properties": {
    "addr:full":"13, Via Arezzo 59100 Prato Prato Prato 59100",
    "addr:postcode":"59100;59100",
    "addr:street":"Via Arezzo",
    "iso:country":"IT",
    "sg:address":"13, Via Arezzo 59100 Prato",
    "sg:city":"Prato",
    "sg:classifiers":[
        {
            "category":"Shopping",
            "subcategory":"Crafts & Fabrics",
            "type":"Retail Goods"
        }
    ],
    "sg:phone":"+39 39057442891",
    "sg:postcode":"59100",
    "sg:province":"Prato",
    "wof:name":"Manifatture Tessili La Torre (s.p.a.)",
    "wof:placetype":"venue"
},
  "geometry": {"coordinates":[11.1283311844,43.9413719177],"type":"Point"}
}