{
  "type": "Feature",
  "properties": {
    "iso:country":"IT",
    "sg:address":"5, Strada Pezze Del Sole 70126 Bari",
    "sg:city":"Bari",
    "sg:classifiers":[
        {
            "category":"Wholesale",
            "subcategory":"Machinery & Supplies",
            "type":"Manufacturing & Wholesale Goods"
        }
    ],
    "sg:phone":"+39 080 548 2886",
    "sg:postcode":"70126",
    "sg:province":"Bari",
    "sg:tags":[
        "equipment",
        "precision"
    ],
    "wof:name":"Security System (s.r.l.)",
    "wof:placetype":"venue"
},
  "geometry": {"coordinates":[16.8924770355,41.0961418152],"type":"Point"}
}