{
  "type": "Feature",
  "properties": {
    "iso:country":"IT",
    "sg:address":"15033 Casale Monferrato",
    "sg:city":"Casale Monferrato",
    "sg:orig_category":"Abbigliamento Esterno, Maglierie E Pelliccerie. Calzature, Pelletterie E Pelli. Sport - Articoli E Forniture",
    "sg:phone":"+39 0142 74424",
    "sg:postcode":"15033",
    "sg:province":"Alessandria",
    "wof:name":"Viadana Eugenio",
    "wof:placetype":"venue"
},
  "geometry": {"coordinates":[8.705935,44.923347],"type":"Point"}
}