{
  "type": "Feature",
  "properties": {
    "iso:country":"IT",
    "sg:address":"23868 Valmadrera",
    "sg:city":"Valmadrera",
    "sg:orig_category":"Materiali Semilavorati Metallici",
    "sg:phone":"+39 0341 204000",
    "sg:postcode":"23868",
    "sg:province":"Lecco",
    "sg:website":"http://www.inac.it",
    "wof:name":"Inac Spa",
    "wof:placetype":"venue"
},
  "geometry": {"coordinates":[9.373946,45.848217],"type":"Point"}
}