{
  "type": "Feature",
  "properties": {
    "iso:country":"IT",
    "sg:address":"40012 Calderara Di Reno",
    "sg:city":"Bargellino",
    "sg:orig_category":"Articoli Da Regalo. Regalistica Aziendale",
    "sg:phone":"+39 051 727032",
    "sg:postcode":"40012",
    "sg:province":"Bologna",
    "sg:website":"http://www.plastiline.com",
    "wof:name":"Skat Srl",
    "wof:placetype":"venue"
},
  "geometry": {"coordinates":[11.270691,44.53635],"type":"Point"}
}