{
  "type": "Feature",
  "properties": {
    "addr:full":"22030 Orsenigo Orsenigo Como 22030",
    "addr:postcode":"22030;22030",
    "iso:country":"IT",
    "sg:address":"22030 Orsenigo",
    "sg:city":"Orsenigo",
    "sg:orig_category":"Macchine Utensili E Impianti",
    "sg:phone":"+39 031 630844",
    "sg:postcode":"22030",
    "sg:province":"Como",
    "wof:name":"Brenna Tranquillo & Figli",
    "wof:placetype":"venue"
},
  "geometry": {"coordinates":[9.126246,45.791676],"type":"Point"}
}