{
  "type": "Feature",
  "properties": {
    "iso:country":"IT",
    "sg:address":"36, Via Carpaccio 30038 Spinea",
    "sg:city":"Spinea",
    "sg:classifiers":[
        {
            "category":"Professional",
            "subcategory":"Engineering",
            "type":"Services"
        }
    ],
    "sg:phone":"+39 041 508 9611",
    "sg:postcode":"30038",
    "sg:province":"Venezia",
    "sg:tags":[
        "machine",
        "-",
        "mechanical"
    ],
    "wof:name":"Officine M.t.m. Spa",
    "wof:placetype":"venue"
},
  "geometry": {"coordinates":[12.176434,45.488937],"type":"Point"}
}