{
  "type": "Feature",
  "properties": {
    "iso:country":"IT",
    "sg:address":"35/5, Via Del Commercio 58022 Follonica",
    "sg:city":"Follonica",
    "sg:classifiers":[
        {
            "category":"Food & Beverages",
            "subcategory":"Dairy",
            "type":"Retail Goods"
        }
    ],
    "sg:phone":"+39 39056651349",
    "sg:postcode":"58022",
    "sg:province":"Grosseto",
    "sg:tags":[
        "product"
    ],
    "wof:name":"Caseificio Maremma Di Spadi Fortunato E C Srl",
    "wof:placetype":"venue"
},
  "geometry": {"coordinates":[10.782539,42.936329],"type":"Point"}
}