{
  "type": "Feature",
  "properties": {
    "iso:country":"IT",
    "sg:address":"Via Tajani Filippo 9 20133 Milano",
    "sg:city":"Milano",
    "sg:classifiers":[
        {
            "category":"Wholesale",
            "subcategory":"Medical Equipment & Supplies",
            "type":"Manufacturing & Wholesale Goods"
        }
    ],
    "sg:phone":"+39 02 719065",
    "sg:postcode":"20133",
    "sg:province":"Milano",
    "sg:tags":[
        "suction",
        "dental",
        "surgical"
    ],
    "sg:website":"www.demarco.biz",
    "wof:name":"De Marco Srl",
    "wof:placetype":"venue"
},
  "geometry": {"coordinates":[9.23667,45.473137],"type":"Point"}
}