{
  "type": "Feature",
  "properties": {
    "iso:country":"IT",
    "sg:address":"Via E. Fermi 6 24050 Orio Al Serio",
    "sg:city":"Orio al Serio",
    "sg:classifiers":[
        {
            "category":"Wholesale",
            "subcategory":"Construction Materials",
            "type":"Manufacturing & Wholesale Goods"
        }
    ],
    "sg:phone":"+39 035 525115",
    "sg:postcode":"24050",
    "sg:province":"Bergamo",
    "sg:tags":[
        "industrial",
        "stair"
    ],
    "sg:website":"www.frigeriospa.com",
    "wof:name":"Frigerio Carpenterie Spa",
    "wof:placetype":"venue"
},
  "geometry": {"coordinates":[9.681138,45.642761],"type":"Point"}
}