{
  "type": "Feature",
  "properties": {
    "iso:country":"IT",
    "sg:address":"Via Villapizzone 10 20156 Milano",
    "sg:city":"Milano",
    "sg:classifiers":[
        {
            "category":"Health Services",
            "subcategory":"Dentist",
            "type":"Services"
        }
    ],
    "sg:phone":"+39 02 3340 4357",
    "sg:postcode":"20156",
    "sg:province":"Milano",
    "sg:tags":[
        "dental",
        "requisite"
    ],
    "wof:name":"Medical Group M.g. Srl",
    "wof:placetype":"venue"
},
  "geometry": {"coordinates":[9.110395,45.51511],"type":"Point"}
}