{
  "type": "Feature",
  "properties": {
    "addr:full":"25030 Torbole Casaglia Torbole Casaglia Brescia 25030",
    "addr:postcode":"25030;25030",
    "iso:country":"IT",
    "sg:address":"25030 Torbole Casaglia",
    "sg:city":"Torbole Casaglia",
    "sg:orig_category":"Forniture Per Abbigliamento E Pelletterie",
    "sg:phone":"+39 030 265 0154",
    "sg:postcode":"25030",
    "sg:province":"Brescia",
    "wof:name":"Duina Antonelli Liliana",
    "wof:placetype":"venue"
},
  "geometry": {"coordinates":[10.1120738983,45.5132331848],"type":"Point"}
}