{
  "type": "Feature",
  "properties": {
    "iso:country":"IT",
    "sg:address":"96018 Pachino",
    "sg:city":"Pachino",
    "sg:orig_category":"Serramenti Ed Infissi",
    "sg:phone":"+39 0931 846584",
    "sg:postcode":"96018",
    "sg:province":"Siracusa",
    "sg:website":"http://www.dinatale.it",
    "wof:name":"Dinatale Porte & Infissi",
    "wof:placetype":"venue"
},
  "geometry": {"coordinates":[15.087525,36.719643],"type":"Point"}
}