{
  "type": "Feature",
  "properties": {
    "iso:country":"IT",
    "sg:address":"2, Via Parmenide 41012 Carpi",
    "sg:city":"Carpi",
    "sg:classifiers":[
        {
            "category":"Real Estate",
            "subcategory":"Architect",
            "type":"Services"
        }
    ],
    "sg:phone":"+39 39059693344",
    "sg:postcode":"41012",
    "sg:province":"Modena",
    "sg:tags":[
        "textile",
        "clothing"
    ],
    "wof:name":"Imatex (s.p.a.)",
    "wof:placetype":"venue"
},
  "geometry": {"coordinates":[10.861223,44.77457],"type":"Point"}
}