{
  "type": "Feature",
  "properties": {
    "addr:full":"1, Localita' Colombare 37017 Lazise Lazise Verona 37017",
    "addr:postcode":"37017;37017",
    "addr:street":"Localita ' Colombare",
    "iso:country":"IT",
    "sg:address":"1, Localita' Colombare 37017 Lazise",
    "sg:city":"Lazise",
    "sg:classifiers":[
        {
            "category":"Shopping",
            "subcategory":"Clothing, Apparel, & Fashions",
            "type":"Retail Goods"
        }
    ],
    "sg:phone":"+39 045 758 0137",
    "sg:postcode":"37017",
    "sg:province":"Verona",
    "sg:tags":[
        "clothes"
    ],
    "wof:name":"Martinelli Confezioni (s.r.l.)",
    "wof:placetype":"venue"
},
  "geometry": {"coordinates":[10.777215,45.487404],"type":"Point"}
}