{
  "type": "Feature",
  "properties": {
    "iso:country":"IT",
    "sg:address":"14, Via Pioppa 41013 Castelfranco Emilia",
    "sg:city":"Castelfranco Emilia",
    "sg:classifiers":[
        {
            "category":"Professional",
            "subcategory":"Engineering",
            "type":"Services"
        }
    ],
    "sg:phone":"+39 39059926201",
    "sg:postcode":"41013",
    "sg:province":"Modena",
    "sg:tags":[
        "machine",
        "-",
        "mechanical"
    ],
    "wof:name":"Dipizeta (s.r.l.)",
    "wof:placetype":"venue"
},
  "geometry": {"coordinates":[11.038649,44.613632],"type":"Point"}
}