{
  "type": "Feature",
  "properties": {
    "iso:country":"IT",
    "sg:address":"10129 Torino",
    "sg:city":"Torino",
    "sg:classifiers":[
        {
            "category":"Health Services",
            "subcategory":"Health Practitioner",
            "type":"Services"
        }
    ],
    "sg:phone":"+39 011 595326",
    "sg:postcode":"10129",
    "sg:province":"Torino",
    "sg:tags":[
        "medici"
    ],
    "wof:name":"Campini Roberto",
    "wof:placetype":"venue"
},
  "geometry": {"coordinates":[8.39892,45.462345],"type":"Point"}
}