{
  "type": "Feature",
  "properties": {
    "addr:full":"62010 Montelupone Montelupone Macerata 62010",
    "addr:postcode":"62010;62010",
    "iso:country":"IT",
    "sg:address":"62010 Montelupone",
    "sg:city":"Montelupone",
    "sg:orig_category":"Arredo Bagno Ed Idrosanitari. Idrosanitari E Accessori",
    "sg:phone":"+39 0733 220401",
    "sg:postcode":"62010",
    "sg:province":"Macerata",
    "wof:name":"Telma Guzzini Srl",
    "wof:placetype":"venue"
},
  "geometry": {"coordinates":[13.478893,43.356831],"type":"Point"}
}