{
  "type": "Feature",
  "properties": {
    "iso:country":"IT",
    "sg:address":"88100 Catanzaro",
    "sg:city":"Catanzaro",
    "sg:orig_category":"Pubblica Amministrazione",
    "sg:phone":"+39 0961 889111",
    "sg:postcode":"88100",
    "sg:province":"Catanzaro",
    "wof:name":"Prefettura",
    "wof:placetype":"venue"
},
  "geometry": {"coordinates":[16.5838756561,38.9206962585],"type":"Point"}
}