{
  "type": "Feature",
  "properties": {
    "addr:full":"Strada Sabattino 62 47896 Di Repubblica Di San Marino",
    "addr:housenumber":"62",
    "addr:postcode":"47896",
    "addr:street":"Strada Sabattino",
    "iso:country":"IT",
    "sg:address":"Strada Sabattino 62 47896 Di Repubblica Di San Marino",
    "sg:orig_category":"Flexographic Printing",
    "sg:phone":"+39 0549 876211",
    "wof:name":"S.i.t. Sa",
    "wof:placetype":"venue"
},
  "geometry": {"coordinates":[12.4832248688,43.9254684448],"type":"Point"}
}