{
  "type": "Feature",
  "properties": {
    "iso:country":"IT",
    "sg:address":"35043 Monselice",
    "sg:city":"Monselice",
    "sg:orig_category":"Ricerca, Selezione E Formazione Del Personale",
    "sg:phone":"+39 0429 783888",
    "sg:postcode":"35043",
    "sg:province":"Padova",
    "wof:name":"Umana Spa",
    "wof:placetype":"venue"
},
  "geometry": {"coordinates":[11.914321,45.365643],"type":"Point"}
}