{
  "type": "Feature",
  "properties": {
    "addr:full":"11100 Aosta Aosta Aosta 11100",
    "addr:postcode":"11100;11100",
    "iso:country":"IT",
    "sg:address":"11100 Aosta",
    "sg:city":"Aosta",
    "sg:orig_category":"Autostrade, Trafori E Autoporti",
    "sg:phone":"+39 0165 363641",
    "sg:postcode":"11100",
    "sg:province":"Aosta",
    "sg:website":"http://www.sitrasb.it",
    "wof:name":"Sitrasb - Societa' Italiana Traforo Gran S. Bernardo Spa",
    "wof:placetype":"venue"
},
  "geometry": {"coordinates":[7.312007,45.733814],"type":"Point"}
}