{
  "type": "Feature",
  "properties": {
    "iso:country":"IT",
    "sg:address":"90, Corso Buenos Aires 20124 Milano",
    "sg:city":"Milano",
    "sg:classifiers":[
        {
            "category":"Shopping",
            "subcategory":"Clothing, Apparel, & Fashions",
            "type":"Retail Goods"
        }
    ],
    "sg:phone":"+39 02 2024 0951",
    "sg:postcode":"20124",
    "sg:province":"Milano",
    "sg:tags":[
        "clothing",
        "accessory"
    ],
    "wof:name":"Format S.r.l.",
    "wof:placetype":"venue"
},
  "geometry": {"coordinates":[9.216076,45.485504],"type":"Point"}
}