{
  "type": "Feature",
  "properties": {
    "iso:country":"IT",
    "sg:address":"Vle Delle Industrie 13 45100 Rovigo",
    "sg:city":"Rovigo",
    "sg:classifiers":[
        {
            "category":"Utilities",
            "subcategory":"Sewage",
            "type":"Services"
        }
    ],
    "sg:phone":"+39 0425 475801",
    "sg:postcode":"45100",
    "sg:province":"Rovigo",
    "sg:tags":[
        "calculation",
        "reconciliation",
        "charge",
        "water"
    ],
    "sg:website":"www.fimm.com",
    "wof:name":"Fimm Fatturazioni Immediate Srl",
    "wof:placetype":"venue"
},
  "geometry": {"coordinates":[11.768286,45.007301],"type":"Point"}
}