{
  "type": "Feature",
  "properties": {
    "iso:country":"IT",
    "sg:address":"80011 Acerra",
    "sg:city":"Acerra",
    "sg:orig_category":"Prodotti Alimentari",
    "sg:phone":"+39 081 844 6105",
    "sg:postcode":"80011",
    "sg:province":"Napoli",
    "wof:name":"Agravicola Campania (s.r.l.)",
    "wof:placetype":"venue"
},
  "geometry": {"coordinates":[14.4630794525,40.9244804382],"type":"Point"}
}