{
  "type": "Feature",
  "properties": {
    "iso:country":"IT",
    "sg:address":"Via Pantano 13, 20122 Milan, Mi",
    "sg:classifiers":[
        {
            "category":"Banks & Credit Unions",
            "subcategory":"Bank",
            "type":"Services"
        }
    ],
    "sg:postcode":"20122",
    "sg:province":"Milano",
    "wof:name":"Banca Woolwich Spa",
    "wof:placetype":"venue"
},
  "geometry": {"coordinates":[9.191822,45.459606],"type":"Point"}
}