{
  "type": "Feature",
  "properties": {
    "addr:full":"13844 Piatto Piatto Biella 13844",
    "addr:postcode":"13844;13844",
    "iso:country":"IT",
    "sg:address":"13844 Piatto",
    "sg:city":"Piatto",
    "sg:orig_category":"Scuole E Servizi Scolastici. Servizi Per Lo Sport E Il Tempo Libero",
    "sg:phone":"+39 015 744178",
    "sg:postcode":"13844",
    "sg:province":"Biella",
    "wof:name":"Scuola Italiana Sci Bielmonte",
    "wof:placetype":"venue"
},
  "geometry": {"coordinates":[8.083482,45.663467],"type":"Point"}
}