{
  "type": "Feature",
  "properties": {
    "iso:country":"IT",
    "sg:address":"84015 Nocera Superiore",
    "sg:city":"Nocera Superiore",
    "sg:orig_category":"Prodotti Vari In Metallo",
    "sg:phone":"+39 081 932125",
    "sg:postcode":"84015",
    "sg:province":"Salerno",
    "wof:name":"Italrete Dei F.lli Bonacci Snc",
    "wof:placetype":"venue"
},
  "geometry": {"coordinates":[14.6762733459,40.7340698242],"type":"Point"}
}