{
  "type": "Feature",
  "properties": {
    "iso:country":"IT",
    "sg:address":"Zona Industriale Salino 64018 Tortoreto",
    "sg:city":"Salino",
    "sg:orig_category":"Mobile Scaffolding",
    "sg:phone":"+39 0861 772221",
    "sg:postcode":"64018",
    "sg:province":"Teramo",
    "sg:website":"www.faraone.com",
    "wof:name":"Ima Srl",
    "wof:placetype":"venue"
},
  "geometry": {"coordinates":[13.6985311508,42.6612701416],"type":"Point"}
}