{
  "type": "Feature",
  "properties": {
    "addr:full":"24067 Sarnico Sarnico Bergamo 24067",
    "addr:postcode":"24067;24067",
    "iso:country":"IT",
    "sg:address":"24067 Sarnico",
    "sg:city":"Sarnico",
    "sg:orig_category":"Nautica. Automobili E Mezzi Di Trasporto",
    "sg:phone":"+39 035 911404",
    "sg:postcode":"24067",
    "sg:province":"Bergamo",
    "wof:name":"Ma.ri.na. Srl",
    "wof:placetype":"venue"
},
  "geometry": {"coordinates":[9.989478,45.677086],"type":"Point"}
}