{
  "type": "Feature",
  "properties": {
    "iso:country":"IT",
    "sg:address":"20014 Nerviano",
    "sg:city":"Nerviano",
    "sg:orig_category":"Servizi E Lavori Industria Della Gomma",
    "sg:phone":"+39 0331 587654",
    "sg:postcode":"20014",
    "sg:province":"Milano",
    "wof:name":"Mezzanzanica Osvaldo E C. Snc",
    "wof:placetype":"venue"
},
  "geometry": {"coordinates":[8.989345,45.550209],"type":"Point"}
}