{
  "type": "Feature",
  "properties": {
    "addr:full":"66010 Ripa Teatina Ripa Teatina Chieti 66010",
    "addr:postcode":"66010;66010",
    "iso:country":"IT",
    "sg:address":"66010 Ripa Teatina",
    "sg:city":"Ripa Teatina",
    "sg:orig_category":"Carni, Salumi E Pesci. Zootecnia E Pesca, Allevamento Piccoli Animali",
    "sg:phone":"+39 0871 390179",
    "sg:postcode":"66010",
    "sg:province":"Chieti",
    "sg:website":"http://www.salumificioeuropasrl.com",
    "wof:name":"Europa Srl - Import Export",
    "wof:placetype":"venue"
},
  "geometry": {"coordinates":[14.235,42.359703],"type":"Point"}
}