{
  "type": "Feature",
  "properties": {
    "iso:country":"IT",
    "sg:address":"Via Stazione 14 29010 Alseno",
    "sg:city":"Alseno",
    "sg:classifiers":[
        {
            "category":"Education",
            "subcategory":"Special Training",
            "type":"Public Place"
        }
    ],
    "sg:phone":"+39 0523 945181",
    "sg:postcode":"29010",
    "sg:province":"Piacenza",
    "sg:tags":[
        "lock"
    ],
    "wof:name":"Seral Snc",
    "wof:placetype":"venue"
},
  "geometry": {"coordinates":[9.98922,44.892521],"type":"Point"}
}