{
  "type": "Feature",
  "properties": {
    "iso:country":"IT",
    "sg:address":"20037 Paderno Dugnano",
    "sg:city":"Paderno Dugnano",
    "sg:orig_category":"Trattamenti E Finiture Superficiali Metalli",
    "sg:phone":"+39 02 918 0676",
    "sg:postcode":"20037",
    "sg:province":"Milano",
    "sg:website":"http://www.triton.it",
    "wof:name":"Triton Srl",
    "wof:placetype":"venue"
},
  "geometry": {"coordinates":[9.181725,45.559643],"type":"Point"}
}