{
  "type": "Feature",
  "properties": {
    "addr:full":"81024 Maddaloni Maddaloni Caserta 81024",
    "addr:postcode":"81024;81024",
    "iso:country":"IT",
    "sg:address":"81024 Maddaloni",
    "sg:city":"Maddaloni",
    "sg:classifiers":[
        {
            "category":"Cinema",
            "subcategory":"Movie Theater",
            "type":"Entertainment"
        }
    ],
    "sg:phone":"+39 0823 432437",
    "sg:postcode":"81024",
    "sg:province":"Caserta",
    "wof:name":"Barletta Vincenzo",
    "wof:placetype":"venue"
},
  "geometry": {"coordinates":[14.38261,41.038731],"type":"Point"}
}