{
  "type": "Feature",
  "properties": {
    "addr:full":"Po Box 1898, I-20121 Milan, Mi, Italy. Milano 20121",
    "addr:housenumber":"po",
    "addr:postcode":"i-20121;italy. milano 20121",
    "addr:street":"Box 1898",
    "iso:country":"IT",
    "sg:address":"Po Box 1898, I-20121 Milan, Mi, Italy.",
    "sg:classifiers":[
        {
            "category":"Banks & Credit Unions",
            "subcategory":"Bank",
            "type":"Services"
        }
    ],
    "sg:phone":"+39 02 721211",
    "sg:postcode":"20121",
    "sg:province":"Milano",
    "wof:name":"Banca Regionale Europea Spa",
    "wof:placetype":"venue"
},
  "geometry": {"coordinates":[9.190015,45.465603],"type":"Point"}
}