{
  "type": "Feature",
  "properties": {
    "iso:country":"IT",
    "sg:address":"28, V. Piamarta 25021 Bagnolo Mella",
    "sg:city":"Bagnolo Mella",
    "sg:classifiers":[
        {
            "category":"Professional",
            "subcategory":"Engineering",
            "type":"Services"
        }
    ],
    "sg:phone":"+39 030 682 1611",
    "sg:postcode":"25021",
    "sg:province":"Brescia",
    "sg:tags":[
        "machine",
        "-",
        "mechanical"
    ],
    "sg:website":"http://www.selproweb.com",
    "wof:name":"S.el.pro. Di Rizzi Stefano",
    "wof:placetype":"venue"
},
  "geometry": {"coordinates":[10.191312,45.41761],"type":"Point"}
}