{
  "type": "Feature",
  "properties": {
    "addr:full":"20099 Sesto San Giovanni Sesto San Giovanni Milano 20099",
    "addr:postcode":"20099;20099",
    "iso:country":"IT",
    "sg:address":"20099 Sesto San Giovanni",
    "sg:city":"Sesto San Giovanni",
    "sg:orig_category":"Accessori Dei Mezzi Di Trasporto",
    "sg:phone":"+39 02 244 0071",
    "sg:postcode":"20099",
    "sg:province":"Milano",
    "wof:name":"Romeo Racing",
    "wof:placetype":"venue"
},
  "geometry": {"coordinates":[9.234645,45.528313],"type":"Point"}
}