{
  "type": "Feature",
  "properties": {
    "iso:country":"IT",
    "sg:address":"105/107, Via Diaz Armando 20010 Bareggio",
    "sg:city":"Bareggio",
    "sg:classifiers":[
        {
            "category":"Bars & Pubs",
            "subcategory":"Nightclub",
            "type":"Food & Drink"
        }
    ],
    "sg:phone":"+39 39029027146",
    "sg:postcode":"20010",
    "sg:province":"Milano",
    "sg:tags":[
        "cake",
        "bread"
    ],
    "wof:name":"New For Party Snc Di Cella Rodolfo & C.",
    "wof:placetype":"venue"
},
  "geometry": {"coordinates":[9.002264,45.475239],"type":"Point"}
}