{
  "type": "Feature",
  "properties": {
    "iso:country":"IT",
    "sg:address":"11020 Donnas",
    "sg:city":"Donnas",
    "sg:orig_category":"Macchine Ed Impianti Per Edilizia E Lavori Pubblici",
    "sg:postcode":"11020",
    "sg:province":"Aosta",
    "wof:name":"Societa' Edil - Pneumatic (s.a.s.)",
    "wof:placetype":"venue"
},
  "geometry": {"coordinates":[7.769853,45.598038],"type":"Point"}
}