{
  "type": "Feature",
  "properties": {
    "iso:country":"IT",
    "sg:address":"90141 Palermo",
    "sg:city":"Palermo",
    "sg:orig_category":"Arredo Camera Letto E Complementi",
    "sg:phone":"+39 091 323741",
    "sg:postcode":"90141",
    "sg:province":"Palermo",
    "wof:name":"Lentini Antonietta",
    "wof:placetype":"venue"
},
  "geometry": {"coordinates":[13.35411,38.121555],"type":"Point"}
}