{
  "type": "Feature",
  "properties": {
    "iso:country":"IT",
    "sg:address":"16123 Genova",
    "sg:city":"Genova",
    "sg:orig_category":"Articoli Da Regalo. Arte Ed Artigianato Artistico. Shopping",
    "sg:phone":"+39 010 246 8368",
    "sg:postcode":"16123",
    "sg:province":"Genova",
    "wof:name":"La Lampada Di Aladino",
    "wof:placetype":"venue"
},
  "geometry": {"coordinates":[8.931434,44.408623],"type":"Point"}
}