{
  "type": "Feature",
  "properties": {
    "iso:country":"IT",
    "sg:address":"06035 Gualdo Cattaneo",
    "sg:city":"Gualdo Cattaneo",
    "sg:classifiers":[
        {
            "category":"Arena",
            "subcategory":"Sports Club",
            "type":"Entertainment"
        }
    ],
    "sg:phone":"+39 0742 97153",
    "sg:postcode":"06035",
    "sg:province":"Perugia",
    "sg:tags":[
        "equipment",
        "leisure",
        "facility"
    ],
    "wof:name":"Santi Alfio",
    "wof:placetype":"venue"
},
  "geometry": {"coordinates":[12.520819,42.872551],"type":"Point"}
}