{
  "type": "Feature",
  "properties": {
    "iso:country":"IT",
    "sg:address":"49, Via S.d'acquisto 81030 Parete",
    "sg:city":"Parete",
    "sg:classifiers":[
        {
            "category":"Personal",
            "subcategory":"Shoe Repair & Shine",
            "type":"Services"
        }
    ],
    "sg:phone":"+39 081 501 7450",
    "sg:postcode":"81030",
    "sg:province":"Caserta",
    "sg:tags":[
        "leather"
    ],
    "wof:name":"Suolificio 2002 S.a.s. Di Andreozzi Salvatore",
    "wof:placetype":"venue"
},
  "geometry": {"coordinates":[14.332194,41.075417],"type":"Point"}
}