{
  "type": "Feature",
  "properties": {
    "addr:full":"Via Del Giardino 9 50053 Empoli Empoli Firenze 50053",
    "addr:housenumber":"9",
    "addr:postcode":"50053;50053",
    "addr:street":"Via Del Giardino",
    "iso:country":"IT",
    "sg:address":"Via Del Giardino 9 50053 Empoli",
    "sg:city":"Empoli",
    "sg:classifiers":[
        {
            "category":"Home & Garden",
            "subcategory":"Carpets & Floor Coverings",
            "type":"Retail Goods"
        }
    ],
    "sg:phone":"+39 0571 922632",
    "sg:postcode":"50053",
    "sg:province":"Firenze",
    "sg:tags":[
        "animal",
        "skin"
    ],
    "wof:name":"Unionpelli Srl",
    "wof:placetype":"venue"
},
  "geometry": {"coordinates":[10.950056,43.712978],"type":"Point"}
}