{
  "type": "Feature",
  "properties": {
    "iso:country":"IT",
    "sg:address":"39040 Termeno Sulla Strada Del Vino",
    "sg:city":"Termeno sulla strada del vino",
    "sg:orig_category":"Imprese Di Costruzioni Civili Ed Industriali",
    "sg:phone":"+39 0471 861229",
    "sg:postcode":"39040",
    "sg:province":"Bolzano/Bozen",
    "wof:name":"Psenner H. & Kofler K. S.n.c.",
    "wof:placetype":"venue"
},
  "geometry": {"coordinates":[11.250108,46.328232],"type":"Point"}
}