{
  "type": "Feature",
  "properties": {
    "addr:full":"Piazza Dei Signori 1; Treviso; 31100 Treviso Treviso 31100",
    "addr:housenumber":"1",
    "addr:postcode":"31100;31100",
    "addr:street":"Piazza Dei Signori",
    "iso:country":"IT",
    "sg:address":"Piazza Dei Signori 1; Treviso; 31100",
    "sg:city":"Treviso",
    "sg:classifiers":[
        {
            "category":"Banks & Credit Unions",
            "subcategory":"Bank",
            "type":"Services"
        }
    ],
    "sg:phone":"+39 0422 412261",
    "sg:postcode":"31100",
    "sg:province":"Treviso",
    "wof:name":"Banca Antoniana, Popolare Veneta Scarl",
    "wof:placetype":"venue"
},
  "geometry": {"coordinates":[12.24563,45.665714],"type":"Point"}
}