{
  "type": "Feature",
  "properties": {
    "iso:country":"IT",
    "sg:address":"35010 Loreggia",
    "sg:city":"Loreggia",
    "sg:orig_category":"Servizi E Lavori Industria Chimica",
    "sg:phone":"+39 049 935 5620",
    "sg:postcode":"35010",
    "sg:province":"Padova",
    "wof:name":"Top Verniciatura Di Marcato G. & C. (s.n.c.)",
    "wof:placetype":"venue"
},
  "geometry": {"coordinates":[11.915104,45.609726],"type":"Point"}
}