{
  "type": "Feature",
  "properties": {
    "iso:country":"IT",
    "sg:address":"20093 Cologno Monzese",
    "sg:city":"Cologno Monzese",
    "sg:orig_category":"Servizi E Lavori Per Arredamento E Industria Del Legno. Servizi E Lavori Per Edilizia E Lavori Pubblici",
    "sg:phone":"+39 02 253 8342",
    "sg:postcode":"20093",
    "sg:province":"Milano",
    "wof:name":"Irienti Gaetano",
    "wof:placetype":"venue"
},
  "geometry": {"coordinates":[9.270376,45.545982],"type":"Point"}
}