{
  "type": "Feature",
  "properties": {
    "iso:country":"IT",
    "sg:address":"30175 Mestre",
    "sg:city":"Mestre",
    "sg:orig_category":"Servizi Per Lo Sport E Il Tempo Libero. Servizi Ausiliari Dei Mezzi Di Trasporto",
    "sg:phone":"+39 041 974222",
    "sg:postcode":"30175",
    "sg:province":"Venezia",
    "wof:name":"Agenzia Nautica Base Mare 21 Snc Di Alessandro Scarparo & C.",
    "wof:placetype":"venue"
},
  "geometry": {"coordinates":[12.248361,45.489418],"type":"Point"}
}