{
  "type": "Feature",
  "properties": {
    "iso:country":"IT",
    "sg:address":"20159 Milano",
    "sg:city":"Milano",
    "sg:orig_category":"Prodotti Alimentari. Shopping",
    "sg:phone":"+39 02 608 0856",
    "sg:postcode":"20159",
    "sg:province":"Milano",
    "wof:name":"D'oria S.r.l.",
    "wof:placetype":"venue"
},
  "geometry": {"coordinates":[9.1817207336,45.4896965027],"type":"Point"}
}