{
  "type": "Feature",
  "properties": {
    "iso:country":"IT",
    "sg:address":"00143 Roma",
    "sg:city":"Roma",
    "sg:orig_category":"Elettrotecnica Industriale, Prodotti E Apparecchiature. Ricambi E Componenti Dei Mezzi Di Trasporto",
    "sg:phone":"+39 06 5065 2573",
    "sg:postcode":"00143",
    "sg:province":"Roma",
    "wof:name":"Dinamic Power S.r.l.",
    "wof:placetype":"venue"
},
  "geometry": {"coordinates":[12.488002,41.770611],"type":"Point"}
}