{
  "type": "Feature",
  "properties": {
    "iso:country":"IT",
    "sg:address":"12010 Bernezzo",
    "sg:city":"Bernezzo",
    "sg:orig_category":"Bevande, Vini E Liquori",
    "sg:phone":"+39 0171 85037",
    "sg:postcode":"12010",
    "sg:province":"Cuneo",
    "wof:name":"Elia Bibite Di Elia Giuseppe & Figli Snc",
    "wof:placetype":"venue"
},
  "geometry": {"coordinates":[7.479249,44.404152],"type":"Point"}
}