{
  "type": "Feature",
  "properties": {
    "iso:country":"IT",
    "sg:address":"20159 Milano",
    "sg:city":"Milano",
    "sg:orig_category":"Cinematografia E Radiotelevisione. Pubblicita', Marketing E Comunicazione. Acqua, Luce, Gas E Societa' Di Esercizio Pubblico",
    "sg:phone":"+39 02 688 4230",
    "sg:postcode":"20159",
    "sg:province":"Milano",
    "wof:name":"R.c.s. Srl",
    "wof:placetype":"venue"
},
  "geometry": {"coordinates":[9.188173,45.496189],"type":"Point"}
}