{
  "type": "Feature",
  "properties": {
    "iso:country":"IT",
    "sg:address":"20145 Milano",
    "sg:city":"Milano",
    "sg:orig_category":"Arredamenti - Vendita Al Dettaglio",
    "sg:phone":"+39 02 4851 7492",
    "sg:postcode":"20145",
    "sg:province":"Milano",
    "wof:name":"Bimbi \u00c1 La Page Di Laura Teli",
    "wof:placetype":"venue"
},
  "geometry": {"coordinates":[9.157313,45.468266],"type":"Point"}
}