{
  "type": "Feature",
  "properties": {
    "addr:full":"00198 Roma Roma Roma 00198",
    "addr:postcode":"00198;00198",
    "iso:country":"IT",
    "sg:address":"00198 Roma",
    "sg:city":"Roma",
    "sg:orig_category":"Prodotti Chimici Di Base. Prodotti Cosmetici E Da Toeletta",
    "sg:phone":"+39 06 855 3106",
    "sg:postcode":"00198",
    "sg:province":"Roma",
    "wof:name":"Haarmann & Reimer S.r.l.",
    "wof:placetype":"venue"
},
  "geometry": {"coordinates":[12.5042648315,41.9179534912],"type":"Point"}
}