{
  "type": "Feature",
  "properties": {
    "iso:country":"IT",
    "sg:address":"33100 Udine",
    "sg:city":"Udine",
    "sg:orig_category":"Certificazione Qualita', Sicurezza Ed Ambiente",
    "sg:phone":"+39 0432 477474",
    "sg:postcode":"33100",
    "sg:province":"Udine",
    "wof:name":"Ermete Soc. Coop.r.l.",
    "wof:placetype":"venue"
},
  "geometry": {"coordinates":[13.234653,46.07172],"type":"Point"}
}