{
  "type": "Feature",
  "properties": {
    "iso:country":"IT",
    "sg:address":"43100 Parma",
    "sg:city":"Parma",
    "sg:orig_category":"Vetro: Prodotti E Lavorazioni. Articoli Per Imballaggio E Confezionamento",
    "sg:phone":"+39 0521 7901",
    "sg:postcode":"43100",
    "sg:province":"Parma",
    "sg:website":"http://www.bormiolirocco.com",
    "wof:name":"Bormioli Rocco & Figlio Spa",
    "wof:placetype":"venue"
},
  "geometry": {"coordinates":[10.331084,44.797951],"type":"Point"}
}