{
  "type": "Feature",
  "properties": {
    "addr:full":"20132 Milano Milano Milano 20132",
    "addr:postcode":"20132;20132",
    "iso:country":"IT",
    "sg:address":"20132 Milano",
    "sg:city":"Milano",
    "sg:orig_category":"Macchine, Impianti E Forniture Per Industria Grafica, Cartaria E Cartotecnica. Automazione E Macchine Per Ufficio",
    "sg:phone":"+39 02 259 2204",
    "sg:postcode":"20132",
    "sg:province":"Milano",
    "wof:name":"Fiore Ing. Giorgio Eredi (s.r.l.)",
    "wof:placetype":"venue"
},
  "geometry": {"coordinates":[9.244311,45.503754],"type":"Point"}
}