{
  "type": "Feature",
  "properties": {
    "iso:country":"IT",
    "sg:address":"19, Via Pendino 80125 Napoli",
    "sg:city":"Napoli",
    "sg:classifiers":[
        {
            "category":"Real Estate",
            "subcategory":"Surveying",
            "type":"Services"
        }
    ],
    "sg:phone":"+39 081 742 9065",
    "sg:postcode":"80125",
    "sg:province":"Napoli",
    "sg:tags":[
        "equipment",
        "material",
        "good",
        "-",
        "handling"
    ],
    "wof:name":"M.i.t.a. Progetti S.r.l.",
    "wof:placetype":"venue"
},
  "geometry": {"coordinates":[14.213012,40.891758],"type":"Point"}
}