{
  "type": "Feature",
  "properties": {
    "iso:country":"IT",
    "sg:address":"20, Viale Della Repubblica 42014 Castellarano",
    "sg:classifiers":[
        {
            "category":"Manufacturing",
            "subcategory":"Rubber & Plastics",
            "type":"Manufacturing & Wholesale Goods"
        }
    ],
    "sg:phone":"+39 0536 855911",
    "sg:postcode":"42014",
    "sg:province":"Reggio Nell'Emilia",
    "sg:tags":[
        "packaging",
        "material",
        "-"
    ],
    "wof:name":"Gam Plast Spa",
    "wof:placetype":"venue"
},
  "geometry": {"coordinates":[10.6870088577,44.4825553894],"type":"Point"}
}