{
  "type": "Feature",
  "properties": {
    "iso:country":"IT",
    "sg:address":"41100 Modena",
    "sg:city":"Modena",
    "sg:orig_category":"Trasporti E Spedizioni Merci",
    "sg:phone":"+39 059 223682",
    "sg:postcode":"41100",
    "sg:province":"Modena",
    "wof:name":"T.c.f. S.p.a.",
    "wof:placetype":"venue"
},
  "geometry": {"coordinates":[10.914429,44.663944],"type":"Point"}
}