{
  "type": "Feature",
  "properties": {
    "addr:full":"Via Gattamelata 1; Padova; 35128 Padova Padova 35128",
    "addr:housenumber":"1",
    "addr:postcode":"35128;35128",
    "addr:street":"Via Gattamelata",
    "iso:country":"IT",
    "sg:address":"Via Gattamelata 1; Padova; 35128",
    "sg:city":"Padova",
    "sg:classifiers":[
        {
            "category":"Banks & Credit Unions",
            "subcategory":"Bank",
            "type":"Services"
        }
    ],
    "sg:phone":"+39 049 802 0271",
    "sg:postcode":"35128",
    "sg:province":"Padova",
    "wof:name":"Rolo Banca 1473 Spa",
    "wof:placetype":"venue"
},
  "geometry": {"coordinates":[11.887048,45.399284],"type":"Point"}
}