{
  "type": "Feature",
  "properties": {
    "iso:country":"IT",
    "sg:address":"59, Via Degli Inventori 41100 Modena",
    "sg:city":"Modena",
    "sg:classifiers":[
        {
            "category":"Shopping",
            "subcategory":"Computers & Home Electronics",
            "type":"Retail Goods"
        }
    ],
    "sg:phone":"+39 39059281780",
    "sg:postcode":"41100",
    "sg:province":"Modena",
    "sg:tags":[
        "electronic",
        "electrical",
        "equipment"
    ],
    "wof:name":"New Gedag (s.r.l.)",
    "wof:placetype":"venue"
},
  "geometry": {"coordinates":[10.971386,44.641197],"type":"Point"}
}