{
  "type": "Feature",
  "properties": {
    "addr:full":"25069 Villa Carcina Carcina Brescia 25069",
    "addr:postcode":"25069;carcina;25069",
    "iso:country":"IT",
    "sg:address":"25069 Villa Carcina",
    "sg:city":"Carcina",
    "sg:orig_category":"Prodotti Vari In Metallo",
    "sg:phone":"+39 030 898 0253",
    "sg:postcode":"25069",
    "sg:province":"Brescia",
    "wof:name":"T.e.c.i. Spa",
    "wof:placetype":"venue"
},
  "geometry": {"coordinates":[10.1952314377,45.6231956482],"type":"Point"}
}