{
  "type": "Feature",
  "properties": {
    "addr:full":"Via Rometta 28 35018 San Martino Di Lupari San Martino di Lupari Padova 35018",
    "addr:housenumber":"28",
    "addr:postcode":"35018;di lupari;35018",
    "addr:street":"Via Rometta",
    "iso:country":"IT",
    "sg:address":"Via Rometta 28 35018 San Martino Di Lupari",
    "sg:city":"San Martino di Lupari",
    "sg:classifiers":[
        {
            "category":"Wholesale",
            "subcategory":"Metals & Minerals",
            "type":"Manufacturing & Wholesale Goods"
        }
    ],
    "sg:phone":"+39 049 946 1077",
    "sg:postcode":"35018",
    "sg:province":"Padova",
    "sg:tags":[
        "equipment",
        "degreasing",
        "system",
        "cleaning"
    ],
    "sg:website":"www.novatec.it",
    "wof:name":"Novatec Srl",
    "wof:placetype":"venue"
},
  "geometry": {"coordinates":[11.8401784897,45.6521339417],"type":"Point"}
}