{
  "type": "Feature",
  "properties": {
    "addr:full":"Via Don Bosco 116 34170 Gorizia Gorizia Gorizia 34170",
    "addr:housenumber":"116",
    "addr:postcode":"34170;34170",
    "addr:street":"Via Don Bosco",
    "iso:country":"IT",
    "sg:address":"Via Don Bosco 116 34170 Gorizia",
    "sg:city":"Gorizia",
    "sg:classifiers":[
        {
            "category":"Manufacturing",
            "subcategory":"Textiles",
            "type":"Manufacturing & Wholesale Goods"
        }
    ],
    "sg:phone":"+39 0481 591111",
    "sg:postcode":"34170",
    "sg:province":"Gorizia",
    "sg:tags":[
        "used",
        "machines"
    ],
    "wof:name":"Vouk Spa",
    "wof:placetype":"venue"
},
  "geometry": {"coordinates":[13.615099,45.955662],"type":"Point"}
}