{
  "type": "Feature",
  "properties": {
    "addr:full":"65126 Pescara Pescara Pescara 65126",
    "addr:postcode":"65126;65126",
    "iso:country":"IT",
    "sg:address":"65126 Pescara",
    "sg:city":"Pescara",
    "sg:orig_category":"Elettrodomestici. Forniture Alle Strutture Ricettive",
    "sg:phone":"+39 085 64964",
    "sg:postcode":"65126",
    "sg:province":"Pescara",
    "wof:name":"Averardi Antonio",
    "wof:placetype":"venue"
},
  "geometry": {"coordinates":[14.224543,42.460648],"type":"Point"}
}