{
  "type": "Feature",
  "properties": {
    "iso:country":"IT",
    "sg:address":"26029 Soncino",
    "sg:city":"Soncino",
    "sg:orig_category":"Arredamenti E Mobili Professionali. Arredi Ed Attrezzature Per Uffici",
    "sg:phone":"+39 0374 837106",
    "sg:postcode":"26029",
    "sg:province":"Cremona",
    "sg:website":"http://www.ambienti.org",
    "wof:name":"Ambienti Di Regazzi Fabiano E Oscar Snc",
    "wof:placetype":"venue"
},
  "geometry": {"coordinates":[9.862633,45.396214],"type":"Point"}
}