{
  "type": "Feature",
  "properties": {
    "addr:full":"27, V. Per Fenegro' 22070 Veniano Veniano Como 22070",
    "addr:housenumber":"27",
    "addr:postcode":"22070;22070",
    "addr:street":"V. Per Fenegro '",
    "iso:country":"IT",
    "sg:address":"27, V. Per Fenegro' 22070 Veniano",
    "sg:city":"Veniano",
    "sg:classifiers":[
        {
            "category":"Manufacturing",
            "subcategory":"Paper Products",
            "type":"Manufacturing & Wholesale Goods"
        }
    ],
    "sg:phone":"+39 39031970422",
    "sg:postcode":"22070",
    "sg:province":"Como",
    "sg:tags":[
        "cardboard"
    ],
    "sg:website":"http://www.paginegialle.it/mrpaper",
    "wof:name":"Mr. Paper",
    "wof:placetype":"venue"
},
  "geometry": {"coordinates":[8.993188858,45.7191429138],"type":"Point"}
}