{
  "type": "Feature",
  "properties": {
    "iso:country":"IT",
    "sg:address":"20125 Milano",
    "sg:city":"Milano",
    "sg:orig_category":"Servizi E Lavori Per Abbigliamento E Pelletterie",
    "sg:phone":"+39 02 669 7269",
    "sg:postcode":"20125",
    "sg:province":"Milano",
    "wof:name":"Messina Filippa",
    "wof:placetype":"venue"
},
  "geometry": {"coordinates":[9.207575,45.492943],"type":"Point"}
}