{
  "type": "Feature",
  "properties": {
    "iso:country":"IT",
    "sg:address":"16149 Genova",
    "sg:city":"Genova",
    "sg:orig_category":"Filtri - Produzione E Commercio",
    "sg:phone":"+39 010 465140",
    "sg:postcode":"16149",
    "sg:province":"Genova",
    "wof:name":"Belguardi Srl",
    "wof:placetype":"venue"
},
  "geometry": {"coordinates":[8.8880691528,44.9679908752],"type":"Point"}
}