{
  "type": "Feature",
  "properties": {
    "addr:full":"Via Dei Conciatori 42 56024 Ponte A Egola Ponte a egola Pisa 56024",
    "addr:housenumber":"42",
    "addr:postcode":"56024;56024",
    "addr:street":"Via Dei Conciatori;Egola Ponte A",
    "iso:country":"IT",
    "sg:address":"Via Dei Conciatori 42 56024 Ponte A Egola",
    "sg:city":"Ponte a egola",
    "sg:orig_category":"Leather Items, Artisans'",
    "sg:phone":"+39 0571 49555",
    "sg:postcode":"56024",
    "sg:province":"Pisa",
    "sg:website":"www.orice.com",
    "wof:name":"Conceria Orice Srl",
    "wof:placetype":"venue"
},
  "geometry": {"coordinates":[10.76023,43.718452],"type":"Point"}
}