{
  "type": "Feature",
  "properties": {
    "iso:country":"IT",
    "sg:address":"16132 Genova",
    "sg:city":"Genova",
    "sg:orig_category":"Forniture Per Abbigliamento E Pelletterie. Forniture Per Attivita' Commerciali Ed Artigianali",
    "sg:phone":"+39 010 381274",
    "sg:postcode":"16132",
    "sg:province":"Genova",
    "wof:name":"La Vetrina",
    "wof:placetype":"venue"
},
  "geometry": {"coordinates":[8.9275875092,44.4101295471],"type":"Point"}
}