{
  "type": "Feature",
  "properties": {
    "iso:country":"IT",
    "sg:address":"Via Croce 5/d 41014 Castelvetro Di Modena",
    "sg:city":"Castelvetro di Modena",
    "sg:classifiers":[
        {
            "category":"Home & Garden",
            "subcategory":"Carpets & Floor Coverings",
            "type":"Retail Goods"
        }
    ],
    "sg:phone":"+39 059 758111",
    "sg:postcode":"41014",
    "sg:province":"Modena",
    "sg:tags":[
        "industrial",
        "flooring"
    ],
    "sg:website":"www.flaviker.it",
    "wof:name":"Flaviker Spa",
    "wof:placetype":"venue"
},
  "geometry": {"coordinates":[10.911825,44.516171],"type":"Point"}
}