{
  "type": "Feature",
  "properties": {
    "iso:country":"IT",
    "sg:address":"23900 Lecco",
    "sg:city":"Lecco",
    "sg:orig_category":"Ricerca, Selezione E Formazione Del Personale. Pubblica Amministrazione",
    "sg:phone":"+39 0341 284434",
    "sg:postcode":"23900",
    "sg:province":"Lecco",
    "wof:name":"Lecc0 Lavoro Spa",
    "wof:placetype":"venue"
},
  "geometry": {"coordinates":[9.392123,45.850674],"type":"Point"}
}