{
  "type": "Feature",
  "properties": {
    "iso:country":"IT",
    "sg:address":"83, Via Della Padula 57124 Livorno",
    "sg:city":"Livorno",
    "sg:classifiers":[
        {
            "category":"Autos & Motor Vehicles",
            "subcategory":"Boat Sales",
            "type":"Retail Goods"
        }
    ],
    "sg:phone":"+39 0586 868011",
    "sg:postcode":"57124",
    "sg:province":"Livorno",
    "wof:name":"Cos.mo.s. Spa",
    "wof:placetype":"venue"
},
  "geometry": {"coordinates":[10.337607,43.546131],"type":"Point"}
}