{
  "type": "Feature",
  "properties": {
    "iso:country":"IT",
    "sg:address":"20136 Milano",
    "sg:city":"Milano",
    "sg:orig_category":"Gioielleria, Oreficeria E Argenteria. Shopping",
    "sg:phone":"+39 02 5831 4031",
    "sg:postcode":"20136",
    "sg:province":"Milano",
    "wof:name":"Free Line Di Trazzi Marco",
    "wof:placetype":"venue"
},
  "geometry": {"coordinates":[9.186716,45.451801],"type":"Point"}
}