{
  "type": "Feature",
  "properties": {
    "addr:full":"22038 Tavernerio Tavernerio Como 22038",
    "addr:postcode":"22038;22038",
    "iso:country":"IT",
    "sg:address":"22038 Tavernerio",
    "sg:city":"Tavernerio",
    "sg:orig_category":"Caminetti, Forni Da Giardino E Barbecues",
    "sg:phone":"+39 031 421081",
    "sg:postcode":"22038",
    "sg:province":"Como",
    "sg:website":"http://www.larioceramica.it",
    "wof:name":"Larioceramica Sas",
    "wof:placetype":"venue"
},
  "geometry": {"coordinates":[9.141373,45.794781],"type":"Point"}
}