{
  "type": "Feature",
  "properties": {
    "addr:full":"41100 Cognento Cognento Modena 41100",
    "addr:postcode":"41100;41100",
    "addr:street":"Cognento",
    "iso:country":"IT",
    "sg:address":"41100 Cognento",
    "sg:city":"Cognento",
    "sg:orig_category":"Apparecchiature Ed Attrezzature Meccaniche",
    "sg:phone":"+39 059 340666",
    "sg:postcode":"41100",
    "sg:province":"Modena",
    "wof:name":"Depietri Tonelli Piero",
    "wof:placetype":"venue"
},
  "geometry": {"coordinates":[10.871372,44.630878],"type":"Point"}
}