{
  "type": "Feature",
  "properties": {
    "iso:country":"IT",
    "sg:address":"18100 Imperia",
    "sg:city":"Imperia",
    "sg:orig_category":"Servizi E Lavori Per Abbigliamento E Pelletterie",
    "sg:phone":"+39 0183 275516",
    "sg:postcode":"18100",
    "sg:province":"Imperia",
    "wof:name":"Pellicceria Doria",
    "wof:placetype":"venue"
},
  "geometry": {"coordinates":[8.042738,43.887997],"type":"Point"}
}