{
  "type": "Feature",
  "properties": {
    "iso:country":"IT",
    "sg:address":"Via Merli 6 20095 Cusano Milanino",
    "sg:city":"Cusano Milanino",
    "sg:classifiers":[
        {
            "category":"Manufacturing",
            "subcategory":"Rubber & Plastics",
            "type":"Manufacturing & Wholesale Goods"
        }
    ],
    "sg:phone":"+39 02 619 3626",
    "sg:postcode":"20095",
    "sg:province":"Milano",
    "sg:tags":[
        "product",
        "part",
        "moulded"
    ],
    "sg:website":"www.isopren.it",
    "wof:name":"Isopren Srl",
    "wof:placetype":"venue"
},
  "geometry": {"coordinates":[9.1845636368,45.5467681885],"type":"Point"}
}