{
  "type": "Feature",
  "properties": {
    "addr:full":"22066 Mariano Comense Mariano Comense Como 22066",
    "addr:housenumber":"22066",
    "addr:postcode":"22066",
    "iso:country":"IT",
    "sg:address":"22066 Mariano Comense",
    "sg:city":"Mariano Comense",
    "sg:orig_category":"Servizi E Lavori Per Arredamento E Industria Del Legno",
    "sg:phone":"+39 031 747155",
    "sg:postcode":"22066",
    "sg:province":"Como",
    "wof:name":"Guanziroli Bruno",
    "wof:placetype":"venue"
},
  "geometry": {"coordinates":[9.170623,45.698723],"type":"Point"}
}