{
  "type": "Feature",
  "properties": {
    "iso:country":"IT",
    "sg:address":"25010 Borgosatollo",
    "sg:city":"Borgosatollo",
    "sg:orig_category":"Acciaierie",
    "sg:phone":"+39 030 250 0254",
    "sg:postcode":"25010",
    "sg:province":"Brescia",
    "wof:name":"Sirimpianti Srl",
    "wof:placetype":"venue"
},
  "geometry": {"coordinates":[10.253201,45.476749],"type":"Point"}
}