{
  "type": "Feature",
  "properties": {
    "iso:country":"IT",
    "sg:address":"89128 Reggio Calabria",
    "sg:orig_category":"Elettrotecnica Industriale, Prodotti E Apparecchiature. Forniture Per Attivita' Commerciali Ed Artigianali",
    "sg:phone":"+39 0965 28986",
    "sg:province":"RC",
    "wof:name":"Cogliandro Giovanni 3p",
    "wof:placetype":"venue"
},
  "geometry": {"coordinates":[15.657382,38.101734],"type":"Point"}
}