{
  "type": "Feature",
  "properties": {
    "iso:country":"IT",
    "sg:address":"28, Via Raffaello 53036 Poggibonsi",
    "sg:city":"Poggibonsi",
    "sg:classifiers":[
        {
            "category":"Professional",
            "subcategory":"Engineering",
            "type":"Services"
        }
    ],
    "sg:phone":"+39 0577 936880",
    "sg:postcode":"53036",
    "sg:province":"Siena",
    "sg:tags":[
        "machine",
        "-",
        "mechanical"
    ],
    "wof:name":"Diemme S.r.l.",
    "wof:placetype":"venue"
},
  "geometry": {"coordinates":[11.134406,43.468372],"type":"Point"}
}