{
  "type": "Feature",
  "properties": {
    "iso:country":"IT",
    "sg:address":"16155 Genova",
    "sg:city":"Genova",
    "sg:orig_category":"Arredo Camera Letto E Complementi. Servizi E Lavori Per Arredamento E Industria Del Legno",
    "sg:phone":"+39 010 667 1024",
    "sg:postcode":"16155",
    "sg:province":"Genova",
    "wof:name":"Curulli Giuseppe",
    "wof:placetype":"venue"
},
  "geometry": {"coordinates":[8.820585,44.425724],"type":"Point"}
}