{
  "type": "Feature",
  "properties": {
    "iso:country":"IT",
    "sg:address":"90047 Partinico",
    "sg:city":"Partinico",
    "sg:orig_category":"Servizi Ausiliari Dei Mezzi Di Trasporto. Servizi Ausiliari Per Il Trasporto. Acqua, Luce, Gas E Societa' Di Esercizio Pubblico",
    "sg:phone":"+39 091 890 8389",
    "sg:postcode":"90047",
    "sg:province":"Palermo",
    "wof:name":"Lo Cascio Fabrizio",
    "wof:placetype":"venue"
},
  "geometry": {"coordinates":[13.123311,38.045536],"type":"Point"}
}