{
  "type": "Feature",
  "properties": {
    "addr:full":"7, Via Dell' Artigianato 37060 Nogarole Rocca Nogarole Rocca Verona 37060",
    "addr:postcode":"37060;37060",
    "addr:street":"Via Dell ' Artigianato",
    "iso:country":"IT",
    "sg:address":"7, Via Dell' Artigianato 37060 Nogarole Rocca",
    "sg:city":"Nogarole Rocca",
    "sg:classifiers":[
        {
            "category":"Shopping",
            "subcategory":"Clothing, Apparel, & Fashions",
            "type":"Retail Goods"
        }
    ],
    "sg:phone":"+39 045 639 5119",
    "sg:postcode":"37060",
    "sg:province":"Verona",
    "sg:tags":[
        "clothes"
    ],
    "wof:name":"Centro Moda Adry (s.r.l.)",
    "wof:placetype":"venue"
},
  "geometry": {"coordinates":[10.947718,45.339756],"type":"Point"}
}