{
  "type": "Feature",
  "properties": {
    "addr:full":"20081 Abbiategrasso Abbiategrasso Milano 20081",
    "addr:postcode":"20081;20081",
    "iso:country":"IT",
    "sg:address":"20081 Abbiategrasso",
    "sg:city":"Abbiategrasso",
    "sg:orig_category":"Carni, Salumi E Pesci. Zootecnia E Pesca, Allevamento Piccoli Animali",
    "sg:phone":"+39 02 946 2424",
    "sg:postcode":"20081",
    "sg:province":"Milano",
    "wof:name":"Silva Fisch & Frogs Service Di Alfredo Silva",
    "wof:placetype":"venue"
},
  "geometry": {"coordinates":[9.196077,45.460449],"type":"Point"}
}