{
  "type": "Feature",
  "properties": {
    "iso:country":"IT",
    "sg:address":"Via Partigiani D' Italia 6 43055 Mezzano Superiore",
    "sg:city":"Mezzano Superiore",
    "sg:classifiers":[
        {
            "category":"Home & Garden",
            "subcategory":"Home Furnishings",
            "type":"Retail Goods"
        }
    ],
    "sg:phone":"+39 0521 815975",
    "sg:postcode":"43055",
    "sg:province":"Parma",
    "sg:tags":[
        "interior",
        "decoration"
    ],
    "wof:name":"Compagnia Italia S.r.l.",
    "wof:placetype":"venue"
},
  "geometry": {"coordinates":[10.424192,44.926628],"type":"Point"}
}