{
  "type": "Feature",
  "properties": {
    "iso:country":"IT",
    "sg:address":"12, V. Dell'artigianato 48010 Fusignano",
    "sg:city":"Fusignano",
    "sg:classifiers":[
        {
            "category":"Personal",
            "subcategory":"Shoe Repair & Shine",
            "type":"Services"
        }
    ],
    "sg:phone":"+39 39054553228",
    "sg:postcode":"48010",
    "sg:province":"Ravenna",
    "sg:tags":[
        "leather"
    ],
    "sg:website":"http://www.zenit.com/superstar",
    "wof:name":"Calzaturificio Cenerentola & Superstar Srl",
    "wof:placetype":"venue"
},
  "geometry": {"coordinates":[11.945869,44.461376],"type":"Point"}
}