{
  "type": "Feature",
  "properties": {
    "iso:country":"IT",
    "sg:address":"60131 Ancona",
    "sg:city":"Ancona",
    "sg:orig_category":"Associazioni Sindacali E Di Categoria",
    "sg:phone":"+39 071 286 6440",
    "sg:postcode":"60131",
    "sg:province":"Ancona",
    "sg:website":"http://www.an.cna.it/fidimpresa",
    "wof:name":"Fidimpresa - Cooperativa Artigiana Di Garanzia Della Prov. Di Ancona",
    "wof:placetype":"venue"
},
  "geometry": {"coordinates":[13.485862,43.570496],"type":"Point"}
}