{
  "type": "Feature",
  "properties": {
    "iso:country":"IT",
    "sg:address":"24121 Bergamo",
    "sg:city":"Bergamo",
    "sg:orig_category":"Carrozzelle E Poltrone Per Infermi",
    "sg:phone":"+39 035 212110",
    "sg:postcode":"24121",
    "sg:province":"Bergamo",
    "wof:name":"Ortopedia Zambelli Di Santoro & C. Snc",
    "wof:placetype":"venue"
},
  "geometry": {"coordinates":[9.672988,45.694714],"type":"Point"}
}