{
  "type": "Feature",
  "properties": {
    "addr:full":"Via Liberta' 18 24067 Sarnico Sarnico Bergamo 24067",
    "addr:housenumber":"18",
    "addr:postcode":"24067;24067",
    "addr:street":"Via Liberta '",
    "iso:country":"IT",
    "sg:address":"Via Liberta' 18 24067 Sarnico",
    "sg:city":"Sarnico",
    "sg:classifiers":[
        {
            "category":"Banks & Credit Unions",
            "subcategory":"Investment Brokerage",
            "type":"Services"
        }
    ],
    "sg:phone":"+39 035 910015",
    "sg:postcode":"24067",
    "sg:province":"Bergamo",
    "sg:tags":[
        "work",
        "marble"
    ],
    "sg:website":"www.idmindustriadelmarmo.com",
    "wof:name":"I.d.m. Srl",
    "wof:placetype":"venue"
},
  "geometry": {"coordinates":[9.669952,45.694904],"type":"Point"}
}