{
  "type": "Feature",
  "properties": {
    "iso:country":"IT",
    "sg:address":"93017 S. Cataldo",
    "sg:orig_category":"Cine-foto-ottica. Articoli Medico-sanitari Ed Ortopedici",
    "sg:phone":"+39 0934 574445",
    "sg:postcode":"93017",
    "sg:province":"Caltanissetta",
    "wof:name":"Ottica Cigna",
    "wof:placetype":"venue"
},
  "geometry": {"coordinates":[13.989192,37.484264],"type":"Point"}
}