{
  "type": "Feature",
  "properties": {
    "iso:country":"IT",
    "sg:address":"80014 Giugliano Campania",
    "sg:orig_category":"Animali Domestici - Allevamento E Addestramento",
    "sg:phone":"+39 081 506 4683",
    "sg:postcode":"80014",
    "sg:province":"Napoli",
    "wof:name":"Marmoreo Maria Rosaria",
    "wof:placetype":"venue"
},
  "geometry": {"coordinates":[14.208284,40.93409],"type":"Point"}
}