{
  "type": "Feature",
  "properties": {
    "addr:full":"63010 Monte S. Pietrangeli Ascoli Piceno 63010",
    "addr:housenumber":"63010",
    "addr:postcode":"63010",
    "addr:street":"Monte S. Pietrangeli",
    "iso:country":"IT",
    "sg:address":"63010 Monte S. Pietrangeli",
    "sg:orig_category":"Calzature, Pelletterie E Pelli. Servizi E Lavori Per Abbigliamento E Pelletterie",
    "sg:phone":"+39 0734 969235",
    "sg:postcode":"63010",
    "sg:province":"Ascoli Piceno",
    "wof:name":"Gimmi Calzaturificio Di Moretti Egidio",
    "wof:placetype":"venue"
},
  "geometry": {"coordinates":[13.579327,42.853649],"type":"Point"}
}