{
  "type": "Feature",
  "properties": {
    "iso:country":"IT",
    "sg:address":"10141 Torino",
    "sg:city":"Torino",
    "sg:orig_category":"Metalli E Leghe",
    "sg:phone":"+39 011 383 3338",
    "sg:postcode":"10141",
    "sg:province":"Torino",
    "wof:name":"Eschmann - Stahl Gmbh",
    "wof:placetype":"venue"
},
  "geometry": {"coordinates":[7.6370968819,45.0678939819],"type":"Point"}
}