{
  "type": "Feature",
  "properties": {
    "iso:country":"IT",
    "sg:address":"47900 Rimini",
    "sg:city":"Rimini",
    "sg:orig_category":"Abiti Da Sposa E Cerimonia",
    "sg:phone":"+39 0541 390127",
    "sg:postcode":"47900",
    "sg:province":"Rimini",
    "wof:name":"Il Sogno Della Sposa",
    "wof:placetype":"venue"
},
  "geometry": {"coordinates":[12.6266,44.019089],"type":"Point"}
}