{
  "type": "Feature",
  "properties": {
    "iso:country":"IT",
    "sg:address":"00195 Roma",
    "sg:city":"Roma",
    "sg:orig_category":"Forniture Per Attivita' Industriali. Servizi Ausiliari Di Sorveglianza, Manutenzione E Pulizia",
    "sg:phone":"+39 06 3973 2965",
    "sg:postcode":"00195",
    "sg:province":"Roma",
    "wof:name":"Romana Vetro Recupero",
    "wof:placetype":"venue"
},
  "geometry": {"coordinates":[12.438501358,41.7800254822],"type":"Point"}
}