{
  "type": "Feature",
  "properties": {
    "iso:country":"IT",
    "sg:address":"V. S. Agata Al Fiume - Arangea89060 Reggio Calabria",
    "sg:classifiers":[
        {
            "category":"Wholesale",
            "subcategory":"Drugs",
            "type":"Manufacturing & Wholesale Goods"
        }
    ],
    "sg:phone":"+39 0965 641289",
    "sg:postcode":"89060",
    "sg:province":"Reggio Di Calabria",
    "sg:tags":[
        "chemical",
        "pharmaceutical"
    ],
    "sg:website":"http://www.paginegialle.it/cilione",
    "wof:name":"Cilione Antonino Srl",
    "wof:placetype":"venue"
},
  "geometry": {"coordinates":[15.650137,38.114689],"type":"Point"}
}