{
  "type": "Feature",
  "properties": {
    "iso:country":"IT",
    "sg:address":"V. Falegname 06012 Citt\u00e0 Di Castello",
    "sg:classifiers":[
        {
            "category":"Manufacturing",
            "subcategory":"Paper Products",
            "type":"Manufacturing & Wholesale Goods"
        }
    ],
    "sg:phone":"+39 075 855 2272",
    "sg:postcode":"06012",
    "sg:province":"Perugia",
    "sg:tags":[
        "cardboard"
    ],
    "sg:website":"http://www.paginegialle.it/italcartsnc",
    "wof:name":"I.t.a.l.cart Snc",
    "wof:placetype":"venue"
},
  "geometry": {"coordinates":[12.1935968399,43.4776992798],"type":"Point"}
}