{
  "type": "Feature",
  "properties": {
    "addr:full":"22040 Lurago D'erba Como 22040",
    "addr:postcode":"22040;22040",
    "iso:country":"IT",
    "sg:address":"22040 Lurago D'erba",
    "sg:orig_category":"Non-classified Establishments",
    "sg:phone":"+39 031 696119",
    "sg:postcode":"22040",
    "sg:province":"Como",
    "wof:name":"Vittorio Bonacina Di Mario Bonacina & C. S.n.c.",
    "wof:placetype":"venue"
},
  "geometry": {"coordinates":[9.220963,45.752834],"type":"Point"}
}