{
  "type": "Feature",
  "properties": {
    "iso:country":"IT",
    "sg:address":"9, V. Dei Carretti 25040 Corte Franca",
    "sg:city":"Corte Franca",
    "sg:classifiers":[
        {
            "category":"Shopping",
            "type":"Retail Goods"
        }
    ],
    "sg:phone":"+39 030 988 4088",
    "sg:postcode":"25040",
    "sg:province":"Brescia",
    "sg:tags":[
        "finished",
        "-",
        "metallic"
    ],
    "sg:website":"http://www.bonpez.com:ws_end: :mark:ws:http://www.paginegialle.it/bonpez",
    "wof:name":"Bonpez Snc",
    "wof:placetype":"venue"
},
  "geometry": {"coordinates":[9.9979381561,45.6481513977],"type":"Point"}
}