{
  "type": "Feature",
  "properties": {
    "iso:country":"IT",
    "sg:address":"Via Calvagese - Localit\u00e0 Bottenago 25080 Polpenazze",
    "sg:classifiers":[
        {
            "category":"Bars & Pubs",
            "subcategory":"Champagne Bar",
            "type":"Food & Drink"
        }
    ],
    "sg:phone":"+39 036 567 8011",
    "sg:postcode":"25080",
    "sg:province":"Brescia",
    "sg:tags":[
        "sweet",
        "caramel"
    ],
    "wof:name":"Cedrinca Industria Dolciaria Spa",
    "wof:placetype":"venue"
},
  "geometry": {"coordinates":[10.562986,45.560436],"type":"Point"}
}