{
  "type": "Feature",
  "properties": {
    "iso:country":"IT",
    "sg:address":"Cso Europa 206 20017 Rho",
    "sg:city":"Rho",
    "sg:classifiers":[
        {
            "category":"Food & Beverages",
            "subcategory":"Meat & Fish",
            "type":"Retail Goods"
        }
    ],
    "sg:phone":"+39 02 935161",
    "sg:postcode":"20017",
    "sg:province":"Milano",
    "sg:tags":[
        "sausage"
    ],
    "sg:website":"www.citterio.com",
    "wof:name":"Giuseppe Citterio Salumificio Spa",
    "wof:placetype":"venue"
},
  "geometry": {"coordinates":[9.05262,45.525738],"type":"Point"}
}