{
  "type": "Feature",
  "properties": {
    "addr:full":"70013 Castellana Grotte Castellana Grotte Bari 70013",
    "addr:postcode":"70013;70013",
    "iso:country":"IT",
    "sg:address":"70013 Castellana Grotte",
    "sg:city":"Castellana Grotte",
    "sg:classifiers":[
        {
            "category":"Farming",
            "subcategory":"Fish & Marine Products",
            "type":"Manufacturing & Wholesale Goods"
        }
    ],
    "sg:phone":"+39 080 496 7291",
    "sg:postcode":"70013",
    "sg:province":"Bari",
    "sg:tags":[
        "packaging",
        "articles",
        "packing",
        "plastics",
        "article"
    ],
    "wof:name":"Moliterno Srl",
    "wof:placetype":"venue"
},
  "geometry": {"coordinates":[17.1839027405,40.8686904907],"type":"Point"}
}