{
  "type": "Feature",
  "properties": {
    "addr:full":"70026 Modugno Modugno Bari 70026",
    "addr:postcode":"70026;70026",
    "iso:country":"IT",
    "sg:address":"70026 Modugno",
    "sg:city":"Modugno",
    "sg:orig_category":"Adesivi",
    "sg:phone":"+39 080 532 8241",
    "sg:postcode":"70026",
    "sg:province":"Bari",
    "wof:name":"Matera Giuseppe",
    "wof:placetype":"venue"
},
  "geometry": {"coordinates":[16.784237,41.087143],"type":"Point"}
}