{
  "type": "Feature",
  "properties": {
    "iso:country":"IT",
    "sg:address":"Via Zamboni 15 41011 Campogalliano",
    "sg:city":"Campogalliano",
    "sg:classifiers":[
        {
            "category":"Communications",
            "subcategory":"Film & Video Production",
            "type":"Services"
        }
    ],
    "sg:phone":"+39 059 851414",
    "sg:postcode":"41011",
    "sg:province":"Modena",
    "sg:tags":[
        "technical",
        "process",
        "system",
        "automation"
    ],
    "sg:website":"www.esagv.it",
    "wof:name":"Esa/gv Srl",
    "wof:placetype":"venue"
},
  "geometry": {"coordinates":[10.840683,44.696758],"type":"Point"}
}