{
  "type": "Feature",
  "properties": {
    "iso:country":"IT",
    "sg:address":"60030 Monsano",
    "sg:city":"Monsano",
    "sg:classifiers":[
        {
            "category":"Utilities",
            "subcategory":"Refuse",
            "type":"Services"
        }
    ],
    "sg:phone":"+39 0731 605260",
    "sg:postcode":"60030",
    "sg:province":"Ancona",
    "sg:tags":[
        "control",
        "auxiliary",
        "disposal",
        "analysis",
        "research",
        "environmental",
        "protection",
        "works"
    ],
    "wof:name":"Progetti Informatici Srl",
    "wof:placetype":"venue"
},
  "geometry": {"coordinates":[13.255674,43.533146],"type":"Point"}
}