{
  "type": "Feature",
  "properties": {
    "addr:full":"33100 Udine Udine Udine 33100",
    "addr:postcode":"33100;33100",
    "iso:country":"IT",
    "sg:address":"33100 Udine",
    "sg:city":"Udine",
    "sg:orig_category":"Forniture Per Agricoltura E Zootecnia. Animali Domestici",
    "sg:phone":"+39 0432 530486",
    "sg:postcode":"33100",
    "sg:province":"Udine",
    "wof:name":"Studio Associato Dott. Schiavi",
    "wof:placetype":"venue"
},
  "geometry": {"coordinates":[13.2257843018,46.0573425293],"type":"Point"}
}