{
  "type": "Feature",
  "properties": {
    "addr:full":"20020 Lainate Barbaiana Milano 20020",
    "addr:postcode":"20020;20020",
    "addr:street":"Barbaiana",
    "iso:country":"IT",
    "sg:address":"20020 Lainate",
    "sg:city":"Barbaiana",
    "sg:orig_category":"Materiali E Componenti Elettrotecnici",
    "sg:phone":"+39 02 932541",
    "sg:postcode":"20020",
    "sg:province":"Milano",
    "sg:website":"http://www.amphenol.com",
    "wof:name":"Amphenol Italia Spa",
    "wof:placetype":"venue"
},
  "geometry": {"coordinates":[8.992899,45.524792],"type":"Point"}
}