{
  "type": "Feature",
  "properties": {
    "addr:full":"7, Vico Delle Mele 16123 Genova Genova Genova 16123",
    "addr:housenumber":"7",
    "addr:postcode":"16123;16123",
    "addr:street":"Vico Delle Mele",
    "iso:country":"IT",
    "sg:address":"7, Vico Delle Mele 16123 Genova",
    "sg:city":"Genova",
    "sg:classifiers":[
        {
            "category":"Travel",
            "subcategory":"Travel Agent",
            "type":"Entertainment"
        }
    ],
    "sg:phone":"+39 010 247 4240",
    "sg:postcode":"16123",
    "sg:province":"Genova",
    "sg:tags":[
        "business"
    ],
    "wof:name":"Hotel Genziana Di Christian Rosolani",
    "wof:placetype":"venue"
},
  "geometry": {"coordinates":[8.930518,44.409927],"type":"Point"}
}