{
  "type": "Feature",
  "properties": {
    "addr:full":"7, Contrada S. Severo 60010 Ostra Vetere Ostra Ancona 60010",
    "addr:postcode":"60010;60010",
    "addr:street":"Contrada S. Severo",
    "iso:country":"IT",
    "sg:address":"7, Contrada S. Severo 60010 Ostra Vetere",
    "sg:city":"Ostra",
    "sg:classifiers":[
        {
            "category":"Wholesale",
            "subcategory":"Machinery & Supplies",
            "type":"Manufacturing & Wholesale Goods"
        }
    ],
    "sg:phone":"+39 39071965948",
    "sg:postcode":"60010",
    "sg:province":"Ancona",
    "sg:tags":[
        "-",
        "agriculture",
        "equipment"
    ],
    "wof:name":"Acma (s.r.l.)",
    "wof:placetype":"venue"
},
  "geometry": {"coordinates":[13.518757,43.615856],"type":"Point"}
}