{
  "type": "Feature",
  "properties": {
    "iso:country":"IT",
    "sg:address":"Strada Romana Di Sotto 28877 Ornavasso",
    "sg:city":"Ornavasso",
    "sg:classifiers":[
        {
            "category":"Professional",
            "subcategory":"Engineering",
            "type":"Services"
        }
    ],
    "sg:phone":"+39 0323 838111",
    "sg:postcode":"28877",
    "sg:province":"Verbano-Cusio-Ossola",
    "sg:tags":[
        "machine",
        "-",
        "mechanical"
    ],
    "wof:name":"Magistris & Wetzel S.p.a.",
    "wof:placetype":"venue"
},
  "geometry": {"coordinates":[8.422432,45.96447],"type":"Point"}
}