{
  "type": "Feature",
  "properties": {
    "iso:country":"IT",
    "sg:address":"25015 Desenzano Del Garda",
    "sg:city":"Desenzano del Garda",
    "sg:orig_category":"Sport - Articoli E Forniture",
    "sg:phone":"+39 030 914 2311",
    "sg:postcode":"25015",
    "sg:province":"Brescia",
    "wof:name":"Armeria Gardonese",
    "wof:placetype":"venue"
},
  "geometry": {"coordinates":[10.538915,45.472504],"type":"Point"}
}