{
  "type": "Feature",
  "properties": {
    "addr:full":"20040 Cornate D'adda Milano 20040",
    "addr:postcode":"20040;20040",
    "iso:country":"IT",
    "sg:address":"20040 Cornate D'adda",
    "sg:classifiers":[
        {
            "category":"Wholesale",
            "subcategory":"Machinery & Supplies",
            "type":"Manufacturing & Wholesale Goods"
        }
    ],
    "sg:phone":"+39 039 692101",
    "sg:postcode":"20040",
    "sg:province":"Milano",
    "sg:tags":[
        "activities",
        "industrial"
    ],
    "wof:name":"Minuterie Metalliche Cornatesi Sas",
    "wof:placetype":"venue"
},
  "geometry": {"coordinates":[9.462363,45.649914],"type":"Point"}
}