{
  "type": "Feature",
  "properties": {
    "iso:country":"IT",
    "sg:address":"16126 Genova",
    "sg:city":"Genova",
    "sg:orig_category":"Trasporti E Spedizioni Merci",
    "sg:phone":"+39 010 645 1945",
    "sg:postcode":"16126",
    "sg:province":"Genova",
    "wof:name":"Essetipi Snc",
    "wof:placetype":"venue"
},
  "geometry": {"coordinates":[8.909358,44.40567],"type":"Point"}
}