{
  "type": "Feature",
  "properties": {
    "iso:country":"IT",
    "sg:address":"Via Parco 47 20046 Biassono",
    "sg:city":"Biassono",
    "sg:classifiers":[
        {
            "category":"Building & Trades",
            "subcategory":"Electrical",
            "type":"Services"
        }
    ],
    "sg:phone":"+39 0392389701709",
    "sg:postcode":"20046",
    "sg:province":"Milano",
    "sg:tags":[
        "tool",
        "high-quality"
    ],
    "sg:website":"www.stanley.it",
    "wof:name":"Stanley Tools Srl",
    "wof:placetype":"venue"
},
  "geometry": {"coordinates":[9.297191,45.632572],"type":"Point"}
}