{
  "type": "Feature",
  "properties": {
    "addr:full":"00128 Roma Roma Roma 00128",
    "addr:postcode":"00128;00128",
    "iso:country":"IT",
    "sg:address":"00128 Roma",
    "sg:city":"Roma",
    "sg:orig_category":"Assistenti Sociali - Uffici Presso Enti Pubblici E Privati",
    "sg:phone":"+39 06 5079 7597",
    "sg:postcode":"00128",
    "sg:province":"Roma",
    "wof:name":"Centro S.a.m.i. - Studio Arti Motorie Integrate",
    "wof:placetype":"venue"
},
  "geometry": {"coordinates":[12.435735,41.788441],"type":"Point"}
}