{
  "type": "Feature",
  "properties": {
    "addr:full":"20019 Settimo Milanese Settimo Milanese Milano 20019",
    "addr:postcode":"20019;20019",
    "iso:country":"IT",
    "sg:address":"20019 Settimo Milanese",
    "sg:city":"Settimo Milanese",
    "sg:orig_category":"Accessori Dei Mezzi Di Trasporto",
    "sg:phone":"+39 02 328 3622",
    "sg:postcode":"20019",
    "sg:province":"Milano",
    "wof:name":"Gerd Altmann Srl",
    "wof:placetype":"venue"
},
  "geometry": {"coordinates":[9.083132,45.429817],"type":"Point"}
}