{
  "type": "Feature",
  "properties": {
    "iso:country":"IT",
    "sg:address":"Contrada Mangiavacca; Milazzo; 98057",
    "sg:city":"Milazzo",
    "sg:classifiers":[
        {
            "category":"Banks & Credit Unions",
            "subcategory":"Bank",
            "type":"Services"
        }
    ],
    "sg:phone":"+39 090 922 1730",
    "sg:postcode":"98057",
    "sg:province":"Messina",
    "wof:name":"Credito Italiano Spa",
    "wof:placetype":"venue"
},
  "geometry": {"coordinates":[15.237034,38.200718],"type":"Point"}
}