{
  "type": "Feature",
  "properties": {
    "addr:full":"47900 Rimini Rimini Rimini 47900",
    "addr:postcode":"47900;47900",
    "iso:country":"IT",
    "sg:address":"47900 Rimini",
    "sg:city":"Rimini",
    "sg:orig_category":"Pubblica Amministrazione",
    "sg:phone":"+39 0541 704111",
    "sg:postcode":"47900",
    "sg:province":"Rimini",
    "sg:website":"http://www.riminiturismo.it",
    "wof:name":"Comune Di Rimini",
    "wof:placetype":"venue"
},
  "geometry": {"coordinates":[12.5659828186,44.0608825684],"type":"Point"}
}