{
  "type": "Feature",
  "properties": {
    "iso:country":"IT",
    "sg:address":"40068 San Lazzaro Di Savena",
    "sg:city":"San Lazzaro",
    "sg:orig_category":"Elettricisti",
    "sg:phone":"+39 051 627 0004",
    "sg:postcode":"40068",
    "sg:province":"Bologna",
    "sg:website":"http://users.iol.it/sandrocacciari",
    "wof:name":"Cacciari Impianti Srl",
    "wof:placetype":"venue"
},
  "geometry": {"coordinates":[11.41318,44.476543],"type":"Point"}
}