{
  "type": "Feature",
  "properties": {
    "addr:full":"37139 Verona Verona Verona 37139",
    "addr:postcode":"37139;37139",
    "iso:country":"IT",
    "sg:address":"37139 Verona",
    "sg:city":"Verona",
    "sg:orig_category":"Facchinaggio, Carico E Scarico Merci, Portabagagli - Servizio",
    "sg:phone":"+39 045 890 5165",
    "sg:postcode":"37139",
    "sg:province":"Verona",
    "sg:website":"http://www.veloxservizi.it",
    "wof:name":"Velox Servizi Srl",
    "wof:placetype":"venue"
},
  "geometry": {"coordinates":[10.9464120865,45.4397621155],"type":"Point"}
}