{
  "type": "Feature",
  "properties": {
    "iso:country":"IT",
    "sg:address":"25122 Brescia",
    "sg:city":"Brescia",
    "sg:orig_category":"Servizi E Lavori Per Abbigliamento E Pelletterie. Scuole E Servizi Scolastici. Ricerca, Selezione E Formazione Del Personale",
    "sg:phone":"+39 030 377 2165",
    "sg:postcode":"25122",
    "sg:province":"Brescia",
    "wof:name":"Istituto Moda Industriale Di Corbascio Paolo & C. (s.n.c.)",
    "wof:placetype":"venue"
},
  "geometry": {"coordinates":[10.20983,45.53331],"type":"Point"}
}