{
  "type": "Feature",
  "properties": {
    "iso:country":"IT",
    "sg:address":"194, Via Emilia 27058 Voghera",
    "sg:city":"Voghera",
    "sg:classifiers":[
        {
            "category":"Shopping",
            "subcategory":"Clothing, Apparel, & Fashions",
            "type":"Retail Goods"
        }
    ],
    "sg:phone":"+39 39038341453",
    "sg:postcode":"27058",
    "sg:province":"Pavia",
    "sg:tags":[
        "clothes"
    ],
    "wof:name":"Ronchi",
    "wof:placetype":"venue"
},
  "geometry": {"coordinates":[9.01053,44.994259],"type":"Point"}
}