{
  "type": "Feature",
  "properties": {
    "iso:country":"IT",
    "sg:address":"Via Livornese Est 2 56030 Perignano",
    "sg:classifiers":[
        {
            "category":"Home & Garden",
            "subcategory":"Furniture",
            "type":"Retail Goods"
        }
    ],
    "sg:phone":"+39 0587 616287",
    "sg:postcode":"56030",
    "sg:province":"Pisa",
    "sg:tags":[
        "system"
    ],
    "sg:website":"www.grilli.org",
    "wof:name":"Grilli Srl",
    "wof:placetype":"venue"
},
  "geometry": {"coordinates":[10.396585,43.716137],"type":"Point"}
}