{
  "type": "Feature",
  "properties": {
    "iso:country":"IT",
    "sg:address":"80078 Pozzuoli",
    "sg:city":"Pozzuoli",
    "sg:orig_category":"Abbigliamento Esterno, Maglierie E Pelliccerie",
    "sg:phone":"+39 081 526 2517",
    "sg:postcode":"80078",
    "sg:province":"Napoli",
    "wof:name":"Gi.tes. Srl",
    "wof:placetype":"venue"
},
  "geometry": {"coordinates":[14.120078,40.85614],"type":"Point"}
}