{
  "type": "Feature",
  "properties": {
    "addr:full":"00175 Roma Roma Roma 00175",
    "addr:postcode":"00175;00175",
    "iso:country":"IT",
    "sg:address":"00175 Roma",
    "sg:city":"Roma",
    "sg:orig_category":"Servizi Editoriali. Servizi Ausiliari Per Il Trasporto",
    "sg:phone":"+39 06 763611",
    "sg:postcode":"00175",
    "sg:province":"Roma",
    "wof:name":"S.i.d.o.s. S.a.s.",
    "wof:placetype":"venue"
},
  "geometry": {"coordinates":[12.55527,41.864239],"type":"Point"}
}