{
  "type": "Feature",
  "properties": {
    "iso:country":"IT",
    "sg:address":"Via Della Liberta 92; Piadena",
    "sg:classifiers":[
        {
            "category":"Banks & Credit Unions",
            "subcategory":"Bank",
            "type":"Services"
        }
    ],
    "sg:phone":"+39 0375 98108",
    "wof:name":"Banca Popolare Di Cremona Scarl",
    "wof:placetype":"venue"
},
  "geometry": {"coordinates":[10.369349,45.129341],"type":"Point"}
}