{
  "type": "Feature",
  "properties": {
    "iso:country":"IT",
    "sg:address":"66020 San Giovanni Teatino",
    "sg:city":"San Giovanni Teatino",
    "sg:orig_category":"Forniture Industriali Per Prevenzione, Controllo E Sicurezza",
    "sg:phone":"+39 085 44451",
    "sg:postcode":"66020",
    "sg:province":"Chieti",
    "sg:website":"http://www.dececco.net",
    "wof:name":"Confezioni Mario De Cecco Spa",
    "wof:placetype":"venue"
},
  "geometry": {"coordinates":[14.1702060699,42.4048538208],"type":"Point"}
}