{
  "type": "Feature",
  "properties": {
    "iso:country":"IT",
    "sg:address":"20017 Rho",
    "sg:city":"Rho",
    "sg:orig_category":"Cine-foto-ottica. Shopping",
    "sg:phone":"+39 02 931 6657",
    "sg:postcode":"20017",
    "sg:province":"Milano",
    "wof:name":"Minuzzo Roberto",
    "wof:placetype":"venue"
},
  "geometry": {"coordinates":[9.045334,45.523739],"type":"Point"}
}