{
  "type": "Feature",
  "properties": {
    "addr:full":"4, Via Ponte Pagnano 31011 Asolo Asolo Treviso 31011",
    "addr:postcode":"31011;31011",
    "addr:street":"Via Ponte Pagnano",
    "iso:country":"IT",
    "sg:address":"4, Via Ponte Pagnano 31011 Asolo",
    "sg:city":"Asolo",
    "sg:classifiers":[
        {
            "category":"Shopping",
            "subcategory":"Clothing, Apparel, & Fashions",
            "type":"Retail Goods"
        }
    ],
    "sg:phone":"+39 0423 529200",
    "sg:postcode":"31011",
    "sg:province":"Treviso",
    "sg:tags":[
        "clothes"
    ],
    "wof:name":"Lady Cotton (s.r.l.)",
    "wof:placetype":"venue"
},
  "geometry": {"coordinates":[11.893407,45.803886],"type":"Point"}
}