{
  "type": "Feature",
  "properties": {
    "iso:country":"IT",
    "sg:address":"35020 Correzzola",
    "sg:city":"Correzzola",
    "sg:orig_category":"Serramenti Ed Infissi",
    "sg:phone":"+39 049 585 3282",
    "sg:postcode":"35020",
    "sg:province":"Padova",
    "wof:name":"Meneghin Martino",
    "wof:placetype":"venue"
},
  "geometry": {"coordinates":[11.795135,45.475792],"type":"Point"}
}