{
  "type": "Feature",
  "properties": {
    "addr:full":"Via Pul Stretta, 24/26 28024 Gozzano Gozzano Novara 28024",
    "addr:housenumber":"24 / 26",
    "addr:postcode":"28024;28024",
    "addr:street":"Via Pul Stretta",
    "iso:country":"IT",
    "sg:address":"Via Pul Stretta, 24/26 28024 Gozzano",
    "sg:city":"Gozzano",
    "sg:classifiers":[
        {
            "category":"Sports & Exercise",
            "subcategory":"Ski Resort",
            "type":"Entertainment"
        }
    ],
    "sg:phone":"+39 0322 955797",
    "sg:postcode":"28024",
    "sg:province":"Novara",
    "sg:tags":[
        "pipe",
        "fitting"
    ],
    "wof:name":"Piana Snc Di U. Piana",
    "wof:placetype":"venue"
},
  "geometry": {"coordinates":[8.4417104721,45.7383270264],"type":"Point"}
}