{
  "type": "Feature",
  "properties": {
    "addr:full":"00060 Castelnuovo Di Porto Castelnuovo di Porto Roma 00060",
    "addr:postcode":"00060;00060",
    "addr:street":"Porto Castelnuovo",
    "iso:country":"IT",
    "sg:address":"00060 Castelnuovo Di Porto",
    "sg:city":"Castelnuovo di Porto",
    "sg:orig_category":"Forniture Per Agricoltura E Zootecnia. Animali Domestici",
    "sg:phone":"+39 06 907 3586",
    "sg:postcode":"00060",
    "sg:province":"Roma",
    "wof:name":"Technovet S.n.c. Di Cestra Alessandra E Spuntarelli Leonardo",
    "wof:placetype":"venue"
},
  "geometry": {"coordinates":[12.5602636337,42.1058578491],"type":"Point"}
}