{
  "type": "Feature",
  "properties": {
    "iso:country":"IT",
    "sg:address":"00137 Roma",
    "sg:city":"Roma",
    "sg:classifiers":[
        {
            "category":"Professional",
            "subcategory":"Business Services",
            "type":"Services"
        }
    ],
    "sg:phone":"+39 06 8720 1135",
    "sg:postcode":"00137",
    "sg:province":"Roma",
    "sg:tags":[
        "support",
        "companies",
        "events",
        "trade"
    ],
    "wof:name":"Hb Hover Brave Di Aldo Bracciani Designer",
    "wof:placetype":"venue"
},
  "geometry": {"coordinates":[12.542698,41.950676],"type":"Point"}
}