{
  "type": "Feature",
  "properties": {
    "iso:country":"IT",
    "sg:address":"34141 Trieste",
    "sg:city":"Trieste",
    "sg:orig_category":"Telefoni Cellulari E Radiotelefoni",
    "sg:phone":"+39 040 632371",
    "sg:postcode":"34141",
    "sg:province":"Trieste",
    "wof:name":"Sate Tv",
    "wof:placetype":"venue"
},
  "geometry": {"coordinates":[13.785015,45.64386],"type":"Point"}
}