{
  "type": "Feature",
  "properties": {
    "addr:full":"93100 Caltanissetta Caltanissetta Caltanissetta 93100",
    "addr:postcode":"93100;93100",
    "iso:country":"IT",
    "sg:address":"93100 Caltanissetta",
    "sg:city":"Caltanissetta",
    "sg:orig_category":"Forniture Per Attivita' Industriali",
    "sg:phone":"+39 0934 551989",
    "sg:postcode":"93100",
    "sg:province":"Caltanissetta",
    "wof:name":"Centro Prontolegno Fai Da Te Srl",
    "wof:placetype":"venue"
},
  "geometry": {"coordinates":[14.0304536819,37.4545593262],"type":"Point"}
}