{
  "type": "Feature",
  "properties": {
    "iso:country":"IT",
    "sg:address":"98076 Sant'agata Di Militello",
    "sg:orig_category":"Arredo Cucina Ed Elettrodomestici. Elettrodomestici",
    "sg:phone":"+39 0941 721167",
    "sg:postcode":"98076",
    "sg:province":"Messina",
    "wof:name":"Nani' Nicolo'",
    "wof:placetype":"venue"
},
  "geometry": {"coordinates":[14.63861,38.069027],"type":"Point"}
}