{
  "type": "Feature",
  "properties": {
    "iso:country":"IT",
    "sg:address":"20122 Milano",
    "sg:city":"Milano",
    "sg:orig_category":"Studi E Consulenze Legali E Notarili. Avvocati, Notai E Servizi Legali. Professionisti - Studi E Servizi Ed Associazioni Di Interesse Aziendale",
    "sg:phone":"+39 02 541641",
    "sg:postcode":"20122",
    "sg:province":"Milano",
    "sg:website":"http://www.toffoletto.it",
    "wof:name":"Toffoletto & Soci - Studio Legale",
    "wof:placetype":"venue"
},
  "geometry": {"coordinates":[9.203186,45.462822],"type":"Point"}
}