{
  "type": "Feature",
  "properties": {
    "iso:country":"IT",
    "sg:address":"Via Papa Giovanni Xxiii 16 16018 Mignanego",
    "sg:city":"Mignanego",
    "sg:classifiers":[
        {
            "category":"Autos & Motor Vehicles",
            "subcategory":"Boat Sales",
            "type":"Retail Goods"
        }
    ],
    "sg:phone":"+39 010 72211",
    "sg:postcode":"16018",
    "sg:province":"Genova",
    "sg:tags":[
        "varnish"
    ],
    "sg:website":"www.brignola.it",
    "wof:name":"Orazio Brignola Spa",
    "wof:placetype":"venue"
},
  "geometry": {"coordinates":[8.933989,44.407063],"type":"Point"}
}