{
  "type": "Feature",
  "properties": {
    "iso:country":"IT",
    "sg:address":"41100 Modena",
    "sg:city":"Modena",
    "sg:orig_category":"Studi E Consulenze Tecniche E Industriali. Servizi E Lavori Per Edilizia E Lavori Pubblici. Professionisti - Studi E Servizi Ed Associazioni Di Interesse Aziendale",
    "sg:phone":"+39 059 284938",
    "sg:postcode":"41100",
    "sg:province":"Modena",
    "wof:name":"Mazza Geom. Franco",
    "wof:placetype":"venue"
},
  "geometry": {"coordinates":[10.969368,44.638607],"type":"Point"}
}