{
  "type": "Feature",
  "properties": {
    "addr:full":"07040 Uri Uri Sassari 07040",
    "addr:postcode":"07040;07040",
    "iso:country":"IT",
    "sg:address":"07040 Uri",
    "sg:city":"Uri",
    "sg:orig_category":"Prodotti Chimici Secondari",
    "sg:phone":"+39 079 348348",
    "sg:postcode":"07040",
    "sg:province":"Sassari",
    "wof:name":"Sarda Esplosivi Industriali",
    "wof:placetype":"venue"
},
  "geometry": {"coordinates":[8.4822263718,40.6429443359],"type":"Point"}
}