{
  "type": "Feature",
  "properties": {
    "iso:country":"IT",
    "sg:address":"30135 Venezia",
    "sg:city":"Venezia",
    "sg:classifiers":[
        {
            "category":"Health Services",
            "subcategory":"Health Practitioner",
            "type":"Services"
        }
    ],
    "sg:phone":"+39 041 717002",
    "sg:postcode":"30135",
    "sg:province":"Venezia",
    "sg:tags":[
        "medici"
    ],
    "wof:name":"Latella Aurelio",
    "wof:placetype":"venue"
},
  "geometry": {"coordinates":[12.323059,45.439381],"type":"Point"}
}