{
  "type": "Feature",
  "properties": {
    "addr:full":"88, Via Vasto 46044 Goito Goito Mantova 46044",
    "addr:postcode":"46044;46044",
    "addr:street":"Via Vasto",
    "iso:country":"IT",
    "sg:address":"88, Via Vasto 46044 Goito",
    "sg:city":"Goito",
    "sg:classifiers":[
        {
            "category":"Shopping",
            "subcategory":"Clothing, Apparel, & Fashions",
            "type":"Retail Goods"
        }
    ],
    "sg:phone":"+39 0376 607474",
    "sg:postcode":"46044",
    "sg:province":"Mantova",
    "sg:tags":[
        "clothes"
    ],
    "wof:name":"Laboratorio Annika Di Mainenti Antonella E Giramon",
    "wof:placetype":"venue"
},
  "geometry": {"coordinates":[10.610785,45.277229],"type":"Point"}
}