{
  "type": "Feature",
  "properties": {
    "iso:country":"IT",
    "sg:address":"53047 Sarteano",
    "sg:city":"Sarteano",
    "sg:classifiers":[
        {
            "category":"Travel",
            "subcategory":"Hotels & Motels",
            "type":"Entertainment"
        }
    ],
    "sg:phone":"+39 0578 268039",
    "sg:postcode":"53047",
    "sg:province":"Siena",
    "sg:tags":[
        "hotels",
        "facility"
    ],
    "sg:website":"http://www.nocetorta.com",
    "wof:name":"Agriturismo Nocetorta - Ristorante Albergo Al Parco",
    "wof:placetype":"venue"
},
  "geometry": {"coordinates":[11.855347,42.999161],"type":"Point"}
}