{
  "type": "Feature",
  "properties": {
    "iso:country":"IT",
    "sg:address":"Via Canova 30 20020 Lainate",
    "sg:city":"Lainate",
    "sg:classifiers":[
        {
            "category":"Banks & Credit Unions",
            "subcategory":"Investment Brokerage",
            "type":"Services"
        }
    ],
    "sg:phone":"+39 02 937 4477",
    "sg:postcode":"20020",
    "sg:province":"Milano",
    "sg:tags":[
        "machine",
        "metal",
        "circle",
        "cutting",
        "sheet"
    ],
    "sg:website":"www.guidaimpianti.com",
    "wof:name":"Guida Impianti S.p.a.",
    "wof:placetype":"venue"
},
  "geometry": {"coordinates":[9.050109,45.523159],"type":"Point"}
}