{
  "type": "Feature",
  "properties": {
    "iso:country":"IT",
    "sg:address":"88040 Lamezia Terme",
    "sg:orig_category":"Cartotecnica E Servizi",
    "sg:phone":"+39 0968 51009",
    "sg:postcode":"88040",
    "sg:province":"Catanzaro",
    "wof:name":"Batal Sas Di Taballi Eugenia & C.",
    "wof:placetype":"venue"
},
  "geometry": {"coordinates":[16.614702,38.820477],"type":"Point"}
}