{
  "type": "Feature",
  "properties": {
    "iso:country":"IT",
    "sg:address":"57027 San Vincenzo",
    "sg:city":"San Vincenzo",
    "sg:orig_category":"Carrozzerie Autoveicoli Industriali E Speciali",
    "sg:phone":"+39 0565 701325",
    "sg:postcode":"57027",
    "sg:province":"Livorno",
    "wof:name":"Tmo Trasformazioni Snc",
    "wof:placetype":"venue"
},
  "geometry": {"coordinates":[10.550224,43.084045],"type":"Point"}
}