{
  "type": "Feature",
  "properties": {
    "addr:full":"00191 Roma Roma Roma 00191",
    "addr:postcode":"00191;00191",
    "iso:country":"IT",
    "sg:address":"00191 Roma",
    "sg:city":"Roma",
    "sg:classifiers":[
        {
            "category":"Health Services",
            "subcategory":"Health Practitioner",
            "type":"Services"
        }
    ],
    "sg:phone":"+39 06 329 1342",
    "sg:postcode":"00191",
    "sg:province":"Roma",
    "sg:tags":[
        "medici"
    ],
    "wof:name":"Costamagna Guido",
    "wof:placetype":"venue"
},
  "geometry": {"coordinates":[12.478188,41.95248],"type":"Point"}
}