{
  "type": "Feature",
  "properties": {
    "iso:country":"IT",
    "sg:address":"31047 Ponte Di Piave",
    "sg:city":"Ponte di Piave",
    "sg:orig_category":"Arredi Ed Attrezzature Per Uffici",
    "sg:phone":"+39 0422 759619",
    "sg:postcode":"31047",
    "sg:province":"Treviso",
    "wof:name":"E - Z Managing S.r.l.",
    "wof:placetype":"venue"
},
  "geometry": {"coordinates":[12.462945,45.715431],"type":"Point"}
}