{
  "type": "Feature",
  "properties": {
    "addr:full":"8, Via Serralunga Giovanni Battista 13900 Biella Biella Biella 13900",
    "addr:postcode":"13900;13900",
    "addr:street":"Via Serralunga Giovanni Battista",
    "iso:country":"IT",
    "sg:address":"8, Via Serralunga Giovanni Battista 13900 Biella",
    "sg:city":"Biella",
    "sg:classifiers":[
        {
            "category":"Shopping",
            "subcategory":"Crafts & Fabrics",
            "type":"Retail Goods"
        }
    ],
    "sg:phone":"+39 39015351746",
    "sg:postcode":"13900",
    "sg:province":"Biella",
    "wof:name":"Dawson H. Italia (s.r.l.)",
    "wof:placetype":"venue"
},
  "geometry": {"coordinates":[8.0582695007,45.5628356934],"type":"Point"}
}