{
  "type": "Feature",
  "properties": {
    "addr:full":"80055 Portici Portici Napoli 80055",
    "addr:postcode":"80055;80055",
    "iso:country":"IT",
    "sg:address":"80055 Portici",
    "sg:city":"Portici",
    "sg:orig_category":"Chiese Ed Associazioni Religiose",
    "sg:phone":"+39 081 739 5631",
    "sg:postcode":"80055",
    "sg:province":"Napoli",
    "wof:name":"Chiesa Evangelica",
    "wof:placetype":"venue"
},
  "geometry": {"coordinates":[14.339148,40.807434],"type":"Point"}
}