{
  "type": "Feature",
  "properties": {
    "addr:full":"1, Via Repubblica 42014 Castellarano Reggio Nell'Emilia 42014",
    "addr:postcode":"42014;42014",
    "addr:street":"Via Repubblica",
    "iso:country":"IT",
    "sg:address":"1, Via Repubblica 42014 Castellarano",
    "sg:classifiers":[
        {
            "category":"Manufacturing",
            "subcategory":"Wood Products",
            "type":"Manufacturing & Wholesale Goods"
        }
    ],
    "sg:phone":"+39 0536 851784",
    "sg:postcode":"42014",
    "sg:province":"Reggio Nell'Emilia",
    "sg:tags":[
        "furniture"
    ],
    "wof:name":"Falegnameria Pollini Pietro & C. (s.n.c.)",
    "wof:placetype":"venue"
},
  "geometry": {"coordinates":[10.627794,44.696228],"type":"Point"}
}