{
  "type": "Feature",
  "properties": {
    "iso:country":"IT",
    "sg:address":"00040 Cecchina",
    "sg:orig_category":"Abbigliamento Intimo, Calze E Costumi Da Bagno. Sport - Articoli E Forniture. Shopping",
    "sg:phone":"+39 06 934 1277",
    "sg:postcode":"00040",
    "sg:province":"Roma",
    "wof:name":"Amatrudo Maddalena",
    "wof:placetype":"venue"
},
  "geometry": {"coordinates":[12.640429,41.681614],"type":"Point"}
}