{
  "type": "Feature",
  "properties": {
    "addr:full":"Via Della Traversa 1 22074 Lomazzo Lomazzo Como 22074",
    "addr:housenumber":"1",
    "addr:postcode":"22074;22074",
    "addr:street":"Via Della Traversa",
    "iso:country":"IT",
    "sg:address":"Via Della Traversa 1 22074 Lomazzo",
    "sg:city":"Lomazzo",
    "sg:classifiers":[
        {
            "category":"Home & Garden",
            "subcategory":"Kitchen Supply",
            "type":"Retail Goods"
        }
    ],
    "sg:phone":"+39 02 9677 9085",
    "sg:postcode":"22074",
    "sg:province":"Como",
    "sg:tags":[
        "utensil",
        "aluminium",
        "commercial"
    ],
    "sg:website":"www.cifasrl.it",
    "wof:name":"Cifa Srl",
    "wof:placetype":"venue"
},
  "geometry": {"coordinates":[9.042337,45.688412],"type":"Point"}
}