{
  "type": "Feature",
  "properties": {
    "addr:full":"2, Viale Roma 65010 Civitaquana Civitaquana Pescara 65010",
    "addr:postcode":"65010;65010",
    "addr:street":"Viale Roma",
    "iso:country":"IT",
    "sg:address":"2, Viale Roma 65010 Civitaquana",
    "sg:city":"Civitaquana",
    "sg:classifiers":[
        {
            "category":"Real Estate",
            "subcategory":"Architect",
            "type":"Services"
        }
    ],
    "sg:phone":"+39 39085848003",
    "sg:postcode":"65010",
    "sg:province":"Pescara",
    "sg:tags":[
        "textile",
        "clothing"
    ],
    "wof:name":"Aemmegi Confezioni Di Belvedere Tiziana",
    "wof:placetype":"venue"
},
  "geometry": {"coordinates":[13.901842,42.324577],"type":"Point"}
}