{
  "type": "Feature",
  "properties": {
    "iso:country":"IT",
    "sg:address":"57, Viale Italia 51100 Pistoia",
    "sg:city":"Pistoia",
    "sg:classifiers":[
        {
            "category":"Professional",
            "subcategory":"Engineering",
            "type":"Services"
        }
    ],
    "sg:phone":"+39 39057328341",
    "sg:postcode":"51100",
    "sg:province":"Pistoia",
    "sg:tags":[
        "machine",
        "-",
        "mechanical"
    ],
    "wof:name":"Breschi & Melani S.n.c.",
    "wof:placetype":"venue"
},
  "geometry": {"coordinates":[10.920067,43.940617],"type":"Point"}
}