{
  "type": "Feature",
  "properties": {
    "addr:full":"30175 Venezia Marghera Venezia 30175",
    "addr:postcode":"30175;30175",
    "iso:country":"IT",
    "sg:address":"30175 Venezia",
    "sg:city":"Marghera",
    "sg:orig_category":"Spedizioni Aeree, Marittime E Terrestri",
    "sg:phone":"+39 041 929088",
    "sg:postcode":"30175",
    "sg:province":"Venezia",
    "wof:name":"Mazzoleni & Facori Srl",
    "wof:placetype":"venue"
},
  "geometry": {"coordinates":[12.198819,45.455975],"type":"Point"}
}