{
  "type": "Feature",
  "properties": {
    "iso:country":"IT",
    "sg:address":"00176 Roma",
    "sg:city":"Roma",
    "sg:orig_category":"Forniture Per Attivita' Commerciali Ed Artigianali. Arredi Ed Attrezzature Per Attivita' Commerciali Ed Artigianali",
    "sg:phone":"+39 06 2170 2286",
    "sg:postcode":"00176",
    "sg:province":"Roma",
    "wof:name":"M.g. Gas.po.dini. & Co. Snc Di Dell'orco A.",
    "wof:placetype":"venue"
},
  "geometry": {"coordinates":[12.5338363647,41.8838691711],"type":"Point"}
}