{
  "type": "Feature",
  "properties": {
    "addr:full":"80056 Ercolano Ercolano Napoli 80056",
    "addr:postcode":"80056;80056",
    "iso:country":"IT",
    "sg:address":"80056 Ercolano",
    "sg:city":"Ercolano",
    "sg:orig_category":"Prodotti Alimentari",
    "sg:phone":"+39 081 739 0127",
    "sg:postcode":"80056",
    "sg:province":"Napoli",
    "wof:name":"Papale Pietro",
    "wof:placetype":"venue"
},
  "geometry": {"coordinates":[14.3564691544,40.8097648621],"type":"Point"}
}