{
  "type": "Feature",
  "properties": {
    "iso:country":"IT",
    "sg:address":"Via Delle Cantine 61 50041 Calenzano",
    "sg:city":"Calenzano",
    "sg:classifiers":[
        {
            "category":"Banks & Credit Unions",
            "subcategory":"Bureau De Change",
            "type":"Services"
        }
    ],
    "sg:phone":"+39 055 882 5080",
    "sg:postcode":"50041",
    "sg:province":"Firenze",
    "sg:tags":[
        "decoration",
        "accessory"
    ],
    "sg:website":"www.sc3.it",
    "wof:name":"Manifattura Sc 3 Snc",
    "wof:placetype":"venue"
},
  "geometry": {"coordinates":[11.184949,43.860538],"type":"Point"}
}