{
  "type": "Feature",
  "properties": {
    "iso:country":"IT",
    "sg:address":"90013 Castelbuono",
    "sg:city":"Castelbuono",
    "sg:orig_category":"Prodotti E Manufatti In Gomma. Servizi E Lavori Industria Della Gomma. Ricambi E Componenti Dei Mezzi Di Trasporto. Riparazione Dei Mezzi Di Trasporto",
    "sg:phone":"+39 0921 672484",
    "sg:postcode":"90013",
    "sg:province":"Palermo",
    "wof:name":"Cucco Gomme Snc Di Angelo Cucco & C.",
    "wof:placetype":"venue"
},
  "geometry": {"coordinates":[14.088517189,37.9376373291],"type":"Point"}
}