{
  "type": "Feature",
  "properties": {
    "addr:full":"Loc. Z.i., 60025 Villa Musone Villa Musone Ancona 60025",
    "addr:postcode":"60025;60025",
    "addr:street":"Loc. Z.I.;Villa Musone Villa",
    "iso:country":"IT",
    "sg:address":"Loc. Z.i., 60025 Villa Musone",
    "sg:city":"Villa Musone",
    "sg:classifiers":[
        {
            "category":"Utilities",
            "subcategory":"Sewage",
            "type":"Services"
        }
    ],
    "sg:phone":"+39 071 750 1018",
    "sg:postcode":"60025",
    "sg:province":"Ancona",
    "sg:tags":[
        "cnc",
        "grinding"
    ],
    "sg:website":"www.gimaspa.com",
    "wof:name":"Gima Spa",
    "wof:placetype":"venue"
},
  "geometry": {"coordinates":[13.518757,43.615856],"type":"Point"}
}