{
  "type": "Feature",
  "properties": {
    "addr:full":"6, Via Monte Rosa 20020 Vanzaghello Vanzaghello Milano 20020",
    "addr:postcode":"20020;20020",
    "addr:street":"Via Monte Rosa",
    "iso:country":"IT",
    "sg:address":"6, Via Monte Rosa 20020 Vanzaghello",
    "sg:city":"Vanzaghello",
    "sg:classifiers":[
        {
            "category":"Shopping",
            "subcategory":"Crafts & Fabrics",
            "type":"Retail Goods"
        }
    ],
    "sg:phone":"+39 0331 306722",
    "sg:postcode":"20020",
    "sg:province":"Milano",
    "wof:name":"Tessitura Mifer (s.r.l.)",
    "wof:placetype":"venue"
},
  "geometry": {"coordinates":[8.779091835,45.5854263306],"type":"Point"}
}