{
  "type": "Feature",
  "properties": {
    "iso:country":"IT",
    "sg:address":"20019 Settimo Milanese",
    "sg:city":"Settimo Milanese",
    "sg:orig_category":"Vetro: Prodotti E Lavorazioni",
    "sg:phone":"+39 02 3351 2368",
    "sg:postcode":"20019",
    "sg:province":"Milano",
    "wof:name":"Z Film Di Zingarelli Michele",
    "wof:placetype":"venue"
},
  "geometry": {"coordinates":[9.038363,45.498348],"type":"Point"}
}