{
  "type": "Feature",
  "properties": {
    "addr:full":"70032 Bitonto Bitonto Bari 70032",
    "addr:postcode":"70032;70032",
    "iso:country":"IT",
    "sg:address":"70032 Bitonto",
    "sg:city":"Bitonto",
    "sg:classifiers":[
        {
            "category":"Restaurant",
            "type":"Food & Drink"
        }
    ],
    "sg:phone":"+39 080 374 6322",
    "sg:postcode":"70032",
    "sg:province":"Bari",
    "sg:tags":[
        "equipment",
        "industry",
        "machinery"
    ],
    "wof:name":"Vitone Srl",
    "wof:placetype":"venue"
},
  "geometry": {"coordinates":[16.5937652588,41.0751724243],"type":"Point"}
}