{
  "type": "Feature",
  "properties": {
    "addr:full":"37050 Oppeano Oppeano Verona 37050",
    "addr:postcode":"37050;37050",
    "iso:country":"IT",
    "sg:address":"37050 Oppeano",
    "sg:city":"Oppeano",
    "sg:orig_category":"Zootecnia E Pesca, Allevamento Piccoli Animali",
    "sg:phone":"+39 045 713 4044",
    "sg:postcode":"37050",
    "sg:province":"Verona",
    "wof:name":"Troticultura Vallesana",
    "wof:placetype":"venue"
},
  "geometry": {"coordinates":[11.054104805,45.3754577637],"type":"Point"}
}