{
  "type": "Feature",
  "properties": {
    "iso:country":"IT",
    "sg:address":"70015 Noci",
    "sg:city":"Noci",
    "sg:classifiers":[
        {
            "category":"Health Services",
            "subcategory":"Health Practitioner",
            "type":"Services"
        }
    ],
    "sg:phone":"+39 080 497 4012",
    "sg:postcode":"70015",
    "sg:province":"Bari",
    "sg:tags":[
        "medici"
    ],
    "wof:name":"Marco Angelo",
    "wof:placetype":"venue"
},
  "geometry": {"coordinates":[17.128332,40.787834],"type":"Point"}
}