{
  "type": "Feature",
  "properties": {
    "iso:country":"IT",
    "sg:address":"Via Agordat 26 20127 Milano",
    "sg:city":"Milano",
    "sg:classifiers":[
        {
            "category":"Wholesale",
            "subcategory":"Machinery & Supplies",
            "type":"Manufacturing & Wholesale Goods"
        }
    ],
    "sg:phone":"+39 02 284 6904",
    "sg:postcode":"20127",
    "sg:province":"Milano",
    "sg:tags":[
        "pin",
        "clevis"
    ],
    "wof:name":"Angelo Paulli S.r.l.",
    "wof:placetype":"venue"
},
  "geometry": {"coordinates":[9.234035,45.501789],"type":"Point"}
}