{
  "type": "Feature",
  "properties": {
    "addr:full":"35131 Padova Padova Padova 35131",
    "addr:postcode":"35131;35131",
    "iso:country":"IT",
    "sg:address":"35131 Padova",
    "sg:city":"Padova",
    "sg:classifiers":[
        {
            "category":"Banks & Credit Unions",
            "subcategory":"Investment Brokerage",
            "type":"Services"
        }
    ],
    "sg:phone":"+39 049 655023",
    "sg:postcode":"35131",
    "sg:province":"Padova",
    "sg:tags":[
        "parrucchieri",
        "per",
        "donna"
    ],
    "wof:name":"M.c. Studio Snc Di Maniero & Forin",
    "wof:placetype":"venue"
},
  "geometry": {"coordinates":[11.8928194046,45.4134521484],"type":"Point"}
}