{
  "type": "Feature",
  "properties": {
    "addr:full":"22100 Como Como Como 22100",
    "addr:postcode":"22100;22100",
    "iso:country":"IT",
    "sg:address":"22100 Como",
    "sg:city":"Como",
    "sg:orig_category":"Banche E Servizi Finanziari",
    "sg:phone":"+39 031 240857",
    "sg:postcode":"22100",
    "sg:province":"Como",
    "sg:website":"http://www.sicurcredit.it",
    "wof:name":"Sicurcredit Di Lentoni Laura",
    "wof:placetype":"venue"
},
  "geometry": {"coordinates":[9.091042,45.800575],"type":"Point"}
}