{
  "type": "Feature",
  "properties": {
    "addr:full":"Via S. Rocco 24060 Solto Collina Solto Collina Bergamo 24060",
    "addr:housenumber":"collina",
    "addr:postcode":"24060;24060",
    "addr:street":"Via S. Rocco;Collina",
    "iso:country":"IT",
    "sg:address":"Via S. Rocco 24060 Solto Collina",
    "sg:city":"Solto Collina",
    "sg:classifiers":[
        {
            "category":"Shopping",
            "subcategory":"Crafts & Fabrics",
            "type":"Retail Goods"
        }
    ],
    "sg:phone":"+39 39035986127",
    "sg:postcode":"24060",
    "sg:province":"Bergamo",
    "wof:name":"Belometti Innocente",
    "wof:placetype":"venue"
},
  "geometry": {"coordinates":[9.6699523926,45.6949043274],"type":"Point"}
}