{
  "type": "Feature",
  "properties": {
    "addr:full":"10071 Borgaro Torinese Borgaro Torinese Torino 10071",
    "addr:postcode":"10071;10071",
    "iso:country":"IT",
    "sg:address":"10071 Borgaro Torinese",
    "sg:city":"Borgaro Torinese",
    "sg:orig_category":"Filati E Materie Prime Tessili",
    "sg:phone":"+39 011 470 3615",
    "sg:postcode":"10071",
    "sg:province":"Torino",
    "wof:name":"Il Gomitolo",
    "wof:placetype":"venue"
},
  "geometry": {"coordinates":[7.6563606262,45.1536216736],"type":"Point"}
}