{
  "type": "Feature",
  "properties": {
    "iso:country":"IT",
    "sg:address":"66054 Vasto",
    "sg:city":"Vasto",
    "sg:orig_category":"Macchine Ed Impianti Per Edilizia E Lavori Pubblici. Macchine, Strumenti Ed Apparecchi Per Attivita' Industriali",
    "sg:phone":"+39 0873 311004",
    "sg:postcode":"66054",
    "sg:province":"Chieti",
    "sg:website":"http://www.bht.it",
    "wof:name":"B.h.t. Srl",
    "wof:placetype":"venue"
},
  "geometry": {"coordinates":[14.693768,42.11887],"type":"Point"}
}