{
  "type": "Feature",
  "properties": {
    "iso:country":"IT",
    "sg:address":"Via Pio La Torre 7 60022 Castelfidardo",
    "sg:city":"Castelfidardo",
    "sg:classifiers":[
        {
            "category":"Shopping",
            "subcategory":"Musical Instruments",
            "type":"Retail Goods"
        }
    ],
    "sg:phone":"+39 071 782 2314",
    "sg:postcode":"60022",
    "sg:province":"Ancona",
    "sg:tags":[
        "accordion"
    ],
    "sg:website":"www.beltuna.com",
    "wof:name":"Beltuna Accordions Srl",
    "wof:placetype":"venue"
},
  "geometry": {"coordinates":[13.543146,43.455254],"type":"Point"}
}