{
  "type": "Feature",
  "properties": {
    "addr:full":"6, Via Emilia Parmense 29100 Piacenza Piacenza Piacenza 29100",
    "addr:postcode":"29100;29100",
    "addr:street":"Via Emilia Parmense",
    "iso:country":"IT",
    "sg:address":"6, Via Emilia Parmense 29100 Piacenza",
    "sg:city":"Piacenza",
    "sg:classifiers":[
        {
            "category":"Autos & Motor Vehicles",
            "subcategory":"Automobile Sales",
            "type":"Retail Goods"
        }
    ],
    "sg:phone":"+39 0523 590940",
    "sg:postcode":"29100",
    "sg:province":"Piacenza",
    "sg:tags":[
        "motor-cars"
    ],
    "wof:name":"Mirani (s.r.l.)",
    "wof:placetype":"venue"
},
  "geometry": {"coordinates":[9.718173027,45.0401992798],"type":"Point"}
}