{
  "type": "Feature",
  "properties": {
    "addr:full":"5/a, Via Galilei Galileo 35042 Este Este Padova 35042",
    "addr:housenumber":"5 / a",
    "addr:postcode":"35042;35042",
    "addr:street":"Via Galilei Galileo",
    "iso:country":"IT",
    "sg:address":"5/a, Via Galilei Galileo 35042 Este",
    "sg:city":"Este",
    "sg:classifiers":[
        {
            "category":"Shopping",
            "type":"Retail Goods"
        }
    ],
    "sg:phone":"+39 0429 602766",
    "sg:postcode":"35042",
    "sg:province":"Padova",
    "sg:tags":[
        "finished",
        "-",
        "metallic"
    ],
    "wof:name":"Emporio Forniture Idrauliche Industriali E Affini (s.r.l.)",
    "wof:placetype":"venue"
},
  "geometry": {"coordinates":[11.8765888214,45.4095687866],"type":"Point"}
}