{
  "type": "Feature",
  "properties": {
    "addr:full":"41012 Carpi Carpi Modena 41012",
    "addr:postcode":"41012;41012",
    "iso:country":"IT",
    "sg:address":"41012 Carpi",
    "sg:city":"Carpi",
    "sg:orig_category":"Forniture Per Abbigliamento E Pelletterie. Complementi Di Arredamento",
    "sg:phone":"+39 059 645843",
    "sg:postcode":"41012",
    "sg:province":"Modena",
    "sg:website":"http://www.paginegialle.it/manifatturacarpigian",
    "wof:name":"Manifattura Carpigiana Sas",
    "wof:placetype":"venue"
},
  "geometry": {"coordinates":[10.88676548,44.817615509],"type":"Point"}
}