{
  "type": "Feature",
  "properties": {
    "addr:full":"Via Di Vittorio Giuseppe 17 25125 Brescia Brescia Brescia 25125",
    "addr:housenumber":"17",
    "addr:postcode":"25125;25125",
    "addr:street":"Via Di Vittorio Giuseppe",
    "iso:country":"IT",
    "sg:address":"Via Di Vittorio Giuseppe 17 25125 Brescia",
    "sg:city":"Brescia",
    "sg:orig_category":"Video Signal Transmission Equipment",
    "sg:phone":"+39 030 358 2226",
    "sg:postcode":"25125",
    "sg:province":"Brescia",
    "sg:website":"www.screen.it",
    "wof:name":"Screen Service Italia S.r.l.",
    "wof:placetype":"venue"
},
  "geometry": {"coordinates":[10.222958,45.539829],"type":"Point"}
}