{
  "type": "Feature",
  "properties": {
    "addr:full":"25018 Montichiari Montichiari Brescia 25018",
    "addr:postcode":"25018;25018",
    "iso:country":"IT",
    "sg:address":"25018 Montichiari",
    "sg:city":"Montichiari",
    "sg:classifiers":[
        {
            "category":"Banks & Credit Unions",
            "subcategory":"Investment Brokerage",
            "type":"Services"
        }
    ],
    "sg:phone":"+39 030 962096",
    "sg:postcode":"25018",
    "sg:province":"Brescia",
    "sg:tags":[
        "handling",
        "storage"
    ],
    "wof:name":"Autotrasporti Cogno Snc",
    "wof:placetype":"venue"
},
  "geometry": {"coordinates":[10.393111,45.398247],"type":"Point"}
}