{
  "type": "Feature",
  "properties": {
    "addr:full":"Km. 26.650, Via Sannitica 81020 San Marco Evangelista San Marco Evangelista Caserta 81020",
    "addr:postcode":"81020;81020",
    "addr:street":"Km. 26.650 Via Sannitica",
    "iso:country":"IT",
    "sg:address":"Km. 26.650, Via Sannitica 81020 San Marco Evangelista",
    "sg:city":"San Marco Evangelista",
    "sg:classifiers":[
        {
            "category":"Shopping",
            "subcategory":"Crafts & Fabrics",
            "type":"Retail Goods"
        }
    ],
    "sg:phone":"+39 0823 408964",
    "sg:postcode":"81020",
    "sg:province":"Caserta",
    "wof:name":"San Leucio Passamanerie Srl.",
    "wof:placetype":"venue"
},
  "geometry": {"coordinates":[14.3321943283,41.0754165649],"type":"Point"}
}