{
  "type": "Feature",
  "properties": {
    "iso:country":"IT",
    "sg:address":"20159 Milano",
    "sg:city":"Milano",
    "sg:orig_category":"Elettrotecnica Industriale, Prodotti E Apparecchiature. Elettrotecnica Professionale E Di Consumo",
    "sg:phone":"+39 02 6900 7417",
    "sg:postcode":"20159",
    "sg:province":"Milano",
    "wof:name":"Recon Di Gallibariggio Elio",
    "wof:placetype":"venue"
},
  "geometry": {"coordinates":[9.18616,45.48666],"type":"Point"}
}