{
  "type": "Feature",
  "properties": {
    "iso:country":"IT",
    "sg:address":"20121 Milano",
    "sg:city":"Milano",
    "sg:orig_category":"Materiali Semilavorati Metallici",
    "sg:phone":"+39 02 2901 7005",
    "sg:postcode":"20121",
    "sg:province":"Milano",
    "wof:name":"Midland Green Srl",
    "wof:placetype":"venue"
},
  "geometry": {"coordinates":[9.186829,45.478973],"type":"Point"}
}