{
  "type": "Feature",
  "properties": {
    "iso:country":"IT",
    "sg:address":"31058 Susegana",
    "sg:city":"Susegana",
    "sg:orig_category":"Forniture Per Edilizia E Lavori Pubblici. Prodotti Vari In Metallo",
    "sg:phone":"+39 0438 73446",
    "sg:postcode":"31058",
    "sg:province":"Treviso",
    "wof:name":"Improv Di Cesca Alessandro",
    "wof:placetype":"venue"
},
  "geometry": {"coordinates":[12.2328681946,45.8540611267],"type":"Point"}
}