{
  "type": "Feature",
  "properties": {
    "iso:country":"IT",
    "sg:address":"1, V. Del Melo 51018 Pieve A Nievole",
    "sg:city":"Pieve a Nievole",
    "sg:classifiers":[
        {
            "category":"Personal",
            "subcategory":"Shoe Repair & Shine",
            "type":"Services"
        }
    ],
    "sg:phone":"+39 39057295661",
    "sg:postcode":"51018",
    "sg:province":"Pistoia",
    "sg:tags":[
        "leather"
    ],
    "sg:website":"http://www.balducci.it",
    "wof:name":"Balducci Spa",
    "wof:placetype":"venue"
},
  "geometry": {"coordinates":[10.793729,43.873116],"type":"Point"}
}