{
  "type": "Feature",
  "properties": {
    "iso:country":"IT",
    "sg:address":"00065 Fiano Romano",
    "sg:city":"Fiano Romano",
    "sg:orig_category":"Macchine, Impianti Ed Attrezzature Per Abbigliamento E Pelletterie. Macchine E Impianti Per Attivita' Commerciali Ed Artigianali",
    "sg:phone":"+39 0765 455299",
    "sg:postcode":"00065",
    "sg:province":"Roma",
    "wof:name":"Nuova Folati Dry Cleaning Srl",
    "wof:placetype":"venue"
},
  "geometry": {"coordinates":[12.585456,42.136951],"type":"Point"}
}