{
  "type": "Feature",
  "properties": {
    "iso:country":"IT",
    "sg:address":"90039 Villabate",
    "sg:city":"Villabate",
    "sg:orig_category":"Prodotti Alimentari. Agricoltura, Orticoltura E Floricoltura",
    "sg:phone":"+39 091 492838",
    "sg:postcode":"90039",
    "sg:province":"Palermo",
    "wof:name":"E.s.a.v.di Gargano Nunzio & C.s.n.c.",
    "wof:placetype":"venue"
},
  "geometry": {"coordinates":[13.4508838654,38.0853996277],"type":"Point"}
}