{
  "type": "Feature",
  "properties": {
    "iso:country":"IT",
    "sg:address":"Molino Di Bascio 61016 Pennabilli",
    "sg:city":"Molino di Bascio",
    "sg:classifiers":[
        {
            "category":"Real Estate",
            "subcategory":"Architect",
            "type":"Services"
        }
    ],
    "sg:phone":"+39 0541 915721",
    "sg:postcode":"61016",
    "sg:province":"Pesaro E Urbino",
    "sg:tags":[
        "textile",
        "clothing"
    ],
    "wof:name":"Sartoria Crescentini S.n.c. Di Angelini Gianluca &",
    "wof:placetype":"venue"
},
  "geometry": {"coordinates":[12.200167,43.766724],"type":"Point"}
}