{
  "type": "Feature",
  "properties": {
    "addr:full":"56010 Vicopisano Vicopisano Pisa 56010",
    "addr:housenumber":"56010",
    "addr:postcode":"56010",
    "addr:street":"Vicopisano Vicopisano",
    "iso:country":"IT",
    "sg:address":"56010 Vicopisano",
    "sg:city":"Vicopisano",
    "sg:orig_category":"Distributors: Automatici - Commercio E Gestione",
    "sg:phone":"+39 050 799136",
    "sg:postcode":"56010",
    "sg:province":"Pisa",
    "wof:name":"Novi Caffe' Snc",
    "wof:placetype":"venue"
},
  "geometry": {"coordinates":[10.582597,43.687145],"type":"Point"}
}