{
  "type": "Feature",
  "properties": {
    "iso:country":"IT",
    "sg:address":"20052 Monza",
    "sg:city":"Monza",
    "sg:orig_category":"Materiali E Componenti Elettrotecnici",
    "sg:phone":"+39 039 360155",
    "sg:postcode":"20052",
    "sg:province":"Milano",
    "wof:name":"Optotec Societa' Per Azioni",
    "wof:placetype":"venue"
},
  "geometry": {"coordinates":[9.18729,45.465607],"type":"Point"}
}