{
  "type": "Feature",
  "properties": {
    "iso:country":"IT",
    "sg:address":"Via A. Ciucani 8 20060 Ornago",
    "sg:city":"Ornago",
    "sg:classifiers":[
        {
            "category":"Manufacturing",
            "subcategory":"Motor Vehicles & Parts",
            "type":"Manufacturing & Wholesale Goods"
        }
    ],
    "sg:phone":"+39 039 66581",
    "sg:postcode":"20060",
    "sg:province":"Milano",
    "sg:tags":[
        "extruded",
        "product",
        "aluminium",
        "wrought"
    ],
    "sg:website":"www.hydro.com",
    "wof:name":"Hydro Alluminio Ornago Spa",
    "wof:placetype":"venue"
},
  "geometry": {"coordinates":[9.188141,45.463688],"type":"Point"}
}