{
  "type": "Feature",
  "properties": {
    "addr:full":"84098 Pontecagnano Faiano Faiano Salerno 84098",
    "addr:postcode":"84098;84098",
    "iso:country":"IT",
    "sg:address":"84098 Pontecagnano Faiano",
    "sg:city":"Faiano",
    "sg:classifiers":[
        {
            "category":"Shopping",
            "subcategory":"Bicycles & Sporting Goods",
            "type":"Retail Goods"
        }
    ],
    "sg:phone":"+39 0828 355052",
    "sg:postcode":"84098",
    "sg:province":"Salerno",
    "sg:tags":[
        "tempo",
        "lo",
        "-",
        "libero",
        "per",
        "servizi",
        "forniture",
        "articoli",
        "e",
        "sport",
        "il"
    ],
    "wof:name":"A.n.p.d.i Salerno",
    "wof:placetype":"venue"
},
  "geometry": {"coordinates":[14.889038,40.611504],"type":"Point"}
}