{
  "type": "Feature",
  "properties": {
    "iso:country":"IT",
    "sg:address":"88900 Crotone",
    "sg:city":"Crotone",
    "sg:orig_category":"Case Editrici",
    "sg:phone":"+39 0962 22345",
    "sg:postcode":"88900",
    "sg:province":"Crotone",
    "wof:name":"Scerra Cinzia",
    "wof:placetype":"venue"
},
  "geometry": {"coordinates":[17.125629,39.078865],"type":"Point"}
}