{
  "type": "Feature",
  "properties": {
    "iso:country":"IT",
    "sg:address":"30121 Venezia",
    "sg:city":"Cannaregio",
    "sg:orig_category":"Accessori Moda D'abbigliamento. Shopping",
    "sg:phone":"+39 041 520 6647",
    "sg:postcode":"30121",
    "sg:province":"Venezia",
    "wof:name":"Zamengo Tiziano",
    "wof:placetype":"venue"
},
  "geometry": {"coordinates":[12.327647,45.445717],"type":"Point"}
}