{
  "type": "Feature",
  "properties": {
    "iso:country":"IT",
    "sg:address":"235, V. Nizza 15011 Acqui Terme",
    "sg:city":"Acqui Terme",
    "sg:classifiers":[
        {
            "category":"Professional",
            "subcategory":"Printing & Photocopies",
            "type":"Services"
        }
    ],
    "sg:postcode":"15011",
    "sg:province":"Alessandria",
    "sg:website":"http://www.tiscalinet.it/laltraimmagine",
    "wof:name":"L'altra Immagine Di Drago Giovanni",
    "wof:placetype":"venue"
},
  "geometry": {"coordinates":[8.4728307724,44.680431366],"type":"Point"}
}