{
  "type": "Feature",
  "properties": {
    "addr:full":"20024 Garbagnate Milanese Garbagnate Milanese Milano 20024",
    "addr:postcode":"20024;20024",
    "iso:country":"IT",
    "sg:address":"20024 Garbagnate Milanese",
    "sg:city":"Garbagnate Milanese",
    "sg:orig_category":"Forniture Per Attivita' Commerciali Ed Artigianali",
    "sg:phone":"+39 02 9902 8798",
    "sg:postcode":"20024",
    "sg:province":"Milano",
    "wof:name":"Biazzi Claudio",
    "wof:placetype":"venue"
},
  "geometry": {"coordinates":[9.0896034241,45.5811424255],"type":"Point"}
}