{
  "type": "Feature",
  "properties": {
    "addr:full":"Piazza Matteotti 17; Bellaria; 47041",
    "addr:housenumber":"17",
    "addr:postcode":"47041",
    "addr:street":"Piazza Matteotti;Bellaria",
    "iso:country":"IT",
    "sg:address":"Piazza Matteotti 17; Bellaria; 47041",
    "sg:classifiers":[
        {
            "category":"Banks & Credit Unions",
            "subcategory":"Bank",
            "type":"Services"
        }
    ],
    "sg:phone":"+39 0541 344496",
    "wof:name":"Rolo Banca 1473 Spa",
    "wof:placetype":"venue"
},
  "geometry": {"coordinates":[12.463616,44.146259],"type":"Point"}
}