{
  "type": "Feature",
  "properties": {
    "iso:country":"IT",
    "sg:address":"00178 Roma",
    "sg:city":"Roma",
    "sg:orig_category":"Armadi Guardaroba",
    "sg:phone":"+39 06 7107 2264",
    "sg:postcode":"00178",
    "sg:province":"Roma",
    "wof:name":"Fornari Arredamenti Srl",
    "wof:placetype":"venue"
},
  "geometry": {"coordinates":[12.544804,41.841248],"type":"Point"}
}