{
  "type": "Feature",
  "properties": {
    "iso:country":"IT",
    "sg:address":"Via S. Allende 104 47030 Gatteo",
    "sg:classifiers":[
        {
            "category":"Utilities",
            "subcategory":"Mobile Phone",
            "type":"Services"
        }
    ],
    "sg:phone":"+39 0541 818382",
    "sg:postcode":"47030",
    "sg:province":"Forl\u00ec-Cesena",
    "sg:tags":[
        "sculpture"
    ],
    "wof:name":"Sculture In Pane Di Giannatempo Ottavio E Teresa",
    "wof:placetype":"venue"
},
  "geometry": {"coordinates":[12.38427,44.135193],"type":"Point"}
}