{
  "type": "Feature",
  "properties": {
    "iso:country":"IT",
    "sg:address":"20123 Milano",
    "sg:city":"Milano",
    "sg:orig_category":"Servizi E Lavori Industria Chimica. Riparazione Dei Mezzi Di Trasporto",
    "sg:phone":"+39 02 5810 0546",
    "sg:postcode":"20123",
    "sg:province":"Milano",
    "wof:name":"Forza E Toffanello",
    "wof:placetype":"venue"
},
  "geometry": {"coordinates":[9.170892,45.459057],"type":"Point"}
}