{
  "type": "Feature",
  "properties": {
    "iso:country":"IT",
    "sg:address":"23870 Cernusco Lombardone",
    "sg:city":"Cernusco Lombardone",
    "sg:orig_category":"Articoli Per Imballaggio E Confezionamento",
    "sg:phone":"+39 039 990 2120",
    "sg:postcode":"23870",
    "sg:province":"Lecco",
    "wof:name":"Casalini Srl",
    "wof:placetype":"venue"
},
  "geometry": {"coordinates":[9.401498,45.691021],"type":"Point"}
}