{
  "type": "Feature",
  "properties": {
    "iso:country":"IT",
    "sg:address":"Via Roma 68; Zugliano; 36030",
    "sg:city":"Zugliano",
    "sg:classifiers":[
        {
            "category":"Banks & Credit Unions",
            "subcategory":"Bank",
            "type":"Services"
        }
    ],
    "sg:phone":"+39 0445 330114",
    "sg:postcode":"36030",
    "sg:province":"Vicenza",
    "wof:name":"Banca Popolare Vicentina",
    "wof:placetype":"venue"
},
  "geometry": {"coordinates":[11.521798,45.733398],"type":"Point"}
}