{
  "type": "Feature",
  "properties": {
    "addr:full":"52, Via Mazzini 23811 Ballabio Ballabio Lecco 23811",
    "addr:postcode":"23811;23811",
    "addr:street":"Via Mazzini",
    "iso:country":"IT",
    "sg:address":"52, Via Mazzini 23811 Ballabio",
    "sg:city":"Ballabio",
    "sg:classifiers":[
        {
            "category":"Food & Beverages",
            "subcategory":"Dairy",
            "type":"Retail Goods"
        }
    ],
    "sg:phone":"+39 0341 530113",
    "sg:postcode":"23811",
    "sg:province":"Lecco",
    "sg:tags":[
        "product"
    ],
    "wof:name":"Ganassa (s.n.c.)",
    "wof:placetype":"venue"
},
  "geometry": {"coordinates":[9.422254,45.89328],"type":"Point"}
}