{
  "type": "Feature",
  "properties": {
    "iso:country":"IT",
    "sg:address":"39012 Merano",
    "sg:city":"Merano",
    "sg:classifiers":[
        {
            "category":"Restaurant",
            "type":"Food & Drink"
        }
    ],
    "sg:phone":"+39 0473 271000",
    "sg:postcode":"39012",
    "sg:province":"Bolzano/Bozen",
    "sg:tags":[
        "auxiliary",
        "entertainment",
        "premises",
        "related",
        "catering",
        "similar",
        "public",
        "restaurants"
    ],
    "sg:website":"http://www.palace.it",
    "wof:name":"Grand Hotel Palace Espace Henri Chenot",
    "wof:placetype":"venue"
},
  "geometry": {"coordinates":[11.358081,46.501728],"type":"Point"}
}