{
  "type": "Feature",
  "properties": {
    "addr:full":"10, Via Mangesa 31015 Conegliano Conegliano Treviso 31015",
    "addr:postcode":"31015;31015",
    "addr:street":"Via Mangesa",
    "iso:country":"IT",
    "sg:address":"10, Via Mangesa 31015 Conegliano",
    "sg:city":"Conegliano",
    "sg:classifiers":[
        {
            "category":"Food & Beverages",
            "subcategory":"Groceries & Convenience Stores",
            "type":"Retail Goods"
        }
    ],
    "sg:phone":"+39 39043823719",
    "sg:postcode":"31015",
    "sg:province":"Treviso",
    "sg:tags":[
        "drink"
    ],
    "wof:name":"Azienda Loggia Del Colle (s.r.l.)",
    "wof:placetype":"venue"
},
  "geometry": {"coordinates":[12.294645,45.915066],"type":"Point"}
}