{
  "type": "Feature",
  "properties": {
    "iso:country":"IT",
    "sg:address":"24030 Medolago",
    "sg:city":"Medolago",
    "sg:orig_category":"Stampi Materie Plastiche E Gomma",
    "sg:phone":"+39 035 493 3444",
    "sg:postcode":"24030",
    "sg:province":"Bergamo",
    "sg:website":"http://www.previtali.it",
    "wof:name":"Previtali F. Lli Snc",
    "wof:placetype":"venue"
},
  "geometry": {"coordinates":[9.496722,45.669537],"type":"Point"}
}