{
  "type": "Feature",
  "properties": {
    "addr:full":"38, Corso Montevecchio Torino Torino 10129",
    "addr:postcode":"10129",
    "addr:street":"Corso Montevecchio",
    "iso:country":"IT",
    "sg:address":"38, Corso Montevecchio",
    "sg:city":"Torino",
    "sg:classifiers":[
        {
            "category":"Banks & Credit Unions",
            "subcategory":"Bank",
            "type":"Services"
        }
    ],
    "sg:phone":"+39 011 517 6990",
    "sg:postcode":"10129",
    "sg:province":"Torino",
    "sg:tags":[
        "banking",
        "institution"
    ],
    "wof:name":"Locat (s.p.a.)",
    "wof:placetype":"venue"
},
  "geometry": {"coordinates":[7.686619,45.07056],"type":"Point"}
}