{
  "type": "Feature",
  "properties": {
    "iso:country":"IT",
    "sg:address":"19/21, Strada St. Ss 401 85020 Pescopagano",
    "sg:city":"Pescopagano",
    "sg:classifiers":[
        {
            "category":"Home & Garden",
            "subcategory":"Home Furnishings",
            "type":"Retail Goods"
        }
    ],
    "sg:phone":"+39 390 976 5358",
    "sg:postcode":"85020",
    "sg:province":"Potenza",
    "sg:tags":[
        "household"
    ],
    "wof:name":"F.a.t A. Snc Di Farese Vito & C.",
    "wof:placetype":"venue"
},
  "geometry": {"coordinates":[15.802221,40.637241],"type":"Point"}
}