{
  "type": "Feature",
  "properties": {
    "iso:country":"IT",
    "sg:address":"21013 Gallarate",
    "sg:city":"Gallarate",
    "sg:orig_category":"Serramenti Ed Infissi",
    "sg:phone":"+39 0331 779055",
    "sg:postcode":"21013",
    "sg:province":"Varese",
    "wof:name":"Ardal Di Argenziano M. & Dal Maso A. Snc",
    "wof:placetype":"venue"
},
  "geometry": {"coordinates":[8.783525,45.673882],"type":"Point"}
}