{
  "type": "Feature",
  "properties": {
    "iso:country":"IT",
    "sg:address":"Via Campo Del Fiume 96 47890 Di Repubblica Di San Marino",
    "sg:classifiers":[
        {
            "category":"Manufacturing",
            "subcategory":"Rubber & Plastics",
            "type":"Manufacturing & Wholesale Goods"
        }
    ],
    "sg:phone":"+39 0549 996204",
    "sg:tags":[
        "additive"
    ],
    "sg:website":"www.titanstuc.com",
    "wof:name":"Titanstuc Sa",
    "wof:placetype":"venue"
},
  "geometry": {"coordinates":[12.481517,43.926212],"type":"Point"}
}