{
  "type": "Feature",
  "properties": {
    "iso:country":"IT",
    "sg:address":"31040 Venegazzu'",
    "sg:orig_category":"Macchine E Forniture Per Arredamento E Industria Del Legno",
    "sg:phone":"+39 0423 621674",
    "sg:postcode":"31040",
    "sg:province":"Treviso",
    "wof:name":"Natale Nardello & Figli S.n.c. Di Giovanni Battista E Paolo Nardello",
    "wof:placetype":"venue"
},
  "geometry": {"coordinates":[12.108458,45.748913],"type":"Point"}
}