{
  "type": "Feature",
  "properties": {
    "addr:full":"80, Via Moggia 16033 Lavagna Lavagna Genova 16033",
    "addr:postcode":"16033;16033",
    "addr:street":"Via Moggia",
    "iso:country":"IT",
    "sg:address":"80, Via Moggia 16033 Lavagna",
    "sg:city":"Lavagna",
    "sg:classifiers":[
        {
            "category":"Shopping",
            "subcategory":"Clothing, Apparel, & Fashions",
            "type":"Retail Goods"
        }
    ],
    "sg:phone":"+39 0185 322279",
    "sg:postcode":"16033",
    "sg:province":"Genova",
    "sg:tags":[
        "clothes"
    ],
    "wof:name":"Galson International S.r.l.",
    "wof:placetype":"venue"
},
  "geometry": {"coordinates":[9.348807,44.321339],"type":"Point"}
}