{
  "type": "Feature",
  "properties": {
    "iso:country":"IT",
    "sg:address":"30173 Mestre",
    "sg:city":"Mestre",
    "sg:orig_category":"Servizi Per Lo Sport E Il Tempo Libero. Servizi Ausiliari Dei Mezzi Di Trasporto",
    "sg:phone":"+39 041 531 1523",
    "sg:postcode":"30173",
    "sg:province":"Venezia",
    "wof:name":"Agenzia Nautica Base Mare 21 S.n.c.",
    "wof:placetype":"venue"
},
  "geometry": {"coordinates":[12.275324,45.468891],"type":"Point"}
}