{
  "type": "Feature",
  "properties": {
    "iso:country":"IT",
    "sg:address":"20094 Corsico",
    "sg:city":"Corsico",
    "sg:orig_category":"Servizi Per Aziende, Manifestazioni E Supporto Agli Scambi Commerciali",
    "sg:phone":"+39 02 4510 0125",
    "sg:postcode":"20094",
    "sg:province":"Milano",
    "sg:website":"http://www.plotini.com",
    "wof:name":"Plotini Allestimenti Srl",
    "wof:placetype":"venue"
},
  "geometry": {"coordinates":[9.082188,45.425179],"type":"Point"}
}