{
  "type": "Feature",
  "properties": {
    "iso:country":"IT",
    "sg:address":"57037 Portoferraio",
    "sg:city":"Portoferraio",
    "sg:orig_category":"Informatica - Consulenza E Servizi. Editoria",
    "sg:phone":"+39 0565 944012",
    "sg:postcode":"57037",
    "sg:province":"Livorno",
    "wof:name":"Daisy Group Srl",
    "wof:placetype":"venue"
},
  "geometry": {"coordinates":[10.327121,43.493439],"type":"Point"}
}