{
  "type": "Feature",
  "properties": {
    "addr:full":"Via Orefici Michelin 3 33170 Pordenone Pordenone Pordenone 33170",
    "addr:housenumber":"3",
    "addr:postcode":"33170;33170",
    "addr:street":"Via Orefici Michelin",
    "iso:country":"IT",
    "sg:address":"Via Orefici Michelin 3 33170 Pordenone",
    "sg:city":"Pordenone",
    "sg:classifiers":[
        {
            "category":"Communications",
            "subcategory":"Television Station",
            "type":"Services"
        }
    ],
    "sg:phone":"+39 0434 570261",
    "sg:postcode":"33170",
    "sg:province":"Pordenone",
    "sg:tags":[
        "curtain",
        "black-out"
    ],
    "sg:website":"www.marcolinsrl.it",
    "wof:name":"Marcolin Srl",
    "wof:placetype":"venue"
},
  "geometry": {"coordinates":[12.653548,45.93504],"type":"Point"}
}