{
  "type": "Feature",
  "properties": {
    "iso:country":"IT",
    "sg:address":"16126 Genova",
    "sg:city":"Genova",
    "sg:orig_category":"Scuole Di Orientamento, Formazione E Addestramento Professionale",
    "sg:phone":"+39 010 267850",
    "sg:postcode":"16126",
    "sg:province":"Genova",
    "wof:name":"S.a.a.u.l. Scuola Parrucchieri Ed Est. Di Triolo D. & C. Sas",
    "wof:placetype":"venue"
},
  "geometry": {"coordinates":[8.888069,44.967991],"type":"Point"}
}