{
  "type": "Feature",
  "properties": {
    "addr:full":"20051 Limbiate Limbiate Milano 20051",
    "addr:postcode":"20051;20051",
    "iso:country":"IT",
    "sg:address":"20051 Limbiate",
    "sg:city":"Limbiate",
    "sg:orig_category":"Servizi E Lavori Per Industria Alimentare E Bevande",
    "sg:phone":"+39 02 996 0063",
    "sg:postcode":"20051",
    "sg:province":"Milano",
    "wof:name":"Cooperativa Di Consumo E Agricola Di Limbiate",
    "wof:placetype":"venue"
},
  "geometry": {"coordinates":[9.149875,45.571587],"type":"Point"}
}