{
  "type": "Feature",
  "properties": {
    "iso:country":"IT",
    "sg:address":"55012 Capannori",
    "sg:city":"Capannori",
    "sg:orig_category":"Forniture Per Abbigliamento E Pelletterie. Forniture Per Attivita' Commerciali Ed Artigianali",
    "sg:phone":"+39 0583 928171",
    "sg:postcode":"55012",
    "sg:province":"Lucca",
    "wof:name":"Chelini Giuseppe - Accoppiature Gc",
    "wof:placetype":"venue"
},
  "geometry": {"coordinates":[10.5961847305,43.8854942322],"type":"Point"}
}