{
  "type": "Feature",
  "properties": {
    "iso:country":"IT",
    "sg:address":"20094 Corsico",
    "sg:city":"Corsico",
    "sg:orig_category":"Materiali E Componenti Elettrotecnici",
    "sg:phone":"+39 02 458 1541",
    "sg:postcode":"20094",
    "sg:province":"Milano",
    "sg:website":"http://www.ezioselva.it",
    "wof:name":"Ezio Selva Srl",
    "wof:placetype":"venue"
},
  "geometry": {"coordinates":[9.089705,45.436378],"type":"Point"}
}