{
  "type": "Feature",
  "properties": {
    "iso:country":"IT",
    "sg:address":"20131 Milano",
    "sg:city":"Milano",
    "sg:orig_category":"Valvole Automatiche E Di Sicurezza",
    "sg:phone":"+39 02 7063 4720",
    "sg:postcode":"20131",
    "sg:province":"Milano",
    "wof:name":"Besa Ing. Santangelo Spa",
    "wof:placetype":"venue"
},
  "geometry": {"coordinates":[9.221508,45.480331],"type":"Point"}
}