{
  "type": "Feature",
  "properties": {
    "iso:country":"IT",
    "sg:address":"37135 Verona",
    "sg:city":"Verona",
    "sg:orig_category":"Macchine, Impianti Ed Attrezzature Per Industria Alimentare E Bevande. Elettrodomestici. Macchine E Impianti Per Attivita' Commerciali Ed Artigianali",
    "sg:phone":"+39 045 820 1788",
    "sg:postcode":"37135",
    "sg:province":"Verona",
    "wof:name":"Seno & Seno (s.r.l.)",
    "wof:placetype":"venue"
},
  "geometry": {"coordinates":[10.978859,45.409595],"type":"Point"}
}