{
  "type": "Feature",
  "properties": {
    "addr:full":"58, Via Fontanina 40041 Gaggio Montano Gaggio Montano Bologna 40041",
    "addr:postcode":"40041;40041",
    "addr:street":"Via Fontanina",
    "iso:country":"IT",
    "sg:address":"58, Via Fontanina 40041 Gaggio Montano",
    "sg:city":"Gaggio Montano",
    "sg:classifiers":[
        {
            "category":"Professional",
            "subcategory":"Engineering",
            "type":"Services"
        }
    ],
    "sg:phone":"+39 39053437056",
    "sg:postcode":"40041",
    "sg:province":"Bologna",
    "sg:tags":[
        "machine",
        "-",
        "mechanical"
    ],
    "wof:name":"Tomasi Costruzioni Meccaniche (s.n.c.)",
    "wof:placetype":"venue"
},
  "geometry": {"coordinates":[11.346481,44.494221],"type":"Point"}
}