{
  "type": "Feature",
  "properties": {
    "iso:country":"IT",
    "sg:address":"52045 Foiano Della Chiana",
    "sg:city":"Foiano della Chiana",
    "sg:orig_category":"Alberghi E Strutture Extra Alberghiere",
    "sg:phone":"+39 0575 64071",
    "sg:postcode":"52045",
    "sg:province":"Arezzo",
    "sg:website":"http://www.hotelforum.net",
    "wof:name":"Hotel Forum",
    "wof:placetype":"venue"
},
  "geometry": {"coordinates":[11.809359,43.264778],"type":"Point"}
}