{
  "type": "Feature",
  "properties": {
    "addr:full":"48, Via Colonia 38030 Daiano Daiano Trento 38030",
    "addr:postcode":"38030;38030",
    "addr:street":"Via Colonia",
    "iso:country":"IT",
    "sg:address":"48, Via Colonia 38030 Daiano",
    "sg:city":"Daiano",
    "sg:classifiers":[
        {
            "category":"Shopping",
            "subcategory":"Clothing, Apparel, & Fashions",
            "type":"Retail Goods"
        }
    ],
    "sg:phone":"+39 0462 342694",
    "sg:postcode":"38030",
    "sg:province":"Trento",
    "sg:tags":[
        "clothes"
    ],
    "wof:name":"Confezioni Zeni Saverio & C. (s.n.c.)",
    "wof:placetype":"venue"
},
  "geometry": {"coordinates":[11.449883,46.303143],"type":"Point"}
}