{
  "type": "Feature",
  "properties": {
    "iso:country":"IT",
    "sg:address":"24128 Bergamo",
    "sg:city":"Bergamo",
    "sg:orig_category":"Scuole E Servizi Scolastici. Servizi Per Lo Sport E Il Tempo Libero",
    "sg:phone":"+39 035 257200",
    "sg:postcode":"24128",
    "sg:province":"Bergamo",
    "wof:name":"Autoscuola Fratelli Calvi Di Russo Evandro & C. Snc",
    "wof:placetype":"venue"
},
  "geometry": {"coordinates":[9.65008,45.693581],"type":"Point"}
}