{
  "type": "Feature",
  "properties": {
    "iso:country":"IT",
    "sg:address":"50013 Campi Bisenzio",
    "sg:city":"Campi Bisenzio",
    "sg:orig_category":"Arredamenti E Mobili Professionali. Apparecchi, Attrezzature E Forniture Per Centri Estetici. Arredi Ed Attrezzature Per Attivita' Commerciali Ed Artigianali",
    "sg:phone":"+39 055 896 5010",
    "sg:postcode":"50013",
    "sg:province":"Firenze",
    "sg:website":"http://www.gigliemeglio.com",
    "wof:name":"Gigli & Meglio Industria Di Arredamenti Spa",
    "wof:placetype":"venue"
},
  "geometry": {"coordinates":[11.127766,43.827488],"type":"Point"}
}