{
  "type": "Feature",
  "properties": {
    "addr:full":"10024 Moncalieri Moncalieri Torino 10024",
    "addr:postcode":"10024;10024",
    "iso:country":"IT",
    "sg:address":"10024 Moncalieri",
    "sg:city":"Moncalieri",
    "sg:orig_category":"Abbigliamento Intimo, Calze E Costumi Da Bagno",
    "sg:phone":"+39 011 643566",
    "sg:postcode":"10024",
    "sg:province":"Torino",
    "wof:name":"D.p. Company S.a.s.",
    "wof:placetype":"venue"
},
  "geometry": {"coordinates":[7.683527,45.000324],"type":"Point"}
}