{
  "type": "Feature",
  "properties": {
    "addr:full":"21012 Cassano Magnago Cassano Magnago Varese 21012",
    "addr:postcode":"21012;21012",
    "iso:country":"IT",
    "sg:address":"21012 Cassano Magnago",
    "sg:city":"Cassano Magnago",
    "sg:classifiers":[
        {
            "category":"Communications",
            "subcategory":"Newspaper",
            "type":"Services"
        }
    ],
    "sg:phone":"+39 0331 792059",
    "sg:postcode":"21012",
    "sg:province":"Varese",
    "sg:tags":[
        "publishing"
    ],
    "wof:name":"Dante Bertoni Srl",
    "wof:placetype":"venue"
},
  "geometry": {"coordinates":[8.8254728317,45.6512184143],"type":"Point"}
}