{
  "type": "Feature",
  "properties": {
    "addr:full":"04010 Cori Cori Latina 04010",
    "addr:postcode":"04010;04010",
    "iso:country":"IT",
    "sg:address":"04010 Cori",
    "sg:city":"Cori",
    "sg:orig_category":"Prodotti Alimentari. Servizi E Lavori Per Industria Alimentare E Bevande",
    "sg:phone":"+39 06 967 9277",
    "sg:postcode":"04010",
    "sg:province":"Latina",
    "wof:name":"Forno F.lli Pistilli",
    "wof:placetype":"venue"
},
  "geometry": {"coordinates":[12.6566562653,41.4794158936],"type":"Point"}
}