{
  "type": "Feature",
  "properties": {
    "addr:full":"24050 Palosco Palosco Bergamo 24050",
    "addr:postcode":"24050;24050",
    "iso:country":"IT",
    "sg:address":"24050 Palosco",
    "sg:city":"Palosco",
    "sg:orig_category":"Forniture Per Uffici",
    "sg:phone":"+39 035 845285",
    "sg:postcode":"24050",
    "sg:province":"Bergamo",
    "wof:name":"I.n.c.a. Snc Di Sormani Silvio & C.",
    "wof:placetype":"venue"
},
  "geometry": {"coordinates":[9.862947464,45.5994796753],"type":"Point"}
}