{
  "type": "Feature",
  "properties": {
    "iso:country":"IT",
    "sg:address":"Piazza Cesare Battisti 9, 00037 Segni, Rm",
    "sg:city":"Segni",
    "sg:classifiers":[
        {
            "category":"Banks & Credit Unions",
            "subcategory":"Bank",
            "type":"Services"
        }
    ],
    "sg:postcode":"00037",
    "sg:province":"Roma",
    "wof:name":"Banca Di Credito Cooperativo Di Segni Scrl",
    "wof:placetype":"venue"
},
  "geometry": {"coordinates":[13.021476,41.691719],"type":"Point"}
}