{
  "type": "Feature",
  "properties": {
    "addr:full":"19/h, V. Notarbartolo 90141 Palermo Palermo Palermo 90141",
    "addr:housenumber":"19 / h",
    "addr:postcode":"90141;90141",
    "addr:street":"V. Notarbartolo",
    "iso:country":"IT",
    "sg:address":"19/h, V. Notarbartolo 90141 Palermo",
    "sg:city":"Palermo",
    "sg:classifiers":[
        {
            "category":"Shopping",
            "subcategory":"Clothing, Apparel, & Fashions",
            "type":"Retail Goods"
        }
    ],
    "sg:postcode":"90141",
    "sg:province":"Palermo",
    "sg:tags":[
        "clothes"
    ],
    "sg:website":"http://www.ferrarieferrari.it",
    "wof:name":"Ferrari Sartoria Italiana",
    "wof:placetype":"venue"
},
  "geometry": {"coordinates":[13.338376,38.130852],"type":"Point"}
}