{
  "type": "Feature",
  "properties": {
    "iso:country":"IT",
    "sg:address":"20125 Milano",
    "sg:city":"Milano",
    "sg:orig_category":"Chiese Ed Associazioni Religiose",
    "sg:phone":"+39 02 668 7136",
    "sg:postcode":"20125",
    "sg:province":"Milano",
    "wof:name":"Parrocchia Di S. Angela Merci",
    "wof:placetype":"venue"
},
  "geometry": {"coordinates":[9.205317,45.494701],"type":"Point"}
}