{
  "type": "Feature",
  "properties": {
    "addr:full":"45, Via Sarno 80040 Striano Striano Napoli 80040",
    "addr:postcode":"80040;80040",
    "addr:street":"Via Sarno",
    "iso:country":"IT",
    "sg:address":"45, Via Sarno 80040 Striano",
    "sg:city":"Striano",
    "sg:classifiers":[
        {
            "category":"Manufacturing",
            "subcategory":"Food",
            "type":"Manufacturing & Wholesale Goods"
        }
    ],
    "sg:phone":"+39 081 827 6302",
    "sg:postcode":"80040",
    "sg:province":"Napoli",
    "sg:tags":[
        "equipment",
        "processing",
        "-",
        "machinery"
    ],
    "wof:name":"Sorvillo Santolo & Figli S.r.l",
    "wof:placetype":"venue"
},
  "geometry": {"coordinates":[14.5821943283,40.8129272461],"type":"Point"}
}