{
  "type": "Feature",
  "properties": {
    "iso:country":"IT",
    "sg:address":"41100 Modena",
    "sg:city":"Modena",
    "sg:orig_category":"Forniture Per Attivita' Industriali",
    "sg:phone":"+39 059 280605",
    "sg:postcode":"41100",
    "sg:province":"Modena",
    "wof:name":"Cri-mo Srl",
    "wof:placetype":"venue"
},
  "geometry": {"coordinates":[10.9691896439,44.6381912231],"type":"Point"}
}