{
  "type": "Feature",
  "properties": {
    "addr:full":"Via G.marconi 2; Castelletto Stura; 12040 Castelletto Stura Cuneo 12040",
    "addr:housenumber":"2",
    "addr:postcode":"12040;12040",
    "addr:street":"Via G.Marconi",
    "iso:country":"IT",
    "sg:address":"Via G.marconi 2; Castelletto Stura; 12040",
    "sg:city":"Castelletto Stura",
    "sg:classifiers":[
        {
            "category":"Banks & Credit Unions",
            "subcategory":"Bank",
            "type":"Services"
        }
    ],
    "sg:phone":"+39 0171 791374",
    "sg:postcode":"12040",
    "sg:province":"Cuneo",
    "wof:name":"Cassa Di Risparmio Di Cuneo",
    "wof:placetype":"venue"
},
  "geometry": {"coordinates":[7.7055897713,44.4211578369],"type":"Point"}
}