{
  "type": "Feature",
  "properties": {
    "iso:country":"IT",
    "sg:address":"41100 Modena",
    "sg:city":"Modena",
    "sg:orig_category":"Macchine, Impianti Ed Attrezzature Per Abbigliamento E Pelletterie",
    "sg:phone":"+39 059 345517",
    "sg:postcode":"41100",
    "sg:province":"Modena",
    "wof:name":"Corbani Roberto",
    "wof:placetype":"venue"
},
  "geometry": {"coordinates":[10.936522,44.552723],"type":"Point"}
}