{
  "type": "Feature",
  "properties": {
    "addr:full":"Via Fontonale 5 37055 Ronco All'adige Verona 37055",
    "addr:housenumber":"5",
    "addr:postcode":"37055;37055",
    "addr:street":"Via Fontonale",
    "iso:country":"IT",
    "sg:address":"Via Fontonale 5 37055 Ronco All'adige",
    "sg:classifiers":[
        {
            "category":"Building & Trades",
            "subcategory":"Plumbing",
            "type":"Services"
        }
    ],
    "sg:phone":"+39 045 828 5111",
    "sg:postcode":"37055",
    "sg:province":"Verona",
    "sg:tags":[
        "pipe",
        "stove",
        "chimney"
    ],
    "sg:website":"www.caminiwierer.com",
    "wof:name":"Camini Wierer Spa",
    "wof:placetype":"venue"
},
  "geometry": {"coordinates":[10.991748,45.438366],"type":"Point"}
}