{
  "type": "Feature",
  "properties": {
    "iso:country":"IT",
    "sg:address":"46100 Mantova",
    "sg:city":"Mantova",
    "sg:orig_category":"Cine-foto-ottica",
    "sg:phone":"+39 0376 221808",
    "sg:postcode":"46100",
    "sg:province":"Mantova",
    "sg:website":"http://www.multimediando.net",
    "wof:name":"Multimediando Srl",
    "wof:placetype":"venue"
},
  "geometry": {"coordinates":[10.790058,45.153008],"type":"Point"}
}