{
  "type": "Feature",
  "properties": {
    "iso:country":"IT",
    "sg:address":"Via Toscana 57/59 20090 Buccinasco",
    "sg:city":"Buccinasco",
    "sg:classifiers":[
        {
            "category":"Government",
            "subcategory":"Post Office",
            "type":"Public Place"
        }
    ],
    "sg:phone":"+39 02 4571 3300",
    "sg:postcode":"20090",
    "sg:province":"Milano",
    "sg:tags":[
        "spare",
        "television",
        "set",
        "radio",
        "part"
    ],
    "sg:website":"www.siel.com",
    "wof:name":"Siel Srl",
    "wof:placetype":"venue"
},
  "geometry": {"coordinates":[9.121889,45.416489],"type":"Point"}
}