{
  "type": "Feature",
  "properties": {
    "addr:full":"37, Via Dell' Industria 31020 San Vendemiano San Vendemiano Treviso 31020",
    "addr:housenumber":"vendemiano",
    "addr:postcode":"31020;vendemiano;31020",
    "addr:street":"Via Dell ' Industria;Treviso",
    "iso:country":"IT",
    "sg:address":"37, Via Dell' Industria 31020 San Vendemiano",
    "sg:city":"San Vendemiano",
    "sg:classifiers":[
        {
            "category":"Shopping",
            "subcategory":"Computers & Home Electronics",
            "type":"Retail Goods"
        }
    ],
    "sg:phone":"+39 0438 470003",
    "sg:postcode":"31020",
    "sg:province":"Treviso",
    "sg:tags":[
        "electronic",
        "electrical",
        "equipment"
    ],
    "wof:name":"Adria - Cab S.r.l.",
    "wof:placetype":"venue"
},
  "geometry": {"coordinates":[12.363326,45.873775],"type":"Point"}
}