{
  "type": "Feature",
  "properties": {
    "iso:country":"IT",
    "sg:address":"20010 Bareggio",
    "sg:city":"Bareggio",
    "sg:orig_category":"Trattamenti Termici E Superficiali Metalli, Galvanotecnica",
    "sg:phone":"+39 02 9036 2309",
    "sg:postcode":"20010",
    "sg:province":"Milano",
    "wof:name":"T.t.b. Trattamenti Termici Bruni Srl",
    "wof:placetype":"venue"
},
  "geometry": {"coordinates":[9.212106,45.559498],"type":"Point"}
}