{
  "type": "Feature",
  "properties": {
    "addr:full":"1, Via Monte D'oro 00040 Pomezia Pomezia Roma 00040",
    "addr:postcode":"00040;roma 00040",
    "addr:street":"Via Monte D'Oro",
    "iso:country":"IT",
    "sg:address":"1, Via Monte D'oro 00040 Pomezia",
    "sg:city":"Pomezia",
    "sg:classifiers":[
        {
            "category":"Utilities",
            "subcategory":"Telephone",
            "type":"Services"
        }
    ],
    "sg:phone":"+39 390 691 1951",
    "sg:postcode":"00040",
    "sg:province":"Roma",
    "sg:tags":[
        "telecommunication"
    ],
    "wof:name":"Mistel Srl",
    "wof:placetype":"venue"
},
  "geometry": {"coordinates":[12.48119,41.677502],"type":"Point"}
}