{
  "type": "Feature",
  "properties": {
    "iso:country":"IT",
    "sg:address":"13, Via Curiel Eugenio 20090 Buccinasco",
    "sg:city":"Buccinasco",
    "sg:classifiers":[
        {
            "category":"Shopping",
            "subcategory":"Gifts & Souvenirs",
            "type":"Retail Goods"
        }
    ],
    "sg:phone":"+39 02 4570 0549",
    "sg:postcode":"20090",
    "sg:province":"Milano",
    "wof:name":"Zanchetti Snc Di Sanchetti Antonio E Sanchetti Anna Paola",
    "wof:placetype":"venue"
},
  "geometry": {"coordinates":[9.160477,45.438816],"type":"Point"}
}