{
  "type": "Feature",
  "properties": {
    "iso:country":"IT",
    "sg:address":"52, Corso Del Rinascimento 00186 Roma",
    "sg:city":"Roma",
    "sg:classifiers":[
        {
            "category":"Professional",
            "subcategory":"Computer Services",
            "type":"Services"
        }
    ],
    "sg:phone":"+39 39066864715",
    "sg:postcode":"00186",
    "sg:province":"Roma",
    "sg:tags":[
        "information",
        "technology"
    ],
    "wof:name":"Fin.sa Consulting S.r.l.",
    "wof:placetype":"venue"
},
  "geometry": {"coordinates":[12.473868,41.899612],"type":"Point"}
}