{
  "type": "Feature",
  "properties": {
    "addr:full":"40069 Zola Predosa Zola Bologna 40069",
    "addr:postcode":"40069;40069",
    "iso:country":"IT",
    "sg:address":"40069 Zola Predosa",
    "sg:city":"Zola",
    "sg:orig_category":"Frigoriferi Industriali E Commerciali - Riparazione",
    "sg:phone":"+39 051 605 6867",
    "sg:postcode":"40069",
    "sg:province":"Bologna",
    "wof:name":"Gel Service Sas",
    "wof:placetype":"venue"
},
  "geometry": {"coordinates":[11.2220983505,44.4908027649],"type":"Point"}
}