{
  "type": "Feature",
  "properties": {
    "iso:country":"IT",
    "sg:address":"16154 Genova",
    "sg:city":"Genova",
    "sg:classifiers":[
        {
            "category":"Health Services",
            "subcategory":"Health Practitioner",
            "type":"Services"
        }
    ],
    "sg:phone":"+39 010 604 2665",
    "sg:postcode":"16154",
    "sg:province":"Genova",
    "sg:tags":[
        "medici"
    ],
    "wof:name":"Beretta Ferdinando",
    "wof:placetype":"venue"
},
  "geometry": {"coordinates":[8.841875,44.411953],"type":"Point"}
}