{
  "type": "Feature",
  "properties": {
    "iso:country":"IT",
    "sg:address":"Km. 3.500, Via Per Grottaglie 72021 Francavilla Fontana",
    "sg:city":"Francavilla Fontana",
    "sg:classifiers":[
        {
            "category":"Manufacturing",
            "subcategory":"Lumber",
            "type":"Manufacturing & Wholesale Goods"
        }
    ],
    "sg:phone":"+39 0831 810755",
    "sg:postcode":"72021",
    "sg:province":"Brindisi",
    "sg:tags":[
        "wood"
    ],
    "wof:name":"Europak Imballaggi S.r.l.",
    "wof:placetype":"venue"
},
  "geometry": {"coordinates":[17.938992,40.636177],"type":"Point"}
}