{
  "type": "Feature",
  "properties": {
    "addr:full":"50, Via Dell' Industria 36040 Grisignano Di Zocco Grisignano di Zocco Vicenza 36040",
    "addr:postcode":"36040;36040",
    "addr:street":"Via Dell ' Industria;Di Zocco Grisignano Di Zocco",
    "iso:country":"IT",
    "sg:address":"50, Via Dell' Industria 36040 Grisignano Di Zocco",
    "sg:city":"Grisignano di Zocco",
    "sg:classifiers":[
        {
            "category":"Professional",
            "subcategory":"Engineering",
            "type":"Services"
        }
    ],
    "sg:phone":"+39 0444 418388",
    "sg:postcode":"36040",
    "sg:province":"Vicenza",
    "sg:tags":[
        "machine",
        "-",
        "mechanical"
    ],
    "wof:name":"E.c.a. Technology Spa",
    "wof:placetype":"venue"
},
  "geometry": {"coordinates":[11.706356,45.483887],"type":"Point"}
}