{
  "type": "Feature",
  "properties": {
    "iso:country":"IT",
    "sg:address":"00063 Campagnano Di Roma",
    "sg:city":"Campagnano di Roma",
    "sg:orig_category":"Automobili E Mezzi Di Trasporto",
    "sg:phone":"+39 06 904 1251",
    "sg:postcode":"00063",
    "sg:province":"Roma",
    "wof:name":"Quasar",
    "wof:placetype":"venue"
},
  "geometry": {"coordinates":[12.377262,42.136356],"type":"Point"}
}