{
  "type": "Feature",
  "properties": {
    "addr:full":"38, V. Italia 22050 Casargo LC",
    "addr:housenumber":"38",
    "addr:postcode":"22050",
    "addr:street":"V. Italia",
    "iso:country":"IT",
    "sg:address":"38, V. Italia 22050 Casargo",
    "sg:classifiers":[
        {
            "category":"Shopping",
            "type":"Retail Goods"
        }
    ],
    "sg:phone":"+39 0341 840441",
    "sg:province":"LC",
    "sg:tags":[
        "finished",
        "-",
        "metallic"
    ],
    "sg:website":"http://www.valexport.com",
    "wof:name":"Valexport Srl Di Fazzini Giovanni",
    "wof:placetype":"venue"
},
  "geometry": {"coordinates":[9.3824825287,46.0329093933],"type":"Point"}
}