{
  "type": "Feature",
  "properties": {
    "iso:country":"IT",
    "sg:address":"10100 Torino",
    "sg:orig_category":"Servizi E Lavori Per Arredamento E Industria Del Legno",
    "sg:phone":"+39 011 387543",
    "sg:province":"TO",
    "wof:name":"Studio Grafico Aldo Varano",
    "wof:placetype":"venue"
},
  "geometry": {"coordinates":[7.744349,45.122169],"type":"Point"}
}