{
  "type": "Feature",
  "properties": {
    "iso:country":"IT",
    "sg:address":"10, V. Kravogl - Zona Produttiva 39020 Parcines",
    "sg:city":"Parcines",
    "sg:classifiers":[
        {
            "category":"Manufacturing",
            "subcategory":"Paper Products",
            "type":"Manufacturing & Wholesale Goods"
        }
    ],
    "sg:phone":"+39 0473 965052",
    "sg:postcode":"39020",
    "sg:province":"Bolzano/Bozen",
    "sg:tags":[
        "cardboard"
    ],
    "sg:website":"http://www.alpiplast.com",
    "wof:name":"Alpiplast Sas",
    "wof:placetype":"venue"
},
  "geometry": {"coordinates":[11.35800457,46.4967155457],"type":"Point"}
}