{
  "type": "Feature",
  "properties": {
    "addr:full":"25082 Botticino Botticino Brescia 25082",
    "addr:postcode":"25082;25082",
    "iso:country":"IT",
    "sg:address":"25082 Botticino",
    "sg:city":"Botticino",
    "sg:orig_category":"Calze E Collants - Vendita Al Dettaglio",
    "sg:phone":"+39 030 269 2138",
    "sg:postcode":"25082",
    "sg:province":"Brescia",
    "wof:name":"Boniotti Luigi",
    "wof:placetype":"venue"
},
  "geometry": {"coordinates":[10.299626,45.545223],"type":"Point"}
}