{
  "type": "Feature",
  "properties": {
    "iso:country":"IT",
    "sg:address":"3/7, Via Lombardia 50054 Fucecchio",
    "sg:city":"Fucecchio",
    "sg:classifiers":[
        {
            "category":"Manufacturing",
            "subcategory":"Textiles",
            "type":"Manufacturing & Wholesale Goods"
        }
    ],
    "sg:phone":"+39 0571 297021",
    "sg:postcode":"50054",
    "sg:province":"Firenze",
    "sg:tags":[
        "leather",
        "raw",
        "material",
        "-"
    ],
    "wof:name":"Conceria Eugenia Srl",
    "wof:placetype":"venue"
},
  "geometry": {"coordinates":[10.780862,43.742611],"type":"Point"}
}