{
  "type": "Feature",
  "properties": {
    "addr:full":"Via Pitagora 15 35030 Rubano Rubano Padova 35030",
    "addr:housenumber":"15",
    "addr:postcode":"35030;35030",
    "addr:street":"Via Pitagora",
    "iso:country":"IT",
    "sg:address":"Via Pitagora 15 35030 Rubano",
    "sg:city":"Rubano",
    "sg:classifiers":[
        {
            "category":"Bus Stop",
            "subcategory":"None",
            "type":"Transportation"
        }
    ],
    "sg:phone":"+39 049 897 6755",
    "sg:postcode":"35030",
    "sg:province":"Padova",
    "sg:tags":[
        "cardiac",
        "valve",
        "artificial"
    ],
    "wof:name":"Medico Spa",
    "wof:placetype":"venue"
},
  "geometry": {"coordinates":[11.835418,45.418945],"type":"Point"}
}