{
  "type": "Feature",
  "properties": {
    "iso:country":"IT",
    "sg:address":"Viale Europa 24023 Clusone",
    "sg:city":"Clusone",
    "sg:classifiers":[
        {
            "category":"Food & Beverages",
            "subcategory":"Groceries & Convenience Stores",
            "type":"Retail Goods"
        }
    ],
    "sg:phone":"+39 39034622591",
    "sg:postcode":"24023",
    "sg:province":"Bergamo",
    "sg:tags":[
        "drink"
    ],
    "wof:name":"Fonti Pineta",
    "wof:placetype":"venue"
},
  "geometry": {"coordinates":[10.00166,45.889442],"type":"Point"}
}