{
  "type": "Feature",
  "properties": {
    "iso:country":"IT",
    "sg:address":"16152 Genova",
    "sg:city":"Genova",
    "sg:orig_category":"Macchine Utensili E Impianti",
    "sg:phone":"+39 010 651 3632",
    "sg:postcode":"16152",
    "sg:province":"Genova",
    "wof:name":"S.i.f.i. S.p.a.",
    "wof:placetype":"venue"
},
  "geometry": {"coordinates":[8.876893,44.415562],"type":"Point"}
}