{
  "type": "Feature",
  "properties": {
    "addr:full":"Via Bogino Conte; Torino; 10123 Torino Torino 10123",
    "addr:postcode":"10123;10123",
    "addr:street":"Via Bogino",
    "iso:country":"IT",
    "sg:address":"Via Bogino Conte; Torino; 10123",
    "sg:city":"Torino",
    "sg:classifiers":[
        {
            "category":"Banks & Credit Unions",
            "subcategory":"Bank",
            "type":"Services"
        }
    ],
    "sg:phone":"+39 011 55981",
    "sg:postcode":"10123",
    "sg:province":"Torino",
    "wof:name":"Banca Nazionale Dell' Agricoltura",
    "wof:placetype":"venue"
},
  "geometry": {"coordinates":[7.686985,45.067638],"type":"Point"}
}