{
  "type": "Feature",
  "properties": {
    "iso:country":"IT",
    "sg:address":"16121 Genova",
    "sg:city":"Genova",
    "sg:orig_category":"Pubblica Amministrazione",
    "sg:phone":"+39 010 530871",
    "sg:postcode":"16121",
    "sg:province":"Genova",
    "wof:name":"Provincia Di Genova",
    "wof:placetype":"venue"
},
  "geometry": {"coordinates":[8.941822052,44.4025611877],"type":"Point"}
}