{
  "type": "Feature",
  "properties": {
    "addr:full":"64, Via B. Cellini 50028 Tavarnelle Val Di Pesa Tavarnelle Val di Pesa Firenze 50028",
    "addr:postcode":"50028;50028",
    "addr:street":"Via B. Cellini;Val Di Pesa",
    "iso:country":"IT",
    "sg:address":"64, Via B. Cellini 50028 Tavarnelle Val Di Pesa",
    "sg:city":"Tavarnelle Val di Pesa",
    "sg:classifiers":[
        {
            "category":"Food & Beverages",
            "subcategory":"Groceries & Convenience Stores",
            "type":"Retail Goods"
        }
    ],
    "sg:phone":"+39 055 807 1461",
    "sg:postcode":"50028",
    "sg:province":"Firenze",
    "sg:tags":[
        "product",
        "related"
    ],
    "wof:name":"Foodco S.r.l.",
    "wof:placetype":"venue"
},
  "geometry": {"coordinates":[11.256901741,43.7687339783],"type":"Point"}
}