{
  "type": "Feature",
  "properties": {
    "addr:full":"46040 Monzambano Monzambano Mantova 46040",
    "addr:postcode":"46040;46040",
    "iso:country":"IT",
    "sg:address":"46040 Monzambano",
    "sg:city":"Monzambano",
    "sg:orig_category":"Apparecchiature Ed Attrezzature Meccaniche",
    "sg:phone":"+39 0376 800200",
    "sg:postcode":"46040",
    "sg:province":"Mantova",
    "sg:website":"http://www.hbs.it",
    "wof:name":"H.b.s. Oleoidraulica Srl",
    "wof:placetype":"venue"
},
  "geometry": {"coordinates":[10.690206,45.394039],"type":"Point"}
}