{
  "type": "Feature",
  "properties": {
    "iso:country":"IT",
    "sg:address":"20149 Milano",
    "sg:city":"Milano",
    "sg:orig_category":"Banche E Servizi Finanziari",
    "sg:postcode":"20149",
    "sg:province":"Milano",
    "wof:name":"Capital Money Milano Due Sas Di Civitenga M. & C.",
    "wof:placetype":"venue"
},
  "geometry": {"coordinates":[9.154373,45.467571],"type":"Point"}
}