{
  "type": "Feature",
  "properties": {
    "addr:full":"55042 Forte Dei Marmi Forte dei Marmi Lucca 55042",
    "addr:postcode":"55042;55042",
    "iso:country":"IT",
    "sg:address":"55042 Forte Dei Marmi",
    "sg:city":"Forte dei Marmi",
    "sg:orig_category":"Forniture Alberghi, Bar, Ristoranti E Comunita'",
    "sg:phone":"+39 0584 89895",
    "sg:postcode":"55042",
    "sg:province":"Lucca",
    "wof:name":"Nardini Forniture",
    "wof:placetype":"venue"
},
  "geometry": {"coordinates":[10.1759281158,43.9594306946],"type":"Point"}
}