{
  "type": "Feature",
  "properties": {
    "addr:full":"86, Via Di Monte Brianzo 00186 Roma Roma Roma 00186",
    "addr:postcode":"00186;00186",
    "addr:street":"Via Di Monte Brianzo",
    "iso:country":"IT",
    "sg:address":"86, Via Di Monte Brianzo 00186 Roma",
    "sg:city":"Roma",
    "sg:classifiers":[
        {
            "category":"Manufacturing",
            "subcategory":"Printing",
            "type":"Manufacturing & Wholesale Goods"
        }
    ],
    "sg:phone":"+39 39066869269",
    "sg:postcode":"00186",
    "sg:province":"Roma",
    "sg:tags":[
        "publishing"
    ],
    "wof:name":"Leuto (s.r.l.)",
    "wof:placetype":"venue"
},
  "geometry": {"coordinates":[12.4726657867,41.9022064209],"type":"Point"}
}