{
  "type": "Feature",
  "properties": {
    "addr:full":"06073 Corciano Corciano Perugia 06073",
    "addr:postcode":"06073;06073",
    "iso:country":"IT",
    "sg:address":"06073 Corciano",
    "sg:city":"Corciano",
    "sg:orig_category":"Arredamento Negozi E Supermercati",
    "sg:phone":"+39 075 697 8303",
    "sg:postcode":"06073",
    "sg:province":"Perugia",
    "wof:name":"Ciellepi Srl",
    "wof:placetype":"venue"
},
  "geometry": {"coordinates":[12.28627,43.128433],"type":"Point"}
}