{
  "type": "Feature",
  "properties": {
    "iso:country":"IT",
    "sg:address":"50053 Empoli",
    "sg:city":"Empoli",
    "sg:orig_category":"Servizi E Lavori Per Agricoltura E Zootecnia. Imprese Di Costruzioni Civili Ed Industriali",
    "sg:phone":"+39 0571 823330",
    "sg:postcode":"50053",
    "sg:province":"Firenze",
    "wof:name":"Bocini Luca",
    "wof:placetype":"venue"
},
  "geometry": {"coordinates":[11.251961,43.767036],"type":"Point"}
}