{
  "type": "Feature",
  "properties": {
    "iso:country":"IT",
    "sg:address":"10070 San Carlo Canavese",
    "sg:city":"San Carlo Canavese",
    "sg:orig_category":"Lavorazioni Metalli, Stampaggio E Saldatura",
    "sg:phone":"+39 011 921 6777",
    "sg:postcode":"10070",
    "sg:province":"Torino",
    "wof:name":"San Grato Spa",
    "wof:placetype":"venue"
},
  "geometry": {"coordinates":[7.604003,45.226715],"type":"Point"}
}