{
  "type": "Feature",
  "properties": {
    "iso:country":"IT",
    "sg:address":"09045 Quartu Sant'elena",
    "sg:orig_category":"Minuterie Metalliche E Ferramenta",
    "sg:phone":"+39 070 815236",
    "sg:postcode":"09045",
    "sg:province":"Cagliari",
    "wof:name":"Flange Industriali E Derivati Srl",
    "wof:placetype":"venue"
},
  "geometry": {"coordinates":[9.1888074875,39.2440948486],"type":"Point"}
}