{
  "type": "Feature",
  "properties": {
    "iso:country":"IT",
    "sg:address":"23811 Ballabio",
    "sg:city":"Ballabio",
    "sg:orig_category":"Giocattoli E Giochi - Produzione E Ingrosso",
    "sg:phone":"+39 0341 530870",
    "sg:postcode":"23811",
    "sg:province":"Lecco",
    "sg:website":"http://www.gitre.it",
    "wof:name":"Gitr\u00c8 Srl",
    "wof:placetype":"venue"
},
  "geometry": {"coordinates":[9.424522,45.899239],"type":"Point"}
}