{
  "type": "Feature",
  "properties": {
    "iso:country":"IT",
    "sg:address":"00131 Roma",
    "sg:city":"Roma",
    "sg:orig_category":"Servizi E Lavori Per Industria Alimentare E Bevande. Servizi E Lavori Per Abbigliamento E Pelletterie. Servizi E Lavori Per Arredamento E Industria Del Legno. Servizi Vari Di Interesse Pubblico",
    "sg:phone":"+39 06 413 1559",
    "sg:postcode":"00131",
    "sg:province":"Roma",
    "wof:name":"Euro Max Snc Di Farina Massimiliano & C.",
    "wof:placetype":"venue"
},
  "geometry": {"coordinates":[12.643586,41.93029],"type":"Point"}
}