{
  "type": "Feature",
  "properties": {
    "iso:country":"IT",
    "sg:address":"35137 Padova",
    "sg:city":"Padova",
    "sg:orig_category":"Trasporti E Spedizioni Merci",
    "sg:phone":"+39 049 875 0601",
    "sg:postcode":"35137",
    "sg:province":"Padova",
    "wof:name":"La Patavina Srl",
    "wof:placetype":"venue"
},
  "geometry": {"coordinates":[11.863667,45.337643],"type":"Point"}
}