{
  "type": "Feature",
  "properties": {
    "iso:country":"IT",
    "sg:address":"37030 Badia Calavena",
    "sg:city":"Badia Calavena",
    "sg:orig_category":"Lavorazioni Metalli, Stampaggio E Saldatura",
    "sg:phone":"+39 045 651 0015",
    "sg:postcode":"37030",
    "sg:province":"Verona",
    "wof:name":"Penta Servizi Srl",
    "wof:placetype":"venue"
},
  "geometry": {"coordinates":[11.152077,45.563488],"type":"Point"}
}