{
  "type": "Feature",
  "properties": {
    "iso:country":"IT",
    "sg:address":"Via Ginestrino 13 20093 Cologno Monzese",
    "sg:city":"Cologno Monzese",
    "sg:classifiers":[
        {
            "category":"Autos & Motor Vehicles",
            "subcategory":"Automobile Sales",
            "type":"Retail Goods"
        }
    ],
    "sg:phone":"+39 02 2730 2750",
    "sg:postcode":"20093",
    "sg:province":"Milano",
    "sg:tags":[
        "machine",
        "microelectronics",
        "special"
    ],
    "sg:website":"www.etneo.com",
    "wof:name":"Etneo Italia S.r.l.",
    "wof:placetype":"venue"
},
  "geometry": {"coordinates":[9.289901,45.530674],"type":"Point"}
}