{
  "type": "Feature",
  "properties": {
    "iso:country":"IT",
    "sg:address":"28, Via Sauro Nazario 30030 Martellago",
    "sg:city":"Martellago",
    "sg:classifiers":[
        {
            "category":"Manufacturing",
            "subcategory":"Metals",
            "type":"Manufacturing & Wholesale Goods"
        }
    ],
    "sg:phone":"+39 39041908236",
    "sg:postcode":"30030",
    "sg:province":"Venezia",
    "sg:tags":[
        "metallurgy",
        "metalworking"
    ],
    "wof:name":"Costruzioni Bison (s.n.c.)",
    "wof:placetype":"venue"
},
  "geometry": {"coordinates":[12.1879997253,45.5127639771],"type":"Point"}
}