{
  "type": "Feature",
  "properties": {
    "addr:full":"1, Localita' Massolina 50060 Pelago Pelago Firenze 50060",
    "addr:postcode":"50060;50060",
    "addr:street":"Localita ' Massolina",
    "iso:country":"IT",
    "sg:address":"1, Localita' Massolina 50060 Pelago",
    "sg:city":"Pelago",
    "sg:classifiers":[
        {
            "category":"Professional",
            "subcategory":"Engineering",
            "type":"Services"
        }
    ],
    "sg:phone":"+39 055 831 1548",
    "sg:postcode":"50060",
    "sg:province":"Firenze",
    "sg:tags":[
        "machine",
        "-",
        "mechanical"
    ],
    "wof:name":"Nuova Cb Srl",
    "wof:placetype":"venue"
},
  "geometry": {"coordinates":[11.497551,43.732143],"type":"Point"}
}