{
  "type": "Feature",
  "properties": {
    "iso:country":"IT",
    "sg:address":"28015 Alzate",
    "sg:orig_category":"Prodotti Alimentari. Agricoltura, Orticoltura E Floricoltura",
    "sg:phone":"+39 0321 925916",
    "sg:postcode":"28015",
    "sg:province":"Novara",
    "wof:name":"Molino Riseria Bovio S.a.s.",
    "wof:placetype":"venue"
},
  "geometry": {"coordinates":[8.5830631256,45.5590896606],"type":"Point"}
}