{
  "type": "Feature",
  "properties": {
    "iso:country":"IT",
    "sg:address":"26029 Soncino",
    "sg:city":"Soncino",
    "sg:orig_category":"Studi E Consulenze Legali E Notarili. Avvocati, Notai E Servizi Legali. Professionisti - Studi E Servizi Ed Associazioni Di Interesse Aziendale",
    "sg:phone":"+39 0374 837020",
    "sg:postcode":"26029",
    "sg:province":"Cremona",
    "wof:name":"Cristaldi Avv. Giuseppe",
    "wof:placetype":"venue"
},
  "geometry": {"coordinates":[10.023313,45.182175],"type":"Point"}
}