{
  "type": "Feature",
  "properties": {
    "iso:country":"IT",
    "sg:address":"59100 Prato",
    "sg:city":"Prato",
    "sg:orig_category":"Servizi E Lavori Per Abbigliamento E Pelletterie",
    "sg:phone":"+39 0574 37741",
    "sg:postcode":"59100",
    "sg:province":"Prato",
    "wof:name":"Rifinizione Tessuti Vannucchi Corrado Spa",
    "wof:placetype":"venue"
},
  "geometry": {"coordinates":[11.115698,43.909958],"type":"Point"}
}