{
  "type": "Feature",
  "properties": {
    "iso:country":"IT",
    "sg:address":"00192 Roma",
    "sg:city":"Roma",
    "sg:orig_category":"Agenzie Viaggi E Turismo",
    "sg:phone":"+39 06 3975 0943",
    "sg:postcode":"00192",
    "sg:province":"Roma",
    "wof:name":"Abaroma",
    "wof:placetype":"venue"
},
  "geometry": {"coordinates":[12.458914,41.90876],"type":"Point"}
}