{
  "type": "Feature",
  "properties": {
    "iso:country":"IT",
    "sg:address":"95131 Catania",
    "sg:city":"Catania",
    "sg:orig_category":"Studi E Consulenze Tecniche E Industriali. Servizi E Lavori Per Edilizia E Lavori Pubblici. Professionisti - Studi E Servizi Ed Associazioni Di Interesse Aziendale",
    "sg:phone":"+39 095 746 2083",
    "sg:postcode":"95131",
    "sg:province":"Catania",
    "wof:name":"Studio P & P Ing. Vito Palmeri & Ing. Alfio Parisi Associati",
    "wof:placetype":"venue"
},
  "geometry": {"coordinates":[15.093981,37.507336],"type":"Point"}
}