{
  "type": "Feature",
  "properties": {
    "iso:country":"IT",
    "sg:address":"21013 Gallarate",
    "sg:city":"Gallarate",
    "sg:orig_category":"Non-classified Establishments",
    "sg:phone":"+39 0331 795493",
    "sg:postcode":"21013",
    "sg:province":"Varese",
    "wof:name":"Clerici Angelo",
    "wof:placetype":"venue"
},
  "geometry": {"coordinates":[8.78849,45.653267],"type":"Point"}
}