{
  "type": "Feature",
  "properties": {
    "iso:country":"IT",
    "sg:address":"20068 Peschiera Borromeo",
    "sg:city":"Peschiera Borromeo",
    "sg:orig_category":"Materiali Semilavorati Metallici",
    "sg:phone":"+39 02 547 0145",
    "sg:postcode":"20068",
    "sg:province":"Milano",
    "wof:name":"F.lli Vigevano (s.r.l.)",
    "wof:placetype":"venue"
},
  "geometry": {"coordinates":[9.28621,45.427155],"type":"Point"}
}