{
  "type": "Feature",
  "properties": {
    "addr:full":"17100 Savona Savona Savona 17100",
    "addr:postcode":"17100;17100",
    "iso:country":"IT",
    "sg:address":"17100 Savona",
    "sg:city":"Savona",
    "sg:orig_category":"Mobili Metallici",
    "sg:phone":"+39 019 812932",
    "sg:postcode":"17100",
    "sg:province":"Savona",
    "wof:name":"Mutti Valter",
    "wof:placetype":"venue"
},
  "geometry": {"coordinates":[8.3352766037,44.3345451355],"type":"Point"}
}