{
  "type": "Feature",
  "properties": {
    "addr:full":"63033 Monte Prandone Centobuchi Ascoli Piceno 63033",
    "addr:housenumber":"63033",
    "addr:postcode":"63033",
    "addr:street":"Monte Prandone Centobuchi",
    "iso:country":"IT",
    "sg:address":"63033 Monte Prandone",
    "sg:city":"Centobuchi",
    "sg:orig_category":"Forniture Per Abbigliamento E Pelletterie",
    "sg:phone":"+39 0735 701404",
    "sg:postcode":"63033",
    "sg:province":"Ascoli Piceno",
    "wof:name":"Sister's Di Vagnoni Mariella & C. Sas",
    "wof:placetype":"venue"
},
  "geometry": {"coordinates":[13.8531484604,42.8989257812],"type":"Point"}
}