{
  "type": "Feature",
  "properties": {
    "iso:country":"IT",
    "sg:address":"30020 Quarto D'altino",
    "sg:orig_category":"Elettrotecnica Professionale E Di Consumo",
    "sg:phone":"+39 0422 823555",
    "sg:postcode":"30020",
    "sg:province":"Venezia",
    "wof:name":"Primavera Di Battaggia Luca E Miatto Maurizio S.n.c.",
    "wof:placetype":"venue"
},
  "geometry": {"coordinates":[12.350571,45.562325],"type":"Point"}
}