{
  "type": "Feature",
  "properties": {
    "addr:full":"23, Via Crespi 24027 Nembro Nembro Bergamo 24027",
    "addr:postcode":"24027;24027",
    "addr:street":"Via Crespi",
    "iso:country":"IT",
    "sg:address":"23, Via Crespi 24027 Nembro",
    "sg:city":"Nembro",
    "sg:classifiers":[
        {
            "category":"Professional",
            "subcategory":"Business Services",
            "type":"Services"
        }
    ],
    "sg:phone":"+39 39035520505",
    "sg:postcode":"24027",
    "sg:province":"Bergamo",
    "sg:tags":[
        "advice"
    ],
    "wof:name":"Impresa Bergamelli Martino & Mario (s.r.l.)",
    "wof:placetype":"venue"
},
  "geometry": {"coordinates":[9.773213,45.748138],"type":"Point"}
}