{
  "type": "Feature",
  "properties": {
    "addr:full":"Piazza Fonte Diana 19; Comiso; 97013 Comiso Ragusa 97013",
    "addr:housenumber":"19",
    "addr:postcode":"97013;97013",
    "addr:street":"Piazza Fonte Diana",
    "iso:country":"IT",
    "sg:address":"Piazza Fonte Diana 19; Comiso; 97013",
    "sg:city":"Comiso",
    "sg:classifiers":[
        {
            "category":"Banks & Credit Unions",
            "subcategory":"Bank",
            "type":"Services"
        }
    ],
    "sg:phone":"+39 0923 961622",
    "sg:postcode":"97013",
    "sg:province":"Ragusa",
    "wof:name":"Banco Di Sicilia Spa",
    "wof:placetype":"venue"
},
  "geometry": {"coordinates":[14.605038,36.946167],"type":"Point"}
}