{
  "type": "Feature",
  "properties": {
    "iso:country":"IT",
    "sg:address":"240, Viale Epipoli 96100 Siracusa",
    "sg:city":"Siracusa",
    "sg:classifiers":[
        {
            "category":"Wholesale",
            "subcategory":"Drugs",
            "type":"Manufacturing & Wholesale Goods"
        }
    ],
    "sg:phone":"+39 0931 740573",
    "sg:postcode":"96100",
    "sg:province":"Siracusa",
    "sg:tags":[
        "chemical",
        "pharmaceutical"
    ],
    "wof:name":"B. & C. Commercial Union (s.r.l.)",
    "wof:placetype":"venue"
},
  "geometry": {"coordinates":[15.246458,37.084785],"type":"Point"}
}