{
  "type": "Feature",
  "properties": {
    "iso:country":"IT",
    "sg:address":"25045 Castegnato",
    "sg:city":"Castegnato",
    "sg:orig_category":"Trattamenti Termici E Superficiali Metalli, Galvanotecnica",
    "sg:phone":"+39 030 214 8045",
    "sg:postcode":"25045",
    "sg:province":"Brescia",
    "sg:website":"http://www.intra-tt.it",
    "wof:name":"Intra Srl",
    "wof:placetype":"venue"
},
  "geometry": {"coordinates":[10.094222,45.558613],"type":"Point"}
}