{
  "type": "Feature",
  "properties": {
    "iso:country":"IT",
    "sg:address":"Corso Venezia 37 20121 Milano",
    "sg:city":"Milano",
    "sg:orig_category":"Ladies' Trousers Suits, Suits, Jackets, Skirts, And Trousers",
    "sg:phone":"+39 02 782727",
    "sg:postcode":"20121",
    "sg:province":"Milano",
    "wof:name":"Oggi Italia Studio Moda S.r.l.",
    "wof:placetype":"venue"
},
  "geometry": {"coordinates":[9.200456,45.47007],"type":"Point"}
}