{
  "type": "Feature",
  "properties": {
    "iso:country":"IT",
    "sg:address":"Via San Giuliano 39a 15040 Castelceriolo",
    "sg:orig_category":"Wearing Parts For Motor Vehicles",
    "sg:phone":"+39 0131 216505",
    "sg:postcode":"15040",
    "sg:province":"Alessandria",
    "sg:website":"www.gieffesrl.it",
    "wof:name":"Gieffe S.r.l.",
    "wof:placetype":"venue"
},
  "geometry": {"coordinates":[8.69386,44.915825],"type":"Point"}
}