{
  "type": "Feature",
  "properties": {
    "iso:country":"IT",
    "sg:address":"13028 Scopello",
    "sg:city":"Scopello",
    "sg:orig_category":"Servizi Per Lo Sport E Il Tempo Libero. Servizi Al Turismo",
    "sg:phone":"+39 0163 78004",
    "sg:postcode":"13028",
    "sg:province":"Vercelli",
    "wof:name":"Seggiovia Mera (s.p.a.)",
    "wof:placetype":"venue"
},
  "geometry": {"coordinates":[8.100668,45.764416],"type":"Point"}
}