{
  "type": "Feature",
  "properties": {
    "addr:full":"83 Via Rizzo Luigi, 06128 Perugia Perugia Perugia 06128",
    "addr:postcode":"06128;06128",
    "addr:street":"Via Rizzo Luigi",
    "iso:country":"IT",
    "sg:address":"83 Via Rizzo Luigi, 06128 Perugia",
    "sg:city":"Perugia",
    "sg:classifiers":[
        {
            "category":"Banks & Credit Unions",
            "subcategory":"Financial Services",
            "type":"Services"
        }
    ],
    "sg:phone":"+39 075 501 0649",
    "sg:postcode":"06128",
    "sg:province":"Perugia",
    "sg:tags":[
        "banking",
        "finance",
        "insurance"
    ],
    "wof:name":"Studio Leasing (sas)",
    "wof:placetype":"venue"
},
  "geometry": {"coordinates":[12.3891716003,43.1107025146],"type":"Point"}
}