{
  "type": "Feature",
  "properties": {
    "addr:full":"98, V. Lago Di Pergusa 74100 Taranto Taranto Taranto 74100",
    "addr:housenumber":"98",
    "addr:postcode":"74100;74100",
    "addr:street":"V. Lago Di Pergusa",
    "iso:country":"IT",
    "sg:address":"98, V. Lago Di Pergusa 74100 Taranto",
    "sg:city":"Taranto",
    "sg:classifiers":[
        {
            "category":"Manufacturing",
            "subcategory":"Motor Vehicles & Parts",
            "type":"Manufacturing & Wholesale Goods"
        }
    ],
    "sg:phone":"+39 099 772 9102",
    "sg:postcode":"74100",
    "sg:province":"Taranto",
    "sg:tags":[
        "engine"
    ],
    "sg:website":"http://www.paginegialle.it/sogecota",
    "wof:name":"So.ge.co. Srl",
    "wof:placetype":"venue"
},
  "geometry": {"coordinates":[17.263357,40.434296],"type":"Point"}
}