{
  "type": "Feature",
  "properties": {
    "addr:full":"4, Via Dell' Arboreto 51100 Pistoia Pistoia Pistoia 51100",
    "addr:postcode":"51100;51100",
    "addr:street":"Via Dell ' Arboreto",
    "iso:country":"IT",
    "sg:address":"4, Via Dell' Arboreto 51100 Pistoia",
    "sg:city":"Pistoia",
    "sg:classifiers":[
        {
            "category":"Professional",
            "subcategory":"Engineering",
            "type":"Services"
        }
    ],
    "sg:phone":"+39 0573 402654",
    "sg:postcode":"51100",
    "sg:province":"Pistoia",
    "sg:tags":[
        "machine",
        "-",
        "mechanical"
    ],
    "wof:name":"Erdi Bardini Arrigo Di Bardini Marco",
    "wof:placetype":"venue"
},
  "geometry": {"coordinates":[10.918524,43.932156],"type":"Point"}
}