{
  "type": "Feature",
  "properties": {
    "iso:country":"IT",
    "sg:address":"37136 Verona",
    "sg:city":"Verona",
    "sg:orig_category":"Impianti, Attrezzature E Forniture Sanitarie Ed Ospedaliere",
    "sg:phone":"+39 045 502998",
    "sg:postcode":"37136",
    "sg:province":"Verona",
    "wof:name":"Sopel S.r.l.",
    "wof:placetype":"venue"
},
  "geometry": {"coordinates":[10.964271,45.409363],"type":"Point"}
}