{
  "type": "Feature",
  "properties": {
    "addr:full":"66054 Vasto Vasto Chieti 66054",
    "addr:postcode":"66054;66054",
    "iso:country":"IT",
    "sg:address":"66054 Vasto",
    "sg:city":"Vasto",
    "sg:orig_category":"Frigotecnica, Apparecchiature E Servizi",
    "sg:phone":"+39 0873 311007",
    "sg:postcode":"66054",
    "sg:province":"Chieti",
    "wof:name":"Delta Serv Snc",
    "wof:placetype":"venue"
},
  "geometry": {"coordinates":[14.6937675476,42.1188697815],"type":"Point"}
}