{
  "type": "Feature",
  "properties": {
    "iso:country":"IT",
    "sg:address":"20010 Inveruno",
    "sg:city":"Inveruno",
    "sg:orig_category":"Tessuti E Stoffe. Filati E Materie Prime Tessili",
    "sg:phone":"+39 02 978 8951",
    "sg:postcode":"20010",
    "sg:province":"Milano",
    "wof:name":"Cotonificio Carlo Bonomi Spa",
    "wof:placetype":"venue"
},
  "geometry": {"coordinates":[8.884944,45.545815],"type":"Point"}
}