{
  "type": "Feature",
  "properties": {
    "addr:full":"Via Bellini 2 40067 Rastignano Rastignano Bologna 40067",
    "addr:housenumber":"2",
    "addr:postcode":"40067;rastignano bologna 40067",
    "addr:street":"Via Bellini",
    "iso:country":"IT",
    "sg:address":"Via Bellini 2 40067 Rastignano",
    "sg:city":"Rastignano",
    "sg:classifiers":[
        {
            "category":"Shopping",
            "subcategory":"Clothing, Apparel, & Fashions",
            "type":"Retail Goods"
        }
    ],
    "sg:phone":"+39 051 620 5111",
    "sg:postcode":"40067",
    "sg:province":"Bologna",
    "sg:tags":[
        "blouse",
        "ladies'",
        "dress"
    ],
    "sg:website":"www.wings.it",
    "wof:name":"Wings Spa",
    "wof:placetype":"venue"
},
  "geometry": {"coordinates":[11.370265,44.462685],"type":"Point"}
}