{
  "type": "Feature",
  "properties": {
    "addr:full":"19020 Bolano Bolano La Spezia 19020",
    "addr:postcode":"19020;19020",
    "iso:country":"IT",
    "sg:address":"19020 Bolano",
    "sg:city":"Bolano",
    "sg:orig_category":"Armadi Guardaroba",
    "sg:phone":"+39 0187 933498",
    "sg:postcode":"19020",
    "sg:province":"La Spezia",
    "sg:website":"http://www.chiappinimobili.com",
    "wof:name":"Chiappini Mobili Srl",
    "wof:placetype":"venue"
},
  "geometry": {"coordinates":[9.902441,44.117611],"type":"Point"}
}