{
  "type": "Feature",
  "properties": {
    "iso:country":"IT",
    "sg:address":"Via Dell' Elettronica 36016 Thiene",
    "sg:city":"Thiene",
    "sg:classifiers":[
        {
            "category":"Wholesale",
            "subcategory":"Drugs",
            "type":"Manufacturing & Wholesale Goods"
        }
    ],
    "sg:phone":"+39 0445 362311",
    "sg:postcode":"36016",
    "sg:province":"Vicenza",
    "sg:tags":[
        "chemical",
        "pharmaceutical"
    ],
    "wof:name":"Larps Srl",
    "wof:placetype":"venue"
},
  "geometry": {"coordinates":[11.468003,45.681145],"type":"Point"}
}