{
  "type": "Feature",
  "properties": {
    "iso:country":"IT",
    "sg:address":"51018 Pieve A Nievole",
    "sg:city":"Pieve a Nievole",
    "sg:classifiers":[
        {
            "category":"Retail",
            "subcategory":"Storage",
            "type":"Services"
        }
    ],
    "sg:phone":"+39 0572 81034",
    "sg:postcode":"51018",
    "sg:province":"Pistoia",
    "sg:tags":[
        "packaging",
        "article",
        "packing"
    ],
    "sg:website":"http://www.niccoligroup.it",
    "wof:name":"Scatolificio Niccoli",
    "wof:placetype":"venue"
},
  "geometry": {"coordinates":[10.7838516235,43.8697471619],"type":"Point"}
}