{
  "type": "Feature",
  "properties": {
    "addr:full":"80124 Napoli Napoli Napoli 80124",
    "addr:housenumber":"80124",
    "addr:postcode":"80124",
    "iso:country":"IT",
    "sg:address":"80124 Napoli",
    "sg:city":"Napoli",
    "sg:orig_category":"Resistenze Elettriche Corazzate",
    "sg:phone":"+39 081 762 4164",
    "sg:postcode":"80124",
    "sg:province":"Napoli",
    "wof:name":"So.ge.pro. Srl",
    "wof:placetype":"venue"
},
  "geometry": {"coordinates":[14.274373,40.939301],"type":"Point"}
}