{
  "type": "Feature",
  "properties": {
    "iso:country":"IT",
    "sg:address":"37126 Verona",
    "sg:city":"Verona",
    "sg:classifiers":[
        {
            "category":"Health Services",
            "subcategory":"Health Practitioner",
            "type":"Services"
        }
    ],
    "sg:phone":"+39 045 830 2592",
    "sg:postcode":"37126",
    "sg:province":"Verona",
    "sg:tags":[
        "medici"
    ],
    "wof:name":"Scanagatta Alberto",
    "wof:placetype":"venue"
},
  "geometry": {"coordinates":[10.9883165359,45.4477729797],"type":"Point"}
}