{
  "type": "Feature",
  "properties": {
    "addr:full":"Via Del Mercato 6; Donoratico; 57024",
    "addr:housenumber":"6",
    "addr:postcode":"57024",
    "addr:street":"Via Del Mercato",
    "iso:country":"IT",
    "sg:address":"Via Del Mercato 6; Donoratico; 57024",
    "sg:classifiers":[
        {
            "category":"Banks & Credit Unions",
            "subcategory":"Bank",
            "type":"Services"
        }
    ],
    "sg:phone":"+39 0565 775020",
    "wof:name":"Banca Toscana Spa",
    "wof:placetype":"venue"
},
  "geometry": {"coordinates":[10.563925,43.163635],"type":"Point"}
}