{
  "type": "Feature",
  "properties": {
    "iso:country":"IT",
    "sg:address":"31010 Cimadolmo",
    "sg:city":"Cimadolmo",
    "sg:classifiers":[
        {
            "category":"Arts & Performance",
            "subcategory":"Dance",
            "type":"Entertainment"
        }
    ],
    "sg:phone":"+39 0422 803288",
    "sg:postcode":"31010",
    "sg:province":"Treviso",
    "sg:tags":[
        "decorative",
        "craft",
        "objects",
        "furnishings",
        "artistic"
    ],
    "sg:website":"http://www.farframes.com",
    "wof:name":"Far Srl",
    "wof:placetype":"venue"
},
  "geometry": {"coordinates":[12.3629817963,45.7929763794],"type":"Point"}
}