{
  "type": "Feature",
  "properties": {
    "iso:country":"IT",
    "sg:address":"56, Via Nazionale 16039 Sestri Levante",
    "sg:city":"Sestri Levante",
    "sg:classifiers":[
        {
            "category":"Manufacturing",
            "subcategory":"Rubber & Plastics",
            "type":"Manufacturing & Wholesale Goods"
        }
    ],
    "sg:phone":"+39 0185 487370",
    "sg:postcode":"16039",
    "sg:province":"Genova",
    "wof:name":"Casalbergo Forniture S.a.s.",
    "wof:placetype":"venue"
},
  "geometry": {"coordinates":[9.408955574,44.2724838257],"type":"Point"}
}