{
  "type": "Feature",
  "properties": {
    "iso:country":"IT",
    "sg:address":"Piazza A Gramsci 18; Empoli",
    "sg:classifiers":[
        {
            "category":"Banks & Credit Unions",
            "subcategory":"Bank",
            "type":"Services"
        }
    ],
    "sg:phone":"+39 0571 79573",
    "wof:name":"Banca Di Roma",
    "wof:placetype":"venue"
},
  "geometry": {"coordinates":[10.950251,43.721657],"type":"Point"}
}