{
  "type": "Feature",
  "properties": {
    "addr:full":"30032 Fiesso D'artico Venezia 30032",
    "addr:postcode":"30032;30032",
    "iso:country":"IT",
    "sg:address":"30032 Fiesso D'artico",
    "sg:orig_category":"Ricambi E Componenti Dei Mezzi Di Trasporto",
    "sg:phone":"+39 041 411135",
    "sg:postcode":"30032",
    "sg:province":"Venezia",
    "wof:name":"Paiaro Aldo",
    "wof:placetype":"venue"
},
  "geometry": {"coordinates":[12.128951,45.435066],"type":"Point"}
}