{
  "type": "Feature",
  "properties": {
    "iso:country":"IT",
    "sg:address":"00197 Roma",
    "sg:city":"Roma",
    "sg:classifiers":[
        {
            "category":"Health Services",
            "subcategory":"Nursing And Care Facility",
            "type":"Services"
        }
    ],
    "sg:phone":"+39 06 802201",
    "sg:postcode":"00197",
    "sg:province":"Roma",
    "sg:tags":[
        "case",
        "cura",
        "private",
        "di"
    ],
    "sg:website":"http://www.materdei.it",
    "wof:name":"Casa Di Cura Mater Dei Spa",
    "wof:placetype":"venue"
},
  "geometry": {"coordinates":[12.486789,41.924664],"type":"Point"}
}