{
  "type": "Feature",
  "properties": {
    "iso:country":"IT",
    "sg:address":"20054 Nova Milanese",
    "sg:city":"Nova Milanese",
    "sg:orig_category":"Materiali E Componenti Elettrotecnici",
    "sg:phone":"+39 036 245 0871",
    "sg:postcode":"20054",
    "sg:province":"Milano",
    "wof:name":"Flowserve S.p.a.",
    "wof:placetype":"venue"
},
  "geometry": {"coordinates":[9.1765,45.559612],"type":"Point"}
}