{
  "type": "Feature",
  "properties": {
    "addr:full":"80123 Napoli Napoli Napoli 80123",
    "addr:housenumber":"80123",
    "addr:postcode":"80123",
    "iso:country":"IT",
    "sg:address":"80123 Napoli",
    "sg:city":"Napoli",
    "sg:orig_category":"Dolciumi E Gelati",
    "sg:phone":"+39 081 575 4993",
    "sg:postcode":"80123",
    "sg:province":"Napoli",
    "wof:name":"Dolci Creazioni Di Gobbo M.",
    "wof:placetype":"venue"
},
  "geometry": {"coordinates":[14.192534,40.834789],"type":"Point"}
}