{
  "type": "Feature",
  "properties": {
    "iso:country":"IT",
    "sg:address":"25018 Montichiari",
    "sg:city":"Montichiari",
    "sg:orig_category":"Onoranze E Pompe Funebri",
    "sg:phone":"+39 030 961797",
    "sg:postcode":"25018",
    "sg:province":"Brescia",
    "wof:name":"Coffani Dino Onoranze Funebri",
    "wof:placetype":"venue"
},
  "geometry": {"coordinates":[10.389707,45.414948],"type":"Point"}
}