{
  "type": "Feature",
  "properties": {
    "addr:full":"51013 Chiesina Uzzanese Chiesina Uzzanese Pistoia 51013",
    "addr:postcode":"51013;51013",
    "addr:street":"Uzzanese",
    "iso:country":"IT",
    "sg:address":"51013 Chiesina Uzzanese",
    "sg:city":"Chiesina Uzzanese",
    "sg:orig_category":"Servizi Ausiliari Dei Mezzi Di Trasporto",
    "sg:phone":"+39 0572 411432",
    "sg:postcode":"51013",
    "sg:province":"Pistoia",
    "wof:name":"Iacopini Debora",
    "wof:placetype":"venue"
},
  "geometry": {"coordinates":[11.024074,43.846573],"type":"Point"}
}