{
  "type": "Feature",
  "properties": {
    "addr:full":"20124 Milano Milano Milano 20124",
    "addr:postcode":"20124;20124",
    "iso:country":"IT",
    "sg:address":"20124 Milano",
    "sg:city":"Milano",
    "sg:orig_category":"Minuterie Metalliche E Ferramenta",
    "sg:phone":"+39 02 655 1621",
    "sg:postcode":"20124",
    "sg:province":"Milano",
    "wof:name":"M.g.m. Chiavette Srl",
    "wof:placetype":"venue"
},
  "geometry": {"coordinates":[9.1935415268,45.4807815552],"type":"Point"}
}