{
  "type": "Feature",
  "properties": {
    "addr:full":"66020 San Giovanni Teatino San Giovanni Teatino Chieti 66020",
    "addr:housenumber":"66020",
    "addr:postcode":"66020",
    "addr:street":"San",
    "iso:country":"IT",
    "sg:address":"66020 San Giovanni Teatino",
    "sg:city":"San Giovanni Teatino",
    "sg:orig_category":"Macchine, Impianti Ed Attrezzature Per Industria Alimentare E Bevande",
    "sg:phone":"+39 085 446 3563",
    "sg:postcode":"66020",
    "sg:province":"Chieti",
    "wof:name":"Mida Snc Di Michelucci E D'angelo & C.",
    "wof:placetype":"venue"
},
  "geometry": {"coordinates":[14.195978,42.428207],"type":"Point"}
}