{
  "type": "Feature",
  "properties": {
    "iso:country":"IT",
    "sg:address":"96 Via Vittorio Veneto, 00187 Roma",
    "sg:city":"Roma",
    "sg:classifiers":[
        {
            "category":"Banks & Credit Unions",
            "subcategory":"Financial Services",
            "type":"Services"
        }
    ],
    "sg:phone":"+39 390 647 9801",
    "sg:postcode":"00187",
    "sg:province":"Roma",
    "sg:tags":[
        "banking",
        "finance",
        "insurance"
    ],
    "wof:name":"Lucente Giovanni",
    "wof:placetype":"venue"
},
  "geometry": {"coordinates":[12.4468002319,42.1051635742],"type":"Point"}
}