{
  "type": "Feature",
  "properties": {
    "iso:country":"IT",
    "sg:address":"40122 Bologna",
    "sg:city":"Bologna",
    "sg:orig_category":"Salotti, Poltrone, Sedie E Tavoli",
    "sg:phone":"+39 051 227484",
    "sg:postcode":"40122",
    "sg:province":"Bologna",
    "wof:name":"Ugo Notte",
    "wof:placetype":"venue"
},
  "geometry": {"coordinates":[11.288667,44.535446],"type":"Point"}
}