{
  "type": "Feature",
  "properties": {
    "addr:full":"10042 Nichelino Nichelino Torino 10042",
    "addr:postcode":"10042;10042",
    "iso:country":"IT",
    "sg:address":"10042 Nichelino",
    "sg:city":"Nichelino",
    "sg:orig_category":"Macchine Ed Impianti Per Edilizia E Lavori Pubblici. Forniture Per Edilizia E Lavori Pubblici",
    "sg:phone":"+39 011 680 9805",
    "sg:postcode":"10042",
    "sg:province":"Torino",
    "sg:website":"http://www.edilcomec.com",
    "wof:name":"Nuova Edilcomec Srl",
    "wof:placetype":"venue"
},
  "geometry": {"coordinates":[7.623737812,44.9889755249],"type":"Point"}
}