{
  "type": "Feature",
  "properties": {
    "iso:country":"IT",
    "sg:address":"16164 Genova",
    "sg:city":"Genova",
    "sg:orig_category":"Non-classified Establishments",
    "sg:phone":"+39 010 781490",
    "sg:postcode":"16164",
    "sg:province":"Genova",
    "wof:name":"Parodi Erminia",
    "wof:placetype":"venue"
},
  "geometry": {"coordinates":[8.902912,44.499271],"type":"Point"}
}