{
  "type": "Feature",
  "properties": {
    "iso:country":"IT",
    "sg:address":"33, Via Piave 17047 Vado Ligure",
    "sg:city":"Vado Ligure",
    "sg:classifiers":[
        {
            "category":"Parking",
            "subcategory":"Lot",
            "type":"Transportation"
        }
    ],
    "sg:phone":"+39 39019880764",
    "sg:postcode":"17047",
    "sg:province":"Savona",
    "sg:tags":[
        "transport",
        "road"
    ],
    "wof:name":"Ottonello Francesco Di Ottonello M E C Snc",
    "wof:placetype":"venue"
},
  "geometry": {"coordinates":[8.410193,44.25983],"type":"Point"}
}