{
  "type": "Feature",
  "properties": {
    "addr:full":"60021 Camerano Camerano Ancona 60021",
    "addr:postcode":"60021;60021",
    "iso:country":"IT",
    "sg:address":"60021 Camerano",
    "sg:city":"Camerano",
    "sg:orig_category":"Prodotti Alimentari",
    "sg:phone":"+39 071 95278",
    "sg:postcode":"60021",
    "sg:province":"Ancona",
    "wof:name":"Burattini Alberto",
    "wof:placetype":"venue"
},
  "geometry": {"coordinates":[13.5492963791,43.5314865112],"type":"Point"}
}