{
  "type": "Feature",
  "properties": {
    "addr:full":"126, Regione Soria 14053 Canelli Canelli Asti 14053",
    "addr:housenumber":"126",
    "addr:postcode":"14053;14053",
    "addr:street":"Regione Soria",
    "iso:country":"IT",
    "sg:address":"126, Regione Soria 14053 Canelli",
    "sg:city":"Canelli",
    "sg:classifiers":[
        {
            "category":"Manufacturing",
            "subcategory":"Food",
            "type":"Manufacturing & Wholesale Goods"
        }
    ],
    "sg:phone":"+39 0141 831316",
    "sg:postcode":"14053",
    "sg:province":"Asti",
    "sg:tags":[
        "equipment",
        "processing",
        "-",
        "machinery"
    ],
    "wof:name":"Comen (s.r.l.)",
    "wof:placetype":"venue"
},
  "geometry": {"coordinates":[8.2165594101,44.7314834595],"type":"Point"}
}