{
  "type": "Feature",
  "properties": {
    "addr:full":"10151 Torino Torino Torino 10151",
    "addr:housenumber":"10151",
    "addr:postcode":"10151",
    "iso:country":"IT",
    "sg:address":"10151 Torino",
    "sg:city":"Torino",
    "sg:orig_category":"Materiali Semilavorati Metallici",
    "sg:phone":"+39 011 455 3792",
    "sg:postcode":"10151",
    "sg:province":"Torino",
    "wof:name":"Tecni.co Edilizia S.r.l.",
    "wof:placetype":"venue"
},
  "geometry": {"coordinates":[7.649207,45.110622],"type":"Point"}
}