{
  "type": "Feature",
  "properties": {
    "addr:full":"25045 Castegnato Castegnato Brescia 25045",
    "addr:postcode":"25045;25045",
    "iso:country":"IT",
    "sg:address":"25045 Castegnato",
    "sg:city":"Castegnato",
    "sg:orig_category":"Imprese Di Costruzioni Civili Ed Industriali",
    "sg:phone":"+39 030 272 1141",
    "sg:postcode":"25045",
    "sg:province":"Brescia",
    "wof:name":"Bettoni Spa",
    "wof:placetype":"venue"
},
  "geometry": {"coordinates":[10.110495,45.55209],"type":"Point"}
}