{
  "type": "Feature",
  "properties": {
    "iso:country":"IT",
    "sg:address":"17021 Alassio",
    "sg:city":"Alassio",
    "sg:orig_category":"Ospedali E Servizi Sanitari",
    "sg:phone":"+39 0182 470707",
    "sg:postcode":"17021",
    "sg:province":"Savona",
    "wof:name":"Antismoking Center",
    "wof:placetype":"venue"
},
  "geometry": {"coordinates":[8.16117,44.017982],"type":"Point"}
}