{
  "type": "Feature",
  "properties": {
    "iso:country":"IT",
    "sg:address":"226, Via De I Goti 45032 Bergantino",
    "sg:city":"Bergantino",
    "sg:classifiers":[
        {
            "category":"Shopping",
            "subcategory":"Clothing, Apparel, & Fashions",
            "type":"Retail Goods"
        }
    ],
    "sg:phone":"+39 0425 805115",
    "sg:postcode":"45032",
    "sg:province":"Rovigo",
    "sg:tags":[
        "clothes"
    ],
    "wof:name":"Bi E Gi (s.r.l.)",
    "wof:placetype":"venue"
},
  "geometry": {"coordinates":[11.789797,45.070736],"type":"Point"}
}