{
  "type": "Feature",
  "properties": {
    "iso:country":"IT",
    "sg:address":"26855 Lodi Vecchio",
    "sg:city":"Lodi Vecchio",
    "sg:orig_category":"Lavorazioni Metalli, Stampaggio E Saldatura",
    "sg:phone":"+39 0371 753750",
    "sg:postcode":"26855",
    "sg:province":"Lodi",
    "sg:website":"http://www.delinox.it",
    "wof:name":"Delinox Snc Di Giovanni E Luciano Dellavia",
    "wof:placetype":"venue"
},
  "geometry": {"coordinates":[9.415573,45.308685],"type":"Point"}
}