{
  "type": "Feature",
  "properties": {
    "iso:country":"IT",
    "sg:address":"66050 San Salvo",
    "sg:city":"San Salvo",
    "sg:orig_category":"Servizi Culturali E Per Lo Spettacolo. Servizi Per Lo Sport E Il Tempo Libero. Servizi Per Aziende, Manifestazioni E Supporto Agli Scambi Commerciali",
    "sg:phone":"+39 0873 346056",
    "sg:postcode":"66050",
    "sg:province":"Chieti",
    "wof:name":"New Slem Sas",
    "wof:placetype":"venue"
},
  "geometry": {"coordinates":[14.751207,42.049664],"type":"Point"}
}