{
  "type": "Feature",
  "properties": {
    "addr:full":"20060 Pessano Con Bornago Ornago Milano 20060",
    "addr:postcode":"20060;20060",
    "iso:country":"IT",
    "sg:address":"20060 Pessano Con Bornago",
    "sg:city":"Ornago",
    "sg:orig_category":"Forniture Per Attivita' Commerciali Ed Artigianali",
    "sg:phone":"+39 02 9574 3362",
    "sg:postcode":"20060",
    "sg:province":"Milano",
    "wof:name":"Quadranti E Targhe S.r.l.",
    "wof:placetype":"venue"
},
  "geometry": {"coordinates":[9.391002655,45.5539169312],"type":"Point"}
}