{
  "type": "Feature",
  "properties": {
    "iso:country":"IT",
    "sg:address":"09045 Quartu Sant'elena",
    "sg:orig_category":"Forniture Per Edilizia E Lavori Pubblici",
    "sg:phone":"+39 070 814537",
    "sg:postcode":"09045",
    "sg:province":"Cagliari",
    "wof:name":"C.s.v. & C. Di Loi Silvestro Sas",
    "wof:placetype":"venue"
},
  "geometry": {"coordinates":[9.1933708191,39.235408783],"type":"Point"}
}