{
  "type": "Feature",
  "properties": {
    "iso:country":"IT",
    "sg:address":"28100 Novara",
    "sg:city":"Novara",
    "sg:orig_category":"Studi E Consulenze Amministrative, Commerciali E Aziendali. Consulenze Tecniche, Amministrative E Perizie. Professionisti - Studi E Servizi Ed Associazioni Di Interesse Aziendale",
    "sg:phone":"+39 0321 628818",
    "sg:postcode":"28100",
    "sg:province":"Novara",
    "wof:name":"Rag. Gili",
    "wof:placetype":"venue"
},
  "geometry": {"coordinates":[8.610478,45.447083],"type":"Point"}
}