{
  "type": "Feature",
  "properties": {
    "addr:full":"Via Calabria, 3/5 35020 Saonara Saonara Padova 35020",
    "addr:housenumber":"3 / 5",
    "addr:postcode":"35020;35020",
    "addr:street":"Via Calabria",
    "iso:country":"IT",
    "sg:address":"Via Calabria, 3/5 35020 Saonara",
    "sg:city":"Saonara",
    "sg:classifiers":[
        {
            "category":"Manufacturing",
            "subcategory":"Printing",
            "type":"Manufacturing & Wholesale Goods"
        }
    ],
    "sg:phone":"+39 049 879 0775",
    "sg:postcode":"35020",
    "sg:province":"Padova",
    "sg:tags":[
        "plastic"
    ],
    "wof:name":"Tecnoplastic Srl",
    "wof:placetype":"venue"
},
  "geometry": {"coordinates":[11.9584665298,45.3802871704],"type":"Point"}
}