{
  "type": "Feature",
  "properties": {
    "iso:country":"IT",
    "sg:address":"20051 Limbiate",
    "sg:city":"Limbiate",
    "sg:orig_category":"Macchine Utensili E Impianti",
    "sg:phone":"+39 02 9905 4773",
    "sg:postcode":"20051",
    "sg:province":"Milano",
    "wof:name":"Sacma Limbiate Spa",
    "wof:placetype":"venue"
},
  "geometry": {"coordinates":[9.117207,45.601707],"type":"Point"}
}