{
  "type": "Feature",
  "properties": {
    "iso:country":"IT",
    "sg:address":"80011 Acerra",
    "sg:city":"Acerra",
    "sg:orig_category":"Carni, Salumi E Pesci",
    "sg:phone":"+39 081 520 5181",
    "sg:postcode":"80011",
    "sg:province":"Napoli",
    "wof:name":"Terracciano Raffaele",
    "wof:placetype":"venue"
},
  "geometry": {"coordinates":[14.348743,40.949623],"type":"Point"}
}