{
  "type": "Feature",
  "properties": {
    "iso:country":"IT",
    "sg:address":"61, Via Capitano Alessio 36027 Rosa'",
    "sg:classifiers":[
        {
            "category":"Manufacturing",
            "subcategory":"Rubber & Plastics",
            "type":"Manufacturing & Wholesale Goods"
        }
    ],
    "sg:phone":"+39 39042485404",
    "sg:postcode":"36027",
    "sg:province":"Vicenza",
    "sg:tags":[
        "packaging",
        "material",
        "-"
    ],
    "wof:name":"Parolin Vittorio & C. (s.n.c.)",
    "wof:placetype":"venue"
},
  "geometry": {"coordinates":[11.7617034912,45.72838974],"type":"Point"}
}