{
  "type": "Feature",
  "properties": {
    "iso:country":"IT",
    "sg:address":"22063 Cantu'",
    "sg:orig_category":"Arti Grafiche",
    "sg:phone":"+39 031 730103",
    "sg:postcode":"22063",
    "sg:province":"Como",
    "wof:name":"Ideagrafica Sas Di Caspani & C.",
    "wof:placetype":"venue"
},
  "geometry": {"coordinates":[9.099385,45.742321],"type":"Point"}
}