{
  "type": "Feature",
  "properties": {
    "iso:country":"IT",
    "sg:address":"13872 Borriana",
    "sg:city":"Borriana",
    "sg:orig_category":"Filati E Materie Prime Tessili",
    "sg:phone":"+39 015 446167",
    "sg:postcode":"13872",
    "sg:province":"Biella",
    "wof:name":"Bof Paolo",
    "wof:placetype":"venue"
},
  "geometry": {"coordinates":[8.0371770859,45.5072212219],"type":"Point"}
}