{
  "type": "Feature",
  "properties": {
    "addr:full":"00128 Roma Roma Roma 00128",
    "addr:postcode":"00128;00128",
    "iso:country":"IT",
    "sg:address":"00128 Roma",
    "sg:city":"Roma",
    "sg:orig_category":"Pescherie",
    "sg:phone":"+39 06 506 1722",
    "sg:postcode":"00128",
    "sg:province":"Roma",
    "wof:name":"Due Emme Srl",
    "wof:placetype":"venue"
},
  "geometry": {"coordinates":[12.4796457291,41.7714347839],"type":"Point"}
}