{
  "type": "Feature",
  "properties": {
    "iso:country":"IT",
    "sg:address":"72100 Brindisi",
    "sg:city":"Brindisi",
    "sg:orig_category":"Non-classified Establishments",
    "sg:phone":"+39 0831 546876",
    "sg:postcode":"72100",
    "sg:province":"Brindisi",
    "wof:name":"Giano Elite Praticopp",
    "wof:placetype":"venue"
},
  "geometry": {"coordinates":[17.968412,40.624546],"type":"Point"}
}