{
  "type": "Feature",
  "properties": {
    "iso:country":"IT",
    "sg:address":"20090 Vimodrone",
    "sg:city":"Vimodrone",
    "sg:orig_category":"Professionisti - Studi E Servizi Ed Associazioni Di Interesse Aziendale. Associazioni Ed Organismi Di Interesse Pubblico. Chiese Ed Associazioni Religiose",
    "sg:phone":"+39 02 250 1339",
    "sg:postcode":"20090",
    "sg:province":"Milano",
    "wof:name":"Parrocchia S. Remigio",
    "wof:placetype":"venue"
},
  "geometry": {"coordinates":[9.2848768234,45.5133247375],"type":"Point"}
}