{
  "type": "Feature",
  "properties": {
    "addr:full":"10100 Torino TO",
    "addr:postcode":"10100",
    "iso:country":"IT",
    "sg:address":"10100 Torino",
    "sg:orig_category":"Forniture E Materiali Per Imballaggio E Confezionamento. Forniture Per Uffici. Forniture Per Attivita' Commerciali Ed Artigianali",
    "sg:phone":"+39 800 802 145",
    "sg:province":"TO",
    "wof:name":"3m Italia Spa",
    "wof:placetype":"venue"
},
  "geometry": {"coordinates":[7.1777758598,45.107219696],"type":"Point"}
}