{
  "type": "Feature",
  "properties": {
    "addr:full":"39010 Gargazzone Gargazzone Bolzano/Bozen 39010",
    "addr:postcode":"39010;39010",
    "iso:country":"IT",
    "sg:address":"39010 Gargazzone",
    "sg:city":"Gargazzone",
    "sg:orig_category":"Biliardi Ed Accessori",
    "sg:phone":"+39 0473 291077",
    "sg:postcode":"39010",
    "sg:province":"Bolzano/Bozen",
    "wof:name":"Alpigame Snc",
    "wof:placetype":"venue"
},
  "geometry": {"coordinates":[11.212697,46.578606],"type":"Point"}
}