{
  "type": "Feature",
  "properties": {
    "addr:full":"25016 Ghedi Ghedi Brescia 25016",
    "addr:postcode":"25016;25016",
    "iso:country":"IT",
    "sg:address":"25016 Ghedi",
    "sg:city":"Ghedi",
    "sg:orig_category":"Servizi E Lavori Per Abbigliamento E Pelletterie. Arte Ed Artigianato Artistico. Shopping",
    "sg:phone":"+39 030 902516",
    "sg:postcode":"25016",
    "sg:province":"Brescia",
    "wof:name":"Cuoieria",
    "wof:placetype":"venue"
},
  "geometry": {"coordinates":[10.278018,45.403496],"type":"Point"}
}