{
  "type": "Feature",
  "properties": {
    "iso:country":"IT",
    "sg:address":"43, Fdm. Vetrai - Murano 30141 Venezia",
    "sg:city":"Murano",
    "sg:classifiers":[
        {
            "category":"Shopping",
            "subcategory":"Computers & Home Electronics",
            "type":"Retail Goods"
        }
    ],
    "sg:phone":"+39 39041739477",
    "sg:postcode":"30141",
    "sg:province":"Venezia",
    "sg:tags":[
        "electronic",
        "electrical",
        "equipment"
    ],
    "sg:website":"http://www.gallianoferro.it",
    "wof:name":"Vetreria Artistica Galliano Ferro Di Eredi Giorgio Ferro Snc",
    "wof:placetype":"venue"
},
  "geometry": {"coordinates":[12.354899,45.457439],"type":"Point"}
}