{
  "type": "Feature",
  "properties": {
    "addr:full":"Via Divisione Acqui 16 61100 Pesaro Pesaro Pesaro E Urbino 61100",
    "addr:housenumber":"16",
    "addr:postcode":"61100;61100",
    "addr:street":"Via Divisione Acqui",
    "iso:country":"IT",
    "sg:address":"Via Divisione Acqui 16 61100 Pesaro",
    "sg:city":"Pesaro",
    "sg:classifiers":[
        {
            "category":"Autos & Motor Vehicles",
            "subcategory":"Fuel & Gas Station",
            "type":"Retail Goods"
        }
    ],
    "sg:phone":"+39 0721 283134",
    "sg:postcode":"61100",
    "sg:province":"Pesaro E Urbino",
    "sg:tags":[
        "feed",
        "pump",
        "pneumatic",
        "pumps",
        "metering"
    ],
    "sg:website":"www.falcionipompe.com",
    "wof:name":"Falcioni Pompe Srl",
    "wof:placetype":"venue"
},
  "geometry": {"coordinates":[12.8614397049,43.8831787109],"type":"Point"}
}