{
  "type": "Feature",
  "properties": {
    "addr:full":"61, Via Cetino 50013 Campi Bisenzio Campi Bisenzio Firenze 50013",
    "addr:postcode":"50013;50013",
    "addr:street":"Via Cetino;Bisenzio",
    "iso:country":"IT",
    "sg:address":"61, Via Cetino 50013 Campi Bisenzio",
    "sg:city":"Campi Bisenzio",
    "sg:classifiers":[
        {
            "category":"Professional",
            "subcategory":"Business Services",
            "type":"Services"
        }
    ],
    "sg:phone":"+39 055 896 2761",
    "sg:postcode":"50013",
    "sg:province":"Firenze",
    "sg:tags":[
        "advice"
    ],
    "wof:name":"New Itineraries Cultural And Educational",
    "wof:placetype":"venue"
},
  "geometry": {"coordinates":[11.147985,43.819576],"type":"Point"}
}