{
  "type": "Feature",
  "properties": {
    "addr:full":"30030 Martellago Martellago Venezia 30030",
    "addr:postcode":"30030;30030",
    "iso:country":"IT",
    "sg:address":"30030 Martellago",
    "sg:city":"Martellago",
    "sg:orig_category":"Bricolage E Fai Da Te",
    "sg:phone":"+39 041 680576",
    "sg:postcode":"30030",
    "sg:province":"Venezia",
    "wof:name":"Elettroveneta Snc",
    "wof:placetype":"venue"
},
  "geometry": {"coordinates":[12.189852,45.517666],"type":"Point"}
}