{
  "type": "Feature",
  "properties": {
    "iso:country":"IT",
    "sg:address":"Via Prati 36022 Cassola",
    "sg:city":"Cassola",
    "sg:classifiers":[
        {
            "category":"Manufacturing",
            "subcategory":"Metals",
            "type":"Manufacturing & Wholesale Goods"
        }
    ],
    "sg:phone":"+39 0424 570246",
    "sg:postcode":"36022",
    "sg:province":"Vicenza",
    "sg:tags":[
        "processing"
    ],
    "wof:name":"Torneria Ferraro Di Chiminello Ruggero & Paolo (s.n.c.)",
    "wof:placetype":"venue"
},
  "geometry": {"coordinates":[11.7681121826,45.7502479553],"type":"Point"}
}