{
  "type": "Feature",
  "properties": {
    "iso:country":"IT",
    "sg:address":"26100 Cremona",
    "sg:city":"Cremona",
    "sg:orig_category":"Macchine E Forniture Per Ecologia E Smaltimento Rifiuti",
    "sg:phone":"+39 0372 471100",
    "sg:postcode":"26100",
    "sg:province":"Cremona",
    "wof:name":"Tedoldi Servizi Ecologici Srl",
    "wof:placetype":"venue"
},
  "geometry": {"coordinates":[9.983044,45.150284],"type":"Point"}
}