{
  "type": "Feature",
  "properties": {
    "addr:full":"31057 Silea Silea Treviso 31057",
    "addr:postcode":"31057;31057",
    "iso:country":"IT",
    "sg:address":"31057 Silea",
    "sg:city":"Silea",
    "sg:classifiers":[
        {
            "category":"Manufacturing",
            "subcategory":"Metals",
            "type":"Manufacturing & Wholesale Goods"
        }
    ],
    "sg:phone":"+39 0422 94461",
    "sg:postcode":"31057",
    "sg:province":"Treviso",
    "sg:tags":[
        "forming",
        "working",
        "welding"
    ],
    "wof:name":"Zanatta Ferdinando",
    "wof:placetype":"venue"
},
  "geometry": {"coordinates":[12.2898836136,45.6541824341],"type":"Point"}
}