{
  "type": "Feature",
  "properties": {
    "addr:full":"Tortona, Al",
    "iso:country":"IT",
    "sg:address":"Tortona, Al",
    "sg:classifiers":[
        {
            "category":"Banks & Credit Unions",
            "subcategory":"Bank",
            "type":"Services"
        }
    ],
    "wof:name":"Parco Scientifico Tecnologico",
    "wof:placetype":"venue"
},
  "geometry": {"coordinates":[8.865485,44.897171],"type":"Point"}
}