{
  "type": "Feature",
  "properties": {
    "addr:full":"63023 Fermo Fermo Ascoli Piceno 63023",
    "addr:postcode":"63023;63023",
    "addr:street":"Piceno",
    "iso:country":"IT",
    "sg:address":"63023 Fermo",
    "sg:city":"Fermo",
    "sg:orig_category":"Gioiellerie E Oreficerie - Vendita Al Dettaglio",
    "sg:phone":"+39 0734 229149",
    "sg:postcode":"63023",
    "sg:province":"Ascoli Piceno",
    "sg:website":"http://www.marzi-panichi.com",
    "wof:name":"Gioielleria Marzi & Panichi",
    "wof:placetype":"venue"
},
  "geometry": {"coordinates":[13.716876,43.161995],"type":"Point"}
}