{
  "type": "Feature",
  "properties": {
    "addr:full":"Via Mazzini 3 23014 Delebio Delebio Sondrio 23014",
    "addr:housenumber":"3",
    "addr:postcode":"23014;23014",
    "addr:street":"Via Mazzini",
    "iso:country":"IT",
    "sg:address":"Via Mazzini 3 23014 Delebio",
    "sg:city":"Delebio",
    "sg:classifiers":[
        {
            "category":"Train Station",
            "subcategory":"Light Rail",
            "type":"Transportation"
        }
    ],
    "sg:phone":"+39 0342 685206",
    "sg:postcode":"23014",
    "sg:province":"Sondrio",
    "sg:tags":[
        "stockings",
        "medical",
        "elastic"
    ],
    "sg:website":"www.manifatturabernina.it",
    "wof:name":"Manifattura Bernina Srl",
    "wof:placetype":"venue"
},
  "geometry": {"coordinates":[9.461271,46.13739],"type":"Point"}
}