{
  "type": "Feature",
  "properties": {
    "addr:full":"27029 Vigevano Vigevano Pavia 27029",
    "addr:postcode":"27029;27029",
    "iso:country":"IT",
    "sg:address":"27029 Vigevano",
    "sg:city":"Vigevano",
    "sg:orig_category":"Termotecnica E Riscaldamento, Apparecchiature E Servizi",
    "sg:phone":"+39 0381 311228",
    "sg:postcode":"27029",
    "sg:province":"Pavia",
    "wof:name":"Celada S.n.c. Di Terragno & Valentini",
    "wof:placetype":"venue"
},
  "geometry": {"coordinates":[8.842996,45.31366],"type":"Point"}
}