{
  "type": "Feature",
  "properties": {
    "iso:country":"IT",
    "sg:address":"90133 Palermo",
    "sg:city":"Palermo",
    "sg:orig_category":"Forniture E Prodotti Informatici. Forniture Per Uffici",
    "sg:phone":"+39 091 321694",
    "sg:postcode":"90133",
    "sg:province":"Palermo",
    "wof:name":"Cartoleria Crisci Srl",
    "wof:placetype":"venue"
},
  "geometry": {"coordinates":[13.3618192673,38.120174408],"type":"Point"}
}