{
  "type": "Feature",
  "properties": {
    "iso:country":"IT",
    "sg:address":"73024 Maglie",
    "sg:city":"Maglie",
    "sg:orig_category":"Pubblica Amministrazione",
    "sg:phone":"+39 0836 428715",
    "sg:postcode":"73024",
    "sg:province":"Lecce",
    "wof:name":"Vigili Del Fuoco",
    "wof:placetype":"venue"
},
  "geometry": {"coordinates":[18.2970695496,40.1206016541],"type":"Point"}
}