{
  "type": "Feature",
  "properties": {
    "iso:country":"IT",
    "sg:address":"Via Cannizzaro Stanislao 16 56121 Pisa",
    "sg:city":"Pisa",
    "sg:classifiers":[
        {
            "category":"Wholesale",
            "subcategory":"Medical Equipment & Supplies",
            "type":"Manufacturing & Wholesale Goods"
        }
    ],
    "sg:phone":"+39 050 982206",
    "sg:postcode":"56121",
    "sg:province":"Pisa",
    "sg:tags":[
        "lens",
        "microscope",
        "system"
    ],
    "sg:website":"www.lace.it",
    "wof:name":"Lace Elettronica Srl",
    "wof:placetype":"venue"
},
  "geometry": {"coordinates":[10.396585,43.716137],"type":"Point"}
}