{
  "type": "Feature",
  "properties": {
    "iso:country":"IT",
    "sg:address":"10099 San Mauro Torinese",
    "sg:city":"San Mauro Torinese",
    "sg:orig_category":"Banche E Servizi Finanziari",
    "sg:phone":"+39 011 223 8960",
    "sg:postcode":"10099",
    "sg:province":"Torino",
    "wof:name":"Burgo Factor (s.p.a.)",
    "wof:placetype":"venue"
},
  "geometry": {"coordinates":[7.742089,45.111004],"type":"Point"}
}