{
  "type": "Feature",
  "properties": {
    "iso:country":"IT",
    "sg:address":"22100 Como",
    "sg:city":"Como",
    "sg:classifiers":[
        {
            "category":"Shopping",
            "subcategory":"Crafts & Fabrics",
            "type":"Retail Goods"
        }
    ],
    "sg:phone":"+39 031 264403",
    "sg:postcode":"22100",
    "sg:province":"Como",
    "sg:tags":[
        "material"
    ],
    "wof:name":"T.j.s.s. Srl",
    "wof:placetype":"venue"
},
  "geometry": {"coordinates":[9.0854110718,45.8101196289],"type":"Point"}
}