{
  "type": "Feature",
  "properties": {
    "addr:full":"42100 Reggio Emilia Reggio Nell'Emilia 42100",
    "addr:postcode":"42100;42100",
    "iso:country":"IT",
    "sg:address":"42100 Reggio Emilia",
    "sg:orig_category":"Animali Domestici - Allevamento E Addestramento",
    "sg:phone":"+39 0522 950749",
    "sg:postcode":"42100",
    "sg:province":"Reggio Nell'Emilia",
    "wof:name":"Schiatti Fausto",
    "wof:placetype":"venue"
},
  "geometry": {"coordinates":[10.674934,44.717697],"type":"Point"}
}