{
  "type": "Feature",
  "properties": {
    "iso:country":"IT",
    "sg:address":"90143 Palermo",
    "sg:city":"Palermo",
    "sg:orig_category":"Imprese Pulizia",
    "sg:phone":"+39 091 301339",
    "sg:postcode":"90143",
    "sg:province":"Palermo",
    "wof:name":"Centro Pulizia Srl",
    "wof:placetype":"venue"
},
  "geometry": {"coordinates":[13.353512,38.136837],"type":"Point"}
}