{
  "type": "Feature",
  "properties": {
    "addr:full":"10040 Leini' Lombardore Torino 10040",
    "addr:housenumber":"10040",
    "addr:postcode":"10040",
    "addr:street":"Leini ' Lombardore",
    "iso:country":"IT",
    "sg:address":"10040 Leini'",
    "sg:city":"Lombardore",
    "sg:orig_category":"Trattamenti Termici E Superficiali Metalli, Galvanotecnica",
    "sg:phone":"+39 011 997 8323",
    "sg:postcode":"10040",
    "sg:province":"Torino",
    "wof:name":"R.g. Snc Di Pantella Giovanni",
    "wof:placetype":"venue"
},
  "geometry": {"coordinates":[7.731494,45.224285],"type":"Point"}
}