{
  "type": "Feature",
  "properties": {
    "iso:country":"IT",
    "sg:address":"60/a, Via Donizetti Gaetano 09128 Cagliari",
    "sg:city":"Cagliari",
    "sg:classifiers":[
        {
            "category":"Professional",
            "subcategory":"Computer Services",
            "type":"Services"
        }
    ],
    "sg:phone":"+39 39070497413",
    "sg:postcode":"09128",
    "sg:province":"Cagliari",
    "sg:tags":[
        "information",
        "technology"
    ],
    "wof:name":"Reprograf (s.n.c.)",
    "wof:placetype":"venue"
},
  "geometry": {"coordinates":[9.109228,39.215458],"type":"Point"}
}