{
  "type": "Feature",
  "properties": {
    "iso:country":"IT",
    "sg:address":"23826 Mandello Del Lario",
    "sg:city":"Mandello del Lario",
    "sg:orig_category":"Impiantistica E Prodotti Tecnologici Per Edilizia. Elettrotecnica Professionale E Di Consumo. Telecomunicazioni E Telefonia, Impianti, Apparecchi E Servizi",
    "sg:phone":"+39 0341 730710",
    "sg:postcode":"23826",
    "sg:province":"Lecco",
    "wof:name":"Gorlux Snc Di Mansueto & Armando",
    "wof:placetype":"venue"
},
  "geometry": {"coordinates":[9.400284,45.865768],"type":"Point"}
}