{
  "type": "Feature",
  "properties": {
    "addr:full":"00054 Fiumicino Fiumicino Roma 00054",
    "addr:postcode":"00054;roma 00054",
    "iso:country":"IT",
    "sg:address":"00054 Fiumicino",
    "sg:city":"Fiumicino",
    "sg:classifiers":[
        {
            "category":"Bars & Pubs",
            "subcategory":"Champagne Bar",
            "type":"Food & Drink"
        }
    ],
    "sg:phone":"+39 06 6502 9886",
    "sg:postcode":"00054",
    "sg:province":"Roma",
    "sg:tags":[
        "caffe'",
        "e"
    ],
    "wof:name":"Taverna Vecchia Srl",
    "wof:placetype":"venue"
},
  "geometry": {"coordinates":[12.249841,41.768101],"type":"Point"}
}