{
  "type": "Feature",
  "properties": {
    "addr:full":"10, Via Cellini 25030 Roncadelle Roncadelle Brescia 25030",
    "addr:postcode":"25030;25030",
    "addr:street":"Via Cellini",
    "iso:country":"IT",
    "sg:address":"10, Via Cellini 25030 Roncadelle",
    "sg:city":"Roncadelle",
    "sg:classifiers":[
        {
            "category":"Personal",
            "subcategory":"Shoe Repair & Shine",
            "type":"Services"
        }
    ],
    "sg:phone":"+39 030 258 3160",
    "sg:postcode":"25030",
    "sg:province":"Brescia",
    "sg:tags":[
        "leather"
    ],
    "wof:name":"Pianellificio Marilan Di Galesi Anna & C. (s.n.c.)",
    "wof:placetype":"venue"
},
  "geometry": {"coordinates":[10.157127,45.533031],"type":"Point"}
}