{
  "type": "Feature",
  "properties": {
    "addr:full":"20090 Trezzano Sul Naviglio Trezzano sul Naviglio Milano 20090",
    "addr:postcode":"20090;20090",
    "iso:country":"IT",
    "sg:address":"20090 Trezzano Sul Naviglio",
    "sg:city":"Trezzano sul Naviglio",
    "sg:orig_category":"Pubblica Amministrazione",
    "sg:phone":"+39 02 484181",
    "sg:postcode":"20090",
    "sg:province":"Milano",
    "wof:name":"Comune Di Trezzano Sul Naviglio",
    "wof:placetype":"venue"
},
  "geometry": {"coordinates":[9.0707321167,45.4183387756],"type":"Point"}
}