{
  "type": "Feature",
  "properties": {
    "iso:country":"IT",
    "sg:address":"97, Via Salviati 00155 Roma",
    "sg:city":"Roma",
    "sg:classifiers":[
        {
            "category":"Home & Garden",
            "subcategory":"Home Furnishings",
            "type":"Retail Goods"
        }
    ],
    "sg:phone":"+39 39062280533",
    "sg:postcode":"00155",
    "sg:province":"Roma",
    "sg:tags":[
        "household"
    ],
    "wof:name":"Fimac",
    "wof:placetype":"venue"
},
  "geometry": {"coordinates":[12.45191,41.872616],"type":"Point"}
}