{
  "type": "Feature",
  "properties": {
    "iso:country":"IT",
    "sg:address":"24/28, Via Marazzi 26017 Torlino Vimercati",
    "sg:city":"Torlino Vimercati",
    "sg:classifiers":[
        {
            "category":"Shopping",
            "type":"Retail Goods"
        }
    ],
    "sg:phone":"+39 0373 288901",
    "sg:postcode":"26017",
    "sg:province":"Cremona",
    "sg:tags":[
        "finished",
        "-",
        "metallic"
    ],
    "wof:name":"Sangiovanni (s.r.l.)",
    "wof:placetype":"venue"
},
  "geometry": {"coordinates":[9.5927791595,45.4166030884],"type":"Point"}
}