{
  "type": "Feature",
  "properties": {
    "iso:country":"IT",
    "sg:address":"Via S. Teresa 16; Torino; 10121",
    "sg:city":"Torino",
    "sg:classifiers":[
        {
            "category":"Banks & Credit Unions",
            "subcategory":"Bank",
            "type":"Services"
        }
    ],
    "sg:phone":"+39 011 533011",
    "sg:postcode":"10121",
    "sg:province":"Torino",
    "wof:name":"Banca Popolare Vicentina Scparl",
    "wof:placetype":"venue"
},
  "geometry": {"coordinates":[7.680553,45.069279],"type":"Point"}
}