{
  "type": "Feature",
  "properties": {
    "iso:country":"IT",
    "sg:address":"60037 Monte San Vito",
    "sg:city":"Monte San Vito",
    "sg:orig_category":"Termotecnica E Riscaldamento, Apparecchiature E Servizi",
    "sg:phone":"+39 071 948303",
    "sg:postcode":"60037",
    "sg:province":"Ancona",
    "wof:name":"C.m.m. Bruciatori",
    "wof:placetype":"venue"
},
  "geometry": {"coordinates":[13.32589,43.604652],"type":"Point"}
}