{
  "type": "Feature",
  "properties": {
    "addr:full":"10, Via Juri Gagarin 06073 Corciano Corciano Perugia 06073",
    "addr:postcode":"06073;06073",
    "addr:street":"Via Juri Gagarin",
    "iso:country":"IT",
    "sg:address":"10, Via Juri Gagarin 06073 Corciano",
    "sg:city":"Corciano",
    "sg:classifiers":[
        {
            "category":"Real Estate",
            "subcategory":"Architect",
            "type":"Services"
        }
    ],
    "sg:phone":"+39 39800218715",
    "sg:postcode":"06073",
    "sg:province":"Perugia",
    "sg:tags":[
        "textile",
        "clothing"
    ],
    "wof:name":"Igi Calzature E Tecnologie (s.p.a.)",
    "wof:placetype":"venue"
},
  "geometry": {"coordinates":[12.389172,43.110703],"type":"Point"}
}