{
  "type": "Feature",
  "properties": {
    "addr:full":"41018 San Cesario Sul Panaro San Cesario sul Panaro Modena 41018",
    "addr:housenumber":"41018",
    "addr:postcode":"cesario;panaro;41018",
    "addr:street":"San",
    "iso:country":"IT",
    "sg:address":"41018 San Cesario Sul Panaro",
    "sg:city":"San Cesario sul Panaro",
    "sg:orig_category":"Filati E Materie Prime Tessili. Prodotti E Manufatti In Materie Plastiche",
    "sg:phone":"+39 059 921462",
    "sg:postcode":"41018",
    "sg:province":"Modena",
    "wof:name":"Fili & Forme Srl",
    "wof:placetype":"venue"
},
  "geometry": {"coordinates":[11.0281658173,44.5943641663],"type":"Point"}
}