{
  "type": "Feature",
  "properties": {
    "iso:country":"IT",
    "sg:address":"23900 Lecco",
    "sg:city":"Lecco",
    "sg:classifiers":[
        {
            "category":"Health Services",
            "subcategory":"Health Practitioner",
            "type":"Services"
        }
    ],
    "sg:phone":"+39 0341 282051",
    "sg:postcode":"23900",
    "sg:province":"Lecco",
    "sg:tags":[
        "medici"
    ],
    "wof:name":"Larius S.n.c.",
    "wof:placetype":"venue"
},
  "geometry": {"coordinates":[9.415548,45.849552],"type":"Point"}
}