{
  "type": "Feature",
  "properties": {
    "iso:country":"IT",
    "sg:address":"V.le Del Lavoro 74 37035 San Giovanni Ilarione",
    "sg:city":"San Giovanni Ilarione",
    "sg:classifiers":[
        {
            "category":"Manufacturing",
            "subcategory":"Rubber & Plastics",
            "type":"Manufacturing & Wholesale Goods"
        }
    ],
    "sg:phone":"+39 045 746 5838",
    "sg:postcode":"37035",
    "sg:province":"Verona",
    "sg:tags":[
        "galosh",
        "boot",
        "boots",
        "polyvinyl",
        "pvc",
        "chloride"
    ],
    "sg:website":"www.relaxshoe.it",
    "wof:name":"Relaxshoe S.r.l.",
    "wof:placetype":"venue"
},
  "geometry": {"coordinates":[11.242667,45.509094],"type":"Point"}
}