{
  "type": "Feature",
  "properties": {
    "addr:full":"Via Giovanni Xxiii, 2/4 26020 Madignano Madignano Cremona 26020",
    "addr:housenumber":"2 / 4",
    "addr:postcode":"26020;26020",
    "addr:street":"Via Giovanni Xxiii",
    "iso:country":"IT",
    "sg:address":"Via Giovanni Xxiii, 2/4 26020 Madignano",
    "sg:city":"Madignano",
    "sg:classifiers":[
        {
            "category":"Utilities",
            "subcategory":"Natural Gas",
            "type":"Services"
        }
    ],
    "sg:phone":"+39 0373 659111",
    "sg:postcode":"26020",
    "sg:province":"Cremona",
    "sg:tags":[
        "industry",
        "petrochemical",
        "heat",
        "exchanger"
    ],
    "sg:website":"www.villascambiatori.com",
    "wof:name":"Villa Scambiatori Srl",
    "wof:placetype":"venue"
},
  "geometry": {"coordinates":[9.724786,45.347729],"type":"Point"}
}