{
  "type": "Feature",
  "properties": {
    "addr:full":"105, Via Leini 10036 Settimo Torinese Settimo Torinese Torino 10036",
    "addr:housenumber":"105",
    "addr:postcode":"10036;10036",
    "addr:street":"Via Leini",
    "iso:country":"IT",
    "sg:address":"105, Via Leini 10036 Settimo Torinese",
    "sg:city":"Settimo Torinese",
    "sg:classifiers":[
        {
            "category":"Wholesale",
            "subcategory":"Drugs",
            "type":"Manufacturing & Wholesale Goods"
        }
    ],
    "sg:phone":"+39 011 800 1366",
    "sg:postcode":"10036",
    "sg:province":"Torino",
    "sg:tags":[
        "chemical",
        "pharmaceutical"
    ],
    "wof:name":"S.i.c.r.a. (s.r.l.)",
    "wof:placetype":"venue"
},
  "geometry": {"coordinates":[7.746902,45.14423],"type":"Point"}
}