{
  "type": "Feature",
  "properties": {
    "addr:full":"00185 Roma Roma Roma 00185",
    "addr:postcode":"00185;00185",
    "iso:country":"IT",
    "sg:address":"00185 Roma",
    "sg:city":"Roma",
    "sg:orig_category":"Calzature, Pelletterie E Pelli",
    "sg:phone":"+39 06 487 2485",
    "sg:postcode":"00185",
    "sg:province":"Roma",
    "wof:name":"Franco Borse",
    "wof:placetype":"venue"
},
  "geometry": {"coordinates":[12.501813,41.894348],"type":"Point"}
}