{
  "type": "Feature",
  "properties": {
    "iso:country":"IT",
    "sg:address":"5, Via L.b. Alberti 42048 Rubiera",
    "sg:classifiers":[
        {
            "category":"Professional",
            "subcategory":"Engineering",
            "type":"Services"
        }
    ],
    "sg:phone":"+39 0522 628098",
    "sg:postcode":"42048",
    "sg:province":"Reggio Nell'Emilia",
    "sg:tags":[
        "machine",
        "-",
        "mechanical"
    ],
    "wof:name":"Arrow Line S.r.l.",
    "wof:placetype":"venue"
},
  "geometry": {"coordinates":[10.788323,44.656906],"type":"Point"}
}