{
  "type": "Feature",
  "properties": {
    "addr:full":"48100 Ravenna Ravenna Ravenna 48100",
    "addr:housenumber":"48100",
    "addr:postcode":"48100",
    "iso:country":"IT",
    "sg:address":"48100 Ravenna",
    "sg:city":"Ravenna",
    "sg:orig_category":"Antifurto",
    "sg:phone":"+39 0544 67910",
    "sg:postcode":"48100",
    "sg:province":"Ravenna",
    "wof:name":"Siat Sicurezza Di Baldetti Mario & C. Snc",
    "wof:placetype":"venue"
},
  "geometry": {"coordinates":[12.213957,44.263042],"type":"Point"}
}