{
  "type": "Feature",
  "properties": {
    "iso:country":"IT",
    "sg:address":"2, Via Benzoni 46045 Marmirolo",
    "sg:city":"Marmirolo",
    "sg:classifiers":[
        {
            "category":"Autos & Motor Vehicles",
            "subcategory":"Automobile Sales",
            "type":"Retail Goods"
        }
    ],
    "sg:phone":"+39 0376 466686",
    "sg:postcode":"46045",
    "sg:province":"Mantova",
    "sg:tags":[
        "motor-cars"
    ],
    "wof:name":"C.s.p.srl",
    "wof:placetype":"venue"
},
  "geometry": {"coordinates":[10.7621126175,45.2064399719],"type":"Point"}
}