{
  "type": "Feature",
  "properties": {
    "iso:country":"IT",
    "sg:address":"Via Galileo Galilei 1 30033 Noale",
    "sg:city":"Noale",
    "sg:classifiers":[
        {
            "category":"Autos & Motor Vehicles",
            "subcategory":"Motorcycle Sales",
            "type":"Retail Goods"
        }
    ],
    "sg:phone":"+39 041 582 9111",
    "sg:postcode":"30033",
    "sg:province":"Venezia",
    "sg:tags":[
        "bicycle",
        "chain"
    ],
    "sg:website":"www.aprilia.com",
    "wof:name":"Aprilia Spa",
    "wof:placetype":"venue"
},
  "geometry": {"coordinates":[12.071142,45.546444],"type":"Point"}
}