{
  "type": "Feature",
  "properties": {
    "iso:country":"IT",
    "sg:address":"53034 Colle Di Val D'elsa",
    "sg:classifiers":[
        {
            "category":"Restaurant",
            "type":"Food & Drink"
        }
    ],
    "sg:phone":"+39 0577 922854",
    "sg:postcode":"53034",
    "sg:province":"Siena",
    "sg:tags":[
        "auxiliary",
        "entertainment",
        "premises",
        "related",
        "catering",
        "similar",
        "public",
        "restaurants"
    ],
    "wof:name":"Video Action Di Bartalozzi Monica",
    "wof:placetype":"venue"
},
  "geometry": {"coordinates":[11.093808,43.384811],"type":"Point"}
}