{
  "type": "Feature",
  "properties": {
    "iso:country":"IT",
    "sg:address":"97015 Modica",
    "sg:city":"Modica",
    "sg:orig_category":"Torrefazione Di Caffe' Ed Affini - Lavorazione E Ingrosso",
    "sg:phone":"+39 0932 904755",
    "sg:postcode":"97015",
    "sg:province":"Ragusa",
    "sg:website":"http://www.caffemoak.com",
    "wof:name":"Caff\u00c8 Moak Di G. Spadola & C. Sas",
    "wof:placetype":"venue"
},
  "geometry": {"coordinates":[14.770985,36.836376],"type":"Point"}
}