{
  "type": "Feature",
  "properties": {
    "addr:full":"33080 Porcia Porcia Pordenone 33080",
    "addr:postcode":"33080;33080",
    "iso:country":"IT",
    "sg:address":"33080 Porcia",
    "sg:city":"Porcia",
    "sg:orig_category":"Lavorazioni Meccaniche E Servizi",
    "sg:phone":"+39 0434 591234",
    "sg:postcode":"33080",
    "sg:province":"Pordenone",
    "sg:website":"http://www.co-meta.it",
    "wof:name":"I.m.p. Srl",
    "wof:placetype":"venue"
},
  "geometry": {"coordinates":[12.593617,45.958355],"type":"Point"}
}