{
  "type": "Feature",
  "properties": {
    "addr:full":"28010 Veruno Veruno Novara 28010",
    "addr:postcode":"28010;28010",
    "iso:country":"IT",
    "sg:address":"28010 Veruno",
    "sg:city":"Veruno",
    "sg:orig_category":"Prodotti Vari In Metallo",
    "sg:phone":"+39 0322 830167",
    "sg:postcode":"28010",
    "sg:province":"Novara",
    "wof:name":"Arbo Srl",
    "wof:placetype":"venue"
},
  "geometry": {"coordinates":[8.5201530457,45.6932563782],"type":"Point"}
}