{
  "type": "Feature",
  "properties": {
    "iso:country":"IT",
    "sg:address":"66, Via Napoleone Iii 00185 Roma",
    "sg:city":"Roma",
    "sg:classifiers":[
        {
            "category":"Real Estate",
            "subcategory":"Architect",
            "type":"Services"
        }
    ],
    "sg:phone":"+39 390 649 1881",
    "sg:postcode":"00185",
    "sg:province":"Roma",
    "sg:tags":[
        "textile",
        "clothing"
    ],
    "wof:name":"Yu",
    "wof:placetype":"venue"
},
  "geometry": {"coordinates":[12.502727,41.89642],"type":"Point"}
}