{
  "type": "Feature",
  "properties": {
    "addr:full":"54100 Massa Massa Massa-Carrara 54100",
    "addr:postcode":"54100;54100",
    "iso:country":"IT",
    "sg:address":"54100 Massa",
    "sg:city":"Massa",
    "sg:orig_category":"Alberghi E Strutture Extra Alberghiere. Ospedali E Servizi Sanitari",
    "sg:phone":"+39 0585 47703",
    "sg:postcode":"54100",
    "sg:province":"Massa-Carrara",
    "wof:name":"San Carlo Terme & Sorgenti",
    "wof:placetype":"venue"
},
  "geometry": {"coordinates":[10.167402,44.04866],"type":"Point"}
}