{
  "type": "Feature",
  "properties": {
    "iso:country":"IT",
    "sg:address":"20048 Carate Brianza",
    "sg:city":"Carate Brianza",
    "sg:orig_category":"Valvole E Apparecchiature Di Misura",
    "sg:phone":"+39 036 299 1128",
    "sg:postcode":"20048",
    "sg:province":"Milano",
    "wof:name":"Bremer Spa",
    "wof:placetype":"venue"
},
  "geometry": {"coordinates":[9.236983,45.66304],"type":"Point"}
}