{
  "type": "Feature",
  "properties": {
    "iso:country":"IT",
    "sg:address":"Via Della Stazione 3/b, Bolognano, 38062 Arco, Tn",
    "sg:city":"Arco",
    "sg:classifiers":[
        {
            "category":"Banks & Credit Unions",
            "subcategory":"Bank",
            "type":"Services"
        }
    ],
    "sg:postcode":"38062",
    "sg:province":"Trento",
    "wof:name":"Credito Cooperativo Dell'alto Garda Scrl",
    "wof:placetype":"venue"
},
  "geometry": {"coordinates":[10.902238,45.912411],"type":"Point"}
}