{
  "type": "Feature",
  "properties": {
    "addr:full":"85021 Avigliano Avigliano Potenza 85021",
    "addr:postcode":"85021;85021",
    "iso:country":"IT",
    "sg:address":"85021 Avigliano",
    "sg:city":"Avigliano",
    "sg:orig_category":"Carta, Cartone E Prodotti Primari. Forniture Per Uffici",
    "sg:phone":"+39 0971 700666",
    "sg:postcode":"85021",
    "sg:province":"Potenza",
    "wof:name":"Fort James Italia S.r.l.",
    "wof:placetype":"venue"
},
  "geometry": {"coordinates":[15.721277,40.730797],"type":"Point"}
}