{
  "type": "Feature",
  "properties": {
    "addr:full":"155, Viale Europa 50126 Firenze Firenze Firenze 50126",
    "addr:postcode":"50126;50126",
    "addr:street":"Viale Europa",
    "iso:country":"IT",
    "sg:address":"155, Viale Europa 50126 Firenze",
    "sg:city":"Firenze",
    "sg:orig_category":"Miscellaneous Products",
    "sg:phone":"+39 055 681 1859",
    "sg:postcode":"50126",
    "sg:province":"Firenze",
    "wof:name":"Bluetex Co (s.r.l.)",
    "wof:placetype":"venue"
},
  "geometry": {"coordinates":[11.1742086411,43.8183059692],"type":"Point"}
}