{
  "type": "Feature",
  "properties": {
    "addr:full":"20149 Milano Milano Milano 20149",
    "addr:postcode":"20149;20149",
    "iso:country":"IT",
    "sg:address":"20149 Milano",
    "sg:city":"Milano",
    "sg:orig_category":"Prodotti E Manufatti In Materie Plastiche",
    "sg:phone":"+39 02 481 7679",
    "sg:postcode":"20149",
    "sg:province":"Milano",
    "wof:name":"Sitre Societa' Italiana Trasformazione Resine Epossidiche (s.r.l.)",
    "wof:placetype":"venue"
},
  "geometry": {"coordinates":[9.1471719742,45.4691085815],"type":"Point"}
}