{
  "type": "Feature",
  "properties": {
    "iso:country":"IT",
    "sg:address":"51039 Quarrata",
    "sg:city":"Quarrata",
    "sg:orig_category":"Articoli Per Imballaggio E Confezionamento",
    "sg:phone":"+39 0573 737398",
    "sg:postcode":"51039",
    "sg:province":"Pistoia",
    "wof:name":"Bonaccorsi Srl",
    "wof:placetype":"venue"
},
  "geometry": {"coordinates":[10.994006,43.853233],"type":"Point"}
}