{
  "type": "Feature",
  "properties": {
    "addr:full":"30016 Jesolo Venezia 30016",
    "addr:postcode":"30016;30016",
    "iso:country":"IT",
    "sg:address":"30016 Jesolo",
    "sg:orig_category":"Arredo Cucina Ed Elettrodomestici. Frigotecnica, Apparecchiature E Servizi. Elettrodomestici",
    "sg:phone":"+39 0421 971840",
    "sg:postcode":"30016",
    "sg:province":"Venezia",
    "wof:name":"Tiepolo Esterino",
    "wof:placetype":"venue"
},
  "geometry": {"coordinates":[12.613426,45.500233],"type":"Point"}
}