{
  "type": "Feature",
  "properties": {
    "addr:full":"20128 Milano Milano Milano 20128",
    "addr:postcode":"20128;20128",
    "iso:country":"IT",
    "sg:address":"20128 Milano",
    "sg:city":"Milano",
    "sg:orig_category":"Servizi E Lavori Per Industria Alimentare E Bevande",
    "sg:phone":"+39 02 256 7094",
    "sg:postcode":"20128",
    "sg:province":"Milano",
    "wof:name":"Circoli Famigliare Romeo Cerizza (s.r.l.)",
    "wof:placetype":"venue"
},
  "geometry": {"coordinates":[9.247045,45.510006],"type":"Point"}
}