{
  "type": "Feature",
  "properties": {
    "addr:full":"05100 Terni Terni Terni 05100",
    "addr:postcode":"05100;05100",
    "iso:country":"IT",
    "sg:address":"05100 Terni",
    "sg:city":"Terni",
    "sg:orig_category":"Elettrodomestici - Riparazione E Vendita Al Dettaglio Di Accessori",
    "sg:phone":"+39 0744 405310",
    "sg:postcode":"05100",
    "sg:province":"Terni",
    "wof:name":"C.r.e.t. Snc",
    "wof:placetype":"venue"
},
  "geometry": {"coordinates":[12.644587,42.569992],"type":"Point"}
}