{
  "type": "Feature",
  "properties": {
    "iso:country":"IT",
    "sg:address":"20068 Peschiera Borromeo",
    "sg:city":"Peschiera Borromeo",
    "sg:orig_category":"Prodotti Chimici Secondari",
    "sg:phone":"+39 02 547451",
    "sg:postcode":"20068",
    "sg:province":"Milano",
    "wof:name":"Carbodoll S.r.l.",
    "wof:placetype":"venue"
},
  "geometry": {"coordinates":[9.3037433624,45.4392166138],"type":"Point"}
}