{
  "type": "Feature",
  "properties": {
    "iso:country":"IT",
    "sg:address":"20090 Trezzano Sul Naviglio",
    "sg:city":"Trezzano sul Naviglio",
    "sg:orig_category":"Trattamenti Termici E Superficiali Metalli, Galvanotecnica",
    "sg:phone":"+39 02 445 5018",
    "sg:postcode":"20090",
    "sg:province":"Milano",
    "wof:name":"Ossital",
    "wof:placetype":"venue"
},
  "geometry": {"coordinates":[9.04355,45.414169],"type":"Point"}
}