{
  "type": "Feature",
  "properties": {
    "iso:country":"IT",
    "sg:address":"81020 Casapulla",
    "sg:city":"Casapulla",
    "sg:orig_category":"Arredamenti E Mobili Professionali. Arredi Ed Attrezzature Per Attivita' Commerciali Ed Artigianali",
    "sg:phone":"+39 0823 256452",
    "sg:postcode":"81020",
    "sg:province":"Caserta",
    "wof:name":"Studio Design",
    "wof:placetype":"venue"
},
  "geometry": {"coordinates":[14.287869,41.073917],"type":"Point"}
}