{
  "type": "Feature",
  "properties": {
    "addr:full":"136, Via Torino 24030 Pontida Pontida Bergamo 24030",
    "addr:housenumber":"136",
    "addr:postcode":"24030;24030",
    "addr:street":"Via Torino",
    "iso:country":"IT",
    "sg:address":"136, Via Torino 24030 Pontida",
    "sg:city":"Pontida",
    "sg:classifiers":[
        {
            "category":"Manufacturing",
            "subcategory":"Paper Products",
            "type":"Manufacturing & Wholesale Goods"
        }
    ],
    "sg:phone":"+39 39035795056",
    "sg:postcode":"24030",
    "sg:province":"Bergamo",
    "sg:tags":[
        "cardboard"
    ],
    "wof:name":"Fustelgraf S.p.a.",
    "wof:placetype":"venue"
},
  "geometry": {"coordinates":[9.518705368,45.7314605713],"type":"Point"}
}