{
  "type": "Feature",
  "properties": {
    "iso:country":"IT",
    "sg:address":"56, Via Zini Zino 10134 Torino",
    "sg:city":"Torino",
    "sg:classifiers":[
        {
            "category":"Professional",
            "subcategory":"Advertising",
            "type":"Services"
        }
    ],
    "sg:phone":"+39 011 319 5925",
    "sg:postcode":"10134",
    "sg:province":"Torino",
    "sg:tags":[
        "communication",
        "medium"
    ],
    "wof:name":"Photorec Spa",
    "wof:placetype":"venue"
},
  "geometry": {"coordinates":[7.686619,45.07056],"type":"Point"}
}