{
  "type": "Feature",
  "properties": {
    "iso:country":"IT",
    "sg:address":"20134 Milano",
    "sg:city":"Milano",
    "sg:orig_category":"Non-classified Establishments",
    "sg:phone":"+39 02 215 2241",
    "sg:postcode":"20134",
    "sg:province":"Milano",
    "wof:name":"Rosenthal Italia Srl",
    "wof:placetype":"venue"
},
  "geometry": {"coordinates":[9.249043,45.476654],"type":"Point"}
}