{
  "type": "Feature",
  "properties": {
    "addr:full":"Piazza Torelli, 19; Solferino; 46040 Solferino Mantova 46040",
    "addr:housenumber":"19",
    "addr:postcode":"46040;46040",
    "addr:street":"Piazza Torelli;Solferino",
    "iso:country":"IT",
    "sg:address":"Piazza Torelli, 19; Solferino; 46040",
    "sg:city":"Solferino",
    "sg:classifiers":[
        {
            "category":"Banks & Credit Unions",
            "subcategory":"Bank",
            "type":"Services"
        }
    ],
    "sg:phone":"+39 0376 854003",
    "sg:postcode":"46040",
    "sg:province":"Mantova",
    "wof:name":"Banca Agricola Mantovana",
    "wof:placetype":"venue"
},
  "geometry": {"coordinates":[10.566108,45.370079],"type":"Point"}
}