{
  "type": "Feature",
  "properties": {
    "iso:country":"IT",
    "sg:address":"60124 Ancona",
    "sg:city":"Ancona",
    "sg:classifiers":[
        {
            "category":"Travel",
            "subcategory":"Hotels & Motels",
            "type":"Entertainment"
        }
    ],
    "sg:phone":"+39 071 358991",
    "sg:postcode":"60124",
    "sg:province":"Ancona",
    "sg:tags":[
        "hotels",
        "facility"
    ],
    "sg:website":"http://www.marcheturismo.it",
    "wof:name":"Azienda Di Promozione Turistica Regionale",
    "wof:placetype":"venue"
},
  "geometry": {"coordinates":[13.534431,43.614155],"type":"Point"}
}