{
  "type": "Feature",
  "properties": {
    "addr:full":"10098 Rivoli Cascine vica Torino 10098",
    "addr:postcode":"10098;10098",
    "iso:country":"IT",
    "sg:address":"10098 Rivoli",
    "sg:city":"Cascine vica",
    "sg:orig_category":"Apparecchi, Attrezzature E Forniture Per Centri Estetici",
    "sg:phone":"+39 011 957 6467",
    "sg:postcode":"10098",
    "sg:province":"Torino",
    "wof:name":"Soledad Snc Di Rotondo C. & G.",
    "wof:placetype":"venue"
},
  "geometry": {"coordinates":[7.543037,45.073174],"type":"Point"}
}