{
  "type": "Feature",
  "properties": {
    "addr:full":"00047 Marino Marino Roma 00047",
    "addr:postcode":"00047;00047",
    "addr:street":"Marino Roma",
    "iso:country":"IT",
    "sg:address":"00047 Marino",
    "sg:city":"Marino",
    "sg:orig_category":"Forniture Per Agricoltura E Zootecnia. Prodotti Chimici Secondari",
    "sg:phone":"+39 06 938 7042",
    "sg:postcode":"00047",
    "sg:province":"Roma",
    "wof:name":"Vinciguerra Fratelli",
    "wof:placetype":"venue"
},
  "geometry": {"coordinates":[12.6598501205,41.7701721191],"type":"Point"}
}