{
  "type": "Feature",
  "properties": {
    "iso:country":"IT",
    "sg:address":"Cso Cuneo 63 10078 Venaria",
    "sg:classifiers":[
        {
            "category":"Manufacturing",
            "subcategory":"Rubber & Plastics",
            "type":"Manufacturing & Wholesale Goods"
        }
    ],
    "sg:phone":"+39 011 424 1871",
    "sg:postcode":"10078",
    "sg:province":"Torino",
    "sg:tags":[
        "membrane"
    ],
    "sg:website":"www.sigom.it",
    "wof:name":"Sigom Societa' A Responsabilita' Limitata",
    "wof:placetype":"venue"
},
  "geometry": {"coordinates":[7.630929,45.116032],"type":"Point"}
}