{
  "type": "Feature",
  "properties": {
    "addr:full":"92014 Porto Empedocle Porto Empedocle Agrigento 92014",
    "addr:postcode":"92014;92014",
    "iso:country":"IT",
    "sg:address":"92014 Porto Empedocle",
    "sg:city":"Porto Empedocle",
    "sg:orig_category":"Articoli Per Imballaggio E Confezionamento",
    "sg:phone":"+39 0922 530031",
    "sg:postcode":"92014",
    "sg:province":"Agrigento",
    "wof:name":"Siracusa Anna Pia",
    "wof:placetype":"venue"
},
  "geometry": {"coordinates":[13.517593,37.290607],"type":"Point"}
}