{
  "type": "Feature",
  "properties": {
    "addr:full":"Via Primo Villa 17 20040 Burago Di Molgora Burago di Molgora Milano 20040",
    "addr:housenumber":"17",
    "addr:postcode":"20040;20040",
    "addr:street":"Via Primo Villa",
    "iso:country":"IT",
    "sg:address":"Via Primo Villa 17 20040 Burago Di Molgora",
    "sg:city":"Burago di Molgora",
    "sg:classifiers":[
        {
            "category":"Shopping",
            "subcategory":"Clothing, Apparel, & Fashions",
            "type":"Retail Goods"
        }
    ],
    "sg:phone":"+39 039 68761",
    "sg:postcode":"20040",
    "sg:province":"Milano",
    "sg:tags":[
        "sportswear"
    ],
    "sg:website":"www.cemacc.it",
    "wof:name":"Cemacc Srl",
    "wof:placetype":"venue"
},
  "geometry": {"coordinates":[9.374678,45.599998],"type":"Point"}
}