{
  "type": "Feature",
  "properties": {
    "iso:country":"IT",
    "sg:address":"00186 Roma",
    "sg:city":"Roma",
    "sg:orig_category":"Servizi E Lavori Per Agricoltura E Zootecnia",
    "sg:phone":"+39 06 699861",
    "sg:postcode":"00186",
    "sg:province":"Roma",
    "sg:website":"http://www.fitd.it",
    "wof:name":"Fondo Interbancario Di Tutela Dei Depositi",
    "wof:placetype":"venue"
},
  "geometry": {"coordinates":[12.48049,41.89642],"type":"Point"}
}