{
  "type": "Feature",
  "properties": {
    "iso:country":"IT",
    "sg:address":"43100 Parma",
    "sg:city":"Parma",
    "sg:orig_category":"Distributors: Automatici - Commercio E Gestione",
    "sg:phone":"+39 0521 245260",
    "sg:postcode":"43100",
    "sg:province":"Parma",
    "wof:name":"Dap Sirmad Srl",
    "wof:placetype":"venue"
},
  "geometry": {"coordinates":[10.32296,44.7756],"type":"Point"}
}