{
  "type": "Feature",
  "properties": {
    "iso:country":"IT",
    "sg:address":"20146 Milano",
    "sg:city":"Milano",
    "sg:orig_category":"Prodotti Alimentari",
    "sg:phone":"+39 02 474742",
    "sg:postcode":"20146",
    "sg:province":"Milano",
    "wof:name":"Rutigliani Lucia",
    "wof:placetype":"venue"
},
  "geometry": {"coordinates":[9.1468830109,45.4519844055],"type":"Point"}
}