{
  "type": "Feature",
  "properties": {
    "addr:full":"174, Via Maglias 09122 Cagliari Cagliari Cagliari 09122",
    "addr:housenumber":"174",
    "addr:postcode":"09122;09122",
    "addr:street":"Via Maglias",
    "iso:country":"IT",
    "sg:address":"174, Via Maglias 09122 Cagliari",
    "sg:city":"Cagliari",
    "sg:classifiers":[
        {
            "category":"Banks & Credit Unions",
            "subcategory":"Bank",
            "type":"Services"
        }
    ],
    "sg:phone":"+39 39070290500",
    "sg:postcode":"09122",
    "sg:province":"Cagliari",
    "sg:tags":[
        "banking",
        "institution"
    ],
    "wof:name":"Masile",
    "wof:placetype":"venue"
},
  "geometry": {"coordinates":[9.105803,39.230915],"type":"Point"}
}