{
  "type": "Feature",
  "properties": {
    "iso:country":"IT",
    "sg:address":"12/c, V. San Giacomo 22100 Como",
    "sg:city":"Como",
    "sg:classifiers":[
        {
            "category":"Professional",
            "subcategory":"Engineering",
            "type":"Services"
        }
    ],
    "sg:phone":"+39 39031541241",
    "sg:postcode":"22100",
    "sg:province":"Como",
    "sg:tags":[
        "machine",
        "-",
        "mechanical"
    ],
    "sg:website":"http://www.paginegialle.it/rotowashco",
    "wof:name":"Rotowash Snc",
    "wof:placetype":"venue"
},
  "geometry": {"coordinates":[9.042883,45.8326],"type":"Point"}
}