{
  "type": "Feature",
  "properties": {
    "iso:country":"IT",
    "sg:address":"22070 Rovello Porro",
    "sg:city":"Rovello Porro",
    "sg:orig_category":"Cinture E Bretelle",
    "sg:phone":"+39 02 963001",
    "sg:postcode":"22070",
    "sg:province":"Como",
    "sg:website":"http://www.italseta2000.com",
    "wof:name":"Italseta 2000 Srl",
    "wof:placetype":"venue"
},
  "geometry": {"coordinates":[9.041574,45.656113],"type":"Point"}
}