{
  "type": "Feature",
  "properties": {
    "iso:country":"IT",
    "sg:address":"Via Nazionale 1/g 25070 Caino",
    "sg:city":"Caino",
    "sg:classifiers":[
        {
            "category":"Shopping",
            "subcategory":"Computers & Home Electronics",
            "type":"Retail Goods"
        }
    ],
    "sg:phone":"+39 030 683 0121",
    "sg:postcode":"25070",
    "sg:province":"Brescia",
    "sg:tags":[
        "electronic",
        "electrical",
        "equipment"
    ],
    "wof:name":"Italquadri Di Ronchi Felice E C. S.a.s.",
    "wof:placetype":"venue"
},
  "geometry": {"coordinates":[10.309928,45.604652],"type":"Point"}
}