{
  "type": "Feature",
  "properties": {
    "iso:country":"IT",
    "sg:address":"27029 Vigevano",
    "sg:city":"Vigevano",
    "sg:orig_category":"Macchine, Impianti Ed Attrezzature Per Abbigliamento E Pelletterie",
    "sg:phone":"+39 0381 329752",
    "sg:postcode":"27029",
    "sg:province":"Pavia",
    "wof:name":"Due.r Srl",
    "wof:placetype":"venue"
},
  "geometry": {"coordinates":[8.839713,45.30518],"type":"Point"}
}