{
  "type": "Feature",
  "properties": {
    "iso:country":"IT",
    "sg:address":"13100 Vercelli",
    "sg:city":"Vercelli",
    "sg:orig_category":"Macchine, Impianti E Forniture Per Industria Grafica, Cartaria E Cartotecnica",
    "sg:phone":"+39 0161 250565",
    "sg:postcode":"13100",
    "sg:province":"Vercelli",
    "wof:name":"Studio Cardano Di Cardano Simonetta E Cardano Mario - Sviluppo Disegni",
    "wof:placetype":"venue"
},
  "geometry": {"coordinates":[8.413157,45.319042],"type":"Point"}
}