{
  "type": "Feature",
  "properties": {
    "addr:full":"56, Viale Postumia 37069 Villafranca Di Verona Villafranca di Verona Verona 37069",
    "addr:housenumber":"56",
    "addr:postcode":"37069;37069",
    "addr:street":"Viale Postumia;Verona",
    "iso:country":"IT",
    "sg:address":"56, Viale Postumia 37069 Villafranca Di Verona",
    "sg:city":"Villafranca di Verona",
    "sg:classifiers":[
        {
            "category":"Professional",
            "subcategory":"Engineering",
            "type":"Services"
        }
    ],
    "sg:phone":"+39 045 790 0522",
    "sg:postcode":"37069",
    "sg:province":"Verona",
    "sg:tags":[
        "machine",
        "-",
        "mechanical"
    ],
    "wof:name":"Mazzimpianti (s.r.l.)",
    "wof:placetype":"venue"
},
  "geometry": {"coordinates":[10.890113,45.381947],"type":"Point"}
}