{
  "type": "Feature",
  "properties": {
    "iso:country":"IT",
    "sg:address":"Via Bellini, 6; 36078 Valdagno, Vicenza, Italy",
    "sg:city":"Valdagno",
    "sg:classifiers":[
        {
            "category":"Industrial Area",
            "type":"Public Place"
        }
    ],
    "sg:phone":"+39 0445 410000",
    "sg:postcode":"36078",
    "sg:province":"Vicenza",
    "sg:tags":[
        "large",
        "private"
    ],
    "sg:website":"www.jollyhotels.it",
    "wof:name":"Compagnia Italiana Dei Jolly Hotels S.p.a.",
    "wof:placetype":"venue"
},
  "geometry": {"coordinates":[11.540307045,45.5459060669],"type":"Point"}
}