{
  "type": "Feature",
  "properties": {
    "iso:country":"IT",
    "sg:address":"35010 Cadoneghe",
    "sg:city":"Cadoneghe",
    "sg:orig_category":"Materiali E Componenti Elettrotecnici",
    "sg:phone":"+39 049 700485",
    "sg:postcode":"35010",
    "sg:province":"Padova",
    "wof:name":"Multi Contact Italia Srl",
    "wof:placetype":"venue"
},
  "geometry": {"coordinates":[11.903332,45.449146],"type":"Point"}
}