{
  "type": "Feature",
  "properties": {
    "addr:full":"40131 Bologna Bologna Bologna 40131",
    "addr:postcode":"40131;40131",
    "iso:country":"IT",
    "sg:address":"40131 Bologna",
    "sg:city":"Bologna",
    "sg:orig_category":"Imprese Di Costruzioni Civili Ed Industriali. Servizi Ausiliari Di Sorveglianza, Manutenzione E Pulizia",
    "sg:phone":"+39 051 528 5111",
    "sg:postcode":"40131",
    "sg:province":"Bologna",
    "sg:website":"http://www.consorzioagi.com",
    "wof:name":"A.g.i. Srl",
    "wof:placetype":"venue"
},
  "geometry": {"coordinates":[11.326166,44.52528],"type":"Point"}
}