{
  "type": "Feature",
  "properties": {
    "iso:country":"IT",
    "sg:address":"Via Circonvallazione Ovest 54 15048 Valenza",
    "sg:city":"Valenza",
    "sg:classifiers":[
        {
            "category":"Shopping",
            "subcategory":"Jewelry",
            "type":"Retail Goods"
        }
    ],
    "sg:phone":"+39 0131 943129",
    "sg:postcode":"15048",
    "sg:province":"Alessandria",
    "sg:tags":[
        "jewellery",
        "gold"
    ],
    "wof:name":"F.a. Gioielli Srl",
    "wof:placetype":"venue"
},
  "geometry": {"coordinates":[8.632095,45.010262],"type":"Point"}
}