{
  "type": "Feature",
  "properties": {
    "addr:full":"V. Di Gavardina Di Sopra 25011 Calcinato Calcinato Brescia 25011",
    "addr:postcode":"25011;25011",
    "addr:street":"V.",
    "iso:country":"IT",
    "sg:address":"V. Di Gavardina Di Sopra 25011 Calcinato",
    "sg:city":"Calcinato",
    "sg:classifiers":[
        {
            "category":"Autos & Motor Vehicles",
            "subcategory":"Fuel & Gas Station",
            "type":"Retail Goods"
        }
    ],
    "sg:phone":"+39 030 996 4552",
    "sg:postcode":"25011",
    "sg:province":"Brescia",
    "sg:tags":[
        "steel",
        "gray",
        "installation",
        "foundry",
        "cast",
        "iron",
        "casting"
    ],
    "sg:website":"www.diessesrl.com",
    "wof:name":"Diesse Srl",
    "wof:placetype":"venue"
},
  "geometry": {"coordinates":[11.1159410477,45.4183425903],"type":"Point"}
}