{
  "type": "Feature",
  "properties": {
    "addr:full":"20090 Fizzonasco Di Pieve Emanuele Fizzonasco Milano 20090",
    "addr:postcode":"20090;20090",
    "iso:country":"IT",
    "sg:address":"20090 Fizzonasco Di Pieve Emanuele",
    "sg:city":"Fizzonasco",
    "sg:orig_category":"Metalli E Leghe",
    "sg:phone":"+39 02 9072 4591",
    "sg:postcode":"20090",
    "sg:province":"Milano",
    "wof:name":"Ims Spa",
    "wof:placetype":"venue"
},
  "geometry": {"coordinates":[9.1773891449,45.3748512268],"type":"Point"}
}