{
  "type": "Feature",
  "properties": {
    "iso:country":"IT",
    "sg:address":"133/a, Via Flavia Di Stramare 34015 Muggia",
    "sg:city":"Muggia",
    "sg:classifiers":[
        {
            "category":"Farming",
            "subcategory":"Livestock Farm",
            "type":"Manufacturing & Wholesale Goods"
        }
    ],
    "sg:phone":"+39 39040231501",
    "sg:postcode":"34015",
    "sg:province":"Trieste",
    "sg:tags":[
        "agriculture"
    ],
    "wof:name":"Garden Center (s.a.s.)",
    "wof:placetype":"venue"
},
  "geometry": {"coordinates":[13.800437,45.586658],"type":"Point"}
}