{
  "type": "Feature",
  "properties": {
    "addr:full":"124/126c, Via Roma 23855 Pescate Pescate Lecco 23855",
    "addr:housenumber":"124 / 126c",
    "addr:postcode":"23855;23855",
    "addr:street":"Via Roma",
    "iso:country":"IT",
    "sg:address":"124/126c, Via Roma 23855 Pescate",
    "sg:city":"Pescate",
    "sg:classifiers":[
        {
            "category":"Wholesale",
            "subcategory":"Drugs",
            "type":"Manufacturing & Wholesale Goods"
        }
    ],
    "sg:phone":"+39 0341 362509",
    "sg:postcode":"23855",
    "sg:province":"Lecco",
    "sg:tags":[
        "chemical",
        "pharmaceutical"
    ],
    "wof:name":"Colorificio Lecchese (s.r.l.)",
    "wof:placetype":"venue"
},
  "geometry": {"coordinates":[9.395351,45.832069],"type":"Point"}
}