{
  "type": "Feature",
  "properties": {
    "addr:full":"03036 Isola Del Liri Isola del Liri Frosinone 03036",
    "addr:postcode":"03036;03036",
    "iso:country":"IT",
    "sg:address":"03036 Isola Del Liri",
    "sg:city":"Isola del Liri",
    "sg:orig_category":"Videogiochi, Flippers E Biliardini - Vendita Al Dettaglio E Noleggio",
    "sg:phone":"+39 0776 809856",
    "sg:postcode":"03036",
    "sg:province":"Frosinone",
    "wof:name":"Autunno Paolo",
    "wof:placetype":"venue"
},
  "geometry": {"coordinates":[13.570809,41.675613],"type":"Point"}
}