{
  "type": "Feature",
  "properties": {
    "addr:full":"90144 Palermo Palermo Palermo 90144",
    "addr:postcode":"90144;90144",
    "iso:country":"IT",
    "sg:address":"90144 Palermo",
    "sg:city":"Palermo",
    "sg:orig_category":"Fotolito",
    "sg:phone":"+39 091 730 9010",
    "sg:postcode":"90144",
    "sg:province":"Palermo",
    "wof:name":"Pi.gi.emme. Srl Arti Grafiche",
    "wof:placetype":"venue"
},
  "geometry": {"coordinates":[13.3449354172,38.1313247681],"type":"Point"}
}