{
  "type": "Feature",
  "properties": {
    "iso:country":"IT",
    "sg:address":"59100 Prato",
    "sg:city":"Prato",
    "sg:classifiers":[
        {
            "category":"Shopping",
            "subcategory":"Beauty & Cosmetics",
            "type":"Retail Goods"
        }
    ],
    "sg:phone":"+39 0574 36039",
    "sg:postcode":"59100",
    "sg:province":"Prato",
    "sg:tags":[
        "salons",
        "activities",
        "supply",
        "commercial",
        "equipment",
        "artisan",
        "supplies"
    ],
    "wof:name":"Ro.ial. Srl",
    "wof:placetype":"venue"
},
  "geometry": {"coordinates":[11.060285,43.876511],"type":"Point"}
}