{
  "type": "Feature",
  "properties": {
    "iso:country":"IT",
    "sg:address":"42025 Cavriago",
    "sg:orig_category":"Amplificazione Sonora",
    "sg:phone":"+39 0522 941596",
    "sg:postcode":"42025",
    "sg:province":"Reggio Nell'Emilia",
    "sg:website":"http://www.eighteensound.it",
    "wof:name":"Eighteen Sound",
    "wof:placetype":"venue"
},
  "geometry": {"coordinates":[10.627794,44.696228],"type":"Point"}
}