{
  "type": "Feature",
  "properties": {
    "addr:full":"65127 Pescara Pescara Pescara 65127",
    "addr:postcode":"65127;65127",
    "iso:country":"IT",
    "sg:address":"65127 Pescara",
    "sg:city":"Pescara",
    "sg:classifiers":[
        {
            "category":"Utilities",
            "subcategory":"Fuel Oil & Lpg",
            "type":"Services"
        }
    ],
    "sg:phone":"+39 085 45361",
    "sg:postcode":"65127",
    "sg:province":"Pescara",
    "sg:tags":[
        "auxiliary",
        "light",
        "vehicles",
        "gas",
        "water",
        "motor",
        "services",
        "public",
        "transport"
    ],
    "wof:name":"Camera Di Commercio Industria Artigianato E Agricoltura",
    "wof:placetype":"venue"
},
  "geometry": {"coordinates":[14.2161064148,42.4617271423],"type":"Point"}
}