{
  "type": "Feature",
  "properties": {
    "iso:country":"IT",
    "sg:address":"Pizza Xx Settembre 23; Asola",
    "sg:classifiers":[
        {
            "category":"Banks & Credit Unions",
            "subcategory":"Bank",
            "type":"Services"
        }
    ],
    "sg:phone":"+39 0376 710124",
    "wof:name":"Cassa Di Risparmio Di, Parma E Piacenza Spa",
    "wof:placetype":"venue"
},
  "geometry": {"coordinates":[10.414703,45.222038],"type":"Point"}
}