{
  "type": "Feature",
  "properties": {
    "iso:country":"IT",
    "sg:address":"48100 Ravenna",
    "sg:city":"Ravenna",
    "sg:orig_category":"Agenzie D'affari E Servizi Commerciali",
    "sg:phone":"+39 0544 456601",
    "sg:postcode":"48100",
    "sg:province":"Ravenna",
    "wof:name":"Andrini Luca",
    "wof:placetype":"venue"
},
  "geometry": {"coordinates":[12.188546,44.427681],"type":"Point"}
}