{
  "type": "Feature",
  "properties": {
    "iso:country":"IT",
    "sg:address":"63038 Ripatransone",
    "sg:city":"Ripatransone",
    "sg:orig_category":"Elettronica Industriale, Prodotti E Apparecchiature",
    "sg:phone":"+39 0735 90605",
    "sg:postcode":"63038",
    "sg:province":"Ascoli Piceno",
    "sg:website":"http://www.microtelweb.com",
    "wof:name":"Microtel Srl",
    "wof:placetype":"venue"
},
  "geometry": {"coordinates":[13.574977,42.8554],"type":"Point"}
}