{
  "type": "Feature",
  "properties": {
    "addr:full":"17014 Cairo Montenotte Cairo Montenotte Savona 17014",
    "addr:housenumber":"17014",
    "addr:postcode":"17014",
    "iso:country":"IT",
    "sg:address":"17014 Cairo Montenotte",
    "sg:city":"Cairo Montenotte",
    "sg:orig_category":"Legno E Semilavorati",
    "sg:phone":"+39 019 501480",
    "sg:postcode":"17014",
    "sg:province":"Savona",
    "wof:name":"Chinelli Roberto",
    "wof:placetype":"venue"
},
  "geometry": {"coordinates":[8.278477,44.396347],"type":"Point"}
}