{
  "type": "Feature",
  "properties": {
    "addr:full":"119/121, Via Di Rebibbia 00156 Roma Roma Roma 00156",
    "addr:housenumber":"119 / 121",
    "addr:postcode":"00156;00156",
    "addr:street":"Via Di Rebibbia",
    "iso:country":"IT",
    "sg:address":"119/121, Via Di Rebibbia 00156 Roma",
    "sg:city":"Roma",
    "sg:classifiers":[
        {
            "category":"Parking",
            "subcategory":"Lot",
            "type":"Transportation"
        }
    ],
    "sg:phone":"+39 39064073393",
    "sg:postcode":"00156",
    "sg:province":"Roma",
    "sg:tags":[
        "transport",
        "road"
    ],
    "wof:name":"Stein C. Di Arnaldo Righetti",
    "wof:placetype":"venue"
},
  "geometry": {"coordinates":[12.569068,41.927692],"type":"Point"}
}