{
  "type": "Feature",
  "properties": {
    "addr:full":"17, Via Vaccara Luigi 91026 Mazara Del Vallo Mazara del Vallo Trapani 91026",
    "addr:postcode":"91026;91026",
    "addr:street":"Via Vaccara Luigi",
    "iso:country":"IT",
    "sg:address":"17, Via Vaccara Luigi 91026 Mazara Del Vallo",
    "sg:city":"Mazara del Vallo",
    "sg:classifiers":[
        {
            "category":"Shopping",
            "subcategory":"Clothing, Apparel, & Fashions",
            "type":"Retail Goods"
        }
    ],
    "sg:phone":"+39 0923 945633",
    "sg:postcode":"91026",
    "sg:province":"Trapani",
    "sg:tags":[
        "clothes"
    ],
    "wof:name":"I.con.f. S.a.s. Di Messina Rosaria & C.",
    "wof:placetype":"venue"
},
  "geometry": {"coordinates":[12.514634,38.018589],"type":"Point"}
}