{
  "type": "Feature",
  "properties": {
    "iso:country":"IT",
    "sg:address":"00166 Roma",
    "sg:city":"Roma",
    "sg:orig_category":"Ospedali E Servizi Sanitari",
    "sg:phone":"+39 06 6618 0608",
    "sg:postcode":"00166",
    "sg:province":"Roma",
    "wof:name":"Giordanella Perilli Dr. Gabriella",
    "wof:placetype":"venue"
},
  "geometry": {"coordinates":[12.363484,41.873211],"type":"Point"}
}