{
  "type": "Feature",
  "properties": {
    "iso:country":"IT",
    "sg:address":"24122 Bergamo",
    "sg:city":"Bergamo",
    "sg:orig_category":"Accessori Moda D'abbigliamento. Shopping",
    "sg:phone":"+39 035 247669",
    "sg:postcode":"24122",
    "sg:province":"Bergamo",
    "wof:name":"Oldrati Antonietta",
    "wof:placetype":"venue"
},
  "geometry": {"coordinates":[9.665857,45.694897],"type":"Point"}
}