{
  "type": "Feature",
  "properties": {
    "iso:country":"IT",
    "sg:address":"50050 Cerreto Guidi",
    "sg:city":"Cerreto Guidi",
    "sg:classifiers":[
        {
            "category":"Manufacturing",
            "subcategory":"Leather Goods",
            "type":"Manufacturing & Wholesale Goods"
        }
    ],
    "sg:phone":"+39 0571 580301",
    "sg:postcode":"50050",
    "sg:province":"Firenze",
    "sg:tags":[
        "goods",
        "clothing",
        "supply"
    ],
    "wof:name":"Versopelle Di Sorrentino Veronica",
    "wof:placetype":"venue"
},
  "geometry": {"coordinates":[10.880647,43.72282],"type":"Point"}
}