{
  "type": "Feature",
  "properties": {
    "addr:full":"42011 Bagnolo In Piano Reggio Nell'Emilia 42011",
    "addr:postcode":"42011;42011",
    "iso:country":"IT",
    "sg:address":"42011 Bagnolo In Piano",
    "sg:orig_category":"Impiantistica E Prodotti Tecnologici Per Edilizia. Forniture Industriali Per Prevenzione, Controllo E Sicurezza",
    "sg:phone":"+39 0522 952637",
    "sg:postcode":"42011",
    "sg:province":"Reggio Nell'Emilia",
    "wof:name":"F.l. Accessori Snc",
    "wof:placetype":"venue"
},
  "geometry": {"coordinates":[10.673699,44.76445],"type":"Point"}
}