{
  "type": "Feature",
  "properties": {
    "iso:country":"IT",
    "sg:address":"Via Col Dei Pioppi, Sn 63039 San Benedetto Del Tronto",
    "sg:city":"San Benedetto del Tronto",
    "sg:orig_category":"Fine Wire Ropes",
    "sg:phone":"+39 0735 583586",
    "sg:postcode":"63039",
    "sg:province":"Ascoli Piceno",
    "wof:name":"Merlini Giuseppe Dei Fratelli Merlini Snc",
    "wof:placetype":"venue"
},
  "geometry": {"coordinates":[13.5749769211,42.8554000854],"type":"Point"}
}