{
  "type": "Feature",
  "properties": {
    "addr:full":"40128 Bologna Bologna Bologna 40128",
    "addr:postcode":"40128;40128",
    "iso:country":"IT",
    "sg:address":"40128 Bologna",
    "sg:city":"Bologna",
    "sg:orig_category":"Studi E Consulenze Legali E Notarili. Avvocati, Notai E Servizi Legali. Professionisti - Studi E Servizi Ed Associazioni Di Interesse Aziendale",
    "sg:phone":"+39 051 327169",
    "sg:postcode":"40128",
    "sg:province":"Bologna",
    "wof:name":"Baiesi Avv. Carla",
    "wof:placetype":"venue"
},
  "geometry": {"coordinates":[11.358707,44.541992],"type":"Point"}
}