{
  "type": "Feature",
  "properties": {
    "iso:country":"IT",
    "sg:address":"20015 Parabiago",
    "sg:city":"Parabiago",
    "sg:orig_category":"Forniture Per Abbigliamento E Pelletterie",
    "sg:phone":"+39 0331 555534",
    "sg:postcode":"20015",
    "sg:province":"Milano",
    "wof:name":"Beltac Di Tresoldi G.& C. S.n.c.",
    "wof:placetype":"venue"
},
  "geometry": {"coordinates":[9.1874103546,45.4681625366],"type":"Point"}
}