{
  "type": "Feature",
  "properties": {
    "addr:full":"Via Regina 22016 Lenno Lenno Como 22016",
    "addr:postcode":"22016;22016",
    "addr:street":"Via Regina",
    "iso:country":"IT",
    "sg:address":"Via Regina 22016 Lenno",
    "sg:city":"Lenno",
    "sg:classifiers":[
        {
            "category":"Utilities",
            "subcategory":"Electric",
            "type":"Services"
        }
    ],
    "sg:phone":"+39 39034455193",
    "sg:postcode":"22016",
    "sg:province":"Como",
    "sg:tags":[
        "component",
        "electronic"
    ],
    "wof:name":"Electronic News (s.n.c.)",
    "wof:placetype":"venue"
},
  "geometry": {"coordinates":[9.111042,45.866222],"type":"Point"}
}