{
  "type": "Feature",
  "properties": {
    "iso:country":"IT",
    "sg:address":"06012 Citt\u00e0 Di Castello",
    "sg:city":"Cerbara",
    "sg:orig_category":"Abbigliamento - Produzione E Ingrosso",
    "sg:phone":"+39 075 851 1287",
    "sg:postcode":"06012",
    "sg:province":"Perugia",
    "wof:name":"Confezioni Castell Srl",
    "wof:placetype":"venue"
},
  "geometry": {"coordinates":[12.203209,43.502922],"type":"Point"}
}