{
  "type": "Feature",
  "properties": {
    "addr:full":"40010 Sala Bolognese Sala Bolognese Bologna 40010",
    "addr:postcode":"40010;40010",
    "addr:street":"Bolognese",
    "iso:country":"IT",
    "sg:address":"40010 Sala Bolognese",
    "sg:city":"Sala Bolognese",
    "sg:classifiers":[
        {
            "category":"Train Station",
            "subcategory":"Light Rail",
            "type":"Transportation"
        }
    ],
    "sg:phone":"+39 051 681 4225",
    "sg:postcode":"40010",
    "sg:province":"Bologna",
    "sg:tags":[
        "plating",
        "treatments",
        "metals",
        "heat",
        "electroforming",
        "surface"
    ],
    "sg:website":"http://www.informatutto.it/emmeti",
    "wof:name":"Emmeti Srl",
    "wof:placetype":"venue"
},
  "geometry": {"coordinates":[11.2425756454,44.5802497864],"type":"Point"}
}