{
  "type": "Feature",
  "properties": {
    "addr:full":"46100 Mantova Mantova Mantova 46100",
    "addr:postcode":"46100;46100",
    "iso:country":"IT",
    "sg:address":"46100 Mantova",
    "sg:city":"Mantova",
    "sg:orig_category":"Petroli, Gas E Combustibili. Servizi E Lavori Industria Chimica",
    "sg:phone":"+39 0376 326283",
    "sg:postcode":"46100",
    "sg:province":"Mantova",
    "wof:name":"C.l.a.i.p.a.",
    "wof:placetype":"venue"
},
  "geometry": {"coordinates":[10.7927865982,45.1576194763],"type":"Point"}
}