{
  "type": "Feature",
  "properties": {
    "iso:country":"IT",
    "sg:address":"25030 Pompiano",
    "sg:city":"Pompiano",
    "sg:orig_category":"Elettrotecnica Industriale, Prodotti E Apparecchiature",
    "sg:phone":"+39 030 946 0900",
    "sg:postcode":"25030",
    "sg:province":"Brescia",
    "wof:name":"Gi-da Costruzioni Magnetiche Di Girelli - Damini E C. S.n.c.",
    "wof:placetype":"venue"
},
  "geometry": {"coordinates":[10.120727,45.559902],"type":"Point"}
}