{
  "type": "Feature",
  "properties": {
    "iso:country":"IT",
    "sg:address":"55/e, Via San Paolo Dell'uso 47030 Sogliano Al Rubicone",
    "sg:city":"Sogliano al Rubicone",
    "sg:classifiers":[
        {
            "category":"Shopping",
            "subcategory":"Clothing, Apparel, & Fashions",
            "type":"Retail Goods"
        }
    ],
    "sg:phone":"+39 0541 948606",
    "sg:postcode":"47030",
    "sg:province":"Forl\u00ec-Cesena",
    "sg:tags":[
        "clothes"
    ],
    "wof:name":"Tris Confezioni",
    "wof:placetype":"venue"
},
  "geometry": {"coordinates":[11.980461,43.994766],"type":"Point"}
}