{
  "type": "Feature",
  "properties": {
    "addr:full":"Via Torino 1 36063 Marostica Marostica Vicenza 36063",
    "addr:housenumber":"1",
    "addr:postcode":"36063;36063",
    "addr:street":"Via Torino",
    "iso:country":"IT",
    "sg:address":"Via Torino 1 36063 Marostica",
    "sg:city":"Marostica",
    "sg:classifiers":[
        {
            "category":"Train Station",
            "subcategory":"Light Rail",
            "type":"Transportation"
        }
    ],
    "sg:phone":"+39 0424 470930",
    "sg:postcode":"36063",
    "sg:province":"Vicenza",
    "sg:tags":[
        "switch"
    ],
    "sg:website":"www.pizzato.it",
    "wof:name":"Pizzato Elettrica Srl",
    "wof:placetype":"venue"
},
  "geometry": {"coordinates":[11.747228,45.78899],"type":"Point"}
}