{
  "type": "Feature",
  "properties": {
    "addr:full":"20159 Milano Milano Milano 20159",
    "addr:postcode":"20159;20159",
    "iso:country":"IT",
    "sg:address":"20159 Milano",
    "sg:city":"Milano",
    "sg:orig_category":"Prodotti Chimici Secondari. Tempo Libero - Articoli E Forniture. Servizi Per Lo Sport E Il Tempo Libero. Servizi Per Aziende, Manifestazioni E Supporto Agli Scambi Commerciali",
    "sg:phone":"+39 02 608 0373",
    "sg:postcode":"20159",
    "sg:province":"Milano",
    "wof:name":"Bob Caselli Di Gina Caselli",
    "wof:placetype":"venue"
},
  "geometry": {"coordinates":[9.1854066849,45.4875068665],"type":"Point"}
}