{
  "type": "Feature",
  "properties": {
    "iso:country":"IT",
    "sg:address":"24, Via Roma Vigo 38060 Brentonico",
    "sg:city":"Brentonico",
    "sg:classifiers":[
        {
            "category":"Banks & Credit Unions",
            "subcategory":"Bank",
            "type":"Services"
        }
    ],
    "sg:phone":"+39 0464 399399",
    "sg:postcode":"38060",
    "sg:province":"Trento",
    "sg:tags":[
        "banking",
        "institution"
    ],
    "wof:name":"Cassa Rurale Di Brentonico",
    "wof:placetype":"venue"
},
  "geometry": {"coordinates":[11.119053,46.066738],"type":"Point"}
}