{
  "type": "Feature",
  "properties": {
    "addr:full":"65122 Pescara Pescara Pescara 65122",
    "addr:postcode":"65122;65122",
    "iso:country":"IT",
    "sg:address":"65122 Pescara",
    "sg:city":"Pescara",
    "sg:orig_category":"Incisione Metalli E Plastica",
    "sg:phone":"+39 085 421 6775",
    "sg:postcode":"65122",
    "sg:province":"Pescara",
    "wof:name":"Rosati Giorgio Sas",
    "wof:placetype":"venue"
},
  "geometry": {"coordinates":[14.209741,42.47047],"type":"Point"}
}