{
  "type": "Feature",
  "properties": {
    "iso:country":"IT",
    "sg:address":"Via Raffaello Sanzio 5 20090 Cesano Boscone",
    "sg:city":"Cesano Boscone",
    "sg:classifiers":[
        {
            "category":"Shopping",
            "subcategory":"Books",
            "type":"Retail Goods"
        }
    ],
    "sg:phone":"+39 02 458 7971",
    "sg:postcode":"20090",
    "sg:province":"Milano",
    "wof:name":"Eurolitho Spa",
    "wof:placetype":"venue"
},
  "geometry": {"coordinates":[9.102571,45.446518],"type":"Point"}
}