{
  "type": "Feature",
  "properties": {
    "addr:full":"98123 Messina Messina Messina 98123",
    "addr:postcode":"98123;98123",
    "iso:country":"IT",
    "sg:address":"98123 Messina",
    "sg:city":"Messina",
    "sg:orig_category":"Articoli Da Regalo. Arte Ed Artigianato Artistico",
    "sg:phone":"+39 090 663640",
    "sg:postcode":"98123",
    "sg:province":"Messina",
    "sg:website":"http://www.bisazza1888.it",
    "wof:name":"Bisazza 1888",
    "wof:placetype":"venue"
},
  "geometry": {"coordinates":[15.553579,38.184269],"type":"Point"}
}