{
  "type": "Feature",
  "properties": {
    "iso:country":"IT",
    "sg:address":"01021 Acquapendente",
    "sg:city":"Acquapendente",
    "sg:orig_category":"Servizi Vari Di Interesse Pubblico",
    "sg:phone":"+39 0577 779876",
    "sg:postcode":"01021",
    "sg:province":"Viterbo",
    "wof:name":"Demonaco Andrea",
    "wof:placetype":"venue"
},
  "geometry": {"coordinates":[11.866362,42.731392],"type":"Point"}
}