{
  "type": "Feature",
  "properties": {
    "iso:country":"IT",
    "sg:address":"Via Boaria 15 40065 Pianoro",
    "sg:city":"Pianoro",
    "sg:orig_category":"Biodegradable Packaging Machines",
    "sg:phone":"+39 051 652 0911",
    "sg:postcode":"40065",
    "sg:province":"Bologna",
    "wof:name":"O.a.m. 2 Spa",
    "wof:placetype":"venue"
},
  "geometry": {"coordinates":[11.346618,44.408768],"type":"Point"}
}