{
  "type": "Feature",
  "properties": {
    "iso:country":"IT",
    "sg:address":"20093 Cologno Monzese",
    "sg:city":"Cologno Monzese",
    "sg:orig_category":"Servizi E Lavori Industria Della Gomma",
    "sg:phone":"+39 02 2730 1561",
    "sg:postcode":"20093",
    "sg:province":"Milano",
    "wof:name":"Artecnigom S.r.l.",
    "wof:placetype":"venue"
},
  "geometry": {"coordinates":[9.263891,45.534771],"type":"Point"}
}