{
  "type": "Feature",
  "properties": {
    "iso:country":"IT",
    "sg:address":"12, V. San Gregorio 20124 Milano",
    "sg:city":"Milano",
    "sg:classifiers":[
        {
            "category":"Shopping",
            "subcategory":"Gifts & Souvenirs",
            "type":"Retail Goods"
        }
    ],
    "sg:phone":"+39 02 2940 6188",
    "sg:postcode":"20124",
    "sg:province":"Milano",
    "sg:website":"http://www.danjo.it",
    "wof:name":"D'anjo' Promotion Srl",
    "wof:placetype":"venue"
},
  "geometry": {"coordinates":[9.206601,45.478512],"type":"Point"}
}