{
  "type": "Feature",
  "properties": {
    "iso:country":"IT",
    "sg:address":"22, Via Del Mare 45017 Loreo",
    "sg:city":"Loreo",
    "sg:classifiers":[
        {
            "category":"Home & Garden",
            "subcategory":"Home Furnishings",
            "type":"Retail Goods"
        }
    ],
    "sg:phone":"+39 0426 334644",
    "sg:postcode":"45017",
    "sg:province":"Rovigo",
    "sg:tags":[
        "household"
    ],
    "wof:name":"Tecnolegno (s.r.l.)",
    "wof:placetype":"venue"
},
  "geometry": {"coordinates":[12.187442,45.059975],"type":"Point"}
}