{
  "type": "Feature",
  "properties": {
    "addr:full":"26, Via Togliatti Palmiro 20030 Senago Senago Milano 20030",
    "addr:postcode":"20030;20030",
    "addr:street":"Via Togliatti Palmiro",
    "iso:country":"IT",
    "sg:address":"26, Via Togliatti Palmiro 20030 Senago",
    "sg:city":"Senago",
    "sg:classifiers":[
        {
            "category":"Shopping",
            "subcategory":"Computers & Home Electronics",
            "type":"Retail Goods"
        }
    ],
    "sg:phone":"+39 39029988341",
    "sg:postcode":"20030",
    "sg:province":"Milano",
    "sg:tags":[
        "electronic",
        "electrical",
        "equipment"
    ],
    "wof:name":"Baraldi (s.r.l.)",
    "wof:placetype":"venue"
},
  "geometry": {"coordinates":[9.152998,45.574459],"type":"Point"}
}