{
  "type": "Feature",
  "properties": {
    "addr:full":"20122 Milano Milano Milano 20122",
    "addr:postcode":"20122;20122",
    "iso:country":"IT",
    "sg:address":"20122 Milano",
    "sg:city":"Milano",
    "sg:orig_category":"Servizi Editoriali. Servizi Ausiliari Per Il Trasporto",
    "sg:phone":"+39 02 5831 8001",
    "sg:postcode":"20122",
    "sg:province":"Milano",
    "wof:name":"Editoriale Investire Srl",
    "wof:placetype":"venue"
},
  "geometry": {"coordinates":[9.188756,45.456345],"type":"Point"}
}