{
  "type": "Feature",
  "properties": {
    "iso:country":"IT",
    "sg:address":"50, Via Gallarate 21010 Besnate",
    "sg:city":"Besnate",
    "sg:classifiers":[
        {
            "category":"Shopping",
            "subcategory":"Clothing, Apparel, & Fashions",
            "type":"Retail Goods"
        }
    ],
    "sg:phone":"+39 0331 274126",
    "sg:postcode":"21010",
    "sg:province":"Varese",
    "sg:tags":[
        "clothes"
    ],
    "wof:name":"Creazioni Bip Bip (s.r.l.)",
    "wof:placetype":"venue"
},
  "geometry": {"coordinates":[8.771336,45.688156],"type":"Point"}
}