{
  "type": "Feature",
  "properties": {
    "addr:full":"97100 Ragusa Ragusa Ragusa 97100",
    "addr:postcode":"97100;97100",
    "iso:country":"IT",
    "sg:address":"97100 Ragusa",
    "sg:city":"Ragusa",
    "sg:orig_category":"Associazioni Ed Organismi Di Interesse Pubblico",
    "sg:phone":"+39 0932 686165",
    "sg:postcode":"97100",
    "sg:province":"Ragusa",
    "wof:name":"Caruso Antonio",
    "wof:placetype":"venue"
},
  "geometry": {"coordinates":[14.725199,36.915371],"type":"Point"}
}