{
  "type": "Feature",
  "properties": {
    "addr:full":"10128 Torino Torino Torino 10128",
    "addr:postcode":"10128;10128",
    "iso:country":"IT",
    "sg:address":"10128 Torino",
    "sg:city":"Torino",
    "sg:orig_category":"Agenzie Investigative",
    "sg:phone":"+39 011 538315",
    "sg:postcode":"10128",
    "sg:province":"Torino",
    "wof:name":"Holmes Investigazioni Di Costa Carmelina & C. Sas",
    "wof:placetype":"venue"
},
  "geometry": {"coordinates":[7.670603,45.060139],"type":"Point"}
}