{
  "type": "Feature",
  "properties": {
    "addr:full":"59015 Carmignano Carmignano Prato 59015",
    "addr:postcode":"59015;59015",
    "iso:country":"IT",
    "sg:address":"59015 Carmignano",
    "sg:city":"Carmignano",
    "sg:orig_category":"Lavorazioni Meccaniche E Servizi",
    "sg:phone":"+39 055 871 0107",
    "sg:postcode":"59015",
    "sg:province":"Prato",
    "wof:name":"Mecart Di Simone Cei & C Sas",
    "wof:placetype":"venue"
},
  "geometry": {"coordinates":[11.059974,43.794941],"type":"Point"}
}