{
  "type": "Feature",
  "properties": {
    "iso:country":"IT",
    "sg:address":"4, Via Pordenone 20132 Milano",
    "sg:city":"Milano",
    "sg:classifiers":[
        {
            "category":"Professional",
            "subcategory":"Engineering",
            "type":"Services"
        }
    ],
    "sg:phone":"+39 39022154714",
    "sg:postcode":"20132",
    "sg:province":"Milano",
    "sg:tags":[
        "machine",
        "-",
        "mechanical"
    ],
    "wof:name":"Bekaitalia Impianti S.r.l.",
    "wof:placetype":"venue"
},
  "geometry": {"coordinates":[9.233807,45.489853],"type":"Point"}
}