{
  "type": "Feature",
  "properties": {
    "addr:full":"82100 Benevento Benevento Benevento 82100",
    "addr:postcode":"82100;82100",
    "iso:country":"IT",
    "sg:address":"82100 Benevento",
    "sg:city":"Benevento",
    "sg:orig_category":"Ospedali E Servizi Sanitari. Centri Di Estetica E Cosmesi E Servizi",
    "sg:phone":"+39 0824 28376",
    "sg:postcode":"82100",
    "sg:province":"Benevento",
    "wof:name":"Vietri Antonio",
    "wof:placetype":"venue"
},
  "geometry": {"coordinates":[14.774832,41.133255],"type":"Point"}
}