{
  "type": "Feature",
  "properties": {
    "addr:full":"80128 Napoli Napoli Napoli 80128",
    "addr:housenumber":"80128",
    "addr:postcode":"80128",
    "iso:country":"IT",
    "sg:address":"80128 Napoli",
    "sg:city":"Napoli",
    "sg:orig_category":"Medici. Assicurazioni E Servizi Assicurativi. Avvocati, Notai E Servizi Legali. Professionisti - Studi E Servizi Ed Associazioni Di Interesse Aziendale",
    "sg:phone":"+39 081 241 1709",
    "sg:postcode":"80128",
    "sg:province":"Napoli",
    "wof:name":"Costabile Vincenzo",
    "wof:placetype":"venue"
},
  "geometry": {"coordinates":[14.2203226089,40.8461112976],"type":"Point"}
}