{
  "type": "Feature",
  "properties": {
    "addr:full":"20093 Cologno Monzese Cologno Monzese Milano 20093",
    "addr:postcode":"20093;20093",
    "iso:country":"IT",
    "sg:address":"20093 Cologno Monzese",
    "sg:city":"Cologno Monzese",
    "sg:orig_category":"Forniture Per Attivita' Industriali",
    "sg:phone":"+39 02 253 1648",
    "sg:postcode":"20093",
    "sg:province":"Milano",
    "wof:name":"Italcol (s.r.l.)",
    "wof:placetype":"venue"
},
  "geometry": {"coordinates":[9.2795219421,45.5400810242],"type":"Point"}
}