{
  "type": "Feature",
  "properties": {
    "iso:country":"IT",
    "sg:address":"70037 Ruvo Di Puglia",
    "sg:city":"Ruvo di Puglia",
    "sg:classifiers":[
        {
            "category":"Wholesale",
            "subcategory":"Machinery & Supplies",
            "type":"Manufacturing & Wholesale Goods"
        }
    ],
    "sg:phone":"+39 080 360 1675",
    "sg:postcode":"70037",
    "sg:province":"Bari",
    "sg:tags":[
        "activities",
        "industrial"
    ],
    "sg:website":"http://www.tre-d.it",
    "wof:name":"Tre D Srl",
    "wof:placetype":"venue"
},
  "geometry": {"coordinates":[16.464146,41.064796],"type":"Point"}
}