{
  "type": "Feature",
  "properties": {
    "addr:full":"Via Fratelli Cagnoni 19 27029 Vigevano Vigevano Pavia 27029",
    "addr:housenumber":"19",
    "addr:postcode":"27029;27029",
    "addr:street":"Via Fratelli Cagnoni",
    "iso:country":"IT",
    "sg:address":"Via Fratelli Cagnoni 19 27029 Vigevano",
    "sg:city":"Vigevano",
    "sg:orig_category":"Die Cutting Systems For Printed Circuit Boards Pcb",
    "sg:phone":"+39 0381 82358",
    "sg:postcode":"27029",
    "sg:province":"Pavia",
    "sg:website":"www.chisaartorige.com",
    "wof:name":"Chiesa Artorige Srl",
    "wof:placetype":"venue"
},
  "geometry": {"coordinates":[8.853973,45.307663],"type":"Point"}
}