{
  "type": "Feature",
  "properties": {
    "iso:country":"IT",
    "sg:address":"20127 Milano",
    "sg:city":"Milano",
    "sg:orig_category":"Telecomunicazioni E Telefonia, Impianti, Apparecchi E Servizi. Acqua, Luce, Gas E Societa' Di Esercizio Pubblico. Servizi Vari Di Interesse Pubblico",
    "sg:phone":"+39 02 272 9211",
    "sg:postcode":"20127",
    "sg:province":"Milano",
    "wof:name":"Datacom Srl",
    "wof:placetype":"venue"
},
  "geometry": {"coordinates":[9.237919,45.504421],"type":"Point"}
}