{
  "type": "Feature",
  "properties": {
    "iso:country":"IT",
    "sg:address":"25036 Palazzolo Sull'oglio",
    "sg:orig_category":"Accessori Moda D'abbigliamento",
    "sg:phone":"+39 030 730 0469",
    "sg:postcode":"25036",
    "sg:province":"Brescia",
    "wof:name":"V.a.m.p. Di Viola Luigi & C. Snc",
    "wof:placetype":"venue"
},
  "geometry": {"coordinates":[9.891932,45.586918],"type":"Point"}
}