{
  "type": "Feature",
  "properties": {
    "iso:country":"IT",
    "sg:address":"Via Guinizzelli 20 50041 Calenzano",
    "sg:city":"Calenzano",
    "sg:classifiers":[
        {
            "category":"Shopping",
            "subcategory":"Books",
            "type":"Retail Goods"
        }
    ],
    "sg:phone":"+39 055 882 5140",
    "sg:postcode":"50041",
    "sg:province":"Firenze",
    "sg:website":"www.contitipocolor.it",
    "wof:name":"Conti Tipocolor Srl",
    "wof:placetype":"venue"
},
  "geometry": {"coordinates":[11.176449,43.853245],"type":"Point"}
}