{
  "type": "Feature",
  "properties": {
    "iso:country":"IT",
    "sg:address":"70043 Monopoli",
    "sg:city":"Monopoli",
    "sg:orig_category":"Ricambi E Componenti Dei Mezzi Di Trasporto. Riparazione Dei Mezzi Di Trasporto",
    "sg:phone":"+39 080 937 6424",
    "sg:postcode":"70043",
    "sg:province":"Bari",
    "wof:name":"De Martino Gruppo & Demarcar Sas",
    "wof:placetype":"venue"
},
  "geometry": {"coordinates":[17.289976,40.960331],"type":"Point"}
}