{
  "type": "Feature",
  "properties": {
    "iso:country":"IT",
    "sg:address":"37036 San Martino Buon Albergo",
    "sg:city":"San Martino Buon Albergo",
    "sg:orig_category":"Campeggio. Accessori Dei Mezzi Di Trasporto",
    "sg:phone":"+39 045 990073",
    "sg:postcode":"37036",
    "sg:province":"Verona",
    "wof:name":"Racasi Luigi",
    "wof:placetype":"venue"
},
  "geometry": {"coordinates":[11.037227,45.389416],"type":"Point"}
}