{
  "type": "Feature",
  "properties": {
    "addr:full":"Via Predda Niedda Nord 07100 Sassari Sassari Sassari 07100",
    "addr:postcode":"07100;07100",
    "addr:street":"Via Predda Niedda Nord",
    "iso:country":"IT",
    "sg:address":"Via Predda Niedda Nord 07100 Sassari",
    "sg:city":"Sassari",
    "sg:classifiers":[
        {
            "category":"Wholesale",
            "subcategory":"Drugs",
            "type":"Manufacturing & Wholesale Goods"
        }
    ],
    "sg:phone":"+39 39079260522",
    "sg:postcode":"07100",
    "sg:province":"Sassari",
    "sg:tags":[
        "chemical",
        "pharmaceutical"
    ],
    "wof:name":"Transport (s.a.s.)",
    "wof:placetype":"venue"
},
  "geometry": {"coordinates":[8.5538892746,40.7294425964],"type":"Point"}
}