{
  "type": "Feature",
  "properties": {
    "addr:full":"Km. 16,500, S.s. 476 73013 Galatina Galatina Lecce 73013",
    "addr:housenumber":"16,500",
    "addr:postcode":"73013;73013",
    "addr:street":"S.S. 476",
    "iso:country":"IT",
    "sg:address":"Km. 16,500, S.s. 476 73013 Galatina",
    "sg:city":"Galatina",
    "sg:classifiers":[
        {
            "category":"Manufacturing",
            "subcategory":"Metals",
            "type":"Manufacturing & Wholesale Goods"
        }
    ],
    "sg:phone":"+39 0836 561235",
    "sg:postcode":"73013",
    "sg:province":"Lecce",
    "sg:tags":[
        "processing"
    ],
    "sg:website":"http://www.zincogam.it:ws_end: :mark:ws:http://www.paginegialle.it/zincogam",
    "wof:name":"Zincogam Spa",
    "wof:placetype":"venue"
},
  "geometry": {"coordinates":[18.1344451904,40.2374992371],"type":"Point"}
}