{
  "type": "Feature",
  "properties": {
    "addr:full":"00174 Roma Roma Roma 00174",
    "addr:postcode":"00174;00174",
    "iso:country":"IT",
    "sg:address":"00174 Roma",
    "sg:city":"Roma",
    "sg:orig_category":"Carni, Salumi E Pesci. Zootecnia E Pesca, Allevamento Piccoli Animali",
    "sg:phone":"+39 06 723 5462",
    "sg:postcode":"00174",
    "sg:province":"Roma",
    "wof:name":"Nonna Pi' Srl",
    "wof:placetype":"venue"
},
  "geometry": {"coordinates":[12.561311,41.852512],"type":"Point"}
}