{
  "type": "Feature",
  "properties": {
    "iso:country":"IT",
    "sg:address":"7/8, V. Lazzaris 31027 Spresiano",
    "sg:city":"Spresiano",
    "sg:classifiers":[
        {
            "category":"Sports & Exercise",
            "subcategory":"Playing Field",
            "type":"Entertainment"
        }
    ],
    "sg:phone":"+39 0422 887025",
    "sg:postcode":"31027",
    "sg:province":"Treviso",
    "sg:tags":[
        "game"
    ],
    "sg:website":"http://www.paginegialle.it/rondo",
    "wof:name":"Paola Crivellari",
    "wof:placetype":"venue"
},
  "geometry": {"coordinates":[12.263533,45.778652],"type":"Point"}
}