{
  "type": "Feature",
  "properties": {
    "addr:full":"00185 Roma Roma Roma 00185",
    "addr:postcode":"00185;00185",
    "iso:country":"IT",
    "sg:address":"00185 Roma",
    "sg:city":"Roma",
    "sg:orig_category":"Abbigliamento Esterno, Maglierie E Pelliccerie. Calzature, Pelletterie E Pelli",
    "sg:phone":"+39 06 481 4223",
    "sg:postcode":"00185",
    "sg:province":"Roma",
    "wof:name":"Ma.mi.",
    "wof:placetype":"venue"
},
  "geometry": {"coordinates":[12.509727,41.897701],"type":"Point"}
}