{
  "type": "Feature",
  "properties": {
    "addr:full":"25135 Brescia Brescia Brescia 25135",
    "addr:postcode":"25135;25135",
    "iso:country":"IT",
    "sg:address":"25135 Brescia",
    "sg:city":"Brescia",
    "sg:orig_category":"Forniture Per Edilizia E Lavori Pubblici. Forniture Industriali Per Prevenzione, Controllo E Sicurezza",
    "sg:phone":"+39 030 235099",
    "sg:postcode":"25135",
    "sg:province":"Brescia",
    "sg:website":"http://www.sidan.it",
    "wof:name":"Sidan Srl",
    "wof:placetype":"venue"
},
  "geometry": {"coordinates":[10.2857084274,45.5157623291],"type":"Point"}
}