{
  "type": "Feature",
  "properties": {
    "iso:country":"IT",
    "sg:address":"Via Pascoli 17 20090 Vimodrone",
    "sg:city":"Vimodrone",
    "sg:classifiers":[
        {
            "category":"Military Area",
            "subcategory":"Naval Base",
            "type":"Public Place"
        }
    ],
    "sg:phone":"+39 02 250731",
    "sg:postcode":"20090",
    "sg:province":"Milano",
    "sg:tags":[
        "pump",
        "acid"
    ],
    "sg:website":"www.pemo.com",
    "wof:name":"Perissinotto S.p.a.",
    "wof:placetype":"venue"
},
  "geometry": {"coordinates":[9.291013,45.520184],"type":"Point"}
}