{
  "type": "Feature",
  "properties": {
    "iso:country":"IT",
    "sg:address":"09124 Cagliari",
    "sg:city":"Cagliari",
    "sg:orig_category":"Ospedali E Servizi Sanitari. Servizi Sociali",
    "sg:phone":"+39 070 664497",
    "sg:postcode":"09124",
    "sg:province":"Cagliari",
    "wof:name":"Soc. Coop. C.t.r. Primavera",
    "wof:placetype":"venue"
},
  "geometry": {"coordinates":[9.112147,39.212975],"type":"Point"}
}