{
  "type": "Feature",
  "properties": {
    "iso:country":"IT",
    "sg:address":"20010 Ossona",
    "sg:city":"Ossona",
    "sg:orig_category":"Servizi E Lavori Per Abbigliamento E Pelletterie",
    "sg:postcode":"20010",
    "sg:province":"Milano",
    "wof:name":"Tessil Asmonte (s.p.a.)",
    "wof:placetype":"venue"
},
  "geometry": {"coordinates":[9.115293,45.547501],"type":"Point"}
}