{
  "type": "Feature",
  "properties": {
    "iso:country":"IT",
    "sg:address":"20020 Cogliate",
    "sg:city":"Cogliate",
    "sg:orig_category":"Nautica. Automobili E Mezzi Di Trasporto",
    "sg:phone":"+39 02 9646 9289",
    "sg:postcode":"20020",
    "sg:province":"Milano",
    "wof:name":"Gransea Marine Di Hopfgartiner Roberto",
    "wof:placetype":"venue"
},
  "geometry": {"coordinates":[9.082735,45.648964],"type":"Point"}
}