{
  "type": "Feature",
  "properties": {
    "addr:full":"Via Genova 28 29022 Bobbio Bobbio Piacenza 29022",
    "addr:housenumber":"28",
    "addr:postcode":"29022;29022",
    "addr:street":"Via Genova",
    "iso:country":"IT",
    "sg:address":"Via Genova 28 29022 Bobbio",
    "sg:city":"Bobbio",
    "sg:orig_category":"Resistors, Electrical",
    "sg:phone":"+39 0523 932150",
    "sg:postcode":"29022",
    "sg:province":"Piacenza",
    "sg:website":"www.gruppoladirio.it",
    "wof:name":"Carmatech Srl",
    "wof:placetype":"venue"
},
  "geometry": {"coordinates":[9.383416,44.762749],"type":"Point"}
}