{
  "type": "Feature",
  "properties": {
    "iso:country":"IT",
    "sg:address":"81024 Maddaloni",
    "sg:city":"Maddaloni",
    "sg:orig_category":"Suites, Armchairs, Chairs And Tables",
    "sg:phone":"+39 0823 435717",
    "sg:postcode":"81024",
    "sg:province":"Caserta",
    "wof:name":"Mad Sedie Snc",
    "wof:placetype":"venue"
},
  "geometry": {"coordinates":[14.385262,41.037952],"type":"Point"}
}