{
  "type": "Feature",
  "properties": {
    "iso:country":"IT",
    "sg:address":"25136 Brescia",
    "sg:city":"Brescia",
    "sg:orig_category":"Utensili Meccanici E Materiali",
    "sg:phone":"+39 030 201 0678",
    "sg:postcode":"25136",
    "sg:province":"Brescia",
    "wof:name":"L'utensileria Di Beschi Franco E C Sas",
    "wof:placetype":"venue"
},
  "geometry": {"coordinates":[10.228413,45.580883],"type":"Point"}
}