{
  "type": "Feature",
  "properties": {
    "iso:country":"IT",
    "sg:address":"36034 Malo",
    "sg:city":"Malo",
    "sg:orig_category":"Lavorazioni Metalli, Stampaggio E Saldatura",
    "sg:phone":"+39 0445 637020",
    "sg:postcode":"36034",
    "sg:province":"Vicenza",
    "sg:website":"http://www.buzzolan.it",
    "wof:name":"Torneria Fratelli Buzzolan Srl",
    "wof:placetype":"venue"
},
  "geometry": {"coordinates":[11.41788,45.665546],"type":"Point"}
}