{
  "type": "Feature",
  "properties": {
    "iso:country":"IT",
    "sg:address":"Via San Martino 52 22066 Mariano Comense",
    "sg:city":"Mariano Comense",
    "sg:orig_category":"Stamped Articles, Mass Production",
    "sg:phone":"+39 031 749233",
    "sg:postcode":"22066",
    "sg:province":"Como",
    "sg:website":"www.legno-piu.com",
    "wof:name":"Legno Piu' Srl",
    "wof:placetype":"venue"
},
  "geometry": {"coordinates":[9.184642,45.706203],"type":"Point"}
}