{
  "type": "Feature",
  "properties": {
    "iso:country":"IT",
    "sg:address":"20016 Pero",
    "sg:city":"Pero",
    "sg:orig_category":"Hobbistica",
    "sg:phone":"+39 02 3391 0956",
    "sg:postcode":"20016",
    "sg:province":"Milano",
    "wof:name":"Magistroni Alessio Ernesto",
    "wof:placetype":"venue"
},
  "geometry": {"coordinates":[9.089937,45.50893],"type":"Point"}
}