{
  "type": "Feature",
  "properties": {
    "iso:country":"IT",
    "sg:address":"27100 Pavia",
    "sg:city":"Pavia",
    "sg:orig_category":"Manufacturers: Prefabbricati. Impianti E Attrezzature Per Lo Sport E Il Tempo Libero",
    "sg:phone":"+39 0382 302389",
    "sg:postcode":"27100",
    "sg:province":"Pavia",
    "sg:website":"http://web.tiscalinet.it/swimmproject",
    "wof:name":"Swimm Project",
    "wof:placetype":"venue"
},
  "geometry": {"coordinates":[9.074553,45.254559],"type":"Point"}
}