{
  "type": "Feature",
  "properties": {
    "addr:full":"55016 Porcari Porcari Lucca 55016",
    "addr:postcode":"55016;55016",
    "iso:country":"IT",
    "sg:address":"55016 Porcari",
    "sg:city":"Porcari",
    "sg:orig_category":"Fotografia - Servizi, Studi, Sviluppo E Stampa",
    "sg:phone":"+39 0583 211044",
    "sg:postcode":"55016",
    "sg:province":"Lucca",
    "wof:name":"Foto Nadir Srl",
    "wof:placetype":"venue"
},
  "geometry": {"coordinates":[10.3395338058,43.8703804016],"type":"Point"}
}