{
  "type": "Feature",
  "properties": {
    "iso:country":"IT",
    "sg:address":"57021 Campiglia Marittima - Fraz. Venturina",
    "sg:city":"Campiglia Marittima",
    "sg:orig_category":"Acquedotti, Gasdotti Ed Oleodotti - Impianti Ed Attrezzature",
    "sg:phone":"+39 0565 853213",
    "sg:postcode":"57021",
    "sg:province":"Livorno",
    "wof:name":"Cigri Spa",
    "wof:placetype":"venue"
},
  "geometry": {"coordinates":[10.608395,43.038868],"type":"Point"}
}