{
  "type": "Feature",
  "properties": {
    "addr:full":"108, Via Roma 25060 Collebeato Collebeato Brescia 25060",
    "addr:housenumber":"108",
    "addr:postcode":"25060;25060",
    "addr:street":"Via Roma",
    "iso:country":"IT",
    "sg:address":"108, Via Roma 25060 Collebeato",
    "sg:city":"Collebeato",
    "sg:classifiers":[
        {
            "category":"Professional",
            "subcategory":"Engineering",
            "type":"Services"
        }
    ],
    "sg:phone":"+39 030 251 0827",
    "sg:postcode":"25060",
    "sg:province":"Brescia",
    "sg:tags":[
        "machine",
        "-",
        "mechanical"
    ],
    "wof:name":"Mec Sirio S.r.l.",
    "wof:placetype":"venue"
},
  "geometry": {"coordinates":[10.215563,45.578808],"type":"Point"}
}