{
  "type": "Feature",
  "properties": {
    "addr:full":"45024 Fiesso Umbertiano Fiesso Umbertiano Rovigo 45024",
    "addr:postcode":"45024;45024",
    "addr:street":"Umbertiano Rovigo",
    "iso:country":"IT",
    "sg:address":"45024 Fiesso Umbertiano",
    "sg:city":"Fiesso Umbertiano",
    "sg:orig_category":"Servizi Ausiliari Per Il Trasporto. Servizi Vari Di Interesse Pubblico",
    "sg:phone":"+39 0425 754021",
    "sg:postcode":"45024",
    "sg:province":"Rovigo",
    "wof:name":"Fonti Di Bignardi Ermenegildo",
    "wof:placetype":"venue"
},
  "geometry": {"coordinates":[11.597081,44.957932],"type":"Point"}
}