{
  "type": "Feature",
  "properties": {
    "iso:country":"IT",
    "sg:address":"29010 Castelvetro Piacentino",
    "sg:city":"Castelvetro Piacentino",
    "sg:orig_category":"Nautica. Ricambi E Componenti Dei Mezzi Di Trasporto",
    "sg:phone":"+39 0523 824379",
    "sg:postcode":"29010",
    "sg:province":"Piacenza",
    "wof:name":"C.n. Sas Di Arfini Fabio",
    "wof:placetype":"venue"
},
  "geometry": {"coordinates":[10.001153,45.112705],"type":"Point"}
}