{
  "type": "Feature",
  "properties": {
    "addr:full":"70024 Gravina In Puglia Gravina in Puglia Bari 70024",
    "addr:postcode":"70024;70024",
    "iso:country":"IT",
    "sg:address":"70024 Gravina In Puglia",
    "sg:city":"Gravina in Puglia",
    "sg:orig_category":"Consulenza Amministrativa, Fiscale E Tributaria",
    "sg:phone":"+39 080 325 1263",
    "sg:postcode":"70024",
    "sg:province":"Bari",
    "wof:name":"Studio Commerciale Associato Rag. L. Dinicolamaria - Rag. L. Montepeloso",
    "wof:placetype":"venue"
},
  "geometry": {"coordinates":[16.369926,40.842537],"type":"Point"}
}