{
  "type": "Feature",
  "properties": {
    "iso:country":"IT",
    "sg:address":"10, Via Passo Valles 21013 Gallarate",
    "sg:city":"Gallarate",
    "sg:classifiers":[
        {
            "category":"Shopping",
            "subcategory":"Clothing, Apparel, & Fashions",
            "type":"Retail Goods"
        }
    ],
    "sg:phone":"+39 0331 245734",
    "sg:postcode":"21013",
    "sg:province":"Varese",
    "sg:tags":[
        "clothing",
        "accessory"
    ],
    "wof:name":"New Lace Srl",
    "wof:placetype":"venue"
},
  "geometry": {"coordinates":[8.7946,45.68726],"type":"Point"}
}