{
  "type": "Feature",
  "properties": {
    "addr:full":"Pian Di Contro 63021 Amandola Amandola Ascoli Piceno 63021",
    "addr:postcode":"63021;63021",
    "iso:country":"IT",
    "sg:address":"Pian Di Contro 63021 Amandola",
    "sg:city":"Amandola",
    "sg:classifiers":[
        {
            "category":"Food & Beverages",
            "subcategory":"Dairy",
            "type":"Retail Goods"
        }
    ],
    "sg:phone":"+39 0736 847210",
    "sg:postcode":"63021",
    "sg:province":"Ascoli Piceno",
    "sg:tags":[
        "product"
    ],
    "wof:name":"Fattorie Marchigiane Cons.coop.ar.l",
    "wof:placetype":"venue"
},
  "geometry": {"coordinates":[13.574977,42.8554],"type":"Point"}
}