{
  "type": "Feature",
  "properties": {
    "addr:full":"38010 Sanzeno Sanzeno Trento 38010",
    "addr:postcode":"38010;38010",
    "iso:country":"IT",
    "sg:address":"38010 Sanzeno",
    "sg:city":"Sanzeno",
    "sg:orig_category":"Pubblica Amministrazione",
    "sg:phone":"+39 0463 434100",
    "sg:postcode":"38010",
    "sg:province":"Trento",
    "wof:name":"Corpo Volontario Vigili Del Fuoco Di Sanzeno",
    "wof:placetype":"venue"
},
  "geometry": {"coordinates":[11.0391559601,46.3949699402],"type":"Point"}
}