{
  "type": "Feature",
  "properties": {
    "iso:country":"IT",
    "sg:address":"33042 Buttrio",
    "sg:city":"Buttrio",
    "sg:orig_category":"Macchine, Impianti Ed Attrezzature Per Industria Alimentare E Bevande",
    "sg:phone":"+39 0432 673217",
    "sg:postcode":"33042",
    "sg:province":"Udine",
    "wof:name":"Studio Enoagri Di Spitaleri Francesco",
    "wof:placetype":"venue"
},
  "geometry": {"coordinates":[13.331301,46.013634],"type":"Point"}
}