{
  "type": "Feature",
  "properties": {
    "iso:country":"IT",
    "sg:address":"00161 Roma",
    "sg:city":"Roma",
    "sg:orig_category":"Pubblica Amministrazione",
    "sg:phone":"+39 06 440 2217",
    "sg:postcode":"00161",
    "sg:province":"Roma",
    "wof:name":"Regione Umbria",
    "wof:placetype":"venue"
},
  "geometry": {"coordinates":[12.519821167,41.915222168],"type":"Point"}
}