{
  "type": "Feature",
  "properties": {
    "addr:full":"30122 Venezia Castello Venezia 30122",
    "addr:postcode":"30122;30122",
    "iso:country":"IT",
    "sg:address":"30122 Venezia",
    "sg:city":"Castello",
    "sg:orig_category":"Agenzie D'affari E Servizi Commerciali",
    "sg:phone":"+39 041 520 8880",
    "sg:postcode":"30122",
    "sg:province":"Venezia",
    "sg:website":"http://www.casa.it/age/uscotti.htm",
    "wof:name":"Immobiliare Uscotti",
    "wof:placetype":"venue"
},
  "geometry": {"coordinates":[12.343287,45.438637],"type":"Point"}
}