{
  "type": "Feature",
  "properties": {
    "addr:full":"25, Via Giosue' Carducci 24066 Pedrengo Pedrengo Bergamo 24066",
    "addr:postcode":"24066;24066",
    "addr:street":"Via Giosue ' Carducci",
    "iso:country":"IT",
    "sg:address":"25, Via Giosue' Carducci 24066 Pedrengo",
    "sg:city":"Pedrengo",
    "sg:classifiers":[
        {
            "category":"Food & Beverages",
            "subcategory":"Groceries & Convenience Stores",
            "type":"Retail Goods"
        }
    ],
    "sg:phone":"+39 39035664141",
    "sg:postcode":"24066",
    "sg:province":"Bergamo",
    "sg:tags":[
        "drink"
    ],
    "wof:name":"Distillerie Ilas (s.p.a.)",
    "wof:placetype":"venue"
},
  "geometry": {"coordinates":[9.747067,45.694012],"type":"Point"}
}