{
  "type": "Feature",
  "properties": {
    "iso:country":"IT",
    "sg:address":"Viale Belforte 45 21100 Varese",
    "sg:city":"Varese",
    "sg:classifiers":[
        {
            "category":"Retail",
            "subcategory":"Emissions Testing",
            "type":"Services"
        }
    ],
    "sg:phone":"+39 0332 335525",
    "sg:postcode":"21100",
    "sg:province":"Varese",
    "sg:tags":[
        "consumer",
        "good",
        "export"
    ],
    "wof:name":"Wat - Sun Srl",
    "wof:placetype":"venue"
},
  "geometry": {"coordinates":[8.847424,45.815987],"type":"Point"}
}