{
  "type": "Feature",
  "properties": {
    "iso:country":"IT",
    "sg:address":"12053 Castiglione Tinella",
    "sg:city":"Castiglione Tinella",
    "sg:classifiers":[
        {
            "category":"Sports & Exercise",
            "subcategory":"Tennis Court",
            "type":"Entertainment"
        }
    ],
    "sg:phone":"+39 0141 855405",
    "sg:postcode":"12053",
    "sg:province":"Cuneo",
    "sg:tags":[
        "e",
        "lo",
        "tempo",
        "libero",
        "per",
        "impianti",
        "il",
        "attrezzature"
    ],
    "wof:name":"Elettra Service Di Manzo Roberto",
    "wof:placetype":"venue"
},
  "geometry": {"coordinates":[8.189603,44.729675],"type":"Point"}
}