{
  "type": "Feature",
  "properties": {
    "iso:country":"IT",
    "sg:address":"23, Via Cogozzo 25081 Bedizzole",
    "sg:city":"Bedizzole",
    "sg:classifiers":[
        {
            "category":"Manufacturing",
            "subcategory":"Rubber & Plastics",
            "type":"Manufacturing & Wholesale Goods"
        }
    ],
    "sg:phone":"+39 39030674721",
    "sg:postcode":"25081",
    "sg:province":"Brescia",
    "wof:name":"M.z. Zambelli (s.p.a.)",
    "wof:placetype":"venue"
},
  "geometry": {"coordinates":[10.4324712753,45.5136108398],"type":"Point"}
}