{
  "type": "Feature",
  "properties": {
    "iso:country":"IT",
    "sg:address":"Via S. Giovanni 102 33044 Manzano",
    "sg:city":"Manzano",
    "sg:classifiers":[
        {
            "category":"Communications",
            "subcategory":"Television Station",
            "type":"Services"
        }
    ],
    "sg:phone":"+39 0432 755224",
    "sg:postcode":"33044",
    "sg:province":"Udine",
    "sg:tags":[
        "curtain",
        "black-out"
    ],
    "sg:website":"www.tessilconvert.it",
    "wof:name":"Tessil Convert Srl",
    "wof:placetype":"venue"
},
  "geometry": {"coordinates":[13.398383,45.987667],"type":"Point"}
}