{
  "type": "Feature",
  "properties": {
    "iso:country":"IT",
    "sg:address":"20017 Rho",
    "sg:city":"Rho",
    "sg:orig_category":"Materiali E Componenti Elettrotecnici",
    "sg:phone":"+39 02 939 7091",
    "sg:postcode":"20017",
    "sg:province":"Milano",
    "sg:website":"http://www.ceaweb.it",
    "wof:name":"C.e.a. Spa",
    "wof:placetype":"venue"
},
  "geometry": {"coordinates":[9.086823,45.524017],"type":"Point"}
}