{
  "type": "Feature",
  "properties": {
    "addr:full":"36030 Caldogno Caldogno Vicenza 36030",
    "addr:postcode":"36030;36030",
    "iso:country":"IT",
    "sg:address":"36030 Caldogno",
    "sg:city":"Caldogno",
    "sg:orig_category":"Servizi E Lavori Per Agricoltura E Zootecnia",
    "sg:phone":"+39 0444 986535",
    "sg:postcode":"36030",
    "sg:province":"Vicenza",
    "wof:name":"Agromeccanica Faccin Snc Di Faccin Gianni - Gianfranco - Moreno",
    "wof:placetype":"venue"
},
  "geometry": {"coordinates":[11.532738,45.600357],"type":"Point"}
}