{
  "type": "Feature",
  "properties": {
    "addr:full":"21053 Castellanza Castellanza Varese 21053",
    "addr:postcode":"21053;21053",
    "iso:country":"IT",
    "sg:address":"21053 Castellanza",
    "sg:city":"Castellanza",
    "sg:orig_category":"Calzature, Pelletterie E Pelli",
    "sg:phone":"+39 0331 503659",
    "sg:postcode":"21053",
    "sg:province":"Varese",
    "wof:name":"Argopel Snc",
    "wof:placetype":"venue"
},
  "geometry": {"coordinates":[8.836055,45.809528],"type":"Point"}
}