{
  "type": "Feature",
  "properties": {
    "iso:country":"IT",
    "sg:address":"00154 Roma",
    "sg:city":"Roma",
    "sg:orig_category":"Scuole E Servizi Scolastici. Ospedali E Servizi Sanitari",
    "sg:phone":"+39 06 5160 4620",
    "sg:postcode":"00154",
    "sg:province":"Roma",
    "wof:name":"Special Education Service Snc",
    "wof:placetype":"venue"
},
  "geometry": {"coordinates":[12.494729,41.865875],"type":"Point"}
}