{
  "type": "Feature",
  "properties": {
    "iso:country":"IT",
    "sg:address":"18100 Imperia",
    "sg:city":"Imperia",
    "sg:orig_category":"Oli Alimentari E Frantoi Oleari",
    "sg:phone":"+39 0183 293372",
    "sg:postcode":"18100",
    "sg:province":"Imperia",
    "wof:name":"Guardone Paolo",
    "wof:placetype":"venue"
},
  "geometry": {"coordinates":[8.037509,43.895145],"type":"Point"}
}