{
  "type": "Feature",
  "properties": {
    "iso:country":"IT",
    "sg:address":"13, Via Rho 20125 Milano",
    "sg:city":"Milano",
    "sg:classifiers":[
        {
            "category":"Manufacturing",
            "subcategory":"Metals",
            "type":"Manufacturing & Wholesale Goods"
        }
    ],
    "sg:phone":"+39 02 6698 0974",
    "sg:postcode":"20125",
    "sg:province":"Milano",
    "sg:tags":[
        "metallurgy",
        "metalworking"
    ],
    "wof:name":"Generalacciai S.n.c.",
    "wof:placetype":"venue"
},
  "geometry": {"coordinates":[9.0614805222,45.5122756958],"type":"Point"}
}