{
  "type": "Feature",
  "properties": {
    "iso:country":"IT",
    "sg:address":"24060 Bolgare",
    "sg:city":"Bolgare",
    "sg:orig_category":"Abbigliamento Industria - Forniture Ed Accessori",
    "sg:phone":"+39 035 442 3501",
    "sg:postcode":"24060",
    "sg:province":"Bergamo",
    "sg:website":"http://www.ilbottone.it",
    "wof:name":"Il Bottone Di Ranica Terenzio Snc",
    "wof:placetype":"venue"
},
  "geometry": {"coordinates":[9.57219,45.692978],"type":"Point"}
}