{
  "type": "Feature",
  "properties": {
    "iso:country":"IT",
    "sg:address":"24126 Bergamo",
    "sg:city":"Bergamo",
    "sg:classifiers":[
        {
            "category":"Health Services",
            "subcategory":"Health Practitioner",
            "type":"Services"
        }
    ],
    "sg:phone":"+39 035 312093",
    "sg:postcode":"24126",
    "sg:province":"Bergamo",
    "sg:tags":[
        "medici"
    ],
    "wof:name":"Sammarco Agostino",
    "wof:placetype":"venue"
},
  "geometry": {"coordinates":[9.6551141739,45.6543693542],"type":"Point"}
}