{
  "type": "Feature",
  "properties": {
    "iso:country":"IT",
    "sg:address":"55017 Lucca",
    "sg:orig_category":"Motocicli E Motocarri Accessori E Parti - Produzione E Ingrosso",
    "sg:phone":"+39 0583 494670",
    "sg:province":"LU",
    "sg:website":"http://www.planet-h.it",
    "wof:name":"Planet H Di Bianchi Monica E C. Sas",
    "wof:placetype":"venue"
},
  "geometry": {"coordinates":[-93.4459228516,45.6813201904],"type":"Point"}
}