{
  "type": "Feature",
  "properties": {
    "iso:country":"IT",
    "sg:address":"11, Via Colle Ramole 50023 Impruneta",
    "sg:city":"Impruneta",
    "sg:classifiers":[
        {
            "category":"Manufacturing",
            "subcategory":"Metals",
            "type":"Manufacturing & Wholesale Goods"
        }
    ],
    "sg:phone":"+39 055 232 6222",
    "sg:postcode":"50023",
    "sg:province":"Firenze",
    "sg:tags":[
        "metallurgy",
        "metalworking"
    ],
    "wof:name":"L.o.a.m. Srl",
    "wof:placetype":"venue"
},
  "geometry": {"coordinates":[11.2234992981,43.7273101807],"type":"Point"}
}