{
  "type": "Feature",
  "properties": {
    "iso:country":"IT",
    "sg:address":"90143 Palermo",
    "sg:city":"Palermo",
    "sg:orig_category":"Autofficine E Centri Assistenza",
    "sg:phone":"+39 091 625 7492",
    "sg:postcode":"90143",
    "sg:province":"Palermo",
    "wof:name":"Sav Srl",
    "wof:placetype":"venue"
},
  "geometry": {"coordinates":[13.350065,38.141975],"type":"Point"}
}