{
  "type": "Feature",
  "properties": {
    "iso:country":"IT",
    "sg:address":"20, Via Buzzi V. 20017 Rho",
    "sg:city":"Rho",
    "sg:classifiers":[
        {
            "category":"Wholesale",
            "subcategory":"Medical Equipment & Supplies",
            "type":"Manufacturing & Wholesale Goods"
        }
    ],
    "sg:phone":"+39 02 9390 1527",
    "sg:postcode":"20017",
    "sg:province":"Milano",
    "sg:tags":[
        "-",
        "health",
        "instrument"
    ],
    "wof:name":"Ab Medica S.p.a.",
    "wof:placetype":"venue"
},
  "geometry": {"coordinates":[9.087435,45.52499],"type":"Point"}
}