{
  "type": "Feature",
  "properties": {
    "iso:country":"IT",
    "sg:address":"Via S. Franc D'assisi, 15; Collebeato; 25060",
    "sg:city":"Collebeato",
    "sg:classifiers":[
        {
            "category":"Banks & Credit Unions",
            "subcategory":"Bank",
            "type":"Services"
        }
    ],
    "sg:phone":"+39 030 274 1363",
    "sg:postcode":"25060",
    "sg:province":"Brescia",
    "wof:name":"Banca Popolare Di Brescia",
    "wof:placetype":"venue"
},
  "geometry": {"coordinates":[10.211259,45.582203],"type":"Point"}
}