{
  "type": "Feature",
  "properties": {
    "addr:full":"10122 Torino Torino Torino 10122",
    "addr:housenumber":"10122",
    "addr:postcode":"10122",
    "iso:country":"IT",
    "sg:address":"10122 Torino",
    "sg:city":"Torino",
    "sg:orig_category":"Cancelleria",
    "sg:phone":"+39 011 436 6029",
    "sg:postcode":"10122",
    "sg:province":"Torino",
    "wof:name":"Geotecnica Sas",
    "wof:placetype":"venue"
},
  "geometry": {"coordinates":[7.678906,45.075371],"type":"Point"}
}