{
  "type": "Feature",
  "properties": {
    "addr:full":"35026 Conselve Conselve Padova 35026",
    "addr:postcode":"35026;35026",
    "iso:country":"IT",
    "sg:address":"35026 Conselve",
    "sg:city":"Conselve",
    "sg:classifiers":[
        {
            "category":"Retail",
            "subcategory":"Event Space",
            "type":"Services"
        }
    ],
    "sg:phone":"+39 049 950 0864",
    "sg:postcode":"35026",
    "sg:province":"Padova",
    "sg:tags":[
        "articles",
        "product",
        "plastics",
        "publishing",
        "packaging",
        "packing",
        "services",
        "article"
    ],
    "wof:name":"Tramontan Srl",
    "wof:placetype":"venue"
},
  "geometry": {"coordinates":[11.9339170456,45.4003715515],"type":"Point"}
}