{
  "type": "Feature",
  "properties": {
    "iso:country":"IT",
    "sg:address":"Contrada Pisciariello 86095 Sant'elena Sannita",
    "sg:classifiers":[
        {
            "category":"Food & Beverages",
            "subcategory":"Groceries & Convenience Stores",
            "type":"Retail Goods"
        }
    ],
    "sg:phone":"+39 0874 890423",
    "sg:postcode":"86095",
    "sg:province":"Isernia",
    "sg:tags":[
        "drink"
    ],
    "wof:name":"F.lli Di Iorio (s.n.c.)",
    "wof:placetype":"venue"
},
  "geometry": {"coordinates":[14.230827,41.594334],"type":"Point"}
}