{
  "type": "Feature",
  "properties": {
    "iso:country":"IT",
    "sg:address":"38042 Baselga Di Pin\u00e8",
    "sg:orig_category":"Irrigazione - Impianti",
    "sg:phone":"+39 0461 557117",
    "sg:postcode":"38042",
    "sg:province":"Trento",
    "wof:name":"Maiodi Srl",
    "wof:placetype":"venue"
},
  "geometry": {"coordinates":[11.24719,46.136303],"type":"Point"}
}