{
  "type": "Feature",
  "properties": {
    "addr:full":"1, Vl. Europa 70123 Bari Bari Bari 70123",
    "addr:housenumber":"1",
    "addr:postcode":"70123;70123",
    "addr:street":"Vl. Europa",
    "iso:country":"IT",
    "sg:address":"1, Vl. Europa 70123 Bari",
    "sg:city":"Bari",
    "sg:classifiers":[
        {
            "category":"Professional",
            "subcategory":"Engineering",
            "type":"Services"
        }
    ],
    "sg:phone":"+39 080 534 7677",
    "sg:postcode":"70123",
    "sg:province":"Bari",
    "sg:tags":[
        "machine",
        "-",
        "mechanical"
    ],
    "sg:website":"http://www.re-co.it:ws_end: :mark:ws:http://www.paginegialle.it/recoba",
    "wof:name":"Re.co. Srl",
    "wof:placetype":"venue"
},
  "geometry": {"coordinates":[16.83869,41.119865],"type":"Point"}
}