{
  "type": "Feature",
  "properties": {
    "iso:country":"IT",
    "sg:address":"50018 Scandicci",
    "sg:city":"Scandicci",
    "sg:orig_category":"Impianti, Attrezzature E Forniture Sanitarie Ed Ospedaliere",
    "sg:phone":"+39 055 790040",
    "sg:postcode":"50018",
    "sg:province":"Firenze",
    "wof:name":"Baldi Dino Toscana Fongel",
    "wof:placetype":"venue"
},
  "geometry": {"coordinates":[11.14794,43.778378],"type":"Point"}
}