{
  "type": "Feature",
  "properties": {
    "addr:full":"18, Via Waiblingen 91024 Gibellina Gibellina Trapani 91024",
    "addr:postcode":"91024;91024",
    "addr:street":"Via Waiblingen",
    "iso:country":"IT",
    "sg:address":"18, Via Waiblingen 91024 Gibellina",
    "sg:city":"Gibellina",
    "sg:classifiers":[
        {
            "category":"Autos & Motor Vehicles",
            "subcategory":"Automobile Sales",
            "type":"Retail Goods"
        }
    ],
    "sg:phone":"+39 39092467108",
    "sg:postcode":"91024",
    "sg:province":"Trapani",
    "sg:tags":[
        "motor-cars"
    ],
    "wof:name":"Tramonte Domenico",
    "wof:placetype":"venue"
},
  "geometry": {"coordinates":[12.5146341324,38.0185890198],"type":"Point"}
}