{
  "type": "Feature",
  "properties": {
    "iso:country":"IT",
    "sg:address":"21040 Santo Stefano",
    "sg:city":"Santo Stefano",
    "sg:orig_category":"Macchine, Impianti Ed Attrezzature Per Industria Alimentare E Bevande. Elettrodomestici. Macchine E Impianti Per Attivita' Commerciali Ed Artigianali",
    "sg:phone":"+39 0331 739024",
    "sg:postcode":"21040",
    "sg:province":"Varese",
    "wof:name":"Maineri Luciano & C. (s.n.c.)",
    "wof:placetype":"venue"
},
  "geometry": {"coordinates":[8.820679,45.694313],"type":"Point"}
}