{
  "type": "Feature",
  "properties": {
    "iso:country":"IT",
    "sg:address":"50, Via Cane Guido 12055 Diano D'alba",
    "sg:classifiers":[
        {
            "category":"Food & Beverages",
            "subcategory":"Groceries & Convenience Stores",
            "type":"Retail Goods"
        }
    ],
    "sg:phone":"+39 390 173 2222",
    "sg:postcode":"12055",
    "sg:province":"Cuneo",
    "sg:tags":[
        "drink"
    ],
    "wof:name":"Giordano Ferdinando S.p.a.",
    "wof:placetype":"venue"
},
  "geometry": {"coordinates":[7.547111,44.388798],"type":"Point"}
}