{
  "type": "Feature",
  "properties": {
    "iso:country":"IT",
    "sg:address":"30, Via Del Tribunale 05100 Terni",
    "sg:city":"Terni",
    "sg:classifiers":[
        {
            "category":"Banks & Credit Unions",
            "subcategory":"Bank",
            "type":"Services"
        }
    ],
    "sg:phone":"+39 0744 425051",
    "sg:postcode":"05100",
    "sg:province":"Terni",
    "sg:tags":[
        "banking",
        "institution"
    ],
    "wof:name":"C.r.l. Compagnia Regionale Leasing (s.p.a.)",
    "wof:placetype":"venue"
},
  "geometry": {"coordinates":[12.649592,42.56324],"type":"Point"}
}