{
  "type": "Feature",
  "properties": {
    "addr:full":"130, Via Trani 70051 Barletta Barletta Bari 70051",
    "addr:housenumber":"130",
    "addr:postcode":"70051;70051",
    "addr:street":"Via Trani",
    "iso:country":"IT",
    "sg:address":"130, Via Trani 70051 Barletta",
    "sg:city":"Barletta",
    "sg:classifiers":[
        {
            "category":"Personal",
            "subcategory":"Shoe Repair & Shine",
            "type":"Services"
        }
    ],
    "sg:phone":"+39 0883 531309",
    "sg:postcode":"70051",
    "sg:province":"Bari",
    "sg:tags":[
        "leather"
    ],
    "wof:name":"Calzaturificio Rutil (s.r.l.)",
    "wof:placetype":"venue"
},
  "geometry": {"coordinates":[16.316193,41.306427],"type":"Point"}
}