{
  "type": "Feature",
  "properties": {
    "iso:country":"IT",
    "sg:address":"20040 Usmate Velate",
    "sg:city":"Usmate Velate",
    "sg:orig_category":"Articoli Da Regalo. Arte Ed Artigianato Artistico. Shopping",
    "sg:phone":"+39 039 607 6606",
    "sg:postcode":"20040",
    "sg:province":"Milano",
    "sg:website":"http://www.tiche.it",
    "wof:name":"Tiche",
    "wof:placetype":"venue"
},
  "geometry": {"coordinates":[9.365093,45.652458],"type":"Point"}
}