{
  "type": "Feature",
  "properties": {
    "addr:full":"Zona Industriale Mazzocchio 04014 Pontinia Pontinia Latina 04014",
    "addr:postcode":"04014;04014",
    "addr:street":"Zona Industriale Mazzocchio",
    "iso:country":"IT",
    "sg:address":"Zona Industriale Mazzocchio 04014 Pontinia",
    "sg:city":"Pontinia",
    "sg:classifiers":[
        {
            "category":"Military Area",
            "subcategory":"Air Force Base",
            "type":"Public Place"
        }
    ],
    "sg:phone":"+39 0773 8421",
    "sg:postcode":"04014",
    "sg:province":"Latina",
    "sg:tags":[
        "box",
        "aluminium"
    ],
    "sg:website":"www.saiac.com",
    "wof:name":"Europack Spa",
    "wof:placetype":"venue"
},
  "geometry": {"coordinates":[12.9037,41.467598],"type":"Point"}
}