{
  "type": "Feature",
  "properties": {
    "addr:full":"00184 Roma Roma Roma 00184",
    "addr:postcode":"00184;00184",
    "iso:country":"IT",
    "sg:address":"00184 Roma",
    "sg:city":"Roma",
    "sg:orig_category":"Agenzie Ed Enti Turistici. Acqua, Luce, Gas E Societa' Di Esercizio Pubblico",
    "sg:phone":"+39 06 488 0267",
    "sg:postcode":"00184",
    "sg:province":"Roma",
    "wof:name":"Ente Turistico Romania",
    "wof:placetype":"venue"
},
  "geometry": {"coordinates":[12.486156,41.821774],"type":"Point"}
}