{
  "type": "Feature",
  "properties": {
    "iso:country":"IT",
    "sg:address":"59100 Prato",
    "sg:city":"Prato",
    "sg:orig_category":"Prodotti Alimentari. Bevande, Vini E Liquori. Medicinali E Prodotti Parafarmaceutici",
    "sg:phone":"+39 0574 550559",
    "sg:postcode":"59100",
    "sg:province":"Prato",
    "wof:name":"Vitamin Store",
    "wof:placetype":"venue"
},
  "geometry": {"coordinates":[11.0938081741,43.8780326843],"type":"Point"}
}