{
  "type": "Feature",
  "properties": {
    "iso:country":"IT",
    "sg:address":"Via Berlino 6 24040 Zingonia",
    "sg:city":"Zingonia",
    "sg:classifiers":[
        {
            "category":"Health Services",
            "subcategory":"Nursing And Care Facility",
            "type":"Services"
        }
    ],
    "sg:phone":"+39 035 883122",
    "sg:postcode":"24040",
    "sg:province":"Bergamo",
    "sg:tags":[
        "equipment",
        "hospital",
        "clinic",
        "rehabilitation"
    ],
    "sg:website":"www.metalarredinox.it",
    "wof:name":"Metalarredinox Spa",
    "wof:placetype":"venue"
},
  "geometry": {"coordinates":[9.613541,45.595383],"type":"Point"}
}