{
  "type": "Feature",
  "properties": {
    "addr:full":"95131 Catania Catania Catania 95131",
    "addr:postcode":"95131;95131",
    "iso:country":"IT",
    "sg:address":"95131 Catania",
    "sg:city":"Catania",
    "sg:orig_category":"Servizi E Lavori Per Industria Alimentare E Bevande. Servizi E Lavori Per Abbigliamento E Pelletterie. Servizi E Lavori Per Arredamento E Industria Del Legno",
    "sg:phone":"+39 095 532255",
    "sg:postcode":"95131",
    "sg:province":"Catania",
    "wof:name":"Despar",
    "wof:placetype":"venue"
},
  "geometry": {"coordinates":[15.097772,37.509651],"type":"Point"}
}