{
  "type": "Feature",
  "properties": {
    "iso:country":"IT",
    "sg:address":"25045 Castegnato",
    "sg:city":"Castegnato",
    "sg:orig_category":"Petroli, Gas E Combustibili. Materiali Edili",
    "sg:phone":"+39 030 272 1141",
    "sg:postcode":"25045",
    "sg:province":"Brescia",
    "wof:name":"Bettoni Spa",
    "wof:placetype":"venue"
},
  "geometry": {"coordinates":[10.1104946136,45.5520896912],"type":"Point"}
}