{
  "type": "Feature",
  "properties": {
    "addr:full":"28010 Briga Novarese Briga Novarese Novara 28010",
    "addr:postcode":"28010;28010",
    "iso:country":"IT",
    "sg:address":"28010 Briga Novarese",
    "sg:city":"Briga Novarese",
    "sg:orig_category":"Antifurto",
    "sg:phone":"+39 0322 955275",
    "sg:postcode":"28010",
    "sg:province":"Novara",
    "sg:website":"http://www.duegiantifurto.com",
    "wof:name":"Duegi Antifurto Di Giacomini Roberto",
    "wof:placetype":"venue"
},
  "geometry": {"coordinates":[8.450604,45.732738],"type":"Point"}
}