{
  "type": "Feature",
  "properties": {
    "iso:country":"IT",
    "sg:address":"3/5, V. Caduti Del Lavoro 43058 Sorbolo",
    "sg:city":"Sorbolo",
    "sg:classifiers":[
        {
            "category":"Professional",
            "subcategory":"Engineering",
            "type":"Services"
        }
    ],
    "sg:phone":"+39 0521 664074",
    "sg:postcode":"43058",
    "sg:province":"Parma",
    "sg:tags":[
        "machine",
        "-",
        "mechanical"
    ],
    "sg:website":"http://www.paginegialle.it/movi-pr",
    "wof:name":"Movi Alluminium Srl",
    "wof:placetype":"venue"
},
  "geometry": {"coordinates":[10.401526,44.830971],"type":"Point"}
}