{
  "type": "Feature",
  "properties": {
    "addr:full":"Corso Xxv Aprile 64; Erba; 22036 Erba Como 22036",
    "addr:housenumber":"64",
    "addr:postcode":"22036;22036",
    "addr:street":"Corso Xxv Aprile",
    "iso:country":"IT",
    "sg:address":"Corso Xxv Aprile 64; Erba; 22036",
    "sg:city":"Erba",
    "sg:classifiers":[
        {
            "category":"Banks & Credit Unions",
            "subcategory":"Bank",
            "type":"Services"
        }
    ],
    "sg:phone":"+39 031 641041",
    "sg:postcode":"22036",
    "sg:province":"Como",
    "wof:name":"Istituto Bancario, San Paolo Di Torino Spa",
    "wof:placetype":"venue"
},
  "geometry": {"coordinates":[9.217548,45.803574],"type":"Point"}
}