{
  "type": "Feature",
  "properties": {
    "iso:country":"IT",
    "sg:address":"00198 Roma",
    "sg:city":"Roma",
    "sg:orig_category":"Shopping. Prodotti Cosmetici E Da Toeletta",
    "sg:phone":"+39 06 440 2266",
    "sg:postcode":"00198",
    "sg:province":"Roma",
    "wof:name":"Gaudio Dr. Giorgio",
    "wof:placetype":"venue"
},
  "geometry": {"coordinates":[12.447337,42.105598],"type":"Point"}
}