{
  "type": "Feature",
  "properties": {
    "addr:full":"80075 Forio Forio Napoli 80075",
    "addr:postcode":"80075;80075",
    "iso:country":"IT",
    "sg:address":"80075 Forio",
    "sg:city":"Forio",
    "sg:orig_category":"Non-classified Establishments",
    "sg:phone":"+39 081 997399",
    "sg:postcode":"80075",
    "sg:province":"Napoli",
    "wof:name":"Portovecchio Di Monica Pieraccini",
    "wof:placetype":"venue"
},
  "geometry": {"coordinates":[14.242155,40.858692],"type":"Point"}
}