{
  "type": "Feature",
  "properties": {
    "addr:full":"80045 Pompei Pompei Napoli 80045",
    "addr:housenumber":"80045",
    "addr:postcode":"80045",
    "iso:country":"IT",
    "sg:address":"80045 Pompei",
    "sg:city":"Pompei",
    "sg:orig_category":"Distributors: Carburanti E Stazioni Di Servizio",
    "sg:phone":"+39 081 859 0386",
    "sg:postcode":"80045",
    "sg:province":"Napoli",
    "wof:name":"Meridional Gpl Srl",
    "wof:placetype":"venue"
},
  "geometry": {"coordinates":[14.509755,40.744186],"type":"Point"}
}