{
  "type": "Feature",
  "properties": {
    "addr:full":"31040 Volpago Del Montello Volpago del Montello Treviso 31040",
    "addr:housenumber":"del montello",
    "addr:postcode":"31040;31040",
    "addr:street":"Del Montello",
    "iso:country":"IT",
    "sg:address":"31040 Volpago Del Montello",
    "sg:city":"Volpago del Montello",
    "sg:orig_category":"Impiantistica E Prodotti Tecnologici Per Edilizia. Orologeria",
    "sg:phone":"+39 0423 620272",
    "sg:postcode":"31040",
    "sg:province":"Treviso",
    "wof:name":"Comin S.n.c. Di Comin Andrea & C.",
    "wof:placetype":"venue"
},
  "geometry": {"coordinates":[12.110387,45.775833],"type":"Point"}
}