{
  "type": "Feature",
  "properties": {
    "iso:country":"IT",
    "sg:address":"Via Burlin 37014 Castelnuovo Del Garda",
    "sg:city":"Castelnuovo del Garda",
    "sg:classifiers":[
        {
            "category":"Shopping",
            "subcategory":"Clothing, Apparel, & Fashions",
            "type":"Retail Goods"
        }
    ],
    "sg:phone":"+39 045 757 0080",
    "sg:postcode":"37014",
    "sg:province":"Verona",
    "sg:tags":[
        "clothes"
    ],
    "wof:name":"Miele Italia S.r.l. A Socio Unico",
    "wof:placetype":"venue"
},
  "geometry": {"coordinates":[10.736689,45.437019],"type":"Point"}
}