{
  "type": "Feature",
  "properties": {
    "iso:country":"IT",
    "sg:address":"97014 Ispica",
    "sg:city":"Ispica",
    "sg:orig_category":"Ferro Battuto",
    "sg:phone":"+39 0932 950316",
    "sg:postcode":"97014",
    "sg:province":"Ragusa",
    "wof:name":"Monica F.lli Snc",
    "wof:placetype":"venue"
},
  "geometry": {"coordinates":[14.9272041321,36.7656059265],"type":"Point"}
}