{
  "type": "Feature",
  "properties": {
    "iso:country":"IT",
    "sg:address":"Via Vallone 95024 Acireale",
    "sg:city":"Acireale",
    "sg:classifiers":[
        {
            "category":"Farming",
            "subcategory":"Livestock Farm",
            "type":"Manufacturing & Wholesale Goods"
        }
    ],
    "sg:phone":"+39 39095877650",
    "sg:postcode":"95024",
    "sg:province":"Catania",
    "sg:tags":[
        "agriculture"
    ],
    "wof:name":"Conagrus",
    "wof:placetype":"venue"
},
  "geometry": {"coordinates":[15.166493,37.586353],"type":"Point"}
}