{
  "type": "Feature",
  "properties": {
    "addr:full":"70122 Bari Bari Bari 70122",
    "addr:postcode":"70122;70122",
    "iso:country":"IT",
    "sg:address":"70122 Bari",
    "sg:city":"Bari",
    "sg:orig_category":"Agenzie Marittime",
    "sg:phone":"+39 080 524 1830",
    "sg:postcode":"70122",
    "sg:province":"Bari",
    "sg:website":"http://www.inmedia.it/canzano",
    "wof:name":"Canzano & C. Srl",
    "wof:placetype":"venue"
},
  "geometry": {"coordinates":[16.866514,41.12886],"type":"Point"}
}