{
  "type": "Feature",
  "properties": {
    "iso:country":"IT",
    "sg:address":"15, Via Matteotti 20018 Sedriano",
    "sg:city":"Sedriano",
    "sg:classifiers":[
        {
            "category":"Professional",
            "subcategory":"Engineering",
            "type":"Services"
        }
    ],
    "sg:phone":"+39 02 9031 9174",
    "sg:postcode":"20018",
    "sg:province":"Milano",
    "sg:tags":[
        "machine",
        "-",
        "mechanical"
    ],
    "wof:name":"Pigliafreddo",
    "wof:placetype":"venue"
},
  "geometry": {"coordinates":[9.023834,45.494099],"type":"Point"}
}