{
  "type": "Feature",
  "properties": {
    "addr:full":"19020 Borghetto Vara La Spezia 19020",
    "addr:postcode":"19020;19020",
    "iso:country":"IT",
    "sg:address":"19020 Borghetto Vara",
    "sg:classifiers":[
        {
            "category":"Travel",
            "subcategory":"Hotels & Motels",
            "type":"Entertainment"
        }
    ],
    "sg:phone":"+39 0187 897421",
    "sg:postcode":"19020",
    "sg:province":"La Spezia",
    "sg:tags":[
        "hotels",
        "facility"
    ],
    "wof:name":"Locanda Belsole Snc",
    "wof:placetype":"venue"
},
  "geometry": {"coordinates":[9.768876,44.194141],"type":"Point"}
}