{
  "type": "Feature",
  "properties": {
    "iso:country":"IT",
    "sg:address":"36100 Vicenza",
    "sg:city":"Vicenza",
    "sg:orig_category":"Macchine, Impianti Ed Attrezzature Industria Chimica. Macchine Ed Impianti Per Edilizia E Lavori Pubblici",
    "sg:phone":"+39 0444 569360",
    "sg:postcode":"36100",
    "sg:province":"Vicenza",
    "sg:website":"http://www.pegoraro.it",
    "wof:name":"Pegoraro Srl",
    "wof:placetype":"venue"
},
  "geometry": {"coordinates":[11.561045,45.53619],"type":"Point"}
}