{
  "type": "Feature",
  "properties": {
    "addr:full":"41100 Modena Modena Modena 41100",
    "addr:postcode":"41100;41100",
    "iso:country":"IT",
    "sg:address":"41100 Modena",
    "sg:city":"Modena",
    "sg:orig_category":"Prodotti E Manufatti In Materie Plastiche. Forniture Per Attivita' Industriali",
    "sg:phone":"+39 059 253244",
    "sg:postcode":"41100",
    "sg:province":"Modena",
    "wof:name":"Co.m.a.t. Srl",
    "wof:placetype":"venue"
},
  "geometry": {"coordinates":[10.961268425,44.6541366577],"type":"Point"}
}