{
  "type": "Feature",
  "properties": {
    "iso:country":"IT",
    "sg:address":"80044 Ottaviano",
    "sg:city":"Ottaviano",
    "sg:orig_category":"Biancheria, Telerie E Coperte. Arredo Camera Letto E Complementi",
    "sg:phone":"+39 081 529 4368",
    "sg:postcode":"80044",
    "sg:province":"Napoli",
    "wof:name":"Allotex Srl",
    "wof:placetype":"venue"
},
  "geometry": {"coordinates":[14.489715,40.83176],"type":"Point"}
}