{
  "type": "Feature",
  "properties": {
    "iso:country":"IT",
    "sg:address":"101/103, Via Chieri 10022 Carmagnola",
    "sg:city":"Carmagnola",
    "sg:classifiers":[
        {
            "category":"Manufacturing",
            "subcategory":"Metals",
            "type":"Manufacturing & Wholesale Goods"
        }
    ],
    "sg:phone":"+39 011 972 6111",
    "sg:postcode":"10022",
    "sg:province":"Torino",
    "sg:tags":[
        "processing"
    ],
    "wof:name":"I.m.c. S.r.l.",
    "wof:placetype":"venue"
},
  "geometry": {"coordinates":[7.7258825302,44.8687782288],"type":"Point"}
}