{
  "type": "Feature",
  "properties": {
    "iso:country":"IT",
    "sg:address":"Viale Unita D'italia, 11; Altavilla Vicentina; 15041",
    "sg:classifiers":[
        {
            "category":"Banks & Credit Unions",
            "subcategory":"Bank",
            "type":"Services"
        }
    ],
    "sg:phone":"+39 0142 926148",
    "sg:postcode":"15041",
    "sg:province":"Alessandria",
    "wof:name":"Banca Popolare Di Novara",
    "wof:placetype":"venue"
},
  "geometry": {"coordinates":[8.368602,44.997414],"type":"Point"}
}