{
  "type": "Feature",
  "properties": {
    "iso:country":"IT",
    "sg:address":"Via Badia 8 56030 Terricciola",
    "sg:city":"Terricciola",
    "sg:classifiers":[
        {
            "category":"Wholesale",
            "subcategory":"Fruits & Vegetables",
            "type":"Manufacturing & Wholesale Goods"
        }
    ],
    "sg:phone":"+39 0587 658505",
    "sg:postcode":"56030",
    "sg:province":"Pisa",
    "sg:tags":[
        "product",
        "cereal"
    ],
    "wof:name":"Agricola Fondiaria Ligure Toscana Spa",
    "wof:placetype":"venue"
},
  "geometry": {"coordinates":[10.651364,43.536228],"type":"Point"}
}