{
  "type": "Feature",
  "properties": {
    "addr:full":"29027 Podenzano Podenzano Piacenza 29027",
    "addr:postcode":"29027;29027",
    "iso:country":"IT",
    "sg:address":"29027 Podenzano",
    "sg:city":"Podenzano",
    "sg:orig_category":"Manufacturers: Prefabbricati",
    "sg:phone":"+39 0523 524099",
    "sg:postcode":"29027",
    "sg:province":"Piacenza",
    "wof:name":"Metalcentro Edile (s.r.l.)",
    "wof:placetype":"venue"
},
  "geometry": {"coordinates":[9.68783,44.998043],"type":"Point"}
}