{
  "type": "Feature",
  "properties": {
    "addr:full":"40128 Bologna Bologna Bologna 40128",
    "addr:postcode":"40128;40128",
    "iso:country":"IT",
    "sg:address":"40128 Bologna",
    "sg:city":"Bologna",
    "sg:orig_category":"Elettronica Professionale E Di Consumo. Musica",
    "sg:phone":"+39 051 415 7374",
    "sg:postcode":"40128",
    "sg:province":"Bologna",
    "sg:website":"http://www.digitalhouse.bo.it",
    "wof:name":"Digital House Snc Di Buttieri & C.",
    "wof:placetype":"venue"
},
  "geometry": {"coordinates":[11.363979,44.529026],"type":"Point"}
}