{
  "type": "Feature",
  "properties": {
    "iso:country":"IT",
    "sg:address":"20145 Milano",
    "sg:city":"Milano",
    "sg:orig_category":"Chiese Ed Associazioni Religiose",
    "sg:phone":"+39 02 498 6832",
    "sg:postcode":"20145",
    "sg:province":"Milano",
    "wof:name":"Padri Gesuiti",
    "wof:placetype":"venue"
},
  "geometry": {"coordinates":[9.163506,45.474083],"type":"Point"}
}