{
  "type": "Feature",
  "properties": {
    "addr:full":"10138 Torino Torino Torino 10138",
    "addr:housenumber":"10138",
    "addr:postcode":"10138",
    "iso:country":"IT",
    "sg:address":"10138 Torino",
    "sg:city":"Torino",
    "sg:orig_category":"Servizi Editoriali. Shopping",
    "sg:phone":"+39 011 434 3257",
    "sg:postcode":"10138",
    "sg:province":"Torino",
    "wof:name":"Bernardis Antichita'",
    "wof:placetype":"venue"
},
  "geometry": {"coordinates":[7.665691,45.073048],"type":"Point"}
}