{
  "type": "Feature",
  "properties": {
    "iso:country":"IT",
    "sg:address":"30016 Jesolo",
    "sg:orig_category":"Cine-foto-ottica. Shopping",
    "sg:phone":"+39 0421 380700",
    "sg:postcode":"30016",
    "sg:province":"Venezia",
    "wof:name":"Roadhouse Sas",
    "wof:placetype":"venue"
},
  "geometry": {"coordinates":[12.651593,45.509335],"type":"Point"}
}