{
  "type": "Feature",
  "properties": {
    "addr:full":"36, Strada Gianturco Emanuele 80055 Portici Portici Napoli 80055",
    "addr:postcode":"80055;80055",
    "addr:street":"Strada Gianturco Emanuele",
    "iso:country":"IT",
    "sg:address":"36, Strada Gianturco Emanuele 80055 Portici",
    "sg:city":"Portici",
    "sg:classifiers":[
        {
            "category":"Building & Trades",
            "subcategory":"Construction",
            "type":"Services"
        }
    ],
    "sg:phone":"+39 39081273978",
    "sg:postcode":"80055",
    "sg:province":"Napoli",
    "sg:tags":[
        "work",
        "public"
    ],
    "wof:name":"C.i.s. Costruzioni Industriali E Stradali Dell'ing. Miele A.",
    "wof:placetype":"venue"
},
  "geometry": {"coordinates":[14.335834,40.812954],"type":"Point"}
}