{
  "type": "Feature",
  "properties": {
    "addr:full":"1, Piazzale Cosulich A. 34074 Monfalcone Monfalcone Gorizia 34074",
    "addr:postcode":"34074;34074",
    "addr:street":"Piazzale Cosulich A.",
    "iso:country":"IT",
    "sg:address":"1, Piazzale Cosulich A. 34074 Monfalcone",
    "sg:city":"Monfalcone",
    "sg:classifiers":[
        {
            "category":"Manufacturing",
            "subcategory":"Metals",
            "type":"Manufacturing & Wholesale Goods"
        }
    ],
    "sg:phone":"+39 0481 482211",
    "sg:postcode":"34074",
    "sg:province":"Gorizia",
    "sg:tags":[
        "processing"
    ],
    "wof:name":"Secta S.r.l.",
    "wof:placetype":"venue"
},
  "geometry": {"coordinates":[13.6215457916,45.9413032532],"type":"Point"}
}