{
  "type": "Feature",
  "properties": {
    "addr:full":"25126 Brescia Brescia Brescia 25126",
    "addr:postcode":"25126;25126",
    "iso:country":"IT",
    "sg:address":"25126 Brescia",
    "sg:city":"Brescia",
    "sg:orig_category":"Gioielleria, Oreficeria E Argenteria. Articoli Da Regalo. Shopping",
    "sg:phone":"+39 030 313177",
    "sg:postcode":"25126",
    "sg:province":"Brescia",
    "wof:name":"Felter & Bonfadelli",
    "wof:placetype":"venue"
},
  "geometry": {"coordinates":[9.614247,45.640415],"type":"Point"}
}