{
  "type": "Feature",
  "properties": {
    "addr:full":"50126 Firenze Firenze Firenze 50126",
    "addr:postcode":"50126;50126",
    "iso:country":"IT",
    "sg:address":"50126 Firenze",
    "sg:city":"Firenze",
    "sg:orig_category":"Bevande, Vini E Liquori",
    "sg:phone":"+39 055 681 1290",
    "sg:postcode":"50126",
    "sg:province":"Firenze",
    "wof:name":"Gema Sas",
    "wof:placetype":"venue"
},
  "geometry": {"coordinates":[11.288232,43.761505],"type":"Point"}
}