{
  "type": "Feature",
  "properties": {
    "iso:country":"IT",
    "sg:address":"Via Puccini 12 20015 Parabiago",
    "sg:city":"Parabiago",
    "sg:orig_category":"Ladies' Shoes",
    "sg:phone":"+39 0331 551642",
    "sg:postcode":"20015",
    "sg:province":"Milano",
    "sg:website":"www.nebuloni.it",
    "wof:name":"Calzaturificio Nebuloni Srl",
    "wof:placetype":"venue"
},
  "geometry": {"coordinates":[8.956386,45.578831],"type":"Point"}
}