{
  "type": "Feature",
  "properties": {
    "iso:country":"IT",
    "sg:address":"13900 Biella",
    "sg:city":"Biella",
    "sg:orig_category":"Ricambi E Componenti Dei Mezzi Di Trasporto",
    "sg:phone":"+39 015 402935",
    "sg:postcode":"13900",
    "sg:province":"Biella",
    "wof:name":"Coda Zabetta Maurizio",
    "wof:placetype":"venue"
},
  "geometry": {"coordinates":[8.045113,45.559654],"type":"Point"}
}