{
  "type": "Feature",
  "properties": {
    "iso:country":"IT",
    "sg:address":"20132 Milano",
    "sg:city":"Milano",
    "sg:orig_category":"Termotecnica E Riscaldamento, Apparecchiature E Servizi",
    "sg:phone":"+39 02 2630 6356",
    "sg:postcode":"20132",
    "sg:province":"Milano",
    "wof:name":"S.i.r.c. S.n.c. Di Cavallotti Ambrogio & C.",
    "wof:placetype":"venue"
},
  "geometry": {"coordinates":[9.253364,45.509724],"type":"Point"}
}