{
  "type": "Feature",
  "properties": {
    "iso:country":"IT",
    "sg:address":"10152 Torino",
    "sg:city":"Torino",
    "sg:orig_category":"Bagno - Accessori E Mobili",
    "sg:phone":"+39 011 859344",
    "sg:postcode":"10152",
    "sg:province":"Torino",
    "wof:name":"Fornengo Srl",
    "wof:placetype":"venue"
},
  "geometry": {"coordinates":[7.687315,45.080673],"type":"Point"}
}