{
  "type": "Feature",
  "properties": {
    "iso:country":"IT",
    "sg:address":"31, Via Nominale 80146 Napoli",
    "sg:city":"Napoli",
    "sg:classifiers":[
        {
            "category":"Professional",
            "subcategory":"Engineering",
            "type":"Services"
        }
    ],
    "sg:phone":"+39 081 752 7890",
    "sg:postcode":"80146",
    "sg:province":"Napoli",
    "sg:tags":[
        "machine",
        "-",
        "mechanical"
    ],
    "wof:name":"Meccanica T.a.c.c. S.n.c.",
    "wof:placetype":"venue"
},
  "geometry": {"coordinates":[14.296966,40.838043],"type":"Point"}
}