{
  "type": "Feature",
  "properties": {
    "iso:country":"IT",
    "sg:address":"40068 San Lazzaro Di Savena",
    "sg:city":"San Lazzaro",
    "sg:orig_category":"Utensili Meccanici E Materiali",
    "sg:phone":"+39 051 627 2351",
    "sg:postcode":"40068",
    "sg:province":"Bologna",
    "wof:name":"F.er. Menetti Forniture E Rapp.menetti Di Menetti V. & C.",
    "wof:placetype":"venue"
},
  "geometry": {"coordinates":[11.410314,44.474976],"type":"Point"}
}