{
  "type": "Feature",
  "properties": {
    "iso:country":"IT",
    "sg:address":"11, Via Vercelli 16033 Lavagna",
    "sg:city":"Lavagna",
    "sg:classifiers":[
        {
            "category":"Travel",
            "subcategory":"Travel Agent",
            "type":"Entertainment"
        }
    ],
    "sg:phone":"+39 0185 395277",
    "sg:postcode":"16033",
    "sg:province":"Genova",
    "sg:tags":[
        "business"
    ],
    "wof:name":"Albergo Maggi",
    "wof:placetype":"venue"
},
  "geometry": {"coordinates":[9.368859,44.296577],"type":"Point"}
}