{
  "type": "Feature",
  "properties": {
    "iso:country":"IT",
    "sg:address":"17058 Dego",
    "sg:city":"Dego",
    "sg:orig_category":"Macchine Ed Impianti Per Edilizia E Lavori Pubblici. Macchine, Strumenti Ed Apparecchi Per Attivita' Industriali",
    "sg:phone":"+39 019 51661",
    "sg:postcode":"17058",
    "sg:province":"Savona",
    "wof:name":"Emhart Glass Srl",
    "wof:placetype":"venue"
},
  "geometry": {"coordinates":[8.307037,44.444073],"type":"Point"}
}