{
  "type": "Feature",
  "properties": {
    "iso:country":"IT",
    "sg:address":"06016 San Giustino",
    "sg:city":"San Giustino",
    "sg:orig_category":"Accessori Dei Mezzi Di Trasporto",
    "sg:phone":"+39 075 856 0211",
    "sg:postcode":"06016",
    "sg:province":"Perugia",
    "wof:name":"G.r.s. Di Gobbi Rosa & C. Snc",
    "wof:placetype":"venue"
},
  "geometry": {"coordinates":[12.168217,43.555225],"type":"Point"}
}