{
  "type": "Feature",
  "properties": {
    "addr:full":"37131 Verona Verona Verona 37131",
    "addr:postcode":"37131;37131",
    "iso:country":"IT",
    "sg:address":"37131 Verona",
    "sg:city":"Verona",
    "sg:orig_category":"Porte",
    "sg:phone":"+39 045 527696",
    "sg:postcode":"37131",
    "sg:province":"Verona",
    "wof:name":"Perlini - Chiusure Per L'edilizia",
    "wof:placetype":"venue"
},
  "geometry": {"coordinates":[11.0183858871,45.4393463135],"type":"Point"}
}