{
  "type": "Feature",
  "properties": {
    "iso:country":"IT",
    "sg:address":"40069 Zola Predosa",
    "sg:city":"Zola",
    "sg:classifiers":[
        {
            "category":"Manufacturing",
            "subcategory":"Motor Vehicles & Parts",
            "type":"Manufacturing & Wholesale Goods"
        }
    ],
    "sg:phone":"+39 051 758517",
    "sg:postcode":"40069",
    "sg:province":"Bologna",
    "sg:tags":[
        "drive"
    ],
    "sg:website":"http://www.gbgearboxes.it",
    "wof:name":"Gb Srl",
    "wof:placetype":"venue"
},
  "geometry": {"coordinates":[11.2529506683,44.4947471619],"type":"Point"}
}