{
  "type": "Feature",
  "properties": {
    "addr:full":"Via Torino 30 10088 Volpiano Volpiano Torino 10088",
    "addr:housenumber":"30",
    "addr:postcode":"10088;10088",
    "addr:street":"Via Torino",
    "iso:country":"IT",
    "sg:address":"Via Torino 30 10088 Volpiano",
    "sg:city":"Volpiano",
    "sg:orig_category":"Galloons",
    "sg:phone":"+39 011 988 2251",
    "sg:postcode":"10088",
    "sg:province":"Torino",
    "wof:name":"Ocsalm Srl",
    "wof:placetype":"venue"
},
  "geometry": {"coordinates":[7.759646,45.168266],"type":"Point"}
}