{
  "type": "Feature",
  "properties": {
    "iso:country":"IT",
    "sg:address":"20032 Cormano",
    "sg:city":"Cormano",
    "sg:orig_category":"Imballaggi In Plastica",
    "sg:phone":"+39 02 6630 6492",
    "sg:postcode":"20032",
    "sg:province":"Milano",
    "sg:website":"http://www.intrapak.it",
    "wof:name":"Intrapak Spa",
    "wof:placetype":"venue"
},
  "geometry": {"coordinates":[9.170284,45.536629],"type":"Point"}
}