{
  "type": "Feature",
  "properties": {
    "iso:country":"IT",
    "sg:address":"68, Via Monte S. Michele 70124 Bari",
    "sg:city":"Bari",
    "sg:classifiers":[
        {
            "category":"Manufacturing",
            "subcategory":"Printing",
            "type":"Manufacturing & Wholesale Goods"
        }
    ],
    "sg:phone":"+39 080 501 3256",
    "sg:postcode":"70124",
    "sg:province":"Bari",
    "sg:tags":[
        "publishing"
    ],
    "wof:name":"Scoppio",
    "wof:placetype":"venue"
},
  "geometry": {"coordinates":[16.8650035858,41.0636711121],"type":"Point"}
}