{
  "type": "Feature",
  "properties": {
    "addr:full":"Strada Statale 115 92027 Licata Licata Agrigento 92027",
    "addr:housenumber":"115",
    "addr:postcode":"92027;92027",
    "addr:street":"Strada Statale",
    "iso:country":"IT",
    "sg:address":"Strada Statale 115 92027 Licata",
    "sg:city":"Licata",
    "sg:classifiers":[
        {
            "category":"Professional",
            "subcategory":"Engineering",
            "type":"Services"
        }
    ],
    "sg:phone":"+39 0922 894336",
    "sg:postcode":"92027",
    "sg:province":"Agrigento",
    "sg:tags":[
        "machine",
        "-",
        "mechanical"
    ],
    "wof:name":"S.i.c.e.m. Srl",
    "wof:placetype":"venue"
},
  "geometry": {"coordinates":[13.772778,37.182373],"type":"Point"}
}