{
  "type": "Feature",
  "properties": {
    "iso:country":"IT",
    "sg:address":"35020 Maser\u00e0 Di Padova",
    "sg:orig_category":"Minuterie Di Precisione",
    "sg:phone":"+39 049 886 2478",
    "sg:postcode":"35020",
    "sg:province":"Padova",
    "wof:name":"Lampo Srl",
    "wof:placetype":"venue"
},
  "geometry": {"coordinates":[11.8610553741,45.313495636],"type":"Point"}
}