{
  "type": "Feature",
  "properties": {
    "iso:country":"IT",
    "sg:address":"20146 Milano",
    "sg:city":"Milano",
    "sg:orig_category":"Telecomunicazioni Impianti Ed Apparecchi - Produzione E Ingrosso",
    "sg:phone":"+39 02 4870 6150",
    "sg:postcode":"20146",
    "sg:province":"Milano",
    "wof:name":"A.t.s. Telematica",
    "wof:placetype":"venue"
},
  "geometry": {"coordinates":[9.141242,45.461376],"type":"Point"}
}