{
  "type": "Feature",
  "properties": {
    "iso:country":"IT",
    "sg:address":"31021 Mogliano Veneto",
    "sg:city":"Mogliano Veneto",
    "sg:orig_category":"Articoli Da Regalo. Forniture Per Attivita' Commerciali Ed Artigianali",
    "sg:phone":"+39 041 593 7048",
    "sg:postcode":"31021",
    "sg:province":"Treviso",
    "wof:name":"Moonflower Srl",
    "wof:placetype":"venue"
},
  "geometry": {"coordinates":[12.298657,45.589001],"type":"Point"}
}