{
  "type": "Feature",
  "properties": {
    "iso:country":"IT",
    "sg:address":"Via Risorgimento 10 20017 Rho",
    "sg:city":"Rho",
    "sg:classifiers":[
        {
            "category":"Bus Stop",
            "subcategory":"None",
            "type":"Transportation"
        }
    ],
    "sg:phone":"+39 02 9390 0686",
    "sg:postcode":"20017",
    "sg:province":"Milano",
    "sg:tags":[
        "valve",
        "solenoid"
    ],
    "sg:website":"www.nadi.it",
    "wof:name":"Nadi S.r.l.",
    "wof:placetype":"venue"
},
  "geometry": {"coordinates":[9.071503,45.528088],"type":"Point"}
}