{
  "type": "Feature",
  "properties": {
    "iso:country":"IT",
    "sg:address":"21013 Gallarate",
    "sg:city":"Gallarate",
    "sg:orig_category":"Biancheria, Telerie E Coperte",
    "sg:phone":"+39 0331 771066",
    "sg:postcode":"21013",
    "sg:province":"Varese",
    "wof:name":"Tessitura Giulio Petoletti",
    "wof:placetype":"venue"
},
  "geometry": {"coordinates":[8.816078,45.64901],"type":"Point"}
}