{
  "type": "Feature",
  "properties": {
    "iso:country":"IT",
    "sg:address":"21042 Caronno Pertusella",
    "sg:city":"Caronno Pertusella",
    "sg:orig_category":"Macchine Ed Impianti Per Edilizia E Lavori Pubblici",
    "sg:phone":"+39 02 965 0610",
    "sg:postcode":"21042",
    "sg:province":"Varese",
    "wof:name":"Antonelli Macchine Srl",
    "wof:placetype":"venue"
},
  "geometry": {"coordinates":[9.06104,45.602684],"type":"Point"}
}