{
  "type": "Feature",
  "properties": {
    "addr:full":"V.lo Pascoli 6 35020 Albignasego Albignasego Padova 35020",
    "addr:housenumber":"6",
    "addr:postcode":"35020;35020",
    "addr:street":"V.Lo Pascoli",
    "iso:country":"IT",
    "sg:address":"V.lo Pascoli 6 35020 Albignasego",
    "sg:city":"Albignasego",
    "sg:classifiers":[
        {
            "category":"Real Estate",
            "subcategory":"Surveying",
            "type":"Services"
        }
    ],
    "sg:phone":"+39 049 731 3057",
    "sg:postcode":"35020",
    "sg:province":"Padova",
    "sg:tags":[
        "stationery",
        "writing",
        "material",
        "creative"
    ],
    "wof:name":"Sapi Srl",
    "wof:placetype":"venue"
},
  "geometry": {"coordinates":[11.849425,45.349403],"type":"Point"}
}