{
  "type": "Feature",
  "properties": {
    "iso:country":"IT",
    "sg:address":"Strada Beneceto 37/a 43100 Parma",
    "sg:city":"Parma",
    "sg:orig_category":"Leather Items, Artisans'",
    "sg:phone":"+39 0521 486806",
    "sg:postcode":"43100",
    "sg:province":"Parma",
    "sg:website":"www.francodessigaffe.com",
    "wof:name":"Gaffe Snc Di Dessi' Franco E C.",
    "wof:placetype":"venue"
},
  "geometry": {"coordinates":[10.29492,44.823208],"type":"Point"}
}