{
  "type": "Feature",
  "properties": {
    "iso:country":"IT",
    "sg:address":"00158 Roma",
    "sg:city":"Roma",
    "sg:orig_category":"Registrazione Sonora - Sale Prova",
    "sg:phone":"+39 06 418 0935",
    "sg:postcode":"00158",
    "sg:province":"Roma",
    "sg:website":"http://www.houserecordingstudio.it",
    "wof:name":"House Recording Studio Srl - 'doppiosaltomortale'",
    "wof:placetype":"venue"
},
  "geometry": {"coordinates":[12.512096,41.901852],"type":"Point"}
}