{
  "type": "Feature",
  "properties": {
    "iso:country":"IT",
    "sg:address":"17, Via Sicilia 40017 San Giovanni In Persiceto",
    "sg:city":"San Giovanni in Persiceto",
    "sg:classifiers":[
        {
            "category":"Shopping",
            "subcategory":"Clothing, Apparel, & Fashions",
            "type":"Retail Goods"
        }
    ],
    "sg:phone":"+39 051 682 7028",
    "sg:postcode":"40017",
    "sg:province":"Bologna",
    "sg:tags":[
        "clothes"
    ],
    "wof:name":"Amalia P.s.c.r.l.",
    "wof:placetype":"venue"
},
  "geometry": {"coordinates":[11.226681,44.700981],"type":"Point"}
}