{
  "type": "Feature",
  "properties": {
    "iso:country":"IT",
    "sg:address":"74011 Castellaneta",
    "sg:city":"Castellaneta",
    "sg:orig_category":"Ristorazione E Locali Pubblici Affini. Ristoranti Ed Esercizi Affini. Servizi Ausiliari Di Ristorazione E Di Intrattenimento",
    "sg:phone":"+39 099 844 1114",
    "sg:postcode":"74011",
    "sg:province":"Taranto",
    "sg:website":"http://www.gcosta.it",
    "wof:name":"Costa G. Srl",
    "wof:placetype":"venue"
},
  "geometry": {"coordinates":[17.449268,40.390205],"type":"Point"}
}