{
  "type": "Feature",
  "properties": {
    "addr:full":"4, Via C.a. Dalla Chiesa 42025 Cavriago Reggio Nell'Emilia 42025",
    "addr:postcode":"42025;42025",
    "addr:street":"Via C.A. Dalla Chiesa",
    "iso:country":"IT",
    "sg:address":"4, Via C.a. Dalla Chiesa 42025 Cavriago",
    "sg:classifiers":[
        {
            "category":"Manufacturing",
            "subcategory":"Printing",
            "type":"Manufacturing & Wholesale Goods"
        }
    ],
    "sg:phone":"+39 0522 577745",
    "sg:postcode":"42025",
    "sg:province":"Reggio Nell'Emilia",
    "sg:tags":[
        "publishing"
    ],
    "wof:name":"Bertani & C. (s.r.l.)",
    "wof:placetype":"venue"
},
  "geometry": {"coordinates":[10.5348901749,44.6940498352],"type":"Point"}
}