{
  "type": "Feature",
  "properties": {
    "iso:country":"IT",
    "sg:address":"16, Via Adua 21052 Busto Arsizio",
    "sg:city":"Busto Arsizio",
    "sg:classifiers":[
        {
            "category":"Shopping",
            "subcategory":"Crafts & Fabrics",
            "type":"Retail Goods"
        }
    ],
    "sg:phone":"+39 0331 679029",
    "sg:postcode":"21052",
    "sg:province":"Varese",
    "wof:name":"Tosi Luigi & C. S.p.a.",
    "wof:placetype":"venue"
},
  "geometry": {"coordinates":[8.8488826752,45.6190567017],"type":"Point"}
}