{
  "type": "Feature",
  "properties": {
    "iso:country":"IT",
    "sg:address":"Via S. Floriano 8 39050 Cornaiano",
    "sg:classifiers":[
        {
            "category":"Food & Beverages",
            "subcategory":"Liquor & Beverages",
            "type":"Retail Goods"
        }
    ],
    "sg:phone":"+39 0471 662419",
    "sg:postcode":"39050",
    "sg:province":"Bolzano/Bozen",
    "sg:tags":[
        "wine",
        "italian"
    ],
    "wof:name":"Josef Brigl Spa % Josef Brigl A.g.",
    "wof:placetype":"venue"
},
  "geometry": {"coordinates":[11.282047,46.463608],"type":"Point"}
}