{
  "type": "Feature",
  "properties": {
    "addr:full":"Via Generale C.a. Dalla Chiesa 16 84081 Baronissi Baronissi Salerno 84081",
    "addr:housenumber":"16",
    "addr:postcode":"84081;84081",
    "addr:street":"Via Generale C.A. Dalla Chiesa",
    "iso:country":"IT",
    "sg:address":"Via Generale C.a. Dalla Chiesa 16 84081 Baronissi",
    "sg:city":"Baronissi",
    "sg:classifiers":[
        {
            "category":"Food & Beverages",
            "subcategory":"Groceries & Convenience Stores",
            "type":"Retail Goods"
        }
    ],
    "sg:phone":"+39 089 953714",
    "sg:postcode":"84081",
    "sg:province":"Salerno",
    "sg:tags":[
        "frozen",
        "goods",
        "baked"
    ],
    "sg:website":"www.ispadsud.com",
    "wof:name":"Ispad Sud Srl",
    "wof:placetype":"venue"
},
  "geometry": {"coordinates":[14.765912,40.677956],"type":"Point"}
}