{
  "type": "Feature",
  "properties": {
    "addr:full":"8/10, Via Alessandro Volta 24011 Alme' Bergamo 24011",
    "addr:housenumber":"8 / 10",
    "addr:postcode":"24011;24011",
    "addr:street":"Via Alessandro Volta",
    "iso:country":"IT",
    "sg:address":"8/10, Via Alessandro Volta 24011 Alme'",
    "sg:classifiers":[
        {
            "category":"Food & Beverages",
            "subcategory":"Groceries & Convenience Stores",
            "type":"Retail Goods"
        }
    ],
    "sg:phone":"+39 39035545455",
    "sg:postcode":"24011",
    "sg:province":"Bergamo",
    "sg:tags":[
        "product",
        "related"
    ],
    "wof:name":"Boffetti Marino & C. (s.n.c.)",
    "wof:placetype":"venue"
},
  "geometry": {"coordinates":[9.6063280106,45.7350120544],"type":"Point"}
}