{
  "type": "Feature",
  "properties": {
    "addr:full":"50019 Sesto Fiorentino Sesto Fiorentino Firenze 50019",
    "addr:postcode":"50019;50019",
    "iso:country":"IT",
    "sg:address":"50019 Sesto Fiorentino",
    "sg:city":"Sesto Fiorentino",
    "sg:orig_category":"Motori Ed Organi Di Trasmissione",
    "sg:phone":"+39 055 421 1611",
    "sg:postcode":"50019",
    "sg:province":"Firenze",
    "sg:website":"http://www.tecniflon.com",
    "wof:name":"Tecniflon Di Annalisa Poccetti",
    "wof:placetype":"venue"
},
  "geometry": {"coordinates":[11.1737241745,43.8386802673],"type":"Point"}
}