{
  "type": "Feature",
  "properties": {
    "iso:country":"IT",
    "sg:address":"Via Giardini 23030 Chiuro",
    "sg:city":"Chiuro",
    "sg:classifiers":[
        {
            "category":"Professional",
            "subcategory":"Engineering",
            "type":"Services"
        }
    ],
    "sg:phone":"+39 390 342 4851",
    "sg:postcode":"23030",
    "sg:province":"Sondrio",
    "sg:tags":[
        "machine",
        "-",
        "mechanical"
    ],
    "wof:name":"Baltimore Aircoil Italia S.r.l.",
    "wof:placetype":"venue"
},
  "geometry": {"coordinates":[9.869333,46.171261],"type":"Point"}
}