{
  "type": "Feature",
  "properties": {
    "iso:country":"IT",
    "sg:address":"Via Filos 31 38015 Lavis",
    "sg:city":"Lavis",
    "sg:orig_category":"Felsite Porphyry",
    "sg:phone":"+39 0461 246619",
    "sg:postcode":"38015",
    "sg:province":"Trento",
    "wof:name":"Porfidi Trentini",
    "wof:placetype":"venue"
},
  "geometry": {"coordinates":[11.0960302353,46.1457061768],"type":"Point"}
}