{
  "type": "Feature",
  "properties": {
    "iso:country":"IT",
    "sg:address":"86042 Campomarino",
    "sg:city":"Campomarino",
    "sg:orig_category":"Metalli E Leghe",
    "sg:phone":"+39 0875 538404",
    "sg:postcode":"86042",
    "sg:province":"Campobasso",
    "wof:name":"Eurorottami Srl",
    "wof:placetype":"venue"
},
  "geometry": {"coordinates":[15.0674314499,41.9144020081],"type":"Point"}
}