{
  "type": "Feature",
  "properties": {
    "iso:country":"IT",
    "sg:address":"21013 Gallarate",
    "sg:city":"Gallarate",
    "sg:orig_category":"Elettrodomestici. Elettronica Professionale E Di Consumo. Arredi Ed Attrezzature Per Attivita' Commerciali Ed Artigianali. Macchine, Strumenti Ed Apparecchi Per Attivita' Industriali",
    "sg:phone":"+39 0331 775209",
    "sg:postcode":"21013",
    "sg:province":"Varese",
    "wof:name":"G.u.m. Srl",
    "wof:placetype":"venue"
},
  "geometry": {"coordinates":[8.799276,45.664864],"type":"Point"}
}