{
  "type": "Feature",
  "properties": {
    "iso:country":"IT",
    "sg:address":"80, Corso Italia 32043 Cortina D'ampezzo",
    "sg:classifiers":[
        {
            "category":"Banks & Credit Unions",
            "subcategory":"Bank",
            "type":"Services"
        }
    ],
    "sg:phone":"+39 0436 862076",
    "sg:postcode":"32043",
    "sg:province":"Belluno",
    "sg:tags":[
        "banking",
        "institution"
    ],
    "wof:name":"Cassa Rurale Ed Artigiana Di Cortina D'ampezzo E Delle Dolomiti",
    "wof:placetype":"venue"
},
  "geometry": {"coordinates":[12.134055,46.547138],"type":"Point"}
}