{
  "type": "Feature",
  "properties": {
    "addr:full":"16149 Genova Genova Genova 16149",
    "addr:postcode":"16149;16149",
    "iso:country":"IT",
    "sg:address":"16149 Genova",
    "sg:city":"Genova",
    "sg:orig_category":"Servizi E Lavori Per Ecologia E Smaltimento Rifiuti",
    "sg:phone":"+39 010 254 9311",
    "sg:postcode":"16149",
    "sg:province":"Genova",
    "wof:name":"Nitco Spa",
    "wof:placetype":"venue"
},
  "geometry": {"coordinates":[8.898056,44.41058],"type":"Point"}
}