{
  "type": "Feature",
  "properties": {
    "iso:country":"IT",
    "sg:address":"30, Via Cortili Mariani 44039 Tresigallo",
    "sg:city":"Tresigallo",
    "sg:classifiers":[
        {
            "category":"Farming",
            "subcategory":"Livestock Farm",
            "type":"Manufacturing & Wholesale Goods"
        }
    ],
    "sg:phone":"+39 0533 602394",
    "sg:postcode":"44039",
    "sg:province":"Ferrara",
    "sg:tags":[
        "agriculture"
    ],
    "wof:name":"Sapar S.p.a.",
    "wof:placetype":"venue"
},
  "geometry": {"coordinates":[11.87185,44.808559],"type":"Point"}
}