{
  "type": "Feature",
  "properties": {
    "addr:full":"53036 Poggibonsi Poggibonsi Siena 53036",
    "addr:postcode":"53036;53036",
    "iso:country":"IT",
    "sg:address":"53036 Poggibonsi",
    "sg:city":"Poggibonsi",
    "sg:orig_category":"Motori Ed Organi Di Trasmissione. Ricambi E Componenti Dei Mezzi Di Trasporto",
    "sg:phone":"+39 0577 938153",
    "sg:postcode":"53036",
    "sg:province":"Siena",
    "wof:name":"C.b.s. Srl",
    "wof:placetype":"venue"
},
  "geometry": {"coordinates":[11.1325511932,43.4774169922],"type":"Point"}
}