{
  "type": "Feature",
  "properties": {
    "addr:full":"12, Via Benaco 20098 San Giuliano Milanese San Giuliano Milanese Milano 20098",
    "addr:postcode":"20098;20098",
    "addr:street":"Via Benaco",
    "iso:country":"IT",
    "sg:address":"12, Via Benaco 20098 San Giuliano Milanese",
    "sg:city":"San Giuliano Milanese",
    "sg:classifiers":[
        {
            "category":"Manufacturing",
            "subcategory":"Food",
            "type":"Manufacturing & Wholesale Goods"
        }
    ],
    "sg:phone":"+39 02 9828 9294",
    "sg:postcode":"20098",
    "sg:province":"Milano",
    "sg:tags":[
        "equipment",
        "processing",
        "-",
        "machinery"
    ],
    "wof:name":"Top Gel Srl",
    "wof:placetype":"venue"
},
  "geometry": {"coordinates":[9.2454900742,45.4021148682],"type":"Point"}
}