{
  "type": "Feature",
  "properties": {
    "iso:country":"IT",
    "sg:address":"13, Via Scipione Ammirato 50136 Firenze",
    "sg:city":"Firenze",
    "sg:classifiers":[
        {
            "category":"Autos & Motor Vehicles",
            "subcategory":"Automobile Sales",
            "type":"Retail Goods"
        }
    ],
    "sg:phone":"+39 39055669679",
    "sg:postcode":"50136",
    "sg:province":"Firenze",
    "sg:tags":[
        "motor-cars"
    ],
    "wof:name":"Buratti Srl",
    "wof:placetype":"venue"
},
  "geometry": {"coordinates":[11.276679039,43.7709007263],"type":"Point"}
}