{
  "type": "Feature",
  "properties": {
    "iso:country":"IT",
    "sg:address":"31020 San Vendemiano",
    "sg:city":"San Vendemiano",
    "sg:classifiers":[
        {
            "category":"Manufacturing",
            "subcategory":"Tools & Machinery",
            "type":"Manufacturing & Wholesale Goods"
        }
    ],
    "sg:phone":"+39 0438 409048",
    "sg:postcode":"31020",
    "sg:province":"Treviso",
    "sg:tags":[
        "machining",
        "mechanical"
    ],
    "wof:name":"Meneghin Luigino",
    "wof:placetype":"venue"
},
  "geometry": {"coordinates":[12.324897,45.893059],"type":"Point"}
}