{
  "type": "Feature",
  "properties": {
    "iso:country":"IT",
    "sg:address":"20089 Rozzano",
    "sg:city":"Rozzano",
    "sg:orig_category":"Petroli, Gas E Combustibili. Servizi E Lavori Industria Chimica. Servizi E Lavori Per Edilizia E Lavori Pubblici. Acqua, Luce, Gas E Societa' Di Esercizio Pubblico",
    "sg:phone":"+39 02 5751 4719",
    "sg:postcode":"20089",
    "sg:province":"Milano",
    "wof:name":"Azienda Multiservizi Ambientali A.m.a. S.p.a.",
    "wof:placetype":"venue"
},
  "geometry": {"coordinates":[9.1587533951,45.3828277588],"type":"Point"}
}