{
  "type": "Feature",
  "properties": {
    "iso:country":"IT",
    "sg:address":"Via Appia Antica 81100 Caserta",
    "sg:city":"Caserta",
    "sg:classifiers":[
        {
            "category":"Utilities",
            "subcategory":"Electric",
            "type":"Services"
        }
    ],
    "sg:phone":"+39 0823 421722",
    "sg:postcode":"81100",
    "sg:province":"Caserta",
    "sg:tags":[
        "component",
        "electronic"
    ],
    "wof:name":"Elettronica Faleni Srl",
    "wof:placetype":"venue"
},
  "geometry": {"coordinates":[14.29914,41.069111],"type":"Point"}
}