{
  "type": "Feature",
  "properties": {
    "addr:full":"20122 Milano Milano Milano 20122",
    "addr:postcode":"20122;20122",
    "iso:country":"IT",
    "sg:address":"20122 Milano",
    "sg:city":"Milano",
    "sg:orig_category":"Servizi Culturali E Per Lo Spettacolo. Servizi Al Turismo. Acqua, Luce, Gas E Societa' Di Esercizio Pubblico",
    "sg:phone":"+39 02 7600 3097",
    "sg:postcode":"20122",
    "sg:province":"Milano",
    "wof:name":"Conservatorio Di Musica =g. Verdi=",
    "wof:placetype":"venue"
},
  "geometry": {"coordinates":[9.203131,45.464577],"type":"Point"}
}