{
  "type": "Feature",
  "properties": {
    "iso:country":"IT",
    "sg:address":"47814 Bellaria Igea Marina",
    "sg:city":"Bellaria",
    "sg:orig_category":"Motocicli E Motocarri - Commercio E Riparazione",
    "sg:phone":"+39 0541 340146",
    "sg:postcode":"47814",
    "sg:province":"Rimini",
    "wof:name":"Caiti Moto Di Caiti Daniele & C. Snc",
    "wof:placetype":"venue"
},
  "geometry": {"coordinates":[12.4596157074,44.1487121582],"type":"Point"}
}