{
  "type": "Feature",
  "properties": {
    "iso:country":"IT",
    "sg:address":"20049 Concorezzo",
    "sg:city":"Concorezzo",
    "sg:orig_category":"Forniture Per Abbigliamento E Pelletterie. Forniture E Materiali Per Imballaggio E Confezionamento",
    "sg:phone":"+39 039 604 1617",
    "sg:postcode":"20049",
    "sg:province":"Milano",
    "sg:website":"http://www.albertbonati.com",
    "wof:name":"Nastrificio Albert Bonati Srl",
    "wof:placetype":"venue"
},
  "geometry": {"coordinates":[9.1524152756,45.4725990295],"type":"Point"}
}