{
  "type": "Feature",
  "properties": {
    "iso:country":"IT",
    "sg:address":"22032 Albese Con Cassano",
    "sg:city":"Albese con Cassano",
    "sg:orig_category":"Articoli Pulizia. Forniture Per Attivita' Industriali",
    "sg:phone":"+39 031 360995",
    "sg:postcode":"22032",
    "sg:province":"Como",
    "wof:name":"Sital Srl",
    "wof:placetype":"venue"
},
  "geometry": {"coordinates":[9.137424,45.77002],"type":"Point"}
}