{
  "type": "Feature",
  "properties": {
    "iso:country":"IT",
    "sg:address":"20017 Rho",
    "sg:city":"Rho",
    "sg:orig_category":"Macchine E Forniture Per Industria Orafa E Per Orologeria",
    "sg:phone":"+39 02 9390 0319",
    "sg:postcode":"20017",
    "sg:province":"Milano",
    "sg:website":"http://www.paginegialle.it/duvesnc",
    "wof:name":"D.u.v.e. Di Malaspina Silvia & C. Snc",
    "wof:placetype":"venue"
},
  "geometry": {"coordinates":[9.086473,45.527843],"type":"Point"}
}