{
  "type": "Feature",
  "properties": {
    "addr:full":"50058 Signa Signa Firenze 50058",
    "addr:postcode":"50058;50058",
    "iso:country":"IT",
    "sg:address":"50058 Signa",
    "sg:city":"Signa",
    "sg:orig_category":"Arredamento Cinema E Teatri",
    "sg:phone":"+39 055 875614",
    "sg:postcode":"50058",
    "sg:province":"Firenze",
    "sg:website":"http://www.parrettivasco.it",
    "wof:name":"Parretti Vasco",
    "wof:placetype":"venue"
},
  "geometry": {"coordinates":[11.123769,43.826031],"type":"Point"}
}