{
  "type": "Feature",
  "properties": {
    "iso:country":"IT",
    "sg:address":"00189 Roma",
    "sg:city":"Roma",
    "sg:orig_category":"Prodotti Chimici Secondari. Prodotti Cosmetici E Da Toeletta",
    "sg:phone":"+39 06 3031 1314",
    "sg:postcode":"00189",
    "sg:province":"Roma",
    "wof:name":"Charabot Italiana Srl",
    "wof:placetype":"venue"
},
  "geometry": {"coordinates":[12.4335670471,41.9719467163],"type":"Point"}
}