{
  "type": "Feature",
  "properties": {
    "iso:country":"IT",
    "sg:address":"Via Brofferio 4 14100 Asti",
    "sg:city":"Asti",
    "sg:classifiers":[
        {
            "category":"Food & Beverages",
            "subcategory":"Chocolate",
            "type":"Retail Goods"
        }
    ],
    "sg:phone":"+39 0141 594004",
    "sg:postcode":"14100",
    "sg:province":"Asti",
    "sg:website":"www.barberodavide.it",
    "wof:name":"Barbero Davide Srl",
    "wof:placetype":"venue"
},
  "geometry": {"coordinates":[8.251861,44.790356],"type":"Point"}
}