{
  "type": "Feature",
  "properties": {
    "iso:country":"IT",
    "sg:address":"Via Arbizzani 2 40012 Calderara Di Reno",
    "sg:city":"Calderara di Reno",
    "sg:classifiers":[
        {
            "category":"Wholesale",
            "subcategory":"Construction Materials",
            "type":"Manufacturing & Wholesale Goods"
        }
    ],
    "sg:phone":"+39 051 723082",
    "sg:postcode":"40012",
    "sg:province":"Bologna",
    "sg:tags":[
        "mould",
        "injection"
    ],
    "sg:website":"www.tecmit.com",
    "wof:name":"Tecmit Srl",
    "wof:placetype":"venue"
},
  "geometry": {"coordinates":[11.30554,44.572388],"type":"Point"}
}