{
  "type": "Feature",
  "properties": {
    "iso:country":"IT",
    "sg:address":"65015 Montesilvano",
    "sg:city":"Montesilvano",
    "sg:orig_category":"Arredamenti E Mobili Professionali. Forniture Per Il Settore Dello Spettacolo",
    "sg:phone":"+39 085 445 4844",
    "sg:postcode":"65015",
    "sg:province":"Pescara",
    "wof:name":"Ergonomie S.a.s.",
    "wof:placetype":"venue"
},
  "geometry": {"coordinates":[14.167637,42.494816],"type":"Point"}
}