{
  "type": "Feature",
  "properties": {
    "addr:full":"10156 Torino Torino Torino 10156",
    "addr:postcode":"10156;10156",
    "iso:country":"IT",
    "sg:address":"10156 Torino",
    "sg:city":"Torino",
    "sg:classifiers":[
        {
            "category":"Home & Garden",
            "subcategory":"Building Materials",
            "type":"Retail Goods"
        }
    ],
    "sg:phone":"+39 011 470 1996",
    "sg:postcode":"10156",
    "sg:province":"Torino",
    "sg:tags":[
        "window",
        "door",
        "frame"
    ],
    "sg:website":"http://www.boschis.com",
    "wof:name":"Boschis Spa",
    "wof:placetype":"venue"
},
  "geometry": {"coordinates":[7.70615,45.119347],"type":"Point"}
}