{
  "type": "Feature",
  "properties": {
    "iso:country":"IT",
    "sg:address":"25, Via Provinciale Campigliano 84099 San Cipriano Picentino",
    "sg:city":"Campigliano",
    "sg:classifiers":[
        {
            "category":"Real Estate",
            "subcategory":"Surveying",
            "type":"Services"
        }
    ],
    "sg:phone":"+39 39089882414",
    "sg:postcode":"84099",
    "sg:province":"Salerno",
    "sg:tags":[
        "equipment",
        "material",
        "good",
        "-",
        "handling"
    ],
    "wof:name":"So.for.in. (s.r.l.)",
    "wof:placetype":"venue"
},
  "geometry": {"coordinates":[14.887424,40.688721],"type":"Point"}
}