{
  "type": "Feature",
  "properties": {
    "iso:country":"IT",
    "sg:address":"13100 Vercelli",
    "sg:city":"Vercelli",
    "sg:orig_category":"Prodotti Alimentari. Agricoltura, Orticoltura E Floricoltura",
    "sg:phone":"+39 0161 217537",
    "sg:postcode":"13100",
    "sg:province":"Vercelli",
    "wof:name":"Mundi Riso Srl",
    "wof:placetype":"venue"
},
  "geometry": {"coordinates":[8.4184741974,45.332359314],"type":"Point"}
}