{
  "type": "Feature",
  "properties": {
    "addr:full":"20092 Cinisello Balsamo Cinisello Balsamo Milano 20092",
    "addr:postcode":"20092;20092",
    "iso:country":"IT",
    "sg:address":"20092 Cinisello Balsamo",
    "sg:city":"Cinisello Balsamo",
    "sg:orig_category":"Valvole E Apparecchiature Di Misura. Apparecchiature E Sistemi Per Imballaggio E Confezionamento",
    "sg:phone":"+39 02 617 5405",
    "sg:postcode":"20092",
    "sg:province":"Milano",
    "wof:name":"I.d.i. (s.p.a.)",
    "wof:placetype":"venue"
},
  "geometry": {"coordinates":[9.228981,45.555244],"type":"Point"}
}