{
  "type": "Feature",
  "properties": {
    "iso:country":"IT",
    "sg:address":"93/a, Contrada Martucci 72015 Fasano",
    "sg:city":"Fasano",
    "sg:classifiers":[
        {
            "category":"Food & Beverages",
            "subcategory":"Groceries & Convenience Stores",
            "type":"Retail Goods"
        }
    ],
    "sg:phone":"+39 080 439 3677",
    "sg:postcode":"72015",
    "sg:province":"Brindisi",
    "sg:tags":[
        "product",
        "related"
    ],
    "wof:name":"Bluver S.r.l.",
    "wof:placetype":"venue"
},
  "geometry": {"coordinates":[17.3533763885,40.8467254639],"type":"Point"}
}