{
  "type": "Feature",
  "properties": {
    "iso:country":"IT",
    "sg:address":"16, Via Costa Andrea 40013 Castel Maggiore",
    "sg:city":"Castel Maggiore",
    "sg:classifiers":[
        {
            "category":"Autos & Motor Vehicles",
            "subcategory":"Automobile Sales",
            "type":"Retail Goods"
        }
    ],
    "sg:phone":"+39 39051701710",
    "sg:postcode":"40013",
    "sg:province":"Bologna",
    "sg:tags":[
        "industrial"
    ],
    "wof:name":"Bologna Gru Soc. Coop. A.r.l.",
    "wof:placetype":"venue"
},
  "geometry": {"coordinates":[11.348975,44.555454],"type":"Point"}
}