{
  "type": "Feature",
  "properties": {
    "addr:full":"10125 Torino Torino Torino 10125",
    "addr:postcode":"10125;10125",
    "iso:country":"IT",
    "sg:address":"10125 Torino",
    "sg:city":"Torino",
    "sg:orig_category":"Climatizzazione E Condizionamento, Apparecchiature E Servizi",
    "sg:phone":"+39 011 650 7159",
    "sg:postcode":"10125",
    "sg:province":"Torino",
    "wof:name":"Muro - Therapie",
    "wof:placetype":"venue"
},
  "geometry": {"coordinates":[7.830617,45.487606],"type":"Point"}
}