{
  "type": "Feature",
  "properties": {
    "addr:full":"Via Alessandro Volta, 8/10 24011 Alme' Bergamo 24011",
    "addr:housenumber":"8 / 10",
    "addr:postcode":"24011;24011",
    "addr:street":"Via Alessandro Volta",
    "iso:country":"IT",
    "sg:address":"Via Alessandro Volta, 8/10 24011 Alme'",
    "sg:classifiers":[
        {
            "category":"Food & Beverages",
            "subcategory":"Fruits & Vegetables",
            "type":"Retail Goods"
        }
    ],
    "sg:phone":"+39 035 545455",
    "sg:postcode":"24011",
    "sg:province":"Bergamo",
    "sg:website":"www.boffettimarino.com",
    "wof:name":"La Frutta Del Sole S.r.l.",
    "wof:placetype":"venue"
},
  "geometry": {"coordinates":[9.6063280106,45.7350120544],"type":"Point"}
}