{
  "type": "Feature",
  "properties": {
    "iso:country":"IT",
    "sg:address":"56025 Pontedera",
    "sg:city":"Pontedera",
    "sg:orig_category":"Prodotti Finiti Stampati. Articoli Da Regalo. Arte Ed Artigianato Artistico. Shopping",
    "sg:phone":"+39 0587 296007",
    "sg:postcode":"56025",
    "sg:province":"Pisa",
    "wof:name":"Centrostampa Pontedera Di Andolfi Floriano & C: Snc",
    "wof:placetype":"venue"
},
  "geometry": {"coordinates":[10.5960407257,43.6415176392],"type":"Point"}
}