{
  "type": "Feature",
  "properties": {
    "iso:country":"IT",
    "sg:address":"00044 Frascati",
    "sg:city":"Frascati",
    "sg:orig_category":"Prodotti Alimentari",
    "sg:phone":"+39 06 942 0549",
    "sg:postcode":"00044",
    "sg:province":"Roma",
    "wof:name":"Bottoni Luciano",
    "wof:placetype":"venue"
},
  "geometry": {"coordinates":[12.6841592789,41.8104095459],"type":"Point"}
}