{
  "type": "Feature",
  "properties": {
    "iso:country":"IT",
    "sg:address":"4, Via Puglia 35043 Monselice",
    "sg:city":"Monselice",
    "sg:classifiers":[
        {
            "category":"Shopping",
            "subcategory":"Computers & Home Electronics",
            "type":"Retail Goods"
        }
    ],
    "sg:phone":"+39 0429 780895",
    "sg:postcode":"35043",
    "sg:province":"Padova",
    "sg:tags":[
        "electronic",
        "electrical",
        "equipment"
    ],
    "wof:name":"Elettromeccanica Conforto Antonio",
    "wof:placetype":"venue"
},
  "geometry": {"coordinates":[11.743351,45.173603],"type":"Point"}
}