{
  "type": "Feature",
  "properties": {
    "iso:country":"IT",
    "sg:address":"50054 Fucecchio",
    "sg:city":"Fucecchio",
    "sg:orig_category":"Calzature, Pelletterie E Pelli",
    "sg:phone":"+39 0571 261418",
    "sg:postcode":"50054",
    "sg:province":"Firenze",
    "wof:name":"Fedi Silvano",
    "wof:placetype":"venue"
},
  "geometry": {"coordinates":[11.218877,43.777908],"type":"Point"}
}