{
  "type": "Feature",
  "properties": {
    "iso:country":"IT",
    "sg:address":"13011 Borgosesia",
    "sg:city":"Borgosesia",
    "sg:orig_category":"Prodotti E Manufatti In Materie Plastiche",
    "sg:phone":"+39 0163 22668",
    "sg:postcode":"13011",
    "sg:province":"Vercelli",
    "wof:name":"Plastica Di Mucci - S.a.s. Di Di Mucci Vincenzo E C.",
    "wof:placetype":"venue"
},
  "geometry": {"coordinates":[8.2574167252,45.7293128967],"type":"Point"}
}