{
  "type": "Feature",
  "properties": {
    "addr:full":"39014 Postal Postal Bolzano/Bozen 39014",
    "addr:postcode":"39014;39014",
    "iso:country":"IT",
    "sg:address":"39014 Postal",
    "sg:city":"Postal",
    "sg:orig_category":"Carni, Salumi E Pesci",
    "sg:phone":"+39 0473 291373",
    "sg:postcode":"39014",
    "sg:province":"Bolzano/Bozen",
    "wof:name":"Zoggeler F. & S. Snc",
    "wof:placetype":"venue"
},
  "geometry": {"coordinates":[11.342319,46.490051],"type":"Point"}
}