{
  "type": "Feature",
  "properties": {
    "iso:country":"IT",
    "sg:address":"Via Della Resistenza 67 Localita Badesse; Monteriggioni/sienna",
    "sg:classifiers":[
        {
            "category":"Travel",
            "subcategory":"Travel Agent",
            "type":"Entertainment"
        }
    ],
    "wof:name":"Best Western La Residenza Delle Badesse",
    "wof:placetype":"venue"
},
  "geometry": {"coordinates":[11.274549,43.382835],"type":"Point"}
}