{
  "type": "Feature",
  "properties": {
    "iso:country":"IT",
    "sg:address":"95123 Catania",
    "sg:city":"Catania",
    "sg:orig_category":"Bomboniere Ed Accessori",
    "sg:phone":"+39 348 733 8542",
    "sg:postcode":"95123",
    "sg:province":"Catania",
    "wof:name":"Rocaille Di Monaco Giuseppa",
    "wof:placetype":"venue"
},
  "geometry": {"coordinates":[15.060095,37.563732],"type":"Point"}
}