{
  "type": "Feature",
  "properties": {
    "iso:country":"IT",
    "sg:address":"15, V. S. Teresa 88838 Mesoraca",
    "sg:city":"Mesoraca",
    "sg:classifiers":[
        {
            "category":"Manufacturing",
            "subcategory":"Lumber",
            "type":"Manufacturing & Wholesale Goods"
        }
    ],
    "sg:phone":"+39 096245199835",
    "sg:postcode":"88838",
    "sg:province":"Crotone",
    "sg:tags":[
        "wood"
    ],
    "sg:website":"http://www.paginegialle.it/",
    "wof:name":"Impresa Boschiva Carnovale",
    "wof:placetype":"venue"
},
  "geometry": {"coordinates":[17.127079,39.080738],"type":"Point"}
}