{
  "type": "Feature",
  "properties": {
    "iso:country":"IT",
    "sg:address":"38037 Predazzo",
    "sg:city":"Predazzo",
    "sg:orig_category":"Legno E Semilavorati. Articoli Per Imballaggio E Confezionamento",
    "sg:phone":"+39 0462 501115",
    "sg:postcode":"38037",
    "sg:province":"Trento",
    "wof:name":"Imballaggi Piazzi Di Marco E Giorgio & C. Snc",
    "wof:placetype":"venue"
},
  "geometry": {"coordinates":[11.596447,46.32077],"type":"Point"}
}