{
  "type": "Feature",
  "properties": {
    "addr:full":"25030 Rudiano Rudiano Brescia 25030",
    "addr:postcode":"25030;25030",
    "iso:country":"IT",
    "sg:address":"25030 Rudiano",
    "sg:city":"Rudiano",
    "sg:orig_category":"Servizi E Lavori Per Arredamento E Industria Del Legno. Servizi E Lavori Per Edilizia E Lavori Pubblici",
    "sg:phone":"+39 030 716 7088",
    "sg:postcode":"25030",
    "sg:province":"Brescia",
    "wof:name":"Rossi Angelo",
    "wof:placetype":"venue"
},
  "geometry": {"coordinates":[10.184527,45.580566],"type":"Point"}
}