{
  "type": "Feature",
  "properties": {
    "iso:country":"IT",
    "sg:address":"Viale Nino Bixio 1, 31100 Treviso, Tv",
    "sg:city":"Treviso",
    "sg:classifiers":[
        {
            "category":"Banks & Credit Unions",
            "subcategory":"Bank",
            "type":"Services"
        }
    ],
    "sg:phone":"+39 0422 697411",
    "sg:postcode":"31100",
    "sg:province":"Treviso",
    "wof:name":"Banca Italo-romena Spa",
    "wof:placetype":"venue"
},
  "geometry": {"coordinates":[12.16978,45.600018],"type":"Point"}
}