{
  "type": "Feature",
  "properties": {
    "addr:full":"21052 Busto Arsizio Busto Arsizio Varese 21052",
    "addr:postcode":"21052;21052",
    "iso:country":"IT",
    "sg:address":"21052 Busto Arsizio",
    "sg:city":"Busto Arsizio",
    "sg:orig_category":"Mobili Metallici Ufficio",
    "sg:phone":"+39 0331 626790",
    "sg:postcode":"21052",
    "sg:province":"Varese",
    "wof:name":"Tmb Srl",
    "wof:placetype":"venue"
},
  "geometry": {"coordinates":[8.8548440933,45.6145439148],"type":"Point"}
}