{
  "type": "Feature",
  "properties": {
    "addr:full":"31100 Treviso Treviso Treviso 31100",
    "addr:postcode":"31100;31100",
    "iso:country":"IT",
    "sg:address":"31100 Treviso",
    "sg:city":"Treviso",
    "sg:orig_category":"Automobili E Mezzi Di Trasporto. Riparazione Dei Mezzi Di Trasporto",
    "sg:phone":"+39 0422 5721",
    "sg:postcode":"31100",
    "sg:province":"Treviso",
    "sg:website":"http://www.zorzi.com",
    "wof:name":"Zorzi Spa",
    "wof:placetype":"venue"
},
  "geometry": {"coordinates":[12.18887043,45.6681632996],"type":"Point"}
}