{
  "type": "Feature",
  "properties": {
    "iso:country":"IT",
    "sg:address":"19, Via Col De Rust 33070 Caneva",
    "sg:city":"Caneva",
    "sg:classifiers":[
        {
            "category":"Shopping",
            "subcategory":"Stationery & Office Supplies",
            "type":"Retail Goods"
        }
    ],
    "sg:phone":"+39 0434 777333",
    "sg:postcode":"33070",
    "sg:province":"Pordenone",
    "sg:tags":[
        "professional"
    ],
    "wof:name":"C.m.c. S.r.l.",
    "wof:placetype":"venue"
},
  "geometry": {"coordinates":[12.466591835,45.997051239],"type":"Point"}
}