{
  "type": "Feature",
  "properties": {
    "addr:full":"28/2, Via Per Molteno 23848 Oggiono Oggiono Lecco 23848",
    "addr:housenumber":"28 / 2",
    "addr:postcode":"23848;23848",
    "addr:street":"Via Per Molteno",
    "iso:country":"IT",
    "sg:address":"28/2, Via Per Molteno 23848 Oggiono",
    "sg:city":"Oggiono",
    "sg:classifiers":[
        {
            "category":"Shopping",
            "subcategory":"Crafts & Fabrics",
            "type":"Retail Goods"
        }
    ],
    "sg:phone":"+39 0341 260497",
    "sg:postcode":"23848",
    "sg:province":"Lecco",
    "wof:name":"Castello Del Barro (s.r.l.)",
    "wof:placetype":"venue"
},
  "geometry": {"coordinates":[9.3609294891,45.8066329956],"type":"Point"}
}