{
  "type": "Feature",
  "properties": {
    "iso:country":"IT",
    "sg:address":"130, Regione Annunziata 12064 La Morra",
    "sg:city":"La Morra",
    "sg:classifiers":[
        {
            "category":"Professional",
            "subcategory":"Engineering",
            "type":"Services"
        }
    ],
    "sg:phone":"+39 0173 509589",
    "sg:postcode":"12064",
    "sg:province":"Cuneo",
    "sg:tags":[
        "machine",
        "-",
        "mechanical"
    ],
    "wof:name":"Cravanzola Roberto & Veglio Bruno Snc",
    "wof:placetype":"venue"
},
  "geometry": {"coordinates":[7.922998,44.67141],"type":"Point"}
}