{
  "type": "Feature",
  "properties": {
    "addr:full":"10135 Torino Torino Torino 10135",
    "addr:postcode":"10135;10135",
    "iso:country":"IT",
    "sg:address":"10135 Torino",
    "sg:city":"Torino",
    "sg:orig_category":"Lavorazioni Meccaniche E Servizi",
    "sg:phone":"+39 011 347 2363",
    "sg:postcode":"10135",
    "sg:province":"Torino",
    "wof:name":"Chiabotto Michele",
    "wof:placetype":"venue"
},
  "geometry": {"coordinates":[7.568359,45.068111],"type":"Point"}
}