{
  "type": "Feature",
  "properties": {
    "addr:full":"Via Pasubio 17 36034 Malo Malo Vicenza 36034",
    "addr:housenumber":"17",
    "addr:postcode":"36034;36034",
    "addr:street":"Via Pasubio",
    "iso:country":"IT",
    "sg:address":"Via Pasubio 17 36034 Malo",
    "sg:city":"Malo",
    "sg:classifiers":[
        {
            "category":"Train Station",
            "subcategory":"Light Rail",
            "type":"Transportation"
        }
    ],
    "sg:phone":"+39 0445 595311",
    "sg:postcode":"36034",
    "sg:province":"Vicenza",
    "sg:tags":[
        "pot",
        "flower"
    ],
    "sg:website":"www.deroma.it",
    "wof:name":"Deroma Spa",
    "wof:placetype":"venue"
},
  "geometry": {"coordinates":[11.540307045,45.5459060669],"type":"Point"}
}