{
  "type": "Feature",
  "properties": {
    "addr:full":"Via Are 212 37026 Pescantina Pescantina Verona 37026",
    "addr:housenumber":"212",
    "addr:postcode":"37026;37026",
    "addr:street":"Via Are",
    "iso:country":"IT",
    "sg:address":"Via Are 212 37026 Pescantina",
    "sg:city":"Pescantina",
    "sg:orig_category":"Ladies' Shoes",
    "sg:phone":"+39 045 715 0372",
    "sg:postcode":"37026",
    "sg:province":"Verona",
    "wof:name":"Calzaturificio Trebi Di Banterle Gabriele E F.lli Snc",
    "wof:placetype":"venue"
},
  "geometry": {"coordinates":[10.875047,45.481384],"type":"Point"}
}