{
  "type": "Feature",
  "properties": {
    "iso:country":"IT",
    "sg:address":"Via S. Pertini 8-z.i. A 62012 Civitanova Marche",
    "sg:city":"Civitanova Marche",
    "sg:orig_category":"Soles, Heels",
    "sg:phone":"+39 0733 800111",
    "sg:postcode":"62012",
    "sg:province":"Macerata",
    "sg:website":"www.eurosuole.com",
    "wof:name":"Eurosuole Spa",
    "wof:placetype":"venue"
},
  "geometry": {"coordinates":[13.456262,43.300747],"type":"Point"}
}