{
  "type": "Feature",
  "properties": {
    "iso:country":"IT",
    "sg:address":"10152 Torino",
    "sg:city":"Torino",
    "sg:orig_category":"Macchine, Impianti E Forniture Per Industria Grafica, Cartaria E Cartotecnica",
    "sg:phone":"+39 011 852891",
    "sg:postcode":"10152",
    "sg:province":"Torino",
    "wof:name":"Binder",
    "wof:placetype":"venue"
},
  "geometry": {"coordinates":[7.695519,45.079723],"type":"Point"}
}