{
  "type": "Feature",
  "properties": {
    "addr:full":"10064 Pinerolo Pinerolo Torino 10064",
    "addr:postcode":"10064;10064",
    "iso:country":"IT",
    "sg:address":"10064 Pinerolo",
    "sg:city":"Pinerolo",
    "sg:orig_category":"Macchine, Impianti E Forniture Per Industria Grafica, Cartaria E Cartotecnica",
    "sg:phone":"+39 0121 322542",
    "sg:postcode":"10064",
    "sg:province":"Torino",
    "wof:name":"Camusso Ettore",
    "wof:placetype":"venue"
},
  "geometry": {"coordinates":[7.345604,44.883583],"type":"Point"}
}