{
  "type": "Feature",
  "properties": {
    "iso:country":"IT",
    "sg:address":"37060 Castel D'azzano",
    "sg:city":"Azzano",
    "sg:orig_category":"Centri Di Estetica E Cosmesi E Servizi",
    "sg:phone":"+39 045 852 0753",
    "sg:postcode":"37060",
    "sg:province":"Verona",
    "wof:name":"Centro Di Estetica Di Campedelli Clarice",
    "wof:placetype":"venue"
},
  "geometry": {"coordinates":[11.02362,45.441444],"type":"Point"}
}