{
  "type": "Feature",
  "properties": {
    "addr:full":"04019 Terracina Terracina Latina 04019",
    "addr:postcode":"04019;04019",
    "iso:country":"IT",
    "sg:address":"04019 Terracina",
    "sg:city":"Terracina",
    "sg:orig_category":"Cine-foto-ottica. Shopping",
    "sg:phone":"+39 0773 732090",
    "sg:postcode":"04019",
    "sg:province":"Latina",
    "wof:name":"Sey Shop Moment D'amour",
    "wof:placetype":"venue"
},
  "geometry": {"coordinates":[13.197106,41.336266],"type":"Point"}
}