{
  "type": "Feature",
  "properties": {
    "iso:country":"IT",
    "sg:address":"67100 L'aquila",
    "sg:orig_category":"Servizi Ausiliari Di Analisi, Controllo E Ricerca. Acqua, Luce, Gas E Societa' Di Esercizio Pubblico",
    "sg:phone":"+39 0862 400008",
    "sg:postcode":"67100",
    "sg:province":"L'Aquila",
    "wof:name":"Osservatorio Astronomico Di Roma",
    "wof:placetype":"venue"
},
  "geometry": {"coordinates":[13.508463,42.416721],"type":"Point"}
}