{
  "type": "Feature",
  "properties": {
    "iso:country":"IT",
    "sg:address":"05018 Orvieto",
    "sg:city":"Orvieto",
    "sg:orig_category":"Attrezzature E Forniture Per Officine Riparazione E Servizi Ausiliari",
    "sg:phone":"+39 0763 301989",
    "sg:postcode":"05018",
    "sg:province":"Terni",
    "wof:name":"Autofficina Luzi Luigi",
    "wof:placetype":"venue"
},
  "geometry": {"coordinates":[12.130985,42.723213],"type":"Point"}
}