{
  "type": "Feature",
  "properties": {
    "iso:country":"IT",
    "sg:address":"19/4, V. Laterza 70029 Santeramo In Colle",
    "sg:city":"Santeramo in Colle",
    "sg:classifiers":[
        {
            "category":"Parking",
            "subcategory":"Lot",
            "type":"Transportation"
        }
    ],
    "sg:phone":"+39 080 302 3716",
    "sg:postcode":"70029",
    "sg:province":"Bari",
    "sg:tags":[
        "transport",
        "road"
    ],
    "sg:website":"http://www.paginegialle.it/meluzzo",
    "wof:name":"Agenzia Funebre Meluzzo",
    "wof:placetype":"venue"
},
  "geometry": {"coordinates":[16.758438,40.792557],"type":"Point"}
}