{
  "type": "Feature",
  "properties": {
    "iso:country":"IT",
    "sg:address":"06059 Todi",
    "sg:city":"Pantalla",
    "sg:orig_category":"Articoli Per Imballaggio E Confezionamento",
    "sg:phone":"+39 075 888174",
    "sg:postcode":"06059",
    "sg:province":"Perugia",
    "sg:website":"http://www.baccarelli.it",
    "wof:name":"Baccarelli Nazzareno Srl",
    "wof:placetype":"venue"
},
  "geometry": {"coordinates":[12.400314,42.874241],"type":"Point"}
}