{
  "type": "Feature",
  "properties": {
    "iso:country":"IT",
    "sg:address":"20034 Giussano",
    "sg:city":"Giussano",
    "sg:orig_category":"Dottori Commercialisti - Studi",
    "sg:phone":"+39 036 285 1415",
    "sg:postcode":"20034",
    "sg:province":"Milano",
    "wof:name":"Barzaghi Dr. Gianni",
    "wof:placetype":"venue"
},
  "geometry": {"coordinates":[9.173182,45.460251],"type":"Point"}
}