{
  "type": "Feature",
  "properties": {
    "addr:full":"20037 Paderno Dugnano Paderno Dugnano Milano 20037",
    "addr:postcode":"20037;20037",
    "iso:country":"IT",
    "sg:address":"20037 Paderno Dugnano",
    "sg:city":"Paderno Dugnano",
    "sg:classifiers":[
        {
            "category":"Restaurant",
            "type":"Food & Drink"
        }
    ],
    "sg:phone":"+39 02 9904 3680",
    "sg:postcode":"20037",
    "sg:province":"Milano",
    "sg:tags":[
        "equipment",
        "industry",
        "machinery"
    ],
    "wof:name":"Nima Erre.ti Packaging Srl",
    "wof:placetype":"venue"
},
  "geometry": {"coordinates":[9.185092926,45.5603523254],"type":"Point"}
}