{
  "type": "Feature",
  "properties": {
    "iso:country":"IT",
    "sg:address":"4, Via Enrico Fermi 10040 Caselette",
    "sg:city":"Caselette",
    "sg:classifiers":[
        {
            "category":"Manufacturing",
            "subcategory":"Metals",
            "type":"Manufacturing & Wholesale Goods"
        }
    ],
    "sg:phone":"+39 011 968 8691",
    "sg:postcode":"10040",
    "sg:province":"Torino",
    "sg:tags":[
        "metallurgy",
        "metalworking"
    ],
    "wof:name":"Fonderia L.e.a. S.r.l.",
    "wof:placetype":"venue"
},
  "geometry": {"coordinates":[7.4957838058,45.1062507629],"type":"Point"}
}