{
  "type": "Feature",
  "properties": {
    "addr:full":"00198 Roma Roma Roma 00198",
    "addr:postcode":"00198;00198",
    "iso:country":"IT",
    "sg:address":"00198 Roma",
    "sg:city":"Roma",
    "sg:orig_category":"Scuole E Servizi Scolastici. Ricerca, Selezione E Formazione Del Personale",
    "sg:phone":"+39 06 855 7078",
    "sg:postcode":"00198",
    "sg:province":"Roma",
    "sg:website":"http://www.istitutoquasar.com",
    "wof:name":"Istituto Quasar",
    "wof:placetype":"venue"
},
  "geometry": {"coordinates":[12.5036211014,41.9140319824],"type":"Point"}
}