{
  "type": "Feature",
  "properties": {
    "addr:full":"50059 Vinci Vinci Firenze 50059",
    "addr:postcode":"50059;50059",
    "iso:country":"IT",
    "sg:address":"50059 Vinci",
    "sg:city":"Vinci",
    "sg:orig_category":"Canne Fumarie, Ciminiere E Camini",
    "sg:phone":"+39 0571 508339",
    "sg:postcode":"50059",
    "sg:province":"Firenze",
    "wof:name":"Nuova Idrotermo Snc",
    "wof:placetype":"venue"
},
  "geometry": {"coordinates":[10.934161,43.726616],"type":"Point"}
}