{
  "type": "Feature",
  "properties": {
    "iso:country":"IT",
    "sg:address":"09124 Cagliari",
    "sg:city":"Cagliari",
    "sg:classifiers":[
        {
            "category":"Health Services",
            "subcategory":"Health Practitioner",
            "type":"Services"
        }
    ],
    "sg:phone":"+39 070 650677",
    "sg:postcode":"09124",
    "sg:province":"Cagliari",
    "sg:tags":[
        "medici"
    ],
    "wof:name":"Scarpa Antonio Luigi",
    "wof:placetype":"venue"
},
  "geometry": {"coordinates":[9.1138219833,39.2160263062],"type":"Point"}
}