{
  "type": "Feature",
  "properties": {
    "iso:country":"IT",
    "sg:address":"Via Ravegnana 139 48018 Faenza",
    "sg:city":"Faenza",
    "sg:classifiers":[
        {
            "category":"Shopping",
            "subcategory":"Crafts & Fabrics",
            "type":"Retail Goods"
        }
    ],
    "sg:phone":"+39 0546 667380",
    "sg:postcode":"48018",
    "sg:province":"Ravenna",
    "sg:tags":[
        "decorative",
        "ceramic",
        "artistic"
    ],
    "sg:website":"www.girasoleceramiche.it",
    "wof:name":"Girasole Srl",
    "wof:placetype":"venue"
},
  "geometry": {"coordinates":[12.00582,44.347797],"type":"Point"}
}