{
  "type": "Feature",
  "properties": {
    "iso:country":"IT",
    "sg:address":"20131 Milano",
    "sg:city":"Milano",
    "sg:orig_category":"Automazione E Macchine Per Ufficio",
    "sg:phone":"+39 02 2611 3028",
    "sg:postcode":"20131",
    "sg:province":"Milano",
    "wof:name":"Punto Stampa Discount Leoncavallo",
    "wof:placetype":"venue"
},
  "geometry": {"coordinates":[9.225144,45.490845],"type":"Point"}
}