{
  "type": "Feature",
  "properties": {
    "iso:country":"IT",
    "sg:address":"41100 Modena",
    "sg:city":"Modena",
    "sg:classifiers":[
        {
            "category":"Social Services",
            "subcategory":"Job Training",
            "type":"Services"
        }
    ],
    "sg:phone":"+39 059 205 6511",
    "sg:postcode":"41100",
    "sg:province":"Modena",
    "sg:tags":[
        "services",
        "personnel",
        "school",
        "educational",
        "recruitment"
    ],
    "sg:website":"http://www.unimo.it",
    "wof:name":"Universit\u00c0 Degli Studi Di Modena E Reggio Emilia",
    "wof:placetype":"venue"
},
  "geometry": {"coordinates":[10.927855,44.644958],"type":"Point"}
}