{
  "type": "Feature",
  "properties": {
    "addr:full":"Via Marangoni, 4/6 20030 Bovisio Masciago Bovisio Milano 20030",
    "addr:housenumber":"4 / 6",
    "addr:postcode":"20030;20030",
    "addr:street":"Via Marangoni",
    "iso:country":"IT",
    "sg:address":"Via Marangoni, 4/6 20030 Bovisio Masciago",
    "sg:city":"Bovisio",
    "sg:classifiers":[
        {
            "category":"Communications",
            "subcategory":"Film & Video Production",
            "type":"Services"
        }
    ],
    "sg:phone":"+39 036 259 2208",
    "sg:postcode":"20030",
    "sg:province":"Milano",
    "sg:tags":[
        "picture",
        "framing",
        "accessory"
    ],
    "wof:name":"Aste Briantea Srl",
    "wof:placetype":"venue"
},
  "geometry": {"coordinates":[9.1435918808,45.6111335754],"type":"Point"}
}