{
  "type": "Feature",
  "properties": {
    "addr:full":"Piazza Garibaldi, 45/46; Bari; 70100",
    "addr:housenumber":"45 / 46",
    "addr:postcode":"70100",
    "addr:street":"Piazza Garibaldi",
    "iso:country":"IT",
    "sg:address":"Piazza Garibaldi, 45/46; Bari; 70100",
    "sg:classifiers":[
        {
            "category":"Banks & Credit Unions",
            "subcategory":"Bank",
            "type":"Services"
        }
    ],
    "sg:phone":"+39 080 521 0995",
    "wof:name":"Banca Nazionale Del Lavoro",
    "wof:placetype":"venue"
},
  "geometry": {"coordinates":[16.862896,41.125149],"type":"Point"}
}