{
  "type": "Feature",
  "properties": {
    "iso:country":"IT",
    "sg:address":"60019 Senigallia",
    "sg:city":"Senigallia",
    "sg:orig_category":"Materiali E Componenti Elettrotecnici",
    "sg:phone":"+39 071 792 3670",
    "sg:postcode":"60019",
    "sg:province":"Ancona",
    "wof:name":"L.a.m. Sas Di Magnini Velia & C.",
    "wof:placetype":"venue"
},
  "geometry": {"coordinates":[13.204335,43.708141],"type":"Point"}
}