{
  "type": "Feature",
  "properties": {
    "iso:country":"IT",
    "sg:address":"59100 Prato",
    "sg:city":"Prato",
    "sg:orig_category":"Prodotti Chimici",
    "sg:phone":"+39 0574 622448",
    "sg:postcode":"59100",
    "sg:province":"Prato",
    "sg:website":"http://www.lafprato.com",
    "wof:name":"L.a.f. Srl",
    "wof:placetype":"venue"
},
  "geometry": {"coordinates":[11.0750455856,43.8904342651],"type":"Point"}
}