{
  "type": "Feature",
  "properties": {
    "iso:country":"IT",
    "sg:address":"6, Via Isonzo 24040 Stezzano",
    "sg:city":"Stezzano",
    "sg:classifiers":[
        {
            "category":"Shopping",
            "subcategory":"Crafts & Fabrics",
            "type":"Retail Goods"
        }
    ],
    "sg:phone":"+39 035 454 5011",
    "sg:postcode":"24040",
    "sg:province":"Bergamo",
    "sg:tags":[
        "linen"
    ],
    "wof:name":"Proget S.p.a.",
    "wof:placetype":"venue"
},
  "geometry": {"coordinates":[9.6496124268,45.6497268677],"type":"Point"}
}