{
  "type": "Feature",
  "properties": {
    "iso:country":"IT",
    "sg:address":"80132 Napoli",
    "sg:city":"Napoli",
    "sg:orig_category":"Agenzie Investigative",
    "sg:phone":"+39 081 764 5661",
    "sg:postcode":"80132",
    "sg:province":"Napoli",
    "sg:website":"http://www.partenopol.it",
    "wof:name":"Partenopol Sas",
    "wof:placetype":"venue"
},
  "geometry": {"coordinates":[14.245849,40.833103],"type":"Point"}
}