{
  "type": "Feature",
  "properties": {
    "addr:full":"20122 Milano Milano Milano 20122",
    "addr:postcode":"20122;20122",
    "iso:country":"IT",
    "sg:address":"20122 Milano",
    "sg:city":"Milano",
    "sg:orig_category":"Petroli, Gas E Combustibili",
    "sg:phone":"+39 02 875061",
    "sg:postcode":"20122",
    "sg:province":"Milano",
    "wof:name":"I.p.l.o.m. (s.p.a.)",
    "wof:placetype":"venue"
},
  "geometry": {"coordinates":[9.1904144287,45.4600601196],"type":"Point"}
}