{
  "type": "Feature",
  "properties": {
    "iso:country":"IT",
    "sg:address":"13900 Biella",
    "sg:city":"Biella",
    "sg:orig_category":"Servizi E Lavori Per Abbigliamento E Pelletterie",
    "sg:phone":"+39 015 405821",
    "sg:postcode":"13900",
    "sg:province":"Biella",
    "wof:name":"Varale Antonio",
    "wof:placetype":"venue"
},
  "geometry": {"coordinates":[8.045113,45.559654],"type":"Point"}
}