{
  "type": "Feature",
  "properties": {
    "addr:full":"25, Via Luigi Cacciatore 72020 Cellino S. Marco Brindisi 72020",
    "addr:postcode":"72020;72020",
    "addr:street":"Via Luigi Cacciatore",
    "iso:country":"IT",
    "sg:address":"25, Via Luigi Cacciatore 72020 Cellino S. Marco",
    "sg:classifiers":[
        {
            "category":"Food & Beverages",
            "subcategory":"Groceries & Convenience Stores",
            "type":"Retail Goods"
        }
    ],
    "sg:phone":"+39 0831 619710",
    "sg:postcode":"72020",
    "sg:province":"Brindisi",
    "sg:tags":[
        "product",
        "related"
    ],
    "wof:name":"Greens & Grill Di Gravili Salvatore",
    "wof:placetype":"venue"
},
  "geometry": {"coordinates":[17.9389915466,40.636177063],"type":"Point"}
}