{
  "type": "Feature",
  "properties": {
    "iso:country":"IT",
    "sg:address":"Via Majorana , 10/12 36045 Lonigo",
    "sg:city":"Lonigo",
    "sg:classifiers":[
        {
            "category":"Shopping",
            "subcategory":"Pets & Pet Supplies",
            "type":"Retail Goods"
        }
    ],
    "sg:phone":"+39 0444 436491",
    "sg:postcode":"36045",
    "sg:province":"Vicenza",
    "sg:website":"www.fop.it",
    "wof:name":"Fop Spa",
    "wof:placetype":"venue"
},
  "geometry": {"coordinates":[11.3716688156,45.3943252563],"type":"Point"}
}