{
  "type": "Feature",
  "properties": {
    "iso:country":"IT",
    "sg:address":"20060 Basiano",
    "sg:city":"Basiano",
    "sg:orig_category":"Professionisti - Studi E Servizi Ed Associazioni Di Interesse Aziendale. Associazioni Ed Organismi Di Interesse Pubblico",
    "sg:phone":"+39 02 9576 2007",
    "sg:postcode":"20060",
    "sg:province":"Milano",
    "wof:name":"Partito Democratico Della Sinistra",
    "wof:placetype":"venue"
},
  "geometry": {"coordinates":[9.467382431,45.5716133118],"type":"Point"}
}