{
  "type": "Feature",
  "properties": {
    "addr:full":"13884 Sala Biellese Sala Biellese Biella 13884",
    "addr:housenumber":"13884 sala;sala",
    "addr:postcode":"13884",
    "addr:street":"Biellese",
    "iso:country":"IT",
    "sg:address":"13884 Sala Biellese",
    "sg:city":"Sala Biellese",
    "sg:orig_category":"Servizi E Lavori Per Edilizia E Lavori Pubblici",
    "sg:phone":"+39 015 255 1297",
    "sg:postcode":"13884",
    "sg:province":"Biella",
    "wof:name":"Raimondo Giovanni",
    "wof:placetype":"venue"
},
  "geometry": {"coordinates":[8.008069,45.518143],"type":"Point"}
}