{
  "type": "Feature",
  "properties": {
    "iso:country":"IT",
    "sg:address":"50143 Firenze",
    "sg:city":"Firenze",
    "sg:orig_category":"Macchine E Forniture Per Ecologia E Smaltimento Rifiuti. Termotecnica E Riscaldamento, Apparecchiature E Servizi",
    "sg:phone":"+39 055 732 7229",
    "sg:postcode":"50143",
    "sg:province":"Firenze",
    "wof:name":"Pezzati Impianti Di Pezzati Valerio",
    "wof:placetype":"venue"
},
  "geometry": {"coordinates":[11.202537,43.766983],"type":"Point"}
}