{
  "type": "Feature",
  "properties": {
    "addr:full":"91, Via Manin Daniele 35010 Vigodarzere Vigodarzere Padova 35010",
    "addr:postcode":"35010;35010",
    "addr:street":"Via Manin Daniele",
    "iso:country":"IT",
    "sg:address":"91, Via Manin Daniele 35010 Vigodarzere",
    "sg:city":"Vigodarzere",
    "sg:classifiers":[
        {
            "category":"Shopping",
            "type":"Retail Goods"
        }
    ],
    "sg:phone":"+39 39049702333",
    "sg:postcode":"35010",
    "sg:province":"Padova",
    "sg:tags":[
        "finished",
        "-",
        "metallic"
    ],
    "wof:name":"Modelleria Unita Di R. Guadagnin G.p. Turato E C. (s.n.c.)",
    "wof:placetype":"venue"
},
  "geometry": {"coordinates":[11.8940534592,45.4535064697],"type":"Point"}
}