{
  "type": "Feature",
  "properties": {
    "addr:full":"Via Capparola 1 25078 Vestone Vestone Brescia 25078",
    "addr:housenumber":"1",
    "addr:postcode":"25078;25078",
    "addr:street":"Via Capparola",
    "iso:country":"IT",
    "sg:address":"Via Capparola 1 25078 Vestone",
    "sg:city":"Vestone",
    "sg:orig_category":"Brass Items, Artisans'",
    "sg:phone":"+39 036 581660",
    "sg:postcode":"25078",
    "sg:province":"Brescia",
    "sg:website":"www.levrangi.com",
    "wof:name":"Levrangi Di Levrangi Uberto E C. S.n.c.",
    "wof:placetype":"venue"
},
  "geometry": {"coordinates":[10.409634,45.714024],"type":"Point"}
}