{
  "type": "Feature",
  "properties": {
    "iso:country":"IT",
    "sg:address":"43058 Sorbolo",
    "sg:city":"Sorbolo",
    "sg:orig_category":"Mangimi, Foraggi Ed Integratori Zootecnici",
    "sg:phone":"+39 0521 604101",
    "sg:postcode":"43058",
    "sg:province":"Parma",
    "wof:name":"Carra Artemio Srl",
    "wof:placetype":"venue"
},
  "geometry": {"coordinates":[10.404383,44.831627],"type":"Point"}
}