{
  "type": "Feature",
  "properties": {
    "addr:full":"Piazza Vittorio; Castellazzo Bormida; 15073 Castellazzo Bormida Alessandria 15073",
    "addr:postcode":"15073;15073",
    "addr:street":"Piazza Vittorio Castellazzo Bormida",
    "iso:country":"IT",
    "sg:address":"Piazza Vittorio; Castellazzo Bormida; 15073",
    "sg:city":"Castellazzo Bormida",
    "sg:classifiers":[
        {
            "category":"Banks & Credit Unions",
            "subcategory":"Bank",
            "type":"Services"
        }
    ],
    "sg:phone":"+39 0131 275733",
    "sg:postcode":"15073",
    "sg:province":"Alessandria",
    "wof:name":"Istituto Bancario, San Paolo Di Torino Spa",
    "wof:placetype":"venue"
},
  "geometry": {"coordinates":[8.575274,44.844906],"type":"Point"}
}