{
  "type": "Feature",
  "properties": {
    "addr:full":"128, Strada Provinciale Maceratese 62012 Civitanova Marche Civitanova Marche Macerata 62012",
    "addr:postcode":"62012;62012",
    "addr:street":"Strada Provinciale Maceratese",
    "iso:country":"IT",
    "sg:address":"128, Strada Provinciale Maceratese 62012 Civitanova Marche",
    "sg:city":"Civitanova Marche",
    "sg:classifiers":[
        {
            "category":"Personal",
            "subcategory":"Shoe Repair & Shine",
            "type":"Services"
        }
    ],
    "sg:phone":"+39 0733 898824",
    "sg:postcode":"62012",
    "sg:province":"Macerata",
    "sg:tags":[
        "leather"
    ],
    "wof:name":"Calzaturificio Confort S.n.c.",
    "wof:placetype":"venue"
},
  "geometry": {"coordinates":[13.456262,43.300747],"type":"Point"}
}