{
  "type": "Feature",
  "properties": {
    "iso:country":"IT",
    "sg:address":"20154 Milano",
    "sg:city":"Milano",
    "sg:orig_category":"Prodotti Alimentari",
    "sg:phone":"+39 02 345 1693",
    "sg:postcode":"20154",
    "sg:province":"Milano",
    "wof:name":"Liberatore Enrico",
    "wof:placetype":"venue"
},
  "geometry": {"coordinates":[9.1619338989,45.4873657227],"type":"Point"}
}