{
  "type": "Feature",
  "properties": {
    "addr:full":"60019 Senigallia Senigallia Ancona 60019",
    "addr:postcode":"60019;60019",
    "iso:country":"IT",
    "sg:address":"60019 Senigallia",
    "sg:city":"Senigallia",
    "sg:orig_category":"Fotografia - Servizi, Studi, Sviluppo E Stampa",
    "sg:phone":"+39 071 659252",
    "sg:postcode":"60019",
    "sg:province":"Ancona",
    "wof:name":"Costantini Nello",
    "wof:placetype":"venue"
},
  "geometry": {"coordinates":[13.2184438705,43.7145385742],"type":"Point"}
}