{
  "type": "Feature",
  "properties": {
    "iso:country":"IT",
    "sg:address":"64024 Notaresco",
    "sg:city":"Notaresco",
    "sg:classifiers":[
        {
            "category":"Home & Garden",
            "subcategory":"Furniture",
            "type":"Retail Goods"
        }
    ],
    "sg:phone":"+39 085 895 8666",
    "sg:postcode":"64024",
    "sg:province":"Teramo",
    "sg:tags":[
        "furnishing"
    ],
    "wof:name":"Fedele M Dei F.lli Leo & Luigi Fedele",
    "wof:placetype":"venue"
},
  "geometry": {"coordinates":[13.8648118973,42.7294197083],"type":"Point"}
}