{
  "type": "Feature",
  "properties": {
    "iso:country":"IT",
    "sg:address":"55060 Piegaio",
    "sg:orig_category":"Articoli Per Imballaggio E Confezionamento",
    "sg:phone":"+39 0583 359820",
    "sg:postcode":"55060",
    "sg:province":"Lucca",
    "wof:name":"Tielle (s.r.l.)",
    "wof:placetype":"venue"
},
  "geometry": {"coordinates":[10.420444,43.955536],"type":"Point"}
}