{
  "type": "Feature",
  "properties": {
    "iso:country":"IT",
    "sg:address":"40129 Bologna",
    "sg:city":"Bologna",
    "sg:orig_category":"Arredi Ed Attrezzature Per Uffici",
    "sg:phone":"+39 051 326236",
    "sg:postcode":"40129",
    "sg:province":"Bologna",
    "sg:website":"http://www.seda-da.it",
    "wof:name":"S.e.d.a. Srl",
    "wof:placetype":"venue"
},
  "geometry": {"coordinates":[11.347674,44.535789],"type":"Point"}
}