{
  "type": "Feature",
  "properties": {
    "addr:full":"Via Artigianato 4 31025 Santa Lucia Di Piave Santa Lucia di Piave Treviso 31025",
    "addr:housenumber":"4",
    "addr:postcode":"31025;31025",
    "addr:street":"Via Artigianato",
    "iso:country":"IT",
    "sg:address":"Via Artigianato 4 31025 Santa Lucia Di Piave",
    "sg:city":"Santa Lucia di Piave",
    "sg:classifiers":[
        {
            "category":"Manufacturing",
            "subcategory":"Motor Vehicles & Parts",
            "type":"Manufacturing & Wholesale Goods"
        }
    ],
    "sg:phone":"+39 0438 64846",
    "sg:postcode":"31025",
    "sg:province":"Treviso",
    "sg:tags":[
        "bolts",
        "shaped",
        "component",
        "nuts",
        "dy",
        "carbide",
        "rivets"
    ],
    "wof:name":"Pamek Di Pasqualotti Giovanni",
    "wof:placetype":"venue"
},
  "geometry": {"coordinates":[12.274223,45.857132],"type":"Point"}
}