{
  "type": "Feature",
  "properties": {
    "addr:full":"84128 Salerno Salerno Salerno 84128",
    "addr:postcode":"84128;84128",
    "iso:country":"IT",
    "sg:address":"84128 Salerno",
    "sg:city":"Salerno",
    "sg:orig_category":"Impiantistica E Prodotti Tecnologici Per Edilizia. Elettrotecnica Professionale E Di Consumo. Telecomunicazioni E Telefonia, Impianti, Apparecchi E Servizi",
    "sg:phone":"+39 089 72368",
    "sg:postcode":"84128",
    "sg:province":"Salerno",
    "sg:website":"http://www.videosud.it",
    "wof:name":"Video Sud Di Lamberti Alfonso",
    "wof:placetype":"venue"
},
  "geometry": {"coordinates":[14.792723,40.666439],"type":"Point"}
}