{
  "type": "Feature",
  "properties": {
    "iso:country":"IT",
    "sg:address":"Via Matteotti 6 24050 Grassobbio",
    "sg:city":"Grassobbio",
    "sg:classifiers":[
        {
            "category":"Wholesale",
            "subcategory":"Vending Machines",
            "type":"Manufacturing & Wholesale Goods"
        }
    ],
    "sg:phone":"+39 035 525239",
    "sg:postcode":"24050",
    "sg:province":"Bergamo",
    "sg:tags":[
        "engineering",
        "special",
        "mechanical"
    ],
    "sg:website":"www.marchettispa.it",
    "wof:name":"Marchetti Spa",
    "wof:placetype":"venue"
},
  "geometry": {"coordinates":[9.72002,45.662746],"type":"Point"}
}