{
  "type": "Feature",
  "properties": {
    "iso:country":"IT",
    "sg:address":"20125 Milano",
    "sg:city":"Milano",
    "sg:orig_category":"Termotecnica E Riscaldamento, Apparecchiature E Servizi",
    "sg:phone":"+39 02 607 1373",
    "sg:postcode":"20125",
    "sg:province":"Milano",
    "wof:name":"Palumbo Guido",
    "wof:placetype":"venue"
},
  "geometry": {"coordinates":[9.196333,45.495358],"type":"Point"}
}