{
  "type": "Feature",
  "properties": {
    "addr:full":"25014 Castenedolo Castenedolo Brescia 25014",
    "addr:postcode":"25014;25014",
    "iso:country":"IT",
    "sg:address":"25014 Castenedolo",
    "sg:city":"Castenedolo",
    "sg:orig_category":"Motori Diesel E Componenti",
    "sg:phone":"+39 030 213 1221",
    "sg:postcode":"25014",
    "sg:province":"Brescia",
    "wof:name":"Eurodiesel Di Ferrari Franco",
    "wof:placetype":"venue"
},
  "geometry": {"coordinates":[10.3000793457,45.4710388184],"type":"Point"}
}