{
  "type": "Feature",
  "properties": {
    "iso:country":"IT",
    "sg:address":"00060 Capena",
    "sg:city":"Capena",
    "sg:orig_category":"Onoranze E Pompe Funebri",
    "sg:phone":"+39 06 903 3900",
    "sg:postcode":"00060",
    "sg:province":"Roma",
    "wof:name":"Impresa Funebre San Leone",
    "wof:placetype":"venue"
},
  "geometry": {"coordinates":[12.615486,42.053341],"type":"Point"}
}