{
  "type": "Feature",
  "properties": {
    "iso:country":"IT",
    "sg:address":"12073 Ceva",
    "sg:city":"Ceva",
    "sg:orig_category":"Prodotti Di Base E Forniture Per Industria Alimentare E Bevande",
    "sg:phone":"+39 0174 700162",
    "sg:postcode":"12073",
    "sg:province":"Cuneo",
    "wof:name":"Tripperia Bamac",
    "wof:placetype":"venue"
},
  "geometry": {"coordinates":[8.0350036621,44.3873672485],"type":"Point"}
}