{
  "type": "Feature",
  "properties": {
    "iso:country":"IT",
    "sg:address":"41042 Fiorano Modenese",
    "sg:city":"Fiorano Modenese",
    "sg:orig_category":"Macchine Ed Impianti Per Edilizia E Lavori Pubblici",
    "sg:phone":"+39 0536 920450",
    "sg:postcode":"41042",
    "sg:province":"Modena",
    "wof:name":"Zama Sensor Srl",
    "wof:placetype":"venue"
},
  "geometry": {"coordinates":[10.83915,44.538376],"type":"Point"}
}