{
  "type": "Feature",
  "properties": {
    "iso:country":"IT",
    "sg:address":"18, Via Enrico Mattei 31010 Maser",
    "sg:city":"Maser",
    "sg:classifiers":[
        {
            "category":"Personal",
            "subcategory":"Shoe Repair & Shine",
            "type":"Services"
        }
    ],
    "sg:phone":"+39 0423 923087",
    "sg:postcode":"31010",
    "sg:province":"Treviso",
    "sg:tags":[
        "leather"
    ],
    "wof:name":"Vet Sport Di Vettoretto Germano & C. S.n.c.",
    "wof:placetype":"venue"
},
  "geometry": {"coordinates":[11.963385,45.79232],"type":"Point"}
}