{
  "type": "Feature",
  "properties": {
    "iso:country":"IT",
    "sg:address":"24124 Bergamo",
    "sg:city":"Bergamo",
    "sg:orig_category":"Motori Ed Organi Di Trasmissione. Ricambi E Componenti Dei Mezzi Di Trasporto",
    "sg:phone":"+39 035 346061",
    "sg:postcode":"24124",
    "sg:province":"Bergamo",
    "wof:name":"Cesareni Srl",
    "wof:placetype":"venue"
},
  "geometry": {"coordinates":[9.6879968643,45.7109718323],"type":"Point"}
}