{
  "type": "Feature",
  "properties": {
    "addr:full":"04011 Aprilia Aprilia Latina 04011",
    "addr:postcode":"04011;04011",
    "iso:country":"IT",
    "sg:address":"04011 Aprilia",
    "sg:city":"Aprilia",
    "sg:orig_category":"Alimenti Dietetici, Macrobiotici E Biologici - Produzione E Ingrosso",
    "sg:phone":"+39 06 928 2423",
    "sg:postcode":"04011",
    "sg:province":"Latina",
    "wof:name":"Centro Latte Alimentare Pontino Srl",
    "wof:placetype":"venue"
},
  "geometry": {"coordinates":[12.64357,41.595242],"type":"Point"}
}