{
  "type": "Feature",
  "properties": {
    "iso:country":"IT",
    "sg:address":"9, Via Delle Querce 31033 Castelfranco Veneto",
    "sg:city":"Castelfranco Veneto",
    "sg:classifiers":[
        {
            "category":"Home & Garden",
            "subcategory":"Home Furnishings",
            "type":"Retail Goods"
        }
    ],
    "sg:phone":"+39 0423 496222",
    "sg:postcode":"31033",
    "sg:province":"Treviso",
    "sg:tags":[
        "household"
    ],
    "wof:name":"Axia S.r.l.",
    "wof:placetype":"venue"
},
  "geometry": {"coordinates":[11.933412,45.681156],"type":"Point"}
}