{
  "type": "Feature",
  "properties": {
    "iso:country":"IT",
    "sg:address":"48026 Russi",
    "sg:city":"Russi",
    "sg:orig_category":"Agricoltura, Orticoltura E Floricoltura",
    "sg:phone":"+39 0544 580144",
    "sg:postcode":"48026",
    "sg:province":"Ravenna",
    "wof:name":"Tenuta Uccellina",
    "wof:placetype":"venue"
},
  "geometry": {"coordinates":[12.028787,44.370281],"type":"Point"}
}