{
  "type": "Feature",
  "properties": {
    "addr:full":"00040 Pomezia Pomezia Roma 00040",
    "addr:postcode":"00040;roma 00040",
    "iso:country":"IT",
    "sg:address":"00040 Pomezia",
    "sg:city":"Pomezia",
    "sg:orig_category":"Materiali E Componenti Elettrotecnici",
    "sg:phone":"+39 06 912 0179",
    "sg:postcode":"00040",
    "sg:province":"Roma",
    "wof:name":"Med.el. S.r.l.",
    "wof:placetype":"venue"
},
  "geometry": {"coordinates":[12.543641,41.686451],"type":"Point"}
}