{
  "type": "Feature",
  "properties": {
    "iso:country":"IT",
    "sg:address":"87050 Mangone",
    "sg:city":"Mangone",
    "sg:orig_category":"Non-classified Establishments",
    "sg:phone":"+39 0984 969678",
    "sg:postcode":"87050",
    "sg:province":"Cosenza",
    "wof:name":"Societa Trasformazione Del Legno S.a.s. Di Carpino",
    "wof:placetype":"venue"
},
  "geometry": {"coordinates":[16.317316,39.211918],"type":"Point"}
}