{
  "type": "Feature",
  "properties": {
    "addr:full":"Fraz. Gallenca 102 10087 Valperga Valperga Torino 10087",
    "addr:housenumber":"102",
    "addr:postcode":"10087;10087",
    "addr:street":"Fraz. Gallenca",
    "iso:country":"IT",
    "sg:address":"Fraz. Gallenca 102 10087 Valperga",
    "sg:city":"Valperga",
    "sg:classifiers":[
        {
            "category":"Building & Trades",
            "subcategory":"Landfill",
            "type":"Services"
        }
    ],
    "sg:phone":"+39 0124 659929",
    "sg:postcode":"10087",
    "sg:province":"Torino",
    "sg:tags":[
        "leather",
        "industry",
        "leatherware"
    ],
    "wof:name":"Conceria Peradotto Srl",
    "wof:placetype":"venue"
},
  "geometry": {"coordinates":[7.686619,45.07056],"type":"Point"}
}