{
  "type": "Feature",
  "properties": {
    "addr:full":"35131 Padova Padova Padova 35131",
    "addr:postcode":"35131;35131",
    "iso:country":"IT",
    "sg:address":"35131 Padova",
    "sg:city":"Padova",
    "sg:orig_category":"Serramenti Ed Infissi",
    "sg:phone":"+39 049 875 1513",
    "sg:postcode":"35131",
    "sg:province":"Padova",
    "sg:website":"http://www.rcpsrl.it",
    "wof:name":"R.c.p. Srl",
    "wof:placetype":"venue"
},
  "geometry": {"coordinates":[11.892819,45.413452],"type":"Point"}
}