{
  "type": "Feature",
  "properties": {
    "iso:country":"IT",
    "sg:address":"10072 Caselle Torinese",
    "sg:city":"Caselle Torinese",
    "sg:orig_category":"Macchine Ed Impianti Per Edilizia E Lavori Pubblici",
    "sg:phone":"+39 011 991 4270",
    "sg:postcode":"10072",
    "sg:province":"Torino",
    "wof:name":"Rm. Gru S.r.l.",
    "wof:placetype":"venue"
},
  "geometry": {"coordinates":[7.636133,45.168049],"type":"Point"}
}