{
  "type": "Feature",
  "properties": {
    "iso:country":"IT",
    "sg:address":"27, Via Del Cascamificio 60035 Jesi",
    "sg:city":"Jesi",
    "sg:classifiers":[
        {
            "category":"Utilities",
            "subcategory":"Electric",
            "type":"Services"
        }
    ],
    "sg:phone":"+39 0731 219162",
    "sg:postcode":"60035",
    "sg:province":"Ancona",
    "sg:tags":[
        "component",
        "electronic"
    ],
    "wof:name":"F.c.e. Elettronica",
    "wof:placetype":"venue"
},
  "geometry": {"coordinates":[13.2543,43.523369],"type":"Point"}
}