{
  "type": "Feature",
  "properties": {
    "addr:full":"6/g, Via R.bacchini 40026 Imola Imola Bologna 40026",
    "addr:housenumber":"6 / g",
    "addr:postcode":"40026;40026",
    "addr:street":"Via R.Bacchini",
    "iso:country":"IT",
    "sg:address":"6/g, Via R.bacchini 40026 Imola",
    "sg:city":"Imola",
    "sg:classifiers":[
        {
            "category":"Shopping",
            "subcategory":"Stationery & Office Supplies",
            "type":"Retail Goods"
        }
    ],
    "sg:phone":"+39 0542 643730",
    "sg:postcode":"40026",
    "sg:province":"Bologna",
    "sg:tags":[
        "professional"
    ],
    "wof:name":"Di.gi. Arredamenti (s.n.c.)",
    "wof:placetype":"venue"
},
  "geometry": {"coordinates":[11.3464813232,44.4942207336],"type":"Point"}
}