{
  "type": "Feature",
  "properties": {
    "iso:country":"IT",
    "sg:address":"25121 Brescia",
    "sg:city":"Brescia",
    "sg:orig_category":"Tessuti Arredamento, Tende E Tappeti. Forniture Per Edilizia E Lavori Pubblici",
    "sg:phone":"+39 030 375 7131",
    "sg:postcode":"25121",
    "sg:province":"Brescia",
    "wof:name":"Edil Moquette Snc",
    "wof:placetype":"venue"
},
  "geometry": {"coordinates":[10.2233,45.53368],"type":"Point"}
}