{
  "type": "Feature",
  "properties": {
    "addr:full":"37040 Arcole Arcole Verona 37040",
    "addr:postcode":"37040;37040",
    "iso:country":"IT",
    "sg:address":"37040 Arcole",
    "sg:city":"Arcole",
    "sg:orig_category":"Stirerie - Servizio Conto Terzi",
    "sg:phone":"+39 045 763 6372",
    "sg:postcode":"37040",
    "sg:province":"Verona",
    "wof:name":"Stireria R.m. Snc",
    "wof:placetype":"venue"
},
  "geometry": {"coordinates":[11.290717,45.350933],"type":"Point"}
}