{
  "type": "Feature",
  "properties": {
    "iso:country":"IT",
    "sg:address":"00184 Roma",
    "sg:city":"Roma",
    "sg:orig_category":"Medici Specialisti - Chirurgia Plastica E Ricostruttiva",
    "sg:phone":"+39 06 474 7113",
    "sg:postcode":"00184",
    "sg:province":"Roma",
    "sg:website":"http://www.vitocontreas.it",
    "wof:name":"Contreas Dott. Vito",
    "wof:placetype":"venue"
},
  "geometry": {"coordinates":[12.493292,41.903015],"type":"Point"}
}