{
  "type": "Feature",
  "properties": {
    "iso:country":"IT",
    "sg:address":"41019 Soliera",
    "sg:city":"Soliera",
    "sg:orig_category":"Trattamenti Termici E Superficiali Metalli, Galvanotecnica",
    "sg:phone":"+39 059 565216",
    "sg:postcode":"41019",
    "sg:province":"Modena",
    "wof:name":"Mochem Di Gadda Guido",
    "wof:placetype":"venue"
},
  "geometry": {"coordinates":[10.919653,44.725925],"type":"Point"}
}