{
  "type": "Feature",
  "properties": {
    "iso:country":"IT",
    "sg:address":"51011 Buggiano",
    "sg:city":"Buggiano",
    "sg:orig_category":"Legno E Semilavorati",
    "sg:phone":"+39 0572 32289",
    "sg:postcode":"51011",
    "sg:province":"Pistoia",
    "sg:website":"http://www.lis.it",
    "wof:name":"Lavorazione Italiana Sughero L.i.s.",
    "wof:placetype":"venue"
},
  "geometry": {"coordinates":[10.730442,43.867474],"type":"Point"}
}