{
  "type": "Feature",
  "properties": {
    "iso:country":"IT",
    "sg:address":"Via Fiori Oscuri 11 20121 Milano",
    "sg:city":"Milano",
    "sg:orig_category":"Ladies' Trousers Suits, Suits, Jackets, Skirts, And Trousers",
    "sg:phone":"+39 02 862172",
    "sg:postcode":"20121",
    "sg:province":"Milano",
    "sg:website":"www.moschino.it",
    "wof:name":"Fashoff S.r.l.",
    "wof:placetype":"venue"
},
  "geometry": {"coordinates":[9.188862,45.472515],"type":"Point"}
}