{
  "type": "Feature",
  "properties": {
    "iso:country":"IT",
    "sg:address":"Via Bruno Buozzi 2 20090 Caleppio Di Settala",
    "sg:city":"Caleppio",
    "sg:classifiers":[
        {
            "category":"Food & Beverages",
            "subcategory":"Specialty",
            "type":"Retail Goods"
        }
    ],
    "sg:phone":"+39 02 950 9661",
    "sg:postcode":"20090",
    "sg:province":"Milano",
    "sg:tags":[
        "solvent"
    ],
    "sg:website":"www.dollmar.com",
    "wof:name":"Dollmar & C. Spa",
    "wof:placetype":"venue"
},
  "geometry": {"coordinates":[9.188141,45.463688],"type":"Point"}
}