{
  "type": "Feature",
  "properties": {
    "addr:full":"00195 Roma Roma Roma 00195",
    "addr:postcode":"00195;00195",
    "iso:country":"IT",
    "sg:address":"00195 Roma",
    "sg:city":"Roma",
    "sg:classifiers":[
        {
            "category":"Health Services",
            "subcategory":"Health Practitioner",
            "type":"Services"
        }
    ],
    "sg:phone":"+39 06 372 9702",
    "sg:postcode":"00195",
    "sg:province":"Roma",
    "sg:tags":[
        "medici"
    ],
    "wof:name":"Stirpe Gilberto",
    "wof:placetype":"venue"
},
  "geometry": {"coordinates":[12.4572219849,41.9195899963],"type":"Point"}
}