{
  "type": "Feature",
  "properties": {
    "iso:country":"IT",
    "sg:address":"95126 Catania",
    "sg:city":"Catania",
    "sg:orig_category":"Ristorazione E Locali Pubblici Affini. Servizi Per Lo Sport E Il Tempo Libero. Alberghi E Strutture Extra Alberghiere. Ristoranti Ed Esercizi Affini",
    "sg:phone":"+39 0932 989038",
    "sg:postcode":"95126",
    "sg:province":"Catania",
    "wof:name":"Il Carrubo Srl",
    "wof:placetype":"venue"
},
  "geometry": {"coordinates":[15.0953,37.523647],"type":"Point"}
}