{
  "type": "Feature",
  "properties": {
    "addr:full":"Contrada Coretto 87046 Montalto Uffugo Montalto Uffugo Cosenza 87046",
    "addr:postcode":"87046;87046",
    "addr:street":"Contrada Coretto",
    "iso:country":"IT",
    "sg:address":"Contrada Coretto 87046 Montalto Uffugo",
    "sg:city":"Montalto Uffugo",
    "sg:classifiers":[
        {
            "category":"Shopping",
            "subcategory":"Crafts & Fabrics",
            "type":"Retail Goods"
        }
    ],
    "sg:phone":"+39 0984 937182",
    "sg:postcode":"87046",
    "sg:province":"Cosenza",
    "wof:name":"Tessil Pizzi Sud Srl",
    "wof:placetype":"venue"
},
  "geometry": {"coordinates":[16.2538089752,39.2982635498],"type":"Point"}
}