{
  "type": "Feature",
  "properties": {
    "iso:country":"IT",
    "sg:address":"Ss 16 Km. 315, 05 60022 Castelfidardo",
    "sg:city":"Castelfidardo",
    "sg:classifiers":[
        {
            "category":"Military Area",
            "subcategory":"Air Force Base",
            "type":"Public Place"
        }
    ],
    "sg:phone":"+39 071 781 9152",
    "sg:postcode":"60022",
    "sg:province":"Ancona",
    "sg:tags":[
        "instrument",
        "part",
        "musical",
        "accessory"
    ],
    "sg:website":"www.bespeco.it",
    "wof:name":"Bespeco Professional Srl",
    "wof:placetype":"venue"
},
  "geometry": {"coordinates":[13.5187568665,43.6158561707],"type":"Point"}
}