{
  "type": "Feature",
  "properties": {
    "addr:full":"20040 Bellusco Bellusco Milano 20040",
    "addr:postcode":"20040;20040",
    "iso:country":"IT",
    "sg:address":"20040 Bellusco",
    "sg:city":"Bellusco",
    "sg:orig_category":"Serigrafia",
    "sg:phone":"+39 039 622613",
    "sg:postcode":"20040",
    "sg:province":"Milano",
    "sg:website":"http://www.mbserigrafia.it",
    "wof:name":"M.b. Serigrafia",
    "wof:placetype":"venue"
},
  "geometry": {"coordinates":[9.423265,45.616161],"type":"Point"}
}