{
  "type": "Feature",
  "properties": {
    "iso:country":"IT",
    "sg:address":"39100 Bolzano",
    "sg:city":"Bolzano",
    "sg:orig_category":"Argenterie - Vendita Al Dettaglio",
    "sg:phone":"+39 0471 973353",
    "sg:postcode":"39100",
    "sg:province":"Bolzano/Bozen",
    "wof:name":"Ranzi & Knapp Di Anneliese Knapp & C. Snc",
    "wof:placetype":"venue"
},
  "geometry": {"coordinates":[11.356886,46.499229],"type":"Point"}
}