{
  "type": "Feature",
  "properties": {
    "iso:country":"IT",
    "sg:address":"37139 Verona",
    "sg:city":"Verona",
    "sg:orig_category":"Materiali Semilavorati Metallici",
    "sg:phone":"+39 045 851 0088",
    "sg:postcode":"37139",
    "sg:province":"Verona",
    "sg:website":"http://www.brunoventuri.it",
    "wof:name":"Bruno Venturi Spa",
    "wof:placetype":"venue"
},
  "geometry": {"coordinates":[10.889404,45.449764],"type":"Point"}
}