{
  "type": "Feature",
  "properties": {
    "iso:country":"IT",
    "sg:address":"1/a, Via Leini' 10077 San Maurizio Canavese",
    "sg:city":"San Maurizio Canavese",
    "sg:classifiers":[
        {
            "category":"Shopping",
            "subcategory":"Clothing, Apparel, & Fashions",
            "type":"Retail Goods"
        }
    ],
    "sg:phone":"+39 011 924 4037",
    "sg:postcode":"10077",
    "sg:province":"Torino",
    "sg:tags":[
        "clothes"
    ],
    "wof:name":"Malpi Di Perchinelli Pasquale E C. S.a.s.",
    "wof:placetype":"venue"
},
  "geometry": {"coordinates":[7.830617,45.487606],"type":"Point"}
}