{
  "type": "Feature",
  "properties": {
    "addr:full":"72021 Francavilla Fontana Francavilla Fontana Brindisi 72021",
    "addr:postcode":"72021;72021",
    "iso:country":"IT",
    "sg:address":"72021 Francavilla Fontana",
    "sg:city":"Francavilla Fontana",
    "sg:orig_category":"Macchine, Impianti Ed Attrezzature Per Industria Alimentare E Bevande",
    "sg:postcode":"72021",
    "sg:province":"Brindisi",
    "wof:name":"Comagri (s.p.a.)",
    "wof:placetype":"venue"
},
  "geometry": {"coordinates":[17.578669,40.536713],"type":"Point"}
}