{
  "type": "Feature",
  "properties": {
    "addr:full":"27049 Stradella Stradella Pavia 27049",
    "addr:postcode":"27049;27049",
    "iso:country":"IT",
    "sg:address":"27049 Stradella",
    "sg:city":"Stradella",
    "sg:orig_category":"Motori Ed Organi Di Trasmissione. Ricambi E Componenti Dei Mezzi Di Trasporto",
    "sg:phone":"+39 0385 246010",
    "sg:postcode":"27049",
    "sg:province":"Pavia",
    "sg:website":"http://www.maggicesare.it",
    "wof:name":"Maggi Cesare",
    "wof:placetype":"venue"
},
  "geometry": {"coordinates":[9.3018884659,45.0740737915],"type":"Point"}
}