{
  "type": "Feature",
  "properties": {
    "addr:full":"04011 Aprilia Aprilia Latina 04011",
    "addr:postcode":"04011;04011",
    "iso:country":"IT",
    "sg:address":"04011 Aprilia",
    "sg:city":"Aprilia",
    "sg:orig_category":"Automobili E Mezzi Di Trasporto",
    "sg:phone":"+39 06 9270 4981",
    "sg:postcode":"04011",
    "sg:province":"Latina",
    "wof:name":"Paolangeli Andrea",
    "wof:placetype":"venue"
},
  "geometry": {"coordinates":[12.886179,41.472767],"type":"Point"}
}