{
  "type": "Feature",
  "properties": {
    "addr:full":"37050 Angiari Angiari Verona 37050",
    "addr:postcode":"37050;37050",
    "iso:country":"IT",
    "sg:address":"37050 Angiari",
    "sg:city":"Angiari",
    "sg:orig_category":"Materiali E Componenti Elettronici",
    "sg:phone":"+39 0442 98077",
    "sg:postcode":"37050",
    "sg:province":"Verona",
    "sg:website":"http://www.pacpcb.com",
    "wof:name":"P.a.c. Circuiti Stampati Srl",
    "wof:placetype":"venue"
},
  "geometry": {"coordinates":[10.980285,45.415653],"type":"Point"}
}