{
  "type": "Feature",
  "properties": {
    "iso:country":"IT",
    "sg:address":"15, Via Alfieri Vittorio 15011 Acqui Terme",
    "sg:city":"Acqui Terme",
    "sg:classifiers":[
        {
            "category":"Real Estate",
            "subcategory":"Architect",
            "type":"Services"
        }
    ],
    "sg:phone":"+39 39014456248",
    "sg:postcode":"15011",
    "sg:province":"Alessandria",
    "sg:tags":[
        "textile",
        "clothing"
    ],
    "wof:name":"C.p.l. Cooperativa Produzione Lavoro",
    "wof:placetype":"venue"
},
  "geometry": {"coordinates":[8.470155,44.671032],"type":"Point"}
}