{
  "type": "Feature",
  "properties": {
    "addr:full":"29010 Rottofreno Rottofreno Piacenza 29010",
    "addr:postcode":"29010;29010",
    "iso:country":"IT",
    "sg:address":"29010 Rottofreno",
    "sg:city":"Rottofreno",
    "sg:orig_category":"Bevande, Vini E Liquori. Ristorazione E Locali Pubblici Affini. Ristoranti Ed Esercizi Affini. Servizi Ausiliari Di Ristorazione E Di Intrattenimento",
    "sg:phone":"+39 0523 769205",
    "sg:postcode":"29010",
    "sg:province":"Piacenza",
    "wof:name":"Crocodile Corner Srl",
    "wof:placetype":"venue"
},
  "geometry": {"coordinates":[9.643223,45.055141],"type":"Point"}
}