{
  "type": "Feature",
  "properties": {
    "addr:full":"64100 Teramo Teramo Teramo 64100",
    "addr:postcode":"64100;64100",
    "iso:country":"IT",
    "sg:address":"64100 Teramo",
    "sg:city":"Teramo",
    "sg:orig_category":"Forniture Per Edilizia E Lavori Pubblici",
    "sg:phone":"+39 0861 328644",
    "sg:postcode":"64100",
    "sg:province":"Teramo",
    "wof:name":"E.f.m. Legno Srl",
    "wof:placetype":"venue"
},
  "geometry": {"coordinates":[13.7057495117,42.6772766113],"type":"Point"}
}