{
  "type": "Feature",
  "properties": {
    "iso:country":"IT",
    "sg:address":"Via Milano 24050 Spirano",
    "sg:city":"Spirano",
    "sg:classifiers":[
        {
            "category":"Professional",
            "subcategory":"Engineering",
            "type":"Services"
        }
    ],
    "sg:phone":"+39 39035877117",
    "sg:postcode":"24050",
    "sg:province":"Bergamo",
    "sg:tags":[
        "machine",
        "-",
        "mechanical"
    ],
    "wof:name":"Costruzioni Aeromeccaniche Di Gritti Fertile & C.(s.n.c.)",
    "wof:placetype":"venue"
},
  "geometry": {"coordinates":[9.665606,45.576473],"type":"Point"}
}