{
  "type": "Feature",
  "properties": {
    "addr:full":"90145 Palermo Palermo Palermo 90145",
    "addr:postcode":"90145;90145",
    "iso:country":"IT",
    "sg:address":"90145 Palermo",
    "sg:city":"Palermo",
    "sg:orig_category":"Ospedali E Servizi Sanitari",
    "sg:phone":"+39 091 683 1034",
    "sg:postcode":"90145",
    "sg:province":"Palermo",
    "wof:name":"Mini' Domenico",
    "wof:placetype":"venue"
},
  "geometry": {"coordinates":[13.332808,38.130768],"type":"Point"}
}