{
  "type": "Feature",
  "properties": {
    "addr:full":"Corso Marrucino 102; Chieti; 66100 Chieti Chieti 66100",
    "addr:housenumber":"102",
    "addr:postcode":"66100;66100",
    "addr:street":"Corso Marrucino",
    "iso:country":"IT",
    "sg:address":"Corso Marrucino 102; Chieti; 66100",
    "sg:city":"Chieti",
    "sg:classifiers":[
        {
            "category":"Banks & Credit Unions",
            "subcategory":"Bank",
            "type":"Services"
        }
    ],
    "sg:phone":"+39 0871 3511",
    "sg:postcode":"66100",
    "sg:province":"Chieti",
    "wof:name":"Banco Di Napoli Spa",
    "wof:placetype":"venue"
},
  "geometry": {"coordinates":[14.166742,42.349365],"type":"Point"}
}