{
  "type": "Feature",
  "properties": {
    "addr:full":"50019 Sesto Fiorentino Sesto Fiorentino Firenze 50019",
    "addr:postcode":"50019;50019",
    "iso:country":"IT",
    "sg:address":"50019 Sesto Fiorentino",
    "sg:city":"Sesto Fiorentino",
    "sg:orig_category":"Automobili E Mezzi Di Trasporto",
    "sg:phone":"+39 055 421 1323",
    "sg:postcode":"50019",
    "sg:province":"Firenze",
    "wof:name":"Bresci Motor Snc Di Bresci Paolo & C.",
    "wof:placetype":"venue"
},
  "geometry": {"coordinates":[11.195206,43.828876],"type":"Point"}
}