{
  "type": "Feature",
  "properties": {
    "iso:country":"IT",
    "sg:address":"24060 Telgate",
    "sg:city":"Telgate",
    "sg:orig_category":"Forniture Per Attivita' Industriali",
    "sg:phone":"+39 035 833443",
    "sg:postcode":"24060",
    "sg:province":"Bergamo",
    "wof:name":"Nicolai F.lli (s.r.l.)",
    "wof:placetype":"venue"
},
  "geometry": {"coordinates":[9.8534173965,45.6285591125],"type":"Point"}
}