{
  "type": "Feature",
  "properties": {
    "iso:country":"IT",
    "sg:address":"05021 Acquasparta",
    "sg:city":"Acquasparta",
    "sg:orig_category":"Ospedali E Servizi Sanitari",
    "sg:phone":"+39 0744 943764",
    "sg:postcode":"05021",
    "sg:province":"Terni",
    "wof:name":"Leonori Maria",
    "wof:placetype":"venue"
},
  "geometry": {"coordinates":[12.54404,42.69162],"type":"Point"}
}