{
  "type": "Feature",
  "properties": {
    "addr:full":"73042 Casarano Casarano Lecce 73042",
    "addr:postcode":"73042;73042",
    "iso:country":"IT",
    "sg:address":"73042 Casarano",
    "sg:city":"Casarano",
    "sg:orig_category":"Assemblaggio Conto Terzi",
    "sg:phone":"+39 0833 513796",
    "sg:postcode":"73042",
    "sg:province":"Lecce",
    "wof:name":"Deas Di De Marco Luigi",
    "wof:placetype":"venue"
},
  "geometry": {"coordinates":[18.143536,40.307217],"type":"Point"}
}