{
  "type": "Feature",
  "properties": {
    "iso:country":"IT",
    "sg:address":"21052 Busto Arsizio",
    "sg:city":"Busto Arsizio",
    "sg:orig_category":"Materie Plastiche Lavorazione - Macchine",
    "sg:phone":"+39 0331 627347",
    "sg:postcode":"21052",
    "sg:province":"Varese",
    "wof:name":"Eurotec Di Colombo Emanuele Impianti Per Materie Plastiche",
    "wof:placetype":"venue"
},
  "geometry": {"coordinates":[8.83711,45.595325],"type":"Point"}
}