{
  "type": "Feature",
  "properties": {
    "addr:full":"Via Roma 77; Corte Franca; 25040 Corte Franca Brescia 25040",
    "addr:housenumber":"77",
    "addr:postcode":"25040;25040",
    "addr:street":"Via Roma",
    "iso:country":"IT",
    "sg:address":"Via Roma 77; Corte Franca; 25040",
    "sg:city":"Corte Franca",
    "sg:classifiers":[
        {
            "category":"Banks & Credit Unions",
            "subcategory":"Bank",
            "type":"Services"
        }
    ],
    "sg:phone":"+39 030 984114",
    "sg:postcode":"25040",
    "sg:province":"Brescia",
    "wof:name":"Credito Bergamasco Spa",
    "wof:placetype":"venue"
},
  "geometry": {"coordinates":[10.010292,45.63784],"type":"Point"}
}