{
  "type": "Feature",
  "properties": {
    "iso:country":"IT",
    "sg:address":"21040 Sumirago",
    "sg:city":"Sumirago",
    "sg:orig_category":"Serramenti Ed Infissi",
    "sg:phone":"+39 0331 909586",
    "sg:postcode":"21040",
    "sg:province":"Varese",
    "wof:name":"Luxport Snc",
    "wof:placetype":"venue"
},
  "geometry": {"coordinates":[8.782833,45.738777],"type":"Point"}
}