{
  "type": "Feature",
  "properties": {
    "iso:country":"IT",
    "sg:address":"06059 Todi",
    "sg:city":"Todi",
    "sg:orig_category":"Agriturismo",
    "sg:phone":"+39 075 894 2268",
    "sg:postcode":"06059",
    "sg:province":"Perugia",
    "wof:name":"Istituto Suore Serve Di Maria Riparatrici",
    "wof:placetype":"venue"
},
  "geometry": {"coordinates":[12.289194,43.017349],"type":"Point"}
}