{
  "type": "Feature",
  "properties": {
    "addr:full":"00179 Roma Roma Roma 00179",
    "addr:postcode":"00179;00179",
    "iso:country":"IT",
    "sg:address":"00179 Roma",
    "sg:city":"Roma",
    "sg:orig_category":"Pasticceria E Confetteria Prodotti - Produzione E Ingrosso",
    "sg:phone":"+39 06 780 6157",
    "sg:postcode":"00179",
    "sg:province":"Roma",
    "wof:name":"Gruppo Abartian Srl",
    "wof:placetype":"venue"
},
  "geometry": {"coordinates":[12.5247631073,41.8711585999],"type":"Point"}
}