{
  "type": "Feature",
  "properties": {
    "iso:country":"IT",
    "sg:address":"13/b, Via Firenze 20063 Cernusco Sul Naviglio",
    "sg:city":"Cernusco sul Naviglio",
    "sg:classifiers":[
        {
            "category":"Manufacturing",
            "subcategory":"Metals",
            "type":"Manufacturing & Wholesale Goods"
        }
    ],
    "sg:phone":"+39 02 9210 7762",
    "sg:postcode":"20063",
    "sg:province":"Milano",
    "sg:tags":[
        "metallurgy",
        "metalworking"
    ],
    "wof:name":"B P 2 Inox S.r.l.",
    "wof:placetype":"venue"
},
  "geometry": {"coordinates":[9.3378429413,45.465045929],"type":"Point"}
}