{
  "type": "Feature",
  "properties": {
    "addr:full":"50019 Sesto Fiorentino Sesto Fiorentino Firenze 50019",
    "addr:postcode":"50019;50019",
    "iso:country":"IT",
    "sg:address":"50019 Sesto Fiorentino",
    "sg:city":"Sesto Fiorentino",
    "sg:orig_category":"Decalcomanie E Vetrofanie",
    "sg:phone":"+39 055 421 1258",
    "sg:postcode":"50019",
    "sg:province":"Firenze",
    "wof:name":"S.i.a.p. Snc",
    "wof:placetype":"venue"
},
  "geometry": {"coordinates":[11.181205,43.832462],"type":"Point"}
}