{
  "type": "Feature",
  "properties": {
    "addr:full":"48, Loc. Gerbido - Str. St. 143 13881 Cavagli\u00e0 Biella 13881",
    "addr:housenumber":"143",
    "addr:postcode":"13881;13881",
    "addr:street":"Gerbido Str. St.",
    "iso:country":"IT",
    "sg:address":"48, Loc. Gerbido - Str. St. 143 13881 Cavagli\u00e0",
    "sg:classifiers":[
        {
            "category":"Manufacturing",
            "subcategory":"Metals",
            "type":"Manufacturing & Wholesale Goods"
        }
    ],
    "sg:phone":"+39 0161 967051",
    "sg:postcode":"13881",
    "sg:province":"Biella",
    "sg:tags":[
        "metallurgy",
        "metalworking"
    ],
    "wof:name":"Mercuri Alfredo Alluminio",
    "wof:placetype":"venue"
},
  "geometry": {"coordinates":[8.0582695007,45.5628356934],"type":"Point"}
}