{
  "type": "Feature",
  "properties": {
    "iso:country":"IT",
    "sg:address":"Via Roma 25060 Collebeato",
    "sg:city":"Collebeato",
    "sg:classifiers":[
        {
            "category":"Shopping",
            "type":"Retail Goods"
        }
    ],
    "sg:phone":"+39 030 251 0391",
    "sg:postcode":"25060",
    "sg:province":"Brescia",
    "sg:tags":[
        "finished",
        "-",
        "metallic"
    ],
    "wof:name":"Emer (s.r.l.)",
    "wof:placetype":"venue"
},
  "geometry": {"coordinates":[10.2155628204,45.5788078308],"type":"Point"}
}