{
  "type": "Feature",
  "properties": {
    "addr:full":"30030 Pianiga Pianiga Venezia 30030",
    "addr:postcode":"30030;30030",
    "iso:country":"IT",
    "sg:address":"30030 Pianiga",
    "sg:city":"Pianiga",
    "sg:orig_category":"Servizi E Lavori Per Arredamento E Industria Del Legno",
    "sg:phone":"+39 041 513 8176",
    "sg:postcode":"30030",
    "sg:province":"Venezia",
    "wof:name":"Padana Tranciati (s.a.s.)",
    "wof:placetype":"venue"
},
  "geometry": {"coordinates":[12.080393,45.448769],"type":"Point"}
}