{
  "type": "Feature",
  "properties": {
    "iso:country":"IT",
    "sg:address":"35020 Ponte San Nicolo'",
    "sg:orig_category":"Macchine, Impianti Ed Attrezzature Industria Chimica. Attrezzature E Forniture Per Officine Riparazione E Servizi Ausiliari",
    "sg:phone":"+39 049 896 1140",
    "sg:postcode":"35020",
    "sg:province":"Padova",
    "wof:name":"Cima Di Spadin Luciano E C. Snc",
    "wof:placetype":"venue"
},
  "geometry": {"coordinates":[11.913318,45.375839],"type":"Point"}
}