{
  "type": "Feature",
  "properties": {
    "iso:country":"IT",
    "sg:address":"23900 Lecco",
    "sg:city":"Lecco",
    "sg:orig_category":"Forniture Per Attivita' Industriali",
    "sg:phone":"+39 0341 423039",
    "sg:postcode":"23900",
    "sg:province":"Lecco",
    "sg:website":"http://www.pavano.it",
    "wof:name":"P.tre Srl",
    "wof:placetype":"venue"
},
  "geometry": {"coordinates":[9.4091835022,45.8297805786],"type":"Point"}
}