{
  "type": "Feature",
  "properties": {
    "addr:full":"1, Via Della Casetta 53037 San Gimignano San Gimignano Siena 53037",
    "addr:postcode":"53037;gimignano;53037",
    "addr:street":"Via Della Casetta;Gimignano Siena",
    "iso:country":"IT",
    "sg:address":"1, Via Della Casetta 53037 San Gimignano",
    "sg:city":"San Gimignano",
    "sg:classifiers":[
        {
            "category":"Home & Garden",
            "subcategory":"Home Furnishings",
            "type":"Retail Goods"
        }
    ],
    "sg:phone":"+39 0577 945001",
    "sg:postcode":"53037",
    "sg:province":"Siena",
    "sg:tags":[
        "household"
    ],
    "wof:name":"San.cor. S.r.l.",
    "wof:placetype":"venue"
},
  "geometry": {"coordinates":[11.031607,43.540051],"type":"Point"}
}