{
  "type": "Feature",
  "properties": {
    "addr:full":"09040 Villaputzu Villaputzu Cagliari 09040",
    "addr:postcode":"09040;09040",
    "iso:country":"IT",
    "sg:address":"09040 Villaputzu",
    "sg:city":"Villaputzu",
    "sg:orig_category":"Scuole E Servizi Scolastici. Servizi Per Lo Sport E Il Tempo Libero",
    "sg:phone":"+39 070 993 8054",
    "sg:postcode":"09040",
    "sg:province":"Cagliari",
    "wof:name":"Velasport",
    "wof:placetype":"venue"
},
  "geometry": {"coordinates":[9.638675,39.441326],"type":"Point"}
}