{
  "type": "Feature",
  "properties": {
    "iso:country":"IT",
    "sg:address":"88046 Lamezia Terme",
    "sg:city":"Lamezia Terme",
    "sg:orig_category":"Servizi E Lavori Per Edilizia E Lavori Pubblici. Servizi E Lavori Per Ecologia E Smaltimento Rifiuti",
    "sg:phone":"+39 0968 442032",
    "sg:postcode":"88046",
    "sg:province":"Catanzaro",
    "sg:website":"http://www.ecologiaoggi.it",
    "wof:name":"Ecologia Oggi Srl",
    "wof:placetype":"venue"
},
  "geometry": {"coordinates":[16.275751,38.93362],"type":"Point"}
}