{
  "type": "Feature",
  "properties": {
    "iso:country":"IT",
    "sg:address":"31031 Caerano Di San Marco",
    "sg:city":"Caerano di San Marco",
    "sg:classifiers":[
        {
            "category":"Shopping",
            "subcategory":"Clothing, Apparel, & Fashions",
            "type":"Retail Goods"
        }
    ],
    "sg:phone":"+39 0423 6565",
    "sg:postcode":"31031",
    "sg:province":"Treviso",
    "sg:tags":[
        "clothing",
        "fur",
        "knitwear"
    ],
    "sg:website":"http://www.montegrappainc.com",
    "wof:name":"Maglificio Montegrappa Srl",
    "wof:placetype":"venue"
},
  "geometry": {"coordinates":[11.99416,45.770355],"type":"Point"}
}