{
  "type": "Feature",
  "properties": {
    "iso:country":"IT",
    "sg:address":"60030 Belvedere Ostrense",
    "sg:city":"Belvedere Ostrense",
    "sg:orig_category":"Serramenti Ed Infissi",
    "sg:phone":"+39 0731 200089",
    "sg:postcode":"60030",
    "sg:province":"Ancona",
    "wof:name":"Ceccarelli Dario",
    "wof:placetype":"venue"
},
  "geometry": {"coordinates":[13.146222,43.565262],"type":"Point"}
}