{
  "type": "Feature",
  "properties": {
    "iso:country":"IT",
    "sg:address":"83100 Avellino",
    "sg:city":"Avellino",
    "sg:orig_category":"Orologeria",
    "sg:phone":"+39 0825 36447",
    "sg:postcode":"83100",
    "sg:province":"Avellino",
    "wof:name":"Gioielleria Rossano Di Saccone Alfonsina & C.",
    "wof:placetype":"venue"
},
  "geometry": {"coordinates":[14.787101,40.912838],"type":"Point"}
}