{
  "type": "Feature",
  "properties": {
    "iso:country":"IT",
    "sg:address":"46042 Castel Goffredo",
    "sg:city":"Castel Goffredo",
    "sg:orig_category":"Abbigliamento Intimo, Calze E Costumi Da Bagno",
    "sg:phone":"+39 0376 780968",
    "sg:postcode":"46042",
    "sg:province":"Mantova",
    "wof:name":"Katia Calze Srl",
    "wof:placetype":"venue"
},
  "geometry": {"coordinates":[10.479351,45.297077],"type":"Point"}
}