{
  "type": "Feature",
  "properties": {
    "addr:full":"10, Via Polo Marco 20036 Meda Meda Milano 20036",
    "addr:postcode":"20036;20036",
    "addr:street":"Via Polo Marco",
    "iso:country":"IT",
    "sg:address":"10, Via Polo Marco 20036 Meda",
    "sg:city":"Meda",
    "sg:classifiers":[
        {
            "category":"Manufacturing",
            "subcategory":"Lumber",
            "type":"Manufacturing & Wholesale Goods"
        }
    ],
    "sg:phone":"+39 39036275301",
    "sg:postcode":"20036",
    "sg:province":"Milano",
    "sg:tags":[
        "wood"
    ],
    "wof:name":"Itallegno (s.p.a.)",
    "wof:placetype":"venue"
},
  "geometry": {"coordinates":[9.188141,45.463688],"type":"Point"}
}