{
  "type": "Feature",
  "properties": {
    "iso:country":"IT",
    "sg:address":"95032 Belpasso",
    "sg:city":"Belpasso",
    "sg:orig_category":"Non-classified Establishments",
    "sg:phone":"+39 095 791 3016",
    "sg:postcode":"95032",
    "sg:province":"Catania",
    "wof:name":"Sicil-canne-sinatra Di Sinatra Salvatore",
    "wof:placetype":"venue"
},
  "geometry": {"coordinates":[14.930637,37.565407],"type":"Point"}
}