{
  "type": "Feature",
  "properties": {
    "iso:country":"IT",
    "sg:address":"29022 Bobbio",
    "sg:city":"Bobbio",
    "sg:orig_category":"Agricoltura, Orticoltura E Floricoltura",
    "sg:phone":"+39 0523 936263",
    "sg:postcode":"29022",
    "sg:province":"Piacenza",
    "wof:name":"Castelli Paolo",
    "wof:placetype":"venue"
},
  "geometry": {"coordinates":[9.391006,44.790989],"type":"Point"}
}