{
  "type": "Feature",
  "properties": {
    "iso:country":"IT",
    "sg:address":"40013 Castel Maggiore",
    "sg:city":"Castel Maggiore",
    "sg:orig_category":"Studi E Consulenze Amministrative, Commerciali E Aziendali. Consulenze Tecniche, Amministrative E Perizie",
    "sg:phone":"+39 051 713990",
    "sg:postcode":"40013",
    "sg:province":"Bologna",
    "wof:name":"Beghelli Gianni",
    "wof:placetype":"venue"
},
  "geometry": {"coordinates":[11.378896,44.567295],"type":"Point"}
}