{
  "type": "Feature",
  "properties": {
    "addr:full":"61, Via Aristotele 20010 Cornaredo Cornaredo Milano 20010",
    "addr:postcode":"20010;20010",
    "addr:street":"Via Aristotele",
    "iso:country":"IT",
    "sg:address":"61, Via Aristotele 20010 Cornaredo",
    "sg:city":"Cornaredo",
    "sg:classifiers":[
        {
            "category":"Manufacturing",
            "subcategory":"Printing",
            "type":"Manufacturing & Wholesale Goods"
        }
    ],
    "sg:phone":"+39 02 9356 5172",
    "sg:postcode":"20010",
    "sg:province":"Milano",
    "sg:tags":[
        "publishing"
    ],
    "wof:name":"C.i.a.",
    "wof:placetype":"venue"
},
  "geometry": {"coordinates":[9.0242128372,45.5054969788],"type":"Point"}
}