{
  "type": "Feature",
  "properties": {
    "iso:country":"IT",
    "sg:address":"23, Via Moreno Ottavio 12038 Savigliano",
    "sg:city":"Savigliano",
    "sg:classifiers":[
        {
            "category":"Autos & Motor Vehicles",
            "subcategory":"Automobile Sales",
            "type":"Retail Goods"
        }
    ],
    "sg:phone":"+39 0172 718111",
    "sg:postcode":"12038",
    "sg:province":"Cuneo",
    "sg:tags":[
        "equipment",
        "transport"
    ],
    "wof:name":"Alstom Ferroviaria Spa",
    "wof:placetype":"venue"
},
  "geometry": {"coordinates":[7.547111,44.388798],"type":"Point"}
}