{
  "type": "Feature",
  "properties": {
    "iso:country":"IT",
    "sg:address":"54027 Pontremoli",
    "sg:city":"Pontremoli",
    "sg:orig_category":"Abbigliamento Sportivo - Produzione E Ingrosso",
    "sg:phone":"+39 0187 831571",
    "sg:postcode":"54027",
    "sg:province":"Massa-Carrara",
    "wof:name":"Erluison Enzo",
    "wof:placetype":"venue"
},
  "geometry": {"coordinates":[9.875902,44.377949],"type":"Point"}
}