{
  "type": "Feature",
  "properties": {
    "addr:full":"Viale Europa 70123 Bari Bari Bari 70123",
    "addr:postcode":"70123;70123",
    "addr:street":"Viale Europa",
    "iso:country":"IT",
    "sg:address":"Viale Europa 70123 Bari",
    "sg:city":"Bari",
    "sg:classifiers":[
        {
            "category":"Home & Garden",
            "subcategory":"Home Furnishings",
            "type":"Retail Goods"
        }
    ],
    "sg:phone":"+39 080 534 1546",
    "sg:postcode":"70123",
    "sg:province":"Bari",
    "sg:tags":[
        "household"
    ],
    "wof:name":"Pandaflex (s.r.l.)",
    "wof:placetype":"venue"
},
  "geometry": {"coordinates":[16.861673,41.089905],"type":"Point"}
}