{
  "type": "Feature",
  "properties": {
    "addr:full":"44, V. Bissarre 44034 Copparo Copparo Ferrara 44034",
    "addr:housenumber":"44",
    "addr:postcode":"44034;44034",
    "addr:street":"V. Bissarre",
    "iso:country":"IT",
    "sg:address":"44, V. Bissarre 44034 Copparo",
    "sg:city":"Copparo",
    "sg:classifiers":[
        {
            "category":"Parking",
            "subcategory":"Lot",
            "type":"Transportation"
        }
    ],
    "sg:phone":"+39 0532 863225",
    "sg:postcode":"44034",
    "sg:province":"Ferrara",
    "sg:tags":[
        "transport",
        "road"
    ],
    "sg:website":"http://www.cagnonisped.it:ws_end: :mark:ws:http://www.paginegialle.it/cagnoni-02",
    "wof:name":"Casa Di Spedizioni Cagnoni Snc",
    "wof:placetype":"venue"
},
  "geometry": {"coordinates":[11.80965,44.88681],"type":"Point"}
}