{
  "type": "Feature",
  "properties": {
    "iso:country":"IT",
    "sg:address":"80135 Napoli",
    "sg:city":"Napoli",
    "sg:orig_category":"Trasporti E Spedizioni Merci",
    "sg:phone":"+39 081 544 1568",
    "sg:postcode":"80135",
    "sg:province":"Napoli",
    "wof:name":"Motoflash Di Luciano Mario",
    "wof:placetype":"venue"
},
  "geometry": {"coordinates":[14.246515,40.853271],"type":"Point"}
}