{
  "type": "Feature",
  "properties": {
    "addr:full":"20123 Milano Milano Milano 20123",
    "addr:postcode":"20123;20123",
    "iso:country":"IT",
    "sg:address":"20123 Milano",
    "sg:city":"Milano",
    "sg:orig_category":"Forniture Per Abbigliamento E Pelletterie",
    "sg:phone":"+39 02 8646 2499",
    "sg:postcode":"20123",
    "sg:province":"Milano",
    "wof:name":"Casa Di Modelli S.n.c.",
    "wof:placetype":"venue"
},
  "geometry": {"coordinates":[9.1861639023,45.4636802673],"type":"Point"}
}