{
  "type": "Feature",
  "properties": {
    "iso:country":"IT",
    "sg:address":"Via Leonardo Da Vinci 10 36050 Zermeghedo",
    "sg:city":"Zermeghedo",
    "sg:classifiers":[
        {
            "category":"Personal",
            "subcategory":"Tanning Parlor",
            "type":"Services"
        }
    ],
    "sg:phone":"+39 0444 685452",
    "sg:postcode":"36050",
    "sg:province":"Vicenza",
    "sg:tags":[
        "hide",
        "auxiliary"
    ],
    "wof:name":"F.c.v. Di Paiusco Costantino Srl",
    "wof:placetype":"venue"
},
  "geometry": {"coordinates":[11.432038,45.494766],"type":"Point"}
}