{
  "type": "Feature",
  "properties": {
    "iso:country":"IT",
    "sg:address":"31020 San Vendemiano",
    "sg:city":"San Vendemiano",
    "sg:orig_category":"Biancheria, Telerie E Coperte. Forniture Alle Strutture Ricettive",
    "sg:phone":"+39 0438 470120",
    "sg:postcode":"31020",
    "sg:province":"Treviso",
    "wof:name":"Tessitura Fratelli Bortolotto",
    "wof:placetype":"venue"
},
  "geometry": {"coordinates":[12.361248,45.890408],"type":"Point"}
}