{
  "type": "Feature",
  "properties": {
    "iso:country":"IT",
    "sg:address":"Zona Ind. Squartabue 62019 Recanati",
    "sg:city":"Recanati",
    "sg:classifiers":[
        {
            "category":"Manufacturing",
            "subcategory":"Metals",
            "type":"Manufacturing & Wholesale Goods"
        }
    ],
    "sg:phone":"+39 071 750 6168",
    "sg:postcode":"62019",
    "sg:province":"Macerata",
    "sg:tags":[
        "processing"
    ],
    "sg:website":"http://www.paginegialle.it/fcf-04",
    "wof:name":"F.c.f. Srl",
    "wof:placetype":"venue"
},
  "geometry": {"coordinates":[13.4562616348,43.3007469177],"type":"Point"}
}