{
  "type": "Feature",
  "properties": {
    "addr:full":"00175 Roma Roma Roma 00175",
    "addr:postcode":"00175;00175",
    "iso:country":"IT",
    "sg:address":"00175 Roma",
    "sg:city":"Roma",
    "sg:orig_category":"Amministrazioni Immobiliari",
    "sg:phone":"+39 06 7154 5873",
    "sg:postcode":"00175",
    "sg:province":"Roma",
    "wof:name":"Amministrazioni Schillaci",
    "wof:placetype":"venue"
},
  "geometry": {"coordinates":[12.567202,41.856422],"type":"Point"}
}