{
  "type": "Feature",
  "properties": {
    "iso:country":"IT",
    "sg:address":"51039 Quarrata",
    "sg:city":"Quarrata",
    "sg:orig_category":"Istituti Di Bellezza",
    "sg:phone":"+39 0573 705031",
    "sg:postcode":"51039",
    "sg:province":"Pistoia",
    "sg:website":"http://www.lineasaluteitalia.it",
    "wof:name":"Linea Salute Italia Srl",
    "wof:placetype":"venue"
},
  "geometry": {"coordinates":[10.958095,43.853477],"type":"Point"}
}