{
  "type": "Feature",
  "properties": {
    "iso:country":"IT",
    "sg:address":"52, Via Boscaccio 21012 Cassano Magnago",
    "sg:city":"Cassano Magnago",
    "sg:classifiers":[
        {
            "category":"Wholesale",
            "subcategory":"Drugs",
            "type":"Manufacturing & Wholesale Goods"
        }
    ],
    "sg:phone":"+39 0331 200758",
    "sg:postcode":"21012",
    "sg:province":"Varese",
    "sg:tags":[
        "chemical",
        "pharmaceutical"
    ],
    "wof:name":"Emmepi (s.r.l.)",
    "wof:placetype":"venue"
},
  "geometry": {"coordinates":[8.831985,45.651775],"type":"Point"}
}