{
  "type": "Feature",
  "properties": {
    "iso:country":"IT",
    "sg:address":"Via C. Battisti 22; Rogeno",
    "sg:classifiers":[
        {
            "category":"Banks & Credit Unions",
            "subcategory":"Bank",
            "type":"Services"
        }
    ],
    "sg:phone":"+39 031 876100",
    "wof:name":"Banca Briantea Spa",
    "wof:placetype":"venue"
},
  "geometry": {"coordinates":[9.272956,45.782269],"type":"Point"}
}