{
  "type": "Feature",
  "properties": {
    "addr:full":"5, V. Isonzo - Terraglione 35010 Vigodarzere Terraglione Padova 35010",
    "addr:housenumber":"5",
    "addr:postcode":"35010;35010",
    "addr:street":"V. Isonzo Terraglione",
    "iso:country":"IT",
    "sg:address":"5, V. Isonzo - Terraglione 35010 Vigodarzere",
    "sg:city":"Terraglione",
    "sg:classifiers":[
        {
            "category":"Autos & Motor Vehicles",
            "subcategory":"Automobile Sales",
            "type":"Retail Goods"
        }
    ],
    "sg:phone":"+39 049 887 3876",
    "sg:postcode":"35010",
    "sg:province":"Padova",
    "sg:tags":[
        "motor-cars"
    ],
    "sg:website":"http://www.paginegialle.it/frigocar",
    "wof:name":"Comalin Frigocar",
    "wof:placetype":"venue"
},
  "geometry": {"coordinates":[11.8945522308,45.4825439453],"type":"Point"}
}