{
  "type": "Feature",
  "properties": {
    "iso:country":"IT",
    "sg:address":"Via Quartaccio 01033 Civita Castellana",
    "sg:city":"Civita Castellana",
    "sg:classifiers":[
        {
            "category":"Home & Garden",
            "subcategory":"Home Furnishings",
            "type":"Retail Goods"
        }
    ],
    "sg:phone":"+39 0761 513765",
    "sg:postcode":"01033",
    "sg:province":"Viterbo",
    "sg:tags":[
        "household"
    ],
    "wof:name":"Siderplast S.r.l. Di Mattioli G.",
    "wof:placetype":"venue"
},
  "geometry": {"coordinates":[12.416199,42.323547],"type":"Point"}
}