{
  "type": "Feature",
  "properties": {
    "iso:country":"IT",
    "sg:address":"20121 Milano",
    "sg:city":"Milano",
    "sg:orig_category":"Pubblicita', Marketing E Comunicazione",
    "sg:phone":"+39 02 653464",
    "sg:postcode":"20121",
    "sg:province":"Milano",
    "wof:name":"Ascari Patrizia",
    "wof:placetype":"venue"
},
  "geometry": {"coordinates":[9.1962461472,45.4741706848],"type":"Point"}
}