{
  "type": "Feature",
  "properties": {
    "addr:full":"Via Cividale 33040 Moimacco Moimacco Udine 33040",
    "addr:postcode":"33040;33040",
    "addr:street":"Via Cividale",
    "iso:country":"IT",
    "sg:address":"Via Cividale 33040 Moimacco",
    "sg:city":"Moimacco",
    "sg:classifiers":[
        {
            "category":"Wholesale",
            "subcategory":"Home Furnishings",
            "type":"Manufacturing & Wholesale Goods"
        }
    ],
    "sg:phone":"+39 0432 733738",
    "sg:postcode":"33040",
    "sg:province":"Udine",
    "sg:tags":[
        "chair"
    ],
    "wof:name":"Novalia Srl",
    "wof:placetype":"venue"
},
  "geometry": {"coordinates":[13.288441,46.076626],"type":"Point"}
}