{
  "type": "Feature",
  "properties": {
    "iso:country":"IT",
    "sg:address":"Via Borgo Treviso 151; Castelfranco Veneto; 31033",
    "sg:city":"Castelfranco Veneto",
    "sg:classifiers":[
        {
            "category":"Banks & Credit Unions",
            "subcategory":"Bank",
            "type":"Services"
        }
    ],
    "sg:phone":"+39 0423 721841",
    "sg:postcode":"31033",
    "sg:province":"Treviso",
    "wof:name":"Credito Italiano Spa",
    "wof:placetype":"venue"
},
  "geometry": {"coordinates":[11.949275,45.672993],"type":"Point"}
}