{
  "type": "Feature",
  "properties": {
    "addr:full":"57123 Livorno Livorno Livorno 57123",
    "addr:postcode":"57123;57123",
    "iso:country":"IT",
    "sg:address":"57123 Livorno",
    "sg:city":"Livorno",
    "sg:orig_category":"Trasporti E Spedizioni Merci",
    "sg:phone":"+39 0586 891234",
    "sg:postcode":"57123",
    "sg:province":"Livorno",
    "sg:website":"http://www.olympia-alltrans.com",
    "wof:name":"Olympia Alltrans Srl",
    "wof:placetype":"venue"
},
  "geometry": {"coordinates":[10.310501,43.577747],"type":"Point"}
}