{
  "type": "Feature",
  "properties": {
    "iso:country":"IT",
    "sg:address":"53036 Poggibonsi",
    "sg:city":"Poggibonsi",
    "sg:orig_category":"Arredo Bagno Ed Idrosanitari",
    "sg:phone":"+39 0577 978611",
    "sg:postcode":"53036",
    "sg:province":"Siena",
    "wof:name":"Aurora Spa",
    "wof:placetype":"venue"
},
  "geometry": {"coordinates":[11.184389,43.452106],"type":"Point"}
}