{
  "type": "Feature",
  "properties": {
    "iso:country":"IT",
    "sg:address":"9, Localita' S. Vitale 43038 Sala Baganza",
    "sg:city":"Sala Baganza",
    "sg:classifiers":[
        {
            "category":"Professional",
            "subcategory":"Engineering",
            "type":"Services"
        }
    ],
    "sg:phone":"+39 0521 833014",
    "sg:postcode":"43038",
    "sg:province":"Parma",
    "sg:tags":[
        "machine",
        "-",
        "mechanical"
    ],
    "wof:name":"Nuova Metal Plast (s.r.l.)",
    "wof:placetype":"venue"
},
  "geometry": {"coordinates":[10.221166,44.695545],"type":"Point"}
}