{
  "type": "Feature",
  "properties": {
    "addr:full":"35121 Padova Padova Padova 35121",
    "addr:postcode":"35121;35121",
    "iso:country":"IT",
    "sg:address":"35121 Padova",
    "sg:city":"Padova",
    "sg:orig_category":"Servizi E Lavori Per Ecologia E Smaltimento Rifiuti. Termotecnica E Riscaldamento, Apparecchiature E Servizi. Servizi Ausiliari Di Sorveglianza, Manutenzione E Pulizia",
    "sg:phone":"+39 049 657407",
    "sg:postcode":"35121",
    "sg:province":"Padova",
    "wof:name":"Uni-k S.r.l.",
    "wof:placetype":"venue"
},
  "geometry": {"coordinates":[11.803267,45.360806],"type":"Point"}
}