{
  "type": "Feature",
  "properties": {
    "addr:full":"21040 Cislago Cislago Varese 21040",
    "addr:postcode":"21040;21040",
    "iso:country":"IT",
    "sg:address":"21040 Cislago",
    "sg:city":"Cislago",
    "sg:orig_category":"Servizi E Lavori Per Edilizia E Lavori Pubblici",
    "sg:phone":"+39 02 9638 0914",
    "sg:postcode":"21040",
    "sg:province":"Varese",
    "wof:name":"Reggiori Enrico",
    "wof:placetype":"venue"
},
  "geometry": {"coordinates":[8.969393,45.662678],"type":"Point"}
}