{
  "type": "Feature",
  "properties": {
    "iso:country":"IT",
    "sg:address":"21, Vicolo Spercenigo 31030 Carbonera",
    "sg:city":"Carbonera",
    "sg:classifiers":[
        {
            "category":"Shopping",
            "subcategory":"Crafts & Fabrics",
            "type":"Retail Goods"
        }
    ],
    "sg:phone":"+39 0422 396366",
    "sg:postcode":"31030",
    "sg:province":"Treviso",
    "sg:tags":[
        "ceramic"
    ],
    "wof:name":"Ceramgres S.r.l.",
    "wof:placetype":"venue"
},
  "geometry": {"coordinates":[12.325892,45.689045],"type":"Point"}
}