{
  "type": "Feature",
  "properties": {
    "iso:country":"IT",
    "sg:address":"80049 Somma Vesuviana",
    "sg:city":"Somma Vesuviana",
    "sg:orig_category":"Arredo Cucina Ed Elettrodomestici. Elettrodomestici",
    "sg:phone":"+39 081 531 7273",
    "sg:postcode":"80049",
    "sg:province":"Napoli",
    "wof:name":"Merone Srl",
    "wof:placetype":"venue"
},
  "geometry": {"coordinates":[14.437396,40.878773],"type":"Point"}
}