{
  "type": "Feature",
  "properties": {
    "iso:country":"IT",
    "sg:address":"37013 Caprino Veronese",
    "sg:city":"Caprino Veronese",
    "sg:orig_category":"Legno E Semilavorati",
    "sg:phone":"+39 045 724 1100",
    "sg:postcode":"37013",
    "sg:province":"Verona",
    "wof:name":"Bertoldi Cav. Tobia",
    "wof:placetype":"venue"
},
  "geometry": {"coordinates":[10.812489,45.610195],"type":"Point"}
}