{
  "type": "Feature",
  "properties": {
    "iso:country":"IT",
    "sg:address":"Corso G.matteotti 123; S. Remo; 18038",
    "sg:classifiers":[
        {
            "category":"Banks & Credit Unions",
            "subcategory":"Bank",
            "type":"Services"
        }
    ],
    "sg:phone":"+39 0184 534071",
    "sg:postcode":"18038",
    "sg:province":"Imperia",
    "wof:name":"Banca Commerciale Italiana Spa",
    "wof:placetype":"venue"
},
  "geometry": {"coordinates":[7.774302,43.815723],"type":"Point"}
}