{
  "type": "Feature",
  "properties": {
    "iso:country":"IT",
    "sg:address":"00050 Torrimpietra",
    "sg:city":"Torrimpietra",
    "sg:orig_category":"Non-classified Establishments",
    "sg:phone":"+39 06 667 4349",
    "sg:postcode":"00050",
    "sg:province":"Roma",
    "wof:name":"Spaghetti Carlo",
    "wof:placetype":"venue"
},
  "geometry": {"coordinates":[12.200711,41.916836],"type":"Point"}
}