{
  "type": "Feature",
  "properties": {
    "iso:country":"IT",
    "sg:address":"6/a, Strada Dell' Assenzio 47031 Repubblica Di San Marino",
    "sg:classifiers":[
        {
            "category":"Shopping",
            "subcategory":"Clothing, Apparel, & Fashions",
            "type":"Retail Goods"
        }
    ],
    "sg:phone":"+39 0549 900362",
    "sg:province":"SM",
    "sg:tags":[
        "clothes"
    ],
    "wof:name":"Ponte & Mellini S.a.",
    "wof:placetype":"venue"
},
  "geometry": {"coordinates":[12.46558,43.969975],"type":"Point"}
}