{
  "type": "Feature",
  "properties": {
    "iso:country":"IT",
    "sg:address":"00187 Roma",
    "sg:city":"Roma",
    "sg:orig_category":"Abbigliamento Esterno, Maglierie E Pelliccerie. Shopping",
    "sg:phone":"+39 06 488 1266",
    "sg:postcode":"00187",
    "sg:province":"Roma",
    "wof:name":"Anna Maria Buoncristiani",
    "wof:placetype":"venue"
},
  "geometry": {"coordinates":[12.486777,41.908039],"type":"Point"}
}