{
  "type": "Feature",
  "properties": {
    "addr:full":"07100 Sassari Sassari Sassari 07100",
    "addr:postcode":"07100;07100",
    "iso:country":"IT",
    "sg:address":"07100 Sassari",
    "sg:city":"Sassari",
    "sg:orig_category":"Materiali Edili",
    "sg:phone":"+39 079 232021",
    "sg:postcode":"07100",
    "sg:province":"Sassari",
    "wof:name":"Tekedil Srl",
    "wof:placetype":"venue"
},
  "geometry": {"coordinates":[8.519426,40.712742],"type":"Point"}
}