{
  "type": "Feature",
  "properties": {
    "addr:full":"60020 Ancona Ancona 60020",
    "addr:postcode":"60020;60020",
    "iso:country":"IT",
    "sg:address":"60020 Ancona",
    "sg:orig_category":"Impianti, Attrezzature E Forniture Sanitarie Ed Ospedaliere",
    "sg:phone":"+39 071 218 1277",
    "sg:postcode":"60020",
    "sg:province":"Ancona",
    "sg:website":"http://www.sanitaritalia.it/com/index.htm",
    "wof:name":"Centro Ortopedico Marchigiano",
    "wof:placetype":"venue"
},
  "geometry": {"coordinates":[13.425691,43.61805],"type":"Point"}
}