{
  "type": "Feature",
  "properties": {
    "addr:full":"Corso Europa 2 Milan 20122",
    "addr:housenumber":"2",
    "addr:postcode":"20122",
    "addr:street":"Corso Europa",
    "iso:country":"IT",
    "sg:address":"Corso Europa 2",
    "sg:city":"Milan",
    "sg:classifiers":[
        {
            "category":"Professional",
            "subcategory":"Computer Services",
            "type":"Services"
        }
    ],
    "sg:postcode":"20122",
    "sg:tags":[
        "google",
        "search",
        "gmail",
        "blogger",
        "find",
        "information",
        "youtube"
    ],
    "sg:website":"http://google.com",
    "wof:name":"Google",
    "wof:placetype":"venue"
},
  "geometry": {"coordinates":[9.195978,45.46381],"type":"Point"}
}