{
  "type": "Feature",
  "properties": {
    "addr:full":"26034 Piadena Piadena Cremona 26034",
    "addr:postcode":"26034;26034",
    "iso:country":"IT",
    "sg:address":"26034 Piadena",
    "sg:city":"Piadena",
    "sg:orig_category":"Articoli Pulizia",
    "sg:phone":"+39 0375 98637",
    "sg:postcode":"26034",
    "sg:province":"Cremona",
    "wof:name":"Bruni Ernesto",
    "wof:placetype":"venue"
},
  "geometry": {"coordinates":[10.006044,45.147484],"type":"Point"}
}