{
  "type": "Feature",
  "properties": {
    "addr:full":"8, Via Borghi 22060 Cucciago Cucciago Como 22060",
    "addr:postcode":"22060;22060",
    "addr:street":"Via Borghi",
    "iso:country":"IT",
    "sg:address":"8, Via Borghi 22060 Cucciago",
    "sg:city":"Cucciago",
    "sg:classifiers":[
        {
            "category":"Professional",
            "subcategory":"Printing & Photocopies",
            "type":"Services"
        }
    ],
    "sg:phone":"+39 39031714726",
    "sg:postcode":"22060",
    "sg:province":"Como",
    "wof:name":"Foto Green (s.n.c.)",
    "wof:placetype":"venue"
},
  "geometry": {"coordinates":[9.1086149216,45.7408180237],"type":"Point"}
}