{
  "type": "Feature",
  "properties": {
    "addr:full":"00040 Pomezia Pomezia Roma 00040",
    "addr:postcode":"00040;roma 00040",
    "iso:country":"IT",
    "sg:address":"00040 Pomezia",
    "sg:city":"Pomezia",
    "sg:orig_category":"Arredo Cucina Ed Elettrodomestici. Elettrodomestici",
    "sg:phone":"+39 06 911 1503",
    "sg:postcode":"00040",
    "sg:province":"Roma",
    "wof:name":"Micromic Srl",
    "wof:placetype":"venue"
},
  "geometry": {"coordinates":[12.505219,41.667309],"type":"Point"}
}