{
  "type": "Feature",
  "properties": {
    "addr:full":"Via Don E. Cingolani 13 62010 Montecassiano Montecassiano Macerata 62010",
    "addr:housenumber":"13",
    "addr:postcode":"62010;62010",
    "addr:street":"Via Don E. Cingolani",
    "iso:country":"IT",
    "sg:address":"Via Don E. Cingolani 13 62010 Montecassiano",
    "sg:city":"Montecassiano",
    "sg:classifiers":[
        {
            "category":"Shopping",
            "subcategory":"Clothing, Apparel, & Fashions",
            "type":"Retail Goods"
        }
    ],
    "sg:phone":"+39 0733 290120",
    "sg:postcode":"62010",
    "sg:province":"Macerata",
    "sg:tags":[
        "image",
        "clothing",
        "basic"
    ],
    "sg:website":"www.ropam.com",
    "wof:name":"Ropam Srl",
    "wof:placetype":"venue"
},
  "geometry": {"coordinates":[13.459662,43.354935],"type":"Point"}
}