{
  "type": "Feature",
  "properties": {
    "addr:full":"10090 Trana Sangano Torino 10090",
    "addr:postcode":"10090;10090",
    "iso:country":"IT",
    "sg:address":"10090 Trana",
    "sg:city":"Sangano",
    "sg:orig_category":"Acciaierie E Fonderie",
    "sg:phone":"+39 011 933 8014",
    "sg:postcode":"10090",
    "sg:province":"Torino",
    "wof:name":"Procast S.r.l.",
    "wof:placetype":"venue"
},
  "geometry": {"coordinates":[7.461948,45.022007],"type":"Point"}
}