{
  "type": "Feature",
  "properties": {
    "iso:country":"IT",
    "sg:address":"Via Altaguardia 8 20135 Milano",
    "sg:city":"Milano",
    "sg:orig_category":"Ladies' Knitwear",
    "sg:phone":"+39 02 5831 8648",
    "sg:postcode":"20135",
    "sg:province":"Milano",
    "wof:name":"Santagiulia S.r.l.",
    "wof:placetype":"venue"
},
  "geometry": {"coordinates":[9.199824,45.449902],"type":"Point"}
}