{
  "type": "Feature",
  "properties": {
    "iso:country":"IT",
    "sg:address":"10, Via Tiso Camposampiero 35012 Camposampiero",
    "sg:city":"Camposampiero",
    "sg:classifiers":[
        {
            "category":"Personal",
            "subcategory":"Shoe Repair & Shine",
            "type":"Services"
        }
    ],
    "sg:phone":"+39 049 930 3350",
    "sg:postcode":"35012",
    "sg:province":"Padova",
    "sg:tags":[
        "leather"
    ],
    "wof:name":"Arkimedia S.a.s",
    "wof:placetype":"venue"
},
  "geometry": {"coordinates":[11.933789,45.570187],"type":"Point"}
}