{
  "type": "Feature",
  "properties": {
    "iso:country":"IT",
    "sg:address":"19121 La Spezia",
    "sg:classifiers":[
        {
            "category":"Social Services",
            "subcategory":"Job Training",
            "type":"Services"
        }
    ],
    "sg:phone":"+39 0187 732331",
    "sg:province":"SP",
    "sg:tags":[
        "services",
        "personnel",
        "school",
        "educational",
        "recruitment"
    ],
    "wof:name":"International House & C. Sas",
    "wof:placetype":"venue"
},
  "geometry": {"coordinates":[9.820863,44.106209],"type":"Point"}
}