{
  "type": "Feature",
  "properties": {
    "addr:full":"1, Via Provinciale 24059 Urgnano Urgnano Bergamo 24059",
    "addr:postcode":"24059;24059",
    "addr:street":"Via Provinciale",
    "iso:country":"IT",
    "sg:address":"1, Via Provinciale 24059 Urgnano",
    "sg:city":"Urgnano",
    "sg:classifiers":[
        {
            "category":"Manufacturing",
            "subcategory":"Textiles",
            "type":"Manufacturing & Wholesale Goods"
        }
    ],
    "sg:phone":"+39 39035893016",
    "sg:postcode":"24059",
    "sg:province":"Bergamo",
    "sg:tags":[
        "leather",
        "raw",
        "material",
        "-"
    ],
    "wof:name":"Ve-pi S.p.a.",
    "wof:placetype":"venue"
},
  "geometry": {"coordinates":[9.703554,45.587193],"type":"Point"}
}