{
  "type": "Feature",
  "properties": {
    "iso:country":"IT",
    "sg:address":"21013 Gallarate",
    "sg:city":"Gallarate",
    "sg:orig_category":"Accessori Moda D'abbigliamento. Forniture Per Abbigliamento E Pelletterie",
    "sg:phone":"+39 0331 730033",
    "sg:postcode":"21013",
    "sg:province":"Varese",
    "wof:name":"Saporiti Giuliano",
    "wof:placetype":"venue"
},
  "geometry": {"coordinates":[8.784987,45.64846],"type":"Point"}
}