{
  "type": "Feature",
  "properties": {
    "iso:country":"IT",
    "sg:address":"80061 Massa Lubrense",
    "sg:city":"Massa Lubrense",
    "sg:orig_category":"Liquori - Produzione E Ingrosso",
    "sg:phone":"+39 081 808 1368",
    "sg:postcode":"80061",
    "sg:province":"Napoli",
    "wof:name":"Nastro D'oro",
    "wof:placetype":"venue"
},
  "geometry": {"coordinates":[14.350098,40.596878],"type":"Point"}
}