{
  "type": "Feature",
  "properties": {
    "iso:country":"IT",
    "sg:address":"Via Valsorda 22044 Inverigo",
    "sg:city":"Inverigo",
    "sg:classifiers":[
        {
            "category":"Home & Garden",
            "subcategory":"Home Furnishings",
            "type":"Retail Goods"
        }
    ],
    "sg:phone":"+39 39031698245",
    "sg:postcode":"22044",
    "sg:province":"Como",
    "sg:tags":[
        "household"
    ],
    "wof:name":"Fimar (s.r.l.)",
    "wof:placetype":"venue"
},
  "geometry": {"coordinates":[9.198104,45.737427],"type":"Point"}
}