{
  "type": "Feature",
  "properties": {
    "iso:country":"IT",
    "sg:address":"2, V. Ferrari 22100 Como",
    "sg:city":"Como",
    "sg:classifiers":[
        {
            "category":"Shopping",
            "subcategory":"Crafts & Fabrics",
            "type":"Retail Goods"
        }
    ],
    "sg:phone":"+39 39031303333",
    "sg:postcode":"22100",
    "sg:province":"Como",
    "sg:website":"http://www.paginegialle.it/sonvicora",
    "wof:name":"Sonvico Renato, Manuela Srl",
    "wof:placetype":"venue"
},
  "geometry": {"coordinates":[9.088891983,45.8095741272],"type":"Point"}
}