{
  "type": "Feature",
  "properties": {
    "addr:full":"134, V. Cesare Battisti 24025 Gazzaniga Gazzaniga Bergamo 24025",
    "addr:housenumber":"134",
    "addr:postcode":"24025;24025",
    "addr:street":"V. Cesare Battisti",
    "iso:country":"IT",
    "sg:address":"134, V. Cesare Battisti 24025 Gazzaniga",
    "sg:city":"Gazzaniga",
    "sg:classifiers":[
        {
            "category":"Autos & Motor Vehicles",
            "subcategory":"Automobile Sales",
            "type":"Retail Goods"
        }
    ],
    "sg:phone":"+39 39035712091",
    "sg:postcode":"24025",
    "sg:province":"Bergamo",
    "sg:tags":[
        "industrial"
    ],
    "sg:website":"http://www.acmrs.com:ws_end: :mark:ws:http://www.paginegialle.it/mrssrl-bg",
    "wof:name":"Mrs Srl",
    "wof:placetype":"venue"
},
  "geometry": {"coordinates":[9.824736,45.789436],"type":"Point"}
}