{
  "type": "Feature",
  "properties": {
    "iso:country":"IT",
    "sg:address":"Frazione Piticchio 60011 Arcevia",
    "sg:city":"Arcevia",
    "sg:classifiers":[
        {
            "category":"Real Estate",
            "subcategory":"Surveying",
            "type":"Services"
        }
    ],
    "sg:phone":"+39 0731 981046",
    "sg:postcode":"60011",
    "sg:province":"Ancona",
    "sg:tags":[
        "equipment",
        "material",
        "good",
        "-",
        "handling"
    ],
    "wof:name":"Copriradiator Di Ugolini R. & F. Snc",
    "wof:placetype":"venue"
},
  "geometry": {"coordinates":[12.980696,43.549618],"type":"Point"}
}