{
  "type": "Feature",
  "properties": {
    "addr:full":"80026 Casoria Casoria Napoli 80026",
    "addr:postcode":"80026;80026",
    "iso:country":"IT",
    "sg:address":"80026 Casoria",
    "sg:city":"Casoria",
    "sg:orig_category":"Manufacturers: Prefabbricati",
    "sg:phone":"+39 081 759 0431",
    "sg:postcode":"80026",
    "sg:province":"Napoli",
    "wof:name":"Tecnopref S.r.l.",
    "wof:placetype":"venue"
},
  "geometry": {"coordinates":[14.312369,40.881283],"type":"Point"}
}