{
  "type": "Feature",
  "properties": {
    "iso:country":"IT",
    "sg:address":"10060 Prali",
    "sg:city":"Prali",
    "sg:orig_category":"Prodotti Cosmetici E Da Toeletta. Forniture Per Attivita' Industriali",
    "sg:phone":"+39 0121 848811",
    "sg:postcode":"10060",
    "sg:province":"Torino",
    "wof:name":"Luzenac Val Chisone Spa",
    "wof:placetype":"venue"
},
  "geometry": {"coordinates":[7.0693469048,44.9321784973],"type":"Point"}
}