{
  "type": "Feature",
  "properties": {
    "addr:full":"88100 Catanzaro Catanzaro Catanzaro 88100",
    "addr:postcode":"88100;88100",
    "iso:country":"IT",
    "sg:address":"88100 Catanzaro",
    "sg:city":"Catanzaro",
    "sg:orig_category":"Insegne Luminose",
    "sg:phone":"+39 0961 789349",
    "sg:postcode":"88100",
    "sg:province":"Catanzaro",
    "wof:name":"Cristal Neon Srl",
    "wof:placetype":"venue"
},
  "geometry": {"coordinates":[16.608791,38.831573],"type":"Point"}
}