{
  "type": "Feature",
  "properties": {
    "addr:full":"83, Lung'adige Leopardi Giacomo 38100 Trento Trento Trento 38100",
    "addr:housenumber":"83",
    "addr:postcode":"38100;38100",
    "addr:street":"Lung'Adige Leopardi Giacomo",
    "iso:country":"IT",
    "sg:address":"83, Lung'adige Leopardi Giacomo 38100 Trento",
    "sg:city":"Trento",
    "sg:classifiers":[
        {
            "category":"Shopping",
            "subcategory":"Stationery & Office Supplies",
            "type":"Retail Goods"
        }
    ],
    "sg:phone":"+39 0461 828900",
    "sg:postcode":"38100",
    "sg:province":"Trento",
    "sg:tags":[
        "professional"
    ],
    "wof:name":"Habitat Ufficio (s.r.l.)",
    "wof:placetype":"venue"
},
  "geometry": {"coordinates":[11.1170539856,46.0742378235],"type":"Point"}
}