{
  "type": "Feature",
  "properties": {
    "iso:country":"IT",
    "sg:address":"Viale Risorgimento 56 45011 Adria",
    "sg:city":"Adria",
    "sg:classifiers":[
        {
            "category":"Shopping",
            "subcategory":"Clothing, Apparel, & Fashions",
            "type":"Retail Goods"
        }
    ],
    "sg:phone":"+39 0426 42500",
    "sg:postcode":"45011",
    "sg:province":"Rovigo",
    "sg:tags":[
        "children's",
        "clothing"
    ],
    "wof:name":"Giada Srl",
    "wof:placetype":"venue"
},
  "geometry": {"coordinates":[12.027908,45.059418],"type":"Point"}
}