{
  "type": "Feature",
  "properties": {
    "iso:country":"IT",
    "sg:address":"74100 Taranto",
    "sg:city":"Taranto",
    "sg:orig_category":"Valvole E Apparecchiature Di Misura",
    "sg:phone":"+39 099 477 6333",
    "sg:postcode":"74100",
    "sg:province":"Taranto",
    "wof:name":"Societa' Deda",
    "wof:placetype":"venue"
},
  "geometry": {"coordinates":[17.111071,40.593098],"type":"Point"}
}