{
  "type": "Feature",
  "properties": {
    "iso:country":"IT",
    "sg:address":"Via Europa Unita 28 33050 Terenzano",
    "sg:city":"Terenzano",
    "sg:classifiers":[
        {
            "category":"Banks & Credit Unions",
            "subcategory":"Financial Services",
            "type":"Services"
        }
    ],
    "sg:phone":"+39 0432 561431",
    "sg:postcode":"33050",
    "sg:province":"Udine",
    "sg:tags":[
        "wreath",
        "spray",
        "flower"
    ],
    "sg:website":"www.altierinillo.com",
    "wof:name":"Commerciale Altieri Sas",
    "wof:placetype":"venue"
},
  "geometry": {"coordinates":[13.2307243347,46.0649414062],"type":"Point"}
}