{
  "type": "Feature",
  "properties": {
    "iso:country":"IT",
    "sg:address":"37131 Verona",
    "sg:city":"Verona",
    "sg:orig_category":"Chiese Ed Associazioni Religiose",
    "sg:phone":"+39 045 520618",
    "sg:postcode":"37131",
    "sg:province":"Verona",
    "wof:name":"Comunita' Ebraica",
    "wof:placetype":"venue"
},
  "geometry": {"coordinates":[11.028115,45.441219],"type":"Point"}
}