{
  "type": "Feature",
  "properties": {
    "addr:full":"40033 Casalecchio Di Reno Casalecchio di Reno Bologna 40033",
    "addr:postcode":"40033;40033",
    "addr:street":"Di Reno",
    "iso:country":"IT",
    "sg:address":"40033 Casalecchio Di Reno",
    "sg:city":"Casalecchio di Reno",
    "sg:orig_category":"Imprese Di Costruzioni Civili Ed Industriali",
    "sg:phone":"+39 051 613 2909",
    "sg:postcode":"40033",
    "sg:province":"Bologna",
    "wof:name":"Euroinfissi Sas",
    "wof:placetype":"venue"
},
  "geometry": {"coordinates":[11.266168,44.489155],"type":"Point"}
}