{
  "type": "Feature",
  "properties": {
    "iso:country":"IT",
    "sg:address":"00176 Roma",
    "sg:city":"Roma",
    "sg:orig_category":"Automobili - Commercio",
    "sg:phone":"+39 06 241 5061",
    "sg:postcode":"00176",
    "sg:province":"Roma",
    "wof:name":"Nikoauto Srl",
    "wof:placetype":"venue"
},
  "geometry": {"coordinates":[12.539624,41.876945],"type":"Point"}
}