{
  "type": "Feature",
  "properties": {
    "addr:full":"153, Via Gramsci Antonio 51037 Montale Montale Pistoia 51037",
    "addr:housenumber":"153",
    "addr:postcode":"51037;51037",
    "addr:street":"Via Gramsci Antonio",
    "iso:country":"IT",
    "sg:address":"153, Via Gramsci Antonio 51037 Montale",
    "sg:city":"Montale",
    "sg:classifiers":[
        {
            "category":"Shopping",
            "subcategory":"Crafts & Fabrics",
            "type":"Retail Goods"
        }
    ],
    "sg:phone":"+39 0573 558266",
    "sg:postcode":"51037",
    "sg:province":"Pistoia",
    "wof:name":"Filati Biagioli Modesto Spa",
    "wof:placetype":"venue"
},
  "geometry": {"coordinates":[11.0339756012,43.9477424622],"type":"Point"}
}