{
  "type": "Feature",
  "properties": {
    "iso:country":"IT",
    "sg:address":"Via Cav. Di Vittorio Veneto 45 15066 Gavi",
    "sg:city":"Gavi",
    "sg:classifiers":[
        {
            "category":"Food & Beverages",
            "subcategory":"Liquor & Beverages",
            "type":"Retail Goods"
        }
    ],
    "sg:phone":"+39 0143 642786",
    "sg:postcode":"15066",
    "sg:province":"Alessandria",
    "sg:tags":[
        "wine",
        "italian"
    ],
    "wof:name":"Cantina Produttori Del Gavi Scrl",
    "wof:placetype":"venue"
},
  "geometry": {"coordinates":[8.616951,44.913216],"type":"Point"}
}