{
  "type": "Feature",
  "properties": {
    "iso:country":"IT",
    "sg:address":"25, Piazza Roma 60121 Ancona",
    "sg:city":"Ancona",
    "sg:classifiers":[
        {
            "category":"Banks & Credit Unions",
            "subcategory":"Bank",
            "type":"Services"
        }
    ],
    "sg:phone":"+39 390 712 8231",
    "sg:postcode":"60121",
    "sg:province":"Ancona",
    "sg:tags":[
        "banking",
        "institution"
    ],
    "wof:name":"Cariverona Banca S.p.a.",
    "wof:placetype":"venue"
},
  "geometry": {"coordinates":[13.51321,43.617382],"type":"Point"}
}