{
  "type": "Feature",
  "properties": {
    "addr:full":"Via Francesco Lonati 3 25124 Brescia Brescia Brescia 25124",
    "addr:housenumber":"3",
    "addr:postcode":"25124;25124",
    "addr:street":"Via Francesco Lonati",
    "iso:country":"IT",
    "sg:address":"Via Francesco Lonati 3 25124 Brescia",
    "sg:city":"Brescia",
    "sg:classifiers":[
        {
            "category":"Manufacturing",
            "subcategory":"Motor Vehicles & Parts",
            "type":"Manufacturing & Wholesale Goods"
        }
    ],
    "sg:phone":"+39 030 23901",
    "sg:postcode":"25124",
    "sg:province":"Brescia",
    "sg:tags":[
        "machine",
        "wire",
        "coating"
    ],
    "sg:website":"www.lonati.com",
    "wof:name":"Lonati Spa",
    "wof:placetype":"venue"
},
  "geometry": {"coordinates":[10.222958,45.539829],"type":"Point"}
}