{
  "type": "Feature",
  "properties": {
    "iso:country":"IT",
    "sg:address":"16162 Genova",
    "sg:city":"Genova",
    "sg:orig_category":"Forniture Industriali Per Prevenzione, Controllo E Sicurezza",
    "sg:phone":"+39 010 740 8267",
    "sg:postcode":"16162",
    "sg:province":"Genova",
    "wof:name":"Riberti Francesco (s.n.c.)",
    "wof:placetype":"venue"
},
  "geometry": {"coordinates":[8.8880691528,44.9679908752],"type":"Point"}
}