{
  "type": "Feature",
  "properties": {
    "iso:country":"IT",
    "sg:address":"18, Via Guido Rossa 20040 Cornate D'adda",
    "sg:classifiers":[
        {
            "category":"Shopping",
            "subcategory":"Computers & Home Electronics",
            "type":"Retail Goods"
        }
    ],
    "sg:phone":"+39 390 396 1001",
    "sg:postcode":"20040",
    "sg:province":"Milano",
    "sg:tags":[
        "electronic",
        "electrical",
        "equipment"
    ],
    "wof:name":"Compel Electronics S.p.a.",
    "wof:placetype":"venue"
},
  "geometry": {"coordinates":[9.188141,45.463688],"type":"Point"}
}