{
  "type": "Feature",
  "properties": {
    "iso:country":"IT",
    "sg:address":"80122 Napoli",
    "sg:city":"Napoli",
    "sg:orig_category":"Imprese Edili",
    "sg:phone":"+39 081 666360",
    "sg:postcode":"80122",
    "sg:province":"Napoli",
    "sg:website":"http://www.paginegialle.it/olivacostruzioni",
    "wof:name":"Oliva Costruzioni & Servizi Srl",
    "wof:placetype":"venue"
},
  "geometry": {"coordinates":[14.212977,40.913803],"type":"Point"}
}