{
  "type": "Feature",
  "properties": {
    "iso:country":"IT",
    "sg:address":"61100 Pesaro",
    "sg:city":"Pesaro",
    "sg:orig_category":"Supermercati, Grandi Magazzini E Centri Commerciali",
    "sg:phone":"+39 0721 42741",
    "sg:postcode":"61100",
    "sg:province":"Pesaro E Urbino",
    "wof:name":"Iper Pesaro",
    "wof:placetype":"venue"
},
  "geometry": {"coordinates":[12.873857,43.907509],"type":"Point"}
}