{
  "type": "Feature",
  "properties": {
    "iso:country":"IT",
    "sg:address":"43, Via Di S. Pieretto 55012 Capannori",
    "sg:city":"Capannori",
    "sg:classifiers":[
        {
            "category":"Professional",
            "subcategory":"Printing & Photocopies",
            "type":"Services"
        }
    ],
    "sg:phone":"+39 0583 403242",
    "sg:postcode":"55012",
    "sg:province":"Lucca",
    "wof:name":"S. Marco Litotipo S.r.l.",
    "wof:placetype":"venue"
},
  "geometry": {"coordinates":[10.5043392181,43.8109970093],"type":"Point"}
}