{
  "type": "Feature",
  "properties": {
    "iso:country":"IT",
    "sg:address":"Largo Richini 6, 20122 Milan, Mi",
    "sg:classifiers":[
        {
            "category":"Banks & Credit Unions",
            "subcategory":"Bank",
            "type":"Services"
        }
    ],
    "sg:phone":"+39 02 583741",
    "sg:postcode":"20122",
    "sg:province":"Milano",
    "wof:name":"Sopaf-societa' Partecipazioni Finanziarie Spa",
    "wof:placetype":"venue"
},
  "geometry": {"coordinates":[9.192913,45.460045],"type":"Point"}
}