{
  "type": "Feature",
  "properties": {
    "addr:full":"34073 Grado Grado Gorizia 34073",
    "addr:postcode":"34073;34073",
    "iso:country":"IT",
    "sg:address":"34073 Grado",
    "sg:city":"Grado",
    "sg:orig_category":"Agenzie Immobiliari",
    "sg:phone":"+39 0431 83546",
    "sg:postcode":"34073",
    "sg:province":"Gorizia",
    "wof:name":"Agenzia Immobiliare Athena",
    "wof:placetype":"venue"
},
  "geometry": {"coordinates":[13.3796339035,45.6996841431],"type":"Point"}
}