{
  "type": "Feature",
  "properties": {
    "iso:country":"IT",
    "sg:address":"00162 Roma",
    "sg:city":"Roma",
    "sg:orig_category":"Accessori Dei Mezzi Di Trasporto. Riparazione Dei Mezzi Di Trasporto",
    "sg:phone":"+39 06 860 4452",
    "sg:postcode":"00162",
    "sg:province":"Roma",
    "wof:name":"Massenzi S.r.l.",
    "wof:placetype":"venue"
},
  "geometry": {"coordinates":[12.526935,41.905579],"type":"Point"}
}