{
  "type": "Feature",
  "properties": {
    "iso:country":"IT",
    "sg:address":"25030 Erbusco",
    "sg:city":"Erbusco",
    "sg:orig_category":"Servizi E Lavori Per Agricoltura E Zootecnia",
    "sg:phone":"+39 030 770 9842",
    "sg:postcode":"25030",
    "sg:province":"Brescia",
    "wof:name":"Gatti Carlo",
    "wof:placetype":"venue"
},
  "geometry": {"coordinates":[10.207389,45.608902],"type":"Point"}
}