{
  "type": "Feature",
  "properties": {
    "iso:country":"IT",
    "sg:address":"06121 Perugia",
    "sg:city":"Perugia",
    "sg:orig_category":"Pubblica Amministrazione",
    "sg:phone":"+39 075 572 1499",
    "sg:postcode":"06121",
    "sg:province":"Perugia",
    "wof:name":"Proc.repubbl. Co Trib.pg",
    "wof:placetype":"venue"
},
  "geometry": {"coordinates":[12.3897590637,43.1111030579],"type":"Point"}
}