{
  "type": "Feature",
  "properties": {
    "iso:country":"IT",
    "sg:address":"25065 Lumezzane",
    "sg:city":"Lumezzane",
    "sg:orig_category":"Stampi, Maschere E Ferri Da Trancia",
    "sg:phone":"+39 030 892 0542",
    "sg:postcode":"25065",
    "sg:province":"Brescia",
    "wof:name":"Officina Meccanica Ricetti Di Ricetti Antonio & Ziglioli G. Snc",
    "wof:placetype":"venue"
},
  "geometry": {"coordinates":[10.255478,45.650322],"type":"Point"}
}