{
  "type": "Feature",
  "properties": {
    "iso:country":"IT",
    "sg:address":"73100 Lecce",
    "sg:city":"Lecce",
    "sg:orig_category":"Prodotti Alimentari",
    "sg:phone":"+39 0832 240951",
    "sg:postcode":"73100",
    "sg:province":"Lecce",
    "wof:name":"In.t.e.r. Frutta Spa",
    "wof:placetype":"venue"
},
  "geometry": {"coordinates":[18.2140274048,40.401058197],"type":"Point"}
}