{
  "type": "Feature",
  "properties": {
    "iso:country":"IT",
    "sg:address":"20095 Cusano Milanino",
    "sg:city":"Cusano Milanino",
    "sg:orig_category":"Frigotecnica, Apparecchiature E Servizi. Forniture Alle Strutture Ricettive",
    "sg:phone":"+39 02 613 3037",
    "sg:postcode":"20095",
    "sg:province":"Milano",
    "sg:website":"http://www.coaf.it",
    "wof:name":"Co.a.f. Srl",
    "wof:placetype":"venue"
},
  "geometry": {"coordinates":[9.1795845032,45.5470199585],"type":"Point"}
}