{
  "type": "Feature",
  "properties": {
    "addr:full":"109, Viale Dante 47838 Riccione Riccione Rimini 47838",
    "addr:postcode":"47838;47838",
    "addr:street":"Viale Dante",
    "iso:country":"IT",
    "sg:address":"109, Viale Dante 47838 Riccione",
    "sg:city":"Riccione",
    "sg:classifiers":[
        {
            "category":"Sports & Exercise",
            "subcategory":"Playing Field",
            "type":"Entertainment"
        }
    ],
    "sg:phone":"+39 0541 648456",
    "sg:postcode":"47838",
    "sg:province":"Rimini",
    "sg:tags":[
        "game"
    ],
    "wof:name":"Bartolucci Francesco E C. S.n.c.",
    "wof:placetype":"venue"
},
  "geometry": {"coordinates":[12.652999,44.006569],"type":"Point"}
}