{
  "type": "Feature",
  "properties": {
    "iso:country":"IT",
    "sg:address":"24050 Grassobbio",
    "sg:city":"Grassobbio",
    "sg:orig_category":"Macchine E Forniture Per Ecologia E Smaltimento Rifiuti",
    "sg:phone":"+39 035 526911",
    "sg:postcode":"24050",
    "sg:province":"Bergamo",
    "wof:name":"Tre Effe Srl",
    "wof:placetype":"venue"
},
  "geometry": {"coordinates":[9.726722,45.657814],"type":"Point"}
}