{
  "type": "Feature",
  "properties": {
    "addr:full":"38020 Rumo Rumo Trento 38020",
    "addr:postcode":"38020;38020",
    "iso:country":"IT",
    "sg:address":"38020 Rumo",
    "sg:city":"Rumo",
    "sg:orig_category":"Elettronica Professionale E Di Consumo. Musica",
    "sg:phone":"+39 0463 530071",
    "sg:postcode":"38020",
    "sg:province":"Trento",
    "wof:name":"Carrara Giorgio",
    "wof:placetype":"venue"
},
  "geometry": {"coordinates":[11.030558,46.435806],"type":"Point"}
}