{
  "type": "Feature",
  "properties": {
    "iso:country":"IT",
    "sg:address":"40, Via Occimiano 10156 Torino",
    "sg:city":"Torino",
    "sg:classifiers":[
        {
            "category":"Banks & Credit Unions",
            "subcategory":"Investment Brokerage",
            "type":"Services"
        }
    ],
    "sg:phone":"+39 011 273 3576",
    "sg:postcode":"10156",
    "sg:province":"Torino",
    "sg:tags":[
        "-",
        "transport",
        "related"
    ],
    "wof:name":"Reviati Egidio (s.r.l.)",
    "wof:placetype":"venue"
},
  "geometry": {"coordinates":[7.733638,45.108875],"type":"Point"}
}