{
  "type": "Feature",
  "properties": {
    "iso:country":"IT",
    "sg:address":"20092 Cinisello Balsamo",
    "sg:city":"Cinisello Balsamo",
    "sg:orig_category":"Calzature, Pelletterie E Pelli",
    "sg:phone":"+39 02 6604 9541",
    "sg:postcode":"20092",
    "sg:province":"Milano",
    "wof:name":"Motta Alfredo (s.p.a.)",
    "wof:placetype":"venue"
},
  "geometry": {"coordinates":[9.246626,45.556496],"type":"Point"}
}