{
  "type": "Feature",
  "properties": {
    "addr:full":"33030 Maiano Udine 33030",
    "addr:postcode":"33030;33030",
    "iso:country":"IT",
    "sg:address":"33030 Maiano",
    "sg:orig_category":"Arredamenti - Produzione E Ingrosso",
    "sg:phone":"+39 0432 948138",
    "sg:postcode":"33030",
    "sg:province":"Udine",
    "wof:name":"Idea Effe Srl",
    "wof:placetype":"venue"
},
  "geometry": {"coordinates":[13.269931,46.017456],"type":"Point"}
}