{
  "type": "Feature",
  "properties": {
    "iso:country":"IT",
    "sg:address":"02024 Pescorocchiano",
    "sg:city":"Pescorocchiano",
    "sg:orig_category":"Pubblica Amministrazione",
    "sg:phone":"+39 0746 338113",
    "sg:postcode":"02024",
    "sg:province":"Rieti",
    "wof:name":"Comando Prov. Vv.ff.",
    "wof:placetype":"venue"
},
  "geometry": {"coordinates":[13.1492395401,42.2047767639],"type":"Point"}
}