{
  "type": "Feature",
  "properties": {
    "addr:full":"Via Provana, 1 Torino 10123",
    "addr:housenumber":"1",
    "addr:postcode":"10123",
    "addr:street":"Via Provana",
    "iso:country":"IT",
    "sg:address":"Via Provana, 1",
    "sg:city":"Torino",
    "sg:classifiers":[
        {
            "category":"Professional",
            "subcategory":"Computer Services",
            "type":"Services"
        }
    ],
    "sg:postcode":"10123",
    "sg:tags":[
        "video",
        "film",
        "television",
        "italy",
        "los-angeles",
        "mcvicar",
        "mcvlog",
        "latenitemash"
    ],
    "sg:website":"http://www.magmawave.com/en",
    "wof:name":"MagmaWave",
    "wof:placetype":"venue"
},
  "geometry": {"coordinates":[7.6887893,45.0626743],"type":"Point"}
}