{
  "type": "Feature",
  "properties": {
    "iso:country":"IT",
    "sg:address":"95128 Catania",
    "sg:city":"Catania",
    "sg:orig_category":"Abbigliamento Esterno, Maglierie E Pelliccerie. Calzature, Pelletterie E Pelli. Sport - Articoli E Forniture",
    "sg:phone":"+39 095 434733",
    "sg:postcode":"95128",
    "sg:province":"Catania",
    "wof:name":"Equitana Di Agosta Dario",
    "wof:placetype":"venue"
},
  "geometry": {"coordinates":[15.087279,37.514847],"type":"Point"}
}