{
  "type": "Feature",
  "properties": {
    "iso:country":"IT",
    "sg:address":"8/10/12, Via Di Vittorio 23844 Sirone",
    "sg:city":"Sirone",
    "sg:classifiers":[
        {
            "category":"Parking",
            "subcategory":"Lot",
            "type":"Transportation"
        }
    ],
    "sg:phone":"+39 39031852494",
    "sg:postcode":"23844",
    "sg:province":"Lecco",
    "sg:tags":[
        "transport",
        "road"
    ],
    "wof:name":"Autotrasporti Corti S.r.l.",
    "wof:placetype":"venue"
},
  "geometry": {"coordinates":[9.374392,45.792953],"type":"Point"}
}