{
  "type": "Feature",
  "properties": {
    "addr:full":"15, V. Pradelle 24021 Albino Albino Bergamo 24021",
    "addr:housenumber":"15",
    "addr:postcode":"24021;24021",
    "addr:street":"V. Pradelle",
    "iso:country":"IT",
    "sg:address":"15, V. Pradelle 24021 Albino",
    "sg:city":"Albino",
    "sg:classifiers":[
        {
            "category":"Wholesale",
            "subcategory":"Drugs",
            "type":"Manufacturing & Wholesale Goods"
        }
    ],
    "sg:phone":"+39 39035751231",
    "sg:postcode":"24021",
    "sg:province":"Bergamo",
    "sg:tags":[
        "chemical",
        "pharmaceutical"
    ],
    "sg:website":"http://www.druckfarben.it:ws_end: :mark:ws:http://www.paginegialle.it/druckfarb",
    "wof:name":"Druckfarben Srl",
    "wof:placetype":"venue"
},
  "geometry": {"coordinates":[9.669952,45.694904],"type":"Point"}
}