{
  "type": "Feature",
  "properties": {
    "addr:full":"24125 Bergamo Bergamo Bergamo 24125",
    "addr:postcode":"24125;24125",
    "iso:country":"IT",
    "sg:address":"24125 Bergamo",
    "sg:city":"Bergamo",
    "sg:orig_category":"Forniture Per Edilizia E Lavori Pubblici. Prodotti Vari In Metallo",
    "sg:phone":"+39 035 219065",
    "sg:postcode":"24125",
    "sg:province":"Bergamo",
    "wof:name":"Biancolini Alessandro",
    "wof:placetype":"venue"
},
  "geometry": {"coordinates":[9.6911754608,45.6952362061],"type":"Point"}
}