{
  "type": "Feature",
  "properties": {
    "iso:country":"IT",
    "sg:address":"47020 Castello Montenovo",
    "sg:orig_category":"Macchine, Impianti Ed Attrezzature Per Industria Alimentare E Bevande. Forniture Alle Strutture Ricettive. Macchine E Impianti Per Attivita' Commerciali Ed Artigianali",
    "sg:phone":"+39 0547 327014",
    "sg:postcode":"47020",
    "sg:province":"Forl\u00ec-Cesena",
    "wof:name":"F.lli Pollini En.pa.er. Di Pollini Enzo & C. (s.n.c.)",
    "wof:placetype":"venue"
},
  "geometry": {"coordinates":[12.124581,44.114918],"type":"Point"}
}