{
  "type": "Feature",
  "properties": {
    "addr:full":"316, Via Torino 12044 Centallo Centallo Cuneo 12044",
    "addr:housenumber":"316",
    "addr:postcode":"12044;12044",
    "addr:street":"Via Torino",
    "iso:country":"IT",
    "sg:address":"316, Via Torino 12044 Centallo",
    "sg:city":"Centallo",
    "sg:classifiers":[
        {
            "category":"Shopping",
            "subcategory":"Clothing, Apparel, & Fashions",
            "type":"Retail Goods"
        }
    ],
    "sg:phone":"+39 0171 211640",
    "sg:postcode":"12044",
    "sg:province":"Cuneo",
    "sg:tags":[
        "clothes"
    ],
    "wof:name":"Apprhodo (s.r.l.)",
    "wof:placetype":"venue"
},
  "geometry": {"coordinates":[7.567436,44.453693],"type":"Point"}
}