{
  "type": "Feature",
  "properties": {
    "addr:full":"Viale F.lli Casiraghi 422 20099 Sesto San Giovanni Sesto San Giovanni Milano 20099",
    "addr:housenumber":"422",
    "addr:postcode":"20099;20099",
    "addr:street":"Viale F.Lli Casiraghi",
    "iso:country":"IT",
    "sg:address":"Viale F.lli Casiraghi 422 20099 Sesto San Giovanni",
    "sg:city":"Sesto San Giovanni",
    "sg:classifiers":[
        {
            "category":"Farming",
            "subcategory":"Fish & Marine Products",
            "type":"Manufacturing & Wholesale Goods"
        }
    ],
    "sg:phone":"+39 02 248 5650",
    "sg:postcode":"20099",
    "sg:province":"Milano",
    "sg:tags":[
        "food",
        "chemical",
        "industry"
    ],
    "wof:name":"Gildo Dal Cin Spa",
    "wof:placetype":"venue"
},
  "geometry": {"coordinates":[9.188141,45.463688],"type":"Point"}
}