{
  "type": "Feature",
  "properties": {
    "iso:country":"IT",
    "sg:address":"43013 Langhirano",
    "sg:city":"Langhirano",
    "sg:orig_category":"Studi E Consulenze Tecniche E Industriali. Servizi E Lavori Per Edilizia E Lavori Pubblici. Professionisti - Studi E Servizi Ed Associazioni Di Interesse Aziendale",
    "sg:phone":"+39 0521 858380",
    "sg:postcode":"43013",
    "sg:province":"Parma",
    "wof:name":"Rossi Geom. Simone",
    "wof:placetype":"venue"
},
  "geometry": {"coordinates":[9.996408,44.693462],"type":"Point"}
}