{
  "type": "Feature",
  "properties": {
    "addr:full":"9, Via Vodice 20148 Milano Milano Milano 20148",
    "addr:postcode":"20148;20148",
    "addr:street":"Via Vodice",
    "iso:country":"IT",
    "sg:address":"9, Via Vodice 20148 Milano",
    "sg:city":"Milano",
    "sg:classifiers":[
        {
            "category":"Autos & Motor Vehicles",
            "subcategory":"Automobile Sales",
            "type":"Retail Goods"
        }
    ],
    "sg:phone":"+39 39024042439",
    "sg:postcode":"20148",
    "sg:province":"Milano",
    "sg:tags":[
        "equipment",
        "transport"
    ],
    "wof:name":"Olympia Srl",
    "wof:placetype":"venue"
},
  "geometry": {"coordinates":[9.141672,45.474857],"type":"Point"}
}