{
  "type": "Feature",
  "properties": {
    "addr:full":"67032 Pescasseroli L'Aquila 67032",
    "addr:postcode":"67032;l'aquila 67032",
    "iso:country":"IT",
    "sg:address":"67032 Pescasseroli",
    "sg:classifiers":[
        {
            "category":"Restaurant",
            "type":"Food & Drink"
        }
    ],
    "sg:phone":"+39 0863 912858",
    "sg:postcode":"67032",
    "sg:province":"L'Aquila",
    "sg:tags":[
        "auxiliary",
        "entertainment",
        "premises",
        "related",
        "catering",
        "similar",
        "public",
        "restaurants"
    ],
    "wof:name":"Vail Club Vacanze Srl",
    "wof:placetype":"venue"
},
  "geometry": {"coordinates":[13.394314,42.354118],"type":"Point"}
}