{
  "type": "Feature",
  "properties": {
    "iso:country":"IT",
    "sg:address":"Via Delle Forze Armate 260; Milano; 20152",
    "sg:city":"Milano",
    "sg:classifiers":[
        {
            "category":"Banks & Credit Unions",
            "subcategory":"Bank",
            "type":"Services"
        }
    ],
    "sg:phone":"+39 02 4891 5910",
    "sg:postcode":"20152",
    "sg:province":"Milano",
    "wof:name":"Banca Popolare Di Sondrio Scarl",
    "wof:placetype":"venue"
},
  "geometry": {"coordinates":[9.104414,45.459557],"type":"Point"}
}