{
  "type": "Feature",
  "properties": {
    "addr:full":"10098 Rivoli Cascine vica Torino 10098",
    "addr:postcode":"10098;10098",
    "iso:country":"IT",
    "sg:address":"10098 Rivoli",
    "sg:city":"Cascine vica",
    "sg:orig_category":"Impiantistica E Prodotti Tecnologici Per Edilizia. Elettrotecnica Industriale, Prodotti E Apparecchiature. Elettrotecnica Professionale E Di Consumo",
    "sg:phone":"+39 011 958 8231",
    "sg:postcode":"10098",
    "sg:province":"Torino",
    "sg:website":"http://www.colderitalia.com",
    "wof:name":"Colder Italia Srl",
    "wof:placetype":"venue"
},
  "geometry": {"coordinates":[7.546569,45.061653],"type":"Point"}
}