{
  "type": "Feature",
  "properties": {
    "addr:full":"Via I\u00b0 Maggio 18 40057 Quarto Inferiore Quarto Inferiore Bologna 40057",
    "addr:housenumber":"18",
    "addr:postcode":"40057;40057",
    "addr:street":"Via I\u00b0 Maggio;Inferiore;Inferiore",
    "iso:country":"IT",
    "sg:address":"Via I\u00b0 Maggio 18 40057 Quarto Inferiore",
    "sg:city":"Quarto Inferiore",
    "sg:classifiers":[
        {
            "category":"Manufacturing",
            "subcategory":"Petroleum Products",
            "type":"Manufacturing & Wholesale Goods"
        }
    ],
    "sg:phone":"+39 051 768124",
    "sg:postcode":"40057",
    "sg:province":"Bologna",
    "sg:tags":[
        "train",
        "tanned",
        "chamois",
        "oil"
    ],
    "sg:website":"www.compel-bo.com",
    "wof:name":"Compel Sas",
    "wof:placetype":"venue"
},
  "geometry": {"coordinates":[11.414498,44.532661],"type":"Point"}
}