{
  "type": "Feature",
  "properties": {
    "iso:country":"IT",
    "sg:address":"Viale Monza 259; Milano; 20126",
    "sg:city":"Milano",
    "sg:classifiers":[
        {
            "category":"Banks & Credit Unions",
            "subcategory":"Bank",
            "type":"Services"
        }
    ],
    "sg:phone":"+39 02 257 1147",
    "sg:postcode":"20126",
    "sg:province":"Milano",
    "wof:name":"Banca Agricola Milanese Spa",
    "wof:placetype":"venue"
},
  "geometry": {"coordinates":[9.224305,45.511692],"type":"Point"}
}