{
  "type": "Feature",
  "properties": {
    "addr:full":"Loc Tre Fontane 24034 Cisano Bergamasco Cisano Bergamasco Bergamo 24034",
    "addr:postcode":"24034;24034",
    "addr:street":"Loc Tre Fontane",
    "iso:country":"IT",
    "sg:address":"Loc Tre Fontane 24034 Cisano Bergamasco",
    "sg:city":"Cisano Bergamasco",
    "sg:classifiers":[
        {
            "category":"Retail",
            "subcategory":"Auto Repair",
            "type":"Services"
        }
    ],
    "sg:phone":"+39 035 787833",
    "sg:postcode":"24034",
    "sg:province":"Bergamo",
    "sg:tags":[
        "machine",
        "abrasive",
        "cut-off"
    ],
    "sg:website":"www.imetsaws.com",
    "wof:name":"Imet Spa",
    "wof:placetype":"venue"
},
  "geometry": {"coordinates":[9.669952,45.694904],"type":"Point"}
}