{
  "type": "Feature",
  "properties": {
    "iso:country":"IT",
    "sg:address":"10056 Oulx",
    "sg:city":"Oulx",
    "sg:orig_category":"Alberghi E Strutture Extra Alberghiere. Ospedali E Servizi Sanitari",
    "sg:phone":"+39 0122 851545",
    "sg:postcode":"10056",
    "sg:province":"Torino",
    "wof:name":"Casa Formazione Cristiana",
    "wof:placetype":"venue"
},
  "geometry": {"coordinates":[6.784796,45.041775],"type":"Point"}
}