{
  "type": "Feature",
  "properties": {
    "addr:full":"9, Via Quartiere Dell'industria 30032 Fiesso D'artico Venezia 30032",
    "addr:postcode":"30032;30032",
    "addr:street":"Via Quartiere Dell'Industria",
    "iso:country":"IT",
    "sg:address":"9, Via Quartiere Dell'industria 30032 Fiesso D'artico",
    "sg:classifiers":[
        {
            "category":"Personal",
            "subcategory":"Shoe Repair & Shine",
            "type":"Services"
        }
    ],
    "sg:phone":"+39 049 980 1540",
    "sg:postcode":"30032",
    "sg:province":"Venezia",
    "sg:tags":[
        "leather"
    ],
    "wof:name":"Calzaturificio Maripe' S.p.a.",
    "wof:placetype":"venue"
},
  "geometry": {"coordinates":[12.016694,45.422367],"type":"Point"}
}