{
  "type": "Feature",
  "properties": {
    "addr:full":"Via Busche 51 31020 Sernaglia Della Battaglia Sernaglia della Battaglia Treviso 31020",
    "addr:housenumber":"51",
    "addr:postcode":"31020;31020",
    "addr:street":"Via Busche",
    "iso:country":"IT",
    "sg:address":"Via Busche 51 31020 Sernaglia Della Battaglia",
    "sg:city":"Sernaglia della Battaglia",
    "sg:classifiers":[
        {
            "category":"Manufacturing",
            "subcategory":"Furniture",
            "type":"Manufacturing & Wholesale Goods"
        }
    ],
    "sg:phone":"+39 0438 966218",
    "sg:postcode":"31020",
    "sg:province":"Treviso",
    "sg:tags":[
        "bedroom"
    ],
    "sg:website":"www.mariovillanova.it",
    "wof:name":"Mobilificio Cav. Mario Villanova & C. Srl",
    "wof:placetype":"venue"
},
  "geometry": {"coordinates":[12.124498,45.878498],"type":"Point"}
}