{
  "type": "Feature",
  "properties": {
    "iso:country":"IT",
    "sg:address":"3, Via Patti 00132 Roma",
    "sg:city":"Roma",
    "sg:classifiers":[
        {
            "category":"Utilities",
            "subcategory":"Telephone",
            "type":"Services"
        }
    ],
    "sg:phone":"+39 39062072272",
    "sg:postcode":"00132",
    "sg:province":"Roma",
    "sg:tags":[
        "telecommunication"
    ],
    "wof:name":"Tlc Italia Srl",
    "wof:placetype":"venue"
},
  "geometry": {"coordinates":[12.685188,41.861668],"type":"Point"}
}