{
  "type": "Feature",
  "properties": {
    "addr:full":"20145 Milano Milano Milano 20145",
    "addr:postcode":"20145;20145",
    "iso:country":"IT",
    "sg:address":"20145 Milano",
    "sg:city":"Milano",
    "sg:orig_category":"Prodotti Chimici Secondari. Prodotti Cosmetici E Da Toeletta",
    "sg:phone":"+39 02 481 4440",
    "sg:postcode":"20145",
    "sg:province":"Milano",
    "wof:name":"Atron Italiana Srl",
    "wof:placetype":"venue"
},
  "geometry": {"coordinates":[9.158411026,45.4743995667],"type":"Point"}
}