{
  "type": "Feature",
  "properties": {
    "iso:country":"IT",
    "sg:address":"Via C. Battisti 20 36042 Breganze",
    "sg:city":"Breganze",
    "sg:classifiers":[
        {
            "category":"Personal",
            "subcategory":"Day Spa",
            "type":"Services"
        }
    ],
    "sg:phone":"+39 0445 874462",
    "sg:postcode":"36042",
    "sg:province":"Vicenza",
    "sg:tags":[
        "denim"
    ],
    "wof:name":"Didone S.r.l.",
    "wof:placetype":"venue"
},
  "geometry": {"coordinates":[11.540307,45.545906],"type":"Point"}
}