{
  "type": "Feature",
  "properties": {
    "addr:full":"9, Via Provinciale 55064 Pescaglia Pescaglia Lucca 55064",
    "addr:postcode":"55064;55064",
    "addr:street":"Via Provinciale",
    "iso:country":"IT",
    "sg:address":"9, Via Provinciale 55064 Pescaglia",
    "sg:city":"Pescaglia",
    "sg:classifiers":[
        {
            "category":"Personal",
            "subcategory":"Shoe Repair & Shine",
            "type":"Services"
        }
    ],
    "sg:phone":"+39 39058332061",
    "sg:postcode":"55064",
    "sg:province":"Lucca",
    "sg:tags":[
        "leather"
    ],
    "wof:name":"Rontani Industria Materie Plastiche",
    "wof:placetype":"venue"
},
  "geometry": {"coordinates":[10.420444,43.955536],"type":"Point"}
}