{
  "type": "Feature",
  "properties": {
    "iso:country":"IT",
    "sg:address":"37014 Castelnuovo Del Garda",
    "sg:city":"Castelnuovo del Garda",
    "sg:orig_category":"Macchine Ed Impianti Per Edilizia E Lavori Pubblici",
    "sg:phone":"+39 045 759 6337",
    "sg:postcode":"37014",
    "sg:province":"Verona",
    "wof:name":"Molesini Alberto Snc",
    "wof:placetype":"venue"
},
  "geometry": {"coordinates":[10.833522,45.461769],"type":"Point"}
}