{
  "type": "Feature",
  "properties": {
    "addr:full":"95032 Piano Tavola Piano tavola Catania 95032",
    "addr:postcode":"95032;95032",
    "iso:country":"IT",
    "sg:address":"95032 Piano Tavola",
    "sg:city":"Piano tavola",
    "sg:orig_category":"Prodotti E Manufatti In Materie Plastiche",
    "sg:phone":"+39 095 713 2528",
    "sg:postcode":"95032",
    "sg:province":"Catania",
    "wof:name":"Landucci Corinna Elvira",
    "wof:placetype":"venue"
},
  "geometry": {"coordinates":[14.9744710922,37.5376853943],"type":"Point"}
}