{
  "type": "Feature",
  "properties": {
    "iso:country":"IT",
    "sg:address":"60020 Agugliano",
    "sg:city":"Agugliano",
    "sg:orig_category":"Macchine Agricole - Produzione",
    "sg:phone":"+39 0444 891281",
    "sg:postcode":"60020",
    "sg:province":"Ancona",
    "wof:name":"Ar.co.m. Snc",
    "wof:placetype":"venue"
},
  "geometry": {"coordinates":[13.390481,43.544537],"type":"Point"}
}