{
  "type": "Feature",
  "properties": {
    "iso:country":"IT",
    "sg:address":"1028, Via Salaria 00138 Roma",
    "sg:city":"Roma",
    "sg:classifiers":[
        {
            "category":"Autos & Motor Vehicles",
            "subcategory":"Boat Sales",
            "type":"Retail Goods"
        }
    ],
    "sg:phone":"+39 390 688 201",
    "sg:postcode":"00138",
    "sg:province":"Roma",
    "wof:name":"Vitrociset Spa",
    "wof:placetype":"venue"
},
  "geometry": {"coordinates":[12.505915,41.954369],"type":"Point"}
}