{
  "type": "Feature",
  "properties": {
    "iso:country":"IT",
    "sg:address":"Vle Gandhi 25 10051 Avigliana",
    "sg:city":"Avigliana",
    "sg:classifiers":[
        {
            "category":"Wholesale",
            "subcategory":"Motor Vehicles",
            "type":"Manufacturing & Wholesale Goods"
        }
    ],
    "sg:phone":"+39 011 932 7477",
    "sg:postcode":"10051",
    "sg:province":"Torino",
    "sg:tags":[
        "tube",
        "inner",
        "tyre"
    ],
    "wof:name":"Subalpina Gomme Srl",
    "wof:placetype":"venue"
},
  "geometry": {"coordinates":[7.413602,45.086479],"type":"Point"}
}