{
  "type": "Feature",
  "properties": {
    "addr:full":"14/a, Via Pervilli Cesare 42100 Reggio Emilia Reggio Nell'Emilia 42100",
    "addr:housenumber":"14 / a",
    "addr:postcode":"42100;42100",
    "addr:street":"Via Pervilli Cesare",
    "iso:country":"IT",
    "sg:address":"14/a, Via Pervilli Cesare 42100 Reggio Emilia",
    "sg:classifiers":[
        {
            "category":"Manufacturing",
            "subcategory":"Metals",
            "type":"Manufacturing & Wholesale Goods"
        }
    ],
    "sg:phone":"+39 0522 516946",
    "sg:postcode":"42100",
    "sg:province":"Reggio Nell'Emilia",
    "sg:tags":[
        "processing"
    ],
    "wof:name":"Daver (s.r.l.)",
    "wof:placetype":"venue"
},
  "geometry": {"coordinates":[10.6467504501,44.739200592],"type":"Point"}
}