{
  "type": "Feature",
  "properties": {
    "iso:country":"IT",
    "sg:address":"50136 Firenze",
    "sg:city":"Firenze",
    "sg:orig_category":"Agenzie D'affari E Servizi Commerciali",
    "sg:postcode":"50136",
    "sg:province":"Firenze",
    "wof:name":"Nanni Roberta",
    "wof:placetype":"venue"
},
  "geometry": {"coordinates":[11.283442,43.769108],"type":"Point"}
}