{
  "type": "Feature",
  "properties": {
    "addr:full":"33048 San Giovanni Al Natisone San Giovanni al Natisone Udine 33048",
    "addr:postcode":"33048;33048",
    "iso:country":"IT",
    "sg:address":"33048 San Giovanni Al Natisone",
    "sg:city":"San Giovanni al Natisone",
    "sg:orig_category":"Macchine Utensili E Impianti",
    "sg:phone":"+39 0432 756137",
    "sg:postcode":"33048",
    "sg:province":"Udine",
    "wof:name":"Iurigh Stefano",
    "wof:placetype":"venue"
},
  "geometry": {"coordinates":[13.393488,45.971928],"type":"Point"}
}