{
  "type": "Feature",
  "properties": {
    "iso:country":"IT",
    "sg:address":"20097 San Donato Milanese",
    "sg:city":"San Donato Milanese",
    "sg:classifiers":[
        {
            "category":"Health Services",
            "subcategory":"Health Practitioner",
            "type":"Services"
        }
    ],
    "sg:phone":"+39 02 527 0818",
    "sg:postcode":"20097",
    "sg:province":"Milano",
    "sg:tags":[
        "medici"
    ],
    "wof:name":"Tempera Roberto",
    "wof:placetype":"venue"
},
  "geometry": {"coordinates":[9.2674064636,45.4127693176],"type":"Point"}
}