{
  "type": "Feature",
  "properties": {
    "iso:country":"IT",
    "sg:address":"31020 Villorba",
    "sg:city":"Villorba",
    "sg:orig_category":"Legno E Semilavorati",
    "sg:phone":"+39 0422 918258",
    "sg:postcode":"31020",
    "sg:province":"Treviso",
    "wof:name":"Mussi Bianchi Fossati (s.r.l.)",
    "wof:placetype":"venue"
},
  "geometry": {"coordinates":[12.254459,45.734833],"type":"Point"}
}