{
  "type": "Feature",
  "properties": {
    "addr:full":"00139 Roma Roma Roma 00139",
    "addr:postcode":"00139;00139",
    "iso:country":"IT",
    "sg:address":"00139 Roma",
    "sg:city":"Roma",
    "sg:orig_category":"Forniture Per Agricoltura E Zootecnia. Animali Domestici",
    "sg:phone":"+39 06 881 9215",
    "sg:postcode":"00139",
    "sg:province":"Roma",
    "wof:name":"La Mensa Degli Animali",
    "wof:placetype":"venue"
},
  "geometry": {"coordinates":[12.5221910477,41.964805603],"type":"Point"}
}