{
  "type": "Feature",
  "properties": {
    "iso:country":"IT",
    "sg:address":"66100 Chieti",
    "sg:city":"Chieti",
    "sg:orig_category":"Elettrodomestici. Elettronica Professionale E Di Consumo. Arredi Ed Attrezzature Per Attivita' Commerciali Ed Artigianali. Macchine, Strumenti Ed Apparecchi Per Attivita' Industriali",
    "sg:phone":"+39 0871 562508",
    "sg:postcode":"66100",
    "sg:province":"Chieti",
    "wof:name":"Di Michele Adriano & C. Snc",
    "wof:placetype":"venue"
},
  "geometry": {"coordinates":[14.141932,42.367027],"type":"Point"}
}