{
  "type": "Feature",
  "properties": {
    "iso:country":"IT",
    "sg:address":"Contrada Lupini Cs 46 74019 Palagiano",
    "sg:city":"Palagiano",
    "sg:classifiers":[
        {
            "category":"Wholesale",
            "subcategory":"Drugs",
            "type":"Manufacturing & Wholesale Goods"
        }
    ],
    "sg:phone":"+39 099 888 5353",
    "sg:postcode":"74019",
    "sg:province":"Taranto",
    "sg:tags":[
        "chemical",
        "pharmaceutical"
    ],
    "wof:name":"Lubritalia S.p.a.",
    "wof:placetype":"venue"
},
  "geometry": {"coordinates":[17.240009,40.469238],"type":"Point"}
}