{
  "type": "Feature",
  "properties": {
    "iso:country":"IT",
    "sg:address":"09013 Carbonia",
    "sg:city":"Carbonia",
    "sg:orig_category":"Serramenti Ed Infissi Alluminio",
    "sg:phone":"+39 0781 671572",
    "sg:postcode":"09013",
    "sg:province":"Carbonia-Iglesias",
    "wof:name":"M.a.p. Legn. All. Srl",
    "wof:placetype":"venue"
},
  "geometry": {"coordinates":[8.540161,39.157639],"type":"Point"}
}