{
  "type": "Feature",
  "properties": {
    "addr:full":"20032 Cormano Cormano Milano 20032",
    "addr:postcode":"20032;20032",
    "iso:country":"IT",
    "sg:address":"20032 Cormano",
    "sg:city":"Cormano",
    "sg:orig_category":"Accessori Moda D'abbigliamento. Forniture Per Abbigliamento E Pelletterie",
    "sg:phone":"+39 02 6650 0171",
    "sg:postcode":"20032",
    "sg:province":"Milano",
    "wof:name":"Andrea Bilics & C. Srl",
    "wof:placetype":"venue"
},
  "geometry": {"coordinates":[9.181299,45.542328],"type":"Point"}
}