{
  "type": "Feature",
  "properties": {
    "addr:full":"20134 Milano Milano Milano 20134",
    "addr:postcode":"20134;20134",
    "iso:country":"IT",
    "sg:address":"20134 Milano",
    "sg:city":"Milano",
    "sg:orig_category":"Carta, Cartone E Prodotti Primari",
    "sg:phone":"+39 02 7000 1625",
    "sg:postcode":"20134",
    "sg:province":"Milano",
    "wof:name":"C.a.d.a. Cart (s.r.l.)",
    "wof:placetype":"venue"
},
  "geometry": {"coordinates":[9.251833,45.476692],"type":"Point"}
}