{
  "type": "Feature",
  "properties": {
    "iso:country":"IT",
    "sg:address":"40137 Bologna",
    "sg:city":"Bologna",
    "sg:orig_category":"Legno E Semilavorati. Macchine E Forniture Per Arredamento E Industria Del Legno. Hobbistica",
    "sg:phone":"+39 051 470898",
    "sg:postcode":"40137",
    "sg:province":"Bologna",
    "wof:name":"Impresa Edile Maurizzi Alessandro   Colorline",
    "wof:placetype":"venue"
},
  "geometry": {"coordinates":[10.980762,44.132687],"type":"Point"}
}