{
  "type": "Feature",
  "properties": {
    "addr:full":"10144 Torino Torino Torino 10144",
    "addr:postcode":"10144;10144",
    "iso:country":"IT",
    "sg:address":"10144 Torino",
    "sg:city":"Torino",
    "sg:orig_category":"Pubblica Amministrazione",
    "sg:phone":"+39 011 437 0311",
    "sg:postcode":"10144",
    "sg:province":"Torino",
    "wof:name":"Commissione Tributaria Regionale",
    "wof:placetype":"venue"
},
  "geometry": {"coordinates":[7.6622982025,45.0843238831],"type":"Point"}
}