{
  "type": "Feature",
  "properties": {
    "addr:full":"25, Via I Maggio 21040 Origgio Origgio Varese 21040",
    "addr:postcode":"21040;21040",
    "addr:street":"Via I Maggio",
    "iso:country":"IT",
    "sg:address":"25, Via I Maggio 21040 Origgio",
    "sg:city":"Origgio",
    "sg:classifiers":[
        {
            "category":"Manufacturing",
            "subcategory":"Paper Products",
            "type":"Manufacturing & Wholesale Goods"
        }
    ],
    "sg:phone":"+39 02 9673 0302",
    "sg:postcode":"21040",
    "sg:province":"Varese",
    "sg:tags":[
        "cardboard"
    ],
    "wof:name":"Cartotecnica Di Origgio (s.n.c.)",
    "wof:placetype":"venue"
},
  "geometry": {"coordinates":[8.8263845444,45.8176040649],"type":"Point"}
}