{
  "type": "Feature",
  "properties": {
    "iso:country":"IT",
    "sg:address":"Ss 77, Km. 74,500 62029 Tolentino",
    "sg:city":"Tolentino",
    "sg:orig_category":"Car Seat Furs",
    "sg:phone":"+39 0733 9091",
    "sg:postcode":"62029",
    "sg:province":"Macerata",
    "sg:website":"www.poltronafrau.it",
    "wof:name":"Poltrona Frau Srl",
    "wof:placetype":"venue"
},
  "geometry": {"coordinates":[13.456262,43.300747],"type":"Point"}
}