{
  "type": "Feature",
  "properties": {
    "addr:full":"00186 Roma Roma Roma 00186",
    "addr:postcode":"00186;00186",
    "iso:country":"IT",
    "sg:address":"00186 Roma",
    "sg:city":"Roma",
    "sg:classifiers":[
        {
            "category":"Communications",
            "type":"Services"
        }
    ],
    "sg:phone":"+39 06 686 5557",
    "sg:postcode":"00186",
    "sg:province":"Roma",
    "sg:tags":[
        "perle"
    ],
    "sg:website":"http://www.diamanti.it",
    "wof:name":"Carlo Paolillo & C.",
    "wof:placetype":"venue"
},
  "geometry": {"coordinates":[12.4751138687,41.9025840759],"type":"Point"}
}