{
  "type": "Feature",
  "properties": {
    "addr:full":"5, Via Strada Vecchia Per Rivignano 33050 Teor Rivignano Udine 33050",
    "addr:postcode":"33050;33050",
    "addr:street":"Via Strada Vecchia Per Rivignano",
    "iso:country":"IT",
    "sg:address":"5, Via Strada Vecchia Per Rivignano 33050 Teor",
    "sg:city":"Rivignano",
    "sg:classifiers":[
        {
            "category":"Shopping",
            "type":"Retail Goods"
        }
    ],
    "sg:phone":"+39 0432 775436",
    "sg:postcode":"33050",
    "sg:province":"Udine",
    "sg:tags":[
        "finished",
        "-",
        "metallic"
    ],
    "wof:name":"Mariotti S.r.l.",
    "wof:placetype":"venue"
},
  "geometry": {"coordinates":[13.0510578156,45.8603630066],"type":"Point"}
}