{
  "type": "Feature",
  "properties": {
    "iso:country":"IT",
    "sg:address":"30036 Santa Maria Di Sala",
    "sg:city":"Santa Maria di Sala",
    "sg:classifiers":[
        {
            "category":"Sports & Exercise",
            "subcategory":"Sports Center",
            "type":"Entertainment"
        }
    ],
    "sg:phone":"+39 041 578 0472",
    "sg:postcode":"30036",
    "sg:province":"Venezia",
    "sg:tags":[
        "knitwear",
        "furs",
        "clothing",
        "article",
        "supply"
    ],
    "wof:name":"Mercerie Luciano Di Favarotto Sebastiano",
    "wof:placetype":"venue"
},
  "geometry": {"coordinates":[12.045521,45.525475],"type":"Point"}
}