{
  "type": "Feature",
  "properties": {
    "iso:country":"IT",
    "sg:address":"Loc Coselli Zona Inustriale 55060 Guamo",
    "sg:city":"Guamo",
    "sg:classifiers":[
        {
            "category":"Food & Beverages",
            "subcategory":"Specialty",
            "type":"Retail Goods"
        }
    ],
    "sg:phone":"+39 0583 403400",
    "sg:postcode":"55060",
    "sg:province":"Lucca",
    "sg:tags":[
        "olive-oil"
    ],
    "wof:name":"Frediani & Del Greco Spa",
    "wof:placetype":"venue"
},
  "geometry": {"coordinates":[10.507994,43.843014],"type":"Point"}
}