{
  "type": "Feature",
  "properties": {
    "iso:country":"IT",
    "sg:address":"48022 Lugo",
    "sg:city":"Lugo",
    "sg:orig_category":"Valvole E Apparecchiature Di Misura. Minuterie Metalliche E Ferramenta. Forniture Per Attivita' Industriali",
    "sg:phone":"+39 0545 901001",
    "sg:postcode":"48022",
    "sg:province":"Ravenna",
    "sg:website":"http://www.bucchi.it",
    "wof:name":"Bucchi Srl",
    "wof:placetype":"venue"
},
  "geometry": {"coordinates":[11.897842,44.435768],"type":"Point"}
}