{
  "type": "Feature",
  "properties": {
    "addr:full":"46045 Marmirolo Marmirolo Mantova 46045",
    "addr:postcode":"46045;46045",
    "iso:country":"IT",
    "sg:address":"46045 Marmirolo",
    "sg:city":"Marmirolo",
    "sg:orig_category":"Bagno - Accessori E Mobili",
    "sg:phone":"+39 0376 466350",
    "sg:postcode":"46045",
    "sg:province":"Mantova",
    "wof:name":"Esagono Di Treccani & C. Snc",
    "wof:placetype":"venue"
},
  "geometry": {"coordinates":[10.759972,45.211163],"type":"Point"}
}