{
  "type": "Feature",
  "properties": {
    "iso:country":"IT",
    "sg:address":"90049 Terrasini",
    "sg:city":"Terrasini",
    "sg:orig_category":"Servizi Per Lo Sport E Il Tempo Libero. Servizi Al Turismo",
    "sg:phone":"+39 091 869 5061",
    "sg:postcode":"90049",
    "sg:province":"Palermo",
    "wof:name":"Zoo Fattoria",
    "wof:placetype":"venue"
},
  "geometry": {"coordinates":[13.087553,38.101803],"type":"Point"}
}