{
  "type": "Feature",
  "properties": {
    "addr:full":"70124 Bari Bari Bari 70124",
    "addr:postcode":"70124;70124",
    "iso:country":"IT",
    "sg:address":"70124 Bari",
    "sg:city":"Bari",
    "sg:orig_category":"Elettronica Professionale E Di Consumo. Automazione E Macchine Per Ufficio",
    "sg:phone":"+39 080 542 8021",
    "sg:postcode":"70124",
    "sg:province":"Bari",
    "wof:name":"Sitrade Italia (s.r.l.)",
    "wof:placetype":"venue"
},
  "geometry": {"coordinates":[16.864294,41.109867],"type":"Point"}
}