{
  "type": "Feature",
  "properties": {
    "iso:country":"IT",
    "sg:address":"74, Via Palermo 59013 Montemurlo",
    "sg:city":"Montemurlo",
    "sg:classifiers":[
        {
            "category":"Shopping",
            "subcategory":"Clothing, Apparel, & Fashions",
            "type":"Retail Goods"
        }
    ],
    "sg:phone":"+39 0574 682274",
    "sg:postcode":"59013",
    "sg:province":"Prato",
    "sg:tags":[
        "clothes"
    ],
    "wof:name":"Maglificio Duerre (s.a.s.)",
    "wof:placetype":"venue"
},
  "geometry": {"coordinates":[11.02552,43.921841],"type":"Point"}
}