{
  "type": "Feature",
  "properties": {
    "addr:full":"Via Buscarino 25030 Coccaglio Coccaglio Brescia 25030",
    "addr:postcode":"25030;25030",
    "addr:street":"Via Buscarino",
    "iso:country":"IT",
    "sg:address":"Via Buscarino 25030 Coccaglio",
    "sg:city":"Coccaglio",
    "sg:classifiers":[
        {
            "category":"Farming",
            "subcategory":"Livestock Farm",
            "type":"Manufacturing & Wholesale Goods"
        }
    ],
    "sg:phone":"+39 030 770 0968",
    "sg:postcode":"25030",
    "sg:province":"Brescia",
    "sg:tags":[
        "agriculture"
    ],
    "wof:name":"Lini Import (s.r.l.)",
    "wof:placetype":"venue"
},
  "geometry": {"coordinates":[9.976575,45.567699],"type":"Point"}
}