{
  "type": "Feature",
  "properties": {
    "iso:country":"IT",
    "sg:address":"20084 Lacchiarella",
    "sg:city":"Lacchiarella",
    "sg:orig_category":"Articoli Medico-sanitari Ed Ortopedici. Impianti, Attrezzature E Forniture Sanitarie Ed Ospedaliere",
    "sg:phone":"+39 02 9003 3045",
    "sg:postcode":"20084",
    "sg:province":"Milano",
    "wof:name":"Corman Srl",
    "wof:placetype":"venue"
},
  "geometry": {"coordinates":[9.209348,45.460899],"type":"Point"}
}