{
  "type": "Feature",
  "properties": {
    "addr:full":"88046 Lamezia Terme Lamezia Terme Catanzaro 88046",
    "addr:postcode":"88046;88046",
    "iso:country":"IT",
    "sg:address":"88046 Lamezia Terme",
    "sg:city":"Lamezia Terme",
    "sg:orig_category":"Forniture Per Edilizia E Lavori Pubblici",
    "sg:phone":"+39 0968 209154",
    "sg:postcode":"88046",
    "sg:province":"Catanzaro",
    "wof:name":"Gecoprem Srl",
    "wof:placetype":"venue"
},
  "geometry": {"coordinates":[16.2757511139,38.9336204529],"type":"Point"}
}