{
  "type": "Feature",
  "properties": {
    "iso:country":"IT",
    "sg:address":"13018 Valduggia",
    "sg:city":"Valduggia",
    "sg:orig_category":"Valvole E Apparecchiature Di Misura",
    "sg:phone":"+39 0163 47427",
    "sg:postcode":"13018",
    "sg:province":"Vercelli",
    "wof:name":"Astori Rubinetterie Spa",
    "wof:placetype":"venue"
},
  "geometry": {"coordinates":[8.347718,45.722725],"type":"Point"}
}