{
  "type": "Feature",
  "properties": {
    "iso:country":"IT",
    "sg:address":"60019 Marzocca",
    "sg:city":"Marzocca",
    "sg:orig_category":"Ospedali E Servizi Sanitari. Centri Di Estetica E Cosmesi E Servizi",
    "sg:phone":"+39 071 69264",
    "sg:postcode":"60019",
    "sg:province":"Ancona",
    "wof:name":"Studio Fisioterapico Pegaso",
    "wof:placetype":"venue"
},
  "geometry": {"coordinates":[13.288907,43.67485],"type":"Point"}
}