{
  "type": "Feature",
  "properties": {
    "iso:country":"IT",
    "sg:address":"111, Via Trento 38017 Mezzolombardo",
    "sg:city":"Mezzolombardo",
    "sg:classifiers":[
        {
            "category":"Shopping",
            "subcategory":"Crafts & Fabrics",
            "type":"Retail Goods"
        }
    ],
    "sg:phone":"+39 0461 602090",
    "sg:postcode":"38017",
    "sg:province":"Trento",
    "wof:name":"Rotaltes (s.p.a.)",
    "wof:placetype":"venue"
},
  "geometry": {"coordinates":[11.1004333496,46.2007064819],"type":"Point"}
}