{
  "type": "Feature",
  "properties": {
    "iso:country":"IT",
    "sg:address":"Via Giacomo Leopardi 39 22070 Grandate",
    "sg:city":"Grandate",
    "sg:classifiers":[
        {
            "category":"Manufacturing",
            "subcategory":"Chemicals & Compounds",
            "type":"Manufacturing & Wholesale Goods"
        }
    ],
    "sg:phone":"+39 031 564550",
    "sg:postcode":"22070",
    "sg:province":"Como",
    "sg:tags":[
        "base"
    ],
    "sg:website":"www.borghispa.it",
    "wof:name":"Borghi Spa",
    "wof:placetype":"venue"
},
  "geometry": {"coordinates":[9.058579,45.768124],"type":"Point"}
}