{
  "type": "Feature",
  "properties": {
    "iso:country":"IT",
    "sg:address":"31040 Segusino",
    "sg:city":"Segusino",
    "sg:orig_category":"Occhiali - Produzione E Ingrosso",
    "sg:phone":"+39 0423 979354",
    "sg:postcode":"31040",
    "sg:province":"Treviso",
    "wof:name":"F.g.m. Snc Di Furlan M. & C.",
    "wof:placetype":"venue"
},
  "geometry": {"coordinates":[11.95674,45.91798],"type":"Point"}
}