{
  "type": "Feature",
  "properties": {
    "iso:country":"IT",
    "sg:address":"31100 San Pelaio",
    "sg:orig_category":"Macchine, Impianti Ed Attrezzature Per Industria Alimentare E Bevande. Macchine, Impianti Ed Attrezzature Industria Chimica",
    "sg:phone":"+39 0422 300311",
    "sg:postcode":"31100",
    "sg:province":"Treviso",
    "wof:name":"Visentin Antenore Di Visentin Pieralfonso",
    "wof:placetype":"venue"
},
  "geometry": {"coordinates":[12.235473,45.694874],"type":"Point"}
}