{
  "type": "Feature",
  "properties": {
    "iso:country":"IT",
    "sg:address":"36030 Caldogno",
    "sg:city":"Caldogno",
    "sg:orig_category":"Servizi E Lavori Per Abbigliamento E Pelletterie. Servizi Ausiliari Di Sorveglianza, Manutenzione E Pulizia",
    "sg:phone":"+39 0444 585786",
    "sg:postcode":"36030",
    "sg:province":"Vicenza",
    "wof:name":"Lavanderia Edelweiss Di Dal Bello Giovanni & C. Sas",
    "wof:placetype":"venue"
},
  "geometry": {"coordinates":[11.522984,45.550407],"type":"Point"}
}