{
  "type": "Feature",
  "properties": {
    "iso:country":"IT",
    "sg:address":"40012 Calderara Di Reno",
    "sg:city":"Calderara di Reno",
    "sg:orig_category":"Carte Plastiche, Magnetiche E Smart - Badges",
    "sg:phone":"+39 051 646 5011",
    "sg:postcode":"40012",
    "sg:province":"Bologna",
    "sg:website":"http://www.cimitaly.it",
    "wof:name":"Cim Spa",
    "wof:placetype":"venue"
},
  "geometry": {"coordinates":[11.297067,44.544659],"type":"Point"}
}