{
  "type": "Feature",
  "properties": {
    "iso:country":"IT",
    "sg:address":"75, Via Cavecchia 47023 Cesena",
    "sg:city":"Cesena",
    "sg:classifiers":[
        {
            "category":"Farming",
            "subcategory":"Livestock Farm",
            "type":"Manufacturing & Wholesale Goods"
        }
    ],
    "sg:phone":"+39 39054758166",
    "sg:postcode":"47023",
    "sg:province":"Forl\u00ec-Cesena",
    "sg:tags":[
        "agriculture"
    ],
    "wof:name":"Co.p.r.a. Soc.coop. A R.l.",
    "wof:placetype":"venue"
},
  "geometry": {"coordinates":[12.238655,44.138969],"type":"Point"}
}