{
  "type": "Feature",
  "properties": {
    "addr:full":"20093 Cologno Monzese Cologno Monzese Milano 20093",
    "addr:postcode":"20093;20093",
    "iso:country":"IT",
    "sg:address":"20093 Cologno Monzese",
    "sg:city":"Cologno Monzese",
    "sg:orig_category":"Carta, Cartone E Prodotti Primari",
    "sg:phone":"+39 02 2730 3636",
    "sg:postcode":"20093",
    "sg:province":"Milano",
    "wof:name":"Alfa Maceri S.p.a.",
    "wof:placetype":"venue"
},
  "geometry": {"coordinates":[9.267579,45.525009],"type":"Point"}
}