{
  "type": "Feature",
  "properties": {
    "iso:country":"IT",
    "sg:address":"40067 Rastignano",
    "sg:city":"Rastignano",
    "sg:orig_category":"Fotocomposizione",
    "sg:phone":"+39 051 742018",
    "sg:postcode":"40067",
    "sg:province":"Bologna",
    "wof:name":"Videocomp Snc",
    "wof:placetype":"venue"
},
  "geometry": {"coordinates":[11.3697376251,44.4627494812],"type":"Point"}
}