{
  "type": "Feature",
  "properties": {
    "addr:full":"34148 Trieste Trieste Trieste 34148",
    "addr:postcode":"34148;34148",
    "iso:country":"IT",
    "sg:address":"34148 Trieste",
    "sg:city":"Trieste",
    "sg:classifiers":[
        {
            "category":"Health Services",
            "subcategory":"Health Practitioner",
            "type":"Services"
        }
    ],
    "sg:phone":"+39 040 830450",
    "sg:postcode":"34148",
    "sg:province":"Trieste",
    "sg:tags":[
        "medici"
    ],
    "wof:name":"Riccardi Barbara",
    "wof:placetype":"venue"
},
  "geometry": {"coordinates":[13.8033952713,45.6241416931],"type":"Point"}
}