{
  "type": "Feature",
  "properties": {
    "iso:country":"IT",
    "sg:address":"Localita' Luna 2 23020 Torre Di Santa Maria",
    "sg:city":"Torre di Santa Maria",
    "sg:classifiers":[
        {
            "category":"Landmark",
            "subcategory":"City Walls",
            "type":"Public Place"
        }
    ],
    "sg:phone":"+39 0342 451558",
    "sg:postcode":"23020",
    "sg:province":"Sondrio",
    "sg:tags":[
        "raw",
        "roofing",
        "slate",
        "dressed"
    ],
    "sg:website":"www.zafa.it",
    "wof:name":"Zafa Srl",
    "wof:placetype":"venue"
},
  "geometry": {"coordinates":[9.846891,46.252312],"type":"Point"}
}