{
  "type": "Feature",
  "properties": {
    "iso:country":"IT",
    "sg:address":"00042 Anzio",
    "sg:city":"Anzio",
    "sg:orig_category":"Forniture Per Abbigliamento E Pelletterie. Impianti, Attrezzature E Forniture Sanitarie Ed Ospedaliere",
    "sg:phone":"+39 06 987 2957",
    "sg:postcode":"00042",
    "sg:province":"Roma",
    "wof:name":"Ovattificio Ro.oli.tex Srl",
    "wof:placetype":"venue"
},
  "geometry": {"coordinates":[12.6206073761,41.9959526062],"type":"Point"}
}