{
  "type": "Feature",
  "properties": {
    "addr:full":"00042 Anzio Anzio Roma 00042",
    "addr:postcode":"00042;roma 00042",
    "iso:country":"IT",
    "sg:address":"00042 Anzio",
    "sg:city":"Anzio",
    "sg:orig_category":"Arredo Cucina Ed Elettrodomestici. Elettrodomestici",
    "sg:phone":"+39 06 986 4271",
    "sg:postcode":"00042",
    "sg:province":"Roma",
    "wof:name":"Cerilli Giorgia",
    "wof:placetype":"venue"
},
  "geometry": {"coordinates":[12.632552,41.451054],"type":"Point"}
}