{
  "type": "Feature",
  "properties": {
    "iso:country":"IT",
    "sg:address":"3, Via Iv Novembre 55016 Porcari",
    "sg:city":"Porcari",
    "sg:classifiers":[
        {
            "category":"Wholesale",
            "subcategory":"Drugs",
            "type":"Manufacturing & Wholesale Goods"
        }
    ],
    "sg:phone":"+39 390 583 2901",
    "sg:postcode":"55016",
    "sg:province":"Lucca",
    "sg:tags":[
        "chemical",
        "pharmaceutical"
    ],
    "wof:name":"Baldini (s.p.a.)",
    "wof:placetype":"venue"
},
  "geometry": {"coordinates":[10.507994,43.843014],"type":"Point"}
}