{
  "type": "Feature",
  "properties": {
    "iso:country":"IT",
    "sg:address":"21, Via Strada Nuova 27029 Vigevano",
    "sg:city":"Vigevano",
    "sg:classifiers":[
        {
            "category":"Personal",
            "subcategory":"Shoe Repair & Shine",
            "type":"Services"
        }
    ],
    "sg:phone":"+39 0381 311071",
    "sg:postcode":"27029",
    "sg:province":"Pavia",
    "sg:tags":[
        "leather"
    ],
    "wof:name":"Saija Concetto",
    "wof:placetype":"venue"
},
  "geometry": {"coordinates":[8.842772,45.312359],"type":"Point"}
}