{
  "type": "Feature",
  "properties": {
    "addr:full":"25011 Calcinato Calcinato Brescia 25011",
    "addr:postcode":"25011;25011",
    "iso:country":"IT",
    "sg:address":"25011 Calcinato",
    "sg:city":"Calcinato",
    "sg:orig_category":"Servizi Culturali E Per Lo Spettacolo. Servizi Al Turismo. Acqua, Luce, Gas E Societa' Di Esercizio Pubblico",
    "sg:phone":"+39 030 963481",
    "sg:postcode":"25011",
    "sg:province":"Brescia",
    "wof:name":"Biblioteca Comunale",
    "wof:placetype":"venue"
},
  "geometry": {"coordinates":[10.395603,45.458496],"type":"Point"}
}