{
  "type": "Feature",
  "properties": {
    "addr:full":"20095 Cusano Milanino Cusano Milanino Milano 20095",
    "addr:postcode":"20095;20095",
    "iso:country":"IT",
    "sg:address":"20095 Cusano Milanino",
    "sg:city":"Cusano Milanino",
    "sg:orig_category":"Prodotti Alimentari",
    "sg:phone":"+39 02 619 8228",
    "sg:postcode":"20095",
    "sg:province":"Milano",
    "wof:name":"Maino Vittoria",
    "wof:placetype":"venue"
},
  "geometry": {"coordinates":[9.1778860092,45.556022644],"type":"Point"}
}