{
  "type": "Feature",
  "properties": {
    "iso:country":"IT",
    "sg:address":"16123 Genova",
    "sg:city":"Genova",
    "sg:orig_category":"Centri Di Estetica E Cosmesi E Servizi",
    "sg:phone":"+39 010 246 3481",
    "sg:postcode":"16123",
    "sg:province":"Genova",
    "wof:name":"Piaggio Riccardo",
    "wof:placetype":"venue"
},
  "geometry": {"coordinates":[8.931434,44.408623],"type":"Point"}
}