{
  "type": "Feature",
  "properties": {
    "iso:country":"IT",
    "sg:address":"85024 Lavello",
    "sg:city":"Lavello",
    "sg:orig_category":"Servizi Ausiliari Dei Mezzi Di Trasporto",
    "sg:phone":"+39 0972 88592",
    "sg:postcode":"85024",
    "sg:province":"Potenza",
    "sg:website":"http://www.carrozzeriamilanese.it",
    "wof:name":"Carrozzeria Milanese",
    "wof:placetype":"venue"
},
  "geometry": {"coordinates":[15.840773,41.065815],"type":"Point"}
}