{
  "type": "Feature",
  "properties": {
    "iso:country":"IT",
    "sg:address":"56011 Calci",
    "sg:city":"Calci",
    "sg:orig_category":"Arte Ed Artigianato Artistico",
    "sg:phone":"+39 050 938543",
    "sg:postcode":"56011",
    "sg:province":"Pisa",
    "wof:name":"O.c.e.d. Di Destri Egisto",
    "wof:placetype":"venue"
},
  "geometry": {"coordinates":[10.512646,43.718849],"type":"Point"}
}