{
  "type": "Feature",
  "properties": {
    "iso:country":"IT",
    "sg:address":"09076 Sedilo",
    "sg:city":"Sedilo",
    "sg:orig_category":"Servizi Al Turismo. Trasporto Pubblico E Privato",
    "sg:phone":"+39 0785 59405",
    "sg:postcode":"09076",
    "sg:province":"Oristano",
    "wof:name":"Pisanu Geraldo",
    "wof:placetype":"venue"
},
  "geometry": {"coordinates":[8.946614,40.186974],"type":"Point"}
}