{
  "type": "Feature",
  "properties": {
    "addr:full":"1, Via Vittorio Veneto 21048 Solbiate Arno Solbiate Arno Varese 21048",
    "addr:housenumber":"arno",
    "addr:postcode":"21048;21048",
    "addr:street":"Via Vittorio Veneto",
    "iso:country":"IT",
    "sg:address":"1, Via Vittorio Veneto 21048 Solbiate Arno",
    "sg:city":"Solbiate Arno",
    "sg:classifiers":[
        {
            "category":"Professional",
            "subcategory":"Engineering",
            "type":"Services"
        }
    ],
    "sg:phone":"+39 0331 988600",
    "sg:postcode":"21048",
    "sg:province":"Varese",
    "sg:tags":[
        "machine",
        "-",
        "mechanical"
    ],
    "wof:name":"Riganti S.p.a.",
    "wof:placetype":"venue"
},
  "geometry": {"coordinates":[8.817358,45.719959],"type":"Point"}
}