{
  "type": "Feature",
  "properties": {
    "addr:full":"30125 Venezia Venezia Venezia 30125",
    "addr:postcode":"30125;30125",
    "iso:country":"IT",
    "sg:address":"30125 Venezia",
    "sg:city":"Venezia",
    "sg:classifiers":[
        {
            "category":"Banks & Credit Unions",
            "subcategory":"Investment Brokerage",
            "type":"Services"
        }
    ],
    "sg:phone":"+39 041 520 7555",
    "sg:postcode":"30125",
    "sg:province":"Venezia",
    "sg:tags":[
        "vehicles",
        "auxiliary",
        "motor"
    ],
    "sg:website":"http://www.veniceparking.it",
    "wof:name":"Venezia Tronchetto Parking Srl",
    "wof:placetype":"venue"
},
  "geometry": {"coordinates":[12.3266267776,45.4408950806],"type":"Point"}
}