{
  "type": "Feature",
  "properties": {
    "addr:full":"01034 Fabrica Di Roma Fabrica di Roma Viterbo 01034",
    "addr:postcode":"01034;01034",
    "iso:country":"IT",
    "sg:address":"01034 Fabrica Di Roma",
    "sg:city":"Fabrica di Roma",
    "sg:orig_category":"Materiali Semilavorati Metallici",
    "sg:phone":"+39 0761 574187",
    "sg:postcode":"01034",
    "sg:province":"Viterbo",
    "wof:name":"Scopetti G. - Metalli Srl",
    "wof:placetype":"venue"
},
  "geometry": {"coordinates":[12.334934,42.323509],"type":"Point"}
}