{
  "type": "Feature",
  "properties": {
    "addr:full":"20096 Pioltello Pioltello Milano 20096",
    "addr:postcode":"20096;20096",
    "iso:country":"IT",
    "sg:address":"20096 Pioltello",
    "sg:city":"Pioltello",
    "sg:orig_category":"Macchine, Impianti E Forniture Per Industria Grafica, Cartaria E Cartotecnica",
    "sg:phone":"+39 02 926 7609",
    "sg:postcode":"20096",
    "sg:province":"Milano",
    "wof:name":"Repro Master Electronic-o.g.parrini Srl",
    "wof:placetype":"venue"
},
  "geometry": {"coordinates":[9.322278,45.486526],"type":"Point"}
}