{
  "type": "Feature",
  "properties": {
    "iso:country":"IT",
    "sg:address":"5, Via Olimpia 20052 Monza",
    "sg:city":"Monza",
    "sg:classifiers":[
        {
            "category":"Professional",
            "subcategory":"Engineering",
            "type":"Services"
        }
    ],
    "sg:phone":"+39 39039321145",
    "sg:postcode":"20052",
    "sg:province":"Milano",
    "sg:tags":[
        "machine",
        "-",
        "mechanical"
    ],
    "wof:name":"Valtorta & C. S.r.l.",
    "wof:placetype":"venue"
},
  "geometry": {"coordinates":[9.244743,45.595745],"type":"Point"}
}