{
  "type": "Feature",
  "properties": {
    "iso:country":"IT",
    "sg:address":"92026 Favara",
    "sg:city":"Favara",
    "sg:orig_category":"Arredo Cucina Ed Elettrodomestici. Elettrodomestici",
    "sg:phone":"+39 0922 32825",
    "sg:postcode":"92026",
    "sg:province":"Agrigento",
    "wof:name":"Veneziano Broccia Antonio",
    "wof:placetype":"venue"
},
  "geometry": {"coordinates":[13.664347,37.322334],"type":"Point"}
}