{
  "type": "Feature",
  "properties": {
    "addr:full":"97100 Ragusa Ragusa Ragusa 97100",
    "addr:postcode":"97100;97100",
    "iso:country":"IT",
    "sg:address":"97100 Ragusa",
    "sg:city":"Ragusa",
    "sg:orig_category":"Prodotti Alimentari",
    "sg:phone":"+39 0932 624232",
    "sg:postcode":"97100",
    "sg:province":"Ragusa",
    "wof:name":"Euroforno Di Cascone Salvatore Baglieri Carlo & C. Snc",
    "wof:placetype":"venue"
},
  "geometry": {"coordinates":[14.6821050644,36.9125175476],"type":"Point"}
}