{
  "type": "Feature",
  "properties": {
    "addr:full":"20146 Milano Milano Milano 20146",
    "addr:postcode":"20146;20146",
    "iso:country":"IT",
    "sg:address":"20146 Milano",
    "sg:city":"Milano",
    "sg:orig_category":"Servizi E Lavori Per Arredamento E Industria Del Legno. Servizi E Lavori Per Edilizia E Lavori Pubblici",
    "sg:phone":"+39 02 406924",
    "sg:postcode":"20146",
    "sg:province":"Milano",
    "wof:name":"Monti Giuliano",
    "wof:placetype":"venue"
},
  "geometry": {"coordinates":[9.13886,45.465675],"type":"Point"}
}