{
  "type": "Feature",
  "properties": {
    "iso:country":"IT",
    "sg:address":"21057 Olgiate Olona",
    "sg:city":"Olgiate Olona",
    "sg:orig_category":"Prodotti E Manufatti In Materie Plastiche. Forniture Per Edilizia E Lavori Pubblici. Forniture E Materiali Per Imballaggio E Confezionamento",
    "sg:phone":"+39 0331 631396",
    "sg:postcode":"21057",
    "sg:province":"Varese",
    "sg:website":"http://www.eredicaimi.it",
    "wof:name":"Eredi Caimi Srl",
    "wof:placetype":"venue"
},
  "geometry": {"coordinates":[8.8713884354,45.6227607727],"type":"Point"}
}