{
  "type": "Feature",
  "properties": {
    "addr:full":"20026 Novate Milanese Novate Milanese Milano 20026",
    "addr:postcode":"20026;20026",
    "iso:country":"IT",
    "sg:address":"20026 Novate Milanese",
    "sg:city":"Novate Milanese",
    "sg:orig_category":"Resistenze Elettriche - Produzione E Commercio",
    "sg:phone":"+39 02 3910 0295",
    "sg:postcode":"20026",
    "sg:province":"Milano",
    "wof:name":"Ra.co. Sas",
    "wof:placetype":"venue"
},
  "geometry": {"coordinates":[9.14929,45.53318],"type":"Point"}
}