{
  "type": "Feature",
  "properties": {
    "iso:country":"IT",
    "sg:address":"00153 Roma",
    "sg:city":"Roma",
    "sg:orig_category":"Impiantistica E Prodotti Tecnologici Per Edilizia. Servizi Ausiliari Di Sorveglianza, Manutenzione E Pulizia",
    "sg:phone":"+39 06 580 6330",
    "sg:postcode":"00153",
    "sg:province":"Roma",
    "wof:name":"Ambrosia Technologies Srl",
    "wof:placetype":"venue"
},
  "geometry": {"coordinates":[12.465486,41.878208],"type":"Point"}
}