{
  "type": "Feature",
  "properties": {
    "addr:full":"Via Vienna, 46/48 24040 Zingonia Zingonia Bergamo 24040",
    "addr:housenumber":"46 / 48",
    "addr:postcode":"24040;24040",
    "addr:street":"Via Vienna",
    "iso:country":"IT",
    "sg:address":"Via Vienna, 46/48 24040 Zingonia",
    "sg:city":"Zingonia",
    "sg:classifiers":[
        {
            "category":"Structure",
            "subcategory":"Building",
            "type":"Public Place"
        }
    ],
    "sg:phone":"+39 035 884452",
    "sg:postcode":"24040",
    "sg:province":"Bergamo",
    "sg:tags":[
        "plug",
        "special-design",
        "moulded",
        "cable"
    ],
    "wof:name":"Elettronica Di Vitali Gabriella Srl",
    "wof:placetype":"venue"
},
  "geometry": {"coordinates":[9.620271,45.593235],"type":"Point"}
}