{
  "type": "Feature",
  "properties": {
    "iso:country":"IT",
    "sg:address":"Via Venezia 47; Scorze; 30037",
    "sg:classifiers":[
        {
            "category":"Banks & Credit Unions",
            "subcategory":"Bank",
            "type":"Services"
        }
    ],
    "sg:phone":"+39 041 584 1151",
    "sg:postcode":"30037",
    "sg:province":"Venezia",
    "wof:name":"Rolo Banca 1473 Spa",
    "wof:placetype":"venue"
},
  "geometry": {"coordinates":[12.11016,45.57],"type":"Point"}
}