{
  "type": "Feature",
  "properties": {
    "iso:country":"IT",
    "sg:address":"Via Cantone Valle 22 13851 Castelletto Cervo",
    "sg:city":"Castelletto Cervo",
    "sg:classifiers":[
        {
            "category":"Shopping",
            "subcategory":"Crafts & Fabrics",
            "type":"Retail Goods"
        }
    ],
    "sg:phone":"+39 0161 859121",
    "sg:postcode":"13851",
    "sg:province":"Biella",
    "sg:tags":[
        "textile",
        "machinery",
        "accessory"
    ],
    "sg:website":"www.tre-b.com",
    "wof:name":"Officine Tre B Macchine Tessili Di Brenzan Adino E Figli Snc",
    "wof:placetype":"venue"
},
  "geometry": {"coordinates":[8.05827,45.562836],"type":"Point"}
}