{
  "type": "Feature",
  "properties": {
    "iso:country":"IT",
    "sg:address":"55030 Vagli Sotto",
    "sg:city":"Vagli sopra",
    "sg:orig_category":"Agriturismo",
    "sg:phone":"+39 0583 664103",
    "sg:postcode":"55030",
    "sg:province":"Lucca",
    "wof:name":"Buca Dei Gracchi",
    "wof:placetype":"venue"
},
  "geometry": {"coordinates":[10.266586,44.117672],"type":"Point"}
}