{
  "type": "Feature",
  "properties": {
    "addr:full":"19, Via Xxv Aprile 20097 San Donato Milanese San Donato Milanese Milano 20097",
    "addr:postcode":"20097;20097",
    "addr:street":"Via Xxv Aprile",
    "iso:country":"IT",
    "sg:address":"19, Via Xxv Aprile 20097 San Donato Milanese",
    "sg:city":"San Donato Milanese",
    "sg:classifiers":[
        {
            "category":"Manufacturing",
            "subcategory":"Metals",
            "type":"Manufacturing & Wholesale Goods"
        }
    ],
    "sg:phone":"+39 390 251 5051",
    "sg:postcode":"20097",
    "sg:province":"Milano",
    "sg:tags":[
        "metallurgy",
        "metalworking"
    ],
    "wof:name":"Ubk S.p.a.",
    "wof:placetype":"venue"
},
  "geometry": {"coordinates":[9.1881408691,45.4636878967],"type":"Point"}
}