{
  "type": "Feature",
  "properties": {
    "iso:country":"IT",
    "sg:address":"10, Via Sereni 51018 Pieve A Nievole",
    "sg:city":"Pieve a Nievole",
    "sg:classifiers":[
        {
            "category":"Manufacturing",
            "subcategory":"Wood Products",
            "type":"Manufacturing & Wholesale Goods"
        }
    ],
    "sg:phone":"+39 39057281660",
    "sg:postcode":"51018",
    "sg:province":"Pistoia",
    "sg:tags":[
        "furniture"
    ],
    "wof:name":"Mechanical Cork Di Romani Maria Claudia",
    "wof:placetype":"venue"
},
  "geometry": {"coordinates":[10.790265,43.852852],"type":"Point"}
}