{
  "type": "Feature",
  "properties": {
    "iso:country":"IT",
    "sg:address":"Via Emilia S.pietro; Reggio Emilia; 42100",
    "sg:classifiers":[
        {
            "category":"Banks & Credit Unions",
            "subcategory":"Bank",
            "type":"Services"
        }
    ],
    "sg:phone":"+39 0522 44391",
    "sg:postcode":"42100",
    "sg:province":"Reggio Nell'Emilia",
    "wof:name":"Credito Italiano Spa",
    "wof:placetype":"venue"
},
  "geometry": {"coordinates":[10.641138,44.694984],"type":"Point"}
}