{
  "type": "Feature",
  "properties": {
    "iso:country":"IT",
    "sg:address":"20124 Milano",
    "sg:city":"Milano",
    "sg:orig_category":"Brevetti D'invenzione - Consulenza Tecnica E Legale",
    "sg:phone":"+39 02 6738 0280",
    "sg:postcode":"20124",
    "sg:province":"Milano",
    "sg:website":"http://www.botti-ferrari.com",
    "wof:name":"Botti & Ferrari Srl",
    "wof:placetype":"venue"
},
  "geometry": {"coordinates":[9.198327,45.481152],"type":"Point"}
}