{
  "type": "Feature",
  "properties": {
    "addr:full":"20148 Milano Milano Milano 20148",
    "addr:postcode":"20148;20148",
    "iso:country":"IT",
    "sg:address":"20148 Milano",
    "sg:city":"Milano",
    "sg:orig_category":"Pubblica Amministrazione",
    "sg:phone":"+39 02 400851",
    "sg:postcode":"20148",
    "sg:province":"Milano",
    "wof:name":"Poste Italiane Spa",
    "wof:placetype":"venue"
},
  "geometry": {"coordinates":[9.1418371201,45.4702720642],"type":"Point"}
}