{
  "type": "Feature",
  "properties": {
    "addr:full":"75, Strada Statale Per Voghera 15057 Tortona Tortona Alessandria 15057",
    "addr:postcode":"15057;15057",
    "addr:street":"Strada Statale Per Voghera",
    "iso:country":"IT",
    "sg:address":"75, Strada Statale Per Voghera 15057 Tortona",
    "sg:city":"Tortona",
    "sg:classifiers":[
        {
            "category":"Parking",
            "subcategory":"Lot",
            "type":"Transportation"
        }
    ],
    "sg:phone":"+39 0131 861738",
    "sg:postcode":"15057",
    "sg:province":"Alessandria",
    "sg:tags":[
        "transport",
        "road"
    ],
    "wof:name":"Itac (s.p.a.)",
    "wof:placetype":"venue"
},
  "geometry": {"coordinates":[8.879961,44.909573],"type":"Point"}
}