{
  "type": "Feature",
  "properties": {
    "iso:country":"IT",
    "sg:address":"36031 Dueville",
    "sg:city":"Dueville",
    "sg:classifiers":[
        {
            "category":"Manufacturing",
            "subcategory":"Metals",
            "type":"Manufacturing & Wholesale Goods"
        }
    ],
    "sg:phone":"+39 0444 361165",
    "sg:postcode":"36031",
    "sg:province":"Vicenza",
    "sg:tags":[
        "forming",
        "working",
        "welding"
    ],
    "wof:name":"Plast Inox Snc",
    "wof:placetype":"venue"
},
  "geometry": {"coordinates":[11.5740661621,45.6190109253],"type":"Point"}
}