{
  "type": "Feature",
  "properties": {
    "iso:country":"IT",
    "sg:address":"20067 Paullo",
    "sg:city":"Paullo",
    "sg:orig_category":"Materiali E Componenti Elettronici",
    "sg:phone":"+39 02 9063 1583",
    "sg:postcode":"20067",
    "sg:province":"Milano",
    "wof:name":"Label Di Spini Massimo",
    "wof:placetype":"venue"
},
  "geometry": {"coordinates":[9.395782,45.417404],"type":"Point"}
}