{
  "type": "Feature",
  "properties": {
    "iso:country":"IT",
    "sg:address":"17014 Cairo Montenotte",
    "sg:city":"Cairo Montenotte",
    "sg:classifiers":[
        {
            "category":"Health Services",
            "subcategory":"Nursing And Care Facility",
            "type":"Services"
        }
    ],
    "sg:phone":"+39 019 500260",
    "sg:postcode":"17014",
    "sg:province":"Savona",
    "sg:tags":[
        "case",
        "cura",
        "private",
        "di"
    ],
    "wof:name":"Pra Ellera Srl",
    "wof:placetype":"venue"
},
  "geometry": {"coordinates":[8.212707,44.356495],"type":"Point"}
}