{
  "type": "Feature",
  "properties": {
    "iso:country":"IT",
    "sg:address":"Via Dalmazia, 13; La Spezia; 19100",
    "sg:classifiers":[
        {
            "category":"Banks & Credit Unions",
            "subcategory":"Bank",
            "type":"Services"
        }
    ],
    "sg:phone":"+39 0187 20131",
    "wof:name":"Banca Nazionale Del Lavoro",
    "wof:placetype":"venue"
},
  "geometry": {"coordinates":[9.831332,44.110458],"type":"Point"}
}