{
  "type": "Feature",
  "properties": {
    "iso:country":"IT",
    "sg:address":"10088 Volpiano",
    "sg:city":"Volpiano",
    "sg:orig_category":"Utensili Meccanici E Materiali. Forniture Per Attivita' Industriali",
    "sg:phone":"+39 011 988 1558",
    "sg:postcode":"10088",
    "sg:province":"Torino",
    "wof:name":"I.s.a.p. S.r.l.",
    "wof:placetype":"venue"
},
  "geometry": {"coordinates":[7.830256,45.172955],"type":"Point"}
}