{
  "type": "Feature",
  "properties": {
    "iso:country":"IT",
    "sg:address":"Viale Europa 17, 45020 Lusia, Ro",
    "sg:city":"Lusia",
    "sg:classifiers":[
        {
            "category":"Banks & Credit Unions",
            "subcategory":"Bank",
            "type":"Services"
        }
    ],
    "sg:postcode":"45020",
    "sg:province":"Rovigo",
    "wof:name":"Banca Di Credito Cooperativo Di Lusia E Cavazzana (rovigo) Scrl",
    "wof:placetype":"venue"
},
  "geometry": {"coordinates":[11.663951,45.099438],"type":"Point"}
}