{
  "type": "Feature",
  "properties": {
    "addr:full":"10083 Favria Favria Torino 10083",
    "addr:housenumber":"10083",
    "addr:postcode":"10083",
    "addr:street":"Favria Favria",
    "iso:country":"IT",
    "sg:address":"10083 Favria",
    "sg:city":"Favria",
    "sg:classifiers":[
        {
            "category":"Travel",
            "subcategory":"Hotels & Motels",
            "type":"Entertainment"
        }
    ],
    "sg:phone":"+39 0185 273533",
    "sg:postcode":"10083",
    "sg:province":"Torino",
    "sg:tags":[
        "hotels",
        "facility"
    ],
    "wof:name":"Futura Hotels Srl",
    "wof:placetype":"venue"
},
  "geometry": {"coordinates":[7.685839,45.313885],"type":"Point"}
}