{
  "type": "Feature",
  "properties": {
    "iso:country":"IT",
    "sg:address":"12012 Boves",
    "sg:city":"Boves",
    "sg:orig_category":"Serramenti Ed Infissi",
    "sg:phone":"+39 0171 380248",
    "sg:postcode":"12012",
    "sg:province":"Cuneo",
    "sg:website":"http://www.boves-online.com/eliosflex",
    "wof:name":"Eliosflex Di Giuliano Stefano & C. Snc",
    "wof:placetype":"venue"
},
  "geometry": {"coordinates":[7.559422,44.329273],"type":"Point"}
}