{
  "type": "Feature",
  "properties": {
    "iso:country":"IT",
    "sg:address":"10143 Torino",
    "sg:city":"Torino",
    "sg:orig_category":"Prodotti Vari In Metallo",
    "sg:phone":"+39 011 752484",
    "sg:postcode":"10143",
    "sg:province":"Torino",
    "wof:name":"Cannata Giorgio",
    "wof:placetype":"venue"
},
  "geometry": {"coordinates":[7.654302597,45.0910720825],"type":"Point"}
}