{
  "type": "Feature",
  "properties": {
    "addr:full":"Km. 19, Strada St. 229 28010 Vaprio D'agogna Novara 28010",
    "addr:housenumber":"229",
    "addr:postcode":"28010;28010",
    "addr:street":"Km. 19 Strada St.",
    "iso:country":"IT",
    "sg:address":"Km. 19, Strada St. 229 28010 Vaprio D'agogna",
    "sg:classifiers":[
        {
            "category":"Food & Beverages",
            "subcategory":"Groceries & Convenience Stores",
            "type":"Retail Goods"
        }
    ],
    "sg:phone":"+39 0321 996371",
    "sg:postcode":"28010",
    "sg:province":"Novara",
    "sg:tags":[
        "product",
        "related"
    ],
    "wof:name":"I.d.i. Industria Dolciaria Italiana S.p.a.",
    "wof:placetype":"venue"
},
  "geometry": {"coordinates":[8.6186714172,45.4450836182],"type":"Point"}
}