{
  "type": "Feature",
  "properties": {
    "iso:country":"IT",
    "sg:address":"Piazza De Angeli 9; Milano; 20146",
    "sg:city":"Milano",
    "sg:classifiers":[
        {
            "category":"Banks & Credit Unions",
            "subcategory":"Bank",
            "type":"Services"
        }
    ],
    "sg:phone":"+39 02 481 5348",
    "sg:postcode":"20146",
    "sg:province":"Milano",
    "wof:name":"Banca Sella Spa",
    "wof:placetype":"venue"
},
  "geometry": {"coordinates":[9.148705,45.466362],"type":"Point"}
}