{
  "type": "Feature",
  "properties": {
    "iso:country":"IT",
    "sg:address":"35010 Gazzo",
    "sg:city":"Gazzo",
    "sg:orig_category":"Ospedali E Servizi Sanitari",
    "sg:phone":"+39 049 942 5751",
    "sg:postcode":"35010",
    "sg:province":"Padova",
    "wof:name":"Cricini Mazzanti Licia",
    "wof:placetype":"venue"
},
  "geometry": {"coordinates":[11.82475,45.286007],"type":"Point"}
}