{
  "type": "Feature",
  "properties": {
    "iso:country":"IT",
    "sg:address":"51010 Massa E Cozzile",
    "sg:city":"Massa e Cozzile",
    "sg:classifiers":[
        {
            "category":"Travel",
            "subcategory":"Travel Agent",
            "type":"Entertainment"
        }
    ],
    "sg:phone":"+39 572772586",
    "sg:postcode":"51010",
    "sg:province":"Pistoia",
    "sg:tags":[
        "operator",
        "tour",
        "tourist"
    ],
    "sg:website":"http://www.afratour.it",
    "wof:name":"Afra Tour By Incoming Center Srl",
    "wof:placetype":"venue"
},
  "geometry": {"coordinates":[10.753665,43.869514],"type":"Point"}
}