{
  "type": "Feature",
  "properties": {
    "iso:country":"IT",
    "sg:address":"35134 Padova",
    "sg:city":"Padova",
    "sg:orig_category":"Articoli Medico-sanitari Ed Ortopedici. Impianti, Attrezzature E Forniture Sanitarie Ed Ospedaliere",
    "sg:phone":"+39 049 610042",
    "sg:postcode":"35134",
    "sg:province":"Padova",
    "wof:name":"Verderi Bruno",
    "wof:placetype":"venue"
},
  "geometry": {"coordinates":[11.957263,45.329105],"type":"Point"}
}