{
  "type": "Feature",
  "properties": {
    "addr:full":"80053 Castellammare Di Stabia Castellammare di Stabia Napoli 80053",
    "addr:postcode":"80053;80053",
    "iso:country":"IT",
    "sg:address":"80053 Castellammare Di Stabia",
    "sg:city":"Castellammare di Stabia",
    "sg:orig_category":"Arredo Cucina Ed Elettrodomestici. Frigotecnica, Apparecchiature E Servizi. Elettrodomestici",
    "sg:phone":"+39 081 870 5676",
    "sg:postcode":"80053",
    "sg:province":"Napoli",
    "wof:name":"Ascione Vincenzo & Catello",
    "wof:placetype":"venue"
},
  "geometry": {"coordinates":[14.4898,40.698475],"type":"Point"}
}