{
  "type": "Feature",
  "properties": {
    "addr:full":"Via Gramsci 11 20048 Carate Brianza Carate Brianza Milano 20048",
    "addr:housenumber":"11",
    "addr:postcode":"20048;20048",
    "addr:street":"Via Gramsci",
    "iso:country":"IT",
    "sg:address":"Via Gramsci 11 20048 Carate Brianza",
    "sg:city":"Carate Brianza",
    "sg:classifiers":[
        {
            "category":"Wholesale",
            "subcategory":"Auto Parts",
            "type":"Manufacturing & Wholesale Goods"
        }
    ],
    "sg:phone":"+39 036 290 1236",
    "sg:postcode":"20048",
    "sg:province":"Milano",
    "sg:tags":[
        "machine",
        "screw"
    ],
    "wof:name":"La Standarsteel Srl",
    "wof:placetype":"venue"
},
  "geometry": {"coordinates":[9.238098,45.652542],"type":"Point"}
}