{
  "type": "Feature",
  "properties": {
    "addr:full":"00157 Roma Roma Roma 00157",
    "addr:postcode":"00157;00157",
    "iso:country":"IT",
    "sg:address":"00157 Roma",
    "sg:city":"Roma",
    "sg:classifiers":[
        {
            "category":"Shopping",
            "subcategory":"Bicycles & Sporting Goods",
            "type":"Retail Goods"
        }
    ],
    "sg:phone":"+39 06 438 0134",
    "sg:postcode":"00157",
    "sg:province":"Roma",
    "sg:tags":[
        "tempo",
        "lo",
        "-",
        "libero",
        "per",
        "servizi",
        "forniture",
        "articoli",
        "e",
        "sport",
        "il"
    ],
    "wof:name":"Romh Pesca Di Stella M.",
    "wof:placetype":"venue"
},
  "geometry": {"coordinates":[12.538407,41.914082],"type":"Point"}
}