{
  "type": "Feature",
  "properties": {
    "addr:full":"20143 Milano Milano Milano 20143",
    "addr:postcode":"20143;20143",
    "iso:country":"IT",
    "sg:address":"20143 Milano",
    "sg:city":"Milano",
    "sg:orig_category":"Servizi E Lavori Per Edilizia E Lavori Pubblici. Telecomunicazioni E Telefonia, Impianti, Apparecchi E Servizi. Acqua, Luce, Gas E Societa' Di Esercizio Pubblico",
    "sg:phone":"+39 02 8942 2570",
    "sg:postcode":"20143",
    "sg:province":"Milano",
    "wof:name":"Quantum Telecom Srl",
    "wof:placetype":"venue"
},
  "geometry": {"coordinates":[9.167654,45.445274],"type":"Point"}
}