{
  "type": "Feature",
  "properties": {
    "iso:country":"IT",
    "sg:address":"66020 S. Giovanni Teatino",
    "sg:orig_category":"Apparecchiature E Sistemi Per Magazzinaggio E Movimentazione. Macchine E Impianti Per Attivita' Commerciali Ed Artigianali. Macchine, Strumenti Ed Apparecchi Per Attivita' Industriali",
    "sg:phone":"+39 085 446 5725",
    "sg:postcode":"66020",
    "sg:province":"Chieti",
    "wof:name":"Pesa Service Srl",
    "wof:placetype":"venue"
},
  "geometry": {"coordinates":[14.171074,42.406048],"type":"Point"}
}