{
  "type": "Feature",
  "properties": {
    "iso:country":"IT",
    "sg:address":"11, Via Artigiani 25030 Maclodio",
    "sg:city":"Maclodio",
    "sg:classifiers":[
        {
            "category":"Shopping",
            "subcategory":"Crafts & Fabrics",
            "type":"Retail Goods"
        }
    ],
    "sg:phone":"+39 030 978 9811",
    "sg:postcode":"25030",
    "sg:province":"Brescia",
    "wof:name":"Valtrompia Filati Srl",
    "wof:placetype":"venue"
},
  "geometry": {"coordinates":[10.04941082,45.4710006714],"type":"Point"}
}