{
  "type": "Feature",
  "properties": {
    "addr:full":"Via Kennedy 32 20020 Misinto Misinto Milano 20020",
    "addr:housenumber":"32",
    "addr:postcode":"20020;20020",
    "addr:street":"Via Kennedy",
    "iso:country":"IT",
    "sg:address":"Via Kennedy 32 20020 Misinto",
    "sg:city":"Misinto",
    "sg:orig_category":"Filters For The Pharmaceutical Industry",
    "sg:phone":"+39 02 9632 0289",
    "sg:postcode":"20020",
    "sg:province":"Milano",
    "wof:name":"Dcm Delta Costruzioni Meccaniche Srl",
    "wof:placetype":"venue"
},
  "geometry": {"coordinates":[9.1881408691,45.4636878967],"type":"Point"}
}