{
  "type": "Feature",
  "properties": {
    "iso:country":"IT",
    "sg:address":"98030 Giardini Naxos",
    "sg:classifiers":[
        {
            "category":"Travel",
            "subcategory":"Hotels & Motels",
            "type":"Entertainment"
        }
    ],
    "sg:phone":"+39 0942 52116",
    "sg:postcode":"98030",
    "sg:province":"Messina",
    "sg:tags":[
        "hotels",
        "facility"
    ],
    "wof:name":"Kalos Hotel",
    "wof:placetype":"venue"
},
  "geometry": {"coordinates":[15.555523,38.192333],"type":"Point"}
}