{
  "type": "Feature",
  "properties": {
    "iso:country":"IT",
    "sg:address":"20093 Cologno Monzese",
    "sg:city":"Cologno Monzese",
    "sg:orig_category":"Utensili Meccanici E Materiali. Elettrotecnica Industriale, Prodotti E Apparecchiature",
    "sg:phone":"+39 02 2730 5393",
    "sg:postcode":"20093",
    "sg:province":"Milano",
    "wof:name":"Perles Italiana S.r.l.",
    "wof:placetype":"venue"
},
  "geometry": {"coordinates":[9.264175,45.51936],"type":"Point"}
}