{
  "type": "Feature",
  "properties": {
    "iso:country":"IT",
    "sg:address":"20133 Milano",
    "sg:city":"Milano",
    "sg:orig_category":"Ospedali E Servizi Sanitari. Servizi Sociali. Associazioni Ed Organismi Di Interesse Pubblico",
    "sg:phone":"+39 02 266 7466",
    "sg:postcode":"20133",
    "sg:province":"Milano",
    "wof:name":"Comunica Onlus",
    "wof:placetype":"venue"
},
  "geometry": {"coordinates":[9.233382,45.480831],"type":"Point"}
}