{
  "type": "Feature",
  "properties": {
    "iso:country":"IT",
    "sg:address":"Contrada Luvar\u00e0 66b 98129 Messina",
    "sg:city":"Messina",
    "sg:classifiers":[
        {
            "category":"Building & Trades",
            "subcategory":"Plumbing",
            "type":"Services"
        }
    ],
    "sg:phone":"+39 090 730112",
    "sg:postcode":"98129",
    "sg:province":"Messina",
    "sg:tags":[
        "steel",
        "pipes",
        "welded"
    ],
    "wof:name":"Metallurgica F.lli Frisardi Sas",
    "wof:placetype":"venue"
},
  "geometry": {"coordinates":[15.555523,38.192333],"type":"Point"}
}