{
  "type": "Feature",
  "properties": {
    "addr:full":"87, Strada Della Cebrosa 10156 Torino Torino Torino 10156",
    "addr:postcode":"10156;10156",
    "addr:street":"Strada Della Cebrosa",
    "iso:country":"IT",
    "sg:address":"87, Strada Della Cebrosa 10156 Torino",
    "sg:city":"Torino",
    "sg:classifiers":[
        {
            "category":"Manufacturing",
            "subcategory":"Metals",
            "type":"Manufacturing & Wholesale Goods"
        }
    ],
    "sg:phone":"+39 011 225 0911",
    "sg:postcode":"10156",
    "sg:province":"Torino",
    "sg:tags":[
        "processing"
    ],
    "wof:name":"Euroweld S.r.l.",
    "wof:placetype":"venue"
},
  "geometry": {"coordinates":[7.7317376137,45.1200904846],"type":"Point"}
}