{
  "type": "Feature",
  "properties": {
    "iso:country":"IT",
    "sg:address":"80122 Napoli",
    "sg:city":"Napoli",
    "sg:orig_category":"Non-classified Establishments",
    "sg:phone":"+39 081 664354",
    "sg:postcode":"80122",
    "sg:province":"Napoli",
    "wof:name":"R.g. Gagliardi Sas",
    "wof:placetype":"venue"
},
  "geometry": {"coordinates":[14.222571,40.833881],"type":"Point"}
}