{
  "type": "Feature",
  "properties": {
    "iso:country":"IT",
    "sg:address":"16139 Genova",
    "sg:city":"Genova",
    "sg:orig_category":"Prodotti Chimici Secondari. Macchine E Forniture Per Ecologia E Smaltimento Rifiuti. Forniture Per Attivita' Industriali",
    "sg:phone":"+39 010 881061",
    "sg:postcode":"16139",
    "sg:province":"Genova",
    "wof:name":"Dusmar Snc Di Saburri Mariangela & C.",
    "wof:placetype":"venue"
},
  "geometry": {"coordinates":[8.9522027969,44.4191703796],"type":"Point"}
}