{
  "type": "Feature",
  "properties": {
    "addr:full":"90135 Palermo Palermo Palermo 90135",
    "addr:postcode":"90135;90135",
    "iso:country":"IT",
    "sg:address":"90135 Palermo",
    "sg:city":"Palermo",
    "sg:orig_category":"Nautica. Ricambi E Componenti Dei Mezzi Di Trasporto",
    "sg:phone":"+39 091 228898",
    "sg:postcode":"90135",
    "sg:province":"Palermo",
    "wof:name":"Evola Motori Spa",
    "wof:placetype":"venue"
},
  "geometry": {"coordinates":[13.40838,38.086281],"type":"Point"}
}