{
  "type": "Feature",
  "properties": {
    "iso:country":"IT",
    "sg:address":"12046 Monta'",
    "sg:orig_category":"Nautica. Forniture Per Attivita' Commerciali Ed Artigianali",
    "sg:phone":"+39 0173 975946",
    "sg:postcode":"12046",
    "sg:province":"Cuneo",
    "wof:name":"Filelast",
    "wof:placetype":"venue"
},
  "geometry": {"coordinates":[7.547111,44.388798],"type":"Point"}
}