{
  "type": "Feature",
  "properties": {
    "iso:country":"IT",
    "sg:address":"Piazza Garibaldi, 7; Montebelluna; 31044",
    "sg:city":"Montebelluna",
    "sg:classifiers":[
        {
            "category":"Banks & Credit Unions",
            "subcategory":"Bank",
            "type":"Services"
        }
    ],
    "sg:phone":"+39 0423 302571",
    "sg:postcode":"31044",
    "sg:province":"Treviso",
    "wof:name":"Cassa Marca",
    "wof:placetype":"venue"
},
  "geometry": {"coordinates":[12.068209,45.737789],"type":"Point"}
}