{
  "type": "Feature",
  "properties": {
    "addr:full":"20136 Milano Milano Milano 20136",
    "addr:postcode":"20136;20136",
    "iso:country":"IT",
    "sg:address":"20136 Milano",
    "sg:city":"Milano",
    "sg:classifiers":[
        {
            "category":"Health Services",
            "subcategory":"Health Practitioner",
            "type":"Services"
        }
    ],
    "sg:phone":"+39 02 5831 7440",
    "sg:postcode":"20136",
    "sg:province":"Milano",
    "sg:tags":[
        "medici"
    ],
    "wof:name":"Istituto Fisioterapico Per La Ricerca E Terapia Del Dolore",
    "wof:placetype":"venue"
},
  "geometry": {"coordinates":[9.185329,45.45113],"type":"Point"}
}