{
  "type": "Feature",
  "properties": {
    "iso:country":"IT",
    "sg:address":"Via Marconi 8 23897 Vigano'",
    "sg:classifiers":[
        {
            "category":"Wholesale",
            "subcategory":"Vending Machines",
            "type":"Manufacturing & Wholesale Goods"
        }
    ],
    "sg:phone":"+39 039 955653",
    "sg:postcode":"23897",
    "sg:province":"Lecco",
    "sg:tags":[
        "boring",
        "combined",
        "machines",
        "milling"
    ],
    "sg:website":"www.fubri.com",
    "wof:name":"Fubri Srl",
    "wof:placetype":"venue"
},
  "geometry": {"coordinates":[9.390071,45.852982],"type":"Point"}
}