{
  "type": "Feature",
  "properties": {
    "iso:country":"IT",
    "sg:address":"80142 Napoli",
    "sg:city":"Napoli",
    "sg:orig_category":"Scuole E Servizi Scolastici. Ricerca, Selezione E Formazione Del Personale",
    "sg:phone":"+39 081 287385",
    "sg:postcode":"80142",
    "sg:province":"Napoli",
    "wof:name":"Work Casa Srl",
    "wof:placetype":"venue"
},
  "geometry": {"coordinates":[14.307995,40.915379],"type":"Point"}
}