{
  "type": "Feature",
  "properties": {
    "iso:country":"IT",
    "sg:address":"20158 Milano",
    "sg:city":"Milano",
    "sg:orig_category":"Riscaldamento - Impianti E Manutenzione",
    "sg:phone":"+39 02 3932 0998",
    "sg:postcode":"20158",
    "sg:province":"Milano",
    "sg:website":"http://www.",
    "wof:name":"Ri.co Srl",
    "wof:placetype":"venue"
},
  "geometry": {"coordinates":[9.170543,45.497478],"type":"Point"}
}