{
  "type": "Feature",
  "properties": {
    "addr:full":"10029 Villastellone Villastellone Torino 10029",
    "addr:housenumber":"10029",
    "addr:postcode":"10029",
    "addr:street":"Villastellone Villastellone",
    "iso:country":"IT",
    "sg:address":"10029 Villastellone",
    "sg:city":"Villastellone",
    "sg:orig_category":"Forniture Per Edilizia E Lavori Pubblici. Forniture Per Attivita' Industriali",
    "sg:phone":"+39 011 961 9555",
    "sg:postcode":"10029",
    "sg:province":"Torino",
    "wof:name":"Clares S.p.a.",
    "wof:placetype":"venue"
},
  "geometry": {"coordinates":[7.732793808,44.9285964966],"type":"Point"}
}