{
  "type": "Feature",
  "properties": {
    "iso:country":"IT",
    "sg:address":"16040 Orero",
    "sg:city":"Orero",
    "sg:orig_category":"Arredi Ed Attrezzature Per Uffici. Forniture Per Congressi, Fiere E Manifestazioni",
    "sg:phone":"+39 0185 354844",
    "sg:postcode":"16040",
    "sg:province":"Genova",
    "wof:name":"L.s.a Lavagne Scolastiche In Ardesia Di Garbarino Davide &c.",
    "wof:placetype":"venue"
},
  "geometry": {"coordinates":[9.269073,44.412369],"type":"Point"}
}