{
  "type": "Feature",
  "properties": {
    "addr:full":"47, Via Giuseppe Di Vittorio 51035 Lamporecchio Lamporecchio Pistoia 51035",
    "addr:postcode":"51035;51035",
    "addr:street":"Via Giuseppe Di Vittorio",
    "iso:country":"IT",
    "sg:address":"47, Via Giuseppe Di Vittorio 51035 Lamporecchio",
    "sg:city":"Lamporecchio",
    "sg:classifiers":[
        {
            "category":"Professional",
            "subcategory":"Engineering",
            "type":"Services"
        }
    ],
    "sg:phone":"+39 39057382303",
    "sg:postcode":"51035",
    "sg:province":"Pistoia",
    "sg:tags":[
        "machine",
        "-",
        "mechanical"
    ],
    "wof:name":"T.m.c. (s.r.l.)",
    "wof:placetype":"venue"
},
  "geometry": {"coordinates":[10.914819,43.874512],"type":"Point"}
}