{
  "type": "Feature",
  "properties": {
    "iso:country":"IT",
    "sg:address":"25, Via Isonzo 34070 Mossa",
    "sg:city":"Mossa",
    "sg:classifiers":[
        {
            "category":"Home & Garden",
            "subcategory":"Home Furnishings",
            "type":"Retail Goods"
        }
    ],
    "sg:phone":"+39 39048180080",
    "sg:postcode":"34070",
    "sg:province":"Gorizia",
    "sg:tags":[
        "household"
    ],
    "wof:name":"Medeot Mario (s.r.l.)",
    "wof:placetype":"venue"
},
  "geometry": {"coordinates":[13.548534,45.928867],"type":"Point"}
}