{
  "type": "Feature",
  "properties": {
    "iso:country":"IT",
    "sg:address":"14040 Quaranti",
    "sg:city":"Quaranti",
    "sg:classifiers":[
        {
            "category":"Communications",
            "subcategory":"Film & Video Production",
            "type":"Services"
        }
    ],
    "sg:phone":"+39 0141 775115",
    "sg:postcode":"14040",
    "sg:province":"Asti",
    "sg:tags":[
        "cracker",
        "e",
        "biscotti"
    ],
    "wof:name":"Amaretti Di Mattia",
    "wof:placetype":"venue"
},
  "geometry": {"coordinates":[8.449991,44.750973],"type":"Point"}
}