{
  "type": "Feature",
  "properties": {
    "iso:country":"IT",
    "sg:address":"25043 Breno",
    "sg:city":"Breno",
    "sg:orig_category":"Enti Turistici",
    "sg:phone":"+39 036 432 1556",
    "sg:postcode":"25043",
    "sg:province":"Brescia",
    "sg:website":"http://www.galvallecamonica.it",
    "wof:name":"G.a.l. Vallecamonica Srl",
    "wof:placetype":"venue"
},
  "geometry": {"coordinates":[10.21396,45.524174],"type":"Point"}
}