{
  "type": "Feature",
  "properties": {
    "addr:full":"27, Via Castelbarco Gian Carlo 20136 Milano Milano Milano 20136",
    "addr:postcode":"20136;20136",
    "addr:street":"Via Castelbarco Gian Carlo",
    "iso:country":"IT",
    "sg:address":"27, Via Castelbarco Gian Carlo 20136 Milano",
    "sg:city":"Milano",
    "sg:classifiers":[
        {
            "category":"Food & Beverages",
            "subcategory":"Dairy",
            "type":"Retail Goods"
        }
    ],
    "sg:phone":"+39 390 258 3991",
    "sg:postcode":"20136",
    "sg:province":"Milano",
    "sg:tags":[
        "product"
    ],
    "wof:name":"Azienda Municipalizzata Centrale Del Latte",
    "wof:placetype":"venue"
},
  "geometry": {"coordinates":[9.187253,45.446903],"type":"Point"}
}