{
  "type": "Feature",
  "properties": {
    "iso:country":"IT",
    "sg:address":"83100 Avellino",
    "sg:city":"Avellino",
    "sg:orig_category":"Trasporti E Spedizioni Merci",
    "sg:phone":"+39 0825 624591",
    "sg:postcode":"83100",
    "sg:province":"Avellino",
    "wof:name":"Bove Alfonso",
    "wof:placetype":"venue"
},
  "geometry": {"coordinates":[14.787101,40.912838],"type":"Point"}
}