{
  "type": "Feature",
  "properties": {
    "iso:country":"IT",
    "sg:address":"35139 Padova",
    "sg:city":"Padova",
    "sg:classifiers":[
        {
            "category":"Health Services",
            "subcategory":"Health Practitioner",
            "type":"Services"
        }
    ],
    "sg:phone":"+39 049 663889",
    "sg:postcode":"35139",
    "sg:province":"Padova",
    "sg:tags":[
        "medici"
    ],
    "wof:name":"Lago Cristina",
    "wof:placetype":"venue"
},
  "geometry": {"coordinates":[11.899858,45.337048],"type":"Point"}
}