{
  "type": "Feature",
  "properties": {
    "addr:full":"51/b, Via S. Biagio 42024 Castelnovo Di Sotto Reggio Nell'Emilia 42024",
    "addr:housenumber":"51 / b",
    "addr:postcode":"42024;42024",
    "addr:street":"Via S. Biagio",
    "iso:country":"IT",
    "sg:address":"51/b, Via S. Biagio 42024 Castelnovo Di Sotto",
    "sg:classifiers":[
        {
            "category":"Wholesale",
            "subcategory":"Machinery & Supplies",
            "type":"Manufacturing & Wholesale Goods"
        }
    ],
    "sg:phone":"+39 0522 683743",
    "sg:postcode":"42024",
    "sg:province":"Reggio Nell'Emilia",
    "sg:tags":[
        "-",
        "agriculture",
        "equipment"
    ],
    "wof:name":"Atlantic Man. (s.r.l.)",
    "wof:placetype":"venue"
},
  "geometry": {"coordinates":[10.565506,44.807617],"type":"Point"}
}