{
  "type": "Feature",
  "properties": {
    "iso:country":"IT",
    "sg:address":"41012 Carpi",
    "sg:city":"Carpi",
    "sg:orig_category":"Macchine, Impianti Ed Attrezzature Per Abbigliamento E Pelletterie",
    "sg:phone":"+39 059 698327",
    "sg:postcode":"41012",
    "sg:province":"Modena",
    "wof:name":"Tex Cam Srl",
    "wof:placetype":"venue"
},
  "geometry": {"coordinates":[10.891506,44.780651],"type":"Point"}
}