{
  "type": "Feature",
  "properties": {
    "iso:country":"IT",
    "sg:address":"Via Asti 63 10026 Santena",
    "sg:city":"Santena",
    "sg:classifiers":[
        {
            "category":"Manufacturing",
            "subcategory":"Rubber & Plastics",
            "type":"Manufacturing & Wholesale Goods"
        }
    ],
    "sg:phone":"+39 011 945 6618",
    "sg:postcode":"10026",
    "sg:province":"Torino",
    "sg:tags":[
        "mould",
        "industry"
    ],
    "wof:name":"Fire Plast Italia Srl",
    "wof:placetype":"venue"
},
  "geometry": {"coordinates":[8.7059354782,44.9233474731],"type":"Point"}
}