{
  "type": "Feature",
  "properties": {
    "iso:country":"IT",
    "sg:address":"6, Strada Attiraglio 41100 Modena",
    "sg:city":"Modena",
    "sg:classifiers":[
        {
            "category":"Manufacturing",
            "subcategory":"Lumber",
            "type":"Manufacturing & Wholesale Goods"
        }
    ],
    "sg:phone":"+39 39059312089",
    "sg:postcode":"41100",
    "sg:province":"Modena",
    "sg:tags":[
        "wood"
    ],
    "wof:name":"Baroni S.r.l.",
    "wof:placetype":"venue"
},
  "geometry": {"coordinates":[10.933679,44.654438],"type":"Point"}
}