{
  "type": "Feature",
  "properties": {
    "addr:full":"00040 Pomezia Pomezia Roma 00040",
    "addr:postcode":"00040;roma 00040",
    "iso:country":"IT",
    "sg:address":"00040 Pomezia",
    "sg:city":"Pomezia",
    "sg:orig_category":"Vetro: Prodotti E Lavorazioni",
    "sg:phone":"+39 06 912 1949",
    "sg:postcode":"00040",
    "sg:province":"Roma",
    "wof:name":"Solar Films Snc",
    "wof:placetype":"venue"
},
  "geometry": {"coordinates":[12.502442,41.671551],"type":"Point"}
}