{
  "type": "Feature",
  "properties": {
    "addr:full":"117, Via Piave 50050 Cerreto Guidi Cerreto Guidi Firenze 50050",
    "addr:housenumber":"117",
    "addr:postcode":"50050;50050",
    "addr:street":"Via Piave",
    "iso:country":"IT",
    "sg:address":"117, Via Piave 50050 Cerreto Guidi",
    "sg:city":"Cerreto Guidi",
    "sg:classifiers":[
        {
            "category":"Personal",
            "subcategory":"Shoe Repair & Shine",
            "type":"Services"
        }
    ],
    "sg:phone":"+39 39057155144",
    "sg:postcode":"50050",
    "sg:province":"Firenze",
    "sg:tags":[
        "leather"
    ],
    "wof:name":"Gestione Industrie Pelletterie S.r.l.",
    "wof:placetype":"venue"
},
  "geometry": {"coordinates":[11.256902,43.768734],"type":"Point"}
}