{
  "type": "Feature",
  "properties": {
    "iso:country":"IT",
    "sg:address":"37135 Verona",
    "sg:city":"Verona",
    "sg:orig_category":"Autotrasporti",
    "sg:phone":"+39 045 505555",
    "sg:postcode":"37135",
    "sg:province":"Verona",
    "sg:website":"http://www.meneghellotrasporti.com",
    "wof:name":"Meneghello Trasporti Snc",
    "wof:placetype":"venue"
},
  "geometry": {"coordinates":[10.974191,45.412876],"type":"Point"}
}