{
  "type": "Feature",
  "properties": {
    "iso:country":"IT",
    "sg:address":"37126 Verona",
    "sg:city":"Verona",
    "sg:orig_category":"Consulenza Assicurativa",
    "sg:phone":"+39 045 830 0333",
    "sg:postcode":"37126",
    "sg:province":"Verona",
    "wof:name":"Dival Ras",
    "wof:placetype":"venue"
},
  "geometry": {"coordinates":[10.988317,45.447773],"type":"Point"}
}