{
  "type": "Feature",
  "properties": {
    "iso:country":"IT",
    "sg:address":"20020 Arese",
    "sg:city":"Arese",
    "sg:orig_category":"Imballaggi In Legno",
    "sg:phone":"+39 02 938 0362",
    "sg:postcode":"20020",
    "sg:province":"Milano",
    "sg:website":"http://www.imexpo.it",
    "wof:name":"Imballaggi Export Logistics And Packaging Srl",
    "wof:placetype":"venue"
},
  "geometry": {"coordinates":[9.08888,45.534298],"type":"Point"}
}