{
  "type": "Feature",
  "properties": {
    "iso:country":"IT",
    "sg:address":"06121 Perugia",
    "sg:city":"Perugia",
    "sg:orig_category":"Dolciumi E Gelati",
    "sg:phone":"+39 075 36034",
    "sg:postcode":"06121",
    "sg:province":"Perugia",
    "wof:name":"Antica Dolciaria Perugina Srl",
    "wof:placetype":"venue"
},
  "geometry": {"coordinates":[12.292624,43.146118],"type":"Point"}
}