{
  "type": "Feature",
  "properties": {
    "iso:country":"IT",
    "sg:address":"00155 Roma",
    "sg:city":"Roma",
    "sg:orig_category":"Arredo Cucina Ed Elettrodomestici. Elettrodomestici",
    "sg:phone":"+39 06 228 1533",
    "sg:postcode":"00155",
    "sg:province":"Roma",
    "wof:name":"Soc. Generale Rappresentanze Srl",
    "wof:placetype":"venue"
},
  "geometry": {"coordinates":[12.608181,41.887684],"type":"Point"}
}