{
  "type": "Feature",
  "properties": {
    "iso:country":"IT",
    "sg:address":"14, Via Dei Rivi 29020 Gossolengo",
    "sg:city":"Gossolengo",
    "sg:classifiers":[
        {
            "category":"Professional",
            "subcategory":"Engineering",
            "type":"Services"
        }
    ],
    "sg:phone":"+39 0523 779121",
    "sg:postcode":"29020",
    "sg:province":"Piacenza",
    "sg:tags":[
        "machine",
        "-",
        "mechanical"
    ],
    "wof:name":"C.m.o.2. (s.r.l.)",
    "wof:placetype":"venue"
},
  "geometry": {"coordinates":[9.621715,45.002178],"type":"Point"}
}