{
  "type": "Feature",
  "properties": {
    "iso:country":"IT",
    "sg:address":"00040 Ardea",
    "sg:city":"Ardea",
    "sg:orig_category":"Legno E Semilavorati",
    "sg:phone":"+39 06 913 5088",
    "sg:postcode":"00040",
    "sg:province":"Roma",
    "wof:name":"Loconte Felice",
    "wof:placetype":"venue"
},
  "geometry": {"coordinates":[12.517671,41.908344],"type":"Point"}
}