{
  "type": "Feature",
  "properties": {
    "iso:country":"IT",
    "sg:address":"35020 Legnaro",
    "sg:city":"Legnaro",
    "sg:orig_category":"Materiali Semilavorati Metallici",
    "sg:phone":"+39 049 790800",
    "sg:postcode":"35020",
    "sg:province":"Padova",
    "wof:name":"Ilva Spa",
    "wof:placetype":"venue"
},
  "geometry": {"coordinates":[11.909371,45.327084],"type":"Point"}
}