{
  "type": "Feature",
  "properties": {
    "addr:full":"Via Manzoni 7; Milano",
    "addr:housenumber":"7",
    "addr:street":"Via Manzoni",
    "iso:country":"IT",
    "sg:address":"Via Manzoni 7; Milano",
    "sg:classifiers":[
        {
            "category":"Banks & Credit Unions",
            "subcategory":"Bank",
            "type":"Services"
        }
    ],
    "sg:phone":"+39 02 722541",
    "wof:name":"Banca Popolare Di Bergamo, Credito Varesino Scarl",
    "wof:placetype":"venue"
},
  "geometry": {"coordinates":[9.191196,45.468601],"type":"Point"}
}