{
  "type": "Feature",
  "properties": {
    "iso:country":"IT",
    "sg:address":"45026 Lendinara",
    "sg:city":"Lendinara",
    "sg:orig_category":"Arredo Cucina Ed Elettrodomestici. Elettrodomestici",
    "sg:phone":"+39 0425 641891",
    "sg:postcode":"45026",
    "sg:province":"Rovigo",
    "wof:name":"Timaco U. Di Timaco Natalino (s.a.s.)",
    "wof:placetype":"venue"
},
  "geometry": {"coordinates":[11.591523,45.07663],"type":"Point"}
}