{
  "type": "Feature",
  "properties": {
    "iso:country":"IT",
    "sg:address":"Via Torri Bianche 1 20059 Vimercate",
    "sg:city":"Vimercate",
    "sg:classifiers":[
        {
            "category":"Manufacturing",
            "subcategory":"Rubber & Plastics",
            "type":"Manufacturing & Wholesale Goods"
        }
    ],
    "sg:phone":"+39 039 60161",
    "sg:postcode":"20059",
    "sg:province":"Milano",
    "sg:tags":[
        "hose"
    ],
    "sg:website":"www.alfagomma.com",
    "wof:name":"Alfa Gomma Spa",
    "wof:placetype":"venue"
},
  "geometry": {"coordinates":[9.359053,45.60162],"type":"Point"}
}