{
  "type": "Feature",
  "properties": {
    "iso:country":"IT",
    "sg:address":"95014 Giarre",
    "sg:city":"Giarre",
    "sg:orig_category":"Ospedali E Servizi Sanitari. Servizi Sociali. Associazioni Ed Organismi Di Interesse Pubblico",
    "sg:phone":"+39 095 779 1325",
    "sg:postcode":"95014",
    "sg:province":"Catania",
    "wof:name":"Ambulanze Aurora Associazione",
    "wof:placetype":"venue"
},
  "geometry": {"coordinates":[15.166833,37.72337],"type":"Point"}
}