{
  "type": "Feature",
  "properties": {
    "iso:country":"IT",
    "sg:address":"10123 Torino",
    "sg:city":"Torino",
    "sg:orig_category":"Servizi E Lavori Per Abbigliamento E Pelletterie",
    "sg:phone":"+39 011 545087",
    "sg:postcode":"10123",
    "sg:province":"Torino",
    "wof:name":"Carella Giuseppina",
    "wof:placetype":"venue"
},
  "geometry": {"coordinates":[7.586685,45.021263],"type":"Point"}
}