{
  "type": "Feature",
  "properties": {
    "addr:full":"57017 Stagno Stagno Livorno 57017",
    "addr:postcode":"57017;57017",
    "iso:country":"IT",
    "sg:address":"57017 Stagno",
    "sg:city":"Stagno",
    "sg:orig_category":"Prodotti Di Base E Forniture Per Industria Alimentare E Bevande. Carta, Cartone E Prodotti Primari. Forniture Per Attivita' Commerciali Ed Artigianali",
    "sg:phone":"+39 0586 942040",
    "sg:postcode":"57017",
    "sg:province":"Livorno",
    "wof:name":"La Casa Della Carta",
    "wof:placetype":"venue"
},
  "geometry": {"coordinates":[10.3519515991,43.5796318054],"type":"Point"}
}