{
  "type": "Feature",
  "properties": {
    "iso:country":"IT",
    "sg:address":"20020 Arese",
    "sg:city":"Arese",
    "sg:orig_category":"Articoli Da Regalo. Shopping. Regalistica Aziendale",
    "sg:phone":"+39 02 9358 9462",
    "sg:postcode":"20020",
    "sg:province":"Milano",
    "sg:website":"http://www.goccedarte.com",
    "wof:name":"Gocce D'arte",
    "wof:placetype":"venue"
},
  "geometry": {"coordinates":[9.080128,45.552692],"type":"Point"}
}