{
  "type": "Feature",
  "properties": {
    "iso:country":"IT",
    "sg:address":"Via Laghetto, 817 - Tipano 47023 Cesena",
    "sg:city":"Cesena",
    "sg:classifiers":[
        {
            "category":"Transit Center",
            "subcategory":"Freight",
            "type":"Transportation"
        }
    ],
    "sg:phone":"+39 0547 661627",
    "sg:postcode":"47023",
    "sg:province":"Forl\u00ec-Cesena",
    "sg:tags":[
        "food"
    ],
    "wof:name":"Legni Trasporti Srl",
    "wof:placetype":"venue"
},
  "geometry": {"coordinates":[12.2033672333,44.1177749634],"type":"Point"}
}