{
  "type": "Feature",
  "properties": {
    "iso:country":"IT",
    "sg:address":"93100 Caltanissetta",
    "sg:city":"Caltanissetta",
    "sg:orig_category":"Arredamenti - Vendita Al Dettaglio",
    "sg:phone":"+39 0934 575826",
    "sg:postcode":"93100",
    "sg:province":"Caltanissetta",
    "sg:website":"http://www.raimondicucine.it",
    "wof:name":"Raimondi Sistemi Componibili Srl",
    "wof:placetype":"venue"
},
  "geometry": {"coordinates":[14.030454,37.454559],"type":"Point"}
}