{
  "type": "Feature",
  "properties": {
    "iso:country":"IT",
    "sg:address":"Via Dell' Industria 58022 Follonica",
    "sg:city":"Follonica",
    "sg:classifiers":[
        {
            "category":"Wholesale",
            "subcategory":"Machinery & Supplies",
            "type":"Manufacturing & Wholesale Goods"
        }
    ],
    "sg:phone":"+39 39056651340",
    "sg:postcode":"58022",
    "sg:province":"Grosseto",
    "sg:tags":[
        "-",
        "agriculture",
        "equipment"
    ],
    "wof:name":"C.r.f. Costruzioni S.r.l.",
    "wof:placetype":"venue"
},
  "geometry": {"coordinates":[10.786094,42.933495],"type":"Point"}
}