{
  "type": "Feature",
  "properties": {
    "iso:country":"IT",
    "sg:address":"41043 Formigine",
    "sg:city":"Formigine",
    "sg:orig_category":"Automazione E Robotica - Apparecchiature E Componenti",
    "sg:phone":"+39 059 557325",
    "sg:postcode":"41043",
    "sg:province":"Modena",
    "wof:name":"Sigmat Srl",
    "wof:placetype":"venue"
},
  "geometry": {"coordinates":[10.935554,44.554535],"type":"Point"}
}