{
  "type": "Feature",
  "properties": {
    "addr:full":"103/b, Via Regina Margherita 30014 Cavarzere Cavarzere Venezia 30014",
    "addr:housenumber":"103 / b",
    "addr:postcode":"30014;30014",
    "addr:street":"Regina Margherita",
    "iso:country":"IT",
    "sg:address":"103/b, Via Regina Margherita 30014 Cavarzere",
    "sg:city":"Cavarzere",
    "sg:classifiers":[
        {
            "category":"Autos & Motor Vehicles",
            "subcategory":"Automobile Sales",
            "type":"Retail Goods"
        }
    ],
    "sg:phone":"+39 39042651004",
    "sg:postcode":"30014",
    "sg:province":"Venezia",
    "sg:tags":[
        "industrial"
    ],
    "wof:name":"Crivellaro Pasquale",
    "wof:placetype":"venue"
},
  "geometry": {"coordinates":[12.338784,45.434338],"type":"Point"}
}