{
  "type": "Feature",
  "properties": {
    "addr:full":"80, Via Dei Perlar 37135 Verona Verona Verona 37135",
    "addr:postcode":"37135;37135",
    "addr:street":"Via Dei Perlar",
    "iso:country":"IT",
    "sg:address":"80, Via Dei Perlar 37135 Verona",
    "sg:city":"Verona",
    "sg:classifiers":[
        {
            "category":"Wholesale",
            "subcategory":"Machinery & Supplies",
            "type":"Manufacturing & Wholesale Goods"
        }
    ],
    "sg:phone":"+39 39045580801",
    "sg:postcode":"37135",
    "sg:province":"Verona",
    "sg:tags":[
        "equipment",
        "precision"
    ],
    "wof:name":"S.t.a.s. (s.r.l.)",
    "wof:placetype":"venue"
},
  "geometry": {"coordinates":[10.9710483551,45.409198761],"type":"Point"}
}