{
  "type": "Feature",
  "properties": {
    "iso:country":"IT",
    "sg:address":"25, Via Battiana 13853 Lessona",
    "sg:city":"Lessona",
    "sg:classifiers":[
        {
            "category":"Manufacturing",
            "subcategory":"Metals",
            "type":"Manufacturing & Wholesale Goods"
        }
    ],
    "sg:phone":"+39 39015983976",
    "sg:postcode":"13853",
    "sg:province":"Biella",
    "sg:tags":[
        "metallurgy",
        "metalworking"
    ],
    "wof:name":"Fonderia Fratelli Zerbetto (s.n.c.)",
    "wof:placetype":"venue"
},
  "geometry": {"coordinates":[8.2173480988,45.5391082764],"type":"Point"}
}