{
  "type": "Feature",
  "properties": {
    "addr:full":"25055 Pisogne Pisogne Brescia 25055",
    "addr:postcode":"25055;25055",
    "iso:country":"IT",
    "sg:address":"25055 Pisogne",
    "sg:city":"Pisogne",
    "sg:orig_category":"Bagno - Accessori E Mobili",
    "sg:phone":"+39 036 488 0447",
    "sg:postcode":"25055",
    "sg:province":"Brescia",
    "wof:name":"Rubi Zeta Di Zanardi G. & A. Snc",
    "wof:placetype":"venue"
},
  "geometry": {"coordinates":[10.139048,45.8064],"type":"Point"}
}