{
  "type": "Feature",
  "properties": {
    "addr:full":"47023 Cesena Cesena Forl\u00ec-Cesena 47023",
    "addr:postcode":"47023;47023",
    "iso:country":"IT",
    "sg:address":"47023 Cesena",
    "sg:city":"Cesena",
    "sg:classifiers":[
        {
            "category":"Shopping",
            "subcategory":"Gifts & Souvenirs",
            "type":"Retail Goods"
        }
    ],
    "sg:phone":"+39 0547 384213",
    "sg:postcode":"47023",
    "sg:province":"Forl\u00ec-Cesena",
    "sg:tags":[
        "gifts",
        "business"
    ],
    "wof:name":"Soqquadro Di Alma Compagnone",
    "wof:placetype":"venue"
},
  "geometry": {"coordinates":[12.269052,44.159084],"type":"Point"}
}