{
  "type": "Feature",
  "properties": {
    "addr:full":"Via F.ll. Verra 56 10080 Ozegna Ozegna Torino 10080",
    "addr:housenumber":"56",
    "addr:postcode":"10080;10080",
    "addr:street":"Via F.Ll. Verra",
    "iso:country":"IT",
    "sg:address":"Via F.ll. Verra 56 10080 Ozegna",
    "sg:city":"Ozegna",
    "sg:classifiers":[
        {
            "category":"Health Services",
            "subcategory":"Nursing And Care Facility",
            "type":"Services"
        }
    ],
    "sg:phone":"+39 0124 26305",
    "sg:postcode":"10080",
    "sg:province":"Torino",
    "sg:tags":[
        "industrial",
        "robot"
    ],
    "wof:name":"Asmut Srl",
    "wof:placetype":"venue"
},
  "geometry": {"coordinates":[7.686619,45.07056],"type":"Point"}
}