{
  "type": "Feature",
  "properties": {
    "iso:country":"IT",
    "sg:address":"20144 Milano",
    "sg:city":"Milano",
    "sg:orig_category":"Cinematografia E Radiotelevisione",
    "sg:phone":"+39 02 424121",
    "sg:postcode":"20144",
    "sg:province":"Milano",
    "wof:name":"Brw & Partners S.r.l.",
    "wof:placetype":"venue"
},
  "geometry": {"coordinates":[9.15175,45.450188],"type":"Point"}
}