{
  "type": "Feature",
  "properties": {
    "iso:country":"IT",
    "sg:address":"18, Via Ca' Negri 35044 Montagnana",
    "sg:city":"Montagnana",
    "sg:classifiers":[
        {
            "category":"Manufacturing",
            "subcategory":"Lumber",
            "type":"Manufacturing & Wholesale Goods"
        }
    ],
    "sg:phone":"+39 0429 800360",
    "sg:postcode":"35044",
    "sg:province":"Padova",
    "sg:tags":[
        "wood"
    ],
    "wof:name":"Padana Mobili (s.r.l.)",
    "wof:placetype":"venue"
},
  "geometry": {"coordinates":[11.494862,45.218914],"type":"Point"}
}