{
  "type": "Feature",
  "properties": {
    "iso:country":"IT",
    "sg:address":"10036 Settimo Torinese",
    "sg:city":"Settimo Torinese",
    "sg:orig_category":"Utensili Meccanici E Materiali",
    "sg:phone":"+39 011 897 7540",
    "sg:postcode":"10036",
    "sg:province":"Torino",
    "sg:website":"http://www.della-ferrera.com",
    "wof:name":"Della Ferrera Srl",
    "wof:placetype":"venue"
},
  "geometry": {"coordinates":[7.750926,45.150932],"type":"Point"}
}