{
  "type": "Feature",
  "properties": {
    "iso:country":"IT",
    "sg:address":"62010 Montecassiano",
    "sg:city":"Montecassiano",
    "sg:orig_category":"Prodotti E Manufatti In Gomma. Servizi E Lavori Industria Della Gomma. Ricambi E Componenti Dei Mezzi Di Trasporto. Riparazione Dei Mezzi Di Trasporto",
    "sg:phone":"+39 0733 290066",
    "sg:postcode":"62010",
    "sg:province":"Macerata",
    "wof:name":"Comebo Gomme",
    "wof:placetype":"venue"
},
  "geometry": {"coordinates":[13.4343290329,43.3471984863],"type":"Point"}
}