{
  "type": "Feature",
  "properties": {
    "iso:country":"IT",
    "sg:address":"47824 Poggio Berni",
    "sg:city":"Poggio Berni",
    "sg:orig_category":"Minuterie Metalliche E Ferramenta",
    "sg:phone":"+39 0541 627025",
    "sg:postcode":"47824",
    "sg:province":"Rimini",
    "wof:name":"C.m.s. Snc Di Monti Lorenzo Mario & C",
    "wof:placetype":"venue"
},
  "geometry": {"coordinates":[12.4136447906,44.0496902466],"type":"Point"}
}