{
  "type": "Feature",
  "properties": {
    "iso:country":"IT",
    "sg:address":"36050 Bolzano Vicentino",
    "sg:city":"Bolzano Vicentino",
    "sg:orig_category":"Motocicli E Motocarri Accessori E Parti - Produzione E Ingrosso",
    "sg:phone":"+39 0444 357936",
    "sg:postcode":"36050",
    "sg:province":"Vicenza",
    "sg:website":"http://www.ramirez.it",
    "wof:name":"P.f.r. Srl",
    "wof:placetype":"venue"
},
  "geometry": {"coordinates":[11.6231021881,45.6027984619],"type":"Point"}
}