{
  "type": "Feature",
  "properties": {
    "iso:country":"IT",
    "sg:address":"35020 Albignasego",
    "sg:city":"Albignasego",
    "sg:orig_category":"Servizi E Lavori Per Ecologia E Smaltimento Rifiuti",
    "sg:phone":"+39 049 711182",
    "sg:postcode":"35020",
    "sg:province":"Padova",
    "wof:name":"Maroncelli Snc Di Maroncelli Mario & C.",
    "wof:placetype":"venue"
},
  "geometry": {"coordinates":[11.863477,45.349552],"type":"Point"}
}