{
  "type": "Feature",
  "properties": {
    "addr:full":"Strada Di Settimo 154 10156 Torino Torino Torino 10156",
    "addr:housenumber":"154",
    "addr:postcode":"10156;10156",
    "addr:street":"Strada Di Settimo",
    "iso:country":"IT",
    "sg:address":"Strada Di Settimo 154 10156 Torino",
    "sg:city":"Torino",
    "sg:orig_category":"Magnetic Tools",
    "sg:phone":"+39 011 273 3588",
    "sg:postcode":"10156",
    "sg:province":"Torino",
    "sg:website":"www.firmagnetic.com",
    "wof:name":"Firma S.r.l.",
    "wof:placetype":"venue"
},
  "geometry": {"coordinates":[7.736893,45.135956],"type":"Point"}
}