{
  "type": "Feature",
  "properties": {
    "iso:country":"IT",
    "sg:address":"20094 Corsico",
    "sg:city":"Corsico",
    "sg:orig_category":"Gioielleria, Oreficeria E Argenteria",
    "sg:phone":"+39 02 449 1037",
    "sg:postcode":"20094",
    "sg:province":"Milano",
    "wof:name":"Olivi Srl",
    "wof:placetype":"venue"
},
  "geometry": {"coordinates":[9.115758,45.432709],"type":"Point"}
}