{
  "type": "Feature",
  "properties": {
    "addr:full":"87070 Rocca Imperiale Marina Cosenza 87070",
    "addr:postcode":"87070;87070",
    "iso:country":"IT",
    "sg:address":"87070 Rocca Imperiale Marina",
    "sg:orig_category":"Musica",
    "sg:phone":"+39 0981 933117",
    "sg:postcode":"87070",
    "sg:province":"Cosenza",
    "wof:name":"Fbt Elettronica Spa",
    "wof:placetype":"venue"
},
  "geometry": {"coordinates":[16.2538089752,39.2982635498],"type":"Point"}
}