{
  "type": "Feature",
  "properties": {
    "iso:country":"IT",
    "sg:address":"40057 Granarolo Emilia",
    "sg:orig_category":"Macchine, Impianti Ed Attrezzature Industria Chimica. Attrezzature E Forniture Per Officine Riparazione E Servizi Ausiliari",
    "sg:phone":"+39 051 761294",
    "sg:postcode":"40057",
    "sg:province":"Bologna",
    "wof:name":"Boss Div. Saico Spa",
    "wof:placetype":"venue"
},
  "geometry": {"coordinates":[11.442793,44.549309],"type":"Point"}
}