{
  "type": "Feature",
  "properties": {
    "iso:country":"IT",
    "sg:address":"58033 Castel Del Piano",
    "sg:city":"Castel del Piano",
    "sg:orig_category":"Caminetti, Forni Da Giardino E Barbecues",
    "sg:phone":"+39 0564 955303",
    "sg:postcode":"58033",
    "sg:province":"Grosseto",
    "wof:name":"Perugini Di Fazzi Lido",
    "wof:placetype":"venue"
},
  "geometry": {"coordinates":[11.537359,42.890606],"type":"Point"}
}