{
  "type": "Feature",
  "properties": {
    "iso:country":"IT",
    "sg:address":"Via Dell Industria 11 47832 San Clemente",
    "sg:city":"San Clemente",
    "sg:classifiers":[
        {
            "category":"Utilities",
            "subcategory":"Recycling",
            "type":"Services"
        }
    ],
    "sg:phone":"+39 0541 988953",
    "sg:postcode":"47832",
    "sg:province":"Rimini",
    "sg:tags":[
        "vehicle",
        "truck",
        "accessory"
    ],
    "sg:website":"www.montanaritende.it",
    "wof:name":"Montanari Narcisio & C. Snc",
    "wof:placetype":"venue"
},
  "geometry": {"coordinates":[12.639709,43.977371],"type":"Point"}
}