{
  "type": "Feature",
  "properties": {
    "iso:country":"IT",
    "sg:address":"23844 Sirone",
    "sg:city":"Sirone",
    "sg:orig_category":"Macchine Utensili E Impianti",
    "sg:phone":"+39 031 851044",
    "sg:postcode":"23844",
    "sg:province":"Lecco",
    "wof:name":"S.g.m. Spa",
    "wof:placetype":"venue"
},
  "geometry": {"coordinates":[9.317825,45.78194],"type":"Point"}
}