{
  "type": "Feature",
  "properties": {
    "iso:country":"IT",
    "sg:address":"Via Fucine 6 25060 Tavernole Sul Mella",
    "sg:city":"Tavernole sul Mella",
    "sg:classifiers":[
        {
            "category":"Building & Trades",
            "subcategory":"Pest Control",
            "type":"Services"
        }
    ],
    "sg:phone":"+39 030 922 0297",
    "sg:postcode":"25060",
    "sg:province":"Brescia",
    "sg:tags":[
        "wood",
        "painting",
        "preserving"
    ],
    "sg:website":"www.rainbowgraphics.it",
    "wof:name":"Rainbow Graphics Di Camanini Luciano",
    "wof:placetype":"venue"
},
  "geometry": {"coordinates":[10.243038,45.746693],"type":"Point"}
}