{
  "type": "Feature",
  "properties": {
    "addr:full":"35, Via Grandi Achille 20091 Bresso Bresso Milano 20091",
    "addr:postcode":"20091;20091",
    "addr:street":"Via Grandi Achille",
    "iso:country":"IT",
    "sg:address":"35, Via Grandi Achille 20091 Bresso",
    "sg:city":"Bresso",
    "sg:classifiers":[
        {
            "category":"Shopping",
            "subcategory":"Computers & Home Electronics",
            "type":"Retail Goods"
        }
    ],
    "sg:phone":"+39 02 6650 0284",
    "sg:postcode":"20091",
    "sg:province":"Milano",
    "sg:tags":[
        "electronic",
        "electrical",
        "equipment"
    ],
    "wof:name":"Sesamo Distribuzione Lombardia Srl",
    "wof:placetype":"venue"
},
  "geometry": {"coordinates":[9.197551,45.544338],"type":"Point"}
}