{
  "type": "Feature",
  "properties": {
    "addr:full":"Via Monticella 14 16 18 25050 Rodengo Saiano Brescia 25050",
    "addr:housenumber":"14 16 18",
    "addr:postcode":"25050;25050",
    "addr:street":"Via Monticella",
    "iso:country":"IT",
    "sg:address":"Via Monticella 14 16 18 25050 Rodengo Saiano",
    "sg:classifiers":[
        {
            "category":"Manufacturing",
            "subcategory":"Rubber & Plastics",
            "type":"Manufacturing & Wholesale Goods"
        }
    ],
    "sg:phone":"+39 030 681 1045",
    "sg:postcode":"25050",
    "sg:province":"Brescia",
    "sg:tags":[
        "decoration",
        "article"
    ],
    "sg:website":"www.alba2.com",
    "wof:name":"Alba Due Mpm Srl",
    "wof:placetype":"venue"
},
  "geometry": {"coordinates":[10.222958,45.539829],"type":"Point"}
}