{
  "type": "Feature",
  "properties": {
    "addr:full":"2, Via Colombaie 56020 Santa Maria A Monte Santa Maria a Monte Pisa 56020",
    "addr:postcode":"56020;56020",
    "addr:street":"Via Colombaie;Maria A Monte Pisa",
    "iso:country":"IT",
    "sg:address":"2, Via Colombaie 56020 Santa Maria A Monte",
    "sg:city":"Santa Maria a Monte",
    "sg:classifiers":[
        {
            "category":"Personal",
            "subcategory":"Shoe Repair & Shine",
            "type":"Services"
        }
    ],
    "sg:phone":"+39 0587 706270",
    "sg:postcode":"56020",
    "sg:province":"Pisa",
    "sg:tags":[
        "leather"
    ],
    "wof:name":"Calzaturificio Ambra S.a.s.",
    "wof:placetype":"venue"
},
  "geometry": {"coordinates":[10.708566,43.692181],"type":"Point"}
}