{
  "type": "Feature",
  "properties": {
    "addr:full":"10125 Torino Torino Torino 10125",
    "addr:postcode":"10125;10125",
    "iso:country":"IT",
    "sg:address":"10125 Torino",
    "sg:city":"Torino",
    "sg:orig_category":"Impiantistica E Prodotti Tecnologici Per Edilizia. Elettronica Professionale E Di Consumo",
    "sg:phone":"+39 011 655225",
    "sg:postcode":"10125",
    "sg:province":"Torino",
    "wof:name":"Security 2000",
    "wof:placetype":"venue"
},
  "geometry": {"coordinates":[7.682802,45.059528],"type":"Point"}
}