{
  "type": "Feature",
  "properties": {
    "iso:country":"IT",
    "sg:address":"2, Via Del Lavoro 37060 Nogarole Rocca",
    "sg:city":"Nogarole Rocca",
    "sg:classifiers":[
        {
            "category":"Manufacturing",
            "subcategory":"Metals",
            "type":"Manufacturing & Wholesale Goods"
        }
    ],
    "sg:phone":"+39 045 792 5200",
    "sg:postcode":"37060",
    "sg:province":"Verona",
    "sg:tags":[
        "metallurgy",
        "metalworking"
    ],
    "wof:name":"Disall S.r.l.",
    "wof:placetype":"venue"
},
  "geometry": {"coordinates":[10.8570661545,45.2782440186],"type":"Point"}
}