{
  "type": "Feature",
  "properties": {
    "iso:country":"IT",
    "sg:address":"137, Via Panza Ernesto 15046 San Salvatore Monferrato",
    "sg:city":"San Salvatore Monferrato",
    "sg:classifiers":[
        {
            "category":"Shopping",
            "subcategory":"Jewelry",
            "type":"Retail Goods"
        }
    ],
    "sg:phone":"+39 0131 238200",
    "sg:postcode":"15046",
    "sg:province":"Alessandria",
    "sg:tags":[
        "jewellery"
    ],
    "wof:name":"Rimas Gioielli (s.n.c.)",
    "wof:placetype":"venue"
},
  "geometry": {"coordinates":[8.616951,44.913216],"type":"Point"}
}