{
  "type": "Feature",
  "properties": {
    "iso:country":"IT",
    "sg:address":"06128 Perugia",
    "sg:city":"Perugia",
    "sg:classifiers":[
        {
            "category":"Utilities",
            "subcategory":"Mobile Phone",
            "type":"Services"
        }
    ],
    "sg:phone":"+39 075 500 3819",
    "sg:postcode":"06128",
    "sg:province":"Perugia",
    "sg:tags":[
        "equipment",
        "telecommunication",
        "systems",
        "telephony"
    ],
    "wof:name":"Copy Office Srl",
    "wof:placetype":"venue"
},
  "geometry": {"coordinates":[12.360706,43.093658],"type":"Point"}
}