{
  "type": "Feature",
  "properties": {
    "iso:country":"IT",
    "sg:address":"00195 Roma",
    "sg:city":"Roma",
    "sg:classifiers":[
        {
            "category":"Health Services",
            "subcategory":"Health Practitioner",
            "type":"Services"
        }
    ],
    "sg:phone":"+39 06 372 4095",
    "sg:postcode":"00195",
    "sg:province":"Roma",
    "sg:tags":[
        "medici"
    ],
    "wof:name":"Russo Alfio",
    "wof:placetype":"venue"
},
  "geometry": {"coordinates":[12.4556188583,41.9138298035],"type":"Point"}
}