{
  "type": "Feature",
  "properties": {
    "iso:country":"IT",
    "sg:address":"Via Maggiore 81 35045 Ospedaletto Euganeo",
    "sg:city":"Ospedaletto Euganeo",
    "sg:classifiers":[
        {
            "category":"Manufacturing",
            "subcategory":"Food",
            "type":"Manufacturing & Wholesale Goods"
        }
    ],
    "sg:phone":"+39 0429 679060",
    "sg:postcode":"35045",
    "sg:province":"Padova",
    "sg:tags":[
        "agriculture",
        "industry",
        "installation"
    ],
    "sg:website":"www.tecnoimpiantisnc.it",
    "wof:name":"Tecnoimpianti Snc",
    "wof:placetype":"venue"
},
  "geometry": {"coordinates":[11.586555,45.224682],"type":"Point"}
}