{
  "type": "Feature",
  "properties": {
    "iso:country":"IT",
    "sg:address":"31021 Mogliano Veneto",
    "sg:city":"Mogliano Veneto",
    "sg:classifiers":[
        {
            "category":"Utilities",
            "subcategory":"Water",
            "type":"Services"
        }
    ],
    "sg:phone":"+39 041 590 4990",
    "sg:postcode":"31021",
    "sg:province":"Treviso",
    "sg:tags":[
        "organizations",
        "tourist",
        "light",
        "gas",
        "tour",
        "operator",
        "public"
    ],
    "wof:name":"Hotel Duca D'aosta",
    "wof:placetype":"venue"
},
  "geometry": {"coordinates":[12.26002,45.558147],"type":"Point"}
}