{
  "type": "Feature",
  "properties": {
    "iso:country":"IT",
    "sg:address":"20024 Garbagnate Milanese",
    "sg:city":"Garbagnate Milanese",
    "sg:classifiers":[
        {
            "category":"Health Services",
            "subcategory":"Health Practitioner",
            "type":"Services"
        }
    ],
    "sg:phone":"+39 02 995 8461",
    "sg:postcode":"20024",
    "sg:province":"Milano",
    "sg:tags":[
        "medici"
    ],
    "wof:name":"Foschi Cinzia",
    "wof:placetype":"venue"
},
  "geometry": {"coordinates":[9.102575,45.542786],"type":"Point"}
}