{
  "type": "Feature",
  "properties": {
    "iso:country":"IT",
    "sg:address":"180/14, Via Marsala 33100 Udine",
    "sg:city":"Udine",
    "sg:classifiers":[
        {
            "category":"Communications",
            "subcategory":"Television Station",
            "type":"Services"
        }
    ],
    "sg:phone":"+39 0432 522685",
    "sg:postcode":"33100",
    "sg:province":"Udine",
    "sg:tags":[
        "audio-visual"
    ],
    "wof:name":"Abramo",
    "wof:placetype":"venue"
},
  "geometry": {"coordinates":[13.237535,46.053886],"type":"Point"}
}