{
  "type": "Feature",
  "properties": {
    "iso:country":"IT",
    "sg:address":"Viale Sabotino 1a; Milano; 20135",
    "sg:city":"Milano",
    "sg:classifiers":[
        {
            "category":"Banks & Credit Unions",
            "subcategory":"Bank",
            "type":"Services"
        }
    ],
    "sg:phone":"+39 02 545 6881",
    "sg:postcode":"20135",
    "sg:province":"Milano",
    "wof:name":"Banca Di Roma",
    "wof:placetype":"venue"
},
  "geometry": {"coordinates":[9.196852,45.450943],"type":"Point"}
}