{
  "type": "Feature",
  "properties": {
    "iso:country":"IT",
    "sg:address":"20010 Bareggio",
    "sg:city":"Bareggio",
    "sg:orig_category":"Forniture Per Abbigliamento E Pelletterie. Forniture E Materiali Per Imballaggio E Confezionamento",
    "sg:phone":"+39 02 9036 1190",
    "sg:postcode":"20010",
    "sg:province":"Milano",
    "wof:name":"Lustrosa Srl",
    "wof:placetype":"venue"
},
  "geometry": {"coordinates":[9.0038976669,45.475730896],"type":"Point"}
}