{
  "type": "Feature",
  "properties": {
    "iso:country":"IT",
    "sg:address":"Via Villanova, 19 Zona Industriale. 32013 Longarone",
    "sg:city":"Longarone",
    "sg:classifiers":[
        {
            "category":"Manufacturing",
            "subcategory":"Glass & Minerals",
            "type":"Manufacturing & Wholesale Goods"
        }
    ],
    "sg:phone":"+39 0437 770148",
    "sg:postcode":"32013",
    "sg:province":"Belluno",
    "sg:tags":[
        "frame"
    ],
    "sg:website":"www.trevicoliseum.it",
    "wof:name":"Trevi Coliseum Spa",
    "wof:placetype":"venue"
},
  "geometry": {"coordinates":[12.229148,46.265717],"type":"Point"}
}