{
  "type": "Feature",
  "properties": {
    "iso:country":"IT",
    "sg:address":"10145 Torino",
    "sg:city":"Torino",
    "sg:orig_category":"Servizi E Lavori Per Edilizia E Lavori Pubblici. Servizi Ausiliari Di Sorveglianza, Manutenzione E Pulizia",
    "sg:phone":"+39 011 741 0609",
    "sg:postcode":"10145",
    "sg:province":"Torino",
    "wof:name":"Termoidraulica Snc Di G. Selvaggio",
    "wof:placetype":"venue"
},
  "geometry": {"coordinates":[7.641166,45.082664],"type":"Point"}
}