{
  "type": "Feature",
  "properties": {
    "iso:country":"IT",
    "sg:address":"35135 Padova",
    "sg:city":"Padova",
    "sg:orig_category":"Automazione E Macchine Per Ufficio. Forniture Industriali Per Prevenzione, Controllo E Sicurezza",
    "sg:phone":"+39 049 865 8888",
    "sg:postcode":"35135",
    "sg:province":"Padova",
    "wof:name":"Germadata Srl",
    "wof:placetype":"venue"
},
  "geometry": {"coordinates":[11.869109,45.444569],"type":"Point"}
}