{
  "type": "Feature",
  "properties": {
    "iso:country":"IT",
    "sg:address":"24030 Almenno San Bartolomeo",
    "sg:city":"Almenno San Bartolomeo",
    "sg:orig_category":"Carpenterie Meccaniche",
    "sg:phone":"+39 035 553041",
    "sg:postcode":"24030",
    "sg:province":"Bergamo",
    "sg:website":"http://www.krion.it",
    "wof:name":"Krion Srl",
    "wof:placetype":"venue"
},
  "geometry": {"coordinates":[9.584407,45.730507],"type":"Point"}
}