{
  "type": "Feature",
  "properties": {
    "iso:country":"IT",
    "sg:address":"06063 Magione",
    "sg:city":"Magione",
    "sg:orig_category":"Elettrodomestici - Produzione E Ingrosso",
    "sg:phone":"+39 075 847 2120",
    "sg:postcode":"06063",
    "sg:province":"Perugia",
    "sg:website":"http://www.isdnews.it",
    "wof:name":"Isd Interstudio Design Srl",
    "wof:placetype":"venue"
},
  "geometry": {"coordinates":[12.186145,43.119774],"type":"Point"}
}