{
  "type": "Feature",
  "properties": {
    "iso:country":"IT",
    "sg:address":"97, Via Fenilon 37137 Verona",
    "sg:city":"Verona",
    "sg:classifiers":[
        {
            "category":"Parking",
            "subcategory":"Lot",
            "type":"Transportation"
        }
    ],
    "sg:phone":"+39 045 862 2285",
    "sg:postcode":"37137",
    "sg:province":"Verona",
    "sg:tags":[
        "transport",
        "road"
    ],
    "wof:name":"Fert S.p.a.",
    "wof:placetype":"venue"
},
  "geometry": {"coordinates":[10.946245,45.424782],"type":"Point"}
}