{
  "type": "Feature",
  "properties": {
    "iso:country":"IT",
    "sg:address":"66052 Gissi",
    "sg:city":"Gissi",
    "sg:classifiers":[
        {
            "category":"Manufacturing",
            "subcategory":"Chemicals & Compounds",
            "type":"Manufacturing & Wholesale Goods"
        }
    ],
    "sg:phone":"+39 0873 944055",
    "sg:postcode":"66052",
    "sg:province":"Chieti",
    "sg:tags":[
        "product",
        "chemicals",
        "basic"
    ],
    "wof:name":"I.s.a. Engineering Di Ottaviano Stefano",
    "wof:placetype":"venue"
},
  "geometry": {"coordinates":[14.168909,42.351643],"type":"Point"}
}