{
  "type": "Feature",
  "properties": {
    "addr:full":"40055 Villanova Villanova Bologna 40055",
    "addr:housenumber":"40055",
    "addr:postcode":"40055",
    "addr:street":"Villanova Villanova",
    "iso:country":"IT",
    "sg:address":"40055 Villanova",
    "sg:city":"Villanova",
    "sg:orig_category":"Servizi E Lavori Industria Della Gomma",
    "sg:phone":"+39 051 780632",
    "sg:postcode":"40055",
    "sg:province":"Bologna",
    "wof:name":"Cesari Rubber (s.r.l.)",
    "wof:placetype":"venue"
},
  "geometry": {"coordinates":[11.435755,44.498478],"type":"Point"}
}