{
  "type": "Feature",
  "properties": {
    "addr:full":"97015 Modica Modica Ragusa 97015",
    "addr:postcode":"97015;97015",
    "iso:country":"IT",
    "sg:address":"97015 Modica",
    "sg:city":"Modica",
    "sg:orig_category":"Marmo Ed Affini - Lavorazione",
    "sg:phone":"+39 0932 901951",
    "sg:postcode":"97015",
    "sg:province":"Ragusa",
    "wof:name":"Poidomani Luigi",
    "wof:placetype":"venue"
},
  "geometry": {"coordinates":[14.822115,36.852718],"type":"Point"}
}