{
  "type": "Feature",
  "properties": {
    "addr:full":"C.so Umberto I 134 12020 Villafalletto Villafalletto Cuneo 12020",
    "addr:housenumber":"134",
    "addr:postcode":"12020;12020",
    "addr:street":"C.So Umberto I",
    "iso:country":"IT",
    "sg:address":"C.so Umberto I 134 12020 Villafalletto",
    "sg:city":"Villafalletto",
    "sg:classifiers":[
        {
            "category":"Autos & Motor Vehicles",
            "subcategory":"Recreational Vehicle Sales",
            "type":"Retail Goods"
        }
    ],
    "sg:phone":"+39 0171 942032",
    "sg:postcode":"12020",
    "sg:province":"Cuneo",
    "sg:tags":[
        "trailer"
    ],
    "sg:website":"www.balbi.it",
    "wof:name":"Balbi Rimorchi S.r.l.",
    "wof:placetype":"venue"
},
  "geometry": {"coordinates":[7.471043,44.360207],"type":"Point"}
}