{
  "type": "Feature",
  "properties": {
    "iso:country":"IT",
    "sg:address":"24125 Bergamo",
    "sg:city":"Bergamo",
    "sg:orig_category":"Biancheria, Telerie E Coperte. Arredo Camera Letto E Complementi",
    "sg:phone":"+39 035 219220",
    "sg:postcode":"24125",
    "sg:province":"Bergamo",
    "sg:website":"http://www.tastex.it",
    "wof:name":"Tastex Spa",
    "wof:placetype":"venue"
},
  "geometry": {"coordinates":[9.685356,45.699024],"type":"Point"}
}