{
  "type": "Feature",
  "properties": {
    "iso:country":"IT",
    "sg:address":"00176 Roma",
    "sg:city":"Roma",
    "sg:orig_category":"Porte",
    "sg:phone":"+39 06 295934",
    "sg:postcode":"00176",
    "sg:province":"Roma",
    "wof:name":"Euro Door Sas",
    "wof:placetype":"venue"
},
  "geometry": {"coordinates":[12.5351428986,41.886592865],"type":"Point"}
}