{
  "type": "Feature",
  "properties": {
    "iso:country":"IT",
    "sg:address":"34146 Trieste",
    "sg:city":"Trieste",
    "sg:orig_category":"Marmo, Pietre Ed Affini",
    "sg:phone":"+39 040 823266",
    "sg:postcode":"34146",
    "sg:province":"Trieste",
    "sg:website":"http://www.onenet.it/ts/biecher",
    "wof:name":"Biecher Bruno",
    "wof:placetype":"venue"
},
  "geometry": {"coordinates":[13.794121,45.627792],"type":"Point"}
}