{
  "type": "Feature",
  "properties": {
    "iso:country":"IT",
    "sg:address":"16011 Arenzano",
    "sg:city":"Arenzano",
    "sg:orig_category":"Servizi E Lavori Per Agricoltura E Zootecnia. Servizi E Lavori Industria Chimica. Servizi Ausiliari Di Analisi, Controllo E Ricerca",
    "sg:phone":"+39 010 913 0218",
    "sg:postcode":"16011",
    "sg:province":"Genova",
    "wof:name":"Idrabel Italia Srl",
    "wof:placetype":"venue"
},
  "geometry": {"coordinates":[8.677761,44.403706],"type":"Point"}
}