{
  "type": "Feature",
  "properties": {
    "iso:country":"IT",
    "sg:address":"Via Giognano, 3 - Marano 40041 Gaggio Montano",
    "sg:city":"Gaggio Montano",
    "sg:classifiers":[
        {
            "category":"Shopping Center",
            "type":"Public Place"
        }
    ],
    "sg:phone":"+39 0534 47173",
    "sg:postcode":"40041",
    "sg:province":"Bologna",
    "sg:tags":[
        "aluminium",
        "casting"
    ],
    "wof:name":"Officina Meccanica Moruzzi Srl",
    "wof:placetype":"venue"
},
  "geometry": {"coordinates":[11.346481,44.494221],"type":"Point"}
}