{
  "type": "Feature",
  "properties": {
    "iso:country":"IT",
    "sg:address":"06127 Ferro Di Cavallo",
    "sg:orig_category":"Pubblica Amministrazione",
    "sg:phone":"+39 075 50621",
    "sg:postcode":"06127",
    "sg:province":"Perugia",
    "wof:name":"Questura",
    "wof:placetype":"venue"
},
  "geometry": {"coordinates":[12.3534355164,43.1042900085],"type":"Point"}
}