{
  "type": "Feature",
  "properties": {
    "iso:country":"IT",
    "sg:address":"40050 Monte San Pietro",
    "sg:city":"Monte San Pietro",
    "sg:orig_category":"Agricoltura, Orticoltura E Floricoltura",
    "sg:phone":"+39 051 676 8303",
    "sg:postcode":"40050",
    "sg:province":"Bologna",
    "wof:name":"Agriturismo La Torretta",
    "wof:placetype":"venue"
},
  "geometry": {"coordinates":[11.131507,44.437977],"type":"Point"}
}