{
  "type": "Feature",
  "properties": {
    "iso:country":"IT",
    "sg:address":"20124 Milano",
    "sg:city":"Milano",
    "sg:classifiers":[
        {
            "category":"Health Services",
            "subcategory":"Health Practitioner",
            "type":"Services"
        }
    ],
    "sg:phone":"+39 02 2951 0075",
    "sg:postcode":"20124",
    "sg:province":"Milano",
    "sg:tags":[
        "medici"
    ],
    "wof:name":"Marchetti Dr. Franco",
    "wof:placetype":"venue"
},
  "geometry": {"coordinates":[9.207139,45.478241],"type":"Point"}
}