{
  "type": "Feature",
  "properties": {
    "iso:country":"IT",
    "sg:address":"Str. Statale 10 Km 150,400 27040 Cigognola",
    "sg:city":"Cigognola",
    "sg:orig_category":"Chipboards",
    "sg:phone":"+39 0385 257711",
    "sg:postcode":"27040",
    "sg:province":"Pavia",
    "sg:website":"www.xilopan.it",
    "wof:name":"Xilopan Spa",
    "wof:placetype":"venue"
},
  "geometry": {"coordinates":[9.156563,45.185886],"type":"Point"}
}