{
  "type": "Feature",
  "properties": {
    "addr:full":"21011 Casorate Sempione Casorate Sempione Varese 21011",
    "addr:postcode":"21011;21011",
    "iso:country":"IT",
    "sg:address":"21011 Casorate Sempione",
    "sg:city":"Casorate Sempione",
    "sg:orig_category":"Non-classified Establishments",
    "sg:phone":"+39 0331 295152",
    "sg:postcode":"21011",
    "sg:province":"Varese",
    "wof:name":"Pinato Silvio Di Pinato Maurizio & C Sas",
    "wof:placetype":"venue"
},
  "geometry": {"coordinates":[8.740108,45.672497],"type":"Point"}
}