{
  "type": "Feature",
  "properties": {
    "iso:country":"IT",
    "sg:address":"20124 Milano",
    "sg:city":"Milano",
    "sg:orig_category":"Macchine E Forniture Per Industria Orafa E Per Orologeria",
    "sg:phone":"+39 02 670 4029",
    "sg:postcode":"20124",
    "sg:province":"Milano",
    "wof:name":"Effepielle Di Leoni Paolo",
    "wof:placetype":"venue"
},
  "geometry": {"coordinates":[9.214191,45.486031],"type":"Point"}
}