{
  "type": "Feature",
  "properties": {
    "iso:country":"IT",
    "sg:address":"41019 Soliera",
    "sg:city":"Soliera",
    "sg:orig_category":"Nautica - Equipaggiamenti",
    "sg:phone":"+39 059 566650",
    "sg:postcode":"41019",
    "sg:province":"Modena",
    "sg:website":"http://www.scoutantenne.com",
    "wof:name":"Scout Telecomunicazioni Snc",
    "wof:placetype":"venue"
},
  "geometry": {"coordinates":[10.915816,44.728592],"type":"Point"}
}