{
  "type": "Feature",
  "properties": {
    "iso:country":"IT",
    "sg:address":"20145 Milano",
    "sg:city":"Milano",
    "sg:orig_category":"Pubblica Amministrazione",
    "sg:phone":"+39 02 436436",
    "sg:postcode":"20145",
    "sg:province":"Milano",
    "wof:name":"Forze Armate/esercito/ufficio Leva",
    "wof:placetype":"venue"
},
  "geometry": {"coordinates":[9.1600790024,45.4722557068],"type":"Point"}
}