{
  "type": "Feature",
  "properties": {
    "iso:country":"IT",
    "sg:address":"49, Via Pieve Bassa 36072 Chiampo",
    "sg:city":"Chiampo",
    "sg:classifiers":[
        {
            "category":"Manufacturing",
            "subcategory":"Textiles",
            "type":"Manufacturing & Wholesale Goods"
        }
    ],
    "sg:phone":"+39 0444 623499",
    "sg:postcode":"36072",
    "sg:province":"Vicenza",
    "sg:tags":[
        "leather",
        "raw",
        "material",
        "-"
    ],
    "wof:name":"Conceria Fratelli Pellizzari (s.p.a.)",
    "wof:placetype":"venue"
},
  "geometry": {"coordinates":[11.290175,45.537331],"type":"Point"}
}