{
  "type": "Feature",
  "properties": {
    "iso:country":"IT",
    "sg:address":"2, Via Orti 20122 Milano",
    "sg:city":"Milano",
    "sg:classifiers":[
        {
            "category":"Shopping",
            "subcategory":"Clothing, Apparel, & Fashions",
            "type":"Retail Goods"
        }
    ],
    "sg:phone":"+39 02 5518 1645",
    "sg:postcode":"20122",
    "sg:province":"Milano",
    "sg:tags":[
        "clothes"
    ],
    "wof:name":"Elementi Moda (s.r.l.)",
    "wof:placetype":"venue"
},
  "geometry": {"coordinates":[9.198481,45.454769],"type":"Point"}
}