{
  "type": "Feature",
  "properties": {
    "iso:country":"IT",
    "sg:address":"Corso Garibaldi 153; Fossombrone; 61034",
    "sg:city":"Fossombrone",
    "sg:classifiers":[
        {
            "category":"Banks & Credit Unions",
            "subcategory":"Bank",
            "type":"Services"
        }
    ],
    "sg:phone":"+39 0721 714740",
    "sg:postcode":"61034",
    "sg:province":"Pesaro E Urbino",
    "wof:name":"Banca Delle Marche Spa",
    "wof:placetype":"venue"
},
  "geometry": {"coordinates":[12.809474,43.689697],"type":"Point"}
}