{
  "type": "Feature",
  "properties": {
    "addr:full":"00198 Roma Roma Roma 00198",
    "addr:postcode":"00198;00198",
    "iso:country":"IT",
    "sg:address":"00198 Roma",
    "sg:city":"Roma",
    "sg:orig_category":"Filati E Materie Prime Tessili",
    "sg:phone":"+39 06 855 7580",
    "sg:postcode":"00198",
    "sg:province":"Roma",
    "wof:name":"Nutarelli Amata",
    "wof:placetype":"venue"
},
  "geometry": {"coordinates":[12.4986076355,41.9184074402],"type":"Point"}
}