{
  "type": "Feature",
  "properties": {
    "addr:full":"00138 Roma Roma Roma 00138",
    "addr:postcode":"00138;00138",
    "iso:country":"IT",
    "sg:address":"00138 Roma",
    "sg:city":"Roma",
    "sg:orig_category":"Automobili E Mezzi Di Trasporto",
    "sg:phone":"+39 06 880911",
    "sg:postcode":"00138",
    "sg:province":"Roma",
    "sg:website":"http://www.samocar.it",
    "wof:name":"Sa.mo.car. Spa",
    "wof:placetype":"venue"
},
  "geometry": {"coordinates":[12.514142,41.991802],"type":"Point"}
}