{
  "type": "Feature",
  "properties": {
    "iso:country":"IT",
    "sg:address":"00034 Colleferro",
    "sg:city":"Colleferro",
    "sg:classifiers":[
        {
            "category":"Health Services",
            "subcategory":"Health Practitioner",
            "type":"Services"
        }
    ],
    "sg:phone":"+39 06 9730 4784",
    "sg:postcode":"00034",
    "sg:province":"Roma",
    "sg:tags":[
        "medici"
    ],
    "wof:name":"Ecoerre Srl",
    "wof:placetype":"venue"
},
  "geometry": {"coordinates":[12.476028,41.84063],"type":"Point"}
}