{
  "type": "Feature",
  "properties": {
    "addr:full":"Viale Dell' Economia 36016 Thiene Thiene Vicenza 36016",
    "addr:postcode":"36016;36016",
    "addr:street":"Viale Dell ' Economia",
    "iso:country":"IT",
    "sg:address":"Viale Dell' Economia 36016 Thiene",
    "sg:city":"Thiene",
    "sg:classifiers":[
        {
            "category":"Shopping",
            "subcategory":"Clothing, Apparel, & Fashions",
            "type":"Retail Goods"
        }
    ],
    "sg:phone":"+39 0445 380463",
    "sg:postcode":"36016",
    "sg:province":"Vicenza",
    "sg:tags":[
        "clothes"
    ],
    "wof:name":"Kinder (s.p.a.)",
    "wof:placetype":"venue"
},
  "geometry": {"coordinates":[11.51108,45.706848],"type":"Point"}
}