{
  "type": "Feature",
  "properties": {
    "addr:full":"97100 Ragusa Ragusa Ragusa 97100",
    "addr:postcode":"97100;97100",
    "iso:country":"IT",
    "sg:address":"97100 Ragusa",
    "sg:city":"Ragusa",
    "sg:orig_category":"Servizi Per Lo Sport E Il Tempo Libero. Servizi Al Turismo",
    "sg:phone":"+39 0932 229053",
    "sg:postcode":"97100",
    "sg:province":"Ragusa",
    "wof:name":"Baby Planet Di Dimartino Annamaria",
    "wof:placetype":"venue"
},
  "geometry": {"coordinates":[14.524981,36.786053],"type":"Point"}
}