{
  "type": "Feature",
  "properties": {
    "addr:full":"Via Terracini, 17/19 Ex N 11 20089 Rozzano Rozzano Milano 20089",
    "addr:housenumber":"17 / 19 ex",
    "addr:postcode":"20089;20089",
    "addr:street":"Via Terracini;N 11",
    "iso:country":"IT",
    "sg:address":"Via Terracini, 17/19 Ex N 11 20089 Rozzano",
    "sg:city":"Rozzano",
    "sg:classifiers":[
        {
            "category":"Manufacturing",
            "subcategory":"Glass & Minerals",
            "type":"Manufacturing & Wholesale Goods"
        }
    ],
    "sg:phone":"+39 02 8920 0280",
    "sg:postcode":"20089",
    "sg:province":"Milano",
    "sg:tags":[
        "fibre"
    ],
    "sg:website":"www.resipol.com",
    "wof:name":"Resipol Srl",
    "wof:placetype":"venue"
},
  "geometry": {"coordinates":[9.188141,45.463688],"type":"Point"}
}