{
  "type": "Feature",
  "properties": {
    "addr:full":"80128 Napoli Napoli Napoli 80128",
    "addr:housenumber":"80128",
    "addr:postcode":"80128",
    "iso:country":"IT",
    "sg:address":"80128 Napoli",
    "sg:city":"Napoli",
    "sg:orig_category":"Cancelleria",
    "sg:phone":"+39 081 556 4585",
    "sg:postcode":"80128",
    "sg:province":"Napoli",
    "wof:name":"Rigena",
    "wof:placetype":"venue"
},
  "geometry": {"coordinates":[14.229069,40.856281],"type":"Point"}
}