{
  "type": "Feature",
  "properties": {
    "iso:country":"IT",
    "sg:address":"Via Locchi 19, Trieste, Ts",
    "sg:classifiers":[
        {
            "category":"Banks & Credit Unions",
            "subcategory":"Bank",
            "type":"Services"
        }
    ],
    "wof:name":"Friulia Spa",
    "wof:placetype":"venue"
},
  "geometry": {"coordinates":[13.761062,45.641155],"type":"Point"}
}