{
  "type": "Feature",
  "properties": {
    "iso:country":"IT",
    "sg:address":"Via A. Manzoni 46 20080 Vermezzo",
    "sg:city":"Vermezzo",
    "sg:classifiers":[
        {
            "category":"Industrial Area",
            "type":"Public Place"
        }
    ],
    "sg:phone":"+39 02 944 0839",
    "sg:postcode":"20080",
    "sg:province":"Milano",
    "sg:tags":[
        "pump"
    ],
    "sg:website":"www.stellaom.com",
    "wof:name":"Stella Om Sas",
    "wof:placetype":"venue"
},
  "geometry": {"coordinates":[9.188141,45.463688],"type":"Point"}
}