{
  "type": "Feature",
  "properties": {
    "iso:country":"IT",
    "sg:address":"35122 Padova",
    "sg:city":"Padova",
    "sg:orig_category":"Camere Di Commercio",
    "sg:phone":"+39 049 820 8111",
    "sg:postcode":"35122",
    "sg:province":"Padova",
    "sg:website":"http://www.pd.camcom.it",
    "wof:name":"Camera Di Commercio Industria Artigianato E Agricoltura",
    "wof:placetype":"venue"
},
  "geometry": {"coordinates":[11.870431,45.400311],"type":"Point"}
}