{
  "type": "Feature",
  "properties": {
    "addr:full":"350/b, V. Napoli 80053 Castellammare Di Stabia Castellammare di Stabia Napoli 80053",
    "addr:housenumber":"350 / b v.",
    "addr:postcode":"80053;80053",
    "addr:street":"Napoli",
    "iso:country":"IT",
    "sg:address":"350/b, V. Napoli 80053 Castellammare Di Stabia",
    "sg:city":"Castellammare di Stabia",
    "sg:classifiers":[
        {
            "category":"Food & Beverages",
            "subcategory":"Groceries & Convenience Stores",
            "type":"Retail Goods"
        }
    ],
    "sg:phone":"+39 081 539 1735",
    "sg:postcode":"80053",
    "sg:province":"Napoli",
    "sg:tags":[
        "product",
        "related"
    ],
    "sg:website":"http://www.paginegialle.it/gidal-granarolo",
    "wof:name":"Gidal Spa 'cash & Carry'",
    "wof:placetype":"venue"
},
  "geometry": {"coordinates":[14.4788627625,40.7285270691],"type":"Point"}
}