{
  "type": "Feature",
  "properties": {
    "addr:full":"14049 Nizza Monferrato Nizza Monferrato Asti 14049",
    "addr:postcode":"14049;14049",
    "iso:country":"IT",
    "sg:address":"14049 Nizza Monferrato",
    "sg:city":"Nizza Monferrato",
    "sg:orig_category":"Apparecchiature E Sistemi Per Magazzinaggio E Movimentazione",
    "sg:phone":"+39 0141 793479",
    "sg:postcode":"14049",
    "sg:province":"Asti",
    "wof:name":"Rimam Di Gioanola",
    "wof:placetype":"venue"
},
  "geometry": {"coordinates":[8.355,44.774853],"type":"Point"}
}