{
  "type": "Feature",
  "properties": {
    "addr:full":"24052 Azzano San Paolo Azzano San Paolo Bergamo 24052",
    "addr:postcode":"24052;24052",
    "iso:country":"IT",
    "sg:address":"24052 Azzano San Paolo",
    "sg:city":"Azzano San Paolo",
    "sg:orig_category":"Servizi E Lavori Per Edilizia E Lavori Pubblici. Servizi E Lavori Per Ecologia E Smaltimento Rifiuti",
    "sg:phone":"+39 035 530372",
    "sg:postcode":"24052",
    "sg:province":"Bergamo",
    "wof:name":"A.s.m. Ambiente Servizi Montaggi Srl",
    "wof:placetype":"venue"
},
  "geometry": {"coordinates":[9.663796,45.656708],"type":"Point"}
}