{
  "type": "Feature",
  "properties": {
    "addr:full":"00041 Albano Laziale Albano Laziale Roma 00041",
    "addr:postcode":"00041;00041",
    "addr:street":"Roma",
    "iso:country":"IT",
    "sg:address":"00041 Albano Laziale",
    "sg:city":"Albano Laziale",
    "sg:orig_category":"Chiese Ed Associazioni Religiose",
    "sg:phone":"+39 06 936 9451",
    "sg:postcode":"00041",
    "sg:province":"Roma",
    "wof:name":"Padri Somaschi",
    "wof:placetype":"venue"
},
  "geometry": {"coordinates":[12.657924,41.7178],"type":"Point"}
}