{
  "type": "Feature",
  "properties": {
    "iso:country":"IT",
    "sg:address":"30020 Marcon",
    "sg:city":"Marcon",
    "sg:orig_category":"Arredamenti E Mobili Professionali. Impianti, Attrezzature E Forniture Sanitarie Ed Ospedaliere",
    "sg:phone":"+39 041 595 2522",
    "sg:postcode":"30020",
    "sg:province":"Venezia",
    "wof:name":"Arredi Tecnici Casarin Srl",
    "wof:placetype":"venue"
},
  "geometry": {"coordinates":[12.289915,45.538284],"type":"Point"}
}