{
  "type": "Feature",
  "properties": {
    "iso:country":"IT",
    "sg:address":"Via Padana Superiore 72/74 25080 Mazzano",
    "sg:city":"Mazzano",
    "sg:orig_category":"Glass-fibre Reinforced Plastic Grp Moulds",
    "sg:phone":"+39 030 212 0152",
    "sg:postcode":"25080",
    "sg:province":"Brescia",
    "sg:website":"www.italstampi.it",
    "wof:name":"Italstampi Srl",
    "wof:placetype":"venue"
},
  "geometry": {"coordinates":[10.356923,45.49501],"type":"Point"}
}