{
  "type": "Feature",
  "properties": {
    "iso:country":"IT",
    "sg:address":"23801 Calolziocorte",
    "sg:city":"Calolziocorte",
    "sg:orig_category":"Verniciatura A Fuoco E A Forno",
    "sg:phone":"+39 0341 634878",
    "sg:postcode":"23801",
    "sg:province":"Lecco",
    "wof:name":"Vernislac Srl",
    "wof:placetype":"venue"
},
  "geometry": {"coordinates":[9.441471,45.777538],"type":"Point"}
}