{
  "type": "Feature",
  "properties": {
    "iso:country":"IT",
    "sg:address":"20052 Monza",
    "sg:city":"Monza",
    "sg:orig_category":"Accessori Moda D'abbigliamento",
    "sg:phone":"+39 039 831028",
    "sg:postcode":"20052",
    "sg:province":"Milano",
    "wof:name":"Rival Srl-feltri Cappelli E Confezioni",
    "wof:placetype":"venue"
},
  "geometry": {"coordinates":[9.277159,45.535713],"type":"Point"}
}