{
  "type": "Feature",
  "properties": {
    "addr:full":"28, Via Del Tuscolano 40128 Bologna Bologna Bologna 40128",
    "addr:postcode":"40128;40128",
    "addr:street":"Via Del Tuscolano",
    "iso:country":"IT",
    "sg:address":"28, Via Del Tuscolano 40128 Bologna",
    "sg:city":"Bologna",
    "sg:classifiers":[
        {
            "category":"Utilities",
            "subcategory":"Telephone",
            "type":"Services"
        }
    ],
    "sg:phone":"+39 051 638 0711",
    "sg:postcode":"40128",
    "sg:province":"Bologna",
    "sg:tags":[
        "telecommunication"
    ],
    "wof:name":"Teleimpianti (s.p.a.)",
    "wof:placetype":"venue"
},
  "geometry": {"coordinates":[11.359389,44.535484],"type":"Point"}
}