{
  "type": "Feature",
  "properties": {
    "addr:full":"43, Viale Mosca Zadina Zadina 47042 Cesenatico Cesenatico Forl\u00ec-Cesena 47042",
    "addr:housenumber":"43",
    "addr:postcode":"47042;47042",
    "addr:street":"Viale Mosca Zadina Zadina",
    "iso:country":"IT",
    "sg:address":"43, Viale Mosca Zadina Zadina 47042 Cesenatico",
    "sg:city":"Cesenatico",
    "sg:classifiers":[
        {
            "category":"Travel",
            "subcategory":"Travel Agent",
            "type":"Entertainment"
        }
    ],
    "sg:phone":"+39 39054782209",
    "sg:postcode":"47042",
    "sg:province":"Forl\u00ec-Cesena",
    "sg:tags":[
        "business"
    ],
    "wof:name":"Hotel Beau Soleil",
    "wof:placetype":"venue"
},
  "geometry": {"coordinates":[11.980461,43.994766],"type":"Point"}
}