{
  "type": "Feature",
  "properties": {
    "iso:country":"IT",
    "sg:address":"Piazza San Michele, 7; Lucca; 55100",
    "sg:city":"Lucca",
    "sg:classifiers":[
        {
            "category":"Banks & Credit Unions",
            "subcategory":"Bank",
            "type":"Services"
        }
    ],
    "sg:phone":"+39 0583 9760",
    "sg:postcode":"55100",
    "sg:province":"Lucca",
    "wof:name":"Banca Nazionale Del Lavoro Spa",
    "wof:placetype":"venue"
},
  "geometry": {"coordinates":[10.502225,43.843338],"type":"Point"}
}