{
  "type": "Feature",
  "properties": {
    "iso:country":"IT",
    "sg:address":"81020 Casapulla",
    "sg:city":"Casapulla",
    "sg:orig_category":"Macchine, Impianti Ed Attrezzature Industria Chimica. Prodotti Vari In Metallo. Articoli Per Imballaggio E Confezionamento",
    "sg:phone":"+39 0823 465205",
    "sg:postcode":"81020",
    "sg:province":"Caserta",
    "wof:name":"Tifata Gas Srl",
    "wof:placetype":"venue"
},
  "geometry": {"coordinates":[14.290986,41.086487],"type":"Point"}
}