{
  "type": "Feature",
  "properties": {
    "iso:country":"IT",
    "sg:address":"62, Viale Europa 21017 Samarate",
    "sg:city":"Samarate",
    "sg:classifiers":[
        {
            "category":"Professional",
            "subcategory":"Engineering",
            "type":"Services"
        }
    ],
    "sg:phone":"+39 0331 235353",
    "sg:postcode":"21017",
    "sg:province":"Varese",
    "sg:tags":[
        "machine",
        "-",
        "mechanical"
    ],
    "wof:name":"San Gregorio S.p.a. Fonderia Officina Meccanica",
    "wof:placetype":"venue"
},
  "geometry": {"coordinates":[8.785473,45.610306],"type":"Point"}
}