{
  "type": "Feature",
  "properties": {
    "addr:full":"80125 Napoli Napoli Napoli 80125",
    "addr:housenumber":"80125",
    "addr:postcode":"80125",
    "iso:country":"IT",
    "sg:address":"80125 Napoli",
    "sg:city":"Napoli",
    "sg:classifiers":[
        {
            "category":"Health Services",
            "subcategory":"Health Practitioner",
            "type":"Services"
        }
    ],
    "sg:phone":"+39 081 239 1446",
    "sg:postcode":"80125",
    "sg:province":"Napoli",
    "sg:tags":[
        "medici"
    ],
    "wof:name":"Theo Gennaro",
    "wof:placetype":"venue"
},
  "geometry": {"coordinates":[14.158041954,40.9264831543],"type":"Point"}
}