{
  "type": "Feature",
  "properties": {
    "iso:country":"IT",
    "sg:address":"Via Verdi, 1/3 28060 San Pietro Mosezzo",
    "sg:city":"San Pietro Mosezzo",
    "sg:classifiers":[
        {
            "category":"Food & Beverages",
            "subcategory":"Cheese",
            "type":"Retail Goods"
        }
    ],
    "sg:phone":"+39 0321 468747",
    "sg:postcode":"28060",
    "sg:province":"Novara",
    "wof:name":"Invernizzi Rag. Franco Srl",
    "wof:placetype":"venue"
},
  "geometry": {"coordinates":[8.566253,45.45668],"type":"Point"}
}