{
  "type": "Feature",
  "properties": {
    "addr:full":"Via Privata Eden Fumagalli 20047 Brugherio Brugherio Milano 20047",
    "addr:postcode":"20047;20047",
    "addr:street":"Via Privata Eden Fumagalli",
    "iso:country":"IT",
    "sg:address":"Via Privata Eden Fumagalli 20047 Brugherio",
    "sg:city":"Brugherio",
    "sg:classifiers":[
        {
            "category":"Shopping",
            "subcategory":"Computers & Home Electronics",
            "type":"Retail Goods"
        }
    ],
    "sg:phone":"+39 390 392 0861",
    "sg:postcode":"20047",
    "sg:province":"Milano",
    "sg:tags":[
        "electronic",
        "electrical",
        "equipment"
    ],
    "wof:name":"Candy Elettrodomestici S.r.l.",
    "wof:placetype":"venue"
},
  "geometry": {"coordinates":[9.188141,45.463688],"type":"Point"}
}