{
  "type": "Feature",
  "properties": {
    "iso:country":"IT",
    "sg:address":"Via Provinciale Di Mercatale 152/a 50059 Vinci",
    "sg:city":"Vinci",
    "sg:classifiers":[
        {
            "category":"Professional",
            "subcategory":"Art Services",
            "type":"Services"
        }
    ],
    "sg:phone":"+39 0571 501854",
    "sg:postcode":"50059",
    "sg:province":"Firenze",
    "sg:tags":[
        "glass",
        "article"
    ],
    "sg:website":"www.cristalrobert.it",
    "wof:name":"Cristal Robert Line Di Sani Roberta",
    "wof:placetype":"venue"
},
  "geometry": {"coordinates":[11.256902,43.768734],"type":"Point"}
}