{
  "type": "Feature",
  "properties": {
    "addr:full":"5, Via Torino 20039 Varedo Varedo Milano 20039",
    "addr:postcode":"20039;20039",
    "addr:street":"Via Torino",
    "iso:country":"IT",
    "sg:address":"5, Via Torino 20039 Varedo",
    "sg:city":"Varedo",
    "sg:classifiers":[
        {
            "category":"Shopping",
            "subcategory":"Stationery & Office Supplies",
            "type":"Retail Goods"
        }
    ],
    "sg:phone":"+39 036 258 3225",
    "sg:postcode":"20039",
    "sg:province":"Milano",
    "sg:tags":[
        "professional"
    ],
    "wof:name":"Skema Arredamenti S.r.l.",
    "wof:placetype":"venue"
},
  "geometry": {"coordinates":[9.1756134033,45.5950927734],"type":"Point"}
}