{
  "type": "Feature",
  "properties": {
    "addr:full":"7, Vicolo Billi 95021 Aci Castello Aci Castello Catania 95021",
    "addr:housenumber":"7",
    "addr:postcode":"95021;95021",
    "addr:street":"Vicolo Billi",
    "iso:country":"IT",
    "sg:address":"7, Vicolo Billi 95021 Aci Castello",
    "sg:city":"Aci Castello",
    "sg:classifiers":[
        {
            "category":"Building & Trades",
            "subcategory":"Construction",
            "type":"Services"
        }
    ],
    "sg:phone":"+39 39095270700",
    "sg:postcode":"95021",
    "sg:province":"Catania",
    "sg:tags":[
        "work",
        "public"
    ],
    "wof:name":"G.l.s. Costruzioni S.r.l.",
    "wof:placetype":"venue"
},
  "geometry": {"coordinates":[15.124617,37.557705],"type":"Point"}
}