{
  "type": "Feature",
  "properties": {
    "iso:country":"IT",
    "sg:address":"26 Via Torino, 12040 Vezza D'alba",
    "sg:classifiers":[
        {
            "category":"Banks & Credit Unions",
            "subcategory":"Financial Services",
            "type":"Services"
        }
    ],
    "sg:phone":"+39 0173 659111",
    "sg:postcode":"12040",
    "sg:province":"Cuneo",
    "sg:tags":[
        "banking",
        "finance",
        "insurance"
    ],
    "wof:name":"Banca Di Credito Cooperativo Di Alba Langhe E Roero Scrl",
    "wof:placetype":"venue"
},
  "geometry": {"coordinates":[8.0094823837,44.7612533569],"type":"Point"}
}