{
  "type": "Feature",
  "properties": {
    "addr:full":"Via Pertini 15 42100 Reggio Emilia Reggio Nell'Emilia 42100",
    "addr:housenumber":"15",
    "addr:postcode":"42100;42100",
    "addr:street":"Via Pertini",
    "iso:country":"IT",
    "sg:address":"Via Pertini 15 42100 Reggio Emilia",
    "sg:classifiers":[
        {
            "category":"Food & Beverages",
            "subcategory":"Chocolate",
            "type":"Retail Goods"
        }
    ],
    "sg:phone":"+39 0522 3888",
    "sg:postcode":"42100",
    "sg:province":"Reggio Nell'Emilia",
    "sg:tags":[
        "export"
    ],
    "wof:name":"Re.al. Spa",
    "wof:placetype":"venue"
},
  "geometry": {"coordinates":[10.5926170349,44.7046356201],"type":"Point"}
}