{
  "type": "Feature",
  "properties": {
    "addr:full":"84015 Nocera Superiore Nocera Superiore Salerno 84015",
    "addr:postcode":"84015;84015",
    "iso:country":"IT",
    "sg:address":"84015 Nocera Superiore",
    "sg:city":"Nocera Superiore",
    "sg:orig_category":"Macchine Ed Impianti Per Edilizia E Lavori Pubblici",
    "sg:phone":"+39 081 932493",
    "sg:postcode":"84015",
    "sg:province":"Salerno",
    "wof:name":"Meccanica Meridionale Srl",
    "wof:placetype":"venue"
},
  "geometry": {"coordinates":[14.679022,40.736912],"type":"Point"}
}