{
  "type": "Feature",
  "properties": {
    "iso:country":"IT",
    "sg:address":"23, Viale Dante 53042 Chianciano Terme",
    "sg:city":"Chianciano Terme",
    "sg:classifiers":[
        {
            "category":"Shopping",
            "subcategory":"Computers & Home Electronics",
            "type":"Retail Goods"
        }
    ],
    "sg:phone":"+39 39057831641",
    "sg:postcode":"53042",
    "sg:province":"Siena",
    "sg:tags":[
        "electronic",
        "electrical",
        "equipment"
    ],
    "wof:name":"Movimento Rifondazione Comunista",
    "wof:placetype":"venue"
},
  "geometry": {"coordinates":[11.827817,43.058041],"type":"Point"}
}