{
  "type": "Feature",
  "properties": {
    "iso:country":"IT",
    "sg:address":"159, Via Del Brennero 38100 Trento",
    "sg:city":"Trento",
    "sg:classifiers":[
        {
            "category":"Home & Garden",
            "subcategory":"Home Furnishings",
            "type":"Retail Goods"
        }
    ],
    "sg:phone":"+39 0461 821279",
    "sg:postcode":"38100",
    "sg:province":"Trento",
    "sg:tags":[
        "household"
    ],
    "wof:name":"Piffer Arreda Di Zanetti Ermanno",
    "wof:placetype":"venue"
},
  "geometry": {"coordinates":[11.11496,46.091942],"type":"Point"}
}