{
  "type": "Feature",
  "properties": {
    "iso:country":"IT",
    "sg:address":"51019 Ponte Buggianese",
    "sg:city":"Ponte Buggianese",
    "sg:orig_category":"Macchine, Impianti Ed Attrezzature Per Abbigliamento E Pelletterie",
    "sg:phone":"+39 0572 634994",
    "sg:postcode":"51019",
    "sg:province":"Pistoia",
    "wof:name":"Bg Assistenza Di Gialdini A. Moreno",
    "wof:placetype":"venue"
},
  "geometry": {"coordinates":[10.738632,43.851311],"type":"Point"}
}