{
  "type": "Feature",
  "properties": {
    "addr:full":"Via Paschero 33 12031 Bagnolo Piemonte Bagnolo Piemonte Cuneo 12031",
    "addr:housenumber":"33",
    "addr:postcode":"12031;12031",
    "addr:street":"Via Paschero",
    "iso:country":"IT",
    "sg:address":"Via Paschero 33 12031 Bagnolo Piemonte",
    "sg:city":"Bagnolo Piemonte",
    "sg:classifiers":[
        {
            "category":"Mining & Drilling",
            "type":"Manufacturing & Wholesale Goods"
        }
    ],
    "sg:phone":"+39 0175 391064",
    "sg:postcode":"12031",
    "sg:province":"Cuneo",
    "sg:tags":[
        "quarry"
    ],
    "sg:website":"www.votteroriccardo.com",
    "wof:name":"Vottero Riccardo & C. S.n.c.",
    "wof:placetype":"venue"
},
  "geometry": {"coordinates":[7.318417,44.761803],"type":"Point"}
}