{
  "type": "Feature",
  "properties": {
    "iso:country":"IT",
    "sg:address":"188, Via Crescenzago 20099 Sesto San Giovanni",
    "sg:city":"Sesto San Giovanni",
    "sg:classifiers":[
        {
            "category":"Manufacturing",
            "subcategory":"Rubber & Plastics",
            "type":"Manufacturing & Wholesale Goods"
        }
    ],
    "sg:phone":"+39 02 2247 6787",
    "sg:postcode":"20099",
    "sg:province":"Milano",
    "wof:name":"Fava (s.r.l.)",
    "wof:placetype":"venue"
},
  "geometry": {"coordinates":[9.2407302856,45.4945106506],"type":"Point"}
}