{
  "type": "Feature",
  "properties": {
    "iso:country":"IT",
    "sg:address":"34124 Trieste",
    "sg:city":"Trieste",
    "sg:orig_category":"Servizi Per Aziende, Manifestazioni E Supporto Agli Scambi Commerciali",
    "sg:phone":"+39 040 304888",
    "sg:postcode":"34124",
    "sg:province":"Trieste",
    "sg:website":"http://www.promotrieste.it",
    "wof:name":"Promotrieste - Convention Bureau",
    "wof:placetype":"venue"
},
  "geometry": {"coordinates":[13.767696,45.646229],"type":"Point"}
}