{
  "type": "Feature",
  "properties": {
    "iso:country":"IT",
    "sg:address":"35042 Este",
    "sg:city":"Este",
    "sg:orig_category":"Giocattoli E Giochi - Produzione E Ingrosso",
    "sg:phone":"+39 0429 690620",
    "sg:postcode":"35042",
    "sg:province":"Padova",
    "wof:name":"Mabel Di Bettio Maria Grazia",
    "wof:placetype":"venue"
},
  "geometry": {"coordinates":[11.709725,45.208668],"type":"Point"}
}