{
  "type": "Feature",
  "properties": {
    "addr:full":"Via Merula 1; Vigevano; 27029 Vigevano Pavia 27029",
    "addr:housenumber":"1",
    "addr:postcode":"27029;27029",
    "addr:street":"Via Merula",
    "iso:country":"IT",
    "sg:address":"Via Merula 1; Vigevano; 27029",
    "sg:city":"Vigevano",
    "sg:classifiers":[
        {
            "category":"Banks & Credit Unions",
            "subcategory":"Bank",
            "type":"Services"
        }
    ],
    "sg:phone":"+39 0381 908911",
    "sg:postcode":"27029",
    "sg:province":"Pavia",
    "wof:name":"Banco Ambrosiano Veneto Spa",
    "wof:placetype":"venue"
},
  "geometry": {"coordinates":[8.857281,45.318626],"type":"Point"}
}