{
  "type": "Feature",
  "properties": {
    "iso:country":"IT",
    "sg:address":"24060 Castelli Calepio",
    "sg:city":"Castelli Calepio",
    "sg:orig_category":"Non-classified Establishments",
    "sg:phone":"+39 035 848800",
    "sg:postcode":"24060",
    "sg:province":"Bergamo",
    "wof:name":"Prendi Al Volo Di Seck Ndongo & C. S.a.s.",
    "wof:placetype":"venue"
},
  "geometry": {"coordinates":[9.897128,45.639465],"type":"Point"}
}