{
  "type": "Feature",
  "properties": {
    "iso:country":"IT",
    "sg:address":"Piazza Della Vittoria 22; Fanano; 41021",
    "sg:city":"Fanano",
    "sg:classifiers":[
        {
            "category":"Banks & Credit Unions",
            "subcategory":"Bank",
            "type":"Services"
        }
    ],
    "sg:phone":"+39 0536 69901",
    "sg:postcode":"41021",
    "sg:province":"Modena",
    "wof:name":"Banca Popolare Di Verona",
    "wof:placetype":"venue"
},
  "geometry": {"coordinates":[10.794591,44.208351],"type":"Point"}
}