{
  "type": "Feature",
  "properties": {
    "iso:country":"IT",
    "sg:address":"35, Viale Dell' Artigianato 24049 Verdello",
    "sg:city":"Verdello",
    "sg:classifiers":[
        {
            "category":"Shopping",
            "subcategory":"Jewelry",
            "type":"Retail Goods"
        }
    ],
    "sg:phone":"+39 39035871710",
    "sg:postcode":"24049",
    "sg:province":"Bergamo",
    "sg:tags":[
        "jewellery"
    ],
    "wof:name":"Clod Accessori Snc Di Rovaris Claudio & C.",
    "wof:placetype":"venue"
},
  "geometry": {"coordinates":[9.615128,45.647205],"type":"Point"}
}