{
  "type": "Feature",
  "properties": {
    "iso:country":"IT",
    "sg:address":"73100 Lecce",
    "sg:city":"Lecce",
    "sg:orig_category":"Petroli, Gas E Combustibili. Materiali Edili",
    "sg:phone":"+39 0832 391555",
    "sg:postcode":"73100",
    "sg:province":"Lecce",
    "wof:name":"Valerio Srl",
    "wof:placetype":"venue"
},
  "geometry": {"coordinates":[18.1876468658,40.3566741943],"type":"Point"}
}