{
  "type": "Feature",
  "properties": {
    "iso:country":"IT",
    "sg:address":"16124 Genova",
    "sg:city":"Genova",
    "sg:orig_category":"Macchine, Impianti Ed Attrezzature Per Industria Alimentare E Bevande",
    "sg:phone":"+39 010 261723",
    "sg:postcode":"16124",
    "sg:province":"Genova",
    "wof:name":"Tecnoforni Srl Macchine Per Panificazione E Pasticcerie",
    "wof:placetype":"venue"
},
  "geometry": {"coordinates":[8.928145,44.411381],"type":"Point"}
}