{
  "type": "Feature",
  "properties": {
    "iso:country":"IT",
    "sg:address":"Via Rivaltella 36071 Arzignano",
    "sg:city":"Arzignano",
    "sg:classifiers":[
        {
            "category":"Manufacturing",
            "subcategory":"Textiles",
            "type":"Manufacturing & Wholesale Goods"
        }
    ],
    "sg:phone":"+39 0444 451804",
    "sg:postcode":"36071",
    "sg:province":"Vicenza",
    "sg:tags":[
        "leather",
        "raw",
        "material",
        "-"
    ],
    "wof:name":"Serenissima (s.r.l.)",
    "wof:placetype":"venue"
},
  "geometry": {"coordinates":[11.348117,45.501518],"type":"Point"}
}