{
  "type": "Feature",
  "properties": {
    "addr:full":"80025 Casandrino Casandrino Napoli 80025",
    "addr:postcode":"80025;80025",
    "iso:country":"IT",
    "sg:address":"80025 Casandrino",
    "sg:city":"Casandrino",
    "sg:orig_category":"Materiali E Componenti Elettrotecnici. Elettrotecnica Industriale, Prodotti E Apparecchiature",
    "sg:phone":"+39 081 833 2554",
    "sg:postcode":"80025",
    "sg:province":"Napoli",
    "sg:website":"http://mace.it",
    "wof:name":"Mace Sas",
    "wof:placetype":"venue"
},
  "geometry": {"coordinates":[14.248315,40.924988],"type":"Point"}
}