{
  "type": "Feature",
  "properties": {
    "addr:full":"41019 Soliera Soliera Modena 41019",
    "addr:postcode":"41019;41019",
    "iso:country":"IT",
    "sg:address":"41019 Soliera",
    "sg:city":"Soliera",
    "sg:orig_category":"Forniture Per Abbigliamento E Pelletterie. Forniture Per Attivita' Commerciali Ed Artigianali",
    "sg:phone":"+39 059 566803",
    "sg:postcode":"41019",
    "sg:province":"Modena",
    "wof:name":"Diesse (s.n.c.)",
    "wof:placetype":"venue"
},
  "geometry": {"coordinates":[10.9122219086,44.7285385132],"type":"Point"}
}