{
  "type": "Feature",
  "properties": {
    "iso:country":"IT",
    "sg:address":"Via Reggio Emilia 17 20090 Segrate",
    "sg:city":"Segrate",
    "sg:classifiers":[
        {
            "category":"Home & Garden",
            "subcategory":"Household Appliances",
            "type":"Retail Goods"
        }
    ],
    "sg:phone":"+39 02 213 2078",
    "sg:postcode":"20090",
    "sg:province":"Milano",
    "sg:tags":[
        "heater",
        "industrial",
        "electric",
        "us"
    ],
    "sg:website":"www.tre-c.it",
    "wof:name":"Tre C Srl",
    "wof:placetype":"venue"
},
  "geometry": {"coordinates":[9.267924,45.481659],"type":"Point"}
}