{
  "type": "Feature",
  "properties": {
    "iso:country":"IT",
    "sg:address":"30175 Mestre",
    "sg:city":"Mestre",
    "sg:orig_category":"Tempo Libero - Articoli E Forniture. Regalistica Aziendale",
    "sg:phone":"+39 041 936704",
    "sg:postcode":"30175",
    "sg:province":"Venezia",
    "wof:name":"Perez Sebastiano",
    "wof:placetype":"venue"
},
  "geometry": {"coordinates":[12.234448,45.486],"type":"Point"}
}