{
  "type": "Feature",
  "properties": {
    "iso:country":"IT",
    "sg:address":"20011 Corbetta",
    "sg:city":"Corbetta",
    "sg:orig_category":"Servizi Ausiliari Dei Mezzi Di Trasporto",
    "sg:phone":"+39 02 9727 3150",
    "sg:postcode":"20011",
    "sg:province":"Milano",
    "wof:name":"Linecar Srl",
    "wof:placetype":"venue"
},
  "geometry": {"coordinates":[8.944199,45.478912],"type":"Point"}
}