{
  "type": "Feature",
  "properties": {
    "addr:full":"10146 Torino Torino Torino 10146",
    "addr:postcode":"10146;10146",
    "iso:country":"IT",
    "sg:address":"10146 Torino",
    "sg:city":"Torino",
    "sg:orig_category":"Martelli Elettrici E Pneumatici",
    "sg:phone":"+39 011 771 5455",
    "sg:postcode":"10146",
    "sg:province":"Torino",
    "wof:name":"O.r.a.i.t. Di Iezza Antonio",
    "wof:placetype":"venue"
},
  "geometry": {"coordinates":[7.120077,45.126019],"type":"Point"}
}