{
  "type": "Feature",
  "properties": {
    "iso:country":"IT",
    "sg:address":"40127 Bologna",
    "sg:city":"Bologna",
    "sg:orig_category":"Arredo Cucina Ed Elettrodomestici. Climatizzazione E Condizionamento, Apparecchiature E Servizi",
    "sg:phone":"+39 051 633 0090",
    "sg:postcode":"40127",
    "sg:province":"Bologna",
    "wof:name":"Delvem S.r.l",
    "wof:placetype":"venue"
},
  "geometry": {"coordinates":[11.372915,44.516754],"type":"Point"}
}