{
  "type": "Feature",
  "properties": {
    "addr:full":"19, Via Piceno Aprutina 63100 Ascoli Piceno Ascoli Piceno Ascoli Piceno 63100",
    "addr:postcode":"63100;63100",
    "addr:street":"Via Piceno Aprutina",
    "iso:country":"IT",
    "sg:address":"19, Via Piceno Aprutina 63100 Ascoli Piceno",
    "sg:city":"Ascoli Piceno",
    "sg:classifiers":[
        {
            "category":"Food & Beverages",
            "subcategory":"Groceries & Convenience Stores",
            "type":"Retail Goods"
        }
    ],
    "sg:phone":"+39 0736 342990",
    "sg:postcode":"63100",
    "sg:province":"Ascoli Piceno",
    "sg:tags":[
        "drink"
    ],
    "wof:name":"Distillerie Centro Adriatico (s.p.a.)",
    "wof:placetype":"venue"
},
  "geometry": {"coordinates":[13.620031,42.843727],"type":"Point"}
}