{
  "type": "Feature",
  "properties": {
    "addr:full":"20044 Bernareggio Bernareggio Milano 20044",
    "addr:postcode":"20044;20044",
    "iso:country":"IT",
    "sg:address":"20044 Bernareggio",
    "sg:city":"Bernareggio",
    "sg:orig_category":"Prodotti E Manufatti In Materie Plastiche. Forniture Per Edilizia E Lavori Pubblici. Forniture E Materiali Per Imballaggio E Confezionamento",
    "sg:phone":"+39 039 690 2352",
    "sg:postcode":"20044",
    "sg:province":"Milano",
    "wof:name":"Visim S.r.l.",
    "wof:placetype":"venue"
},
  "geometry": {"coordinates":[9.4002361298,45.6341972351],"type":"Point"}
}