{
  "type": "Feature",
  "properties": {
    "addr:full":"00153 Roma Roma Roma 00153",
    "addr:postcode":"00153;00153",
    "iso:country":"IT",
    "sg:address":"00153 Roma",
    "sg:city":"Roma",
    "sg:orig_category":"Macchine, Impianti E Forniture Per Industria Grafica, Cartaria E Cartotecnica",
    "sg:phone":"+39 06 580 3887",
    "sg:postcode":"00153",
    "sg:province":"Roma",
    "wof:name":"Carasso Nicola",
    "wof:placetype":"venue"
},
  "geometry": {"coordinates":[12.4693,41.886612],"type":"Point"}
}