{
  "type": "Feature",
  "properties": {
    "addr:full":"34073 Grado Grado Gorizia 34073",
    "addr:postcode":"34073;34073",
    "iso:country":"IT",
    "sg:address":"34073 Grado",
    "sg:city":"Grado",
    "sg:classifiers":[
        {
            "category":"Restaurant",
            "type":"Food & Drink"
        }
    ],
    "sg:phone":"+39 0431 80745",
    "sg:postcode":"34073",
    "sg:province":"Gorizia",
    "sg:tags":[
        "auxiliary",
        "entertainment",
        "premises",
        "related",
        "catering",
        "similar",
        "public",
        "restaurants"
    ],
    "wof:name":"Albergo Meubl\u00c8 Carol",
    "wof:placetype":"venue"
},
  "geometry": {"coordinates":[13.395288,45.678753],"type":"Point"}
}