{
  "type": "Feature",
  "properties": {
    "addr:full":"125, Via Brenta 36056 Tezze Sul Brenta Tezze sul Brenta Vicenza 36056",
    "addr:housenumber":"125",
    "addr:postcode":"36056;36056",
    "addr:street":"Via Brenta",
    "iso:country":"IT",
    "sg:address":"125, Via Brenta 36056 Tezze Sul Brenta",
    "sg:city":"Tezze sul Brenta",
    "sg:classifiers":[
        {
            "category":"Manufacturing",
            "subcategory":"Textiles",
            "type":"Manufacturing & Wholesale Goods"
        }
    ],
    "sg:phone":"+39 0424 539111",
    "sg:postcode":"36056",
    "sg:province":"Vicenza",
    "sg:tags":[
        "leather",
        "raw",
        "material",
        "-"
    ],
    "wof:name":"S. Marco Pelli Grezze (s.p.a.)",
    "wof:placetype":"venue"
},
  "geometry": {"coordinates":[11.740978,45.646339],"type":"Point"}
}