{
  "type": "Feature",
  "properties": {
    "iso:country":"IT",
    "sg:address":"09124 Cagliari",
    "sg:city":"Cagliari",
    "sg:orig_category":"Studi E Consulenze Tecniche E Industriali. Servizi E Lavori Per Edilizia E Lavori Pubblici. Professionisti - Studi E Servizi Ed Associazioni Di Interesse Aziendale",
    "sg:phone":"+39 070 657426",
    "sg:postcode":"09124",
    "sg:province":"Cagliari",
    "wof:name":"Baldussi Ing. Franco",
    "wof:placetype":"venue"
},
  "geometry": {"coordinates":[9.116107,39.218983],"type":"Point"}
}