{
  "type": "Feature",
  "properties": {
    "addr:full":"23020 Prata Camportaccio Prata Camportaccio Sondrio 23020",
    "addr:postcode":"23020;23020",
    "iso:country":"IT",
    "sg:address":"23020 Prata Camportaccio",
    "sg:city":"Prata Camportaccio",
    "sg:orig_category":"Prodotti Alimentari",
    "sg:phone":"+39 0343 32757",
    "sg:postcode":"23020",
    "sg:province":"Sondrio",
    "wof:name":"Pastificio Di Chiavenna Srl",
    "wof:placetype":"venue"
},
  "geometry": {"coordinates":[9.3896999359,46.3047943115],"type":"Point"}
}