{
  "type": "Feature",
  "properties": {
    "iso:country":"IT",
    "sg:address":"35122 Padova",
    "sg:city":"Padova",
    "sg:orig_category":"Calzature, Pelletterie E Pelli",
    "sg:phone":"+39 049 651366",
    "sg:postcode":"35122",
    "sg:province":"Padova",
    "wof:name":"Padovafurs (s.r.l.)",
    "wof:placetype":"venue"
},
  "geometry": {"coordinates":[11.864736,45.346676],"type":"Point"}
}