{
  "type": "Feature",
  "properties": {
    "addr:full":"20080 Zibido San Giacomo Zibido San Giacomo Milano 20080",
    "addr:postcode":"20080;20080",
    "addr:street":"San",
    "iso:country":"IT",
    "sg:address":"20080 Zibido San Giacomo",
    "sg:city":"Zibido San Giacomo",
    "sg:classifiers":[
        {
            "category":"Manufacturing",
            "subcategory":"Motor Vehicles & Parts",
            "type":"Manufacturing & Wholesale Goods"
        }
    ],
    "sg:phone":"+39 02 9009 2330",
    "sg:postcode":"20080",
    "sg:province":"Milano",
    "sg:tags":[
        "vehicles",
        "accessory"
    ],
    "wof:name":"Gianpit",
    "wof:placetype":"venue"
},
  "geometry": {"coordinates":[9.1296358109,45.3528785706],"type":"Point"}
}