{
  "type": "Feature",
  "properties": {
    "iso:country":"IT",
    "sg:address":"V. Nazionale 7 35047 Solesino",
    "sg:city":"Solesino",
    "sg:classifiers":[
        {
            "category":"Home & Garden",
            "subcategory":"Home Furnishings",
            "type":"Retail Goods"
        }
    ],
    "sg:phone":"+39 0429 709533",
    "sg:postcode":"35047",
    "sg:province":"Padova",
    "sg:tags":[
        "household"
    ],
    "wof:name":"Euroflex Srl Commerciale Italiana",
    "wof:placetype":"venue"
},
  "geometry": {"coordinates":[11.756193,45.178288],"type":"Point"}
}