{
  "type": "Feature",
  "properties": {
    "iso:country":"IT",
    "sg:address":"20138 Milano",
    "sg:city":"Milano",
    "sg:classifiers":[
        {
            "category":"Manufacturing",
            "subcategory":"Tools & Machinery",
            "type":"Manufacturing & Wholesale Goods"
        }
    ],
    "sg:phone":"+39 02 504095",
    "sg:postcode":"20138",
    "sg:province":"Milano",
    "sg:tags":[
        "chemical",
        "equipment",
        "industry",
        "mechanical"
    ],
    "sg:website":"http://www.danioni.it/",
    "wof:name":"Danioni Italo Srl",
    "wof:placetype":"venue"
},
  "geometry": {"coordinates":[9.251227,45.453423],"type":"Point"}
}