{
  "type": "Feature",
  "properties": {
    "addr:full":"40128 Bologna Bologna Bologna 40128",
    "addr:postcode":"40128;40128",
    "iso:country":"IT",
    "sg:address":"40128 Bologna",
    "sg:city":"Bologna",
    "sg:orig_category":"Artigianato Tipico",
    "sg:phone":"+39 051 325276",
    "sg:postcode":"40128",
    "sg:province":"Bologna",
    "wof:name":"Foglia Paolo",
    "wof:placetype":"venue"
},
  "geometry": {"coordinates":[11.360289,44.52668],"type":"Point"}
}