{
  "type": "Feature",
  "properties": {
    "addr:full":"10, Regione Verdese 13876 Sandigliano Sandigliano Biella 13876",
    "addr:housenumber":"10",
    "addr:postcode":"13876;13876",
    "addr:street":"Regione Verdese",
    "iso:country":"IT",
    "sg:address":"10, Regione Verdese 13876 Sandigliano",
    "sg:city":"Sandigliano",
    "sg:classifiers":[
        {
            "category":"Real Estate",
            "subcategory":"Surveying",
            "type":"Services"
        }
    ],
    "sg:phone":"+39 39015692145",
    "sg:postcode":"13876",
    "sg:province":"Biella",
    "sg:tags":[
        "equipment",
        "material",
        "good",
        "-",
        "handling"
    ],
    "wof:name":"Sacma (s.p.a.)",
    "wof:placetype":"venue"
},
  "geometry": {"coordinates":[8.05827,45.562836],"type":"Point"}
}