{
  "type": "Feature",
  "properties": {
    "addr:full":"00159 Roma Roma Roma 00159",
    "addr:postcode":"00159;00159",
    "iso:country":"IT",
    "sg:address":"00159 Roma",
    "sg:city":"Roma",
    "sg:orig_category":"Internet, Telematica E Audiotex - Servizi",
    "sg:phone":"+39 06 4359 9887",
    "sg:postcode":"00159",
    "sg:province":"Roma",
    "sg:website":"http://www.it-point.it",
    "wof:name":"It Point Srl",
    "wof:placetype":"venue"
},
  "geometry": {"coordinates":[12.539064,41.907627],"type":"Point"}
}