{
  "type": "Feature",
  "properties": {
    "iso:country":"IT",
    "sg:address":"50, Viale Europa 31018 Gaiarine",
    "sg:city":"Gaiarine",
    "sg:classifiers":[
        {
            "category":"Home & Garden",
            "subcategory":"Home Furnishings",
            "type":"Retail Goods"
        }
    ],
    "sg:phone":"+39 0434 756311",
    "sg:postcode":"31018",
    "sg:province":"Treviso",
    "sg:tags":[
        "household"
    ],
    "wof:name":"S.m.a. S.p.a.",
    "wof:placetype":"venue"
},
  "geometry": {"coordinates":[12.511917,45.882782],"type":"Point"}
}