{
  "type": "Feature",
  "properties": {
    "iso:country":"IT",
    "sg:address":"27, Via Molino 20036 Meda",
    "sg:city":"Meda",
    "sg:classifiers":[
        {
            "category":"Home & Garden",
            "subcategory":"Home Furnishings",
            "type":"Retail Goods"
        }
    ],
    "sg:phone":"+39 036 234 0522",
    "sg:postcode":"20036",
    "sg:province":"Milano",
    "sg:tags":[
        "household"
    ],
    "wof:name":"Elam Industria Per L'arredamento Spa",
    "wof:placetype":"venue"
},
  "geometry": {"coordinates":[9.146151,45.666386],"type":"Point"}
}