{
  "type": "Feature",
  "properties": {
    "addr:full":"00193 Roma Roma Roma 00193",
    "addr:postcode":"00193;00193",
    "iso:country":"IT",
    "sg:address":"00193 Roma",
    "sg:city":"Roma",
    "sg:orig_category":"Prodotti Chimici Secondari. Servizi E Lavori Per Ecologia E Smaltimento Rifiuti. Macchine E Forniture Per Ecologia E Smaltimento Rifiuti",
    "sg:phone":"+39 06 681 0161",
    "sg:postcode":"00193",
    "sg:province":"Roma",
    "wof:name":"S.i.g.e.s.a.",
    "wof:placetype":"venue"
},
  "geometry": {"coordinates":[12.4678163528,41.9054145813],"type":"Point"}
}