{
  "type": "Feature",
  "properties": {
    "addr:full":"S.da Per Voghera - Regione Villoria, 93/5/f 15057 Tortona Tortona Alessandria 15057",
    "addr:housenumber":"93 / 5 / f",
    "addr:postcode":"15057;15057",
    "addr:street":"S.Da;Regione Villoria",
    "iso:country":"IT",
    "sg:address":"S.da Per Voghera - Regione Villoria, 93/5/f 15057 Tortona",
    "sg:city":"Tortona",
    "sg:classifiers":[
        {
            "category":"Shopping",
            "subcategory":"Mobile Phones",
            "type":"Retail Goods"
        }
    ],
    "sg:phone":"+39 0131 81641",
    "sg:postcode":"15057",
    "sg:province":"Alessandria",
    "sg:tags":[
        "communication",
        "global",
        "gsm",
        "system"
    ],
    "sg:website":"www.p-com.com",
    "wof:name":"P-com Italia S.p.a.",
    "wof:placetype":"venue"
},
  "geometry": {"coordinates":[8.616951,44.913216],"type":"Point"}
}