{
  "type": "Feature",
  "properties": {
    "iso:country":"IT",
    "sg:address":"10149 Torino",
    "sg:city":"Torino",
    "sg:orig_category":"Servizi Per Aziende, Manifestazioni E Supporto Agli Scambi Commerciali",
    "sg:phone":"+39 011 751020",
    "sg:postcode":"10149",
    "sg:province":"Torino",
    "wof:name":"Centro Operativo Servizi Di Vicario Rosella",
    "wof:placetype":"venue"
},
  "geometry": {"coordinates":[7.830617,45.487606],"type":"Point"}
}