{
  "type": "Feature",
  "properties": {
    "iso:country":"IT",
    "sg:address":"51, Via Bengasi 47100 Forli'",
    "sg:classifiers":[
        {
            "category":"Wholesale",
            "subcategory":"Drugs",
            "type":"Manufacturing & Wholesale Goods"
        }
    ],
    "sg:phone":"+39 0543 723457",
    "sg:postcode":"47100",
    "sg:province":"Forl\u00ec-Cesena",
    "sg:tags":[
        "chemical",
        "pharmaceutical"
    ],
    "wof:name":"Nuova Saicima S.r.l.",
    "wof:placetype":"venue"
},
  "geometry": {"coordinates":[11.980461,43.994766],"type":"Point"}
}