{
  "type": "Feature",
  "properties": {
    "addr:full":"16145 Genova Genova Genova 16145",
    "addr:postcode":"16145;16145",
    "iso:country":"IT",
    "sg:address":"16145 Genova",
    "sg:city":"Genova",
    "sg:orig_category":"Medici. Assicurazioni E Servizi Assicurativi. Avvocati, Notai E Servizi Legali. Professionisti - Studi E Servizi Ed Associazioni Di Interesse Aziendale",
    "sg:phone":"+39 010 310200",
    "sg:postcode":"16145",
    "sg:province":"Genova",
    "wof:name":"De Lucchi Massimo Antonio",
    "wof:placetype":"venue"
},
  "geometry": {"coordinates":[8.9604177475,44.3981399536],"type":"Point"}
}