{
  "type": "Feature",
  "properties": {
    "iso:country":"IT",
    "sg:address":"90144 Palermo",
    "sg:city":"Palermo",
    "sg:orig_category":"Centri Di Estetica E Cosmesi E Servizi",
    "sg:phone":"+39 091 518307",
    "sg:postcode":"90144",
    "sg:province":"Palermo",
    "wof:name":"Longevity Life",
    "wof:placetype":"venue"
},
  "geometry": {"coordinates":[13.338514,38.143307],"type":"Point"}
}