{
  "type": "Feature",
  "properties": {
    "iso:country":"IT",
    "sg:address":"28921 Verbania",
    "sg:city":"Verbania",
    "sg:classifiers":[
        {
            "category":"Travel",
            "subcategory":"Travel Agent",
            "type":"Entertainment"
        }
    ],
    "sg:phone":"+39 0323 52486",
    "sg:postcode":"28921",
    "sg:province":"Verbano-Cusio-Ossola",
    "sg:tags":[
        "operator",
        "tour",
        "tourist"
    ],
    "wof:name":"Lake & Mountain",
    "wof:placetype":"venue"
},
  "geometry": {"coordinates":[8.572133,45.93924],"type":"Point"}
}