{
  "type": "Feature",
  "properties": {
    "iso:country":"IT",
    "sg:address":"04011 Aprilia",
    "sg:city":"Aprilia",
    "sg:orig_category":"Prodotti Chimici Secondari. Prodotti Cosmetici E Da Toeletta",
    "sg:phone":"+39 06 928 2436",
    "sg:postcode":"04011",
    "sg:province":"Latina",
    "wof:name":"Pavan Adriano",
    "wof:placetype":"venue"
},
  "geometry": {"coordinates":[12.6574544907,41.5839805603],"type":"Point"}
}