{
  "type": "Feature",
  "properties": {
    "iso:country":"IT",
    "sg:address":"25, Via Madonna Delle Grazie 66016 Guardiagrele",
    "sg:city":"Guardiagrele",
    "sg:classifiers":[
        {
            "category":"Professional",
            "subcategory":"Engineering",
            "type":"Services"
        }
    ],
    "sg:phone":"+39 0871 801079",
    "sg:postcode":"66016",
    "sg:province":"Chieti",
    "sg:tags":[
        "machine",
        "-",
        "mechanical"
    ],
    "wof:name":"Tecnoal Srl",
    "wof:placetype":"venue"
},
  "geometry": {"coordinates":[14.221966,42.204746],"type":"Point"}
}