{
  "type": "Feature",
  "properties": {
    "iso:country":"IT",
    "sg:address":"25018 Ro'disopra",
    "sg:orig_category":"Zootecnia E Pesca, Allevamento Piccoli Animali",
    "sg:phone":"+39 030 962418",
    "sg:postcode":"25018",
    "sg:province":"Brescia",
    "wof:name":"Allevamenti Monteclarensi Di Zamboni Cesarino & C. S.n.c.",
    "wof:placetype":"venue"
},
  "geometry": {"coordinates":[10.206272,45.547504],"type":"Point"}
}