{
  "type": "Feature",
  "properties": {
    "iso:country":"IT",
    "sg:address":"15067 Novi Ligure",
    "sg:city":"Novi Ligure",
    "sg:orig_category":"Dentisti Medici Chirurghi Ed Odontoiatri",
    "sg:phone":"+39 0143 2056",
    "sg:postcode":"15067",
    "sg:province":"Alessandria",
    "wof:name":"Fossati Dr. Mario",
    "wof:placetype":"venue"
},
  "geometry": {"coordinates":[8.790218,44.763023],"type":"Point"}
}