{
  "type": "Feature",
  "properties": {
    "iso:country":"IT",
    "sg:address":"14, Strada St. Regina 62019 Recanati",
    "sg:city":"Recanati",
    "sg:classifiers":[
        {
            "category":"Wholesale",
            "subcategory":"Drugs",
            "type":"Manufacturing & Wholesale Goods"
        }
    ],
    "sg:phone":"+39 39071987163",
    "sg:postcode":"62019",
    "sg:province":"Macerata",
    "sg:tags":[
        "chemical",
        "pharmaceutical"
    ],
    "wof:name":"Natural Gas Srl",
    "wof:placetype":"venue"
},
  "geometry": {"coordinates":[13.456262,43.300747],"type":"Point"}
}