{
  "type": "Feature",
  "properties": {
    "iso:country":"IT",
    "sg:address":"1910, Via Bergamo 21042 Caronno Pertusella",
    "sg:city":"Caronno Pertusella",
    "sg:classifiers":[
        {
            "category":"Professional",
            "subcategory":"Engineering",
            "type":"Services"
        }
    ],
    "sg:phone":"+39 39029655444",
    "sg:postcode":"21042",
    "sg:province":"Varese",
    "sg:tags":[
        "machine",
        "-",
        "mechanical"
    ],
    "wof:name":"Ms Machinery And Systems Srl",
    "wof:placetype":"venue"
},
  "geometry": {"coordinates":[9.029841,45.599335],"type":"Point"}
}