{
  "type": "Feature",
  "properties": {
    "iso:country":"IT",
    "sg:address":"25131 Brescia",
    "sg:city":"Brescia",
    "sg:orig_category":"Servizi Ausiliari Di Certificati, Riproduzioni, Disegni E Foto",
    "sg:phone":"+39 030 358 2133",
    "sg:postcode":"25131",
    "sg:province":"Brescia",
    "sg:website":"http://www.safetyglass.it",
    "wof:name":"Safetyglass Srl",
    "wof:placetype":"venue"
},
  "geometry": {"coordinates":[10.176337,45.489475],"type":"Point"}
}