{
  "type": "Feature",
  "properties": {
    "addr:full":"Via Avogadro 18 50019 Sesto Fiorentino Sesto Fiorentino Firenze 50019",
    "addr:housenumber":"18",
    "addr:postcode":"50019;50019",
    "addr:street":"Via Avogadro",
    "iso:country":"IT",
    "sg:address":"Via Avogadro 18 50019 Sesto Fiorentino",
    "sg:city":"Sesto Fiorentino",
    "sg:classifiers":[
        {
            "category":"Community Center",
            "subcategory":"Youth",
            "type":"Public Place"
        }
    ],
    "sg:phone":"+39 055 374483",
    "sg:postcode":"50019",
    "sg:province":"Firenze",
    "sg:tags":[
        "case",
        "petit",
        "bags",
        "item",
        "point"
    ],
    "wof:name":"New Ri-ve S.r.l.",
    "wof:placetype":"venue"
},
  "geometry": {"coordinates":[11.256901741,43.7687339783],"type":"Point"}
}