{
  "type": "Feature",
  "properties": {
    "iso:country":"IT",
    "sg:address":"20139 Milano",
    "sg:city":"Milano",
    "sg:orig_category":"Filati E Materie Prime Tessili",
    "sg:phone":"+39 02 539 0721",
    "sg:postcode":"20139",
    "sg:province":"Milano",
    "wof:name":"Giugliano Teresa",
    "wof:placetype":"venue"
},
  "geometry": {"coordinates":[9.2838106155,45.519153595],"type":"Point"}
}