{
  "type": "Feature",
  "properties": {
    "iso:country":"IT",
    "sg:address":"92100 Agrigento",
    "sg:city":"Agrigento",
    "sg:classifiers":[
        {
            "category":"Home & Garden",
            "subcategory":"Kitchen Supply",
            "type":"Retail Goods"
        }
    ],
    "sg:phone":"+39 0922 441868",
    "sg:postcode":"92100",
    "sg:province":"Agrigento",
    "sg:tags":[
        "utensil",
        "houseware"
    ],
    "wof:name":"C.c. Srl Centro Casalinghi",
    "wof:placetype":"venue"
},
  "geometry": {"coordinates":[13.578402,37.30899],"type":"Point"}
}