{
  "type": "Feature",
  "properties": {
    "iso:country":"IT",
    "sg:address":"20132 Milano",
    "sg:city":"Milano",
    "sg:orig_category":"Impiantistica E Prodotti Tecnologici Per Edilizia",
    "sg:phone":"+39 02 256 4613",
    "sg:postcode":"20132",
    "sg:province":"Milano",
    "wof:name":"Label (s.r.l.)",
    "wof:placetype":"venue"
},
  "geometry": {"coordinates":[9.24159,45.501659],"type":"Point"}
}