{
  "type": "Feature",
  "properties": {
    "iso:country":"IT",
    "sg:address":"20049 Concorezzo",
    "sg:city":"Concorezzo",
    "sg:orig_category":"Elettrotecnica Industriale, Prodotti E Apparecchiature",
    "sg:phone":"+39 039 604 1001",
    "sg:postcode":"20049",
    "sg:province":"Milano",
    "wof:name":"Mge Italia S.p.a.",
    "wof:placetype":"venue"
},
  "geometry": {"coordinates":[9.324499,45.59309],"type":"Point"}
}