{
  "type": "Feature",
  "properties": {
    "iso:country":"IT",
    "sg:address":"34018 San Dorligo Della Valle",
    "sg:city":"San Dorligo della Valle",
    "sg:orig_category":"Carriponte - Costruzione",
    "sg:phone":"+39 040 381529",
    "sg:postcode":"34018",
    "sg:province":"Trieste",
    "sg:website":"http://www.redox-group.com",
    "wof:name":"Redox Group Srl",
    "wof:placetype":"venue"
},
  "geometry": {"coordinates":[13.825081,45.606323],"type":"Point"}
}