{
  "type": "Feature",
  "properties": {
    "iso:country":"IT",
    "sg:address":"80040 San Sebastiano Al Vesuvio",
    "sg:city":"San Sebastiano al Vesuvio",
    "sg:orig_category":"Accessori Dei Mezzi Di Trasporto",
    "sg:phone":"+39 081 771 6763",
    "sg:postcode":"80040",
    "sg:province":"Napoli",
    "wof:name":"Geven S.r.l.",
    "wof:placetype":"venue"
},
  "geometry": {"coordinates":[14.352306,40.8451],"type":"Point"}
}