{
  "type": "Feature",
  "properties": {
    "iso:country":"IT",
    "sg:address":"91011 Alcamo",
    "sg:city":"Alcamo",
    "sg:orig_category":"Forniture Per Edilizia E Lavori Pubblici. Prodotti Vari In Metallo",
    "sg:phone":"+39 0924 24428",
    "sg:postcode":"91011",
    "sg:province":"Trapani",
    "wof:name":"Cuccia Geom. Tommaso Sas Di Cuccia Tommaso & C.",
    "wof:placetype":"venue"
},
  "geometry": {"coordinates":[12.7745742798,37.9389686584],"type":"Point"}
}