{
  "type": "Feature",
  "properties": {
    "iso:country":"IT",
    "sg:address":"00185 Roma",
    "sg:city":"Roma",
    "sg:orig_category":"Marmo, Pietre Ed Affini. Arte Ed Artigianato Artistico",
    "sg:phone":"+39 06 490194",
    "sg:postcode":"00185",
    "sg:province":"Roma",
    "wof:name":"Sectile Di Piras Rinaldo & C. Snc",
    "wof:placetype":"venue"
},
  "geometry": {"coordinates":[12.514601,41.900723],"type":"Point"}
}