{
  "type": "Feature",
  "properties": {
    "addr:full":"57, Via Xxv Aprile 37014 Castelnuovo Del Garda Castelnuovo del Garda Verona 37014",
    "addr:postcode":"37014;37014",
    "addr:street":"Via Xxv Aprile",
    "iso:country":"IT",
    "sg:address":"57, Via Xxv Aprile 37014 Castelnuovo Del Garda",
    "sg:city":"Castelnuovo del Garda",
    "sg:classifiers":[
        {
            "category":"Shopping",
            "subcategory":"Clothing, Apparel, & Fashions",
            "type":"Retail Goods"
        }
    ],
    "sg:phone":"+39 045 755 0064",
    "sg:postcode":"37014",
    "sg:province":"Verona",
    "sg:tags":[
        "clothes"
    ],
    "wof:name":"C.m.m.a. S.r.l.",
    "wof:placetype":"venue"
},
  "geometry": {"coordinates":[10.991748,45.438366],"type":"Point"}
}