{
  "type": "Feature",
  "properties": {
    "iso:country":"IT",
    "sg:address":"06078 Perugia",
    "sg:orig_category":"Tempo Libero - Articoli E Forniture. Automobili E Mezzi Di Trasporto. Riparazione Dei Mezzi Di Trasporto",
    "sg:phone":"+39 075 517 7357",
    "sg:province":"PG",
    "wof:name":"Testi Srl",
    "wof:placetype":"venue"
},
  "geometry": {"coordinates":[12.152628,43.330963],"type":"Point"}
}