{
  "type": "Feature",
  "properties": {
    "iso:country":"IT",
    "sg:address":"33100 Udine",
    "sg:city":"Udine",
    "sg:orig_category":"Cartotecnica E Servizi. Forniture Per Attivita' Commerciali Ed Artigianali",
    "sg:phone":"+39 0432 232321",
    "sg:postcode":"33100",
    "sg:province":"Udine",
    "wof:name":"Bardelli Daniela",
    "wof:placetype":"venue"
},
  "geometry": {"coordinates":[13.206345,46.060963],"type":"Point"}
}