{
  "type": "Feature",
  "properties": {
    "iso:country":"IT",
    "sg:address":"00040 Rocca Priora",
    "sg:city":"Rocca Priora",
    "sg:orig_category":"Ristorazione E Locali Pubblici Affini. Ristoranti Ed Esercizi Affini. Servizi Ausiliari Di Ristorazione E Di Intrattenimento",
    "sg:phone":"+39 06 940 6240",
    "sg:postcode":"00040",
    "sg:province":"Roma",
    "wof:name":"Ristorante Bruni",
    "wof:placetype":"venue"
},
  "geometry": {"coordinates":[12.760655,41.791779],"type":"Point"}
}