{
  "type": "Feature",
  "properties": {
    "iso:country":"IT",
    "sg:address":"Via Degli Orti 13 56029 Santa Croce Sull'arno",
    "sg:classifiers":[
        {
            "category":"Home & Garden",
            "subcategory":"Carpets & Floor Coverings",
            "type":"Retail Goods"
        }
    ],
    "sg:phone":"+39 0571 367163",
    "sg:postcode":"56029",
    "sg:province":"Pisa",
    "sg:tags":[
        "animal",
        "skin"
    ],
    "sg:website":"www.conceriaalaska.it",
    "wof:name":"Nuova Mistral Spa",
    "wof:placetype":"venue"
},
  "geometry": {"coordinates":[10.776454,43.70919],"type":"Point"}
}