{
  "type": "Feature",
  "properties": {
    "addr:full":"20151 Milano Milano Milano 20151",
    "addr:postcode":"20151;20151",
    "iso:country":"IT",
    "sg:address":"20151 Milano",
    "sg:city":"Milano",
    "sg:orig_category":"Prodotti Alimentari",
    "sg:phone":"+39 02 3800 4415",
    "sg:postcode":"20151",
    "sg:province":"Milano",
    "wof:name":"Fainozzi Bruno",
    "wof:placetype":"venue"
},
  "geometry": {"coordinates":[9.1111326218,45.4927024841],"type":"Point"}
}