{
  "type": "Feature",
  "properties": {
    "iso:country":"IT",
    "sg:address":"Via Torino, 70/b; Chivasso; 10034",
    "sg:city":"Chivasso",
    "sg:classifiers":[
        {
            "category":"Banks & Credit Unions",
            "subcategory":"Bank",
            "type":"Services"
        }
    ],
    "sg:phone":"+39 011 917 1222",
    "sg:postcode":"10034",
    "sg:province":"Torino",
    "wof:name":"Banca Popolare Di Novara",
    "wof:placetype":"venue"
},
  "geometry": {"coordinates":[7.888073,45.190121],"type":"Point"}
}