{
  "type": "Feature",
  "properties": {
    "addr:full":"Via Ponticino 59024 Vernio Vernio Prato 59024",
    "addr:postcode":"59024;59024",
    "addr:street":"Via Ponticino",
    "iso:country":"IT",
    "sg:address":"Via Ponticino 59024 Vernio",
    "sg:city":"Vernio",
    "sg:classifiers":[
        {
            "category":"Shopping",
            "subcategory":"Crafts & Fabrics",
            "type":"Retail Goods"
        }
    ],
    "sg:phone":"+39 0574 957174",
    "sg:postcode":"59024",
    "sg:province":"Prato",
    "wof:name":"Pucci Figli Di Ugo",
    "wof:placetype":"venue"
},
  "geometry": {"coordinates":[11.1528959274,44.0583992004],"type":"Point"}
}