{
  "type": "Feature",
  "properties": {
    "addr:full":"00154 Roma Roma Roma 00154",
    "addr:postcode":"00154;00154",
    "iso:country":"IT",
    "sg:address":"00154 Roma",
    "sg:city":"Roma",
    "sg:orig_category":"Arredi Ed Attrezzature Per Uffici",
    "sg:phone":"+39 06 575 6389",
    "sg:postcode":"00154",
    "sg:province":"Roma",
    "wof:name":"Cascapera Fabio",
    "wof:placetype":"venue"
},
  "geometry": {"coordinates":[12.481956,41.87204],"type":"Point"}
}