{
  "type": "Feature",
  "properties": {
    "iso:country":"IT",
    "sg:address":"41, Via Gasdotto 36078 Valdagno",
    "sg:city":"Valdagno",
    "sg:classifiers":[
        {
            "category":"Shopping",
            "subcategory":"Clothing, Apparel, & Fashions",
            "type":"Retail Goods"
        }
    ],
    "sg:phone":"+39 0445 480961",
    "sg:postcode":"36078",
    "sg:province":"Vicenza",
    "sg:tags":[
        "clothing",
        "accessory"
    ],
    "wof:name":"Nastrificio Veneto Srl",
    "wof:placetype":"venue"
},
  "geometry": {"coordinates":[11.308481,45.62606],"type":"Point"}
}