{
  "type": "Feature",
  "properties": {
    "addr:full":"16166 Genova Genova Genova 16166",
    "addr:postcode":"16166;16166",
    "iso:country":"IT",
    "sg:address":"16166 Genova",
    "sg:city":"Genova",
    "sg:orig_category":"Pubblica Amministrazione",
    "sg:phone":"+39 010 322549",
    "sg:postcode":"16166",
    "sg:province":"Genova",
    "wof:name":"Universale Sas ' Augusto Gorziglia ' Di Enrico Gorziglia & C",
    "wof:placetype":"venue"
},
  "geometry": {"coordinates":[9.0216464996,44.3833885193],"type":"Point"}
}