{
  "type": "Feature",
  "properties": {
    "addr:full":"3/e, Via A. Gramsci 42023 Cadelbosco Di Sopra Reggio Nell'Emilia 42023",
    "addr:housenumber":"3 / e",
    "addr:postcode":"42023;42023",
    "addr:street":"Via A. Gramsci",
    "iso:country":"IT",
    "sg:address":"3/e, Via A. Gramsci 42023 Cadelbosco Di Sopra",
    "sg:classifiers":[
        {
            "category":"Shopping",
            "type":"Retail Goods"
        }
    ],
    "sg:phone":"+39 0522 911870",
    "sg:postcode":"42023",
    "sg:province":"Reggio Nell'Emilia",
    "sg:tags":[
        "finished",
        "-",
        "metallic"
    ],
    "wof:name":"M. P. Stampi (s.r.l.)",
    "wof:placetype":"venue"
},
  "geometry": {"coordinates":[10.6365861893,44.775390625],"type":"Point"}
}