{
  "type": "Feature",
  "properties": {
    "iso:country":"IT",
    "sg:address":"Via Marconi; Chiampo; 36072",
    "sg:city":"Chiampo",
    "sg:classifiers":[
        {
            "category":"Banks & Credit Unions",
            "subcategory":"Bank",
            "type":"Services"
        }
    ],
    "sg:phone":"+39 0444 420966",
    "sg:postcode":"36072",
    "sg:province":"Vicenza",
    "wof:name":"Banca Popolare Vicentina Scarl",
    "wof:placetype":"venue"
},
  "geometry": {"coordinates":[11.283331,45.545826],"type":"Point"}
}