{
  "type": "Feature",
  "properties": {
    "addr:full":"Via Copernico 1/a; Osnago",
    "addr:housenumber":"1 / a",
    "addr:street":"Via Copernico",
    "iso:country":"IT",
    "sg:address":"Via Copernico 1/a; Osnago",
    "sg:classifiers":[
        {
            "category":"Banks & Credit Unions",
            "subcategory":"Bank",
            "type":"Services"
        }
    ],
    "sg:phone":"+39 039 952 0015",
    "wof:name":"Banca Di Roma",
    "wof:placetype":"venue"
},
  "geometry": {"coordinates":[9.389801,45.670925],"type":"Point"}
}