{
  "type": "Feature",
  "properties": {
    "iso:country":"IT",
    "sg:address":"17047 Vado Ligure",
    "sg:city":"Vado Ligure",
    "sg:orig_category":"Isolanti Termici Ed Acustici - Installazione",
    "sg:phone":"+39 019 886005",
    "sg:postcode":"17047",
    "sg:province":"Savona",
    "wof:name":"C&d Di D'arrigo Giovanni & C. Sas",
    "wof:placetype":"venue"
},
  "geometry": {"coordinates":[8.374572,44.299606],"type":"Point"}
}