{
  "type": "Feature",
  "properties": {
    "iso:country":"IT",
    "sg:address":"21, Via Issogne 11029 Verres",
    "sg:city":"Verres",
    "sg:classifiers":[
        {
            "category":"Professional",
            "subcategory":"Engineering",
            "type":"Services"
        }
    ],
    "sg:phone":"+39 0125 920280",
    "sg:postcode":"11029",
    "sg:province":"Aosta",
    "sg:tags":[
        "machine",
        "-",
        "mechanical"
    ],
    "wof:name":"Metallurgiche Balzano",
    "wof:placetype":"venue"
},
  "geometry": {"coordinates":[7.688466,45.658581],"type":"Point"}
}