{
  "type": "Feature",
  "properties": {
    "addr:full":"20143 Milano Milano Milano 20143",
    "addr:postcode":"20143;20143",
    "iso:country":"IT",
    "sg:address":"20143 Milano",
    "sg:city":"Milano",
    "sg:orig_category":"Servizi Editoriali. Pubblicita', Marketing E Comunicazione",
    "sg:phone":"+39 02 8915 5134",
    "sg:postcode":"20143",
    "sg:province":"Milano",
    "wof:name":"Emblema Societa' Fotografica Editoriale Italiana Sas Di Pezzetti Riccardo & C",
    "wof:placetype":"venue"
},
  "geometry": {"coordinates":[9.155025,45.447208],"type":"Point"}
}