{
  "type": "Feature",
  "properties": {
    "addr:full":"32, Via Fiorentina 52011 Bibbiena Bibbiena Arezzo 52011",
    "addr:postcode":"52011;52011",
    "addr:street":"Via Fiorentina",
    "iso:country":"IT",
    "sg:address":"32, Via Fiorentina 52011 Bibbiena",
    "sg:city":"Bibbiena",
    "sg:classifiers":[
        {
            "category":"Shopping",
            "type":"Retail Goods"
        }
    ],
    "sg:phone":"+39 0575 560139",
    "sg:postcode":"52011",
    "sg:province":"Arezzo",
    "sg:tags":[
        "finished",
        "-",
        "metallic"
    ],
    "wof:name":"Ca.ma.no (s.n.c.)",
    "wof:placetype":"venue"
},
  "geometry": {"coordinates":[11.8041696548,43.7379226685],"type":"Point"}
}