{
  "type": "Feature",
  "properties": {
    "iso:country":"IT",
    "sg:address":"17, V. B. Buozzi 25125 Brescia",
    "sg:city":"Brescia",
    "sg:classifiers":[
        {
            "category":"Professional",
            "subcategory":"Engineering",
            "type":"Services"
        }
    ],
    "sg:phone":"+39 030 353 9052",
    "sg:postcode":"25125",
    "sg:province":"Brescia",
    "sg:tags":[
        "machine",
        "-",
        "mechanical"
    ],
    "sg:website":"http://www.pfcbrescia.it",
    "wof:name":"P.f.c. Srl",
    "wof:placetype":"venue"
},
  "geometry": {"coordinates":[10.161466,45.518509],"type":"Point"}
}