{
  "type": "Feature",
  "properties": {
    "iso:country":"IT",
    "sg:address":"09045 Quartu Sant'elena",
    "sg:orig_category":"Zootecnia E Pesca, Allevamento Piccoli Animali",
    "sg:phone":"+39 070 885200",
    "sg:postcode":"09045",
    "sg:province":"Cagliari",
    "wof:name":"Acquacoltura E Ricerca Soc. Coop. A R.l.",
    "wof:placetype":"venue"
},
  "geometry": {"coordinates":[9.267471,39.230923],"type":"Point"}
}