{
  "type": "Feature",
  "properties": {
    "iso:country":"IT",
    "sg:address":"33082 Azzano Decimo",
    "sg:city":"Azzano Decimo",
    "sg:classifiers":[
        {
            "category":"Manufacturing",
            "subcategory":"Tobacco Products",
            "type":"Manufacturing & Wholesale Goods"
        }
    ],
    "sg:phone":"+39 0434 631246",
    "sg:postcode":"33082",
    "sg:province":"Pordenone",
    "sg:tags":[
        "activities",
        "refuse",
        "industrial",
        "supply",
        "disposal",
        "environmental",
        "chemicals",
        "protection",
        "products",
        "machinery",
        "supplies",
        "secondary"
    ],
    "sg:website":"http://www.altur.it",
    "wof:name":"Altur Snc Di Turcatel M. & C.",
    "wof:placetype":"venue"
},
  "geometry": {"coordinates":[12.713155,45.886272],"type":"Point"}
}