{
  "type": "Feature",
  "properties": {
    "addr:full":"87100 Cosenza Cosenza Cosenza 87100",
    "addr:postcode":"87100;87100",
    "iso:country":"IT",
    "sg:address":"87100 Cosenza",
    "sg:city":"Cosenza",
    "sg:orig_category":"Cinematografia E Radiotelevisione. Pubblicita', Marketing E Comunicazione. Acqua, Luce, Gas E Societa' Di Esercizio Pubblico",
    "sg:phone":"+39 0984 4801",
    "sg:postcode":"87100",
    "sg:province":"Cosenza",
    "wof:name":"Rai Radiotelevisione Italiana",
    "wof:placetype":"venue"
},
  "geometry": {"coordinates":[16.256229,39.293175],"type":"Point"}
}