{
  "type": "Feature",
  "properties": {
    "iso:country":"IT",
    "sg:address":"37135 Verona",
    "sg:city":"Verona",
    "sg:orig_category":"Medici. Assicurazioni E Servizi Assicurativi. Avvocati, Notai E Servizi Legali. Professionisti - Studi E Servizi Ed Associazioni Di Interesse Aziendale",
    "sg:phone":"+39 045 820 0791",
    "sg:postcode":"37135",
    "sg:province":"Verona",
    "wof:name":"Studio Medico Associato L.romeo E.peroni S.martini D.zambon Specialisti In Medicina Del Lavoro",
    "wof:placetype":"venue"
},
  "geometry": {"coordinates":[10.9747409821,45.4101676941],"type":"Point"}
}