{
  "type": "Feature",
  "properties": {
    "addr:full":"20124 Milano Milano Milano 20124",
    "addr:postcode":"20124;20124",
    "iso:country":"IT",
    "sg:address":"20124 Milano",
    "sg:city":"Milano",
    "sg:classifiers":[
        {
            "category":"Professional",
            "subcategory":"Lawyer & Legal Services",
            "type":"Services"
        }
    ],
    "sg:phone":"+39 02 6738 0280",
    "sg:postcode":"20124",
    "sg:province":"Milano",
    "sg:tags":[
        "lawyers",
        "technical",
        "consultant",
        "services",
        "notary",
        "administrative",
        "appraiser"
    ],
    "sg:website":"http://www.botti-ferrari.com",
    "wof:name":"Botti & Ferrari Srl",
    "wof:placetype":"venue"
},
  "geometry": {"coordinates":[9.198327,45.481152],"type":"Point"}
}