{
  "type": "Feature",
  "properties": {
    "addr:full":"10014 Caluso Caluso Torino 10014",
    "addr:postcode":"10014;10014",
    "iso:country":"IT",
    "sg:address":"10014 Caluso",
    "sg:city":"Caluso",
    "sg:orig_category":"Forniture Per Uffici. Servizi Vari Di Interesse Pubblico",
    "sg:phone":"+39 011 983 1790",
    "sg:postcode":"10014",
    "sg:province":"Torino",
    "wof:name":"Leoni Laura",
    "wof:placetype":"venue"
},
  "geometry": {"coordinates":[7.8918476105,45.2555847168],"type":"Point"}
}