{
  "type": "Feature",
  "properties": {
    "iso:country":"IT",
    "sg:address":"20010 Cornaredo",
    "sg:city":"Cornaredo",
    "sg:orig_category":"Apparecchi, Attrezzature E Forniture Per Centri Estetici",
    "sg:phone":"+39 02 9356 3352",
    "sg:postcode":"20010",
    "sg:province":"Milano",
    "wof:name":"Nouvelles Cartes S.r.l",
    "wof:placetype":"venue"
},
  "geometry": {"coordinates":[9.030166,45.504791],"type":"Point"}
}