{
  "type": "Feature",
  "properties": {
    "addr:full":"48100 Ravenna Fornace zarattini Ravenna 48100",
    "addr:housenumber":"48100",
    "addr:postcode":"48100",
    "iso:country":"IT",
    "sg:address":"48100 Ravenna",
    "sg:city":"Fornace zarattini",
    "sg:orig_category":"Automobili E Mezzi Di Trasporto",
    "sg:phone":"+39 0544 465357",
    "sg:postcode":"48100",
    "sg:province":"Ravenna",
    "wof:name":"Lineabl\u00d9 Srl",
    "wof:placetype":"venue"
},
  "geometry": {"coordinates":[12.140048,44.416389],"type":"Point"}
}