{
  "type": "Feature",
  "properties": {
    "addr:full":"15, Via Cella Raibano 47843 Misano Adriatico Cella Rimini 47843",
    "addr:postcode":"47843;47843",
    "addr:street":"Via Cella Raibano",
    "iso:country":"IT",
    "sg:address":"15, Via Cella Raibano 47843 Misano Adriatico",
    "sg:city":"Cella",
    "sg:classifiers":[
        {
            "category":"Shopping",
            "type":"Retail Goods"
        }
    ],
    "sg:phone":"+39 0541 606320",
    "sg:postcode":"47843",
    "sg:province":"Rimini",
    "sg:tags":[
        "finished",
        "-",
        "metallic"
    ],
    "wof:name":"Masterlam Srl",
    "wof:placetype":"venue"
},
  "geometry": {"coordinates":[12.6458749771,43.972076416],"type":"Point"}
}