{
  "type": "Feature",
  "properties": {
    "addr:full":"43010 Fontevivo Fontevivo Parma 43010",
    "addr:postcode":"43010;43010",
    "iso:country":"IT",
    "sg:address":"43010 Fontevivo",
    "sg:city":"Fontevivo",
    "sg:orig_category":"Trasporti E Spedizioni Merci",
    "sg:phone":"+39 0521 615702",
    "sg:postcode":"43010",
    "sg:province":"Parma",
    "wof:name":"Centro Padano Interascmbio Merci (s.p.a.)",
    "wof:placetype":"venue"
},
  "geometry": {"coordinates":[10.235511,44.846992],"type":"Point"}
}