{
  "type": "Feature",
  "properties": {
    "iso:country":"IT",
    "sg:address":"20092 Cinisello Balsamo",
    "sg:city":"Cinisello Balsamo",
    "sg:orig_category":"Arredi Ed Attrezzature Per Uffici",
    "sg:phone":"+39 02 6604 7971",
    "sg:postcode":"20092",
    "sg:province":"Milano",
    "wof:name":"Sistema Ricambi (s.r.l.)",
    "wof:placetype":"venue"
},
  "geometry": {"coordinates":[9.232212,45.559952],"type":"Point"}
}