{
  "type": "Feature",
  "properties": {
    "iso:country":"IT",
    "sg:address":"20087 Robecco Sul Naviglio",
    "sg:city":"Robecco sul Naviglio",
    "sg:orig_category":"Servizi E Lavori Per Agricoltura E Zootecnia",
    "sg:phone":"+39 02 947 0636",
    "sg:postcode":"20087",
    "sg:province":"Milano",
    "wof:name":"Prandoni Gabriele",
    "wof:placetype":"venue"
},
  "geometry": {"coordinates":[8.889754,45.439571],"type":"Point"}
}