{
  "type": "Feature",
  "properties": {
    "iso:country":"IT",
    "sg:address":"7, Via Leopardi Giacomo 15048 Valenza",
    "sg:city":"Valenza",
    "sg:classifiers":[
        {
            "category":"Shopping",
            "subcategory":"Jewelry",
            "type":"Retail Goods"
        }
    ],
    "sg:phone":"+39 0131 953006",
    "sg:postcode":"15048",
    "sg:province":"Alessandria",
    "sg:tags":[
        "jewellery"
    ],
    "wof:name":"Megazzini Di Megazzini Massimo & C. S.a.s.",
    "wof:placetype":"venue"
},
  "geometry": {"coordinates":[8.637686,45.009781],"type":"Point"}
}