{
  "type": "Feature",
  "properties": {
    "addr:full":"56017 Pontasserchio Pontasserchio Pisa 56017",
    "addr:postcode":"56017;56017",
    "iso:country":"IT",
    "sg:address":"56017 Pontasserchio",
    "sg:city":"Pontasserchio",
    "sg:orig_category":"Prodotti Alimentari",
    "sg:phone":"+39 050 861225",
    "sg:postcode":"56017",
    "sg:province":"Pisa",
    "wof:name":"Pastificio Artigianale Jolly",
    "wof:placetype":"venue"
},
  "geometry": {"coordinates":[10.3938531876,43.7658195496],"type":"Point"}
}