{
  "type": "Feature",
  "properties": {
    "addr:full":"00195 Roma Roma Roma 00195",
    "addr:postcode":"00195;00195",
    "iso:country":"IT",
    "sg:address":"00195 Roma",
    "sg:city":"Roma",
    "sg:orig_category":"Hobbistica",
    "sg:phone":"+39 06 3735 3738",
    "sg:postcode":"00195",
    "sg:province":"Roma",
    "wof:name":"Le Nebbie Di Avalon",
    "wof:placetype":"venue"
},
  "geometry": {"coordinates":[12.458121,41.918045],"type":"Point"}
}