{
  "type": "Feature",
  "properties": {
    "iso:country":"IT",
    "sg:address":"72019 San Vito Dei Normanni",
    "sg:city":"San Vito dei Normanni",
    "sg:orig_category":"Forniture Per Agricoltura E Zootecnia",
    "sg:phone":"+39 0831 952299",
    "sg:postcode":"72019",
    "sg:province":"Brindisi",
    "wof:name":"Planet Di Giuseppe Iaia",
    "wof:placetype":"venue"
},
  "geometry": {"coordinates":[17.6999893188,40.6570739746],"type":"Point"}
}