{
  "type": "Feature",
  "properties": {
    "iso:country":"IT",
    "sg:address":"95127 Catania",
    "sg:city":"Catania",
    "sg:orig_category":"Arredo Cucina Ed Elettrodomestici",
    "sg:phone":"+39 095 551878",
    "sg:postcode":"95127",
    "sg:province":"Catania",
    "wof:name":"Studio Poggenpohl",
    "wof:placetype":"venue"
},
  "geometry": {"coordinates":[15.092556,37.518719],"type":"Point"}
}