{
  "type": "Feature",
  "properties": {
    "iso:country":"IT",
    "sg:address":"84019 Vietri Sul Mare",
    "sg:city":"Molina",
    "sg:classifiers":[
        {
            "category":"Shopping",
            "subcategory":"Gifts & Souvenirs",
            "type":"Retail Goods"
        }
    ],
    "sg:phone":"+39 089 210694",
    "sg:postcode":"84019",
    "sg:province":"Salerno",
    "sg:tags":[
        "gifts",
        "business"
    ],
    "wof:name":"Ceramica Margherita Di D'acunto Angela & C. Sas",
    "wof:placetype":"venue"
},
  "geometry": {"coordinates":[14.699599,40.671471],"type":"Point"}
}