{
  "type": "Feature",
  "properties": {
    "iso:country":"IT",
    "sg:address":"9, Via Salara 64026 Roseto Degli Abruzzi",
    "sg:city":"Roseto degli Abruzzi",
    "sg:classifiers":[
        {
            "category":"Food & Beverages",
            "subcategory":"Groceries & Convenience Stores",
            "type":"Retail Goods"
        }
    ],
    "sg:phone":"+39 085 899 0178",
    "sg:postcode":"64026",
    "sg:province":"Teramo",
    "sg:tags":[
        "product",
        "related"
    ],
    "wof:name":"Pastificio Verrigni Snc",
    "wof:placetype":"venue"
},
  "geometry": {"coordinates":[14.0222740173,42.6646842957],"type":"Point"}
}