{
  "type": "Feature",
  "properties": {
    "addr:full":"20090 Pieve Emanuele Pieve Emanuele Milano 20090",
    "addr:postcode":"20090;20090",
    "iso:country":"IT",
    "sg:address":"20090 Pieve Emanuele",
    "sg:city":"Pieve Emanuele",
    "sg:orig_category":"Tempo Libero - Articoli E Forniture. Accessori Dei Mezzi Di Trasporto",
    "sg:phone":"+39 02 9072 2385",
    "sg:postcode":"20090",
    "sg:province":"Milano",
    "wof:name":"Star Bianchi (s.r.l.)",
    "wof:placetype":"venue"
},
  "geometry": {"coordinates":[9.215263,45.378525],"type":"Point"}
}