{
  "type": "Feature",
  "properties": {
    "iso:country":"IT",
    "sg:address":"35037 Teolo",
    "sg:city":"Teolo",
    "sg:orig_category":"Arredo Bagno Ed Idrosanitari. Forniture Alle Strutture Ricettive. Apparecchi, Attrezzature E Forniture Per Centri Estetici",
    "sg:phone":"+39 049 993 5380",
    "sg:postcode":"35037",
    "sg:province":"Padova",
    "sg:website":"http://www.stenal.it",
    "wof:name":"Stenal Srl",
    "wof:placetype":"venue"
},
  "geometry": {"coordinates":[11.747521,45.352383],"type":"Point"}
}