{
  "type": "Feature",
  "properties": {
    "iso:country":"IT",
    "sg:address":"Via Santhia' 72 13881 Cavaglia'",
    "sg:classifiers":[
        {
            "category":"Government",
            "subcategory":"Post Office",
            "type":"Public Place"
        }
    ],
    "sg:phone":"+39 0161 96543",
    "sg:postcode":"13881",
    "sg:province":"Biella",
    "sg:tags":[
        "item",
        "household",
        "design"
    ],
    "wof:name":"Casastile - S.n.c. Di Carrara Agostino & C.",
    "wof:placetype":"venue"
},
  "geometry": {"coordinates":[8.12958,45.389122],"type":"Point"}
}