{
  "type": "Feature",
  "properties": {
    "addr:full":"73011 Alezio Alezio Lecce 73011",
    "addr:postcode":"73011;73011",
    "iso:country":"IT",
    "sg:address":"73011 Alezio",
    "sg:city":"Alezio",
    "sg:orig_category":"Artigianato Tipico",
    "sg:phone":"+39 0833 282874",
    "sg:postcode":"73011",
    "sg:province":"Lecce",
    "wof:name":"Arte Del Salento",
    "wof:placetype":"venue"
},
  "geometry": {"coordinates":[18.054955,40.05946],"type":"Point"}
}