{
  "type": "Feature",
  "properties": {
    "iso:country":"IT",
    "sg:address":"12084 Mondovi'",
    "sg:orig_category":"Servizi Ausiliari Di Certificati, Riproduzioni, Disegni E Foto",
    "sg:phone":"+39 0174 554258",
    "sg:postcode":"12084",
    "sg:province":"Cuneo",
    "wof:name":"Digital World Snc",
    "wof:placetype":"venue"
},
  "geometry": {"coordinates":[7.821198,44.390598],"type":"Point"}
}