{
  "type": "Feature",
  "properties": {
    "addr:full":"00198 Roma Roma Roma 00198",
    "addr:postcode":"00198;00198",
    "iso:country":"IT",
    "sg:address":"00198 Roma",
    "sg:city":"Roma",
    "sg:orig_category":"Librerie",
    "sg:phone":"+39 06 8535 8288",
    "sg:postcode":"00198",
    "sg:province":"Roma",
    "wof:name":"Libreria Quasar Di Bortot Liliana",
    "wof:placetype":"venue"
},
  "geometry": {"coordinates":[12.509624,41.919281],"type":"Point"}
}