{
  "type": "Feature",
  "properties": {
    "iso:country":"IT",
    "sg:address":"Via Ugo La Malfa 11 61030 Fano",
    "sg:classifiers":[
        {
            "category":"Structure",
            "subcategory":"Office Building",
            "type":"Public Place"
        }
    ],
    "sg:phone":"+39 0721 855448",
    "sg:postcode":"61030",
    "sg:province":"Pesaro E Urbino",
    "sg:tags":[
        "door",
        "accordion"
    ],
    "sg:website":"www.fanoflex.com",
    "wof:name":"Fanoflex",
    "wof:placetype":"venue"
},
  "geometry": {"coordinates":[12.529803,43.633556],"type":"Point"}
}