{
  "type": "Feature",
  "properties": {
    "addr:full":"55, Via Per Ornago 20040 Bellusco Bellusco Milano 20040",
    "addr:postcode":"20040;20040",
    "addr:street":"Via Per Ornago",
    "iso:country":"IT",
    "sg:address":"55, Via Per Ornago 20040 Bellusco",
    "sg:city":"Bellusco",
    "sg:classifiers":[
        {
            "category":"Manufacturing",
            "subcategory":"Paper Products",
            "type":"Manufacturing & Wholesale Goods"
        }
    ],
    "sg:phone":"+39 39039627451",
    "sg:postcode":"20040",
    "sg:province":"Milano",
    "sg:tags":[
        "cardboard"
    ],
    "wof:name":"International Paper Italia Spa",
    "wof:placetype":"venue"
},
  "geometry": {"coordinates":[9.1881408691,45.4636878967],"type":"Point"}
}