{
  "type": "Feature",
  "properties": {
    "iso:country":"IT",
    "sg:address":"Viale Della Stazione Di Prosecco 5/b, Sgonico, 34010 Trieste, Ts",
    "sg:city":"Sgonico",
    "sg:classifiers":[
        {
            "category":"Banks & Credit Unions",
            "subcategory":"Bank",
            "type":"Services"
        }
    ],
    "sg:postcode":"34010",
    "sg:province":"Trieste",
    "wof:name":"Telit Mobile Terminals Spa",
    "wof:placetype":"venue"
},
  "geometry": {"coordinates":[13.778407,45.653629],"type":"Point"}
}