{
  "type": "Feature",
  "properties": {
    "iso:country":"IT",
    "sg:address":"10, V. Fodde 07020 Buddus\u00f2",
    "sg:classifiers":[
        {
            "category":"Home & Garden",
            "subcategory":"Home Furnishings",
            "type":"Retail Goods"
        }
    ],
    "sg:phone":"+39 39079714043",
    "sg:postcode":"07020",
    "sg:province":"Olbia-Tempio",
    "sg:tags":[
        "household"
    ],
    "sg:website":"http://www.azetta.com/artintaglio",
    "wof:name":"Solinas Arte Intaglio Mastru Mimmiu",
    "wof:placetype":"venue"
},
  "geometry": {"coordinates":[9.255426,40.578182],"type":"Point"}
}