{
  "type": "Feature",
  "properties": {
    "addr:full":"77, Via S. Giuseppe La Rena 95121 Catania Catania Catania 95121",
    "addr:postcode":"95121;95121",
    "addr:street":"Via S. Giuseppe La Rena",
    "iso:country":"IT",
    "sg:address":"77, Via S. Giuseppe La Rena 95121 Catania",
    "sg:city":"Catania",
    "sg:classifiers":[
        {
            "category":"Shopping",
            "subcategory":"Clothing, Apparel, & Fashions",
            "type":"Retail Goods"
        }
    ],
    "sg:phone":"+39 095 723 2198",
    "sg:postcode":"95121",
    "sg:province":"Catania",
    "sg:tags":[
        "clothes"
    ],
    "wof:name":"Sidep Siciliana Depositi Spa",
    "wof:placetype":"venue"
},
  "geometry": {"coordinates":[15.035744,37.470638],"type":"Point"}
}