{
  "type": "Feature",
  "properties": {
    "iso:country":"IT",
    "sg:address":"20123 Milano",
    "sg:city":"Milano",
    "sg:orig_category":"Servizi Per Lo Sport E Il Tempo Libero. Servizi Al Turismo",
    "sg:phone":"+39 02 8645 1441",
    "sg:postcode":"20123",
    "sg:province":"Milano",
    "wof:name":"Ge.pe Srl Gestione Esercizi Pubblici",
    "wof:placetype":"venue"
},
  "geometry": {"coordinates":[9.18469,45.461018],"type":"Point"}
}