{
  "type": "Feature",
  "properties": {
    "iso:country":"IT",
    "sg:address":"46040 Rodigo",
    "sg:city":"Rodigo",
    "sg:orig_category":"Agricoltura, Orticoltura E Floricoltura",
    "sg:phone":"+39 0376 650465",
    "sg:postcode":"46040",
    "sg:province":"Mantova",
    "wof:name":"Mantovagricoltura Di Burato F. & C. Snc",
    "wof:placetype":"venue"
},
  "geometry": {"coordinates":[10.644482,45.206905],"type":"Point"}
}