{
  "type": "Feature",
  "properties": {
    "iso:country":"IT",
    "sg:address":"48, Strada Maratta Bassa 05100 Terni",
    "sg:city":"Terni",
    "sg:classifiers":[
        {
            "category":"Sports & Exercise",
            "subcategory":"Playing Field",
            "type":"Entertainment"
        }
    ],
    "sg:phone":"+39 0744 300347",
    "sg:postcode":"05100",
    "sg:province":"Terni",
    "sg:tags":[
        "game"
    ],
    "wof:name":"Societa' Riunite S.r.l",
    "wof:placetype":"venue"
},
  "geometry": {"coordinates":[12.601599,42.569881],"type":"Point"}
}