{
  "type": "Feature",
  "properties": {
    "iso:country":"IT",
    "sg:address":"75, Via Torino 10060 Airasca",
    "sg:city":"Airasca",
    "sg:classifiers":[
        {
            "category":"Autos & Motor Vehicles",
            "subcategory":"Automobile Sales",
            "type":"Retail Goods"
        }
    ],
    "sg:phone":"+39 011 990 8602",
    "sg:postcode":"10060",
    "sg:province":"Torino",
    "sg:tags":[
        "motor-cars"
    ],
    "wof:name":"Dayco Europe S.r.l A Socio Unico",
    "wof:placetype":"venue"
},
  "geometry": {"coordinates":[7.496243,44.9194755554],"type":"Point"}
}