{
  "type": "Feature",
  "properties": {
    "iso:country":"IT",
    "sg:address":"68, Via Marconi 30010 Cona",
    "sg:city":"Cona",
    "sg:classifiers":[
        {
            "category":"Real Estate",
            "subcategory":"Architect",
            "type":"Services"
        }
    ],
    "sg:phone":"+39 0426 509083",
    "sg:postcode":"30010",
    "sg:province":"Venezia",
    "sg:tags":[
        "textile",
        "clothing"
    ],
    "wof:name":"Fiorin Gilberto",
    "wof:placetype":"venue"
},
  "geometry": {"coordinates":[12.038318,45.189308],"type":"Point"}
}