{
  "type": "Feature",
  "properties": {
    "addr:full":"Via Cardito S. S., 90 20800 83031 Ariano Irpino Ariano Irpino Avellino 83031",
    "addr:housenumber":"90",
    "addr:postcode":"20800;83031",
    "addr:street":"Via Cardito S. S.;Irpino;Irpino",
    "iso:country":"IT",
    "sg:address":"Via Cardito S. S., 90 20800 83031 Ariano Irpino",
    "sg:city":"Ariano Irpino",
    "sg:classifiers":[
        {
            "category":"Structure",
            "subcategory":"Office Building",
            "type":"Public Place"
        }
    ],
    "sg:phone":"+39 0825 891945",
    "sg:postcode":"83031",
    "sg:province":"Avellino",
    "sg:tags":[
        "profiled",
        "window",
        "seal"
    ],
    "wof:name":"Deltaplast S.p.a.",
    "wof:placetype":"venue"
},
  "geometry": {"coordinates":[14.792722702,40.9147491455],"type":"Point"}
}