{
  "type": "Feature",
  "properties": {
    "addr:full":"20092 Cinisello Balsamo Cinisello Balsamo Milano 20092",
    "addr:postcode":"20092;20092",
    "iso:country":"IT",
    "sg:address":"20092 Cinisello Balsamo",
    "sg:city":"Cinisello Balsamo",
    "sg:orig_category":"Servizi E Lavori Per Ecologia E Smaltimento Rifiuti. Termotecnica E Riscaldamento, Apparecchiature E Servizi. Servizi Ausiliari Di Sorveglianza, Manutenzione E Pulizia",
    "sg:phone":"+39 02 6129 8372",
    "sg:postcode":"20092",
    "sg:province":"Milano",
    "wof:name":"Termofumi Srl",
    "wof:placetype":"venue"
},
  "geometry": {"coordinates":[9.220683,45.555634],"type":"Point"}
}