{
  "type": "Feature",
  "properties": {
    "iso:country":"IT",
    "sg:address":"70038 Terlizzi",
    "sg:city":"Terlizzi",
    "sg:orig_category":"Musica",
    "sg:phone":"+39 080 351 1398",
    "sg:postcode":"70038",
    "sg:province":"Bari",
    "wof:name":"Music Center Service",
    "wof:placetype":"venue"
},
  "geometry": {"coordinates":[16.6725559235,41.1875343323],"type":"Point"}
}