{
  "type": "Feature",
  "properties": {
    "iso:country":"IT",
    "sg:address":"70013 Castellana Grotte",
    "sg:city":"Castellana Grotte",
    "sg:orig_category":"Abbigliamento Alta Moda E Stilisti - Boutiques",
    "sg:phone":"+39 080 496 1775",
    "sg:postcode":"70013",
    "sg:province":"Bari",
    "sg:website":"http://www.paginegialle.it/calzaturesposa",
    "wof:name":"Beatrice Di Bellino Marcello",
    "wof:placetype":"venue"
},
  "geometry": {"coordinates":[17.183903,40.86869],"type":"Point"}
}