{
  "type": "Feature",
  "properties": {
    "addr:full":"10141 Torino Torino Torino 10141",
    "addr:postcode":"10141;10141",
    "iso:country":"IT",
    "sg:address":"10141 Torino",
    "sg:city":"Torino",
    "sg:orig_category":"Forniture Per Edilizia E Lavori Pubblici. Prodotti Vari In Metallo",
    "sg:phone":"+39 011 377569",
    "sg:postcode":"10141",
    "sg:province":"Torino",
    "wof:name":"Global Service Ponteggi Srl",
    "wof:placetype":"venue"
},
  "geometry": {"coordinates":[7.6456346512,45.0579719543],"type":"Point"}
}