{
  "type": "Feature",
  "properties": {
    "addr:full":"20049 Concorezzo Concorezzo Milano 20049",
    "addr:postcode":"20049;20049",
    "iso:country":"IT",
    "sg:address":"20049 Concorezzo",
    "sg:city":"Concorezzo",
    "sg:orig_category":"Frigoriferi Industriali E Commerciali - Produzione",
    "sg:phone":"+39 039 604 0566",
    "sg:postcode":"20049",
    "sg:province":"Milano",
    "wof:name":"Frimer Snc",
    "wof:placetype":"venue"
},
  "geometry": {"coordinates":[9.3368177414,45.5933952332],"type":"Point"}
}