{
  "type": "Feature",
  "properties": {
    "iso:country":"IT",
    "sg:address":"13, Via Piemonte 35043 Monselice",
    "sg:city":"Monselice",
    "sg:classifiers":[
        {
            "category":"Sports & Exercise",
            "subcategory":"Playing Field",
            "type":"Entertainment"
        }
    ],
    "sg:phone":"+39 39042972230",
    "sg:postcode":"35043",
    "sg:province":"Padova",
    "sg:tags":[
        "game"
    ],
    "wof:name":"Intertoys S.a.s. Di Bizzaro Valeriano E C.",
    "wof:placetype":"venue"
},
  "geometry": {"coordinates":[11.74879,45.221954],"type":"Point"}
}