{
  "type": "Feature",
  "properties": {
    "iso:country":"IT",
    "sg:address":"98100 Messina",
    "sg:orig_category":"Ospedali E Servizi Sanitari",
    "sg:phone":"+39 090 629040",
    "sg:province":"ME",
    "wof:name":"San Mauro Sas Di Di Salvo Letterio & C.",
    "wof:placetype":"venue"
},
  "geometry": {"coordinates":[15.505354,38.100151],"type":"Point"}
}