{
  "type": "Feature",
  "properties": {
    "iso:country":"IT",
    "sg:address":"00187 Roma",
    "sg:city":"Roma",
    "sg:orig_category":"Articoli Da Regalo. Shopping. Regalistica Aziendale",
    "sg:phone":"+39 06 4281 5256",
    "sg:postcode":"00187",
    "sg:province":"Roma",
    "wof:name":"Souvenirs Tritone S.r.l.",
    "wof:placetype":"venue"
},
  "geometry": {"coordinates":[12.485875,41.902916],"type":"Point"}
}