{
  "type": "Feature",
  "properties": {
    "iso:country":"IT",
    "sg:address":"20092 Cinisello Balsamo",
    "sg:city":"Cinisello Balsamo",
    "sg:orig_category":"Articoli Per Fumatori",
    "sg:phone":"+39 02 242 1903",
    "sg:postcode":"20092",
    "sg:province":"Milano",
    "sg:website":"http://www.bi-effe.com",
    "wof:name":"Bi-effe Di Beretta Aldo & C. Snc",
    "wof:placetype":"venue"
},
  "geometry": {"coordinates":[9.226615,45.54567],"type":"Point"}
}