{
  "type": "Feature",
  "properties": {
    "iso:country":"IT",
    "sg:address":"84015 Nocera Superiore",
    "sg:city":"Nocera Superiore",
    "sg:orig_category":"Argenterie - Vendita Al Dettaglio",
    "sg:phone":"+39 081 514 4629",
    "sg:postcode":"84015",
    "sg:province":"Salerno",
    "wof:name":"Angolo D'oro Di Morrone Annarita Sas",
    "wof:placetype":"venue"
},
  "geometry": {"coordinates":[14.676273,40.73407],"type":"Point"}
}