{
  "type": "Feature",
  "properties": {
    "addr:full":"25030 Torbole Casaglia Torbole Casaglia Brescia 25030",
    "addr:postcode":"25030;25030",
    "iso:country":"IT",
    "sg:address":"25030 Torbole Casaglia",
    "sg:city":"Torbole Casaglia",
    "sg:orig_category":"Apparecchiature E Sistemi Per Magazzinaggio E Movimentazione. Macchine E Impianti Per Attivita' Commerciali Ed Artigianali. Macchine, Strumenti Ed Apparecchi Per Attivita' Industriali",
    "sg:phone":"+39 030 265 0828",
    "sg:postcode":"25030",
    "sg:province":"Brescia",
    "wof:name":"Civini Bilance Di Civini Remo & C. Snc",
    "wof:placetype":"venue"
},
  "geometry": {"coordinates":[10.126692,45.518864],"type":"Point"}
}