{
  "type": "Feature",
  "properties": {
    "addr:full":"20154 Milano Milano Milano 20154",
    "addr:postcode":"20154;20154",
    "iso:country":"IT",
    "sg:address":"20154 Milano",
    "sg:city":"Milano",
    "sg:orig_category":"Servizi Ausiliari Dei Mezzi Di Trasporto",
    "sg:phone":"+39 02 331 9959",
    "sg:postcode":"20154",
    "sg:province":"Milano",
    "wof:name":"Autorimessa Sempione",
    "wof:placetype":"venue"
},
  "geometry": {"coordinates":[9.166327,45.48225],"type":"Point"}
}