{
  "type": "Feature",
  "properties": {
    "iso:country":"IT",
    "sg:address":"39100 Bolzano",
    "sg:city":"Bolzano",
    "sg:orig_category":"Pubblicita', Marketing E Comunicazione",
    "sg:phone":"+39 0471 979711",
    "sg:postcode":"39100",
    "sg:province":"Bolzano/Bozen",
    "wof:name":"Piovesan Schutz Laura Lps",
    "wof:placetype":"venue"
},
  "geometry": {"coordinates":[11.3618354797,46.5006942749],"type":"Point"}
}