{
  "type": "Feature",
  "properties": {
    "iso:country":"IT",
    "sg:address":"64021 Giulianova",
    "sg:city":"Giulianova",
    "sg:orig_category":"Forniture Per Attivita' Industriali",
    "sg:phone":"+39 085 800 8850",
    "sg:postcode":"64021",
    "sg:province":"Teramo",
    "wof:name":"Gaglioti Ricambi Industriali Snc",
    "wof:placetype":"venue"
},
  "geometry": {"coordinates":[13.9594936371,42.7594642639],"type":"Point"}
}