{
  "type": "Feature",
  "properties": {
    "addr:full":"31028 Tezze Tezze Treviso 31028",
    "addr:postcode":"31028;31028",
    "iso:country":"IT",
    "sg:address":"31028 Tezze",
    "sg:city":"Tezze",
    "sg:orig_category":"Forniture Per Attivita' Industriali",
    "sg:phone":"+39 0438 488075",
    "sg:postcode":"31028",
    "sg:province":"Treviso",
    "wof:name":"Jolly P. Plast S.a.s.",
    "wof:placetype":"venue"
},
  "geometry": {"coordinates":[12.2582292557,45.6562957764],"type":"Point"}
}