{
  "type": "Feature",
  "properties": {
    "iso:country":"IT",
    "sg:address":"9, Via Siena 36070 Castelgomberto",
    "sg:city":"Castelgomberto",
    "sg:classifiers":[
        {
            "category":"Manufacturing",
            "subcategory":"Textiles",
            "type":"Manufacturing & Wholesale Goods"
        }
    ],
    "sg:phone":"+39 0445 941076",
    "sg:postcode":"36070",
    "sg:province":"Vicenza",
    "sg:tags":[
        "leather",
        "raw",
        "material",
        "-"
    ],
    "wof:name":"Pina S.n.c.",
    "wof:placetype":"venue"
},
  "geometry": {"coordinates":[11.393551,45.584362],"type":"Point"}
}