{
  "type": "Feature",
  "properties": {
    "addr:full":"Via Ghislarengo 28064 Carpignano Sesia Carpignano Sesia Novara 28064",
    "addr:postcode":"28064;28064",
    "addr:street":"Via Ghislarengo",
    "iso:country":"IT",
    "sg:address":"Via Ghislarengo 28064 Carpignano Sesia",
    "sg:city":"Carpignano Sesia",
    "sg:classifiers":[
        {
            "category":"Farming",
            "subcategory":"Livestock Farm",
            "type":"Manufacturing & Wholesale Goods"
        }
    ],
    "sg:phone":"+39 0321 825122",
    "sg:postcode":"28064",
    "sg:province":"Novara",
    "sg:tags":[
        "agriculture"
    ],
    "wof:name":"Riso Mittino - Riserie D'italia (s.r.l.)",
    "wof:placetype":"venue"
},
  "geometry": {"coordinates":[8.422143,45.534931],"type":"Point"}
}