{
  "type": "Feature",
  "properties": {
    "addr:full":"Via C. Ottone 14 27029 Vigevano Vigevano Pavia 27029",
    "addr:housenumber":"14",
    "addr:postcode":"27029;27029",
    "addr:street":"Via C. Ottone",
    "iso:country":"IT",
    "sg:address":"Via C. Ottone 14 27029 Vigevano",
    "sg:city":"Vigevano",
    "sg:classifiers":[
        {
            "category":"Manufacturing",
            "subcategory":"Rubber & Plastics",
            "type":"Manufacturing & Wholesale Goods"
        }
    ],
    "sg:phone":"+39 0381 348332",
    "sg:postcode":"27029",
    "sg:province":"Pavia",
    "sg:tags":[
        "device",
        "processing"
    ],
    "wof:name":"Costruzioni Meccaniche C.m.v. Di Simonetti Anna & C Sas",
    "wof:placetype":"venue"
},
  "geometry": {"coordinates":[9.156563,45.185886],"type":"Point"}
}