{
  "type": "Feature",
  "properties": {
    "addr:full":"Corso P Giannone 64; Caserta",
    "addr:housenumber":"64",
    "addr:street":"Corso P Giannone",
    "iso:country":"IT",
    "sg:address":"Corso P Giannone 64; Caserta",
    "sg:classifiers":[
        {
            "category":"Banks & Credit Unions",
            "subcategory":"Bank",
            "type":"Services"
        }
    ],
    "sg:phone":"+39 0823 444744",
    "wof:name":"Banca Di Roma",
    "wof:placetype":"venue"
},
  "geometry": {"coordinates":[14.331285,41.07769],"type":"Point"}
}