{
  "type": "Feature",
  "properties": {
    "iso:country":"IT",
    "sg:address":"37131 Verona",
    "sg:city":"Verona",
    "sg:orig_category":"Non-classified Establishments",
    "sg:phone":"+39 045 534098",
    "sg:postcode":"37131",
    "sg:province":"Verona",
    "wof:name":"Del Prete Marco",
    "wof:placetype":"venue"
},
  "geometry": {"coordinates":[11.019567,45.453331],"type":"Point"}
}