{
  "type": "Feature",
  "properties": {
    "iso:country":"IT",
    "sg:address":"52100 Arezzo",
    "sg:city":"Arezzo",
    "sg:orig_category":"Argenteria - Lavorazione E Ingrosso",
    "sg:phone":"+39 0575 382517",
    "sg:postcode":"52100",
    "sg:province":"Arezzo",
    "wof:name":"Oro 90 Srl",
    "wof:placetype":"venue"
},
  "geometry": {"coordinates":[11.86221,43.478271],"type":"Point"}
}