{
  "type": "Feature",
  "properties": {
    "iso:country":"IT",
    "sg:address":"50028 Tavarnelle Val Di Pesa",
    "sg:city":"Tavarnelle Val di Pesa",
    "sg:orig_category":"Accessori Moda D'abbigliamento. Forniture Per Abbigliamento E Pelletterie. Shopping",
    "sg:phone":"+39 055 807 2916",
    "sg:postcode":"50028",
    "sg:province":"Firenze",
    "wof:name":"Aiguille D'or S.n.c.",
    "wof:placetype":"venue"
},
  "geometry": {"coordinates":[11.199808,43.59082],"type":"Point"}
}