{
  "type": "Feature",
  "properties": {
    "iso:country":"IT",
    "sg:address":"50059 Vinci",
    "sg:city":"Vinci",
    "sg:orig_category":"Animali Domestici, Articoli Ed Attrezzature - Produzione E Ingrosso",
    "sg:phone":"+39 0571 585755",
    "sg:postcode":"50059",
    "sg:province":"Firenze",
    "wof:name":"Malucchi Srl",
    "wof:placetype":"venue"
},
  "geometry": {"coordinates":[10.873394,43.791897],"type":"Point"}
}