{
  "type": "Feature",
  "properties": {
    "addr:full":"6, Frazione Zoccolo 13835 Trivero Trivero Biella 13835",
    "addr:postcode":"13835;13835",
    "addr:street":"Frazione Zoccolo",
    "iso:country":"IT",
    "sg:address":"6, Frazione Zoccolo 13835 Trivero",
    "sg:city":"Trivero",
    "sg:classifiers":[
        {
            "category":"Shopping",
            "subcategory":"Crafts & Fabrics",
            "type":"Retail Goods"
        }
    ],
    "sg:phone":"+39 390 157 5135",
    "sg:postcode":"13835",
    "sg:province":"Biella",
    "wof:name":"Comune Giovanni & C. Di Comune Claudio (s.a.s.)",
    "wof:placetype":"venue"
},
  "geometry": {"coordinates":[8.1722669601,45.6699676514],"type":"Point"}
}