{
  "type": "Feature",
  "properties": {
    "addr:full":"16, Via Mameli Goffredo 20058 Villasanta Villasanta Milano 20058",
    "addr:postcode":"20058;20058",
    "addr:street":"Via Mameli Goffredo",
    "iso:country":"IT",
    "sg:address":"16, Via Mameli Goffredo 20058 Villasanta",
    "sg:city":"Villasanta",
    "sg:classifiers":[
        {
            "category":"Shopping",
            "subcategory":"Crafts & Fabrics",
            "type":"Retail Goods"
        }
    ],
    "sg:phone":"+39 039 205 0317",
    "sg:postcode":"20058",
    "sg:province":"Milano",
    "wof:name":"Rossi Tessuti Arredamento S.r.l.",
    "wof:placetype":"venue"
},
  "geometry": {"coordinates":[9.1881408691,45.4636878967],"type":"Point"}
}