{
  "type": "Feature",
  "properties": {
    "iso:country":"IT",
    "sg:address":"90044 Carini",
    "sg:city":"Carini",
    "sg:orig_category":"Legno E Semilavorati. Manufatti Edili E Prefabbricati",
    "sg:phone":"+39 091 868 8311",
    "sg:postcode":"90044",
    "sg:province":"Palermo",
    "wof:name":"Ipa Spa",
    "wof:placetype":"venue"
},
  "geometry": {"coordinates":[13.220803,38.165516],"type":"Point"}
}