{
  "type": "Feature",
  "properties": {
    "iso:country":"IT",
    "sg:address":"55012 Capannori",
    "sg:city":"Capannori",
    "sg:orig_category":"Pavimenti",
    "sg:phone":"+39 0583 981082",
    "sg:postcode":"55012",
    "sg:province":"Lucca",
    "wof:name":"Il Quadrifoglio Di Franciosini Umberto Snc",
    "wof:placetype":"venue"
},
  "geometry": {"coordinates":[10.548535347,43.8964309692],"type":"Point"}
}