{
  "type": "Feature",
  "properties": {
    "iso:country":"IT",
    "sg:address":"51035 Lamporecchio",
    "sg:city":"Lamporecchio",
    "sg:orig_category":"Agenzie Immobiliari",
    "sg:phone":"+39 0573 88027",
    "sg:postcode":"51035",
    "sg:province":"Pistoia",
    "wof:name":"Agenzia Montalbano",
    "wof:placetype":"venue"
},
  "geometry": {"coordinates":[10.921136,43.86372],"type":"Point"}
}