{
  "type": "Feature",
  "properties": {
    "addr:full":"Raggio Dell'ostro 63; Lignano",
    "addr:housenumber":"63",
    "addr:street":"Dell'Ostro",
    "iso:country":"IT",
    "sg:address":"Raggio Dell'ostro 63; Lignano",
    "sg:classifiers":[
        {
            "category":"Banks & Credit Unions",
            "subcategory":"Bank",
            "type":"Services"
        }
    ],
    "sg:phone":"+39 0431 427469",
    "wof:name":"Banca Popolare Friuladria",
    "wof:placetype":"venue"
},
  "geometry": {"coordinates":[13.107534,45.667366],"type":"Point"}
}