{
  "type": "Feature",
  "properties": {
    "iso:country":"IT",
    "sg:address":"73100 Lecce",
    "sg:city":"Lecce",
    "sg:orig_category":"Argenterie - Vendita Al Dettaglio",
    "sg:phone":"+39 0832 317309",
    "sg:postcode":"73100",
    "sg:province":"Lecce",
    "wof:name":"Iacovelli Sas",
    "wof:placetype":"venue"
},
  "geometry": {"coordinates":[18.179607,40.353313],"type":"Point"}
}