{
  "type": "Feature",
  "properties": {
    "addr:full":"82037 Telese Terme Telese Terme Benevento 82037",
    "addr:postcode":"82037;82037",
    "iso:country":"IT",
    "sg:address":"82037 Telese Terme",
    "sg:city":"Telese Terme",
    "sg:orig_category":"Elettrotecnica Industriale, Prodotti E Apparecchiature. Elettrotecnica Professionale E Di Consumo",
    "sg:phone":"+39 0824 941887",
    "sg:postcode":"82037",
    "sg:province":"Benevento",
    "wof:name":"Alfieri Giovanni & C. Spa",
    "wof:placetype":"venue"
},
  "geometry": {"coordinates":[14.518705,41.218502],"type":"Point"}
}