{
  "type": "Feature",
  "properties": {
    "iso:country":"IT",
    "sg:address":"40141 Bologna",
    "sg:city":"Bologna",
    "sg:orig_category":"Giornalai",
    "sg:phone":"+39 051 473162",
    "sg:postcode":"40141",
    "sg:province":"Bologna",
    "wof:name":"Edicola Degli Esposti Gianni",
    "wof:placetype":"venue"
},
  "geometry": {"coordinates":[11.370197,44.47192],"type":"Point"}
}