{
  "type": "Feature",
  "properties": {
    "iso:country":"IT",
    "sg:address":"21047 Saronno",
    "sg:city":"Saronno",
    "sg:orig_category":"Metalli E Leghe",
    "sg:phone":"+39 02 9624 8710",
    "sg:postcode":"21047",
    "sg:province":"Varese",
    "wof:name":"B.s. Alloy Service Srl",
    "wof:placetype":"venue"
},
  "geometry": {"coordinates":[9.037021637,45.6295928955],"type":"Point"}
}