{
  "type": "Feature",
  "properties": {
    "iso:country":"IT",
    "sg:address":"7, Largo Domodossola 20145 Milano",
    "sg:city":"Milano",
    "sg:classifiers":[
        {
            "category":"Wholesale",
            "subcategory":"Drugs",
            "type":"Manufacturing & Wholesale Goods"
        }
    ],
    "sg:phone":"+39 390 234 5531",
    "sg:postcode":"20145",
    "sg:province":"Milano",
    "sg:tags":[
        "chemical",
        "pharmaceutical"
    ],
    "wof:name":"Compagnia Italiana Lubrificanti S.p.a.",
    "wof:placetype":"venue"
},
  "geometry": {"coordinates":[9.160355,45.480072],"type":"Point"}
}