{
  "type": "Feature",
  "properties": {
    "iso:country":"IT",
    "sg:address":"32013 Longarone",
    "sg:city":"Longarone",
    "sg:orig_category":"Astucci",
    "sg:phone":"+39 0437 573130",
    "sg:postcode":"32013",
    "sg:province":"Belluno",
    "wof:name":"Scatolificio Bellunese Srl",
    "wof:placetype":"venue"
},
  "geometry": {"coordinates":[12.283333,46.233334],"type":"Point"}
}