{
  "type": "Feature",
  "properties": {
    "addr:full":"59100 Prato Prato Prato 59100",
    "addr:postcode":"59100;59100",
    "iso:country":"IT",
    "sg:address":"59100 Prato",
    "sg:city":"Prato",
    "sg:orig_category":"Forniture Per Attivita' Industriali",
    "sg:phone":"+39 0574 33679",
    "sg:postcode":"59100",
    "sg:province":"Prato",
    "wof:name":"Giusti Cesare Giuseppe",
    "wof:placetype":"venue"
},
  "geometry": {"coordinates":[11.0836610794,43.8759460449],"type":"Point"}
}