{
  "type": "Feature",
  "properties": {
    "iso:country":"IT",
    "sg:address":"34, Via Brioschi Ferrante 20045 Besana In Brianza",
    "sg:city":"Besana in Brianza",
    "sg:classifiers":[
        {
            "category":"Home & Garden",
            "subcategory":"Home Furnishings",
            "type":"Retail Goods"
        }
    ],
    "sg:phone":"+39 036 296 7530",
    "sg:postcode":"20045",
    "sg:province":"Milano",
    "sg:tags":[
        "household"
    ],
    "wof:name":"Gruppo U.n.i.c.a. Srl",
    "wof:placetype":"venue"
},
  "geometry": {"coordinates":[9.188141,45.463688],"type":"Point"}
}