{
  "type": "Feature",
  "properties": {
    "iso:country":"IT",
    "sg:address":"Via Marconi 16 31035 Crocetta Del Montello",
    "sg:city":"Crocetta del Montello",
    "sg:classifiers":[
        {
            "category":"Manufacturing",
            "subcategory":"Wood Products",
            "type":"Manufacturing & Wholesale Goods"
        }
    ],
    "sg:phone":"+39 0423 86263",
    "sg:postcode":"31035",
    "sg:province":"Treviso",
    "sg:tags":[
        "case"
    ],
    "wof:name":"Segheria Piave Srl",
    "wof:placetype":"venue"
},
  "geometry": {"coordinates":[12.242072,45.666286],"type":"Point"}
}