{
  "type": "Feature",
  "properties": {
    "addr:full":"00133 Roma Roma Roma 00133",
    "addr:postcode":"00133;00133",
    "iso:country":"IT",
    "sg:address":"00133 Roma",
    "sg:city":"Roma",
    "sg:orig_category":"Materiali Edili",
    "sg:phone":"+39 06 205 2933",
    "sg:postcode":"00133",
    "sg:province":"Roma",
    "wof:name":"Cemenfer Srl",
    "wof:placetype":"venue"
},
  "geometry": {"coordinates":[12.653855,41.871319],"type":"Point"}
}