{
  "type": "Feature",
  "properties": {
    "iso:country":"IT",
    "sg:address":"25125 Brescia",
    "sg:city":"Brescia",
    "sg:orig_category":"Banche E Servizi Finanziari. Agenzie D'affari E Servizi Commerciali",
    "sg:phone":"+39 030 353 0968",
    "sg:postcode":"25125",
    "sg:province":"Brescia",
    "wof:name":"Mercato Mobiliare Di Nord-est S.p.a.",
    "wof:placetype":"venue"
},
  "geometry": {"coordinates":[10.188512,45.526779],"type":"Point"}
}