{
  "type": "Feature",
  "properties": {
    "iso:country":"IT",
    "sg:address":"00192 Roma",
    "sg:city":"Roma",
    "sg:orig_category":"Servizi Ausiliari Per Il Trasporto. Servizi Vari Di Interesse Pubblico",
    "sg:phone":"+39 06 324 1754",
    "sg:postcode":"00192",
    "sg:province":"Roma",
    "wof:name":"Audino Snc",
    "wof:placetype":"venue"
},
  "geometry": {"coordinates":[12.462062,41.907921],"type":"Point"}
}