{
  "type": "Feature",
  "properties": {
    "iso:country":"IT",
    "sg:address":"38070 Padergnone",
    "sg:city":"Padergnone",
    "sg:orig_category":"Bevande, Vini E Liquori. Agricoltura, Orticoltura E Floricoltura",
    "sg:phone":"+39 0461 864142",
    "sg:postcode":"38070",
    "sg:province":"Trento",
    "wof:name":"Vivai Cooperativi Di Padergnone",
    "wof:placetype":"venue"
},
  "geometry": {"coordinates":[10.990325,46.058998],"type":"Point"}
}