{
  "type": "Feature",
  "properties": {
    "addr:full":"20035 Lissone Lissone Milano 20035",
    "addr:postcode":"20035;20035",
    "iso:country":"IT",
    "sg:address":"20035 Lissone",
    "sg:city":"Lissone",
    "sg:orig_category":"Servizi Ausiliari Di Analisi, Controllo E Ricerca",
    "sg:phone":"+39 039 464567",
    "sg:postcode":"20035",
    "sg:province":"Milano",
    "sg:website":"http://www.catas.com",
    "wof:name":"C.a.t.a.s. Spa",
    "wof:placetype":"venue"
},
  "geometry": {"coordinates":[9.166376,45.413746],"type":"Point"}
}