{
  "type": "Feature",
  "properties": {
    "addr:full":"Corso Genova 29 20123 Milano Milano Milano 20123",
    "addr:housenumber":"29",
    "addr:postcode":"20123;20123",
    "addr:street":"Corso Genova",
    "iso:country":"IT",
    "sg:address":"Corso Genova 29 20123 Milano",
    "sg:city":"Milano",
    "sg:classifiers":[
        {
            "category":"Professional",
            "subcategory":"Business Services",
            "type":"Services"
        }
    ],
    "sg:phone":"+39 02 833821",
    "sg:postcode":"20123",
    "sg:province":"Milano",
    "sg:tags":[
        "high-precision",
        "mechanic"
    ],
    "wof:name":"Telema Spa",
    "wof:placetype":"venue"
},
  "geometry": {"coordinates":[9.173971,45.456146],"type":"Point"}
}