{
  "type": "Feature",
  "properties": {
    "addr:full":"33037 Pasian Di Prato Pasian di Prato Udine 33037",
    "addr:postcode":"33037;33037",
    "iso:country":"IT",
    "sg:address":"33037 Pasian Di Prato",
    "sg:city":"Pasian di Prato",
    "sg:orig_category":"Forniture Per Attivita' Industriali",
    "sg:phone":"+39 0432 644314",
    "sg:postcode":"33037",
    "sg:province":"Udine",
    "wof:name":"Gkn Srl",
    "wof:placetype":"venue"
},
  "geometry": {"coordinates":[13.16218853,46.0530815125],"type":"Point"}
}