{
  "type": "Feature",
  "properties": {
    "addr:full":"15100 Alessandria Alessandria Alessandria 15100",
    "addr:postcode":"15100;15100",
    "iso:country":"IT",
    "sg:address":"15100 Alessandria",
    "sg:city":"Alessandria",
    "sg:orig_category":"Colori, Vernici E Smalti - Vendita Al Dettaglio",
    "sg:phone":"+39 0131 260020",
    "sg:postcode":"15100",
    "sg:province":"Alessandria",
    "wof:name":"Hobby Market - T.e.i.c.o. Srl",
    "wof:placetype":"venue"
},
  "geometry": {"coordinates":[8.626416,44.910576],"type":"Point"}
}