{
  "type": "Feature",
  "properties": {
    "addr:full":"35020 Polverara Polverara Padova 35020",
    "addr:postcode":"35020;35020",
    "iso:country":"IT",
    "sg:address":"35020 Polverara",
    "sg:city":"Polverara",
    "sg:orig_category":"Climatizzazione E Condizionamento, Apparecchiature E Servizi. Elettrodomestici",
    "sg:phone":"+39 049 585 5355",
    "sg:postcode":"35020",
    "sg:province":"Padova",
    "wof:name":"Antoni S.r.l.",
    "wof:placetype":"venue"
},
  "geometry": {"coordinates":[11.938669,45.309807],"type":"Point"}
}