{
  "type": "Feature",
  "properties": {
    "iso:country":"IT",
    "sg:address":"44049 Vigarano Mainarda",
    "sg:city":"Vigarano Mainarda",
    "sg:orig_category":"Forniture Per Edilizia E Lavori Pubblici",
    "sg:phone":"+39 0532 436464",
    "sg:postcode":"44049",
    "sg:province":"Ferrara",
    "wof:name":"Rampado Snc",
    "wof:placetype":"venue"
},
  "geometry": {"coordinates":[11.5031709671,44.8407592773],"type":"Point"}
}