{
  "type": "Feature",
  "properties": {
    "iso:country":"IT",
    "sg:address":"23, Via Risorgimento 22070 Lurago Marinone",
    "sg:city":"Lurago Marinone",
    "sg:classifiers":[
        {
            "category":"Home & Garden",
            "subcategory":"Home Furnishings",
            "type":"Retail Goods"
        }
    ],
    "sg:phone":"+39 39031935864",
    "sg:postcode":"22070",
    "sg:province":"Como",
    "sg:tags":[
        "household"
    ],
    "wof:name":"S.i.l.l.",
    "wof:placetype":"venue"
},
  "geometry": {"coordinates":[8.983513,45.707302],"type":"Point"}
}