{
  "type": "Feature",
  "properties": {
    "addr:full":"49, Via Battisti 22070 Locate Varesino Locate Varesino Como 22070",
    "addr:housenumber":"varesino",
    "addr:postcode":"22070;22070",
    "addr:street":"Via Battisti",
    "iso:country":"IT",
    "sg:address":"49, Via Battisti 22070 Locate Varesino",
    "sg:city":"Locate Varesino",
    "sg:classifiers":[
        {
            "category":"Manufacturing",
            "subcategory":"Printing",
            "type":"Manufacturing & Wholesale Goods"
        }
    ],
    "sg:phone":"+39 0331 830154",
    "sg:postcode":"22070",
    "sg:province":"Como",
    "sg:tags":[
        "publishing"
    ],
    "wof:name":"Castiglioni Cartotecnica (s.p.a.)",
    "wof:placetype":"venue"
},
  "geometry": {"coordinates":[9.0854558945,45.8119659424],"type":"Point"}
}