{
  "type": "Feature",
  "properties": {
    "addr:full":"61040 Barchi Barchi Pesaro E Urbino 61040",
    "addr:postcode":"61040;61040",
    "iso:country":"IT",
    "sg:address":"61040 Barchi",
    "sg:city":"Barchi",
    "sg:orig_category":"Non-classified Establishments",
    "sg:phone":"+39 0721 981890",
    "sg:postcode":"61040",
    "sg:province":"Pesaro E Urbino",
    "wof:name":"Linea Arredamenti Di Tombari Alvaro",
    "wof:placetype":"venue"
},
  "geometry": {"coordinates":[12.892218,43.69622],"type":"Point"}
}