{
  "type": "Feature",
  "properties": {
    "iso:country":"IT",
    "sg:address":"22036 Erba",
    "sg:city":"Erba",
    "sg:orig_category":"Non-classified Establishments",
    "sg:phone":"+39 031 641195",
    "sg:postcode":"22036",
    "sg:province":"Como",
    "wof:name":"Colombo Pietro",
    "wof:placetype":"venue"
},
  "geometry": {"coordinates":[9.228731,45.802696],"type":"Point"}
}