{
  "type": "Feature",
  "properties": {
    "iso:country":"IT",
    "sg:address":"12038 Savigliano",
    "sg:city":"Savigliano",
    "sg:orig_category":"Non-classified Establishments",
    "sg:phone":"+39 0172 726186",
    "sg:postcode":"12038",
    "sg:province":"Cuneo",
    "wof:name":"C.e.r.s. Snc",
    "wof:placetype":"venue"
},
  "geometry": {"coordinates":[7.676516,44.648762],"type":"Point"}
}