{
  "type": "Feature",
  "properties": {
    "iso:country":"IT",
    "sg:address":"22020 Drezzo",
    "sg:city":"Drezzo",
    "sg:orig_category":"Termotecnica E Riscaldamento, Apparecchiature E Servizi. Prodotti Vari In Metallo",
    "sg:phone":"+39 031 440873",
    "sg:postcode":"22020",
    "sg:province":"Como",
    "wof:name":"Ecocalor Snc",
    "wof:placetype":"venue"
},
  "geometry": {"coordinates":[8.9987,45.813263],"type":"Point"}
}