{
  "type": "Feature",
  "properties": {
    "iso:country":"IT",
    "sg:address":"16, Via Bosco 41030 San Prospero Sulla Secchia",
    "sg:city":"San Prospero",
    "sg:classifiers":[
        {
            "category":"Wholesale",
            "subcategory":"Medical Equipment & Supplies",
            "type":"Manufacturing & Wholesale Goods"
        }
    ],
    "sg:phone":"+39 39059908999",
    "sg:postcode":"41030",
    "sg:province":"Modena",
    "sg:tags":[
        "-",
        "health",
        "instrument"
    ],
    "wof:name":"Alessandrini Strumentazione (s.p.a.)",
    "wof:placetype":"venue"
},
  "geometry": {"coordinates":[11.045014,44.810345],"type":"Point"}
}