{
  "type": "Feature",
  "properties": {
    "iso:country":"IT",
    "sg:address":"23807 Merate",
    "sg:city":"Merate",
    "sg:orig_category":"Impianti, Attrezzature E Forniture Sanitarie Ed Ospedaliere",
    "sg:phone":"+39 039 990 8816",
    "sg:postcode":"23807",
    "sg:province":"Lecco",
    "wof:name":"Bonfanti (s.n.c.)",
    "wof:placetype":"venue"
},
  "geometry": {"coordinates":[9.424027,45.697998],"type":"Point"}
}