{
  "type": "Feature",
  "properties": {
    "iso:country":"IT",
    "sg:address":"20029 Turbigo",
    "sg:city":"Turbigo",
    "sg:orig_category":"Prodotti E Manufatti In Materie Plastiche. Prodotti Cosmetici E Da Toeletta. Forniture Per Attivita' Industriali",
    "sg:phone":"+39 0331 871587",
    "sg:postcode":"20029",
    "sg:province":"Milano",
    "wof:name":"Confezione Lisa Di Modica Emilia",
    "wof:placetype":"venue"
},
  "geometry": {"coordinates":[9.1856527328,45.4514923096],"type":"Point"}
}