{
  "type": "Feature",
  "properties": {
    "iso:country":"IT",
    "sg:address":"27013 Chignolo Po",
    "sg:city":"Chignolo Po",
    "sg:orig_category":"Forniture Per Abbigliamento E Pelletterie",
    "sg:phone":"+39 0382 723027",
    "sg:postcode":"27013",
    "sg:province":"Pavia",
    "wof:name":"Ideal Piumini Snc",
    "wof:placetype":"venue"
},
  "geometry": {"coordinates":[9.1559715271,45.1852645874],"type":"Point"}
}