{
  "type": "Feature",
  "properties": {
    "iso:country":"IT",
    "sg:address":"35019 Tombolo",
    "sg:city":"Tombolo",
    "sg:orig_category":"Trasporti E Spedizioni Merci",
    "sg:phone":"+39 049 596 8723",
    "sg:postcode":"35019",
    "sg:province":"Padova",
    "wof:name":"Ditta Andretta Giuseppe E Figli Di Andretta Amelio E R. Snc",
    "wof:placetype":"venue"
},
  "geometry": {"coordinates":[11.849185,45.646255],"type":"Point"}
}