{
  "type": "Feature",
  "properties": {
    "iso:country":"IT",
    "sg:address":"92100 Agrigento",
    "sg:city":"Agrigento",
    "sg:orig_category":"Box Prefabbricati",
    "sg:phone":"+39 0922 591226",
    "sg:postcode":"92100",
    "sg:province":"Agrigento",
    "wof:name":"Mata Costruzioni",
    "wof:placetype":"venue"
},
  "geometry": {"coordinates":[13.628471,37.356991],"type":"Point"}
}