{
  "type": "Feature",
  "properties": {
    "iso:country":"IT",
    "sg:address":"00138 Roma",
    "sg:city":"Roma",
    "sg:classifiers":[
        {
            "category":"Sports & Exercise",
            "subcategory":"Tennis Court",
            "type":"Entertainment"
        }
    ],
    "sg:phone":"+39 06 8713 3902",
    "sg:postcode":"00138",
    "sg:province":"Roma",
    "sg:tags":[
        "e",
        "lo",
        "tempo",
        "libero",
        "per",
        "impianti",
        "il",
        "attrezzature"
    ],
    "wof:name":"New Green Hill Srl",
    "wof:placetype":"venue"
},
  "geometry": {"coordinates":[12.52967,42.015732],"type":"Point"}
}