{
  "type": "Feature",
  "properties": {
    "addr:full":"1, Via Tasso 37010 Costermano Costermano Verona 37010",
    "addr:postcode":"37010;37010",
    "addr:street":"Via Tasso",
    "iso:country":"IT",
    "sg:address":"1, Via Tasso 37010 Costermano",
    "sg:city":"Costermano",
    "sg:classifiers":[
        {
            "category":"Wholesale",
            "subcategory":"Machinery & Supplies",
            "type":"Manufacturing & Wholesale Goods"
        }
    ],
    "sg:phone":"+39 045 720 0888",
    "sg:postcode":"37010",
    "sg:province":"Verona",
    "sg:tags":[
        "-",
        "agriculture",
        "equipment"
    ],
    "wof:name":"Sita Societa' Installazioni Tecnologie Agricole (s.r.l.)",
    "wof:placetype":"venue"
},
  "geometry": {"coordinates":[10.764956,45.56741],"type":"Point"}
}