{
  "type": "Feature",
  "properties": {
    "addr:full":"83100 Avellino Avellino Avellino 83100",
    "addr:postcode":"83100;83100",
    "iso:country":"IT",
    "sg:address":"83100 Avellino",
    "sg:city":"Avellino",
    "sg:classifiers":[
        {
            "category":"Health Services",
            "subcategory":"Health Practitioner",
            "type":"Services"
        }
    ],
    "sg:phone":"+39 0825 22958",
    "sg:postcode":"83100",
    "sg:province":"Avellino",
    "sg:tags":[
        "medici"
    ],
    "wof:name":"Nutile Gaetano",
    "wof:placetype":"venue"
},
  "geometry": {"coordinates":[14.7872228622,40.9165725708],"type":"Point"}
}