{
  "type": "Feature",
  "properties": {
    "addr:full":"46030 Cerese Cerese Mantova 46030",
    "addr:postcode":"46030;46030",
    "addr:street":"Cerese",
    "iso:country":"IT",
    "sg:address":"46030 Cerese",
    "sg:city":"Cerese",
    "sg:orig_category":"Accessori Moda D'abbigliamento. Shopping",
    "sg:phone":"+39 0376 280921",
    "sg:postcode":"46030",
    "sg:province":"Mantova",
    "wof:name":"Da Andre Di Franchini Andrea",
    "wof:placetype":"venue"
},
  "geometry": {"coordinates":[10.784559,45.114983],"type":"Point"}
}