{
  "type": "Feature",
  "properties": {
    "iso:country":"IT",
    "sg:address":"20098 S. Giuliano Milanese",
    "sg:orig_category":"Strumenti Per Misura, Controllo E Regolazione",
    "sg:phone":"+39 02 988 0404",
    "sg:postcode":"20098",
    "sg:province":"Milano",
    "wof:name":"Colima Srl",
    "wof:placetype":"venue"
},
  "geometry": {"coordinates":[9.246363,45.403515],"type":"Point"}
}