{
  "type": "Feature",
  "properties": {
    "addr:full":"00191 Roma Roma Roma 00191",
    "addr:postcode":"00191;00191",
    "iso:country":"IT",
    "sg:address":"00191 Roma",
    "sg:city":"Roma",
    "sg:orig_category":"Professionisti - Studi E Servizi Ed Associazioni Di Interesse Aziendale. Servizi Sociali. Associazioni Ed Organismi Di Interesse Pubblico",
    "sg:phone":"+39 06 329 5240",
    "sg:postcode":"00191",
    "sg:province":"Roma",
    "wof:name":"Lega Italiana Contro I Tumori",
    "wof:placetype":"venue"
},
  "geometry": {"coordinates":[12.4701328278,41.9474105835],"type":"Point"}
}