{
  "type": "Feature",
  "properties": {
    "iso:country":"IT",
    "sg:address":"2, Via Bibiana 12031 Bagnolo Piemonte",
    "sg:city":"Bagnolo Piemonte",
    "sg:classifiers":[
        {
            "category":"Manufacturing",
            "subcategory":"Glass & Minerals",
            "type":"Manufacturing & Wholesale Goods"
        }
    ],
    "sg:phone":"+39 0175 392392",
    "sg:postcode":"12031",
    "sg:province":"Cuneo",
    "sg:tags":[
        "building",
        "material"
    ],
    "wof:name":"Ediltutto",
    "wof:placetype":"venue"
},
  "geometry": {"coordinates":[7.309038,44.767838],"type":"Point"}
}