{
  "type": "Feature",
  "properties": {
    "iso:country":"IT",
    "sg:address":"4, Vl. G. Marconi 00146 Roma",
    "sg:city":"Roma",
    "sg:classifiers":[
        {
            "category":"Communications",
            "subcategory":"Television Station",
            "type":"Services"
        }
    ],
    "sg:phone":"+39 06 5530 0575",
    "sg:postcode":"00146",
    "sg:province":"Roma",
    "sg:tags":[
        "audio-visual"
    ],
    "sg:website":"http://www.harmonia.it",
    "wof:name":"Harmonia Srl",
    "wof:placetype":"venue"
},
  "geometry": {"coordinates":[12.467714,41.869251],"type":"Point"}
}