{
  "type": "Feature",
  "properties": {
    "iso:country":"IT",
    "sg:address":"Via Luigi Vanvitelli 7 22063 Cantu'",
    "sg:classifiers":[
        {
            "category":"Manufacturing",
            "subcategory":"Glass & Minerals",
            "type":"Manufacturing & Wholesale Goods"
        }
    ],
    "sg:phone":"+39 031 714946",
    "sg:postcode":"22063",
    "sg:province":"Como",
    "sg:tags":[
        "finishing"
    ],
    "sg:website":"www.makingglass.it",
    "wof:name":"Making Glass S.r.l.",
    "wof:placetype":"venue"
},
  "geometry": {"coordinates":[9.140995,45.735371],"type":"Point"}
}