{
  "type": "Feature",
  "properties": {
    "addr:full":"20037 Paderno Dugnano Paderno Dugnano Milano 20037",
    "addr:postcode":"20037;20037",
    "iso:country":"IT",
    "sg:address":"20037 Paderno Dugnano",
    "sg:city":"Paderno Dugnano",
    "sg:orig_category":"Agenzie D'affari E Servizi Commerciali",
    "sg:phone":"+39 02 918 2787",
    "sg:postcode":"20037",
    "sg:province":"Milano",
    "wof:name":"Gestioni & Servizi",
    "wof:placetype":"venue"
},
  "geometry": {"coordinates":[9.165664,45.561264],"type":"Point"}
}