{
  "type": "Feature",
  "properties": {
    "addr:full":"92, Corso Sicilia 98040 Torregrotta Torregrotta Messina 98040",
    "addr:postcode":"98040;98040",
    "addr:street":"Corso Sicilia",
    "iso:country":"IT",
    "sg:address":"92, Corso Sicilia 98040 Torregrotta",
    "sg:city":"Torregrotta",
    "sg:classifiers":[
        {
            "category":"Food & Beverages",
            "subcategory":"Dairy",
            "type":"Retail Goods"
        }
    ],
    "sg:phone":"+39 090 998 1186",
    "sg:postcode":"98040",
    "sg:province":"Messina",
    "sg:tags":[
        "product"
    ],
    "wof:name":"Industria Casearia Velo Sas",
    "wof:placetype":"venue"
},
  "geometry": {"coordinates":[15.349566,38.206177],"type":"Point"}
}