{
  "type": "Feature",
  "properties": {
    "iso:country":"IT",
    "sg:address":"13900 Biella",
    "sg:city":"Biella",
    "sg:orig_category":"Attrezzature E Forniture Per Officine Riparazione E Servizi Ausiliari",
    "sg:phone":"+39 015 403140",
    "sg:postcode":"13900",
    "sg:province":"Biella",
    "wof:name":"Garella Elettroricambi Di Garella Bruno & C. (s.n.c.)",
    "wof:placetype":"venue"
},
  "geometry": {"coordinates":[8.054688,45.555931],"type":"Point"}
}