{
  "type": "Feature",
  "properties": {
    "iso:country":"IT",
    "sg:address":"34133 Trieste",
    "sg:city":"Trieste",
    "sg:orig_category":"Pubblica Amministrazione",
    "sg:phone":"+39 040 779 2111",
    "sg:postcode":"34133",
    "sg:province":"Trieste",
    "wof:name":"Uffici Giudiziari",
    "wof:placetype":"venue"
},
  "geometry": {"coordinates":[13.7797822952,45.6544837952],"type":"Point"}
}