{
  "type": "Feature",
  "properties": {
    "iso:country":"IT",
    "sg:address":"10148 Torino",
    "sg:city":"Torino",
    "sg:orig_category":"Vigilanza E Sorveglianza",
    "sg:phone":"+39 011 22521",
    "sg:postcode":"10148",
    "sg:province":"Torino",
    "wof:name":"Union Security Srl",
    "wof:placetype":"venue"
},
  "geometry": {"coordinates":[7.670164,45.106548],"type":"Point"}
}