{
  "type": "Feature",
  "properties": {
    "addr:full":"107, Via Lufrano 80026 Casoria Casoria Napoli 80026",
    "addr:housenumber":"107",
    "addr:postcode":"80026;80026",
    "addr:street":"Via Lufrano",
    "iso:country":"IT",
    "sg:address":"107, Via Lufrano 80026 Casoria",
    "sg:city":"Casoria",
    "sg:classifiers":[
        {
            "category":"Sports & Exercise",
            "subcategory":"Playing Field",
            "type":"Entertainment"
        }
    ],
    "sg:phone":"+39 081 774 4833",
    "sg:postcode":"80026",
    "sg:province":"Napoli",
    "sg:tags":[
        "game"
    ],
    "wof:name":"Electrogames Di De Martino Arturo E C. Sas",
    "wof:placetype":"venue"
},
  "geometry": {"coordinates":[14.335067,40.886471],"type":"Point"}
}