{
  "type": "Feature",
  "properties": {
    "iso:country":"IT",
    "sg:address":"1, Via Giuseppe Verdi 31010 Cimadolmo",
    "sg:city":"Cimadolmo",
    "sg:classifiers":[
        {
            "category":"Shopping",
            "subcategory":"Crafts & Fabrics",
            "type":"Retail Goods"
        }
    ],
    "sg:phone":"+39 0422 743027",
    "sg:postcode":"31010",
    "sg:province":"Treviso",
    "sg:tags":[
        "ceramic"
    ],
    "wof:name":"F.lli Falsarella Spa",
    "wof:placetype":"venue"
},
  "geometry": {"coordinates":[12.344918,45.797462],"type":"Point"}
}