{
  "type": "Feature",
  "properties": {
    "iso:country":"IT",
    "sg:address":"31, Via Zucchi Carlo 41100 Modena",
    "sg:city":"Modena",
    "sg:classifiers":[
        {
            "category":"Manufacturing",
            "subcategory":"Tools & Machinery",
            "type":"Manufacturing & Wholesale Goods"
        }
    ],
    "sg:phone":"+39 39059822614",
    "sg:postcode":"41100",
    "sg:province":"Modena",
    "sg:tags":[
        "environment",
        "equipment",
        "-"
    ],
    "wof:name":"Consulting Service Srl Societa' A Responsabilita' Limitata",
    "wof:placetype":"venue"
},
  "geometry": {"coordinates":[10.92522,44.647079],"type":"Point"}
}