{
  "type": "Feature",
  "properties": {
    "iso:country":"IT",
    "sg:address":"1, Via Umberto I 07026 Olbia",
    "sg:city":"Olbia",
    "sg:classifiers":[
        {
            "category":"Marine",
            "type":"Transportation"
        }
    ],
    "sg:phone":"+39 39078923524",
    "sg:postcode":"07026",
    "sg:province":"Olbia-Tempio",
    "sg:tags":[
        "transport",
        "sea"
    ],
    "wof:name":"Unimare Unione Agenti Marittimi S.r.l.",
    "wof:placetype":"venue"
},
  "geometry": {"coordinates":[9.483603,40.927494],"type":"Point"}
}