{
  "type": "Feature",
  "properties": {
    "addr:full":"Via Beura 44 28844 Villadossola Villadossola Verbano-Cusio-Ossola 28844",
    "addr:housenumber":"44",
    "addr:postcode":"28844;28844",
    "addr:street":"Via Beura",
    "iso:country":"IT",
    "sg:address":"Via Beura 44 28844 Villadossola",
    "sg:city":"Villadossola",
    "sg:classifiers":[
        {
            "category":"Utilities",
            "subcategory":"Natural Gas",
            "type":"Services"
        }
    ],
    "sg:phone":"+39 0324 575106",
    "sg:postcode":"28844",
    "sg:province":"Verbano-Cusio-Ossola",
    "sg:tags":[
        "blasting",
        "explosive",
        "drilling",
        "quarry"
    ],
    "sg:website":"www.mariniqg.it",
    "wof:name":"Marini Quarries Group Srl",
    "wof:placetype":"venue"
},
  "geometry": {"coordinates":[8.272465,46.139969],"type":"Point"}
}