{
  "type": "Feature",
  "properties": {
    "iso:country":"IT",
    "sg:address":"40138 Bologna",
    "sg:city":"Bologna",
    "sg:orig_category":"Arte Ed Artigianato Artistico",
    "sg:phone":"+39 051 601 4827",
    "sg:postcode":"40138",
    "sg:province":"Bologna",
    "wof:name":"S.d.r. Engineering Srl",
    "wof:placetype":"venue"
},
  "geometry": {"coordinates":[11.398565,44.499325],"type":"Point"}
}