{
  "type": "Feature",
  "properties": {
    "iso:country":"IT",
    "sg:address":"00198 Roma",
    "sg:city":"Roma",
    "sg:orig_category":"Servizi Per Aziende, Manifestazioni E Supporto Agli Scambi Commerciali",
    "sg:phone":"+39 06 852371",
    "sg:postcode":"00198",
    "sg:province":"Roma",
    "wof:name":"Executive Services Business Centres Spa",
    "wof:placetype":"venue"
},
  "geometry": {"coordinates":[12.500775,41.913536],"type":"Point"}
}