{
  "type": "Feature",
  "properties": {
    "addr:full":"20033 Desio Desio Milano 20033",
    "addr:postcode":"20033;20033",
    "iso:country":"IT",
    "sg:address":"20033 Desio",
    "sg:city":"Desio",
    "sg:orig_category":"Manufacturers: Prefabbricati",
    "sg:phone":"+39 036 233 1161",
    "sg:postcode":"20033",
    "sg:province":"Milano",
    "sg:website":"http://www.termocom.it",
    "wof:name":"Termocom Srl",
    "wof:placetype":"venue"
},
  "geometry": {"coordinates":[9.198744,45.61895],"type":"Point"}
}