{
  "type": "Feature",
  "properties": {
    "iso:country":"IT",
    "sg:address":"Via Faentina 169 50010 Caldine",
    "sg:city":"Caldine",
    "sg:classifiers":[
        {
            "category":"Professional",
            "subcategory":"Advertising",
            "type":"Services"
        }
    ],
    "sg:phone":"+39 055 541261",
    "sg:postcode":"50010",
    "sg:province":"Firenze",
    "sg:tags":[
        "poster"
    ],
    "wof:name":"Target Pubblicita' Srl",
    "wof:placetype":"venue"
},
  "geometry": {"coordinates":[11.303431,43.826866],"type":"Point"}
}