{
  "type": "Feature",
  "properties": {
    "iso:country":"IT",
    "sg:address":"31030 Carbonera",
    "sg:city":"Carbonera",
    "sg:orig_category":"Edilizia - Materiali",
    "sg:phone":"+39 0422 445507",
    "sg:postcode":"31030",
    "sg:province":"Treviso",
    "wof:name":"Silcart Srl",
    "wof:placetype":"venue"
},
  "geometry": {"coordinates":[12.326929,45.686245],"type":"Point"}
}