{
  "type": "Feature",
  "properties": {
    "addr:full":"Via Davila 40; Piove Di Sacco; 35028 Piove di Sacco Padova 35028",
    "addr:housenumber":"40",
    "addr:postcode":"35028;35028",
    "addr:street":"Via Davila",
    "iso:country":"IT",
    "sg:address":"Via Davila 40; Piove Di Sacco; 35028",
    "sg:city":"Piove di Sacco",
    "sg:classifiers":[
        {
            "category":"Banks & Credit Unions",
            "subcategory":"Bank",
            "type":"Services"
        }
    ],
    "sg:phone":"+39 049 970 0655",
    "sg:postcode":"35028",
    "sg:province":"Padova",
    "wof:name":"Istituto Bancario, San Paolo Di Torino Spa",
    "wof:placetype":"venue"
},
  "geometry": {"coordinates":[12.036781,45.300041],"type":"Point"}
}