{
  "type": "Feature",
  "properties": {
    "iso:country":"IT",
    "sg:address":"00148 Roma",
    "sg:city":"Roma",
    "sg:orig_category":"Cartotecnica E Servizi. Composizione, Stampa E Confezione. Servizi E Lavori Industria Delle Materie Plastiche. Servizi Per Imballaggio E Confezionamento",
    "sg:phone":"+39 06 657 2685",
    "sg:postcode":"00148",
    "sg:province":"Roma",
    "wof:name":"Seriplast Snc Di Sgnaolin Maurizio & C.",
    "wof:placetype":"venue"
},
  "geometry": {"coordinates":[12.428543,41.834663],"type":"Point"}
}