{
  "type": "Feature",
  "properties": {
    "iso:country":"IT",
    "sg:address":"302, Via Dei Gianni 55100 Lucca",
    "sg:city":"Lucca",
    "sg:classifiers":[
        {
            "category":"Shopping",
            "subcategory":"Crafts & Fabrics",
            "type":"Retail Goods"
        }
    ],
    "sg:phone":"+39 0583 998126",
    "sg:postcode":"55100",
    "sg:province":"Lucca",
    "wof:name":"Idea Tessuto (s.r.l.)",
    "wof:placetype":"venue"
},
  "geometry": {"coordinates":[10.5338220596,43.8616104126],"type":"Point"}
}