{
  "type": "Feature",
  "properties": {
    "iso:country":"IT",
    "sg:address":"70029 Santeramo In Colle",
    "sg:city":"Santeramo in Colle",
    "sg:orig_category":"Dolciumi E Gelati",
    "sg:phone":"+39 080 302 6525",
    "sg:postcode":"70029",
    "sg:province":"Bari",
    "wof:name":"Dolce Forno Di Giove Tiziana",
    "wof:placetype":"venue"
},
  "geometry": {"coordinates":[16.759283,40.791767],"type":"Point"}
}