{
  "type": "Feature",
  "properties": {
    "iso:country":"IT",
    "sg:address":"95040 Belpasso",
    "sg:orig_category":"Non-classified Establishments",
    "sg:phone":"+39 095 791 3796",
    "sg:postcode":"95040",
    "sg:province":"Catania",
    "wof:name":"Sinatra Antonino",
    "wof:placetype":"venue"
},
  "geometry": {"coordinates":[15.087834,37.502483],"type":"Point"}
}