{
  "type": "Feature",
  "properties": {
    "addr:full":"20, Via Pasubio 24025 Gazzaniga Gazzaniga Bergamo 24025",
    "addr:postcode":"24025;24025",
    "addr:street":"Via Pasubio",
    "iso:country":"IT",
    "sg:address":"20, Via Pasubio 24025 Gazzaniga",
    "sg:city":"Gazzaniga",
    "sg:classifiers":[
        {
            "category":"Real Estate",
            "subcategory":"Architect",
            "type":"Services"
        }
    ],
    "sg:phone":"+39 39035713421",
    "sg:postcode":"24025",
    "sg:province":"Bergamo",
    "sg:tags":[
        "textile",
        "clothing"
    ],
    "wof:name":"Candotex S.r.l.",
    "wof:placetype":"venue"
},
  "geometry": {"coordinates":[9.828712,45.792061],"type":"Point"}
}