{
  "type": "Feature",
  "properties": {
    "iso:country":"IT",
    "sg:address":"00174 Roma",
    "sg:city":"Roma",
    "sg:orig_category":"Trasporti E Spedizioni Merci",
    "sg:phone":"+39 06 7158 7673",
    "sg:postcode":"00174",
    "sg:province":"Roma",
    "wof:name":"Il Recapito Espresso Di G. Di Carlo & C. Sas",
    "wof:placetype":"venue"
},
  "geometry": {"coordinates":[12.561688,41.854408],"type":"Point"}
}