{
  "type": "Feature",
  "properties": {
    "iso:country":"IT",
    "sg:address":"34077 Ronchi Dei Legionari",
    "sg:city":"Ronchi dei Legionari",
    "sg:orig_category":"Imprese Di Costruzioni Civili Ed Industriali",
    "sg:phone":"+39 0481 778652",
    "sg:postcode":"34077",
    "sg:province":"Gorizia",
    "sg:website":"http://www.ansercostruzioni.it",
    "wof:name":"An.s.e.r. Srl",
    "wof:placetype":"venue"
},
  "geometry": {"coordinates":[13.500229,45.824284],"type":"Point"}
}