{
  "type": "Feature",
  "properties": {
    "addr:full":"21020 Brebbia Brebbia Varese 21020",
    "addr:postcode":"21020;21020",
    "iso:country":"IT",
    "sg:address":"21020 Brebbia",
    "sg:city":"Brebbia",
    "sg:orig_category":"Forniture Per Edilizia E Lavori Pubblici. Arredi Ed Attrezzature Per Attivita' Commerciali Ed Artigianali. Forniture Per Attivita' Industriali",
    "sg:phone":"+39 0332 771149",
    "sg:postcode":"21020",
    "sg:province":"Varese",
    "wof:name":"Realini & C. Srl",
    "wof:placetype":"venue"
},
  "geometry": {"coordinates":[8.7102069855,45.8088417053],"type":"Point"}
}