{
  "type": "Feature",
  "properties": {
    "iso:country":"IT",
    "sg:address":"00197 Roma",
    "sg:city":"Roma",
    "sg:orig_category":"Ambasciate Ed Enti Internazionali",
    "sg:phone":"+39 06 320 7249",
    "sg:postcode":"00197",
    "sg:province":"Roma",
    "wof:name":"Ambasciata Presso La S. Sede Nicaragua",
    "wof:placetype":"venue"
},
  "geometry": {"coordinates":[12.480801,41.922211],"type":"Point"}
}