{
  "type": "Feature",
  "properties": {
    "iso:country":"IT",
    "sg:address":"64, Via Carducci 56017 San Giuliano Terme",
    "sg:city":"San Giuliano Terme",
    "sg:classifiers":[
        {
            "category":"Wholesale",
            "subcategory":"Drugs",
            "type":"Manufacturing & Wholesale Goods"
        }
    ],
    "sg:phone":"+39 39050879834",
    "sg:postcode":"56017",
    "sg:province":"Pisa",
    "sg:tags":[
        "chemical",
        "pharmaceutical"
    ],
    "wof:name":"Grifols Italia Spa",
    "wof:placetype":"venue"
},
  "geometry": {"coordinates":[10.42067,43.725044],"type":"Point"}
}