{
  "type": "Feature",
  "properties": {
    "addr:full":"94, Via Vallazze 20131 Milano Milano Milano 20131",
    "addr:postcode":"20131;20131",
    "addr:street":"Via Vallazze",
    "iso:country":"IT",
    "sg:address":"94, Via Vallazze 20131 Milano",
    "sg:city":"Milano",
    "sg:classifiers":[
        {
            "category":"Professional",
            "subcategory":"Advertising",
            "type":"Services"
        }
    ],
    "sg:phone":"+39 02 7063 5445",
    "sg:postcode":"20131",
    "sg:province":"Milano",
    "sg:tags":[
        "communication",
        "medium"
    ],
    "wof:name":"Granata Photo Stock Srl",
    "wof:placetype":"venue"
},
  "geometry": {"coordinates":[9.228803,45.484657],"type":"Point"}
}