{
  "type": "Feature",
  "properties": {
    "iso:country":"IT",
    "sg:address":"104, Via Colle 80049 Somma Vesuviana",
    "sg:city":"Somma Vesuviana",
    "sg:classifiers":[
        {
            "category":"Wholesale",
            "subcategory":"Medical Equipment & Supplies",
            "type":"Manufacturing & Wholesale Goods"
        }
    ],
    "sg:phone":"+39 081 893 1992",
    "sg:postcode":"80049",
    "sg:province":"Napoli",
    "sg:tags":[
        "-",
        "health",
        "instrument"
    ],
    "wof:name":"Svas Biosana S.r.l.",
    "wof:placetype":"venue"
},
  "geometry": {"coordinates":[14.469976,40.876831],"type":"Point"}
}