{
  "type": "Feature",
  "properties": {
    "iso:country":"IT",
    "sg:address":"39100 Bolzano",
    "sg:city":"Bolzano",
    "sg:orig_category":"Servizi Per Aziende, Manifestazioni E Supporto Agli Scambi Commerciali",
    "sg:phone":"+39 0471 300040",
    "sg:postcode":"39100",
    "sg:province":"Bolzano/Bozen",
    "wof:name":"S.i.r. Detectives",
    "wof:placetype":"venue"
},
  "geometry": {"coordinates":[11.356112,46.498768],"type":"Point"}
}