{
  "type": "Feature",
  "properties": {
    "addr:full":"25068 Sarezzo Sarezzo Brescia 25068",
    "addr:postcode":"25068;25068",
    "iso:country":"IT",
    "sg:address":"25068 Sarezzo",
    "sg:city":"Sarezzo",
    "sg:classifiers":[
        {
            "category":"Home & Garden",
            "subcategory":"Home Furnishings",
            "type":"Retail Goods"
        }
    ],
    "sg:phone":"+39 030 832881",
    "sg:postcode":"25068",
    "sg:province":"Brescia",
    "sg:tags":[
        "bathroom",
        "accessories"
    ],
    "sg:website":"http://www.isa-idrosanitaria.it",
    "wof:name":"I.s.a. Idrosanitaria Spa",
    "wof:placetype":"venue"
},
  "geometry": {"coordinates":[10.1798009872,45.6703948975],"type":"Point"}
}