{
  "type": "Feature",
  "properties": {
    "iso:country":"IT",
    "sg:address":"Frosinone, Fr",
    "sg:classifiers":[
        {
            "category":"Banks & Credit Unions",
            "subcategory":"Bank",
            "type":"Services"
        }
    ],
    "wof:name":"Acque E Terme Di Bognanco Spa",
    "wof:placetype":"venue"
},
  "geometry": {"coordinates":[13.351902,41.640137],"type":"Point"}
}