{
  "type": "Feature",
  "properties": {
    "addr:full":"09045 Quartu Sant'elena Cagliari 09045",
    "addr:postcode":"09045;09045",
    "iso:country":"IT",
    "sg:address":"09045 Quartu Sant'elena",
    "sg:orig_category":"Chiese Ed Associazioni Religiose",
    "sg:phone":"+39 070 885602",
    "sg:postcode":"09045",
    "sg:province":"Cagliari",
    "wof:name":"Ente Patrim. Chiesa Di Gesu'cristo Dei Santi Ultimi Giorni",
    "wof:placetype":"venue"
},
  "geometry": {"coordinates":[9.176654,39.23856],"type":"Point"}
}