{
  "type": "Feature",
  "properties": {
    "iso:country":"IT",
    "sg:address":"35010 Limena",
    "sg:city":"Limena",
    "sg:orig_category":"Prodotti E Manufatti In Materie Plastiche",
    "sg:phone":"+39 049 884 1355",
    "sg:postcode":"35010",
    "sg:province":"Padova",
    "wof:name":"Acrilgraph Spa",
    "wof:placetype":"venue"
},
  "geometry": {"coordinates":[11.8584899902,45.4607467651],"type":"Point"}
}