{
  "type": "Feature",
  "properties": {
    "addr:full":"09032 Assemini Assemini Cagliari 09032",
    "addr:postcode":"09032;09032",
    "iso:country":"IT",
    "sg:address":"09032 Assemini",
    "sg:city":"Assemini",
    "sg:orig_category":"Accessori Dei Mezzi Di Trasporto. Riparazione Dei Mezzi Di Trasporto",
    "sg:phone":"+39 070 942450",
    "sg:postcode":"09032",
    "sg:province":"Cagliari",
    "wof:name":"Manca Silvia",
    "wof:placetype":"venue"
},
  "geometry": {"coordinates":[8.999051,39.293137],"type":"Point"}
}