{
  "type": "Feature",
  "properties": {
    "iso:country":"IT",
    "sg:address":"21017 Samarate",
    "sg:city":"Samarate",
    "sg:orig_category":"Macchine Utensili E Impianti",
    "sg:phone":"+39 0331 235353",
    "sg:postcode":"21017",
    "sg:province":"Varese",
    "wof:name":"San Gregorio S.p.a. Fonderia Officina Meccanica",
    "wof:placetype":"venue"
},
  "geometry": {"coordinates":[8.831178,45.806862],"type":"Point"}
}