{
  "type": "Feature",
  "properties": {
    "iso:country":"IT",
    "sg:address":"40011 Anzola Dell'emilia",
    "sg:orig_category":"Motori Ed Organi Di Trasmissione",
    "sg:phone":"+39 051 733083",
    "sg:postcode":"40011",
    "sg:province":"Bologna",
    "sg:website":"http://www.cei.it",
    "wof:name":"C.e.i. Spa",
    "wof:placetype":"venue"
},
  "geometry": {"coordinates":[11.2149620056,44.5368766785],"type":"Point"}
}