{
  "type": "Feature",
  "properties": {
    "iso:country":"IT",
    "sg:address":"24012 Brembilla",
    "sg:city":"Brembilla",
    "sg:orig_category":"Minuterie Metalliche E Ferramenta",
    "sg:phone":"+39 0345 98130",
    "sg:postcode":"24012",
    "sg:province":"Bergamo",
    "wof:name":"La T.a.m.m. Di Zanardi Rocco & C. Snc",
    "wof:placetype":"venue"
},
  "geometry": {"coordinates":[9.5720930099,45.6935081482],"type":"Point"}
}