{
  "type": "Feature",
  "properties": {
    "addr:full":"25018 Montichiari Montichiari Brescia 25018",
    "addr:postcode":"25018;25018",
    "iso:country":"IT",
    "sg:address":"25018 Montichiari",
    "sg:city":"Montichiari",
    "sg:orig_category":"Apparecchiature E Sistemi Per Magazzinaggio E Movimentazione",
    "sg:phone":"+39 030 961872",
    "sg:postcode":"25018",
    "sg:province":"Brescia",
    "wof:name":"Maggi Mauro",
    "wof:placetype":"venue"
},
  "geometry": {"coordinates":[10.294683,45.469013],"type":"Point"}
}