{
  "type": "Feature",
  "properties": {
    "iso:country":"IT",
    "sg:address":"13894 Gaglianico",
    "sg:city":"Gaglianico",
    "sg:orig_category":"Materiali Semilavorati Metallici",
    "sg:phone":"+39 015 35921",
    "sg:postcode":"13894",
    "sg:province":"Biella",
    "sg:website":"http://www.moscasider.it",
    "wof:name":"Mosca Srl",
    "wof:placetype":"venue"
},
  "geometry": {"coordinates":[8.077891,45.542656],"type":"Point"}
}