{
  "type": "Feature",
  "properties": {
    "iso:country":"IT",
    "sg:address":"53024 Montalcino",
    "sg:city":"Montalcino",
    "sg:classifiers":[
        {
            "category":"Travel",
            "subcategory":"Hotels & Motels",
            "type":"Entertainment"
        }
    ],
    "sg:phone":"+39 0577 847188",
    "sg:postcode":"53024",
    "sg:province":"Siena",
    "sg:tags":[
        "hotels",
        "facility"
    ],
    "sg:website":"http://www.residencemontalcino.it",
    "wof:name":"Hotel Residence Montalcino",
    "wof:placetype":"venue"
},
  "geometry": {"coordinates":[11.45663,43.042759],"type":"Point"}
}