{
  "type": "Feature",
  "properties": {
    "addr:full":"Via Parini 17 23861 Cesana Brianza Cesana Brianza Lecco 23861",
    "addr:housenumber":"17",
    "addr:postcode":"23861;brianza;23861",
    "addr:street":"Via Parini",
    "iso:country":"IT",
    "sg:address":"Via Parini 17 23861 Cesana Brianza",
    "sg:city":"Cesana Brianza",
    "sg:classifiers":[
        {
            "category":"Bars & Pubs",
            "subcategory":"Nightclub",
            "type":"Food & Drink"
        }
    ],
    "sg:phone":"+39 031 658050",
    "sg:postcode":"23861",
    "sg:province":"Lecco",
    "sg:tags":[
        "bars",
        "forming",
        "tube",
        "machine",
        "section",
        "rods",
        "drawing"
    ],
    "sg:website":"www.emespa.com",
    "wof:name":"Elettromeccanica Erbese Spa",
    "wof:placetype":"venue"
},
  "geometry": {"coordinates":[9.390071,45.852982],"type":"Point"}
}