{
  "type": "Feature",
  "properties": {
    "addr:full":"107, Via Treviso 31040 Trevignano Trevignano Treviso 31040",
    "addr:housenumber":"107",
    "addr:postcode":"31040;31040",
    "addr:street":"Via Treviso",
    "iso:country":"IT",
    "sg:address":"107, Via Treviso 31040 Trevignano",
    "sg:city":"Trevignano",
    "sg:classifiers":[
        {
            "category":"Shopping",
            "subcategory":"Clothing, Apparel, & Fashions",
            "type":"Retail Goods"
        }
    ],
    "sg:phone":"+39 0423 677157",
    "sg:postcode":"31040",
    "sg:province":"Treviso",
    "sg:tags":[
        "clothing",
        "accessory"
    ],
    "wof:name":"Nastrificio Di Signoressa Di Carmagnola - Canonico & C. (s.n.c.)",
    "wof:placetype":"venue"
},
  "geometry": {"coordinates":[12.133673,45.732773],"type":"Point"}
}