{
  "type": "Feature",
  "properties": {
    "iso:country":"IT",
    "sg:address":"Via Amba Aradam 9; Roma",
    "sg:classifiers":[
        {
            "category":"Banks & Credit Unions",
            "subcategory":"Bank",
            "type":"Services"
        }
    ],
    "sg:phone":"+39 06 7049 7174",
    "wof:name":"Banca Di Roma",
    "wof:placetype":"venue"
},
  "geometry": {"coordinates":[12.499756,41.883408],"type":"Point"}
}