{
  "type": "Feature",
  "properties": {
    "iso:country":"IT",
    "sg:address":"Via Ingegno 84087 Sarno",
    "sg:city":"Sarno",
    "sg:classifiers":[
        {
            "category":"Coffee & Tea",
            "type":"Food & Drink"
        }
    ],
    "sg:phone":"+39 081 513 6356",
    "sg:postcode":"84087",
    "sg:province":"Salerno",
    "sg:tags":[
        "sauce",
        "pizza"
    ],
    "wof:name":"Giaguaro S.p.a.",
    "wof:placetype":"venue"
},
  "geometry": {"coordinates":[14.6017580032,40.8198013306],"type":"Point"}
}