{
  "type": "Feature",
  "properties": {
    "addr:full":"10, Via Venezia 33085 Maniago Maniago Pordenone 33085",
    "addr:postcode":"33085;33085",
    "addr:street":"Via Venezia",
    "iso:country":"IT",
    "sg:address":"10, Via Venezia 33085 Maniago",
    "sg:city":"Maniago",
    "sg:classifiers":[
        {
            "category":"Shopping",
            "subcategory":"Crafts & Fabrics",
            "type":"Retail Goods"
        }
    ],
    "sg:phone":"+39 0427 736200",
    "sg:postcode":"33085",
    "sg:province":"Pordenone",
    "wof:name":"Sunfil S.r.l.",
    "wof:placetype":"venue"
},
  "geometry": {"coordinates":[12.7175951004,46.1515693665],"type":"Point"}
}