{
  "type": "Feature",
  "properties": {
    "iso:country":"IT",
    "sg:address":"20010 Arluno",
    "sg:city":"Arluno",
    "sg:orig_category":"Servizi Culturali E Per Lo Spettacolo. Musica",
    "sg:phone":"+39 02 9037 6917",
    "sg:postcode":"20010",
    "sg:province":"Milano",
    "wof:name":"Minuto Ruben",
    "wof:placetype":"venue"
},
  "geometry": {"coordinates":[8.976373,45.506287],"type":"Point"}
}