{
  "type": "Feature",
  "properties": {
    "iso:country":"IT",
    "sg:address":"5, Via Mascagni 22070 Casnate Con Bernate",
    "sg:city":"Casnate",
    "sg:classifiers":[
        {
            "category":"Farming",
            "subcategory":"Livestock Farm",
            "type":"Manufacturing & Wholesale Goods"
        }
    ],
    "sg:phone":"+39 39031564270",
    "sg:postcode":"22070",
    "sg:province":"Como",
    "sg:tags":[
        "agriculture"
    ],
    "wof:name":"Rattiflora S.n.c.",
    "wof:placetype":"venue"
},
  "geometry": {"coordinates":[9.07025,45.764042],"type":"Point"}
}