{
  "type": "Feature",
  "properties": {
    "addr:full":"20138 Milano Milano Milano 20138",
    "addr:postcode":"20138;20138",
    "iso:country":"IT",
    "sg:address":"20138 Milano",
    "sg:city":"Milano",
    "sg:orig_category":"Petroli, Gas E Combustibili",
    "sg:phone":"+39 02 5801 8076",
    "sg:postcode":"20138",
    "sg:province":"Milano",
    "wof:name":"Mauro Carenini Di Alberto",
    "wof:placetype":"venue"
},
  "geometry": {"coordinates":[9.1827917099,45.4678268433],"type":"Point"}
}