{
  "type": "Feature",
  "properties": {
    "iso:country":"IT",
    "sg:address":"00185 Roma",
    "sg:city":"Roma",
    "sg:orig_category":"Servizi Culturali E Per Lo Spettacolo. Servizi Al Turismo. Acqua, Luce, Gas E Societa' Di Esercizio Pubblico",
    "sg:phone":"+39 06 445 0914",
    "sg:postcode":"00185",
    "sg:province":"Roma",
    "wof:name":"Ist.centr.per Il Catalogo Unico Delle Bibl.it.e Per Inf.bibl",
    "wof:placetype":"venue"
},
  "geometry": {"coordinates":[12.505505,41.906097],"type":"Point"}
}