{
  "type": "Feature",
  "properties": {
    "iso:country":"IT",
    "sg:address":"20148 Milano",
    "sg:city":"Milano",
    "sg:orig_category":"Motori Ed Organi Di Trasmissione",
    "sg:phone":"+39 02 4007 0845",
    "sg:postcode":"20148",
    "sg:province":"Milano",
    "wof:name":"M W M Freni E Frizioni (s.r.l.)",
    "wof:placetype":"venue"
},
  "geometry": {"coordinates":[9.1433362961,45.46875],"type":"Point"}
}