{
  "type": "Feature",
  "properties": {
    "addr:full":"21018 Sesto Calende Sesto Calende Varese 21018",
    "addr:postcode":"21018;21018",
    "iso:country":"IT",
    "sg:address":"21018 Sesto Calende",
    "sg:city":"Sesto Calende",
    "sg:classifiers":[
        {
            "category":"Autos & Motor Vehicles",
            "subcategory":"Automobile Sales",
            "type":"Retail Goods"
        }
    ],
    "sg:phone":"+39 0331 924174",
    "sg:postcode":"21018",
    "sg:province":"Varese",
    "sg:tags":[
        "car"
    ],
    "wof:name":"Aviotecnica Srl",
    "wof:placetype":"venue"
},
  "geometry": {"coordinates":[8.696323,45.789188],"type":"Point"}
}