{
  "type": "Feature",
  "properties": {
    "iso:country":"IT",
    "sg:address":"46030 Virgilio",
    "sg:city":"Virgilio",
    "sg:orig_category":"Macchine, Impianti Ed Attrezzature Per Agricoltura E Zootecnia",
    "sg:phone":"+39 0376 448285",
    "sg:postcode":"46030",
    "sg:province":"Mantova",
    "wof:name":"Bonatti Irrigazioni Srl",
    "wof:placetype":"venue"
},
  "geometry": {"coordinates":[10.781524,45.099827],"type":"Point"}
}