{
  "type": "Feature",
  "properties": {
    "addr:full":"Str. Padana Superiore, 18/20 25045 Castegnato Castegnato Brescia 25045",
    "addr:housenumber":"18 / 20",
    "addr:postcode":"25045;25045",
    "addr:street":"Str. Padana Superiore",
    "iso:country":"IT",
    "sg:address":"Str. Padana Superiore, 18/20 25045 Castegnato",
    "sg:city":"Castegnato",
    "sg:classifiers":[
        {
            "category":"Wholesale",
            "subcategory":"Auto Parts",
            "type":"Manufacturing & Wholesale Goods"
        }
    ],
    "sg:phone":"+39 030 373 0111",
    "sg:postcode":"25045",
    "sg:province":"Brescia",
    "sg:tags":[
        "wheel",
        "car",
        "alloy",
        "rims"
    ],
    "sg:website":"www.mimwheels.com",
    "wof:name":"M.i.m. Ruote Alloy Wheels Spa",
    "wof:placetype":"venue"
},
  "geometry": {"coordinates":[10.13415,45.550236],"type":"Point"}
}