{
  "type": "Feature",
  "properties": {
    "iso:country":"IT",
    "sg:address":"20019 Settimo Milanese",
    "sg:city":"Settimo Milanese",
    "sg:orig_category":"Apparecchiature Ed Attrezzature Meccaniche",
    "sg:phone":"+39 02 3350 2335",
    "sg:postcode":"20019",
    "sg:province":"Milano",
    "wof:name":"Vibi Spa",
    "wof:placetype":"venue"
},
  "geometry": {"coordinates":[9.068201,45.477322],"type":"Point"}
}