{
  "type": "Feature",
  "properties": {
    "addr:full":"Via Faruffini 3; Milano; 20149 Milano Milano 20149",
    "addr:housenumber":"3",
    "addr:postcode":"20149;20149",
    "addr:street":"Via Faruffini",
    "iso:country":"IT",
    "sg:address":"Via Faruffini 3; Milano; 20149",
    "sg:city":"Milano",
    "sg:classifiers":[
        {
            "category":"Banks & Credit Unions",
            "subcategory":"Bank",
            "type":"Services"
        }
    ],
    "sg:phone":"+39 02 434322",
    "sg:postcode":"20149",
    "sg:province":"Milano",
    "wof:name":"Banca Agricola Milanese Spa",
    "wof:placetype":"venue"
},
  "geometry": {"coordinates":[9.149889,45.466881],"type":"Point"}
}