{
  "type": "Feature",
  "properties": {
    "iso:country":"IT",
    "sg:address":"60044 Fabriano",
    "sg:city":"Fabriano",
    "sg:orig_category":"Acciaierie E Fonderie",
    "sg:phone":"+39 0732 71006",
    "sg:postcode":"60044",
    "sg:province":"Ancona",
    "wof:name":"Pramfer Di Moretti Massimo",
    "wof:placetype":"venue"
},
  "geometry": {"coordinates":[12.870448,43.339912],"type":"Point"}
}