{
  "type": "Feature",
  "properties": {
    "iso:country":"IT",
    "sg:address":"20049 Concorezzo",
    "sg:city":"Concorezzo",
    "sg:orig_category":"Arredamenti E Mobili Professionali. Impianti, Attrezzature E Forniture Sanitarie Ed Ospedaliere",
    "sg:phone":"+39 039 604 0145",
    "sg:postcode":"20049",
    "sg:province":"Milano",
    "wof:name":"Nuova F.i.m.s. (s.r.l.)",
    "wof:placetype":"venue"
},
  "geometry": {"coordinates":[9.336818,45.593395],"type":"Point"}
}