{
  "type": "Feature",
  "properties": {
    "iso:country":"IT",
    "sg:address":"89133 Reggio Calabria",
    "sg:orig_category":"Antincendio - Impianti, Attrezzature E Materiali",
    "sg:phone":"+39 0965 54934",
    "sg:province":"RC",
    "sg:website":"http://space.tin.it/economia/pmilasi",
    "wof:name":"Cadi Dei F.lli Milasi & C. Snc",
    "wof:placetype":"venue"
},
  "geometry": {"coordinates":[15.723381,38.099182],"type":"Point"}
}