{
  "type": "Feature",
  "properties": {
    "iso:country":"IT",
    "sg:address":"27043 Broni",
    "sg:city":"Broni",
    "sg:classifiers":[
        {
            "category":"Professional",
            "subcategory":"Printing & Photocopies",
            "type":"Services"
        }
    ],
    "sg:phone":"+39 0385 250354",
    "sg:postcode":"27043",
    "sg:province":"Pavia",
    "sg:tags":[
        "packaging",
        "setting"
    ],
    "wof:name":"Litografia Pironi Di Pironi G. & C. Snc",
    "wof:placetype":"venue"
},
  "geometry": {"coordinates":[9.263463,45.066406],"type":"Point"}
}