{
  "type": "Feature",
  "properties": {
    "iso:country":"IT",
    "sg:address":"45, Via Feltrina 31040 Pederobba",
    "sg:city":"Pederobba",
    "sg:classifiers":[
        {
            "category":"Parking",
            "subcategory":"Lot",
            "type":"Transportation"
        }
    ],
    "sg:phone":"+39 0423 688144",
    "sg:postcode":"31040",
    "sg:province":"Treviso",
    "sg:tags":[
        "transport",
        "road"
    ],
    "wof:name":"Officina Trasporti Piave S.r.l.",
    "wof:placetype":"venue"
},
  "geometry": {"coordinates":[11.96874,45.869949],"type":"Point"}
}