{
  "type": "Feature",
  "properties": {
    "iso:country":"IT",
    "sg:address":"20064 Gorgonzola",
    "sg:city":"Gorgonzola",
    "sg:orig_category":"Forniture E Materiali Per Imballaggio E Confezionamento",
    "sg:phone":"+39 02 951 3051",
    "sg:postcode":"20064",
    "sg:province":"Milano",
    "wof:name":"I.c.a.",
    "wof:placetype":"venue"
},
  "geometry": {"coordinates":[9.409696579,45.5290489197],"type":"Point"}
}