{
  "type": "Feature",
  "properties": {
    "iso:country":"IT",
    "sg:address":"20131 Milano",
    "sg:city":"Milano",
    "sg:orig_category":"Biancheria, Telerie E Coperte",
    "sg:phone":"+39 02 7060 5199",
    "sg:postcode":"20131",
    "sg:province":"Milano",
    "wof:name":"Fi.di. Di Di Mauro Filippo",
    "wof:placetype":"venue"
},
  "geometry": {"coordinates":[9.229906,45.484447],"type":"Point"}
}