{
  "type": "Feature",
  "properties": {
    "addr:full":"10093 Collegno Collegno Torino 10093",
    "addr:postcode":"10093;10093",
    "iso:country":"IT",
    "sg:address":"10093 Collegno",
    "sg:city":"Collegno",
    "sg:orig_category":"Biancheria, Telerie E Coperte. Arredo Camera Letto E Complementi",
    "sg:phone":"+39 011 781026",
    "sg:postcode":"10093",
    "sg:province":"Torino",
    "wof:name":"Turinflex (s.a.s.)",
    "wof:placetype":"venue"
},
  "geometry": {"coordinates":[7.572362,45.069519],"type":"Point"}
}