{
  "type": "Feature",
  "properties": {
    "iso:country":"IT",
    "sg:address":"25010 Borgosatollo",
    "sg:city":"Borgosatollo",
    "sg:orig_category":"Impiantistica E Prodotti Tecnologici Per Edilizia. Elettrotecnica Industriale, Prodotti E Apparecchiature. Elettrotecnica Professionale E Di Consumo",
    "sg:phone":"+39 030 250 0350",
    "sg:postcode":"25010",
    "sg:province":"Brescia",
    "wof:name":"B.f.t. Di Beduschi Filippini Tavelli",
    "wof:placetype":"venue"
},
  "geometry": {"coordinates":[10.255073,45.476124],"type":"Point"}
}