{
  "type": "Feature",
  "properties": {
    "iso:country":"IT",
    "sg:address":"73031 Alessano",
    "sg:city":"Alessano",
    "sg:orig_category":"Addobbi E Addobbatori",
    "sg:phone":"+39 0833 782249",
    "sg:postcode":"73031",
    "sg:province":"Lecce",
    "wof:name":"Premiata Ditta Antonio Santoro Srl",
    "wof:placetype":"venue"
},
  "geometry": {"coordinates":[18.339672,39.874424],"type":"Point"}
}