{
  "type": "Feature",
  "properties": {
    "iso:country":"IT",
    "sg:address":"24124 Bergamo",
    "sg:city":"Bergamo",
    "sg:orig_category":"Forniture Per Agricoltura E Zootecnia. Animali Domestici",
    "sg:phone":"+39 035 417 5326",
    "sg:postcode":"24124",
    "sg:province":"Bergamo",
    "wof:name":"Iperzoo S.r.l.",
    "wof:placetype":"venue"
},
  "geometry": {"coordinates":[9.6898317337,45.7069664001],"type":"Point"}
}