{
  "type": "Feature",
  "properties": {
    "iso:country":"IT",
    "sg:address":"71019 Vieste",
    "sg:city":"Vieste",
    "sg:orig_category":"Campeggio. Alberghi E Strutture Extra Alberghiere",
    "sg:phone":"+39 0884 706391",
    "sg:postcode":"71019",
    "sg:province":"Foggia",
    "wof:name":"Club In Vacanze",
    "wof:placetype":"venue"
},
  "geometry": {"coordinates":[16.11105,41.837559],"type":"Point"}
}