{
  "type": "Feature",
  "properties": {
    "iso:country":"IT",
    "sg:address":"00054 Fiumicino",
    "sg:city":"Fiumicino",
    "sg:orig_category":"Nautica. Servizi Per Lo Sport E Il Tempo Libero. Servizi Al Turismo. Servizi Ausiliari Dei Mezzi Di Trasporto",
    "sg:phone":"+39 06 652 2012",
    "sg:postcode":"00054",
    "sg:province":"Roma",
    "wof:name":"Comar Srl",
    "wof:placetype":"venue"
},
  "geometry": {"coordinates":[12.229798,41.770775],"type":"Point"}
}