{
  "type": "Feature",
  "properties": {
    "iso:country":"IT",
    "sg:address":"Via De' Pescioni, 8; Firenze; 50123",
    "sg:city":"Firenze",
    "sg:classifiers":[
        {
            "category":"Banks & Credit Unions",
            "subcategory":"Bank",
            "type":"Services"
        }
    ],
    "sg:phone":"+39 0552782",
    "sg:postcode":"50123",
    "sg:province":"Firenze",
    "wof:name":"Banca Di Roma",
    "wof:placetype":"venue"
},
  "geometry": {"coordinates":[11.25221,43.772541],"type":"Point"}
}