{
  "type": "Feature",
  "properties": {
    "iso:country":"IT",
    "sg:address":"20127 Milano",
    "sg:city":"Milano",
    "sg:orig_category":"Servizi Culturali E Per Lo Spettacolo. Musica",
    "sg:phone":"+39 02 2611 2360",
    "sg:postcode":"20127",
    "sg:province":"Milano",
    "wof:name":"Cavallone Marco",
    "wof:placetype":"venue"
},
  "geometry": {"coordinates":[9.22081,45.495918],"type":"Point"}
}