{
  "type": "Feature",
  "properties": {
    "iso:country":"IT",
    "sg:address":"1, Via Della Repubblica 18039 Ventimiglia",
    "sg:city":"Ventimiglia",
    "sg:classifiers":[
        {
            "category":"Communications",
            "subcategory":"Newspaper",
            "type":"Services"
        }
    ],
    "sg:phone":"+39 39018433924",
    "sg:postcode":"18039",
    "sg:province":"Imperia",
    "sg:tags":[
        "advertising"
    ],
    "wof:name":"Radio Relax",
    "wof:placetype":"venue"
},
  "geometry": {"coordinates":[7.608985,43.791458],"type":"Point"}
}