{
  "type": "Feature",
  "properties": {
    "addr:full":"40013 Castel Maggiore Castel Maggiore Bologna 40013",
    "addr:postcode":"40013;40013",
    "iso:country":"IT",
    "sg:address":"40013 Castel Maggiore",
    "sg:city":"Castel Maggiore",
    "sg:orig_category":"Spedizioni Internazionali",
    "sg:phone":"+39 051 710711",
    "sg:postcode":"40013",
    "sg:province":"Bologna",
    "wof:name":"C. & C. Srl",
    "wof:placetype":"venue"
},
  "geometry": {"coordinates":[11.377914,44.561676],"type":"Point"}
}