{
  "type": "Feature",
  "properties": {
    "addr:full":"Via Peregallo 16 20040 Briosco Briosco Milano 20040",
    "addr:housenumber":"16",
    "addr:postcode":"20040;20040",
    "addr:street":"Via Peregallo",
    "iso:country":"IT",
    "sg:address":"Via Peregallo 16 20040 Briosco",
    "sg:city":"Briosco",
    "sg:orig_category":"Freewheel Clutches, Back-stops, Overrun Clutches",
    "sg:phone":"+39 036 295 8479",
    "sg:postcode":"20040",
    "sg:province":"Milano",
    "sg:website":"www.ctsitaly.it",
    "wof:name":"Cts Srl",
    "wof:placetype":"venue"
},
  "geometry": {"coordinates":[9.233086586,45.7174415588],"type":"Point"}
}