{
  "type": "Feature",
  "properties": {
    "iso:country":"IT",
    "sg:address":"80045 Pompei",
    "sg:city":"Pompei",
    "sg:orig_category":"Hobbistica",
    "sg:phone":"+39 081 856 4170",
    "sg:postcode":"80045",
    "sg:province":"Napoli",
    "wof:name":"Collezionando Insieme S.a.s Di Fattorusso Aniello & C.",
    "wof:placetype":"venue"
},
  "geometry": {"coordinates":[14.175199,40.862625],"type":"Point"}
}