{
  "type": "Feature",
  "properties": {
    "iso:country":"IT",
    "sg:address":"30030 Mestre",
    "sg:orig_category":"Manufacturers: Prefabbricati",
    "sg:phone":"+39 041 632794",
    "sg:postcode":"30030",
    "sg:province":"Venezia",
    "wof:name":"Sgolmin Adriano",
    "wof:placetype":"venue"
},
  "geometry": {"coordinates":[12.286149,45.49762],"type":"Point"}
}