{
  "type": "Feature",
  "properties": {
    "addr:full":"Via Borgo Fausto 15/17; Longiano; 47020 Longiano Forl\u00ec-Cesena 47020",
    "addr:housenumber":"15 / 17",
    "addr:postcode":"47020;47020",
    "addr:street":"Via Borgo Fausto;Longiano",
    "iso:country":"IT",
    "sg:address":"Via Borgo Fausto 15/17; Longiano; 47020",
    "sg:city":"Longiano",
    "sg:classifiers":[
        {
            "category":"Banks & Credit Unions",
            "subcategory":"Bank",
            "type":"Services"
        }
    ],
    "sg:phone":"+39 0547 665104",
    "sg:postcode":"47020",
    "sg:province":"Forl\u00ec-Cesena",
    "wof:name":"Cassa Di Risparmio Di Cesena Spa",
    "wof:placetype":"venue"
},
  "geometry": {"coordinates":[12.325337,44.073036],"type":"Point"}
}