{
  "type": "Feature",
  "properties": {
    "addr:full":"54, Via Leopoldo Di Toscana 52048 Monte San Savino Monte San Savino Arezzo 52048",
    "addr:postcode":"52048;52048",
    "addr:street":"Via Leopoldo Di Toscana",
    "iso:country":"IT",
    "sg:address":"54, Via Leopoldo Di Toscana 52048 Monte San Savino",
    "sg:city":"Monte San Savino",
    "sg:classifiers":[
        {
            "category":"Manufacturing",
            "subcategory":"Metals",
            "type":"Manufacturing & Wholesale Goods"
        }
    ],
    "sg:phone":"+39 0575 848182",
    "sg:postcode":"52048",
    "sg:province":"Arezzo",
    "sg:tags":[
        "metallurgy",
        "metalworking"
    ],
    "wof:name":"Giallo (s.r.l.)",
    "wof:placetype":"venue"
},
  "geometry": {"coordinates":[11.804813385,43.3561439514],"type":"Point"}
}