{
  "type": "Feature",
  "properties": {
    "iso:country":"IT",
    "sg:address":"Viale Burchiellati 28/c; Treviso; 31100",
    "sg:city":"Treviso",
    "sg:classifiers":[
        {
            "category":"Banks & Credit Unions",
            "subcategory":"Bank",
            "type":"Services"
        }
    ],
    "sg:phone":"+39 0422 411711",
    "sg:postcode":"31100",
    "sg:province":"Treviso",
    "wof:name":"Rolo Banca 1473 Spa",
    "wof:placetype":"venue"
},
  "geometry": {"coordinates":[12.24855,45.669296],"type":"Point"}
}