{
  "type": "Feature",
  "properties": {
    "iso:country":"IT",
    "sg:address":"10, Via Serenissima 36040 Grisignano Di Zocco",
    "sg:city":"Grisignano di Zocco",
    "sg:classifiers":[
        {
            "category":"Banks & Credit Unions",
            "subcategory":"Investment Brokerage",
            "type":"Services"
        }
    ],
    "sg:phone":"+39 0444 414367",
    "sg:postcode":"36040",
    "sg:province":"Vicenza",
    "sg:tags":[
        "-",
        "transport",
        "related"
    ],
    "wof:name":"Ce.di. Sisa Centro Nord S.r.l.",
    "wof:placetype":"venue"
},
  "geometry": {"coordinates":[11.705454,45.483639],"type":"Point"}
}