{
  "type": "Feature",
  "properties": {
    "iso:country":"IT",
    "sg:address":"38068 Rovereto",
    "sg:city":"Rovereto",
    "sg:classifiers":[
        {
            "category":"Sports & Exercise",
            "subcategory":"Tennis Court",
            "type":"Entertainment"
        }
    ],
    "sg:phone":"+39 0464 480055",
    "sg:postcode":"38068",
    "sg:province":"Trento",
    "sg:tags":[
        "e",
        "lo",
        "tempo",
        "libero",
        "per",
        "impianti",
        "il",
        "attrezzature"
    ],
    "wof:name":"Leisure Solutions And Products Di Mauro Pizzini",
    "wof:placetype":"venue"
},
  "geometry": {"coordinates":[11.044579,45.889454],"type":"Point"}
}