{
  "type": "Feature",
  "properties": {
    "addr:full":"47, Strada Fantasia 10040 Leini' Torino 10040",
    "addr:postcode":"10040 leini;10040",
    "addr:street":"Strada Fantasia",
    "iso:country":"IT",
    "sg:address":"47, Strada Fantasia 10040 Leini'",
    "sg:classifiers":[
        {
            "category":"Professional",
            "subcategory":"Engineering",
            "type":"Services"
        }
    ],
    "sg:phone":"+39 011 998 0316",
    "sg:postcode":"10040",
    "sg:province":"Torino",
    "sg:tags":[
        "machine",
        "-",
        "mechanical"
    ],
    "wof:name":"S.i.b. - Sideral (s.r.l.)",
    "wof:placetype":"venue"
},
  "geometry": {"coordinates":[7.715268,45.158211],"type":"Point"}
}