{
  "type": "Feature",
  "properties": {
    "iso:country":"IT",
    "sg:address":"80040 Poggiomarino",
    "sg:city":"Poggiomarino",
    "sg:orig_category":"Gas Compressi E Liquefatti - Produzione E Ingrosso",
    "sg:phone":"+39 081 528 5800",
    "sg:postcode":"80040",
    "sg:province":"Napoli",
    "sg:website":"http://www.longas.com",
    "wof:name":"Napoletana Calor Srl",
    "wof:placetype":"venue"
},
  "geometry": {"coordinates":[14.483976,40.79353],"type":"Point"}
}