{
  "type": "Feature",
  "properties": {
    "addr:full":"Via Dell Artigianato 6 38026 Fucine Di Ossana Fucine Trento 38026",
    "addr:housenumber":"6",
    "addr:postcode":"38026;38026",
    "addr:street":"Via Dell Artigianato",
    "iso:country":"IT",
    "sg:address":"Via Dell Artigianato 6 38026 Fucine Di Ossana",
    "sg:city":"Fucine",
    "sg:classifiers":[
        {
            "category":"Communications",
            "subcategory":"Film & Video Production",
            "type":"Services"
        }
    ],
    "sg:phone":"+39 0463 760411",
    "sg:postcode":"38026",
    "sg:province":"Trento",
    "sg:tags":[
        "pvc",
        "chloride",
        "polyvinyl"
    ],
    "sg:website":"www.solvay.com",
    "wof:name":"Caleppiovinil Spa",
    "wof:placetype":"venue"
},
  "geometry": {"coordinates":[10.7313556671,46.3110771179],"type":"Point"}
}