{
  "type": "Feature",
  "properties": {
    "addr:full":"20077 Melegnano Melegnano Milano 20077",
    "addr:postcode":"20077;20077",
    "iso:country":"IT",
    "sg:address":"20077 Melegnano",
    "sg:city":"Melegnano",
    "sg:orig_category":"Carta, Cartone E Prodotti Primari. Forniture E Materiali Per Imballaggio E Confezionamento",
    "sg:phone":"+39 02 983 0848",
    "sg:postcode":"20077",
    "sg:province":"Milano",
    "wof:name":"Studio Romano' Sas Di Romano' D. E C.",
    "wof:placetype":"venue"
},
  "geometry": {"coordinates":[9.319358,45.353706],"type":"Point"}
}