{
  "type": "Feature",
  "properties": {
    "addr:full":"16139 Genova Genova Genova 16139",
    "addr:postcode":"16139;16139",
    "iso:country":"IT",
    "sg:address":"16139 Genova",
    "sg:city":"Genova",
    "sg:classifiers":[
        {
            "category":"Health Services",
            "subcategory":"Health Practitioner",
            "type":"Services"
        }
    ],
    "sg:phone":"+39 010 839 1076",
    "sg:postcode":"16139",
    "sg:province":"Genova",
    "sg:tags":[
        "medici"
    ],
    "wof:name":"Ardy Cesare",
    "wof:placetype":"venue"
},
  "geometry": {"coordinates":[8.949887,44.420326],"type":"Point"}
}