{
  "type": "Feature",
  "properties": {
    "iso:country":"IT",
    "sg:address":"40013 Castel Maggiore",
    "sg:city":"Castel Maggiore",
    "sg:orig_category":"Prodotti E Manufatti In Gomma",
    "sg:phone":"+39 051 712143",
    "sg:postcode":"40013",
    "sg:province":"Bologna",
    "wof:name":"Vig Venturoli Industria Gomma (s.r.l.)",
    "wof:placetype":"venue"
},
  "geometry": {"coordinates":[11.3720989227,44.56275177],"type":"Point"}
}