{
  "type": "Feature",
  "properties": {
    "iso:country":"IT",
    "sg:address":"53, Via Provinciale Di Mercatale 50059 Vinci",
    "sg:city":"Vinci",
    "sg:classifiers":[
        {
            "category":"Food & Beverages",
            "subcategory":"Groceries & Convenience Stores",
            "type":"Retail Goods"
        }
    ],
    "sg:phone":"+39 0571 902444",
    "sg:postcode":"50059",
    "sg:province":"Firenze",
    "sg:tags":[
        "drink"
    ],
    "wof:name":"Cantine Leonardo Vinci Societa' Coop. A (r.l.)",
    "wof:placetype":"venue"
},
  "geometry": {"coordinates":[10.906584,43.755516],"type":"Point"}
}