{
  "type": "Feature",
  "properties": {
    "addr:full":"58019 Monte Argentario Monte Argentario Grosseto 58019",
    "addr:housenumber":"58019",
    "addr:postcode":"58019",
    "addr:street":"Monte",
    "iso:country":"IT",
    "sg:address":"58019 Monte Argentario",
    "sg:city":"Monte Argentario",
    "sg:classifiers":[
        {
            "category":"Home & Garden",
            "subcategory":"Home Furnishings",
            "type":"Retail Goods"
        }
    ],
    "sg:phone":"+39 0564 817701",
    "sg:postcode":"58019",
    "sg:province":"Grosseto",
    "sg:tags":[
        "professional",
        "furniture",
        "accommodation",
        "supply"
    ],
    "wof:name":"Fabbroni & Vongher Srl",
    "wof:placetype":"venue"
},
  "geometry": {"coordinates":[11.1199245453,42.4249610901],"type":"Point"}
}