{
  "type": "Feature",
  "properties": {
    "addr:full":"12051 Alba Alba Cuneo 12051",
    "addr:postcode":"12051;12051",
    "iso:country":"IT",
    "sg:address":"12051 Alba",
    "sg:city":"Alba",
    "sg:orig_category":"Odontotecnici - Laboratori",
    "sg:phone":"+39 0173 290539",
    "sg:postcode":"12051",
    "sg:province":"Cuneo",
    "wof:name":"L.d.",
    "wof:placetype":"venue"
},
  "geometry": {"coordinates":[8.033948,44.691036],"type":"Point"}
}