{
  "type": "Feature",
  "properties": {
    "iso:country":"IT",
    "sg:address":"Via Merello, 8 16141 Genova",
    "sg:city":"Genova",
    "sg:classifiers":[
        {
            "category":"Home & Garden",
            "subcategory":"Home Furnishings",
            "type":"Retail Goods"
        }
    ],
    "sg:phone":"+39 010 838 0753",
    "sg:postcode":"16141",
    "sg:province":"Genova",
    "sg:tags":[
        "air-conditioners"
    ],
    "wof:name":"Gesco Srl Div. Limoli",
    "wof:placetype":"venue"
},
  "geometry": {"coordinates":[8.971672,44.446205],"type":"Point"}
}