{
  "type": "Feature",
  "properties": {
    "iso:country":"IT",
    "sg:address":"20138 Milano",
    "sg:city":"Milano",
    "sg:orig_category":"Servizi E Lavori Per Industria Alimentare E Bevande",
    "sg:phone":"+39 02 504120",
    "sg:postcode":"20138",
    "sg:province":"Milano",
    "wof:name":"Cooperativa Cieffeti A.r.l.",
    "wof:placetype":"venue"
},
  "geometry": {"coordinates":[9.245012,45.448807],"type":"Point"}
}