{
  "type": "Feature",
  "properties": {
    "addr:full":"197, Via Dei Devoto 16033 Lavagna Lavagna Genova 16033",
    "addr:housenumber":"197",
    "addr:postcode":"16033;16033",
    "addr:street":"Via Dei Devoto",
    "iso:country":"IT",
    "sg:address":"197, Via Dei Devoto 16033 Lavagna",
    "sg:city":"Lavagna",
    "sg:classifiers":[
        {
            "category":"Autos & Motor Vehicles",
            "subcategory":"Boat Sales",
            "type":"Retail Goods"
        }
    ],
    "sg:phone":"+39 0185 306601",
    "sg:postcode":"16033",
    "sg:province":"Genova",
    "wof:name":"Cantieri Navali Lavagna (s.r.l.)",
    "wof:placetype":"venue"
},
  "geometry": {"coordinates":[9.336542,44.310005],"type":"Point"}
}