{
  "type": "Feature",
  "properties": {
    "iso:country":"IT",
    "sg:address":"31030 Casier",
    "sg:city":"Casier",
    "sg:orig_category":"Apparecchiature Ed Attrezzature Meccaniche. Elettronica Industriale, Prodotti E Apparecchiature",
    "sg:phone":"+39 0422 383277",
    "sg:postcode":"31030",
    "sg:province":"Treviso",
    "sg:website":"http://www.macla.com",
    "wof:name":"Ma.cla. Snc Di Fael Marco",
    "wof:placetype":"venue"
},
  "geometry": {"coordinates":[12.263131,45.633766],"type":"Point"}
}