{
  "type": "Feature",
  "properties": {
    "addr:full":"9, Localita' Piani Di Potenza 62022 Gagliole Gagliole Macerata 62022",
    "addr:postcode":"62022;62022",
    "addr:street":"Localita ' Piani Di Potenza",
    "iso:country":"IT",
    "sg:address":"9, Localita' Piani Di Potenza 62022 Gagliole",
    "sg:city":"Gagliole",
    "sg:classifiers":[
        {
            "category":"Shopping",
            "type":"Retail Goods"
        }
    ],
    "sg:phone":"+39 0737 641057",
    "sg:postcode":"62022",
    "sg:province":"Macerata",
    "sg:tags":[
        "finished",
        "-",
        "metallic"
    ],
    "wof:name":"Cipef",
    "wof:placetype":"venue"
},
  "geometry": {"coordinates":[13.0684938431,43.2188949585],"type":"Point"}
}