{
  "type": "Feature",
  "properties": {
    "addr:full":"300, Via Struppa 16165 Genova Genova Genova 16165",
    "addr:housenumber":"300",
    "addr:postcode":"16165;16165",
    "addr:street":"Via Struppa",
    "iso:country":"IT",
    "sg:address":"300, Via Struppa 16165 Genova",
    "sg:city":"Genova",
    "sg:classifiers":[
        {
            "category":"Manufacturing",
            "subcategory":"Printing",
            "type":"Manufacturing & Wholesale Goods"
        }
    ],
    "sg:phone":"+39 39010802186",
    "sg:postcode":"16165",
    "sg:province":"Genova",
    "sg:tags":[
        "publishing"
    ],
    "wof:name":"Ernesto Marini (s.r.l.)",
    "wof:placetype":"venue"
},
  "geometry": {"coordinates":[9.0207309723,44.4495429993],"type":"Point"}
}