{
  "type": "Feature",
  "properties": {
    "iso:country":"IT",
    "sg:address":"20, V. Feltre 32030 Quero",
    "sg:city":"Quero",
    "sg:classifiers":[
        {
            "category":"Shopping",
            "subcategory":"Computers & Home Electronics",
            "type":"Retail Goods"
        }
    ],
    "sg:phone":"+39 0439 788266",
    "sg:postcode":"32030",
    "sg:province":"Belluno",
    "sg:tags":[
        "electronic",
        "electrical",
        "equipment"
    ],
    "sg:website":"http://www.gallonetto.com",
    "wof:name":"Gallonetto Srl",
    "wof:placetype":"venue"
},
  "geometry": {"coordinates":[11.932411,45.931553],"type":"Point"}
}