{
  "type": "Feature",
  "properties": {
    "iso:country":"IT",
    "sg:address":"30, Via Vasari Giorgio 20052 Monza",
    "sg:city":"Monza",
    "sg:classifiers":[
        {
            "category":"Wholesale",
            "subcategory":"Drugs",
            "type":"Manufacturing & Wholesale Goods"
        }
    ],
    "sg:phone":"+39 39039831283",
    "sg:postcode":"20052",
    "sg:province":"Milano",
    "sg:tags":[
        "chemical",
        "pharmaceutical"
    ],
    "wof:name":"Buzzoni Fratelli Di Buzzoni Lauro E Claudio (s.n.c.)",
    "wof:placetype":"venue"
},
  "geometry": {"coordinates":[9.207261,45.566807],"type":"Point"}
}