{
  "type": "Feature",
  "properties": {
    "iso:country":"IT",
    "sg:address":"101, Contrada Martucci 72015 Fasano",
    "sg:city":"Fasano",
    "sg:classifiers":[
        {
            "category":"Real Estate",
            "subcategory":"Architect",
            "type":"Services"
        }
    ],
    "sg:phone":"+39 080 442 6691",
    "sg:postcode":"72015",
    "sg:province":"Brindisi",
    "sg:tags":[
        "textile",
        "clothing"
    ],
    "wof:name":"L.b.m. Di Lacerignola Domenico",
    "wof:placetype":"venue"
},
  "geometry": {"coordinates":[17.353458,40.846794],"type":"Point"}
}