{
  "type": "Feature",
  "properties": {
    "iso:country":"IT",
    "sg:address":"10, Corso Spagna 35127 Padova",
    "sg:city":"Padova",
    "sg:classifiers":[
        {
            "category":"Parking",
            "subcategory":"Lot",
            "type":"Transportation"
        }
    ],
    "sg:phone":"+39 049 870 0992",
    "sg:postcode":"35127",
    "sg:province":"Padova",
    "sg:tags":[
        "transport",
        "road"
    ],
    "wof:name":"Log.i.trans. (s.r.l.)",
    "wof:placetype":"venue"
},
  "geometry": {"coordinates":[11.924494,45.354332],"type":"Point"}
}