{
  "type": "Feature",
  "properties": {
    "iso:country":"IT",
    "sg:address":"20132 Milano",
    "sg:city":"Milano",
    "sg:orig_category":"Materiali Edili",
    "sg:phone":"+39 02 2630 0628",
    "sg:postcode":"20132",
    "sg:province":"Milano",
    "wof:name":"Edilbomo S.r.l.",
    "wof:placetype":"venue"
},
  "geometry": {"coordinates":[9.247397,45.506954],"type":"Point"}
}