{
  "type": "Feature",
  "properties": {
    "addr:full":"28021 Borgomanero Borgomanero Novara 28021",
    "addr:postcode":"28021;28021",
    "iso:country":"IT",
    "sg:address":"28021 Borgomanero",
    "sg:city":"Borgomanero",
    "sg:orig_category":"Apparecchiature E Sistemi Per Magazzinaggio E Movimentazione",
    "sg:phone":"+39 0321 90449",
    "sg:postcode":"28021",
    "sg:province":"Novara",
    "wof:name":"Leto Barone Antonio",
    "wof:placetype":"venue"
},
  "geometry": {"coordinates":[8.459283,45.702423],"type":"Point"}
}