{
  "type": "Feature",
  "properties": {
    "iso:country":"IT",
    "sg:address":"20090 Vimodrone",
    "sg:city":"Vimodrone",
    "sg:orig_category":"Legno E Semilavorati",
    "sg:phone":"+39 02 250 3085",
    "sg:postcode":"20090",
    "sg:province":"Milano",
    "wof:name":"Metrolegno (s.a.s.)",
    "wof:placetype":"venue"
},
  "geometry": {"coordinates":[9.281069,45.511829],"type":"Point"}
}