{
  "type": "Feature",
  "properties": {
    "iso:country":"IT",
    "sg:address":"20127 Milano",
    "sg:city":"Milano",
    "sg:orig_category":"Scuole E Servizi Scolastici",
    "sg:phone":"+39 02 284 7859",
    "sg:postcode":"20127",
    "sg:province":"Milano",
    "wof:name":"Figlie Della Presentazione Di Maria Ss.",
    "wof:placetype":"venue"
},
  "geometry": {"coordinates":[9.215105,45.493088],"type":"Point"}
}