{
  "type": "Feature",
  "properties": {
    "iso:country":"IT",
    "sg:address":"35010 Limena",
    "sg:city":"Limena",
    "sg:orig_category":"Servizi Per Lo Sport E Il Tempo Libero. Ristoranti Ed Esercizi Affini. Servizi Ausiliari Di Ristorazione E Di Intrattenimento",
    "sg:phone":"+39 049 768785",
    "sg:postcode":"35010",
    "sg:province":"Padova",
    "wof:name":"Bellepoque Sexy Service",
    "wof:placetype":"venue"
},
  "geometry": {"coordinates":[11.84451,45.473175],"type":"Point"}
}