{
  "type": "Feature",
  "properties": {
    "addr:full":"Via Bisceglie 71 20152 Milano Milano Milano 20152",
    "addr:housenumber":"71",
    "addr:postcode":"20152;20152",
    "addr:street":"Via Bisceglie",
    "iso:country":"IT",
    "sg:address":"Via Bisceglie 71 20152 Milano",
    "sg:city":"Milano",
    "sg:classifiers":[
        {
            "category":"Shopping",
            "subcategory":"Hobbies, Toys, & Games",
            "type":"Retail Goods"
        }
    ],
    "sg:phone":"+39 02 413031",
    "sg:postcode":"20152",
    "sg:province":"Milano",
    "sg:tags":[
        "video"
    ],
    "sg:website":"www.halifax.it",
    "wof:name":"Halifax S.p.a.",
    "wof:placetype":"venue"
},
  "geometry": {"coordinates":[9.11657,45.453171],"type":"Point"}
}