{
  "type": "Feature",
  "properties": {
    "iso:country":"IT",
    "sg:address":"84, Via Palermo Porta 91011 Alcamo",
    "sg:city":"Alcamo",
    "sg:classifiers":[
        {
            "category":"Manufacturing",
            "subcategory":"Metals",
            "type":"Manufacturing & Wholesale Goods"
        }
    ],
    "sg:phone":"+39 0924 507050",
    "sg:postcode":"91011",
    "sg:province":"Trapani",
    "sg:tags":[
        "metallurgy",
        "metalworking"
    ],
    "wof:name":"Comas S.r.l.",
    "wof:placetype":"venue"
},
  "geometry": {"coordinates":[12.5146341324,38.0185890198],"type":"Point"}
}