{
  "type": "Feature",
  "properties": {
    "iso:country":"IT",
    "sg:address":"8/1, Via T.tasso 40050 Monteveglio",
    "sg:city":"Monteveglio",
    "sg:classifiers":[
        {
            "category":"Manufacturing",
            "subcategory":"Motor Vehicles & Parts",
            "type":"Manufacturing & Wholesale Goods"
        }
    ],
    "sg:phone":"+39 39051832878",
    "sg:postcode":"40050",
    "sg:province":"Bologna",
    "sg:tags":[
        "engine"
    ],
    "wof:name":"Montek S.r.l. Di Bencivenni R. & C.",
    "wof:placetype":"venue"
},
  "geometry": {"coordinates":[11.346481,44.494221],"type":"Point"}
}