{
  "type": "Feature",
  "properties": {
    "iso:country":"IT",
    "sg:address":"40050 Monteveglio",
    "sg:city":"Monteveglio",
    "sg:orig_category":"Bevande, Vini E Liquori. Shopping",
    "sg:phone":"+39 051 830758",
    "sg:postcode":"40050",
    "sg:province":"Bologna",
    "wof:name":"Bonfiglio Srl",
    "wof:placetype":"venue"
},
  "geometry": {"coordinates":[11.101495,44.489006],"type":"Point"}
}