{
  "type": "Feature",
  "properties": {
    "addr:full":"46100 Mantova Mantova Mantova 46100",
    "addr:postcode":"46100;46100",
    "iso:country":"IT",
    "sg:address":"46100 Mantova",
    "sg:city":"Mantova",
    "sg:orig_category":"Studi E Consulenze Amministrative, Commerciali E Aziendali. Consulenze Tecniche, Amministrative E Perizie",
    "sg:phone":"+39 0376 322612",
    "sg:postcode":"46100",
    "sg:province":"Mantova",
    "wof:name":"Papazzoni Rag. Alfio",
    "wof:placetype":"venue"
},
  "geometry": {"coordinates":[10.789535,45.15704],"type":"Point"}
}