{
  "type": "Feature",
  "properties": {
    "iso:country":"IT",
    "sg:address":"20122 Milano",
    "sg:city":"Milano",
    "sg:orig_category":"Macchine, Impianti Ed Attrezzature Per Industria Alimentare E Bevande",
    "sg:phone":"+39 02 5831 8155",
    "sg:postcode":"20122",
    "sg:province":"Milano",
    "sg:website":"http://www.opacsrl.it",
    "wof:name":"Opac Srl - Rappresentanze Industriali",
    "wof:placetype":"venue"
},
  "geometry": {"coordinates":[9.191689,45.453819],"type":"Point"}
}