{
  "type": "Feature",
  "properties": {
    "iso:country":"IT",
    "sg:address":"62012 Civitanova Marche",
    "sg:city":"Civitanova Marche",
    "sg:orig_category":"Calzature, Pelletterie E Pelli",
    "sg:phone":"+39 0733 810932",
    "sg:postcode":"62012",
    "sg:province":"Macerata",
    "wof:name":"Gattini Abbigliamento Di Gattini Mauro",
    "wof:placetype":"venue"
},
  "geometry": {"coordinates":[13.728413,43.304455],"type":"Point"}
}