{
  "type": "Feature",
  "properties": {
    "iso:country":"IT",
    "sg:address":"Km. 136.630, Via Appia Lato Roma 04024 Gaeta",
    "sg:city":"Gaeta",
    "sg:classifiers":[
        {
            "category":"Shopping",
            "subcategory":"Clothing, Apparel, & Fashions",
            "type":"Retail Goods"
        }
    ],
    "sg:phone":"+39 0771 712355",
    "sg:postcode":"04024",
    "sg:province":"Latina",
    "sg:tags":[
        "clothing",
        "accessory"
    ],
    "wof:name":"General Clothing Srl",
    "wof:placetype":"venue"
},
  "geometry": {"coordinates":[12.9037,41.467598],"type":"Point"}
}