{
  "type": "Feature",
  "properties": {
    "iso:country":"IT",
    "sg:address":"62, Via Degli Olmi 00172 Roma",
    "sg:city":"Roma",
    "sg:classifiers":[
        {
            "category":"Professional",
            "subcategory":"Business Services",
            "type":"Services"
        }
    ],
    "sg:phone":"+39 39062305773",
    "sg:postcode":"00172",
    "sg:province":"Roma",
    "sg:tags":[
        "advice"
    ],
    "wof:name":"Edizioni Rinnovamento Nello Spirito Santo S.c.r.l.",
    "wof:placetype":"venue"
},
  "geometry": {"coordinates":[12.621875,41.727242],"type":"Point"}
}