{
  "type": "Feature",
  "properties": {
    "addr:full":"00152 Roma Roma Roma 00152",
    "addr:postcode":"00152;00152",
    "iso:country":"IT",
    "sg:address":"00152 Roma",
    "sg:city":"Roma",
    "sg:orig_category":"Ospedali E Servizi Sanitari. Centri Di Estetica E Cosmesi E Servizi",
    "sg:phone":"+39 06 534 2270",
    "sg:postcode":"00152",
    "sg:province":"Roma",
    "wof:name":"Filippi Sabrina",
    "wof:placetype":"venue"
},
  "geometry": {"coordinates":[12.452255,41.875805],"type":"Point"}
}