{
  "type": "Feature",
  "properties": {
    "iso:country":"IT",
    "sg:address":"20123 Milano",
    "sg:city":"Milano",
    "sg:orig_category":"Pelli Per Pellicceria",
    "sg:phone":"+39 02 805 3652",
    "sg:postcode":"20123",
    "sg:province":"Milano",
    "sg:website":"http://www.irpa.it",
    "wof:name":"I.r.p.a. Spa",
    "wof:placetype":"venue"
},
  "geometry": {"coordinates":[9.1874513626,45.4584274292],"type":"Point"}
}