{
  "type": "Feature",
  "properties": {
    "addr:full":"12, Via Amedeo Modigliani 20022 Castano Primo Castano Primo Milano 20022",
    "addr:postcode":"20022;20022",
    "addr:street":"Via Amedeo Modigliani",
    "iso:country":"IT",
    "sg:address":"12, Via Amedeo Modigliani 20022 Castano Primo",
    "sg:city":"Castano Primo",
    "sg:classifiers":[
        {
            "category":"Manufacturing",
            "subcategory":"Rubber & Plastics",
            "type":"Manufacturing & Wholesale Goods"
        }
    ],
    "sg:phone":"+39 0331 880354",
    "sg:postcode":"20022",
    "sg:province":"Milano",
    "wof:name":"Vibiplast (s.r.l.)",
    "wof:placetype":"venue"
},
  "geometry": {"coordinates":[9.1881408691,45.4636878967],"type":"Point"}
}