{
  "type": "Feature",
  "properties": {
    "iso:country":"IT",
    "sg:address":"00100 Roma",
    "sg:classifiers":[
        {
            "category":"Bars & Pubs",
            "subcategory":"Biergarten",
            "type":"Food & Drink"
        }
    ],
    "sg:phone":"+39 06 2780 0278",
    "sg:province":"RM",
    "sg:tags":[
        "birrerie",
        "e"
    ],
    "wof:name":"Ass.ne Guardie E Ladri",
    "wof:placetype":"venue"
},
  "geometry": {"coordinates":[12.807235,42.137844],"type":"Point"}
}