{
  "type": "Feature",
  "properties": {
    "iso:country":"IT",
    "sg:address":"Via Dell Ecologia / 3 20080 Casarile",
    "sg:city":"Casarile",
    "sg:classifiers":[
        {
            "category":"Autos & Motor Vehicles",
            "subcategory":"Auto Supplies",
            "type":"Retail Goods"
        }
    ],
    "sg:phone":"+39 02 900531",
    "sg:postcode":"20080",
    "sg:province":"Milano",
    "sg:tags":[
        "bevel",
        "gearbox"
    ],
    "sg:website":"www.cattini.com",
    "wof:name":"Cattini & Figlio Srl",
    "wof:placetype":"venue"
},
  "geometry": {"coordinates":[9.10311,45.324196],"type":"Point"}
}