{
  "type": "Feature",
  "properties": {
    "iso:country":"IT",
    "sg:address":"65126 Pescara",
    "sg:city":"Pescara",
    "sg:orig_category":"Bilance, Bilici E Bascule",
    "sg:phone":"+39 085 67044",
    "sg:postcode":"65126",
    "sg:province":"Pescara",
    "sg:website":"http://www.scurtibilance.it",
    "wof:name":"Scurti Silvio & C. Sas",
    "wof:placetype":"venue"
},
  "geometry": {"coordinates":[14.222923,42.457901],"type":"Point"}
}