{
  "type": "Feature",
  "properties": {
    "iso:country":"IT",
    "sg:address":"80046 San Giorgio A Cremano",
    "sg:city":"San Giorgio a Cremano",
    "sg:orig_category":"Legno E Semilavorati",
    "sg:phone":"+39 081 485200",
    "sg:postcode":"80046",
    "sg:province":"Napoli",
    "wof:name":"Essetti Snc",
    "wof:placetype":"venue"
},
  "geometry": {"coordinates":[14.335155,40.827343],"type":"Point"}
}