{
  "type": "Feature",
  "properties": {
    "iso:country":"IT",
    "sg:address":"10, Via Bellini Vincenzo 20122 Milano",
    "sg:city":"Milano",
    "sg:classifiers":[
        {
            "category":"Communications",
            "subcategory":"Newspaper",
            "type":"Services"
        }
    ],
    "sg:phone":"+39 02 7600 4299",
    "sg:postcode":"20122",
    "sg:province":"Milano",
    "sg:tags":[
        "advertising"
    ],
    "wof:name":"La Carta Stampata (s.n.c.)",
    "wof:placetype":"venue"
},
  "geometry": {"coordinates":[9.205138,45.465618],"type":"Point"}
}