{
  "type": "Feature",
  "properties": {
    "iso:country":"IT",
    "sg:address":"6, Via Dei Montecchi 34137 Trieste",
    "sg:city":"Trieste",
    "sg:classifiers":[
        {
            "category":"Professional",
            "subcategory":"Printing & Photocopies",
            "type":"Services"
        }
    ],
    "sg:phone":"+39 39040765209",
    "sg:postcode":"34137",
    "sg:province":"Trieste",
    "wof:name":"Edigraf (s.r.l.)",
    "wof:placetype":"venue"
},
  "geometry": {"coordinates":[13.781703949,45.6423339844],"type":"Point"}
}