{
  "type": "Feature",
  "properties": {
    "iso:country":"IT",
    "sg:address":"46100 Mantova",
    "sg:city":"Mantova",
    "sg:orig_category":"Automazione E Macchine Per Ufficio. Forniture Industriali Per Prevenzione, Controllo E Sicurezza",
    "sg:phone":"+39 030 353 4431",
    "sg:postcode":"46100",
    "sg:province":"Mantova",
    "sg:website":"http://www.progetto6.it",
    "wof:name":"Progetto 6 Srl",
    "wof:placetype":"venue"
},
  "geometry": {"coordinates":[10.775153,45.154362],"type":"Point"}
}