{
  "type": "Feature",
  "properties": {
    "addr:full":"41049 Sassuolo Sassuolo Modena 41049",
    "addr:postcode":"41049;41049",
    "iso:country":"IT",
    "sg:address":"41049 Sassuolo",
    "sg:city":"Sassuolo",
    "sg:classifiers":[
        {
            "category":"Home & Garden",
            "subcategory":"Building Materials",
            "type":"Retail Goods"
        }
    ],
    "sg:phone":"+39 0536 920061",
    "sg:postcode":"41049",
    "sg:province":"Modena",
    "sg:tags":[
        "stone",
        "similar",
        "marble"
    ],
    "wof:name":"Manfredini Marmi E Graniti",
    "wof:placetype":"venue"
},
  "geometry": {"coordinates":[10.783485,44.544563],"type":"Point"}
}