{
  "type": "Feature",
  "properties": {
    "iso:country":"IT",
    "sg:address":"Via Venegono 57 21040 Vedano Olona",
    "sg:city":"Vedano Olona",
    "sg:orig_category":"Didactical Toys",
    "sg:phone":"+39 0332 400497",
    "sg:postcode":"21040",
    "sg:province":"Varese",
    "sg:website":"www.vervespa.it",
    "wof:name":"Verve Spa",
    "wof:placetype":"venue"
},
  "geometry": {"coordinates":[8.886576,45.769009],"type":"Point"}
}