{
  "type": "Feature",
  "properties": {
    "addr:full":"32030 Cesiomaggiore Cesiomaggiore Belluno 32030",
    "addr:postcode":"32030;32030",
    "iso:country":"IT",
    "sg:address":"32030 Cesiomaggiore",
    "sg:city":"Cesiomaggiore",
    "sg:orig_category":"Minuterie Metalliche E Ferramenta",
    "sg:phone":"+39 0439 438244",
    "sg:postcode":"32030",
    "sg:province":"Belluno",
    "sg:website":"http://www.didieffe.com",
    "wof:name":"Di Dieffe Di De Bastiani Rolando & C. Snc",
    "wof:placetype":"venue"
},
  "geometry": {"coordinates":[11.9876661301,46.0890731812],"type":"Point"}
}