{
  "type": "Feature",
  "properties": {
    "addr:full":"10138 Torino Torino Torino 10138",
    "addr:housenumber":"10138",
    "addr:postcode":"10138",
    "iso:country":"IT",
    "sg:address":"10138 Torino",
    "sg:city":"Torino",
    "sg:orig_category":"Studi E Consulenze Amministrative, Commerciali E Aziendali. Consulenze Tecniche, Amministrative E Perizie. Professionisti - Studi E Servizi Ed Associazioni Di Interesse Aziendale",
    "sg:phone":"+39 011 434 5590",
    "sg:postcode":"10138",
    "sg:province":"Torino",
    "wof:name":"Massucco Rag. Guido",
    "wof:placetype":"venue"
},
  "geometry": {"coordinates":[7.659314,45.074951],"type":"Point"}
}