{
  "type": "Feature",
  "properties": {
    "addr:full":"10064 Pinerolo Pinerolo Torino 10064",
    "addr:postcode":"10064;10064",
    "iso:country":"IT",
    "sg:address":"10064 Pinerolo",
    "sg:city":"Pinerolo",
    "sg:orig_category":"Accessori Moda D'abbigliamento. Shopping",
    "sg:phone":"+39 0121 322749",
    "sg:postcode":"10064",
    "sg:province":"Torino",
    "wof:name":"Trucco Angela",
    "wof:placetype":"venue"
},
  "geometry": {"coordinates":[7.665073,45.066116],"type":"Point"}
}