{
  "type": "Feature",
  "properties": {
    "iso:country":"IT",
    "sg:address":"42/b, Corso Vittorio Emanuele Ii 33170 Pordenone",
    "sg:city":"Pordenone",
    "sg:classifiers":[
        {
            "category":"Wholesale",
            "subcategory":"Machinery & Supplies",
            "type":"Manufacturing & Wholesale Goods"
        }
    ],
    "sg:phone":"+39 0434 521390",
    "sg:postcode":"33170",
    "sg:province":"Pordenone",
    "sg:tags":[
        "equipment",
        "-",
        "instrument",
        "measurement"
    ],
    "wof:name":"Falcomer S.r.l.",
    "wof:placetype":"venue"
},
  "geometry": {"coordinates":[12.572839,45.867706],"type":"Point"}
}