{
  "type": "Feature",
  "properties": {
    "addr:full":"12, Via Grimaldo 39030 Falzes Falzes Bolzano/Bozen 39030",
    "addr:postcode":"39030;39030",
    "addr:street":"Via Grimaldo",
    "iso:country":"IT",
    "sg:address":"12, Via Grimaldo 39030 Falzes",
    "sg:city":"Falzes",
    "sg:classifiers":[
        {
            "category":"Manufacturing",
            "subcategory":"Lumber",
            "type":"Manufacturing & Wholesale Goods"
        }
    ],
    "sg:phone":"+39 0474 528300",
    "sg:postcode":"39030",
    "sg:province":"Bolzano/Bozen",
    "sg:tags":[
        "wood"
    ],
    "wof:name":"Alpinholz S.a.s.",
    "wof:placetype":"venue"
},
  "geometry": {"coordinates":[11.89951,46.807747],"type":"Point"}
}