{
  "type": "Feature",
  "properties": {
    "addr:full":"Via Datini Francesco 27 50126 Firenze Firenze Firenze 50126",
    "addr:housenumber":"27",
    "addr:postcode":"50126;50126",
    "addr:street":"Via Datini Francesco",
    "iso:country":"IT",
    "sg:address":"Via Datini Francesco 27 50126 Firenze",
    "sg:city":"Firenze",
    "sg:classifiers":[
        {
            "category":"Shopping",
            "subcategory":"Jewelry",
            "type":"Retail Goods"
        }
    ],
    "sg:phone":"+39 055 686518",
    "sg:postcode":"50126",
    "sg:province":"Firenze",
    "sg:tags":[
        "fashion",
        "jewellery"
    ],
    "sg:website":"www.passavinti.it",
    "wof:name":"Passavinti Romano Srl",
    "wof:placetype":"venue"
},
  "geometry": {"coordinates":[11.256901741,43.7687339783],"type":"Point"}
}