{
  "type": "Feature",
  "properties": {
    "iso:country":"IT",
    "sg:address":"35010 Cadoneghe",
    "sg:city":"Cadoneghe",
    "sg:orig_category":"Coppe E Trofei - Produzione E Ingrosso",
    "sg:phone":"+39 049 706544",
    "sg:postcode":"35010",
    "sg:province":"Padova",
    "wof:name":"Serielle Targhe Snc",
    "wof:placetype":"venue"
},
  "geometry": {"coordinates":[11.901815,45.470901],"type":"Point"}
}