{
  "type": "Feature",
  "properties": {
    "addr:full":"8, Via Pilla Leopoldo 46010 Curtatone Curtatone Mantova 46010",
    "addr:postcode":"46010;46010",
    "addr:street":"Via Pilla Leopoldo",
    "iso:country":"IT",
    "sg:address":"8, Via Pilla Leopoldo 46010 Curtatone",
    "sg:city":"Curtatone",
    "sg:classifiers":[
        {
            "category":"Autos & Motor Vehicles",
            "subcategory":"Automobile Sales",
            "type":"Retail Goods"
        }
    ],
    "sg:phone":"+39 0376 346311",
    "sg:postcode":"46010",
    "sg:province":"Mantova",
    "sg:tags":[
        "industrial"
    ],
    "wof:name":"Marconi Industrial Services Spa",
    "wof:placetype":"venue"
},
  "geometry": {"coordinates":[10.724653,45.15377],"type":"Point"}
}