{
  "type": "Feature",
  "properties": {
    "addr:full":"40, Via Galileo Galilei 36030 Costabissara Costabissara Vicenza 36030",
    "addr:postcode":"36030;36030",
    "addr:street":"Via Galileo Galilei",
    "iso:country":"IT",
    "sg:address":"40, Via Galileo Galilei 36030 Costabissara",
    "sg:city":"Costabissara",
    "sg:classifiers":[
        {
            "category":"Communications",
            "subcategory":"Television Station",
            "type":"Services"
        }
    ],
    "sg:phone":"+39 0444 557999",
    "sg:postcode":"36030",
    "sg:province":"Vicenza",
    "sg:tags":[
        "audio-visual"
    ],
    "wof:name":"Mosele Elettronica S.r.l.",
    "wof:placetype":"venue"
},
  "geometry": {"coordinates":[11.503879,45.588718],"type":"Point"}
}