{
  "type": "Feature",
  "properties": {
    "iso:country":"IT",
    "sg:address":"38036 Pozza Di Fassa",
    "sg:city":"Pozza di Fassa",
    "sg:orig_category":"Servizi E Lavori Per Edilizia E Lavori Pubblici. Servizi Al Turismo",
    "sg:phone":"+39 0462 764064",
    "sg:postcode":"38036",
    "sg:province":"Trento",
    "wof:name":"Immobiliare Fassana Srl",
    "wof:placetype":"venue"
},
  "geometry": {"coordinates":[11.680252,46.425774],"type":"Point"}
}