{
  "type": "Feature",
  "properties": {
    "iso:country":"IT",
    "sg:address":"57122 Livorno",
    "sg:city":"Livorno",
    "sg:orig_category":"Servizi Ausiliari Di Analisi, Controllo E Ricerca",
    "sg:postcode":"57122",
    "sg:province":"Livorno",
    "wof:name":"Sgs Redwood Italia Srl",
    "wof:placetype":"venue"
},
  "geometry": {"coordinates":[10.312408,43.559002],"type":"Point"}
}