{
  "type": "Feature",
  "properties": {
    "addr:full":"51037 Montale Montale Pistoia 51037",
    "addr:postcode":"51037;51037",
    "iso:country":"IT",
    "sg:address":"51037 Montale",
    "sg:city":"Montale",
    "sg:orig_category":"Filati E Materie Prime Tessili",
    "sg:phone":"+39 0573 558430",
    "sg:postcode":"51037",
    "sg:province":"Pistoia",
    "wof:name":"For.mar Di Marseo Enrico E C. Sas",
    "wof:placetype":"venue"
},
  "geometry": {"coordinates":[11.0111246109,43.9132041931],"type":"Point"}
}