{
  "type": "Feature",
  "properties": {
    "iso:country":"IT",
    "sg:address":"20125 Milano",
    "sg:city":"Milano",
    "sg:orig_category":"Macchine, Impianti Ed Attrezzature Per Industria Alimentare E Bevande",
    "sg:phone":"+39 02 6671 4822",
    "sg:postcode":"20125",
    "sg:province":"Milano",
    "wof:name":"Panificio Di V. Zuretti Di Natrella Giovanni E C. S.a.s.",
    "wof:placetype":"venue"
},
  "geometry": {"coordinates":[9.206517,45.491119],"type":"Point"}
}