{
  "type": "Feature",
  "properties": {
    "addr:full":"20090 Trezzano Sul Naviglio Trezzano sul Naviglio Milano 20090",
    "addr:postcode":"20090;20090",
    "iso:country":"IT",
    "sg:address":"20090 Trezzano Sul Naviglio",
    "sg:city":"Trezzano sul Naviglio",
    "sg:orig_category":"Forniture Per Edilizia E Lavori Pubblici",
    "sg:phone":"+39 02 4840 1020",
    "sg:postcode":"20090",
    "sg:province":"Milano",
    "wof:name":"Algalite Spa",
    "wof:placetype":"venue"
},
  "geometry": {"coordinates":[9.0418205261,45.4142951965],"type":"Point"}
}