{
  "type": "Feature",
  "properties": {
    "iso:country":"IT",
    "sg:address":"12078 Ormea",
    "sg:city":"Ormea",
    "sg:orig_category":"Bevande, Vini E Liquori",
    "sg:phone":"+39 0174 392238",
    "sg:postcode":"12078",
    "sg:province":"Cuneo",
    "wof:name":"San Pellegrino S.p.a.",
    "wof:placetype":"venue"
},
  "geometry": {"coordinates":[7.926541,44.155491],"type":"Point"}
}