{
  "type": "Feature",
  "properties": {
    "iso:country":"IT",
    "sg:address":"20026 Novate Milanese",
    "sg:city":"Novate Milanese",
    "sg:orig_category":"Prodotti Chimici Di Base. Forniture Per Attivita' Industriali",
    "sg:phone":"+39 02 354 3707",
    "sg:postcode":"20026",
    "sg:province":"Milano",
    "wof:name":"Industria Ceraria F.lli Cicogna S.r.l.",
    "wof:placetype":"venue"
},
  "geometry": {"coordinates":[9.1540021896,45.5271148682],"type":"Point"}
}