{
  "type": "Feature",
  "properties": {
    "iso:country":"IT",
    "sg:address":"63039 S. Benedetto Del Tronto",
    "sg:orig_category":"Metalli E Leghe",
    "sg:phone":"+39 0735 650964",
    "sg:postcode":"63039",
    "sg:province":"Ascoli Piceno",
    "wof:name":"Fersider Di Piermartiri L. & C. Snc",
    "wof:placetype":"venue"
},
  "geometry": {"coordinates":[13.5749769211,42.8554000854],"type":"Point"}
}