{
  "type": "Feature",
  "properties": {
    "iso:country":"IT",
    "sg:address":"25020 Flero",
    "sg:city":"Flero",
    "sg:orig_category":"Materiali Semilavorati Metallici",
    "sg:phone":"+39 030 276 1362",
    "sg:postcode":"25020",
    "sg:province":"Brescia",
    "wof:name":"Eridian Srl",
    "wof:placetype":"venue"
},
  "geometry": {"coordinates":[10.178952,45.474609],"type":"Point"}
}