{
  "type": "Feature",
  "properties": {
    "addr:full":"66054 Vasto Vasto Chieti 66054",
    "addr:postcode":"66054;66054",
    "iso:country":"IT",
    "sg:address":"66054 Vasto",
    "sg:city":"Vasto",
    "sg:orig_category":"Abbigliamento Esterno, Maglierie E Pelliccerie. Shopping",
    "sg:phone":"+39 0873 363709",
    "sg:postcode":"66054",
    "sg:province":"Chieti",
    "wof:name":"Colucci Di Vtr Sartoriale Di Nanni Tania",
    "wof:placetype":"venue"
},
  "geometry": {"coordinates":[14.707646,42.111546],"type":"Point"}
}