{
  "type": "Feature",
  "properties": {
    "addr:full":"Via Dante 1 15060 Vignole Borbera Vignole Borbera Alessandria 15060",
    "addr:housenumber":"1",
    "addr:postcode":"15060;15060",
    "addr:street":"Via Dante",
    "iso:country":"IT",
    "sg:address":"Via Dante 1 15060 Vignole Borbera",
    "sg:city":"Vignole Borbera",
    "sg:classifiers":[
        {
            "category":"Wholesale",
            "subcategory":"Chemicals & Plastics",
            "type":"Manufacturing & Wholesale Goods"
        }
    ],
    "sg:phone":"+39 0143 606111",
    "sg:postcode":"15060",
    "sg:province":"Alessandria",
    "sg:tags":[
        "canister"
    ],
    "sg:website":"www.incoplas.com",
    "wof:name":"Incoplas Italia Spa",
    "wof:placetype":"venue"
},
  "geometry": {"coordinates":[8.91912,44.714981],"type":"Point"}
}