{
  "type": "Feature",
  "properties": {
    "addr:full":"32, Viale Avis 46042 Castel Goffredo Castel Goffredo Mantova 46042",
    "addr:housenumber":"32",
    "addr:postcode":"46042;46042",
    "addr:street":"Viale Avis;Goffredo",
    "iso:country":"IT",
    "sg:address":"32, Viale Avis 46042 Castel Goffredo",
    "sg:city":"Castel Goffredo",
    "sg:classifiers":[
        {
            "category":"Shopping",
            "subcategory":"Clothing, Apparel, & Fashions",
            "type":"Retail Goods"
        }
    ],
    "sg:phone":"+39 0376 770374",
    "sg:postcode":"46042",
    "sg:province":"Mantova",
    "sg:tags":[
        "clothes"
    ],
    "wof:name":"Levante (s.p.a.)",
    "wof:placetype":"venue"
},
  "geometry": {"coordinates":[10.484406,45.29509],"type":"Point"}
}