{
  "type": "Feature",
  "properties": {
    "addr:full":"6, Via Linguetta 60027 Osimo Osimo Ancona 60027",
    "addr:postcode":"60027;60027",
    "addr:street":"Via Linguetta",
    "iso:country":"IT",
    "sg:address":"6, Via Linguetta 60027 Osimo",
    "sg:city":"Osimo",
    "sg:classifiers":[
        {
            "category":"Professional",
            "subcategory":"Engineering",
            "type":"Services"
        }
    ],
    "sg:phone":"+39 39071717148",
    "sg:postcode":"60027",
    "sg:province":"Ancona",
    "sg:tags":[
        "machine",
        "-",
        "mechanical"
    ],
    "wof:name":"F.p.o. Srl",
    "wof:placetype":"venue"
},
  "geometry": {"coordinates":[13.465982,43.474735],"type":"Point"}
}