{
  "type": "Feature",
  "properties": {
    "iso:country":"IT",
    "sg:address":"16121 Genova",
    "sg:city":"Genova",
    "sg:orig_category":"Forniture Di Bordo E Navali",
    "sg:phone":"+39 010 542523",
    "sg:postcode":"16121",
    "sg:province":"Genova",
    "sg:website":"http://www.teccontainer.com",
    "wof:name":"Tec Container Srl",
    "wof:placetype":"venue"
},
  "geometry": {"coordinates":[8.9363069534,44.4048576355],"type":"Point"}
}