{
  "type": "Feature",
  "properties": {
    "addr:full":"31040 Volpago Del Montello Volpago del Montello Treviso 31040",
    "addr:housenumber":"del montello",
    "addr:postcode":"31040;31040",
    "addr:street":"Del Montello",
    "iso:country":"IT",
    "sg:address":"31040 Volpago Del Montello",
    "sg:city":"Volpago del Montello",
    "sg:orig_category":"Metalli E Leghe",
    "sg:phone":"+39 0423 620117",
    "sg:postcode":"31040",
    "sg:province":"Treviso",
    "wof:name":"F.a. Giori Di Giori Francesco",
    "wof:placetype":"venue"
},
  "geometry": {"coordinates":[12.1506061554,45.7804985046],"type":"Point"}
}