{
  "type": "Feature",
  "properties": {
    "iso:country":"IT",
    "sg:address":"3, Via Rosario 36027 Rosa'",
    "sg:classifiers":[
        {
            "category":"Home & Garden",
            "subcategory":"Home Furnishings",
            "type":"Retail Goods"
        }
    ],
    "sg:phone":"+39 0424 580502",
    "sg:postcode":"36027",
    "sg:province":"Vicenza",
    "sg:tags":[
        "household"
    ],
    "wof:name":"Torresan F.lli S.r.l.",
    "wof:placetype":"venue"
},
  "geometry": {"coordinates":[11.540307,45.545906],"type":"Point"}
}