{
  "type": "Feature",
  "properties": {
    "iso:country":"IT",
    "sg:address":"16, Via Greppi Leonardo 00149 Roma",
    "sg:city":"Roma",
    "sg:classifiers":[
        {
            "category":"Sports & Exercise",
            "subcategory":"Playing Field",
            "type":"Entertainment"
        }
    ],
    "sg:phone":"+39 39065587781",
    "sg:postcode":"00149",
    "sg:province":"Roma",
    "sg:tags":[
        "game"
    ],
    "wof:name":"Ridi & Madon S.a.s. Di Ridi Massimo",
    "wof:placetype":"venue"
},
  "geometry": {"coordinates":[12.459918,41.863064],"type":"Point"}
}