{
  "type": "Feature",
  "properties": {
    "iso:country":"IT",
    "sg:address":"Viale Monza 355 20126 Milano",
    "sg:city":"Milano",
    "sg:classifiers":[
        {
            "category":"Farming",
            "subcategory":"Nursery",
            "type":"Manufacturing & Wholesale Goods"
        }
    ],
    "sg:phone":"+39 02 255 0725",
    "sg:postcode":"20126",
    "sg:province":"Milano",
    "sg:tags":[
        "greenhouse"
    ],
    "sg:website":"www.laserra2003.3000.it",
    "wof:name":"La Serra 2003",
    "wof:placetype":"venue"
},
  "geometry": {"coordinates":[9.227214,45.521374],"type":"Point"}
}