{
  "type": "Feature",
  "properties": {
    "addr:full":"20068 Bellingera Milano 20068",
    "addr:postcode":"20068;20068",
    "addr:street":"Bellingera",
    "iso:country":"IT",
    "sg:address":"20068 Bellingera",
    "sg:orig_category":"Prodotti Chimici Di Base",
    "sg:phone":"+39 02 547 1944",
    "sg:postcode":"20068",
    "sg:province":"Milano",
    "wof:name":"La Nuova Corpis Snc",
    "wof:placetype":"venue"
},
  "geometry": {"coordinates":[9.1881408691,45.4636878967],"type":"Point"}
}