{
  "type": "Feature",
  "properties": {
    "addr:full":"37012 Bussolengo Bussolengo Verona 37012",
    "addr:postcode":"37012;37012",
    "iso:country":"IT",
    "sg:address":"37012 Bussolengo",
    "sg:city":"Bussolengo",
    "sg:orig_category":"Forniture Ospedaliere",
    "sg:phone":"+39 045 670 1977",
    "sg:postcode":"37012",
    "sg:province":"Verona",
    "sg:website":"http://www.servicemed.it",
    "wof:name":"Service Med Srl",
    "wof:placetype":"venue"
},
  "geometry": {"coordinates":[10.8640918732,45.4496955872],"type":"Point"}
}