{
  "type": "Feature",
  "properties": {
    "iso:country":"IT",
    "sg:address":"23015 Dubino",
    "sg:city":"Dubino",
    "sg:orig_category":"Macchine Ed Impianti Per Edilizia E Lavori Pubblici",
    "sg:phone":"+39 0342 680913",
    "sg:postcode":"23015",
    "sg:province":"Sondrio",
    "wof:name":"Mpi Di Cipriani Andrea",
    "wof:placetype":"venue"
},
  "geometry": {"coordinates":[9.442695,46.154037],"type":"Point"}
}