{
  "type": "Feature",
  "properties": {
    "iso:country":"IT",
    "sg:address":"24046 Osio Sotto",
    "sg:city":"Osio Sotto",
    "sg:orig_category":"Non-classified Establishments",
    "sg:phone":"+39 035 808981",
    "sg:postcode":"24046",
    "sg:province":"Bergamo",
    "wof:name":"Terrecotte Gerbelli",
    "wof:placetype":"venue"
},
  "geometry": {"coordinates":[9.590505,45.671326],"type":"Point"}
}