{
  "type": "Feature",
  "properties": {
    "iso:country":"IT",
    "sg:address":"36015 Schio",
    "sg:city":"Schio",
    "sg:orig_category":"Serramenti Ed Infissi",
    "sg:phone":"+39 0445 575249",
    "sg:postcode":"36015",
    "sg:province":"Vicenza",
    "wof:name":"Liras Srl",
    "wof:placetype":"venue"
},
  "geometry": {"coordinates":[11.370108,45.706112],"type":"Point"}
}