{
  "type": "Feature",
  "properties": {
    "iso:country":"IT",
    "sg:address":"37136 Verona",
    "sg:city":"Verona",
    "sg:orig_category":"Automazione E Macchine Per Ufficio. Servizi Ausiliari Di Certificati, Riproduzioni, Disegni E Foto",
    "sg:phone":"+39 045 950500",
    "sg:postcode":"37136",
    "sg:province":"Verona",
    "wof:name":"Sip Microfilm Service (s.r.l.)",
    "wof:placetype":"venue"
},
  "geometry": {"coordinates":[10.962977,45.415493],"type":"Point"}
}