{
  "type": "Feature",
  "properties": {
    "addr:full":"Via Beccaria 1, 95123 Catania, Ct Catania Catania 95123",
    "addr:housenumber":"1",
    "addr:postcode":"95123;95123",
    "addr:street":"Via Beccaria;Ct",
    "iso:country":"IT",
    "sg:address":"Via Beccaria 1, 95123 Catania, Ct",
    "sg:city":"Catania",
    "sg:classifiers":[
        {
            "category":"Banks & Credit Unions",
            "subcategory":"Bank",
            "type":"Services"
        }
    ],
    "sg:phone":"+39 095 716 4112",
    "sg:postcode":"95123",
    "sg:province":"Catania",
    "wof:name":"Credito Etneo-banca Di Credito Cooperativo Scrl",
    "wof:placetype":"venue"
},
  "geometry": {"coordinates":[15.074985,37.514503],"type":"Point"}
}