{
  "type": "Feature",
  "properties": {
    "addr:full":"96010 Palazzolo Acreide Palazzolo Acreide Siracusa 96010",
    "addr:postcode":"96010;96010",
    "iso:country":"IT",
    "sg:address":"96010 Palazzolo Acreide",
    "sg:city":"Palazzolo Acreide",
    "sg:orig_category":"Acque Minerali E Bevande, Naturali E Gassate - Commercio",
    "sg:phone":"+39 0931 882040",
    "sg:postcode":"96010",
    "sg:province":"Siracusa",
    "wof:name":"Amodio Paolo",
    "wof:placetype":"venue"
},
  "geometry": {"coordinates":[15.121301,37.103283],"type":"Point"}
}