{
  "type": "Feature",
  "properties": {
    "addr:full":"00195 Roma Roma Roma 00195",
    "addr:postcode":"00195;00195",
    "iso:country":"IT",
    "sg:address":"00195 Roma",
    "sg:city":"Roma",
    "sg:orig_category":"Elettronica Professionale E Di Consumo. Automazione E Macchine Per Ufficio. Forniture Per Congressi, Fiere E Manifestazioni",
    "sg:phone":"+39 06 321 2694",
    "sg:postcode":"00195",
    "sg:province":"Roma",
    "wof:name":"Tecnedit (s.r.l.)",
    "wof:placetype":"venue"
},
  "geometry": {"coordinates":[12.465498,41.913795],"type":"Point"}
}