{
  "type": "Feature",
  "properties": {
    "iso:country":"IT",
    "sg:address":"20145 Milano",
    "sg:city":"Milano",
    "sg:orig_category":"Prodotti Alimentari. Shopping",
    "sg:phone":"+39 02 4802 2126",
    "sg:postcode":"20145",
    "sg:province":"Milano",
    "wof:name":"Poli Fabio",
    "wof:placetype":"venue"
},
  "geometry": {"coordinates":[9.1550445557,45.4676475525],"type":"Point"}
}