{
  "type": "Feature",
  "properties": {
    "addr:full":"70, Corso Cavour Camillo Benso 70121 Bari Bari Bari 70121",
    "addr:postcode":"70121;70121",
    "addr:street":"Corso Cavour Camillo Benso",
    "iso:country":"IT",
    "sg:address":"70, Corso Cavour Camillo Benso 70121 Bari",
    "sg:city":"Bari",
    "sg:classifiers":[
        {
            "category":"Wholesale",
            "subcategory":"Machinery & Supplies",
            "type":"Manufacturing & Wholesale Goods"
        }
    ],
    "sg:phone":"+39 080 528 2619",
    "sg:postcode":"70121",
    "sg:province":"Bari",
    "sg:tags":[
        "equipment",
        "precision"
    ],
    "wof:name":"Campus S.a.s. Di Salvatore Scalabrino & C.",
    "wof:placetype":"venue"
},
  "geometry": {"coordinates":[16.8846282959,41.0466117859],"type":"Point"}
}