{
  "type": "Feature",
  "properties": {
    "addr:full":"40010 Sala Bolognese Sala Bolognese Bologna 40010",
    "addr:postcode":"40010;40010",
    "addr:street":"Bolognese",
    "iso:country":"IT",
    "sg:address":"40010 Sala Bolognese",
    "sg:city":"Sala Bolognese",
    "sg:classifiers":[
        {
            "category":"Home & Garden",
            "subcategory":"Furniture",
            "type":"Retail Goods"
        }
    ],
    "sg:phone":"+39 051 681 4796",
    "sg:postcode":"40010",
    "sg:province":"Bologna",
    "sg:tags":[
        "furnishing"
    ],
    "sg:website":"http://www.mcmsrlmonti.it",
    "wof:name":"M.c.m. Srl",
    "wof:placetype":"venue"
},
  "geometry": {"coordinates":[11.2667160034,44.5393638611],"type":"Point"}
}