{
  "type": "Feature",
  "properties": {
    "iso:country":"IT",
    "sg:address":"Via Volta , 15/17 46030 San Giorgio Di Mantova",
    "sg:city":"San Giorgio di Mantova",
    "sg:classifiers":[
        {
            "category":"Shopping",
            "subcategory":"Clothing, Apparel, & Fashions",
            "type":"Retail Goods"
        }
    ],
    "sg:phone":"+39 0376 372952",
    "sg:postcode":"46030",
    "sg:province":"Mantova",
    "sg:tags":[
        "knitted",
        "knitwear",
        "clothes"
    ],
    "sg:website":"www.maglificiogianni.it",
    "wof:name":"Maglificio Gianni Di Zapparoli Gian",
    "wof:placetype":"venue"
},
  "geometry": {"coordinates":[10.835391,45.161167],"type":"Point"}
}