{
  "type": "Feature",
  "properties": {
    "addr:full":"24030 Mapello Mapello Bergamo 24030",
    "addr:postcode":"24030;24030",
    "iso:country":"IT",
    "sg:address":"24030 Mapello",
    "sg:city":"Mapello",
    "sg:orig_category":"Macchine, Impianti Ed Attrezzature Industria Chimica",
    "sg:phone":"+39 035 909078",
    "sg:postcode":"24030",
    "sg:province":"Bergamo",
    "sg:website":"http://www.simas.net",
    "wof:name":"S.i.m.a.s. Spa",
    "wof:placetype":"venue"
},
  "geometry": {"coordinates":[9.580441,45.740799],"type":"Point"}
}