{
  "type": "Feature",
  "properties": {
    "iso:country":"IT",
    "sg:address":"Via Pineta Sacchetti 506; Roma",
    "sg:classifiers":[
        {
            "category":"Banks & Credit Unions",
            "subcategory":"Bank",
            "type":"Services"
        }
    ],
    "sg:phone":"+39 06 3551 0200",
    "wof:name":"Banca Di Roma",
    "wof:placetype":"venue"
},
  "geometry": {"coordinates":[12.426665,41.92717],"type":"Point"}
}