{
  "type": "Feature",
  "properties": {
    "addr:full":"15100 Alessandria Alessandria Alessandria 15100",
    "addr:postcode":"15100;15100",
    "iso:country":"IT",
    "sg:address":"15100 Alessandria",
    "sg:city":"Alessandria",
    "sg:orig_category":"Ospedali E Servizi Sanitari",
    "sg:phone":"+39 0131 43225",
    "sg:postcode":"15100",
    "sg:province":"Alessandria",
    "wof:name":"Ferraris Mauro & Alcidi Renato Snc",
    "wof:placetype":"venue"
},
  "geometry": {"coordinates":[8.635797,44.655628],"type":"Point"}
}