{
  "type": "Feature",
  "properties": {
    "iso:country":"IT",
    "sg:address":"19, Via Trivulzia 23027 Samolaco",
    "sg:city":"Samolaco",
    "sg:classifiers":[
        {
            "category":"Manufacturing",
            "subcategory":"Metals",
            "type":"Manufacturing & Wholesale Goods"
        }
    ],
    "sg:phone":"+39 39034348000",
    "sg:postcode":"23027",
    "sg:province":"Sondrio",
    "sg:tags":[
        "metallurgy",
        "metalworking"
    ],
    "wof:name":"Ommes S.r.l.",
    "wof:placetype":"venue"
},
  "geometry": {"coordinates":[9.3996152878,46.2446784973],"type":"Point"}
}