{
  "type": "Feature",
  "properties": {
    "iso:country":"IT",
    "sg:address":"86100 Campobasso",
    "sg:city":"Campobasso",
    "sg:orig_category":"Servizi Editoriali. Pubblicita', Marketing E Comunicazione",
    "sg:phone":"+39 0874 484624",
    "sg:postcode":"86100",
    "sg:province":"Campobasso",
    "wof:name":"Teleregione Srl",
    "wof:placetype":"venue"
},
  "geometry": {"coordinates":[14.659244,41.557777],"type":"Point"}
}