{
  "type": "Feature",
  "properties": {
    "iso:country":"IT",
    "sg:address":"5, Via Console Flaminio 20134 Milano",
    "sg:city":"Milano",
    "sg:classifiers":[
        {
            "category":"Manufacturing",
            "subcategory":"Paper Products",
            "type":"Manufacturing & Wholesale Goods"
        }
    ],
    "sg:phone":"+39 02 2641 3463",
    "sg:postcode":"20134",
    "sg:province":"Milano",
    "sg:tags":[
        "cardboard"
    ],
    "wof:name":"Malta Srl",
    "wof:placetype":"venue"
},
  "geometry": {"coordinates":[9.2420415878,45.4804916382],"type":"Point"}
}