{
  "type": "Feature",
  "properties": {
    "addr:full":"00153 Roma Roma Roma 00153",
    "addr:postcode":"00153;00153",
    "iso:country":"IT",
    "sg:address":"00153 Roma",
    "sg:city":"Roma",
    "sg:orig_category":"Servizi Per Lo Sport E Il Tempo Libero. Servizi Al Turismo",
    "sg:phone":"+39 06 574 0637",
    "sg:postcode":"00153",
    "sg:province":"Roma",
    "wof:name":"Centro Sportivo Aventino",
    "wof:placetype":"venue"
},
  "geometry": {"coordinates":[12.478448,41.879753],"type":"Point"}
}