{
  "type": "Feature",
  "properties": {
    "iso:country":"IT",
    "sg:address":"Viale Asia 21 00144 Roma",
    "sg:city":"Roma",
    "sg:classifiers":[
        {
            "category":"Professional",
            "subcategory":"Business Services",
            "type":"Services"
        }
    ],
    "sg:phone":"+39 06 5422 0352",
    "sg:postcode":"00144",
    "sg:province":"Roma",
    "sg:tags":[
        "agency",
        "export"
    ],
    "sg:website":"www.iisit.com",
    "wof:name":"Intertrade International Services Srl",
    "wof:placetype":"venue"
},
  "geometry": {"coordinates":[12.466896,41.832352],"type":"Point"}
}