{
  "type": "Feature",
  "properties": {
    "iso:country":"IT",
    "sg:address":"52044 Cortona",
    "sg:city":"Cortona",
    "sg:orig_category":"Pozzi Artesiani - Trivellazione E Manutenzione",
    "sg:phone":"+39 0575 603569",
    "sg:postcode":"52044",
    "sg:province":"Arezzo",
    "wof:name":"Finocchi Silvano Di Adriano E Claudio Finocchi",
    "wof:placetype":"venue"
},
  "geometry": {"coordinates":[11.9758167267,43.2588653564],"type":"Point"}
}