{
  "type": "Feature",
  "properties": {
    "addr:full":"63010 Lido Di Fermo Ascoli Piceno 63010",
    "addr:postcode":"63010;63010",
    "addr:street":"Di Fermo;Piceno",
    "iso:country":"IT",
    "sg:address":"63010 Lido Di Fermo",
    "sg:orig_category":"Abbigliamento Esterno, Maglierie E Pelliccerie",
    "sg:phone":"+39 0734 641542",
    "sg:postcode":"63010",
    "sg:province":"Ascoli Piceno",
    "wof:name":"Casa Del Cameriere",
    "wof:placetype":"venue"
},
  "geometry": {"coordinates":[13.574977,42.8554],"type":"Point"}
}