{
  "type": "Feature",
  "properties": {
    "iso:country":"IT",
    "sg:address":"Via Panza 37; S. Salvatore Monferrato; 15046",
    "sg:classifiers":[
        {
            "category":"Banks & Credit Unions",
            "subcategory":"Bank",
            "type":"Services"
        }
    ],
    "sg:phone":"+39 0131 237006",
    "sg:postcode":"15046",
    "sg:province":"Alessandria",
    "wof:name":"Istituto Bancario, San Paolo Di Torino Spa",
    "wof:placetype":"venue"
},
  "geometry": {"coordinates":[8.566593,44.995087],"type":"Point"}
}