{
  "type": "Feature",
  "properties": {
    "addr:full":"13878 Candelo Candelo Biella 13878",
    "addr:postcode":"13878;13878",
    "iso:country":"IT",
    "sg:address":"13878 Candelo",
    "sg:city":"Candelo",
    "sg:orig_category":"Filati E Materie Prime Tessili",
    "sg:phone":"+39 015 253 0003",
    "sg:postcode":"13878",
    "sg:province":"Biella",
    "wof:name":"Cofil Di Fila Robattino Dario & C. Snc",
    "wof:placetype":"venue"
},
  "geometry": {"coordinates":[8.1053161621,45.5375099182],"type":"Point"}
}