{
  "type": "Feature",
  "properties": {
    "iso:country":"IT",
    "sg:address":"Corso Garibaldi 71, 66050 San Salvo, Ch",
    "sg:city":"San Salvo",
    "sg:classifiers":[
        {
            "category":"Banks & Credit Unions",
            "subcategory":"Bank",
            "type":"Services"
        }
    ],
    "sg:postcode":"66050",
    "sg:province":"Chieti",
    "wof:name":"Banca Di Credito Cooperativo Della Valle Del Trigno Scrl",
    "wof:placetype":"venue"
},
  "geometry": {"coordinates":[14.7276,42.044559],"type":"Point"}
}