{
  "type": "Feature",
  "properties": {
    "iso:country":"IT",
    "sg:address":"457, Viale Dell' Appennino 47100 Forli'",
    "sg:classifiers":[
        {
            "category":"Wholesale",
            "subcategory":"Drugs",
            "type":"Manufacturing & Wholesale Goods"
        }
    ],
    "sg:phone":"+39 39054384747",
    "sg:postcode":"47100",
    "sg:province":"Forl\u00ec-Cesena",
    "sg:tags":[
        "chemical",
        "pharmaceutical"
    ],
    "wof:name":"L.e.i.c.a. Spa",
    "wof:placetype":"venue"
},
  "geometry": {"coordinates":[11.980461,43.994766],"type":"Point"}
}