{
  "type": "Feature",
  "properties": {
    "iso:country":"IT",
    "sg:address":"00175 Roma",
    "sg:city":"Roma",
    "sg:orig_category":"Ricambi E Componenti Dei Mezzi Di Trasporto",
    "sg:phone":"+39 06 7696 0474",
    "sg:postcode":"00175",
    "sg:province":"Roma",
    "wof:name":"Stacchi Alfredo",
    "wof:placetype":"venue"
},
  "geometry": {"coordinates":[12.584893,41.910336],"type":"Point"}
}