{
  "type": "Feature",
  "properties": {
    "iso:country":"IT",
    "sg:address":"Via Provinciale Per Colle Brianza 23851 Galbiate",
    "sg:city":"Galbiate",
    "sg:orig_category":"Plexiglass Machining",
    "sg:phone":"+39 0341 240222",
    "sg:postcode":"23851",
    "sg:province":"Lecco",
    "sg:website":"www.artvetro.com",
    "wof:name":"Art Vetro Srl",
    "wof:placetype":"venue"
},
  "geometry": {"coordinates":[9.3742361069,45.7993202209],"type":"Point"}
}