{
  "type": "Feature",
  "properties": {
    "addr:full":"Via Elpidiense Sud 289/b 63014 Montegranaro Montegranaro Ascoli Piceno 63014",
    "addr:housenumber":"289 / b",
    "addr:postcode":"63014;63014",
    "addr:street":"Via Elpidiense Sud",
    "iso:country":"IT",
    "sg:address":"Via Elpidiense Sud 289/b 63014 Montegranaro",
    "sg:city":"Montegranaro",
    "sg:classifiers":[
        {
            "category":"Shopping",
            "subcategory":"Shoes",
            "type":"Retail Goods"
        }
    ],
    "sg:phone":"+39 0734 891242",
    "sg:postcode":"63014",
    "sg:province":"Ascoli Piceno",
    "sg:tags":[
        "men's",
        "boot"
    ],
    "wof:name":"Calzaturificio Duca Del Nord Srl",
    "wof:placetype":"venue"
},
  "geometry": {"coordinates":[13.5749769211,42.8554000854],"type":"Point"}
}