{
  "type": "Feature",
  "properties": {
    "iso:country":"IT",
    "sg:address":"Via Meucci 19 37036 San Martino Buon Albergo",
    "sg:city":"San Martino Buon Albergo",
    "sg:classifiers":[
        {
            "category":"Banks & Credit Unions",
            "subcategory":"Investment Brokerage",
            "type":"Services"
        }
    ],
    "sg:phone":"+39 045 990261",
    "sg:postcode":"37036",
    "sg:province":"Verona",
    "sg:tags":[
        "women's",
        "clothing",
        "accessory"
    ],
    "sg:website":"www.lcbcompanz.com",
    "wof:name":"Lcb Company Srl",
    "wof:placetype":"venue"
},
  "geometry": {"coordinates":[11.109232,45.420265],"type":"Point"}
}