{
  "type": "Feature",
  "properties": {
    "addr:full":"90139 Palermo Palermo Palermo 90139",
    "addr:postcode":"90139;90139",
    "iso:country":"IT",
    "sg:address":"90139 Palermo",
    "sg:city":"Palermo",
    "sg:orig_category":"Agenzie Ed Enti Turistici. Acqua, Luce, Gas E Societa' Di Esercizio Pubblico",
    "sg:phone":"+39 091 332766",
    "sg:postcode":"90139",
    "sg:province":"Palermo",
    "sg:website":"http://www.cormorano.net/ebrts",
    "wof:name":"Ente Bilaterale Regionale Turismo Siciliano",
    "wof:placetype":"venue"
},
  "geometry": {"coordinates":[13.358455,38.121315],"type":"Point"}
}