{
  "type": "Feature",
  "properties": {
    "iso:country":"IT",
    "sg:address":"74020 Avetrana",
    "sg:city":"Avetrana",
    "sg:orig_category":"Marmo, Pietre Ed Affini",
    "sg:phone":"+39 348 827 4254",
    "sg:postcode":"74020",
    "sg:province":"Taranto",
    "wof:name":"Edil Decor Di Scarciglia Vincenzo",
    "wof:placetype":"venue"
},
  "geometry": {"coordinates":[17.727739,40.349419],"type":"Point"}
}