{
  "type": "Feature",
  "properties": {
    "addr:full":"20060 Bussero Bussero Milano 20060",
    "addr:postcode":"20060;20060",
    "iso:country":"IT",
    "sg:address":"20060 Bussero",
    "sg:city":"Bussero",
    "sg:orig_category":"Servizi Ausiliari Di Analisi, Controllo E Ricerca",
    "sg:phone":"+39 02 9533 0351",
    "sg:postcode":"20060",
    "sg:province":"Milano",
    "wof:name":"Teknema Srl",
    "wof:placetype":"venue"
},
  "geometry": {"coordinates":[9.2455053329,45.5177230835],"type":"Point"}
}