{
  "type": "Feature",
  "properties": {
    "iso:country":"IT",
    "sg:address":"28845 Domodossola",
    "sg:city":"Domodossola",
    "sg:orig_category":"Cartotecnica E Servizi. Forniture Per Uffici",
    "sg:phone":"+39 0324 242883",
    "sg:postcode":"28845",
    "sg:province":"Verbano-Cusio-Ossola",
    "wof:name":"Bolamperti Snc",
    "wof:placetype":"venue"
},
  "geometry": {"coordinates":[8.272465,46.139969],"type":"Point"}
}