{
  "type": "Feature",
  "properties": {
    "addr:full":"20122 Milano Milano Milano 20122",
    "addr:postcode":"20122;20122",
    "iso:country":"IT",
    "sg:address":"20122 Milano",
    "sg:city":"Milano",
    "sg:orig_category":"Consulenze Speciali",
    "sg:phone":"+39 02 265991",
    "sg:postcode":"20122",
    "sg:province":"Milano",
    "sg:website":"http://www.sergio.coppola.com",
    "wof:name":"Sergio Coppola Designer",
    "wof:placetype":"venue"
},
  "geometry": {"coordinates":[9.20331,45.454441],"type":"Point"}
}