{
  "type": "Feature",
  "properties": {
    "iso:country":"IT",
    "sg:address":"Via Brabbia 5 21020 Varano Borghi",
    "sg:city":"Varano Borghi",
    "sg:orig_category":"Rescue Service Clothing",
    "sg:phone":"+39 0332 960000",
    "sg:postcode":"21020",
    "sg:province":"Varese",
    "sg:website":"www.reversesrl.com",
    "wof:name":"Reverse S.r.l.",
    "wof:placetype":"venue"
},
  "geometry": {"coordinates":[8.728173,45.795578],"type":"Point"}
}