{
  "type": "Feature",
  "properties": {
    "addr:full":"65010 Spoltore Spoltore Pescara 65010",
    "addr:postcode":"65010;65010",
    "iso:country":"IT",
    "sg:address":"65010 Spoltore",
    "sg:city":"Spoltore",
    "sg:orig_category":"Prodotti Alimentari",
    "sg:phone":"+39 085 497 1233",
    "sg:postcode":"65010",
    "sg:province":"Pescara",
    "wof:name":"Ipid-diodati M.&trabucco L.sas",
    "wof:placetype":"venue"
},
  "geometry": {"coordinates":[14.1594705582,42.4263763428],"type":"Point"}
}