{
  "type": "Feature",
  "properties": {
    "iso:country":"IT",
    "sg:address":"16018 Mignanego",
    "sg:city":"Mignanego",
    "sg:orig_category":"Prodotti Chimici Di Base",
    "sg:phone":"+39 010 772 0751",
    "sg:postcode":"16018",
    "sg:province":"Genova",
    "wof:name":"Api (s.p.a.)",
    "wof:placetype":"venue"
},
  "geometry": {"coordinates":[8.9099092484,44.5277099609],"type":"Point"}
}