{
  "type": "Feature",
  "properties": {
    "iso:country":"IT",
    "sg:address":"80146 Napoli",
    "sg:city":"Napoli",
    "sg:orig_category":"Autoaccessori - Commercio",
    "sg:phone":"+39 081 752 9184",
    "sg:postcode":"80146",
    "sg:province":"Napoli",
    "wof:name":"D.e.r. Snc",
    "wof:placetype":"venue"
},
  "geometry": {"coordinates":[14.302327,40.837688],"type":"Point"}
}