{
  "type": "Feature",
  "properties": {
    "addr:full":"59100 Prato Prato Prato 59100",
    "addr:postcode":"59100;59100",
    "iso:country":"IT",
    "sg:address":"59100 Prato",
    "sg:city":"Prato",
    "sg:orig_category":"Arredi Ed Attrezzature Per Attivita' Commerciali Ed Artigianali",
    "sg:phone":"+39 0574 550054",
    "sg:postcode":"59100",
    "sg:province":"Prato",
    "wof:name":"Anteprima Sas",
    "wof:placetype":"venue"
},
  "geometry": {"coordinates":[11.139304,43.857925],"type":"Point"}
}