{
  "type": "Feature",
  "properties": {
    "iso:country":"IT",
    "sg:address":"20129 Milano",
    "sg:city":"Milano",
    "sg:classifiers":[
        {
            "category":"Health Services",
            "subcategory":"Health Practitioner",
            "type":"Services"
        }
    ],
    "sg:phone":"+39 02 2940 0324",
    "sg:postcode":"20129",
    "sg:province":"Milano",
    "sg:tags":[
        "medici"
    ],
    "wof:name":"Omodeo Sale' Giorgio",
    "wof:placetype":"venue"
},
  "geometry": {"coordinates":[9.2149791718,45.4781112671],"type":"Point"}
}