{
  "type": "Feature",
  "properties": {
    "iso:country":"IT",
    "sg:address":"4, Via Della Casa Buia 40129 Bologna",
    "sg:city":"Bologna",
    "sg:classifiers":[
        {
            "category":"Utilities",
            "subcategory":"Electric",
            "type":"Services"
        }
    ],
    "sg:phone":"+39 39051327892",
    "sg:postcode":"40129",
    "sg:province":"Bologna",
    "sg:tags":[
        "component",
        "electronic"
    ],
    "wof:name":"Torel (s.r.l.)",
    "wof:placetype":"venue"
},
  "geometry": {"coordinates":[11.350967,44.542213],"type":"Point"}
}