{
  "type": "Feature",
  "properties": {
    "iso:country":"IT",
    "sg:address":"86039 Termoli",
    "sg:city":"Termoli",
    "sg:orig_category":"Cambia Valute",
    "sg:phone":"+39 0875 705979",
    "sg:postcode":"86039",
    "sg:province":"Campobasso",
    "wof:name":"Cambia Valute Ge.scos.s.",
    "wof:placetype":"venue"
},
  "geometry": {"coordinates":[14.997303,41.962578],"type":"Point"}
}