{
  "type": "Feature",
  "properties": {
    "iso:country":"IT",
    "sg:address":"20047 Brugherio",
    "sg:city":"Brugherio",
    "sg:orig_category":"Bevande, Vini E Liquori",
    "sg:phone":"+39 039 287 5809",
    "sg:postcode":"20047",
    "sg:province":"Milano",
    "sg:website":"http://www.samsaratsc.com",
    "wof:name":"La Volta Rossa",
    "wof:placetype":"venue"
},
  "geometry": {"coordinates":[9.31269,45.541588],"type":"Point"}
}