{
  "type": "Feature",
  "properties": {
    "iso:country":"IT",
    "sg:address":"Strada Epitaffio 04100 Latina",
    "sg:city":"Latina",
    "sg:classifiers":[
        {
            "category":"Sports & Exercise",
            "subcategory":"Playing Field",
            "type":"Entertainment"
        }
    ],
    "sg:phone":"+39 0773 489915",
    "sg:postcode":"04100",
    "sg:province":"Latina",
    "sg:tags":[
        "game"
    ],
    "wof:name":"Dino Mantovani E C. Snc.",
    "wof:placetype":"venue"
},
  "geometry": {"coordinates":[12.931159,41.508556],"type":"Point"}
}