{
  "type": "Feature",
  "properties": {
    "addr:full":"15, Via Dell' Artigianato 46048 Roverbella Roverbella Mantova 46048",
    "addr:postcode":"46048;46048",
    "addr:street":"Via Dell ' Artigianato",
    "iso:country":"IT",
    "sg:address":"15, Via Dell' Artigianato 46048 Roverbella",
    "sg:city":"Roverbella",
    "sg:classifiers":[
        {
            "category":"Manufacturing",
            "subcategory":"Metals",
            "type":"Manufacturing & Wholesale Goods"
        }
    ],
    "sg:phone":"+39 0376 694118",
    "sg:postcode":"46048",
    "sg:province":"Mantova",
    "sg:tags":[
        "processing"
    ],
    "wof:name":"Torneria T.r.c.g. Di Corradi Gianni E C. (s.r.l.)",
    "wof:placetype":"venue"
},
  "geometry": {"coordinates":[10.7960681915,45.2175559998],"type":"Point"}
}