{
  "type": "Feature",
  "properties": {
    "addr:full":"20059 Vimercate Vimercate Milano 20059",
    "addr:postcode":"20059;20059",
    "iso:country":"IT",
    "sg:address":"20059 Vimercate",
    "sg:city":"Vimercate",
    "sg:classifiers":[
        {
            "category":"Retail",
            "subcategory":"Storage",
            "type":"Services"
        }
    ],
    "sg:phone":"+39 039 608 2860",
    "sg:postcode":"20059",
    "sg:province":"Milano",
    "sg:tags":[
        "packaging",
        "article",
        "packing"
    ],
    "sg:website":"http://www.simisrl.it",
    "wof:name":"Simi Srl",
    "wof:placetype":"venue"
},
  "geometry": {"coordinates":[9.3688325882,45.619342804],"type":"Point"}
}