{
  "type": "Feature",
  "properties": {
    "addr:full":"00146 Roma Roma Roma 00146",
    "addr:postcode":"00146;00146",
    "iso:country":"IT",
    "sg:address":"00146 Roma",
    "sg:city":"Roma",
    "sg:classifiers":[
        {
            "category":"Health Services",
            "subcategory":"Health Practitioner",
            "type":"Services"
        }
    ],
    "sg:phone":"+39 06 556 1702",
    "sg:postcode":"00146",
    "sg:province":"Roma",
    "sg:tags":[
        "medici"
    ],
    "wof:name":"Liturri Aldo",
    "wof:placetype":"venue"
},
  "geometry": {"coordinates":[12.467546,41.871635],"type":"Point"}
}