{
  "type": "Feature",
  "properties": {
    "addr:full":"20121 Milano Milano Milano 20121",
    "addr:postcode":"20121;20121",
    "iso:country":"IT",
    "sg:address":"20121 Milano",
    "sg:city":"Milano",
    "sg:orig_category":"Studi E Consulenze Amministrative, Commerciali E Aziendali. Consulenze Tecniche, Amministrative E Perizie",
    "sg:phone":"+39 02 291 1487",
    "sg:postcode":"20121",
    "sg:province":"Milano",
    "sg:website":"http://www.mega.com",
    "wof:name":"Mega International Srl",
    "wof:placetype":"venue"
},
  "geometry": {"coordinates":[9.184191,45.477821],"type":"Point"}
}