{
  "type": "Feature",
  "properties": {
    "iso:country":"IT",
    "sg:address":"30175 Venezia",
    "sg:city":"Venezia",
    "sg:orig_category":"Metalli E Leghe",
    "sg:phone":"+39 041 258 4711",
    "sg:postcode":"30175",
    "sg:province":"Venezia",
    "wof:name":"Ilva Spa",
    "wof:placetype":"venue"
},
  "geometry": {"coordinates":[12.0995635986,45.4514961243],"type":"Point"}
}