{
  "type": "Feature",
  "properties": {
    "addr:full":"Strada Brandizzo 130 10088 Volpiano Volpiano Torino 10088",
    "addr:housenumber":"130",
    "addr:postcode":"10088;10088",
    "addr:street":"Strada Brandizzo",
    "iso:country":"IT",
    "sg:address":"Strada Brandizzo 130 10088 Volpiano",
    "sg:city":"Volpiano",
    "sg:classifiers":[
        {
            "category":"Home & Garden",
            "subcategory":"Carpets & Floor Coverings",
            "type":"Retail Goods"
        }
    ],
    "sg:phone":"+39 011 982 8519",
    "sg:postcode":"10088",
    "sg:province":"Torino",
    "sg:tags":[
        "aluminium",
        "foil"
    ],
    "sg:website":"www.saiag.com",
    "wof:name":"Comital Spa",
    "wof:placetype":"venue"
},
  "geometry": {"coordinates":[7.813622,45.174004],"type":"Point"}
}