{
  "type": "Feature",
  "properties": {
    "addr:full":"75, Via Fermi Enrico 21042 Caronno Pertusella Caronno Pertusella Varese 21042",
    "addr:postcode":"21042;pertusella;21042",
    "addr:street":"Via Fermi Enrico;Pertusella",
    "iso:country":"IT",
    "sg:address":"75, Via Fermi Enrico 21042 Caronno Pertusella",
    "sg:city":"Caronno Pertusella",
    "sg:classifiers":[
        {
            "category":"Manufacturing",
            "subcategory":"Metals",
            "type":"Manufacturing & Wholesale Goods"
        }
    ],
    "sg:phone":"+39 39029639951",
    "sg:postcode":"21042",
    "sg:province":"Varese",
    "sg:tags":[
        "processing"
    ],
    "wof:name":"Pangborn Europe S.p.a.",
    "wof:placetype":"venue"
},
  "geometry": {"coordinates":[8.8263845444,45.8176040649],"type":"Point"}
}