{
  "type": "Feature",
  "properties": {
    "iso:country":"IT",
    "sg:address":"25124 Brescia",
    "sg:city":"Brescia",
    "sg:orig_category":"Arredo Cucina Ed Elettrodomestici. Elettrodomestici",
    "sg:phone":"+39 030 221718",
    "sg:postcode":"25124",
    "sg:province":"Brescia",
    "sg:website":"http://www.cmcolombini.it",
    "wof:name":"C.m. Di Colombini E C. Snc",
    "wof:placetype":"venue"
},
  "geometry": {"coordinates":[10.224299,45.523781],"type":"Point"}
}