{
  "type": "Feature",
  "properties": {
    "addr:full":"20154 Milano Milano Milano 20154",
    "addr:postcode":"20154;20154",
    "iso:country":"IT",
    "sg:address":"20154 Milano",
    "sg:city":"Milano",
    "sg:orig_category":"Studi E Consulenze Tecniche E Industriali. Assicurazioni E Servizi Assicurativi. Consulenze Tecniche, Amministrative E Perizie",
    "sg:phone":"+39 02 6269 0191",
    "sg:postcode":"20154",
    "sg:province":"Milano",
    "wof:name":"Contec Di Guido Cennamo",
    "wof:placetype":"venue"
},
  "geometry": {"coordinates":[9.175912,45.485226],"type":"Point"}
}