{
  "type": "Feature",
  "properties": {
    "iso:country":"IT",
    "sg:address":"81049 Mignano Monte Lungo",
    "sg:city":"Mignano Monte Lungo",
    "sg:orig_category":"Macchine Ed Impianti Per Edilizia E Lavori Pubblici",
    "sg:phone":"+39 0823 904332",
    "sg:postcode":"81049",
    "sg:province":"Caserta",
    "wof:name":"M.c. Group Molise Conglomerati S.p.a.",
    "wof:placetype":"venue"
},
  "geometry": {"coordinates":[13.985638,41.410183],"type":"Point"}
}