{
  "type": "Feature",
  "properties": {
    "iso:country":"IT",
    "sg:address":"41100 Modena",
    "sg:city":"Modena",
    "sg:orig_category":"Fotoriproduttori E Fotocopiatrici",
    "sg:phone":"+39 059 394677",
    "sg:postcode":"41100",
    "sg:province":"Modena",
    "sg:website":"http://www.teletelsrl.it",
    "wof:name":"Teletel Srl",
    "wof:placetype":"venue"
},
  "geometry": {"coordinates":[10.9254322052,44.6308326721],"type":"Point"}
}