{
  "type": "Feature",
  "properties": {
    "iso:country":"IT",
    "sg:address":"25, Via Navicello 38068 Rovereto",
    "sg:city":"Rovereto",
    "sg:classifiers":[
        {
            "category":"Manufacturing",
            "subcategory":"Metals",
            "type":"Manufacturing & Wholesale Goods"
        }
    ],
    "sg:phone":"+39 0464 439484",
    "sg:postcode":"38068",
    "sg:province":"Trento",
    "sg:tags":[
        "metallurgy",
        "metalworking"
    ],
    "wof:name":"Profilerie Trentine S.p.a.",
    "wof:placetype":"venue"
},
  "geometry": {"coordinates":[11.0209245682,45.8755950928],"type":"Point"}
}