{
  "type": "Feature",
  "properties": {
    "addr:full":"10043 Orbassano Orbassano Torino 10043",
    "addr:postcode":"10043;10043",
    "iso:country":"IT",
    "sg:address":"10043 Orbassano",
    "sg:city":"Orbassano",
    "sg:orig_category":"Legname Da Lavoro",
    "sg:phone":"+39 011 900 7411",
    "sg:postcode":"10043",
    "sg:province":"Torino",
    "sg:website":"http://www.guercio-forma.com",
    "wof:name":"Guercio Spa",
    "wof:placetype":"venue"
},
  "geometry": {"coordinates":[7.584508,45.027153],"type":"Point"}
}