{
  "type": "Feature",
  "properties": {
    "iso:country":"IT",
    "sg:address":"70052 Bisceglie",
    "sg:city":"Bisceglie",
    "sg:orig_category":"Articoli Medico-sanitari Ed Ortopedici. Impianti, Attrezzature E Forniture Sanitarie Ed Ospedaliere",
    "sg:phone":"+39 080 395 8030",
    "sg:postcode":"70052",
    "sg:province":"Bari",
    "sg:website":"http://www.connection.it/ortopediadecicco",
    "wof:name":"Ortopedia De Cicco Snc",
    "wof:placetype":"venue"
},
  "geometry": {"coordinates":[16.499325,41.238216],"type":"Point"}
}