{
  "type": "Feature",
  "properties": {
    "iso:country":"IT",
    "sg:address":"55035 Piazza Al Serchio",
    "sg:city":"Piazza al Serchio",
    "sg:orig_category":"Marmo Ed Affini - Commercio",
    "sg:phone":"+39 0583 605700",
    "sg:postcode":"55035",
    "sg:province":"Lucca",
    "sg:website":"http://www.semap.it",
    "wof:name":"Se.ma.p. Spa",
    "wof:placetype":"venue"
},
  "geometry": {"coordinates":[10.293669,44.188915],"type":"Point"}
}