{
  "type": "Feature",
  "properties": {
    "iso:country":"IT",
    "sg:address":"859, Via Emilia Est 41100 Modena",
    "sg:city":"Modena",
    "sg:classifiers":[
        {
            "category":"Bars & Pubs",
            "subcategory":"Nightclub",
            "type":"Food & Drink"
        }
    ],
    "sg:phone":"+39 39059360320",
    "sg:postcode":"41100",
    "sg:province":"Modena",
    "sg:tags":[
        "cake",
        "bread"
    ],
    "wof:name":"Pasticceria Emiliana",
    "wof:placetype":"venue"
},
  "geometry": {"coordinates":[10.936594,44.641979],"type":"Point"}
}