{
  "type": "Feature",
  "properties": {
    "addr:full":"95124 Catania Catania Catania 95124",
    "addr:postcode":"95124;95124",
    "iso:country":"IT",
    "sg:address":"95124 Catania",
    "sg:city":"Catania",
    "sg:orig_category":"Pubblica Amministrazione",
    "sg:phone":"+39 095 715 9310",
    "sg:postcode":"95124",
    "sg:province":"Catania",
    "wof:name":"Ufficio Speciale Forestale",
    "wof:placetype":"venue"
},
  "geometry": {"coordinates":[15.0768289566,37.5118865967],"type":"Point"}
}