{
  "type": "Feature",
  "properties": {
    "addr:full":"39100 Bolzano Bolzano Bolzano/Bozen 39100",
    "addr:postcode":"39100;39100",
    "iso:country":"IT",
    "sg:address":"39100 Bolzano",
    "sg:city":"Bolzano",
    "sg:orig_category":"Servizi E Lavori Per Ecologia E Smaltimento Rifiuti. Termotecnica E Riscaldamento, Apparecchiature E Servizi. Servizi Ausiliari Di Sorveglianza, Manutenzione E Pulizia",
    "sg:phone":"+39 0471 271839",
    "sg:postcode":"39100",
    "sg:province":"Bolzano/Bozen",
    "wof:name":"Hofst\u00c4tter Morandel E.",
    "wof:placetype":"venue"
},
  "geometry": {"coordinates":[11.347113,46.495247],"type":"Point"}
}