{
  "type": "Feature",
  "properties": {
    "iso:country":"IT",
    "sg:address":"Piazza Verdi 1; Verolavecchia; 25029",
    "sg:city":"Verolavecchia",
    "sg:classifiers":[
        {
            "category":"Banks & Credit Unions",
            "subcategory":"Bank",
            "type":"Services"
        }
    ],
    "sg:phone":"+39 030 992 0850",
    "sg:postcode":"25029",
    "sg:province":"Brescia",
    "wof:name":"Credito Bergamasco Spa",
    "wof:placetype":"venue"
},
  "geometry": {"coordinates":[10.079296,45.327499],"type":"Point"}
}