{
  "type": "Feature",
  "properties": {
    "addr:full":"Strada San Donato 21/a 43027 San Prospero Parmense PR",
    "addr:housenumber":"21 / a",
    "addr:postcode":"43027",
    "addr:street":"Strada San Donato",
    "iso:country":"IT",
    "sg:address":"Strada San Donato 21/a 43027 San Prospero Parmense",
    "sg:classifiers":[
        {
            "category":"Transit Center",
            "subcategory":"Freight",
            "type":"Transportation"
        }
    ],
    "sg:phone":"+39 0521 644311",
    "sg:province":"PR",
    "sg:tags":[
        "food"
    ],
    "sg:website":"www.tfeda.it",
    "wof:name":"T.f.e.d.a. Spa - Trasporti Frigoriferi Europei Derrate Alimentari",
    "wof:placetype":"venue"
},
  "geometry": {"coordinates":[10.4001703262,44.7781791687],"type":"Point"}
}