{
  "type": "Feature",
  "properties": {
    "addr:full":"Via Maniago 57 33080 San Quirino San Quirino Pordenone 33080",
    "addr:housenumber":"57",
    "addr:postcode":"33080;33080",
    "addr:street":"Via Maniago;Quirino San Quirino",
    "iso:country":"IT",
    "sg:address":"Via Maniago 57 33080 San Quirino",
    "sg:city":"San Quirino",
    "sg:classifiers":[
        {
            "category":"Manufacturing",
            "subcategory":"Rubber & Plastics",
            "type":"Manufacturing & Wholesale Goods"
        }
    ],
    "sg:phone":"+39 0434 916311",
    "sg:postcode":"33080",
    "sg:province":"Pordenone",
    "sg:tags":[
        "item",
        "household",
        "made"
    ],
    "sg:website":"www.microstamp.com",
    "wof:name":"Microstamp Srl",
    "wof:placetype":"venue"
},
  "geometry": {"coordinates":[12.652166,46.023624],"type":"Point"}
}