{
  "type": "Feature",
  "properties": {
    "iso:country":"IT",
    "sg:address":"20092 Cinisello Balsamo",
    "sg:city":"Cinisello Balsamo",
    "sg:orig_category":"Materiali E Componenti Elettrotecnici",
    "sg:phone":"+39 02 660 0696",
    "sg:postcode":"20092",
    "sg:province":"Milano",
    "wof:name":"Riva Giuseppe",
    "wof:placetype":"venue"
},
  "geometry": {"coordinates":[9.211022,45.550133],"type":"Point"}
}