{
  "type": "Feature",
  "properties": {
    "iso:country":"IT",
    "sg:address":"20086 Motta Visconti",
    "sg:city":"Motta Visconti",
    "sg:orig_category":"Forniture Per Attivita' Industriali",
    "sg:phone":"+39 02 9000 1124",
    "sg:postcode":"20086",
    "sg:province":"Milano",
    "wof:name":"Aiello Epifanio",
    "wof:placetype":"venue"
},
  "geometry": {"coordinates":[9.0295982361,45.2598495483],"type":"Point"}
}