{
  "type": "Feature",
  "properties": {
    "iso:country":"IT",
    "sg:address":"22079 Villa Guardia",
    "sg:city":"Villa Guardia",
    "sg:orig_category":"Fotoincisioni",
    "sg:phone":"+39 031 563366",
    "sg:postcode":"22079",
    "sg:province":"Como",
    "wof:name":"F. 40 Srl",
    "wof:placetype":"venue"
},
  "geometry": {"coordinates":[9.0194530487,45.7716674805],"type":"Point"}
}