{
  "type": "Feature",
  "properties": {
    "iso:country":"IT",
    "sg:address":"Via Galliani 66 Bis 21020 Casale Litta",
    "sg:city":"Casale Litta",
    "sg:classifiers":[
        {
            "category":"Manufacturing",
            "subcategory":"Chemicals & Compounds",
            "type":"Manufacturing & Wholesale Goods"
        }
    ],
    "sg:phone":"+39 0332 945488",
    "sg:postcode":"21020",
    "sg:province":"Varese",
    "sg:tags":[
        "tpe",
        "elastomer",
        "thermoplastic"
    ],
    "sg:website":"www.compotec.it",
    "wof:name":"Compotec Spa",
    "wof:placetype":"venue"
},
  "geometry": {"coordinates":[8.826385,45.817604],"type":"Point"}
}