{
  "type": "Feature",
  "properties": {
    "addr:full":"55012 Capannori Capannori Lucca 55012",
    "addr:postcode":"55012;55012",
    "iso:country":"IT",
    "sg:address":"55012 Capannori",
    "sg:city":"Capannori",
    "sg:orig_category":"Carta, Cartone E Prodotti Primari",
    "sg:phone":"+39 0583 429469",
    "sg:postcode":"55012",
    "sg:province":"Lucca",
    "wof:name":"Re.ca.l. Sas",
    "wof:placetype":"venue"
},
  "geometry": {"coordinates":[10.568039,43.85548],"type":"Point"}
}