{
  "type": "Feature",
  "properties": {
    "addr:full":"33, Via G. Mazzini 46029 Rivarolo Mantovano Riva Mantova 46029",
    "addr:postcode":"46029;46029",
    "addr:street":"Via G.;Riva Mantova",
    "iso:country":"IT",
    "sg:address":"33, Via G. Mazzini 46029 Rivarolo Mantovano",
    "sg:city":"Riva",
    "sg:classifiers":[
        {
            "category":"Banks & Credit Unions",
            "subcategory":"Bank",
            "type":"Services"
        }
    ],
    "sg:phone":"+39 39037699581",
    "sg:postcode":"46029",
    "sg:province":"Mantova",
    "sg:tags":[
        "banking",
        "institution"
    ],
    "wof:name":"Cassa Rurale Ed Artigiana Di Rivarolo Mantovano",
    "wof:placetype":"venue"
},
  "geometry": {"coordinates":[10.797698,45.160366],"type":"Point"}
}