{
  "type": "Feature",
  "properties": {
    "addr:full":"26022 Castelverde Castelverde Cremona 26022",
    "addr:housenumber":"26022",
    "addr:postcode":"26022",
    "addr:street":"Castelverde",
    "iso:country":"IT",
    "sg:address":"26022 Castelverde",
    "sg:city":"Castelverde",
    "sg:orig_category":"Strumenti Per Misura, Controllo E Regolazione",
    "sg:phone":"+39 0372 429290",
    "sg:postcode":"26022",
    "sg:province":"Cremona",
    "wof:name":"Tecsas Snc",
    "wof:placetype":"venue"
},
  "geometry": {"coordinates":[9.994499,45.197453],"type":"Point"}
}