{
  "type": "Feature",
  "properties": {
    "addr:full":"15020 Mombello Monferrato Mombello Monferrato Alessandria 15020",
    "addr:postcode":"15020;15020",
    "iso:country":"IT",
    "sg:address":"15020 Mombello Monferrato",
    "sg:city":"Mombello Monferrato",
    "sg:orig_category":"Servizi E Lavori Per Arredamento E Industria Del Legno. Vetro: Prodotti E Lavorazioni",
    "sg:phone":"+39 0142 944686",
    "sg:postcode":"15020",
    "sg:province":"Alessandria",
    "wof:name":"Zuanne",
    "wof:placetype":"venue"
},
  "geometry": {"coordinates":[8.251408,45.133926],"type":"Point"}
}