{
  "type": "Feature",
  "properties": {
    "iso:country":"IT",
    "sg:address":"24040 Zingonia",
    "sg:city":"Zingonia",
    "sg:orig_category":"Motori Ed Organi Di Trasmissione. Ricambi E Componenti Dei Mezzi Di Trasporto",
    "sg:phone":"+39 035 884471",
    "sg:postcode":"24040",
    "sg:province":"Bergamo",
    "wof:name":"M.r.a.",
    "wof:placetype":"venue"
},
  "geometry": {"coordinates":[9.5626220703,45.5850639343],"type":"Point"}
}