{
  "type": "Feature",
  "properties": {
    "iso:country":"IT",
    "sg:address":"50041 Calenzano",
    "sg:city":"Calenzano",
    "sg:orig_category":"Tessuti E Stoffe. Forniture Per Attivita' Industriali",
    "sg:phone":"+39 055 882 6665",
    "sg:postcode":"50041",
    "sg:province":"Firenze",
    "wof:name":"Marco Agency Di Cardoso Lynes Marco",
    "wof:placetype":"venue"
},
  "geometry": {"coordinates":[11.148009,43.854671],"type":"Point"}
}