{
  "type": "Feature",
  "properties": {
    "iso:country":"IT",
    "sg:address":"16149 Genova",
    "sg:city":"Genova",
    "sg:orig_category":"Studi E Consulenze Tecniche E Industriali. Consulenze Tecniche, Amministrative E Perizie. Servizi Ausiliari Di Analisi, Controllo E Ricerca",
    "sg:phone":"+39 010 469731",
    "sg:postcode":"16149",
    "sg:province":"Genova",
    "sg:website":"http://www.interprogetti.it",
    "wof:name":"Interprogetti Genova Srl",
    "wof:placetype":"venue"
},
  "geometry": {"coordinates":[8.900476,44.408707],"type":"Point"}
}