{
  "type": "Feature",
  "properties": {
    "addr:full":"24121 Bergamo Bergamo Bergamo 24121",
    "addr:postcode":"24121;24121",
    "iso:country":"IT",
    "sg:address":"24121 Bergamo",
    "sg:city":"Bergamo",
    "sg:orig_category":"Abbigliamento Esterno, Maglierie E Pelliccerie. Shopping",
    "sg:phone":"+39 035 224142",
    "sg:postcode":"24121",
    "sg:province":"Bergamo",
    "sg:website":"http://www.tizianafausti.com",
    "wof:name":"Tiziana Fausti",
    "wof:placetype":"venue"
},
  "geometry": {"coordinates":[9.6736240387,45.6975479126],"type":"Point"}
}