{
  "type": "Feature",
  "properties": {
    "iso:country":"IT",
    "sg:address":"11, Via Como 21020 Monvalle",
    "sg:city":"Monvalle",
    "sg:classifiers":[
        {
            "category":"Real Estate",
            "subcategory":"Surveying",
            "type":"Services"
        }
    ],
    "sg:phone":"+39 0332 970970",
    "sg:postcode":"21020",
    "sg:province":"Varese",
    "sg:tags":[
        "equipment",
        "material",
        "good",
        "-",
        "handling"
    ],
    "wof:name":"Monte Ferro (s.p.a.)",
    "wof:placetype":"venue"
},
  "geometry": {"coordinates":[8.635526,45.85004],"type":"Point"}
}