{
  "type": "Feature",
  "properties": {
    "addr:full":"24, Via Brendibusio 25050 Niardo Niardo Brescia 25050",
    "addr:postcode":"25050;25050",
    "addr:street":"Via Brendibusio",
    "iso:country":"IT",
    "sg:address":"24, Via Brendibusio 25050 Niardo",
    "sg:city":"Niardo",
    "sg:classifiers":[
        {
            "category":"Autos & Motor Vehicles",
            "subcategory":"Automobile Sales",
            "type":"Retail Goods"
        }
    ],
    "sg:phone":"+39 036 433 5711",
    "sg:postcode":"25050",
    "sg:province":"Brescia",
    "sg:tags":[
        "equipment",
        "transport"
    ],
    "wof:name":"K.l. S.r.l.",
    "wof:placetype":"venue"
},
  "geometry": {"coordinates":[10.323218,45.979263],"type":"Point"}
}