{
  "type": "Feature",
  "properties": {
    "addr:full":"40132 Bologna Bologna Bologna 40132",
    "addr:postcode":"40132;40132",
    "iso:country":"IT",
    "sg:address":"40132 Bologna",
    "sg:city":"Bologna",
    "sg:classifiers":[
        {
            "category":"Utilities",
            "subcategory":"Natural Gas",
            "type":"Services"
        }
    ],
    "sg:phone":"+39 051 647 9680",
    "sg:postcode":"40132",
    "sg:province":"Bologna",
    "sg:tags":[
        "auxiliary",
        "light",
        "vehicles",
        "water",
        "motor",
        "services",
        "tourism",
        "public",
        "transport"
    ],
    "sg:website":"http://www.bologna-airport.it",
    "wof:name":"Aeroporto G. Marconi Spa",
    "wof:placetype":"venue"
},
  "geometry": {"coordinates":[11.296445,44.521103],"type":"Point"}
}