{
  "type": "Feature",
  "properties": {
    "addr:full":"27/e, Via Chiari 25033 Cologne Cologne Brescia 25033",
    "addr:housenumber":"27 / e",
    "addr:postcode":"25033;25033",
    "addr:street":"Via Chiari",
    "iso:country":"IT",
    "sg:address":"27/e, Via Chiari 25033 Cologne",
    "sg:city":"Cologne",
    "sg:classifiers":[
        {
            "category":"Professional",
            "subcategory":"Engineering",
            "type":"Services"
        }
    ],
    "sg:phone":"+39 030 715 6503",
    "sg:postcode":"25033",
    "sg:province":"Brescia",
    "sg:tags":[
        "machine",
        "-",
        "mechanical"
    ],
    "wof:name":"Ser.ma.tes. (s.r.l.)",
    "wof:placetype":"venue"
},
  "geometry": {"coordinates":[9.984098,45.583237],"type":"Point"}
}