{
  "type": "Feature",
  "properties": {
    "iso:country":"IT",
    "sg:address":"80053 Castellammare Di Stabia",
    "sg:city":"Castellammare di Stabia",
    "sg:orig_category":"Servizi Ausiliari Di Certificati, Riproduzioni, Disegni E Foto",
    "sg:phone":"+39 081 871 2209",
    "sg:postcode":"80053",
    "sg:province":"Napoli",
    "wof:name":"Studio Di Consulenza Globale Immobil. Di Rocco Antonio",
    "wof:placetype":"venue"
},
  "geometry": {"coordinates":[14.484029,40.699219],"type":"Point"}
}