{
  "type": "Feature",
  "properties": {
    "addr:full":"42025 Cavriago Reggio Nell'Emilia 42025",
    "addr:postcode":"42025;42025",
    "iso:country":"IT",
    "sg:address":"42025 Cavriago",
    "sg:orig_category":"Prodotti Chimici Di Base",
    "sg:phone":"+39 0522 371818",
    "sg:postcode":"42025",
    "sg:province":"Reggio Nell'Emilia",
    "wof:name":"I.c.r. Industria Chimica Reggiana (s.p.a.)",
    "wof:placetype":"venue"
},
  "geometry": {"coordinates":[10.514582634,44.6969299316],"type":"Point"}
}