{
  "type": "Feature",
  "properties": {
    "addr:full":"34076 Romans D'isonzo Gorizia 34076",
    "addr:postcode":"34076;34076",
    "iso:country":"IT",
    "sg:address":"34076 Romans D'isonzo",
    "sg:classifiers":[
        {
            "category":"Manufacturing",
            "subcategory":"Tobacco Products",
            "type":"Manufacturing & Wholesale Goods"
        }
    ],
    "sg:phone":"+39 0481 908918",
    "sg:postcode":"34076",
    "sg:province":"Gorizia",
    "sg:tags":[
        "activities",
        "supply",
        "commercial",
        "finished",
        "packaging",
        "packing",
        "materials",
        "products",
        "printed",
        "artisan"
    ],
    "wof:name":"B. & P. Italia Srl",
    "wof:placetype":"venue"
},
  "geometry": {"coordinates":[13.4094905853,45.840927124],"type":"Point"}
}