{
  "type": "Feature",
  "properties": {
    "addr:full":"Viale Magna Grecia, 112; Taranto; 74100 Taranto Taranto 74100",
    "addr:housenumber":"112",
    "addr:postcode":"74100;74100",
    "addr:street":"Viale Magna Grecia",
    "iso:country":"IT",
    "sg:address":"Viale Magna Grecia, 112; Taranto; 74100",
    "sg:city":"Taranto",
    "sg:classifiers":[
        {
            "category":"Banks & Credit Unions",
            "subcategory":"Bank",
            "type":"Services"
        }
    ],
    "sg:phone":"+39 099 321123",
    "sg:postcode":"74100",
    "sg:province":"Taranto",
    "wof:name":"Banca Nazionale Del Lavoro",
    "wof:placetype":"venue"
},
  "geometry": {"coordinates":[17.268105,40.460922],"type":"Point"}
}