{
  "type": "Feature",
  "properties": {
    "iso:country":"IT",
    "sg:address":"00195 Roma",
    "sg:city":"Roma",
    "sg:orig_category":"Medici. Assicurazioni E Servizi Assicurativi. Avvocati, Notai E Servizi Legali. Professionisti - Studi E Servizi Ed Associazioni Di Interesse Aziendale",
    "sg:phone":"+39 06 3751 6569",
    "sg:postcode":"00195",
    "sg:province":"Roma",
    "wof:name":"Di Luca Natale Mario",
    "wof:placetype":"venue"
},
  "geometry": {"coordinates":[12.4605703354,41.9205741882],"type":"Point"}
}