{
  "type": "Feature",
  "properties": {
    "iso:country":"IT",
    "sg:address":"212, Via Roma 30030 Salzano",
    "sg:city":"Salzano",
    "sg:classifiers":[
        {
            "category":"Shopping",
            "subcategory":"Computers & Home Electronics",
            "type":"Retail Goods"
        }
    ],
    "sg:phone":"+39 39041437800",
    "sg:postcode":"30030",
    "sg:province":"Venezia",
    "sg:tags":[
        "electronic",
        "electrical",
        "equipment"
    ],
    "wof:name":"Geol Due O (s.r.l.)",
    "wof:placetype":"venue"
},
  "geometry": {"coordinates":[12.162787,45.492279],"type":"Point"}
}