{
  "type": "Feature",
  "properties": {
    "iso:country":"IT",
    "sg:address":"5, Via Noai 32040 Domegge Di Cadore",
    "sg:city":"Domegge di Cadore",
    "sg:classifiers":[
        {
            "category":"Manufacturing",
            "subcategory":"Glass & Minerals",
            "type":"Manufacturing & Wholesale Goods"
        }
    ],
    "sg:phone":"+39 39043572111",
    "sg:postcode":"32040",
    "sg:province":"Belluno",
    "wof:name":"Dalbel (s.r.l.)",
    "wof:placetype":"venue"
},
  "geometry": {"coordinates":[12.399562,46.450603],"type":"Point"}
}