{
  "type": "Feature",
  "properties": {
    "iso:country":"IT",
    "sg:address":"00153 Roma",
    "sg:city":"Roma",
    "sg:classifiers":[
        {
            "category":"Health Services",
            "subcategory":"Health Practitioner",
            "type":"Services"
        }
    ],
    "sg:phone":"+39 06 575 0930",
    "sg:postcode":"00153",
    "sg:province":"Roma",
    "sg:tags":[
        "medici"
    ],
    "wof:name":"Negro Antonio",
    "wof:placetype":"venue"
},
  "geometry": {"coordinates":[12.475320816,41.8819313049],"type":"Point"}
}