{
  "type": "Feature",
  "properties": {
    "iso:country":"IT",
    "sg:address":"05014 Castel Viscardo",
    "sg:city":"Castel Viscardo",
    "sg:orig_category":"Materiali Edili",
    "sg:phone":"+39 0763 361656",
    "sg:postcode":"05014",
    "sg:province":"Terni",
    "wof:name":"Calandrelli Lorenzo",
    "wof:placetype":"venue"
},
  "geometry": {"coordinates":[12.014714,42.763924],"type":"Point"}
}