{
  "type": "Feature",
  "properties": {
    "addr:full":"20131 Milano Milano Milano 20131",
    "addr:postcode":"20131;20131",
    "iso:country":"IT",
    "sg:address":"20131 Milano",
    "sg:city":"Milano",
    "sg:orig_category":"Forniture Per Uffici",
    "sg:phone":"+39 02 261 3308",
    "sg:postcode":"20131",
    "sg:province":"Milano",
    "wof:name":"Invernizzi Antonio",
    "wof:placetype":"venue"
},
  "geometry": {"coordinates":[9.2327251434,45.4879608154],"type":"Point"}
}