{
  "type": "Feature",
  "properties": {
    "addr:full":"20094 Corsico Corsico Milano 20094",
    "addr:postcode":"20094;20094",
    "iso:country":"IT",
    "sg:address":"20094 Corsico",
    "sg:city":"Corsico",
    "sg:orig_category":"Motori Ed Organi Di Trasmissione",
    "sg:phone":"+39 02 440 3428",
    "sg:postcode":"20094",
    "sg:province":"Milano",
    "wof:name":"Turmax Sas Di Maffi Massimo & C.",
    "wof:placetype":"venue"
},
  "geometry": {"coordinates":[9.1134729385,45.431098938],"type":"Point"}
}