{
  "type": "Feature",
  "properties": {
    "addr:full":"00144 Roma Roma Roma 00144",
    "addr:postcode":"00144;00144",
    "iso:country":"IT",
    "sg:address":"00144 Roma",
    "sg:city":"Roma",
    "sg:orig_category":"Servizi E Lavori Per Abbigliamento E Pelletterie",
    "sg:phone":"+39 06 5220 0320",
    "sg:postcode":"00144",
    "sg:province":"Roma",
    "wof:name":"Volpi Eugenia",
    "wof:placetype":"venue"
},
  "geometry": {"coordinates":[12.454614,41.821224],"type":"Point"}
}