{
  "type": "Feature",
  "properties": {
    "iso:country":"IT",
    "sg:address":"35, Via Macchi Mauro 20124 Milano",
    "sg:city":"Milano",
    "sg:classifiers":[
        {
            "category":"Manufacturing",
            "subcategory":"Textiles",
            "type":"Manufacturing & Wholesale Goods"
        }
    ],
    "sg:phone":"+39 39026709006",
    "sg:postcode":"20124",
    "sg:province":"Milano",
    "sg:tags":[
        "leather",
        "raw",
        "material",
        "-"
    ],
    "wof:name":"Italhide S.p.a.",
    "wof:placetype":"venue"
},
  "geometry": {"coordinates":[9.206436,45.483589],"type":"Point"}
}