{
  "type": "Feature",
  "properties": {
    "iso:country":"IT",
    "sg:address":"21019 Somma Lombardo",
    "sg:city":"Somma Lombardo",
    "sg:orig_category":"Tessuti E Stoffe",
    "sg:phone":"+39 0331 259934",
    "sg:postcode":"21019",
    "sg:province":"Varese",
    "sg:website":"http://www.biritrading.com",
    "wof:name":"Biri Trading Snc",
    "wof:placetype":"venue"
},
  "geometry": {"coordinates":[8.708783,45.676949],"type":"Point"}
}