{
  "type": "Feature",
  "properties": {
    "iso:country":"IT",
    "sg:address":"90147 Palermo",
    "sg:city":"Palermo",
    "sg:orig_category":"Abiti Da Lavoro Ed Indumenti Protettivi",
    "sg:phone":"+39 091 691 1480",
    "sg:postcode":"90147",
    "sg:province":"Palermo",
    "wof:name":"Ginova Sud Srl",
    "wof:placetype":"venue"
},
  "geometry": {"coordinates":[13.282984,38.189232],"type":"Point"}
}