{
  "type": "Feature",
  "properties": {
    "addr:full":"14042 Calamandrana Calamandrana Asti 14042",
    "addr:postcode":"14042;14042",
    "iso:country":"IT",
    "sg:address":"14042 Calamandrana",
    "sg:city":"Calamandrana",
    "sg:orig_category":"Bevande, Vini E Liquori. Agricoltura, Orticoltura E Floricoltura",
    "sg:phone":"+39 0141 75547",
    "sg:postcode":"14042",
    "sg:province":"Asti",
    "wof:name":"Barbero Agr. Luigi",
    "wof:placetype":"venue"
},
  "geometry": {"coordinates":[8.322208,44.741047],"type":"Point"}
}