{
  "type": "Feature",
  "properties": {
    "iso:country":"IT",
    "sg:address":"Via Cadriano 2 40057 Granarolo Dell'emilia",
    "sg:classifiers":[
        {
            "category":"Wholesale",
            "subcategory":"Motor Vehicles",
            "type":"Manufacturing & Wholesale Goods"
        }
    ],
    "sg:phone":"+39 051 766512",
    "sg:postcode":"40057",
    "sg:province":"Bologna",
    "sg:tags":[
        "processing",
        "cleaning",
        "agent"
    ],
    "sg:website":"www.campi.net",
    "wof:name":"C.a.m.p.i. Srl",
    "wof:placetype":"venue"
},
  "geometry": {"coordinates":[11.396729,44.543194],"type":"Point"}
}