{
  "type": "Feature",
  "properties": {
    "iso:country":"IT",
    "sg:address":"80143 Napoli",
    "sg:city":"Napoli",
    "sg:orig_category":"Macchine, Impianti Ed Attrezzature Per Abbigliamento E Pelletterie",
    "sg:phone":"+39 081 201916",
    "sg:postcode":"80143",
    "sg:province":"Napoli",
    "wof:name":"Minori Paolo",
    "wof:placetype":"venue"
},
  "geometry": {"coordinates":[14.275235,40.859352],"type":"Point"}
}