{
  "type": "Feature",
  "properties": {
    "iso:country":"IT",
    "sg:address":"16, Via Torricelli Evangelista 31020 Villorba",
    "sg:city":"Villorba",
    "sg:classifiers":[
        {
            "category":"Home & Garden",
            "subcategory":"Home Furnishings",
            "type":"Retail Goods"
        }
    ],
    "sg:phone":"+39 0422 608044",
    "sg:postcode":"31020",
    "sg:province":"Treviso",
    "sg:tags":[
        "household"
    ],
    "wof:name":"Studioline Srl",
    "wof:placetype":"venue"
},
  "geometry": {"coordinates":[12.242072,45.666286],"type":"Point"}
}