{
  "type": "Feature",
  "properties": {
    "iso:country":"IT",
    "sg:address":"Via Degli Alfani 84 50121 Firenze",
    "sg:city":"Firenze",
    "sg:orig_category":"Substances And Auxiliaries For Immunology",
    "sg:phone":"+39 055 293030",
    "sg:postcode":"50121",
    "sg:province":"Firenze",
    "sg:website":"www.anallergo.it",
    "wof:name":"Anallergo Srl",
    "wof:placetype":"venue"
},
  "geometry": {"coordinates":[11.258142,43.776413],"type":"Point"}
}