{
  "type": "Feature",
  "properties": {
    "iso:country":"IT",
    "sg:address":"20156 Milano",
    "sg:city":"Milano",
    "sg:orig_category":"Discoteche, Locali Notturni E Sale Da Ballo",
    "sg:phone":"+39 02 308 6076",
    "sg:postcode":"20156",
    "sg:province":"Milano",
    "sg:website":"http://www.madisonmusichall.it",
    "wof:name":"Tron Srl",
    "wof:placetype":"venue"
},
  "geometry": {"coordinates":[9.134976,45.502777],"type":"Point"}
}