{
  "type": "Feature",
  "properties": {
    "iso:country":"IT",
    "sg:address":"Corso Umberto I 52/b, 70058 Spinazzola, Ba",
    "sg:city":"Spinazzola",
    "sg:classifiers":[
        {
            "category":"Banks & Credit Unions",
            "subcategory":"Bank",
            "type":"Services"
        }
    ],
    "sg:postcode":"70058",
    "sg:province":"Bari",
    "wof:name":"Banca Di Credito Cooperativo Di Spinazzola (bari) Scrl",
    "wof:placetype":"venue"
},
  "geometry": {"coordinates":[16.869291,41.126053],"type":"Point"}
}