{
  "type": "Feature",
  "properties": {
    "addr:full":"26836 Montanaso Lombardo Montanaso Lombardo Lodi 26836",
    "addr:postcode":"26836;26836",
    "addr:street":"Lombardo",
    "iso:country":"IT",
    "sg:address":"26836 Montanaso Lombardo",
    "sg:city":"Montanaso Lombardo",
    "sg:orig_category":"Macchine, Impianti Ed Attrezzature Per Industria Alimentare E Bevande",
    "sg:phone":"+39 0371 68793",
    "sg:postcode":"26836",
    "sg:province":"Lodi",
    "wof:name":"Sordi S.p.a.",
    "wof:placetype":"venue"
},
  "geometry": {"coordinates":[9.453686,45.335106],"type":"Point"}
}