{
  "type": "Feature",
  "properties": {
    "iso:country":"IT",
    "sg:address":"39, Via Marchesane 36061 Bassano Del Grappa",
    "sg:city":"Bassano del Grappa",
    "sg:classifiers":[
        {
            "category":"Home & Garden",
            "subcategory":"Home Furnishings",
            "type":"Retail Goods"
        }
    ],
    "sg:phone":"+39 0424 502058",
    "sg:postcode":"36061",
    "sg:province":"Vicenza",
    "sg:tags":[
        "household"
    ],
    "wof:name":"Maroso S.n.c. Di Maroso Alessandra & C.",
    "wof:placetype":"venue"
},
  "geometry": {"coordinates":[11.703251,45.756363],"type":"Point"}
}