{
  "type": "Feature",
  "properties": {
    "addr:full":"31015 Conegliano Conegliano Treviso 31015",
    "addr:postcode":"31015;31015",
    "iso:country":"IT",
    "sg:address":"31015 Conegliano",
    "sg:city":"Conegliano",
    "sg:orig_category":"Apparecchiature E Sistemi Per Magazzinaggio E Movimentazione",
    "sg:phone":"+39 0438 451284",
    "sg:postcode":"31015",
    "sg:province":"Treviso",
    "wof:name":"Movint M.b. Di Masut A. & C.",
    "wof:placetype":"venue"
},
  "geometry": {"coordinates":[12.27992,45.87257],"type":"Point"}
}