{
  "type": "Feature",
  "properties": {
    "iso:country":"IT",
    "sg:address":"11, V. Roma 23829 Varenna",
    "sg:city":"Varenna",
    "sg:classifiers":[
        {
            "category":"Professional",
            "subcategory":"Engineering",
            "type":"Services"
        }
    ],
    "sg:phone":"+39 0341 815301",
    "sg:postcode":"23829",
    "sg:province":"Lecco",
    "sg:tags":[
        "machine",
        "-",
        "mechanical"
    ],
    "sg:website":"http://www.paginegialle.it/eremogaudio",
    "wof:name":"Albergo Eremo Gaudio",
    "wof:placetype":"venue"
},
  "geometry": {"coordinates":[9.301891,45.949635],"type":"Point"}
}