{
  "type": "Feature",
  "properties": {
    "iso:country":"IT",
    "sg:address":"00165 Roma",
    "sg:city":"Roma",
    "sg:orig_category":"Servizi E Lavori Per Abbigliamento E Pelletterie",
    "sg:phone":"+39 06 662 3152",
    "sg:postcode":"00165",
    "sg:province":"Roma",
    "wof:name":"Green Point S.r.l.",
    "wof:placetype":"venue"
},
  "geometry": {"coordinates":[12.428203,41.899918],"type":"Point"}
}