{
  "type": "Feature",
  "properties": {
    "addr:full":"20092 Cinisello Balsamo Cinisello Balsamo Milano 20092",
    "addr:postcode":"20092;20092",
    "iso:country":"IT",
    "sg:address":"20092 Cinisello Balsamo",
    "sg:city":"Cinisello Balsamo",
    "sg:orig_category":"Apparecchiature E Sistemi Per Magazzinaggio E Movimentazione. Macchine E Impianti Per Attivita' Commerciali Ed Artigianali. Macchine, Strumenti Ed Apparecchi Per Attivita' Industriali",
    "sg:phone":"+39 02 6129 0138",
    "sg:postcode":"20092",
    "sg:province":"Milano",
    "wof:name":"Co.ri.ma. Pese (s.n.c.)",
    "wof:placetype":"venue"
},
  "geometry": {"coordinates":[9.228735,45.556789],"type":"Point"}
}