{
  "type": "Feature",
  "properties": {
    "addr:full":"Via Spine 15; Oderzo; 31046 Oderzo Treviso 31046",
    "addr:housenumber":"15",
    "addr:postcode":"31046;31046",
    "addr:street":"Via Spine",
    "iso:country":"IT",
    "sg:address":"Via Spine 15; Oderzo; 31046",
    "sg:city":"Oderzo",
    "sg:classifiers":[
        {
            "category":"Banks & Credit Unions",
            "subcategory":"Bank",
            "type":"Services"
        }
    ],
    "sg:phone":"+39 0422 815277",
    "sg:postcode":"31046",
    "sg:province":"Treviso",
    "wof:name":"Banca Nazionale Del Lavoro Spa",
    "wof:placetype":"venue"
},
  "geometry": {"coordinates":[12.496511,45.780293],"type":"Point"}
}