{
  "type": "Feature",
  "properties": {
    "iso:country":"IT",
    "sg:address":"V.le Umbria 11 20089 Rozzano",
    "sg:city":"Rozzano",
    "sg:classifiers":[
        {
            "category":"Home & Garden",
            "subcategory":"Carpets & Floor Coverings",
            "type":"Retail Goods"
        }
    ],
    "sg:phone":"+39 02 5750 6447",
    "sg:postcode":"20089",
    "sg:province":"Milano",
    "sg:tags":[
        "suction-scrubbing",
        "industrial",
        "single-disc",
        "machine",
        "mac",
        "cleaning",
        "wet",
        "polishing",
        "scrubbers",
        "automatic",
        "machines"
    ],
    "sg:website":"www.leoncini.it",
    "wof:name":"Leoncini Motorscop Srl",
    "wof:placetype":"venue"
},
  "geometry": {"coordinates":[9.1504764557,45.3835906982],"type":"Point"}
}