{
  "type": "Feature",
  "properties": {
    "addr:full":"60027 Osimo Osimo Ancona 60027",
    "addr:postcode":"60027;60027",
    "iso:country":"IT",
    "sg:address":"60027 Osimo",
    "sg:city":"Osimo",
    "sg:orig_category":"Motori Ed Organi Di Trasmissione",
    "sg:phone":"+39 071 715693",
    "sg:postcode":"60027",
    "sg:province":"Ancona",
    "wof:name":"Saito Srl",
    "wof:placetype":"venue"
},
  "geometry": {"coordinates":[13.5007562637,43.4953536987],"type":"Point"}
}