{
  "type": "Feature",
  "properties": {
    "addr:full":"24040 Ciserano Ciserano Bergamo 24040",
    "addr:postcode":"24040;24040",
    "iso:country":"IT",
    "sg:address":"24040 Ciserano",
    "sg:city":"Ciserano",
    "sg:orig_category":"Vernici Protettive Speciali",
    "sg:phone":"+39 035 885101",
    "sg:postcode":"24040",
    "sg:province":"Bergamo",
    "wof:name":"Italiana Resine Snc",
    "wof:placetype":"venue"
},
  "geometry": {"coordinates":[9.603433,45.59409],"type":"Point"}
}