{
  "type": "Feature",
  "properties": {
    "addr:full":"42015 Correggio Reggio Nell'Emilia 42015",
    "addr:postcode":"42015;42015",
    "iso:country":"IT",
    "sg:address":"42015 Correggio",
    "sg:orig_category":"Abbigliamento Industria - Forniture Ed Accessori",
    "sg:phone":"+39 0522 637783",
    "sg:postcode":"42015",
    "sg:province":"Reggio Nell'Emilia",
    "wof:name":"Davolio Giuseppe",
    "wof:placetype":"venue"
},
  "geometry": {"coordinates":[10.62106,44.705463],"type":"Point"}
}