{
  "type": "Feature",
  "properties": {
    "addr:full":"20015 Parabiago Parabiago Milano 20015",
    "addr:postcode":"20015;20015",
    "iso:country":"IT",
    "sg:address":"20015 Parabiago",
    "sg:city":"Parabiago",
    "sg:orig_category":"Elettrotecnica Industriale, Prodotti E Apparecchiature",
    "sg:phone":"+39 0331 552269",
    "sg:postcode":"20015",
    "sg:province":"Milano",
    "wof:name":"Grimi Ferruccio",
    "wof:placetype":"venue"
},
  "geometry": {"coordinates":[8.941732,45.544281],"type":"Point"}
}