{
  "type": "Feature",
  "properties": {
    "addr:full":"16010 Savignone Isorelle Genova 16010",
    "addr:postcode":"16010;16010",
    "iso:country":"IT",
    "sg:address":"16010 Savignone",
    "sg:city":"Isorelle",
    "sg:orig_category":"Prodotti Alimentari",
    "sg:phone":"+39 010 964 2474",
    "sg:postcode":"16010",
    "sg:province":"Genova",
    "wof:name":"Gelomarkets",
    "wof:placetype":"venue"
},
  "geometry": {"coordinates":[8.9640130997,44.5661582947],"type":"Point"}
}