{
  "type": "Feature",
  "properties": {
    "addr:full":"1309, Via Vecchia Porto 63019 Sant'elpidio A Mare Ascoli Piceno 63019",
    "addr:housenumber":"1309",
    "addr:postcode":"63019;63019",
    "addr:street":"Via Vecchia Porto",
    "iso:country":"IT",
    "sg:address":"1309, Via Vecchia Porto 63019 Sant'elpidio A Mare",
    "sg:classifiers":[
        {
            "category":"Personal",
            "subcategory":"Shoe Repair & Shine",
            "type":"Services"
        }
    ],
    "sg:phone":"+39 0734 810360",
    "sg:postcode":"63019",
    "sg:province":"Ascoli Piceno",
    "sg:tags":[
        "leather"
    ],
    "wof:name":"Calzaturificio Zafan S.r.l.",
    "wof:placetype":"venue"
},
  "geometry": {"coordinates":[13.713368,43.233288],"type":"Point"}
}