{
  "type": "Feature",
  "properties": {
    "addr:full":"19038 Sarzana Sarzana La Spezia 19038",
    "addr:postcode":"19038;19038",
    "iso:country":"IT",
    "sg:address":"19038 Sarzana",
    "sg:city":"Sarzana",
    "sg:classifiers":[
        {
            "category":"Professional",
            "type":"Services"
        }
    ],
    "sg:phone":"+39 0187 691219",
    "sg:postcode":"19038",
    "sg:province":"La Spezia",
    "sg:tags":[
        "activities",
        "supply",
        "commercial",
        "artisan",
        "supplies",
        "accommodation"
    ],
    "wof:name":"Samas - Santa Maria Srl",
    "wof:placetype":"venue"
},
  "geometry": {"coordinates":[9.971735,44.102196],"type":"Point"}
}