{
  "type": "Feature",
  "properties": {
    "iso:country":"IT",
    "sg:address":"Via Emilia 28 43010 Ponte Taro",
    "sg:city":"Ponte Taro",
    "sg:classifiers":[
        {
            "category":"Landmark",
            "subcategory":"Unesco World Heritage Site",
            "type":"Public Place"
        }
    ],
    "sg:phone":"+39 0521 619142",
    "sg:postcode":"43010",
    "sg:province":"Parma",
    "sg:tags":[
        "rolled",
        "boring",
        "section",
        "cutting",
        "line"
    ],
    "wof:name":"Giuliano Saj - Cutter Impresa Individuale",
    "wof:placetype":"venue"
},
  "geometry": {"coordinates":[10.205507,44.826565],"type":"Point"}
}