{
  "type": "Feature",
  "properties": {
    "iso:country":"IT",
    "sg:address":"62018 Potenza Picena",
    "sg:city":"Potenza Picena",
    "sg:orig_category":"Forniture Per Attivita' Industriali",
    "sg:phone":"+39 0733 672561",
    "sg:postcode":"62018",
    "sg:province":"Macerata",
    "wof:name":"Savoretti Armando & C. (s.n.c.)",
    "wof:placetype":"venue"
},
  "geometry": {"coordinates":[13.6478481293,43.3617668152],"type":"Point"}
}