{
  "type": "Feature",
  "properties": {
    "iso:country":"IT",
    "sg:address":"87028 Praia A Mare",
    "sg:city":"Praia a Mare",
    "sg:orig_category":"Apparecchiature E Sistemi Per Magazzinaggio E Movimentazione. Macchine E Impianti Per Attivita' Commerciali Ed Artigianali. Macchine, Strumenti Ed Apparecchi Per Attivita' Industriali",
    "sg:phone":"+39 0985 72081",
    "sg:postcode":"87028",
    "sg:province":"Cosenza",
    "wof:name":"Italo Serio",
    "wof:placetype":"venue"
},
  "geometry": {"coordinates":[15.780662,39.895134],"type":"Point"}
}