{
  "type": "Feature",
  "properties": {
    "addr:full":"2, V. Tavigliana 37023 Grezzana Grezzana Verona 37023",
    "addr:housenumber":"2",
    "addr:postcode":"37023;37023",
    "addr:street":"Tavigliana",
    "iso:country":"IT",
    "sg:address":"2, V. Tavigliana 37023 Grezzana",
    "sg:city":"Grezzana",
    "sg:classifiers":[
        {
            "category":"Professional",
            "subcategory":"Engineering",
            "type":"Services"
        }
    ],
    "sg:phone":"+39 045 865 0303",
    "sg:postcode":"37023",
    "sg:province":"Verona",
    "sg:tags":[
        "machine",
        "-",
        "mechanical"
    ],
    "sg:website":"http://www.bombieriventuri.it:ws_end: :mark:ws:http://www.paginegialle.it/bv",
    "wof:name":"Bombieri & Venturi Spa",
    "wof:placetype":"venue"
},
  "geometry": {"coordinates":[11.011543,45.529961],"type":"Point"}
}