{
  "type": "Feature",
  "properties": {
    "iso:country":"IT",
    "sg:address":"Loc Sorino 38083 Condino",
    "sg:city":"Condino",
    "sg:classifiers":[
        {
            "category":"Building & Trades",
            "subcategory":"Construction",
            "type":"Services"
        }
    ],
    "sg:phone":"+39 0465 621215",
    "sg:postcode":"38083",
    "sg:province":"Trento",
    "sg:tags":[
        "industrial",
        "timber"
    ],
    "sg:website":"www.sorino.it",
    "wof:name":"Sorino S.r.l.",
    "wof:placetype":"venue"
},
  "geometry": {"coordinates":[11.119053,46.066738],"type":"Point"}
}