{
  "type": "Feature",
  "properties": {
    "iso:country":"IT",
    "sg:address":"33170 Pordenone",
    "sg:city":"Pordenone",
    "sg:orig_category":"Non-classified Establishments",
    "sg:phone":"+39 0434 520310",
    "sg:postcode":"33170",
    "sg:province":"Pordenone",
    "wof:name":"Giovanetti Snc",
    "wof:placetype":"venue"
},
  "geometry": {"coordinates":[12.572839,45.867706],"type":"Point"}
}