{
  "type": "Feature",
  "properties": {
    "iso:country":"IT",
    "sg:address":"10023 Chieri",
    "sg:city":"Chieri",
    "sg:orig_category":"Cartotecnica",
    "sg:phone":"+39 011 943 6674",
    "sg:postcode":"10023",
    "sg:province":"Torino",
    "wof:name":"Bosco & Persico Snc",
    "wof:placetype":"venue"
},
  "geometry": {"coordinates":[7.83915,44.978943],"type":"Point"}
}