{
  "type": "Feature",
  "properties": {
    "addr:full":"20, Via Camol 33070 Brugnera Brugnera Pordenone 33070",
    "addr:postcode":"33070;33070",
    "addr:street":"Via Camol",
    "iso:country":"IT",
    "sg:address":"20, Via Camol 33070 Brugnera",
    "sg:city":"Brugnera",
    "sg:classifiers":[
        {
            "category":"Home & Garden",
            "subcategory":"Home Furnishings",
            "type":"Retail Goods"
        }
    ],
    "sg:phone":"+39 0434 627860",
    "sg:postcode":"33070",
    "sg:province":"Pordenone",
    "sg:tags":[
        "household"
    ],
    "wof:name":"Tecnoarredolegno S.r.l.",
    "wof:placetype":"venue"
},
  "geometry": {"coordinates":[12.527328,45.909023],"type":"Point"}
}