{
  "type": "Feature",
  "properties": {
    "iso:country":"IT",
    "sg:address":"66020 San Giovanni Teatino",
    "sg:city":"Sambuceto",
    "sg:orig_category":"Non-classified Establishments",
    "sg:phone":"+39 085 446 0664",
    "sg:postcode":"66020",
    "sg:province":"Chieti",
    "wof:name":"Esedra Srl - Abruzzo Tenda",
    "wof:placetype":"venue"
},
  "geometry": {"coordinates":[14.173164,42.418186],"type":"Point"}
}