{
  "type": "Feature",
  "properties": {
    "iso:country":"IT",
    "sg:address":"00184 Roma",
    "sg:city":"Roma",
    "sg:orig_category":"Prodotti Chimici Secondari. Prodotti Cosmetici E Da Toeletta",
    "sg:phone":"+39 06 474 3302",
    "sg:postcode":"00184",
    "sg:province":"Roma",
    "wof:name":"Progetto Profumeria Srl",
    "wof:placetype":"venue"
},
  "geometry": {"coordinates":[12.490240097,41.8960418701],"type":"Point"}
}