{
  "type": "Feature",
  "properties": {
    "iso:country":"IT",
    "sg:address":"50018 Scandicci",
    "sg:city":"Scandicci",
    "sg:orig_category":"Abrasivi",
    "sg:phone":"+39 055 731 0362",
    "sg:postcode":"50018",
    "sg:province":"Firenze",
    "wof:name":"Fontana Macchine Srl",
    "wof:placetype":"venue"
},
  "geometry": {"coordinates":[11.159955,43.763142],"type":"Point"}
}