{
  "type": "Feature",
  "properties": {
    "iso:country":"IT",
    "sg:address":"9/15, Via Enrico Mattei 20050 Ronco Briantino",
    "sg:city":"Ronco Briantino",
    "sg:classifiers":[
        {
            "category":"Home & Garden",
            "subcategory":"Home Furnishings",
            "type":"Retail Goods"
        }
    ],
    "sg:phone":"+39 039 607 9030",
    "sg:postcode":"20050",
    "sg:province":"Milano",
    "sg:tags":[
        "household"
    ],
    "wof:name":"Stema S.r.l.",
    "wof:placetype":"venue"
},
  "geometry": {"coordinates":[9.417623,45.666698],"type":"Point"}
}