{
  "type": "Feature",
  "properties": {
    "iso:country":"IT",
    "sg:address":"7, C. Re Umberto -, 10121 Torino",
    "sg:city":"Torino",
    "sg:classifiers":[
        {
            "category":"Banks & Credit Unions",
            "subcategory":"Financial Services",
            "type":"Services"
        }
    ],
    "sg:phone":"+39 011 517 5023",
    "sg:postcode":"10121",
    "sg:province":"Torino",
    "sg:tags":[
        "banking",
        "finance",
        "insurance"
    ],
    "wof:name":"Ilgrasim Spa",
    "wof:placetype":"venue"
},
  "geometry": {"coordinates":[7.675588131,45.0663490295],"type":"Point"}
}