{
  "type": "Feature",
  "properties": {
    "addr:full":"74100 Taranto Taranto Taranto 74100",
    "addr:postcode":"74100;74100",
    "iso:country":"IT",
    "sg:address":"74100 Taranto",
    "sg:city":"Taranto",
    "sg:orig_category":"Fotografia - Servizi, Studi, Sviluppo E Stampa",
    "sg:phone":"+39 099 452 5862",
    "sg:postcode":"74100",
    "sg:province":"Taranto",
    "wof:name":"Ingenito Cav. Renato Studio Fotografico Professionale",
    "wof:placetype":"venue"
},
  "geometry": {"coordinates":[17.2456626892,40.4682502747],"type":"Point"}
}