{
  "type": "Feature",
  "properties": {
    "iso:country":"IT",
    "sg:address":"20092 Cinisello Balsamo",
    "sg:city":"Cinisello Balsamo",
    "sg:classifiers":[
        {
            "category":"Professional",
            "subcategory":"Engineering",
            "type":"Services"
        }
    ],
    "sg:phone":"+39 02 660681",
    "sg:postcode":"20092",
    "sg:province":"Milano",
    "sg:tags":[
        "component",
        "material",
        "electronic"
    ],
    "sg:website":"http://www.weidmuller.com",
    "wof:name":"Weidmuller Srl",
    "wof:placetype":"venue"
},
  "geometry": {"coordinates":[9.219064,45.555416],"type":"Point"}
}