{
  "type": "Feature",
  "properties": {
    "iso:country":"IT",
    "sg:address":"31, Via Staiti 91100 Trapani",
    "sg:city":"Trapani",
    "sg:classifiers":[
        {
            "category":"Marine",
            "type":"Transportation"
        }
    ],
    "sg:phone":"+39 0923 873215",
    "sg:postcode":"91100",
    "sg:province":"Trapani",
    "sg:tags":[
        "transport",
        "sea"
    ],
    "wof:name":"Moramar Snc Di Morana Giulia & Maltese Roberto",
    "wof:placetype":"venue"
},
  "geometry": {"coordinates":[12.511337,38.013771],"type":"Point"}
}