{
  "type": "Feature",
  "properties": {
    "iso:country":"IT",
    "sg:address":"08047 Tertenia",
    "sg:city":"Tertenia",
    "sg:classifiers":[
        {
            "category":"Travel",
            "subcategory":"Hotels & Motels",
            "type":"Entertainment"
        }
    ],
    "sg:phone":"+39 0782 90065",
    "sg:postcode":"08047",
    "sg:province":"Ogliastra",
    "sg:tags":[
        "camping",
        "facility"
    ],
    "wof:name":"Campeggio Capo Sferracavallo",
    "wof:placetype":"venue"
},
  "geometry": {"coordinates":[9.611867,39.68523],"type":"Point"}
}