{
  "type": "Feature",
  "properties": {
    "iso:country":"IT",
    "sg:address":"Sda Statale Torino Asti Km 20 10026 Santena",
    "sg:city":"Santena",
    "sg:classifiers":[
        {
            "category":"Coffee & Tea",
            "type":"Food & Drink"
        }
    ],
    "sg:phone":"+39 011 945 5111",
    "sg:postcode":"10026",
    "sg:province":"Torino",
    "sg:tags":[
        "roasted"
    ],
    "sg:website":"www.caffevergnano.com",
    "wof:name":"Casa Del Caffe' Vergnano Spa",
    "wof:placetype":"venue"
},
  "geometry": {"coordinates":[7.686619,45.07056],"type":"Point"}
}