{
  "type": "Feature",
  "properties": {
    "iso:country":"IT",
    "sg:address":"14100 Asti",
    "sg:city":"Asti",
    "sg:orig_category":"Abbigliamento Esterno, Maglierie E Pelliccerie. Forniture Per Il Settore Dello Spettacolo",
    "sg:phone":"+39 0141 530966",
    "sg:postcode":"14100",
    "sg:province":"Asti",
    "wof:name":"La Nuova Maschera (s.n.c.)",
    "wof:placetype":"venue"
},
  "geometry": {"coordinates":[8.213656,44.91024],"type":"Point"}
}