{
  "type": "Feature",
  "properties": {
    "addr:full":"20124 Milano Milano Milano 20124",
    "addr:postcode":"20124;20124",
    "iso:country":"IT",
    "sg:address":"20124 Milano",
    "sg:city":"Milano",
    "sg:orig_category":"Forniture Per Attivita' Commerciali Ed Artigianali",
    "sg:phone":"+39 02 2952 2619",
    "sg:postcode":"20124",
    "sg:province":"Milano",
    "wof:name":"Rossi M. & C.",
    "wof:placetype":"venue"
},
  "geometry": {"coordinates":[9.2098035812,45.4807281494],"type":"Point"}
}