{
  "type": "Feature",
  "properties": {
    "iso:country":"IT",
    "sg:address":"Via Roma 91; Fivizzano; 54013",
    "sg:city":"Fivizzano",
    "sg:classifiers":[
        {
            "category":"Banks & Credit Unions",
            "subcategory":"Bank",
            "type":"Services"
        }
    ],
    "sg:phone":"+39 0585 92035",
    "sg:postcode":"54013",
    "sg:province":"Massa-Carrara",
    "wof:name":"Banca Toscana Spa",
    "wof:placetype":"venue"
},
  "geometry": {"coordinates":[10.125576,44.238937],"type":"Point"}
}