{
  "type": "Feature",
  "properties": {
    "iso:country":"IT",
    "sg:address":"Via Delle Giere 21050 Cairate",
    "sg:city":"Cairate",
    "sg:classifiers":[
        {
            "category":"Parking",
            "subcategory":"Lot",
            "type":"Transportation"
        }
    ],
    "sg:phone":"+39 0331 310890",
    "sg:postcode":"21050",
    "sg:province":"Varese",
    "sg:tags":[
        "transport",
        "road"
    ],
    "wof:name":"E.l.c.a. Trasporti S.r.l.",
    "wof:placetype":"venue"
},
  "geometry": {"coordinates":[8.856423,45.692341],"type":"Point"}
}