{
  "type": "Feature",
  "properties": {
    "iso:country":"IT",
    "sg:address":"97015 Modica",
    "sg:city":"Modica",
    "sg:orig_category":"Servizi E Lavori Per Edilizia E Lavori Pubblici. Servizi E Lavori Per Ecologia E Smaltimento Rifiuti",
    "sg:phone":"+39 0932 942102",
    "sg:postcode":"97015",
    "sg:province":"Ragusa",
    "wof:name":"Buscema Giovanni Carmelo",
    "wof:placetype":"venue"
},
  "geometry": {"coordinates":[14.822115,36.852718],"type":"Point"}
}