{
  "type": "Feature",
  "properties": {
    "iso:country":"IT",
    "sg:address":"59100 Prato",
    "sg:city":"Prato",
    "sg:orig_category":"Prodotti Chimici Di Base",
    "sg:phone":"+39 0574 663303",
    "sg:postcode":"59100",
    "sg:province":"Prato",
    "sg:website":"http://www.catex.it",
    "wof:name":"C.a.tex Snc",
    "wof:placetype":"venue"
},
  "geometry": {"coordinates":[11.0602846146,43.8765106201],"type":"Point"}
}