{
  "type": "Feature",
  "properties": {
    "iso:country":"IT",
    "sg:address":"20064 Gorgonzola",
    "sg:city":"Gorgonzola",
    "sg:orig_category":"Cartotecnica E Servizi. Articoli Per Imballaggio E Confezionamento",
    "sg:phone":"+39 02 9530 1799",
    "sg:postcode":"20064",
    "sg:province":"Milano",
    "wof:name":"Decordolce Srl",
    "wof:placetype":"venue"
},
  "geometry": {"coordinates":[9.211499,45.563053],"type":"Point"}
}