{
  "type": "Feature",
  "properties": {
    "iso:country":"IT",
    "sg:address":"20146 Milano",
    "sg:city":"Milano",
    "sg:orig_category":"Servizi E Lavori Per Agricoltura E Zootecnia. Animali Domestici",
    "sg:phone":"+39 02 481 4340",
    "sg:postcode":"20146",
    "sg:province":"Milano",
    "wof:name":"Dorcaratto Andrea",
    "wof:placetype":"venue"
},
  "geometry": {"coordinates":[9.154828,45.461697],"type":"Point"}
}