{
  "type": "Feature",
  "properties": {
    "iso:country":"IT",
    "sg:address":"35010 Cadoneghe",
    "sg:city":"Cadoneghe",
    "sg:classifiers":[
        {
            "category":"Utilities",
            "subcategory":"Natural Gas",
            "type":"Services"
        }
    ],
    "sg:phone":"+39 049 701242",
    "sg:postcode":"35010",
    "sg:province":"Padova",
    "sg:tags":[
        "aria",
        "e",
        "compressori"
    ],
    "wof:name":"Co.mar Srl",
    "wof:placetype":"venue"
},
  "geometry": {"coordinates":[11.894617,45.462433],"type":"Point"}
}