{
  "type": "Feature",
  "properties": {
    "iso:country":"IT",
    "sg:address":"20037 Paderno Dugnano",
    "sg:city":"Paderno Dugnano",
    "sg:orig_category":"Climatizzazione E Condizionamento, Apparecchiature E Servizi",
    "sg:phone":"+39 02 910 6940",
    "sg:postcode":"20037",
    "sg:province":"Milano",
    "wof:name":"M.a.p.i. Sas",
    "wof:placetype":"venue"
},
  "geometry": {"coordinates":[9.165154,45.56929],"type":"Point"}
}