{
  "type": "Feature",
  "properties": {
    "addr:full":"94019 Valguarnera Enna 94019",
    "addr:postcode":"94019;94019",
    "iso:country":"IT",
    "sg:address":"94019 Valguarnera",
    "sg:orig_category":"Impianti Elettrici - Linee Elettriche Blindate",
    "sg:phone":"+39 0935 958427",
    "sg:postcode":"94019",
    "sg:province":"Enna",
    "wof:name":"Luxor Srl",
    "wof:placetype":"venue"
},
  "geometry": {"coordinates":[14.385869,37.49342],"type":"Point"}
}