{
  "type": "Feature",
  "properties": {
    "iso:country":"IT",
    "sg:address":"52025 Montevarchi",
    "sg:city":"Montevarchi",
    "sg:orig_category":"Pubblica Amministrazione",
    "sg:phone":"+39 055 985 0177",
    "sg:postcode":"52025",
    "sg:province":"Arezzo",
    "wof:name":"Scuole Pubbliche",
    "wof:placetype":"venue"
},
  "geometry": {"coordinates":[11.5589103699,43.5000801086],"type":"Point"}
}