{
  "type": "Feature",
  "properties": {
    "addr:full":"29, Via Pietro Polato 35027 Noventa Padovana Noventa Padovana Padova 35027",
    "addr:postcode":"35027;35027",
    "addr:street":"Via Pietro Polato",
    "iso:country":"IT",
    "sg:address":"29, Via Pietro Polato 35027 Noventa Padovana",
    "sg:city":"Noventa Padovana",
    "sg:classifiers":[
        {
            "category":"Manufacturing",
            "subcategory":"Rubber & Plastics",
            "type":"Manufacturing & Wholesale Goods"
        }
    ],
    "sg:phone":"+39 049 895 9086",
    "sg:postcode":"35027",
    "sg:province":"Padova",
    "wof:name":"Tacchificio F.lli Polato (s.r.l.)",
    "wof:placetype":"venue"
},
  "geometry": {"coordinates":[11.982509613,45.412525177],"type":"Point"}
}