{
  "type": "Feature",
  "properties": {
    "iso:country":"IT",
    "sg:address":"Via Torino 95 10040 Givoletto",
    "sg:city":"Givoletto",
    "sg:classifiers":[
        {
            "category":"Shopping",
            "subcategory":"Computers & Home Electronics",
            "type":"Retail Goods"
        }
    ],
    "sg:phone":"+39 011 994 7649",
    "sg:postcode":"10040",
    "sg:province":"Torino",
    "sg:tags":[
        "installation",
        "accessory"
    ],
    "sg:website":"www.maxtitaly.com",
    "wof:name":"Maxt Srl",
    "wof:placetype":"venue"
},
  "geometry": {"coordinates":[7.521653,45.152176],"type":"Point"}
}