{
  "type": "Feature",
  "properties": {
    "iso:country":"IT",
    "sg:address":"54031 Carrara",
    "sg:orig_category":"Gioielleria, Oreficeria E Argenteria",
    "sg:phone":"+39 0585 859356",
    "sg:province":"MS",
    "wof:name":"Jardella Giorgio & C. Snc",
    "wof:placetype":"venue"
},
  "geometry": {"coordinates":[10.060489,44.050114],"type":"Point"}
}