{
  "type": "Feature",
  "properties": {
    "iso:country":"IT",
    "sg:address":"20134 Milano",
    "sg:city":"Milano",
    "sg:orig_category":"Petroli, Gas E Combustibili. Servizi E Lavori Industria Chimica. Servizi E Lavori Per Edilizia E Lavori Pubblici. Acqua, Luce, Gas E Societa' Di Esercizio Pubblico",
    "sg:phone":"+39 02 733124",
    "sg:postcode":"20134",
    "sg:province":"Milano",
    "wof:name":"Simgas (s.r.l.)",
    "wof:placetype":"venue"
},
  "geometry": {"coordinates":[9.2618522644,45.4714126587],"type":"Point"}
}