{
  "type": "Feature",
  "properties": {
    "iso:country":"IT",
    "sg:address":"02100 Rieti",
    "sg:city":"Rieti",
    "sg:orig_category":"Servizi E Lavori Per Edilizia E Lavori Pubblici. Consulenze Tecniche, Amministrative E Perizie",
    "sg:phone":"+39 0746 202000",
    "sg:postcode":"02100",
    "sg:province":"Rieti",
    "wof:name":"A.p. Immobiliare",
    "wof:placetype":"venue"
},
  "geometry": {"coordinates":[12.853088,42.400902],"type":"Point"}
}