{
  "type": "Feature",
  "properties": {
    "iso:country":"IT",
    "sg:address":"00185 Roma",
    "sg:city":"Roma",
    "sg:orig_category":"Arte Ed Artigianato Artistico",
    "sg:phone":"+39 06 445 6318",
    "sg:postcode":"00185",
    "sg:province":"Roma",
    "wof:name":"Melotta Michele",
    "wof:placetype":"venue"
},
  "geometry": {"coordinates":[12.516103,41.89925],"type":"Point"}
}