{
  "type": "Feature",
  "properties": {
    "iso:country":"IT",
    "sg:address":"36045 Lonigo",
    "sg:city":"Lonigo",
    "sg:orig_category":"Macchine Ed Impianti Per Edilizia E Lavori Pubblici. Macchine, Strumenti Ed Apparecchi Per Attivita' Industriali",
    "sg:phone":"+39 0444 830233",
    "sg:postcode":"36045",
    "sg:province":"Vicenza",
    "wof:name":"Ecoglass (s.r.l.)",
    "wof:placetype":"venue"
},
  "geometry": {"coordinates":[11.36982,45.42374],"type":"Point"}
}