{
  "type": "Feature",
  "properties": {
    "addr:full":"48100 Ravenna Ravenna Ravenna 48100",
    "addr:housenumber":"48100",
    "addr:postcode":"48100",
    "iso:country":"IT",
    "sg:address":"48100 Ravenna",
    "sg:city":"Ravenna",
    "sg:orig_category":"Agenzie Ed Uffici Commerciali",
    "sg:phone":"+39 0544 451700",
    "sg:postcode":"48100",
    "sg:province":"Ravenna",
    "wof:name":"L'affare",
    "wof:placetype":"venue"
},
  "geometry": {"coordinates":[12.2545347214,44.2608833313],"type":"Point"}
}