{
  "type": "Feature",
  "properties": {
    "iso:country":"IT",
    "sg:address":"14, Via Gavardina 25011 Calcinato",
    "sg:city":"Calcinato",
    "sg:classifiers":[
        {
            "category":"Professional",
            "subcategory":"Engineering",
            "type":"Services"
        }
    ],
    "sg:phone":"+39 39030963162",
    "sg:postcode":"25011",
    "sg:province":"Brescia",
    "sg:tags":[
        "machine",
        "-",
        "mechanical"
    ],
    "wof:name":"C.m.i. S.r.l.",
    "wof:placetype":"venue"
},
  "geometry": {"coordinates":[10.396931,45.46632],"type":"Point"}
}