{
  "type": "Feature",
  "properties": {
    "addr:full":"10060 Fenestrelle Fenestrelle Torino 10060",
    "addr:postcode":"10060;10060",
    "iso:country":"IT",
    "sg:address":"10060 Fenestrelle",
    "sg:city":"Fenestrelle",
    "sg:orig_category":"Alberghi E Strutture Extra Alberghiere. Ospedali E Servizi Sanitari",
    "sg:phone":"+39 0121 83850",
    "sg:postcode":"10060",
    "sg:province":"Torino",
    "wof:name":"Casa Alpina Pio Xii",
    "wof:placetype":"venue"
},
  "geometry": {"coordinates":[7.05223,45.034485],"type":"Point"}
}