{
  "type": "Feature",
  "properties": {
    "addr:full":"92014 Porto Empedocle Porto Empedocle Agrigento 92014",
    "addr:postcode":"92014;92014",
    "iso:country":"IT",
    "sg:address":"92014 Porto Empedocle",
    "sg:city":"Porto Empedocle",
    "sg:orig_category":"Carpenterie Metalliche",
    "sg:phone":"+39 0922 633472",
    "sg:postcode":"92014",
    "sg:province":"Agrigento",
    "wof:name":"Scire' Scappuzzo Maurizio",
    "wof:placetype":"venue"
},
  "geometry": {"coordinates":[13.534281,37.293667],"type":"Point"}
}