{
  "type": "Feature",
  "properties": {
    "iso:country":"IT",
    "sg:address":"35127 Camin",
    "sg:orig_category":"Macchine, Impianti Ed Attrezzature Per Industria Alimentare E Bevande. Macchine, Impianti Ed Attrezzature Industria Chimica",
    "sg:phone":"+39 049 894 9494",
    "sg:postcode":"35127",
    "sg:province":"Padova",
    "wof:name":"G B S Group S.p.a.",
    "wof:placetype":"venue"
},
  "geometry": {"coordinates":[11.936097,45.39386],"type":"Point"}
}