{
  "type": "Feature",
  "properties": {
    "addr:full":"Via E. Quirino Visconti 80, 00193 Rome, Rm Roma 00193",
    "addr:housenumber":"80",
    "addr:postcode":"00193;rm;00193",
    "addr:street":"Via E. Quirino Visconti",
    "iso:country":"IT",
    "sg:address":"Via E. Quirino Visconti 80, 00193 Rome, Rm",
    "sg:classifiers":[
        {
            "category":"Banks & Credit Unions",
            "subcategory":"Bank",
            "type":"Services"
        }
    ],
    "sg:phone":"+39 0635711",
    "sg:postcode":"00193",
    "sg:province":"Roma",
    "wof:name":"Fideuram Vita",
    "wof:placetype":"venue"
},
  "geometry": {"coordinates":[12.468519,41.907177],"type":"Point"}
}