{
  "type": "Feature",
  "properties": {
    "addr:full":"Via Statale 467, N. 119 42013 Casalgrande Reggio Nell'Emilia 42013",
    "addr:housenumber":"467 n. 119",
    "addr:postcode":"42013;42013",
    "addr:street":"Via Statale",
    "iso:country":"IT",
    "sg:address":"Via Statale 467, N. 119 42013 Casalgrande",
    "sg:classifiers":[
        {
            "category":"Home & Garden",
            "subcategory":"Carpets & Floor Coverings",
            "type":"Retail Goods"
        }
    ],
    "sg:phone":"+39 0522 846890",
    "sg:postcode":"42013",
    "sg:province":"Reggio Nell'Emilia",
    "sg:tags":[
        "tile"
    ],
    "sg:website":"www.cipagres.com",
    "wof:name":"Cipa Gres Spa",
    "wof:placetype":"venue"
},
  "geometry": {"coordinates":[10.692736,44.600838],"type":"Point"}
}