{
  "type": "Feature",
  "properties": {
    "iso:country":"IT",
    "sg:address":"25, Via Artigianato 25034 Orzinuovi",
    "sg:city":"Orzinuovi",
    "sg:classifiers":[
        {
            "category":"Shopping",
            "subcategory":"Clothing, Apparel, & Fashions",
            "type":"Retail Goods"
        }
    ],
    "sg:phone":"+39 39030944140",
    "sg:postcode":"25034",
    "sg:province":"Brescia",
    "sg:tags":[
        "clothes"
    ],
    "wof:name":"Alfa Confezioni (s.r.l.)",
    "wof:placetype":"venue"
},
  "geometry": {"coordinates":[9.942841,45.411678],"type":"Point"}
}