{
  "type": "Feature",
  "properties": {
    "iso:country":"IT",
    "sg:address":"Via Boncompagni 6; Roma",
    "sg:classifiers":[
        {
            "category":"Banks & Credit Unions",
            "subcategory":"Bank",
            "type":"Services"
        }
    ],
    "sg:phone":"+39 06 481691",
    "wof:name":"Banco Di Sardegna Spa",
    "wof:placetype":"venue"
},
  "geometry": {"coordinates":[12.492482,41.908054],"type":"Point"}
}