{
  "type": "Feature",
  "properties": {
    "iso:country":"IT",
    "sg:address":"7, Via Quarto 13875 Ponderano",
    "sg:city":"Ponderano",
    "sg:classifiers":[
        {
            "category":"Manufacturing",
            "subcategory":"Rubber & Plastics",
            "type":"Manufacturing & Wholesale Goods"
        }
    ],
    "sg:phone":"+39 39015541900",
    "sg:postcode":"13875",
    "sg:province":"Biella",
    "wof:name":"Daisy Di Demargherita Giuseppe & Figlio (s.n.c.)",
    "wof:placetype":"venue"
},
  "geometry": {"coordinates":[8.0523757935,45.5408210754],"type":"Point"}
}