{
  "type": "Feature",
  "properties": {
    "iso:country":"IT",
    "sg:address":"59, Via Fonda Di Mezzana 59100 Prato",
    "sg:city":"Mezzana",
    "sg:classifiers":[
        {
            "category":"Sports & Exercise",
            "subcategory":"Playing Field",
            "type":"Entertainment"
        }
    ],
    "sg:phone":"+39 0574 582283",
    "sg:postcode":"59100",
    "sg:province":"Prato",
    "sg:tags":[
        "game"
    ],
    "wof:name":"Vannucchi Mauro & C. (s.n.c.)",
    "wof:placetype":"venue"
},
  "geometry": {"coordinates":[11.098834,43.84676],"type":"Point"}
}