{
  "type": "Feature",
  "properties": {
    "addr:full":"55013 Capannori Capannori Lucca 55013",
    "addr:postcode":"55013;55013",
    "iso:country":"IT",
    "sg:address":"55013 Capannori",
    "sg:city":"Capannori",
    "sg:classifiers":[
        {
            "category":"Manufacturing",
            "subcategory":"Paper Products",
            "type":"Manufacturing & Wholesale Goods"
        }
    ],
    "sg:phone":"+39 0583 438133",
    "sg:postcode":"55013",
    "sg:province":"Lucca",
    "sg:tags":[
        "graphic",
        "publishing",
        "supply",
        "industry",
        "equipment",
        "machinery"
    ],
    "wof:name":"Spares & More Srl",
    "wof:placetype":"venue"
},
  "geometry": {"coordinates":[10.560395,43.871193],"type":"Point"}
}