{
  "type": "Feature",
  "properties": {
    "iso:country":"IT",
    "sg:address":"00186 Roma",
    "sg:city":"Roma",
    "sg:orig_category":"Abbigliamento Intimo, Calze E Costumi Da Bagno. Sport - Articoli E Forniture. Shopping",
    "sg:phone":"+39 06 687 6191",
    "sg:postcode":"00186",
    "sg:province":"Roma",
    "wof:name":"Emiliozzi",
    "wof:placetype":"venue"
},
  "geometry": {"coordinates":[12.47615,41.904831],"type":"Point"}
}