{
  "type": "Feature",
  "properties": {
    "iso:country":"IT",
    "sg:address":"46, Via Del Sale 26100 Cremona",
    "sg:city":"Cremona",
    "sg:classifiers":[
        {
            "category":"Shopping",
            "subcategory":"Computers & Home Electronics",
            "type":"Retail Goods"
        }
    ],
    "sg:phone":"+39 39037237880",
    "sg:postcode":"26100",
    "sg:province":"Cremona",
    "sg:tags":[
        "electronic",
        "electrical",
        "equipment"
    ],
    "wof:name":"Solzi Luce (s.r.l.)",
    "wof:placetype":"venue"
},
  "geometry": {"coordinates":[10.012919,45.128994],"type":"Point"}
}