{
  "type": "Feature",
  "properties": {
    "iso:country":"IT",
    "sg:address":"10022 Carmagnola",
    "sg:city":"Carmagnola",
    "sg:orig_category":"Macchine Ed Impianti Per Edilizia E Lavori Pubblici",
    "sg:phone":"+39 011 972 1415",
    "sg:postcode":"10022",
    "sg:province":"Torino",
    "wof:name":"Ronchietto Battista",
    "wof:placetype":"venue"
},
  "geometry": {"coordinates":[7.711326,44.863525],"type":"Point"}
}