{
  "type": "Feature",
  "properties": {
    "iso:country":"IT",
    "sg:address":"1150, Via Argine 80147 Napoli",
    "sg:city":"Napoli",
    "sg:classifiers":[
        {
            "category":"Manufacturing",
            "subcategory":"Wood Products",
            "type":"Manufacturing & Wholesale Goods"
        }
    ],
    "sg:phone":"+39 081 733 4211",
    "sg:postcode":"80147",
    "sg:province":"Napoli",
    "sg:tags":[
        "furniture"
    ],
    "wof:name":"Breglia (s.p.a.)",
    "wof:placetype":"venue"
},
  "geometry": {"coordinates":[14.345167,40.866051],"type":"Point"}
}