{
  "type": "Feature",
  "properties": {
    "iso:country":"IT",
    "sg:address":"42014 Castellarano",
    "sg:classifiers":[
        {
            "category":"Manufacturing",
            "subcategory":"Tools & Machinery",
            "type":"Manufacturing & Wholesale Goods"
        }
    ],
    "sg:phone":"+39 0536 851654",
    "sg:postcode":"42014",
    "sg:province":"Reggio Nell'Emilia",
    "sg:tags":[
        "material",
        "mechanical"
    ],
    "wof:name":"M.e.m. Srl",
    "wof:placetype":"venue"
},
  "geometry": {"coordinates":[10.680069,44.484123],"type":"Point"}
}