{
  "type": "Feature",
  "properties": {
    "iso:country":"IT",
    "sg:address":"10155 Torino",
    "sg:city":"Torino",
    "sg:orig_category":"Campeggio. Automobili E Mezzi Di Trasporto",
    "sg:phone":"+39 011 50065",
    "sg:postcode":"10155",
    "sg:province":"Torino",
    "wof:name":"Capello Pietro",
    "wof:placetype":"venue"
},
  "geometry": {"coordinates":[7.688006,45.091301],"type":"Point"}
}