{
  "type": "Feature",
  "properties": {
    "addr:full":"1, Via Filottrano 60027 Osimo Osimo Ancona 60027",
    "addr:postcode":"60027;60027",
    "addr:street":"Via Filottrano",
    "iso:country":"IT",
    "sg:address":"1, Via Filottrano 60027 Osimo",
    "sg:city":"Osimo",
    "sg:classifiers":[
        {
            "category":"Manufacturing",
            "subcategory":"Metals",
            "type":"Manufacturing & Wholesale Goods"
        }
    ],
    "sg:phone":"+39 071 710 0666",
    "sg:postcode":"60027",
    "sg:province":"Ancona",
    "sg:tags":[
        "processing"
    ],
    "wof:name":"Siva S.r.l.",
    "wof:placetype":"venue"
},
  "geometry": {"coordinates":[13.4429616928,43.4492378235],"type":"Point"}
}