{
  "type": "Feature",
  "properties": {
    "iso:country":"IT",
    "sg:address":"164, Via S. Francesco D'assisi 70018 Rutigliano",
    "sg:city":"Rutigliano",
    "sg:classifiers":[
        {
            "category":"Wholesale",
            "subcategory":"Machinery & Supplies",
            "type":"Manufacturing & Wholesale Goods"
        }
    ],
    "sg:phone":"+39 080 476 2150",
    "sg:postcode":"70018",
    "sg:province":"Bari",
    "sg:tags":[
        "equipment",
        "-",
        "instrument",
        "measurement"
    ],
    "wof:name":"Poliforniture (s.a.s.)",
    "wof:placetype":"venue"
},
  "geometry": {"coordinates":[16.999729,41.009323],"type":"Point"}
}