{
  "type": "Feature",
  "properties": {
    "iso:country":"IT",
    "sg:address":"Via Quinto Ennio 70031 Andria",
    "sg:city":"Andria",
    "sg:classifiers":[
        {
            "category":"Shopping",
            "subcategory":"Clothing, Apparel, & Fashions",
            "type":"Retail Goods"
        }
    ],
    "sg:phone":"+39 0883 552428",
    "sg:postcode":"70031",
    "sg:province":"Bari",
    "sg:tags":[
        "clothes"
    ],
    "wof:name":"Creazione Tesy Di Mosca Teresa",
    "wof:placetype":"venue"
},
  "geometry": {"coordinates":[16.306883,41.236767],"type":"Point"}
}