{
  "type": "Feature",
  "properties": {
    "addr:full":"Via Umberto 3; Cesa; 81030 Cesa Caserta 81030",
    "addr:housenumber":"3",
    "addr:postcode":"81030;81030",
    "addr:street":"Via Umberto",
    "iso:country":"IT",
    "sg:address":"Via Umberto 3; Cesa; 81030",
    "sg:city":"Cesa",
    "sg:classifiers":[
        {
            "category":"Banks & Credit Unions",
            "subcategory":"Bank",
            "type":"Services"
        }
    ],
    "sg:phone":"+39 081 503 2401",
    "sg:postcode":"81030",
    "sg:province":"Caserta",
    "wof:name":"Banco Di Napoli Spa",
    "wof:placetype":"venue"
},
  "geometry": {"coordinates":[14.231167,40.960888],"type":"Point"}
}