{
  "type": "Feature",
  "properties": {
    "iso:country":"IT",
    "sg:address":"22100 Como",
    "sg:city":"Como",
    "sg:orig_category":"Musica",
    "sg:phone":"+39 031 593577",
    "sg:postcode":"22100",
    "sg:province":"Como",
    "wof:name":"Valtellina Giuochi Di Spandrio Alberto E Tarabini R. Snc",
    "wof:placetype":"venue"
},
  "geometry": {"coordinates":[9.0783195496,45.7876777649],"type":"Point"}
}