{
  "type": "Feature",
  "properties": {
    "addr:full":"Via Nazionale, 91; Cerrina Monferrato; 15033 Alessandria 15033",
    "addr:housenumber":"91",
    "addr:postcode":"15033;15033",
    "addr:street":"Via Nazionale",
    "iso:country":"IT",
    "sg:address":"Via Nazionale, 91; Cerrina Monferrato; 15033",
    "sg:classifiers":[
        {
            "category":"Banks & Credit Unions",
            "subcategory":"Bank",
            "type":"Services"
        }
    ],
    "sg:phone":"+39 0142 94125",
    "sg:postcode":"15033",
    "sg:province":"Alessandria",
    "wof:name":"Banca Nazionale Dell' Agricoltura",
    "wof:placetype":"venue"
},
  "geometry": {"coordinates":[8.211443,45.1134],"type":"Point"}
}