{
  "type": "Feature",
  "properties": {
    "iso:country":"IT",
    "sg:address":"51012 Pescia",
    "sg:city":"Pescia",
    "sg:orig_category":"Ottica, Lenti A Contatto Ed Occhiali - Vendita Al Dettaglio",
    "sg:phone":"+39 0572 451288",
    "sg:postcode":"51012",
    "sg:province":"Pistoia",
    "wof:name":"Belpassi Giancarlo",
    "wof:placetype":"venue"
},
  "geometry": {"coordinates":[10.687795,43.888283],"type":"Point"}
}