{
  "type": "Feature",
  "properties": {
    "addr:full":"58015 Orbetello Orbetello Grosseto 58015",
    "addr:postcode":"58015;58015",
    "iso:country":"IT",
    "sg:address":"58015 Orbetello",
    "sg:city":"Orbetello",
    "sg:orig_category":"Macchine, Impianti Ed Attrezzature Per Abbigliamento E Pelletterie",
    "sg:phone":"+39 0564 863937",
    "sg:postcode":"58015",
    "sg:province":"Grosseto",
    "wof:name":"Bartolini Dina",
    "wof:placetype":"venue"
},
  "geometry": {"coordinates":[11.229711,42.525593],"type":"Point"}
}