{
  "type": "Feature",
  "properties": {
    "addr:full":"25010 Limone Sul Garda Limone sul Garda Brescia 25010",
    "addr:postcode":"25010;25010",
    "iso:country":"IT",
    "sg:address":"25010 Limone Sul Garda",
    "sg:city":"Limone sul Garda",
    "sg:orig_category":"Articoli Sportivi - Vendita Al Dettaglio",
    "sg:phone":"+39 0464 505993",
    "sg:postcode":"25010",
    "sg:province":"Brescia",
    "wof:name":"Vasco Renna Professional Surcenter",
    "wof:placetype":"venue"
},
  "geometry": {"coordinates":[10.79322,45.814678],"type":"Point"}
}