{
  "type": "Feature",
  "properties": {
    "iso:country":"IT",
    "sg:address":"04020 Itri",
    "sg:city":"Itri",
    "sg:orig_category":"Frantumazione E Macinazione - Macchine",
    "sg:phone":"+39 0771 721261",
    "sg:postcode":"04020",
    "sg:province":"Latina",
    "sg:website":"http://www.imoil.com",
    "wof:name":"Imoil Srl",
    "wof:placetype":"venue"
},
  "geometry": {"coordinates":[13.4340744019,41.2590293884],"type":"Point"}
}