{
  "type": "Feature",
  "properties": {
    "iso:country":"IT",
    "sg:address":"00165 Roma",
    "sg:city":"Roma",
    "sg:orig_category":"Scuole Per Parrucchieri",
    "sg:phone":"+39 06 3937 5350",
    "sg:postcode":"00165",
    "sg:province":"Roma",
    "wof:name":"Ara Accademia Romana Acconciature",
    "wof:placetype":"venue"
},
  "geometry": {"coordinates":[12.4573,41.896385],"type":"Point"}
}