{
  "type": "Feature",
  "properties": {
    "addr:full":"20121 Milano Milano Milano 20121",
    "addr:postcode":"20121;20121",
    "iso:country":"IT",
    "sg:address":"20121 Milano",
    "sg:city":"Milano",
    "sg:classifiers":[
        {
            "category":"Health Services",
            "subcategory":"Health Practitioner",
            "type":"Services"
        }
    ],
    "sg:phone":"+39 02 863261",
    "sg:postcode":"20121",
    "sg:province":"Milano",
    "sg:tags":[
        "medici"
    ],
    "wof:name":"Rusconi Clerici Chiara",
    "wof:placetype":"venue"
},
  "geometry": {"coordinates":[9.1820573807,45.4704818726],"type":"Point"}
}