{
  "type": "Feature",
  "properties": {
    "iso:country":"IT",
    "sg:address":"40128 Bologna",
    "sg:city":"Bologna",
    "sg:orig_category":"Cinematografia E Radiotelevisione. Servizi Per Aziende, Manifestazioni E Supporto Agli Scambi Commerciali",
    "sg:phone":"+39 051 352264",
    "sg:postcode":"40128",
    "sg:province":"Bologna",
    "wof:name":"Tekne Immagine Sas Di M. Faggioli & C.",
    "wof:placetype":"venue"
},
  "geometry": {"coordinates":[11.354643,44.518017],"type":"Point"}
}