{
  "type": "Feature",
  "properties": {
    "iso:country":"IT",
    "sg:address":"42018 San Martino In Rio",
    "sg:orig_category":"Abbigliamento - Vendita Al Dettaglio",
    "sg:phone":"+39 0522 646330",
    "sg:postcode":"42018",
    "sg:province":"Reggio Nell'Emilia",
    "wof:name":"Ricami Laura Snc",
    "wof:placetype":"venue"
},
  "geometry": {"coordinates":[10.788067,44.718208],"type":"Point"}
}