{
  "type": "Feature",
  "properties": {
    "iso:country":"IT",
    "sg:address":"Via Caduti Senza Croce 15/a 41100 Modena",
    "sg:city":"Modena",
    "sg:orig_category":"Low-voltage Motors",
    "sg:phone":"+39 059 510716",
    "sg:postcode":"41100",
    "sg:province":"Modena",
    "sg:website":"www.nuovavecchibenedetti.it",
    "wof:name":"Nuova Vecchi & Benedetti Srl",
    "wof:placetype":"venue"
},
  "geometry": {"coordinates":[10.92522,44.647079],"type":"Point"}
}