{
  "type": "Feature",
  "properties": {
    "iso:country":"IT",
    "sg:address":"25011 Calcinato",
    "sg:city":"Calcinato",
    "sg:orig_category":"Automobili - Commercio",
    "sg:phone":"+39 030 963 7067",
    "sg:postcode":"25011",
    "sg:province":"Brescia",
    "wof:name":"Bianchini Lorenzo",
    "wof:placetype":"venue"
},
  "geometry": {"coordinates":[10.405449,45.475636],"type":"Point"}
}