{
  "type": "Feature",
  "properties": {
    "iso:country":"IT",
    "sg:address":"35, Strada Statale Dei Giovi 20080 Zibido San Giacomo",
    "sg:city":"Zibido San Giacomo",
    "sg:classifiers":[
        {
            "category":"Shopping",
            "subcategory":"Crafts & Fabrics",
            "type":"Retail Goods"
        }
    ],
    "sg:phone":"+39 39029053757",
    "sg:postcode":"20080",
    "sg:province":"Milano",
    "wof:name":"Vaiani",
    "wof:placetype":"venue"
},
  "geometry": {"coordinates":[9.1103725433,45.3579177856],"type":"Point"}
}