{
  "type": "Feature",
  "properties": {
    "iso:country":"IT",
    "sg:address":"96010 Palazzolo Acreide",
    "sg:city":"Palazzolo Acreide",
    "sg:orig_category":"Zootecnia E Pesca, Allevamento Piccoli Animali",
    "sg:phone":"+39 0931 883433",
    "sg:postcode":"96010",
    "sg:province":"Siracusa",
    "sg:website":"http://www.latrota.it",
    "wof:name":"La Trota Di La Mesa Sebastiano & Amodio S. Sas",
    "wof:placetype":"venue"
},
  "geometry": {"coordinates":[14.904502,37.063393],"type":"Point"}
}