{
  "type": "Feature",
  "properties": {
    "iso:country":"IT",
    "sg:address":"20030 Senago",
    "sg:city":"Senago",
    "sg:orig_category":"Elettronica Professionale E Di Consumo. Tempo Libero - Articoli E Forniture",
    "sg:phone":"+39 02 998 6369",
    "sg:postcode":"20030",
    "sg:province":"Milano",
    "wof:name":"Flora Games S.a.s.",
    "wof:placetype":"venue"
},
  "geometry": {"coordinates":[9.101866,45.541412],"type":"Point"}
}