{
  "type": "Feature",
  "properties": {
    "iso:country":"IT",
    "sg:address":"73, Via Marzabotto 41042 Fiorano Modenese",
    "sg:city":"Fiorano Modenese",
    "sg:classifiers":[
        {
            "category":"Professional",
            "subcategory":"Printing & Photocopies",
            "type":"Services"
        }
    ],
    "sg:phone":"+39 0536 830438",
    "sg:postcode":"41042",
    "sg:province":"Modena",
    "wof:name":"Fioranese Srl",
    "wof:placetype":"venue"
},
  "geometry": {"coordinates":[10.8205728531,44.5583610535],"type":"Point"}
}