{
  "type": "Feature",
  "properties": {
    "iso:country":"IT",
    "sg:address":"23873 Missaglia",
    "sg:city":"Missaglia",
    "sg:orig_category":"Catene A Rulli Per Trasmissioni",
    "sg:phone":"+39 039 920 0551",
    "sg:postcode":"23873",
    "sg:province":"Lecco",
    "sg:website":"http://www.sircatene.com",
    "wof:name":"Sircatene Spa",
    "wof:placetype":"venue"
},
  "geometry": {"coordinates":[9.347558,45.697399],"type":"Point"}
}