{
  "type": "Feature",
  "properties": {
    "addr:full":"16164 Genova Genova Genova 16164",
    "addr:postcode":"16164;16164",
    "iso:country":"IT",
    "sg:address":"16164 Genova",
    "sg:city":"Genova",
    "sg:orig_category":"Geologia, Geotecnica E Topografia - Studi E Servizi",
    "sg:phone":"+39 010 781121",
    "sg:postcode":"16164",
    "sg:province":"Genova",
    "wof:name":"Zenit",
    "wof:placetype":"venue"
},
  "geometry": {"coordinates":[8.905833,44.494167],"type":"Point"}
}