{
  "type": "Feature",
  "properties": {
    "addr:full":"Via Dei Pini 46040 Casalromano Casalromano Mantova 46040",
    "addr:postcode":"46040;46040",
    "addr:street":"Via Dei Pini",
    "iso:country":"IT",
    "sg:address":"Via Dei Pini 46040 Casalromano",
    "sg:city":"Casalromano",
    "sg:classifiers":[
        {
            "category":"Manufacturing",
            "subcategory":"Rubber & Plastics",
            "type":"Manufacturing & Wholesale Goods"
        }
    ],
    "sg:phone":"+39 39037676078",
    "sg:postcode":"46040",
    "sg:province":"Mantova",
    "wof:name":"Sevenplast Di Longhini Matilde & C. (s.n.c.)",
    "wof:placetype":"venue"
},
  "geometry": {"coordinates":[10.3614416122,45.2072181702],"type":"Point"}
}