{
  "type": "Feature",
  "properties": {
    "addr:full":"36100 Vicenza Vicenza Vicenza 36100",
    "addr:postcode":"36100;36100",
    "iso:country":"IT",
    "sg:address":"36100 Vicenza",
    "sg:city":"Vicenza",
    "sg:orig_category":"Fiere, Mostre E Saloni - Enti Organizzatori",
    "sg:phone":"+39 0444 969111",
    "sg:postcode":"36100",
    "sg:province":"Vicenza",
    "sg:website":"http://www.vicenzafiera.it",
    "wof:name":"Ente Fiera Vicenza",
    "wof:placetype":"venue"
},
  "geometry": {"coordinates":[11.561044693,45.536190033],"type":"Point"}
}