{
  "type": "Feature",
  "properties": {
    "iso:country":"IT",
    "sg:address":"21058 Solbiate Olona",
    "sg:city":"Solbiate Olona",
    "sg:orig_category":"Forniture Per Abbigliamento E Pelletterie",
    "sg:phone":"+39 0331 640049",
    "sg:postcode":"21058",
    "sg:province":"Varese",
    "wof:name":"Rogora Enrico",
    "wof:placetype":"venue"
},
  "geometry": {"coordinates":[8.875869751,45.6493835449],"type":"Point"}
}