{
  "type": "Feature",
  "properties": {
    "iso:country":"IT",
    "sg:address":"30, Via Guglielmo Marconi 10085 Pont Canavese",
    "sg:classifiers":[
        {
            "category":"Professional",
            "subcategory":"Engineering",
            "type":"Services"
        }
    ],
    "sg:phone":"+39 0124 862222",
    "sg:postcode":"10085",
    "sg:province":"Torino",
    "sg:tags":[
        "machine",
        "-",
        "mechanical"
    ],
    "wof:name":"Componenti Presse S.r.l.",
    "wof:placetype":"venue"
},
  "geometry": {"coordinates":[7.593894,45.422642],"type":"Point"}
}