{
  "type": "Feature",
  "properties": {
    "iso:country":"IT",
    "sg:address":"20124 Milano",
    "sg:city":"Milano",
    "sg:orig_category":"Servizi E Lavori Per Edilizia E Lavori Pubblici. Banche E Servizi Finanziari",
    "sg:phone":"+39 02 6749 3283",
    "sg:postcode":"20124",
    "sg:province":"Milano",
    "wof:name":"Sviluppo Franchising Immobiliare S.r.l.",
    "wof:placetype":"venue"
},
  "geometry": {"coordinates":[9.203065,45.483391],"type":"Point"}
}