{
  "type": "Feature",
  "properties": {
    "iso:country":"IT",
    "sg:address":"38069 Torbole Sul Garda",
    "sg:city":"Torbole",
    "sg:orig_category":"Scuole E Servizi Scolastici. Servizi Per Lo Sport E Il Tempo Libero",
    "sg:phone":"+39 0464 506078",
    "sg:postcode":"38069",
    "sg:province":"Trento",
    "wof:name":"3 S Surf Di Reinhard Schneiderhan & C. (s.n.c.)",
    "wof:placetype":"venue"
},
  "geometry": {"coordinates":[10.874689,45.872253],"type":"Point"}
}