{
  "type": "Feature",
  "properties": {
    "addr:full":"Loc. Fiastra62010 Petriolo Macerata 62010",
    "addr:postcode":"62010",
    "addr:street":"Loc. Fiastra62010",
    "iso:country":"IT",
    "sg:address":"Loc. Fiastra62010 Petriolo",
    "sg:classifiers":[
        {
            "category":"Personal",
            "subcategory":"Shoe Repair & Shine",
            "type":"Services"
        }
    ],
    "sg:phone":"+39 0733 550262",
    "sg:postcode":"62010",
    "sg:province":"Macerata",
    "sg:tags":[
        "leather"
    ],
    "wof:name":"Ingom Srl",
    "wof:placetype":"venue"
},
  "geometry": {"coordinates":[13.456262,43.300747],"type":"Point"}
}