{
  "type": "Feature",
  "properties": {
    "iso:country":"IT",
    "sg:address":"20149 Milano",
    "sg:city":"Milano",
    "sg:orig_category":"Servizi E Lavori Per Abbigliamento E Pelletterie",
    "sg:phone":"+39 02 349 2128",
    "sg:postcode":"20149",
    "sg:province":"Milano",
    "wof:name":"Scarpa Geraldina",
    "wof:placetype":"venue"
},
  "geometry": {"coordinates":[9.156144,45.485073],"type":"Point"}
}