{
  "type": "Feature",
  "properties": {
    "iso:country":"IT",
    "sg:address":"24059 Urgnano",
    "sg:city":"Urgnano",
    "sg:orig_category":"Maglierie - Vendita Al Dettaglio",
    "sg:phone":"+39 035 898996",
    "sg:postcode":"24059",
    "sg:province":"Bergamo",
    "sg:website":"http://www.grea.it/maglificiodiurgnano",
    "wof:name":"Maglificio Di Urgnano",
    "wof:placetype":"venue"
},
  "geometry": {"coordinates":[9.704788,45.584267],"type":"Point"}
}