{
  "type": "Feature",
  "properties": {
    "addr:full":"64028 Silvi Silvi Teramo 64028",
    "addr:postcode":"64028;64028",
    "iso:country":"IT",
    "sg:address":"64028 Silvi",
    "sg:city":"Silvi",
    "sg:orig_category":"Associazioni Ed Organismi Di Interesse Pubblico",
    "sg:phone":"+39 085 930071",
    "sg:postcode":"64028",
    "sg:province":"Teramo",
    "wof:name":"S.i.a.e. Societa' Italiana Autori Ed Editori",
    "wof:placetype":"venue"
},
  "geometry": {"coordinates":[14.116326,42.553284],"type":"Point"}
}