{
  "type": "Feature",
  "properties": {
    "addr:full":"00187 Roma Roma Roma 00187",
    "addr:postcode":"00187;00187",
    "iso:country":"IT",
    "sg:address":"00187 Roma",
    "sg:city":"Roma",
    "sg:orig_category":"Arte Ed Artigianato Artistico",
    "sg:phone":"+39 06 320 7735",
    "sg:postcode":"00187",
    "sg:province":"Roma",
    "wof:name":"Venezia Paolo",
    "wof:placetype":"venue"
},
  "geometry": {"coordinates":[12.479874,41.908298],"type":"Point"}
}