{
  "type": "Feature",
  "properties": {
    "addr:full":"36012 Asiago Asiago Vicenza 36012",
    "addr:postcode":"36012;36012",
    "iso:country":"IT",
    "sg:address":"36012 Asiago",
    "sg:city":"Asiago",
    "sg:orig_category":"Prodotti E Manufatti In Materie Plastiche. Materiali Edili",
    "sg:phone":"+39 0424 460121",
    "sg:postcode":"36012",
    "sg:province":"Vicenza",
    "wof:name":"Fast Pur S.r.l. - Societa' Unipersonale",
    "wof:placetype":"venue"
},
  "geometry": {"coordinates":[11.5154294968,45.5282440186],"type":"Point"}
}