{
  "type": "Feature",
  "properties": {
    "iso:country":"IT",
    "sg:address":"22078 Turate",
    "sg:city":"Turate",
    "sg:orig_category":"Gomma Articoli Tecnici - Produzione E Commercio",
    "sg:phone":"+39 02 9675 1661",
    "sg:postcode":"22078",
    "sg:province":"Como",
    "wof:name":"F.c.e. Gomma Srl",
    "wof:placetype":"venue"
},
  "geometry": {"coordinates":[9.00681,45.658146],"type":"Point"}
}