{
  "type": "Feature",
  "properties": {
    "addr:full":"25124 Brescia Brescia Brescia 25124",
    "addr:postcode":"25124;25124",
    "iso:country":"IT",
    "sg:address":"25124 Brescia",
    "sg:city":"Brescia",
    "sg:orig_category":"Forniture Per Edilizia E Lavori Pubblici",
    "sg:phone":"+39 030 354 4360",
    "sg:postcode":"25124",
    "sg:province":"Brescia",
    "wof:name":"Apc Artigian Posa",
    "wof:placetype":"venue"
},
  "geometry": {"coordinates":[9.6142473221,45.6404151917],"type":"Point"}
}