{
  "type": "Feature",
  "properties": {
    "iso:country":"IT",
    "sg:address":"86, Via Damiano Chiesa 38060 Villa Lagarina",
    "sg:city":"Villa Lagarina",
    "sg:classifiers":[
        {
            "category":"Building & Trades",
            "subcategory":"Construction",
            "type":"Services"
        }
    ],
    "sg:phone":"+39 0464 490220",
    "sg:postcode":"38060",
    "sg:province":"Trento",
    "sg:tags":[
        "work",
        "public"
    ],
    "wof:name":"Floragard Vertriebs S.r.l.",
    "wof:placetype":"venue"
},
  "geometry": {"coordinates":[11.029757,45.91465],"type":"Point"}
}