{
  "type": "Feature",
  "properties": {
    "iso:country":"IT",
    "sg:address":"20125 Milano",
    "sg:city":"Milano",
    "sg:orig_category":"Valvole E Apparecchiature Di Misura",
    "sg:phone":"+39 02 6710 0303",
    "sg:postcode":"20125",
    "sg:province":"Milano",
    "wof:name":"Sanital Srl",
    "wof:placetype":"venue"
},
  "geometry": {"coordinates":[9.205371,45.496017],"type":"Point"}
}