{
  "type": "Feature",
  "properties": {
    "iso:country":"IT",
    "sg:address":"55060 Capannori",
    "sg:city":"Capannori",
    "sg:orig_category":"Materiali E Componenti Elettrotecnici",
    "sg:phone":"+39 0583 403388",
    "sg:postcode":"55060",
    "sg:province":"Lucca",
    "wof:name":"Innocenti & Cammelli Spa",
    "wof:placetype":"venue"
},
  "geometry": {"coordinates":[10.511333,43.809525],"type":"Point"}
}