{
  "type": "Feature",
  "properties": {
    "iso:country":"IT",
    "sg:address":"20090 Assago",
    "sg:city":"Assago",
    "sg:orig_category":"Colori, Vernici E Smalti - Produzione E Ingrosso",
    "sg:phone":"+39 02 4570 3145",
    "sg:postcode":"20090",
    "sg:province":"Milano",
    "wof:name":"Cs-interglas Ag",
    "wof:placetype":"venue"
},
  "geometry": {"coordinates":[9.117491,45.409061],"type":"Point"}
}