{
  "type": "Feature",
  "properties": {
    "addr:full":"27, Via Ferri 25010 Borgosatollo Borgosatollo Brescia 25010",
    "addr:postcode":"25010;25010",
    "addr:street":"Via Ferri",
    "iso:country":"IT",
    "sg:address":"27, Via Ferri 25010 Borgosatollo",
    "sg:city":"Borgosatollo",
    "sg:classifiers":[
        {
            "category":"Manufacturing",
            "subcategory":"Rubber & Plastics",
            "type":"Manufacturing & Wholesale Goods"
        }
    ],
    "sg:phone":"+39 030 270 2785",
    "sg:postcode":"25010",
    "sg:province":"Brescia",
    "wof:name":"Garden Plast Di Parissenti & C. (s.n.c.)",
    "wof:placetype":"venue"
},
  "geometry": {"coordinates":[10.2542505264,45.4740905762],"type":"Point"}
}