{
  "type": "Feature",
  "properties": {
    "addr:full":"50052 Certaldo Certaldo Firenze 50052",
    "addr:postcode":"50052;50052",
    "iso:country":"IT",
    "sg:address":"50052 Certaldo",
    "sg:city":"Certaldo",
    "sg:orig_category":"Articoli Da Regalo. Arte Ed Artigianato Artistico. Shopping. Regalistica Aziendale",
    "sg:phone":"+39 0571 666537",
    "sg:postcode":"50052",
    "sg:province":"Firenze",
    "wof:name":"Cioni Cornici Snc Di Cioni Luca & C.",
    "wof:placetype":"venue"
},
  "geometry": {"coordinates":[11.020825,43.570217],"type":"Point"}
}