{
  "type": "Feature",
  "properties": {
    "iso:country":"IT",
    "sg:address":"6, Via Trieste 00040 Pomezia",
    "sg:city":"Pomezia",
    "sg:classifiers":[
        {
            "category":"Manufacturing",
            "subcategory":"Rubber & Plastics",
            "type":"Manufacturing & Wholesale Goods"
        }
    ],
    "sg:phone":"+39 39069121561",
    "sg:postcode":"00040",
    "sg:province":"Roma",
    "wof:name":"I.r.p.p. (s.r.l.)",
    "wof:placetype":"venue"
},
  "geometry": {"coordinates":[12.498559,41.689236],"type":"Point"}
}