{
  "type": "Feature",
  "properties": {
    "iso:country":"IT",
    "sg:address":"Via Delle Industrie 9 30020 Fossalta Di Piave",
    "sg:city":"Fossalta di Piave",
    "sg:classifiers":[
        {
            "category":"Banks & Credit Unions",
            "subcategory":"Investment Brokerage",
            "type":"Services"
        }
    ],
    "sg:phone":"+39 0421 679996",
    "sg:postcode":"30020",
    "sg:province":"Venezia",
    "sg:tags":[
        "fuel",
        "cap",
        "tank"
    ],
    "sg:website":"www.venetaacciai.it",
    "wof:name":"Veneta Acciai Srl",
    "wof:placetype":"venue"
},
  "geometry": {"coordinates":[12.5048885345,45.6499023438],"type":"Point"}
}