{
  "type": "Feature",
  "properties": {
    "addr:full":"1, V. Schiavetti Monfalcone Gorizia 34074",
    "addr:housenumber":"1",
    "addr:postcode":"34074",
    "addr:street":"V. Schiavetti",
    "iso:country":"IT",
    "sg:address":"1, V. Schiavetti",
    "sg:city":"Monfalcone",
    "sg:classifiers":[
        {
            "category":"Shopping",
            "type":"Retail Goods"
        }
    ],
    "sg:phone":"+39 0481 711390",
    "sg:postcode":"34074",
    "sg:province":"Gorizia",
    "sg:tags":[
        "finished",
        "-",
        "metallic"
    ],
    "sg:website":"http://www.officina-apollonio.it",
    "wof:name":"Officina Meccanica G. Apollonio",
    "wof:placetype":"venue"
},
  "geometry": {"coordinates":[13.6215457916,45.9413032532],"type":"Point"}
}