{
  "type": "Feature",
  "properties": {
    "addr:full":"00142 Roma Roma Roma 00142",
    "addr:postcode":"00142;00142",
    "iso:country":"IT",
    "sg:address":"00142 Roma",
    "sg:city":"Roma",
    "sg:orig_category":"Scuole E Servizi Scolastici. Servizi Per Lo Sport E Il Tempo Libero",
    "sg:phone":"+39 06 540 0324",
    "sg:postcode":"00142",
    "sg:province":"Roma",
    "wof:name":"Accademia Musicale Artitalia Ass. Culturale",
    "wof:placetype":"venue"
},
  "geometry": {"coordinates":[12.484946,41.84713],"type":"Point"}
}