{
  "type": "Feature",
  "properties": {
    "iso:country":"IT",
    "sg:address":"10023 Chieri",
    "sg:city":"Chieri",
    "sg:orig_category":"Macchine, Impianti Ed Attrezzature Per Agricoltura E Zootecnia",
    "sg:phone":"+39 011 942 5126",
    "sg:postcode":"10023",
    "sg:province":"Torino",
    "sg:website":"http://www.trasmitec.it",
    "wof:name":"Trasmitec",
    "wof:placetype":"venue"
},
  "geometry": {"coordinates":[7.827914,45.011066],"type":"Point"}
}