{
  "type": "Feature",
  "properties": {
    "iso:country":"IT",
    "sg:address":"18, Via Gavardina Di Sopra 25011 Calcinato",
    "sg:city":"Calcinato",
    "sg:classifiers":[
        {
            "category":"Autos & Motor Vehicles",
            "subcategory":"Automobile Sales",
            "type":"Retail Goods"
        }
    ],
    "sg:phone":"+39 030 996 4204",
    "sg:postcode":"25011",
    "sg:province":"Brescia",
    "sg:tags":[
        "motor-cars"
    ],
    "wof:name":"Carrozzeria Industrialcar S.r.l.",
    "wof:placetype":"venue"
},
  "geometry": {"coordinates":[10.3924484253,45.4756088257],"type":"Point"}
}