{
  "type": "Feature",
  "properties": {
    "iso:country":"IT",
    "sg:address":"39042 Bressanone",
    "sg:city":"Bressanone",
    "sg:orig_category":"Servizi Per Aziende, Manifestazioni E Supporto Agli Scambi Commerciali",
    "sg:phone":"+39 0472 830939",
    "sg:postcode":"39042",
    "sg:province":"Bolzano/Bozen",
    "sg:website":"http://www.plettac-roeder.com",
    "wof:name":"Plettac R\u00d6der Italia Srl",
    "wof:placetype":"venue"
},
  "geometry": {"coordinates":[11.328485,46.502995],"type":"Point"}
}