{
  "type": "Feature",
  "properties": {
    "iso:country":"IT",
    "sg:address":"Via Patini 7 64026 Roseto Degli Abruzzi",
    "sg:city":"Roseto degli Abruzzi",
    "sg:classifiers":[
        {
            "category":"Food & Beverages",
            "subcategory":"Liquor & Beverages",
            "type":"Retail Goods"
        }
    ],
    "sg:phone":"+39 085 899 8226",
    "sg:postcode":"64026",
    "sg:province":"Teramo",
    "sg:tags":[
        "wine",
        "italian"
    ],
    "sg:website":"www.webzone.it/barba",
    "wof:name":"Societa' Agricola Fratelli Barba Srl",
    "wof:placetype":"venue"
},
  "geometry": {"coordinates":[14.004831,42.688187],"type":"Point"}
}