{
  "type": "Feature",
  "properties": {
    "addr:full":"10070 Rocca Canavese Barbania Torino 10070",
    "addr:postcode":"10070;10070",
    "addr:street":"Canavese",
    "iso:country":"IT",
    "sg:address":"10070 Rocca Canavese",
    "sg:city":"Barbania",
    "sg:orig_category":"Motori Ed Organi Di Trasmissione",
    "sg:phone":"+39 011 924 0941",
    "sg:postcode":"10070",
    "sg:province":"Torino",
    "wof:name":"M.e.f.o.m. Snc",
    "wof:placetype":"venue"
},
  "geometry": {"coordinates":[7.5545639992,45.2841758728],"type":"Point"}
}