{
  "type": "Feature",
  "properties": {
    "iso:country":"IT",
    "sg:address":"20121 Milano",
    "sg:city":"Milano",
    "sg:orig_category":"Servizi E Lavori Per Arredamento E Industria Del Legno. Servizi E Lavori Per Edilizia E Lavori Pubblici. Arte Ed Artigianato Artistico",
    "sg:phone":"+39 02 659 8071",
    "sg:postcode":"20121",
    "sg:province":"Milano",
    "wof:name":"Cooperativa Di Solidariet\u00c0 Sociale S. Marco",
    "wof:placetype":"venue"
},
  "geometry": {"coordinates":[9.187876,45.47348],"type":"Point"}
}