{
  "type": "Feature",
  "properties": {
    "iso:country":"IT",
    "sg:address":"24040 Bottanuco",
    "sg:city":"Bottanuco",
    "sg:orig_category":"Macchine, Impianti Ed Attrezzature Per Industria Alimentare E Bevande",
    "sg:phone":"+39 035 499 2010",
    "sg:postcode":"24040",
    "sg:province":"Bergamo",
    "sg:website":"http://www.valko.com",
    "wof:name":"Valko Srl",
    "wof:placetype":"venue"
},
  "geometry": {"coordinates":[9.514165,45.642937],"type":"Point"}
}