{
  "type": "Feature",
  "properties": {
    "iso:country":"IT",
    "sg:address":"22040 Anzano Del Parco",
    "sg:city":"Anzano del Parco",
    "sg:orig_category":"Arredi Ed Attrezzature Per Attivita' Commerciali Ed Artigianali",
    "sg:phone":"+39 031 630298",
    "sg:postcode":"22040",
    "sg:province":"Como",
    "wof:name":"Cappellini Srl",
    "wof:placetype":"venue"
},
  "geometry": {"coordinates":[9.223866,45.757401],"type":"Point"}
}