{
  "type": "Feature",
  "properties": {
    "iso:country":"IT",
    "sg:address":"22060 Figino Serenza",
    "sg:city":"Figino Serenza",
    "sg:orig_category":"Servizi E Lavori Per Arredamento E Industria Del Legno. Arte Ed Artigianato Artistico",
    "sg:phone":"+39 031 790568",
    "sg:postcode":"22060",
    "sg:province":"Como",
    "wof:name":"Livio Claudio",
    "wof:placetype":"venue"
},
  "geometry": {"coordinates":[9.121887,45.733246],"type":"Point"}
}