{
  "type": "Feature",
  "properties": {
    "iso:country":"IT",
    "sg:address":"07026 Olbia",
    "sg:city":"Olbia",
    "sg:orig_category":"Carni, Salumi E Pesci",
    "sg:phone":"+39 0789 66084",
    "sg:postcode":"07026",
    "sg:province":"Olbia-Tempio",
    "wof:name":"Calvisi Giovanni & C. Snc",
    "wof:placetype":"venue"
},
  "geometry": {"coordinates":[9.278559,40.826839],"type":"Point"}
}