{
  "type": "Feature",
  "properties": {
    "addr:full":"36/38, Via Mura Rotta 35013 Cittadella Cittadella Padova 35013",
    "addr:housenumber":"36 / 38",
    "addr:postcode":"35013;35013",
    "addr:street":"Via Mura Rotta",
    "iso:country":"IT",
    "sg:address":"36/38, Via Mura Rotta 35013 Cittadella",
    "sg:city":"Cittadella",
    "sg:classifiers":[
        {
            "category":"Personal",
            "subcategory":"Shoe Repair & Shine",
            "type":"Services"
        }
    ],
    "sg:phone":"+39 049 597 1333",
    "sg:postcode":"35013",
    "sg:province":"Padova",
    "sg:tags":[
        "leather"
    ],
    "wof:name":"Ortopedia Cittadellese Laboratorio Di Faggin & C. (s.n.c.)",
    "wof:placetype":"venue"
},
  "geometry": {"coordinates":[11.8765888214,45.4095687866],"type":"Point"}
}