{
  "type": "Feature",
  "properties": {
    "iso:country":"IT",
    "sg:address":"Via Colli Aminei, 293; Napoli; 80100",
    "sg:classifiers":[
        {
            "category":"Banks & Credit Unions",
            "subcategory":"Bank",
            "type":"Services"
        }
    ],
    "sg:phone":"+39 081 741 8901",
    "wof:name":"Banca Sannitica",
    "wof:placetype":"venue"
},
  "geometry": {"coordinates":[14.237847,40.87019],"type":"Point"}
}