{
  "type": "Feature",
  "properties": {
    "iso:country":"IT",
    "sg:address":"60, Via Ferrante Franco 81100 Caserta",
    "sg:city":"Caserta",
    "sg:classifiers":[
        {
            "category":"Shopping",
            "subcategory":"Clothing, Apparel, & Fashions",
            "type":"Retail Goods"
        }
    ],
    "sg:phone":"+39 0823 325105",
    "sg:postcode":"81100",
    "sg:province":"Caserta",
    "sg:tags":[
        "clothes"
    ],
    "wof:name":"Olivieri",
    "wof:placetype":"venue"
},
  "geometry": {"coordinates":[14.330421,41.073074],"type":"Point"}
}