{
  "type": "Feature",
  "properties": {
    "iso:country":"IT",
    "sg:address":"20010 Ossona",
    "sg:city":"Ossona",
    "sg:orig_category":"Bevande, Vini E Liquori",
    "sg:phone":"+39 02 9038 1010",
    "sg:postcode":"20010",
    "sg:province":"Milano",
    "wof:name":"Nexus Company Srl",
    "wof:placetype":"venue"
},
  "geometry": {"coordinates":[8.901443,45.506695],"type":"Point"}
}