{
  "type": "Feature",
  "properties": {
    "addr:full":"24023 Clusone Clusone Bergamo 24023",
    "addr:postcode":"24023;24023",
    "iso:country":"IT",
    "sg:address":"24023 Clusone",
    "sg:city":"Clusone",
    "sg:orig_category":"Impiantistica E Prodotti Tecnologici Per Edilizia. Climatizzazione E Condizionamento, Apparecchiature E Servizi",
    "sg:phone":"+39 0346 21417",
    "sg:postcode":"24023",
    "sg:province":"Bergamo",
    "wof:name":"Aerotermica Bergamasca Srl",
    "wof:placetype":"venue"
},
  "geometry": {"coordinates":[9.936003,45.888203],"type":"Point"}
}