{
  "type": "Feature",
  "properties": {
    "addr:full":"Via Marchesi De Taddei Malachia 16 20146 Milano Milano Milano 20146",
    "addr:housenumber":"16",
    "addr:postcode":"20146;20146",
    "addr:street":"Via Marchesi De Taddei Malachia",
    "iso:country":"IT",
    "sg:address":"Via Marchesi De Taddei Malachia 16 20146 Milano",
    "sg:city":"Milano",
    "sg:classifiers":[
        {
            "category":"Banks & Credit Unions",
            "subcategory":"Investment Brokerage",
            "type":"Services"
        }
    ],
    "sg:phone":"+39 02 436712",
    "sg:postcode":"20146",
    "sg:province":"Milano",
    "sg:tags":[
        "product",
        "hair-care"
    ],
    "sg:website":"www.melanton.it",
    "wof:name":"Nor-man's Center Srl",
    "wof:placetype":"venue"
},
  "geometry": {"coordinates":[9.150641,45.461971],"type":"Point"}
}