{
  "type": "Feature",
  "properties": {
    "iso:country":"IT",
    "sg:address":"Localita' Terra Padedda 08020 San Teodoro",
    "sg:classifiers":[
        {
            "category":"Building & Trades",
            "subcategory":"Construction",
            "type":"Services"
        }
    ],
    "sg:phone":"+39 0784 865166",
    "sg:postcode":"08020",
    "sg:province":"Nuoro",
    "sg:tags":[
        "work",
        "public"
    ],
    "wof:name":"S. Simone - S. Teodoro S.c.a R.l.",
    "wof:placetype":"venue"
},
  "geometry": {"coordinates":[9.330436,40.321007],"type":"Point"}
}