{
  "type": "Feature",
  "properties": {
    "iso:country":"IT",
    "sg:address":"20092 Cinisello Balsamo",
    "sg:city":"Cinisello Balsamo",
    "sg:orig_category":"Macchine E Forniture Per Ecologia E Smaltimento Rifiuti. Macchine, Strumenti Ed Apparecchi Per Attivita' Industriali",
    "sg:phone":"+39 02 612 8031",
    "sg:postcode":"20092",
    "sg:province":"Milano",
    "sg:website":"http://www.dierresrl.com",
    "wof:name":"Dierre Srl",
    "wof:placetype":"venue"
},
  "geometry": {"coordinates":[9.230933,45.565273],"type":"Point"}
}