{
  "type": "Feature",
  "properties": {
    "iso:country":"IT",
    "sg:address":"30174 Mestre",
    "sg:city":"Mestre",
    "sg:orig_category":"Servizi Vari Di Interesse Pubblico",
    "sg:phone":"+39 041 912786",
    "sg:postcode":"30174",
    "sg:province":"Venezia",
    "wof:name":"Istituto Dott. Prof. Bogatti",
    "wof:placetype":"venue"
},
  "geometry": {"coordinates":[12.217063,45.487366],"type":"Point"}
}