{
  "type": "Feature",
  "properties": {
    "addr:full":"20123 Milano Milano Milano 20123",
    "addr:postcode":"20123;20123",
    "iso:country":"IT",
    "sg:address":"20123 Milano",
    "sg:city":"Milano",
    "sg:orig_category":"Macchine E Forniture Per Industria Orafa E Per Orologeria",
    "sg:phone":"+39 02 7200 8127",
    "sg:postcode":"20123",
    "sg:province":"Milano",
    "wof:name":"Arnoldi Virginio",
    "wof:placetype":"venue"
},
  "geometry": {"coordinates":[9.185205,45.461296],"type":"Point"}
}