{
  "type": "Feature",
  "properties": {
    "iso:country":"IT",
    "sg:address":"20063 Cernusco Sul Naviglio",
    "sg:city":"Cernusco sul Naviglio",
    "sg:orig_category":"Elettrotecnica Industriale, Prodotti E Apparecchiature. Elettrotecnica Professionale E Di Consumo",
    "sg:phone":"+39 02 927281",
    "sg:postcode":"20063",
    "sg:province":"Milano",
    "sg:website":"http://www.kiepeelectric.com",
    "wof:name":"Kiepe Electric Spa",
    "wof:placetype":"venue"
},
  "geometry": {"coordinates":[9.340194,45.519463],"type":"Point"}
}