{
  "type": "Feature",
  "properties": {
    "addr:full":"00141 Roma Roma Roma 00141",
    "addr:postcode":"00141;00141",
    "iso:country":"IT",
    "sg:address":"00141 Roma",
    "sg:city":"Roma",
    "sg:orig_category":"Scuole E Servizi Scolastici. Servizi Per Lo Sport E Il Tempo Libero",
    "sg:phone":"+39 06 817 4150",
    "sg:postcode":"00141",
    "sg:province":"Roma",
    "wof:name":"Scuole Di Musica Geofonia",
    "wof:placetype":"venue"
},
  "geometry": {"coordinates":[12.532671,41.939144],"type":"Point"}
}