{
  "type": "Feature",
  "properties": {
    "iso:country":"IT",
    "sg:address":"40053 Bazzano",
    "sg:city":"Bazzano",
    "sg:orig_category":"Prodotti Alimentari",
    "sg:phone":"+39 051 835511",
    "sg:postcode":"40053",
    "sg:province":"Bologna",
    "wof:name":"The Lorenz Bahlsen Snack-world S.r.l. Italy",
    "wof:placetype":"venue"
},
  "geometry": {"coordinates":[11.0679912567,44.5114135742],"type":"Point"}
}