{
  "type": "Feature",
  "properties": {
    "addr:full":"26, Via Rossa Guido 35020 Ponte San Nicolo' Padova 35020",
    "addr:postcode":"35020;35020",
    "addr:street":"Via Rossa Guido;Nicolo ' Padova",
    "iso:country":"IT",
    "sg:address":"26, Via Rossa Guido 35020 Ponte San Nicolo'",
    "sg:classifiers":[
        {
            "category":"Professional",
            "subcategory":"Business Services",
            "type":"Services"
        }
    ],
    "sg:phone":"+39 049 896 8311",
    "sg:postcode":"35020",
    "sg:province":"Padova",
    "sg:tags":[
        "advice"
    ],
    "wof:name":"Soluzioni Software (s.r.l.)",
    "wof:placetype":"venue"
},
  "geometry": {"coordinates":[11.913318,45.375839],"type":"Point"}
}