{
  "type": "Feature",
  "properties": {
    "iso:country":"IT",
    "sg:address":"25036 Palazzolo Sull'oglio",
    "sg:orig_category":"Punzonatrici E Punzoni",
    "sg:phone":"+39 030 730 1804",
    "sg:postcode":"25036",
    "sg:province":"Brescia",
    "wof:name":"Omac Snc Di Piensi A. & Belometti Emilio",
    "wof:placetype":"venue"
},
  "geometry": {"coordinates":[9.8911876678,45.5941009521],"type":"Point"}
}