{
  "type": "Feature",
  "properties": {
    "iso:country":"IT",
    "sg:address":"41033 Concordia Sulla Secchia",
    "sg:city":"Concordia sulla Secchia",
    "sg:orig_category":"Filati E Materie Prime Tessili",
    "sg:phone":"+39 0535 43411",
    "sg:postcode":"41033",
    "sg:province":"Modena",
    "wof:name":"Cucirini Rama Srl",
    "wof:placetype":"venue"
},
  "geometry": {"coordinates":[10.9944753647,44.9054870605],"type":"Point"}
}