{
  "type": "Feature",
  "properties": {
    "iso:country":"IT",
    "sg:address":"33087 Pasiano Di Pordenone",
    "sg:city":"Pasiano",
    "sg:orig_category":"Cucine Componibili",
    "sg:phone":"+39 0434 614911",
    "sg:postcode":"33087",
    "sg:province":"Pordenone",
    "sg:website":"http://www.msg.it",
    "wof:name":"Meson's Cucine Spa",
    "wof:placetype":"venue"
},
  "geometry": {"coordinates":[12.625946,45.861622],"type":"Point"}
}