{
  "type": "Feature",
  "properties": {
    "iso:country":"IT",
    "sg:address":"41100 Modena",
    "sg:city":"Modena",
    "sg:orig_category":"Frigotecnica, Apparecchiature E Servizi",
    "sg:phone":"+39 059 311111",
    "sg:postcode":"41100",
    "sg:province":"Modena",
    "wof:name":"Casagrande Mauro",
    "wof:placetype":"venue"
},
  "geometry": {"coordinates":[10.9177236557,44.6390953064],"type":"Point"}
}