{
  "type": "Feature",
  "properties": {
    "addr:full":"25131 Brescia Brescia Brescia 25131",
    "addr:postcode":"25131;25131",
    "iso:country":"IT",
    "sg:address":"25131 Brescia",
    "sg:city":"Brescia",
    "sg:orig_category":"Apparecchiature Oleodinamiche",
    "sg:phone":"+39 030 358 3533",
    "sg:postcode":"25131",
    "sg:province":"Brescia",
    "sg:website":"http://www.go-fluid.com",
    "wof:name":"Vortal Spa",
    "wof:placetype":"venue"
},
  "geometry": {"coordinates":[10.176337,45.489475],"type":"Point"}
}