{
  "type": "Feature",
  "properties": {
    "iso:country":"IT",
    "sg:address":"48, Via Tonale 24026 Leffe",
    "sg:city":"Leffe",
    "sg:classifiers":[
        {
            "category":"Manufacturing",
            "subcategory":"Paper Products",
            "type":"Manufacturing & Wholesale Goods"
        }
    ],
    "sg:phone":"+39 39035733335",
    "sg:postcode":"24026",
    "sg:province":"Bergamo",
    "sg:tags":[
        "cardboard"
    ],
    "wof:name":"I.g.t. Imballaggi Grafici Tecnici Di Mosconi Ferdinando & C. (s.a.s.)",
    "wof:placetype":"venue"
},
  "geometry": {"coordinates":[9.8781938553,45.7976493835],"type":"Point"}
}