{
  "type": "Feature",
  "properties": {
    "addr:full":"20131 Milano Milano Milano 20131",
    "addr:postcode":"20131;20131",
    "iso:country":"IT",
    "sg:address":"20131 Milano",
    "sg:city":"Milano",
    "sg:orig_category":"Servizi Per Lo Sport E Il Tempo Libero. Servizi Al Turismo",
    "sg:phone":"+39 02 7063 0415",
    "sg:postcode":"20131",
    "sg:province":"Milano",
    "wof:name":"Ironman Nutrition Snc Di Bolognini Sara E Davanzo Andrea",
    "wof:placetype":"venue"
},
  "geometry": {"coordinates":[9.235739,45.485168],"type":"Point"}
}