{
  "type": "Feature",
  "properties": {
    "iso:country":"IT",
    "sg:address":"39023 Lasa",
    "sg:city":"Lasa",
    "sg:orig_category":"Elettricisti",
    "sg:phone":"+39 0473 739938",
    "sg:postcode":"39023",
    "sg:province":"Bolzano/Bozen",
    "wof:name":"Electro Peer Snc Di Peer Otto & C.",
    "wof:placetype":"venue"
},
  "geometry": {"coordinates":[11.358005,46.496716],"type":"Point"}
}