{
  "type": "Feature",
  "properties": {
    "addr:full":"Via Grazia Deledda, 10/12 90039 Villabate Villabate Palermo 90039",
    "addr:housenumber":"10 / 12",
    "addr:postcode":"90039;90039",
    "addr:street":"Via Grazia Deledda",
    "iso:country":"IT",
    "sg:address":"Via Grazia Deledda, 10/12 90039 Villabate",
    "sg:city":"Villabate",
    "sg:classifiers":[
        {
            "category":"Manufacturing",
            "subcategory":"Food",
            "type":"Manufacturing & Wholesale Goods"
        }
    ],
    "sg:phone":"+39 091 492336",
    "sg:postcode":"90039",
    "sg:province":"Palermo",
    "sg:tags":[
        "frozen"
    ],
    "wof:name":"Bonagel Di Francesca Paola Bonura E Giovanni Napoli S.n.c.",
    "wof:placetype":"venue"
},
  "geometry": {"coordinates":[13.4426364899,38.0760650635],"type":"Point"}
}