{
  "type": "Feature",
  "properties": {
    "iso:country":"IT",
    "sg:address":"55100 Lucca",
    "sg:city":"Lucca",
    "sg:classifiers":[
        {
            "category":"Banks & Credit Unions",
            "subcategory":"Investment Brokerage",
            "type":"Services"
        }
    ],
    "sg:phone":"+39 0583 492755",
    "sg:postcode":"55100",
    "sg:province":"Lucca",
    "sg:tags":[
        "parrucchieri",
        "per",
        "donna"
    ],
    "wof:name":"Di.vi. Coiffeurs Snc",
    "wof:placetype":"venue"
},
  "geometry": {"coordinates":[10.5119304657,43.8429222107],"type":"Point"}
}