{
  "type": "Feature",
  "properties": {
    "addr:full":"22026 Maslianico Maslianico Como 22026",
    "addr:postcode":"22026;22026",
    "iso:country":"IT",
    "sg:address":"22026 Maslianico",
    "sg:city":"Maslianico",
    "sg:orig_category":"Servizi Editoriali",
    "sg:phone":"+39 031 341069",
    "sg:postcode":"22026",
    "sg:province":"Como",
    "wof:name":"Sedigraf (soc.coop.r.l.)",
    "wof:placetype":"venue"
},
  "geometry": {"coordinates":[9.041964,45.84198],"type":"Point"}
}