{
  "type": "Feature",
  "properties": {
    "addr:full":"192, Viale Testi Fulvio 20092 Cinisello Balsamo Cinisello Balsamo Milano 20092",
    "addr:postcode":"20092;20092",
    "addr:street":"Viale Testi Fulvio",
    "iso:country":"IT",
    "sg:address":"192, Viale Testi Fulvio 20092 Cinisello Balsamo",
    "sg:city":"Cinisello Balsamo",
    "sg:classifiers":[
        {
            "category":"Manufacturing",
            "subcategory":"Motor Vehicles & Parts",
            "type":"Manufacturing & Wholesale Goods"
        }
    ],
    "sg:phone":"+39 39022487621",
    "sg:postcode":"20092",
    "sg:province":"Milano",
    "sg:tags":[
        "engine"
    ],
    "wof:name":"Sicc Regina (s.r.l.)",
    "wof:placetype":"venue"
},
  "geometry": {"coordinates":[9.228541,45.546303],"type":"Point"}
}