{
  "type": "Feature",
  "properties": {
    "addr:full":"4, Via Cirillo Bassi 40010 Galliera Bologna 40010",
    "addr:postcode":"40010 galliera;40010",
    "addr:street":"Via Cirillo Bassi",
    "iso:country":"IT",
    "sg:address":"4, Via Cirillo Bassi 40010 Galliera",
    "sg:classifiers":[
        {
            "category":"Shopping",
            "type":"Retail Goods"
        }
    ],
    "sg:phone":"+39 39051812032",
    "sg:postcode":"40010",
    "sg:province":"Bologna",
    "sg:tags":[
        "finished",
        "-",
        "metallic"
    ],
    "wof:name":"M.d.m. (s.r.l.)",
    "wof:placetype":"venue"
},
  "geometry": {"coordinates":[11.3464813232,44.4942207336],"type":"Point"}
}