{
  "type": "Feature",
  "properties": {
    "iso:country":"IT",
    "sg:address":"20099 Sesto San Giovanni",
    "sg:city":"Sesto San Giovanni",
    "sg:orig_category":"Forniture Per Uffici",
    "sg:phone":"+39 02 240 5651",
    "sg:postcode":"20099",
    "sg:province":"Milano",
    "wof:name":"Johnson Roltelex Srl",
    "wof:placetype":"venue"
},
  "geometry": {"coordinates":[9.2341241837,45.5452690125],"type":"Point"}
}