{
  "type": "Feature",
  "properties": {
    "iso:country":"IT",
    "sg:address":"Viale Dell'industria 40 21052 Busto Arsizio",
    "sg:city":"Busto Arsizio",
    "sg:classifiers":[
        {
            "category":"Wholesale",
            "subcategory":"Vending Machines",
            "type":"Manufacturing & Wholesale Goods"
        }
    ],
    "sg:phone":"+39 0331 351175",
    "sg:postcode":"21052",
    "sg:province":"Varese",
    "sg:tags":[
        "lining"
    ],
    "sg:website":"www.mpengineering.com",
    "wof:name":"M.p. Engineering Srl",
    "wof:placetype":"venue"
},
  "geometry": {"coordinates":[8.829494,45.58918],"type":"Point"}
}