{
  "type": "Feature",
  "properties": {
    "iso:country":"IT",
    "sg:address":"10154 Torino",
    "sg:city":"Torino",
    "sg:classifiers":[
        {
            "category":"Banks & Credit Unions",
            "subcategory":"Investment Brokerage",
            "type":"Services"
        }
    ],
    "sg:phone":"+39 011 242 2255",
    "sg:postcode":"10154",
    "sg:province":"Torino",
    "sg:tags":[
        "vehicles",
        "auxiliary",
        "motor"
    ],
    "wof:name":"Mint Di Alessio Francone",
    "wof:placetype":"venue"
},
  "geometry": {"coordinates":[7.7052650452,45.0957145691],"type":"Point"}
}