{
  "type": "Feature",
  "properties": {
    "iso:country":"IT",
    "sg:address":"47100 Forli'",
    "sg:orig_category":"Legno E Semilavorati",
    "sg:phone":"+39 0543 725575",
    "sg:postcode":"47100",
    "sg:province":"Forl\u00ec-Cesena",
    "wof:name":"Parlanti Srl",
    "wof:placetype":"venue"
},
  "geometry": {"coordinates":[12.05715,44.225655],"type":"Point"}
}