{
  "type": "Feature",
  "properties": {
    "addr:full":"00040 Pomezia Pomezia Roma 00040",
    "addr:postcode":"00040;roma 00040",
    "iso:country":"IT",
    "sg:address":"00040 Pomezia",
    "sg:city":"Pomezia",
    "sg:orig_category":"Servizi Vari Di Interesse Pubblico",
    "sg:phone":"+39 338 560 7299",
    "sg:postcode":"00040",
    "sg:province":"Roma",
    "wof:name":"S & S",
    "wof:placetype":"venue"
},
  "geometry": {"coordinates":[12.474644,41.931179],"type":"Point"}
}