{
  "type": "Feature",
  "properties": {
    "iso:country":"IT",
    "sg:address":"10141 Torino",
    "sg:city":"Torino",
    "sg:orig_category":"Scuole E Servizi Scolastici. Centri Di Estetica E Cosmesi E Servizi. Ricerca, Selezione E Formazione Del Personale",
    "sg:phone":"+39 011 337608",
    "sg:postcode":"10141",
    "sg:province":"Torino",
    "wof:name":"Istituto G. Resy",
    "wof:placetype":"venue"
},
  "geometry": {"coordinates":[7.646844,45.070194],"type":"Point"}
}