{
  "type": "Feature",
  "properties": {
    "addr:full":"81011 Alife Alife Caserta 81011",
    "addr:postcode":"81011;81011",
    "iso:country":"IT",
    "sg:address":"81011 Alife",
    "sg:city":"Alife",
    "sg:orig_category":"Cartotecnica E Servizi. Forniture Per Attivita' Commerciali Ed Artigianali",
    "sg:phone":"+39 0823 918234",
    "sg:postcode":"81011",
    "sg:province":"Caserta",
    "wof:name":"Cartiera Del Torano Omniafiltra (s.p.a.)",
    "wof:placetype":"venue"
},
  "geometry": {"coordinates":[14.344279,41.324829],"type":"Point"}
}