{
  "type": "Feature",
  "properties": {
    "iso:country":"IT",
    "sg:address":"12012 Boves",
    "sg:city":"Boves",
    "sg:orig_category":"Apparecchiature Ed Attrezzature Meccaniche",
    "sg:phone":"+39 0171 380614",
    "sg:postcode":"12012",
    "sg:province":"Cuneo",
    "wof:name":"Giordanengo Stefano",
    "wof:placetype":"venue"
},
  "geometry": {"coordinates":[7.560186,44.332539],"type":"Point"}
}