{
  "type": "Feature",
  "properties": {
    "addr:full":"Via Brenta 5; Siracusa; 96010 Siracusa 96010",
    "addr:housenumber":"5",
    "addr:postcode":"96010;96010",
    "addr:street":"Via Brenta",
    "iso:country":"IT",
    "sg:address":"Via Brenta 5; Siracusa; 96010",
    "sg:classifiers":[
        {
            "category":"Banks & Credit Unions",
            "subcategory":"Bank",
            "type":"Services"
        }
    ],
    "sg:phone":"+39 0931 461508",
    "sg:postcode":"96010",
    "sg:province":"Siracusa",
    "wof:name":"Banca Popolare Santa Venera",
    "wof:placetype":"venue"
},
  "geometry": {"coordinates":[15.284086,37.068954],"type":"Point"}
}