{
  "type": "Feature",
  "properties": {
    "iso:country":"IT",
    "sg:address":"Via Francesca Sud 1204 51036 Larciano",
    "sg:city":"Larciano",
    "sg:classifiers":[
        {
            "category":"Manufacturing",
            "subcategory":"Textiles",
            "type":"Manufacturing & Wholesale Goods"
        }
    ],
    "sg:phone":"+39 0573 84086",
    "sg:postcode":"51036",
    "sg:province":"Pistoia",
    "sg:tags":[
        "blended",
        "yarn"
    ],
    "wof:name":"Manifattura Toscana Filati Srl",
    "wof:placetype":"venue"
},
  "geometry": {"coordinates":[10.918524,43.932156],"type":"Point"}
}