{
  "type": "Feature",
  "properties": {
    "iso:country":"IT",
    "sg:address":"71036 Lucera",
    "sg:city":"Lucera",
    "sg:orig_category":"Materiali Semilavorati Metallici",
    "sg:phone":"+39 0881 529377",
    "sg:postcode":"71036",
    "sg:province":"Foggia",
    "wof:name":"Elema (s.r.l.)",
    "wof:placetype":"venue"
},
  "geometry": {"coordinates":[15.359957,41.47551],"type":"Point"}
}