{
  "type": "Feature",
  "properties": {
    "addr:full":"20064 Gorgonzola Gorgonzola Milano 20064",
    "addr:postcode":"20064;20064",
    "iso:country":"IT",
    "sg:address":"20064 Gorgonzola",
    "sg:city":"Gorgonzola",
    "sg:orig_category":"Pietre Dure Semipreziose",
    "sg:phone":"+39 02 9530 1040",
    "sg:postcode":"20064",
    "sg:province":"Milano",
    "wof:name":"L'eta' Della Pietra Snc",
    "wof:placetype":"venue"
},
  "geometry": {"coordinates":[9.4097528458,45.5302658081],"type":"Point"}
}