{
  "type": "Feature",
  "properties": {
    "addr:full":"37059 Perzacco Perzacco Verona 37059",
    "addr:postcode":"37059;37059",
    "addr:street":"Perzacco",
    "iso:country":"IT",
    "sg:address":"37059 Perzacco",
    "sg:city":"Perzacco",
    "sg:classifiers":[
        {
            "category":"Health Services",
            "subcategory":"Health Practitioner",
            "type":"Services"
        }
    ],
    "sg:phone":"+39 045 787 5175",
    "sg:postcode":"37059",
    "sg:province":"Verona",
    "sg:tags":[
        "medici"
    ],
    "wof:name":"Mischi Eros",
    "wof:placetype":"venue"
},
  "geometry": {"coordinates":[11.189233,45.364063],"type":"Point"}
}