{
  "type": "Feature",
  "properties": {
    "iso:country":"IT",
    "sg:address":"Via Mantegna 6, 20154 Milan, Mi",
    "sg:classifiers":[
        {
            "category":"Banks & Credit Unions",
            "subcategory":"Bank",
            "type":"Services"
        }
    ],
    "sg:postcode":"20154",
    "sg:province":"Milano",
    "wof:name":"Monte Titoli Spa",
    "wof:placetype":"venue"
},
  "geometry": {"coordinates":[9.168411,45.483055],"type":"Point"}
}