{
  "type": "Feature",
  "properties": {
    "iso:country":"IT",
    "sg:address":"Via Cavallera 1 24060 Telgate",
    "sg:city":"Telgate",
    "sg:classifiers":[
        {
            "category":"Home & Garden",
            "subcategory":"Building Materials",
            "type":"Retail Goods"
        }
    ],
    "sg:phone":"+39 035 830555",
    "sg:postcode":"24060",
    "sg:province":"Bergamo",
    "sg:tags":[
        "slab",
        "marble"
    ],
    "sg:website":"www.marmiorobici.it",
    "wof:name":"Marmi Orobici Graniti Spa",
    "wof:placetype":"venue"
},
  "geometry": {"coordinates":[9.807305,45.632359],"type":"Point"}
}