{
  "type": "Feature",
  "properties": {
    "iso:country":"IT",
    "sg:address":"10142 Torino",
    "sg:city":"Torino",
    "sg:orig_category":"Autodemolizioni",
    "sg:phone":"+39 011 704985",
    "sg:postcode":"10142",
    "sg:province":"Torino",
    "wof:name":"Autodemolizioni Morelli",
    "wof:placetype":"venue"
},
  "geometry": {"coordinates":[7.606139,45.064495],"type":"Point"}
}