{
  "type": "Feature",
  "properties": {
    "addr:full":"24, Via Madonna Del Piave 32020 Lentiai Lentiai Belluno 32020",
    "addr:postcode":"32020;32020",
    "addr:street":"Via Madonna Del Piave",
    "iso:country":"IT",
    "sg:address":"24, Via Madonna Del Piave 32020 Lentiai",
    "sg:city":"Lentiai",
    "sg:classifiers":[
        {
            "category":"Shopping",
            "type":"Retail Goods"
        }
    ],
    "sg:phone":"+39 0437 751209",
    "sg:postcode":"32020",
    "sg:province":"Belluno",
    "sg:tags":[
        "finished",
        "-",
        "metallic"
    ],
    "wof:name":"Metallurgie Industriali Vincenzo",
    "wof:placetype":"venue"
},
  "geometry": {"coordinates":[11.9977016449,46.0295600891],"type":"Point"}
}