{
  "type": "Feature",
  "properties": {
    "iso:country":"IT",
    "sg:address":"73, Via Levate 24044 Dalmine",
    "sg:city":"Dalmine",
    "sg:classifiers":[
        {
            "category":"Professional",
            "subcategory":"Engineering",
            "type":"Services"
        }
    ],
    "sg:phone":"+39 39035370850",
    "sg:postcode":"24044",
    "sg:province":"Bergamo",
    "sg:tags":[
        "machine",
        "-",
        "mechanical"
    ],
    "wof:name":"Welding Export - Srl",
    "wof:placetype":"venue"
},
  "geometry": {"coordinates":[9.616766,45.637287],"type":"Point"}
}