{
  "type": "Feature",
  "properties": {
    "iso:country":"IT",
    "sg:address":"74015 Martina Franca",
    "sg:city":"Martina Franca",
    "sg:classifiers":[
        {
            "category":"Manufacturing",
            "subcategory":"Leather Goods",
            "type":"Manufacturing & Wholesale Goods"
        }
    ],
    "sg:phone":"+39 080 485 5278",
    "sg:postcode":"74015",
    "sg:province":"Taranto",
    "sg:tags":[
        "goods",
        "clothing",
        "supply"
    ],
    "wof:name":"De.sa. International Srl",
    "wof:placetype":"venue"
},
  "geometry": {"coordinates":[17.313931,40.701206],"type":"Point"}
}