{
  "type": "Feature",
  "properties": {
    "addr:full":"Via Oglio 22 59013 Montemurlo Montemurlo Prato 59013",
    "addr:housenumber":"22",
    "addr:postcode":"59013;59013",
    "addr:street":"Via Oglio",
    "iso:country":"IT",
    "sg:address":"Via Oglio 22 59013 Montemurlo",
    "sg:city":"Montemurlo",
    "sg:classifiers":[
        {
            "category":"Shopping",
            "subcategory":"Clothing, Apparel, & Fashions",
            "type":"Retail Goods"
        }
    ],
    "sg:phone":"+39 0574 682520",
    "sg:postcode":"59013",
    "sg:province":"Prato",
    "sg:tags":[
        "clothing",
        "fabric"
    ],
    "wof:name":"Chiarugitex Di Chiarugi Ombretta",
    "wof:placetype":"venue"
},
  "geometry": {"coordinates":[11.023872,43.913242],"type":"Point"}
}