{
  "type": "Feature",
  "properties": {
    "iso:country":"IT",
    "sg:address":"22100 Como",
    "sg:city":"Como",
    "sg:orig_category":"Forniture Per Attivita' Commerciali Ed Artigianali",
    "sg:phone":"+39 031 591233",
    "sg:postcode":"22100",
    "sg:province":"Como",
    "wof:name":"Asco Snc",
    "wof:placetype":"venue"
},
  "geometry": {"coordinates":[9.0927476883,45.799282074],"type":"Point"}
}