{
  "type": "Feature",
  "properties": {
    "addr:full":"16158 Genova Genova Genova 16158",
    "addr:postcode":"16158;16158",
    "iso:country":"IT",
    "sg:address":"16158 Genova",
    "sg:city":"Genova",
    "sg:orig_category":"Scuole E Servizi Scolastici. Ospedali E Servizi Sanitari",
    "sg:phone":"+39 010 619 7782",
    "sg:postcode":"16158",
    "sg:province":"Genova",
    "wof:name":"Casa Del S. Bambino Soc. Mutua Coop. A.r.l.",
    "wof:placetype":"venue"
},
  "geometry": {"coordinates":[8.74408,44.429359],"type":"Point"}
}