{
  "type": "Feature",
  "properties": {
    "iso:country":"IT",
    "sg:address":"33081 Aviano",
    "sg:city":"Aviano",
    "sg:orig_category":"Servizi E Lavori Per Edilizia E Lavori Pubblici",
    "sg:phone":"+39 0434 657112",
    "sg:postcode":"33081",
    "sg:province":"Pordenone",
    "wof:name":"Z.f. Snc",
    "wof:placetype":"venue"
},
  "geometry": {"coordinates":[12.653152,46.067051],"type":"Point"}
}