{
  "type": "Feature",
  "properties": {
    "iso:country":"IT",
    "sg:address":"05100 Terni",
    "sg:city":"Terni",
    "sg:orig_category":"Servizi E Lavori Per Arredamento E Industria Del Legno. Servizi E Lavori Per Edilizia E Lavori Pubblici. Arte Ed Artigianato Artistico",
    "sg:phone":"+39 0744 441105",
    "sg:postcode":"05100",
    "sg:province":"Terni",
    "sg:website":"http://www.iter.cc",
    "wof:name":"Iter Snc Di Nitti Paola & C.",
    "wof:placetype":"venue"
},
  "geometry": {"coordinates":[12.65811,42.568134],"type":"Point"}
}