{
  "type": "Feature",
  "properties": {
    "iso:country":"IT",
    "sg:address":"26030 Volongo",
    "sg:city":"Volongo",
    "sg:orig_category":"Carpenterie Metalliche",
    "sg:phone":"+39 0372 845900",
    "sg:postcode":"26030",
    "sg:province":"Cremona",
    "wof:name":"Euromet Srl",
    "wof:placetype":"venue"
},
  "geometry": {"coordinates":[10.302519,45.212814],"type":"Point"}
}