{
  "type": "Feature",
  "properties": {
    "iso:country":"IT",
    "sg:address":"22031 Albavilla",
    "sg:city":"Albavilla",
    "sg:orig_category":"Articoli Da Regalo. Tempo Libero - Articoli E Forniture. Regalistica Aziendale",
    "sg:phone":"+39 031 629204",
    "sg:postcode":"22031",
    "sg:province":"Como",
    "wof:name":"Corti Sergio",
    "wof:placetype":"venue"
},
  "geometry": {"coordinates":[9.127735,45.803875],"type":"Point"}
}