{
  "type": "Feature",
  "properties": {
    "addr:full":"120, V. Dell'osservatorio 50141 Firenze Firenze Firenze 50141",
    "addr:housenumber":"120",
    "addr:postcode":"50141;50141",
    "addr:street":"V. Dell'Osservatorio",
    "iso:country":"IT",
    "sg:address":"120, V. Dell'osservatorio 50141 Firenze",
    "sg:city":"Firenze",
    "sg:orig_category":"Miscellaneous Products",
    "sg:phone":"+39 39055456521",
    "sg:postcode":"50141",
    "sg:province":"Firenze",
    "sg:website":"http://www.paginegialle.it/visconti-fi",
    "wof:name":"Visconti Srl",
    "wof:placetype":"venue"
},
  "geometry": {"coordinates":[11.2386064529,43.8155822754],"type":"Point"}
}