{
  "type": "Feature",
  "properties": {
    "addr:full":"20123 Milano Milano Milano 20123",
    "addr:postcode":"20123;20123",
    "iso:country":"IT",
    "sg:address":"20123 Milano",
    "sg:city":"Milano",
    "sg:classifiers":[
        {
            "category":"Health Services",
            "subcategory":"Health Practitioner",
            "type":"Services"
        }
    ],
    "sg:phone":"+39 02 832 2392",
    "sg:postcode":"20123",
    "sg:province":"Milano",
    "sg:tags":[
        "medici"
    ],
    "wof:name":"Dellisanti Nicola",
    "wof:placetype":"venue"
},
  "geometry": {"coordinates":[9.178056,45.455379],"type":"Point"}
}