{
  "type": "Feature",
  "properties": {
    "iso:country":"IT",
    "sg:address":"15, Via Mattei 24050 Calcinate",
    "sg:city":"Calcinate",
    "sg:orig_category":"Miscellaneous Products",
    "sg:phone":"+39 39035843572",
    "sg:postcode":"24050",
    "sg:province":"Bergamo",
    "wof:name":"Ellepack (s.r.l.)",
    "wof:placetype":"venue"
},
  "geometry": {"coordinates":[9.7814998627,45.6177558899],"type":"Point"}
}