{
  "type": "Feature",
  "properties": {
    "iso:country":"IT",
    "sg:address":"46100 Mantova",
    "sg:city":"Mantova",
    "sg:orig_category":"Agenzie Immobiliari",
    "sg:phone":"+39 0376 368490",
    "sg:postcode":"46100",
    "sg:province":"Mantova",
    "sg:website":"http://www.studiotecnicoimmobiliare.it",
    "wof:name":"Agenzia Immobiliare Studio Tecnico Srl",
    "wof:placetype":"venue"
},
  "geometry": {"coordinates":[10.790806,45.159622],"type":"Point"}
}