{
  "type": "Feature",
  "properties": {
    "iso:country":"IT",
    "sg:address":"21100 Varese",
    "sg:city":"Varese",
    "sg:orig_category":"Nastri Adesivi E Biadesivi",
    "sg:phone":"+39 0332 265379",
    "sg:postcode":"21100",
    "sg:province":"Varese",
    "sg:website":"http://www.interpaknastriadesivi.it",
    "wof:name":"Ziliotto Romina Interpack",
    "wof:placetype":"venue"
},
  "geometry": {"coordinates":[8.848942,45.805431],"type":"Point"}
}