{
  "type": "Feature",
  "properties": {
    "iso:country":"IT",
    "sg:address":"15043 Fubine",
    "sg:city":"Fubine",
    "sg:orig_category":"Cine-foto-ottica",
    "sg:phone":"+39 0131 772288",
    "sg:postcode":"15043",
    "sg:province":"Alessandria",
    "wof:name":"Space Cannon Vh Srl",
    "wof:placetype":"venue"
},
  "geometry": {"coordinates":[8.42691,44.965824],"type":"Point"}
}