{
  "type": "Feature",
  "properties": {
    "iso:country":"IT",
    "sg:address":"88064 Chiaravalle Centrale",
    "sg:city":"Chiaravalle Centrale",
    "sg:orig_category":"Legno Compensato E Profilati - Produzione E Ingrosso",
    "sg:phone":"+39 0967 998200",
    "sg:postcode":"88064",
    "sg:province":"Catanzaro",
    "wof:name":"Fabiano Legnami Srl",
    "wof:placetype":"venue"
},
  "geometry": {"coordinates":[16.38759,38.688419],"type":"Point"}
}