{
  "type": "Feature",
  "properties": {
    "addr:full":"77, Via Monte Leone 21013 Gallarate Gallarate Varese 21013",
    "addr:postcode":"21013;21013",
    "addr:street":"Via Monte Leone",
    "iso:country":"IT",
    "sg:address":"77, Via Monte Leone 21013 Gallarate",
    "sg:city":"Gallarate",
    "sg:classifiers":[
        {
            "category":"Manufacturing",
            "subcategory":"Paper Products",
            "type":"Manufacturing & Wholesale Goods"
        }
    ],
    "sg:phone":"+39 0331 776285",
    "sg:postcode":"21013",
    "sg:province":"Varese",
    "sg:tags":[
        "cardboard"
    ],
    "wof:name":"Indet (s.n.c.)",
    "wof:placetype":"venue"
},
  "geometry": {"coordinates":[8.7655239105,45.6686592102],"type":"Point"}
}