{
  "type": "Feature",
  "properties": {
    "iso:country":"IT",
    "sg:address":"91027 Paceco",
    "sg:city":"Paceco",
    "sg:orig_category":"Elaborazione Dati - Macchine E Forniture",
    "sg:phone":"+39 0923 526576",
    "sg:postcode":"91027",
    "sg:province":"Trapani",
    "wof:name":"Pace Daniela",
    "wof:placetype":"venue"
},
  "geometry": {"coordinates":[12.556133,37.984627],"type":"Point"}
}