{
  "type": "Feature",
  "properties": {
    "iso:country":"IT",
    "sg:address":"84081 Baronissi",
    "sg:city":"Baronissi",
    "sg:orig_category":"Aspirazione Impianti",
    "sg:phone":"+39 089 955212",
    "sg:postcode":"84081",
    "sg:province":"Salerno",
    "wof:name":"Euro Air Sas",
    "wof:placetype":"venue"
},
  "geometry": {"coordinates":[14.780395,40.751438],"type":"Point"}
}