{
  "type": "Feature",
  "properties": {
    "addr:full":"00179 Roma Roma Roma 00179",
    "addr:postcode":"00179;00179",
    "iso:country":"IT",
    "sg:address":"00179 Roma",
    "sg:city":"Roma",
    "sg:orig_category":"Ospedali E Servizi Sanitari",
    "sg:phone":"+39 06 780 8760",
    "sg:postcode":"00179",
    "sg:province":"Roma",
    "wof:name":"St.diagnostico Amelia Srl.",
    "wof:placetype":"venue"
},
  "geometry": {"coordinates":[12.578022,41.80909],"type":"Point"}
}