{
  "type": "Feature",
  "properties": {
    "addr:full":"20050 Veduggio Con Colzano Veduggio con Colzano Milano 20050",
    "addr:housenumber":"20050",
    "addr:postcode":"20050",
    "addr:street":"Veduggio Con Colzano",
    "iso:country":"IT",
    "sg:address":"20050 Veduggio Con Colzano",
    "sg:city":"Veduggio con Colzano",
    "sg:orig_category":"Prodotti E Manufatti In Materie Plastiche",
    "sg:phone":"+39 036 291 0772",
    "sg:postcode":"20050",
    "sg:province":"Milano",
    "wof:name":"P.w.s. Plast Sas",
    "wof:placetype":"venue"
},
  "geometry": {"coordinates":[9.2704610825,45.7330818176],"type":"Point"}
}