{
  "type": "Feature",
  "properties": {
    "iso:country":"IT",
    "sg:address":"36010 Zane'",
    "sg:orig_category":"Prodotti Di Base E Forniture Per Industria Alimentare E Bevande",
    "sg:phone":"+39 0445 314242",
    "sg:postcode":"36010",
    "sg:province":"Vicenza",
    "wof:name":"Dal Pra' Giuliano E Vasco (s.n.c.)",
    "wof:placetype":"venue"
},
  "geometry": {"coordinates":[11.4445533752,45.7278900146],"type":"Point"}
}