{
  "type": "Feature",
  "properties": {
    "addr:full":"Via Panama 88 00198 Roma Roma Roma 00198",
    "addr:housenumber":"88",
    "addr:postcode":"00198;00198",
    "addr:street":"Via Panama",
    "iso:country":"IT",
    "sg:address":"Via Panama 88 00198 Roma",
    "sg:city":"Roma",
    "sg:classifiers":[
        {
            "category":"Health Services",
            "subcategory":"Nursing And Care Facility",
            "type":"Services"
        }
    ],
    "sg:phone":"+39 06 841 1566",
    "sg:postcode":"00198",
    "sg:province":"Roma",
    "sg:tags":[
        "electro-medical",
        "apparatus"
    ],
    "sg:website":"www.ibg-srl.com",
    "wof:name":"Ibg Italia Srl",
    "wof:placetype":"venue"
},
  "geometry": {"coordinates":[12.498482,41.924633],"type":"Point"}
}