{
  "type": "Feature",
  "properties": {
    "addr:full":"43022 Montechiarugolo Montechiarugolo Parma 43022",
    "addr:postcode":"43022;43022",
    "iso:country":"IT",
    "sg:address":"43022 Montechiarugolo",
    "sg:city":"Montechiarugolo",
    "sg:orig_category":"Prodotti Alimentari",
    "sg:phone":"+39 0521 653125",
    "sg:postcode":"43022",
    "sg:province":"Parma",
    "sg:website":"http://www.mutti-parma.com",
    "wof:name":"Mutti Fratelli Spa",
    "wof:placetype":"venue"
},
  "geometry": {"coordinates":[10.3769140244,44.6946907043],"type":"Point"}
}