{
  "type": "Feature",
  "properties": {
    "iso:country":"IT",
    "sg:address":"53045 Montepulciano",
    "sg:city":"Montepulciano",
    "sg:orig_category":"Ristorazione E Locali Pubblici Affini. Ristoranti Ed Esercizi Affini. Servizi Ausiliari Di Ristorazione E Di Intrattenimento",
    "sg:phone":"+39 0578 798078",
    "sg:postcode":"53045",
    "sg:province":"Siena",
    "wof:name":"Hotel 3 Stelle",
    "wof:placetype":"venue"
},
  "geometry": {"coordinates":[11.811535,43.066238],"type":"Point"}
}