{
  "type": "Feature",
  "properties": {
    "iso:country":"IT",
    "sg:address":"80121 Napoli",
    "sg:city":"Napoli",
    "sg:orig_category":"Agenzie D'affari E Servizi Commerciali. Acqua, Luce, Gas E Societa' Di Esercizio Pubblico",
    "sg:phone":"+39 081 764 2545",
    "sg:postcode":"80121",
    "sg:province":"Napoli",
    "wof:name":"Blindhouse Spa",
    "wof:placetype":"venue"
},
  "geometry": {"coordinates":[14.208365,40.905563],"type":"Point"}
}