{
  "type": "Feature",
  "properties": {
    "addr:full":"36040 San Germano Dei Berici San Germano dei Berici Vicenza 36040",
    "addr:housenumber":"36040",
    "addr:postcode":"germano dei berici;36040",
    "addr:street":"San;Germano Dei Berici",
    "iso:country":"IT",
    "sg:address":"36040 San Germano Dei Berici",
    "sg:city":"San Germano dei Berici",
    "sg:orig_category":"Pompe. Elettrotecnica Industriale, Prodotti E Apparecchiature",
    "sg:phone":"+39 0444 868222",
    "sg:postcode":"36040",
    "sg:province":"Vicenza",
    "wof:name":"Tesla S.r.l.",
    "wof:placetype":"venue"
},
  "geometry": {"coordinates":[11.5174722672,45.5269088745],"type":"Point"}
}