{
  "type": "Feature",
  "properties": {
    "iso:country":"IT",
    "sg:address":"00042 Anzio",
    "sg:city":"Anzio",
    "sg:classifiers":[
        {
            "category":"Professional",
            "subcategory":"Business Services",
            "type":"Services"
        }
    ],
    "sg:phone":"+39 06 9834 1043",
    "sg:postcode":"00042",
    "sg:province":"Roma",
    "sg:tags":[
        "support",
        "companies",
        "events",
        "trade"
    ],
    "wof:name":"Istituto Magnum Investigazioni Sas",
    "wof:placetype":"venue"
},
  "geometry": {"coordinates":[12.61014,41.511349],"type":"Point"}
}