{
  "type": "Feature",
  "properties": {
    "iso:country":"IT",
    "sg:address":"37135 Verona",
    "sg:city":"Verona",
    "sg:orig_category":"Telecomunicazioni E Telefonia, Impianti, Apparecchi E Servizi",
    "sg:phone":"+39 045 820 0616",
    "sg:postcode":"37135",
    "sg:province":"Verona",
    "wof:name":"Marcomini Gianfranco",
    "wof:placetype":"venue"
},
  "geometry": {"coordinates":[10.973211,45.411938],"type":"Point"}
}