{
  "type": "Feature",
  "properties": {
    "iso:country":"IT",
    "sg:address":"20099 Sesto San Giovanni",
    "sg:city":"Sesto San Giovanni",
    "sg:orig_category":"Servizi Culturali E Per Lo Spettacolo",
    "sg:phone":"+39 02 248 0707",
    "sg:postcode":"20099",
    "sg:province":"Milano",
    "wof:name":"Cinema Teatro Elena",
    "wof:placetype":"venue"
},
  "geometry": {"coordinates":[9.229838,45.533253],"type":"Point"}
}