{
  "type": "Feature",
  "properties": {
    "addr:full":"110, Via Roma 23855 Pescate Pescate Lecco 23855",
    "addr:housenumber":"110",
    "addr:postcode":"23855;23855",
    "addr:street":"Via Roma",
    "iso:country":"IT",
    "sg:address":"110, Via Roma 23855 Pescate",
    "sg:city":"Pescate",
    "sg:classifiers":[
        {
            "category":"Autos & Motor Vehicles",
            "subcategory":"Automobile Sales",
            "type":"Retail Goods"
        }
    ],
    "sg:phone":"+39 0341 282889",
    "sg:postcode":"23855",
    "sg:province":"Lecco",
    "sg:tags":[
        "motor-cars"
    ],
    "wof:name":"Negri Iginio (s.r.l.)",
    "wof:placetype":"venue"
},
  "geometry": {"coordinates":[9.3958797455,45.8290748596],"type":"Point"}
}