{
  "type": "Feature",
  "properties": {
    "iso:country":"IT",
    "sg:address":"42100 Reggio Emilia",
    "sg:classifiers":[
        {
            "category":"Autos & Motor Vehicles",
            "subcategory":"Fuel & Gas Station",
            "type":"Retail Goods"
        }
    ],
    "sg:phone":"+39 0522 280255",
    "sg:postcode":"42100",
    "sg:province":"Reggio Nell'Emilia",
    "sg:tags":[
        "petroleum",
        "products"
    ],
    "wof:name":"Preti Alfonso",
    "wof:placetype":"venue"
},
  "geometry": {"coordinates":[10.6158981323,44.6900291443],"type":"Point"}
}