{
  "type": "Feature",
  "properties": {
    "iso:country":"IT",
    "sg:address":"04100 Latina",
    "sg:city":"Borgo Piave",
    "sg:orig_category":"Trasporti E Spedizioni Merci",
    "sg:phone":"+39 0773 480851",
    "sg:postcode":"04100",
    "sg:province":"Latina",
    "wof:name":"Grasselli & C. Srl",
    "wof:placetype":"venue"
},
  "geometry": {"coordinates":[12.859113,41.498352],"type":"Point"}
}