{
  "type": "Feature",
  "properties": {
    "addr:full":"22, Via Vigne S. Antonio 80058 Torre Annunziata Torre Annunziata Napoli 80058",
    "addr:postcode":"80058;80058",
    "addr:street":"Via Vigne S. Antonio",
    "iso:country":"IT",
    "sg:address":"22, Via Vigne S. Antonio 80058 Torre Annunziata",
    "sg:city":"Torre Annunziata",
    "sg:classifiers":[
        {
            "category":"Manufacturing",
            "subcategory":"Metals",
            "type":"Manufacturing & Wholesale Goods"
        }
    ],
    "sg:phone":"+39 081 862 3614",
    "sg:postcode":"80058",
    "sg:province":"Napoli",
    "sg:tags":[
        "metallurgy",
        "metalworking"
    ],
    "wof:name":"Officine Leone Srl",
    "wof:placetype":"venue"
},
  "geometry": {"coordinates":[14.4733781815,40.735370636],"type":"Point"}
}