{
  "type": "Feature",
  "properties": {
    "iso:country":"IT",
    "sg:address":"Localit\u00e0 Ratto 37 15070 Tagliolo Monferrato",
    "sg:city":"Tagliolo Monferrato",
    "sg:classifiers":[
        {
            "category":"Banks & Credit Unions",
            "subcategory":"Investment Brokerage",
            "type":"Services"
        }
    ],
    "sg:phone":"+39 0143 882111",
    "sg:postcode":"15070",
    "sg:province":"Alessandria",
    "sg:tags":[
        "ocean-going",
        "vessel"
    ],
    "wof:name":"Ma.ga.ri. Snc",
    "wof:placetype":"venue"
},
  "geometry": {"coordinates":[8.616951,44.913216],"type":"Point"}
}