{
  "type": "Feature",
  "properties": {
    "iso:country":"IT",
    "sg:address":"20059 Vimercate",
    "sg:city":"Vimercate",
    "sg:classifiers":[
        {
            "category":"Shopping",
            "subcategory":"Stationery & Office Supplies",
            "type":"Retail Goods"
        }
    ],
    "sg:phone":"+39 039 669165",
    "sg:postcode":"20059",
    "sg:province":"Milano",
    "sg:tags":[
        "equipment",
        "furniture",
        "furnishing",
        "professional"
    ],
    "wof:name":"Rotra Snc",
    "wof:placetype":"venue"
},
  "geometry": {"coordinates":[9.3688325882,45.619342804],"type":"Point"}
}