{
  "type": "Feature",
  "properties": {
    "addr:full":"13012 Borgo Vercelli Borgo Vercelli Vercelli 13012",
    "addr:postcode":"13012;13012",
    "iso:country":"IT",
    "sg:address":"13012 Borgo Vercelli",
    "sg:city":"Borgo Vercelli",
    "sg:orig_category":"Acciai Inossidabili - Lavorazione",
    "sg:phone":"+39 0161 32818",
    "sg:postcode":"13012",
    "sg:province":"Vercelli",
    "wof:name":"Stocco Cesare Impianti",
    "wof:placetype":"venue"
},
  "geometry": {"coordinates":[8.460711,45.352745],"type":"Point"}
}