{
  "type": "Feature",
  "properties": {
    "addr:full":"20159 Milano Milano Milano 20159",
    "addr:postcode":"20159;20159",
    "iso:country":"IT",
    "sg:address":"20159 Milano",
    "sg:city":"Milano",
    "sg:orig_category":"Utensili Meccanici E Materiali",
    "sg:phone":"+39 02 607 1721",
    "sg:postcode":"20159",
    "sg:province":"Milano",
    "wof:name":"Somigli Utensili Sas Di Carlo Somigli E C.",
    "wof:placetype":"venue"
},
  "geometry": {"coordinates":[9.193353,45.495266],"type":"Point"}
}