{
  "type": "Feature",
  "properties": {
    "iso:country":"IT",
    "sg:address":"39, Via Galliani 21020 Casale Litta",
    "sg:city":"Casale Litta",
    "sg:classifiers":[
        {
            "category":"Autos & Motor Vehicles",
            "subcategory":"Automobile Sales",
            "type":"Retail Goods"
        }
    ],
    "sg:phone":"+39 0332 945005",
    "sg:postcode":"21020",
    "sg:province":"Varese",
    "sg:tags":[
        "motor-cars"
    ],
    "wof:name":"Betanord (s.r.l.)",
    "wof:placetype":"venue"
},
  "geometry": {"coordinates":[8.7348651886,45.754650116],"type":"Point"}
}