{
  "type": "Feature",
  "properties": {
    "addr:full":"95024 Acireale Acireale Catania 95024",
    "addr:postcode":"95024;95024",
    "iso:country":"IT",
    "sg:address":"95024 Acireale",
    "sg:city":"Acireale",
    "sg:orig_category":"Motocicli E Motocarri - Commercio E Riparazione",
    "sg:phone":"+39 095 765 0039",
    "sg:postcode":"95024",
    "sg:province":"Catania",
    "sg:website":"http://www.massimoto.it",
    "wof:name":"Massimoto Di Massimino Sebastiano",
    "wof:placetype":"venue"
},
  "geometry": {"coordinates":[15.1249647141,37.5780105591],"type":"Point"}
}