{
  "type": "Feature",
  "properties": {
    "iso:country":"IT",
    "sg:address":"40020 Casalfiumanese",
    "sg:city":"Casalfiumanese",
    "sg:orig_category":"Carta E Cartone - Produzione E Commercio",
    "sg:phone":"+39 0542 666152",
    "sg:postcode":"40020",
    "sg:province":"Bologna",
    "wof:name":"Ondulati Santerno Spa",
    "wof:placetype":"venue"
},
  "geometry": {"coordinates":[11.267826,44.428631],"type":"Point"}
}