{
  "type": "Feature",
  "properties": {
    "iso:country":"IT",
    "sg:address":"165/1, Via Del Brennero 38100 Trento",
    "sg:city":"Trento",
    "sg:classifiers":[
        {
            "category":"Professional",
            "subcategory":"Engineering",
            "type":"Services"
        }
    ],
    "sg:phone":"+39 0461 826259",
    "sg:postcode":"38100",
    "sg:province":"Trento",
    "sg:tags":[
        "machine",
        "-",
        "mechanical"
    ],
    "wof:name":"Comec (s.r.l.)",
    "wof:placetype":"venue"
},
  "geometry": {"coordinates":[11.111198,46.094051],"type":"Point"}
}