{
  "type": "Feature",
  "properties": {
    "iso:country":"IT",
    "sg:address":"20047 Brugherio",
    "sg:city":"Brugherio",
    "sg:orig_category":"Utensili Meccanici E Materiali",
    "sg:phone":"+39 039 287 3077",
    "sg:postcode":"20047",
    "sg:province":"Milano",
    "sg:website":"http://www.alcon.it",
    "wof:name":"Al.con Srl",
    "wof:placetype":"venue"
},
  "geometry": {"coordinates":[9.29151,45.545372],"type":"Point"}
}