{
  "type": "Feature",
  "properties": {
    "iso:country":"IT",
    "sg:address":"50056 Montelupo Fiorentino",
    "sg:city":"Montelupo Fiorentino",
    "sg:classifiers":[
        {
            "category":"Professional",
            "subcategory":"Art Services",
            "type":"Services"
        }
    ],
    "sg:phone":"+39 0571 912261",
    "sg:postcode":"50056",
    "sg:province":"Firenze",
    "sg:tags":[
        "entertainment",
        "cultural",
        "artistic",
        "crafts",
        "services",
        "tourism"
    ],
    "wof:name":"Mirenda Salvatore - La Galleria",
    "wof:placetype":"venue"
},
  "geometry": {"coordinates":[11.020273,43.719772],"type":"Point"}
}