{
  "type": "Feature",
  "properties": {
    "iso:country":"IT",
    "sg:address":"17011 Albisola Superiore",
    "sg:city":"Albisola Superiore",
    "sg:orig_category":"Dolciumi E Gelati",
    "sg:phone":"+39 019 488141",
    "sg:postcode":"17011",
    "sg:province":"Savona",
    "wof:name":"Gaino Claudio",
    "wof:placetype":"venue"
},
  "geometry": {"coordinates":[8.48225,44.353413],"type":"Point"}
}