{
  "type": "Feature",
  "properties": {
    "addr:full":"37069 Villafranca Verona Verona 37069",
    "addr:postcode":"37069;37069",
    "iso:country":"IT",
    "sg:address":"37069 Villafranca Verona",
    "sg:orig_category":"Caminetti, Forni Da Giardino E Barbecues",
    "sg:phone":"+39 045 790 1409",
    "sg:postcode":"37069",
    "sg:province":"Verona",
    "wof:name":"Girardi Snc Di Girardi Flavio & C.",
    "wof:placetype":"venue"
},
  "geometry": {"coordinates":[10.863776,45.485744],"type":"Point"}
}