{
  "type": "Feature",
  "properties": {
    "addr:full":"Via Pistoiese 51 50054 Fucecchio Fucecchio Firenze 50054",
    "addr:housenumber":"51",
    "addr:postcode":"50054;50054",
    "addr:street":"Via Pistoiese",
    "iso:country":"IT",
    "sg:address":"Via Pistoiese 51 50054 Fucecchio",
    "sg:city":"Fucecchio",
    "sg:classifiers":[
        {
            "category":"Shopping",
            "subcategory":"Luggage & Leather Goods",
            "type":"Retail Goods"
        }
    ],
    "sg:phone":"+39 0571 261602",
    "sg:postcode":"50054",
    "sg:province":"Firenze",
    "sg:tags":[
        "bag"
    ],
    "sg:website":"www.marianelli.it",
    "wof:name":"Marianelli Srl",
    "wof:placetype":"venue"
},
  "geometry": {"coordinates":[10.747909,43.860737],"type":"Point"}
}