{
  "type": "Feature",
  "properties": {
    "iso:country":"IT",
    "sg:address":"22066 Mariano Comense",
    "sg:city":"Mariano Comense",
    "sg:orig_category":"Servizi Per Imballaggio E Confezionamento",
    "sg:phone":"+39 031 743826",
    "sg:postcode":"22066",
    "sg:province":"Como",
    "wof:name":"Enneci Di Nicoletti Cinzia",
    "wof:placetype":"venue"
},
  "geometry": {"coordinates":[9.197596,45.75843],"type":"Point"}
}