{
  "type": "Feature",
  "properties": {
    "addr:full":"19, Via De Vecchi 20090 Assago Assago Milano 20090",
    "addr:postcode":"20090;20090",
    "addr:street":"Via De Vecchi;Assago",
    "iso:country":"IT",
    "sg:address":"19, Via De Vecchi 20090 Assago",
    "sg:city":"Assago",
    "sg:classifiers":[
        {
            "category":"Shopping",
            "subcategory":"Computers & Home Electronics",
            "type":"Retail Goods"
        }
    ],
    "sg:phone":"+39 02 4884 1865",
    "sg:postcode":"20090",
    "sg:province":"Milano",
    "sg:tags":[
        "electronic",
        "electrical",
        "equipment"
    ],
    "wof:name":"Rotork Controls Italia (s.r.l.)",
    "wof:placetype":"venue"
},
  "geometry": {"coordinates":[9.118657,45.410011],"type":"Point"}
}