{
  "type": "Feature",
  "properties": {
    "addr:full":"Via Roma 76 23892 Bulciago Bulciago Lecco 23892",
    "addr:housenumber":"76",
    "addr:postcode":"23892;23892",
    "addr:street":"Via Roma",
    "iso:country":"IT",
    "sg:address":"Via Roma 76 23892 Bulciago",
    "sg:city":"Bulciago",
    "sg:classifiers":[
        {
            "category":"Home & Garden",
            "subcategory":"Home Furnishings",
            "type":"Retail Goods"
        }
    ],
    "sg:phone":"+39 031 874370",
    "sg:postcode":"23892",
    "sg:province":"Lecco",
    "sg:tags":[
        "textile"
    ],
    "wof:name":"Prosetex Tessitura Jacquard Spa",
    "wof:placetype":"venue"
},
  "geometry": {"coordinates":[9.280264,45.7486],"type":"Point"}
}