{
  "type": "Feature",
  "properties": {
    "iso:country":"IT",
    "sg:address":"64021 Giulianova",
    "sg:city":"Giulianova",
    "sg:orig_category":"Termotecnica E Riscaldamento, Apparecchiature E Servizi",
    "sg:phone":"+39 085 800 1382",
    "sg:postcode":"64021",
    "sg:province":"Teramo",
    "wof:name":"Faga Luigi",
    "wof:placetype":"venue"
},
  "geometry": {"coordinates":[13.926,42.736652],"type":"Point"}
}