{
  "type": "Feature",
  "properties": {
    "addr:full":"Vle Brianza 204 20043 Arcore Arcore Milano 20043",
    "addr:housenumber":"204",
    "addr:postcode":"20043;20043",
    "addr:street":"Vle Brianza",
    "iso:country":"IT",
    "sg:address":"Vle Brianza 204 20043 Arcore",
    "sg:city":"Arcore",
    "sg:classifiers":[
        {
            "category":"Shopping",
            "subcategory":"Beauty & Cosmetics",
            "type":"Retail Goods"
        }
    ],
    "sg:phone":"+39 039 606 6137",
    "sg:postcode":"20043",
    "sg:province":"Milano",
    "sg:tags":[
        "product",
        "special"
    ],
    "wof:name":"Silacos Di Sinelli Gabriele E Lavezzari Fausto Srl",
    "wof:placetype":"venue"
},
  "geometry": {"coordinates":[9.188141,45.463688],"type":"Point"}
}