{
  "type": "Feature",
  "properties": {
    "addr:full":"25060 Cellatica Cellatica Brescia 25060",
    "addr:postcode":"25060;25060",
    "iso:country":"IT",
    "sg:address":"25060 Cellatica",
    "sg:city":"Cellatica",
    "sg:orig_category":"Macchine Pulizia Industriale",
    "sg:phone":"+39 030 277 3940",
    "sg:postcode":"25060",
    "sg:province":"Brescia",
    "wof:name":"Eco-tron Di Minuti Luigi",
    "wof:placetype":"venue"
},
  "geometry": {"coordinates":[10.169372,45.58078],"type":"Point"}
}