{
  "type": "Feature",
  "properties": {
    "addr:full":"Piazza Ricci, 29 - 30; Massa Lombarda; 48024 Massa Lombarda Ravenna 48024",
    "addr:housenumber":"29 30",
    "addr:postcode":"48024;48024",
    "addr:street":"Piazza Ricci;Lombarda",
    "iso:country":"IT",
    "sg:address":"Piazza Ricci, 29 - 30; Massa Lombarda; 48024",
    "sg:city":"Massa Lombarda",
    "sg:classifiers":[
        {
            "category":"Banks & Credit Unions",
            "subcategory":"Bank",
            "type":"Services"
        }
    ],
    "sg:phone":"+39 0545 81697",
    "sg:postcode":"48024",
    "sg:province":"Ravenna",
    "wof:name":"Banca Del Monte",
    "wof:placetype":"venue"
},
  "geometry": {"coordinates":[11.825826,44.447121],"type":"Point"}
}