{
  "type": "Feature",
  "properties": {
    "iso:country":"IT",
    "sg:address":"; Ponte Arche; 38077",
    "sg:classifiers":[
        {
            "category":"Banks & Credit Unions",
            "subcategory":"Bank",
            "type":"Services"
        }
    ],
    "sg:phone":"+39 39046571424",
    "wof:name":"Cassa Rurale Delle Giudicarie",
    "wof:placetype":"venue"
},
  "geometry": {"coordinates":[10.87623,46.037018],"type":"Point"}
}