{
  "type": "Feature",
  "properties": {
    "iso:country":"IT",
    "sg:address":"24040 Calvenzano",
    "sg:city":"Calvenzano",
    "sg:orig_category":"Guarnizioni Industriali",
    "sg:phone":"+39 036 333 5479",
    "sg:postcode":"24040",
    "sg:province":"Bergamo",
    "wof:name":"Guarnizioni Industriali Colombo Srl",
    "wof:placetype":"venue"
},
  "geometry": {"coordinates":[9.601708,45.482689],"type":"Point"}
}