{
  "type": "Feature",
  "properties": {
    "iso:country":"IT",
    "sg:address":"20010 Buscate",
    "sg:city":"Buscate",
    "sg:orig_category":"Articoli Pulizia",
    "sg:phone":"+39 0331 800211",
    "sg:postcode":"20010",
    "sg:province":"Milano",
    "wof:name":"Pisoni Renato",
    "wof:placetype":"venue"
},
  "geometry": {"coordinates":[9.174796,45.464397],"type":"Point"}
}