{
  "type": "Feature",
  "properties": {
    "iso:country":"IT",
    "sg:address":"141, Via Di Scorticabove 00156 Roma",
    "sg:city":"Roma",
    "sg:classifiers":[
        {
            "category":"Wholesale",
            "subcategory":"Machinery & Supplies",
            "type":"Manufacturing & Wholesale Goods"
        }
    ],
    "sg:phone":"+39 39064101592",
    "sg:postcode":"00156",
    "sg:province":"Roma",
    "sg:tags":[
        "equipment",
        "precision"
    ],
    "wof:name":"Quadri System Srl",
    "wof:placetype":"venue"
},
  "geometry": {"coordinates":[12.5921821594,41.9349784851],"type":"Point"}
}