{
  "type": "Feature",
  "properties": {
    "addr:full":"Loc Campagna Magra 37068 Vigasio Vigasio Verona 37068",
    "addr:postcode":"37068;37068",
    "addr:street":"Loc Campagna Magra",
    "iso:country":"IT",
    "sg:address":"Loc Campagna Magra 37068 Vigasio",
    "sg:city":"Vigasio",
    "sg:orig_category":"Fish, Frozen",
    "sg:phone":"+39 045 736 3333",
    "sg:postcode":"37068",
    "sg:province":"Verona",
    "wof:name":"Pescicoltura Campagna Magra S.r.l.",
    "wof:placetype":"venue"
},
  "geometry": {"coordinates":[10.9917478561,45.4383659363],"type":"Point"}
}