{
  "type": "Feature",
  "properties": {
    "addr:full":"87064 Corigliano Calabro Corigliano Calabro Cosenza 87064",
    "addr:postcode":"87064;87064",
    "iso:country":"IT",
    "sg:address":"87064 Corigliano Calabro",
    "sg:city":"Corigliano Calabro",
    "sg:orig_category":"Servizi Per Lo Sport E Il Tempo Libero. Servizi Ausiliari Dei Mezzi Di Trasporto",
    "sg:phone":"+39 0983 888256",
    "sg:postcode":"87064",
    "sg:province":"Cosenza",
    "wof:name":"Agenzia Marittima Mare Sud Sas Cataldi F.sco & C.",
    "wof:placetype":"venue"
},
  "geometry": {"coordinates":[16.511271,39.627613],"type":"Point"}
}