{
  "type": "Feature",
  "properties": {
    "iso:country":"IT",
    "sg:address":"26010 Sergnano",
    "sg:city":"Sergnano",
    "sg:orig_category":"Societa' Immobiliari",
    "sg:phone":"+39 0373 458025",
    "sg:postcode":"26010",
    "sg:province":"Cremona",
    "sg:website":"http://www.mediocasaonline.it",
    "wof:name":"Mediocasa",
    "wof:placetype":"venue"
},
  "geometry": {"coordinates":[9.701717,45.427349],"type":"Point"}
}