{
  "type": "Feature",
  "properties": {
    "iso:country":"IT",
    "sg:address":"9, Vico Caroli 72021 Francavilla Fontana",
    "sg:city":"Francavilla Fontana",
    "sg:classifiers":[
        {
            "category":"Shopping",
            "subcategory":"Clothing, Apparel, & Fashions",
            "type":"Retail Goods"
        }
    ],
    "sg:phone":"+39 0831 841754",
    "sg:postcode":"72021",
    "sg:province":"Brindisi",
    "sg:tags":[
        "clothes"
    ],
    "wof:name":"De Fazio",
    "wof:placetype":"venue"
},
  "geometry": {"coordinates":[17.5825,40.527061],"type":"Point"}
}