{
  "type": "Feature",
  "properties": {
    "iso:country":"IT",
    "sg:address":"6, V. Redipuglia 21053 Castellanza",
    "sg:city":"Castellanza",
    "sg:classifiers":[
        {
            "category":"Professional",
            "subcategory":"Engineering",
            "type":"Services"
        }
    ],
    "sg:phone":"+39 0331 502571",
    "sg:postcode":"21053",
    "sg:province":"Varese",
    "sg:tags":[
        "machine",
        "-",
        "mechanical"
    ],
    "sg:website":"http://www.cmzmixer.com",
    "wof:name":"C.m.z. - Zanzottera",
    "wof:placetype":"venue"
},
  "geometry": {"coordinates":[8.895773,45.616142],"type":"Point"}
}