{
  "type": "Feature",
  "properties": {
    "iso:country":"IT",
    "sg:address":"16163 Genova",
    "sg:city":"Genova",
    "sg:orig_category":"Articoli Da Regalo. Shopping. Regalistica Aziendale",
    "sg:phone":"+39 010 714921",
    "sg:postcode":"16163",
    "sg:province":"Genova",
    "sg:website":"http://www.giangio.com",
    "wof:name":"G. & G. Srl",
    "wof:placetype":"venue"
},
  "geometry": {"coordinates":[8.89692,44.491676],"type":"Point"}
}