{
  "type": "Feature",
  "properties": {
    "iso:country":"IT",
    "sg:address":"37038 Soave",
    "sg:city":"Soave",
    "sg:orig_category":"Servizi Di Magazzinaggio E Movimentazione",
    "sg:phone":"+39 045 768 0760",
    "sg:postcode":"37038",
    "sg:province":"Verona",
    "wof:name":"M. Ventiquattro S.r.l.",
    "wof:placetype":"venue"
},
  "geometry": {"coordinates":[10.947059,45.476757],"type":"Point"}
}