{
  "type": "Feature",
  "properties": {
    "iso:country":"IT",
    "sg:address":"37023 Grezzana",
    "sg:city":"Grezzana",
    "sg:orig_category":"Marmo, Pietre Ed Affini",
    "sg:phone":"+39 045 907245",
    "sg:postcode":"37023",
    "sg:province":"Verona",
    "sg:website":"http://www.scandolamarmi.it",
    "wof:name":"Scandola Marmi Snc",
    "wof:placetype":"venue"
},
  "geometry": {"coordinates":[11.024289,45.532475],"type":"Point"}
}