{
  "type": "Feature",
  "properties": {
    "addr:full":"34070 Fogliano - Redipuglia Redipuglia Gorizia 34070",
    "addr:postcode":"34070;34070",
    "iso:country":"IT",
    "sg:address":"34070 Fogliano - Redipuglia",
    "sg:city":"Redipuglia",
    "sg:orig_category":"Abbigliamento Esterno, Maglierie E Pelliccerie. Sport - Articoli E Forniture",
    "sg:phone":"+39 0481 488200",
    "sg:postcode":"34070",
    "sg:province":"Gorizia",
    "wof:name":"Essegi Srl",
    "wof:placetype":"venue"
},
  "geometry": {"coordinates":[13.487041,45.849415],"type":"Point"}
}