{
  "type": "Feature",
  "properties": {
    "addr:full":"8/e, Ctr. Tirit\u00ec Catania 95040",
    "addr:housenumber":"8 / e",
    "addr:postcode":"95040",
    "addr:street":"Ctr. Tiriti\u0300",
    "iso:country":"IT",
    "sg:address":"8/e, Ctr. Tirit\u00ec",
    "sg:classifiers":[
        {
            "category":"Manufacturing",
            "subcategory":"Metals",
            "type":"Manufacturing & Wholesale Goods"
        }
    ],
    "sg:phone":"+39 39095302291",
    "sg:postcode":"95040",
    "sg:province":"Catania",
    "sg:tags":[
        "metallurgy",
        "metalworking"
    ],
    "sg:website":"http://www.paginegialle.it/anfuso",
    "wof:name":"Anfuso Emanuele Spa",
    "wof:placetype":"venue"
},
  "geometry": {"coordinates":[15.0878343582,37.5024833679],"type":"Point"}
}