{
  "type": "Feature",
  "properties": {
    "iso:country":"IT",
    "sg:address":"95, V. S. Giovanni De Matha 80141 Napoli",
    "sg:city":"Napoli",
    "sg:classifiers":[
        {
            "category":"Manufacturing",
            "subcategory":"Glass & Minerals",
            "type":"Manufacturing & Wholesale Goods"
        }
    ],
    "sg:phone":"+39 081 599 1471",
    "sg:postcode":"80141",
    "sg:province":"Napoli",
    "sg:website":"http://www.paginegialle.it/memydesign",
    "wof:name":"Design Memy",
    "wof:placetype":"venue"
},
  "geometry": {"coordinates":[14.280592,40.86536],"type":"Point"}
}