{
  "type": "Feature",
  "properties": {
    "iso:country":"IT",
    "sg:address":"2, Via Linfano 38062 Arco",
    "sg:city":"Arco",
    "sg:classifiers":[
        {
            "category":"Professional",
            "subcategory":"Engineering",
            "type":"Services"
        }
    ],
    "sg:phone":"+39 0464 516778",
    "sg:postcode":"38062",
    "sg:province":"Trento",
    "sg:tags":[
        "machine",
        "-",
        "mechanical"
    ],
    "wof:name":"C.a.m.u. (s.n.c.)",
    "wof:placetype":"venue"
},
  "geometry": {"coordinates":[10.879704,45.907494],"type":"Point"}
}