{
  "type": "Feature",
  "properties": {
    "iso:country":"IT",
    "sg:address":"84125 Salerno",
    "sg:city":"Salerno",
    "sg:classifiers":[
        {
            "category":"Health Services",
            "subcategory":"Health Practitioner",
            "type":"Services"
        }
    ],
    "sg:phone":"+39 089 228117",
    "sg:postcode":"84125",
    "sg:province":"Salerno",
    "sg:tags":[
        "medici"
    ],
    "wof:name":"Poto Sergio",
    "wof:placetype":"venue"
},
  "geometry": {"coordinates":[14.7647504807,40.6764335632],"type":"Point"}
}