{
  "type": "Feature",
  "properties": {
    "addr:full":"Via C. Battisti 94 21040 Venegono Superiore Venegono Superiore Varese 21040",
    "addr:housenumber":"94",
    "addr:postcode":"21040;21040",
    "addr:street":"Via C. Battisti",
    "iso:country":"IT",
    "sg:address":"Via C. Battisti 94 21040 Venegono Superiore",
    "sg:city":"Venegono Superiore",
    "sg:classifiers":[
        {
            "category":"Government",
            "subcategory":"Fire Station",
            "type":"Public Place"
        }
    ],
    "sg:phone":"+39 0331 865451",
    "sg:postcode":"21040",
    "sg:province":"Varese",
    "sg:tags":[
        "sun",
        "glass"
    ],
    "sg:website":"www.sordelli.it",
    "wof:name":"Sordelli Snc",
    "wof:placetype":"venue"
},
  "geometry": {"coordinates":[8.893665,45.747734],"type":"Point"}
}