{
  "type": "Feature",
  "properties": {
    "iso:country":"IT",
    "sg:address":"1, Via Ricasoli 50122 Firenze",
    "sg:city":"Firenze",
    "sg:classifiers":[
        {
            "category":"Shopping",
            "subcategory":"Clothing, Apparel, & Fashions",
            "type":"Retail Goods"
        }
    ],
    "sg:phone":"+39 39055217548",
    "sg:postcode":"50122",
    "sg:province":"Firenze",
    "sg:tags":[
        "clothes"
    ],
    "wof:name":"Cioni",
    "wof:placetype":"venue"
},
  "geometry": {"coordinates":[11.256053,43.773479],"type":"Point"}
}