{
  "type": "Feature",
  "properties": {
    "iso:country":"IT",
    "sg:address":"35036 Montegrotto Terme",
    "sg:city":"Montegrotto Terme",
    "sg:orig_category":"Antiquariato",
    "sg:phone":"+39 049 891 2564",
    "sg:postcode":"35036",
    "sg:province":"Padova",
    "sg:website":"http://www.gallerieriunite.it",
    "wof:name":"Arte 3 Gallerie Riunite",
    "wof:placetype":"venue"
},
  "geometry": {"coordinates":[11.780075,45.342964],"type":"Point"}
}