{
  "type": "Feature",
  "properties": {
    "addr:full":"20015 Parabiago Parabiago Milano 20015",
    "addr:postcode":"20015;20015",
    "iso:country":"IT",
    "sg:address":"20015 Parabiago",
    "sg:city":"Parabiago",
    "sg:orig_category":"Forniture Per Abbigliamento E Pelletterie",
    "sg:phone":"+39 0331 490471",
    "sg:postcode":"20015",
    "sg:province":"Milano",
    "wof:name":"Italcompo S.r.l.",
    "wof:placetype":"venue"
},
  "geometry": {"coordinates":[9.2160272598,45.473903656],"type":"Point"}
}