{
  "type": "Feature",
  "properties": {
    "iso:country":"IT",
    "sg:address":"16149 Genova",
    "sg:city":"Genova",
    "sg:orig_category":"Audiovisivi Filmati, Spot E Multimediali - Realizzazione E Duplicazione",
    "sg:phone":"+39 010 469 4283",
    "sg:postcode":"16149",
    "sg:province":"Genova",
    "wof:name":"Videosistem Srl",
    "wof:placetype":"venue"
},
  "geometry": {"coordinates":[8.899701,44.412285],"type":"Point"}
}