{
  "type": "Feature",
  "properties": {
    "iso:country":"IT",
    "sg:address":"41100 Modena",
    "sg:city":"Modena",
    "sg:orig_category":"Forniture Per Abbigliamento E Pelletterie",
    "sg:phone":"+39 059 303060",
    "sg:postcode":"41100",
    "sg:province":"Modena",
    "wof:name":"Spazio Donna",
    "wof:placetype":"venue"
},
  "geometry": {"coordinates":[10.9260406494,44.6355438232],"type":"Point"}
}