{
  "type": "Feature",
  "properties": {
    "addr:full":"30030 Martellago Maerne Venezia 30030",
    "addr:postcode":"30030;30030",
    "iso:country":"IT",
    "sg:address":"30030 Martellago",
    "sg:city":"Maerne",
    "sg:orig_category":"Macchine, Impianti Ed Attrezzature Industria Delle Materie Plastiche E Gomma",
    "sg:phone":"+39 041 640732",
    "sg:postcode":"30030",
    "sg:province":"Venezia",
    "wof:name":"Vesco Andrea",
    "wof:placetype":"venue"
},
  "geometry": {"coordinates":[12.150904,45.514893],"type":"Point"}
}