{
  "type": "Feature",
  "properties": {
    "iso:country":"IT",
    "sg:address":"00167 Roma",
    "sg:city":"Roma",
    "sg:orig_category":"Telecomunicazioni E Telefonia, Impianti, Apparecchi E Servizi",
    "sg:phone":"+39 06 662 4603",
    "sg:postcode":"00167",
    "sg:province":"Roma",
    "wof:name":"Rotolo Alessandro",
    "wof:placetype":"venue"
},
  "geometry": {"coordinates":[12.418289,41.903557],"type":"Point"}
}