{
  "type": "Feature",
  "properties": {
    "addr:full":"6, Via Albertario Don Davide 41012 Carpi Carpi Modena 41012",
    "addr:postcode":"41012;41012",
    "addr:street":"Via Albertario Don Davide",
    "iso:country":"IT",
    "sg:address":"6, Via Albertario Don Davide 41012 Carpi",
    "sg:city":"Carpi",
    "sg:classifiers":[
        {
            "category":"Shopping",
            "subcategory":"Clothing, Apparel, & Fashions",
            "type":"Retail Goods"
        }
    ],
    "sg:phone":"+39 39059686046",
    "sg:postcode":"41012",
    "sg:province":"Modena",
    "sg:tags":[
        "clothes"
    ],
    "wof:name":"Fausta Tricot (s.r.l.)",
    "wof:placetype":"venue"
},
  "geometry": {"coordinates":[10.884562,44.798256],"type":"Point"}
}