{
  "type": "Feature",
  "properties": {
    "iso:country":"IT",
    "sg:address":"Via Lago Di Alleghe 45 36015 Schio",
    "sg:city":"Schio",
    "sg:orig_category":"Non-classified Establishments",
    "sg:phone":"+39 0445 575130",
    "sg:postcode":"36015",
    "sg:province":"Vicenza",
    "wof:name":"Calce Barattoni Srl",
    "wof:placetype":"venue"
},
  "geometry": {"coordinates":[11.420546,45.716915],"type":"Point"}
}