{
  "type": "Feature",
  "properties": {
    "iso:country":"IT",
    "sg:address":"36060 Romano D'ezzelino",
    "sg:orig_category":"Fotolito",
    "sg:phone":"+39 0424 30460",
    "sg:postcode":"36060",
    "sg:province":"Vicenza",
    "wof:name":"Laboratorio Grafico Stopiglia",
    "wof:placetype":"venue"
},
  "geometry": {"coordinates":[11.7425336838,45.790561676],"type":"Point"}
}