{
  "type": "Feature",
  "properties": {
    "iso:country":"IT",
    "sg:address":"00199 Roma",
    "sg:city":"Roma",
    "sg:classifiers":[
        {
            "category":"Health Services",
            "subcategory":"Health Practitioner",
            "type":"Services"
        }
    ],
    "sg:phone":"+39 06 8621 1351",
    "sg:postcode":"00199",
    "sg:province":"Roma",
    "sg:tags":[
        "medici"
    ],
    "wof:name":"De Martino Rosa Roll Guido",
    "wof:placetype":"venue"
},
  "geometry": {"coordinates":[12.511119,41.932377],"type":"Point"}
}