{
  "type": "Feature",
  "properties": {
    "addr:full":"40069 Zola Predosa Zola Bologna 40069",
    "addr:postcode":"40069;40069",
    "iso:country":"IT",
    "sg:address":"40069 Zola Predosa",
    "sg:city":"Zola",
    "sg:orig_category":"Prodotti Alimentari",
    "sg:phone":"+39 051 616 6632",
    "sg:postcode":"40069",
    "sg:province":"Bologna",
    "sg:website":"http://www.nutrilifeint.com",
    "wof:name":"Nutrilife Srl",
    "wof:placetype":"venue"
},
  "geometry": {"coordinates":[11.2529506683,44.4947471619],"type":"Point"}
}