{
  "type": "Feature",
  "properties": {
    "iso:country":"IT",
    "sg:address":"04024 Gaeta",
    "sg:city":"Gaeta",
    "sg:classifiers":[
        {
            "category":"Parking",
            "subcategory":"Lot",
            "type":"Transportation"
        }
    ],
    "sg:phone":"+39 0771 471303",
    "sg:postcode":"04024",
    "sg:province":"Latina",
    "sg:tags":[
        "good",
        "shipment",
        "transport"
    ],
    "sg:website":"http://www.sannatrasporti.it",
    "wof:name":"Sanna Autotrasporti Traslochi",
    "wof:placetype":"venue"
},
  "geometry": {"coordinates":[13.560674,41.223877],"type":"Point"}
}