{
  "type": "Feature",
  "properties": {
    "addr:full":"40033 Casalecchio Di Reno Casalecchio di Reno Bologna 40033",
    "addr:postcode":"40033;40033",
    "addr:street":"Di Reno",
    "iso:country":"IT",
    "sg:address":"40033 Casalecchio Di Reno",
    "sg:city":"Casalecchio di Reno",
    "sg:orig_category":"Attrezzature E Forniture Per Officine Riparazione E Servizi Ausiliari",
    "sg:phone":"+39 051 613 1561",
    "sg:postcode":"40033",
    "sg:province":"Bologna",
    "wof:name":"Passarella Enzo",
    "wof:placetype":"venue"
},
  "geometry": {"coordinates":[11.270485,44.463768],"type":"Point"}
}