{
  "type": "Feature",
  "properties": {
    "iso:country":"IT",
    "sg:address":"1, Via Altobelli Bonetti 40026 Imola",
    "sg:city":"Imola",
    "sg:classifiers":[
        {
            "category":"Shopping",
            "subcategory":"Computers & Home Electronics",
            "type":"Retail Goods"
        }
    ],
    "sg:phone":"+39 0542 641667",
    "sg:postcode":"40026",
    "sg:province":"Bologna",
    "sg:tags":[
        "electronic",
        "electrical",
        "equipment"
    ],
    "wof:name":"C.e.m.i. Di Conti E. E C. Snc",
    "wof:placetype":"venue"
},
  "geometry": {"coordinates":[11.725215,44.357483],"type":"Point"}
}