{
  "type": "Feature",
  "properties": {
    "iso:country":"IT",
    "sg:address":"22039 Valbrona",
    "sg:city":"Valbrona",
    "sg:orig_category":"Tessuti E Stoffe. Filati E Materie Prime Tessili",
    "sg:phone":"+39 031 660026",
    "sg:postcode":"22039",
    "sg:province":"Como",
    "wof:name":"Lattuada Carlo & Figli",
    "wof:placetype":"venue"
},
  "geometry": {"coordinates":[9.299309,45.873493],"type":"Point"}
}