{
  "type": "Feature",
  "properties": {
    "iso:country":"IT",
    "sg:address":"50123 Firenze",
    "sg:city":"Firenze",
    "sg:orig_category":"Fotografia - Servizi, Studi, Sviluppo E Stampa",
    "sg:phone":"+39 055 23951",
    "sg:postcode":"50123",
    "sg:province":"Firenze",
    "sg:website":"http://www.alinari.it",
    "wof:name":"Alinari Fratelli I.d.e.a. Spa",
    "wof:placetype":"venue"
},
  "geometry": {"coordinates":[11.2495450974,43.7752914429],"type":"Point"}
}