{
  "type": "Feature",
  "properties": {
    "iso:country":"IT",
    "sg:address":"98043 Rometta",
    "sg:city":"Rometta",
    "sg:orig_category":"Abbigliamento - Vendita Al Dettaglio",
    "sg:phone":"+39 090 996 3599",
    "sg:postcode":"98043",
    "sg:province":"Messina",
    "wof:name":"D'amico Claudia New Age",
    "wof:placetype":"venue"
},
  "geometry": {"coordinates":[15.446724,38.241928],"type":"Point"}
}