{
  "type": "Feature",
  "properties": {
    "iso:country":"IT",
    "sg:address":"20127 Milano",
    "sg:city":"Milano",
    "sg:orig_category":"Forniture Per Abbigliamento E Pelletterie",
    "sg:phone":"+39 02 284 6577",
    "sg:postcode":"20127",
    "sg:province":"Milano",
    "wof:name":"Linea Del Bottone",
    "wof:placetype":"venue"
},
  "geometry": {"coordinates":[9.2262973785,45.4998817444],"type":"Point"}
}