{
  "type": "Feature",
  "properties": {
    "iso:country":"IT",
    "sg:address":"39100 Bolzano",
    "sg:city":"Bolzano",
    "sg:classifiers":[
        {
            "category":"Shopping",
            "subcategory":"Beauty & Cosmetics",
            "type":"Retail Goods"
        }
    ],
    "sg:phone":"+39 0471 501138",
    "sg:postcode":"39100",
    "sg:province":"Bolzano/Bozen",
    "sg:tags":[
        "pharmaceutical",
        "product",
        "products",
        "related",
        "toilet"
    ],
    "sg:website":"http://www.hederanatur.com",
    "wof:name":"Hedera Natur Srl",
    "wof:placetype":"venue"
},
  "geometry": {"coordinates":[11.35800457,46.4967155457],"type":"Point"}
}