{
  "type": "Feature",
  "properties": {
    "addr:full":"Via Sonna 23806 Torre De' Busi Lecco 23806",
    "addr:postcode":"23806;de ' busi;23806",
    "addr:street":"Via Sonna",
    "iso:country":"IT",
    "sg:address":"Via Sonna 23806 Torre De' Busi",
    "sg:classifiers":[
        {
            "category":"Professional",
            "subcategory":"Engineering",
            "type":"Services"
        }
    ],
    "sg:phone":"+39 035 438 4499",
    "sg:postcode":"23806",
    "sg:province":"Lecco",
    "sg:tags":[
        "machine",
        "-",
        "mechanical"
    ],
    "wof:name":"Warcof S.r.l.",
    "wof:placetype":"venue"
},
  "geometry": {"coordinates":[9.47582,45.770817],"type":"Point"}
}