{
  "type": "Feature",
  "properties": {
    "iso:country":"IT",
    "sg:address":"33070 Brugnera",
    "sg:city":"Brugnera",
    "sg:orig_category":"Legno Lavorazione Macchine - Commercio",
    "sg:phone":"+39 0434 623891",
    "sg:postcode":"33070",
    "sg:province":"Pordenone",
    "sg:website":"http://www.bremac.com",
    "wof:name":"Bremac Spa",
    "wof:placetype":"venue"
},
  "geometry": {"coordinates":[12.559553,45.894737],"type":"Point"}
}