{
  "type": "Feature",
  "properties": {
    "iso:country":"IT",
    "sg:address":"Via Del Commissario 61 35124 Padova",
    "sg:city":"Padova",
    "sg:orig_category":"Hoisiery Goods",
    "sg:phone":"+39 049 880 5430",
    "sg:postcode":"35124",
    "sg:province":"Padova",
    "wof:name":"Gruppo Manifatture Tessili Italiane",
    "wof:placetype":"venue"
},
  "geometry": {"coordinates":[11.889501,45.378487],"type":"Point"}
}