{
  "type": "Feature",
  "properties": {
    "iso:country":"IT",
    "sg:address":"10095 Grugliasco",
    "sg:city":"Grugliasco",
    "sg:orig_category":"Dolciumi E Gelati",
    "sg:postcode":"10095",
    "sg:province":"Torino",
    "wof:name":"Dolca (s.n.c.)",
    "wof:placetype":"venue"
},
  "geometry": {"coordinates":[7.580005,45.069935],"type":"Point"}
}