{
  "type": "Feature",
  "properties": {
    "iso:country":"IT",
    "sg:address":"25010 Pozzolengo",
    "sg:city":"Pozzolengo",
    "sg:orig_category":"Dolciumi E Gelati",
    "sg:phone":"+39 030 918492",
    "sg:postcode":"25010",
    "sg:province":"Brescia",
    "wof:name":"Quarenghi Marmellate (s.r.l.)",
    "wof:placetype":"venue"
},
  "geometry": {"coordinates":[10.627172,45.408398],"type":"Point"}
}