{
  "type": "Feature",
  "properties": {
    "addr:full":"00063 Campagnano Di Roma Campagnano di Roma Roma 00063",
    "addr:postcode":"00063;00063",
    "iso:country":"IT",
    "sg:address":"00063 Campagnano Di Roma",
    "sg:city":"Campagnano di Roma",
    "sg:orig_category":"Prodotti Alimentari",
    "sg:phone":"+39 06 9015 4759",
    "sg:postcode":"00063",
    "sg:province":"Roma",
    "wof:name":"Di Benedetto Marina",
    "wof:placetype":"venue"
},
  "geometry": {"coordinates":[12.4014415741,42.0791282654],"type":"Point"}
}