{
  "type": "Feature",
  "properties": {
    "addr:full":"Piazza Umberto I, 14; Moretta; 12033 Moretta Cuneo 12033",
    "addr:housenumber":"14",
    "addr:postcode":"12033;12033",
    "addr:street":"Piazza Umberto I;Moretta",
    "iso:country":"IT",
    "sg:address":"Piazza Umberto I, 14; Moretta; 12033",
    "sg:city":"Moretta",
    "sg:classifiers":[
        {
            "category":"Banks & Credit Unions",
            "subcategory":"Bank",
            "type":"Services"
        }
    ],
    "sg:phone":"+39 0172 94134",
    "sg:postcode":"12033",
    "sg:province":"Cuneo",
    "wof:name":"Banca Crt",
    "wof:placetype":"venue"
},
  "geometry": {"coordinates":[7.537031,44.763096],"type":"Point"}
}