{
  "type": "Feature",
  "properties": {
    "iso:country":"IT",
    "sg:address":"Via Dell' Industria 4 24040 Canonica D'adda",
    "sg:classifiers":[
        {
            "category":"Manufacturing",
            "subcategory":"Rubber & Plastics",
            "type":"Manufacturing & Wholesale Goods"
        }
    ],
    "sg:phone":"+39 02 909 4934",
    "sg:postcode":"24040",
    "sg:province":"Bergamo",
    "sg:tags":[
        "product",
        "part",
        "moulded"
    ],
    "wof:name":"M.c.m. Plast Srl",
    "wof:placetype":"venue"
},
  "geometry": {"coordinates":[9.5362262726,45.5659255981],"type":"Point"}
}