{
  "type": "Feature",
  "properties": {
    "addr:full":"Via Rigosa 5 40069 Zola Predosa Zola Bologna 40069",
    "addr:housenumber":"5",
    "addr:postcode":"40069;40069",
    "addr:street":"Via Rigosa",
    "iso:country":"IT",
    "sg:address":"Via Rigosa 5 40069 Zola Predosa",
    "sg:city":"Zola",
    "sg:classifiers":[
        {
            "category":"Wholesale",
            "subcategory":"Plants",
            "type":"Manufacturing & Wholesale Goods"
        }
    ],
    "sg:phone":"+39 051 618 6811",
    "sg:postcode":"40069",
    "sg:province":"Bologna",
    "sg:tags":[
        "packaging",
        "plants",
        "complete"
    ],
    "sg:website":"www.amotek.it",
    "wof:name":"Amotek Srl",
    "wof:placetype":"venue"
},
  "geometry": {"coordinates":[11.227845192,44.4883460999],"type":"Point"}
}