{
  "type": "Feature",
  "properties": {
    "iso:country":"IT",
    "sg:address":"185, Via Rimaggio 50019 Sesto Fiorentino",
    "sg:city":"Sesto Fiorentino",
    "sg:classifiers":[
        {
            "category":"Manufacturing",
            "subcategory":"Glass & Minerals",
            "type":"Manufacturing & Wholesale Goods"
        }
    ],
    "sg:phone":"+39 055 421 6853",
    "sg:postcode":"50019",
    "sg:province":"Firenze",
    "wof:name":"Pecchioli Marcello Di Pecchioli Paola & C. Sas",
    "wof:placetype":"venue"
},
  "geometry": {"coordinates":[11.193994,43.824913],"type":"Point"}
}