{
  "type": "Feature",
  "properties": {
    "iso:country":"IT",
    "sg:address":"12044 Centallo",
    "sg:city":"Centallo",
    "sg:orig_category":"Macchine, Impianti Ed Attrezzature Per Agricoltura E Zootecnia. Macchine, Strumenti Ed Apparecchi Per Attivita' Industriali",
    "sg:phone":"+39 0171 214424",
    "sg:postcode":"12044",
    "sg:province":"Cuneo",
    "wof:name":"Abba' Giuseppe",
    "wof:placetype":"venue"
},
  "geometry": {"coordinates":[7.583389,44.501472],"type":"Point"}
}