{
  "type": "Feature",
  "properties": {
    "iso:country":"IT",
    "sg:address":"40133 Bologna",
    "sg:city":"Bologna",
    "sg:orig_category":"Arredo Bagno Ed Idrosanitari",
    "sg:phone":"+39 051 619 0109",
    "sg:postcode":"40133",
    "sg:province":"Bologna",
    "sg:website":"http://www.fraver.it",
    "wof:name":"Veronesi Fratelli Srl",
    "wof:placetype":"venue"
},
  "geometry": {"coordinates":[11.302074,44.502007],"type":"Point"}
}