{
  "type": "Feature",
  "properties": {
    "iso:country":"IT",
    "sg:address":"20122 Milano",
    "sg:city":"Milano",
    "sg:orig_category":"Professionisti - Studi E Servizi Ed Associazioni Di Interesse Aziendale. Associazioni Ed Organismi Di Interesse Pubblico. Chiese Ed Associazioni Religiose",
    "sg:phone":"+39 02 782389",
    "sg:postcode":"20122",
    "sg:province":"Milano",
    "wof:name":"Convento Dei Servi Di Maria",
    "wof:placetype":"venue"
},
  "geometry": {"coordinates":[9.1965408325,45.4661254883],"type":"Point"}
}