{
  "type": "Feature",
  "properties": {
    "addr:full":"80131 Napoli Napoli Napoli 80131",
    "addr:housenumber":"80131",
    "addr:postcode":"80131",
    "iso:country":"IT",
    "sg:address":"80131 Napoli",
    "sg:city":"Napoli",
    "sg:orig_category":"Ospedali E Servizi Sanitari. Servizi Sociali",
    "sg:phone":"+39 081 741 0115",
    "sg:postcode":"80131",
    "sg:province":"Napoli",
    "wof:name":"M&t Service Srl",
    "wof:placetype":"venue"
},
  "geometry": {"coordinates":[14.239138,40.87088],"type":"Point"}
}