{
  "type": "Feature",
  "properties": {
    "iso:country":"IT",
    "sg:address":"92019 Sciacca",
    "sg:city":"Sciacca",
    "sg:orig_category":"Carpenterie Ferro",
    "sg:phone":"+39 0925 26993",
    "sg:postcode":"92019",
    "sg:province":"Agrigento",
    "wof:name":"Venezia Giuseppe Lavorazione In Ferro E Acciaio",
    "wof:placetype":"venue"
},
  "geometry": {"coordinates":[13.582274,37.320301],"type":"Point"}
}