{
  "type": "Feature",
  "properties": {
    "addr:full":"93, Via Plaja 95121 Catania Catania Catania 95121",
    "addr:postcode":"95121;95121",
    "addr:street":"Via Plaja",
    "iso:country":"IT",
    "sg:address":"93, Via Plaja 95121 Catania",
    "sg:city":"Catania",
    "sg:classifiers":[
        {
            "category":"Food & Beverages",
            "subcategory":"Bakery",
            "type":"Retail Goods"
        }
    ],
    "sg:phone":"+39 39095340144",
    "sg:postcode":"95121",
    "sg:province":"Catania",
    "sg:tags":[
        "grain",
        "cereal"
    ],
    "wof:name":"Mulini Maione Filippo (s.p.a.)",
    "wof:placetype":"venue"
},
  "geometry": {"coordinates":[15.066168,37.467422],"type":"Point"}
}