{
  "type": "Feature",
  "properties": {
    "iso:country":"IT",
    "sg:address":"6, Via Catti 45015 Corbola",
    "sg:city":"Corbola",
    "sg:classifiers":[
        {
            "category":"Shopping",
            "subcategory":"Clothing, Apparel, & Fashions",
            "type":"Retail Goods"
        }
    ],
    "sg:phone":"+39 39042645173",
    "sg:postcode":"45015",
    "sg:province":"Rovigo",
    "sg:tags":[
        "clothes"
    ],
    "wof:name":"Crepaldi Mario",
    "wof:placetype":"venue"
},
  "geometry": {"coordinates":[12.088241,44.980495],"type":"Point"}
}