{
  "type": "Feature",
  "properties": {
    "iso:country":"IT",
    "sg:address":"12, Via Piave 31100 Treviso",
    "sg:city":"Treviso",
    "sg:classifiers":[
        {
            "category":"Utilities",
            "subcategory":"Telephone",
            "type":"Services"
        }
    ],
    "sg:phone":"+39 0422 300866",
    "sg:postcode":"31100",
    "sg:province":"Treviso",
    "sg:tags":[
        "telecommunication"
    ],
    "wof:name":"Neon Pubbli Lux",
    "wof:placetype":"venue"
},
  "geometry": {"coordinates":[12.163977,45.647884],"type":"Point"}
}