{
  "type": "Feature",
  "properties": {
    "iso:country":"IT",
    "sg:address":"Via Sampoi 73 32020 Limana",
    "sg:city":"Limana",
    "sg:classifiers":[
        {
            "category":"Manufacturing",
            "subcategory":"Rubber & Plastics",
            "type":"Manufacturing & Wholesale Goods"
        }
    ],
    "sg:phone":"+39 0437 968711",
    "sg:postcode":"32020",
    "sg:province":"Belluno",
    "sg:tags":[
        "mould",
        "industry"
    ],
    "sg:website":"www.meccanostampi.it",
    "wof:name":"Meccanostampi Srl",
    "wof:placetype":"venue"
},
  "geometry": {"coordinates":[12.1821603775,46.1020393372],"type":"Point"}
}