{
  "type": "Feature",
  "properties": {
    "addr:full":"6, V. Calamattia 09134 Cagliari Cagliari Cagliari 09134",
    "addr:housenumber":"6",
    "addr:postcode":"09134;09134",
    "addr:street":"V. Calamattia",
    "iso:country":"IT",
    "sg:address":"6, V. Calamattia 09134 Cagliari",
    "sg:city":"Cagliari",
    "sg:classifiers":[
        {
            "category":"Manufacturing",
            "subcategory":"Glass & Minerals",
            "type":"Manufacturing & Wholesale Goods"
        }
    ],
    "sg:phone":"+39 39070521632",
    "sg:postcode":"09134",
    "sg:province":"Cagliari",
    "sg:website":"http://www.paginegialle.it/laborvetro-01",
    "wof:name":"Laborvetro",
    "wof:placetype":"venue"
},
  "geometry": {"coordinates":[9.122645,39.238777],"type":"Point"}
}