{
  "type": "Feature",
  "properties": {
    "iso:country":"IT",
    "sg:address":"1, Via Kennedy 21055 Gorla Minore",
    "sg:city":"Gorla Minore",
    "sg:classifiers":[
        {
            "category":"Professional",
            "subcategory":"Engineering",
            "type":"Services"
        }
    ],
    "sg:phone":"+39 0331 366193",
    "sg:postcode":"21055",
    "sg:province":"Varese",
    "sg:tags":[
        "machine",
        "-",
        "mechanical"
    ],
    "wof:name":"Stabile Srl",
    "wof:placetype":"venue"
},
  "geometry": {"coordinates":[8.896624,45.653038],"type":"Point"}
}