{
  "type": "Feature",
  "properties": {
    "addr:full":"22, Via Doberdo' 20126 Milano Milano Milano 20126",
    "addr:postcode":"20126;20126",
    "addr:street":"Via Doberdo '",
    "iso:country":"IT",
    "sg:address":"22, Via Doberdo' 20126 Milano",
    "sg:city":"Milano",
    "sg:classifiers":[
        {
            "category":"Banks & Credit Unions",
            "subcategory":"Bank",
            "type":"Services"
        }
    ],
    "sg:phone":"+39 39022579732",
    "sg:postcode":"20126",
    "sg:province":"Milano",
    "sg:tags":[
        "banking",
        "institution"
    ],
    "wof:name":"Team Prodec S.r.l.",
    "wof:placetype":"venue"
},
  "geometry": {"coordinates":[9.223322,45.519215],"type":"Point"}
}