{
  "type": "Feature",
  "properties": {
    "addr:full":"73045 Leverano Leverano Lecce 73045",
    "addr:postcode":"73045;73045",
    "iso:country":"IT",
    "sg:address":"73045 Leverano",
    "sg:city":"Leverano",
    "sg:orig_category":"Concimi E Fertilizzanti",
    "sg:phone":"+39 0832 925053",
    "sg:postcode":"73045",
    "sg:province":"Lecce",
    "wof:name":"Cantina Sociale Cooperativa Di Leverano Srl",
    "wof:placetype":"venue"
},
  "geometry": {"coordinates":[18.081083,40.401054],"type":"Point"}
}