{
  "type": "Feature",
  "properties": {
    "iso:country":"IT",
    "sg:address":"Via Provinciale Verzuolo 2 12026 Piasco",
    "sg:city":"Piasco",
    "sg:classifiers":[
        {
            "category":"Military Area",
            "subcategory":"Air Force Base",
            "type":"Public Place"
        }
    ],
    "sg:phone":"+39 0175 79301",
    "sg:postcode":"12026",
    "sg:province":"Cuneo",
    "sg:tags":[
        "gear",
        "hoisting"
    ],
    "wof:name":"Gruniverpal Tranchero Snc",
    "wof:placetype":"venue"
},
  "geometry": {"coordinates":[7.461833,44.574162],"type":"Point"}
}