{
  "type": "Feature",
  "properties": {
    "iso:country":"IT",
    "sg:address":"27055 Rivanazzano",
    "sg:city":"Rivanazzano",
    "sg:orig_category":"Arredo Camera Letto E Complementi",
    "sg:phone":"+39 0383 93194",
    "sg:postcode":"27055",
    "sg:province":"Pavia",
    "wof:name":"Euroflex Srl",
    "wof:placetype":"venue"
},
  "geometry": {"coordinates":[9.137446,45.238136],"type":"Point"}
}