{
  "type": "Feature",
  "properties": {
    "addr:full":"10156 Torino Torino Torino 10156",
    "addr:postcode":"10156;10156",
    "iso:country":"IT",
    "sg:address":"10156 Torino",
    "sg:city":"Torino",
    "sg:orig_category":"Filati E Materie Prime Tessili",
    "sg:phone":"+39 011 223 8998",
    "sg:postcode":"10156",
    "sg:province":"Torino",
    "wof:name":"Freudenberg (s.p.a.)",
    "wof:placetype":"venue"
},
  "geometry": {"coordinates":[7.7061495781,45.1193466187],"type":"Point"}
}