{
  "type": "Feature",
  "properties": {
    "addr:full":"Via Di Vittorio 43038 Sala Baganza Sala Baganza Parma 43038",
    "addr:housenumber":"baganza",
    "addr:postcode":"43038;43038",
    "addr:street":"Via Di Vittorio;Parma",
    "iso:country":"IT",
    "sg:address":"Via Di Vittorio 43038 Sala Baganza",
    "sg:city":"Sala Baganza",
    "sg:classifiers":[
        {
            "category":"Shopping",
            "type":"Retail Goods"
        }
    ],
    "sg:phone":"+39 0521 833586",
    "sg:postcode":"43038",
    "sg:province":"Parma",
    "sg:tags":[
        "finished",
        "-",
        "metallic"
    ],
    "wof:name":"Emilsilo (s.r.l.)",
    "wof:placetype":"venue"
},
  "geometry": {"coordinates":[10.2305192947,44.7100067139],"type":"Point"}
}