{
  "type": "Feature",
  "properties": {
    "addr:full":"35020 Legnaro Legnaro Padova 35020",
    "addr:postcode":"35020;35020",
    "iso:country":"IT",
    "sg:address":"35020 Legnaro",
    "sg:city":"Legnaro",
    "sg:orig_category":"Prodotti Vari In Metallo",
    "sg:phone":"+39 049 641157",
    "sg:postcode":"35020",
    "sg:province":"Padova",
    "wof:name":"Giacometti Fratelli",
    "wof:placetype":"venue"
},
  "geometry": {"coordinates":[11.966176033,45.3423309326],"type":"Point"}
}