{
  "type": "Feature",
  "properties": {
    "iso:country":"IT",
    "sg:address":"50041 Calenzano",
    "sg:city":"Calenzano",
    "sg:orig_category":"Forniture Ospedaliere",
    "sg:phone":"+39 055 882 5498",
    "sg:postcode":"50041",
    "sg:province":"Firenze",
    "sg:website":"http://www.montex.it",
    "wof:name":"Mon&tex Spa",
    "wof:placetype":"venue"
},
  "geometry": {"coordinates":[11.2085819244,43.8370933533],"type":"Point"}
}