{
  "type": "Feature",
  "properties": {
    "addr:full":"10128 Torino Torino Torino 10128",
    "addr:postcode":"10128;10128",
    "iso:country":"IT",
    "sg:address":"10128 Torino",
    "sg:city":"Torino",
    "sg:orig_category":"Utensili Meccanici E Materiali",
    "sg:phone":"+39 011 504989",
    "sg:postcode":"10128",
    "sg:province":"Torino",
    "wof:name":"O.s.l. Magivi Srl",
    "wof:placetype":"venue"
},
  "geometry": {"coordinates":[7.665637,45.051918],"type":"Point"}
}