{
  "type": "Feature",
  "properties": {
    "iso:country":"IT",
    "sg:address":"Via G. Carducci 34 25069 Villa Carcina",
    "sg:city":"Carcina",
    "sg:orig_category":"Manufacturers: Equipment For Electroplated Diamond And Cubic Boron Nitride Cbn Tools",
    "sg:phone":"+39 030 800565",
    "sg:postcode":"25069",
    "sg:province":"Brescia",
    "sg:website":"www.buffoligroup.com",
    "wof:name":"Fratelli Buffoli Srl",
    "wof:placetype":"venue"
},
  "geometry": {"coordinates":[10.218349,45.604637],"type":"Point"}
}