{
  "type": "Feature",
  "properties": {
    "iso:country":"IT",
    "sg:address":"Via P. Di Piemonte, 51/a; Casoria; 80026",
    "sg:city":"Casoria",
    "sg:classifiers":[
        {
            "category":"Banks & Credit Unions",
            "subcategory":"Bank",
            "type":"Services"
        }
    ],
    "sg:phone":"+39 081 758 3012",
    "sg:postcode":"80026",
    "sg:province":"Napoli",
    "wof:name":"Banca Popolare Di Novara",
    "wof:placetype":"venue"
},
  "geometry": {"coordinates":[14.285766,40.901634],"type":"Point"}
}