{
  "type": "Feature",
  "properties": {
    "addr:full":"7, Via Paghera 24060 Castelli Calepio Castelli Calepio Bergamo 24060",
    "addr:postcode":"24060;24060",
    "addr:street":"Via Paghera",
    "iso:country":"IT",
    "sg:address":"7, Via Paghera 24060 Castelli Calepio",
    "sg:city":"Castelli Calepio",
    "sg:classifiers":[
        {
            "category":"Manufacturing",
            "subcategory":"Metals",
            "type":"Manufacturing & Wholesale Goods"
        }
    ],
    "sg:phone":"+39 39035847433",
    "sg:postcode":"24060",
    "sg:province":"Bergamo",
    "sg:tags":[
        "processing"
    ],
    "wof:name":"Sabrorazi (s.r.l.)",
    "wof:placetype":"venue"
},
  "geometry": {"coordinates":[9.8892183304,45.6277389526],"type":"Point"}
}