{
  "type": "Feature",
  "properties": {
    "iso:country":"IT",
    "sg:address":"36100 Vicenza",
    "sg:city":"Vicenza",
    "sg:orig_category":"Elettronica Professionale E Di Consumo. Musica. Accessori Dei Mezzi Di Trasporto",
    "sg:phone":"+39 0444 965353",
    "sg:postcode":"36100",
    "sg:province":"Vicenza",
    "wof:name":"Centro Autoradio Srl",
    "wof:placetype":"venue"
},
  "geometry": {"coordinates":[11.561045,45.53619],"type":"Point"}
}