{
  "type": "Feature",
  "properties": {
    "iso:country":"IT",
    "sg:address":"41100 Modena",
    "sg:city":"Modena",
    "sg:orig_category":"Medici Specialisti - Chirurgia Plastica E Ricostruttiva",
    "sg:phone":"+39 059 243570",
    "sg:postcode":"41100",
    "sg:province":"Modena",
    "sg:website":"http://www.gennaichirurgia.it",
    "wof:name":"Gennai Dr. Alessandro",
    "wof:placetype":"venue"
},
  "geometry": {"coordinates":[10.923098,44.648556],"type":"Point"}
}