{
  "type": "Feature",
  "properties": {
    "addr:full":"54, Via Piossasco Rivalta 10090 Bruino Bruino Torino 10090",
    "addr:postcode":"10090;10090",
    "addr:street":"Via Piossasco Rivalta",
    "iso:country":"IT",
    "sg:address":"54, Via Piossasco Rivalta 10090 Bruino",
    "sg:city":"Bruino",
    "sg:classifiers":[
        {
            "category":"Professional",
            "subcategory":"Engineering",
            "type":"Services"
        }
    ],
    "sg:phone":"+39 011 904 8052",
    "sg:postcode":"10090",
    "sg:province":"Torino",
    "sg:tags":[
        "machine",
        "-",
        "mechanical"
    ],
    "wof:name":"Co.ma.t Srl",
    "wof:placetype":"venue"
},
  "geometry": {"coordinates":[7.486368,45.003326],"type":"Point"}
}