{
  "type": "Feature",
  "properties": {
    "iso:country":"IT",
    "sg:address":"Via Lama Di Macina 70052 Bisceglie",
    "sg:city":"Bisceglie",
    "sg:classifiers":[
        {
            "category":"Manufacturing",
            "subcategory":"Lumber",
            "type":"Manufacturing & Wholesale Goods"
        }
    ],
    "sg:phone":"+39 080 392 2505",
    "sg:postcode":"70052",
    "sg:province":"Bari",
    "sg:tags":[
        "wood"
    ],
    "wof:name":"Wood Box S.r.l.",
    "wof:placetype":"venue"
},
  "geometry": {"coordinates":[16.514603,41.228569],"type":"Point"}
}