{
  "type": "Feature",
  "properties": {
    "addr:full":"20020 Arese Arese Milano 20020",
    "addr:postcode":"20020;20020",
    "iso:country":"IT",
    "sg:address":"20020 Arese",
    "sg:city":"Arese",
    "sg:orig_category":"Pompe. Apparecchiature E Sistemi Per Imballaggio E Confezionamento",
    "sg:phone":"+39 02 9358 2660",
    "sg:postcode":"20020",
    "sg:province":"Milano",
    "sg:website":"http://www.pompe-lewa.it",
    "wof:name":"Pompe Lewa Srl",
    "wof:placetype":"venue"
},
  "geometry": {"coordinates":[9.0887641907,45.5370826721],"type":"Point"}
}