{
  "type": "Feature",
  "properties": {
    "iso:country":"IT",
    "sg:address":"00050 Fregene",
    "sg:orig_category":"Alberghi E Strutture Extra Alberghiere. Ospedali E Servizi Sanitari",
    "sg:phone":"+39 06 6656 0472",
    "sg:postcode":"00050",
    "sg:province":"Roma",
    "wof:name":"Ministero Difesa Marina",
    "wof:placetype":"venue"
},
  "geometry": {"coordinates":[12.192988,41.85989],"type":"Point"}
}