{
  "type": "Feature",
  "properties": {
    "iso:country":"IT",
    "sg:address":"35131 Padova",
    "sg:city":"Padova",
    "sg:orig_category":"Informatica - Consulenza E Servizi. Servizi Ausiliari Di Analisi, Controllo E Ricerca. Servizi Per Aziende, Manifestazioni E Supporto Agli Scambi Commerciali",
    "sg:phone":"+39 049 875 3854",
    "sg:postcode":"35131",
    "sg:province":"Padova",
    "wof:name":"Studio Faggian Rag. Renato",
    "wof:placetype":"venue"
},
  "geometry": {"coordinates":[11.892819,45.413452],"type":"Point"}
}