{
  "type": "Feature",
  "properties": {
    "addr:full":"39020 Parcines Parcines Bolzano/Bozen 39020",
    "addr:postcode":"39020;39020",
    "iso:country":"IT",
    "sg:address":"39020 Parcines",
    "sg:city":"Parcines",
    "sg:orig_category":"Imprese Di Costruzioni Civili Ed Industriali",
    "sg:phone":"+39 0473 967083",
    "sg:postcode":"39020",
    "sg:province":"Bolzano/Bozen",
    "wof:name":"Pf\u00d6stl Maria",
    "wof:placetype":"venue"
},
  "geometry": {"coordinates":[11.059003,46.670086],"type":"Point"}
}