{
  "type": "Feature",
  "properties": {
    "iso:country":"IT",
    "sg:address":"19124 La Spezia",
    "sg:orig_category":"Motori Ed Organi Di Trasmissione. Ricambi E Componenti Dei Mezzi Di Trasporto",
    "sg:phone":"+39 0187 511133",
    "sg:province":"SP",
    "wof:name":"Bruno Srl",
    "wof:placetype":"venue"
},
  "geometry": {"coordinates":[9.8250484467,44.1140861511],"type":"Point"}
}