{
  "type": "Feature",
  "properties": {
    "iso:country":"IT",
    "sg:address":"35010 San Giorgio In Bosco",
    "sg:city":"San Giorgio in Bosco",
    "sg:orig_category":"Abiti Da Lavoro Ed Indumenti Protettivi",
    "sg:phone":"+39 049 945 4434",
    "sg:postcode":"35010",
    "sg:province":"Padova",
    "wof:name":"Tecnoingros Sas",
    "wof:placetype":"venue"
},
  "geometry": {"coordinates":[11.806621,45.59063],"type":"Point"}
}