{
  "type": "Feature",
  "properties": {
    "iso:country":"IT",
    "sg:address":"30174 Venezia",
    "sg:city":"Venezia",
    "sg:classifiers":[
        {
            "category":"Shopping",
            "subcategory":"Bicycles & Sporting Goods",
            "type":"Retail Goods"
        }
    ],
    "sg:phone":"+39 041 906029",
    "sg:postcode":"30174",
    "sg:province":"Venezia",
    "sg:tags":[
        "tempo",
        "lo",
        "-",
        "libero",
        "per",
        "servizi",
        "forniture",
        "articoli",
        "e",
        "sport",
        "il"
    ],
    "wof:name":"Mestre Scuba Team",
    "wof:placetype":"venue"
},
  "geometry": {"coordinates":[12.20288,45.517731],"type":"Point"}
}