{
  "type": "Feature",
  "properties": {
    "iso:country":"IT",
    "sg:address":"33, Viale Vicenza 15048 Valenza",
    "sg:city":"Valenza",
    "sg:classifiers":[
        {
            "category":"Shopping",
            "subcategory":"Jewelry",
            "type":"Retail Goods"
        }
    ],
    "sg:phone":"+39 0131 924345",
    "sg:postcode":"15048",
    "sg:province":"Alessandria",
    "sg:tags":[
        "jewellery"
    ],
    "wof:name":"Accornero",
    "wof:placetype":"venue"
},
  "geometry": {"coordinates":[8.648447,45.01506],"type":"Point"}
}