{
  "type": "Feature",
  "properties": {
    "iso:country":"IT",
    "sg:address":"20147 Milano",
    "sg:city":"Milano",
    "sg:orig_category":"Abbigliamento Esterno, Maglierie E Pelliccerie. Calzature, Pelletterie E Pelli",
    "sg:phone":"+39 02 404 1889",
    "sg:postcode":"20147",
    "sg:province":"Milano",
    "wof:name":"Styledil Snc Di R. Bordieri & C.",
    "wof:placetype":"venue"
},
  "geometry": {"coordinates":[9.125766,45.456024],"type":"Point"}
}