{
  "type": "Feature",
  "properties": {
    "iso:country":"IT",
    "sg:address":"C Palladio 108; Vicenza; 36100",
    "sg:city":"Vicenza",
    "sg:classifiers":[
        {
            "category":"Banks & Credit Unions",
            "subcategory":"Bank",
            "type":"Services"
        }
    ],
    "sg:phone":"+39 0444 320635",
    "sg:postcode":"36100",
    "sg:province":"Vicenza",
    "wof:name":"Banco Ambrosiano Veneto Spa",
    "wof:placetype":"venue"
},
  "geometry": {"coordinates":[11.545986,45.548046],"type":"Point"}
}