{
  "type": "Feature",
  "properties": {
    "iso:country":"IT",
    "sg:address":"20, Via Ariberto 20123 Milano",
    "sg:city":"Milano",
    "sg:classifiers":[
        {
            "category":"Wholesale",
            "subcategory":"Drugs",
            "type":"Manufacturing & Wholesale Goods"
        }
    ],
    "sg:phone":"+39 02 8940 7890",
    "sg:postcode":"20123",
    "sg:province":"Milano",
    "sg:tags":[
        "chemical",
        "pharmaceutical"
    ],
    "wof:name":"Bellini (s.a.s.)",
    "wof:placetype":"venue"
},
  "geometry": {"coordinates":[9.172786,45.459129],"type":"Point"}
}