{
  "type": "Feature",
  "properties": {
    "addr:full":"20148 Milano Milano Milano 20148",
    "addr:postcode":"20148;20148",
    "iso:country":"IT",
    "sg:address":"20148 Milano",
    "sg:city":"Milano",
    "sg:orig_category":"Studi E Consulenze Tecniche E Industriali. Assicurazioni E Servizi Assicurativi. Consulenze Tecniche, Amministrative E Perizie",
    "sg:phone":"+39 02 403 9283",
    "sg:postcode":"20148",
    "sg:province":"Milano",
    "wof:name":"G.s.a. Sas - Gestione Servizi Assicurativi",
    "wof:placetype":"venue"
},
  "geometry": {"coordinates":[9.129233,45.471653],"type":"Point"}
}