{
  "type": "Feature",
  "properties": {
    "addr:full":"20093 Cologno Monzese Cologno Monzese Milano 20093",
    "addr:postcode":"20093;20093",
    "iso:country":"IT",
    "sg:address":"20093 Cologno Monzese",
    "sg:city":"Cologno Monzese",
    "sg:orig_category":"Materiali E Componenti Elettrotecnici",
    "sg:phone":"+39 02 251571",
    "sg:postcode":"20093",
    "sg:province":"Milano",
    "sg:website":"http://www.galvanicheripamonti.it",
    "wof:name":"Galvaniche Ripamonti Spa",
    "wof:placetype":"venue"
},
  "geometry": {"coordinates":[9.265991,45.53558],"type":"Point"}
}