{
  "type": "Feature",
  "properties": {
    "iso:country":"IT",
    "sg:address":"Via Alcide De Gasperi, 6/8 25030 Zocco",
    "sg:city":"Zocco",
    "sg:classifiers":[
        {
            "category":"Banks & Credit Unions",
            "subcategory":"Investment Brokerage",
            "type":"Services"
        }
    ],
    "sg:phone":"+39 030 726 7734",
    "sg:postcode":"25030",
    "sg:province":"Brescia",
    "sg:tags":[
        "women's",
        "clothing",
        "accessory"
    ],
    "wof:name":"Pelletteria 3 Corone Srl",
    "wof:placetype":"venue"
},
  "geometry": {"coordinates":[9.93273,45.604061],"type":"Point"}
}