{
  "type": "Feature",
  "properties": {
    "iso:country":"IT",
    "sg:address":"17, Via Stazione 39040 Ora",
    "sg:city":"Ora",
    "sg:classifiers":[
        {
            "category":"Manufacturing",
            "subcategory":"Lumber",
            "type":"Manufacturing & Wholesale Goods"
        }
    ],
    "sg:phone":"+39 0471 810093",
    "sg:postcode":"39040",
    "sg:province":"Bolzano/Bozen",
    "sg:tags":[
        "wood"
    ],
    "wof:name":"Legnosud S.p.a.",
    "wof:placetype":"venue"
},
  "geometry": {"coordinates":[11.298966,46.351715],"type":"Point"}
}