{
  "type": "Feature",
  "properties": {
    "addr:full":"33, Via Giulio Pastore 25040 Corte Franca Corte Franca Brescia 25040",
    "addr:postcode":"25040;25040",
    "addr:street":"Via Giulio Pastore",
    "iso:country":"IT",
    "sg:address":"33, Via Giulio Pastore 25040 Corte Franca",
    "sg:city":"Corte Franca",
    "sg:classifiers":[
        {
            "category":"Manufacturing",
            "subcategory":"Rubber & Plastics",
            "type":"Manufacturing & Wholesale Goods"
        }
    ],
    "sg:phone":"+39 030 986 0511",
    "sg:postcode":"25040",
    "sg:province":"Brescia",
    "wof:name":"Valerio Franceschetti Elastomeri Spa",
    "wof:placetype":"venue"
},
  "geometry": {"coordinates":[10.0010528564,45.6296844482],"type":"Point"}
}