{
  "type": "Feature",
  "properties": {
    "addr:full":"00155 Roma Roma Roma 00155",
    "addr:postcode":"00155;00155",
    "iso:country":"IT",
    "sg:address":"00155 Roma",
    "sg:city":"Roma",
    "sg:orig_category":"Forniture Per Edilizia E Lavori Pubblici. Prodotti Vari In Metallo",
    "sg:phone":"+39 06 228 8971",
    "sg:postcode":"00155",
    "sg:province":"Roma",
    "wof:name":"Ponteggi Dalmine (s.p.a.)",
    "wof:placetype":"venue"
},
  "geometry": {"coordinates":[12.8843755722,41.889793396],"type":"Point"}
}