{
  "type": "Feature",
  "properties": {
    "iso:country":"IT",
    "sg:address":"21, Via Trieste 27011 Belgioioso",
    "sg:city":"Belgioioso",
    "sg:classifiers":[
        {
            "category":"Real Estate",
            "subcategory":"Architect",
            "type":"Services"
        }
    ],
    "sg:phone":"+39 0382 969619",
    "sg:postcode":"27011",
    "sg:province":"Pavia",
    "sg:tags":[
        "textile",
        "clothing"
    ],
    "wof:name":"Intimoda Line Di Grugni Sandro",
    "wof:placetype":"venue"
},
  "geometry": {"coordinates":[9.312167,45.156654],"type":"Point"}
}