{
  "type": "Feature",
  "properties": {
    "iso:country":"IT",
    "sg:address":"09043 Muravera",
    "sg:city":"Muravera",
    "sg:orig_category":"Agenzie Immobiliari",
    "sg:phone":"+39 070 999032",
    "sg:postcode":"09043",
    "sg:province":"Cagliari",
    "sg:website":"http://www.camping-torre-salinas.de",
    "wof:name":"Campeggio Salinas Di Buske E Gierstorfer",
    "wof:placetype":"venue"
},
  "geometry": {"coordinates":[9.578475,39.329151],"type":"Point"}
}