{
  "type": "Feature",
  "properties": {
    "addr:full":"57/59, Via Delle Fornaci 50023 Impruneta Impruneta Firenze 50023",
    "addr:housenumber":"57 / 59",
    "addr:postcode":"50023;50023",
    "addr:street":"Via Delle Fornaci",
    "iso:country":"IT",
    "sg:address":"57/59, Via Delle Fornaci 50023 Impruneta",
    "sg:city":"Impruneta",
    "sg:classifiers":[
        {
            "category":"Home & Garden",
            "subcategory":"Home Furnishings",
            "type":"Retail Goods"
        }
    ],
    "sg:phone":"+39 055 201 1683",
    "sg:postcode":"50023",
    "sg:province":"Firenze",
    "sg:tags":[
        "household"
    ],
    "wof:name":"Masini F.lli Snc",
    "wof:placetype":"venue"
},
  "geometry": {"coordinates":[11.25225,43.682541],"type":"Point"}
}