{
  "type": "Feature",
  "properties": {
    "iso:country":"IT",
    "sg:address":"Via E. Fermi 2 72100 Brindisi",
    "sg:city":"Brindisi",
    "sg:classifiers":[
        {
            "category":"Community Center",
            "subcategory":"Social",
            "type":"Public Place"
        }
    ],
    "sg:phone":"+39 0831 548482",
    "sg:postcode":"72100",
    "sg:province":"Brindisi",
    "sg:tags":[
        "profile",
        "aluminium",
        "system",
        "accessory"
    ],
    "sg:website":"www.simpres.it/marchionna",
    "wof:name":"Marchionna S.r.l.",
    "wof:placetype":"venue"
},
  "geometry": {"coordinates":[17.942587,40.66259],"type":"Point"}
}