{
  "type": "Feature",
  "properties": {
    "iso:country":"IT",
    "sg:address":"3/a, Via Oberdan Guglielmo 27029 Vigevano",
    "sg:city":"Vigevano",
    "sg:classifiers":[
        {
            "category":"Personal",
            "subcategory":"Shoe Repair & Shine",
            "type":"Services"
        }
    ],
    "sg:phone":"+39 39038173728",
    "sg:postcode":"27029",
    "sg:province":"Pavia",
    "sg:tags":[
        "leather"
    ],
    "wof:name":"Effegi Srl Manufatture Suole",
    "wof:placetype":"venue"
},
  "geometry": {"coordinates":[9.156563,45.185886],"type":"Point"}
}