{
  "type": "Feature",
  "properties": {
    "iso:country":"IT",
    "sg:address":"42100 Reggio Emilia",
    "sg:orig_category":"Articoli Natalizi",
    "sg:phone":"+39 0522 268064",
    "sg:postcode":"42100",
    "sg:province":"Reggio Nell'Emilia",
    "wof:name":"Le Vetrine Di Chicca Di Tietto Cristina",
    "wof:placetype":"venue"
},
  "geometry": {"coordinates":[10.666919,44.682346],"type":"Point"}
}