{
  "type": "Feature",
  "properties": {
    "addr:full":"50121 Firenze Firenze Firenze 50121",
    "addr:postcode":"50121;50121",
    "iso:country":"IT",
    "sg:address":"50121 Firenze",
    "sg:city":"Firenze",
    "sg:orig_category":"Climatizzazione E Condizionamento, Apparecchiature E Servizi",
    "sg:phone":"+39 055 661277",
    "sg:postcode":"50121",
    "sg:province":"Firenze",
    "wof:name":"Muro Therapie International",
    "wof:placetype":"venue"
},
  "geometry": {"coordinates":[11.267967,43.774639],"type":"Point"}
}