{
  "type": "Feature",
  "properties": {
    "iso:country":"IT",
    "sg:address":"30030 Salzano",
    "sg:city":"Salzano",
    "sg:orig_category":"Acciaierie E Fonderie",
    "sg:phone":"+39 041 437036",
    "sg:postcode":"30030",
    "sg:province":"Venezia",
    "wof:name":"Fometal Di Marchiori & C. Snc",
    "wof:placetype":"venue"
},
  "geometry": {"coordinates":[12.138499,45.527637],"type":"Point"}
}