{
  "type": "Feature",
  "properties": {
    "iso:country":"IT",
    "sg:address":"20068 Peschiera Borromeo",
    "sg:city":"Peschiera Borromeo",
    "sg:orig_category":"Servizi Culturali E Per Lo Spettacolo. Musica",
    "sg:phone":"+39 02 547 3062",
    "sg:postcode":"20068",
    "sg:province":"Milano",
    "wof:name":"Griffini Fulvio",
    "wof:placetype":"venue"
},
  "geometry": {"coordinates":[9.306401,45.42934],"type":"Point"}
}