{
  "type": "Feature",
  "properties": {
    "iso:country":"IT",
    "sg:address":"80126 Napoli",
    "sg:city":"Napoli",
    "sg:orig_category":"Arredo Bagno Ed Idrosanitari. Forniture Alle Strutture Ricettive. Apparecchi, Attrezzature E Forniture Per Centri Estetici",
    "sg:phone":"+39 081 588 5458",
    "sg:postcode":"80126",
    "sg:province":"Napoli",
    "wof:name":"Tecno House Sas",
    "wof:placetype":"venue"
},
  "geometry": {"coordinates":[14.175657,40.857288],"type":"Point"}
}