{
  "type": "Feature",
  "properties": {
    "iso:country":"IT",
    "sg:address":"30034 Mira",
    "sg:city":"Mira",
    "sg:orig_category":"Non-classified Establishments",
    "sg:phone":"+39 041 560 0923",
    "sg:postcode":"30034",
    "sg:province":"Venezia",
    "wof:name":"Navali Allestimenti Interni Di Confalonieri Umberto E C. S.a.s.",
    "wof:placetype":"venue"
},
  "geometry": {"coordinates":[12.138432,45.429783],"type":"Point"}
}