{
  "type": "Feature",
  "properties": {
    "addr:full":"Via Dell' Artigianato 9 20040 Usmate Milano 20040",
    "addr:housenumber":"9",
    "addr:postcode":"20040;20040",
    "addr:street":"Via Dell ' Artigianato",
    "iso:country":"IT",
    "sg:address":"Via Dell' Artigianato 9 20040 Usmate",
    "sg:orig_category":"Torque Wrenches",
    "sg:phone":"+39 039 674819",
    "sg:postcode":"20040",
    "sg:province":"Milano",
    "sg:website":"www.tecnogisrl.it",
    "wof:name":"Tecnogi Srl",
    "wof:placetype":"venue"
},
  "geometry": {"coordinates":[9.188141,45.463688],"type":"Point"}
}