{
  "type": "Feature",
  "properties": {
    "iso:country":"IT",
    "sg:address":"22100 Como",
    "sg:city":"Como",
    "sg:orig_category":"Prodotti E Manufatti In Gomma",
    "sg:phone":"+39 031 270186",
    "sg:postcode":"22100",
    "sg:province":"Como",
    "wof:name":"Banfi Guglielmo E Umberto S.n.c.",
    "wof:placetype":"venue"
},
  "geometry": {"coordinates":[9.0854110718,45.8101196289],"type":"Point"}
}