{
  "type": "Feature",
  "properties": {
    "iso:country":"IT",
    "sg:address":"46036 Revere",
    "sg:city":"Revere",
    "sg:orig_category":"Macchine, Impianti Ed Attrezzature Per Industria Alimentare E Bevande",
    "sg:phone":"+39 0386 46427",
    "sg:postcode":"46036",
    "sg:province":"Mantova",
    "wof:name":"Berselli Giovanni & C. (s.n.c.)",
    "wof:placetype":"venue"
},
  "geometry": {"coordinates":[10.715063,45.130711],"type":"Point"}
}