{
  "type": "Feature",
  "properties": {
    "iso:country":"IT",
    "sg:address":"Via Jacopo De Diacceto 48, 50129 Florence, Fi",
    "sg:classifiers":[
        {
            "category":"Banks & Credit Unions",
            "subcategory":"Bank",
            "type":"Services"
        }
    ],
    "sg:phone":"+39 055 27011",
    "sg:postcode":"50129",
    "sg:province":"Firenze",
    "wof:name":"Findomestic Banca Spa",
    "wof:placetype":"venue"
},
  "geometry": {"coordinates":[11.256902,43.768734],"type":"Point"}
}