{
  "type": "Feature",
  "properties": {
    "addr:full":"63030 Acquaviva Picena Acquaviva Picena Ascoli Piceno 63030",
    "addr:postcode":"63030;63030",
    "iso:country":"IT",
    "sg:address":"63030 Acquaviva Picena",
    "sg:city":"Acquaviva Picena",
    "sg:orig_category":"Materiali E Componenti Elettronici",
    "sg:phone":"+39 0735 587745",
    "sg:postcode":"63030",
    "sg:province":"Ascoli Piceno",
    "wof:name":"Ad.el. Electronics Srl",
    "wof:placetype":"venue"
},
  "geometry": {"coordinates":[13.570302,42.855843],"type":"Point"}
}