{
  "type": "Feature",
  "properties": {
    "iso:country":"IT",
    "sg:address":"20049 Concorezzo",
    "sg:city":"Concorezzo",
    "sg:orig_category":"Macchine, Impianti Ed Attrezzature Per Industria Alimentare E Bevande",
    "sg:phone":"+39 039 604 0437",
    "sg:postcode":"20049",
    "sg:province":"Milano",
    "wof:name":"Meroni Natale Snc",
    "wof:placetype":"venue"
},
  "geometry": {"coordinates":[9.209215,45.447094],"type":"Point"}
}