{
  "type": "Feature",
  "properties": {
    "addr:full":"22060 Figino Serenza Figino Serenza Como 22060",
    "addr:housenumber":"serenza",
    "addr:postcode":"22060;22060",
    "addr:street":"Como",
    "iso:country":"IT",
    "sg:address":"22060 Figino Serenza",
    "sg:city":"Figino Serenza",
    "sg:orig_category":"Curvatura E Conificatura Tubi",
    "sg:phone":"+39 031 782130",
    "sg:postcode":"22060",
    "sg:province":"Como",
    "wof:name":"Curvinox Srl",
    "wof:placetype":"venue"
},
  "geometry": {"coordinates":[9.129773,45.706081],"type":"Point"}
}