{
  "type": "Feature",
  "properties": {
    "addr:full":"59013 Montemurlo Montemurlo Prato 59013",
    "addr:postcode":"59013;59013",
    "iso:country":"IT",
    "sg:address":"59013 Montemurlo",
    "sg:city":"Montemurlo",
    "sg:orig_category":"Tessuti E Stoffe. Tessuti Arredamento, Tende E Tappeti",
    "sg:phone":"+39 0574 689249",
    "sg:postcode":"59013",
    "sg:province":"Prato",
    "wof:name":"Sintex Srl Soluzioni Innovative Tessili",
    "wof:placetype":"venue"
},
  "geometry": {"coordinates":[11.036492,43.911053],"type":"Point"}
}