{
  "type": "Feature",
  "properties": {
    "iso:country":"IT",
    "sg:address":"Via Stradone 37040 Boschi Sant'anna",
    "sg:orig_category":"Special-design Hydraulic Cylinders",
    "sg:phone":"+39 0442 99330",
    "sg:postcode":"37040",
    "sg:province":"Verona",
    "sg:website":"www.altersrl.com",
    "wof:name":"Alter Srl",
    "wof:placetype":"venue"
},
  "geometry": {"coordinates":[11.372732,45.203426],"type":"Point"}
}