{
  "type": "Feature",
  "properties": {
    "iso:country":"IT",
    "sg:address":"35129 Padova",
    "sg:city":"Padova",
    "sg:orig_category":"Forniture Per Attivita' Industriali",
    "sg:phone":"+39 049 775133",
    "sg:postcode":"35129",
    "sg:province":"Padova",
    "wof:name":"Ferramenta I.e.f. Spa",
    "wof:placetype":"venue"
},
  "geometry": {"coordinates":[11.9338588715,45.4247055054],"type":"Point"}
}