{
  "type": "Feature",
  "properties": {
    "addr:full":"33070 Vigonovo Di Fontanafredda Pordenone 33070",
    "addr:postcode":"33070;33070",
    "iso:country":"IT",
    "sg:address":"33070 Vigonovo Di Fontanafredda",
    "sg:orig_category":"Macchine E Forniture Per Ecologia E Smaltimento Rifiuti",
    "sg:phone":"+39 0434 567911",
    "sg:postcode":"33070",
    "sg:province":"Pordenone",
    "sg:website":"http://www.emmeti.com",
    "wof:name":"Emmeti Spa",
    "wof:placetype":"venue"
},
  "geometry": {"coordinates":[12.710835,46.037888],"type":"Point"}
}