{
  "type": "Feature",
  "properties": {
    "iso:country":"IT",
    "sg:address":"52100 Arezzo",
    "sg:city":"Arezzo",
    "sg:orig_category":"Gioielleria, Oreficeria E Argenteria",
    "sg:phone":"+39 0575 22101",
    "sg:postcode":"52100",
    "sg:province":"Arezzo",
    "sg:website":"http://www.farinex.com",
    "wof:name":"Far.in-ex Spa",
    "wof:placetype":"venue"
},
  "geometry": {"coordinates":[11.83962,43.462116],"type":"Point"}
}