{
  "type": "Feature",
  "properties": {
    "iso:country":"IT",
    "sg:address":"35010 Curtarolo",
    "sg:city":"Curtarolo",
    "sg:orig_category":"Prodotti E Manufatti In Materie Plastiche",
    "sg:phone":"+39 049 962 0751",
    "sg:postcode":"35010",
    "sg:province":"Padova",
    "wof:name":"Wood Design Di Bedin Aurelio",
    "wof:placetype":"venue"
},
  "geometry": {"coordinates":[11.8319950104,45.5379333496],"type":"Point"}
}