{
  "type": "Feature",
  "properties": {
    "iso:country":"IT",
    "sg:address":"09134 Cagliari",
    "sg:city":"Cagliari",
    "sg:orig_category":"Elettronica Professionale E Di Consumo. Tempo Libero - Articoli E Forniture",
    "sg:phone":"+39 070 504046",
    "sg:postcode":"09134",
    "sg:province":"Cagliari",
    "wof:name":"Sarda Games Srl",
    "wof:placetype":"venue"
},
  "geometry": {"coordinates":[9.123557,39.240871],"type":"Point"}
}