{
  "type": "Feature",
  "properties": {
    "iso:country":"IT",
    "sg:address":"25050 Passirano",
    "sg:city":"Passirano",
    "sg:orig_category":"Materiali Semilavorati Metallici",
    "sg:phone":"+39 030 654 9011",
    "sg:postcode":"25050",
    "sg:province":"Brescia",
    "wof:name":"Feinrohren Spa",
    "wof:placetype":"venue"
},
  "geometry": {"coordinates":[10.04312,45.575409],"type":"Point"}
}