{
  "type": "Feature",
  "properties": {
    "addr:full":"Via Giovanni Xxiii 98066 Patti Patti Messina 98066",
    "addr:postcode":"98066;98066",
    "addr:street":"Via Giovanni Xxiii",
    "iso:country":"IT",
    "sg:address":"Via Giovanni Xxiii 98066 Patti",
    "sg:city":"Patti",
    "sg:classifiers":[
        {
            "category":"Personal",
            "subcategory":"Shoe Repair & Shine",
            "type":"Services"
        }
    ],
    "sg:phone":"+39 0941 362049",
    "sg:postcode":"98066",
    "sg:province":"Messina",
    "sg:tags":[
        "leather"
    ],
    "wof:name":"Killin S.p.a.",
    "wof:placetype":"venue"
},
  "geometry": {"coordinates":[15.555523,38.192333],"type":"Point"}
}