{
  "type": "Feature",
  "properties": {
    "iso:country":"IT",
    "sg:address":"Via Duccio Di; Roma; 00142",
    "sg:city":"Roma",
    "sg:classifiers":[
        {
            "category":"Banks & Credit Unions",
            "subcategory":"Bank",
            "type":"Services"
        }
    ],
    "sg:phone":"+39 06 519 2778",
    "sg:postcode":"00142",
    "sg:province":"Roma",
    "wof:name":"Istituto Bancario San Paolo, Di Torino Spa",
    "wof:placetype":"venue"
},
  "geometry": {"coordinates":[12.490979,41.830177],"type":"Point"}
}