{
  "type": "Feature",
  "properties": {
    "addr:full":"90011 Bagheria Bagheria Palermo 90011",
    "addr:postcode":"90011;90011",
    "iso:country":"IT",
    "sg:address":"90011 Bagheria",
    "sg:city":"Bagheria",
    "sg:orig_category":"Forniture Per Edilizia E Lavori Pubblici",
    "sg:phone":"+39 091 928617",
    "sg:postcode":"90011",
    "sg:province":"Palermo",
    "wof:name":"Caruso Giovanna",
    "wof:placetype":"venue"
},
  "geometry": {"coordinates":[13.5024747849,38.0775985718],"type":"Point"}
}