{
  "type": "Feature",
  "properties": {
    "iso:country":"IT",
    "sg:address":"50, Via L. Da Vinci 52021 Bucine",
    "sg:city":"Bucine",
    "sg:orig_category":"Miscellaneous Products",
    "sg:phone":"+39 39055996659",
    "sg:postcode":"52021",
    "sg:province":"Arezzo",
    "wof:name":"Carbonai",
    "wof:placetype":"venue"
},
  "geometry": {"coordinates":[11.8630619049,43.4712028503],"type":"Point"}
}