{
  "type": "Feature",
  "properties": {
    "addr:full":"Via Fattori 2; Vaiano; 50040",
    "addr:housenumber":"2",
    "addr:postcode":"50040",
    "addr:street":"Via Fattori",
    "iso:country":"IT",
    "sg:address":"Via Fattori 2; Vaiano; 50040",
    "sg:classifiers":[
        {
            "category":"Banks & Credit Unions",
            "subcategory":"Bank",
            "type":"Services"
        }
    ],
    "sg:phone":"+39 0574 984670",
    "wof:name":"Cassa Di Risparmio Di Prato Spa",
    "wof:placetype":"venue"
},
  "geometry": {"coordinates":[11.127619,43.936329],"type":"Point"}
}