{
  "type": "Feature",
  "properties": {
    "addr:full":"00197 Roma Roma Roma 00197",
    "addr:postcode":"00197;00197",
    "iso:country":"IT",
    "sg:address":"00197 Roma",
    "sg:city":"Roma",
    "sg:orig_category":"Ambasciate Ed Enti Internazionali",
    "sg:phone":"+39 06 807 4380",
    "sg:postcode":"00197",
    "sg:province":"Roma",
    "wof:name":"Ambasciata Presso La S. Sede Grecia",
    "wof:placetype":"venue"
},
  "geometry": {"coordinates":[12.487174,41.922699],"type":"Point"}
}