{
  "type": "Feature",
  "properties": {
    "addr:full":"20089 Rozzano Rozzano Milano 20089",
    "addr:postcode":"20089;20089",
    "iso:country":"IT",
    "sg:address":"20089 Rozzano",
    "sg:city":"Rozzano",
    "sg:orig_category":"Professionisti - Studi E Servizi Ed Associazioni Di Interesse Aziendale. Associazioni Ed Organismi Di Interesse Pubblico",
    "sg:phone":"+39 02 825 6230",
    "sg:postcode":"20089",
    "sg:province":"Milano",
    "wof:name":"Movimento Antidroga Rozzano",
    "wof:placetype":"venue"
},
  "geometry": {"coordinates":[9.1583719254,45.3849716187],"type":"Point"}
}