{
  "type": "Feature",
  "properties": {
    "addr:full":"10070 Mappano Torino 10070",
    "addr:postcode":"10070;10070",
    "iso:country":"IT",
    "sg:address":"10070 Mappano",
    "sg:orig_category":"Materiali E Componenti Elettrotecnici",
    "sg:phone":"+39 011 996 8136",
    "sg:postcode":"10070",
    "sg:province":"Torino",
    "wof:name":"Castelli Di Giovanni Castelli & C. (s.a.s.)",
    "wof:placetype":"venue"
},
  "geometry": {"coordinates":[7.705963,45.150688],"type":"Point"}
}