{
  "type": "Feature",
  "properties": {
    "iso:country":"IT",
    "sg:address":"56029 Santa Croce Sull'arno",
    "sg:classifiers":[
        {
            "category":"Manufacturing",
            "subcategory":"Leather Goods",
            "type":"Manufacturing & Wholesale Goods"
        }
    ],
    "sg:phone":"+39 0571 35055",
    "sg:postcode":"56029",
    "sg:province":"Pisa",
    "sg:tags":[
        "footwear",
        "skin"
    ],
    "wof:name":"Astropelli Srl",
    "wof:placetype":"venue"
},
  "geometry": {"coordinates":[10.7605237961,43.7257919312],"type":"Point"}
}