{
  "type": "Feature",
  "properties": {
    "iso:country":"IT",
    "sg:address":"21038 Leggiuno",
    "sg:city":"Leggiuno",
    "sg:orig_category":"Nautica. Servizi Per Lo Sport E Il Tempo Libero. Servizi Al Turismo. Servizi Ausiliari Dei Mezzi Di Trasporto",
    "sg:phone":"+39 0332 647246",
    "sg:postcode":"21038",
    "sg:province":"Varese",
    "wof:name":"Cantiere Costantini Snc",
    "wof:placetype":"venue"
},
  "geometry": {"coordinates":[8.606291,45.870613],"type":"Point"}
}