{
  "type": "Feature",
  "properties": {
    "iso:country":"IT",
    "sg:address":"66020 San Giovanni Teatino",
    "sg:city":"Sambuceto",
    "sg:orig_category":"Strumenti Per Misura, Controllo E Regolazione",
    "sg:phone":"+39 085 446 5730",
    "sg:postcode":"66020",
    "sg:province":"Chieti",
    "wof:name":"Digitherm Srl",
    "wof:placetype":"venue"
},
  "geometry": {"coordinates":[14.202207,42.410213],"type":"Point"}
}