{
  "type": "Feature",
  "properties": {
    "iso:country":"IT",
    "sg:address":"56, Viale Marconi 51016 Montecatini Terme",
    "sg:classifiers":[
        {
            "category":"Wholesale",
            "subcategory":"Drugs",
            "type":"Manufacturing & Wholesale Goods"
        }
    ],
    "sg:phone":"+39 0572 771751",
    "sg:postcode":"51016",
    "sg:province":"Pistoia",
    "sg:tags":[
        "chemical",
        "pharmaceutical"
    ],
    "wof:name":"Global 87 (s.r.l.)",
    "wof:placetype":"venue"
},
  "geometry": {"coordinates":[10.918524,43.932156],"type":"Point"}
}