{
  "type": "Feature",
  "properties": {
    "iso:country":"IT",
    "sg:address":"87041 Acri",
    "sg:city":"Acri",
    "sg:orig_category":"Arredo Cucina Ed Elettrodomestici. Climatizzazione E Condizionamento, Apparecchiature E Servizi",
    "sg:phone":"+39 0984 950492",
    "sg:postcode":"87041",
    "sg:province":"Cosenza",
    "wof:name":"De Marco Gennaro",
    "wof:placetype":"venue"
},
  "geometry": {"coordinates":[16.41703,39.480255],"type":"Point"}
}