{
  "type": "Feature",
  "properties": {
    "addr:full":"27039 Sannazzaro De'burgondi Pavia 27039",
    "addr:postcode":"27039;27039",
    "addr:street":"Sannazzaro De'Burgondi",
    "iso:country":"IT",
    "sg:address":"27039 Sannazzaro De'burgondi",
    "sg:orig_category":"Cine-foto-ottica. Articoli Medico-sanitari Ed Ortopedici. Impianti, Attrezzature E Forniture Sanitarie Ed Ospedaliere",
    "sg:phone":"+39 0382 995371",
    "sg:postcode":"27039",
    "sg:province":"Pavia",
    "wof:name":"Il Punto Di Vista Di Imperiale & Massarone Snc",
    "wof:placetype":"venue"
},
  "geometry": {"coordinates":[8.903737,45.101936],"type":"Point"}
}