{
  "type": "Feature",
  "properties": {
    "addr:full":"12, Via Del Selciatore 40138 Bologna Bologna Bologna 40138",
    "addr:postcode":"40138;40138",
    "addr:street":"Via Del Selciatore",
    "iso:country":"IT",
    "sg:address":"12, Via Del Selciatore 40138 Bologna",
    "sg:city":"Bologna",
    "sg:classifiers":[
        {
            "category":"Autos & Motor Vehicles",
            "subcategory":"Automobile Sales",
            "type":"Retail Goods"
        }
    ],
    "sg:phone":"+39 39051535318",
    "sg:postcode":"40138",
    "sg:province":"Bologna",
    "sg:tags":[
        "motor-cars"
    ],
    "wof:name":"Macap S.r.l.",
    "wof:placetype":"venue"
},
  "geometry": {"coordinates":[11.4173259735,44.5022239685],"type":"Point"}
}