{
  "type": "Feature",
  "properties": {
    "addr:full":"65122 Pescara Pescara Pescara 65122",
    "addr:postcode":"65122;65122",
    "iso:country":"IT",
    "sg:address":"65122 Pescara",
    "sg:city":"Pescara",
    "sg:orig_category":"Agenzie Matrimoniali",
    "sg:phone":"+39 085 421 3967",
    "sg:postcode":"65122",
    "sg:province":"Pescara",
    "wof:name":"Il Girasole Di Liberi Nora",
    "wof:placetype":"venue"
},
  "geometry": {"coordinates":[14.20876,42.467175],"type":"Point"}
}