{
  "type": "Feature",
  "properties": {
    "iso:country":"IT",
    "sg:address":"92019 Sciacca",
    "sg:city":"Sciacca",
    "sg:orig_category":"Arredi Sacri",
    "sg:phone":"+39 0925 21053",
    "sg:postcode":"92019",
    "sg:province":"Agrigento",
    "sg:website":"http://www.paginegialle.veneziaalfonso.it",
    "wof:name":"Venezia Alfonso & Figli Snc",
    "wof:placetype":"venue"
},
  "geometry": {"coordinates":[13.589818,37.322475],"type":"Point"}
}