{
  "type": "Feature",
  "properties": {
    "addr:full":"00040 Roma Roma 00040",
    "addr:postcode":"00040;00040",
    "iso:country":"IT",
    "sg:address":"00040 Roma",
    "sg:orig_category":"Pompe. Elettrotecnica Industriale, Prodotti E Apparecchiature",
    "sg:phone":"+39 06 723 5890",
    "sg:postcode":"00040",
    "sg:province":"Roma",
    "wof:name":"Lowara Spa",
    "wof:placetype":"venue"
},
  "geometry": {"coordinates":[12.6151351929,41.8293228149],"type":"Point"}
}