{
  "type": "Feature",
  "properties": {
    "addr:full":"22060 Cabiate Cabiate Como 22060",
    "addr:postcode":"22060;22060",
    "iso:country":"IT",
    "sg:address":"22060 Cabiate",
    "sg:city":"Cabiate",
    "sg:orig_category":"Prodotti E Manufatti In Materie Plastiche",
    "sg:phone":"+39 031 767509",
    "sg:postcode":"22060",
    "sg:province":"Como",
    "wof:name":"Trasform Espansi",
    "wof:placetype":"venue"
},
  "geometry": {"coordinates":[9.1742696762,45.6734886169],"type":"Point"}
}