{
  "type": "Feature",
  "properties": {
    "iso:country":"IT",
    "sg:address":"16044 Cicagna",
    "sg:city":"Cicagna",
    "sg:orig_category":"Marmo, Pietre Ed Affini",
    "sg:phone":"+39 0185 92167",
    "sg:postcode":"16044",
    "sg:province":"Genova",
    "wof:name":"Nerardesia Snc",
    "wof:placetype":"venue"
},
  "geometry": {"coordinates":[9.251088,44.40604],"type":"Point"}
}