{
  "type": "Feature",
  "properties": {
    "iso:country":"IT",
    "sg:address":"10128 Torino",
    "sg:city":"Torino",
    "sg:classifiers":[
        {
            "category":"Health Services",
            "subcategory":"Health Practitioner",
            "type":"Services"
        }
    ],
    "sg:phone":"+39 011 518 4578",
    "sg:postcode":"10128",
    "sg:province":"Torino",
    "sg:tags":[
        "medici"
    ],
    "wof:name":"Salus Center S.r.l.",
    "wof:placetype":"venue"
},
  "geometry": {"coordinates":[7.6711907387,45.0594215393],"type":"Point"}
}