{
  "type": "Feature",
  "properties": {
    "iso:country":"IT",
    "sg:address":"Via Venezia 22 35010 Vigonza",
    "sg:city":"Vigonza",
    "sg:orig_category":"Ladies' Shoes",
    "sg:phone":"+39 049 828 4211",
    "sg:postcode":"35010",
    "sg:province":"Padova",
    "sg:website":"www.rossimoda.com",
    "wof:name":"Calzaturificio Rossi Moda Spa",
    "wof:placetype":"venue"
},
  "geometry": {"coordinates":[11.901639,45.451126],"type":"Point"}
}