{
  "type": "Feature",
  "properties": {
    "addr:full":"65129 Pescara Pescara Pescara 65129",
    "addr:postcode":"65129;65129",
    "iso:country":"IT",
    "sg:address":"65129 Pescara",
    "sg:city":"Pescara",
    "sg:orig_category":"Centri Di Estetica E Cosmesi E Servizi",
    "sg:phone":"+39 085 454 9020",
    "sg:postcode":"65129",
    "sg:province":"Pescara",
    "sg:website":"http://www.centrorinascita.it",
    "wof:name":"Centro Rinascita",
    "wof:placetype":"venue"
},
  "geometry": {"coordinates":[14.23339,42.450226],"type":"Point"}
}