{
  "type": "Feature",
  "properties": {
    "iso:country":"IT",
    "sg:address":"06055 Marsciano",
    "sg:city":"Marsciano",
    "sg:classifiers":[
        {
            "category":"Professional",
            "type":"Services"
        }
    ],
    "sg:phone":"+39 075 874021",
    "sg:postcode":"06055",
    "sg:province":"Perugia",
    "sg:tags":[
        "activities",
        "supply",
        "commercial",
        "artisan",
        "supplies",
        "accommodation"
    ],
    "sg:website":"http://www.emu.it",
    "wof:name":"Emu Group Spa",
    "wof:placetype":"venue"
},
  "geometry": {"coordinates":[12.323482,42.951721],"type":"Point"}
}