{
  "type": "Feature",
  "properties": {
    "iso:country":"IT",
    "sg:address":"Via Merlina 57 23011 Ardenno",
    "sg:city":"Ardenno",
    "sg:classifiers":[
        {
            "category":"Home & Garden",
            "subcategory":"Building Materials",
            "type":"Retail Goods"
        }
    ],
    "sg:phone":"+39 0342 660354",
    "sg:postcode":"23011",
    "sg:province":"Sondrio",
    "sg:tags":[
        "granite",
        "syenite"
    ],
    "sg:website":"www.pvg.it",
    "wof:name":"Paolo Vigano' Graniti Spa",
    "wof:placetype":"venue"
},
  "geometry": {"coordinates":[9.646256,46.169449],"type":"Point"}
}