{
  "type": "Feature",
  "properties": {
    "iso:country":"IT",
    "sg:address":"Corso Verdi 55, 34170 Gorizia, Go",
    "sg:city":"Gorizia",
    "sg:classifiers":[
        {
            "category":"Banks & Credit Unions",
            "subcategory":"Bank",
            "type":"Services"
        }
    ],
    "sg:postcode":"34170",
    "sg:province":"Gorizia",
    "wof:name":"Banca Agricola-kmecka Banka Spa",
    "wof:placetype":"venue"
},
  "geometry": {"coordinates":[13.622085,45.945286],"type":"Point"}
}