{
  "type": "Feature",
  "properties": {
    "addr:full":"98026 Nizza Di Sicilia Nizza di Sicilia Messina 98026",
    "addr:postcode":"98026;98026",
    "iso:country":"IT",
    "sg:address":"98026 Nizza Di Sicilia",
    "sg:city":"Nizza di Sicilia",
    "sg:orig_category":"Copisterie",
    "sg:phone":"+39 0942 716428",
    "sg:postcode":"98026",
    "sg:province":"Messina",
    "wof:name":"Copy & Copy Di Todaro Bruno",
    "wof:placetype":"venue"
},
  "geometry": {"coordinates":[15.354101,38.019924],"type":"Point"}
}