{
  "type": "Feature",
  "properties": {
    "iso:country":"IT",
    "sg:address":"36051 Creazzo",
    "sg:city":"Creazzo",
    "sg:orig_category":"Articoli Da Regalo. Regalistica Aziendale",
    "sg:phone":"+39 0444 340881",
    "sg:postcode":"36051",
    "sg:province":"Vicenza",
    "wof:name":"L'eden Del Fiore Snc",
    "wof:placetype":"venue"
},
  "geometry": {"coordinates":[11.463141,45.525196],"type":"Point"}
}