{
  "type": "Feature",
  "properties": {
    "iso:country":"IT",
    "sg:address":"4, V Mon. Angelini 27028 S. Martino Siccomario",
    "sg:classifiers":[
        {
            "category":"Wholesale",
            "subcategory":"Medical Equipment & Supplies",
            "type":"Manufacturing & Wholesale Goods"
        }
    ],
    "sg:phone":"+39 0382 498146",
    "sg:postcode":"27028",
    "sg:province":"Pavia",
    "sg:tags":[
        "-",
        "health",
        "instrument"
    ],
    "sg:website":"http://www.gholineadentale.it",
    "wof:name":"Gho Ettore",
    "wof:placetype":"venue"
},
  "geometry": {"coordinates":[9.156563,45.185886],"type":"Point"}
}