{
  "type": "Feature",
  "properties": {
    "iso:country":"IT",
    "sg:address":"44, Strada Bresciana S. Massimo All'adige S.massimo 37139 Verona",
    "sg:city":"Verona",
    "sg:classifiers":[
        {
            "category":"Shopping",
            "subcategory":"Computers & Home Electronics",
            "type":"Retail Goods"
        }
    ],
    "sg:phone":"+39 045 890 3874",
    "sg:postcode":"37139",
    "sg:province":"Verona",
    "sg:tags":[
        "electronic",
        "electrical",
        "equipment"
    ],
    "wof:name":"Sensi - Sogim (s.r.l.)",
    "wof:placetype":"venue"
},
  "geometry": {"coordinates":[10.90323,45.439056],"type":"Point"}
}