{
  "type": "Feature",
  "properties": {
    "iso:country":"IT",
    "sg:address":"33030 Buia",
    "sg:orig_category":"Fustelle E Fustellatrici",
    "sg:phone":"+39 0432 960300",
    "sg:postcode":"33030",
    "sg:province":"Udine",
    "wof:name":"Fra.va. Snc Di Vattolo V. & A.",
    "wof:placetype":"venue"
},
  "geometry": {"coordinates":[13.0885219574,46.2136611938],"type":"Point"}
}