{
  "type": "Feature",
  "properties": {
    "addr:full":"21, Via A Varisco 42020 Albinea Reggio Nell'Emilia 42020",
    "addr:postcode":"42020;42020",
    "addr:street":"Via A Varisco",
    "iso:country":"IT",
    "sg:address":"21, Via A Varisco 42020 Albinea",
    "sg:classifiers":[
        {
            "category":"Manufacturing",
            "subcategory":"Motor Vehicles & Parts",
            "type":"Manufacturing & Wholesale Goods"
        }
    ],
    "sg:phone":"+39 0522 598188",
    "sg:postcode":"42020",
    "sg:province":"Reggio Nell'Emilia",
    "sg:tags":[
        "engine"
    ],
    "wof:name":"Ielli Gianfranco O.m. (s.r.l.)",
    "wof:placetype":"venue"
},
  "geometry": {"coordinates":[10.576953,44.624905],"type":"Point"}
}