{
  "type": "Feature",
  "properties": {
    "addr:full":"02100 Rieti Rieti Rieti 02100",
    "addr:postcode":"02100;02100",
    "iso:country":"IT",
    "sg:address":"02100 Rieti",
    "sg:city":"Rieti",
    "sg:orig_category":"Servizi E Lavori Per Edilizia E Lavori Pubblici. Professionisti - Studi E Servizi Ed Associazioni Di Interesse Aziendale",
    "sg:phone":"+39 0746 228801",
    "sg:postcode":"02100",
    "sg:province":"Rieti",
    "wof:name":"D.g. Service Srl",
    "wof:placetype":"venue"
},
  "geometry": {"coordinates":[12.912106,42.408714],"type":"Point"}
}