{
  "type": "Feature",
  "properties": {
    "iso:country":"IT",
    "sg:address":"Via Genovesi 14 70016 Noicattaro",
    "sg:city":"Noicattaro",
    "sg:classifiers":[
        {
            "category":"Food & Beverages",
            "subcategory":"Fruits & Vegetables",
            "type":"Retail Goods"
        }
    ],
    "sg:phone":"+39 080 479 6032",
    "sg:postcode":"70016",
    "sg:province":"Bari",
    "sg:tags":[
        "grape"
    ],
    "sg:website":"www.ermesnet.it",
    "wof:name":"Ermes Snc Di Giacomo Suglia & Fratelli",
    "wof:placetype":"venue"
},
  "geometry": {"coordinates":[16.993744,41.029068],"type":"Point"}
}