{
  "type": "Feature",
  "properties": {
    "iso:country":"IT",
    "sg:address":"70043 Monopoli",
    "sg:city":"Antonelli",
    "sg:orig_category":"Ricambi E Componenti Dei Mezzi Di Trasporto",
    "sg:phone":"+39 080 690 0494",
    "sg:postcode":"70043",
    "sg:province":"Bari",
    "wof:name":"Goffredo Kart Di Goffredo Francesco",
    "wof:placetype":"venue"
},
  "geometry": {"coordinates":[17.235531,40.894512],"type":"Point"}
}