{
  "type": "Feature",
  "properties": {
    "iso:country":"IT",
    "sg:address":"10, Corso Novara 10078 Venaria",
    "sg:classifiers":[
        {
            "category":"Professional",
            "subcategory":"Engineering",
            "type":"Services"
        }
    ],
    "sg:phone":"+39 011 424 0272",
    "sg:postcode":"10078",
    "sg:province":"Torino",
    "sg:tags":[
        "machine",
        "-",
        "mechanical"
    ],
    "wof:name":"Cos.mec S.r.l.",
    "wof:placetype":"venue"
},
  "geometry": {"coordinates":[7.633577,45.116589],"type":"Point"}
}