{
  "type": "Feature",
  "properties": {
    "iso:country":"IT",
    "sg:address":"Via Recanatese 37 60022 Castelfidardo",
    "sg:city":"Castelfidardo",
    "sg:classifiers":[
        {
            "category":"Manufacturing",
            "subcategory":"Wood Products",
            "type":"Manufacturing & Wholesale Goods"
        }
    ],
    "sg:phone":"+39 071 727171",
    "sg:postcode":"60022",
    "sg:province":"Ancona",
    "sg:tags":[
        "solid",
        "door"
    ],
    "sg:website":"www.garofoli.com",
    "wof:name":"Garofoli Spa",
    "wof:placetype":"venue"
},
  "geometry": {"coordinates":[13.53425,43.449379],"type":"Point"}
}