{
  "type": "Feature",
  "properties": {
    "addr:full":"10098 Rivoli Cascine vica Torino 10098",
    "addr:postcode":"10098;10098",
    "iso:country":"IT",
    "sg:address":"10098 Rivoli",
    "sg:city":"Cascine vica",
    "sg:orig_category":"Riparazione Dei Mezzi Di Trasporto",
    "sg:phone":"+39 011 959 3048",
    "sg:postcode":"10098",
    "sg:province":"Torino",
    "wof:name":"Carrozzeria Pavia Snc",
    "wof:placetype":"venue"
},
  "geometry": {"coordinates":[7.553098,45.062813],"type":"Point"}
}