{
  "type": "Feature",
  "properties": {
    "iso:country":"IT",
    "sg:address":"Via Aldo Moro 10/c 45026 Lendinara",
    "sg:city":"Lendinara",
    "sg:classifiers":[
        {
            "category":"Bus Stop",
            "subcategory":"None",
            "type":"Transportation"
        }
    ],
    "sg:phone":"+39 0425 601401",
    "sg:postcode":"45026",
    "sg:province":"Rovigo",
    "sg:tags":[
        "pipe",
        "aluminium"
    ],
    "sg:website":"www.inoxtech.com",
    "wof:name":"Inox Tech S.p.a.",
    "wof:placetype":"venue"
},
  "geometry": {"coordinates":[11.647169,45.028572],"type":"Point"}
}