{
  "type": "Feature",
  "properties": {
    "addr:full":"30, Via Galeazza 40132 Bologna Bologna Bologna 40132",
    "addr:postcode":"40132;40132",
    "addr:street":"Via Galeazza",
    "iso:country":"IT",
    "sg:address":"30, Via Galeazza 40132 Bologna",
    "sg:city":"Bologna",
    "sg:classifiers":[
        {
            "category":"Manufacturing",
            "subcategory":"Rubber & Plastics",
            "type":"Manufacturing & Wholesale Goods"
        }
    ],
    "sg:phone":"+39 39051561559",
    "sg:postcode":"40132",
    "sg:province":"Bologna",
    "wof:name":"Vignoli (s.r.l.)",
    "wof:placetype":"venue"
},
  "geometry": {"coordinates":[11.2756280899,44.5037498474],"type":"Point"}
}