{
  "type": "Feature",
  "properties": {
    "addr:full":"Piazza Degli Eroi, 31; Mola; 70042 Bari 70042",
    "addr:housenumber":"31",
    "addr:postcode":"70042;70042",
    "addr:street":"Piazza Degli Eroi;Mola",
    "iso:country":"IT",
    "sg:address":"Piazza Degli Eroi, 31; Mola; 70042",
    "sg:classifiers":[
        {
            "category":"Banks & Credit Unions",
            "subcategory":"Bank",
            "type":"Services"
        }
    ],
    "sg:phone":"+39 080 641085",
    "sg:postcode":"70042",
    "sg:province":"Bari",
    "wof:name":"Cassa Di Risparmio Di Puglia",
    "wof:placetype":"venue"
},
  "geometry": {"coordinates":[17.088133,41.059391],"type":"Point"}
}