{
  "type": "Feature",
  "properties": {
    "iso:country":"IT",
    "sg:address":"20098 San Giuliano Milanese",
    "sg:city":"San Giuliano Milanese",
    "sg:orig_category":"Prodotti Alimentari",
    "sg:phone":"+39 02 9828 2174",
    "sg:postcode":"20098",
    "sg:province":"Milano",
    "wof:name":"Il Fior Fiore Srl",
    "wof:placetype":"venue"
},
  "geometry": {"coordinates":[9.2579059601,45.4008674622],"type":"Point"}
}