{
  "type": "Feature",
  "properties": {
    "addr:full":"13, Via Mulini 26013 Crema Crema Cremona 26013",
    "addr:postcode":"26013;26013",
    "addr:street":"Via Mulini",
    "iso:country":"IT",
    "sg:address":"13, Via Mulini 26013 Crema",
    "sg:city":"Crema",
    "sg:classifiers":[
        {
            "category":"Shopping",
            "subcategory":"Crafts & Fabrics",
            "type":"Retail Goods"
        }
    ],
    "sg:phone":"+39 0373 250628",
    "sg:postcode":"26013",
    "sg:province":"Cremona",
    "wof:name":"Stireria Essegielle Moda (s.r.l.)",
    "wof:placetype":"venue"
},
  "geometry": {"coordinates":[9.6952171326,45.3736457825],"type":"Point"}
}