{
  "type": "Feature",
  "properties": {
    "iso:country":"IT",
    "sg:address":"38100 Trento",
    "sg:city":"Trento",
    "sg:orig_category":"Studi E Consulenze Legali E Notarili. Avvocati, Notai E Servizi Legali. Professionisti - Studi E Servizi Ed Associazioni Di Interesse Aziendale",
    "sg:phone":"+39 0461 985250",
    "sg:postcode":"38100",
    "sg:province":"Trento",
    "wof:name":"Defant Dott. Carlo - Notaio",
    "wof:placetype":"venue"
},
  "geometry": {"coordinates":[11.125156,46.071991],"type":"Point"}
}