{
  "type": "Feature",
  "properties": {
    "addr:full":"50145 Firenze Firenze Firenze 50145",
    "addr:postcode":"50145;50145",
    "iso:country":"IT",
    "sg:address":"50145 Firenze",
    "sg:city":"Firenze",
    "sg:orig_category":"Servizi Al Turismo. Trasporto Pubblico E Privato",
    "sg:phone":"+39 055 301399",
    "sg:postcode":"50145",
    "sg:province":"Firenze",
    "wof:name":"Bs Fast Cargo S.p.a",
    "wof:placetype":"venue"
},
  "geometry": {"coordinates":[11.187696,43.802879],"type":"Point"}
}