{
  "type": "Feature",
  "properties": {
    "addr:full":"50144 Firenze Firenze Firenze 50144",
    "addr:postcode":"50144;50144",
    "iso:country":"IT",
    "sg:address":"50144 Firenze",
    "sg:city":"Firenze",
    "sg:orig_category":"Batterie, Accumulatori E Pile - Commercio",
    "sg:phone":"+39 055 357948",
    "sg:postcode":"50144",
    "sg:province":"Firenze",
    "wof:name":"Elettromec Sas Di Casini Carla & C.",
    "wof:placetype":"venue"
},
  "geometry": {"coordinates":[11.242866,43.779648],"type":"Point"}
}