{
  "type": "Feature",
  "properties": {
    "addr:full":"52011 Bibbiena Bibbiena Arezzo 52011",
    "addr:postcode":"52011;52011",
    "iso:country":"IT",
    "sg:address":"52011 Bibbiena",
    "sg:city":"Bibbiena",
    "sg:orig_category":"Carpenterie Metalliche",
    "sg:phone":"+39 0575 560027",
    "sg:postcode":"52011",
    "sg:province":"Arezzo",
    "wof:name":"Corezzi Pasquale & C. Snc",
    "wof:placetype":"venue"
},
  "geometry": {"coordinates":[11.812283,43.732601],"type":"Point"}
}