{
  "type": "Feature",
  "properties": {
    "iso:country":"IT",
    "sg:address":"25050 Rodengo Saiano",
    "sg:orig_category":"Macchine, Impianti Ed Attrezzature Industria Delle Materie Plastiche E Gomma",
    "sg:phone":"+39 030 611561",
    "sg:postcode":"25050",
    "sg:province":"Brescia",
    "wof:name":"Industrial Service (s.r.l.)",
    "wof:placetype":"venue"
},
  "geometry": {"coordinates":[10.124055,45.577286],"type":"Point"}
}