{
  "type": "Feature",
  "properties": {
    "iso:country":"IT",
    "sg:address":"71100 Foggia",
    "sg:city":"Foggia",
    "sg:orig_category":"Climatizzazione E Condizionamento, Apparecchiature E Servizi",
    "sg:phone":"+39 0881 727354",
    "sg:postcode":"71100",
    "sg:province":"Foggia",
    "wof:name":"Edil Termogas Srl",
    "wof:placetype":"venue"
},
  "geometry": {"coordinates":[15.5339,41.464977],"type":"Point"}
}