{
  "type": "Feature",
  "properties": {
    "addr:full":"20010 Cornaredo Cornaredo Milano 20010",
    "addr:postcode":"20010;20010",
    "iso:country":"IT",
    "sg:address":"20010 Cornaredo",
    "sg:city":"Cornaredo",
    "sg:orig_category":"Frigotecnica, Apparecchiature E Servizi. Servizi Di Magazzinaggio E Movimentazione",
    "sg:phone":"+39 02 931901",
    "sg:postcode":"20010",
    "sg:province":"Milano",
    "wof:name":"Frigoscandia S.p.a.",
    "wof:placetype":"venue"
},
  "geometry": {"coordinates":[9.0320463181,45.4798774719],"type":"Point"}
}