{
  "type": "Feature",
  "properties": {
    "addr:full":"47838 Riccione Riccione Rimini 47838",
    "addr:postcode":"47838;47838",
    "iso:country":"IT",
    "sg:address":"47838 Riccione",
    "sg:city":"Riccione",
    "sg:classifiers":[
        {
            "category":"Travel",
            "subcategory":"Hotels & Motels",
            "type":"Entertainment"
        }
    ],
    "sg:phone":"+39 0541 648260",
    "sg:postcode":"47838",
    "sg:province":"Rimini",
    "sg:tags":[
        "hotels",
        "facility"
    ],
    "wof:name":"Hotel San Leo Sole E Mare Srl",
    "wof:placetype":"venue"
},
  "geometry": {"coordinates":[12.651556,44.007145],"type":"Point"}
}