{
  "type": "Feature",
  "properties": {
    "iso:country":"IT",
    "sg:address":"65013 Citta'santangelo",
    "sg:classifiers":[
        {
            "category":"Manufacturing",
            "subcategory":"Food",
            "type":"Manufacturing & Wholesale Goods"
        }
    ],
    "sg:phone":"+39 085 950266",
    "sg:postcode":"65013",
    "sg:province":"Pescara",
    "sg:tags":[
        "product"
    ],
    "wof:name":"Tecnomet Italia Spa",
    "wof:placetype":"venue"
},
  "geometry": {"coordinates":[14.129368782,42.5211906433],"type":"Point"}
}