{
  "type": "Feature",
  "properties": {
    "iso:country":"IT",
    "sg:address":"12, Via Castiglioni E. 21100 Varese",
    "sg:city":"Varese",
    "sg:classifiers":[
        {
            "category":"Professional",
            "subcategory":"Advertising",
            "type":"Services"
        }
    ],
    "sg:phone":"+39 0332 240315",
    "sg:postcode":"21100",
    "sg:province":"Varese",
    "sg:tags":[
        "communication",
        "medium"
    ],
    "wof:name":"Delpi S.r.l.",
    "wof:placetype":"venue"
},
  "geometry": {"coordinates":[8.832713,45.849468],"type":"Point"}
}