{
  "type": "Feature",
  "properties": {
    "iso:country":"IT",
    "sg:address":"10078 Venaria",
    "sg:orig_category":"Bronzine",
    "sg:phone":"+39 011 424 1730",
    "sg:postcode":"10078",
    "sg:province":"Torino",
    "wof:name":"General Sinter Snc",
    "wof:placetype":"venue"
},
  "geometry": {"coordinates":[7.631071,45.115448],"type":"Point"}
}