{
  "type": "Feature",
  "properties": {
    "iso:country":"IT",
    "sg:address":"10098 Rivoli",
    "sg:city":"Rivoli",
    "sg:orig_category":"Articoli Per Neonati E Bambini",
    "sg:phone":"+39 011 953 4876",
    "sg:postcode":"10098",
    "sg:province":"Torino",
    "wof:name":"Centro Gioco Educativo Di Valgiusti",
    "wof:placetype":"venue"
},
  "geometry": {"coordinates":[7.519221,45.069363],"type":"Point"}
}