{
  "type": "Feature",
  "properties": {
    "iso:country":"IT",
    "sg:address":"09094 Marrubiu",
    "sg:city":"Marrubiu",
    "sg:orig_category":"Servizi Di Magazzinaggio E Movimentazione",
    "sg:phone":"+39 0783 859789",
    "sg:postcode":"09094",
    "sg:province":"Oristano",
    "wof:name":"Melis Mario",
    "wof:placetype":"venue"
},
  "geometry": {"coordinates":[8.635748,39.75235],"type":"Point"}
}