{
  "type": "Feature",
  "properties": {
    "iso:country":"IT",
    "sg:address":"4, Via Cavallo Giuseppe 10078 Venaria",
    "sg:classifiers":[
        {
            "category":"Manufacturing",
            "subcategory":"Printing",
            "type":"Manufacturing & Wholesale Goods"
        }
    ],
    "sg:phone":"+39 011 459 4040",
    "sg:postcode":"10078",
    "sg:province":"Torino",
    "sg:tags":[
        "publishing"
    ],
    "wof:name":"Editrice La Gazzetta Informazione E Comunicazione",
    "wof:placetype":"venue"
},
  "geometry": {"coordinates":[7.6328845024,45.1332473755],"type":"Point"}
}