{
  "type": "Feature",
  "properties": {
    "iso:country":"IT",
    "sg:address":"19121 La Spezia",
    "sg:orig_category":"Argenterie - Vendita Al Dettaglio",
    "sg:phone":"+39 0187 22134",
    "sg:province":"SP",
    "wof:name":"I Cigni Di Volorio Sandra",
    "wof:placetype":"venue"
},
  "geometry": {"coordinates":[9.820231,44.103497],"type":"Point"}
}