{
  "type": "Feature",
  "properties": {
    "addr:full":"20127 Milano Milano Milano 20127",
    "addr:postcode":"20127;20127",
    "iso:country":"IT",
    "sg:address":"20127 Milano",
    "sg:city":"Milano",
    "sg:orig_category":"Cine-foto-ottica. Articoli Medico-sanitari Ed Ortopedici",
    "sg:phone":"+39 02 2611 3163",
    "sg:postcode":"20127",
    "sg:province":"Milano",
    "wof:name":"Rovani Optik S.n.c. Di Roberto Maggioni & C.",
    "wof:placetype":"venue"
},
  "geometry": {"coordinates":[9.219787,45.503342],"type":"Point"}
}