{
  "type": "Feature",
  "properties": {
    "addr:full":"24043 Caravaggio Caravaggio Bergamo 24043",
    "addr:postcode":"24043;24043",
    "iso:country":"IT",
    "sg:address":"24043 Caravaggio",
    "sg:city":"Caravaggio",
    "sg:orig_category":"Forniture Per Edilizia E Lavori Pubblici",
    "sg:phone":"+39 036 350049",
    "sg:postcode":"24043",
    "sg:province":"Bergamo",
    "sg:website":"http://www.mombrini.it",
    "wof:name":"Mombrini Srl",
    "wof:placetype":"venue"
},
  "geometry": {"coordinates":[9.6537857056,45.5050239563],"type":"Point"}
}