{
  "type": "Feature",
  "properties": {
    "addr:full":"33070 Maron Maron Pordenone 33070",
    "addr:postcode":"33070;33070",
    "iso:country":"IT",
    "sg:address":"33070 Maron",
    "sg:city":"Maron",
    "sg:orig_category":"Servizi E Lavori Per Arredamento E Industria Del Legno",
    "sg:phone":"+39 0434 624783",
    "sg:postcode":"33070",
    "sg:province":"Pordenone",
    "wof:name":"Giuntati 2000 S.r.l.",
    "wof:placetype":"venue"
},
  "geometry": {"coordinates":[12.554892,45.908497],"type":"Point"}
}