{
  "type": "Feature",
  "properties": {
    "iso:country":"IT",
    "sg:address":"7, Via Baviera 35127 Padova",
    "sg:city":"Padova",
    "sg:classifiers":[
        {
            "category":"Manufacturing",
            "subcategory":"Lumber",
            "type":"Manufacturing & Wholesale Goods"
        }
    ],
    "sg:phone":"+39 049 870 0711",
    "sg:postcode":"35127",
    "sg:province":"Padova",
    "sg:tags":[
        "wood"
    ],
    "wof:name":"Italignum S.r.l.",
    "wof:placetype":"venue"
},
  "geometry": {"coordinates":[11.844167,45.397499],"type":"Point"}
}