{
  "type": "Feature",
  "properties": {
    "addr:full":"55, Strada Stazione 14025 Montechiaro D'asti Asti 14025",
    "addr:postcode":"14025;14025",
    "addr:street":"Strada Stazione",
    "iso:country":"IT",
    "sg:address":"55, Strada Stazione 14025 Montechiaro D'asti",
    "sg:classifiers":[
        {
            "category":"Utilities",
            "subcategory":"Electric",
            "type":"Services"
        }
    ],
    "sg:phone":"+39 0141 999216",
    "sg:postcode":"14025",
    "sg:province":"Asti",
    "sg:tags":[
        "component",
        "electronic"
    ],
    "wof:name":"S.a.t. Societa' Assemblaggi Tecnici (s.n.c.)",
    "wof:placetype":"venue"
},
  "geometry": {"coordinates":[8.1098,44.999641],"type":"Point"}
}