{
  "type": "Feature",
  "properties": {
    "iso:country":"IT",
    "sg:address":"Corso Cavour 6; Novara; 28100",
    "sg:city":"Novara",
    "sg:classifiers":[
        {
            "category":"Banks & Credit Unions",
            "subcategory":"Bank",
            "type":"Services"
        }
    ],
    "sg:phone":"+39 0321 3841",
    "sg:postcode":"28100",
    "sg:province":"Novara",
    "wof:name":"Credito Italiano Spa",
    "wof:placetype":"venue"
},
  "geometry": {"coordinates":[8.622139,45.447735],"type":"Point"}
}