{
  "type": "Feature",
  "properties": {
    "addr:full":"23807 Merate Merate Lecco 23807",
    "addr:postcode":"23807;23807",
    "iso:country":"IT",
    "sg:address":"23807 Merate",
    "sg:city":"Merate",
    "sg:orig_category":"Macchine Ed Impianti Per Edilizia E Lavori Pubblici",
    "sg:phone":"+39 039 990 6118",
    "sg:postcode":"23807",
    "sg:province":"Lecco",
    "wof:name":"I.m.e. Di Zuccarini Massimo & C. (s.a.s.)",
    "wof:placetype":"venue"
},
  "geometry": {"coordinates":[9.4317,45.69767],"type":"Point"}
}