{
  "type": "Feature",
  "properties": {
    "addr:full":"Via Chiarugi 4; Empoli; 50053 Empoli Firenze 50053",
    "addr:housenumber":"4",
    "addr:postcode":"50053;50053",
    "addr:street":"Via Chiarugi",
    "iso:country":"IT",
    "sg:address":"Via Chiarugi 4; Empoli; 50053",
    "sg:city":"Empoli",
    "sg:classifiers":[
        {
            "category":"Banks & Credit Unions",
            "subcategory":"Bank",
            "type":"Services"
        }
    ],
    "sg:phone":"+39 0571 78772",
    "sg:postcode":"50053",
    "sg:province":"Firenze",
    "wof:name":"Banca Di Credito, Cooperativo Di Cambiano",
    "wof:placetype":"venue"
},
  "geometry": {"coordinates":[10.942325,43.719891],"type":"Point"}
}