{
  "type": "Feature",
  "properties": {
    "iso:country":"IT",
    "sg:address":"20, Corso Italia 20020 Vanzaghello",
    "sg:city":"Vanzaghello",
    "sg:classifiers":[
        {
            "category":"Autos & Motor Vehicles",
            "subcategory":"Automobile Sales",
            "type":"Retail Goods"
        }
    ],
    "sg:phone":"+39 0331 657600",
    "sg:postcode":"20020",
    "sg:province":"Milano",
    "sg:tags":[
        "equipment",
        "transport"
    ],
    "wof:name":"Speedcross (s.n.c.)",
    "wof:placetype":"venue"
},
  "geometry": {"coordinates":[8.79426,45.597637],"type":"Point"}
}