{
  "type": "Feature",
  "properties": {
    "iso:country":"IT",
    "sg:address":"33, Via Moro Aldo 41043 Formigine",
    "sg:city":"Formigine",
    "sg:classifiers":[
        {
            "category":"Professional",
            "subcategory":"Engineering",
            "type":"Services"
        }
    ],
    "sg:phone":"+39 39059558174",
    "sg:postcode":"41043",
    "sg:province":"Modena",
    "sg:tags":[
        "machine",
        "-",
        "mechanical"
    ],
    "wof:name":"Imac Italia (s.r.l.)",
    "wof:placetype":"venue"
},
  "geometry": {"coordinates":[10.923737,44.545532],"type":"Point"}
}