{
  "type": "Feature",
  "properties": {
    "iso:country":"IT",
    "sg:address":"28859 Trontano",
    "sg:city":"Trontano",
    "sg:orig_category":"Motori Ed Organi Di Trasmissione. Ricambi E Componenti Dei Mezzi Di Trasporto",
    "sg:phone":"+39 0324 47627",
    "sg:postcode":"28859",
    "sg:province":"Verbano-Cusio-Ossola",
    "wof:name":"Delsindaco Massimo",
    "wof:placetype":"venue"
},
  "geometry": {"coordinates":[8.3080768585,46.1046867371],"type":"Point"}
}