{
  "type": "Feature",
  "properties": {
    "iso:country":"IT",
    "sg:address":"34121 Trieste",
    "sg:city":"Trieste",
    "sg:orig_category":"Sport - Articoli E Forniture",
    "sg:phone":"+39 040 638324",
    "sg:postcode":"34121",
    "sg:province":"Trieste",
    "wof:name":"L'esca Di Del Bianco",
    "wof:placetype":"venue"
},
  "geometry": {"coordinates":[13.773808,45.651081],"type":"Point"}
}