{
  "type": "Feature",
  "properties": {
    "iso:country":"IT",
    "sg:address":"41, Via Alessandro Manzoni 24031 Almenno San Salvatore",
    "sg:city":"Almenno San Salvatore",
    "sg:classifiers":[
        {
            "category":"Manufacturing",
            "subcategory":"Metals",
            "type":"Manufacturing & Wholesale Goods"
        }
    ],
    "sg:phone":"+39 39035643131",
    "sg:postcode":"24031",
    "sg:province":"Bergamo",
    "sg:tags":[
        "processing"
    ],
    "wof:name":"Algra (s.p.a.)",
    "wof:placetype":"venue"
},
  "geometry": {"coordinates":[9.5750007629,45.7201080322],"type":"Point"}
}