{
  "type": "Feature",
  "properties": {
    "addr:full":"1, Via Str.vic. Forchetta 70033 Corato Corato Bari 70033",
    "addr:postcode":"70033;70033",
    "addr:street":"Via Str.Vic. Forchetta",
    "iso:country":"IT",
    "sg:address":"1, Via Str.vic. Forchetta 70033 Corato",
    "sg:city":"Corato",
    "sg:classifiers":[
        {
            "category":"Wholesale",
            "subcategory":"Drugs",
            "type":"Manufacturing & Wholesale Goods"
        }
    ],
    "sg:phone":"+39 080 898 5883",
    "sg:postcode":"70033",
    "sg:province":"Bari",
    "sg:tags":[
        "chemical",
        "pharmaceutical"
    ],
    "wof:name":"Ge.ne.s.i. S.p.a. Servizio Sorvaglianza",
    "wof:placetype":"venue"
},
  "geometry": {"coordinates":[16.869291,41.126053],"type":"Point"}
}