{
  "type": "Feature",
  "properties": {
    "iso:country":"IT",
    "sg:address":"34170 Gorizia",
    "sg:city":"Gorizia",
    "sg:orig_category":"Accessori Moda D'abbigliamento. Forniture Per Abbigliamento E Pelletterie",
    "sg:phone":"+39 0481 534601",
    "sg:postcode":"34170",
    "sg:province":"Gorizia",
    "wof:name":"Ricamificio Spillo",
    "wof:placetype":"venue"
},
  "geometry": {"coordinates":[13.623115,45.944469],"type":"Point"}
}