{
  "type": "Feature",
  "properties": {
    "iso:country":"IT",
    "sg:address":"10082 Cuorgne'",
    "sg:classifiers":[
        {
            "category":"Health Services",
            "subcategory":"Health Practitioner",
            "type":"Services"
        }
    ],
    "sg:phone":"+39 0124 620242",
    "sg:postcode":"10082",
    "sg:province":"Torino",
    "sg:tags":[
        "medici"
    ],
    "wof:name":"Gianotti Laura",
    "wof:placetype":"venue"
},
  "geometry": {"coordinates":[7.635225,45.397617],"type":"Point"}
}