{
  "type": "Feature",
  "properties": {
    "iso:country":"IT",
    "sg:address":"16121 Genova",
    "sg:city":"Genova",
    "sg:orig_category":"Articoli Da Regalo. Tempo Libero - Articoli E Forniture. Regalistica Aziendale",
    "sg:phone":"+39 010 580631",
    "sg:postcode":"16121",
    "sg:province":"Genova",
    "wof:name":"Arte Della Medaglia Di Marco E Gabriella Benzo & C. Snc",
    "wof:placetype":"venue"
},
  "geometry": {"coordinates":[8.939713,44.405628],"type":"Point"}
}