{
  "type": "Feature",
  "properties": {
    "addr:full":"15100 Alessandria Alessandria Alessandria 15100",
    "addr:postcode":"15100;15100",
    "iso:country":"IT",
    "sg:address":"15100 Alessandria",
    "sg:city":"Alessandria",
    "sg:orig_category":"Automobili E Mezzi Di Trasporto",
    "sg:phone":"+39 0131 342312",
    "sg:postcode":"15100",
    "sg:province":"Alessandria",
    "wof:name":"Ar.fer. (s.r.l.)",
    "wof:placetype":"venue"
},
  "geometry": {"coordinates":[8.605398,44.903984],"type":"Point"}
}