{
  "type": "Feature",
  "properties": {
    "iso:country":"IT",
    "sg:address":"40138 Bologna",
    "sg:city":"Bologna",
    "sg:orig_category":"Servizi E Lavori Per Agricoltura E Zootecnia",
    "sg:phone":"+39 051 530118",
    "sg:postcode":"40138",
    "sg:province":"Bologna",
    "wof:name":"Cesari Alfredo",
    "wof:placetype":"venue"
},
  "geometry": {"coordinates":[11.398565,44.499325],"type":"Point"}
}