{
  "type": "Feature",
  "properties": {
    "addr:full":"10153 Torino Torino Torino 10153",
    "addr:postcode":"10153;10153",
    "iso:country":"IT",
    "sg:address":"10153 Torino",
    "sg:city":"Torino",
    "sg:orig_category":"Elettrotecnica Industriale, Prodotti E Apparecchiature. Elettronica Industriale, Prodotti E Apparecchiature. Macchine, Strumenti Ed Apparecchi Per Attivita' Industriali",
    "sg:phone":"+39 011 280289",
    "sg:postcode":"10153",
    "sg:province":"Torino",
    "wof:name":"Risatti Instruments Srl",
    "wof:placetype":"venue"
},
  "geometry": {"coordinates":[7.715995,45.076519],"type":"Point"}
}