{
  "type": "Feature",
  "properties": {
    "iso:country":"IT",
    "sg:address":"Pza Del Popolo 15, 12038 Savigliano",
    "sg:city":"Savigliano",
    "sg:classifiers":[
        {
            "category":"Banks & Credit Unions",
            "subcategory":"Financial Services",
            "type":"Services"
        }
    ],
    "sg:phone":"+39 390 172 2031",
    "sg:postcode":"12038",
    "sg:province":"Cuneo",
    "sg:tags":[
        "banking",
        "finance",
        "insurance"
    ],
    "wof:name":"Banca Cassa Di Risparmio Di Savigliano Spa",
    "wof:placetype":"venue"
},
  "geometry": {"coordinates":[7.5471105576,44.38879776],"type":"Point"}
}