{
  "type": "Feature",
  "properties": {
    "iso:country":"IT",
    "sg:address":"50143 Firenze",
    "sg:city":"Firenze",
    "sg:orig_category":"Vetro: Prodotti E Lavorazioni",
    "sg:phone":"+39 055 711004",
    "sg:postcode":"50143",
    "sg:province":"Firenze",
    "wof:name":"Tecnosolar Film Srl",
    "wof:placetype":"venue"
},
  "geometry": {"coordinates":[11.217282,43.764549],"type":"Point"}
}