{
  "type": "Feature",
  "properties": {
    "iso:country":"IT",
    "sg:address":"20021 Bollate",
    "sg:city":"Bollate",
    "sg:orig_category":"Cartotecnica E Servizi. Composizione, Stampa E Confezione. Forniture E Prodotti Informatici. Forniture Per Congressi, Fiere E Manifestazioni",
    "sg:phone":"+39 02 3820 2031",
    "sg:postcode":"20021",
    "sg:province":"Milano",
    "wof:name":"Satec Srl",
    "wof:placetype":"venue"
},
  "geometry": {"coordinates":[9.115243,45.53413],"type":"Point"}
}