{
  "type": "Feature",
  "properties": {
    "addr:full":"20, Via Pitagora 35030 Rubano Rubano Padova 35030",
    "addr:postcode":"35030;35030",
    "addr:street":"Via Pitagora",
    "iso:country":"IT",
    "sg:address":"20, Via Pitagora 35030 Rubano",
    "sg:city":"Rubano",
    "sg:classifiers":[
        {
            "category":"Shopping",
            "subcategory":"Jewelry",
            "type":"Retail Goods"
        }
    ],
    "sg:phone":"+39 39049633344",
    "sg:postcode":"35030",
    "sg:province":"Padova",
    "sg:tags":[
        "jewellery"
    ],
    "wof:name":"Argenterie Ferrara Di Ferrara Vincenzo & C. (s.n.c.)",
    "wof:placetype":"venue"
},
  "geometry": {"coordinates":[11.836113,45.418659],"type":"Point"}
}