{
  "type": "Feature",
  "properties": {
    "iso:country":"IT",
    "sg:address":"18/a, Via Salvaterra 42048 Rubiera",
    "sg:classifiers":[
        {
            "category":"Shopping",
            "subcategory":"Crafts & Fabrics",
            "type":"Retail Goods"
        }
    ],
    "sg:phone":"+39 0522 628841",
    "sg:postcode":"42048",
    "sg:province":"Reggio Nell'Emilia",
    "sg:tags":[
        "ceramic"
    ],
    "wof:name":"Antica Ceramica Rubiera (s.r.l.)",
    "wof:placetype":"venue"
},
  "geometry": {"coordinates":[10.778672,44.637112],"type":"Point"}
}