{
  "type": "Feature",
  "properties": {
    "addr:full":"28921 Verbania Verbania Verbano-Cusio-Ossola 28921",
    "addr:postcode":"28921;28921",
    "iso:country":"IT",
    "sg:address":"28921 Verbania",
    "sg:city":"Verbania",
    "sg:orig_category":"Ricambi E Componenti Dei Mezzi Di Trasporto",
    "sg:phone":"+39 0323 516695",
    "sg:postcode":"28921",
    "sg:province":"Verbano-Cusio-Ossola",
    "wof:name":"B.s.m. Sas",
    "wof:placetype":"venue"
},
  "geometry": {"coordinates":[8.573103,45.939686],"type":"Point"}
}