{
  "type": "Feature",
  "properties": {
    "addr:full":"90145 Palermo Palermo Palermo 90145",
    "addr:postcode":"90145;90145",
    "iso:country":"IT",
    "sg:address":"90145 Palermo",
    "sg:city":"Palermo",
    "sg:orig_category":"Bagno - Accessori E Mobili",
    "sg:phone":"+39 091 220291",
    "sg:postcode":"90145",
    "sg:province":"Palermo",
    "wof:name":"Reina Antonino",
    "wof:placetype":"venue"
},
  "geometry": {"coordinates":[13.315365,38.135616],"type":"Point"}
}