{
  "type": "Feature",
  "properties": {
    "iso:country":"IT",
    "sg:address":"25087 Salo'",
    "sg:orig_category":"Macchine Utensili E Impianti",
    "sg:phone":"+39 036 552 0780",
    "sg:postcode":"25087",
    "sg:province":"Brescia",
    "wof:name":"B R G (s.r.l.)",
    "wof:placetype":"venue"
},
  "geometry": {"coordinates":[10.47663,45.45385],"type":"Point"}
}