{
  "type": "Feature",
  "properties": {
    "addr:full":"104, V. Lago Di Garda 36015 Schio Schio Vicenza 36015",
    "addr:housenumber":"104",
    "addr:postcode":"36015;36015",
    "addr:street":"V. Lago Di Garda",
    "iso:country":"IT",
    "sg:address":"104, V. Lago Di Garda 36015 Schio",
    "sg:city":"Schio",
    "sg:classifiers":[
        {
            "category":"Shopping",
            "type":"Retail Goods"
        }
    ],
    "sg:phone":"+39 0445 578100",
    "sg:postcode":"36015",
    "sg:province":"Vicenza",
    "sg:tags":[
        "finished",
        "-",
        "metallic"
    ],
    "sg:website":"http://www.artifer.com:ws_end: :mark:ws:http://www.paginegialle.it/artifer",
    "wof:name":"Artifer Srl",
    "wof:placetype":"venue"
},
  "geometry": {"coordinates":[11.3989982605,45.7194633484],"type":"Point"}
}