{
  "type": "Feature",
  "properties": {
    "addr:full":"20068 Peschiera Borromeo Peschiera Borromeo Milano 20068",
    "addr:postcode":"20068;20068",
    "iso:country":"IT",
    "sg:address":"20068 Peschiera Borromeo",
    "sg:city":"Peschiera Borromeo",
    "sg:orig_category":"Musica",
    "sg:phone":"+39 02 5530 8149",
    "sg:postcode":"20068",
    "sg:province":"Milano",
    "wof:name":"Dsi Italia S.p.a.",
    "wof:placetype":"venue"
},
  "geometry": {"coordinates":[9.3234939575,45.4330291748],"type":"Point"}
}