{
  "type": "Feature",
  "properties": {
    "iso:country":"IT",
    "sg:address":"19123 La Spezia",
    "sg:orig_category":"Arredamento Bar E Ristoranti",
    "sg:phone":"+39 0187 770617",
    "sg:province":"SP",
    "wof:name":"A.l.b.a. Grandi Impianti Srl",
    "wof:placetype":"venue"
},
  "geometry": {"coordinates":[9.812456,44.097828],"type":"Point"}
}