{
  "type": "Feature",
  "properties": {
    "addr:full":"Via Provinciale Pesaro 69 47836 Mondaino Mondaino Rimini 47836",
    "addr:housenumber":"69",
    "addr:postcode":"47836;47836",
    "addr:street":"Via Provinciale Pesaro",
    "iso:country":"IT",
    "sg:address":"Via Provinciale Pesaro 69 47836 Mondaino",
    "sg:city":"Mondaino",
    "sg:classifiers":[
        {
            "category":"Manufacturing",
            "subcategory":"Furniture",
            "type":"Manufacturing & Wholesale Goods"
        }
    ],
    "sg:phone":"+39 0541 981421",
    "sg:postcode":"47836",
    "sg:province":"Rimini",
    "sg:tags":[
        "bedroom"
    ],
    "wof:name":"Eusebi Mobili Di Marchetti N. & C. Sas",
    "wof:placetype":"venue"
},
  "geometry": {"coordinates":[12.677249,43.858513],"type":"Point"}
}