{
  "type": "Feature",
  "properties": {
    "addr:full":"Contrada Ponte Valentino 82100 Benevento Benevento Benevento 82100",
    "addr:postcode":"82100;82100",
    "addr:street":"Contrada Ponte Valentino",
    "iso:country":"IT",
    "sg:address":"Contrada Ponte Valentino 82100 Benevento",
    "sg:city":"Benevento",
    "sg:classifiers":[
        {
            "category":"Professional",
            "subcategory":"Engineering",
            "type":"Services"
        }
    ],
    "sg:phone":"+39 0824 357248",
    "sg:postcode":"82100",
    "sg:province":"Benevento",
    "sg:tags":[
        "machine",
        "-",
        "mechanical"
    ],
    "wof:name":"Tools Srl",
    "wof:placetype":"venue"
},
  "geometry": {"coordinates":[14.831263,41.146179],"type":"Point"}
}