{
  "type": "Feature",
  "properties": {
    "iso:country":"IT",
    "sg:address":"100, Via Romentino 28069 Trecate",
    "sg:city":"Trecate",
    "sg:classifiers":[
        {
            "category":"Food & Beverages",
            "subcategory":"Dairy",
            "type":"Retail Goods"
        }
    ],
    "sg:phone":"+39 0321 783090",
    "sg:postcode":"28069",
    "sg:province":"Novara",
    "sg:tags":[
        "product"
    ],
    "wof:name":"Si Invernizzi Srl",
    "wof:placetype":"venue"
},
  "geometry": {"coordinates":[8.730727,45.444557],"type":"Point"}
}