{
  "type": "Feature",
  "properties": {
    "iso:country":"IT",
    "sg:address":"09170 Oristano",
    "sg:city":"Oristano",
    "sg:orig_category":"Articoli Da Regalo. Arte Ed Artigianato Artistico. Shopping",
    "sg:phone":"+39 0783 767046",
    "sg:postcode":"09170",
    "sg:province":"Oristano",
    "wof:name":"Misterios Di  Marongiu Maria Luisa",
    "wof:placetype":"venue"
},
  "geometry": {"coordinates":[8.605074,39.917812],"type":"Point"}
}