{
  "type": "Feature",
  "properties": {
    "iso:country":"IT",
    "sg:address":"Via Degli Esportatori 2 96016 Lentini",
    "sg:city":"Lentini",
    "sg:classifiers":[
        {
            "category":"Food & Beverages",
            "subcategory":"Fruits & Vegetables",
            "type":"Retail Goods"
        }
    ],
    "sg:phone":"+39 095 901344",
    "sg:postcode":"96016",
    "sg:province":"Siracusa",
    "sg:website":"www.sestoesorrentino.com",
    "wof:name":"Fratelli Sesto E Sorrentino S.r.l.",
    "wof:placetype":"venue"
},
  "geometry": {"coordinates":[14.9981422424,37.299621582],"type":"Point"}
}