{
  "type": "Feature",
  "properties": {
    "addr:full":"33052 Cervignano Friuli Udine 33052",
    "addr:postcode":"33052;33052",
    "iso:country":"IT",
    "sg:address":"33052 Cervignano Friuli",
    "sg:orig_category":"Pratiche Automobilistiche",
    "sg:phone":"+39 0431 33725",
    "sg:postcode":"33052",
    "sg:province":"Udine",
    "wof:name":"Agenzia La Pratica",
    "wof:placetype":"venue"
},
  "geometry": {"coordinates":[13.3313369751,45.8259658813],"type":"Point"}
}