{
  "type": "Feature",
  "properties": {
    "iso:country":"IT",
    "sg:address":"19/21, Via Socrate 22070 Casnate Con Bernate",
    "sg:city":"Casnate",
    "sg:classifiers":[
        {
            "category":"Banks & Credit Unions",
            "subcategory":"Investment Brokerage",
            "type":"Services"
        }
    ],
    "sg:phone":"+39 39031451619",
    "sg:postcode":"22070",
    "sg:province":"Como",
    "sg:tags":[
        "-",
        "transport",
        "related"
    ],
    "wof:name":"Piffaretti E Olivieri (s.p.a.)",
    "wof:placetype":"venue"
},
  "geometry": {"coordinates":[9.082734,45.762218],"type":"Point"}
}