{
  "type": "Feature",
  "properties": {
    "iso:country":"IT",
    "sg:address":"20131 Milano",
    "sg:city":"Milano",
    "sg:orig_category":"Persiane Ed Avvolgibili",
    "sg:phone":"+39 02 259 2375",
    "sg:postcode":"20131",
    "sg:province":"Milano",
    "sg:website":"http://www.cobrecosrl.it",
    "wof:name":"Tecno Edil Componenti Srl",
    "wof:placetype":"venue"
},
  "geometry": {"coordinates":[9.2411775589,45.5045967102],"type":"Point"}
}