{
  "type": "Feature",
  "properties": {
    "iso:country":"IT",
    "sg:address":"10071 Borgaro Torinese",
    "sg:city":"Borgaro Torinese",
    "sg:orig_category":"Accessori Moda D'abbigliamento. Forniture Per Abbigliamento E Pelletterie",
    "sg:phone":"+39 011 450 2056",
    "sg:postcode":"10071",
    "sg:province":"Torino",
    "wof:name":"Ripari Massimo Ricamificio Lufra",
    "wof:placetype":"venue"
},
  "geometry": {"coordinates":[7.64851,45.153957],"type":"Point"}
}