{
  "type": "Feature",
  "properties": {
    "iso:country":"IT",
    "sg:address":"Via Ernesto Cabruna 9 15100 Alessandria",
    "sg:city":"Alessandria",
    "sg:classifiers":[
        {
            "category":"Wholesale",
            "subcategory":"Construction Materials",
            "type":"Manufacturing & Wholesale Goods"
        }
    ],
    "sg:phone":"+39 0131 222552",
    "sg:postcode":"15100",
    "sg:province":"Alessandria",
    "sg:tags":[
        "mould",
        "injection"
    ],
    "sg:website":"www.amcstampi.it",
    "wof:name":"A.m.c. Stampi Srl",
    "wof:placetype":"venue"
},
  "geometry": {"coordinates":[8.616552,44.92514],"type":"Point"}
}