{
  "type": "Feature",
  "properties": {
    "iso:country":"IT",
    "sg:address":"24042 Capriate San Gervasio",
    "sg:city":"Capriate San Gervasio",
    "sg:orig_category":"Ospedali E Servizi Sanitari",
    "sg:phone":"+39 02 9096 2737",
    "sg:postcode":"24042",
    "sg:province":"Bergamo",
    "wof:name":"Croce Rossa",
    "wof:placetype":"venue"
},
  "geometry": {"coordinates":[9.532485,45.628239],"type":"Point"}
}