{
  "type": "Feature",
  "properties": {
    "iso:country":"IT",
    "sg:address":"Via Agnoletti 16/a 42100 Reggio Emilia",
    "sg:classifiers":[
        {
            "category":"Manufacturing",
            "subcategory":"Tools & Machinery",
            "type":"Manufacturing & Wholesale Goods"
        }
    ],
    "sg:phone":"+39 0522 303692",
    "sg:postcode":"42100",
    "sg:province":"Reggio Nell'Emilia",
    "sg:tags":[
        "machine"
    ],
    "wof:name":"Catellani & C. Srl",
    "wof:placetype":"venue"
},
  "geometry": {"coordinates":[10.617789,44.712536],"type":"Point"}
}