{
  "type": "Feature",
  "properties": {
    "addr:full":"10153 Torino Torino Torino 10153",
    "addr:postcode":"10153;10153",
    "iso:country":"IT",
    "sg:address":"10153 Torino",
    "sg:city":"Torino",
    "sg:orig_category":"Forniture Per Attivita' Industriali",
    "sg:phone":"+39 011 898 7237",
    "sg:postcode":"10153",
    "sg:province":"Torino",
    "wof:name":"S.u.m.m.a. (s.n.c.)",
    "wof:placetype":"venue"
},
  "geometry": {"coordinates":[7.7134866714,45.0742073059],"type":"Point"}
}