{
  "type": "Feature",
  "properties": {
    "iso:country":"IT",
    "sg:address":"61, Via Frattalunga 31011 Asolo",
    "sg:city":"Asolo",
    "sg:classifiers":[
        {
            "category":"Home & Garden",
            "subcategory":"Home Furnishings",
            "type":"Retail Goods"
        }
    ],
    "sg:phone":"+39 39042355124",
    "sg:postcode":"31011",
    "sg:province":"Treviso",
    "sg:tags":[
        "household"
    ],
    "wof:name":"Soligo",
    "wof:placetype":"venue"
},
  "geometry": {"coordinates":[11.937717,45.76873],"type":"Point"}
}