{
  "type": "Feature",
  "properties": {
    "iso:country":"IT",
    "sg:address":"20090 Trezzano Sul Naviglio",
    "sg:city":"Trezzano sul Naviglio",
    "sg:orig_category":"Servizi Ausiliari Dei Mezzi Di Trasporto",
    "sg:phone":"+39 02 445 3746",
    "sg:postcode":"20090",
    "sg:province":"Milano",
    "wof:name":"Restelli S.n.c. Di Marazzina Paolo E Venturelli Loris",
    "wof:placetype":"venue"
},
  "geometry": {"coordinates":[9.051887,45.418362],"type":"Point"}
}