{
  "type": "Feature",
  "properties": {
    "addr:full":"1, Via Garibaldi 20090 Assago Assago Milano 20090",
    "addr:postcode":"20090;20090",
    "addr:street":"Via Garibaldi;Assago",
    "iso:country":"IT",
    "sg:address":"1, Via Garibaldi 20090 Assago",
    "sg:city":"Assago",
    "sg:classifiers":[
        {
            "category":"Utilities",
            "subcategory":"Telephone",
            "type":"Services"
        }
    ],
    "sg:phone":"+39 02 4884 1173",
    "sg:postcode":"20090",
    "sg:province":"Milano",
    "sg:tags":[
        "telecommunication"
    ],
    "wof:name":"Specialtel - Lem S.p.a.",
    "wof:placetype":"venue"
},
  "geometry": {"coordinates":[9.127235,45.409901],"type":"Point"}
}