{
  "type": "Feature",
  "properties": {
    "iso:country":"IT",
    "sg:address":"33100 Udine",
    "sg:city":"Udine",
    "sg:orig_category":"Prodotti Finiti Stampati. Forniture E Materiali Per Imballaggio E Confezionamento. Forniture Per Attivita' Commerciali Ed Artigianali",
    "sg:phone":"+39 0432 43818",
    "sg:postcode":"33100",
    "sg:province":"Udine",
    "wof:name":"Erjavec Stefano",
    "wof:placetype":"venue"
},
  "geometry": {"coordinates":[13.2349233627,46.0676994324],"type":"Point"}
}