{
  "type": "Feature",
  "properties": {
    "addr:full":"06083 Bastia Bastia Perugia 06083",
    "addr:postcode":"06083;06083",
    "iso:country":"IT",
    "sg:address":"06083 Bastia",
    "sg:city":"Bastia",
    "sg:orig_category":"Ospedali E Servizi Sanitari",
    "sg:phone":"+39 075 800 0308",
    "sg:postcode":"06083",
    "sg:province":"Perugia",
    "wof:name":"Villa Salus",
    "wof:placetype":"venue"
},
  "geometry": {"coordinates":[12.549567,43.06638],"type":"Point"}
}