{
  "type": "Feature",
  "properties": {
    "iso:country":"IT",
    "sg:address":"48100 Ravenna",
    "sg:city":"Ravenna",
    "sg:orig_category":"Imprese Edili",
    "sg:phone":"+39 0544 428111",
    "sg:postcode":"48100",
    "sg:province":"Ravenna",
    "sg:website":"http://www.cmcra.com",
    "wof:name":"Cooperativa Muratori E Cementisti - Cmc Di Ravenna S.c.a.r.l.",
    "wof:placetype":"venue"
},
  "geometry": {"coordinates":[12.274966,44.486099],"type":"Point"}
}