{
  "type": "Feature",
  "properties": {
    "addr:full":"22063 Cantu' Como 22063",
    "addr:postcode":"22063;22063",
    "addr:street":"Cantu ' Como",
    "iso:country":"IT",
    "sg:address":"22063 Cantu'",
    "sg:orig_category":"Automobili - Commercio",
    "sg:phone":"+39 031 732315",
    "sg:postcode":"22063",
    "sg:province":"Como",
    "wof:name":"Mb Auto Di Matteo Borghi",
    "wof:placetype":"venue"
},
  "geometry": {"coordinates":[9.124004,45.749664],"type":"Point"}
}