{
  "type": "Feature",
  "properties": {
    "iso:country":"IT",
    "sg:address":"32026 Mel",
    "sg:city":"Mel",
    "sg:classifiers":[
        {
            "category":"Home & Garden",
            "subcategory":"Home Furnishings",
            "type":"Retail Goods"
        }
    ],
    "sg:phone":"+39 0437 540388",
    "sg:postcode":"32026",
    "sg:province":"Belluno",
    "sg:tags":[
        "professional",
        "furniture",
        "accommodation",
        "supply"
    ],
    "sg:website":"http://www.agma.it",
    "wof:name":"Agma Arredo Inox Professionale Srl",
    "wof:placetype":"venue"
},
  "geometry": {"coordinates":[12.1084871292,46.0800704956],"type":"Point"}
}