{
  "type": "Feature",
  "properties": {
    "addr:full":"63029 Servigliano Servigliano Ascoli Piceno 63029",
    "addr:housenumber":"63029",
    "addr:postcode":"63029",
    "addr:street":"Servigliano Servigliano",
    "iso:country":"IT",
    "sg:address":"63029 Servigliano",
    "sg:city":"Servigliano",
    "sg:classifiers":[
        {
            "category":"Cinema",
            "subcategory":"Movie Theater",
            "type":"Entertainment"
        }
    ],
    "sg:phone":"+39 0734 710075",
    "sg:postcode":"63029",
    "sg:province":"Ascoli Piceno",
    "wof:name":"Cinema Moderno Multisala Di Caraffa P.",
    "wof:placetype":"venue"
},
  "geometry": {"coordinates":[13.574977,42.8554],"type":"Point"}
}