{
  "type": "Feature",
  "properties": {
    "iso:country":"IT",
    "sg:address":"62012 Civitanova Marche",
    "sg:city":"Civitanova Marche",
    "sg:orig_category":"Abbigliamento Intimo, Calze E Costumi Da Bagno. Sport - Articoli E Forniture. Shopping",
    "sg:phone":"+39 0733 755694",
    "sg:postcode":"62012",
    "sg:province":"Macerata",
    "wof:name":"Centro Sport Medi@store",
    "wof:placetype":"venue"
},
  "geometry": {"coordinates":[13.694167,43.318214],"type":"Point"}
}