{
  "type": "Feature",
  "properties": {
    "addr:full":"00174 Roma Roma Roma 00174",
    "addr:postcode":"00174;00174",
    "iso:country":"IT",
    "sg:address":"00174 Roma",
    "sg:city":"Roma",
    "sg:orig_category":"Servizi Culturali E Per Lo Spettacolo",
    "sg:phone":"+39 06 761 0656",
    "sg:postcode":"00174",
    "sg:province":"Roma",
    "wof:name":"Cinematografo Atlantic",
    "wof:placetype":"venue"
},
  "geometry": {"coordinates":[12.555319,41.860836],"type":"Point"}
}