{
  "type": "Feature",
  "properties": {
    "addr:full":"Via Bioli 18 36072 Chiampo Chiampo Vicenza 36072",
    "addr:housenumber":"18",
    "addr:postcode":"36072;36072",
    "addr:street":"Via Bioli",
    "iso:country":"IT",
    "sg:address":"Via Bioli 18 36072 Chiampo",
    "sg:city":"Chiampo",
    "sg:classifiers":[
        {
            "category":"Home & Garden",
            "subcategory":"Carpets & Floor Coverings",
            "type":"Retail Goods"
        }
    ],
    "sg:phone":"+39 0444 625143",
    "sg:postcode":"36072",
    "sg:province":"Vicenza",
    "sg:tags":[
        "animal",
        "skin"
    ],
    "wof:name":"Esapel Spa",
    "wof:placetype":"venue"
},
  "geometry": {"coordinates":[11.304137,45.527115],"type":"Point"}
}