{
  "type": "Feature",
  "properties": {
    "iso:country":"IT",
    "sg:address":"35010 Vigonza",
    "sg:city":"Vigonza",
    "sg:orig_category":"Elettronica Industriale, Prodotti E Apparecchiature",
    "sg:phone":"+39 049 893 1563",
    "sg:postcode":"35010",
    "sg:province":"Padova",
    "sg:website":"http://www.micronovasrl.com",
    "wof:name":"Micronova Srl",
    "wof:placetype":"venue"
},
  "geometry": {"coordinates":[11.956394,45.433239],"type":"Point"}
}