{
  "type": "Feature",
  "properties": {
    "iso:country":"IT",
    "sg:address":"20, V. Somalia 20032 Cormano",
    "sg:city":"Cormano",
    "sg:classifiers":[
        {
            "category":"Shopping",
            "subcategory":"Computers & Home Electronics",
            "type":"Retail Goods"
        }
    ],
    "sg:phone":"+39 390 266 3271",
    "sg:postcode":"20032",
    "sg:province":"Milano",
    "sg:tags":[
        "electronic",
        "electrical",
        "equipment"
    ],
    "sg:website":"http://www.aros.it:ws_end: :mark:ws:http://www.paginegialle.it/arossrl",
    "wof:name":"Aros",
    "wof:placetype":"venue"
},
  "geometry": {"coordinates":[9.163473,45.541145],"type":"Point"}
}