{
  "type": "Feature",
  "properties": {
    "addr:full":"21, Via Di Vittorio Giuseppe 20068 Peschiera Borromeo Peschiera Borromeo Milano 20068",
    "addr:postcode":"20068;20068",
    "addr:street":"Via Di Vittorio Giuseppe",
    "iso:country":"IT",
    "sg:address":"21, Via Di Vittorio Giuseppe 20068 Peschiera Borromeo",
    "sg:city":"Peschiera Borromeo",
    "sg:classifiers":[
        {
            "category":"Shopping",
            "type":"Retail Goods"
        }
    ],
    "sg:phone":"+39 02 5530 1577",
    "sg:postcode":"20068",
    "sg:province":"Milano",
    "sg:tags":[
        "finished",
        "-",
        "metallic"
    ],
    "wof:name":"Fratelli Tassalini Officina Meccanica (s.p.a.)",
    "wof:placetype":"venue"
},
  "geometry": {"coordinates":[9.2884464264,45.4307479858],"type":"Point"}
}