{
  "type": "Feature",
  "properties": {
    "addr:full":"4, Via Pacinotti Antonio Valdaro 46100 Mantova Mantova Mantova 46100",
    "addr:postcode":"46100;46100",
    "addr:street":"Via Pacinotti Antonio Valdaro",
    "iso:country":"IT",
    "sg:address":"4, Via Pacinotti Antonio Valdaro 46100 Mantova",
    "sg:city":"Mantova",
    "sg:classifiers":[
        {
            "category":"Manufacturing",
            "subcategory":"Rubber & Plastics",
            "type":"Manufacturing & Wholesale Goods"
        }
    ],
    "sg:phone":"+39 0376 302412",
    "sg:postcode":"46100",
    "sg:province":"Mantova",
    "wof:name":"Plastindustria Mantovana (s.p.a.)",
    "wof:placetype":"venue"
},
  "geometry": {"coordinates":[10.7976980209,45.1603660583],"type":"Point"}
}