{
  "type": "Feature",
  "properties": {
    "addr:full":"20049 Concorezzo Concorezzo Milano 20049",
    "addr:postcode":"20049;20049",
    "iso:country":"IT",
    "sg:address":"20049 Concorezzo",
    "sg:city":"Concorezzo",
    "sg:orig_category":"Filati E Tessuti - Trattamenti",
    "sg:phone":"+39 039 604 0865",
    "sg:postcode":"20049",
    "sg:province":"Milano",
    "wof:name":"Texservice Srl",
    "wof:placetype":"venue"
},
  "geometry": {"coordinates":[9.3685150146,45.6080093384],"type":"Point"}
}