{
  "type": "Feature",
  "properties": {
    "iso:country":"IT",
    "sg:address":"30010 Campolongo Maggiore",
    "sg:city":"Lova",
    "sg:orig_category":"Accessori Moda D'abbigliamento. Forniture Per Abbigliamento E Pelletterie. Shopping",
    "sg:phone":"+39 049 972 5184",
    "sg:postcode":"30010",
    "sg:province":"Venezia",
    "wof:name":"Dona' Vilma & C. S.n.c.",
    "wof:placetype":"venue"
},
  "geometry": {"coordinates":[12.092596,45.354263],"type":"Point"}
}