{
  "type": "Feature",
  "properties": {
    "addr:full":"Via Risorgimento 22 26033 Pescarolo Pescarolo Cremona 26033",
    "addr:housenumber":"22",
    "addr:postcode":"26033;26033",
    "addr:street":"Via Risorgimento",
    "iso:country":"IT",
    "sg:address":"Via Risorgimento 22 26033 Pescarolo",
    "sg:city":"Pescarolo",
    "sg:orig_category":"Inside Door Elements Of Wood And Plastic",
    "sg:phone":"+39 0372 835238",
    "sg:postcode":"26033",
    "sg:province":"Cremona",
    "sg:website":"www.melgari.com",
    "wof:name":"Melgari Srl",
    "wof:placetype":"venue"
},
  "geometry": {"coordinates":[10.221629,45.184395],"type":"Point"}
}