{
  "type": "Feature",
  "properties": {
    "iso:country":"IT",
    "sg:address":"00131 Roma",
    "sg:city":"Roma",
    "sg:orig_category":"Prodotti Alimentari",
    "sg:phone":"+39 06 414851",
    "sg:postcode":"00131",
    "sg:province":"Roma",
    "wof:name":"Centrale Del Latte Di Roma Spa",
    "wof:placetype":"venue"
},
  "geometry": {"coordinates":[12.6004800797,41.9526634216],"type":"Point"}
}