{
  "type": "Feature",
  "properties": {
    "iso:country":"IT",
    "sg:address":"32036 Sedico",
    "sg:city":"Sedico",
    "sg:orig_category":"Forniture Per Edilizia E Lavori Pubblici",
    "sg:phone":"+39 0437 838581",
    "sg:postcode":"32036",
    "sg:province":"Belluno",
    "wof:name":"Finblok Montaggi (s.p.a.)",
    "wof:placetype":"venue"
},
  "geometry": {"coordinates":[12.0998687744,46.1094970703],"type":"Point"}
}