{
  "type": "Feature",
  "properties": {
    "addr:full":"65/f, Via Garibaldi Giuseppe Piatucco 25065 Lumezzane Lumezzane Brescia 25065",
    "addr:housenumber":"65 / f",
    "addr:postcode":"25065;25065",
    "addr:street":"Via Garibaldi Giuseppe Piatucco",
    "iso:country":"IT",
    "sg:address":"65/f, Via Garibaldi Giuseppe Piatucco 25065 Lumezzane",
    "sg:city":"Lumezzane",
    "sg:classifiers":[
        {
            "category":"Shopping",
            "type":"Retail Goods"
        }
    ],
    "sg:phone":"+39 030 897 0660",
    "sg:postcode":"25065",
    "sg:province":"Brescia",
    "sg:tags":[
        "finished",
        "-",
        "metallic"
    ],
    "wof:name":"S.i.t. Di Tampalini G. & C. (s.n.c.)",
    "wof:placetype":"venue"
},
  "geometry": {"coordinates":[10.2229576111,45.5398292542],"type":"Point"}
}