{
  "type": "Feature",
  "properties": {
    "iso:country":"IT",
    "sg:address":"66, Via Monte Rosa 10098 Rivoli",
    "sg:city":"Rivoli",
    "sg:classifiers":[
        {
            "category":"Professional",
            "subcategory":"Engineering",
            "type":"Services"
        }
    ],
    "sg:phone":"+39 011 953 1717",
    "sg:postcode":"10098",
    "sg:province":"Torino",
    "sg:tags":[
        "machine",
        "-",
        "mechanical"
    ],
    "wof:name":"Costalla Srl",
    "wof:placetype":"venue"
},
  "geometry": {"coordinates":[7.476822,45.02454],"type":"Point"}
}