{
  "type": "Feature",
  "properties": {
    "addr:full":"25014 Castenedolo Castenedolo Brescia 25014",
    "addr:postcode":"25014;25014",
    "iso:country":"IT",
    "sg:address":"25014 Castenedolo",
    "sg:city":"Castenedolo",
    "sg:orig_category":"Prodotti Alimentari",
    "sg:phone":"+39 030 213 0439",
    "sg:postcode":"25014",
    "sg:province":"Brescia",
    "wof:name":"Zanella Angiolino",
    "wof:placetype":"venue"
},
  "geometry": {"coordinates":[10.2950363159,45.465675354],"type":"Point"}
}