{
  "type": "Feature",
  "properties": {
    "iso:country":"IT",
    "sg:address":"Via Delle Acacie 2; Perugia; 06100",
    "sg:classifiers":[
        {
            "category":"Banks & Credit Unions",
            "subcategory":"Bank",
            "type":"Services"
        }
    ],
    "sg:phone":"+39 075 500 5013",
    "wof:name":"Banca Delle Marche Spa",
    "wof:placetype":"venue"
},
  "geometry": {"coordinates":[12.635885,43.052929],"type":"Point"}
}