{
  "type": "Feature",
  "properties": {
    "addr:full":"10142 Torino Torino Torino 10142",
    "addr:postcode":"10142;10142",
    "iso:country":"IT",
    "sg:address":"10142 Torino",
    "sg:city":"Torino",
    "sg:orig_category":"Trattamenti Termici E Superficiali Metalli, Galvanotecnica",
    "sg:phone":"+39 011 772 4202",
    "sg:postcode":"10142",
    "sg:province":"Torino",
    "wof:name":"Crom.al.t Di Allara Mario & C. Snc",
    "wof:placetype":"venue"
},
  "geometry": {"coordinates":[7.6183176041,45.0704994202],"type":"Point"}
}