{
  "type": "Feature",
  "properties": {
    "iso:country":"IT",
    "sg:address":"19, Via Selva 60037 Monte San Vito",
    "sg:city":"Monte San Vito",
    "sg:classifiers":[
        {
            "category":"Manufacturing",
            "subcategory":"Rubber & Plastics",
            "type":"Manufacturing & Wholesale Goods"
        }
    ],
    "sg:phone":"+39 39071749891",
    "sg:postcode":"60037",
    "sg:province":"Ancona",
    "wof:name":"Tecno Plast S.r.l.",
    "wof:placetype":"venue"
},
  "geometry": {"coordinates":[13.3004760742,43.5885925293],"type":"Point"}
}