{
  "type": "Feature",
  "properties": {
    "addr:full":"Via Delle Industrie 17 31047 Ponte Di Piave Ponte di Piave Treviso 31047",
    "addr:housenumber":"17;di piave",
    "addr:postcode":"31047;31047",
    "addr:street":"Via Delle Industrie",
    "iso:country":"IT",
    "sg:address":"Via Delle Industrie 17 31047 Ponte Di Piave",
    "sg:city":"Ponte di Piave",
    "sg:classifiers":[
        {
            "category":"Sports & Exercise",
            "subcategory":"Race Track",
            "type":"Entertainment"
        }
    ],
    "sg:phone":"+39 0422 853018",
    "sg:postcode":"31047",
    "sg:province":"Treviso",
    "sg:tags":[
        "abrasive",
        "belt"
    ],
    "sg:website":"www.nastroflex.it",
    "wof:name":"Nastroflex Spa",
    "wof:placetype":"venue"
},
  "geometry": {"coordinates":[12.509977,45.702202],"type":"Point"}
}