{
  "type": "Feature",
  "properties": {
    "iso:country":"IT",
    "sg:address":"124, Via Dante 25080 Prevalle",
    "sg:city":"Prevalle",
    "sg:classifiers":[
        {
            "category":"Manufacturing",
            "subcategory":"Rubber & Plastics",
            "type":"Manufacturing & Wholesale Goods"
        }
    ],
    "sg:phone":"+39 39030603416",
    "sg:postcode":"25080",
    "sg:province":"Brescia",
    "wof:name":"Resine Ragnoli (s.r.l.)",
    "wof:placetype":"venue"
},
  "geometry": {"coordinates":[10.2229576111,45.5398292542],"type":"Point"}
}