{
  "type": "Feature",
  "properties": {
    "iso:country":"IT",
    "sg:address":"80, Via Roma 46037 Roncoferraro",
    "sg:city":"Roncoferraro",
    "sg:classifiers":[
        {
            "category":"Manufacturing",
            "subcategory":"Tools & Machinery",
            "type":"Manufacturing & Wholesale Goods"
        }
    ],
    "sg:phone":"+39 0376 664290",
    "sg:postcode":"46037",
    "sg:province":"Mantova",
    "sg:tags":[
        "environment",
        "equipment",
        "-"
    ],
    "wof:name":"Savi Officine Meccaniche Srl",
    "wof:placetype":"venue"
},
  "geometry": {"coordinates":[10.951674,45.132225],"type":"Point"}
}