{
  "type": "Feature",
  "properties": {
    "iso:country":"IT",
    "sg:address":"25060 Collebeato",
    "sg:city":"Collebeato",
    "sg:orig_category":"Cancelli, Porte E Portoni Automatici E Telecomandati",
    "sg:phone":"+39 030 251 0518",
    "sg:postcode":"25060",
    "sg:province":"Brescia",
    "wof:name":"Serr Metall Snc",
    "wof:placetype":"venue"
},
  "geometry": {"coordinates":[10.211319,45.576591],"type":"Point"}
}