{
  "type": "Feature",
  "properties": {
    "iso:country":"IT",
    "sg:address":"23899 Robbiate",
    "sg:city":"Robbiate",
    "sg:orig_category":"Antifurto",
    "sg:phone":"+39 039 511017",
    "sg:postcode":"23899",
    "sg:province":"Lecco",
    "wof:name":"Reani Sergio - Rs Lan",
    "wof:placetype":"venue"
},
  "geometry": {"coordinates":[9.444743,45.686531],"type":"Point"}
}