{
  "type": "Feature",
  "properties": {
    "iso:country":"IT",
    "sg:address":"96, Via Chiesanuova 30027 San Dona' Di Piave",
    "sg:classifiers":[
        {
            "category":"Shopping",
            "subcategory":"Clothing, Apparel, & Fashions",
            "type":"Retail Goods"
        }
    ],
    "sg:phone":"+39 0421 235804",
    "sg:postcode":"30027",
    "sg:province":"Venezia",
    "sg:tags":[
        "clothes"
    ],
    "wof:name":"Giemme S.r.l.",
    "wof:placetype":"venue"
},
  "geometry": {"coordinates":[12.577342,45.596626],"type":"Point"}
}