{
  "type": "Feature",
  "properties": {
    "iso:country":"IT",
    "sg:address":"80038 Pomigliano D'arco",
    "sg:orig_category":"Scuole E Servizi Scolastici",
    "sg:phone":"+39 081 803 1640",
    "sg:postcode":"80038",
    "sg:province":"Napoli",
    "wof:name":"Istituto Magistrale Statale M. Serao",
    "wof:placetype":"venue"
},
  "geometry": {"coordinates":[14.341682,40.878067],"type":"Point"}
}