{
  "type": "Feature",
  "properties": {
    "addr:full":"9, Via S. Francesco 36056 Tezze Sul Brenta Tezze sul Brenta Vicenza 36056",
    "addr:postcode":"36056;36056",
    "addr:street":"Via S. Francesco",
    "iso:country":"IT",
    "sg:address":"9, Via S. Francesco 36056 Tezze Sul Brenta",
    "sg:city":"Tezze sul Brenta",
    "sg:classifiers":[
        {
            "category":"Manufacturing",
            "subcategory":"Glass & Minerals",
            "type":"Manufacturing & Wholesale Goods"
        }
    ],
    "sg:phone":"+39 0424 560226",
    "sg:postcode":"36056",
    "sg:province":"Vicenza",
    "wof:name":"Therm - Is (s.r.l.)",
    "wof:placetype":"venue"
},
  "geometry": {"coordinates":[11.799861,45.669445],"type":"Point"}
}