{
  "type": "Feature",
  "properties": {
    "iso:country":"IT",
    "sg:address":"80059 Torre Del Greco",
    "sg:city":"Torre del Greco",
    "sg:orig_category":"Dolciumi E Gelati",
    "sg:phone":"+39 081 847 2499",
    "sg:postcode":"80059",
    "sg:province":"Napoli",
    "wof:name":"Garofalo Nicola",
    "wof:placetype":"venue"
},
  "geometry": {"coordinates":[14.333447,40.83054],"type":"Point"}
}