{
  "type": "Feature",
  "properties": {
    "iso:country":"IT",
    "sg:address":"20121 Milano",
    "sg:city":"Milano",
    "sg:orig_category":"Servizi Editoriali. Professionisti - Studi E Servizi Ed Associazioni Di Interesse Aziendale",
    "sg:phone":"+39 02 2900 3860",
    "sg:postcode":"20121",
    "sg:province":"Milano",
    "wof:name":"Marchelli Maria Grazia",
    "wof:placetype":"venue"
},
  "geometry": {"coordinates":[9.189754,45.478733],"type":"Point"}
}