{
  "type": "Feature",
  "properties": {
    "addr:full":"22072 Cermenate Cermenate Como 22072",
    "addr:postcode":"22072;22072",
    "iso:country":"IT",
    "sg:address":"22072 Cermenate",
    "sg:city":"Cermenate",
    "sg:orig_category":"Centri Di Estetica E Cosmesi E Servizi",
    "sg:phone":"+39 031 778999",
    "sg:postcode":"22072",
    "sg:province":"Como",
    "wof:name":"Keen S.n.c. Di Pellucchi Alessia Maria E Beltrame Massimo",
    "wof:placetype":"venue"
},
  "geometry": {"coordinates":[9.124907,45.740074],"type":"Point"}
}