{
  "type": "Feature",
  "properties": {
    "addr:full":"2, Via Paolo Vi 46044 Goito Goito Mantova 46044",
    "addr:postcode":"46044;46044",
    "addr:street":"Via Paolo Vi",
    "iso:country":"IT",
    "sg:address":"2, Via Paolo Vi 46044 Goito",
    "sg:city":"Goito",
    "sg:classifiers":[
        {
            "category":"Professional",
            "subcategory":"Engineering",
            "type":"Services"
        }
    ],
    "sg:phone":"+39 0376 687620",
    "sg:postcode":"46044",
    "sg:province":"Mantova",
    "sg:tags":[
        "machine",
        "-",
        "mechanical"
    ],
    "wof:name":"Newtec Labelling Srl",
    "wof:placetype":"venue"
},
  "geometry": {"coordinates":[10.660057,45.274345],"type":"Point"}
}