{
  "type": "Feature",
  "properties": {
    "addr:full":"34077 Ronchi Dei Legionari Ronchi dei Legionari Gorizia 34077",
    "addr:postcode":"34077;34077",
    "iso:country":"IT",
    "sg:address":"34077 Ronchi Dei Legionari",
    "sg:city":"Ronchi dei Legionari",
    "sg:orig_category":"Serramenti Ed Infissi. Prodotti Vari In Metallo",
    "sg:phone":"+39 0481 777465",
    "sg:postcode":"34077",
    "sg:province":"Gorizia",
    "wof:name":"Glereani Ervino",
    "wof:placetype":"venue"
},
  "geometry": {"coordinates":[13.513687,45.833191],"type":"Point"}
}