{
  "type": "Feature",
  "properties": {
    "addr:full":"20, V. Guido Rossa 20020 Arconate Arconate Milano 20020",
    "addr:housenumber":"20",
    "addr:postcode":"20020;20020",
    "addr:street":"V. Guido Rossa",
    "iso:country":"IT",
    "sg:address":"20, V. Guido Rossa 20020 Arconate",
    "sg:city":"Arconate",
    "sg:classifiers":[
        {
            "category":"Manufacturing",
            "subcategory":"Metals",
            "type":"Manufacturing & Wholesale Goods"
        }
    ],
    "sg:phone":"+39 0331 462380",
    "sg:postcode":"20020",
    "sg:province":"Milano",
    "sg:tags":[
        "processing"
    ],
    "wof:name":"C.m.g.",
    "wof:placetype":"venue"
},
  "geometry": {"coordinates":[8.8589954376,45.5460510254],"type":"Point"}
}