{
  "type": "Feature",
  "properties": {
    "addr:full":"Via Carlo Erba 6 27029 Vigevano Vigevano Pavia 27029",
    "addr:housenumber":"6",
    "addr:postcode":"27029;27029",
    "addr:street":"Via Carlo Erba",
    "iso:country":"IT",
    "sg:address":"Via Carlo Erba 6 27029 Vigevano",
    "sg:city":"Vigevano",
    "sg:classifiers":[
        {
            "category":"Shopping",
            "subcategory":"Bridal",
            "type":"Retail Goods"
        }
    ],
    "sg:phone":"+39 0381 82100",
    "sg:postcode":"27029",
    "sg:province":"Pavia",
    "sg:tags":[
        "gown"
    ],
    "sg:website":"www.domoadami.com",
    "wof:name":"Glam Srl",
    "wof:placetype":"venue"
},
  "geometry": {"coordinates":[8.858808,45.312225],"type":"Point"}
}