{
  "type": "Feature",
  "properties": {
    "iso:country":"IT",
    "sg:address":"1, Via Portenari 30100 Venezia",
    "sg:classifiers":[
        {
            "category":"Autos & Motor Vehicles",
            "subcategory":"Boat Sales",
            "type":"Retail Goods"
        }
    ],
    "sg:phone":"+39 39041931833",
    "sg:province":"VE",
    "wof:name":"Vio Ing. Ruggero (s.r.l.)",
    "wof:placetype":"venue"
},
  "geometry": {"coordinates":[12.211774,45.461899],"type":"Point"}
}