{
  "type": "Feature",
  "properties": {
    "iso:country":"IT",
    "sg:address":"9, Via Dell' Industria 37060 Castel D'azzano",
    "sg:city":"Azzano",
    "sg:classifiers":[
        {
            "category":"Professional",
            "subcategory":"Engineering",
            "type":"Services"
        }
    ],
    "sg:phone":"+39 045 852 0519",
    "sg:postcode":"37060",
    "sg:province":"Verona",
    "sg:tags":[
        "machine",
        "-",
        "mechanical"
    ],
    "wof:name":"Cebi (s.n.c.)",
    "wof:placetype":"venue"
},
  "geometry": {"coordinates":[10.954378,45.349148],"type":"Point"}
}