{
  "type": "Feature",
  "properties": {
    "iso:country":"IT",
    "sg:address":"20026 Novate Milanese",
    "sg:city":"Novate Milanese",
    "sg:orig_category":"Tessuti E Stoffe",
    "sg:phone":"+39 02 356 5821",
    "sg:postcode":"20026",
    "sg:province":"Milano",
    "wof:name":"Olona Jersey Di Gori Roberto Marco E C. Sas",
    "wof:placetype":"venue"
},
  "geometry": {"coordinates":[9.1275682449,45.5267410278],"type":"Point"}
}