{
  "type": "Feature",
  "properties": {
    "iso:country":"IT",
    "sg:address":"Via E. Mattei 17 - Casier 31030 Dosson",
    "sg:city":"Casier",
    "sg:classifiers":[
        {
            "category":"Shopping",
            "subcategory":"Computers & Home Electronics",
            "type":"Retail Goods"
        }
    ],
    "sg:phone":"+39 0422 490177",
    "sg:postcode":"31030",
    "sg:province":"Treviso",
    "sg:tags":[
        "printer",
        "type"
    ],
    "wof:name":"S.v.e.t. S.r.l. Stamperia Veneta Editrice Tipografica",
    "wof:placetype":"venue"
},
  "geometry": {"coordinates":[12.242449,45.615597],"type":"Point"}
}