{
  "type": "Feature",
  "properties": {
    "iso:country":"IT",
    "sg:address":"20090 Opera",
    "sg:city":"Opera",
    "sg:orig_category":"Macchine, Impianti Ed Attrezzature Industria Chimica. Pompe",
    "sg:phone":"+39 02 5760 6287",
    "sg:postcode":"20090",
    "sg:province":"Milano",
    "sg:website":"http://www.pompecucchi.it",
    "wof:name":"Pompe Cucchi Srl",
    "wof:placetype":"venue"
},
  "geometry": {"coordinates":[9.225561,45.376831],"type":"Point"}
}