{
  "type": "Feature",
  "properties": {
    "addr:full":"67027 Raiano L'Aquila 67027",
    "addr:postcode":"67027;67027",
    "iso:country":"IT",
    "sg:address":"67027 Raiano",
    "sg:classifiers":[
        {
            "category":"Manufacturing",
            "subcategory":"Leather Goods",
            "type":"Manufacturing & Wholesale Goods"
        }
    ],
    "sg:phone":"+39 0864 726007",
    "sg:postcode":"67027",
    "sg:province":"L'Aquila",
    "sg:tags":[
        "goods",
        "clothing",
        "supply"
    ],
    "wof:name":"Little Africa Of Tulliani Srl",
    "wof:placetype":"venue"
},
  "geometry": {"coordinates":[13.827972,42.098301],"type":"Point"}
}