{
  "type": "Feature",
  "properties": {
    "iso:country":"IT",
    "sg:address":"00198 Roma",
    "sg:city":"Roma",
    "sg:orig_category":"Servizi Per Lo Sport E Il Tempo Libero. Servizi Vari Di Interesse Pubblico",
    "sg:phone":"+39 06 4425 0904",
    "sg:postcode":"00198",
    "sg:province":"Roma",
    "wof:name":"I Butteri Srl",
    "wof:placetype":"venue"
},
  "geometry": {"coordinates":[12.503992,41.917881],"type":"Point"}
}