{
  "type": "Feature",
  "properties": {
    "iso:country":"IT",
    "sg:address":"46100 Mantova",
    "sg:city":"Mantova",
    "sg:orig_category":"Banche E Servizi Finanziari",
    "sg:phone":"+39 0376 224634",
    "sg:postcode":"46100",
    "sg:province":"Mantova",
    "wof:name":"G.c.a. Italia",
    "wof:placetype":"venue"
},
  "geometry": {"coordinates":[10.785723,45.15538],"type":"Point"}
}