{
  "type": "Feature",
  "properties": {
    "addr:full":"Via Cavalieri Del Lavoro 70017 Putignano Putignano Bari 70017",
    "addr:postcode":"70017;70017",
    "addr:street":"Via Cavalieri Del Lavoro",
    "iso:country":"IT",
    "sg:address":"Via Cavalieri Del Lavoro 70017 Putignano",
    "sg:city":"Putignano",
    "sg:classifiers":[
        {
            "category":"Bars & Pubs",
            "subcategory":"Nightclub",
            "type":"Food & Drink"
        }
    ],
    "sg:phone":"+39 080 493 4552",
    "sg:postcode":"70017",
    "sg:province":"Bari",
    "sg:tags":[
        "cake",
        "bread"
    ],
    "wof:name":"Dolce Bonta' Industria Alimentari Dolciaria (s.r.l.)",
    "wof:placetype":"venue"
},
  "geometry": {"coordinates":[17.107431,40.840576],"type":"Point"}
}