{
  "type": "Feature",
  "properties": {
    "iso:country":"IT",
    "sg:address":"20031 Cesano Maderno",
    "sg:city":"Cesano Maderno",
    "sg:classifiers":[
        {
            "category":"Professional",
            "subcategory":"Engineering",
            "type":"Services"
        }
    ],
    "sg:phone":"+39 036 255 3989",
    "sg:postcode":"20031",
    "sg:province":"Milano",
    "sg:tags":[
        "equipment",
        "product",
        "industrial",
        "electronic"
    ],
    "wof:name":"Selco Srl",
    "wof:placetype":"venue"
},
  "geometry": {"coordinates":[9.148945,45.627731],"type":"Point"}
}