{
  "type": "Feature",
  "properties": {
    "iso:country":"IT",
    "sg:address":"10040 Val Della Torre",
    "sg:city":"Val della Torre",
    "sg:orig_category":"Articoli Funerari",
    "sg:phone":"+39 011 968 9582",
    "sg:postcode":"10040",
    "sg:province":"Torino",
    "wof:name":"Repole Marmi Di Repole Giuseppe",
    "wof:placetype":"venue"
},
  "geometry": {"coordinates":[7.488925,45.141972],"type":"Point"}
}