{
  "type": "Feature",
  "properties": {
    "iso:country":"IT",
    "sg:address":"35036 Montegrotto Terme",
    "sg:city":"Montegrotto Terme",
    "sg:orig_category":"Servizi Per Lo Sport E Il Tempo Libero. Servizi Al Turismo",
    "sg:phone":"+39 049 891 0189",
    "sg:postcode":"35036",
    "sg:province":"Padova",
    "wof:name":"Butterfly Arc (s.r.l.)",
    "wof:placetype":"venue"
},
  "geometry": {"coordinates":[11.793275,45.331268],"type":"Point"}
}