{
  "type": "Feature",
  "properties": {
    "addr:full":"23/a, Via Fossanuova 55016 Porcari Porcari Lucca 55016",
    "addr:housenumber":"23 / a",
    "addr:postcode":"55016;55016",
    "addr:street":"Via Fossanuova",
    "iso:country":"IT",
    "sg:address":"23/a, Via Fossanuova 55016 Porcari",
    "sg:city":"Porcari",
    "sg:classifiers":[
        {
            "category":"Manufacturing",
            "subcategory":"Metals",
            "type":"Manufacturing & Wholesale Goods"
        }
    ],
    "sg:phone":"+39 0583 298688",
    "sg:postcode":"55016",
    "sg:province":"Lucca",
    "sg:tags":[
        "metallurgy",
        "metalworking"
    ],
    "wof:name":"Nova Spa",
    "wof:placetype":"venue"
},
  "geometry": {"coordinates":[10.5079936981,43.8430137634],"type":"Point"}
}