{
  "type": "Feature",
  "properties": {
    "iso:country":"IT",
    "sg:address":"62012 Civitanova Marche",
    "sg:city":"Civitanova Marche",
    "sg:orig_category":"Giocattoli E Giochi - Vendita Al Dettaglio",
    "sg:phone":"+39 0733 813978",
    "sg:postcode":"62012",
    "sg:province":"Macerata",
    "wof:name":"Scoponi Ivo",
    "wof:placetype":"venue"
},
  "geometry": {"coordinates":[13.727027,43.30143],"type":"Point"}
}