{
  "type": "Feature",
  "properties": {
    "iso:country":"IT",
    "sg:address":"22072 Cermenate",
    "sg:city":"Cermenate",
    "sg:orig_category":"Edilizia - Materiali",
    "sg:phone":"+39 031 771538",
    "sg:postcode":"22072",
    "sg:province":"Como",
    "sg:website":"http://www.colmegnaedilizia.it",
    "wof:name":"Colmegna Srl",
    "wof:placetype":"venue"
},
  "geometry": {"coordinates":[9.078601,45.700119],"type":"Point"}
}