{
  "type": "Feature",
  "properties": {
    "iso:country":"IT",
    "sg:address":"00147 Roma",
    "sg:city":"Roma",
    "sg:orig_category":"Vetro: Prodotti E Lavorazioni",
    "sg:phone":"+39 06 513 6904",
    "sg:postcode":"00147",
    "sg:province":"Roma",
    "wof:name":"Katrin Srl",
    "wof:placetype":"venue"
},
  "geometry": {"coordinates":[12.495024,41.851837],"type":"Point"}
}