{
  "type": "Feature",
  "properties": {
    "iso:country":"IT",
    "sg:address":"09131 Cagliari",
    "sg:city":"Cagliari",
    "sg:orig_category":"Servizi Ausiliari Dei Mezzi Di Trasporto. Servizi Ausiliari Per Il Trasporto. Acqua, Luce, Gas E Societa' Di Esercizio Pubblico",
    "sg:postcode":"09131",
    "sg:province":"Cagliari",
    "wof:name":"Azienda Nazionale Autonoma Delle Strade - A.n.a.s.",
    "wof:placetype":"venue"
},
  "geometry": {"coordinates":[9.126141,39.233192],"type":"Point"}
}