{
  "type": "Feature",
  "properties": {
    "iso:country":"IT",
    "sg:address":"Via Brancadoro 63019 Sant'elpidio A Mare",
    "sg:classifiers":[
        {
            "category":"Professional",
            "subcategory":"Engineering",
            "type":"Services"
        }
    ],
    "sg:phone":"+39 0734 872004",
    "sg:postcode":"63019",
    "sg:province":"Ascoli Piceno",
    "sg:tags":[
        "machine",
        "-",
        "mechanical"
    ],
    "wof:name":"Talamonti F.lli Macchine",
    "wof:placetype":"venue"
},
  "geometry": {"coordinates":[13.66998,43.265865],"type":"Point"}
}