{
  "type": "Feature",
  "properties": {
    "iso:country":"IT",
    "sg:address":"93100 Caltanissetta",
    "sg:city":"Caltanissetta",
    "sg:classifiers":[
        {
            "category":"Communications",
            "subcategory":"Film & Video Production",
            "type":"Services"
        }
    ],
    "sg:phone":"+39 0934 564091",
    "sg:postcode":"93100",
    "sg:province":"Caltanissetta",
    "sg:tags":[
        "semi-finished",
        "materials",
        "metal"
    ],
    "wof:name":"Kal Tubi Di Re Alessandra & C. Sas",
    "wof:placetype":"venue"
},
  "geometry": {"coordinates":[14.0608463287,37.4765319824],"type":"Point"}
}