{
  "type": "Feature",
  "properties": {
    "iso:country":"IT",
    "sg:address":"21049 Tradate",
    "sg:city":"Tradate",
    "sg:orig_category":"Prodotti E Manufatti In Materie Plastiche",
    "sg:phone":"+39 0331 841620",
    "sg:postcode":"21049",
    "sg:province":"Varese",
    "wof:name":"Re - Flex (s.r.l.)",
    "wof:placetype":"venue"
},
  "geometry": {"coordinates":[8.9089736938,45.6916046143],"type":"Point"}
}