{
  "type": "Feature",
  "properties": {
    "addr:full":"10156 Torino Torino Torino 10156",
    "addr:postcode":"10156;10156",
    "iso:country":"IT",
    "sg:address":"10156 Torino",
    "sg:city":"Torino",
    "sg:orig_category":"Macchine, Impianti Ed Attrezzature Per Abbigliamento E Pelletterie",
    "sg:phone":"+39 011 274 1079",
    "sg:postcode":"10156",
    "sg:province":"Torino",
    "wof:name":"C.a.m.impianti Snc Di Nervi Cesare Angelo E C.",
    "wof:placetype":"venue"
},
  "geometry": {"coordinates":[7.745191,45.101185],"type":"Point"}
}