{
  "type": "Feature",
  "properties": {
    "addr:full":"48100 Ravenna Ravenna Ravenna 48100",
    "addr:housenumber":"48100",
    "addr:postcode":"48100",
    "iso:country":"IT",
    "sg:address":"48100 Ravenna",
    "sg:city":"Ravenna",
    "sg:orig_category":"Forniture Per Edilizia E Lavori Pubblici. Forniture Industriali Per Prevenzione, Controllo E Sicurezza",
    "sg:phone":"+39 0544 591282",
    "sg:postcode":"48100",
    "sg:province":"Ravenna",
    "wof:name":"Montanari Andrea",
    "wof:placetype":"venue"
},
  "geometry": {"coordinates":[12.2244577408,44.3803138733],"type":"Point"}
}