{
  "type": "Feature",
  "properties": {
    "addr:full":"20066 Melzo Melzo Milano 20066",
    "addr:postcode":"20066;20066",
    "iso:country":"IT",
    "sg:address":"20066 Melzo",
    "sg:city":"Melzo",
    "sg:orig_category":"Ospedali E Servizi Sanitari",
    "sg:phone":"+39 02 9571 0167",
    "sg:postcode":"20066",
    "sg:province":"Milano",
    "wof:name":"Allara Alessandro",
    "wof:placetype":"venue"
},
  "geometry": {"coordinates":[9.298115,45.492683],"type":"Point"}
}