{
  "type": "Feature",
  "properties": {
    "iso:country":"IT",
    "sg:address":"20094 Corsico",
    "sg:city":"Corsico",
    "sg:orig_category":"Apparecchiature Ed Attrezzature Meccaniche",
    "sg:phone":"+39 02 486 1111",
    "sg:postcode":"20094",
    "sg:province":"Milano",
    "sg:website":"http://www.enerpac.com",
    "wof:name":"Enerpac - Applied Power Italiana Spa",
    "wof:placetype":"venue"
},
  "geometry": {"coordinates":[9.091503,45.43425],"type":"Point"}
}