{
  "type": "Feature",
  "properties": {
    "addr:full":"7, Via Fra' Paolo Sarpi 50136 Firenze Firenze Firenze 50136",
    "addr:postcode":"50136;50136",
    "addr:street":"Via Fra ' Paolo Sarpi",
    "iso:country":"IT",
    "sg:address":"7, Via Fra' Paolo Sarpi 50136 Firenze",
    "sg:city":"Firenze",
    "sg:classifiers":[
        {
            "category":"Manufacturing",
            "subcategory":"Printing",
            "type":"Manufacturing & Wholesale Goods"
        }
    ],
    "sg:phone":"+39 055 623 6504",
    "sg:postcode":"50136",
    "sg:province":"Firenze",
    "sg:tags":[
        "publishing"
    ],
    "wof:name":"O.s. Organizzazioni Speciali Srl",
    "wof:placetype":"venue"
},
  "geometry": {"coordinates":[11.2772884369,43.7708625793],"type":"Point"}
}