{
  "type": "Feature",
  "properties": {
    "iso:country":"IT",
    "sg:address":"81041 Bellona",
    "sg:city":"Bellona",
    "sg:orig_category":"Abbigliamento Esterno, Maglierie E Pelliccerie. Calzature, Pelletterie E Pelli. Sport - Articoli E Forniture. Shopping",
    "sg:phone":"+39 0823 965334",
    "sg:postcode":"81041",
    "sg:province":"Caserta",
    "wof:name":"Spazio Danza",
    "wof:placetype":"venue"
},
  "geometry": {"coordinates":[14.233296,41.16111],"type":"Point"}
}