{
  "type": "Feature",
  "properties": {
    "iso:country":"IT",
    "sg:address":"24030 Carvico",
    "sg:city":"Carvico",
    "sg:classifiers":[
        {
            "category":"Shopping",
            "subcategory":"Crafts & Fabrics",
            "type":"Retail Goods"
        }
    ],
    "sg:phone":"+39 035 780111",
    "sg:postcode":"24030",
    "sg:province":"Bergamo",
    "sg:tags":[
        "material"
    ],
    "sg:website":"http://www.carvico.com",
    "wof:name":"Carvico Spa",
    "wof:placetype":"venue"
},
  "geometry": {"coordinates":[9.4977483749,45.6986694336],"type":"Point"}
}