{
  "type": "Feature",
  "properties": {
    "iso:country":"IT",
    "sg:address":"Via Piovola 131 50053 Empoli",
    "sg:city":"Empoli",
    "sg:classifiers":[
        {
            "category":"Shopping",
            "subcategory":"Clothing, Apparel, & Fashions",
            "type":"Retail Goods"
        }
    ],
    "sg:phone":"+39 0571 590821",
    "sg:postcode":"50053",
    "sg:province":"Firenze",
    "sg:tags":[
        "leather",
        "clothing"
    ],
    "wof:name":"Ivan Di Romagnoli Anna Maria & C. Snc",
    "wof:placetype":"venue"
},
  "geometry": {"coordinates":[10.977883,43.71133],"type":"Point"}
}