{
  "type": "Feature",
  "properties": {
    "addr:full":"5, Via Cellini Benvenuto 20094 Corsico Corsico Milano 20094",
    "addr:postcode":"20094;20094",
    "addr:street":"Via Cellini Benvenuto",
    "iso:country":"IT",
    "sg:address":"5, Via Cellini Benvenuto 20094 Corsico",
    "sg:city":"Corsico",
    "sg:classifiers":[
        {
            "category":"Manufacturing",
            "subcategory":"Printing",
            "type":"Manufacturing & Wholesale Goods"
        }
    ],
    "sg:phone":"+39 39024581912",
    "sg:postcode":"20094",
    "sg:province":"Milano",
    "sg:tags":[
        "publishing"
    ],
    "wof:name":"La Moderna Cartotecnica Srl",
    "wof:placetype":"venue"
},
  "geometry": {"coordinates":[9.0936250687,45.4352340698],"type":"Point"}
}