{
  "type": "Feature",
  "properties": {
    "addr:full":"53045 Montepulciano Montepulciano Siena 53045",
    "addr:postcode":"53045;53045",
    "iso:country":"IT",
    "sg:address":"53045 Montepulciano",
    "sg:city":"Montepulciano",
    "sg:orig_category":"Arredamenti - Vendita Al Dettaglio",
    "sg:phone":"+39 0578 738627",
    "sg:postcode":"53045",
    "sg:province":"Siena",
    "wof:name":"Falciani Arredamenti",
    "wof:placetype":"venue"
},
  "geometry": {"coordinates":[11.848361,43.136585],"type":"Point"}
}