{
  "type": "Feature",
  "properties": {
    "addr:full":"Via Cairoli 167; Treviso; 3100",
    "addr:housenumber":"167",
    "addr:postcode":"3100",
    "addr:street":"Via Cairoli",
    "iso:country":"IT",
    "sg:address":"Via Cairoli 167; Treviso; 3100",
    "sg:classifiers":[
        {
            "category":"Banks & Credit Unions",
            "subcategory":"Bank",
            "type":"Services"
        }
    ],
    "sg:phone":"+39 0422 421853",
    "wof:name":"Banca Popolare Friuladria",
    "wof:placetype":"venue"
},
  "geometry": {"coordinates":[12.24812,45.670135],"type":"Point"}
}