{
  "type": "Feature",
  "properties": {
    "iso:country":"IT",
    "sg:address":"Via Cairoli 167; Treviso; 3100",
    "sg:classifiers":[
        {
            "category":"Banks & Credit Unions",
            "subcategory":"Bank",
            "type":"Services"
        }
    ],
    "sg:phone":"+39 0422 421853",
    "wof:name":"Banca Popolare Friuladria",
    "wof:placetype":"venue"
},
  "geometry": {"coordinates":[12.24812,45.670135],"type":"Point"}
}