{
  "type": "Feature",
  "properties": {
    "addr:full":"90143 Palermo Palermo Palermo 90143",
    "addr:postcode":"90143;90143",
    "iso:country":"IT",
    "sg:address":"90143 Palermo",
    "sg:city":"Palermo",
    "sg:orig_category":"Impiantistica E Prodotti Tecnologici Per Edilizia. Elettrotecnica Professionale E Di Consumo. Telecomunicazioni E Telefonia, Impianti, Apparecchi E Servizi",
    "sg:phone":"+39 091 302940",
    "sg:postcode":"90143",
    "sg:province":"Palermo",
    "wof:name":"Pronto Intervento Casa Di Barcellona & C. Sas",
    "wof:placetype":"venue"
},
  "geometry": {"coordinates":[13.347951,38.138161],"type":"Point"}
}