{
  "type": "Feature",
  "properties": {
    "iso:country":"IT",
    "sg:address":"21013 Gallarate",
    "sg:city":"Gallarate",
    "sg:orig_category":"Lotto, Ricevitorie Concorsi E Giocate",
    "sg:phone":"+39 0331 784703",
    "sg:postcode":"21013",
    "sg:province":"Varese",
    "wof:name":"Caianiello Gioacchino",
    "wof:placetype":"venue"
},
  "geometry": {"coordinates":[8.62293,45.85965],"type":"Point"}
}