{
  "type": "Feature",
  "properties": {
    "iso:country":"IT",
    "sg:address":"Via Vittorio Veneto 45, 92020 Camastra, Ag",
    "sg:city":"Camastra",
    "sg:classifiers":[
        {
            "category":"Banks & Credit Unions",
            "subcategory":"Bank",
            "type":"Services"
        }
    ],
    "sg:postcode":"92020",
    "sg:province":"Agrigento",
    "wof:name":"Banca Di Credito Cooperativo 'unione' Di Camastra E Naro",
    "wof:placetype":"venue"
},
  "geometry": {"coordinates":[13.760085,37.196697],"type":"Point"}
}