{
  "type": "Feature",
  "properties": {
    "iso:country":"IT",
    "sg:address":"38065 Mori",
    "sg:city":"Mori",
    "sg:orig_category":"Forniture Per Edilizia E Lavori Pubblici",
    "sg:phone":"+39 0464 918142",
    "sg:postcode":"38065",
    "sg:province":"Trento",
    "sg:website":"http://web.tiscalinet.i/alpimarmo/",
    "wof:name":"Alpimarmo Srl",
    "wof:placetype":"venue"
},
  "geometry": {"coordinates":[10.9799671173,45.8527412415],"type":"Point"}
}