{
  "type": "Feature",
  "properties": {
    "addr:full":"03013 Ferentino Ferentino Frosinone 03013",
    "addr:postcode":"03013;03013",
    "iso:country":"IT",
    "sg:address":"03013 Ferentino",
    "sg:city":"Ferentino",
    "sg:orig_category":"Gelati - Produzione E Commercio",
    "sg:phone":"+39 0775 397326",
    "sg:postcode":"03013",
    "sg:province":"Frosinone",
    "wof:name":"Massari Luigi",
    "wof:placetype":"venue"
},
  "geometry": {"coordinates":[13.253358,41.692711],"type":"Point"}
}