{
  "type": "Feature",
  "properties": {
    "iso:country":"IT",
    "sg:address":"Via Paolo Maura 1; Mineo; 95044",
    "sg:city":"Mineo",
    "sg:classifiers":[
        {
            "category":"Banks & Credit Unions",
            "subcategory":"Bank",
            "type":"Services"
        }
    ],
    "sg:phone":"+39 0933 981012",
    "sg:postcode":"95044",
    "sg:province":"Catania",
    "wof:name":"Banco Di Sicilia Spa",
    "wof:placetype":"venue"
},
  "geometry": {"coordinates":[14.690487,37.264313],"type":"Point"}
}