{
  "type": "Feature",
  "properties": {
    "iso:country":"IT",
    "sg:address":"00155 Roma",
    "sg:city":"Roma",
    "sg:classifiers":[
        {
            "category":"Health Services",
            "subcategory":"Health Practitioner",
            "type":"Services"
        }
    ],
    "sg:phone":"+39 06 230 3588",
    "sg:postcode":"00155",
    "sg:province":"Roma",
    "sg:tags":[
        "medici"
    ],
    "wof:name":"Mariani Mario",
    "wof:placetype":"venue"
},
  "geometry": {"coordinates":[12.590966,41.882763],"type":"Point"}
}