{
  "type": "Feature",
  "properties": {
    "iso:country":"IT",
    "sg:address":"16, Via Adriatica 60018 Montemarciano",
    "sg:city":"Montemarciano",
    "sg:classifiers":[
        {
            "category":"Utilities",
            "subcategory":"Electric",
            "type":"Services"
        }
    ],
    "sg:phone":"+39 071 919 8145",
    "sg:postcode":"60018",
    "sg:province":"Ancona",
    "sg:tags":[
        "energy"
    ],
    "wof:name":"Elf Gas Fl.marina Di Montemarciano",
    "wof:placetype":"venue"
},
  "geometry": {"coordinates":[13.357131,43.594074],"type":"Point"}
}