{
  "type": "Feature",
  "properties": {
    "addr:full":"Via G. Oberdan 12 06012 Citta' Di Castello Perugia 06012",
    "addr:housenumber":"12",
    "addr:postcode":"06012;06012",
    "addr:street":"Via G. Oberdan",
    "iso:country":"IT",
    "sg:address":"Via G. Oberdan 12 06012 Citta' Di Castello",
    "sg:classifiers":[
        {
            "category":"Shopping",
            "subcategory":"Tobacco",
            "type":"Retail Goods"
        }
    ],
    "sg:phone":"+39 075 862 7911",
    "sg:postcode":"06012",
    "sg:province":"Perugia",
    "sg:website":"www.protab.it",
    "wof:name":"Fat - Fattoria Autonoma Tabacchi Scrl",
    "wof:placetype":"venue"
},
  "geometry": {"coordinates":[12.389172,43.110703],"type":"Point"}
}