{
  "type": "Feature",
  "properties": {
    "iso:country":"IT",
    "sg:address":"25060 Marcheno",
    "sg:city":"Marcheno",
    "sg:orig_category":"Sport - Articoli E Forniture",
    "sg:phone":"+39 030 861196",
    "sg:postcode":"25060",
    "sg:province":"Brescia",
    "wof:name":"Zanardini Luigi",
    "wof:placetype":"venue"
},
  "geometry": {"coordinates":[10.230003,45.723663],"type":"Point"}
}