{
  "type": "Feature",
  "properties": {
    "iso:country":"IT",
    "sg:address":"20121 Milano",
    "sg:city":"Milano",
    "sg:orig_category":"Non-classified Establishments",
    "sg:phone":"+39 02 655 1849",
    "sg:postcode":"20121",
    "sg:province":"Milano",
    "wof:name":"Giulietti Biancamaria",
    "wof:placetype":"venue"
},
  "geometry": {"coordinates":[9.185298,45.47855],"type":"Point"}
}