{
  "type": "Feature",
  "properties": {
    "addr:full":"20090 Assago Assago Milano 20090",
    "addr:postcode":"20090;20090",
    "addr:street":"Assago",
    "iso:country":"IT",
    "sg:address":"20090 Assago",
    "sg:city":"Assago",
    "sg:orig_category":"Pompe",
    "sg:phone":"+39 02 488 2614",
    "sg:postcode":"20090",
    "sg:province":"Milano",
    "wof:name":"T.b.f. Snc",
    "wof:placetype":"venue"
},
  "geometry": {"coordinates":[9.1160240173,45.4071617126],"type":"Point"}
}