{
  "type": "Feature",
  "properties": {
    "iso:country":"IT",
    "sg:address":"Via D. Alighieri 2 28075 Grignasco",
    "sg:city":"Grignasco",
    "sg:classifiers":[
        {
            "category":"Banks & Credit Unions",
            "subcategory":"Atm",
            "type":"Services"
        }
    ],
    "sg:phone":"+39 0163 4101",
    "sg:postcode":"28075",
    "sg:province":"Novara",
    "sg:tags":[
        "wool",
        "blend",
        "woollen",
        "yarn"
    ],
    "sg:website":"www.filgri.it",
    "wof:name":"Filatura Di Grignasco Spa",
    "wof:placetype":"venue"
},
  "geometry": {"coordinates":[8.34354,45.672989],"type":"Point"}
}