{
  "type": "Feature",
  "properties": {
    "addr:full":"10040 La Cassa La Cassa Torino 10040",
    "addr:housenumber":"10040",
    "addr:postcode":"10040",
    "addr:street":"La",
    "iso:country":"IT",
    "sg:address":"10040 La Cassa",
    "sg:city":"La Cassa",
    "sg:orig_category":"Materiali E Componenti Elettrotecnici",
    "sg:phone":"+39 011 984 2525",
    "sg:postcode":"10040",
    "sg:province":"Torino",
    "wof:name":"C.d.f. Due Di Centinaro E C. Snc",
    "wof:placetype":"venue"
},
  "geometry": {"coordinates":[7.502663,45.156391],"type":"Point"}
}