{
  "type": "Feature",
  "properties": {
    "iso:country":"IT",
    "sg:address":"93100 Caltanissetta",
    "sg:city":"Caltanissetta",
    "sg:orig_category":"Vetrate Artistiche",
    "sg:phone":"+39 0934 25698",
    "sg:postcode":"93100",
    "sg:province":"Caltanissetta",
    "wof:name":"Garozzo Industria Vetraria",
    "wof:placetype":"venue"
},
  "geometry": {"coordinates":[14.054168,37.467731],"type":"Point"}
}