{
  "type": "Feature",
  "properties": {
    "iso:country":"IT",
    "sg:address":"16039 Sestri Levante",
    "sg:city":"Sestri Levante",
    "sg:orig_category":"Automobili E Mezzi Di Trasporto",
    "sg:phone":"+39 0185 458344",
    "sg:postcode":"16039",
    "sg:province":"Genova",
    "wof:name":"Berto Edoardo",
    "wof:placetype":"venue"
},
  "geometry": {"coordinates":[9.411387,44.27552],"type":"Point"}
}