{
  "type": "Feature",
  "properties": {
    "iso:country":"IT",
    "sg:address":"Via Meucci 7 20019 Settimo Milanese",
    "sg:city":"Settimo Milanese",
    "sg:classifiers":[
        {
            "category":"Bars & Pubs",
            "subcategory":"Sports Bar",
            "type":"Food & Drink"
        }
    ],
    "sg:phone":"+39 02 4892 0048",
    "sg:postcode":"20019",
    "sg:province":"Milano",
    "sg:tags":[
        "dy",
        "forging"
    ],
    "wof:name":"Amp Snc Di Giancarlo Pini & C",
    "wof:placetype":"venue"
},
  "geometry": {"coordinates":[9.0686388016,45.4672164917],"type":"Point"}
}