{
  "type": "Feature",
  "properties": {
    "iso:country":"IT",
    "sg:address":"91025 Marsala",
    "sg:city":"Marsala",
    "sg:orig_category":"Tessuti E Stoffe. Tessuti Arredamento, Tende E Tappeti. Shopping",
    "sg:phone":"+39 0923 982230",
    "sg:postcode":"91025",
    "sg:province":"Trapani",
    "wof:name":"Parrinello Rosa Maria",
    "wof:placetype":"venue"
},
  "geometry": {"coordinates":[12.447227,37.805096],"type":"Point"}
}