{
  "type": "Feature",
  "properties": {
    "addr:full":"7, Corso Francia 12084 Mondovi' Cuneo 12084",
    "addr:postcode":"12084;12084",
    "addr:street":"Corso Francia",
    "iso:country":"IT",
    "sg:address":"7, Corso Francia 12084 Mondovi'",
    "sg:classifiers":[
        {
            "category":"Manufacturing",
            "subcategory":"Metals",
            "type":"Manufacturing & Wholesale Goods"
        }
    ],
    "sg:phone":"+39 39017442405",
    "sg:postcode":"12084",
    "sg:province":"Cuneo",
    "sg:tags":[
        "metallurgy",
        "metalworking"
    ],
    "wof:name":"Fim Fonderie Industriale Mondovi S.r.l.",
    "wof:placetype":"venue"
},
  "geometry": {"coordinates":[7.7909135818,44.4759216309],"type":"Point"}
}