{
  "type": "Feature",
  "properties": {
    "addr:full":"35020 Albignasego Albignasego Padova 35020",
    "addr:postcode":"35020;35020",
    "iso:country":"IT",
    "sg:address":"35020 Albignasego",
    "sg:city":"Albignasego",
    "sg:orig_category":"Macchine, Impianti Ed Attrezzature Industria Chimica",
    "sg:phone":"+39 049 862 5933",
    "sg:postcode":"35020",
    "sg:province":"Padova",
    "wof:name":"Granziero Srl",
    "wof:placetype":"venue"
},
  "geometry": {"coordinates":[11.831532,45.344246],"type":"Point"}
}