{
  "type": "Feature",
  "properties": {
    "iso:country":"IT",
    "sg:address":"64021 Giulianova",
    "sg:city":"Giulianova",
    "sg:orig_category":"Manufacturers: Prefabbricati. Impianti E Attrezzature Per Lo Sport E Il Tempo Libero",
    "sg:phone":"+39 085 800 2326",
    "sg:postcode":"64021",
    "sg:province":"Teramo",
    "wof:name":"Tentarelli Nicola",
    "wof:placetype":"venue"
},
  "geometry": {"coordinates":[13.926,42.736652],"type":"Point"}
}