{
  "type": "Feature",
  "properties": {
    "addr:full":"20159 Milano Milano Milano 20159",
    "addr:postcode":"20159;20159",
    "iso:country":"IT",
    "sg:address":"20159 Milano",
    "sg:city":"Milano",
    "sg:orig_category":"Utensili Meccanici E Materiali",
    "sg:postcode":"20159",
    "sg:province":"Milano",
    "wof:name":"Beta Utensili (s.r.l.)",
    "wof:placetype":"venue"
},
  "geometry": {"coordinates":[9.187316,45.488415],"type":"Point"}
}