{
  "type": "Feature",
  "properties": {
    "addr:full":"Viale Gramsci 9; S. Croce Sull'arno; 56029 Pisa 56029",
    "addr:housenumber":"9",
    "addr:postcode":"56029;56029",
    "addr:street":"Viale Gramsci",
    "iso:country":"IT",
    "sg:address":"Viale Gramsci 9; S. Croce Sull'arno; 56029",
    "sg:classifiers":[
        {
            "category":"Banks & Credit Unions",
            "subcategory":"Bank",
            "type":"Services"
        }
    ],
    "sg:phone":"+39 0571 34114",
    "sg:postcode":"56029",
    "sg:province":"Pisa",
    "wof:name":"Cassa Di Risparmio Di Pisa Spa",
    "wof:placetype":"venue"
},
  "geometry": {"coordinates":[10.78397,43.71035],"type":"Point"}
}