{
  "type": "Feature",
  "properties": {
    "iso:country":"IT",
    "sg:address":"Via Abetone Brennero 177/b 46025 Poggio Rusco",
    "sg:city":"Poggio Rusco",
    "sg:classifiers":[
        {
            "category":"Organizations",
            "subcategory":"Community Association",
            "type":"Services"
        }
    ],
    "sg:phone":"+39 0386 522011",
    "sg:postcode":"46025",
    "sg:province":"Mantova",
    "sg:tags":[
        "control",
        "automatic"
    ],
    "sg:website":"www.gibidi.com",
    "wof:name":"Gi.bi.di. Continental S.p.a.",
    "wof:placetype":"venue"
},
  "geometry": {"coordinates":[10.797698,45.160366],"type":"Point"}
}