{
  "type": "Feature",
  "properties": {
    "addr:full":"83045 Calitri Calitri Avellino 83045",
    "addr:postcode":"83045;83045",
    "iso:country":"IT",
    "sg:address":"83045 Calitri",
    "sg:city":"Calitri",
    "sg:orig_category":"Servizi E Lavori Per Edilizia E Lavori Pubblici. Acqua, Luce, Gas E Societa' Di Esercizio Pubblico",
    "sg:phone":"+39 0827 30212",
    "sg:postcode":"83045",
    "sg:province":"Avellino",
    "wof:name":"Acquedotto Pugliese Spa",
    "wof:placetype":"venue"
},
  "geometry": {"coordinates":[15.432268,40.900131],"type":"Point"}
}