{
  "type": "Feature",
  "properties": {
    "iso:country":"IT",
    "sg:address":"20137 Milano",
    "sg:city":"Milano",
    "sg:orig_category":"Informatica - Consulenza E Servizi. Editoria",
    "sg:phone":"+39 02 5518 7485",
    "sg:postcode":"20137",
    "sg:province":"Milano",
    "sg:website":"http://www.makelab.it",
    "wof:name":"Makelab Srl",
    "wof:placetype":"venue"
},
  "geometry": {"coordinates":[9.22368,45.452866],"type":"Point"}
}