{
  "type": "Feature",
  "properties": {
    "addr:full":"10070 San Francesco Al Campo San Francesco al Campo Torino 10070",
    "addr:housenumber":"10070",
    "addr:postcode":"10070",
    "addr:street":"San Francesco Al Campo",
    "iso:country":"IT",
    "sg:address":"10070 San Francesco Al Campo",
    "sg:city":"San Francesco al Campo",
    "sg:orig_category":"Servizi E Lavori Industria Della Gomma",
    "sg:phone":"+39 011 927 6322",
    "sg:postcode":"10070",
    "sg:province":"Torino",
    "wof:name":"Zucco Monaco Giuditta",
    "wof:placetype":"venue"
},
  "geometry": {"coordinates":[7.648616,45.174999],"type":"Point"}
}