{
  "type": "Feature",
  "properties": {
    "iso:country":"IT",
    "sg:address":"449, Via Pistoiese 59100 Prato",
    "sg:city":"Prato",
    "sg:classifiers":[
        {
            "category":"Shopping",
            "subcategory":"Clothing, Apparel, & Fashions",
            "type":"Retail Goods"
        }
    ],
    "sg:phone":"+39 0574 662612",
    "sg:postcode":"59100",
    "sg:province":"Prato",
    "sg:tags":[
        "clothes"
    ],
    "wof:name":"Cheress S.r.l.",
    "wof:placetype":"venue"
},
  "geometry": {"coordinates":[11.060285,43.876511],"type":"Point"}
}