{
  "type": "Feature",
  "properties": {
    "addr:full":"Via Parmense, 19; Rimini; 47900 Rimini Rimini 47900",
    "addr:housenumber":"19",
    "addr:postcode":"47900;47900",
    "addr:street":"Via Parmense",
    "iso:country":"IT",
    "sg:address":"Via Parmense, 19; Rimini; 47900",
    "sg:city":"Rimini",
    "sg:classifiers":[
        {
            "category":"Travel",
            "subcategory":"Travel Agent",
            "type":"Entertainment"
        }
    ],
    "sg:phone":"+39 390 541 3632",
    "sg:postcode":"47900",
    "sg:province":"Rimini",
    "sg:website":"caravantours.it",
    "wof:name":"Caravantours",
    "wof:placetype":"venue"
},
  "geometry": {"coordinates":[12.558433,44.055862],"type":"Point"}
}