{
  "type": "Feature",
  "properties": {
    "iso:country":"IT",
    "sg:address":"Via Cuneo 31 10042 Nichelino",
    "sg:city":"Nichelino",
    "sg:classifiers":[
        {
            "category":"Professional",
            "subcategory":"Testing Lab",
            "type":"Services"
        }
    ],
    "sg:phone":"+39 011 605 1260",
    "sg:postcode":"10042",
    "sg:province":"Torino",
    "sg:tags":[
        "equipment",
        "electronics"
    ],
    "wof:name":"M.l.t.a. Srl",
    "wof:placetype":"venue"
},
  "geometry": {"coordinates":[7.660626,45.004528],"type":"Point"}
}