{
  "type": "Feature",
  "properties": {
    "iso:country":"IT",
    "sg:address":"20129 Milano",
    "sg:city":"Milano",
    "sg:orig_category":"Macchine, Impianti Ed Attrezzature Industria Chimica",
    "sg:phone":"+39 02 236 7750",
    "sg:postcode":"20129",
    "sg:province":"Milano",
    "wof:name":"Proge (s.r.l.)",
    "wof:placetype":"venue"
},
  "geometry": {"coordinates":[9.223047,45.475937],"type":"Point"}
}