{
  "type": "Feature",
  "properties": {
    "iso:country":"IT",
    "sg:address":"50132 Firenze",
    "sg:city":"Firenze",
    "sg:orig_category":"Manufacturers: Prefabbricati",
    "sg:phone":"+39 055 582608",
    "sg:postcode":"50132",
    "sg:province":"Firenze",
    "wof:name":"Cimitero Evangelico Porta A Pinti",
    "wof:placetype":"venue"
},
  "geometry": {"coordinates":[11.2708015442,43.779083252],"type":"Point"}
}