{
  "type": "Feature",
  "properties": {
    "addr:full":"95128 Catania Catania Catania 95128",
    "addr:postcode":"95128;95128",
    "iso:country":"IT",
    "sg:address":"95128 Catania",
    "sg:city":"Catania",
    "sg:orig_category":"Impianti, Attrezzature E Forniture Sanitarie Ed Ospedaliere",
    "sg:phone":"+39 095 435362",
    "sg:postcode":"95128",
    "sg:province":"Catania",
    "wof:name":"Micromed Srl",
    "wof:placetype":"venue"
},
  "geometry": {"coordinates":[15.092015,37.5158],"type":"Point"}
}