{
  "type": "Feature",
  "properties": {
    "iso:country":"IT",
    "sg:address":"41057 Spilamberto",
    "sg:city":"Spilamberto",
    "sg:orig_category":"Luna Park E Spettacoli Viaggianti - Attrezzature",
    "sg:phone":"+39 059 784017",
    "sg:postcode":"41057",
    "sg:province":"Modena",
    "sg:website":"http://www.bctoday.it/elp",
    "wof:name":"Emiliana Luna Park Srl",
    "wof:placetype":"venue"
},
  "geometry": {"coordinates":[11.020013,44.519756],"type":"Point"}
}