{
  "type": "Feature",
  "properties": {
    "addr:full":"00179 Roma Roma Roma 00179",
    "addr:postcode":"00179;00179",
    "iso:country":"IT",
    "sg:address":"00179 Roma",
    "sg:city":"Roma",
    "sg:orig_category":"Informatica - Consulenza E Servizi. Pubblicita', Marketing E Comunicazione",
    "sg:phone":"+39 06 780 4711",
    "sg:postcode":"00179",
    "sg:province":"Roma",
    "sg:website":"http://www.tiscalinet.it/elettrosistemi/",
    "wof:name":"Elettrosistemi Di Gusmeroli Franco & C. Snc",
    "wof:placetype":"venue"
},
  "geometry": {"coordinates":[12.525384,41.870335],"type":"Point"}
}