{
  "type": "Feature",
  "properties": {
    "addr:full":"00198 Roma Roma Roma 00198",
    "addr:postcode":"00198;00198",
    "iso:country":"IT",
    "sg:address":"00198 Roma",
    "sg:city":"Roma",
    "sg:orig_category":"Forniture Per Agricoltura E Zootecnia",
    "sg:phone":"+39 06 8535 7826",
    "sg:postcode":"00198",
    "sg:province":"Roma",
    "wof:name":"Assalzoo Servizi Srl",
    "wof:placetype":"venue"
},
  "geometry": {"coordinates":[12.4975910187,41.9209136963],"type":"Point"}
}