{
  "type": "Feature",
  "properties": {
    "iso:country":"IT",
    "sg:address":"Vocabolo Fiore 31 05100 Terni",
    "sg:city":"Terni",
    "sg:classifiers":[
        {
            "category":"Social Services",
            "subcategory":"Retirement Home",
            "type":"Services"
        }
    ],
    "sg:phone":"+39 0744 406603",
    "sg:postcode":"05100",
    "sg:province":"Terni",
    "sg:tags":[
        "fixture",
        "street",
        "lighting"
    ],
    "wof:name":"Fonderie Bernardini Di Bernardini N. & C. Snc",
    "wof:placetype":"venue"
},
  "geometry": {"coordinates":[12.625197,42.572308],"type":"Point"}
}