{
  "type": "Feature",
  "properties": {
    "iso:country":"IT",
    "sg:address":"64028 Silvi",
    "sg:city":"Silvi",
    "sg:orig_category":"Servizi E Lavori Per Abbigliamento E Pelletterie. Scuole E Servizi Scolastici. Ricerca, Selezione E Formazione Del Personale",
    "sg:phone":"+39 085 935 4309",
    "sg:postcode":"64028",
    "sg:province":"Teramo",
    "wof:name":"Milano Moda 1 Luddi Eleonora",
    "wof:placetype":"venue"
},
  "geometry": {"coordinates":[13.717282,42.66333],"type":"Point"}
}