{
  "type": "Feature",
  "properties": {
    "addr:full":"27039 Sannazzaro De'burgondi Pavia 27039",
    "addr:postcode":"27039;27039",
    "addr:street":"Sannazzaro De'Burgondi",
    "iso:country":"IT",
    "sg:address":"27039 Sannazzaro De'burgondi",
    "sg:orig_category":"Petroli, Gas E Combustibili. Servizi E Lavori Industria Chimica",
    "sg:phone":"+39 0382 998409",
    "sg:postcode":"27039",
    "sg:province":"Pavia",
    "wof:name":"Officine Tecniche De Pasquale S.r.l.",
    "wof:placetype":"venue"
},
  "geometry": {"coordinates":[13.3210573196,45.9774513245],"type":"Point"}
}