{
  "type": "Feature",
  "properties": {
    "iso:country":"IT",
    "sg:address":"35028 Piove Di Sacco",
    "sg:city":"Piove di Sacco",
    "sg:orig_category":"Automobili E Mezzi Di Trasporto",
    "sg:phone":"+39 049 970 2900",
    "sg:postcode":"35028",
    "sg:province":"Padova",
    "wof:name":"Pavan Srl",
    "wof:placetype":"venue"
},
  "geometry": {"coordinates":[11.656878,44.977913],"type":"Point"}
}