{
  "type": "Feature",
  "properties": {
    "iso:country":"IT",
    "sg:address":"15100 Alessandria",
    "sg:city":"Alessandria",
    "sg:orig_category":"Fotolito",
    "sg:phone":"+39 0131 222686",
    "sg:postcode":"15100",
    "sg:province":"Alessandria",
    "wof:name":"Agostudio Di Roberto Ricchini & C. Snc",
    "wof:placetype":"venue"
},
  "geometry": {"coordinates":[8.6123867035,44.9159431458],"type":"Point"}
}