{
  "type": "Feature",
  "properties": {
    "iso:country":"IT",
    "sg:address":"70031 Andria",
    "sg:city":"Andria",
    "sg:orig_category":"Abbigliamento Esterno, Maglierie E Pelliccerie. Shopping",
    "sg:phone":"+39 0883 557016",
    "sg:postcode":"70031",
    "sg:province":"Bari",
    "wof:name":"Confezioni Zeta Due Di Zingaro Vincenzo & C. Sas",
    "wof:placetype":"venue"
},
  "geometry": {"coordinates":[16.303761,41.238174],"type":"Point"}
}