{
  "type": "Feature",
  "properties": {
    "iso:country":"IT",
    "sg:address":"Via Salato 40 10080 Busano",
    "sg:city":"Busano",
    "sg:classifiers":[
        {
            "category":"Autos & Motor Vehicles",
            "subcategory":"Auto Supplies",
            "type":"Retail Goods"
        }
    ],
    "sg:phone":"+39 0124 48072",
    "sg:postcode":"10080",
    "sg:province":"Torino",
    "sg:tags":[
        "automobile",
        "part",
        "spare"
    ],
    "wof:name":"B.m.a. - Srl",
    "wof:placetype":"venue"
},
  "geometry": {"coordinates":[7.655842,45.33028],"type":"Point"}
}