{
  "type": "Feature",
  "properties": {
    "iso:country":"IT",
    "sg:address":"40033 Casalecchio Di Reno",
    "sg:city":"Casalecchio di Reno",
    "sg:orig_category":"Apparecchiature E Sistemi Per Imballaggio E Confezionamento",
    "sg:phone":"+39 051 575579",
    "sg:postcode":"40033",
    "sg:province":"Bologna",
    "wof:name":"Preci Srl",
    "wof:placetype":"venue"
},
  "geometry": {"coordinates":[11.260542,44.487148],"type":"Point"}
}