{
  "type": "Feature",
  "properties": {
    "iso:country":"IT",
    "sg:address":"63015 Monte Urano",
    "sg:city":"Monte Urano",
    "sg:orig_category":"Calzaturifici E Calzolai - Forniture",
    "sg:phone":"+39 0734 841372",
    "sg:postcode":"63015",
    "sg:province":"Ascoli Piceno",
    "sg:website":"http://www.felicioni.it",
    "wof:name":"Scatolificio Felicioni Costantino",
    "wof:placetype":"venue"
},
  "geometry": {"coordinates":[13.644351,42.84531],"type":"Point"}
}