{
  "type": "Feature",
  "properties": {
    "addr:full":"24050 Orio Al Serio Orio al Serio Bergamo 24050",
    "addr:postcode":"24050;24050",
    "iso:country":"IT",
    "sg:address":"24050 Orio Al Serio",
    "sg:city":"Orio al Serio",
    "sg:orig_category":"Elettrovalvole",
    "sg:phone":"+39 035 531298",
    "sg:postcode":"24050",
    "sg:province":"Bergamo",
    "wof:name":"M & M International Srl",
    "wof:placetype":"venue"
},
  "geometry": {"coordinates":[9.684618,45.664501],"type":"Point"}
}