{
  "type": "Feature",
  "properties": {
    "iso:country":"IT",
    "sg:address":"Piazza Grifoni 12, 56027 San Miniato, Pi",
    "sg:classifiers":[
        {
            "category":"Banks & Credit Unions",
            "subcategory":"Bank",
            "type":"Services"
        }
    ],
    "wof:name":"Finanziaria Cassa Di Risparmio Di San Miniato Spa",
    "wof:placetype":"venue"
},
  "geometry": {"coordinates":[10.84738,43.678509],"type":"Point"}
}