{
  "type": "Feature",
  "properties": {
    "addr:full":"44042 Dodici Morelli Ferrara 44042",
    "addr:postcode":"44042;44042",
    "iso:country":"IT",
    "sg:address":"44042 Dodici Morelli",
    "sg:orig_category":"Prodotti Di Base E Forniture Per Industria Alimentare E Bevande",
    "sg:phone":"+39 051 684 1022",
    "sg:postcode":"44042",
    "sg:province":"Ferrara",
    "wof:name":"Alberghini Angelo",
    "wof:placetype":"venue"
},
  "geometry": {"coordinates":[11.292640686,44.7916297913],"type":"Point"}
}