{
  "type": "Feature",
  "properties": {
    "iso:country":"IT",
    "sg:address":"10, Via Stella Maris 09170 Oristano",
    "sg:city":"Oristano",
    "sg:classifiers":[
        {
            "category":"Wholesale",
            "subcategory":"Drugs",
            "type":"Manufacturing & Wholesale Goods"
        }
    ],
    "sg:phone":"+39 39078322024",
    "sg:postcode":"09170",
    "sg:province":"Oristano",
    "sg:tags":[
        "chemical",
        "pharmaceutical"
    ],
    "wof:name":"Sarbit - Sarda Bitumi (s.p.a.)",
    "wof:placetype":"venue"
},
  "geometry": {"coordinates":[8.520804,39.90807],"type":"Point"}
}