{
  "type": "Feature",
  "properties": {
    "addr:full":"52020 Laterina Laterina Arezzo 52020",
    "addr:postcode":"52020;52020",
    "iso:country":"IT",
    "sg:address":"52020 Laterina",
    "sg:city":"Laterina",
    "sg:orig_category":"Macchine, Impianti Ed Attrezzature Industria Chimica",
    "sg:phone":"+39 0575 894760",
    "sg:postcode":"52020",
    "sg:province":"Arezzo",
    "wof:name":"Ayr S.r.l.",
    "wof:placetype":"venue"
},
  "geometry": {"coordinates":[11.711169,43.503468],"type":"Point"}
}