{
  "type": "Feature",
  "properties": {
    "addr:full":"Via Fratelli Vianello Moro 3/a; Monticello Conte Otto; 36010 Monticello Conte Otto Vicenza 36010",
    "addr:housenumber":"3 / a",
    "addr:postcode":"36010;36010",
    "addr:street":"Via Fratelli Vianello Moro",
    "iso:country":"IT",
    "sg:address":"Via Fratelli Vianello Moro 3/a; Monticello Conte Otto; 36010",
    "sg:city":"Monticello Conte Otto",
    "sg:classifiers":[
        {
            "category":"Banks & Credit Unions",
            "subcategory":"Bank",
            "type":"Services"
        }
    ],
    "sg:phone":"+39 0444 945660",
    "sg:postcode":"36010",
    "sg:province":"Vicenza",
    "wof:name":"Cariverona Banca Spa",
    "wof:placetype":"venue"
},
  "geometry": {"coordinates":[11.585255,45.595695],"type":"Point"}
}