{
  "type": "Feature",
  "properties": {
    "addr:full":"Km. 26.500, Via Laurentina 00040 Pomezia Pomezia Roma 00040",
    "addr:postcode":"00040;roma 00040",
    "addr:street":"Km. 26.500 Via Laurentina",
    "iso:country":"IT",
    "sg:address":"Km. 26.500, Via Laurentina 00040 Pomezia",
    "sg:city":"Pomezia",
    "sg:classifiers":[
        {
            "category":"Personal",
            "subcategory":"Shoe Repair & Shine",
            "type":"Services"
        }
    ],
    "sg:phone":"+39 39069147193",
    "sg:postcode":"00040",
    "sg:province":"Roma",
    "sg:tags":[
        "leather"
    ],
    "wof:name":"Moretti Group Int.spa",
    "wof:placetype":"venue"
},
  "geometry": {"coordinates":[12.482325,41.895466],"type":"Point"}
}