{
  "type": "Feature",
  "properties": {
    "iso:country":"IT",
    "sg:address":"59016 Poggio A Caiano",
    "sg:city":"Poggio a Caiano",
    "sg:orig_category":"Abbigliamento Esterno, Maglierie E Pelliccerie",
    "sg:phone":"+39 055 879 8527",
    "sg:postcode":"59016",
    "sg:province":"Prato",
    "wof:name":"Tecnopull",
    "wof:placetype":"venue"
},
  "geometry": {"coordinates":[11.061623,43.810005],"type":"Point"}
}