{
  "type": "Feature",
  "properties": {
    "addr:full":"50056 Montelupo Fiorentino Montelupo Fiorentino Firenze 50056",
    "addr:postcode":"50056;50056",
    "addr:street":"Fiorentino",
    "iso:country":"IT",
    "sg:address":"50056 Montelupo Fiorentino",
    "sg:city":"Montelupo Fiorentino",
    "sg:orig_category":"Non-classified Establishments",
    "sg:phone":"+39 0571 541053",
    "sg:postcode":"50056",
    "sg:province":"Firenze",
    "sg:website":"http://www.bitossifilippo.com",
    "wof:name":"Bitossi Filippo & Figli Srl",
    "wof:placetype":"venue"
},
  "geometry": {"coordinates":[11.001816,43.728333],"type":"Point"}
}