{
  "type": "Feature",
  "properties": {
    "iso:country":"IT",
    "sg:address":"20122 Milano",
    "sg:city":"Milano",
    "sg:orig_category":"Articoli Da Regalo. Arte Ed Artigianato Artistico. Shopping. Regalistica Aziendale",
    "sg:phone":"+39 02 7600 0908",
    "sg:postcode":"20122",
    "sg:province":"Milano",
    "wof:name":"Il Timpano",
    "wof:placetype":"venue"
},
  "geometry": {"coordinates":[9.196806,45.459793],"type":"Point"}
}