{
  "type": "Feature",
  "properties": {
    "addr:full":"10070 Robassomero Robassomero Torino 10070",
    "addr:housenumber":"10070",
    "addr:postcode":"10070",
    "addr:street":"Robassomero Robassomero",
    "iso:country":"IT",
    "sg:address":"10070 Robassomero",
    "sg:city":"Robassomero",
    "sg:orig_category":"Impiantistica E Prodotti Tecnologici Per Edilizia. Telecomunicazioni E Telefonia, Impianti, Apparecchi E Servizi",
    "sg:phone":"+39 011 923 5999",
    "sg:postcode":"10070",
    "sg:province":"Torino",
    "sg:website":"http://www.btgspa.it",
    "wof:name":"Btg Spa",
    "wof:placetype":"venue"
},
  "geometry": {"coordinates":[7.684883,45.066113],"type":"Point"}
}