{
  "type": "Feature",
  "properties": {
    "iso:country":"IT",
    "sg:address":"01014 Montalto Di Castro",
    "sg:city":"Montalto di Castro",
    "sg:orig_category":"Scuole E Servizi Scolastici. Servizi Per Lo Sport E Il Tempo Libero",
    "sg:phone":"+39 0766 830779",
    "sg:postcode":"01014",
    "sg:province":"Viterbo",
    "wof:name":"Associazione Circolo Nautico Mal Di Mare",
    "wof:placetype":"venue"
},
  "geometry": {"coordinates":[11.593027,42.372658],"type":"Point"}
}