{
  "type": "Feature",
  "properties": {
    "addr:full":"20092 Cinisello Balsamo Cinisello Balsamo Milano 20092",
    "addr:postcode":"20092;20092",
    "iso:country":"IT",
    "sg:address":"20092 Cinisello Balsamo",
    "sg:city":"Cinisello Balsamo",
    "sg:orig_category":"Aspiratori",
    "sg:phone":"+39 02 6604 0103",
    "sg:postcode":"20092",
    "sg:province":"Milano",
    "wof:name":"Dipielle Di P. Durazzi & C. Sas",
    "wof:placetype":"venue"
},
  "geometry": {"coordinates":[9.236194,45.557617],"type":"Point"}
}