{
  "type": "Feature",
  "properties": {
    "addr:full":"00161 Roma Roma Roma 00161",
    "addr:postcode":"00161;00161",
    "iso:country":"IT",
    "sg:address":"00161 Roma",
    "sg:city":"Roma",
    "sg:orig_category":"Medici. Assicurazioni E Servizi Assicurativi. Avvocati, Notai E Servizi Legali. Professionisti - Studi E Servizi Ed Associazioni Di Interesse Aziendale",
    "sg:phone":"+39 06 4429 2082",
    "sg:postcode":"00161",
    "sg:province":"Roma",
    "wof:name":"Mezzelani Stefano",
    "wof:placetype":"venue"
},
  "geometry": {"coordinates":[12.5196361542,41.9109191895],"type":"Point"}
}