{
  "type": "Feature",
  "properties": {
    "addr:full":"37015 Domegliara Domegliara Verona 37015",
    "addr:postcode":"37015;37015",
    "addr:street":"Domegliara",
    "iso:country":"IT",
    "sg:address":"37015 Domegliara",
    "sg:city":"Domegliara",
    "sg:orig_category":"Servizi Al Turismo. Trasporto Pubblico E Privato. Acqua, Luce, Gas E Societa' Di Esercizio Pubblico",
    "sg:phone":"+39 045 686 1053",
    "sg:postcode":"37015",
    "sg:province":"Verona",
    "wof:name":"Azienda Provinciale Trasporti",
    "wof:placetype":"venue"
},
  "geometry": {"coordinates":[10.824814,45.51828],"type":"Point"}
}