{
  "type": "Feature",
  "properties": {
    "addr:full":"80142 Napoli Napoli Napoli 80142",
    "addr:housenumber":"80142",
    "addr:postcode":"80142",
    "iso:country":"IT",
    "sg:address":"80142 Napoli",
    "sg:city":"Napoli",
    "sg:classifiers":[
        {
            "category":"Sports & Exercise",
            "subcategory":"Sports Center",
            "type":"Entertainment"
        }
    ],
    "sg:phone":"+39 081 553 8278",
    "sg:postcode":"80142",
    "sg:province":"Napoli",
    "sg:tags":[
        "knitwear",
        "furs",
        "clothing",
        "article",
        "supply"
    ],
    "wof:name":"American Gear Inc. - Fashion & Cosmetics",
    "wof:placetype":"venue"
},
  "geometry": {"coordinates":[14.31223,40.914867],"type":"Point"}
}