{
  "type": "Feature",
  "properties": {
    "iso:country":"IT",
    "sg:address":"Via Montecastello 40 13037 Serravalle Sesia",
    "sg:city":"Serravalle Sesia",
    "sg:classifiers":[
        {
            "category":"Home & Garden",
            "subcategory":"Hardware",
            "type":"Retail Goods"
        }
    ],
    "sg:phone":"+39 0163 450497",
    "sg:postcode":"13037",
    "sg:province":"Vercelli",
    "sg:tags":[
        "small",
        "ironware",
        "item"
    ],
    "sg:website":"www.bertisalina.it",
    "wof:name":"Berti & Salina Sas Di Berti Giovanni & C.",
    "wof:placetype":"venue"
},
  "geometry": {"coordinates":[8.291463,45.69389],"type":"Point"}
}