{
  "type": "Feature",
  "properties": {
    "addr:full":"00195 Roma Roma Roma 00195",
    "addr:postcode":"00195;00195",
    "iso:country":"IT",
    "sg:address":"00195 Roma",
    "sg:city":"Roma",
    "sg:classifiers":[
        {
            "category":"Government",
            "subcategory":"Office",
            "type":"Public Place"
        }
    ],
    "sg:phone":"+39 06 321 6950",
    "sg:postcode":"00195",
    "sg:province":"Roma",
    "sg:tags":[
        "e",
        "lo",
        "tempo",
        "libero",
        "per",
        "spettacolo",
        "servizi",
        "culturali",
        "sport",
        "il"
    ],
    "wof:name":"Rossodisera Edizioni Musicali",
    "wof:placetype":"venue"
},
  "geometry": {"coordinates":[12.462487,41.919491],"type":"Point"}
}