{
  "type": "Feature",
  "properties": {
    "iso:country":"IT",
    "sg:address":"30038 Spinea",
    "sg:city":"Spinea",
    "sg:orig_category":"Ospedali E Servizi Sanitari. Servizi Sociali. Associazioni Ed Organismi Di Interesse Pubblico",
    "sg:phone":"+39 041 999777",
    "sg:postcode":"30038",
    "sg:province":"Venezia",
    "wof:name":"Centro Di Ascolto 'attilio Scocco' Spinea",
    "wof:placetype":"venue"
},
  "geometry": {"coordinates":[12.167483,45.490128],"type":"Point"}
}