{
  "type": "Feature",
  "properties": {
    "addr:full":"4, Via Don E.cingolani 62010 Montecassiano Montecassiano Macerata 62010",
    "addr:postcode":"62010;62010",
    "addr:street":"Via Don E.Cingolani",
    "iso:country":"IT",
    "sg:address":"4, Via Don E.cingolani 62010 Montecassiano",
    "sg:city":"Montecassiano",
    "sg:classifiers":[
        {
            "category":"Home & Garden",
            "subcategory":"Home Furnishings",
            "type":"Retail Goods"
        }
    ],
    "sg:phone":"+39 0733 290404",
    "sg:postcode":"62010",
    "sg:province":"Macerata",
    "sg:tags":[
        "household"
    ],
    "wof:name":"Falma Italia Coop. (s.r.l.)",
    "wof:placetype":"venue"
},
  "geometry": {"coordinates":[13.458343,43.354313],"type":"Point"}
}