{
  "type": "Feature",
  "properties": {
    "iso:country":"IT",
    "sg:address":"80078 Pozzuoli",
    "sg:city":"Pozzuoli",
    "sg:orig_category":"Servizi E Lavori Industria Della Gomma",
    "sg:phone":"+39 081 866 2930",
    "sg:postcode":"80078",
    "sg:province":"Napoli",
    "wof:name":"Vulcanizzazione Gomme Coppola",
    "wof:placetype":"venue"
},
  "geometry": {"coordinates":[14.096144,40.839844],"type":"Point"}
}