{
  "type": "Feature",
  "properties": {
    "addr:full":"21, Via Piave 21020 Brebbia Brebbia Varese 21020",
    "addr:postcode":"21020;21020",
    "addr:street":"Via Piave",
    "iso:country":"IT",
    "sg:address":"21, Via Piave 21020 Brebbia",
    "sg:city":"Brebbia",
    "sg:classifiers":[
        {
            "category":"Manufacturing",
            "subcategory":"Metals",
            "type":"Manufacturing & Wholesale Goods"
        }
    ],
    "sg:phone":"+39 0332 770358",
    "sg:postcode":"21020",
    "sg:province":"Varese",
    "sg:tags":[
        "metallurgy",
        "metalworking"
    ],
    "wof:name":"Pressofusione Brebbia (s.r.l.)",
    "wof:placetype":"venue"
},
  "geometry": {"coordinates":[8.7116641998,45.8095245361],"type":"Point"}
}