{
  "type": "Feature",
  "properties": {
    "iso:country":"IT",
    "sg:address":"52100 Arezzo, Ar",
    "sg:city":"Arezzo",
    "sg:classifiers":[
        {
            "category":"Banks & Credit Unions",
            "subcategory":"Bank",
            "type":"Services"
        }
    ],
    "sg:postcode":"52100",
    "sg:province":"Arezzo",
    "wof:name":"Get-gestione Esattorie E Tesorerie Spa",
    "wof:placetype":"venue"
},
  "geometry": {"coordinates":[11.8756,43.461102],"type":"Point"}
}