{
  "type": "Feature",
  "properties": {
    "addr:full":"Piazza Duca D'aosta 12; Milano; 20124 Milano Milano 20124",
    "addr:housenumber":"12",
    "addr:postcode":"20124;20124",
    "addr:street":"Piazza Duca D'Aosta",
    "iso:country":"IT",
    "sg:address":"Piazza Duca D'aosta 12; Milano; 20124",
    "sg:city":"Milano",
    "sg:classifiers":[
        {
            "category":"Banks & Credit Unions",
            "subcategory":"Bank",
            "type":"Services"
        }
    ],
    "sg:phone":"+39 02 669 2423",
    "sg:postcode":"20124",
    "sg:province":"Milano",
    "wof:name":"Fincea Finanziaria Spa",
    "wof:placetype":"venue"
},
  "geometry": {"coordinates":[9.203326,45.485268],"type":"Point"}
}