{
  "type": "Feature",
  "properties": {
    "iso:country":"IT",
    "sg:address":"74100 Taranto",
    "sg:city":"Taranto",
    "sg:orig_category":"Sport - Articoli E Forniture",
    "sg:phone":"+39 099 732 6448",
    "sg:postcode":"74100",
    "sg:province":"Taranto",
    "wof:name":"Asso Di Coppe",
    "wof:placetype":"venue"
},
  "geometry": {"coordinates":[17.259628,40.456577],"type":"Point"}
}