{
  "type": "Feature",
  "properties": {
    "addr:full":"29100 Piacenza Piacenza Piacenza 29100",
    "addr:postcode":"29100;29100",
    "iso:country":"IT",
    "sg:address":"29100 Piacenza",
    "sg:city":"Piacenza",
    "sg:orig_category":"Antifurto",
    "sg:phone":"+39 0523 305364",
    "sg:postcode":"29100",
    "sg:province":"Piacenza",
    "wof:name":"Electric Stema Di Forlini & Codeghini Snc",
    "wof:placetype":"venue"
},
  "geometry": {"coordinates":[9.699035,45.054844],"type":"Point"}
}