{
  "type": "Feature",
  "properties": {
    "addr:full":"3, Contrada Arci 65017 Penne Penne Pescara 65017",
    "addr:postcode":"65017;65017",
    "addr:street":"Contrada Arci",
    "iso:country":"IT",
    "sg:address":"3, Contrada Arci 65017 Penne",
    "sg:city":"Penne",
    "sg:classifiers":[
        {
            "category":"Real Estate",
            "subcategory":"Architect",
            "type":"Services"
        }
    ],
    "sg:phone":"+39 085 827 8945",
    "sg:postcode":"65017",
    "sg:province":"Pescara",
    "sg:tags":[
        "textile",
        "clothing"
    ],
    "wof:name":"Confezioni Tinacci Lucio",
    "wof:placetype":"venue"
},
  "geometry": {"coordinates":[13.916319,42.465057],"type":"Point"}
}