{
  "type": "Feature",
  "properties": {
    "iso:country":"IT",
    "sg:address":"25122 Brescia",
    "sg:city":"Brescia",
    "sg:orig_category":"Prodotti E Manufatti In Materie Plastiche",
    "sg:phone":"+39 030 375 7769",
    "sg:postcode":"25122",
    "sg:province":"Brescia",
    "wof:name":"Penta Chimica (s.r.l.)",
    "wof:placetype":"venue"
},
  "geometry": {"coordinates":[10.2193155289,45.5389709473],"type":"Point"}
}