{
  "type": "Feature",
  "properties": {
    "iso:country":"IT",
    "sg:address":"20089 Rozzano",
    "sg:city":"Rozzano",
    "sg:orig_category":"Calzature, Pelletterie E Pelli. Servizi E Lavori Per Abbigliamento E Pelletterie",
    "sg:phone":"+39 02 5751 2933",
    "sg:postcode":"20089",
    "sg:province":"Milano",
    "wof:name":"D'adamo Luigi",
    "wof:placetype":"venue"
},
  "geometry": {"coordinates":[9.173133,45.397182],"type":"Point"}
}