{
  "type": "Feature",
  "properties": {
    "addr:full":"12035 Racconigi Racconigi Cuneo 12035",
    "addr:postcode":"12035;12035",
    "iso:country":"IT",
    "sg:address":"12035 Racconigi",
    "sg:city":"Racconigi",
    "sg:orig_category":"Forniture Alle Strutture Ricettive. Forniture Per Attivita' Commerciali Ed Artigianali",
    "sg:phone":"+39 0172 812600",
    "sg:postcode":"12035",
    "sg:province":"Cuneo",
    "sg:website":"http://www.monetti.it",
    "wof:name":"Monetti Spa",
    "wof:placetype":"venue"
},
  "geometry": {"coordinates":[7.5471105576,44.38879776],"type":"Point"}
}