{
  "type": "Feature",
  "properties": {
    "iso:country":"IT",
    "sg:address":"20121 Milano",
    "sg:city":"Milano",
    "sg:classifiers":[
        {
            "category":"Health Services",
            "subcategory":"Health Practitioner",
            "type":"Services"
        }
    ],
    "sg:phone":"+39 02 659 8478",
    "sg:postcode":"20121",
    "sg:province":"Milano",
    "sg:tags":[
        "medici"
    ],
    "wof:name":"S.i.med Srl",
    "wof:placetype":"venue"
},
  "geometry": {"coordinates":[9.1948080063,45.4741973877],"type":"Point"}
}