{
  "type": "Feature",
  "properties": {
    "addr:full":"20025 Legnano Legnano Milano 20025",
    "addr:postcode":"20025;20025",
    "iso:country":"IT",
    "sg:address":"20025 Legnano",
    "sg:city":"Legnano",
    "sg:orig_category":"Non-classified Establishments",
    "sg:phone":"+39 0331 599400",
    "sg:postcode":"20025",
    "sg:province":"Milano",
    "wof:name":"Toys Center",
    "wof:placetype":"venue"
},
  "geometry": {"coordinates":[8.909721,45.605],"type":"Point"}
}