{
  "type": "Feature",
  "properties": {
    "addr:full":"60035 Jesi Jesi Ancona 60035",
    "addr:postcode":"60035;60035",
    "iso:country":"IT",
    "sg:address":"60035 Jesi",
    "sg:city":"Jesi",
    "sg:orig_category":"Elettrotecnica Industriale, Prodotti E Apparecchiature",
    "sg:phone":"+39 0731 207607",
    "sg:postcode":"60035",
    "sg:province":"Ancona",
    "wof:name":"C.e.m.j. Srl",
    "wof:placetype":"venue"
},
  "geometry": {"coordinates":[13.275714,43.537289],"type":"Point"}
}