{
  "type": "Feature",
  "properties": {
    "iso:country":"IT",
    "sg:address":"67030 Vittorito",
    "sg:orig_category":"Accessori Moda D'abbigliamento. Complementi Di Arredamento. Tempo Libero - Articoli E Forniture",
    "sg:phone":"+39 0864 727146",
    "sg:postcode":"67030",
    "sg:province":"L\\\\\\\\\\\\\\\\\\\\\\\\\\\\\\\\\\\\\\\\\\\\\\\\\\\\\\\\\\\\\\\\\\\\\\\\\\\\\\\\\\\\\\\\\\\\\\\\\\\\\\\\\\\\\\\\\\\\\\\\\\\\\\\\\\\\\\\\\\\\\\\\\\\\\\\\\\\\\\\\\\\\\\\\\\\\\\\\\\\\\\\\\\\\\\\\\\\\",
    "wof:name":"Ombrellificio Di Felice",
    "wof:placetype":"venue"
},
  "geometry": {"coordinates":[13.817657,42.128056],"type":"Point"}
}