{
  "type": "Feature",
  "properties": {
    "iso:country":"IT",
    "sg:address":"20123 Milano",
    "sg:city":"Milano",
    "sg:orig_category":"Scuole E Servizi Scolastici. Ricerca, Selezione E Formazione Del Personale. Pubblica Amministrazione",
    "sg:phone":"+39 02 801263",
    "sg:postcode":"20123",
    "sg:province":"Milano",
    "wof:name":"Civico Istituto Tecnico Serale Per Geometri",
    "wof:placetype":"venue"
},
  "geometry": {"coordinates":[9.183043,45.459446],"type":"Point"}
}