{
  "type": "Feature",
  "properties": {
    "iso:country":"IT",
    "sg:address":"22063 Cantu'",
    "sg:orig_category":"Servizi E Lavori Per Edilizia E Lavori Pubblici. Servizi E Lavori Per Ecologia E Smaltimento Rifiuti. Macchine E Forniture Per Ecologia E Smaltimento Rifiuti. Acqua, Luce, Gas E Societa' Di Esercizio ",
    "sg:phone":"+39 031 714590",
    "sg:postcode":"22063",
    "sg:province":"Como",
    "wof:name":"Protezione Civile",
    "wof:placetype":"venue"
},
  "geometry": {"coordinates":[9.126958,45.740993],"type":"Point"}
}