{
  "type": "Feature",
  "properties": {
    "iso:country":"IT",
    "sg:address":"93016 Riesi",
    "sg:city":"Riesi",
    "sg:orig_category":"Musica. Shopping",
    "sg:phone":"+39 0934 928348",
    "sg:postcode":"93016",
    "sg:province":"Caltanissetta",
    "wof:name":"Orizzonti Musicali Di Gangitano Luciano",
    "wof:placetype":"venue"
},
  "geometry": {"coordinates":[14.083527565,37.2833023071],"type":"Point"}
}