{
  "type": "Feature",
  "properties": {
    "iso:country":"IT",
    "sg:address":"13, P. Kennedy 60122 Ancona",
    "sg:city":"Ancona",
    "sg:classifiers":[
        {
            "category":"Banks & Credit Unions",
            "subcategory":"Investment Brokerage",
            "type":"Services"
        }
    ],
    "sg:phone":"+39 39071201904",
    "sg:postcode":"60122",
    "sg:province":"Ancona",
    "sg:tags":[
        "-",
        "transport",
        "related"
    ],
    "sg:website":"http://www.odino-valperga.com",
    "wof:name":"Odino Valperga General Cargo Srl",
    "wof:placetype":"venue"
},
  "geometry": {"coordinates":[13.509628,43.61842],"type":"Point"}
}