{
  "type": "Feature",
  "properties": {
    "iso:country":"IT",
    "sg:address":"80127 Napoli",
    "sg:city":"Napoli",
    "sg:orig_category":"Servizi E Lavori Per Abbigliamento E Pelletterie. Scuole E Servizi Scolastici. Ricerca, Selezione E Formazione Del Personale",
    "sg:phone":"+39 081 560 4522",
    "sg:postcode":"80127",
    "sg:province":"Napoli",
    "wof:name":"Coppola Carmela",
    "wof:placetype":"venue"
},
  "geometry": {"coordinates":[14.2005996704,40.9142494202],"type":"Point"}
}