{
  "type": "Feature",
  "properties": {
    "iso:country":"IT",
    "sg:address":"Via Principale 4, 39050 Nova Ponente, Bz",
    "sg:city":"Nova Ponente",
    "sg:classifiers":[
        {
            "category":"Banks & Credit Unions",
            "subcategory":"Bank",
            "type":"Services"
        }
    ],
    "sg:postcode":"39050",
    "sg:province":"Bolzano/Bozen",
    "wof:name":"Cassa Raiifeisen Di Nova Ponente-aldino Scrl",
    "wof:placetype":"venue"
},
  "geometry": {"coordinates":[11.426953,46.41357],"type":"Point"}
}