{
  "type": "Feature",
  "properties": {
    "addr:full":"23846 Garbagnate Monastero Garbagnate Monastero Lecco 23846",
    "addr:postcode":"23846;23846",
    "iso:country":"IT",
    "sg:address":"23846 Garbagnate Monastero",
    "sg:city":"Garbagnate Monastero",
    "sg:classifiers":[
        {
            "category":"Building & Trades",
            "subcategory":"Construction",
            "type":"Services"
        }
    ],
    "sg:phone":"+39 031 852200",
    "sg:postcode":"23846",
    "sg:province":"Lecco",
    "sg:tags":[
        "industry",
        "work",
        "plastic"
    ],
    "wof:name":"Baldelli & Colombo Snc",
    "wof:placetype":"venue"
},
  "geometry": {"coordinates":[9.288359642,45.7704353333],"type":"Point"}
}