{
  "type": "Feature",
  "properties": {
    "addr:full":"95128 Catania Catania Catania 95128",
    "addr:postcode":"95128;95128",
    "iso:country":"IT",
    "sg:address":"95128 Catania",
    "sg:city":"Catania",
    "sg:orig_category":"Imprese Pulizia",
    "sg:phone":"+39 095 444146",
    "sg:postcode":"95128",
    "sg:province":"Catania",
    "wof:name":"I.p.m. Service Di Marchese",
    "wof:placetype":"venue"
},
  "geometry": {"coordinates":[15.08705,37.5168],"type":"Point"}
}