{
  "type": "Feature",
  "properties": {
    "addr:full":"35010 Limena Limena Padova 35010",
    "addr:postcode":"35010;35010",
    "iso:country":"IT",
    "sg:address":"35010 Limena",
    "sg:city":"Limena",
    "sg:orig_category":"Non-classified Establishments",
    "sg:phone":"+39 049 884 1655",
    "sg:postcode":"35010",
    "sg:province":"Padova",
    "sg:website":"http://www.ivalentini.it",
    "wof:name":"I Valentini Srl",
    "wof:placetype":"venue"
},
  "geometry": {"coordinates":[11.843712,45.466293],"type":"Point"}
}