{
  "type": "Feature",
  "properties": {
    "addr:full":"88100 Catanzaro Catanzaro Catanzaro 88100",
    "addr:postcode":"88100;88100",
    "iso:country":"IT",
    "sg:address":"88100 Catanzaro",
    "sg:city":"Catanzaro",
    "sg:orig_category":"Servizi E Lavori Per Agricoltura E Zootecnia. Servizi Ausiliari Di Analisi, Controllo E Ricerca",
    "sg:phone":"+39 0961 32586",
    "sg:postcode":"88100",
    "sg:province":"Catanzaro",
    "wof:name":"Istituto Zooprofilattico Sperimentale Del Mezzogiorno",
    "wof:placetype":"venue"
},
  "geometry": {"coordinates":[16.619936,38.824703],"type":"Point"}
}