{
  "type": "Feature",
  "properties": {
    "iso:country":"IT",
    "sg:address":"13/b, Via G.ungaretti 40050 Castello D'argile",
    "sg:classifiers":[
        {
            "category":"Shopping",
            "subcategory":"Computers & Home Electronics",
            "type":"Retail Goods"
        }
    ],
    "sg:phone":"+39 051 686 7182",
    "sg:postcode":"40050",
    "sg:province":"Bologna",
    "sg:tags":[
        "electronic",
        "electrical",
        "equipment"
    ],
    "wof:name":"Delta System (s.r.l.)",
    "wof:placetype":"venue"
},
  "geometry": {"coordinates":[11.346481,44.494221],"type":"Point"}
}