{
  "type": "Feature",
  "properties": {
    "iso:country":"IT",
    "sg:address":"20091 Bresso",
    "sg:city":"Bresso",
    "sg:orig_category":"Chiese Ed Associazioni Religiose",
    "sg:phone":"+39 02 610 0996",
    "sg:postcode":"20091",
    "sg:province":"Milano",
    "wof:name":"Parrocchia Madonna Della Misericordia",
    "wof:placetype":"venue"
},
  "geometry": {"coordinates":[9.196553,45.531494],"type":"Point"}
}