{
  "type": "Feature",
  "properties": {
    "iso:country":"IT",
    "sg:address":"00147 Roma",
    "sg:city":"Roma",
    "sg:orig_category":"Abbigliamento Esterno, Maglierie E Pelliccerie. Forniture Per Il Settore Dello Spettacolo",
    "sg:phone":"+39 06 511 5639",
    "sg:postcode":"00147",
    "sg:province":"Roma",
    "wof:name":"Costumi D'arte S.r.l.",
    "wof:placetype":"venue"
},
  "geometry": {"coordinates":[12.501447,41.857254],"type":"Point"}
}