{
  "type": "Feature",
  "properties": {
    "iso:country":"IT",
    "sg:address":"36060 Romano D'ezzelino",
    "sg:orig_category":"Prodotti E Manufatti In Gomma",
    "sg:phone":"+39 0424 34261",
    "sg:postcode":"36060",
    "sg:province":"Vicenza",
    "wof:name":"Galvan Luciano",
    "wof:placetype":"venue"
},
  "geometry": {"coordinates":[11.7811412811,45.7509384155],"type":"Point"}
}