{
  "type": "Feature",
  "properties": {
    "addr:full":"40012 Calderara Di Reno Calderara di Reno Bologna 40012",
    "addr:postcode":"40012;40012",
    "iso:country":"IT",
    "sg:address":"40012 Calderara Di Reno",
    "sg:city":"Calderara di Reno",
    "sg:orig_category":"Macchine E Forniture Per Ecologia E Smaltimento Rifiuti",
    "sg:phone":"+39 051 727416",
    "sg:postcode":"40012",
    "sg:province":"Bologna",
    "sg:website":"http://www.manganelliecologia.com",
    "wof:name":"Manganelli Ecologia Impianti Srl",
    "wof:placetype":"venue"
},
  "geometry": {"coordinates":[11.270288,44.535423],"type":"Point"}
}