{
  "type": "Feature",
  "properties": {
    "iso:country":"IT",
    "sg:address":"41, Vicolo Vienna 24040 Bottanuco",
    "sg:city":"Bottanuco",
    "sg:classifiers":[
        {
            "category":"Professional",
            "subcategory":"Engineering",
            "type":"Services"
        }
    ],
    "sg:phone":"+39 39035906440",
    "sg:postcode":"24040",
    "sg:province":"Bergamo",
    "sg:tags":[
        "machine",
        "-",
        "mechanical"
    ],
    "wof:name":"Cb (s.r.l.)",
    "wof:placetype":"venue"
},
  "geometry": {"coordinates":[9.515844,45.644192],"type":"Point"}
}