{
  "type": "Feature",
  "properties": {
    "addr:full":"76/78, Via Trento 25024 Leno Leno Brescia 25024",
    "addr:housenumber":"76 / 78",
    "addr:postcode":"25024;25024",
    "addr:street":"Via Trento",
    "iso:country":"IT",
    "sg:address":"76/78, Via Trento 25024 Leno",
    "sg:city":"Leno",
    "sg:classifiers":[
        {
            "category":"Manufacturing",
            "subcategory":"Metals",
            "type":"Manufacturing & Wholesale Goods"
        }
    ],
    "sg:phone":"+39 030 903 8994",
    "sg:postcode":"25024",
    "sg:province":"Brescia",
    "sg:tags":[
        "metallurgy",
        "metalworking"
    ],
    "wof:name":"Alnor - Nuova Alluminio Nord (s.p.a.)",
    "wof:placetype":"venue"
},
  "geometry": {"coordinates":[10.1971063614,45.4000816345],"type":"Point"}
}