{
  "type": "Feature",
  "properties": {
    "iso:country":"IT",
    "sg:address":"24, Via Statale 23807 Merate",
    "sg:city":"Merate",
    "sg:classifiers":[
        {
            "category":"Shopping",
            "subcategory":"Clothing, Apparel, & Fashions",
            "type":"Retail Goods"
        }
    ],
    "sg:phone":"+39 39800205777",
    "sg:postcode":"23807",
    "sg:province":"Lecco",
    "sg:tags":[
        "clothes"
    ],
    "wof:name":"Rue Royale Diana Spa",
    "wof:placetype":"venue"
},
  "geometry": {"coordinates":[9.411344,45.704655],"type":"Point"}
}