{
  "type": "Feature",
  "properties": {
    "iso:country":"IT",
    "sg:address":"1, Via Nenni Pietro 37051 Bovolone",
    "sg:city":"Bovolone",
    "sg:classifiers":[
        {
            "category":"Farming",
            "subcategory":"Livestock Farm",
            "type":"Manufacturing & Wholesale Goods"
        }
    ],
    "sg:phone":"+39 045 690 0536",
    "sg:postcode":"37051",
    "sg:province":"Verona",
    "sg:tags":[
        "agriculture"
    ],
    "wof:name":"Maldotti Giorgio (s.n.c.)",
    "wof:placetype":"venue"
},
  "geometry": {"coordinates":[10.991748,45.438366],"type":"Point"}
}