{
  "type": "Feature",
  "properties": {
    "addr:full":"23, Via Papa Giovanni Xxiii 20080 Zibido San Giacomo Zibido San Giacomo Milano 20080",
    "addr:postcode":"20080;20080",
    "addr:street":"Via Papa Giovanni Xxiii;San",
    "iso:country":"IT",
    "sg:address":"23, Via Papa Giovanni Xxiii 20080 Zibido San Giacomo",
    "sg:city":"Zibido San Giacomo",
    "sg:classifiers":[
        {
            "category":"Manufacturing",
            "subcategory":"Printing",
            "type":"Manufacturing & Wholesale Goods"
        }
    ],
    "sg:phone":"+39 02 9000 2411",
    "sg:postcode":"20080",
    "sg:province":"Milano",
    "sg:tags":[
        "publishing"
    ],
    "wof:name":"Tecnicart S.r.l.",
    "wof:placetype":"venue"
},
  "geometry": {"coordinates":[9.1340255737,45.4028663635],"type":"Point"}
}