{
  "type": "Feature",
  "properties": {
    "iso:country":"IT",
    "sg:address":"Zona Industriale 73040 Specchia",
    "sg:city":"Specchia",
    "sg:classifiers":[
        {
            "category":"Professional",
            "subcategory":"Engineering",
            "type":"Services"
        }
    ],
    "sg:phone":"+39 0833 539172",
    "sg:postcode":"73040",
    "sg:province":"Lecce",
    "sg:tags":[
        "machine",
        "-",
        "mechanical"
    ],
    "wof:name":"O.l.c. Officine Lavorazione Calibri (s.r.l.)",
    "wof:placetype":"venue"
},
  "geometry": {"coordinates":[18.174015,40.353291],"type":"Point"}
}