{
  "type": "Feature",
  "properties": {
    "addr:full":"91017 Pantelleria Pantelleria Trapani 91017",
    "addr:postcode":"91017;91017",
    "iso:country":"IT",
    "sg:address":"91017 Pantelleria",
    "sg:city":"Pantelleria",
    "sg:orig_category":"Agricoltura, Orticoltura E Floricoltura",
    "sg:phone":"+39 0923 916021",
    "sg:postcode":"91017",
    "sg:province":"Trapani",
    "wof:name":"Bonomo & Giglio",
    "wof:placetype":"venue"
},
  "geometry": {"coordinates":[11.972068,36.768257],"type":"Point"}
}