{
  "type": "Feature",
  "properties": {
    "iso:country":"IT",
    "sg:address":"33, Via Pordenone 33080 San Quirino",
    "sg:city":"San Quirino",
    "sg:classifiers":[
        {
            "category":"Food & Beverages",
            "subcategory":"Groceries & Convenience Stores",
            "type":"Retail Goods"
        }
    ],
    "sg:phone":"+39 39043491061",
    "sg:postcode":"33080",
    "sg:province":"Pordenone",
    "sg:tags":[
        "drink"
    ],
    "wof:name":"Casa Vinicola Pavan (s.r.l.)",
    "wof:placetype":"venue"
},
  "geometry": {"coordinates":[12.649587,46.009651],"type":"Point"}
}