{
  "type": "Feature",
  "properties": {
    "iso:country":"IT",
    "sg:address":"20/22, Via Diaz 21030 Mesenzana",
    "sg:city":"Mesenzana",
    "sg:classifiers":[
        {
            "category":"Manufacturing",
            "subcategory":"Metals",
            "type":"Manufacturing & Wholesale Goods"
        }
    ],
    "sg:phone":"+39 0332 575060",
    "sg:postcode":"21030",
    "sg:province":"Varese",
    "sg:tags":[
        "processing"
    ],
    "wof:name":"Zuretti Luigi",
    "wof:placetype":"venue"
},
  "geometry": {"coordinates":[8.7628984451,45.946472168],"type":"Point"}
}