{
  "type": "Feature",
  "properties": {
    "iso:country":"IT",
    "sg:address":"30034 Mira",
    "sg:city":"Mira",
    "sg:orig_category":"Servizi E Lavori Per Agricoltura E Zootecnia. Servizi E Lavori Per Ecologia E Smaltimento Rifiuti",
    "sg:phone":"+39 041 477053",
    "sg:postcode":"30034",
    "sg:province":"Venezia",
    "wof:name":"Consorzio Di Bonifica Sinistra Medio Brenta",
    "wof:placetype":"venue"
},
  "geometry": {"coordinates":[12.1323871613,45.4197349548],"type":"Point"}
}