{
  "type": "Feature",
  "properties": {
    "iso:country":"IT",
    "sg:address":"97015 Modica",
    "sg:city":"Modica",
    "sg:orig_category":"Abbigliamento Esterno, Maglierie E Pelliccerie. Calzature, Pelletterie E Pelli",
    "sg:phone":"+39 0932 454842",
    "sg:postcode":"97015",
    "sg:province":"Ragusa",
    "wof:name":"New Pel Srl",
    "wof:placetype":"venue"
},
  "geometry": {"coordinates":[14.822115,36.852718],"type":"Point"}
}