{
  "type": "Feature",
  "properties": {
    "iso:country":"IT",
    "sg:address":"20043 Arcore",
    "sg:city":"Arcore",
    "sg:orig_category":"Carta, Cartone E Prodotti Primari. Forniture E Materiali Per Imballaggio E Confezionamento",
    "sg:phone":"+39 039 601 3543",
    "sg:postcode":"20043",
    "sg:province":"Milano",
    "wof:name":"Ro.ond. Italiana Cartotecnica Srl",
    "wof:placetype":"venue"
},
  "geometry": {"coordinates":[9.155725,45.398102],"type":"Point"}
}