{
  "type": "Feature",
  "properties": {
    "addr:full":"15 Piazza Ferrari, 47900 Rimini Rimini Rimini 47900",
    "addr:postcode":"47900;47900",
    "addr:street":"Piazza Ferrari",
    "iso:country":"IT",
    "sg:address":"15 Piazza Ferrari, 47900 Rimini",
    "sg:city":"Rimini",
    "sg:classifiers":[
        {
            "category":"Banks & Credit Unions",
            "subcategory":"Financial Services",
            "type":"Services"
        }
    ],
    "sg:phone":"+39 0541 701111",
    "sg:postcode":"47900",
    "sg:province":"Rimini",
    "sg:tags":[
        "banking",
        "finance",
        "insurance"
    ],
    "wof:name":"Cassa Di Risparmio Di Rimini (spa)",
    "wof:placetype":"venue"
},
  "geometry": {"coordinates":[12.4772968292,44.0697364807],"type":"Point"}
}