{
  "type": "Feature",
  "properties": {
    "iso:country":"IT",
    "sg:address":"20092 Cinisello Balsamo",
    "sg:city":"Cinisello Balsamo",
    "sg:orig_category":"Serramenti Ed Infissi",
    "sg:phone":"+39 02 611151",
    "sg:postcode":"20092",
    "sg:province":"Milano",
    "sg:website":"http://www.bpbitalia.it",
    "wof:name":"Bpb Italia Spa",
    "wof:placetype":"venue"
},
  "geometry": {"coordinates":[9.275837,45.532516],"type":"Point"}
}