{
  "type": "Feature",
  "properties": {
    "addr:full":"26013 Ombriano Ombriano Cremona 26013",
    "addr:postcode":"26013;26013",
    "iso:country":"IT",
    "sg:address":"26013 Ombriano",
    "sg:city":"Ombriano",
    "sg:orig_category":"Macchine, Impianti Ed Attrezzature Per Industria Alimentare E Bevande",
    "sg:phone":"+39 0373 30153",
    "sg:postcode":"26013",
    "sg:province":"Cremona",
    "wof:name":"Scandelli S.n.c. Di Marco E Massimo Scandelli",
    "wof:placetype":"venue"
},
  "geometry": {"coordinates":[9.649172,45.349945],"type":"Point"}
}