{
  "type": "Feature",
  "properties": {
    "addr:full":"00166 Roma Roma Roma 00166",
    "addr:postcode":"00166;00166",
    "iso:country":"IT",
    "sg:address":"00166 Roma",
    "sg:city":"Roma",
    "sg:orig_category":"Tempo Libero - Articoli E Forniture. Automobili E Mezzi Di Trasporto. Riparazione Dei Mezzi Di Trasporto",
    "sg:phone":"+39 06 6156 3012",
    "sg:postcode":"00166",
    "sg:province":"Roma",
    "wof:name":"Stringati Aurora & Fabio",
    "wof:placetype":"venue"
},
  "geometry": {"coordinates":[12.374999,41.917675],"type":"Point"}
}