{
  "type": "Feature",
  "properties": {
    "addr:full":"15100 Alessandria Alessandria Alessandria 15100",
    "addr:postcode":"15100;15100",
    "iso:country":"IT",
    "sg:address":"15100 Alessandria",
    "sg:city":"Alessandria",
    "sg:orig_category":"Prodotti Chimici Secondari. Macchine, Impianti Ed Attrezzature Industria Chimica. Servizi E Lavori Industria Chimica",
    "sg:phone":"+39 0131 261865",
    "sg:postcode":"15100",
    "sg:province":"Alessandria",
    "wof:name":"De Carlis Stefania",
    "wof:placetype":"venue"
},
  "geometry": {"coordinates":[8.6154127121,44.908367157],"type":"Point"}
}