{
  "type": "Feature",
  "properties": {
    "iso:country":"IT",
    "sg:address":"1, Contrada S. Stefano 66010 Ripa Teatina",
    "sg:city":"Ripa Teatina",
    "sg:classifiers":[
        {
            "category":"Farming",
            "subcategory":"Livestock Farm",
            "type":"Manufacturing & Wholesale Goods"
        }
    ],
    "sg:phone":"+39 0871 399290",
    "sg:postcode":"66010",
    "sg:province":"Chieti",
    "sg:tags":[
        "agriculture"
    ],
    "wof:name":"Ortofrutticola Val Di Foro",
    "wof:placetype":"venue"
},
  "geometry": {"coordinates":[14.247526,42.354355],"type":"Point"}
}