{
  "type": "Feature",
  "properties": {
    "addr:full":"20144 Milano Milano Milano 20144",
    "addr:postcode":"20144;20144",
    "iso:country":"IT",
    "sg:address":"20144 Milano",
    "sg:city":"Milano",
    "sg:orig_category":"Bullonerie",
    "sg:phone":"+39 02 4895 2785",
    "sg:postcode":"20144",
    "sg:province":"Milano",
    "wof:name":"Dm Utensili Srl",
    "wof:placetype":"venue"
},
  "geometry": {"coordinates":[9.160282,45.452999],"type":"Point"}
}