{
  "type": "Feature",
  "properties": {
    "iso:country":"IT",
    "sg:address":"13848 Zumaglia",
    "sg:city":"Zumaglia",
    "sg:orig_category":"Servizi E Lavori Per Abbigliamento E Pelletterie",
    "sg:phone":"+39 015 461952",
    "sg:postcode":"13848",
    "sg:province":"Biella",
    "wof:name":"Garzatura Botto (s.n.c.)",
    "wof:placetype":"venue"
},
  "geometry": {"coordinates":[8.081428,45.595829],"type":"Point"}
}