{
  "type": "Feature",
  "properties": {
    "iso:country":"IT",
    "sg:address":"Via Stazione 18; Turi; 70010",
    "sg:city":"Turi",
    "sg:classifiers":[
        {
            "category":"Banks & Credit Unions",
            "subcategory":"Bank",
            "type":"Services"
        }
    ],
    "sg:phone":"+39 080 891 2216",
    "sg:postcode":"70010",
    "sg:province":"Bari",
    "wof:name":"Banco Di Napoli Spa",
    "wof:placetype":"venue"
},
  "geometry": {"coordinates":[17.017443,40.915016],"type":"Point"}
}