{
  "type": "Feature",
  "properties": {
    "iso:country":"IT",
    "sg:address":"13, Via Costituzione 42015 Correggio",
    "sg:classifiers":[
        {
            "category":"Manufacturing",
            "subcategory":"Rubber & Plastics",
            "type":"Manufacturing & Wholesale Goods"
        }
    ],
    "sg:phone":"+39 0522 694075",
    "sg:postcode":"42015",
    "sg:province":"Reggio Nell'Emilia",
    "wof:name":"Plaster (s.n.c.)",
    "wof:placetype":"venue"
},
  "geometry": {"coordinates":[10.8186502457,44.7700462341],"type":"Point"}
}