{
  "type": "Feature",
  "properties": {
    "iso:country":"IT",
    "sg:address":"99 Via Pratese, 50145 Firenze",
    "sg:city":"Firenze",
    "sg:classifiers":[
        {
            "category":"Banks & Credit Unions",
            "subcategory":"Financial Services",
            "type":"Services"
        }
    ],
    "sg:phone":"+39 390 553 3619",
    "sg:postcode":"50145",
    "sg:province":"Firenze",
    "sg:tags":[
        "banking",
        "finance",
        "insurance"
    ],
    "wof:name":"Brinks Securmark Spa",
    "wof:placetype":"venue"
},
  "geometry": {"coordinates":[11.1909303665,43.8009643555],"type":"Point"}
}