{
  "type": "Feature",
  "properties": {
    "iso:country":"IT",
    "sg:address":"16042 Carasco",
    "sg:city":"Carasco",
    "sg:orig_category":"Termotecnica E Riscaldamento, Apparecchiature E Servizi",
    "sg:phone":"+39 0185 350219",
    "sg:postcode":"16042",
    "sg:province":"Genova",
    "wof:name":"D.e.l.t.a. (s.r.l.)",
    "wof:placetype":"venue"
},
  "geometry": {"coordinates":[9.361758,44.358757],"type":"Point"}
}