{
  "type": "Feature",
  "properties": {
    "iso:country":"IT",
    "sg:address":"Via A. Vitale 102 84013 Cava De' Tirreni",
    "sg:classifiers":[
        {
            "category":"Wholesale",
            "subcategory":"Tobacco Products",
            "type":"Manufacturing & Wholesale Goods"
        }
    ],
    "sg:phone":"+39 089 562373",
    "sg:postcode":"84013",
    "sg:province":"Salerno",
    "sg:tags":[
        "case"
    ],
    "wof:name":"Vitale Natale",
    "wof:placetype":"venue"
},
  "geometry": {"coordinates":[14.711693,40.732002],"type":"Point"}
}