{
  "type": "Feature",
  "properties": {
    "addr:full":"00052 Cerveteri Cerveteri Roma 00052",
    "addr:postcode":"00052;roma 00052",
    "iso:country":"IT",
    "sg:address":"00052 Cerveteri",
    "sg:city":"Cerveteri",
    "sg:orig_category":"Servizi E Lavori Per Abbigliamento E Pelletterie",
    "sg:phone":"+39 06 995 2385",
    "sg:postcode":"00052",
    "sg:province":"Roma",
    "wof:name":"Frasca Barbara",
    "wof:placetype":"venue"
},
  "geometry": {"coordinates":[12.510372,41.893852],"type":"Point"}
}