{
  "type": "Feature",
  "properties": {
    "addr:full":"15, Via Maglio Di Sopra 36073 Cornedo Vicentino Cornedo Vicentino Vicenza 36073",
    "addr:postcode":"36073;36073",
    "addr:street":"Via Maglio Di Sopra;Vicentino",
    "iso:country":"IT",
    "sg:address":"15, Via Maglio Di Sopra 36073 Cornedo Vicentino",
    "sg:city":"Cornedo Vicentino",
    "sg:classifiers":[
        {
            "category":"Manufacturing",
            "subcategory":"Rubber & Plastics",
            "type":"Manufacturing & Wholesale Goods"
        }
    ],
    "sg:phone":"+39 0445 446957",
    "sg:postcode":"36073",
    "sg:province":"Vicenza",
    "wof:name":"Multiplast S.r.l.",
    "wof:placetype":"venue"
},
  "geometry": {"coordinates":[11.3320932388,45.6150016785],"type":"Point"}
}