{
  "type": "Feature",
  "properties": {
    "iso:country":"IT",
    "sg:address":"Km. 111.500, Via Tiburtina Valeria 67068 Scurcola Marsicana",
    "sg:classifiers":[
        {
            "category":"Travel",
            "subcategory":"Travel Agent",
            "type":"Entertainment"
        }
    ],
    "sg:phone":"+39 390 863 4521",
    "sg:postcode":"67068",
    "sg:province":"L'Aquila",
    "sg:tags":[
        "business"
    ],
    "wof:name":"Hotel Olimpia",
    "wof:placetype":"venue"
},
  "geometry": {"coordinates":[13.431372,42.039116],"type":"Point"}
}