{
  "type": "Feature",
  "properties": {
    "iso:country":"IT",
    "sg:address":"26, Via Creta 25124 Brescia",
    "sg:city":"Brescia",
    "sg:classifiers":[
        {
            "category":"Manufacturing",
            "subcategory":"Metals",
            "type":"Manufacturing & Wholesale Goods"
        }
    ],
    "sg:phone":"+39 030 242 5530",
    "sg:postcode":"25124",
    "sg:province":"Brescia",
    "sg:tags":[
        "metallurgy",
        "metalworking"
    ],
    "wof:name":"Raffineria Metalli Capra (s.p.a.)",
    "wof:placetype":"venue"
},
  "geometry": {"coordinates":[10.2135810852,45.5279083252],"type":"Point"}
}