{
  "type": "Feature",
  "properties": {
    "iso:country":"IT",
    "sg:address":"Localita' Lagoscuro 19020 Vezzano Ligure",
    "sg:city":"Vezzano Ligure",
    "sg:classifiers":[
        {
            "category":"Wholesale",
            "subcategory":"Drugs",
            "type":"Manufacturing & Wholesale Goods"
        }
    ],
    "sg:phone":"+39 0187 934566",
    "sg:postcode":"19020",
    "sg:province":"La Spezia",
    "sg:tags":[
        "chemical",
        "pharmaceutical"
    ],
    "wof:name":"Nuova Connavi S.r.l.",
    "wof:placetype":"venue"
},
  "geometry": {"coordinates":[9.877204,44.171276],"type":"Point"}
}