{
  "type": "Feature",
  "properties": {
    "iso:country":"IT",
    "sg:address":"71043 Manfredonia",
    "sg:city":"Manfredonia",
    "sg:orig_category":"Analisi Chimiche, Industriali E Merceologiche",
    "sg:phone":"+39 0884 541530",
    "sg:postcode":"71043",
    "sg:province":"Foggia",
    "sg:website":"http://www.laboratoriomarchionni.it",
    "wof:name":"Laboratorio Marchionni Sas",
    "wof:placetype":"venue"
},
  "geometry": {"coordinates":[15.805547,41.550507],"type":"Point"}
}