{
  "type": "Feature",
  "properties": {
    "iso:country":"IT",
    "sg:address":"Via Santello 15 25065 Lumezzane",
    "sg:city":"Lumezzane",
    "sg:classifiers":[
        {
            "category":"Home & Garden",
            "subcategory":"Kitchen Supply",
            "type":"Retail Goods"
        }
    ],
    "sg:phone":"+39 030 897 0734",
    "sg:postcode":"25065",
    "sg:province":"Brescia",
    "sg:tags":[
        "utensils",
        "household",
        "galvanized"
    ],
    "wof:name":"Fratelli Scaramuzzi Srl",
    "wof:placetype":"venue"
},
  "geometry": {"coordinates":[10.22943,45.659008],"type":"Point"}
}