{
  "type": "Feature",
  "properties": {
    "addr:full":"00181 Roma Roma Roma 00181",
    "addr:postcode":"00181;00181",
    "iso:country":"IT",
    "sg:address":"00181 Roma",
    "sg:city":"Roma",
    "sg:orig_category":"Arredamenti E Mobili Professionali. Arredi Ed Attrezzature Per Uffici",
    "sg:phone":"+39 06 7690 0300",
    "sg:postcode":"00181",
    "sg:province":"Roma",
    "wof:name":"Casa Dello Scaffale (s.r.l.)",
    "wof:placetype":"venue"
},
  "geometry": {"coordinates":[12.538283,41.869095],"type":"Point"}
}