{
  "type": "Feature",
  "properties": {
    "iso:country":"IT",
    "sg:address":"41100 Modena",
    "sg:city":"Modena",
    "sg:orig_category":"Servizi E Lavori Per Abbigliamento E Pelletterie. Servizi Ausiliari Di Sorveglianza, Manutenzione E Pulizia",
    "sg:phone":"+39 059 312556",
    "sg:postcode":"41100",
    "sg:province":"Modena",
    "sg:website":"http://www.pulipel3r.it",
    "wof:name":"Pulipel 3r Candor Snc",
    "wof:placetype":"venue"
},
  "geometry": {"coordinates":[10.925406,44.664608],"type":"Point"}
}