{
  "type": "Feature",
  "properties": {
    "addr:full":"20, Via Croce Rossa 98124 Messina Messina Messina 98124",
    "addr:postcode":"98124;98124",
    "addr:street":"Via Croce Rossa",
    "iso:country":"IT",
    "sg:address":"20, Via Croce Rossa 98124 Messina",
    "sg:city":"Messina",
    "sg:classifiers":[
        {
            "category":"Professional",
            "subcategory":"Printing & Photocopies",
            "type":"Services"
        }
    ],
    "sg:phone":"+39 090 293 1094",
    "sg:postcode":"98124",
    "sg:province":"Messina",
    "wof:name":"Grafo Editor (s.r.l.)",
    "wof:placetype":"venue"
},
  "geometry": {"coordinates":[15.5508985519,38.1743507385],"type":"Point"}
}