{
  "type": "Feature",
  "properties": {
    "iso:country":"IT",
    "sg:address":"4, V. Fontanelle 25030 Paratico",
    "sg:city":"Paratico",
    "sg:classifiers":[
        {
            "category":"Professional",
            "subcategory":"Engineering",
            "type":"Services"
        }
    ],
    "sg:phone":"+39 39035914455",
    "sg:postcode":"25030",
    "sg:province":"Brescia",
    "sg:tags":[
        "machine",
        "-",
        "mechanical"
    ],
    "sg:website":"http://www.evoltex.com:ws_end: :mark:ws:http://www.paginegialle.it/evoltex",
    "wof:name":"Evoltex Srl",
    "wof:placetype":"venue"
},
  "geometry": {"coordinates":[9.959071,45.65184],"type":"Point"}
}