{
  "type": "Feature",
  "properties": {
    "iso:country":"IT",
    "sg:address":"66054 Vasto",
    "sg:city":"Vasto",
    "sg:orig_category":"Elettrotecnica Industriale, Prodotti E Apparecchiature. Elettronica Industriale, Prodotti E Apparecchiature",
    "sg:phone":"+39 0873 301014",
    "sg:postcode":"66054",
    "sg:province":"Chieti",
    "wof:name":"Iceel Srl",
    "wof:placetype":"venue"
},
  "geometry": {"coordinates":[14.693768,42.11887],"type":"Point"}
}