{
  "type": "Feature",
  "properties": {
    "iso:country":"IT",
    "sg:address":"110/112, Via Di Coreglia 55025 Coreglia Antelminelli",
    "sg:city":"Coreglia Antelminelli",
    "sg:classifiers":[
        {
            "category":"Manufacturing",
            "subcategory":"Paper Products",
            "type":"Manufacturing & Wholesale Goods"
        }
    ],
    "sg:phone":"+39 39058377036",
    "sg:postcode":"55025",
    "sg:province":"Lucca",
    "sg:tags":[
        "cardboard"
    ],
    "wof:name":"Scatolificio Gonnella Serafino (s.n.c.)",
    "wof:placetype":"venue"
},
  "geometry": {"coordinates":[10.5255994797,44.0611686707],"type":"Point"}
}