{
  "type": "Feature",
  "properties": {
    "iso:country":"IT",
    "sg:address":"20122 Milano",
    "sg:city":"Milano",
    "sg:orig_category":"Macchine E Forniture Per Industria Orafa E Per Orologeria",
    "sg:phone":"+39 02 804904",
    "sg:postcode":"20122",
    "sg:province":"Milano",
    "wof:name":"Dal Trozzo Luigi Ditta Di Rossana Dal Trozzo E C. (s.n.c.)",
    "wof:placetype":"venue"
},
  "geometry": {"coordinates":[9.189745,45.461033],"type":"Point"}
}