{
  "type": "Feature",
  "properties": {
    "iso:country":"IT",
    "sg:address":"Via Del Casone 71 51039 Quarrata",
    "sg:city":"Quarrata",
    "sg:classifiers":[
        {
            "category":"Wholesale",
            "subcategory":"Farm Supplies",
            "type":"Manufacturing & Wholesale Goods"
        }
    ],
    "sg:phone":"+39 0573 775676",
    "sg:postcode":"51039",
    "sg:province":"Pistoia",
    "sg:tags":[
        "agricultural",
        "part",
        "spare",
        "machinery",
        "accessory"
    ],
    "sg:website":"www.pazzaglia.it",
    "wof:name":"Pazzaglia Spa",
    "wof:placetype":"venue"
},
  "geometry": {"coordinates":[10.976597,43.866589],"type":"Point"}
}