{
  "type": "Feature",
  "properties": {
    "iso:country":"IT",
    "sg:address":"16149 Genova",
    "sg:city":"Genova",
    "sg:orig_category":"Forniture Per Attivita' Industriali",
    "sg:phone":"+39 010 413341",
    "sg:postcode":"16149",
    "sg:province":"Genova",
    "sg:website":"http://www.montiebarabino.it",
    "wof:name":"Monti & Barabino",
    "wof:placetype":"venue"
},
  "geometry": {"coordinates":[8.8933029175,44.4100074768],"type":"Point"}
}