{
  "type": "Feature",
  "properties": {
    "addr:full":"16, Via Vergnano 25125 Brescia Brescia Brescia 25125",
    "addr:postcode":"25125;25125",
    "addr:street":"Via Vergnano",
    "iso:country":"IT",
    "sg:address":"16, Via Vergnano 25125 Brescia",
    "sg:city":"Brescia",
    "sg:classifiers":[
        {
            "category":"Shopping",
            "subcategory":"Clothing, Apparel, & Fashions",
            "type":"Retail Goods"
        }
    ],
    "sg:phone":"+39 030 353 1600",
    "sg:postcode":"25125",
    "sg:province":"Brescia",
    "sg:tags":[
        "clothes"
    ],
    "wof:name":"Madras (s.r.l.)",
    "wof:placetype":"venue"
},
  "geometry": {"coordinates":[10.180795,45.533226],"type":"Point"}
}