{
  "type": "Feature",
  "properties": {
    "addr:full":"38, Via Della Stamperia 36014 Santorso Santorso Vicenza 36014",
    "addr:postcode":"36014;36014",
    "addr:street":"Via Della Stamperia",
    "iso:country":"IT",
    "sg:address":"38, Via Della Stamperia 36014 Santorso",
    "sg:city":"Santorso",
    "sg:classifiers":[
        {
            "category":"Manufacturing",
            "subcategory":"Rubber & Plastics",
            "type":"Manufacturing & Wholesale Goods"
        }
    ],
    "sg:phone":"+39 0445 641020",
    "sg:postcode":"36014",
    "sg:province":"Vicenza",
    "wof:name":"Molino Facci & Mangimi Pasubio (s.r.l.)",
    "wof:placetype":"venue"
},
  "geometry": {"coordinates":[11.376584053,45.7348670959],"type":"Point"}
}