{
  "type": "Feature",
  "properties": {
    "addr:full":"Localita' Bastardo 06030 Giano Dell'umbria Bastardo Perugia 06030",
    "addr:postcode":"06030;06030",
    "addr:street":"Localita ' Bastardo",
    "iso:country":"IT",
    "sg:address":"Localita' Bastardo 06030 Giano Dell'umbria",
    "sg:city":"Bastardo",
    "sg:classifiers":[
        {
            "category":"Parking",
            "subcategory":"Lot",
            "type":"Transportation"
        }
    ],
    "sg:phone":"+39 39074299164",
    "sg:postcode":"06030",
    "sg:province":"Perugia",
    "sg:tags":[
        "transport",
        "road"
    ],
    "wof:name":"Cooperativa Autotrasporti Gualdo C. Giano U.",
    "wof:placetype":"venue"
},
  "geometry": {"coordinates":[12.389172,43.110703],"type":"Point"}
}