{
  "type": "Feature",
  "properties": {
    "iso:country":"IT",
    "sg:address":"70, Viale Bicchierai Alessandro 51016 Montecatini Terme",
    "sg:classifiers":[
        {
            "category":"Travel",
            "subcategory":"Travel Agent",
            "type":"Entertainment"
        }
    ],
    "sg:phone":"+39 39057270086",
    "sg:postcode":"51016",
    "sg:province":"Pistoia",
    "sg:tags":[
        "business"
    ],
    "wof:name":"Albergo Brennero E Varsavia",
    "wof:placetype":"venue"
},
  "geometry": {"coordinates":[10.918524,43.932156],"type":"Point"}
}