{
  "type": "Feature",
  "properties": {
    "iso:country":"IT",
    "sg:address":"32020 Limana",
    "sg:city":"Limana",
    "sg:orig_category":"Argenteria, Oreficeria E Gioielleria - Macchine E Forniture",
    "sg:phone":"+39 0437 967422",
    "sg:postcode":"32020",
    "sg:province":"Belluno",
    "wof:name":"Tormen Guerrino & C. Snc",
    "wof:placetype":"venue"
},
  "geometry": {"coordinates":[12.156329,46.102066],"type":"Point"}
}