{
  "type": "Feature",
  "properties": {
    "iso:country":"IT",
    "sg:address":"12, Via Milano 61020 Petriano",
    "sg:city":"Petriano",
    "sg:classifiers":[
        {
            "category":"Home & Garden",
            "subcategory":"Home Furnishings",
            "type":"Retail Goods"
        }
    ],
    "sg:phone":"+39 39072252162",
    "sg:postcode":"61020",
    "sg:province":"Pesaro E Urbino",
    "sg:tags":[
        "household"
    ],
    "wof:name":"Benedetti Srl",
    "wof:placetype":"venue"
},
  "geometry": {"coordinates":[12.723715,43.788933],"type":"Point"}
}