{
  "type": "Feature",
  "properties": {
    "addr:full":"59100 Prato Prato Prato 59100",
    "addr:postcode":"59100;59100",
    "iso:country":"IT",
    "sg:address":"59100 Prato",
    "sg:city":"Prato",
    "sg:classifiers":[
        {
            "category":"Manufacturing",
            "subcategory":"Leather Goods",
            "type":"Manufacturing & Wholesale Goods"
        }
    ],
    "sg:phone":"+39 0574 690993",
    "sg:postcode":"59100",
    "sg:province":"Prato",
    "sg:tags":[
        "goods",
        "clothing",
        "supply"
    ],
    "wof:name":"Campionar Conf",
    "wof:placetype":"venue"
},
  "geometry": {"coordinates":[11.104278,43.900372],"type":"Point"}
}