{
  "type": "Feature",
  "properties": {
    "iso:country":"IT",
    "sg:address":"33030 Rive D'arcano",
    "sg:orig_category":"Bevande, Vini E Liquori. Agricoltura, Orticoltura E Floricoltura",
    "sg:phone":"+39 0432 986118",
    "sg:postcode":"33030",
    "sg:province":"Udine",
    "wof:name":"Bidoli Vini Snc Di Bidoli Margherita & C.",
    "wof:placetype":"venue"
},
  "geometry": {"coordinates":[13.032928,46.126553],"type":"Point"}
}