{
  "type": "Feature",
  "properties": {
    "addr:full":"Via Die Castani, Snc 64014 Martinsicuro Martinsicuro Teramo 64014",
    "addr:housenumber":"snc",
    "addr:postcode":"64014;64014",
    "addr:street":"Via Die Castani",
    "iso:country":"IT",
    "sg:address":"Via Die Castani, Snc 64014 Martinsicuro",
    "sg:city":"Martinsicuro",
    "sg:classifiers":[
        {
            "category":"Autos & Motor Vehicles",
            "subcategory":"Auto Supplies",
            "type":"Retail Goods"
        }
    ],
    "sg:phone":"+39 0861 761835",
    "sg:postcode":"64014",
    "sg:province":"Teramo",
    "sg:tags":[
        "automotive",
        "electronics",
        "electronic",
        "equipment"
    ],
    "sg:website":"www.masterelettronica.it",
    "wof:name":"Master Elettronica Srl",
    "wof:placetype":"venue"
},
  "geometry": {"coordinates":[13.698531,42.66127],"type":"Point"}
}