{
  "type": "Feature",
  "properties": {
    "iso:country":"IT",
    "sg:address":"00171 Roma",
    "sg:city":"Roma",
    "sg:orig_category":"Utensili Meccanici E Materiali",
    "sg:phone":"+39 06 259 2851",
    "sg:postcode":"00171",
    "sg:province":"Roma",
    "wof:name":"Elettromeccanica Sarda",
    "wof:placetype":"venue"
},
  "geometry": {"coordinates":[12.563031,41.892876],"type":"Point"}
}