{
  "type": "Feature",
  "properties": {
    "iso:country":"IT",
    "sg:address":"24040 Bonate Sotto",
    "sg:city":"Bonate Sotto",
    "sg:orig_category":"Cartotecnica E Servizi. Articoli Per Imballaggio E Confezionamento",
    "sg:phone":"+39 035 494 2272",
    "sg:postcode":"24040",
    "sg:province":"Bergamo",
    "wof:name":"Bonifaccio Walter",
    "wof:placetype":"venue"
},
  "geometry": {"coordinates":[9.559871,45.669239],"type":"Point"}
}