{
  "type": "Feature",
  "properties": {
    "iso:country":"IT",
    "sg:address":"Via Canovetti Cosimo 7 25128 Brescia",
    "sg:city":"Brescia",
    "sg:classifiers":[
        {
            "category":"Wholesale",
            "subcategory":"Auto Parts",
            "type":"Manufacturing & Wholesale Goods"
        }
    ],
    "sg:phone":"+39 030 200 2432",
    "sg:postcode":"25128",
    "sg:province":"Brescia",
    "sg:tags":[
        "wheel",
        "car",
        "alloy",
        "rims"
    ],
    "sg:website":"www.millemigliawheels.it",
    "wof:name":"Due Emme - Mille Miglia S.r.l.",
    "wof:placetype":"venue"
},
  "geometry": {"coordinates":[10.222958,45.539829],"type":"Point"}
}