{
  "type": "Feature",
  "properties": {
    "iso:country":"IT",
    "sg:address":"10141 Torino",
    "sg:city":"Torino",
    "sg:orig_category":"Dentisti Medici Chirurghi Ed Odontoiatri",
    "sg:phone":"+39 011 385 4634",
    "sg:postcode":"10141",
    "sg:province":"Torino",
    "wof:name":"Cal\u00d2 Dr. Giuseppe",
    "wof:placetype":"venue"
},
  "geometry": {"coordinates":[7.632255,45.067032],"type":"Point"}
}