{
  "type": "Feature",
  "properties": {
    "iso:country":"IT",
    "sg:address":"80134 Napoli",
    "sg:city":"Napoli",
    "sg:orig_category":"Pubblica Amministrazione",
    "sg:phone":"+39 081 420 1169",
    "sg:postcode":"80134",
    "sg:province":"Napoli",
    "wof:name":"Comando Prov. Carabinieri",
    "wof:placetype":"venue"
},
  "geometry": {"coordinates":[14.24979496,40.8448028564],"type":"Point"}
}