{
  "type": "Feature",
  "properties": {
    "iso:country":"IT",
    "sg:address":"Via Matteotti; Borgio; 17022",
    "sg:city":"Borgio",
    "sg:classifiers":[
        {
            "category":"Banks & Credit Unions",
            "subcategory":"Bank",
            "type":"Services"
        }
    ],
    "sg:phone":"+39 019 610440",
    "sg:postcode":"17022",
    "sg:province":"Savona",
    "wof:name":"Cassa Risparmio Di Savona",
    "wof:placetype":"venue"
},
  "geometry": {"coordinates":[8.307637,44.159222],"type":"Point"}
}