{
  "type": "Feature",
  "properties": {
    "iso:country":"IT",
    "sg:address":"7 Via Cernaia, 10121 Torino",
    "sg:city":"Torino",
    "sg:classifiers":[
        {
            "category":"Banks & Credit Unions",
            "subcategory":"Financial Services",
            "type":"Services"
        }
    ],
    "sg:phone":"+39 390 115 6521",
    "sg:postcode":"10121",
    "sg:province":"Torino",
    "sg:tags":[
        "banking",
        "finance",
        "insurance"
    ],
    "wof:name":"Banca Banca Del Piemonte Spa",
    "wof:placetype":"venue"
},
  "geometry": {"coordinates":[7.6767892838,45.0705451965],"type":"Point"}
}