{
  "type": "Feature",
  "properties": {
    "addr:full":"33037 Pasian Di Prato Pasian di Prato Udine 33037",
    "addr:postcode":"33037;33037",
    "iso:country":"IT",
    "sg:address":"33037 Pasian Di Prato",
    "sg:city":"Pasian di Prato",
    "sg:orig_category":"Cartotecnica E Servizi. Composizione, Stampa E Confezione. Servizi E Lavori Industria Delle Materie Plastiche. Servizi Per Imballaggio E Confezionamento",
    "sg:phone":"+39 0432 400186",
    "sg:postcode":"33037",
    "sg:province":"Udine",
    "wof:name":"Erreci Pubblicita' Di Cattarossi & C. Snc",
    "wof:placetype":"venue"
},
  "geometry": {"coordinates":[13.185373,46.078896],"type":"Point"}
}