{
  "type": "Feature",
  "properties": {
    "iso:country":"IT",
    "sg:address":"10128 Torino",
    "sg:city":"Torino",
    "sg:orig_category":"Medici. Assicurazioni E Servizi Assicurativi. Avvocati, Notai E Servizi Legali. Professionisti - Studi E Servizi Ed Associazioni Di Interesse Aziendale",
    "sg:phone":"+39 011 581 8985",
    "sg:postcode":"10128",
    "sg:province":"Torino",
    "wof:name":"Bonziglia Sergio",
    "wof:placetype":"venue"
},
  "geometry": {"coordinates":[7.6706252098,45.0583457947],"type":"Point"}
}