{
  "type": "Feature",
  "properties": {
    "iso:country":"IT",
    "sg:address":"06024 Gubbio",
    "sg:city":"Gubbio",
    "sg:orig_category":"Calzature, Pelletterie E Pelli",
    "sg:phone":"+39 075 927 3876",
    "sg:postcode":"06024",
    "sg:province":"Perugia",
    "wof:name":"Star Furs International (s.a.s.)",
    "wof:placetype":"venue"
},
  "geometry": {"coordinates":[12.582886,43.347092],"type":"Point"}
}