{
  "type": "Feature",
  "properties": {
    "addr:full":"32/e, Via Settore Sud 52028 Terranuova Bracciolini Terranuova Bracciolini Arezzo 52028",
    "addr:housenumber":"32 / e",
    "addr:postcode":"52028;52028",
    "addr:street":"Via Settore Sud",
    "iso:country":"IT",
    "sg:address":"32/e, Via Settore Sud 52028 Terranuova Bracciolini",
    "sg:city":"Terranuova Bracciolini",
    "sg:classifiers":[
        {
            "category":"Personal",
            "subcategory":"Shoe Repair & Shine",
            "type":"Services"
        }
    ],
    "sg:phone":"+39 055 919 8201",
    "sg:postcode":"52028",
    "sg:province":"Arezzo",
    "sg:tags":[
        "leather"
    ],
    "wof:name":"Calzaturificio Fada (s.r.l.)",
    "wof:placetype":"venue"
},
  "geometry": {"coordinates":[11.863062,43.471203],"type":"Point"}
}