{
  "type": "Feature",
  "properties": {
    "iso:country":"IT",
    "sg:address":"7, V. Di Basserone52041 Badia Al Pino",
    "sg:city":"Badia al Pino",
    "sg:classifiers":[
        {
            "category":"Real Estate",
            "subcategory":"Architect",
            "type":"Services"
        }
    ],
    "sg:phone":"+39 0575 410465",
    "sg:postcode":"52041",
    "sg:province":"Arezzo",
    "sg:tags":[
        "textile",
        "clothing"
    ],
    "sg:website":"http://www.stockeritalia.com:ws_end: :mark:ws:http://www.paginegialle.it/stockeritalia",
    "wof:name":"Stocker Italia Srl",
    "wof:placetype":"venue"
},
  "geometry": {"coordinates":[11.769588,43.411274],"type":"Point"}
}