{
  "type": "Feature",
  "properties": {
    "addr:full":"50038 Scarperia Scarperia Firenze 50038",
    "addr:postcode":"50038;50038",
    "iso:country":"IT",
    "sg:address":"50038 Scarperia",
    "sg:city":"Scarperia",
    "sg:classifiers":[
        {
            "category":"Manufacturing",
            "subcategory":"Metals",
            "type":"Manufacturing & Wholesale Goods"
        }
    ],
    "sg:phone":"+39 055 843 0967",
    "sg:postcode":"50038",
    "sg:province":"Firenze",
    "sg:tags":[
        "forming",
        "working",
        "welding"
    ],
    "wof:name":"Ditta Dori Carlo",
    "wof:placetype":"venue"
},
  "geometry": {"coordinates":[11.3204164505,44.0439796448],"type":"Point"}
}