{
  "type": "Feature",
  "properties": {
    "iso:country":"IT",
    "sg:address":"44, Via Cresci S. 50022 Greve In Chianti",
    "sg:city":"Greve in Chianti",
    "sg:classifiers":[
        {
            "category":"Food & Beverages",
            "subcategory":"Groceries & Convenience Stores",
            "type":"Retail Goods"
        }
    ],
    "sg:phone":"+39 39055853739",
    "sg:postcode":"50022",
    "sg:province":"Firenze",
    "sg:tags":[
        "drink"
    ],
    "wof:name":"Tenuta Vecchie Terre Di Montefili",
    "wof:placetype":"venue"
},
  "geometry": {"coordinates":[11.256902,43.768734],"type":"Point"}
}