{
  "type": "Feature",
  "properties": {
    "addr:full":"20016 Pero Pero Milano 20016",
    "addr:postcode":"20016;20016",
    "iso:country":"IT",
    "sg:address":"20016 Pero",
    "sg:city":"Pero",
    "sg:orig_category":"Carta, Cartone E Prodotti Primari. Forniture E Materiali Per Imballaggio E Confezionamento",
    "sg:phone":"+39 02 353 7181",
    "sg:postcode":"20016",
    "sg:province":"Milano",
    "wof:name":"Mactac Europe S.a.",
    "wof:placetype":"venue"
},
  "geometry": {"coordinates":[9.076962,45.499798],"type":"Point"}
}