{
  "type": "Feature",
  "properties": {
    "iso:country":"IT",
    "sg:address":"1, Via Del Macello 21046 Malnate",
    "sg:city":"Malnate",
    "sg:classifiers":[
        {
            "category":"Professional",
            "subcategory":"Engineering",
            "type":"Services"
        }
    ],
    "sg:phone":"+39 0332 425449",
    "sg:postcode":"21046",
    "sg:province":"Varese",
    "sg:tags":[
        "machine",
        "-",
        "mechanical"
    ],
    "wof:name":"Carrara Luigi Di Carrara L. & C. S.n.c.",
    "wof:placetype":"venue"
},
  "geometry": {"coordinates":[8.826385,45.817604],"type":"Point"}
}