{
  "type": "Feature",
  "properties": {
    "iso:country":"IT",
    "sg:address":"Via Scena 10 39017 Scena",
    "sg:city":"Scena",
    "sg:classifiers":[
        {
            "category":"Professional",
            "subcategory":"Employment Agencies",
            "type":"Services"
        }
    ],
    "sg:phone":"+39 0473 945545",
    "sg:postcode":"39017",
    "sg:province":"Bolzano/Bozen",
    "sg:tags":[
        "cargo"
    ],
    "sg:website":"www.nordtrans.com",
    "wof:name":"Nordtrans Srl",
    "wof:placetype":"venue"
},
  "geometry": {"coordinates":[11.177076,46.66993],"type":"Point"}
}