{
  "type": "Feature",
  "properties": {
    "iso:country":"IT",
    "sg:address":"40010 Sala Bolognese",
    "sg:city":"Sala Bolognese",
    "sg:orig_category":"Servizi E Lavori Per Edilizia E Lavori Pubblici. Servizi E Lavori Per Ecologia E Smaltimento Rifiuti",
    "sg:phone":"+39 051 681 4737",
    "sg:postcode":"40010",
    "sg:province":"Bologna",
    "sg:website":"http://www.betambiente.it",
    "wof:name":"Specialtrasporti Srl",
    "wof:placetype":"venue"
},
  "geometry": {"coordinates":[11.240767,44.580105],"type":"Point"}
}