{
  "type": "Feature",
  "properties": {
    "addr:full":"98100 Messina ME",
    "addr:postcode":"98100",
    "iso:country":"IT",
    "sg:address":"98100 Messina",
    "sg:orig_category":"Servizi Di Magazzinaggio E Movimentazione. Servizi Ausiliari Di Sorveglianza, Manutenzione E Pulizia",
    "sg:phone":"+39 090 293 8630",
    "sg:province":"ME",
    "sg:website":"http://www.gentiletraslochi.it",
    "wof:name":"Gentile Carmelo Traslochi Sas",
    "wof:placetype":"venue"
},
  "geometry": {"coordinates":[15.534369,38.157619],"type":"Point"}
}