{
  "type": "Feature",
  "properties": {
    "addr:full":"Via De' Calzolari 7/9 56022 Castelfranco Di Sotto Castelfranco di Sotto Pisa 56022",
    "addr:housenumber":"7 / 9",
    "addr:postcode":"56022;56022",
    "addr:street":"Via De ' Calzolari;Di Sotto Pisa",
    "iso:country":"IT",
    "sg:address":"Via De' Calzolari 7/9 56022 Castelfranco Di Sotto",
    "sg:city":"Castelfranco di Sotto",
    "sg:classifiers":[
        {
            "category":"Shopping",
            "subcategory":"Shoes",
            "type":"Retail Goods"
        }
    ],
    "sg:phone":"+39 0571 489030",
    "sg:postcode":"56022",
    "sg:province":"Pisa",
    "sg:tags":[
        "leather",
        "chemical",
        "product",
        "industry"
    ],
    "sg:website":"www.centralkimica.it",
    "wof:name":"Centralkimica S.p.a",
    "wof:placetype":"venue"
},
  "geometry": {"coordinates":[10.760281,43.705666],"type":"Point"}
}