{
  "type": "Feature",
  "properties": {
    "addr:full":"40128 Bologna Bologna Bologna 40128",
    "addr:postcode":"40128;40128",
    "iso:country":"IT",
    "sg:address":"40128 Bologna",
    "sg:city":"Bologna",
    "sg:orig_category":"Automazione E Macchine Per Ufficio. Forniture Industriali Per Prevenzione, Controllo E Sicurezza",
    "sg:phone":"+39 051 250408",
    "sg:postcode":"40128",
    "sg:province":"Bologna",
    "wof:name":"Teleoffice Srl",
    "wof:placetype":"venue"
},
  "geometry": {"coordinates":[11.354772,44.505596],"type":"Point"}
}