{
  "type": "Feature",
  "properties": {
    "iso:country":"IT",
    "sg:address":"125, Via Vittorio Emanuele Iii 73049 Ruffano",
    "sg:city":"Ruffano",
    "sg:classifiers":[
        {
            "category":"Personal",
            "subcategory":"Shoe Repair & Shine",
            "type":"Services"
        }
    ],
    "sg:phone":"+39 0833 690613",
    "sg:postcode":"73049",
    "sg:province":"Lecce",
    "sg:tags":[
        "leather"
    ],
    "wof:name":"Tre Emme S.r.l.",
    "wof:placetype":"venue"
},
  "geometry": {"coordinates":[18.174015,40.353291],"type":"Point"}
}