{
  "type": "Feature",
  "properties": {
    "iso:country":"IT",
    "sg:address":"Via Roma 235 10123 Torino",
    "sg:city":"Torino",
    "sg:classifiers":[
        {
            "category":"Autos & Motor Vehicles",
            "subcategory":"Auto Supplies",
            "type":"Retail Goods"
        }
    ],
    "sg:phone":"+39 011 562 2432",
    "sg:postcode":"10123",
    "sg:province":"Torino",
    "sg:tags":[
        "automobile",
        "accessory"
    ],
    "wof:name":"Euro Ricambi S.r.l.",
    "wof:placetype":"venue"
},
  "geometry": {"coordinates":[7.57748,45.02277],"type":"Point"}
}