{
  "type": "Feature",
  "properties": {
    "iso:country":"IT",
    "sg:address":"80122 Napoli",
    "sg:city":"Napoli",
    "sg:orig_category":"Articoli Carnevaleschi E Per Feste",
    "sg:phone":"+39 081 668944",
    "sg:postcode":"80122",
    "sg:province":"Napoli",
    "sg:website":"http://www.bambinosas.it",
    "wof:name":"Bambino Di Gagliardi & C. Sas",
    "wof:placetype":"venue"
},
  "geometry": {"coordinates":[14.221094,40.833252],"type":"Point"}
}