{
  "type": "Feature",
  "properties": {
    "addr:full":"Via del Parco Margherita 32 Napoli 80121",
    "addr:housenumber":"32",
    "addr:postcode":"80121",
    "addr:street":"Via Del Parco Margherita",
    "iso:country":"IT",
    "sg:address":"Via del Parco Margherita 32",
    "sg:city":"Napoli",
    "sg:classifiers":[
        {
            "category":"Professional",
            "subcategory":"Advertising",
            "type":"Services"
        }
    ],
    "sg:postcode":"80121",
    "sg:tags":[
        "web-design",
        "web-site",
        "cms",
        "seo",
        "sem",
        "web-marketing",
        "internet-marketing",
        "ppc",
        "roi",
        "internet-advertising",
        "web-application",
        "e-commerce"
    ],
    "sg:website":"http://www.meetweb.it",
    "wof:name":"Meetweb",
    "wof:placetype":"venue"
},
  "geometry": {"coordinates":[14.235889,40.838338],"type":"Point"}
}