{
  "type": "Feature",
  "properties": {
    "addr:full":"8, Via Milano 20020 Ceriano Laghetto Ceriano Laghetto Milano 20020",
    "addr:postcode":"20020;20020",
    "addr:street":"Via Milano",
    "iso:country":"IT",
    "sg:address":"8, Via Milano 20020 Ceriano Laghetto",
    "sg:city":"Ceriano Laghetto",
    "sg:classifiers":[
        {
            "category":"Shopping",
            "type":"Retail Goods"
        }
    ],
    "sg:phone":"+39 02 9646 0643",
    "sg:postcode":"20020",
    "sg:province":"Milano",
    "sg:tags":[
        "finished",
        "-",
        "metallic"
    ],
    "wof:name":"Maggioni International S.r.l.",
    "wof:placetype":"venue"
},
  "geometry": {"coordinates":[9.1012039185,45.6294975281],"type":"Point"}
}