{
  "type": "Feature",
  "properties": {
    "iso:country":"IT",
    "sg:address":"40, Via Vittorio Veneto 24030 Presezzo",
    "sg:city":"Presezzo",
    "sg:classifiers":[
        {
            "category":"Shopping",
            "subcategory":"Clothing, Apparel, & Fashions",
            "type":"Retail Goods"
        }
    ],
    "sg:phone":"+39 39035462722",
    "sg:postcode":"24030",
    "sg:province":"Bergamo",
    "sg:tags":[
        "clothes"
    ],
    "wof:name":"New Line Away (s.r.l.)",
    "wof:placetype":"venue"
},
  "geometry": {"coordinates":[9.574886,45.693203],"type":"Point"}
}