{
  "type": "Feature",
  "properties": {
    "iso:country":"IT",
    "sg:address":"40132 Bologna",
    "sg:city":"Bologna",
    "sg:orig_category":"Forniture Per Attivita' Industriali",
    "sg:phone":"+39 051 641 5006",
    "sg:postcode":"40132",
    "sg:province":"Bologna",
    "wof:name":"Serma S.r.l.",
    "wof:placetype":"venue"
},
  "geometry": {"coordinates":[11.2760715485,44.5284194946],"type":"Point"}
}