{
  "type": "Feature",
  "properties": {
    "iso:country":"IT",
    "sg:address":"00187 Roma",
    "sg:city":"Roma",
    "sg:orig_category":"Banche E Servizi Finanziari",
    "sg:phone":"+39 06 678 0056",
    "sg:postcode":"00187",
    "sg:province":"Roma",
    "wof:name":"Easy Change S.n.c.",
    "wof:placetype":"venue"
},
  "geometry": {"coordinates":[12.484404,41.901119],"type":"Point"}
}