{
  "type": "Feature",
  "properties": {
    "addr:full":"21040 Venegono Superiore Venegono Superiore Varese 21040",
    "addr:postcode":"21040;21040",
    "iso:country":"IT",
    "sg:address":"21040 Venegono Superiore",
    "sg:city":"Venegono Superiore",
    "sg:orig_category":"Abbigliamento Intimo, Calze E Costumi Da Bagno",
    "sg:phone":"+39 0331 824877",
    "sg:postcode":"21040",
    "sg:province":"Varese",
    "wof:name":"Textilross Srl",
    "wof:placetype":"venue"
},
  "geometry": {"coordinates":[8.894585,45.756096],"type":"Point"}
}