{
  "type": "Feature",
  "properties": {
    "iso:country":"IT",
    "sg:address":"43, Viale Del Lavoro 25045 Castegnato",
    "sg:city":"Castegnato",
    "sg:classifiers":[
        {
            "category":"Manufacturing",
            "subcategory":"Metals",
            "type":"Manufacturing & Wholesale Goods"
        }
    ],
    "sg:phone":"+39 030 214 8100",
    "sg:postcode":"25045",
    "sg:province":"Brescia",
    "sg:tags":[
        "metallurgy",
        "metalworking"
    ],
    "wof:name":"Brelasco",
    "wof:placetype":"venue"
},
  "geometry": {"coordinates":[10.1041822433,45.5339927673],"type":"Point"}
}