{
  "type": "Feature",
  "properties": {
    "iso:country":"IT",
    "sg:address":"205/15, Via Sansovino 10151 Torino",
    "sg:city":"Torino",
    "sg:classifiers":[
        {
            "category":"Manufacturing",
            "subcategory":"Metals",
            "type":"Manufacturing & Wholesale Goods"
        }
    ],
    "sg:phone":"+39 011 739 5300",
    "sg:postcode":"10151",
    "sg:province":"Torino",
    "sg:tags":[
        "processing"
    ],
    "wof:name":"Fils - Audino (s.p.a.)",
    "wof:placetype":"venue"
},
  "geometry": {"coordinates":[7.6492724419,45.1077880859],"type":"Point"}
}