{
  "type": "Feature",
  "properties": {
    "addr:full":"Via Legione Ceccopieri 2 26100 Cremona Cremona Cremona 26100",
    "addr:housenumber":"2",
    "addr:postcode":"26100;26100",
    "addr:street":"Via Legione Ceccopieri",
    "iso:country":"IT",
    "sg:address":"Via Legione Ceccopieri 2 26100 Cremona",
    "sg:city":"Cremona",
    "sg:classifiers":[
        {
            "category":"Bakery",
            "type":"Food & Drink"
        }
    ],
    "sg:phone":"+39 0372 450374",
    "sg:postcode":"26100",
    "sg:province":"Cremona",
    "sg:tags":[
        "pastry"
    ],
    "sg:website":"www.nuovaruggeri.com",
    "wof:name":"Nuova Ruggeri Srl",
    "wof:placetype":"venue"
},
  "geometry": {"coordinates":[10.0299348831,45.1451530457],"type":"Point"}
}