{
  "type": "Feature",
  "properties": {
    "addr:full":"59013 Montemurlo Montemurlo Prato 59013",
    "addr:postcode":"59013;59013",
    "iso:country":"IT",
    "sg:address":"59013 Montemurlo",
    "sg:city":"Montemurlo",
    "sg:orig_category":"Macchine Tessili",
    "sg:phone":"+39 0574 651256",
    "sg:postcode":"59013",
    "sg:province":"Prato",
    "wof:name":"Officine Meccaniche Videma Di Macchi Pietro & C. Snc",
    "wof:placetype":"venue"
},
  "geometry": {"coordinates":[11.045253,43.906033],"type":"Point"}
}