{
  "type": "Feature",
  "properties": {
    "iso:country":"IT",
    "sg:address":"34/a, Via Leone Carlo 10098 Rivoli",
    "sg:city":"Rivoli",
    "sg:classifiers":[
        {
            "category":"Manufacturing",
            "subcategory":"Metals",
            "type":"Manufacturing & Wholesale Goods"
        }
    ],
    "sg:phone":"+39 011 959 7252",
    "sg:postcode":"10098",
    "sg:province":"Torino",
    "sg:tags":[
        "metallurgy",
        "metalworking"
    ],
    "wof:name":"Baico Trading S.r.l.",
    "wof:placetype":"venue"
},
  "geometry": {"coordinates":[7.5465688705,45.0616531372],"type":"Point"}
}