{
  "type": "Feature",
  "properties": {
    "iso:country":"IT",
    "sg:address":"25036 Palazzolo Sull'oglio",
    "sg:orig_category":"Macchine, Impianti Ed Attrezzature Per Abbigliamento E Pelletterie",
    "sg:phone":"+39 030 732809",
    "sg:postcode":"25036",
    "sg:province":"Brescia",
    "wof:name":"Morandi Guglielmo",
    "wof:placetype":"venue"
},
  "geometry": {"coordinates":[9.879304,45.627823],"type":"Point"}
}