{
  "type": "Feature",
  "properties": {
    "iso:country":"IT",
    "sg:address":"20122 Milano",
    "sg:city":"Milano",
    "sg:classifiers":[
        {
            "category":"Restaurant",
            "type":"Food & Drink"
        }
    ],
    "sg:phone":"+39 02 5831 4122",
    "sg:postcode":"20122",
    "sg:province":"Milano",
    "sg:tags":[
        "auxiliary",
        "entertainment",
        "premises",
        "related",
        "catering",
        "similar",
        "public",
        "restaurants"
    ],
    "wof:name":"Elle Bi Snc",
    "wof:placetype":"venue"
},
  "geometry": {"coordinates":[9.200422,45.461826],"type":"Point"}
}