{
  "type": "Feature",
  "properties": {
    "iso:country":"IT",
    "sg:address":"10126 Torino",
    "sg:city":"Torino",
    "sg:orig_category":"Motori Ed Organi Di Trasmissione. Ricambi E Componenti Dei Mezzi Di Trasporto",
    "sg:phone":"+39 011 655497",
    "sg:postcode":"10126",
    "sg:province":"Torino",
    "wof:name":"Comelli Roberto",
    "wof:placetype":"venue"
},
  "geometry": {"coordinates":[7.5533671379,45.0109863281],"type":"Point"}
}