{
  "type": "Feature",
  "properties": {
    "iso:country":"IT",
    "sg:address":"03043 Cassino",
    "sg:city":"Cassino",
    "sg:orig_category":"Materiali Semilavorati Metallici",
    "sg:phone":"+39 0776 280744",
    "sg:postcode":"03043",
    "sg:province":"Frosinone",
    "wof:name":"C.m.a. Srl",
    "wof:placetype":"venue"
},
  "geometry": {"coordinates":[13.83322,41.486694],"type":"Point"}
}