{
  "type": "Feature",
  "properties": {
    "iso:country":"IT",
    "sg:address":"59100 Prato",
    "sg:city":"Prato",
    "sg:orig_category":"Abbigliamento Industria - Macchine Ed Attrezzature",
    "sg:phone":"+39 0574 620484",
    "sg:postcode":"59100",
    "sg:province":"Prato",
    "wof:name":"R.t.m. Sas",
    "wof:placetype":"venue"
},
  "geometry": {"coordinates":[11.093808,43.878033],"type":"Point"}
}