{
  "type": "Feature",
  "properties": {
    "addr:full":"37, Via Torino 70031 Andria Andria Bari 70031",
    "addr:postcode":"70031;70031",
    "addr:street":"Via Torino",
    "iso:country":"IT",
    "sg:address":"37, Via Torino 70031 Andria",
    "sg:city":"Andria",
    "sg:classifiers":[
        {
            "category":"Shopping",
            "subcategory":"Clothing, Apparel, & Fashions",
            "type":"Retail Goods"
        }
    ],
    "sg:phone":"+39 0883 597111",
    "sg:postcode":"70031",
    "sg:province":"Bari",
    "sg:tags":[
        "clothes"
    ],
    "wof:name":"Merafina Carlo (s.r.l.)",
    "wof:placetype":"venue"
},
  "geometry": {"coordinates":[16.300137,41.229671],"type":"Point"}
}