{
  "type": "Feature",
  "properties": {
    "iso:country":"IT",
    "sg:address":"06132 Perugia",
    "sg:city":"Perugia",
    "sg:orig_category":"Ristorazione E Locali Pubblici Affini. Servizi Ausiliari Di Ristorazione E Di Intrattenimento",
    "sg:phone":"+39 075 528 7311",
    "sg:postcode":"06132",
    "sg:province":"Perugia",
    "wof:name":"Master Chef Srl",
    "wof:placetype":"venue"
},
  "geometry": {"coordinates":[12.336421,43.078934],"type":"Point"}
}