{
  "type": "Feature",
  "properties": {
    "iso:country":"IT",
    "sg:address":"89131 Reggio Calabria",
    "sg:orig_category":"Telecomunicazioni E Telefonia, Impianti, Apparecchi E Servizi",
    "sg:phone":"+39 0965 592777",
    "sg:province":"RC",
    "sg:website":"http://www.sicet.it",
    "wof:name":"S.i.c.e.t. Srl",
    "wof:placetype":"venue"
},
  "geometry": {"coordinates":[15.705779,38.07579],"type":"Point"}
}