{
  "type": "Feature",
  "properties": {
    "iso:country":"IT",
    "sg:address":"20062 Cassano D'adda",
    "sg:orig_category":"Servizi E Lavori Per Arredamento E Industria Del Legno. Servizi E Lavori Per Edilizia E Lavori Pubblici. Arte Ed Artigianato Artistico",
    "sg:phone":"+39 036 336 1777",
    "sg:postcode":"20062",
    "sg:province":"Milano",
    "wof:name":"Umidbloc Srl",
    "wof:placetype":"venue"
},
  "geometry": {"coordinates":[9.508604,45.517723],"type":"Point"}
}