{
  "type": "Feature",
  "properties": {
    "iso:country":"IT",
    "sg:address":"00037 Segni",
    "sg:city":"Segni",
    "sg:orig_category":"Materiali Semilavorati Metallici",
    "sg:phone":"+39 06 978 0910",
    "sg:postcode":"00037",
    "sg:province":"Roma",
    "wof:name":"Salvitti Anna",
    "wof:placetype":"venue"
},
  "geometry": {"coordinates":[13.001133,41.683338],"type":"Point"}
}