{
  "type": "Feature",
  "properties": {
    "iso:country":"IT",
    "sg:address":"25030 Castrezzato",
    "sg:city":"Castrezzato",
    "sg:orig_category":"Servizi E Lavori Per Edilizia E Lavori Pubblici",
    "sg:phone":"+39 030 714597",
    "sg:postcode":"25030",
    "sg:province":"Brescia",
    "wof:name":"Molari Luciano",
    "wof:placetype":"venue"
},
  "geometry": {"coordinates":[10.200047,45.558712],"type":"Point"}
}