{
  "type": "Feature",
  "properties": {
    "iso:country":"IT",
    "sg:address":"37039 Tregnago",
    "sg:city":"Tregnago",
    "sg:orig_category":"Abbigliamento - Produzione E Ingrosso",
    "sg:phone":"+39 045 780 8128",
    "sg:postcode":"37039",
    "sg:province":"Verona",
    "wof:name":"Salgari Snc",
    "wof:placetype":"venue"
},
  "geometry": {"coordinates":[11.171547,45.537125],"type":"Point"}
}