{
  "type": "Feature",
  "properties": {
    "iso:country":"IT",
    "sg:address":"25065 Lumezzane",
    "sg:city":"Lumezzane",
    "sg:orig_category":"Prodotti E Manufatti In Materie Plastiche",
    "sg:phone":"+39 030 827396",
    "sg:postcode":"25065",
    "sg:province":"Brescia",
    "wof:name":"Serraino Tecnopolimeri (s.n.c.)",
    "wof:placetype":"venue"
},
  "geometry": {"coordinates":[10.2804574966,45.6529388428],"type":"Point"}
}