{
  "type": "Feature",
  "properties": {
    "iso:country":"IT",
    "sg:address":"20062 Cassano D'adda",
    "sg:orig_category":"Audiovisivi Filmati, Spot E Multimediali - Realizzazione E Duplicazione",
    "sg:phone":"+39 036 336 1467",
    "sg:postcode":"20062",
    "sg:province":"Milano",
    "wof:name":"Multilogos Srl",
    "wof:placetype":"venue"
},
  "geometry": {"coordinates":[9.515581,45.53096],"type":"Point"}
}