{
  "type": "Feature",
  "properties": {
    "addr:full":"65015 Montesilvano Montesilvano Pescara 65015",
    "addr:postcode":"65015;65015",
    "iso:country":"IT",
    "sg:address":"65015 Montesilvano",
    "sg:city":"Montesilvano",
    "sg:orig_category":"Fognature",
    "sg:phone":"+39 085 468 0627",
    "sg:postcode":"65015",
    "sg:province":"Pescara",
    "wof:name":"Pescara Spurgo Srl",
    "wof:placetype":"venue"
},
  "geometry": {"coordinates":[14.1349849701,42.480014801],"type":"Point"}
}