{
  "type": "Feature",
  "properties": {
    "addr:full":"Via Serracavallo Km 4 03043 Cassino Cassino Frosinone 03043",
    "addr:postcode":"03043;03043",
    "addr:street":"Via Serracavallo Km 4",
    "iso:country":"IT",
    "sg:address":"Via Serracavallo Km 4 03043 Cassino",
    "sg:city":"Cassino",
    "sg:classifiers":[
        {
            "category":"Banks & Credit Unions",
            "subcategory":"Investment Brokerage",
            "type":"Services"
        }
    ],
    "sg:phone":"+39 0776 21960",
    "sg:postcode":"03043",
    "sg:province":"Frosinone",
    "sg:tags":[
        "work",
        "marble"
    ],
    "wof:name":"F.lli Salvatore Ind. Marmi Srl",
    "wof:placetype":"venue"
},
  "geometry": {"coordinates":[13.351902,41.640137],"type":"Point"}
}