{
  "type": "Feature",
  "properties": {
    "iso:country":"IT",
    "sg:address":"32014 Ponte Nelle Alpi",
    "sg:city":"Ponte nelle Alpi",
    "sg:orig_category":"Materiali Edili",
    "sg:phone":"+39 0437 900148",
    "sg:postcode":"32014",
    "sg:province":"Belluno",
    "wof:name":"Nogare' Mirto",
    "wof:placetype":"venue"
},
  "geometry": {"coordinates":[12.30944,46.1544],"type":"Point"}
}