{
  "type": "Feature",
  "properties": {
    "addr:full":"21, Via Don M. Mauri 22060 Cabiate Cabiate Como 22060",
    "addr:postcode":"22060;22060",
    "addr:street":"Via Don M. Mauri",
    "iso:country":"IT",
    "sg:address":"21, Via Don M. Mauri 22060 Cabiate",
    "sg:city":"Cabiate",
    "sg:classifiers":[
        {
            "category":"Sports & Exercise",
            "subcategory":"Playing Field",
            "type":"Entertainment"
        }
    ],
    "sg:phone":"+39 39031766277",
    "sg:postcode":"22060",
    "sg:province":"Como",
    "sg:tags":[
        "game"
    ],
    "wof:name":"Galli",
    "wof:placetype":"venue"
},
  "geometry": {"coordinates":[9.085456,45.811966],"type":"Point"}
}