{
  "type": "Feature",
  "properties": {
    "addr:full":"03024 Ceprano Ceprano Frosinone 03024",
    "addr:postcode":"03024;03024",
    "iso:country":"IT",
    "sg:address":"03024 Ceprano",
    "sg:city":"Ceprano",
    "sg:orig_category":"Nautica. Ricambi E Componenti Dei Mezzi Di Trasporto",
    "sg:phone":"+39 0775 918050",
    "sg:postcode":"03024",
    "sg:province":"Frosinone",
    "wof:name":"Eddy Moto Srl",
    "wof:placetype":"venue"
},
  "geometry": {"coordinates":[13.5282478333,41.5376014709],"type":"Point"}
}