{
  "type": "Feature",
  "properties": {
    "iso:country":"IT",
    "sg:address":"73049 Ruffano",
    "sg:city":"Ruffano",
    "sg:orig_category":"Petroli, Gas E Combustibili",
    "sg:phone":"+39 0833 691593",
    "sg:postcode":"73049",
    "sg:province":"Lecce",
    "wof:name":"Toma Carburanti Srl",
    "wof:placetype":"venue"
},
  "geometry": {"coordinates":[18.1605854034,40.0126190186],"type":"Point"}
}