{
  "type": "Feature",
  "properties": {
    "addr:full":"181, V. Vittorio Emanuele 13049 Tronzano Vercellese Tronzano Vercellese Vercelli 13049",
    "addr:housenumber":"181",
    "addr:postcode":"13049;13049",
    "addr:street":"V. Vittorio Emanuele;Vercellese",
    "iso:country":"IT",
    "sg:address":"181, V. Vittorio Emanuele 13049 Tronzano Vercellese",
    "sg:city":"Tronzano Vercellese",
    "sg:orig_category":"Miscellaneous Products",
    "sg:phone":"+39 0161 911606",
    "sg:postcode":"13049",
    "sg:province":"Vercelli",
    "sg:website":"http://www.luvertinsas.it",
    "wof:name":"Luvertin Sas",
    "wof:placetype":"venue"
},
  "geometry": {"coordinates":[8.4263935089,45.3210601807],"type":"Point"}
}