{
  "type": "Feature",
  "properties": {
    "addr:full":"34018 San Dorligo Della Valle San Dorligo della Valle Trieste 34018",
    "addr:postcode":"34018;dorligo della valle san;34018",
    "addr:street":"San",
    "iso:country":"IT",
    "sg:address":"34018 San Dorligo Della Valle",
    "sg:city":"San Dorligo della Valle",
    "sg:orig_category":"Servizi Di Magazzinaggio E Movimentazione. Servizi Ausiliari Di Sorveglianza, Manutenzione E Pulizia. Servizi Per Aziende, Manifestazioni E Supporto Agli Scambi Commerciali",
    "sg:phone":"+39 040 832 5089",
    "sg:postcode":"34018",
    "sg:province":"Trieste",
    "sg:website":"http://www.workservice.net",
    "wof:name":"Work Service Scrl",
    "wof:placetype":"venue"
},
  "geometry": {"coordinates":[13.857952,45.601021],"type":"Point"}
}