{
  "type": "Feature",
  "properties": {
    "iso:country":"IT",
    "sg:address":"21, Via L. Romagnoli 43030 Torrile",
    "sg:classifiers":[
        {
            "category":"Wholesale",
            "subcategory":"Drugs",
            "type":"Manufacturing & Wholesale Goods"
        }
    ],
    "sg:phone":"+39 0521 819101",
    "sg:postcode":"43030",
    "sg:province":"Parma",
    "sg:tags":[
        "chemical",
        "pharmaceutical"
    ],
    "wof:name":"Reichhold S.r.l.",
    "wof:placetype":"venue"
},
  "geometry": {"coordinates":[10.36561,44.898914],"type":"Point"}
}