{
  "type": "Feature",
  "properties": {
    "addr:full":"Via Tambarin 16 34077 Ronchi Dei Legionari Ronchi dei Legionari Gorizia 34077",
    "addr:housenumber":"16",
    "addr:postcode":"34077;34077",
    "addr:street":"Via Tambarin",
    "iso:country":"IT",
    "sg:address":"Via Tambarin 16 34077 Ronchi Dei Legionari",
    "sg:city":"Ronchi dei Legionari",
    "sg:orig_category":"Fish, Frozen",
    "sg:phone":"+39 0481 474884",
    "sg:postcode":"34077",
    "sg:province":"Gorizia",
    "sg:website":"www.frigonord.com",
    "wof:name":"Frigo Nord 1 Srl",
    "wof:placetype":"venue"
},
  "geometry": {"coordinates":[13.4750328064,45.8225708008],"type":"Point"}
}