{
  "type": "Feature",
  "properties": {
    "iso:country":"IT",
    "sg:address":"Via Xxv Aprile 47 37010 Cavalcaselle",
    "sg:classifiers":[
        {
            "category":"Health Services",
            "subcategory":"Medical Lab",
            "type":"Services"
        }
    ],
    "sg:phone":"+39 045 640 0865",
    "sg:postcode":"37010",
    "sg:province":"Verona",
    "sg:tags":[
        "laboratory",
        "dental",
        "equipment"
    ],
    "sg:website":"www.orotig.com",
    "wof:name":"Orotig Srl",
    "wof:placetype":"venue"
},
  "geometry": {"coordinates":[10.991748,45.438366],"type":"Point"}
}