{
  "type": "Feature",
  "properties": {
    "iso:country":"IT",
    "sg:address":"37050 Belfiore",
    "sg:city":"Belfiore",
    "sg:orig_category":"Macchine, Impianti Ed Attrezzature Industria Chimica",
    "sg:phone":"+39 045 764 0150",
    "sg:postcode":"37050",
    "sg:province":"Verona",
    "wof:name":"Promac Srl",
    "wof:placetype":"venue"
},
  "geometry": {"coordinates":[11.215466,45.396114],"type":"Point"}
}