{
  "type": "Feature",
  "properties": {
    "iso:country":"IT",
    "sg:address":"20125 Milano",
    "sg:city":"Milano",
    "sg:orig_category":"Servizi Editoriali",
    "sg:phone":"+39 02 2614 9008",
    "sg:postcode":"20125",
    "sg:province":"Milano",
    "wof:name":"Milan E Media Andbook Service Srl",
    "wof:placetype":"venue"
},
  "geometry": {"coordinates":[9.215603,45.493999],"type":"Point"}
}