{
  "type": "Feature",
  "properties": {
    "iso:country":"IT",
    "sg:address":"10131 Torino",
    "sg:city":"Torino",
    "sg:orig_category":"Pasticceria E Confetteria Prodotti - Produzione E Ingrosso",
    "sg:phone":"+39 011 819 4319",
    "sg:postcode":"10131",
    "sg:province":"Torino",
    "wof:name":"Medico Di Medico Francesco & C. S.n.c.",
    "wof:placetype":"venue"
},
  "geometry": {"coordinates":[7.7037539482,45.0637779236],"type":"Point"}
}