{
  "type": "Feature",
  "properties": {
    "iso:country":"IT",
    "sg:address":"24040 Ciserano",
    "sg:city":"Ciserano",
    "sg:orig_category":"Prodotti Alimentari",
    "sg:phone":"+39 035 882121",
    "sg:postcode":"24040",
    "sg:province":"Bergamo",
    "wof:name":"Grissinificio Zingonia (s.r.l.)",
    "wof:placetype":"venue"
},
  "geometry": {"coordinates":[9.6044206619,45.5896377563],"type":"Point"}
}