{
  "type": "Feature",
  "properties": {
    "addr:full":"20122 Milano Milano Milano 20122",
    "addr:postcode":"20122;20122",
    "iso:country":"IT",
    "sg:address":"20122 Milano",
    "sg:city":"Milano",
    "sg:classifiers":[
        {
            "category":"Health Services",
            "subcategory":"Nursing And Care Facility",
            "type":"Services"
        }
    ],
    "sg:phone":"+39 02 541761",
    "sg:postcode":"20122",
    "sg:province":"Milano",
    "sg:tags":[
        "case",
        "cura",
        "private",
        "di"
    ],
    "wof:name":"Istituto Stomatologico Italiano Srl",
    "wof:placetype":"venue"
},
  "geometry": {"coordinates":[9.203462,45.457687],"type":"Point"}
}