{
  "type": "Feature",
  "properties": {
    "iso:country":"IT",
    "sg:address":"20154 Milano",
    "sg:city":"Milano",
    "sg:orig_category":"Banche E Servizi Finanziari",
    "sg:phone":"+39 02 2900 2108",
    "sg:postcode":"20154",
    "sg:province":"Milano",
    "wof:name":"Ottagono Secondo Cortile S.a.s.",
    "wof:placetype":"venue"
},
  "geometry": {"coordinates":[9.181602,45.482914],"type":"Point"}
}