{
  "type": "Feature",
  "properties": {
    "addr:full":"20010 Cornaredo Cornaredo Milano 20010",
    "addr:postcode":"20010;20010",
    "iso:country":"IT",
    "sg:address":"20010 Cornaredo",
    "sg:city":"Cornaredo",
    "sg:orig_category":"Ospedali E Servizi Sanitari",
    "sg:phone":"+39 02 9356 9180",
    "sg:postcode":"20010",
    "sg:province":"Milano",
    "wof:name":"Municipio",
    "wof:placetype":"venue"
},
  "geometry": {"coordinates":[9.011911,45.485588],"type":"Point"}
}