{
  "type": "Feature",
  "properties": {
    "addr:full":"Piazza Municipio, 5; Rieti; 02100 Rieti Rieti 02100",
    "addr:housenumber":"5",
    "addr:postcode":"02100;02100",
    "addr:street":"Piazza Municipio",
    "iso:country":"IT",
    "sg:address":"Piazza Municipio, 5; Rieti; 02100",
    "sg:city":"Rieti",
    "sg:classifiers":[
        {
            "category":"Banks & Credit Unions",
            "subcategory":"Bank",
            "type":"Services"
        }
    ],
    "sg:phone":"+39 0765 29014",
    "sg:postcode":"02100",
    "sg:province":"Rieti",
    "wof:name":"Banca Popolare",
    "wof:placetype":"venue"
},
  "geometry": {"coordinates":[12.692663,42.321281],"type":"Point"}
}