{
  "type": "Feature",
  "properties": {
    "iso:country":"IT",
    "sg:address":"20063 Cernusco Sul Naviglio",
    "sg:city":"Cernusco sul Naviglio",
    "sg:orig_category":"Materiali E Componenti Elettrotecnici",
    "sg:phone":"+39 02 9211 8105",
    "sg:postcode":"20063",
    "sg:province":"Milano",
    "wof:name":"Italsmea",
    "wof:placetype":"venue"
},
  "geometry": {"coordinates":[9.333385,45.534874],"type":"Point"}
}