{
  "type": "Feature",
  "properties": {
    "addr:full":"15, Via Della Fontanella 00187 Roma Roma Roma 00187",
    "addr:postcode":"00187;00187",
    "addr:street":"Via Della Fontanella",
    "iso:country":"IT",
    "sg:address":"15, Via Della Fontanella 00187 Roma",
    "sg:city":"Roma",
    "sg:classifiers":[
        {
            "category":"Travel",
            "subcategory":"Travel Agent",
            "type":"Entertainment"
        }
    ],
    "sg:phone":"+39 39063611998",
    "sg:postcode":"00187",
    "sg:province":"Roma",
    "sg:tags":[
        "business"
    ],
    "wof:name":"Hotel Valadier",
    "wof:placetype":"venue"
},
  "geometry": {"coordinates":[12.477502,41.90926],"type":"Point"}
}