{
  "type": "Feature",
  "properties": {
    "iso:country":"IT",
    "sg:address":"25135 Brescia",
    "sg:city":"Brescia",
    "sg:orig_category":"Registrazione Sonora - Sale Prova",
    "sg:phone":"+39 030 336 3041",
    "sg:postcode":"25135",
    "sg:province":"Brescia",
    "wof:name":"Bontempi Maria",
    "wof:placetype":"venue"
},
  "geometry": {"coordinates":[10.285708,45.515762],"type":"Point"}
}