{
  "type": "Feature",
  "properties": {
    "iso:country":"IT",
    "sg:address":"40065 Pianoro",
    "sg:city":"Pianoro",
    "sg:orig_category":"Agricoltura, Orticoltura E Floricoltura. Articoli Da Regalo",
    "sg:phone":"+39 051 777906",
    "sg:postcode":"40065",
    "sg:province":"Bologna",
    "wof:name":"Az. Agricola D&d Garden",
    "wof:placetype":"venue"
},
  "geometry": {"coordinates":[11.264565,44.423771],"type":"Point"}
}