{
  "type": "Feature",
  "properties": {
    "iso:country":"IT",
    "sg:address":"31020 Villorba",
    "sg:city":"Lancenigo",
    "sg:orig_category":"Elettrotecnica Industriale, Prodotti E Apparecchiature",
    "sg:phone":"+39 0422 6155",
    "sg:postcode":"31020",
    "sg:province":"Treviso",
    "sg:website":"http://www.lelux.it",
    "wof:name":"Le Lux Spa",
    "wof:placetype":"venue"
},
  "geometry": {"coordinates":[12.255618,45.719898],"type":"Point"}
}