{
  "type": "Feature",
  "properties": {
    "addr:full":"20149 Milano Milano Milano 20149",
    "addr:postcode":"20149;20149",
    "iso:country":"IT",
    "sg:address":"20149 Milano",
    "sg:city":"Milano",
    "sg:orig_category":"Termotecnica E Riscaldamento, Apparecchiature E Servizi",
    "sg:phone":"+39 02 331 9621",
    "sg:postcode":"20149",
    "sg:province":"Milano",
    "wof:name":"Zanocco Antonio Marco",
    "wof:placetype":"venue"
},
  "geometry": {"coordinates":[9.15619,45.486046],"type":"Point"}
}