{
  "type": "Feature",
  "properties": {
    "iso:country":"IT",
    "sg:address":"35037 Teolo",
    "sg:city":"Teolo",
    "sg:orig_category":"Gioielleria, Oreficeria E Argenteria",
    "sg:phone":"+39 049 990 0124",
    "sg:postcode":"35037",
    "sg:province":"Padova",
    "wof:name":"Fratelli Calegaro Spa",
    "wof:placetype":"venue"
},
  "geometry": {"coordinates":[11.792189,45.387203],"type":"Point"}
}