{
  "type": "Feature",
  "properties": {
    "iso:country":"IT",
    "sg:address":"43, Via Ca' Di Aprili - Ca' Di David 37061 Verona",
    "sg:classifiers":[
        {
            "category":"Manufacturing",
            "subcategory":"Paper Products",
            "type":"Manufacturing & Wholesale Goods"
        }
    ],
    "sg:phone":"+39 045 829 0711",
    "sg:province":"VR",
    "sg:tags":[
        "cardboard"
    ],
    "wof:name":"Cartiera Di Cadidavid S.r.l.",
    "wof:placetype":"venue"
},
  "geometry": {"coordinates":[11.0031442642,45.3825454712],"type":"Point"}
}