{
  "type": "Feature",
  "properties": {
    "iso:country":"IT",
    "sg:address":"39030 San Lorenzo Di Sebato",
    "sg:city":"San Lorenzo di Sebato",
    "sg:orig_category":"Materiali Edili",
    "sg:phone":"+39 0474 479500",
    "sg:postcode":"39030",
    "sg:province":"Bolzano/Bozen",
    "wof:name":"Rienz Beton Srl",
    "wof:placetype":"venue"
},
  "geometry": {"coordinates":[11.910592,46.78677],"type":"Point"}
}