{
  "type": "Feature",
  "properties": {
    "addr:full":"36030 Zugliano Zugliano Vicenza 36030",
    "addr:postcode":"36030;36030",
    "iso:country":"IT",
    "sg:address":"36030 Zugliano",
    "sg:city":"Zugliano",
    "sg:orig_category":"Minuterie Di Precisione",
    "sg:phone":"+39 0445 368327",
    "sg:postcode":"36030",
    "sg:province":"Vicenza",
    "wof:name":"Gasparella Giovanni",
    "wof:placetype":"venue"
},
  "geometry": {"coordinates":[11.4955015182,45.7272567749],"type":"Point"}
}