{
  "type": "Feature",
  "properties": {
    "iso:country":"IT",
    "sg:address":"80010 Quarto",
    "sg:city":"Quarto",
    "sg:orig_category":"Bevande, Vini E Liquori",
    "sg:phone":"+39 081 876 4463",
    "sg:postcode":"80010",
    "sg:province":"Napoli",
    "wof:name":"Helios Di Lucio Troise E C",
    "wof:placetype":"venue"
},
  "geometry": {"coordinates":[14.145821,40.879066],"type":"Point"}
}