{
  "type": "Feature",
  "properties": {
    "iso:country":"IT",
    "sg:address":"16129 Genova",
    "sg:city":"Genova",
    "sg:orig_category":"Prodotti Chimici Secondari. Prodotti Cosmetici E Da Toeletta",
    "sg:phone":"+39 010 317836",
    "sg:postcode":"16129",
    "sg:province":"Genova",
    "wof:name":"La Profumeria Matta",
    "wof:placetype":"venue"
},
  "geometry": {"coordinates":[8.9523429871,44.4012565613],"type":"Point"}
}