{
  "type": "Feature",
  "properties": {
    "iso:country":"IT",
    "sg:address":"41, Via Manfredi 38057 Pergine Valsugana",
    "sg:city":"Pergine Valsugana",
    "sg:classifiers":[
        {
            "category":"Building & Trades",
            "subcategory":"Construction",
            "type":"Services"
        }
    ],
    "sg:phone":"+39 0461 532322",
    "sg:postcode":"38057",
    "sg:province":"Trento",
    "sg:tags":[
        "work",
        "public"
    ],
    "wof:name":"Morelli S.r.l.",
    "wof:placetype":"venue"
},
  "geometry": {"coordinates":[11.203329,46.080849],"type":"Point"}
}