{
  "type": "Feature",
  "properties": {
    "iso:country":"IT",
    "sg:address":"29010 Castelvetro Piacentino",
    "sg:city":"Castelvetro Piacentino",
    "sg:orig_category":"Abbigliamento Esterno, Maglierie E Pelliccerie. Shopping",
    "sg:phone":"+39 0523 825019",
    "sg:postcode":"29010",
    "sg:province":"Piacenza",
    "wof:name":"Media Srl",
    "wof:placetype":"venue"
},
  "geometry": {"coordinates":[9.987891,45.10281],"type":"Point"}
}