{
  "type": "Feature",
  "properties": {
    "iso:country":"IT",
    "sg:address":"26815 Massalengo",
    "sg:city":"Massalengo",
    "sg:orig_category":"Trasporti E Spedizioni Merci",
    "sg:phone":"+39 0371 481082",
    "sg:postcode":"26815",
    "sg:province":"Lodi",
    "sg:website":"http://www.capuanodistribuzione.it",
    "wof:name":"Cdf Srl",
    "wof:placetype":"venue"
},
  "geometry": {"coordinates":[9.502068,45.257996],"type":"Point"}
}