{
  "type": "Feature",
  "properties": {
    "iso:country":"IT",
    "sg:address":"00133 Roma",
    "sg:city":"Roma",
    "sg:orig_category":"Termotecnica E Riscaldamento, Apparecchiature E Servizi",
    "sg:phone":"+39 06 202 1661",
    "sg:postcode":"00133",
    "sg:province":"Roma",
    "wof:name":"Casella Ciro",
    "wof:placetype":"venue"
},
  "geometry": {"coordinates":[12.633103,41.862022],"type":"Point"}
}