{
  "type": "Feature",
  "properties": {
    "addr:full":"39023 Lasa Lasa Bolzano/Bozen 39023",
    "addr:postcode":"39023;39023",
    "iso:country":"IT",
    "sg:address":"39023 Lasa",
    "sg:city":"Lasa",
    "sg:orig_category":"Petroli, Gas E Combustibili. Termotecnica E Riscaldamento, Apparecchiature E Servizi",
    "sg:phone":"+39 0473 739921",
    "sg:postcode":"39023",
    "sg:province":"Bolzano/Bozen",
    "wof:name":"Sch\u00d6nthaler Gentilini Srl",
    "wof:placetype":"venue"
},
  "geometry": {"coordinates":[10.7024068832,46.6165657043],"type":"Point"}
}