{
  "type": "Feature",
  "properties": {
    "iso:country":"IT",
    "sg:address":"23851 Galbiate",
    "sg:city":"Galbiate",
    "sg:orig_category":"Materiali Semilavorati Metallici",
    "sg:phone":"+39 0341 540526",
    "sg:postcode":"23851",
    "sg:province":"Lecco",
    "wof:name":"Filofiori Di Milani Luigi E C. (s.n.c.)",
    "wof:placetype":"venue"
},
  "geometry": {"coordinates":[9.381739,45.815796],"type":"Point"}
}