{
  "type": "Feature",
  "properties": {
    "addr:full":"31044 Montebelluna Montebelluna Treviso 31044",
    "addr:postcode":"31044;31044",
    "iso:country":"IT",
    "sg:address":"31044 Montebelluna",
    "sg:city":"Montebelluna",
    "sg:orig_category":"Forniture Per Abbigliamento E Pelletterie",
    "sg:phone":"+39 0423 300262",
    "sg:postcode":"31044",
    "sg:province":"Treviso",
    "sg:website":"http://www.tessiturarove.com",
    "wof:name":"Tessitura Rove Srl",
    "wof:placetype":"venue"
},
  "geometry": {"coordinates":[12.05427742,45.7722053528],"type":"Point"}
}