{
  "type": "Feature",
  "properties": {
    "addr:full":"Localit\u00e0 Laghetto 03013 Ferentino Ferentino Frosinone 03013",
    "addr:postcode":"03013;03013",
    "addr:street":"Localita\u0300 Laghetto",
    "iso:country":"IT",
    "sg:address":"Localit\u00e0 Laghetto 03013 Ferentino",
    "sg:city":"Ferentino",
    "sg:classifiers":[
        {
            "category":"Structure",
            "subcategory":"Tunnel",
            "type":"Public Place"
        }
    ],
    "sg:phone":"+39 0775 2741",
    "sg:postcode":"03013",
    "sg:province":"Frosinone",
    "sg:tags":[
        "heating",
        "element"
    ],
    "sg:website":"www.valeo.com",
    "wof:name":"Valeo Spa",
    "wof:placetype":"venue"
},
  "geometry": {"coordinates":[13.351902,41.640137],"type":"Point"}
}