{
  "type": "Feature",
  "properties": {
    "addr:full":"10020 Pecetto Torinese Pecetto Torinese Torino 10020",
    "addr:postcode":"10020;10020",
    "iso:country":"IT",
    "sg:address":"10020 Pecetto Torinese",
    "sg:city":"Pecetto Torinese",
    "sg:orig_category":"Dolciumi E Gelati. Shopping",
    "sg:phone":"+39 011 860 8160",
    "sg:postcode":"10020",
    "sg:province":"Torino",
    "wof:name":"Pasticceria Caffetteria Augusto",
    "wof:placetype":"venue"
},
  "geometry": {"coordinates":[7.749331,45.017475],"type":"Point"}
}