{
  "type": "Feature",
  "properties": {
    "addr:full":"84010 San Valentino Torio San Valentino Torio Salerno 84010",
    "addr:housenumber":"84010;valentino torio",
    "addr:postcode":"valentino torio;84010",
    "addr:street":"San;Salerno",
    "iso:country":"IT",
    "sg:address":"84010 San Valentino Torio",
    "sg:city":"San Valentino Torio",
    "sg:orig_category":"Forniture Per Abbigliamento E Pelletterie",
    "sg:phone":"+39 081 518 6072",
    "sg:postcode":"84010",
    "sg:province":"Salerno",
    "wof:name":"Cuomo Maria",
    "wof:placetype":"venue"
},
  "geometry": {"coordinates":[14.5978021622,40.7911109924],"type":"Point"}
}