{
  "type": "Feature",
  "properties": {
    "addr:full":"50041 Calenzano Calenzano Firenze 50041",
    "addr:postcode":"50041;50041",
    "iso:country":"IT",
    "sg:address":"50041 Calenzano",
    "sg:city":"Calenzano",
    "sg:orig_category":"Forniture Per Abbigliamento E Pelletterie",
    "sg:phone":"+39 055 882 5359",
    "sg:postcode":"50041",
    "sg:province":"Firenze",
    "wof:name":"Messino Assunta",
    "wof:placetype":"venue"
},
  "geometry": {"coordinates":[11.1648159027,43.85181427],"type":"Point"}
}