{
  "type": "Feature",
  "properties": {
    "iso:country":"IT",
    "sg:address":"Via Olona 181/a 21013 Gallarate",
    "sg:city":"Gallarate",
    "sg:classifiers":[
        {
            "category":"Sports & Exercise",
            "subcategory":"Athletic Track",
            "type":"Entertainment"
        }
    ],
    "sg:phone":"+39 0331 776170",
    "sg:postcode":"21013",
    "sg:province":"Varese",
    "sg:tags":[
        "conveyor",
        "belt"
    ],
    "sg:website":"www.bimac-gallarate.it",
    "wof:name":"Bimac Srl",
    "wof:placetype":"venue"
},
  "geometry": {"coordinates":[8.826385,45.817604],"type":"Point"}
}