{
  "type": "Feature",
  "properties": {
    "iso:country":"IT",
    "sg:address":"26831 Casalmaiocco",
    "sg:city":"Casalmaiocco",
    "sg:classifiers":[
        {
            "category":"Wholesale",
            "subcategory":"Machinery & Supplies",
            "type":"Manufacturing & Wholesale Goods"
        }
    ],
    "sg:phone":"+39 02 9826 4006",
    "sg:postcode":"26831",
    "sg:province":"Lodi",
    "sg:tags":[
        "activities",
        "industrial"
    ],
    "wof:name":"Carbomet Srl",
    "wof:placetype":"venue"
},
  "geometry": {"coordinates":[9.36656,45.357796],"type":"Point"}
}