{
  "type": "Feature",
  "properties": {
    "addr:full":"62100 Macerata Macerata Macerata 62100",
    "addr:postcode":"62100;62100",
    "iso:country":"IT",
    "sg:address":"62100 Macerata",
    "sg:city":"Macerata",
    "sg:orig_category":"Scuole E Servizi Scolastici. Ricerca, Selezione E Formazione Del Personale",
    "sg:phone":"+39 0733 33844",
    "sg:postcode":"62100",
    "sg:province":"Macerata",
    "sg:website":"http://www.grupposinergie.com",
    "wof:name":"Ced Servizi Srl",
    "wof:placetype":"venue"
},
  "geometry": {"coordinates":[13.431648,43.284599],"type":"Point"}
}