{
  "type": "Feature",
  "properties": {
    "addr:full":"33, Via Fol 31049 Valdobbiadene Valdobbiadene Treviso 31049",
    "addr:postcode":"31049;31049",
    "addr:street":"Via Fol",
    "iso:country":"IT",
    "sg:address":"33, Via Fol 31049 Valdobbiadene",
    "sg:city":"Valdobbiadene",
    "sg:classifiers":[
        {
            "category":"Food & Beverages",
            "subcategory":"Groceries & Convenience Stores",
            "type":"Retail Goods"
        }
    ],
    "sg:phone":"+39 0423 900138",
    "sg:postcode":"31049",
    "sg:province":"Treviso",
    "sg:tags":[
        "drink"
    ],
    "wof:name":"Bisol Desiderio & Figli",
    "wof:placetype":"venue"
},
  "geometry": {"coordinates":[12.242072,45.666286],"type":"Point"}
}