{
  "type": "Feature",
  "properties": {
    "iso:country":"IT",
    "sg:address":"20124 Milano",
    "sg:city":"Milano",
    "sg:orig_category":"Forniture Per Attivita' Commerciali Ed Artigianali. Pubblicita', Marketing E Comunicazione",
    "sg:phone":"+39 02 2940 6188",
    "sg:postcode":"20124",
    "sg:province":"Milano",
    "sg:website":"http://www.danjo.it",
    "wof:name":"D'anjo' Promotion Srl",
    "wof:placetype":"venue"
},
  "geometry": {"coordinates":[9.2066011429,45.4785118103],"type":"Point"}
}