{
  "type": "Feature",
  "properties": {
    "addr:full":"55, Via Sirtori Giuseppe Generale 90145 Palermo Palermo Palermo 90145",
    "addr:postcode":"90145;90145",
    "addr:street":"Via Sirtori Giuseppe Generale",
    "iso:country":"IT",
    "sg:address":"55, Via Sirtori Giuseppe Generale 90145 Palermo",
    "sg:city":"Palermo",
    "sg:classifiers":[
        {
            "category":"Professional",
            "subcategory":"Business Services",
            "type":"Services"
        }
    ],
    "sg:phone":"+39 39091225440",
    "sg:postcode":"90145",
    "sg:province":"Palermo",
    "sg:tags":[
        "advice"
    ],
    "wof:name":"Liceo Linguistico John Milton Di Guastella Greco Rosa & C. S.a.s",
    "wof:placetype":"venue"
},
  "geometry": {"coordinates":[13.361376,38.11562],"type":"Point"}
}