{
  "type": "Feature",
  "properties": {
    "addr:full":"6, V. Livingstone 41100 Modena Modena Modena 41100",
    "addr:housenumber":"6",
    "addr:postcode":"41100;41100",
    "addr:street":"V. Livingstone",
    "iso:country":"IT",
    "sg:address":"6, V. Livingstone 41100 Modena",
    "sg:city":"Modena",
    "sg:classifiers":[
        {
            "category":"Autos & Motor Vehicles",
            "subcategory":"Automobile Sales",
            "type":"Retail Goods"
        }
    ],
    "sg:phone":"+39 39059894411",
    "sg:postcode":"41100",
    "sg:province":"Modena",
    "sg:tags":[
        "industrial"
    ],
    "sg:website":"http://www.safim.it",
    "wof:name":"Safim",
    "wof:placetype":"venue"
},
  "geometry": {"coordinates":[10.885102,44.657127],"type":"Point"}
}