{
  "type": "Feature",
  "properties": {
    "addr:full":"20127 Milano Milano Milano 20127",
    "addr:postcode":"20127;20127",
    "iso:country":"IT",
    "sg:address":"20127 Milano",
    "sg:city":"Milano",
    "sg:orig_category":"Professionisti - Studi E Servizi Ed Associazioni Di Interesse Aziendale. Associazioni Ed Organismi Di Interesse Pubblico",
    "sg:phone":"+39 02 261 0343",
    "sg:postcode":"20127",
    "sg:province":"Milano",
    "wof:name":"Legambiente Lombardia Onlus",
    "wof:placetype":"venue"
},
  "geometry": {"coordinates":[9.2265386581,45.4987030029],"type":"Point"}
}