{
  "type": "Feature",
  "properties": {
    "addr:full":"31057 Silea Silea Treviso 31057",
    "addr:postcode":"31057;31057",
    "iso:country":"IT",
    "sg:address":"31057 Silea",
    "sg:city":"Silea",
    "sg:orig_category":"Macchine Per Cucire - Commercio E Riparazione",
    "sg:phone":"+39 0422 361114",
    "sg:postcode":"31057",
    "sg:province":"Treviso",
    "wof:name":"Rossi Riccardo",
    "wof:placetype":"venue"
},
  "geometry": {"coordinates":[12.291192,45.661484],"type":"Point"}
}