{
  "type": "Feature",
  "properties": {
    "addr:full":"Via Italia 43 20060 Gessate Gessate Milano 20060",
    "addr:housenumber":"43",
    "addr:postcode":"20060;20060",
    "addr:street":"Via Italia",
    "iso:country":"IT",
    "sg:address":"Via Italia 43 20060 Gessate",
    "sg:city":"Gessate",
    "sg:classifiers":[
        {
            "category":"Autos & Motor Vehicles",
            "subcategory":"Auto Supplies",
            "type":"Retail Goods"
        }
    ],
    "sg:phone":"+39 02 950881",
    "sg:postcode":"20060",
    "sg:province":"Milano",
    "sg:tags":[
        "machine",
        "filling",
        "sealing",
        "bottle"
    ],
    "sg:website":"www.ronchi.it",
    "wof:name":"Mario Ronchi S.p.a.",
    "wof:placetype":"venue"
},
  "geometry": {"coordinates":[9.405577,45.530827],"type":"Point"}
}