{
  "type": "Feature",
  "properties": {
    "iso:country":"IT",
    "sg:address":"46025 Poggio Rusco",
    "sg:city":"Poggio Rusco",
    "sg:orig_category":"Manufacturers: Prefabbricati",
    "sg:phone":"+39 0386 51973",
    "sg:postcode":"46025",
    "sg:province":"Mantova",
    "wof:name":"Italmontaggi Di Galeotti Enzo & C. Snc",
    "wof:placetype":"venue"
},
  "geometry": {"coordinates":[11.163723,44.968525],"type":"Point"}
}