{
  "type": "Feature",
  "properties": {
    "iso:country":"IT",
    "sg:address":"45, Via S. Domenico Savio Fr. Pessione 10023 Chieri",
    "sg:city":"Chieri",
    "sg:classifiers":[
        {
            "category":"Manufacturing",
            "subcategory":"Paper Products",
            "type":"Manufacturing & Wholesale Goods"
        }
    ],
    "sg:phone":"+39 011 943 2811",
    "sg:postcode":"10023",
    "sg:province":"Torino",
    "sg:tags":[
        "cardboard"
    ],
    "wof:name":"Sca Packaging Italia Spa",
    "wof:placetype":"venue"
},
  "geometry": {"coordinates":[7.8781118393,44.9940948486],"type":"Point"}
}