{
  "type": "Feature",
  "properties": {
    "addr:full":"20135 Milano Milano Milano 20135",
    "addr:postcode":"20135;20135",
    "iso:country":"IT",
    "sg:address":"20135 Milano",
    "sg:city":"Milano",
    "sg:orig_category":"Idraulici E Lattonieri",
    "sg:phone":"+39 02 551 6034",
    "sg:postcode":"20135",
    "sg:province":"Milano",
    "sg:website":"http://www.edilizia-adige.it",
    "wof:name":"Edilizia Adige Snc",
    "wof:placetype":"venue"
},
  "geometry": {"coordinates":[9.28957,45.494251],"type":"Point"}
}