{
  "type": "Feature",
  "properties": {
    "iso:country":"IT",
    "sg:address":"20090 Pieve Emanuele",
    "sg:city":"Pieve Emanuele",
    "sg:orig_category":"Arte Ed Artigianato Artistico",
    "sg:phone":"+39 02 9078 6444",
    "sg:postcode":"20090",
    "sg:province":"Milano",
    "wof:name":"Igor 2001 Srl",
    "wof:placetype":"venue"
},
  "geometry": {"coordinates":[9.180867,45.371185],"type":"Point"}
}