{
  "type": "Feature",
  "properties": {
    "addr:full":"55041 Camaiore Camaiore Lucca 55041",
    "addr:postcode":"55041;55041",
    "iso:country":"IT",
    "sg:address":"55041 Camaiore",
    "sg:city":"Camaiore",
    "sg:classifiers":[
        {
            "category":"Health Services",
            "subcategory":"Nursing And Care Facility",
            "type":"Services"
        }
    ],
    "sg:phone":"+39 0584 951782",
    "sg:postcode":"55041",
    "sg:province":"Lucca",
    "sg:tags":[
        "case",
        "riposo",
        "di"
    ],
    "sg:website":"http://www.villailcontesso.com",
    "wof:name":"Villa Il Contesso",
    "wof:placetype":"venue"
},
  "geometry": {"coordinates":[10.504115,43.840157],"type":"Point"}
}