{
  "type": "Feature",
  "properties": {
    "addr:full":"32, Via Euripide 20041 Agrate Brianza Agrate Brianza Milano 20041",
    "addr:postcode":"20041;20041",
    "addr:street":"Via Euripide",
    "iso:country":"IT",
    "sg:address":"32, Via Euripide 20041 Agrate Brianza",
    "sg:city":"Agrate Brianza",
    "sg:classifiers":[
        {
            "category":"Shopping",
            "subcategory":"Crafts & Fabrics",
            "type":"Retail Goods"
        }
    ],
    "sg:phone":"+39 39039634031",
    "sg:postcode":"20041",
    "sg:province":"Milano",
    "wof:name":"Scotti (s.r.l.)",
    "wof:placetype":"venue"
},
  "geometry": {"coordinates":[9.3291702271,45.5722389221],"type":"Point"}
}