{
  "type": "Feature",
  "properties": {
    "iso:country":"IT",
    "sg:address":"20, Via Del Carpineto 34148 Trieste",
    "sg:city":"Trieste",
    "sg:classifiers":[
        {
            "category":"Professional",
            "subcategory":"Printing & Photocopies",
            "type":"Services"
        }
    ],
    "sg:phone":"+39 39040814309",
    "sg:postcode":"34148",
    "sg:province":"Trieste",
    "wof:name":"Schor",
    "wof:placetype":"venue"
},
  "geometry": {"coordinates":[13.7896575928,45.623966217],"type":"Point"}
}