{
  "type": "Feature",
  "properties": {
    "addr:full":"80044 Ottaviano Ottaviano Napoli 80044",
    "addr:postcode":"80044;80044",
    "iso:country":"IT",
    "sg:address":"80044 Ottaviano",
    "sg:city":"Ottaviano",
    "sg:orig_category":"Bevande, Vini E Liquori. Servizi E Lavori Per Industria Alimentare E Bevande",
    "sg:phone":"+39 081 827 0954",
    "sg:postcode":"80044",
    "sg:province":"Napoli",
    "wof:name":"Distellerie Pascale",
    "wof:placetype":"venue"
},
  "geometry": {"coordinates":[14.197858,40.804905],"type":"Point"}
}