{
  "type": "Feature",
  "properties": {
    "addr:full":"1, Via Roma 22020 Cerano D'intelvi Como 22020",
    "addr:postcode":"22020;22020",
    "addr:street":"Via Roma",
    "iso:country":"IT",
    "sg:address":"1, Via Roma 22020 Cerano D'intelvi",
    "sg:classifiers":[
        {
            "category":"Shopping",
            "subcategory":"Crafts & Fabrics",
            "type":"Retail Goods"
        }
    ],
    "sg:phone":"+39 39031817804",
    "sg:postcode":"22020",
    "sg:province":"Como",
    "wof:name":"Muttoni",
    "wof:placetype":"venue"
},
  "geometry": {"coordinates":[9.1244068146,45.9557495117],"type":"Point"}
}