{
  "type": "Feature",
  "properties": {
    "addr:full":"65015 Montesilvano Montesilvano Pescara 65015",
    "addr:postcode":"65015;65015",
    "iso:country":"IT",
    "sg:address":"65015 Montesilvano",
    "sg:city":"Montesilvano",
    "sg:orig_category":"Pavimenti",
    "sg:phone":"+39 085 468 2575",
    "sg:postcode":"65015",
    "sg:province":"Pescara",
    "wof:name":"De Vitis Parquet",
    "wof:placetype":"venue"
},
  "geometry": {"coordinates":[14.1327095032,42.5046157837],"type":"Point"}
}