{
  "type": "Feature",
  "properties": {
    "addr:full":"21040 Gerenzano Gerenzano Varese 21040",
    "addr:postcode":"21040;21040",
    "iso:country":"IT",
    "sg:address":"21040 Gerenzano",
    "sg:city":"Gerenzano",
    "sg:orig_category":"Prodotti Alimentari. Shopping",
    "sg:phone":"+39 02 9648 0586",
    "sg:postcode":"21040",
    "sg:province":"Varese",
    "wof:name":"Galbani Egidio Spa",
    "wof:placetype":"venue"
},
  "geometry": {"coordinates":[8.8280391693,45.8162193298],"type":"Point"}
}