{
  "type": "Feature",
  "properties": {
    "iso:country":"IT",
    "sg:address":"19/21, Via Dante 15045 Sale",
    "sg:city":"Sale",
    "sg:classifiers":[
        {
            "category":"Bars & Pubs",
            "subcategory":"Nightclub",
            "type":"Food & Drink"
        }
    ],
    "sg:phone":"+39 39013184114",
    "sg:postcode":"15045",
    "sg:province":"Alessandria",
    "sg:tags":[
        "cake",
        "bread"
    ],
    "wof:name":"Pasticceria Rippa (s.n.c.)",
    "wof:placetype":"venue"
},
  "geometry": {"coordinates":[8.808812,44.980141],"type":"Point"}
}