{
  "type": "Feature",
  "properties": {
    "addr:full":"20122 Milano Milano Milano 20122",
    "addr:postcode":"20122;20122",
    "iso:country":"IT",
    "sg:address":"20122 Milano",
    "sg:city":"Milano",
    "sg:orig_category":"Banche E Servizi Finanziari",
    "sg:phone":"+39 02 5832 3002",
    "sg:postcode":"20122",
    "sg:province":"Milano",
    "wof:name":"Unicredit Factoring S.p.a.",
    "wof:placetype":"venue"
},
  "geometry": {"coordinates":[9.191183,45.452637],"type":"Point"}
}