{
  "type": "Feature",
  "properties": {
    "iso:country":"IT",
    "sg:address":"50059 Vinci",
    "sg:city":"Vinci",
    "sg:orig_category":"Cartotecnica E Servizi. Articoli Per Imballaggio E Confezionamento",
    "sg:phone":"+39 0571 584891",
    "sg:postcode":"50059",
    "sg:province":"Firenze",
    "wof:name":"Scatolificio Emmepi Snc",
    "wof:placetype":"venue"
},
  "geometry": {"coordinates":[10.944158,43.758057],"type":"Point"}
}