{
  "type": "Feature",
  "properties": {
    "iso:country":"IT",
    "sg:address":"20159 Milano",
    "sg:city":"Milano",
    "sg:orig_category":"Abbigliamento Intimo, Calze E Costumi Da Bagno",
    "sg:phone":"+39 02 683601",
    "sg:postcode":"20159",
    "sg:province":"Milano",
    "wof:name":"Memorabilia Di Girolama Buzzanca",
    "wof:placetype":"venue"
},
  "geometry": {"coordinates":[9.183267,45.489826],"type":"Point"}
}