{
  "type": "Feature",
  "properties": {
    "addr:full":"5, Via Trentun 17015 Celle Ligure Celle Ligure Savona 17015",
    "addr:postcode":"17015;17015",
    "addr:street":"Via Trentun",
    "iso:country":"IT",
    "sg:address":"5, Via Trentun 17015 Celle Ligure",
    "sg:city":"Celle Ligure",
    "sg:classifiers":[
        {
            "category":"Travel",
            "subcategory":"Travel Agent",
            "type":"Entertainment"
        }
    ],
    "sg:phone":"+39 39019991929",
    "sg:postcode":"17015",
    "sg:province":"Savona",
    "sg:tags":[
        "business"
    ],
    "wof:name":"Hotel Villa Adele Di Rizzin Lidia",
    "wof:placetype":"venue"
},
  "geometry": {"coordinates":[8.548791,44.345024],"type":"Point"}
}