{
  "type": "Feature",
  "properties": {
    "iso:country":"IT",
    "sg:address":"65121 Pescara",
    "sg:city":"Pescara",
    "sg:orig_category":"Termotecnica E Riscaldamento, Apparecchiature E Servizi",
    "sg:phone":"+39 085 421 1740",
    "sg:postcode":"65121",
    "sg:province":"Pescara",
    "wof:name":"Bruciatori Thermovur",
    "wof:placetype":"venue"
},
  "geometry": {"coordinates":[14.20944,42.465942],"type":"Point"}
}