{
  "type": "Feature",
  "properties": {
    "addr:full":"45, Via Stalingrado 40128 Bologna Bologna Bologna 40128",
    "addr:postcode":"40128;40128",
    "addr:street":"Via Stalingrado",
    "iso:country":"IT",
    "sg:address":"45, Via Stalingrado 40128 Bologna",
    "sg:city":"Bologna",
    "sg:classifiers":[
        {
            "category":"Banks & Credit Unions",
            "subcategory":"Financial Services",
            "type":"Services"
        }
    ],
    "sg:phone":"+39 051 609 7111",
    "sg:postcode":"40128",
    "sg:province":"Bologna",
    "sg:tags":[
        "banking",
        "finance",
        "insurance"
    ],
    "wof:name":"Unipol (s.p.a.)",
    "wof:placetype":"venue"
},
  "geometry": {"coordinates":[11.358486,44.513538],"type":"Point"}
}