{
  "type": "Feature",
  "properties": {
    "iso:country":"IT",
    "sg:address":"28012 Cressa",
    "sg:city":"Cressa",
    "sg:orig_category":"Acquedotti, Gasdotti Ed Oleodotti - Impianti Ed Attrezzature",
    "sg:phone":"+39 0322 863318",
    "sg:postcode":"28012",
    "sg:province":"Novara",
    "wof:name":"De Giuliani Impresa Snc",
    "wof:placetype":"venue"
},
  "geometry": {"coordinates":[8.505205,45.633045],"type":"Point"}
}