{
  "type": "Feature",
  "properties": {
    "addr:full":"71016 San Severo San Severo Foggia 71016",
    "addr:housenumber":"71016",
    "addr:postcode":"71016",
    "addr:street":"San Severo",
    "iso:country":"IT",
    "sg:address":"71016 San Severo",
    "sg:city":"San Severo",
    "sg:orig_category":"Sport - Articoli E Forniture",
    "sg:phone":"+39 0882 371068",
    "sg:postcode":"71016",
    "sg:province":"Foggia",
    "wof:name":"Angeloro Import Export S.r.l.",
    "wof:placetype":"venue"
},
  "geometry": {"coordinates":[15.370345,41.690704],"type":"Point"}
}