{
  "type": "Feature",
  "properties": {
    "addr:full":"20, Via Verdi 46030 Dosolo Dosolo Mantova 46030",
    "addr:postcode":"46030;46030",
    "addr:street":"Via Verdi",
    "iso:country":"IT",
    "sg:address":"20, Via Verdi 46030 Dosolo",
    "sg:city":"Dosolo",
    "sg:classifiers":[
        {
            "category":"Food & Beverages",
            "subcategory":"Groceries & Convenience Stores",
            "type":"Retail Goods"
        }
    ],
    "sg:phone":"+39 39037586000",
    "sg:postcode":"46030",
    "sg:province":"Mantova",
    "sg:tags":[
        "product",
        "related"
    ],
    "wof:name":"Salumificio Valpadana Srl",
    "wof:placetype":"venue"
},
  "geometry": {"coordinates":[10.6198987961,44.9308013916],"type":"Point"}
}