{
  "type": "Feature",
  "properties": {
    "addr:full":"00155 Roma Roma Roma 00155",
    "addr:postcode":"00155;00155",
    "iso:country":"IT",
    "sg:address":"00155 Roma",
    "sg:city":"Roma",
    "sg:orig_category":"Prodotti Finiti Stampati. Servizi Editoriali. Tempo Libero - Articoli E Forniture",
    "sg:phone":"+39 06 407 0100",
    "sg:postcode":"00155",
    "sg:province":"Roma",
    "wof:name":"Aerofotogrammetrica",
    "wof:placetype":"venue"
},
  "geometry": {"coordinates":[12.3758935928,42.1130142212],"type":"Point"}
}