{
  "type": "Feature",
  "properties": {
    "addr:full":"00184 Roma Roma Roma 00184",
    "addr:postcode":"00184;00184",
    "iso:country":"IT",
    "sg:address":"00184 Roma",
    "sg:city":"Roma",
    "sg:orig_category":"Tessuti Arredamento, Tende E Tappeti",
    "sg:phone":"+39 06 487 0739",
    "sg:postcode":"00184",
    "sg:province":"Roma",
    "wof:name":"Conte Luigi",
    "wof:placetype":"venue"
},
  "geometry": {"coordinates":[12.492245,41.899094],"type":"Point"}
}