{
  "type": "Feature",
  "properties": {
    "iso:country":"IT",
    "sg:address":"Stadtgasse 62 39031 Bruneck",
    "sg:classifiers":[
        {
            "category":"Professional",
            "subcategory":"Computer Services",
            "type":"Services"
        }
    ],
    "sg:phone":"+39 0474 551820",
    "sg:postcode":"39031",
    "sg:province":"Bolzano/Bozen",
    "sg:tags":[
        "development",
        "software"
    ],
    "sg:website":"www.ekontrol.com",
    "wof:name":"Ekon Gmbh",
    "wof:placetype":"venue"
},
  "geometry": {"coordinates":[11.938282,46.795845],"type":"Point"}
}