{
  "type": "Feature",
  "properties": {
    "iso:country":"IT",
    "sg:address":"30, V. Rosa Luxemburg 06012 Citt\u00e0 Di Castello",
    "sg:classifiers":[
        {
            "category":"Food & Beverages",
            "subcategory":"Groceries & Convenience Stores",
            "type":"Retail Goods"
        }
    ],
    "sg:phone":"+39 39075851781",
    "sg:postcode":"06012",
    "sg:province":"Perugia",
    "sg:tags":[
        "product",
        "related"
    ],
    "sg:website":"http://www.conagit.it",
    "wof:name":"Con. Ag. It. Scarl",
    "wof:placetype":"venue"
},
  "geometry": {"coordinates":[12.2201061249,43.4859352112],"type":"Point"}
}