{
  "type": "Feature",
  "properties": {
    "addr:full":"70017 Putignano Putignano Bari 70017",
    "addr:postcode":"70017;70017",
    "iso:country":"IT",
    "sg:address":"70017 Putignano",
    "sg:city":"Putignano",
    "sg:orig_category":"Accessori Moda D'abbigliamento. Forniture Per Abbigliamento E Pelletterie",
    "sg:phone":"+39 080 405 4454",
    "sg:postcode":"70017",
    "sg:province":"Bari",
    "wof:name":"Lady Ricami Snc Di Impedovo Carmela",
    "wof:placetype":"venue"
},
  "geometry": {"coordinates":[17.08938,40.843807],"type":"Point"}
}