{
  "type": "Feature",
  "properties": {
    "iso:country":"IT",
    "sg:address":"54015 Comano",
    "sg:city":"Comano",
    "sg:orig_category":"Alberghi E Strutture Extra Alberghiere. Ospedali E Servizi Sanitari",
    "sg:phone":"+39 0187 484313",
    "sg:postcode":"54015",
    "sg:province":"Massa-Carrara",
    "wof:name":"Casa Di Riposo Villa Serena Di Galeazzi Lucilla E C. Sas",
    "wof:placetype":"venue"
},
  "geometry": {"coordinates":[10.130145,44.026119],"type":"Point"}
}