{
  "type": "Feature",
  "properties": {
    "addr:full":"Via S Pellico 17/19; Cornate; 20040 Milano 20040",
    "addr:housenumber":"17 / 19",
    "addr:postcode":"20040;20040",
    "addr:street":"Via S Pellico;Cornate",
    "iso:country":"IT",
    "sg:address":"Via S Pellico 17/19; Cornate; 20040",
    "sg:classifiers":[
        {
            "category":"Banks & Credit Unions",
            "subcategory":"Bank",
            "type":"Services"
        }
    ],
    "sg:phone":"+39 039 609 5323",
    "sg:postcode":"20040",
    "sg:province":"Milano",
    "wof:name":"Istituto Bancario, San Paolo Di Torino Spa",
    "wof:placetype":"venue"
},
  "geometry": {"coordinates":[9.472538,45.631096],"type":"Point"}
}