{
  "type": "Feature",
  "properties": {
    "iso:country":"IT",
    "sg:address":"3, V. A. Ponchielli 30038 Spinea",
    "sg:city":"Spinea",
    "sg:classifiers":[
        {
            "category":"Professional",
            "subcategory":"Engineering",
            "type":"Services"
        }
    ],
    "sg:phone":"+39 39041991246",
    "sg:postcode":"30038",
    "sg:province":"Venezia",
    "sg:tags":[
        "machine",
        "-",
        "mechanical"
    ],
    "sg:website":"http://www.crefin.it",
    "wof:name":"C.re.f.in. Srl",
    "wof:placetype":"venue"
},
  "geometry": {"coordinates":[12.166206,45.48848],"type":"Point"}
}