{
  "type": "Feature",
  "properties": {
    "iso:country":"IT",
    "sg:address":"Via Monte Di Dio, 9; Naples; 80132",
    "sg:classifiers":[
        {
            "category":"Travel",
            "subcategory":"Travel Agent",
            "type":"Entertainment"
        }
    ],
    "sg:phone":"+39 390 817 6449",
    "sg:postcode":"80132",
    "sg:province":"Napoli",
    "sg:website":"www.riorimontitours.com",
    "wof:name":"Rising Incoming Organizer",
    "wof:placetype":"venue"
},
  "geometry": {"coordinates":[14.245568,40.833843],"type":"Point"}
}