{
  "type": "Feature",
  "properties": {
    "iso:country":"IT",
    "sg:address":"41100 Modena",
    "sg:city":"Modena",
    "sg:classifiers":[
        {
            "category":"Health Services",
            "subcategory":"Dentist",
            "type":"Services"
        }
    ],
    "sg:phone":"+39 059 422 2210",
    "sg:postcode":"41100",
    "sg:province":"Modena",
    "sg:tags":[
        "hospital"
    ],
    "sg:website":"http://www.policlinico.mo.it",
    "wof:name":"Azienda Ospedaliero-universitaria Policlinico Di Modena",
    "wof:placetype":"venue"
},
  "geometry": {"coordinates":[10.914429,44.663944],"type":"Point"}
}