{
  "type": "Feature",
  "properties": {
    "addr:full":"27029 Vigevano Vigevano Pavia 27029",
    "addr:postcode":"27029;27029",
    "iso:country":"IT",
    "sg:address":"27029 Vigevano",
    "sg:city":"Vigevano",
    "sg:orig_category":"Macchine, Impianti Ed Attrezzature Industria Delle Materie Plastiche E Gomma",
    "sg:phone":"+39 0381 344813",
    "sg:postcode":"27029",
    "sg:province":"Pavia",
    "wof:name":"Ci Due (s.r.l.)",
    "wof:placetype":"venue"
},
  "geometry": {"coordinates":[8.863476,45.302814],"type":"Point"}
}