{
  "type": "Feature",
  "properties": {
    "addr:full":"Contrada Feudotto 92013 Menfi Menfi Agrigento 92013",
    "addr:postcode":"92013;92013",
    "addr:street":"Contrada Feudotto",
    "iso:country":"IT",
    "sg:address":"Contrada Feudotto 92013 Menfi",
    "sg:city":"Menfi",
    "sg:classifiers":[
        {
            "category":"Shopping",
            "type":"Retail Goods"
        }
    ],
    "sg:phone":"+39 39092571101",
    "sg:postcode":"92013",
    "sg:province":"Agrigento",
    "sg:tags":[
        "finished",
        "-",
        "metallic"
    ],
    "wof:name":"Co.m. Mer.",
    "wof:placetype":"venue"
},
  "geometry": {"coordinates":[12.9862232208,37.6257705688],"type":"Point"}
}