{
  "type": "Feature",
  "properties": {
    "addr:full":"01027 Montefiascone Montefiascone Viterbo 01027",
    "addr:postcode":"01027;01027",
    "iso:country":"IT",
    "sg:address":"01027 Montefiascone",
    "sg:city":"Montefiascone",
    "sg:orig_category":"Automobili E Mezzi Di Trasporto",
    "sg:phone":"+39 0761 823859",
    "sg:postcode":"01027",
    "sg:province":"Viterbo",
    "wof:name":"Caprio 1906 Sas Di Caprio G. & C.",
    "wof:placetype":"venue"
},
  "geometry": {"coordinates":[12.027486,42.545979],"type":"Point"}
}