{
  "type": "Feature",
  "properties": {
    "iso:country":"IT",
    "sg:address":"282, Viale Alessandro Magno 00124 Roma",
    "sg:city":"Roma",
    "sg:classifiers":[
        {
            "category":"Airport",
            "subcategory":"General Aviation",
            "type":"Transportation"
        }
    ],
    "sg:phone":"+39 39065098413",
    "sg:postcode":"00124",
    "sg:province":"Roma",
    "sg:tags":[
        "transport",
        "air"
    ],
    "wof:name":"Air Seychelles Limited",
    "wof:placetype":"venue"
},
  "geometry": {"coordinates":[12.344543,41.742554],"type":"Point"}
}