{
  "type": "Feature",
  "properties": {
    "iso:country":"IT",
    "sg:address":"90132 Palermo",
    "sg:orig_category":"Arti Grafiche",
    "sg:phone":"+39 091 668 8857",
    "sg:province":"PA",
    "sg:website":"http://www.os2.it.",
    "wof:name":"Os2 Sas",
    "wof:placetype":"venue"
},
  "geometry": {"coordinates":[13.106359,37.989853],"type":"Point"}
}