{
  "type": "Feature",
  "properties": {
    "iso:country":"IT",
    "sg:address":"72017 Ostuni",
    "sg:city":"Ostuni",
    "sg:orig_category":"Barche, Canotti Pneumatici E Motoscafi - Vendita Al Dettaglio",
    "sg:phone":"+39 0831 308810",
    "sg:postcode":"72017",
    "sg:province":"Brindisi",
    "wof:name":"Orlandino Marco",
    "wof:placetype":"venue"
},
  "geometry": {"coordinates":[17.595072,40.78714],"type":"Point"}
}