{
  "type": "Feature",
  "properties": {
    "iso:country":"IT",
    "sg:address":"60035 Jesi",
    "sg:city":"Jesi",
    "sg:orig_category":"Lavorazioni Metalli, Stampaggio E Saldatura",
    "sg:phone":"+39 0731 202581",
    "sg:postcode":"60035",
    "sg:province":"Ancona",
    "wof:name":"Termo Forgia S P A",
    "wof:placetype":"venue"
},
  "geometry": {"coordinates":[13.244062,43.514885],"type":"Point"}
}