{
  "type": "Feature",
  "properties": {
    "addr:full":"22076 Mozzate Mozzate Como 22076",
    "addr:postcode":"22076;22076",
    "iso:country":"IT",
    "sg:address":"22076 Mozzate",
    "sg:city":"Mozzate",
    "sg:orig_category":"Valvole E Apparecchiature Di Misura. Forniture Per Attivita' Industriali",
    "sg:phone":"+39 0331 832515",
    "sg:postcode":"22076",
    "sg:province":"Como",
    "wof:name":"R.p.e. Snc",
    "wof:placetype":"venue"
},
  "geometry": {"coordinates":[8.952842,45.67194],"type":"Point"}
}