{
  "type": "Feature",
  "properties": {
    "addr:full":"23, Strada Torino 10092 Beinasco Beinasco Torino 10092",
    "addr:postcode":"10092;10092",
    "addr:street":"Strada Torino",
    "iso:country":"IT",
    "sg:address":"23, Strada Torino 10092 Beinasco",
    "sg:city":"Beinasco",
    "sg:classifiers":[
        {
            "category":"Autos & Motor Vehicles",
            "subcategory":"Automobile Sales",
            "type":"Retail Goods"
        }
    ],
    "sg:phone":"+39 011 349 4911",
    "sg:postcode":"10092",
    "sg:province":"Torino",
    "sg:tags":[
        "industrial"
    ],
    "wof:name":"Aries S.p.a",
    "wof:placetype":"venue"
},
  "geometry": {"coordinates":[7.587924,45.022953],"type":"Point"}
}