{
  "type": "Feature",
  "properties": {
    "iso:country":"IT",
    "sg:address":"70044 Polignano A Mare",
    "sg:city":"Polignano a Mare",
    "sg:orig_category":"Impianti, Attrezzature E Forniture Sanitarie Ed Ospedaliere",
    "sg:phone":"+39 080 424 7382",
    "sg:postcode":"70044",
    "sg:province":"Bari",
    "wof:name":"Ferrucio Ferrucci",
    "wof:placetype":"venue"
},
  "geometry": {"coordinates":[17.222103,40.994923],"type":"Point"}
}