{
  "type": "Feature",
  "properties": {
    "iso:country":"IT",
    "sg:address":"21040 Origgio",
    "sg:city":"Origgio",
    "sg:orig_category":"Biancheria, Telerie E Coperte. Forniture Alle Strutture Ricettive",
    "sg:phone":"+39 02 9673 0030",
    "sg:postcode":"21040",
    "sg:province":"Varese",
    "wof:name":"Jacobosky S.r.l.",
    "wof:placetype":"venue"
},
  "geometry": {"coordinates":[9.017855,45.596848],"type":"Point"}
}