{
  "type": "Feature",
  "properties": {
    "addr:full":"Via Giuseppe Di Vittorio 62 20026 Novate Milanese Novate Milanese Milano 20026",
    "addr:housenumber":"62",
    "addr:postcode":"20026;20026",
    "addr:street":"Via Giuseppe Di Vittorio",
    "iso:country":"IT",
    "sg:address":"Via Giuseppe Di Vittorio 62 20026 Novate Milanese",
    "sg:city":"Novate Milanese",
    "sg:classifiers":[
        {
            "category":"Retail",
            "subcategory":"Laundry & Dry Cleaning",
            "type":"Services"
        }
    ],
    "sg:phone":"+39 02 356 0785",
    "sg:postcode":"20026",
    "sg:province":"Milano",
    "sg:tags":[
        "equipment"
    ],
    "wof:name":"Lavenda Laundry E Textile Machineries Srl",
    "wof:placetype":"venue"
},
  "geometry": {"coordinates":[9.129129,45.532318],"type":"Point"}
}