{
  "type": "Feature",
  "properties": {
    "addr:full":"71100 Foggia Foggia Foggia 71100",
    "addr:postcode":"71100;71100",
    "iso:country":"IT",
    "sg:address":"71100 Foggia",
    "sg:city":"Foggia",
    "sg:orig_category":"Pompe. Elettrotecnica Industriale, Prodotti E Apparecchiature",
    "sg:phone":"+39 0881 723474",
    "sg:postcode":"71100",
    "sg:province":"Foggia",
    "wof:name":"Impiantistica Dar Snc Di Anzivino Eugenio E Renzullo Gaetano",
    "wof:placetype":"venue"
},
  "geometry": {"coordinates":[16.0882968903,41.3582954407],"type":"Point"}
}