{
  "type": "Feature",
  "properties": {
    "addr:full":"35028 Piove Di Sacco Piove di Sacco Padova 35028",
    "addr:postcode":"35028;35028",
    "iso:country":"IT",
    "sg:address":"35028 Piove Di Sacco",
    "sg:city":"Piove di Sacco",
    "sg:orig_category":"Prodotti Alimentari. Agricoltura, Orticoltura E Floricoltura",
    "sg:phone":"+39 049 584 2780",
    "sg:postcode":"35028",
    "sg:province":"Padova",
    "wof:name":"L.c.f.p.",
    "wof:placetype":"venue"
},
  "geometry": {"coordinates":[12.047832489,45.2945976257],"type":"Point"}
}