{
  "type": "Feature",
  "properties": {
    "addr:full":"80023 Caivano Caivano Napoli 80023",
    "addr:postcode":"80023;80023",
    "iso:country":"IT",
    "sg:address":"80023 Caivano",
    "sg:city":"Caivano",
    "sg:classifiers":[
        {
            "category":"Home & Garden",
            "subcategory":"Building Materials",
            "type":"Retail Goods"
        }
    ],
    "sg:phone":"+39 081 834 9133",
    "sg:postcode":"80023",
    "sg:province":"Napoli",
    "sg:tags":[
        "gas",
        "caldaie"
    ],
    "wof:name":"Fusco Guido",
    "wof:placetype":"venue"
},
  "geometry": {"coordinates":[14.303983,40.977459],"type":"Point"}
}