{
  "type": "Feature",
  "properties": {
    "iso:country":"IT",
    "sg:address":"45, Strada Torino 13100 Vercelli",
    "sg:city":"Vercelli",
    "sg:classifiers":[
        {
            "category":"Parking",
            "subcategory":"Lot",
            "type":"Transportation"
        }
    ],
    "sg:phone":"+39 0161 294983",
    "sg:postcode":"13100",
    "sg:province":"Vercelli",
    "sg:tags":[
        "transport",
        "road"
    ],
    "wof:name":"Cgt S.p.a.",
    "wof:placetype":"venue"
},
  "geometry": {"coordinates":[8.401438,45.323883],"type":"Point"}
}