{
  "type": "Feature",
  "properties": {
    "iso:country":"IT",
    "sg:address":"Via Apollonio 11 36061 Bassano Del Grappa",
    "sg:city":"Bassano del Grappa",
    "sg:classifiers":[
        {
            "category":"Home & Garden",
            "subcategory":"Kitchen Supply",
            "type":"Retail Goods"
        }
    ],
    "sg:phone":"+39 0424 500006",
    "sg:postcode":"36061",
    "sg:province":"Vicenza",
    "sg:tags":[
        "steel",
        "stainless"
    ],
    "sg:website":"www.smev.com",
    "wof:name":"S.me.v. Srl",
    "wof:placetype":"venue"
},
  "geometry": {"coordinates":[11.69628,45.746262],"type":"Point"}
}