{
  "type": "Feature",
  "properties": {
    "addr:full":"Via Amerina 05022 Amelia Amelia Terni 05022",
    "addr:postcode":"05022;05022",
    "addr:street":"Via Amerina",
    "iso:country":"IT",
    "sg:address":"Via Amerina 05022 Amelia",
    "sg:city":"Amelia",
    "sg:classifiers":[
        {
            "category":"Professional",
            "subcategory":"Engineering",
            "type":"Services"
        }
    ],
    "sg:phone":"+39 0744 989621",
    "sg:postcode":"05022",
    "sg:province":"Terni",
    "sg:tags":[
        "machine",
        "-",
        "mechanical"
    ],
    "wof:name":"Pulsoni",
    "wof:placetype":"venue"
},
  "geometry": {"coordinates":[12.486025,42.538216],"type":"Point"}
}