{
  "type": "Feature",
  "properties": {
    "addr:full":"24, Via Garibaldi Botticino Sera 25082 Botticino Botticino Brescia 25082",
    "addr:postcode":"25082;25082",
    "addr:street":"Via Garibaldi",
    "iso:country":"IT",
    "sg:address":"24, Via Garibaldi Botticino Sera 25082 Botticino",
    "sg:city":"Botticino",
    "sg:classifiers":[
        {
            "category":"Shopping",
            "subcategory":"Clothing, Apparel, & Fashions",
            "type":"Retail Goods"
        }
    ],
    "sg:phone":"+39 030 269 1885",
    "sg:postcode":"25082",
    "sg:province":"Brescia",
    "sg:tags":[
        "clothes"
    ],
    "wof:name":"Calzificio Emy Di Apostoli Emiliano & C. (s.n.c.)",
    "wof:placetype":"venue"
},
  "geometry": {"coordinates":[10.305086,45.52504],"type":"Point"}
}