{
  "type": "Feature",
  "properties": {
    "iso:country":"IT",
    "sg:address":"Via Roma 2, 01030 Bassano Romano, Vt",
    "sg:city":"Bassano Romano",
    "sg:classifiers":[
        {
            "category":"Banks & Credit Unions",
            "subcategory":"Bank",
            "type":"Services"
        }
    ],
    "sg:postcode":"01030",
    "sg:province":"Viterbo",
    "wof:name":"Banca Di Credito Cooperativo Di Bassano Romano Scrl",
    "wof:placetype":"venue"
},
  "geometry": {"coordinates":[12.192178,42.21788],"type":"Point"}
}