{
  "type": "Feature",
  "properties": {
    "iso:country":"IT",
    "sg:address":"470, Contrada Berbaro 91025 Marsala",
    "sg:city":"Marsala",
    "sg:classifiers":[
        {
            "category":"Travel",
            "subcategory":"Travel Agent",
            "type":"Entertainment"
        }
    ],
    "sg:phone":"+39 0923 751076",
    "sg:postcode":"91025",
    "sg:province":"Trapani",
    "sg:tags":[
        "business"
    ],
    "wof:name":"Delfino Beach Hotel",
    "wof:placetype":"venue"
},
  "geometry": {"coordinates":[12.514634,38.018589],"type":"Point"}
}