{
  "type": "Feature",
  "properties": {
    "iso:country":"IT",
    "sg:address":"74100 Taranto",
    "sg:city":"Taranto",
    "sg:orig_category":"Valvole E Apparecchiature Di Misura",
    "sg:phone":"+39 099 452 6592",
    "sg:postcode":"74100",
    "sg:province":"Taranto",
    "wof:name":"L'idraulica S.n.c. Di Gasparini & Albano",
    "wof:placetype":"venue"
},
  "geometry": {"coordinates":[17.243799,40.468788],"type":"Point"}
}