{
  "type": "Feature",
  "properties": {
    "addr:full":"37135 Verona Verona Verona 37135",
    "addr:postcode":"37135;37135",
    "iso:country":"IT",
    "sg:address":"37135 Verona",
    "sg:city":"Verona",
    "sg:orig_category":"Scuole E Servizi Scolastici",
    "sg:phone":"+39 045 500398",
    "sg:postcode":"37135",
    "sg:province":"Verona",
    "wof:name":"Istituto San Giuseppe",
    "wof:placetype":"venue"
},
  "geometry": {"coordinates":[10.987287,45.416595],"type":"Point"}
}