{
  "type": "Feature",
  "properties": {
    "addr:full":"35129 Padova Padova Padova 35129",
    "addr:postcode":"35129;35129",
    "iso:country":"IT",
    "sg:address":"35129 Padova",
    "sg:city":"Padova",
    "sg:orig_category":"Arredo Cucina Ed Elettrodomestici",
    "sg:phone":"+39 049 807 2555",
    "sg:postcode":"35129",
    "sg:province":"Padova",
    "wof:name":"Mainox Padova (s.r.l.)",
    "wof:placetype":"venue"
},
  "geometry": {"coordinates":[11.921788,45.427876],"type":"Point"}
}