{
  "type": "Feature",
  "properties": {
    "iso:country":"IT",
    "sg:address":"Via Pratese 26/b/c 50145 Firenze",
    "sg:city":"Firenze",
    "sg:classifiers":[
        {
            "category":"Banks & Credit Unions",
            "subcategory":"Investment Brokerage",
            "type":"Services"
        }
    ],
    "sg:phone":"+39 055 373717",
    "sg:postcode":"50145",
    "sg:province":"Firenze",
    "sg:tags":[
        "embroidery",
        "accessory"
    ],
    "wof:name":"Megas Srl",
    "wof:placetype":"venue"
},
  "geometry": {"coordinates":[11.256902,43.768734],"type":"Point"}
}