{
  "type": "Feature",
  "properties": {
    "iso:country":"IT",
    "sg:address":"00151 Roma",
    "sg:city":"Roma",
    "sg:orig_category":"Servizi E Lavori Per Arredamento E Industria Del Legno",
    "sg:phone":"+39 06 582 6294",
    "sg:postcode":"00151",
    "sg:province":"Roma",
    "wof:name":"Falciani Emidio",
    "wof:placetype":"venue"
},
  "geometry": {"coordinates":[12.440924,41.866146],"type":"Point"}
}