{
  "type": "Feature",
  "properties": {
    "iso:country":"IT",
    "sg:address":"47100 Forli'",
    "sg:orig_category":"Carni, Salumi E Pesci. Zootecnia E Pesca, Allevamento Piccoli Animali",
    "sg:phone":"+39 0543 32905",
    "sg:postcode":"47100",
    "sg:province":"Forl\u00ec-Cesena",
    "wof:name":"Tecnolab Alimentare Snc Di Paganelli Dott. Ermes E Pazzi Dott. Lorenzo",
    "wof:placetype":"venue"
},
  "geometry": {"coordinates":[12.034868,44.226116],"type":"Point"}
}