{
  "type": "Feature",
  "properties": {
    "addr:full":"64028 Silvi Silvi Teramo 64028",
    "addr:postcode":"64028;64028",
    "iso:country":"IT",
    "sg:address":"64028 Silvi",
    "sg:city":"Silvi",
    "sg:orig_category":"Alberghi E Strutture Extra Alberghiere",
    "sg:phone":"+39 085 930141",
    "sg:postcode":"64028",
    "sg:province":"Teramo",
    "wof:name":"Ristorante Vecchia Silvi",
    "wof:placetype":"venue"
},
  "geometry": {"coordinates":[14.11679,42.520134],"type":"Point"}
}