{
  "type": "Feature",
  "properties": {
    "iso:country":"IT",
    "sg:address":"20093 Cologno Monzese",
    "sg:city":"Cologno Monzese",
    "sg:orig_category":"Servizi E Lavori Per Agricoltura E Zootecnia. Animali Domestici",
    "sg:phone":"+39 02 254 3324",
    "sg:postcode":"20093",
    "sg:province":"Milano",
    "wof:name":"Tovini Roberto",
    "wof:placetype":"venue"
},
  "geometry": {"coordinates":[9.278956,45.533028],"type":"Point"}
}