{
  "type": "Feature",
  "properties": {
    "addr:full":"20070 San Zenone Al Lambro San Zenone al Lambro Milano 20070",
    "addr:housenumber":"20070",
    "addr:postcode":"zenone;lambro;20070",
    "addr:street":"San",
    "iso:country":"IT",
    "sg:address":"20070 San Zenone Al Lambro",
    "sg:city":"San Zenone al Lambro",
    "sg:orig_category":"Servizi Per Lo Sport E Il Tempo Libero. Associazioni Ed Organismi Di Interesse Pubblico",
    "sg:phone":"+39 02 987441",
    "sg:postcode":"20070",
    "sg:province":"Milano",
    "wof:name":"Associazione Polisportiva La Locomotiva",
    "wof:placetype":"venue"
},
  "geometry": {"coordinates":[9.359522,45.324722],"type":"Point"}
}