{
  "type": "Feature",
  "properties": {
    "iso:country":"IT",
    "sg:address":"40017 San Giovanni In Persiceto",
    "sg:city":"San Giovanni in Persiceto",
    "sg:orig_category":"Motori Ed Organi Di Trasmissione",
    "sg:phone":"+39 051 681 0680",
    "sg:postcode":"40017",
    "sg:province":"Bologna",
    "wof:name":"Tecnoingranaggi Riduttori S.n.c.",
    "wof:placetype":"venue"
},
  "geometry": {"coordinates":[11.1893634796,44.6349029541],"type":"Point"}
}