{
  "type": "Feature",
  "properties": {
    "addr:full":"35043 Monselice Monselice Padova 35043",
    "addr:postcode":"35043;35043",
    "iso:country":"IT",
    "sg:address":"35043 Monselice",
    "sg:city":"Monselice",
    "sg:orig_category":"Ospedali E Servizi Sanitari",
    "sg:phone":"+39 0429 786666",
    "sg:postcode":"35043",
    "sg:province":"Padova",
    "sg:website":"http://www.iniziativamedica.it",
    "wof:name":"Iniziativa Medica Srl",
    "wof:placetype":"venue"
},
  "geometry": {"coordinates":[11.874748,45.404472],"type":"Point"}
}