{
  "type": "Feature",
  "properties": {
    "iso:country":"IT",
    "sg:address":"30023 Concordia Sagittaria",
    "sg:city":"Concordia Sagittaria",
    "sg:orig_category":"Assemblaggio Conto Terzi",
    "sg:phone":"+39 0421 275601",
    "sg:postcode":"30023",
    "sg:province":"Venezia",
    "wof:name":"Gitimont Srl",
    "wof:placetype":"venue"
},
  "geometry": {"coordinates":[12.811685,45.754463],"type":"Point"}
}