{
  "type": "Feature",
  "properties": {
    "iso:country":"IT",
    "sg:address":"00062 Bracciano",
    "sg:city":"Bracciano",
    "sg:orig_category":"Associazioni E Federazioni Sportive",
    "sg:phone":"+39 06 9980 3202",
    "sg:postcode":"00062",
    "sg:province":"Roma",
    "wof:name":"Festina Lente Srl Palestre",
    "wof:placetype":"venue"
},
  "geometry": {"coordinates":[12.176338,42.101982],"type":"Point"}
}