{
  "type": "Feature",
  "properties": {
    "iso:country":"IT",
    "sg:address":"4, Via Koristka Francesco 20154 Milano",
    "sg:city":"Milano",
    "sg:classifiers":[
        {
            "category":"Professional",
            "subcategory":"Engineering",
            "type":"Services"
        }
    ],
    "sg:phone":"+39 02 3360 0236",
    "sg:postcode":"20154",
    "sg:province":"Milano",
    "sg:tags":[
        "machine",
        "-",
        "mechanical"
    ],
    "wof:name":"Karrena (s.p.a.)",
    "wof:placetype":"venue"
},
  "geometry": {"coordinates":[9.1635694504,45.4867973328],"type":"Point"}
}