{
  "type": "Feature",
  "properties": {
    "addr:full":"37060 Nogarole Rocca Nogarole Rocca Verona 37060",
    "addr:postcode":"37060;37060",
    "iso:country":"IT",
    "sg:address":"37060 Nogarole Rocca",
    "sg:city":"Nogarole Rocca",
    "sg:orig_category":"Pubblica Amministrazione",
    "sg:phone":"+39 045 639 5158",
    "sg:postcode":"37060",
    "sg:province":"Verona",
    "wof:name":"Unione Dei Cinque Comuni",
    "wof:placetype":"venue"
},
  "geometry": {"coordinates":[10.8127231598,45.3028030396],"type":"Point"}
}