{
  "type": "Feature",
  "properties": {
    "addr:full":"43015 Noceto Noceto Parma 43015",
    "addr:postcode":"43015;43015",
    "iso:country":"IT",
    "sg:address":"43015 Noceto",
    "sg:city":"Noceto",
    "sg:orig_category":"Articoli Da Regalo. Shopping. Regalistica Aziendale",
    "sg:phone":"+39 0521 625398",
    "sg:postcode":"43015",
    "sg:province":"Parma",
    "wof:name":"Ristorante Aquila Romana",
    "wof:placetype":"venue"
},
  "geometry": {"coordinates":[10.178861,44.808636],"type":"Point"}
}