{
  "type": "Feature",
  "properties": {
    "iso:country":"IT",
    "sg:address":"80069 Vico Equense",
    "sg:city":"Vico Equense",
    "sg:orig_category":"Enoteche E Vendita Vini",
    "sg:phone":"+39 081 801 6420",
    "sg:postcode":"80069",
    "sg:province":"Napoli",
    "wof:name":"Gia.ma. Snc Di Di Guida Anna",
    "wof:placetype":"venue"
},
  "geometry": {"coordinates":[14.443848,40.661213],"type":"Point"}
}