{
  "type": "Feature",
  "properties": {
    "addr:full":"Via Sauro Nazario 32 47100 Forli' Forl\u00ec-Cesena 47100",
    "addr:housenumber":"32",
    "addr:postcode":"47100;47100",
    "addr:street":"Via Sauro Nazario;' Forli\u0300-Cesena",
    "iso:country":"IT",
    "sg:address":"Via Sauro Nazario 32 47100 Forli'",
    "sg:classifiers":[
        {
            "category":"Coffee & Tea",
            "type":"Food & Drink"
        }
    ],
    "sg:phone":"+39 0543 33321",
    "sg:postcode":"47100",
    "sg:province":"Forl\u00ec-Cesena",
    "sg:tags":[
        "raw",
        "decaffeinated"
    ],
    "sg:website":"www.mokadiscio.it",
    "wof:name":"Torrefazione Guarany Spa",
    "wof:placetype":"venue"
},
  "geometry": {"coordinates":[11.980461,43.994766],"type":"Point"}
}