{
  "type": "Feature",
  "properties": {
    "iso:country":"IT",
    "sg:address":"10058 Sestriere",
    "sg:city":"Sestriere",
    "sg:orig_category":"Non-classified Establishments",
    "sg:phone":"+39 0122 77444",
    "sg:postcode":"10058",
    "sg:province":"Torino",
    "wof:name":"Bois De Rose Sas",
    "wof:placetype":"venue"
},
  "geometry": {"coordinates":[6.887967,44.970013],"type":"Point"}
}