{
  "type": "Feature",
  "properties": {
    "iso:country":"IT",
    "sg:address":"10080 Ozegna",
    "sg:city":"Ozegna",
    "sg:orig_category":"Metalli E Leghe",
    "sg:phone":"+39 0124 424466",
    "sg:postcode":"10080",
    "sg:province":"Torino",
    "wof:name":"H.m.c. (s.r.l.)",
    "wof:placetype":"venue"
},
  "geometry": {"coordinates":[7.7513484955,45.3462791443],"type":"Point"}
}