{
  "type": "Feature",
  "properties": {
    "addr:full":"Via Mulini 2 03044 Cervaro Cervaro Frosinone 03044",
    "addr:housenumber":"2",
    "addr:postcode":"03044;03044",
    "addr:street":"Via Mulini",
    "iso:country":"IT",
    "sg:address":"Via Mulini 2 03044 Cervaro",
    "sg:city":"Cervaro",
    "sg:classifiers":[
        {
            "category":"Food & Beverages",
            "subcategory":"Specialty",
            "type":"Retail Goods"
        }
    ],
    "sg:phone":"+39 0776 367016",
    "sg:postcode":"03044",
    "sg:province":"Frosinone",
    "sg:tags":[
        "olive-oil"
    ],
    "wof:name":"Azienda Agricola Maraone M.",
    "wof:placetype":"venue"
},
  "geometry": {"coordinates":[13.906611,41.4799],"type":"Point"}
}