{
  "type": "Feature",
  "properties": {
    "iso:country":"IT",
    "sg:address":"97019 Vittoria",
    "sg:city":"Vittoria",
    "sg:orig_category":"Agricoltura, Orticoltura E Floricoltura",
    "sg:phone":"+39 0932 871464",
    "sg:postcode":"97019",
    "sg:province":"Ragusa",
    "wof:name":"Fontana Epifanio Imballaggi Fontana",
    "wof:placetype":"venue"
},
  "geometry": {"coordinates":[14.433086,36.891827],"type":"Point"}
}