{
  "type": "Feature",
  "properties": {
    "iso:country":"IT",
    "sg:address":"74100 Taranto",
    "sg:city":"Taranto",
    "sg:classifiers":[
        {
            "category":"Health Services",
            "subcategory":"Health Practitioner",
            "type":"Services"
        }
    ],
    "sg:phone":"+39 099 735 3630",
    "sg:postcode":"74100",
    "sg:province":"Taranto",
    "sg:tags":[
        "medici"
    ],
    "wof:name":"Mascellaro Dr.teresa & Annarita",
    "wof:placetype":"venue"
},
  "geometry": {"coordinates":[17.258087,40.464035],"type":"Point"}
}