{
  "type": "Feature",
  "properties": {
    "addr:full":"63014 Montegranaro Montegranaro Ascoli Piceno 63014",
    "addr:postcode":"63014;63014",
    "iso:country":"IT",
    "sg:address":"63014 Montegranaro",
    "sg:city":"Montegranaro",
    "sg:orig_category":"Studi E Consulenze Amministrative, Commerciali E Aziendali. Consulenze Tecniche, Amministrative E Perizie",
    "sg:phone":"+39 800 803 155",
    "sg:postcode":"63014",
    "sg:province":"Ascoli Piceno",
    "sg:website":"http://www.consula.it",
    "wof:name":"Consula Srl",
    "wof:placetype":"venue"
},
  "geometry": {"coordinates":[13.574977,42.8554],"type":"Point"}
}