{
  "type": "Feature",
  "properties": {
    "iso:country":"IT",
    "sg:address":"20020 Lainate",
    "sg:city":"Lainate",
    "sg:orig_category":"Apparecchiature Ed Attrezzature Meccaniche",
    "sg:phone":"+39 02 9379 9445",
    "sg:postcode":"20020",
    "sg:province":"Milano",
    "wof:name":"Panatronix Srl",
    "wof:placetype":"venue"
},
  "geometry": {"coordinates":[9.045439,45.525589],"type":"Point"}
}