{
  "type": "Feature",
  "properties": {
    "iso:country":"IT",
    "sg:address":"17, Via Mascagni Pietro 22066 Mariano Comense",
    "sg:city":"Mariano Comense",
    "sg:classifiers":[
        {
            "category":"Manufacturing",
            "subcategory":"Lumber",
            "type":"Manufacturing & Wholesale Goods"
        }
    ],
    "sg:phone":"+39 39031746015",
    "sg:postcode":"22066",
    "sg:province":"Como",
    "sg:tags":[
        "wood"
    ],
    "wof:name":"Comp Industria (s.p.a.)",
    "wof:placetype":"venue"
},
  "geometry": {"coordinates":[9.085456,45.811966],"type":"Point"}
}