{
  "type": "Feature",
  "properties": {
    "iso:country":"IT",
    "sg:address":"60025 Loreto",
    "sg:city":"Loreto",
    "sg:orig_category":"Medici. Assicurazioni E Servizi Assicurativi. Avvocati, Notai E Servizi Legali. Professionisti - Studi E Servizi Ed Associazioni Di Interesse Aziendale",
    "sg:phone":"+39 071 750 0794",
    "sg:postcode":"60025",
    "sg:province":"Ancona",
    "wof:name":"Gambini Fabiola",
    "wof:placetype":"venue"
},
  "geometry": {"coordinates":[13.6159772873,43.4384880066],"type":"Point"}
}