{
  "type": "Feature",
  "properties": {
    "addr:full":"23, Via Quintino Sella 13852 Cerreto Castello Cerreto Castello Biella 13852",
    "addr:postcode":"13852;13852",
    "addr:street":"Via Quintino Sella;Castello",
    "iso:country":"IT",
    "sg:address":"23, Via Quintino Sella 13852 Cerreto Castello",
    "sg:city":"Cerreto Castello",
    "sg:classifiers":[
        {
            "category":"Professional",
            "subcategory":"Engineering",
            "type":"Services"
        }
    ],
    "sg:phone":"+39 39015881715",
    "sg:postcode":"13852",
    "sg:province":"Biella",
    "sg:tags":[
        "machine",
        "-",
        "mechanical"
    ],
    "wof:name":"Officina Meccanica Di Cerreto Di Selva Bonino Giorgio-graziano & C. (s.a.s.)",
    "wof:placetype":"venue"
},
  "geometry": {"coordinates":[8.129254,45.563591],"type":"Point"}
}