{
  "type": "Feature",
  "properties": {
    "iso:country":"IT",
    "sg:address":"28053 Castelletto Sopra Ticino",
    "sg:city":"Castelletto sopra Ticino",
    "sg:orig_category":"Abbigliamento Sportivo, Jeans E Casuals - Vendita Al Dettaglio",
    "sg:phone":"+39 0331 920363",
    "sg:postcode":"28053",
    "sg:province":"Novara",
    "wof:name":"Planet Shoes Srl",
    "wof:placetype":"venue"
},
  "geometry": {"coordinates":[8.603868,45.719456],"type":"Point"}
}