{
  "type": "Feature",
  "properties": {
    "iso:country":"IT",
    "sg:address":"12100 Cuneo -",
    "sg:city":"Cuneo",
    "sg:orig_category":"Automobili - Commercio",
    "sg:phone":"+39 0171 682594",
    "sg:postcode":"12100",
    "sg:province":"Cuneo",
    "wof:name":"Auto Mattiauda Di Mattiauda P. Giorgi & C. Snc",
    "wof:placetype":"venue"
},
  "geometry": {"coordinates":[7.568185,44.459415],"type":"Point"}
}