{
  "type": "Feature",
  "properties": {
    "iso:country":"IT",
    "sg:address":"20127 Milano",
    "sg:city":"Milano",
    "sg:orig_category":"Scuole E Servizi Scolastici. Servizi Per Lo Sport E Il Tempo Libero",
    "sg:phone":"+39 02 2804 0100",
    "sg:postcode":"20127",
    "sg:province":"Milano",
    "wof:name":"Centro Nautico Utopia",
    "wof:placetype":"venue"
},
  "geometry": {"coordinates":[9.215817,45.488331],"type":"Point"}
}