{
  "type": "Feature",
  "properties": {
    "iso:country":"IT",
    "sg:address":"00172 Roma",
    "sg:city":"Roma",
    "sg:orig_category":"Servizi E Lavori Per Edilizia E Lavori Pubblici. Servizi E Lavori Per Ecologia E Smaltimento Rifiuti",
    "sg:phone":"+39 06 2321 9198",
    "sg:postcode":"00172",
    "sg:province":"Roma",
    "wof:name":"Blu Ambiente Snc",
    "wof:placetype":"venue"
},
  "geometry": {"coordinates":[12.572833,41.880943],"type":"Point"}
}