{
  "type": "Feature",
  "properties": {
    "addr:full":"Via Maggio 13 50125 Firenze Firenze Firenze 50125",
    "addr:housenumber":"13",
    "addr:postcode":"50125;50125",
    "addr:street":"Via Maggio",
    "iso:country":"IT",
    "sg:address":"Via Maggio 13 50125 Firenze",
    "sg:city":"Firenze",
    "sg:classifiers":[
        {
            "category":"Arts & Performance",
            "subcategory":"Dance",
            "type":"Entertainment"
        }
    ],
    "sg:phone":"+39 055 287519",
    "sg:postcode":"50125",
    "sg:province":"Firenze",
    "sg:tags":[
        "nouveau",
        "lamp"
    ],
    "wof:name":"Gherardo Degli Albizzi Srl",
    "wof:placetype":"venue"
},
  "geometry": {"coordinates":[11.214581,43.708813],"type":"Point"}
}