{
  "type": "Feature",
  "properties": {
    "iso:country":"IT",
    "sg:address":"29100 Piacenza",
    "sg:city":"Piacenza",
    "sg:orig_category":"Psicologi - Studi",
    "sg:phone":"+39 0523 325638",
    "sg:postcode":"29100",
    "sg:province":"Piacenza",
    "wof:name":"Sgorbani Annamaria",
    "wof:placetype":"venue"
},
  "geometry": {"coordinates":[9.6993198395,45.049621582],"type":"Point"}
}