{
  "type": "Feature",
  "properties": {
    "iso:country":"IT",
    "sg:address":"00063 Campagnano Di Roma",
    "sg:city":"Campagnano di Roma",
    "sg:orig_category":"Cinematografia E Radiotelevisione",
    "sg:phone":"+39 06 907 7130",
    "sg:postcode":"00063",
    "sg:province":"Roma",
    "wof:name":"Audio Experience Di Lucci Fabio Massimo",
    "wof:placetype":"venue"
},
  "geometry": {"coordinates":[12.40172,42.114609],"type":"Point"}
}