{
  "type": "Feature",
  "properties": {
    "addr:full":"12/r, Lungo Torrente Secca 16163 Genova Genova Genova 16163",
    "addr:housenumber":"12 / r",
    "addr:postcode":"16163;16163",
    "addr:street":"Secca",
    "iso:country":"IT",
    "sg:address":"12/r, Lungo Torrente Secca 16163 Genova",
    "sg:city":"Genova",
    "sg:classifiers":[
        {
            "category":"Professional",
            "subcategory":"Printing & Photocopies",
            "type":"Services"
        }
    ],
    "sg:phone":"+39 39010710241",
    "sg:postcode":"16163",
    "sg:province":"Genova",
    "wof:name":"Martelli Graficart Srl",
    "wof:placetype":"venue"
},
  "geometry": {"coordinates":[8.9339885712,44.4070625305],"type":"Point"}
}