{
  "type": "Feature",
  "properties": {
    "addr:full":"282/a, Via Iv Novembre 28887 Omegna Omegna Verbano-Cusio-Ossola 28887",
    "addr:housenumber":"282 / a",
    "addr:postcode":"28887;28887",
    "addr:street":"Via Iv Novembre",
    "iso:country":"IT",
    "sg:address":"282/a, Via Iv Novembre 28887 Omegna",
    "sg:city":"Omegna",
    "sg:classifiers":[
        {
            "category":"Manufacturing",
            "subcategory":"Paper Products",
            "type":"Manufacturing & Wholesale Goods"
        }
    ],
    "sg:phone":"+39 39032363993",
    "sg:postcode":"28887",
    "sg:province":"Verbano-Cusio-Ossola",
    "sg:tags":[
        "cardboard"
    ],
    "wof:name":"Euroadhesiv S.r.l.",
    "wof:placetype":"venue"
},
  "geometry": {"coordinates":[8.2724647522,46.1399688721],"type":"Point"}
}