{
  "type": "Feature",
  "properties": {
    "iso:country":"IT",
    "sg:address":"39, Via Giuseppe Mazzini 21050 Gorla Maggiore",
    "sg:city":"Gorla Maggiore",
    "sg:classifiers":[
        {
            "category":"Shopping",
            "subcategory":"Clothing, Apparel, & Fashions",
            "type":"Retail Goods"
        }
    ],
    "sg:phone":"+39 0331 619960",
    "sg:postcode":"21050",
    "sg:province":"Varese",
    "sg:tags":[
        "clothes"
    ],
    "wof:name":"Manifattura Panda (s.r.l.)",
    "wof:placetype":"venue"
},
  "geometry": {"coordinates":[8.894556,45.662285],"type":"Point"}
}