{
  "type": "Feature",
  "properties": {
    "iso:country":"IT",
    "sg:address":"90121 Palermo",
    "sg:city":"Palermo",
    "sg:orig_category":"Agricoltura, Orticoltura E Floricoltura",
    "sg:phone":"+39 091 307783",
    "sg:postcode":"90121",
    "sg:province":"Palermo",
    "wof:name":"Ente Tabacchi Italiani S.p.a.",
    "wof:placetype":"venue"
},
  "geometry": {"coordinates":[13.345078,38.128525],"type":"Point"}
}