{
  "type": "Feature",
  "properties": {
    "iso:country":"IT",
    "sg:address":"17021 Alassio",
    "sg:city":"Alassio",
    "sg:orig_category":"Dischi, Musicassette E Compact Disc - Vendita Al Dettaglio",
    "sg:phone":"+39 0182 646071",
    "sg:postcode":"17021",
    "sg:province":"Savona",
    "wof:name":"Babilonia",
    "wof:placetype":"venue"
},
  "geometry": {"coordinates":[8.16117,44.017982],"type":"Point"}
}