{
  "type": "Feature",
  "properties": {
    "iso:country":"IT",
    "sg:address":"81, Via Molinara 25036 Palazzolo Sull'oglio",
    "sg:classifiers":[
        {
            "category":"Shopping",
            "subcategory":"Crafts & Fabrics",
            "type":"Retail Goods"
        }
    ],
    "sg:phone":"+39 390 307 4091",
    "sg:postcode":"25036",
    "sg:province":"Brescia",
    "wof:name":"Cotonificio Roberto Ferrari (s.p.a.)",
    "wof:placetype":"venue"
},
  "geometry": {"coordinates":[9.8205432892,45.6405982971],"type":"Point"}
}