{
  "type": "Feature",
  "properties": {
    "iso:country":"IT",
    "sg:address":"95011 Calatabiano",
    "sg:city":"Calatabiano",
    "sg:orig_category":"Materiali Edili",
    "sg:phone":"+39 095 641303",
    "sg:postcode":"95011",
    "sg:province":"Catania",
    "wof:name":"Fratelli Finocchiaro Di F. Natale Antonino & C. Snc",
    "wof:placetype":"venue"
},
  "geometry": {"coordinates":[15.20778,37.81662],"type":"Point"}
}