{
  "type": "Feature",
  "properties": {
    "iso:country":"IT",
    "sg:address":"83026 Montoro Superiore",
    "sg:city":"Montoro Superiore",
    "sg:orig_category":"Calzature, Pelletterie E Pelli",
    "sg:phone":"+39 0825 597717",
    "sg:postcode":"83026",
    "sg:province":"Avellino",
    "wof:name":"Mik Marpel Di Cirino Mario",
    "wof:placetype":"venue"
},
  "geometry": {"coordinates":[14.804606,40.826424],"type":"Point"}
}