{
  "type": "Feature",
  "properties": {
    "addr:full":"52037 Sansepolcro Sansepolcro Arezzo 52037",
    "addr:postcode":"52037;52037",
    "iso:country":"IT",
    "sg:address":"52037 Sansepolcro",
    "sg:city":"Sansepolcro",
    "sg:orig_category":"Metalli E Leghe",
    "sg:phone":"+39 0575 749511",
    "sg:postcode":"52037",
    "sg:province":"Arezzo",
    "sg:website":"http://www.giorniferro.it",
    "wof:name":"Giorni Ferro Spa",
    "wof:placetype":"venue"
},
  "geometry": {"coordinates":[12.1289710999,43.5921516418],"type":"Point"}
}