{
  "type": "Feature",
  "properties": {
    "addr:full":"61100 Pesaro Pesaro Pesaro E Urbino 61100",
    "addr:postcode":"61100;61100",
    "iso:country":"IT",
    "sg:address":"61100 Pesaro",
    "sg:city":"Pesaro",
    "sg:orig_category":"Prodotti Chimici Secondari. Prodotti Cosmetici E Da Toeletta",
    "sg:phone":"+39 0721 415707",
    "sg:postcode":"61100",
    "sg:province":"Pesaro E Urbino",
    "wof:name":"Skin System Srl",
    "wof:placetype":"venue"
},
  "geometry": {"coordinates":[12.8774986267,43.9041900635],"type":"Point"}
}