{
  "type": "Feature",
  "properties": {
    "addr:full":"20068 Peschiera Borromeo Peschiera Borromeo Milano 20068",
    "addr:postcode":"20068;20068",
    "iso:country":"IT",
    "sg:address":"20068 Peschiera Borromeo",
    "sg:city":"Peschiera Borromeo",
    "sg:classifiers":[
        {
            "category":"Health Services",
            "subcategory":"Health Practitioner",
            "type":"Services"
        }
    ],
    "sg:phone":"+39 02 5530 0203",
    "sg:postcode":"20068",
    "sg:province":"Milano",
    "sg:tags":[
        "medici"
    ],
    "wof:name":"Graffagnino Gioacchino",
    "wof:placetype":"venue"
},
  "geometry": {"coordinates":[9.264519,45.40126],"type":"Point"}
}