{
  "type": "Feature",
  "properties": {
    "addr:full":"66, Via Bergamo 20040 Bellusco Bellusco Milano 20040",
    "addr:postcode":"20040;20040",
    "addr:street":"Via Bergamo",
    "iso:country":"IT",
    "sg:address":"66, Via Bergamo 20040 Bellusco",
    "sg:city":"Bellusco",
    "sg:classifiers":[
        {
            "category":"Shopping",
            "subcategory":"Crafts & Fabrics",
            "type":"Retail Goods"
        }
    ],
    "sg:phone":"+39 39039623605",
    "sg:postcode":"20040",
    "sg:province":"Milano",
    "wof:name":"Torcitura Lei - Tsu (s.r.l.)",
    "wof:placetype":"venue"
},
  "geometry": {"coordinates":[9.4243507385,45.616771698],"type":"Point"}
}