{
  "type": "Feature",
  "properties": {
    "addr:full":"84025 Eboli Eboli Salerno 84025",
    "addr:postcode":"84025;84025",
    "iso:country":"IT",
    "sg:address":"84025 Eboli",
    "sg:city":"Eboli",
    "sg:orig_category":"Bevande, Vini E Liquori",
    "sg:phone":"+39 0828 367382",
    "sg:postcode":"84025",
    "sg:province":"Salerno",
    "wof:name":"Della Corte Luca Antonio",
    "wof:placetype":"venue"
},
  "geometry": {"coordinates":[14.96225,40.522766],"type":"Point"}
}