{
  "type": "Feature",
  "properties": {
    "iso:country":"IT",
    "sg:address":"80131 Napoli",
    "sg:city":"Napoli",
    "sg:orig_category":"Forniture Per Edilizia E Lavori Pubblici. Prodotti Vari In Metallo",
    "sg:phone":"+39 081 545 1269",
    "sg:postcode":"80131",
    "sg:province":"Napoli",
    "wof:name":"Gedech Pont Di De Chiara Sas",
    "wof:placetype":"venue"
},
  "geometry": {"coordinates":[14.2133274078,40.868057251],"type":"Point"}
}