{
  "type": "Feature",
  "properties": {
    "addr:full":"80078 Pozzuoli Pozzuoli Napoli 80078",
    "addr:postcode":"80078;80078",
    "iso:country":"IT",
    "sg:address":"80078 Pozzuoli",
    "sg:city":"Pozzuoli",
    "sg:orig_category":"Pompe. Macchine, Strumenti Ed Apparecchi Per Attivita' Industriali",
    "sg:phone":"+39 081 524 2600",
    "sg:postcode":"80078",
    "sg:province":"Napoli",
    "wof:name":"Elettro.nav. Sas Di Grillo Guido & C.",
    "wof:placetype":"venue"
},
  "geometry": {"coordinates":[14.1704874039,40.8581962585],"type":"Point"}
}