{
  "type": "Feature",
  "properties": {
    "iso:country":"IT",
    "sg:address":"Via Rontani 929/c 55050 Bozzano",
    "sg:orig_category":"Ladies' Shoes",
    "sg:phone":"+39 0584 93163",
    "sg:province":"LU",
    "wof:name":"Calzaturificio Toscana Nord Srl",
    "wof:placetype":"venue"
},
  "geometry": {"coordinates":[10.356757,43.864052],"type":"Point"}
}