{
  "type": "Feature",
  "properties": {
    "addr:full":"20048 Carate Brianza Carate Brianza Milano 20048",
    "addr:postcode":"20048;20048",
    "iso:country":"IT",
    "sg:address":"20048 Carate Brianza",
    "sg:city":"Carate Brianza",
    "sg:orig_category":"Radiatori Riscaldamento",
    "sg:phone":"+39 036 291 2200",
    "sg:postcode":"20048",
    "sg:province":"Milano",
    "wof:name":"D.a.s. Di Dascola Aurelio",
    "wof:placetype":"venue"
},
  "geometry": {"coordinates":[9.175157,45.633572],"type":"Point"}
}