{
  "type": "Feature",
  "properties": {
    "addr:full":"24040 Madone Madone Bergamo 24040",
    "addr:postcode":"24040;24040",
    "iso:country":"IT",
    "sg:address":"24040 Madone",
    "sg:city":"Madone",
    "sg:orig_category":"Apparecchiature Ed Attrezzature Meccaniche",
    "sg:phone":"+39 035 991103",
    "sg:postcode":"24040",
    "sg:province":"Bergamo",
    "wof:name":"Milanoflex (s.p.a.)",
    "wof:placetype":"venue"
},
  "geometry": {"coordinates":[9.742456,45.692375],"type":"Point"}
}