{
  "type": "Feature",
  "properties": {
    "addr:full":"97, Viale Della Navigazione Interna 35027 Noventa Padovana Noventa Padovana Padova 35027",
    "addr:housenumber":"97",
    "addr:postcode":"35027;35027",
    "addr:street":"Viale Della Navigazione Interna",
    "iso:country":"IT",
    "sg:address":"97, Viale Della Navigazione Interna 35027 Noventa Padovana",
    "sg:city":"Noventa Padovana",
    "sg:classifiers":[
        {
            "category":"Manufacturing",
            "subcategory":"Food",
            "type":"Manufacturing & Wholesale Goods"
        }
    ],
    "sg:phone":"+39 049 780 0155",
    "sg:postcode":"35027",
    "sg:province":"Padova",
    "sg:tags":[
        "equipment",
        "processing",
        "-",
        "machinery"
    ],
    "wof:name":"Martellato Snc Di Martellato Alessandro E Dario",
    "wof:placetype":"venue"
},
  "geometry": {"coordinates":[11.929816246,45.4086837769],"type":"Point"}
}