{
  "type": "Feature",
  "properties": {
    "addr:full":"Via Borgomanero, 90/92 28012 Cressa Cressa Novara 28012",
    "addr:housenumber":"90 / 92",
    "addr:postcode":"28012;28012",
    "addr:street":"Via Borgomanero",
    "iso:country":"IT",
    "sg:address":"Via Borgomanero, 90/92 28012 Cressa",
    "sg:city":"Cressa",
    "sg:orig_category":"Fittings, Valves",
    "sg:phone":"+39 0322 863655",
    "sg:postcode":"28012",
    "sg:province":"Novara",
    "sg:website":"www.everflowsrl.com",
    "wof:name":"Everflow By Inuggi Srl",
    "wof:placetype":"venue"
},
  "geometry": {"coordinates":[8.4968633652,45.6527481079],"type":"Point"}
}