{
  "type": "Feature",
  "properties": {
    "addr:full":"Via Selva 21 33085 Maniago Maniago Pordenone 33085",
    "addr:housenumber":"21",
    "addr:postcode":"33085;33085",
    "addr:street":"Via Selva",
    "iso:country":"IT",
    "sg:address":"Via Selva 21 33085 Maniago",
    "sg:city":"Maniago",
    "sg:classifiers":[
        {
            "category":"Food & Beverages",
            "subcategory":"Farmers Market",
            "type":"Retail Goods"
        }
    ],
    "sg:phone":"+39 0427 71271",
    "sg:postcode":"33085",
    "sg:province":"Pordenone",
    "sg:tags":[
        "opener",
        "bottle"
    ],
    "sg:website":"www.farfalli.com",
    "wof:name":"Farfalli Srl",
    "wof:placetype":"venue"
},
  "geometry": {"coordinates":[12.698723,46.168018],"type":"Point"}
}