{
  "type": "Feature",
  "properties": {
    "addr:full":"Contrada Saline 65013 Citta' Sant'angelo Pescara 65013",
    "addr:postcode":"65013 citta;65013",
    "addr:street":"Contrada Saline",
    "iso:country":"IT",
    "sg:address":"Contrada Saline 65013 Citta' Sant'angelo",
    "sg:classifiers":[
        {
            "category":"Manufacturing",
            "subcategory":"Paper Products",
            "type":"Manufacturing & Wholesale Goods"
        }
    ],
    "sg:phone":"+39 39085959321",
    "sg:postcode":"65013",
    "sg:province":"Pescara",
    "sg:tags":[
        "cardboard"
    ],
    "wof:name":"Muratti S.r.l.",
    "wof:placetype":"venue"
},
  "geometry": {"coordinates":[14.1408100128,42.5246810913],"type":"Point"}
}