{
  "type": "Feature",
  "properties": {
    "iso:country":"IT",
    "sg:address":"00153 Roma",
    "sg:city":"Roma",
    "sg:orig_category":"Servizi E Lavori Per Arredamento E Industria Del Legno. Arte Ed Artigianato Artistico",
    "sg:phone":"+39 06 580 3385",
    "sg:postcode":"00153",
    "sg:province":"Roma",
    "wof:name":"Santilli Francesco",
    "wof:placetype":"venue"
},
  "geometry": {"coordinates":[12.477508,41.887867],"type":"Point"}
}