{
  "type": "Feature",
  "properties": {
    "iso:country":"IT",
    "sg:address":"44100 Ferrara",
    "sg:city":"Ferrara",
    "sg:orig_category":"Condizionatori Aria - Produzione",
    "sg:phone":"+39 0532 774066",
    "sg:postcode":"44100",
    "sg:province":"Ferrara",
    "sg:website":"http://www.pacetti.it",
    "wof:name":"Art Di Pacetti & C. Sas",
    "wof:placetype":"venue"
},
  "geometry": {"coordinates":[11.598012,44.848301],"type":"Point"}
}