{
  "type": "Feature",
  "properties": {
    "addr:full":"Via Baschenis 11 24044 Dalmine Dalmine Bergamo 24044",
    "addr:housenumber":"11",
    "addr:postcode":"24044;24044",
    "addr:street":"Via Baschenis",
    "iso:country":"IT",
    "sg:address":"Via Baschenis 11 24044 Dalmine",
    "sg:city":"Dalmine",
    "sg:classifiers":[
        {
            "category":"Retail",
            "subcategory":"Event Space",
            "type":"Services"
        }
    ],
    "sg:phone":"+39 035 370777",
    "sg:postcode":"24044",
    "sg:province":"Bergamo",
    "sg:tags":[
        "wire",
        "bare"
    ],
    "sg:website":"www.filatilastex.com.my",
    "wof:name":"Filati Lastex Sdn.bhd",
    "wof:placetype":"venue"
},
  "geometry": {"coordinates":[9.614988,45.64587],"type":"Point"}
}