{
  "type": "Feature",
  "properties": {
    "iso:country":"IT",
    "sg:address":"20089 Rozzano",
    "sg:city":"Rozzano",
    "sg:orig_category":"Climatizzazione E Condizionamento, Apparecchiature E Servizi. Accessori Dei Mezzi Di Trasporto",
    "sg:phone":"+39 02 8920 0781",
    "sg:postcode":"20089",
    "sg:province":"Milano",
    "wof:name":"Climar Di Martino Giovanni E Figli",
    "wof:placetype":"venue"
},
  "geometry": {"coordinates":[9.15622,45.397789],"type":"Point"}
}