{
  "type": "Feature",
  "properties": {
    "addr:full":"Via Limitese 106 50059 Vinci Vinci Firenze 50059",
    "addr:housenumber":"106",
    "addr:postcode":"50059;50059",
    "addr:street":"Via Limitese",
    "iso:country":"IT",
    "sg:address":"Via Limitese 106 50059 Vinci",
    "sg:city":"Vinci",
    "sg:classifiers":[
        {
            "category":"Shopping",
            "subcategory":"Clothing, Apparel, & Fashions",
            "type":"Retail Goods"
        }
    ],
    "sg:phone":"+39 0571 75811",
    "sg:postcode":"50059",
    "sg:province":"Firenze",
    "sg:tags":[
        "image",
        "clothing",
        "basic"
    ],
    "sg:website":"www.allegri.it",
    "wof:name":"Dismi 92 Spa",
    "wof:placetype":"venue"
},
  "geometry": {"coordinates":[10.956163,43.73341],"type":"Point"}
}