{
  "type": "Feature",
  "properties": {
    "iso:country":"IT",
    "sg:address":"10128 Torino",
    "sg:city":"Torino",
    "sg:orig_category":"Imprese Di Costruzioni Civili Ed Industriali",
    "sg:phone":"+39 011 549314",
    "sg:postcode":"10128",
    "sg:province":"Torino",
    "wof:name":"Impresa Monateri S.r.l.",
    "wof:placetype":"venue"
},
  "geometry": {"coordinates":[7.669201,45.06216],"type":"Point"}
}