{
  "type": "Feature",
  "properties": {
    "iso:country":"IT",
    "sg:address":"20010 Vanzago",
    "sg:city":"Vanzago",
    "sg:orig_category":"Arte Ed Artigianato Artistico",
    "sg:phone":"+39 02 934 0100",
    "sg:postcode":"20010",
    "sg:province":"Milano",
    "wof:name":"Corsanini Gino",
    "wof:placetype":"venue"
},
  "geometry": {"coordinates":[9.024891,45.500134],"type":"Point"}
}