{
  "type": "Feature",
  "properties": {
    "iso:country":"IT",
    "sg:address":"00154 Roma",
    "sg:city":"Roma",
    "sg:orig_category":"Serigrafia",
    "sg:phone":"+39 06 5160 7350",
    "sg:postcode":"00154",
    "sg:province":"Roma",
    "wof:name":"Kiwigraph Sas",
    "wof:placetype":"venue"
},
  "geometry": {"coordinates":[12.488041,41.86636],"type":"Point"}
}