{
  "type": "Feature",
  "properties": {
    "addr:full":"75012 Bernalda Bernalda Matera 75012",
    "addr:postcode":"75012;75012",
    "iso:country":"IT",
    "sg:address":"75012 Bernalda",
    "sg:city":"Bernalda",
    "sg:orig_category":"Prodotti E Manufatti In Materie Plastiche",
    "sg:phone":"+39 0835 544160",
    "sg:postcode":"75012",
    "sg:province":"Matera",
    "wof:name":"Favale Giuseppe",
    "wof:placetype":"venue"
},
  "geometry": {"coordinates":[16.6905651093,40.4086914062],"type":"Point"}
}