{
  "type": "Feature",
  "properties": {
    "addr:full":"15055 Pontecurone Pontecurone Alessandria 15055",
    "addr:housenumber":"15055",
    "addr:postcode":"15055",
    "addr:street":"Pontecurone Pontecurone",
    "iso:country":"IT",
    "sg:address":"15055 Pontecurone",
    "sg:city":"Pontecurone",
    "sg:orig_category":"Macchine, Impianti Ed Attrezzature Per Agricoltura E Zootecnia",
    "sg:phone":"+39 0131 886647",
    "sg:postcode":"15055",
    "sg:province":"Alessandria",
    "wof:name":"Selis Giuseppe Agricab",
    "wof:placetype":"venue"
},
  "geometry": {"coordinates":[8.615396,44.889412],"type":"Point"}
}