{
  "type": "Feature",
  "properties": {
    "addr:full":"69, Via Ponte Alle Mosse 50144 Firenze Firenze Firenze 50144",
    "addr:postcode":"50144;50144",
    "addr:street":"Via Ponte Alle Mosse",
    "iso:country":"IT",
    "sg:address":"69, Via Ponte Alle Mosse 50144 Firenze",
    "sg:city":"Firenze",
    "sg:classifiers":[
        {
            "category":"Manufacturing",
            "subcategory":"Metals",
            "type":"Manufacturing & Wholesale Goods"
        }
    ],
    "sg:phone":"+39 39055330952",
    "sg:postcode":"50144",
    "sg:province":"Firenze",
    "sg:tags":[
        "metallurgy",
        "metalworking"
    ],
    "wof:name":"Manetti Giusto Battiloro S.a.s.",
    "wof:placetype":"venue"
},
  "geometry": {"coordinates":[11.2361478806,43.7815742493],"type":"Point"}
}