{
  "type": "Feature",
  "properties": {
    "iso:country":"IT",
    "sg:address":"15, Via Serio 24021 Albino",
    "sg:city":"Albino",
    "sg:classifiers":[
        {
            "category":"Real Estate",
            "subcategory":"Surveying",
            "type":"Services"
        }
    ],
    "sg:phone":"+39 39035752909",
    "sg:postcode":"24021",
    "sg:province":"Bergamo",
    "sg:tags":[
        "equipment",
        "material",
        "good",
        "-",
        "handling"
    ],
    "wof:name":"Armanni Carrelli Elevatori (s.r.l.)",
    "wof:placetype":"venue"
},
  "geometry": {"coordinates":[9.748095,45.737953],"type":"Point"}
}