{
  "type": "Feature",
  "properties": {
    "addr:full":"Borgo San Frediano 47/n 50124 Firenze Firenze Firenze 50124",
    "addr:housenumber":"47 / n",
    "addr:postcode":"50124;50124",
    "addr:street":"Borgo San Frediano",
    "iso:country":"IT",
    "sg:address":"Borgo San Frediano 47/n 50124 Firenze",
    "sg:city":"Firenze",
    "sg:classifiers":[
        {
            "category":"Community Center",
            "subcategory":"Social",
            "type":"Public Place"
        }
    ],
    "sg:phone":"+39 055 239 6760",
    "sg:postcode":"50124",
    "sg:province":"Firenze",
    "sg:tags":[
        "lamp",
        "period"
    ],
    "sg:website":"www.ilparalume.it",
    "wof:name":"Il Paralume",
    "wof:placetype":"venue"
},
  "geometry": {"coordinates":[10.7479085922,43.8607368469],"type":"Point"}
}