{
  "type": "Feature",
  "properties": {
    "addr:full":"20124 Milano Milano Milano 20124",
    "addr:postcode":"20124;20124",
    "iso:country":"IT",
    "sg:address":"20124 Milano",
    "sg:city":"Milano",
    "sg:orig_category":"Ospedali E Servizi Sanitari",
    "sg:phone":"+39 02 2024 1526",
    "sg:postcode":"20124",
    "sg:province":"Milano",
    "wof:name":"Mascherpa Elisabetta Silvia",
    "wof:placetype":"venue"
},
  "geometry": {"coordinates":[9.206845,45.476265],"type":"Point"}
}