{
  "type": "Feature",
  "properties": {
    "iso:country":"IT",
    "sg:address":"60027 Osimo",
    "sg:city":"Osimo",
    "sg:orig_category":"Servizi E Lavori Per Arredamento E Industria Del Legno",
    "sg:phone":"+39 071 717481",
    "sg:postcode":"60027",
    "sg:province":"Ancona",
    "wof:name":"Aerre Di Re Alberto",
    "wof:placetype":"venue"
},
  "geometry": {"coordinates":[13.487013,43.461319],"type":"Point"}
}