{
  "type": "Feature",
  "properties": {
    "addr:full":"30030 Pianiga Pianiga Venezia 30030",
    "addr:postcode":"30030;30030",
    "iso:country":"IT",
    "sg:address":"30030 Pianiga",
    "sg:city":"Pianiga",
    "sg:orig_category":"Forniture Alle Strutture Ricettive. Macchine E Impianti Per Attivita' Commerciali Ed Artigianali",
    "sg:phone":"+39 041 519 5444",
    "sg:postcode":"30030",
    "sg:province":"Venezia",
    "sg:website":"http://www.lanuovaera.com",
    "wof:name":"La Nuova Era Srl",
    "wof:placetype":"venue"
},
  "geometry": {"coordinates":[12.0380420685,45.4512634277],"type":"Point"}
}