{
  "type": "Feature",
  "properties": {
    "iso:country":"IT",
    "sg:address":"36015 Schio",
    "sg:city":"Schio",
    "sg:orig_category":"Tempo Libero - Articoli E Forniture. Regalistica Aziendale",
    "sg:phone":"+39 0445 527870",
    "sg:postcode":"36015",
    "sg:province":"Vicenza",
    "wof:name":"Sandri Sonia - Cartoleria Boldu'",
    "wof:placetype":"venue"
},
  "geometry": {"coordinates":[11.358963,45.725388],"type":"Point"}
}