{
  "type": "Feature",
  "properties": {
    "addr:full":"43100 Parma Parma Parma 43100",
    "addr:postcode":"43100;43100",
    "iso:country":"IT",
    "sg:address":"43100 Parma",
    "sg:city":"Parma",
    "sg:orig_category":"Ospedali E Servizi Sanitari. Servizi Sociali",
    "sg:phone":"+39 0521 220011",
    "sg:postcode":"43100",
    "sg:province":"Parma",
    "sg:website":"http://www.proges.it",
    "wof:name":"Pro.ges. Soc.coop.r.l.",
    "wof:placetype":"venue"
},
  "geometry": {"coordinates":[10.321516,44.69503],"type":"Point"}
}