{
  "type": "Feature",
  "properties": {
    "addr:full":"15, Via Minzoni Don 25065 Lumezzane Lumezzane Brescia 25065",
    "addr:postcode":"25065;25065",
    "addr:street":"Via Minzoni Don",
    "iso:country":"IT",
    "sg:address":"15, Via Minzoni Don 25065 Lumezzane",
    "sg:city":"Lumezzane",
    "sg:classifiers":[
        {
            "category":"Shopping",
            "type":"Retail Goods"
        }
    ],
    "sg:phone":"+39 030 897 0661",
    "sg:postcode":"25065",
    "sg:province":"Brescia",
    "sg:tags":[
        "finished",
        "-",
        "metallic"
    ],
    "wof:name":"A.s. Di Sala Achille Di Sala Luciano & C. Snc",
    "wof:placetype":"venue"
},
  "geometry": {"coordinates":[10.2180271149,45.6055641174],"type":"Point"}
}