{
  "type": "Feature",
  "properties": {
    "addr:full":"51100 Pistoia Pistoia Pistoia 51100",
    "addr:postcode":"51100;51100",
    "iso:country":"IT",
    "sg:address":"51100 Pistoia",
    "sg:city":"Pistoia",
    "sg:classifiers":[
        {
            "category":"Community Center",
            "subcategory":"Youth",
            "type":"Public Place"
        }
    ],
    "sg:phone":"+39 0573 367680",
    "sg:postcode":"51100",
    "sg:province":"Pistoia",
    "sg:tags":[
        "underwear",
        "bathing",
        "stocking",
        "costume"
    ],
    "wof:name":"Se.al. Creazioni Srl",
    "wof:placetype":"venue"
},
  "geometry": {"coordinates":[10.899513,43.934341],"type":"Point"}
}