{
  "type": "Feature",
  "properties": {
    "addr:full":"34072 Farra D'isonzo Gorizia 34072",
    "addr:postcode":"34072;34072",
    "iso:country":"IT",
    "sg:address":"34072 Farra D'isonzo",
    "sg:orig_category":"Utensili Meccanici E Materiali",
    "sg:phone":"+39 0481 889007",
    "sg:postcode":"34072",
    "sg:province":"Gorizia",
    "wof:name":"Modelleria Zorzenon",
    "wof:placetype":"venue"
},
  "geometry": {"coordinates":[13.536602,45.904388],"type":"Point"}
}