{
  "type": "Feature",
  "properties": {
    "iso:country":"IT",
    "sg:address":"36, Via Carboncine 31056 Roncade",
    "sg:city":"Roncade",
    "sg:classifiers":[
        {
            "category":"Manufacturing",
            "subcategory":"Lumber",
            "type":"Manufacturing & Wholesale Goods"
        }
    ],
    "sg:phone":"+39 0422 849076",
    "sg:postcode":"31056",
    "sg:province":"Treviso",
    "sg:tags":[
        "wood"
    ],
    "wof:name":"Beninca",
    "wof:placetype":"venue"
},
  "geometry": {"coordinates":[12.383131,45.647732],"type":"Point"}
}