{
  "type": "Feature",
  "properties": {
    "addr:full":"07041 Alghero Alghero Sassari 07041",
    "addr:postcode":"07041;07041",
    "iso:country":"IT",
    "sg:address":"07041 Alghero",
    "sg:city":"Alghero",
    "sg:orig_category":"Fotografia Pubblicitaria",
    "sg:phone":"+39 079 973 3000",
    "sg:postcode":"07041",
    "sg:province":"Sassari",
    "wof:name":"Fotoedizioni Madau",
    "wof:placetype":"venue"
},
  "geometry": {"coordinates":[8.31798172,40.5542449951],"type":"Point"}
}