{
  "type": "Feature",
  "properties": {
    "iso:country":"IT",
    "sg:address":"31057 Silea",
    "sg:city":"Silea",
    "sg:orig_category":"Prodotti Alimentari",
    "sg:phone":"+39 0422 683003",
    "sg:postcode":"31057",
    "sg:province":"Treviso",
    "wof:name":"Bellio Fratelli Srl",
    "wof:placetype":"venue"
},
  "geometry": {"coordinates":[12.3043375015,45.6471061707],"type":"Point"}
}