{
  "type": "Feature",
  "properties": {
    "iso:country":"IT",
    "sg:address":"37020 Marano Di Valpolicella",
    "sg:city":"Marano di Valpolicella",
    "sg:orig_category":"Cantine Sociali",
    "sg:phone":"+39 045 683 2500",
    "sg:postcode":"37020",
    "sg:province":"Verona",
    "wof:name":"Boscaini Paolo & Figli",
    "wof:placetype":"venue"
},
  "geometry": {"coordinates":[10.915437,45.556091],"type":"Point"}
}