{
  "type": "Feature",
  "properties": {
    "iso:country":"IT",
    "sg:address":"37122 Verona",
    "sg:city":"Verona",
    "sg:classifiers":[
        {
            "category":"Education",
            "subcategory":"School",
            "type":"Public Place"
        }
    ],
    "sg:phone":"+39 045 803 4094",
    "sg:postcode":"37122",
    "sg:province":"Verona",
    "sg:tags":[
        "scuole",
        "informatica",
        "di"
    ],
    "wof:name":"Istituto Sorelle Della Misericordia",
    "wof:placetype":"venue"
},
  "geometry": {"coordinates":[10.915236,45.399265],"type":"Point"}
}