{
  "type": "Feature",
  "properties": {
    "iso:country":"IT",
    "sg:address":"12043 Canale",
    "sg:city":"Canale",
    "sg:orig_category":"Macchine, Impianti Ed Attrezzature Per Industria Alimentare E Bevande",
    "sg:phone":"+39 0173 979408",
    "sg:postcode":"12043",
    "sg:province":"Cuneo",
    "wof:name":"Lurgo Dino",
    "wof:placetype":"venue"
},
  "geometry": {"coordinates":[8.015151,44.802776],"type":"Point"}
}