{
  "type": "Feature",
  "properties": {
    "addr:full":"Via Delle Caserane, 20/3 Int 3 59100 Prato Prato Prato 59100",
    "addr:housenumber":"20 / 3 int 3",
    "addr:postcode":"59100;59100",
    "addr:street":"Via Delle Caserane",
    "iso:country":"IT",
    "sg:address":"Via Delle Caserane, 20/3 Int 3 59100 Prato",
    "sg:city":"Prato",
    "sg:classifiers":[
        {
            "category":"Parking",
            "subcategory":"Lot",
            "type":"Transportation"
        }
    ],
    "sg:phone":"+39 0574 811923",
    "sg:postcode":"59100",
    "sg:province":"Prato",
    "sg:tags":[
        "stockinette",
        "yarn"
    ],
    "wof:name":"Filati Isabella Srl",
    "wof:placetype":"venue"
},
  "geometry": {"coordinates":[11.031732,43.876152],"type":"Point"}
}