{
  "type": "Feature",
  "properties": {
    "iso:country":"IT",
    "sg:address":"31045 Motta Di Livenza",
    "sg:city":"Motta di Livenza",
    "sg:orig_category":"Ottica, Lenti A Contatto Ed Occhiali - Vendita Al Dettaglio",
    "sg:phone":"+39 0422 768775",
    "sg:postcode":"31045",
    "sg:province":"Treviso",
    "wof:name":"Ottica Tmc Di Marcuz Edoardo",
    "wof:placetype":"venue"
},
  "geometry": {"coordinates":[12.626995,45.767303],"type":"Point"}
}