{
  "type": "Feature",
  "properties": {
    "iso:country":"IT",
    "sg:address":"Viale Plinio 64; Milano",
    "sg:classifiers":[
        {
            "category":"Banks & Credit Unions",
            "subcategory":"Bank",
            "type":"Services"
        }
    ],
    "sg:phone":"+39 02 2940 4755",
    "wof:name":"Banca Di Roma",
    "wof:placetype":"venue"
},
  "geometry": {"coordinates":[9.220764,45.475224],"type":"Point"}
}