{
  "type": "Feature",
  "properties": {
    "addr:full":"40, Via Del Burano 61100 Pesaro Pesaro Pesaro E Urbino 61100",
    "addr:postcode":"61100;61100",
    "addr:street":"Via Del Burano",
    "iso:country":"IT",
    "sg:address":"40, Via Del Burano 61100 Pesaro",
    "sg:city":"Pesaro",
    "sg:classifiers":[
        {
            "category":"Home & Garden",
            "subcategory":"Home Furnishings",
            "type":"Retail Goods"
        }
    ],
    "sg:phone":"+39 39072128821",
    "sg:postcode":"61100",
    "sg:province":"Pesaro E Urbino",
    "sg:tags":[
        "household"
    ],
    "wof:name":"Belligotti S.p.a.",
    "wof:placetype":"venue"
},
  "geometry": {"coordinates":[12.863528,43.915653],"type":"Point"}
}