{
  "type": "Feature",
  "properties": {
    "iso:country":"IT",
    "sg:address":"1, Via Veneto 60030 Monsano",
    "sg:city":"Monsano",
    "sg:classifiers":[
        {
            "category":"Travel",
            "subcategory":"Travel Agent",
            "type":"Entertainment"
        }
    ],
    "sg:phone":"+39 0731 605565",
    "sg:postcode":"60030",
    "sg:province":"Ancona",
    "sg:tags":[
        "business"
    ],
    "wof:name":"Albergo Ristorante 2000",
    "wof:placetype":"venue"
},
  "geometry": {"coordinates":[13.280821,43.556908],"type":"Point"}
}