{
  "type": "Feature",
  "properties": {
    "addr:full":"25039 Travagliato Travagliato Brescia 25039",
    "addr:postcode":"25039;25039",
    "iso:country":"IT",
    "sg:address":"25039 Travagliato",
    "sg:city":"Travagliato",
    "sg:classifiers":[
        {
            "category":"Building & Trades",
            "subcategory":"Construction",
            "type":"Services"
        }
    ],
    "sg:phone":"+39 030 662261",
    "sg:postcode":"25039",
    "sg:province":"Brescia",
    "sg:tags":[
        "activities",
        "industrial",
        "supply",
        "valve",
        "equipment",
        "measurement"
    ],
    "sg:website":"http://www.acquatec.it",
    "wof:name":"Acquatec Srl",
    "wof:placetype":"venue"
},
  "geometry": {"coordinates":[10.100862,45.535774],"type":"Point"}
}