{
  "type": "Feature",
  "properties": {
    "iso:country":"IT",
    "sg:address":"20051 Limbiate",
    "sg:city":"Limbiate",
    "sg:orig_category":"Viterie E Bullonerie - Macchine",
    "sg:phone":"+39 02 9905 6923",
    "sg:postcode":"20051",
    "sg:province":"Milano",
    "sg:website":"http://www.sacmalimbiate.it",
    "wof:name":"Sacma Limbiate Spa",
    "wof:placetype":"venue"
},
  "geometry": {"coordinates":[9.184489,45.480846],"type":"Point"}
}