{
  "type": "Feature",
  "properties": {
    "addr:full":"6, Via Giorgione 31056 Roncade Roncade Treviso 31056",
    "addr:postcode":"31056;31056",
    "addr:street":"Via Giorgione",
    "iso:country":"IT",
    "sg:address":"6, Via Giorgione 31056 Roncade",
    "sg:city":"Roncade",
    "sg:classifiers":[
        {
            "category":"Professional",
            "subcategory":"Printing & Photocopies",
            "type":"Services"
        }
    ],
    "sg:phone":"+39 390 422 7050",
    "sg:postcode":"31056",
    "sg:province":"Treviso",
    "wof:name":"Nu-maber (s.r.l.)",
    "wof:placetype":"venue"
},
  "geometry": {"coordinates":[12.3886756897,45.6381912231],"type":"Point"}
}