{
  "type": "Feature",
  "properties": {
    "iso:country":"IT",
    "sg:address":"P. Della Vittoria 1; Campobasso; 86100",
    "sg:city":"Campobasso",
    "sg:classifiers":[
        {
            "category":"Shopping",
            "subcategory":"Computers & Home Electronics",
            "type":"Retail Goods"
        }
    ],
    "sg:phone":"+39 0874 4711",
    "sg:postcode":"86100",
    "sg:province":"Campobasso",
    "sg:tags":[
        "chamber",
        "commerce"
    ],
    "wof:name":"Campobasso Cci",
    "wof:placetype":"venue"
},
  "geometry": {"coordinates":[14.657537,41.55608],"type":"Point"}
}