{
  "type": "Feature",
  "properties": {
    "iso:country":"IT",
    "sg:address":"33100 Udine",
    "sg:city":"Udine",
    "sg:orig_category":"Cartotecnica E Servizi. Forniture Per Attivita' Commerciali Ed Artigianali",
    "sg:phone":"+39 0432 520623",
    "sg:postcode":"33100",
    "sg:province":"Udine",
    "wof:name":"Cartolnova Di Segale Dante E Figlio Snc",
    "wof:placetype":"venue"
},
  "geometry": {"coordinates":[13.236205,46.053535],"type":"Point"}
}