{
  "type": "Feature",
  "properties": {
    "iso:country":"IT",
    "sg:address":"20142 Milano",
    "sg:city":"Milano",
    "sg:orig_category":"Elettrotecnica Industriale, Prodotti E Apparecchiature",
    "sg:phone":"+39 02 895901",
    "sg:postcode":"20142",
    "sg:province":"Milano",
    "sg:website":"http://www.fitre.it",
    "wof:name":"Fitre Spa",
    "wof:placetype":"venue"
},
  "geometry": {"coordinates":[9.169755,45.442955],"type":"Point"}
}