{
  "type": "Feature",
  "properties": {
    "iso:country":"IT",
    "sg:address":"Via G. Regnoli Ang; Forli; 47100",
    "sg:classifiers":[
        {
            "category":"Banks & Credit Unions",
            "subcategory":"Bank",
            "type":"Services"
        }
    ],
    "sg:phone":"+39 0543 29230",
    "sg:postcode":"47100",
    "sg:province":"Forl\u00ec-Cesena",
    "wof:name":"Istituto Bancario, San Paolo Di Torino Spa",
    "wof:placetype":"venue"
},
  "geometry": {"coordinates":[12.048979,44.231167],"type":"Point"}
}