{
  "type": "Feature",
  "properties": {
    "iso:country":"IT",
    "sg:address":"Piazza Corte Dei Santi, San Vittore Del Lazio, Fr",
    "sg:classifiers":[
        {
            "category":"Banks & Credit Unions",
            "subcategory":"Bank",
            "type":"Services"
        }
    ],
    "wof:name":"Cassa Rurale Ed Artigiana Di S Vittore Del Lazio (frosinone)",
    "wof:placetype":"venue"
},
  "geometry": {"coordinates":[13.933778,41.462502],"type":"Point"}
}