{
  "type": "Feature",
  "properties": {
    "iso:country":"IT",
    "sg:address":"60027 San Biagio",
    "sg:city":"San Biagio",
    "sg:orig_category":"Prodotti E Manufatti In Gomma",
    "sg:phone":"+39 071 710 8970",
    "sg:postcode":"60027",
    "sg:province":"Ancona",
    "wof:name":"Gommauto Di Paolucci & C. S.n.c",
    "wof:placetype":"venue"
},
  "geometry": {"coordinates":[13.4975004196,43.5173721313],"type":"Point"}
}