{
  "type": "Feature",
  "properties": {
    "iso:country":"IT",
    "sg:address":"20129 Milano",
    "sg:city":"Milano",
    "sg:classifiers":[
        {
            "category":"Health Services",
            "subcategory":"Health Practitioner",
            "type":"Services"
        }
    ],
    "sg:phone":"+39 02 2952 5273",
    "sg:postcode":"20129",
    "sg:province":"Milano",
    "sg:tags":[
        "medici"
    ],
    "wof:name":"Zalewska Bozena Jolanta",
    "wof:placetype":"venue"
},
  "geometry": {"coordinates":[9.2830343246,45.5232124329],"type":"Point"}
}