{
  "type": "Feature",
  "properties": {
    "iso:country":"IT",
    "sg:address":"Via Mercato Vecchio 17/19; Udine; 33100",
    "sg:city":"Udine",
    "sg:classifiers":[
        {
            "category":"Banks & Credit Unions",
            "subcategory":"Bank",
            "type":"Services"
        }
    ],
    "sg:phone":"+39 0432 4961",
    "sg:postcode":"33100",
    "sg:province":"Udine",
    "wof:name":"Banca Nazionale Del Lavoro",
    "wof:placetype":"venue"
},
  "geometry": {"coordinates":[13.329021,45.975758],"type":"Point"}
}