{
  "type": "Feature",
  "properties": {
    "addr:full":"35035 Arlesega Arlesega Padova 35035",
    "addr:postcode":"35035;35035",
    "addr:street":"Arlesega",
    "iso:country":"IT",
    "sg:address":"35035 Arlesega",
    "sg:city":"Arlesega",
    "sg:orig_category":"Frigotecnica, Apparecchiature E Servizi",
    "sg:phone":"+39 049 900 1425",
    "sg:postcode":"35035",
    "sg:province":"Padova",
    "wof:name":"Gottardo Inox Frigo",
    "wof:placetype":"venue"
},
  "geometry": {"coordinates":[11.8686132431,45.3833389282],"type":"Point"}
}