{
  "type": "Feature",
  "properties": {
    "iso:country":"IT",
    "sg:address":"Via Agrate 31 20049 Concorezzo",
    "sg:city":"Concorezzo",
    "sg:classifiers":[
        {
            "category":"Utilities",
            "subcategory":"Mobile Phone",
            "type":"Services"
        }
    ],
    "sg:phone":"+39 039 604 0135",
    "sg:postcode":"20049",
    "sg:province":"Milano",
    "sg:tags":[
        "article",
        "promotional"
    ],
    "wof:name":"The Winner Snc Di Pary Gisele E C.",
    "wof:placetype":"venue"
},
  "geometry": {"coordinates":[9.340341568,45.5870513916],"type":"Point"}
}