{
  "type": "Feature",
  "properties": {
    "addr:full":"Via Carradoro 14 31030 Altivole Altivole Treviso 31030",
    "addr:housenumber":"14",
    "addr:postcode":"31030;31030",
    "addr:street":"Via Carradoro",
    "iso:country":"IT",
    "sg:address":"Via Carradoro 14 31030 Altivole",
    "sg:city":"Altivole",
    "sg:classifiers":[
        {
            "category":"Military Area",
            "subcategory":"Naval Base",
            "type":"Public Place"
        }
    ],
    "sg:phone":"+39 0423 569815",
    "sg:postcode":"31030",
    "sg:province":"Treviso",
    "sg:tags":[
        "boot",
        "motorcyclist's"
    ],
    "sg:website":"www.z-a-c.com",
    "wof:name":"Calzaturificio Zac S.r.l.",
    "wof:placetype":"venue"
},
  "geometry": {"coordinates":[12.2420721054,45.6662864685],"type":"Point"}
}