{
  "type": "Feature",
  "properties": {
    "addr:full":"24/b, Via Per Maggiana 23826 Mandello Del Lario Mandello del Lario Lecco 23826",
    "addr:housenumber":"24 / b",
    "addr:postcode":"23826;23826",
    "addr:street":"Via Per Maggiana",
    "iso:country":"IT",
    "sg:address":"24/b, Via Per Maggiana 23826 Mandello Del Lario",
    "sg:city":"Mandello del Lario",
    "sg:classifiers":[
        {
            "category":"Manufacturing",
            "subcategory":"Rubber & Plastics",
            "type":"Manufacturing & Wholesale Goods"
        }
    ],
    "sg:phone":"+39 0341 731344",
    "sg:postcode":"23826",
    "sg:province":"Lecco",
    "wof:name":"Stucchi Luigi (s.r.l.)",
    "wof:placetype":"venue"
},
  "geometry": {"coordinates":[9.3900709152,45.8529815674],"type":"Point"}
}