{
  "type": "Feature",
  "properties": {
    "iso:country":"IT",
    "sg:address":"67051 Avezzano",
    "sg:orig_category":"Materiali E Componenti Elettronici",
    "sg:phone":"+39 0863 413014",
    "sg:postcode":"67051",
    "sg:province":"L'Aquila",
    "wof:name":"Az Impianti Srl",
    "wof:placetype":"venue"
},
  "geometry": {"coordinates":[13.419894,42.036747],"type":"Point"}
}