{
  "type": "Feature",
  "properties": {
    "iso:country":"IT",
    "sg:address":"50019 Sesto Fiorentino",
    "sg:city":"Sesto Fiorentino",
    "sg:orig_category":"Arredo Bagno Ed Idrosanitari. Complementi Di Arredamento. Vetro: Prodotti E Lavorazioni",
    "sg:phone":"+39 055 451691",
    "sg:postcode":"50019",
    "sg:province":"Firenze",
    "wof:name":"Furlanetto Teresa",
    "wof:placetype":"venue"
},
  "geometry": {"coordinates":[11.272458,43.786728],"type":"Point"}
}