{
  "type": "Feature",
  "properties": {
    "addr:full":"55010 Lunata Capannori Capannori Lucca 55010",
    "addr:postcode":"55010;55010",
    "iso:country":"IT",
    "sg:address":"55010 Lunata Capannori",
    "sg:city":"Capannori",
    "sg:orig_category":"Pratiche Automobilistiche",
    "sg:phone":"+39 0583 933093",
    "sg:postcode":"55010",
    "sg:province":"Lucca",
    "wof:name":"Studio Chieffallo Snc",
    "wof:placetype":"venue"
},
  "geometry": {"coordinates":[10.5636758804,43.8553924561],"type":"Point"}
}