{
  "type": "Feature",
  "properties": {
    "iso:country":"IT",
    "sg:address":"26, Via Piemonte 63100 Ascoli Piceno",
    "sg:city":"Ascoli Piceno",
    "sg:classifiers":[
        {
            "category":"Wholesale",
            "subcategory":"Drugs",
            "type":"Manufacturing & Wholesale Goods"
        }
    ],
    "sg:phone":"+39 0736 342620",
    "sg:postcode":"63100",
    "sg:province":"Ascoli Piceno",
    "sg:tags":[
        "chemical",
        "pharmaceutical"
    ],
    "wof:name":"Baiengas Sas",
    "wof:placetype":"venue"
},
  "geometry": {"coordinates":[13.588969,42.85611],"type":"Point"}
}