{
  "type": "Feature",
  "properties": {
    "iso:country":"IT",
    "sg:address":"21/23, Via Don Luigi Sturzo 25028 Verolanuova",
    "sg:city":"Verolanuova",
    "sg:classifiers":[
        {
            "category":"Food & Beverages",
            "subcategory":"Groceries & Convenience Stores",
            "type":"Retail Goods"
        }
    ],
    "sg:phone":"+39 030 936 4411",
    "sg:postcode":"25028",
    "sg:province":"Brescia",
    "sg:tags":[
        "product",
        "related"
    ],
    "wof:name":"Iapc Italia Srl",
    "wof:placetype":"venue"
},
  "geometry": {"coordinates":[10.0841398239,45.3341712952],"type":"Point"}
}