{
  "type": "Feature",
  "properties": {
    "addr:full":"6/a, V. Zabatta 80040 Terzigno Terzigno Napoli 80040",
    "addr:housenumber":"6 / a",
    "addr:postcode":"80040;80040",
    "addr:street":"V. Zabatta",
    "iso:country":"IT",
    "sg:address":"6/a, V. Zabatta 80040 Terzigno",
    "sg:city":"Terzigno",
    "sg:classifiers":[
        {
            "category":"Shopping",
            "subcategory":"Clothing, Apparel, & Fashions",
            "type":"Retail Goods"
        }
    ],
    "sg:phone":"+39 081 529 4445",
    "sg:postcode":"80040",
    "sg:province":"Napoli",
    "sg:tags":[
        "clothes"
    ],
    "sg:website":"http://www.paginegialle.it/exex",
    "wof:name":"Exex Di Malinconico Antonio",
    "wof:placetype":"venue"
},
  "geometry": {"coordinates":[14.251636,40.840096],"type":"Point"}
}