{
  "type": "Feature",
  "properties": {
    "iso:country":"IT",
    "sg:address":"46, Via Visan 36034 Malo",
    "sg:city":"Malo",
    "sg:classifiers":[
        {
            "category":"Manufacturing",
            "subcategory":"Textiles",
            "type":"Manufacturing & Wholesale Goods"
        }
    ],
    "sg:phone":"+39 0445 588021",
    "sg:postcode":"36034",
    "sg:province":"Vicenza",
    "sg:tags":[
        "leather",
        "raw",
        "material",
        "-"
    ],
    "wof:name":"Comec S.r.l.",
    "wof:placetype":"venue"
},
  "geometry": {"coordinates":[11.436214,45.642529],"type":"Point"}
}