{
  "type": "Feature",
  "properties": {
    "addr:full":"Via Roma 54/c; Castelnuovo Di Sotto; 42035 Reggio Nell'Emilia 42035",
    "addr:housenumber":"54 / c",
    "addr:postcode":"42035;42035",
    "addr:street":"Via Roma;Castelnuovo Di Sotto",
    "iso:country":"IT",
    "sg:address":"Via Roma 54/c; Castelnuovo Di Sotto; 42035",
    "sg:classifiers":[
        {
            "category":"Banks & Credit Unions",
            "subcategory":"Bank",
            "type":"Services"
        }
    ],
    "sg:phone":"+39 0522 811005",
    "sg:postcode":"42035",
    "sg:province":"Reggio Nell'Emilia",
    "wof:name":"Banca Popolare Di Verona",
    "wof:placetype":"venue"
},
  "geometry": {"coordinates":[10.417181,44.430557],"type":"Point"}
}