{
  "type": "Feature",
  "properties": {
    "iso:country":"IT",
    "sg:address":"00166 Roma",
    "sg:city":"Roma",
    "sg:orig_category":"Servizi Culturali E Per Lo Spettacolo. Servizi Per Lo Sport E Il Tempo Libero. Servizi Per Aziende, Manifestazioni E Supporto Agli Scambi Commerciali",
    "sg:phone":"+39 06 6156 8218",
    "sg:postcode":"00166",
    "sg:province":"Roma",
    "sg:website":"http://www.newsoundservice.com",
    "wof:name":"New Sound Service Di Marco Lovato",
    "wof:placetype":"venue"
},
  "geometry": {"coordinates":[12.367548,41.916008],"type":"Point"}
}