{
  "type": "Feature",
  "properties": {
    "iso:country":"IT",
    "sg:address":"06128 Perugia",
    "sg:city":"Perugia",
    "sg:orig_category":"Videogiochi, Flippers E Biliardini - Vendita Al Dettaglio E Noleggio",
    "sg:phone":"+39 075 500 5622",
    "sg:postcode":"06128",
    "sg:province":"Perugia",
    "wof:name":"Automatic Umbra Srl",
    "wof:placetype":"venue"
},
  "geometry": {"coordinates":[12.3702,43.095203],"type":"Point"}
}