{
  "type": "Feature",
  "properties": {
    "iso:country":"IT",
    "sg:address":"22, Via Rossa Guido 35020 Ponte San Nicolo'",
    "sg:classifiers":[
        {
            "category":"Home & Garden",
            "subcategory":"Home Furnishings",
            "type":"Retail Goods"
        }
    ],
    "sg:phone":"+39 39049717624",
    "sg:postcode":"35020",
    "sg:province":"Padova",
    "sg:tags":[
        "household"
    ],
    "wof:name":"Crivellari Divani & Poltrone S.r.l.",
    "wof:placetype":"venue"
},
  "geometry": {"coordinates":[11.913318,45.375839],"type":"Point"}
}