{
  "type": "Feature",
  "properties": {
    "addr:full":"7, Via Di Vittorio Giuseppe 20063 Cernusco Sul Naviglio Cernusco sul Naviglio Milano 20063",
    "addr:postcode":"20063;20063",
    "addr:street":"Via Di Vittorio Giuseppe",
    "iso:country":"IT",
    "sg:address":"7, Via Di Vittorio Giuseppe 20063 Cernusco Sul Naviglio",
    "sg:city":"Cernusco sul Naviglio",
    "sg:classifiers":[
        {
            "category":"Professional",
            "subcategory":"Printing & Photocopies",
            "type":"Services"
        }
    ],
    "sg:phone":"+39 02 9210 6321",
    "sg:postcode":"20063",
    "sg:province":"Milano",
    "wof:name":"Amplyvox (s.p.a.)",
    "wof:placetype":"venue"
},
  "geometry": {"coordinates":[9.3009138107,45.499546051],"type":"Point"}
}