{
  "type": "Feature",
  "properties": {
    "addr:full":"41100 Modena Modena Modena 41100",
    "addr:postcode":"41100;41100",
    "iso:country":"IT",
    "sg:address":"41100 Modena",
    "sg:city":"Modena",
    "sg:orig_category":"Zootecnia E Pesca, Allevamento Piccoli Animali. Animali Domestici",
    "sg:phone":"+39 059 260286",
    "sg:postcode":"41100",
    "sg:province":"Modena",
    "wof:name":"L'arca Centro Cuccioli",
    "wof:placetype":"venue"
},
  "geometry": {"coordinates":[11.008611,44.690483],"type":"Point"}
}