{
  "type": "Feature",
  "properties": {
    "iso:country":"IT",
    "sg:address":"34012 Trieste",
    "sg:city":"Basovizza",
    "sg:orig_category":"Macchine, Impianti Ed Attrezzature Industria Chimica. Prodotti Vari In Metallo. Articoli Per Imballaggio E Confezionamento",
    "sg:phone":"+39 040 226819",
    "sg:postcode":"34012",
    "sg:province":"Trieste",
    "wof:name":"Baitz Lucio",
    "wof:placetype":"venue"
},
  "geometry": {"coordinates":[13.850697,45.657104],"type":"Point"}
}