{
  "type": "Feature",
  "properties": {
    "addr:full":"18, Via Galliera 40050 Argelato Argelato Bologna 40050",
    "addr:postcode":"40050;40050",
    "addr:street":"Via Galliera",
    "iso:country":"IT",
    "sg:address":"18, Via Galliera 40050 Argelato",
    "sg:city":"Argelato",
    "sg:classifiers":[
        {
            "category":"Professional",
            "subcategory":"Business Services",
            "type":"Services"
        }
    ],
    "sg:phone":"+39 39051861258",
    "sg:postcode":"40050",
    "sg:province":"Bologna",
    "sg:tags":[
        "advice"
    ],
    "wof:name":"Boni",
    "wof:placetype":"venue"
},
  "geometry": {"coordinates":[11.357627,44.561752],"type":"Point"}
}