{
  "type": "Feature",
  "properties": {
    "addr:full":"35042 Este Este Padova 35042",
    "addr:postcode":"35042;35042",
    "addr:street":"Este Este",
    "iso:country":"IT",
    "sg:address":"35042 Este",
    "sg:city":"Este",
    "sg:orig_category":"Motori Ed Organi Di Trasmissione",
    "sg:phone":"+39 0429 55029",
    "sg:postcode":"35042",
    "sg:province":"Padova",
    "wof:name":"Cabor",
    "wof:placetype":"venue"
},
  "geometry": {"coordinates":[11.8525381088,45.3832168579],"type":"Point"}
}