{
  "type": "Feature",
  "properties": {
    "iso:country":"IT",
    "sg:address":"50139 Firenze",
    "sg:city":"Firenze",
    "sg:orig_category":"Agenzie D'affari E Servizi Commerciali",
    "sg:phone":"+39 055 482400",
    "sg:postcode":"50139",
    "sg:province":"Firenze",
    "wof:name":"Inter Mark S.r.l.",
    "wof:placetype":"venue"
},
  "geometry": {"coordinates":[11.24846,43.797493],"type":"Point"}
}