{
  "type": "Feature",
  "properties": {
    "iso:country":"IT",
    "sg:address":"1, V. Coppalati - Loc. Le Mose 29100 Piacenza",
    "sg:city":"Piacenza",
    "sg:classifiers":[
        {
            "category":"Parking",
            "subcategory":"Lot",
            "type":"Transportation"
        }
    ],
    "sg:phone":"+39 0523 571123",
    "sg:postcode":"29100",
    "sg:province":"Piacenza",
    "sg:tags":[
        "transport",
        "road"
    ],
    "sg:website":"http://www.paginegialle.it/containersfidenza",
    "wof:name":"Containers Fidenza Srl",
    "wof:placetype":"venue"
},
  "geometry": {"coordinates":[9.754587,45.040398],"type":"Point"}
}