{
  "type": "Feature",
  "properties": {
    "iso:country":"IT",
    "sg:address":"20139 Milano",
    "sg:city":"Milano",
    "sg:orig_category":"Elettrodomestici - Riparazione E Vendita Al Dettaglio Di Accessori",
    "sg:phone":"+39 02 534769",
    "sg:postcode":"20139",
    "sg:province":"Milano",
    "wof:name":"La Tecnica Di Bigheri Daniele",
    "wof:placetype":"venue"
},
  "geometry": {"coordinates":[9.255376,45.528603],"type":"Point"}
}