{
  "type": "Feature",
  "properties": {
    "iso:country":"IT",
    "sg:address":"Corso Porta Nuova, 135; Verona; 37100",
    "sg:classifiers":[
        {
            "category":"Banks & Credit Unions",
            "subcategory":"Bank",
            "type":"Services"
        }
    ],
    "sg:phone":"+39 045 594644",
    "wof:name":"Banca D'america E D'italia",
    "wof:placetype":"venue"
},
  "geometry": {"coordinates":[10.988449,45.431751],"type":"Point"}
}