{
  "type": "Feature",
  "properties": {
    "addr:full":"6, Via Iv Novembre 21040 Oggiona Con Santo Stefano Oggiona Varese 21040",
    "addr:postcode":"21040;21040",
    "addr:street":"Via Iv Novembre",
    "iso:country":"IT",
    "sg:address":"6, Via Iv Novembre 21040 Oggiona Con Santo Stefano",
    "sg:city":"Oggiona",
    "sg:classifiers":[
        {
            "category":"Manufacturing",
            "subcategory":"Food",
            "type":"Manufacturing & Wholesale Goods"
        }
    ],
    "sg:phone":"+39 0331 214311",
    "sg:postcode":"21040",
    "sg:province":"Varese",
    "sg:tags":[
        "equipment",
        "processing",
        "-",
        "machinery"
    ],
    "wof:name":"Omas S.p.a.",
    "wof:placetype":"venue"
},
  "geometry": {"coordinates":[8.8513784409,45.790763855],"type":"Point"}
}