{
  "type": "Feature",
  "properties": {
    "addr:full":"00176 Roma Roma Roma 00176",
    "addr:postcode":"00176;00176",
    "iso:country":"IT",
    "sg:address":"00176 Roma",
    "sg:city":"Roma",
    "sg:orig_category":"Cinematografia E Radiotelevisione. Cine-foto-ottica",
    "sg:phone":"+39 06 273592",
    "sg:postcode":"00176",
    "sg:province":"Roma",
    "wof:name":"Attini Antonio",
    "wof:placetype":"venue"
},
  "geometry": {"coordinates":[12.448578,41.84808],"type":"Point"}
}