{
  "type": "Feature",
  "properties": {
    "iso:country":"IT",
    "sg:address":"56017 San Giuliano Terme",
    "sg:city":"San Giuliano Terme",
    "sg:orig_category":"Pubblicita', Marketing E Comunicazione",
    "sg:phone":"+39 050 861397",
    "sg:postcode":"56017",
    "sg:province":"Pisa",
    "sg:website":"http://ideacharme.com",
    "wof:name":"Ideacharme Di M. Antonietta Mitrugno",
    "wof:placetype":"venue"
},
  "geometry": {"coordinates":[10.4117650986,43.7653503418],"type":"Point"}
}