{
  "type": "Feature",
  "properties": {
    "iso:country":"IT",
    "sg:address":"30, Via Torre 28040 Borgo Ticino",
    "sg:city":"Borgo Ticino",
    "sg:classifiers":[
        {
            "category":"Shopping",
            "subcategory":"Crafts & Fabrics",
            "type":"Retail Goods"
        }
    ],
    "sg:phone":"+39 39032190500",
    "sg:postcode":"28040",
    "sg:province":"Novara",
    "wof:name":"Tessile Piemontese S.r.l.",
    "wof:placetype":"venue"
},
  "geometry": {"coordinates":[8.6010894775,45.6949882507],"type":"Point"}
}