{
  "type": "Feature",
  "properties": {
    "iso:country":"IT",
    "sg:address":"3, Via Polo Marco 35011 Campodarsego",
    "sg:city":"Campodarsego",
    "sg:classifiers":[
        {
            "category":"Shopping",
            "type":"Retail Goods"
        }
    ],
    "sg:phone":"+39 049 920 0811",
    "sg:postcode":"35011",
    "sg:province":"Padova",
    "sg:tags":[
        "finished",
        "-",
        "metallic"
    ],
    "wof:name":"La Modelleria (s.n.c.)",
    "wof:placetype":"venue"
},
  "geometry": {"coordinates":[11.8965234756,45.4609375],"type":"Point"}
}