{
  "type": "Feature",
  "properties": {
    "addr:full":"78, Via Dell' Arcoveggio 40129 Bologna Bologna Bologna 40129",
    "addr:postcode":"40129;40129",
    "addr:street":"Via Dell '",
    "iso:country":"IT",
    "sg:address":"78, Via Dell' Arcoveggio 40129 Bologna",
    "sg:city":"Bologna",
    "sg:classifiers":[
        {
            "category":"Shopping",
            "subcategory":"Computers & Home Electronics",
            "type":"Retail Goods"
        }
    ],
    "sg:phone":"+39 051 638 9110",
    "sg:postcode":"40129",
    "sg:province":"Bologna",
    "sg:tags":[
        "electronic",
        "electrical",
        "equipment"
    ],
    "wof:name":"Zaniboni Adriano (s.r.l.)",
    "wof:placetype":"venue"
},
  "geometry": {"coordinates":[11.349145,44.536987],"type":"Point"}
}