{
  "type": "Feature",
  "properties": {
    "iso:country":"IT",
    "sg:address":"Via Brunetti 14 50033 Firenzuola",
    "sg:city":"Firenzuola",
    "sg:classifiers":[
        {
            "category":"Banks & Credit Unions",
            "subcategory":"Investment Brokerage",
            "type":"Services"
        }
    ],
    "sg:phone":"+39 055 819180",
    "sg:postcode":"50033",
    "sg:province":"Firenze",
    "sg:tags":[
        "women's",
        "clothing",
        "accessory"
    ],
    "sg:website":"www.galeottipiume.com",
    "wof:name":"Galeottipiume Srl",
    "wof:placetype":"venue"
},
  "geometry": {"coordinates":[11.256902,43.768734],"type":"Point"}
}