{
  "type": "Feature",
  "properties": {
    "addr:full":"21057 Olgiate Olona Olgiate Olona Varese 21057",
    "addr:postcode":"21057;21057",
    "iso:country":"IT",
    "sg:address":"21057 Olgiate Olona",
    "sg:city":"Olgiate Olona",
    "sg:orig_category":"Valvole Saracinesche",
    "sg:phone":"+39 0331 375450",
    "sg:postcode":"21057",
    "sg:province":"Varese",
    "wof:name":"La Quotata Saracinesca Snc",
    "wof:placetype":"venue"
},
  "geometry": {"coordinates":[8.881413,45.629898],"type":"Point"}
}