{
  "type": "Feature",
  "properties": {
    "iso:country":"IT",
    "sg:address":"25027 Quinzano D'oglio",
    "sg:orig_category":"Valvole E Apparecchiature Di Misura. Attrezzature E Forniture Per Officine Riparazione E Servizi Ausiliari. Macchine, Strumenti Ed Apparecchi Per Attivita' Industriali",
    "sg:phone":"+39 030 933087",
    "sg:postcode":"25027",
    "sg:province":"Brescia",
    "wof:name":"Odolini Automotive Consulting S.r.l.",
    "wof:placetype":"venue"
},
  "geometry": {"coordinates":[10.009055,45.320534],"type":"Point"}
}