{
  "type": "Feature",
  "properties": {
    "iso:country":"IT",
    "sg:address":"4, Via Terra Matta 37010 Rivoli Veronese",
    "sg:city":"Rivoli Veronese",
    "sg:classifiers":[
        {
            "category":"Farming",
            "subcategory":"Livestock Farm",
            "type":"Manufacturing & Wholesale Goods"
        }
    ],
    "sg:phone":"+39 045 728 0330",
    "sg:postcode":"37010",
    "sg:province":"Verona",
    "sg:tags":[
        "agriculture"
    ],
    "wof:name":"Riv.zoo Soc. Coop. A R.l.",
    "wof:placetype":"venue"
},
  "geometry": {"coordinates":[10.991748,45.438366],"type":"Point"}
}