{
  "type": "Feature",
  "properties": {
    "iso:country":"IT",
    "sg:address":"37062 Dossobuono",
    "sg:city":"Dossobuono",
    "sg:orig_category":"Studi E Consulenze Tecniche E Industriali. Consulenze Tecniche, Amministrative E Perizie. Servizi Ausiliari Di Analisi, Controllo E Ricerca",
    "sg:phone":"+39 045 987075",
    "sg:postcode":"37062",
    "sg:province":"Verona",
    "sg:website":"http://www.arcosas.net",
    "wof:name":"Arco Sas Di Lonardi C. E C.",
    "wof:placetype":"venue"
},
  "geometry": {"coordinates":[10.914136,45.395824],"type":"Point"}
}