{
  "type": "Feature",
  "properties": {
    "addr:full":"5/a, V. Col Di Lana 22100 Como Como Como 22100",
    "addr:housenumber":"5 / a",
    "addr:postcode":"22100;22100",
    "addr:street":"V. Col Di Lana",
    "iso:country":"IT",
    "sg:address":"5/a, V. Col Di Lana 22100 Como",
    "sg:city":"Como",
    "sg:classifiers":[
        {
            "category":"Shopping",
            "subcategory":"Clothing, Apparel, & Fashions",
            "type":"Retail Goods"
        }
    ],
    "sg:phone":"+39 39031265425",
    "sg:postcode":"22100",
    "sg:province":"Como",
    "sg:tags":[
        "clothing",
        "accessory"
    ],
    "sg:website":"http://www.paginegialle.it/tties",
    "wof:name":"T-ties Di Tortora",
    "wof:placetype":"venue"
},
  "geometry": {"coordinates":[9.094743,45.796856],"type":"Point"}
}