{
  "type": "Feature",
  "properties": {
    "iso:country":"IT",
    "sg:address":"1, Via Lugo 40128 Bologna",
    "sg:city":"Bologna",
    "sg:classifiers":[
        {
            "category":"Professional",
            "subcategory":"Computer Services",
            "type":"Services"
        }
    ],
    "sg:phone":"+39 39051320409",
    "sg:postcode":"40128",
    "sg:province":"Bologna",
    "sg:tags":[
        "information",
        "technology"
    ],
    "wof:name":"Italsel S.r.l.",
    "wof:placetype":"venue"
},
  "geometry": {"coordinates":[11.3549,44.530052],"type":"Point"}
}