{
  "type": "Feature",
  "properties": {
    "iso:country":"IT",
    "sg:address":"24, Via Gheghi 55012 Capannori",
    "sg:city":"Capannori",
    "sg:classifiers":[
        {
            "category":"Shopping",
            "subcategory":"Computers & Home Electronics",
            "type":"Retail Goods"
        }
    ],
    "sg:phone":"+39 0583 927369",
    "sg:postcode":"55012",
    "sg:province":"Lucca",
    "sg:tags":[
        "electronic",
        "electrical",
        "equipment"
    ],
    "wof:name":"Co.ge.pi. Srl",
    "wof:placetype":"venue"
},
  "geometry": {"coordinates":[10.585422,43.873756],"type":"Point"}
}