{
  "type": "Feature",
  "properties": {
    "iso:country":"IT",
    "sg:address":"40069 Zola Predosa",
    "sg:city":"Zola",
    "sg:orig_category":"Macchine Utensili - Produzione",
    "sg:phone":"+39 051 2980 5211",
    "sg:postcode":"40069",
    "sg:province":"Bologna",
    "wof:name":"Meccanica Nova Spa",
    "wof:placetype":"venue"
},
  "geometry": {"coordinates":[11.246904,44.496292],"type":"Point"}
}