{
  "type": "Feature",
  "properties": {
    "addr:full":"09127 Cagliari Cagliari Cagliari 09127",
    "addr:postcode":"09127;09127",
    "iso:country":"IT",
    "sg:address":"09127 Cagliari",
    "sg:city":"Cagliari",
    "sg:orig_category":"Arredamenti Ed Architettura D'interni",
    "sg:phone":"+39 070 684 8152",
    "sg:postcode":"09127",
    "sg:province":"Cagliari",
    "wof:name":"Plantera Sebastiano",
    "wof:placetype":"venue"
},
  "geometry": {"coordinates":[9.121759,39.216465],"type":"Point"}
}