{
  "type": "Feature",
  "properties": {
    "iso:country":"IT",
    "sg:address":"6, Via Damiano Chiesa 24026 Leffe",
    "sg:city":"Leffe",
    "sg:classifiers":[
        {
            "category":"Shopping",
            "subcategory":"Clothing, Apparel, & Fashions",
            "type":"Retail Goods"
        }
    ],
    "sg:phone":"+39 39035733453",
    "sg:postcode":"24026",
    "sg:province":"Bergamo",
    "sg:tags":[
        "clothing",
        "accessory"
    ],
    "wof:name":"Warmor (s.r.l.)",
    "wof:placetype":"venue"
},
  "geometry": {"coordinates":[9.89154,45.800014],"type":"Point"}
}