{
  "type": "Feature",
  "properties": {
    "iso:country":"IT",
    "sg:address":"41042 Fiorano Modenese",
    "sg:city":"Fiorano Modenese",
    "sg:orig_category":"Antinfortunistica - Attrezzature Ed Articoli",
    "sg:phone":"+39 0536 910270",
    "sg:postcode":"41042",
    "sg:province":"Modena",
    "wof:name":"Mecom Sas",
    "wof:placetype":"venue"
},
  "geometry": {"coordinates":[10.828786,44.536949],"type":"Point"}
}