{
  "type": "Feature",
  "properties": {
    "addr:full":"10155 Torino Torino Torino 10155",
    "addr:postcode":"10155;10155",
    "iso:country":"IT",
    "sg:address":"10155 Torino",
    "sg:city":"Torino",
    "sg:orig_category":"Impiantistica E Prodotti Tecnologici Per Edilizia. Elettrotecnica Industriale, Prodotti E Apparecchiature. Elettrotecnica Professionale E Di Consumo",
    "sg:phone":"+39 011 221 5416",
    "sg:postcode":"10155",
    "sg:province":"Torino",
    "wof:name":"A.t.a. Di Ternavasio Antonio & C. Snc",
    "wof:placetype":"venue"
},
  "geometry": {"coordinates":[7.693822,45.095821],"type":"Point"}
}