{
  "type": "Feature",
  "properties": {
    "iso:country":"IT",
    "sg:address":"30030 Venezia",
    "sg:orig_category":"Servizi E Lavori Per Agricoltura E Zootecnia. Servizi E Lavori Per Ecologia E Smaltimento Rifiuti",
    "sg:phone":"+39 041 541 6353",
    "sg:postcode":"30030",
    "sg:province":"Venezia",
    "wof:name":"Consorzio Di Bonifica Dese Sile",
    "wof:placetype":"venue"
},
  "geometry": {"coordinates":[12.690209,45.714836],"type":"Point"}
}