{
  "type": "Feature",
  "properties": {
    "addr:full":"7, Via Cinelli Oreste 50058 Signa Signa Firenze 50058",
    "addr:postcode":"50058;50058",
    "addr:street":"Via Cinelli Oreste",
    "iso:country":"IT",
    "sg:address":"7, Via Cinelli Oreste 50058 Signa",
    "sg:city":"Signa",
    "sg:classifiers":[
        {
            "category":"Shopping",
            "subcategory":"Crafts & Fabrics",
            "type":"Retail Goods"
        }
    ],
    "sg:phone":"+39 39055875607",
    "sg:postcode":"50058",
    "sg:province":"Firenze",
    "sg:tags":[
        "linen"
    ],
    "wof:name":"F.b.",
    "wof:placetype":"venue"
},
  "geometry": {"coordinates":[11.256901741,43.7687339783],"type":"Point"}
}