{
  "type": "Feature",
  "properties": {
    "addr:full":"88, V. Caracciolo Milano Milano 20155",
    "addr:housenumber":"88",
    "addr:postcode":"20155",
    "addr:street":"V. Caracciolo",
    "iso:country":"IT",
    "sg:address":"88, V. Caracciolo",
    "sg:city":"Milano",
    "sg:classifiers":[
        {
            "category":"Shopping",
            "subcategory":"Clothing, Apparel, & Fashions",
            "type":"Retail Goods"
        }
    ],
    "sg:phone":"+39 39023450365",
    "sg:postcode":"20155",
    "sg:province":"Milano",
    "sg:tags":[
        "clothes"
    ],
    "sg:website":"http://www.paginegialle.it/sartoriagemmati",
    "wof:name":"Sartoria Gemmati",
    "wof:placetype":"venue"
},
  "geometry": {"coordinates":[9.160377,45.49123],"type":"Point"}
}