{
  "type": "Feature",
  "properties": {
    "iso:country":"IT",
    "sg:address":"50056 Montelupo Fiorentino",
    "sg:city":"Montelupo Fiorentino",
    "sg:classifiers":[
        {
            "category":"Farming",
            "subcategory":"Berry Farm",
            "type":"Manufacturing & Wholesale Goods"
        }
    ],
    "sg:phone":"+39 0571 51411",
    "sg:postcode":"50056",
    "sg:province":"Firenze",
    "sg:tags":[
        "vegetable",
        "growing",
        "flower",
        "agriculture"
    ],
    "sg:website":"http://www.san-vito.com",
    "wof:name":"Drighi Roberto Tenuta San Vito In Fior Di Selva",
    "wof:placetype":"venue"
},
  "geometry": {"coordinates":[11.043718,43.744545],"type":"Point"}
}