{
  "type": "Feature",
  "properties": {
    "addr:full":"2/c, Strada Alla Diga 15033 Casale Monferrato Casale Monferrato Alessandria 15033",
    "addr:housenumber":"2 / c",
    "addr:postcode":"15033;15033",
    "addr:street":"Strada Alla Diga",
    "iso:country":"IT",
    "sg:address":"2/c, Strada Alla Diga 15033 Casale Monferrato",
    "sg:city":"Casale Monferrato",
    "sg:classifiers":[
        {
            "category":"Shopping",
            "subcategory":"Computers & Home Electronics",
            "type":"Retail Goods"
        }
    ],
    "sg:phone":"+39 0142 454007",
    "sg:postcode":"15033",
    "sg:province":"Alessandria",
    "sg:tags":[
        "electronic",
        "electrical",
        "equipment"
    ],
    "wof:name":"De.na. (s.r.l.)",
    "wof:placetype":"venue"
},
  "geometry": {"coordinates":[8.616951,44.913216],"type":"Point"}
}