{
  "type": "Feature",
  "properties": {
    "iso:country":"IT",
    "sg:address":"40055 Castenaso",
    "sg:city":"Castenaso",
    "sg:classifiers":[
        {
            "category":"Banks & Credit Unions",
            "subcategory":"Financial Services",
            "type":"Services"
        }
    ],
    "sg:phone":"+39 051 787318",
    "sg:postcode":"40055",
    "sg:province":"Bologna",
    "sg:tags":[
        "articles",
        "product",
        "plastics",
        "industry",
        "work",
        "plastic"
    ],
    "sg:website":"http://www.oto.it",
    "wof:name":"Oto Di Tosi Odoardo",
    "wof:placetype":"venue"
},
  "geometry": {"coordinates":[11.3961687088,44.5503959656],"type":"Point"}
}