{
  "type": "Feature",
  "properties": {
    "addr:full":"10093 Collegno Collegno Torino 10093",
    "addr:postcode":"10093;10093",
    "iso:country":"IT",
    "sg:address":"10093 Collegno",
    "sg:city":"Collegno",
    "sg:orig_category":"Vernici Edilizia",
    "sg:phone":"+39 011 411 1718",
    "sg:postcode":"10093",
    "sg:province":"Torino",
    "sg:website":"http://www.vires.it",
    "wof:name":"Vires Srl",
    "wof:placetype":"venue"
},
  "geometry": {"coordinates":[7.594311,45.079376],"type":"Point"}
}