{
  "type": "Feature",
  "properties": {
    "iso:country":"IT",
    "sg:address":"19032 Lerici",
    "sg:city":"Lerici",
    "sg:orig_category":"Carte Geografiche, Topografiche E Nautiche",
    "sg:phone":"+39 0187 967358",
    "sg:postcode":"19032",
    "sg:province":"La Spezia",
    "wof:name":"Bruno Gatti",
    "wof:placetype":"venue"
},
  "geometry": {"coordinates":[9.911414,44.073879],"type":"Point"}
}