{
  "type": "Feature",
  "properties": {
    "addr:full":"31033 Castelfranco Veneto Castelfranco Veneto Treviso 31033",
    "addr:postcode":"31033;31033",
    "iso:country":"IT",
    "sg:address":"31033 Castelfranco Veneto",
    "sg:city":"Castelfranco Veneto",
    "sg:orig_category":"Forniture Per Attivita' Industriali",
    "sg:phone":"+39 0423 722812",
    "sg:postcode":"31033",
    "sg:province":"Treviso",
    "wof:name":"Guidolin & Sbrissa Srl",
    "wof:placetype":"venue"
},
  "geometry": {"coordinates":[11.9316997528,45.672077179],"type":"Point"}
}