{
  "type": "Feature",
  "properties": {
    "iso:country":"IT",
    "sg:address":"14100 Asti",
    "sg:city":"Asti",
    "sg:orig_category":"Prodotti Alimentari. Agricoltura, Orticoltura E Floricoltura",
    "sg:phone":"+39 0141 599800",
    "sg:postcode":"14100",
    "sg:province":"Asti",
    "wof:name":"Micoplant S.s.",
    "wof:placetype":"venue"
},
  "geometry": {"coordinates":[8.2136564255,44.9102401733],"type":"Point"}
}