{
  "type": "Feature",
  "properties": {
    "iso:country":"IT",
    "sg:address":"90139 Palermo",
    "sg:city":"Palermo",
    "sg:classifiers":[
        {
            "category":"Health Services",
            "subcategory":"Health Practitioner",
            "type":"Services"
        }
    ],
    "sg:phone":"+39 091 585233",
    "sg:postcode":"90139",
    "sg:province":"Palermo",
    "sg:tags":[
        "medici"
    ],
    "wof:name":"Liotta Andrea",
    "wof:placetype":"venue"
},
  "geometry": {"coordinates":[13.356972,38.125717],"type":"Point"}
}