{
  "type": "Feature",
  "properties": {
    "iso:country":"IT",
    "sg:address":"05100 Terni",
    "sg:city":"Terni",
    "sg:orig_category":"Utensili Meccanici E Materiali",
    "sg:phone":"+39 0744 812604",
    "sg:postcode":"05100",
    "sg:province":"Terni",
    "wof:name":"Casarin Walter Snc",
    "wof:placetype":"venue"
},
  "geometry": {"coordinates":[12.593997,42.569714],"type":"Point"}
}