{
  "type": "Feature",
  "properties": {
    "addr:full":"17, Via Sassetti Filippo 20124 Milano Milano Milano 20124",
    "addr:postcode":"20124;20124",
    "addr:street":"Via Sassetti Filippo",
    "iso:country":"IT",
    "sg:address":"17, Via Sassetti Filippo 20124 Milano",
    "sg:city":"Milano",
    "sg:classifiers":[
        {
            "category":"Food & Beverages",
            "subcategory":"Groceries & Convenience Stores",
            "type":"Retail Goods"
        }
    ],
    "sg:phone":"+39 02 6680 5771",
    "sg:postcode":"20124",
    "sg:province":"Milano",
    "sg:tags":[
        "product",
        "related"
    ],
    "wof:name":"Emar Di Romeo Mario E C. Snc",
    "wof:placetype":"venue"
},
  "geometry": {"coordinates":[9.1938333511,45.4867668152],"type":"Point"}
}