{
  "type": "Feature",
  "properties": {
    "addr:full":"20141 Milano Milano Milano 20141",
    "addr:postcode":"20141;20141",
    "iso:country":"IT",
    "sg:address":"20141 Milano",
    "sg:city":"Milano",
    "sg:orig_category":"Forniture Uffici",
    "sg:phone":"+39 02 5730 0528",
    "sg:postcode":"20141",
    "sg:province":"Milano",
    "wof:name":"Poron Italia Soc.coop.r.l.",
    "wof:placetype":"venue"
},
  "geometry": {"coordinates":[9.1898603439,45.4402198792],"type":"Point"}
}