{
  "type": "Feature",
  "properties": {
    "addr:full":"80124 Napoli Napoli Napoli 80124",
    "addr:housenumber":"80124",
    "addr:postcode":"80124",
    "iso:country":"IT",
    "sg:address":"80124 Napoli",
    "sg:city":"Napoli",
    "sg:orig_category":"Impianti, Attrezzature E Forniture Sanitarie Ed Ospedaliere",
    "sg:phone":"+39 081 239 7519",
    "sg:postcode":"80124",
    "sg:province":"Napoli",
    "wof:name":"Bollino Ruggiero",
    "wof:placetype":"venue"
},
  "geometry": {"coordinates":[14.313208,40.93079],"type":"Point"}
}