{
  "type": "Feature",
  "properties": {
    "iso:country":"IT",
    "sg:address":"18, Viale Delle Industrie 20020 Arese",
    "sg:city":"Arese",
    "sg:classifiers":[
        {
            "category":"Communications",
            "subcategory":"Television Station",
            "type":"Services"
        }
    ],
    "sg:phone":"+39 390 293 7731",
    "sg:postcode":"20020",
    "sg:province":"Milano",
    "sg:tags":[
        "equipment",
        "optical",
        "instrument"
    ],
    "wof:name":"Zeiss Carl Spa",
    "wof:placetype":"venue"
},
  "geometry": {"coordinates":[9.08831,45.534939],"type":"Point"}
}