{
  "type": "Feature",
  "properties": {
    "iso:country":"IT",
    "sg:address":"20157 Milano",
    "sg:city":"Milano",
    "sg:orig_category":"Servizi E Lavori Per Ecologia E Smaltimento Rifiuti. Ospedali E Servizi Sanitari. Servizi Ausiliari Di Analisi, Controllo E Ricerca",
    "sg:phone":"+39 02 390 9101",
    "sg:postcode":"20157",
    "sg:province":"Milano",
    "sg:website":"http://www.instron.com",
    "wof:name":"Instron International Limited",
    "wof:placetype":"venue"
},
  "geometry": {"coordinates":[9.135863,45.514584],"type":"Point"}
}