{
  "type": "Feature",
  "properties": {
    "iso:country":"IT",
    "sg:address":"00040 Pomezia",
    "sg:city":"Pomezia",
    "sg:orig_category":"Impiantistica E Prodotti Tecnologici Per Edilizia. Elettronica Professionale E Di Consumo",
    "sg:phone":"+39 06 9160 3319",
    "sg:postcode":"00040",
    "sg:province":"Roma",
    "wof:name":"Itac - Tron Srl",
    "wof:placetype":"venue"
},
  "geometry": {"coordinates":[12.489904,41.68066],"type":"Point"}
}