{
  "type": "Feature",
  "properties": {
    "iso:country":"IT",
    "sg:address":"1, V. Del Lavoro - C.p. 30 70051 Barletta",
    "sg:city":"Barletta",
    "sg:classifiers":[
        {
            "category":"Personal",
            "subcategory":"Shoe Repair & Shine",
            "type":"Services"
        }
    ],
    "sg:phone":"+39 0883 348011",
    "sg:postcode":"70051",
    "sg:province":"Bari",
    "sg:tags":[
        "leather"
    ],
    "sg:website":"http://www.miros-shoes.it:ws_end: :mark:ws:http://www.paginegialle.it/calzaturemiros",
    "wof:name":"Calzaturificio Miros Srl",
    "wof:placetype":"venue"
},
  "geometry": {"coordinates":[16.310213,41.311424],"type":"Point"}
}