{
  "type": "Feature",
  "properties": {
    "iso:country":"IT",
    "sg:address":"16153 Genova",
    "sg:city":"Genova",
    "sg:orig_category":"Ferro Battuto",
    "sg:phone":"+39 010 651 2114",
    "sg:postcode":"16153",
    "sg:province":"Genova",
    "wof:name":"Ligurstandar Di Grotto E. & C. Snc",
    "wof:placetype":"venue"
},
  "geometry": {"coordinates":[8.8165931702,44.4276733398],"type":"Point"}
}