{
  "type": "Feature",
  "properties": {
    "iso:country":"IT",
    "sg:address":"14, Localita' Centergross Blocco 40050 Argelato",
    "sg:city":"Argelato",
    "sg:classifiers":[
        {
            "category":"Real Estate",
            "subcategory":"Architect",
            "type":"Services"
        }
    ],
    "sg:phone":"+39 39051864620",
    "sg:postcode":"40050",
    "sg:province":"Bologna",
    "sg:tags":[
        "textile",
        "clothing"
    ],
    "wof:name":"Atos Lombardini & C. (s.a.s.)",
    "wof:placetype":"venue"
},
  "geometry": {"coordinates":[11.346481,44.494221],"type":"Point"}
}