{
  "type": "Feature",
  "properties": {
    "iso:country":"IT",
    "sg:address":"31, Via L. Da Vinci 42023 Cadelbosco Di Sopra",
    "sg:classifiers":[
        {
            "category":"Retail",
            "subcategory":"Animal Services",
            "type":"Services"
        }
    ],
    "sg:phone":"+39 0522 911621",
    "sg:postcode":"42023",
    "sg:province":"Reggio Nell'Emilia",
    "sg:tags":[
        "breeding"
    ],
    "wof:name":"Val Po (s.r.l.)",
    "wof:placetype":"venue"
},
  "geometry": {"coordinates":[10.618957,44.804279],"type":"Point"}
}