{
  "type": "Feature",
  "properties": {
    "addr:full":"2, Via Felicetto 95010 Santa Venerina Santa Venerina Catania 95010",
    "addr:postcode":"95010;95010",
    "addr:street":"Via Felicetto",
    "iso:country":"IT",
    "sg:address":"2, Via Felicetto 95010 Santa Venerina",
    "sg:city":"Santa Venerina",
    "sg:classifiers":[
        {
            "category":"Building & Trades",
            "subcategory":"Construction",
            "type":"Services"
        }
    ],
    "sg:phone":"+39 39095958426",
    "sg:postcode":"95010",
    "sg:province":"Catania",
    "sg:tags":[
        "work",
        "public"
    ],
    "wof:name":"Scaviter (s.r.l.)",
    "wof:placetype":"venue"
},
  "geometry": {"coordinates":[15.139026,37.665207],"type":"Point"}
}