{
  "type": "Feature",
  "properties": {
    "iso:country":"IT",
    "sg:address":"34135 Trieste",
    "sg:city":"Trieste",
    "sg:orig_category":"Abiti Da Lavoro Ed Indumenti Protettivi",
    "sg:phone":"+39 040 413043",
    "sg:postcode":"34135",
    "sg:province":"Trieste",
    "wof:name":"Sider Trieste Di Gianfranco Pergolis",
    "wof:placetype":"venue"
},
  "geometry": {"coordinates":[13.772827,45.666752],"type":"Point"}
}