{
  "type": "Feature",
  "properties": {
    "iso:country":"IT",
    "sg:address":"25065 Lumezzane",
    "sg:city":"Lumezzane",
    "sg:orig_category":"Utensili Meccanici E Materiali",
    "sg:phone":"+39 030 826284",
    "sg:postcode":"25065",
    "sg:province":"Brescia",
    "wof:name":"F.b.s. Di Bossini & C. Snc",
    "wof:placetype":"venue"
},
  "geometry": {"coordinates":[10.271223,45.641441],"type":"Point"}
}