{
  "type": "Feature",
  "properties": {
    "addr:full":"20099 Sesto San Giovanni Sesto San Giovanni Milano 20099",
    "addr:postcode":"20099;20099",
    "iso:country":"IT",
    "sg:address":"20099 Sesto San Giovanni",
    "sg:city":"Sesto San Giovanni",
    "sg:orig_category":"Servizi Ausiliari Dei Mezzi Di Trasporto",
    "sg:phone":"+39 02 240 4609",
    "sg:postcode":"20099",
    "sg:province":"Milano",
    "wof:name":"Tufo Carmine S.n.c. Di Tufo Carmine E C.",
    "wof:placetype":"venue"
},
  "geometry": {"coordinates":[9.243684,45.535271],"type":"Point"}
}