{
  "type": "Feature",
  "properties": {
    "iso:country":"IT",
    "sg:address":"00042 Anzio",
    "sg:city":"Anzio",
    "sg:orig_category":"Servizi Per Lo Sport E Il Tempo Libero. Alberghi E Strutture Extra Alberghiere",
    "sg:phone":"+39 06 984 5680",
    "sg:postcode":"00042",
    "sg:province":"Roma",
    "wof:name":"Stabilimento Balneare Tirrena",
    "wof:placetype":"venue"
},
  "geometry": {"coordinates":[12.61014,41.511349],"type":"Point"}
}