{
  "type": "Feature",
  "properties": {
    "addr:full":"80121 Napoli Napoli Napoli 80121",
    "addr:housenumber":"80121",
    "addr:postcode":"80121",
    "iso:country":"IT",
    "sg:address":"80121 Napoli",
    "sg:city":"Napoli",
    "sg:orig_category":"Pubblicita', Marketing E Comunicazione",
    "sg:phone":"+39 081 764 7901",
    "sg:postcode":"80121",
    "sg:province":"Napoli",
    "sg:website":"http://www.blupromo.it",
    "wof:name":"Blu Srl",
    "wof:placetype":"venue"
},
  "geometry": {"coordinates":[14.2417764664,40.8330345154],"type":"Point"}
}