{
  "type": "Feature",
  "properties": {
    "iso:country":"IT",
    "sg:address":"54033 Carrara",
    "sg:city":"Carrara",
    "sg:orig_category":"Prodotti Finiti Stampati. Servizi Editoriali. Tempo Libero - Articoli E Forniture",
    "sg:phone":"+39 0585 788870",
    "sg:postcode":"54033",
    "sg:province":"Massa-Carrara",
    "wof:name":"C-map S.r.l.",
    "wof:placetype":"venue"
},
  "geometry": {"coordinates":[10.0706748962,44.0259819031],"type":"Point"}
}