{
  "type": "Feature",
  "properties": {
    "addr:full":"Via Borgo Ai Fossi 7 50018 Scandicci Scandicci Firenze 50018",
    "addr:housenumber":"7",
    "addr:postcode":"50018;50018",
    "addr:street":"Via Borgo Ai Fossi",
    "iso:country":"IT",
    "sg:address":"Via Borgo Ai Fossi 7 50018 Scandicci",
    "sg:city":"Scandicci",
    "sg:classifiers":[
        {
            "category":"Shopping",
            "subcategory":"Crafts & Fabrics",
            "type":"Retail Goods"
        }
    ],
    "sg:phone":"+39 055 722 1189",
    "sg:postcode":"50018",
    "sg:province":"Firenze",
    "sg:tags":[
        "industry",
        "shoe"
    ],
    "wof:name":"M.b.f. Italia Srl",
    "wof:placetype":"venue"
},
  "geometry": {"coordinates":[11.1519832611,43.7704162598],"type":"Point"}
}