{
  "type": "Feature",
  "properties": {
    "iso:country":"IT",
    "sg:address":"44100 Ferrara",
    "sg:city":"Ferrara",
    "sg:orig_category":"Carta Da Macero",
    "sg:phone":"+39 0532 730260",
    "sg:postcode":"44100",
    "sg:province":"Ferrara",
    "wof:name":"Pasqualini Dario",
    "wof:placetype":"venue"
},
  "geometry": {"coordinates":[11.61939,44.838329],"type":"Point"}
}