{
  "type": "Feature",
  "properties": {
    "addr:full":"03043 Cassino Cassino Frosinone 03043",
    "addr:postcode":"03043;03043",
    "iso:country":"IT",
    "sg:address":"03043 Cassino",
    "sg:city":"Cassino",
    "sg:classifiers":[
        {
            "category":"Health Services",
            "subcategory":"Health Practitioner",
            "type":"Services"
        }
    ],
    "sg:phone":"+39 0776 26130",
    "sg:postcode":"03043",
    "sg:province":"Frosinone",
    "sg:tags":[
        "medici"
    ],
    "wof:name":"Tamburrini Dr. Luigi",
    "wof:placetype":"venue"
},
  "geometry": {"coordinates":[13.8310441971,41.4870796204],"type":"Point"}
}