{
  "type": "Feature",
  "properties": {
    "iso:country":"IT",
    "sg:address":"45, Via Della Misericordia 20057 Vedano Al Lambro",
    "sg:city":"Vedano al Lambro",
    "sg:classifiers":[
        {
            "category":"Shopping",
            "subcategory":"Computers & Home Electronics",
            "type":"Retail Goods"
        }
    ],
    "sg:phone":"+39 039 249 5678",
    "sg:postcode":"20057",
    "sg:province":"Milano",
    "sg:tags":[
        "electronic",
        "electrical",
        "equipment"
    ],
    "wof:name":"Esperia Distribuzione Sas",
    "wof:placetype":"venue"
},
  "geometry": {"coordinates":[9.265638,45.618057],"type":"Point"}
}