{
  "type": "Feature",
  "properties": {
    "iso:country":"IT",
    "sg:address":"20013 Magenta",
    "sg:city":"Magenta",
    "sg:orig_category":"Servizi Culturali E Per Lo Spettacolo. Servizi Al Turismo. Acqua, Luce, Gas E Societa' Di Esercizio Pubblico",
    "sg:phone":"+39 02 979 0828",
    "sg:postcode":"20013",
    "sg:province":"Milano",
    "wof:name":"Biblioteca Comunale Centro Culturale",
    "wof:placetype":"venue"
},
  "geometry": {"coordinates":[8.753222,45.467358],"type":"Point"}
}