{
  "type": "Feature",
  "properties": {
    "addr:full":"20, Via Montecuccoli Raimondo 20147 Milano Milano Milano 20147",
    "addr:postcode":"20147;20147",
    "addr:street":"Via Montecuccoli Raimondo",
    "iso:country":"IT",
    "sg:address":"20, Via Montecuccoli Raimondo 20147 Milano",
    "sg:city":"Milano",
    "sg:classifiers":[
        {
            "category":"Food & Beverages",
            "subcategory":"Dairy",
            "type":"Retail Goods"
        }
    ],
    "sg:phone":"+39 390 241 351",
    "sg:postcode":"20147",
    "sg:province":"Milano",
    "sg:tags":[
        "product"
    ],
    "wof:name":"Kraft Foods Italia Spa",
    "wof:placetype":"venue"
},
  "geometry": {"coordinates":[9.134881,45.459522],"type":"Point"}
}