{
  "type": "Feature",
  "properties": {
    "iso:country":"IT",
    "sg:address":"20010 Arluno",
    "sg:city":"Arluno",
    "sg:orig_category":"Utensili Meccanici E Materiali. Forniture Per Attivita' Industriali",
    "sg:phone":"+39 02 901 7145",
    "sg:postcode":"20010",
    "sg:province":"Milano",
    "wof:name":"Restelli Gianluigi",
    "wof:placetype":"venue"
},
  "geometry": {"coordinates":[8.940435,45.512115],"type":"Point"}
}