{
  "type": "Feature",
  "properties": {
    "iso:country":"IT",
    "sg:address":"Via Dei Materassai 15 57121 Livorno",
    "sg:city":"Livorno",
    "sg:classifiers":[
        {
            "category":"Home & Garden",
            "subcategory":"Home Furnishings",
            "type":"Retail Goods"
        }
    ],
    "sg:phone":"+39 0586 429696",
    "sg:postcode":"57121",
    "sg:province":"Livorno",
    "sg:tags":[
        "bathroom",
        "wc",
        "fitting"
    ],
    "wof:name":"Lino Veroni Srl",
    "wof:placetype":"venue"
},
  "geometry": {"coordinates":[10.340712,43.571411],"type":"Point"}
}