{
  "type": "Feature",
  "properties": {
    "iso:country":"IT",
    "sg:address":"95121 Catania",
    "sg:city":"Catania",
    "sg:orig_category":"Elettrotecnica Industriale, Prodotti E Apparecchiature. Ricambi E Componenti Dei Mezzi Di Trasporto",
    "sg:phone":"+39 095 713 9215",
    "sg:postcode":"95121",
    "sg:province":"Catania",
    "wof:name":"D. & D. Carrelli Elevatori Snc Di Distefano",
    "wof:placetype":"venue"
},
  "geometry": {"coordinates":[15.008988,37.415855],"type":"Point"}
}