{
  "type": "Feature",
  "properties": {
    "iso:country":"IT",
    "sg:address":"36036 Torrebelvicino",
    "sg:city":"Torrebelvicino",
    "sg:orig_category":"Prodotti Finiti Stampati. Forniture E Prodotti Informatici. Forniture Per Uffici",
    "sg:phone":"+39 0445 660067",
    "sg:postcode":"36036",
    "sg:province":"Vicenza",
    "wof:name":"Arti Grafiche Di Menegozzo Pier Franco & C. Snc",
    "wof:placetype":"venue"
},
  "geometry": {"coordinates":[11.540596962,45.5548095703],"type":"Point"}
}