{
  "type": "Feature",
  "properties": {
    "addr:full":"80039 Saviano Saviano Napoli 80039",
    "addr:postcode":"80039;80039",
    "iso:country":"IT",
    "sg:address":"80039 Saviano",
    "sg:city":"Saviano",
    "sg:orig_category":"Scuole E Servizi Scolastici. Servizi Ausiliari Dei Mezzi Di Trasporto. Ricerca, Selezione E Formazione Del Personale",
    "sg:phone":"+39 338 951 2058",
    "sg:postcode":"80039",
    "sg:province":"Napoli",
    "wof:name":"Autoscuola La Super",
    "wof:placetype":"venue"
},
  "geometry": {"coordinates":[14.510825,40.910759],"type":"Point"}
}