{
  "type": "Feature",
  "properties": {
    "iso:country":"IT",
    "sg:address":"50066 Reggello",
    "sg:city":"Reggello",
    "sg:orig_category":"Materiali Edili",
    "sg:phone":"+39 055 861228",
    "sg:postcode":"50066",
    "sg:province":"Firenze",
    "wof:name":"Venturini Pasquale",
    "wof:placetype":"venue"
},
  "geometry": {"coordinates":[11.502075,43.686054],"type":"Point"}
}