{
  "type": "Feature",
  "properties": {
    "iso:country":"IT",
    "sg:address":"15, Via Alberto Da Giussano 21053 Castellanza",
    "sg:city":"Castellanza",
    "sg:classifiers":[
        {
            "category":"Professional",
            "subcategory":"Computer Services",
            "type":"Services"
        }
    ],
    "sg:phone":"+39 0331 501395",
    "sg:postcode":"21053",
    "sg:province":"Varese",
    "sg:tags":[
        "information",
        "technology"
    ],
    "wof:name":"Blu 3 Programma Ufficio (s.r.l.)",
    "wof:placetype":"venue"
},
  "geometry": {"coordinates":[8.85716,45.609749],"type":"Point"}
}