{
  "type": "Feature",
  "properties": {
    "iso:country":"IT",
    "sg:address":"16, Via Monte Rosa 20049 Concorezzo",
    "sg:city":"Concorezzo",
    "sg:classifiers":[
        {
            "category":"Shopping",
            "subcategory":"Crafts & Fabrics",
            "type":"Retail Goods"
        }
    ],
    "sg:phone":"+39 039 604 1617",
    "sg:postcode":"20049",
    "sg:province":"Milano",
    "wof:name":"Nastrificio Albert Bonati Srl",
    "wof:placetype":"venue"
},
  "geometry": {"coordinates":[9.3269138336,45.5954666138],"type":"Point"}
}