{
  "type": "Feature",
  "properties": {
    "iso:country":"IT",
    "sg:address":"Via Dante 35 20032 Cormano",
    "sg:city":"Cormano",
    "sg:classifiers":[
        {
            "category":"Professional",
            "subcategory":"Testing Lab",
            "type":"Services"
        }
    ],
    "sg:phone":"+39 02 615 2021",
    "sg:postcode":"20032",
    "sg:province":"Milano",
    "sg:tags":[
        "development",
        "pharmaceutical",
        "clinical"
    ],
    "sg:website":"www.newscientific.com",
    "wof:name":"New Scientific Company Srl",
    "wof:placetype":"venue"
},
  "geometry": {"coordinates":[9.160259,45.547928],"type":"Point"}
}