{
  "type": "Feature",
  "properties": {
    "addr:full":"80147 Napoli Napoli Napoli 80147",
    "addr:postcode":"80147;80147",
    "iso:country":"IT",
    "sg:address":"80147 Napoli",
    "sg:city":"Napoli",
    "sg:orig_category":"Manufacturers: Prefabbricati. Servizi E Lavori Per Ecologia E Smaltimento Rifiuti",
    "sg:phone":"+39 081 584 6420",
    "sg:postcode":"80147",
    "sg:province":"Napoli",
    "wof:name":"Mediterranea Espurghi Srl",
    "wof:placetype":"venue"
},
  "geometry": {"coordinates":[14.318336,40.858311],"type":"Point"}
}