{
  "type": "Feature",
  "properties": {
    "addr:full":"Via Campi Della Rienza 41 39031 Bruneck Bolzano/Bozen 39031",
    "addr:housenumber":"41",
    "addr:postcode":"39031;39031",
    "addr:street":"Via Campi Della Rienza",
    "iso:country":"IT",
    "sg:address":"Via Campi Della Rienza 41 39031 Bruneck",
    "sg:orig_category":"Window Locks",
    "sg:phone":"+39 0474 550853",
    "sg:postcode":"39031",
    "sg:province":"Bolzano/Bozen",
    "sg:website":"www.climainfo.com",
    "wof:name":"Clima Srl",
    "wof:placetype":"venue"
},
  "geometry": {"coordinates":[11.925877,46.798061],"type":"Point"}
}