{
  "type": "Feature",
  "properties": {
    "iso:country":"IT",
    "sg:address":"43100 Baganzola",
    "sg:city":"Baganzola",
    "sg:orig_category":"Termotecnica E Riscaldamento, Apparecchiature E Servizi",
    "sg:phone":"+39 0521 983826",
    "sg:postcode":"43100",
    "sg:province":"Parma",
    "wof:name":"Tecnotermica (s.r.l.)",
    "wof:placetype":"venue"
},
  "geometry": {"coordinates":[10.309452,44.831703],"type":"Point"}
}