{
  "type": "Feature",
  "properties": {
    "addr:full":"07100 Sassari Sassari Sassari 07100",
    "addr:postcode":"07100;07100",
    "iso:country":"IT",
    "sg:address":"07100 Sassari",
    "sg:city":"Sassari",
    "sg:classifiers":[
        {
            "category":"Autos & Motor Vehicles",
            "subcategory":"Recreational Vehicle Sales",
            "type":"Retail Goods"
        }
    ],
    "sg:phone":"+39 079 274246",
    "sg:postcode":"07100",
    "sg:province":"Sassari",
    "sg:tags":[
        "spare",
        "part",
        "vehicles",
        "component",
        "pumps"
    ],
    "wof:name":"De Montis Cesare",
    "wof:placetype":"venue"
},
  "geometry": {"coordinates":[8.3745718002,40.7555809021],"type":"Point"}
}