{
  "type": "Feature",
  "properties": {
    "addr:full":"Piazza Xx Settembre, 11; S. Agata; 71028 Foggia 71028",
    "addr:housenumber":"11",
    "addr:postcode":"71028;71028",
    "addr:street":"Piazza Xx Settembre;Agata",
    "iso:country":"IT",
    "sg:address":"Piazza Xx Settembre, 11; S. Agata; 71028",
    "sg:classifiers":[
        {
            "category":"Banks & Credit Unions",
            "subcategory":"Bank",
            "type":"Services"
        }
    ],
    "sg:phone":"+39 0881 984006",
    "sg:postcode":"71028",
    "sg:province":"Foggia",
    "wof:name":"Cassa Di Risparmio Di Puglia",
    "wof:placetype":"venue"
},
  "geometry": {"coordinates":[15.383381,41.138966],"type":"Point"}
}