{
  "type": "Feature",
  "properties": {
    "addr:full":"85024 Lavello Lavello Potenza 85024",
    "addr:postcode":"85024;85024",
    "addr:street":"Lavello Lavello",
    "iso:country":"IT",
    "sg:address":"85024 Lavello",
    "sg:city":"Lavello",
    "sg:orig_category":"Servizi E Lavori Per Agricoltura E Zootecnia. Consulenze Tecniche, Amministrative E Perizie",
    "sg:phone":"+39 0972 877212",
    "sg:postcode":"85024",
    "sg:province":"Potenza",
    "wof:name":"Studio Progettazione Aree Verdi-ingegneria Naturalistica Di Michele Dr. Ranauro",
    "wof:placetype":"venue"
},
  "geometry": {"coordinates":[15.840773,41.065815],"type":"Point"}
}