{
  "type": "Feature",
  "properties": {
    "iso:country":"IT",
    "sg:address":"111, Corso Racconigi 10141 Torino",
    "sg:city":"Torino",
    "sg:classifiers":[
        {
            "category":"Shopping",
            "subcategory":"Computers & Home Electronics",
            "type":"Retail Goods"
        }
    ],
    "sg:phone":"+39 011 385 4414",
    "sg:postcode":"10141",
    "sg:province":"Torino",
    "sg:tags":[
        "electronic",
        "electrical",
        "equipment"
    ],
    "wof:name":"Grondona",
    "wof:placetype":"venue"
},
  "geometry": {"coordinates":[7.646844,45.070194],"type":"Point"}
}