{
  "type": "Feature",
  "properties": {
    "addr:full":"21042 Caronno Pertusella Caronno Pertusella Varese 21042",
    "addr:postcode":"21042;pertusella;21042",
    "addr:street":"Pertusella",
    "iso:country":"IT",
    "sg:address":"21042 Caronno Pertusella",
    "sg:city":"Caronno Pertusella",
    "sg:orig_category":"Metalli E Leghe",
    "sg:phone":"+39 02 965 9028",
    "sg:postcode":"21042",
    "sg:province":"Varese",
    "sg:website":"http://www.famprofili.it",
    "wof:name":"Ferriera Alto Milanese Spa",
    "wof:placetype":"venue"
},
  "geometry": {"coordinates":[9.0371799469,45.599357605],"type":"Point"}
}