{
  "type": "Feature",
  "properties": {
    "iso:country":"IT",
    "sg:address":"45, Via Martiri Zannolli 66010 Miglianico",
    "sg:city":"Miglianico",
    "sg:classifiers":[
        {
            "category":"Real Estate",
            "subcategory":"Architect",
            "type":"Services"
        }
    ],
    "sg:phone":"+39 0871 950070",
    "sg:postcode":"66010",
    "sg:province":"Chieti",
    "sg:tags":[
        "textile",
        "clothing"
    ],
    "wof:name":"Fenice S.r.l. Confezione Abiti",
    "wof:placetype":"venue"
},
  "geometry": {"coordinates":[14.294332,42.360138],"type":"Point"}
}