{
  "type": "Feature",
  "properties": {
    "addr:full":"59, Via Voghera 15052 Casalnoceto Casalnoceto Alessandria 15052",
    "addr:postcode":"15052;15052",
    "addr:street":"Via Voghera",
    "iso:country":"IT",
    "sg:address":"59, Via Voghera 15052 Casalnoceto",
    "sg:city":"Casalnoceto",
    "sg:classifiers":[
        {
            "category":"Food & Beverages",
            "subcategory":"Dairy",
            "type":"Retail Goods"
        }
    ],
    "sg:phone":"+39 0131 809620",
    "sg:postcode":"15052",
    "sg:province":"Alessandria",
    "sg:tags":[
        "product"
    ],
    "wof:name":"Al.gro - S.r.l.",
    "wof:placetype":"venue"
},
  "geometry": {"coordinates":[8.986404,44.915718],"type":"Point"}
}