{
  "type": "Feature",
  "properties": {
    "addr:full":"172/5, Via Sempione 21052 Busto Arsizio Busto Arsizio Varese 21052",
    "addr:housenumber":"172 / 5",
    "addr:postcode":"21052;21052",
    "addr:street":"Via Sempione",
    "iso:country":"IT",
    "sg:address":"172/5, Via Sempione 21052 Busto Arsizio",
    "sg:city":"Busto Arsizio",
    "sg:classifiers":[
        {
            "category":"Shopping",
            "subcategory":"Clothing, Apparel, & Fashions",
            "type":"Retail Goods"
        }
    ],
    "sg:phone":"+39 0331 683296",
    "sg:postcode":"21052",
    "sg:province":"Varese",
    "sg:tags":[
        "clothes"
    ],
    "wof:name":"Maglif. Gallazzi & Farioli Di Farioli Rosa E Osvaldo Snc",
    "wof:placetype":"venue"
},
  "geometry": {"coordinates":[8.838435,45.631874],"type":"Point"}
}