{
  "type": "Feature",
  "properties": {
    "iso:country":"IT",
    "sg:address":"27010 Cura Carpignano",
    "sg:city":"Cura Carpignano",
    "sg:orig_category":"Affettatrici E Tritacarne",
    "sg:phone":"+39 0382 474396",
    "sg:postcode":"27010",
    "sg:province":"Pavia",
    "wof:name":"Essedue Srl",
    "wof:placetype":"venue"
},
  "geometry": {"coordinates":[9.219943,45.206768],"type":"Point"}
}