{
  "type": "Feature",
  "properties": {
    "iso:country":"IT",
    "sg:address":"20037 Paderno Dugnano",
    "sg:city":"Paderno Dugnano",
    "sg:orig_category":"Macchine, Impianti Ed Attrezzature Industria Chimica. Attrezzature E Forniture Per Officine Riparazione E Servizi Ausiliari",
    "sg:phone":"+39 02 910 6159",
    "sg:postcode":"20037",
    "sg:province":"Milano",
    "wof:name":"Diana Impianti Sas Di Marson Gabriele & C.",
    "wof:placetype":"venue"
},
  "geometry": {"coordinates":[9.169607,45.591766],"type":"Point"}
}