{
  "type": "Feature",
  "properties": {
    "iso:country":"IT",
    "sg:address":"16152 Genova",
    "sg:city":"Genova",
    "sg:orig_category":"Forniture Per Agricoltura E Zootecnia. Animali Domestici",
    "sg:phone":"+39 010 601 1457",
    "sg:postcode":"16152",
    "sg:province":"Genova",
    "wof:name":"A.m. Forniture Ospedaliere S.r.l.",
    "wof:placetype":"venue"
},
  "geometry": {"coordinates":[8.88022995,44.4217071533],"type":"Point"}
}