{
  "type": "Feature",
  "properties": {
    "addr:full":"12051 Alba Alba Cuneo 12051",
    "addr:postcode":"12051;12051",
    "iso:country":"IT",
    "sg:address":"12051 Alba",
    "sg:city":"Alba",
    "sg:orig_category":"Centri Di Estetica E Cosmesi E Servizi",
    "sg:phone":"+39 0173 440597",
    "sg:postcode":"12051",
    "sg:province":"Cuneo",
    "wof:name":"Xavier Snc",
    "wof:placetype":"venue"
},
  "geometry": {"coordinates":[8.034093,44.692822],"type":"Point"}
}