{
  "type": "Feature",
  "properties": {
    "iso:country":"IT",
    "sg:address":"05029 Terni",
    "sg:orig_category":"Apparecchiature E Sistemi Per Imballaggio E Confezionamento. Apparecchiature E Sistemi Per Magazzinaggio E Movimentazione",
    "sg:phone":"+39 0744 243444",
    "sg:postcode":"05029",
    "sg:province":"Terni",
    "sg:website":"http://www.faeterni.it",
    "wof:name":"Fae Spa",
    "wof:placetype":"venue"
},
  "geometry": {"coordinates":[12.646781,42.560219],"type":"Point"}
}