{
  "type": "Feature",
  "properties": {
    "iso:country":"IT",
    "sg:address":"41100 Modena",
    "sg:city":"Modena",
    "sg:orig_category":"Non-classified Establishments",
    "sg:phone":"+39 059 394153",
    "sg:postcode":"41100",
    "sg:province":"Modena",
    "sg:website":"http://www.riflessivetro.it",
    "wof:name":"Riflessi Vetreria Artistica",
    "wof:placetype":"venue"
},
  "geometry": {"coordinates":[10.914199,44.628681],"type":"Point"}
}