{
  "type": "Feature",
  "properties": {
    "addr:full":"10123 Torino Torino Torino 10123",
    "addr:postcode":"10123;10123",
    "iso:country":"IT",
    "sg:address":"10123 Torino",
    "sg:city":"Torino",
    "sg:orig_category":"Autoscuole",
    "sg:phone":"+39 011 812 6828",
    "sg:postcode":"10123",
    "sg:province":"Torino",
    "wof:name":"Bibiana Di Minischetti & C. Sas",
    "wof:placetype":"venue"
},
  "geometry": {"coordinates":[7.686757,45.063103],"type":"Point"}
}