{
  "type": "Feature",
  "properties": {
    "addr:full":"47, Corso Moncenisio 10090 Rosta Rosta Torino 10090",
    "addr:postcode":"10090;10090",
    "addr:street":"Corso Moncenisio",
    "iso:country":"IT",
    "sg:address":"47, Corso Moncenisio 10090 Rosta",
    "sg:city":"Rosta",
    "sg:classifiers":[
        {
            "category":"Professional",
            "subcategory":"Printing & Photocopies",
            "type":"Services"
        }
    ],
    "sg:phone":"+39 011 954 2608",
    "sg:postcode":"10090",
    "sg:province":"Torino",
    "wof:name":"Litograf S.r.l.",
    "wof:placetype":"venue"
},
  "geometry": {"coordinates":[7.4760994911,45.0230255127],"type":"Point"}
}