{
  "type": "Feature",
  "properties": {
    "iso:country":"IT",
    "sg:address":"40055 Castenaso",
    "sg:city":"Castenaso",
    "sg:orig_category":"Petroli, Gas E Combustibili. Termotecnica E Riscaldamento, Apparecchiature E Servizi",
    "sg:phone":"+39 051 788197",
    "sg:postcode":"40055",
    "sg:province":"Bologna",
    "wof:name":"Mondialgas Di Calderari Renzo",
    "wof:placetype":"venue"
},
  "geometry": {"coordinates":[11.4537963867,44.5037269592],"type":"Point"}
}