{
  "type": "Feature",
  "properties": {
    "addr:full":"39100 Bolzano Bolzano Bolzano/Bozen 39100",
    "addr:postcode":"39100;39100",
    "iso:country":"IT",
    "sg:address":"39100 Bolzano",
    "sg:city":"Bolzano",
    "sg:orig_category":"Non-classified Establishments",
    "sg:phone":"+39 0471 305777",
    "sg:postcode":"39100",
    "sg:province":"Bolzano/Bozen",
    "wof:name":"Eccel-decorona Srl Gmbh",
    "wof:placetype":"venue"
},
  "geometry": {"coordinates":[11.361835,46.500694],"type":"Point"}
}