{
  "type": "Feature",
  "properties": {
    "iso:country":"IT",
    "sg:address":"Contrada Curatoio 5 70059 Trani",
    "sg:city":"Trani",
    "sg:orig_category":"Ladies' Shoes",
    "sg:phone":"+39 0883 491678",
    "sg:postcode":"70059",
    "sg:province":"Bari",
    "wof:name":"A. Bridge Company",
    "wof:placetype":"venue"
},
  "geometry": {"coordinates":[16.869291,41.126053],"type":"Point"}
}