{
  "type": "Feature",
  "properties": {
    "addr:full":"9, V. Morigi 20123 Milano Milano Milano 20123",
    "addr:housenumber":"9",
    "addr:postcode":"20123;20123",
    "addr:street":"V. Morigi",
    "iso:country":"IT",
    "sg:address":"9, V. Morigi 20123 Milano",
    "sg:city":"Milano",
    "sg:classifiers":[
        {
            "category":"Shopping",
            "subcategory":"Jewelry",
            "type":"Retail Goods"
        }
    ],
    "sg:phone":"+39 02 7201 0199",
    "sg:postcode":"20123",
    "sg:province":"Milano",
    "sg:tags":[
        "jewellery"
    ],
    "sg:website":"http://www.paginegialle.it/pellini",
    "wof:name":"Pellini Srl",
    "wof:placetype":"venue"
},
  "geometry": {"coordinates":[9.180923,45.463356],"type":"Point"}
}