{
  "type": "Feature",
  "properties": {
    "iso:country":"IT",
    "sg:address":"10051 Avigliana",
    "sg:city":"Avigliana",
    "sg:orig_category":"Ospedali E Servizi Sanitari",
    "sg:phone":"+39 011 931 1392",
    "sg:postcode":"10051",
    "sg:province":"Torino",
    "wof:name":"Cooperativa Sociale Di Assistenza Arl",
    "wof:placetype":"venue"
},
  "geometry": {"coordinates":[7.401068,45.082779],"type":"Point"}
}