{
  "type": "Feature",
  "properties": {
    "addr:full":"50053 Empoli Empoli Firenze 50053",
    "addr:postcode":"50053;50053",
    "iso:country":"IT",
    "sg:address":"50053 Empoli",
    "sg:city":"Empoli",
    "sg:orig_category":"Servizi E Lavori Industria Della Gomma. Servizi E Lavori Industria Delle Materie Plastiche. Forniture Per Edilizia E Lavori Pubblici",
    "sg:phone":"+39 0571 920067",
    "sg:postcode":"50053",
    "sg:province":"Firenze",
    "wof:name":"Solgomma Spa",
    "wof:placetype":"venue"
},
  "geometry": {"coordinates":[10.747925,43.67762],"type":"Point"}
}