{
  "type": "Feature",
  "properties": {
    "addr:full":"35010 Carmignano Di Brenta Carmignano di Brenta Padova 35010",
    "addr:postcode":"35010;35010",
    "addr:street":"Di Brenta",
    "iso:country":"IT",
    "sg:address":"35010 Carmignano Di Brenta",
    "sg:city":"Carmignano di Brenta",
    "sg:orig_category":"Servizi E Lavori Per Agricoltura E Zootecnia. Servizi E Lavori Per Ecologia E Smaltimento Rifiuti",
    "sg:phone":"+39 049 943 0775",
    "sg:postcode":"35010",
    "sg:province":"Padova",
    "wof:name":"Consorzio Bonifica Pedemontano Brenta",
    "wof:placetype":"venue"
},
  "geometry": {"coordinates":[11.715286,45.62191],"type":"Point"}
}