{
  "type": "Feature",
  "properties": {
    "iso:country":"IT",
    "sg:address":"Via Po 35 10098 Rivoli",
    "sg:city":"Rivoli",
    "sg:classifiers":[
        {
            "category":"Manufacturing",
            "subcategory":"Rubber & Plastics",
            "type":"Manufacturing & Wholesale Goods"
        }
    ],
    "sg:phone":"+39 011 959 6622",
    "sg:postcode":"10098",
    "sg:province":"Torino",
    "sg:tags":[
        "mould",
        "industry"
    ],
    "sg:website":"www.a-rostan.com",
    "wof:name":"Rostan Adolfo Sas",
    "wof:placetype":"venue"
},
  "geometry": {"coordinates":[7.4715647697,45.0223655701],"type":"Point"}
}