{
  "type": "Feature",
  "properties": {
    "iso:country":"IT",
    "sg:address":"18100 Imperia",
    "sg:city":"Imperia",
    "sg:orig_category":"Agenzie D'affari E Servizi Commerciali",
    "sg:phone":"+39 800 117 766",
    "sg:postcode":"18100",
    "sg:province":"Imperia",
    "wof:name":"Pec - Pronto Emergenza Casa Srl",
    "wof:placetype":"venue"
},
  "geometry": {"coordinates":[8.019358,43.907528],"type":"Point"}
}