{
  "type": "Feature",
  "properties": {
    "iso:country":"IT",
    "sg:address":"Via Piovego 20 35010 Santa Giustina In Colle",
    "sg:city":"Santa Giustina in Colle",
    "sg:classifiers":[
        {
            "category":"Home & Garden",
            "subcategory":"Household Appliances",
            "type":"Retail Goods"
        }
    ],
    "sg:phone":"+39 049 574 2645",
    "sg:postcode":"35010",
    "sg:province":"Padova",
    "sg:tags":[
        "implement",
        "gardening",
        "tool"
    ],
    "sg:website":"www.agrinova-italia.it",
    "wof:name":"Agrinova",
    "wof:placetype":"venue"
},
  "geometry": {"coordinates":[11.870393,45.530174],"type":"Point"}
}