{
  "type": "Feature",
  "properties": {
    "addr:full":"20139 Milano Milano Milano 20139",
    "addr:postcode":"20139;20139",
    "iso:country":"IT",
    "sg:address":"20139 Milano",
    "sg:city":"Milano",
    "sg:orig_category":"Depurazione E Trattamento Delle Acque - Impianti Ed Apparecchi",
    "sg:phone":"+39 02 5730 1187",
    "sg:postcode":"20139",
    "sg:province":"Milano",
    "sg:website":"http://www.dellatoffola.it",
    "wof:name":"Uni.co Srl",
    "wof:placetype":"venue"
},
  "geometry": {"coordinates":[9.227516,45.428825],"type":"Point"}
}