{
  "type": "Feature",
  "properties": {
    "addr:full":"20019 Settimo Milanese Settimo Milanese Milano 20019",
    "addr:postcode":"20019;20019",
    "iso:country":"IT",
    "sg:address":"20019 Settimo Milanese",
    "sg:city":"Settimo Milanese",
    "sg:orig_category":"Ricambi E Componenti Dei Mezzi Di Trasporto",
    "sg:phone":"+39 02 328 2811",
    "sg:postcode":"20019",
    "sg:province":"Milano",
    "wof:name":"Montagano Mario",
    "wof:placetype":"venue"
},
  "geometry": {"coordinates":[9.071325,45.470287],"type":"Point"}
}