{
  "type": "Feature",
  "properties": {
    "iso:country":"IT",
    "sg:address":"Cascina Dei Poveri 26845 Codogno",
    "sg:city":"Codogno",
    "sg:classifiers":[
        {
            "category":"Autos & Motor Vehicles",
            "subcategory":"Boat Sales",
            "type":"Retail Goods"
        }
    ],
    "sg:phone":"+39 39037730440",
    "sg:postcode":"26845",
    "sg:province":"Lodi",
    "wof:name":"Nettuno Motobarche Di Delledonne Dario",
    "wof:placetype":"venue"
},
  "geometry": {"coordinates":[9.49785,45.312878],"type":"Point"}
}