{
  "type": "Feature",
  "properties": {
    "addr:full":"42100 Reggio Emilia Reggio Nell'Emilia 42100",
    "addr:postcode":"42100;42100",
    "iso:country":"IT",
    "sg:address":"42100 Reggio Emilia",
    "sg:orig_category":"Lavorazioni Meccaniche E Servizi. Macchine E Impianti Per Attivita' Commerciali Ed Artigianali. Macchine, Strumenti Ed Apparecchi Per Attivita' Industriali. Servizi Per Aziende, Manifestazioni E Suppo",
    "sg:phone":"+39 0522 308112",
    "sg:postcode":"42100",
    "sg:province":"Reggio Nell'Emilia",
    "wof:name":"Casini Danilo",
    "wof:placetype":"venue"
},
  "geometry": {"coordinates":[10.582343,44.697788],"type":"Point"}
}