{
  "type": "Feature",
  "properties": {
    "addr:full":"Zona Industriale 53041 Asciano Asciano Siena 53041",
    "addr:postcode":"53041;53041",
    "addr:street":"Zona Industriale",
    "iso:country":"IT",
    "sg:address":"Zona Industriale 53041 Asciano",
    "sg:city":"Asciano",
    "sg:classifiers":[
        {
            "category":"Shopping",
            "type":"Retail Goods"
        }
    ],
    "sg:phone":"+39 0577 718370",
    "sg:postcode":"53041",
    "sg:province":"Siena",
    "sg:tags":[
        "finished",
        "-",
        "metallic"
    ],
    "wof:name":"2 - Ma S.r.l",
    "wof:placetype":"venue"
},
  "geometry": {"coordinates":[11.3305139542,43.3186607361],"type":"Point"}
}