{
  "type": "Feature",
  "properties": {
    "iso:country":"IT",
    "sg:address":"88050 Petrona'",
    "sg:orig_category":"Sport - Articoli E Forniture",
    "sg:phone":"+39 0961 933788",
    "sg:postcode":"88050",
    "sg:province":"Catanzaro",
    "wof:name":"Talarico Graziella",
    "wof:placetype":"venue"
},
  "geometry": {"coordinates":[16.61025,38.825569],"type":"Point"}
}