{
  "type": "Feature",
  "properties": {
    "addr:full":"27/29, Via Per Sacile 31018 Gaiarine Gaiarine Treviso 31018",
    "addr:housenumber":"27 / 29",
    "addr:postcode":"31018;31018",
    "addr:street":"Via Per Sacile",
    "iso:country":"IT",
    "sg:address":"27/29, Via Per Sacile 31018 Gaiarine",
    "sg:city":"Gaiarine",
    "sg:classifiers":[
        {
            "category":"Shopping",
            "type":"Retail Goods"
        }
    ],
    "sg:phone":"+39 39043476053",
    "sg:postcode":"31018",
    "sg:province":"Treviso",
    "sg:tags":[
        "finished",
        "-",
        "metallic"
    ],
    "wof:name":"Martin Valmore Srl",
    "wof:placetype":"venue"
},
  "geometry": {"coordinates":[12.5078735352,45.9089851379],"type":"Point"}
}