{
  "type": "Feature",
  "properties": {
    "addr:full":"96100 Cassibile Fontane Bianche Cassibile Siracusa 96100",
    "addr:postcode":"96100;96100",
    "iso:country":"IT",
    "sg:address":"96100 Cassibile Fontane Bianche",
    "sg:city":"Cassibile",
    "sg:classifiers":[
        {
            "category":"Health Services",
            "subcategory":"Health Practitioner",
            "type":"Services"
        }
    ],
    "sg:phone":"+39 0931 718036",
    "sg:postcode":"96100",
    "sg:province":"Siracusa",
    "sg:tags":[
        "medici"
    ],
    "wof:name":"Cianci Rosaria",
    "wof:placetype":"venue"
},
  "geometry": {"coordinates":[15.196856,36.976036],"type":"Point"}
}