{
  "type": "Feature",
  "properties": {
    "iso:country":"IT",
    "sg:address":"16014 Ceranesi",
    "sg:city":"Ceranesi",
    "sg:orig_category":"Pubblica Amministrazione",
    "sg:phone":"+39 010 782707",
    "sg:postcode":"16014",
    "sg:province":"Genova",
    "wof:name":"Comunita' Montana =alta Val Polcevera=",
    "wof:placetype":"venue"
},
  "geometry": {"coordinates":[8.8839607239,44.508354187],"type":"Point"}
}