{
  "type": "Feature",
  "properties": {
    "iso:country":"IT",
    "sg:address":"36070 Castelgomberto",
    "sg:city":"Castelgomberto",
    "sg:orig_category":"Caffe' Crudo E Torrefatto",
    "sg:phone":"+39 0445 440506",
    "sg:postcode":"36070",
    "sg:province":"Vicenza",
    "wof:name":"Portorico Srl",
    "wof:placetype":"venue"
},
  "geometry": {"coordinates":[11.617281,45.519444],"type":"Point"}
}