{
  "type": "Feature",
  "properties": {
    "iso:country":"IT",
    "sg:address":"20123 Milano",
    "sg:city":"Milano",
    "sg:orig_category":"Prodotti Alimentari. Shopping",
    "sg:phone":"+39 02 8940 2991",
    "sg:postcode":"20123",
    "sg:province":"Milano",
    "wof:name":"Foscati Giampietro",
    "wof:placetype":"venue"
},
  "geometry": {"coordinates":[9.1770467758,45.4675064087],"type":"Point"}
}