{
  "type": "Feature",
  "properties": {
    "addr:full":"41100 Modena Modena Modena 41100",
    "addr:postcode":"41100;41100",
    "iso:country":"IT",
    "sg:address":"41100 Modena",
    "sg:city":"Modena",
    "sg:orig_category":"Minuterie Metalliche E Ferramenta",
    "sg:phone":"+39 059 351072",
    "sg:postcode":"41100",
    "sg:province":"Modena",
    "sg:website":"http://www.pmontecchi.com",
    "wof:name":"P.m. Di Montecchi Srl",
    "wof:placetype":"venue"
},
  "geometry": {"coordinates":[10.8763799667,44.6370811462],"type":"Point"}
}