{
  "type": "Feature",
  "properties": {
    "addr:full":"Via Sandro Pertini 74027 San Giorgio Jonico Taranto 74027",
    "addr:postcode":"74027;74027",
    "addr:street":"Via Sandro Pertini",
    "iso:country":"IT",
    "sg:address":"Via Sandro Pertini 74027 San Giorgio Jonico",
    "sg:classifiers":[
        {
            "category":"Manufacturing",
            "subcategory":"Glass & Minerals",
            "type":"Manufacturing & Wholesale Goods"
        }
    ],
    "sg:phone":"+39 099 592 1209",
    "sg:postcode":"74027",
    "sg:province":"Taranto",
    "wof:name":"Kristal Cosmo Di Scialpi Francesco Saverio",
    "wof:placetype":"venue"
},
  "geometry": {"coordinates":[8.862255,45.206055],"type":"Point"}
}