{
  "type": "Feature",
  "properties": {
    "iso:country":"IT",
    "sg:address":"Dorf Nr. 117; Renon; 39054",
    "sg:city":"Renon",
    "sg:classifiers":[
        {
            "category":"Banks & Credit Unions",
            "subcategory":"Bank",
            "type":"Services"
        }
    ],
    "sg:phone":"+39 0471 56493",
    "sg:postcode":"39054",
    "sg:province":"Bolzano/Bozen",
    "wof:name":"S\u00fcdtiroler Landessparkasse",
    "wof:placetype":"venue"
},
  "geometry": {"coordinates":[11.440425,46.511906],"type":"Point"}
}