{
  "type": "Feature",
  "properties": {
    "addr:full":"36010 Carre' Vicenza 36010",
    "addr:postcode":"36010;36010",
    "addr:street":"Carre ' Vicenza",
    "iso:country":"IT",
    "sg:address":"36010 Carre'",
    "sg:orig_category":"Forniture Per Attivita' Industriali",
    "sg:phone":"+39 0445 891007",
    "sg:postcode":"36010",
    "sg:province":"Vicenza",
    "wof:name":"Dimax Srl",
    "wof:placetype":"venue"
},
  "geometry": {"coordinates":[11.464427948,45.7365722656],"type":"Point"}
}