{
  "type": "Feature",
  "properties": {
    "iso:country":"IT",
    "sg:address":"10060 Campiglione Fenile",
    "sg:city":"Campiglione",
    "sg:orig_category":"Telecomunicazioni E Telefonia, Impianti, Apparecchi E Servizi",
    "sg:phone":"+39 0121 590293",
    "sg:postcode":"10060",
    "sg:province":"Torino",
    "wof:name":"Airaudo Claudia",
    "wof:placetype":"venue"
},
  "geometry": {"coordinates":[7.324765,44.80267],"type":"Point"}
}