{
  "type": "Feature",
  "properties": {
    "iso:country":"IT",
    "sg:address":"Via E. Fermi 17 42027 Montecchio Emilia",
    "sg:classifiers":[
        {
            "category":"Health Services",
            "subcategory":"Hospital",
            "type":"Services"
        }
    ],
    "sg:phone":"+39 0522 865194",
    "sg:postcode":"42027",
    "sg:province":"Reggio Nell'Emilia",
    "sg:tags":[
        "capsule",
        "cap",
        "bottle"
    ],
    "sg:website":"www.correggi.it",
    "wof:name":"Correggi Cork Italia Srl",
    "wof:placetype":"venue"
},
  "geometry": {"coordinates":[10.47998,44.670715],"type":"Point"}
}