{
  "type": "Feature",
  "properties": {
    "iso:country":"IT",
    "sg:address":"Pontoglio; 25037",
    "sg:city":"Pontoglio",
    "sg:classifiers":[
        {
            "category":"Banks & Credit Unions",
            "subcategory":"Bank",
            "type":"Services"
        }
    ],
    "sg:phone":"+39 030 737001",
    "sg:postcode":"25037",
    "sg:province":"Brescia",
    "wof:name":"Cassa Rurale Ed Artigiana, Di Pontoglio",
    "wof:placetype":"venue"
},
  "geometry": {"coordinates":[9.855311,45.559101],"type":"Point"}
}