{
  "type": "Feature",
  "properties": {
    "addr:full":"22070 Senna Comasco Senna Comasco Como 22070",
    "addr:housenumber":"comasco",
    "addr:postcode":"22070;22070",
    "iso:country":"IT",
    "sg:address":"22070 Senna Comasco",
    "sg:city":"Senna Comasco",
    "sg:orig_category":"Articoli Regalo - Produzione E Ingrosso",
    "sg:phone":"+39 031 460769",
    "sg:postcode":"22070",
    "sg:province":"Como",
    "wof:name":"Mapes Commerciale Snc",
    "wof:placetype":"venue"
},
  "geometry": {"coordinates":[9.105053,45.764191],"type":"Point"}
}