{
  "type": "Feature",
  "properties": {
    "addr:full":"56, Via Albinatico 51019 Ponte Buggianese Ponte Buggianese Pistoia 51019",
    "addr:postcode":"51019;51019",
    "addr:street":"Via Albinatico",
    "iso:country":"IT",
    "sg:address":"56, Via Albinatico 51019 Ponte Buggianese",
    "sg:city":"Ponte Buggianese",
    "sg:classifiers":[
        {
            "category":"Shopping",
            "subcategory":"Crafts & Fabrics",
            "type":"Retail Goods"
        }
    ],
    "sg:phone":"+39 0572 636173",
    "sg:postcode":"51019",
    "sg:province":"Pistoia",
    "sg:tags":[
        "linen"
    ],
    "wof:name":"Lavanderia Lavachiara S.a.s.",
    "wof:placetype":"venue"
},
  "geometry": {"coordinates":[10.761054039,43.8420143127],"type":"Point"}
}