{
  "type": "Feature",
  "properties": {
    "iso:country":"IT",
    "sg:address":"00040 Pomezia",
    "sg:city":"Pomezia",
    "sg:orig_category":"Macchine Ed Impianti Per Edilizia E Lavori Pubblici. Macchine, Strumenti Ed Apparecchi Per Attivita' Industriali",
    "sg:phone":"+39 06 910 7623",
    "sg:postcode":"00040",
    "sg:province":"Roma",
    "wof:name":"Grandi Vetri S.r.l.",
    "wof:placetype":"venue"
},
  "geometry": {"coordinates":[12.515931,41.685719],"type":"Point"}
}