{
  "type": "Feature",
  "properties": {
    "iso:country":"IT",
    "sg:address":"20131 Milano",
    "sg:city":"Milano",
    "sg:orig_category":"Parrucchieri - Forniture",
    "sg:phone":"+39 02 266 5146",
    "sg:postcode":"20131",
    "sg:province":"Milano",
    "wof:name":"Sabbadini Mauro Srl",
    "wof:placetype":"venue"
},
  "geometry": {"coordinates":[9.2280082703,45.4829673767],"type":"Point"}
}