{
  "type": "Feature",
  "properties": {
    "addr:full":"20092 Cinisello Balsamo Cinisello Balsamo Milano 20092",
    "addr:postcode":"20092;20092",
    "iso:country":"IT",
    "sg:address":"20092 Cinisello Balsamo",
    "sg:city":"Cinisello Balsamo",
    "sg:orig_category":"Materiali Edili",
    "sg:phone":"+39 02 617 0217",
    "sg:postcode":"20092",
    "sg:province":"Milano",
    "wof:name":"P.i.a.r. Srl",
    "wof:placetype":"venue"
},
  "geometry": {"coordinates":[9.267994,45.526653],"type":"Point"}
}