{
  "type": "Feature",
  "properties": {
    "addr:full":"54, Via Delle Langhe 12084 Mondovi' Cuneo 12084",
    "addr:postcode":"12084;12084",
    "addr:street":"Via Delle Langhe",
    "iso:country":"IT",
    "sg:address":"54, Via Delle Langhe 12084 Mondovi'",
    "sg:orig_category":"Miscellaneous Products",
    "sg:phone":"+39 39017443451",
    "sg:postcode":"12084",
    "sg:province":"Cuneo",
    "wof:name":"Holz Italia Di F. Bruno E F.lli Sas",
    "wof:placetype":"venue"
},
  "geometry": {"coordinates":[7.5471105576,44.38879776],"type":"Point"}
}