{
  "type": "Feature",
  "properties": {
    "iso:country":"IT",
    "sg:address":"9/11, V. Del Commercio 36065 Mussolente",
    "sg:city":"Mussolente",
    "sg:classifiers":[
        {
            "category":"Shopping",
            "subcategory":"Jewelry",
            "type":"Retail Goods"
        }
    ],
    "sg:phone":"+39 0424 577424",
    "sg:postcode":"36065",
    "sg:province":"Vicenza",
    "sg:tags":[
        "jewellery"
    ],
    "wof:name":"Alangold Creazioni Spa",
    "wof:placetype":"venue"
},
  "geometry": {"coordinates":[11.808536,45.765202],"type":"Point"}
}