{
  "type": "Feature",
  "properties": {
    "iso:country":"IT",
    "sg:address":"38068 Rovereto",
    "sg:city":"Rovereto",
    "sg:orig_category":"Falegnami",
    "sg:phone":"+39 0464 438939",
    "sg:postcode":"38068",
    "sg:province":"Trento",
    "wof:name":"Falegnameria - Lavorazioni Speciali Maraschin Sergio",
    "wof:placetype":"venue"
},
  "geometry": {"coordinates":[11.0357942581,45.8786239624],"type":"Point"}
}