{
  "type": "Feature",
  "properties": {
    "addr:full":"10, Via Oriano 21018 Sesto Calende Sesto Calende Varese 21018",
    "addr:postcode":"21018;21018",
    "addr:street":"Via Oriano",
    "iso:country":"IT",
    "sg:address":"10, Via Oriano 21018 Sesto Calende",
    "sg:city":"Sesto Calende",
    "sg:classifiers":[
        {
            "category":"Shopping",
            "subcategory":"Clothing, Apparel, & Fashions",
            "type":"Retail Goods"
        }
    ],
    "sg:phone":"+39 0331 920425",
    "sg:postcode":"21018",
    "sg:province":"Varese",
    "sg:tags":[
        "clothes"
    ],
    "wof:name":"Essepi 75 Confezioni (s.r.l.)",
    "wof:placetype":"venue"
},
  "geometry": {"coordinates":[8.64995,45.730568],"type":"Point"}
}