{
  "type": "Feature",
  "properties": {
    "addr:full":"21019 Somma Lombardo Somma Lombardo Varese 21019",
    "addr:postcode":"21019;21019",
    "iso:country":"IT",
    "sg:address":"21019 Somma Lombardo",
    "sg:city":"Somma Lombardo",
    "sg:orig_category":"Valvole E Apparecchiature Di Misura. Minuterie Metalliche E Ferramenta. Forniture Per Attivita' Industriali",
    "sg:phone":"+39 0331 988411",
    "sg:postcode":"21019",
    "sg:province":"Varese",
    "wof:name":"Fratelli Tognella Spa",
    "wof:placetype":"venue"
},
  "geometry": {"coordinates":[8.70927,45.673992],"type":"Point"}
}