{
  "type": "Feature",
  "properties": {
    "iso:country":"IT",
    "sg:address":"54033 Carrara",
    "sg:city":"Carrara",
    "sg:orig_category":"Marmo, Pietre Ed Affini",
    "sg:phone":"+39 0585 846300",
    "sg:postcode":"54033",
    "sg:province":"Massa-Carrara",
    "sg:website":"http://www.statuariamarmi.it",
    "wof:name":"Statuaria Marmi Srl",
    "wof:placetype":"venue"
},
  "geometry": {"coordinates":[10.069672,44.054035],"type":"Point"}
}