{
  "type": "Feature",
  "properties": {
    "addr:full":"10078 Venaria Torino 10078",
    "addr:postcode":"10078;10078",
    "iso:country":"IT",
    "sg:address":"10078 Venaria",
    "sg:orig_category":"Cartotecnica E Servizi. Composizione, Stampa E Confezione. Servizi E Lavori Industria Delle Materie Plastiche. Servizi Per Imballaggio E Confezionamento",
    "sg:phone":"+39 011 455 1228",
    "sg:postcode":"10078",
    "sg:province":"Torino",
    "wof:name":"Tensioplast (s.r.l.)",
    "wof:placetype":"venue"
},
  "geometry": {"coordinates":[7.640901,45.112282],"type":"Point"}
}