{
  "type": "Feature",
  "properties": {
    "addr:full":"138, Via De Amicis Edmondo 10093 Collegno Collegno Torino 10093",
    "addr:housenumber":"138",
    "addr:postcode":"10093;10093",
    "addr:street":"Via De Amicis Edmondo",
    "iso:country":"IT",
    "sg:address":"138, Via De Amicis Edmondo 10093 Collegno",
    "sg:city":"Collegno",
    "sg:classifiers":[
        {
            "category":"Manufacturing",
            "subcategory":"Paper Products",
            "type":"Manufacturing & Wholesale Goods"
        }
    ],
    "sg:phone":"+39 011 403 1605",
    "sg:postcode":"10093",
    "sg:province":"Torino",
    "sg:tags":[
        "cardboard"
    ],
    "wof:name":"Cartotecnica Vallesusa (s.r.l.)",
    "wof:placetype":"venue"
},
  "geometry": {"coordinates":[7.5920872688,45.0758132935],"type":"Point"}
}