{
  "type": "Feature",
  "properties": {
    "iso:country":"IT",
    "sg:address":"Via Roma 195 47014 Meldola",
    "sg:city":"Meldola",
    "sg:orig_category":"Furniture, General",
    "sg:phone":"+39 0543 495180",
    "sg:postcode":"47014",
    "sg:province":"Forl\u00ec-Cesena",
    "wof:name":"Mobilificio Ranieri Franco Snc Di Ranieri D.p.r.",
    "wof:placetype":"venue"
},
  "geometry": {"coordinates":[12.1351385117,44.1469802856],"type":"Point"}
}