{
  "type": "Feature",
  "properties": {
    "addr:full":"21047 Saronno Saronno Varese 21047",
    "addr:postcode":"21047;21047",
    "iso:country":"IT",
    "sg:address":"21047 Saronno",
    "sg:city":"Saronno",
    "sg:orig_category":"Prodotti E Manufatti In Materie Plastiche. Forniture Per Edilizia E Lavori Pubblici",
    "sg:phone":"+39 02 960 1462",
    "sg:postcode":"21047",
    "sg:province":"Varese",
    "wof:name":"Saronplast (s.r.l.)",
    "wof:placetype":"venue"
},
  "geometry": {"coordinates":[9.0370101929,45.616394043],"type":"Point"}
}