{
  "type": "Feature",
  "properties": {
    "iso:country":"IT",
    "sg:address":"2, Via Vaccareccia 00040 Pomezia",
    "sg:city":"Pomezia",
    "sg:classifiers":[
        {
            "category":"Shopping",
            "subcategory":"Crafts & Fabrics",
            "type":"Retail Goods"
        }
    ],
    "sg:phone":"+39 06 9160 1072",
    "sg:postcode":"00040",
    "sg:province":"Roma",
    "sg:tags":[
        "linen"
    ],
    "wof:name":"Hotelservice Spa",
    "wof:placetype":"venue"
},
  "geometry": {"coordinates":[12.4724712372,41.6836433411],"type":"Point"}
}