{
  "type": "Feature",
  "properties": {
    "iso:country":"IT",
    "sg:address":"98, Via Colloredo 33037 Pasian Di Prato",
    "sg:city":"Pasian di Prato",
    "sg:classifiers":[
        {
            "category":"Manufacturing",
            "subcategory":"Chemicals & Compounds",
            "type":"Manufacturing & Wholesale Goods"
        }
    ],
    "sg:phone":"+39 39043269480",
    "sg:postcode":"33037",
    "sg:province":"Udine",
    "sg:tags":[
        "chemistry"
    ],
    "wof:name":"Pravisani Dr. Mariano & C. (s.r.l.)",
    "wof:placetype":"venue"
},
  "geometry": {"coordinates":[13.174155,46.051319],"type":"Point"}
}