{
  "type": "Feature",
  "properties": {
    "addr:full":"5, Via Fermi Enrico 10148 Torino Torino Torino 10148",
    "addr:postcode":"10148;10148",
    "addr:street":"Via Fermi Enrico",
    "iso:country":"IT",
    "sg:address":"5, Via Fermi Enrico 10148 Torino",
    "sg:city":"Torino",
    "sg:classifiers":[
        {
            "category":"Manufacturing",
            "subcategory":"Metals",
            "type":"Manufacturing & Wholesale Goods"
        }
    ],
    "sg:phone":"+39 011 226 4901",
    "sg:postcode":"10148",
    "sg:province":"Torino",
    "sg:tags":[
        "metallurgy",
        "metalworking"
    ],
    "wof:name":"Tubauto (s.r.l.)",
    "wof:placetype":"venue"
},
  "geometry": {"coordinates":[7.5750389099,45.017074585],"type":"Point"}
}