{
  "type": "Feature",
  "properties": {
    "addr:full":"10024 Moncalieri Moncalieri Torino 10024",
    "addr:postcode":"10024;10024",
    "iso:country":"IT",
    "sg:address":"10024 Moncalieri",
    "sg:city":"Moncalieri",
    "sg:orig_category":"Agenzie D'affari E Servizi Commerciali. Servizi Per Aziende, Manifestazioni E Supporto Agli Scambi Commerciali. Acqua, Luce, Gas E Societa' Di Esercizio Pubblico",
    "sg:phone":"+39 011 571 4600",
    "sg:postcode":"10024",
    "sg:province":"Torino",
    "wof:name":"Camera Di Commercio Di Torino",
    "wof:placetype":"venue"
},
  "geometry": {"coordinates":[7.687352,44.999268],"type":"Point"}
}