{
  "type": "Feature",
  "properties": {
    "addr:full":"5, Strada Della Grotta 34072 Farra D'isonzo Gorizia 34072",
    "addr:postcode":"34072;34072",
    "addr:street":"Strada Della Grotta",
    "iso:country":"IT",
    "sg:address":"5, Strada Della Grotta 34072 Farra D'isonzo",
    "sg:classifiers":[
        {
            "category":"Farming",
            "subcategory":"Livestock Farm",
            "type":"Manufacturing & Wholesale Goods"
        }
    ],
    "sg:phone":"+39 0481 888445",
    "sg:postcode":"34072",
    "sg:province":"Gorizia",
    "sg:tags":[
        "agriculture"
    ],
    "wof:name":"Aziende Agricole L.bennati Spa",
    "wof:placetype":"venue"
},
  "geometry": {"coordinates":[13.541094,45.905468],"type":"Point"}
}