{
  "type": "Feature",
  "properties": {
    "iso:country":"IT",
    "sg:address":"97100 Ragusa",
    "sg:city":"Ragusa",
    "sg:orig_category":"Tessuti Arredamento, Tende E Tappeti. Forniture Per Edilizia E Lavori Pubblici",
    "sg:phone":"+39 0932 653722",
    "sg:postcode":"97100",
    "sg:province":"Ragusa",
    "sg:website":"http://www.emporiodelmobile.com",
    "wof:name":"Cappuzzello Emanuele",
    "wof:placetype":"venue"
},
  "geometry": {"coordinates":[14.714571,36.901592],"type":"Point"}
}