{
  "type": "Feature",
  "properties": {
    "iso:country":"IT",
    "sg:address":"55, Via Friuli 20031 Cesano Maderno",
    "sg:city":"Cesano Maderno",
    "sg:classifiers":[
        {
            "category":"Shopping",
            "subcategory":"Crafts & Fabrics",
            "type":"Retail Goods"
        }
    ],
    "sg:phone":"+39 036 257 5183",
    "sg:postcode":"20031",
    "sg:province":"Milano",
    "wof:name":"Nuova Rayon Spa",
    "wof:placetype":"venue"
},
  "geometry": {"coordinates":[9.131775856,45.631690979],"type":"Point"}
}