{
  "type": "Feature",
  "properties": {
    "iso:country":"IT",
    "sg:address":"41049 Sassuolo",
    "sg:city":"Sassuolo",
    "sg:orig_category":"Elettrodomestici - Vendita Al Dettaglio",
    "sg:phone":"+39 0536 810255",
    "sg:postcode":"41049",
    "sg:province":"Modena",
    "wof:name":"Casa Della Lampada Di Cuoghi Ermentina & C. Snc",
    "wof:placetype":"venue"
},
  "geometry": {"coordinates":[10.783298,44.536282],"type":"Point"}
}