{
  "type": "Feature",
  "properties": {
    "addr:full":"27, Via Aquileia 21100 Varese Varese Varese 21100",
    "addr:postcode":"21100;21100",
    "addr:street":"Via Aquileia",
    "iso:country":"IT",
    "sg:address":"27, Via Aquileia 21100 Varese",
    "sg:city":"Varese",
    "sg:classifiers":[
        {
            "category":"Shopping",
            "subcategory":"Computers & Home Electronics",
            "type":"Retail Goods"
        }
    ],
    "sg:phone":"+39 0332 330690",
    "sg:postcode":"21100",
    "sg:province":"Varese",
    "sg:tags":[
        "electronic",
        "electrical",
        "equipment"
    ],
    "wof:name":"Dansi Italia Srl",
    "wof:placetype":"venue"
},
  "geometry": {"coordinates":[8.844629,45.827641],"type":"Point"}
}