{
  "type": "Feature",
  "properties": {
    "addr:full":"91022 Castelvetrano Castelvetrano Trapani 91022",
    "addr:postcode":"91022;91022",
    "iso:country":"IT",
    "sg:address":"91022 Castelvetrano",
    "sg:city":"Castelvetrano",
    "sg:orig_category":"Servizi Per Lo Sport E Il Tempo Libero. Alberghi E Strutture Extra Alberghiere",
    "sg:phone":"+39 0924 86011",
    "sg:postcode":"91022",
    "sg:province":"Trapani",
    "wof:name":"Mokambo Beach",
    "wof:placetype":"venue"
},
  "geometry": {"coordinates":[12.80638,37.583103],"type":"Point"}
}