{
  "type": "Feature",
  "properties": {
    "iso:country":"IT",
    "sg:address":"Via Raffaello Sanzio 366 45027 Trecenta",
    "sg:city":"Trecenta",
    "sg:classifiers":[
        {
            "category":"Wholesale",
            "subcategory":"Office Equipment",
            "type":"Manufacturing & Wholesale Goods"
        }
    ],
    "sg:phone":"+39 0425 701181",
    "sg:postcode":"45027",
    "sg:province":"Rovigo",
    "sg:tags":[
        "furniture"
    ],
    "sg:website":"www.mobilferro.net",
    "wof:name":"Mobilferro Srl",
    "wof:placetype":"venue"
},
  "geometry": {"coordinates":[11.44334,45.024353],"type":"Point"}
}