{
  "type": "Feature",
  "properties": {
    "iso:country":"IT",
    "sg:address":"162, Via Giacomo Matteotti 25014 Castenedolo",
    "sg:city":"Castenedolo",
    "sg:classifiers":[
        {
            "category":"Shopping",
            "subcategory":"Computers & Home Electronics",
            "type":"Retail Goods"
        }
    ],
    "sg:phone":"+39 030 213 5811",
    "sg:postcode":"25014",
    "sg:province":"Brescia",
    "sg:tags":[
        "electronic",
        "electrical",
        "equipment"
    ],
    "wof:name":"R.i.b. Srl",
    "wof:placetype":"venue"
},
  "geometry": {"coordinates":[10.304938,45.466812],"type":"Point"}
}