{
  "type": "Feature",
  "properties": {
    "addr:full":"5, V. Fermi 43030 S. Polo Di Torrile Parma 43030",
    "addr:housenumber":"5",
    "addr:postcode":"43030;43030",
    "addr:street":"V. Fermi",
    "iso:country":"IT",
    "sg:address":"5, V. Fermi 43030 S. Polo Di Torrile",
    "sg:classifiers":[
        {
            "category":"Manufacturing",
            "subcategory":"Metals",
            "type":"Manufacturing & Wholesale Goods"
        }
    ],
    "sg:phone":"+39 0521 819352",
    "sg:postcode":"43030",
    "sg:province":"Parma",
    "sg:tags":[
        "metallurgy",
        "metalworking"
    ],
    "sg:website":"http://www.paginegialle.it/terenziani-02",
    "wof:name":"Terenziani Giuseppe & C. Srl",
    "wof:placetype":"venue"
},
  "geometry": {"coordinates":[10.3585796356,44.8959159851],"type":"Point"}
}