{
  "type": "Feature",
  "properties": {
    "iso:country":"IT",
    "sg:address":"20122 Milano",
    "sg:city":"Milano",
    "sg:orig_category":"Servizi Editoriali",
    "sg:phone":"+39 02 781925",
    "sg:postcode":"20122",
    "sg:province":"Milano",
    "wof:name":"Desidera' Giordano",
    "wof:placetype":"venue"
},
  "geometry": {"coordinates":[9.200581,45.465782],"type":"Point"}
}