{
  "type": "Feature",
  "properties": {
    "iso:country":"IT",
    "sg:address":"20040 Cornate D'adda",
    "sg:orig_category":"Tappezzerie E Sellerie Veicoli - Lavorazione E Riparazione",
    "sg:phone":"+39 039 606 0328",
    "sg:postcode":"20040",
    "sg:province":"Milano",
    "sg:website":"http://www.brminterniauto.com",
    "wof:name":"B.r.m. Snc Di Bertini Mario E C.",
    "wof:placetype":"venue"
},
  "geometry": {"coordinates":[9.462363,45.649914],"type":"Point"}
}