{
  "type": "Feature",
  "properties": {
    "addr:full":"Via Pag 21 48100 Ravenna Ravenna Ravenna 48100",
    "addr:housenumber":"21",
    "addr:postcode":"48100;48100",
    "addr:street":"Via Pag",
    "iso:country":"IT",
    "sg:address":"Via Pag 21 48100 Ravenna",
    "sg:city":"Ravenna",
    "sg:classifiers":[
        {
            "category":"Professional",
            "subcategory":"Employment Agencies",
            "type":"Services"
        }
    ],
    "sg:phone":"+39 0544 420041",
    "sg:postcode":"48100",
    "sg:province":"Ravenna",
    "sg:tags":[
        "cargo"
    ],
    "sg:website":"www.tntitaly.it",
    "wof:name":"Tnt Global Express Spa",
    "wof:placetype":"venue"
},
  "geometry": {"coordinates":[12.225,44.363888],"type":"Point"}
}