{
  "type": "Feature",
  "properties": {
    "addr:full":"01010 Civitella Cesi Civitella Cesi Viterbo 01010",
    "addr:postcode":"01010;01010",
    "iso:country":"IT",
    "sg:address":"01010 Civitella Cesi",
    "sg:city":"Civitella Cesi",
    "sg:orig_category":"Servizi Per Aziende, Manifestazioni E Supporto Agli Scambi Commerciali",
    "sg:phone":"+39 0761 415031",
    "sg:postcode":"01010",
    "sg:province":"Viterbo",
    "wof:name":"Antiquitates Srl",
    "wof:placetype":"venue"
},
  "geometry": {"coordinates":[12.018034,42.21936],"type":"Point"}
}