{
  "type": "Feature",
  "properties": {
    "addr:full":"31, Via A.grandi 41033 Concordia Sulla Secchia Concordia sulla Secchia Modena 41033",
    "addr:postcode":"41033;41033",
    "addr:street":"Via A.Grandi",
    "iso:country":"IT",
    "sg:address":"31, Via A.grandi 41033 Concordia Sulla Secchia",
    "sg:city":"Concordia sulla Secchia",
    "sg:classifiers":[
        {
            "category":"Shopping",
            "subcategory":"Computers & Home Electronics",
            "type":"Retail Goods"
        }
    ],
    "sg:phone":"+39 39053555411",
    "sg:postcode":"41033",
    "sg:province":"Modena",
    "sg:tags":[
        "electronic",
        "electrical",
        "equipment"
    ],
    "wof:name":"Elettromeccanica Carra (s.r.l.)",
    "wof:placetype":"venue"
},
  "geometry": {"coordinates":[10.995315,44.907867],"type":"Point"}
}