{
  "type": "Feature",
  "properties": {
    "iso:country":"IT",
    "sg:address":"32, Via Leonardo Da Vinci 35028 Piove Di Sacco",
    "sg:city":"Piove di Sacco",
    "sg:classifiers":[
        {
            "category":"Autos & Motor Vehicles",
            "subcategory":"Automobile Sales",
            "type":"Retail Goods"
        }
    ],
    "sg:phone":"+39 049 971 3911",
    "sg:postcode":"35028",
    "sg:province":"Padova",
    "sg:tags":[
        "equipment",
        "transport"
    ],
    "wof:name":"Cicli Esperia (s.p.a.)",
    "wof:placetype":"venue"
},
  "geometry": {"coordinates":[11.957159,45.354099],"type":"Point"}
}