{
  "type": "Feature",
  "properties": {
    "addr:full":"28891 Cesara Cesara Verbano-Cusio-Ossola 28891",
    "addr:postcode":"28891;28891",
    "iso:country":"IT",
    "sg:address":"28891 Cesara",
    "sg:city":"Cesara",
    "sg:orig_category":"Minuterie Metalliche E Ferramenta",
    "sg:phone":"+39 0323 827133",
    "sg:postcode":"28891",
    "sg:province":"Verbano-Cusio-Ossola",
    "wof:name":"Barbotti F.lli Snc",
    "wof:placetype":"venue"
},
  "geometry": {"coordinates":[8.415895462,45.8454780579],"type":"Point"}
}