{
  "type": "Feature",
  "properties": {
    "addr:full":"10040 Caprie Caprie Torino 10040",
    "addr:housenumber":"10040",
    "addr:postcode":"10040",
    "addr:street":"Caprie Caprie",
    "iso:country":"IT",
    "sg:address":"10040 Caprie",
    "sg:city":"Caprie",
    "sg:orig_category":"Utensili Meccanici E Materiali",
    "sg:phone":"+39 011 964 2207",
    "sg:postcode":"10040",
    "sg:province":"Torino",
    "wof:name":"Icma Spa",
    "wof:placetype":"venue"
},
  "geometry": {"coordinates":[7.31193,45.117466],"type":"Point"}
}