{
  "type": "Feature",
  "properties": {
    "iso:country":"IT",
    "sg:address":"00135 Roma",
    "sg:city":"Roma",
    "sg:orig_category":"Elettronica Professionale E Di Consumo. Automazione E Macchine Per Ufficio. Forniture Per Congressi, Fiere E Manifestazioni",
    "sg:phone":"+39 06 331 0505",
    "sg:postcode":"00135",
    "sg:province":"Roma",
    "wof:name":"Q.u.e.r.c.i.a. Srl",
    "wof:placetype":"venue"
},
  "geometry": {"coordinates":[12.451241,41.952232],"type":"Point"}
}