{
  "type": "Feature",
  "properties": {
    "addr:full":"37011 Bardolino Bardolino Verona 37011",
    "addr:postcode":"37011;37011",
    "iso:country":"IT",
    "sg:address":"37011 Bardolino",
    "sg:city":"Bardolino",
    "sg:orig_category":"Apparecchiature E Sistemi Per Magazzinaggio E Movimentazione",
    "sg:phone":"+39 045 721 0206",
    "sg:postcode":"37011",
    "sg:province":"Verona",
    "wof:name":"Autogru Buniotto",
    "wof:placetype":"venue"
},
  "geometry": {"coordinates":[11.047957,45.429028],"type":"Point"}
}