{
  "type": "Feature",
  "properties": {
    "addr:full":"Via A. Costa, 8/21 - Cadriano 40057 Granarolo Dell'emilia Bologna 40057",
    "addr:housenumber":"8 / 21",
    "addr:postcode":"40057;40057",
    "addr:street":"Via A. Costa",
    "iso:country":"IT",
    "sg:address":"Via A. Costa, 8/21 - Cadriano 40057 Granarolo Dell'emilia",
    "sg:classifiers":[
        {
            "category":"Autos & Motor Vehicles",
            "subcategory":"Auto Supplies",
            "type":"Retail Goods"
        }
    ],
    "sg:phone":"+39 051 765314",
    "sg:postcode":"40057",
    "sg:province":"Bologna",
    "sg:tags":[
        "machine",
        "packing"
    ],
    "wof:name":"Promaut Snc",
    "wof:placetype":"venue"
},
  "geometry": {"coordinates":[11.397236824,44.5524902344],"type":"Point"}
}