{
  "type": "Feature",
  "properties": {
    "addr:full":"22024 Lanzo D'intelvi Como 22024",
    "addr:postcode":"22024;22024",
    "iso:country":"IT",
    "sg:address":"22024 Lanzo D'intelvi",
    "sg:orig_category":"Scuole E Servizi Scolastici. Ospedali E Servizi Sanitari",
    "sg:phone":"+39 031 831113",
    "sg:postcode":"22024",
    "sg:province":"Como",
    "wof:name":"Cooperativa Sociale Varieta'",
    "wof:placetype":"venue"
},
  "geometry": {"coordinates":[9.021194,45.976357],"type":"Point"}
}