{
  "type": "Feature",
  "properties": {
    "addr:full":"50019 Sesto Fiorentino Sesto Fiorentino Firenze 50019",
    "addr:postcode":"50019;50019",
    "iso:country":"IT",
    "sg:address":"50019 Sesto Fiorentino",
    "sg:city":"Sesto Fiorentino",
    "sg:orig_category":"Scuole E Servizi Scolastici. Ospedali E Servizi Sanitari",
    "sg:phone":"+39 055 421 8982",
    "sg:postcode":"50019",
    "sg:province":"Firenze",
    "wof:name":"Dondoli Marcella",
    "wof:placetype":"venue"
},
  "geometry": {"coordinates":[11.197824,43.839077],"type":"Point"}
}