{
  "type": "Feature",
  "properties": {
    "iso:country":"IT",
    "sg:address":"8, Via Adua 20029 Turbigo",
    "sg:city":"Turbigo",
    "sg:classifiers":[
        {
            "category":"Shopping",
            "subcategory":"Clothing, Apparel, & Fashions",
            "type":"Retail Goods"
        }
    ],
    "sg:phone":"+39 0331 899078",
    "sg:postcode":"20029",
    "sg:province":"Milano",
    "sg:tags":[
        "clothes"
    ],
    "wof:name":"Maglificio Mabrat (s.n.c.)",
    "wof:placetype":"venue"
},
  "geometry": {"coordinates":[8.742548,45.530357],"type":"Point"}
}