{
  "type": "Feature",
  "properties": {
    "addr:full":"38030 Rovere'dellaluna Trento 38030",
    "addr:postcode":"38030;38030",
    "addr:street":"Rovere'Dellaluna Trento",
    "iso:country":"IT",
    "sg:address":"38030 Rovere'dellaluna",
    "sg:orig_category":"Prodotti Alimentari",
    "sg:phone":"+39 0461 658211",
    "sg:postcode":"38030",
    "sg:province":"Trento",
    "wof:name":"Trentinalatte Spa",
    "wof:placetype":"venue"
},
  "geometry": {"coordinates":[11.119052887,46.0667381287],"type":"Point"}
}