{
  "type": "Feature",
  "properties": {
    "iso:country":"IT",
    "sg:address":"1, Via Lago Di Levico 36015 Schio",
    "sg:city":"Schio",
    "sg:classifiers":[
        {
            "category":"Shopping",
            "subcategory":"Crafts & Fabrics",
            "type":"Retail Goods"
        }
    ],
    "sg:phone":"+39 0445 575590",
    "sg:postcode":"36015",
    "sg:province":"Vicenza",
    "wof:name":"Zirtex Di Cavion Albano & C. (s.n.c.)",
    "wof:placetype":"venue"
},
  "geometry": {"coordinates":[11.402797699,45.7155036926],"type":"Point"}
}