{
  "type": "Feature",
  "properties": {
    "iso:country":"IT",
    "sg:address":"Corso Umberto I 44; Ribera; 92016",
    "sg:city":"Ribera",
    "sg:classifiers":[
        {
            "category":"Banks & Credit Unions",
            "subcategory":"Bank",
            "type":"Services"
        }
    ],
    "sg:phone":"+39 0925 928111",
    "sg:postcode":"92016",
    "sg:province":"Agrigento",
    "wof:name":"Banco Di Sicilia Spa",
    "wof:placetype":"venue"
},
  "geometry": {"coordinates":[13.267079,37.503136],"type":"Point"}
}