{
  "type": "Feature",
  "properties": {
    "addr:full":"37057 S. Giovanni Lupatoto Verona 37057",
    "addr:housenumber":"37057",
    "addr:postcode":"37057",
    "addr:street":"S. Giovanni Lupatoto",
    "iso:country":"IT",
    "sg:address":"37057 S. Giovanni Lupatoto",
    "sg:orig_category":"Articoli Pulizia. Macchine E Forniture Per Arredamento E Industria Del Legno. Prodotti Chimici Di Base",
    "sg:phone":"+39 045 925 0734",
    "sg:postcode":"37057",
    "sg:province":"Verona",
    "wof:name":"Isover Snc",
    "wof:placetype":"venue"
},
  "geometry": {"coordinates":[11.029703,45.391022],"type":"Point"}
}