{
  "type": "Feature",
  "properties": {
    "iso:country":"IT",
    "sg:address":"10040 Lein\u00ec",
    "sg:orig_category":"Prodotti E Manufatti In Materie Plastiche. Servizi E Lavori Industria Delle Materie Plastiche",
    "sg:phone":"+39 011 998 8733",
    "sg:postcode":"10040",
    "sg:province":"Torino",
    "sg:website":"http://www.verplast.net",
    "wof:name":"Ver Plast Srl",
    "wof:placetype":"venue"
},
  "geometry": {"coordinates":[7.7224230766,45.1769599915],"type":"Point"}
}