{
  "type": "Feature",
  "properties": {
    "iso:country":"IT",
    "sg:address":"46, Via Fallena 03034 Casalvieri",
    "sg:city":"Casalvieri",
    "sg:classifiers":[
        {
            "category":"Shopping",
            "subcategory":"Gifts & Souvenirs",
            "type":"Retail Goods"
        }
    ],
    "sg:phone":"+39 0776 617241",
    "sg:postcode":"03034",
    "sg:province":"Frosinone",
    "wof:name":"Fratelli Direzze Di Direzze Cesidio & C. S.a.s.",
    "wof:placetype":"venue"
},
  "geometry": {"coordinates":[13.351902,41.640137],"type":"Point"}
}