{
  "type": "Feature",
  "properties": {
    "iso:country":"IT",
    "sg:address":"38, Via Guglielmo Marconi 27010 Vellezzo Bellini",
    "sg:city":"Vellezzo Bellini",
    "sg:classifiers":[
        {
            "category":"Real Estate",
            "subcategory":"Surveying",
            "type":"Services"
        }
    ],
    "sg:phone":"+39 0382 926902",
    "sg:postcode":"27010",
    "sg:province":"Pavia",
    "sg:tags":[
        "equipment",
        "material",
        "good",
        "-",
        "handling"
    ],
    "wof:name":"F.b. Automazione S.r.l.",
    "wof:placetype":"venue"
},
  "geometry": {"coordinates":[9.128327,45.252331],"type":"Point"}
}