{
  "type": "Feature",
  "properties": {
    "addr:full":"Via Salvo D' Acquisto 12 42020 Albinea Reggio Nell'Emilia 42020",
    "addr:housenumber":"12",
    "addr:postcode":"42020;42020",
    "addr:street":"Via Salvo D ' Acquisto",
    "iso:country":"IT",
    "sg:address":"Via Salvo D' Acquisto 12 42020 Albinea",
    "sg:classifiers":[
        {
            "category":"Structure",
            "subcategory":"Factory",
            "type":"Public Place"
        }
    ],
    "sg:phone":"+39 0522 885771",
    "sg:postcode":"42020",
    "sg:province":"Reggio Nell'Emilia",
    "sg:tags":[
        "complete",
        "installations"
    ],
    "sg:website":"www.parinisrl.it",
    "wof:name":"Parini Srl",
    "wof:placetype":"venue"
},
  "geometry": {"coordinates":[10.5744447708,44.6228294373],"type":"Point"}
}