{
  "type": "Feature",
  "properties": {
    "iso:country":"IT",
    "sg:address":"31032 Casale Sul Sile",
    "sg:city":"Casale sul Sile",
    "sg:orig_category":"Prodotti E Manufatti In Materie Plastiche",
    "sg:phone":"+39 0422 822842",
    "sg:postcode":"31032",
    "sg:province":"Treviso",
    "sg:website":"http://www.impaspa.com",
    "wof:name":"Impa Spa",
    "wof:placetype":"venue"
},
  "geometry": {"coordinates":[12.3076400757,45.6104507446],"type":"Point"}
}