{
  "type": "Feature",
  "properties": {
    "addr:full":"00121 Lido Di Ostia Roma 00121",
    "addr:postcode":"00121;00121",
    "addr:street":"Di Ostia Roma",
    "iso:country":"IT",
    "sg:address":"00121 Lido Di Ostia",
    "sg:orig_category":"Servizi Per Lo Sport E Il Tempo Libero. Servizi Al Turismo",
    "sg:phone":"+39 06 561 1333",
    "sg:postcode":"00121",
    "sg:province":"Roma",
    "wof:name":"S.t.a. Euro Int.companysrl",
    "wof:placetype":"venue"
},
  "geometry": {"coordinates":[12.275268,41.734253],"type":"Point"}
}