{
  "type": "Feature",
  "properties": {
    "addr:full":"00159 Roma Roma Roma 00159",
    "addr:postcode":"00159;00159",
    "iso:country":"IT",
    "sg:address":"00159 Roma",
    "sg:city":"Roma",
    "sg:orig_category":"Arredo Camera Letto E Complementi",
    "sg:phone":"+39 06 438 4818",
    "sg:postcode":"00159",
    "sg:province":"Roma",
    "wof:name":"Baby Service Srl",
    "wof:placetype":"venue"
},
  "geometry": {"coordinates":[12.54143,41.908474],"type":"Point"}
}