{
  "type": "Feature",
  "properties": {
    "iso:country":"IT",
    "sg:address":"48100 Ravenna",
    "sg:city":"Ravenna",
    "sg:classifiers":[
        {
            "category":"Retail",
            "subcategory":"Storage",
            "type":"Services"
        }
    ],
    "sg:phone":"+39 0544 451555",
    "sg:postcode":"48100",
    "sg:province":"Ravenna",
    "sg:tags":[
        "equipment",
        "handling",
        "system"
    ],
    "wof:name":"Italmet Srl",
    "wof:placetype":"venue"
},
  "geometry": {"coordinates":[12.224458,44.380314],"type":"Point"}
}