{
  "type": "Feature",
  "properties": {
    "iso:country":"IT",
    "sg:address":"38085 Bersone",
    "sg:city":"Bersone",
    "sg:orig_category":"Pubblica Amministrazione",
    "sg:phone":"+39 0465 674252",
    "sg:postcode":"38085",
    "sg:province":"Trento",
    "wof:name":"Vigili Volontari Del Fuoco - Bersone",
    "wof:placetype":"venue"
},
  "geometry": {"coordinates":[10.6342887878,45.941444397],"type":"Point"}
}