{
  "type": "Feature",
  "properties": {
    "iso:country":"IT",
    "sg:address":"20090 Rodano",
    "sg:city":"Rodano",
    "sg:orig_category":"Trasporti E Spedizioni Merci",
    "sg:phone":"+39 02 9532 8598",
    "sg:postcode":"20090",
    "sg:province":"Milano",
    "sg:website":"http://www.columbiatransport.com",
    "wof:name":"Columbia Transport Srl",
    "wof:placetype":"venue"
},
  "geometry": {"coordinates":[9.334831,45.470749],"type":"Point"}
}