{
  "type": "Feature",
  "properties": {
    "iso:country":"IT",
    "sg:address":"20096 Pioltello",
    "sg:city":"Pioltello",
    "sg:orig_category":"Servizi Vari Di Interesse Pubblico",
    "sg:phone":"+39 02 9216 1286",
    "sg:postcode":"20096",
    "sg:province":"Milano",
    "wof:name":"Contestabile Alfonso",
    "wof:placetype":"venue"
},
  "geometry": {"coordinates":[9.329738,45.489082],"type":"Point"}
}