{
  "type": "Feature",
  "properties": {
    "iso:country":"IT",
    "sg:address":"28021 Borgomanero",
    "sg:city":"Borgomanero",
    "sg:orig_category":"Automazione E Macchine Per Ufficio. Arredi Ed Attrezzature Per Attivita' Commerciali Ed Artigianali",
    "sg:phone":"+39 0322 831047",
    "sg:postcode":"28021",
    "sg:province":"Novara",
    "wof:name":"Tg System Snc",
    "wof:placetype":"venue"
},
  "geometry": {"coordinates":[8.449133,45.702957],"type":"Point"}
}