{
  "type": "Feature",
  "properties": {
    "iso:country":"IT",
    "sg:address":"42, Via Montolmo 62014 Corridonia",
    "sg:city":"Corridonia",
    "sg:classifiers":[
        {
            "category":"Personal",
            "subcategory":"Shoe Repair & Shine",
            "type":"Services"
        }
    ],
    "sg:phone":"+39 0733 432355",
    "sg:postcode":"62014",
    "sg:province":"Macerata",
    "sg:tags":[
        "leather"
    ],
    "wof:name":"Rodi S.r.l.",
    "wof:placetype":"venue"
},
  "geometry": {"coordinates":[13.501603,43.254063],"type":"Point"}
}