{
  "type": "Feature",
  "properties": {
    "addr:full":"06012 Citt\u00e0 Di Castello San Secondo Perugia 06012",
    "addr:postcode":"06012;06012",
    "iso:country":"IT",
    "sg:address":"06012 Citt\u00e0 Di Castello",
    "sg:city":"San Secondo",
    "sg:orig_category":"Mobili - Produzione E Ingrosso",
    "sg:phone":"+39 075 857 7005",
    "sg:postcode":"06012",
    "sg:province":"Perugia",
    "wof:name":"Crm Di Alunni & Nesci Snc",
    "wof:placetype":"venue"
},
  "geometry": {"coordinates":[12.2319049835,43.4577865601],"type":"Point"}
}