{
  "type": "Feature",
  "properties": {
    "addr:full":"00155 Roma Roma Roma 00155",
    "addr:postcode":"00155;00155",
    "iso:country":"IT",
    "sg:address":"00155 Roma",
    "sg:city":"Roma",
    "sg:orig_category":"Prodotti Alimentari",
    "sg:phone":"+39 06 407 1093",
    "sg:postcode":"00155",
    "sg:province":"Roma",
    "wof:name":"Sottozero Due S.a.s.",
    "wof:placetype":"venue"
},
  "geometry": {"coordinates":[12.5753717422,41.9123840332],"type":"Point"}
}