{
  "type": "Feature",
  "properties": {
    "addr:full":"22036 Erba Erba Como 22036",
    "addr:postcode":"22036;22036",
    "iso:country":"IT",
    "sg:address":"22036 Erba",
    "sg:city":"Erba",
    "sg:orig_category":"Servizi Editoriali. Shopping",
    "sg:phone":"+39 031 610978",
    "sg:postcode":"22036",
    "sg:province":"Como",
    "sg:website":"http://www.paginegialle.it/erbalibri",
    "wof:name":"Erbalibri",
    "wof:placetype":"venue"
},
  "geometry": {"coordinates":[9.159458,45.791641],"type":"Point"}
}