{
  "type": "Feature",
  "properties": {
    "iso:country":"IT",
    "sg:address":"20010 Boffalora Sopra Ticino",
    "sg:city":"Boffalora sopra Ticino",
    "sg:orig_category":"Carni, Salumi E Pesci",
    "sg:phone":"+39 02 975 4086",
    "sg:postcode":"20010",
    "sg:province":"Milano",
    "wof:name":"Rolla Teresa",
    "wof:placetype":"venue"
},
  "geometry": {"coordinates":[8.831346,45.467083],"type":"Point"}
}