{
  "type": "Feature",
  "properties": {
    "iso:country":"IT",
    "sg:address":"50018 Scandicci",
    "sg:city":"Scandicci",
    "sg:orig_category":"Arredamenti In Stile E D'epoca",
    "sg:phone":"+39 347 002 8431",
    "sg:postcode":"50018",
    "sg:province":"Firenze",
    "wof:name":"Betancourt Rosaida",
    "wof:placetype":"venue"
},
  "geometry": {"coordinates":[11.129361,43.76881],"type":"Point"}
}