{
  "type": "Feature",
  "properties": {
    "addr:full":"35020 Pernumia Pernumia Padova 35020",
    "addr:postcode":"35020;35020",
    "iso:country":"IT",
    "sg:address":"35020 Pernumia",
    "sg:city":"Pernumia",
    "sg:orig_category":"Cosmetici, Prodotti Di Bellezza E Di Igiene",
    "sg:phone":"+39 0429 779330",
    "sg:postcode":"35020",
    "sg:province":"Padova",
    "wof:name":"Farmacia Toniolo Dr. Valeria",
    "wof:placetype":"venue"
},
  "geometry": {"coordinates":[11.870229,45.402748],"type":"Point"}
}