{
  "type": "Feature",
  "properties": {
    "addr:full":"20010 Mesero Mesero Milano 20010",
    "addr:postcode":"20010;20010",
    "iso:country":"IT",
    "sg:address":"20010 Mesero",
    "sg:city":"Mesero",
    "sg:orig_category":"Coperture Edili Impermeabili",
    "sg:phone":"+39 02 978 8220",
    "sg:postcode":"20010",
    "sg:province":"Milano",
    "wof:name":"Asfalti Temporiti Di Temporiti",
    "wof:placetype":"venue"
},
  "geometry": {"coordinates":[8.829379,45.492096],"type":"Point"}
}