{
  "type": "Feature",
  "properties": {
    "addr:full":"20099 Sesto San Giovanni Sesto San Giovanni Milano 20099",
    "addr:postcode":"20099;20099",
    "iso:country":"IT",
    "sg:address":"20099 Sesto San Giovanni",
    "sg:city":"Sesto San Giovanni",
    "sg:orig_category":"Forniture Per Congressi, Fiere E Manifestazioni",
    "sg:phone":"+39 02 2441 2968",
    "sg:postcode":"20099",
    "sg:province":"Milano",
    "sg:website":"http://www.impact.it",
    "wof:name":"Impact Communication Technology Srl",
    "wof:placetype":"venue"
},
  "geometry": {"coordinates":[9.2387695312,45.5479507446],"type":"Point"}
}