{
  "type": "Feature",
  "properties": {
    "iso:country":"IT",
    "sg:address":"46100 Mantova",
    "sg:city":"Mantova",
    "sg:orig_category":"Apparecchiature Ed Attrezzature Meccaniche",
    "sg:phone":"+39 0376 392061",
    "sg:postcode":"46100",
    "sg:province":"Mantova",
    "wof:name":"Hilti Italia Spa",
    "wof:placetype":"venue"
},
  "geometry": {"coordinates":[10.787313,45.177917],"type":"Point"}
}