{
  "type": "Feature",
  "properties": {
    "iso:country":"IT",
    "sg:address":"18019 Vallecrosia",
    "sg:city":"Vallecrosia",
    "sg:orig_category":"Giardinaggio - Macchine Ed Attrezzi",
    "sg:phone":"+39 0184 291397",
    "sg:postcode":"18019",
    "sg:province":"Imperia",
    "wof:name":"Bestagno Giuseppe",
    "wof:placetype":"venue"
},
  "geometry": {"coordinates":[7.639215,43.789829],"type":"Point"}
}