{
  "type": "Feature",
  "properties": {
    "iso:country":"IT",
    "sg:address":"29/a, Frazione S. Margherita 12016 Peveragno",
    "sg:city":"Peveragno",
    "sg:classifiers":[
        {
            "category":"Parking",
            "subcategory":"Lot",
            "type":"Transportation"
        }
    ],
    "sg:phone":"+39 0171 383036",
    "sg:postcode":"12016",
    "sg:province":"Cuneo",
    "sg:tags":[
        "transport",
        "road"
    ],
    "wof:name":"Giraudi Trasporti Di Giraudi Mauro E C. (s.a.s.)",
    "wof:placetype":"venue"
},
  "geometry": {"coordinates":[7.626683,44.351906],"type":"Point"}
}