{
  "type": "Feature",
  "properties": {
    "iso:country":"IT",
    "sg:address":"20144 Milano",
    "sg:city":"Milano",
    "sg:orig_category":"Studi E Consulenze Tecniche E Industriali. Consulenze Tecniche, Amministrative E Perizie. Servizi Ausiliari Di Analisi, Controllo E Ricerca",
    "sg:phone":"+39 02 4895 8115",
    "sg:postcode":"20144",
    "sg:province":"Milano",
    "sg:website":"http://www.paginegialle.it/zooi",
    "wof:name":"Zooi Snc Di Kulhanek Hisam E De Koning Mindert Tjebbo",
    "wof:placetype":"venue"
},
  "geometry": {"coordinates":[9.15175,45.450188],"type":"Point"}
}