{
  "type": "Feature",
  "properties": {
    "addr:full":"Via Cesare Battisti 104 21040 Lozza Lozza Varese 21040",
    "addr:housenumber":"104",
    "addr:postcode":"21040;21040",
    "addr:street":"Via Cesare Battisti",
    "iso:country":"IT",
    "sg:address":"Via Cesare Battisti 104 21040 Lozza",
    "sg:city":"Lozza",
    "sg:classifiers":[
        {
            "category":"Shopping",
            "subcategory":"Mobile Phones",
            "type":"Retail Goods"
        }
    ],
    "sg:phone":"+39 0332 270711",
    "sg:postcode":"21040",
    "sg:province":"Varese",
    "sg:tags":[
        "shop",
        "trailer"
    ],
    "sg:website":"www.minonziospa.it",
    "wof:name":"Carrozzeria Antonio Minonzio Spa",
    "wof:placetype":"venue"
},
  "geometry": {"coordinates":[8.8638381958,45.7816581726],"type":"Point"}
}