{
  "type": "Feature",
  "properties": {
    "iso:country":"IT",
    "sg:address":"44047 Sant'agostino",
    "sg:city":"Dosso",
    "sg:classifiers":[
        {
            "category":"Shopping",
            "subcategory":"Stationery & Office Supplies",
            "type":"Retail Goods"
        }
    ],
    "sg:phone":"+39 0532 848005",
    "sg:postcode":"44047",
    "sg:province":"Ferrara",
    "sg:tags":[
        "activities",
        "commercial",
        "packaging",
        "packing",
        "materials",
        "artisan",
        "supplies"
    ],
    "wof:name":"Manifatture Bonzagni Mb Srl",
    "wof:placetype":"venue"
},
  "geometry": {"coordinates":[11.3814983368,44.7961730957],"type":"Point"}
}