{
  "type": "Feature",
  "properties": {
    "addr:full":"20010 Bareggio Bareggio Milano 20010",
    "addr:postcode":"20010;20010",
    "iso:country":"IT",
    "sg:address":"20010 Bareggio",
    "sg:city":"Bareggio",
    "sg:orig_category":"Macchine, Impianti E Forniture Per Industria Grafica, Cartaria E Cartotecnica. Automazione E Macchine Per Ufficio",
    "sg:phone":"+39 02 9036 1498",
    "sg:postcode":"20010",
    "sg:province":"Milano",
    "wof:name":"Etipoint Sas Di Dallari Antonella & C.",
    "wof:placetype":"venue"
},
  "geometry": {"coordinates":[9.00595,45.485325],"type":"Point"}
}