{
  "type": "Feature",
  "properties": {
    "addr:full":"61018 San Leo San Leo Pesaro E Urbino 61018",
    "addr:housenumber":"61018",
    "addr:postcode":"61018",
    "addr:street":"San",
    "iso:country":"IT",
    "sg:address":"61018 San Leo",
    "sg:city":"San Leo",
    "sg:orig_category":"Manufacturers: Prefabbricati",
    "sg:phone":"+39 0541 923101",
    "sg:postcode":"61018",
    "sg:province":"Pesaro E Urbino",
    "wof:name":"Carpenteria P.m.s.m. Snc",
    "wof:placetype":"venue"
},
  "geometry": {"coordinates":[12.529803,43.633556],"type":"Point"}
}