{
  "type": "Feature",
  "properties": {
    "addr:full":"28100 Novara Novara Novara 28100",
    "addr:postcode":"28100;28100",
    "iso:country":"IT",
    "sg:address":"28100 Novara",
    "sg:city":"Novara",
    "sg:orig_category":"Abbigliamento Esterno, Maglierie E Pelliccerie. Calzature, Pelletterie E Pelli. Sport - Articoli E Forniture",
    "sg:phone":"+39 0321 623776",
    "sg:postcode":"28100",
    "sg:province":"Novara",
    "wof:name":"Caglieris Umberto",
    "wof:placetype":"venue"
},
  "geometry": {"coordinates":[8.627156,45.446835],"type":"Point"}
}