{
  "type": "Feature",
  "properties": {
    "iso:country":"IT",
    "sg:address":"25085 Gavardo",
    "sg:city":"Gavardo",
    "sg:orig_category":"Caldaie - Produzione E Commercio",
    "sg:phone":"+39 036 531264",
    "sg:postcode":"25085",
    "sg:province":"Brescia",
    "wof:name":"Gavardo Officine Meccaniche Srl",
    "wof:placetype":"venue"
},
  "geometry": {"coordinates":[10.380643,45.644794],"type":"Point"}
}