{
  "type": "Feature",
  "properties": {
    "iso:country":"IT",
    "sg:address":"33100 Udine",
    "sg:city":"Udine",
    "sg:orig_category":"Materiali E Componenti Elettrotecnici",
    "sg:phone":"+39 0432 478373",
    "sg:postcode":"33100",
    "sg:province":"Udine",
    "wof:name":"Antenna System Srl",
    "wof:placetype":"venue"
},
  "geometry": {"coordinates":[13.237736,46.001442],"type":"Point"}
}