{
  "type": "Feature",
  "properties": {
    "iso:country":"IT",
    "sg:address":"25040 Esine",
    "sg:city":"Esine",
    "sg:orig_category":"Termotecnica E Riscaldamento, Apparecchiature E Servizi",
    "sg:phone":"+39 036 446060",
    "sg:postcode":"25040",
    "sg:province":"Brescia",
    "wof:name":"Frigotermica Stofler Di Stofler Diego Gian Paolo E C. S.a.s.",
    "wof:placetype":"venue"
},
  "geometry": {"coordinates":[10.251747,45.925724],"type":"Point"}
}