{
  "type": "Feature",
  "properties": {
    "iso:country":"IT",
    "sg:address":"12042 Bra",
    "sg:city":"Bra",
    "sg:orig_category":"Dolciumi E Gelati",
    "sg:phone":"+39 0172 412181",
    "sg:postcode":"12042",
    "sg:province":"Cuneo",
    "wof:name":"Essepi Di Scavino B. & C. Sas",
    "wof:placetype":"venue"
},
  "geometry": {"coordinates":[7.806885,44.714588],"type":"Point"}
}