{
  "type": "Feature",
  "properties": {
    "addr:full":"24054 Calcio Calcio Bergamo 24054",
    "addr:postcode":"24054;24054",
    "iso:country":"IT",
    "sg:address":"24054 Calcio",
    "sg:city":"Calcio",
    "sg:orig_category":"Articoli Per Imballaggio E Confezionamento",
    "sg:phone":"+39 036 396 8117",
    "sg:postcode":"24054",
    "sg:province":"Bergamo",
    "wof:name":"Saccheria Fratelli Manzoli Di Manzoli Giovanni Virginio Snc",
    "wof:placetype":"venue"
},
  "geometry": {"coordinates":[9.846524,45.516724],"type":"Point"}
}