{
  "type": "Feature",
  "properties": {
    "iso:country":"IT",
    "sg:address":"41100 Modena",
    "sg:city":"Modena",
    "sg:orig_category":"Apparecchiature E Sistemi Per Magazzinaggio E Movimentazione",
    "sg:phone":"+39 059 821404",
    "sg:postcode":"41100",
    "sg:province":"Modena",
    "wof:name":"Eurocar Srl",
    "wof:placetype":"venue"
},
  "geometry": {"coordinates":[10.880608,44.655609],"type":"Point"}
}