{
  "type": "Feature",
  "properties": {
    "iso:country":"IT",
    "sg:address":"25020 Pavone Del Mella",
    "sg:city":"Pavone del Mella",
    "sg:orig_category":"Macchine Utensili E Impianti",
    "sg:phone":"+39 030 959 0001",
    "sg:postcode":"25020",
    "sg:province":"Brescia",
    "wof:name":"Rovetta Presse Spa",
    "wof:placetype":"venue"
},
  "geometry": {"coordinates":[10.261707,45.298145],"type":"Point"}
}