{
  "type": "Feature",
  "properties": {
    "iso:country":"IT",
    "sg:address":"00023 Arsoli",
    "sg:city":"Arsoli",
    "sg:orig_category":"Studi E Consulenze Amministrative, Commerciali E Aziendali. Consulenze Tecniche, Amministrative E Perizie. Professionisti - Studi E Servizi Ed Associazioni Di Interesse Aziendale",
    "sg:phone":"+39 0774 921100",
    "sg:postcode":"00023",
    "sg:province":"Roma",
    "wof:name":"Crisci Enrico",
    "wof:placetype":"venue"
},
  "geometry": {"coordinates":[13.015553,42.043144],"type":"Point"}
}