{
  "type": "Feature",
  "properties": {
    "iso:country":"IT",
    "sg:address":"Regione Scarrone 10040 Pralormo",
    "sg:city":"Pralormo",
    "sg:classifiers":[
        {
            "category":"Utilities",
            "subcategory":"Telephone",
            "type":"Services"
        }
    ],
    "sg:phone":"+39 011 948 1635",
    "sg:postcode":"10040",
    "sg:province":"Torino",
    "sg:tags":[
        "telecommunication"
    ],
    "wof:name":"O.c.e.t. (s.p.a.)",
    "wof:placetype":"venue"
},
  "geometry": {"coordinates":[7.897217,44.861629],"type":"Point"}
}