{
  "type": "Feature",
  "properties": {
    "iso:country":"IT",
    "sg:address":"7, Via Praga 41049 Sassuolo",
    "sg:city":"Sassuolo",
    "sg:classifiers":[
        {
            "category":"Utilities",
            "subcategory":"Electric",
            "type":"Services"
        }
    ],
    "sg:phone":"+39 0536 999611",
    "sg:postcode":"41049",
    "sg:province":"Modena",
    "sg:tags":[
        "component",
        "electronic"
    ],
    "wof:name":"B.c.r. (s.r.l.)",
    "wof:placetype":"venue"
},
  "geometry": {"coordinates":[10.786469,44.557625],"type":"Point"}
}