{
  "type": "Feature",
  "properties": {
    "iso:country":"IT",
    "sg:address":"29, Via Merloni 62024 Matelica",
    "sg:city":"Matelica",
    "sg:classifiers":[
        {
            "category":"Farming",
            "subcategory":"Livestock Farm",
            "type":"Manufacturing & Wholesale Goods"
        }
    ],
    "sg:phone":"+39 39073785833",
    "sg:postcode":"62024",
    "sg:province":"Macerata",
    "sg:tags":[
        "agriculture"
    ],
    "wof:name":"Esino Incubazioni S.r.l.",
    "wof:placetype":"venue"
},
  "geometry": {"coordinates":[13.005765,43.271503],"type":"Point"}
}