{
  "type": "Feature",
  "properties": {
    "iso:country":"IT",
    "sg:address":"41058 Vignola",
    "sg:city":"Vignola",
    "sg:orig_category":"Prodotti Chimici Di Base",
    "sg:phone":"+39 059 763143",
    "sg:postcode":"41058",
    "sg:province":"Modena",
    "wof:name":"Alchimia Snc",
    "wof:placetype":"venue"
},
  "geometry": {"coordinates":[10.9924964905,44.4968795776],"type":"Point"}
}