{
  "type": "Feature",
  "properties": {
    "iso:country":"IT",
    "sg:address":"Via Dello Sport 5; Colleferro; 00034",
    "sg:city":"Colleferro",
    "sg:classifiers":[
        {
            "category":"Banks & Credit Unions",
            "subcategory":"Bank",
            "type":"Services"
        }
    ],
    "sg:phone":"+39 06 973264",
    "sg:postcode":"00034",
    "sg:province":"Roma",
    "wof:name":"Banca Di Roma",
    "wof:placetype":"venue"
},
  "geometry": {"coordinates":[13.009234,41.688217],"type":"Point"}
}