{
  "type": "Feature",
  "properties": {
    "addr:full":"10051 Avigliana Avigliana Torino 10051",
    "addr:postcode":"10051;10051",
    "iso:country":"IT",
    "sg:address":"10051 Avigliana",
    "sg:city":"Avigliana",
    "sg:orig_category":"Pulitura E Lucidatura Metalli",
    "sg:phone":"+39 011 934 8625",
    "sg:postcode":"10051",
    "sg:province":"Torino",
    "wof:name":"Tecnolux Di Di Mauro Umberto",
    "wof:placetype":"venue"
},
  "geometry": {"coordinates":[7.3901081085,45.0888710022],"type":"Point"}
}