{
  "type": "Feature",
  "properties": {
    "iso:country":"IT",
    "sg:address":"25, Via Roma 35046 Saletto",
    "sg:city":"Saletto",
    "sg:classifiers":[
        {
            "category":"Shopping",
            "subcategory":"Clothing, Apparel, & Fashions",
            "type":"Retail Goods"
        }
    ],
    "sg:phone":"+39 39042989132",
    "sg:postcode":"35046",
    "sg:province":"Padova",
    "sg:tags":[
        "clothes"
    ],
    "wof:name":"Pantalonificio Padovano Soc. Coop. A R.l.",
    "wof:placetype":"venue"
},
  "geometry": {"coordinates":[11.886561,45.453526],"type":"Point"}
}