{
  "type": "Feature",
  "properties": {
    "iso:country":"IT",
    "sg:address":"82, Via Prati Giovanni 25086 Rezzato",
    "sg:city":"Rezzato",
    "sg:classifiers":[
        {
            "category":"Manufacturing",
            "subcategory":"Metals",
            "type":"Manufacturing & Wholesale Goods"
        }
    ],
    "sg:phone":"+39 030 279 2257",
    "sg:postcode":"25086",
    "sg:province":"Brescia",
    "sg:tags":[
        "metallurgy",
        "metalworking"
    ],
    "wof:name":"Frascio",
    "wof:placetype":"venue"
},
  "geometry": {"coordinates":[10.3021879196,45.5116729736],"type":"Point"}
}