{
  "type": "Feature",
  "properties": {
    "iso:country":"IT",
    "sg:address":"Zona Industriale 62017 Porto Recanati",
    "sg:city":"Porto Recanati",
    "sg:classifiers":[
        {
            "category":"Shopping",
            "subcategory":"Stationery & Office Supplies",
            "type":"Retail Goods"
        }
    ],
    "sg:phone":"+39 071 759 1707",
    "sg:postcode":"62017",
    "sg:province":"Macerata",
    "sg:tags":[
        "professional"
    ],
    "wof:name":"Grottini (s.n.c.)",
    "wof:placetype":"venue"
},
  "geometry": {"coordinates":[13.4562616348,43.3007469177],"type":"Point"}
}