{
  "type": "Feature",
  "properties": {
    "iso:country":"IT",
    "sg:address":"35030 Rubano",
    "sg:city":"Rubano",
    "sg:orig_category":"Recapito Pacchi, Plichi E Lettere - Agenzie",
    "sg:phone":"+39 348 444 7788",
    "sg:postcode":"35030",
    "sg:province":"Padova",
    "wof:name":"Afb Trasporti E Traslochi",
    "wof:placetype":"venue"
},
  "geometry": {"coordinates":[11.786985,45.429173],"type":"Point"}
}