{
  "type": "Feature",
  "properties": {
    "addr:full":"10137 Torino Torino Torino 10137",
    "addr:postcode":"10137;10137",
    "iso:country":"IT",
    "sg:address":"10137 Torino",
    "sg:city":"Torino",
    "sg:classifiers":[
        {
            "category":"Manufacturing",
            "subcategory":"Tools & Machinery",
            "type":"Manufacturing & Wholesale Goods"
        }
    ],
    "sg:phone":"+39 011 300 0333",
    "sg:postcode":"10137",
    "sg:province":"Torino",
    "sg:tags":[
        "machine",
        "system"
    ],
    "sg:website":"http://www.simu.it",
    "wof:name":"Societ\u00c0 Istrumenti Macchine Utensili S.i.m.u. Spa",
    "wof:placetype":"venue"
},
  "geometry": {"coordinates":[7.592778,45.025333],"type":"Point"}
}