{
  "type": "Feature",
  "properties": {
    "addr:full":"00191 Roma Roma Roma 00191",
    "addr:postcode":"00191;00191",
    "iso:country":"IT",
    "sg:address":"00191 Roma",
    "sg:city":"Roma",
    "sg:orig_category":"Agenzie D'affari E Servizi Commerciali. Avvocati, Notai E Servizi Legali. Consulenze Tecniche, Amministrative E Perizie",
    "sg:phone":"+39 06 330871",
    "sg:postcode":"00191",
    "sg:province":"Roma",
    "wof:name":"Deloitte & Touche",
    "wof:placetype":"venue"
},
  "geometry": {"coordinates":[12.469205,41.939419],"type":"Point"}
}