{
  "type": "Feature",
  "properties": {
    "iso:country":"IT",
    "sg:address":"24044 Dalmine",
    "sg:city":"Dalmine",
    "sg:orig_category":"Motori Ed Organi Di Trasmissione",
    "sg:phone":"+39 035 561475",
    "sg:postcode":"24044",
    "sg:province":"Bergamo",
    "sg:website":"http://www.amadeisrl.com",
    "wof:name":"Amadei Srl",
    "wof:placetype":"venue"
},
  "geometry": {"coordinates":[9.6152029037,45.6443786621],"type":"Point"}
}