{
  "type": "Feature",
  "properties": {
    "addr:full":"22070 Cirimido Cirimido Como 22070",
    "addr:postcode":"22070;22070",
    "iso:country":"IT",
    "sg:address":"22070 Cirimido",
    "sg:city":"Cirimido",
    "sg:orig_category":"Pubblicita' - Cartelli, Insegne E Targhe",
    "sg:phone":"+39 031 938102",
    "sg:postcode":"22070",
    "sg:province":"Como",
    "wof:name":"Borghi Franco",
    "wof:placetype":"venue"
},
  "geometry": {"coordinates":[9.0137777328,45.7007980347],"type":"Point"}
}