{
  "type": "Feature",
  "properties": {
    "addr:full":"18017 San Lorenzo Al Mare San Lorenzo al Mare Imperia 18017",
    "addr:housenumber":"18017",
    "addr:postcode":"18017",
    "addr:street":"San;Al",
    "iso:country":"IT",
    "sg:address":"18017 San Lorenzo Al Mare",
    "sg:city":"San Lorenzo al Mare",
    "sg:orig_category":"Imprese Di Costruzioni Civili Ed Industriali",
    "sg:phone":"+39 0183 92083",
    "sg:postcode":"18017",
    "sg:province":"Imperia",
    "wof:name":"Comar S. R. L.",
    "wof:placetype":"venue"
},
  "geometry": {"coordinates":[7.96237,43.856602],"type":"Point"}
}