{
  "type": "Feature",
  "properties": {
    "iso:country":"IT",
    "sg:address":"20124 Milano",
    "sg:city":"Milano",
    "sg:orig_category":"Abbigliamento Esterno, Maglierie E Pelliccerie. Shopping",
    "sg:phone":"+39 02 669 2885",
    "sg:postcode":"20124",
    "sg:province":"Milano",
    "wof:name":"Camiceria Montegrappa S.r.l.",
    "wof:placetype":"venue"
},
  "geometry": {"coordinates":[9.205231,45.481045],"type":"Point"}
}