{
  "type": "Feature",
  "properties": {
    "addr:full":"27058 Voghera Voghera Pavia 27058",
    "addr:postcode":"27058;27058",
    "iso:country":"IT",
    "sg:address":"27058 Voghera",
    "sg:city":"Voghera",
    "sg:orig_category":"Metalli E Leghe",
    "sg:phone":"+39 0383 41575",
    "sg:postcode":"27058",
    "sg:province":"Pavia",
    "sg:website":"http://www.gardella-srl.it",
    "wof:name":"Gardella Srl",
    "wof:placetype":"venue"
},
  "geometry": {"coordinates":[9.0118846893,44.999912262],"type":"Point"}
}