{
  "type": "Feature",
  "properties": {
    "iso:country":"IT",
    "sg:address":"51037 Montale",
    "sg:city":"Montale",
    "sg:orig_category":"Riparazione Dei Mezzi Di Trasporto. Servizi Ausiliari Dei Mezzi Di Trasporto",
    "sg:phone":"+39 0574 675335",
    "sg:postcode":"51037",
    "sg:province":"Pistoia",
    "wof:name":"Mitos Corse",
    "wof:placetype":"venue"
},
  "geometry": {"coordinates":[11.020273,43.95594],"type":"Point"}
}