{
  "type": "Feature",
  "properties": {
    "addr:full":"Borgo Santa Croce 6, 50122 Firenze Firenze Firenze 50122",
    "addr:housenumber":"6",
    "addr:postcode":"50122;50122",
    "addr:street":"Borgo Santa Croce",
    "iso:country":"IT",
    "sg:address":"Borgo Santa Croce 6, 50122 Firenze",
    "sg:city":"Firenze",
    "sg:classifiers":[
        {
            "category":"Banks & Credit Unions",
            "subcategory":"Financial Services",
            "type":"Services"
        }
    ],
    "sg:phone":"+39 39055242914",
    "sg:postcode":"50122",
    "sg:province":"Firenze",
    "sg:tags":[
        "banking",
        "finance",
        "insurance"
    ],
    "wof:name":"Istituto Araldico Coccia",
    "wof:placetype":"venue"
},
  "geometry": {"coordinates":[11.2599554062,43.7679481506],"type":"Point"}
}