{
  "type": "Feature",
  "properties": {
    "addr:full":"Via Europa 24069 Cenate Sotto Cenate Sotto Bergamo 24069",
    "addr:postcode":"24069;24069",
    "addr:street":"Via Europa",
    "iso:country":"IT",
    "sg:address":"Via Europa 24069 Cenate Sotto",
    "sg:city":"Cenate Sotto",
    "sg:classifiers":[
        {
            "category":"Manufacturing",
            "subcategory":"Rubber & Plastics",
            "type":"Manufacturing & Wholesale Goods"
        }
    ],
    "sg:phone":"+39 39035941589",
    "sg:postcode":"24069",
    "sg:province":"Bergamo",
    "wof:name":"Omplast Srl",
    "wof:placetype":"venue"
},
  "geometry": {"coordinates":[9.8193120956,45.6866073608],"type":"Point"}
}