{
  "type": "Feature",
  "properties": {
    "iso:country":"IT",
    "sg:address":"Viale Delle Rimembranze 42; Nonantola; 41015",
    "sg:city":"Nonantola",
    "sg:classifiers":[
        {
            "category":"Banks & Credit Unions",
            "subcategory":"Bank",
            "type":"Services"
        }
    ],
    "sg:phone":"+39 059 549235",
    "sg:postcode":"41015",
    "sg:province":"Modena",
    "wof:name":"Banca Popolare Di Verona",
    "wof:placetype":"venue"
},
  "geometry": {"coordinates":[11.042329,44.676826],"type":"Point"}
}