{
  "type": "Feature",
  "properties": {
    "iso:country":"IT",
    "sg:address":"1, Via Ricetti 10018 Pavone Canavese",
    "sg:city":"Pavone Canavese",
    "sg:classifiers":[
        {
            "category":"Wholesale",
            "subcategory":"Medical Equipment & Supplies",
            "type":"Manufacturing & Wholesale Goods"
        }
    ],
    "sg:phone":"+39 0125 672311",
    "sg:postcode":"10018",
    "sg:province":"Torino",
    "sg:tags":[
        "-",
        "health",
        "instrument"
    ],
    "wof:name":"Medic (s.r.l.)",
    "wof:placetype":"venue"
},
  "geometry": {"coordinates":[7.854978,45.435467],"type":"Point"}
}