{
  "type": "Feature",
  "properties": {
    "iso:country":"IT",
    "sg:address":"09129 Cagliari",
    "sg:city":"Cagliari",
    "sg:orig_category":"Chiese Ed Associazioni Religiose",
    "sg:phone":"+39 070 41266",
    "sg:postcode":"09129",
    "sg:province":"Cagliari",
    "wof:name":"Ente Patrim.chiesa Di Gesu'cristo Dei Santi Ultimi Giorni",
    "wof:placetype":"venue"
},
  "geometry": {"coordinates":[9.130187,39.222652],"type":"Point"}
}