{
  "type": "Feature",
  "properties": {
    "iso:country":"IT",
    "sg:address":"12080 Vicoforte",
    "sg:city":"Vicoforte",
    "sg:orig_category":"Ascensori - Costruzione",
    "sg:phone":"+39 0174 565007",
    "sg:postcode":"12080",
    "sg:province":"Cuneo",
    "sg:website":"http://www.ascensorirossini.it",
    "wof:name":"Ascensori Rossini",
    "wof:placetype":"venue"
},
  "geometry": {"coordinates":[7.812268,44.398773],"type":"Point"}
}