{
  "type": "Feature",
  "properties": {
    "addr:full":"12, Via Amsterdam 24049 Verdellino Bergamo 24049",
    "addr:postcode":"24049;24049",
    "addr:street":"Via Amsterdam",
    "iso:country":"IT",
    "sg:address":"12, Via Amsterdam 24049 Verdellino",
    "sg:classifiers":[
        {
            "category":"Shopping",
            "type":"Retail Goods"
        }
    ],
    "sg:phone":"+39 035 419 1172",
    "sg:postcode":"24049",
    "sg:province":"Bergamo",
    "sg:tags":[
        "finished",
        "-",
        "metallic"
    ],
    "wof:name":"Meyer Europe Srl",
    "wof:placetype":"venue"
},
  "geometry": {"coordinates":[9.6699523926,45.6949043274],"type":"Point"}
}