{
  "type": "Feature",
  "properties": {
    "iso:country":"IT",
    "sg:address":"43/b, Via Di Vittorio Giuseppe 20068 Peschiera Borromeo",
    "sg:city":"Peschiera Borromeo",
    "sg:classifiers":[
        {
            "category":"Professional",
            "subcategory":"Printing & Photocopies",
            "type":"Services"
        }
    ],
    "sg:phone":"+39 39025470776",
    "sg:postcode":"20068",
    "sg:province":"Milano",
    "wof:name":"Orion Grafic (s.r.l.)",
    "wof:placetype":"venue"
},
  "geometry": {"coordinates":[9.2884225845,45.4290733337],"type":"Point"}
}