{
  "type": "Feature",
  "properties": {
    "addr:full":"Kulturhaus 116, 1; Valles; 39037 Bolzano/Bozen 39037",
    "addr:housenumber":"116 1",
    "addr:postcode":"39037;39037",
    "addr:street":"Valles",
    "iso:country":"IT",
    "sg:address":"Kulturhaus 116, 1; Valles; 39037",
    "sg:classifiers":[
        {
            "category":"Banks & Credit Unions",
            "subcategory":"Bank",
            "type":"Services"
        }
    ],
    "sg:phone":"+39 0472 547141",
    "sg:postcode":"39037",
    "sg:province":"Bolzano/Bozen",
    "wof:name":"Banca Popolare Dell'alto Adige",
    "wof:placetype":"venue"
},
  "geometry": {"coordinates":[11.358005,46.496716],"type":"Point"}
}