{
  "type": "Feature",
  "properties": {
    "addr:full":"82020 Fragneto L'abate Benevento 82020",
    "addr:postcode":"82020;82020",
    "iso:country":"IT",
    "sg:address":"82020 Fragneto L'abate",
    "sg:orig_category":"Macchine Utensili E Impianti",
    "sg:phone":"+39 0824 996308",
    "sg:postcode":"82020",
    "sg:province":"Benevento",
    "wof:name":"Metal-cald Snc Di Marrone Raffaele & C.",
    "wof:placetype":"venue"
},
  "geometry": {"coordinates":[14.785282,41.259651],"type":"Point"}
}