{
  "type": "Feature",
  "properties": {
    "iso:country":"IT",
    "sg:address":"6, Via Martini 41037 Mirandola",
    "sg:city":"Mirandola",
    "sg:classifiers":[
        {
            "category":"Wholesale",
            "subcategory":"Medical Equipment & Supplies",
            "type":"Manufacturing & Wholesale Goods"
        }
    ],
    "sg:phone":"+39 39053535233",
    "sg:postcode":"41037",
    "sg:province":"Modena",
    "sg:tags":[
        "-",
        "health",
        "instrument"
    ],
    "wof:name":"M.p.",
    "wof:placetype":"venue"
},
  "geometry": {"coordinates":[10.997725,44.888748],"type":"Point"}
}