{
  "type": "Feature",
  "properties": {
    "addr:full":"50041 Calenzano Calenzano Firenze 50041",
    "addr:postcode":"50041;50041",
    "iso:country":"IT",
    "sg:address":"50041 Calenzano",
    "sg:city":"Calenzano",
    "sg:orig_category":"Serramenti Ed Infissi",
    "sg:phone":"+39 055 882335",
    "sg:postcode":"50041",
    "sg:province":"Firenze",
    "sg:website":"http://www.fabbri.it",
    "wof:name":"Fabbri Antonio & Figli Snc",
    "wof:placetype":"venue"
},
  "geometry": {"coordinates":[11.210319,43.840897],"type":"Point"}
}