{
  "type": "Feature",
  "properties": {
    "iso:country":"IT",
    "sg:address":"03039 Sora",
    "sg:city":"Sora",
    "sg:classifiers":[
        {
            "category":"Education",
            "subcategory":"School",
            "type":"Public Place"
        }
    ],
    "sg:phone":"+39 0776 832160",
    "sg:postcode":"03039",
    "sg:province":"Frosinone",
    "sg:tags":[
        "scuole",
        "informatica",
        "di"
    ],
    "wof:name":"Scuola Brusca Di Gabriele & C. Sas",
    "wof:placetype":"venue"
},
  "geometry": {"coordinates":[13.6138877869,41.7199859619],"type":"Point"}
}