{
  "type": "Feature",
  "properties": {
    "iso:country":"IT",
    "sg:address":"212, Via Sempione 21052 Busto Arsizio",
    "sg:city":"Busto Arsizio",
    "sg:classifiers":[
        {
            "category":"Shopping",
            "subcategory":"Clothing, Apparel, & Fashions",
            "type":"Retail Goods"
        }
    ],
    "sg:phone":"+39 0331 680260",
    "sg:postcode":"21052",
    "sg:province":"Varese",
    "sg:tags":[
        "clothes"
    ],
    "wof:name":"Maglificio Casvit Di Castiglioni V. & C. (s.n.c.)",
    "wof:placetype":"venue"
},
  "geometry": {"coordinates":[8.874477,45.617817],"type":"Point"}
}