{
  "type": "Feature",
  "properties": {
    "iso:country":"IT",
    "sg:address":"Via Dell'industria 57 63023 Fermo",
    "sg:city":"Fermo",
    "sg:orig_category":"Ladies' Shoes",
    "sg:phone":"+39 0734 644111",
    "sg:postcode":"63023",
    "sg:province":"Ascoli Piceno",
    "sg:website":"www.mary.it",
    "wof:name":"Calzaturificio Mary Srl",
    "wof:placetype":"venue"
},
  "geometry": {"coordinates":[13.746622,43.209923],"type":"Point"}
}