{
  "type": "Feature",
  "properties": {
    "iso:country":"IT",
    "sg:address":"26100 Cremona",
    "sg:city":"Cremona",
    "sg:orig_category":"Articoli Medico-sanitari Ed Ortopedici",
    "sg:phone":"+39 0372 26718",
    "sg:postcode":"26100",
    "sg:province":"Cremona",
    "wof:name":"Ottica Cristina",
    "wof:placetype":"venue"
},
  "geometry": {"coordinates":[10.016362,45.142113],"type":"Point"}
}