{
  "type": "Feature",
  "properties": {
    "iso:country":"IT",
    "sg:address":"1, Via Pratobello 13852 Cerreto Castello",
    "sg:city":"Cerreto Castello",
    "sg:classifiers":[
        {
            "category":"Real Estate",
            "subcategory":"Architect",
            "type":"Services"
        }
    ],
    "sg:phone":"+39 015 828 5064",
    "sg:postcode":"13852",
    "sg:province":"Biella",
    "sg:tags":[
        "textile",
        "clothing"
    ],
    "wof:name":"Tessitura Zanello Velato Bianca S.n.c.",
    "wof:placetype":"venue"
},
  "geometry": {"coordinates":[8.161068,45.562366],"type":"Point"}
}