{
  "type": "Feature",
  "properties": {
    "iso:country":"IT",
    "sg:address":"00153 Roma",
    "sg:city":"Roma",
    "sg:orig_category":"Materiali Semilavorati Metallici",
    "sg:phone":"+39 06 581 5041",
    "sg:postcode":"00153",
    "sg:province":"Roma",
    "wof:name":"Tubi Acciaio Srl",
    "wof:placetype":"venue"
},
  "geometry": {"coordinates":[12.468705,41.872906],"type":"Point"}
}