{
  "type": "Feature",
  "properties": {
    "iso:country":"IT",
    "sg:address":"93018 Santa Caterina Villarmosa",
    "sg:city":"Santa Caterina Villarmosa",
    "sg:orig_category":"Termotecnica E Riscaldamento, Apparecchiature E Servizi",
    "sg:phone":"+39 0934 672288",
    "sg:postcode":"93018",
    "sg:province":"Caltanissetta",
    "wof:name":"Idroitalia Sud Srl",
    "wof:placetype":"venue"
},
  "geometry": {"coordinates":[14.035807,37.589329],"type":"Point"}
}