{
  "type": "Feature",
  "properties": {
    "iso:country":"IT",
    "sg:address":"27020 Gardolo",
    "sg:orig_category":"Arredamenti - Vendita Al Dettaglio",
    "sg:phone":"+39 0461 990690",
    "sg:postcode":"27020",
    "sg:province":"Pavia",
    "sg:website":"http://www.casacrea.com",
    "wof:name":"Casacrea",
    "wof:placetype":"venue"
},
  "geometry": {"coordinates":[9.156563,45.185886],"type":"Point"}
}