{
  "type": "Feature",
  "properties": {
    "iso:country":"IT",
    "sg:address":"23, Via Casali 24060 Castelli Calepio",
    "sg:city":"Castelli Calepio",
    "sg:classifiers":[
        {
            "category":"Home & Garden",
            "subcategory":"Home Furnishings",
            "type":"Retail Goods"
        }
    ],
    "sg:phone":"+39 035 442 5460",
    "sg:postcode":"24060",
    "sg:province":"Bergamo",
    "sg:tags":[
        "household"
    ],
    "wof:name":"Effearredi Di Allievi - Fretti & C.(s.r.l.)",
    "wof:placetype":"venue"
},
  "geometry": {"coordinates":[9.923241,45.654659],"type":"Point"}
}