{
  "type": "Feature",
  "properties": {
    "iso:country":"IT",
    "sg:address":"00054 Fiumicino",
    "sg:city":"Fiumicino",
    "sg:orig_category":"Prodotti Alimentari",
    "sg:phone":"+39 06 652 0570",
    "sg:postcode":"00054",
    "sg:province":"Roma",
    "wof:name":"Casa Del Surgelato",
    "wof:placetype":"venue"
},
  "geometry": {"coordinates":[12.2351226807,41.7622261047],"type":"Point"}
}