{
  "type": "Feature",
  "properties": {
    "addr:full":"Via Casilina 81052 Pignataro Maggiore Pignataro Maggiore Caserta 81052",
    "addr:housenumber":"maggiore",
    "addr:postcode":"81052;81052",
    "addr:street":"Via Casilina;Maggiore",
    "iso:country":"IT",
    "sg:address":"Via Casilina 81052 Pignataro Maggiore",
    "sg:city":"Pignataro Maggiore",
    "sg:classifiers":[
        {
            "category":"Shopping",
            "subcategory":"Crafts & Fabrics",
            "type":"Retail Goods"
        }
    ],
    "sg:phone":"+39 0823 871177",
    "sg:postcode":"81052",
    "sg:province":"Caserta",
    "wof:name":"A.s.a. Arte Seta Alois Srl",
    "wof:placetype":"venue"
},
  "geometry": {"coordinates":[14.1042795181,41.2210578918],"type":"Point"}
}