{
  "type": "Feature",
  "properties": {
    "iso:country":"IT",
    "sg:address":"35030 Saccolongo",
    "sg:city":"Saccolongo",
    "sg:orig_category":"Ascensori - Costruzione",
    "sg:phone":"+39 049 801 5338",
    "sg:postcode":"35030",
    "sg:province":"Padova",
    "wof:name":"Vi.m.a. Ascensori Snc Di Visentin Andrea & Alessandro",
    "wof:placetype":"venue"
},
  "geometry": {"coordinates":[11.74714,45.403816],"type":"Point"}
}