{
  "type": "Feature",
  "properties": {
    "iso:country":"IT",
    "sg:address":"25, Via Stelvio 23020 Poggiridenti",
    "sg:city":"Poggiridenti",
    "sg:classifiers":[
        {
            "category":"Professional",
            "subcategory":"Engineering",
            "type":"Services"
        }
    ],
    "sg:phone":"+39 0342 216419",
    "sg:postcode":"23020",
    "sg:province":"Sondrio",
    "sg:tags":[
        "machine",
        "-",
        "mechanical"
    ],
    "wof:name":"So - Fin - A Srl",
    "wof:placetype":"venue"
},
  "geometry": {"coordinates":[9.921701,46.1693],"type":"Point"}
}