{
  "type": "Feature",
  "properties": {
    "iso:country":"IT",
    "sg:address":"41012 Carpi",
    "sg:city":"Carpi",
    "sg:classifiers":[
        {
            "category":"Manufacturing",
            "subcategory":"Tools & Machinery",
            "type":"Manufacturing & Wholesale Goods"
        }
    ],
    "sg:phone":"+39 059 643989",
    "sg:postcode":"41012",
    "sg:province":"Modena",
    "sg:tags":[
        "machining",
        "mechanical"
    ],
    "wof:name":"Evl Torneria Automatica Srl",
    "wof:placetype":"venue"
},
  "geometry": {"coordinates":[10.863265,44.837715],"type":"Point"}
}