{
  "type": "Feature",
  "properties": {
    "iso:country":"IT",
    "sg:address":"Via Del Santuario 54 12045 Fossano",
    "sg:city":"Fossano",
    "sg:classifiers":[
        {
            "category":"Bus Stop",
            "subcategory":"None",
            "type":"Transportation"
        }
    ],
    "sg:phone":"+39 0172 692141",
    "sg:postcode":"12045",
    "sg:province":"Cuneo",
    "sg:tags":[
        "chopping",
        "block"
    ],
    "sg:website":"www.michelefruttero.com",
    "wof:name":"Michele Fruttero & C. Snc",
    "wof:placetype":"venue"
},
  "geometry": {"coordinates":[7.707131,44.566013],"type":"Point"}
}