{
  "type": "Feature",
  "properties": {
    "addr:full":"42100 Reggio Emilia Reggio Nell'Emilia 42100",
    "addr:postcode":"42100;42100",
    "iso:country":"IT",
    "sg:address":"42100 Reggio Emilia",
    "sg:orig_category":"Banche E Servizi Finanziari",
    "sg:phone":"+39 0522 554368",
    "sg:postcode":"42100",
    "sg:province":"Reggio Nell'Emilia",
    "wof:name":"Recognition Express",
    "wof:placetype":"venue"
},
  "geometry": {"coordinates":[10.644044,44.672997],"type":"Point"}
}