{
  "type": "Feature",
  "properties": {
    "iso:country":"IT",
    "sg:address":"70014 Conversano",
    "sg:city":"Conversano",
    "sg:orig_category":"Frigotecnica, Apparecchiature E Servizi. Forniture Alle Strutture Ricettive",
    "sg:phone":"+39 080 495 7159",
    "sg:postcode":"70014",
    "sg:province":"Bari",
    "wof:name":"Norbafrigo",
    "wof:placetype":"venue"
},
  "geometry": {"coordinates":[17.1248207092,40.9660568237],"type":"Point"}
}