{
  "type": "Feature",
  "properties": {
    "addr:full":"7/a, Via Lincoln Abramo 20092 Cinisello Balsamo Cinisello Balsamo Milano 20092",
    "addr:housenumber":"7 / a",
    "addr:postcode":"20092;20092",
    "iso:country":"IT",
    "sg:address":"7/a, Via Lincoln Abramo 20092 Cinisello Balsamo",
    "sg:city":"Cinisello Balsamo",
    "sg:classifiers":[
        {
            "category":"Wholesale",
            "subcategory":"Drugs",
            "type":"Manufacturing & Wholesale Goods"
        }
    ],
    "sg:phone":"+39 02 6604 9189",
    "sg:postcode":"20092",
    "sg:province":"Milano",
    "sg:tags":[
        "chemical",
        "pharmaceutical"
    ],
    "wof:name":"Effik Italia Spa",
    "wof:placetype":"venue"
},
  "geometry": {"coordinates":[9.188141,45.463688],"type":"Point"}
}