{
  "type": "Feature",
  "properties": {
    "iso:country":"IT",
    "sg:address":"Via La Bionda 2 43036 Fidenza",
    "sg:city":"Fidenza",
    "sg:classifiers":[
        {
            "category":"Communications",
            "subcategory":"Television Station",
            "type":"Services"
        }
    ],
    "sg:phone":"+39 0524 84814",
    "sg:postcode":"43036",
    "sg:province":"Parma",
    "sg:tags":[
        "ignition",
        "cable"
    ],
    "sg:website":"www.cavifermi.it",
    "wof:name":"Cavi F.e.r.m.i Srl",
    "wof:placetype":"venue"
},
  "geometry": {"coordinates":[10.329548,44.807865],"type":"Point"}
}