{
  "type": "Feature",
  "properties": {
    "iso:country":"IT",
    "sg:address":"30033 Noale",
    "sg:city":"Noale",
    "sg:orig_category":"Carpenterie Metalliche",
    "sg:phone":"+39 041 580 0829",
    "sg:postcode":"30033",
    "sg:province":"Venezia",
    "wof:name":"Fer Bat",
    "wof:placetype":"venue"
},
  "geometry": {"coordinates":[12.062837,45.560242],"type":"Point"}
}