{
  "type": "Feature",
  "properties": {
    "addr:full":"60016 Marina Di Montemarciano AN",
    "addr:postcode":"60016",
    "addr:street":"An",
    "iso:country":"IT",
    "sg:address":"60016 Marina Di Montemarciano",
    "sg:orig_category":"Ospedali E Servizi Sanitari",
    "sg:phone":"+39 071 919 8119",
    "sg:province":"AN",
    "wof:name":"Galeazzi Olivio",
    "wof:placetype":"venue"
},
  "geometry": {"coordinates":[-87.90406,42.049213],"type":"Point"}
}