{
  "type": "Feature",
  "properties": {
    "addr:full":"Via Venasca 38 12026 Piasco Piasco Cuneo 12026",
    "addr:housenumber":"38",
    "addr:postcode":"12026;12026",
    "addr:street":"Via Venasca",
    "iso:country":"IT",
    "sg:address":"Via Venasca 38 12026 Piasco",
    "sg:city":"Piasco",
    "sg:orig_category":"Non-classified Establishments",
    "sg:phone":"+39 0175 797727",
    "sg:postcode":"12026",
    "sg:province":"Cuneo",
    "wof:name":"Calce Piasco Spa",
    "wof:placetype":"venue"
},
  "geometry": {"coordinates":[7.446938,44.561386],"type":"Point"}
}