{
  "type": "Feature",
  "properties": {
    "iso:country":"IT",
    "sg:address":"60035 Jesi",
    "sg:city":"Jesi",
    "sg:orig_category":"Freni E Frizioni",
    "sg:phone":"+39 0731 53680",
    "sg:postcode":"60035",
    "sg:province":"Ancona",
    "wof:name":"Star Clutch Srl",
    "wof:placetype":"venue"
},
  "geometry": {"coordinates":[13.2543802261,43.5290145874],"type":"Point"}
}