{
  "type": "Feature",
  "properties": {
    "iso:country":"IT",
    "sg:address":"24020 Cene",
    "sg:city":"Cene",
    "sg:classifiers":[
        {
            "category":"Utilities",
            "subcategory":"Mobile Phone",
            "type":"Services"
        }
    ],
    "sg:phone":"+39 035 729191",
    "sg:postcode":"24020",
    "sg:province":"Bergamo",
    "sg:tags":[
        "equipment",
        "telecommunication",
        "systems",
        "telephony"
    ],
    "sg:website":"http://www.gegsrl.com",
    "wof:name":"G.e.g. Srl",
    "wof:placetype":"venue"
},
  "geometry": {"coordinates":[9.567667,45.669537],"type":"Point"}
}