{
  "type": "Feature",
  "properties": {
    "iso:country":"IT",
    "sg:address":"00137 Roma",
    "sg:city":"Roma",
    "sg:orig_category":"Apparecchiature Ed Attrezzature Meccaniche",
    "sg:phone":"+39 06 8713 2565",
    "sg:postcode":"00137",
    "sg:province":"Roma",
    "wof:name":"Linea Investments Srl",
    "wof:placetype":"venue"
},
  "geometry": {"coordinates":[12.545093,41.949482],"type":"Point"}
}