{
  "type": "Feature",
  "properties": {
    "addr:full":"20090 Assago Assago Milano 20090",
    "addr:postcode":"20090;20090",
    "addr:street":"Assago",
    "iso:country":"IT",
    "sg:address":"20090 Assago",
    "sg:city":"Assago",
    "sg:orig_category":"Servizi Per Lo Sport E Il Tempo Libero. Servizi Al Turismo",
    "sg:phone":"+39 02 5751 1224",
    "sg:postcode":"20090",
    "sg:province":"Milano",
    "wof:name":"Funivie Saslong (s.p.a.)",
    "wof:placetype":"venue"
},
  "geometry": {"coordinates":[9.148091,45.403061],"type":"Point"}
}