{
  "type": "Feature",
  "properties": {
    "iso:country":"IT",
    "sg:address":"Via F. Pisani 10; Soverato; 88068",
    "sg:city":"Soverato",
    "sg:classifiers":[
        {
            "category":"Banks & Credit Unions",
            "subcategory":"Bank",
            "type":"Services"
        }
    ],
    "sg:phone":"+39 0967 522365",
    "sg:postcode":"88068",
    "sg:province":"Catanzaro",
    "wof:name":"Banca Nazionale Del Lavoro Spa",
    "wof:placetype":"venue"
},
  "geometry": {"coordinates":[16.549995,38.686096],"type":"Point"}
}