{
  "type": "Feature",
  "properties": {
    "iso:country":"IT",
    "sg:address":"Via Zona Industriale 70015 Noci",
    "sg:city":"Noci",
    "sg:classifiers":[
        {
            "category":"Manufacturing",
            "subcategory":"Tools & Machinery",
            "type":"Manufacturing & Wholesale Goods"
        }
    ],
    "sg:phone":"+39 080 497 7344",
    "sg:postcode":"70015",
    "sg:province":"Bari",
    "sg:tags":[
        "environment",
        "equipment",
        "-"
    ],
    "wof:name":"Putignano Giovanni E Figli (s.r.l.)",
    "wof:placetype":"venue"
},
  "geometry": {"coordinates":[16.869291,41.126053],"type":"Point"}
}