{
  "type": "Feature",
  "properties": {
    "addr:full":"Via Felice Vedani 16 28045 Invorio Invorio Novara 28045",
    "addr:housenumber":"16",
    "addr:postcode":"28045;28045",
    "addr:street":"Via Felice Vedani",
    "iso:country":"IT",
    "sg:address":"Via Felice Vedani 16 28045 Invorio",
    "sg:city":"Invorio",
    "sg:orig_category":"Shower Head Hoses Made Of Metal",
    "sg:phone":"+39 0322 255686",
    "sg:postcode":"28045",
    "sg:province":"Novara",
    "sg:website":"www.ilflessibile.it",
    "wof:name":"Il Flessibile Di Nicastri & C. S.r.l",
    "wof:placetype":"venue"
},
  "geometry": {"coordinates":[8.48894,45.763092],"type":"Point"}
}