{
  "type": "Feature",
  "properties": {
    "addr:full":"16/c, Strada Villa Garibaldi 46027 San Benedetto Po San Benedetto Po Mantova 46027",
    "addr:housenumber":"16 / c strada",
    "addr:postcode":"46027;46027",
    "addr:street":"Villa Garibaldi;Po",
    "iso:country":"IT",
    "sg:address":"16/c, Strada Villa Garibaldi 46027 San Benedetto Po",
    "sg:city":"San Benedetto Po",
    "sg:classifiers":[
        {
            "category":"Manufacturing",
            "subcategory":"Metals",
            "type":"Manufacturing & Wholesale Goods"
        }
    ],
    "sg:phone":"+39 0376 614052",
    "sg:postcode":"46027",
    "sg:province":"Mantova",
    "sg:tags":[
        "metallurgy",
        "metalworking"
    ],
    "wof:name":"Dmw S.r.l.",
    "wof:placetype":"venue"
},
  "geometry": {"coordinates":[10.7976980209,45.1603660583],"type":"Point"}
}