{
  "type": "Feature",
  "properties": {
    "iso:country":"IT",
    "sg:address":"35, Via Meucci Antonio 50041 Calenzano",
    "sg:city":"Calenzano",
    "sg:classifiers":[
        {
            "category":"Wholesale",
            "subcategory":"Medical Equipment & Supplies",
            "type":"Manufacturing & Wholesale Goods"
        }
    ],
    "sg:phone":"+39 055 882 5498",
    "sg:postcode":"50041",
    "sg:province":"Firenze",
    "sg:tags":[
        "-",
        "health",
        "instrument"
    ],
    "wof:name":"Mon E Tex (s.p.a.)",
    "wof:placetype":"venue"
},
  "geometry": {"coordinates":[11.208582,43.837093],"type":"Point"}
}