{
  "type": "Feature",
  "properties": {
    "addr:full":"10, Via Alpini 24059 Urgnano Urgnano Bergamo 24059",
    "addr:postcode":"24059;24059",
    "addr:street":"Via Alpini",
    "iso:country":"IT",
    "sg:address":"10, Via Alpini 24059 Urgnano",
    "sg:city":"Urgnano",
    "sg:classifiers":[
        {
            "category":"Wholesale",
            "subcategory":"Machinery & Supplies",
            "type":"Manufacturing & Wholesale Goods"
        }
    ],
    "sg:phone":"+39 39035897697",
    "sg:postcode":"24059",
    "sg:province":"Bergamo",
    "sg:tags":[
        "equipment",
        "-",
        "instrument",
        "measurement"
    ],
    "wof:name":"Gavazzi (s.r.l.)",
    "wof:placetype":"venue"
},
  "geometry": {"coordinates":[9.669952,45.694904],"type":"Point"}
}