{
  "type": "Feature",
  "properties": {
    "addr:full":"02100 Frosinone Rieti 02100",
    "addr:postcode":"02100;02100",
    "iso:country":"IT",
    "sg:address":"02100 Frosinone",
    "sg:orig_category":"Trattamenti Termici E Superficiali Metalli, Galvanotecnica",
    "sg:phone":"+39 0775 290746",
    "sg:postcode":"02100",
    "sg:province":"Rieti",
    "wof:name":"Gemi Srl",
    "wof:placetype":"venue"
},
  "geometry": {"coordinates":[12.861179,42.403057],"type":"Point"}
}