{
  "type": "Feature",
  "properties": {
    "addr:full":"19, Via Bodoni 20090 Buccinasco Buccinasco Milano 20090",
    "addr:postcode":"20090;20090",
    "addr:street":"Via Bodoni",
    "iso:country":"IT",
    "sg:address":"19, Via Bodoni 20090 Buccinasco",
    "sg:city":"Buccinasco",
    "sg:classifiers":[
        {
            "category":"Shopping",
            "subcategory":"Stationery & Office Supplies",
            "type":"Retail Goods"
        }
    ],
    "sg:phone":"+39 02 4570 8607",
    "sg:postcode":"20090",
    "sg:province":"Milano",
    "sg:tags":[
        "professional"
    ],
    "wof:name":"Addicalco Concessionaria S.r.l.",
    "wof:placetype":"venue"
},
  "geometry": {"coordinates":[9.1164369583,45.4107589722],"type":"Point"}
}