{
  "type": "Feature",
  "properties": {
    "iso:country":"IT",
    "sg:address":"16, Via Badini 40057 Granarolo Dell'emilia",
    "sg:classifiers":[
        {
            "category":"Wholesale",
            "subcategory":"Machinery & Supplies",
            "type":"Manufacturing & Wholesale Goods"
        }
    ],
    "sg:phone":"+39 39051767347",
    "sg:postcode":"40057",
    "sg:province":"Bologna",
    "sg:tags":[
        "equipment",
        "-",
        "instrument",
        "measurement"
    ],
    "wof:name":"Tecnoelettronica",
    "wof:placetype":"venue"
},
  "geometry": {"coordinates":[11.412495,44.533844],"type":"Point"}
}