{
  "type": "Feature",
  "properties": {
    "iso:country":"IT",
    "sg:address":"41043 Formigine",
    "sg:city":"Formigine",
    "sg:orig_category":"Ceramiche E Refrattari - Impianti, Macchine E Materiali",
    "sg:phone":"+39 059 575 0193",
    "sg:postcode":"41043",
    "sg:province":"Modena",
    "wof:name":"P.v.m. Di Vivi Pier Paolo",
    "wof:placetype":"venue"
},
  "geometry": {"coordinates":[10.935829,44.552532],"type":"Point"}
}