{
  "type": "Feature",
  "properties": {
    "addr:full":"61044 Cantiano Cantiano Pesaro E Urbino 61044",
    "addr:postcode":"61044;61044",
    "iso:country":"IT",
    "sg:address":"61044 Cantiano",
    "sg:city":"Cantiano",
    "sg:orig_category":"Macchine, Impianti Ed Attrezzature Per Agricoltura E Zootecnia",
    "sg:phone":"+39 0721 788244",
    "sg:postcode":"61044",
    "sg:province":"Pesaro E Urbino",
    "wof:name":"Candiracci Luigi & C. Snc",
    "wof:placetype":"venue"
},
  "geometry": {"coordinates":[12.623271,43.484905],"type":"Point"}
}