{
  "type": "Feature",
  "properties": {
    "iso:country":"IT",
    "sg:address":"00048 Nettuno",
    "sg:city":"Nettuno",
    "sg:orig_category":"Servizi Vari Di Interesse Pubblico",
    "sg:phone":"+39 06 985 5333",
    "sg:postcode":"00048",
    "sg:province":"Roma",
    "wof:name":"Picone Stefania",
    "wof:placetype":"venue"
},
  "geometry": {"coordinates":[12.5234,42.06303],"type":"Point"}
}