{
  "type": "Feature",
  "properties": {
    "addr:full":"20094 Corsico Corsico Milano 20094",
    "addr:postcode":"20094;20094",
    "iso:country":"IT",
    "sg:address":"20094 Corsico",
    "sg:city":"Corsico",
    "sg:orig_category":"Impianti Elettrici Industriali E Civili - Installazione E Manutenzione",
    "sg:phone":"+39 02 458 5344",
    "sg:postcode":"20094",
    "sg:province":"Milano",
    "sg:website":"http://www.digifiera.com/simir",
    "wof:name":"Simir Srl",
    "wof:placetype":"venue"
},
  "geometry": {"coordinates":[9.104895,45.444565],"type":"Point"}
}