{
  "type": "Feature",
  "properties": {
    "iso:country":"IT",
    "sg:address":"35020 Albignasego",
    "sg:city":"Albignasego",
    "sg:orig_category":"Tempo Libero - Articoli E Forniture. Forniture Per Congressi, Fiere E Manifestazioni. Regalistica Aziendale",
    "sg:phone":"+39 049 880 8066",
    "sg:postcode":"35020",
    "sg:province":"Padova",
    "wof:name":"Flags - Sandona' Antonietta",
    "wof:placetype":"venue"
},
  "geometry": {"coordinates":[11.840024,45.361362],"type":"Point"}
}