{
  "type": "Feature",
  "properties": {
    "iso:country":"IT",
    "sg:address":"20060 Colturano",
    "sg:city":"Colturano",
    "sg:orig_category":"Manufacturers: Prefabbricati",
    "sg:phone":"+39 02 9823 7418",
    "sg:postcode":"20060",
    "sg:province":"Milano",
    "wof:name":"Battistoni Umberto Snc Umberto",
    "wof:placetype":"venue"
},
  "geometry": {"coordinates":[9.336125,45.380199],"type":"Point"}
}