{
  "type": "Feature",
  "properties": {
    "addr:full":"Via Del Bisenzio 216; Vernio; 50048",
    "addr:housenumber":"216",
    "addr:postcode":"50048",
    "addr:street":"Via Del Bisenzio",
    "iso:country":"IT",
    "sg:address":"Via Del Bisenzio 216; Vernio; 50048",
    "sg:classifiers":[
        {
            "category":"Banks & Credit Unions",
            "subcategory":"Bank",
            "type":"Services"
        }
    ],
    "sg:phone":"+39 0574 957006",
    "wof:name":"Cassa Di Risparmio Di Prato Spa",
    "wof:placetype":"venue"
},
  "geometry": {"coordinates":[11.149534,44.043491],"type":"Point"}
}