{
  "type": "Feature",
  "properties": {
    "addr:full":"20146 Milano Milano Milano 20146",
    "addr:postcode":"20146;20146",
    "iso:country":"IT",
    "sg:address":"20146 Milano",
    "sg:city":"Milano",
    "sg:orig_category":"Palificazioni, Fondazioni E Consolidamenti",
    "sg:phone":"+39 02 468897",
    "sg:postcode":"20146",
    "sg:province":"Milano",
    "wof:name":"Co-dia-fon Srl - So.geo Srl",
    "wof:placetype":"venue"
},
  "geometry": {"coordinates":[9.1547050476,45.4596252441],"type":"Point"}
}