{
  "type": "Feature",
  "properties": {
    "iso:country":"IT",
    "sg:address":"41049 Sassuolo",
    "sg:city":"Sassuolo",
    "sg:orig_category":"Prodotti E Manufatti In Gomma",
    "sg:phone":"+39 0536 801765",
    "sg:postcode":"41049",
    "sg:province":"Modena",
    "wof:name":"Beta - Tre (s.n.c.)",
    "wof:placetype":"venue"
},
  "geometry": {"coordinates":[10.7832984924,44.5362815857],"type":"Point"}
}