{
  "type": "Feature",
  "properties": {
    "iso:country":"IT",
    "sg:address":"10, Via Passo Resia 21013 Gallarate",
    "sg:city":"Gallarate",
    "sg:classifiers":[
        {
            "category":"Professional",
            "subcategory":"Printing & Photocopies",
            "type":"Services"
        }
    ],
    "sg:phone":"+39 0331 796083",
    "sg:postcode":"21013",
    "sg:province":"Varese",
    "wof:name":"Moderna (s.r.l.)",
    "wof:placetype":"venue"
},
  "geometry": {"coordinates":[8.8005876541,45.6793365479],"type":"Point"}
}