{
  "type": "Feature",
  "properties": {
    "addr:full":"12, Via Dell' Artigianato 35023 Bagnoli Di Sopra Bagnoli di Sopra Padova 35023",
    "addr:postcode":"35023;35023",
    "addr:street":"Via Dell ' Artigianato",
    "iso:country":"IT",
    "sg:address":"12, Via Dell' Artigianato 35023 Bagnoli Di Sopra",
    "sg:city":"Bagnoli di Sopra",
    "sg:classifiers":[
        {
            "category":"Shopping",
            "subcategory":"Clothing, Apparel, & Fashions",
            "type":"Retail Goods"
        }
    ],
    "sg:phone":"+39 049 953 5157",
    "sg:postcode":"35023",
    "sg:province":"Padova",
    "sg:tags":[
        "clothes"
    ],
    "wof:name":"Confezioni Lara (s.n.c.)",
    "wof:placetype":"venue"
},
  "geometry": {"coordinates":[11.894059,45.199451],"type":"Point"}
}