{
  "type": "Feature",
  "properties": {
    "addr:full":"03030 Broccostella Broccostella Frosinone 03030",
    "addr:postcode":"03030;03030",
    "iso:country":"IT",
    "sg:address":"03030 Broccostella",
    "sg:city":"Broccostella",
    "sg:orig_category":"Mobili Per Ufficio",
    "sg:phone":"+39 0776 8961",
    "sg:postcode":"03030",
    "sg:province":"Frosinone",
    "sg:website":"http://www.gruppo-francobruno.it",
    "wof:name":"I.c.a.m. Brunosteel Spa",
    "wof:placetype":"venue"
},
  "geometry": {"coordinates":[13.6359825134,41.7017936707],"type":"Point"}
}