{
  "type": "Feature",
  "properties": {
    "iso:country":"IT",
    "sg:address":"16036 Recco",
    "sg:city":"Recco",
    "sg:orig_category":"Ombrelli Ed Ombrelloni",
    "sg:phone":"+39 0185 722777",
    "sg:postcode":"16036",
    "sg:province":"Genova",
    "wof:name":"Capurro Valentino",
    "wof:placetype":"venue"
},
  "geometry": {"coordinates":[9.15115,44.366539],"type":"Point"}
}