{
  "type": "Feature",
  "properties": {
    "iso:country":"IT",
    "sg:address":"83013 Mercogliano",
    "sg:city":"Mercogliano",
    "sg:orig_category":"Apparecchiature E Sistemi Per Magazzinaggio E Movimentazione",
    "sg:phone":"+39 0825 682556",
    "sg:postcode":"83013",
    "sg:province":"Avellino",
    "wof:name":"Mannesmann Dematic Spa",
    "wof:placetype":"venue"
},
  "geometry": {"coordinates":[14.75209,40.907299],"type":"Point"}
}