{
  "type": "Feature",
  "properties": {
    "iso:country":"IT",
    "sg:address":"37062 Verona",
    "sg:city":"Dossobuono",
    "sg:orig_category":"Avvocati, Notai E Servizi Legali. Consulenze Tecniche, Amministrative E Perizie",
    "sg:phone":"+39 045 860 0651",
    "sg:postcode":"37062",
    "sg:province":"Verona",
    "wof:name":"Sib Spa",
    "wof:placetype":"venue"
},
  "geometry": {"coordinates":[10.913811,45.396229],"type":"Point"}
}