{
  "type": "Feature",
  "properties": {
    "addr:full":"14050 San Marzano Oliveto San Marzano Oliveto Asti 14050",
    "addr:housenumber":"14050;marzano oliveto",
    "addr:postcode":"marzano oliveto;14050",
    "addr:street":"San",
    "iso:country":"IT",
    "sg:address":"14050 San Marzano Oliveto",
    "sg:city":"San Marzano Oliveto",
    "sg:orig_category":"Legno E Semilavorati. Manufatti Edili E Prefabbricati",
    "sg:phone":"+39 0141 856636",
    "sg:postcode":"14050",
    "sg:province":"Asti",
    "wof:name":"Agritema (s.r.l.)",
    "wof:placetype":"venue"
},
  "geometry": {"coordinates":[8.295921,44.754288],"type":"Point"}
}