{
  "type": "Feature",
  "properties": {
    "iso:country":"IT",
    "sg:address":"Via Campagna 20 31020 San Polo Di Piave",
    "sg:city":"San Polo di Piave",
    "sg:classifiers":[
        {
            "category":"Home & Garden",
            "subcategory":"Carpets & Floor Coverings",
            "type":"Retail Goods"
        }
    ],
    "sg:phone":"+39 0422 856327",
    "sg:postcode":"31020",
    "sg:province":"Treviso",
    "sg:tags":[
        "wooden",
        "flooring"
    ],
    "sg:website":"www.colema.it",
    "wof:name":"Colema - S.r.l.",
    "wof:placetype":"venue"
},
  "geometry": {"coordinates":[12.383198,45.799229],"type":"Point"}
}