{
  "type": "Feature",
  "properties": {
    "iso:country":"IT",
    "sg:address":"00167 Roma",
    "sg:city":"Roma",
    "sg:orig_category":"Termotecnica E Riscaldamento, Apparecchiature E Servizi",
    "sg:phone":"+39 06 629 1124",
    "sg:postcode":"00167",
    "sg:province":"Roma",
    "wof:name":"Fa.be. Impianti Snc",
    "wof:placetype":"venue"
},
  "geometry": {"coordinates":[12.420506,41.907547],"type":"Point"}
}