{
  "type": "Feature",
  "properties": {
    "iso:country":"IT",
    "sg:address":"Via Milano 20 21046 Malnate",
    "sg:city":"Malnate",
    "sg:classifiers":[
        {
            "category":"Utilities",
            "subcategory":"Water",
            "type":"Services"
        }
    ],
    "sg:phone":"+39 0332 426481",
    "sg:postcode":"21046",
    "sg:province":"Varese",
    "sg:tags":[
        "sew-on",
        "badge"
    ],
    "sg:website":"www.tecnicoll.it",
    "wof:name":"Tecni-coll Srl",
    "wof:placetype":"venue"
},
  "geometry": {"coordinates":[8.884444,45.787838],"type":"Point"}
}