{
  "type": "Feature",
  "properties": {
    "addr:full":"50041 Calenzano Calenzano Firenze 50041",
    "addr:postcode":"50041;50041",
    "iso:country":"IT",
    "sg:address":"50041 Calenzano",
    "sg:city":"Calenzano",
    "sg:orig_category":"Accessori Dei Mezzi Di Trasporto",
    "sg:phone":"+39 055 882 6415",
    "sg:postcode":"50041",
    "sg:province":"Firenze",
    "wof:name":"Bi.en S.r.l",
    "wof:placetype":"venue"
},
  "geometry": {"coordinates":[11.290806,43.759647],"type":"Point"}
}