{
  "type": "Feature",
  "properties": {
    "addr:full":"00153 Roma Roma Roma 00153",
    "addr:postcode":"00153;00153",
    "iso:country":"IT",
    "sg:address":"00153 Roma",
    "sg:city":"Roma",
    "sg:orig_category":"Forniture Per Uffici. Servizi Vari Di Interesse Pubblico",
    "sg:phone":"+39 06 585501",
    "sg:postcode":"00153",
    "sg:province":"Roma",
    "sg:website":"http://www.tabaccai.it/fit-html",
    "wof:name":"Federazione Italiana Tabaccai",
    "wof:placetype":"venue"
},
  "geometry": {"coordinates":[12.4428501129,41.8432884216],"type":"Point"}
}