{
  "type": "Feature",
  "properties": {
    "addr:full":"20129 Milano Milano Milano 20129",
    "addr:postcode":"20129;20129",
    "iso:country":"IT",
    "sg:address":"20129 Milano",
    "sg:city":"Milano",
    "sg:classifiers":[
        {
            "category":"Professional",
            "subcategory":"Management & Consulting",
            "type":"Services"
        }
    ],
    "sg:phone":"+39 0273931",
    "sg:postcode":"20129",
    "sg:province":"Milano",
    "sg:tags":[
        "business",
        "technical",
        "consultant",
        "administration",
        "consultancies",
        "administrative",
        "appraiser"
    ],
    "wof:name":"Sgs Societe Generale De Surveillance Italia Holding Spa",
    "wof:placetype":"venue"
},
  "geometry": {"coordinates":[9.212657,45.472752],"type":"Point"}
}