{
  "type": "Feature",
  "properties": {
    "iso:country":"IT",
    "sg:address":"51017 Pescia",
    "sg:city":"Pescia",
    "sg:orig_category":"Impiantistica E Prodotti Tecnologici Per Edilizia. Climatizzazione E Condizionamento, Apparecchiature E Servizi",
    "sg:phone":"+39 0572 453437",
    "sg:postcode":"51017",
    "sg:province":"Pistoia",
    "wof:name":"Castellare Impianti Snc",
    "wof:placetype":"venue"
},
  "geometry": {"coordinates":[10.967526,43.897701],"type":"Point"}
}