{
  "type": "Feature",
  "properties": {
    "iso:country":"IT",
    "sg:address":"Sda Di Sabbione 91/a 05100 Terni",
    "sg:city":"Terni",
    "sg:orig_category":"Pipes For Flue Gas Desulphurisation Plants",
    "sg:phone":"+39 0744 8081",
    "sg:postcode":"05100",
    "sg:province":"Terni",
    "sg:website":"www.tubiterni.it",
    "wof:name":"Tubificio Di Terni Srl",
    "wof:placetype":"venue"
},
  "geometry": {"coordinates":[12.6251974106,42.5723075867],"type":"Point"}
}