{
  "type": "Feature",
  "properties": {
    "iso:country":"IT",
    "sg:address":"80014 Giugliano In Campania",
    "sg:city":"Giugliano in Campania",
    "sg:orig_category":"Filati E Materie Prime Tessili",
    "sg:phone":"+39 081 330 2609",
    "sg:postcode":"80014",
    "sg:province":"Napoli",
    "wof:name":"Musmanno Maria",
    "wof:placetype":"venue"
},
  "geometry": {"coordinates":[14.2142391205,40.942565918],"type":"Point"}
}