{
  "type": "Feature",
  "properties": {
    "addr:full":"00053 Civitavecchia Civitavecchia Roma 00053",
    "addr:postcode":"00053;roma 00053",
    "iso:country":"IT",
    "sg:address":"00053 Civitavecchia",
    "sg:city":"Civitavecchia",
    "sg:orig_category":"Lubrificanti - Produzione E Commercio",
    "sg:phone":"+39 0766 21938",
    "sg:postcode":"00053",
    "sg:province":"Roma",
    "wof:name":"So.com.ci Srl",
    "wof:placetype":"venue"
},
  "geometry": {"coordinates":[12.491863,41.87743],"type":"Point"}
}