{
  "type": "Feature",
  "properties": {
    "iso:country":"IT",
    "sg:address":"10124 Torino",
    "sg:city":"Torino",
    "sg:orig_category":"Servizi E Lavori Per Arredamento E Industria Del Legno. Arte Ed Artigianato Artistico",
    "sg:phone":"+39 011 817 2251",
    "sg:postcode":"10124",
    "sg:province":"Torino",
    "wof:name":"Ciocchetti Clemente",
    "wof:placetype":"venue"
},
  "geometry": {"coordinates":[7.700215,45.070175],"type":"Point"}
}