{
  "type": "Feature",
  "properties": {
    "iso:country":"IT",
    "sg:address":"Via Cantu 1; Milan; 20123",
    "sg:classifiers":[
        {
            "category":"Shopping",
            "subcategory":"Computers & Home Electronics",
            "type":"Retail Goods"
        }
    ],
    "sg:phone":"+39 39028690661",
    "sg:postcode":"20123",
    "sg:province":"Milano",
    "sg:tags":[
        "chamber",
        "commerce"
    ],
    "sg:website":"www.amcham.it",
    "wof:name":"American Chamber Of Commerce In Italy",
    "wof:placetype":"venue"
},
  "geometry": {"coordinates":[9.186906,45.464367],"type":"Point"}
}