{
  "type": "Feature",
  "properties": {
    "iso:country":"IT",
    "sg:address":"Via Cairoli 9 07012 Bonorva",
    "sg:city":"Bonorva",
    "sg:classifiers":[
        {
            "category":"Food & Beverages",
            "subcategory":"Cheese",
            "type":"Retail Goods"
        }
    ],
    "sg:phone":"+39 079 867756",
    "sg:postcode":"07012",
    "sg:province":"Sassari",
    "wof:name":"Latteria Sociale Coopeativa Di Bonorva Arl",
    "wof:placetype":"venue"
},
  "geometry": {"coordinates":[8.558469,40.727165],"type":"Point"}
}