{
  "type": "Feature",
  "properties": {
    "iso:country":"IT",
    "sg:address":"Via Delle Serre N. 54, 88060 Santa Caterina, Cz",
    "sg:classifiers":[
        {
            "category":"Banks & Credit Unions",
            "subcategory":"Bank",
            "type":"Services"
        }
    ],
    "sg:postcode":"88060",
    "sg:province":"Catanzaro",
    "wof:name":"Banca Di Credito Cooperativo Jonica Scrl",
    "wof:placetype":"venue"
},
  "geometry": {"coordinates":[16.587679,38.910599],"type":"Point"}
}