{
  "type": "Feature",
  "properties": {
    "iso:country":"IT",
    "sg:address":"52028 Terranuova Bracciolini",
    "sg:city":"Terranuova Bracciolini",
    "sg:orig_category":"Animali Domestici - Allevamento E Addestramento",
    "sg:phone":"+39 055 914 9279",
    "sg:postcode":"52028",
    "sg:province":"Arezzo",
    "wof:name":"Lucky Animals Sas",
    "wof:placetype":"venue"
},
  "geometry": {"coordinates":[11.542338,43.603733],"type":"Point"}
}