{
  "type": "Feature",
  "properties": {
    "iso:country":"IT",
    "sg:address":"36, Via Guidini 31059 Zero Branco",
    "sg:city":"Zero Branco",
    "sg:classifiers":[
        {
            "category":"Real Estate",
            "subcategory":"Surveying",
            "type":"Services"
        }
    ],
    "sg:phone":"+39 0422 485697",
    "sg:postcode":"31059",
    "sg:province":"Treviso",
    "sg:tags":[
        "equipment",
        "material",
        "good",
        "-",
        "handling"
    ],
    "wof:name":"Imballaggi Bortolato Di Bortolato Antonio & C. (s.n.c.)",
    "wof:placetype":"venue"
},
  "geometry": {"coordinates":[12.172767,45.609818],"type":"Point"}
}