{
  "type": "Feature",
  "properties": {
    "addr:full":"30026 Portogruaro Portogruaro Venezia 30026",
    "addr:postcode":"30026;30026",
    "iso:country":"IT",
    "sg:address":"30026 Portogruaro",
    "sg:city":"Portogruaro",
    "sg:classifiers":[
        {
            "category":"Manufacturing",
            "subcategory":"Metals",
            "type":"Manufacturing & Wholesale Goods"
        }
    ],
    "sg:phone":"+39 0421 760038",
    "sg:postcode":"30026",
    "sg:province":"Venezia",
    "sg:tags":[
        "forming",
        "working",
        "welding"
    ],
    "wof:name":"Faid Anticorrosione Srl",
    "wof:placetype":"venue"
},
  "geometry": {"coordinates":[12.8150873184,45.7780647278],"type":"Point"}
}