{
  "type": "Feature",
  "properties": {
    "iso:country":"IT",
    "sg:address":"20030 Senago",
    "sg:city":"Senago",
    "sg:orig_category":"Servizi E Lavori Per Industria Alimentare E Bevande",
    "sg:phone":"+39 02 998 8232",
    "sg:postcode":"20030",
    "sg:province":"Milano",
    "wof:name":"Cooperativa La Popolare",
    "wof:placetype":"venue"
},
  "geometry": {"coordinates":[9.118519,45.577168],"type":"Point"}
}