{
  "type": "Feature",
  "properties": {
    "iso:country":"IT",
    "sg:address":"20122 Milano",
    "sg:city":"Milano",
    "sg:orig_category":"Servizi Editoriali",
    "sg:phone":"+39 02 546 9531",
    "sg:postcode":"20122",
    "sg:province":"Milano",
    "wof:name":"Carbone Piero",
    "wof:placetype":"venue"
},
  "geometry": {"coordinates":[9.201881,45.462383],"type":"Point"}
}