{
  "type": "Feature",
  "properties": {
    "iso:country":"IT",
    "sg:address":"41, Via Luxenburg Rosa 51037 Montale",
    "sg:city":"Montale",
    "sg:classifiers":[
        {
            "category":"Banks & Credit Unions",
            "subcategory":"Investment Brokerage",
            "type":"Services"
        }
    ],
    "sg:phone":"+39 0573 959480",
    "sg:postcode":"51037",
    "sg:province":"Pistoia",
    "sg:tags":[
        "-",
        "transport",
        "related"
    ],
    "wof:name":"Carlo Righetti Srl",
    "wof:placetype":"venue"
},
  "geometry": {"coordinates":[10.918524,43.932156],"type":"Point"}
}