{
  "type": "Feature",
  "properties": {
    "addr:full":"Via Nuova, 27 - Cadriano 40057 Granarolo Dell'emilia Bologna 40057",
    "addr:housenumber":"27",
    "addr:postcode":"40057;40057",
    "addr:street":"Via Nuova",
    "iso:country":"IT",
    "sg:address":"Via Nuova, 27 - Cadriano 40057 Granarolo Dell'emilia",
    "sg:classifiers":[
        {
            "category":"Banks & Credit Unions",
            "subcategory":"Investment Brokerage",
            "type":"Services"
        }
    ],
    "sg:phone":"+39 051 765321",
    "sg:postcode":"40057",
    "sg:province":"Bologna",
    "sg:tags":[
        "bag",
        "carrier",
        "plastic"
    ],
    "wof:name":"Le Solim Srl",
    "wof:placetype":"venue"
},
  "geometry": {"coordinates":[11.39115,44.549118],"type":"Point"}
}