{
  "type": "Feature",
  "properties": {
    "iso:country":"IT",
    "sg:address":"Localita' Capo D'orso 07020 Palau",
    "sg:city":"Palau",
    "sg:classifiers":[
        {
            "category":"Travel",
            "subcategory":"Travel Agent",
            "type":"Entertainment"
        }
    ],
    "sg:phone":"+39 0789 702155",
    "sg:postcode":"07020",
    "sg:province":"Olbia-Tempio",
    "sg:tags":[
        "business"
    ],
    "wof:name":"Campeggio Capo D'orso",
    "wof:placetype":"venue"
},
  "geometry": {"coordinates":[9.417815,41.169075],"type":"Point"}
}