{
  "type": "Feature",
  "properties": {
    "iso:country":"IT",
    "sg:address":"35020 Legnaro",
    "sg:city":"Legnaro",
    "sg:orig_category":"Raccordi Per Tubi",
    "sg:phone":"+39 049 790922",
    "sg:postcode":"35020",
    "sg:province":"Padova",
    "wof:name":"O.m.l. Srl",
    "wof:placetype":"venue"
},
  "geometry": {"coordinates":[11.960094,45.35276],"type":"Point"}
}