{
  "type": "Feature",
  "properties": {
    "addr:full":"521, V. Tiburtina 00159 Roma Roma Roma 00159",
    "addr:housenumber":"521",
    "addr:postcode":"00159;00159",
    "addr:street":"V. Tiburtina",
    "iso:country":"IT",
    "sg:address":"521, V. Tiburtina 00159 Roma",
    "sg:city":"Roma",
    "sg:classifiers":[
        {
            "category":"Communications",
            "subcategory":"Newspaper",
            "type":"Services"
        }
    ],
    "sg:phone":"+39 39064370010",
    "sg:postcode":"00159",
    "sg:province":"Roma",
    "sg:tags":[
        "advertising"
    ],
    "sg:website":"http://www.leonirossi.com",
    "wof:name":"Leonirossi Srl",
    "wof:placetype":"venue"
},
  "geometry": {"coordinates":[12.541134,41.908691],"type":"Point"}
}