{
  "type": "Feature",
  "properties": {
    "addr:full":"35015 Galliera Veneta Galliera Veneta Padova 35015",
    "addr:postcode":"35015;35015",
    "iso:country":"IT",
    "sg:address":"35015 Galliera Veneta",
    "sg:city":"Galliera Veneta",
    "sg:orig_category":"Cancelli, Porte E Portoni Automatici E Telecomandati",
    "sg:phone":"+39 049 596 5097",
    "sg:postcode":"35015",
    "sg:province":"Padova",
    "wof:name":"Sicc Srl",
    "wof:placetype":"venue"
},
  "geometry": {"coordinates":[11.815034,45.673798],"type":"Point"}
}