{
  "type": "Feature",
  "properties": {
    "iso:country":"IT",
    "sg:address":"20093 Cologno Monzese",
    "sg:city":"Cologno Monzese",
    "sg:orig_category":"Carpenterie Metalliche",
    "sg:phone":"+39 02 2539 0128",
    "sg:postcode":"20093",
    "sg:province":"Milano",
    "wof:name":"Ca.bi. Snc",
    "wof:placetype":"venue"
},
  "geometry": {"coordinates":[9.263864,45.518356],"type":"Point"}
}