{
  "type": "Feature",
  "properties": {
    "iso:country":"IT",
    "sg:address":"Pzza.v. Emanuele Ii, 29; Badia; 45021",
    "sg:classifiers":[
        {
            "category":"Banks & Credit Unions",
            "subcategory":"Bank",
            "type":"Services"
        }
    ],
    "sg:phone":"+39 0425 51882",
    "sg:postcode":"45021",
    "sg:province":"Rovigo",
    "wof:name":"Banco Popolare Veneta",
    "wof:placetype":"venue"
},
  "geometry": {"coordinates":[11.491666,45.094681],"type":"Point"}
}