{
  "type": "Feature",
  "properties": {
    "iso:country":"IT",
    "sg:address":"16154 Genova",
    "sg:city":"Genova",
    "sg:orig_category":"Manufacturers: Prefabbricati",
    "sg:phone":"+39 010 604 3204",
    "sg:postcode":"16154",
    "sg:province":"Genova",
    "sg:website":"http://www.nextprint.net",
    "wof:name":"Thesis Snc Di A. Patrone & C.",
    "wof:placetype":"venue"
},
  "geometry": {"coordinates":[8.842559,44.426262],"type":"Point"}
}