{
  "type": "Feature",
  "properties": {
    "iso:country":"IT",
    "sg:address":"00133 Roma",
    "sg:city":"Roma",
    "sg:orig_category":"Sedie E Tavoli - Produzione E Ingrosso",
    "sg:phone":"+39 06 201 3344",
    "sg:postcode":"00133",
    "sg:province":"Roma",
    "wof:name":"Lotito E Panoni Srl",
    "wof:placetype":"venue"
},
  "geometry": {"coordinates":[12.613029,41.883976],"type":"Point"}
}