{
  "type": "Feature",
  "properties": {
    "addr:full":"56124 Pisa Pisa Pisa 56124",
    "addr:postcode":"56124;56124",
    "iso:country":"IT",
    "sg:address":"56124 Pisa",
    "sg:city":"Pisa",
    "sg:orig_category":"Isolanti Termici Ed Acustici - Installazione",
    "sg:phone":"+39 050 577773",
    "sg:postcode":"56124",
    "sg:province":"Pisa",
    "wof:name":"M.t. Di Mureddu E Terzi Snc",
    "wof:placetype":"venue"
},
  "geometry": {"coordinates":[10.439537,43.709957],"type":"Point"}
}