{
  "type": "Feature",
  "properties": {
    "iso:country":"IT",
    "sg:address":"13, Via Giovanni Xxiii 37060 Mozzecane",
    "sg:city":"Mozzecane",
    "sg:classifiers":[
        {
            "category":"Manufacturing",
            "subcategory":"Paper Products",
            "type":"Manufacturing & Wholesale Goods"
        }
    ],
    "sg:phone":"+39 045 634 0175",
    "sg:postcode":"37060",
    "sg:province":"Verona",
    "sg:tags":[
        "cardboard"
    ],
    "wof:name":"Scatolificio Maffioli & Turrina (s.p.a.)",
    "wof:placetype":"venue"
},
  "geometry": {"coordinates":[10.8152399063,45.3113441467],"type":"Point"}
}