{
  "type": "Feature",
  "properties": {
    "addr:full":"50035 Palazzuolo Sul Senio Palazzuolo sul Senio Firenze 50035",
    "addr:postcode":"50035;50035",
    "iso:country":"IT",
    "sg:address":"50035 Palazzuolo Sul Senio",
    "sg:city":"Palazzuolo sul Senio",
    "sg:classifiers":[
        {
            "category":"Manufacturing",
            "subcategory":"Metals",
            "type":"Manufacturing & Wholesale Goods"
        }
    ],
    "sg:phone":"+39 055 804 6658",
    "sg:postcode":"50035",
    "sg:province":"Firenze",
    "sg:tags":[
        "forming",
        "working",
        "welding"
    ],
    "wof:name":"Meccanica R.c. Srl",
    "wof:placetype":"venue"
},
  "geometry": {"coordinates":[11.5543069839,44.1193161011],"type":"Point"}
}