{
  "type": "Feature",
  "properties": {
    "iso:country":"IT",
    "sg:address":"12084 Mondov\u00ec",
    "sg:orig_category":"Materiali Edili",
    "sg:phone":"+39 0174 46384",
    "sg:postcode":"12084",
    "sg:province":"Cuneo",
    "wof:name":"S.i.l.t.e. Spa",
    "wof:placetype":"venue"
},
  "geometry": {"coordinates":[7.819031,44.405319],"type":"Point"}
}