{
  "type": "Feature",
  "properties": {
    "addr:full":"48, V. Monfalcone 74100 Taranto Taranto Taranto 74100",
    "addr:housenumber":"48",
    "addr:postcode":"74100;74100",
    "addr:street":"V. Monfalcone",
    "iso:country":"IT",
    "sg:address":"48, V. Monfalcone 74100 Taranto",
    "sg:city":"Taranto",
    "sg:orig_category":"Miscellaneous Products",
    "sg:phone":"+39 099 459 4998",
    "sg:postcode":"74100",
    "sg:province":"Taranto",
    "sg:website":"http://www.paginegialle.it/liuzzitommaso",
    "wof:name":"Onoranze Funebri Tommaso Liuzzi",
    "wof:placetype":"venue"
},
  "geometry": {"coordinates":[17.2496891022,40.4674682617],"type":"Point"}
}