{
  "type": "Feature",
  "properties": {
    "iso:country":"IT",
    "sg:address":"20121 Milano",
    "sg:city":"Milano",
    "sg:orig_category":"Servizi Culturali E Per Lo Spettacolo. Servizi Al Turismo. Acqua, Luce, Gas E Societa' Di Esercizio Pubblico",
    "sg:phone":"+39 02 2900 2736",
    "sg:postcode":"20121",
    "sg:province":"Milano",
    "wof:name":"Biblioteca Francescana",
    "wof:placetype":"venue"
},
  "geometry": {"coordinates":[9.192266,45.475903],"type":"Point"}
}