{
  "type": "Feature",
  "properties": {
    "iso:country":"IT",
    "sg:address":"47100 Villa Selva",
    "sg:orig_category":"Nautica. Automobili E Mezzi Di Trasporto",
    "sg:phone":"+39 0543 473560",
    "sg:postcode":"47100",
    "sg:province":"Forl\u00ec-Cesena",
    "wof:name":"Cantiere Nautico Forlivese Di Zanoni Maurizio & C. Snc",
    "wof:placetype":"venue"
},
  "geometry": {"coordinates":[11.980461,43.994766],"type":"Point"}
}