{
  "type": "Feature",
  "properties": {
    "addr:full":"91029 Santa Ninfa Santa Ninfa Trapani 91029",
    "addr:housenumber":"ninfa",
    "addr:postcode":"91029;91029",
    "addr:street":"Santa Ninfa",
    "iso:country":"IT",
    "sg:address":"91029 Santa Ninfa",
    "sg:city":"Santa Ninfa",
    "sg:orig_category":"Impiantistica E Prodotti Tecnologici Per Edilizia. Elettrotecnica Professionale E Di Consumo. Telecomunicazioni E Telefonia, Impianti, Apparecchi E Servizi",
    "sg:phone":"+39 0924 62230",
    "sg:postcode":"91029",
    "sg:province":"Trapani",
    "sg:website":"http://www.etelettronica.com",
    "wof:name":"E.t. Elettronica T. Sas Di Rizzo Calogero",
    "wof:placetype":"venue"
},
  "geometry": {"coordinates":[12.880908,37.774857],"type":"Point"}
}