{
  "type": "Feature",
  "properties": {
    "iso:country":"IT",
    "sg:address":"Via Oderzo , 68 - Villanova 33080 Prata Di Pordenone",
    "sg:city":"Prata di Pordenone",
    "sg:classifiers":[
        {
            "category":"Shopping",
            "subcategory":"Stationery & Office Supplies",
            "type":"Retail Goods"
        }
    ],
    "sg:phone":"+39 0434 615311",
    "sg:postcode":"33080",
    "sg:province":"Pordenone",
    "sg:tags":[
        "component",
        "furniture"
    ],
    "sg:website":"www.friulintagli.com",
    "wof:name":"Friul Intagli Spa",
    "wof:placetype":"venue"
},
  "geometry": {"coordinates":[12.557693,45.865261],"type":"Point"}
}