{
  "type": "Feature",
  "properties": {
    "addr:full":"37047 S. Bonifacio Verona 37047",
    "addr:housenumber":"37047",
    "addr:postcode":"37047",
    "addr:street":"S. Bonifacio",
    "iso:country":"IT",
    "sg:address":"37047 S. Bonifacio",
    "sg:orig_category":"Trasporto Pubblico E Privato",
    "sg:phone":"+39 045 761 4393",
    "sg:postcode":"37047",
    "sg:province":"Verona",
    "sg:website":"http://www.daneseviaggi.it",
    "wof:name":"Danese Mario",
    "wof:placetype":"venue"
},
  "geometry": {"coordinates":[10.991748,45.438366],"type":"Point"}
}