{
  "type": "Feature",
  "properties": {
    "iso:country":"IT",
    "sg:address":"20098 San Giuliano Milanese",
    "sg:city":"San Giuliano Milanese",
    "sg:orig_category":"Materiali E Componenti Elettronici",
    "sg:phone":"+39 02 9824 1820",
    "sg:postcode":"20098",
    "sg:province":"Milano",
    "wof:name":"Bieffe Di Belloni Paolo (s.n.c.)",
    "wof:placetype":"venue"
},
  "geometry": {"coordinates":[9.285596,45.383781],"type":"Point"}
}