{
  "type": "Feature",
  "properties": {
    "iso:country":"IT",
    "sg:address":"23879 Verderio Inferiore",
    "sg:city":"Verderio Inferiore",
    "sg:orig_category":"Agricoltura - Attrezzi, Prodotti E Forniture",
    "sg:phone":"+39 039 510070",
    "sg:postcode":"23879",
    "sg:province":"Lecco",
    "wof:name":"Macchine Agricole Pietro Sala Di Sala Dino E Ezio Snc",
    "wof:placetype":"venue"
},
  "geometry": {"coordinates":[9.433374,45.661877],"type":"Point"}
}