{
  "type": "Feature",
  "properties": {
    "iso:country":"IT",
    "sg:address":"Largo Garibaldi 44; Pieris; 34075",
    "sg:city":"Pieris",
    "sg:classifiers":[
        {
            "category":"Banks & Credit Unions",
            "subcategory":"Bank",
            "type":"Services"
        }
    ],
    "sg:phone":"+39 0481 76008",
    "sg:postcode":"34075",
    "sg:province":"Gorizia",
    "wof:name":"Cassa Di Risparmio Di Gorizia Spa",
    "wof:placetype":"venue"
},
  "geometry": {"coordinates":[13.444364,45.809013],"type":"Point"}
}