{
  "type": "Feature",
  "properties": {
    "iso:country":"IT",
    "sg:address":"16, Via Bevano 48100 Ravenna",
    "sg:city":"Ravenna",
    "sg:classifiers":[
        {
            "category":"Wholesale",
            "subcategory":"Drugs",
            "type":"Manufacturing & Wholesale Goods"
        }
    ],
    "sg:phone":"+39 0544 554227",
    "sg:postcode":"48100",
    "sg:province":"Ravenna",
    "sg:tags":[
        "chemical",
        "pharmaceutical"
    ],
    "wof:name":"Agostini Nautica (s.r.l.)",
    "wof:placetype":"venue"
},
  "geometry": {"coordinates":[12.235844,44.269566],"type":"Point"}
}