{
  "type": "Feature",
  "properties": {
    "iso:country":"IT",
    "sg:address":"Via Unita D'italia 4 35010 Limena",
    "sg:city":"Limena",
    "sg:classifiers":[
        {
            "category":"Wholesale",
            "subcategory":"Auto Parts",
            "type":"Manufacturing & Wholesale Goods"
        }
    ],
    "sg:phone":"+39 049 884 0270",
    "sg:postcode":"35010",
    "sg:province":"Padova",
    "sg:tags":[
        "shutter",
        "component",
        "roller"
    ],
    "wof:name":"B & B Padova Sas Di Andrea Bisello",
    "wof:placetype":"venue"
},
  "geometry": {"coordinates":[11.855786,45.460197],"type":"Point"}
}