{
  "type": "Feature",
  "properties": {
    "iso:country":"IT",
    "sg:address":"90124 Palermo",
    "sg:city":"Palermo",
    "sg:orig_category":"Forniture Per Edilizia E Lavori Pubblici. Prodotti Vari In Metallo",
    "sg:phone":"+39 091 474349",
    "sg:postcode":"90124",
    "sg:province":"Palermo",
    "sg:website":"http://www.sudferro.it",
    "wof:name":"Sud Ferro Srl",
    "wof:placetype":"venue"
},
  "geometry": {"coordinates":[13.4005317688,38.0946388245],"type":"Point"}
}