{
  "type": "Feature",
  "properties": {
    "iso:country":"IT",
    "sg:address":"36051 Creazzo",
    "sg:city":"Creazzo",
    "sg:orig_category":"Cartotecnica E Servizi",
    "sg:phone":"+39 0444 520440",
    "sg:postcode":"36051",
    "sg:province":"Vicenza",
    "wof:name":"Costruzioni Meccaniche Pizzolato Massimiliano Srl",
    "wof:placetype":"venue"
},
  "geometry": {"coordinates":[11.495905,45.528957],"type":"Point"}
}