{
  "type": "Feature",
  "properties": {
    "iso:country":"IT",
    "sg:address":"50143 Firenze",
    "sg:city":"Firenze",
    "sg:orig_category":"Alimentari - Vendita Al Dettaglio",
    "sg:phone":"+39 055 710716",
    "sg:postcode":"50143",
    "sg:province":"Firenze",
    "wof:name":"La Buona Tavola",
    "wof:placetype":"venue"
},
  "geometry": {"coordinates":[11.20988,43.765041],"type":"Point"}
}