{
  "type": "Feature",
  "properties": {
    "iso:country":"IT",
    "sg:address":"84123 Salerno",
    "sg:city":"Salerno",
    "sg:classifiers":[
        {
            "category":"Health Services",
            "subcategory":"Health Practitioner",
            "type":"Services"
        }
    ],
    "sg:phone":"+39 089 224855",
    "sg:postcode":"84123",
    "sg:province":"Salerno",
    "sg:tags":[
        "medici"
    ],
    "wof:name":"Landolfi Luigi",
    "wof:placetype":"venue"
},
  "geometry": {"coordinates":[14.76475,40.676434],"type":"Point"}
}