{
  "type": "Feature",
  "properties": {
    "iso:country":"IT",
    "sg:address":"157, Strada Statale 35 Dei Giovi 20037 Paderno Dugnano",
    "sg:city":"Paderno Dugnano",
    "sg:classifiers":[
        {
            "category":"Bars & Pubs",
            "subcategory":"Nightclub",
            "type":"Food & Drink"
        }
    ],
    "sg:phone":"+39 02 9904 5090",
    "sg:postcode":"20037",
    "sg:province":"Milano",
    "sg:tags":[
        "cake",
        "bread"
    ],
    "wof:name":"Veropan Di Finaldi Antonia",
    "wof:placetype":"venue"
},
  "geometry": {"coordinates":[9.169345,45.558731],"type":"Point"}
}