{
  "type": "Feature",
  "properties": {
    "addr:full":"56, Via Ferraris Galileo 31044 Montebelluna Montebelluna Treviso 31044",
    "addr:postcode":"31044;31044",
    "addr:street":"Via Ferraris Galileo",
    "iso:country":"IT",
    "sg:address":"56, Via Ferraris Galileo 31044 Montebelluna",
    "sg:city":"Montebelluna",
    "sg:classifiers":[
        {
            "category":"Personal",
            "subcategory":"Shoe Repair & Shine",
            "type":"Services"
        }
    ],
    "sg:phone":"+39 0423 292211",
    "sg:postcode":"31044",
    "sg:province":"Treviso",
    "sg:tags":[
        "leather"
    ],
    "wof:name":"Jolly Scarpe (s.r.l.)",
    "wof:placetype":"venue"
},
  "geometry": {"coordinates":[12.242072,45.666286],"type":"Point"}
}