{
  "type": "Feature",
  "properties": {
    "addr:full":"30030 Tombelle Tombelle Venezia 30030",
    "addr:postcode":"30030;30030",
    "addr:street":"Tombelle",
    "iso:country":"IT",
    "sg:address":"30030 Tombelle",
    "sg:city":"Tombelle",
    "sg:orig_category":"Campeggio. Accessori Dei Mezzi Di Trasporto",
    "sg:phone":"+39 049 980 0034",
    "sg:postcode":"30030",
    "sg:province":"Venezia",
    "wof:name":"Italstand S.a.s.",
    "wof:placetype":"venue"
},
  "geometry": {"coordinates":[11.983916,45.398762],"type":"Point"}
}