{
  "type": "Feature",
  "properties": {
    "iso:country":"IT",
    "sg:address":"35020 Albignasego",
    "sg:city":"Albignasego",
    "sg:orig_category":"Servizi E Lavori Per Abbigliamento E Pelletterie",
    "sg:phone":"+39 049 693931",
    "sg:postcode":"35020",
    "sg:province":"Padova",
    "wof:name":"Schiavon Giuseppe",
    "wof:placetype":"venue"
},
  "geometry": {"coordinates":[11.858023,45.372269],"type":"Point"}
}