{
  "type": "Feature",
  "properties": {
    "iso:country":"IT",
    "sg:address":"20013 Magenta",
    "sg:city":"Magenta",
    "sg:orig_category":"Macchine, Impianti Ed Attrezzature Industria Delle Materie Plastiche E Gomma",
    "sg:phone":"+39 02 970 0071",
    "sg:postcode":"20013",
    "sg:province":"Milano",
    "sg:website":"http://www.uniloymilacron.com",
    "wof:name":"Uniloy Milacron Srl S.u.",
    "wof:placetype":"venue"
},
  "geometry": {"coordinates":[8.887688,45.454414],"type":"Point"}
}