{
  "type": "Feature",
  "properties": {
    "iso:country":"IT",
    "sg:address":"20018 Sedriano",
    "sg:city":"Sedriano",
    "sg:orig_category":"Servizi Ausiliari Di Analisi, Controllo E Ricerca",
    "sg:phone":"+39 02 9031 0207",
    "sg:postcode":"20018",
    "sg:province":"Milano",
    "wof:name":"Dimart Srl",
    "wof:placetype":"venue"
},
  "geometry": {"coordinates":[8.961251,45.497059],"type":"Point"}
}