{
  "type": "Feature",
  "properties": {
    "addr:full":"1, Piazza Stazione 39042 Bressanone Bressanone Bolzano/Bozen 39042",
    "addr:postcode":"39042;39042",
    "addr:street":"Piazza Stazione",
    "iso:country":"IT",
    "sg:address":"1, Piazza Stazione 39042 Bressanone",
    "sg:city":"Bressanone",
    "sg:classifiers":[
        {
            "category":"Travel",
            "subcategory":"Travel Agent",
            "type":"Entertainment"
        }
    ],
    "sg:phone":"+39 0472 836230",
    "sg:postcode":"39042",
    "sg:province":"Bolzano/Bozen",
    "sg:tags":[
        "business"
    ],
    "wof:name":"Hotel Jarolim",
    "wof:placetype":"venue"
},
  "geometry": {"coordinates":[11.652281,46.71328],"type":"Point"}
}