{
  "type": "Feature",
  "properties": {
    "iso:country":"IT",
    "sg:address":"Contrada Difesa 88050 Caraffa Di Catanzaro",
    "sg:city":"Caraffa di Catanzaro",
    "sg:classifiers":[
        {
            "category":"Utilities",
            "subcategory":"Telephone",
            "type":"Services"
        }
    ],
    "sg:phone":"+39 0961 956478",
    "sg:postcode":"88050",
    "sg:province":"Catanzaro",
    "sg:tags":[
        "telecommunication"
    ],
    "wof:name":"Publineon's Di Talarico & C. Snc",
    "wof:placetype":"venue"
},
  "geometry": {"coordinates":[16.511995,38.876709],"type":"Point"}
}