{
  "type": "Feature",
  "properties": {
    "addr:full":"13, Via Vivaldi 46042 Castel Goffredo Castel Goffredo Mantova 46042",
    "addr:postcode":"46042;46042",
    "addr:street":"Via Vivaldi;Goffredo",
    "iso:country":"IT",
    "sg:address":"13, Via Vivaldi 46042 Castel Goffredo",
    "sg:city":"Castel Goffredo",
    "sg:orig_category":"Miscellaneous Products",
    "sg:phone":"+39 0376 779813",
    "sg:postcode":"46042",
    "sg:province":"Mantova",
    "wof:name":"Clodipack (s.r.l.)",
    "wof:placetype":"venue"
},
  "geometry": {"coordinates":[10.4807538986,45.2950668335],"type":"Point"}
}