{
  "type": "Feature",
  "properties": {
    "iso:country":"IT",
    "sg:address":"27026 Garlasco",
    "sg:city":"Garlasco",
    "sg:orig_category":"Arredo Cucina Ed Elettrodomestici. Elettrodomestici",
    "sg:phone":"+39 388 822 218",
    "sg:postcode":"27026",
    "sg:province":"Pavia",
    "wof:name":"Arredamenti Curti",
    "wof:placetype":"venue"
},
  "geometry": {"coordinates":[9.157214,45.186348],"type":"Point"}
}