{
  "type": "Feature",
  "properties": {
    "iso:country":"IT",
    "sg:address":"56/3, Via Panciatichi 50127 Firenze",
    "sg:city":"Firenze",
    "sg:classifiers":[
        {
            "category":"Shopping",
            "subcategory":"Crafts & Fabrics",
            "type":"Retail Goods"
        }
    ],
    "sg:phone":"+39 39055417938",
    "sg:postcode":"50127",
    "sg:province":"Firenze",
    "sg:tags":[
        "linen"
    ],
    "wof:name":"Narim Srl",
    "wof:placetype":"venue"
},
  "geometry": {"coordinates":[11.2318954468,43.8014755249],"type":"Point"}
}