{
  "type": "Feature",
  "properties": {
    "addr:full":"52 Via Creta, 25124 Brescia Brescia Brescia 25124",
    "addr:postcode":"25124;25124",
    "addr:street":"Via Creta",
    "iso:country":"IT",
    "sg:address":"52 Via Creta, 25124 Brescia",
    "sg:city":"Brescia",
    "sg:classifiers":[
        {
            "category":"Banks & Credit Unions",
            "subcategory":"Financial Services",
            "type":"Services"
        }
    ],
    "sg:phone":"+39 030 242 0281",
    "sg:postcode":"25124",
    "sg:province":"Brescia",
    "sg:tags":[
        "banking",
        "finance",
        "insurance"
    ],
    "wof:name":"Prevex Lewis (srl)",
    "wof:placetype":"venue"
},
  "geometry": {"coordinates":[10.2140932083,45.5280151367],"type":"Point"}
}