{
  "type": "Feature",
  "properties": {
    "iso:country":"IT",
    "sg:address":"53036 Poggibonsi",
    "sg:city":"Poggibonsi",
    "sg:orig_category":"Arredo Camera Letto E Complementi",
    "sg:phone":"+39 0577 982502",
    "sg:postcode":"53036",
    "sg:province":"Siena",
    "wof:name":"Bisniflex Snc Di Bisciarri Gianni & C.",
    "wof:placetype":"venue"
},
  "geometry": {"coordinates":[11.137915,43.472214],"type":"Point"}
}