{
  "type": "Feature",
  "properties": {
    "addr:full":"87040 Luzzi Luzzi Cosenza 87040",
    "addr:postcode":"87040;87040",
    "iso:country":"IT",
    "sg:address":"87040 Luzzi",
    "sg:city":"Luzzi",
    "sg:orig_category":"Edilizia - Materiali",
    "sg:phone":"+39 0984 543855",
    "sg:postcode":"87040",
    "sg:province":"Cosenza",
    "wof:name":"Profilati Plastici Srl",
    "wof:placetype":"venue"
},
  "geometry": {"coordinates":[16.28924,39.447205],"type":"Point"}
}