{
  "type": "Feature",
  "properties": {
    "iso:country":"IT",
    "sg:address":"Via Della Madonnina 31044 Montebelluna",
    "sg:city":"Montebelluna",
    "sg:classifiers":[
        {
            "category":"Airport",
            "subcategory":"General Aviation",
            "type":"Transportation"
        }
    ],
    "sg:phone":"+39 0423 603712",
    "sg:postcode":"31044",
    "sg:province":"Treviso",
    "sg:tags":[
        "transport",
        "air"
    ],
    "wof:name":"Savitransport Triveneto S.r.l.",
    "wof:placetype":"venue"
},
  "geometry": {"coordinates":[12.08092,45.764973],"type":"Point"}
}