{
  "type": "Feature",
  "properties": {
    "addr:full":"31050 Ponzano Veneto Ponzano Veneto Treviso 31050",
    "addr:postcode":"31050;31050",
    "iso:country":"IT",
    "sg:address":"31050 Ponzano Veneto",
    "sg:city":"Ponzano Veneto",
    "sg:orig_category":"Filati E Materie Prime Tessili",
    "sg:phone":"+39 0422 442491",
    "sg:postcode":"31050",
    "sg:province":"Treviso",
    "wof:name":"Durak Italia S.p.a.",
    "wof:placetype":"venue"
},
  "geometry": {"coordinates":[12.2331628799,45.666809082],"type":"Point"}
}