{
  "type": "Feature",
  "properties": {
    "iso:country":"IT",
    "sg:address":"65121 Pescara",
    "sg:city":"Pescara",
    "sg:orig_category":"Articoli Da Regalo. Tempo Libero - Articoli E Forniture. Regalistica Aziendale",
    "sg:phone":"+39 085 205 6217",
    "sg:postcode":"65121",
    "sg:province":"Pescara",
    "wof:name":"Farinaccia Ivo",
    "wof:placetype":"venue"
},
  "geometry": {"coordinates":[14.214261,42.467152],"type":"Point"}
}