{
  "type": "Feature",
  "properties": {
    "iso:country":"IT",
    "sg:address":"23852 Garlate",
    "sg:city":"Garlate",
    "sg:orig_category":"Nautica. Ricambi E Componenti Dei Mezzi Di Trasporto",
    "sg:phone":"+39 0341 680265",
    "sg:postcode":"23852",
    "sg:province":"Lecco",
    "wof:name":"Pettinato Luigi",
    "wof:placetype":"venue"
},
  "geometry": {"coordinates":[9.401132,45.810467],"type":"Point"}
}