{
  "type": "Feature",
  "properties": {
    "addr:full":"66021 Casalbordino Casalbordino Chieti 66021",
    "addr:postcode":"66021;66021",
    "iso:country":"IT",
    "sg:address":"66021 Casalbordino",
    "sg:city":"Casalbordino",
    "sg:orig_category":"Macchine, Impianti Ed Attrezzature Per Agricoltura E Zootecnia",
    "sg:phone":"+39 0873 902506",
    "sg:postcode":"66021",
    "sg:province":"Chieti",
    "wof:name":"Sermetal 2000 Di Ratti Massimo",
    "wof:placetype":"venue"
},
  "geometry": {"coordinates":[14.604248,42.154984],"type":"Point"}
}