{
  "type": "Feature",
  "properties": {
    "iso:country":"IT",
    "sg:address":"41018 San Cesario Sul Panaro",
    "sg:city":"San Cesario sul Panaro",
    "sg:orig_category":"Servizi E Lavori Per Agricoltura E Zootecnia",
    "sg:phone":"+39 059 926268",
    "sg:postcode":"41018",
    "sg:province":"Modena",
    "wof:name":"Istituto Sperimentale Zootecnia",
    "wof:placetype":"venue"
},
  "geometry": {"coordinates":[11.04248,44.581745],"type":"Point"}
}