{
  "type": "Feature",
  "properties": {
    "iso:country":"IT",
    "sg:address":"20092 Cinisello Balsamo",
    "sg:city":"Cinisello Balsamo",
    "sg:orig_category":"Professionisti - Studi E Servizi Ed Associazioni Di Interesse Aziendale. Associazioni Ed Organismi Di Interesse Pubblico. Chiese Ed Associazioni Religiose",
    "sg:phone":"+39 02 6604 7392",
    "sg:postcode":"20092",
    "sg:province":"Milano",
    "wof:name":"Oratorio Maschile Emmaus",
    "wof:placetype":"venue"
},
  "geometry": {"coordinates":[9.221326828,45.5461654663],"type":"Point"}
}