{
  "type": "Feature",
  "properties": {
    "iso:country":"IT",
    "sg:address":"Via Toro Sottano 83029 Solofra",
    "sg:city":"Solofra",
    "sg:classifiers":[
        {
            "category":"Manufacturing",
            "subcategory":"Textiles",
            "type":"Manufacturing & Wholesale Goods"
        }
    ],
    "sg:phone":"+39 0825 581385",
    "sg:postcode":"83029",
    "sg:province":"Avellino",
    "sg:tags":[
        "leather",
        "raw",
        "material",
        "-"
    ],
    "wof:name":"Gaia Srl",
    "wof:placetype":"venue"
},
  "geometry": {"coordinates":[14.842401,40.834766],"type":"Point"}
}