{
  "type": "Feature",
  "properties": {
    "iso:country":"IT",
    "sg:address":"14, Via Roma 42022 Boretto",
    "sg:classifiers":[
        {
            "category":"Travel",
            "subcategory":"Travel Agent",
            "type":"Entertainment"
        }
    ],
    "sg:phone":"+39 0522 963188",
    "sg:postcode":"42022",
    "sg:province":"Reggio Nell'Emilia",
    "sg:tags":[
        "business"
    ],
    "wof:name":"G.a.m.p. Srl",
    "wof:placetype":"venue"
},
  "geometry": {"coordinates":[10.627794,44.696228],"type":"Point"}
}