{
  "type": "Feature",
  "properties": {
    "addr:full":"16, Via Caduti Di Superga 84016 Pagani Pagani Salerno 84016",
    "addr:postcode":"84016;84016",
    "addr:street":"Via Caduti Di Superga",
    "iso:country":"IT",
    "sg:address":"16, Via Caduti Di Superga 84016 Pagani",
    "sg:city":"Pagani",
    "sg:classifiers":[
        {
            "category":"Farming",
            "subcategory":"Livestock Farm",
            "type":"Manufacturing & Wholesale Goods"
        }
    ],
    "sg:phone":"+39 39081916989",
    "sg:postcode":"84016",
    "sg:province":"Salerno",
    "sg:tags":[
        "agriculture"
    ],
    "wof:name":"Boccia Salvatore Dei Fratelli Boccia S.r.l.",
    "wof:placetype":"venue"
},
  "geometry": {"coordinates":[14.623534,40.742706],"type":"Point"}
}