{
  "type": "Feature",
  "properties": {
    "iso:country":"IT",
    "sg:address":"23900 Lecco",
    "sg:city":"Lecco",
    "sg:orig_category":"Nastri Ferro E Acciaio",
    "sg:phone":"+39 0341 250496",
    "sg:postcode":"23900",
    "sg:province":"Lecco",
    "wof:name":"Mepla Srl",
    "wof:placetype":"venue"
},
  "geometry": {"coordinates":[9.407782,45.856716],"type":"Point"}
}