{
  "type": "Feature",
  "properties": {
    "iso:country":"IT",
    "sg:address":"47042 Cesenatico",
    "sg:city":"Cesenatico",
    "sg:orig_category":"Servizi E Lavori Per Edilizia E Lavori Pubblici. Servizi Al Turismo",
    "sg:phone":"+39 0544 970942",
    "sg:postcode":"47042",
    "sg:province":"Forl\u00ec-Cesena",
    "sg:website":"http://www.romagnaonweb.com",
    "wof:name":"Alberghi Cesenatico Romagna On Web",
    "wof:placetype":"venue"
},
  "geometry": {"coordinates":[12.395361,44.198948],"type":"Point"}
}