{
  "type": "Feature",
  "properties": {
    "iso:country":"IT",
    "sg:address":"10073 Ciri\u00e8",
    "sg:orig_category":"Legno E Semilavorati",
    "sg:phone":"+39 011 921 4937",
    "sg:postcode":"10073",
    "sg:province":"Torino",
    "sg:website":"http://www.palumbo-legnami.it",
    "wof:name":"Eredi Palumbo Achille Snc",
    "wof:placetype":"venue"
},
  "geometry": {"coordinates":[7.604771,45.227013],"type":"Point"}
}