{
  "type": "Feature",
  "properties": {
    "addr:full":"29020 Gossolengo Gossolengo Piacenza 29020",
    "addr:postcode":"29020;29020",
    "iso:country":"IT",
    "sg:address":"29020 Gossolengo",
    "sg:city":"Gossolengo",
    "sg:orig_category":"Materiali Edili",
    "sg:phone":"+39 0523 778682",
    "sg:postcode":"29020",
    "sg:province":"Piacenza",
    "wof:name":"Inerti Trebbia Srl",
    "wof:placetype":"venue"
},
  "geometry": {"coordinates":[9.606259,44.989555],"type":"Point"}
}