{
  "type": "Feature",
  "properties": {
    "iso:country":"IT",
    "sg:address":"65020 Cugnoli",
    "sg:city":"Cugnoli",
    "sg:orig_category":"Abbigliamento - Produzione E Ingrosso",
    "sg:phone":"+39 085 857 6015",
    "sg:postcode":"65020",
    "sg:province":"Pescara",
    "wof:name":"Elleciemme Di La Cioppa Massimo",
    "wof:placetype":"venue"
},
  "geometry": {"coordinates":[13.934973,42.307331],"type":"Point"}
}