{
  "type": "Feature",
  "properties": {
    "addr:full":"96019 Rosolini Rosolini Siracusa 96019",
    "addr:postcode":"96019;96019",
    "iso:country":"IT",
    "sg:address":"96019 Rosolini",
    "sg:city":"Rosolini",
    "sg:orig_category":"Abbigliamento Esterno, Maglierie E Pelliccerie. Servizi E Lavori Per Abbigliamento E Pelletterie",
    "sg:phone":"+39 0931 856557",
    "sg:postcode":"96019",
    "sg:province":"Siracusa",
    "wof:name":"Sogno Confezioni Di Balbuena Erika",
    "wof:placetype":"venue"
},
  "geometry": {"coordinates":[15.288034,37.067863],"type":"Point"}
}