{
  "type": "Feature",
  "properties": {
    "addr:full":"Via Marco Polo 125 56031 Bientina Bientina Pisa 56031",
    "addr:housenumber":"125",
    "addr:postcode":"56031;56031",
    "addr:street":"Via Marco Polo",
    "iso:country":"IT",
    "sg:address":"Via Marco Polo 125 56031 Bientina",
    "sg:city":"Bientina",
    "sg:classifiers":[
        {
            "category":"Communications",
            "subcategory":"Television Station",
            "type":"Services"
        }
    ],
    "sg:phone":"+39 0587 489877",
    "sg:postcode":"56031",
    "sg:province":"Pisa",
    "sg:tags":[
        "shower",
        "cabinet"
    ],
    "sg:website":"www.lineabox.net",
    "wof:name":"Linea Box Srl",
    "wof:placetype":"venue"
},
  "geometry": {"coordinates":[10.396585,43.716137],"type":"Point"}
}