{
  "type": "Feature",
  "properties": {
    "iso:country":"IT",
    "sg:address":"Piazza Fulcheria, 27; Crema; 26013",
    "sg:city":"Crema",
    "sg:classifiers":[
        {
            "category":"Banks & Credit Unions",
            "subcategory":"Bank",
            "type":"Services"
        }
    ],
    "sg:phone":"+39 0373 891315",
    "sg:postcode":"26013",
    "sg:province":"Cremona",
    "wof:name":"Banca Popolare Di Crema",
    "wof:placetype":"venue"
},
  "geometry": {"coordinates":[9.679576,45.364334],"type":"Point"}
}