{
  "type": "Feature",
  "properties": {
    "iso:country":"IT",
    "sg:address":"62100 Macerata",
    "sg:city":"Macerata",
    "sg:orig_category":"Ricambi E Componenti Dei Mezzi Di Trasporto",
    "sg:phone":"+39 0733 264498",
    "sg:postcode":"62100",
    "sg:province":"Macerata",
    "wof:name":"Zizzo Pietro",
    "wof:placetype":"venue"
},
  "geometry": {"coordinates":[13.435965,43.34647],"type":"Point"}
}