{
  "type": "Feature",
  "properties": {
    "iso:country":"IT",
    "sg:address":"10, Via S. Antonio 10090 Rosta",
    "sg:city":"Rosta",
    "sg:classifiers":[
        {
            "category":"Manufacturing",
            "subcategory":"Rubber & Plastics",
            "type":"Manufacturing & Wholesale Goods"
        }
    ],
    "sg:phone":"+39 011 954 0960",
    "sg:postcode":"10090",
    "sg:province":"Torino",
    "wof:name":"Saturno Industriale S.p.a.",
    "wof:placetype":"venue"
},
  "geometry": {"coordinates":[7.1200766563,45.1260185242],"type":"Point"}
}