{
  "type": "Feature",
  "properties": {
    "addr:full":"121, Via S. Croce 47032 Bertinoro Bertinoro Forl\u00ec-Cesena 47032",
    "addr:housenumber":"121",
    "addr:postcode":"47032;47032",
    "addr:street":"Via S. Croce",
    "iso:country":"IT",
    "sg:address":"121, Via S. Croce 47032 Bertinoro",
    "sg:city":"Bertinoro",
    "sg:classifiers":[
        {
            "category":"Shopping",
            "subcategory":"Computers & Home Electronics",
            "type":"Retail Goods"
        }
    ],
    "sg:phone":"+39 0543 449090",
    "sg:postcode":"47032",
    "sg:province":"Forl\u00ec-Cesena",
    "sg:tags":[
        "electronic",
        "electrical",
        "equipment"
    ],
    "wof:name":"Mareco Luce S.r.l.",
    "wof:placetype":"venue"
},
  "geometry": {"coordinates":[12.172427,44.185093],"type":"Point"}
}