{
  "type": "Feature",
  "properties": {
    "iso:country":"IT",
    "sg:address":"29015 Castel San Giovanni",
    "sg:city":"Castel San Giovanni",
    "sg:orig_category":"Prodotti Alimentari",
    "sg:phone":"+39 0523 842659",
    "sg:postcode":"29015",
    "sg:province":"Piacenza",
    "wof:name":"Macciotti Giorgio Michela Renzo Snc",
    "wof:placetype":"venue"
},
  "geometry": {"coordinates":[9.4309949875,45.0505523682],"type":"Point"}
}