{
  "type": "Feature",
  "properties": {
    "iso:country":"IT",
    "sg:address":"70017 Putignano",
    "sg:city":"Putignano",
    "sg:orig_category":"Elettrotecnica Industriale, Prodotti E Apparecchiature",
    "sg:phone":"+39 080 405 7433",
    "sg:postcode":"70017",
    "sg:province":"Bari",
    "wof:name":"Gestioni Servizi Industriali Srl",
    "wof:placetype":"venue"
},
  "geometry": {"coordinates":[17.08938,40.843807],"type":"Point"}
}