{
  "type": "Feature",
  "properties": {
    "iso:country":"IT",
    "sg:address":"80134 Napoli",
    "sg:city":"Napoli",
    "sg:orig_category":"Parrucche E Toupets",
    "sg:phone":"+39 081 551 0000",
    "sg:postcode":"80134",
    "sg:province":"Napoli",
    "wof:name":"I.c.m. Di Miranda Caterina",
    "wof:placetype":"venue"
},
  "geometry": {"coordinates":[14.2503728867,40.8461608887],"type":"Point"}
}