{
  "type": "Feature",
  "properties": {
    "iso:country":"IT",
    "sg:address":"43012 Fontanellato",
    "sg:city":"Fontanellato",
    "sg:classifiers":[
        {
            "category":"Professional",
            "subcategory":"Management & Consulting",
            "type":"Services"
        }
    ],
    "sg:phone":"+39 0521 822853",
    "sg:postcode":"43012",
    "sg:province":"Parma",
    "sg:tags":[
        "business",
        "technical",
        "consultant",
        "administration",
        "consultancies",
        "administrative",
        "appraiser"
    ],
    "wof:name":"Ziliotti Dr. Vincenzo",
    "wof:placetype":"venue"
},
  "geometry": {"coordinates":[10.028778,44.441277],"type":"Point"}
}