{
  "type": "Feature",
  "properties": {
    "addr:full":"8, Via Del Lavoro 40033 Casalecchio Di Reno Casalecchio di Reno Bologna 40033",
    "addr:postcode":"40033;40033",
    "addr:street":"Via Del Lavoro;Di Reno",
    "iso:country":"IT",
    "sg:address":"8, Via Del Lavoro 40033 Casalecchio Di Reno",
    "sg:city":"Casalecchio di Reno",
    "sg:classifiers":[
        {
            "category":"Professional",
            "subcategory":"Business Services",
            "type":"Services"
        }
    ],
    "sg:phone":"+39 39051596111",
    "sg:postcode":"40033",
    "sg:province":"Bologna",
    "sg:tags":[
        "advice"
    ],
    "wof:name":"Coop Italia Soc.coop. A R.l.",
    "wof:placetype":"venue"
},
  "geometry": {"coordinates":[11.266842,44.480091],"type":"Point"}
}