{
  "type": "Feature",
  "properties": {
    "iso:country":"IT",
    "sg:address":"24060 Adrara San Rocco",
    "sg:city":"Adrara San Rocco",
    "sg:orig_category":"Prodotti E Manufatti In Gomma",
    "sg:phone":"+39 035 934241",
    "sg:postcode":"24060",
    "sg:province":"Bergamo",
    "wof:name":"Cma",
    "wof:placetype":"venue"
},
  "geometry": {"coordinates":[9.9601669312,45.7167205811],"type":"Point"}
}