{
  "type": "Feature",
  "properties": {
    "addr:full":"20026 Novate Milanese Novate Milanese Milano 20026",
    "addr:postcode":"20026;20026",
    "iso:country":"IT",
    "sg:address":"20026 Novate Milanese",
    "sg:city":"Novate Milanese",
    "sg:orig_category":"Cavi E Conduttori Elettrici E Telefonici",
    "sg:phone":"+39 02 3820 1030",
    "sg:postcode":"20026",
    "sg:province":"Milano",
    "sg:website":"http://www.salvi-spa.com",
    "wof:name":"Salvi Spa",
    "wof:placetype":"venue"
},
  "geometry": {"coordinates":[9.13502,45.52766],"type":"Point"}
}