{
  "type": "Feature",
  "properties": {
    "iso:country":"IT",
    "sg:address":"42, Viale Piave 20129 Milano",
    "sg:city":"Milano",
    "sg:classifiers":[
        {
            "category":"Travel",
            "subcategory":"Travel Agent",
            "type":"Entertainment"
        }
    ],
    "sg:phone":"+39 390 220 581",
    "sg:postcode":"20129",
    "sg:province":"Milano",
    "sg:tags":[
        "business"
    ],
    "wof:name":"Hotel Diana Majestic",
    "wof:placetype":"venue"
},
  "geometry": {"coordinates":[9.206573,45.473869],"type":"Point"}
}