{
  "type": "Feature",
  "properties": {
    "addr:full":"25065 Lumezzane Lumezzane Brescia 25065",
    "addr:postcode":"25065;25065",
    "iso:country":"IT",
    "sg:address":"25065 Lumezzane",
    "sg:city":"Lumezzane",
    "sg:orig_category":"Servizi Ausiliari Di Analisi, Controllo E Ricerca. Acqua, Luce, Gas E Societa' Di Esercizio Pubblico",
    "sg:phone":"+39 030 829109",
    "sg:postcode":"25065",
    "sg:province":"Brescia",
    "wof:name":"Centro Studi E Ricerche Serafino Zani",
    "wof:placetype":"venue"
},
  "geometry": {"coordinates":[10.204735,45.609615],"type":"Point"}
}