{
  "type": "Feature",
  "properties": {
    "iso:country":"IT",
    "sg:address":"27, Via Palmieri Pietro 10138 Torino",
    "sg:city":"Torino",
    "sg:classifiers":[
        {
            "category":"Utilities",
            "subcategory":"Electric",
            "type":"Services"
        }
    ],
    "sg:phone":"+39 011 440 4444",
    "sg:postcode":"10138",
    "sg:province":"Torino",
    "sg:tags":[
        "component",
        "electronic"
    ],
    "wof:name":"Sisram S.p.a.",
    "wof:placetype":"venue"
},
  "geometry": {"coordinates":[7.661274,45.075626],"type":"Point"}
}