{
  "type": "Feature",
  "properties": {
    "iso:country":"IT",
    "sg:address":"20020 Lainate",
    "sg:city":"Lainate",
    "sg:classifiers":[
        {
            "category":"Manufacturing",
            "subcategory":"Rubber & Plastics",
            "type":"Manufacturing & Wholesale Goods"
        }
    ],
    "sg:phone":"+39 02 937 2090",
    "sg:postcode":"20020",
    "sg:province":"Milano",
    "sg:tags":[
        "article",
        "product"
    ],
    "sg:website":"http://www.rubbermax.com",
    "wof:name":"Rubbermax Srl Trafilati In Gomma E Silicone",
    "wof:placetype":"venue"
},
  "geometry": {"coordinates":[9.028877,45.570511],"type":"Point"}
}