{
  "type": "Feature",
  "properties": {
    "iso:country":"IT",
    "sg:address":"05024 Giove",
    "sg:city":"Giove",
    "sg:orig_category":"Discoteche, Locali Notturni E Sale Da Ballo",
    "sg:phone":"+39 0744 992827",
    "sg:postcode":"05024",
    "sg:province":"Terni",
    "wof:name":"Disa Srl",
    "wof:placetype":"venue"
},
  "geometry": {"coordinates":[12.329207,42.503345],"type":"Point"}
}