{
  "type": "Feature",
  "properties": {
    "iso:country":"IT",
    "sg:address":"5, Via Buttrio 33100 Udine",
    "sg:city":"Udine",
    "sg:classifiers":[
        {
            "category":"Professional",
            "subcategory":"Engineering",
            "type":"Services"
        }
    ],
    "sg:phone":"+39 0432 299556",
    "sg:postcode":"33100",
    "sg:province":"Udine",
    "sg:tags":[
        "machine",
        "-",
        "mechanical"
    ],
    "wof:name":"Intec Di Santini S.n.c.",
    "wof:placetype":"venue"
},
  "geometry": {"coordinates":[13.275155,46.04673],"type":"Point"}
}