{
  "type": "Feature",
  "properties": {
    "iso:country":"IT",
    "sg:address":"Viale Roma 20; Sestri Levante",
    "sg:classifiers":[
        {
            "category":"Banks & Credit Unions",
            "subcategory":"Bank",
            "type":"Services"
        }
    ],
    "sg:phone":"+39 0185 487352",
    "wof:name":"Banca Di Roma",
    "wof:placetype":"venue"
},
  "geometry": {"coordinates":[9.396237,44.274818],"type":"Point"}
}