{
  "type": "Feature",
  "properties": {
    "iso:country":"IT",
    "sg:address":"Strada Stale Sannitica Km 10 80024 Cardito",
    "sg:city":"Cardito",
    "sg:orig_category":"Fish, Frozen",
    "sg:phone":"+39 081 831 5432",
    "sg:postcode":"80024",
    "sg:province":"Napoli",
    "wof:name":"Avistar Fish Sas",
    "wof:placetype":"venue"
},
  "geometry": {"coordinates":[14.2516355515,40.84009552],"type":"Point"}
}