{
  "type": "Feature",
  "properties": {
    "addr:full":"87069 San Demetrio Corone San Demetrio Corone Cosenza 87069",
    "addr:housenumber":"87069",
    "addr:postcode":"demetrio corone;87069",
    "addr:street":"San;Demetrio Corone",
    "iso:country":"IT",
    "sg:address":"87069 San Demetrio Corone",
    "sg:city":"San Demetrio Corone",
    "sg:orig_category":"Aziende Agricole",
    "sg:phone":"+39 0984 956025",
    "sg:postcode":"87069",
    "sg:province":"Cosenza",
    "wof:name":"Azienda Agricola E Frantoio Oleario Bellucci Leopoldo",
    "wof:placetype":"venue"
},
  "geometry": {"coordinates":[16.36002,39.569801],"type":"Point"}
}