{
  "type": "Feature",
  "properties": {
    "addr:full":"Cso Torino 95 10019 Strambino Strambino Torino 10019",
    "addr:housenumber":"95",
    "addr:postcode":"10019;10019",
    "addr:street":"Cso",
    "iso:country":"IT",
    "sg:address":"Cso Torino 95 10019 Strambino",
    "sg:city":"Strambino",
    "sg:classifiers":[
        {
            "category":"Wholesale",
            "subcategory":"Vending Machines",
            "type":"Manufacturing & Wholesale Goods"
        }
    ],
    "sg:phone":"+39 0125 637034",
    "sg:postcode":"10019",
    "sg:province":"Torino",
    "sg:tags":[
        "modelling"
    ],
    "wof:name":"Tecno Di Cerino Graziano",
    "wof:placetype":"venue"
},
  "geometry": {"coordinates":[7.830617,45.487606],"type":"Point"}
}