{
  "type": "Feature",
  "properties": {
    "iso:country":"IT",
    "sg:address":"40037 Sasso Marconi",
    "sg:city":"Sasso Marconi",
    "sg:orig_category":"Macchine E Forniture Per Arredamento E Industria Del Legno. Utensili Meccanici E Materiali",
    "sg:phone":"+39 051 678 1462",
    "sg:postcode":"40037",
    "sg:province":"Bologna",
    "wof:name":"Fiober S.n.c.",
    "wof:placetype":"venue"
},
  "geometry": {"coordinates":[11.274828,44.444244],"type":"Point"}
}