{
  "type": "Feature",
  "properties": {
    "iso:country":"IT",
    "sg:address":"25033 Cologne",
    "sg:city":"Cologne",
    "sg:orig_category":"Acciaierie E Fonderie",
    "sg:phone":"+39 030 715403",
    "sg:postcode":"25033",
    "sg:province":"Brescia",
    "wof:name":"Spinola Riccardo",
    "wof:placetype":"venue"
},
  "geometry": {"coordinates":[10.158787,45.519024],"type":"Point"}
}