{
  "type": "Feature",
  "properties": {
    "addr:full":"4/a, Via Sforza Cesarini 43100 Parma Parma Parma 43100",
    "addr:housenumber":"4 / a",
    "addr:postcode":"43100;43100",
    "addr:street":"Via Sforza Cesarini",
    "iso:country":"IT",
    "sg:address":"4/a, Via Sforza Cesarini 43100 Parma",
    "sg:city":"Parma",
    "sg:classifiers":[
        {
            "category":"Manufacturing",
            "subcategory":"Food",
            "type":"Manufacturing & Wholesale Goods"
        }
    ],
    "sg:phone":"+39 0521 631193",
    "sg:postcode":"43100",
    "sg:province":"Parma",
    "sg:tags":[
        "equipment",
        "processing",
        "-",
        "machinery"
    ],
    "wof:name":"Tecnica Inox Meccanica Srl",
    "wof:placetype":"venue"
},
  "geometry": {"coordinates":[10.2949199677,44.8232078552],"type":"Point"}
}