{
  "type": "Feature",
  "properties": {
    "iso:country":"IT",
    "sg:address":"1, Via Giuseppe Di Vittorio 06038 Spello",
    "sg:city":"Spello",
    "sg:classifiers":[
        {
            "category":"Professional",
            "subcategory":"Engineering",
            "type":"Services"
        }
    ],
    "sg:phone":"+39 0742 301904",
    "sg:postcode":"06038",
    "sg:province":"Perugia",
    "sg:tags":[
        "machine",
        "-",
        "mechanical"
    ],
    "wof:name":"Bartolini S.r.l.",
    "wof:placetype":"venue"
},
  "geometry": {"coordinates":[12.663355,42.993462],"type":"Point"}
}