{
  "type": "Feature",
  "properties": {
    "iso:country":"IT",
    "sg:address":"22, Via Ariosto Ludovico 35010 Vigonza",
    "sg:city":"Vigonza",
    "sg:classifiers":[
        {
            "category":"Professional",
            "subcategory":"Business Services",
            "type":"Services"
        }
    ],
    "sg:phone":"+39 049 809 5654",
    "sg:postcode":"35010",
    "sg:province":"Padova",
    "sg:tags":[
        "advice"
    ],
    "wof:name":"Scipioni Anna (s.r.l.)",
    "wof:placetype":"venue"
},
  "geometry": {"coordinates":[11.90606,45.451401],"type":"Point"}
}