{
  "type": "Feature",
  "properties": {
    "iso:country":"IT",
    "sg:address":"42020 Quattro Castella",
    "sg:orig_category":"Apparecchiature E Sistemi Per Magazzinaggio E Movimentazione",
    "sg:phone":"+39 0522 888121",
    "sg:postcode":"42020",
    "sg:province":"Reggio Nell'Emilia",
    "sg:website":"http://www.matter.it",
    "wof:name":"Matter Srl",
    "wof:placetype":"venue"
},
  "geometry": {"coordinates":[10.627794,44.696228],"type":"Point"}
}