{
  "type": "Feature",
  "properties": {
    "addr:full":"21015 Lonate Pozzolo Lonate Pozzolo Varese 21015",
    "addr:postcode":"21015;21015",
    "iso:country":"IT",
    "sg:address":"21015 Lonate Pozzolo",
    "sg:city":"Lonate Pozzolo",
    "sg:orig_category":"Magazzinaggio E Logistica Industriale - Impianti Ed Attrezzature",
    "sg:phone":"+39 0331 669168",
    "sg:postcode":"21015",
    "sg:province":"Varese",
    "sg:website":"http://www.leonarditrasporti.com",
    "wof:name":"Leonardi Trasporti Nazionali Con Gru Di Leonardi E. & C. Sas",
    "wof:placetype":"venue"
},
  "geometry": {"coordinates":[8.739009,45.596092],"type":"Point"}
}