{
  "type": "Feature",
  "properties": {
    "iso:country":"IT",
    "sg:address":"00186 Roma",
    "sg:city":"Roma",
    "sg:orig_category":"Cartotecnica E Servizi. Composizione, Stampa E Confezione. Servizi E Lavori Industria Delle Materie Plastiche. Servizi Per Imballaggio E Confezionamento",
    "sg:phone":"+39 06 6880 4763",
    "sg:postcode":"00186",
    "sg:province":"Roma",
    "wof:name":"Agenzia Arenula Di Aliperti Giuseppe",
    "wof:placetype":"venue"
},
  "geometry": {"coordinates":[12.474656,41.893017],"type":"Point"}
}