{
  "type": "Feature",
  "properties": {
    "iso:country":"IT",
    "sg:address":"Piazza S. Maria Nuova; Asti; 14100",
    "sg:city":"Asti",
    "sg:classifiers":[
        {
            "category":"Banks & Credit Unions",
            "subcategory":"Bank",
            "type":"Services"
        }
    ],
    "sg:phone":"+39 0141 352402",
    "sg:postcode":"14100",
    "sg:province":"Asti",
    "wof:name":"Banco Di Roma",
    "wof:placetype":"venue"
},
  "geometry": {"coordinates":[8.208958,44.901371],"type":"Point"}
}