{
  "type": "Feature",
  "properties": {
    "addr:full":"70056 Molfetta Molfetta Bari 70056",
    "addr:postcode":"70056;70056",
    "iso:country":"IT",
    "sg:address":"70056 Molfetta",
    "sg:city":"Molfetta",
    "sg:orig_category":"Cosmetici, Prodotti Di Bellezza E Di Igiene",
    "sg:phone":"+39 080 338 7853",
    "sg:postcode":"70056",
    "sg:province":"Bari",
    "wof:name":"Italian Style Due Srl",
    "wof:placetype":"venue"
},
  "geometry": {"coordinates":[16.59017,41.195049],"type":"Point"}
}