{
  "type": "Feature",
  "properties": {
    "iso:country":"IT",
    "sg:address":"28, Via Zara 20096 Pioltello",
    "sg:city":"Pioltello",
    "sg:classifiers":[
        {
            "category":"Manufacturing",
            "subcategory":"Metals",
            "type":"Manufacturing & Wholesale Goods"
        }
    ],
    "sg:phone":"+39 02 9216 2705",
    "sg:postcode":"20096",
    "sg:province":"Milano",
    "sg:tags":[
        "processing"
    ],
    "wof:name":"Tvc Torneria Di Vigano' Carlo & C. Snc",
    "wof:placetype":"venue"
},
  "geometry": {"coordinates":[9.3146696091,45.4942779541],"type":"Point"}
}