{
  "type": "Feature",
  "properties": {
    "addr:full":"226, Via Statale 41014 Castelvetro Modena 41014",
    "addr:housenumber":"226",
    "addr:postcode":"41014;41014",
    "addr:street":"Via Statale",
    "iso:country":"IT",
    "sg:address":"226, Via Statale 41014 Castelvetro",
    "sg:classifiers":[
        {
            "category":"Shopping",
            "subcategory":"Crafts & Fabrics",
            "type":"Retail Goods"
        }
    ],
    "sg:phone":"+39 39059748118",
    "sg:postcode":"41014",
    "sg:province":"Modena",
    "sg:tags":[
        "ceramic"
    ],
    "wof:name":"Sir Tiles - Spa",
    "wof:placetype":"venue"
},
  "geometry": {"coordinates":[10.950952,44.531097],"type":"Point"}
}