{
  "type": "Feature",
  "properties": {
    "addr:full":"Via Montello, 6; Castel Goffredo; 46042 Castel Goffredo Mantova 46042",
    "addr:housenumber":"6",
    "addr:postcode":"46042;46042",
    "addr:street":"Via Montello;Goffredo",
    "iso:country":"IT",
    "sg:address":"Via Montello, 6; Castel Goffredo; 46042",
    "sg:city":"Castel Goffredo",
    "sg:classifiers":[
        {
            "category":"Banks & Credit Unions",
            "subcategory":"Bank",
            "type":"Services"
        }
    ],
    "sg:phone":"+39 0376 780687",
    "sg:postcode":"46042",
    "sg:province":"Mantova",
    "wof:name":"Banca Agricola Mantovana",
    "wof:placetype":"venue"
},
  "geometry": {"coordinates":[10.472525,45.298164],"type":"Point"}
}