{
  "type": "Feature",
  "properties": {
    "iso:country":"IT",
    "sg:address":"91100 Trapani",
    "sg:city":"Trapani",
    "sg:classifiers":[
        {
            "category":"Building & Trades",
            "subcategory":"Pest Control",
            "type":"Services"
        }
    ],
    "sg:phone":"+39 0923 27731",
    "sg:postcode":"91100",
    "sg:province":"Trapani",
    "sg:tags":[
        "saline",
        "e",
        "sale",
        "miniere",
        "di"
    ],
    "wof:name":"S.i.e.s. Spa",
    "wof:placetype":"venue"
},
  "geometry": {"coordinates":[12.517059,38.015591],"type":"Point"}
}