{
  "type": "Feature",
  "properties": {
    "iso:country":"IT",
    "sg:address":"37045 Legnago",
    "sg:city":"Legnago",
    "sg:orig_category":"Manufacturers: Prefabbricati",
    "sg:phone":"+39 0442 22961",
    "sg:postcode":"37045",
    "sg:province":"Verona",
    "wof:name":"Trentin Pietro Giorgio",
    "wof:placetype":"venue"
},
  "geometry": {"coordinates":[11.316556,45.197784],"type":"Point"}
}