{
  "type": "Feature",
  "properties": {
    "iso:country":"IT",
    "sg:address":"15057 Tortona",
    "sg:city":"Tortona",
    "sg:orig_category":"Trasporti E Spedizioni Merci",
    "sg:phone":"+39 0131 868033",
    "sg:postcode":"15057",
    "sg:province":"Alessandria",
    "wof:name":"Emmegi Di Mangione Giorgio",
    "wof:placetype":"venue"
},
  "geometry": {"coordinates":[8.843711,44.900482],"type":"Point"}
}