{
  "type": "Feature",
  "properties": {
    "iso:country":"IT",
    "sg:address":"72014 Cisternino",
    "sg:city":"Cisternino",
    "sg:orig_category":"Accessori Dei Mezzi Di Trasporto",
    "sg:phone":"+39 080 444 6791",
    "sg:postcode":"72014",
    "sg:province":"Brindisi",
    "wof:name":"Autoaccessori Fusillo Di Fusillo Antonio",
    "wof:placetype":"venue"
},
  "geometry": {"coordinates":[17.429415,40.741615],"type":"Point"}
}