{
  "type": "Feature",
  "properties": {
    "iso:country":"IT",
    "sg:address":"Via Torino 9 20032 Cormano",
    "sg:city":"Cormano",
    "sg:classifiers":[
        {
            "category":"Autos & Motor Vehicles",
            "subcategory":"Boat Sales",
            "type":"Retail Goods"
        }
    ],
    "sg:phone":"+39 02 615 1142",
    "sg:postcode":"20032",
    "sg:province":"Milano",
    "sg:tags":[
        "girder",
        "forming",
        "pipe",
        "machine",
        "drawing",
        "machines"
    ],
    "wof:name":"Ing. V. & P. Rizzi Srl",
    "wof:placetype":"venue"
},
  "geometry": {"coordinates":[9.1570272446,45.5342178345],"type":"Point"}
}