{
  "type": "Feature",
  "properties": {
    "addr:full":"27, Via Colombo Cristoforo 24046 Osio Sotto Osio Sotto Bergamo 24046",
    "addr:postcode":"24046;24046",
    "addr:street":"Via Colombo Cristoforo",
    "iso:country":"IT",
    "sg:address":"27, Via Colombo Cristoforo 24046 Osio Sotto",
    "sg:city":"Osio Sotto",
    "sg:classifiers":[
        {
            "category":"Manufacturing",
            "subcategory":"Metals",
            "type":"Manufacturing & Wholesale Goods"
        }
    ],
    "sg:phone":"+39 39035808143",
    "sg:postcode":"24046",
    "sg:province":"Bergamo",
    "sg:tags":[
        "processing"
    ],
    "wof:name":"Italveber (s.r.l.)",
    "wof:placetype":"venue"
},
  "geometry": {"coordinates":[9.6581945419,45.6471786499],"type":"Point"}
}