{
  "type": "Feature",
  "properties": {
    "iso:country":"IT",
    "sg:address":"36027 Rosa'",
    "sg:orig_category":"Impiantistica E Prodotti Tecnologici Per Edilizia. Elettronica Professionale E Di Consumo. Accessori Dei Mezzi Di Trasporto. Forniture Industriali Per Prevenzione, Controllo E Sicurezza",
    "sg:phone":"+39 0424 85343",
    "sg:postcode":"36027",
    "sg:province":"Vicenza",
    "wof:name":"Elettrorosa' Srl",
    "wof:placetype":"venue"
},
  "geometry": {"coordinates":[11.824366,45.671757],"type":"Point"}
}