{
  "type": "Feature",
  "properties": {
    "iso:country":"IT",
    "sg:address":"Dolomitenstr. 16; Sexten; 39030",
    "sg:classifiers":[
        {
            "category":"Banks & Credit Unions",
            "subcategory":"Bank",
            "type":"Services"
        }
    ],
    "sg:phone":"+39 0474 70327",
    "sg:postcode":"39030",
    "sg:province":"Bolzano/Bozen",
    "wof:name":"Raiffeisenkasse Hochpustertal",
    "wof:placetype":"venue"
},
  "geometry": {"coordinates":[12.355028,46.697849],"type":"Point"}
}