{
  "type": "Feature",
  "properties": {
    "iso:country":"IT",
    "sg:address":"00069 Trevignano Romano",
    "sg:city":"Trevignano Romano",
    "sg:orig_category":"Servizi Editoriali. Pubblicita', Marketing E Comunicazione",
    "sg:phone":"+39 06 9991 0266",
    "sg:postcode":"00069",
    "sg:province":"Roma",
    "wof:name":"Mediamed Srl",
    "wof:placetype":"venue"
},
  "geometry": {"coordinates":[12.266237,42.15601],"type":"Point"}
}