{
  "type": "Feature",
  "properties": {
    "addr:full":"28881 Casale Corte Cerro Casale Corte Cerro Verbano-Cusio-Ossola 28881",
    "addr:postcode":"28881;28881",
    "addr:street":"Corte Cerro Casale Corte Cerro Verbano-Cusio-Ossola",
    "iso:country":"IT",
    "sg:address":"28881 Casale Corte Cerro",
    "sg:city":"Casale Corte Cerro",
    "sg:orig_category":"Metalli E Leghe",
    "sg:phone":"+39 0323 60233",
    "sg:postcode":"28881",
    "sg:province":"Verbano-Cusio-Ossola",
    "wof:name":"Zami 1950 S.r.l.",
    "wof:placetype":"venue"
},
  "geometry": {"coordinates":[8.419631958,45.9095306396],"type":"Point"}
}