{
  "type": "Feature",
  "properties": {
    "iso:country":"IT",
    "sg:address":"00161 Roma",
    "sg:city":"Roma",
    "sg:orig_category":"Petroli, Gas E Combustibili",
    "sg:phone":"+39 06 4423 2172",
    "sg:postcode":"00161",
    "sg:province":"Roma",
    "wof:name":"D.i.c.a. (s.a.s.)",
    "wof:placetype":"venue"
},
  "geometry": {"coordinates":[12.5144615173,41.9140968323],"type":"Point"}
}