{
  "type": "Feature",
  "properties": {
    "iso:country":"IT",
    "sg:address":"46, Via Roma 73040 Neviano",
    "sg:city":"Neviano",
    "sg:classifiers":[
        {
            "category":"Sports & Exercise",
            "subcategory":"Playing Field",
            "type":"Entertainment"
        }
    ],
    "sg:phone":"+39 0836 610481",
    "sg:postcode":"73040",
    "sg:province":"Lecce",
    "sg:tags":[
        "game"
    ],
    "wof:name":"Chirivi' Giancarlo",
    "wof:placetype":"venue"
},
  "geometry": {"coordinates":[18.114265,40.109543],"type":"Point"}
}