{
  "type": "Feature",
  "properties": {
    "addr:full":"Via Vespucci Amerigo 24046 Osio Sotto Osio Sotto Bergamo 24046",
    "addr:postcode":"24046;24046",
    "addr:street":"Via Vespucci Amerigo",
    "iso:country":"IT",
    "sg:address":"Via Vespucci Amerigo 24046 Osio Sotto",
    "sg:city":"Osio Sotto",
    "sg:classifiers":[
        {
            "category":"Manufacturing",
            "subcategory":"Metals",
            "type":"Manufacturing & Wholesale Goods"
        }
    ],
    "sg:phone":"+39 035 482 3343",
    "sg:postcode":"24046",
    "sg:province":"Bergamo",
    "sg:tags":[
        "processing"
    ],
    "wof:name":"I.p. Industrial Paintings (s.p.a.)",
    "wof:placetype":"venue"
},
  "geometry": {"coordinates":[9.6561441422,45.647857666],"type":"Point"}
}