{
  "type": "Feature",
  "properties": {
    "iso:country":"IT",
    "sg:address":"10, Vl. Europa 25046 Cazzago San Martino",
    "sg:city":"Cazzago San Martino",
    "sg:classifiers":[
        {
            "category":"Wholesale",
            "subcategory":"Drugs",
            "type":"Manufacturing & Wholesale Goods"
        }
    ],
    "sg:phone":"+39 030 775 0570",
    "sg:postcode":"25046",
    "sg:province":"Brescia",
    "sg:tags":[
        "chemical",
        "pharmaceutical"
    ],
    "sg:website":"http://www.eurovix.it",
    "wof:name":"Eurovix Srl",
    "wof:placetype":"venue"
},
  "geometry": {"coordinates":[10.035379,45.571712],"type":"Point"}
}