{
  "type": "Feature",
  "properties": {
    "iso:country":"IT",
    "sg:address":"Via Fermi 6 34071 Cormons",
    "sg:city":"Cormons",
    "sg:classifiers":[
        {
            "category":"Manufacturing",
            "subcategory":"Rubber & Plastics",
            "type":"Manufacturing & Wholesale Goods"
        }
    ],
    "sg:phone":"+39 0481 637311",
    "sg:postcode":"34071",
    "sg:province":"Gorizia",
    "sg:tags":[
        "metal",
        "electronics",
        "electrotechnology",
        "component",
        "assembled"
    ],
    "sg:website":"www.astrel.it",
    "wof:name":"Astrel Spa",
    "wof:placetype":"venue"
},
  "geometry": {"coordinates":[13.621546,45.941303],"type":"Point"}
}