{
  "type": "Feature",
  "properties": {
    "iso:country":"IT",
    "sg:address":"1, Via Monte Amiata 37057 San Giovanni Lupatoto",
    "sg:city":"San Giovanni Lupatoto",
    "sg:classifiers":[
        {
            "category":"Manufacturing",
            "subcategory":"Metals",
            "type":"Manufacturing & Wholesale Goods"
        }
    ],
    "sg:phone":"+39 045 826 6566",
    "sg:postcode":"37057",
    "sg:province":"Verona",
    "sg:tags":[
        "metallurgy",
        "metalworking"
    ],
    "wof:name":"Ferramenta Veneta Spa",
    "wof:placetype":"venue"
},
  "geometry": {"coordinates":[11.0136642456,45.3954620361],"type":"Point"}
}