{
  "type": "Feature",
  "properties": {
    "addr:full":"Via Torino, 5/7/9 51011 Buggiano Buggiano Pistoia 51011",
    "addr:housenumber":"5 / 7 / 9",
    "addr:postcode":"51011;51011",
    "addr:street":"Via Torino",
    "iso:country":"IT",
    "sg:address":"Via Torino, 5/7/9 51011 Buggiano",
    "sg:city":"Buggiano",
    "sg:classifiers":[
        {
            "category":"Government",
            "subcategory":"Post Office",
            "type":"Public Place"
        }
    ],
    "sg:phone":"+39 0572 32985",
    "sg:postcode":"51011",
    "sg:province":"Pistoia",
    "sg:tags":[
        "illumination",
        "power",
        "emergency",
        "supply"
    ],
    "sg:website":"www.ismos.it",
    "wof:name":"Ismos Illuminazione Srl",
    "wof:placetype":"venue"
},
  "geometry": {"coordinates":[10.918524,43.932156],"type":"Point"}
}