{
  "type": "Feature",
  "properties": {
    "addr:full":"Via Roncaglia, 5 - Comenduno 24021 Albino Albino Bergamo 24021",
    "addr:housenumber":"5",
    "addr:postcode":"24021;24021",
    "addr:street":"Via Roncaglia",
    "iso:country":"IT",
    "sg:address":"Via Roncaglia, 5 - Comenduno 24021 Albino",
    "sg:city":"Albino",
    "sg:orig_category":"Hotels: Equipment",
    "sg:phone":"+39 035 751426",
    "sg:postcode":"24021",
    "sg:province":"Bergamo",
    "sg:website":"www.euroceppi.com",
    "wof:name":"Euroceppi Srl",
    "wof:placetype":"venue"
},
  "geometry": {"coordinates":[9.81935,45.777843],"type":"Point"}
}