{
  "type": "Feature",
  "properties": {
    "iso:country":"IT",
    "sg:address":"46030 Borgoforte",
    "sg:city":"Borgoforte",
    "sg:orig_category":"Elettrotecnica Industriale, Prodotti E Apparecchiature",
    "sg:phone":"+39 0376 649232",
    "sg:postcode":"46030",
    "sg:province":"Mantova",
    "sg:website":"http://www.brigiotti.com",
    "wof:name":"Brigiotti Elio",
    "wof:placetype":"venue"
},
  "geometry": {"coordinates":[10.760619,45.070282],"type":"Point"}
}