{
  "type": "Feature",
  "properties": {
    "addr:full":"3, Via Dosso Faiti 22066 Mariano Comense Mariano Comense Como 22066",
    "addr:postcode":"22066;22066",
    "addr:street":"Via Dosso Faiti",
    "iso:country":"IT",
    "sg:address":"3, Via Dosso Faiti 22066 Mariano Comense",
    "sg:city":"Mariano Comense",
    "sg:classifiers":[
        {
            "category":"Manufacturing",
            "subcategory":"Lumber",
            "type":"Manufacturing & Wholesale Goods"
        }
    ],
    "sg:phone":"+39 39031745412",
    "sg:postcode":"22066",
    "sg:province":"Como",
    "sg:tags":[
        "wood"
    ],
    "wof:name":"Menegolo Luigi E Figli (s.a.s.)",
    "wof:placetype":"venue"
},
  "geometry": {"coordinates":[9.186574,45.69022],"type":"Point"}
}