{
  "type": "Feature",
  "properties": {
    "iso:country":"IT",
    "sg:address":"Via Lombardia 20b 42100 Reggio Emilia",
    "sg:classifiers":[
        {
            "category":"Utilities",
            "subcategory":"Water",
            "type":"Services"
        }
    ],
    "sg:phone":"+39 0522 2387",
    "sg:postcode":"42100",
    "sg:province":"Reggio Nell'Emilia",
    "sg:tags":[
        "component",
        "hydraulic",
        "accessory"
    ],
    "wof:name":"Ferrari International 2 Srl",
    "wof:placetype":"venue"
},
  "geometry": {"coordinates":[10.636703,44.71265],"type":"Point"}
}