{
  "type": "Feature",
  "properties": {
    "addr:full":"33010 Osoppo Osoppo Udine 33010",
    "addr:postcode":"33010;33010",
    "iso:country":"IT",
    "sg:address":"33010 Osoppo",
    "sg:city":"Osoppo",
    "sg:orig_category":"Automobili E Mezzi Di Trasporto",
    "sg:phone":"+39 0432 899111",
    "sg:postcode":"33010",
    "sg:province":"Udine",
    "wof:name":"De Simon S.r.l.",
    "wof:placetype":"venue"
},
  "geometry": {"coordinates":[13.068296,46.22126],"type":"Point"}
}