{
  "type": "Feature",
  "properties": {
    "addr:full":"Via Enrico Berlinguer 26030 Gadesco Pieve Delmona Gadesco Pieve Delmona Cremona 26030",
    "addr:postcode":"26030;26030",
    "addr:street":"Via Enrico Berlinguer;Cremona",
    "iso:country":"IT",
    "sg:address":"Via Enrico Berlinguer 26030 Gadesco Pieve Delmona",
    "sg:city":"Gadesco Pieve Delmona",
    "sg:orig_category":"Miscellaneous Products",
    "sg:phone":"+39 0372 838369",
    "sg:postcode":"26030",
    "sg:province":"Cremona",
    "wof:name":"Lindenberg",
    "wof:placetype":"venue"
},
  "geometry": {"coordinates":[10.1017045975,45.1546707153],"type":"Point"}
}