{
  "type": "Feature",
  "properties": {
    "addr:full":"72100 Brindisi Brindisi Brindisi 72100",
    "addr:postcode":"72100;72100",
    "iso:country":"IT",
    "sg:address":"72100 Brindisi",
    "sg:city":"Brindisi",
    "sg:orig_category":"Prodotti Di Base E Forniture Per Industria Alimentare E Bevande. Carta, Cartone E Prodotti Primari. Forniture Per Attivita' Commerciali Ed Artigianali",
    "sg:phone":"+39 0831 508190",
    "sg:postcode":"72100",
    "sg:province":"Brindisi",
    "wof:name":"Cartapiu' Di Roma Antonio",
    "wof:placetype":"venue"
},
  "geometry": {"coordinates":[17.9298744202,40.6332244873],"type":"Point"}
}