{
  "type": "Feature",
  "properties": {
    "addr:full":"20122 Milano Milano Milano 20122",
    "addr:postcode":"20122;20122",
    "iso:country":"IT",
    "sg:address":"20122 Milano",
    "sg:city":"Milano",
    "sg:orig_category":"Servizi E Lavori Per Abbigliamento E Pelletterie",
    "sg:phone":"+39 02 5518 1703",
    "sg:postcode":"20122",
    "sg:province":"Milano",
    "wof:name":"Algesta (s.r.l.)",
    "wof:placetype":"venue"
},
  "geometry": {"coordinates":[9.200191,45.460724],"type":"Point"}
}