{
  "type": "Feature",
  "properties": {
    "addr:full":"91026 Mazara Del Vallo Mazara del Vallo Trapani 91026",
    "addr:postcode":"91026;91026",
    "iso:country":"IT",
    "sg:address":"91026 Mazara Del Vallo",
    "sg:city":"Mazara del Vallo",
    "sg:orig_category":"Tempo Libero - Articoli E Forniture. Automobili E Mezzi Di Trasporto",
    "sg:phone":"+39 0923 908442",
    "sg:postcode":"91026",
    "sg:province":"Trapani",
    "wof:name":"Giammarinaro Anna",
    "wof:placetype":"venue"
},
  "geometry": {"coordinates":[12.589779,37.655373],"type":"Point"}
}