{
  "type": "Feature",
  "properties": {
    "iso:country":"IT",
    "sg:address":"51037 Montale",
    "sg:city":"Montale",
    "sg:orig_category":"Abbigliamento Esterno, Maglierie E Pelliccerie. Calzature, Pelletterie E Pelli",
    "sg:phone":"+39 0573 959698",
    "sg:postcode":"51037",
    "sg:province":"Pistoia",
    "wof:name":"Bbs Srl",
    "wof:placetype":"venue"
},
  "geometry": {"coordinates":[11.016227,43.922169],"type":"Point"}
}