{
  "type": "Feature",
  "properties": {
    "iso:country":"IT",
    "sg:address":"10099 San Mauro Torinese",
    "sg:city":"San Mauro Torinese",
    "sg:orig_category":"Trasporti E Spedizioni Merci",
    "sg:phone":"+39 011 222 6111",
    "sg:postcode":"10099",
    "sg:province":"Torino",
    "sg:website":"http://www.pony.it",
    "wof:name":"Pony Express",
    "wof:placetype":"venue"
},
  "geometry": {"coordinates":[7.745466,45.115791],"type":"Point"}
}