{
  "type": "Feature",
  "properties": {
    "iso:country":"IT",
    "sg:address":"21020 Cadrezzate",
    "sg:city":"Cadrezzate",
    "sg:orig_category":"Impiantistica E Prodotti Tecnologici Per Edilizia. Elettrotecnica Professionale E Di Consumo. Telecomunicazioni E Telefonia, Impianti, Apparecchi E Servizi",
    "sg:phone":"+39 0331 953578",
    "sg:postcode":"21020",
    "sg:province":"Varese",
    "sg:website":"http://www.bindasat-gift.it",
    "wof:name":"Binda Giuseppe",
    "wof:placetype":"venue"
},
  "geometry": {"coordinates":[8.64419,45.797642],"type":"Point"}
}