{
  "type": "Feature",
  "properties": {
    "iso:country":"IT",
    "sg:address":"Via Conche 35020 Brugine",
    "sg:city":"Brugine",
    "sg:classifiers":[
        {
            "category":"Shopping",
            "subcategory":"Computers & Home Electronics",
            "type":"Retail Goods"
        }
    ],
    "sg:phone":"+39 049 973 5016",
    "sg:postcode":"35020",
    "sg:province":"Padova",
    "sg:tags":[
        "electronic",
        "electrical",
        "equipment"
    ],
    "wof:name":"Zecchin",
    "wof:placetype":"venue"
},
  "geometry": {"coordinates":[11.986857,45.276333],"type":"Point"}
}