{
  "type": "Feature",
  "properties": {
    "addr:full":"06049 Spoleto Spoleto Perugia 06049",
    "addr:postcode":"06049;06049",
    "iso:country":"IT",
    "sg:address":"06049 Spoleto",
    "sg:city":"Spoleto",
    "sg:orig_category":"Distributors: Automatici - Commercio E Gestione",
    "sg:phone":"+39 0743 224575",
    "sg:postcode":"06049",
    "sg:province":"Perugia",
    "wof:name":"D.a. Distribuzione Automatica Srl",
    "wof:placetype":"venue"
},
  "geometry": {"coordinates":[12.85237,42.953129],"type":"Point"}
}