{
  "type": "Feature",
  "properties": {
    "iso:country":"IT",
    "sg:address":"66010 Torrevecchia Teatina",
    "sg:city":"Torrevecchia Teatina",
    "sg:orig_category":"Fiori E Piante - Ingrosso",
    "sg:phone":"+39 0871 360226",
    "sg:postcode":"66010",
    "sg:province":"Chieti",
    "wof:name":"Vivaio Cuore Verde",
    "wof:placetype":"venue"
},
  "geometry": {"coordinates":[14.2556629181,42.3858718872],"type":"Point"}
}