{
  "type": "Feature",
  "properties": {
    "addr:full":"Str. Prov. Mola Mola di Bari Bari 70042",
    "addr:postcode":"70042",
    "addr:street":"Str. Prov. Mola",
    "iso:country":"IT",
    "sg:address":"Str. Prov. Mola",
    "sg:city":"Mola di Bari",
    "sg:classifiers":[
        {
            "category":"Banks & Credit Unions",
            "subcategory":"Investment Brokerage",
            "type":"Services"
        }
    ],
    "sg:phone":"+39 080 474 1975",
    "sg:postcode":"70042",
    "sg:province":"Bari",
    "sg:tags":[
        "work",
        "marble"
    ],
    "wof:name":"Romagno Marmi S.r.l.",
    "wof:placetype":"venue"
},
  "geometry": {"coordinates":[17.065756,41.043667],"type":"Point"}
}