{
  "type": "Feature",
  "properties": {
    "iso:country":"IT",
    "sg:address":"29, Viale Vicenza 36045 Lonigo",
    "sg:city":"Lonigo",
    "sg:classifiers":[
        {
            "category":"Food & Beverages",
            "subcategory":"Groceries & Convenience Stores",
            "type":"Retail Goods"
        }
    ],
    "sg:phone":"+39 0444 436420",
    "sg:postcode":"36045",
    "sg:province":"Vicenza",
    "sg:tags":[
        "drink"
    ],
    "wof:name":"Cantine Dei Colli Berici (soc.coop.r.l.)",
    "wof:placetype":"venue"
},
  "geometry": {"coordinates":[11.393257,45.394417],"type":"Point"}
}