{
  "type": "Feature",
  "properties": {
    "addr:full":"10155 Torino Torino Torino 10155",
    "addr:postcode":"10155;10155",
    "iso:country":"IT",
    "sg:address":"10155 Torino",
    "sg:city":"Torino",
    "sg:orig_category":"Abbigliamento Esterno, Maglierie E Pelliccerie. Forniture Industriali Per Prevenzione, Controllo E Sicurezza",
    "sg:phone":"+39 011 205 2223",
    "sg:postcode":"10155",
    "sg:province":"Torino",
    "wof:name":"Abaf Snc",
    "wof:placetype":"venue"
},
  "geometry": {"coordinates":[7.692299,45.099133],"type":"Point"}
}