{
  "type": "Feature",
  "properties": {
    "addr:full":"00136 Roma Roma Roma 00136",
    "addr:postcode":"00136;00136",
    "iso:country":"IT",
    "sg:address":"00136 Roma",
    "sg:city":"Roma",
    "sg:orig_category":"Palestre",
    "sg:phone":"+39 06 3534 3711",
    "sg:postcode":"00136",
    "sg:province":"Roma",
    "wof:name":"Kgm Lazio",
    "wof:placetype":"venue"
},
  "geometry": {"coordinates":[12.443944931,41.9223365784],"type":"Point"}
}