{
  "type": "Feature",
  "properties": {
    "addr:full":"Via Dei Galla E; Roma; 00199 Roma Roma 00199",
    "addr:postcode":"00199;00199",
    "addr:street":"Via Dei Galla E Roma",
    "iso:country":"IT",
    "sg:address":"Via Dei Galla E; Roma; 00199",
    "sg:city":"Roma",
    "sg:classifiers":[
        {
            "category":"Banks & Credit Unions",
            "subcategory":"Bank",
            "type":"Services"
        }
    ],
    "sg:phone":"+39 06 839 1662",
    "sg:postcode":"00199",
    "sg:province":"Roma",
    "wof:name":"Banca Popolare Dell Marsica Scarl",
    "wof:placetype":"venue"
},
  "geometry": {"coordinates":[12.52288,41.930637],"type":"Point"}
}