{
  "type": "Feature",
  "properties": {
    "iso:country":"IT",
    "sg:address":"17011 Albisola Superiore",
    "sg:city":"Albisola Superiore",
    "sg:orig_category":"Ospedali E Servizi Sanitari. Centri Di Estetica E Cosmesi E Servizi",
    "sg:phone":"+39 019 481170",
    "sg:postcode":"17011",
    "sg:province":"Savona",
    "wof:name":"Centro Podologico Specializzato",
    "wof:placetype":"venue"
},
  "geometry": {"coordinates":[8.51855,44.332382],"type":"Point"}
}