{
  "type": "Feature",
  "properties": {
    "iso:country":"IT",
    "sg:address":"149, V. Garibaldi 21055 Gorla Minore",
    "sg:city":"Gorla Minore",
    "sg:classifiers":[
        {
            "category":"Professional",
            "subcategory":"Engineering",
            "type":"Services"
        }
    ],
    "sg:phone":"+39 0331 601697",
    "sg:postcode":"21055",
    "sg:province":"Varese",
    "sg:tags":[
        "machine",
        "-",
        "mechanical"
    ],
    "sg:website":"http://www.ilclube.com:ws_end: :mark:ws:http://www.paginegialle.it/ilcsrl",
    "wof:name":"I.l.c. Srl",
    "wof:placetype":"venue"
},
  "geometry": {"coordinates":[8.826385,45.817604],"type":"Point"}
}