{
  "type": "Feature",
  "properties": {
    "iso:country":"IT",
    "sg:address":"50059 Vinci",
    "sg:city":"Vinci",
    "sg:orig_category":"Servizi Culturali E Per Lo Spettacolo. Servizi Al Turismo. Acqua, Luce, Gas E Societa' Di Esercizio Pubblico",
    "sg:phone":"+39 0571 56296",
    "sg:postcode":"50059",
    "sg:province":"Firenze",
    "wof:name":"Strumenti Memoria Del Territorio Di A. Vezzosi & C. Sas",
    "wof:placetype":"venue"
},
  "geometry": {"coordinates":[10.924196,43.771671],"type":"Point"}
}