{
  "type": "Feature",
  "properties": {
    "addr:full":"5, Via Aranci 97100 Ragusa Ragusa Ragusa 97100",
    "addr:postcode":"97100;97100",
    "addr:street":"Via Aranci",
    "iso:country":"IT",
    "sg:address":"5, Via Aranci 97100 Ragusa",
    "sg:city":"Ragusa",
    "sg:classifiers":[
        {
            "category":"Wholesale",
            "subcategory":"Machinery & Supplies",
            "type":"Manufacturing & Wholesale Goods"
        }
    ],
    "sg:phone":"+39 0932 655368",
    "sg:postcode":"97100",
    "sg:province":"Ragusa",
    "sg:tags":[
        "equipment",
        "precision"
    ],
    "wof:name":"Cora Industria S.r.l.",
    "wof:placetype":"venue"
},
  "geometry": {"coordinates":[14.7203578949,36.9252052307],"type":"Point"}
}