{
  "type": "Feature",
  "properties": {
    "iso:country":"IT",
    "sg:address":"80077 Ischia",
    "sg:city":"Ischia",
    "sg:orig_category":"Alberghi",
    "sg:phone":"+39 081 991316",
    "sg:postcode":"80077",
    "sg:province":"Napoli",
    "wof:name":"Hotel La Villarosa",
    "wof:placetype":"venue"
},
  "geometry": {"coordinates":[14.236448,40.853951],"type":"Point"}
}