{
  "type": "Feature",
  "properties": {
    "iso:country":"IT",
    "sg:address":"20021 Bollate",
    "sg:city":"Bollate",
    "sg:orig_category":"Macchine, Impianti E Forniture Per Industria Grafica, Cartaria E Cartotecnica. Automazione E Macchine Per Ufficio",
    "sg:phone":"+39 02 3820 1029",
    "sg:postcode":"20021",
    "sg:province":"Milano",
    "sg:website":"http://www.belcosystem.it",
    "wof:name":"Belcosystem Srl",
    "wof:placetype":"venue"
},
  "geometry": {"coordinates":[9.159385,45.562672],"type":"Point"}
}