{
  "type": "Feature",
  "properties": {
    "iso:country":"IT",
    "sg:address":"36100 Vicenza",
    "sg:city":"Vicenza",
    "sg:orig_category":"Cartotecnica E Servizi. Forniture Per Uffici",
    "sg:phone":"+39 0444 225200",
    "sg:postcode":"36100",
    "sg:province":"Vicenza",
    "sg:website":"http://www.gallabookstore.it",
    "wof:name":"Galla 1880 Srl",
    "wof:placetype":"venue"
},
  "geometry": {"coordinates":[11.561045,45.53619],"type":"Point"}
}