{
  "type": "Feature",
  "properties": {
    "addr:full":"Via Mercatelli 31058 Susegana Susegana Treviso 31058",
    "addr:postcode":"31058;31058",
    "addr:street":"Via Mercatelli",
    "iso:country":"IT",
    "sg:address":"Via Mercatelli 31058 Susegana",
    "sg:city":"Susegana",
    "sg:classifiers":[
        {
            "category":"Wholesale",
            "subcategory":"Drugs",
            "type":"Manufacturing & Wholesale Goods"
        }
    ],
    "sg:phone":"+39 0438 482013",
    "sg:postcode":"31058",
    "sg:province":"Treviso",
    "sg:tags":[
        "chemical",
        "pharmaceutical"
    ],
    "wof:name":"Edison Gas S.p.a.",
    "wof:placetype":"venue"
},
  "geometry": {"coordinates":[12.245297,45.825527],"type":"Point"}
}