{
  "type": "Feature",
  "properties": {
    "addr:full":"05100 Terni Terni Terni 05100",
    "addr:postcode":"05100;05100",
    "iso:country":"IT",
    "sg:address":"05100 Terni",
    "sg:city":"Terni",
    "sg:orig_category":"Ristorazione E Locali Pubblici Affini. Ristoranti Ed Esercizi Affini. Servizi Ausiliari Di Ristorazione E Di Intrattenimento",
    "sg:phone":"+39 0744 407102",
    "sg:postcode":"05100",
    "sg:province":"Terni",
    "wof:name":"Pasticceria Pazzaglia Srl",
    "wof:placetype":"venue"
},
  "geometry": {"coordinates":[12.647379,42.56237],"type":"Point"}
}