{
  "type": "Feature",
  "properties": {
    "iso:country":"IT",
    "sg:address":"41053 Maranello",
    "sg:city":"Maranello",
    "sg:orig_category":"Ascensori - Costruzione",
    "sg:phone":"+39 0536 940376",
    "sg:postcode":"41053",
    "sg:province":"Modena",
    "sg:website":"http://www.metalift.it",
    "wof:name":"Metalift Srl",
    "wof:placetype":"venue"
},
  "geometry": {"coordinates":[10.875631,44.530685],"type":"Point"}
}