{
  "type": "Feature",
  "properties": {
    "iso:country":"IT",
    "sg:address":"Strada Comunale Del Fucino 67041 Aielli",
    "sg:classifiers":[
        {
            "category":"Manufacturing",
            "subcategory":"Metals",
            "type":"Manufacturing & Wholesale Goods"
        }
    ],
    "sg:phone":"+39 0863 788122",
    "sg:postcode":"67041",
    "sg:province":"L'Aquila",
    "sg:tags":[
        "processing"
    ],
    "wof:name":"Kromoss S.r.l.",
    "wof:placetype":"venue"
},
  "geometry": {"coordinates":[13.5832252502,42.059463501],"type":"Point"}
}