{
  "type": "Feature",
  "properties": {
    "iso:country":"IT",
    "sg:address":"21047 Saronno",
    "sg:city":"Saronno",
    "sg:orig_category":"Materiali E Componenti Elettrotecnici",
    "sg:phone":"+39 02 9670 4970",
    "sg:postcode":"21047",
    "sg:province":"Varese",
    "wof:name":"L.c.a. Di Castagnino Loretta",
    "wof:placetype":"venue"
},
  "geometry": {"coordinates":[9.033397,45.614853],"type":"Point"}
}