{
  "type": "Feature",
  "properties": {
    "addr:full":"226, Viale Italia 20099 Sesto San Giovanni Sesto San Giovanni Milano 20099",
    "addr:postcode":"20099;20099",
    "addr:street":"Viale Italia",
    "iso:country":"IT",
    "sg:address":"226, Viale Italia 20099 Sesto San Giovanni",
    "sg:city":"Sesto San Giovanni",
    "sg:classifiers":[
        {
            "category":"Autos & Motor Vehicles",
            "subcategory":"Automobile Sales",
            "type":"Retail Goods"
        }
    ],
    "sg:phone":"+39 390 226 2831",
    "sg:postcode":"20099",
    "sg:province":"Milano",
    "sg:tags":[
        "motor-cars"
    ],
    "wof:name":"Sesto Autoveicoli S.p.a.",
    "wof:placetype":"venue"
},
  "geometry": {"coordinates":[9.243683815,45.5352706909],"type":"Point"}
}