{
  "type": "Feature",
  "properties": {
    "addr:full":"17, Via Arena 61020 Sant'angelo In Lizzola Pesaro E Urbino 61020",
    "addr:postcode":"61020;61020",
    "addr:street":"Via Arena;Lizzola Pesaro E Urbino",
    "iso:country":"IT",
    "sg:address":"17, Via Arena 61020 Sant'angelo In Lizzola",
    "sg:orig_category":"Miscellaneous Products",
    "sg:phone":"+39 0721 490379",
    "sg:postcode":"61020",
    "sg:province":"Pesaro E Urbino",
    "wof:name":"Rovea Industrie Chimiche (s.r.l.)",
    "wof:placetype":"venue"
},
  "geometry": {"coordinates":[12.784740448,43.8527641296],"type":"Point"}
}