{
  "type": "Feature",
  "properties": {
    "iso:country":"IT",
    "sg:address":"20032 Cormano",
    "sg:city":"Cormano",
    "sg:orig_category":"Servizi E Lavori Per Arredamento E Industria Del Legno",
    "sg:phone":"+39 02 6630 4955",
    "sg:postcode":"20032",
    "sg:province":"Milano",
    "wof:name":"Romito Michele Dei F.lli Romito A. & C.(s.n.c.)",
    "wof:placetype":"venue"
},
  "geometry": {"coordinates":[9.167078,45.536549],"type":"Point"}
}