{
  "type": "Feature",
  "properties": {
    "addr:full":"16154 Genova Genova Genova 16154",
    "addr:postcode":"16154;16154",
    "iso:country":"IT",
    "sg:address":"16154 Genova",
    "sg:city":"Genova",
    "sg:orig_category":"Prodotti Finiti Stampati. Articoli Da Regalo. Arte Ed Artigianato Artistico. Shopping",
    "sg:phone":"+39 010 604 4740",
    "sg:postcode":"16154",
    "sg:province":"Genova",
    "wof:name":"Essedi Edizioni Snc",
    "wof:placetype":"venue"
},
  "geometry": {"coordinates":[8.8480558395,44.4225006104],"type":"Point"}
}