{
  "type": "Feature",
  "properties": {
    "iso:country":"IT",
    "sg:address":"Via Cavour 37/41; Empoli; 50053",
    "sg:city":"Empoli",
    "sg:classifiers":[
        {
            "category":"Banks & Credit Unions",
            "subcategory":"Bank",
            "type":"Services"
        }
    ],
    "sg:phone":"+39 0571 79642",
    "sg:postcode":"50053",
    "sg:province":"Firenze",
    "wof:name":"Cassa Di Risparmio Di San Miniato",
    "wof:placetype":"venue"
},
  "geometry": {"coordinates":[10.946215,43.718044],"type":"Point"}
}