{
  "type": "Feature",
  "properties": {
    "iso:country":"IT",
    "sg:address":"Via Lombardia 38 29100 Piacenza",
    "sg:city":"Piacenza",
    "sg:classifiers":[
        {
            "category":"Military Area",
            "subcategory":"Coast Guard Base",
            "type":"Public Place"
        }
    ],
    "sg:phone":"+39 0523 593000",
    "sg:postcode":"29100",
    "sg:province":"Piacenza",
    "sg:tags":[
        "steel",
        "door",
        "safety"
    ],
    "sg:website":"www.masterdoor.it",
    "wof:name":"Master Srl",
    "wof:placetype":"venue"
},
  "geometry": {"coordinates":[9.59527,45.064018],"type":"Point"}
}