{
  "type": "Feature",
  "properties": {
    "addr:full":"35, Via Firenze 70031 Andria Andria Bari 70031",
    "addr:postcode":"70031;70031",
    "addr:street":"Via Firenze",
    "iso:country":"IT",
    "sg:address":"35, Via Firenze 70031 Andria",
    "sg:city":"Andria",
    "sg:classifiers":[
        {
            "category":"Travel",
            "subcategory":"Travel Agent",
            "type":"Entertainment"
        }
    ],
    "sg:phone":"+39 0883 556444",
    "sg:postcode":"70031",
    "sg:province":"Bari",
    "sg:tags":[
        "business"
    ],
    "wof:name":"Cristal Palace Hotel",
    "wof:placetype":"venue"
},
  "geometry": {"coordinates":[16.299698,41.230446],"type":"Point"}
}