{
  "type": "Feature",
  "properties": {
    "iso:country":"IT",
    "sg:address":"1, Via Terra Dei Ceci 57023 Cecina",
    "sg:city":"Cecina",
    "sg:classifiers":[
        {
            "category":"Sports & Exercise",
            "subcategory":"Playing Field",
            "type":"Entertainment"
        }
    ],
    "sg:phone":"+39 0586 684351",
    "sg:postcode":"57023",
    "sg:province":"Livorno",
    "sg:tags":[
        "game"
    ],
    "wof:name":"Isac - Statue (s.r.l.)",
    "wof:placetype":"venue"
},
  "geometry": {"coordinates":[10.532025,43.297394],"type":"Point"}
}