{
  "type": "Feature",
  "properties": {
    "addr:full":"15, Via Teroldego 38016 Mezzocorona Mezzocorona Trento 38016",
    "addr:postcode":"38016;38016",
    "addr:street":"Via Teroldego",
    "iso:country":"IT",
    "sg:address":"15, Via Teroldego 38016 Mezzocorona",
    "sg:city":"Mezzocorona",
    "sg:classifiers":[
        {
            "category":"Manufacturing",
            "subcategory":"Lumber",
            "type":"Manufacturing & Wholesale Goods"
        }
    ],
    "sg:phone":"+39 0461 605107",
    "sg:postcode":"38016",
    "sg:province":"Trento",
    "sg:tags":[
        "wood"
    ],
    "wof:name":"Vender Legnami S.r.l.",
    "wof:placetype":"venue"
},
  "geometry": {"coordinates":[11.113842,46.20816],"type":"Point"}
}