{
  "type": "Feature",
  "properties": {
    "iso:country":"IT",
    "sg:address":"Via Pasano 1 24030 Ponte Giurino",
    "sg:city":"Ponte giurino",
    "sg:classifiers":[
        {
            "category":"Manufacturing",
            "subcategory":"Wood Products",
            "type":"Manufacturing & Wholesale Goods"
        }
    ],
    "sg:phone":"+39 035 863330",
    "sg:postcode":"24030",
    "sg:province":"Bergamo",
    "sg:tags":[
        "wooden",
        "items",
        "artistic",
        "handcraft"
    ],
    "wof:name":"C.o.l.b.i. Srl",
    "wof:placetype":"venue"
},
  "geometry": {"coordinates":[9.553948,45.801617],"type":"Point"}
}