{
  "type": "Feature",
  "properties": {
    "iso:country":"IT",
    "sg:address":"20030 Senago",
    "sg:city":"Senago",
    "sg:orig_category":"Ospedali E Servizi Sanitari",
    "sg:phone":"+39 02 9948 1453",
    "sg:postcode":"20030",
    "sg:province":"Milano",
    "wof:name":"Pubblica Assistenza Senago",
    "wof:placetype":"venue"
},
  "geometry": {"coordinates":[9.081843,45.550999],"type":"Point"}
}