{
  "type": "Feature",
  "properties": {
    "addr:full":"Via Mazzini, 14; Dro; 38074 Dro Trento 38074",
    "addr:housenumber":"14",
    "addr:postcode":"38074;38074",
    "addr:street":"Via Mazzini;Dro",
    "iso:country":"IT",
    "sg:address":"Via Mazzini, 14; Dro; 38074",
    "sg:city":"Dro",
    "sg:classifiers":[
        {
            "category":"Banks & Credit Unions",
            "subcategory":"Bank",
            "type":"Services"
        }
    ],
    "sg:phone":"+39 0464 504376",
    "sg:postcode":"38074",
    "sg:province":"Trento",
    "wof:name":"Cassa Rurale Di Arco",
    "wof:placetype":"venue"
},
  "geometry": {"coordinates":[10.913429,45.960915],"type":"Point"}
}