{
  "type": "Feature",
  "properties": {
    "addr:full":"P Garibaldi Giusepp Ambia 7; Bucine; 52021 Bucine Arezzo 52021",
    "addr:housenumber":"7",
    "addr:postcode":"52021;52021",
    "addr:street":"P;Giusepp Ambia",
    "iso:country":"IT",
    "sg:address":"P Garibaldi Giusepp Ambia 7; Bucine; 52021",
    "sg:city":"Bucine",
    "sg:classifiers":[
        {
            "category":"Banks & Credit Unions",
            "subcategory":"Bank",
            "type":"Services"
        }
    ],
    "sg:phone":"+39 055 991 7182",
    "sg:postcode":"52021",
    "sg:province":"Arezzo",
    "wof:name":"Monte Dei Paschi Di Siena",
    "wof:placetype":"venue"
},
  "geometry": {"coordinates":[11.593027,43.449066],"type":"Point"}
}