{
  "type": "Feature",
  "properties": {
    "addr:full":"Via Malaguti; Crespellano",
    "addr:street":"Via Malaguti",
    "iso:country":"IT",
    "sg:address":"Via Malaguti; Crespellano",
    "sg:classifiers":[
        {
            "category":"Banks & Credit Unions",
            "subcategory":"Bank",
            "type":"Services"
        }
    ],
    "sg:phone":"+39 051 960142",
    "wof:name":"Cassa Di Risparmio In Bologna Spa",
    "wof:placetype":"venue"
},
  "geometry": {"coordinates":[11.128707,44.513767],"type":"Point"}
}