{
  "type": "Feature",
  "properties": {
    "iso:country":"IT",
    "sg:address":"4, Via Lanzone 20123 Milano",
    "sg:city":"Milano",
    "sg:classifiers":[
        {
            "category":"Communications",
            "subcategory":"Newspaper",
            "type":"Services"
        }
    ],
    "sg:phone":"+39 02 7202 1201",
    "sg:postcode":"20123",
    "sg:province":"Milano",
    "sg:tags":[
        "advertising"
    ],
    "wof:name":"Arianna S.r.l.",
    "wof:placetype":"venue"
},
  "geometry": {"coordinates":[9.178732,45.460575],"type":"Point"}
}