{
  "type": "Feature",
  "properties": {
    "addr:full":"00154 Roma Roma Roma 00154",
    "addr:postcode":"00154;00154",
    "iso:country":"IT",
    "sg:address":"00154 Roma",
    "sg:city":"Roma",
    "sg:orig_category":"Sport And Leisure, Services. Tourism, Services. Motor Vehicles, Auxiliary Services. Transport, Auxiliary Services",
    "sg:phone":"+39 06 558 5250",
    "sg:postcode":"00154",
    "sg:province":"Roma",
    "wof:name":"Sa.ra. Snc Di Saracini Stefano",
    "wof:placetype":"venue"
},
  "geometry": {"coordinates":[12.449033,41.829304],"type":"Point"}
}