{
  "type": "Feature",
  "properties": {
    "iso:country":"IT",
    "sg:address":"20017 Rho",
    "sg:city":"Rho",
    "sg:classifiers":[
        {
            "category":"Organizations",
            "subcategory":"Professional Association",
            "type":"Services"
        }
    ],
    "sg:phone":"+39 02 939 7001",
    "sg:postcode":"20017",
    "sg:province":"Milano",
    "sg:tags":[
        "activities",
        "industrial",
        "equipment",
        "valve",
        "heating",
        "instrument",
        "heat",
        "machines",
        "measurement",
        "services",
        "engineering"
    ],
    "sg:website":"http://www.wika.it",
    "wof:name":"Wika Italiana Srl",
    "wof:placetype":"venue"
},
  "geometry": {"coordinates":[9.090048,45.522751],"type":"Point"}
}