{
  "type": "Feature",
  "properties": {
    "iso:country":"IT",
    "sg:address":"84129 Salerno",
    "sg:city":"Salerno",
    "sg:orig_category":"Banche E Servizi Finanziari. Avvocati, Notai E Servizi Legali",
    "sg:phone":"+39 089 726 6378",
    "sg:postcode":"84129",
    "sg:province":"Salerno",
    "wof:name":"La Segretissima Recupercrediti Di D'amore Giulia & C. Snc",
    "wof:placetype":"venue"
},
  "geometry": {"coordinates":[14.794975,40.663925],"type":"Point"}
}