{
  "type": "Feature",
  "properties": {
    "iso:country":"IT",
    "sg:address":"09010 Uta",
    "sg:city":"Uta",
    "sg:orig_category":"Macchine Ed Impianti Per Edilizia E Lavori Pubblici. Macchine, Strumenti Ed Apparecchi Per Attivita' Industriali",
    "sg:phone":"+39 070 968504",
    "sg:postcode":"09010",
    "sg:province":"Cagliari",
    "wof:name":"Pusceddu Costantino",
    "wof:placetype":"venue"
},
  "geometry": {"coordinates":[8.941882,39.302258],"type":"Point"}
}