{
  "type": "Feature",
  "properties": {
    "iso:country":"IT",
    "sg:address":"20052 Monza",
    "sg:city":"Monza",
    "sg:orig_category":"Servizi Di Magazzinaggio E Movimentazione",
    "sg:phone":"+39 039 200 2278",
    "sg:postcode":"20052",
    "sg:province":"Milano",
    "wof:name":"Columbus Srl",
    "wof:placetype":"venue"
},
  "geometry": {"coordinates":[9.206328,45.558205],"type":"Point"}
}