{
  "type": "Feature",
  "properties": {
    "iso:country":"IT",
    "sg:address":"109, Via Flora 20025 Legnano",
    "sg:city":"Legnano",
    "sg:classifiers":[
        {
            "category":"Sports & Exercise",
            "subcategory":"Playing Field",
            "type":"Entertainment"
        }
    ],
    "sg:phone":"+39 0331 541281",
    "sg:postcode":"20025",
    "sg:province":"Milano",
    "sg:tags":[
        "game"
    ],
    "wof:name":"Mistral Di Colnago Rinaldo - Vaccani Luciano & C. Snc",
    "wof:placetype":"venue"
},
  "geometry": {"coordinates":[8.902615,45.592819],"type":"Point"}
}