{
  "type": "Feature",
  "properties": {
    "addr:full":"16132 Genova Genova Genova 16132",
    "addr:postcode":"16132;16132",
    "iso:country":"IT",
    "sg:address":"16132 Genova",
    "sg:city":"Genova",
    "sg:orig_category":"Utensili Meccanici E Materiali",
    "sg:phone":"+39 010 396034",
    "sg:postcode":"16132",
    "sg:province":"Genova",
    "wof:name":"Deka Tools S.r.l.",
    "wof:placetype":"venue"
},
  "geometry": {"coordinates":[8.982509,44.415142],"type":"Point"}
}