{
  "type": "Feature",
  "properties": {
    "iso:country":"IT",
    "sg:address":"63020 Monte Vidon Corrado",
    "sg:city":"Monte Vidon Corrado",
    "sg:orig_category":"Filati - Produzione E Ingrosso",
    "sg:phone":"+39 0734 759110",
    "sg:postcode":"63020",
    "sg:province":"Ascoli Piceno",
    "wof:name":"S.g.s. Di Procaccini Sergio, Nardi Giovanni E C. Sas",
    "wof:placetype":"venue"
},
  "geometry": {"coordinates":[13.4880123138,43.120677948],"type":"Point"}
}