{
  "type": "Feature",
  "properties": {
    "iso:country":"IT",
    "sg:address":"3, Via Antonio Meucci Z.i. Aussa Corno 33058 San Giorgio Di Nogaro",
    "sg:city":"San Giorgio di Nogaro",
    "sg:classifiers":[
        {
            "category":"Shopping",
            "subcategory":"Crafts & Fabrics",
            "type":"Retail Goods"
        }
    ],
    "sg:phone":"+39 39043165575",
    "sg:postcode":"33058",
    "sg:province":"Udine",
    "wof:name":"Armare Di Stefano Finco",
    "wof:placetype":"venue"
},
  "geometry": {"coordinates":[13.2307243347,46.0649414062],"type":"Point"}
}