{
  "type": "Feature",
  "properties": {
    "addr:full":"334, Localita' Bagnoli Della Rosandra 34018 San Dorligo Della Valle Bagnoli della Rosandra Trieste 34018",
    "addr:housenumber":"334",
    "addr:postcode":"34018;34018",
    "addr:street":"Localita ' Bagnoli Della Rosandra;Bagnoli Della Rosandra",
    "iso:country":"IT",
    "sg:address":"334, Localita' Bagnoli Della Rosandra 34018 San Dorligo Della Valle",
    "sg:city":"Bagnoli della Rosandra",
    "sg:classifiers":[
        {
            "category":"Manufacturing",
            "subcategory":"Motor Vehicles & Parts",
            "type":"Manufacturing & Wholesale Goods"
        }
    ],
    "sg:phone":"+39 040 319 5000",
    "sg:postcode":"34018",
    "sg:province":"Trieste",
    "sg:tags":[
        "engine"
    ],
    "wof:name":"Wartsila Italia S.p.a.",
    "wof:placetype":"venue"
},
  "geometry": {"coordinates":[13.857105,45.612766],"type":"Point"}
}