{
  "type": "Feature",
  "properties": {
    "addr:full":"90141 Palermo Palermo Palermo 90141",
    "addr:postcode":"90141;90141",
    "iso:country":"IT",
    "sg:address":"90141 Palermo",
    "sg:city":"Palermo",
    "sg:orig_category":"Forniture Per Agricoltura E Zootecnia. Animali Domestici",
    "sg:phone":"+39 091 336677",
    "sg:postcode":"90141",
    "sg:province":"Palermo",
    "wof:name":"Acquario Club",
    "wof:placetype":"venue"
},
  "geometry": {"coordinates":[13.3486213684,38.1278648376],"type":"Point"}
}