{
  "type": "Feature",
  "properties": {
    "iso:country":"IT",
    "sg:address":"10128 Torino",
    "sg:city":"Torino",
    "sg:orig_category":"Servizi Vari Di Interesse Pubblico",
    "sg:phone":"+39 011 304 2964",
    "sg:postcode":"10128",
    "sg:province":"Torino",
    "wof:name":"Bosisio Silvia Maria",
    "wof:placetype":"venue"
},
  "geometry": {"coordinates":[8.39892,45.462345],"type":"Point"}
}