{
  "type": "Feature",
  "properties": {
    "iso:country":"IT",
    "sg:address":"20020 Vanzaghello",
    "sg:city":"Vanzaghello",
    "sg:orig_category":"Lavorazioni Metalli, Stampaggio E Saldatura",
    "sg:phone":"+39 0331 657818",
    "sg:postcode":"20020",
    "sg:province":"Milano",
    "wof:name":"Tiesse Di Simontacchi Angelo & C. Snc",
    "wof:placetype":"venue"
},
  "geometry": {"coordinates":[9.14016,45.500553],"type":"Point"}
}