{
  "type": "Feature",
  "properties": {
    "addr:full":"40018 Poggetto Bologna 40018",
    "addr:postcode":"40018;40018",
    "addr:street":"Poggetto",
    "iso:country":"IT",
    "sg:address":"40018 Poggetto",
    "sg:orig_category":"Servizi E Lavori Per Agricoltura E Zootecnia",
    "sg:phone":"+39 051 813194",
    "sg:postcode":"40018",
    "sg:province":"Bologna",
    "wof:name":"Borghi Enzo",
    "wof:placetype":"venue"
},
  "geometry": {"coordinates":[11.37075,44.488026],"type":"Point"}
}