{
  "type": "Feature",
  "properties": {
    "iso:country":"IT",
    "sg:address":"153, Viale Milano 21013 Gallarate",
    "sg:city":"Gallarate",
    "sg:classifiers":[
        {
            "category":"Manufacturing",
            "subcategory":"Metals",
            "type":"Manufacturing & Wholesale Goods"
        }
    ],
    "sg:phone":"+39 0331 792028",
    "sg:postcode":"21013",
    "sg:province":"Varese",
    "sg:tags":[
        "metallurgy",
        "metalworking"
    ],
    "wof:name":"Mario Crespi (s.p.a.)",
    "wof:placetype":"venue"
},
  "geometry": {"coordinates":[8.8165235519,45.6444587708],"type":"Point"}
}