{
  "type": "Feature",
  "properties": {
    "addr:full":"36070 Trissino Trissino Vicenza 36070",
    "addr:postcode":"36070;36070",
    "iso:country":"IT",
    "sg:address":"36070 Trissino",
    "sg:city":"Trissino",
    "sg:orig_category":"Macchine, Impianti Ed Attrezzature Per Abbigliamento E Pelletterie",
    "sg:phone":"+39 0445 490740",
    "sg:postcode":"36070",
    "sg:province":"Vicenza",
    "wof:name":"Bauce Tri.ma Srl",
    "wof:placetype":"venue"
},
  "geometry": {"coordinates":[11.514935,45.526394],"type":"Point"}
}