{
  "type": "Feature",
  "properties": {
    "iso:country":"IT",
    "sg:address":"33170 Pordenone",
    "sg:city":"Pordenone",
    "sg:classifiers":[
        {
            "category":"Home & Garden",
            "subcategory":"Home Furnishings",
            "type":"Retail Goods"
        }
    ],
    "sg:phone":"+39 0434 522514",
    "sg:postcode":"33170",
    "sg:province":"Pordenone",
    "sg:tags":[
        "decorative",
        "door",
        "furnishings",
        "frame",
        "window",
        "objects"
    ],
    "wof:name":"Lucasam Sas",
    "wof:placetype":"venue"
},
  "geometry": {"coordinates":[12.6614522934,45.9563674927],"type":"Point"}
}