{
  "type": "Feature",
  "properties": {
    "addr:full":"Via Alcide De Gasperi 17 25030 Erbusco Erbusco Brescia 25030",
    "addr:housenumber":"17",
    "addr:postcode":"25030;25030",
    "addr:street":"Via Alcide De Gasperi",
    "iso:country":"IT",
    "sg:address":"Via Alcide De Gasperi 17 25030 Erbusco",
    "sg:city":"Erbusco",
    "sg:classifiers":[
        {
            "category":"Landmark",
            "subcategory":"Marketplace",
            "type":"Public Place"
        }
    ],
    "sg:phone":"+39 030 726 8344",
    "sg:postcode":"25030",
    "sg:province":"Brescia",
    "sg:tags":[
        "industry",
        "part",
        "bought-in",
        "furniture"
    ],
    "sg:website":"www.fonderialancini.com",
    "wof:name":"Fonderia Artistica Lancini Srl",
    "wof:placetype":"venue"
},
  "geometry": {"coordinates":[10.213513,45.579239],"type":"Point"}
}