{
  "type": "Feature",
  "properties": {
    "iso:country":"IT",
    "sg:address":"Via C Battisti 8; Agrate Brianza",
    "sg:classifiers":[
        {
            "category":"Banks & Credit Unions",
            "subcategory":"Bank",
            "type":"Services"
        }
    ],
    "sg:phone":"+39 039 605 7688",
    "wof:name":"Banca Di Roma",
    "wof:placetype":"venue"
},
  "geometry": {"coordinates":[9.339575,45.548958],"type":"Point"}
}