{
  "type": "Feature",
  "properties": {
    "addr:full":"10071 Borgaro Torinese Borgaro Torinese Torino 10071",
    "addr:postcode":"10071;10071",
    "iso:country":"IT",
    "sg:address":"10071 Borgaro Torinese",
    "sg:city":"Borgaro Torinese",
    "sg:orig_category":"Metalli E Leghe",
    "sg:phone":"+39 011 470 4840",
    "sg:postcode":"10071",
    "sg:province":"Torino",
    "wof:name":"Comasid International (s.r.l.)",
    "wof:placetype":"venue"
},
  "geometry": {"coordinates":[7.667529583,45.134552002],"type":"Point"}
}