{
  "type": "Feature",
  "properties": {
    "addr:full":"92020 S.giovanni Gemini Agrigento 92020",
    "addr:postcode":"92020;92020",
    "iso:country":"IT",
    "sg:address":"92020 S.giovanni Gemini",
    "sg:orig_category":"Aspirapolvere E Lucidatrici Uso Domestico",
    "sg:phone":"+39 0922 904622",
    "sg:postcode":"92020",
    "sg:province":"Agrigento",
    "wof:name":"Sansone Elettrodomestici",
    "wof:placetype":"venue"
},
  "geometry": {"coordinates":[13.576956,37.311188],"type":"Point"}
}