{
  "type": "Feature",
  "properties": {
    "iso:country":"IT",
    "sg:address":"25065 Lumezzane",
    "sg:city":"Lumezzane",
    "sg:orig_category":"Articoli Da Regalo. Tempo Libero - Articoli E Forniture. Regalistica Aziendale",
    "sg:phone":"+39 030 897 0468",
    "sg:postcode":"25065",
    "sg:province":"Brescia",
    "wof:name":"Sport Art Di Piardi Giorgio & C. (s.n.c.)",
    "wof:placetype":"venue"
},
  "geometry": {"coordinates":[10.20318,45.527573],"type":"Point"}
}