{
  "type": "Feature",
  "properties": {
    "iso:country":"IT",
    "sg:address":"20040 Cambiago",
    "sg:city":"Cambiago",
    "sg:orig_category":"Macchine, Impianti Ed Attrezzature Per Abbigliamento E Pelletterie",
    "sg:phone":"+39 02 950 6168",
    "sg:postcode":"20040",
    "sg:province":"Milano",
    "wof:name":"Grittini & Motta (s.n.c.)",
    "wof:placetype":"venue"
},
  "geometry": {"coordinates":[9.177293,45.49678],"type":"Point"}
}