{
  "type": "Feature",
  "properties": {
    "iso:country":"IT",
    "sg:address":"Via Bandiera Fratelli 2 24048 Treviolo",
    "sg:city":"Treviolo",
    "sg:classifiers":[
        {
            "category":"Food & Beverages",
            "subcategory":"Fruits & Vegetables",
            "type":"Retail Goods"
        }
    ],
    "sg:phone":"+39 035 698811",
    "sg:postcode":"24048",
    "sg:province":"Bergamo",
    "sg:tags":[
        "water",
        "plant",
        "processing",
        "lime"
    ],
    "sg:website":"www.termorobica.it",
    "wof:name":"Termorobica Srl",
    "wof:placetype":"venue"
},
  "geometry": {"coordinates":[9.637853,45.678333],"type":"Point"}
}