{
  "type": "Feature",
  "properties": {
    "iso:country":"IT",
    "sg:address":"20161 Milano",
    "sg:city":"Milano",
    "sg:orig_category":"Bevande, Vini E Liquori",
    "sg:phone":"+39 02 646 4771",
    "sg:postcode":"20161",
    "sg:province":"Milano",
    "wof:name":"Cooperativa Co.di.be. Distributori Bevande Soc. Coop. A R.l.",
    "wof:placetype":"venue"
},
  "geometry": {"coordinates":[9.189205,45.460072],"type":"Point"}
}