{
  "type": "Feature",
  "properties": {
    "iso:country":"IT",
    "sg:address":"00199 Roma",
    "sg:city":"Roma",
    "sg:orig_category":"Accessori Moda D'abbigliamento",
    "sg:phone":"+39 06 8620 1091",
    "sg:postcode":"00199",
    "sg:province":"Roma",
    "wof:name":"Punto Griffe Srl",
    "wof:placetype":"venue"
},
  "geometry": {"coordinates":[12.522312,41.930965],"type":"Point"}
}