{
  "type": "Feature",
  "properties": {
    "iso:country":"IT",
    "sg:address":"40050 Loiano",
    "sg:city":"Loiano",
    "sg:orig_category":"Ristorazione E Locali Pubblici Affini. Ristoranti Ed Esercizi Affini. Servizi Ausiliari Di Ristorazione E Di Intrattenimento",
    "sg:phone":"+39 051 654 4934",
    "sg:postcode":"40050",
    "sg:province":"Bologna",
    "sg:website":"http://www.loiano.com",
    "wof:name":"Trattoria 'il Telegrafo'",
    "wof:placetype":"venue"
},
  "geometry": {"coordinates":[11.351653,44.480591],"type":"Point"}
}