{
  "type": "Feature",
  "properties": {
    "iso:country":"IT",
    "sg:address":"40057 Granarolo Dell'emilia",
    "sg:orig_category":"Macchine Ed Impianti Per Edilizia E Lavori Pubblici",
    "sg:phone":"+39 051 765010",
    "sg:postcode":"40057",
    "sg:province":"Bologna",
    "wof:name":"Mac - Impianti S.r.l.",
    "wof:placetype":"venue"
},
  "geometry": {"coordinates":[11.395608,44.54781],"type":"Point"}
}