{
  "type": "Feature",
  "properties": {
    "iso:country":"IT",
    "sg:address":"55049 Viareggio",
    "sg:city":"Viareggio",
    "sg:orig_category":"Vetrate Artistiche",
    "sg:phone":"+39 0584 49543",
    "sg:postcode":"55049",
    "sg:province":"Lucca",
    "wof:name":"Studio Artistico Mal\u00d2",
    "wof:placetype":"venue"
},
  "geometry": {"coordinates":[10.246056,43.874496],"type":"Point"}
}