{
  "type": "Feature",
  "properties": {
    "addr:full":"80019 Qualiano Qualiano Napoli 80019",
    "addr:postcode":"80019;80019",
    "iso:country":"IT",
    "sg:address":"80019 Qualiano",
    "sg:city":"Qualiano",
    "sg:orig_category":"Prodotti Chimici Secondari. Macchine, Impianti Ed Attrezzature Industria Chimica. Servizi E Lavori Industria Chimica",
    "sg:phone":"+39 081 818 1760",
    "sg:postcode":"80019",
    "sg:province":"Napoli",
    "wof:name":"Univer Giovanni Romano",
    "wof:placetype":"venue"
},
  "geometry": {"coordinates":[14.1524477005,40.9202461243],"type":"Point"}
}