{
  "type": "Feature",
  "properties": {
    "addr:full":"Via C. Pasquali 38 26040 Casalbellotto Cremona 26040",
    "addr:housenumber":"38",
    "addr:postcode":"26040;26040",
    "addr:street":"Via C. Pasquali",
    "iso:country":"IT",
    "sg:address":"Via C. Pasquali 38 26040 Casalbellotto",
    "sg:classifiers":[
        {
            "category":"Shopping",
            "subcategory":"Stationery & Office Supplies",
            "type":"Retail Goods"
        }
    ],
    "sg:phone":"+39 0375 59108",
    "sg:postcode":"26040",
    "sg:province":"Cremona",
    "sg:tags":[
        "paint",
        "brush"
    ],
    "sg:website":"www.pennellirex.com",
    "wof:name":"Pennelli Rex Di Galli Franco E C Snc",
    "wof:placetype":"venue"
},
  "geometry": {"coordinates":[10.0261354446,45.1334991455],"type":"Point"}
}