{
  "type": "Feature",
  "properties": {
    "iso:country":"IT",
    "sg:address":"31033 Castelfranco Veneto",
    "sg:city":"Castelfranco Veneto",
    "sg:classifiers":[
        {
            "category":"Building & Trades",
            "subcategory":"Construction",
            "type":"Services"
        }
    ],
    "sg:phone":"+39 0423 721003",
    "sg:postcode":"31033",
    "sg:province":"Treviso",
    "sg:tags":[
        "equipment",
        "heat",
        "heating",
        "engineering"
    ],
    "sg:website":"http://www.fraccaro.it",
    "wof:name":"Officine Termotecniche Fraccaro Srl",
    "wof:placetype":"venue"
},
  "geometry": {"coordinates":[11.951897,45.67329],"type":"Point"}
}