{
  "type": "Feature",
  "properties": {
    "iso:country":"IT",
    "sg:address":"56, Via Molino Dei Signori 61049 Urbania",
    "sg:city":"Urbania",
    "sg:classifiers":[
        {
            "category":"Shopping",
            "subcategory":"Clothing, Apparel, & Fashions",
            "type":"Retail Goods"
        }
    ],
    "sg:phone":"+39 0722 318993",
    "sg:postcode":"61049",
    "sg:province":"Pesaro E Urbino",
    "sg:tags":[
        "clothes"
    ],
    "wof:name":"Joal Jeans Manifatture (s.p.a.)",
    "wof:placetype":"venue"
},
  "geometry": {"coordinates":[12.519543,43.674126],"type":"Point"}
}