{
  "type": "Feature",
  "properties": {
    "addr:full":"Via Delle Fabbriche 18 16158 Genova Genova Genova 16158",
    "addr:housenumber":"18",
    "addr:postcode":"16158;16158",
    "addr:street":"Via Delle Fabbriche",
    "iso:country":"IT",
    "sg:address":"Via Delle Fabbriche 18 16158 Genova",
    "sg:city":"Genova",
    "sg:classifiers":[
        {
            "category":"Military Area",
            "subcategory":"Army Base",
            "type":"Public Place"
        }
    ],
    "sg:phone":"+39 010 613 5202",
    "sg:postcode":"16158",
    "sg:province":"Genova",
    "sg:tags":[
        "mandrel"
    ],
    "wof:name":"O.r.m.p. Srl",
    "wof:placetype":"venue"
},
  "geometry": {"coordinates":[8.735953,44.434177],"type":"Point"}
}