{
  "type": "Feature",
  "properties": {
    "iso:country":"IT",
    "sg:address":"40033 Casalecchio Di Reno",
    "sg:city":"Casalecchio di Reno",
    "sg:orig_category":"Forniture Per Abbigliamento E Pelletterie",
    "sg:phone":"+39 051 613 2431",
    "sg:postcode":"40033",
    "sg:province":"Bologna",
    "wof:name":"Giorgio Leone S.r.l.",
    "wof:placetype":"venue"
},
  "geometry": {"coordinates":[11.2829799652,44.4739646912],"type":"Point"}
}