{
  "type": "Feature",
  "properties": {
    "iso:country":"IT",
    "sg:address":"47031 Repubblica Di S. Marino",
    "sg:orig_category":"Servizi Culturali E Per Lo Spettacolo. Cine-foto-ottica",
    "sg:phone":"+39 0549 909670",
    "sg:province":"SM",
    "sg:website":"http://www.genesi.com",
    "wof:name":"Music Store Srl",
    "wof:placetype":"venue"
},
  "geometry": {"coordinates":[-85.168671,39.07534],"type":"Point"}
}