{
  "type": "Feature",
  "properties": {
    "iso:country":"IT",
    "sg:address":"41, Via Cossa Pietro 00193 Roma",
    "sg:city":"Roma",
    "sg:classifiers":[
        {
            "category":"Manufacturing",
            "subcategory":"Printing",
            "type":"Manufacturing & Wholesale Goods"
        }
    ],
    "sg:phone":"+39 39063215673",
    "sg:postcode":"00193",
    "sg:province":"Roma",
    "sg:tags":[
        "publishing"
    ],
    "wof:name":"G.le Il Foro Italiano S.r.l.",
    "wof:placetype":"venue"
},
  "geometry": {"coordinates":[12.4718170166,41.9066734314],"type":"Point"}
}