{
  "type": "Feature",
  "properties": {
    "addr:full":"28100 Novara Novara Novara 28100",
    "addr:postcode":"28100;28100",
    "iso:country":"IT",
    "sg:address":"28100 Novara",
    "sg:city":"Novara",
    "sg:orig_category":"Studi E Consulenze Legali E Notarili. Avvocati, Notai E Servizi Legali. Professionisti - Studi E Servizi Ed Associazioni Di Interesse Aziendale",
    "sg:phone":"+39 0321 623173",
    "sg:postcode":"28100",
    "sg:province":"Novara",
    "wof:name":"Studio Ass. Dr. E. Comola Notaio Dr. E. Caroselli Notaio",
    "wof:placetype":"venue"
},
  "geometry": {"coordinates":[8.599689,45.447224],"type":"Point"}
}