{
  "type": "Feature",
  "properties": {
    "iso:country":"IT",
    "sg:address":"20, Via Serini Pietro 25131 Brescia",
    "sg:city":"Brescia",
    "sg:classifiers":[
        {
            "category":"Manufacturing",
            "subcategory":"Metals",
            "type":"Manufacturing & Wholesale Goods"
        }
    ],
    "sg:phone":"+39 030 268 1141",
    "sg:postcode":"25131",
    "sg:province":"Brescia",
    "sg:tags":[
        "metallurgy",
        "metalworking"
    ],
    "wof:name":"Metra Alca S.p.a.",
    "wof:placetype":"venue"
},
  "geometry": {"coordinates":[10.1598625183,45.5007858276],"type":"Point"}
}