{
  "type": "Feature",
  "properties": {
    "iso:country":"IT",
    "sg:address":"70124 Bari",
    "sg:city":"Bari",
    "sg:classifiers":[
        {
            "category":"Health Services",
            "subcategory":"Health Practitioner",
            "type":"Services"
        }
    ],
    "sg:phone":"+39 080 542 6905",
    "sg:postcode":"70124",
    "sg:province":"Bari",
    "sg:tags":[
        "medici"
    ],
    "wof:name":"Cardone Dr. Felice",
    "wof:placetype":"venue"
},
  "geometry": {"coordinates":[16.847338,41.091347],"type":"Point"}
}