{
  "type": "Feature",
  "properties": {
    "addr:full":"10060 San Secondo Di Pinerolo San Secondo di Pinerolo Torino 10060",
    "addr:housenumber":"10060",
    "addr:postcode":"10060",
    "addr:street":"San",
    "iso:country":"IT",
    "sg:address":"10060 San Secondo Di Pinerolo",
    "sg:city":"San Secondo di Pinerolo",
    "sg:orig_category":"Impiantistica E Prodotti Tecnologici Per Edilizia. Forniture Industriali Per Prevenzione, Controllo E Sicurezza",
    "sg:phone":"+39 0121 502055",
    "sg:postcode":"10060",
    "sg:province":"Torino",
    "wof:name":"Fireblock (s.n.c.)",
    "wof:placetype":"venue"
},
  "geometry": {"coordinates":[7.321447,44.851009],"type":"Point"}
}