{
  "type": "Feature",
  "properties": {
    "iso:country":"IT",
    "sg:address":"50136 Firenze",
    "sg:city":"Firenze",
    "sg:orig_category":"Accessori Dei Mezzi Di Trasporto",
    "sg:phone":"+39 055 660360",
    "sg:postcode":"50136",
    "sg:province":"Firenze",
    "wof:name":"Motorama Di Senesi G. & C. Sas",
    "wof:placetype":"venue"
},
  "geometry": {"coordinates":[11.273645,43.780132],"type":"Point"}
}