{
  "type": "Feature",
  "properties": {
    "iso:country":"IT",
    "sg:address":"Viale Carlo Fasso 2; Borgosesia; 13011",
    "sg:city":"Borgosesia",
    "sg:classifiers":[
        {
            "category":"Banks & Credit Unions",
            "subcategory":"Bank",
            "type":"Services"
        }
    ],
    "sg:phone":"+39 0163 204111",
    "sg:postcode":"13011",
    "sg:province":"Vercelli",
    "wof:name":"Istituto Bancario, San Paolo Di Torino Spa",
    "wof:placetype":"venue"
},
  "geometry": {"coordinates":[8.278168,45.714443],"type":"Point"}
}