{
  "type": "Feature",
  "properties": {
    "addr:full":"21046 Malnate Malnate Varese 21046",
    "addr:postcode":"21046;21046",
    "iso:country":"IT",
    "sg:address":"21046 Malnate",
    "sg:city":"Malnate",
    "sg:orig_category":"Telecomunicazioni E Telefonia, Impianti, Apparecchi E Servizi. Acqua, Luce, Gas E Societa' Di Esercizio Pubblico. Servizi Vari Di Interesse Pubblico",
    "sg:phone":"+39 02 380791",
    "sg:postcode":"21046",
    "sg:province":"Varese",
    "sg:website":"http://www.irpe.it",
    "wof:name":"Irpe Spa",
    "wof:placetype":"venue"
},
  "geometry": {"coordinates":[8.878903,45.784546],"type":"Point"}
}