{
  "type": "Feature",
  "properties": {
    "addr:full":"50145 Firenze Firenze Firenze 50145",
    "addr:postcode":"50145;50145",
    "iso:country":"IT",
    "sg:address":"50145 Firenze",
    "sg:city":"Firenze",
    "sg:orig_category":"Prodotti Chimici Di Base",
    "sg:phone":"+39 055 315162",
    "sg:postcode":"50145",
    "sg:province":"Firenze",
    "wof:name":"So.co.fi. (s.r.l.)",
    "wof:placetype":"venue"
},
  "geometry": {"coordinates":[11.1914901733,43.7983856201],"type":"Point"}
}