{
  "type": "Feature",
  "properties": {
    "addr:full":"9, Via Primo Maggio 22073 Fino Mornasco Fino Mornasco Como 22073",
    "addr:postcode":"22073;22073",
    "addr:street":"Via Primo Maggio",
    "iso:country":"IT",
    "sg:address":"9, Via Primo Maggio 22073 Fino Mornasco",
    "sg:city":"Fino Mornasco",
    "sg:classifiers":[
        {
            "category":"Manufacturing",
            "subcategory":"Printing",
            "type":"Manufacturing & Wholesale Goods"
        }
    ],
    "sg:phone":"+39 39031880562",
    "sg:postcode":"22073",
    "sg:province":"Como",
    "sg:tags":[
        "publishing"
    ],
    "wof:name":"Centro Arti Grafiche (s.n.c.)",
    "wof:placetype":"venue"
},
  "geometry": {"coordinates":[9.0750675201,45.7851066589],"type":"Point"}
}