{
  "type": "Feature",
  "properties": {
    "iso:country":"IT",
    "sg:address":"94014 Nicosia",
    "sg:city":"Nicosia",
    "sg:orig_category":"Forniture Per Edilizia E Lavori Pubblici",
    "sg:phone":"+39 0935 640684",
    "sg:postcode":"94014",
    "sg:province":"Enna",
    "wof:name":"Edilferro Di Modica Maria & Giusto Francesco",
    "wof:placetype":"venue"
},
  "geometry": {"coordinates":[14.4024705887,37.7430076599],"type":"Point"}
}