{
  "type": "Feature",
  "properties": {
    "addr:full":"Via Gallo Pat, 72 - Cecchini 33087 Pasiano Di Pordenone Cecchini Pordenone 33087",
    "addr:housenumber":"72",
    "addr:postcode":"33087;33087",
    "addr:street":"Via Gallo Pat",
    "iso:country":"IT",
    "sg:address":"Via Gallo Pat, 72 - Cecchini 33087 Pasiano Di Pordenone",
    "sg:city":"Cecchini",
    "sg:classifiers":[
        {
            "category":"Autos & Motor Vehicles",
            "subcategory":"Auto Supplies",
            "type":"Retail Goods"
        }
    ],
    "sg:phone":"+39 0434 625613",
    "sg:postcode":"33087",
    "sg:province":"Pordenone",
    "sg:tags":[
        "automobile",
        "accessory"
    ],
    "sg:website":"www.cubiksystem.com",
    "wof:name":"Cubik System Srl",
    "wof:placetype":"venue"
},
  "geometry": {"coordinates":[12.655044,45.96265],"type":"Point"}
}