{
  "type": "Feature",
  "properties": {
    "addr:full":"35020 Correzzola Correzzola Padova 35020",
    "addr:postcode":"35020;35020",
    "iso:country":"IT",
    "sg:address":"35020 Correzzola",
    "sg:city":"Correzzola",
    "sg:orig_category":"Servizi E Lavori Per Agricoltura E Zootecnia",
    "sg:phone":"+39 049 585 3386",
    "sg:postcode":"35020",
    "sg:province":"Padova",
    "wof:name":"Gabrieli Antonio",
    "wof:placetype":"venue"
},
  "geometry": {"coordinates":[12.037177,45.195793],"type":"Point"}
}