{
  "type": "Feature",
  "properties": {
    "iso:country":"IT",
    "sg:address":"50144 Firenze",
    "sg:city":"Firenze",
    "sg:orig_category":"Servizi E Lavori Per Ecologia E Smaltimento Rifiuti. Arte Ed Artigianato Artistico. Servizi Ausiliari Di Sorveglianza, Manutenzione E Pulizia",
    "sg:phone":"+39 055 360024",
    "sg:postcode":"50144",
    "sg:province":"Firenze",
    "wof:name":"Pennicot",
    "wof:placetype":"venue"
},
  "geometry": {"coordinates":[11.23469,43.782501],"type":"Point"}
}