{
  "type": "Feature",
  "properties": {
    "iso:country":"IT",
    "sg:address":"33, Via Ferrara Andrea 00165 Roma",
    "sg:city":"Roma",
    "sg:classifiers":[
        {
            "category":"Travel",
            "subcategory":"Travel Agent",
            "type":"Entertainment"
        }
    ],
    "sg:phone":"+39 390 666 4931",
    "sg:postcode":"00165",
    "sg:province":"Roma",
    "sg:tags":[
        "business"
    ],
    "wof:name":"Cristoforo Colombo International Alberghiera Srl",
    "wof:placetype":"venue"
},
  "geometry": {"coordinates":[12.482325,41.895466],"type":"Point"}
}