{
  "type": "Feature",
  "properties": {
    "addr:full":"91025 Marsala Marsala Trapani 91025",
    "addr:postcode":"91025;91025",
    "iso:country":"IT",
    "sg:address":"91025 Marsala",
    "sg:city":"Marsala",
    "sg:orig_category":"Riparazione Dei Mezzi Di Trasporto. Servizi Ausiliari Dei Mezzi Di Trasporto",
    "sg:phone":"+39 0923 721601",
    "sg:postcode":"91025",
    "sg:province":"Trapani",
    "wof:name":"Essemotors Srl",
    "wof:placetype":"venue"
},
  "geometry": {"coordinates":[12.446328,37.795589],"type":"Point"}
}