{
  "type": "Feature",
  "properties": {
    "iso:country":"IT",
    "sg:address":"20099 Sesto San Giovanni",
    "sg:city":"Sesto San Giovanni",
    "sg:orig_category":"Impiantistica E Prodotti Tecnologici Per Edilizia. Elettrotecnica Industriale, Prodotti E Apparecchiature. Elettrotecnica Professionale E Di Consumo",
    "sg:phone":"+39 02 240 6326",
    "sg:postcode":"20099",
    "sg:province":"Milano",
    "wof:name":"C.i.s.a.p. Snc",
    "wof:placetype":"venue"
},
  "geometry": {"coordinates":[9.25639,45.530041],"type":"Point"}
}