{
  "type": "Feature",
  "properties": {
    "addr:full":"8, Via Venini 20010 Vittuone Vittuone Milano 20010",
    "addr:postcode":"20010;20010",
    "addr:street":"Via Venini",
    "iso:country":"IT",
    "sg:address":"8, Via Venini 20010 Vittuone",
    "sg:city":"Vittuone",
    "sg:classifiers":[
        {
            "category":"Shopping",
            "type":"Retail Goods"
        }
    ],
    "sg:phone":"+39 02 9011 1058",
    "sg:postcode":"20010",
    "sg:province":"Milano",
    "sg:tags":[
        "finished",
        "-",
        "metallic"
    ],
    "wof:name":"Officin E Fonderie Pasquale Ghidoli & Co. S.a.s.",
    "wof:placetype":"venue"
},
  "geometry": {"coordinates":[8.9539957047,45.4874305725],"type":"Point"}
}