{
  "type": "Feature",
  "properties": {
    "addr:full":"Via Benvenuto Cellini 50 50020 Sambuca Val Di Pesa Firenze 50020",
    "addr:housenumber":"50",
    "addr:postcode":"50020;50020",
    "addr:street":"Via Benvenuto Cellini",
    "iso:country":"IT",
    "sg:address":"Via Benvenuto Cellini 50 50020 Sambuca Val Di Pesa",
    "sg:classifiers":[
        {
            "category":"Manufacturing",
            "subcategory":"Tools & Machinery",
            "type":"Manufacturing & Wholesale Goods"
        }
    ],
    "sg:phone":"+39 055 807 1809",
    "sg:postcode":"50020",
    "sg:province":"Firenze",
    "sg:tags":[
        "shutter",
        "aluminium",
        "section",
        "roller"
    ],
    "sg:website":"www.smsicurezza.com",
    "wof:name":"S.m. Sicurezza Srl",
    "wof:placetype":"venue"
},
  "geometry": {"coordinates":[11.256901741,43.7687339783],"type":"Point"}
}