{
  "type": "Feature",
  "properties": {
    "iso:country":"IT",
    "sg:address":"70123 Bari",
    "sg:city":"Bari",
    "sg:orig_category":"Tende Da Sole",
    "sg:phone":"+39 080 534 4085",
    "sg:postcode":"70123",
    "sg:province":"Bari",
    "wof:name":"Stil Tende Di Fusco Vito",
    "wof:placetype":"venue"
},
  "geometry": {"coordinates":[16.835537,41.122498],"type":"Point"}
}