{
  "type": "Feature",
  "properties": {
    "addr:full":"06100 Perugia PG",
    "addr:postcode":"06100",
    "addr:street":"Pg",
    "iso:country":"IT",
    "sg:address":"06100 Perugia",
    "sg:orig_category":"Ricambi E Componenti Dei Mezzi Di Trasporto",
    "sg:phone":"+39 075 500 7854",
    "sg:province":"PG",
    "wof:name":"Brunelli Massimo & C. (s.n.c.)",
    "wof:placetype":"venue"
},
  "geometry": {"coordinates":[12.365896,43.085602],"type":"Point"}
}