{
  "type": "Feature",
  "properties": {
    "iso:country":"IT",
    "sg:address":"50059 Vinci",
    "sg:city":"Vinci",
    "sg:orig_category":"Pavimenti Gomma, Linoleum E Plastica",
    "sg:phone":"+39 335 705 1655",
    "sg:postcode":"50059",
    "sg:province":"Firenze",
    "sg:website":"http://www.papy.it",
    "wof:name":"Papillon Di Piacentini",
    "wof:placetype":"venue"
},
  "geometry": {"coordinates":[10.9241962433,43.7716712952],"type":"Point"}
}