{
  "type": "Feature",
  "properties": {
    "iso:country":"IT",
    "sg:address":"76, Viale Dell' Artigianato Le Mose 29100 Piacenza",
    "sg:city":"Piacenza",
    "sg:classifiers":[
        {
            "category":"Personal",
            "subcategory":"Shoe Repair & Shine",
            "type":"Services"
        }
    ],
    "sg:phone":"+39 0523 591670",
    "sg:postcode":"29100",
    "sg:province":"Piacenza",
    "sg:tags":[
        "leather"
    ],
    "wof:name":"Shoes Group S.r.l.",
    "wof:placetype":"venue"
},
  "geometry": {"coordinates":[9.737352,45.044228],"type":"Point"}
}