{
  "type": "Feature",
  "properties": {
    "iso:country":"IT",
    "sg:address":"89852 Mileto",
    "sg:city":"Mileto",
    "sg:orig_category":"Non-classified Establishments",
    "sg:phone":"+39 0963 339733",
    "sg:postcode":"89852",
    "sg:province":"Vibo Valentia",
    "wof:name":"Luccisano Anna",
    "wof:placetype":"venue"
},
  "geometry": {"coordinates":[16.070486,38.610847],"type":"Point"}
}