{
  "type": "Feature",
  "properties": {
    "iso:country":"IT",
    "sg:address":"Via Campo Dei Fiori 21040 Venegono Superiore",
    "sg:city":"Venegono Superiore",
    "sg:classifiers":[
        {
            "category":"Manufacturing",
            "subcategory":"Rubber & Plastics",
            "type":"Manufacturing & Wholesale Goods"
        }
    ],
    "sg:phone":"+39 0331 866663",
    "sg:postcode":"21040",
    "sg:province":"Varese",
    "wof:name":"Nassi S.r.l.",
    "wof:placetype":"venue"
},
  "geometry": {"coordinates":[8.8760318756,45.7527236938],"type":"Point"}
}