{
  "type": "Feature",
  "properties": {
    "addr:full":"21, Via Del Brennero 55023 Borgo A Mozzano Borgo a Mozzano Lucca 55023",
    "addr:housenumber":"mozzano",
    "addr:postcode":"55023;55023",
    "addr:street":"Via Del Brennero",
    "iso:country":"IT",
    "sg:address":"21, Via Del Brennero 55023 Borgo A Mozzano",
    "sg:city":"Borgo a Mozzano",
    "sg:classifiers":[
        {
            "category":"Autos & Motor Vehicles",
            "subcategory":"Automobile Sales",
            "type":"Retail Goods"
        }
    ],
    "sg:phone":"+39 0583 805405",
    "sg:postcode":"55023",
    "sg:province":"Lucca",
    "sg:tags":[
        "motor-cars"
    ],
    "wof:name":"Tomei Motors S.r.l.",
    "wof:placetype":"venue"
},
  "geometry": {"coordinates":[10.534485817,43.9715805054],"type":"Point"}
}