{
  "type": "Feature",
  "properties": {
    "iso:country":"IT",
    "sg:address":"95030 S.agata Li Battiati",
    "sg:orig_category":"Alimentari - Vendita Al Dettaglio",
    "sg:phone":"+39 333 348 9503",
    "sg:postcode":"95030",
    "sg:province":"Catania",
    "wof:name":"Coco Orazio",
    "wof:placetype":"venue"
},
  "geometry": {"coordinates":[15.079496,37.535442],"type":"Point"}
}