{
  "type": "Feature",
  "properties": {
    "addr:full":"25082 Botticino Botticino Brescia 25082",
    "addr:postcode":"25082;25082",
    "iso:country":"IT",
    "sg:address":"25082 Botticino",
    "sg:city":"Botticino",
    "sg:orig_category":"Macchine, Impianti Ed Attrezzature Per Abbigliamento E Pelletterie",
    "sg:phone":"+39 030 219 0477",
    "sg:postcode":"25082",
    "sg:province":"Brescia",
    "wof:name":"Bonetti Giordano",
    "wof:placetype":"venue"
},
  "geometry": {"coordinates":[10.305294,45.537987],"type":"Point"}
}