{
  "type": "Feature",
  "properties": {
    "addr:full":"35047 Solesino Solesino Padova 35047",
    "addr:postcode":"35047;35047",
    "iso:country":"IT",
    "sg:address":"35047 Solesino",
    "sg:city":"Solesino",
    "sg:orig_category":"Forniture Per Abbigliamento E Pelletterie",
    "sg:phone":"+39 0429 709668",
    "sg:postcode":"35047",
    "sg:province":"Padova",
    "wof:name":"Canazza Roberto",
    "wof:placetype":"venue"
},
  "geometry": {"coordinates":[11.7439126968,45.1769371033],"type":"Point"}
}