{
  "type": "Feature",
  "properties": {
    "iso:country":"IT",
    "sg:address":"2/d, Via Di Gonfienti 59100 Prato",
    "sg:city":"Prato",
    "sg:classifiers":[
        {
            "category":"Airport",
            "subcategory":"General Aviation",
            "type":"Transportation"
        }
    ],
    "sg:phone":"+39 0574 562109",
    "sg:postcode":"59100",
    "sg:province":"Prato",
    "sg:tags":[
        "transport",
        "air"
    ],
    "wof:name":"Star Freight Srl",
    "wof:placetype":"venue"
},
  "geometry": {"coordinates":[11.096313,43.8797],"type":"Point"}
}