{
  "type": "Feature",
  "properties": {
    "iso:country":"IT",
    "sg:address":"05022 Amelia",
    "sg:city":"Amelia",
    "sg:orig_category":"Articoli Per Neonati E Bambini",
    "sg:phone":"+39 0744 982108",
    "sg:postcode":"05022",
    "sg:province":"Terni",
    "wof:name":"Perotti Carlo",
    "wof:placetype":"venue"
},
  "geometry": {"coordinates":[12.415133,42.556774],"type":"Point"}
}