{
  "type": "Feature",
  "properties": {
    "iso:country":"IT",
    "sg:address":"33010 Tavagnacco",
    "sg:city":"Tavagnacco",
    "sg:orig_category":"Minuterie Metalliche E Ferramenta",
    "sg:phone":"+39 0432 570608",
    "sg:postcode":"33010",
    "sg:province":"Udine",
    "wof:name":"Viterie Friulane",
    "wof:placetype":"venue"
},
  "geometry": {"coordinates":[13.225815773,46.1214523315],"type":"Point"}
}