{
  "type": "Feature",
  "properties": {
    "addr:full":"20080 Coazzano Milano 20080",
    "addr:postcode":"20080;20080",
    "addr:street":"Coazzano",
    "iso:country":"IT",
    "sg:address":"20080 Coazzano",
    "sg:orig_category":"Professionisti - Studi E Servizi Ed Associazioni Di Interesse Aziendale. Associazioni Ed Organismi Di Interesse Pubblico. Chiese Ed Associazioni Religiose",
    "sg:phone":"+39 02 905 2756",
    "sg:postcode":"20080",
    "sg:province":"Milano",
    "wof:name":"Associazione Riccardo Pampuri",
    "wof:placetype":"venue"
},
  "geometry": {"coordinates":[9.0494689941,45.3320846558],"type":"Point"}
}