{
  "type": "Feature",
  "properties": {
    "iso:country":"IT",
    "sg:address":"00047 Marino",
    "sg:city":"Marino",
    "sg:orig_category":"Macchine, Impianti Ed Attrezzature Per Agricoltura E Zootecnia",
    "sg:phone":"+39 06 935 2963",
    "sg:postcode":"00047",
    "sg:province":"Roma",
    "wof:name":"C.r.a.i. Appia S.r.l.",
    "wof:placetype":"venue"
},
  "geometry": {"coordinates":[12.609859,41.775948],"type":"Point"}
}