{
  "type": "Feature",
  "properties": {
    "addr:full":"20057 Vedano Al Lambro Vedano al Lambro Milano 20057",
    "addr:postcode":"20057;20057",
    "iso:country":"IT",
    "sg:address":"20057 Vedano Al Lambro",
    "sg:city":"Vedano al Lambro",
    "sg:classifiers":[
        {
            "category":"Health Services",
            "subcategory":"Health Practitioner",
            "type":"Services"
        }
    ],
    "sg:phone":"+39 039 249 7568",
    "sg:postcode":"20057",
    "sg:province":"Milano",
    "sg:tags":[
        "medici"
    ],
    "wof:name":"Merlini Marco",
    "wof:placetype":"venue"
},
  "geometry": {"coordinates":[9.273363,45.610641],"type":"Point"}
}