{
  "type": "Feature",
  "properties": {
    "iso:country":"IT",
    "sg:address":"80144 Napoli",
    "sg:city":"Napoli",
    "sg:classifiers":[
        {
            "category":"Home & Garden",
            "subcategory":"Building Materials",
            "type":"Retail Goods"
        }
    ],
    "sg:phone":"+39 0389 979 3196",
    "sg:postcode":"80144",
    "sg:province":"Napoli",
    "sg:tags":[
        "window",
        "door",
        "frame"
    ],
    "wof:name":"Colella Raffaele",
    "wof:placetype":"venue"
},
  "geometry": {"coordinates":[14.280296,40.883812],"type":"Point"}
}