{
  "type": "Feature",
  "properties": {
    "iso:country":"IT",
    "sg:address":"6, Via Trento 20013 Magenta",
    "sg:city":"Magenta",
    "sg:classifiers":[
        {
            "category":"Manufacturing",
            "subcategory":"Paper Products",
            "type":"Manufacturing & Wholesale Goods"
        }
    ],
    "sg:phone":"+39 02 9729 8220",
    "sg:postcode":"20013",
    "sg:province":"Milano",
    "sg:tags":[
        "cardboard"
    ],
    "wof:name":"Molho & C. (s.r.l.)",
    "wof:placetype":"venue"
},
  "geometry": {"coordinates":[8.9077014923,45.4241256714],"type":"Point"}
}