{
  "type": "Feature",
  "properties": {
    "iso:country":"IT",
    "sg:address":"10064 Pinerolo",
    "sg:city":"Pinerolo",
    "sg:orig_category":"Antenne Radio-televisione",
    "sg:phone":"+39 0121 78778",
    "sg:postcode":"10064",
    "sg:province":"Torino",
    "wof:name":"Sicur Impianti Di Morat Marco",
    "wof:placetype":"venue"
},
  "geometry": {"coordinates":[7.325455,44.895668],"type":"Point"}
}