{
  "type": "Feature",
  "properties": {
    "addr:full":"20090 Trezzano Sul Naviglio Trezzano sul Naviglio Milano 20090",
    "addr:postcode":"20090;20090",
    "iso:country":"IT",
    "sg:address":"20090 Trezzano Sul Naviglio",
    "sg:city":"Trezzano sul Naviglio",
    "sg:orig_category":"Non-classified Establishments",
    "sg:phone":"+39 02 445 3041",
    "sg:postcode":"20090",
    "sg:province":"Milano",
    "wof:name":"Gruppo Fontana S.p.a.",
    "wof:placetype":"venue"
},
  "geometry": {"coordinates":[9.049609,45.415451],"type":"Point"}
}