{
  "type": "Feature",
  "properties": {
    "iso:country":"IT",
    "sg:address":"24065 Lovere",
    "sg:city":"Lovere",
    "sg:classifiers":[
        {
            "category":"Health Services",
            "subcategory":"Health Practitioner",
            "type":"Services"
        }
    ],
    "sg:phone":"+39 035 964067",
    "sg:postcode":"24065",
    "sg:province":"Bergamo",
    "sg:tags":[
        "medici"
    ],
    "wof:name":"Radiologia Sebina (s.r.l.)",
    "wof:placetype":"venue"
},
  "geometry": {"coordinates":[10.0771341324,45.8187980652],"type":"Point"}
}