{
  "type": "Feature",
  "properties": {
    "iso:country":"IT",
    "sg:address":"00199 Roma",
    "sg:city":"Roma",
    "sg:orig_category":"Prodotti Alimentari",
    "sg:phone":"+39 06 8621 8464",
    "sg:postcode":"00199",
    "sg:province":"Roma",
    "wof:name":"Panosetti Mauro",
    "wof:placetype":"venue"
},
  "geometry": {"coordinates":[12.5154628754,41.9312744141],"type":"Point"}
}