{
  "type": "Feature",
  "properties": {
    "addr:full":"Via Monte Grappa 8 24026 Leffe Leffe Bergamo 24026",
    "addr:housenumber":"8",
    "addr:postcode":"24026;24026",
    "addr:street":"Via Monte Grappa",
    "iso:country":"IT",
    "sg:address":"Via Monte Grappa 8 24026 Leffe",
    "sg:city":"Leffe",
    "sg:classifiers":[
        {
            "category":"Manufacturing",
            "subcategory":"Furniture",
            "type":"Manufacturing & Wholesale Goods"
        }
    ],
    "sg:phone":"+39 035 731474",
    "sg:postcode":"24026",
    "sg:province":"Bergamo",
    "sg:tags":[
        "fabric"
    ],
    "sg:website":"www.nuovatessitura.com",
    "wof:name":"Nuova Tessitura F.lli Bosio S.n.c. Di Bosio Giuliano & C.",
    "wof:placetype":"venue"
},
  "geometry": {"coordinates":[9.8757982254,45.7997055054],"type":"Point"}
}