{
  "type": "Feature",
  "properties": {
    "iso:country":"IT",
    "sg:address":"191, Viale Sabotino 20025 Legnano",
    "sg:city":"Legnano",
    "sg:classifiers":[
        {
            "category":"Shopping",
            "subcategory":"Computers & Home Electronics",
            "type":"Retail Goods"
        }
    ],
    "sg:phone":"+39 0331 598122",
    "sg:postcode":"20025",
    "sg:province":"Milano",
    "sg:tags":[
        "electronic",
        "electrical",
        "equipment"
    ],
    "wof:name":"Elektro Di Gadda & Caprioli S.n.c.",
    "wof:placetype":"venue"
},
  "geometry": {"coordinates":[8.896397,45.596764],"type":"Point"}
}