{
  "type": "Feature",
  "properties": {
    "iso:country":"IT",
    "sg:address":"31021 Mogliano Veneto",
    "sg:city":"Mogliano Veneto",
    "sg:classifiers":[
        {
            "category":"Wholesale",
            "subcategory":"Machinery & Supplies",
            "type":"Manufacturing & Wholesale Goods"
        }
    ],
    "sg:phone":"+39 041 590 2638",
    "sg:postcode":"31021",
    "sg:province":"Treviso",
    "sg:tags":[
        "component",
        "engineering",
        "material",
        "electrical"
    ],
    "sg:website":"http://www.albait.com",
    "wof:name":"Alba Elettronica Snc",
    "wof:placetype":"venue"
},
  "geometry": {"coordinates":[12.242948,45.626007],"type":"Point"}
}