{
  "type": "Feature",
  "properties": {
    "addr:full":"Via Della Repubblica, 17; Lecce; 73100 Lecce Lecce 73100",
    "addr:housenumber":"17",
    "addr:postcode":"73100;73100",
    "addr:street":"Via Della Repubblica",
    "iso:country":"IT",
    "sg:address":"Via Della Repubblica, 17; Lecce; 73100",
    "sg:city":"Lecce",
    "sg:classifiers":[
        {
            "category":"Banks & Credit Unions",
            "subcategory":"Bank",
            "type":"Services"
        }
    ],
    "sg:phone":"+39 0832 44124",
    "sg:postcode":"73100",
    "sg:province":"Lecce",
    "wof:name":"Banca Nazionale Del Lavoro",
    "wof:placetype":"venue"
},
  "geometry": {"coordinates":[18.153986,40.357334],"type":"Point"}
}