{
  "type": "Feature",
  "properties": {
    "addr:full":"10071 Borgaro Torinese Borgaro Torinese Torino 10071",
    "addr:postcode":"10071;10071",
    "iso:country":"IT",
    "sg:address":"10071 Borgaro Torinese",
    "sg:city":"Borgaro Torinese",
    "sg:orig_category":"Trattamenti Termici E Superficiali Metalli, Galvanotecnica",
    "sg:phone":"+39 011 262 0011",
    "sg:postcode":"10071",
    "sg:province":"Torino",
    "wof:name":"Novazinc",
    "wof:placetype":"venue"
},
  "geometry": {"coordinates":[7.686952,45.135048],"type":"Point"}
}