{
  "type": "Feature",
  "properties": {
    "addr:full":"38030 Rover\u00e8 Della Luna Trento 38030",
    "addr:postcode":"38030;38030",
    "iso:country":"IT",
    "sg:address":"38030 Rover\u00e8 Della Luna",
    "sg:orig_category":"Legno E Semilavorati. Apparecchiature E Sistemi Per Magazzinaggio E Movimentazione",
    "sg:phone":"+39 0461 659070",
    "sg:postcode":"38030",
    "sg:province":"Trento",
    "sg:website":"http://www.pejopallet.it",
    "wof:name":"Pejo Pallet Snc",
    "wof:placetype":"venue"
},
  "geometry": {"coordinates":[11.171556,46.249496],"type":"Point"}
}