{
  "type": "Feature",
  "properties": {
    "iso:country":"IT",
    "sg:address":"37036 San Martino Buon Albergo",
    "sg:city":"San Martino Buon Albergo",
    "sg:orig_category":"Articoli Da Regalo. Regalistica Aziendale",
    "sg:phone":"+39 045 991666",
    "sg:postcode":"37036",
    "sg:province":"Verona",
    "sg:website":"http://www.emmedue.net",
    "wof:name":"Emmedue Minuterie Snc",
    "wof:placetype":"venue"
},
  "geometry": {"coordinates":[11.086507,45.418587],"type":"Point"}
}