{
  "type": "Feature",
  "properties": {
    "iso:country":"IT",
    "sg:address":"13900 Valdengo",
    "sg:classifiers":[
        {
            "category":"Manufacturing",
            "subcategory":"Tools & Machinery",
            "type":"Manufacturing & Wholesale Goods"
        }
    ],
    "sg:phone":"+39 015 882110",
    "sg:postcode":"13900",
    "sg:province":"Biella",
    "sg:tags":[
        "leather",
        "equipment",
        "goods",
        "clothing"
    ],
    "sg:website":"http://www.bematex.com",
    "wof:name":"Be.ma.tex Srl",
    "wof:placetype":"venue"
},
  "geometry": {"coordinates":[8.1292543411,45.5635910034],"type":"Point"}
}