{
  "type": "Feature",
  "properties": {
    "addr:full":"20123 Milano Milano Milano 20123",
    "addr:postcode":"20123;20123",
    "iso:country":"IT",
    "sg:address":"20123 Milano",
    "sg:city":"Milano",
    "sg:orig_category":"Macchine, Impianti E Forniture Per Industria Grafica, Cartaria E Cartotecnica",
    "sg:phone":"+39 02 805 4888",
    "sg:postcode":"20123",
    "sg:province":"Milano",
    "wof:name":"R.g. Rappresentanze Grafiche Srl",
    "wof:placetype":"venue"
},
  "geometry": {"coordinates":[9.174335,45.463634],"type":"Point"}
}