{
  "type": "Feature",
  "properties": {
    "iso:country":"IT",
    "sg:address":"24060 Castelli Calepio",
    "sg:city":"Castelli Calepio",
    "sg:orig_category":"Termotecnica E Riscaldamento, Apparecchiature E Servizi",
    "sg:phone":"+39 035 847257",
    "sg:postcode":"24060",
    "sg:province":"Bergamo",
    "sg:website":"http://www.saitsrl.it",
    "wof:name":"S.a.i.t. Bruciatori Srl",
    "wof:placetype":"venue"
},
  "geometry": {"coordinates":[9.894686,45.62521],"type":"Point"}
}