{
  "type": "Feature",
  "properties": {
    "addr:full":"10090 Gassino Torinese Gassino Torinese Torino 10090",
    "addr:postcode":"10090;10090",
    "addr:street":"Torinese",
    "iso:country":"IT",
    "sg:address":"10090 Gassino Torinese",
    "sg:city":"Gassino Torinese",
    "sg:orig_category":"Servizi Al Turismo. Trasporto Pubblico E Privato. Acqua, Luce, Gas E Societa' Di Esercizio Pubblico",
    "sg:phone":"+39 011 960 6232",
    "sg:postcode":"10090",
    "sg:province":"Torino",
    "wof:name":"S.a.t.t.i. Torinese Trasporti Intercomunali S.p.a.",
    "wof:placetype":"venue"
},
  "geometry": {"coordinates":[7.76686,45.14045],"type":"Point"}
}