{
  "type": "Feature",
  "properties": {
    "iso:country":"IT",
    "sg:address":"06053 Deruta",
    "sg:city":"Deruta",
    "sg:orig_category":"Arredamenti E Mobili Professionali",
    "sg:phone":"+39 075 971 1476",
    "sg:postcode":"06053",
    "sg:province":"Perugia",
    "wof:name":"F.a.a. Snc",
    "wof:placetype":"venue"
},
  "geometry": {"coordinates":[12.413292,42.98143],"type":"Point"}
}