{
  "type": "Feature",
  "properties": {
    "iso:country":"IT",
    "sg:address":"06129 Perugia",
    "sg:city":"Perugia",
    "sg:orig_category":"Trasporti E Spedizioni Merci",
    "sg:phone":"+39 075 52741",
    "sg:postcode":"06129",
    "sg:province":"Perugia",
    "sg:website":"http://www.raco.it",
    "wof:name":"Rasimelli E Coletti Spa",
    "wof:placetype":"venue"
},
  "geometry": {"coordinates":[12.344966,43.07114],"type":"Point"}
}