{
  "type": "Feature",
  "properties": {
    "iso:country":"IT",
    "sg:address":"50032 Borgo San Lorenzo",
    "sg:city":"Borgo San Lorenzo",
    "sg:orig_category":"Ceramiche: Prodotti E Lavorazioni",
    "sg:phone":"+39 055 845 5138",
    "sg:postcode":"50032",
    "sg:province":"Firenze",
    "wof:name":"La Futura Di Bini Marcella E C.snc",
    "wof:placetype":"venue"
},
  "geometry": {"coordinates":[11.411205,43.997242],"type":"Point"}
}