{
  "type": "Feature",
  "properties": {
    "iso:country":"IT",
    "sg:address":"00196 Roma",
    "sg:city":"Roma",
    "sg:orig_category":"Carni, Salumi E Pesci",
    "sg:phone":"+39 06 323 4459",
    "sg:postcode":"00196",
    "sg:province":"Roma",
    "wof:name":"Caponnetto Ludovico",
    "wof:placetype":"venue"
},
  "geometry": {"coordinates":[12.463733,41.926022],"type":"Point"}
}