{
  "type": "Feature",
  "properties": {
    "iso:country":"IT",
    "sg:address":"64100 Teramo",
    "sg:city":"Teramo",
    "sg:orig_category":"Servizi E Lavori Per Edilizia E Lavori Pubblici. Professionisti - Studi E Servizi Ed Associazioni Di Interesse Aziendale",
    "sg:phone":"+39 0861 219096",
    "sg:postcode":"64100",
    "sg:province":"Teramo",
    "wof:name":"Abruzzi Sonda Sas Del Geometra Lorenzo Di Franco & C.",
    "wof:placetype":"venue"
},
  "geometry": {"coordinates":[13.70575,42.677277],"type":"Point"}
}