{
  "type": "Feature",
  "properties": {
    "iso:country":"IT",
    "sg:address":"Piazza Garibaldi 17; Massa Marittima; 58024",
    "sg:city":"Massa Marittima",
    "sg:classifiers":[
        {
            "category":"Banks & Credit Unions",
            "subcategory":"Bank",
            "type":"Services"
        }
    ],
    "sg:phone":"+39 0566 902281",
    "sg:postcode":"58024",
    "sg:province":"Grosseto",
    "wof:name":"Banca Toscana Spa",
    "wof:placetype":"venue"
},
  "geometry": {"coordinates":[10.987438,43.083241],"type":"Point"}
}