{
  "type": "Feature",
  "properties": {
    "iso:country":"IT",
    "sg:address":"80, Strada Della Berlia 10093 Collegno",
    "sg:city":"Collegno",
    "sg:classifiers":[
        {
            "category":"Professional",
            "subcategory":"Engineering",
            "type":"Services"
        }
    ],
    "sg:phone":"+39 39011712216",
    "sg:postcode":"10093",
    "sg:province":"Torino",
    "sg:tags":[
        "machine",
        "-",
        "mechanical"
    ],
    "wof:name":"First Italia S.r.l.",
    "wof:placetype":"venue"
},
  "geometry": {"coordinates":[7.615929,45.089394],"type":"Point"}
}