{
  "type": "Feature",
  "properties": {
    "iso:country":"IT",
    "sg:address":"20090 Cusago",
    "sg:city":"Cusago",
    "sg:orig_category":"Materiali E Componenti Elettronici",
    "sg:phone":"+39 02 903971",
    "sg:postcode":"20090",
    "sg:province":"Milano",
    "sg:website":"http://www.eccabacus.it",
    "wof:name":"Ecc Elettronica Spa",
    "wof:placetype":"venue"
},
  "geometry": {"coordinates":[9.047132,45.441761],"type":"Point"}
}