{
  "type": "Feature",
  "properties": {
    "addr:full":"38066 Riva Del Garda Riva del Garda Trento 38066",
    "addr:postcode":"38066;38066",
    "iso:country":"IT",
    "sg:address":"38066 Riva Del Garda",
    "sg:city":"Riva del Garda",
    "sg:orig_category":"Automobili E Mezzi Di Trasporto",
    "sg:phone":"+39 0464 554699",
    "sg:postcode":"38066",
    "sg:province":"Trento",
    "wof:name":"Gippi Moto Di Gipponi Alessandra",
    "wof:placetype":"venue"
},
  "geometry": {"coordinates":[10.839044,45.887112],"type":"Point"}
}