{
  "type": "Feature",
  "properties": {
    "iso:country":"IT",
    "sg:address":"42100 Reggio Emilia",
    "sg:orig_category":"Motori Ed Organi Di Trasmissione. Ricambi E Componenti Dei Mezzi Di Trasporto",
    "sg:phone":"+39 0522 550202",
    "sg:postcode":"42100",
    "sg:province":"Reggio Nell'Emilia",
    "wof:name":"Industria Italiana Pistoni Di Carlo Grisendi & C. (s.a.s.)",
    "wof:placetype":"venue"
},
  "geometry": {"coordinates":[10.6539096832,44.693031311],"type":"Point"}
}