{
  "type": "Feature",
  "properties": {
    "addr:full":"84020 Oliveto Citra Oliveto Citra Salerno 84020",
    "addr:postcode":"84020;84020",
    "addr:street":"Citra Salerno",
    "iso:country":"IT",
    "sg:address":"84020 Oliveto Citra",
    "sg:city":"Oliveto Citra",
    "sg:orig_category":"Ospedali E Servizi Sanitari. Pubblica Amministrazione. Servizi Sociali",
    "sg:phone":"+39 0828 797111",
    "sg:postcode":"84020",
    "sg:province":"Salerno",
    "wof:name":"Ospedale S. Francesco D'assisi",
    "wof:placetype":"venue"
},
  "geometry": {"coordinates":[15.230963,40.691425],"type":"Point"}
}