{
  "type": "Feature",
  "properties": {
    "iso:country":"IT",
    "sg:address":"21040 Uboldo",
    "sg:city":"Uboldo",
    "sg:orig_category":"Arte Ed Artigianato Artistico",
    "sg:phone":"+39 02 9678 9553",
    "sg:postcode":"21040",
    "sg:province":"Varese",
    "wof:name":"Vendramin Fabrizio",
    "wof:placetype":"venue"
},
  "geometry": {"coordinates":[9.005,45.616261],"type":"Point"}
}