{
  "type": "Feature",
  "properties": {
    "iso:country":"IT",
    "sg:address":"20030 Senago",
    "sg:city":"Senago",
    "sg:orig_category":"Arredo Cucina Ed Elettrodomestici. Climatizzazione E Condizionamento, Apparecchiature E Servizi",
    "sg:phone":"+39 02 998 8341",
    "sg:postcode":"20030",
    "sg:province":"Milano",
    "sg:website":"http://www.cappebaraldi.it",
    "wof:name":"Baraldi Srl",
    "wof:placetype":"venue"
},
  "geometry": {"coordinates":[9.152998,45.574459],"type":"Point"}
}