{
  "type": "Feature",
  "properties": {
    "iso:country":"IT",
    "sg:address":"1, Strada Provinciale Per Novi 15050 Villalvernia",
    "sg:city":"Villalvernia",
    "sg:classifiers":[
        {
            "category":"Shopping",
            "type":"Retail Goods"
        }
    ],
    "sg:phone":"+39 0131 836211",
    "sg:postcode":"15050",
    "sg:province":"Alessandria",
    "sg:tags":[
        "finished",
        "-",
        "metallic"
    ],
    "wof:name":"Albasider S.p.a.",
    "wof:placetype":"venue"
},
  "geometry": {"coordinates":[8.6169509888,44.9132156372],"type":"Point"}
}