{
  "type": "Feature",
  "properties": {
    "iso:country":"IT",
    "sg:address":"98049 Villafranca Tirrena",
    "sg:city":"Villafranca Tirrena",
    "sg:orig_category":"Ceramiche: Prodotti E Lavorazioni",
    "sg:phone":"+39 090 334861",
    "sg:postcode":"98049",
    "sg:province":"Messina",
    "wof:name":"Anastasi Nicol\u00d2",
    "wof:placetype":"venue"
},
  "geometry": {"coordinates":[15.446527,38.241863],"type":"Point"}
}