{
  "type": "Feature",
  "properties": {
    "iso:country":"IT",
    "sg:address":"06030 Bastardo",
    "sg:city":"Bastardo",
    "sg:orig_category":"Dolciumi E Gelati",
    "sg:phone":"+39 0742 99050",
    "sg:postcode":"06030",
    "sg:province":"Perugia",
    "wof:name":"Il Fornaio Di Proietti A.e Sartini M. (s.n.c.)",
    "wof:placetype":"venue"
},
  "geometry": {"coordinates":[12.562427,42.873226],"type":"Point"}
}