{
  "type": "Feature",
  "properties": {
    "iso:country":"IT",
    "sg:address":"15067 Novi Ligure",
    "sg:city":"Novi Ligure",
    "sg:classifiers":[
        {
            "category":"Health Services",
            "subcategory":"Health Practitioner",
            "type":"Services"
        }
    ],
    "sg:phone":"+39 0143 75761",
    "sg:postcode":"15067",
    "sg:province":"Alessandria",
    "sg:tags":[
        "medici"
    ],
    "wof:name":"Pesce Federica",
    "wof:placetype":"venue"
},
  "geometry": {"coordinates":[8.798324585,44.7542495728],"type":"Point"}
}