{
  "type": "Feature",
  "properties": {
    "iso:country":"IT",
    "sg:address":"Via San Giustina 85 38010 Tassullo",
    "sg:city":"Tassullo",
    "sg:classifiers":[
        {
            "category":"Food & Beverages",
            "subcategory":"Fruits & Vegetables",
            "type":"Retail Goods"
        }
    ],
    "sg:phone":"+39 0463 451300",
    "sg:postcode":"38010",
    "sg:province":"Trento",
    "wof:name":"Industrialfrut Di Zadra Fernando E C. Snc",
    "wof:placetype":"venue"
},
  "geometry": {"coordinates":[11.119052887,46.0667381287],"type":"Point"}
}