{
  "type": "Feature",
  "properties": {
    "addr:full":"10139 Torino Torino Torino 10139",
    "addr:postcode":"10139;10139",
    "iso:country":"IT",
    "sg:address":"10139 Torino",
    "sg:city":"Torino",
    "sg:orig_category":"Odontoiatria - Apparecchi E Forniture",
    "sg:phone":"+39 011 447 2336",
    "sg:postcode":"10139",
    "sg:province":"Torino",
    "sg:website":"http://www.enzolattore.com",
    "wof:name":"Enzo Lattore",
    "wof:placetype":"venue"
},
  "geometry": {"coordinates":[7.649451,45.067074],"type":"Point"}
}