{
  "type": "Feature",
  "properties": {
    "iso:country":"IT",
    "sg:address":"45, Via Della Liberta' 10095 Grugliasco",
    "sg:city":"Grugliasco",
    "sg:classifiers":[
        {
            "category":"Professional",
            "subcategory":"Engineering",
            "type":"Services"
        }
    ],
    "sg:phone":"+39 39011781259",
    "sg:postcode":"10095",
    "sg:province":"Torino",
    "sg:tags":[
        "machine",
        "-",
        "mechanical"
    ],
    "wof:name":"Metal Imprex (s.p.a.)",
    "wof:placetype":"venue"
},
  "geometry": {"coordinates":[7.58903,45.044117],"type":"Point"}
}