{
  "type": "Feature",
  "properties": {
    "addr:full":"Corso Svizzera 185 10149 Torino Torino Torino 10149",
    "addr:housenumber":"185",
    "addr:postcode":"10149;10149",
    "addr:street":"Corso Svizzera",
    "iso:country":"IT",
    "sg:address":"Corso Svizzera 185 10149 Torino",
    "sg:city":"Torino",
    "sg:orig_category":"Electronic Adapting Equipment For Uv Applications",
    "sg:phone":"+39 011 771 4343",
    "sg:postcode":"10149",
    "sg:province":"Torino",
    "sg:website":"www.telsy.com",
    "wof:name":"Telsy Spa",
    "wof:placetype":"venue"
},
  "geometry": {"coordinates":[7.830617,45.487606],"type":"Point"}
}