{
  "type": "Feature",
  "properties": {
    "addr:full":"Via Del Caminaccio 2-s. Maria D 06081 Assisi Assisi Perugia 06081",
    "addr:housenumber":"2-s;d",
    "addr:postcode":"06081;06081",
    "addr:street":"Via Del Caminaccio",
    "iso:country":"IT",
    "sg:address":"Via Del Caminaccio 2-s. Maria D 06081 Assisi",
    "sg:city":"Assisi",
    "sg:classifiers":[
        {
            "category":"Animal Shelter",
            "type":"Public Place"
        }
    ],
    "sg:phone":"+39 075 805291",
    "sg:postcode":"06081",
    "sg:province":"Perugia",
    "sg:tags":[
        "feed",
        "system",
        "dispensing"
    ],
    "sg:website":"www.fragolaspa.com",
    "wof:name":"Fratelli Fragola Spa",
    "wof:placetype":"venue"
},
  "geometry": {"coordinates":[12.389172,43.110703],"type":"Point"}
}