{
  "type": "Feature",
  "properties": {
    "addr:full":"99/100, Frazione Granero 13833 Portula Portula Biella 13833",
    "addr:housenumber":"99 / 100;13833",
    "addr:postcode":"13833",
    "addr:street":"Frazione Granero",
    "iso:country":"IT",
    "sg:address":"99/100, Frazione Granero 13833 Portula",
    "sg:city":"Portula",
    "sg:classifiers":[
        {
            "category":"Professional",
            "subcategory":"Engineering",
            "type":"Services"
        }
    ],
    "sg:phone":"+39 39015767653",
    "sg:postcode":"13833",
    "sg:province":"Biella",
    "sg:tags":[
        "machine",
        "-",
        "mechanical"
    ],
    "wof:name":"Minox (s.p.a.)",
    "wof:placetype":"venue"
},
  "geometry": {"coordinates":[8.178642,45.685238],"type":"Point"}
}