{
  "type": "Feature",
  "properties": {
    "addr:full":"20017 Rho Rho Milano 20017",
    "addr:postcode":"20017;20017",
    "iso:country":"IT",
    "sg:address":"20017 Rho",
    "sg:city":"Rho",
    "sg:orig_category":"Macchine Pulizia Industriale",
    "sg:phone":"+39 02 9390 9460",
    "sg:postcode":"20017",
    "sg:province":"Milano",
    "sg:website":"http://www.paginegialle.it/calitalia",
    "wof:name":"C.a-l. Italia Srl",
    "wof:placetype":"venue"
},
  "geometry": {"coordinates":[9.060493,45.529423],"type":"Point"}
}