{
  "type": "Feature",
  "properties": {
    "addr:full":"06034 Foligno Foligno Perugia 06034",
    "addr:postcode":"06034;06034",
    "iso:country":"IT",
    "sg:address":"06034 Foligno",
    "sg:city":"Foligno",
    "sg:classifiers":[
        {
            "category":"Health Services",
            "subcategory":"Health Practitioner",
            "type":"Services"
        }
    ],
    "sg:phone":"+39 0742 355958",
    "sg:postcode":"06034",
    "sg:province":"Perugia",
    "sg:tags":[
        "medici"
    ],
    "wof:name":"Lambrocco Francesco",
    "wof:placetype":"venue"
},
  "geometry": {"coordinates":[12.307384,43.062138],"type":"Point"}
}