{
  "type": "Feature",
  "properties": {
    "iso:country":"IT",
    "sg:address":"43059 Tornolo",
    "sg:city":"Tornolo",
    "sg:orig_category":"Non-classified Establishments",
    "sg:phone":"+39 0525 80143",
    "sg:postcode":"43059",
    "sg:province":"Parma",
    "wof:name":"Fratelli Squeri Di Squeri Giovanni E Massimino Sdf",
    "wof:placetype":"venue"
},
  "geometry": {"coordinates":[9.511733,44.444637],"type":"Point"}
}