{
  "type": "Feature",
  "properties": {
    "addr:full":"41100 Modena Modena Modena 41100",
    "addr:postcode":"41100;41100",
    "iso:country":"IT",
    "sg:address":"41100 Modena",
    "sg:city":"Modena",
    "sg:orig_category":"Riparazione Dei Mezzi Di Trasporto. Servizi Ausiliari Dei Mezzi Di Trasporto",
    "sg:phone":"+39 059 849350",
    "sg:postcode":"41100",
    "sg:province":"Modena",
    "wof:name":"Rem Di Penazzi Maurizio",
    "wof:placetype":"venue"
},
  "geometry": {"coordinates":[10.895621,44.684532],"type":"Point"}
}