{
  "type": "Feature",
  "properties": {
    "addr:full":"20093 Cologno Monzese Cologno Monzese Milano 20093",
    "addr:postcode":"20093;20093",
    "iso:country":"IT",
    "sg:address":"20093 Cologno Monzese",
    "sg:city":"Cologno Monzese",
    "sg:orig_category":"Cartotecnica E Servizi. Articoli Per Imballaggio E Confezionamento",
    "sg:phone":"+39 02 254 2441",
    "sg:postcode":"20093",
    "sg:province":"Milano",
    "wof:name":"Scatolificio Fumagalli Srl",
    "wof:placetype":"venue"
},
  "geometry": {"coordinates":[9.273158,45.54261],"type":"Point"}
}