{
  "type": "Feature",
  "properties": {
    "iso:country":"IT",
    "sg:address":"38068 Rovereto",
    "sg:city":"Rovereto",
    "sg:orig_category":"Abbigliamento Esterno, Maglierie E Pelliccerie. Shopping",
    "sg:phone":"+39 0464 433440",
    "sg:postcode":"38068",
    "sg:province":"Trento",
    "sg:website":"http://www.armeriaveronesi.it",
    "wof:name":"Armeria Centro Sport Caccia Pesca Di Veronesi & C. Sas",
    "wof:placetype":"venue"
},
  "geometry": {"coordinates":[11.044458,45.888252],"type":"Point"}
}