{
  "type": "Feature",
  "properties": {
    "addr:full":"17100 Savona Savona Savona 17100",
    "addr:postcode":"17100;17100",
    "iso:country":"IT",
    "sg:address":"17100 Savona",
    "sg:city":"Savona",
    "sg:orig_category":"Studi E Consulenze Tecniche E Industriali. Consulenze Tecniche, Amministrative E Perizie. Professionisti - Studi E Servizi Ed Associazioni Di Interesse Aziendale",
    "sg:phone":"+39 019 815192",
    "sg:postcode":"17100",
    "sg:province":"Savona",
    "wof:name":"Acquarone Fabio",
    "wof:placetype":"venue"
},
  "geometry": {"coordinates":[8.483315,44.309196],"type":"Point"}
}