{
  "type": "Feature",
  "properties": {
    "iso:country":"IT",
    "sg:address":"16, Via Oberdan Guglielmo 06034 Foligno",
    "sg:city":"Foligno",
    "sg:classifiers":[
        {
            "category":"Manufacturing",
            "subcategory":"Printing",
            "type":"Manufacturing & Wholesale Goods"
        }
    ],
    "sg:phone":"+39 0742 358301",
    "sg:postcode":"06034",
    "sg:province":"Perugia",
    "sg:tags":[
        "publishing"
    ],
    "wof:name":"Corriere Dell'umbria",
    "wof:placetype":"venue"
},
  "geometry": {"coordinates":[12.3891716003,43.1107025146],"type":"Point"}
}