{
  "type": "Feature",
  "properties": {
    "addr:full":"00172 Roma Roma Roma 00172",
    "addr:postcode":"00172;00172",
    "iso:country":"IT",
    "sg:address":"00172 Roma",
    "sg:city":"Roma",
    "sg:orig_category":"Prodotti Alimentari",
    "sg:phone":"+39 06 231 6199",
    "sg:postcode":"00172",
    "sg:province":"Roma",
    "wof:name":"Cremona Maria",
    "wof:placetype":"venue"
},
  "geometry": {"coordinates":[12.5675954819,41.8819656372],"type":"Point"}
}