{
  "type": "Feature",
  "properties": {
    "iso:country":"IT",
    "sg:address":"46042 Castel Goffredo",
    "sg:city":"Castel Goffredo",
    "sg:orig_category":"Gioielleria, Oreficeria E Argenteria. Shopping",
    "sg:phone":"+39 0376 779590",
    "sg:postcode":"46042",
    "sg:province":"Mantova",
    "wof:name":"Spazio Dolly Snc Di Sciannimanico Francesco & C.",
    "wof:placetype":"venue"
},
  "geometry": {"coordinates":[10.47395,45.298069],"type":"Point"}
}