{
  "type": "Feature",
  "properties": {
    "addr:full":"126, Strada Del Francese 10156 Torino Torino Torino 10156",
    "addr:postcode":"10156;10156",
    "addr:street":"Strada Del Francese",
    "iso:country":"IT",
    "sg:address":"126, Strada Del Francese 10156 Torino",
    "sg:city":"Torino",
    "sg:classifiers":[
        {
            "category":"Shopping",
            "subcategory":"Computers & Home Electronics",
            "type":"Retail Goods"
        }
    ],
    "sg:phone":"+39 011 407 6311",
    "sg:postcode":"10156",
    "sg:province":"Torino",
    "sg:tags":[
        "electronic",
        "electrical",
        "equipment"
    ],
    "wof:name":"Sicme Motori S.p.a.",
    "wof:placetype":"venue"
},
  "geometry": {"coordinates":[7.672274,45.134285],"type":"Point"}
}