{
  "type": "Feature",
  "properties": {
    "iso:country":"IT",
    "sg:address":"15, Via Regia 35018 San Martino Di Lupari",
    "sg:city":"San Martino di Lupari",
    "sg:classifiers":[
        {
            "category":"Professional",
            "subcategory":"Engineering",
            "type":"Services"
        }
    ],
    "sg:phone":"+39 049 946 1217",
    "sg:postcode":"35018",
    "sg:province":"Padova",
    "sg:tags":[
        "machine",
        "-",
        "mechanical"
    ],
    "wof:name":"Digipack S.r.l.",
    "wof:placetype":"venue"
},
  "geometry": {"coordinates":[11.849271,45.666695],"type":"Point"}
}