{
  "type": "Feature",
  "properties": {
    "iso:country":"IT",
    "sg:address":"21047 Saronno",
    "sg:city":"Saronno",
    "sg:classifiers":[
        {
            "category":"Health Services",
            "subcategory":"Health Practitioner",
            "type":"Services"
        }
    ],
    "sg:phone":"+39 02 962 6449",
    "sg:postcode":"21047",
    "sg:province":"Varese",
    "sg:tags":[
        "medici"
    ],
    "wof:name":"Chirico Domenico",
    "wof:placetype":"venue"
},
  "geometry": {"coordinates":[9.032098,45.627552],"type":"Point"}
}