{
  "type": "Feature",
  "properties": {
    "iso:country":"IT",
    "sg:address":"Localita' La Campigliola 58014 Manciano",
    "sg:city":"Manciano",
    "sg:classifiers":[
        {
            "category":"Wholesale",
            "subcategory":"Drugs",
            "type":"Manufacturing & Wholesale Goods"
        }
    ],
    "sg:phone":"+39 0564 627002",
    "sg:postcode":"58014",
    "sg:province":"Grosseto",
    "sg:tags":[
        "chemical",
        "pharmaceutical"
    ],
    "wof:name":"S.e.c.o.t.o. S.r.l.",
    "wof:placetype":"venue"
},
  "geometry": {"coordinates":[11.112782,42.762859],"type":"Point"}
}