{
  "type": "Feature",
  "properties": {
    "addr:full":"20159 Milano Milano Milano 20159",
    "addr:postcode":"20159;20159",
    "iso:country":"IT",
    "sg:address":"20159 Milano",
    "sg:city":"Milano",
    "sg:orig_category":"Servizi Editoriali",
    "sg:phone":"+39 02 608 0521",
    "sg:postcode":"20159",
    "sg:province":"Milano",
    "wof:name":"Cavallaro Gianluca",
    "wof:placetype":"venue"
},
  "geometry": {"coordinates":[9.188904,45.490032],"type":"Point"}
}