{
  "type": "Feature",
  "properties": {
    "iso:country":"IT",
    "sg:address":"20138 Milano",
    "sg:city":"Milano",
    "sg:orig_category":"Pellicce E Pelli - Custodia E Pulitura",
    "sg:phone":"+39 02 506 5321",
    "sg:postcode":"20138",
    "sg:province":"Milano",
    "wof:name":"Rinnovapel",
    "wof:placetype":"venue"
},
  "geometry": {"coordinates":[9.2647724152,45.4402999878],"type":"Point"}
}