{
  "type": "Feature",
  "properties": {
    "addr:full":"10098 Rivoli Rivoli Torino 10098",
    "addr:postcode":"10098;10098",
    "iso:country":"IT",
    "sg:address":"10098 Rivoli",
    "sg:city":"Rivoli",
    "sg:orig_category":"Arredo Bagno Ed Idrosanitari. Idrosanitari E Accessori",
    "sg:phone":"+39 011 958 0234",
    "sg:postcode":"10098",
    "sg:province":"Torino",
    "wof:name":"Ris Srl",
    "wof:placetype":"venue"
},
  "geometry": {"coordinates":[7.571621,45.083035],"type":"Point"}
}