{
  "type": "Feature",
  "properties": {
    "iso:country":"IT",
    "sg:address":"23030 Livigno",
    "sg:city":"Livigno",
    "sg:orig_category":"Servizi Per Lo Sport E Il Tempo Libero. Servizi Al Turismo",
    "sg:phone":"+39 0342 996741",
    "sg:postcode":"23030",
    "sg:province":"Sondrio",
    "wof:name":"Societa' Livigno (s.r.l.)",
    "wof:placetype":"venue"
},
  "geometry": {"coordinates":[10.137379,46.540928],"type":"Point"}
}