{
  "type": "Feature",
  "properties": {
    "iso:country":"IT",
    "sg:address":"91100 Trapani",
    "sg:city":"Trapani",
    "sg:orig_category":"Forniture Per Attivita' Commerciali Ed Artigianali",
    "sg:phone":"+39 0923 20295",
    "sg:postcode":"91100",
    "sg:province":"Trapani",
    "wof:name":"La Francesca Vito",
    "wof:placetype":"venue"
},
  "geometry": {"coordinates":[12.506606102,38.0162200928],"type":"Point"}
}