{
  "type": "Feature",
  "properties": {
    "iso:country":"IT",
    "sg:address":"Via Matteotti 7 42042 Fabbrico",
    "sg:orig_category":"Tractors For Industry, Shunting Tractors",
    "sg:phone":"+39 0522 656111",
    "sg:postcode":"42042",
    "sg:province":"Reggio Nell'Emilia",
    "sg:website":"www.landini.it",
    "wof:name":"Landini Spa",
    "wof:placetype":"venue"
},
  "geometry": {"coordinates":[10.809144,44.872463],"type":"Point"}
}