{
  "type": "Feature",
  "properties": {
    "addr:full":"53049 Torrita Di Siena Torrita di Siena Siena 53049",
    "addr:postcode":"53049;53049",
    "iso:country":"IT",
    "sg:address":"53049 Torrita Di Siena",
    "sg:city":"Torrita di Siena",
    "sg:orig_category":"Minuterie Metalliche E Ferramenta",
    "sg:phone":"+39 0577 687800",
    "sg:postcode":"53049",
    "sg:province":"Siena",
    "wof:name":"M.g.m. Snc",
    "wof:placetype":"venue"
},
  "geometry": {"coordinates":[11.7928514481,43.1807136536],"type":"Point"}
}