{
  "type": "Feature",
  "properties": {
    "iso:country":"IT",
    "sg:address":"37060 Erbe'",
    "sg:orig_category":"Tempo Libero - Articoli E Forniture. Automobili E Mezzi Di Trasporto",
    "sg:phone":"+39 045 732 5073",
    "sg:postcode":"37060",
    "sg:province":"Verona",
    "wof:name":"Malagnini Vittorio",
    "wof:placetype":"venue"
},
  "geometry": {"coordinates":[10.970333,45.242519],"type":"Point"}
}