{
  "type": "Feature",
  "properties": {
    "addr:full":"80143 Napoli Napoli Napoli 80143",
    "addr:housenumber":"80143",
    "addr:postcode":"80143",
    "iso:country":"IT",
    "sg:address":"80143 Napoli",
    "sg:city":"Napoli",
    "sg:orig_category":"Bagno - Accessori E Mobili",
    "sg:phone":"+39 081 562 5192",
    "sg:postcode":"80143",
    "sg:province":"Napoli",
    "sg:website":"http://www.incea.it",
    "wof:name":"Incea Spa",
    "wof:placetype":"venue"
},
  "geometry": {"coordinates":[14.282045,40.856991],"type":"Point"}
}