{
  "type": "Feature",
  "properties": {
    "iso:country":"IT",
    "sg:address":"10139 Torino",
    "sg:city":"Torino",
    "sg:orig_category":"Riparazione Dei Mezzi Di Trasporto. Servizi Ausiliari Dei Mezzi Di Trasporto",
    "sg:phone":"+39 011 725788",
    "sg:postcode":"10139",
    "sg:province":"Torino",
    "sg:website":"http://www.gonellapaolo.it",
    "wof:name":"Gonella Paolo",
    "wof:placetype":"venue"
},
  "geometry": {"coordinates":[7.120077,45.126019],"type":"Point"}
}