{
  "type": "Feature",
  "properties": {
    "iso:country":"IT",
    "sg:address":"20090 Pieve Emanuele",
    "sg:city":"Pieve Emanuele",
    "sg:orig_category":"Nautica. Forniture Per Attivita' Commerciali Ed Artigianali",
    "sg:phone":"+39 02 9072 4849",
    "sg:postcode":"20090",
    "sg:province":"Milano",
    "wof:name":"Manifattura Zanutti",
    "wof:placetype":"venue"
},
  "geometry": {"coordinates":[9.170377,45.373833],"type":"Point"}
}