{
  "type": "Feature",
  "properties": {
    "addr:full":"30038 Spinea Spinea Venezia 30038",
    "addr:postcode":"30038;30038",
    "iso:country":"IT",
    "sg:address":"30038 Spinea",
    "sg:city":"Spinea",
    "sg:orig_category":"Utensili Meccanici E Materiali",
    "sg:phone":"+39 041 544 1787",
    "sg:postcode":"30038",
    "sg:province":"Venezia",
    "wof:name":"Effedigi S.n.c.",
    "wof:placetype":"venue"
},
  "geometry": {"coordinates":[12.171155,45.473434],"type":"Point"}
}