{
  "type": "Feature",
  "properties": {
    "iso:country":"IT",
    "sg:address":"37019 Peschiera Del Garda",
    "sg:city":"Peschiera del Garda",
    "sg:orig_category":"Campeggio, Tende, Attrezzature Ed Articoli - Vendita Al Dettaglio",
    "sg:phone":"+39 045 755 3088",
    "sg:postcode":"37019",
    "sg:province":"Verona",
    "wof:name":"West Caravan Di Bendinelli Agnese E C. Sas",
    "wof:placetype":"venue"
},
  "geometry": {"coordinates":[10.668892,45.437851],"type":"Point"}
}