{
  "type": "Feature",
  "properties": {
    "iso:country":"IT",
    "sg:address":"40, Viale Unita' D'italia 70020 Cassano Delle Murge",
    "sg:city":"Cassano delle Murge",
    "sg:classifiers":[
        {
            "category":"Shopping",
            "subcategory":"Computers & Home Electronics",
            "type":"Retail Goods"
        }
    ],
    "sg:phone":"+39 39080775348",
    "sg:postcode":"70020",
    "sg:province":"Bari",
    "sg:tags":[
        "electronic",
        "electrical",
        "equipment"
    ],
    "wof:name":"General Medical Merate Spa",
    "wof:placetype":"venue"
},
  "geometry": {"coordinates":[16.751328,40.892563],"type":"Point"}
}