{
  "type": "Feature",
  "properties": {
    "addr:full":"43058 Sorbolo Sorbolo Parma 43058",
    "addr:postcode":"43058;43058",
    "iso:country":"IT",
    "sg:address":"43058 Sorbolo",
    "sg:city":"Sorbolo",
    "sg:orig_category":"Carni, Salumi E Pesci",
    "sg:phone":"+39 0521 690675",
    "sg:postcode":"43058",
    "sg:province":"Parma",
    "sg:website":"http://www.cominal.it",
    "wof:name":"Cominal Sas",
    "wof:placetype":"venue"
},
  "geometry": {"coordinates":[10.451388,44.855228],"type":"Point"}
}