{
  "type": "Feature",
  "properties": {
    "iso:country":"IT",
    "sg:address":"04100 Latina",
    "sg:city":"Latina",
    "sg:classifiers":[
        {
            "category":"Parking",
            "subcategory":"Lot",
            "type":"Transportation"
        }
    ],
    "sg:phone":"+39 0773 623672",
    "sg:postcode":"04100",
    "sg:province":"Latina",
    "sg:tags":[
        "good",
        "shipment",
        "transport"
    ],
    "sg:website":"http://www.agorascavi.it",
    "wof:name":"Agora Scavi E Trasporti",
    "wof:placetype":"venue"
},
  "geometry": {"coordinates":[12.874495,41.452148],"type":"Point"}
}