{
  "type": "Feature",
  "properties": {
    "iso:country":"IT",
    "sg:address":"46047 Porto Mantovano",
    "sg:city":"Porto Mantovano",
    "sg:classifiers":[
        {
            "category":"Banks & Credit Unions",
            "subcategory":"Investment Brokerage",
            "type":"Services"
        }
    ],
    "sg:phone":"+39 0376 387096",
    "sg:postcode":"46047",
    "sg:province":"Mantova",
    "sg:tags":[
        "activities",
        "industrial",
        "instrument",
        "hospital",
        "equipment",
        "health",
        "systems",
        "supplies",
        "machines"
    ],
    "sg:website":"http://www.ameditalia.com/bioindustry",
    "wof:name":"Bio Industrie Mantova Srl",
    "wof:placetype":"venue"
},
  "geometry": {"coordinates":[10.794166,45.200073],"type":"Point"}
}