{
  "type": "Feature",
  "properties": {
    "iso:country":"IT",
    "sg:address":"25030 Mairano",
    "sg:city":"Mairano",
    "sg:orig_category":"Servizi E Lavori Per Abbigliamento E Pelletterie",
    "sg:phone":"+39 030 975232",
    "sg:postcode":"25030",
    "sg:province":"Brescia",
    "wof:name":"Pellegrini Luigi",
    "wof:placetype":"venue"
},
  "geometry": {"coordinates":[10.214272,45.536011],"type":"Point"}
}