{
  "type": "Feature",
  "properties": {
    "iso:country":"IT",
    "sg:address":"10020 Cambiano",
    "sg:city":"Cambiano",
    "sg:orig_category":"Automobili E Mezzi Di Trasporto",
    "sg:phone":"+39 011 944 1906",
    "sg:postcode":"10020",
    "sg:province":"Torino",
    "wof:name":"S.v. Di Valzan Silvano",
    "wof:placetype":"venue"
},
  "geometry": {"coordinates":[7.773129,44.969387],"type":"Point"}
}