{
  "type": "Feature",
  "properties": {
    "iso:country":"IT",
    "sg:address":"Corso V.emanuele 175; Torre Del Greco; 80059",
    "sg:city":"Torre del Greco",
    "sg:classifiers":[
        {
            "category":"Banks & Credit Unions",
            "subcategory":"Bank",
            "type":"Services"
        }
    ],
    "sg:phone":"+39 081 881 1781",
    "sg:postcode":"80059",
    "sg:province":"Napoli",
    "wof:name":"Banca Di Credito Popolare Scarl",
    "wof:placetype":"venue"
},
  "geometry": {"coordinates":[14.366516,40.789894],"type":"Point"}
}