{
  "type": "Feature",
  "properties": {
    "iso:country":"IT",
    "sg:address":"41012 Carpi",
    "sg:city":"Carpi",
    "sg:orig_category":"Etichette Tessute E Stampate",
    "sg:phone":"+39 059 689032",
    "sg:postcode":"41012",
    "sg:province":"Modena",
    "wof:name":"Carpitex Srl",
    "wof:placetype":"venue"
},
  "geometry": {"coordinates":[10.893676,44.796837],"type":"Point"}
}