{
  "type": "Feature",
  "properties": {
    "addr:full":"27100 Pavia Pavia Pavia 27100",
    "addr:postcode":"27100;27100",
    "iso:country":"IT",
    "sg:address":"27100 Pavia",
    "sg:city":"Pavia",
    "sg:orig_category":"Vetri E Cristalli Temperati E Di Sicurezza",
    "sg:phone":"+39 0382 473393",
    "sg:postcode":"27100",
    "sg:province":"Pavia",
    "wof:name":"Vetreria Vetraplic Di Marabelli L. E Vai M. Snc",
    "wof:placetype":"venue"
},
  "geometry": {"coordinates":[9.160125,45.195839],"type":"Point"}
}