{
  "type": "Feature",
  "properties": {
    "iso:country":"IT",
    "sg:address":"Via F. Maestri, 2/a; Sala Baganza; 43038",
    "sg:city":"Sala Baganza",
    "sg:classifiers":[
        {
            "category":"Banks & Credit Unions",
            "subcategory":"Bank",
            "type":"Services"
        }
    ],
    "sg:phone":"+39 0521 833129",
    "sg:postcode":"43038",
    "sg:province":"Parma",
    "wof:name":"Cassa Di Risparmio Di Parma, E Piacenza Spa",
    "wof:placetype":"venue"
},
  "geometry": {"coordinates":[10.230938,44.713295],"type":"Point"}
}