{
  "type": "Feature",
  "properties": {
    "addr:full":"10020 Andezeno Andezeno Torino 10020",
    "addr:housenumber":"10020",
    "addr:postcode":"10020",
    "addr:street":"Andezeno Andezeno",
    "iso:country":"IT",
    "sg:address":"10020 Andezeno",
    "sg:city":"Andezeno",
    "sg:orig_category":"Prodotti E Manufatti In Materie Plastiche",
    "sg:phone":"+39 011 943 3035",
    "sg:postcode":"10020",
    "sg:province":"Torino",
    "sg:website":"http://www.blistup.it",
    "wof:name":"Blistup Di Valter Barbera E Lina Patrizia Ziccardi Snc",
    "wof:placetype":"venue"
},
  "geometry": {"coordinates":[7.8565688133,45.0305213928],"type":"Point"}
}