{
  "type": "Feature",
  "properties": {
    "iso:country":"IT",
    "sg:address":"Piazzale Roma 468/b; Venice",
    "sg:classifiers":[
        {
            "category":"Travel",
            "subcategory":"Travel Agent",
            "type":"Entertainment"
        }
    ],
    "wof:name":"International Limousine Service",
    "wof:placetype":"venue"
},
  "geometry": {"coordinates":[12.317035,45.437969],"type":"Point"}
}