{
  "type": "Feature",
  "properties": {
    "addr:full":"10149 Torino Torino Torino 10149",
    "addr:postcode":"10149;10149",
    "iso:country":"IT",
    "sg:address":"10149 Torino",
    "sg:city":"Torino",
    "sg:orig_category":"Antenne Radio-televisione",
    "sg:phone":"+39 011 221 7710",
    "sg:postcode":"10149",
    "sg:province":"Torino",
    "wof:name":"Do.it Sas Di Arcuri",
    "wof:placetype":"venue"
},
  "geometry": {"coordinates":[7.674372,45.09333],"type":"Point"}
}