{
  "type": "Feature",
  "properties": {
    "iso:country":"IT",
    "sg:address":"44047 Sant'agostino",
    "sg:city":"Dosso",
    "sg:orig_category":"Termotecnica E Riscaldamento, Apparecchiature E Servizi. Prodotti Vari In Metallo",
    "sg:phone":"+39 0532 359811",
    "sg:postcode":"44047",
    "sg:province":"Ferrara",
    "sg:website":"http://www.lamborghinicalor.it",
    "wof:name":"Lamborghini Calor Spa",
    "wof:placetype":"venue"
},
  "geometry": {"coordinates":[11.381498,44.796173],"type":"Point"}
}