{
  "type": "Feature",
  "properties": {
    "addr:full":"16, Via Boetti Carlo 42100 Reggio Emilia Reggio Nell'Emilia 42100",
    "addr:postcode":"42100;42100",
    "addr:street":"Via Boetti Carlo",
    "iso:country":"IT",
    "sg:address":"16, Via Boetti Carlo 42100 Reggio Emilia",
    "sg:classifiers":[
        {
            "category":"Manufacturing",
            "subcategory":"Rubber & Plastics",
            "type":"Manufacturing & Wholesale Goods"
        }
    ],
    "sg:phone":"+39 0522 271676",
    "sg:postcode":"42100",
    "sg:province":"Reggio Nell'Emilia",
    "wof:name":"Replast (s.r.l.)",
    "wof:placetype":"venue"
},
  "geometry": {"coordinates":[10.647936821,44.7434997559],"type":"Point"}
}