{
  "type": "Feature",
  "properties": {
    "iso:country":"IT",
    "sg:address":"16, Via Firenze 41053 Maranello",
    "sg:city":"Maranello",
    "sg:classifiers":[
        {
            "category":"Shopping",
            "subcategory":"Crafts & Fabrics",
            "type":"Retail Goods"
        }
    ],
    "sg:phone":"+39 0536 948262",
    "sg:postcode":"41053",
    "sg:province":"Modena",
    "sg:tags":[
        "ceramic"
    ],
    "wof:name":"Studio 88 (s.r.l.)",
    "wof:placetype":"venue"
},
  "geometry": {"coordinates":[10.886825,44.521896],"type":"Point"}
}