{
  "type": "Feature",
  "properties": {
    "addr:full":"00185 Roma Roma Roma 00185",
    "addr:postcode":"00185;00185",
    "iso:country":"IT",
    "sg:address":"00185 Roma",
    "sg:city":"Roma",
    "sg:orig_category":"Petroli, Gas E Combustibili",
    "sg:phone":"+39 06 491860",
    "sg:postcode":"00185",
    "sg:province":"Roma",
    "wof:name":"Marchetti Vito",
    "wof:placetype":"venue"
},
  "geometry": {"coordinates":[12.5042085648,41.9020996094],"type":"Point"}
}