{
  "type": "Feature",
  "properties": {
    "iso:country":"IT",
    "sg:address":"20129 Milano",
    "sg:city":"Milano",
    "sg:orig_category":"Servizi Editoriali. Servizi Ausiliari Per Il Trasporto",
    "sg:phone":"+39 02 2941 2366",
    "sg:postcode":"20129",
    "sg:province":"Milano",
    "wof:name":"Euroscuola Di Brusoni Annibale",
    "wof:placetype":"venue"
},
  "geometry": {"coordinates":[9.212106,45.477276],"type":"Point"}
}