{
  "type": "Feature",
  "properties": {
    "iso:country":"IT",
    "sg:address":"30028 San Michele Al Tagliamento",
    "sg:city":"San Michele al Tagliamento",
    "sg:orig_category":"Musica",
    "sg:phone":"+39 0431 59893",
    "sg:postcode":"30028",
    "sg:province":"Venezia",
    "wof:name":"Cinel Giacomo",
    "wof:placetype":"venue"
},
  "geometry": {"coordinates":[12.9981279373,45.758228302],"type":"Point"}
}