{
  "type": "Feature",
  "properties": {
    "addr:full":"40013 Castel Maggiore Castel Maggiore Bologna 40013",
    "addr:postcode":"40013;40013",
    "iso:country":"IT",
    "sg:address":"40013 Castel Maggiore",
    "sg:city":"Castel Maggiore",
    "sg:orig_category":"Servizi E Lavori Per Arredamento E Industria Del Legno",
    "sg:phone":"+39 051 700296",
    "sg:postcode":"40013",
    "sg:province":"Bologna",
    "wof:name":"Silvestrini Srl",
    "wof:placetype":"venue"
},
  "geometry": {"coordinates":[11.369448,44.556404],"type":"Point"}
}