{
  "type": "Feature",
  "properties": {
    "addr:full":"00128 Roma Roma Roma 00128",
    "addr:postcode":"00128;00128",
    "iso:country":"IT",
    "sg:address":"00128 Roma",
    "sg:city":"Roma",
    "sg:orig_category":"Psicologi - Studi",
    "sg:phone":"+39 06 508 2532",
    "sg:postcode":"00128",
    "sg:province":"Roma",
    "wof:name":"Salles Dr. Virginia",
    "wof:placetype":"venue"
},
  "geometry": {"coordinates":[12.4462947845,41.7988586426],"type":"Point"}
}