{
  "type": "Feature",
  "properties": {
    "addr:full":"Viale F.cassani 15 24047 Treviglio Treviglio Bergamo 24047",
    "addr:housenumber":"15",
    "addr:postcode":"24047;24047",
    "addr:street":"Viale F.Cassani",
    "iso:country":"IT",
    "sg:address":"Viale F.cassani 15 24047 Treviglio",
    "sg:city":"Treviglio",
    "sg:classifiers":[
        {
            "category":"Home & Garden",
            "subcategory":"Garden Supply",
            "type":"Retail Goods"
        }
    ],
    "sg:phone":"+39 036 34211",
    "sg:postcode":"24047",
    "sg:province":"Bergamo",
    "sg:tags":[
        "small",
        "tractors",
        "compact-design",
        "tractor"
    ],
    "sg:website":"www.same.samedeutz-fahr.com",
    "wof:name":"Same Deutz-fahr Italia Spa",
    "wof:placetype":"venue"
},
  "geometry": {"coordinates":[9.669952,45.694904],"type":"Point"}
}