{
  "type": "Feature",
  "properties": {
    "iso:country":"IT",
    "sg:address":"Viale Jenner Edoardo 73 20159 Milano",
    "sg:city":"Milano",
    "sg:classifiers":[
        {
            "category":"Utilities",
            "subcategory":"Mobile Phone",
            "type":"Services"
        }
    ],
    "sg:phone":"+39 02 696851",
    "sg:postcode":"20159",
    "sg:province":"Milano",
    "sg:tags":[
        "battery",
        "operated",
        "clock"
    ],
    "sg:website":"www.lorenz.it",
    "wof:name":"Lorenz Spa",
    "wof:placetype":"venue"
},
  "geometry": {"coordinates":[9.172468,45.496513],"type":"Point"}
}