{
  "type": "Feature",
  "properties": {
    "iso:country":"IT",
    "sg:address":"24122 Bergamo",
    "sg:city":"Bergamo",
    "sg:orig_category":"Bevande, Vini E Liquori",
    "sg:phone":"+39 035 236313",
    "sg:postcode":"24122",
    "sg:province":"Bergamo",
    "wof:name":"Acqua Minerale Stella Alpina (s.r.l.)",
    "wof:placetype":"venue"
},
  "geometry": {"coordinates":[9.666595,45.694988],"type":"Point"}
}