{
  "type": "Feature",
  "properties": {
    "addr:full":"Via Porrettana Nord 33/a 40043 Marzabotto Marzabotto Bologna 40043",
    "addr:housenumber":"33 / a",
    "addr:postcode":"40043;40043",
    "addr:street":"Via Porrettana Nord",
    "iso:country":"IT",
    "sg:address":"Via Porrettana Nord 33/a 40043 Marzabotto",
    "sg:city":"Marzabotto",
    "sg:classifiers":[
        {
            "category":"Utilities",
            "subcategory":"Fuel Oil & Lpg",
            "type":"Services"
        }
    ],
    "sg:phone":"+39 051 932836",
    "sg:postcode":"40043",
    "sg:province":"Bologna",
    "sg:tags":[
        "fluid",
        "mechanic"
    ],
    "wof:name":"Bini Giorgio Officina Meccanica",
    "wof:placetype":"venue"
},
  "geometry": {"coordinates":[11.3464813232,44.4942207336],"type":"Point"}
}