{
  "type": "Feature",
  "properties": {
    "addr:full":"13, Via Xx Settembre 19038 Sarzana Sarzana La Spezia 19038",
    "addr:postcode":"19038;19038",
    "addr:street":"Via Xx Settembre",
    "iso:country":"IT",
    "sg:address":"13, Via Xx Settembre 19038 Sarzana",
    "sg:city":"Sarzana",
    "sg:classifiers":[
        {
            "category":"Food & Beverages",
            "subcategory":"Groceries & Convenience Stores",
            "type":"Retail Goods"
        }
    ],
    "sg:phone":"+39 0187 620130",
    "sg:postcode":"19038",
    "sg:province":"La Spezia",
    "sg:tags":[
        "product",
        "related"
    ],
    "wof:name":"Franceschini Luigi Sergio & C. S.n.c.",
    "wof:placetype":"venue"
},
  "geometry": {"coordinates":[9.8292188644,44.1067352295],"type":"Point"}
}