{
  "type": "Feature",
  "properties": {
    "addr:full":"23, Via Calabria 20090 Pieve Emanuele Pieve Emanuele Milano 20090",
    "addr:postcode":"20090;20090",
    "addr:street":"Via Calabria",
    "iso:country":"IT",
    "sg:address":"23, Via Calabria 20090 Pieve Emanuele",
    "sg:city":"Pieve Emanuele",
    "sg:classifiers":[
        {
            "category":"Manufacturing",
            "subcategory":"Rubber & Plastics",
            "type":"Manufacturing & Wholesale Goods"
        }
    ],
    "sg:phone":"+39 02 9072 4621",
    "sg:postcode":"20090",
    "sg:province":"Milano",
    "wof:name":"Camillo Galante (s.r.l.)",
    "wof:placetype":"venue"
},
  "geometry": {"coordinates":[9.174761,45.37431],"type":"Point"}
}