{
  "type": "Feature",
  "properties": {
    "iso:country":"IT",
    "sg:address":"80125 Napoli",
    "sg:city":"Napoli",
    "sg:orig_category":"Banche E Servizi Finanziari",
    "sg:phone":"+39 081 239 0349",
    "sg:postcode":"80125",
    "sg:province":"Napoli",
    "wof:name":"Agenzia Pegni La Flegrea",
    "wof:placetype":"venue"
},
  "geometry": {"coordinates":[14.274931,40.943207],"type":"Point"}
}