{
  "type": "Feature",
  "properties": {
    "addr:full":"24040 Casirate D'adda Bergamo 24040",
    "addr:postcode":"24040;24040",
    "iso:country":"IT",
    "sg:address":"24040 Casirate D'adda",
    "sg:orig_category":"Macchine Utensili E Impianti",
    "sg:phone":"+39 036 387 9171",
    "sg:postcode":"24040",
    "sg:province":"Bergamo",
    "wof:name":"La Modellistica Snc",
    "wof:placetype":"venue"
},
  "geometry": {"coordinates":[9.567351,45.497833],"type":"Point"}
}