{
  "type": "Feature",
  "properties": {
    "addr:full":"860, Via Emilia Est 41100 Modena Modena Modena 41100",
    "addr:housenumber":"860",
    "addr:postcode":"41100;41100",
    "addr:street":"Via Emilia Est",
    "iso:country":"IT",
    "sg:address":"860, Via Emilia Est 41100 Modena",
    "sg:city":"Modena",
    "sg:classifiers":[
        {
            "category":"Communications",
            "subcategory":"Television Station",
            "type":"Services"
        }
    ],
    "sg:phone":"+39 39059375405",
    "sg:postcode":"41100",
    "sg:province":"Modena",
    "sg:tags":[
        "equipment",
        "optical",
        "instrument"
    ],
    "wof:name":"S.m.a.f. (s.p.a.)",
    "wof:placetype":"venue"
},
  "geometry": {"coordinates":[10.936594,44.641979],"type":"Point"}
}