{
  "type": "Feature",
  "properties": {
    "addr:full":"16021 Bargagli Bargagli Genova 16021",
    "addr:postcode":"16021;16021",
    "iso:country":"IT",
    "sg:address":"16021 Bargagli",
    "sg:city":"Bargagli",
    "sg:orig_category":"Forniture Per Agricoltura E Zootecnia",
    "sg:phone":"+39 010 810789",
    "sg:postcode":"16021",
    "sg:province":"Genova",
    "sg:website":"http://www.carbonevivai.com",
    "wof:name":"Carbone Vivai Sas Di Enrico Carbone & C.",
    "wof:placetype":"venue"
},
  "geometry": {"coordinates":[9.0543661118,44.4401397705],"type":"Point"}
}