{
  "type": "Feature",
  "properties": {
    "addr:full":"Strada Braide 27058 Voghera Voghera Pavia 27058",
    "addr:postcode":"27058;27058",
    "addr:street":"Strada Braide",
    "iso:country":"IT",
    "sg:address":"Strada Braide 27058 Voghera",
    "sg:city":"Voghera",
    "sg:classifiers":[
        {
            "category":"Manufacturing",
            "subcategory":"Metals",
            "type":"Manufacturing & Wholesale Goods"
        }
    ],
    "sg:phone":"+39 39038346934",
    "sg:postcode":"27058",
    "sg:province":"Pavia",
    "sg:tags":[
        "metallurgy",
        "metalworking"
    ],
    "wof:name":"S.m.i.t.i. Di Sugliano Pietro E F.lli Guzzon (s.n.c.)",
    "wof:placetype":"venue"
},
  "geometry": {"coordinates":[9.0341825485,45.0026664734],"type":"Point"}
}