{
  "type": "Feature",
  "properties": {
    "iso:country":"IT",
    "sg:address":"48/c, Viale Gramsci Antonio - Camucia 52044 Cortona",
    "sg:city":"Camucia",
    "sg:classifiers":[
        {
            "category":"Professional",
            "subcategory":"Engineering",
            "type":"Services"
        }
    ],
    "sg:phone":"+39 0575 631020",
    "sg:postcode":"52044",
    "sg:province":"Arezzo",
    "sg:tags":[
        "machine",
        "-",
        "mechanical"
    ],
    "wof:name":"Motor X (s.r.l.)",
    "wof:placetype":"venue"
},
  "geometry": {"coordinates":[11.863062,43.471203],"type":"Point"}
}