{
  "type": "Feature",
  "properties": {
    "iso:country":"IT",
    "sg:address":"229, V. Maestra - Terranova 15033 Casale Monferrato",
    "sg:city":"Casale Monferrato",
    "sg:classifiers":[
        {
            "category":"Shopping",
            "type":"Retail Goods"
        }
    ],
    "sg:phone":"+39 0142 805154",
    "sg:postcode":"15033",
    "sg:province":"Alessandria",
    "sg:tags":[
        "finished",
        "-",
        "metallic"
    ],
    "sg:website":"http://www.paginegialle.it/patruccopaolo",
    "wof:name":"Patrucco Paolo",
    "wof:placetype":"venue"
},
  "geometry": {"coordinates":[8.5233392715,45.1638526917],"type":"Point"}
}