{
  "type": "Feature",
  "properties": {
    "iso:country":"IT",
    "sg:address":"10156 Torino",
    "sg:city":"Torino",
    "sg:classifiers":[
        {
            "category":"Professional",
            "subcategory":"Engineering",
            "type":"Services"
        }
    ],
    "sg:phone":"+39 011 273 1708",
    "sg:postcode":"10156",
    "sg:province":"Torino",
    "sg:tags":[
        "equipment",
        "product",
        "industrial",
        "electronic"
    ],
    "wof:name":"Didacta Italia Srl",
    "wof:placetype":"venue"
},
  "geometry": {"coordinates":[7.70615,45.119347],"type":"Point"}
}