{
  "type": "Feature",
  "properties": {
    "addr:full":"50018 Scandicci Scandicci Firenze 50018",
    "addr:postcode":"50018;50018",
    "iso:country":"IT",
    "sg:address":"50018 Scandicci",
    "sg:city":"Scandicci",
    "sg:orig_category":"Olografia",
    "sg:phone":"+39 055 768903",
    "sg:postcode":"50018",
    "sg:province":"Firenze",
    "wof:name":"Solos Srl",
    "wof:placetype":"venue"
},
  "geometry": {"coordinates":[11.180566,43.746059],"type":"Point"}
}