{
  "type": "Feature",
  "properties": {
    "iso:country":"IT",
    "sg:address":"71, Vocabolo Casali 05100 Terni",
    "sg:city":"Terni",
    "sg:classifiers":[
        {
            "category":"Professional",
            "subcategory":"Engineering",
            "type":"Services"
        }
    ],
    "sg:phone":"+39 0744 221065",
    "sg:postcode":"05100",
    "sg:province":"Terni",
    "sg:tags":[
        "machine",
        "-",
        "mechanical"
    ],
    "wof:name":"C.m.d. S.a.s. Di Cesari Marisa E C.",
    "wof:placetype":"venue"
},
  "geometry": {"coordinates":[12.682089,42.552364],"type":"Point"}
}