{
  "type": "Feature",
  "properties": {
    "iso:country":"IT",
    "sg:address":"10, V. Facca 35013 Cittadella",
    "sg:city":"Cittadella",
    "sg:classifiers":[
        {
            "category":"Professional",
            "subcategory":"Engineering",
            "type":"Services"
        }
    ],
    "sg:phone":"+39 049 948 1111",
    "sg:postcode":"35013",
    "sg:province":"Padova",
    "sg:tags":[
        "machine",
        "-",
        "mechanical"
    ],
    "sg:website":"http://www.ine.it:ws_end: :mark:ws:http://www.paginegialle.it/inespa",
    "wof:name":"Ine Spa",
    "wof:placetype":"venue"
},
  "geometry": {"coordinates":[11.787229,45.639488],"type":"Point"}
}