{
  "type": "Feature",
  "properties": {
    "iso:country":"IT",
    "sg:address":"25035 Ospitaletto",
    "sg:city":"Ospitaletto",
    "sg:orig_category":"Aspiratori",
    "sg:phone":"+39 030 684 8036",
    "sg:postcode":"25035",
    "sg:province":"Brescia",
    "sg:website":"http://www.lacoro.it",
    "wof:name":"La Coro Impianti Srl",
    "wof:placetype":"venue"
},
  "geometry": {"coordinates":[10.122912,45.551258],"type":"Point"}
}