{
  "type": "Feature",
  "properties": {
    "iso:country":"IT",
    "sg:address":"22060 Cabiate",
    "sg:city":"Cabiate",
    "sg:classifiers":[
        {
            "category":"Shopping",
            "subcategory":"Gifts & Souvenirs",
            "type":"Retail Goods"
        }
    ],
    "sg:phone":"+39 031 766504",
    "sg:postcode":"22060",
    "sg:province":"Como",
    "sg:tags":[
        "gifts",
        "business"
    ],
    "wof:name":"Utilcasa Fratelli Dell'orto Sas",
    "wof:placetype":"venue"
},
  "geometry": {"coordinates":[9.174851,45.675167],"type":"Point"}
}