{
  "type": "Feature",
  "properties": {
    "iso:country":"IT",
    "sg:address":"5/a, Via Castellana 31050 Vedelago",
    "sg:city":"Vedelago",
    "sg:classifiers":[
        {
            "category":"Shopping",
            "subcategory":"Clothing, Apparel, & Fashions",
            "type":"Retail Goods"
        }
    ],
    "sg:phone":"+39 0423 700032",
    "sg:postcode":"31050",
    "sg:province":"Treviso",
    "sg:tags":[
        "clothes"
    ],
    "wof:name":"Ca.ma. Confezioni Di Campagnolo O. E Marcon M. S.n.c.",
    "wof:placetype":"venue"
},
  "geometry": {"coordinates":[12.102342,45.655933],"type":"Point"}
}