{
  "type": "Feature",
  "properties": {
    "addr:full":"00164 Roma Roma Roma 00164",
    "addr:postcode":"00164;00164",
    "iso:country":"IT",
    "sg:address":"00164 Roma",
    "sg:city":"Roma",
    "sg:orig_category":"Ricambi E Componenti Dei Mezzi Di Trasporto",
    "sg:phone":"+39 06 666 4339",
    "sg:postcode":"00164",
    "sg:province":"Roma",
    "wof:name":"Gasauto S.r.l.",
    "wof:placetype":"venue"
},
  "geometry": {"coordinates":[12.428786,41.870735],"type":"Point"}
}