{
  "type": "Feature",
  "properties": {
    "iso:country":"IT",
    "sg:address":"33087 Pasiano Di Pordenone",
    "sg:city":"Pasiano",
    "sg:orig_category":"Macchine E Forniture Per Arredamento E Industria Del Legno",
    "sg:phone":"+39 0434 625360",
    "sg:postcode":"33087",
    "sg:province":"Pordenone",
    "wof:name":"M.c.m. Di Roman Pietro & C. Snc",
    "wof:placetype":"venue"
},
  "geometry": {"coordinates":[12.632847,45.87114],"type":"Point"}
}