{
  "type": "Feature",
  "properties": {
    "iso:country":"IT",
    "sg:address":"Via Lucca 60/62 50142 Firenze",
    "sg:city":"Firenze",
    "sg:classifiers":[
        {
            "category":"Home & Garden",
            "subcategory":"Hardware",
            "type":"Retail Goods"
        }
    ],
    "sg:phone":"+39 055 732 3806",
    "sg:postcode":"50142",
    "sg:province":"Firenze",
    "sg:tags":[
        "small",
        "ironware",
        "item"
    ],
    "wof:name":"Logos Srl",
    "wof:placetype":"venue"
},
  "geometry": {"coordinates":[10.747909,43.860737],"type":"Point"}
}