{
  "type": "Feature",
  "properties": {
    "addr:full":"64100 Teramo Teramo Teramo 64100",
    "addr:postcode":"64100;64100",
    "iso:country":"IT",
    "sg:address":"64100 Teramo",
    "sg:city":"Teramo",
    "sg:orig_category":"Articoli Pulizia. Macchine E Forniture Per Ecologia E Smaltimento Rifiuti. Forniture Per Attivita' Commerciali Ed Artigianali",
    "sg:phone":"+39 0861 247569",
    "sg:postcode":"64100",
    "sg:province":"Teramo",
    "wof:name":"La Pulicenter Di Di Sante & C. Sas",
    "wof:placetype":"venue"
},
  "geometry": {"coordinates":[13.69477,42.663124],"type":"Point"}
}