{
  "type": "Feature",
  "properties": {
    "iso:country":"IT",
    "sg:address":"60121 Ancona",
    "sg:city":"Ancona",
    "sg:orig_category":"Ricami - Vendita Al Dettaglio",
    "sg:phone":"+39 071 205022",
    "sg:postcode":"60121",
    "sg:province":"Ancona",
    "wof:name":"Cappanera Gioia",
    "wof:placetype":"venue"
},
  "geometry": {"coordinates":[13.515857,43.61858],"type":"Point"}
}