{
  "type": "Feature",
  "properties": {
    "iso:country":"IT",
    "sg:address":"9, Via Volpiano 10034 Chivasso",
    "sg:city":"Chivasso",
    "sg:classifiers":[
        {
            "category":"Professional",
            "subcategory":"Engineering",
            "type":"Services"
        }
    ],
    "sg:phone":"+39 011 911 1462",
    "sg:postcode":"10034",
    "sg:province":"Torino",
    "sg:tags":[
        "machine",
        "-",
        "mechanical"
    ],
    "wof:name":"Di.de.t. S.r.l.",
    "wof:placetype":"venue"
},
  "geometry": {"coordinates":[7.827464,45.181065],"type":"Point"}
}