{
  "type": "Feature",
  "properties": {
    "addr:full":"20085 Locate Di Triulzi Locate di Triulzi Milano 20085",
    "addr:postcode":"20085;20085",
    "iso:country":"IT",
    "sg:address":"20085 Locate Di Triulzi",
    "sg:city":"Locate di Triulzi",
    "sg:orig_category":"Carni, Salumi E Pesci",
    "sg:phone":"+39 02 907 9167",
    "sg:postcode":"20085",
    "sg:province":"Milano",
    "wof:name":"Sconfietti Natalino",
    "wof:placetype":"venue"
},
  "geometry": {"coordinates":[9.274845,45.403664],"type":"Point"}
}