{
  "type": "Feature",
  "properties": {
    "addr:full":"75, Via Filippo Da Desio 20033 Desio Desio Milano 20033",
    "addr:postcode":"20033;20033",
    "addr:street":"Via Filippo Da Desio",
    "iso:country":"IT",
    "sg:address":"75, Via Filippo Da Desio 20033 Desio",
    "sg:city":"Desio",
    "sg:classifiers":[
        {
            "category":"Manufacturing",
            "subcategory":"Metals",
            "type":"Manufacturing & Wholesale Goods"
        }
    ],
    "sg:phone":"+39 036 262 4629",
    "sg:postcode":"20033",
    "sg:province":"Milano",
    "sg:tags":[
        "metallurgy",
        "metalworking"
    ],
    "wof:name":"Profilati A Freddo Brollo (s.p.a.)",
    "wof:placetype":"venue"
},
  "geometry": {"coordinates":[9.2183961868,45.6255645752],"type":"Point"}
}