{
  "type": "Feature",
  "properties": {
    "addr:full":"00165 Roma Roma Roma 00165",
    "addr:postcode":"00165;00165",
    "iso:country":"IT",
    "sg:address":"00165 Roma",
    "sg:city":"Roma",
    "sg:orig_category":"Articoli Da Regalo. Shopping. Regalistica Aziendale",
    "sg:phone":"+39 06 6601 8069",
    "sg:postcode":"00165",
    "sg:province":"Roma",
    "sg:website":"http://www.lorenfa.com",
    "wof:name":"Lorenfa Di Simeone Fabio",
    "wof:placetype":"venue"
},
  "geometry": {"coordinates":[12.434281,41.897461],"type":"Point"}
}