{
  "type": "Feature",
  "properties": {
    "iso:country":"IT",
    "sg:address":"20127 Milano",
    "sg:city":"Milano",
    "sg:orig_category":"Centri Di Estetica E Cosmesi E Servizi. Prodotti Cosmetici E Da Toeletta",
    "sg:phone":"+39 02 2614 1451",
    "sg:postcode":"20127",
    "sg:province":"Milano",
    "wof:name":"Laboratorio Centri New Man International Sas Di Baroni Giampietro & C.",
    "wof:placetype":"venue"
},
  "geometry": {"coordinates":[9.222342,45.503216],"type":"Point"}
}