{
  "type": "Feature",
  "properties": {
    "addr:full":"36028 Rossano Veneto Rossano Veneto Vicenza 36028",
    "addr:postcode":"36028;36028",
    "addr:street":"Veneto",
    "iso:country":"IT",
    "sg:address":"36028 Rossano Veneto",
    "sg:city":"Rossano Veneto",
    "sg:orig_category":"Forniture Per Abbigliamento E Pelletterie",
    "sg:phone":"+39 0424 848250",
    "sg:postcode":"36028",
    "sg:province":"Vicenza",
    "wof:name":"Baggio Giuseppe",
    "wof:placetype":"venue"
},
  "geometry": {"coordinates":[11.8126020432,45.7165184021],"type":"Point"}
}