{
  "type": "Feature",
  "properties": {
    "addr:full":"Via Loc. Torri Chiusine 53043 Chiusi Chiusi Siena 53043",
    "addr:postcode":"53043;53043",
    "addr:street":"Via Loc. Torri Chiusine",
    "iso:country":"IT",
    "sg:address":"Via Loc. Torri Chiusine 53043 Chiusi",
    "sg:city":"Chiusi",
    "sg:classifiers":[
        {
            "category":"Farming",
            "subcategory":"Livestock Farm",
            "type":"Manufacturing & Wholesale Goods"
        }
    ],
    "sg:phone":"+39 0578 227686",
    "sg:postcode":"53043",
    "sg:province":"Siena",
    "sg:tags":[
        "agriculture"
    ],
    "wof:name":"Margheriti Fratelli E. & M.",
    "wof:placetype":"venue"
},
  "geometry": {"coordinates":[11.330514,43.318661],"type":"Point"}
}