{
  "type": "Feature",
  "properties": {
    "addr:full":"09123 Cagliari Cagliari Cagliari 09123",
    "addr:postcode":"09123;09123",
    "iso:country":"IT",
    "sg:address":"09123 Cagliari",
    "sg:city":"Cagliari",
    "sg:orig_category":"Arredo Cucina Ed Elettrodomestici. Elettrodomestici",
    "sg:phone":"+39 070 273998",
    "sg:postcode":"09123",
    "sg:province":"Cagliari",
    "wof:name":"Tumminia Mirko",
    "wof:placetype":"venue"
},
  "geometry": {"coordinates":[9.104519,39.220097],"type":"Point"}
}