{
  "type": "Feature",
  "properties": {
    "addr:full":"20083 Gaggiano Gaggiano Milano 20083",
    "addr:postcode":"20083;20083",
    "iso:country":"IT",
    "sg:address":"20083 Gaggiano",
    "sg:city":"Gaggiano",
    "sg:classifiers":[
        {
            "category":"Banks & Credit Unions",
            "subcategory":"Atm",
            "type":"Services"
        }
    ],
    "sg:phone":"+39 02 9084 2041",
    "sg:postcode":"20083",
    "sg:province":"Milano",
    "sg:tags":[
        "building",
        "articles",
        "product",
        "plastics",
        "supply",
        "civil",
        "industry",
        "material",
        "packaging",
        "packing",
        "supplies",
        "works"
    ],
    "wof:name":"Ram Sas",
    "wof:placetype":"venue"
},
  "geometry": {"coordinates":[9.0294103622,45.3996887207],"type":"Point"}
}