{
  "type": "Feature",
  "properties": {
    "iso:country":"IT",
    "sg:address":"70016 Noicattaro",
    "sg:city":"Noicattaro",
    "sg:orig_category":"Servizi E Lavori Per Agricoltura E Zootecnia. Imprese Di Costruzioni Civili Ed Industriali",
    "sg:phone":"+39 080 478 1430",
    "sg:postcode":"70016",
    "sg:province":"Bari",
    "wof:name":"Scarpelli Marino",
    "wof:placetype":"venue"
},
  "geometry": {"coordinates":[16.986675,41.036266],"type":"Point"}
}