{
  "type": "Feature",
  "properties": {
    "iso:country":"IT",
    "sg:address":"10156 Torino",
    "sg:city":"Torino",
    "sg:orig_category":"Insegne Luminose",
    "sg:phone":"+39 011 470 1580",
    "sg:postcode":"10156",
    "sg:province":"Torino",
    "sg:website":"http://www.splendorneonrigotti.it",
    "wof:name":"Splendor Neon Di Rigotti Mario & C. Snc",
    "wof:placetype":"venue"
},
  "geometry": {"coordinates":[7.70615,45.119347],"type":"Point"}
}