{
  "type": "Feature",
  "properties": {
    "addr:full":"3/d, Via Moro 10040 San Gillio San Gillio Torino 10040",
    "addr:housenumber":"3 / d",
    "addr:postcode":"10040;gillio;10040",
    "addr:street":"Via Moro",
    "iso:country":"IT",
    "sg:address":"3/d, Via Moro 10040 San Gillio",
    "sg:city":"San Gillio",
    "sg:classifiers":[
        {
            "category":"Professional",
            "subcategory":"Engineering",
            "type":"Services"
        }
    ],
    "sg:phone":"+39 011 984 0269",
    "sg:postcode":"10040",
    "sg:province":"Torino",
    "sg:tags":[
        "machine",
        "-",
        "mechanical"
    ],
    "wof:name":"P.a.s.i.t. S.r.l.",
    "wof:placetype":"venue"
},
  "geometry": {"coordinates":[7.686619,45.07056],"type":"Point"}
}