{
  "type": "Feature",
  "properties": {
    "iso:country":"IT",
    "sg:address":"Calata Vittorio Veneto 80133 Napoli",
    "sg:city":"Napoli",
    "sg:classifiers":[
        {
            "category":"Autos & Motor Vehicles",
            "subcategory":"Boat Sales",
            "type":"Retail Goods"
        }
    ],
    "sg:phone":"+39 081 554 3507",
    "sg:postcode":"80133",
    "sg:province":"Napoli",
    "wof:name":"O.r.n.i. (s.n.c.)",
    "wof:placetype":"venue"
},
  "geometry": {"coordinates":[14.281948,40.84185],"type":"Point"}
}