{
  "type": "Feature",
  "properties": {
    "iso:country":"IT",
    "sg:address":"06059 Todi",
    "sg:city":"Todi",
    "sg:orig_category":"Serramenti Ed Infissi",
    "sg:phone":"+39 075 898 7339",
    "sg:postcode":"06059",
    "sg:province":"Perugia",
    "wof:name":"A.p.i.a.f. Snc",
    "wof:placetype":"venue"
},
  "geometry": {"coordinates":[11.942351,43.071407],"type":"Point"}
}