{
  "type": "Feature",
  "properties": {
    "addr:full":"41011 Campogalliano Campogalliano Modena 41011",
    "addr:postcode":"41011;41011",
    "iso:country":"IT",
    "sg:address":"41011 Campogalliano",
    "sg:city":"Campogalliano",
    "sg:orig_category":"Macchine Ed Impianti Per Edilizia E Lavori Pubblici",
    "sg:phone":"+39 059 526728",
    "sg:postcode":"41011",
    "sg:province":"Modena",
    "wof:name":"Ime (s.r.l.)",
    "wof:placetype":"venue"
},
  "geometry": {"coordinates":[10.821028,44.666988],"type":"Point"}
}