{
  "type": "Feature",
  "properties": {
    "iso:country":"IT",
    "sg:address":"09124 Cagliari",
    "sg:city":"Cagliari",
    "sg:orig_category":"Hobbistica",
    "sg:phone":"+39 070 664684",
    "sg:postcode":"09124",
    "sg:province":"Cagliari",
    "wof:name":"Mondial Phil Collezionismo Srl",
    "wof:placetype":"venue"
},
  "geometry": {"coordinates":[9.112062,39.214626],"type":"Point"}
}