{
  "type": "Feature",
  "properties": {
    "addr:full":"Via Dell' Aviazione Merci 16154 Genova Genova Genova 16154",
    "addr:postcode":"16154;16154",
    "addr:street":"Via Dell ' Aviazione Merci",
    "iso:country":"IT",
    "sg:address":"Via Dell' Aviazione Merci 16154 Genova",
    "sg:city":"Genova",
    "sg:classifiers":[
        {
            "category":"Banks & Credit Unions",
            "subcategory":"Investment Brokerage",
            "type":"Services"
        }
    ],
    "sg:phone":"+39 010 651 7967",
    "sg:postcode":"16154",
    "sg:province":"Genova",
    "sg:tags":[
        "-",
        "transport",
        "related"
    ],
    "wof:name":"Intertransport Spedizioni Aeree",
    "wof:placetype":"venue"
},
  "geometry": {"coordinates":[8.933989,44.407063],"type":"Point"}
}