{
  "type": "Feature",
  "properties": {
    "iso:country":"IT",
    "sg:address":"20123 Milano",
    "sg:city":"Milano",
    "sg:orig_category":"Alberghi E Strutture Extra Alberghiere. Ospedali E Servizi Sanitari",
    "sg:phone":"+39 0285991",
    "sg:postcode":"20123",
    "sg:province":"Milano",
    "wof:name":"Ospedale S.giuseppe",
    "wof:placetype":"venue"
},
  "geometry": {"coordinates":[9.171526,45.463001],"type":"Point"}
}