{
  "type": "Feature",
  "properties": {
    "addr:full":"00055 Ladispoli Ladispoli Roma 00055",
    "addr:postcode":"00055;roma 00055",
    "iso:country":"IT",
    "sg:address":"00055 Ladispoli",
    "sg:city":"Ladispoli",
    "sg:orig_category":"Servizi Per Lo Sport E Il Tempo Libero. Alberghi E Strutture Extra Alberghiere",
    "sg:phone":"+39 06 994 6015",
    "sg:postcode":"00055",
    "sg:province":"Roma",
    "wof:name":"Pirisi Anna Rita",
    "wof:placetype":"venue"
},
  "geometry": {"coordinates":[12.517396,41.904385],"type":"Point"}
}