{
  "type": "Feature",
  "properties": {
    "addr:full":"40128 Bologna Bologna Bologna 40128",
    "addr:postcode":"40128;40128",
    "iso:country":"IT",
    "sg:address":"40128 Bologna",
    "sg:city":"Bologna",
    "sg:orig_category":"Medici. Assicurazioni E Servizi Assicurativi. Avvocati, Notai E Servizi Legali. Professionisti - Studi E Servizi Ed Associazioni Di Interesse Aziendale",
    "sg:phone":"+39 051 631 1764",
    "sg:postcode":"40128",
    "sg:province":"Bologna",
    "wof:name":"Montesi Maurizio",
    "wof:placetype":"venue"
},
  "geometry": {"coordinates":[11.36195755,44.5333709717],"type":"Point"}
}