{
  "type": "Feature",
  "properties": {
    "iso:country":"IT",
    "sg:address":"29, Via Dei Colombi 09126 Cagliari",
    "sg:city":"Cagliari",
    "sg:classifiers":[
        {
            "category":"Utilities",
            "subcategory":"Electric",
            "type":"Services"
        }
    ],
    "sg:phone":"+39 39070306462",
    "sg:postcode":"09126",
    "sg:province":"Cagliari",
    "sg:tags":[
        "component",
        "electronic"
    ],
    "wof:name":"Teletron Electronics (s.r.l.)",
    "wof:placetype":"venue"
},
  "geometry": {"coordinates":[9.134922,39.209148],"type":"Point"}
}