{
  "type": "Feature",
  "properties": {
    "iso:country":"IT",
    "sg:address":"42044 Gualtieri",
    "sg:classifiers":[
        {
            "category":"Manufacturing",
            "subcategory":"Motor Vehicles & Parts",
            "type":"Manufacturing & Wholesale Goods"
        }
    ],
    "sg:phone":"+39 0522 828414",
    "sg:postcode":"42044",
    "sg:province":"Reggio Nell'Emilia",
    "sg:tags":[
        "vehicles",
        "accessory"
    ],
    "wof:name":"Plasticpadana System Srl",
    "wof:placetype":"venue"
},
  "geometry": {"coordinates":[10.5169687271,44.7417144775],"type":"Point"}
}