{
  "type": "Feature",
  "properties": {
    "iso:country":"IT",
    "sg:address":"20127 Milano",
    "sg:city":"Milano",
    "sg:orig_category":"Servizi E Lavori Per Abbigliamento E Pelletterie",
    "sg:phone":"+39 02 282 7413",
    "sg:postcode":"20127",
    "sg:province":"Milano",
    "wof:name":"Lisotti Pasqualina",
    "wof:placetype":"venue"
},
  "geometry": {"coordinates":[9.213186,45.49292],"type":"Point"}
}