{
  "type": "Feature",
  "properties": {
    "addr:full":"6, Via Privata Primo Maggio 23862 Civate Civate Lecco 23862",
    "addr:postcode":"23862;23862",
    "addr:street":"Via Privata Primo Maggio",
    "iso:country":"IT",
    "sg:address":"6, Via Privata Primo Maggio 23862 Civate",
    "sg:city":"Civate",
    "sg:classifiers":[
        {
            "category":"Manufacturing",
            "subcategory":"Metals",
            "type":"Manufacturing & Wholesale Goods"
        }
    ],
    "sg:phone":"+39 0341 550391",
    "sg:postcode":"23862",
    "sg:province":"Lecco",
    "sg:tags":[
        "metallurgy",
        "metalworking"
    ],
    "wof:name":"Camusso Tubi (s.p.a.)",
    "wof:placetype":"venue"
},
  "geometry": {"coordinates":[9.3900709152,45.8529815674],"type":"Point"}
}