{
  "type": "Feature",
  "properties": {
    "addr:full":"51015 Monsummano Terme Monsummano Terme Pistoia 51015",
    "addr:postcode":"51015;51015",
    "iso:country":"IT",
    "sg:address":"51015 Monsummano Terme",
    "sg:city":"Monsummano Terme",
    "sg:classifiers":[
        {
            "category":"Organizations",
            "subcategory":"Professional Association",
            "type":"Services"
        }
    ],
    "sg:phone":"+39 0572 950725",
    "sg:postcode":"51015",
    "sg:province":"Pistoia",
    "sg:tags":[
        "activities",
        "commercial",
        "non-professional",
        "equipment",
        "engineering",
        "electrical",
        "artisan",
        "supplies",
        "accommodation",
        "furnishing"
    ],
    "sg:website":"http://www.byness.it",
    "wof:name":"Byness Srl",
    "wof:placetype":"venue"
},
  "geometry": {"coordinates":[10.8338594437,43.8559799194],"type":"Point"}
}