{
  "type": "Feature",
  "properties": {
    "iso:country":"IT",
    "sg:address":"20131 Milano",
    "sg:city":"Milano",
    "sg:orig_category":"Non-classified Establishments",
    "sg:phone":"+39 02 2951 2030",
    "sg:postcode":"20131",
    "sg:province":"Milano",
    "wof:name":"Misticoni Lidia",
    "wof:placetype":"venue"
},
  "geometry": {"coordinates":[9.217319,45.484467],"type":"Point"}
}