{
  "type": "Feature",
  "properties": {
    "addr:full":"2/a, Via Perini 60010 Ostra Vetere Ostra Ancona 60010",
    "addr:housenumber":"2 / a",
    "addr:postcode":"60010;60010",
    "addr:street":"Via Perini",
    "iso:country":"IT",
    "sg:address":"2/a, Via Perini 60010 Ostra Vetere",
    "sg:city":"Ostra",
    "sg:classifiers":[
        {
            "category":"Manufacturing",
            "subcategory":"Metals",
            "type":"Manufacturing & Wholesale Goods"
        }
    ],
    "sg:phone":"+39 39071965301",
    "sg:postcode":"60010",
    "sg:province":"Ancona",
    "sg:tags":[
        "metallurgy",
        "metalworking"
    ],
    "wof:name":"Flying Fasteners S.r.l.",
    "wof:placetype":"venue"
},
  "geometry": {"coordinates":[13.5187568665,43.6158561707],"type":"Point"}
}