{
  "type": "Feature",
  "properties": {
    "iso:country":"IT",
    "sg:address":"Via Dell'industria 42 42025 Cavriago",
    "sg:classifiers":[
        {
            "category":"Banks & Credit Unions",
            "subcategory":"Investment Brokerage",
            "type":"Services"
        }
    ],
    "sg:phone":"+39 0522 941192",
    "sg:postcode":"42025",
    "sg:province":"Reggio Nell'Emilia",
    "sg:tags":[
        "dynamic",
        "components",
        "maintenance",
        "overhauling"
    ],
    "wof:name":"Oleodinamica Bi.effe Srl",
    "wof:placetype":"venue"
},
  "geometry": {"coordinates":[10.552473,44.719162],"type":"Point"}
}