{
  "type": "Feature",
  "properties": {
    "addr:full":"14045 Incisa Scapaccino Incisa Scapaccino Asti 14045",
    "addr:postcode":"14045;14045",
    "iso:country":"IT",
    "sg:address":"14045 Incisa Scapaccino",
    "sg:city":"Incisa Scapaccino",
    "sg:orig_category":"Forniture Per Agricoltura E Zootecnia. Animali Domestici",
    "sg:phone":"+39 0141 747820",
    "sg:postcode":"14045",
    "sg:province":"Asti",
    "wof:name":"Globalcibo Srl",
    "wof:placetype":"venue"
},
  "geometry": {"coordinates":[8.3704462051,44.8071098328],"type":"Point"}
}