{
  "type": "Feature",
  "properties": {
    "iso:country":"IT",
    "sg:address":"Via Delle Nazioni; Gatteo; 47043",
    "sg:city":"Gatteo",
    "sg:classifiers":[
        {
            "category":"Banks & Credit Unions",
            "subcategory":"Bank",
            "type":"Services"
        }
    ],
    "sg:phone":"+39 0547 86193",
    "sg:postcode":"47043",
    "sg:province":"Forl\u00ec-Cesena",
    "wof:name":"Rolo Banca 1473 Spa",
    "wof:placetype":"venue"
},
  "geometry": {"coordinates":[12.432521,44.17131],"type":"Point"}
}