{
  "type": "Feature",
  "properties": {
    "iso:country":"IT",
    "sg:address":"Via Galileo Galilei 3 22070 Guanzate",
    "sg:city":"Guanzate",
    "sg:classifiers":[
        {
            "category":"Health Services",
            "subcategory":"Podiatrist",
            "type":"Services"
        }
    ],
    "sg:phone":"+39 031 352 9129",
    "sg:postcode":"22070",
    "sg:province":"Como",
    "sg:tags":[
        "incubator"
    ],
    "sg:website":"www.victoria-srl.com",
    "wof:name":"Victoria Srl",
    "wof:placetype":"venue"
},
  "geometry": {"coordinates":[9.034117,45.76469],"type":"Point"}
}