{
  "type": "Feature",
  "properties": {
    "iso:country":"IT",
    "sg:address":"Via Dei Vigneti 57031 Capoliveri",
    "sg:city":"Capoliveri",
    "sg:classifiers":[
        {
            "category":"Manufacturing",
            "subcategory":"Tools & Machinery",
            "type":"Manufacturing & Wholesale Goods"
        }
    ],
    "sg:phone":"+39 0565 964488",
    "sg:postcode":"57031",
    "sg:province":"Livorno",
    "sg:tags":[
        "environment",
        "equipment",
        "-"
    ],
    "wof:name":"Beniamino Cooperativa Sociale Elba A R.l.",
    "wof:placetype":"venue"
},
  "geometry": {"coordinates":[10.306466,42.764778],"type":"Point"}
}