{
  "type": "Feature",
  "properties": {
    "addr:full":"40132 Bologna Bologna Bologna 40132",
    "addr:postcode":"40132;40132",
    "iso:country":"IT",
    "sg:address":"40132 Bologna",
    "sg:city":"Bologna",
    "sg:orig_category":"Macchine, Impianti Ed Attrezzature Per Industria Alimentare E Bevande. Macchine, Impianti Ed Attrezzature Industria Chimica",
    "sg:phone":"+39 051 406650",
    "sg:postcode":"40132",
    "sg:province":"Bologna",
    "wof:name":"Molitecnica S.r.l.",
    "wof:placetype":"venue"
},
  "geometry": {"coordinates":[11.286427,44.528667],"type":"Point"}
}