{
  "type": "Feature",
  "properties": {
    "addr:full":"Via Rondanina 40026 Imola Imola Bologna 40026",
    "addr:postcode":"40026;40026",
    "addr:street":"Via Rondanina",
    "iso:country":"IT",
    "sg:address":"Via Rondanina 40026 Imola",
    "sg:city":"Imola",
    "sg:classifiers":[
        {
            "category":"Farming",
            "subcategory":"Livestock Farm",
            "type":"Manufacturing & Wholesale Goods"
        }
    ],
    "sg:phone":"+39 39054276511",
    "sg:postcode":"40026",
    "sg:province":"Bologna",
    "sg:tags":[
        "agriculture"
    ],
    "wof:name":"Avicola Selice S.p.a.",
    "wof:placetype":"venue"
},
  "geometry": {"coordinates":[11.768822,44.446926],"type":"Point"}
}