{
  "type": "Feature",
  "properties": {
    "addr:full":"10121 Torino Torino Torino 10121",
    "addr:postcode":"10121;10121",
    "iso:country":"IT",
    "sg:address":"10121 Torino",
    "sg:city":"Torino",
    "sg:classifiers":[
        {
            "category":"Professional",
            "subcategory":"Business Services",
            "type":"Services"
        }
    ],
    "sg:phone":"+39 011 562 5522",
    "sg:postcode":"10121",
    "sg:province":"Torino",
    "sg:tags":[
        "support",
        "companies",
        "events",
        "trade"
    ],
    "wof:name":"Quinto Srl",
    "wof:placetype":"venue"
},
  "geometry": {"coordinates":[7.6781,45.067207],"type":"Point"}
}