{
  "type": "Feature",
  "properties": {
    "addr:full":"25017 Lonato Lonato Brescia 25017",
    "addr:postcode":"25017;25017",
    "iso:country":"IT",
    "sg:address":"25017 Lonato",
    "sg:city":"Lonato",
    "sg:orig_category":"Materiali Edili",
    "sg:phone":"+39 030 991 3132",
    "sg:postcode":"25017",
    "sg:province":"Brescia",
    "wof:name":"La Murosan Tecnologie Edili Srl",
    "wof:placetype":"venue"
},
  "geometry": {"coordinates":[10.463279,45.46571],"type":"Point"}
}