{
  "type": "Feature",
  "properties": {
    "addr:full":"40054 Budrio Budrio Bologna 40054",
    "addr:postcode":"40054;40054",
    "iso:country":"IT",
    "sg:address":"40054 Budrio",
    "sg:city":"Budrio",
    "sg:orig_category":"Servizi Ausiliari Dei Mezzi Di Trasporto",
    "sg:phone":"+39 051 801980",
    "sg:postcode":"40054",
    "sg:province":"Bologna",
    "wof:name":"Stefanoni Carla E C. S.a.s.",
    "wof:placetype":"venue"
},
  "geometry": {"coordinates":[11.569953,44.557564],"type":"Point"}
}