{
  "type": "Feature",
  "properties": {
    "iso:country":"IT",
    "sg:address":"Via Lainate 1456 21042 Caronno Pertusella",
    "sg:city":"Caronno Pertusella",
    "sg:classifiers":[
        {
            "category":"Wholesale",
            "subcategory":"Chemicals & Plastics",
            "type":"Manufacturing & Wholesale Goods"
        }
    ],
    "sg:phone":"+39 02 9645 0280",
    "sg:postcode":"21042",
    "sg:province":"Varese",
    "sg:tags":[
        "textile",
        "product",
        "industry"
    ],
    "sg:website":"www.rottaitalia.it",
    "wof:name":"Ric Rotta Industria Chimica S.p.a.",
    "wof:placetype":"venue"
},
  "geometry": {"coordinates":[9.042449,45.583084],"type":"Point"}
}