{
  "type": "Feature",
  "properties": {
    "iso:country":"IT",
    "sg:address":"Ctr. Landolina - Donnalucata 97018 Scicli",
    "sg:city":"Donnalucata",
    "sg:classifiers":[
        {
            "category":"Food & Beverages",
            "subcategory":"Groceries & Convenience Stores",
            "type":"Retail Goods"
        }
    ],
    "sg:phone":"+39 0932 937944",
    "sg:postcode":"97018",
    "sg:province":"Ragusa",
    "sg:tags":[
        "product",
        "related"
    ],
    "sg:website":"http://www.cooprisorgimento.it",
    "wof:name":"Risorgimento",
    "wof:placetype":"venue"
},
  "geometry": {"coordinates":[14.7285032272,36.9259109497],"type":"Point"}
}