{
  "type": "Feature",
  "properties": {
    "addr:full":"1, Strada Nascosa 04100 Latina Latina Latina 04100",
    "addr:postcode":"04100;04100",
    "addr:street":"Strada Nascosa",
    "iso:country":"IT",
    "sg:address":"1, Strada Nascosa 04100 Latina",
    "sg:city":"Latina",
    "sg:classifiers":[
        {
            "category":"Shopping",
            "subcategory":"Computers & Home Electronics",
            "type":"Retail Goods"
        }
    ],
    "sg:phone":"+39 0773 601056",
    "sg:postcode":"04100",
    "sg:province":"Latina",
    "sg:tags":[
        "electronic",
        "electrical",
        "equipment"
    ],
    "wof:name":"Onorati Elettroforniture S.r.l.",
    "wof:placetype":"venue"
},
  "geometry": {"coordinates":[12.841578,41.453476],"type":"Point"}
}