{
  "type": "Feature",
  "properties": {
    "iso:country":"IT",
    "sg:address":"101, Via Della Musia 25135 Brescia",
    "sg:city":"Brescia",
    "sg:classifiers":[
        {
            "category":"Shopping",
            "type":"Retail Goods"
        }
    ],
    "sg:phone":"+39 030 336 6279",
    "sg:postcode":"25135",
    "sg:province":"Brescia",
    "sg:tags":[
        "finished",
        "-",
        "metallic"
    ],
    "wof:name":"Bossini Stampaggio (s.r.l.)",
    "wof:placetype":"venue"
},
  "geometry": {"coordinates":[10.2901992798,45.5153312683],"type":"Point"}
}