{
  "type": "Feature",
  "properties": {
    "addr:full":"19, Via Casella 52010 Capolona Capolona Arezzo 52010",
    "addr:postcode":"52010;52010",
    "addr:street":"Via Casella",
    "iso:country":"IT",
    "sg:address":"19, Via Casella 52010 Capolona",
    "sg:city":"Capolona",
    "sg:classifiers":[
        {
            "category":"Manufacturing",
            "subcategory":"Metals",
            "type":"Manufacturing & Wholesale Goods"
        }
    ],
    "sg:phone":"+39 0575 420765",
    "sg:postcode":"52010",
    "sg:province":"Arezzo",
    "sg:tags":[
        "metallurgy",
        "metalworking"
    ],
    "wof:name":"Oro Azzurro (s.r.l)",
    "wof:placetype":"venue"
},
  "geometry": {"coordinates":[11.8596744537,43.565486908],"type":"Point"}
}