{
  "type": "Feature",
  "properties": {
    "iso:country":"IT",
    "sg:address":"10098 Rivoli",
    "sg:city":"Rivoli",
    "sg:orig_category":"Arti Grafiche",
    "sg:phone":"+39 011 957 2960",
    "sg:postcode":"10098",
    "sg:province":"Torino",
    "sg:website":"http://www.dfserigrafia.it",
    "wof:name":"D.f. Serigrafia",
    "wof:placetype":"venue"
},
  "geometry": {"coordinates":[7.588079,45.073185],"type":"Point"}
}