{
  "type": "Feature",
  "properties": {
    "addr:full":"20127 Milano Milano Milano 20127",
    "addr:postcode":"20127;20127",
    "iso:country":"IT",
    "sg:address":"20127 Milano",
    "sg:city":"Milano",
    "sg:orig_category":"Forniture Per Uffici. Servizi Vari Di Interesse Pubblico",
    "sg:phone":"+39 02 261 3112",
    "sg:postcode":"20127",
    "sg:province":"Milano",
    "wof:name":"Fortarezza Rocco",
    "wof:placetype":"venue"
},
  "geometry": {"coordinates":[9.2315950394,45.4973983765],"type":"Point"}
}