{
  "type": "Feature",
  "properties": {
    "iso:country":"IT",
    "sg:address":"20020 Arese",
    "sg:city":"Arese",
    "sg:orig_category":"Professionisti - Studi E Servizi Ed Associazioni Di Interesse Aziendale. Associazioni Ed Organismi Di Interesse Pubblico. Chiese Ed Associazioni Religiose",
    "sg:phone":"+39 02 938 5454",
    "sg:postcode":"20020",
    "sg:province":"Milano",
    "wof:name":"Parrocchia Maria Aiuto Dei Cristiani",
    "wof:placetype":"venue"
},
  "geometry": {"coordinates":[9.0769176483,45.5565223694],"type":"Point"}
}