{
  "type": "Feature",
  "properties": {
    "iso:country":"IT",
    "sg:address":"20132 Milano",
    "sg:city":"Milano",
    "sg:orig_category":"Utensili Meccanici E Materiali. Elettrotecnica Industriale, Prodotti E Apparecchiature",
    "sg:phone":"+39 02 261 9704",
    "sg:postcode":"20132",
    "sg:province":"Milano",
    "wof:name":"Labras Lattanzi",
    "wof:placetype":"venue"
},
  "geometry": {"coordinates":[9.236725,45.499172],"type":"Point"}
}