{
  "type": "Feature",
  "properties": {
    "addr:full":"98123 Messina Messina Messina 98123",
    "addr:postcode":"98123;98123",
    "iso:country":"IT",
    "sg:address":"98123 Messina",
    "sg:city":"Messina",
    "sg:orig_category":"Forniture Per Abbigliamento E Pelletterie",
    "sg:phone":"+39 090 718712",
    "sg:postcode":"98123",
    "sg:province":"Messina",
    "wof:name":"Nanni C.",
    "wof:placetype":"venue"
},
  "geometry": {"coordinates":[15.5546865463,38.1852531433],"type":"Point"}
}