{
  "type": "Feature",
  "properties": {
    "iso:country":"IT",
    "sg:address":"23900 Lecco",
    "sg:city":"Lecco",
    "sg:orig_category":"Cartotecnica E Servizi. Forniture Per Uffici",
    "sg:phone":"+39 0341 362314",
    "sg:postcode":"23900",
    "sg:province":"Lecco",
    "sg:website":"http://www.cogliatieleris.it",
    "wof:name":"Cogliati & Leris Srl",
    "wof:placetype":"venue"
},
  "geometry": {"coordinates":[9.406668,45.843533],"type":"Point"}
}