{
  "type": "Feature",
  "properties": {
    "iso:country":"IT",
    "sg:address":"37046 Minerbe",
    "sg:city":"Minerbe",
    "sg:orig_category":"Alimenti Conservati",
    "sg:phone":"+39 0442 640011",
    "sg:postcode":"37046",
    "sg:province":"Verona",
    "wof:name":"Ferrari & Franceschetti - Ista' Spa",
    "wof:placetype":"venue"
},
  "geometry": {"coordinates":[11.348978,45.252884],"type":"Point"}
}