{
  "type": "Feature",
  "properties": {
    "iso:country":"IT",
    "sg:address":"20010 Bareggio",
    "sg:city":"Bareggio",
    "sg:orig_category":"Servizi E Lavori Per Arredamento E Industria Del Legno. Servizi E Lavori Per Edilizia E Lavori Pubblici",
    "sg:phone":"+39 02 901 4581",
    "sg:postcode":"20010",
    "sg:province":"Milano",
    "wof:name":"Alberti Ermanno",
    "wof:placetype":"venue"
},
  "geometry": {"coordinates":[9.058573,45.485554],"type":"Point"}
}