{
  "type": "Feature",
  "properties": {
    "iso:country":"IT",
    "sg:address":"33070 Sarone",
    "sg:city":"Sarone",
    "sg:orig_category":"Valvole E Apparecchiature Di Misura",
    "sg:phone":"+39 0434 778609",
    "sg:postcode":"33070",
    "sg:province":"Pordenone",
    "wof:name":"Plastomeccanica",
    "wof:placetype":"venue"
},
  "geometry": {"coordinates":[12.465425,45.997276],"type":"Point"}
}