{
  "type": "Feature",
  "properties": {
    "iso:country":"IT",
    "sg:address":"24, Via Zuccola 36050 Bolzano Vicentino",
    "sg:city":"Bolzano Vicentino",
    "sg:classifiers":[
        {
            "category":"Shopping",
            "subcategory":"Clothing, Apparel, & Fashions",
            "type":"Retail Goods"
        }
    ],
    "sg:phone":"+39 0444 356044",
    "sg:postcode":"36050",
    "sg:province":"Vicenza",
    "sg:tags":[
        "clothes"
    ],
    "wof:name":"Magazzini Berton (s.r.l.)",
    "wof:placetype":"venue"
},
  "geometry": {"coordinates":[11.623065,45.593628],"type":"Point"}
}