{
  "type": "Feature",
  "properties": {
    "iso:country":"IT",
    "sg:address":"33054 Lignano Sabbiadoro",
    "sg:city":"Lignano Sabbiadoro",
    "sg:classifiers":[
        {
            "category":"Wholesale",
            "subcategory":"Motor Vehicles",
            "type":"Manufacturing & Wholesale Goods"
        }
    ],
    "sg:phone":"+39 0431 428524",
    "sg:postcode":"33054",
    "sg:province":"Udine",
    "sg:tags":[
        "boats",
        "car"
    ],
    "wof:name":"Offshore Unimar Srl",
    "wof:placetype":"venue"
},
  "geometry": {"coordinates":[13.14772,45.693714],"type":"Point"}
}