{
  "type": "Feature",
  "properties": {
    "addr:full":"1397, Dorsoduro 30123 Venezia Dorsoduro Venezia 30123",
    "addr:housenumber":"1397",
    "addr:postcode":"30123;30123",
    "addr:street":"Dorsoduro",
    "iso:country":"IT",
    "sg:address":"1397, Dorsoduro 30123 Venezia",
    "sg:city":"Dorsoduro",
    "sg:classifiers":[
        {
            "category":"Marine",
            "type":"Transportation"
        }
    ],
    "sg:phone":"+39 041 240 1111",
    "sg:postcode":"30123",
    "sg:province":"Venezia",
    "sg:tags":[
        "transport",
        "sea"
    ],
    "wof:name":"Sernavimar S.r.l.",
    "wof:placetype":"venue"
},
  "geometry": {"coordinates":[12.326658,45.431362],"type":"Point"}
}