{
  "type": "Feature",
  "properties": {
    "iso:country":"IT",
    "sg:address":"Piazza Cavour, 5; Cremona; 26100",
    "sg:city":"Cremona",
    "sg:classifiers":[
        {
            "category":"Shopping",
            "subcategory":"Computers & Home Electronics",
            "type":"Retail Goods"
        }
    ],
    "sg:phone":"+39 390 372 4901",
    "sg:postcode":"26100",
    "sg:province":"Cremona",
    "sg:tags":[
        "chamber",
        "commerce"
    ],
    "sg:website":"www.cr.camcom.it",
    "wof:name":"Cremona Chamber Of Commerce & Industry",
    "wof:placetype":"venue"
},
  "geometry": {"coordinates":[10.023435,45.133541],"type":"Point"}
}