{
  "type": "Feature",
  "properties": {
    "addr:full":"92024 Canicatti' Agrigento 92024",
    "addr:postcode":"92024;92024",
    "iso:country":"IT",
    "sg:address":"92024 Canicatti'",
    "sg:orig_category":"Depurazione E Trattamento Delle Acque - Impianti Ed Apparecchi",
    "sg:phone":"+39 0922 855955",
    "sg:postcode":"92024",
    "sg:province":"Agrigento",
    "sg:website":"http://www.olympicpiscine.it",
    "wof:name":"Olympic Italia",
    "wof:placetype":"venue"
},
  "geometry": {"coordinates":[13.588239,37.310402],"type":"Point"}
}