{
  "type": "Feature",
  "properties": {
    "iso:country":"IT",
    "sg:address":"40139 Bologna",
    "sg:city":"Bologna",
    "sg:orig_category":"Apparecchiature E Sistemi Per Imballaggio E Confezionamento",
    "sg:phone":"+39 051 465750",
    "sg:postcode":"40139",
    "sg:province":"Bologna",
    "sg:website":"http://www.studiopack.net",
    "wof:name":"Studiopack Srl",
    "wof:placetype":"venue"
},
  "geometry": {"coordinates":[11.396635,44.470493],"type":"Point"}
}