{
  "type": "Feature",
  "properties": {
    "addr:full":"41042 Fiorano Modenese Fiorano Modenese Modena 41042",
    "addr:postcode":"41042;41042",
    "iso:country":"IT",
    "sg:address":"41042 Fiorano Modenese",
    "sg:city":"Fiorano Modenese",
    "sg:orig_category":"Servizi Ausiliari Di Analisi, Controllo E Ricerca",
    "sg:phone":"+39 0536 910169",
    "sg:postcode":"41042",
    "sg:province":"Modena",
    "wof:name":"Il Colibri' Di Fabrizi Augusto & C. (s.n.c.)",
    "wof:placetype":"venue"
},
  "geometry": {"coordinates":[10.828964,44.537205],"type":"Point"}
}