{
  "type": "Feature",
  "properties": {
    "iso:country":"IT",
    "sg:address":"52037 Sansepolcro",
    "sg:city":"Sansepolcro",
    "sg:orig_category":"Servizi Ausiliari Dei Mezzi Di Trasporto",
    "sg:phone":"+39 0575 742836",
    "sg:postcode":"52037",
    "sg:province":"Arezzo",
    "wof:name":"Piccini Paolo Spa",
    "wof:placetype":"venue"
},
  "geometry": {"coordinates":[12.082436,43.493744],"type":"Point"}
}