{
  "type": "Feature",
  "properties": {
    "iso:country":"IT",
    "sg:address":"22, Via Dell' Artigianato S.pancrazio 48026 Russi",
    "sg:city":"Russi",
    "sg:classifiers":[
        {
            "category":"Professional",
            "subcategory":"Engineering",
            "type":"Services"
        }
    ],
    "sg:phone":"+39 0544 534557",
    "sg:postcode":"48026",
    "sg:province":"Ravenna",
    "sg:tags":[
        "machine",
        "-",
        "mechanical"
    ],
    "wof:name":"Co.me.r. Snc Di Cola Bruno Melandri Gilberto E Rubboli Luciano",
    "wof:placetype":"venue"
},
  "geometry": {"coordinates":[12.073771,44.359123],"type":"Point"}
}