{
  "type": "Feature",
  "properties": {
    "addr:full":"00162 Roma Roma Roma 00162",
    "addr:postcode":"00162;00162",
    "iso:country":"IT",
    "sg:address":"00162 Roma",
    "sg:city":"Roma",
    "sg:orig_category":"Servizi Ausiliari Di Certificati, Riproduzioni, Disegni E Foto",
    "sg:phone":"+39 06 4423 9196",
    "sg:postcode":"00162",
    "sg:province":"Roma",
    "wof:name":"F & P Studio Di Umberto Fortini",
    "wof:placetype":"venue"
},
  "geometry": {"coordinates":[12.521569,41.912552],"type":"Point"}
}