{
  "type": "Feature",
  "properties": {
    "iso:country":"IT",
    "sg:address":"81100 Caserta",
    "sg:city":"Caserta",
    "sg:orig_category":"Manufacturers: Prefabbricati",
    "sg:phone":"+39 0823 215009",
    "sg:postcode":"81100",
    "sg:province":"Caserta",
    "wof:name":"S.anna S.r.l.",
    "wof:placetype":"venue"
},
  "geometry": {"coordinates":[14.332393,41.070122],"type":"Point"}
}