{
  "type": "Feature",
  "properties": {
    "iso:country":"IT",
    "sg:address":"20094 Corsico",
    "sg:city":"Corsico",
    "sg:orig_category":"Servizi Editoriali",
    "sg:phone":"+39 02 447 1776",
    "sg:postcode":"20094",
    "sg:province":"Milano",
    "wof:name":"Cavallari Franca",
    "wof:placetype":"venue"
},
  "geometry": {"coordinates":[9.112161,45.441689],"type":"Point"}
}