{
  "type": "Feature",
  "properties": {
    "iso:country":"IT",
    "sg:address":"16121 Genova",
    "sg:city":"Genova",
    "sg:orig_category":"Servizi Al Turismo. Trasporto Pubblico E Privato",
    "sg:phone":"+39 010 595 5437",
    "sg:postcode":"16121",
    "sg:province":"Genova",
    "wof:name":"Traghettionline",
    "wof:placetype":"venue"
},
  "geometry": {"coordinates":[8.941349,44.403976],"type":"Point"}
}