{
  "type": "Feature",
  "properties": {
    "iso:country":"IT",
    "sg:address":"13, Via Don Minzoni 28024 Gozzano",
    "sg:city":"Gozzano",
    "sg:classifiers":[
        {
            "category":"Shopping",
            "type":"Retail Goods"
        }
    ],
    "sg:phone":"+39 39032294131",
    "sg:postcode":"28024",
    "sg:province":"Novara",
    "sg:tags":[
        "finished",
        "-",
        "metallic"
    ],
    "wof:name":"M.r.g. S.p.a.",
    "wof:placetype":"venue"
},
  "geometry": {"coordinates":[8.4361095428,45.735824585],"type":"Point"}
}