{
  "type": "Feature",
  "properties": {
    "addr:full":"35129 Padova Padova Padova 35129",
    "addr:postcode":"35129;35129",
    "iso:country":"IT",
    "sg:address":"35129 Padova",
    "sg:city":"Padova",
    "sg:orig_category":"Motori Ed Organi Di Trasmissione",
    "sg:phone":"+39 049 807 0911",
    "sg:postcode":"35129",
    "sg:province":"Padova",
    "wof:name":"Bonfiglioli Riduttori S.p.a.",
    "wof:placetype":"venue"
},
  "geometry": {"coordinates":[11.9259986877,45.4266471863],"type":"Point"}
}