{
  "type": "Feature",
  "properties": {
    "iso:country":"IT",
    "sg:address":"20129 Milano",
    "sg:city":"Milano",
    "sg:orig_category":"Banche E Servizi Finanziari. Avvocati, Notai E Servizi Legali",
    "sg:phone":"+39 02 2953 6120",
    "sg:postcode":"20129",
    "sg:province":"Milano",
    "wof:name":"Geprim S.r.l.",
    "wof:placetype":"venue"
},
  "geometry": {"coordinates":[9.212793,45.47691],"type":"Point"}
}