{
  "type": "Feature",
  "properties": {
    "iso:country":"IT",
    "sg:address":"Via Calamandrei 6 51018 Pieve A Nievole",
    "sg:city":"Pieve a Nievole",
    "sg:classifiers":[
        {
            "category":"Shopping",
            "subcategory":"Shoes",
            "type":"Retail Goods"
        }
    ],
    "sg:phone":"+39 0572 81812",
    "sg:postcode":"51018",
    "sg:province":"Pistoia",
    "sg:tags":[
        "men's",
        "boot"
    ],
    "wof:name":"Bona' Srl",
    "wof:placetype":"venue"
},
  "geometry": {"coordinates":[10.8000335693,43.8700485229],"type":"Point"}
}