{
  "type": "Feature",
  "properties": {
    "addr:full":"39011 Lana Lana Bolzano/Bozen 39011",
    "addr:postcode":"39011;39011",
    "iso:country":"IT",
    "sg:address":"39011 Lana",
    "sg:city":"Lana",
    "sg:classifiers":[
        {
            "category":"Sports & Exercise",
            "subcategory":"Tennis Court",
            "type":"Entertainment"
        }
    ],
    "sg:phone":"+39 0473 562888",
    "sg:postcode":"39011",
    "sg:province":"Bolzano/Bozen",
    "sg:tags":[
        "e",
        "lo",
        "tempo",
        "libero",
        "per",
        "impianti",
        "il",
        "attrezzature"
    ],
    "wof:name":"Elektro Egger Sas/kg D. Egger Josef & Co.",
    "wof:placetype":"venue"
},
  "geometry": {"coordinates":[11.358005,46.496716],"type":"Point"}
}