{
  "type": "Feature",
  "properties": {
    "iso:country":"IT",
    "sg:address":"62010 Montelupone",
    "sg:city":"Montelupone",
    "sg:orig_category":"Macchine, Impianti Ed Attrezzature Per Industria Alimentare E Bevande",
    "sg:phone":"+39 0733 228344",
    "sg:postcode":"62010",
    "sg:province":"Macerata",
    "wof:name":"Ruffini Romolo",
    "wof:placetype":"venue"
},
  "geometry": {"coordinates":[13.561423,43.340157],"type":"Point"}
}