{
  "type": "Feature",
  "properties": {
    "addr:full":"16043 Chiavari Chiavari Genova 16043",
    "addr:postcode":"16043;16043",
    "iso:country":"IT",
    "sg:address":"16043 Chiavari",
    "sg:city":"Chiavari",
    "sg:orig_category":"Calzature, Pelletterie E Pelli. Shopping",
    "sg:phone":"+39 0185 308024",
    "sg:postcode":"16043",
    "sg:province":"Genova",
    "wof:name":"Pelletteria Diana",
    "wof:placetype":"venue"
},
  "geometry": {"coordinates":[9.326461,44.316666],"type":"Point"}
}