{
  "type": "Feature",
  "properties": {
    "iso:country":"IT",
    "sg:address":"3, Via Valgobbia 25068 Sarezzo",
    "sg:city":"Sarezzo",
    "sg:classifiers":[
        {
            "category":"Parking",
            "subcategory":"Lot",
            "type":"Transportation"
        }
    ],
    "sg:phone":"+39 030 890 0890",
    "sg:postcode":"25068",
    "sg:province":"Brescia",
    "sg:tags":[
        "transport",
        "road"
    ],
    "wof:name":"Autotrasporti Cram S.r.l.",
    "wof:placetype":"venue"
},
  "geometry": {"coordinates":[10.202061,45.646824],"type":"Point"}
}