{
  "type": "Feature",
  "properties": {
    "iso:country":"IT",
    "sg:address":"2, Via Dell' Artigianato 37047 San Bonifacio",
    "sg:city":"San Bonifacio",
    "sg:classifiers":[
        {
            "category":"Real Estate",
            "subcategory":"Surveying",
            "type":"Services"
        }
    ],
    "sg:phone":"+39 045 766 5665",
    "sg:postcode":"37047",
    "sg:province":"Verona",
    "sg:tags":[
        "equipment",
        "material",
        "good",
        "-",
        "handling"
    ],
    "wof:name":"San Bonifacio Pallets S.r.l.",
    "wof:placetype":"venue"
},
  "geometry": {"coordinates":[11.305999,45.387398],"type":"Point"}
}