{
  "type": "Feature",
  "properties": {
    "addr:full":"20155 Milano Milano Milano 20155",
    "addr:postcode":"20155;20155",
    "iso:country":"IT",
    "sg:address":"20155 Milano",
    "sg:city":"Milano",
    "sg:orig_category":"Forniture E Materiali Per Imballaggio E Confezionamento. Forniture Per Uffici. Forniture Per Attivita' Commerciali Ed Artigianali",
    "sg:phone":"+39 02 3300 0461",
    "sg:postcode":"20155",
    "sg:province":"Milano",
    "sg:website":"http://www.rollprint.it",
    "wof:name":"Rollprint Sas",
    "wof:placetype":"venue"
},
  "geometry": {"coordinates":[9.1500225067,45.4909248352],"type":"Point"}
}