{
  "type": "Feature",
  "properties": {
    "addr:full":"20019 Settimo Milanese Settimo Milanese Milano 20019",
    "addr:postcode":"20019;20019",
    "iso:country":"IT",
    "sg:address":"20019 Settimo Milanese",
    "sg:city":"Settimo Milanese",
    "sg:orig_category":"Cinematografia E Radiotelevisione. Forniture Per Il Settore Dello Spettacolo",
    "sg:phone":"+39 02 328 7660",
    "sg:postcode":"20019",
    "sg:province":"Milano",
    "wof:name":"Prevost Srl",
    "wof:placetype":"venue"
},
  "geometry": {"coordinates":[9.074434,45.474506],"type":"Point"}
}