{
  "type": "Feature",
  "properties": {
    "iso:country":"IT",
    "sg:address":"27055 Rivanazzano",
    "sg:city":"Rivanazzano",
    "sg:orig_category":"Servizi Al Turismo. Trasporto Pubblico E Privato",
    "sg:phone":"+39 0383 944440",
    "sg:postcode":"27055",
    "sg:province":"Pavia",
    "sg:website":"http://www.elisystem.it",
    "wof:name":"Elisystem Eliagricola Srl",
    "wof:placetype":"venue"
},
  "geometry": {"coordinates":[9.017974,44.928997],"type":"Point"}
}