{
  "type": "Feature",
  "properties": {
    "addr:full":"118, Via Azzarita Capitano 70056 Molfetta Molfetta Bari 70056",
    "addr:housenumber":"118",
    "addr:postcode":"70056;70056",
    "addr:street":"Via Azzarita Capitano",
    "iso:country":"IT",
    "sg:address":"118, Via Azzarita Capitano 70056 Molfetta",
    "sg:city":"Molfetta",
    "sg:classifiers":[
        {
            "category":"Personal",
            "subcategory":"Shoe Repair & Shine",
            "type":"Services"
        }
    ],
    "sg:phone":"+39 080 338 8227",
    "sg:postcode":"70056",
    "sg:province":"Bari",
    "sg:tags":[
        "leather"
    ],
    "wof:name":"Gisam Di Altomare Salvatore",
    "wof:placetype":"venue"
},
  "geometry": {"coordinates":[16.869291,41.126053],"type":"Point"}
}