{
  "type": "Feature",
  "properties": {
    "addr:full":"Via Piano All'isola,55/57 50053 Empoli Empoli Firenze 50053",
    "addr:housenumber":"55 / 57",
    "addr:postcode":"50053;50053",
    "addr:street":"Via Piano All'Isola",
    "iso:country":"IT",
    "sg:address":"Via Piano All'isola,55/57 50053 Empoli",
    "sg:city":"Empoli",
    "sg:classifiers":[
        {
            "category":"Manufacturing",
            "subcategory":"Chemicals & Compounds",
            "type":"Manufacturing & Wholesale Goods"
        }
    ],
    "sg:phone":"+39 0571 591625",
    "sg:postcode":"50053",
    "sg:province":"Firenze",
    "sg:tags":[
        "base"
    ],
    "wof:name":"Vetro Impianti Sas",
    "wof:placetype":"venue"
},
  "geometry": {"coordinates":[10.977839,43.723484],"type":"Point"}
}