{
  "type": "Feature",
  "properties": {
    "iso:country":"IT",
    "sg:address":"37036 San Martino Buon Albergo",
    "sg:city":"San Martino Buon Albergo",
    "sg:classifiers":[
        {
            "category":"Health Services",
            "subcategory":"Health Practitioner",
            "type":"Services"
        }
    ],
    "sg:phone":"+39 045 995269",
    "sg:postcode":"37036",
    "sg:province":"Verona",
    "sg:tags":[
        "medici"
    ],
    "wof:name":"Ambrosi Maurizio",
    "wof:placetype":"venue"
},
  "geometry": {"coordinates":[11.10061,45.4258],"type":"Point"}
}