{
  "type": "Feature",
  "properties": {
    "iso:country":"IT",
    "sg:address":"20052 Monza",
    "sg:city":"Monza",
    "sg:orig_category":"Motori Ed Organi Di Trasmissione. Ricambi E Componenti Dei Mezzi Di Trasporto",
    "sg:phone":"+39 039 230 1117",
    "sg:postcode":"20052",
    "sg:province":"Milano",
    "wof:name":"Progetti Tau Srl",
    "wof:placetype":"venue"
},
  "geometry": {"coordinates":[9.2249803543,45.4607849121],"type":"Point"}
}