{
  "type": "Feature",
  "properties": {
    "iso:country":"IT",
    "sg:address":"1, Via Del Capitello 36066 Sandrigo",
    "sg:city":"Sandrigo",
    "sg:classifiers":[
        {
            "category":"Shopping",
            "type":"Retail Goods"
        }
    ],
    "sg:phone":"+39 0444 658683",
    "sg:postcode":"36066",
    "sg:province":"Vicenza",
    "sg:tags":[
        "finished",
        "-",
        "metallic"
    ],
    "wof:name":"Staubli Italia S.p.a.",
    "wof:placetype":"venue"
},
  "geometry": {"coordinates":[11.6236839294,45.6033210754],"type":"Point"}
}