{
  "type": "Feature",
  "properties": {
    "iso:country":"IT",
    "sg:address":"Via Decumana 12/c 40133 Bologna",
    "sg:city":"Bologna",
    "sg:classifiers":[
        {
            "category":"Community Center",
            "subcategory":"Social",
            "type":"Public Place"
        }
    ],
    "sg:phone":"+39 051 385848",
    "sg:postcode":"40133",
    "sg:province":"Bologna",
    "sg:tags":[
        "machine",
        "milling",
        "bench"
    ],
    "sg:website":"www.bdbsrl.com",
    "wof:name":"B.d.b. Srl",
    "wof:placetype":"venue"
},
  "geometry": {"coordinates":[11.301365,44.50716],"type":"Point"}
}