{
  "type": "Feature",
  "properties": {
    "addr:full":"30135 Venezia Venezia Venezia 30135",
    "addr:postcode":"30135;30135",
    "iso:country":"IT",
    "sg:address":"30135 Venezia",
    "sg:city":"Venezia",
    "sg:orig_category":"Materiali E Componenti Elettrotecnici",
    "sg:phone":"+39 041 524 0556",
    "sg:postcode":"30135",
    "sg:province":"Venezia",
    "wof:name":"I.r.c.a. (s.p.a.)",
    "wof:placetype":"venue"
},
  "geometry": {"coordinates":[12.321123,45.437801],"type":"Point"}
}