{
  "type": "Feature",
  "properties": {
    "iso:country":"IT",
    "sg:address":"35020 Terrassa Padovana",
    "sg:city":"Terrassa Padovana",
    "sg:orig_category":"Servizi E Lavori Per Abbigliamento E Pelletterie",
    "sg:phone":"+39 049 538 3014",
    "sg:postcode":"35020",
    "sg:province":"Padova",
    "wof:name":"Taglieria S. Giorgio Di Silvestrin A. E C. (s.n.c.)",
    "wof:placetype":"venue"
},
  "geometry": {"coordinates":[11.964399,45.236942],"type":"Point"}
}