{
  "type": "Feature",
  "properties": {
    "addr:full":"10138 Torino Torino Torino 10138",
    "addr:housenumber":"10138",
    "addr:postcode":"10138",
    "iso:country":"IT",
    "sg:address":"10138 Torino",
    "sg:city":"Torino",
    "sg:orig_category":"Servizi Vari Di Interesse Pubblico",
    "sg:phone":"+39 011 433 0208",
    "sg:postcode":"10138",
    "sg:province":"Torino",
    "wof:name":"Studio M & M Snc Di Marciale Mirella E Russo Maria Adelaide",
    "wof:placetype":"venue"
},
  "geometry": {"coordinates":[7.654967,45.069084],"type":"Point"}
}