{
  "type": "Feature",
  "properties": {
    "iso:country":"IT",
    "sg:address":"Via Del Fosso 3 52100 Arezzo",
    "sg:city":"Arezzo",
    "sg:classifiers":[
        {
            "category":"Shopping",
            "subcategory":"Jewelry",
            "type":"Retail Goods"
        }
    ],
    "sg:phone":"+39 0575 984725",
    "sg:postcode":"52100",
    "sg:province":"Arezzo",
    "sg:tags":[
        "jewellery",
        "gold"
    ],
    "sg:website":"www.koalapreziosi.com",
    "wof:name":"Koala Preziosi S.r.l.",
    "wof:placetype":"venue"
},
  "geometry": {"coordinates":[11.859384,43.481312],"type":"Point"}
}