{
  "type": "Feature",
  "properties": {
    "addr:full":"06022 Fossato Di Vico Fossato di Vico Perugia 06022",
    "addr:postcode":"06022;06022",
    "addr:street":"Vico Fossato Di Vico",
    "iso:country":"IT",
    "sg:address":"06022 Fossato Di Vico",
    "sg:city":"Fossato di Vico",
    "sg:orig_category":"Alberghi E Strutture Extra Alberghiere",
    "sg:phone":"+39 075 919 0121",
    "sg:postcode":"06022",
    "sg:province":"Perugia",
    "wof:name":"Hotel Camino Vecchio",
    "wof:placetype":"venue"
},
  "geometry": {"coordinates":[12.749456,43.291016],"type":"Point"}
}