{
  "type": "Feature",
  "properties": {
    "iso:country":"IT",
    "sg:address":"697, Via Galilea 63019 Sant'elpidio A Mare",
    "sg:classifiers":[
        {
            "category":"Personal",
            "subcategory":"Shoe Repair & Shine",
            "type":"Services"
        }
    ],
    "sg:phone":"+39 0734 858668",
    "sg:postcode":"63019",
    "sg:province":"Ascoli Piceno",
    "sg:tags":[
        "leather"
    ],
    "wof:name":"Calzaturificio F.lli Pacioni G. & R. S.n.c.",
    "wof:placetype":"venue"
},
  "geometry": {"coordinates":[13.702632,43.237492],"type":"Point"}
}