{
  "type": "Feature",
  "properties": {
    "iso:country":"IT",
    "sg:address":"1, Via S. Giuseppe 25075 Nave",
    "sg:city":"Nave",
    "sg:classifiers":[
        {
            "category":"Shopping",
            "type":"Retail Goods"
        }
    ],
    "sg:phone":"+39 030 253 7211",
    "sg:postcode":"25075",
    "sg:province":"Brescia",
    "sg:tags":[
        "finished",
        "-",
        "metallic"
    ],
    "wof:name":"R B M Spa",
    "wof:placetype":"venue"
},
  "geometry": {"coordinates":[10.2549114227,45.5838851929],"type":"Point"}
}