{
  "type": "Feature",
  "properties": {
    "addr:full":"26, Via Trieste 13900 Biella Biella Biella 13900",
    "addr:postcode":"13900;13900",
    "addr:street":"Via Trieste",
    "iso:country":"IT",
    "sg:address":"26, Via Trieste 13900 Biella",
    "sg:city":"Biella",
    "sg:classifiers":[
        {
            "category":"Manufacturing",
            "subcategory":"Printing",
            "type":"Manufacturing & Wholesale Goods"
        }
    ],
    "sg:phone":"+39 015 849 2282",
    "sg:postcode":"13900",
    "sg:province":"Biella",
    "sg:tags":[
        "publishing"
    ],
    "wof:name":"La Nuova Provincia Di Biella Editoriale (s.r.l.)",
    "wof:placetype":"venue"
},
  "geometry": {"coordinates":[8.0615730286,45.5594406128],"type":"Point"}
}