{
  "type": "Feature",
  "properties": {
    "iso:country":"IT",
    "sg:address":"07040 Fertilia",
    "sg:orig_category":"Lavorazioni Meccaniche E Servizi. Riparazione Dei Mezzi Di Trasporto",
    "sg:phone":"+39 079 930088",
    "sg:postcode":"07040",
    "sg:province":"Sassari",
    "wof:name":"Base Nautica Usai Srl",
    "wof:placetype":"venue"
},
  "geometry": {"coordinates":[8.558469,40.727165],"type":"Point"}
}