{
  "type": "Feature",
  "properties": {
    "iso:country":"IT",
    "sg:address":"Strada Cenerente Colle Umberto 06070 Perugia",
    "sg:classifiers":[
        {
            "category":"Travel",
            "subcategory":"Travel Agent",
            "type":"Entertainment"
        }
    ],
    "sg:phone":"+39 39075690125",
    "sg:postcode":"06070",
    "sg:province":"Perugia",
    "sg:tags":[
        "business"
    ],
    "wof:name":"Oscano Convention Center S.r.l.",
    "wof:placetype":"venue"
},
  "geometry": {"coordinates":[12.334569,43.157726],"type":"Point"}
}