{
  "type": "Feature",
  "properties": {
    "addr:full":"00187 Roma Roma Roma 00187",
    "addr:postcode":"00187;00187",
    "iso:country":"IT",
    "sg:address":"00187 Roma",
    "sg:city":"Roma",
    "sg:orig_category":"Scuole E Servizi Scolastici. Ricerca, Selezione E Formazione Del Personale",
    "sg:phone":"+39 06 474 2814",
    "sg:postcode":"00187",
    "sg:province":"Roma",
    "sg:website":"http://www.inlingua.it",
    "wof:name":"International School",
    "wof:placetype":"venue"
},
  "geometry": {"coordinates":[12.495555,41.905659],"type":"Point"}
}