{
  "type": "Feature",
  "properties": {
    "addr:full":"5, Via Tonale 20052 Monza Monza Milano 20052",
    "addr:postcode":"20052;20052",
    "addr:street":"Via Tonale",
    "iso:country":"IT",
    "sg:address":"5, Via Tonale 20052 Monza",
    "sg:city":"Monza",
    "sg:classifiers":[
        {
            "category":"Shopping",
            "subcategory":"Crafts & Fabrics",
            "type":"Retail Goods"
        }
    ],
    "sg:phone":"+39 39039323662",
    "sg:postcode":"20052",
    "sg:province":"Milano",
    "wof:name":"Manifattura Longoni Giuseppe S.a.s. Di Dr. Ing. Giovanni Longoni & C.",
    "wof:placetype":"venue"
},
  "geometry": {"coordinates":[9.2377681732,45.5326042175],"type":"Point"}
}