{
  "type": "Feature",
  "properties": {
    "addr:full":"Via Europa 24069 Cenate Sotto Cenate Sotto Bergamo 24069",
    "addr:postcode":"24069;24069",
    "addr:street":"Via Europa",
    "iso:country":"IT",
    "sg:address":"Via Europa 24069 Cenate Sotto",
    "sg:city":"Cenate Sotto",
    "sg:classifiers":[
        {
            "category":"Shopping",
            "subcategory":"Clothing, Apparel, & Fashions",
            "type":"Retail Goods"
        }
    ],
    "sg:phone":"+39 39035940319",
    "sg:postcode":"24069",
    "sg:province":"Bergamo",
    "sg:tags":[
        "clothes"
    ],
    "wof:name":"Marianna Di Vescovi Agnese & C. (s.n.c.)",
    "wof:placetype":"venue"
},
  "geometry": {"coordinates":[9.819312,45.686607],"type":"Point"}
}