{
  "type": "Feature",
  "properties": {
    "addr:full":"27010 San Genesio Ed Uniti San Genesio ed Uniti Pavia 27010",
    "addr:postcode":"27010;genesio ed uniti;27010",
    "addr:street":"San;Genesio Ed Uniti",
    "iso:country":"IT",
    "sg:address":"27010 San Genesio Ed Uniti",
    "sg:city":"San Genesio ed Uniti",
    "sg:orig_category":"Prodotti Di Base E Forniture Per Industria Alimentare E Bevande",
    "sg:phone":"+39 0382 586824",
    "sg:postcode":"27010",
    "sg:province":"Pavia",
    "wof:name":"Chiesa F.lli",
    "wof:placetype":"venue"
},
  "geometry": {"coordinates":[9.1832351685,45.2321128845],"type":"Point"}
}