{
  "type": "Feature",
  "properties": {
    "iso:country":"IT",
    "sg:address":"06100 Perugia",
    "sg:orig_category":"Serre - Impianti Ed Attrezzature",
    "sg:phone":"+39 075 527 1336",
    "sg:province":"PG",
    "wof:name":"Umbria Serre Snc Di Rosatini & Pasqualoni",
    "wof:placetype":"venue"
},
  "geometry": {"coordinates":[12.294537,43.165943],"type":"Point"}
}