{
  "type": "Feature",
  "properties": {
    "addr:full":"73100 Lecce Lecce Lecce 73100",
    "addr:postcode":"73100;73100",
    "iso:country":"IT",
    "sg:address":"73100 Lecce",
    "sg:city":"Lecce",
    "sg:orig_category":"Servizi E Lavori Per Arredamento E Industria Del Legno. Servizi E Lavori Per Edilizia E Lavori Pubblici. Arte Ed Artigianato Artistico",
    "sg:phone":"+39 0832 629235",
    "sg:postcode":"73100",
    "sg:province":"Lecce",
    "sg:website":"http://www.italcantierilecce.it",
    "wof:name":"Italcantieri Srl",
    "wof:placetype":"venue"
},
  "geometry": {"coordinates":[18.216127,40.342113],"type":"Point"}
}