{
  "type": "Feature",
  "properties": {
    "addr:full":"35, Via Rimembranze 27023 Cassolnovo Cassolnovo Pavia 27023",
    "addr:postcode":"27023;27023",
    "addr:street":"Via Rimembranze",
    "iso:country":"IT",
    "sg:address":"35, Via Rimembranze 27023 Cassolnovo",
    "sg:city":"Cassolnovo",
    "sg:classifiers":[
        {
            "category":"Food & Beverages",
            "subcategory":"Dairy",
            "type":"Retail Goods"
        }
    ],
    "sg:phone":"+39 39038192175",
    "sg:postcode":"27023",
    "sg:province":"Pavia",
    "sg:tags":[
        "product"
    ],
    "wof:name":"Signorelli Pietro Dei F.lli Signorelli (s.r.l.)",
    "wof:placetype":"venue"
},
  "geometry": {"coordinates":[8.808062,45.369106],"type":"Point"}
}