{
  "type": "Feature",
  "properties": {
    "iso:country":"IT",
    "sg:address":"65121 Pescara",
    "sg:city":"Pescara",
    "sg:orig_category":"Scuole E Servizi Scolastici. Ricerca, Selezione E Formazione Del Personale",
    "sg:phone":"+39 085 421 1986",
    "sg:postcode":"65121",
    "sg:province":"Pescara",
    "sg:website":"http://www.centro-psicologia.it",
    "wof:name":"Centro Di Psicologia Clinica Formazione Cognitivo-compartimentale",
    "wof:placetype":"venue"
},
  "geometry": {"coordinates":[14.213996,42.468334],"type":"Point"}
}