{
  "type": "Feature",
  "properties": {
    "iso:country":"IT",
    "sg:address":"Via A. Grandi 5 22077 Olgiate Comasco",
    "sg:city":"Olgiate Comasco",
    "sg:classifiers":[
        {
            "category":"Shopping",
            "subcategory":"Computers & Home Electronics",
            "type":"Retail Goods"
        }
    ],
    "sg:phone":"+39 39031997111",
    "sg:postcode":"22077",
    "sg:province":"Como",
    "sg:tags":[
        "electronic",
        "electrical",
        "equipment"
    ],
    "wof:name":"Sisme - Soc Ital Statori E Motori Elet S",
    "wof:placetype":"venue"
},
  "geometry": {"coordinates":[9.000822,45.804081],"type":"Point"}
}