{
  "type": "Feature",
  "properties": {
    "iso:country":"IT",
    "sg:address":"04022 Fondi",
    "sg:city":"Fondi",
    "sg:orig_category":"Automobili E Mezzi Di Trasporto. Riparazione Dei Mezzi Di Trasporto",
    "sg:phone":"+39 0771 515954",
    "sg:postcode":"04022",
    "sg:province":"Latina",
    "wof:name":"Parisella Tullio",
    "wof:placetype":"venue"
},
  "geometry": {"coordinates":[13.479647,41.324867],"type":"Point"}
}