{
  "type": "Feature",
  "properties": {
    "addr:full":"87043 Bisignano Bisignano Cosenza 87043",
    "addr:postcode":"87043;87043",
    "iso:country":"IT",
    "sg:address":"87043 Bisignano",
    "sg:city":"Bisignano",
    "sg:orig_category":"Prodotti Alimentari",
    "sg:phone":"+39 0984 949106",
    "sg:postcode":"87043",
    "sg:province":"Cosenza",
    "wof:name":"Azienda Agricola Rosa",
    "wof:placetype":"venue"
},
  "geometry": {"coordinates":[16.2639827728,39.5123558044],"type":"Point"}
}