{
  "type": "Feature",
  "properties": {
    "iso:country":"IT",
    "sg:address":"16129 Genova",
    "sg:city":"Genova",
    "sg:classifiers":[
        {
            "category":"Professional",
            "subcategory":"Management & Consulting",
            "type":"Services"
        }
    ],
    "sg:phone":"+39 010 595 9465",
    "sg:postcode":"16129",
    "sg:province":"Genova",
    "sg:tags":[
        "information",
        "communication",
        "marketing",
        "-",
        "advertising",
        "consultant",
        "services",
        "technology"
    ],
    "wof:name":"Punto 2 Sas Di Guido Di Muzio & C.",
    "wof:placetype":"venue"
},
  "geometry": {"coordinates":[8.950755,44.400074],"type":"Point"}
}