{
  "type": "Feature",
  "properties": {
    "addr:full":"Via Maiolo 70 10044 Pianezza Pianezza Torino 10044",
    "addr:housenumber":"70",
    "addr:postcode":"10044;10044",
    "addr:street":"Via Maiolo",
    "iso:country":"IT",
    "sg:address":"Via Maiolo 70 10044 Pianezza",
    "sg:city":"Pianezza",
    "sg:classifiers":[
        {
            "category":"Parking",
            "subcategory":"Bicycle",
            "type":"Transportation"
        }
    ],
    "sg:phone":"+39 011 966 5806",
    "sg:postcode":"10044",
    "sg:province":"Torino",
    "sg:tags":[
        "wheel",
        "dull",
        "grinding"
    ],
    "wof:name":"Csb Abrasivi Snc",
    "wof:placetype":"venue"
},
  "geometry": {"coordinates":[7.565848,45.10133],"type":"Point"}
}