{
  "type": "Feature",
  "properties": {
    "iso:country":"IT",
    "sg:address":"10, Via Zambrini 40026 Imola",
    "sg:city":"Imola",
    "sg:classifiers":[
        {
            "category":"Manufacturing",
            "subcategory":"Metals",
            "type":"Manufacturing & Wholesale Goods"
        }
    ],
    "sg:phone":"+39 0542 642670",
    "sg:postcode":"40026",
    "sg:province":"Bologna",
    "sg:tags":[
        "metallurgy",
        "metalworking"
    ],
    "wof:name":"Fonderia Fomar Ghisa S.r.l.",
    "wof:placetype":"venue"
},
  "geometry": {"coordinates":[11.7203636169,44.3730010986],"type":"Point"}
}