{
  "type": "Feature",
  "properties": {
    "addr:full":"25121 Brescia Brescia Brescia 25121",
    "addr:postcode":"25121;25121",
    "iso:country":"IT",
    "sg:address":"25121 Brescia",
    "sg:city":"Brescia",
    "sg:orig_category":"Case Editrici",
    "sg:phone":"+39 030 375 7897",
    "sg:postcode":"25121",
    "sg:province":"Brescia",
    "sg:website":"http://www.lavocedelpopolo.it",
    "wof:name":"La Voce Del Popolo Srl",
    "wof:placetype":"venue"
},
  "geometry": {"coordinates":[10.223478,45.536995],"type":"Point"}
}