{
  "type": "Feature",
  "properties": {
    "iso:country":"IT",
    "sg:address":"00044 Frascati",
    "sg:city":"Frascati",
    "sg:orig_category":"Pubblicita', Marketing E Comunicazione",
    "sg:phone":"+39 06 949 6568",
    "sg:postcode":"00044",
    "sg:province":"Roma",
    "sg:website":"http://in-media.it",
    "wof:name":"Inmedia Consulting Srl",
    "wof:placetype":"venue"
},
  "geometry": {"coordinates":[12.6816635132,41.808303833],"type":"Point"}
}