{
  "type": "Feature",
  "properties": {
    "iso:country":"IT",
    "sg:address":"25047 Darfo Boario Terme",
    "sg:city":"Darfo",
    "sg:orig_category":"Persiane Ed Avvolgibili",
    "sg:phone":"+39 036 453 3193",
    "sg:postcode":"25047",
    "sg:province":"Brescia",
    "sg:website":"http://www.isamser.it",
    "wof:name":"Isam Snc Di Mariolini G. & Fratelli",
    "wof:placetype":"venue"
},
  "geometry": {"coordinates":[10.1998615265,45.9012031555],"type":"Point"}
}