{
  "type": "Feature",
  "properties": {
    "iso:country":"IT",
    "sg:address":"Via Zara 34 21049 Tradate",
    "sg:city":"Tradate",
    "sg:classifiers":[
        {
            "category":"Manufacturing",
            "subcategory":"Printing",
            "type":"Manufacturing & Wholesale Goods"
        }
    ],
    "sg:phone":"+39 0331 841146",
    "sg:postcode":"21049",
    "sg:province":"Varese",
    "sg:tags":[
        "house",
        "book"
    ],
    "wof:name":"La Litografica Tradatese S.r.l.",
    "wof:placetype":"venue"
},
  "geometry": {"coordinates":[8.909595,45.712391],"type":"Point"}
}