{
  "type": "Feature",
  "properties": {
    "iso:country":"IT",
    "sg:address":"62012 Civitanova Marche",
    "sg:city":"Civitanova Marche",
    "sg:orig_category":"Agenzie D'affari E Servizi Commerciali",
    "sg:phone":"+39 0733 817643",
    "sg:postcode":"62012",
    "sg:province":"Macerata",
    "wof:name":"Brokernet Sas Di Vallesi Vincenzo E C.",
    "wof:placetype":"venue"
},
  "geometry": {"coordinates":[13.728851,43.301346],"type":"Point"}
}