{
  "type": "Feature",
  "properties": {
    "iso:country":"IT",
    "sg:address":"06074 Perugia",
    "sg:orig_category":"Banche E Servizi Finanziari",
    "sg:phone":"+39 075 517 0510",
    "sg:province":"PG",
    "wof:name":"Aci Leasing Centro Italia Spa",
    "wof:placetype":"venue"
},
  "geometry": {"coordinates":[-72.579636,41.844532],"type":"Point"}
}