{
  "type": "Feature",
  "properties": {
    "iso:country":"IT",
    "sg:address":"Via Santi 2 20077 Melegnano",
    "sg:city":"Melegnano",
    "sg:classifiers":[
        {
            "category":"Shopping",
            "subcategory":"Mobile Phones",
            "type":"Retail Goods"
        }
    ],
    "sg:phone":"+39 02 983 7583",
    "sg:postcode":"20077",
    "sg:province":"Milano",
    "sg:tags":[
        "telephone",
        "accessory"
    ],
    "sg:website":"www.lemm.it",
    "wof:name":"Lemm S.r.l.",
    "wof:placetype":"venue"
},
  "geometry": {"coordinates":[9.188141,45.463688],"type":"Point"}
}