{
  "type": "Feature",
  "properties": {
    "iso:country":"IT",
    "sg:address":"3, Via Oriolo 26020 Madignano",
    "sg:city":"Madignano",
    "sg:classifiers":[
        {
            "category":"Utilities",
            "subcategory":"Electric",
            "type":"Services"
        }
    ],
    "sg:phone":"+39 0373 658203",
    "sg:postcode":"26020",
    "sg:province":"Cremona",
    "sg:tags":[
        "component",
        "electronic"
    ],
    "wof:name":"F.m.elettronica Di Foglio L.e C. (s.n.c.)",
    "wof:placetype":"venue"
},
  "geometry": {"coordinates":[9.733704,45.337513],"type":"Point"}
}