{
  "type": "Feature",
  "properties": {
    "iso:country":"IT",
    "sg:address":"Via Del Teroldego 6 38016 Mezzocorona",
    "sg:city":"Mezzocorona",
    "sg:classifiers":[
        {
            "category":"Building & Trades",
            "subcategory":"Construction",
            "type":"Services"
        }
    ],
    "sg:phone":"+39 0461 601656",
    "sg:postcode":"38016",
    "sg:province":"Trento",
    "sg:tags":[
        "mortar",
        "sealing",
        "additive",
        "concrete"
    ],
    "sg:website":"www.uniflexitalia.it",
    "wof:name":"Uniflex Srl",
    "wof:placetype":"venue"
},
  "geometry": {"coordinates":[11.121729,46.207764],"type":"Point"}
}