{
  "type": "Feature",
  "properties": {
    "addr:full":"10044 Pianezza Pianezza Torino 10044",
    "addr:postcode":"10044;10044",
    "iso:country":"IT",
    "sg:address":"10044 Pianezza",
    "sg:city":"Pianezza",
    "sg:orig_category":"Frigotecnica, Apparecchiature E Servizi",
    "sg:phone":"+39 011 967 4935",
    "sg:postcode":"10044",
    "sg:province":"Torino",
    "wof:name":"Tecnes Nova Snc",
    "wof:placetype":"venue"
},
  "geometry": {"coordinates":[7.5932478905,45.0965690613],"type":"Point"}
}