{
  "type": "Feature",
  "properties": {
    "addr:full":"20099 Sesto San Giovanni Sesto San Giovanni Milano 20099",
    "addr:postcode":"20099;20099",
    "iso:country":"IT",
    "sg:address":"20099 Sesto San Giovanni",
    "sg:city":"Sesto San Giovanni",
    "sg:orig_category":"Materiali E Componenti Elettrotecnici",
    "sg:phone":"+39 02 2622 1492",
    "sg:postcode":"20099",
    "sg:province":"Milano",
    "wof:name":"Ab 1 Di Arreghini Alberto",
    "wof:placetype":"venue"
},
  "geometry": {"coordinates":[9.2236,45.531509],"type":"Point"}
}