{
  "type": "Feature",
  "properties": {
    "addr:full":"18, Via Meucci Antonio 31029 Vittorio Veneto Vittorio Veneto Treviso 31029",
    "addr:postcode":"31029;31029",
    "addr:street":"Via Meucci Antonio",
    "iso:country":"IT",
    "sg:address":"18, Via Meucci Antonio 31029 Vittorio Veneto",
    "sg:city":"Vittorio Veneto",
    "sg:classifiers":[
        {
            "category":"Manufacturing",
            "subcategory":"Tools & Machinery",
            "type":"Manufacturing & Wholesale Goods"
        }
    ],
    "sg:phone":"+39 0438 912437",
    "sg:postcode":"31029",
    "sg:province":"Treviso",
    "sg:tags":[
        "environment",
        "equipment",
        "-"
    ],
    "wof:name":"Ecoglobal S.p.a.",
    "wof:placetype":"venue"
},
  "geometry": {"coordinates":[12.242072,45.666286],"type":"Point"}
}