{
  "type": "Feature",
  "properties": {
    "iso:country":"IT",
    "sg:address":"448, Via Delle Sorgenti 57121 Livorno",
    "sg:city":"Livorno",
    "sg:classifiers":[
        {
            "category":"Parking",
            "subcategory":"Lot",
            "type":"Transportation"
        }
    ],
    "sg:phone":"+39 0586 429988",
    "sg:postcode":"57121",
    "sg:province":"Livorno",
    "sg:tags":[
        "transport",
        "road"
    ],
    "wof:name":"Double V Transport (s.r.l.)",
    "wof:placetype":"venue"
},
  "geometry": {"coordinates":[10.369663,43.570133],"type":"Point"}
}