{
  "type": "Feature",
  "properties": {
    "addr:full":"27029 Vigevano Vigevano Pavia 27029",
    "addr:postcode":"27029;27029",
    "iso:country":"IT",
    "sg:address":"27029 Vigevano",
    "sg:city":"Vigevano",
    "sg:orig_category":"Prodotti Di Base E Forniture Per Industria Alimentare E Bevande. Carta, Cartone E Prodotti Primari. Forniture Per Attivita' Commerciali Ed Artigianali",
    "sg:phone":"+39 0381 20020",
    "sg:postcode":"27029",
    "sg:province":"Pavia",
    "wof:name":"Policart Di Pittau Andrea",
    "wof:placetype":"venue"
},
  "geometry": {"coordinates":[8.7475290298,45.3064193726],"type":"Point"}
}