{
  "type": "Feature",
  "properties": {
    "iso:country":"IT",
    "sg:address":"33, Via Delle Fornaci Comunali 60125 Ancona",
    "sg:city":"Ancona",
    "sg:classifiers":[
        {
            "category":"Marine",
            "type":"Transportation"
        }
    ],
    "sg:phone":"+39 39071201206",
    "sg:postcode":"60125",
    "sg:province":"Ancona",
    "sg:tags":[
        "transport",
        "sea"
    ],
    "wof:name":"Provvedinavi",
    "wof:placetype":"venue"
},
  "geometry": {"coordinates":[13.504767,43.61084],"type":"Point"}
}