{
  "type": "Feature",
  "properties": {
    "iso:country":"IT",
    "sg:address":"50018 Scandicci",
    "sg:city":"Scandicci",
    "sg:classifiers":[
        {
            "category":"Home & Garden",
            "subcategory":"Home Furnishings",
            "type":"Retail Goods"
        }
    ],
    "sg:phone":"+39 055 731 0194",
    "sg:postcode":"50018",
    "sg:province":"Firenze",
    "sg:tags":[
        "decorative",
        "goods",
        "furnishings",
        "leather",
        "object",
        "supplies",
        "clothing"
    ],
    "sg:website":"http://www.silvi-trimmings.it",
    "wof:name":"Silvi Srl",
    "wof:placetype":"venue"
},
  "geometry": {"coordinates":[11.146401,43.758804],"type":"Point"}
}