{
  "type": "Feature",
  "properties": {
    "iso:country":"IT",
    "sg:address":"75/a, Via Emilio Lepido 43100 Parma",
    "sg:city":"Parma",
    "sg:classifiers":[
        {
            "category":"Shopping",
            "subcategory":"Crafts & Fabrics",
            "type":"Retail Goods"
        }
    ],
    "sg:phone":"+39 0521 480611",
    "sg:postcode":"43100",
    "sg:province":"Parma",
    "wof:name":"Sa.te.co. (s.p.a.)",
    "wof:placetype":"venue"
},
  "geometry": {"coordinates":[10.2949199677,44.8232078552],"type":"Point"}
}