{
  "type": "Feature",
  "properties": {
    "iso:country":"IT",
    "sg:address":"Via Francia 53 37069 Villafranca Di Verona",
    "sg:city":"Villafranca di Verona",
    "sg:classifiers":[
        {
            "category":"Manufacturing",
            "subcategory":"Metals",
            "type":"Manufacturing & Wholesale Goods"
        }
    ],
    "sg:phone":"+39 045 630 2222",
    "sg:postcode":"37069",
    "sg:province":"Verona",
    "sg:tags":[
        "aluminium"
    ],
    "wof:name":"Fover Alluminio S.r.l.",
    "wof:placetype":"venue"
},
  "geometry": {"coordinates":[10.974078,45.410942],"type":"Point"}
}