{
  "type": "Feature",
  "properties": {
    "addr:full":"95019 Zafferana Etnea Zafferana Etnea Catania 95019",
    "addr:postcode":"95019;95019",
    "iso:country":"IT",
    "sg:address":"95019 Zafferana Etnea",
    "sg:city":"Zafferana Etnea",
    "sg:orig_category":"Arredamenti - Vendita Al Dettaglio",
    "sg:phone":"+39 095 708 2164",
    "sg:postcode":"95019",
    "sg:province":"Catania",
    "wof:name":"Di Mauro Arredi Di Di Mauro Santo & C. Snc",
    "wof:placetype":"venue"
},
  "geometry": {"coordinates":[15.067431,37.710384],"type":"Point"}
}