{
  "type": "Feature",
  "properties": {
    "iso:country":"IT",
    "sg:address":"3, Via Leopardi Giacomo 46043 Castiglione Delle Stiviere",
    "sg:city":"Castiglione delle Stiviere",
    "sg:classifiers":[
        {
            "category":"Shopping",
            "subcategory":"Clothing, Apparel, & Fashions",
            "type":"Retail Goods"
        }
    ],
    "sg:phone":"+39 0376 943211",
    "sg:postcode":"46043",
    "sg:province":"Mantova",
    "sg:tags":[
        "clothes"
    ],
    "wof:name":"Si Si S.p.a.",
    "wof:placetype":"venue"
},
  "geometry": {"coordinates":[10.797698,45.160366],"type":"Point"}
}