{
  "type": "Feature",
  "properties": {
    "iso:country":"IT",
    "sg:address":"73020 Carpignano Salentino",
    "sg:city":"Carpignano Salentino",
    "sg:orig_category":"Macchine, Impianti Ed Attrezzature Industria Chimica. Prodotti Vari In Metallo. Articoli Per Imballaggio E Confezionamento",
    "sg:phone":"+39 0836 586793",
    "sg:postcode":"73020",
    "sg:province":"Lecce",
    "wof:name":"Cito Elio",
    "wof:placetype":"venue"
},
  "geometry": {"coordinates":[18.340775,40.197937],"type":"Point"}
}