{
  "type": "Feature",
  "properties": {
    "addr:full":"20060 Gessate Gessate Milano 20060",
    "addr:postcode":"20060;20060",
    "iso:country":"IT",
    "sg:address":"20060 Gessate",
    "sg:city":"Gessate",
    "sg:orig_category":"Servizi E Lavori Per Arredamento E Industria Del Legno. Arte Ed Artigianato Artistico",
    "sg:phone":"+39 02 9578 0507",
    "sg:postcode":"20060",
    "sg:province":"Milano",
    "wof:name":"Valvassori Francesco",
    "wof:placetype":"venue"
},
  "geometry": {"coordinates":[9.448064,45.546276],"type":"Point"}
}