{
  "type": "Feature",
  "properties": {
    "addr:full":"60035 Jesi Jesi Ancona 60035",
    "addr:postcode":"60035;60035",
    "iso:country":"IT",
    "sg:address":"60035 Jesi",
    "sg:city":"Jesi",
    "sg:orig_category":"Macchine, Impianti Ed Attrezzature Industria Chimica",
    "sg:phone":"+39 0731 2311",
    "sg:postcode":"60035",
    "sg:province":"Ancona",
    "sg:website":"http://www.pieralisi.com",
    "wof:name":"Nuova M.a.i.p Macchine Agricole Industriali Pieralisi Spa",
    "wof:placetype":"venue"
},
  "geometry": {"coordinates":[13.23155,43.518715],"type":"Point"}
}