{
  "type": "Feature",
  "properties": {
    "iso:country":"IT",
    "sg:address":"20122 Milano",
    "sg:city":"Milano",
    "sg:orig_category":"Provincia E Servizi Provinciali",
    "sg:phone":"+39 0277401",
    "sg:postcode":"20122",
    "sg:province":"Milano",
    "sg:website":"http://www.provincia.milano.it",
    "wof:name":"Provincia Di Milano",
    "wof:placetype":"venue"
},
  "geometry": {"coordinates":[9.2034025192,45.4682655334],"type":"Point"}
}