{
  "type": "Feature",
  "properties": {
    "iso:country":"IT",
    "sg:address":"20081 Abbiategrasso",
    "sg:city":"Abbiategrasso",
    "sg:orig_category":"Pubblica Amministrazione",
    "sg:phone":"+39 02 9496 7586",
    "sg:postcode":"20081",
    "sg:province":"Milano",
    "wof:name":"Amministrazione Provinciale Di Milano",
    "wof:placetype":"venue"
},
  "geometry": {"coordinates":[8.9198246002,45.3930358887],"type":"Point"}
}