{
  "type": "Feature",
  "properties": {
    "iso:country":"IT",
    "sg:address":"20132 Milano",
    "sg:city":"Milano",
    "sg:orig_category":"Macchine, Impianti E Forniture Per Industria Grafica, Cartaria E Cartotecnica",
    "sg:phone":"+39 02 2630 6408",
    "sg:postcode":"20132",
    "sg:province":"Milano",
    "wof:name":"Emba Machinery Srl",
    "wof:placetype":"venue"
},
  "geometry": {"coordinates":[9.246145,45.508339],"type":"Point"}
}