{
  "type": "Feature",
  "properties": {
    "addr:full":"21019 Somma Lombardo Somma Lombardo Varese 21019",
    "addr:postcode":"21019;21019",
    "iso:country":"IT",
    "sg:address":"21019 Somma Lombardo",
    "sg:city":"Somma Lombardo",
    "sg:orig_category":"Accessori Moda D'abbigliamento. Forniture Per Abbigliamento E Pelletterie",
    "sg:phone":"+39 0331 255069",
    "sg:postcode":"21019",
    "sg:province":"Varese",
    "wof:name":"Ricamificio Val Di Rile",
    "wof:placetype":"venue"
},
  "geometry": {"coordinates":[8.711244,45.675224],"type":"Point"}
}