{
  "type": "Feature",
  "properties": {
    "iso:country":"IT",
    "sg:address":"Localita' Fontanaccio 57037 Portoferraio",
    "sg:city":"Portoferraio",
    "sg:classifiers":[
        {
            "category":"Travel",
            "subcategory":"Travel Agent",
            "type":"Entertainment"
        }
    ],
    "sg:phone":"+39 0565 915392",
    "sg:postcode":"57037",
    "sg:province":"Livorno",
    "sg:tags":[
        "business"
    ],
    "wof:name":"Acquaviva Park Hotel",
    "wof:placetype":"venue"
},
  "geometry": {"coordinates":[10.308011,43.551876],"type":"Point"}
}