{
  "type": "Feature",
  "properties": {
    "addr:full":"Via Brescia 185 25039 Travagliato Travagliato Brescia 25039",
    "addr:housenumber":"185",
    "addr:postcode":"25039;25039",
    "addr:street":"Via Brescia",
    "iso:country":"IT",
    "sg:address":"Via Brescia 185 25039 Travagliato",
    "sg:city":"Travagliato",
    "sg:classifiers":[
        {
            "category":"Shopping",
            "subcategory":"Clothing, Apparel, & Fashions",
            "type":"Retail Goods"
        }
    ],
    "sg:phone":"+39 030 686 3366",
    "sg:postcode":"25039",
    "sg:province":"Brescia",
    "sg:tags":[
        "sportswear"
    ],
    "sg:website":"www.gazelle.it",
    "wof:name":"Cedas Compagnia Europea Distribuzione Articoli Sportivi Srl",
    "wof:placetype":"venue"
},
  "geometry": {"coordinates":[10.100757,45.520061],"type":"Point"}
}