{
  "type": "Feature",
  "properties": {
    "iso:country":"IT",
    "sg:address":"37067 Valeggio Sul Mincio",
    "sg:city":"Valeggio sul Mincio",
    "sg:orig_category":"Formaggi E Latticini - Produzione E Ingrosso",
    "sg:phone":"+39 045 637 0255",
    "sg:postcode":"37067",
    "sg:province":"Verona",
    "wof:name":"Euroformaggi",
    "wof:placetype":"venue"
},
  "geometry": {"coordinates":[10.7328367233,45.3351821899],"type":"Point"}
}