{
  "type": "Feature",
  "properties": {
    "iso:country":"IT",
    "sg:address":"12, Via Firenze 57121 Livorno",
    "sg:city":"Livorno",
    "sg:classifiers":[
        {
            "category":"Wholesale",
            "subcategory":"Drugs",
            "type":"Manufacturing & Wholesale Goods"
        }
    ],
    "sg:phone":"+39 0586 405355",
    "sg:postcode":"57121",
    "sg:province":"Livorno",
    "sg:tags":[
        "chemical",
        "pharmaceutical"
    ],
    "wof:name":"Co.e.ci Trans Oil (s.r.l.)",
    "wof:placetype":"venue"
},
  "geometry": {"coordinates":[10.326382,43.560223],"type":"Point"}
}