{
  "type": "Feature",
  "properties": {
    "iso:country":"IT",
    "sg:address":"00142 Roma",
    "sg:city":"Roma",
    "sg:orig_category":"Servizi E Lavori Per Ecologia E Smaltimento Rifiuti. Acqua, Luce, Gas E Societa' Di Esercizio Pubblico",
    "sg:phone":"+39 06 5169 2845",
    "sg:postcode":"00142",
    "sg:province":"Roma",
    "wof:name":"All Clean",
    "wof:placetype":"venue"
},
  "geometry": {"coordinates":[12.51202,41.840939],"type":"Point"}
}