{
  "type": "Feature",
  "properties": {
    "iso:country":"IT",
    "sg:address":"Via Xxv Aprile 11 42015 Correggio",
    "sg:classifiers":[
        {
            "category":"Autos & Motor Vehicles",
            "subcategory":"Recreational Vehicle Sales",
            "type":"Retail Goods"
        }
    ],
    "sg:phone":"+39 0522 692195",
    "sg:postcode":"42015",
    "sg:province":"Reggio Nell'Emilia",
    "sg:tags":[
        "haying",
        "machine"
    ],
    "wof:name":"O.m.c. Di Cattini Giancarlo & C. S.n.c.",
    "wof:placetype":"venue"
},
  "geometry": {"coordinates":[10.627794,44.696228],"type":"Point"}
}