{
  "type": "Feature",
  "properties": {
    "iso:country":"IT",
    "sg:address":"35020 Legnaro",
    "sg:city":"Legnaro",
    "sg:orig_category":"Carni, Salumi E Pesci",
    "sg:phone":"+39 049 790951",
    "sg:postcode":"35020",
    "sg:province":"Padova",
    "wof:name":"Massaro Doriano",
    "wof:placetype":"venue"
},
  "geometry": {"coordinates":[11.966176,45.342331],"type":"Point"}
}