{
  "type": "Feature",
  "properties": {
    "iso:country":"IT",
    "sg:address":"5, Via Genova 20060 Bussero",
    "sg:city":"Bussero",
    "sg:classifiers":[
        {
            "category":"Manufacturing",
            "subcategory":"Metals",
            "type":"Manufacturing & Wholesale Goods"
        }
    ],
    "sg:phone":"+39 02 9503 9334",
    "sg:postcode":"20060",
    "sg:province":"Milano",
    "sg:tags":[
        "processing"
    ],
    "wof:name":"Modercromo S.r.l.",
    "wof:placetype":"venue"
},
  "geometry": {"coordinates":[9.3642835617,45.5294380188],"type":"Point"}
}