{
  "type": "Feature",
  "properties": {
    "iso:country":"IT",
    "sg:address":"10090 Villarbasse",
    "sg:city":"Villarbasse",
    "sg:orig_category":"Macchine Utensili E Impianti",
    "sg:phone":"+39 011 952294",
    "sg:postcode":"10090",
    "sg:province":"Torino",
    "wof:name":"Meccanoplast",
    "wof:placetype":"venue"
},
  "geometry": {"coordinates":[7.495471,45.048588],"type":"Point"}
}