{
  "type": "Feature",
  "properties": {
    "addr:full":"Via Fiume 19 53036 Poggibonsi Poggibonsi Siena 53036",
    "addr:housenumber":"19",
    "addr:postcode":"53036;53036",
    "addr:street":"Via Fiume",
    "iso:country":"IT",
    "sg:address":"Via Fiume 19 53036 Poggibonsi",
    "sg:city":"Poggibonsi",
    "sg:classifiers":[
        {
            "category":"Home & Garden",
            "subcategory":"Kitchen Supply",
            "type":"Retail Goods"
        }
    ],
    "sg:phone":"+39 0577 938003",
    "sg:postcode":"53036",
    "sg:province":"Siena",
    "sg:tags":[
        "fitted"
    ],
    "sg:website":"www.cucinezani.it",
    "wof:name":"Zani Cucine Spa",
    "wof:placetype":"venue"
},
  "geometry": {"coordinates":[11.1460170746,43.4708557129],"type":"Point"}
}