{
  "type": "Feature",
  "properties": {
    "addr:full":"95, Via S. Cristina 10071 Borgaro Torinese Borgaro Torinese Torino 10071",
    "addr:postcode":"10071;10071",
    "addr:street":"Via S. Cristina",
    "iso:country":"IT",
    "sg:address":"95, Via S. Cristina 10071 Borgaro Torinese",
    "sg:city":"Borgaro Torinese",
    "sg:classifiers":[
        {
            "category":"Manufacturing",
            "subcategory":"Chemicals & Compounds",
            "type":"Manufacturing & Wholesale Goods"
        }
    ],
    "sg:phone":"+39 011 262 4375",
    "sg:postcode":"10071",
    "sg:province":"Torino",
    "sg:tags":[
        "chemistry"
    ],
    "wof:name":"So.co.met S.r.l.",
    "wof:placetype":"venue"
},
  "geometry": {"coordinates":[7.686822,45.135269],"type":"Point"}
}