{
  "type": "Feature",
  "properties": {
    "iso:country":"IT",
    "sg:address":"95030 Nicolosi",
    "sg:city":"Nicolosi",
    "sg:orig_category":"Bagno - Accessori E Mobili",
    "sg:phone":"+39 095 911347",
    "sg:postcode":"95030",
    "sg:province":"Catania",
    "wof:name":"Ceramiche Nicoloso",
    "wof:placetype":"venue"
},
  "geometry": {"coordinates":[15.07143,37.5751],"type":"Point"}
}