{
  "type": "Feature",
  "properties": {
    "iso:country":"IT",
    "sg:address":"102, Via Pescosolido 00158 Roma",
    "sg:city":"Roma",
    "sg:classifiers":[
        {
            "category":"Wholesale",
            "subcategory":"Machinery & Supplies",
            "type":"Manufacturing & Wholesale Goods"
        }
    ],
    "sg:phone":"+39 06 4173 2929",
    "sg:postcode":"00158",
    "sg:province":"Roma",
    "sg:tags":[
        "equipment",
        "-",
        "instrument",
        "measurement"
    ],
    "wof:name":"Europrocess Srl",
    "wof:placetype":"venue"
},
  "geometry": {"coordinates":[12.562222,41.91888],"type":"Point"}
}