{
  "type": "Feature",
  "properties": {
    "iso:country":"IT",
    "sg:address":"39023 Lasa",
    "sg:city":"Lasa",
    "sg:orig_category":"Materiali Edili",
    "sg:phone":"+39 0473 739937",
    "sg:postcode":"39023",
    "sg:province":"Bolzano/Bozen",
    "sg:website":"http://www.schoenthaler.com",
    "wof:name":"Schoenthaler Alosi & Josef Snc",
    "wof:placetype":"venue"
},
  "geometry": {"coordinates":[10.645309,46.629429],"type":"Point"}
}