{
  "type": "Feature",
  "properties": {
    "addr:full":"Via Salgari 2/m 30036 Santa Maria Di Sala Santa Maria di Sala Venezia 30036",
    "addr:housenumber":"2;m",
    "addr:postcode":"30036;30036",
    "addr:street":"Via Salgari;/;Maria",
    "iso:country":"IT",
    "sg:address":"Via Salgari 2/m 30036 Santa Maria Di Sala",
    "sg:city":"Santa Maria di Sala",
    "sg:classifiers":[
        {
            "category":"Manufacturing",
            "subcategory":"Leather Goods",
            "type":"Manufacturing & Wholesale Goods"
        }
    ],
    "sg:phone":"+39 041 487616",
    "sg:postcode":"30036",
    "sg:province":"Venezia",
    "sg:tags":[
        "synthetic",
        "label"
    ],
    "wof:name":"Etichettificio Salese Sas",
    "wof:placetype":"venue"
},
  "geometry": {"coordinates":[12.012215,45.502628],"type":"Point"}
}