{
  "type": "Feature",
  "properties": {
    "iso:country":"IT",
    "sg:address":"16137 Genova",
    "sg:city":"Genova",
    "sg:orig_category":"Servizi E Lavori Per Ecologia E Smaltimento Rifiuti. Arte Ed Artigianato Artistico. Servizi Ausiliari Di Sorveglianza, Manutenzione E Pulizia",
    "sg:phone":"+39 010 831 5233",
    "sg:postcode":"16137",
    "sg:province":"Genova",
    "wof:name":"T.e.d. Srl",
    "wof:placetype":"venue"
},
  "geometry": {"coordinates":[8.949682,44.408459],"type":"Point"}
}