{
  "type": "Feature",
  "properties": {
    "iso:country":"IT",
    "sg:address":"20127 Milano",
    "sg:city":"Milano",
    "sg:orig_category":"Studi E Consulenze Tecniche E Industriali. Assicurazioni E Servizi Assicurativi. Consulenze Tecniche, Amministrative E Perizie",
    "sg:phone":"+39 02 282 9602",
    "sg:postcode":"20127",
    "sg:province":"Milano",
    "wof:name":"Polizzi Nicola",
    "wof:placetype":"venue"
},
  "geometry": {"coordinates":[9.220168,45.495895],"type":"Point"}
}