{
  "type": "Feature",
  "properties": {
    "iso:country":"IT",
    "sg:address":"40135 Bologna",
    "sg:city":"Bologna",
    "sg:orig_category":"Studi E Consulenze Amministrative, Commerciali E Aziendali. Banche E Servizi Finanziari. Agenzie D'affari E Servizi Commerciali. Consulenze Tecniche, Amministrative E Perizie",
    "sg:phone":"+39 051 615 3369",
    "sg:postcode":"40135",
    "sg:province":"Bologna",
    "sg:website":"http://www.sassiconsulting.com",
    "wof:name":"Studio Sassi - Ragionieri Commercialisti Associati",
    "wof:placetype":"venue"
},
  "geometry": {"coordinates":[11.304607,44.471416],"type":"Point"}
}