{
  "type": "Feature",
  "properties": {
    "addr:full":"44020 Ostellato Ostellato Ferrara 44020",
    "addr:postcode":"44020;44020",
    "iso:country":"IT",
    "sg:address":"44020 Ostellato",
    "sg:city":"Ostellato",
    "sg:orig_category":"Porte",
    "sg:phone":"+39 0533 680937",
    "sg:postcode":"44020",
    "sg:province":"Ferrara",
    "wof:name":"F.b. Infissi Srl",
    "wof:placetype":"venue"
},
  "geometry": {"coordinates":[11.8444461823,44.7671813965],"type":"Point"}
}