{
  "type": "Feature",
  "properties": {
    "addr:full":"Via Caldera 21 20153 Milano Milano Milano 20153",
    "addr:housenumber":"21",
    "addr:postcode":"20153;20153",
    "addr:street":"Via Caldera",
    "iso:country":"IT",
    "sg:address":"Via Caldera 21 20153 Milano",
    "sg:city":"Milano",
    "sg:classifiers":[
        {
            "category":"Manufacturing",
            "subcategory":"Petroleum Products",
            "type":"Manufacturing & Wholesale Goods"
        }
    ],
    "sg:phone":"+39 02 452771",
    "sg:postcode":"20153",
    "sg:province":"Milano",
    "sg:tags":[
        "cosmetic",
        "distributors"
    ],
    "sg:website":"www.univarspa.it",
    "wof:name":"Univar Spa",
    "wof:placetype":"venue"
},
  "geometry": {"coordinates":[9.094625,45.476025],"type":"Point"}
}