{
  "type": "Feature",
  "properties": {
    "addr:full":"21041 Albizzate Albizzate Varese 21041",
    "addr:postcode":"21041;21041",
    "iso:country":"IT",
    "sg:address":"21041 Albizzate",
    "sg:city":"Albizzate",
    "sg:orig_category":"Prodotti Chimici Di Base",
    "sg:phone":"+39 0331 715111",
    "sg:postcode":"21041",
    "sg:province":"Varese",
    "sg:website":"http://www.lamberti.com",
    "wof:name":"Lamberti Spa",
    "wof:placetype":"venue"
},
  "geometry": {"coordinates":[8.7909383774,45.7752914429],"type":"Point"}
}