{
  "type": "Feature",
  "properties": {
    "addr:full":"8, Via Vivaldi 92024 Canicatti' Agrigento 92024",
    "addr:postcode":"92024;92024",
    "addr:street":"Via Vivaldi",
    "iso:country":"IT",
    "sg:address":"8, Via Vivaldi 92024 Canicatti'",
    "sg:classifiers":[
        {
            "category":"Manufacturing",
            "subcategory":"Food",
            "type":"Manufacturing & Wholesale Goods"
        }
    ],
    "sg:phone":"+39 0922 830106",
    "sg:postcode":"92024",
    "sg:province":"Agrigento",
    "sg:tags":[
        "equipment",
        "processing",
        "-",
        "machinery"
    ],
    "wof:name":"Livana Gel S.r.l.",
    "wof:placetype":"venue"
},
  "geometry": {"coordinates":[13.5769557953,37.3111877441],"type":"Point"}
}