{
  "type": "Feature",
  "properties": {
    "iso:country":"IT",
    "sg:address":"36060 Longare",
    "sg:city":"Longa",
    "sg:classifiers":[
        {
            "category":"Wholesale",
            "subcategory":"Machinery & Supplies",
            "type":"Manufacturing & Wholesale Goods"
        }
    ],
    "sg:phone":"+39 0444 554025",
    "sg:postcode":"36060",
    "sg:province":"Vicenza",
    "sg:tags":[
        "product",
        "industrial",
        "equipment",
        "engineering",
        "mechanical",
        "electronic"
    ],
    "wof:name":"Palladio Impianti Srl",
    "wof:placetype":"venue"
},
  "geometry": {"coordinates":[11.603009,45.482582],"type":"Point"}
}