{
  "type": "Feature",
  "properties": {
    "addr:full":"Via Aldo Moro 131; Frosinone; 03100 Frosinone Frosinone 03100",
    "addr:housenumber":"131",
    "addr:postcode":"03100;03100",
    "addr:street":"Via Aldo Moro",
    "iso:country":"IT",
    "sg:address":"Via Aldo Moro 131; Frosinone; 03100",
    "sg:city":"Frosinone",
    "sg:classifiers":[
        {
            "category":"Banks & Credit Unions",
            "subcategory":"Bank",
            "type":"Services"
        }
    ],
    "sg:phone":"+39 0775 270421",
    "sg:postcode":"03100",
    "sg:province":"Frosinone",
    "wof:name":"Istituto Bancario, San Paolo Di Torino Spa",
    "wof:placetype":"venue"
},
  "geometry": {"coordinates":[13.34718,41.644623],"type":"Point"}
}