{
  "type": "Feature",
  "properties": {
    "iso:country":"IT",
    "sg:address":"04012 Cisterna Di Latina",
    "sg:city":"Cisterna di Latina",
    "sg:orig_category":"Chiese Ed Associazioni Religiose",
    "sg:phone":"+39 06 969 5825",
    "sg:postcode":"04012",
    "sg:province":"Latina",
    "wof:name":"Sala Del Regno Testimoni Di Geova",
    "wof:placetype":"venue"
},
  "geometry": {"coordinates":[12.829252,41.60561],"type":"Point"}
}