{
  "type": "Feature",
  "properties": {
    "addr:full":"Pza Lega Lombarda 3 23900 Lecco Lecco Lecco 23900",
    "addr:housenumber":"3",
    "addr:postcode":"23900;23900",
    "addr:street":"Pza Lega Lombarda",
    "iso:country":"IT",
    "sg:address":"Pza Lega Lombarda 3 23900 Lecco",
    "sg:city":"Lecco",
    "sg:classifiers":[
        {
            "category":"Home & Garden",
            "subcategory":"Hardware",
            "type":"Retail Goods"
        }
    ],
    "sg:phone":"+39 0341 285124",
    "sg:postcode":"23900",
    "sg:province":"Lecco",
    "sg:tags":[
        "agricultural",
        "implement"
    ],
    "sg:website":"www.sartex.it",
    "wof:name":"Sartex Dr. Gabriele Sartori & C. S As",
    "wof:placetype":"venue"
},
  "geometry": {"coordinates":[9.392495,45.856277],"type":"Point"}
}