{
  "type": "Feature",
  "properties": {
    "iso:country":"IT",
    "sg:address":"20093 Cologno Monzese",
    "sg:city":"Cologno Monzese",
    "sg:orig_category":"Macchine, Impianti Ed Attrezzature Per Industria Alimentare E Bevande",
    "sg:phone":"+39 02 2730 0794",
    "sg:postcode":"20093",
    "sg:province":"Milano",
    "wof:name":"Bi - Pan Di Zampieri Aldo & Montini Ines Sdf",
    "wof:placetype":"venue"
},
  "geometry": {"coordinates":[9.275508,45.545238],"type":"Point"}
}