{
  "type": "Feature",
  "properties": {
    "iso:country":"IT",
    "sg:address":"Via Spinelle 03012 Anagni",
    "sg:city":"Anagni",
    "sg:classifiers":[
        {
            "category":"Shopping",
            "subcategory":"Computers & Home Electronics",
            "type":"Retail Goods"
        }
    ],
    "sg:phone":"+39 0775 767932",
    "sg:postcode":"03012",
    "sg:province":"Frosinone",
    "sg:tags":[
        "electronic",
        "electrical",
        "equipment"
    ],
    "wof:name":"H.t.s. Elettromeccanica S.r.l.",
    "wof:placetype":"venue"
},
  "geometry": {"coordinates":[13.351902,41.640137],"type":"Point"}
}