{
  "type": "Feature",
  "properties": {
    "iso:country":"IT",
    "sg:address":"14, Via Ca' Balletto 30034 Mira",
    "sg:city":"Mira",
    "sg:classifiers":[
        {
            "category":"Parking",
            "subcategory":"Lot",
            "type":"Transportation"
        }
    ],
    "sg:phone":"+39 041 547 0113",
    "sg:postcode":"30034",
    "sg:province":"Venezia",
    "sg:tags":[
        "transport",
        "road"
    ],
    "wof:name":"T.c.a. Trasporti (s.r.l.)",
    "wof:placetype":"venue"
},
  "geometry": {"coordinates":[12.182125,45.430157],"type":"Point"}
}