{
  "type": "Feature",
  "properties": {
    "iso:country":"IT",
    "sg:address":"20010 Mesero",
    "sg:city":"Mesero",
    "sg:orig_category":"Materiali E Componenti Elettrotecnici",
    "sg:phone":"+39 02 9728 5187",
    "sg:postcode":"20010",
    "sg:province":"Milano",
    "wof:name":"Giuliani Giuseppe",
    "wof:placetype":"venue"
},
  "geometry": {"coordinates":[9.273092,45.409405],"type":"Point"}
}