{
  "type": "Feature",
  "properties": {
    "addr:full":"Via Quadro, 175; Lisignago; 38030 Lisignago Trento 38030",
    "addr:housenumber":"175",
    "addr:postcode":"38030;38030",
    "addr:street":"Via Quadro",
    "iso:country":"IT",
    "sg:address":"Via Quadro, 175; Lisignago; 38030",
    "sg:city":"Lisignago",
    "sg:classifiers":[
        {
            "category":"Banks & Credit Unions",
            "subcategory":"Bank",
            "type":"Services"
        }
    ],
    "sg:phone":"+39 0461 683600",
    "sg:postcode":"38030",
    "sg:province":"Trento",
    "wof:name":"Cassa Rurale",
    "wof:placetype":"venue"
},
  "geometry": {"coordinates":[11.189109,46.158577],"type":"Point"}
}