{
  "type": "Feature",
  "properties": {
    "addr:full":"Piazza Madonnella 8; S. Felice Circeo",
    "addr:housenumber":"8",
    "addr:street":"Piazza Madonnella;S. Felice Circeo",
    "iso:country":"IT",
    "sg:address":"Piazza Madonnella 8; S. Felice Circeo",
    "sg:classifiers":[
        {
            "category":"Banks & Credit Unions",
            "subcategory":"Bank",
            "type":"Services"
        }
    ],
    "sg:phone":"+39 0773 548213",
    "wof:name":"Banca Di Roma",
    "wof:placetype":"venue"
},
  "geometry": {"coordinates":[13.097545,41.242035],"type":"Point"}
}