{
  "type": "Feature",
  "properties": {
    "addr:full":"Piazza Risorgimento 2; Gallarate",
    "addr:housenumber":"2",
    "addr:street":"Piazza Risorgimento",
    "iso:country":"IT",
    "sg:address":"Piazza Risorgimento 2; Gallarate",
    "sg:classifiers":[
        {
            "category":"Banks & Credit Unions",
            "subcategory":"Bank",
            "type":"Services"
        }
    ],
    "sg:phone":"+39 0331 775042",
    "wof:name":"Banca Di Roma",
    "wof:placetype":"venue"
},
  "geometry": {"coordinates":[8.791799,45.662445],"type":"Point"}
}