{
  "type": "Feature",
  "properties": {
    "addr:full":"39042 Bressanone Bressanone Bolzano/Bozen 39042",
    "addr:postcode":"39042;39042",
    "iso:country":"IT",
    "sg:address":"39042 Bressanone",
    "sg:city":"Bressanone",
    "sg:orig_category":"Forniture Per Abbigliamento E Pelletterie",
    "sg:phone":"+39 0472 837307",
    "sg:postcode":"39042",
    "sg:province":"Bolzano/Bozen",
    "wof:name":"Betten Erler Piumini Thomas Erler & C. S.a.s.",
    "wof:placetype":"venue"
},
  "geometry": {"coordinates":[11.6387796402,46.6878128052],"type":"Point"}
}