{
  "type": "Feature",
  "properties": {
    "iso:country":"IT",
    "sg:address":"52, Via Veneto 95024 Acireale",
    "sg:city":"Acireale",
    "sg:classifiers":[
        {
            "category":"Parking",
            "subcategory":"Lot",
            "type":"Transportation"
        }
    ],
    "sg:phone":"+39 39095891645",
    "sg:postcode":"95024",
    "sg:province":"Catania",
    "sg:tags":[
        "transport",
        "road"
    ],
    "wof:name":"La Sicilia Traslochi",
    "wof:placetype":"venue"
},
  "geometry": {"coordinates":[15.146601,37.555691],"type":"Point"}
}