{
  "type": "Feature",
  "properties": {
    "iso:country":"IT",
    "sg:address":"10040 Caselette",
    "sg:city":"Caselette",
    "sg:orig_category":"Motori Ed Organi Di Trasmissione. Ricambi E Componenti Dei Mezzi Di Trasporto",
    "sg:phone":"+39 011 968 8090",
    "sg:postcode":"10040",
    "sg:province":"Torino",
    "wof:name":"C.s.b. Di Baron S.",
    "wof:placetype":"venue"
},
  "geometry": {"coordinates":[7.4842729568,45.1368522644],"type":"Point"}
}