{
  "type": "Feature",
  "properties": {
    "addr:full":"Via Cerbaia 107 51035 Lamporecchio Lamporecchio Pistoia 51035",
    "addr:housenumber":"107",
    "addr:postcode":"51035;51035",
    "addr:street":"Via Cerbaia",
    "iso:country":"IT",
    "sg:address":"Via Cerbaia 107 51035 Lamporecchio",
    "sg:city":"Lamporecchio",
    "sg:classifiers":[
        {
            "category":"Food & Beverages",
            "subcategory":"Liquor & Beverages",
            "type":"Retail Goods"
        }
    ],
    "sg:phone":"+39 0573 82917",
    "sg:postcode":"51035",
    "sg:province":"Pistoia",
    "sg:tags":[
        "wine",
        "italian"
    ],
    "sg:website":"www.sensivini.com",
    "wof:name":"Sensi Vigne E Vini Srl",
    "wof:placetype":"venue"
},
  "geometry": {"coordinates":[10.872278,43.806065],"type":"Point"}
}