{
  "type": "Feature",
  "properties": {
    "iso:country":"IT",
    "sg:address":"00148 Roma",
    "sg:city":"Roma",
    "sg:classifiers":[
        {
            "category":"Health Services",
            "subcategory":"Health Practitioner",
            "type":"Services"
        }
    ],
    "sg:phone":"+39 06 653 4868",
    "sg:postcode":"00148",
    "sg:province":"Roma",
    "sg:tags":[
        "medici"
    ],
    "wof:name":"Proietti Italo",
    "wof:placetype":"venue"
},
  "geometry": {"coordinates":[12.4424200058,41.8439941406],"type":"Point"}
}