{
  "type": "Feature",
  "properties": {
    "iso:country":"IT",
    "sg:address":"37100 Verona",
    "sg:orig_category":"Ricerca, Selezione E Formazione Del Personale",
    "sg:phone":"+39 045 810411",
    "sg:province":"VR",
    "wof:name":"Umana Spa",
    "wof:placetype":"venue"
},
  "geometry": {"coordinates":[11.043932,45.382828],"type":"Point"}
}