{
  "type": "Feature",
  "properties": {
    "iso:country":"IT",
    "sg:address":"40026 Imola",
    "sg:city":"Imola",
    "sg:orig_category":"Utensili Meccanici E Materiali. Forniture Per Attivita' Industriali",
    "sg:phone":"+39 0542 641081",
    "sg:postcode":"40026",
    "sg:province":"Bologna",
    "wof:name":"A. Ros. Snc Di Fabio Arrigoni E Luca Rossetti",
    "wof:placetype":"venue"
},
  "geometry": {"coordinates":[11.727327,44.359402],"type":"Point"}
}