{
  "type": "Feature",
  "properties": {
    "iso:country":"IT",
    "sg:address":"Via Milano 15 22036 Erba",
    "sg:city":"Erba",
    "sg:classifiers":[
        {
            "category":"Wholesale",
            "subcategory":"Machinery & Supplies",
            "type":"Manufacturing & Wholesale Goods"
        }
    ],
    "sg:phone":"+39 031 641606",
    "sg:postcode":"22036",
    "sg:province":"Como",
    "sg:tags":[
        "pin",
        "clevis"
    ],
    "sg:website":"www.ome-it.com",
    "wof:name":"Ome Metallurgica Erbese Srl",
    "wof:placetype":"venue"
},
  "geometry": {"coordinates":[9.240331,45.796875],"type":"Point"}
}