{
  "type": "Feature",
  "properties": {
    "iso:country":"IT",
    "sg:address":"92100 Agrigento",
    "sg:city":"Agrigento",
    "sg:classifiers":[
        {
            "category":"Shopping",
            "subcategory":"Stationery & Office Supplies",
            "type":"Retail Goods"
        }
    ],
    "sg:phone":"+39 0922 441871",
    "sg:postcode":"92100",
    "sg:province":"Agrigento",
    "sg:tags":[
        "activities",
        "articles",
        "commercial",
        "packaging",
        "packing",
        "artisan",
        "supplies"
    ],
    "wof:name":"Techno Sacchi Srl",
    "wof:placetype":"venue"
},
  "geometry": {"coordinates":[13.5784015656,37.3089904785],"type":"Point"}
}