{
  "type": "Feature",
  "properties": {
    "addr:full":"Via Umberto I 48, 90044 Carini, Pa Carini Palermo 90044",
    "addr:housenumber":"48",
    "addr:postcode":"90044;90044",
    "addr:street":"Via Umberto I",
    "iso:country":"IT",
    "sg:address":"Via Umberto I 48, 90044 Carini, Pa",
    "sg:city":"Carini",
    "sg:classifiers":[
        {
            "category":"Banks & Credit Unions",
            "subcategory":"Bank",
            "type":"Services"
        }
    ],
    "sg:postcode":"90044",
    "sg:province":"Palermo",
    "wof:name":"Banca Popolare Di Carini Spa",
    "wof:placetype":"venue"
},
  "geometry": {"coordinates":[13.233733,38.129662],"type":"Point"}
}