{
  "type": "Feature",
  "properties": {
    "iso:country":"IT",
    "sg:address":"59100 Prato",
    "sg:city":"Prato",
    "sg:orig_category":"Serramenti Ed Infissi. Prodotti Vari In Metallo",
    "sg:phone":"+39 0574 630094",
    "sg:postcode":"59100",
    "sg:province":"Prato",
    "sg:website":"http://www.centrodiffserr.it",
    "wof:name":"Centro Diffusione Serramenti Srl",
    "wof:placetype":"venue"
},
  "geometry": {"coordinates":[11.08718,43.869297],"type":"Point"}
}