{
  "type": "Feature",
  "properties": {
    "addr:full":"46037 Roncoferraro Roncoferraro Mantova 46037",
    "addr:postcode":"46037;46037",
    "iso:country":"IT",
    "sg:address":"46037 Roncoferraro",
    "sg:city":"Roncoferraro",
    "sg:orig_category":"Studi E Consulenze Tecniche E Industriali. Servizi E Lavori Per Edilizia E Lavori Pubblici. Professionisti - Studi E Servizi Ed Associazioni Di Interesse Aziendale",
    "sg:phone":"+39 0376 664164",
    "sg:postcode":"46037",
    "sg:province":"Mantova",
    "wof:name":"Noema Solid Di Cavicchini Ing. Sante & C. Sas",
    "wof:placetype":"venue"
},
  "geometry": {"coordinates":[10.947917,45.145512],"type":"Point"}
}