{
  "type": "Feature",
  "properties": {
    "iso:country":"IT",
    "sg:address":"11, Via Canada' 35020 Padova",
    "sg:classifiers":[
        {
            "category":"Wholesale",
            "subcategory":"Medical Equipment & Supplies",
            "type":"Manufacturing & Wholesale Goods"
        }
    ],
    "sg:phone":"+39 049 879 0199",
    "sg:postcode":"35020",
    "sg:province":"Padova",
    "sg:tags":[
        "-",
        "health",
        "instrument"
    ],
    "wof:name":"Givas (s.r.l.)",
    "wof:placetype":"venue"
},
  "geometry": {"coordinates":[11.844167,45.397499],"type":"Point"}
}