{
  "type": "Feature",
  "properties": {
    "addr:full":"31046 Oderzo Oderzo Treviso 31046",
    "addr:postcode":"31046;31046",
    "iso:country":"IT",
    "sg:address":"31046 Oderzo",
    "sg:city":"Oderzo",
    "sg:orig_category":"Accessori Moda D'abbigliamento. Forniture Per Abbigliamento E Pelletterie",
    "sg:phone":"+39 422716267",
    "sg:postcode":"31046",
    "sg:province":"Treviso",
    "sg:website":"http://www.cuciservice.com",
    "wof:name":"Cuci Service Di Feltrin Denise",
    "wof:placetype":"venue"
},
  "geometry": {"coordinates":[12.497724,45.790432],"type":"Point"}
}