{
  "type": "Feature",
  "properties": {
    "addr:full":"95125 Catania Catania Catania 95125",
    "addr:postcode":"95125;95125",
    "iso:country":"IT",
    "sg:address":"95125 Catania",
    "sg:city":"Catania",
    "sg:classifiers":[
        {
            "category":"Parking",
            "subcategory":"Lot",
            "type":"Transportation"
        }
    ],
    "sg:phone":"+39 095 433705",
    "sg:postcode":"95125",
    "sg:province":"Catania",
    "sg:tags":[
        "good",
        "shipment",
        "transport"
    ],
    "wof:name":"Eurotraslochi Di Giuffrida Antonio",
    "wof:placetype":"venue"
},
  "geometry": {"coordinates":[15.083538,37.518665],"type":"Point"}
}