{
  "type": "Feature",
  "properties": {
    "iso:country":"IT",
    "sg:address":"24059 Urgnano",
    "sg:city":"Urgnano",
    "sg:orig_category":"Apparecchiature E Sistemi Per Imballaggio E Confezionamento",
    "sg:phone":"+39 035 890271",
    "sg:postcode":"24059",
    "sg:province":"Bergamo",
    "wof:name":"Testa Engineering S.r.l.",
    "wof:placetype":"venue"
},
  "geometry": {"coordinates":[9.704748,45.584454],"type":"Point"}
}