{
  "type": "Feature",
  "properties": {
    "iso:country":"IT",
    "sg:address":"34135 Trieste",
    "sg:city":"Trieste",
    "sg:orig_category":"Bevande, Vini E Liquori",
    "sg:phone":"+39 040 414289",
    "sg:postcode":"34135",
    "sg:province":"Trieste",
    "wof:name":"Castelli Oscar",
    "wof:placetype":"venue"
},
  "geometry": {"coordinates":[13.771305,45.664352],"type":"Point"}
}