{
  "type": "Feature",
  "properties": {
    "addr:full":"16, Via Postumia 31045 Motta Di Livenza Motta di Livenza Treviso 31045",
    "addr:postcode":"31045;31045",
    "addr:street":"Via Postumia",
    "iso:country":"IT",
    "sg:address":"16, Via Postumia 31045 Motta Di Livenza",
    "sg:city":"Motta di Livenza",
    "sg:orig_category":"Miscellaneous Products",
    "sg:phone":"+39 390 422 7657",
    "sg:postcode":"31045",
    "sg:province":"Treviso",
    "wof:name":"Elettronica Veneta & In.el. S.p.a.",
    "wof:placetype":"venue"
},
  "geometry": {"coordinates":[12.5945577621,45.7815513611],"type":"Point"}
}