{
  "type": "Feature",
  "properties": {
    "iso:country":"IT",
    "sg:address":"80022 Arzano",
    "sg:city":"Arzano",
    "sg:orig_category":"Cancelli, Porte E Portoni Automatici E Telecomandati",
    "sg:phone":"+39 081 731 3316",
    "sg:postcode":"80022",
    "sg:province":"Napoli",
    "sg:website":"http://www.madasrl.com",
    "wof:name":"Mada D&d Srl",
    "wof:placetype":"venue"
},
  "geometry": {"coordinates":[14.247883,40.930782],"type":"Point"}
}