{
  "type": "Feature",
  "properties": {
    "iso:country":"IT",
    "sg:address":"47034 Forlimpopoli",
    "sg:city":"Forlimpopoli",
    "sg:orig_category":"Lucernari",
    "sg:phone":"+39 0543 743910",
    "sg:postcode":"47034",
    "sg:province":"Forl\u00ec-Cesena",
    "wof:name":"Luxin Srl",
    "wof:placetype":"venue"
},
  "geometry": {"coordinates":[12.12564,44.186607],"type":"Point"}
}