{
  "type": "Feature",
  "properties": {
    "addr:full":"91100 Trapani Trapani Trapani 91100",
    "addr:postcode":"91100;91100",
    "iso:country":"IT",
    "sg:address":"91100 Trapani",
    "sg:city":"Trapani",
    "sg:orig_category":"Prodotti Chimici Di Base",
    "sg:phone":"+39 0923 871048",
    "sg:postcode":"91100",
    "sg:province":"Trapani",
    "wof:name":"I.m.a. Industria Meridionale Alcolici (s.r.l.)",
    "wof:placetype":"venue"
},
  "geometry": {"coordinates":[12.5223464966,38.0100059509],"type":"Point"}
}