{
  "type": "Feature",
  "properties": {
    "iso:country":"IT",
    "sg:address":"73043 Copertino",
    "sg:city":"Copertino",
    "sg:orig_category":"Articoli Per Imballaggio E Confezionamento. Forniture Per Uffici. Forniture Per Attivita' Commerciali Ed Artigianali",
    "sg:phone":"+39 0832 931184",
    "sg:postcode":"73043",
    "sg:province":"Lecce",
    "wof:name":"Gennaro Giovanni New Plast",
    "wof:placetype":"venue"
},
  "geometry": {"coordinates":[18.059866,40.277798],"type":"Point"}
}