{
  "type": "Feature",
  "properties": {
    "iso:country":"IT",
    "sg:address":"42025 Cavriago",
    "sg:orig_category":"Fonderie Alluminio",
    "sg:phone":"+39 0522 941325",
    "sg:postcode":"42025",
    "sg:province":"Reggio Nell'Emilia",
    "wof:name":"Eurofond Srl",
    "wof:placetype":"venue"
},
  "geometry": {"coordinates":[10.5461616516,44.713760376],"type":"Point"}
}