{
  "type": "Feature",
  "properties": {
    "addr:full":"72015 Fasano Fasano Brindisi 72015",
    "addr:housenumber":"72015",
    "addr:postcode":"72015",
    "iso:country":"IT",
    "sg:address":"72015 Fasano",
    "sg:city":"Fasano",
    "sg:orig_category":"Ricambi E Componenti Dei Mezzi Di Trasporto",
    "sg:phone":"+39 080 439 1800",
    "sg:postcode":"72015",
    "sg:province":"Brindisi",
    "wof:name":"Pagnelli Luigi",
    "wof:placetype":"venue"
},
  "geometry": {"coordinates":[17.364479,40.835045],"type":"Point"}
}