{
  "type": "Feature",
  "properties": {
    "addr:full":"02100 Rieti Rieti Rieti 02100",
    "addr:postcode":"02100;02100",
    "iso:country":"IT",
    "sg:address":"02100 Rieti",
    "sg:city":"Rieti",
    "sg:classifiers":[
        {
            "category":"Transit Center",
            "subcategory":"Freight",
            "type":"Transportation"
        }
    ],
    "sg:phone":"+39 0746 270763",
    "sg:postcode":"02100",
    "sg:province":"Rieti",
    "sg:tags":[
        "fibre",
        "e",
        "lana",
        "di",
        "roccia",
        "vetro"
    ],
    "wof:name":"Manutenzioni Alto Lazio Snc",
    "wof:placetype":"venue"
},
  "geometry": {"coordinates":[12.8284769058,42.3946495056],"type":"Point"}
}