{
  "type": "Feature",
  "properties": {
    "iso:country":"IT",
    "sg:address":"144, Strada Martiri Della Liberta' Mezzano In 43055 Mezzani",
    "sg:city":"Mezzani",
    "sg:classifiers":[
        {
            "category":"Real Estate",
            "subcategory":"Surveying",
            "type":"Services"
        }
    ],
    "sg:phone":"+39 0521 818618",
    "sg:postcode":"43055",
    "sg:province":"Parma",
    "sg:tags":[
        "equipment",
        "material",
        "good",
        "-",
        "handling"
    ],
    "wof:name":"Barigazzi F.lli S.r.l.",
    "wof:placetype":"venue"
},
  "geometry": {"coordinates":[10.46484,44.910782],"type":"Point"}
}