{
  "type": "Feature",
  "properties": {
    "iso:country":"IT",
    "sg:address":"40064 Ozzano Dell'emilia",
    "sg:classifiers":[
        {
            "category":"Farming",
            "subcategory":"Berry Farm",
            "type":"Manufacturing & Wholesale Goods"
        }
    ],
    "sg:phone":"+39 051 790176",
    "sg:postcode":"40064",
    "sg:province":"Bologna",
    "sg:tags":[
        "vegetable",
        "growing",
        "flower",
        "agriculture"
    ],
    "wof:name":"Arborea Piccola Soc. Coop. R.l.",
    "wof:placetype":"venue"
},
  "geometry": {"coordinates":[11.502067,44.453754],"type":"Point"}
}