{
  "type": "Feature",
  "properties": {
    "addr:full":"80142 Napoli Napoli Napoli 80142",
    "addr:housenumber":"80142",
    "addr:postcode":"80142",
    "iso:country":"IT",
    "sg:address":"80142 Napoli",
    "sg:city":"Napoli",
    "sg:orig_category":"Minuterie Metalliche E Ferramenta. Ricambi E Componenti Dei Mezzi Di Trasporto",
    "sg:phone":"+39 081 734 0184",
    "sg:postcode":"80142",
    "sg:province":"Napoli",
    "wof:name":"Piscopo Antonio",
    "wof:placetype":"venue"
},
  "geometry": {"coordinates":[14.2888631821,40.851524353],"type":"Point"}
}