{
  "type": "Feature",
  "properties": {
    "addr:full":"90146 Palermo Palermo Palermo 90146",
    "addr:postcode":"90146;90146",
    "iso:country":"IT",
    "sg:address":"90146 Palermo",
    "sg:city":"Palermo",
    "sg:orig_category":"Cine-foto-ottica. Articoli Medico-sanitari Ed Ortopedici. Impianti, Attrezzature E Forniture Sanitarie Ed Ospedaliere",
    "sg:phone":"+39 091 670 9895",
    "sg:postcode":"90146",
    "sg:province":"Palermo",
    "wof:name":"Ocular System Srl",
    "wof:placetype":"venue"
},
  "geometry": {"coordinates":[13.342275,38.152767],"type":"Point"}
}