{
  "type": "Feature",
  "properties": {
    "iso:country":"IT",
    "sg:address":"Piazza Repubblica 9/f; Monte San Pietro; 40050",
    "sg:city":"Monte San Pietro",
    "sg:classifiers":[
        {
            "category":"Banks & Credit Unions",
            "subcategory":"Bank",
            "type":"Services"
        }
    ],
    "sg:phone":"+39 051 676 1658",
    "sg:postcode":"40050",
    "sg:province":"Bologna",
    "wof:name":"Rolo Banca 1473 Spa",
    "wof:placetype":"venue"
},
  "geometry": {"coordinates":[11.198373,44.464985],"type":"Point"}
}