{
  "type": "Feature",
  "properties": {
    "iso:country":"IT",
    "sg:address":"Via Delle Industrie 9 20070 San Zenone Al Lambro",
    "sg:city":"San Zenone al Lambro",
    "sg:classifiers":[
        {
            "category":"Banks & Credit Unions",
            "subcategory":"Investment Brokerage",
            "type":"Services"
        }
    ],
    "sg:phone":"+39 02 9887 0353",
    "sg:postcode":"20070",
    "sg:province":"Milano",
    "sg:tags":[
        "product",
        "hair-care"
    ],
    "wof:name":"Cosmec S.p.a.",
    "wof:placetype":"venue"
},
  "geometry": {"coordinates":[9.352048,45.333645],"type":"Point"}
}