{
  "type": "Feature",
  "properties": {
    "iso:country":"IT",
    "sg:address":"10127 Torino",
    "sg:city":"Torino",
    "sg:orig_category":"Serramenti Ed Infissi",
    "sg:phone":"+39 011 619 2626",
    "sg:postcode":"10127",
    "sg:province":"Torino",
    "wof:name":"Al.pi. Serramenti Snc",
    "wof:placetype":"venue"
},
  "geometry": {"coordinates":[7.654738,45.021843],"type":"Point"}
}