{
  "type": "Feature",
  "properties": {
    "addr:full":"20144 Milano Milano Milano 20144",
    "addr:postcode":"20144;20144",
    "iso:country":"IT",
    "sg:address":"20144 Milano",
    "sg:city":"Milano",
    "sg:orig_category":"Minuterie Metalliche E Ferramenta",
    "sg:phone":"+39 02 423 9867",
    "sg:postcode":"20144",
    "sg:province":"Milano",
    "wof:name":"De Angeli Romano Sas",
    "wof:placetype":"venue"
},
  "geometry": {"coordinates":[9.1537399292,45.4555435181],"type":"Point"}
}