{
  "type": "Feature",
  "properties": {
    "iso:country":"IT",
    "sg:address":"87032 Amantea",
    "sg:city":"Amantea",
    "sg:orig_category":"Articoli Da Regalo. Arte Ed Artigianato Artistico. Shopping. Regalistica Aziendale",
    "sg:phone":"+39 0982 425606",
    "sg:postcode":"87032",
    "sg:province":"Cosenza",
    "wof:name":"L'antiquario Di Bruni Eugenio & Paola Guido",
    "wof:placetype":"venue"
},
  "geometry": {"coordinates":[16.238838,39.240166],"type":"Point"}
}