{
  "type": "Feature",
  "properties": {
    "iso:country":"IT",
    "sg:address":"00189 Roma",
    "sg:city":"Roma",
    "sg:orig_category":"Arredo Cucina Ed Elettrodomestici. Elettrodomestici",
    "sg:phone":"+39 06 3326 5755",
    "sg:postcode":"00189",
    "sg:province":"Roma",
    "wof:name":"C.a.t.e. Cassia",
    "wof:placetype":"venue"
},
  "geometry": {"coordinates":[12.470194,41.96566],"type":"Point"}
}