{
  "type": "Feature",
  "properties": {
    "iso:country":"IT",
    "sg:address":"22100 Como",
    "sg:city":"Como",
    "sg:orig_category":"Dolciumi E Gelati",
    "sg:phone":"+39 031 267592",
    "sg:postcode":"22100",
    "sg:province":"Como",
    "wof:name":"Cooperativa Apicomo",
    "wof:placetype":"venue"
},
  "geometry": {"coordinates":[9.090197,45.802731],"type":"Point"}
}