{
  "type": "Feature",
  "properties": {
    "addr:full":"00183 Roma Roma Roma 00183",
    "addr:postcode":"00183;00183",
    "iso:country":"IT",
    "sg:address":"00183 Roma",
    "sg:city":"Roma",
    "sg:orig_category":"Scuole E Servizi Scolastici. Ricerca, Selezione E Formazione Del Personale",
    "sg:phone":"+39 06 7720 9710",
    "sg:postcode":"00183",
    "sg:province":"Roma",
    "wof:name":"A.c. Easy London",
    "wof:placetype":"venue"
},
  "geometry": {"coordinates":[12.508293,41.879524],"type":"Point"}
}