{
  "type": "Feature",
  "properties": {
    "addr:full":"Via Biancamano Principe 04016 Sabaudia Sabaudia Latina 04016",
    "addr:postcode":"04016;04016",
    "addr:street":"Via Biancamano",
    "iso:country":"IT",
    "sg:address":"Via Biancamano Principe 04016 Sabaudia",
    "sg:city":"Sabaudia",
    "sg:classifiers":[
        {
            "category":"Manufacturing",
            "subcategory":"Aerospace",
            "type":"Manufacturing & Wholesale Goods"
        }
    ],
    "sg:phone":"+39 0773 515216",
    "sg:postcode":"04016",
    "sg:province":"Latina",
    "sg:tags":[
        "aeronautic"
    ],
    "wof:name":"S.g. Aviation S.r.l.",
    "wof:placetype":"venue"
},
  "geometry": {"coordinates":[12.9037,41.467598],"type":"Point"}
}