{
  "type": "Feature",
  "properties": {
    "iso:country":"IT",
    "sg:address":"48010 Cotignola",
    "sg:city":"Barbiano",
    "sg:orig_category":"Prodotti E Manufatti In Materie Plastiche. Forniture Per Edilizia E Lavori Pubblici",
    "sg:phone":"+39 0545 78008",
    "sg:postcode":"48010",
    "sg:province":"Ravenna",
    "wof:name":"S.i.r.e.a. Spa",
    "wof:placetype":"venue"
},
  "geometry": {"coordinates":[11.8848667145,44.3798065186],"type":"Point"}
}