{
  "type": "Feature",
  "properties": {
    "iso:country":"IT",
    "sg:address":"38100 Trento",
    "sg:city":"Trento",
    "sg:orig_category":"Arredi Ed Attrezzature Per Uffici. Forniture Per Congressi, Fiere E Manifestazioni",
    "sg:phone":"+39 0461 421091",
    "sg:postcode":"38100",
    "sg:province":"Trento",
    "wof:name":"Arkom Sas",
    "wof:placetype":"venue"
},
  "geometry": {"coordinates":[11.122093,46.084534],"type":"Point"}
}