{
  "type": "Feature",
  "properties": {
    "addr:full":"24062 Costa Volpino Costa Volpino Bergamo 24062",
    "addr:housenumber":"24062;volpino",
    "addr:postcode":"24062",
    "addr:street":"Costa",
    "iso:country":"IT",
    "sg:address":"24062 Costa Volpino",
    "sg:city":"Costa Volpino",
    "sg:orig_category":"Sport - Articoli E Forniture",
    "sg:phone":"+39 035 970314",
    "sg:postcode":"24062",
    "sg:province":"Bergamo",
    "wof:name":"Armeria Sebina Di Romele G.",
    "wof:placetype":"venue"
},
  "geometry": {"coordinates":[10.105975,45.828918],"type":"Point"}
}