{
  "type": "Feature",
  "properties": {
    "iso:country":"IT",
    "sg:address":"4/d, Via Marescalchi 40123 Bologna",
    "sg:city":"Bologna",
    "sg:classifiers":[
        {
            "category":"Wholesale",
            "subcategory":"Drugs",
            "type":"Manufacturing & Wholesale Goods"
        }
    ],
    "sg:phone":"+39 39051220993",
    "sg:postcode":"40123",
    "sg:province":"Bologna",
    "sg:tags":[
        "chemical",
        "pharmaceutical"
    ],
    "wof:name":"Mingardi",
    "wof:placetype":"venue"
},
  "geometry": {"coordinates":[11.346481,44.494221],"type":"Point"}
}