{
  "type": "Feature",
  "properties": {
    "addr:full":"Via Locatelli Antonio 20/a 24121 Bergamo Bergamo Bergamo 24121",
    "addr:housenumber":"20 / a",
    "addr:postcode":"24121;24121",
    "addr:street":"Via Locatelli Antonio",
    "iso:country":"IT",
    "sg:address":"Via Locatelli Antonio 20/a 24121 Bergamo",
    "sg:city":"Bergamo",
    "sg:classifiers":[
        {
            "category":"Manufacturing",
            "subcategory":"Building Materials",
            "type":"Manufacturing & Wholesale Goods"
        }
    ],
    "sg:phone":"+39 035 388 8511",
    "sg:postcode":"24121",
    "sg:province":"Bergamo",
    "sg:tags":[
        "cement"
    ],
    "wof:name":"Cementeria Di Monselice Spa",
    "wof:placetype":"venue"
},
  "geometry": {"coordinates":[9.669227,45.698311],"type":"Point"}
}