{
  "type": "Feature",
  "properties": {
    "iso:country":"IT",
    "sg:address":"Str. Naviglio Alto 26/a 43100 Parma",
    "sg:city":"Parma",
    "sg:classifiers":[
        {
            "category":"Freight",
            "type":"Transportation"
        }
    ],
    "sg:phone":"+39 0521 785647",
    "sg:postcode":"43100",
    "sg:province":"Parma",
    "sg:tags":[
        "lift",
        "appliances",
        "lifting"
    ],
    "sg:website":"www.ece.it",
    "wof:name":"E.c.e. Srl",
    "wof:placetype":"venue"
},
  "geometry": {"coordinates":[10.29492,44.823208],"type":"Point"}
}