{
  "type": "Feature",
  "properties": {
    "addr:full":"20135 Milano Milano Milano 20135",
    "addr:postcode":"20135;20135",
    "iso:country":"IT",
    "sg:address":"20135 Milano",
    "sg:city":"Milano",
    "sg:classifiers":[
        {
            "category":"Health Services",
            "subcategory":"Health Practitioner",
            "type":"Services"
        }
    ],
    "sg:phone":"+39 02 551 2810",
    "sg:postcode":"20135",
    "sg:province":"Milano",
    "sg:tags":[
        "medici"
    ],
    "wof:name":"Vercellini Paolo",
    "wof:placetype":"venue"
},
  "geometry": {"coordinates":[9.2138309479,45.4584121704],"type":"Point"}
}