{
  "type": "Feature",
  "properties": {
    "iso:country":"IT",
    "sg:address":"Contrada S. Giacomo 70015 Noci",
    "sg:city":"Noci",
    "sg:classifiers":[
        {
            "category":"Food & Beverages",
            "subcategory":"Groceries & Convenience Stores",
            "type":"Retail Goods"
        }
    ],
    "sg:phone":"+39 080 497 9657",
    "sg:postcode":"70015",
    "sg:province":"Bari",
    "sg:tags":[
        "drink"
    ],
    "wof:name":"Barsento S.p.a.",
    "wof:placetype":"venue"
},
  "geometry": {"coordinates":[16.869291,41.126053],"type":"Point"}
}