{
  "type": "Feature",
  "properties": {
    "iso:country":"IT",
    "sg:address":"90143 Palermo",
    "sg:city":"Palermo",
    "sg:orig_category":"Macchine Ed Impianti Per Edilizia E Lavori Pubblici. Elettronica Industriale, Prodotti E Apparecchiature",
    "sg:phone":"+39 091 868 5160",
    "sg:postcode":"90143",
    "sg:province":"Palermo",
    "wof:name":"Amato Impianti Srl",
    "wof:placetype":"venue"
},
  "geometry": {"coordinates":[13.349258,38.13863],"type":"Point"}
}