{
  "type": "Feature",
  "properties": {
    "addr:full":"00198 Roma Roma Roma 00198",
    "addr:postcode":"00198;00198",
    "iso:country":"IT",
    "sg:address":"00198 Roma",
    "sg:city":"Roma",
    "sg:orig_category":"Servizi Per Aziende, Manifestazioni E Supporto Agli Scambi Commerciali",
    "sg:phone":"+39 06 6992 0875",
    "sg:postcode":"00198",
    "sg:province":"Roma",
    "sg:website":"http://www.tecnoroma@nexus.it",
    "wof:name":"Tecnoroma Srl",
    "wof:placetype":"venue"
},
  "geometry": {"coordinates":[12.499722,41.918945],"type":"Point"}
}