{
  "type": "Feature",
  "properties": {
    "iso:country":"IT",
    "sg:address":"34170 Gorizia",
    "sg:city":"Gorizia",
    "sg:orig_category":"Acciaierie E Fonderie",
    "sg:phone":"+39 0481 21669",
    "sg:postcode":"34170",
    "sg:province":"Gorizia",
    "wof:name":"Meccanica Isontina",
    "wof:placetype":"venue"
},
  "geometry": {"coordinates":[13.58588,45.912163],"type":"Point"}
}