{
  "type": "Feature",
  "properties": {
    "addr:full":"20149 Milano Milano Milano 20149",
    "addr:postcode":"20149;20149",
    "iso:country":"IT",
    "sg:address":"20149 Milano",
    "sg:city":"Milano",
    "sg:orig_category":"Prodotti Finiti Stampati. Articoli Da Regalo. Arte Ed Artigianato Artistico. Shopping",
    "sg:phone":"+39 02 4800 3995",
    "sg:postcode":"20149",
    "sg:province":"Milano",
    "wof:name":"Nuova Soqquadro Sas Di Savi Pieralberto",
    "wof:placetype":"venue"
},
  "geometry": {"coordinates":[9.154091835,45.4858474731],"type":"Point"}
}