{
  "type": "Feature",
  "properties": {
    "iso:country":"IT",
    "sg:address":"37135 Verona",
    "sg:city":"Verona",
    "sg:orig_category":"Arredamento Negozi E Supermercati",
    "sg:phone":"+39 045 820 4623",
    "sg:postcode":"37135",
    "sg:province":"Verona",
    "sg:website":"http://www.lavetrina.com",
    "wof:name":"La Vetrina Snc",
    "wof:placetype":"venue"
},
  "geometry": {"coordinates":[10.973845,45.408184],"type":"Point"}
}