{
  "type": "Feature",
  "properties": {
    "iso:country":"IT",
    "sg:address":"20064 Gorgonzola",
    "sg:city":"Gorgonzola",
    "sg:classifiers":[
        {
            "category":"Health Services",
            "subcategory":"Health Practitioner",
            "type":"Services"
        }
    ],
    "sg:phone":"+39 02 9530 2231",
    "sg:postcode":"20064",
    "sg:province":"Milano",
    "sg:tags":[
        "medici"
    ],
    "wof:name":"Campagnoli Piera",
    "wof:placetype":"venue"
},
  "geometry": {"coordinates":[9.405286,45.533546],"type":"Point"}
}