{
  "type": "Feature",
  "properties": {
    "iso:country":"IT",
    "sg:address":"1098, Via Della Magliana 00050 Roma",
    "sg:classifiers":[
        {
            "category":"Banks & Credit Unions",
            "subcategory":"Investment Brokerage",
            "type":"Services"
        }
    ],
    "sg:phone":"+39 06 6500 4846",
    "sg:postcode":"00050",
    "sg:province":"Roma",
    "sg:tags":[
        "-",
        "transport",
        "related"
    ],
    "wof:name":"Expotrans M.t.o. S.r.l.",
    "wof:placetype":"venue"
},
  "geometry": {"coordinates":[12.45968,41.858383],"type":"Point"}
}