{
  "type": "Feature",
  "properties": {
    "iso:country":"IT",
    "sg:address":"06038 Spello",
    "sg:city":"Spello",
    "sg:orig_category":"Macchine, Impianti Ed Attrezzature Per Abbigliamento E Pelletterie",
    "sg:phone":"+39 0742 301952",
    "sg:postcode":"06038",
    "sg:province":"Perugia",
    "wof:name":"Tordoni Diego",
    "wof:placetype":"venue"
},
  "geometry": {"coordinates":[12.657628,42.998852],"type":"Point"}
}