{
  "type": "Feature",
  "properties": {
    "iso:country":"IT",
    "sg:address":"Sett. A/25 Centro Commerciale 33170 Pordenone",
    "sg:city":"Pordenone",
    "sg:classifiers":[
        {
            "category":"Professional",
            "subcategory":"Engineering",
            "type":"Services"
        }
    ],
    "sg:phone":"+39 0434 598123",
    "sg:postcode":"33170",
    "sg:province":"Pordenone",
    "sg:tags":[
        "machine",
        "-",
        "mechanical"
    ],
    "sg:website":"http://www.frigoraservice.it:ws_end: :mark:ws:http://www.paginegialle.it/frigoraservice",
    "wof:name":"Frigoraservice Sas",
    "wof:placetype":"venue"
},
  "geometry": {"coordinates":[12.661452,45.956367],"type":"Point"}
}