{
  "type": "Feature",
  "properties": {
    "iso:country":"IT",
    "sg:address":"14057 Isola D'asti",
    "sg:orig_category":"Prodotti E Manufatti In Materie Plastiche. Servizi E Lavori Industria Delle Materie Plastiche",
    "sg:phone":"+39 0141 960046",
    "sg:postcode":"14057",
    "sg:province":"Asti",
    "wof:name":"Elmeg Srl",
    "wof:placetype":"venue"
},
  "geometry": {"coordinates":[8.1145133972,44.7810707092],"type":"Point"}
}