{
  "type": "Feature",
  "properties": {
    "iso:country":"IT",
    "sg:address":"40121 Bologna",
    "sg:city":"Bologna",
    "sg:orig_category":"Scuole E Servizi Scolastici. Centri Di Estetica E Cosmesi E Servizi. Ricerca, Selezione E Formazione Del Personale",
    "sg:phone":"+39 051 269051",
    "sg:postcode":"40121",
    "sg:province":"Bologna",
    "wof:name":"S.e.a. Di Tabo' Anna Pierina E C.",
    "wof:placetype":"venue"
},
  "geometry": {"coordinates":[11.33943,44.497486],"type":"Point"}
}