{
  "type": "Feature",
  "properties": {
    "iso:country":"IT",
    "sg:address":"22070 Capiago Intimiano",
    "sg:city":"Capiago",
    "sg:orig_category":"Disegni Per Tessuti",
    "sg:phone":"+39 031 460000",
    "sg:postcode":"22070",
    "sg:province":"Como",
    "wof:name":"Mosconi Franco",
    "wof:placetype":"venue"
},
  "geometry": {"coordinates":[9.093249,45.807899],"type":"Point"}
}