{
  "type": "Feature",
  "properties": {
    "iso:country":"IT",
    "sg:address":"19, Via Degli Ombrellai 41013 Castelfranco Emilia",
    "sg:city":"Castelfranco Emilia",
    "sg:classifiers":[
        {
            "category":"Shopping",
            "subcategory":"Clothing, Apparel, & Fashions",
            "type":"Retail Goods"
        }
    ],
    "sg:phone":"+39 39059924592",
    "sg:postcode":"41013",
    "sg:province":"Modena",
    "sg:tags":[
        "clothes"
    ],
    "wof:name":"Melotti",
    "wof:placetype":"venue"
},
  "geometry": {"coordinates":[11.067887,44.5868],"type":"Point"}
}