{
  "type": "Feature",
  "properties": {
    "addr:full":"8, V. Galvani - Tezze 36071 Arzignano Arzignano Vicenza 36071",
    "addr:housenumber":"8",
    "addr:postcode":"36071;36071",
    "addr:street":"V. Galvani",
    "iso:country":"IT",
    "sg:address":"8, V. Galvani - Tezze 36071 Arzignano",
    "sg:city":"Arzignano",
    "sg:classifiers":[
        {
            "category":"Utilities",
            "subcategory":"Electric",
            "type":"Services"
        }
    ],
    "sg:phone":"+39 0444 482100",
    "sg:postcode":"36071",
    "sg:province":"Vicenza",
    "sg:tags":[
        "component",
        "electronic"
    ],
    "sg:website":"http://www.seatrasformatori.it",
    "wof:name":"Sea Trasformatori Spa",
    "wof:placetype":"venue"
},
  "geometry": {"coordinates":[11.376091,45.535004],"type":"Point"}
}