{
  "type": "Feature",
  "properties": {
    "iso:country":"IT",
    "sg:address":"51039 Quarrata",
    "sg:city":"Quarrata",
    "sg:orig_category":"Tessuti E Stoffe",
    "sg:phone":"+39 0573 711311",
    "sg:postcode":"51039",
    "sg:province":"Pistoia",
    "wof:name":"Campionatura R.p. Di Bigagli & Bonacci Snc",
    "wof:placetype":"venue"
},
  "geometry": {"coordinates":[10.996065,43.855057],"type":"Point"}
}