{
  "type": "Feature",
  "properties": {
    "iso:country":"IT",
    "sg:address":"Strada Maggiore 46; Bologna; 40125",
    "sg:city":"Bologna",
    "sg:classifiers":[
        {
            "category":"Banks & Credit Unions",
            "subcategory":"Bank",
            "type":"Services"
        }
    ],
    "sg:phone":"+39 051 226326",
    "sg:postcode":"40125",
    "sg:province":"Bologna",
    "wof:name":"Interbanca",
    "wof:placetype":"venue"
},
  "geometry": {"coordinates":[11.352192,44.492054],"type":"Point"}
}