{
  "type": "Feature",
  "properties": {
    "addr:full":"16035 Rapallo Rapallo Genova 16035",
    "addr:postcode":"16035;16035",
    "iso:country":"IT",
    "sg:address":"16035 Rapallo",
    "sg:city":"Rapallo",
    "sg:classifiers":[
        {
            "category":"Restaurant",
            "type":"Food & Drink"
        }
    ],
    "sg:phone":"+39 0185 206036",
    "sg:postcode":"16035",
    "sg:province":"Genova",
    "sg:tags":[
        "auxiliary",
        "entertainment",
        "premises",
        "related",
        "catering",
        "similar",
        "public",
        "restaurants"
    ],
    "sg:website":"http://www.anticacucinagenovese.it",
    "wof:name":"Antica Cucina Genovese",
    "wof:placetype":"venue"
},
  "geometry": {"coordinates":[9.210166,44.35564],"type":"Point"}
}