{
  "type": "Feature",
  "properties": {
    "iso:country":"IT",
    "sg:address":"70038 Terlizzi",
    "sg:city":"Terlizzi",
    "sg:orig_category":"Apparecchiature E Sistemi Per Magazzinaggio E Movimentazione",
    "sg:phone":"+39 080 351 2911",
    "sg:postcode":"70038",
    "sg:province":"Bari",
    "wof:name":"Edil Meccanica",
    "wof:placetype":"venue"
},
  "geometry": {"coordinates":[16.538185,41.117859],"type":"Point"}
}