{
  "type": "Feature",
  "properties": {
    "addr:full":"41035 Massa Finalese Massa finalese Modena 41035",
    "addr:postcode":"41035;41035",
    "addr:street":"Finalese",
    "iso:country":"IT",
    "sg:address":"41035 Massa Finalese",
    "sg:city":"Massa finalese",
    "sg:orig_category":"Prodotti Chimici Di Base",
    "sg:phone":"+39 0535 99007",
    "sg:postcode":"41035",
    "sg:province":"Modena",
    "wof:name":"Padana Sali",
    "wof:placetype":"venue"
},
  "geometry": {"coordinates":[11.2119064331,44.8522758484],"type":"Point"}
}