{
  "type": "Feature",
  "properties": {
    "iso:country":"IT",
    "sg:address":"Cso Cuneo 57 10078 Venaria",
    "sg:classifiers":[
        {
            "category":"Autos & Motor Vehicles",
            "subcategory":"Fuel & Gas Station",
            "type":"Retail Goods"
        }
    ],
    "sg:phone":"+39 011 450 9011",
    "sg:postcode":"10078",
    "sg:province":"Torino",
    "sg:tags":[
        "carburettor"
    ],
    "sg:website":"www.rcacarparts.it",
    "wof:name":"R.c.a. Di F.lli Cossentino S.n.c.",
    "wof:placetype":"venue"
},
  "geometry": {"coordinates":[7.631214,45.116108],"type":"Point"}
}