{
  "type": "Feature",
  "properties": {
    "iso:country":"IT",
    "sg:address":"25017 Lonato",
    "sg:city":"Lonato",
    "sg:orig_category":"Zootecnia E Pesca, Allevamento Piccoli Animali",
    "sg:phone":"+39 030 913 0198",
    "sg:postcode":"25017",
    "sg:province":"Brescia",
    "wof:name":"Anselmi Giuseppe",
    "wof:placetype":"venue"
},
  "geometry": {"coordinates":[10.19345,45.552979],"type":"Point"}
}