{
  "type": "Feature",
  "properties": {
    "addr:full":"72100 Brindisi Brindisi Brindisi 72100",
    "addr:postcode":"72100;72100",
    "iso:country":"IT",
    "sg:address":"72100 Brindisi",
    "sg:city":"Brindisi",
    "sg:orig_category":"Servizi E Lavori Per Arredamento E Industria Del Legno. Servizi E Lavori Per Edilizia E Lavori Pubblici. Arte Ed Artigianato Artistico",
    "sg:phone":"+39 0831 560293",
    "sg:postcode":"72100",
    "sg:province":"Brindisi",
    "wof:name":"La Piroga",
    "wof:placetype":"venue"
},
  "geometry": {"coordinates":[17.927864,40.630821],"type":"Point"}
}