{
  "type": "Feature",
  "properties": {
    "addr:full":"70, Via Pontarola 35011 Campodarsego Campodarsego Padova 35011",
    "addr:postcode":"35011;35011",
    "addr:street":"Via Pontarola",
    "iso:country":"IT",
    "sg:address":"70, Via Pontarola 35011 Campodarsego",
    "sg:city":"Campodarsego",
    "sg:classifiers":[
        {
            "category":"Wholesale",
            "subcategory":"Machinery & Supplies",
            "type":"Manufacturing & Wholesale Goods"
        }
    ],
    "sg:phone":"+39 049 920 0320",
    "sg:postcode":"35011",
    "sg:province":"Padova",
    "sg:tags":[
        "equipment",
        "precision"
    ],
    "wof:name":"El.mo. (s.p.a.)",
    "wof:placetype":"venue"
},
  "geometry": {"coordinates":[11.9157180786,45.4793930054],"type":"Point"}
}