{
  "type": "Feature",
  "properties": {
    "addr:full":"Contrada Quartarella 97015 Modica Modica Ragusa 97015",
    "addr:postcode":"97015;97015",
    "addr:street":"Contrada Quartarella",
    "iso:country":"IT",
    "sg:address":"Contrada Quartarella 97015 Modica",
    "sg:city":"Modica",
    "sg:classifiers":[
        {
            "category":"Farming",
            "subcategory":"Livestock Farm",
            "type":"Manufacturing & Wholesale Goods"
        }
    ],
    "sg:phone":"+39 0932 903733",
    "sg:postcode":"97015",
    "sg:province":"Ragusa",
    "sg:tags":[
        "agriculture"
    ],
    "wof:name":"Azienda Agricola Avicarne (s.p.a.)",
    "wof:placetype":"venue"
},
  "geometry": {"coordinates":[14.76939,36.818447],"type":"Point"}
}