{
  "type": "Feature",
  "properties": {
    "iso:country":"IT",
    "sg:address":"Corso Aldo Moro 126; Gravina; 70024",
    "sg:classifiers":[
        {
            "category":"Banks & Credit Unions",
            "subcategory":"Bank",
            "type":"Services"
        }
    ],
    "sg:phone":"+39 080 696 7821",
    "sg:postcode":"70024",
    "sg:province":"Bari",
    "wof:name":"Banco Di Napoli Spa",
    "wof:placetype":"venue"
},
  "geometry": {"coordinates":[16.417953,40.822533],"type":"Point"}
}