{
  "type": "Feature",
  "properties": {
    "iso:country":"IT",
    "sg:address":"37049 Villa Bartolomea",
    "sg:city":"Villa Bartolomea",
    "sg:orig_category":"Trattamenti Termici E Superficiali Metalli, Galvanotecnica",
    "sg:phone":"+39 0442 91734",
    "sg:postcode":"37049",
    "sg:province":"Verona",
    "sg:website":"http://www.bazzanivalentino.com",
    "wof:name":"Bazzani Valentino",
    "wof:placetype":"venue"
},
  "geometry": {"coordinates":[11.34414,45.120651],"type":"Point"}
}