{
  "type": "Feature",
  "properties": {
    "iso:country":"IT",
    "sg:address":"28100 Novara",
    "sg:city":"Novara",
    "sg:orig_category":"Servizi Di Magazzinaggio E Movimentazione",
    "sg:phone":"+39 0321 611023",
    "sg:postcode":"28100",
    "sg:province":"Novara",
    "wof:name":"Devecchi Romano",
    "wof:placetype":"venue"
},
  "geometry": {"coordinates":[8.617283,45.43998],"type":"Point"}
}