{
  "type": "Feature",
  "properties": {
    "iso:country":"IT",
    "sg:address":"06083 Bastia",
    "sg:city":"Bastia",
    "sg:orig_category":"Accessori Moda D'abbigliamento. Shopping",
    "sg:phone":"+39 075 801 0738",
    "sg:postcode":"06083",
    "sg:province":"Perugia",
    "wof:name":"Lestini Elisa Punto Art",
    "wof:placetype":"venue"
},
  "geometry": {"coordinates":[12.550882,43.067913],"type":"Point"}
}