{
  "type": "Feature",
  "properties": {
    "iso:country":"IT",
    "sg:address":"35011 Campodarsego",
    "sg:city":"Campodarsego",
    "sg:classifiers":[
        {
            "category":"Professional",
            "subcategory":"Employment Agencies",
            "type":"Services"
        }
    ],
    "sg:phone":"+39 049 920 0555",
    "sg:postcode":"35011",
    "sg:province":"Padova",
    "sg:tags":[
        "activities",
        "commercial",
        "equipment",
        "artisan",
        "supplies",
        "furniture",
        "accommodation",
        "furnishing"
    ],
    "wof:name":"Transarredi Di Meneghello Daniele",
    "wof:placetype":"venue"
},
  "geometry": {"coordinates":[11.913769722,45.4995536804],"type":"Point"}
}