{
  "type": "Feature",
  "properties": {
    "addr:full":"95126 Catania Catania Catania 95126",
    "addr:postcode":"95126;95126",
    "iso:country":"IT",
    "sg:address":"95126 Catania",
    "sg:city":"Catania",
    "sg:orig_category":"Pubblicita', Marketing E Comunicazione",
    "sg:phone":"+39 095 722 3075",
    "sg:postcode":"95126",
    "sg:province":"Catania",
    "wof:name":"Newprint Srl",
    "wof:placetype":"venue"
},
  "geometry": {"coordinates":[15.104016304,37.519947052],"type":"Point"}
}