{
  "type": "Feature",
  "properties": {
    "iso:country":"IT",
    "sg:address":"10153 Torino",
    "sg:city":"Torino",
    "sg:orig_category":"Lenti A Contatto E Per Occhiali - Produzione E Ingrosso",
    "sg:phone":"+39 011 817 7274",
    "sg:postcode":"10153",
    "sg:province":"Torino",
    "sg:website":"http://www.tatoni.it",
    "wof:name":"Ottico Tatoni",
    "wof:placetype":"venue"
},
  "geometry": {"coordinates":[7.707769,45.069954],"type":"Point"}
}