{
  "type": "Feature",
  "properties": {
    "addr:full":"C.so Colombo 1a 15016 Cassine Cassine Alessandria 15016",
    "addr:housenumber":"1a",
    "addr:postcode":"15016;15016",
    "addr:street":"C.So Colombo",
    "iso:country":"IT",
    "sg:address":"C.so Colombo 1a 15016 Cassine",
    "sg:city":"Cassine",
    "sg:classifiers":[
        {
            "category":"Health Services",
            "subcategory":"Hospital",
            "type":"Services"
        }
    ],
    "sg:phone":"+39 0144 714988",
    "sg:postcode":"15016",
    "sg:province":"Alessandria",
    "sg:tags":[
        "capsule",
        "cap",
        "bottle"
    ],
    "wof:name":"Fic Fabbrica Italiana Capsule Srl",
    "wof:placetype":"venue"
},
  "geometry": {"coordinates":[8.529243,44.751301],"type":"Point"}
}