{
  "type": "Feature",
  "properties": {
    "iso:country":"IT",
    "sg:address":"20121 Milano",
    "sg:city":"Milano",
    "sg:orig_category":"Servizi Culturali E Per Lo Spettacolo. Servizi Al Turismo. Acqua, Luce, Gas E Societa' Di Esercizio Pubblico",
    "sg:phone":"+39 02 8698 4840",
    "sg:postcode":"20121",
    "sg:province":"Milano",
    "wof:name":"Compagnia Stabile Del Teatro Filodrammatici Soc.coop.",
    "wof:placetype":"venue"
},
  "geometry": {"coordinates":[9.188611,45.467304],"type":"Point"}
}