{
  "type": "Feature",
  "properties": {
    "iso:country":"IT",
    "sg:address":"Via Ponteselice 81100 Caserta",
    "sg:city":"Caserta",
    "sg:classifiers":[
        {
            "category":"Wholesale",
            "subcategory":"Drugs",
            "type":"Manufacturing & Wholesale Goods"
        }
    ],
    "sg:phone":"+39 0823 356772",
    "sg:postcode":"81100",
    "sg:province":"Caserta",
    "sg:tags":[
        "chemical",
        "pharmaceutical"
    ],
    "wof:name":"Ipco Sud Srl",
    "wof:placetype":"venue"
},
  "geometry": {"coordinates":[14.295203,41.049862],"type":"Point"}
}