{
  "type": "Feature",
  "properties": {
    "addr:full":"12012 Boves Boves Cuneo 12012",
    "addr:postcode":"12012;12012",
    "iso:country":"IT",
    "sg:address":"12012 Boves",
    "sg:city":"Boves",
    "sg:orig_category":"Vetrerie Artistiche - Produzione E Ingrosso",
    "sg:phone":"+39 0171 388289",
    "sg:postcode":"12012",
    "sg:province":"Cuneo",
    "wof:name":"Vetraria Di Giuliano C. & C. Sdf",
    "wof:placetype":"venue"
},
  "geometry": {"coordinates":[7.575434,44.334465],"type":"Point"}
}