{
  "type": "Feature",
  "properties": {
    "iso:country":"IT",
    "sg:address":"Via Romagna 35 20093 Cologno Monzese",
    "sg:city":"Cologno Monzese",
    "sg:orig_category":"Magnets, Permanent",
    "sg:phone":"+39 02 2539 1445",
    "sg:postcode":"20093",
    "sg:province":"Milano",
    "sg:website":"www.calamit.com",
    "wof:name":"Calamit Srl",
    "wof:placetype":"venue"
},
  "geometry": {"coordinates":[9.269949,45.530487],"type":"Point"}
}