{
  "type": "Feature",
  "properties": {
    "iso:country":"IT",
    "sg:address":"Via Alba 84 33100 Udine",
    "sg:city":"Udine",
    "sg:classifiers":[
        {
            "category":"Health Services",
            "subcategory":"Nursing And Care Facility",
            "type":"Services"
        }
    ],
    "sg:phone":"+39 0432 480306",
    "sg:postcode":"33100",
    "sg:province":"Udine",
    "sg:tags":[
        "fa\u00e7ades",
        "treatment",
        "hydrophobic"
    ],
    "sg:website":"www.pozzi-martinenghi.com",
    "wof:name":"Pozzi & Martinenghi Srl",
    "wof:placetype":"venue"
},
  "geometry": {"coordinates":[13.242167,46.090614],"type":"Point"}
}