{
  "type": "Feature",
  "properties": {
    "iso:country":"IT",
    "sg:address":"24010 Sedrina",
    "sg:city":"Sedrina",
    "sg:orig_category":"Biancheria, Telerie E Coperte. Arredo Camera Letto E Complementi",
    "sg:phone":"+39 035 638092",
    "sg:postcode":"24010",
    "sg:province":"Bergamo",
    "wof:name":"Confezioni A & G Snc",
    "wof:placetype":"venue"
},
  "geometry": {"coordinates":[9.612643,45.770237],"type":"Point"}
}