{
  "type": "Feature",
  "properties": {
    "iso:country":"IT",
    "sg:address":"98057 Milazzo",
    "sg:city":"Milazzo",
    "sg:orig_category":"Alberghi",
    "sg:phone":"+39 090 928 1450",
    "sg:postcode":"98057",
    "sg:province":"Messina",
    "wof:name":"Lisa Santo & Francesco Snc",
    "wof:placetype":"venue"
},
  "geometry": {"coordinates":[15.238754,38.217583],"type":"Point"}
}