{
  "type": "Feature",
  "properties": {
    "iso:country":"IT",
    "sg:address":"73016 S. Cesario Di Lecce",
    "sg:orig_category":"Imprese Edili",
    "sg:phone":"+39 0832 205496",
    "sg:postcode":"73016",
    "sg:province":"Lecce",
    "sg:website":"http://www.lecostruzioni.it",
    "wof:name":"Leo Costruzioni Srl",
    "wof:placetype":"venue"
},
  "geometry": {"coordinates":[18.187954,40.353127],"type":"Point"}
}