{
  "type": "Feature",
  "properties": {
    "addr:full":"31033 Castelfranco Veneto Castelfranco Veneto Treviso 31033",
    "addr:postcode":"31033;31033",
    "iso:country":"IT",
    "sg:address":"31033 Castelfranco Veneto",
    "sg:city":"Castelfranco Veneto",
    "sg:orig_category":"Associazioni E Federazioni Sportive",
    "sg:phone":"+39 0423 490749",
    "sg:postcode":"31033",
    "sg:province":"Treviso",
    "sg:website":"http://www.fardef.it",
    "wof:name":"Fardef Piscine Srl",
    "wof:placetype":"venue"
},
  "geometry": {"coordinates":[11.936238,45.669506],"type":"Point"}
}