{
  "type": "Feature",
  "properties": {
    "addr:full":"33030 Maiano Udine 33030",
    "addr:postcode":"33030;33030",
    "iso:country":"IT",
    "sg:address":"33030 Maiano",
    "sg:orig_category":"Automazione E Macchine Per Ufficio. Servizi Ausiliari Di Certificati, Riproduzioni, Disegni E Foto",
    "sg:phone":"+39 0432 948568",
    "sg:postcode":"33030",
    "sg:province":"Udine",
    "wof:name":"Idea (soc.coop.r.l.)",
    "wof:placetype":"venue"
},
  "geometry": {"coordinates":[12.985049,46.173153],"type":"Point"}
}