{
  "type": "Feature",
  "properties": {
    "addr:full":"Borgata Macchia 4; Ferrandina; 75013 Ferrandina Matera 75013",
    "addr:housenumber":"4",
    "addr:postcode":"75013;75013",
    "addr:street":"Borgata Macchia;Ferrandina",
    "iso:country":"IT",
    "sg:address":"Borgata Macchia 4; Ferrandina; 75013",
    "sg:city":"Ferrandina",
    "sg:classifiers":[
        {
            "category":"Banks & Credit Unions",
            "subcategory":"Bank",
            "type":"Services"
        }
    ],
    "sg:phone":"+39 0835 757007",
    "sg:postcode":"75013",
    "sg:province":"Matera",
    "wof:name":"Banco Di Napoli Spa",
    "wof:placetype":"venue"
},
  "geometry": {"coordinates":[16.506327,40.466045],"type":"Point"}
}