{
  "type": "Feature",
  "properties": {
    "iso:country":"IT",
    "sg:address":"20050 Verano Brianza",
    "sg:city":"Verano Brianza",
    "sg:orig_category":"Vetro: Prodotti E Lavorazioni",
    "sg:phone":"+39 036 280 5282",
    "sg:postcode":"20050",
    "sg:province":"Milano",
    "wof:name":"Solarline Srl",
    "wof:placetype":"venue"
},
  "geometry": {"coordinates":[9.226361,45.681465],"type":"Point"}
}