{
  "type": "Feature",
  "properties": {
    "iso:country":"IT",
    "sg:address":"Via Dell' Artigianato 20 35044 Montagnana",
    "sg:city":"Montagnana",
    "sg:classifiers":[
        {
            "category":"Manufacturing",
            "subcategory":"Wood Products",
            "type":"Manufacturing & Wholesale Goods"
        }
    ],
    "sg:phone":"+39 0429 82946",
    "sg:postcode":"35044",
    "sg:province":"Padova",
    "sg:tags":[
        "semi-finished"
    ],
    "wof:name":"Italmobili S.r.l.",
    "wof:placetype":"venue"
},
  "geometry": {"coordinates":[11.497784,45.22596],"type":"Point"}
}