{
  "type": "Feature",
  "properties": {
    "addr:full":"6, Via Gaetano Donizetti 24050 Lurano Lurano Bergamo 24050",
    "addr:postcode":"24050;24050",
    "addr:street":"Via Gaetano Donizetti",
    "iso:country":"IT",
    "sg:address":"6, Via Gaetano Donizetti 24050 Lurano",
    "sg:city":"Lurano",
    "sg:classifiers":[
        {
            "category":"Shopping",
            "subcategory":"Crafts & Fabrics",
            "type":"Retail Goods"
        }
    ],
    "sg:phone":"+39 39035800095",
    "sg:postcode":"24050",
    "sg:province":"Bergamo",
    "sg:tags":[
        "linen"
    ],
    "wof:name":"Tisca Italia (s.r.l.)",
    "wof:placetype":"venue"
},
  "geometry": {"coordinates":[9.640745163,45.5684242249],"type":"Point"}
}