{
  "type": "Feature",
  "properties": {
    "addr:full":"28921 Verbania Verbania Verbano-Cusio-Ossola 28921",
    "addr:postcode":"28921;28921",
    "iso:country":"IT",
    "sg:address":"28921 Verbania",
    "sg:city":"Verbania",
    "sg:orig_category":"Macchine, Impianti Ed Attrezzature Per Agricoltura E Zootecnia",
    "sg:phone":"+39 0323 53336",
    "sg:postcode":"28921",
    "sg:province":"Verbano-Cusio-Ossola",
    "wof:name":"Metalcarpenteria Dei F.lli Siviero Silvano & Fabio Snc",
    "wof:placetype":"venue"
},
  "geometry": {"coordinates":[8.560012,45.937172],"type":"Point"}
}