{
  "type": "Feature",
  "properties": {
    "iso:country":"IT",
    "sg:address":"20080 Albairate",
    "sg:city":"Albairate",
    "sg:orig_category":"Macchine Utensili E Impianti",
    "sg:phone":"+39 02 9492 0082",
    "sg:postcode":"20080",
    "sg:province":"Milano",
    "wof:name":"Elvinox S.r.l.",
    "wof:placetype":"venue"
},
  "geometry": {"coordinates":[8.935589,45.419605],"type":"Point"}
}