{
  "type": "Feature",
  "properties": {
    "iso:country":"IT",
    "sg:address":"Via V. Alfieri 1/a-1/b 47030 San Mauro Pascoli",
    "sg:city":"San Mauro Pascoli",
    "sg:classifiers":[
        {
            "category":"Banks & Credit Unions",
            "subcategory":"Investment Brokerage",
            "type":"Services"
        }
    ],
    "sg:phone":"+39 0541 933235",
    "sg:postcode":"47030",
    "sg:province":"Forl\u00ec-Cesena",
    "sg:tags":[
        "embroidery",
        "hand"
    ],
    "sg:website":"www.puntopiu.com",
    "wof:name":"Punto Piu' Snc Di Paola Quadrelli & C.",
    "wof:placetype":"venue"
},
  "geometry": {"coordinates":[11.980461,43.994766],"type":"Point"}
}