{
  "type": "Feature",
  "properties": {
    "iso:country":"IT",
    "sg:address":"35, Via Metella Nuova 64027 Sant'omero",
    "sg:classifiers":[
        {
            "category":"Shopping",
            "subcategory":"Clothing, Apparel, & Fashions",
            "type":"Retail Goods"
        }
    ],
    "sg:phone":"+39 0861 887596",
    "sg:postcode":"64027",
    "sg:province":"Teramo",
    "sg:tags":[
        "clothes"
    ],
    "wof:name":"Naax Srl",
    "wof:placetype":"venue"
},
  "geometry": {"coordinates":[13.795177,42.797493],"type":"Point"}
}