{
  "type": "Feature",
  "properties": {
    "iso:country":"IT",
    "sg:address":"Piazza Del Municipio 11; Pieve Di Cadore; 32044",
    "sg:city":"Pieve di Cadore",
    "sg:classifiers":[
        {
            "category":"Banks & Credit Unions",
            "subcategory":"Bank",
            "type":"Services"
        }
    ],
    "sg:phone":"+39 0435 31647",
    "sg:postcode":"32044",
    "sg:province":"Belluno",
    "wof:name":"Rolo Banca 1473 Spa",
    "wof:placetype":"venue"
},
  "geometry": {"coordinates":[12.374811,46.429344],"type":"Point"}
}