{
  "type": "Feature",
  "properties": {
    "addr:full":"55049 Viareggio Viareggio Lucca 55049",
    "addr:postcode":"55049;55049",
    "iso:country":"IT",
    "sg:address":"55049 Viareggio",
    "sg:city":"Viareggio",
    "sg:orig_category":"Petroli, Gas E Combustibili",
    "sg:phone":"+39 0584 389802",
    "sg:postcode":"55049",
    "sg:province":"Lucca",
    "wof:name":"Colapietro Lubrificanti",
    "wof:placetype":"venue"
},
  "geometry": {"coordinates":[10.2466917038,43.8631477356],"type":"Point"}
}