{
  "type": "Feature",
  "properties": {
    "iso:country":"IT",
    "sg:address":"35019 Tombolo",
    "sg:city":"Onara",
    "sg:orig_category":"Cartotecnica E Servizi. Articoli Per Imballaggio E Confezionamento",
    "sg:phone":"+39 049 599 3025",
    "sg:postcode":"35019",
    "sg:province":"Padova",
    "wof:name":"Scatolificio I.v.i. Di Andretta Giuseppina & C. Snc",
    "wof:placetype":"venue"
},
  "geometry": {"coordinates":[11.817221,45.632435],"type":"Point"}
}