{
  "type": "Feature",
  "properties": {
    "iso:country":"IT",
    "sg:address":"22063 Cantu'",
    "sg:orig_category":"Articoli Orientali",
    "sg:phone":"+39 031 700577",
    "sg:postcode":"22063",
    "sg:province":"Como",
    "wof:name":"Incoll - Industrie Collegate Lombarde Srl",
    "wof:placetype":"venue"
},
  "geometry": {"coordinates":[9.129192,45.735043],"type":"Point"}
}