{
  "type": "Feature",
  "properties": {
    "iso:country":"IT",
    "sg:address":"37050 Belfiore",
    "sg:city":"Belfiore",
    "sg:orig_category":"Macchine, Impianti Ed Attrezzature Per Agricoltura E Zootecnia. Macchine, Strumenti Ed Apparecchi Per Attivita' Industriali",
    "sg:phone":"+39 045 764 0518",
    "sg:postcode":"37050",
    "sg:province":"Verona",
    "wof:name":"Genesini Renzo",
    "wof:placetype":"venue"
},
  "geometry": {"coordinates":[10.980285,45.415653],"type":"Point"}
}