{
  "type": "Feature",
  "properties": {
    "addr:full":"15076 Ovada Ovada Alessandria 15076",
    "addr:postcode":"15076;15076",
    "iso:country":"IT",
    "sg:address":"15076 Ovada",
    "sg:city":"Ovada",
    "sg:orig_category":"Servizi E Lavori Per Arredamento E Industria Del Legno. Vetro: Prodotti E Lavorazioni",
    "sg:phone":"+39 0143 80107",
    "sg:postcode":"15076",
    "sg:province":"Alessandria",
    "sg:website":"http://www.cristalvetro.it",
    "wof:name":"Cristalvetro Di Parodi Ugo",
    "wof:placetype":"venue"
},
  "geometry": {"coordinates":[8.627063,44.646046],"type":"Point"}
}