{
  "type": "Feature",
  "properties": {
    "iso:country":"IT",
    "sg:address":"58100 Grosseto",
    "sg:city":"Grosseto",
    "sg:orig_category":"Elettrotecnica Industriale, Prodotti E Apparecchiature",
    "sg:phone":"+39 0564 451513",
    "sg:postcode":"58100",
    "sg:province":"Grosseto",
    "wof:name":"Bemedo Srl",
    "wof:placetype":"venue"
},
  "geometry": {"coordinates":[11.0966,42.788475],"type":"Point"}
}