{
  "type": "Feature",
  "properties": {
    "iso:country":"IT",
    "sg:address":"Strada Torino 23 10092 Beinasco",
    "sg:city":"Beinasco",
    "sg:classifiers":[
        {
            "category":"Manufacturing",
            "subcategory":"Metals",
            "type":"Manufacturing & Wholesale Goods"
        }
    ],
    "sg:phone":"+39 011 397 2600",
    "sg:postcode":"10092",
    "sg:province":"Torino",
    "sg:tags":[
        "profile"
    ],
    "wof:name":"Aries Industrie Spa",
    "wof:placetype":"venue"
},
  "geometry": {"coordinates":[7.5879244804,45.0229530334],"type":"Point"}
}