{
  "type": "Feature",
  "properties": {
    "iso:country":"IT",
    "sg:address":"53016 Murlo",
    "sg:city":"Casciano",
    "sg:orig_category":"Agriturismo",
    "sg:phone":"+39 0577 817667",
    "sg:postcode":"53016",
    "sg:province":"Siena",
    "sg:website":"http://www.hotelmirella.com",
    "wof:name":"Albergo Ristorante Mirella",
    "wof:placetype":"venue"
},
  "geometry": {"coordinates":[11.287666,43.321426],"type":"Point"}
}