{
  "type": "Feature",
  "properties": {
    "addr:full":"90011 Bagheria Bagheria Palermo 90011",
    "addr:postcode":"90011;90011",
    "iso:country":"IT",
    "sg:address":"90011 Bagheria",
    "sg:city":"Bagheria",
    "sg:orig_category":"Elettronica Professionale E Di Consumo. Tempo Libero - Articoli E Forniture",
    "sg:phone":"+39 091 968370",
    "sg:postcode":"90011",
    "sg:province":"Palermo",
    "wof:name":"Mi.to. Snc",
    "wof:placetype":"venue"
},
  "geometry": {"coordinates":[13.501579,38.082882],"type":"Point"}
}