{
  "type": "Feature",
  "properties": {
    "addr:full":"Via Nazionale Emilia 1938 47822 Santarcangelo Di Romagna Santarcangelo di Romagna Rimini 47822",
    "addr:housenumber":"1938",
    "addr:postcode":"47822;47822",
    "addr:street":"Via Nazionale Emilia",
    "iso:country":"IT",
    "sg:address":"Via Nazionale Emilia 1938 47822 Santarcangelo Di Romagna",
    "sg:city":"Santarcangelo di Romagna",
    "sg:classifiers":[
        {
            "category":"Professional",
            "subcategory":"Accounting & Tax Preparation",
            "type":"Services"
        }
    ],
    "sg:phone":"+39 0541 350511",
    "sg:postcode":"47822",
    "sg:province":"Rimini",
    "sg:tags":[
        "filling",
        "balance"
    ],
    "sg:website":"www.paglierani.com",
    "wof:name":"Paglierani Sas",
    "wof:placetype":"venue"
},
  "geometry": {"coordinates":[12.5662565231,44.0607795715],"type":"Point"}
}