{
  "type": "Feature",
  "properties": {
    "iso:country":"IT",
    "sg:address":"09122 Cagliari",
    "sg:city":"Cagliari",
    "sg:orig_category":"Carta, Cartone E Prodotti Primari",
    "sg:phone":"+39 070 291843",
    "sg:postcode":"09122",
    "sg:province":"Cagliari",
    "wof:name":"Eredi Schirru Piero Sdf",
    "wof:placetype":"venue"
},
  "geometry": {"coordinates":[9.09761,39.228039],"type":"Point"}
}