{
  "type": "Feature",
  "properties": {
    "addr:full":"21, Via Giorgione 30035 Mirano Mirano Venezia 30035",
    "addr:postcode":"30035;30035",
    "addr:street":"Via Giorgione",
    "iso:country":"IT",
    "sg:address":"21, Via Giorgione 30035 Mirano",
    "sg:city":"Mirano",
    "sg:classifiers":[
        {
            "category":"Shopping",
            "subcategory":"Clothing, Apparel, & Fashions",
            "type":"Retail Goods"
        }
    ],
    "sg:phone":"+39 39041431030",
    "sg:postcode":"30035",
    "sg:province":"Venezia",
    "sg:tags":[
        "clothes"
    ],
    "wof:name":"Masiero Confezioni (s.n.c.)",
    "wof:placetype":"venue"
},
  "geometry": {"coordinates":[12.1559104919,45.5224761963],"type":"Point"}
}