{
  "type": "Feature",
  "properties": {
    "addr:full":"34132 Trieste Trieste Trieste 34132",
    "addr:postcode":"34132;34132",
    "iso:country":"IT",
    "sg:address":"34132 Trieste",
    "sg:city":"Trieste",
    "sg:orig_category":"Legno E Semilavorati",
    "sg:phone":"+39 040 348 0437",
    "sg:postcode":"34132",
    "sg:province":"Trieste",
    "wof:name":"Uniles Di Paolo Pockaj",
    "wof:placetype":"venue"
},
  "geometry": {"coordinates":[13.774733,45.655975],"type":"Point"}
}