{
  "type": "Feature",
  "properties": {
    "addr:full":"21013 Gallarate Gallarate Varese 21013",
    "addr:postcode":"21013;21013",
    "iso:country":"IT",
    "sg:address":"21013 Gallarate",
    "sg:city":"Gallarate",
    "sg:orig_category":"Abbigliamento Esterno, Maglierie E Pelliccerie. Forniture Per Il Settore Dello Spettacolo",
    "sg:phone":"+39 0331 245613",
    "sg:postcode":"21013",
    "sg:province":"Varese",
    "wof:name":"Peroni Spa",
    "wof:placetype":"venue"
},
  "geometry": {"coordinates":[8.799276,45.664864],"type":"Point"}
}