{
  "type": "Feature",
  "properties": {
    "iso:country":"IT",
    "sg:address":"67054 Civitella Roveto",
    "sg:orig_category":"Vetri E Cristalli Temperati E Di Sicurezza",
    "sg:phone":"+39 0863 977977",
    "sg:postcode":"67054",
    "sg:province":"L'Aquila",
    "wof:name":"Liri Glass Snc Di Maurizio Persia",
    "wof:placetype":"venue"
},
  "geometry": {"coordinates":[13.439617,41.925434],"type":"Point"}
}