{
  "type": "Feature",
  "properties": {
    "addr:full":"41100 Modena Modena Modena 41100",
    "addr:postcode":"41100;41100",
    "iso:country":"IT",
    "sg:address":"41100 Modena",
    "sg:city":"Modena",
    "sg:orig_category":"Materiali E Componenti Elettronici",
    "sg:phone":"+39 059 315554",
    "sg:postcode":"41100",
    "sg:province":"Modena",
    "wof:name":"Ceruti Luigi",
    "wof:placetype":"venue"
},
  "geometry": {"coordinates":[10.93433,44.669491],"type":"Point"}
}