{
  "type": "Feature",
  "properties": {
    "iso:country":"IT",
    "sg:address":"Via Martiri D'ungheria 4 63014 Montegranaro",
    "sg:city":"Montegranaro",
    "sg:classifiers":[
        {
            "category":"Autos & Motor Vehicles",
            "subcategory":"Fuel & Gas Station",
            "type":"Retail Goods"
        }
    ],
    "sg:phone":"+39 0734 893120",
    "sg:postcode":"63014",
    "sg:province":"Ascoli Piceno",
    "sg:tags":[
        "punch",
        "hollow"
    ],
    "wof:name":"Fustellificio Alpha Di Sebastiani F Ranco & C. Snc",
    "wof:placetype":"venue"
},
  "geometry": {"coordinates":[13.635702,43.233509],"type":"Point"}
}