{
  "type": "Feature",
  "properties": {
    "iso:country":"IT",
    "sg:address":"50/52, Via Cilea 20090 Trezzano Sul Naviglio",
    "sg:city":"Trezzano sul Naviglio",
    "sg:classifiers":[
        {
            "category":"Manufacturing",
            "subcategory":"Printing",
            "type":"Manufacturing & Wholesale Goods"
        }
    ],
    "sg:phone":"+39 39024455321",
    "sg:postcode":"20090",
    "sg:province":"Milano",
    "sg:tags":[
        "publishing"
    ],
    "wof:name":"Lithotris S.r.l.",
    "wof:placetype":"venue"
},
  "geometry": {"coordinates":[9.0480251312,45.4133682251],"type":"Point"}
}