{
  "type": "Feature",
  "properties": {
    "iso:country":"IT",
    "sg:address":"Via Campiglione 63023 Fermo",
    "sg:city":"Campiglione",
    "sg:classifiers":[
        {
            "category":"Personal",
            "subcategory":"Shoe Repair & Shine",
            "type":"Services"
        }
    ],
    "sg:phone":"+39 0734 628381",
    "sg:postcode":"63023",
    "sg:province":"Ascoli Piceno",
    "sg:tags":[
        "leather"
    ],
    "wof:name":"Stamplast (s.r.l.)",
    "wof:placetype":"venue"
},
  "geometry": {"coordinates":[13.574977,42.8554],"type":"Point"}
}