{
  "type": "Feature",
  "properties": {
    "iso:country":"IT",
    "sg:address":"37139 Verona",
    "sg:city":"Verona",
    "sg:orig_category":"Non-classified Establishments",
    "sg:phone":"+39 045 851 0500",
    "sg:postcode":"37139",
    "sg:province":"Verona",
    "wof:name":"Arquati Verona Snc",
    "wof:placetype":"venue"
},
  "geometry": {"coordinates":[10.90323,45.439056],"type":"Point"}
}