{
  "type": "Feature",
  "properties": {
    "iso:country":"IT",
    "sg:address":"10149 Torino",
    "sg:city":"Torino",
    "sg:orig_category":"Servizi E Lavori Per Edilizia E Lavori Pubblici",
    "sg:phone":"+39 011 216 7546",
    "sg:postcode":"10149",
    "sg:province":"Torino",
    "wof:name":"Bianco Snc Di Bianco Giuseppe & C.",
    "wof:placetype":"venue"
},
  "geometry": {"coordinates":[7.674044,45.093491],"type":"Point"}
}