{
  "type": "Feature",
  "properties": {
    "iso:country":"IT",
    "sg:address":"18, Corso Mameli Goffredo 28921 Verbania",
    "sg:city":"Verbania",
    "sg:classifiers":[
        {
            "category":"Professional",
            "subcategory":"Business Services",
            "type":"Services"
        }
    ],
    "sg:phone":"+39 0323 402446",
    "sg:postcode":"28921",
    "sg:province":"Verbano-Cusio-Ossola",
    "sg:tags":[
        "advice"
    ],
    "wof:name":"Unione Industriale Del Verbano Cusio E Ossola",
    "wof:placetype":"venue"
},
  "geometry": {"coordinates":[8.272465,46.139969],"type":"Point"}
}