{
  "type": "Feature",
  "properties": {
    "addr:full":"53100 Siena Siena Siena 53100",
    "addr:postcode":"53100;53100",
    "iso:country":"IT",
    "sg:address":"53100 Siena",
    "sg:city":"Siena",
    "sg:orig_category":"Prodotti Chimici Di Base. Prodotti Cosmetici E Da Toeletta",
    "sg:phone":"+39 0577 365156",
    "sg:postcode":"53100",
    "sg:province":"Siena",
    "wof:name":"Saniropole Snc",
    "wof:placetype":"venue"
},
  "geometry": {"coordinates":[11.3658008575,43.3197097778],"type":"Point"}
}