{
  "type": "Feature",
  "properties": {
    "iso:country":"IT",
    "sg:address":"24021 Albino",
    "sg:city":"Albino",
    "sg:orig_category":"Macchine E Forniture Per Ecologia E Smaltimento Rifiuti. Termotecnica E Riscaldamento, Apparecchiature E Servizi",
    "sg:phone":"+39 035 760111",
    "sg:postcode":"24021",
    "sg:province":"Bergamo",
    "sg:website":"http://www.celtica-ambiente.com",
    "wof:name":"Gruppo Celtica Ambiente Sa",
    "wof:placetype":"venue"
},
  "geometry": {"coordinates":[9.736801,45.738033],"type":"Point"}
}