{
  "type": "Feature",
  "properties": {
    "iso:country":"IT",
    "sg:address":"Via Lodi 86 21042 Caronno Pertusella",
    "sg:city":"Caronno Pertusella",
    "sg:classifiers":[
        {
            "category":"Military Area",
            "subcategory":"Air Force Base",
            "type":"Public Place"
        }
    ],
    "sg:phone":"+39 02 963981",
    "sg:postcode":"21042",
    "sg:province":"Varese",
    "sg:tags":[
        "electronic",
        "wound",
        "components"
    ],
    "sg:website":"www.belcoproducts.it",
    "wof:name":"Belco Spa",
    "wof:placetype":"venue"
},
  "geometry": {"coordinates":[9.049555,45.588734],"type":"Point"}
}