{
  "type": "Feature",
  "properties": {
    "iso:country":"IT",
    "sg:address":"50100 Firenze",
    "sg:orig_category":"Minuterie Metalliche E Ferramenta",
    "sg:phone":"+39 055 355744",
    "sg:province":"FI",
    "wof:name":"Mobilufficio Srl",
    "wof:placetype":"venue"
},
  "geometry": {"coordinates":[11.2399816513,43.7778968811],"type":"Point"}
}