{
  "type": "Feature",
  "properties": {
    "iso:country":"IT",
    "sg:address":"Via Quorchio 70032 Bitonto",
    "sg:city":"Bitonto",
    "sg:classifiers":[
        {
            "category":"Shopping",
            "subcategory":"Clothing, Apparel, & Fashions",
            "type":"Retail Goods"
        }
    ],
    "sg:phone":"+39 080 374 9095",
    "sg:postcode":"70032",
    "sg:province":"Bari",
    "sg:tags":[
        "clothes"
    ],
    "wof:name":"Maglificio Acdela S.r.l.",
    "wof:placetype":"venue"
},
  "geometry": {"coordinates":[16.679941,41.117489],"type":"Point"}
}