{
  "type": "Feature",
  "properties": {
    "addr:full":"36031 Dueville Dueville Vicenza 36031",
    "addr:postcode":"36031;36031",
    "iso:country":"IT",
    "sg:address":"36031 Dueville",
    "sg:city":"Dueville",
    "sg:orig_category":"Macchine, Impianti Ed Attrezzature Per Abbigliamento E Pelletterie. Macchine E Impianti Per Attivita' Commerciali Ed Artigianali",
    "sg:phone":"+39 0444 593529",
    "sg:postcode":"36031",
    "sg:province":"Vicenza",
    "wof:name":"Il Sole Lavasecco Sas Di Fin Monica",
    "wof:placetype":"venue"
},
  "geometry": {"coordinates":[11.54726,45.638054],"type":"Point"}
}