{
  "type": "Feature",
  "properties": {
    "iso:country":"IT",
    "sg:address":"37057 San Giovanni Lupatoto",
    "sg:city":"San Giovanni Lupatoto",
    "sg:orig_category":"Aspirazione Impianti",
    "sg:phone":"+39 045 925 0002",
    "sg:postcode":"37057",
    "sg:province":"Verona",
    "wof:name":"Stilfrigor Srl",
    "wof:placetype":"venue"
},
  "geometry": {"coordinates":[11.04432,45.373322],"type":"Point"}
}