{
  "type": "Feature",
  "properties": {
    "iso:country":"IT",
    "sg:address":"Via Fonda Di Mezzana 61/10 59100 Prato",
    "sg:city":"Mezzana",
    "sg:classifiers":[
        {
            "category":"Shopping",
            "subcategory":"Clothing, Apparel, & Fashions",
            "type":"Retail Goods"
        }
    ],
    "sg:phone":"+39 0574 574295",
    "sg:postcode":"59100",
    "sg:province":"Prato",
    "sg:tags":[
        "clothing",
        "fabric"
    ],
    "wof:name":"Lanificio Di Seano Di Ciappi Ezio",
    "wof:placetype":"venue"
},
  "geometry": {"coordinates":[11.09868,43.846581],"type":"Point"}
}