{
  "type": "Feature",
  "properties": {
    "addr:full":"11, Via Busto Arsizio 00040 Pomezia Pomezia Roma 00040",
    "addr:postcode":"00040;roma 00040",
    "addr:street":"Via Busto Arsizio",
    "iso:country":"IT",
    "sg:address":"11, Via Busto Arsizio 00040 Pomezia",
    "sg:city":"Pomezia",
    "sg:classifiers":[
        {
            "category":"Professional",
            "subcategory":"Printing & Photocopies",
            "type":"Services"
        }
    ],
    "sg:phone":"+39 39069107922",
    "sg:postcode":"00040",
    "sg:province":"Roma",
    "wof:name":"A.g.p. Srl Allestimento Grafico Pontino",
    "wof:placetype":"venue"
},
  "geometry": {"coordinates":[12.4924545288,41.6879653931],"type":"Point"}
}