{
  "type": "Feature",
  "properties": {
    "addr:full":"35, Piazza Aspromonte 20131 Milano Milano Milano 20131",
    "addr:postcode":"20131;20131",
    "addr:street":"Piazza Aspromonte",
    "iso:country":"IT",
    "sg:address":"35, Piazza Aspromonte 20131 Milano",
    "sg:city":"Milano",
    "sg:classifiers":[
        {
            "category":"Shopping",
            "subcategory":"Crafts & Fabrics",
            "type":"Retail Goods"
        }
    ],
    "sg:phone":"+39 02 2940 9994",
    "sg:postcode":"20131",
    "sg:province":"Milano",
    "wof:name":"Cottonfibre (s.r.l.)",
    "wof:placetype":"venue"
},
  "geometry": {"coordinates":[9.2192907333,45.4836082458],"type":"Point"}
}