{
  "type": "Feature",
  "properties": {
    "iso:country":"IT",
    "sg:address":"20121 Milano",
    "sg:city":"Milano",
    "sg:orig_category":"Servizi Ausiliari Per Il Trasporto",
    "sg:phone":"+39 02 865595",
    "sg:postcode":"20121",
    "sg:province":"Milano",
    "wof:name":"Intermedia (s.a.s.)",
    "wof:placetype":"venue"
},
  "geometry": {"coordinates":[9.186586,45.46751],"type":"Point"}
}