{
  "type": "Feature",
  "properties": {
    "iso:country":"IT",
    "sg:address":"74015 Martina Franca",
    "sg:city":"Martina Franca",
    "sg:orig_category":"Scuole E Servizi Scolastici",
    "sg:phone":"+39 080 483 1867",
    "sg:postcode":"74015",
    "sg:province":"Taranto",
    "wof:name":"Centro Artistico Teatrale Artemide",
    "wof:placetype":"venue"
},
  "geometry": {"coordinates":[17.475262,40.589626],"type":"Point"}
}