{
  "type": "Feature",
  "properties": {
    "iso:country":"IT",
    "sg:address":"25020 Bassano Bresciano",
    "sg:city":"Bassano Bresciano",
    "sg:orig_category":"Trattamenti Termici E Superficiali Metalli, Galvanotecnica",
    "sg:phone":"+39 030 993 5172",
    "sg:postcode":"25020",
    "sg:province":"Brescia",
    "wof:name":"Nuova Eurocrom Snc Di Berteni' Robert & C.",
    "wof:placetype":"venue"
},
  "geometry": {"coordinates":[10.121168,45.247398],"type":"Point"}
}