{
  "type": "Feature",
  "properties": {
    "addr:full":"20123 Milano Milano Milano 20123",
    "addr:postcode":"20123;20123",
    "iso:country":"IT",
    "sg:address":"20123 Milano",
    "sg:city":"Milano",
    "sg:orig_category":"Antincendio - Impianti, Attrezzature E Materiali",
    "sg:phone":"+39 02 835 7493",
    "sg:postcode":"20123",
    "sg:province":"Milano",
    "sg:website":"http://www.atelierdellegno.it",
    "wof:name":"Atelier Del Legno",
    "wof:placetype":"venue"
},
  "geometry": {"coordinates":[9.176802,45.456146],"type":"Point"}
}