{
  "type": "Feature",
  "properties": {
    "addr:full":"Strada Statale 31 Bis 13039 Trino Trino Vercelli 13039",
    "addr:housenumber":"31 bis",
    "addr:postcode":"13039;13039",
    "addr:street":"Strada Statale",
    "iso:country":"IT",
    "sg:address":"Strada Statale 31 Bis 13039 Trino",
    "sg:city":"Trino",
    "sg:classifiers":[
        {
            "category":"Shopping",
            "type":"Retail Goods"
        }
    ],
    "sg:phone":"+39 0161 801464",
    "sg:postcode":"13039",
    "sg:province":"Vercelli",
    "sg:tags":[
        "finished",
        "-",
        "metallic"
    ],
    "wof:name":"Of.me.t.",
    "wof:placetype":"venue"
},
  "geometry": {"coordinates":[8.3487443924,45.2575492859],"type":"Point"}
}