{
  "type": "Feature",
  "properties": {
    "addr:full":"Via Nazionale 1/n-u 38060 Besenello Besenello Trento 38060",
    "addr:housenumber":"1 / n-u",
    "addr:postcode":"38060;38060",
    "addr:street":"Via Nazionale",
    "iso:country":"IT",
    "sg:address":"Via Nazionale 1/n-u 38060 Besenello",
    "sg:city":"Besenello",
    "sg:classifiers":[
        {
            "category":"Communications",
            "subcategory":"Film & Video Production",
            "type":"Services"
        }
    ],
    "sg:phone":"+39 0464 830004",
    "sg:postcode":"38060",
    "sg:province":"Trento",
    "sg:tags":[
        "screen",
        "projection"
    ],
    "sg:website":"www.screenline.it",
    "wof:name":"Screen Line Srl",
    "wof:placetype":"venue"
},
  "geometry": {"coordinates":[11.1048583984,45.947883606],"type":"Point"}
}