{
  "type": "Feature",
  "properties": {
    "addr:full":"00013 Mentana Mentana Roma 00013",
    "addr:postcode":"00013;00013",
    "iso:country":"IT",
    "sg:address":"00013 Mentana",
    "sg:city":"Mentana",
    "sg:orig_category":"Forniture Per Agricoltura E Zootecnia",
    "sg:phone":"+39 06 905 9515",
    "sg:postcode":"00013",
    "sg:province":"Roma",
    "wof:name":"Proietti Tolmina",
    "wof:placetype":"venue"
},
  "geometry": {"coordinates":[12.6361494064,42.0092506409],"type":"Point"}
}