{
  "type": "Feature",
  "properties": {
    "iso:country":"IT",
    "sg:address":"29, Via Orlandi Ferdinando 43100 Parma",
    "sg:city":"Parma",
    "sg:classifiers":[
        {
            "category":"Professional",
            "subcategory":"Printing & Photocopies",
            "type":"Services"
        }
    ],
    "sg:phone":"+39 0521 242863",
    "sg:postcode":"43100",
    "sg:province":"Parma",
    "wof:name":"Graphital (s.n.c.)",
    "wof:placetype":"venue"
},
  "geometry": {"coordinates":[10.2949199677,44.8232078552],"type":"Point"}
}