{
  "type": "Feature",
  "properties": {
    "iso:country":"IT",
    "sg:address":"24040 Bonate Sotto",
    "sg:city":"Bonate Sotto",
    "sg:orig_category":"Valvole E Apparecchiature Di Misura. Forniture Per Attivita' Industriali",
    "sg:phone":"+39 035 991150",
    "sg:postcode":"24040",
    "sg:province":"Bergamo",
    "wof:name":"Record (s.p.a.)",
    "wof:placetype":"venue"
},
  "geometry": {"coordinates":[9.5764,45.693237],"type":"Point"}
}