{
  "type": "Feature",
  "properties": {
    "addr:full":"30, Via Ludovico Ariosto 20089 Rozzano Rozzano Milano 20089",
    "addr:postcode":"20089;20089",
    "addr:street":"Via Ludovico Ariosto",
    "iso:country":"IT",
    "sg:address":"30, Via Ludovico Ariosto 20089 Rozzano",
    "sg:city":"Rozzano",
    "sg:classifiers":[
        {
            "category":"Autos & Motor Vehicles",
            "subcategory":"Automobile Sales",
            "type":"Retail Goods"
        }
    ],
    "sg:phone":"+39 39028259251",
    "sg:postcode":"20089",
    "sg:province":"Milano",
    "sg:tags":[
        "equipment",
        "transport"
    ],
    "wof:name":"Cesare Landi (s.r.l.)",
    "wof:placetype":"venue"
},
  "geometry": {"coordinates":[9.174798,45.381023],"type":"Point"}
}