{
  "type": "Feature",
  "properties": {
    "iso:country":"IT",
    "sg:address":"50018 Scandicci",
    "sg:city":"Scandicci",
    "sg:classifiers":[
        {
            "category":"Professional",
            "subcategory":"Art Services",
            "type":"Services"
        }
    ],
    "sg:phone":"+39 055 756554",
    "sg:postcode":"50018",
    "sg:province":"Firenze",
    "sg:tags":[
        "stone",
        "craft",
        "similar",
        "artistic",
        "marble"
    ],
    "sg:website":"http://www.bertimosaici.com",
    "wof:name":"Berti A. & P. Snc Di Alessio & Patrizio Berti",
    "wof:placetype":"venue"
},
  "geometry": {"coordinates":[11.166104,43.763489],"type":"Point"}
}