{
  "type": "Feature",
  "properties": {
    "iso:country":"IT",
    "sg:address":"Contrada Piano Corte Larderia 98129 Messina",
    "sg:city":"Larderia",
    "sg:classifiers":[
        {
            "category":"Parking",
            "subcategory":"Lot",
            "type":"Transportation"
        }
    ],
    "sg:phone":"+39 39090730252",
    "sg:postcode":"98129",
    "sg:province":"Messina",
    "sg:tags":[
        "transport",
        "road"
    ],
    "wof:name":"Mazzeo",
    "wof:placetype":"venue"
},
  "geometry": {"coordinates":[15.555523,38.192333],"type":"Point"}
}