{
  "type": "Feature",
  "properties": {
    "iso:country":"IT",
    "sg:address":"63033 Monte Prandone",
    "sg:orig_category":"Sport And Leisure, Services. Tourism, Services. Motor Vehicles, Auxiliary Services. Transport, Auxiliary Services",
    "sg:phone":"+39 0735 711403",
    "sg:postcode":"63033",
    "sg:province":"Ascoli Piceno",
    "sg:website":"http://www.boomerangviaggi.it",
    "wof:name":"Boomerang Viaggi - Canali Bus",
    "wof:placetype":"venue"
},
  "geometry": {"coordinates":[13.574977,42.8554],"type":"Point"}
}