{
  "type": "Feature",
  "properties": {
    "iso:country":"IT",
    "sg:address":"Sant'apolinare, Corso Del Popolo 260, 45100 Rovigo, Ro",
    "sg:city":"Rovigo",
    "sg:classifiers":[
        {
            "category":"Banks & Credit Unions",
            "subcategory":"Bank",
            "type":"Services"
        }
    ],
    "sg:postcode":"45100",
    "sg:province":"Rovigo",
    "wof:name":"Banca Di Credito Cooperativo Delta Po (rovigo)",
    "wof:placetype":"venue"
},
  "geometry": {"coordinates":[11.789797,45.070736],"type":"Point"}
}