{
  "type": "Feature",
  "properties": {
    "iso:country":"IT",
    "sg:address":"5, Via Dell' Impresa 46029 Rivarolo Mantovano",
    "sg:city":"Riva",
    "sg:classifiers":[
        {
            "category":"Shopping",
            "type":"Retail Goods"
        }
    ],
    "sg:phone":"+39 0376 957002",
    "sg:postcode":"46029",
    "sg:province":"Mantova",
    "sg:tags":[
        "finished",
        "-",
        "metallic"
    ],
    "wof:name":"Metallurgica Rivarolese S.r.l.",
    "wof:placetype":"venue"
},
  "geometry": {"coordinates":[10.7976980209,45.1603660583],"type":"Point"}
}