{
  "type": "Feature",
  "properties": {
    "addr:full":"65122 Pescara Pescara Pescara 65122",
    "addr:postcode":"65122;65122",
    "iso:country":"IT",
    "sg:address":"65122 Pescara",
    "sg:city":"Pescara",
    "sg:classifiers":[
        {
            "category":"Education",
            "subcategory":"School",
            "type":"Public Place"
        }
    ],
    "sg:phone":"+39 085 421 0262",
    "sg:postcode":"65122",
    "sg:province":"Pescara",
    "sg:tags":[
        "scuole",
        "informatica",
        "di"
    ],
    "sg:website":"http://www.obsonline.it",
    "wof:name":"Jobs Di Paolo F.diazzi & C. Sas",
    "wof:placetype":"venue"
},
  "geometry": {"coordinates":[14.209075,42.471901],"type":"Point"}
}