{
  "type": "Feature",
  "properties": {
    "iso:country":"IT",
    "sg:address":"06122 Perugia",
    "sg:city":"Perugia",
    "sg:orig_category":"Campeggio. Alberghi E Strutture Extra Alberghiere",
    "sg:phone":"+39 075 572 2880",
    "sg:postcode":"06122",
    "sg:province":"Perugia",
    "sg:website":"http://www.ostello.perugia.it",
    "wof:name":"Ostello Della Giovent\u00d9 - Centro Internaz. Accoglienza",
    "wof:placetype":"venue"
},
  "geometry": {"coordinates":[12.391486,43.11256],"type":"Point"}
}