{
  "type": "Feature",
  "properties": {
    "iso:country":"IT",
    "sg:address":"00178 Roma",
    "sg:city":"Roma",
    "sg:orig_category":"Elettromeccanica",
    "sg:phone":"+39 06 718 6541",
    "sg:postcode":"00178",
    "sg:province":"Roma",
    "sg:website":"http://www.bernarditecnel.com",
    "wof:name":"Bernardi Srl",
    "wof:placetype":"venue"
},
  "geometry": {"coordinates":[12.546526,41.842964],"type":"Point"}
}