{
  "type": "Feature",
  "properties": {
    "iso:country":"IT",
    "sg:address":"4, Via Soastene 36040 Brendola",
    "sg:city":"Brendola",
    "sg:classifiers":[
        {
            "category":"Shopping",
            "subcategory":"Computers & Home Electronics",
            "type":"Retail Goods"
        }
    ],
    "sg:phone":"+39 0444 601455",
    "sg:postcode":"36040",
    "sg:province":"Vicenza",
    "sg:tags":[
        "electronic",
        "electrical",
        "equipment"
    ],
    "wof:name":"Ate Applicazioni Termo Elettroniche S.r.l.",
    "wof:placetype":"venue"
},
  "geometry": {"coordinates":[11.43716,45.48436],"type":"Point"}
}