{
  "type": "Feature",
  "properties": {
    "addr:full":"42100 Reggio Emilia Reggio Nell'Emilia 42100",
    "addr:postcode":"42100;42100",
    "iso:country":"IT",
    "sg:address":"42100 Reggio Emilia",
    "sg:orig_category":"Impianti Idraulici E Termoidraulici",
    "sg:phone":"+39 0522 307841",
    "sg:postcode":"42100",
    "sg:province":"Reggio Nell'Emilia",
    "sg:website":"http://www.pi2000.it",
    "wof:name":"Plast Industria 2000 Srl",
    "wof:placetype":"venue"
},
  "geometry": {"coordinates":[10.609287,44.714016],"type":"Point"}
}