{
  "type": "Feature",
  "properties": {
    "addr:full":"59016 Poggio A Caiano Poggio a Caiano Prato 59016",
    "addr:postcode":"59016;59016",
    "iso:country":"IT",
    "sg:address":"59016 Poggio A Caiano",
    "sg:city":"Poggio a Caiano",
    "sg:orig_category":"Ospedali E Servizi Sanitari",
    "sg:phone":"+39 055 877236",
    "sg:postcode":"59016",
    "sg:province":"Prato",
    "wof:name":"Cherubini Anna",
    "wof:placetype":"venue"
},
  "geometry": {"coordinates":[11.049688,43.819897],"type":"Point"}
}