{
  "type": "Feature",
  "properties": {
    "addr:full":"2, Via Ballarin 37024 Negrar Negrar Verona 37024",
    "addr:postcode":"37024;37024",
    "addr:street":"Via Ballarin",
    "iso:country":"IT",
    "sg:address":"2, Via Ballarin 37024 Negrar",
    "sg:city":"Negrar",
    "sg:classifiers":[
        {
            "category":"Food & Beverages",
            "subcategory":"Groceries & Convenience Stores",
            "type":"Retail Goods"
        }
    ],
    "sg:phone":"+39 045 750 2121",
    "sg:postcode":"37024",
    "sg:province":"Verona",
    "sg:tags":[
        "drink"
    ],
    "wof:name":"Cantina Soc. Valpolicella",
    "wof:placetype":"venue"
},
  "geometry": {"coordinates":[10.938617,45.519131],"type":"Point"}
}