{
  "type": "Feature",
  "properties": {
    "iso:country":"IT",
    "sg:address":"Via 12 Ottobre 1492, 5 41040 Ubersetto",
    "sg:classifiers":[
        {
            "category":"Wholesale",
            "subcategory":"Plants",
            "type":"Manufacturing & Wholesale Goods"
        }
    ],
    "sg:phone":"+39 0536 845151",
    "sg:postcode":"41040",
    "sg:province":"Modena",
    "sg:tags":[
        "screen",
        "printing"
    ],
    "sg:website":"www.essepiesse.it",
    "wof:name":"Essepiesse Srl",
    "wof:placetype":"venue"
},
  "geometry": {"coordinates":[10.92522,44.647079],"type":"Point"}
}