{
  "type": "Feature",
  "properties": {
    "iso:country":"IT",
    "sg:address":"20052 Monza",
    "sg:city":"Monza",
    "sg:orig_category":"Ospedali E Servizi Sanitari",
    "sg:phone":"+39 039 366335",
    "sg:postcode":"20052",
    "sg:province":"Milano",
    "wof:name":"Saip Studio Associato Infermieri Professionali",
    "wof:placetype":"venue"
},
  "geometry": {"coordinates":[9.16888,45.480309],"type":"Point"}
}