{
  "type": "Feature",
  "properties": {
    "iso:country":"IT",
    "sg:address":"Via Emilia Est, 2/g; Rubiera; 42048",
    "sg:classifiers":[
        {
            "category":"Banks & Credit Unions",
            "subcategory":"Bank",
            "type":"Services"
        }
    ],
    "sg:phone":"+39 0522 628185",
    "sg:postcode":"42048",
    "sg:province":"Reggio Nell'Emilia",
    "wof:name":"Cooper Banca",
    "wof:placetype":"venue"
},
  "geometry": {"coordinates":[10.782327,44.653561],"type":"Point"}
}