{
  "type": "Feature",
  "properties": {
    "iso:country":"IT",
    "sg:address":"Via Quattro Martiri 10; Mugnano Di Napoli; 80018",
    "sg:city":"Mugnano di Napoli",
    "sg:classifiers":[
        {
            "category":"Banks & Credit Unions",
            "subcategory":"Bank",
            "type":"Services"
        }
    ],
    "sg:phone":"+39 081 745 1244",
    "sg:postcode":"80018",
    "sg:province":"Napoli",
    "wof:name":"Istituto Bancario, San Paolo Di Torino Spa",
    "wof:placetype":"venue"
},
  "geometry": {"coordinates":[14.206182,40.909927],"type":"Point"}
}