{
  "type": "Feature",
  "properties": {
    "iso:country":"IT",
    "sg:address":"20024 Garbagnate Milanese",
    "sg:city":"Garbagnate Milanese",
    "sg:orig_category":"Sport - Articoli E Forniture",
    "sg:phone":"+39 02 9902 5110",
    "sg:postcode":"20024",
    "sg:province":"Milano",
    "wof:name":"Scubatec Di Finesso Giuseppe",
    "wof:placetype":"venue"
},
  "geometry": {"coordinates":[9.084313,45.584583],"type":"Point"}
}