{
  "type": "Feature",
  "properties": {
    "iso:country":"IT",
    "sg:address":"47031 Repubblica Di San Marino",
    "sg:orig_category":"Insegne Luminose",
    "sg:phone":"+39 0549 909116",
    "sg:province":"SM",
    "wof:name":"Ugolini Press",
    "wof:placetype":"venue"
},
  "geometry": {"coordinates":[12.484912,43.980053],"type":"Point"}
}