{
  "type": "Feature",
  "properties": {
    "iso:country":"IT",
    "sg:address":"Contrada Torre Chimera 93019 Sommatino",
    "sg:city":"Sommatino",
    "sg:classifiers":[
        {
            "category":"Professional",
            "subcategory":"Engineering",
            "type":"Services"
        }
    ],
    "sg:phone":"+39 0922 871694",
    "sg:postcode":"93019",
    "sg:province":"Caltanissetta",
    "sg:tags":[
        "machine",
        "-",
        "mechanical"
    ],
    "wof:name":"Dentallin Metalli Di Mantione & C Snc",
    "wof:placetype":"venue"
},
  "geometry": {"coordinates":[14.06329,37.48991],"type":"Point"}
}