{
  "type": "Feature",
  "properties": {
    "addr:full":"25030 Adro Adro Brescia 25030",
    "addr:postcode":"25030;25030",
    "iso:country":"IT",
    "sg:address":"25030 Adro",
    "sg:city":"Adro",
    "sg:orig_category":"Biancheria, Telerie E Coperte. Arredo Camera Letto E Complementi",
    "sg:phone":"+39 030 735 7369",
    "sg:postcode":"25030",
    "sg:province":"Brescia",
    "wof:name":"Mpl S.r.l.",
    "wof:placetype":"venue"
},
  "geometry": {"coordinates":[10.159481,45.520477],"type":"Point"}
}