{
  "type": "Feature",
  "properties": {
    "iso:country":"IT",
    "sg:address":"40133 Bologna",
    "sg:city":"Bologna",
    "sg:orig_category":"Equilibratura Statica E Dinamica",
    "sg:phone":"+39 051 387600",
    "sg:postcode":"40133",
    "sg:province":"Bologna",
    "sg:website":"http://www.progettieditoriali.com/reno",
    "wof:name":"Reno Srl",
    "wof:placetype":"venue"
},
  "geometry": {"coordinates":[11.296215,44.51004],"type":"Point"}
}