{
  "type": "Feature",
  "properties": {
    "iso:country":"IT",
    "sg:address":"Corso Garibaldi 57/a, 88812 Crucoli, Kr",
    "sg:city":"Crucoli",
    "sg:classifiers":[
        {
            "category":"Banks & Credit Unions",
            "subcategory":"Bank",
            "type":"Services"
        }
    ],
    "sg:postcode":"88812",
    "sg:province":"Crotone",
    "wof:name":"Cassa Di Credito Cooperativo Della Media Magna Grecia Scrl",
    "wof:placetype":"venue"
},
  "geometry": {"coordinates":[17.127079,39.080738],"type":"Point"}
}