{
  "type": "Feature",
  "properties": {
    "iso:country":"IT",
    "sg:address":"11, Via Di Vittorio Giuseppe 20068 Peschiera Borromeo",
    "sg:city":"Peschiera Borromeo",
    "sg:classifiers":[
        {
            "category":"Utilities",
            "subcategory":"Electric",
            "type":"Services"
        }
    ],
    "sg:phone":"+39 02 5530 1151",
    "sg:postcode":"20068",
    "sg:province":"Milano",
    "sg:tags":[
        "component",
        "electronic"
    ],
    "wof:name":"Vertola (s.r.l.)",
    "wof:placetype":"venue"
},
  "geometry": {"coordinates":[9.289042,45.436001],"type":"Point"}
}