{
  "type": "Feature",
  "properties": {
    "iso:country":"IT",
    "sg:address":"73100 Lecce",
    "sg:city":"Lecce",
    "sg:classifiers":[
        {
            "category":"Retail",
            "subcategory":"Storage",
            "type":"Services"
        }
    ],
    "sg:phone":"+39 0832 331452",
    "sg:postcode":"73100",
    "sg:province":"Lecce",
    "sg:tags":[
        "equipment",
        "handling",
        "systems"
    ],
    "wof:name":"Grandi Sollevamenti Di Gianluca Carla' Srl",
    "wof:placetype":"venue"
},
  "geometry": {"coordinates":[18.139355,40.366394],"type":"Point"}
}