{
  "type": "Feature",
  "properties": {
    "iso:country":"IT",
    "sg:address":"20090 Rodano",
    "sg:city":"Rodano",
    "sg:orig_category":"Prodotti Chimici Di Base. Ospedali E Servizi Sanitari",
    "sg:phone":"+39 02 9532 0725",
    "sg:postcode":"20090",
    "sg:province":"Milano",
    "wof:name":"Air Liquide Italia S.r.l.",
    "wof:placetype":"venue"
},
  "geometry": {"coordinates":[9.3110895157,45.4782485962],"type":"Point"}
}