{
  "type": "Feature",
  "properties": {
    "addr:full":"8, Via Roma 10040 Caprie Caprie Torino 10040",
    "addr:postcode":"10040;10040",
    "addr:street":"Via Roma",
    "iso:country":"IT",
    "sg:address":"8, Via Roma 10040 Caprie",
    "sg:city":"Caprie",
    "sg:classifiers":[
        {
            "category":"Building & Trades",
            "subcategory":"Construction",
            "type":"Services"
        }
    ],
    "sg:phone":"+39 011 964 2253",
    "sg:postcode":"10040",
    "sg:province":"Torino",
    "sg:tags":[
        "work",
        "public"
    ],
    "wof:name":"Rotunno Ing.vito (s.p.a.)",
    "wof:placetype":"venue"
},
  "geometry": {"coordinates":[7.329735,45.11335],"type":"Point"}
}