{
  "type": "Feature",
  "properties": {
    "addr:full":"46010 Gazzuolo Gazzuolo Mantova 46010",
    "addr:postcode":"46010;46010",
    "iso:country":"IT",
    "sg:address":"46010 Gazzuolo",
    "sg:city":"Gazzuolo",
    "sg:orig_category":"Arredamento Scuole E Comunita'",
    "sg:phone":"+39 0376 97924",
    "sg:postcode":"46010",
    "sg:province":"Mantova",
    "sg:website":"http://www.manerbaspa.com",
    "wof:name":"Manerba Spa",
    "wof:placetype":"venue"
},
  "geometry": {"coordinates":[10.576321,45.062469],"type":"Point"}
}