{
  "type": "Feature",
  "properties": {
    "iso:country":"IT",
    "sg:address":"2/a, Strada Fontana 43013 Langhirano",
    "sg:city":"Langhirano",
    "sg:classifiers":[
        {
            "category":"Food & Beverages",
            "subcategory":"Groceries & Convenience Stores",
            "type":"Retail Goods"
        }
    ],
    "sg:phone":"+39 0521 357007",
    "sg:postcode":"43013",
    "sg:province":"Parma",
    "sg:tags":[
        "product",
        "related"
    ],
    "wof:name":"Salumificio Conti Snc Di Conti Givanni - Claudio E Aufrodisio",
    "wof:placetype":"venue"
},
  "geometry": {"coordinates":[10.1992988586,44.5920333862],"type":"Point"}
}