{
  "type": "Feature",
  "properties": {
    "addr:full":"34, Viale Zaccagna D. 54033 Carrara Carrara Massa-Carrara 54033",
    "addr:housenumber":"34",
    "addr:postcode":"54033;54033",
    "addr:street":"Viale Zaccagna D.",
    "iso:country":"IT",
    "sg:address":"34, Viale Zaccagna D. 54033 Carrara",
    "sg:city":"Carrara",
    "sg:classifiers":[
        {
            "category":"Marine",
            "type":"Transportation"
        }
    ],
    "sg:phone":"+39 0585 633346",
    "sg:postcode":"54033",
    "sg:province":"Massa-Carrara",
    "sg:tags":[
        "transport",
        "sea"
    ],
    "wof:name":"Csc Logistica Srl",
    "wof:placetype":"venue"
},
  "geometry": {"coordinates":[10.059723,44.038677],"type":"Point"}
}