{
  "type": "Feature",
  "properties": {
    "addr:full":"For Us Off-road Vehicles51034 Casalguidi Casalguidi Pistoia 51034",
    "addr:postcode":"51034",
    "iso:country":"IT",
    "sg:address":"For Us Off-road Vehicles51034 Casalguidi",
    "sg:city":"Casalguidi",
    "sg:classifiers":[
        {
            "category":"Manufacturing",
            "subcategory":"Paper Products",
            "type":"Manufacturing & Wholesale Goods"
        }
    ],
    "sg:phone":"+39 0573 929362",
    "sg:postcode":"51034",
    "sg:province":"Pistoia",
    "sg:tags":[
        "cardboard"
    ],
    "sg:website":"http://www.linearoll.it",
    "wof:name":"Linea Roll",
    "wof:placetype":"venue"
},
  "geometry": {"coordinates":[10.9185237885,43.9321556091],"type":"Point"}
}