{
  "type": "Feature",
  "properties": {
    "iso:country":"IT",
    "sg:address":"80125 Napoli",
    "sg:city":"Napoli",
    "sg:orig_category":"Accessori Dei Mezzi Di Trasporto. Riparazione Dei Mezzi Di Trasporto",
    "sg:phone":"+39 081 624100",
    "sg:postcode":"80125",
    "sg:province":"Napoli",
    "wof:name":"Grilli Gaetano",
    "wof:placetype":"venue"
},
  "geometry": {"coordinates":[14.234497,40.918205],"type":"Point"}
}