{
  "type": "Feature",
  "properties": {
    "iso:country":"IT",
    "sg:address":"Via Starza Novella 83029 Solofra",
    "sg:city":"Solofra",
    "sg:classifiers":[
        {
            "category":"Manufacturing",
            "subcategory":"Textiles",
            "type":"Manufacturing & Wholesale Goods"
        }
    ],
    "sg:phone":"+39 0825 532645",
    "sg:postcode":"83029",
    "sg:province":"Avellino",
    "sg:tags":[
        "leather",
        "raw",
        "material",
        "-"
    ],
    "wof:name":"Conceria Airone S.r.l.",
    "wof:placetype":"venue"
},
  "geometry": {"coordinates":[14.843181,40.830647],"type":"Point"}
}