{
  "type": "Feature",
  "properties": {
    "iso:country":"IT",
    "sg:address":"50013 Campi Bisenzio",
    "sg:city":"Campi Bisenzio",
    "sg:orig_category":"Forniture Per Abbigliamento E Pelletterie. Complementi Di Arredamento",
    "sg:phone":"+39 055 896 0516",
    "sg:postcode":"50013",
    "sg:province":"Firenze",
    "wof:name":"Principe Decimo S.r.l.",
    "wof:placetype":"venue"
},
  "geometry": {"coordinates":[11.1966180801,43.8377799988],"type":"Point"}
}