{
  "type": "Feature",
  "properties": {
    "iso:country":"IT",
    "sg:address":"Via Gaetana Agnesi 251 20033 Desio",
    "sg:city":"Desio",
    "sg:classifiers":[
        {
            "category":"Wholesale",
            "subcategory":"Construction Materials",
            "type":"Manufacturing & Wholesale Goods"
        }
    ],
    "sg:phone":"+39 036 239 4501",
    "sg:postcode":"20033",
    "sg:province":"Milano",
    "sg:tags":[
        "sound",
        "insulation",
        "element"
    ],
    "wof:name":"Rieter Automotive Fimit Spa",
    "wof:placetype":"venue"
},
  "geometry": {"coordinates":[9.189416,45.610741],"type":"Point"}
}