{
  "type": "Feature",
  "properties": {
    "iso:country":"IT",
    "sg:address":"50145 Firenze",
    "sg:city":"Firenze",
    "sg:orig_category":"Petroli, Gas E Combustibili",
    "sg:phone":"+39 055 317312",
    "sg:postcode":"50145",
    "sg:province":"Firenze",
    "wof:name":"Venturini Fratelli",
    "wof:placetype":"venue"
},
  "geometry": {"coordinates":[11.2183599472,43.7086830139],"type":"Point"}
}