{
  "type": "Feature",
  "properties": {
    "addr:full":"00136 Roma Roma Roma 00136",
    "addr:postcode":"00136;00136",
    "iso:country":"IT",
    "sg:address":"00136 Roma",
    "sg:city":"Roma",
    "sg:classifiers":[
        {
            "category":"Health Services",
            "subcategory":"Health Practitioner",
            "type":"Services"
        }
    ],
    "sg:phone":"+39 06 3545 0508",
    "sg:postcode":"00136",
    "sg:province":"Roma",
    "sg:tags":[
        "medici"
    ],
    "wof:name":"Fedele Filippo",
    "wof:placetype":"venue"
},
  "geometry": {"coordinates":[12.439562,41.91626],"type":"Point"}
}