{
  "type": "Feature",
  "properties": {
    "iso:country":"IT",
    "sg:address":"14, Via Galvani 20091 Bresso",
    "sg:city":"Bresso",
    "sg:classifiers":[
        {
            "category":"Shopping",
            "subcategory":"Clothing, Apparel, & Fashions",
            "type":"Retail Goods"
        }
    ],
    "sg:phone":"+39 02 6650 4034",
    "sg:postcode":"20091",
    "sg:province":"Milano",
    "sg:tags":[
        "clothing",
        "accessory"
    ],
    "wof:name":"Arte Del Tricot Srl",
    "wof:placetype":"venue"
},
  "geometry": {"coordinates":[9.190199,45.529469],"type":"Point"}
}