{
  "type": "Feature",
  "properties": {
    "addr:full":"13, Via Di Vittorio Giuseppe 40026 Imola Imola Bologna 40026",
    "addr:postcode":"40026;40026",
    "addr:street":"Via Di Vittorio Giuseppe",
    "iso:country":"IT",
    "sg:address":"13, Via Di Vittorio Giuseppe 40026 Imola",
    "sg:city":"Imola",
    "sg:classifiers":[
        {
            "category":"Shopping",
            "type":"Retail Goods"
        }
    ],
    "sg:phone":"+39 0542 641851",
    "sg:postcode":"40026",
    "sg:province":"Bologna",
    "sg:tags":[
        "finished",
        "-",
        "metallic"
    ],
    "wof:name":"Oral (s.r.l.)",
    "wof:placetype":"venue"
},
  "geometry": {"coordinates":[11.3464813232,44.4942207336],"type":"Point"}
}