{
  "type": "Feature",
  "properties": {
    "addr:full":"8, Via Liberta' 13862 Brusnengo Brusnengo Biella 13862",
    "addr:postcode":"13862;brusnengo;13862",
    "addr:street":"Via Liberta '",
    "iso:country":"IT",
    "sg:address":"8, Via Liberta' 13862 Brusnengo",
    "sg:city":"Brusnengo",
    "sg:classifiers":[
        {
            "category":"Shopping",
            "subcategory":"Crafts & Fabrics",
            "type":"Retail Goods"
        }
    ],
    "sg:phone":"+39 39015985166",
    "sg:postcode":"13862",
    "sg:province":"Biella",
    "sg:tags":[
        "ceramic"
    ],
    "wof:name":"Sasil (s.p.a.)",
    "wof:placetype":"venue"
},
  "geometry": {"coordinates":[8.252733,45.593517],"type":"Point"}
}