{
  "type": "Feature",
  "properties": {
    "iso:country":"IT",
    "sg:address":"48018 Faenza",
    "sg:city":"Faenza",
    "sg:orig_category":"Arredamenti - Materiali",
    "sg:phone":"+39 0546 622422",
    "sg:postcode":"48018",
    "sg:province":"Ravenna",
    "wof:name":"S.a.m. Societa' Artistica Marmi Di Cerchierini & C.",
    "wof:placetype":"venue"
},
  "geometry": {"coordinates":[11.862634,44.305393],"type":"Point"}
}