{
  "type": "Feature",
  "properties": {
    "iso:country":"IT",
    "sg:address":"Via Molina 10 21100 Varese",
    "sg:city":"Varese",
    "sg:classifiers":[
        {
            "category":"Home & Garden",
            "subcategory":"Hardware",
            "type":"Retail Goods"
        }
    ],
    "sg:phone":"+39 0332 334188",
    "sg:postcode":"21100",
    "sg:province":"Varese",
    "sg:tags":[
        "small",
        "ironware",
        "item"
    ],
    "wof:name":"Ambrosetti Snc",
    "wof:placetype":"venue"
},
  "geometry": {"coordinates":[8.791434,45.8904],"type":"Point"}
}