{
  "type": "Feature",
  "properties": {
    "iso:country":"IT",
    "sg:address":"1, V. Forestola - La Cotarda 04014 Pontinia",
    "sg:city":"Pontinia",
    "sg:classifiers":[
        {
            "category":"Manufacturing",
            "subcategory":"Rubber & Plastics",
            "type":"Manufacturing & Wholesale Goods"
        }
    ],
    "sg:phone":"+39 0773 840042",
    "sg:postcode":"04014",
    "sg:province":"Latina",
    "sg:website":"http://www.paginegialle.it/fgseurope",
    "wof:name":"F.g.s. Europe 98 Srl",
    "wof:placetype":"venue"
},
  "geometry": {"coordinates":[12.9036998749,41.4675979614],"type":"Point"}
}