{
  "type": "Feature",
  "properties": {
    "iso:country":"IT",
    "sg:address":"20090 Segrate",
    "sg:city":"Segrate",
    "sg:orig_category":"Prodotti Chimici Secondari. Medicinali E Prodotti Parafarmaceutici",
    "sg:phone":"+39 02 210181",
    "sg:postcode":"20090",
    "sg:province":"Milano",
    "wof:name":"Schering-plough S.p.a.",
    "wof:placetype":"venue"
},
  "geometry": {"coordinates":[9.2916936874,45.5011444092],"type":"Point"}
}