{
  "type": "Feature",
  "properties": {
    "addr:full":"40141 Bologna Bologna Bologna 40141",
    "addr:postcode":"40141;40141",
    "iso:country":"IT",
    "sg:address":"40141 Bologna",
    "sg:city":"Bologna",
    "sg:orig_category":"Servizi Per Lo Sport E Il Tempo Libero. Servizi Al Turismo",
    "sg:phone":"+39 051 623 7114",
    "sg:postcode":"40141",
    "sg:province":"Bologna",
    "sg:website":"http://www.biodanza.it",
    "wof:name":"Associazione Europea Insegnanti Di Biodanza",
    "wof:placetype":"venue"
},
  "geometry": {"coordinates":[11.382393,44.467659],"type":"Point"}
}