{
  "type": "Feature",
  "properties": {
    "iso:country":"IT",
    "sg:address":"4, Via Giuseppe Di Vittorio 25030 Adro",
    "sg:city":"Adro",
    "sg:classifiers":[
        {
            "category":"Shopping",
            "subcategory":"Crafts & Fabrics",
            "type":"Retail Goods"
        }
    ],
    "sg:phone":"+39 030 735 7494",
    "sg:postcode":"25030",
    "sg:province":"Brescia",
    "sg:tags":[
        "linen"
    ],
    "wof:name":"Mpl S.r.l.",
    "wof:placetype":"venue"
},
  "geometry": {"coordinates":[9.9382543564,45.6179733276],"type":"Point"}
}