{
  "type": "Feature",
  "properties": {
    "iso:country":"IT",
    "sg:address":"63044 Comunanza",
    "sg:city":"Comunanza",
    "sg:orig_category":"Forniture Per Agricoltura E Zootecnia. Animali Domestici",
    "sg:phone":"+39 0736 845268",
    "sg:postcode":"63044",
    "sg:province":"Ascoli Piceno",
    "wof:name":"Tiburtini & Pieragostini Laf S.n.c.",
    "wof:placetype":"venue"
},
  "geometry": {"coordinates":[13.4283103943,42.9645881653],"type":"Point"}
}