{
  "type": "Feature",
  "properties": {
    "iso:country":"IT",
    "sg:address":"14, Via Leopardi 47833 Morciano Di Romagna",
    "sg:city":"Morciano di Romagna",
    "sg:classifiers":[
        {
            "category":"Professional",
            "subcategory":"Printing & Photocopies",
            "type":"Services"
        }
    ],
    "sg:phone":"+39 0541 857444",
    "sg:postcode":"47833",
    "sg:province":"Rimini",
    "wof:name":"Modulsistem (s.r.l.)",
    "wof:placetype":"venue"
},
  "geometry": {"coordinates":[12.5662565231,44.0607795715],"type":"Point"}
}