{
  "type": "Feature",
  "properties": {
    "addr:full":"Via C. Zatti 23 42100 Reggio Emilia Reggio Nell'Emilia 42100",
    "addr:housenumber":"23",
    "addr:postcode":"42100;42100",
    "addr:street":"Via C. Zatti",
    "iso:country":"IT",
    "sg:address":"Via C. Zatti 23 42100 Reggio Emilia",
    "sg:classifiers":[
        {
            "category":"Manufacturing",
            "subcategory":"Rubber & Plastics",
            "type":"Manufacturing & Wholesale Goods"
        }
    ],
    "sg:phone":"+39 0522 551136",
    "sg:postcode":"42100",
    "sg:province":"Reggio Nell'Emilia",
    "sg:tags":[
        "technical",
        "item",
        "us"
    ],
    "sg:website":"www.stranirigomma.it",
    "wof:name":"Stranieri Amadeo Impresa Individuale",
    "wof:placetype":"venue"
},
  "geometry": {"coordinates":[10.650412,44.681637],"type":"Point"}
}