{
  "type": "Feature",
  "properties": {
    "iso:country":"IT",
    "sg:address":"21044 Cavaria Con Premezzo",
    "sg:city":"Cavaria con Premezzo",
    "sg:orig_category":"Impiantistica E Prodotti Tecnologici Per Edilizia",
    "sg:phone":"+39 0331 212904",
    "sg:postcode":"21044",
    "sg:province":"Varese",
    "wof:name":"Elecon Srl",
    "wof:placetype":"venue"
},
  "geometry": {"coordinates":[8.804413,45.697392],"type":"Point"}
}