{
  "type": "Feature",
  "properties": {
    "iso:country":"IT",
    "sg:address":"21047 Saronno",
    "sg:city":"Saronno",
    "sg:orig_category":"Gioielleria, Oreficeria E Argenteria. Shopping",
    "sg:phone":"+39 02 960 9640",
    "sg:postcode":"21047",
    "sg:province":"Varese",
    "wof:name":"Il Mondo Di Alice Di Ambrosi Arianna",
    "wof:placetype":"venue"
},
  "geometry": {"coordinates":[9.0269041061,45.6214561462],"type":"Point"}
}