{
  "type": "Feature",
  "properties": {
    "addr:full":"20090 Assago Assago Milano 20090",
    "addr:postcode":"20090;20090",
    "addr:street":"Assago",
    "iso:country":"IT",
    "sg:address":"20090 Assago",
    "sg:city":"Assago",
    "sg:orig_category":"Pubblicita', Marketing E Comunicazione",
    "sg:phone":"+39 02 4571 2189",
    "sg:postcode":"20090",
    "sg:province":"Milano",
    "sg:website":"http://www.gfastudio.com",
    "wof:name":"G.f.a. Studio Di Cagnazzi",
    "wof:placetype":"venue"
},
  "geometry": {"coordinates":[9.1251535416,45.403465271],"type":"Point"}
}