{
  "type": "Feature",
  "properties": {
    "iso:country":"IT",
    "sg:address":"12, Viale Rimembranze 21052 Busto Arsizio",
    "sg:city":"Busto Arsizio",
    "sg:classifiers":[
        {
            "category":"Shopping",
            "subcategory":"Crafts & Fabrics",
            "type":"Retail Goods"
        }
    ],
    "sg:phone":"+39 0331 632716",
    "sg:postcode":"21052",
    "sg:province":"Varese",
    "wof:name":"Tessitura Giovanni Carnaghi",
    "wof:placetype":"venue"
},
  "geometry": {"coordinates":[8.8394470215,45.6097297668],"type":"Point"}
}