{
  "type": "Feature",
  "properties": {
    "iso:country":"IT",
    "sg:address":"56121 Pisa",
    "sg:city":"Pisa",
    "sg:orig_category":"Elettrotecnica Industriale, Prodotti E Apparecchiature",
    "sg:phone":"+39 050 313371",
    "sg:postcode":"56121",
    "sg:province":"Pisa",
    "wof:name":"Mitsuba F.n. Europe Spa",
    "wof:placetype":"venue"
},
  "geometry": {"coordinates":[10.347248,43.589203],"type":"Point"}
}