{
  "type": "Feature",
  "properties": {
    "iso:country":"IT",
    "sg:address":"20121 Milano",
    "sg:city":"Milano",
    "sg:orig_category":"Servizi E Lavori Per Agricoltura E Zootecnia. Servizi E Lavori Per Ecologia E Smaltimento Rifiuti",
    "sg:phone":"+39 02 657 1729",
    "sg:postcode":"20121",
    "sg:province":"Milano",
    "wof:name":"Consorzio Dell'adda",
    "wof:placetype":"venue"
},
  "geometry": {"coordinates":[9.186909,45.480476],"type":"Point"}
}