{
  "type": "Feature",
  "properties": {
    "iso:country":"IT",
    "sg:address":"20052 Monza",
    "sg:city":"Monza",
    "sg:orig_category":"Prodotti Chimici Secondari. Macchine E Forniture Per Ecologia E Smaltimento Rifiuti",
    "sg:phone":"+39 039 836185",
    "sg:postcode":"20052",
    "sg:province":"Milano",
    "wof:name":"Denisoer Di Forte Felice",
    "wof:placetype":"venue"
},
  "geometry": {"coordinates":[9.2204313278,45.5365982056],"type":"Point"}
}