{
  "type": "Feature",
  "properties": {
    "iso:country":"IT",
    "sg:address":"04100 Latina",
    "sg:city":"Latina",
    "sg:orig_category":"Studi E Consulenze Amministrative, Commerciali E Aziendali. Banche E Servizi Finanziari. Agenzie D'affari E Servizi Commerciali. Consulenze Tecniche, Amministrative E Perizie",
    "sg:phone":"+39 0773 473509",
    "sg:postcode":"04100",
    "sg:province":"Latina",
    "sg:website":"http://www.apconsulting.it",
    "wof:name":"Ap Consulting Sas Di Patane' Alessandro",
    "wof:placetype":"venue"
},
  "geometry": {"coordinates":[12.874495,41.452148],"type":"Point"}
}