{
  "type": "Feature",
  "properties": {
    "addr:full":"09127 Cagliari Cagliari Cagliari 09127",
    "addr:postcode":"09127;09127",
    "iso:country":"IT",
    "sg:address":"09127 Cagliari",
    "sg:city":"Cagliari",
    "sg:orig_category":"Arredamenti E Mobili Professionali. Complementi Di Arredamento",
    "sg:phone":"+39 070 654989",
    "sg:postcode":"09127",
    "sg:province":"Cagliari",
    "wof:name":"Apostolato Liturgico Suore Pie Discepole Del D. M.",
    "wof:placetype":"venue"
},
  "geometry": {"coordinates":[9.122096,39.215393],"type":"Point"}
}