{
  "type": "Feature",
  "properties": {
    "iso:country":"IT",
    "sg:address":"15100 Alessandria",
    "sg:city":"Alessandria",
    "sg:orig_category":"Non-classified Establishments",
    "sg:phone":"+39 0131 223811",
    "sg:postcode":"15100",
    "sg:province":"Alessandria",
    "wof:name":"Il Giocandolo Sas",
    "wof:placetype":"venue"
},
  "geometry": {"coordinates":[8.628011,44.913807],"type":"Point"}
}