{
  "type": "Feature",
  "properties": {
    "addr:full":"13881 Cavagli\u00e0 Biella 13881",
    "addr:postcode":"13881;13881",
    "iso:country":"IT",
    "sg:address":"13881 Cavagli\u00e0",
    "sg:orig_category":"Climatizzazione E Condizionamento, Apparecchiature E Servizi",
    "sg:phone":"+39 0161 966514",
    "sg:postcode":"13881",
    "sg:province":"Biella",
    "wof:name":"I.di.erre Di Ramella Angelo",
    "wof:placetype":"venue"
},
  "geometry": {"coordinates":[8.046866,45.559647],"type":"Point"}
}