{
  "type": "Feature",
  "properties": {
    "iso:country":"IT",
    "sg:address":"28060 Cureggio",
    "sg:city":"Cureggio",
    "sg:orig_category":"Cartotecnica E Servizi. Articoli Per Imballaggio E Confezionamento",
    "sg:phone":"+39 0322 839036",
    "sg:postcode":"28060",
    "sg:province":"Novara",
    "wof:name":"La Nuova Scatola Di Mei & Marica Snc",
    "wof:placetype":"venue"
},
  "geometry": {"coordinates":[8.466863,45.670624],"type":"Point"}
}