{
  "type": "Feature",
  "properties": {
    "addr:full":"46042 Castelgoffredo Mantova 46042",
    "addr:postcode":"46042;46042",
    "iso:country":"IT",
    "sg:address":"46042 Castelgoffredo",
    "sg:orig_category":"Arredo Cucina Ed Elettrodomestici. Elettrodomestici",
    "sg:phone":"+39 0376 779131",
    "sg:postcode":"46042",
    "sg:province":"Mantova",
    "wof:name":"Termoidraulica Di Rossitti Angelo",
    "wof:placetype":"venue"
},
  "geometry": {"coordinates":[10.476002,45.29792],"type":"Point"}
}