{
  "type": "Feature",
  "properties": {
    "addr:full":"20081 Abbiategrasso Abbiategrasso Milano 20081",
    "addr:postcode":"20081;20081",
    "iso:country":"IT",
    "sg:address":"20081 Abbiategrasso",
    "sg:city":"Abbiategrasso",
    "sg:orig_category":"Motori Elettrici E Componenti",
    "sg:phone":"+39 02 9496 4134",
    "sg:postcode":"20081",
    "sg:province":"Milano",
    "sg:website":"http://www.comelmar.it",
    "wof:name":"Comelmar Italia Spa",
    "wof:placetype":"venue"
},
  "geometry": {"coordinates":[9.201628685,45.4251785278],"type":"Point"}
}