{
  "type": "Feature",
  "properties": {
    "addr:full":"33050 Marano Lagunare Marano Lagunare Udine 33050",
    "addr:postcode":"33050;33050",
    "iso:country":"IT",
    "sg:address":"33050 Marano Lagunare",
    "sg:city":"Marano Lagunare",
    "sg:classifiers":[
        {
            "category":"Restaurant",
            "type":"Food & Drink"
        }
    ],
    "sg:phone":"+39 0431 67019",
    "sg:postcode":"33050",
    "sg:province":"Udine",
    "sg:tags":[
        "auxiliary",
        "entertainment",
        "premises",
        "related",
        "catering",
        "similar",
        "public",
        "restaurants"
    ],
    "wof:name":"Trattoria Alla Laguna Vedova Raddi Di Della Ricca Mara E C. Sas",
    "wof:placetype":"venue"
},
  "geometry": {"coordinates":[13.167517,45.765091],"type":"Point"}
}