{
  "type": "Feature",
  "properties": {
    "iso:country":"IT",
    "sg:address":"25065 Lumezzane",
    "sg:city":"Lumezzane",
    "sg:orig_category":"Acciaierie E Fonderie",
    "sg:phone":"+39 030 897 0416",
    "sg:postcode":"25065",
    "sg:province":"Brescia",
    "wof:name":"Pressafusione Moretti Di Moretti Domenico & C. Snc",
    "wof:placetype":"venue"
},
  "geometry": {"coordinates":[10.21873,45.604397],"type":"Point"}
}