{
  "type": "Feature",
  "properties": {
    "iso:country":"IT",
    "sg:address":"5, Via Curiel 40069 Zola Predosa",
    "sg:city":"Zola",
    "sg:classifiers":[
        {
            "category":"Shopping",
            "subcategory":"Crafts & Fabrics",
            "type":"Retail Goods"
        }
    ],
    "sg:phone":"+39 39051752402",
    "sg:postcode":"40069",
    "sg:province":"Bologna",
    "wof:name":"Marcel Art Stamperia (s.r.l.)",
    "wof:placetype":"venue"
},
  "geometry": {"coordinates":[11.2484817505,44.4954452515],"type":"Point"}
}