{
  "type": "Feature",
  "properties": {
    "iso:country":"IT",
    "sg:address":"20060 Pozzo D'adda",
    "sg:orig_category":"Lavorazioni Meccaniche E Servizi",
    "sg:phone":"+39 02 9096 9977",
    "sg:postcode":"20060",
    "sg:province":"Milano",
    "wof:name":"Gisonno Antonio",
    "wof:placetype":"venue"
},
  "geometry": {"coordinates":[9.558848,45.609005],"type":"Point"}
}