{
  "type": "Feature",
  "properties": {
    "addr:full":"Via Roma 23 33070 Caneva Caneva Pordenone 33070",
    "addr:housenumber":"23",
    "addr:postcode":"33070;33070",
    "addr:street":"Via Roma",
    "iso:country":"IT",
    "sg:address":"Via Roma 23 33070 Caneva",
    "sg:city":"Caneva",
    "sg:classifiers":[
        {
            "category":"Home & Garden",
            "subcategory":"Building Materials",
            "type":"Retail Goods"
        }
    ],
    "sg:phone":"+39 0434 79007",
    "sg:postcode":"33070",
    "sg:province":"Pordenone",
    "sg:tags":[
        "slab",
        "marble"
    ],
    "sg:website":"www.allegranzimarmisti.com",
    "wof:name":"Allegranzi Marmisti Srl",
    "wof:placetype":"venue"
},
  "geometry": {"coordinates":[12.452446,45.969627],"type":"Point"}
}