{
  "type": "Feature",
  "properties": {
    "addr:full":"36066 Sandrigo Sandrigo Vicenza 36066",
    "addr:postcode":"36066;36066",
    "iso:country":"IT",
    "sg:address":"36066 Sandrigo",
    "sg:city":"Sandrigo",
    "sg:orig_category":"Acciai Inossidabili - Lavorazione",
    "sg:phone":"+39 0444 658866",
    "sg:postcode":"36066",
    "sg:province":"Vicenza",
    "wof:name":"Centofante Giorgio",
    "wof:placetype":"venue"
},
  "geometry": {"coordinates":[11.587605,45.600948],"type":"Point"}
}