{
  "type": "Feature",
  "properties": {
    "addr:full":"5, Via Guido Rossa 31059 Zero Branco Zero Branco Treviso 31059",
    "addr:postcode":"31059;31059",
    "addr:street":"Via Guido Rossa",
    "iso:country":"IT",
    "sg:address":"5, Via Guido Rossa 31059 Zero Branco",
    "sg:city":"Zero Branco",
    "sg:classifiers":[
        {
            "category":"Wholesale",
            "subcategory":"Drugs",
            "type":"Manufacturing & Wholesale Goods"
        }
    ],
    "sg:phone":"+39 0422 485666",
    "sg:postcode":"31059",
    "sg:province":"Treviso",
    "sg:tags":[
        "chemical",
        "pharmaceutical"
    ],
    "wof:name":"Requale & Regas S.r.l.",
    "wof:placetype":"venue"
},
  "geometry": {"coordinates":[12.151809,45.595345],"type":"Point"}
}