{
  "type": "Feature",
  "properties": {
    "addr:full":"10123 Torino Torino Torino 10123",
    "addr:postcode":"10123;10123",
    "iso:country":"IT",
    "sg:address":"10123 Torino",
    "sg:city":"Torino",
    "sg:orig_category":"Articoli Regalo - Vendita Al Dettaglio",
    "sg:phone":"+39 011 530165",
    "sg:postcode":"10123",
    "sg:province":"Torino",
    "wof:name":"Porto Castello",
    "wof:placetype":"venue"
},
  "geometry": {"coordinates":[7.685569,45.071026],"type":"Point"}
}