{
  "type": "Feature",
  "properties": {
    "iso:country":"IT",
    "sg:address":"39, Via Tribolina 24064 Grumello Del Monte",
    "sg:city":"Grumello del Monte",
    "sg:classifiers":[
        {
            "category":"Manufacturing",
            "subcategory":"Rubber & Plastics",
            "type":"Manufacturing & Wholesale Goods"
        }
    ],
    "sg:phone":"+39 39035832422",
    "sg:postcode":"24064",
    "sg:province":"Bergamo",
    "wof:name":"Robecchi S.a.s.",
    "wof:placetype":"venue"
},
  "geometry": {"coordinates":[9.8834285736,45.6285743713],"type":"Point"}
}