{
  "type": "Feature",
  "properties": {
    "addr:full":"332, V. Aurelia 00165 Roma Roma Roma 00165",
    "addr:housenumber":"332",
    "addr:postcode":"00165;00165",
    "addr:street":"V. Aurelia",
    "iso:country":"IT",
    "sg:address":"332, V. Aurelia 00165 Roma",
    "sg:city":"Roma",
    "sg:orig_category":"Miscellaneous Products",
    "sg:phone":"+39 06 6601 8069",
    "sg:postcode":"00165",
    "sg:province":"Roma",
    "sg:website":"http://www.lorenfa.com",
    "wof:name":"Lorenfa Di Simeone Fabio",
    "wof:placetype":"venue"
},
  "geometry": {"coordinates":[12.4342813492,41.8974609375],"type":"Point"}
}