{
  "type": "Feature",
  "properties": {
    "iso:country":"IT",
    "sg:address":"20052 Monza",
    "sg:city":"Monza",
    "sg:orig_category":"Studi E Consulenze Amministrative, Commerciali E Aziendali. Consulenze Tecniche, Amministrative E Perizie",
    "sg:phone":"+39 039 230 0117",
    "sg:postcode":"20052",
    "sg:province":"Milano",
    "sg:website":"http://www.colombopaghemonza.org",
    "wof:name":"Colombo Antonio",
    "wof:placetype":"venue"
},
  "geometry": {"coordinates":[9.177588,45.46003],"type":"Point"}
}