{
  "type": "Feature",
  "properties": {
    "addr:full":"2, Via Umbria 42100 Reggio Emilia Reggio Nell'Emilia 42100",
    "addr:postcode":"42100;42100",
    "addr:street":"Via Umbria",
    "iso:country":"IT",
    "sg:address":"2, Via Umbria 42100 Reggio Emilia",
    "sg:classifiers":[
        {
            "category":"Manufacturing",
            "subcategory":"Wood Products",
            "type":"Manufacturing & Wholesale Goods"
        }
    ],
    "sg:phone":"+39 0522 511474",
    "sg:postcode":"42100",
    "sg:province":"Reggio Nell'Emilia",
    "sg:tags":[
        "furniture"
    ],
    "wof:name":"G.m.t. (s.r.l.)",
    "wof:placetype":"venue"
},
  "geometry": {"coordinates":[10.6512,44.720303],"type":"Point"}
}