{
  "type": "Feature",
  "properties": {
    "iso:country":"IT",
    "sg:address":"42, Corso Vittorio Emanuele Ii 10123 Torino",
    "sg:city":"Torino",
    "sg:classifiers":[
        {
            "category":"Food & Beverages",
            "subcategory":"Groceries & Convenience Stores",
            "type":"Retail Goods"
        }
    ],
    "sg:phone":"+39 011 810 8111",
    "sg:postcode":"10123",
    "sg:province":"Torino",
    "sg:tags":[
        "drink"
    ],
    "wof:name":"Martini & Rossi S.p.a.",
    "wof:placetype":"venue"
},
  "geometry": {"coordinates":[7.683095,45.06142],"type":"Point"}
}