{
  "type": "Feature",
  "properties": {
    "iso:country":"IT",
    "sg:address":"48018 Faenza",
    "sg:city":"Faenza",
    "sg:orig_category":"Cinematografia E Radiotelevisione. Pubblicita', Marketing E Comunicazione",
    "sg:phone":"+39 0546 30135",
    "sg:postcode":"48018",
    "sg:province":"Ravenna",
    "wof:name":"Tele 1 Srl",
    "wof:placetype":"venue"
},
  "geometry": {"coordinates":[11.94079,44.262558],"type":"Point"}
}