{
  "type": "Feature",
  "properties": {
    "iso:country":"IT",
    "sg:address":"19, Viale Della Regione Veneto 35127 Padova",
    "sg:city":"Padova",
    "sg:classifiers":[
        {
            "category":"Professional",
            "subcategory":"Engineering",
            "type":"Services"
        }
    ],
    "sg:phone":"+39 39049760777",
    "sg:postcode":"35127",
    "sg:province":"Padova",
    "sg:tags":[
        "machine",
        "-",
        "mechanical"
    ],
    "wof:name":"Vollmer Italia S.r.l.",
    "wof:placetype":"venue"
},
  "geometry": {"coordinates":[11.956322,45.387569],"type":"Point"}
}