{
  "type": "Feature",
  "properties": {
    "iso:country":"IT",
    "sg:address":"63014 Montegranaro",
    "sg:city":"Montegranaro",
    "sg:orig_category":"Servizi Al Turismo. Servizi Ausiliari Per Il Trasporto",
    "sg:phone":"+39 0734 892444",
    "sg:postcode":"63014",
    "sg:province":"Ascoli Piceno",
    "wof:name":"Ibis Viaggi E Turismo Di Alberto Coscia & C. Snc",
    "wof:placetype":"venue"
},
  "geometry": {"coordinates":[13.635718,43.233959],"type":"Point"}
}