{
  "type": "Feature",
  "properties": {
    "iso:country":"IT",
    "sg:address":"25049 Iseo",
    "sg:city":"Iseo",
    "sg:orig_category":"Arredo Bagno Ed Idrosanitari",
    "sg:phone":"+39 030 989459",
    "sg:postcode":"25049",
    "sg:province":"Brescia",
    "sg:website":"http://www.stamsrl.it",
    "wof:name":"Stam Srl - Rubinetterie E Accessori",
    "wof:placetype":"venue"
},
  "geometry": {"coordinates":[10.002266,45.660454],"type":"Point"}
}