{
  "type": "Feature",
  "properties": {
    "iso:country":"IT",
    "sg:address":"151, Via Leini 10036 Settimo Torinese",
    "sg:city":"Settimo Torinese",
    "sg:classifiers":[
        {
            "category":"Manufacturing",
            "subcategory":"Metals",
            "type":"Manufacturing & Wholesale Goods"
        }
    ],
    "sg:phone":"+39 011 897 7780",
    "sg:postcode":"10036",
    "sg:province":"Torino",
    "sg:tags":[
        "metallurgy",
        "metalworking"
    ],
    "wof:name":"Providus (s.r.l.)",
    "wof:placetype":"venue"
},
  "geometry": {"coordinates":[7.7317194939,45.147895813],"type":"Point"}
}