{
  "type": "Feature",
  "properties": {
    "iso:country":"IT",
    "sg:address":"04100 Latina",
    "sg:city":"Latina",
    "sg:orig_category":"Alimentari - Produzione E Ingrosso",
    "sg:phone":"+39 0773 4681",
    "sg:postcode":"04100",
    "sg:province":"Latina",
    "wof:name":"M.i.d.a.l. Spa",
    "wof:placetype":"venue"
},
  "geometry": {"coordinates":[12.944578,41.524944],"type":"Point"}
}