{
  "type": "Feature",
  "properties": {
    "addr:full":"00138 Roma Roma Roma 00138",
    "addr:postcode":"00138;00138",
    "iso:country":"IT",
    "sg:address":"00138 Roma",
    "sg:city":"Roma",
    "sg:orig_category":"Pubblicita', Marketing E Comunicazione",
    "sg:phone":"+39 06 881 4559",
    "sg:postcode":"00138",
    "sg:province":"Roma",
    "wof:name":"Vision System",
    "wof:placetype":"venue"
},
  "geometry": {"coordinates":[12.5272417068,41.9940490723],"type":"Point"}
}