{
  "type": "Feature",
  "properties": {
    "iso:country":"IT",
    "sg:address":"80078 Pozzuoli",
    "sg:city":"Pozzuoli",
    "sg:orig_category":"Legno E Semilavorati. Manufatti Edili E Prefabbricati",
    "sg:phone":"+39 081 526 2913",
    "sg:postcode":"80078",
    "sg:province":"Napoli",
    "wof:name":"Sicurtraffic Srl",
    "wof:placetype":"venue"
},
  "geometry": {"coordinates":[14.119798,40.854553],"type":"Point"}
}