{
  "type": "Feature",
  "properties": {
    "iso:country":"IT",
    "sg:address":"20122 Milano",
    "sg:city":"Milano",
    "sg:orig_category":"Servizi E Lavori Per Agricoltura E Zootecnia. Consulenze Tecniche, Amministrative E Perizie",
    "sg:phone":"+39 02 7631 8315",
    "sg:postcode":"20122",
    "sg:province":"Milano",
    "wof:name":"Fassati Dr. Leonardo",
    "wof:placetype":"venue"
},
  "geometry": {"coordinates":[9.197976,45.46447],"type":"Point"}
}