{
  "type": "Feature",
  "properties": {
    "iso:country":"IT",
    "sg:address":"42/44, Via Goito 20035 Lissone",
    "sg:city":"Lissone",
    "sg:classifiers":[
        {
            "category":"Manufacturing",
            "subcategory":"Tools & Machinery",
            "type":"Manufacturing & Wholesale Goods"
        }
    ],
    "sg:phone":"+39 39039461412",
    "sg:postcode":"20035",
    "sg:province":"Milano",
    "sg:tags":[
        "environment",
        "equipment",
        "-"
    ],
    "wof:name":"Tekno Impianti Srl",
    "wof:placetype":"venue"
},
  "geometry": {"coordinates":[9.229798,45.614952],"type":"Point"}
}