{
  "type": "Feature",
  "properties": {
    "addr:full":"18, Via Fenil Novo 37036 San Martino Buon Albergo San Martino Buon Albergo Verona 37036",
    "addr:postcode":"37036;buon albergo;37036",
    "addr:street":"Via Fenil Novo",
    "iso:country":"IT",
    "sg:address":"18, Via Fenil Novo 37036 San Martino Buon Albergo",
    "sg:city":"San Martino Buon Albergo",
    "sg:classifiers":[
        {
            "category":"Professional",
            "subcategory":"Engineering",
            "type":"Services"
        }
    ],
    "sg:phone":"+39 045 878 1240",
    "sg:postcode":"37036",
    "sg:province":"Verona",
    "sg:tags":[
        "machine",
        "-",
        "mechanical"
    ],
    "wof:name":"Of.e.m. Srl",
    "wof:placetype":"venue"
},
  "geometry": {"coordinates":[11.088177,45.416142],"type":"Point"}
}