{
  "type": "Feature",
  "properties": {
    "addr:full":"46018 Sabbioneta Sabbioneta Mantova 46018",
    "addr:postcode":"46018;46018",
    "iso:country":"IT",
    "sg:address":"46018 Sabbioneta",
    "sg:city":"Sabbioneta",
    "sg:orig_category":"Forniture Per Attivita' Industriali",
    "sg:phone":"+39 0375 52602",
    "sg:postcode":"46018",
    "sg:province":"Mantova",
    "wof:name":"Bonazzi Patrizia",
    "wof:placetype":"venue"
},
  "geometry": {"coordinates":[10.7657976151,45.1461830139],"type":"Point"}
}