{
  "type": "Feature",
  "properties": {
    "iso:country":"IT",
    "sg:address":"Via Ponte Di Costozza 12, 36023 Longare, Vi",
    "sg:city":"Longare",
    "sg:classifiers":[
        {
            "category":"Banks & Credit Unions",
            "subcategory":"Bank",
            "type":"Services"
        }
    ],
    "sg:postcode":"36023",
    "sg:province":"Vicenza",
    "wof:name":"Banca Del Centroveneto-credito Cooperativo Scarl Longare (vi)",
    "wof:placetype":"venue"
},
  "geometry": {"coordinates":[11.610142,45.465981],"type":"Point"}
}