{
  "type": "Feature",
  "properties": {
    "addr:full":"10, Via Vespucci Amerigo 20016 Pero Pero Milano 20016",
    "addr:postcode":"20016;20016",
    "addr:street":"Via Vespucci Amerigo",
    "iso:country":"IT",
    "sg:address":"10, Via Vespucci Amerigo 20016 Pero",
    "sg:city":"Pero",
    "sg:classifiers":[
        {
            "category":"Real Estate",
            "subcategory":"Surveying",
            "type":"Services"
        }
    ],
    "sg:phone":"+39 39023393161",
    "sg:postcode":"20016",
    "sg:province":"Milano",
    "sg:tags":[
        "equipment",
        "material",
        "good",
        "-",
        "handling"
    ],
    "wof:name":"Hydronic Lift Spa",
    "wof:placetype":"venue"
},
  "geometry": {"coordinates":[9.078194,45.505222],"type":"Point"}
}