{
  "type": "Feature",
  "properties": {
    "iso:country":"IT",
    "sg:address":"25010 Acquafredda",
    "sg:city":"Acquafredda",
    "sg:orig_category":"Zootecnia E Pesca, Allevamento Piccoli Animali",
    "sg:phone":"+39 030 996 7832",
    "sg:postcode":"25010",
    "sg:province":"Brescia",
    "wof:name":"Faganelli Romano",
    "wof:placetype":"venue"
},
  "geometry": {"coordinates":[10.301889,45.470757],"type":"Point"}
}