{
  "type": "Feature",
  "properties": {
    "addr:full":"5, Via Lombardia 22074 Lomazzo Lomazzo Como 22074",
    "addr:postcode":"22074;22074",
    "addr:street":"Via Lombardia",
    "iso:country":"IT",
    "sg:address":"5, Via Lombardia 22074 Lomazzo",
    "sg:city":"Lomazzo",
    "sg:classifiers":[
        {
            "category":"Sports & Exercise",
            "subcategory":"Playing Field",
            "type":"Entertainment"
        }
    ],
    "sg:phone":"+39 02 9637 0081",
    "sg:postcode":"22074",
    "sg:province":"Como",
    "sg:tags":[
        "game"
    ],
    "wof:name":"Galvas G.p. (s.p.a.)",
    "wof:placetype":"venue"
},
  "geometry": {"coordinates":[9.002871,45.70895],"type":"Point"}
}