{
  "type": "Feature",
  "properties": {
    "addr:full":"22, Via Mancini Francesco 05100 Terni Terni Terni 05100",
    "addr:postcode":"05100;05100",
    "addr:street":"Via Mancini Francesco",
    "iso:country":"IT",
    "sg:address":"22, Via Mancini Francesco 05100 Terni",
    "sg:city":"Terni",
    "sg:classifiers":[
        {
            "category":"Manufacturing",
            "subcategory":"Lumber",
            "type":"Manufacturing & Wholesale Goods"
        }
    ],
    "sg:phone":"+39 0744 401340",
    "sg:postcode":"05100",
    "sg:province":"Terni",
    "sg:tags":[
        "wood"
    ],
    "wof:name":"Import Export Trade S.r.l.",
    "wof:placetype":"venue"
},
  "geometry": {"coordinates":[12.625197,42.572308],"type":"Point"}
}