{
  "type": "Feature",
  "properties": {
    "iso:country":"IT",
    "sg:address":"414, Viale Isonzo 88100 Catanzaro",
    "sg:city":"Catanzaro",
    "sg:classifiers":[
        {
            "category":"Manufacturing",
            "subcategory":"Lumber",
            "type":"Manufacturing & Wholesale Goods"
        }
    ],
    "sg:phone":"+39 0961 780391",
    "sg:postcode":"88100",
    "sg:province":"Catanzaro",
    "sg:tags":[
        "wood"
    ],
    "wof:name":"Borelli Legnami Sas Di Borelli Carmine E Fratelli",
    "wof:placetype":"venue"
},
  "geometry": {"coordinates":[16.603432,38.854233],"type":"Point"}
}