{
  "type": "Feature",
  "properties": {
    "iso:country":"IT",
    "sg:address":"35135 Padova",
    "sg:city":"Padova",
    "sg:orig_category":"Fognature",
    "sg:phone":"+39 049 864 8339",
    "sg:postcode":"35135",
    "sg:province":"Padova",
    "wof:name":"Esegio Spurghi Di Esegio Sergio",
    "wof:placetype":"venue"
},
  "geometry": {"coordinates":[11.6568784714,44.9779129028],"type":"Point"}
}