{
  "type": "Feature",
  "properties": {
    "iso:country":"IT",
    "sg:address":"26016 Spino D'adda",
    "sg:orig_category":"Prodotti E Manufatti In Materie Plastiche",
    "sg:phone":"+39 0373 980293",
    "sg:postcode":"26016",
    "sg:province":"Cremona",
    "wof:name":"Europlast Srl",
    "wof:placetype":"venue"
},
  "geometry": {"coordinates":[9.4749946594,45.4032897949],"type":"Point"}
}