{
  "type": "Feature",
  "properties": {
    "addr:full":"25020 Flero Flero Brescia 25020",
    "addr:postcode":"25020;25020",
    "iso:country":"IT",
    "sg:address":"25020 Flero",
    "sg:city":"Flero",
    "sg:orig_category":"Autotrasporti",
    "sg:phone":"+39 030 358 0513",
    "sg:postcode":"25020",
    "sg:province":"Brescia",
    "wof:name":"Autotrasporti Sirio Srl",
    "wof:placetype":"venue"
},
  "geometry": {"coordinates":[10.16216,45.493702],"type":"Point"}
}