{
  "type": "Feature",
  "properties": {
    "addr:full":"39054 Renon Renon Bolzano/Bozen 39054",
    "addr:postcode":"39054;39054",
    "iso:country":"IT",
    "sg:address":"39054 Renon",
    "sg:city":"Renon",
    "sg:orig_category":"Serramenti Ed Infissi",
    "sg:phone":"+39 0471 296611",
    "sg:postcode":"39054",
    "sg:province":"Bolzano/Bozen",
    "sg:website":"http://www.finstral.com",
    "wof:name":"Finstral Spa",
    "wof:placetype":"venue"
},
  "geometry": {"coordinates":[11.453668,46.519993],"type":"Point"}
}