{
  "type": "Feature",
  "properties": {
    "iso:country":"IT",
    "sg:address":"95129 Catania",
    "sg:city":"Catania",
    "sg:orig_category":"Servizi E Lavori Per Edilizia E Lavori Pubblici",
    "sg:phone":"+39 095 746 3388",
    "sg:postcode":"95129",
    "sg:province":"Catania",
    "wof:name":"Bottega Dell'imbianchino",
    "wof:placetype":"venue"
},
  "geometry": {"coordinates":[15.10279,37.513649],"type":"Point"}
}