{
  "type": "Feature",
  "properties": {
    "iso:country":"IT",
    "sg:address":"20090 Vimodrone",
    "sg:city":"Vimodrone",
    "sg:orig_category":"Automazione E Macchine Per Ufficio. Servizi Ausiliari Di Certificati, Riproduzioni, Disegni E Foto",
    "sg:phone":"+39 02 265 0626",
    "sg:postcode":"20090",
    "sg:province":"Milano",
    "wof:name":"Copyter Di Zammaretti Mario",
    "wof:placetype":"venue"
},
  "geometry": {"coordinates":[9.268282,45.512272],"type":"Point"}
}