{
  "type": "Feature",
  "properties": {
    "iso:country":"IT",
    "sg:address":"Via Bonicalza 142 21012 Cassano Magnago",
    "sg:city":"Cassano Magnago",
    "sg:orig_category":"Dosing Devices For Die Casting Machines",
    "sg:phone":"+39 0331 203427",
    "sg:postcode":"21012",
    "sg:province":"Varese",
    "sg:website":"www.omb-bondolin.com",
    "wof:name":"Omb Di Brondolin Davide E Brondolin Lorella & C. Sas",
    "wof:placetype":"venue"
},
  "geometry": {"coordinates":[8.846581,45.655064],"type":"Point"}
}