{
  "type": "Feature",
  "properties": {
    "iso:country":"IT",
    "sg:address":"06063 Magione",
    "sg:city":"Magione",
    "sg:orig_category":"Zootecnia E Pesca, Allevamento Piccoli Animali. Animali Domestici",
    "sg:phone":"+39 075 840592",
    "sg:postcode":"06063",
    "sg:province":"Perugia",
    "wof:name":"Allevamento Del Pastore Tedesco 'centro Italia' Di Pompieri Bruno",
    "wof:placetype":"venue"
},
  "geometry": {"coordinates":[12.186145,43.119774],"type":"Point"}
}