{
  "type": "Feature",
  "properties": {
    "addr:full":"36071 Arzignano Arzignano Vicenza 36071",
    "addr:postcode":"36071;36071",
    "iso:country":"IT",
    "sg:address":"36071 Arzignano",
    "sg:city":"Arzignano",
    "sg:orig_category":"Apparecchiature E Sistemi Per Magazzinaggio E Movimentazione. Servizi Di Magazzinaggio E Movimentazione",
    "sg:phone":"+39 0444 675609",
    "sg:postcode":"36071",
    "sg:province":"Vicenza",
    "wof:name":"Autotrasporti F. Lli Ziggiotti Snc",
    "wof:placetype":"venue"
},
  "geometry": {"coordinates":[11.650844574,45.7217178345],"type":"Point"}
}