{
  "type": "Feature",
  "properties": {
    "addr:full":"24, Via Boccacanale Di Santo Stefano 44100 Ferrara Ferrara Ferrara 44100",
    "addr:postcode":"44100;44100",
    "addr:street":"Via Boccacanale Di;Stefano",
    "iso:country":"IT",
    "sg:address":"24, Via Boccacanale Di Santo Stefano 44100 Ferrara",
    "sg:city":"Ferrara",
    "sg:classifiers":[
        {
            "category":"Manufacturing",
            "subcategory":"Printing",
            "type":"Manufacturing & Wholesale Goods"
        }
    ],
    "sg:phone":"+39 0532 240762",
    "sg:postcode":"44100",
    "sg:province":"Ferrara",
    "sg:tags":[
        "publishing"
    ],
    "wof:name":"Voce Di Ferrara - Comacchio",
    "wof:placetype":"venue"
},
  "geometry": {"coordinates":[11.6164398193,44.8361968994],"type":"Point"}
}