{
  "type": "Feature",
  "properties": {
    "iso:country":"IT",
    "sg:address":"Via Orelli 6 24123 Bergamo",
    "sg:city":"Bergamo",
    "sg:classifiers":[
        {
            "category":"Ice Cream",
            "type":"Food & Drink"
        }
    ],
    "sg:phone":"+39 035 255275",
    "sg:postcode":"24123",
    "sg:province":"Bergamo",
    "sg:tags":[
        "ice-cream",
        "cone"
    ],
    "sg:website":"www.ostificioprealpino.com",
    "wof:name":"Ostificio Prealpino Di A.minetti E C Snc",
    "wof:placetype":"venue"
},
  "geometry": {"coordinates":[9.65698,45.690491],"type":"Point"}
}