{
  "type": "Feature",
  "properties": {
    "iso:country":"IT",
    "sg:address":"Via D. Chiesa, 20; Grosseto; 58100",
    "sg:city":"Grosseto",
    "sg:classifiers":[
        {
            "category":"Banks & Credit Unions",
            "subcategory":"Bank",
            "type":"Services"
        }
    ],
    "sg:phone":"+39 0564 20384",
    "sg:postcode":"58100",
    "sg:province":"Grosseto",
    "wof:name":"Banco Popolare Di Novara",
    "wof:placetype":"venue"
},
  "geometry": {"coordinates":[11.113712,42.764767],"type":"Point"}
}