{
  "type": "Feature",
  "properties": {
    "addr:full":"20149 Milano Milano Milano 20149",
    "addr:postcode":"20149;20149",
    "iso:country":"IT",
    "sg:address":"20149 Milano",
    "sg:city":"Milano",
    "sg:orig_category":"Dischi, Audio E Videocassette, Compact Disc - Produzione E Ingrosso",
    "sg:phone":"+39 02 3360 6113",
    "sg:postcode":"20149",
    "sg:province":"Milano",
    "sg:website":"http://www.studiobarzan.it",
    "wof:name":"Studio Barzan",
    "wof:placetype":"venue"
},
  "geometry": {"coordinates":[9.156221,45.486843],"type":"Point"}
}