{
  "type": "Feature",
  "properties": {
    "iso:country":"IT",
    "sg:address":"Via Napoli 92/98; Arzano",
    "sg:classifiers":[
        {
            "category":"Banks & Credit Unions",
            "subcategory":"Bank",
            "type":"Services"
        }
    ],
    "sg:phone":"+39 081 731 5455",
    "wof:name":"Banca Della Provincia, Di Napoli",
    "wof:placetype":"venue"
},
  "geometry": {"coordinates":[14.265429,40.911377],"type":"Point"}
}