{
  "type": "Feature",
  "properties": {
    "iso:country":"IT",
    "sg:address":"52, Via Croce Rossa 35129 Padova",
    "sg:city":"Padova",
    "sg:classifiers":[
        {
            "category":"Shopping",
            "subcategory":"Computers & Home Electronics",
            "type":"Retail Goods"
        }
    ],
    "sg:phone":"+39 049 807 7466",
    "sg:postcode":"35129",
    "sg:province":"Padova",
    "sg:tags":[
        "electronic",
        "electrical",
        "equipment"
    ],
    "wof:name":"Extel (s.r.l.)",
    "wof:placetype":"venue"
},
  "geometry": {"coordinates":[11.844167,45.397499],"type":"Point"}
}