{
  "type": "Feature",
  "properties": {
    "addr:full":"P. Vitt. Emanuele, 43; Giovinazzo; 70054 Giovinazzo Bari 70054",
    "addr:housenumber":"43",
    "addr:postcode":"70054;70054",
    "addr:street":"P.;Emanuele",
    "iso:country":"IT",
    "sg:address":"P. Vitt. Emanuele, 43; Giovinazzo; 70054",
    "sg:city":"Giovinazzo",
    "sg:classifiers":[
        {
            "category":"Banks & Credit Unions",
            "subcategory":"Bank",
            "type":"Services"
        }
    ],
    "sg:phone":"+39 080 894 2022",
    "sg:postcode":"70054",
    "sg:province":"Bari",
    "wof:name":"Banca Maldari Spa",
    "wof:placetype":"venue"
},
  "geometry": {"coordinates":[16.664501,41.162685],"type":"Point"}
}