{
  "type": "Feature",
  "properties": {
    "addr:full":"07046 Porto Torres Porto Torres Sassari 07046",
    "addr:housenumber":"07046",
    "addr:postcode":"07046",
    "addr:street":"Porto Torres Porto Torres",
    "iso:country":"IT",
    "sg:address":"07046 Porto Torres",
    "sg:city":"Porto Torres",
    "sg:orig_category":"Prodotti Chimici Di Base. Ospedali E Servizi Sanitari",
    "sg:phone":"+39 079 516166",
    "sg:postcode":"07046",
    "sg:province":"Sassari",
    "wof:name":"Sapio Produzione Idrogeno Ossigeno Srl",
    "wof:placetype":"venue"
},
  "geometry": {"coordinates":[8.3847589493,40.8247261047],"type":"Point"}
}