{
  "type": "Feature",
  "properties": {
    "addr:full":"20080 Casarile Casarile Milano 20080",
    "addr:postcode":"20080;20080",
    "iso:country":"IT",
    "sg:address":"20080 Casarile",
    "sg:city":"Casarile",
    "sg:orig_category":"Pubblica Amministrazione",
    "sg:phone":"+39 02 905 5641",
    "sg:postcode":"20080",
    "sg:province":"Milano",
    "wof:name":"Poste Italiane Spa",
    "wof:placetype":"venue"
},
  "geometry": {"coordinates":[9.0708580017,45.4215660095],"type":"Point"}
}