{
  "type": "Feature",
  "properties": {
    "iso:country":"IT",
    "sg:address":"23819 Primaluna",
    "sg:city":"Primaluna",
    "sg:orig_category":"Minuterie Metalliche E Ferramenta",
    "sg:phone":"+39 0341 979828",
    "sg:postcode":"23819",
    "sg:province":"Lecco",
    "wof:name":"Piloni Sergio",
    "wof:placetype":"venue"
},
  "geometry": {"coordinates":[9.4105939865,45.9860801697],"type":"Point"}
}