{
  "type": "Feature",
  "properties": {
    "addr:full":"1, Via Saladino 90134 Palermo Palermo Palermo 90134",
    "addr:postcode":"90134;90134",
    "addr:street":"Via Saladino",
    "iso:country":"IT",
    "sg:address":"1, Via Saladino 90134 Palermo",
    "sg:city":"Palermo",
    "sg:classifiers":[
        {
            "category":"Professional",
            "subcategory":"Printing & Photocopies",
            "type":"Services"
        }
    ],
    "sg:phone":"+39 091 651 1854",
    "sg:postcode":"90134",
    "sg:province":"Palermo",
    "wof:name":"Grafiche Renna S.r.l.",
    "wof:placetype":"venue"
},
  "geometry": {"coordinates":[13.3592510223,38.1128005981],"type":"Point"}
}