{
  "type": "Feature",
  "properties": {
    "iso:country":"IT",
    "sg:address":"59100 Prato",
    "sg:city":"Prato",
    "sg:orig_category":"Servizi Ausiliari Dei Mezzi Di Trasporto",
    "sg:phone":"+39 0574 25341",
    "sg:postcode":"59100",
    "sg:province":"Prato",
    "sg:website":"http://www.gellino.it",
    "wof:name":"Gellino Di Bartolini Mario",
    "wof:placetype":"venue"
},
  "geometry": {"coordinates":[11.085994,43.889221],"type":"Point"}
}