{
  "type": "Feature",
  "properties": {
    "iso:country":"IT",
    "sg:address":"13/a, Via Di Vittorio Giuseppe 10024 Moncalieri",
    "sg:city":"Moncalieri",
    "sg:classifiers":[
        {
            "category":"Professional",
            "subcategory":"Engineering",
            "type":"Services"
        }
    ],
    "sg:phone":"+39 011 681 3255",
    "sg:postcode":"10024",
    "sg:province":"Torino",
    "sg:tags":[
        "machine",
        "-",
        "mechanical"
    ],
    "wof:name":"Tewi (s.r.l.)",
    "wof:placetype":"venue"
},
  "geometry": {"coordinates":[7.648938,45.026222],"type":"Point"}
}