{
  "type": "Feature",
  "properties": {
    "iso:country":"IT",
    "sg:address":"298, Via Madonna 37051 Bovolone",
    "sg:city":"Bovolone",
    "sg:classifiers":[
        {
            "category":"Professional",
            "subcategory":"Printing & Photocopies",
            "type":"Services"
        }
    ],
    "sg:phone":"+39 045 690 1470",
    "sg:postcode":"37051",
    "sg:province":"Verona",
    "wof:name":"Tipolitografia Madonna",
    "wof:placetype":"venue"
},
  "geometry": {"coordinates":[11.1033468246,45.2683677673],"type":"Point"}
}