{
  "type": "Feature",
  "properties": {
    "iso:country":"IT",
    "sg:address":"20093 Cologno Monzese",
    "sg:city":"Cologno Monzese",
    "sg:orig_category":"Carta E Cartone - Produzione E Commercio",
    "sg:phone":"+39 02 2730 4060",
    "sg:postcode":"20093",
    "sg:province":"Milano",
    "wof:name":"Docas Srl",
    "wof:placetype":"venue"
},
  "geometry": {"coordinates":[9.273587,45.534359],"type":"Point"}
}