{
  "type": "Feature",
  "properties": {
    "iso:country":"IT",
    "sg:address":"00192 Roma",
    "sg:city":"Roma",
    "sg:orig_category":"Prodotti Finiti Stampati. Articoli Da Regalo. Arte Ed Artigianato Artistico. Shopping",
    "sg:phone":"+39 06 324 1673",
    "sg:postcode":"00192",
    "sg:province":"Roma",
    "wof:name":"M.2.m (s.r.l.)",
    "wof:placetype":"venue"
},
  "geometry": {"coordinates":[12.4609184265,41.9084854126],"type":"Point"}
}