{
  "type": "Feature",
  "properties": {
    "addr:full":"Via Del Macello 55, 39100 Bolzano Bolzano Bolzano/Bozen 39100",
    "addr:housenumber":"55",
    "addr:postcode":"39100;39100",
    "addr:street":"Via Del Macello",
    "iso:country":"IT",
    "sg:address":"Via Del Macello 55, 39100 Bolzano",
    "sg:city":"Bolzano",
    "sg:classifiers":[
        {
            "category":"Banks & Credit Unions",
            "subcategory":"Financial Services",
            "type":"Services"
        }
    ],
    "sg:phone":"+39 0471 996111",
    "sg:postcode":"39100",
    "sg:province":"Bolzano/Bozen",
    "sg:tags":[
        "banking",
        "finance",
        "insurance"
    ],
    "wof:name":"Banca Popolare Dellalto Adige Spa",
    "wof:placetype":"venue"
},
  "geometry": {"coordinates":[11.3282394409,46.461643219],"type":"Point"}
}