{
  "type": "Feature",
  "properties": {
    "addr:full":"25029 Verolavecchia Verolavecchia Brescia 25029",
    "addr:postcode":"25029;25029",
    "iso:country":"IT",
    "sg:address":"25029 Verolavecchia",
    "sg:city":"Verolavecchia",
    "sg:orig_category":"Servizi E Lavori Industria Chimica",
    "sg:phone":"+39 030 931493",
    "sg:postcode":"25029",
    "sg:province":"Brescia",
    "wof:name":"F.b.f. Di Baronio Santo & C. (s.n.c.)",
    "wof:placetype":"venue"
},
  "geometry": {"coordinates":[10.195837,45.554146],"type":"Point"}
}