{
  "type": "Feature",
  "properties": {
    "iso:country":"IT",
    "sg:address":"31, Via Martiri Della Liberta' 13818 Tollegno",
    "sg:city":"Tollegno",
    "sg:classifiers":[
        {
            "category":"Shopping",
            "subcategory":"Crafts & Fabrics",
            "type":"Retail Goods"
        }
    ],
    "sg:phone":"+39 015 242 9411",
    "sg:postcode":"13818",
    "sg:province":"Biella",
    "wof:name":"Filatura Cervinia Spa",
    "wof:placetype":"venue"
},
  "geometry": {"coordinates":[8.0490226746,45.585975647],"type":"Point"}
}