{
  "type": "Feature",
  "properties": {
    "addr:full":"Largo De Vecchi 11 23813 Cortenova Cortenova Lecco 23813",
    "addr:housenumber":"11",
    "addr:postcode":"23813;23813",
    "addr:street":"Largo De Vecchi",
    "iso:country":"IT",
    "sg:address":"Largo De Vecchi 11 23813 Cortenova",
    "sg:city":"Cortenova",
    "sg:classifiers":[
        {
            "category":"Home & Garden",
            "subcategory":"Building Materials",
            "type":"Retail Goods"
        }
    ],
    "sg:phone":"+39 0341 901521",
    "sg:postcode":"23813",
    "sg:province":"Lecco",
    "sg:tags":[
        "flange",
        "special"
    ],
    "sg:website":"www.melesi.it",
    "wof:name":"Officine Ambrogio Melesi Srl",
    "wof:placetype":"venue"
},
  "geometry": {"coordinates":[9.386143,46.001347],"type":"Point"}
}