{
  "type": "Feature",
  "properties": {
    "iso:country":"IT",
    "sg:address":"13040 Alice Castello",
    "sg:city":"Alice Castello",
    "sg:orig_category":"Ospedali E Servizi Sanitari",
    "sg:phone":"+39 0161 909033",
    "sg:postcode":"13040",
    "sg:province":"Vercelli",
    "wof:name":"Laboratorio Di Protesi Dentale",
    "wof:placetype":"venue"
},
  "geometry": {"coordinates":[8.074074,45.36628],"type":"Point"}
}