{
  "type": "Feature",
  "properties": {
    "addr:full":"20060 Trezzano Rosa Trezzano Rosa Milano 20060",
    "addr:postcode":"20060;20060",
    "iso:country":"IT",
    "sg:address":"20060 Trezzano Rosa",
    "sg:city":"Trezzano Rosa",
    "sg:orig_category":"Manufacturers: Prefabbricati",
    "sg:phone":"+39 02 9096 8545",
    "sg:postcode":"20060",
    "sg:province":"Milano",
    "wof:name":"Ital Legnami Sas",
    "wof:placetype":"venue"
},
  "geometry": {"coordinates":[9.473101,45.588657],"type":"Point"}
}