{
  "type": "Feature",
  "properties": {
    "addr:full":"17027 Pietra Ligure Pietra Ligure Savona 17027",
    "addr:postcode":"17027;17027",
    "iso:country":"IT",
    "sg:address":"17027 Pietra Ligure",
    "sg:city":"Pietra Ligure",
    "sg:orig_category":"Alberghi E Strutture Extra Alberghiere. Ospedali E Servizi Sanitari",
    "sg:phone":"+39 019 617374",
    "sg:postcode":"17027",
    "sg:province":"Savona",
    "wof:name":"Colonia Permanente' Bambino Gesu' '",
    "wof:placetype":"venue"
},
  "geometry": {"coordinates":[8.296967,44.158108],"type":"Point"}
}