{
  "type": "Feature",
  "properties": {
    "addr:full":"Via Edison 14 20090 Trezzano Sul Naviglio Trezzano sul Naviglio Milano 20090",
    "addr:housenumber":"14",
    "addr:postcode":"20090;20090",
    "addr:street":"Via Edison",
    "iso:country":"IT",
    "sg:address":"Via Edison 14 20090 Trezzano Sul Naviglio",
    "sg:city":"Trezzano sul Naviglio",
    "sg:classifiers":[
        {
            "category":"Banks & Credit Unions",
            "subcategory":"Investment Brokerage",
            "type":"Services"
        }
    ],
    "sg:phone":"+39 02 484 2021",
    "sg:postcode":"20090",
    "sg:province":"Milano",
    "sg:tags":[
        "planning",
        "electronic",
        "boards"
    ],
    "sg:website":"www.sei-strumentazione.it",
    "wof:name":"Sei Spa",
    "wof:placetype":"venue"
},
  "geometry": {"coordinates":[9.0650415421,45.4213600159],"type":"Point"}
}