{
  "type": "Feature",
  "properties": {
    "iso:country":"IT",
    "sg:address":"52/54, Via S. Lorenzo 25069 Villa Carcina",
    "sg:city":"Carcina",
    "sg:classifiers":[
        {
            "category":"Manufacturing",
            "subcategory":"Metals",
            "type":"Manufacturing & Wholesale Goods"
        }
    ],
    "sg:phone":"+39 030 890 0427",
    "sg:postcode":"25069",
    "sg:province":"Brescia",
    "sg:tags":[
        "metallurgy",
        "metalworking"
    ],
    "wof:name":"R.m.g. Raffineria Metalli Guizzi (s.p.a.)",
    "wof:placetype":"venue"
},
  "geometry": {"coordinates":[10.2229576111,45.5398292542],"type":"Point"}
}