{
  "type": "Feature",
  "properties": {
    "addr:full":"Via Privata Ferrante Don 8 23900 Lecco Lecco Lecco 23900",
    "addr:housenumber":"8",
    "addr:postcode":"23900;23900",
    "addr:street":"Via Privata Ferrante Don",
    "iso:country":"IT",
    "sg:address":"Via Privata Ferrante Don 8 23900 Lecco",
    "sg:city":"Lecco",
    "sg:orig_category":"Strip Steel, Cold-rolled",
    "sg:phone":"+39 0341 363263",
    "sg:postcode":"23900",
    "sg:province":"Lecco",
    "wof:name":"Metalmanzoni Spa",
    "wof:placetype":"venue"
},
  "geometry": {"coordinates":[9.390071,45.852982],"type":"Point"}
}