{
  "type": "Feature",
  "properties": {
    "addr:full":"50059 Vinci Vinci Firenze 50059",
    "addr:postcode":"50059;50059",
    "iso:country":"IT",
    "sg:address":"50059 Vinci",
    "sg:city":"Vinci",
    "sg:orig_category":"Calzature, Pelletterie E Pelli",
    "sg:phone":"+39 0571 500277",
    "sg:postcode":"50059",
    "sg:province":"Firenze",
    "wof:name":"New Fur Di Marco Masi",
    "wof:placetype":"venue"
},
  "geometry": {"coordinates":[10.88938,43.810085],"type":"Point"}
}