{
  "type": "Feature",
  "properties": {
    "iso:country":"IT",
    "sg:address":"55100 Lucca",
    "sg:city":"Lucca",
    "sg:orig_category":"Servizi Ausiliari Dei Mezzi Di Trasporto",
    "sg:phone":"+39 0583 343477",
    "sg:postcode":"55100",
    "sg:province":"Lucca",
    "wof:name":"Autocarrozzeria La Freddana",
    "wof:placetype":"venue"
},
  "geometry": {"coordinates":[10.511101,43.867001],"type":"Point"}
}