{
  "type": "Feature",
  "properties": {
    "addr:full":"21, Via Comunale Fanucchi 55012 Capannori Capannori Lucca 55012",
    "addr:postcode":"55012;55012",
    "addr:street":"Via Comunale Fanucchi",
    "iso:country":"IT",
    "sg:address":"21, Via Comunale Fanucchi 55012 Capannori",
    "sg:city":"Capannori",
    "sg:classifiers":[
        {
            "category":"Manufacturing",
            "subcategory":"Paper Products",
            "type":"Manufacturing & Wholesale Goods"
        }
    ],
    "sg:phone":"+39 39058330078",
    "sg:postcode":"55012",
    "sg:province":"Lucca",
    "sg:tags":[
        "cardboard"
    ],
    "wof:name":"Cartiera Lucchesi (s.r.l.)",
    "wof:placetype":"venue"
},
  "geometry": {"coordinates":[10.5833330154,43.8333320618],"type":"Point"}
}