{
  "type": "Feature",
  "properties": {
    "addr:full":"22070 Binago Binago Como 22070",
    "addr:postcode":"22070;22070",
    "iso:country":"IT",
    "sg:address":"22070 Binago",
    "sg:city":"Binago",
    "sg:orig_category":"Prodotti Chimici Di Base. Forniture Per Attivita' Industriali",
    "sg:phone":"+39 031 800282",
    "sg:postcode":"22070",
    "sg:province":"Como",
    "wof:name":"A.m.p.e.g. S.a.s.",
    "wof:placetype":"venue"
},
  "geometry": {"coordinates":[8.9298267365,45.7792816162],"type":"Point"}
}