{
  "type": "Feature",
  "properties": {
    "addr:full":"37040 Bonavigo Bonavigo Verona 37040",
    "addr:postcode":"37040;37040",
    "iso:country":"IT",
    "sg:address":"37040 Bonavigo",
    "sg:city":"Bonavigo",
    "sg:orig_category":"Arredo Bagno Ed Idrosanitari. Idrosanitari E Accessori",
    "sg:phone":"+39 0442 73018",
    "sg:postcode":"37040",
    "sg:province":"Verona",
    "wof:name":"Samo Spa",
    "wof:placetype":"venue"
},
  "geometry": {"coordinates":[10.987621,45.412895],"type":"Point"}
}