{
  "type": "Feature",
  "properties": {
    "iso:country":"IT",
    "sg:address":"17047 Vado Ligure",
    "sg:city":"Vado Ligure",
    "sg:orig_category":"Trasporti E Spedizioni Merci",
    "sg:phone":"+39 019 215 4321",
    "sg:postcode":"17047",
    "sg:province":"Savona",
    "wof:name":"Capurro Shipping Agency",
    "wof:placetype":"venue"
},
  "geometry": {"coordinates":[8.436029,44.265942],"type":"Point"}
}