{
  "type": "Feature",
  "properties": {
    "iso:country":"IT",
    "sg:address":"44, Via Crimea Percoto 33050 Pavia Di Udine",
    "sg:city":"Pavia di Udine",
    "sg:classifiers":[
        {
            "category":"Home & Garden",
            "subcategory":"Home Furnishings",
            "type":"Retail Goods"
        }
    ],
    "sg:phone":"+39 0432 676326",
    "sg:postcode":"33050",
    "sg:province":"Udine",
    "sg:tags":[
        "household"
    ],
    "wof:name":"Trafilati Forte Delfino Di Forte Roberto & C. (s.n.c.)",
    "wof:placetype":"venue"
},
  "geometry": {"coordinates":[13.230724,46.064941],"type":"Point"}
}