{
  "type": "Feature",
  "properties": {
    "iso:country":"IT",
    "sg:address":"64, Via Isonzo 21042 Caronno Pertusella",
    "sg:city":"Caronno Pertusella",
    "sg:classifiers":[
        {
            "category":"Manufacturing",
            "subcategory":"Glass & Minerals",
            "type":"Manufacturing & Wholesale Goods"
        }
    ],
    "sg:phone":"+39 39029657271",
    "sg:postcode":"21042",
    "sg:province":"Varese",
    "wof:name":"Restelli Vetri S.r.l.",
    "wof:placetype":"venue"
},
  "geometry": {"coordinates":[9.043919,45.596687],"type":"Point"}
}