{
  "type": "Feature",
  "properties": {
    "iso:country":"IT",
    "sg:address":"34, Via Euripide 20041 Agrate Brianza",
    "sg:city":"Agrate Brianza",
    "sg:classifiers":[
        {
            "category":"Professional",
            "subcategory":"Engineering",
            "type":"Services"
        }
    ],
    "sg:phone":"+39 39039651211",
    "sg:postcode":"20041",
    "sg:province":"Milano",
    "sg:tags":[
        "machine",
        "-",
        "mechanical"
    ],
    "wof:name":"Ksa Italia Srl",
    "wof:placetype":"venue"
},
  "geometry": {"coordinates":[9.329101,45.571877],"type":"Point"}
}