{
  "type": "Feature",
  "properties": {
    "addr:full":"27050 Casei Gerola Casei Pavia 27050",
    "addr:postcode":"27050;27050",
    "addr:street":"Gerola Casei",
    "iso:country":"IT",
    "sg:address":"27050 Casei Gerola",
    "sg:city":"Casei",
    "sg:orig_category":"Legno E Semilavorati. Apparecchiature E Sistemi Per Magazzinaggio E Movimentazione",
    "sg:phone":"+39 0383 381003",
    "sg:postcode":"27050",
    "sg:province":"Pavia",
    "wof:name":"Arona Pietro",
    "wof:placetype":"venue"
},
  "geometry": {"coordinates":[8.911645,45.012615],"type":"Point"}
}