{
  "type": "Feature",
  "properties": {
    "iso:country":"IT",
    "sg:address":"20129 Milano",
    "sg:city":"Milano",
    "sg:orig_category":"Editoria Elettronica E Multimediale",
    "sg:phone":"+39 02 2953 6495",
    "sg:postcode":"20129",
    "sg:province":"Milano",
    "sg:website":"http://www.creo.it",
    "wof:name":"Creo Srl",
    "wof:placetype":"venue"
},
  "geometry": {"coordinates":[9.217976,45.476463],"type":"Point"}
}