{
  "type": "Feature",
  "properties": {
    "addr:full":"24018 Villa D'alme' Bergamo 24018",
    "addr:housenumber":"24018",
    "addr:postcode":"24018",
    "addr:street":"Villa D'Alme'",
    "iso:country":"IT",
    "sg:address":"24018 Villa D'alme'",
    "sg:orig_category":"Macchine E Forniture Per Arredamento E Industria Del Legno. Forniture Per Edilizia E Lavori Pubblici",
    "sg:phone":"+39 035 542253",
    "sg:postcode":"24018",
    "sg:province":"Bergamo",
    "wof:name":"Mauri Mario",
    "wof:placetype":"venue"
},
  "geometry": {"coordinates":[9.617784,45.747616],"type":"Point"}
}