{
  "type": "Feature",
  "properties": {
    "iso:country":"IT",
    "sg:address":"Piazza Europa 8; S. Giovanni Rotondo; 71013",
    "sg:classifiers":[
        {
            "category":"Banks & Credit Unions",
            "subcategory":"Bank",
            "type":"Services"
        }
    ],
    "sg:phone":"+39 0882 411925",
    "sg:postcode":"71013",
    "sg:province":"Foggia",
    "wof:name":"Banco Di Napoli Spa",
    "wof:placetype":"venue"
},
  "geometry": {"coordinates":[15.724401,41.707363],"type":"Point"}
}