{
  "type": "Feature",
  "properties": {
    "addr:full":"20154 Milano Milano Milano 20154",
    "addr:postcode":"20154;20154",
    "iso:country":"IT",
    "sg:address":"20154 Milano",
    "sg:city":"Milano",
    "sg:classifiers":[
        {
            "category":"Health Services",
            "subcategory":"Health Practitioner",
            "type":"Services"
        }
    ],
    "sg:phone":"+39 02 3360 8706",
    "sg:postcode":"20154",
    "sg:province":"Milano",
    "sg:tags":[
        "medici"
    ],
    "wof:name":"Fontana Giuseppe",
    "wof:placetype":"venue"
},
  "geometry": {"coordinates":[9.17554,45.48233],"type":"Point"}
}