{
  "type": "Feature",
  "properties": {
    "iso:country":"IT",
    "sg:address":"90144 Palermo",
    "sg:city":"Palermo",
    "sg:orig_category":"Banche E Servizi Finanziari",
    "sg:phone":"+39 091 730 2632",
    "sg:postcode":"90144",
    "sg:province":"Palermo",
    "wof:name":"Area Banca Spa",
    "wof:placetype":"venue"
},
  "geometry": {"coordinates":[13.348918,38.134995],"type":"Point"}
}