{
  "type": "Feature",
  "properties": {
    "iso:country":"IT",
    "sg:address":"35020 Saonara",
    "sg:city":"Saonara",
    "sg:orig_category":"Valvole E Apparecchiature Di Misura. Forniture Per Attivita' Industriali",
    "sg:phone":"+39 049 640388",
    "sg:postcode":"35020",
    "sg:province":"Padova",
    "wof:name":"Luise Water Engineering (s.r.l.)",
    "wof:placetype":"venue"
},
  "geometry": {"coordinates":[11.961444,45.383041],"type":"Point"}
}