{
  "type": "Feature",
  "properties": {
    "iso:country":"IT",
    "sg:address":"56030 Sterza",
    "sg:orig_category":"Prodotti Chimici Di Base. Forniture Per Attivita' Industriali",
    "sg:phone":"+39 0587 642066",
    "sg:postcode":"56030",
    "sg:province":"Pisa",
    "wof:name":"Colorlegno Di Gallese Francesca",
    "wof:placetype":"venue"
},
  "geometry": {"coordinates":[10.3965845108,43.7161369324],"type":"Point"}
}