{
  "type": "Feature",
  "properties": {
    "addr:full":"10145 Torino Torino Torino 10145",
    "addr:housenumber":"10145",
    "addr:postcode":"10145",
    "iso:country":"IT",
    "sg:address":"10145 Torino",
    "sg:city":"Torino",
    "sg:orig_category":"Elettronica Professionale E Di Consumo. Automazione E Macchine Per Ufficio. Forniture Per Congressi, Fiere E Manifestazioni",
    "sg:phone":"+39 011 771 0888",
    "sg:postcode":"10145",
    "sg:province":"Torino",
    "wof:name":"Studeo (s.n.c.)",
    "wof:placetype":"venue"
},
  "geometry": {"coordinates":[7.641115,45.077881],"type":"Point"}
}