{
  "type": "Feature",
  "properties": {
    "iso:country":"IT",
    "sg:address":"29100 Piacenza",
    "sg:city":"Piacenza",
    "sg:orig_category":"Servizi E Lavori Industria Chimica. Riparazione Dei Mezzi Di Trasporto",
    "sg:phone":"+39 0523 590956",
    "sg:postcode":"29100",
    "sg:province":"Piacenza",
    "wof:name":"Tecnover Srl",
    "wof:placetype":"venue"
},
  "geometry": {"coordinates":[9.767375,45.050365],"type":"Point"}
}