{
  "type": "Feature",
  "properties": {
    "iso:country":"IT",
    "sg:address":"25085 Gavardo",
    "sg:city":"Gavardo",
    "sg:orig_category":"Dischi Tela E Panno Per Pulitrici",
    "sg:phone":"+39 036 537 1347",
    "sg:postcode":"25085",
    "sg:province":"Brescia",
    "wof:name":"Aurodisk Srl",
    "wof:placetype":"venue"
},
  "geometry": {"coordinates":[10.437322,45.597187],"type":"Point"}
}