{
  "type": "Feature",
  "properties": {
    "iso:country":"IT",
    "sg:address":"20126 Milano",
    "sg:city":"Milano",
    "sg:orig_category":"Metalli E Leghe",
    "sg:phone":"+39 02 257 4638",
    "sg:postcode":"20126",
    "sg:province":"Milano",
    "wof:name":"Metal Rof Snc",
    "wof:placetype":"venue"
},
  "geometry": {"coordinates":[9.2184076309,45.5174217224],"type":"Point"}
}