{
  "type": "Feature",
  "properties": {
    "iso:country":"IT",
    "sg:address":"20136 Milano",
    "sg:city":"Milano",
    "sg:orig_category":"Naturopatia",
    "sg:phone":"+39 02 8942 0556",
    "sg:postcode":"20136",
    "sg:province":"Milano",
    "sg:website":"http://www.scuolasimo.it",
    "wof:name":"Si.ri.e. Srl",
    "wof:placetype":"venue"
},
  "geometry": {"coordinates":[9.182389,45.452152],"type":"Point"}
}