{
  "type": "Feature",
  "properties": {
    "addr:full":"20010 Pregnana Milanese Pregnana Milanese Milano 20010",
    "addr:postcode":"20010;20010",
    "addr:street":"Milanese",
    "iso:country":"IT",
    "sg:address":"20010 Pregnana Milanese",
    "sg:city":"Pregnana Milanese",
    "sg:orig_category":"Pubblica Amministrazione",
    "sg:phone":"+39 02 939671",
    "sg:postcode":"20010",
    "sg:province":"Milano",
    "wof:name":"Municipio Di Pregnana",
    "wof:placetype":"venue"
},
  "geometry": {"coordinates":[9.0180702209,45.4813461304],"type":"Point"}
}