{
  "type": "Feature",
  "properties": {
    "iso:country":"IT",
    "sg:address":"42019 Scandiano",
    "sg:orig_category":"Macchine Ed Impianti Per Edilizia E Lavori Pubblici",
    "sg:phone":"+39 0522 984273",
    "sg:postcode":"42019",
    "sg:province":"Reggio Nell'Emilia",
    "wof:name":"Tecno - Sider Snc",
    "wof:placetype":"venue"
},
  "geometry": {"coordinates":[10.670341,44.624851],"type":"Point"}
}