{
  "type": "Feature",
  "properties": {
    "iso:country":"IT",
    "sg:address":"25030 Roncadelle",
    "sg:city":"Roncadelle",
    "sg:orig_category":"Arredo Bagno Ed Idrosanitari. Forniture Alle Strutture Ricettive. Apparecchi, Attrezzature E Forniture Per Centri Estetici",
    "sg:phone":"+39 030 258 6015",
    "sg:postcode":"25030",
    "sg:province":"Brescia",
    "sg:website":"http://www.forit.it",
    "wof:name":"Forit Spa",
    "wof:placetype":"venue"
},
  "geometry": {"coordinates":[10.144691,45.534531],"type":"Point"}
}