{
  "type": "Feature",
  "properties": {
    "iso:country":"IT",
    "sg:address":"50055 Lastra A Signa",
    "sg:city":"Lastra a Signa",
    "sg:orig_category":"Studi E Consulenze Tecniche E Industriali. Consulenze Tecniche, Amministrative E Perizie. Servizi Ausiliari Di Analisi, Controllo E Ricerca",
    "sg:phone":"+39 055 872 2279",
    "sg:postcode":"50055",
    "sg:province":"Firenze",
    "sg:website":"http://www.efc-lattonerie.it",
    "wof:name":"Efc Snc",
    "wof:placetype":"venue"
},
  "geometry": {"coordinates":[11.082491,43.73737],"type":"Point"}
}