{
  "type": "Feature",
  "properties": {
    "iso:country":"IT",
    "sg:address":"110/2, Via Raiale 65128 Pescara",
    "sg:city":"Pescara",
    "sg:classifiers":[
        {
            "category":"Wholesale",
            "subcategory":"Drugs",
            "type":"Manufacturing & Wholesale Goods"
        }
    ],
    "sg:phone":"+39 085 431 8106",
    "sg:postcode":"65128",
    "sg:province":"Pescara",
    "sg:tags":[
        "chemical",
        "pharmaceutical"
    ],
    "wof:name":"S.a.f.a.r Societa' Cooperativa Arl",
    "wof:placetype":"venue"
},
  "geometry": {"coordinates":[14.178262,42.436333],"type":"Point"}
}