{
  "type": "Feature",
  "properties": {
    "iso:country":"IT",
    "sg:address":"20146 Milano",
    "sg:city":"Milano",
    "sg:orig_category":"Impianti, Attrezzature E Forniture Sanitarie Ed Ospedaliere",
    "sg:phone":"+39 02 423 8247",
    "sg:postcode":"20146",
    "sg:province":"Milano",
    "wof:name":"Apex Dental Srl",
    "wof:placetype":"venue"
},
  "geometry": {"coordinates":[9.146522,45.458641],"type":"Point"}
}