{
  "type": "Feature",
  "properties": {
    "iso:country":"IT",
    "sg:address":"45100 Rovigo",
    "sg:city":"Borsea",
    "sg:orig_category":"Apparecchiature Ed Attrezzature Meccaniche",
    "sg:phone":"+39 0425 474838",
    "sg:postcode":"45100",
    "sg:province":"Rovigo",
    "sg:website":"http://www.vesta.it",
    "wof:name":"Vesta Srl",
    "wof:placetype":"venue"
},
  "geometry": {"coordinates":[11.790605,45.040707],"type":"Point"}
}