{
  "type": "Feature",
  "properties": {
    "addr:full":"Via Scaglia Est 136; Modena; 41100 Modena Modena 41100",
    "addr:housenumber":"136",
    "addr:postcode":"41100;41100",
    "addr:street":"Via Scaglia Est",
    "iso:country":"IT",
    "sg:address":"Via Scaglia Est 136; Modena; 41100",
    "sg:city":"Modena",
    "sg:classifiers":[
        {
            "category":"Banks & Credit Unions",
            "subcategory":"Bank",
            "type":"Services"
        }
    ],
    "sg:phone":"+39 059 344799",
    "sg:postcode":"41100",
    "sg:province":"Modena",
    "wof:name":"Banca Fideuram Spa",
    "wof:placetype":"venue"
},
  "geometry": {"coordinates":[10.899453,44.636433],"type":"Point"}
}