{
  "type": "Feature",
  "properties": {
    "iso:country":"IT",
    "sg:address":"20089 Rozzano",
    "sg:city":"Rozzano",
    "sg:orig_category":"Abbigliamento Esterno, Maglierie E Pelliccerie",
    "sg:phone":"+39 02 5750 0631",
    "sg:postcode":"20089",
    "sg:province":"Milano",
    "wof:name":"Italbaby (s.r.l.)",
    "wof:placetype":"venue"
},
  "geometry": {"coordinates":[9.165067,45.396832],"type":"Point"}
}