{
  "type": "Feature",
  "properties": {
    "addr:full":"65121 Pescara Pescara Pescara 65121",
    "addr:postcode":"65121;65121",
    "iso:country":"IT",
    "sg:address":"65121 Pescara",
    "sg:city":"Pescara",
    "sg:orig_category":"Servizi Per Aziende, Manifestazioni E Supporto Agli Scambi Commerciali",
    "sg:phone":"+39 085 421 1780",
    "sg:postcode":"65121",
    "sg:province":"Pescara",
    "wof:name":"Sander Investigazioni Srl",
    "wof:placetype":"venue"
},
  "geometry": {"coordinates":[14.214967,42.467117],"type":"Point"}
}