{
  "type": "Feature",
  "properties": {
    "iso:country":"IT",
    "sg:address":"27046 Santa Giuletta",
    "sg:city":"Santa Giuletta",
    "sg:orig_category":"Apparecchiature E Sistemi Per Magazzinaggio E Movimentazione",
    "sg:phone":"+39 0383 899071",
    "sg:postcode":"27046",
    "sg:province":"Pavia",
    "wof:name":"Maffi G. E Figli Srl",
    "wof:placetype":"venue"
},
  "geometry": {"coordinates":[9.191313,45.03717],"type":"Point"}
}