{
  "type": "Feature",
  "properties": {
    "iso:country":"IT",
    "sg:address":"53, Via Dell' Artigianato 61026 Lunano",
    "sg:city":"Lunano",
    "sg:classifiers":[
        {
            "category":"Home & Garden",
            "subcategory":"Home Furnishings",
            "type":"Retail Goods"
        }
    ],
    "sg:phone":"+39 39072270331",
    "sg:postcode":"61026",
    "sg:province":"Pesaro E Urbino",
    "sg:tags":[
        "household"
    ],
    "wof:name":"Tre Emme S.r.l.",
    "wof:placetype":"venue"
},
  "geometry": {"coordinates":[12.44865,43.735233],"type":"Point"}
}