{
  "type": "Feature",
  "properties": {
    "iso:country":"IT",
    "sg:address":"Piazza Italia, 3; Soresina; 26015",
    "sg:city":"Soresina",
    "sg:classifiers":[
        {
            "category":"Banks & Credit Unions",
            "subcategory":"Bank",
            "type":"Services"
        }
    ],
    "sg:phone":"+39 0374 41610",
    "sg:postcode":"26015",
    "sg:province":"Cremona",
    "wof:name":"Cassa Rurale Ed Artigiana, Di Casalmorano",
    "wof:placetype":"venue"
},
  "geometry": {"coordinates":[9.858454,45.285786],"type":"Point"}
}