{
  "type": "Feature",
  "properties": {
    "iso:country":"IT",
    "sg:address":"10123 Torino",
    "sg:city":"Torino",
    "sg:orig_category":"Associazioni E Federazioni Sportive",
    "sg:phone":"+39 011 837692",
    "sg:postcode":"10123",
    "sg:province":"Torino",
    "wof:name":"Associazione Ginger Company Di C. Serra & C. Snc",
    "wof:placetype":"venue"
},
  "geometry": {"coordinates":[7.692579,45.064259],"type":"Point"}
}