{
  "type": "Feature",
  "properties": {
    "iso:country":"IT",
    "sg:address":"Via G. Marconi 38 35020 Albignasego",
    "sg:city":"Albignasego",
    "sg:orig_category":"Sheets To Measure",
    "sg:phone":"+39 049 897 5903",
    "sg:postcode":"35020",
    "sg:province":"Padova",
    "sg:website":"www.protec.it/padana",
    "wof:name":"Padana Lamiere Sas Di Marini Edda & C",
    "wof:placetype":"venue"
},
  "geometry": {"coordinates":[11.932453,45.365486],"type":"Point"}
}