{
  "type": "Feature",
  "properties": {
    "iso:country":"IT",
    "sg:address":"00175 Roma",
    "sg:city":"Roma",
    "sg:orig_category":"Macchine, Impianti Ed Attrezzature Per Abbigliamento E Pelletterie. Macchine E Impianti Per Attivita' Commerciali Ed Artigianali",
    "sg:phone":"+39 06 714 0963",
    "sg:postcode":"00175",
    "sg:province":"Roma",
    "wof:name":"Sita Stir Sas Di Sita Massimiliano",
    "wof:placetype":"venue"
},
  "geometry": {"coordinates":[12.561069,41.86351],"type":"Point"}
}