{
  "type": "Feature",
  "properties": {
    "iso:country":"IT",
    "sg:address":"42, Via Eugubina 06122 Perugia",
    "sg:city":"Perugia",
    "sg:classifiers":[
        {
            "category":"Travel",
            "subcategory":"Travel Agent",
            "type":"Entertainment"
        }
    ],
    "sg:phone":"+39 075 573 0973",
    "sg:postcode":"06122",
    "sg:province":"Perugia",
    "sg:tags":[
        "business"
    ],
    "wof:name":"Hotel Perusia E La Villa (s.r.l.)",
    "wof:placetype":"venue"
},
  "geometry": {"coordinates":[12.401283,43.116444],"type":"Point"}
}