{
  "type": "Feature",
  "properties": {
    "iso:country":"IT",
    "sg:address":"16039 Sestri Levante",
    "sg:city":"Sestri Levante",
    "sg:orig_category":"Metalli E Leghe",
    "sg:phone":"+39 0185 3661",
    "sg:postcode":"16039",
    "sg:province":"Genova",
    "wof:name":"Arinox Srl",
    "wof:placetype":"venue"
},
  "geometry": {"coordinates":[9.422826767,44.2833366394],"type":"Point"}
}