{
  "type": "Feature",
  "properties": {
    "addr:full":"7, Via Gramsci Antonio 10121 Torino Torino Torino 10121",
    "addr:postcode":"10121;10121",
    "addr:street":"Via Gramsci Antonio",
    "iso:country":"IT",
    "sg:address":"7, Via Gramsci Antonio 10121 Torino",
    "sg:city":"Torino",
    "sg:classifiers":[
        {
            "category":"Banks & Credit Unions",
            "subcategory":"Bank",
            "type":"Services"
        }
    ],
    "sg:phone":"+39 011 516 2411",
    "sg:postcode":"10121",
    "sg:province":"Torino",
    "sg:tags":[
        "banking",
        "institution"
    ],
    "wof:name":"Banca Banca Intermobiliare S.p.a.",
    "wof:placetype":"venue"
},
  "geometry": {"coordinates":[7.579069,45.066582],"type":"Point"}
}