{
  "type": "Feature",
  "properties": {
    "iso:country":"IT",
    "sg:address":"20026 Novate Milanese",
    "sg:city":"Novate Milanese",
    "sg:orig_category":"Tessuti Uso Tecnico E Industriale",
    "sg:phone":"+39 02 332511",
    "sg:postcode":"20026",
    "sg:province":"Milano",
    "wof:name":"Tessitura Quadrelli Spa",
    "wof:placetype":"venue"
},
  "geometry": {"coordinates":[9.13722,45.528545],"type":"Point"}
}