{
  "type": "Feature",
  "properties": {
    "addr:full":"10148 Torino Torino Torino 10148",
    "addr:postcode":"10148;10148",
    "iso:country":"IT",
    "sg:address":"10148 Torino",
    "sg:city":"Torino",
    "sg:orig_category":"Impiantistica E Prodotti Tecnologici Per Edilizia. Forniture Industriali Per Prevenzione, Controllo E Sicurezza",
    "sg:phone":"+39 011 226 2023",
    "sg:postcode":"10148",
    "sg:province":"Torino",
    "wof:name":"Telum (s.a.s.)",
    "wof:placetype":"venue"
},
  "geometry": {"coordinates":[7.688172,45.1087],"type":"Point"}
}