{
  "type": "Feature",
  "properties": {
    "iso:country":"IT",
    "sg:address":"6, Piazzetta Rizzieri Bruno 44100 Ferrara",
    "sg:city":"Ferrara",
    "sg:classifiers":[
        {
            "category":"Parking",
            "subcategory":"Lot",
            "type":"Transportation"
        }
    ],
    "sg:phone":"+39 0532 770317",
    "sg:postcode":"44100",
    "sg:province":"Ferrara",
    "sg:tags":[
        "transport",
        "road"
    ],
    "wof:name":"Gab Spedizioni E Trasporti Internazionali (s.r.l.)",
    "wof:placetype":"venue"
},
  "geometry": {"coordinates":[11.6204395294,44.8378944397],"type":"Point"}
}