{
  "type": "Feature",
  "properties": {
    "iso:country":"IT",
    "sg:address":"Piazza Giardini 6/7; Montegrotto; 35036",
    "sg:classifiers":[
        {
            "category":"Banks & Credit Unions",
            "subcategory":"Bank",
            "type":"Services"
        }
    ],
    "sg:phone":"+39 049 793396",
    "sg:postcode":"35036",
    "sg:province":"Padova",
    "wof:name":"Banca Popolare Veneta",
    "wof:placetype":"venue"
},
  "geometry": {"coordinates":[11.790134,45.321793],"type":"Point"}
}