{
  "type": "Feature",
  "properties": {
    "iso:country":"IT",
    "sg:address":"41011 Campogalliano",
    "sg:city":"Campogalliano",
    "sg:orig_category":"Elettronica Professionale E Di Consumo. Musica",
    "sg:phone":"+39 059 851075",
    "sg:postcode":"41011",
    "sg:province":"Modena",
    "wof:name":"Fratti Marco Sas",
    "wof:placetype":"venue"
},
  "geometry": {"coordinates":[10.841278,44.69381],"type":"Point"}
}