{
  "type": "Feature",
  "properties": {
    "iso:country":"IT",
    "sg:address":"16128 Genova",
    "sg:city":"Genova",
    "sg:orig_category":"Elettrotecnica Industriale, Prodotti E Apparecchiature. Elettronica Industriale, Prodotti E Apparecchiature",
    "sg:phone":"+39 010 246 1190",
    "sg:postcode":"16128",
    "sg:province":"Genova",
    "wof:name":"Arem Automazione Sas",
    "wof:placetype":"venue"
},
  "geometry": {"coordinates":[8.936954,44.401161],"type":"Point"}
}