{
  "type": "Feature",
  "properties": {
    "addr:full":"67, Via Valpellice 10060 San Secondo Di Pinerolo San Secondo di Pinerolo Torino 10060",
    "addr:postcode":"10060;10060",
    "addr:street":"Via Valpellice",
    "iso:country":"IT",
    "sg:address":"67, Via Valpellice 10060 San Secondo Di Pinerolo",
    "sg:city":"San Secondo di Pinerolo",
    "sg:classifiers":[
        {
            "category":"Manufacturing",
            "subcategory":"Metals",
            "type":"Manufacturing & Wholesale Goods"
        }
    ],
    "sg:phone":"+39 0121 501436",
    "sg:postcode":"10060",
    "sg:province":"Torino",
    "sg:tags":[
        "processing"
    ],
    "wof:name":"Tecnomesa Di Tamagno & C. (s.a.s.)",
    "wof:placetype":"venue"
},
  "geometry": {"coordinates":[7.6866188049,45.0705604553],"type":"Point"}
}