{
  "type": "Feature",
  "properties": {
    "iso:country":"IT",
    "sg:address":"15023 Felizzano",
    "sg:city":"Felizzano",
    "sg:orig_category":"Utensili Meccanici E Materiali. Forniture Per Attivita' Industriali",
    "sg:phone":"+39 0131 772284",
    "sg:postcode":"15023",
    "sg:province":"Alessandria",
    "wof:name":"Cvl (s.n.c.)",
    "wof:placetype":"venue"
},
  "geometry": {"coordinates":[8.435108,44.898731],"type":"Point"}
}