{
  "type": "Feature",
  "properties": {
    "addr:full":"09127 Cagliari Cagliari Cagliari 09127",
    "addr:postcode":"09127;09127",
    "iso:country":"IT",
    "sg:address":"09127 Cagliari",
    "sg:city":"Cagliari",
    "sg:orig_category":"Scuole Di Lingue",
    "sg:phone":"+39 070 663535",
    "sg:postcode":"09127",
    "sg:province":"Cagliari",
    "sg:website":"http://www.paginegialle.it/liceolingueasegnil",
    "wof:name":"Liceo Linguistico A. Segni",
    "wof:placetype":"venue"
},
  "geometry": {"coordinates":[9.119576,39.216335],"type":"Point"}
}