{
  "type": "Feature",
  "properties": {
    "iso:country":"IT",
    "sg:address":"12042 Bra",
    "sg:city":"Bra",
    "sg:orig_category":"Scuole E Servizi Scolastici",
    "sg:phone":"+39 0172 412057",
    "sg:postcode":"12042",
    "sg:province":"Cuneo",
    "wof:name":"Istituto San Giuseppe",
    "wof:placetype":"venue"
},
  "geometry": {"coordinates":[7.85039,44.700455],"type":"Point"}
}