{
  "type": "Feature",
  "properties": {
    "iso:country":"IT",
    "sg:address":"6, Piazza Bienheureux V. De Leaval 11017 Morgex",
    "sg:city":"Morgex",
    "sg:classifiers":[
        {
            "category":"Food & Beverages",
            "subcategory":"Groceries & Convenience Stores",
            "type":"Retail Goods"
        }
    ],
    "sg:phone":"+39 0165 801811",
    "sg:postcode":"11017",
    "sg:province":"Aosta",
    "sg:tags":[
        "drink"
    ],
    "wof:name":"Sorgenti Monte Bianco Terme Di Courmayeur Spa",
    "wof:placetype":"venue"
},
  "geometry": {"coordinates":[7.034873,45.75581],"type":"Point"}
}