{
  "type": "Feature",
  "properties": {
    "iso:country":"IT",
    "sg:address":"36063 Marostica",
    "sg:city":"Marostica",
    "sg:orig_category":"Elettrotecnica Industriale, Prodotti E Apparecchiature",
    "sg:phone":"+39 0424 780950",
    "sg:postcode":"36063",
    "sg:province":"Vicenza",
    "wof:name":"Pizzato Elettrica Srl",
    "wof:placetype":"venue"
},
  "geometry": {"coordinates":[11.479014,45.512447],"type":"Point"}
}