{
  "type": "Feature",
  "properties": {
    "iso:country":"IT",
    "sg:address":"10, Strada Oviglio 15073 Castellazzo Bormida",
    "sg:city":"Castellazzo Bormida",
    "sg:classifiers":[
        {
            "category":"Food & Beverages",
            "subcategory":"Bakery",
            "type":"Retail Goods"
        }
    ],
    "sg:phone":"+39 0131 278182",
    "sg:postcode":"15073",
    "sg:province":"Alessandria",
    "sg:tags":[
        "grain",
        "cereal"
    ],
    "wof:name":"Molino Zerba S.p.a.",
    "wof:placetype":"venue"
},
  "geometry": {"coordinates":[8.530027,44.847488],"type":"Point"}
}