{
  "type": "Feature",
  "properties": {
    "addr:full":"51010 Uzzano Uzzano Pistoia 51010",
    "addr:postcode":"51010;51010",
    "iso:country":"IT",
    "sg:address":"51010 Uzzano",
    "sg:city":"Uzzano",
    "sg:orig_category":"Forniture Per Abbigliamento E Pelletterie. Forniture Per Attivita' Commerciali Ed Artigianali",
    "sg:phone":"+39 0572 452693",
    "sg:postcode":"51010",
    "sg:province":"Pistoia",
    "sg:website":"http://www.ipca.it",
    "wof:name":"I.p.c.a. Spa",
    "wof:placetype":"venue"
},
  "geometry": {"coordinates":[10.696149826,43.8851318359],"type":"Point"}
}