{
  "type": "Feature",
  "properties": {
    "iso:country":"IT",
    "sg:address":"67051 Avezzano",
    "sg:orig_category":"Ospedali E Servizi Sanitari",
    "sg:phone":"+39 0863 413692",
    "sg:postcode":"67051",
    "sg:province":"L'Aquila",
    "wof:name":"Casa Di Cura Santa Maria Srl",
    "wof:placetype":"venue"
},
  "geometry": {"coordinates":[13.924189,42.043602],"type":"Point"}
}