{
  "type": "Feature",
  "properties": {
    "iso:country":"IT",
    "sg:address":"Viale Cadore 61/d 32014 Ponte Nelle Alpi",
    "sg:city":"Ponte nelle Alpi",
    "sg:classifiers":[
        {
            "category":"Transit Center",
            "subcategory":"Freight",
            "type":"Transportation"
        }
    ],
    "sg:phone":"+39 0437 981100",
    "sg:postcode":"32014",
    "sg:province":"Belluno",
    "sg:tags":[
        "auger",
        "horizontal",
        "drilling",
        "vertical",
        "earth"
    ],
    "wof:name":"A.t.p. Snc",
    "wof:placetype":"venue"
},
  "geometry": {"coordinates":[12.285767,46.186508],"type":"Point"}
}