{
  "type": "Feature",
  "properties": {
    "iso:country":"IT",
    "sg:address":"1, V. Dei Montini 25070 Sabbio Chiese",
    "sg:city":"Sabbio Chiese",
    "sg:classifiers":[
        {
            "category":"Home & Garden",
            "subcategory":"Home Furnishings",
            "type":"Retail Goods"
        }
    ],
    "sg:phone":"+39 39036585142",
    "sg:postcode":"25070",
    "sg:province":"Brescia",
    "sg:tags":[
        "household"
    ],
    "sg:website":"http://www.pasini.it",
    "wof:name":"Pasini Metal Productions Srl",
    "wof:placetype":"venue"
},
  "geometry": {"coordinates":[10.392503,45.670944],"type":"Point"}
}