{
  "type": "Feature",
  "properties": {
    "iso:country":"IT",
    "sg:address":"20129 Milano",
    "sg:city":"Milano",
    "sg:orig_category":"Pratiche Automobilistiche",
    "sg:phone":"+39 02 2953 1804",
    "sg:postcode":"20129",
    "sg:province":"Milano",
    "wof:name":"Agenzia Billi Snc",
    "wof:placetype":"venue"
},
  "geometry": {"coordinates":[9.2094373703,45.4747962952],"type":"Point"}
}