{
  "type": "Feature",
  "properties": {
    "iso:country":"IT",
    "sg:address":"55054 Massarosa",
    "sg:city":"Massarosa",
    "sg:orig_category":"Riparazione Dei Mezzi Di Trasporto",
    "sg:phone":"+39 0584 938902",
    "sg:postcode":"55054",
    "sg:province":"Lucca",
    "sg:website":"http://www.autocarrozzeria-cipriani.it",
    "wof:name":"Autocarrozzeria Cipriani Srl",
    "wof:placetype":"venue"
},
  "geometry": {"coordinates":[10.409595,43.855106],"type":"Point"}
}