{
  "type": "Feature",
  "properties": {
    "iso:country":"IT",
    "sg:address":"43013 Langhirano",
    "sg:city":"Langhirano",
    "sg:orig_category":"Alimentari - Produzione E Ingrosso",
    "sg:phone":"+39 0521 861313",
    "sg:postcode":"43013",
    "sg:province":"Parma",
    "wof:name":"Monica E Grossi Spa",
    "wof:placetype":"venue"
},
  "geometry": {"coordinates":[10.238123,44.699432],"type":"Point"}
}