{
  "type": "Feature",
  "properties": {
    "addr:full":"24021 Albino Albino Bergamo 24021",
    "addr:postcode":"24021;24021",
    "iso:country":"IT",
    "sg:address":"24021 Albino",
    "sg:city":"Albino",
    "sg:orig_category":"Prodotti E Manufatti In Materie Plastiche",
    "sg:phone":"+39 035 753439",
    "sg:postcode":"24021",
    "sg:province":"Bergamo",
    "wof:name":"Birolini Mario Di Birolini Emilio",
    "wof:placetype":"venue"
},
  "geometry": {"coordinates":[9.6381139755,45.6671142578],"type":"Point"}
}