{
  "type": "Feature",
  "properties": {
    "addr:full":"06073 Taverne Di Corciano Corciano Perugia 06073",
    "addr:postcode":"06073;06073",
    "iso:country":"IT",
    "sg:address":"06073 Taverne Di Corciano",
    "sg:city":"Corciano",
    "sg:orig_category":"Automobili E Mezzi Di Trasporto",
    "sg:phone":"+39 075 697 8597",
    "sg:postcode":"06073",
    "sg:province":"Perugia",
    "wof:name":"Grifo Caravan Snc Di Babini Rosalba & C.",
    "wof:placetype":"venue"
},
  "geometry": {"coordinates":[12.389172,43.110703],"type":"Point"}
}