{
  "type": "Feature",
  "properties": {
    "iso:country":"IT",
    "sg:address":"Via Brunelleschi 50013 Campi Bisenzio",
    "sg:city":"Campi Bisenzio",
    "sg:classifiers":[
        {
            "category":"Shopping",
            "subcategory":"Computers & Home Electronics",
            "type":"Retail Goods"
        }
    ],
    "sg:phone":"+39 055 895 2636",
    "sg:postcode":"50013",
    "sg:province":"Firenze",
    "sg:tags":[
        "electronic",
        "electrical",
        "equipment"
    ],
    "wof:name":"Italsime Macchine Elettriche Srl",
    "wof:placetype":"venue"
},
  "geometry": {"coordinates":[11.196618,43.83778],"type":"Point"}
}