{
  "type": "Feature",
  "properties": {
    "iso:country":"IT",
    "sg:address":"28100 Novara",
    "sg:city":"Novara",
    "sg:orig_category":"Prodotti Chimici Di Base. Forniture Per Attivita' Industriali",
    "sg:phone":"+39 0321 397556",
    "sg:postcode":"28100",
    "sg:province":"Novara",
    "wof:name":"Interskins S.r.l.",
    "wof:placetype":"venue"
},
  "geometry": {"coordinates":[8.623249054,45.4451904297],"type":"Point"}
}