{
  "type": "Feature",
  "properties": {
    "addr:full":"27020 Torre D'isola Pavia 27020",
    "addr:postcode":"27020;27020",
    "iso:country":"IT",
    "sg:address":"27020 Torre D'isola",
    "sg:orig_category":"Forniture E Materiali Per Imballaggio E Confezionamento",
    "sg:phone":"+39 0382 930767",
    "sg:postcode":"27020",
    "sg:province":"Pavia",
    "wof:name":"Alucapvit Spa",
    "wof:placetype":"venue"
},
  "geometry": {"coordinates":[9.0398607254,45.2504882812],"type":"Point"}
}