{
  "type": "Feature",
  "properties": {
    "iso:country":"IT",
    "sg:address":"P. Mazzini, 6; Chiesina; 51013",
    "sg:classifiers":[
        {
            "category":"Banks & Credit Unions",
            "subcategory":"Bank",
            "type":"Services"
        }
    ],
    "sg:phone":"+39 0572 489084",
    "sg:postcode":"51013",
    "sg:province":"Pistoia",
    "wof:name":"Banca Popolare Di Novara",
    "wof:placetype":"venue"
},
  "geometry": {"coordinates":[10.763533,43.870071],"type":"Point"}
}