{
  "type": "Feature",
  "properties": {
    "iso:country":"IT",
    "sg:address":"55012 Capannori",
    "sg:city":"Capannori",
    "sg:orig_category":"Lavorazioni Meccaniche E Servizi",
    "sg:phone":"+39 0583 947127",
    "sg:postcode":"55012",
    "sg:province":"Lucca",
    "wof:name":"Officina Meccanica G.m.m. Snc Di Sani G. & C.",
    "wof:placetype":"venue"
},
  "geometry": {"coordinates":[10.504041,43.81068],"type":"Point"}
}