{
  "type": "Feature",
  "properties": {
    "iso:country":"IT",
    "sg:address":"60019 Senigallia",
    "sg:city":"Senigallia",
    "sg:classifiers":[
        {
            "category":"Professional",
            "type":"Services"
        }
    ],
    "sg:phone":"+39 071 668084",
    "sg:postcode":"60019",
    "sg:province":"Ancona",
    "sg:tags":[
        "activities",
        "supply",
        "commercial",
        "artisan",
        "supplies",
        "accommodation"
    ],
    "wof:name":"Panificio Adriatico Srl",
    "wof:placetype":"venue"
},
  "geometry": {"coordinates":[13.197106,43.68961],"type":"Point"}
}