{
  "type": "Feature",
  "properties": {
    "addr:full":"20090 Segrate Segrate Milano 20090",
    "addr:postcode":"20090;20090",
    "iso:country":"IT",
    "sg:address":"20090 Segrate",
    "sg:city":"Segrate",
    "sg:orig_category":"Tubi Acciaio",
    "sg:phone":"+39 02 7020 0080",
    "sg:postcode":"20090",
    "sg:province":"Milano",
    "wof:name":"Trafilturbi Srl",
    "wof:placetype":"venue"
},
  "geometry": {"coordinates":[9.258446,45.471252],"type":"Point"}
}