{
  "type": "Feature",
  "properties": {
    "iso:country":"IT",
    "sg:address":"Via Quarta Strada, 71/73 36071 Arzignano",
    "sg:city":"Arzignano",
    "sg:classifiers":[
        {
            "category":"Shopping",
            "subcategory":"Shoes",
            "type":"Retail Goods"
        }
    ],
    "sg:phone":"+39 0444 671670",
    "sg:postcode":"36071",
    "sg:province":"Vicenza",
    "sg:tags":[
        "leather",
        "chemical",
        "product",
        "industry"
    ],
    "sg:website":"www.corichem.it",
    "wof:name":"Corichem Srl",
    "wof:placetype":"venue"
},
  "geometry": {"coordinates":[11.358944,45.508675],"type":"Point"}
}