{
  "type": "Feature",
  "properties": {
    "iso:country":"IT",
    "sg:address":"84025 Eboli",
    "sg:city":"Eboli",
    "sg:orig_category":"Automobili E Mezzi Di Trasporto",
    "sg:phone":"+39 0828 361539",
    "sg:postcode":"84025",
    "sg:province":"Salerno",
    "wof:name":"C.r.e. Costruzione Ribaltabili Ebolitana",
    "wof:placetype":"venue"
},
  "geometry": {"coordinates":[15.054687,40.604561],"type":"Point"}
}