{
  "type": "Feature",
  "properties": {
    "iso:country":"IT",
    "sg:address":"50123 Firenze",
    "sg:city":"Firenze",
    "sg:orig_category":"Abbigliamento Esterno, Maglierie E Pelliccerie. Sport - Articoli E Forniture. Shopping",
    "sg:phone":"+39 055 216693",
    "sg:postcode":"50123",
    "sg:province":"Firenze",
    "wof:name":"Mr Sport Srl",
    "wof:placetype":"venue"
},
  "geometry": {"coordinates":[11.249824,43.771217],"type":"Point"}
}