{
  "type": "Feature",
  "properties": {
    "iso:country":"IT",
    "sg:address":"Localita Cason Degli Ulivi 1 37010 Rivoli Veronese",
    "sg:city":"Rivoli Veronese",
    "sg:classifiers":[
        {
            "category":"Banks & Credit Unions",
            "subcategory":"Investment Brokerage",
            "type":"Services"
        }
    ],
    "sg:phone":"+39 045 728 0158",
    "sg:postcode":"37010",
    "sg:province":"Verona",
    "sg:tags":[
        "work",
        "marble"
    ],
    "sg:website":"www.renatodallacosta.com",
    "wof:name":"Dalla Costa Renato",
    "wof:placetype":"venue"
},
  "geometry": {"coordinates":[10.806613,45.544552],"type":"Point"}
}