{
  "type": "Feature",
  "properties": {
    "iso:country":"IT",
    "sg:address":"88841 Isola Capo Rizzuto",
    "sg:orig_category":"Campeggio. Alberghi E Strutture Extra Alberghiere",
    "sg:phone":"+39 0962 799205",
    "sg:postcode":"88841",
    "sg:province":"Crotone",
    "sg:website":"http://www.capopiccolo.it",
    "wof:name":"Club Gestioni Turistiche Piccoli Soc.coop.r.l.",
    "wof:placetype":"venue"
},
  "geometry": {"coordinates":[17.093561,38.959587],"type":"Point"}
}