{
  "type": "Feature",
  "properties": {
    "addr:full":"27028 S. Martino Siccomario Pavia 27028",
    "addr:housenumber":"27028",
    "addr:postcode":"27028",
    "addr:street":"S. Martino Siccomario",
    "iso:country":"IT",
    "sg:address":"27028 S. Martino Siccomario",
    "sg:orig_category":"Carta, Cartone E Prodotti Primari. Forniture E Materiali Per Imballaggio E Confezionamento",
    "sg:phone":"+39 0382 556301",
    "sg:postcode":"27028",
    "sg:province":"Pavia",
    "wof:name":"Fratelli Bersini Snc Di Bersini Sergio & C.",
    "wof:placetype":"venue"
},
  "geometry": {"coordinates":[9.119933,45.141689],"type":"Point"}
}