{
  "type": "Feature",
  "properties": {
    "iso:country":"IT",
    "sg:address":"89, Via Casellina 50018 Scandicci",
    "sg:city":"Casellina",
    "sg:classifiers":[
        {
            "category":"Wholesale",
            "subcategory":"Drugs",
            "type":"Manufacturing & Wholesale Goods"
        }
    ],
    "sg:phone":"+39 39055755225",
    "sg:postcode":"50018",
    "sg:province":"Firenze",
    "sg:tags":[
        "chemical",
        "pharmaceutical"
    ],
    "wof:name":"Petroli Firenze S.p.a.",
    "wof:placetype":"venue"
},
  "geometry": {"coordinates":[11.157589,43.754967],"type":"Point"}
}