{
  "type": "Feature",
  "properties": {
    "iso:country":"IT",
    "sg:address":"Via Rossa G. 40033 Casalecchio Di Reno",
    "sg:city":"Casalecchio di Reno",
    "sg:classifiers":[
        {
            "category":"Professional",
            "subcategory":"Engineering",
            "type":"Services"
        }
    ],
    "sg:phone":"+39 051 613 2414",
    "sg:postcode":"40033",
    "sg:province":"Bologna",
    "sg:tags":[
        "machine",
        "-",
        "mechanical"
    ],
    "wof:name":"M.c. Automations Srl",
    "wof:placetype":"venue"
},
  "geometry": {"coordinates":[11.265407,44.489323],"type":"Point"}
}