{
  "type": "Feature",
  "properties": {
    "iso:country":"IT",
    "sg:address":"25068 Sarezzo",
    "sg:city":"Sarezzo",
    "sg:orig_category":"Acciaierie E Fonderie. Arte Ed Artigianato Artistico",
    "sg:phone":"+39 030 890 0650",
    "sg:postcode":"25068",
    "sg:province":"Brescia",
    "wof:name":"Antik Ars (s.r.l.)",
    "wof:placetype":"venue"
},
  "geometry": {"coordinates":[10.204224,45.649307],"type":"Point"}
}