{
  "type": "Feature",
  "properties": {
    "addr:full":"20136 Milano Milano Milano 20136",
    "addr:postcode":"20136;20136",
    "iso:country":"IT",
    "sg:address":"20136 Milano",
    "sg:city":"Milano",
    "sg:orig_category":"Servizi Culturali E Per Lo Spettacolo. Servizi Al Turismo. Acqua, Luce, Gas E Societa' Di Esercizio Pubblico",
    "sg:phone":"+39 02 833891",
    "sg:postcode":"20136",
    "sg:province":"Milano",
    "wof:name":"Auditorium Di Milano",
    "wof:placetype":"venue"
},
  "geometry": {"coordinates":[9.179526,45.447556],"type":"Point"}
}