{
  "type": "Feature",
  "properties": {
    "iso:country":"IT",
    "sg:address":"59100 Prato",
    "sg:city":"Prato",
    "sg:classifiers":[
        {
            "category":"Health Services",
            "subcategory":"Hospital",
            "type":"Services"
        }
    ],
    "sg:phone":"+39 0574 623696",
    "sg:postcode":"59100",
    "sg:province":"Prato",
    "sg:tags":[
        "control",
        "refuse",
        "auxiliary",
        "disposal",
        "analysis",
        "research",
        "environmental",
        "protection",
        "services",
        "works"
    ],
    "wof:name":"Centro Servizi Tessili Srl",
    "wof:placetype":"venue"
},
  "geometry": {"coordinates":[11.042212,43.860313],"type":"Point"}
}