{
  "type": "Feature",
  "properties": {
    "iso:country":"IT",
    "sg:address":"36061 Bassano Del Grappa",
    "sg:city":"Bassano del Grappa",
    "sg:orig_category":"Macchine E Forniture Per Arredamento E Industria Del Legno. Colori, Vernici E Smalti",
    "sg:phone":"+39 0424 567805",
    "sg:postcode":"36061",
    "sg:province":"Vicenza",
    "wof:name":"Edil Color Designer Di Bonamigo Silvano",
    "wof:placetype":"venue"
},
  "geometry": {"coordinates":[11.710814,45.749134],"type":"Point"}
}