{
  "type": "Feature",
  "properties": {
    "iso:country":"IT",
    "sg:address":"00181 Roma",
    "sg:city":"Roma",
    "sg:orig_category":"Pianoforti",
    "sg:phone":"+39 06 785 6263",
    "sg:postcode":"00181",
    "sg:province":"Roma",
    "sg:website":"http://www.spevi-pianoforti.com",
    "wof:name":"Spedicato Antonio",
    "wof:placetype":"venue"
},
  "geometry": {"coordinates":[12.5314006805,41.8720932007],"type":"Point"}
}