{
  "type": "Feature",
  "properties": {
    "iso:country":"IT",
    "sg:address":"96100 Siracusa",
    "sg:city":"Siracusa",
    "sg:orig_category":"Macchine E Forniture Per Ecologia E Smaltimento Rifiuti. Termotecnica E Riscaldamento, Apparecchiature E Servizi",
    "sg:phone":"+39 0931 64138",
    "sg:postcode":"96100",
    "sg:province":"Siracusa",
    "wof:name":"Due Effe Di Fontana Corrado & C. Sas",
    "wof:placetype":"venue"
},
  "geometry": {"coordinates":[15.196079,37.056709],"type":"Point"}
}