{
  "type": "Feature",
  "properties": {
    "iso:country":"IT",
    "sg:address":"00060 Roma",
    "sg:orig_category":"Forniture Per Agricoltura E Zootecnia",
    "sg:phone":"+39 06 304 6046",
    "sg:postcode":"00060",
    "sg:province":"Roma",
    "wof:name":"Appolloni Mario",
    "wof:placetype":"venue"
},
  "geometry": {"coordinates":[12.2798280716,42.0873374939],"type":"Point"}
}