{
  "type": "Feature",
  "properties": {
    "addr:full":"30, V. Dell'artigianato 36057 Arcugnano Arcugnano Vicenza 36057",
    "addr:housenumber":"30",
    "addr:postcode":"36057;36057",
    "addr:street":"V. Dell'Artigianato",
    "iso:country":"IT",
    "sg:address":"30, V. Dell'artigianato 36057 Arcugnano",
    "sg:city":"Arcugnano",
    "sg:orig_category":"Miscellaneous Products",
    "sg:phone":"+39 0444 532078",
    "sg:postcode":"36057",
    "sg:province":"Vicenza",
    "sg:website":"http://www.paginegialle.it/fotoapplicazioni",
    "wof:name":"Foto Applicazioni Snc",
    "wof:placetype":"venue"
},
  "geometry": {"coordinates":[11.5174741745,45.5291442871],"type":"Point"}
}