{
  "type": "Feature",
  "properties": {
    "iso:country":"IT",
    "sg:address":"53, Via Salemi 00133 Roma",
    "sg:city":"Roma",
    "sg:classifiers":[
        {
            "category":"Home & Garden",
            "subcategory":"Home Furnishings",
            "type":"Retail Goods"
        }
    ],
    "sg:phone":"+39 39062050672",
    "sg:postcode":"00133",
    "sg:province":"Roma",
    "sg:tags":[
        "household"
    ],
    "wof:name":"Caema Srl",
    "wof:placetype":"venue"
},
  "geometry": {"coordinates":[12.651641,41.865967],"type":"Point"}
}