{
  "type": "Feature",
  "properties": {
    "addr:full":"15, Via Cavour 24066 Pedrengo Pedrengo Bergamo 24066",
    "addr:postcode":"24066;24066",
    "addr:street":"Via Cavour",
    "iso:country":"IT",
    "sg:address":"15, Via Cavour 24066 Pedrengo",
    "sg:city":"Pedrengo",
    "sg:classifiers":[
        {
            "category":"Professional",
            "subcategory":"Engineering",
            "type":"Services"
        }
    ],
    "sg:phone":"+39 39035663064",
    "sg:postcode":"24066",
    "sg:province":"Bergamo",
    "sg:tags":[
        "machine",
        "-",
        "mechanical"
    ],
    "wof:name":"Omegher (s.r.l.)",
    "wof:placetype":"venue"
},
  "geometry": {"coordinates":[9.747337,45.688869],"type":"Point"}
}