{
  "type": "Feature",
  "properties": {
    "iso:country":"IT",
    "sg:address":"63023 Fermo",
    "sg:city":"Campiglione",
    "sg:orig_category":"Surgelati Alimentari - Produzione E Ingrosso",
    "sg:phone":"+39 0734 605068",
    "sg:postcode":"63023",
    "sg:province":"Ascoli Piceno",
    "wof:name":"Vittoria Srl",
    "wof:placetype":"venue"
},
  "geometry": {"coordinates":[13.670963,43.178444],"type":"Point"}
}