{
  "type": "Feature",
  "properties": {
    "addr:full":"40026 Imola Imola Bologna 40026",
    "addr:postcode":"40026;40026",
    "iso:country":"IT",
    "sg:address":"40026 Imola",
    "sg:city":"Imola",
    "sg:orig_category":"Arredo Camera Letto E Complementi. Servizi E Lavori Per Arredamento E Industria Del Legno",
    "sg:phone":"+39 0542 641908",
    "sg:postcode":"40026",
    "sg:province":"Bologna",
    "wof:name":"Muccinelli Paolo L.i.t.a.",
    "wof:placetype":"venue"
},
  "geometry": {"coordinates":[11.501509,44.436287],"type":"Point"}
}