{
  "type": "Feature",
  "properties": {
    "iso:country":"IT",
    "sg:address":"332, Via Pompeiana 63023 Fermo",
    "sg:city":"Fermo",
    "sg:classifiers":[
        {
            "category":"Professional",
            "subcategory":"Printing & Photocopies",
            "type":"Services"
        }
    ],
    "sg:phone":"+39 39073421581",
    "sg:postcode":"63023",
    "sg:province":"Ascoli Piceno",
    "wof:name":"Tipolitografia Gicherstampa S.n.c.",
    "wof:placetype":"venue"
},
  "geometry": {"coordinates":[13.7512626648,43.1604423523],"type":"Point"}
}