{
  "type": "Feature",
  "properties": {
    "iso:country":"IT",
    "sg:address":"09100 Cagliari",
    "sg:orig_category":"Telecomunicazioni Impianti Ed Apparecchi - Produzione E Ingrosso",
    "sg:phone":"+39 070 497495",
    "sg:province":"CA",
    "wof:name":"Teleco Srl",
    "wof:placetype":"venue"
},
  "geometry": {"coordinates":[11.828918,45.655518],"type":"Point"}
}