{
  "type": "Feature",
  "properties": {
    "iso:country":"IT",
    "sg:address":"20143 Milano",
    "sg:city":"Milano",
    "sg:orig_category":"Prodotti Cosmetici E Da Toeletta",
    "sg:phone":"+39 02 5810 0855",
    "sg:postcode":"20143",
    "sg:province":"Milano",
    "wof:name":"Rance' & C.",
    "wof:placetype":"venue"
},
  "geometry": {"coordinates":[9.1646203995,45.4484100342],"type":"Point"}
}