{
  "type": "Feature",
  "properties": {
    "iso:country":"IT",
    "sg:address":"22060 Carugo",
    "sg:city":"Carugo",
    "sg:orig_category":"Apparecchiature E Sistemi Per Magazzinaggio E Movimentazione",
    "sg:phone":"+39 031 749442",
    "sg:postcode":"22060",
    "sg:province":"Como",
    "wof:name":"Riva Renzo & C. Snc",
    "wof:placetype":"venue"
},
  "geometry": {"coordinates":[9.143077,45.802677],"type":"Point"}
}