{
  "type": "Feature",
  "properties": {
    "iso:country":"IT",
    "sg:address":"18, Via Per Domo 21010 Porto Valtravaglia",
    "sg:city":"Domo",
    "sg:classifiers":[
        {
            "category":"Professional",
            "subcategory":"Business Services",
            "type":"Services"
        }
    ],
    "sg:phone":"+39 0332 548831",
    "sg:postcode":"21010",
    "sg:province":"Varese",
    "sg:tags":[
        "advice"
    ],
    "wof:name":"I.n.c.a. S.r.l.",
    "wof:placetype":"venue"
},
  "geometry": {"coordinates":[8.691696,45.954365],"type":"Point"}
}