{
  "type": "Feature",
  "properties": {
    "iso:country":"IT",
    "sg:address":"20040 Busnago",
    "sg:city":"Busnago",
    "sg:orig_category":"Molle - Produzione E Commercio",
    "sg:phone":"+39 039 695 7618",
    "sg:postcode":"20040",
    "sg:province":"Milano",
    "wof:name":"Mollificio Marchesi Srl",
    "wof:placetype":"venue"
},
  "geometry": {"coordinates":[9.4503107071,45.616153717],"type":"Point"}
}