{
  "type": "Feature",
  "properties": {
    "addr:full":"70014 Conversano Conversano Bari 70014",
    "addr:postcode":"70014;70014",
    "iso:country":"IT",
    "sg:address":"70014 Conversano",
    "sg:city":"Conversano",
    "sg:orig_category":"Petroli, Gas E Combustibili",
    "sg:phone":"+39 080 495 1856",
    "sg:postcode":"70014",
    "sg:province":"Bari",
    "wof:name":"La Selva Francesco",
    "wof:placetype":"venue"
},
  "geometry": {"coordinates":[17.1057090759,40.9649887085],"type":"Point"}
}