{
  "type": "Feature",
  "properties": {
    "iso:country":"IT",
    "sg:address":"20093 Cologno Monzese",
    "sg:city":"Cologno Monzese",
    "sg:orig_category":"Impiantistica E Prodotti Tecnologici Per Edilizia. Servizi Ausiliari Di Sorveglianza, Manutenzione E Pulizia",
    "sg:phone":"+39 02 2730 5790",
    "sg:postcode":"20093",
    "sg:province":"Milano",
    "wof:name":"G.t.m.-gas Tecnici Milano S.r.l.",
    "wof:placetype":"venue"
},
  "geometry": {"coordinates":[9.280931,45.54314],"type":"Point"}
}