{
  "type": "Feature",
  "properties": {
    "iso:country":"IT",
    "sg:address":"47822 Santarcangelo Di Romagna",
    "sg:city":"Santarcangelo di Romagna",
    "sg:orig_category":"Studi Tecnici Ed Industriali",
    "sg:phone":"+39 0541 622651",
    "sg:postcode":"47822",
    "sg:province":"Rimini",
    "wof:name":"Esa Progetti Studio Associato Di Mami E Ottaviani",
    "wof:placetype":"venue"
},
  "geometry": {"coordinates":[12.449522,44.047272],"type":"Point"}
}