{
  "type": "Feature",
  "properties": {
    "iso:country":"IT",
    "sg:address":"90039 Villabate",
    "sg:city":"Villabate",
    "sg:classifiers":[
        {
            "category":"Health Services",
            "subcategory":"Health Practitioner",
            "type":"Services"
        }
    ],
    "sg:phone":"+39 091 614 3536",
    "sg:postcode":"90039",
    "sg:province":"Palermo",
    "sg:tags":[
        "medici"
    ],
    "wof:name":"Fisiomel Snc",
    "wof:placetype":"venue"
},
  "geometry": {"coordinates":[13.448165,38.075466],"type":"Point"}
}