{
  "type": "Feature",
  "properties": {
    "iso:country":"IT",
    "sg:address":"37134 Verona",
    "sg:city":"Verona",
    "sg:orig_category":"Trasporti E Spedizioni Merci",
    "sg:phone":"+39 045 826 6079",
    "sg:postcode":"37134",
    "sg:province":"Verona",
    "wof:name":"Sart Autotrasporti Verona Srl",
    "wof:placetype":"venue"
},
  "geometry": {"coordinates":[11.013331,45.403858],"type":"Point"}
}