{
  "type": "Feature",
  "properties": {
    "addr:full":"53, Via Talete 20047 Brugherio Brugherio Milano 20047",
    "addr:postcode":"20047;20047",
    "addr:street":"Via Talete",
    "iso:country":"IT",
    "sg:address":"53, Via Talete 20047 Brugherio",
    "sg:city":"Brugherio",
    "sg:classifiers":[
        {
            "category":"Wholesale",
            "subcategory":"Drugs",
            "type":"Manufacturing & Wholesale Goods"
        }
    ],
    "sg:phone":"+39 390 392 1251",
    "sg:postcode":"20047",
    "sg:province":"Milano",
    "sg:tags":[
        "chemical",
        "pharmaceutical"
    ],
    "wof:name":"Henkel Loctite Adesivi Srl",
    "wof:placetype":"venue"
},
  "geometry": {"coordinates":[9.230153,45.521595],"type":"Point"}
}