{
  "type": "Feature",
  "properties": {
    "addr:full":"29100 Piacenza Piacenza Piacenza 29100",
    "addr:postcode":"29100;29100",
    "iso:country":"IT",
    "sg:address":"29100 Piacenza",
    "sg:city":"Piacenza",
    "sg:orig_category":"Frigotecnica, Apparecchiature E Servizi",
    "sg:phone":"+39 0523 484345",
    "sg:postcode":"29100",
    "sg:province":"Piacenza",
    "wof:name":"Frigoriferi Subacchi Snc Di Subacchi Ernesto E Carlo",
    "wof:placetype":"venue"
},
  "geometry": {"coordinates":[9.7673749924,45.050365448],"type":"Point"}
}