{
  "type": "Feature",
  "properties": {
    "addr:full":"84091 Battipaglia Battipaglia Salerno 84091",
    "addr:postcode":"84091;84091",
    "iso:country":"IT",
    "sg:address":"84091 Battipaglia",
    "sg:city":"Battipaglia",
    "sg:orig_category":"Chiese Ed Associazioni Religiose",
    "sg:phone":"+39 0828 300237",
    "sg:postcode":"84091",
    "sg:province":"Salerno",
    "wof:name":"Ente Patrimoniale",
    "wof:placetype":"venue"
},
  "geometry": {"coordinates":[14.987218,40.614826],"type":"Point"}
}