{
  "type": "Feature",
  "properties": {
    "iso:country":"IT",
    "sg:address":"16162 Genova",
    "sg:city":"Genova",
    "sg:orig_category":"Trasporti E Spedizioni Merci",
    "sg:phone":"+39 010 726 1068",
    "sg:postcode":"16162",
    "sg:province":"Genova",
    "wof:name":"Pharma Express Sas",
    "wof:placetype":"venue"
},
  "geometry": {"coordinates":[8.895795,44.469467],"type":"Point"}
}