{
  "type": "Feature",
  "properties": {
    "addr:full":"16029 Torriglia Torriglia Genova 16029",
    "addr:postcode":"16029;16029",
    "iso:country":"IT",
    "sg:address":"16029 Torriglia",
    "sg:city":"Torriglia",
    "sg:orig_category":"Pubblica Amministrazione",
    "sg:phone":"+39 010 944071",
    "sg:postcode":"16029",
    "sg:province":"Genova",
    "wof:name":"Comando Brigata Guardia Di Finanza Torriglia",
    "wof:placetype":"venue"
},
  "geometry": {"coordinates":[9.0902776718,44.4672317505],"type":"Point"}
}