{
  "type": "Feature",
  "properties": {
    "addr:full":"20099 Sesto San Giovanni Sesto San Giovanni Milano 20099",
    "addr:postcode":"20099;20099",
    "iso:country":"IT",
    "sg:address":"20099 Sesto San Giovanni",
    "sg:city":"Sesto San Giovanni",
    "sg:orig_category":"Telecomunicazioni E Telefonia, Impianti, Apparecchi E Servizi. Acqua, Luce, Gas E Societa' Di Esercizio Pubblico. Servizi Vari Di Interesse Pubblico",
    "sg:phone":"+39 02 2626 3686",
    "sg:postcode":"20099",
    "sg:province":"Milano",
    "wof:name":"Etnic Point Snc",
    "wof:placetype":"venue"
},
  "geometry": {"coordinates":[9.22937,45.532013],"type":"Point"}
}