{
  "type": "Feature",
  "properties": {
    "addr:full":"1, Via Piana 60030 Belvedere Ostrense Belvedere Ostrense Ancona 60030",
    "addr:postcode":"60030;60030",
    "addr:street":"Via Piana",
    "iso:country":"IT",
    "sg:address":"1, Via Piana 60030 Belvedere Ostrense",
    "sg:city":"Belvedere Ostrense",
    "sg:classifiers":[
        {
            "category":"Shopping",
            "subcategory":"Clothing, Apparel, & Fashions",
            "type":"Retail Goods"
        }
    ],
    "sg:phone":"+39 39073162311",
    "sg:postcode":"60030",
    "sg:province":"Ancona",
    "sg:tags":[
        "clothes"
    ],
    "wof:name":"Belvedere Confezioni Srl",
    "wof:placetype":"venue"
},
  "geometry": {"coordinates":[13.149749,43.577724],"type":"Point"}
}