{
  "type": "Feature",
  "properties": {
    "addr:full":"10023 Chieri Chieri Torino 10023",
    "addr:postcode":"10023;10023",
    "iso:country":"IT",
    "sg:address":"10023 Chieri",
    "sg:city":"Chieri",
    "sg:orig_category":"Cartotecnica E Servizi. Forniture Per Attivita' Commerciali Ed Artigianali",
    "sg:phone":"+39 011 941 5446",
    "sg:postcode":"10023",
    "sg:province":"Torino",
    "wof:name":"Artimiste S.n.c. Di G. Quattrocolo & S. Razetto",
    "wof:placetype":"venue"
},
  "geometry": {"coordinates":[7.678395,45.106792],"type":"Point"}
}