{
  "type": "Feature",
  "properties": {
    "iso:country":"IT",
    "sg:address":"Via Mantova 21; Milano; 20135",
    "sg:city":"Milano",
    "sg:classifiers":[
        {
            "category":"Banks & Credit Unions",
            "subcategory":"Bank",
            "type":"Services"
        }
    ],
    "sg:phone":"+39 02 5518 8543",
    "sg:postcode":"20135",
    "sg:province":"Milano",
    "wof:name":"Istituto Bancario, San Paolo Di Torino Spa",
    "wof:placetype":"venue"
},
  "geometry": {"coordinates":[9.20705,45.447094],"type":"Point"}
}