{
  "type": "Feature",
  "properties": {
    "iso:country":"IT",
    "sg:address":"Via Milano 94 22063 Cantu'",
    "sg:classifiers":[
        {
            "category":"Building & Trades",
            "subcategory":"Construction",
            "type":"Services"
        }
    ],
    "sg:phone":"+39 031 730373",
    "sg:postcode":"22063",
    "sg:province":"Como",
    "sg:tags":[
        "granite",
        "working"
    ],
    "sg:website":"www.solmargraniti.it",
    "wof:name":"Solmar Spa",
    "wof:placetype":"venue"
},
  "geometry": {"coordinates":[9.129192,45.735043],"type":"Point"}
}