{
  "type": "Feature",
  "properties": {
    "iso:country":"IT",
    "sg:address":"10040 Druento",
    "sg:city":"Druento",
    "sg:orig_category":"Motori Ed Organi Di Trasmissione",
    "sg:phone":"+39 011 984444",
    "sg:postcode":"10040",
    "sg:province":"Torino",
    "wof:name":"Co.m.ing Srl",
    "wof:placetype":"venue"
},
  "geometry": {"coordinates":[7.5916028023,45.1269874573],"type":"Point"}
}