{
  "type": "Feature",
  "properties": {
    "iso:country":"IT",
    "sg:address":"07014 Ozieri",
    "sg:city":"Ozieri",
    "sg:orig_category":"Attrezzature E Forniture Per Officine Riparazione E Servizi Ausiliari",
    "sg:phone":"+39 079 780266",
    "sg:postcode":"07014",
    "sg:province":"Sassari",
    "wof:name":"Az Car Di Saba Vincenzo",
    "wof:placetype":"venue"
},
  "geometry": {"coordinates":[8.946614,40.631954],"type":"Point"}
}