{
  "type": "Feature",
  "properties": {
    "addr:full":"359, Via Matteotti Giacomo 25063 Gardone Val Trompia Gardone Val Trompia Brescia 25063",
    "addr:housenumber":"359",
    "addr:postcode":"25063;25063",
    "addr:street":"Via Matteotti Giacomo",
    "iso:country":"IT",
    "sg:address":"359, Via Matteotti Giacomo 25063 Gardone Val Trompia",
    "sg:city":"Gardone Val Trompia",
    "sg:classifiers":[
        {
            "category":"Manufacturing",
            "subcategory":"Lumber",
            "type":"Manufacturing & Wholesale Goods"
        }
    ],
    "sg:phone":"+39 030 891 2819",
    "sg:postcode":"25063",
    "sg:province":"Brescia",
    "sg:tags":[
        "wood"
    ],
    "wof:name":"Tirelli Di Tirelli Primo E C. (s.n.c.)",
    "wof:placetype":"venue"
},
  "geometry": {"coordinates":[10.222958,45.539829],"type":"Point"}
}