{
  "type": "Feature",
  "properties": {
    "addr:full":"51018 Pieve A Nievole Pieve a Nievole Pistoia 51018",
    "addr:postcode":"51018;51018",
    "addr:street":"A Nievole",
    "iso:country":"IT",
    "sg:address":"51018 Pieve A Nievole",
    "sg:city":"Pieve a Nievole",
    "sg:orig_category":"Serramenti Ed Infissi",
    "sg:phone":"+39 0572 80787",
    "sg:postcode":"51018",
    "sg:province":"Pistoia",
    "wof:name":"Guidi & Bernardi Snc",
    "wof:placetype":"venue"
},
  "geometry": {"coordinates":[10.842136,43.919289],"type":"Point"}
}