{
  "type": "Feature",
  "properties": {
    "addr:full":"182, Via Giuseppe Verdi 64016 Sant'egidio Alla Vibrata Teramo 64016",
    "addr:housenumber":"182",
    "addr:postcode":"64016;64016",
    "addr:street":"Via Giuseppe Verdi",
    "iso:country":"IT",
    "sg:address":"182, Via Giuseppe Verdi 64016 Sant'egidio Alla Vibrata",
    "sg:classifiers":[
        {
            "category":"Shopping",
            "subcategory":"Clothing, Apparel, & Fashions",
            "type":"Retail Goods"
        }
    ],
    "sg:phone":"+39 0861 841587",
    "sg:postcode":"64016",
    "sg:province":"Teramo",
    "sg:tags":[
        "clothes"
    ],
    "wof:name":"Camiceria Cristian Di Caioni Delia",
    "wof:placetype":"venue"
},
  "geometry": {"coordinates":[13.716369,42.816761],"type":"Point"}
}