{
  "type": "Feature",
  "properties": {
    "iso:country":"IT",
    "sg:address":"19, Via Fabio Massimo 74024 Manduria",
    "sg:city":"Manduria",
    "sg:classifiers":[
        {
            "category":"Food & Beverages",
            "subcategory":"Groceries & Convenience Stores",
            "type":"Retail Goods"
        }
    ],
    "sg:phone":"+39 099 973 5332",
    "sg:postcode":"74024",
    "sg:province":"Taranto",
    "sg:tags":[
        "drink"
    ],
    "wof:name":"Consorzio Produttori Vini",
    "wof:placetype":"venue"
},
  "geometry": {"coordinates":[17.639254,40.404766],"type":"Point"}
}