{
  "type": "Feature",
  "properties": {
    "iso:country":"IT",
    "sg:address":"35030 Veggiano",
    "sg:city":"Veggiano",
    "sg:orig_category":"Carpenterie Metalliche",
    "sg:phone":"+39 049 900 0315",
    "sg:postcode":"35030",
    "sg:province":"Padova",
    "wof:name":"Tommasin & C. Srl",
    "wof:placetype":"venue"
},
  "geometry": {"coordinates":[11.747665,45.467091],"type":"Point"}
}