{
  "type": "Feature",
  "properties": {
    "iso:country":"IT",
    "sg:address":"Piazza Toscanini 2/1; Pozza Di Maranello; 41053",
    "sg:city":"Maranello",
    "sg:classifiers":[
        {
            "category":"Banks & Credit Unions",
            "subcategory":"Bank",
            "type":"Services"
        }
    ],
    "sg:phone":"+39 0536 948893",
    "sg:postcode":"41053",
    "sg:province":"Modena",
    "wof:name":"Banca Popolare Di Verona",
    "wof:placetype":"venue"
},
  "geometry": {"coordinates":[10.894154,44.526497],"type":"Point"}
}