{
  "type": "Feature",
  "properties": {
    "iso:country":"IT",
    "sg:address":"Piazza Monumento 26 24060 Zandobbio",
    "sg:city":"Zandobbio",
    "sg:classifiers":[
        {
            "category":"Manufacturing",
            "subcategory":"Tools & Machinery",
            "type":"Manufacturing & Wholesale Goods"
        }
    ],
    "sg:phone":"+39 035 945253",
    "sg:postcode":"24060",
    "sg:province":"Bergamo",
    "sg:tags":[
        "stone",
        "diamond",
        "working"
    ],
    "sg:website":"www.carpediemsrl.it",
    "wof:name":"Carpe Diem Srl",
    "wof:placetype":"venue"
},
  "geometry": {"coordinates":[9.852483,45.688362],"type":"Point"}
}