{
  "type": "Feature",
  "properties": {
    "iso:country":"IT",
    "sg:address":"42100 Reggio Emilia",
    "sg:orig_category":"Materiali Semilavorati Metallici",
    "sg:phone":"+39 0522 941161",
    "sg:postcode":"42100",
    "sg:province":"Reggio Nell'Emilia",
    "wof:name":"Catellani Tubi E Lamiere Srl",
    "wof:placetype":"venue"
},
  "geometry": {"coordinates":[10.555417,44.722572],"type":"Point"}
}