{
  "type": "Feature",
  "properties": {
    "iso:country":"IT",
    "sg:address":"10147 Torino",
    "sg:city":"Torino",
    "sg:orig_category":"Carni, Salumi E Pesci",
    "sg:phone":"+39 011 216 8985",
    "sg:postcode":"10147",
    "sg:province":"Torino",
    "wof:name":"Marzulli Lidia",
    "wof:placetype":"venue"
},
  "geometry": {"coordinates":[7.677018,45.094902],"type":"Point"}
}