{
  "type": "Feature",
  "properties": {
    "iso:country":"IT",
    "sg:address":"10, V. Per Olginate Molgora 23883 Brivio",
    "sg:city":"Brivio",
    "sg:classifiers":[
        {
            "category":"Manufacturing",
            "subcategory":"Rubber & Plastics",
            "type":"Manufacturing & Wholesale Goods"
        }
    ],
    "sg:phone":"+39 039 532 0586",
    "sg:postcode":"23883",
    "sg:province":"Lecco",
    "sg:website":"http://web.tiscali.it/sca.plast-wolit",
    "wof:name":"Sca-plast Snc",
    "wof:placetype":"venue"
},
  "geometry": {"coordinates":[9.3900709152,45.8529815674],"type":"Point"}
}