{
  "type": "Feature",
  "properties": {
    "addr:full":"Sda Biccari Troia 10000 71032 Biccari Biccari Foggia 71032",
    "addr:postcode":"10000 71032;71032",
    "addr:street":"Biccari",
    "iso:country":"IT",
    "sg:address":"Sda Biccari Troia 10000 71032 Biccari",
    "sg:city":"Biccari",
    "sg:classifiers":[
        {
            "category":"Taxi",
            "type":"Transportation"
        }
    ],
    "sg:phone":"+39 0881 591280",
    "sg:postcode":"71032",
    "sg:province":"Foggia",
    "sg:tags":[
        "vacuum-formed",
        "packing"
    ],
    "sg:website":"www.irbiccari.it",
    "wof:name":"Industria Resine Biccari S.p.a.",
    "wof:placetype":"venue"
},
  "geometry": {"coordinates":[15.5447,41.462334],"type":"Point"}
}