{
  "type": "Feature",
  "properties": {
    "addr:full":"Corso Persiani 45; Recanati; 62019 Recanati Macerata 62019",
    "addr:housenumber":"45",
    "addr:postcode":"62019;62019",
    "addr:street":"Corso Persiani",
    "iso:country":"IT",
    "sg:address":"Corso Persiani 45; Recanati; 62019",
    "sg:city":"Recanati",
    "sg:classifiers":[
        {
            "category":"Banks & Credit Unions",
            "subcategory":"Bank",
            "type":"Services"
        }
    ],
    "sg:phone":"+39 071 757 3581",
    "sg:postcode":"62019",
    "sg:province":"Macerata",
    "wof:name":"Banca Delle Marche Spa",
    "wof:placetype":"venue"
},
  "geometry": {"coordinates":[13.547661,43.404667],"type":"Point"}
}