{
  "type": "Feature",
  "properties": {
    "iso:country":"IT",
    "sg:address":"Via Prov. Le Piazza; Caulonia; 89041",
    "sg:city":"Caulonia",
    "sg:classifiers":[
        {
            "category":"Banks & Credit Unions",
            "subcategory":"Bank",
            "type":"Services"
        }
    ],
    "sg:phone":"+39 0964 83110",
    "sg:postcode":"89041",
    "sg:province":"Reggio Di Calabria",
    "wof:name":"Banco Di Napoli Spa",
    "wof:placetype":"venue"
},
  "geometry": {"coordinates":[15.645786,38.102974],"type":"Point"}
}