{
  "type": "Feature",
  "properties": {
    "iso:country":"IT",
    "sg:address":"3, Via Toscanini 24040 Stezzano",
    "sg:city":"Stezzano",
    "sg:classifiers":[
        {
            "category":"Shopping",
            "subcategory":"Crafts & Fabrics",
            "type":"Retail Goods"
        }
    ],
    "sg:phone":"+39 39035591039",
    "sg:postcode":"24040",
    "sg:province":"Bergamo",
    "wof:name":"Rota Virgilio (s.r.l.)",
    "wof:placetype":"venue"
},
  "geometry": {"coordinates":[9.6479024887,45.6552848816],"type":"Point"}
}