{
  "type": "Feature",
  "properties": {
    "iso:country":"IT",
    "sg:address":"3, Regione Catena Rossa 12040 Piobesi D'alba",
    "sg:classifiers":[
        {
            "category":"Wholesale",
            "subcategory":"Machinery & Supplies",
            "type":"Manufacturing & Wholesale Goods"
        }
    ],
    "sg:phone":"+39 0173 290607",
    "sg:postcode":"12040",
    "sg:province":"Cuneo",
    "sg:tags":[
        "-",
        "agriculture",
        "equipment"
    ],
    "wof:name":"Palladino Di Palladino Piergiorgio & C S.n.c.",
    "wof:placetype":"venue"
},
  "geometry": {"coordinates":[7.547111,44.388798],"type":"Point"}
}