{
  "type": "Feature",
  "properties": {
    "addr:full":"3, Via Martiri Di Belfiore 20052 Monza Monza Milano 20052",
    "addr:postcode":"20052;20052",
    "addr:street":"Via Martiri Di Belfiore",
    "iso:country":"IT",
    "sg:address":"3, Via Martiri Di Belfiore 20052 Monza",
    "sg:city":"Monza",
    "sg:classifiers":[
        {
            "category":"Food & Beverages",
            "subcategory":"Groceries & Convenience Stores",
            "type":"Retail Goods"
        }
    ],
    "sg:phone":"+39 39039733291",
    "sg:postcode":"20052",
    "sg:province":"Milano",
    "sg:tags":[
        "product",
        "related"
    ],
    "wof:name":"Presto Chef Di Jannacci Tiziano",
    "wof:placetype":"venue"
},
  "geometry": {"coordinates":[9.2417602539,45.5688362122],"type":"Point"}
}