{
  "type": "Feature",
  "properties": {
    "iso:country":"IT",
    "sg:address":"44022 Comacchio",
    "sg:city":"Comacchio",
    "sg:orig_category":"Agenzie D'affari E Servizi Commerciali",
    "sg:phone":"+39 0533 326250",
    "sg:postcode":"44022",
    "sg:province":"Ferrara",
    "wof:name":"Immobiliare Il Porto Di Bellotti Gianluca",
    "wof:placetype":"venue"
},
  "geometry": {"coordinates":[12.243337,44.669243],"type":"Point"}
}