{
  "type": "Feature",
  "properties": {
    "iso:country":"IT",
    "sg:address":"6, Viale Dell' Industria 35020 Legnaro",
    "sg:city":"Legnaro",
    "sg:classifiers":[
        {
            "category":"Professional",
            "subcategory":"Engineering",
            "type":"Services"
        }
    ],
    "sg:phone":"+39 049 883 0300",
    "sg:postcode":"35020",
    "sg:province":"Padova",
    "sg:tags":[
        "machine",
        "-",
        "mechanical"
    ],
    "wof:name":"Femi S.r.l.",
    "wof:placetype":"venue"
},
  "geometry": {"coordinates":[11.957607,45.350498],"type":"Point"}
}