{
  "type": "Feature",
  "properties": {
    "iso:country":"IT",
    "sg:address":"2, Via Sabbionette 20050 Verano Brianza",
    "sg:city":"Verano Brianza",
    "sg:classifiers":[
        {
            "category":"Manufacturing",
            "subcategory":"Textiles",
            "type":"Manufacturing & Wholesale Goods"
        }
    ],
    "sg:phone":"+39 036 299 3618",
    "sg:postcode":"20050",
    "sg:province":"Milano",
    "sg:tags":[
        "leather",
        "raw",
        "material",
        "-"
    ],
    "wof:name":"Corame S.r.l.",
    "wof:placetype":"venue"
},
  "geometry": {"coordinates":[9.21588,45.680016],"type":"Point"}
}