{
  "type": "Feature",
  "properties": {
    "iso:country":"IT",
    "sg:address":"80128 Napoli",
    "sg:city":"Napoli",
    "sg:orig_category":"Centri Di Estetica E Cosmesi E Servizi",
    "sg:phone":"+39 081 578 1937",
    "sg:postcode":"80128",
    "sg:province":"Napoli",
    "sg:website":"http://www.enfe.it",
    "wof:name":"Enfe Center",
    "wof:placetype":"venue"
},
  "geometry": {"coordinates":[14.219248,40.849354],"type":"Point"}
}