{
  "type": "Feature",
  "properties": {
    "iso:country":"IT",
    "sg:address":"47814 Bellaria Igea Marina",
    "sg:city":"Bellaria",
    "sg:orig_category":"Frigoriferi - Accessori E Parti",
    "sg:phone":"+39 0541 331141",
    "sg:postcode":"47814",
    "sg:province":"Rimini",
    "wof:name":"Morri Cesare",
    "wof:placetype":"venue"
},
  "geometry": {"coordinates":[12.4754247665,44.1396369934],"type":"Point"}
}