{
  "type": "Feature",
  "properties": {
    "iso:country":"IT",
    "sg:address":"84, Via Del Cristo 33044 Manzano",
    "sg:city":"Manzano",
    "sg:classifiers":[
        {
            "category":"Home & Garden",
            "subcategory":"Home Furnishings",
            "type":"Retail Goods"
        }
    ],
    "sg:phone":"+39 0432 754566",
    "sg:postcode":"33044",
    "sg:province":"Udine",
    "sg:tags":[
        "household"
    ],
    "wof:name":"Bernardini Sedie (s.r.l.)",
    "wof:placetype":"venue"
},
  "geometry": {"coordinates":[13.363862,45.982132],"type":"Point"}
}