{
  "type": "Feature",
  "properties": {
    "addr:full":"22075 Lurate Caccivio Lurate Caccivio Como 22075",
    "addr:housenumber":"caccivio",
    "addr:postcode":"22075;22075",
    "addr:street":"Caccivio",
    "iso:country":"IT",
    "sg:address":"22075 Lurate Caccivio",
    "sg:city":"Lurate Caccivio",
    "sg:orig_category":"Tessuti E Stoffe. Filati E Materie Prime Tessili",
    "sg:phone":"+39 031 490022",
    "sg:postcode":"22075",
    "sg:province":"Como",
    "wof:name":"Serikos Neckwear S.r.l.",
    "wof:placetype":"venue"
},
  "geometry": {"coordinates":[9.00661,45.768272],"type":"Point"}
}