{
  "type": "Feature",
  "properties": {
    "iso:country":"IT",
    "sg:address":"20149 Milano",
    "sg:city":"Milano",
    "sg:orig_category":"Servizi E Lavori Per Abbigliamento E Pelletterie",
    "sg:phone":"+39 02 342774",
    "sg:postcode":"20149",
    "sg:province":"Milano",
    "wof:name":"Barbaro Maria Giulia",
    "wof:placetype":"venue"
},
  "geometry": {"coordinates":[9.158319,45.48616],"type":"Point"}
}