{
  "type": "Feature",
  "properties": {
    "addr:full":"7/9, Viale Grandi 42046 Reggiolo Reggio Nell'Emilia 42046",
    "addr:housenumber":"7 / 9",
    "addr:postcode":"42046;42046",
    "addr:street":"Viale Grandi",
    "iso:country":"IT",
    "sg:address":"7/9, Viale Grandi 42046 Reggiolo",
    "sg:classifiers":[
        {
            "category":"Manufacturing",
            "subcategory":"Metals",
            "type":"Manufacturing & Wholesale Goods"
        }
    ],
    "sg:phone":"+39 0522 971421",
    "sg:postcode":"42046",
    "sg:province":"Reggio Nell'Emilia",
    "sg:tags":[
        "metallurgy",
        "metalworking"
    ],
    "wof:name":"Profiltubi (s.p.a.)",
    "wof:placetype":"venue"
},
  "geometry": {"coordinates":[10.6277942657,44.6962280273],"type":"Point"}
}