{
  "type": "Feature",
  "properties": {
    "addr:full":"25080 Moniga Del Garda Moniga del Garda Brescia 25080",
    "addr:postcode":"25080;25080",
    "iso:country":"IT",
    "sg:address":"25080 Moniga Del Garda",
    "sg:city":"Moniga del Garda",
    "sg:orig_category":"Macchine Utensili E Impianti",
    "sg:phone":"+39 036 550 2132",
    "sg:postcode":"25080",
    "sg:province":"Brescia",
    "wof:name":"Graziani Rodolfo & C. (s.n.c.)",
    "wof:placetype":"venue"
},
  "geometry": {"coordinates":[10.541,45.526169],"type":"Point"}
}