{
  "type": "Feature",
  "properties": {
    "addr:full":"74023 Grottaglie Grottaglie Taranto 74023",
    "addr:postcode":"74023;74023",
    "iso:country":"IT",
    "sg:address":"74023 Grottaglie",
    "sg:city":"Grottaglie",
    "sg:orig_category":"Arredamenti E Mobili Professionali. Impianti, Attrezzature E Forniture Sanitarie Ed Ospedaliere",
    "sg:phone":"+39 099 563 8223",
    "sg:postcode":"74023",
    "sg:province":"Taranto",
    "wof:name":"Coviello Salvatore",
    "wof:placetype":"venue"
},
  "geometry": {"coordinates":[17.401098,40.468571],"type":"Point"}
}