{
  "type": "Feature",
  "properties": {
    "iso:country":"IT",
    "sg:address":"65121 Pescara",
    "sg:city":"Pescara",
    "sg:orig_category":"Scuole E Servizi Scolastici. Ricerca, Selezione E Formazione Del Personale",
    "sg:phone":"+39 085 429661",
    "sg:postcode":"65121",
    "sg:province":"Pescara",
    "sg:website":"http://www.assocommercio.it",
    "wof:name":"Assocommercio Abruzzo",
    "wof:placetype":"venue"
},
  "geometry": {"coordinates":[14.21043,42.467381],"type":"Point"}
}