{
  "type": "Feature",
  "properties": {
    "iso:country":"IT",
    "sg:address":"30124 Venezia",
    "sg:city":"Venezia",
    "sg:orig_category":"Banche Ed Istituti Di Credito E Risparmio",
    "sg:phone":"+39 041 529 1111",
    "sg:postcode":"30124",
    "sg:province":"Venezia",
    "sg:website":"http://www.carive.it",
    "wof:name":"Cassa Di Risparmio Di Venezia Spa",
    "wof:placetype":"venue"
},
  "geometry": {"coordinates":[12.335856,45.434925],"type":"Point"}
}