{
  "type": "Feature",
  "properties": {
    "addr:full":"73100 Lecce Lecce Lecce 73100",
    "addr:postcode":"73100;73100",
    "iso:country":"IT",
    "sg:address":"73100 Lecce",
    "sg:city":"Lecce",
    "sg:orig_category":"Manufacturers: Prefabbricati",
    "sg:phone":"+39 0832 312190",
    "sg:postcode":"73100",
    "sg:province":"Lecce",
    "wof:name":"Stucchi & Parati Di Mauro Colella",
    "wof:placetype":"venue"
},
  "geometry": {"coordinates":[18.184793,40.356747],"type":"Point"}
}