{
  "type": "Feature",
  "properties": {
    "iso:country":"IT",
    "sg:address":"Via Iv Novembre 8; Borghetto S. Spirito; 17020",
    "sg:classifiers":[
        {
            "category":"Banks & Credit Unions",
            "subcategory":"Bank",
            "type":"Services"
        }
    ],
    "sg:phone":"+39 0182 970064",
    "sg:postcode":"17020",
    "sg:province":"Savona",
    "wof:name":"Istituto Bancario, San Paolo Di Torino Spa",
    "wof:placetype":"venue"
},
  "geometry": {"coordinates":[8.254115,44.204857],"type":"Point"}
}