{
  "type": "Feature",
  "properties": {
    "iso:country":"IT",
    "sg:address":"24020 Peia",
    "sg:city":"Peia",
    "sg:orig_category":"Nautica. Forniture Per Attivita' Commerciali Ed Artigianali",
    "sg:phone":"+39 035 727112",
    "sg:postcode":"24020",
    "sg:province":"Bergamo",
    "wof:name":"Bosio Beniamino",
    "wof:placetype":"venue"
},
  "geometry": {"coordinates":[9.899787,45.801937],"type":"Point"}
}