{
  "type": "Feature",
  "properties": {
    "addr:full":"16, Via Falcero 13825 Valle Mosso Valle Mosso Biella 13825",
    "addr:postcode":"13825;13825",
    "addr:street":"Via Falcero;Mosso",
    "iso:country":"IT",
    "sg:address":"16, Via Falcero 13825 Valle Mosso",
    "sg:city":"Valle Mosso",
    "sg:classifiers":[
        {
            "category":"Shopping",
            "subcategory":"Crafts & Fabrics",
            "type":"Retail Goods"
        }
    ],
    "sg:phone":"+39 39015702535",
    "sg:postcode":"13825",
    "sg:province":"Biella",
    "wof:name":"Finissaggio E Tintoria Azeta Di Alberto Zanin & C. (s.r.l.)",
    "wof:placetype":"venue"
},
  "geometry": {"coordinates":[8.0582695007,45.5628356934],"type":"Point"}
}