{
  "type": "Feature",
  "properties": {
    "iso:country":"IT",
    "sg:address":"18, Via Mons. Benedini 46010 Marcaria",
    "sg:city":"Marcaria",
    "sg:classifiers":[
        {
            "category":"Home & Garden",
            "subcategory":"Home Furnishings",
            "type":"Retail Goods"
        }
    ],
    "sg:phone":"+39 0376 950521",
    "sg:postcode":"46010",
    "sg:province":"Mantova",
    "sg:tags":[
        "household"
    ],
    "wof:name":"Style House International (s.p.a.)",
    "wof:placetype":"venue"
},
  "geometry": {"coordinates":[10.797698,45.160366],"type":"Point"}
}