{
  "type": "Feature",
  "properties": {
    "iso:country":"IT",
    "sg:address":"25033 Cologne",
    "sg:city":"Cologne",
    "sg:orig_category":"Trattamenti Termici E Superficiali Metalli, Galvanotecnica",
    "sg:phone":"+39 030 715215",
    "sg:postcode":"25033",
    "sg:province":"Brescia",
    "wof:name":"Galvanica Monteorfano",
    "wof:placetype":"venue"
},
  "geometry": {"coordinates":[9.614247,45.640415],"type":"Point"}
}