{
  "type": "Feature",
  "properties": {
    "addr:full":"91025 Marsala Marsala Trapani 91025",
    "addr:postcode":"91025;91025",
    "iso:country":"IT",
    "sg:address":"91025 Marsala",
    "sg:city":"Marsala",
    "sg:orig_category":"Acque Minerali E Bevande, Naturali E Gassate - Commercio",
    "sg:phone":"+39 0923 719860",
    "sg:postcode":"91025",
    "sg:province":"Trapani",
    "wof:name":"Tumbarello Mario Davide",
    "wof:placetype":"venue"
},
  "geometry": {"coordinates":[12.444542,37.800419],"type":"Point"}
}