{
  "type": "Feature",
  "properties": {
    "iso:country":"IT",
    "sg:address":"57023 Cecina",
    "sg:city":"Cecina",
    "sg:orig_category":"Elettrotecnica Industriale, Prodotti E Apparecchiature. Elettrotecnica Professionale E Di Consumo",
    "sg:phone":"+39 0586 662382",
    "sg:postcode":"57023",
    "sg:province":"Livorno",
    "wof:name":"F.c.r. Di Roventini V. & C. Snc",
    "wof:placetype":"venue"
},
  "geometry": {"coordinates":[10.514259,43.328243],"type":"Point"}
}