{
  "type": "Feature",
  "properties": {
    "addr:full":"Via Iii Traversa Via Trani 9 70051 Barletta Barletta Bari 70051",
    "addr:housenumber":"9",
    "addr:postcode":"70051;70051",
    "addr:street":"Via Iii Traversa Via Trani",
    "iso:country":"IT",
    "sg:address":"Via Iii Traversa Via Trani 9 70051 Barletta",
    "sg:city":"Barletta",
    "sg:classifiers":[
        {
            "category":"Shopping",
            "subcategory":"Shoes",
            "type":"Retail Goods"
        }
    ],
    "sg:phone":"+39 0883 332261",
    "sg:postcode":"70051",
    "sg:province":"Bari",
    "sg:tags":[
        "children's"
    ],
    "sg:website":"www.pratika.it",
    "wof:name":"Pratika S.r.l.",
    "wof:placetype":"venue"
},
  "geometry": {"coordinates":[16.869291,41.126053],"type":"Point"}
}