{
  "type": "Feature",
  "properties": {
    "addr:full":"Area Industriale S. Mango Sul Calor 83040 Luogosano Luogosano Avellino 83040",
    "addr:postcode":"83040;83040",
    "addr:street":"Area Industriale S. Mango Sul Calor",
    "iso:country":"IT",
    "sg:address":"Area Industriale S. Mango Sul Calor 83040 Luogosano",
    "sg:city":"Luogosano",
    "sg:orig_category":"Tube Plates",
    "sg:phone":"+39 0827 79210",
    "sg:postcode":"83040",
    "sg:province":"Avellino",
    "wof:name":"Tubisud S.r.l.",
    "wof:placetype":"venue"
},
  "geometry": {"coordinates":[14.792723,40.914749],"type":"Point"}
}