{
  "type": "Feature",
  "properties": {
    "iso:country":"IT",
    "sg:address":"65015 Montesilvano",
    "sg:city":"Montesilvano",
    "sg:orig_category":"Forniture Uffici",
    "sg:phone":"+39 085 468 1677",
    "sg:postcode":"65015",
    "sg:province":"Pescara",
    "sg:website":"http://tfinformatica.it",
    "wof:name":"Tf Informatica Di Tufano Francesco",
    "wof:placetype":"venue"
},
  "geometry": {"coordinates":[14.1432580948,42.4960327148],"type":"Point"}
}