{
  "type": "Feature",
  "properties": {
    "iso:country":"IT",
    "sg:address":"05018 Orvieto",
    "sg:city":"Orvieto",
    "sg:orig_category":"Centri Di Estetica E Cosmesi E Servizi",
    "sg:phone":"+39 0763 302503",
    "sg:postcode":"05018",
    "sg:province":"Terni",
    "wof:name":"Anselmi Stefania",
    "wof:placetype":"venue"
},
  "geometry": {"coordinates":[12.112298,42.719704],"type":"Point"}
}