{
  "type": "Feature",
  "properties": {
    "iso:country":"IT",
    "sg:address":"Via Galileo Galilei 7 35042 Este",
    "sg:city":"Este",
    "sg:classifiers":[
        {
            "category":"Shopping",
            "subcategory":"Hobbies, Toys, & Games",
            "type":"Retail Goods"
        }
    ],
    "sg:phone":"+39 0429 601388",
    "sg:postcode":"35042",
    "sg:province":"Padova",
    "sg:tags":[
        "toy",
        "animals",
        "plush",
        "stuffed"
    ],
    "sg:website":"www.petratoysonline.com",
    "wof:name":"Petra Toys Di Boselli Piero",
    "wof:placetype":"venue"
},
  "geometry": {"coordinates":[11.68243,45.222992],"type":"Point"}
}