{
  "type": "Feature",
  "properties": {
    "iso:country":"IT",
    "sg:address":"80040 San Sebastiano Al Vesuvio",
    "sg:city":"San Sebastiano al Vesuvio",
    "sg:orig_category":"Valvole E Apparecchiature Di Misura",
    "sg:phone":"+39 081 771 5268",
    "sg:postcode":"80040",
    "sg:province":"Napoli",
    "wof:name":"Ascione Gabriele",
    "wof:placetype":"venue"
},
  "geometry": {"coordinates":[14.353136,40.840443],"type":"Point"}
}