{
  "type": "Feature",
  "properties": {
    "iso:country":"IT",
    "sg:address":"31045 Motta Di Livenza",
    "sg:city":"Motta di Livenza",
    "sg:orig_category":"Trasporti E Spedizioni Merci",
    "sg:phone":"+39 0422 766202",
    "sg:postcode":"31045",
    "sg:province":"Treviso",
    "wof:name":"Agroter Srl",
    "wof:placetype":"venue"
},
  "geometry": {"coordinates":[12.60401,45.777489],"type":"Point"}
}