{
  "type": "Feature",
  "properties": {
    "iso:country":"IT",
    "sg:address":"1, Via Sottoviotta 33038 San Daniele Del Friuli",
    "sg:city":"San Daniele del Friuli",
    "sg:classifiers":[
        {
            "category":"Manufacturing",
            "subcategory":"Rubber & Plastics",
            "type":"Manufacturing & Wholesale Goods"
        }
    ],
    "sg:phone":"+39 0432 955043",
    "sg:postcode":"33038",
    "sg:province":"Udine",
    "wof:name":"Tabiplastica S.r.l.",
    "wof:placetype":"venue"
},
  "geometry": {"coordinates":[13.2307243347,46.0649414062],"type":"Point"}
}