{
  "type": "Feature",
  "properties": {
    "addr:full":"14, Via Giuseppe Verdi 24060 Telgate Telgate Bergamo 24060",
    "addr:postcode":"24060;24060",
    "addr:street":"Via Giuseppe Verdi;Telgate Telgate",
    "iso:country":"IT",
    "sg:address":"14, Via Giuseppe Verdi 24060 Telgate",
    "sg:city":"Telgate",
    "sg:classifiers":[
        {
            "category":"Shopping",
            "subcategory":"Clothing, Apparel, & Fashions",
            "type":"Retail Goods"
        }
    ],
    "sg:phone":"+39 035 442 1035",
    "sg:postcode":"24060",
    "sg:province":"Bergamo",
    "sg:tags":[
        "clothes"
    ],
    "wof:name":"Ampa Industriale Italia (s.p.a.)",
    "wof:placetype":"venue"
},
  "geometry": {"coordinates":[9.846232,45.629581],"type":"Point"}
}