{
  "type": "Feature",
  "properties": {
    "iso:country":"IT",
    "sg:address":"70032 Bitonto",
    "sg:city":"Bitonto",
    "sg:orig_category":"Non-classified Establishments",
    "sg:phone":"+39 080 371 4568",
    "sg:postcode":"70032",
    "sg:province":"Bari",
    "wof:name":"Marselli Vincenzo",
    "wof:placetype":"venue"
},
  "geometry": {"coordinates":[16.749985,41.139633],"type":"Point"}
}