{
  "type": "Feature",
  "properties": {
    "iso:country":"IT",
    "sg:address":"10076 Grange",
    "sg:orig_category":"Medicinali E Prodotti Parafarmaceutici",
    "sg:phone":"+39 011 923 6915",
    "sg:postcode":"10076",
    "sg:province":"Torino",
    "wof:name":"Cerrito Alessandro",
    "wof:placetype":"venue"
},
  "geometry": {"coordinates":[7.554046154,45.2203102112],"type":"Point"}
}