{
  "type": "Feature",
  "properties": {
    "iso:country":"IT",
    "sg:address":"80142 Napoli",
    "sg:city":"Napoli",
    "sg:classifiers":[
        {
            "category":"Education",
            "subcategory":"School",
            "type":"Public Place"
        }
    ],
    "sg:phone":"+39 081 262800",
    "sg:postcode":"80142",
    "sg:province":"Napoli",
    "sg:tags":[
        "scuole",
        "informatica",
        "di"
    ],
    "sg:website":"http://www.campaniasviluppo.com",
    "wof:name":"Campania Sviluppo Sas",
    "wof:placetype":"venue"
},
  "geometry": {"coordinates":[14.234691,40.919243],"type":"Point"}
}