{
  "type": "Feature",
  "properties": {
    "addr:full":"25020 Milzano Milzano Brescia 25020",
    "addr:postcode":"25020;25020",
    "iso:country":"IT",
    "sg:address":"25020 Milzano",
    "sg:city":"Milzano",
    "sg:orig_category":"Minuterie Metalliche E Ferramenta. Forniture Per Attivita' Industriali",
    "sg:phone":"+39 030 954385",
    "sg:postcode":"25020",
    "sg:province":"Brescia",
    "wof:name":"Mollificio Bps Di Bellina E Settoni S.n.c.",
    "wof:placetype":"venue"
},
  "geometry": {"coordinates":[10.2003211975,45.2682418823],"type":"Point"}
}