{
  "type": "Feature",
  "properties": {
    "addr:full":"50050 Montaione Montaione Firenze 50050",
    "addr:postcode":"50050;50050",
    "iso:country":"IT",
    "sg:address":"50050 Montaione",
    "sg:city":"Montaione",
    "sg:orig_category":"Restaurants And Related Public Premises. Sport And Leisure, Services. Hotels And Hotel Facilities. Restaurants And Similar",
    "sg:phone":"+39 0571 677170",
    "sg:postcode":"50050",
    "sg:province":"Firenze",
    "wof:name":"Casa Masi Di Alessandro Masi & C. Snc",
    "wof:placetype":"venue"
},
  "geometry": {"coordinates":[10.889751,43.575157],"type":"Point"}
}