{
  "type": "Feature",
  "properties": {
    "iso:country":"IT",
    "sg:address":"4, Via Salvatori Padre E. 02100 Rieti",
    "sg:city":"Rieti",
    "sg:classifiers":[
        {
            "category":"Travel",
            "subcategory":"Travel Agent",
            "type":"Entertainment"
        }
    ],
    "sg:phone":"+39 0746 296471",
    "sg:postcode":"02100",
    "sg:province":"Rieti",
    "sg:tags":[
        "business"
    ],
    "wof:name":"Hotel Flash",
    "wof:placetype":"venue"
},
  "geometry": {"coordinates":[12.861179,42.403057],"type":"Point"}
}