{
  "type": "Feature",
  "properties": {
    "iso:country":"IT",
    "sg:address":"28/30, V. Venaria 10091 Alpignano",
    "sg:city":"Alpignano",
    "sg:classifiers":[
        {
            "category":"Manufacturing",
            "subcategory":"Tools & Machinery",
            "type":"Manufacturing & Wholesale Goods"
        }
    ],
    "sg:phone":"+39 011 966 1007",
    "sg:postcode":"10091",
    "sg:province":"Torino",
    "sg:tags":[
        "environment",
        "equipment",
        "-"
    ],
    "sg:website":"http://www.centrosicurezza.com",
    "wof:name":"Centro Sicurezza Italia Spa",
    "wof:placetype":"venue"
},
  "geometry": {"coordinates":[7.573666,45.092571],"type":"Point"}
}