{
  "type": "Feature",
  "properties": {
    "addr:full":"10093 Collegno Collegno Torino 10093",
    "addr:postcode":"10093;10093",
    "iso:country":"IT",
    "sg:address":"10093 Collegno",
    "sg:city":"Collegno",
    "sg:orig_category":"Articoli Pulizia. Carta, Cartone E Prodotti Primari. Prodotti Cosmetici E Da Toeletta",
    "sg:phone":"+39 011 411 6888",
    "sg:postcode":"10093",
    "sg:province":"Torino",
    "wof:name":"La Torinese Di Greppi Mauro & C. Sas",
    "wof:placetype":"venue"
},
  "geometry": {"coordinates":[7.600845,45.075878],"type":"Point"}
}