{
  "type": "Feature",
  "properties": {
    "iso:country":"IT",
    "sg:address":"12100 Madonna Delle Grazie",
    "sg:city":"Madonna delle Grazie",
    "sg:classifiers":[
        {
            "category":"Health Services",
            "subcategory":"Health Practitioner",
            "type":"Services"
        }
    ],
    "sg:phone":"+39 0171 403882",
    "sg:postcode":"12100",
    "sg:province":"Cuneo",
    "sg:tags":[
        "medici"
    ],
    "wof:name":"Di Martino Antonella",
    "wof:placetype":"venue"
},
  "geometry": {"coordinates":[7.571481,44.396679],"type":"Point"}
}