{
  "type": "Feature",
  "properties": {
    "addr:full":"6, Via Sicilia 96100 Siracusa Siracusa Siracusa 96100",
    "addr:postcode":"96100;96100",
    "addr:street":"Via Sicilia",
    "iso:country":"IT",
    "sg:address":"6, Via Sicilia 96100 Siracusa",
    "sg:city":"Siracusa",
    "sg:classifiers":[
        {
            "category":"Manufacturing",
            "subcategory":"Rubber & Plastics",
            "type":"Manufacturing & Wholesale Goods"
        }
    ],
    "sg:phone":"+39 0931 711311",
    "sg:postcode":"96100",
    "sg:province":"Siracusa",
    "wof:name":"Cielle Imballaggi S.r.l.",
    "wof:placetype":"venue"
},
  "geometry": {"coordinates":[15.2134199142,37.0112533569],"type":"Point"}
}