{
  "type": "Feature",
  "properties": {
    "addr:full":"4/a, Via Moro Aldo 41051 Castelnuovo Rangone Castelnuovo Rangone Modena 41051",
    "addr:housenumber":"4 / a",
    "addr:postcode":"41051;41051",
    "addr:street":"Via Moro Aldo",
    "iso:country":"IT",
    "sg:address":"4/a, Via Moro Aldo 41051 Castelnuovo Rangone",
    "sg:city":"Castelnuovo Rangone",
    "sg:classifiers":[
        {
            "category":"Food & Beverages",
            "subcategory":"Groceries & Convenience Stores",
            "type":"Retail Goods"
        }
    ],
    "sg:phone":"+39 39059536492",
    "sg:postcode":"41051",
    "sg:province":"Modena",
    "sg:tags":[
        "product",
        "related"
    ],
    "wof:name":"D'autore S.r.l.",
    "wof:placetype":"venue"
},
  "geometry": {"coordinates":[10.9237365723,44.5455322266],"type":"Point"}
}