{
  "type": "Feature",
  "properties": {
    "iso:country":"IT",
    "sg:address":"21047 Saronno",
    "sg:city":"Saronno",
    "sg:orig_category":"Servizi E Lavori Per Edilizia E Lavori Pubblici. Banche E Servizi Finanziari",
    "sg:phone":"+39 02 9670 3288",
    "sg:postcode":"21047",
    "sg:province":"Varese",
    "wof:name":"Co.ge.f. (s.r.l.)",
    "wof:placetype":"venue"
},
  "geometry": {"coordinates":[9.030081,45.62738],"type":"Point"}
}