{
  "type": "Feature",
  "properties": {
    "iso:country":"IT",
    "sg:address":"08015 Macomer",
    "sg:city":"Macomer",
    "sg:orig_category":"Agenzie Ed Enti Turistici. Consulenze Tecniche, Amministrative E Perizie",
    "sg:phone":"+39 0785 70475",
    "sg:postcode":"08015",
    "sg:province":"Nuoro",
    "wof:name":"Coop Esedra A Rl",
    "wof:placetype":"venue"
},
  "geometry": {"coordinates":[8.781084,40.267738],"type":"Point"}
}