{
  "type": "Feature",
  "properties": {
    "addr:full":"Piazza Aldo Moro, 61; Bari; 70125 Bari Bari 70125",
    "addr:housenumber":"61",
    "addr:postcode":"70125;70125",
    "addr:street":"Piazza Aldo Moro",
    "iso:country":"IT",
    "sg:address":"Piazza Aldo Moro, 61; Bari; 70125",
    "sg:city":"Bari",
    "sg:classifiers":[
        {
            "category":"Banks & Credit Unions",
            "subcategory":"Bank",
            "type":"Services"
        }
    ],
    "sg:phone":"+39 080 235034",
    "sg:postcode":"70125",
    "sg:province":"Bari",
    "wof:name":"Banco Di Santo Spirito",
    "wof:placetype":"venue"
},
  "geometry": {"coordinates":[16.869207,41.119022],"type":"Point"}
}