{
  "type": "Feature",
  "properties": {
    "iso:country":"IT",
    "sg:address":"72/5, Strada Cascine Barbavara 27029 Vigevano",
    "sg:city":"Vigevano",
    "sg:classifiers":[
        {
            "category":"Professional",
            "subcategory":"Engineering",
            "type":"Services"
        }
    ],
    "sg:phone":"+39 0381 310436",
    "sg:postcode":"27029",
    "sg:province":"Pavia",
    "sg:tags":[
        "machine",
        "-",
        "mechanical"
    ],
    "wof:name":"Benazzato Srl",
    "wof:placetype":"venue"
},
  "geometry": {"coordinates":[8.824301,45.330986],"type":"Point"}
}