{
  "type": "Feature",
  "properties": {
    "addr:full":"95100 Catania CT",
    "addr:postcode":"95100",
    "iso:country":"IT",
    "sg:address":"95100 Catania",
    "sg:orig_category":"Lavorazioni Meccaniche E Servizi",
    "sg:phone":"+39 095 340411",
    "sg:province":"CT",
    "wof:name":"Davide Lagona",
    "wof:placetype":"venue"
},
  "geometry": {"coordinates":[15.079189,37.498787],"type":"Point"}
}