{
  "type": "Feature",
  "properties": {
    "iso:country":"IT",
    "sg:address":"35122 Padova",
    "sg:city":"Padova",
    "sg:orig_category":"Ospedali E Servizi Sanitari",
    "sg:phone":"+39 049 875 1160",
    "sg:postcode":"35122",
    "sg:province":"Padova",
    "wof:name":"Centro Veneto Di Psicoanalisi S.p.i.",
    "wof:placetype":"venue"
},
  "geometry": {"coordinates":[11.870431,45.400311],"type":"Point"}
}