{
  "type": "Feature",
  "properties": {
    "addr:full":"20060 Pessano Con Bornago Ornago Milano 20060",
    "addr:postcode":"20060;20060",
    "iso:country":"IT",
    "sg:address":"20060 Pessano Con Bornago",
    "sg:city":"Ornago",
    "sg:orig_category":"Macchine, Impianti E Forniture Per Industria Grafica, Cartaria E Cartotecnica",
    "sg:phone":"+39 02 9574 3651",
    "sg:postcode":"20060",
    "sg:province":"Milano",
    "wof:name":"Megraf Snc Di Liccione M.& Pagetti E.",
    "wof:placetype":"venue"
},
  "geometry": {"coordinates":[9.18797,45.568253],"type":"Point"}
}