{
  "type": "Feature",
  "properties": {
    "iso:country":"IT",
    "sg:address":"00169 Roma",
    "sg:city":"Roma",
    "sg:orig_category":"Servizi E Lavori Per Edilizia E Lavori Pubblici. Acqua, Luce, Gas E Societa' Di Esercizio Pubblico",
    "sg:phone":"+39 06 238 2280",
    "sg:postcode":"00169",
    "sg:province":"Roma",
    "wof:name":"Acea Ato2 Spa",
    "wof:placetype":"venue"
},
  "geometry": {"coordinates":[12.591913,41.85865],"type":"Point"}
}