{
  "type": "Feature",
  "properties": {
    "addr:full":"37, Via Camasio Sandro 15048 Valenza Valenza Alessandria 15048",
    "addr:postcode":"15048;15048",
    "addr:street":"Via Camasio Sandro",
    "iso:country":"IT",
    "sg:address":"37, Via Camasio Sandro 15048 Valenza",
    "sg:city":"Valenza",
    "sg:classifiers":[
        {
            "category":"Shopping",
            "subcategory":"Jewelry",
            "type":"Retail Goods"
        }
    ],
    "sg:phone":"+39 0131 953185",
    "sg:postcode":"15048",
    "sg:province":"Alessandria",
    "sg:tags":[
        "jewellery"
    ],
    "wof:name":"Bartolini Paolo & C.s.n.c.",
    "wof:placetype":"venue"
},
  "geometry": {"coordinates":[8.643073,45.006111],"type":"Point"}
}