{
  "type": "Feature",
  "properties": {
    "addr:full":"Via G. Rossa 1 40056 Crespellano Crespellano Bologna 40056",
    "addr:housenumber":"1",
    "addr:postcode":"40056;40056",
    "addr:street":"Via G. Rossa",
    "iso:country":"IT",
    "sg:address":"Via G. Rossa 1 40056 Crespellano",
    "sg:city":"Crespellano",
    "sg:orig_category":"Electric Winches",
    "sg:phone":"+39 051 672 0202",
    "sg:postcode":"40056",
    "sg:province":"Bologna",
    "sg:website":"www.sassi.it",
    "wof:name":"Ital Sassi Spa",
    "wof:placetype":"venue"
},
  "geometry": {"coordinates":[11.346481,44.494221],"type":"Point"}
}