{
  "type": "Feature",
  "properties": {
    "addr:full":"20123 Milano Milano Milano 20123",
    "addr:postcode":"20123;20123",
    "iso:country":"IT",
    "sg:address":"20123 Milano",
    "sg:city":"Milano",
    "sg:orig_category":"Prodotti Finiti Stampati. Articoli Da Regalo. Arte Ed Artigianato Artistico. Shopping",
    "sg:phone":"+39 02 8901 0512",
    "sg:postcode":"20123",
    "sg:province":"Milano",
    "wof:name":"Giorgio Upiglio Sas",
    "wof:placetype":"venue"
},
  "geometry": {"coordinates":[9.1849136353,45.4590682983],"type":"Point"}
}