{
  "type": "Feature",
  "properties": {
    "iso:country":"IT",
    "sg:address":"56017 San Giuliano Terme",
    "sg:city":"San Giuliano Terme",
    "sg:orig_category":"Macchine, Impianti Ed Attrezzature Per Agricoltura E Zootecnia",
    "sg:phone":"+39 050 878196",
    "sg:postcode":"56017",
    "sg:province":"Pisa",
    "sg:website":"http://www.elemec.it",
    "wof:name":"Ele Mec Snc",
    "wof:placetype":"venue"
},
  "geometry": {"coordinates":[10.420994,43.725712],"type":"Point"}
}