{
  "type": "Feature",
  "properties": {
    "addr:full":"20096 Pioltello Pioltello Milano 20096",
    "addr:postcode":"20096;20096",
    "iso:country":"IT",
    "sg:address":"20096 Pioltello",
    "sg:city":"Pioltello",
    "sg:orig_category":"Elettronica Professionale E Di Consumo. Musica",
    "sg:phone":"+39 02 926 6749",
    "sg:postcode":"20096",
    "sg:province":"Milano",
    "sg:website":"http://www.alphaelectronic.net",
    "wof:name":"Alpha Electronic Srl",
    "wof:placetype":"venue"
},
  "geometry": {"coordinates":[9.326118,45.48962],"type":"Point"}
}