{
  "type": "Feature",
  "properties": {
    "iso:country":"IT",
    "sg:address":"10080 Bosconero",
    "sg:city":"Bosconero",
    "sg:orig_category":"Trattamenti Termici E Superficiali Metalli, Galvanotecnica",
    "sg:phone":"+39 011 988 6801",
    "sg:postcode":"10080",
    "sg:province":"Torino",
    "wof:name":"Fiore Francesco",
    "wof:placetype":"venue"
},
  "geometry": {"coordinates":[7.764074,45.267982],"type":"Point"}
}