{
  "type": "Feature",
  "properties": {
    "iso:country":"IT",
    "sg:address":"00192 Roma",
    "sg:city":"Roma",
    "sg:orig_category":"Dolciumi E Gelati",
    "sg:phone":"+39 06 323 1005",
    "sg:postcode":"00192",
    "sg:province":"Roma",
    "wof:name":"Napul'\u00c8 Srl",
    "wof:placetype":"venue"
},
  "geometry": {"coordinates":[12.461669,41.910053],"type":"Point"}
}