{
  "type": "Feature",
  "properties": {
    "iso:country":"IT",
    "sg:address":"29010 Alseno",
    "sg:city":"Alseno",
    "sg:orig_category":"Attrezzature E Forniture Per Officine Riparazione E Servizi Ausiliari",
    "sg:phone":"+39 0523 945269",
    "sg:postcode":"29010",
    "sg:province":"Piacenza",
    "wof:name":"Autofficina R.c.m. Snc",
    "wof:placetype":"venue"
},
  "geometry": {"coordinates":[9.604362,45.056126],"type":"Point"}
}