{
  "type": "Feature",
  "properties": {
    "addr:full":"43040 Prelerna Prelerna Parma 43040",
    "addr:postcode":"43040;43040",
    "addr:street":"Prelerna",
    "iso:country":"IT",
    "sg:address":"43040 Prelerna",
    "sg:city":"Prelerna",
    "sg:orig_category":"Macchine, Impianti Ed Attrezzature Per Abbigliamento E Pelletterie. Apparecchiature Ed Attrezzature Meccaniche. Elettrotecnica Industriale, Prodotti E Apparecchiature",
    "sg:phone":"+39 0525 54380",
    "sg:postcode":"43040",
    "sg:province":"Parma",
    "wof:name":"Manfredi Alma",
    "wof:placetype":"venue"
},
  "geometry": {"coordinates":[9.941407,44.625481],"type":"Point"}
}