{
  "type": "Feature",
  "properties": {
    "iso:country":"IT",
    "sg:address":"59013 Montemurlo",
    "sg:city":"Montemurlo",
    "sg:orig_category":"Servizi E Lavori Per Abbigliamento E Pelletterie",
    "sg:phone":"+39 0574 680001",
    "sg:postcode":"59013",
    "sg:province":"Prato",
    "wof:name":"Mazzei Alessandro",
    "wof:placetype":"venue"
},
  "geometry": {"coordinates":[11.033748,43.905884],"type":"Point"}
}