{
  "type": "Feature",
  "properties": {
    "iso:country":"IT",
    "sg:address":"08035 Nurri",
    "sg:city":"Nurri",
    "sg:orig_category":"Carni, Salumi E Pesci. Zootecnia E Pesca, Allevamento Piccoli Animali",
    "sg:phone":"+39 0782 842001",
    "sg:postcode":"08035",
    "sg:province":"Cagliari",
    "wof:name":"Frigomacello Nurri Srl",
    "wof:placetype":"venue"
},
  "geometry": {"coordinates":[9.212059,39.717804],"type":"Point"}
}