{
  "type": "Feature",
  "properties": {
    "iso:country":"IT",
    "sg:address":"41100 Modena",
    "sg:city":"Modena",
    "sg:orig_category":"Termotecnica E Riscaldamento, Apparecchiature E Servizi",
    "sg:phone":"+39 059 359890",
    "sg:postcode":"41100",
    "sg:province":"Modena",
    "wof:name":"Guaitoli & Martinelli S.r.l.",
    "wof:placetype":"venue"
},
  "geometry": {"coordinates":[10.888161,44.627613],"type":"Point"}
}