{
  "type": "Feature",
  "properties": {
    "addr:full":"2, Via Gandini Luigi 27058 Voghera Voghera Pavia 27058",
    "addr:postcode":"27058;27058",
    "addr:street":"Via Gandini Luigi",
    "iso:country":"IT",
    "sg:address":"2, Via Gandini Luigi 27058 Voghera",
    "sg:city":"Voghera",
    "sg:classifiers":[
        {
            "category":"Manufacturing",
            "subcategory":"Tools & Machinery",
            "type":"Manufacturing & Wholesale Goods"
        }
    ],
    "sg:phone":"+39 0383 344611",
    "sg:postcode":"27058",
    "sg:province":"Pavia",
    "sg:tags":[
        "environment",
        "equipment",
        "-"
    ],
    "wof:name":"Pnr Italia Srl",
    "wof:placetype":"venue"
},
  "geometry": {"coordinates":[9.156563,45.185886],"type":"Point"}
}