{
  "type": "Feature",
  "properties": {
    "iso:country":"IT",
    "sg:address":"30, Piazza Unita' D'italia 21047 Saronno",
    "sg:city":"Saronno",
    "sg:classifiers":[
        {
            "category":"Farming",
            "subcategory":"Livestock Farm",
            "type":"Manufacturing & Wholesale Goods"
        }
    ],
    "sg:phone":"+39 02 9670 1803",
    "sg:postcode":"21047",
    "sg:province":"Varese",
    "sg:tags":[
        "agriculture"
    ],
    "wof:name":"Lattuada Fratelli (s.n.c.)",
    "wof:placetype":"venue"
},
  "geometry": {"coordinates":[9.037022,45.629593],"type":"Point"}
}