{
  "type": "Feature",
  "properties": {
    "iso:country":"IT",
    "sg:address":"21053 Castellanza",
    "sg:city":"Castellanza",
    "sg:orig_category":"Forniture Per Agricoltura E Zootecnia. Animali Domestici",
    "sg:phone":"+39 0331 502700",
    "sg:postcode":"21053",
    "sg:province":"Varese",
    "wof:name":"Rebo Srl",
    "wof:placetype":"venue"
},
  "geometry": {"coordinates":[8.8817939758,45.6107635498],"type":"Point"}
}