{
  "type": "Feature",
  "properties": {
    "iso:country":"IT",
    "sg:address":"Via Trentino Alto Adige 6 59100 Prato",
    "sg:city":"Prato",
    "sg:classifiers":[
        {
            "category":"Shopping",
            "subcategory":"Clothing, Apparel, & Fashions",
            "type":"Retail Goods"
        }
    ],
    "sg:phone":"+39 0574 622077",
    "sg:postcode":"59100",
    "sg:province":"Prato",
    "sg:tags":[
        "image",
        "clothing",
        "basic"
    ],
    "wof:name":"L.j.",
    "wof:placetype":"venue"
},
  "geometry": {"coordinates":[11.051189,43.860767],"type":"Point"}
}