{
  "type": "Feature",
  "properties": {
    "addr:full":"90138 Palermo Palermo Palermo 90138",
    "addr:postcode":"90138;90138",
    "iso:country":"IT",
    "sg:address":"90138 Palermo",
    "sg:city":"Palermo",
    "sg:classifiers":[
        {
            "category":"Health Services",
            "subcategory":"Health Practitioner",
            "type":"Services"
        }
    ],
    "sg:phone":"+39 091 611 0613",
    "sg:postcode":"90138",
    "sg:province":"Palermo",
    "sg:tags":[
        "medici"
    ],
    "wof:name":"A.n.s.a.i.",
    "wof:placetype":"venue"
},
  "geometry": {"coordinates":[13.350628,38.120495],"type":"Point"}
}