{
  "type": "Feature",
  "properties": {
    "iso:country":"IT",
    "sg:address":"Via N. Barbato 2 70031 Andria",
    "sg:city":"Andria",
    "sg:classifiers":[
        {
            "category":"Government",
            "subcategory":"Post Office",
            "type":"Public Place"
        }
    ],
    "sg:phone":"+39 0883 555269",
    "sg:postcode":"70031",
    "sg:province":"Bari",
    "sg:tags":[
        "item",
        "household",
        "design"
    ],
    "sg:website":"www.gemitex.it",
    "wof:name":"Gemitex S.r.l.",
    "wof:placetype":"venue"
},
  "geometry": {"coordinates":[16.869291,41.126053],"type":"Point"}
}