{
  "type": "Feature",
  "properties": {
    "iso:country":"IT",
    "sg:address":"47037 Rimini",
    "sg:orig_category":"Pubblicita', Marketing E Comunicazione",
    "sg:phone":"+39 0541 778055",
    "sg:province":"RN",
    "sg:website":"http://www.promosrimini.com",
    "wof:name":"Promos Snc",
    "wof:placetype":"venue"
},
  "geometry": {"coordinates":[-85.3342971802,39.1651725769],"type":"Point"}
}