{
  "type": "Feature",
  "properties": {
    "addr:full":"34, Via Cambiano 10046 Poirino Poirino Torino 10046",
    "addr:postcode":"10046;10046",
    "addr:street":"Via Cambiano",
    "iso:country":"IT",
    "sg:address":"34, Via Cambiano 10046 Poirino",
    "sg:city":"Poirino",
    "sg:classifiers":[
        {
            "category":"Manufacturing",
            "subcategory":"Rubber & Plastics",
            "type":"Manufacturing & Wholesale Goods"
        }
    ],
    "sg:phone":"+39 011 945 3880",
    "sg:postcode":"10046",
    "sg:province":"Torino",
    "wof:name":"G.s.g. Nord (s.r.l.)",
    "wof:placetype":"venue"
},
  "geometry": {"coordinates":[7.8061709404,44.9589881897],"type":"Point"}
}