{
  "type": "Feature",
  "properties": {
    "addr:full":"35020 Saonara Saonara Padova 35020",
    "addr:postcode":"35020;35020",
    "iso:country":"IT",
    "sg:address":"35020 Saonara",
    "sg:city":"Saonara",
    "sg:orig_category":"Arredamenti E Mobili Professionali. Arredi Ed Attrezzature Per Uffici",
    "sg:phone":"+39 049 879 1870",
    "sg:postcode":"35020",
    "sg:province":"Padova",
    "sg:website":"http://www.ambienteufficio.it",
    "wof:name":"Centro Ambiente Ufficio Srl",
    "wof:placetype":"venue"
},
  "geometry": {"coordinates":[11.966248,45.380249],"type":"Point"}
}