{
  "type": "Feature",
  "properties": {
    "iso:country":"IT",
    "sg:address":"09017 Sant'antioco",
    "sg:orig_category":"Servizi Ausiliari Per Il Trasporto. Servizi Vari Di Interesse Pubblico",
    "sg:phone":"+39 0781 83128",
    "sg:postcode":"09017",
    "sg:province":"Carbonia-Iglesias",
    "wof:name":"Incani Maurizio",
    "wof:placetype":"venue"
},
  "geometry": {"coordinates":[8.418423,39.037392],"type":"Point"}
}