{
  "type": "Feature",
  "properties": {
    "addr:full":"27100 Pavia Pavia Pavia 27100",
    "addr:postcode":"27100;27100",
    "iso:country":"IT",
    "sg:address":"27100 Pavia",
    "sg:city":"Pavia",
    "sg:classifiers":[
        {
            "category":"Manufacturing",
            "subcategory":"Tools & Machinery",
            "type":"Manufacturing & Wholesale Goods"
        }
    ],
    "sg:phone":"+39 0382 571442",
    "sg:postcode":"27100",
    "sg:province":"Pavia",
    "sg:tags":[
        "machine",
        "system"
    ],
    "sg:website":"http://www.sommer-automatic.it",
    "wof:name":"Sommer Automatic Italia Srl",
    "wof:placetype":"venue"
},
  "geometry": {"coordinates":[9.180197,45.181149],"type":"Point"}
}