{
  "type": "Feature",
  "properties": {
    "addr:full":"00166 Roma Roma Roma 00166",
    "addr:postcode":"00166;00166",
    "iso:country":"IT",
    "sg:address":"00166 Roma",
    "sg:city":"Roma",
    "sg:classifiers":[
        {
            "category":"Taxi",
            "type":"Transportation"
        }
    ],
    "sg:phone":"+39 06 669 2796",
    "sg:postcode":"00166",
    "sg:province":"Roma",
    "wof:name":"Coop.va Pronto Taxi Srl",
    "wof:placetype":"venue"
},
  "geometry": {"coordinates":[12.378198,41.871971],"type":"Point"}
}