{
  "type": "Feature",
  "properties": {
    "addr:full":"2, Piazza Bucciarelli Gastone 50022 Greve In Chianti Greve in Chianti Firenze 50022",
    "addr:postcode":"50022;50022",
    "addr:street":"Piazza Bucciarelli Gastone",
    "iso:country":"IT",
    "sg:address":"2, Piazza Bucciarelli Gastone 50022 Greve In Chianti",
    "sg:city":"Greve in Chianti",
    "sg:classifiers":[
        {
            "category":"Manufacturing",
            "subcategory":"Wood Products",
            "type":"Manufacturing & Wholesale Goods"
        }
    ],
    "sg:phone":"+39 39055852244",
    "sg:postcode":"50022",
    "sg:province":"Firenze",
    "sg:tags":[
        "furniture"
    ],
    "wof:name":"Quimar Sugheri (s.n.c.)",
    "wof:placetype":"venue"
},
  "geometry": {"coordinates":[11.256902,43.768734],"type":"Point"}
}