{
  "type": "Feature",
  "properties": {
    "iso:country":"IT",
    "sg:address":"17047 Vado Ligure",
    "sg:city":"Vado Ligure",
    "sg:orig_category":"Servizi Ausiliari Per Il Trasporto. Servizi Vari Di Interesse Pubblico",
    "sg:phone":"+39 019 880234",
    "sg:postcode":"17047",
    "sg:province":"Savona",
    "wof:name":"Onoranze Funebri Serra",
    "wof:placetype":"venue"
},
  "geometry": {"coordinates":[8.435718,44.268833],"type":"Point"}
}