{
  "type": "Feature",
  "properties": {
    "iso:country":"IT",
    "sg:address":"Viale Kennedy 77/78; Vibo Valentia; 88018",
    "sg:classifiers":[
        {
            "category":"Banks & Credit Unions",
            "subcategory":"Bank",
            "type":"Services"
        }
    ],
    "sg:phone":"+39 0963 41711",
    "wof:name":"Banca Nazionale Del Lavoro Spa",
    "wof:placetype":"venue"
},
  "geometry": {"coordinates":[16.097742,38.675186],"type":"Point"}
}