{
  "type": "Feature",
  "properties": {
    "iso:country":"IT",
    "sg:address":"Po Box 0021, Via Prov Le Per Matino 5, 73052 Parabita, Le",
    "sg:city":"Parabita",
    "sg:classifiers":[
        {
            "category":"Banks & Credit Unions",
            "subcategory":"Bank",
            "type":"Services"
        }
    ],
    "sg:phone":"+39 0833 551005",
    "sg:postcode":"73052",
    "sg:province":"Lecce",
    "sg:website":"http://www.bpp.it",
    "wof:name":"Banca Popolare Pugliese",
    "wof:placetype":"venue"
},
  "geometry": {"coordinates":[18.174015,40.353291],"type":"Point"}
}