{
  "type": "Feature",
  "properties": {
    "iso:country":"IT",
    "sg:address":"20090 Trezzano Sul Naviglio",
    "sg:city":"Trezzano sul Naviglio",
    "sg:orig_category":"Antincendio - Impianti, Attrezzature E Materiali",
    "sg:phone":"+39 02 4840 2962",
    "sg:postcode":"20090",
    "sg:province":"Milano",
    "wof:name":"Geom. Bosio Sas",
    "wof:placetype":"venue"
},
  "geometry": {"coordinates":[9.048032,45.427643],"type":"Point"}
}