{
  "type": "Feature",
  "properties": {
    "addr:full":"3/5, Via S. Breda 35010 Limena Limena Padova 35010",
    "addr:housenumber":"3 / 5",
    "addr:postcode":"35010;35010",
    "addr:street":"Via S.",
    "iso:country":"IT",
    "sg:address":"3/5, Via S. Breda 35010 Limena",
    "sg:city":"Limena",
    "sg:classifiers":[
        {
            "category":"Manufacturing",
            "subcategory":"Rubber & Plastics",
            "type":"Manufacturing & Wholesale Goods"
        }
    ],
    "sg:phone":"+39 049 884 0988",
    "sg:postcode":"35010",
    "sg:province":"Padova",
    "sg:tags":[
        "packaging",
        "material",
        "-"
    ],
    "wof:name":"Svar (s.r.l.)",
    "wof:placetype":"venue"
},
  "geometry": {"coordinates":[11.8485765457,45.4641647339],"type":"Point"}
}