{
  "type": "Feature",
  "properties": {
    "iso:country":"IT",
    "sg:address":"70023 Gioia Del Colle",
    "sg:city":"Gioia del Colle",
    "sg:orig_category":"Bruciatori Nafta, Gasolio E Kerosene - Commercio",
    "sg:phone":"+39 080 348 4535",
    "sg:postcode":"70023",
    "sg:province":"Bari",
    "wof:name":"Dna Di De Rosa Nicola E C. Sas",
    "wof:placetype":"venue"
},
  "geometry": {"coordinates":[16.888643,40.765903],"type":"Point"}
}