{
  "type": "Feature",
  "properties": {
    "iso:country":"IT",
    "sg:address":"Via Liguria 29/33 10071 Borgaro Torinese",
    "sg:city":"Borgaro Torinese",
    "sg:classifiers":[
        {
            "category":"Bars & Pubs",
            "subcategory":"Lounge",
            "type":"Food & Drink"
        }
    ],
    "sg:phone":"+39 011 470 1173",
    "sg:postcode":"10071",
    "sg:province":"Torino",
    "sg:tags":[
        "shelf"
    ],
    "sg:website":"www.tonon.com",
    "wof:name":"Tonon Di Mariano Tonon & C. S.a.s.",
    "wof:placetype":"venue"
},
  "geometry": {"coordinates":[7.658742,45.138741],"type":"Point"}
}