{
  "type": "Feature",
  "properties": {
    "iso:country":"IT",
    "sg:address":"22066 Mariano Comense",
    "sg:city":"Mariano Comense",
    "sg:orig_category":"Cine-foto-ottica. Shopping",
    "sg:phone":"+39 031 355 1115",
    "sg:postcode":"22066",
    "sg:province":"Como",
    "wof:name":"Cleopatra S.a.s. Di Pellicioli Cornelio & C.",
    "wof:placetype":"venue"
},
  "geometry": {"coordinates":[9.167952,45.709816],"type":"Point"}
}