{
  "type": "Feature",
  "properties": {
    "iso:country":"IT",
    "sg:address":"95047 Patern\u00f2",
    "sg:orig_category":"Arredamenti - Vendita Al Dettaglio",
    "sg:phone":"+39 095 858950",
    "sg:postcode":"95047",
    "sg:province":"Catania",
    "sg:website":"http://www.storiaestile.it",
    "wof:name":"Storia & Stile Srl",
    "wof:placetype":"venue"
},
  "geometry": {"coordinates":[14.904478,37.572544],"type":"Point"}
}