{
  "type": "Feature",
  "properties": {
    "iso:country":"IT",
    "sg:address":"20036 Meda",
    "sg:city":"Meda",
    "sg:orig_category":"Edilizia - Materiali",
    "sg:phone":"+39 036 272142",
    "sg:postcode":"20036",
    "sg:province":"Milano",
    "sg:website":"http://www.cazzanigaelia.it",
    "wof:name":"Cazzaniga Elia Snc Di Pietro Cazzaniga E C.",
    "wof:placetype":"venue"
},
  "geometry": {"coordinates":[9.179062,45.444016],"type":"Point"}
}