{
  "type": "Feature",
  "properties": {
    "addr:full":"80143 Napoli Napoli Napoli 80143",
    "addr:housenumber":"80143",
    "addr:postcode":"80143",
    "iso:country":"IT",
    "sg:address":"80143 Napoli",
    "sg:city":"Napoli",
    "sg:orig_category":"Accessori Moda D'abbigliamento",
    "sg:phone":"+39 081 759 0387",
    "sg:postcode":"80143",
    "sg:province":"Napoli",
    "wof:name":"Gi.an.s.r.l.",
    "wof:placetype":"venue"
},
  "geometry": {"coordinates":[14.27891,40.86919],"type":"Point"}
}