{
  "type": "Feature",
  "properties": {
    "addr:full":"90049 Terrasini Terrasini Palermo 90049",
    "addr:postcode":"90049;90049",
    "iso:country":"IT",
    "sg:address":"90049 Terrasini",
    "sg:city":"Terrasini",
    "sg:orig_category":"Addobbi E Addobbatori",
    "sg:phone":"+39 091 868 1304",
    "sg:postcode":"90049",
    "sg:province":"Palermo",
    "wof:name":"Pensieri Fioriti Di Cipriano Castrenze",
    "wof:placetype":"venue"
},
  "geometry": {"coordinates":[13.087553,38.101803],"type":"Point"}
}