{
  "type": "Feature",
  "properties": {
    "iso:country":"IT",
    "sg:address":"Pfarrplatz 26; Chiusa; 39043",
    "sg:city":"Chiusa",
    "sg:classifiers":[
        {
            "category":"Banks & Credit Unions",
            "subcategory":"Bank",
            "type":"Services"
        }
    ],
    "sg:phone":"+39 0472 47099",
    "sg:postcode":"39043",
    "sg:province":"Bolzano/Bozen",
    "wof:name":"S\u00fcdtiroler Landessparkasse",
    "wof:placetype":"venue"
},
  "geometry": {"coordinates":[11.566186,46.639992],"type":"Point"}
}