{
  "type": "Feature",
  "properties": {
    "iso:country":"IT",
    "sg:address":"95121 Catania",
    "sg:city":"Catania",
    "sg:orig_category":"Macchine, Impianti Ed Attrezzature Per Agricoltura E Zootecnia",
    "sg:phone":"+39 095 570166",
    "sg:postcode":"95121",
    "sg:province":"Catania",
    "wof:name":"Lombardo Carlo",
    "wof:placetype":"venue"
},
  "geometry": {"coordinates":[15.070421,37.484932],"type":"Point"}
}