{
  "type": "Feature",
  "properties": {
    "iso:country":"IT",
    "sg:address":"43024 Neviano Degli Arduini",
    "sg:city":"Neviano degli Arduini",
    "sg:orig_category":"Carni, Salumi E Pesci",
    "sg:phone":"+39 0521 854126",
    "sg:postcode":"43024",
    "sg:province":"Parma",
    "wof:name":"Delsante Dalmazio & C. Srl",
    "wof:placetype":"venue"
},
  "geometry": {"coordinates":[10.333919,44.550167],"type":"Point"}
}