{
  "type": "Feature",
  "properties": {
    "addr:full":"15060 Basaluzzo Basaluzzo Alessandria 15060",
    "addr:housenumber":"15060",
    "addr:postcode":"15060",
    "addr:street":"Basaluzzo Basaluzzo",
    "iso:country":"IT",
    "sg:address":"15060 Basaluzzo",
    "sg:city":"Basaluzzo",
    "sg:orig_category":"Prodotti Vari In Metallo. Articoli Per Imballaggio E Confezionamento",
    "sg:phone":"+39 0143 489170",
    "sg:postcode":"15060",
    "sg:province":"Alessandria",
    "wof:name":"Carezzano Achille",
    "wof:placetype":"venue"
},
  "geometry": {"coordinates":[8.6975193024,44.7719993591],"type":"Point"}
}