{
  "type": "Feature",
  "properties": {
    "iso:country":"IT",
    "sg:address":"80126 Napoli",
    "sg:city":"Napoli",
    "sg:orig_category":"Serramenti Ed Infissi. Forniture Industriali Per Prevenzione, Controllo E Sicurezza",
    "sg:phone":"+39 081 767 5114",
    "sg:postcode":"80126",
    "sg:province":"Napoli",
    "wof:name":"Monaco Giuseppe",
    "wof:placetype":"venue"
},
  "geometry": {"coordinates":[14.20107,40.845581],"type":"Point"}
}