{
  "type": "Feature",
  "properties": {
    "iso:country":"IT",
    "sg:address":"58100 Grosseto",
    "sg:city":"Grosseto",
    "sg:classifiers":[
        {
            "category":"Utilities",
            "subcategory":"Water",
            "type":"Services"
        }
    ],
    "sg:phone":"+39 0564 20298",
    "sg:postcode":"58100",
    "sg:province":"Grosseto",
    "sg:tags":[
        "organizations",
        "tourist",
        "light",
        "gas",
        "tour",
        "operator",
        "public"
    ],
    "wof:name":"Maremmagica Soc.coop.r.l.",
    "wof:placetype":"venue"
},
  "geometry": {"coordinates":[11.116446,42.749512],"type":"Point"}
}