{
  "type": "Feature",
  "properties": {
    "iso:country":"IT",
    "sg:address":"35013 Cittadella",
    "sg:city":"Cittadella",
    "sg:orig_category":"Ospedali E Servizi Sanitari",
    "sg:phone":"+39 049 597 5242",
    "sg:postcode":"35013",
    "sg:province":"Padova",
    "wof:name":"Scapin Daniela",
    "wof:placetype":"venue"
},
  "geometry": {"coordinates":[11.787229,45.639488],"type":"Point"}
}