{
  "type": "Feature",
  "properties": {
    "addr:full":"114, Via Copernico Nicolo' 41015 Nonantola Nonantola Modena 41015",
    "addr:housenumber":"114",
    "addr:postcode":"41015;41015",
    "addr:street":"Via Copernico Nicolo '",
    "iso:country":"IT",
    "sg:address":"114, Via Copernico Nicolo' 41015 Nonantola",
    "sg:city":"Nonantola",
    "sg:classifiers":[
        {
            "category":"Professional",
            "subcategory":"Engineering",
            "type":"Services"
        }
    ],
    "sg:phone":"+39 39059546776",
    "sg:postcode":"41015",
    "sg:province":"Modena",
    "sg:tags":[
        "machine",
        "-",
        "mechanical"
    ],
    "wof:name":"O.m.r.",
    "wof:placetype":"venue"
},
  "geometry": {"coordinates":[11.017952,44.677143],"type":"Point"}
}