{
  "type": "Feature",
  "properties": {
    "addr:full":"00185 Roma Roma Roma 00185",
    "addr:postcode":"00185;00185",
    "iso:country":"IT",
    "sg:address":"00185 Roma",
    "sg:city":"Roma",
    "sg:orig_category":"Articoli Da Regalo. Regalistica Aziendale",
    "sg:phone":"+39 06 487 3670",
    "sg:postcode":"00185",
    "sg:province":"Roma",
    "wof:name":"Di Veroli Srl",
    "wof:placetype":"venue"
},
  "geometry": {"coordinates":[12.502133,41.893295],"type":"Point"}
}