{
  "type": "Feature",
  "properties": {
    "iso:country":"IT",
    "sg:address":"40013 Castel Maggiore",
    "sg:city":"Castel Maggiore",
    "sg:orig_category":"Petroli, Gas E Combustibili. Materiali Edili",
    "sg:phone":"+39 051 701458",
    "sg:postcode":"40013",
    "sg:province":"Bologna",
    "sg:website":"http://www.concave.it",
    "wof:name":"Consorzio Cave Bologna Soc.coop.r.l.",
    "wof:placetype":"venue"
},
  "geometry": {"coordinates":[11.3175258636,44.5556602478],"type":"Point"}
}