{
  "type": "Feature",
  "properties": {
    "addr:full":"00178 Roma Roma Roma 00178",
    "addr:postcode":"00178;00178",
    "iso:country":"IT",
    "sg:address":"00178 Roma",
    "sg:city":"Roma",
    "sg:orig_category":"Esportatori Ed Importatori",
    "sg:phone":"+39 06 718 7734",
    "sg:postcode":"00178",
    "sg:province":"Roma",
    "sg:website":"http://www.ilveliero.it",
    "wof:name":"Il Veliero Import Export Srl",
    "wof:placetype":"venue"
},
  "geometry": {"coordinates":[12.542811,41.840557],"type":"Point"}
}