{
  "type": "Feature",
  "properties": {
    "addr:full":"73055 Racale Racale Lecce 73055",
    "addr:postcode":"73055;73055",
    "iso:country":"IT",
    "sg:address":"73055 Racale",
    "sg:city":"Racale",
    "sg:classifiers":[
        {
            "category":"Manufacturing",
            "subcategory":"Food",
            "type":"Manufacturing & Wholesale Goods"
        }
    ],
    "sg:phone":"+39 0833 585852",
    "sg:postcode":"73055",
    "sg:province":"Lecce",
    "sg:tags":[
        "product"
    ],
    "wof:name":"Agenzia Italfood Di Nunziato Vitale & C. Sas",
    "wof:placetype":"venue"
},
  "geometry": {"coordinates":[18.0223045349,39.9677085876],"type":"Point"}
}