{
  "type": "Feature",
  "properties": {
    "iso:country":"IT",
    "sg:address":"47900 Rimini",
    "sg:city":"Rimini",
    "sg:orig_category":"Servizi Per Aziende, Manifestazioni E Supporto Agli Scambi Commerciali",
    "sg:phone":"+39 0541 380252",
    "sg:postcode":"47900",
    "sg:province":"Rimini",
    "wof:name":"Allexp\u00d2 Srl",
    "wof:placetype":"venue"
},
  "geometry": {"coordinates":[12.546058,44.011654],"type":"Point"}
}