{
  "type": "Feature",
  "properties": {
    "iso:country":"IT",
    "sg:address":"36016 Thiene",
    "sg:city":"Thiene",
    "sg:orig_category":"Macchine E Forniture Per Arredamento E Industria Del Legno",
    "sg:phone":"+39 0445 369180",
    "sg:postcode":"36016",
    "sg:province":"Vicenza",
    "wof:name":"Pamac Srl",
    "wof:placetype":"venue"
},
  "geometry": {"coordinates":[11.512334,45.527046],"type":"Point"}
}