{
  "type": "Feature",
  "properties": {
    "addr:full":"26, Corso Asti 12051 Alba Alba Cuneo 12051",
    "addr:postcode":"12051;12051",
    "addr:street":"Corso Asti",
    "iso:country":"IT",
    "sg:address":"26, Corso Asti 12051 Alba",
    "sg:city":"Alba",
    "sg:classifiers":[
        {
            "category":"Bars & Pubs",
            "subcategory":"Nightclub",
            "type":"Food & Drink"
        }
    ],
    "sg:phone":"+39 0173 440852",
    "sg:postcode":"12051",
    "sg:province":"Cuneo",
    "sg:tags":[
        "cake",
        "bread"
    ],
    "wof:name":"Barbero Snc Di Barbero Rag. Alberto E Ci.",
    "wof:placetype":"venue"
},
  "geometry": {"coordinates":[8.114513,44.781071],"type":"Point"}
}