{
  "type": "Feature",
  "properties": {
    "iso:country":"IT",
    "sg:address":"Contrada S. Lucia 98071 Capo D'orlando",
    "sg:classifiers":[
        {
            "category":"Manufacturing",
            "subcategory":"Rubber & Plastics",
            "type":"Manufacturing & Wholesale Goods"
        }
    ],
    "sg:phone":"+39 0941 913411",
    "sg:postcode":"98071",
    "sg:province":"Messina",
    "wof:name":"Siplast S.a.s. Di C. Giuffre' & C.",
    "wof:placetype":"venue"
},
  "geometry": {"coordinates":[15.5555229187,38.1923332214],"type":"Point"}
}