{
  "type": "Feature",
  "properties": {
    "addr:full":"26020 Palazzo Pignano Palazzo Pignano Cremona 26020",
    "addr:postcode":"26020;pignano;26020",
    "addr:street":"Cremona",
    "iso:country":"IT",
    "sg:address":"26020 Palazzo Pignano",
    "sg:city":"Palazzo Pignano",
    "sg:orig_category":"Servizi Per Imballaggio E Confezionamento",
    "sg:phone":"+39 0373 920205",
    "sg:postcode":"26020",
    "sg:province":"Cremona",
    "wof:name":"Europe Work Soc. Coop. Arl Soc",
    "wof:placetype":"venue"
},
  "geometry": {"coordinates":[9.568013,45.391113],"type":"Point"}
}