{
  "type": "Feature",
  "properties": {
    "addr:full":"10143 Torino Torino Torino 10143",
    "addr:postcode":"10143;10143",
    "iso:country":"IT",
    "sg:address":"10143 Torino",
    "sg:city":"Torino",
    "sg:orig_category":"Non-classified Establishments",
    "sg:phone":"+39 011 749 3811",
    "sg:postcode":"10143",
    "sg:province":"Torino",
    "wof:name":"Garino Arreda",
    "wof:placetype":"venue"
},
  "geometry": {"coordinates":[7.653485,45.082325],"type":"Point"}
}