{
  "type": "Feature",
  "properties": {
    "iso:country":"IT",
    "sg:address":"00043 Ciampino",
    "sg:city":"Ciampino",
    "sg:classifiers":[
        {
            "category":"Health Services",
            "subcategory":"Health Practitioner",
            "type":"Services"
        }
    ],
    "sg:phone":"+39 06 791 4666",
    "sg:postcode":"00043",
    "sg:province":"Roma",
    "sg:tags":[
        "medici"
    ],
    "wof:name":"Ventresca Enrico",
    "wof:placetype":"venue"
},
  "geometry": {"coordinates":[12.6158800125,41.7905387878],"type":"Point"}
}