{
  "type": "Feature",
  "properties": {
    "addr:full":"6, Via Comunale Matraia 55012 Capannori Capannori Lucca 55012",
    "addr:postcode":"55012;55012",
    "addr:street":"Via Comunale Matraia",
    "iso:country":"IT",
    "sg:address":"6, Via Comunale Matraia 55012 Capannori",
    "sg:city":"Capannori",
    "sg:classifiers":[
        {
            "category":"Food & Beverages",
            "subcategory":"Groceries & Convenience Stores",
            "type":"Retail Goods"
        }
    ],
    "sg:phone":"+39 0583 402310",
    "sg:postcode":"55012",
    "sg:province":"Lucca",
    "sg:tags":[
        "drink"
    ],
    "wof:name":"Fattoria Colle Verde S.r.l",
    "wof:placetype":"venue"
},
  "geometry": {"coordinates":[10.583333,43.833332],"type":"Point"}
}