{
  "type": "Feature",
  "properties": {
    "iso:country":"IT",
    "sg:address":"Via Rossini, 28 - Campea 31050 Miane",
    "sg:city":"Miane",
    "sg:classifiers":[
        {
            "category":"Home & Garden",
            "subcategory":"Kitchen Supply",
            "type":"Retail Goods"
        }
    ],
    "sg:phone":"+39 0438 899111",
    "sg:postcode":"31050",
    "sg:province":"Treviso",
    "sg:tags":[
        "fitted"
    ],
    "sg:website":"www.dibiesse.it",
    "wof:name":"Dibiesse S.p.a.",
    "wof:placetype":"venue"
},
  "geometry": {"coordinates":[12.1092329025,45.9299163818],"type":"Point"}
}