{
  "type": "Feature",
  "properties": {
    "iso:country":"IT",
    "sg:address":"00144 Roma",
    "sg:city":"Roma",
    "sg:orig_category":"Macchine E Forniture Per Ecologia E Smaltimento Rifiuti",
    "sg:phone":"+39 06 592 0938",
    "sg:postcode":"00144",
    "sg:province":"Roma",
    "wof:name":"Ecoteam Sud",
    "wof:placetype":"venue"
},
  "geometry": {"coordinates":[12.463317,41.83873],"type":"Point"}
}