{
  "type": "Feature",
  "properties": {
    "iso:country":"IT",
    "sg:address":"05100 Terni",
    "sg:city":"Terni",
    "sg:orig_category":"Telecomunicazioni E Telefonia, Impianti, Apparecchi E Servizi",
    "sg:phone":"+39 0744 3941",
    "sg:postcode":"05100",
    "sg:province":"Terni",
    "sg:website":"http://www.viasystem.com",
    "wof:name":"Viasystems Ems - Italia Srl",
    "wof:placetype":"venue"
},
  "geometry": {"coordinates":[12.608444,42.569221],"type":"Point"}
}