{
  "type": "Feature",
  "properties": {
    "iso:country":"IT",
    "sg:address":"47900 Rimini",
    "sg:city":"Rimini",
    "sg:orig_category":"Servizi E Lavori Per Ecologia E Smaltimento Rifiuti. Servizi Ausiliari Di Sorveglianza, Manutenzione E Pulizia",
    "sg:phone":"+39 0541 361211",
    "sg:postcode":"47900",
    "sg:province":"Rimini",
    "sg:website":"http://www.amiarimini.com",
    "wof:name":"Amia Spa Servizi E Progetti Per L'ambiente",
    "wof:placetype":"venue"
},
  "geometry": {"coordinates":[12.546496,44.019272],"type":"Point"}
}