{
  "type": "Feature",
  "properties": {
    "iso:country":"IT",
    "sg:address":"50018 Scandicci",
    "sg:city":"Scandicci",
    "sg:orig_category":"Calzature, Pelletterie E Pelli",
    "sg:phone":"+39 055 731 1045",
    "sg:postcode":"50018",
    "sg:province":"Firenze",
    "wof:name":"Cellai - Sartini Sas",
    "wof:placetype":"venue"
},
  "geometry": {"coordinates":[11.15299,43.772625],"type":"Point"}
}