{
  "type": "Feature",
  "properties": {
    "addr:full":"20040 Usmate Velate Usmate Velate Milano 20040",
    "addr:postcode":"20040;20040",
    "iso:country":"IT",
    "sg:address":"20040 Usmate Velate",
    "sg:city":"Usmate Velate",
    "sg:orig_category":"Articoli Per Imballaggio E Confezionamento",
    "sg:phone":"+39 039 670244",
    "sg:postcode":"20040",
    "sg:province":"Milano",
    "wof:name":"Grafica Clich\u00c8 Di Redaelli Pierluigia & C.",
    "wof:placetype":"venue"
},
  "geometry": {"coordinates":[9.365633,45.652393],"type":"Point"}
}