{
  "type": "Feature",
  "properties": {
    "iso:country":"IT",
    "sg:address":"20049 Concorezzo",
    "sg:city":"Concorezzo",
    "sg:orig_category":"Etichette",
    "sg:phone":"+39 039 604 3346",
    "sg:postcode":"20049",
    "sg:province":"Milano",
    "wof:name":"Adolfo Felisati & C. Snc",
    "wof:placetype":"venue"
},
  "geometry": {"coordinates":[9.325477,45.586506],"type":"Point"}
}