{
  "type": "Feature",
  "properties": {
    "iso:country":"IT",
    "sg:address":"48, Strada Carignano 10024 Moncalieri",
    "sg:city":"Moncalieri",
    "sg:classifiers":[
        {
            "category":"Shopping",
            "subcategory":"Computers & Home Electronics",
            "type":"Retail Goods"
        }
    ],
    "sg:phone":"+39 011 640 8281",
    "sg:postcode":"10024",
    "sg:province":"Torino",
    "sg:tags":[
        "electronic",
        "electrical",
        "equipment"
    ],
    "wof:name":"Electrolux Commerciale (s.r.l.)",
    "wof:placetype":"venue"
},
  "geometry": {"coordinates":[7.67139,44.991867],"type":"Point"}
}