{
  "type": "Feature",
  "properties": {
    "addr:full":"20142 Milano Milano Milano 20142",
    "addr:postcode":"20142;20142",
    "iso:country":"IT",
    "sg:address":"20142 Milano",
    "sg:city":"Milano",
    "sg:orig_category":"Ospedali E Servizi Sanitari. Servizi Sociali",
    "sg:phone":"+39 02 846 4979",
    "sg:postcode":"20142",
    "sg:province":"Milano",
    "wof:name":"A.s. Ha. Zona 15 Associazione Sostegno Handicappati",
    "wof:placetype":"venue"
},
  "geometry": {"coordinates":[9.176241,45.42635],"type":"Point"}
}