{
  "type": "Feature",
  "properties": {
    "iso:country":"IT",
    "sg:address":"27058 Voghera",
    "sg:city":"Voghera",
    "sg:orig_category":"Macchine Ed Impianti Per Edilizia E Lavori Pubblici",
    "sg:phone":"+39 0383 367788",
    "sg:postcode":"27058",
    "sg:province":"Pavia",
    "wof:name":"Fantin Gian Luigi",
    "wof:placetype":"venue"
},
  "geometry": {"coordinates":[9.011885,44.999912],"type":"Point"}
}