{
  "type": "Feature",
  "properties": {
    "iso:country":"IT",
    "sg:address":"20099 Sesto San Giovanni",
    "sg:city":"Sesto San Giovanni",
    "sg:orig_category":"Lavorazioni Metalli, Stampaggio E Saldatura",
    "sg:phone":"+39 02 2247 2639",
    "sg:postcode":"20099",
    "sg:province":"Milano",
    "wof:name":"Ghezzi Claudio",
    "wof:placetype":"venue"
},
  "geometry": {"coordinates":[9.23584,45.528885],"type":"Point"}
}