{
  "type": "Feature",
  "properties": {
    "iso:country":"IT",
    "sg:address":"10149 Torino",
    "sg:city":"Torino",
    "sg:orig_category":"Non-classified Establishments",
    "sg:phone":"+39 011 741 2060",
    "sg:postcode":"10149",
    "sg:province":"Torino",
    "wof:name":"Alba Srl",
    "wof:placetype":"venue"
},
  "geometry": {"coordinates":[7.830617,45.487606],"type":"Point"}
}