{
  "type": "Feature",
  "properties": {
    "addr:full":"8, Via Dei Legni 52015 Pratovecchio Pratovecchio Arezzo 52015",
    "addr:postcode":"52015;52015",
    "addr:street":"Via Dei Legni",
    "iso:country":"IT",
    "sg:address":"8, Via Dei Legni 52015 Pratovecchio",
    "sg:city":"Pratovecchio",
    "sg:classifiers":[
        {
            "category":"Shopping",
            "subcategory":"Clothing, Apparel, & Fashions",
            "type":"Retail Goods"
        }
    ],
    "sg:phone":"+39 0575 504125",
    "sg:postcode":"52015",
    "sg:province":"Arezzo",
    "sg:tags":[
        "clothes"
    ],
    "wof:name":"Maglificio Viky Tricot (s.n.c.)",
    "wof:placetype":"venue"
},
  "geometry": {"coordinates":[11.726354,43.784504],"type":"Point"}
}