{
  "type": "Feature",
  "properties": {
    "addr:full":"13, Via Gorizia 22070 Luisago Luisago Como 22070",
    "addr:postcode":"22070;22070",
    "addr:street":"Via Gorizia",
    "iso:country":"IT",
    "sg:address":"13, Via Gorizia 22070 Luisago",
    "sg:city":"Luisago",
    "sg:classifiers":[
        {
            "category":"Shopping",
            "subcategory":"Crafts & Fabrics",
            "type":"Retail Goods"
        }
    ],
    "sg:phone":"+39 39031920657",
    "sg:postcode":"22070",
    "sg:province":"Como",
    "wof:name":"Seride (s.r.l.)",
    "wof:placetype":"venue"
},
  "geometry": {"coordinates":[9.054643631,45.7584915161],"type":"Point"}
}