{
  "type": "Feature",
  "properties": {
    "iso:country":"IT",
    "sg:address":"430, Via Balestrieri Emanuele S. Gemignano Di M. 55100 Lucca",
    "sg:city":"Lucca",
    "sg:classifiers":[
        {
            "category":"Professional",
            "subcategory":"Engineering",
            "type":"Services"
        }
    ],
    "sg:phone":"+39 0583 406060",
    "sg:postcode":"55100",
    "sg:province":"Lucca",
    "sg:tags":[
        "machine",
        "-",
        "mechanical"
    ],
    "wof:name":"Me.ro (s.r.l.)",
    "wof:placetype":"venue"
},
  "geometry": {"coordinates":[10.507994,43.843014],"type":"Point"}
}