{
  "type": "Feature",
  "properties": {
    "iso:country":"IT",
    "sg:address":"63038 Ripatransone",
    "sg:city":"Ripatransone",
    "sg:orig_category":"Serramenti Ed Infissi",
    "sg:phone":"+39 0735 90560",
    "sg:postcode":"63038",
    "sg:province":"Ascoli Piceno",
    "wof:name":"Officine Pignotti Infissi Srl",
    "wof:placetype":"venue"
},
  "geometry": {"coordinates":[13.81224,42.982376],"type":"Point"}
}