{
  "type": "Feature",
  "properties": {
    "iso:country":"IT",
    "sg:address":"Via Bollore 53020 Bagni Di San Filippo",
    "sg:classifiers":[
        {
            "category":"Building & Trades",
            "subcategory":"Construction",
            "type":"Services"
        }
    ],
    "sg:phone":"+39 0577 872991",
    "sg:postcode":"53020",
    "sg:province":"Siena",
    "sg:tags":[
        "fireplace"
    ],
    "sg:website":"www.amiatacaminetti.it",
    "wof:name":"Amiata Marmi Srl",
    "wof:placetype":"venue"
},
  "geometry": {"coordinates":[11.6976585388,42.9274978638],"type":"Point"}
}