{
  "type": "Feature",
  "properties": {
    "iso:country":"IT",
    "sg:address":"23/h, Via Padule 50018 Scandicci",
    "sg:city":"Scandicci",
    "sg:classifiers":[
        {
            "category":"Food & Beverages",
            "subcategory":"Groceries & Convenience Stores",
            "type":"Retail Goods"
        }
    ],
    "sg:phone":"+39 39055735081",
    "sg:postcode":"50018",
    "sg:province":"Firenze",
    "sg:tags":[
        "product",
        "related"
    ],
    "wof:name":"S.i.s.a. Spa",
    "wof:placetype":"venue"
},
  "geometry": {"coordinates":[11.1661043167,43.7634887695],"type":"Point"}
}