{
  "type": "Feature",
  "properties": {
    "iso:country":"IT",
    "sg:address":"90133 Palermo",
    "sg:city":"Palermo",
    "sg:orig_category":"Ospedali E Servizi Sanitari",
    "sg:phone":"+39 091 605 4111",
    "sg:postcode":"90133",
    "sg:province":"Palermo",
    "sg:website":"http://www.triolozancla.com",
    "wof:name":"Casa Di Cure Triolo Zancla Spa",
    "wof:placetype":"venue"
},
  "geometry": {"coordinates":[13.365949,38.115482],"type":"Point"}
}