{
  "type": "Feature",
  "properties": {
    "addr:full":"54033 Carrara Carrara Massa-Carrara 54033",
    "addr:postcode":"54033;54033",
    "iso:country":"IT",
    "sg:address":"54033 Carrara",
    "sg:city":"Carrara",
    "sg:orig_category":"Forniture Per Attivita' Industriali",
    "sg:phone":"+39 0585 852811",
    "sg:postcode":"54033",
    "sg:province":"Massa-Carrara",
    "wof:name":"Indiam Di Andrea Valsega",
    "wof:placetype":"venue"
},
  "geometry": {"coordinates":[10.0724687576,44.0446929932],"type":"Point"}
}