{
  "type": "Feature",
  "properties": {
    "iso:country":"IT",
    "sg:address":"36010 Carr\u00e8",
    "sg:orig_category":"Servizi E Lavori Industria Della Gomma",
    "sg:phone":"+39 0445 315149",
    "sg:postcode":"36010",
    "sg:province":"Vicenza",
    "sg:website":"http://www.dbmengineering.it",
    "wof:name":"Dbm Engineering Snc",
    "wof:placetype":"venue"
},
  "geometry": {"coordinates":[11.530158,45.734112],"type":"Point"}
}