{
  "type": "Feature",
  "properties": {
    "iso:country":"IT",
    "sg:address":"33170 Pordenone",
    "sg:city":"Pordenone",
    "sg:orig_category":"Manufacturers: Prefabbricati. Servizi E Lavori Per Ecologia E Smaltimento Rifiuti",
    "sg:phone":"+39 0434 44872",
    "sg:postcode":"33170",
    "sg:province":"Pordenone",
    "wof:name":"Autoespurgo Moschetta Sas Di Lorenzon R. & C.",
    "wof:placetype":"venue"
},
  "geometry": {"coordinates":[12.684278,45.966492],"type":"Point"}
}