{
  "type": "Feature",
  "properties": {
    "iso:country":"IT",
    "sg:address":"6, Via Torino 20063 Cernusco Sul Naviglio",
    "sg:city":"Cernusco sul Naviglio",
    "sg:classifiers":[
        {
            "category":"Manufacturing",
            "subcategory":"Rubber & Plastics",
            "type":"Manufacturing & Wholesale Goods"
        }
    ],
    "sg:phone":"+39 390 292 9071",
    "sg:postcode":"20063",
    "sg:province":"Milano",
    "wof:name":"Virag Di Virag L. & C. S.a.s.",
    "wof:placetype":"venue"
},
  "geometry": {"coordinates":[9.338531,45.502674],"type":"Point"}
}