{
  "type": "Feature",
  "properties": {
    "addr:full":"Via Alessandria 35 27029 Vigevano Vigevano Pavia 27029",
    "addr:housenumber":"35",
    "addr:postcode":"27029;27029",
    "addr:street":"Via Alessandria",
    "iso:country":"IT",
    "sg:address":"Via Alessandria 35 27029 Vigevano",
    "sg:city":"Vigevano",
    "sg:classifiers":[
        {
            "category":"Manufacturing",
            "subcategory":"Tools & Machinery",
            "type":"Manufacturing & Wholesale Goods"
        }
    ],
    "sg:phone":"+39 0381 20545",
    "sg:postcode":"27029",
    "sg:province":"Pavia",
    "sg:tags":[
        "making",
        "shoe"
    ],
    "sg:website":"www.gusbi.it",
    "wof:name":"Gus-bi Spa",
    "wof:placetype":"venue"
},
  "geometry": {"coordinates":[8.834945,45.330276],"type":"Point"}
}