{
  "type": "Feature",
  "properties": {
    "addr:full":"10028 Trofarello Trofarello Torino 10028",
    "addr:postcode":"10028;10028",
    "iso:country":"IT",
    "sg:address":"10028 Trofarello",
    "sg:city":"Trofarello",
    "sg:orig_category":"Scuole E Servizi Scolastici. Ospedali E Servizi Sanitari",
    "sg:phone":"+39 011 649 0331",
    "sg:postcode":"10028",
    "sg:province":"Torino",
    "wof:name":"Fermata D'autobus",
    "wof:placetype":"venue"
},
  "geometry": {"coordinates":[7.733333,45.033333],"type":"Point"}
}