{
  "type": "Feature",
  "properties": {
    "addr:full":"20146 Milano Milano Milano 20146",
    "addr:postcode":"20146;20146",
    "iso:country":"IT",
    "sg:address":"20146 Milano",
    "sg:city":"Milano",
    "sg:orig_category":"Agenzie Ed Enti Turistici. Consulenze Tecniche, Amministrative E Perizie",
    "sg:phone":"+39 02 365 0407",
    "sg:postcode":"20146",
    "sg:province":"Milano",
    "wof:name":"Park Lane S.r.l.",
    "wof:placetype":"venue"
},
  "geometry": {"coordinates":[9.149731,45.464252],"type":"Point"}
}