{
  "type": "Feature",
  "properties": {
    "addr:full":"10121 Torino Torino Torino 10121",
    "addr:postcode":"10121;10121",
    "iso:country":"IT",
    "sg:address":"10121 Torino",
    "sg:city":"Torino",
    "sg:orig_category":"Abbigliamento - Vendita Al Dettaglio",
    "sg:phone":"+39 011 517 5127",
    "sg:postcode":"10121",
    "sg:province":"Torino",
    "wof:name":"Duomo Srl",
    "wof:placetype":"venue"
},
  "geometry": {"coordinates":[7.592328,45.029629],"type":"Point"}
}