{
  "type": "Feature",
  "properties": {
    "addr:full":"00198 Roma Roma Roma 00198",
    "addr:postcode":"00198;00198",
    "iso:country":"IT",
    "sg:address":"00198 Roma",
    "sg:city":"Roma",
    "sg:orig_category":"Articoli Da Regalo. Tempo Libero - Articoli E Forniture. Regalistica Aziendale",
    "sg:phone":"+39 06 8535 4389",
    "sg:postcode":"00198",
    "sg:province":"Roma",
    "sg:website":"http://www.pesceangelo.it",
    "wof:name":"Pesce Angelo",
    "wof:placetype":"venue"
},
  "geometry": {"coordinates":[12.459188,41.843708],"type":"Point"}
}