{
  "type": "Feature",
  "properties": {
    "iso:country":"IT",
    "sg:address":"60/a, Via Della Concia 19126 La Spezia",
    "sg:classifiers":[
        {
            "category":"Autos & Motor Vehicles",
            "subcategory":"Boat Sales",
            "type":"Retail Goods"
        }
    ],
    "sg:phone":"+39 0187 514263",
    "sg:province":"SP",
    "wof:name":"A.r. Naval (s.r.l.)",
    "wof:placetype":"venue"
},
  "geometry": {"coordinates":[10.032511,44.07505],"type":"Point"}
}