{
  "type": "Feature",
  "properties": {
    "iso:country":"IT",
    "sg:address":"37067 Valeggio Sul Mincio",
    "sg:city":"Valeggio sul Mincio",
    "sg:orig_category":"Servizi Ausiliari Per Il Trasporto",
    "sg:phone":"+39 045 637 1019",
    "sg:postcode":"37067",
    "sg:province":"Verona",
    "wof:name":"Aer Benacus Di Rizzi Giorgio",
    "wof:placetype":"venue"
},
  "geometry": {"coordinates":[10.733616,45.354057],"type":"Point"}
}