{
  "type": "Feature",
  "properties": {
    "iso:country":"IT",
    "sg:address":"10123 Torino",
    "sg:city":"Torino",
    "sg:orig_category":"Articoli Sportivi - Vendita Al Dettaglio",
    "sg:phone":"+39 011 531889",
    "sg:postcode":"10123",
    "sg:province":"Torino",
    "wof:name":"Golf Time Srl",
    "wof:placetype":"venue"
},
  "geometry": {"coordinates":[7.685637,45.065716],"type":"Point"}
}