{
  "type": "Feature",
  "properties": {
    "iso:country":"IT",
    "sg:address":"Viale Delle; Urgnano; 24059",
    "sg:city":"Urgnano",
    "sg:classifiers":[
        {
            "category":"Banks & Credit Unions",
            "subcategory":"Bank",
            "type":"Services"
        }
    ],
    "sg:phone":"+39 035 891050",
    "sg:postcode":"24059",
    "sg:province":"Bergamo",
    "wof:name":"Credito Bergamasco Spa",
    "wof:placetype":"venue"
},
  "geometry": {"coordinates":[9.665892,45.614254],"type":"Point"}
}