{
  "type": "Feature",
  "properties": {
    "iso:country":"IT",
    "sg:address":"20131 Milano",
    "sg:city":"Milano",
    "sg:orig_category":"Cartotecnica E Servizi. Articoli Per Imballaggio E Confezionamento",
    "sg:phone":"+39 02 287 0566",
    "sg:postcode":"20131",
    "sg:province":"Milano",
    "wof:name":"Dadi Cart (s.a.s.)",
    "wof:placetype":"venue"
},
  "geometry": {"coordinates":[9.227892,45.48785],"type":"Point"}
}