{
  "type": "Feature",
  "properties": {
    "iso:country":"IT",
    "sg:address":"12, Via Lotto Lorenzo 24068 Seriate",
    "sg:city":"Seriate",
    "sg:classifiers":[
        {
            "category":"Farming",
            "subcategory":"Livestock Farm",
            "type":"Manufacturing & Wholesale Goods"
        }
    ],
    "sg:phone":"+39 39035296944",
    "sg:postcode":"24068",
    "sg:province":"Bergamo",
    "sg:tags":[
        "agriculture"
    ],
    "wof:name":"Garletti Di Garletti Giovanni & C. (s.n.c.)",
    "wof:placetype":"venue"
},
  "geometry": {"coordinates":[9.71523,45.689217],"type":"Point"}
}