{
  "type": "Feature",
  "properties": {
    "addr:full":"Via Aldo Moro 11/13, 53100 Siena, Si Siena Siena 53100",
    "addr:housenumber":"11 / 13",
    "addr:postcode":"53100;53100",
    "addr:street":"Via Aldo Moro",
    "iso:country":"IT",
    "sg:address":"Via Aldo Moro 11/13, 53100 Siena, Si",
    "sg:city":"Siena",
    "sg:classifiers":[
        {
            "category":"Banks & Credit Unions",
            "subcategory":"Bank",
            "type":"Services"
        }
    ],
    "sg:postcode":"53100",
    "sg:province":"Siena",
    "wof:name":"Paschi Gestioni Immobiliari Spa",
    "wof:placetype":"venue"
},
  "geometry": {"coordinates":[11.3224,43.34528],"type":"Point"}
}