{
  "type": "Feature",
  "properties": {
    "iso:country":"IT",
    "sg:address":"Via Zona Industriale 98042 Pace Del Mela",
    "sg:city":"Pace del Mela",
    "sg:classifiers":[
        {
            "category":"Autos & Motor Vehicles",
            "subcategory":"Automobile Sales",
            "type":"Retail Goods"
        }
    ],
    "sg:phone":"+39 090 938 4596",
    "sg:postcode":"98042",
    "sg:province":"Messina",
    "sg:tags":[
        "motor-cars"
    ],
    "wof:name":"Primosole Veicoli Industriali Srl",
    "wof:placetype":"venue"
},
  "geometry": {"coordinates":[15.5555229187,38.1923332214],"type":"Point"}
}