{
  "type": "Feature",
  "properties": {
    "iso:country":"IT",
    "sg:address":"25050 Passirano",
    "sg:city":"Passirano",
    "sg:classifiers":[
        {
            "category":"Wholesale",
            "subcategory":"Machinery & Supplies",
            "type":"Manufacturing & Wholesale Goods"
        }
    ],
    "sg:phone":"+39 030 653011",
    "sg:postcode":"25050",
    "sg:province":"Brescia",
    "sg:tags":[
        "component",
        "engineering",
        "material",
        "electrical"
    ],
    "wof:name":"Elettro Brescia Srl",
    "wof:placetype":"venue"
},
  "geometry": {"coordinates":[10.220278,45.533752],"type":"Point"}
}