{
  "type": "Feature",
  "properties": {
    "addr:full":"25080 Soiano Del Lago Soiano Brescia 25080",
    "addr:postcode":"25080;25080",
    "iso:country":"IT",
    "sg:address":"25080 Soiano Del Lago",
    "sg:city":"Soiano",
    "sg:orig_category":"Apparecchiature Ed Attrezzature Meccaniche",
    "sg:phone":"+39 036 550 3228",
    "sg:postcode":"25080",
    "sg:province":"Brescia",
    "wof:name":"Esse 2 Oleodinamica Srl",
    "wof:placetype":"venue"
},
  "geometry": {"coordinates":[10.496376,45.523472],"type":"Point"}
}