{
  "type": "Feature",
  "properties": {
    "iso:country":"IT",
    "sg:address":"21058 Solbiate Olona",
    "sg:city":"Solbiate Olona",
    "sg:orig_category":"Forniture Per Abbigliamento E Pelletterie",
    "sg:phone":"+39 0331 649474",
    "sg:postcode":"21058",
    "sg:province":"Varese",
    "wof:name":"Cascamificio Solbiatese Sas Di Elio & Dante Caprioli & C.",
    "wof:placetype":"venue"
},
  "geometry": {"coordinates":[8.8814792633,45.7982902527],"type":"Point"}
}