{
  "type": "Feature",
  "properties": {
    "iso:country":"IT",
    "sg:address":"40057 Granarolo Dell'emilia",
    "sg:classifiers":[
        {
            "category":"Manufacturing",
            "subcategory":"Tools & Machinery",
            "type":"Manufacturing & Wholesale Goods"
        }
    ],
    "sg:phone":"+39 051 767309",
    "sg:postcode":"40057",
    "sg:province":"Bologna",
    "sg:tags":[
        "machining",
        "mechanical"
    ],
    "wof:name":"Dozza Snc",
    "wof:placetype":"venue"
},
  "geometry": {"coordinates":[11.413293,44.536732],"type":"Point"}
}