{
  "type": "Feature",
  "properties": {
    "iso:country":"IT",
    "sg:address":"00040 Pomezia",
    "sg:city":"Pomezia",
    "sg:orig_category":"Alluminio E Leghe",
    "sg:phone":"+39 06 910 8200",
    "sg:postcode":"00040",
    "sg:province":"Roma",
    "wof:name":"Edilsystem Srl",
    "wof:placetype":"venue"
},
  "geometry": {"coordinates":[12.444936,41.776138],"type":"Point"}
}