{
  "type": "Feature",
  "properties": {
    "addr:full":"10125 Torino Torino Torino 10125",
    "addr:postcode":"10125;10125",
    "iso:country":"IT",
    "sg:address":"10125 Torino",
    "sg:city":"Torino",
    "sg:orig_category":"Lavorazioni Meccaniche E Servizi",
    "sg:phone":"+39 011 650 5257",
    "sg:postcode":"10125",
    "sg:province":"Torino",
    "wof:name":"Tenderini Carlo",
    "wof:placetype":"venue"
},
  "geometry": {"coordinates":[7.676185,45.055111],"type":"Point"}
}