{
  "type": "Feature",
  "properties": {
    "addr:full":"92019 Sciacca Sciacca Agrigento 92019",
    "addr:postcode":"92019;92019",
    "iso:country":"IT",
    "sg:address":"92019 Sciacca",
    "sg:city":"Sciacca",
    "sg:classifiers":[
        {
            "category":"Health Services",
            "subcategory":"Health Practitioner",
            "type":"Services"
        }
    ],
    "sg:phone":"+39 0925 86911",
    "sg:postcode":"92019",
    "sg:province":"Agrigento",
    "sg:tags":[
        "medici"
    ],
    "wof:name":"Alessi Filippo",
    "wof:placetype":"venue"
},
  "geometry": {"coordinates":[13.080832,37.512749],"type":"Point"}
}