{
  "type": "Feature",
  "properties": {
    "iso:country":"IT",
    "sg:address":"01034 Fabrica Di Roma",
    "sg:city":"Fabrica di Roma",
    "sg:orig_category":"Arredo Bagno Ed Idrosanitari. Idrosanitari E Accessori",
    "sg:phone":"+39 0761 575038",
    "sg:postcode":"01034",
    "sg:province":"Viterbo",
    "wof:name":"Ceramica Eos Srl",
    "wof:placetype":"venue"
},
  "geometry": {"coordinates":[12.334934,42.323509],"type":"Point"}
}