{
  "type": "Feature",
  "properties": {
    "addr:full":"52047 Marciano Della Chiana Marciano Arezzo 52047",
    "addr:postcode":"52047;52047",
    "iso:country":"IT",
    "sg:address":"52047 Marciano Della Chiana",
    "sg:city":"Marciano",
    "sg:orig_category":"Restaurants And Related Public Premises. Sport And Leisure, Services. Hotels And Hotel Facilities. Restaurants And Similar",
    "sg:phone":"+39 0575 845348",
    "sg:postcode":"52047",
    "sg:province":"Arezzo",
    "sg:website":"http://www.eurocasa.com",
    "wof:name":"Eurocasa Srl",
    "wof:placetype":"venue"
},
  "geometry": {"coordinates":[11.776281,43.302528],"type":"Point"}
}