{
  "type": "Feature",
  "properties": {
    "iso:country":"IT",
    "sg:address":"20122 Milano",
    "sg:city":"Milano",
    "sg:orig_category":"Nautica. Automobili E Mezzi Di Trasporto",
    "sg:phone":"+39 02 7600 6601",
    "sg:postcode":"20122",
    "sg:province":"Milano",
    "wof:name":"Cantieri Navali Liguri Di Riva Trigoso S.r.l.",
    "wof:placetype":"venue"
},
  "geometry": {"coordinates":[9.196806,45.459793],"type":"Point"}
}