{
  "type": "Feature",
  "properties": {
    "iso:country":"IT",
    "sg:address":"35035 Mestrino",
    "sg:city":"Mestrino",
    "sg:orig_category":"Servizi E Lavori Per Edilizia E Lavori Pubblici. Servizi E Lavori Per Ecologia E Smaltimento Rifiuti. Macchine E Forniture Per Ecologia E Smaltimento Rifiuti. Acqua, Luce, Gas E Societa' Di Esercizio ",
    "sg:phone":"+39 049 900 0661",
    "sg:postcode":"35035",
    "sg:province":"Padova",
    "wof:name":"Comitato Volontario Protezione Civile",
    "wof:placetype":"venue"
},
  "geometry": {"coordinates":[11.802547,45.387169],"type":"Point"}
}