{
  "type": "Feature",
  "properties": {
    "iso:country":"IT",
    "sg:address":"20123 Milano",
    "sg:city":"Milano",
    "sg:classifiers":[
        {
            "category":"Parking",
            "subcategory":"Lot",
            "type":"Transportation"
        }
    ],
    "sg:phone":"+39 02 8942 1244",
    "sg:postcode":"20123",
    "sg:province":"Milano",
    "sg:tags":[
        "good",
        "shipment",
        "transport"
    ],
    "wof:name":"Gen-ex Cargo",
    "wof:placetype":"venue"
},
  "geometry": {"coordinates":[9.174111,45.461628],"type":"Point"}
}