{
  "type": "Feature",
  "properties": {
    "addr:full":"Strada Statale 20 Km 31,200 12030 Cavallerleone Cavallerleone Cuneo 12030",
    "addr:housenumber":"km 31,200",
    "addr:postcode":"12030;12030",
    "addr:street":"Strada Statale 20",
    "iso:country":"IT",
    "sg:address":"Strada Statale 20 Km 31,200 12030 Cavallerleone",
    "sg:city":"Cavallerleone",
    "sg:classifiers":[
        {
            "category":"Manufacturing",
            "subcategory":"Building Materials",
            "type":"Manufacturing & Wholesale Goods"
        }
    ],
    "sg:phone":"+39 0172 85663",
    "sg:postcode":"12030",
    "sg:province":"Cuneo",
    "sg:tags":[
        "screw",
        "adjusting"
    ],
    "sg:website":"www.bullracconigi.it",
    "wof:name":"Bull Srl",
    "wof:placetype":"venue"
},
  "geometry": {"coordinates":[7.547111,44.388798],"type":"Point"}
}