{
  "type": "Feature",
  "properties": {
    "iso:country":"IT",
    "sg:address":"91025 Marsala",
    "sg:city":"Marsala",
    "sg:orig_category":"Macchine Utensili E Impianti",
    "sg:phone":"+39 0923 721277",
    "sg:postcode":"91025",
    "sg:province":"Trapani",
    "wof:name":"Nistico Varo Antonino",
    "wof:placetype":"venue"
},
  "geometry": {"coordinates":[12.789881,37.685482],"type":"Point"}
}