{
  "type": "Feature",
  "properties": {
    "addr:full":"71043 Manfredonia Manfredonia Foggia 71043",
    "addr:postcode":"71043;71043",
    "iso:country":"IT",
    "sg:address":"71043 Manfredonia",
    "sg:city":"Manfredonia",
    "sg:orig_category":"Abiti Da Lavoro Ed Indumenti Protettivi",
    "sg:phone":"+39 0884 542111",
    "sg:postcode":"71043",
    "sg:province":"Foggia",
    "wof:name":"Forniture Franco E Michele De Nittis & C. Sas",
    "wof:placetype":"venue"
},
  "geometry": {"coordinates":[15.805547,41.550507],"type":"Point"}
}