{
  "type": "Feature",
  "properties": {
    "addr:full":"70020 Bitritto Bitritto Bari 70020",
    "addr:postcode":"70020;70020",
    "iso:country":"IT",
    "sg:address":"70020 Bitritto",
    "sg:city":"Bitritto",
    "sg:classifiers":[
        {
            "category":"Restaurant",
            "type":"Food & Drink"
        }
    ],
    "sg:phone":"+39 080 385 4182",
    "sg:postcode":"70020",
    "sg:province":"Bari",
    "sg:tags":[
        "auxiliary",
        "entertainment",
        "premises",
        "related",
        "catering",
        "similar",
        "public",
        "restaurants"
    ],
    "wof:name":"Ristorante Pizzeria La Campagnola",
    "wof:placetype":"venue"
},
  "geometry": {"coordinates":[16.827328,41.040405],"type":"Point"}
}