{
  "type": "Feature",
  "properties": {
    "iso:country":"IT",
    "sg:address":"03019 Supino",
    "sg:city":"Supino",
    "sg:orig_category":"Gas Compressi E Liquefatti - Produzione E Ingrosso",
    "sg:phone":"+39 0775 201892",
    "sg:postcode":"03019",
    "sg:province":"Frosinone",
    "wof:name":"Energas Spa",
    "wof:placetype":"venue"
},
  "geometry": {"coordinates":[13.288356,41.604637],"type":"Point"}
}