{
  "type": "Feature",
  "properties": {
    "addr:full":"62100 Macerata Macerata Macerata 62100",
    "addr:postcode":"62100;62100",
    "iso:country":"IT",
    "sg:address":"62100 Macerata",
    "sg:city":"Macerata",
    "sg:orig_category":"Arredamenti - Produzione E Ingrosso",
    "sg:phone":"+39 0733 270260",
    "sg:postcode":"62100",
    "sg:province":"Macerata",
    "wof:name":"Verducci Silvano",
    "wof:placetype":"venue"
},
  "geometry": {"coordinates":[13.461816,43.305492],"type":"Point"}
}