{
  "type": "Feature",
  "properties": {
    "iso:country":"IT",
    "sg:address":"Via Fleming Alessandro 11 37135 Verona",
    "sg:city":"Verona",
    "sg:classifiers":[
        {
            "category":"Food & Beverages",
            "subcategory":"Fruits & Vegetables",
            "type":"Retail Goods"
        }
    ],
    "sg:phone":"+39 045 820 1800",
    "sg:postcode":"37135",
    "sg:province":"Verona",
    "wof:name":"Extrafood International Srl",
    "wof:placetype":"venue"
},
  "geometry": {"coordinates":[10.9855737686,45.3997077942],"type":"Point"}
}