{
  "type": "Feature",
  "properties": {
    "iso:country":"IT",
    "sg:address":"00196 Roma",
    "sg:city":"Roma",
    "sg:orig_category":"Scuole E Servizi Scolastici. Servizi Per Lo Sport E Il Tempo Libero",
    "sg:phone":"+39 06 323 1843",
    "sg:postcode":"00196",
    "sg:province":"Roma",
    "wof:name":"Federazione Italiana Atletica Leggera",
    "wof:placetype":"venue"
},
  "geometry": {"coordinates":[12.484874,41.951958],"type":"Point"}
}