{
  "type": "Feature",
  "properties": {
    "iso:country":"IT",
    "sg:address":"62010 Montecassiano",
    "sg:city":"Montecassiano",
    "sg:orig_category":"Animali Domestici - Allevamento E Addestramento",
    "sg:phone":"+39 0733 290531",
    "sg:postcode":"62010",
    "sg:province":"Macerata",
    "sg:website":"http://www.isobox.it",
    "wof:name":"Isobox Srl",
    "wof:placetype":"venue"
},
  "geometry": {"coordinates":[13.068444,43.195961],"type":"Point"}
}