{
  "type": "Feature",
  "properties": {
    "iso:country":"IT",
    "sg:address":"40012 Calderara Di Reno",
    "sg:city":"Calderara di Reno",
    "sg:orig_category":"Motori Ed Organi Di Trasmissione",
    "sg:phone":"+39 051 728935",
    "sg:postcode":"40012",
    "sg:province":"Bologna",
    "wof:name":"Tramec S.r.l.",
    "wof:placetype":"venue"
},
  "geometry": {"coordinates":[11.2666034698,44.5388031006],"type":"Point"}
}