{
  "type": "Feature",
  "properties": {
    "addr:full":"Corso Zanardelli 32, Brescia, Bs",
    "addr:housenumber":"32",
    "addr:street":"Corso Zanardelli",
    "iso:country":"IT",
    "sg:address":"Corso Zanardelli 32, Brescia, Bs",
    "sg:classifiers":[
        {
            "category":"Banks & Credit Unions",
            "subcategory":"Bank",
            "type":"Services"
        }
    ],
    "wof:name":"Hopa Spa",
    "wof:placetype":"venue"
},
  "geometry": {"coordinates":[10.221111,45.53656],"type":"Point"}
}