{
  "type": "Feature",
  "properties": {
    "addr:full":"40011 Anzola Dell'emilia Bologna 40011",
    "addr:postcode":"40011;40011",
    "iso:country":"IT",
    "sg:address":"40011 Anzola Dell'emilia",
    "sg:orig_category":"Cavi E Conduttori Elettrici E Telefonici",
    "sg:phone":"+39 051 734816",
    "sg:postcode":"40011",
    "sg:province":"Bologna",
    "sg:website":"http://www.vemasrl.com",
    "wof:name":"Vema Srl",
    "wof:placetype":"venue"
},
  "geometry": {"coordinates":[11.223577,44.535561],"type":"Point"}
}