{
  "type": "Feature",
  "properties": {
    "addr:full":"Via Penna 62v 52028 Terranuova Bracciolini Penna Arezzo 52028",
    "addr:housenumber":"62v",
    "addr:postcode":"52028;52028",
    "addr:street":"Via Penna",
    "iso:country":"IT",
    "sg:address":"Via Penna 62v 52028 Terranuova Bracciolini",
    "sg:city":"Penna",
    "sg:classifiers":[
        {
            "category":"Military Area",
            "subcategory":"Air Force Base",
            "type":"Public Place"
        }
    ],
    "sg:phone":"+39 055 970 5278",
    "sg:postcode":"52028",
    "sg:province":"Arezzo",
    "sg:tags":[
        "equipment",
        "system",
        "linkage",
        "automation"
    ],
    "sg:website":"www.thecna.it",
    "wof:name":"Th Automazione Di Staderini Giovanni E Vannelli Danilo S.n.c.",
    "wof:placetype":"venue"
},
  "geometry": {"coordinates":[11.737691,43.50536],"type":"Point"}
}