{
  "type": "Feature",
  "properties": {
    "iso:country":"IT",
    "sg:address":"Piazza Volta 6; Albese",
    "sg:classifiers":[
        {
            "category":"Banks & Credit Unions",
            "subcategory":"Bank",
            "type":"Services"
        }
    ],
    "sg:phone":"+39 031 427715",
    "wof:name":"Banca Briantea Spa",
    "wof:placetype":"venue"
},
  "geometry": {"coordinates":[9.166712,45.79702],"type":"Point"}
}