{
  "type": "Feature",
  "properties": {
    "iso:country":"IT",
    "sg:address":"90138 Palermo",
    "sg:city":"Palermo",
    "sg:orig_category":"Gioielleria, Oreficeria E Argenteria. Shopping",
    "sg:phone":"+39 091 611 8311",
    "sg:postcode":"90138",
    "sg:province":"Palermo",
    "wof:name":"Creazioni In Vetro Di Cottone Caterina",
    "wof:placetype":"venue"
},
  "geometry": {"coordinates":[13.349241,38.117783],"type":"Point"}
}