{
  "type": "Feature",
  "properties": {
    "addr:full":"20030 Seveso Seveso Milano 20030",
    "addr:postcode":"20030;20030",
    "iso:country":"IT",
    "sg:address":"20030 Seveso",
    "sg:city":"Seveso",
    "sg:orig_category":"Lampadari - Vendita Al Dettaglio",
    "sg:phone":"+39 036 250 3232",
    "sg:postcode":"20030",
    "sg:province":"Milano",
    "wof:name":"Camas Di Carnelli Renzo",
    "wof:placetype":"venue"
},
  "geometry": {"coordinates":[9.183888,45.472157],"type":"Point"}
}