{
  "type": "Feature",
  "properties": {
    "addr:full":"88046 Nicastro Nicastro Catanzaro 88046",
    "addr:postcode":"88046;88046",
    "iso:country":"IT",
    "sg:address":"88046 Nicastro",
    "sg:city":"Nicastro",
    "sg:classifiers":[
        {
            "category":"Health Services",
            "subcategory":"Health Practitioner",
            "type":"Services"
        }
    ],
    "sg:phone":"+39 0968 22881",
    "sg:postcode":"88046",
    "sg:province":"Catanzaro",
    "sg:tags":[
        "medici"
    ],
    "wof:name":"Di Cello Michele",
    "wof:placetype":"venue"
},
  "geometry": {"coordinates":[16.319246,38.969604],"type":"Point"}
}