{
  "type": "Feature",
  "properties": {
    "iso:country":"IT",
    "sg:address":"Corso Giovecca 108, 44100 Ferrara, Fe",
    "sg:city":"Ferrara",
    "sg:classifiers":[
        {
            "category":"Banks & Credit Unions",
            "subcategory":"Bank",
            "type":"Services"
        }
    ],
    "sg:phone":"+39 0532 296111",
    "sg:postcode":"44100",
    "sg:province":"Ferrara",
    "sg:website":"http://www.carife.it",
    "wof:name":"Cassa Di Risparmio Di Ferrara Spa",
    "wof:placetype":"venue"
},
  "geometry": {"coordinates":[11.624698,44.835941],"type":"Point"}
}