{
  "type": "Feature",
  "properties": {
    "addr:full":"28010 Briga Novarese Briga Novarese Novara 28010",
    "addr:postcode":"28010;28010",
    "iso:country":"IT",
    "sg:address":"28010 Briga Novarese",
    "sg:city":"Briga Novarese",
    "sg:orig_category":"Arredamenti - Materiali",
    "sg:phone":"+39 0322 913201",
    "sg:postcode":"28010",
    "sg:province":"Novara",
    "wof:name":"Bellosta Antonio",
    "wof:placetype":"venue"
},
  "geometry": {"coordinates":[8.451396,45.733967],"type":"Point"}
}