{
  "type": "Feature",
  "properties": {
    "iso:country":"IT",
    "sg:address":"36050 Sovizzo",
    "sg:city":"Sovizzo",
    "sg:orig_category":"Materiali Edili",
    "sg:phone":"+39 0444 334014",
    "sg:postcode":"36050",
    "sg:province":"Vicenza",
    "wof:name":"Sipag Bisalta (s.p.a.)",
    "wof:placetype":"venue"
},
  "geometry": {"coordinates":[11.441817,45.508968],"type":"Point"}
}