{
  "type": "Feature",
  "properties": {
    "iso:country":"IT",
    "sg:address":"33010 Tavagnacco",
    "sg:city":"Tavagnacco",
    "sg:orig_category":"Macchine Utensili E Impianti",
    "sg:phone":"+39 0432 573908",
    "sg:postcode":"33010",
    "sg:province":"Udine",
    "wof:name":"Senini Tecnosiderurgica S.r.l.",
    "wof:placetype":"venue"
},
  "geometry": {"coordinates":[13.23061,46.113056],"type":"Point"}
}