{
  "type": "Feature",
  "properties": {
    "addr:full":"20145 Milano Milano Milano 20145",
    "addr:postcode":"20145;20145",
    "iso:country":"IT",
    "sg:address":"20145 Milano",
    "sg:city":"Milano",
    "sg:orig_category":"Servizi Per Aziende, Manifestazioni E Supporto Agli Scambi Commerciali",
    "sg:phone":"+39 02 438 2101",
    "sg:postcode":"20145",
    "sg:province":"Milano",
    "wof:name":"Inevent Srl",
    "wof:placetype":"venue"
},
  "geometry": {"coordinates":[9.155361,45.471901],"type":"Point"}
}