{
  "type": "Feature",
  "properties": {
    "iso:country":"IT",
    "sg:address":"88040 Falerna",
    "sg:city":"Falerna",
    "sg:orig_category":"Pulitura E Lucidatura Metalli",
    "sg:phone":"+39 0968 93110",
    "sg:postcode":"88040",
    "sg:province":"Catanzaro",
    "wof:name":"M. & G. Di Grandinetti Franco Sas",
    "wof:placetype":"venue"
},
  "geometry": {"coordinates":[16.171957016,39.0034065247],"type":"Point"}
}