{
  "type": "Feature",
  "properties": {
    "iso:country":"IT",
    "sg:address":"20122 Milano",
    "sg:city":"Milano",
    "sg:orig_category":"Tende Da Sole",
    "sg:phone":"+39 02 5831 5644",
    "sg:postcode":"20122",
    "sg:province":"Milano",
    "wof:name":"Progetto Ombra Di Bacci",
    "wof:placetype":"venue"
},
  "geometry": {"coordinates":[9.184138,45.455605],"type":"Point"}
}