{
  "type": "Feature",
  "properties": {
    "addr:full":"06073 Corciano Corciano Perugia 06073",
    "addr:postcode":"06073;06073",
    "iso:country":"IT",
    "sg:address":"06073 Corciano",
    "sg:city":"Corciano",
    "sg:classifiers":[
        {
            "category":"Manufacturing",
            "subcategory":"Tools & Machinery",
            "type":"Manufacturing & Wholesale Goods"
        }
    ],
    "sg:phone":"+39 075 697 8916",
    "sg:postcode":"06073",
    "sg:province":"Perugia",
    "sg:tags":[
        "machining",
        "mechanical"
    ],
    "sg:website":"http://www.sgp.it",
    "wof:name":"S.g.p. Srl",
    "wof:placetype":"venue"
},
  "geometry": {"coordinates":[12.28618,43.116272],"type":"Point"}
}