{
  "type": "Feature",
  "properties": {
    "addr:full":"50123 Firenze Firenze Firenze 50123",
    "addr:postcode":"50123;50123",
    "iso:country":"IT",
    "sg:address":"50123 Firenze",
    "sg:city":"Firenze",
    "sg:orig_category":"Agenzie Viaggi E Turismo",
    "sg:phone":"+39 055 294329",
    "sg:postcode":"50123",
    "sg:province":"Firenze",
    "wof:name":"Biemme Viaggi E Crociere",
    "wof:placetype":"venue"
},
  "geometry": {"coordinates":[11.250507,43.772644],"type":"Point"}
}