{
  "type": "Feature",
  "properties": {
    "iso:country":"IT",
    "sg:address":"30037 Scorze'",
    "sg:orig_category":"Abbigliamento - Produzione E Ingrosso",
    "sg:phone":"+39 041 584 0111",
    "sg:postcode":"30037",
    "sg:province":"Venezia",
    "wof:name":"Pellizzato Manuela",
    "wof:placetype":"venue"
},
  "geometry": {"coordinates":[12.108796,45.570019],"type":"Point"}
}