{
  "type": "Feature",
  "properties": {
    "iso:country":"IT",
    "sg:address":"37136 Verona",
    "sg:city":"Verona",
    "sg:orig_category":"Climatizzazione E Condizionamento, Apparecchiature E Servizi",
    "sg:phone":"+39 045 820 0741",
    "sg:postcode":"37136",
    "sg:province":"Verona",
    "wof:name":"V.i.m.e.c. Srl",
    "wof:placetype":"venue"
},
  "geometry": {"coordinates":[10.965693,45.410999],"type":"Point"}
}