{
  "type": "Feature",
  "properties": {
    "iso:country":"IT",
    "sg:address":"Via Del Progresso 61030 Saltara",
    "sg:city":"Saltara",
    "sg:classifiers":[
        {
            "category":"Manufacturing",
            "subcategory":"Metals",
            "type":"Manufacturing & Wholesale Goods"
        }
    ],
    "sg:phone":"+39 0721 895175",
    "sg:postcode":"61030",
    "sg:province":"Pesaro E Urbino",
    "sg:tags":[
        "processing"
    ],
    "wof:name":"Nuova Plastic Metal Snc",
    "wof:placetype":"venue"
},
  "geometry": {"coordinates":[12.9192323685,43.7449226379],"type":"Point"}
}