{
  "type": "Feature",
  "properties": {
    "addr:full":"81011 Alife Alife Caserta 81011",
    "addr:postcode":"81011;81011",
    "iso:country":"IT",
    "sg:address":"81011 Alife",
    "sg:city":"Alife",
    "sg:orig_category":"Prodotti Di Base E Forniture Per Industria Alimentare E Bevande. Carta, Cartone E Prodotti Primari. Forniture Per Attivita' Commerciali Ed Artigianali",
    "sg:phone":"+39 0823 786172",
    "sg:postcode":"81011",
    "sg:province":"Caserta",
    "wof:name":"Riselli Candida",
    "wof:placetype":"venue"
},
  "geometry": {"coordinates":[14.3442792892,41.3248291016],"type":"Point"}
}