{
  "type": "Feature",
  "properties": {
    "addr:full":"16129 Genova Genova Genova 16129",
    "addr:postcode":"16129;16129",
    "iso:country":"IT",
    "sg:address":"16129 Genova",
    "sg:city":"Genova",
    "sg:orig_category":"Servizi E Lavori Per Abbigliamento E Pelletterie. Arte Ed Artigianato Artistico. Shopping",
    "sg:phone":"+39 010 587804",
    "sg:postcode":"16129",
    "sg:province":"Genova",
    "wof:name":"Barbieri Fratelli",
    "wof:placetype":"venue"
},
  "geometry": {"coordinates":[9.019201,44.434074],"type":"Point"}
}