{
  "type": "Feature",
  "properties": {
    "iso:country":"IT",
    "sg:address":"51017 Pescia",
    "sg:city":"Pescia",
    "sg:orig_category":"Macchine, Impianti E Forniture Per Industria Grafica, Cartaria E Cartotecnica",
    "sg:phone":"+39 0572 427001",
    "sg:postcode":"51017",
    "sg:province":"Pistoia",
    "wof:name":"Meridiana Progetti",
    "wof:placetype":"venue"
},
  "geometry": {"coordinates":[10.940296,43.94735],"type":"Point"}
}