{
  "type": "Feature",
  "properties": {
    "iso:country":"IT",
    "sg:address":"Contrada Petrara 86020 San Polo Matese",
    "sg:city":"San Polo Matese",
    "sg:classifiers":[
        {
            "category":"Food & Beverages",
            "subcategory":"Dairy",
            "type":"Retail Goods"
        }
    ],
    "sg:phone":"+39 0874 782491",
    "sg:postcode":"86020",
    "sg:province":"Campobasso",
    "sg:tags":[
        "product"
    ],
    "wof:name":"Perrella Del Dr. Di Pardo Guglielmo E C. S.n.c.",
    "wof:placetype":"venue"
},
  "geometry": {"coordinates":[14.504766,41.4776],"type":"Point"}
}