{
  "type": "Feature",
  "properties": {
    "iso:country":"IT",
    "sg:address":"15100 Alessandria",
    "sg:city":"Alessandria",
    "sg:orig_category":"Servizi E Lavori Per Ecologia E Smaltimento Rifiuti. Servizi Ausiliari Di Sorveglianza, Manutenzione E Pulizia",
    "sg:phone":"+39 0131 223215",
    "sg:postcode":"15100",
    "sg:province":"Alessandria",
    "wof:name":"Amiu Azienda Municipalizzata Igiene Urbana",
    "wof:placetype":"venue"
},
  "geometry": {"coordinates":[8.627371,44.920555],"type":"Point"}
}