{
  "type": "Feature",
  "properties": {
    "addr:full":"00061 Anguillara Sabazia Anguillara Sabazia Roma 00061",
    "addr:postcode":"00061;00061",
    "addr:street":"Roma",
    "iso:country":"IT",
    "sg:address":"00061 Anguillara Sabazia",
    "sg:city":"Anguillara Sabazia",
    "sg:orig_category":"Articoli Da Regalo. Arte Ed Artigianato Artistico. Shopping",
    "sg:phone":"+39 06 999 6761",
    "sg:postcode":"00061",
    "sg:province":"Roma",
    "wof:name":"Cerioni Pia",
    "wof:placetype":"venue"
},
  "geometry": {"coordinates":[12.276033,42.088596],"type":"Point"}
}