{
  "type": "Feature",
  "properties": {
    "addr:full":"21047 Saronno Saronno Varese 21047",
    "addr:postcode":"21047;21047",
    "iso:country":"IT",
    "sg:address":"21047 Saronno",
    "sg:city":"Saronno",
    "sg:orig_category":"Riparazione Dei Mezzi Di Trasporto. Servizi Ausiliari Dei Mezzi Di Trasporto",
    "sg:phone":"+39 02 960 4981",
    "sg:postcode":"21047",
    "sg:province":"Varese",
    "wof:name":"Blucar Srl",
    "wof:placetype":"venue"
},
  "geometry": {"coordinates":[9.020998,45.612],"type":"Point"}
}