{
  "type": "Feature",
  "properties": {
    "iso:country":"IT",
    "sg:address":"20146 Milano",
    "sg:city":"Milano",
    "sg:orig_category":"Informatica - Consulenza E Servizi. Servizi Ausiliari Di Analisi, Controllo E Ricerca. Servizi Per Aziende, Manifestazioni E Supporto Agli Scambi Commerciali",
    "sg:phone":"+39 02 365 0471",
    "sg:postcode":"20146",
    "sg:province":"Milano",
    "wof:name":"Studio Guzzi",
    "wof:placetype":"venue"
},
  "geometry": {"coordinates":[9.141027,45.461796],"type":"Point"}
}