{
  "type": "Feature",
  "properties": {
    "iso:country":"IT",
    "sg:address":"50018 Scandicci",
    "sg:city":"Scandicci",
    "sg:orig_category":"Borse E Borsette - Produzione E Ingrosso",
    "sg:phone":"+39 055 720569",
    "sg:postcode":"50018",
    "sg:province":"Firenze",
    "wof:name":"Pelletterie Style. Gi Snc",
    "wof:placetype":"venue"
},
  "geometry": {"coordinates":[11.159367,43.762108],"type":"Point"}
}