{
  "type": "Feature",
  "properties": {
    "iso:country":"IT",
    "sg:address":"20121 Milano",
    "sg:city":"Milano",
    "sg:classifiers":[
        {
            "category":"Shopping",
            "subcategory":"Jewelry",
            "type":"Retail Goods"
        }
    ],
    "sg:phone":"+39 02 657 2575",
    "sg:postcode":"20121",
    "sg:province":"Milano",
    "sg:tags":[
        "watchmaker",
        "jewelers",
        "gold",
        "silversmiths"
    ],
    "wof:name":"Antichita' Volta Di Borghi Mauro",
    "wof:placetype":"venue"
},
  "geometry": {"coordinates":[9.190015,45.465603],"type":"Point"}
}