{
  "type": "Feature",
  "properties": {
    "addr:full":"30, Via Carlo Pisacane 20028 San Vittore Olona San Vittore Olona Milano 20028",
    "addr:postcode":"20028;vittore olona;20028",
    "addr:street":"Via Carlo Pisacane",
    "iso:country":"IT",
    "sg:address":"30, Via Carlo Pisacane 20028 San Vittore Olona",
    "sg:city":"San Vittore Olona",
    "sg:classifiers":[
        {
            "category":"Manufacturing",
            "subcategory":"Paper Products",
            "type":"Manufacturing & Wholesale Goods"
        }
    ],
    "sg:phone":"+39 0331 519955",
    "sg:postcode":"20028",
    "sg:province":"Milano",
    "sg:tags":[
        "cardboard"
    ],
    "wof:name":"Scatolificio Mino S.a.s. Di Ciprandi Beniamino & C.",
    "wof:placetype":"venue"
},
  "geometry": {"coordinates":[8.9487085342,45.5794525146],"type":"Point"}
}