{
  "type": "Feature",
  "properties": {
    "addr:full":"00128 Roma Roma Roma 00128",
    "addr:postcode":"00128;00128",
    "iso:country":"IT",
    "sg:address":"00128 Roma",
    "sg:city":"Roma",
    "sg:orig_category":"Tempo Libero - Articoli E Forniture. Regalistica Aziendale",
    "sg:phone":"+39 06 5079 5044",
    "sg:postcode":"00128",
    "sg:province":"Roma",
    "wof:name":"L'albero Dei Giochi",
    "wof:placetype":"venue"
},
  "geometry": {"coordinates":[12.445084,41.795528],"type":"Point"}
}