{
  "type": "Feature",
  "properties": {
    "iso:country":"IT",
    "sg:address":"00152 Roma",
    "sg:city":"Roma",
    "sg:classifiers":[
        {
            "category":"Health Services",
            "subcategory":"Dentist",
            "type":"Services"
        }
    ],
    "sg:phone":"+39 06 558 2229",
    "sg:postcode":"00152",
    "sg:province":"Roma",
    "sg:tags":[
        "hospital"
    ],
    "sg:website":"http://www.anniverdi.org",
    "wof:name":"Associazione Anni Verdi",
    "wof:placetype":"venue"
},
  "geometry": {"coordinates":[12.462209,41.868271],"type":"Point"}
}