{
  "type": "Feature",
  "properties": {
    "iso:country":"IT",
    "sg:address":"37135 Verona",
    "sg:city":"Verona",
    "sg:orig_category":"Minuterie - Produzione E Commercio",
    "sg:phone":"+39 045 504444",
    "sg:postcode":"37135",
    "sg:province":"Verona",
    "sg:website":"http://www.adige-molle.it",
    "wof:name":"Mollificio Adige Spa",
    "wof:placetype":"venue"
},
  "geometry": {"coordinates":[10.9657335281,45.4079093933],"type":"Point"}
}