{
  "type": "Feature",
  "properties": {
    "addr:full":"14, Via Casc. Fabbrica 27040 Arena Po Arena Po Pavia 27040",
    "addr:postcode":"27040;27040",
    "addr:street":"Via Casc. Fabbrica;Po;Po",
    "iso:country":"IT",
    "sg:address":"14, Via Casc. Fabbrica 27040 Arena Po",
    "sg:city":"Arena Po",
    "sg:classifiers":[
        {
            "category":"Airport",
            "subcategory":"General Aviation",
            "type":"Transportation"
        }
    ],
    "sg:phone":"+39 0385 272117",
    "sg:postcode":"27040",
    "sg:province":"Pavia",
    "sg:tags":[
        "transport",
        "air"
    ],
    "wof:name":"Air Service Center S.r.l.",
    "wof:placetype":"venue"
},
  "geometry": {"coordinates":[9.156563,45.185886],"type":"Point"}
}