{
  "type": "Feature",
  "properties": {
    "addr:full":"42048 Rubiera Reggio Nell'Emilia 42048",
    "addr:postcode":"42048;42048",
    "iso:country":"IT",
    "sg:address":"42048 Rubiera",
    "sg:orig_category":"Lavorazioni Metalli, Stampaggio E Saldatura",
    "sg:phone":"+39 0522 629385",
    "sg:postcode":"42048",
    "sg:province":"Reggio Nell'Emilia",
    "wof:name":"Gobbi Silvio & C. Snc",
    "wof:placetype":"venue"
},
  "geometry": {"coordinates":[10.773761,44.656303],"type":"Point"}
}