{
  "type": "Feature",
  "properties": {
    "addr:full":"102/a, Viale Druso 39100 Bolzano Bolzano Bolzano/Bozen 39100",
    "addr:housenumber":"102 / a",
    "addr:postcode":"39100;39100",
    "addr:street":"Viale Druso",
    "iso:country":"IT",
    "sg:address":"102/a, Viale Druso 39100 Bolzano",
    "sg:city":"Bolzano",
    "sg:orig_category":"Miscellaneous Products",
    "sg:phone":"+39 0471 500847",
    "sg:postcode":"39100",
    "sg:province":"Bolzano/Bozen",
    "wof:name":"Vobis Maxi - Store",
    "wof:placetype":"venue"
},
  "geometry": {"coordinates":[11.3282394409,46.461643219],"type":"Point"}
}