{
  "type": "Feature",
  "properties": {
    "iso:country":"IT",
    "sg:address":"26, Via Della Croce 33030 Campoformido",
    "sg:city":"Campoformido",
    "sg:classifiers":[
        {
            "category":"Manufacturing",
            "subcategory":"Lumber",
            "type":"Manufacturing & Wholesale Goods"
        }
    ],
    "sg:phone":"+39 0432 561625",
    "sg:postcode":"33030",
    "sg:province":"Udine",
    "sg:tags":[
        "wood"
    ],
    "wof:name":"Turco Erminio S.n.c.",
    "wof:placetype":"venue"
},
  "geometry": {"coordinates":[13.217357,46.025837],"type":"Point"}
}