{
  "type": "Feature",
  "properties": {
    "iso:country":"IT",
    "sg:address":"24050 Ghisalba",
    "sg:city":"Ghisalba",
    "sg:orig_category":"Forniture Per Agricoltura E Zootecnia. Forniture Per Attivita' Industriali",
    "sg:phone":"+39 036 392421",
    "sg:postcode":"24050",
    "sg:province":"Bergamo",
    "wof:name":"Helios (s.r.l.)",
    "wof:placetype":"venue"
},
  "geometry": {"coordinates":[9.7559556961,45.5862503052],"type":"Point"}
}