{
  "type": "Feature",
  "properties": {
    "addr:full":"63031 Castel Di Lama Castel di Lama Ascoli Piceno 63031",
    "addr:postcode":"63031;63031",
    "addr:street":"Di Lama;Piceno",
    "iso:country":"IT",
    "sg:address":"63031 Castel Di Lama",
    "sg:city":"Castel di Lama",
    "sg:orig_category":"Articoli Regalo - Vendita Al Dettaglio",
    "sg:phone":"+39 0736 814816",
    "sg:postcode":"63031",
    "sg:province":"Ascoli Piceno",
    "wof:name":"Fantasia Di Lucadei Nadia",
    "wof:placetype":"venue"
},
  "geometry": {"coordinates":[13.717805,42.862072],"type":"Point"}
}