{
  "type": "Feature",
  "properties": {
    "iso:country":"IT",
    "sg:address":"5, V. Ponte 95015 Linguaglossa",
    "sg:city":"Linguaglossa",
    "sg:classifiers":[
        {
            "category":"Parking",
            "subcategory":"Lot",
            "type":"Transportation"
        }
    ],
    "sg:phone":"+39 095647755662",
    "sg:postcode":"95015",
    "sg:province":"Catania",
    "sg:tags":[
        "transport",
        "road"
    ],
    "sg:website":"http://www.paginegialle.it/daidoneonoranzefunebri",
    "wof:name":"Agenzia Onoranze Funebri La Sfinge Di Daidone & Lo Giudice Sas",
    "wof:placetype":"venue"
},
  "geometry": {"coordinates":[15.204539,37.8078],"type":"Point"}
}