{
  "type": "Feature",
  "properties": {
    "addr:full":"Via Pacinotti 64 21100 Varese Varese Varese 21100",
    "addr:housenumber":"64",
    "addr:postcode":"21100;21100",
    "addr:street":"Via Pacinotti",
    "iso:country":"IT",
    "sg:address":"Via Pacinotti 64 21100 Varese",
    "sg:city":"Varese",
    "sg:classifiers":[
        {
            "category":"Organizations",
            "subcategory":"Religious Organization",
            "type":"Services"
        }
    ],
    "sg:phone":"+39 0332 491247",
    "sg:postcode":"21100",
    "sg:province":"Varese",
    "sg:tags":[
        "lamp",
        "display",
        "arrangement"
    ],
    "sg:website":"www.formaefunzione.com",
    "wof:name":"Forma E Funzione Srl",
    "wof:placetype":"venue"
},
  "geometry": {"coordinates":[8.832108,45.837299],"type":"Point"}
}