{
  "type": "Feature",
  "properties": {
    "addr:full":"Vle Del Lavoro 18 45100 Rovigo Rovigo Rovigo 45100",
    "addr:housenumber":"18",
    "addr:postcode":"45100;45100",
    "addr:street":"Vle Del Lavoro",
    "iso:country":"IT",
    "sg:address":"Vle Del Lavoro 18 45100 Rovigo",
    "sg:city":"Rovigo",
    "sg:classifiers":[
        {
            "category":"Building & Trades",
            "subcategory":"Construction",
            "type":"Services"
        }
    ],
    "sg:phone":"+39 0425 474815",
    "sg:postcode":"45100",
    "sg:province":"Rovigo",
    "sg:tags":[
        "cistern"
    ],
    "sg:website":"www.zani.it",
    "wof:name":"Zani Srl",
    "wof:placetype":"venue"
},
  "geometry": {"coordinates":[11.789797,45.070736],"type":"Point"}
}