{
  "type": "Feature",
  "properties": {
    "iso:country":"IT",
    "sg:address":"61022 Talacchio Di Colbordolo",
    "sg:city":"Colbordolo",
    "sg:orig_category":"Lucidatura, Laccatura E Verniciatura Mobili",
    "sg:phone":"+39 0721 478276",
    "sg:postcode":"61022",
    "sg:province":"Pesaro E Urbino",
    "wof:name":"Pierre Srl",
    "wof:placetype":"venue"
},
  "geometry": {"coordinates":[12.484241,43.611721],"type":"Point"}
}