{
  "type": "Feature",
  "properties": {
    "iso:country":"IT",
    "sg:address":"51039 Quarrata",
    "sg:city":"Quarrata",
    "sg:orig_category":"Calzature, Pelletterie E Pelli",
    "sg:phone":"+39 0573 72719",
    "sg:postcode":"51039",
    "sg:province":"Pistoia",
    "wof:name":"Tessitura R.c. Srl",
    "wof:placetype":"venue"
},
  "geometry": {"coordinates":[10.954097,43.883736],"type":"Point"}
}