{
  "type": "Feature",
  "properties": {
    "iso:country":"IT",
    "sg:address":"00012 Guidonia Montecelio",
    "sg:city":"Guidonia",
    "sg:orig_category":"Prodotti Chimici Secondari. Tempo Libero - Articoli E Forniture. Servizi Per Lo Sport E Il Tempo Libero. Servizi Per Aziende, Manifestazioni E Supporto Agli Scambi Commerciali",
    "sg:phone":"+39 0774 343944",
    "sg:postcode":"00012",
    "sg:province":"Roma",
    "wof:name":"Raffaele Stefania",
    "wof:placetype":"venue"
},
  "geometry": {"coordinates":[12.7020215988,41.9910736084],"type":"Point"}
}