{
  "type": "Feature",
  "properties": {
    "iso:country":"IT",
    "sg:address":"Via Marano Ticino 7 28040 Mezzomerico",
    "sg:city":"Marano Ticino",
    "sg:orig_category":"Iron Balls",
    "sg:phone":"+39 0321 923010",
    "sg:postcode":"28040",
    "sg:province":"Novara",
    "sg:website":"www.intercom.it/gst",
    "wof:name":"Gst Europa S.p.a.",
    "wof:placetype":"venue"
},
  "geometry": {"coordinates":[8.606902,45.620346],"type":"Point"}
}