{
  "type": "Feature",
  "properties": {
    "addr:full":"37060 Lugagnano Lugagnano Verona 37060",
    "addr:postcode":"37060;37060",
    "iso:country":"IT",
    "sg:address":"37060 Lugagnano",
    "sg:city":"Lugagnano",
    "sg:classifiers":[
        {
            "category":"Government",
            "subcategory":"Office",
            "type":"Public Place"
        }
    ],
    "sg:phone":"+39 045 868 1061",
    "sg:postcode":"37060",
    "sg:province":"Verona",
    "sg:tags":[
        "e",
        "lo",
        "tempo",
        "libero",
        "per",
        "spettacolo",
        "servizi",
        "culturali",
        "sport",
        "il"
    ],
    "wof:name":"Sgaramella Maurizio",
    "wof:placetype":"venue"
},
  "geometry": {"coordinates":[10.88647,45.431572],"type":"Point"}
}