{
  "type": "Feature",
  "properties": {
    "iso:country":"IT",
    "sg:address":"00141 Roma",
    "sg:city":"Roma",
    "sg:orig_category":"Prodotti Finiti Stampati. Forniture E Materiali Per Imballaggio E Confezionamento. Forniture Per Attivita' Commerciali Ed Artigianali",
    "sg:phone":"+39 06 810 2861",
    "sg:postcode":"00141",
    "sg:province":"Roma",
    "wof:name":"Marchionne Marcello",
    "wof:placetype":"venue"
},
  "geometry": {"coordinates":[12.5222043991,41.9435462952],"type":"Point"}
}