{
  "type": "Feature",
  "properties": {
    "addr:full":"55100 Lucca Lucca Lucca 55100",
    "addr:postcode":"55100;55100",
    "iso:country":"IT",
    "sg:address":"55100 Lucca",
    "sg:city":"Lucca",
    "sg:orig_category":"Manufacturers: Prefabbricati. Prodotti Vari In Metallo",
    "sg:phone":"+39 0583 980027",
    "sg:postcode":"55100",
    "sg:province":"Lucca",
    "wof:name":"Bertini Snc",
    "wof:placetype":"venue"
},
  "geometry": {"coordinates":[10.55749,43.843113],"type":"Point"}
}