{
  "type": "Feature",
  "properties": {
    "iso:country":"IT",
    "sg:address":"80025 Casandrino",
    "sg:city":"Casandrino",
    "sg:orig_category":"Forniture Per Attivita' Industriali",
    "sg:phone":"+39 081 833 1263",
    "sg:postcode":"80025",
    "sg:province":"Napoli",
    "wof:name":"Con. Sud (s.n.c.)",
    "wof:placetype":"venue"
},
  "geometry": {"coordinates":[14.2527198792,40.9188346863],"type":"Point"}
}