{
  "type": "Feature",
  "properties": {
    "iso:country":"IT",
    "sg:address":"15048 Valenza",
    "sg:city":"Valenza",
    "sg:orig_category":"Restaurants And Related Public Premises. Sport And Leisure, Services. Hotels And Hotel Facilities. Restaurants And Similar",
    "sg:phone":"+39 0131 954120",
    "sg:postcode":"15048",
    "sg:province":"Alessandria",
    "wof:name":"Felli Federico",
    "wof:placetype":"venue"
},
  "geometry": {"coordinates":[8.610115,44.960964],"type":"Point"}
}