{
  "type": "Feature",
  "properties": {
    "addr:full":"21051 Brenno Useria Brenno useria Varese 21051",
    "addr:postcode":"21051;21051",
    "iso:country":"IT",
    "sg:address":"21051 Brenno Useria",
    "sg:city":"Brenno useria",
    "sg:orig_category":"Forniture Per Abbigliamento E Pelletterie. Forniture Per Attivita' Commerciali Ed Artigianali",
    "sg:phone":"+39 0332 471515",
    "sg:postcode":"21051",
    "sg:province":"Varese",
    "wof:name":"Tenax Plast Di Spennagallo S.",
    "wof:placetype":"venue"
},
  "geometry": {"coordinates":[8.8752727509,45.8583908081],"type":"Point"}
}