{
  "type": "Feature",
  "properties": {
    "iso:country":"IT",
    "sg:address":"08100 Nuoro",
    "sg:city":"Nuoro",
    "sg:orig_category":"Pubblica Amministrazione",
    "sg:phone":"+39 0784 230029",
    "sg:postcode":"08100",
    "sg:province":"Nuoro",
    "wof:name":"Comunita' Montana N. 9 Del Nuorese",
    "wof:placetype":"venue"
},
  "geometry": {"coordinates":[9.3235712051,40.3213043213],"type":"Point"}
}