{
  "type": "Feature",
  "properties": {
    "addr:full":"18038 Sanremo Imperia 18038",
    "addr:postcode":"18038;18038",
    "iso:country":"IT",
    "sg:address":"18038 Sanremo",
    "sg:orig_category":"Impiantistica E Prodotti Tecnologici Per Edilizia. Forniture Industriali Per Prevenzione, Controllo E Sicurezza",
    "sg:phone":"+39 0184 572549",
    "sg:postcode":"18038",
    "sg:province":"Imperia",
    "wof:name":"Rebora Roberto",
    "wof:placetype":"venue"
},
  "geometry": {"coordinates":[7.772501,43.824368],"type":"Point"}
}