{
  "type": "Feature",
  "properties": {
    "iso:country":"IT",
    "sg:address":"03014 Fiuggi",
    "sg:city":"Fiuggi",
    "sg:orig_category":"Automobili E Mezzi Di Trasporto. Riparazione Dei Mezzi Di Trasporto",
    "sg:phone":"+39 0775 504674",
    "sg:postcode":"03014",
    "sg:province":"Frosinone",
    "wof:name":"Principia Moto",
    "wof:placetype":"venue"
},
  "geometry": {"coordinates":[13.193618,41.848114],"type":"Point"}
}