{
  "type": "Feature",
  "properties": {
    "iso:country":"IT",
    "sg:address":"20125 Milano",
    "sg:city":"Milano",
    "sg:orig_category":"Professionisti - Studi E Servizi Ed Associazioni Di Interesse Aziendale. Associazioni Ed Organismi Di Interesse Pubblico. Chiese Ed Associazioni Religiose",
    "sg:postcode":"20125",
    "sg:province":"Milano",
    "wof:name":"Vita Universale",
    "wof:placetype":"venue"
},
  "geometry": {"coordinates":[9.2013082504,45.4950256348],"type":"Point"}
}