{
  "type": "Feature",
  "properties": {
    "iso:country":"IT",
    "sg:address":"80047 San Giuseppe Vesuviano",
    "sg:city":"San Giuseppe Vesuviano",
    "sg:orig_category":"Autotrasporti",
    "sg:phone":"+39 081 529 4361",
    "sg:postcode":"80047",
    "sg:province":"Napoli",
    "sg:website":"http://www.autotrasportitiene.it",
    "wof:name":"Autotrasporti E Spedizioni Tiene Sas",
    "wof:placetype":"venue"
},
  "geometry": {"coordinates":[14.524618,40.815567],"type":"Point"}
}