{
  "type": "Feature",
  "properties": {
    "iso:country":"IT",
    "sg:address":"50019 Sesto Fiorentino",
    "sg:city":"Sesto Fiorentino",
    "sg:orig_category":"Non-classified Establishments",
    "sg:phone":"+39 055 420 7767",
    "sg:postcode":"50019",
    "sg:province":"Firenze",
    "wof:name":"Negozi Richard Ginori",
    "wof:placetype":"venue"
},
  "geometry": {"coordinates":[11.192209,43.800419],"type":"Point"}
}