{
  "type": "Feature",
  "properties": {
    "addr:full":"20099 Sesto San Giovanni Sesto San Giovanni Milano 20099",
    "addr:postcode":"20099;20099",
    "iso:country":"IT",
    "sg:address":"20099 Sesto San Giovanni",
    "sg:city":"Sesto San Giovanni",
    "sg:orig_category":"Materiali E Componenti Elettrotecnici",
    "sg:phone":"+39 02 2247 0669",
    "sg:postcode":"20099",
    "sg:province":"Milano",
    "wof:name":"Fratus Di Colomba Roberto",
    "wof:placetype":"venue"
},
  "geometry": {"coordinates":[9.24081,45.527328],"type":"Point"}
}