{
  "type": "Feature",
  "properties": {
    "addr:full":"55046 Seravezza LU",
    "addr:postcode":"55046",
    "iso:country":"IT",
    "sg:address":"55046 Seravezza",
    "sg:orig_category":"Macchine Ed Impianti Per Edilizia E Lavori Pubblici",
    "sg:phone":"+39 0584 769205",
    "sg:province":"LU",
    "wof:name":"Guglielmi Gino & C. Sas",
    "wof:placetype":"venue"
},
  "geometry": {"coordinates":[10.204556,43.976425],"type":"Point"}
}