{
  "type": "Feature",
  "properties": {
    "iso:country":"IT",
    "sg:address":"24/int., Via Sarzanese 55054 Massarosa",
    "sg:city":"Massarosa",
    "sg:classifiers":[
        {
            "category":"Autos & Motor Vehicles",
            "subcategory":"Automobile Sales",
            "type":"Retail Goods"
        }
    ],
    "sg:phone":"+39 0584 997197",
    "sg:postcode":"55054",
    "sg:province":"Lucca",
    "sg:tags":[
        "motor-cars"
    ],
    "wof:name":"Suncar S.p.a.",
    "wof:placetype":"venue"
},
  "geometry": {"coordinates":[10.4095945358,43.8551063538],"type":"Point"}
}