{
  "type": "Feature",
  "properties": {
    "iso:country":"IT",
    "sg:address":"12, Via Toscanini 20010 Arluno",
    "sg:city":"Arluno",
    "sg:classifiers":[
        {
            "category":"Manufacturing",
            "subcategory":"Glass & Minerals",
            "type":"Manufacturing & Wholesale Goods"
        }
    ],
    "sg:phone":"+39 39029017243",
    "sg:postcode":"20010",
    "sg:province":"Milano",
    "wof:name":"Vetro Project (s.r.l.)",
    "wof:placetype":"venue"
},
  "geometry": {"coordinates":[8.94167,45.495075],"type":"Point"}
}