{
  "type": "Feature",
  "properties": {
    "iso:country":"IT",
    "sg:address":"10/15/bis, Via Guglielminetti Amalia 10136 Torino",
    "sg:city":"Torino",
    "sg:classifiers":[
        {
            "category":"Professional",
            "subcategory":"Printing & Photocopies",
            "type":"Services"
        }
    ],
    "sg:phone":"+39 39011356403",
    "sg:postcode":"10136",
    "sg:province":"Torino",
    "wof:name":"A.g.v. Di Bianchi Rag. Mario & C. (s.n.c.)",
    "wof:placetype":"venue"
},
  "geometry": {"coordinates":[7.6866188049,45.0705604553],"type":"Point"}
}