{
  "type": "Feature",
  "properties": {
    "iso:country":"IT",
    "sg:address":"39012 Merano",
    "sg:city":"Merano",
    "sg:orig_category":"Arredo Cucina Ed Elettrodomestici. Elettrodomestici",
    "sg:phone":"+39 0473 221166",
    "sg:postcode":"39012",
    "sg:province":"Bolzano/Bozen",
    "wof:name":"Da Soghe Ennio",
    "wof:placetype":"venue"
},
  "geometry": {"coordinates":[11.150358,46.669689],"type":"Point"}
}