{
  "type": "Feature",
  "properties": {
    "iso:country":"IT",
    "sg:address":"16035 Rapallo",
    "sg:city":"Rapallo",
    "sg:orig_category":"Serramenti Ed Infissi",
    "sg:phone":"+39 0185 234022",
    "sg:postcode":"16035",
    "sg:province":"Genova",
    "wof:name":"Fattori Fabio",
    "wof:placetype":"venue"
},
  "geometry": {"coordinates":[9.063873,44.430016],"type":"Point"}
}