{
  "type": "Feature",
  "properties": {
    "iso:country":"IT",
    "sg:address":"117, Viale Brenta 36056 Tezze Sul Brenta",
    "sg:city":"Tezze sul Brenta",
    "sg:classifiers":[
        {
            "category":"Manufacturing",
            "subcategory":"Textiles",
            "type":"Manufacturing & Wholesale Goods"
        }
    ],
    "sg:phone":"+39 0424 539150",
    "sg:postcode":"36056",
    "sg:province":"Vicenza",
    "sg:tags":[
        "leather",
        "raw",
        "material",
        "-"
    ],
    "wof:name":"Industria Conciaria Europa (s.p.a.)",
    "wof:placetype":"venue"
},
  "geometry": {"coordinates":[11.740978,45.646339],"type":"Point"}
}