{
  "type": "Feature",
  "properties": {
    "iso:country":"IT",
    "sg:address":"26010 Moscazzano",
    "sg:city":"Moscazzano",
    "sg:orig_category":"Trattamenti Termici E Superficiali Metalli, Galvanotecnica",
    "sg:phone":"+39 0373 66334",
    "sg:postcode":"26010",
    "sg:province":"Cremona",
    "wof:name":"Galvo Di Oneta Alberto",
    "wof:placetype":"venue"
},
  "geometry": {"coordinates":[9.67811,45.292938],"type":"Point"}
}