{
  "type": "Feature",
  "properties": {
    "addr:full":"05100 Terni Terni Terni 05100",
    "addr:postcode":"05100;05100",
    "iso:country":"IT",
    "sg:address":"05100 Terni",
    "sg:city":"Terni",
    "sg:orig_category":"Audiovisivi Apparecchi Ed Impianti - Produzione, Commercio E Noleggio",
    "sg:phone":"+39 0744 306554",
    "sg:postcode":"05100",
    "sg:province":"Terni",
    "wof:name":"Videopro Srl",
    "wof:placetype":"venue"
},
  "geometry": {"coordinates":[12.621644,42.580986],"type":"Point"}
}