{
  "type": "Feature",
  "properties": {
    "iso:country":"IT",
    "sg:address":"55/d, Via Bandiera Fratelli 30175 Venezia",
    "sg:city":"Venezia",
    "sg:classifiers":[
        {
            "category":"Professional",
            "subcategory":"Engineering",
            "type":"Services"
        }
    ],
    "sg:phone":"+39 39041923096",
    "sg:postcode":"30175",
    "sg:province":"Venezia",
    "sg:tags":[
        "machine",
        "-",
        "mechanical"
    ],
    "wof:name":"V.a.m.u. (s.a.s.)",
    "wof:placetype":"venue"
},
  "geometry": {"coordinates":[12.326627,45.440895],"type":"Point"}
}