{
  "type": "Feature",
  "properties": {
    "iso:country":"IT",
    "sg:address":"Via Lungo Gogna 45 36015 Schio",
    "sg:city":"Schio",
    "sg:orig_category":"Heat-sealing Machines And Equipment",
    "sg:phone":"+39 0445 529421",
    "sg:postcode":"36015",
    "sg:province":"Vicenza",
    "sg:website":"www.comiz.com",
    "wof:name":"Comiz Packaging Srl",
    "wof:placetype":"venue"
},
  "geometry": {"coordinates":[11.333372,45.718678],"type":"Point"}
}