{
  "type": "Feature",
  "properties": {
    "addr:full":"00125 Lido Di Ostia Roma 00125",
    "addr:postcode":"00125;00125",
    "addr:street":"Di Ostia Roma",
    "iso:country":"IT",
    "sg:address":"00125 Lido Di Ostia",
    "sg:orig_category":"Forniture Per Agricoltura E Zootecnia",
    "sg:phone":"+39 06 521 4500",
    "sg:postcode":"00125",
    "sg:province":"Roma",
    "wof:name":"Zootecnica Alimentare S.r.l.",
    "wof:placetype":"venue"
},
  "geometry": {"coordinates":[12.3361749649,41.7637023926],"type":"Point"}
}