{
  "type": "Feature",
  "properties": {
    "iso:country":"IT",
    "sg:address":"2 Via S. Domenico, 50133 Firenze",
    "sg:city":"Firenze",
    "sg:classifiers":[
        {
            "category":"Banks & Credit Unions",
            "subcategory":"Financial Services",
            "type":"Services"
        }
    ],
    "sg:phone":"+39 39055583253",
    "sg:postcode":"50133",
    "sg:province":"Firenze",
    "sg:tags":[
        "banking",
        "finance",
        "insurance"
    ],
    "wof:name":"Sif Finanziaria Spa",
    "wof:placetype":"venue"
},
  "geometry": {"coordinates":[11.266453743,43.7714691162],"type":"Point"}
}