{
  "type": "Feature",
  "properties": {
    "addr:full":"61100 Pesaro Pesaro Pesaro E Urbino 61100",
    "addr:postcode":"61100;61100",
    "iso:country":"IT",
    "sg:address":"61100 Pesaro",
    "sg:city":"Pesaro",
    "sg:orig_category":"Legno Lavorazione Macchine - Commercio",
    "sg:phone":"+39 0721 390181",
    "sg:postcode":"61100",
    "sg:province":"Pesaro E Urbino",
    "wof:name":"Elettrosystem Di Magnelli Federico",
    "wof:placetype":"venue"
},
  "geometry": {"coordinates":[12.923156,43.900589],"type":"Point"}
}