{
  "type": "Feature",
  "properties": {
    "iso:country":"IT",
    "sg:address":"21046 Malnate",
    "sg:city":"Malnate",
    "sg:orig_category":"Forniture Per Attivita' Industriali",
    "sg:phone":"+39 0332 425023",
    "sg:postcode":"21046",
    "sg:province":"Varese",
    "wof:name":"Roncoroni Industria Mole Srl",
    "wof:placetype":"venue"
},
  "geometry": {"coordinates":[8.8816223145,45.8033599854],"type":"Point"}
}