{
  "type": "Feature",
  "properties": {
    "iso:country":"IT",
    "sg:address":"Via Don Minzoni 2 20090 Settala",
    "sg:city":"Settala",
    "sg:classifiers":[
        {
            "category":"Utilities",
            "subcategory":"Water",
            "type":"Services"
        }
    ],
    "sg:phone":"+39 02 958 9104",
    "sg:postcode":"20090",
    "sg:province":"Milano",
    "sg:tags":[
        "aerial",
        "accessory"
    ],
    "wof:name":"Ateb Sas",
    "wof:placetype":"venue"
},
  "geometry": {"coordinates":[9.3929,45.424587],"type":"Point"}
}