{
  "type": "Feature",
  "properties": {
    "iso:country":"IT",
    "sg:address":"00, Contrada Pianelle 82027 Pontelandolfo",
    "sg:city":"Pontelandolfo",
    "sg:classifiers":[
        {
            "category":"Professional",
            "subcategory":"Engineering",
            "type":"Services"
        }
    ],
    "sg:phone":"+39 0824 851227",
    "sg:postcode":"82027",
    "sg:province":"Benevento",
    "sg:tags":[
        "machine",
        "-",
        "mechanical"
    ],
    "wof:name":"Ecologica S.r.l.",
    "wof:placetype":"venue"
},
  "geometry": {"coordinates":[14.781174,41.130447],"type":"Point"}
}