{
  "type": "Feature",
  "properties": {
    "iso:country":"IT",
    "sg:address":"45, Via Adriano Publio Elio 20128 Milano",
    "sg:city":"Milano",
    "sg:classifiers":[
        {
            "category":"Professional",
            "subcategory":"Engineering",
            "type":"Services"
        }
    ],
    "sg:phone":"+39 02 2720 2798",
    "sg:postcode":"20128",
    "sg:province":"Milano",
    "sg:tags":[
        "machine",
        "-",
        "mechanical"
    ],
    "wof:name":"Weko Italia (s.r.l.)",
    "wof:placetype":"venue"
},
  "geometry": {"coordinates":[9.203226,45.482468],"type":"Point"}
}