{
  "type": "Feature",
  "properties": {
    "iso:country":"IT",
    "sg:address":"30030 Venezia",
    "sg:orig_category":"Nautica - Equipaggiamenti",
    "sg:phone":"+39 041 901498",
    "sg:postcode":"30030",
    "sg:province":"Venezia",
    "wof:name":"Lem Covers Srl",
    "wof:placetype":"venue"
},
  "geometry": {"coordinates":[12.283148,45.484623],"type":"Point"}
}