{
  "type": "Feature",
  "properties": {
    "addr:full":"70056 Molfetta Molfetta Bari 70056",
    "addr:postcode":"70056;70056",
    "iso:country":"IT",
    "sg:address":"70056 Molfetta",
    "sg:city":"Molfetta",
    "sg:orig_category":"Calzature, Pelletterie E Pelli",
    "sg:phone":"+39 080 334 5340",
    "sg:postcode":"70056",
    "sg:province":"Bari",
    "wof:name":"Pellicceria Di Giovanni S.r.l.",
    "wof:placetype":"venue"
},
  "geometry": {"coordinates":[16.570192,41.176632],"type":"Point"}
}