{
  "type": "Feature",
  "properties": {
    "addr:full":"28100 Novara Novara Novara 28100",
    "addr:postcode":"28100;28100",
    "iso:country":"IT",
    "sg:address":"28100 Novara",
    "sg:city":"Novara",
    "sg:orig_category":"Macchine, Impianti Ed Attrezzature Per Industria Alimentare E Bevande",
    "sg:phone":"+39 0321 455192",
    "sg:postcode":"28100",
    "sg:province":"Novara",
    "wof:name":"Facchinetti Srl",
    "wof:placetype":"venue"
},
  "geometry": {"coordinates":[8.616724,45.417732],"type":"Point"}
}