{
  "type": "Feature",
  "properties": {
    "addr:full":"22070 Casnate Con Bernate Casnate Como 22070",
    "addr:postcode":"22070;22070",
    "addr:street":"Con Bernate Casnate",
    "iso:country":"IT",
    "sg:address":"22070 Casnate Con Bernate",
    "sg:city":"Casnate",
    "sg:orig_category":"Macchine E Forniture Per Ecologia E Smaltimento Rifiuti. Ricambi E Componenti Dei Mezzi Di Trasporto",
    "sg:phone":"+39 031 450010",
    "sg:postcode":"22070",
    "sg:province":"Como",
    "wof:name":"Rainbow Air Cleaner Stefano",
    "wof:placetype":"venue"
},
  "geometry": {"coordinates":[9.072904,45.755627],"type":"Point"}
}