{
  "type": "Feature",
  "properties": {
    "iso:country":"IT",
    "sg:address":"40128 Bologna",
    "sg:city":"Bologna",
    "sg:orig_category":"Lavorazioni Metalli, Stampaggio E Saldatura",
    "sg:phone":"+39 051 328484",
    "sg:postcode":"40128",
    "sg:province":"Bologna",
    "wof:name":"Forgia Rapida (s.r.l.)",
    "wof:placetype":"venue"
},
  "geometry": {"coordinates":[11.360664,44.535244],"type":"Point"}
}