{
  "type": "Feature",
  "properties": {
    "iso:country":"IT",
    "sg:address":"Via San Giovanni Delle Formiche 4 24060 Villongo",
    "sg:city":"Villongo",
    "sg:classifiers":[
        {
            "category":"Recreation",
            "subcategory":"Boat Charter",
            "type":"Entertainment"
        }
    ],
    "sg:phone":"+39 035 927301",
    "sg:postcode":"24060",
    "sg:province":"Bergamo",
    "sg:tags":[
        "work",
        "small",
        "aluminium",
        "made"
    ],
    "sg:website":"www.rioboats.com",
    "wof:name":"Nautica Serena Srl",
    "wof:placetype":"venue"
},
  "geometry": {"coordinates":[9.923359,45.676472],"type":"Point"}
}