{
  "type": "Feature",
  "properties": {
    "iso:country":"IT",
    "sg:address":"16121 Genova",
    "sg:city":"Genova",
    "sg:orig_category":"Arredo Urbano",
    "sg:phone":"+39 010 557 5614",
    "sg:postcode":"16121",
    "sg:province":"Genova",
    "sg:website":"http://www.astergenova.it",
    "wof:name":"A.s.t.e.r. Azienda Servizi Territoriali Comune Di Genova",
    "wof:placetype":"venue"
},
  "geometry": {"coordinates":[8.939713,44.405628],"type":"Point"}
}