{
  "type": "Feature",
  "properties": {
    "iso:country":"IT",
    "sg:address":"Via Portogallo 11 35127 Padova",
    "sg:city":"Padova",
    "sg:classifiers":[
        {
            "category":"Banks & Credit Unions",
            "subcategory":"Investment Brokerage",
            "type":"Services"
        }
    ],
    "sg:phone":"+39 049 761885",
    "sg:postcode":"35127",
    "sg:province":"Padova",
    "sg:tags":[
        "shop",
        "device",
        "equipping"
    ],
    "sg:website":"www.remiro.it",
    "wof:name":"Remiro Srl",
    "wof:placetype":"venue"
},
  "geometry": {"coordinates":[11.923117,45.353432],"type":"Point"}
}