{
  "type": "Feature",
  "properties": {
    "addr:full":"61032 Fano Fano Pesaro E Urbino 61032",
    "addr:postcode":"61032;61032",
    "iso:country":"IT",
    "sg:address":"61032 Fano",
    "sg:city":"Fano",
    "sg:orig_category":"Accessori Dei Mezzi Di Trasporto",
    "sg:phone":"+39 0721 805020",
    "sg:postcode":"61032",
    "sg:province":"Pesaro E Urbino",
    "wof:name":"Autofficina Busca Leonardo",
    "wof:placetype":"venue"
},
  "geometry": {"coordinates":[13.010337,43.839691],"type":"Point"}
}