{
  "type": "Feature",
  "properties": {
    "iso:country":"IT",
    "sg:address":"267, Via Roccagiovine 00156 Roma",
    "sg:city":"Roma",
    "sg:classifiers":[
        {
            "category":"Professional",
            "subcategory":"Printing & Photocopies",
            "type":"Services"
        }
    ],
    "sg:phone":"+39 390 641 6171",
    "sg:postcode":"00156",
    "sg:province":"Roma",
    "wof:name":"Lancio Spa",
    "wof:placetype":"venue"
},
  "geometry": {"coordinates":[12.6474151611,41.9629592896],"type":"Point"}
}