{
  "type": "Feature",
  "properties": {
    "iso:country":"IT",
    "sg:address":"37030 Lavagno",
    "sg:city":"Lavagno",
    "sg:orig_category":"Cinematografia E Radiotelevisione. Servizi Per Aziende, Manifestazioni E Supporto Agli Scambi Commerciali",
    "sg:phone":"+39 045 898 0831",
    "sg:postcode":"37030",
    "sg:province":"Verona",
    "wof:name":"Mediabros Srl",
    "wof:placetype":"venue"
},
  "geometry": {"coordinates":[11.100833,45.448689],"type":"Point"}
}