{
  "type": "Feature",
  "properties": {
    "iso:country":"IT",
    "sg:address":"Via Gerini 10a; Lerici; 19032",
    "sg:city":"Lerici",
    "sg:classifiers":[
        {
            "category":"Banks & Credit Unions",
            "subcategory":"Bank",
            "type":"Services"
        }
    ],
    "sg:phone":"+39 0187 967233",
    "sg:postcode":"19032",
    "sg:province":"La Spezia",
    "wof:name":"Banca Carige Spa",
    "wof:placetype":"venue"
},
  "geometry": {"coordinates":[9.910772,44.076046],"type":"Point"}
}