{
  "type": "Feature",
  "properties": {
    "iso:country":"IT",
    "sg:address":"Via Belvedere 1; Lipomo; 22030",
    "sg:city":"Lipomo",
    "sg:classifiers":[
        {
            "category":"Banks & Credit Unions",
            "subcategory":"Bank",
            "type":"Services"
        }
    ],
    "sg:phone":"+39 031 280500",
    "sg:postcode":"22030",
    "sg:province":"Como",
    "wof:name":"Banca Popolare Di Lecco",
    "wof:placetype":"venue"
},
  "geometry": {"coordinates":[9.127478,45.794952],"type":"Point"}
}