{
  "type": "Feature",
  "properties": {
    "addr:full":"00198 Roma Roma Roma 00198",
    "addr:postcode":"00198;00198",
    "iso:country":"IT",
    "sg:address":"00198 Roma",
    "sg:city":"Roma",
    "sg:orig_category":"Carpenterie Legno",
    "sg:phone":"+39 06 884 0263",
    "sg:postcode":"00198",
    "sg:province":"Roma",
    "sg:website":"http://www.legnostrutture.it",
    "wof:name":"Legnostrutture Roma Di Ing. Massimo Pasanisi",
    "wof:placetype":"venue"
},
  "geometry": {"coordinates":[12.502829,41.919041],"type":"Point"}
}