{
  "type": "Feature",
  "properties": {
    "iso:country":"IT",
    "sg:address":"31044 Montebelluna",
    "sg:city":"Montebelluna",
    "sg:orig_category":"Non-classified Establishments",
    "sg:phone":"+39 0423 812227",
    "sg:postcode":"31044",
    "sg:province":"Treviso",
    "sg:website":"http://www.biebisedie.it",
    "wof:name":"La B & B Srl",
    "wof:placetype":"venue"
},
  "geometry": {"coordinates":[12.06727,45.767292],"type":"Point"}
}