{
  "type": "Feature",
  "properties": {
    "iso:country":"IT",
    "sg:address":"71100 Foggia",
    "sg:city":"Foggia",
    "sg:orig_category":"Utensili Meccanici E Materiali",
    "sg:phone":"+39 0881 773674",
    "sg:postcode":"71100",
    "sg:province":"Foggia",
    "wof:name":"So.r.in. Sas Di Baldassini & C.",
    "wof:placetype":"venue"
},
  "geometry": {"coordinates":[15.564099,41.46796],"type":"Point"}
}