{
  "type": "Feature",
  "properties": {
    "iso:country":"IT",
    "sg:address":"60015 Falconara Marittima",
    "sg:city":"Falconara Marittima",
    "sg:orig_category":"Campeggio",
    "sg:phone":"+39 071 911319",
    "sg:postcode":"60015",
    "sg:province":"Ancona",
    "wof:name":"Il Mercatino",
    "wof:placetype":"venue"
},
  "geometry": {"coordinates":[13.39846,43.62957],"type":"Point"}
}