{
  "type": "Feature",
  "properties": {
    "iso:country":"IT",
    "sg:address":"Contrada Brucazzi 93012 Gela",
    "sg:city":"Gela",
    "sg:classifiers":[
        {
            "category":"Manufacturing",
            "subcategory":"Rubber & Plastics",
            "type":"Manufacturing & Wholesale Goods"
        }
    ],
    "sg:phone":"+39 0933 923533",
    "sg:postcode":"93012",
    "sg:province":"Caltanissetta",
    "wof:name":"Ecoplast S.r.l.",
    "wof:placetype":"venue"
},
  "geometry": {"coordinates":[14.0632896423,37.4899101257],"type":"Point"}
}