{
  "type": "Feature",
  "properties": {
    "addr:full":"65024 Manoppello Manoppello Pescara 65024",
    "addr:postcode":"65024;65024",
    "addr:street":"Manoppello",
    "iso:country":"IT",
    "sg:address":"65024 Manoppello",
    "sg:city":"Manoppello",
    "sg:orig_category":"Elettrotecnica Industriale, Prodotti E Apparecchiature. Ricambi E Componenti Dei Mezzi Di Trasporto",
    "sg:phone":"+39 085 856 1741",
    "sg:postcode":"65024",
    "sg:province":"Pescara",
    "wof:name":"Casa Della Batteria",
    "wof:placetype":"venue"
},
  "geometry": {"coordinates":[14.198356,42.442387],"type":"Point"}
}