{
  "type": "Feature",
  "properties": {
    "iso:country":"IT",
    "sg:address":"Viale Liegi 44; Roma",
    "sg:classifiers":[
        {
            "category":"Banks & Credit Unions",
            "subcategory":"Bank",
            "type":"Services"
        }
    ],
    "sg:phone":"+39 06 859416",
    "wof:name":"Credito Emiliano Spa",
    "wof:placetype":"venue"
},
  "geometry": {"coordinates":[12.496002,41.92123],"type":"Point"}
}