{
  "type": "Feature",
  "properties": {
    "iso:country":"IT",
    "sg:address":"20161 Milano",
    "sg:city":"Milano",
    "sg:orig_category":"Macchine E Forniture Per Industria Orafa E Per Orologeria",
    "sg:phone":"+39 02 6620 4870",
    "sg:postcode":"20161",
    "sg:province":"Milano",
    "wof:name":"Celsi Massimiliano & C. Snc",
    "wof:placetype":"venue"
},
  "geometry": {"coordinates":[9.17084,45.523651],"type":"Point"}
}