{
  "type": "Feature",
  "properties": {
    "iso:country":"IT",
    "sg:address":"22100 Como",
    "sg:city":"Como",
    "sg:orig_category":"Termotecnica E Riscaldamento, Apparecchiature E Servizi",
    "sg:phone":"+39 031 305733",
    "sg:postcode":"22100",
    "sg:province":"Como",
    "wof:name":"Calcaterra Marco Isotherm Calcaterra",
    "wof:placetype":"venue"
},
  "geometry": {"coordinates":[9.100422,45.796135],"type":"Point"}
}