{
  "type": "Feature",
  "properties": {
    "iso:country":"IT",
    "sg:address":"22100 Como",
    "sg:city":"Como",
    "sg:orig_category":"Tessuti E Stoffe - Vendita Al Dettaglio",
    "sg:phone":"+39 031 261320",
    "sg:postcode":"22100",
    "sg:province":"Como",
    "wof:name":"La Pusterla Shop Srl",
    "wof:placetype":"venue"
},
  "geometry": {"coordinates":[9.088156,45.801369],"type":"Point"}
}