{
  "type": "Feature",
  "properties": {
    "iso:country":"IT",
    "sg:address":"Via Emilia 23; Imola; 40026",
    "sg:city":"Imola",
    "sg:classifiers":[
        {
            "category":"Banks & Credit Unions",
            "subcategory":"Bank",
            "type":"Services"
        }
    ],
    "sg:phone":"+39 0542 27240",
    "sg:postcode":"40026",
    "sg:province":"Bologna",
    "wof:name":"Credito Italiano Spa",
    "wof:placetype":"venue"
},
  "geometry": {"coordinates":[11.713673,44.353653],"type":"Point"}
}