{
  "type": "Feature",
  "properties": {
    "iso:country":"IT",
    "sg:address":"80049 Somma Vesuviana",
    "sg:city":"Somma Vesuviana",
    "sg:orig_category":"Abbigliamento - Produzione E Ingrosso",
    "sg:phone":"+39 081 893 4003",
    "sg:postcode":"80049",
    "sg:province":"Napoli",
    "sg:website":"http://www.sharon.it",
    "wof:name":"Sharon Srl",
    "wof:placetype":"venue"
},
  "geometry": {"coordinates":[14.472026,40.862717],"type":"Point"}
}