{
  "type": "Feature",
  "properties": {
    "addr:full":"21040 Venegono Inferiore Venegono Inferiore Varese 21040",
    "addr:postcode":"21040;21040",
    "addr:street":"Inferiore",
    "iso:country":"IT",
    "sg:address":"21040 Venegono Inferiore",
    "sg:city":"Venegono Inferiore",
    "sg:orig_category":"Servizi E Lavori Industria Delle Materie Plastiche",
    "sg:phone":"+39 0331 866587",
    "sg:postcode":"21040",
    "sg:province":"Varese",
    "sg:website":"http://www.emmepiplast.it",
    "wof:name":"Emmepi Plast Srl",
    "wof:placetype":"venue"
},
  "geometry": {"coordinates":[8.900614,45.737915],"type":"Point"}
}