{
  "type": "Feature",
  "properties": {
    "addr:full":"00133 Roma Roma Roma 00133",
    "addr:postcode":"00133;00133",
    "iso:country":"IT",
    "sg:address":"00133 Roma",
    "sg:city":"Roma",
    "sg:orig_category":"Scuole E Servizi Scolastici. Servizi Per Lo Sport E Il Tempo Libero",
    "sg:phone":"+39 06 205 7480",
    "sg:postcode":"00133",
    "sg:province":"Roma",
    "wof:name":"Continenza Bruno",
    "wof:placetype":"venue"
},
  "geometry": {"coordinates":[12.657196,41.871357],"type":"Point"}
}