{
  "type": "Feature",
  "properties": {
    "addr:full":"25080 Manerba Del Garda Manerba del Garda Brescia 25080",
    "addr:postcode":"25080;25080",
    "iso:country":"IT",
    "sg:address":"25080 Manerba Del Garda",
    "sg:city":"Manerba del Garda",
    "sg:classifiers":[
        {
            "category":"Manufacturing",
            "subcategory":"Wood Products",
            "type":"Manufacturing & Wholesale Goods"
        }
    ],
    "sg:phone":"+39 036 555 5113",
    "sg:postcode":"25080",
    "sg:province":"Brescia",
    "sg:tags":[
        "decorative",
        "building",
        "furnishings",
        "semi-finished",
        "industry",
        "objects",
        "article"
    ],
    "wof:name":"Ceramiche Ferrarini Srl",
    "wof:placetype":"venue"
},
  "geometry": {"coordinates":[10.5166873932,45.6086044312],"type":"Point"}
}