{
  "type": "Feature",
  "properties": {
    "iso:country":"IT",
    "sg:address":"20032 Ospitaletto",
    "sg:city":"Ospitaletto",
    "sg:orig_category":"Acciaierie E Fonderie",
    "sg:phone":"+39 02 615521",
    "sg:postcode":"20032",
    "sg:province":"Milano",
    "wof:name":"Simi (s.p.a.)",
    "wof:placetype":"venue"
},
  "geometry": {"coordinates":[9.185416,45.443317],"type":"Point"}
}