{
  "type": "Feature",
  "properties": {
    "addr:full":"2, V. Bergamo 20060 Gessate Gessate Milano 20060",
    "addr:housenumber":"2",
    "addr:postcode":"20060;20060",
    "addr:street":"V. Bergamo",
    "iso:country":"IT",
    "sg:address":"2, V. Bergamo 20060 Gessate",
    "sg:city":"Gessate",
    "sg:classifiers":[
        {
            "category":"Real Estate",
            "subcategory":"Surveying",
            "type":"Services"
        }
    ],
    "sg:phone":"+39 02 9542 3550",
    "sg:postcode":"20060",
    "sg:province":"Milano",
    "sg:tags":[
        "equipment",
        "material",
        "good",
        "-",
        "handling"
    ],
    "wof:name":"Moveel Srl",
    "wof:placetype":"venue"
},
  "geometry": {"coordinates":[9.494099,45.563286],"type":"Point"}
}