{
  "type": "Feature",
  "properties": {
    "iso:country":"IT",
    "sg:address":"Via Carpi Ravarino 146 Limidi 41019 Soliera",
    "sg:city":"Soliera",
    "sg:classifiers":[
        {
            "category":"Organizations",
            "subcategory":"Labor Organization",
            "type":"Services"
        }
    ],
    "sg:phone":"+39 059 897333",
    "sg:postcode":"41019",
    "sg:province":"Modena",
    "sg:tags":[
        "woodworking",
        "machinery"
    ],
    "sg:website":"www.omga.it",
    "wof:name":"Omga Spa",
    "wof:placetype":"venue"
},
  "geometry": {"coordinates":[10.961097,44.752357],"type":"Point"}
}