{
  "type": "Feature",
  "properties": {
    "iso:country":"IT",
    "sg:address":"25018 Montichiari",
    "sg:city":"Montichiari",
    "sg:orig_category":"Decoratori",
    "sg:phone":"+39 030 996 1635",
    "sg:postcode":"25018",
    "sg:province":"Brescia",
    "wof:name":"Mazzardi Giuliano",
    "wof:placetype":"venue"
},
  "geometry": {"coordinates":[10.306363,45.475384],"type":"Point"}
}