{
  "type": "Feature",
  "properties": {
    "iso:country":"IT",
    "sg:address":"00147 Roma",
    "sg:city":"Roma",
    "sg:orig_category":"Arredo Urbano",
    "sg:phone":"+39 06 512 2537",
    "sg:postcode":"00147",
    "sg:province":"Roma",
    "wof:name":"Almet Srl",
    "wof:placetype":"venue"
},
  "geometry": {"coordinates":[12.498631,41.865704],"type":"Point"}
}