{
  "type": "Feature",
  "properties": {
    "iso:country":"IT",
    "sg:address":"00196 Roma",
    "sg:city":"Roma",
    "sg:orig_category":"Dolciumi E Gelati",
    "sg:phone":"+39 06 320 8766",
    "sg:postcode":"00196",
    "sg:province":"Roma",
    "wof:name":"Natoli Massimo",
    "wof:placetype":"venue"
},
  "geometry": {"coordinates":[12.462552,41.928375],"type":"Point"}
}