{
  "type": "Feature",
  "properties": {
    "iso:country":"IT",
    "sg:address":"63, Via Verdi 21010 Germignaga",
    "sg:city":"Germignaga",
    "sg:classifiers":[
        {
            "category":"Shopping",
            "type":"Retail Goods"
        }
    ],
    "sg:phone":"+39 0332 532568",
    "sg:postcode":"21010",
    "sg:province":"Varese",
    "sg:tags":[
        "finished",
        "-",
        "metallic"
    ],
    "wof:name":"Ascanio Masci S.r.l.",
    "wof:placetype":"venue"
},
  "geometry": {"coordinates":[8.8263845444,45.8176040649],"type":"Point"}
}