{
  "type": "Feature",
  "properties": {
    "addr:full":"5, Via Monterotondo 25050 Provaglio D'iseo Monterotondo Brescia 25050",
    "addr:postcode":"25050;25050",
    "addr:street":"Via Monterotondo",
    "iso:country":"IT",
    "sg:address":"5, Via Monterotondo 25050 Provaglio D'iseo",
    "sg:city":"Monterotondo",
    "sg:classifiers":[
        {
            "category":"Manufacturing",
            "subcategory":"Rubber & Plastics",
            "type":"Manufacturing & Wholesale Goods"
        }
    ],
    "sg:phone":"+39 030 982 3606",
    "sg:postcode":"25050",
    "sg:province":"Brescia",
    "wof:name":"Franplast (s.p.a.)",
    "wof:placetype":"venue"
},
  "geometry": {"coordinates":[10.0487375259,45.6282615662],"type":"Point"}
}