{
  "type": "Feature",
  "properties": {
    "iso:country":"IT",
    "sg:address":"19038 Sarzana",
    "sg:city":"Sarzana",
    "sg:orig_category":"Ristoranti",
    "sg:phone":"+39 0187 621088",
    "sg:postcode":"19038",
    "sg:province":"La Spezia",
    "wof:name":"Cargiolli Carlo Alberto - Rist. Girarrosto",
    "wof:placetype":"venue"
},
  "geometry": {"coordinates":[9.817682,44.107353],"type":"Point"}
}