{
  "type": "Feature",
  "properties": {
    "iso:country":"IT",
    "sg:address":"16121 Genova",
    "sg:city":"Genova",
    "sg:orig_category":"Acciai Inossidabili - Commercio",
    "sg:phone":"+39 010 582746",
    "sg:postcode":"16121",
    "sg:province":"Genova",
    "sg:website":"http://www.aksteel.it",
    "wof:name":"Ak Steel Srl",
    "wof:placetype":"venue"
},
  "geometry": {"coordinates":[8.936028,44.40435],"type":"Point"}
}