{
  "type": "Feature",
  "properties": {
    "iso:country":"IT",
    "sg:address":"39052 Caldaro Strada Vino",
    "sg:orig_category":"Enoteche E Vendita Vini",
    "sg:phone":"+39 0471 963122",
    "sg:postcode":"39052",
    "sg:province":"Bolzano/Bozen",
    "sg:website":"http://www.erste-neue.it",
    "wof:name":"Prima & Nuova Cantina Caldaro",
    "wof:placetype":"venue"
},
  "geometry": {"coordinates":[11.242086,46.397293],"type":"Point"}
}