{
  "type": "Feature",
  "properties": {
    "addr:full":"20041 Agrate Brianza Agrate Brianza Milano 20041",
    "addr:postcode":"20041;20041",
    "iso:country":"IT",
    "sg:address":"20041 Agrate Brianza",
    "sg:city":"Agrate Brianza",
    "sg:orig_category":"Apparecchiature E Sistemi Per Magazzinaggio E Movimentazione",
    "sg:phone":"+39 039 609 1797",
    "sg:postcode":"20041",
    "sg:province":"Milano",
    "sg:website":"http://www.rtoores.it",
    "wof:name":"R.t.o. Ores Srl",
    "wof:placetype":"venue"
},
  "geometry": {"coordinates":[9.33646,45.575031],"type":"Point"}
}