{
  "type": "Feature",
  "properties": {
    "iso:country":"IT",
    "sg:address":"Via Argelati Filippo 35 20143 Milano",
    "sg:city":"Milano",
    "sg:classifiers":[
        {
            "category":"Retail",
            "subcategory":"Emissions Testing",
            "type":"Services"
        }
    ],
    "sg:phone":"+39 02 5810 4936",
    "sg:postcode":"20143",
    "sg:province":"Milano",
    "sg:tags":[
        "consumer",
        "good",
        "export"
    ],
    "wof:name":"Samie Srl",
    "wof:placetype":"venue"
},
  "geometry": {"coordinates":[9.168199,45.447922],"type":"Point"}
}