{
  "type": "Feature",
  "properties": {
    "addr:full":"25128 Brescia Brescia Brescia 25128",
    "addr:postcode":"25128;25128",
    "iso:country":"IT",
    "sg:address":"25128 Brescia",
    "sg:city":"Brescia",
    "sg:orig_category":"Musica",
    "sg:phone":"+39 030 321725",
    "sg:postcode":"25128",
    "sg:province":"Brescia",
    "wof:name":"Avs Odracci Di Odracci Giorgio Srl",
    "wof:placetype":"venue"
},
  "geometry": {"coordinates":[9.6142473221,45.6404151917],"type":"Point"}
}