{
  "type": "Feature",
  "properties": {
    "addr:full":"20030 Lentate Sul Seveso Lentate sul Seveso Milano 20030",
    "addr:postcode":"20030;20030",
    "iso:country":"IT",
    "sg:address":"20030 Lentate Sul Seveso",
    "sg:city":"Lentate sul Seveso",
    "sg:orig_category":"Arredamenti - Produzione E Ingrosso",
    "sg:phone":"+39 036 256 0263",
    "sg:postcode":"20030",
    "sg:province":"Milano",
    "wof:name":"Dell'oca Fratelli Snc",
    "wof:placetype":"venue"
},
  "geometry": {"coordinates":[9.118447,45.684559],"type":"Point"}
}