{
  "type": "Feature",
  "properties": {
    "iso:country":"IT",
    "sg:address":"1, Via Giuseppe Spezzapria 36010 Velo D'astico",
    "sg:city":"Velo",
    "sg:classifiers":[
        {
            "category":"Professional",
            "subcategory":"Engineering",
            "type":"Services"
        }
    ],
    "sg:phone":"+39 0445 731313",
    "sg:postcode":"36010",
    "sg:province":"Vicenza",
    "sg:tags":[
        "machine",
        "-",
        "mechanical"
    ],
    "wof:name":"Forgital Italy S.p.a.",
    "wof:placetype":"venue"
},
  "geometry": {"coordinates":[11.379253,45.798351],"type":"Point"}
}