{
  "type": "Feature",
  "properties": {
    "addr:full":"07010 Chilivani Sassari 07010",
    "addr:postcode":"07010;07010",
    "iso:country":"IT",
    "sg:address":"07010 Chilivani",
    "sg:orig_category":"Carni, Salumi E Pesci. Zootecnia E Pesca, Allevamento Piccoli Animali",
    "sg:phone":"+39 079 759012",
    "sg:postcode":"07010",
    "sg:province":"Sassari",
    "wof:name":"Ce.di.al. Sas Di Muzzetto F. & C.",
    "wof:placetype":"venue"
},
  "geometry": {"coordinates":[8.558469,40.727165],"type":"Point"}
}