{
  "type": "Feature",
  "properties": {
    "iso:country":"IT",
    "sg:address":"31022 Preganziol",
    "sg:city":"Preganziol",
    "sg:orig_category":"Cemento E Calcestruzzo - Manufatti",
    "sg:phone":"+39 0422 633156",
    "sg:postcode":"31022",
    "sg:province":"Treviso",
    "wof:name":"Cestaro Cav. Gustavo Snc",
    "wof:placetype":"venue"
},
  "geometry": {"coordinates":[12.177604,45.6483],"type":"Point"}
}