{
  "type": "Feature",
  "properties": {
    "iso:country":"IT",
    "sg:address":"20068 Bettola",
    "sg:city":"Bettola",
    "sg:classifiers":[
        {
            "category":"Health Services",
            "subcategory":"Health Practitioner",
            "type":"Services"
        }
    ],
    "sg:phone":"+39 02 547 0033",
    "sg:postcode":"20068",
    "sg:province":"Milano",
    "sg:tags":[
        "medici"
    ],
    "wof:name":"Cendali Magda",
    "wof:placetype":"venue"
},
  "geometry": {"coordinates":[9.490218,45.56181],"type":"Point"}
}