{
  "type": "Feature",
  "properties": {
    "iso:country":"IT",
    "sg:address":"Localit\u00e0 Munariuola 1 28877 Anzola D'ossola",
    "sg:classifiers":[
        {
            "category":"Wholesale",
            "subcategory":"Metals & Minerals",
            "type":"Manufacturing & Wholesale Goods"
        }
    ],
    "sg:phone":"+39 0323 83988",
    "sg:postcode":"28877",
    "sg:province":"Verbano-Cusio-Ossola",
    "sg:tags":[
        "non-ferrous"
    ],
    "sg:website":"www.atecosrl.com",
    "wof:name":"Ateco S.r.l.",
    "wof:placetype":"venue"
},
  "geometry": {"coordinates":[8.272465,46.139969],"type":"Point"}
}