{
  "type": "Feature",
  "properties": {
    "addr:full":"24020 Castione Della Presolana Castione della Presolana Bergamo 24020",
    "addr:housenumber":"della presolana",
    "addr:postcode":"24020;24020",
    "iso:country":"IT",
    "sg:address":"24020 Castione Della Presolana",
    "sg:city":"Castione della Presolana",
    "sg:orig_category":"Tempo Libero - Articoli E Forniture. Regalistica Aziendale",
    "sg:phone":"+39 0346 60476",
    "sg:postcode":"24020",
    "sg:province":"Bergamo",
    "wof:name":"Tre T Di Trovati A. & C. (s.n.c.)",
    "wof:placetype":"venue"
},
  "geometry": {"coordinates":[10.026031,45.902748],"type":"Point"}
}