{
  "type": "Feature",
  "properties": {
    "iso:country":"IT",
    "sg:address":"12, V. S. Egidio 23900 Lecco",
    "sg:city":"Lecco",
    "sg:classifiers":[
        {
            "category":"Manufacturing",
            "subcategory":"Metals",
            "type":"Manufacturing & Wholesale Goods"
        }
    ],
    "sg:phone":"+39 0341 495023",
    "sg:postcode":"23900",
    "sg:province":"Lecco",
    "sg:tags":[
        "metallurgy",
        "metalworking"
    ],
    "sg:website":"http://www.kapriol.com",
    "wof:name":"Morganti Spa",
    "wof:placetype":"venue"
},
  "geometry": {"coordinates":[9.4222135544,45.870223999],"type":"Point"}
}