{
  "type": "Feature",
  "properties": {
    "iso:country":"IT",
    "sg:address":"36028 Rossano Veneto",
    "sg:city":"Rossano Veneto",
    "sg:classifiers":[
        {
            "category":"Retail",
            "subcategory":"Auto Repair",
            "type":"Services"
        }
    ],
    "sg:phone":"+39 0424 540131",
    "sg:postcode":"36028",
    "sg:province":"Vicenza",
    "sg:tags":[
        "car",
        "vehicles",
        "motor"
    ],
    "sg:website":"http://www.irmasrl.it",
    "wof:name":"I.r.m.a. Srl",
    "wof:placetype":"venue"
},
  "geometry": {"coordinates":[11.809811,45.706776],"type":"Point"}
}