{
  "type": "Feature",
  "properties": {
    "addr:full":"24060 San Paolo D'argon Bergamo 24060",
    "addr:housenumber":"24060",
    "addr:postcode":"24060",
    "addr:street":"San",
    "iso:country":"IT",
    "sg:address":"24060 San Paolo D'argon",
    "sg:orig_category":"Tessuti E Stoffe. Forniture Per Attivita' Industriali",
    "sg:phone":"+39 035 959493",
    "sg:postcode":"24060",
    "sg:province":"Bergamo",
    "wof:name":"Tex 95 Srl",
    "wof:placetype":"venue"
},
  "geometry": {"coordinates":[9.791124,45.682022],"type":"Point"}
}