{
  "type": "Feature",
  "properties": {
    "iso:country":"IT",
    "sg:address":"20144 Milano",
    "sg:city":"Milano",
    "sg:orig_category":"Forniture Per Abbigliamento E Pelletterie",
    "sg:phone":"+39 02 462807",
    "sg:postcode":"20144",
    "sg:province":"Milano",
    "wof:name":"Merceria Isadora Di Dall'ara Mirella",
    "wof:placetype":"venue"
},
  "geometry": {"coordinates":[9.1618051529,45.4570350647],"type":"Point"}
}