{
  "type": "Feature",
  "properties": {
    "iso:country":"IT",
    "sg:address":"00198 Roma",
    "sg:city":"Roma",
    "sg:classifiers":[
        {
            "category":"Wholesale",
            "subcategory":"Tobacco Products",
            "type":"Manufacturing & Wholesale Goods"
        }
    ],
    "sg:phone":"+39 06 855 9917",
    "sg:postcode":"00198",
    "sg:province":"Roma",
    "sg:tags":[
        "underwear",
        "medical-health",
        "bathing",
        "costumes",
        "orthopedic",
        "stocking"
    ],
    "wof:name":"Corm Snc",
    "wof:placetype":"venue"
},
  "geometry": {"coordinates":[12.400001,42.078896],"type":"Point"}
}