{
  "type": "Feature",
  "properties": {
    "iso:country":"IT",
    "sg:address":"Piazza San Lorenzo 47, 38064 Folgaria, Tn",
    "sg:city":"Folgaria",
    "sg:classifiers":[
        {
            "category":"Banks & Credit Unions",
            "subcategory":"Bank",
            "type":"Services"
        }
    ],
    "sg:postcode":"38064",
    "sg:province":"Trento",
    "wof:name":"Cassa Rurale Di Folgaria-banca Di Credito Cooperativo Scarl",
    "wof:placetype":"venue"
},
  "geometry": {"coordinates":[11.169438,45.91679],"type":"Point"}
}