{
  "type": "Feature",
  "properties": {
    "iso:country":"IT",
    "sg:address":"29015 Castel San Giovanni",
    "sg:city":"Castel San Giovanni",
    "sg:orig_category":"Non-classified Establishments",
    "sg:phone":"+39 0523 842256",
    "sg:postcode":"29015",
    "sg:province":"Piacenza",
    "wof:name":"Dosi Prima Infanzia",
    "wof:placetype":"venue"
},
  "geometry": {"coordinates":[9.4381,45.057095],"type":"Point"}
}