{
  "type": "Feature",
  "properties": {
    "iso:country":"IT",
    "sg:address":"10152 Torino",
    "sg:city":"Torino",
    "sg:orig_category":"Traduttori Ed Interpreti",
    "sg:phone":"+39 011 436 7691",
    "sg:postcode":"10152",
    "sg:province":"Torino",
    "sg:website":"http://www.geocities.com/associazione_coruss",
    "wof:name":"Coruss Ass.",
    "wof:placetype":"venue"
},
  "geometry": {"coordinates":[7.676039,45.082676],"type":"Point"}
}