{
  "type": "Feature",
  "properties": {
    "iso:country":"IT",
    "sg:address":"31038 Paese",
    "sg:city":"Castagnole",
    "sg:orig_category":"Estetiste",
    "sg:phone":"+39 0422 450592",
    "sg:postcode":"31038",
    "sg:province":"Treviso",
    "wof:name":"L'estrosita' Di Donella",
    "wof:placetype":"venue"
},
  "geometry": {"coordinates":[12.179534,45.69104],"type":"Point"}
}