{
  "type": "Feature",
  "properties": {
    "iso:country":"IT",
    "sg:address":"23807 Merate",
    "sg:city":"Merate",
    "sg:orig_category":"Macchine E Forniture Per Ecologia E Smaltimento Rifiuti",
    "sg:phone":"+39 039 990 7691",
    "sg:postcode":"23807",
    "sg:province":"Lecco",
    "wof:name":"Polymec S.r.l.",
    "wof:placetype":"venue"
},
  "geometry": {"coordinates":[9.415016,45.70211],"type":"Point"}
}