{
  "type": "Feature",
  "properties": {
    "iso:country":"IT",
    "sg:address":"47838 Riccione",
    "sg:city":"Riccione",
    "sg:orig_category":"Imprese Pulizia",
    "sg:phone":"+39 0541 648156",
    "sg:postcode":"47838",
    "sg:province":"Rimini",
    "wof:name":"Tecnosistem Sdf",
    "wof:placetype":"venue"
},
  "geometry": {"coordinates":[12.638599,44.006893],"type":"Point"}
}