{
  "type": "Feature",
  "properties": {
    "iso:country":"IT",
    "sg:address":"Via Della Repubblica, 50; Imperia; 18100",
    "sg:city":"Imperia",
    "sg:classifiers":[
        {
            "category":"Banks & Credit Unions",
            "subcategory":"Bank",
            "type":"Services"
        }
    ],
    "sg:phone":"+39 0183 275221",
    "sg:postcode":"18100",
    "sg:province":"Imperia",
    "wof:name":"Banca Nazionale Del Lavoro",
    "wof:placetype":"venue"
},
  "geometry": {"coordinates":[8.036235,43.890354],"type":"Point"}
}