{
  "type": "Feature",
  "properties": {
    "iso:country":"IT",
    "sg:address":"5, Via Gamberini Pietro 40133 Bologna",
    "sg:city":"Bologna",
    "sg:classifiers":[
        {
            "category":"Manufacturing",
            "subcategory":"Wood Products",
            "type":"Manufacturing & Wholesale Goods"
        }
    ],
    "sg:phone":"+39 39051560402",
    "sg:postcode":"40133",
    "sg:province":"Bologna",
    "sg:tags":[
        "furniture"
    ],
    "wof:name":"Brumag Di Bruni E Magagnoli (s.n.c.)",
    "wof:placetype":"venue"
},
  "geometry": {"coordinates":[11.292085,44.502544],"type":"Point"}
}