{
  "type": "Feature",
  "properties": {
    "addr:full":"2, Via Bellavista 23900 Lecco Lecco Lecco 23900",
    "addr:postcode":"23900;23900",
    "addr:street":"Via Bellavista",
    "iso:country":"IT",
    "sg:address":"2, Via Bellavista 23900 Lecco",
    "sg:city":"Lecco",
    "sg:classifiers":[
        {
            "category":"Professional",
            "subcategory":"Engineering",
            "type":"Services"
        }
    ],
    "sg:phone":"+39 0341 497171",
    "sg:postcode":"23900",
    "sg:province":"Lecco",
    "sg:tags":[
        "machine",
        "-",
        "mechanical"
    ],
    "wof:name":"F.i.p.a.fabbrica Italiana Punzoni Acciaio Snc",
    "wof:placetype":"venue"
},
  "geometry": {"coordinates":[9.408373,45.865295],"type":"Point"}
}