{
  "type": "Feature",
  "properties": {
    "iso:country":"IT",
    "sg:address":"98040 Torregrotta",
    "sg:city":"Torregrotta",
    "sg:orig_category":"Ospedali E Servizi Sanitari",
    "sg:phone":"+39 090 991 1740",
    "sg:postcode":"98040",
    "sg:province":"Messina",
    "wof:name":"Croce Amica Servizi Sanitari",
    "wof:placetype":"venue"
},
  "geometry": {"coordinates":[15.343857,38.210056],"type":"Point"}
}