{
  "type": "Feature",
  "properties": {
    "iso:country":"IT",
    "sg:address":"20123 Milano",
    "sg:city":"Milano",
    "sg:orig_category":"Studi E Consulenze Legali E Notarili. Avvocati, Notai E Servizi Legali. Professionisti - Studi E Servizi Ed Associazioni Di Interesse Aziendale",
    "sg:phone":"+39 02 498 6959",
    "sg:postcode":"20123",
    "sg:province":"Milano",
    "wof:name":"Caputo Nicola",
    "wof:placetype":"venue"
},
  "geometry": {"coordinates":[9.168266,45.471615],"type":"Point"}
}