{
  "type": "Feature",
  "properties": {
    "iso:country":"IT",
    "sg:address":"40128 Bologna",
    "sg:city":"Bologna",
    "sg:orig_category":"Prodotti E Manufatti In Materie Plastiche",
    "sg:phone":"+39 051 323122",
    "sg:postcode":"40128",
    "sg:province":"Bologna",
    "wof:name":"Plastotecnica Emiliana Sas",
    "wof:placetype":"venue"
},
  "geometry": {"coordinates":[11.359544754,44.5158920288],"type":"Point"}
}