{
  "type": "Feature",
  "properties": {
    "iso:country":"IT",
    "sg:address":"40, Via Della Repubblica 20015 Parabiago",
    "sg:city":"Parabiago",
    "sg:classifiers":[
        {
            "category":"Professional",
            "subcategory":"Engineering",
            "type":"Services"
        }
    ],
    "sg:phone":"+39 0331 495117",
    "sg:postcode":"20015",
    "sg:province":"Milano",
    "sg:tags":[
        "machine",
        "-",
        "mechanical"
    ],
    "wof:name":"Rancilio Macchine Per Caffe' (s.p.a.)",
    "wof:placetype":"venue"
},
  "geometry": {"coordinates":[8.947647,45.531883],"type":"Point"}
}