{
  "type": "Feature",
  "properties": {
    "iso:country":"IT",
    "sg:address":"20048 Carate Brianza",
    "sg:city":"Carate Brianza",
    "sg:orig_category":"Servizi E Lavori Per Abbigliamento E Pelletterie",
    "sg:phone":"+39 036 280 0116",
    "sg:postcode":"20048",
    "sg:province":"Milano",
    "wof:name":"Omniapiega Srl",
    "wof:placetype":"venue"
},
  "geometry": {"coordinates":[9.233266,45.675598],"type":"Point"}
}