{
  "type": "Feature",
  "properties": {
    "addr:full":"Via S. Teresa 1 20010 Bareggio Bareggio Milano 20010",
    "addr:housenumber":"1",
    "addr:postcode":"20010;20010",
    "addr:street":"Via S. Teresa",
    "iso:country":"IT",
    "sg:address":"Via S. Teresa 1 20010 Bareggio",
    "sg:city":"Bareggio",
    "sg:orig_category":"Process Plants For The Pharmaceutical Industry",
    "sg:phone":"+39 02 901 3157",
    "sg:postcode":"20010",
    "sg:province":"Milano",
    "sg:website":"www.acinoxa.com",
    "wof:name":"Acinoxa Srl",
    "wof:placetype":"venue"
},
  "geometry": {"coordinates":[9.0246582031,45.4971733093],"type":"Point"}
}