{
  "type": "Feature",
  "properties": {
    "iso:country":"IT",
    "sg:address":"Via Pitagora 23/a 35030 Rubano",
    "sg:city":"Rubano",
    "sg:classifiers":[
        {
            "category":"Government",
            "subcategory":"Department Of Motor Vehicles",
            "type":"Public Place"
        }
    ],
    "sg:phone":"+39 049 897 5644",
    "sg:postcode":"35030",
    "sg:province":"Padova",
    "sg:tags":[
        "industrial"
    ],
    "sg:website":"www.cami.it",
    "wof:name":"C.a.m.i. S.p.a.",
    "wof:placetype":"venue"
},
  "geometry": {"coordinates":[11.835972,45.418755],"type":"Point"}
}