{
  "type": "Feature",
  "properties": {
    "addr:full":"51, Viale Monza 20034 Giussano Giussano Milano 20034",
    "addr:housenumber":"51",
    "addr:postcode":"20034;20034",
    "addr:street":"Viale",
    "iso:country":"IT",
    "sg:address":"51, Viale Monza 20034 Giussano",
    "sg:city":"Giussano",
    "sg:classifiers":[
        {
            "category":"Professional",
            "subcategory":"Printing & Photocopies",
            "type":"Services"
        }
    ],
    "sg:phone":"+39 036 285 1354",
    "sg:postcode":"20034",
    "sg:province":"Milano",
    "wof:name":"Grafiche Boffi (s.r.l.)",
    "wof:placetype":"venue"
},
  "geometry": {"coordinates":[9.2206716537,45.693561554],"type":"Point"}
}