{
  "type": "Feature",
  "properties": {
    "addr:full":"Via Del Progresso, Sn 61030 Calcinelli Calcinelli Pesaro E Urbino 61030",
    "addr:housenumber":"sn",
    "addr:postcode":"61030;61030",
    "addr:street":"Via Del Progresso",
    "iso:country":"IT",
    "sg:address":"Via Del Progresso, Sn 61030 Calcinelli",
    "sg:city":"Calcinelli",
    "sg:classifiers":[
        {
            "category":"Professional",
            "subcategory":"Printing & Photocopies",
            "type":"Services"
        }
    ],
    "sg:phone":"+39 0721 894032",
    "sg:postcode":"61030",
    "sg:province":"Pesaro E Urbino",
    "sg:tags":[
        "embroidery"
    ],
    "sg:website":"www.forzagiovane.com",
    "wof:name":"Forza Giovane Uno Di Vitalini Piergiovanni & C. Snc",
    "wof:placetype":"venue"
},
  "geometry": {"coordinates":[12.529803,43.633556],"type":"Point"}
}