{
  "type": "Feature",
  "properties": {
    "iso:country":"IT",
    "sg:address":"89125 Reggio Calabria",
    "sg:classifiers":[
        {
            "category":"Banks & Credit Unions",
            "subcategory":"Investment Brokerage",
            "type":"Services"
        }
    ],
    "sg:phone":"+39 0965 814585",
    "sg:province":"RC",
    "sg:tags":[
        "houseware",
        "good",
        "leather",
        "utensil",
        "skins",
        "footwear",
        "kitchen"
    ],
    "wof:name":"Il Cuoio Di Bella Giuseppe",
    "wof:placetype":"venue"
},
  "geometry": {"coordinates":[15.6478509903,38.1101264954],"type":"Point"}
}