{
  "type": "Feature",
  "properties": {
    "addr:full":"Via Treggiaia, 16/18 51030 Serravalle Pistoiese Serravalle Pistoiese Pistoia 51030",
    "addr:housenumber":"16 / 18",
    "addr:postcode":"51030;51030",
    "addr:street":"Via Treggiaia",
    "iso:country":"IT",
    "sg:address":"Via Treggiaia, 16/18 51030 Serravalle Pistoiese",
    "sg:city":"Serravalle Pistoiese",
    "sg:orig_category":"Soles, Heels",
    "sg:phone":"+39 0573 51476",
    "sg:postcode":"51030",
    "sg:province":"Pistoia",
    "wof:name":"Bijou - Srl",
    "wof:placetype":"venue"
},
  "geometry": {"coordinates":[10.824563,43.896336],"type":"Point"}
}