{
  "type": "Feature",
  "properties": {
    "iso:country":"IT",
    "sg:address":"Via Garibaldi 7; Cortemaggiore",
    "sg:classifiers":[
        {
            "category":"Banks & Credit Unions",
            "subcategory":"Bank",
            "type":"Services"
        }
    ],
    "sg:phone":"+39 0523 839326",
    "wof:name":"Banca Popolare Di Cremona Scarl",
    "wof:placetype":"venue"
},
  "geometry": {"coordinates":[9.932479,44.995762],"type":"Point"}
}