{
  "type": "Feature",
  "properties": {
    "iso:country":"IT",
    "sg:address":"00134 Roma",
    "sg:city":"Roma",
    "sg:orig_category":"Impiantistica E Prodotti Tecnologici Per Edilizia. Elettrotecnica Professionale E Di Consumo. Telecomunicazioni E Telefonia, Impianti, Apparecchi E Servizi",
    "sg:phone":"+39 06 7135 5510",
    "sg:postcode":"00134",
    "sg:province":"Roma",
    "wof:name":"Pro Car Service Srl",
    "wof:placetype":"venue"
},
  "geometry": {"coordinates":[12.523749,41.814159],"type":"Point"}
}