{
  "type": "Feature",
  "properties": {
    "iso:country":"IT",
    "sg:address":"2, Via Torino 36063 Marostica",
    "sg:city":"Marostica",
    "sg:classifiers":[
        {
            "category":"Retail",
            "subcategory":"Animal Services",
            "type":"Services"
        }
    ],
    "sg:phone":"+39 0424 470311",
    "sg:postcode":"36063",
    "sg:province":"Vicenza",
    "sg:tags":[
        "breeding"
    ],
    "wof:name":"Tecno - Lab Srl.",
    "wof:placetype":"venue"
},
  "geometry": {"coordinates":[11.749422,45.787926],"type":"Point"}
}