{
  "type": "Feature",
  "properties": {
    "iso:country":"IT",
    "sg:address":"00178 Roma",
    "sg:city":"Roma",
    "sg:orig_category":"Macchine, Impianti Ed Attrezzature Per Agricoltura E Zootecnia",
    "sg:phone":"+39 06 718 5380",
    "sg:postcode":"00178",
    "sg:province":"Roma",
    "wof:name":"Agrigest Srl",
    "wof:placetype":"venue"
},
  "geometry": {"coordinates":[12.578022,41.80909],"type":"Point"}
}