{
  "type": "Feature",
  "properties": {
    "addr:full":"Via Colombera 27 21048 Solbiate Arno Solbiate Arno Varese 21048",
    "addr:housenumber":"27;arno",
    "addr:postcode":"21048;21048",
    "addr:street":"Via Colombera",
    "iso:country":"IT",
    "sg:address":"Via Colombera 27 21048 Solbiate Arno",
    "sg:city":"Solbiate Arno",
    "sg:classifiers":[
        {
            "category":"Shopping",
            "subcategory":"Crafts & Fabrics",
            "type":"Retail Goods"
        }
    ],
    "sg:phone":"+39 0331 989411",
    "sg:postcode":"21048",
    "sg:province":"Varese",
    "sg:tags":[
        "jersey"
    ],
    "sg:website":"www.mabujersey.it",
    "wof:name":"Mabu Jersey Spa",
    "wof:placetype":"venue"
},
  "geometry": {"coordinates":[8.822779,45.713795],"type":"Point"}
}