{
  "type": "Feature",
  "properties": {
    "iso:country":"IT",
    "sg:address":"Via Lino Zanussi 7 33033 Codroipo",
    "sg:city":"Codroipo",
    "sg:classifiers":[
        {
            "category":"Food & Beverages",
            "subcategory":"Ethnic Foods",
            "type":"Retail Goods"
        }
    ],
    "sg:phone":"+39 0432 907166",
    "sg:postcode":"33033",
    "sg:province":"Udine",
    "sg:tags":[
        "equipment",
        "pizzeria"
    ],
    "sg:website":"www.lillycodroipo.com",
    "wof:name":"Lilly Codroipo Srl",
    "wof:placetype":"venue"
},
  "geometry": {"coordinates":[13.2307243347,46.0649414062],"type":"Point"}
}