{
  "type": "Feature",
  "properties": {
    "addr:full":"Piazza Matteotti 2; Tavarnella Val Di Pesa; 50028 Firenze 50028",
    "addr:housenumber":"2",
    "addr:postcode":"50028;50028",
    "addr:street":"Piazza Matteotti;Val",
    "iso:country":"IT",
    "sg:address":"Piazza Matteotti 2; Tavarnella Val Di Pesa; 50028",
    "sg:classifiers":[
        {
            "category":"Banks & Credit Unions",
            "subcategory":"Bank",
            "type":"Services"
        }
    ],
    "sg:phone":"+39 055 807 7005",
    "sg:postcode":"50028",
    "sg:province":"Firenze",
    "wof:name":"Banca Toscana Spa",
    "wof:placetype":"venue"
},
  "geometry": {"coordinates":[11.173265,43.561428],"type":"Point"}
}