{
  "type": "Feature",
  "properties": {
    "addr:full":"25018 Montichiari Montichiari Brescia 25018",
    "addr:postcode":"25018;25018",
    "iso:country":"IT",
    "sg:address":"25018 Montichiari",
    "sg:city":"Montichiari",
    "sg:orig_category":"Macchine, Impianti E Forniture Per Industria Grafica, Cartaria E Cartotecnica",
    "sg:phone":"+39 030 996 2245",
    "sg:postcode":"25018",
    "sg:province":"Brescia",
    "wof:name":"Imas Grafica Srl",
    "wof:placetype":"venue"
},
  "geometry": {"coordinates":[10.367213,45.413536],"type":"Point"}
}