{
  "type": "Feature",
  "properties": {
    "iso:country":"IT",
    "sg:address":"20083 Gaggiano",
    "sg:city":"Gaggiano",
    "sg:orig_category":"Non-classified Establishments",
    "sg:phone":"+39 02 9084 3072",
    "sg:postcode":"20083",
    "sg:province":"Milano",
    "wof:name":"Ma.pa Srl",
    "wof:placetype":"venue"
},
  "geometry": {"coordinates":[9.033511,45.382324],"type":"Point"}
}