{
  "type": "Feature",
  "properties": {
    "iso:country":"IT",
    "sg:address":"1/a, Zona Asi 70056 Molfetta",
    "sg:city":"Molfetta",
    "sg:classifiers":[
        {
            "category":"Professional",
            "subcategory":"Engineering",
            "type":"Services"
        }
    ],
    "sg:phone":"+39 080 338 5870",
    "sg:postcode":"70056",
    "sg:province":"Bari",
    "sg:tags":[
        "machine",
        "-",
        "mechanical"
    ],
    "wof:name":"Co.me.s Sas Di M. Piumelli & C.",
    "wof:placetype":"venue"
},
  "geometry": {"coordinates":[16.869291,41.126053],"type":"Point"}
}