{
  "type": "Feature",
  "properties": {
    "iso:country":"IT",
    "sg:address":"Via Pisano Antonio 67 37131 Verona",
    "sg:city":"Verona",
    "sg:classifiers":[
        {
            "category":"Professional",
            "subcategory":"Art Services",
            "type":"Services"
        }
    ],
    "sg:phone":"+39 045 840 0500",
    "sg:postcode":"37131",
    "sg:province":"Verona",
    "sg:tags":[
        "artistic",
        "glazings"
    ],
    "wof:name":"Arte Stella Snc",
    "wof:placetype":"venue"
},
  "geometry": {"coordinates":[10.991748,45.438366],"type":"Point"}
}