{
  "type": "Feature",
  "properties": {
    "iso:country":"IT",
    "sg:address":"42100 Reggio Emilia",
    "sg:orig_category":"Cartotecnica E Servizi. Articoli Per Imballaggio E Confezionamento",
    "sg:phone":"+39 0522 303040",
    "sg:postcode":"42100",
    "sg:province":"Reggio Nell'Emilia",
    "wof:name":"Eurosei Reggiani Spa",
    "wof:placetype":"venue"
},
  "geometry": {"coordinates":[10.613946,44.712452],"type":"Point"}
}