{
  "type": "Feature",
  "properties": {
    "iso:country":"IT",
    "sg:address":"40033 Casalecchio Di Reno",
    "sg:city":"Casalecchio di Reno",
    "sg:orig_category":"Avvocati - Studi",
    "sg:phone":"+39 051 593793",
    "sg:postcode":"40033",
    "sg:province":"Bologna",
    "wof:name":"Studio Legale Avv. Angelo Forni",
    "wof:placetype":"venue"
},
  "geometry": {"coordinates":[11.266981,44.465843],"type":"Point"}
}