{
  "type": "Feature",
  "properties": {
    "addr:full":"23900 Lecco Lecco Lecco 23900",
    "addr:postcode":"23900;23900",
    "iso:country":"IT",
    "sg:address":"23900 Lecco",
    "sg:city":"Lecco",
    "sg:orig_category":"Prodotti Finiti Stampati. Shopping. Regalistica Aziendale",
    "sg:phone":"+39 0341 364066",
    "sg:postcode":"23900",
    "sg:province":"Lecco",
    "wof:name":"Bel-ami Di Nava Raffaella",
    "wof:placetype":"venue"
},
  "geometry": {"coordinates":[9.3899650574,45.8556251526],"type":"Point"}
}