{
  "type": "Feature",
  "properties": {
    "addr:full":"80013 Casalnuovo Di Napoli Casalnuovo di Napoli Napoli 80013",
    "addr:postcode":"80013;80013",
    "iso:country":"IT",
    "sg:address":"80013 Casalnuovo Di Napoli",
    "sg:city":"Casalnuovo di Napoli",
    "sg:orig_category":"Prodotti E Manufatti In Materie Plastiche",
    "sg:phone":"+39 081 842 4170",
    "sg:postcode":"80013",
    "sg:province":"Napoli",
    "wof:name":"Complastic Snc Di D'alise Gennaro & C.",
    "wof:placetype":"venue"
},
  "geometry": {"coordinates":[14.351064682,40.9160614014],"type":"Point"}
}