{
  "type": "Feature",
  "properties": {
    "addr:full":"20144 Milano Milano Milano 20144",
    "addr:postcode":"20144;20144",
    "iso:country":"IT",
    "sg:address":"20144 Milano",
    "sg:city":"Milano",
    "sg:orig_category":"Cartotecnica E Servizi. Forniture Per Uffici",
    "sg:phone":"+39 02 839 4566",
    "sg:postcode":"20144",
    "sg:province":"Milano",
    "wof:name":"Cantisano Rita",
    "wof:placetype":"venue"
},
  "geometry": {"coordinates":[9.167865,45.454361],"type":"Point"}
}