{
  "type": "Feature",
  "properties": {
    "iso:country":"IT",
    "sg:address":"Via Cavour 34 36040 Brendola",
    "sg:city":"Brendola",
    "sg:classifiers":[
        {
            "category":"Autos & Motor Vehicles",
            "subcategory":"Fuel & Gas Station",
            "type":"Retail Goods"
        }
    ],
    "sg:phone":"+39 0444 401150",
    "sg:postcode":"36040",
    "sg:province":"Vicenza",
    "sg:tags":[
        "petrol",
        "tank"
    ],
    "sg:website":"www.tts.it",
    "wof:name":"T.t.s. Srl",
    "wof:placetype":"venue"
},
  "geometry": {"coordinates":[11.4571437836,45.5080490112],"type":"Point"}
}