{
  "type": "Feature",
  "properties": {
    "iso:country":"IT",
    "sg:address":"22030 Orsenigo",
    "sg:city":"Orsenigo",
    "sg:orig_category":"Carta, Cartone E Prodotti Primari. Forniture E Materiali Per Imballaggio E Confezionamento",
    "sg:phone":"+39 031 630557",
    "sg:postcode":"22030",
    "sg:province":"Como",
    "wof:name":"Roncoroni Spa",
    "wof:placetype":"venue"
},
  "geometry": {"coordinates":[9.152963,45.798904],"type":"Point"}
}