{
  "type": "Feature",
  "properties": {
    "iso:country":"IT",
    "sg:address":"Corso Bergamo 40 23900 Lecco",
    "sg:city":"Lecco",
    "sg:classifiers":[
        {
            "category":"Home & Garden",
            "subcategory":"Building Materials",
            "type":"Retail Goods"
        }
    ],
    "sg:phone":"+39 0341 420056",
    "sg:postcode":"23900",
    "sg:province":"Lecco",
    "sg:tags":[
        "hinge"
    ],
    "sg:website":"www.aldeghi.com",
    "wof:name":"Luigi Aldeghi Spa",
    "wof:placetype":"venue"
},
  "geometry": {"coordinates":[9.417136,45.82729],"type":"Point"}
}