{
  "type": "Feature",
  "properties": {
    "iso:country":"IT",
    "sg:address":"Via Milano 47 28803 Premosello Chiovenda",
    "sg:classifiers":[
        {
            "category":"Home & Garden",
            "subcategory":"Building Materials",
            "type":"Retail Goods"
        }
    ],
    "sg:phone":"+39 0324 88781",
    "sg:postcode":"28803",
    "sg:province":"Verbano-Cusio-Ossola",
    "sg:tags":[
        "slab",
        "marble"
    ],
    "sg:website":"www.italgranit.com",
    "wof:name":"Italgranit Srl",
    "wof:placetype":"venue"
},
  "geometry": {"coordinates":[8.336092,46.001335],"type":"Point"}
}