{
  "type": "Feature",
  "properties": {
    "iso:country":"IT",
    "sg:address":"24040 Stezzano",
    "sg:city":"Stezzano",
    "sg:orig_category":"Alberghi E Strutture Extra Alberghiere",
    "sg:phone":"+39 035 454 1050",
    "sg:postcode":"24040",
    "sg:province":"Bergamo",
    "sg:website":"http://www.hotelpegaso.it",
    "wof:name":"Pegaso Hotel",
    "wof:placetype":"venue"
},
  "geometry": {"coordinates":[9.6307,45.650021],"type":"Point"}
}