{
  "type": "Feature",
  "properties": {
    "iso:country":"IT",
    "sg:address":"29, Via Carabelli 21041 Albizzate",
    "sg:city":"Albizzate",
    "sg:classifiers":[
        {
            "category":"Professional",
            "subcategory":"Engineering",
            "type":"Services"
        }
    ],
    "sg:phone":"+39 0331 990015",
    "sg:postcode":"21041",
    "sg:province":"Varese",
    "sg:tags":[
        "machine",
        "-",
        "mechanical"
    ],
    "wof:name":"T.m.s. Srl Tecnologie Meccaniche Servizi",
    "wof:placetype":"venue"
},
  "geometry": {"coordinates":[8.79741,45.727928],"type":"Point"}
}