{
  "type": "Feature",
  "properties": {
    "addr:full":"5, Via Petos 24010 Ponteranica Ponteranica Bergamo 24010",
    "addr:postcode":"24010;24010",
    "addr:street":"Via Petos",
    "iso:country":"IT",
    "sg:address":"5, Via Petos 24010 Ponteranica",
    "sg:city":"Ponteranica",
    "sg:classifiers":[
        {
            "category":"Manufacturing",
            "subcategory":"Lumber",
            "type":"Manufacturing & Wholesale Goods"
        }
    ],
    "sg:phone":"+39 035 412 8272",
    "sg:postcode":"24010",
    "sg:province":"Bergamo",
    "sg:tags":[
        "wood"
    ],
    "wof:name":"Carminati Ferramenti S.n.c.",
    "wof:placetype":"venue"
},
  "geometry": {"coordinates":[9.646614,45.730194],"type":"Point"}
}