{
  "type": "Feature",
  "properties": {
    "iso:country":"IT",
    "sg:address":"08028 Orosei",
    "sg:city":"Orosei",
    "sg:orig_category":"Imprese Di Costruzioni Civili Ed Industriali",
    "sg:phone":"+39 0784 998350",
    "sg:postcode":"08028",
    "sg:province":"Nuoro",
    "wof:name":"Tre C",
    "wof:placetype":"venue"
},
  "geometry": {"coordinates":[9.712121,40.398346],"type":"Point"}
}