{
  "type": "Feature",
  "properties": {
    "iso:country":"IT",
    "sg:address":"30030 Mestre",
    "sg:orig_category":"Legno E Semilavorati",
    "sg:phone":"+39 041 630850",
    "sg:postcode":"30030",
    "sg:province":"Venezia",
    "wof:name":"De Lazzari Gianni",
    "wof:placetype":"venue"
},
  "geometry": {"coordinates":[12.284652,45.501152],"type":"Point"}
}