{
  "type": "Feature",
  "properties": {
    "addr:full":"20124 Milano Milano Milano 20124",
    "addr:postcode":"20124;20124",
    "iso:country":"IT",
    "sg:address":"20124 Milano",
    "sg:city":"Milano",
    "sg:orig_category":"Pubblicita', Marketing E Comunicazione",
    "sg:phone":"+39 02 204 9114",
    "sg:postcode":"20124",
    "sg:province":"Milano",
    "sg:website":"http://www.nightfashion.it",
    "wof:name":"Night Fashion",
    "wof:placetype":"venue"
},
  "geometry": {"coordinates":[9.2141504288,45.484085083],"type":"Point"}
}