{
  "type": "Feature",
  "properties": {
    "addr:full":"54100 Massa Massa Massa-Carrara 54100",
    "addr:postcode":"54100;54100",
    "iso:country":"IT",
    "sg:address":"54100 Massa",
    "sg:city":"Massa",
    "sg:orig_category":"Materassi - Produzione E Ingrosso",
    "sg:phone":"+39 0585 250225",
    "sg:postcode":"54100",
    "sg:province":"Massa-Carrara",
    "wof:name":"Il Centro Del Materasso Di Leoni Sauro",
    "wof:placetype":"venue"
},
  "geometry": {"coordinates":[10.111387,44.029316],"type":"Point"}
}