{
  "type": "Feature",
  "properties": {
    "iso:country":"IT",
    "sg:address":"Via Rovigo 1 35010 Vigonza",
    "sg:city":"Vigonza",
    "sg:orig_category":"Waste Containers, Waste Baskets",
    "sg:phone":"+39 049 899 3311",
    "sg:postcode":"35010",
    "sg:province":"Padova",
    "sg:website":"www.polander.it",
    "wof:name":"Plastic Omnium Lander Spa",
    "wof:placetype":"venue"
},
  "geometry": {"coordinates":[11.969546,45.424374],"type":"Point"}
}