{
  "type": "Feature",
  "properties": {
    "iso:country":"IT",
    "sg:address":"36043 Camisano Vicentino",
    "sg:city":"Camisano Vicentino",
    "sg:orig_category":"Gioielleria, Oreficeria E Argenteria",
    "sg:phone":"+39 0444 411038",
    "sg:postcode":"36043",
    "sg:province":"Vicenza",
    "wof:name":"Pertegato Snc",
    "wof:placetype":"venue"
},
  "geometry": {"coordinates":[11.695421,45.515705],"type":"Point"}
}