{
  "type": "Feature",
  "properties": {
    "iso:country":"IT",
    "sg:address":"48022 Lugo",
    "sg:city":"Lugo",
    "sg:orig_category":"Materie Plastiche - Produzione E Lavorazione",
    "sg:phone":"+39 0545 23342",
    "sg:postcode":"48022",
    "sg:province":"Ravenna",
    "sg:website":"http://www.ipm-lugo.it",
    "wof:name":"Ipm Di Argnani Claudio & C. Snc",
    "wof:placetype":"venue"
},
  "geometry": {"coordinates":[11.887582,44.436069],"type":"Point"}
}