{
  "type": "Feature",
  "properties": {
    "iso:country":"IT",
    "sg:address":"2, Piazza Della Stazione 56125 Pisa",
    "sg:city":"Pisa",
    "sg:classifiers":[
        {
            "category":"Travel",
            "subcategory":"Travel Agent",
            "type":"Entertainment"
        }
    ],
    "sg:phone":"+39 390 504 3290",
    "sg:postcode":"56125",
    "sg:province":"Pisa",
    "sg:tags":[
        "business"
    ],
    "wof:name":"Albergo Jolly Hotel Cavalieri",
    "wof:placetype":"venue"
},
  "geometry": {"coordinates":[10.398827,43.708939],"type":"Point"}
}