{
  "type": "Feature",
  "properties": {
    "iso:country":"IT",
    "sg:address":"59, Localita' San Sebastiano 12065 Monforte D'alba",
    "sg:classifiers":[
        {
            "category":"Food & Beverages",
            "subcategory":"Groceries & Convenience Stores",
            "type":"Retail Goods"
        }
    ],
    "sg:phone":"+39 39017378340",
    "sg:postcode":"12065",
    "sg:province":"Cuneo",
    "sg:tags":[
        "product",
        "related"
    ],
    "wof:name":"Azienda Agricola Pira Di Giada Due S.r.l.",
    "wof:placetype":"venue"
},
  "geometry": {"coordinates":[7.9637126923,44.5633811951],"type":"Point"}
}