{
  "type": "Feature",
  "properties": {
    "iso:country":"IT",
    "sg:address":"20123 Milano",
    "sg:city":"Milano",
    "sg:orig_category":"Professionisti - Studi E Servizi Ed Associazioni Di Interesse Aziendale. Associazioni Ed Organismi Di Interesse Pubblico",
    "sg:phone":"+39 02 865387",
    "sg:postcode":"20123",
    "sg:province":"Milano",
    "wof:name":"Biofeedback Association Of Europe",
    "wof:placetype":"venue"
},
  "geometry": {"coordinates":[9.1842269897,45.4618988037],"type":"Point"}
}