{
  "type": "Feature",
  "properties": {
    "iso:country":"IT",
    "sg:address":"28028 Pettenasco",
    "sg:city":"Pettenasco",
    "sg:orig_category":"Minuterie Metalliche E Ferramenta",
    "sg:phone":"+39 0323 89694",
    "sg:postcode":"28028",
    "sg:province":"Novara",
    "sg:website":"http://www.laris.it",
    "wof:name":"Laris Srl",
    "wof:placetype":"venue"
},
  "geometry": {"coordinates":[8.4049043655,45.8187332153],"type":"Point"}
}