{
  "type": "Feature",
  "properties": {
    "addr:full":"00012 Guidonia Montecelio Guidonia Roma 00012",
    "addr:postcode":"00012;00012",
    "iso:country":"IT",
    "sg:address":"00012 Guidonia Montecelio",
    "sg:city":"Guidonia",
    "sg:orig_category":"Prodotti Chimici Secondari",
    "sg:phone":"+39 0774 325475",
    "sg:postcode":"00012",
    "sg:province":"Roma",
    "wof:name":"Santabarbara Srl",
    "wof:placetype":"venue"
},
  "geometry": {"coordinates":[12.7664480209,41.9817810059],"type":"Point"}
}