{
  "type": "Feature",
  "properties": {
    "iso:country":"IT",
    "sg:address":"20021 Bollate",
    "sg:city":"Bollate",
    "sg:orig_category":"Ospedali E Servizi Sanitari. Pubblica Amministrazione. Servizi Sociali",
    "sg:phone":"+39 02 351 3186",
    "sg:postcode":"20021",
    "sg:province":"Milano",
    "wof:name":"Azienda Sanitaria Locale Provincia Milano 1",
    "wof:placetype":"venue"
},
  "geometry": {"coordinates":[9.140599,45.554424],"type":"Point"}
}