{
  "type": "Feature",
  "properties": {
    "addr:full":"41012 Carpi Carpi Modena 41012",
    "addr:postcode":"41012;41012",
    "iso:country":"IT",
    "sg:address":"41012 Carpi",
    "sg:city":"Carpi",
    "sg:orig_category":"Articoli Per Imballaggio E Confezionamento. Forniture Per Uffici. Forniture Per Attivita' Commerciali Ed Artigianali",
    "sg:phone":"+39 059 653057",
    "sg:postcode":"41012",
    "sg:province":"Modena",
    "wof:name":"Pavarotti Fashion Packaging Srl",
    "wof:placetype":"venue"
},
  "geometry": {"coordinates":[10.892314,44.797165],"type":"Point"}
}