{
  "type": "Feature",
  "properties": {
    "addr:full":"24038 Sant'omobono Imagna Bergamo 24038",
    "addr:postcode":"24038;24038",
    "iso:country":"IT",
    "sg:address":"24038 Sant'omobono Imagna",
    "sg:orig_category":"Forniture Per Attivita' Commerciali Ed Artigianali. Pubblicita', Marketing E Comunicazione",
    "sg:phone":"+39 035 851085",
    "sg:postcode":"24038",
    "sg:province":"Bergamo",
    "sg:website":"http://www.mager.it",
    "wof:name":"Mager Fratelli Fermo E Gianfranco Snc",
    "wof:placetype":"venue"
},
  "geometry": {"coordinates":[9.5255937576,45.8068695068],"type":"Point"}
}