{
  "type": "Feature",
  "properties": {
    "iso:country":"IT",
    "sg:address":"Nuova Sda Consortile 83100 Avellino",
    "sg:city":"Avellino",
    "sg:classifiers":[
        {
            "category":"Manufacturing",
            "subcategory":"Motor Vehicles & Parts",
            "type":"Manufacturing & Wholesale Goods"
        }
    ],
    "sg:phone":"+39 0825 615411",
    "sg:postcode":"83100",
    "sg:province":"Avellino",
    "sg:tags":[
        "hinge",
        "automotive"
    ],
    "wof:name":"Lima Sud S.p.a.",
    "wof:placetype":"venue"
},
  "geometry": {"coordinates":[14.820302,40.921459],"type":"Point"}
}