{
  "type": "Feature",
  "properties": {
    "iso:country":"IT",
    "sg:address":"36031 Dueville",
    "sg:city":"Dueville",
    "sg:orig_category":"Climatizzazione E Condizionamento, Apparecchiature E Servizi",
    "sg:phone":"+39 0444 590627",
    "sg:postcode":"36031",
    "sg:province":"Vicenza",
    "wof:name":"Mogentale Luigi & C. Snc",
    "wof:placetype":"venue"
},
  "geometry": {"coordinates":[11.573977,45.634521],"type":"Point"}
}