{
  "type": "Feature",
  "properties": {
    "iso:country":"IT",
    "sg:address":"58100 Grosseto",
    "sg:city":"Grosseto",
    "sg:orig_category":"Indirizzi Commerciali",
    "sg:phone":"+39 0564 451033",
    "sg:postcode":"58100",
    "sg:province":"Grosseto",
    "wof:name":"Rossi Claro",
    "wof:placetype":"venue"
},
  "geometry": {"coordinates":[11.103816,42.776787],"type":"Point"}
}