{
  "type": "Feature",
  "properties": {
    "iso:country":"IT",
    "sg:address":"88022 Curinga",
    "sg:city":"Curinga",
    "sg:orig_category":"Agricoltura, Orticoltura E Floricoltura",
    "sg:phone":"+39 0968 78132",
    "sg:postcode":"88022",
    "sg:province":"Catanzaro",
    "wof:name":"Maioranna Salvatore",
    "wof:placetype":"venue"
},
  "geometry": {"coordinates":[16.287521,38.840355],"type":"Point"}
}