{
  "type": "Feature",
  "properties": {
    "iso:country":"IT",
    "sg:address":"80030 Cimitile",
    "sg:city":"Cimitile",
    "sg:orig_category":"Abbigliamento Esterno, Maglierie E Pelliccerie. Calzature, Pelletterie E Pelli. Shopping",
    "sg:phone":"+39 081 512 1017",
    "sg:postcode":"80030",
    "sg:province":"Napoli",
    "wof:name":"Pellicceria Antonella Sas",
    "wof:placetype":"venue"
},
  "geometry": {"coordinates":[14.526426,40.941574],"type":"Point"}
}