{
  "type": "Feature",
  "properties": {
    "iso:country":"IT",
    "sg:address":"1, Via Giovanni Pascoli 24050 Cortenuova",
    "sg:city":"Cortenuova",
    "sg:classifiers":[
        {
            "category":"Shopping",
            "type":"Retail Goods"
        }
    ],
    "sg:phone":"+39 036 399 2424",
    "sg:postcode":"24050",
    "sg:province":"Bergamo",
    "sg:tags":[
        "finished",
        "-",
        "metallic"
    ],
    "wof:name":"Rubini Sinterizzati (s.r.l.)",
    "wof:placetype":"venue"
},
  "geometry": {"coordinates":[9.830953598,45.5540657043],"type":"Point"}
}