{
  "type": "Feature",
  "properties": {
    "addr:full":"90146 Palermo Palermo Palermo 90146",
    "addr:postcode":"90146;90146",
    "iso:country":"IT",
    "sg:address":"90146 Palermo",
    "sg:city":"Palermo",
    "sg:orig_category":"Elettronica Professionale E Di Consumo. Musica",
    "sg:phone":"+39 091 670 9830",
    "sg:postcode":"90146",
    "sg:province":"Palermo",
    "wof:name":"Decibel Di Priolo Vito",
    "wof:placetype":"venue"
},
  "geometry": {"coordinates":[13.333124,38.151958],"type":"Point"}
}