{
  "type": "Feature",
  "properties": {
    "iso:country":"IT",
    "sg:address":"62014 Corridonia",
    "sg:city":"Corridonia",
    "sg:orig_category":"Borse E Borsette - Produzione E Ingrosso",
    "sg:phone":"+39 0733 432090",
    "sg:postcode":"62014",
    "sg:province":"Macerata",
    "sg:website":"http://www.giandaniel.com",
    "wof:name":"Borsettificio Iommi Maria Grazia",
    "wof:placetype":"venue"
},
  "geometry": {"coordinates":[13.513839,43.2505],"type":"Point"}
}