{
  "type": "Feature",
  "properties": {
    "iso:country":"IT",
    "sg:address":"Via Vergine De Mei 2/b 51030 Masiano",
    "sg:classifiers":[
        {
            "category":"Farming",
            "subcategory":"Nursery",
            "type":"Manufacturing & Wholesale Goods"
        }
    ],
    "sg:phone":"+39 0573 381008",
    "sg:postcode":"51030",
    "sg:province":"Pistoia",
    "sg:tags":[
        "tree",
        "seedling"
    ],
    "sg:website":"www.zen.it/cop",
    "wof:name":"Consorzio Ortovivaisti Pistoiesi Scrl",
    "wof:placetype":"venue"
},
  "geometry": {"coordinates":[10.918524,43.932156],"type":"Point"}
}