{
  "type": "Feature",
  "properties": {
    "iso:country":"IT",
    "sg:address":"24026 Leffe",
    "sg:city":"Leffe",
    "sg:orig_category":"Materassi - Vendita Al Dettaglio",
    "sg:phone":"+39 035 731468",
    "sg:postcode":"24026",
    "sg:province":"Bergamo",
    "wof:name":"Centro Moda Casa Di Adriana Pezzoli & C. Sas",
    "wof:placetype":"venue"
},
  "geometry": {"coordinates":[9.886574,45.801743],"type":"Point"}
}