{
  "type": "Feature",
  "properties": {
    "iso:country":"IT",
    "sg:address":"36100 Vicenza",
    "sg:city":"Vicenza",
    "sg:orig_category":"Forniture E Materiali Per Imballaggio E Confezionamento. Forniture Per Uffici. Forniture Per Attivita' Commerciali Ed Artigianali",
    "sg:phone":"+39 0444 928182",
    "sg:postcode":"36100",
    "sg:province":"Vicenza",
    "sg:website":"http://www.duo-tek.it",
    "wof:name":"Duo-tek Snc",
    "wof:placetype":"venue"
},
  "geometry": {"coordinates":[11.561044693,45.536190033],"type":"Point"}
}