{
  "type": "Feature",
  "properties": {
    "addr:full":"5, Via G.di Vittorio 40020 Casalfiumanese Casalfiumanese Bologna 40020",
    "addr:postcode":"40020;40020",
    "addr:street":"Via G.Di Vittorio",
    "iso:country":"IT",
    "sg:address":"5, Via G.di Vittorio 40020 Casalfiumanese",
    "sg:city":"Casalfiumanese",
    "sg:classifiers":[
        {
            "category":"Wholesale",
            "subcategory":"Medical Equipment & Supplies",
            "type":"Manufacturing & Wholesale Goods"
        }
    ],
    "sg:phone":"+39 0542 667066",
    "sg:postcode":"40020",
    "sg:province":"Bologna",
    "sg:tags":[
        "-",
        "health",
        "instrument"
    ],
    "wof:name":"Liarre (s.r.l.)",
    "wof:placetype":"venue"
},
  "geometry": {"coordinates":[11.346481,44.494221],"type":"Point"}
}