{
  "type": "Feature",
  "properties": {
    "iso:country":"IT",
    "sg:address":"30174 Venezia",
    "sg:city":"Venezia",
    "sg:classifiers":[
        {
            "category":"Health Services",
            "subcategory":"Health Practitioner",
            "type":"Services"
        }
    ],
    "sg:phone":"+39 041 534 7373",
    "sg:postcode":"30174",
    "sg:province":"Venezia",
    "sg:tags":[
        "medici"
    ],
    "wof:name":"Camilotti Edoardo",
    "wof:placetype":"venue"
},
  "geometry": {"coordinates":[12.970455,45.810093],"type":"Point"}
}