{
  "type": "Feature",
  "properties": {
    "iso:country":"IT",
    "sg:address":"10043 Orbassano",
    "sg:city":"Orbassano",
    "sg:orig_category":"Macchine Ed Impianti Per Edilizia E Lavori Pubblici",
    "sg:phone":"+39 011 901 1550",
    "sg:postcode":"10043",
    "sg:province":"Torino",
    "wof:name":"Vames Di Loparco & C. (s.n.c.)",
    "wof:placetype":"venue"
},
  "geometry": {"coordinates":[7.547873,45.008419],"type":"Point"}
}