{
  "type": "Feature",
  "properties": {
    "addr:full":"12060 Barolo Barolo Cuneo 12060",
    "addr:postcode":"12060;12060",
    "iso:country":"IT",
    "sg:address":"12060 Barolo",
    "sg:city":"Barolo",
    "sg:classifiers":[
        {
            "category":"Farming",
            "subcategory":"Berry Farm",
            "type":"Manufacturing & Wholesale Goods"
        }
    ],
    "sg:phone":"+39 0173 560016",
    "sg:postcode":"12060",
    "sg:province":"Cuneo",
    "sg:tags":[
        "vegetable",
        "growing",
        "flower",
        "agriculture"
    ],
    "wof:name":"Fenocchio",
    "wof:placetype":"venue"
},
  "geometry": {"coordinates":[7.551219,44.390526],"type":"Point"}
}