{
  "type": "Feature",
  "properties": {
    "iso:country":"IT",
    "sg:address":"10, Via Umberto I 90019 Trabia",
    "sg:city":"Trabia",
    "sg:classifiers":[
        {
            "category":"Banks & Credit Unions",
            "subcategory":"Bank",
            "type":"Services"
        }
    ],
    "sg:phone":"+39 091 814 6775",
    "sg:postcode":"90019",
    "sg:province":"Palermo",
    "sg:tags":[
        "banking",
        "institution"
    ],
    "wof:name":"Banca Di Credito Coop.g. Toniolo",
    "wof:placetype":"venue"
},
  "geometry": {"coordinates":[13.655222,37.995178],"type":"Point"}
}