{
  "type": "Feature",
  "properties": {
    "iso:country":"IT",
    "sg:address":"00156 Roma",
    "sg:city":"Roma",
    "sg:orig_category":"Servizi E Lavori Per Agricoltura E Zootecnia. Servizi E Lavori Per Ecologia E Smaltimento Rifiuti",
    "sg:phone":"+39 06 4121 9503",
    "sg:postcode":"00156",
    "sg:province":"Roma",
    "sg:website":"http://www.seuro.it",
    "wof:name":"Coop. Seuro",
    "wof:placetype":"venue"
},
  "geometry": {"coordinates":[12.59497,41.929478],"type":"Point"}
}