{
  "type": "Feature",
  "properties": {
    "iso:country":"IT",
    "sg:address":"84016 Pagani",
    "sg:city":"Pagani",
    "sg:orig_category":"Non-classified Establishments",
    "sg:phone":"+39 081 917758",
    "sg:postcode":"84016",
    "sg:province":"Salerno",
    "wof:name":"Bove Francesco",
    "wof:placetype":"venue"
},
  "geometry": {"coordinates":[14.607989,40.742435],"type":"Point"}
}