{
  "type": "Feature",
  "properties": {
    "addr:full":"20126 Milano Milano Milano 20126",
    "addr:postcode":"20126;20126",
    "iso:country":"IT",
    "sg:address":"20126 Milano",
    "sg:city":"Milano",
    "sg:orig_category":"Arredo Camera Letto E Complementi",
    "sg:phone":"+39 02 255 2910",
    "sg:postcode":"20126",
    "sg:province":"Milano",
    "wof:name":"Came Snc Di Caprotti Enrico & C.",
    "wof:placetype":"venue"
},
  "geometry": {"coordinates":[9.223515,45.50906],"type":"Point"}
}