{
  "type": "Feature",
  "properties": {
    "iso:country":"IT",
    "sg:address":"28100 Novara",
    "sg:city":"Novara",
    "sg:orig_category":"Impiantistica E Prodotti Tecnologici Per Edilizia",
    "sg:phone":"+39 0321 624726",
    "sg:postcode":"28100",
    "sg:province":"Novara",
    "wof:name":"Rivani Mauro",
    "wof:placetype":"venue"
},
  "geometry": {"coordinates":[8.600078,45.455307],"type":"Point"}
}