{
  "type": "Feature",
  "properties": {
    "addr:full":"31020 S. Polo Di Piave Treviso 31020",
    "addr:housenumber":"31020",
    "addr:postcode":"31020",
    "addr:street":"S. Polo Di Piave",
    "iso:country":"IT",
    "sg:address":"31020 S. Polo Di Piave",
    "sg:classifiers":[
        {
            "category":"Manufacturing",
            "subcategory":"Metals",
            "type":"Manufacturing & Wholesale Goods"
        }
    ],
    "sg:phone":"+39 0422 855576",
    "sg:postcode":"31020",
    "sg:province":"Treviso",
    "sg:tags":[
        "forming",
        "working",
        "welding"
    ],
    "sg:website":"http://www.",
    "wof:name":"Metalinox Srl",
    "wof:placetype":"venue"
},
  "geometry": {"coordinates":[12.2419157028,45.6336708069],"type":"Point"}
}