{
  "type": "Feature",
  "properties": {
    "iso:country":"IT",
    "sg:address":"20121 Milano",
    "sg:city":"Milano",
    "sg:orig_category":"Bevande, Vini E Liquori. Servizi E Lavori Per Industria Alimentare E Bevande",
    "sg:phone":"+39 02 8050 9300",
    "sg:postcode":"20121",
    "sg:province":"Milano",
    "wof:name":"Fratelli Branca Distillerie S.r.l.",
    "wof:placetype":"venue"
},
  "geometry": {"coordinates":[9.185545,45.468018],"type":"Point"}
}