{
  "type": "Feature",
  "properties": {
    "iso:country":"IT",
    "sg:address":"07020 Palau",
    "sg:city":"Palau",
    "sg:orig_category":"Scuole E Servizi Scolastici. Servizi Per Lo Sport E Il Tempo Libero",
    "sg:phone":"+39 0789 704016",
    "sg:postcode":"07020",
    "sg:province":"Olbia-Tempio",
    "wof:name":"J.s.t. Di Rosso-chioso Augusto & C. Snc",
    "wof:placetype":"venue"
},
  "geometry": {"coordinates":[9.325185,41.187908],"type":"Point"}
}