{
  "type": "Feature",
  "properties": {
    "iso:country":"IT",
    "sg:address":"50145 Firenze",
    "sg:city":"Firenze",
    "sg:orig_category":"Accessori Moda D'abbigliamento",
    "sg:phone":"+39 055 373274",
    "sg:postcode":"50145",
    "sg:province":"Firenze",
    "wof:name":"Marpunto Pelletterie Srl",
    "wof:placetype":"venue"
},
  "geometry": {"coordinates":[10.747909,43.860737],"type":"Point"}
}