{
  "type": "Feature",
  "properties": {
    "iso:country":"IT",
    "sg:address":"25027 Quinzano D'oglio",
    "sg:orig_category":"Lavorazioni Meccaniche E Servizi",
    "sg:phone":"+39 030 992 4344",
    "sg:postcode":"25027",
    "sg:province":"Brescia",
    "wof:name":"Fem Di Bassani Fausto & C. Snc",
    "wof:placetype":"venue"
},
  "geometry": {"coordinates":[10.01727,45.319672],"type":"Point"}
}