{
  "type": "Feature",
  "properties": {
    "iso:country":"IT",
    "sg:address":"41019 Soliera",
    "sg:city":"Soliera",
    "sg:orig_category":"Servizi E Lavori Per Edilizia E Lavori Pubblici. Servizi Ausiliari Di Sorveglianza, Manutenzione E Pulizia",
    "sg:phone":"+39 059 857 0152",
    "sg:postcode":"41019",
    "sg:province":"Modena",
    "wof:name":"P.r. Coperture Snc",
    "wof:placetype":"venue"
},
  "geometry": {"coordinates":[10.909117,44.726856],"type":"Point"}
}