{
  "type": "Feature",
  "properties": {
    "iso:country":"IT",
    "sg:address":"88100 Catanzaro",
    "sg:city":"Catanzaro",
    "sg:orig_category":"Prodotti Alimentari",
    "sg:phone":"+39 0961 61031",
    "sg:postcode":"88100",
    "sg:province":"Catanzaro",
    "wof:name":"F.lli Poerio S.r.l.",
    "wof:placetype":"venue"
},
  "geometry": {"coordinates":[16.604095459,38.867729187],"type":"Point"}
}