{
  "type": "Feature",
  "properties": {
    "addr:full":"Via Giulio Locatelli 22 33050 Pocenia Pocenia Udine 33050",
    "addr:housenumber":"22",
    "addr:postcode":"33050;33050",
    "addr:street":"Via Giulio Locatelli",
    "iso:country":"IT",
    "sg:address":"Via Giulio Locatelli 22 33050 Pocenia",
    "sg:city":"Pocenia",
    "sg:classifiers":[
        {
            "category":"Building & Trades",
            "subcategory":"Construction",
            "type":"Services"
        }
    ],
    "sg:phone":"+39 0432 772001",
    "sg:postcode":"33050",
    "sg:province":"Udine",
    "sg:tags":[
        "heat",
        "exchanger"
    ],
    "sg:website":"www.ecogroup.com",
    "wof:name":"Eco Spa",
    "wof:placetype":"venue"
},
  "geometry": {"coordinates":[13.106351,45.831848],"type":"Point"}
}