{
  "type": "Feature",
  "properties": {
    "iso:country":"IT",
    "sg:address":"Viale Del Lavoro 54 37135 Verona",
    "sg:city":"Verona",
    "sg:classifiers":[
        {
            "category":"Food & Beverages",
            "subcategory":"Fruits & Vegetables",
            "type":"Retail Goods"
        }
    ],
    "sg:phone":"+39 045 878 0177",
    "sg:postcode":"37135",
    "sg:province":"Verona",
    "sg:website":"www.bragantini.it",
    "wof:name":"Bragantini Marco & Figli G. D. Snc",
    "wof:placetype":"venue"
},
  "geometry": {"coordinates":[10.9773101807,45.4097213745],"type":"Point"}
}