{
  "type": "Feature",
  "properties": {
    "addr:full":"139, Viale Spagna 20093 Cologno Monzese Cologno Monzese Milano 20093",
    "addr:postcode":"20093;20093",
    "addr:street":"Viale Spagna",
    "iso:country":"IT",
    "sg:address":"139, Viale Spagna 20093 Cologno Monzese",
    "sg:city":"Cologno Monzese",
    "sg:classifiers":[
        {
            "category":"Manufacturing",
            "subcategory":"Rubber & Plastics",
            "type":"Manufacturing & Wholesale Goods"
        }
    ],
    "sg:phone":"+39 39022532539",
    "sg:postcode":"20093",
    "sg:province":"Milano",
    "wof:name":"Niagara Giocattoli (s.p.a.)",
    "wof:placetype":"venue"
},
  "geometry": {"coordinates":[9.2649478912,45.54063797],"type":"Point"}
}