{
  "type": "Feature",
  "properties": {
    "iso:country":"IT",
    "sg:address":"21, Via Savonarola Fra Gerolamo 20149 Milano",
    "sg:city":"Milano",
    "sg:classifiers":[
        {
            "category":"Manufacturing",
            "subcategory":"Metals",
            "type":"Manufacturing & Wholesale Goods"
        }
    ],
    "sg:phone":"+39 39023490230",
    "sg:postcode":"20149",
    "sg:province":"Milano",
    "sg:tags":[
        "metallurgy",
        "metalworking"
    ],
    "wof:name":"Alusim (s.r.l.)",
    "wof:placetype":"venue"
},
  "geometry": {"coordinates":[9.1591024399,45.4813041687],"type":"Point"}
}