{
  "type": "Feature",
  "properties": {
    "iso:country":"IT",
    "sg:address":"30122 Venezia",
    "sg:city":"Castello",
    "sg:orig_category":"Servizi Al Turismo. Servizi Ausiliari Per Il Trasporto",
    "sg:phone":"+39 041 522 4281",
    "sg:postcode":"30122",
    "sg:province":"Venezia",
    "wof:name":"Serenissima Motoscafi Srl",
    "wof:placetype":"venue"
},
  "geometry": {"coordinates":[12.341808,45.434422],"type":"Point"}
}