{
  "type": "Feature",
  "properties": {
    "addr:full":"00146 Roma Roma Roma 00146",
    "addr:postcode":"00146;00146",
    "iso:country":"IT",
    "sg:address":"00146 Roma",
    "sg:city":"Roma",
    "sg:orig_category":"Agenzie D'affari E Servizi Commerciali. Servizi Per Aziende, Manifestazioni E Supporto Agli Scambi Commerciali",
    "sg:phone":"+39 06 559 4602",
    "sg:postcode":"00146",
    "sg:province":"Roma",
    "wof:name":"Studio Associato Lombardo F. & Zambrini",
    "wof:placetype":"venue"
},
  "geometry": {"coordinates":[12.467256,41.8638],"type":"Point"}
}