{
  "type": "Feature",
  "properties": {
    "iso:country":"IT",
    "sg:address":"Via Virgilio 3 47100 Forli'",
    "sg:classifiers":[
        {
            "category":"Communications",
            "subcategory":"Radio Station",
            "type":"Services"
        }
    ],
    "sg:phone":"+39 0543 754213",
    "sg:postcode":"47100",
    "sg:province":"Forl\u00ec-Cesena",
    "sg:tags":[
        "generating",
        "set",
        "emergency"
    ],
    "sg:website":"www.dometic.com",
    "wof:name":"Dometic Wta Srl",
    "wof:placetype":"venue"
},
  "geometry": {"coordinates":[12.001312,44.245434],"type":"Point"}
}