{
  "type": "Feature",
  "properties": {
    "addr:full":"73021 Calimera Calimera Lecce 73021",
    "addr:postcode":"73021;73021",
    "iso:country":"IT",
    "sg:address":"73021 Calimera",
    "sg:city":"Calimera",
    "sg:orig_category":"Autonoleggio",
    "sg:phone":"+39 0832 873485",
    "sg:postcode":"73021",
    "sg:province":"Lecce",
    "wof:name":"Elios Srl Autoservizi",
    "wof:placetype":"venue"
},
  "geometry": {"coordinates":[18.280025,40.250988],"type":"Point"}
}