{
  "type": "Feature",
  "properties": {
    "iso:country":"IT",
    "sg:address":"84, Via Mazzini 10087 Valperga",
    "sg:city":"Valperga",
    "sg:classifiers":[
        {
            "category":"Professional",
            "subcategory":"Engineering",
            "type":"Services"
        }
    ],
    "sg:phone":"+39 0124 656000",
    "sg:postcode":"10087",
    "sg:province":"Torino",
    "sg:tags":[
        "machine",
        "-",
        "mechanical"
    ],
    "wof:name":"Tamic S.r.l.",
    "wof:placetype":"venue"
},
  "geometry": {"coordinates":[7.666122,45.36721],"type":"Point"}
}