{
  "type": "Feature",
  "properties": {
    "iso:country":"IT",
    "sg:address":"80059 Torre Del Greco",
    "sg:city":"Torre del Greco",
    "sg:orig_category":"Gioielleria, Oreficeria E Argenteria. Shopping",
    "sg:phone":"+39 081 881 4229",
    "sg:postcode":"80059",
    "sg:province":"Napoli",
    "wof:name":"Vip Coral Di Palomba Stanislao S.n.c.",
    "wof:placetype":"venue"
},
  "geometry": {"coordinates":[14.373619,40.789635],"type":"Point"}
}