{
  "type": "Feature",
  "properties": {
    "addr:full":"Via Fornaci 70 38068 Rovereto Rovereto Trento 38068",
    "addr:housenumber":"70",
    "addr:postcode":"38068;38068",
    "addr:street":"Via Fornaci",
    "iso:country":"IT",
    "sg:address":"Via Fornaci 70 38068 Rovereto",
    "sg:city":"Rovereto",
    "sg:classifiers":[
        {
            "category":"Manufacturing",
            "subcategory":"Metals",
            "type":"Manufacturing & Wholesale Goods"
        }
    ],
    "sg:phone":"+39 0464 434443",
    "sg:postcode":"38068",
    "sg:province":"Trento",
    "sg:tags":[
        "alloy",
        "construction",
        "lightweight"
    ],
    "wof:name":"Premetal Spa",
    "wof:placetype":"venue"
},
  "geometry": {"coordinates":[11.0054016113,45.8601379395],"type":"Point"}
}