{
  "type": "Feature",
  "properties": {
    "addr:full":"Via Mammarella Nicola 66100 Chieti Chieti Chieti 66100",
    "addr:postcode":"66100;66100",
    "addr:street":"Via Mammarella Nicola",
    "iso:country":"IT",
    "sg:address":"Via Mammarella Nicola 66100 Chieti",
    "sg:city":"Chieti",
    "sg:classifiers":[
        {
            "category":"Shopping",
            "subcategory":"Clothing, Apparel, & Fashions",
            "type":"Retail Goods"
        }
    ],
    "sg:phone":"+39 0871 560817",
    "sg:postcode":"66100",
    "sg:province":"Chieti",
    "sg:tags":[
        "clothes"
    ],
    "wof:name":"Torello Articoli Sportivi",
    "wof:placetype":"venue"
},
  "geometry": {"coordinates":[14.131564,42.356743],"type":"Point"}
}