{
  "type": "Feature",
  "properties": {
    "iso:country":"IT",
    "sg:address":"Via Marco Polo 6 31020 San Fior",
    "sg:city":"San Fior",
    "sg:classifiers":[
        {
            "category":"Bus Stop",
            "subcategory":"None",
            "type":"Transportation"
        }
    ],
    "sg:phone":"+39 0438 388192",
    "sg:postcode":"31020",
    "sg:province":"Treviso",
    "sg:tags":[
        "autoclave"
    ],
    "wof:name":"Nuova Enopieve Srl",
    "wof:placetype":"venue"
},
  "geometry": {"coordinates":[12.242072,45.666286],"type":"Point"}
}