{
  "type": "Feature",
  "properties": {
    "addr:full":"84012 Angri Angri Salerno 84012",
    "addr:postcode":"84012;84012",
    "iso:country":"IT",
    "sg:address":"84012 Angri",
    "sg:city":"Angri",
    "sg:orig_category":"Alimenti Conservati",
    "sg:phone":"+39 081 516 6111",
    "sg:postcode":"84012",
    "sg:province":"Salerno",
    "sg:website":"http://www.ladoria.it",
    "wof:name":"La Doria Spa Industria Conserve Alimentari",
    "wof:placetype":"venue"
},
  "geometry": {"coordinates":[14.570876,40.748577],"type":"Point"}
}