{
  "type": "Feature",
  "properties": {
    "iso:country":"IT",
    "sg:address":"00144 Roma",
    "sg:city":"Roma",
    "sg:classifiers":[
        {
            "category":"Professional",
            "subcategory":"Management & Consulting",
            "type":"Services"
        }
    ],
    "sg:phone":"+39 06 5224 4884",
    "sg:postcode":"00144",
    "sg:province":"Roma",
    "sg:tags":[
        "business",
        "technical",
        "consultant",
        "administration",
        "consultancies",
        "administrative",
        "appraiser"
    ],
    "wof:name":"Masters Microfin Srl",
    "wof:placetype":"venue"
},
  "geometry": {"coordinates":[12.436031,41.803757],"type":"Point"}
}