{
  "type": "Feature",
  "properties": {
    "iso:country":"IT",
    "sg:address":"37057 San Giovanni Lupatoto",
    "sg:city":"San Giovanni Lupatoto",
    "sg:orig_category":"Abbigliamento Esterno, Maglierie E Pelliccerie. Forniture Per Abbigliamento E Pelletterie",
    "sg:phone":"+39 045 545194",
    "sg:postcode":"37057",
    "sg:province":"Verona",
    "wof:name":"Cooperativa La Strada (s.r.l.)",
    "wof:placetype":"venue"
},
  "geometry": {"coordinates":[11.026236,45.400036],"type":"Point"}
}