{
  "type": "Feature",
  "properties": {
    "addr:full":"31050 Vedelago Albaredo Treviso 31050",
    "addr:postcode":"31050;31050",
    "iso:country":"IT",
    "sg:address":"31050 Vedelago",
    "sg:city":"Albaredo",
    "sg:orig_category":"Sport - Articoli E Forniture",
    "sg:phone":"+39 0423 452034",
    "sg:postcode":"31050",
    "sg:province":"Treviso",
    "wof:name":"L'arte Della Pesca Di Cavasin Eros",
    "wof:placetype":"venue"
},
  "geometry": {"coordinates":[12.010678,45.666584],"type":"Point"}
}