{
  "type": "Feature",
  "properties": {
    "iso:country":"IT",
    "sg:address":"26010 Vaiano Cremasco",
    "sg:city":"Vaiano Cremasco",
    "sg:orig_category":"Tempo Libero - Articoli E Forniture. Regalistica Aziendale",
    "sg:phone":"+39 0373 278063",
    "sg:postcode":"26010",
    "sg:province":"Cremona",
    "wof:name":"B.p.s. Snc",
    "wof:placetype":"venue"
},
  "geometry": {"coordinates":[9.590398,45.373867],"type":"Point"}
}