{
  "type": "Feature",
  "properties": {
    "iso:country":"IT",
    "sg:address":"50032 Borgo San Lorenzo",
    "sg:city":"Borgo San Lorenzo",
    "sg:orig_category":"Forniture Per Attivita' Industriali",
    "sg:phone":"+39 055 840 8851",
    "sg:postcode":"50032",
    "sg:province":"Firenze",
    "wof:name":"Morolli Pier Giovanni & C. S.n.c.",
    "wof:placetype":"venue"
},
  "geometry": {"coordinates":[11.4112052917,43.9972419739],"type":"Point"}
}