{
  "type": "Feature",
  "properties": {
    "iso:country":"IT",
    "sg:address":"22100 Como",
    "sg:city":"Como",
    "sg:orig_category":"Non-classified Establishments",
    "sg:phone":"+39 031 300524",
    "sg:postcode":"22100",
    "sg:province":"Como",
    "wof:name":"Cavagnin",
    "wof:placetype":"venue"
},
  "geometry": {"coordinates":[9.094582,45.80703],"type":"Point"}
}