{
  "type": "Feature",
  "properties": {
    "addr:full":"51039 Quarrata Quarrata Pistoia 51039",
    "addr:postcode":"51039;51039",
    "iso:country":"IT",
    "sg:address":"51039 Quarrata",
    "sg:city":"Quarrata",
    "sg:classifiers":[
        {
            "category":"Shopping",
            "type":"Retail Goods"
        }
    ],
    "sg:phone":"+39 0573 775150",
    "sg:postcode":"51039",
    "sg:province":"Pistoia",
    "sg:tags":[
        "letti"
    ],
    "wof:name":"Bresci Riccardo - Il Tappezziere",
    "wof:placetype":"venue"
},
  "geometry": {"coordinates":[10.981159,43.85342],"type":"Point"}
}