{
  "type": "Feature",
  "properties": {
    "iso:country":"IT",
    "sg:address":"Via Nichelino, 1 - Garino 10048 Vinovo",
    "sg:city":"Garino",
    "sg:classifiers":[
        {
            "category":"Arts & Performance",
            "subcategory":"Music",
            "type":"Entertainment"
        }
    ],
    "sg:phone":"+39 011 965 4264",
    "sg:postcode":"10048",
    "sg:province":"Torino",
    "sg:tags":[
        "pattern"
    ],
    "sg:website":"www.sisti.it",
    "wof:name":"F.lli Sisti S.r.l.",
    "wof:placetype":"venue"
},
  "geometry": {"coordinates":[7.6289610863,44.9757385254],"type":"Point"}
}