{
  "type": "Feature",
  "properties": {
    "iso:country":"IT",
    "sg:address":"96100 Siracusa",
    "sg:city":"Siracusa",
    "sg:orig_category":"Servizi Per Aziende, Manifestazioni E Supporto Agli Scambi Commerciali",
    "sg:phone":"+39 0931 481111",
    "sg:postcode":"96100",
    "sg:province":"Siracusa",
    "wof:name":"Soprintendenza Archeologica",
    "wof:placetype":"venue"
},
  "geometry": {"coordinates":[15.293677,37.059948],"type":"Point"}
}