{
  "type": "Feature",
  "properties": {
    "iso:country":"IT",
    "sg:address":"20042 Albiate",
    "sg:city":"Albiate",
    "sg:orig_category":"Articoli Per Imballaggio E Confezionamento",
    "sg:phone":"+39 036 293 0204",
    "sg:postcode":"20042",
    "sg:province":"Milano",
    "wof:name":"Saccheria Antonio Consonni (s.n.c.)",
    "wof:placetype":"venue"
},
  "geometry": {"coordinates":[9.258879,45.654827],"type":"Point"}
}