{
  "type": "Feature",
  "properties": {
    "iso:country":"IT",
    "sg:address":"15100 Alessandria",
    "sg:city":"Alessandria",
    "sg:orig_category":"Macchine, Impianti Ed Attrezzature Per Industria Alimentare E Bevande",
    "sg:phone":"+39 0131 263440",
    "sg:postcode":"15100",
    "sg:province":"Alessandria",
    "wof:name":"Passaggio Lorenzo",
    "wof:placetype":"venue"
},
  "geometry": {"coordinates":[8.71055,44.910763],"type":"Point"}
}