{
  "type": "Feature",
  "properties": {
    "addr:full":"Via Valverde 2; Varese; 21100 Varese Varese 21100",
    "addr:housenumber":"2",
    "addr:postcode":"21100;21100",
    "addr:street":"Via Valverde",
    "iso:country":"IT",
    "sg:address":"Via Valverde 2; Varese; 21100",
    "sg:city":"Varese",
    "sg:classifiers":[
        {
            "category":"Banks & Credit Unions",
            "subcategory":"Bank",
            "type":"Services"
        }
    ],
    "sg:phone":"+39 0332 296111",
    "sg:postcode":"21100",
    "sg:province":"Varese",
    "wof:name":"Banca Popolare Di Luino, E Di Varese Spa",
    "wof:placetype":"venue"
},
  "geometry": {"coordinates":[8.806545,45.835007],"type":"Point"}
}