{
  "type": "Feature",
  "properties": {
    "iso:country":"IT",
    "sg:address":"Via Palestrina 08030 Cagliari",
    "sg:orig_category":"Bird-sand",
    "sg:phone":"+39 0783 35441",
    "sg:postcode":"08030",
    "sg:province":"Cagliari",
    "wof:name":"Bentonite E Argille Attive Srl",
    "wof:placetype":"venue"
},
  "geometry": {"coordinates":[9.130375,39.222565],"type":"Point"}
}