{
  "type": "Feature",
  "properties": {
    "addr:full":"20129 Milano Milano Milano 20129",
    "addr:postcode":"20129;20129",
    "iso:country":"IT",
    "sg:address":"20129 Milano",
    "sg:city":"Milano",
    "sg:orig_category":"Trasporti E Spedizioni Merci",
    "sg:phone":"+39 02 205711",
    "sg:postcode":"20129",
    "sg:province":"Milano",
    "sg:website":"http://www.transpobank.it",
    "wof:name":"Transpobank Srl",
    "wof:placetype":"venue"
},
  "geometry": {"coordinates":[9.21579,45.474285],"type":"Point"}
}