{
  "type": "Feature",
  "properties": {
    "iso:country":"IT",
    "sg:address":"70023 Gioia Del Colle",
    "sg:city":"Gioia del Colle",
    "sg:orig_category":"Dolciumi E Gelati",
    "sg:phone":"+39 080 343 5502",
    "sg:postcode":"70023",
    "sg:province":"Bari",
    "wof:name":"Api Puglia",
    "wof:placetype":"venue"
},
  "geometry": {"coordinates":[16.935596,40.833523],"type":"Point"}
}