{
  "type": "Feature",
  "properties": {
    "iso:country":"IT",
    "sg:address":"20123 Milano",
    "sg:city":"Milano",
    "sg:orig_category":"Hobbistica",
    "sg:phone":"+39 02 804505",
    "sg:postcode":"20123",
    "sg:province":"Milano",
    "wof:name":"Frontini Paolo Srl",
    "wof:placetype":"venue"
},
  "geometry": {"coordinates":[9.182462,45.46455],"type":"Point"}
}