{
  "type": "Feature",
  "properties": {
    "iso:country":"IT",
    "sg:address":"245, Via Romagna 61011 Gabicce Mare",
    "sg:city":"Gabicce Mare",
    "sg:classifiers":[
        {
            "category":"Professional",
            "subcategory":"Engineering",
            "type":"Services"
        }
    ],
    "sg:phone":"+39 0541 950317",
    "sg:postcode":"61011",
    "sg:province":"Pesaro E Urbino",
    "sg:tags":[
        "machine",
        "-",
        "mechanical"
    ],
    "wof:name":"Aesse Arreda Di Scola Davide",
    "wof:placetype":"venue"
},
  "geometry": {"coordinates":[12.773946,43.955044],"type":"Point"}
}