{
  "type": "Feature",
  "properties": {
    "iso:country":"IT",
    "sg:address":"20129 Milano",
    "sg:city":"Milano",
    "sg:orig_category":"Carni, Salumi E Pesci. Zootecnia E Pesca, Allevamento Piccoli Animali",
    "sg:phone":"+39 02 741948",
    "sg:postcode":"20129",
    "sg:province":"Milano",
    "wof:name":"Cattaneo Gianfranco",
    "wof:placetype":"venue"
},
  "geometry": {"coordinates":[9.212657,45.472752],"type":"Point"}
}