{
  "type": "Feature",
  "properties": {
    "iso:country":"IT",
    "sg:address":"Viale Stucchi, 66/8 20052 Monza",
    "sg:city":"Monza",
    "sg:classifiers":[
        {
            "category":"Banks & Credit Unions",
            "subcategory":"Bank",
            "type":"Services"
        }
    ],
    "sg:phone":"+39 039 204901",
    "sg:postcode":"20052",
    "sg:province":"Milano",
    "sg:tags":[
        "chain",
        "systems",
        "cable",
        "guide"
    ],
    "sg:website":"www.brevettistendalto.it",
    "wof:name":"Brevetti Stendalto Spa",
    "wof:placetype":"venue"
},
  "geometry": {"coordinates":[9.308782,45.581165],"type":"Point"}
}