{
  "type": "Feature",
  "properties": {
    "addr:full":"12051 Alba Alba Cuneo 12051",
    "addr:postcode":"12051;12051",
    "iso:country":"IT",
    "sg:address":"12051 Alba",
    "sg:city":"Alba",
    "sg:orig_category":"Studi E Consulenze Amministrative, Commerciali E Aziendali. Banche E Servizi Finanziari. Agenzie D'affari E Servizi Commerciali. Consulenze Tecniche, Amministrative E Perizie",
    "sg:phone":"+39 0173 281613",
    "sg:postcode":"12051",
    "sg:province":"Cuneo",
    "sg:website":"http://itema.net",
    "wof:name":"Itema Snc Di Eandi Emanuele E Borello Italo",
    "wof:placetype":"venue"
},
  "geometry": {"coordinates":[8.035613,44.697369],"type":"Point"}
}