{
  "type": "Feature",
  "properties": {
    "addr:full":"10128 Torino Torino Torino 10128",
    "addr:postcode":"10128;10128",
    "iso:country":"IT",
    "sg:address":"10128 Torino",
    "sg:city":"Torino",
    "sg:orig_category":"Biancheria, Telerie E Coperte. Forniture Alle Strutture Ricettive",
    "sg:phone":"+39 011 542304",
    "sg:postcode":"10128",
    "sg:province":"Torino",
    "wof:name":"Losa Cotonificio Di Robassomero (s.r.l.)",
    "wof:placetype":"venue"
},
  "geometry": {"coordinates":[7.776258,45.074951],"type":"Point"}
}