{
  "type": "Feature",
  "properties": {
    "iso:country":"IT",
    "sg:address":"20123 Milano",
    "sg:city":"Milano",
    "sg:orig_category":"Coppe E Trofei - Produzione E Ingrosso",
    "sg:phone":"+39 02 8645 3529",
    "sg:postcode":"20123",
    "sg:province":"Milano",
    "wof:name":"Vassena Sas",
    "wof:placetype":"venue"
},
  "geometry": {"coordinates":[9.174826,45.464497],"type":"Point"}
}