{
  "type": "Feature",
  "properties": {
    "iso:country":"IT",
    "sg:address":"09030 Elmas",
    "sg:city":"Elmas",
    "sg:orig_category":"Bevande Analcoliche",
    "sg:phone":"+39 070 211281",
    "sg:postcode":"09030",
    "sg:province":"Cagliari",
    "wof:name":"Sosib Industriale E Commerciale Srl",
    "wof:placetype":"venue"
},
  "geometry": {"coordinates":[9.076322,39.260273],"type":"Point"}
}