{
  "type": "Feature",
  "properties": {
    "iso:country":"IT",
    "sg:address":"29, Via Macchi Mauro 20124 Milano",
    "sg:city":"Milano",
    "sg:classifiers":[
        {
            "category":"Sports & Exercise",
            "subcategory":"Playing Field",
            "type":"Entertainment"
        }
    ],
    "sg:phone":"+39 390 267 9161",
    "sg:postcode":"20124",
    "sg:province":"Milano",
    "sg:tags":[
        "game"
    ],
    "wof:name":"Holding Dei Giochi S.r.l.",
    "wof:placetype":"venue"
},
  "geometry": {"coordinates":[9.205955,45.483131],"type":"Point"}
}