{
  "type": "Feature",
  "properties": {
    "iso:country":"IT",
    "sg:address":"38035 Moena",
    "sg:city":"Moena",
    "sg:orig_category":"Autonoleggio",
    "sg:phone":"+39 0462 573734",
    "sg:postcode":"38035",
    "sg:province":"Trento",
    "wof:name":"Autonoleggio Taxi Desilvestro Franco",
    "wof:placetype":"venue"
},
  "geometry": {"coordinates":[11.660828,46.376312],"type":"Point"}
}