{
  "type": "Feature",
  "properties": {
    "iso:country":"IT",
    "sg:address":"10, Via Naviglio 24040 Isso",
    "sg:city":"Isso",
    "sg:classifiers":[
        {
            "category":"Shopping",
            "subcategory":"Crafts & Fabrics",
            "type":"Retail Goods"
        }
    ],
    "sg:phone":"+39 036 391 4414",
    "sg:postcode":"24040",
    "sg:province":"Bergamo",
    "wof:name":"Tlm (s.r.l.)",
    "wof:placetype":"venue"
},
  "geometry": {"coordinates":[9.7497797012,45.477519989],"type":"Point"}
}