{
  "type": "Feature",
  "properties": {
    "iso:country":"IT",
    "sg:address":"44021 Codigoro",
    "sg:city":"Codigoro",
    "sg:orig_category":"Assicurazioni E Servizi Assicurativi",
    "sg:phone":"+39 0533 713348",
    "sg:postcode":"44021",
    "sg:province":"Ferrara",
    "wof:name":"Fabbri Filippo Pietro",
    "wof:placetype":"venue"
},
  "geometry": {"coordinates":[12.118183,44.860775],"type":"Point"}
}