{
  "type": "Feature",
  "properties": {
    "iso:country":"IT",
    "sg:address":"20021 Bollate",
    "sg:city":"Bollate",
    "sg:orig_category":"Accessori Moda D'abbigliamento. Forniture Per Abbigliamento E Pelletterie. Shopping",
    "sg:phone":"+39 02 350 3155",
    "sg:postcode":"20021",
    "sg:province":"Milano",
    "wof:name":"Ricami Radice",
    "wof:placetype":"venue"
},
  "geometry": {"coordinates":[9.115255,45.543343],"type":"Point"}
}