{
  "type": "Feature",
  "properties": {
    "iso:country":"IT",
    "sg:address":"4, V. S. Margherita 09124 Cagliari",
    "sg:city":"Cagliari",
    "sg:classifiers":[
        {
            "category":"Banks & Credit Unions",
            "subcategory":"Bank",
            "type":"Services"
        }
    ],
    "sg:phone":"+39 39070679791",
    "sg:postcode":"09124",
    "sg:province":"Cagliari",
    "sg:tags":[
        "banking",
        "institution"
    ],
    "sg:website":"http://www.sfirs.it",
    "wof:name":"Sfirs Spa",
    "wof:placetype":"venue"
},
  "geometry": {"coordinates":[9.1153,39.212448],"type":"Point"}
}