{
  "type": "Feature",
  "properties": {
    "addr:full":"42025 Cavriago Reggio Nell'Emilia 42025",
    "addr:postcode":"42025;42025",
    "iso:country":"IT",
    "sg:address":"42025 Cavriago",
    "sg:orig_category":"Serramenti Ed Infissi",
    "sg:phone":"+39 0522 371511",
    "sg:postcode":"42025",
    "sg:province":"Reggio Nell'Emilia",
    "wof:name":"Oeffe Arteluce Di Burani O. & Comastri F.",
    "wof:placetype":"venue"
},
  "geometry": {"coordinates":[10.531149,44.704063],"type":"Point"}
}