{
  "type": "Feature",
  "properties": {
    "iso:country":"IT",
    "sg:address":"95037 San Giovanni La Punta",
    "sg:city":"San Giovanni la Punta",
    "sg:orig_category":"Manufacturers: Prefabbricati. Impianti E Attrezzature Per Lo Sport E Il Tempo Libero",
    "sg:phone":"+39 095 751 2549",
    "sg:postcode":"95037",
    "sg:province":"Catania",
    "wof:name":"Etna Giochi Di Mario La Malfa",
    "wof:placetype":"venue"
},
  "geometry": {"coordinates":[15.086736,37.587387],"type":"Point"}
}