{
  "type": "Feature",
  "properties": {
    "addr:full":"Viale Umberto 36, Sassari, Ss",
    "addr:housenumber":"36",
    "addr:street":"Viale Umberto",
    "iso:country":"IT",
    "sg:address":"Viale Umberto 36, Sassari, Ss",
    "sg:classifiers":[
        {
            "category":"Banks & Credit Unions",
            "subcategory":"Bank",
            "type":"Services"
        }
    ],
    "sg:phone":"+39 079 226000",
    "sg:website":"http://www.bancosardegna.it",
    "wof:name":"Banco Di Sardegna Spa",
    "wof:placetype":"venue"
},
  "geometry": {"coordinates":[8.672951,40.742249],"type":"Point"}
}