{
  "type": "Feature",
  "properties": {
    "addr:full":"Via Raffaello, 8/10 23861 Cesana Brianza Cesana Brianza Lecco 23861",
    "addr:housenumber":"8 / 10",
    "addr:postcode":"23861;brianza;23861",
    "addr:street":"Via Raffaello",
    "iso:country":"IT",
    "sg:address":"Via Raffaello, 8/10 23861 Cesana Brianza",
    "sg:city":"Cesana Brianza",
    "sg:classifiers":[
        {
            "category":"Food & Beverages",
            "subcategory":"Groceries & Convenience Stores",
            "type":"Retail Goods"
        }
    ],
    "sg:phone":"+39 031 655998",
    "sg:postcode":"23861",
    "sg:province":"Lecco",
    "sg:tags":[
        "fresh"
    ],
    "wof:name":"Lem Market Spa",
    "wof:placetype":"venue"
},
  "geometry": {"coordinates":[9.30859375,45.8143539429],"type":"Point"}
}