{
  "type": "Feature",
  "properties": {
    "addr:full":"33031 Basiliano Basiliano Udine 33031",
    "addr:postcode":"33031;33031",
    "iso:country":"IT",
    "sg:address":"33031 Basiliano",
    "sg:city":"Basiliano",
    "sg:orig_category":"Apparecchiature E Sistemi Per Imballaggio E Confezionamento",
    "sg:phone":"+39 0432 830249",
    "sg:postcode":"33031",
    "sg:province":"Udine",
    "wof:name":"Semca Industrie Srl",
    "wof:placetype":"venue"
},
  "geometry": {"coordinates":[13.118572,46.007523],"type":"Point"}
}