{
  "type": "Feature",
  "properties": {
    "addr:full":"Via Roma, 70013 Castellana Grotte, Ba Castellana Grotte Bari 70013",
    "addr:postcode":"70013;70013",
    "addr:street":"Via Roma",
    "iso:country":"IT",
    "sg:address":"Via Roma, 70013 Castellana Grotte, Ba",
    "sg:city":"Castellana Grotte",
    "sg:classifiers":[
        {
            "category":"Banks & Credit Unions",
            "subcategory":"Bank",
            "type":"Services"
        }
    ],
    "sg:postcode":"70013",
    "sg:province":"Bari",
    "wof:name":"Cassa Rurale E Artigiana Di Castellana Grotte",
    "wof:placetype":"venue"
},
  "geometry": {"coordinates":[17.166771,40.883572],"type":"Point"}
}