{
  "type": "Feature",
  "properties": {
    "iso:country":"IT",
    "sg:address":"Via Paradigna 187/a 43100 Parma",
    "sg:city":"Paradigna",
    "sg:classifiers":[
        {
            "category":"Banks & Credit Unions",
            "subcategory":"Investment Brokerage",
            "type":"Services"
        }
    ],
    "sg:phone":"+39 0521 607314",
    "sg:postcode":"43100",
    "sg:province":"Parma",
    "sg:tags":[
        "packaging",
        "equipment",
        "machinery",
        "maintenance",
        "servicing"
    ],
    "wof:name":"Rev.mec. Di Turchi, Bravi & Guareschi Snc",
    "wof:placetype":"venue"
},
  "geometry": {"coordinates":[10.29492,44.823208],"type":"Point"}
}