{
  "type": "Feature",
  "properties": {
    "addr:full":"20026 Novate Milanese Novate Milanese Milano 20026",
    "addr:postcode":"20026;20026",
    "iso:country":"IT",
    "sg:address":"20026 Novate Milanese",
    "sg:city":"Novate Milanese",
    "sg:orig_category":"Forniture Per Edilizia E Lavori Pubblici. Arredi Ed Attrezzature Per Attivita' Commerciali Ed Artigianali. Forniture Per Attivita' Industriali",
    "sg:phone":"+39 02 356 7449",
    "sg:postcode":"20026",
    "sg:province":"Milano",
    "wof:name":"M.d.b. Snc Di Massimiliano & David Bastoni & C.",
    "wof:placetype":"venue"
},
  "geometry": {"coordinates":[9.1272764206,45.5280952454],"type":"Point"}
}