{
  "type": "Feature",
  "properties": {
    "addr:full":"20145 Milano Milano Milano 20145",
    "addr:postcode":"20145;20145",
    "iso:country":"IT",
    "sg:address":"20145 Milano",
    "sg:city":"Milano",
    "sg:classifiers":[
        {
            "category":"Health Services",
            "subcategory":"Health Practitioner",
            "type":"Services"
        }
    ],
    "sg:phone":"+39 02 498 9581",
    "sg:postcode":"20145",
    "sg:province":"Milano",
    "sg:tags":[
        "medici"
    ],
    "wof:name":"Associazione A.i.o.s. Italiana Operatori In Sessuologia",
    "wof:placetype":"venue"
},
  "geometry": {"coordinates":[9.155335,45.469452],"type":"Point"}
}