{
  "type": "Feature",
  "properties": {
    "iso:country":"IT",
    "sg:address":"37036 San Martino Buon Albergo",
    "sg:city":"San Martino Buon Albergo",
    "sg:orig_category":"Esportatori Ed Importatori",
    "sg:phone":"+39 045 990922",
    "sg:postcode":"37036",
    "sg:province":"Verona",
    "sg:website":"http://www.paginegialle.it/globalgroup",
    "wof:name":"Global Group Srl",
    "wof:placetype":"venue"
},
  "geometry": {"coordinates":[11.114669,45.423958],"type":"Point"}
}