{
  "type": "Feature",
  "properties": {
    "iso:country":"IT",
    "sg:address":"92014 Porto Empedocle",
    "sg:city":"Porto Empedocle",
    "sg:orig_category":"Servizi E Lavori Per Arredamento E Industria Del Legno. Servizi Di Magazzinaggio E Movimentazione",
    "sg:phone":"+39 0922 601330",
    "sg:postcode":"92014",
    "sg:province":"Agrigento",
    "wof:name":"Traslochi Volpe",
    "wof:placetype":"venue"
},
  "geometry": {"coordinates":[13.495184,37.295883],"type":"Point"}
}