{
  "type": "Feature",
  "properties": {
    "iso:country":"IT",
    "sg:address":"00042 Anzio",
    "sg:city":"Anzio",
    "sg:orig_category":"Lavorazioni Meccaniche E Servizi. Riparazione Dei Mezzi Di Trasporto",
    "sg:phone":"+39 06 9834 1028",
    "sg:postcode":"00042",
    "sg:province":"Roma",
    "wof:name":"Ce.ri.mar. 2001 Di Cua Elisabetta",
    "wof:placetype":"venue"
},
  "geometry": {"coordinates":[12.61014,41.511349],"type":"Point"}
}