{
  "type": "Feature",
  "properties": {
    "addr:full":"15, Via Brasile 20096 Pioltello Pioltello Milano 20096",
    "addr:postcode":"20096;20096",
    "addr:street":"Via Brasile",
    "iso:country":"IT",
    "sg:address":"15, Via Brasile 20096 Pioltello",
    "sg:city":"Pioltello",
    "sg:classifiers":[
        {
            "category":"Parking",
            "subcategory":"Lot",
            "type":"Transportation"
        }
    ],
    "sg:phone":"+39 39029267759",
    "sg:postcode":"20096",
    "sg:province":"Milano",
    "sg:tags":[
        "transport",
        "road"
    ],
    "wof:name":"Ras Trasporti S.r.l.",
    "wof:placetype":"venue"
},
  "geometry": {"coordinates":[9.327901,45.489613],"type":"Point"}
}