{
  "type": "Feature",
  "properties": {
    "iso:country":"IT",
    "sg:address":"10146 Torino",
    "sg:city":"Torino",
    "sg:orig_category":"Banche E Servizi Finanziari",
    "sg:phone":"+39 011 773 1902",
    "sg:postcode":"10146",
    "sg:province":"Torino",
    "sg:website":"http://www.mussofinanziaria.it",
    "wof:name":"Musso Consulenza Finanziaria",
    "wof:placetype":"venue"
},
  "geometry": {"coordinates":[7.595152,45.073586],"type":"Point"}
}