{
  "type": "Feature",
  "properties": {
    "iso:country":"IT",
    "sg:address":"40, Via Salomone Oreste 80144 Napoli",
    "sg:city":"Napoli",
    "sg:classifiers":[
        {
            "category":"Shopping",
            "subcategory":"Clothing, Apparel, & Fashions",
            "type":"Retail Goods"
        }
    ],
    "sg:phone":"+39 081 751 6009",
    "sg:postcode":"80144",
    "sg:province":"Napoli",
    "sg:tags":[
        "clothes"
    ],
    "wof:name":"Turco Fratelli Fu Luigi (s.n.c.)",
    "wof:placetype":"venue"
},
  "geometry": {"coordinates":[14.285278,40.873516],"type":"Point"}
}