{
  "type": "Feature",
  "properties": {
    "iso:country":"IT",
    "sg:address":"16, V. Nazionale 33042 Buttrio",
    "sg:city":"Buttrio",
    "sg:classifiers":[
        {
            "category":"Home & Garden",
            "subcategory":"Home Furnishings",
            "type":"Retail Goods"
        }
    ],
    "sg:phone":"+39 0432 673438",
    "sg:postcode":"33042",
    "sg:province":"Udine",
    "sg:tags":[
        "household"
    ],
    "sg:website":"http://www.fratellimenossi.com:ws_end: :mark:ws:http://www.paginegialle.it/fratellimenossi",
    "wof:name":"Menossi F.lli",
    "wof:placetype":"venue"
},
  "geometry": {"coordinates":[13.323631,46.012455],"type":"Point"}
}