{
  "type": "Feature",
  "properties": {
    "iso:country":"IT",
    "sg:address":"46040 Casalmoro",
    "sg:city":"Casalmoro",
    "sg:orig_category":"Macchine, Impianti Ed Attrezzature Per Abbigliamento E Pelletterie",
    "sg:phone":"+39 0376 737268",
    "sg:postcode":"46040",
    "sg:province":"Mantova",
    "wof:name":"B.t.s.r. International Spa",
    "wof:placetype":"venue"
},
  "geometry": {"coordinates":[10.405648,45.260647],"type":"Point"}
}