{
  "type": "Feature",
  "properties": {
    "addr:full":"20145 Milano Milano Milano 20145",
    "addr:postcode":"20145;20145",
    "iso:country":"IT",
    "sg:address":"20145 Milano",
    "sg:city":"Milano",
    "sg:orig_category":"Servizi Editoriali. Pubblicita', Marketing E Comunicazione",
    "sg:phone":"+39 02 3453 8070",
    "sg:postcode":"20145",
    "sg:province":"Milano",
    "wof:name":"Blue Sas",
    "wof:placetype":"venue"
},
  "geometry": {"coordinates":[9.171194,45.474918],"type":"Point"}
}