{
  "type": "Feature",
  "properties": {
    "iso:country":"IT",
    "sg:address":"31030 Borso Del Grappa",
    "sg:city":"Borso del Grappa",
    "sg:orig_category":"Minuterie Metalliche E Ferramenta",
    "sg:phone":"+39 0423 561142",
    "sg:postcode":"31030",
    "sg:province":"Treviso",
    "sg:website":"http://www.stami.com",
    "wof:name":"Stami Srl",
    "wof:placetype":"venue"
},
  "geometry": {"coordinates":[11.7960863113,45.8207702637],"type":"Point"}
}