{
  "type": "Feature",
  "properties": {
    "iso:country":"IT",
    "sg:address":"22060 Cucciago",
    "sg:city":"Cucciago",
    "sg:orig_category":"Servizi E Lavori Per Arredamento E Industria Del Legno. Servizi E Lavori Per Edilizia E Lavori Pubblici",
    "sg:phone":"+39 031 725192",
    "sg:postcode":"22060",
    "sg:province":"Como",
    "sg:website":"http://www.vanossi.it",
    "wof:name":"Vanossi Andrea & Roberto Snc",
    "wof:placetype":"venue"
},
  "geometry": {"coordinates":[9.103517,45.741573],"type":"Point"}
}