{
  "type": "Feature",
  "properties": {
    "addr:full":"20155 Milano Milano Milano 20155",
    "addr:postcode":"20155;20155",
    "iso:country":"IT",
    "sg:address":"20155 Milano",
    "sg:city":"Milano",
    "sg:orig_category":"Servizi Culturali E Per Lo Spettacolo. Servizi Al Turismo. Acqua, Luce, Gas E Societa' Di Esercizio Pubblico",
    "sg:phone":"+39 02 3921 5239",
    "sg:postcode":"20155",
    "sg:province":"Milano",
    "wof:name":"Teatro Out Off Di Bertoldo B. & C. (s.a.s.)",
    "wof:placetype":"venue"
},
  "geometry": {"coordinates":[9.15802,45.492809],"type":"Point"}
}