{
  "type": "Feature",
  "properties": {
    "addr:full":"Via Garibaldi, 26; Moglia; 46024 Moglia Mantova 46024",
    "addr:housenumber":"26",
    "addr:postcode":"46024;46024",
    "addr:street":"Via Garibaldi;Moglia",
    "iso:country":"IT",
    "sg:address":"Via Garibaldi, 26; Moglia; 46024",
    "sg:city":"Moglia",
    "sg:classifiers":[
        {
            "category":"Banks & Credit Unions",
            "subcategory":"Bank",
            "type":"Services"
        }
    ],
    "sg:phone":"+39 0376 598443",
    "sg:postcode":"46024",
    "sg:province":"Mantova",
    "wof:name":"Banca Agricola Mantovana Scarl",
    "wof:placetype":"venue"
},
  "geometry": {"coordinates":[10.91266,44.933117],"type":"Point"}
}