{
  "type": "Feature",
  "properties": {
    "iso:country":"IT",
    "sg:address":"20088 Rosate",
    "sg:city":"Rosate",
    "sg:orig_category":"Trattamenti Termici E Superficiali Metalli, Galvanotecnica",
    "sg:phone":"+39 02 905 2475",
    "sg:postcode":"20088",
    "sg:province":"Milano",
    "wof:name":"Pulysistem Snc",
    "wof:placetype":"venue"
},
  "geometry": {"coordinates":[9.023475,45.353394],"type":"Point"}
}