{
  "type": "Feature",
  "properties": {
    "iso:country":"IT",
    "sg:address":"34141 Trieste",
    "sg:city":"Trieste",
    "sg:orig_category":"Torrefazione Di Caffe' Ed Affini - Lavorazione E Ingrosso",
    "sg:phone":"+39 040 397310",
    "sg:postcode":"34141",
    "sg:province":"Trieste",
    "wof:name":"Perlanera Srl",
    "wof:placetype":"venue"
},
  "geometry": {"coordinates":[13.787529,45.646103],"type":"Point"}
}