{
  "type": "Feature",
  "properties": {
    "addr:full":"24126 Bergamo Bergamo Bergamo 24126",
    "addr:postcode":"24126;24126",
    "iso:country":"IT",
    "sg:address":"24126 Bergamo",
    "sg:city":"Bergamo",
    "sg:orig_category":"Tessuti E Stoffe. Tessuti Arredamento, Tende E Tappeti",
    "sg:phone":"+39 035 321065",
    "sg:postcode":"24126",
    "sg:province":"Bergamo",
    "wof:name":"Maxim Srl",
    "wof:placetype":"venue"
},
  "geometry": {"coordinates":[9.676983,45.673641],"type":"Point"}
}