{
  "type": "Feature",
  "properties": {
    "addr:full":"19125 La Spezia SP",
    "addr:housenumber":"19125",
    "iso:country":"IT",
    "sg:address":"19125 La Spezia",
    "sg:orig_category":"Associazioni Sindacali E Di Categoria",
    "sg:phone":"+39 0187 518341",
    "sg:province":"SP",
    "wof:name":"Confcommercio",
    "wof:placetype":"venue"
},
  "geometry": {"coordinates":[9.84285,44.122593],"type":"Point"}
}