{
  "type": "Feature",
  "properties": {
    "iso:country":"IT",
    "sg:address":"34, Via Caduti 25065 Lumezzane",
    "sg:city":"Lumezzane",
    "sg:classifiers":[
        {
            "category":"Manufacturing",
            "subcategory":"Food",
            "type":"Manufacturing & Wholesale Goods"
        }
    ],
    "sg:phone":"+39 030 897 0751",
    "sg:postcode":"25065",
    "sg:province":"Brescia",
    "sg:tags":[
        "equipment",
        "processing",
        "-",
        "machinery"
    ],
    "wof:name":"Lonatini Fratelli Di Lonatini Giordano & C. Snc",
    "wof:placetype":"venue"
},
  "geometry": {"coordinates":[10.2229642868,45.6011047363],"type":"Point"}
}