{
  "type": "Feature",
  "properties": {
    "iso:country":"IT",
    "sg:address":"47018 S.sofia",
    "sg:orig_category":"Carni, Salumi E Pesci",
    "sg:phone":"+39 0543 990111",
    "sg:postcode":"47018",
    "sg:province":"Forl\u00ec-Cesena",
    "sg:website":"http://www.pollodelcampo.it",
    "wof:name":"Pollo Del Campo Due Soc.coop.r.l.",
    "wof:placetype":"venue"
},
  "geometry": {"coordinates":[11.908935,43.945404],"type":"Point"}
}