{
  "type": "Feature",
  "properties": {
    "iso:country":"IT",
    "sg:address":"Via Dell' Industria, 23/25 34170 Gorizia",
    "sg:city":"Gorizia",
    "sg:classifiers":[
        {
            "category":"Home & Garden",
            "subcategory":"Furniture",
            "type":"Retail Goods"
        }
    ],
    "sg:phone":"+39 0481 21112",
    "sg:postcode":"34170",
    "sg:province":"Gorizia",
    "sg:tags":[
        "accessory"
    ],
    "sg:website":"www.bramo.net",
    "wof:name":"Giovanni Bramo Srl",
    "wof:placetype":"venue"
},
  "geometry": {"coordinates":[13.604289,45.913441],"type":"Point"}
}