{
  "type": "Feature",
  "properties": {
    "iso:country":"IT",
    "sg:address":"10138 Torino",
    "sg:city":"Torino",
    "sg:orig_category":"Pubblica Amministrazione",
    "sg:phone":"+39 011 433 2875",
    "sg:postcode":"10138",
    "sg:province":"Torino",
    "wof:name":"Provveditorato Agli Studi Di Torino",
    "wof:placetype":"venue"
},
  "geometry": {"coordinates":[7.6563692093,45.0751991272],"type":"Point"}
}