{
  "type": "Feature",
  "properties": {
    "iso:country":"IT",
    "sg:address":"68, Via Garda 63018 Porto Sant'elpidio",
    "sg:orig_category":"Miscellaneous Products",
    "sg:phone":"+39 0734 991125",
    "sg:postcode":"63018",
    "sg:province":"Ascoli Piceno",
    "wof:name":"G.b.a. Italia Snc Di Quadrini Valentini & C.",
    "wof:placetype":"venue"
},
  "geometry": {"coordinates":[13.7395820618,43.24792099],"type":"Point"}
}