{
  "type": "Feature",
  "properties": {
    "addr:full":"44029 Porto Garibaldi Porto Garibaldi Ferrara 44029",
    "addr:housenumber":"44029",
    "addr:postcode":"44029",
    "iso:country":"IT",
    "sg:address":"44029 Porto Garibaldi",
    "sg:city":"Porto Garibaldi",
    "sg:orig_category":"Prodotti Di Base E Forniture Per Industria Alimentare E Bevande. Macchine, Impianti Ed Attrezzature Per Industria Alimentare E Bevande. Frigotecnica, Apparecchiature E Servizi. Macchine E Impianti Per",
    "sg:phone":"+39 0533 327418",
    "sg:postcode":"44029",
    "sg:province":"Ferrara",
    "wof:name":"Fabbrica Ghiaccio Vol.fa S.n.c.",
    "wof:placetype":"venue"
},
  "geometry": {"coordinates":[12.2417469025,44.6754074097],"type":"Point"}
}