{
  "type": "Feature",
  "properties": {
    "addr:full":"20017 Rho Rho Milano 20017",
    "addr:postcode":"20017;20017",
    "iso:country":"IT",
    "sg:address":"20017 Rho",
    "sg:city":"Rho",
    "sg:orig_category":"Frigotecnica, Apparecchiature E Servizi",
    "sg:phone":"+39 02 9390 1150",
    "sg:postcode":"20017",
    "sg:province":"Milano",
    "sg:website":"http://www.",
    "wof:name":"Polithermo Srl",
    "wof:placetype":"venue"
},
  "geometry": {"coordinates":[9.092376709,45.5259475708],"type":"Point"}
}