{
  "type": "Feature",
  "properties": {
    "iso:country":"IT",
    "sg:address":"71042 Cerignola",
    "sg:city":"Cerignola",
    "sg:orig_category":"Non-classified Establishments",
    "sg:phone":"+39 0885 429396",
    "sg:postcode":"71042",
    "sg:province":"Foggia",
    "wof:name":"Mobilificio Italia Di Caputo Giuseppe",
    "wof:placetype":"venue"
},
  "geometry": {"coordinates":[15.895076,41.275951],"type":"Point"}
}