{
  "type": "Feature",
  "properties": {
    "iso:country":"IT",
    "sg:address":"9, Via Alessandro Volta 36057 Arcugnano",
    "sg:city":"Arcugnano",
    "sg:classifiers":[
        {
            "category":"Wholesale",
            "subcategory":"Machinery & Supplies",
            "type":"Manufacturing & Wholesale Goods"
        }
    ],
    "sg:phone":"+39 0444 289200",
    "sg:postcode":"36057",
    "sg:province":"Vicenza",
    "sg:tags":[
        "equipment",
        "precision"
    ],
    "wof:name":"Asa (s.r.l.)",
    "wof:placetype":"venue"
},
  "geometry": {"coordinates":[11.5109176636,45.5112304688],"type":"Point"}
}