{
  "type": "Feature",
  "properties": {
    "addr:full":"43045 Fornovo Di Taro Fornovo di Taro Parma 43045",
    "addr:housenumber":"di taro",
    "addr:postcode":"43045;43045",
    "iso:country":"IT",
    "sg:address":"43045 Fornovo Di Taro",
    "sg:city":"Fornovo di Taro",
    "sg:orig_category":"Ricerca, Selezione E Formazione Del Personale. Pubblica Amministrazione",
    "sg:phone":"+39 0525 2141",
    "sg:postcode":"43045",
    "sg:province":"Parma",
    "wof:name":"Centro Per L'impiego Di Langhirano Borgotaro-sede Di Fornovo Taro",
    "wof:placetype":"venue"
},
  "geometry": {"coordinates":[10.22863,44.71323],"type":"Point"}
}