{
  "type": "Feature",
  "properties": {
    "iso:country":"IT",
    "sg:address":"46030 Bigarello",
    "sg:city":"Bigarello",
    "sg:orig_category":"Macchine, Impianti Ed Attrezzature Per Abbigliamento E Pelletterie",
    "sg:postcode":"46030",
    "sg:province":"Mantova",
    "wof:name":"Rim Mantova (s.r.l.)",
    "wof:placetype":"venue"
},
  "geometry": {"coordinates":[10.898902,45.179989],"type":"Point"}
}