{
  "type": "Feature",
  "properties": {
    "iso:country":"IT",
    "sg:address":"36043 Camisano Vicentino",
    "sg:city":"Camisano Vicentino",
    "sg:orig_category":"Accessori Moda D'abbigliamento. Shopping",
    "sg:phone":"+39 0444 610445",
    "sg:postcode":"36043",
    "sg:province":"Vicenza",
    "wof:name":"Zamunaro Angelo",
    "wof:placetype":"venue"
},
  "geometry": {"coordinates":[11.620983,45.572739],"type":"Point"}
}