{
  "type": "Feature",
  "properties": {
    "addr:full":"36027 Ros\u00e0 Vicenza 36027",
    "addr:postcode":"36027;36027",
    "iso:country":"IT",
    "sg:address":"36027 Ros\u00e0",
    "sg:orig_category":"Lavorazioni Metalli, Stampaggio E Saldatura",
    "sg:phone":"+39 0424 539983",
    "sg:postcode":"36027",
    "sg:province":"Vicenza",
    "wof:name":"Tecnoacciai Srl",
    "wof:placetype":"venue"
},
  "geometry": {"coordinates":[11.515144,45.526569],"type":"Point"}
}