{
  "type": "Feature",
  "properties": {
    "addr:full":"90141 Palermo Palermo Palermo 90141",
    "addr:postcode":"90141;90141",
    "iso:country":"IT",
    "sg:address":"90141 Palermo",
    "sg:city":"Palermo",
    "sg:orig_category":"Scuole E Servizi Scolastici. Ricerca, Selezione E Formazione Del Personale",
    "sg:phone":"+39 091 320522",
    "sg:postcode":"90141",
    "sg:province":"Palermo",
    "wof:name":"Istituto Tecnico Commerciale Nove Studi",
    "wof:placetype":"venue"
},
  "geometry": {"coordinates":[13.349888,38.124981],"type":"Point"}
}