{
  "type": "Feature",
  "properties": {
    "iso:country":"IT",
    "sg:address":"Pescina; 67057",
    "sg:classifiers":[
        {
            "category":"Banks & Credit Unions",
            "subcategory":"Bank",
            "type":"Services"
        }
    ],
    "sg:phone":"+39 0863 82167",
    "sg:postcode":"67057",
    "sg:province":"L'Aquila",
    "wof:name":"Cassa Di Risparmio Della, Provincia Dell'aquila",
    "wof:placetype":"venue"
},
  "geometry": {"coordinates":[13.671006,42.033997],"type":"Point"}
}