{
  "type": "Feature",
  "properties": {
    "addr:full":"20047 Brugherio Brugherio Milano 20047",
    "addr:postcode":"20047;20047",
    "iso:country":"IT",
    "sg:address":"20047 Brugherio",
    "sg:city":"Brugherio",
    "sg:orig_category":"Fotografia Pubblicitaria",
    "sg:phone":"+39 039 287 1790",
    "sg:postcode":"20047",
    "sg:province":"Milano",
    "sg:website":"http://www.aet.cc",
    "wof:name":"Advertising Team Sas",
    "wof:placetype":"venue"
},
  "geometry": {"coordinates":[9.2986774445,45.5425567627],"type":"Point"}
}