{
  "type": "Feature",
  "properties": {
    "addr:full":"06074 Perugia PG",
    "addr:postcode":"06074",
    "addr:street":"Pg",
    "iso:country":"IT",
    "sg:address":"06074 Perugia",
    "sg:orig_category":"Ospedali E Servizi Sanitari. Centri Di Estetica E Cosmesi E Servizi",
    "sg:phone":"+39 075 517 7490",
    "sg:province":"PG",
    "sg:website":"http://www.m-amo.com",
    "wof:name":"M'amo Srl",
    "wof:placetype":"venue"
},
  "geometry": {"coordinates":[-72.57963599999999,41.844532],"type":"Point"}
}