{
  "type": "Feature",
  "properties": {
    "addr:full":"10072 Caselle Torinese Caselle Torinese Torino 10072",
    "addr:postcode":"10072;10072",
    "iso:country":"IT",
    "sg:address":"10072 Caselle Torinese",
    "sg:city":"Caselle Torinese",
    "sg:orig_category":"Termotecnica E Riscaldamento, Apparecchiature E Servizi",
    "sg:phone":"+39 011 996 8341",
    "sg:postcode":"10072",
    "sg:province":"Torino",
    "wof:name":"Air Systems Srl",
    "wof:placetype":"venue"
},
  "geometry": {"coordinates":[7.696568,45.156933],"type":"Point"}
}