{
  "type": "Feature",
  "properties": {
    "iso:country":"IT",
    "sg:address":"Via Pietro Durio 5 28010 Pella",
    "sg:city":"Pella",
    "sg:orig_category":"Fittings, Valves",
    "sg:phone":"+39 0322 969241",
    "sg:postcode":"28010",
    "sg:province":"Novara",
    "sg:website":"www.gattonirubinetteria.com",
    "wof:name":"Gattoni Rubinetteria Spa",
    "wof:placetype":"venue"
},
  "geometry": {"coordinates":[8.3791980743,45.7937850952],"type":"Point"}
}