{
  "type": "Feature",
  "properties": {
    "iso:country":"IT",
    "sg:address":"Via Benedetta 40a 43100 Parma",
    "sg:city":"Parma",
    "sg:classifiers":[
        {
            "category":"Professional",
            "type":"Services"
        }
    ],
    "sg:phone":"+39 0521 273240",
    "sg:postcode":"43100",
    "sg:province":"Parma",
    "sg:tags":[
        "mould",
        "construction"
    ],
    "wof:name":"Stamperia Parmense Di Malpeli Renzo & C Snc",
    "wof:placetype":"venue"
},
  "geometry": {"coordinates":[10.3310050964,44.7979507446],"type":"Point"}
}