{
  "type": "Feature",
  "properties": {
    "iso:country":"IT",
    "sg:address":"47031 Repubblica Di San Marino",
    "sg:orig_category":"Carta, Cartone E Prodotti Primari. Forniture E Materiali Per Imballaggio E Confezionamento",
    "sg:phone":"+39 0549 907161",
    "sg:province":"SM",
    "wof:name":"Titan Screen Di Beccari Katia E Campana Pierpaolo",
    "wof:placetype":"venue"
},
  "geometry": {"coordinates":[12.441867,43.944237],"type":"Point"}
}