{
  "type": "Feature",
  "properties": {
    "addr:full":"35129 Padova Padova Padova 35129",
    "addr:postcode":"35129;35129",
    "iso:country":"IT",
    "sg:address":"35129 Padova",
    "sg:city":"Padova",
    "sg:orig_category":"Motori Ed Organi Di Trasmissione. Ricambi E Componenti Dei Mezzi Di Trasporto",
    "sg:phone":"+39 049 806 5221",
    "sg:postcode":"35129",
    "sg:province":"Padova",
    "sg:website":"http://www.ricambisimac.it",
    "wof:name":"Societa' Ricambi Simac Srl",
    "wof:placetype":"venue"
},
  "geometry": {"coordinates":[11.9524316788,45.4278488159],"type":"Point"}
}