{
  "type": "Feature",
  "properties": {
    "iso:country":"IT",
    "sg:address":"20154 Milano",
    "sg:city":"Milano",
    "sg:orig_category":"Abbigliamento Esterno, Maglierie E Pelliccerie. Servizi E Lavori Per Abbigliamento E Pelletterie",
    "sg:phone":"+39 02 3310 3562",
    "sg:postcode":"20154",
    "sg:province":"Milano",
    "wof:name":"Consentino Francesco Giovanni",
    "wof:placetype":"venue"
},
  "geometry": {"coordinates":[9.175912,45.485226],"type":"Point"}
}