{
  "type": "Feature",
  "properties": {
    "addr:full":"60015 Falconara Marittima Falconara Marittima Ancona 60015",
    "addr:postcode":"60015;60015",
    "iso:country":"IT",
    "sg:address":"60015 Falconara Marittima",
    "sg:city":"Falconara Marittima",
    "sg:orig_category":"Non-classified Establishments",
    "sg:phone":"+39 071 915 7035",
    "sg:postcode":"60015",
    "sg:province":"Ancona",
    "wof:name":"Cereria La Piramide",
    "wof:placetype":"venue"
},
  "geometry": {"coordinates":[13.363099,43.604069],"type":"Point"}
}