{
  "type": "Feature",
  "properties": {
    "iso:country":"IT",
    "sg:address":"Via Deledda Grazia 37060 Sona",
    "sg:city":"Sona",
    "sg:classifiers":[
        {
            "category":"Personal",
            "subcategory":"Shoe Repair & Shine",
            "type":"Services"
        }
    ],
    "sg:phone":"+39 045 608 0206",
    "sg:postcode":"37060",
    "sg:province":"Verona",
    "sg:tags":[
        "leather"
    ],
    "wof:name":"Graffiti (s.r.l.)",
    "wof:placetype":"venue"
},
  "geometry": {"coordinates":[10.840202,45.400936],"type":"Point"}
}