{
  "type": "Feature",
  "properties": {
    "iso:country":"IT",
    "sg:address":"24060 Castelli Calepio",
    "sg:city":"Castelli Calepio",
    "sg:orig_category":"Tessuti E Stoffe. Filati E Materie Prime Tessili",
    "sg:phone":"+39 035 847160",
    "sg:postcode":"24060",
    "sg:province":"Bergamo",
    "sg:website":"http://www.valcalepio.it",
    "wof:name":"Manifattura Valcalepio Srl",
    "wof:placetype":"venue"
},
  "geometry": {"coordinates":[9.903907,45.638981],"type":"Point"}
}