{
  "type": "Feature",
  "properties": {
    "addr:full":"13/a, Via Pier Santi Mattarella 30037 Scorze' Venezia 30037",
    "addr:housenumber":"13 / a",
    "addr:postcode":"30037;30037",
    "addr:street":"Via Pier Santi Mattarella",
    "iso:country":"IT",
    "sg:address":"13/a, Via Pier Santi Mattarella 30037 Scorze'",
    "sg:classifiers":[
        {
            "category":"Shopping",
            "subcategory":"Gifts & Souvenirs",
            "type":"Retail Goods"
        }
    ],
    "sg:phone":"+39 39041448741",
    "sg:postcode":"30037",
    "sg:province":"Venezia",
    "wof:name":"Publiremor",
    "wof:placetype":"venue"
},
  "geometry": {"coordinates":[12.204066,45.561852],"type":"Point"}
}