{
  "type": "Feature",
  "properties": {
    "iso:country":"IT",
    "sg:address":"20094 Corsico",
    "sg:city":"Corsico",
    "sg:orig_category":"Lavorazioni Meccaniche E Servizi. Riparazione Dei Mezzi Di Trasporto",
    "sg:phone":"+39 02 4860 2036",
    "sg:postcode":"20094",
    "sg:province":"Milano",
    "wof:name":"Amd Snc Di Spaggiari Luciano E Spaggiari Antonella E C.",
    "wof:placetype":"venue"
},
  "geometry": {"coordinates":[9.105356,45.444695],"type":"Point"}
}