{
  "type": "Feature",
  "properties": {
    "iso:country":"IT",
    "sg:address":"1, Via Rostoncello 36010 Carre'",
    "sg:classifiers":[
        {
            "category":"Wholesale",
            "subcategory":"Machinery & Supplies",
            "type":"Manufacturing & Wholesale Goods"
        }
    ],
    "sg:phone":"+39 0445 314324",
    "sg:postcode":"36010",
    "sg:province":"Vicenza",
    "sg:tags":[
        "equipment",
        "precision"
    ],
    "wof:name":"Tekno System (s.r.l.)",
    "wof:placetype":"venue"
},
  "geometry": {"coordinates":[11.4422607422,45.7391052246],"type":"Point"}
}