{
  "type": "Feature",
  "properties": {
    "addr:full":"21013 Gallarate Gallarate Varese 21013",
    "addr:postcode":"21013;21013",
    "iso:country":"IT",
    "sg:address":"21013 Gallarate",
    "sg:city":"Gallarate",
    "sg:orig_category":"Fisiokinesiterapia",
    "sg:phone":"+39 0331 792606",
    "sg:postcode":"21013",
    "sg:province":"Varese",
    "wof:name":"Studio Di Riabilitazione E Terapia Fisica Di Caletti Maria Grazia",
    "wof:placetype":"venue"
},
  "geometry": {"coordinates":[8.8265571594,45.8212471008],"type":"Point"}
}