{
  "type": "Feature",
  "properties": {
    "iso:country":"IT",
    "sg:address":"10, Via Carnevale Salvatore 00043 Ciampino",
    "sg:city":"Ciampino",
    "sg:classifiers":[
        {
            "category":"Food & Beverages",
            "subcategory":"Groceries & Convenience Stores",
            "type":"Retail Goods"
        }
    ],
    "sg:phone":"+39 06 7932 1401",
    "sg:postcode":"00043",
    "sg:province":"Roma",
    "sg:tags":[
        "drink"
    ],
    "wof:name":"Partesa Roma Srl",
    "wof:placetype":"venue"
},
  "geometry": {"coordinates":[12.587554,41.81974],"type":"Point"}
}