{
  "type": "Feature",
  "properties": {
    "iso:country":"IT",
    "sg:address":"168, Via Primaticcio Francesco 20147 Milano",
    "sg:city":"Milano",
    "sg:classifiers":[
        {
            "category":"Manufacturing",
            "subcategory":"Tools & Machinery",
            "type":"Manufacturing & Wholesale Goods"
        }
    ],
    "sg:phone":"+39 02 4830 2989",
    "sg:postcode":"20147",
    "sg:province":"Milano",
    "sg:tags":[
        "environment",
        "equipment",
        "-"
    ],
    "wof:name":"Kwi Italia Srl",
    "wof:placetype":"venue"
},
  "geometry": {"coordinates":[9.134661,45.451672],"type":"Point"}
}