{
  "type": "Feature",
  "properties": {
    "iso:country":"IT",
    "sg:address":"19, Viale De' Brozzi 48022 Lugo",
    "sg:city":"Lugo",
    "sg:classifiers":[
        {
            "category":"Shopping",
            "type":"Retail Goods"
        }
    ],
    "sg:phone":"+39 39054522205",
    "sg:postcode":"48022",
    "sg:province":"Ravenna",
    "sg:tags":[
        "finished",
        "-",
        "metallic"
    ],
    "wof:name":"R. Garotti & Figlio S.r.l.",
    "wof:placetype":"venue"
},
  "geometry": {"coordinates":[11.9029254913,44.423992157],"type":"Point"}
}