{
  "type": "Feature",
  "properties": {
    "addr:full":"39056 Nova Levante Nova Levante Bolzano/Bozen 39056",
    "addr:postcode":"39056;39056",
    "iso:country":"IT",
    "sg:address":"39056 Nova Levante",
    "sg:city":"Nova Levante",
    "sg:orig_category":"Decoratori",
    "sg:phone":"+39 0471 613521",
    "sg:postcode":"39056",
    "sg:province":"Bolzano/Bozen",
    "wof:name":"Fratelli Kafmann Snc",
    "wof:placetype":"venue"
},
  "geometry": {"coordinates":[11.552994,46.424362],"type":"Point"}
}