{
  "type": "Feature",
  "properties": {
    "iso:country":"IT",
    "sg:address":"Via Combattenti 8 21058 Solbiate Olona",
    "sg:city":"Solbiate Olona",
    "sg:classifiers":[
        {
            "category":"Communications",
            "subcategory":"Film & Video Production",
            "type":"Services"
        }
    ],
    "sg:phone":"+39 0331 376456",
    "sg:postcode":"21058",
    "sg:province":"Varese",
    "sg:tags":[
        "tape",
        "masking"
    ],
    "wof:name":"Euro Naster Srl",
    "wof:placetype":"venue"
},
  "geometry": {"coordinates":[8.885696,45.771664],"type":"Point"}
}