{
  "type": "Feature",
  "properties": {
    "iso:country":"IT",
    "sg:address":"18, Via Bovisasca 20026 Novate Milanese",
    "sg:city":"Novate Milanese",
    "sg:classifiers":[
        {
            "category":"Home & Garden",
            "subcategory":"Home Furnishings",
            "type":"Retail Goods"
        }
    ],
    "sg:phone":"+39 39023546741",
    "sg:postcode":"20026",
    "sg:province":"Milano",
    "sg:tags":[
        "household"
    ],
    "wof:name":"C.p.e. (s.r.l.)",
    "wof:placetype":"venue"
},
  "geometry": {"coordinates":[9.147978,45.527077],"type":"Point"}
}