{
  "type": "Feature",
  "properties": {
    "iso:country":"IT",
    "sg:address":"70010 Casamassima",
    "sg:city":"Casamassima",
    "sg:orig_category":"Prodotti Alimentari",
    "sg:phone":"+39 080 697 0005",
    "sg:postcode":"70010",
    "sg:province":"Bari",
    "wof:name":"Avicola Iacovo (s.n.c.)",
    "wof:placetype":"venue"
},
  "geometry": {"coordinates":[16.9181346893,40.9553070068],"type":"Point"}
}