{
  "type": "Feature",
  "properties": {
    "iso:country":"IT",
    "sg:address":"00065 Fiano Romano",
    "sg:city":"Fiano Romano",
    "sg:orig_category":"Forniture Alberghi, Bar, Ristoranti E Comunita'",
    "sg:phone":"+39 0765 455299",
    "sg:postcode":"00065",
    "sg:province":"Roma",
    "wof:name":"Nuova Folati Dry Cleaning Srl",
    "wof:placetype":"venue"
},
  "geometry": {"coordinates":[12.5854558945,42.1369514465],"type":"Point"}
}