{
  "type": "Feature",
  "properties": {
    "addr:full":"20131 Milano Milano Milano 20131",
    "addr:postcode":"20131;20131",
    "iso:country":"IT",
    "sg:address":"20131 Milano",
    "sg:city":"Milano",
    "sg:orig_category":"Servizi E Lavori Per Abbigliamento E Pelletterie",
    "sg:phone":"+39 02 2940 5357",
    "sg:postcode":"20131",
    "sg:province":"Milano",
    "wof:name":"Madame Viviani",
    "wof:placetype":"venue"
},
  "geometry": {"coordinates":[9.217825,45.483204],"type":"Point"}
}