{
  "type": "Feature",
  "properties": {
    "iso:country":"IT",
    "sg:address":"00195 Roma",
    "sg:city":"Roma",
    "sg:orig_category":"Arti Grafiche",
    "sg:phone":"+39 06 3751 4652",
    "sg:postcode":"00195",
    "sg:province":"Roma",
    "wof:name":"Loffari Bruno",
    "wof:placetype":"venue"
},
  "geometry": {"coordinates":[12.753893,41.835587],"type":"Point"}
}