{
  "type": "Feature",
  "properties": {
    "iso:country":"IT",
    "sg:address":"5, Via Abba Cesare 95122 Catania",
    "sg:city":"Catania",
    "sg:classifiers":[
        {
            "category":"Home & Garden",
            "subcategory":"Home Furnishings",
            "type":"Retail Goods"
        }
    ],
    "sg:phone":"+39 39095454086",
    "sg:postcode":"95122",
    "sg:province":"Catania",
    "sg:tags":[
        "household"
    ],
    "wof:name":"Di Mauro",
    "wof:placetype":"venue"
},
  "geometry": {"coordinates":[15.052819,37.501465],"type":"Point"}
}