{
  "type": "Feature",
  "properties": {
    "iso:country":"IT",
    "sg:address":"06128 Perugia",
    "sg:city":"Perugia",
    "sg:orig_category":"Macchine, Impianti E Forniture Per Industria Grafica, Cartaria E Cartotecnica. Automazione E Macchine Per Ufficio",
    "sg:phone":"+39 075 500 2399",
    "sg:postcode":"06128",
    "sg:province":"Perugia",
    "wof:name":"Area Ufficio 3 Snc",
    "wof:placetype":"venue"
},
  "geometry": {"coordinates":[12.3702,43.095203],"type":"Point"}
}