{
  "type": "Feature",
  "properties": {
    "addr:full":"87062 Cariati Cariati Cosenza 87062",
    "addr:postcode":"87062;87062",
    "iso:country":"IT",
    "sg:address":"87062 Cariati",
    "sg:city":"Cariati",
    "sg:orig_category":"Legno E Semilavorati. Manufatti Edili E Prefabbricati",
    "sg:phone":"+39 0983 96391",
    "sg:postcode":"87062",
    "sg:province":"Cosenza",
    "wof:name":"Russo Giuseppe",
    "wof:placetype":"venue"
},
  "geometry": {"coordinates":[16.283794,39.259956],"type":"Point"}
}