{
  "type": "Feature",
  "properties": {
    "iso:country":"IT",
    "sg:address":"Via San Pietro 6 24030 Barzana",
    "sg:city":"Barzana",
    "sg:classifiers":[
        {
            "category":"Banks & Credit Unions",
            "subcategory":"Investment Brokerage",
            "type":"Services"
        }
    ],
    "sg:phone":"+39 035 549886",
    "sg:postcode":"24030",
    "sg:province":"Bergamo",
    "sg:tags":[
        "wheel",
        "rim",
        "bicycle",
        "moped"
    ],
    "wof:name":"Malvestiti Cerchi - S.a.s. Di Malvestiti Giuseppe E Sabrina",
    "wof:placetype":"venue"
},
  "geometry": {"coordinates":[9.573962,45.729542],"type":"Point"}
}