{
  "type": "Feature",
  "properties": {
    "iso:country":"IT",
    "sg:address":"20145 Milano",
    "sg:city":"Milano",
    "sg:orig_category":"Servizi Culturali E Per Lo Spettacolo. Musica",
    "sg:phone":"+39 02 311614",
    "sg:postcode":"20145",
    "sg:province":"Milano",
    "wof:name":"Clan Luly Di Luly Raffaello",
    "wof:placetype":"venue"
},
  "geometry": {"coordinates":[9.165816,45.476734],"type":"Point"}
}