{
  "type": "Feature",
  "properties": {
    "iso:country":"IT",
    "sg:address":"50125 Firenze",
    "sg:city":"Firenze",
    "sg:orig_category":"Impianti, Attrezzature E Forniture Sanitarie Ed Ospedaliere",
    "sg:phone":"+39 055 221603",
    "sg:postcode":"50125",
    "sg:province":"Firenze",
    "sg:website":"http://www.mattioli.it",
    "wof:name":"Mattioli Engineering Italia Srl",
    "wof:placetype":"venue"
},
  "geometry": {"coordinates":[11.258047,43.74371],"type":"Point"}
}