{
  "type": "Feature",
  "properties": {
    "iso:country":"IT",
    "sg:address":"00192 Roma",
    "sg:city":"Roma",
    "sg:orig_category":"Biancheria, Telerie E Coperte. Arredo Camera Letto E Complementi",
    "sg:phone":"+39 06 320 4987",
    "sg:postcode":"00192",
    "sg:province":"Roma",
    "wof:name":"Domus Decor Di Ellen Kjellegaard Jensen",
    "wof:placetype":"venue"
},
  "geometry": {"coordinates":[12.46242,41.909019],"type":"Point"}
}