{
  "type": "Feature",
  "properties": {
    "iso:country":"IT",
    "sg:address":"12047 Rocca De'baldi",
    "sg:orig_category":"Acciaierie E Fonderie",
    "sg:phone":"+39 0174 588004",
    "sg:postcode":"12047",
    "sg:province":"Cuneo",
    "wof:name":"Fond Stamp Spa",
    "wof:placetype":"venue"
},
  "geometry": {"coordinates":[7.760922,44.423386],"type":"Point"}
}