{
  "type": "Feature",
  "properties": {
    "addr:full":"16165 Genova Genova Genova 16165",
    "addr:housenumber":"16165",
    "addr:postcode":"16165",
    "iso:country":"IT",
    "sg:address":"16165 Genova",
    "sg:city":"Genova",
    "sg:orig_category":"Minuterie Metalliche E Ferramenta",
    "sg:phone":"+39 010 809388",
    "sg:postcode":"16165",
    "sg:province":"Genova",
    "wof:name":"Ci.f.all. Srl",
    "wof:placetype":"venue"
},
  "geometry": {"coordinates":[9.0184183121,44.4614715576],"type":"Point"}
}