{
  "type": "Feature",
  "properties": {
    "addr:full":"Via Ponte Di Sotto 26 33070 Brugnera Brugnera Pordenone 33070",
    "addr:housenumber":"26",
    "addr:postcode":"33070;33070",
    "addr:street":"Via Ponte Di Sotto",
    "iso:country":"IT",
    "sg:address":"Via Ponte Di Sotto 26 33070 Brugnera",
    "sg:city":"Brugnera",
    "sg:classifiers":[
        {
            "category":"Shopping",
            "subcategory":"Stationery & Office Supplies",
            "type":"Retail Goods"
        }
    ],
    "sg:phone":"+39 0434 613140",
    "sg:postcode":"33070",
    "sg:province":"Pordenone",
    "sg:tags":[
        "packaging"
    ],
    "sg:website":"www.perpack.it",
    "wof:name":"Perpack Srl",
    "wof:placetype":"venue"
},
  "geometry": {"coordinates":[12.5225868225,45.8989067078],"type":"Point"}
}