{
  "type": "Feature",
  "properties": {
    "iso:country":"IT",
    "sg:address":"06069 Tuoro Sul Trasimeno",
    "sg:city":"Tuoro sul Trasimeno",
    "sg:orig_category":"Antiquariato",
    "sg:phone":"+39 075 826183",
    "sg:postcode":"06069",
    "sg:province":"Perugia",
    "wof:name":"Bottega D'arte Antica Snc",
    "wof:placetype":"venue"
},
  "geometry": {"coordinates":[12.070982,43.20063],"type":"Point"}
}