{
  "type": "Feature",
  "properties": {
    "iso:country":"IT",
    "sg:address":"Via Gagarin, 13; Bologna; 40131",
    "sg:city":"Bologna",
    "sg:classifiers":[
        {
            "category":"Banks & Credit Unions",
            "subcategory":"Bank",
            "type":"Services"
        }
    ],
    "sg:phone":"+39 051 634 4644",
    "sg:postcode":"40131",
    "sg:province":"Bologna",
    "wof:name":"Banca Del Monte",
    "wof:placetype":"venue"
},
  "geometry": {"coordinates":[11.331203,44.517014],"type":"Point"}
}