{
  "type": "Feature",
  "properties": {
    "iso:country":"IT",
    "sg:address":"Via Pasquale Grimaldi 84010 Sant'egidio Del Monte Albino",
    "sg:classifiers":[
        {
            "category":"Manufacturing",
            "subcategory":"Lumber",
            "type":"Manufacturing & Wholesale Goods"
        }
    ],
    "sg:phone":"+39 39081917817",
    "sg:postcode":"84010",
    "sg:province":"Salerno",
    "sg:tags":[
        "wood"
    ],
    "wof:name":"Bottaro & F.lli Napodano S.n.c.",
    "wof:placetype":"venue"
},
  "geometry": {"coordinates":[14.591718,40.741268],"type":"Point"}
}