{
  "type": "Feature",
  "properties": {
    "addr:full":"46030 Virgilio Cerese Mantova 46030",
    "addr:postcode":"46030;46030",
    "addr:street":"Virgilio Cerese",
    "iso:country":"IT",
    "sg:address":"46030 Virgilio",
    "sg:city":"Cerese",
    "sg:orig_category":"Impiantistica E Prodotti Tecnologici Per Edilizia. Elettrotecnica Industriale, Prodotti E Apparecchiature. Elettrotecnica Professionale E Di Consumo",
    "sg:phone":"+39 0376 440424",
    "sg:postcode":"46030",
    "sg:province":"Mantova",
    "sg:website":"http://www.tecnika.it",
    "wof:name":"Tecnika Di Peri Roberto & C. Snc",
    "wof:placetype":"venue"
},
  "geometry": {"coordinates":[10.802275,45.137447],"type":"Point"}
}