{
  "type": "Feature",
  "properties": {
    "addr:full":"80147 Napoli Napoli Napoli 80147",
    "addr:postcode":"80147;80147",
    "iso:country":"IT",
    "sg:address":"80147 Napoli",
    "sg:city":"Napoli",
    "sg:orig_category":"Macchine, Impianti Ed Attrezzature Industria Chimica. Impiantistica E Prodotti Tecnologici Per Edilizia. Impianti, Attrezzature E Forniture Sanitarie Ed Ospedaliere",
    "sg:phone":"+39 081 752 7346",
    "sg:postcode":"80147",
    "sg:province":"Napoli",
    "wof:name":"Italcoel",
    "wof:placetype":"venue"
},
  "geometry": {"coordinates":[14.343801,40.865173],"type":"Point"}
}