{
  "type": "Feature",
  "properties": {
    "iso:country":"IT",
    "sg:address":"30, Corso Zanussi Lino 33080 Porcia",
    "sg:city":"Porcia",
    "sg:classifiers":[
        {
            "category":"Shopping",
            "subcategory":"Computers & Home Electronics",
            "type":"Retail Goods"
        }
    ],
    "sg:phone":"+39 390 434 3961",
    "sg:postcode":"33080",
    "sg:province":"Pordenone",
    "sg:tags":[
        "electronic",
        "electrical",
        "equipment"
    ],
    "wof:name":"Electrolux Home Products Italy S.p.a.",
    "wof:placetype":"venue"
},
  "geometry": {"coordinates":[12.617988,45.96841],"type":"Point"}
}