{
  "type": "Feature",
  "properties": {
    "addr:full":"10040 Rubiana Rubiana Torino 10040",
    "addr:housenumber":"10040",
    "addr:postcode":"10040",
    "addr:street":"Rubiana Rubiana",
    "iso:country":"IT",
    "sg:address":"10040 Rubiana",
    "sg:city":"Rubiana",
    "sg:orig_category":"Servizi E Lavori Per Edilizia E Lavori Pubblici. Acqua, Luce, Gas E Societa' Di Esercizio Pubblico",
    "sg:phone":"+39 011 935 6049",
    "sg:postcode":"10040",
    "sg:province":"Torino",
    "wof:name":"Acque Potabili S.p.a.",
    "wof:placetype":"venue"
},
  "geometry": {"coordinates":[7.290798,44.871872],"type":"Point"}
}