{
  "type": "Feature",
  "properties": {
    "addr:full":"55100 Lucca Lucca Lucca 55100",
    "addr:postcode":"55100;55100",
    "iso:country":"IT",
    "sg:address":"55100 Lucca",
    "sg:city":"Lucca",
    "sg:orig_category":"Accessori Moda D'abbigliamento",
    "sg:phone":"+39 0583 580278",
    "sg:postcode":"55100",
    "sg:province":"Lucca",
    "sg:website":"http://www.boccicappellificio.com",
    "wof:name":"Berrettificio Cappellificio Bocci Srl",
    "wof:placetype":"venue"
},
  "geometry": {"coordinates":[10.503563,43.835316],"type":"Point"}
}