{
  "type": "Feature",
  "properties": {
    "iso:country":"IT",
    "sg:address":"12030 Sanfront",
    "sg:city":"Sanfront",
    "sg:orig_category":"Materiali Edili. Forniture Per Attivita' Industriali",
    "sg:phone":"+39 0175 948162",
    "sg:postcode":"12030",
    "sg:province":"Cuneo",
    "wof:name":"Dossetto Giuseppe",
    "wof:placetype":"venue"
},
  "geometry": {"coordinates":[7.318799,44.645123],"type":"Point"}
}