{
  "type": "Feature",
  "properties": {
    "iso:country":"IT",
    "sg:address":"20038 Seregno",
    "sg:city":"Seregno",
    "sg:orig_category":"Arredo Cucina Ed Elettrodomestici. Elettrodomestici",
    "sg:phone":"+39 036 223 6551",
    "sg:postcode":"20038",
    "sg:province":"Milano",
    "wof:name":"F.lli Martinelli Snc",
    "wof:placetype":"venue"
},
  "geometry": {"coordinates":[9.144778,45.472294],"type":"Point"}
}