{
  "type": "Feature",
  "properties": {
    "iso:country":"IT",
    "sg:address":"00042 Anzio",
    "sg:city":"Anzio",
    "sg:orig_category":"Scuole E Servizi Scolastici. Servizi Per Lo Sport E Il Tempo Libero",
    "sg:phone":"+39 06 984 5345",
    "sg:postcode":"00042",
    "sg:province":"Roma",
    "wof:name":"Lega Navale Italiana Sezione Di Anzio",
    "wof:placetype":"venue"
},
  "geometry": {"coordinates":[12.61014,41.511349],"type":"Point"}
}