{
  "type": "Feature",
  "properties": {
    "iso:country":"IT",
    "sg:address":"20093 Cologno Monzese",
    "sg:city":"Cologno Monzese",
    "sg:orig_category":"Servizi E Lavori Per Ecologia E Smaltimento Rifiuti. Acqua, Luce, Gas E Societa' Di Esercizio Pubblico",
    "sg:phone":"+39 02 254 4793",
    "sg:postcode":"20093",
    "sg:province":"Milano",
    "wof:name":"Waste Management Italia Spa",
    "wof:placetype":"venue"
},
  "geometry": {"coordinates":[9.267108,45.531631],"type":"Point"}
}