{
  "type": "Feature",
  "properties": {
    "iso:country":"IT",
    "sg:address":"20052 Monza",
    "sg:city":"Monza",
    "sg:orig_category":"Prodotti Di Base E Forniture Per Industria Alimentare E Bevande. Carta, Cartone E Prodotti Primari. Forniture Per Attivita' Commerciali Ed Artigianali",
    "sg:phone":"+39 039 834189",
    "sg:postcode":"20052",
    "sg:province":"Milano",
    "wof:name":"Carta Snc Di Andreotti Rosella & C.",
    "wof:placetype":"venue"
},
  "geometry": {"coordinates":[9.0503578186,45.5288734436],"type":"Point"}
}