{
  "type": "Feature",
  "properties": {
    "addr:full":"00142 Roma Roma Roma 00142",
    "addr:postcode":"00142;00142",
    "iso:country":"IT",
    "sg:address":"00142 Roma",
    "sg:city":"Roma",
    "sg:orig_category":"Hobbistica",
    "sg:phone":"+39 06 540 8739",
    "sg:postcode":"00142",
    "sg:province":"Roma",
    "wof:name":"Sassone Srl",
    "wof:placetype":"venue"
},
  "geometry": {"coordinates":[12.484698,41.841949],"type":"Point"}
}