{
  "type": "Feature",
  "properties": {
    "iso:country":"IT",
    "sg:address":"Via Privata Liguria, 25/27 20090 Pieve Emanuele",
    "sg:city":"Pieve Emanuele",
    "sg:classifiers":[
        {
            "category":"Home & Garden",
            "subcategory":"Hardware",
            "type":"Retail Goods"
        }
    ],
    "sg:phone":"+39 02 9072 3230",
    "sg:postcode":"20090",
    "sg:province":"Milano",
    "sg:tags":[
        "small",
        "ironware",
        "item"
    ],
    "sg:website":"www.torneriadeco.com",
    "wof:name":"Deco Srl",
    "wof:placetype":"venue"
},
  "geometry": {"coordinates":[9.167212,45.374447],"type":"Point"}
}