{
  "type": "Feature",
  "properties": {
    "iso:country":"IT",
    "sg:address":"06012 Citta'dicastello",
    "sg:orig_category":"Sport And Leisure, Services. Tourism, Services. Motor Vehicles, Auxiliary Services. Transport, Auxiliary Services",
    "sg:phone":"+39 075 857 8251",
    "sg:postcode":"06012",
    "sg:province":"Perugia",
    "wof:name":"Autoservizi Fonti Di Fonti Fabio & C. Sas",
    "wof:placetype":"venue"
},
  "geometry": {"coordinates":[12.231905,43.457787],"type":"Point"}
}