{
  "type": "Feature",
  "properties": {
    "iso:country":"IT",
    "sg:address":"36014 Santorso",
    "sg:city":"Santorso",
    "sg:orig_category":"Prodotti Chimici Di Base",
    "sg:phone":"+39 0445 540241",
    "sg:postcode":"36014",
    "sg:province":"Vicenza",
    "sg:website":"http://www.detercolor.it",
    "wof:name":"Detercolor Srl",
    "wof:placetype":"venue"
},
  "geometry": {"coordinates":[11.4247217178,45.6960067749],"type":"Point"}
}