{
  "type": "Feature",
  "properties": {
    "iso:country":"IT",
    "sg:address":"59, Via Messedaglia Angelo 37069 Villafranca Di Verona",
    "sg:city":"Villafranca di Verona",
    "sg:classifiers":[
        {
            "category":"Home & Garden",
            "subcategory":"Home Furnishings",
            "type":"Retail Goods"
        }
    ],
    "sg:phone":"+39 045 630 3922",
    "sg:postcode":"37069",
    "sg:province":"Verona",
    "sg:tags":[
        "household"
    ],
    "wof:name":"Iris",
    "wof:placetype":"venue"
},
  "geometry": {"coordinates":[10.844815,45.347672],"type":"Point"}
}