{
  "type": "Feature",
  "properties": {
    "iso:country":"IT",
    "sg:address":"20090 Pieve Emanuele",
    "sg:city":"Pieve Emanuele",
    "sg:classifiers":[
        {
            "category":"Manufacturing",
            "subcategory":"Tools & Machinery",
            "type":"Manufacturing & Wholesale Goods"
        }
    ],
    "sg:phone":"+39 02 9072 3489",
    "sg:postcode":"20090",
    "sg:province":"Milano",
    "sg:tags":[
        "material",
        "mechanical"
    ],
    "wof:name":"Drive's Snc",
    "wof:placetype":"venue"
},
  "geometry": {"coordinates":[9.176761,45.370728],"type":"Point"}
}