{
  "type": "Feature",
  "properties": {
    "iso:country":"IT",
    "sg:address":"20124 Milano",
    "sg:city":"Milano",
    "sg:classifiers":[
        {
            "category":"Shopping",
            "subcategory":"Computers & Home Electronics",
            "type":"Retail Goods"
        }
    ],
    "sg:phone":"+39 02 6707 5956",
    "sg:postcode":"20124",
    "sg:province":"Milano",
    "sg:tags":[
        "personal",
        "ed",
        "accessori"
    ],
    "sg:website":"http://www.bytech.it",
    "wof:name":"Bytech Srl",
    "wof:placetype":"venue"
},
  "geometry": {"coordinates":[9.1982536316,45.4872970581],"type":"Point"}
}