{
  "type": "Feature",
  "properties": {
    "addr:full":"20124 Milano Milano Milano 20124",
    "addr:postcode":"20124;20124",
    "iso:country":"IT",
    "sg:address":"20124 Milano",
    "sg:city":"Milano",
    "sg:orig_category":"Materiali E Componenti Elettrotecnici. Elettrotecnica Industriale, Prodotti E Apparecchiature",
    "sg:postcode":"20124",
    "sg:province":"Milano",
    "wof:name":"Terzago L.",
    "wof:placetype":"venue"
},
  "geometry": {"coordinates":[9.198423,45.487419],"type":"Point"}
}