{
  "type": "Feature",
  "properties": {
    "iso:country":"IT",
    "sg:address":"70010 Turi",
    "sg:city":"Turi",
    "sg:orig_category":"Petroli, Gas E Combustibili",
    "sg:phone":"+39 080 891 2227",
    "sg:postcode":"70010",
    "sg:province":"Bari",
    "wof:name":"Fra.ma Petroli & C. Snc",
    "wof:placetype":"venue"
},
  "geometry": {"coordinates":[17.1222038269,40.8528137207],"type":"Point"}
}