{
  "type": "Feature",
  "properties": {
    "addr:full":"10070 Robassomero Robassomero Torino 10070",
    "addr:housenumber":"10070",
    "addr:postcode":"10070",
    "addr:street":"Robassomero Robassomero",
    "iso:country":"IT",
    "sg:address":"10070 Robassomero",
    "sg:city":"Robassomero",
    "sg:orig_category":"Aria Compressa - Impianti Ed Attrezzature",
    "sg:phone":"+39 011 924 6400",
    "sg:postcode":"10070",
    "sg:province":"Torino",
    "sg:website":"http://www.abac.it",
    "wof:name":"Abac Spa",
    "wof:placetype":"venue"
},
  "geometry": {"coordinates":[7.56858,45.200741],"type":"Point"}
}