{
  "type": "Feature",
  "properties": {
    "iso:country":"IT",
    "sg:address":"12041 Bene Vagienna",
    "sg:city":"Bene Vagienna",
    "sg:orig_category":"Caminetti, Forni Da Giardino E Barbecues",
    "sg:phone":"+39 0172 654511",
    "sg:postcode":"12041",
    "sg:province":"Cuneo",
    "wof:name":"Articeram Di Ruggero Rebecchi",
    "wof:placetype":"venue"
},
  "geometry": {"coordinates":[7.83139,44.543526],"type":"Point"}
}