{
  "type": "Feature",
  "properties": {
    "iso:country":"IT",
    "sg:address":"10020 Riva Presso Chieri",
    "sg:city":"Riva presso Chieri",
    "sg:orig_category":"Servizi E Lavori Per Industria Alimentare E Bevande",
    "sg:phone":"+39 011 946 9067",
    "sg:postcode":"10020",
    "sg:province":"Torino",
    "wof:name":"Macinazione Rivese S.a.s.",
    "wof:placetype":"venue"
},
  "geometry": {"coordinates":[7.902556,45.042912],"type":"Point"}
}