{
  "type": "Feature",
  "properties": {
    "iso:country":"IT",
    "sg:address":"42024 Castelnovo Di Sotto",
    "sg:orig_category":"Serramenti Ed Infissi",
    "sg:phone":"+39 0522 683326",
    "sg:postcode":"42024",
    "sg:province":"Reggio Nell'Emilia",
    "wof:name":"Donelli Avvolgibili Di Donelli Costaldo & C. Snc",
    "wof:placetype":"venue"
},
  "geometry": {"coordinates":[10.572768,44.796333],"type":"Point"}
}