{
  "type": "Feature",
  "properties": {
    "addr:full":"3, V. Nazionale 23887 Olgiate Molgora Olgiate Molgora Lecco 23887",
    "addr:housenumber":"3",
    "addr:postcode":"23887;23887",
    "addr:street":"Nazionale",
    "iso:country":"IT",
    "sg:address":"3, V. Nazionale 23887 Olgiate Molgora",
    "sg:city":"Olgiate Molgora",
    "sg:classifiers":[
        {
            "category":"Professional",
            "subcategory":"Engineering",
            "type":"Services"
        }
    ],
    "sg:phone":"+39 039 991 0774",
    "sg:postcode":"23887",
    "sg:province":"Lecco",
    "sg:tags":[
        "machine",
        "-",
        "mechanical"
    ],
    "wof:name":"Vigan\u00d2 Giuseppe",
    "wof:placetype":"venue"
},
  "geometry": {"coordinates":[9.41536,45.72398],"type":"Point"}
}