{
  "type": "Feature",
  "properties": {
    "iso:country":"IT",
    "sg:address":"39, Via Donatori Del Sangue 44015 Portomaggiore",
    "sg:city":"Portomaggiore",
    "sg:classifiers":[
        {
            "category":"Manufacturing",
            "subcategory":"Metals",
            "type":"Manufacturing & Wholesale Goods"
        }
    ],
    "sg:phone":"+39 0532 811991",
    "sg:postcode":"44015",
    "sg:province":"Ferrara",
    "sg:tags":[
        "metallurgy",
        "metalworking"
    ],
    "wof:name":"Fly 2000 S.r.l.",
    "wof:placetype":"venue"
},
  "geometry": {"coordinates":[11.7523002625,44.7667617798],"type":"Point"}
}