{
  "type": "Feature",
  "properties": {
    "iso:country":"IT",
    "sg:address":"20093 Cologno Monzese",
    "sg:city":"Cologno Monzese",
    "sg:orig_category":"Accessori Dei Mezzi Di Trasporto",
    "sg:phone":"+39 02 254 1751",
    "sg:postcode":"20093",
    "sg:province":"Milano",
    "wof:name":"Aliter (s.r.l.)",
    "wof:placetype":"venue"
},
  "geometry": {"coordinates":[9.26615,45.535221],"type":"Point"}
}