{
  "type": "Feature",
  "properties": {
    "addr:full":"Via Donanzola 43 36020 Campiglia Dei Berici Campiglia dei Berici Vicenza 36020",
    "addr:housenumber":"43",
    "addr:postcode":"36020;36020",
    "addr:street":"Via Donanzola;Dei Berici",
    "iso:country":"IT",
    "sg:address":"Via Donanzola 43 36020 Campiglia Dei Berici",
    "sg:city":"Campiglia dei Berici",
    "sg:orig_category":"Poultry, Slaughtered",
    "sg:phone":"+39 0444 767676",
    "sg:postcode":"36020",
    "sg:province":"Vicenza",
    "wof:name":"Ilta Srl",
    "wof:placetype":"venue"
},
  "geometry": {"coordinates":[11.5488376617,45.3330001831],"type":"Point"}
}