{
  "type": "Feature",
  "properties": {
    "iso:country":"IT",
    "sg:address":"30030 Pianiga",
    "sg:city":"Pianiga",
    "sg:orig_category":"Termotecnica E Riscaldamento, Apparecchiature E Servizi",
    "sg:phone":"+39 041 411822",
    "sg:postcode":"30030",
    "sg:province":"Venezia",
    "wof:name":"D.m.c. (s.a.s.) Immobiliare",
    "wof:placetype":"venue"
},
  "geometry": {"coordinates":[12.07111,45.44516],"type":"Point"}
}