{
  "type": "Feature",
  "properties": {
    "iso:country":"IT",
    "sg:address":"16122 Genova",
    "sg:city":"Genova",
    "sg:orig_category":"Elettrotecnica Industriale, Prodotti E Apparecchiature. Forniture Per Attivita' Commerciali Ed Artigianali",
    "sg:phone":"+39 010 839 2465",
    "sg:postcode":"16122",
    "sg:province":"Genova",
    "wof:name":"Neon Sarie Sas",
    "wof:placetype":"venue"
},
  "geometry": {"coordinates":[8.945247,44.415386],"type":"Point"}
}