{
  "type": "Feature",
  "properties": {
    "iso:country":"IT",
    "sg:address":"10, Localita' Ensegua' 38050 Scurelle",
    "sg:city":"Scurelle",
    "sg:classifiers":[
        {
            "category":"Shopping",
            "subcategory":"Clothing, Apparel, & Fashions",
            "type":"Retail Goods"
        }
    ],
    "sg:phone":"+39 0461 763311",
    "sg:postcode":"38050",
    "sg:province":"Trento",
    "sg:tags":[
        "clothes"
    ],
    "wof:name":"Sinergy Group S.r.l.",
    "wof:placetype":"venue"
},
  "geometry": {"coordinates":[11.514174,46.059708],"type":"Point"}
}