{
  "type": "Feature",
  "properties": {
    "addr:full":"21, Via Martiri Della Liberta' 10095 Grugliasco Grugliasco Torino 10095",
    "addr:postcode":"10095;10095",
    "addr:street":"Via Martiri Della Liberta '",
    "iso:country":"IT",
    "sg:address":"21, Via Martiri Della Liberta' 10095 Grugliasco",
    "sg:city":"Grugliasco",
    "sg:classifiers":[
        {
            "category":"Utilities",
            "subcategory":"Telephone",
            "type":"Services"
        }
    ],
    "sg:phone":"+39 39011785067",
    "sg:postcode":"10095",
    "sg:province":"Torino",
    "sg:tags":[
        "telecommunication"
    ],
    "wof:name":"Computherm (s.n.c.)",
    "wof:placetype":"venue"
},
  "geometry": {"coordinates":[7.574609,45.086971],"type":"Point"}
}