{
  "type": "Feature",
  "properties": {
    "iso:country":"IT",
    "sg:address":"20090 Opera",
    "sg:city":"Opera",
    "sg:orig_category":"Forniture E Prodotti Informatici. Forniture Per Uffici",
    "sg:phone":"+39 02 530111",
    "sg:postcode":"20090",
    "sg:province":"Milano",
    "sg:website":"http://www.eso.it",
    "wof:name":"Eso Ecological Services Outsourcing Srl",
    "wof:placetype":"venue"
},
  "geometry": {"coordinates":[9.2229595184,45.3797073364],"type":"Point"}
}