{
  "type": "Feature",
  "properties": {
    "iso:country":"IT",
    "sg:address":"20122 Milano",
    "sg:city":"Milano",
    "sg:orig_category":"Articoli Medico-sanitari Ed Ortopedici",
    "sg:phone":"+39 02 7602 2295",
    "sg:postcode":"20122",
    "sg:province":"Milano",
    "wof:name":"Mercury Compagnia Commerciale Internazionale (s.r.l.)",
    "wof:placetype":"venue"
},
  "geometry": {"coordinates":[9.196534,45.466137],"type":"Point"}
}