{
  "type": "Feature",
  "properties": {
    "iso:country":"IT",
    "sg:address":"14 Via Provinciale, 23813 Cortenova",
    "sg:city":"Cortenova",
    "sg:classifiers":[
        {
            "category":"Banks & Credit Unions",
            "subcategory":"Financial Services",
            "type":"Services"
        }
    ],
    "sg:phone":"+39 0341 901301",
    "sg:postcode":"23813",
    "sg:province":"Lecco",
    "sg:tags":[
        "banking",
        "finance",
        "insurance"
    ],
    "wof:name":"Banca Della Valsassina Credito Cooperativo Scrl",
    "wof:placetype":"venue"
},
  "geometry": {"coordinates":[9.3829374313,46.0063781738],"type":"Point"}
}