{
  "type": "Feature",
  "properties": {
    "iso:country":"IT",
    "sg:address":"10088 Volpiano",
    "sg:city":"Volpiano",
    "sg:classifiers":[
        {
            "category":"Manufacturing",
            "subcategory":"Chemicals & Compounds",
            "type":"Manufacturing & Wholesale Goods"
        }
    ],
    "sg:phone":"+39 011 99571",
    "sg:postcode":"10088",
    "sg:province":"Torino",
    "sg:tags":[
        "product",
        "chemicals",
        "basic"
    ],
    "sg:website":"http://www.tazzetti.com",
    "wof:name":"Guido Tazzetti & C. Spa",
    "wof:placetype":"venue"
},
  "geometry": {"coordinates":[7.766539,45.178349],"type":"Point"}
}