{
  "type": "Feature",
  "properties": {
    "iso:country":"IT",
    "sg:address":"50122 Firenze",
    "sg:city":"Firenze",
    "sg:classifiers":[
        {
            "category":"Restaurant",
            "type":"Food & Drink"
        }
    ],
    "sg:phone":"+39 055 214412",
    "sg:postcode":"50122",
    "sg:province":"Firenze",
    "sg:tags":[
        "auxiliary",
        "entertainment",
        "premises",
        "related",
        "catering",
        "similar",
        "public",
        "restaurants"
    ],
    "wof:name":"Rivoire Srl",
    "wof:placetype":"venue"
},
  "geometry": {"coordinates":[10.747909,43.860737],"type":"Point"}
}