{
  "type": "Feature",
  "properties": {
    "iso:country":"IT",
    "sg:address":"Piazza Castello 14-16; Roseto Valfortore; 71039",
    "sg:city":"Roseto Valfortore",
    "sg:classifiers":[
        {
            "category":"Banks & Credit Unions",
            "subcategory":"Bank",
            "type":"Services"
        }
    ],
    "sg:phone":"+39 0881 994023",
    "sg:postcode":"71039",
    "sg:province":"Foggia",
    "wof:name":"Banco Di Napoli Spa",
    "wof:placetype":"venue"
},
  "geometry": {"coordinates":[15.095017,41.370739],"type":"Point"}
}