{
  "type": "Feature",
  "properties": {
    "addr:full":"79, V. Marconi 12030 Marene Marene Cuneo 12030",
    "addr:housenumber":"79",
    "addr:postcode":"12030;12030",
    "addr:street":"V. Marconi",
    "iso:country":"IT",
    "sg:address":"79, V. Marconi 12030 Marene",
    "sg:city":"Marene",
    "sg:classifiers":[
        {
            "category":"Autos & Motor Vehicles",
            "subcategory":"Automobile Sales",
            "type":"Retail Goods"
        }
    ],
    "sg:phone":"+39 0172 742681",
    "sg:postcode":"12030",
    "sg:province":"Cuneo",
    "sg:tags":[
        "industrial"
    ],
    "sg:website":"http://www.paginegialle.it/dira",
    "wof:name":"Dira Srl",
    "wof:placetype":"venue"
},
  "geometry": {"coordinates":[7.547111,44.388798],"type":"Point"}
}