{
  "type": "Feature",
  "properties": {
    "iso:country":"IT",
    "sg:address":"40, Via Mercatale 50059 Vinci",
    "sg:city":"Vinci",
    "sg:classifiers":[
        {
            "category":"Wholesale",
            "subcategory":"Drugs",
            "type":"Manufacturing & Wholesale Goods"
        }
    ],
    "sg:phone":"+39 39057190361",
    "sg:postcode":"50059",
    "sg:province":"Firenze",
    "sg:tags":[
        "chemical",
        "pharmaceutical"
    ],
    "wof:name":"Syrom Spa",
    "wof:placetype":"venue"
},
  "geometry": {"coordinates":[10.909481,43.756935],"type":"Point"}
}