{
  "type": "Feature",
  "properties": {
    "iso:country":"IT",
    "sg:address":"Via Ronchi Sinistra 15/b 35017 Piombino Dese",
    "sg:city":"Piombino Dese",
    "sg:orig_category":"Kitchen Lamps",
    "sg:phone":"+39 049 936 5207",
    "sg:postcode":"35017",
    "sg:province":"Padova",
    "sg:website":"www.plani.it",
    "wof:name":"Plani Di Mason Snc",
    "wof:placetype":"venue"
},
  "geometry": {"coordinates":[11.876589,45.409569],"type":"Point"}
}