{
  "type": "Feature",
  "properties": {
    "iso:country":"IT",
    "sg:address":"06012 Citta'dicastello",
    "sg:orig_category":"Macchine, Impianti Ed Attrezzature Per Abbigliamento E Pelletterie. Macchine E Impianti Per Attivita' Commerciali Ed Artigianali",
    "sg:phone":"+39 075 862961",
    "sg:postcode":"06012",
    "sg:province":"Perugia",
    "sg:website":"http://www.renzacci.it",
    "wof:name":"Renzacci Spa - Industria Lavatrici",
    "wof:placetype":"venue"
},
  "geometry": {"coordinates":[12.441728,43.131729],"type":"Point"}
}