{
  "type": "Feature",
  "properties": {
    "addr:full":"19125 La Spezia SP",
    "addr:housenumber":"19125",
    "iso:country":"IT",
    "sg:address":"19125 La Spezia",
    "sg:orig_category":"Servizi Per Lo Sport E Il Tempo Libero. Servizi Ausiliari Dei Mezzi Di Trasporto",
    "sg:phone":"+39 0187 515618",
    "sg:province":"SP",
    "wof:name":"Alfanautica Di Gazzanelli Giuseppe & Bartoli Roberto S.n.c.",
    "wof:placetype":"venue"
},
  "geometry": {"coordinates":[9.839995,44.118473],"type":"Point"}
}