{
  "type": "Feature",
  "properties": {
    "addr:full":"167, Via Castel Romano 00128 Roma Roma Roma 00128",
    "addr:housenumber":"167",
    "addr:postcode":"00128;00128",
    "addr:street":"Via Castel Romano",
    "iso:country":"IT",
    "sg:address":"167, Via Castel Romano 00128 Roma",
    "sg:city":"Roma",
    "sg:classifiers":[
        {
            "category":"Utilities",
            "subcategory":"Telephone",
            "type":"Services"
        }
    ],
    "sg:phone":"+39 390 650 2941",
    "sg:postcode":"00128",
    "sg:province":"Roma",
    "sg:tags":[
        "telecommunication"
    ],
    "wof:name":"Urmet Sistemi S.p.a.",
    "wof:placetype":"venue"
},
  "geometry": {"coordinates":[12.559791,42.083408],"type":"Point"}
}