{
  "type": "Feature",
  "properties": {
    "iso:country":"IT",
    "sg:address":"25030 Roncadelle",
    "sg:city":"Roncadelle",
    "sg:orig_category":"Lavorazioni Meccaniche E Servizi",
    "sg:phone":"+39 030 258 3375",
    "sg:postcode":"25030",
    "sg:province":"Brescia",
    "wof:name":"Due P Di Pratesi Carla & C. Snc",
    "wof:placetype":"venue"
},
  "geometry": {"coordinates":[10.159489,45.533195],"type":"Point"}
}