{
  "type": "Feature",
  "properties": {
    "iso:country":"IT",
    "sg:address":"31015 Conegliano",
    "sg:city":"Conegliano",
    "sg:orig_category":"Prodotti Cosmetici E Da Toeletta",
    "sg:phone":"+39 0438 60151",
    "sg:postcode":"31015",
    "sg:province":"Treviso",
    "wof:name":"Boscariol Romano",
    "wof:placetype":"venue"
},
  "geometry": {"coordinates":[12.2214403152,45.6726455688],"type":"Point"}
}