{
  "type": "Feature",
  "properties": {
    "iso:country":"IT",
    "sg:address":"37060 Castel D'azzano",
    "sg:city":"Azzano",
    "sg:orig_category":"Tessuti Arredamento, Tende E Tappeti. Forniture Per Edilizia E Lavori Pubblici",
    "sg:phone":"+39 045 852 1551",
    "sg:postcode":"37060",
    "sg:province":"Verona",
    "wof:name":"Arredauto 2 Srl",
    "wof:placetype":"venue"
},
  "geometry": {"coordinates":[10.961828,45.371185],"type":"Point"}
}