{
  "type": "Feature",
  "properties": {
    "iso:country":"IT",
    "sg:address":"20123 Milano",
    "sg:city":"Milano",
    "sg:orig_category":"Articoli Per Imballaggio E Confezionamento",
    "sg:phone":"+39 02 805 5515",
    "sg:postcode":"20123",
    "sg:province":"Milano",
    "wof:name":"Catu Astucci Srl",
    "wof:placetype":"venue"
},
  "geometry": {"coordinates":[9.185181,45.460793],"type":"Point"}
}