{
  "type": "Feature",
  "properties": {
    "iso:country":"IT",
    "sg:address":"28021 Borgomanero",
    "sg:city":"Borgomanero",
    "sg:orig_category":"Macchine E Forniture Per Ecologia E Smaltimento Rifiuti. Elettrodomestici. Forniture Alle Strutture Ricettive. Macchine, Strumenti Ed Apparecchi Per Attivita' Industriali",
    "sg:phone":"+39 0322 839062",
    "sg:postcode":"28021",
    "sg:province":"Novara",
    "wof:name":"Gruppo Idealimpianti Srl",
    "wof:placetype":"venue"
},
  "geometry": {"coordinates":[8.457661,45.70446],"type":"Point"}
}