{
  "type": "Feature",
  "properties": {
    "iso:country":"IT",
    "sg:address":"71042 Cerignola",
    "sg:city":"Cerignola",
    "sg:orig_category":"Alimentari - Produzione E Ingrosso",
    "sg:phone":"+39 0885 413638",
    "sg:postcode":"71042",
    "sg:province":"Foggia",
    "sg:website":"http://www.cannone.it",
    "wof:name":"Cannone Industrie Alimentari 'gli Antipasti' Srl",
    "wof:placetype":"venue"
},
  "geometry": {"coordinates":[15.92299,41.240726],"type":"Point"}
}