{
  "type": "Feature",
  "properties": {
    "iso:country":"IT",
    "sg:address":"00143 Roma",
    "sg:city":"Roma",
    "sg:orig_category":"Servizi Ausiliari Dei Mezzi Di Trasporto",
    "sg:phone":"+39 06 519 1179",
    "sg:postcode":"00143",
    "sg:province":"Roma",
    "wof:name":"Lucia Guido",
    "wof:placetype":"venue"
},
  "geometry": {"coordinates":[12.509315,41.823536],"type":"Point"}
}