{
  "type": "Feature",
  "properties": {
    "iso:country":"IT",
    "sg:address":"09076 Sedilo",
    "sg:city":"Sedilo",
    "sg:orig_category":"Cartotecnica E Servizi. Articoli Per Imballaggio E Confezionamento",
    "sg:phone":"+39 0785 59306",
    "sg:postcode":"09076",
    "sg:province":"Oristano",
    "wof:name":"Tecnografica Srl",
    "wof:placetype":"venue"
},
  "geometry": {"coordinates":[8.594874,39.89962],"type":"Point"}
}