{
  "type": "Feature",
  "properties": {
    "addr:full":"13, Via Scuderie 39012 Merano Merano Bolzano/Bozen 39012",
    "addr:postcode":"39012;39012",
    "addr:street":"Via Scuderie",
    "iso:country":"IT",
    "sg:address":"13, Via Scuderie 39012 Merano",
    "sg:city":"Merano",
    "sg:classifiers":[
        {
            "category":"Manufacturing",
            "subcategory":"Lumber",
            "type":"Manufacturing & Wholesale Goods"
        }
    ],
    "sg:phone":"+39 0473 221724",
    "sg:postcode":"39012",
    "sg:province":"Bolzano/Bozen",
    "sg:tags":[
        "wood"
    ],
    "wof:name":"Haller Rudolf S.r.l.",
    "wof:placetype":"venue"
},
  "geometry": {"coordinates":[11.150008,46.65546],"type":"Point"}
}