{
  "type": "Feature",
  "properties": {
    "iso:country":"IT",
    "sg:address":"95021 Aci Castello",
    "sg:city":"Aci Castello",
    "sg:orig_category":"Nautica. Automobili E Mezzi Di Trasporto",
    "sg:phone":"+39 095 712 7726",
    "sg:postcode":"95021",
    "sg:province":"Catania",
    "wof:name":"Euromotomarine",
    "wof:placetype":"venue"
},
  "geometry": {"coordinates":[15.129108,37.543755],"type":"Point"}
}