{
  "type": "Feature",
  "properties": {
    "iso:country":"IT",
    "sg:address":"29, Via Vittorio Veneto 20099 Sesto San Giovanni",
    "sg:city":"Sesto San Giovanni",
    "sg:classifiers":[
        {
            "category":"Professional",
            "subcategory":"Printing & Photocopies",
            "type":"Services"
        }
    ],
    "sg:phone":"+39 02 2247 0078",
    "sg:postcode":"20099",
    "sg:province":"Milano",
    "wof:name":"Arti Grafiche G. Beveresco (s.r.l.)",
    "wof:placetype":"venue"
},
  "geometry": {"coordinates":[9.2351751328,45.5360527039],"type":"Point"}
}