{
  "type": "Feature",
  "properties": {
    "iso:country":"IT",
    "sg:address":"23801 Calolziocorte",
    "sg:city":"Calolziocorte",
    "sg:orig_category":"Serrature, Lucchetti E Chiavi",
    "sg:phone":"+39 0341 631500",
    "sg:postcode":"23801",
    "sg:province":"Lecco",
    "sg:website":"http://www.bonaiti.com",
    "wof:name":"Bonaiti Serrature Spa",
    "wof:placetype":"venue"
},
  "geometry": {"coordinates":[9.417506,45.867928],"type":"Point"}
}