{
  "type": "Feature",
  "properties": {
    "addr:full":"13, Viale Galileo Galilei 36066 Sandrigo Sandrigo Vicenza 36066",
    "addr:housenumber":"13",
    "addr:postcode":"36066;36066",
    "addr:street":"Viale Galileo Galilei",
    "iso:country":"IT",
    "sg:address":"13, Viale Galileo Galilei 36066 Sandrigo",
    "sg:city":"Sandrigo",
    "sg:classifiers":[
        {
            "category":"Manufacturing",
            "subcategory":"Rubber & Plastics",
            "type":"Manufacturing & Wholesale Goods"
        }
    ],
    "sg:phone":"+39 0444 461444",
    "sg:postcode":"36066",
    "sg:province":"Vicenza",
    "wof:name":"Nuova Isotex S.p.a.",
    "wof:placetype":"venue"
},
  "geometry": {"coordinates":[11.5502319336,45.6331481934],"type":"Point"}
}