{
  "type": "Feature",
  "properties": {
    "addr:full":"40, Via Decorati Valor Militare 41100 Modena Modena Modena 41100",
    "addr:postcode":"41100;41100",
    "addr:street":"Via Decorati Valor Militare",
    "iso:country":"IT",
    "sg:address":"40, Via Decorati Valor Militare 41100 Modena",
    "sg:city":"Modena",
    "sg:classifiers":[
        {
            "category":"Manufacturing",
            "subcategory":"Motor Vehicles & Parts",
            "type":"Manufacturing & Wholesale Goods"
        }
    ],
    "sg:phone":"+39 39059512121",
    "sg:postcode":"41100",
    "sg:province":"Modena",
    "sg:tags":[
        "engine"
    ],
    "wof:name":"Oral Engineering Srl",
    "wof:placetype":"venue"
},
  "geometry": {"coordinates":[10.865664,44.608841],"type":"Point"}
}