{
  "type": "Feature",
  "properties": {
    "iso:country":"IT",
    "sg:address":"Via Volta 14 35030 Veggiano",
    "sg:city":"Veggiano",
    "sg:classifiers":[
        {
            "category":"Sports & Exercise",
            "subcategory":"Bicycle Rental",
            "type":"Entertainment"
        }
    ],
    "sg:phone":"+39 049 900 3098",
    "sg:postcode":"35030",
    "sg:province":"Padova",
    "sg:tags":[
        "boot",
        "shoes",
        "leisure"
    ],
    "sg:website":"www.sportservicesas.it",
    "wof:name":"Sportservice Sas Di Corradini Pierantonio & C.",
    "wof:placetype":"venue"
},
  "geometry": {"coordinates":[11.115941,45.418343],"type":"Point"}
}