{
  "type": "Feature",
  "properties": {
    "iso:country":"IT",
    "sg:address":"20037 Paderno Dugnano",
    "sg:city":"Paderno Dugnano",
    "sg:orig_category":"Carni, Salumi E Pesci",
    "sg:phone":"+39 02 910 1288",
    "sg:postcode":"20037",
    "sg:province":"Milano",
    "wof:name":"Triggiani Gaetano",
    "wof:placetype":"venue"
},
  "geometry": {"coordinates":[9.188232,45.56982],"type":"Point"}
}