{
  "type": "Feature",
  "properties": {
    "addr:full":"28, V. Cannola Al Trivio 80141 Napoli Napoli Napoli 80141",
    "addr:housenumber":"28",
    "addr:postcode":"80141;80141",
    "addr:street":"V. Cannola Al Trivio",
    "iso:country":"IT",
    "sg:address":"28, V. Cannola Al Trivio 80141 Napoli",
    "sg:city":"Napoli",
    "sg:classifiers":[
        {
            "category":"Shopping",
            "subcategory":"Computers & Home Electronics",
            "type":"Retail Goods"
        }
    ],
    "sg:phone":"+39 081 780 2363",
    "sg:postcode":"80141",
    "sg:province":"Napoli",
    "sg:tags":[
        "electronic",
        "electrical",
        "equipment"
    ],
    "sg:website":"http://www.oralight.it",
    "wof:name":"Ora Light Srl",
    "wof:placetype":"venue"
},
  "geometry": {"coordinates":[14.265759,40.873257],"type":"Point"}
}