{
  "type": "Feature",
  "properties": {
    "addr:full":"22, Via Bonagge 36065 Mussolente Mussolente Vicenza 36065",
    "addr:postcode":"36065;36065",
    "addr:street":"Via Bonagge",
    "iso:country":"IT",
    "sg:address":"22, Via Bonagge 36065 Mussolente",
    "sg:city":"Mussolente",
    "sg:classifiers":[
        {
            "category":"Food & Beverages",
            "subcategory":"Groceries & Convenience Stores",
            "type":"Retail Goods"
        }
    ],
    "sg:phone":"+39 0424 577188",
    "sg:postcode":"36065",
    "sg:province":"Vicenza",
    "sg:tags":[
        "product",
        "related"
    ],
    "wof:name":"Industria Alimentare Ferraro (s.r.l.)",
    "wof:placetype":"venue"
},
  "geometry": {"coordinates":[11.8074531555,45.7852630615],"type":"Point"}
}