{
  "type": "Feature",
  "properties": {
    "iso:country":"IT",
    "sg:address":"41100 Modena",
    "sg:city":"Modena",
    "sg:classifiers":[
        {
            "category":"Health Services",
            "subcategory":"Health Practitioner",
            "type":"Services"
        }
    ],
    "sg:phone":"+39 059 305772",
    "sg:postcode":"41100",
    "sg:province":"Modena",
    "sg:tags":[
        "medici"
    ],
    "wof:name":"Passalacqua Marilena",
    "wof:placetype":"venue"
},
  "geometry": {"coordinates":[10.9347085953,44.6371421814],"type":"Point"}
}