{
  "type": "Feature",
  "properties": {
    "iso:country":"IT",
    "sg:address":"50121 Firenze",
    "sg:city":"Firenze",
    "sg:orig_category":"Professionisti - Studi E Servizi Ed Associazioni Di Interesse Aziendale. Associazioni Ed Organismi Di Interesse Pubblico",
    "sg:phone":"+39 055 27551",
    "sg:postcode":"50121",
    "sg:province":"Firenze",
    "sg:website":"http://www.arsia.toscana.it",
    "wof:name":"Arsia - Ag. Reg. Per Lo Sviluppo E L'innovazione Nel Settore Agricolo-forestale",
    "wof:placetype":"venue"
},
  "geometry": {"coordinates":[11.262462616,43.7713623047],"type":"Point"}
}