{
  "type": "Feature",
  "properties": {
    "addr:full":"50145 Firenze Firenze Firenze 50145",
    "addr:postcode":"50145;50145",
    "iso:country":"IT",
    "sg:address":"50145 Firenze",
    "sg:city":"Firenze",
    "sg:orig_category":"Macchine, Strumenti Ed Apparecchi Per Attivita' Industriali",
    "sg:phone":"+39 055 343 7124",
    "sg:postcode":"50145",
    "sg:province":"Firenze",
    "wof:name":"Seico Di R. Santoni",
    "wof:placetype":"venue"
},
  "geometry": {"coordinates":[11.191176,43.799046],"type":"Point"}
}