{
  "type": "Feature",
  "properties": {
    "addr:full":"00149 Roma Roma Roma 00149",
    "addr:postcode":"00149;00149",
    "iso:country":"IT",
    "sg:address":"00149 Roma",
    "sg:city":"Roma",
    "sg:orig_category":"Macchine E Forniture Per Ecologia E Smaltimento Rifiuti",
    "sg:phone":"+39 06 5526 2981",
    "sg:postcode":"00149",
    "sg:province":"Roma",
    "sg:website":"http://www.acquatecnica.com",
    "wof:name":"Acquatecnica Srl",
    "wof:placetype":"venue"
},
  "geometry": {"coordinates":[12.44765,41.853214],"type":"Point"}
}