{
  "type": "Feature",
  "properties": {
    "iso:country":"IT",
    "sg:address":"56017 Madonna Dell'acqua",
    "sg:orig_category":"Forniture Industriali Per Prevenzione, Controllo E Sicurezza",
    "sg:phone":"+39 050 890564",
    "sg:postcode":"56017",
    "sg:province":"Pisa",
    "wof:name":"Artigianguanto (s.n.c.)",
    "wof:placetype":"venue"
},
  "geometry": {"coordinates":[10.3715982437,43.7441291809],"type":"Point"}
}