{
  "type": "Feature",
  "properties": {
    "iso:country":"IT",
    "sg:address":"10154 Torino",
    "sg:city":"Torino",
    "sg:orig_category":"Valvole E Apparecchiature Di Misura. Attrezzature E Forniture Per Officine Riparazione E Servizi Ausiliari. Macchine, Strumenti Ed Apparecchi Per Attivita' Industriali",
    "sg:phone":"+39 011 855719",
    "sg:postcode":"10154",
    "sg:province":"Torino",
    "wof:name":"Sofca Project Di Alessandrino Giuseppe",
    "wof:placetype":"venue"
},
  "geometry": {"coordinates":[7.702857,45.085785],"type":"Point"}
}