{
  "type": "Feature",
  "properties": {
    "iso:country":"IT",
    "sg:address":"50125 Firenze",
    "sg:city":"Firenze",
    "sg:orig_category":"Cinematografia E Radiotelevisione. Forniture Per Il Settore Dello Spettacolo",
    "sg:phone":"+39 055 204 7693",
    "sg:postcode":"50125",
    "sg:province":"Firenze",
    "wof:name":"Caldini Guerrando Di Caldini Otello",
    "wof:placetype":"venue"
},
  "geometry": {"coordinates":[11.231115,43.744286],"type":"Point"}
}