{
  "type": "Feature",
  "properties": {
    "addr:full":"Via Zona Industriale 64025 Pineto Pineto Teramo 64025",
    "addr:postcode":"64025;64025",
    "addr:street":"Via Zona Industriale",
    "iso:country":"IT",
    "sg:address":"Via Zona Industriale 64025 Pineto",
    "sg:city":"Pineto",
    "sg:classifiers":[
        {
            "category":"Professional",
            "subcategory":"Engineering",
            "type":"Services"
        }
    ],
    "sg:phone":"+39 085 946 3022",
    "sg:postcode":"64025",
    "sg:province":"Teramo",
    "sg:tags":[
        "machine",
        "-",
        "mechanical"
    ],
    "wof:name":"Gapis Srl",
    "wof:placetype":"venue"
},
  "geometry": {"coordinates":[13.698531,42.66127],"type":"Point"}
}