{
  "type": "Feature",
  "properties": {
    "addr:full":"10040 Lein\u00ec Torino 10040",
    "addr:postcode":"10040;10040",
    "iso:country":"IT",
    "sg:address":"10040 Lein\u00ec",
    "sg:orig_category":"Hobbistica",
    "sg:phone":"+39 011 991 0984",
    "sg:postcode":"10040",
    "sg:province":"Torino",
    "wof:name":"Stamas Snc",
    "wof:placetype":"venue"
},
  "geometry": {"coordinates":[7.739897,45.154362],"type":"Point"}
}