{
  "type": "Feature",
  "properties": {
    "iso:country":"IT",
    "sg:address":"6, Via Emilia Nord - Stiava 55054 Massarosa",
    "sg:city":"Massarosa",
    "sg:classifiers":[
        {
            "category":"Building & Trades",
            "subcategory":"Construction",
            "type":"Services"
        }
    ],
    "sg:phone":"+39 0584 970222",
    "sg:postcode":"55054",
    "sg:province":"Lucca",
    "sg:tags":[
        "work",
        "public"
    ],
    "wof:name":"Tirrena Scavi (s.p.a.)",
    "wof:placetype":"venue"
},
  "geometry": {"coordinates":[10.298302,43.893688],"type":"Point"}
}