{
  "type": "Feature",
  "properties": {
    "iso:country":"IT",
    "sg:address":"50124 Firenze",
    "sg:city":"Firenze",
    "sg:orig_category":"Accessori Dei Mezzi Di Trasporto",
    "sg:phone":"+39 055 221686",
    "sg:postcode":"50124",
    "sg:province":"Firenze",
    "sg:website":"http://www.anellietondini.com",
    "wof:name":"Anelli & Tondini & C. Snc",
    "wof:placetype":"venue"
},
  "geometry": {"coordinates":[11.241056,43.763649],"type":"Point"}
}