{
  "type": "Feature",
  "properties": {
    "iso:country":"IT",
    "sg:address":"10098 Rivoli",
    "sg:city":"Rivoli",
    "sg:orig_category":"Legno E Semilavorati",
    "sg:phone":"+39 011 957 6359",
    "sg:postcode":"10098",
    "sg:province":"Torino",
    "wof:name":"Rivolilegno Snc",
    "wof:placetype":"venue"
},
  "geometry": {"coordinates":[7.587491,45.05204],"type":"Point"}
}