{
  "type": "Feature",
  "properties": {
    "iso:country":"IT",
    "sg:address":"46019 Viadana",
    "sg:city":"Viadana",
    "sg:orig_category":"Prodotti Chimici Secondari. Macchine E Forniture Per Ecologia E Smaltimento Rifiuti. Forniture Per Attivita' Industriali",
    "sg:phone":"+39 0375 785209",
    "sg:postcode":"46019",
    "sg:province":"Mantova",
    "wof:name":"G.e. Saverullplast Srl",
    "wof:placetype":"venue"
},
  "geometry": {"coordinates":[10.7764883041,45.1525917053],"type":"Point"}
}