{
  "type": "Feature",
  "properties": {
    "iso:country":"IT",
    "sg:address":"98100 Messina",
    "sg:orig_category":"Fotografia Apparecchi E Materiali - Vendita Al Dettaglio",
    "sg:phone":"+39 090 675493",
    "sg:province":"ME",
    "wof:name":"Mondello Ottica Di Lorenzo E Figli Snc",
    "wof:placetype":"venue"
},
  "geometry": {"coordinates":[15.4946880341,38.1972465515],"type":"Point"}
}