{
  "type": "Feature",
  "properties": {
    "addr:full":"3/a, V. Colombi Guidotti 43100 Parma Parma Parma 43100",
    "addr:housenumber":"3 / a",
    "addr:postcode":"43100;43100",
    "addr:street":"V. Colombi Guidotti",
    "iso:country":"IT",
    "sg:address":"3/a, V. Colombi Guidotti 43100 Parma",
    "sg:city":"Parma",
    "sg:classifiers":[
        {
            "category":"Personal",
            "subcategory":"Shoe Repair & Shine",
            "type":"Services"
        }
    ],
    "sg:phone":"+39 0521 980930",
    "sg:postcode":"43100",
    "sg:province":"Parma",
    "sg:tags":[
        "leather"
    ],
    "sg:website":"http://www.calzaturemattei.com:ws_end: :mark:ws:http://www.paginegialle.it/mattei-03",
    "wof:name":"Mattei Dr. Ivo Srl",
    "wof:placetype":"venue"
},
  "geometry": {"coordinates":[10.304225,44.80872],"type":"Point"}
}