{
  "type": "Feature",
  "properties": {
    "addr:full":"25125 Brescia Brescia Brescia 25125",
    "addr:postcode":"25125;25125",
    "iso:country":"IT",
    "sg:address":"25125 Brescia",
    "sg:city":"Brescia",
    "sg:orig_category":"Tessuti E Stoffe - Produzione E Ingrosso",
    "sg:phone":"+39 030 354 0590",
    "sg:postcode":"25125",
    "sg:province":"Brescia",
    "wof:name":"Radici Commerciale Brescia Spa",
    "wof:placetype":"venue"
},
  "geometry": {"coordinates":[10.179587,45.534073],"type":"Point"}
}