{
  "type": "Feature",
  "properties": {
    "iso:country":"IT",
    "sg:address":"Via Gramsci 44 20090 Opera",
    "sg:city":"Opera",
    "sg:orig_category":"Glass And Metal Bushings For Electronic Components",
    "sg:phone":"+39 02 5760 0376",
    "sg:postcode":"20090",
    "sg:province":"Milano",
    "wof:name":"Sintermetalglass Srl",
    "wof:placetype":"venue"
},
  "geometry": {"coordinates":[9.208535,45.370674],"type":"Point"}
}