{
  "type": "Feature",
  "properties": {
    "addr:full":"Via Ruvolo Sacerdote 91011 Alcamo Alcamo Trapani 91011",
    "addr:postcode":"91011;91011",
    "addr:street":"Via Ruvolo Sacerdote",
    "iso:country":"IT",
    "sg:address":"Via Ruvolo Sacerdote 91011 Alcamo",
    "sg:city":"Alcamo",
    "sg:classifiers":[
        {
            "category":"Manufacturing",
            "subcategory":"Metals",
            "type":"Manufacturing & Wholesale Goods"
        }
    ],
    "sg:phone":"+39 39092421588",
    "sg:postcode":"91011",
    "sg:province":"Trapani",
    "sg:tags":[
        "metallurgy",
        "metalworking"
    ],
    "wof:name":"Edil Sider (s.p.a.) -centralino-",
    "wof:placetype":"venue"
},
  "geometry": {"coordinates":[12.5146341324,38.0185890198],"type":"Point"}
}