{
  "type": "Feature",
  "properties": {
    "addr:full":"Loc Fusara 2 37060 Sona Sona Verona 37060",
    "addr:housenumber":"2",
    "addr:postcode":"37060;37060",
    "addr:street":"Loc Fusara",
    "iso:country":"IT",
    "sg:address":"Loc Fusara 2 37060 Sona",
    "sg:city":"Sona",
    "sg:classifiers":[
        {
            "category":"Manufacturing",
            "subcategory":"Rubber & Plastics",
            "type":"Manufacturing & Wholesale Goods"
        }
    ],
    "sg:phone":"+39 045 608 1511",
    "sg:postcode":"37060",
    "sg:province":"Verona",
    "sg:tags":[
        "safety",
        "cabinet"
    ],
    "sg:website":"www.silmec.it",
    "wof:name":"Silmec Srl",
    "wof:placetype":"venue"
},
  "geometry": {"coordinates":[10.991748,45.438366],"type":"Point"}
}