{
  "type": "Feature",
  "properties": {
    "iso:country":"IT",
    "sg:address":"87032 Amantea",
    "sg:city":"Amantea",
    "sg:orig_category":"Articoli Da Regalo. Tempo Libero - Articoli E Forniture. Regalistica Aziendale",
    "sg:phone":"+39 0982 425181",
    "sg:postcode":"87032",
    "sg:province":"Cosenza",
    "sg:website":"http://www.publyelle.it",
    "wof:name":"Publyelle Di Lo Cicero Natalio & F. Snc",
    "wof:placetype":"venue"
},
  "geometry": {"coordinates":[16.093412,39.08651],"type":"Point"}
}