{
  "type": "Feature",
  "properties": {
    "addr:full":"15100 Alessandria Alessandria Alessandria 15100",
    "addr:postcode":"15100;15100",
    "iso:country":"IT",
    "sg:address":"15100 Alessandria",
    "sg:city":"Alessandria",
    "sg:orig_category":"Automazione E Macchine Per Ufficio",
    "sg:phone":"+39 031 617902",
    "sg:postcode":"15100",
    "sg:province":"Alessandria",
    "wof:name":"S.d. Di Beretta Luca Sas",
    "wof:placetype":"venue"
},
  "geometry": {"coordinates":[8.627007,44.91045],"type":"Point"}
}