{
  "type": "Feature",
  "properties": {
    "addr:full":"20131 Milano Milano Milano 20131",
    "addr:postcode":"20131;20131",
    "iso:country":"IT",
    "sg:address":"20131 Milano",
    "sg:city":"Milano",
    "sg:orig_category":"Ospedali E Servizi Sanitari",
    "sg:phone":"+39 02 2952 6516",
    "sg:postcode":"20131",
    "sg:province":"Milano",
    "wof:name":"Carlo Dott.ssa Egle Centro Psicoterapie Corporee E Di Rilassamento",
    "wof:placetype":"venue"
},
  "geometry": {"coordinates":[9.215697,45.484638],"type":"Point"}
}