{
  "type": "Feature",
  "properties": {
    "iso:country":"IT",
    "sg:address":"09134 Pirri",
    "sg:orig_category":"Macchine, Impianti Ed Attrezzature Industria Chimica. Prodotti Vari In Metallo. Articoli Per Imballaggio E Confezionamento",
    "sg:phone":"+39 070 502915",
    "sg:postcode":"09134",
    "sg:province":"Cagliari",
    "wof:name":"V.e.b. Sas Di Maltesu",
    "wof:placetype":"venue"
},
  "geometry": {"coordinates":[9.131857,39.241714],"type":"Point"}
}