{
  "type": "Feature",
  "properties": {
    "iso:country":"IT",
    "sg:address":"71016 San Severo",
    "sg:city":"San Severo",
    "sg:orig_category":"Legname Da Lavoro",
    "sg:phone":"+39 0882 331370",
    "sg:postcode":"71016",
    "sg:province":"Foggia",
    "wof:name":"Tempesta Legnami",
    "wof:placetype":"venue"
},
  "geometry": {"coordinates":[15.628406,41.316071],"type":"Point"}
}