{
  "type": "Feature",
  "properties": {
    "iso:country":"IT",
    "sg:address":"10, Via Crear 37050 Oppeano",
    "sg:city":"Oppeano",
    "sg:classifiers":[
        {
            "category":"Manufacturing",
            "subcategory":"Tools & Machinery",
            "type":"Manufacturing & Wholesale Goods"
        }
    ],
    "sg:phone":"+39 045 698 5023",
    "sg:postcode":"37050",
    "sg:province":"Verona",
    "sg:tags":[
        "environment",
        "equipment",
        "-"
    ],
    "wof:name":"Depas Srl",
    "wof:placetype":"venue"
},
  "geometry": {"coordinates":[11.024673,45.34676],"type":"Point"}
}