{
  "type": "Feature",
  "properties": {
    "iso:country":"IT",
    "sg:address":"20031 Cesano Maderno",
    "sg:city":"Cesano Maderno",
    "sg:orig_category":"Lavorazioni Meccaniche E Servizi",
    "sg:phone":"+39 036 250 6814",
    "sg:postcode":"20031",
    "sg:province":"Milano",
    "wof:name":"Pavan Mario & C. Snc",
    "wof:placetype":"venue"
},
  "geometry": {"coordinates":[9.171799,45.630978],"type":"Point"}
}