{
  "type": "Feature",
  "properties": {
    "iso:country":"IT",
    "sg:address":"22100 Como",
    "sg:city":"Como",
    "sg:orig_category":"Antenne Radio-televisione",
    "sg:phone":"+39 031 263575",
    "sg:postcode":"22100",
    "sg:province":"Como",
    "wof:name":"Dlg Di Gianluca Di Lonardo",
    "wof:placetype":"venue"
},
  "geometry": {"coordinates":[9.091188,45.7985],"type":"Point"}
}