{
  "type": "Feature",
  "properties": {
    "iso:country":"IT",
    "sg:address":"37026 Pescantina",
    "sg:city":"Pescantina",
    "sg:orig_category":"Legno E Semilavorati",
    "sg:phone":"+39 045 675 0019",
    "sg:postcode":"37026",
    "sg:province":"Verona",
    "wof:name":"Ac Sugheri Italia S.r.l.",
    "wof:placetype":"venue"
},
  "geometry": {"coordinates":[10.905993,45.480793],"type":"Point"}
}