{
  "type": "Feature",
  "properties": {
    "addr:full":"26861 Fombio Fombio Lodi 26861",
    "addr:postcode":"26861;26861",
    "iso:country":"IT",
    "sg:address":"26861 Fombio",
    "sg:city":"Fombio",
    "sg:orig_category":"Elettrotecnica Industriale, Prodotti E Apparecchiature",
    "sg:phone":"+39 0377 33590",
    "sg:postcode":"26861",
    "sg:province":"Lodi",
    "wof:name":"Os. Ra.c. S.r.l.",
    "wof:placetype":"venue"
},
  "geometry": {"coordinates":[9.692412,45.143806],"type":"Point"}
}