{
  "type": "Feature",
  "properties": {
    "iso:country":"IT",
    "sg:address":"00158 Roma",
    "sg:city":"Roma",
    "sg:orig_category":"Abbigliamento Esterno, Maglierie E Pelliccerie. Forniture Per Il Settore Dello Spettacolo",
    "sg:phone":"+39 06 451 2015",
    "sg:postcode":"00158",
    "sg:province":"Roma",
    "wof:name":"G.p. 11 Srl",
    "wof:placetype":"venue"
},
  "geometry": {"coordinates":[12.57191,41.907539],"type":"Point"}
}