{
  "type": "Feature",
  "properties": {
    "iso:country":"IT",
    "sg:address":"31038 Paese",
    "sg:city":"Paese",
    "sg:orig_category":"Prodotti Chimici Di Base. Macchine E Forniture Per Ecologia E Smaltimento Rifiuti",
    "sg:phone":"+39 0422 958446",
    "sg:postcode":"31038",
    "sg:province":"Treviso",
    "wof:name":"Italcarbon (s.r.l.)",
    "wof:placetype":"venue"
},
  "geometry": {"coordinates":[12.1843624115,45.670463562],"type":"Point"}
}