{
  "type": "Feature",
  "properties": {
    "addr:full":"37014 Castelnuovo Del Garda Castelnuovo del Garda Verona 37014",
    "addr:postcode":"37014;37014",
    "iso:country":"IT",
    "sg:address":"37014 Castelnuovo Del Garda",
    "sg:city":"Castelnuovo del Garda",
    "sg:orig_category":"Prodotti Chimici Di Base. Ospedali E Servizi Sanitari",
    "sg:phone":"+39 045 645 0030",
    "sg:postcode":"37014",
    "sg:province":"Verona",
    "wof:name":"Air Liquide Produzione Srl",
    "wof:placetype":"venue"
},
  "geometry": {"coordinates":[10.7584753036,45.4281692505],"type":"Point"}
}