{
  "type": "Feature",
  "properties": {
    "iso:country":"IT",
    "sg:address":"50025 Montespertoli",
    "sg:city":"Montespertoli",
    "sg:orig_category":"Prodotti E Manufatti In Materie Plastiche",
    "sg:phone":"+39 0571 675015",
    "sg:postcode":"50025",
    "sg:province":"Firenze",
    "wof:name":"Scherma Di Scherma Fausto",
    "wof:placetype":"venue"
},
  "geometry": {"coordinates":[11.0651464462,43.6826095581],"type":"Point"}
}