{
  "type": "Feature",
  "properties": {
    "iso:country":"IT",
    "sg:address":"01100 Viterbo",
    "sg:city":"Viterbo",
    "sg:orig_category":"Coperture Edili E Tetti",
    "sg:phone":"+39 0761 830046",
    "sg:postcode":"01100",
    "sg:province":"Viterbo",
    "wof:name":"Interland Gecoop Soc. Coop. A R.l.",
    "wof:placetype":"venue"
},
  "geometry": {"coordinates":[12.048979,42.441536],"type":"Point"}
}