{
  "type": "Feature",
  "properties": {
    "iso:country":"IT",
    "sg:address":"56036 Palaia",
    "sg:city":"Palaia",
    "sg:orig_category":"Geologia, Geotecnica E Topografia - Studi E Servizi",
    "sg:phone":"+39 0587 622141",
    "sg:postcode":"56036",
    "sg:province":"Pisa",
    "wof:name":"Comune Di Palaia",
    "wof:placetype":"venue"
},
  "geometry": {"coordinates":[10.777442,43.605621],"type":"Point"}
}