{
  "type": "Feature",
  "properties": {
    "addr:full":"00193 Roma Roma Roma 00193",
    "addr:postcode":"00193;00193",
    "iso:country":"IT",
    "sg:address":"00193 Roma",
    "sg:city":"Roma",
    "sg:orig_category":"Librerie Antiquarie",
    "sg:phone":"+39 06 305 8975",
    "sg:postcode":"00193",
    "sg:province":"Roma",
    "wof:name":"Raucci Amedeo",
    "wof:placetype":"venue"
},
  "geometry": {"coordinates":[12.698025,41.675446],"type":"Point"}
}