{
  "type": "Feature",
  "properties": {
    "iso:country":"IT",
    "sg:address":"Via Puccini G. 55016 Porcari",
    "sg:city":"Porcari",
    "sg:classifiers":[
        {
            "category":"Personal",
            "subcategory":"Shoe Repair & Shine",
            "type":"Services"
        }
    ],
    "sg:phone":"+39 39058326211",
    "sg:postcode":"55016",
    "sg:province":"Lucca",
    "sg:tags":[
        "leather"
    ],
    "wof:name":"Lenci Calzature Spa",
    "wof:placetype":"venue"
},
  "geometry": {"coordinates":[10.507994,43.843014],"type":"Point"}
}