{
  "type": "Feature",
  "properties": {
    "iso:country":"IT",
    "sg:address":"20040 Bellusco",
    "sg:city":"Bellusco",
    "sg:orig_category":"Materiali E Componenti Elettronici",
    "sg:phone":"+39 039 627411",
    "sg:postcode":"20040",
    "sg:province":"Milano",
    "wof:name":"Metron Technology Italia Srl",
    "wof:placetype":"venue"
},
  "geometry": {"coordinates":[9.423265,45.616161],"type":"Point"}
}