{
  "type": "Feature",
  "properties": {
    "addr:full":"23861 Cesana Brianza Cesana Brianza Lecco 23861",
    "addr:postcode":"23861;brianza;23861",
    "iso:country":"IT",
    "sg:address":"23861 Cesana Brianza",
    "sg:city":"Cesana Brianza",
    "sg:orig_category":"Cesoie Industriali",
    "sg:phone":"+39 031 658511",
    "sg:postcode":"23861",
    "sg:province":"Lecco",
    "sg:website":"http://www.sommer.it",
    "wof:name":"Sommer Srl",
    "wof:placetype":"venue"
},
  "geometry": {"coordinates":[9.326819,45.808475],"type":"Point"}
}