{
  "type": "Feature",
  "properties": {
    "iso:country":"IT",
    "sg:address":"53100 Siena",
    "sg:city":"Siena",
    "sg:orig_category":"Alberghi E Strutture Extra Alberghiere",
    "sg:phone":"+39 0577 288084",
    "sg:postcode":"53100",
    "sg:province":"Siena",
    "sg:website":"http://www.hotelsiena.com",
    "wof:name":"Cooperativa Siena Hotels Promotion",
    "wof:placetype":"venue"
},
  "geometry": {"coordinates":[11.326941,43.319733],"type":"Point"}
}