{
  "type": "Feature",
  "properties": {
    "addr:full":"10024 Moncalieri Moncalieri Torino 10024",
    "addr:postcode":"10024;10024",
    "iso:country":"IT",
    "sg:address":"10024 Moncalieri",
    "sg:city":"Moncalieri",
    "sg:orig_category":"Ricambi E Componenti Dei Mezzi Di Trasporto",
    "sg:phone":"+39 011 640 8222",
    "sg:postcode":"10024",
    "sg:province":"Torino",
    "wof:name":"Valenti Felice",
    "wof:placetype":"venue"
},
  "geometry": {"coordinates":[7.669841,44.998341],"type":"Point"}
}