{
  "type": "Feature",
  "properties": {
    "iso:country":"IT",
    "sg:address":"Via Della Edilizia 85100 Potenza",
    "sg:city":"Potenza",
    "sg:classifiers":[
        {
            "category":"Manufacturing",
            "subcategory":"Metals",
            "type":"Manufacturing & Wholesale Goods"
        }
    ],
    "sg:phone":"+39 39097155538",
    "sg:postcode":"85100",
    "sg:province":"Potenza",
    "sg:tags":[
        "processing"
    ],
    "wof:name":"Societa' Sabia (s.r.l.)",
    "wof:placetype":"venue"
},
  "geometry": {"coordinates":[15.8022212982,40.6372413635],"type":"Point"}
}