{
  "type": "Feature",
  "properties": {
    "addr:full":"00047 Marino Marino Roma 00047",
    "addr:postcode":"00047;00047",
    "addr:street":"Marino Roma",
    "iso:country":"IT",
    "sg:address":"00047 Marino",
    "sg:city":"Marino",
    "sg:orig_category":"Forniture Per Agricoltura E Zootecnia",
    "sg:phone":"+39 06 930 0294",
    "sg:postcode":"00047",
    "sg:province":"Roma",
    "wof:name":"Rizzo Renzo",
    "wof:placetype":"venue"
},
  "geometry": {"coordinates":[12.6181344986,41.7701263428],"type":"Point"}
}