{
  "type": "Feature",
  "properties": {
    "iso:country":"IT",
    "sg:address":"Via Montolmo 70 62014 Corridonia",
    "sg:city":"Corridonia",
    "sg:classifiers":[
        {
            "category":"Shopping",
            "subcategory":"Shoes",
            "type":"Retail Goods"
        }
    ],
    "sg:phone":"+39 0733 292382",
    "sg:postcode":"62014",
    "sg:province":"Macerata",
    "sg:tags":[
        "men's",
        "boot"
    ],
    "sg:website":"www.antoniomaurizi.com",
    "wof:name":"Maurizi Srl",
    "wof:placetype":"venue"
},
  "geometry": {"coordinates":[13.501455307,43.249080658],"type":"Point"}
}