{
  "type": "Feature",
  "properties": {
    "iso:country":"IT",
    "sg:address":"98057 Milazzo",
    "sg:city":"Milazzo",
    "sg:orig_category":"Acquacoltura",
    "sg:phone":"+39 090 928 2953",
    "sg:postcode":"98057",
    "sg:province":"Messina",
    "wof:name":"Gitto Stefano",
    "wof:placetype":"venue"
},
  "geometry": {"coordinates":[15.237034,38.200718],"type":"Point"}
}