{
  "type": "Feature",
  "properties": {
    "addr:full":"89018 Villa San Giovanni Villa San Giovanni Reggio Di Calabria 89018",
    "addr:housenumber":"89018",
    "addr:postcode":"89018",
    "addr:street":"Villa San Giovanni Villa San",
    "iso:country":"IT",
    "sg:address":"89018 Villa San Giovanni",
    "sg:city":"Villa San Giovanni",
    "sg:orig_category":"Agenzie Ed Enti Turistici. Acqua, Luce, Gas E Societa' Di Esercizio Pubblico",
    "sg:phone":"+39 0965 751463",
    "sg:postcode":"89018",
    "sg:province":"Reggio Di Calabria",
    "wof:name":"Micari Sas Viaggi E Turismo Di Aragona Domenico",
    "wof:placetype":"venue"
},
  "geometry": {"coordinates":[15.636061,38.217503],"type":"Point"}
}