{
  "type": "Feature",
  "properties": {
    "iso:country":"IT",
    "sg:address":"10098 Rivoli",
    "sg:city":"Rivoli",
    "sg:orig_category":"Informatica - Consulenza E Servizi. Servizi Ausiliari Di Analisi, Controllo E Ricerca. Servizi Per Aziende, Manifestazioni E Supporto Agli Scambi Commerciali",
    "sg:phone":"+39 011 958 6705",
    "sg:postcode":"10098",
    "sg:province":"Torino",
    "sg:website":"http://www.studioolocco.com",
    "wof:name":"Celdac Sas",
    "wof:placetype":"venue"
},
  "geometry": {"coordinates":[7.528754,45.060741],"type":"Point"}
}