{
  "type": "Feature",
  "properties": {
    "iso:country":"IT",
    "sg:address":"24060 Casazza",
    "sg:city":"Casazza",
    "sg:classifiers":[
        {
            "category":"Home & Garden",
            "subcategory":"Building Materials",
            "type":"Retail Goods"
        }
    ],
    "sg:phone":"+39 035 811567",
    "sg:postcode":"24060",
    "sg:province":"Bergamo",
    "sg:tags":[
        "window",
        "door",
        "frame"
    ],
    "wof:name":"Bettoni Giovanni & C. Snc",
    "wof:placetype":"venue"
},
  "geometry": {"coordinates":[9.909933,45.750038],"type":"Point"}
}