{
  "type": "Feature",
  "properties": {
    "iso:country":"IT",
    "sg:address":"00187 Roma",
    "sg:city":"Roma",
    "sg:orig_category":"Banche E Servizi Finanziari",
    "sg:phone":"+39 06 6994 1639",
    "sg:postcode":"00187",
    "sg:province":"Roma",
    "wof:name":"Nusa Sim S.p.a.",
    "wof:placetype":"venue"
},
  "geometry": {"coordinates":[12.479445,41.903778],"type":"Point"}
}