{
  "type": "Feature",
  "properties": {
    "iso:country":"IT",
    "sg:address":"06083 Bastia",
    "sg:city":"Bastia",
    "sg:orig_category":"Fiere, Mostre E Saloni - Allestimento E Servizi",
    "sg:phone":"+39 075 800 4005",
    "sg:postcode":"06083",
    "sg:province":"Perugia",
    "sg:website":"http://www.umbriafiere.it",
    "wof:name":"Umbriafiere Spa - Centro Fieristico",
    "wof:placetype":"venue"
},
  "geometry": {"coordinates":[12.5495672226,43.0663795471],"type":"Point"}
}