{
  "type": "Feature",
  "properties": {
    "iso:country":"IT",
    "sg:address":"30030 Martellago",
    "sg:city":"Martellago",
    "sg:orig_category":"Trattamenti Termici E Superficiali Metalli, Galvanotecnica",
    "sg:phone":"+39 041 908262",
    "sg:postcode":"30030",
    "sg:province":"Venezia",
    "wof:name":"Galvanica C.m.b. Snc Di Bittante Franco & C.",
    "wof:placetype":"venue"
},
  "geometry": {"coordinates":[12.190865,45.51503],"type":"Point"}
}