{
  "type": "Feature",
  "properties": {
    "addr:full":"21047 Saronno Saronno Varese 21047",
    "addr:postcode":"21047;21047",
    "iso:country":"IT",
    "sg:address":"21047 Saronno",
    "sg:city":"Saronno",
    "sg:orig_category":"Professionisti - Studi E Servizi Ed Associazioni Di Interesse Aziendale. Associazioni Ed Organismi Di Interesse Pubblico. Chiese Ed Associazioni Religiose",
    "sg:phone":"+39 02 962 3795",
    "sg:postcode":"21047",
    "sg:province":"Varese",
    "wof:name":"Casa Di Pronta Accoglienza",
    "wof:placetype":"venue"
},
  "geometry": {"coordinates":[9.0385427475,45.6265296936],"type":"Point"}
}