{
  "type": "Feature",
  "properties": {
    "iso:country":"IT",
    "sg:address":"20095 Cusano Milanino",
    "sg:city":"Cusano Milanino",
    "sg:orig_category":"Articoli Da Regalo. Regalistica Aziendale",
    "sg:phone":"+39 02 6640 1007",
    "sg:postcode":"20095",
    "sg:province":"Milano",
    "wof:name":"De. Pi. Lux Di Busacca Roberto",
    "wof:placetype":"venue"
},
  "geometry": {"coordinates":[9.184348,45.54747],"type":"Point"}
}