{
  "type": "Feature",
  "properties": {
    "iso:country":"IT",
    "sg:address":"20063 Cernusco Sul Naviglio",
    "sg:city":"Cernusco sul Naviglio",
    "sg:orig_category":"Calzature, Pelletterie E Pelli. Shopping",
    "sg:phone":"+39 02 924 0619",
    "sg:postcode":"20063",
    "sg:province":"Milano",
    "wof:name":"Pelletteria Lucas Di Bertolazzi Lodovico",
    "wof:placetype":"venue"
},
  "geometry": {"coordinates":[9.295077,45.49049],"type":"Point"}
}