{
  "type": "Feature",
  "properties": {
    "iso:country":"IT",
    "sg:address":"43052 Colorno",
    "sg:city":"Colorno",
    "sg:orig_category":"Dentisti Medici Chirurghi Ed Odontoiatri",
    "sg:phone":"+39 0521 815536",
    "sg:postcode":"43052",
    "sg:province":"Parma",
    "wof:name":"Bove Dr. Ferdinando",
    "wof:placetype":"venue"
},
  "geometry": {"coordinates":[10.37728,44.932629],"type":"Point"}
}