{
  "type": "Feature",
  "properties": {
    "iso:country":"IT",
    "sg:address":"88046 Lamezia Terme",
    "sg:city":"Lamezia Terme",
    "sg:orig_category":"Prodotti E Manufatti In Materie Plastiche",
    "sg:phone":"+39 0968 209838",
    "sg:postcode":"88046",
    "sg:province":"Catanzaro",
    "wof:name":"Proplast Srl",
    "wof:placetype":"venue"
},
  "geometry": {"coordinates":[16.2757511139,38.9336204529],"type":"Point"}
}