{
  "type": "Feature",
  "properties": {
    "iso:country":"IT",
    "sg:address":"53037 San Gimignano",
    "sg:city":"San Gimignano",
    "sg:orig_category":"Lavorazioni Meccaniche E Servizi. Macchine E Impianti Per Attivita' Commerciali Ed Artigianali. Macchine, Strumenti Ed Apparecchi Per Attivita' Industriali. Servizi Per Aziende, Manifestazioni E Suppo",
    "sg:phone":"+39 0577 909158",
    "sg:postcode":"53037",
    "sg:province":"Siena",
    "sg:website":"http://www.rental2000.it.",
    "wof:name":"Rental 2000 Srl",
    "wof:placetype":"venue"
},
  "geometry": {"coordinates":[11.048549,43.465431],"type":"Point"}
}