{
  "type": "Feature",
  "properties": {
    "iso:country":"IT",
    "sg:address":"12, Via Roma 81030 Cancello Ed Arnone",
    "sg:city":"Arnone",
    "sg:classifiers":[
        {
            "category":"Building & Trades",
            "subcategory":"Construction",
            "type":"Services"
        }
    ],
    "sg:phone":"+39 0823 856716",
    "sg:postcode":"81030",
    "sg:province":"Caserta",
    "sg:tags":[
        "work",
        "public"
    ],
    "wof:name":"Di Benedetto R. Sud Costruzioni",
    "wof:placetype":"venue"
},
  "geometry": {"coordinates":[14.022848,41.078125],"type":"Point"}
}