{
  "type": "Feature",
  "properties": {
    "iso:country":"IT",
    "sg:address":"90045 Cinisi",
    "sg:city":"Cinisi",
    "sg:orig_category":"Servizi E Lavori Per Edilizia E Lavori Pubblici. Servizi E Lavori Per Ecologia E Smaltimento Rifiuti. Macchine E Forniture Per Ecologia E Smaltimento Rifiuti. Acqua, Luce, Gas E Societa' Di Esercizio ",
    "sg:phone":"+39 091 866 7280",
    "sg:postcode":"90045",
    "sg:province":"Palermo",
    "wof:name":"Associazione Nazionale Vigili Del Fuoco In Congedo",
    "wof:placetype":"venue"
},
  "geometry": {"coordinates":[13.116374,38.155689],"type":"Point"}
}