{
  "type": "Feature",
  "properties": {
    "addr:full":"38060 Brentonico Brentonico Trento 38060",
    "addr:postcode":"38060;38060",
    "iso:country":"IT",
    "sg:address":"38060 Brentonico",
    "sg:city":"Brentonico",
    "sg:orig_category":"Prodotti E Manufatti In Materie Plastiche",
    "sg:phone":"+39 0464 928100",
    "sg:postcode":"38060",
    "sg:province":"Trento",
    "wof:name":"Lavesan Srl",
    "wof:placetype":"venue"
},
  "geometry": {"coordinates":[10.9562778473,45.8199996948],"type":"Point"}
}