{
  "type": "Feature",
  "properties": {
    "iso:country":"IT",
    "sg:address":"66026 Ortona",
    "sg:city":"Ortona",
    "sg:classifiers":[
        {
            "category":"Bars & Pubs",
            "subcategory":"Wine Bar",
            "type":"Food & Drink"
        }
    ],
    "sg:phone":"+39 085 903331",
    "sg:postcode":"66026",
    "sg:province":"Chieti",
    "sg:tags":[
        "liqueur",
        "drinks"
    ],
    "wof:name":"Cantine Dragani Srl",
    "wof:placetype":"venue"
},
  "geometry": {"coordinates":[14.363658,42.296257],"type":"Point"}
}