{
  "type": "Feature",
  "properties": {
    "iso:country":"IT",
    "sg:address":"38079 Tione Di Trento",
    "sg:city":"Tione di Trento",
    "sg:orig_category":"Servizi Vari Di Interesse Pubblico",
    "sg:phone":"+39 0465 326061",
    "sg:postcode":"38079",
    "sg:province":"Trento",
    "wof:name":"Cooperativa Sociale Casa Bimbo Uno Tagesmutter Trento",
    "wof:placetype":"venue"
},
  "geometry": {"coordinates":[10.670562,45.984772],"type":"Point"}
}