{
  "type": "Feature",
  "properties": {
    "addr:full":"4, Via Aosta 24040 Ciserano Ciserano Bergamo 24040",
    "addr:postcode":"24040;24040",
    "addr:street":"Via Aosta",
    "iso:country":"IT",
    "sg:address":"4, Via Aosta 24040 Ciserano",
    "sg:city":"Ciserano",
    "sg:classifiers":[
        {
            "category":"Shopping",
            "type":"Retail Goods"
        }
    ],
    "sg:phone":"+39 035 482 1201",
    "sg:postcode":"24040",
    "sg:province":"Bergamo",
    "sg:tags":[
        "finished",
        "-",
        "metallic"
    ],
    "wof:name":"Comest S.r.l.",
    "wof:placetype":"venue"
},
  "geometry": {"coordinates":[9.6014680862,45.59375],"type":"Point"}
}