{
  "type": "Feature",
  "properties": {
    "iso:country":"IT",
    "sg:address":"30030 Salzano",
    "sg:city":"Salzano",
    "sg:classifiers":[
        {
            "category":"Utilities",
            "subcategory":"Natural Gas",
            "type":"Services"
        }
    ],
    "sg:phone":"+39 041 482800",
    "sg:postcode":"30030",
    "sg:province":"Venezia",
    "sg:tags":[
        "alloy",
        "metal"
    ],
    "wof:name":"Fizeta Srl",
    "wof:placetype":"venue"
},
  "geometry": {"coordinates":[12.1467761993,45.4948883057],"type":"Point"}
}