{
  "type": "Feature",
  "properties": {
    "iso:country":"IT",
    "sg:address":"Cso Savona 387 14100 Asti",
    "sg:city":"Asti",
    "sg:orig_category":"Radiation Shielding Building Materials",
    "sg:phone":"+39 0141 593215",
    "sg:postcode":"14100",
    "sg:province":"Asti",
    "sg:website":"www.bigmat.it",
    "wof:name":"Fava & Scarzella Di Fava Gigi & C. Sas",
    "wof:placetype":"venue"
},
  "geometry": {"coordinates":[8.212706,44.882763],"type":"Point"}
}