{
  "type": "Feature",
  "properties": {
    "iso:country":"IT",
    "sg:address":"80044 Ottaviano",
    "sg:city":"Ottaviano",
    "sg:orig_category":"Marmo, Pietre Ed Affini",
    "sg:phone":"+39 081 528 9615",
    "sg:postcode":"80044",
    "sg:province":"Napoli",
    "wof:name":"I.ma.v. Industria Marmi Vesuviana Srl",
    "wof:placetype":"venue"
},
  "geometry": {"coordinates":[14.478153,40.838894],"type":"Point"}
}