{
  "type": "Feature",
  "properties": {
    "iso:country":"IT",
    "sg:address":"Via Caproni 1 38068 Rovereto",
    "sg:city":"Rovereto",
    "sg:classifiers":[
        {
            "category":"Manufacturing",
            "subcategory":"Printing",
            "type":"Manufacturing & Wholesale Goods"
        }
    ],
    "sg:phone":"+39 0464 437811",
    "sg:postcode":"38068",
    "sg:province":"Trento",
    "sg:tags":[
        "plastic"
    ],
    "sg:website":"www.mpstampi.com",
    "wof:name":"Stam Plast Srl",
    "wof:placetype":"venue"
},
  "geometry": {"coordinates":[11.0145225525,45.8646240234],"type":"Point"}
}