{
  "type": "Feature",
  "properties": {
    "iso:country":"IT",
    "sg:address":"36016 Thiene",
    "sg:city":"Thiene",
    "sg:orig_category":"Macchine, Impianti Ed Attrezzature Per Abbigliamento E Pelletterie",
    "sg:phone":"+39 0445 364166",
    "sg:postcode":"36016",
    "sg:province":"Vicenza",
    "wof:name":"T.b. Srl",
    "wof:placetype":"venue"
},
  "geometry": {"coordinates":[11.510476,45.705276],"type":"Point"}
}