{
  "type": "Feature",
  "properties": {
    "iso:country":"IT",
    "sg:address":"00146 Roma",
    "sg:city":"Roma",
    "sg:orig_category":"Ospedali E Servizi Sanitari",
    "sg:phone":"+39 06 556 6533",
    "sg:postcode":"00146",
    "sg:province":"Roma",
    "wof:name":"C.r.i.",
    "wof:placetype":"venue"
},
  "geometry": {"coordinates":[12.465902,41.870232],"type":"Point"}
}