{
  "type": "Feature",
  "properties": {
    "addr:full":"Via Marinella, 65 - Dogana 19034 Ortonovo Dogana La Spezia 19034",
    "addr:housenumber":"65",
    "addr:postcode":"19034;19034",
    "addr:street":"Via Marinella",
    "iso:country":"IT",
    "sg:address":"Via Marinella, 65 - Dogana 19034 Ortonovo",
    "sg:city":"Dogana",
    "sg:orig_category":"Marble Sawmills",
    "sg:phone":"+39 0585 858867",
    "sg:postcode":"19034",
    "sg:province":"La Spezia",
    "wof:name":"F. Andreani E C. Srl",
    "wof:placetype":"venue"
},
  "geometry": {"coordinates":[10.026073,44.05558],"type":"Point"}
}