{
  "type": "Feature",
  "properties": {
    "iso:country":"IT",
    "sg:address":"Via Bonazzi 13/15 40013 Castel Maggiore",
    "sg:city":"Castel Maggiore",
    "sg:classifiers":[
        {
            "category":"Wholesale",
            "subcategory":"Plants",
            "type":"Manufacturing & Wholesale Goods"
        }
    ],
    "sg:phone":"+39 051 700326",
    "sg:postcode":"40013",
    "sg:province":"Bologna",
    "sg:tags":[
        "mobile",
        "plants",
        "asphalting"
    ],
    "sg:website":"www.safer-sicom.it",
    "wof:name":"Safer S.i.co.m Srl Soc. Industriale Costruzione Macchine Modenese",
    "wof:placetype":"venue"
},
  "geometry": {"coordinates":[11.370153,44.559402],"type":"Point"}
}