{
  "type": "Feature",
  "properties": {
    "iso:country":"IT",
    "sg:address":"40060 Dozza",
    "sg:city":"Dozza",
    "sg:orig_category":"Autonoleggio",
    "sg:phone":"+39 0542 672034",
    "sg:postcode":"40060",
    "sg:province":"Bologna",
    "sg:website":"http://www.romagnacarri.it",
    "wof:name":"Romagna Carri Srl",
    "wof:placetype":"venue"
},
  "geometry": {"coordinates":[11.620038,44.389988],"type":"Point"}
}