{
  "type": "Feature",
  "properties": {
    "addr:full":"18038 Sanremo Imperia 18038",
    "addr:postcode":"18038;18038",
    "iso:country":"IT",
    "sg:address":"18038 Sanremo",
    "sg:classifiers":[
        {
            "category":"Home & Garden",
            "subcategory":"Building Materials",
            "type":"Retail Goods"
        }
    ],
    "sg:phone":"+39 0184 667211",
    "sg:postcode":"18038",
    "sg:province":"Imperia",
    "sg:tags":[
        "curtain",
        "furnishing",
        "fabrics",
        "carpet"
    ],
    "wof:name":"Policchi Mario & C. Sas",
    "wof:placetype":"venue"
},
  "geometry": {"coordinates":[7.764816761,43.814907074],"type":"Point"}
}