{
  "type": "Feature",
  "properties": {
    "iso:country":"IT",
    "sg:address":"15, V. Roma 09013 Carbonia",
    "sg:city":"Carbonia",
    "sg:classifiers":[
        {
            "category":"Utilities",
            "subcategory":"Telephone",
            "type":"Services"
        }
    ],
    "sg:phone":"+39 0781 671650",
    "sg:postcode":"09013",
    "sg:province":"Carbonia-Iglesias",
    "sg:tags":[
        "telecommunication"
    ],
    "sg:website":"http://www.studiodesign.it",
    "wof:name":"Studio Design",
    "wof:placetype":"venue"
},
  "geometry": {"coordinates":[8.572102,39.253468],"type":"Point"}
}