{
  "type": "Feature",
  "properties": {
    "iso:country":"IT",
    "sg:address":"20, Via Del Vala' 20048 Carate Brianza",
    "sg:city":"Carate Brianza",
    "sg:classifiers":[
        {
            "category":"Professional",
            "subcategory":"Printing & Photocopies",
            "type":"Services"
        }
    ],
    "sg:phone":"+39 39036291631",
    "sg:postcode":"20048",
    "sg:province":"Milano",
    "wof:name":"Sanvito & Somaschini S.p.a.",
    "wof:placetype":"venue"
},
  "geometry": {"coordinates":[9.2367124557,45.6593818665],"type":"Point"}
}