{
  "type": "Feature",
  "properties": {
    "iso:country":"IT",
    "sg:address":"12, Via Armaroli 40012 Calderara Di Reno",
    "sg:city":"Calderara di Reno",
    "sg:classifiers":[
        {
            "category":"Autos & Motor Vehicles",
            "subcategory":"Automobile Sales",
            "type":"Retail Goods"
        }
    ],
    "sg:phone":"+39 39051722557",
    "sg:postcode":"40012",
    "sg:province":"Bologna",
    "sg:tags":[
        "industrial"
    ],
    "wof:name":"Societa' Generale Ricambi Europa P.a.",
    "wof:placetype":"venue"
},
  "geometry": {"coordinates":[11.276487,44.565845],"type":"Point"}
}