{
  "type": "Feature",
  "properties": {
    "addr:full":"25085 Gavardo Gavardo Brescia 25085",
    "addr:postcode":"25085;25085",
    "iso:country":"IT",
    "sg:address":"25085 Gavardo",
    "sg:city":"Gavardo",
    "sg:orig_category":"Disinfezione, Disinfestazione E Derattizzazione",
    "sg:phone":"+39 036 537 2339",
    "sg:postcode":"25085",
    "sg:province":"Brescia",
    "sg:website":"http://www.sanitariasnc.it",
    "wof:name":"Sanitaria Servizi Ambientali Snc",
    "wof:placetype":"venue"
},
  "geometry": {"coordinates":[10.440859,45.579556],"type":"Point"}
}