{
  "type": "Feature",
  "properties": {
    "addr:full":"33100 Udine Udine Udine 33100",
    "addr:postcode":"33100;33100",
    "iso:country":"IT",
    "sg:address":"33100 Udine",
    "sg:city":"Udine",
    "sg:classifiers":[
        {
            "category":"Health Services",
            "subcategory":"Health Practitioner",
            "type":"Services"
        }
    ],
    "sg:phone":"+39 0432 25403",
    "sg:postcode":"33100",
    "sg:province":"Udine",
    "sg:tags":[
        "medici"
    ],
    "wof:name":"Barbagallo Corrado",
    "wof:placetype":"venue"
},
  "geometry": {"coordinates":[13.236265,46.06773],"type":"Point"}
}