{
  "type": "Feature",
  "properties": {
    "iso:country":"IT",
    "sg:address":"24047 Treviglio",
    "sg:city":"Treviglio",
    "sg:orig_category":"Petroli, Gas E Combustibili",
    "sg:phone":"+39 036 343714",
    "sg:postcode":"24047",
    "sg:province":"Bergamo",
    "wof:name":"Panta Distribuzione Spa",
    "wof:placetype":"venue"
},
  "geometry": {"coordinates":[9.7034349442,45.7258987427],"type":"Point"}
}