{
  "type": "Feature",
  "properties": {
    "iso:country":"IT",
    "sg:address":"35127 Camin",
    "sg:orig_category":"Manufacturers: Prefabbricati",
    "sg:phone":"+39 049 870 2575",
    "sg:postcode":"35127",
    "sg:province":"Padova",
    "wof:name":"Baracco Vetrocemento (s.n.c.)",
    "wof:placetype":"venue"
},
  "geometry": {"coordinates":[11.951415,45.400131],"type":"Point"}
}