{
  "type": "Feature",
  "properties": {
    "iso:country":"IT",
    "sg:address":"20093 Cologno Monzese",
    "sg:city":"Cologno Monzese",
    "sg:orig_category":"Prodotti Finiti Stampati. Forniture Per Uffici",
    "sg:phone":"+39 02 254 1445",
    "sg:postcode":"20093",
    "sg:province":"Milano",
    "wof:name":"Clipsy Srl",
    "wof:placetype":"venue"
},
  "geometry": {"coordinates":[9.2850008011,45.5255241394],"type":"Point"}
}