{
  "type": "Feature",
  "properties": {
    "iso:country":"IT",
    "sg:address":"00148 Roma",
    "sg:city":"Roma",
    "sg:orig_category":"Automobili E Mezzi Di Trasporto",
    "sg:phone":"+39 06 655 2711",
    "sg:postcode":"00148",
    "sg:province":"Roma",
    "wof:name":"Raim Di Bove Francesco E C. S.n.c.",
    "wof:placetype":"venue"
},
  "geometry": {"coordinates":[12.434388,41.831562],"type":"Point"}
}