{
  "type": "Feature",
  "properties": {
    "addr:full":"Via Roncarino 3 15079 Sezzadio Sezzadio Alessandria 15079",
    "addr:housenumber":"3",
    "addr:postcode":"15079;15079",
    "addr:street":"Via Roncarino",
    "iso:country":"IT",
    "sg:address":"Via Roncarino 3 15079 Sezzadio",
    "sg:city":"Sezzadio",
    "sg:classifiers":[
        {
            "category":"Health Services",
            "subcategory":"Hospital",
            "type":"Services"
        }
    ],
    "sg:phone":"+39 0131 703149",
    "sg:postcode":"15079",
    "sg:province":"Alessandria",
    "sg:tags":[
        "capsule",
        "cap",
        "bottle"
    ],
    "wof:name":"Novembal Imballaggi Srl",
    "wof:placetype":"venue"
},
  "geometry": {"coordinates":[8.577332,44.783173],"type":"Point"}
}