{
  "type": "Feature",
  "properties": {
    "iso:country":"IT",
    "sg:address":"Via Sammichele 70021 Acquaviva Delle Fonti",
    "sg:city":"Acquaviva delle Fonti",
    "sg:classifiers":[
        {
            "category":"Manufacturing",
            "subcategory":"Paper Products",
            "type":"Manufacturing & Wholesale Goods"
        }
    ],
    "sg:phone":"+39 080 305 0220",
    "sg:postcode":"70021",
    "sg:province":"Bari",
    "sg:tags":[
        "cardboard"
    ],
    "wof:name":"Onda Pack",
    "wof:placetype":"venue"
},
  "geometry": {"coordinates":[16.8654518127,40.8948135376],"type":"Point"}
}