{
  "type": "Feature",
  "properties": {
    "addr:full":"44, Via Matteotti Giacomo 21012 Cassano Magnago Cassano Magnago Varese 21012",
    "addr:postcode":"21012;21012",
    "addr:street":"Via Matteotti Giacomo",
    "iso:country":"IT",
    "sg:address":"44, Via Matteotti Giacomo 21012 Cassano Magnago",
    "sg:city":"Cassano Magnago",
    "sg:classifiers":[
        {
            "category":"Shopping",
            "subcategory":"Crafts & Fabrics",
            "type":"Retail Goods"
        }
    ],
    "sg:phone":"+39 0331 200420",
    "sg:postcode":"21012",
    "sg:province":"Varese",
    "sg:tags":[
        "linen"
    ],
    "wof:name":"Manifattura Scandroglio (s.r.l.)",
    "wof:placetype":"venue"
},
  "geometry": {"coordinates":[8.8263845444,45.8176040649],"type":"Point"}
}