{
  "type": "Feature",
  "properties": {
    "iso:country":"IT",
    "sg:address":"10036 Settimo Torinese",
    "sg:city":"Settimo Torinese",
    "sg:orig_category":"Elettrotecnica Industriale, Prodotti E Apparecchiature",
    "sg:phone":"+39 011 897 7810",
    "sg:postcode":"10036",
    "sg:province":"Torino",
    "wof:name":"V.a.r.i. S.r.l.",
    "wof:placetype":"venue"
},
  "geometry": {"coordinates":[7.731885,45.147026],"type":"Point"}
}