{
  "type": "Feature",
  "properties": {
    "addr:full":"Via Leonardo Da Vinci 24036 Ponte San Pietro Ponte San Pietro Bergamo 24036",
    "addr:postcode":"24036;24036",
    "addr:street":"Via Leonardo Da Vinci",
    "iso:country":"IT",
    "sg:address":"Via Leonardo Da Vinci 24036 Ponte San Pietro",
    "sg:city":"Ponte San Pietro",
    "sg:classifiers":[
        {
            "category":"Shopping",
            "type":"Retail Goods"
        }
    ],
    "sg:phone":"+39 39035462470",
    "sg:postcode":"24036",
    "sg:province":"Bergamo",
    "sg:tags":[
        "finished",
        "-",
        "metallic"
    ],
    "wof:name":"Bridgeport Brass (s.p.a.)",
    "wof:placetype":"venue"
},
  "geometry": {"coordinates":[9.5986528397,45.710483551],"type":"Point"}
}