{
  "type": "Feature",
  "properties": {
    "iso:country":"IT",
    "sg:address":"56022 Castelfranco Di Sotto",
    "sg:city":"Castelfranco di Sotto",
    "sg:orig_category":"Calzature, Pelletterie E Pelli",
    "sg:phone":"+39 0571 480685",
    "sg:postcode":"56022",
    "sg:province":"Pisa",
    "wof:name":"Turipelle Di Puleo Salvatore",
    "wof:placetype":"venue"
},
  "geometry": {"coordinates":[10.747087,43.696678],"type":"Point"}
}