{
  "type": "Feature",
  "properties": {
    "iso:country":"IT",
    "sg:address":"51018 Pieve A Nievole",
    "sg:city":"Pieve a Nievole",
    "sg:orig_category":"Alimentari - Produzione E Ingrosso",
    "sg:phone":"+39 0572 51180",
    "sg:postcode":"51018",
    "sg:province":"Pistoia",
    "sg:website":"http://www.vlvservice.com",
    "wof:name":"V.l.v. Di Mattera Vincenzo & C. Sas",
    "wof:placetype":"venue"
},
  "geometry": {"coordinates":[10.789555,43.872185],"type":"Point"}
}