{
  "type": "Feature",
  "properties": {
    "iso:country":"IT",
    "sg:address":"20011 Corbetta",
    "sg:city":"Corbetta",
    "sg:orig_category":"Servizi E Lavori Per Industria Alimentare E Bevande",
    "sg:phone":"+39 02 9727 1505",
    "sg:postcode":"20011",
    "sg:province":"Milano",
    "wof:name":"La Piazzetta Societa'cooperativa A.r.l.",
    "wof:placetype":"venue"
},
  "geometry": {"coordinates":[8.933924,45.464149],"type":"Point"}
}