{
  "type": "Feature",
  "properties": {
    "iso:country":"IT",
    "sg:address":"32, V. Dei Mille 91025 Marsala",
    "sg:city":"Marsala",
    "sg:classifiers":[
        {
            "category":"Sports & Exercise",
            "subcategory":"Playing Field",
            "type":"Entertainment"
        }
    ],
    "sg:phone":"+39 0923 712438",
    "sg:postcode":"91025",
    "sg:province":"Trapani",
    "sg:tags":[
        "game"
    ],
    "sg:website":"http://www.paginegialle.it/ursorappresentanze",
    "wof:name":"Urso Cav. Pietro",
    "wof:placetype":"venue"
},
  "geometry": {"coordinates":[12.433411,37.796715],"type":"Point"}
}