{
  "type": "Feature",
  "properties": {
    "addr:full":"37038 Soave Soave Verona 37038",
    "addr:housenumber":"37038",
    "addr:postcode":"37038",
    "addr:street":"Soave Soave",
    "iso:country":"IT",
    "sg:address":"37038 Soave",
    "sg:city":"Soave",
    "sg:orig_category":"Macchine, Impianti Ed Attrezzature Per Industria Alimentare E Bevande. Apparecchiature E Sistemi Per Imballaggio E Confezionamento",
    "sg:phone":"+39 045 767 5023",
    "sg:postcode":"37038",
    "sg:province":"Verona",
    "wof:name":"Tebaldi Marco",
    "wof:placetype":"venue"
},
  "geometry": {"coordinates":[11.229652,45.435886],"type":"Point"}
}