{
  "type": "Feature",
  "properties": {
    "iso:country":"IT",
    "sg:address":"41012 Carpi",
    "sg:city":"Carpi",
    "sg:orig_category":"Maglieria - Produzione E Ingrosso",
    "sg:phone":"+39 059 692009",
    "sg:postcode":"41012",
    "sg:province":"Modena",
    "sg:website":"http://www.miba-tricot.com",
    "wof:name":"Mi-ba Tricot Srl",
    "wof:placetype":"venue"
},
  "geometry": {"coordinates":[10.917405,44.64642],"type":"Point"}
}