{
  "type": "Feature",
  "properties": {
    "addr:full":"1, Via Corazza L. 40012 Calderara Di Reno Calderara di Reno Bologna 40012",
    "addr:postcode":"40012;40012",
    "addr:street":"Via Corazza L.",
    "iso:country":"IT",
    "sg:address":"1, Via Corazza L. 40012 Calderara Di Reno",
    "sg:city":"Calderara di Reno",
    "sg:classifiers":[
        {
            "category":"Shopping",
            "subcategory":"Computers & Home Electronics",
            "type":"Retail Goods"
        }
    ],
    "sg:phone":"+39 39051727014",
    "sg:postcode":"40012",
    "sg:province":"Bologna",
    "sg:tags":[
        "electronic",
        "electrical",
        "equipment"
    ],
    "wof:name":"Niba (s.r.l.)",
    "wof:placetype":"venue"
},
  "geometry": {"coordinates":[11.35684,44.530346],"type":"Point"}
}