{
  "type": "Feature",
  "properties": {
    "iso:country":"IT",
    "sg:address":"36015 Schio",
    "sg:city":"Schio",
    "sg:orig_category":"Carpenterie Metalliche",
    "sg:phone":"+39 0445 575906",
    "sg:postcode":"36015",
    "sg:province":"Vicenza",
    "wof:name":"Albatros Di Fabris Moreno",
    "wof:placetype":"venue"
},
  "geometry": {"coordinates":[11.544188,45.574539],"type":"Point"}
}