{
  "type": "Feature",
  "properties": {
    "iso:country":"IT",
    "sg:address":"50137 Firenze",
    "sg:city":"Firenze",
    "sg:orig_category":"Accessori Dei Mezzi Di Trasporto. Riparazione Dei Mezzi Di Trasporto",
    "sg:phone":"+39 055 600921",
    "sg:postcode":"50137",
    "sg:province":"Firenze",
    "wof:name":"Suisola Valerio",
    "wof:placetype":"venue"
},
  "geometry": {"coordinates":[11.291897,43.78017],"type":"Point"}
}