{
  "type": "Feature",
  "properties": {
    "addr:full":"Via Fermana Sud; Montegranaro; 63014 Montegranaro Ascoli Piceno 63014",
    "addr:postcode":"63014;63014",
    "addr:street":"Via Fermana Sud",
    "iso:country":"IT",
    "sg:address":"Via Fermana Sud; Montegranaro; 63014",
    "sg:city":"Montegranaro",
    "sg:classifiers":[
        {
            "category":"Banks & Credit Unions",
            "subcategory":"Bank",
            "type":"Services"
        }
    ],
    "sg:phone":"+39 0734 890589",
    "sg:postcode":"63014",
    "sg:province":"Ascoli Piceno",
    "wof:name":"Banca Delle Marche Spa",
    "wof:placetype":"venue"
},
  "geometry": {"coordinates":[13.63268,43.224133],"type":"Point"}
}