{
  "type": "Feature",
  "properties": {
    "iso:country":"IT",
    "sg:address":"00156 Roma",
    "sg:city":"Roma",
    "sg:classifiers":[
        {
            "category":"Government",
            "subcategory":"Office",
            "type":"Public Place"
        }
    ],
    "sg:phone":"+39 06 411 5308",
    "sg:postcode":"00156",
    "sg:province":"Roma",
    "sg:tags":[
        "e",
        "lo",
        "tempo",
        "libero",
        "per",
        "spettacolo",
        "servizi",
        "culturali",
        "sport",
        "il"
    ],
    "wof:name":"I.u.m.a. Management Di Francesconi Renato",
    "wof:placetype":"venue"
},
  "geometry": {"coordinates":[12.57317,41.944096],"type":"Point"}
}