{
  "type": "Feature",
  "properties": {
    "addr:full":"16/c, Via Molini 35010 Villafranca Padovana Villafranca Padovana Padova 35010",
    "addr:housenumber":"16 / c",
    "addr:postcode":"35010;35010",
    "addr:street":"Via Molini",
    "iso:country":"IT",
    "sg:address":"16/c, Via Molini 35010 Villafranca Padovana",
    "sg:city":"Villafranca Padovana",
    "sg:classifiers":[
        {
            "category":"Shopping",
            "type":"Retail Goods"
        }
    ],
    "sg:phone":"+39 049 907 5151",
    "sg:postcode":"35010",
    "sg:province":"Padova",
    "sg:tags":[
        "finished",
        "-",
        "metallic"
    ],
    "wof:name":"Bilato (s.n.c.)",
    "wof:placetype":"venue"
},
  "geometry": {"coordinates":[11.8263711929,45.4500236511],"type":"Point"}
}