{
  "type": "Feature",
  "properties": {
    "addr:full":"81039 Villa Literno Villa Literno Caserta 81039",
    "addr:housenumber":"81039;literno",
    "addr:postcode":"81039",
    "addr:street":"Villa Literno",
    "iso:country":"IT",
    "sg:address":"81039 Villa Literno",
    "sg:city":"Villa Literno",
    "sg:orig_category":"Petroli, Gas E Combustibili",
    "sg:phone":"+39 081 892 8103",
    "sg:postcode":"81039",
    "sg:province":"Caserta",
    "wof:name":"C.t.p. Petroli Srl",
    "wof:placetype":"venue"
},
  "geometry": {"coordinates":[14.0702562332,41.0073928833],"type":"Point"}
}