{
  "type": "Feature",
  "properties": {
    "iso:country":"IT",
    "sg:address":"36015 Schio",
    "sg:city":"Schio",
    "sg:orig_category":"Macchine Ed Impianti Per Edilizia E Lavori Pubblici",
    "sg:phone":"+39 0445 576360",
    "sg:postcode":"36015",
    "sg:province":"Vicenza",
    "sg:website":"http://www.tci-italy.it",
    "wof:name":"Tci Srl",
    "wof:placetype":"venue"
},
  "geometry": {"coordinates":[11.39361,45.720131],"type":"Point"}
}