{
  "type": "Feature",
  "properties": {
    "iso:country":"IT",
    "sg:address":"59013 Montemurlo",
    "sg:city":"Montemurlo",
    "sg:orig_category":"Forniture Per Abbigliamento E Pelletterie",
    "sg:phone":"+39 0574 689226",
    "sg:postcode":"59013",
    "sg:province":"Prato",
    "wof:name":"Paolieri Paolo E C Snc",
    "wof:placetype":"venue"
},
  "geometry": {"coordinates":[11.0345411301,43.9015235901],"type":"Point"}
}