{
  "type": "Feature",
  "properties": {
    "addr:full":"14, V. Monegherio 20090 Cesano Boscone Cesano Boscone Milano 20090",
    "addr:housenumber":"14",
    "addr:postcode":"20090;20090",
    "addr:street":"V. Monegherio",
    "iso:country":"IT",
    "sg:address":"14, V. Monegherio 20090 Cesano Boscone",
    "sg:city":"Cesano Boscone",
    "sg:classifiers":[
        {
            "category":"Parking",
            "subcategory":"Lot",
            "type":"Transportation"
        }
    ],
    "sg:phone":"+39 02 4586 4393",
    "sg:postcode":"20090",
    "sg:province":"Milano",
    "sg:tags":[
        "transport",
        "road"
    ],
    "sg:website":"http://www.paginegialle.it/almtrasportisas",
    "wof:name":"A.l.m. Trasporti",
    "wof:placetype":"venue"
},
  "geometry": {"coordinates":[9.092815,45.448685],"type":"Point"}
}