{
  "type": "Feature",
  "properties": {
    "iso:country":"IT",
    "sg:address":"70020 Cassano Delle Murge",
    "sg:city":"Cassano delle Murge",
    "sg:orig_category":"Agricoltura - Attrezzi, Prodotti E Forniture",
    "sg:phone":"+39 080 764035",
    "sg:postcode":"70020",
    "sg:province":"Bari",
    "wof:name":"Vivai Razionali Gentile Del Dott. Agr. Vincenzo Gentile",
    "wof:placetype":"venue"
},
  "geometry": {"coordinates":[16.776432,40.890114],"type":"Point"}
}