{
  "type": "Feature",
  "properties": {
    "addr:full":"33085 Maniago Maniago Pordenone 33085",
    "addr:postcode":"33085;33085",
    "iso:country":"IT",
    "sg:address":"33085 Maniago",
    "sg:city":"Maniago",
    "sg:orig_category":"Utensili Meccanici E Materiali. Forniture Per Attivita' Industriali",
    "sg:phone":"+39 0427 733428",
    "sg:postcode":"33085",
    "sg:province":"Pordenone",
    "sg:website":"http://www.bemar.ws",
    "wof:name":"Bemar Snc Di Beltrame Marcello & Lorenzo",
    "wof:placetype":"venue"
},
  "geometry": {"coordinates":[12.716434,46.176659],"type":"Point"}
}