{
  "type": "Feature",
  "properties": {
    "addr:full":"05100 Terni Terni Terni 05100",
    "addr:postcode":"05100;05100",
    "iso:country":"IT",
    "sg:address":"05100 Terni",
    "sg:city":"Terni",
    "sg:orig_category":"Macchine, Impianti Ed Attrezzature Per Abbigliamento E Pelletterie",
    "sg:phone":"+39 0744 404316",
    "sg:postcode":"05100",
    "sg:province":"Terni",
    "wof:name":"Paloni Raimondo",
    "wof:placetype":"venue"
},
  "geometry": {"coordinates":[12.652127,42.563751],"type":"Point"}
}