{
  "type": "Feature",
  "properties": {
    "iso:country":"IT",
    "sg:address":"10091 Alpignano",
    "sg:city":"Alpignano",
    "sg:orig_category":"Agenzie D'affari E Servizi Commerciali",
    "sg:phone":"+39 011 978 7054",
    "sg:postcode":"10091",
    "sg:province":"Torino",
    "wof:name":"Ubiq Srl",
    "wof:placetype":"venue"
},
  "geometry": {"coordinates":[7.575098,45.08572],"type":"Point"}
}