{
  "type": "Feature",
  "properties": {
    "iso:country":"IT",
    "sg:address":"18100 Imperia",
    "sg:city":"Imperia",
    "sg:orig_category":"Servizi Vari Di Interesse Pubblico",
    "sg:phone":"+39 0183 767613",
    "sg:postcode":"18100",
    "sg:province":"Imperia",
    "wof:name":"L'angelo Azzurro",
    "wof:placetype":"venue"
},
  "geometry": {"coordinates":[8.040918,43.891323],"type":"Point"}
}