{
  "type": "Feature",
  "properties": {
    "iso:country":"IT",
    "sg:address":"38010 Andalo",
    "sg:city":"Andalo",
    "sg:orig_category":"Scuole Di Addestramento Sportivo",
    "sg:phone":"+39 0461 545702",
    "sg:postcode":"38010",
    "sg:province":"Trento",
    "wof:name":"Scuola Italiana Sci Andalo",
    "wof:placetype":"venue"
},
  "geometry": {"coordinates":[11.008556,46.168198],"type":"Point"}
}