{
  "type": "Feature",
  "properties": {
    "addr:full":"45021 Badia Polesine Badia Polesine Rovigo 45021",
    "addr:postcode":"45021;45021",
    "iso:country":"IT",
    "sg:address":"45021 Badia Polesine",
    "sg:city":"Badia Polesine",
    "sg:orig_category":"Certificazione Qualita', Sicurezza Ed Ambiente",
    "sg:phone":"+39 0425 590715",
    "sg:postcode":"45021",
    "sg:province":"Rovigo",
    "wof:name":"Agm Di Maragna Gianni",
    "wof:placetype":"venue"
},
  "geometry": {"coordinates":[11.498839,45.086094],"type":"Point"}
}