{
  "type": "Feature",
  "properties": {
    "addr:full":"00185 Roma Roma Roma 00185",
    "addr:postcode":"00185;00185",
    "iso:country":"IT",
    "sg:address":"00185 Roma",
    "sg:city":"Roma",
    "sg:orig_category":"Serramenti Ed Infissi",
    "sg:phone":"+39 06 446 6616",
    "sg:postcode":"00185",
    "sg:province":"Roma",
    "sg:website":"http://passarelli.it",
    "wof:name":"Passarelli Sas Di Passarelli Stefano & C.",
    "wof:placetype":"venue"
},
  "geometry": {"coordinates":[12.774099,41.956738],"type":"Point"}
}