{
  "type": "Feature",
  "properties": {
    "iso:country":"IT",
    "sg:address":"30124 Venezia",
    "sg:city":"San Marco",
    "sg:orig_category":"Assicurazioni E Servizi Assicurativi. Consulenze Tecniche, Amministrative E Perizie",
    "sg:phone":"+39 041 241 1485",
    "sg:postcode":"30124",
    "sg:province":"Venezia",
    "wof:name":"Studio Legale Associato Rebecchi & Barbieri",
    "wof:placetype":"venue"
},
  "geometry": {"coordinates":[12.337425,45.433746],"type":"Point"}
}