{
  "type": "Feature",
  "properties": {
    "iso:country":"IT",
    "sg:address":"Via Dell' Industria 99 36071 Arzignano",
    "sg:city":"Arzignano",
    "sg:classifiers":[
        {
            "category":"Wholesale",
            "subcategory":"Vending Machines",
            "type":"Manufacturing & Wholesale Goods"
        }
    ],
    "sg:phone":"+39 0444 474200",
    "sg:postcode":"36071",
    "sg:province":"Vicenza",
    "sg:tags":[
        "pharmaceutical",
        "industry",
        "encapsulating"
    ],
    "sg:website":"www.brevettiangela.com",
    "wof:name":"Brevetti Angela Srl",
    "wof:placetype":"venue"
},
  "geometry": {"coordinates":[11.353774,45.511902],"type":"Point"}
}