{
  "type": "Feature",
  "properties": {
    "iso:country":"IT",
    "sg:address":"Corso Garibaldi 2/c; Chiavari; 16043",
    "sg:city":"Chiavari",
    "sg:classifiers":[
        {
            "category":"Banks & Credit Unions",
            "subcategory":"Bank",
            "type":"Services"
        }
    ],
    "sg:phone":"+39 0185 304541",
    "sg:postcode":"16043",
    "sg:province":"Genova",
    "wof:name":"Credito Italiano Spa",
    "wof:placetype":"venue"
},
  "geometry": {"coordinates":[9.32555,44.314148],"type":"Point"}
}