{
  "type": "Feature",
  "properties": {
    "iso:country":"IT",
    "sg:address":"65/67, Via Santa Maria Maddalena 22060 Arosio",
    "sg:city":"Arosio",
    "sg:classifiers":[
        {
            "category":"Professional",
            "subcategory":"Engineering",
            "type":"Services"
        }
    ],
    "sg:phone":"+39 39031760611",
    "sg:postcode":"22060",
    "sg:province":"Como",
    "sg:tags":[
        "machine",
        "-",
        "mechanical"
    ],
    "wof:name":"Ima Spa",
    "wof:placetype":"venue"
},
  "geometry": {"coordinates":[9.208358,45.712616],"type":"Point"}
}