{
  "type": "Feature",
  "properties": {
    "iso:country":"IT",
    "sg:address":"50058 Signa",
    "sg:city":"Signa",
    "sg:orig_category":"Abbigliamento - Produzione E Ingrosso",
    "sg:phone":"+39 055 899 7406",
    "sg:postcode":"50058",
    "sg:province":"Firenze",
    "wof:name":"Catarzi Filippo Snc",
    "wof:placetype":"venue"
},
  "geometry": {"coordinates":[11.128779,43.795982],"type":"Point"}
}