{
  "type": "Feature",
  "properties": {
    "addr:full":"41100 Modena Modena Modena 41100",
    "addr:postcode":"41100;41100",
    "iso:country":"IT",
    "sg:address":"41100 Modena",
    "sg:city":"Modena",
    "sg:orig_category":"Arredamenti - Produzione E Ingrosso",
    "sg:phone":"+39 059 304760",
    "sg:postcode":"41100",
    "sg:province":"Modena",
    "wof:name":"Bettelli Giorgio Snc",
    "wof:placetype":"venue"
},
  "geometry": {"coordinates":[10.926041,44.635544],"type":"Point"}
}