{
  "type": "Feature",
  "properties": {
    "iso:country":"IT",
    "sg:address":"16, Via Fratelli Rosselli 21043 Castiglione Olona",
    "sg:city":"Castiglione Olona",
    "sg:classifiers":[
        {
            "category":"Shopping",
            "subcategory":"Clothing, Apparel, & Fashions",
            "type":"Retail Goods"
        }
    ],
    "sg:phone":"+39 0331 857566",
    "sg:postcode":"21043",
    "sg:province":"Varese",
    "sg:tags":[
        "clothing",
        "accessory"
    ],
    "wof:name":"Azeta Di Dieter Von Chamier & C. (s.a.s.)",
    "wof:placetype":"venue"
},
  "geometry": {"coordinates":[8.881177,45.754608],"type":"Point"}
}