{
  "type": "Feature",
  "properties": {
    "addr:full":"06077 Ponte Felcino PG",
    "addr:postcode":"06077",
    "addr:street":"Pg",
    "iso:country":"IT",
    "sg:address":"06077 Ponte Felcino",
    "sg:orig_category":"Avvocati, Notai E Servizi Legali. Consulenze Tecniche, Amministrative E Perizie",
    "sg:phone":"+39 075 591 3666",
    "sg:province":"PG",
    "wof:name":"Griga Advertising",
    "wof:placetype":"venue"
},
  "geometry": {"coordinates":[-72.259399,41.993801],"type":"Point"}
}