{
  "type": "Feature",
  "properties": {
    "addr:full":"Via Sevardi 7 42010 Mancasale Reggio Nell'Emilia 42010",
    "addr:housenumber":"7",
    "addr:postcode":"42010;42010",
    "addr:street":"Via Sevardi",
    "iso:country":"IT",
    "sg:address":"Via Sevardi 7 42010 Mancasale",
    "sg:orig_category":"Digital Video Broadcasting Dvb Equipment",
    "sg:phone":"+39 0522 509411",
    "sg:postcode":"42010",
    "sg:province":"Reggio Nell'Emilia",
    "sg:website":"www.cte.it",
    "wof:name":"Cte International S.r.l.",
    "wof:placetype":"venue"
},
  "geometry": {"coordinates":[10.658944,44.73996],"type":"Point"}
}