{
  "type": "Feature",
  "properties": {
    "iso:country":"IT",
    "sg:address":"40012 Calderara Di Reno",
    "sg:city":"Calderara di Reno",
    "sg:orig_category":"Trattamenti Termici Metalli",
    "sg:phone":"+39 051 727101",
    "sg:postcode":"40012",
    "sg:province":"Bologna",
    "wof:name":"Car-bo Srl",
    "wof:placetype":"venue"
},
  "geometry": {"coordinates":[11.266426,44.54108],"type":"Point"}
}