{
  "type": "Feature",
  "properties": {
    "addr:full":"22100 Como Como Como 22100",
    "addr:postcode":"22100;22100",
    "iso:country":"IT",
    "sg:address":"22100 Como",
    "sg:city":"Como",
    "sg:orig_category":"Frigotecnica, Apparecchiature E Servizi. Forniture Alle Strutture Ricettive",
    "sg:phone":"+39 031 305388",
    "sg:postcode":"22100",
    "sg:province":"Como",
    "sg:website":"http://www.forgrim.it",
    "wof:name":"Forgrim Srl",
    "wof:placetype":"venue"
},
  "geometry": {"coordinates":[9.0927476883,45.799282074],"type":"Point"}
}