{
  "type": "Feature",
  "properties": {
    "iso:country":"IT",
    "sg:address":"Via A. Da Schio 19 36051 Creazzo",
    "sg:city":"Creazzo",
    "sg:classifiers":[
        {
            "category":"Home & Garden",
            "subcategory":"Building Materials",
            "type":"Retail Goods"
        }
    ],
    "sg:phone":"+39 0444 340133",
    "sg:postcode":"36051",
    "sg:province":"Vicenza",
    "sg:tags":[
        "steel",
        "metal",
        "made",
        "door",
        "gate"
    ],
    "sg:website":"www.mdpoint.it/siaf",
    "wof:name":"S.i.a.f. Serramenti Snc",
    "wof:placetype":"venue"
},
  "geometry": {"coordinates":[11.49113,45.532654],"type":"Point"}
}