{
  "type": "Feature",
  "properties": {
    "iso:country":"IT",
    "sg:address":"9, Via Leonardo Da Vinci 36031 Dueville",
    "sg:city":"Dueville",
    "sg:classifiers":[
        {
            "category":"Manufacturing",
            "subcategory":"Metals",
            "type":"Manufacturing & Wholesale Goods"
        }
    ],
    "sg:phone":"+39 0444 945516",
    "sg:postcode":"36031",
    "sg:province":"Vicenza",
    "sg:tags":[
        "metallurgy",
        "metalworking"
    ],
    "wof:name":"Unifer S. R. L. Unipersonale",
    "wof:placetype":"venue"
},
  "geometry": {"coordinates":[11.565990448,45.6104545593],"type":"Point"}
}