{
  "type": "Feature",
  "properties": {
    "addr:full":"56029 S. Croce Sull'arno Pisa 56029",
    "addr:housenumber":"56029",
    "addr:postcode":"56029",
    "addr:street":"S. Croce Sull'Arno",
    "iso:country":"IT",
    "sg:address":"56029 S. Croce Sull'arno",
    "sg:classifiers":[
        {
            "category":"Manufacturing",
            "subcategory":"Leather Goods",
            "type":"Manufacturing & Wholesale Goods"
        }
    ],
    "sg:phone":"+39 0571 366123",
    "sg:postcode":"56029",
    "sg:province":"Pisa",
    "sg:tags":[
        "footwear",
        "skin"
    ],
    "wof:name":"Maber - Pell Srl",
    "wof:placetype":"venue"
},
  "geometry": {"coordinates":[10.3965845108,43.7161369324],"type":"Point"}
}