{
  "type": "Feature",
  "properties": {
    "addr:full":"Viale Innocenzo Xi 13; Como; 22100 Como Como 22100",
    "addr:housenumber":"13",
    "addr:postcode":"22100;22100",
    "addr:street":"Viale Innocenzo Xi",
    "iso:country":"IT",
    "sg:address":"Viale Innocenzo Xi 13; Como; 22100",
    "sg:city":"Como",
    "sg:classifiers":[
        {
            "category":"Banks & Credit Unions",
            "subcategory":"Bank",
            "type":"Services"
        }
    ],
    "sg:phone":"+39 031 279115",
    "sg:postcode":"22100",
    "sg:province":"Como",
    "wof:name":"Banca Briantea Spa",
    "wof:placetype":"venue"
},
  "geometry": {"coordinates":[9.077852,45.806911],"type":"Point"}
}