{
  "type": "Feature",
  "properties": {
    "iso:country":"IT",
    "sg:address":"10149 Torino",
    "sg:city":"Torino",
    "sg:orig_category":"Abiti Da Sposa E Cerimonia",
    "sg:phone":"+39 011 752244",
    "sg:postcode":"10149",
    "sg:province":"Torino",
    "wof:name":"Codo Vittorio",
    "wof:placetype":"venue"
},
  "geometry": {"coordinates":[7.593248,45.096569],"type":"Point"}
}