{
  "type": "Feature",
  "properties": {
    "iso:country":"IT",
    "sg:address":"00045 Genzano Di Roma",
    "sg:city":"Genzano di Roma",
    "sg:orig_category":"Automazione E Macchine Per Ufficio",
    "sg:phone":"+39 06 939 8495",
    "sg:postcode":"00045",
    "sg:province":"Roma",
    "wof:name":"Cinthia Telematica Srl",
    "wof:placetype":"venue"
},
  "geometry": {"coordinates":[12.466157,41.890396],"type":"Point"}
}