{
  "type": "Feature",
  "properties": {
    "iso:country":"IT",
    "sg:address":"25065 Lumezzane",
    "sg:city":"Lumezzane",
    "sg:orig_category":"Non-classified Establishments",
    "sg:phone":"+39 030 871102",
    "sg:postcode":"25065",
    "sg:province":"Brescia",
    "wof:name":"Zanetti Emiliano & C. (s.n.c.)",
    "wof:placetype":"venue"
},
  "geometry": {"coordinates":[10.220812,45.601948],"type":"Point"}
}