{
  "type": "Feature",
  "properties": {
    "iso:country":"IT",
    "sg:address":"00035 Olevano Romano",
    "sg:city":"Olevano Romano",
    "sg:orig_category":"Impiantistica E Prodotti Tecnologici Per Edilizia. Climatizzazione E Condizionamento, Apparecchiature E Servizi",
    "sg:phone":"+39 06 9560 9056",
    "sg:postcode":"00035",
    "sg:province":"Roma",
    "wof:name":"Schinterm Srl",
    "wof:placetype":"venue"
},
  "geometry": {"coordinates":[13.024173,41.856869],"type":"Point"}
}