{
  "type": "Feature",
  "properties": {
    "iso:country":"IT",
    "sg:address":"Via Calvi Fratelli 15 24122 Bergamo",
    "sg:city":"Bergamo",
    "sg:orig_category":"Video Cards",
    "sg:phone":"+39 035 424 9511",
    "sg:postcode":"24122",
    "sg:province":"Bergamo",
    "sg:website":"www.interpack.it",
    "wof:name":"Interpack Italia Srl",
    "wof:placetype":"venue"
},
  "geometry": {"coordinates":[9.669952,45.694904],"type":"Point"}
}