{
  "type": "Feature",
  "properties": {
    "addr:full":"Km 2.00, Str. Prov. Trani-andria 70059 Trani Trani Bari 70059",
    "addr:postcode":"70059;70059",
    "addr:street":"Km 2.00 Str. Prov. Trani-Andria",
    "iso:country":"IT",
    "sg:address":"Km 2.00, Str. Prov. Trani-andria 70059 Trani",
    "sg:city":"Trani",
    "sg:classifiers":[
        {
            "category":"Real Estate",
            "subcategory":"Surveying",
            "type":"Services"
        }
    ],
    "sg:phone":"+39 0883 484004",
    "sg:postcode":"70059",
    "sg:province":"Bari",
    "sg:tags":[
        "raw",
        "energy",
        "material"
    ],
    "sg:website":"http://www.paginegialle.it/",
    "wof:name":"Campanile Marmi Di Campanile Antonio",
    "wof:placetype":"venue"
},
  "geometry": {"coordinates":[16.869291,41.126053],"type":"Point"}
}