{
  "type": "Feature",
  "properties": {
    "iso:country":"IT",
    "sg:address":"16165 Genova",
    "sg:city":"Genova",
    "sg:orig_category":"Lucidatura, Laccatura E Verniciatura Mobili",
    "sg:phone":"+39 010 830 1275",
    "sg:postcode":"16165",
    "sg:province":"Genova",
    "wof:name":"Ve.met. Sas",
    "wof:placetype":"venue"
},
  "geometry": {"coordinates":[9.018388,44.448132],"type":"Point"}
}