{
  "type": "Feature",
  "properties": {
    "iso:country":"IT",
    "sg:address":"10155 Torino",
    "sg:city":"Torino",
    "sg:orig_category":"Tessuti Arredamento, Tende E Tappeti",
    "sg:phone":"+39 011 200890",
    "sg:postcode":"10155",
    "sg:province":"Torino",
    "wof:name":"Fracchia Snc",
    "wof:placetype":"venue"
},
  "geometry": {"coordinates":[7.695901,45.101139],"type":"Point"}
}