{
  "type": "Feature",
  "properties": {
    "iso:country":"IT",
    "sg:address":"Via Lambro 48 20090 Opera",
    "sg:city":"Opera",
    "sg:orig_category":"Semi-finished Products Of Light Metal",
    "sg:phone":"+39 02 5760 1070",
    "sg:postcode":"20090",
    "sg:province":"Milano",
    "sg:website":"web.tiscali.it/mtmsrl",
    "wof:name":"Maiocchi & Torelli Srl",
    "wof:placetype":"venue"
},
  "geometry": {"coordinates":[9.199254,45.368916],"type":"Point"}
}