{
  "type": "Feature",
  "properties": {
    "iso:country":"IT",
    "sg:address":"00187 Roma",
    "sg:city":"Roma",
    "sg:classifiers":[
        {
            "category":"Professional",
            "subcategory":"Business Services",
            "type":"Services"
        }
    ],
    "sg:phone":"+39 06 478681",
    "sg:postcode":"00187",
    "sg:province":"Roma",
    "sg:tags":[
        "support",
        "companies",
        "events",
        "trade"
    ],
    "sg:website":"http://www.tritonecenter.com",
    "wof:name":"Tritone Center Srl",
    "wof:placetype":"venue"
},
  "geometry": {"coordinates":[12.487182,41.903229],"type":"Point"}
}