{
  "type": "Feature",
  "properties": {
    "iso:country":"IT",
    "sg:address":"Via Setaioli Blocco 3 40050 Argelato",
    "sg:city":"Argelato",
    "sg:classifiers":[
        {
            "category":"Shopping",
            "subcategory":"Clothing, Apparel, & Fashions",
            "type":"Retail Goods"
        }
    ],
    "sg:phone":"+39 39051861391",
    "sg:postcode":"40050",
    "sg:province":"Bologna",
    "sg:tags":[
        "clothes"
    ],
    "wof:name":"Crazy Wool (s.r.l.)",
    "wof:placetype":"venue"
},
  "geometry": {"coordinates":[11.346481,44.494221],"type":"Point"}
}