{
  "type": "Feature",
  "properties": {
    "addr:full":"04100 Latina Latina Latina 04100",
    "addr:postcode":"04100;04100",
    "iso:country":"IT",
    "sg:address":"04100 Latina",
    "sg:city":"Latina",
    "sg:classifiers":[
        {
            "category":"Home & Garden",
            "subcategory":"Carpets & Floor Coverings",
            "type":"Retail Goods"
        }
    ],
    "sg:phone":"+39 0773 479038",
    "sg:postcode":"04100",
    "sg:province":"Latina",
    "sg:tags":[
        "building",
        "supply",
        "civil",
        "industry",
        "furnishing",
        "curtain",
        "works",
        "fabrics",
        "carpets"
    ],
    "wof:name":"Home Di Dino Di Prospero",
    "wof:placetype":"venue"
},
  "geometry": {"coordinates":[12.8744945526,41.4521484375],"type":"Point"}
}