{
  "type": "Feature",
  "properties": {
    "iso:country":"IT",
    "sg:address":"20099 Sesto San Giovanni",
    "sg:city":"Sesto San Giovanni",
    "sg:orig_category":"Chiese Ed Associazioni Religiose",
    "sg:phone":"+39 02 262 1675",
    "sg:postcode":"20099",
    "sg:province":"Milano",
    "wof:name":"Parrocchia Prepositurale S. Stefano",
    "wof:placetype":"venue"
},
  "geometry": {"coordinates":[9.240916,45.536552],"type":"Point"}
}