{
  "type": "Feature",
  "properties": {
    "addr:full":"00183 Roma Roma Roma 00183",
    "addr:postcode":"00183;00183",
    "iso:country":"IT",
    "sg:address":"00183 Roma",
    "sg:city":"Roma",
    "sg:orig_category":"Prodotti E Manufatti In Materie Plastiche. Articoli Per Imballaggio E Confezionamento",
    "sg:phone":"+39 06 701 7389",
    "sg:postcode":"00183",
    "sg:province":"Roma",
    "wof:name":"Artigiana 2000 Di R. Antonetti",
    "wof:placetype":"venue"
},
  "geometry": {"coordinates":[12.5168247223,41.8768539429],"type":"Point"}
}