{
  "type": "Feature",
  "properties": {
    "iso:country":"IT",
    "sg:address":"23880 Casatenovo",
    "sg:city":"Casatenovo",
    "sg:orig_category":"Gioielleria, Oreficeria E Argenteria",
    "sg:phone":"+39 039 920 5357",
    "sg:postcode":"23880",
    "sg:province":"Lecco",
    "sg:website":"http://www.colombogioielleria.it",
    "wof:name":"Co.ri. Sas Di Colombo Dario, Fausto & C.",
    "wof:placetype":"venue"
},
  "geometry": {"coordinates":[9.318551,45.680695],"type":"Point"}
}