{
  "type": "Feature",
  "properties": {
    "iso:country":"IT",
    "sg:address":"65013 Citta's.angelo",
    "sg:orig_category":"Abbigliamento Esterno, Maglierie E Pelliccerie. Shopping",
    "sg:phone":"+39 085 950 6148",
    "sg:postcode":"65013",
    "sg:province":"Pescara",
    "sg:website":"http://www.maximport.com",
    "wof:name":"Max Import",
    "wof:placetype":"venue"
},
  "geometry": {"coordinates":[14.128884,42.514599],"type":"Point"}
}