{
  "type": "Feature",
  "properties": {
    "iso:country":"IT",
    "sg:address":"00198 Roma",
    "sg:city":"Roma",
    "sg:orig_category":"Scuole E Servizi Scolastici. Ospedali E Servizi Sanitari",
    "sg:phone":"+39 06 8424 2103",
    "sg:postcode":"00198",
    "sg:province":"Roma",
    "wof:name":"Ass.ne Istituto Formaz.e Ricerca Per Educat.epsicoterap.",
    "wof:placetype":"venue"
},
  "geometry": {"coordinates":[12.427947,41.845974],"type":"Point"}
}