{
  "type": "Feature",
  "properties": {
    "iso:country":"IT",
    "sg:address":"35020 Casalserugo",
    "sg:city":"Casalserugo",
    "sg:orig_category":"Macchine, Impianti Ed Attrezzature Per Agricoltura E Zootecnia",
    "sg:phone":"+39 049 643082",
    "sg:postcode":"35020",
    "sg:province":"Padova",
    "wof:name":"Aduso Franco Serre (s.r.l.)",
    "wof:placetype":"venue"
},
  "geometry": {"coordinates":[11.912035,45.319717],"type":"Point"}
}