{
  "type": "Feature",
  "properties": {
    "addr:full":"Via Per Civesio 10 20097 San Donato Milanese San Donato Milanese Milano 20097",
    "addr:housenumber":"10",
    "addr:postcode":"20097;20097",
    "addr:street":"Via Per Civesio",
    "iso:country":"IT",
    "sg:address":"Via Per Civesio 10 20097 San Donato Milanese",
    "sg:city":"San Donato Milanese",
    "sg:orig_category":"Electric Platform Tractors",
    "sg:phone":"+39 02 527 8541",
    "sg:postcode":"20097",
    "sg:province":"Milano",
    "sg:website":"www.simai.it",
    "wof:name":"S.i.m.a.i. Spa",
    "wof:placetype":"venue"
},
  "geometry": {"coordinates":[9.262789,45.40522],"type":"Point"}
}