{
  "type": "Feature",
  "properties": {
    "iso:country":"IT",
    "sg:address":"57/a, V. Gaidano 10137 Torino",
    "sg:city":"Torino",
    "sg:classifiers":[
        {
            "category":"Farming",
            "subcategory":"Livestock Farm",
            "type":"Manufacturing & Wholesale Goods"
        }
    ],
    "sg:phone":"+39 011 311 3747",
    "sg:postcode":"10137",
    "sg:province":"Torino",
    "sg:tags":[
        "agriculture"
    ],
    "sg:website":"http://www.s-g-perez.it:ws_end: :mark:ws:http://www.paginegialle.it/sg-perez",
    "wof:name":"S.g. Di Perez G. & C. Sas Alimentari",
    "wof:placetype":"venue"
},
  "geometry": {"coordinates":[7.626155,45.039654],"type":"Point"}
}