{
  "type": "Feature",
  "properties": {
    "iso:country":"IT",
    "sg:address":"00135 Roma",
    "sg:city":"Roma",
    "sg:orig_category":"Pubblica Amministrazione",
    "sg:phone":"+39 06 331841",
    "sg:postcode":"00135",
    "sg:province":"Roma",
    "wof:name":"Marina Militare Italiana",
    "wof:placetype":"venue"
},
  "geometry": {"coordinates":[12.4520950317,41.9569358826],"type":"Point"}
}