{
  "type": "Feature",
  "properties": {
    "addr:full":"40, V. Rigla 24010 Ponteranica Ponteranica Bergamo 24010",
    "addr:housenumber":"40",
    "addr:postcode":"24010;24010",
    "addr:street":"V. Rigla",
    "iso:country":"IT",
    "sg:address":"40, V. Rigla 24010 Ponteranica",
    "sg:city":"Ponteranica",
    "sg:classifiers":[
        {
            "category":"Home & Garden",
            "subcategory":"Home Furnishings",
            "type":"Retail Goods"
        }
    ],
    "sg:phone":"+39 39035575017",
    "sg:postcode":"24010",
    "sg:province":"Bergamo",
    "sg:tags":[
        "household"
    ],
    "sg:website":"http://www.verdevip.it:ws_end: :mark:ws:http://www.paginegialle.it/verdevip-bg",
    "wof:name":"Verdevip Srl",
    "wof:placetype":"venue"
},
  "geometry": {"coordinates":[9.647983,45.734306],"type":"Point"}
}