{
  "type": "Feature",
  "properties": {
    "iso:country":"IT",
    "sg:address":"43, Via Di Vittorio Giuseppe 20017 Rho",
    "sg:city":"Rho",
    "sg:classifiers":[
        {
            "category":"Wholesale",
            "subcategory":"Drugs",
            "type":"Manufacturing & Wholesale Goods"
        }
    ],
    "sg:phone":"+39 39029317961",
    "sg:postcode":"20017",
    "sg:province":"Milano",
    "sg:tags":[
        "chemical",
        "pharmaceutical"
    ],
    "wof:name":"Nuncas Italia S.p.a.",
    "wof:placetype":"venue"
},
  "geometry": {"coordinates":[9.084982,45.525616],"type":"Point"}
}