{
  "type": "Feature",
  "properties": {
    "iso:country":"IT",
    "sg:address":"80146 Napoli",
    "sg:city":"Napoli",
    "sg:orig_category":"Macchine, Impianti E Forniture Per Industria Grafica, Cartaria E Cartotecnica. Automazione E Macchine Per Ufficio",
    "sg:phone":"+39 081 752 9768",
    "sg:postcode":"80146",
    "sg:province":"Napoli",
    "sg:website":"http://www.partenufficio.it",
    "wof:name":"Partenufficio Sas",
    "wof:placetype":"venue"
},
  "geometry": {"coordinates":[14.295424,40.839664],"type":"Point"}
}