{
  "type": "Feature",
  "properties": {
    "addr:full":"130, Strada Della Droma 30126 Venezia Venezia Venezia 30126",
    "addr:postcode":"30126;30126",
    "addr:street":"Strada Della Droma",
    "iso:country":"IT",
    "sg:address":"130, Strada Della Droma 30126 Venezia",
    "sg:city":"Venezia",
    "sg:classifiers":[
        {
            "category":"Farming",
            "subcategory":"Livestock Farm",
            "type":"Manufacturing & Wholesale Goods"
        }
    ],
    "sg:phone":"+39 39041731122",
    "sg:postcode":"30126",
    "sg:province":"Venezia",
    "sg:tags":[
        "agriculture"
    ],
    "wof:name":"Mitilpesca (s.r.l.)",
    "wof:placetype":"venue"
},
  "geometry": {"coordinates":[12.325258,45.350555],"type":"Point"}
}