{
  "type": "Feature",
  "properties": {
    "iso:country":"IT",
    "sg:address":"34071 Cormons",
    "sg:city":"Cormons",
    "sg:orig_category":"Lavorazioni Metalli, Stampaggio E Saldatura",
    "sg:phone":"+39 0481 60154",
    "sg:postcode":"34071",
    "sg:province":"Gorizia",
    "wof:name":"C.m.f. S.r.l.",
    "wof:placetype":"venue"
},
  "geometry": {"coordinates":[13.617157,45.94735],"type":"Point"}
}