{
  "type": "Feature",
  "properties": {
    "iso:country":"IT",
    "sg:address":"14055 Costigliole D'asti",
    "sg:orig_category":"Elettrodomestici - Produzione E Ingrosso",
    "sg:phone":"+39 0141 969494",
    "sg:postcode":"14055",
    "sg:province":"Asti",
    "wof:name":"In.el.pi. Spa",
    "wof:placetype":"venue"
},
  "geometry": {"coordinates":[8.142056,44.807323],"type":"Point"}
}