{
  "type": "Feature",
  "properties": {
    "iso:country":"IT",
    "sg:address":"80078 Napoli",
    "sg:city":"Pozzuoli",
    "sg:orig_category":"Marketing E Ricerche Di Mercato",
    "sg:phone":"+39 081 525 5111",
    "sg:postcode":"80078",
    "sg:province":"Napoli",
    "wof:name":"Alterego Srl",
    "wof:placetype":"venue"
},
  "geometry": {"coordinates":[14.121622,40.823746],"type":"Point"}
}