{
  "type": "Feature",
  "properties": {
    "addr:full":"Sauris Di Sotto 88 33020 Sauris Sauris Udine 33020",
    "addr:housenumber":"88",
    "addr:postcode":"33020;33020",
    "addr:street":"Sauris Di Sotto",
    "iso:country":"IT",
    "sg:address":"Sauris Di Sotto 88 33020 Sauris",
    "sg:city":"Sauris",
    "sg:classifiers":[
        {
            "category":"Food & Beverages",
            "subcategory":"Meat & Fish",
            "type":"Retail Goods"
        }
    ],
    "sg:phone":"+39 0433 86054",
    "sg:postcode":"33020",
    "sg:province":"Udine",
    "sg:tags":[
        "sausage",
        "cured",
        "product",
        "dried"
    ],
    "sg:website":"www.wolfsauris.it",
    "wof:name":"Prosciuttificio Wolf Sauris Spa",
    "wof:placetype":"venue"
},
  "geometry": {"coordinates":[13.230724,46.064941],"type":"Point"}
}