{
  "type": "Feature",
  "properties": {
    "addr:full":"20129 Milano Milano Milano 20129",
    "addr:postcode":"20129;20129",
    "iso:country":"IT",
    "sg:address":"20129 Milano",
    "sg:city":"Milano",
    "sg:orig_category":"Abbigliamento Intimo, Calze E Costumi Da Bagno. Sport - Articoli E Forniture. Shopping",
    "sg:phone":"+39 02 2940 5892",
    "sg:postcode":"20129",
    "sg:province":"Milano",
    "wof:name":"Summertime Sas Di Porru Fabio E C.",
    "wof:placetype":"venue"
},
  "geometry": {"coordinates":[9.212799,45.475502],"type":"Point"}
}