{
  "type": "Feature",
  "properties": {
    "iso:country":"IT",
    "sg:address":"31, Via Nazionale 33011 Artegna",
    "sg:city":"Artegna",
    "sg:classifiers":[
        {
            "category":"Manufacturing",
            "subcategory":"Metals",
            "type":"Manufacturing & Wholesale Goods"
        }
    ],
    "sg:phone":"+39 0432 977277",
    "sg:postcode":"33011",
    "sg:province":"Udine",
    "sg:tags":[
        "metallurgy",
        "metalworking"
    ],
    "wof:name":"De Monte Center (s.p.a.)",
    "wof:placetype":"venue"
},
  "geometry": {"coordinates":[13.1719264984,46.2253456116],"type":"Point"}
}