{
  "type": "Feature",
  "properties": {
    "addr:full":"9, Via Oglio 00198 Roma Roma Roma 00198",
    "addr:postcode":"00198;00198",
    "addr:street":"Via Oglio",
    "iso:country":"IT",
    "sg:address":"9, Via Oglio 00198 Roma",
    "sg:city":"Roma",
    "sg:classifiers":[
        {
            "category":"Professional",
            "subcategory":"Business Services",
            "type":"Services"
        }
    ],
    "sg:phone":"+39 39068550263",
    "sg:postcode":"00198",
    "sg:province":"Roma",
    "sg:tags":[
        "advice"
    ],
    "wof:name":"A.n.i.t.a.",
    "wof:placetype":"venue"
},
  "geometry": {"coordinates":[12.502576,41.922009],"type":"Point"}
}