{
  "type": "Feature",
  "properties": {
    "addr:full":"60126 Ancona Ancona Ancona 60126",
    "addr:postcode":"60126;60126",
    "iso:country":"IT",
    "sg:address":"60126 Ancona",
    "sg:city":"Ancona",
    "sg:orig_category":"Frigotecnica, Apparecchiature E Servizi",
    "sg:phone":"+39 071 280 2318",
    "sg:postcode":"60126",
    "sg:province":"Ancona",
    "wof:name":"Carletti Lido",
    "wof:placetype":"venue"
},
  "geometry": {"coordinates":[13.5033512115,43.6025848389],"type":"Point"}
}