{
  "type": "Feature",
  "properties": {
    "addr:full":"66, Via Monte Grappa 87100 Cosenza Cosenza Cosenza 87100",
    "addr:postcode":"87100;87100",
    "addr:street":"Via Monte Grappa",
    "iso:country":"IT",
    "sg:address":"66, Via Monte Grappa 87100 Cosenza",
    "sg:city":"Cosenza",
    "sg:classifiers":[
        {
            "category":"Banks & Credit Unions",
            "subcategory":"Bank",
            "type":"Services"
        }
    ],
    "sg:phone":"+39 39098423923",
    "sg:postcode":"87100",
    "sg:province":"Cosenza",
    "sg:tags":[
        "banking",
        "institution"
    ],
    "wof:name":"Istituti Riuniti Di Vigilanza S.r.l.",
    "wof:placetype":"venue"
},
  "geometry": {"coordinates":[16.251617,39.295815],"type":"Point"}
}