{
  "type": "Feature",
  "properties": {
    "iso:country":"IT",
    "sg:address":"38, Via Missori Giuseppe 20035 Lissone",
    "sg:city":"Lissone",
    "sg:classifiers":[
        {
            "category":"Shopping",
            "subcategory":"Clothing, Apparel, & Fashions",
            "type":"Retail Goods"
        }
    ],
    "sg:phone":"+39 039 214 3007",
    "sg:postcode":"20035",
    "sg:province":"Milano",
    "sg:tags":[
        "clothing",
        "accessory"
    ],
    "wof:name":"Roma Spa",
    "wof:placetype":"venue"
},
  "geometry": {"coordinates":[9.188141,45.463688],"type":"Point"}
}