{
  "type": "Feature",
  "properties": {
    "iso:country":"IT",
    "sg:address":"22, V. Firenze 98070 Torrenova",
    "sg:city":"Torrenova",
    "sg:classifiers":[
        {
            "category":"Food & Beverages",
            "subcategory":"Groceries & Convenience Stores",
            "type":"Retail Goods"
        }
    ],
    "sg:phone":"+39 0941 785751",
    "sg:postcode":"98070",
    "sg:province":"Messina",
    "sg:tags":[
        "drink"
    ],
    "sg:website":"http://www.lemontorre.it",
    "wof:name":"Lemontorre",
    "wof:placetype":"venue"
},
  "geometry": {"coordinates":[14.675385,38.09219],"type":"Point"}
}