{
  "type": "Feature",
  "properties": {
    "iso:country":"IT",
    "sg:address":"62100 Macerata",
    "sg:city":"Macerata",
    "sg:orig_category":"Arte Ed Artigianato Artistico",
    "sg:phone":"+39 0733 367025",
    "sg:postcode":"62100",
    "sg:province":"Macerata",
    "wof:name":"Malena Cataldo",
    "wof:placetype":"venue"
},
  "geometry": {"coordinates":[13.438386,43.292603],"type":"Point"}
}