{
  "type": "Feature",
  "properties": {
    "addr:full":"25030 Castelmella Brescia 25030",
    "addr:postcode":"25030;25030",
    "iso:country":"IT",
    "sg:address":"25030 Castelmella",
    "sg:orig_category":"Motori Ed Organi Di Trasmissione",
    "sg:phone":"+39 030 358 3245",
    "sg:postcode":"25030",
    "sg:province":"Brescia",
    "wof:name":"Bergamo Trasmissioni Srl",
    "wof:placetype":"venue"
},
  "geometry": {"coordinates":[10.1496591568,45.4880828857],"type":"Point"}
}