{
  "type": "Feature",
  "properties": {
    "iso:country":"IT",
    "sg:address":"00153 Roma",
    "sg:city":"Roma",
    "sg:orig_category":"Servizi Ausiliari Di Sorveglianza, Manutenzione E Pulizia. Servizi Vari Di Interesse Pubblico",
    "sg:phone":"+39 06 581 1352",
    "sg:postcode":"00153",
    "sg:province":"Roma",
    "wof:name":"C/work Agency",
    "wof:placetype":"venue"
},
  "geometry": {"coordinates":[12.471861,41.88858],"type":"Point"}
}