{
  "type": "Feature",
  "properties": {
    "addr:full":"4, Via Industria 35020 Brugine Brugine Padova 35020",
    "addr:postcode":"35020;35020",
    "addr:street":"Via Industria",
    "iso:country":"IT",
    "sg:address":"4, Via Industria 35020 Brugine",
    "sg:city":"Brugine",
    "sg:classifiers":[
        {
            "category":"Shopping",
            "type":"Retail Goods"
        }
    ],
    "sg:phone":"+39 049 580 6027",
    "sg:postcode":"35020",
    "sg:province":"Padova",
    "sg:tags":[
        "finished",
        "-",
        "metallic"
    ],
    "wof:name":"Eurostampi (snc)",
    "wof:placetype":"venue"
},
  "geometry": {"coordinates":[11.9988136292,45.3077011108],"type":"Point"}
}