{
  "type": "Feature",
  "properties": {
    "addr:full":"1, Strada Borgaretto 10043 Orbassano Orbassano Torino 10043",
    "addr:postcode":"10043;10043",
    "addr:street":"Strada Borgaretto",
    "iso:country":"IT",
    "sg:address":"1, Strada Borgaretto 10043 Orbassano",
    "sg:city":"Orbassano",
    "sg:classifiers":[
        {
            "category":"Manufacturing",
            "subcategory":"Metals",
            "type":"Manufacturing & Wholesale Goods"
        }
    ],
    "sg:phone":"+39 011 901 6916",
    "sg:postcode":"10043",
    "sg:province":"Torino",
    "sg:tags":[
        "processing"
    ],
    "wof:name":"Tecnosteel S.r.l.",
    "wof:placetype":"venue"
},
  "geometry": {"coordinates":[7.5892801285,45.0125732422],"type":"Point"}
}