{
  "type": "Feature",
  "properties": {
    "iso:country":"IT",
    "sg:address":"5, Via Falcone 20123 Milano",
    "sg:city":"Milano",
    "sg:classifiers":[
        {
            "category":"Professional",
            "subcategory":"Engineering",
            "type":"Services"
        }
    ],
    "sg:phone":"+39 390 286 5760",
    "sg:postcode":"20123",
    "sg:province":"Milano",
    "sg:tags":[
        "machine",
        "-",
        "mechanical"
    ],
    "wof:name":"Ala Data System (s.r.l.)",
    "wof:placetype":"venue"
},
  "geometry": {"coordinates":[9.187742,45.46249],"type":"Point"}
}