{
  "type": "Feature",
  "properties": {
    "iso:country":"IT",
    "sg:address":"7, Via Salmazza 15032 Borgo San Martino",
    "sg:city":"Borgo San Martino",
    "sg:classifiers":[
        {
            "category":"Food & Beverages",
            "subcategory":"Groceries & Convenience Stores",
            "type":"Retail Goods"
        }
    ],
    "sg:phone":"+39 0142 429207",
    "sg:postcode":"15032",
    "sg:province":"Alessandria",
    "sg:tags":[
        "product",
        "related"
    ],
    "wof:name":"Zerbinati S.r.l.",
    "wof:placetype":"venue"
},
  "geometry": {"coordinates":[8.5258264542,45.0838470459],"type":"Point"}
}