{
  "type": "Feature",
  "properties": {
    "iso:country":"IT",
    "sg:address":"20077 Melegnano",
    "sg:city":"Melegnano",
    "sg:orig_category":"Prodotti Alimentari",
    "sg:phone":"+39 02 983 4717",
    "sg:postcode":"20077",
    "sg:province":"Milano",
    "wof:name":"Bruzzi Vera",
    "wof:placetype":"venue"
},
  "geometry": {"coordinates":[9.2798242569,45.3989219666],"type":"Point"}
}