{
  "type": "Feature",
  "properties": {
    "iso:country":"IT",
    "sg:address":"23026 Ponte In Valtellina",
    "sg:city":"Ponte in Valtellina",
    "sg:orig_category":"Forniture Per Agricoltura E Zootecnia. Prodotti Chimici Secondari",
    "sg:phone":"+39 0342 482178",
    "sg:postcode":"23026",
    "sg:province":"Sondrio",
    "wof:name":"Giuliani Bruno",
    "wof:placetype":"venue"
},
  "geometry": {"coordinates":[9.9797925949,46.1724510193],"type":"Point"}
}