{
  "type": "Feature",
  "properties": {
    "addr:full":"41100 Modena Modena Modena 41100",
    "addr:postcode":"41100;41100",
    "iso:country":"IT",
    "sg:address":"41100 Modena",
    "sg:city":"Modena",
    "sg:orig_category":"Arredo Cucina Ed Elettrodomestici. Elettrodomestici",
    "sg:phone":"+39 059 31114",
    "sg:postcode":"41100",
    "sg:province":"Modena",
    "wof:name":"Ditta Ghinelli Giovanni",
    "wof:placetype":"venue"
},
  "geometry": {"coordinates":[10.938716,44.548519],"type":"Point"}
}