{
  "type": "Feature",
  "properties": {
    "iso:country":"IT",
    "sg:address":"13, Via Leonardo Da Vinci 35042 Este",
    "sg:city":"Este",
    "sg:classifiers":[
        {
            "category":"Wholesale",
            "subcategory":"Drugs",
            "type":"Manufacturing & Wholesale Goods"
        }
    ],
    "sg:phone":"+39 390 429 4538",
    "sg:postcode":"35042",
    "sg:province":"Padova",
    "sg:tags":[
        "chemical",
        "pharmaceutical"
    ],
    "wof:name":"Montros Abrasivi Di Sguoti Giulio & C. (s.n.c.)",
    "wof:placetype":"venue"
},
  "geometry": {"coordinates":[11.686797,45.222809],"type":"Point"}
}