{
  "type": "Feature",
  "properties": {
    "addr:full":"10099 San Mauro Torinese San Mauro Torinese Torino 10099",
    "addr:housenumber":"10099",
    "addr:postcode":"10099",
    "addr:street":"San",
    "iso:country":"IT",
    "sg:address":"10099 San Mauro Torinese",
    "sg:city":"San Mauro Torinese",
    "sg:orig_category":"Forniture Per Uffici. Regalistica Aziendale",
    "sg:phone":"+39 011 223 6881",
    "sg:postcode":"10099",
    "sg:province":"Torino",
    "wof:name":"Etafelt Srl",
    "wof:placetype":"venue"
},
  "geometry": {"coordinates":[7.7475185394,45.1180610657],"type":"Point"}
}