{
  "type": "Feature",
  "properties": {
    "iso:country":"IT",
    "sg:address":"6, Via Mosa 20017 Rho",
    "sg:city":"Rho",
    "sg:classifiers":[
        {
            "category":"Wholesale",
            "subcategory":"Drugs",
            "type":"Manufacturing & Wholesale Goods"
        }
    ],
    "sg:phone":"+39 39029316804",
    "sg:postcode":"20017",
    "sg:province":"Milano",
    "sg:tags":[
        "chemical",
        "pharmaceutical"
    ],
    "wof:name":"Hydro - Line (s.p.a.)",
    "wof:placetype":"venue"
},
  "geometry": {"coordinates":[9.046453,45.516228],"type":"Point"}
}