{
  "type": "Feature",
  "properties": {
    "iso:country":"IT",
    "sg:address":"01016 Tarquinia",
    "sg:city":"Tarquinia",
    "sg:orig_category":"Prodotti Alimentari",
    "sg:phone":"+39 0766 856662",
    "sg:postcode":"01016",
    "sg:province":"Viterbo",
    "wof:name":"San Carlo G. A. S.p.a.",
    "wof:placetype":"venue"
},
  "geometry": {"coordinates":[11.7373905182,42.2401618958],"type":"Point"}
}