{
  "type": "Feature",
  "properties": {
    "iso:country":"IT",
    "sg:address":"43100 Parma",
    "sg:city":"Parma",
    "sg:classifiers":[
        {
            "category":"Building & Trades",
            "subcategory":"Cleaning & Sanitation",
            "type":"Services"
        }
    ],
    "sg:phone":"+39 0521 208961",
    "sg:postcode":"43100",
    "sg:province":"Parma",
    "sg:tags":[
        "handling",
        "auxiliary",
        "storage",
        "surveillance",
        "maintenance",
        "services"
    ],
    "wof:name":"Terzo Millennio Soc.coop.rl.",
    "wof:placetype":"venue"
},
  "geometry": {"coordinates":[10.32296,44.7756],"type":"Point"}
}