{
  "type": "Feature",
  "properties": {
    "iso:country":"IT",
    "sg:address":"20049 Concorezzo",
    "sg:city":"Concorezzo",
    "sg:classifiers":[
        {
            "category":"Utilities",
            "subcategory":"Mobile Phone",
            "type":"Services"
        }
    ],
    "sg:phone":"+39 039 688 6096",
    "sg:postcode":"20049",
    "sg:province":"Milano",
    "sg:tags":[
        "equipment",
        "telecommunication",
        "systems",
        "telephony"
    ],
    "wof:name":"Ing. Caprio E C. Srl",
    "wof:placetype":"venue"
},
  "geometry": {"coordinates":[9.326287,45.587818],"type":"Point"}
}