{
  "type": "Feature",
  "properties": {
    "iso:country":"IT",
    "sg:address":"20011 Corbetta",
    "sg:city":"Corbetta",
    "sg:orig_category":"Prodotti E Manufatti In Materie Plastiche",
    "sg:phone":"+39 02 9748 6090",
    "sg:postcode":"20011",
    "sg:province":"Milano",
    "wof:name":"Leoplast Srl",
    "wof:placetype":"venue"
},
  "geometry": {"coordinates":[8.9339237213,45.4641494751],"type":"Point"}
}