{
  "type": "Feature",
  "properties": {
    "addr:full":"40057 Granarolo Emilia Bologna 40057",
    "addr:postcode":"40057;40057",
    "addr:street":"Emilia Bologna",
    "iso:country":"IT",
    "sg:address":"40057 Granarolo Emilia",
    "sg:orig_category":"Prodotti E Manufatti In Materie Plastiche",
    "sg:phone":"+39 051 767492",
    "sg:postcode":"40057",
    "sg:province":"Bologna",
    "wof:name":"Medici Franco",
    "wof:placetype":"venue"
},
  "geometry": {"coordinates":[11.4132928848,44.53673172],"type":"Point"}
}