{
  "type": "Feature",
  "properties": {
    "iso:country":"IT",
    "sg:address":"84091 Battipaglia",
    "sg:city":"Battipaglia",
    "sg:orig_category":"Elettrotecnica Industriale, Prodotti E Apparecchiature. Ricambi E Componenti Dei Mezzi Di Trasporto",
    "sg:phone":"+39 0828 673088",
    "sg:postcode":"84091",
    "sg:province":"Salerno",
    "wof:name":"Mototecnica Di Streppone Marco",
    "wof:placetype":"venue"
},
  "geometry": {"coordinates":[14.982961,40.612129],"type":"Point"}
}