{
  "type": "Feature",
  "properties": {
    "iso:country":"IT",
    "sg:address":"12, Via Risara 61025 Montelabbate",
    "sg:city":"Montelabbate",
    "sg:classifiers":[
        {
            "category":"Shopping",
            "subcategory":"Stationery & Office Supplies",
            "type":"Retail Goods"
        }
    ],
    "sg:phone":"+39 0721 491422",
    "sg:postcode":"61025",
    "sg:province":"Pesaro E Urbino",
    "sg:tags":[
        "professional"
    ],
    "wof:name":"Komar (s.r.l.)",
    "wof:placetype":"venue"
},
  "geometry": {"coordinates":[12.8051109314,43.8535919189],"type":"Point"}
}