{
  "type": "Feature",
  "properties": {
    "addr:full":"09131 Cagliari Cagliari Cagliari 09131",
    "addr:postcode":"09131;09131",
    "iso:country":"IT",
    "sg:address":"09131 Cagliari",
    "sg:city":"Cagliari",
    "sg:orig_category":"Ricambi E Componenti Dei Mezzi Di Trasporto",
    "sg:phone":"+39 070 42655",
    "sg:postcode":"09131",
    "sg:province":"Cagliari",
    "wof:name":"Ri.a.m. Snc",
    "wof:placetype":"venue"
},
  "geometry": {"coordinates":[9.120355,39.234188],"type":"Point"}
}