{
  "type": "Feature",
  "properties": {
    "iso:country":"IT",
    "sg:address":"6, Via Pellicciaio Marco 31100 Treviso",
    "sg:city":"Treviso",
    "sg:classifiers":[
        {
            "category":"Manufacturing",
            "subcategory":"Paper Products",
            "type":"Manufacturing & Wholesale Goods"
        }
    ],
    "sg:phone":"+39 0422 302884",
    "sg:postcode":"31100",
    "sg:province":"Treviso",
    "sg:tags":[
        "cardboard"
    ],
    "wof:name":"Ti - Vu Plast",
    "wof:placetype":"venue"
},
  "geometry": {"coordinates":[12.2027196884,45.6512107849],"type":"Point"}
}