{
  "type": "Feature",
  "properties": {
    "iso:country":"IT",
    "sg:address":"Piazza Ugo Dallo 28; Castiglione Delle Stiviere; 46043",
    "sg:city":"Castiglione delle Stiviere",
    "sg:classifiers":[
        {
            "category":"Banks & Credit Unions",
            "subcategory":"Bank",
            "type":"Services"
        }
    ],
    "sg:phone":"+39 0376 670282",
    "sg:postcode":"46043",
    "sg:province":"Mantova",
    "wof:name":"Banca Agricola Mantovana Scarl",
    "wof:placetype":"venue"
},
  "geometry": {"coordinates":[10.490196,45.392002],"type":"Point"}
}