{
  "type": "Feature",
  "properties": {
    "addr:full":"43, Via Rettifilo Al Bravo 80022 Arzano Arzano Napoli 80022",
    "addr:postcode":"80022;80022",
    "addr:street":"Via Rettifilo Al Bravo",
    "iso:country":"IT",
    "sg:address":"43, Via Rettifilo Al Bravo 80022 Arzano",
    "sg:city":"Arzano",
    "sg:classifiers":[
        {
            "category":"Manufacturing",
            "subcategory":"Paper Products",
            "type":"Manufacturing & Wholesale Goods"
        }
    ],
    "sg:phone":"+39 081 731 6582",
    "sg:postcode":"80022",
    "sg:province":"Napoli",
    "sg:tags":[
        "cardboard"
    ],
    "wof:name":"Imbalsud S.r.l",
    "wof:placetype":"venue"
},
  "geometry": {"coordinates":[14.2516355515,40.84009552],"type":"Point"}
}