{
  "type": "Feature",
  "properties": {
    "addr:full":"8/r., Via De Litta 17047 Quiliano Quiliano Savona 17047",
    "addr:housenumber":"8 / r.",
    "addr:postcode":"17047;17047",
    "addr:street":"Via De Litta",
    "iso:country":"IT",
    "sg:address":"8/r., Via De Litta 17047 Quiliano",
    "sg:city":"Quiliano",
    "sg:classifiers":[
        {
            "category":"Professional",
            "subcategory":"Engineering",
            "type":"Services"
        }
    ],
    "sg:phone":"+39 39019881997",
    "sg:postcode":"17047",
    "sg:province":"Savona",
    "sg:tags":[
        "machine",
        "-",
        "mechanical"
    ],
    "wof:name":"O.c.e.m. (s.r.l.)",
    "wof:placetype":"venue"
},
  "geometry": {"coordinates":[8.425557,44.283161],"type":"Point"}
}