{
  "type": "Feature",
  "properties": {
    "iso:country":"IT",
    "sg:address":"91011 Alcamo",
    "sg:city":"Alcamo",
    "sg:orig_category":"Servizi E Lavori Per Ecologia E Smaltimento Rifiuti. Servizi Ausiliari Di Analisi, Controllo E Ricerca",
    "sg:phone":"+39 0924 501723",
    "sg:postcode":"91011",
    "sg:province":"Trapani",
    "sg:website":"http://www.trinacria.it/ambientedangelo",
    "wof:name":"D'angelo Vincenzo",
    "wof:placetype":"venue"
},
  "geometry": {"coordinates":[12.966582,37.954071],"type":"Point"}
}