{
  "type": "Feature",
  "properties": {
    "addr:full":"24122 Bergamo Bergamo Bergamo 24122",
    "addr:postcode":"24122;24122",
    "iso:country":"IT",
    "sg:address":"24122 Bergamo",
    "sg:city":"Bergamo",
    "sg:classifiers":[
        {
            "category":"Health Services",
            "subcategory":"Health Practitioner",
            "type":"Services"
        }
    ],
    "sg:phone":"+39 035 237486",
    "sg:postcode":"24122",
    "sg:province":"Bergamo",
    "sg:tags":[
        "medici"
    ],
    "wof:name":"Limonta Massimiliano",
    "wof:placetype":"venue"
},
  "geometry": {"coordinates":[9.671323,45.690834],"type":"Point"}
}