{
  "type": "Feature",
  "properties": {
    "iso:country":"IT",
    "sg:address":"Via Vespucci 12 42020 Montecavolo",
    "sg:classifiers":[
        {
            "category":"Wholesale",
            "subcategory":"Machinery & Supplies",
            "type":"Manufacturing & Wholesale Goods"
        }
    ],
    "sg:phone":"+39 0522 886127",
    "sg:postcode":"42020",
    "sg:province":"Reggio Nell'Emilia",
    "sg:tags":[
        "agricultural",
        "gearbox"
    ],
    "wof:name":"Nuova Azzimondi & Friggeri S.r.l.",
    "wof:placetype":"venue"
},
  "geometry": {"coordinates":[10.536711,44.64061],"type":"Point"}
}