{
  "type": "Feature",
  "properties": {
    "iso:country":"IT",
    "sg:address":"81020 San Nicola La Strada",
    "sg:city":"San Nicola la Strada",
    "sg:orig_category":"Servizi E Lavori Per Arredamento E Industria Del Legno. Servizi E Lavori Per Edilizia E Lavori Pubblici",
    "sg:phone":"+39 0823 421436",
    "sg:postcode":"81020",
    "sg:province":"Caserta",
    "wof:name":"Arte Nuova Di Lino Coppola",
    "wof:placetype":"venue"
},
  "geometry": {"coordinates":[14.330552,41.052242],"type":"Point"}
}