{
  "type": "Feature",
  "properties": {
    "iso:country":"IT",
    "sg:address":"15033 Casale Monferrato",
    "sg:city":"Casale Monferrato",
    "sg:orig_category":"Carrozzerie Automobili",
    "sg:phone":"+39 0142 454530",
    "sg:postcode":"15033",
    "sg:province":"Alessandria",
    "wof:name":"Autocarrozzeria Moderna Srl",
    "wof:placetype":"venue"
},
  "geometry": {"coordinates":[8.470354,45.131035],"type":"Point"}
}