{
  "type": "Feature",
  "properties": {
    "iso:country":"IT",
    "sg:address":"35013 Cittadella",
    "sg:city":"Cittadella",
    "sg:orig_category":"Elettrotecnica Industriale, Prodotti E Apparecchiature. Elettrotecnica Professionale E Di Consumo",
    "sg:phone":"+39 049 597 0138",
    "sg:postcode":"35013",
    "sg:province":"Padova",
    "sg:website":"http://www.zurlo.it",
    "wof:name":"Zurlo Srl",
    "wof:placetype":"venue"
},
  "geometry": {"coordinates":[11.802525,45.661301],"type":"Point"}
}