{
  "type": "Feature",
  "properties": {
    "addr:full":"36027 Rosa' Vicenza 36027",
    "addr:postcode":"36027;36027",
    "addr:street":"Rosa ' Vicenza",
    "iso:country":"IT",
    "sg:address":"36027 Rosa'",
    "sg:orig_category":"Carta, Cartone E Prodotti Primari. Forniture E Materiali Per Imballaggio E Confezionamento",
    "sg:phone":"+39 0424 582056",
    "sg:postcode":"36027",
    "sg:province":"Vicenza",
    "wof:name":"Alveari Rosa' Di Adriano Frighetto & C. (s.n.c.)",
    "wof:placetype":"venue"
},
  "geometry": {"coordinates":[11.774817,45.717655],"type":"Point"}
}