{
  "type": "Feature",
  "properties": {
    "addr:full":"Via Zanon 34 33048 San Giovanni Al Natisone San Giovanni al Natisone Udine 33048",
    "addr:housenumber":"34",
    "addr:postcode":"33048;33048",
    "addr:street":"Via Zanon",
    "iso:country":"IT",
    "sg:address":"Via Zanon 34 33048 San Giovanni Al Natisone",
    "sg:city":"San Giovanni al Natisone",
    "sg:classifiers":[
        {
            "category":"Wholesale",
            "subcategory":"Home Furnishings",
            "type":"Manufacturing & Wholesale Goods"
        }
    ],
    "sg:phone":"+39 0432 746133",
    "sg:postcode":"33048",
    "sg:province":"Udine",
    "sg:tags":[
        "chair"
    ],
    "sg:website":"www.arborsedie.it",
    "wof:name":"Arbor Srl",
    "wof:placetype":"venue"
},
  "geometry": {"coordinates":[13.431346,45.981815],"type":"Point"}
}