{
  "type": "Feature",
  "properties": {
    "iso:country":"IT",
    "sg:address":"20146 Milano",
    "sg:city":"Milano",
    "sg:orig_category":"Autogru - Noleggio",
    "sg:phone":"+39 02 423 1914",
    "sg:postcode":"20146",
    "sg:province":"Milano",
    "wof:name":"Autotraslochi S. Ambrogio Snc",
    "wof:placetype":"venue"
},
  "geometry": {"coordinates":[9.151339,45.450485],"type":"Point"}
}