{
  "type": "Feature",
  "properties": {
    "addr:full":"10155 Torino Torino Torino 10155",
    "addr:postcode":"10155;10155",
    "iso:country":"IT",
    "sg:address":"10155 Torino",
    "sg:city":"Torino",
    "sg:classifiers":[
        {
            "category":"Shopping",
            "subcategory":"Bicycles & Sporting Goods",
            "type":"Retail Goods"
        }
    ],
    "sg:phone":"+39 011 246 7204",
    "sg:postcode":"10155",
    "sg:province":"Torino",
    "sg:tags":[
        "e",
        "sport",
        "-",
        "forniture",
        "articoli"
    ],
    "wof:name":"Mary Kart Di Valenzano Franco",
    "wof:placetype":"venue"
},
  "geometry": {"coordinates":[7.692299,45.099133],"type":"Point"}
}