{
  "type": "Feature",
  "properties": {
    "addr:full":"7, Via Osoppo 20148 Milano Milano Milano 20148",
    "addr:postcode":"20148;20148",
    "addr:street":"Via Osoppo",
    "iso:country":"IT",
    "sg:address":"7, Via Osoppo 20148 Milano",
    "sg:city":"Milano",
    "sg:classifiers":[
        {
            "category":"Professional",
            "subcategory":"Advertising",
            "type":"Services"
        }
    ],
    "sg:phone":"+39 390 248 7931",
    "sg:postcode":"20148",
    "sg:province":"Milano",
    "sg:tags":[
        "communication",
        "medium"
    ],
    "wof:name":"New Reversal Service Srl",
    "wof:placetype":"venue"
},
  "geometry": {"coordinates":[9.14397,45.469524],"type":"Point"}
}