{
  "type": "Feature",
  "properties": {
    "iso:country":"IT",
    "sg:address":"00148 Roma",
    "sg:city":"Roma",
    "sg:orig_category":"Servizi Al Turismo. Servizi Ausiliari Dei Mezzi Di Trasporto. Servizi Ausiliari Per Il Trasporto. Acqua, Luce, Gas E Societa' Di Esercizio Pubblico",
    "sg:phone":"+39 0665621",
    "sg:postcode":"00148",
    "sg:province":"Roma",
    "sg:website":"http://www.alitalia.it",
    "wof:name":"Alitalia Spa",
    "wof:placetype":"venue"
},
  "geometry": {"coordinates":[12.441811,41.77599],"type":"Point"}
}