{
  "type": "Feature",
  "properties": {
    "iso:country":"IT",
    "sg:address":"38030 Castello Molina Di Fiemme",
    "sg:city":"Castello Molina di Fiemme",
    "sg:orig_category":"Servizi E Lavori Per Agricoltura E Zootecnia. Animali Domestici",
    "sg:phone":"+39 0462 341912",
    "sg:postcode":"38030",
    "sg:province":"Trento",
    "wof:name":"Natura Viva",
    "wof:placetype":"venue"
},
  "geometry": {"coordinates":[11.424306,46.274418],"type":"Point"}
}