{
  "type": "Feature",
  "properties": {
    "iso:country":"IT",
    "sg:address":"20136 Milano",
    "sg:city":"Milano",
    "sg:orig_category":"Servizi Editoriali. Servizi Per Aziende, Manifestazioni E Supporto Agli Scambi Commerciali",
    "sg:phone":"+39 02 8942 1271",
    "sg:postcode":"20136",
    "sg:province":"Milano",
    "wof:name":"Flag 2010 S.n.c.",
    "wof:placetype":"venue"
},
  "geometry": {"coordinates":[9.177918,45.447376],"type":"Point"}
}