{
  "type": "Feature",
  "properties": {
    "iso:country":"IT",
    "sg:address":"37135 Verona",
    "sg:city":"Verona",
    "sg:orig_category":"Elettronica Professionale E Di Consumo. Musica",
    "sg:phone":"+39 045 583440",
    "sg:postcode":"37135",
    "sg:province":"Verona",
    "wof:name":"Audio Service Di Comparotto Stefano",
    "wof:placetype":"venue"
},
  "geometry": {"coordinates":[10.989361,45.418453],"type":"Point"}
}