{
  "type": "Feature",
  "properties": {
    "iso:country":"IT",
    "sg:address":"22, Via Piemonte 09032 Assemini",
    "sg:city":"Assemini",
    "sg:classifiers":[
        {
            "category":"Travel",
            "subcategory":"Travel Agent",
            "type":"Entertainment"
        }
    ],
    "sg:phone":"+39 39070947330",
    "sg:postcode":"09032",
    "sg:province":"Cagliari",
    "sg:tags":[
        "business"
    ],
    "wof:name":"Albergo Argentina",
    "wof:placetype":"venue"
},
  "geometry": {"coordinates":[9.012321,39.291962],"type":"Point"}
}