{
  "type": "Feature",
  "properties": {
    "iso:country":"IT",
    "sg:address":"30100 Venezia",
    "sg:orig_category":"Acciaierie E Fonderie",
    "sg:phone":"+39 041 718039",
    "sg:province":"VE",
    "wof:name":"Metallurgica Mainardi Snc Dei F.lli Adriano E Corrado Mainardi",
    "wof:placetype":"venue"
},
  "geometry": {"coordinates":[12.290899,45.373199],"type":"Point"}
}