{
  "type": "Feature",
  "properties": {
    "addr:full":"06126 Perugia Perugia Perugia 06126",
    "addr:postcode":"06126;06126",
    "iso:country":"IT",
    "sg:address":"06126 Perugia",
    "sg:city":"Perugia",
    "sg:orig_category":"Automobili E Mezzi Di Trasporto",
    "sg:phone":"+39 075 32054",
    "sg:postcode":"06126",
    "sg:province":"Perugia",
    "wof:name":"Autosalone Pasca",
    "wof:placetype":"venue"
},
  "geometry": {"coordinates":[12.398782,43.095661],"type":"Point"}
}