{
  "type": "Feature",
  "properties": {
    "iso:country":"IT",
    "sg:address":"20127 Milano",
    "sg:city":"Milano",
    "sg:orig_category":"Cinematografia E Radiotelevisione. Forniture Per Il Settore Dello Spettacolo",
    "sg:phone":"+39 02 669 1433",
    "sg:postcode":"20127",
    "sg:province":"Milano",
    "wof:name":"Seven 75 Srl",
    "wof:placetype":"venue"
},
  "geometry": {"coordinates":[9.209498,45.489021],"type":"Point"}
}