{
  "type": "Feature",
  "properties": {
    "addr:full":"35127 Padova Padova Padova 35127",
    "addr:postcode":"35127;35127",
    "iso:country":"IT",
    "sg:address":"35127 Padova",
    "sg:city":"Padova",
    "sg:orig_category":"Forniture Per Abbigliamento E Pelletterie. Forniture Per Attivita' Commerciali Ed Artigianali",
    "sg:phone":"+39 049 761885",
    "sg:postcode":"35127",
    "sg:province":"Padova",
    "sg:website":"http://www.remiro.it",
    "wof:name":"Remiro Srl",
    "wof:placetype":"venue"
},
  "geometry": {"coordinates":[11.923116684,45.3534317017],"type":"Point"}
}