{
  "type": "Feature",
  "properties": {
    "iso:country":"IT",
    "sg:address":"34074 Monfalcone",
    "sg:city":"Monfalcone",
    "sg:classifiers":[
        {
            "category":"Home & Garden",
            "subcategory":"Furniture",
            "type":"Retail Goods"
        }
    ],
    "sg:phone":"+39 0481 414146",
    "sg:postcode":"34074",
    "sg:province":"Gorizia",
    "sg:tags":[
        "furnishing"
    ],
    "wof:name":"West Srl",
    "wof:placetype":"venue"
},
  "geometry": {"coordinates":[13.5265035629,45.8013076782],"type":"Point"}
}