{
  "type": "Feature",
  "properties": {
    "addr:full":"28041 Arona Arona Novara 28041",
    "addr:postcode":"28041;28041",
    "iso:country":"IT",
    "sg:address":"28041 Arona",
    "sg:city":"Arona",
    "sg:orig_category":"Antifurto",
    "sg:phone":"+39 0322 241939",
    "sg:postcode":"28041",
    "sg:province":"Novara",
    "wof:name":"Elettro-impianti Sas Di Vailati C. & C.",
    "wof:placetype":"venue"
},
  "geometry": {"coordinates":[8.561141,45.761276],"type":"Point"}
}