{
  "type": "Feature",
  "properties": {
    "iso:country":"IT",
    "sg:address":"5, Localita' Canevina 62022 Castelraimondo",
    "sg:city":"Castelraimondo",
    "sg:classifiers":[
        {
            "category":"Shopping",
            "type":"Retail Goods"
        }
    ],
    "sg:phone":"+39 0737 641804",
    "sg:postcode":"62022",
    "sg:province":"Macerata",
    "sg:tags":[
        "finished",
        "-",
        "metallic"
    ],
    "wof:name":"Tecno Mach Profili N. & C. (s.n.c.)",
    "wof:placetype":"venue"
},
  "geometry": {"coordinates":[13.0435304642,43.2194480896],"type":"Point"}
}