{
  "type": "Feature",
  "properties": {
    "iso:country":"IT",
    "sg:address":"21013 Gallarate",
    "sg:city":"Gallarate",
    "sg:orig_category":"Abbigliamento Esterno, Maglierie E Pelliccerie. Shopping",
    "sg:phone":"+39 0331 780923",
    "sg:postcode":"21013",
    "sg:province":"Varese",
    "wof:name":"Texil Pel Srl",
    "wof:placetype":"venue"
},
  "geometry": {"coordinates":[8.799276,45.664864],"type":"Point"}
}