{
  "type": "Feature",
  "properties": {
    "addr:full":"Via F.lli Rosselli 27050 Casei Gerola Casei Pavia 27050",
    "addr:postcode":"27050;27050",
    "addr:street":"Via F.Lli Rosselli;Gerola Casei",
    "iso:country":"IT",
    "sg:address":"Via F.lli Rosselli 27050 Casei Gerola",
    "sg:city":"Casei",
    "sg:classifiers":[
        {
            "category":"Shopping",
            "subcategory":"Crafts & Fabrics",
            "type":"Retail Goods"
        }
    ],
    "sg:phone":"+39 39038361022",
    "sg:postcode":"27050",
    "sg:province":"Pavia",
    "wof:name":"Ricamificio Comat Aurelio Puliatti",
    "wof:placetype":"venue"
},
  "geometry": {"coordinates":[9.1565628052,45.1858863831],"type":"Point"}
}