{
  "type": "Feature",
  "properties": {
    "iso:country":"IT",
    "sg:address":"20036 Meda",
    "sg:city":"Meda",
    "sg:orig_category":"Legno E Semilavorati",
    "sg:phone":"+39 036 271647",
    "sg:postcode":"20036",
    "sg:province":"Milano",
    "wof:name":"Fratelli Ronchetti Di Giorgio E Antonio Ronchetti & C.(s.n.c.)",
    "wof:placetype":"venue"
},
  "geometry": {"coordinates":[9.161995,45.544941],"type":"Point"}
}