{
  "type": "Feature",
  "properties": {
    "iso:country":"IT",
    "sg:address":"Via S Camicia 1; Commessaggio; 46010",
    "sg:city":"Commessaggio",
    "sg:classifiers":[
        {
            "category":"Banks & Credit Unions",
            "subcategory":"Bank",
            "type":"Services"
        }
    ],
    "sg:phone":"+39 0376 98490",
    "sg:postcode":"46010",
    "sg:province":"Mantova",
    "wof:name":"Istituto Bancario, San Paolo Di Torino Spa",
    "wof:placetype":"venue"
},
  "geometry": {"coordinates":[10.545092,45.0345],"type":"Point"}
}