{
  "type": "Feature",
  "properties": {
    "iso:country":"IT",
    "sg:address":"22066 Mariano Comense",
    "sg:city":"Mariano Comense",
    "sg:orig_category":"Acciai Inossidabili - Lavorazione",
    "sg:phone":"+39 031 743325",
    "sg:postcode":"22066",
    "sg:province":"Como",
    "wof:name":"I.m.e. Srl",
    "wof:placetype":"venue"
},
  "geometry": {"coordinates":[9.184532,45.678928],"type":"Point"}
}