{
  "type": "Feature",
  "properties": {
    "iso:country":"IT",
    "sg:address":"50123 Firenze",
    "sg:city":"Firenze",
    "sg:classifiers":[
        {
            "category":"Travel",
            "subcategory":"Hotels & Motels",
            "type":"Entertainment"
        }
    ],
    "sg:phone":"+39 055 284848",
    "sg:postcode":"50123",
    "sg:province":"Firenze",
    "sg:tags":[
        "hotels",
        "facility"
    ],
    "sg:website":"http://www.hotelprincipe.com",
    "wof:name":"Hotel Principe",
    "wof:placetype":"venue"
},
  "geometry": {"coordinates":[11.249545,43.775291],"type":"Point"}
}