{
  "type": "Feature",
  "properties": {
    "iso:country":"IT",
    "sg:address":"Via Cordellina 77 36077 Altavilla Vicentina",
    "sg:city":"Altavilla Vicentina",
    "sg:classifiers":[
        {
            "category":"Manufacturing",
            "subcategory":"Rubber & Plastics",
            "type":"Manufacturing & Wholesale Goods"
        }
    ],
    "sg:phone":"+39 0444 573649",
    "sg:postcode":"36077",
    "sg:province":"Vicenza",
    "sg:tags":[
        "polyurethane"
    ],
    "wof:name":"Covi Srl",
    "wof:placetype":"venue"
},
  "geometry": {"coordinates":[11.4465141296,45.5133972168],"type":"Point"}
}