{
  "type": "Feature",
  "properties": {
    "addr:full":"Via Battisti Cesare 9 10123 Torino Torino Torino 10123",
    "addr:housenumber":"9",
    "addr:postcode":"10123;10123",
    "addr:street":"Via Battisti Cesare",
    "iso:country":"IT",
    "sg:address":"Via Battisti Cesare 9 10123 Torino",
    "sg:city":"Torino",
    "sg:orig_category":"Boys' Clothing",
    "sg:phone":"+39 011 551 6611",
    "sg:postcode":"10123",
    "sg:province":"Torino",
    "wof:name":"Coda Company S.r.l.",
    "wof:placetype":"venue"
},
  "geometry": {"coordinates":[7.573543,45.06319],"type":"Point"}
}