{
  "type": "Feature",
  "properties": {
    "iso:country":"IT",
    "sg:address":"74100 Taranto",
    "sg:city":"Taranto",
    "sg:orig_category":"Forniture Per Edilizia E Lavori Pubblici",
    "sg:phone":"+39 099 779 6476",
    "sg:postcode":"74100",
    "sg:province":"Taranto",
    "wof:name":"So.ge.co. Srl",
    "wof:placetype":"venue"
},
  "geometry": {"coordinates":[17.2680988312,40.4644927979],"type":"Point"}
}