{
  "type": "Feature",
  "properties": {
    "iso:country":"IT",
    "sg:address":"90, Via Mugnano Melito 80018 Mugnano Di Napoli",
    "sg:city":"Mugnano di Napoli",
    "sg:classifiers":[
        {
            "category":"Shopping",
            "subcategory":"Crafts & Fabrics",
            "type":"Retail Goods"
        }
    ],
    "sg:phone":"+39 081 571 3844",
    "sg:postcode":"80018",
    "sg:province":"Napoli",
    "sg:tags":[
        "linen"
    ],
    "wof:name":"Abc Design Di Alfonso",
    "wof:placetype":"venue"
},
  "geometry": {"coordinates":[14.2138376236,40.9117088318],"type":"Point"}
}