{
  "type": "Feature",
  "properties": {
    "iso:country":"IT",
    "sg:address":"00178 Roma",
    "sg:city":"Roma",
    "sg:orig_category":"Cinematografia E Radiotelevisione. Forniture Per Il Settore Dello Spettacolo",
    "sg:phone":"+39 06 784 2599",
    "sg:postcode":"00178",
    "sg:province":"Roma",
    "wof:name":"Cine 800 Srl",
    "wof:placetype":"venue"
},
  "geometry": {"coordinates":[12.547325,41.838459],"type":"Point"}
}