{
  "type": "Feature",
  "properties": {
    "iso:country":"IT",
    "sg:address":"20145 Milano",
    "sg:city":"Milano",
    "sg:classifiers":[
        {
            "category":"Professional",
            "subcategory":"Management & Consulting",
            "type":"Services"
        }
    ],
    "sg:phone":"+39 02 4800 9055",
    "sg:postcode":"20145",
    "sg:province":"Milano",
    "sg:tags":[
        "business",
        "technical",
        "consultant",
        "-",
        "worker",
        "consultancies",
        "administration",
        "appraisers",
        "administrative"
    ],
    "sg:website":"http://www.studiotruppa.com",
    "wof:name":"Studio Truppa - Scorpio Service Srl",
    "wof:placetype":"venue"
},
  "geometry": {"coordinates":[9.155786,45.470848],"type":"Point"}
}