{
  "type": "Feature",
  "properties": {
    "iso:country":"IT",
    "sg:address":"Via Divisione Tridentina 23 24020 Villa Di Serio",
    "sg:city":"Villa di Serio",
    "sg:classifiers":[
        {
            "category":"Structure",
            "subcategory":"Shopping Mall",
            "type":"Public Place"
        }
    ],
    "sg:phone":"+39 035 423 4411",
    "sg:postcode":"24020",
    "sg:province":"Bergamo",
    "sg:tags":[
        "shop",
        "shelf",
        "system",
        "equipment"
    ],
    "sg:website":"www.omcn.it",
    "wof:name":"Omcn Spa",
    "wof:placetype":"venue"
},
  "geometry": {"coordinates":[9.738119,45.725178],"type":"Point"}
}