{
  "type": "Feature",
  "properties": {
    "iso:country":"IT",
    "sg:address":"62020 Caldarola",
    "sg:city":"Caldarola",
    "sg:orig_category":"Acciai Speciali - Produzione",
    "sg:phone":"+39 0733 905923",
    "sg:postcode":"62020",
    "sg:province":"Macerata",
    "wof:name":"Fonderie Farabolini Spa",
    "wof:placetype":"venue"
},
  "geometry": {"coordinates":[13.335023,43.282524],"type":"Point"}
}