{
  "type": "Feature",
  "properties": {
    "iso:country":"IT",
    "sg:address":"50126 Firenze",
    "sg:city":"Firenze",
    "sg:orig_category":"Argenteria - Lavorazione E Ingrosso",
    "sg:phone":"+39 055 680 0181",
    "sg:postcode":"50126",
    "sg:province":"Firenze",
    "wof:name":"Zoppini Srl",
    "wof:placetype":"venue"
},
  "geometry": {"coordinates":[11.284564,43.760414],"type":"Point"}
}