{
  "type": "Feature",
  "properties": {
    "iso:country":"IT",
    "sg:address":"27051 Cava Manara",
    "sg:city":"Cava Manara",
    "sg:orig_category":"Forniture Per Edilizia E Lavori Pubblici. Forniture Industriali Per Prevenzione, Controllo E Sicurezza",
    "sg:phone":"+39 0382 552873",
    "sg:postcode":"27051",
    "sg:province":"Pavia",
    "wof:name":"Di.ru.svo Snc",
    "wof:placetype":"venue"
},
  "geometry": {"coordinates":[9.1271533966,45.1271896362],"type":"Point"}
}