{
  "type": "Feature",
  "properties": {
    "iso:country":"IT",
    "sg:address":"33/a, Via Amisano 15046 San Salvatore Monferrato",
    "sg:city":"San Salvatore Monferrato",
    "sg:classifiers":[
        {
            "category":"Shopping",
            "subcategory":"Jewelry",
            "type":"Retail Goods"
        }
    ],
    "sg:phone":"+39 0131 238220",
    "sg:postcode":"15046",
    "sg:province":"Alessandria",
    "sg:tags":[
        "jewellery"
    ],
    "wof:name":"Borgonuovo (s.r.l.)",
    "wof:placetype":"venue"
},
  "geometry": {"coordinates":[8.568907,44.991425],"type":"Point"}
}