{
  "type": "Feature",
  "properties": {
    "iso:country":"IT",
    "sg:address":"25125 Brescia",
    "sg:city":"Brescia",
    "sg:orig_category":"Macchine Utensili E Impianti",
    "sg:phone":"+39 030 358 2081",
    "sg:postcode":"25125",
    "sg:province":"Brescia",
    "wof:name":"A.g.b. Di Lorenzo Filippini & C. (s.n.c.)",
    "wof:placetype":"venue"
},
  "geometry": {"coordinates":[10.155433,45.516556],"type":"Point"}
}