{
  "type": "Feature",
  "properties": {
    "iso:country":"IT",
    "sg:address":"Via Giorgione 32 51039 Quarrata",
    "sg:city":"Quarrata",
    "sg:orig_category":"Permanent-field Three-phase Motors",
    "sg:phone":"+39 0573 775300",
    "sg:postcode":"51039",
    "sg:province":"Pistoia",
    "wof:name":"Bame Srl",
    "wof:placetype":"venue"
},
  "geometry": {"coordinates":[10.98802948,43.8587226868],"type":"Point"}
}