{
  "type": "Feature",
  "properties": {
    "iso:country":"IT",
    "sg:address":"10071 Borgaro Torinese",
    "sg:city":"Borgaro Torinese",
    "sg:classifiers":[
        {
            "category":"Professional",
            "subcategory":"Printing & Photocopies",
            "type":"Services"
        }
    ],
    "sg:phone":"+39 011 407 8511",
    "sg:postcode":"10071",
    "sg:province":"Torino",
    "sg:tags":[
        "packaging",
        "setting"
    ],
    "sg:website":"http://www.canale.it",
    "wof:name":"Canale G. & C. Spa",
    "wof:placetype":"venue"
},
  "geometry": {"coordinates":[7.658686,45.139042],"type":"Point"}
}