{
  "type": "Feature",
  "properties": {
    "addr:full":"30/a, Viale San Marco 33057 Palmanova Palmanova Udine 33057",
    "addr:housenumber":"30 / a",
    "addr:postcode":"33057;33057",
    "addr:street":"Viale San Marco",
    "iso:country":"IT",
    "sg:address":"30/a, Viale San Marco 33057 Palmanova",
    "sg:city":"Palmanova",
    "sg:classifiers":[
        {
            "category":"Professional",
            "subcategory":"Engineering",
            "type":"Services"
        }
    ],
    "sg:phone":"+39 0432 920766",
    "sg:postcode":"33057",
    "sg:province":"Udine",
    "sg:tags":[
        "machine",
        "-",
        "mechanical"
    ],
    "wof:name":"Casa Del Trattore - Cav.uff.g.marzinotto S.r.l.",
    "wof:placetype":"venue"
},
  "geometry": {"coordinates":[13.334866,45.930607],"type":"Point"}
}