{
  "type": "Feature",
  "properties": {
    "addr:full":"Via Marco Cumano 7 22100 Como Como Como 22100",
    "addr:housenumber":"7",
    "addr:postcode":"22100;22100",
    "addr:street":"Via Marco Cumano",
    "iso:country":"IT",
    "sg:address":"Via Marco Cumano 7 22100 Como",
    "sg:city":"Como",
    "sg:orig_category":"Ladies' Trousers Suits, Suits, Jackets, Skirts, And Trousers",
    "sg:phone":"+39 031 592124",
    "sg:postcode":"22100",
    "sg:province":"Como",
    "sg:website":"www.luansare.com",
    "wof:name":"Luan Sare' Confezioni Altamoda Srl",
    "wof:placetype":"venue"
},
  "geometry": {"coordinates":[9.089264,45.787285],"type":"Point"}
}