{
  "type": "Feature",
  "properties": {
    "iso:country":"IT",
    "sg:address":"Via Della Fametta 22074 Lomazzo",
    "sg:city":"Lomazzo",
    "sg:classifiers":[
        {
            "category":"Wholesale",
            "subcategory":"Machinery & Supplies",
            "type":"Manufacturing & Wholesale Goods"
        }
    ],
    "sg:phone":"+39 02 9677 9281",
    "sg:postcode":"22074",
    "sg:province":"Como",
    "sg:tags":[
        "equipment",
        "precision"
    ],
    "wof:name":"Meclopress (s.r.l.)",
    "wof:placetype":"venue"
},
  "geometry": {"coordinates":[9.029086113,45.7097549438],"type":"Point"}
}