{
  "type": "Feature",
  "properties": {
    "iso:country":"IT",
    "sg:address":"20145 Milano",
    "sg:city":"Milano",
    "sg:classifiers":[
        {
            "category":"Banks & Credit Unions",
            "subcategory":"Investment Brokerage",
            "type":"Services"
        }
    ],
    "sg:phone":"+39 02 463044",
    "sg:postcode":"20145",
    "sg:province":"Milano",
    "sg:tags":[
        "parrucchieri",
        "per",
        "donna"
    ],
    "wof:name":"Bajo Claudio Walter",
    "wof:placetype":"venue"
},
  "geometry": {"coordinates":[9.1573457718,45.4682502747],"type":"Point"}
}