{
  "type": "Feature",
  "properties": {
    "iso:country":"IT",
    "sg:address":"Via Dell' Edilizia 1 29010 Pontenure",
    "sg:city":"Pontenure",
    "sg:classifiers":[
        {
            "category":"Military Area",
            "subcategory":"Air Force Base",
            "type":"Public Place"
        }
    ],
    "sg:phone":"+39 0523 5181",
    "sg:postcode":"29010",
    "sg:province":"Piacenza",
    "sg:tags":[
        "precast",
        "component",
        "concrete"
    ],
    "sg:website":"www.rdb.it",
    "wof:name":"R.d.b. Spa",
    "wof:placetype":"venue"
},
  "geometry": {"coordinates":[9.6951417923,45.0537719727],"type":"Point"}
}