{
  "type": "Feature",
  "properties": {
    "iso:country":"IT",
    "sg:address":"40033 Casalecchio Di Reno",
    "sg:city":"Casalecchio di Reno",
    "sg:orig_category":"Motori Ed Organi Di Trasmissione",
    "sg:phone":"+39 051 758399",
    "sg:postcode":"40033",
    "sg:province":"Bologna",
    "wof:name":"Parazza E Maselli Snc",
    "wof:placetype":"venue"
},
  "geometry": {"coordinates":[11.2669811249,44.4658432007],"type":"Point"}
}