{
  "type": "Feature",
  "properties": {
    "iso:country":"IT",
    "sg:address":"19125 La Spezia",
    "sg:orig_category":"Macchine E Forniture Per Ecologia E Smaltimento Rifiuti. Climatizzazione E Condizionamento, Apparecchiature E Servizi",
    "sg:phone":"+39 0187 525350",
    "sg:province":"SP",
    "sg:website":"http://www.aersana.it",
    "wof:name":"Aersana Di Gigli Enzo",
    "wof:placetype":"venue"
},
  "geometry": {"coordinates":[9.841447,44.127155],"type":"Point"}
}