{
  "type": "Feature",
  "properties": {
    "iso:country":"IT",
    "sg:address":"61100 Pesaro",
    "sg:city":"Pesaro",
    "sg:orig_category":"Assicurazioni",
    "sg:phone":"+39 0721 404942",
    "sg:postcode":"61100",
    "sg:province":"Pesaro E Urbino",
    "sg:website":"http://www.assiservices.it",
    "wof:name":"Assi. Service Snc",
    "wof:placetype":"venue"
},
  "geometry": {"coordinates":[12.863028,43.90501],"type":"Point"}
}