{
  "type": "Feature",
  "properties": {
    "iso:country":"IT",
    "sg:address":"07020 Bassacutena",
    "sg:city":"Bassacutena",
    "sg:orig_category":"Macchine Ed Impianti Per Edilizia E Lavori Pubblici",
    "sg:phone":"+39 079 659720",
    "sg:postcode":"07020",
    "sg:province":"Olbia-Tempio",
    "wof:name":"Putzu Franco",
    "wof:placetype":"venue"
},
  "geometry": {"coordinates":[9.278559,40.826839],"type":"Point"}
}