{
  "type": "Feature",
  "properties": {
    "iso:country":"IT",
    "sg:address":"30030 Vigonovo",
    "sg:city":"Vigonovo",
    "sg:orig_category":"Forniture Per Edilizia E Lavori Pubblici",
    "sg:phone":"+39 049 980 2719",
    "sg:postcode":"30030",
    "sg:province":"Venezia",
    "wof:name":"Eurotre Finiture Sas",
    "wof:placetype":"venue"
},
  "geometry": {"coordinates":[11.991765976,45.394493103],"type":"Point"}
}