{
  "type": "Feature",
  "properties": {
    "iso:country":"IT",
    "sg:address":"Vico I E. Grella 83055 Sturno",
    "sg:city":"Sturno",
    "sg:classifiers":[
        {
            "category":"Manufacturing",
            "subcategory":"Food",
            "type":"Manufacturing & Wholesale Goods"
        }
    ],
    "sg:phone":"+39 0825 448628",
    "sg:postcode":"83055",
    "sg:province":"Avellino",
    "sg:tags":[
        "equipment",
        "processing",
        "-",
        "machinery"
    ],
    "wof:name":"Mecnosud S.r.l.dei F.lli Ingrisano",
    "wof:placetype":"venue"
},
  "geometry": {"coordinates":[14.792722702,40.9147491455],"type":"Point"}
}