{
  "type": "Feature",
  "properties": {
    "iso:country":"IT",
    "sg:address":"70023 Gioia Del Colle",
    "sg:city":"Gioia del Colle",
    "sg:orig_category":"Prodotti E Manufatti In Materie Plastiche",
    "sg:phone":"+39 080 348 4247",
    "sg:postcode":"70023",
    "sg:province":"Bari",
    "wof:name":"Natex (s.r.l.)",
    "wof:placetype":"venue"
},
  "geometry": {"coordinates":[16.8886432648,40.7659034729],"type":"Point"}
}