{
  "type": "Feature",
  "properties": {
    "addr:full":"20040 Bellusco Bellusco Milano 20040",
    "addr:postcode":"20040;20040",
    "iso:country":"IT",
    "sg:address":"20040 Bellusco",
    "sg:city":"Bellusco",
    "sg:orig_category":"Materiali Edili",
    "sg:postcode":"20040",
    "sg:province":"Milano",
    "wof:name":"Isolkalore (s.a.s)",
    "wof:placetype":"venue"
},
  "geometry": {"coordinates":[9.423265,45.616161],"type":"Point"}
}