{
  "type": "Feature",
  "properties": {
    "iso:country":"IT",
    "sg:address":"206, Corso Europa 20017 Rho",
    "sg:city":"Rho",
    "sg:classifiers":[
        {
            "category":"Food & Beverages",
            "subcategory":"Groceries & Convenience Stores",
            "type":"Retail Goods"
        }
    ],
    "sg:phone":"+39 02 9350 3133",
    "sg:postcode":"20017",
    "sg:province":"Milano",
    "sg:tags":[
        "product",
        "related"
    ],
    "wof:name":"Giuseppe Citterio Salumificio S.p.a.",
    "wof:placetype":"venue"
},
  "geometry": {"coordinates":[9.0526199341,45.5257377625],"type":"Point"}
}