{
  "type": "Feature",
  "properties": {
    "iso:country":"IT",
    "sg:address":"80134 Napoli",
    "sg:city":"Napoli",
    "sg:orig_category":"Forniture Per Attivita' Commerciali Ed Artigianali",
    "sg:phone":"+39 081 258 0262",
    "sg:postcode":"80134",
    "sg:province":"Napoli",
    "wof:name":"Sinad Srl",
    "wof:placetype":"venue"
},
  "geometry": {"coordinates":[14.3236093521,40.8649787903],"type":"Point"}
}