{
  "type": "Feature",
  "properties": {
    "iso:country":"IT",
    "sg:address":"41013 Castelfranco Emilia",
    "sg:city":"Castelfranco Emilia",
    "sg:orig_category":"Ceramiche: Prodotti E Lavorazioni. Forniture Per Attivita' Industriali",
    "sg:phone":"+39 059 931961",
    "sg:postcode":"41013",
    "sg:province":"Modena",
    "wof:name":"Kyrex Srl",
    "wof:placetype":"venue"
},
  "geometry": {"coordinates":[10.978554,44.636501],"type":"Point"}
}