{
  "type": "Feature",
  "properties": {
    "iso:country":"IT",
    "sg:address":"38100 Trento",
    "sg:city":"Trento",
    "sg:orig_category":"Marmo, Pietre Ed Affini",
    "sg:phone":"+39 0461 232317",
    "sg:postcode":"38100",
    "sg:province":"Trento",
    "wof:name":"Marmi Pila Srl",
    "wof:placetype":"venue"
},
  "geometry": {"coordinates":[11.122368,46.065357],"type":"Point"}
}