{
  "type": "Feature",
  "properties": {
    "iso:country":"IT",
    "sg:address":"916, Via Bologna 44100 Ferrara",
    "sg:city":"Ferrara",
    "sg:classifiers":[
        {
            "category":"Manufacturing",
            "subcategory":"Rubber & Plastics",
            "type":"Manufacturing & Wholesale Goods"
        }
    ],
    "sg:phone":"+39 0532 713606",
    "sg:postcode":"44100",
    "sg:province":"Ferrara",
    "wof:name":"Europa 2000 (s.p.a.)",
    "wof:placetype":"venue"
},
  "geometry": {"coordinates":[11.611513,44.82793],"type":"Point"}
}