{
  "type": "Feature",
  "properties": {
    "iso:country":"IT",
    "sg:address":"22030 Caslino D'erba",
    "sg:orig_category":"Servizi E Lavori Per Ecologia E Smaltimento Rifiuti. Acqua, Luce, Gas E Societa' Di Esercizio Pubblico",
    "sg:phone":"+39 031 621071",
    "sg:postcode":"22030",
    "sg:province":"Como",
    "wof:name":"Masciadri Luigi",
    "wof:placetype":"venue"
},
  "geometry": {"coordinates":[9.249043,45.843822],"type":"Point"}
}