{
  "type": "Feature",
  "properties": {
    "addr:full":"26032 Ostiano Ostiano Cremona 26032",
    "addr:housenumber":"26032",
    "addr:postcode":"26032",
    "addr:street":"Ostiano",
    "iso:country":"IT",
    "sg:address":"26032 Ostiano",
    "sg:city":"Ostiano",
    "sg:orig_category":"Prodotti E Manufatti In Materie Plastiche",
    "sg:phone":"+39 0372 840374",
    "sg:postcode":"26032",
    "sg:province":"Cremona",
    "wof:name":"Ra.ma. S.r.l.",
    "wof:placetype":"venue"
},
  "geometry": {"coordinates":[9.9945030212,45.1527175903],"type":"Point"}
}