{
  "type": "Feature",
  "properties": {
    "iso:country":"IT",
    "sg:address":"20122 Milano",
    "sg:city":"Milano",
    "sg:orig_category":"Agenzie Ed Enti Turistici. Acqua, Luce, Gas E Societa' Di Esercizio Pubblico",
    "sg:phone":"+39 02 7200 1001",
    "sg:postcode":"20122",
    "sg:province":"Milano",
    "wof:name":"Europ Assistance Trade S.p.a.",
    "wof:placetype":"venue"
},
  "geometry": {"coordinates":[9.189188,45.460934],"type":"Point"}
}