{
  "type": "Feature",
  "properties": {
    "addr:full":"07026 Olbia Olbia Olbia-Tempio 07026",
    "addr:postcode":"07026;07026",
    "iso:country":"IT",
    "sg:address":"07026 Olbia",
    "sg:city":"Olbia",
    "sg:orig_category":"Automobili E Mezzi Di Trasporto",
    "sg:phone":"+39 0789 51000",
    "sg:postcode":"07026",
    "sg:province":"Olbia-Tempio",
    "wof:name":"Olbia Fuoristrada Srl",
    "wof:placetype":"venue"
},
  "geometry": {"coordinates":[9.382113,41.179443],"type":"Point"}
}