{
  "type": "Feature",
  "properties": {
    "addr:full":"36051 Creazzo Creazzo Vicenza 36051",
    "addr:postcode":"36051;36051",
    "iso:country":"IT",
    "sg:address":"36051 Creazzo",
    "sg:city":"Creazzo",
    "sg:classifiers":[
        {
            "category":"Communications",
            "subcategory":"Newspaper",
            "type":"Services"
        }
    ],
    "sg:phone":"+39 0444 520440",
    "sg:postcode":"36051",
    "sg:province":"Vicenza",
    "sg:tags":[
        "publishing"
    ],
    "wof:name":"Costruzioni Meccaniche Pizzolato Massimiliano Srl",
    "wof:placetype":"venue"
},
  "geometry": {"coordinates":[11.4959049225,45.5289573669],"type":"Point"}
}