{
  "type": "Feature",
  "properties": {
    "iso:country":"IT",
    "sg:address":"25124 Brescia",
    "sg:city":"Brescia",
    "sg:orig_category":"Banche E Servizi Finanziari. Acqua, Luce, Gas E Societa' Di Esercizio Pubblico. Pubblica Amministrazione",
    "sg:phone":"+39 030 245 1006",
    "sg:postcode":"25124",
    "sg:province":"Brescia",
    "wof:name":"Sezione Staccata Di Milano D.dir.reg.d.ent.p.la Lombardia",
    "wof:placetype":"venue"
},
  "geometry": {"coordinates":[10.216022,45.525124],"type":"Point"}
}