{
  "type": "Feature",
  "properties": {
    "iso:country":"IT",
    "sg:address":"41100 Modena",
    "sg:city":"Modena",
    "sg:orig_category":"Apparecchiature E Sistemi Per Magazzinaggio E Movimentazione",
    "sg:phone":"+39 059 469112",
    "sg:postcode":"41100",
    "sg:province":"Modena",
    "sg:website":"http://www.officinamasetti.it",
    "wof:name":"Officina Masetti Snc",
    "wof:placetype":"venue"
},
  "geometry": {"coordinates":[10.973394,44.604187],"type":"Point"}
}