{
  "type": "Feature",
  "properties": {
    "iso:country":"IT",
    "sg:address":"56127 Pisa",
    "sg:city":"Pisa",
    "sg:orig_category":"Edilizia Materiali - Produzione E Ingrosso",
    "sg:phone":"+39 050 554100",
    "sg:postcode":"56127",
    "sg:province":"Pisa",
    "sg:website":"http://www.cogemar.it",
    "wof:name":"Co.ge.mar. Srl",
    "wof:placetype":"venue"
},
  "geometry": {"coordinates":[10.411055,43.722977],"type":"Point"}
}