{
  "type": "Feature",
  "properties": {
    "iso:country":"IT",
    "sg:address":"Via 4 Novembre 21 46024 Moglia",
    "sg:city":"Moglia",
    "sg:classifiers":[
        {
            "category":"Building & Trades",
            "subcategory":"Construction",
            "type":"Services"
        }
    ],
    "sg:phone":"+39 0522 556525",
    "sg:postcode":"46024",
    "sg:province":"Mantova",
    "sg:tags":[
        "equipment",
        "industry",
        "installation",
        "concrete"
    ],
    "sg:website":"www.blendsrl.com",
    "wof:name":"Blend S.r.l.",
    "wof:placetype":"venue"
},
  "geometry": {"coordinates":[10.933055,44.950161],"type":"Point"}
}