{
  "type": "Feature",
  "properties": {
    "addr:full":"Via Monte, 1/3 52015 Pratovecchio Pratovecchio Arezzo 52015",
    "addr:housenumber":"1 / 3",
    "addr:postcode":"52015;52015",
    "addr:street":"Via Monte",
    "iso:country":"IT",
    "sg:address":"Via Monte, 1/3 52015 Pratovecchio",
    "sg:city":"Pratovecchio",
    "sg:orig_category":"Nightwear, Pyjamas, Nightgowns",
    "sg:phone":"+39 0575 582565",
    "sg:postcode":"52015",
    "sg:province":"Arezzo",
    "sg:website":"www.ladyman.com",
    "wof:name":"Lady Man Srl",
    "wof:placetype":"venue"
},
  "geometry": {"coordinates":[11.722856,43.788082],"type":"Point"}
}