{
  "type": "Feature",
  "properties": {
    "iso:country":"IT",
    "sg:address":"29100 Piacenza",
    "sg:city":"Piacenza",
    "sg:orig_category":"Musica",
    "sg:phone":"+39 0523 616234",
    "sg:postcode":"29100",
    "sg:province":"Piacenza",
    "wof:name":"Chiusa Ugo",
    "wof:placetype":"venue"
},
  "geometry": {"coordinates":[9.7235441208,45.0441970825],"type":"Point"}
}