{
  "type": "Feature",
  "properties": {
    "iso:country":"IT",
    "sg:address":"40013 Castel Maggiore",
    "sg:city":"Castel Maggiore",
    "sg:orig_category":"Carta E Cartone - Produzione E Commercio",
    "sg:phone":"+39 051 701279",
    "sg:postcode":"40013",
    "sg:province":"Bologna",
    "sg:website":"http://www.allcart.it",
    "wof:name":"Allcart Srl",
    "wof:placetype":"venue"
},
  "geometry": {"coordinates":[11.376293,44.55938],"type":"Point"}
}