{
  "type": "Feature",
  "properties": {
    "iso:country":"IT",
    "sg:address":"20122 Milano",
    "sg:city":"Milano",
    "sg:orig_category":"Non-classified Establishments",
    "sg:phone":"+39 02 7600 3131",
    "sg:postcode":"20122",
    "sg:province":"Milano",
    "wof:name":"Richard-ginori 1735 Spa",
    "wof:placetype":"venue"
},
  "geometry": {"coordinates":[9.19753,45.466831],"type":"Point"}
}