{
  "type": "Feature",
  "properties": {
    "iso:country":"IT",
    "sg:address":"38020 Passo Del Tonale",
    "sg:orig_category":"Funivie, Sciovie E Impianti Di Risalita - Societa' Di Esercizio",
    "sg:phone":"+39 036 490 3767",
    "sg:postcode":"38020",
    "sg:province":"Trento",
    "wof:name":"Carosello Tonale Spa",
    "wof:placetype":"venue"
},
  "geometry": {"coordinates":[10.587305069,46.2611541748],"type":"Point"}
}