{
  "type": "Feature",
  "properties": {
    "iso:country":"IT",
    "sg:address":"Piazza Umberto 1; Specchia; 73040",
    "sg:city":"Specchia",
    "sg:classifiers":[
        {
            "category":"Banks & Credit Unions",
            "subcategory":"Bank",
            "type":"Services"
        }
    ],
    "sg:phone":"+39 0833 11049",
    "sg:postcode":"73040",
    "sg:province":"Lecce",
    "wof:name":"Consorzio Di Banca Private Del Sud",
    "wof:placetype":"venue"
},
  "geometry": {"coordinates":[18.29896,39.942398],"type":"Point"}
}