{
  "type": "Feature",
  "properties": {
    "addr:full":"6, V. Palazzetto - Mappano 10071 Borgaro Torinese Borgaro Torinese Torino 10071",
    "addr:housenumber":"6",
    "addr:postcode":"10071;10071",
    "addr:street":"V. Palazzetto",
    "iso:country":"IT",
    "sg:address":"6, V. Palazzetto - Mappano 10071 Borgaro Torinese",
    "sg:city":"Borgaro Torinese",
    "sg:classifiers":[
        {
            "category":"Wholesale",
            "subcategory":"Medical Equipment & Supplies",
            "type":"Manufacturing & Wholesale Goods"
        }
    ],
    "sg:phone":"+39 011 262 5140",
    "sg:postcode":"10071",
    "sg:province":"Torino",
    "sg:tags":[
        "-",
        "health",
        "instrument"
    ],
    "sg:website":"http://www.paginegialle.it/nuoblandin",
    "wof:name":"Nuova Blandino Spa",
    "wof:placetype":"venue"
},
  "geometry": {"coordinates":[7.704254,45.141644],"type":"Point"}
}