{
  "type": "Feature",
  "properties": {
    "addr:full":"47100 Forli' Forl\u00ec-Cesena 47100",
    "addr:postcode":"47100;47100",
    "addr:street":"Forli ' Forli\u0300-Cesena",
    "iso:country":"IT",
    "sg:address":"47100 Forli'",
    "sg:orig_category":"Prodotti E Manufatti In Materie Plastiche",
    "sg:phone":"+39 0543 83513",
    "sg:postcode":"47100",
    "sg:province":"Forl\u00ec-Cesena",
    "wof:name":"Galeotti & Cavallucci Snc",
    "wof:placetype":"venue"
},
  "geometry": {"coordinates":[11.9804611206,43.9947662354],"type":"Point"}
}