{
  "type": "Feature",
  "properties": {
    "iso:country":"IT",
    "sg:address":"Via S. Leonardo 97a 43100 Parma",
    "sg:city":"Parma",
    "sg:classifiers":[
        {
            "category":"Manufacturing",
            "subcategory":"Glass & Minerals",
            "type":"Manufacturing & Wholesale Goods"
        }
    ],
    "sg:phone":"+39 0521 784441",
    "sg:postcode":"43100",
    "sg:province":"Parma",
    "sg:tags":[
        "crystal"
    ],
    "sg:website":"www.scherzer1880.com",
    "wof:name":"Scherzer Srl",
    "wof:placetype":"venue"
},
  "geometry": {"coordinates":[10.331039,44.814163],"type":"Point"}
}