{
  "type": "Feature",
  "properties": {
    "iso:country":"IT",
    "sg:address":"Via Panoramica 55; Ercolano",
    "sg:classifiers":[
        {
            "category":"Banks & Credit Unions",
            "subcategory":"Bank",
            "type":"Services"
        }
    ],
    "sg:phone":"+39 081 739 0695",
    "wof:name":"Banca Di Roma",
    "wof:placetype":"venue"
},
  "geometry": {"coordinates":[14.356447,40.807808],"type":"Point"}
}