{
  "type": "Feature",
  "properties": {
    "addr:full":"63033 Monte Prandone Ascoli Piceno 63033",
    "addr:housenumber":"63033",
    "addr:postcode":"63033",
    "addr:street":"Monte Prandone",
    "iso:country":"IT",
    "sg:address":"63033 Monte Prandone",
    "sg:orig_category":"Prodotti Chimici Secondari. Prodotti Cosmetici E Da Toeletta",
    "sg:phone":"+39 0735 702607",
    "sg:postcode":"63033",
    "sg:province":"Ascoli Piceno",
    "wof:name":"Ceramiche Neve Sas Di Capriotti Anna & C.",
    "wof:placetype":"venue"
},
  "geometry": {"coordinates":[13.5749769211,42.8554000854],"type":"Point"}
}