{
  "type": "Feature",
  "properties": {
    "addr:full":"25050 Paderno Franciacorta Paderno Franciacorta Brescia 25050",
    "addr:postcode":"25050;franciacorta;25050",
    "addr:street":"Brescia",
    "iso:country":"IT",
    "sg:address":"25050 Paderno Franciacorta",
    "sg:city":"Paderno Franciacorta",
    "sg:orig_category":"Filati E Materie Prime Tessili",
    "sg:phone":"+39 030 685 7565",
    "sg:postcode":"25050",
    "sg:province":"Brescia",
    "sg:website":"http://www.cittadini.it",
    "wof:name":"Cittadini Spa",
    "wof:placetype":"venue"
},
  "geometry": {"coordinates":[10.0891828537,45.5773429871],"type":"Point"}
}