{
  "type": "Feature",
  "properties": {
    "iso:country":"IT",
    "sg:address":"14, Via Rossa Guido 20066 Melzo",
    "sg:city":"Melzo",
    "sg:classifiers":[
        {
            "category":"Manufacturing",
            "subcategory":"Rubber & Plastics",
            "type":"Manufacturing & Wholesale Goods"
        }
    ],
    "sg:phone":"+39 02 9573 6856",
    "sg:postcode":"20066",
    "sg:province":"Milano",
    "sg:tags":[
        "packaging",
        "material",
        "-"
    ],
    "wof:name":"Sipi S.r.l.",
    "wof:placetype":"venue"
},
  "geometry": {"coordinates":[9.1881408691,45.4636878967],"type":"Point"}
}