{
  "type": "Feature",
  "properties": {
    "iso:country":"IT",
    "sg:address":"10042 Nichelino",
    "sg:city":"Nichelino",
    "sg:orig_category":"Modellismo",
    "sg:phone":"+39 011 605 6688",
    "sg:postcode":"10042",
    "sg:province":"Torino",
    "wof:name":"Md Model",
    "wof:placetype":"venue"
},
  "geometry": {"coordinates":[7.6622085571,45.0042114258],"type":"Point"}
}