{
  "type": "Feature",
  "properties": {
    "addr:full":"21, Piazza Sallustio 00187 Roma Roma Roma 00187",
    "addr:postcode":"00187;00187",
    "addr:street":"Piazza Sallustio",
    "iso:country":"IT",
    "sg:address":"21, Piazza Sallustio 00187 Roma",
    "sg:city":"Roma",
    "sg:classifiers":[
        {
            "category":"Professional",
            "subcategory":"Business Services",
            "type":"Services"
        }
    ],
    "sg:phone":"+39 390 647 041",
    "sg:postcode":"00187",
    "sg:province":"Roma",
    "sg:tags":[
        "advice"
    ],
    "wof:name":"Unione Italiana Delle Camere Di Commercio Industria Artigianato E Agricoltura",
    "wof:placetype":"venue"
},
  "geometry": {"coordinates":[12.49716,41.908463],"type":"Point"}
}