{
  "type": "Feature",
  "properties": {
    "iso:country":"IT",
    "sg:address":"04012 Cisterna Di Latina",
    "sg:city":"Cisterna di Latina",
    "sg:orig_category":"Impiantistica E Prodotti Tecnologici Per Edilizia. Servizi Ausiliari Di Sorveglianza, Manutenzione E Pulizia",
    "sg:phone":"+39 06 969 4366",
    "sg:postcode":"04012",
    "sg:province":"Latina",
    "wof:name":"C.m.i. Piccola Soc. Coop. Arl",
    "wof:placetype":"venue"
},
  "geometry": {"coordinates":[12.832111,41.581852],"type":"Point"}
}