{
  "type": "Feature",
  "properties": {
    "addr:full":"00122 Lido Di Ostia Roma 00122",
    "addr:postcode":"00122;00122",
    "addr:street":"Di Ostia Roma",
    "iso:country":"IT",
    "sg:address":"00122 Lido Di Ostia",
    "sg:orig_category":"Materiali E Componenti Elettronici",
    "sg:phone":"+39 06 568 5701",
    "sg:postcode":"00122",
    "sg:province":"Roma",
    "wof:name":"De Angelis Giuseppe",
    "wof:placetype":"venue"
},
  "geometry": {"coordinates":[12.28604,41.733116],"type":"Point"}
}