{
  "type": "Feature",
  "properties": {
    "iso:country":"IT",
    "sg:address":"37057 San Giovanni Lupatoto",
    "sg:city":"San Giovanni Lupatoto",
    "sg:orig_category":"Carni, Salumi E Pesci",
    "sg:phone":"+39 045 549780",
    "sg:postcode":"37057",
    "sg:province":"Verona",
    "wof:name":"Lionetti Giuseppe",
    "wof:placetype":"venue"
},
  "geometry": {"coordinates":[11.052363,45.379398],"type":"Point"}
}