{
  "type": "Feature",
  "properties": {
    "addr:full":"43100 Parma Parma Parma 43100",
    "addr:postcode":"43100;43100",
    "iso:country":"IT",
    "sg:address":"43100 Parma",
    "sg:city":"Parma",
    "sg:orig_category":"Prodotti Finiti Stampati. Forniture Per Uffici",
    "sg:phone":"+39 0521 233162",
    "sg:postcode":"43100",
    "sg:province":"Parma",
    "wof:name":"Margini Ugo",
    "wof:placetype":"venue"
},
  "geometry": {"coordinates":[9.9964075089,44.6934623718],"type":"Point"}
}