{
  "type": "Feature",
  "properties": {
    "addr:full":"87010 Saracena Saracena Cosenza 87010",
    "addr:postcode":"87010;87010",
    "iso:country":"IT",
    "sg:address":"87010 Saracena",
    "sg:city":"Saracena",
    "sg:orig_category":"Materiali E Componenti Elettrotecnici",
    "sg:phone":"+39 0981 34058",
    "sg:postcode":"87010",
    "sg:province":"Cosenza",
    "wof:name":"Olf Di Brasca Antonio",
    "wof:placetype":"venue"
},
  "geometry": {"coordinates":[16.17,39.288612],"type":"Point"}
}