{
  "type": "Feature",
  "properties": {
    "addr:full":"73041 Carmiano Carmiano Lecce 73041",
    "addr:postcode":"73041;73041",
    "iso:country":"IT",
    "sg:address":"73041 Carmiano",
    "sg:city":"Carmiano",
    "sg:orig_category":"Serramenti Ed Infissi",
    "sg:phone":"+39 0832 601100",
    "sg:postcode":"73041",
    "sg:province":"Lecce",
    "wof:name":"Curto Eupremio",
    "wof:placetype":"venue"
},
  "geometry": {"coordinates":[18.042578,40.33802],"type":"Point"}
}