{
  "type": "Feature",
  "properties": {
    "iso:country":"IT",
    "sg:address":"14, Via A. Meucci 42027 Montecchio Emilia",
    "sg:classifiers":[
        {
            "category":"Food & Beverages",
            "subcategory":"Bakery",
            "type":"Retail Goods"
        }
    ],
    "sg:phone":"+39 0522 865464",
    "sg:postcode":"42027",
    "sg:province":"Reggio Nell'Emilia",
    "sg:tags":[
        "grain",
        "cereal"
    ],
    "wof:name":"Nathura (s.r.l.)",
    "wof:placetype":"venue"
},
  "geometry": {"coordinates":[10.627794,44.696228],"type":"Point"}
}