{
  "type": "Feature",
  "properties": {
    "addr:full":"3, Corso Trieste 28100 Novara Novara Novara 28100",
    "addr:postcode":"28100;28100",
    "addr:street":"Corso Trieste",
    "iso:country":"IT",
    "sg:address":"3, Corso Trieste 28100 Novara",
    "sg:city":"Novara",
    "sg:classifiers":[
        {
            "category":"Professional",
            "subcategory":"Engineering",
            "type":"Services"
        }
    ],
    "sg:phone":"+39 0321 696626",
    "sg:postcode":"28100",
    "sg:province":"Novara",
    "sg:tags":[
        "machine",
        "-",
        "mechanical"
    ],
    "wof:name":"Villa Angelo S.a.c.i.f. Srl",
    "wof:placetype":"venue"
},
  "geometry": {"coordinates":[8.632773,45.447475],"type":"Point"}
}