{
  "type": "Feature",
  "properties": {
    "addr:full":"Via Battistotti Sassi 11a, 20133 Milan, Mi Milano 20133",
    "addr:housenumber":"11a",
    "addr:postcode":"20133;20133",
    "addr:street":"Via Battistotti Sassi",
    "iso:country":"IT",
    "sg:address":"Via Battistotti Sassi 11a, 20133 Milan, Mi",
    "sg:classifiers":[
        {
            "category":"Banks & Credit Unions",
            "subcategory":"Bank",
            "type":"Services"
        }
    ],
    "sg:postcode":"20133",
    "sg:province":"Milano",
    "wof:name":"Selmabipiemme Leasing Spa",
    "wof:placetype":"venue"
},
  "geometry": {"coordinates":[9.227766,45.462811],"type":"Point"}
}