{
  "type": "Feature",
  "properties": {
    "iso:country":"IT",
    "sg:address":"20090 Trezzano Sul Naviglio",
    "sg:city":"Trezzano sul Naviglio",
    "sg:orig_category":"Medicali Ed Elettromedicali Impianti Ed Apparecchi - Produzione",
    "sg:phone":"+39 02 4840 0362",
    "sg:postcode":"20090",
    "sg:province":"Milano",
    "wof:name":"Faset Spa",
    "wof:placetype":"venue"
},
  "geometry": {"coordinates":[9.071596,45.428452],"type":"Point"}
}