{
  "type": "Feature",
  "properties": {
    "iso:country":"IT",
    "sg:address":"00040 Pomezia",
    "sg:city":"Pomezia",
    "sg:classifiers":[
        {
            "category":"Building & Trades",
            "subcategory":"Construction",
            "type":"Services"
        }
    ],
    "sg:phone":"+39 06 910 8660",
    "sg:postcode":"00040",
    "sg:province":"Roma",
    "sg:tags":[
        "equipment",
        "heat",
        "heating",
        "engineering"
    ],
    "wof:name":"Multimpianti Srl",
    "wof:placetype":"venue"
},
  "geometry": {"coordinates":[12.506921,41.68074],"type":"Point"}
}