{
  "type": "Feature",
  "properties": {
    "iso:country":"IT",
    "sg:address":"1356, Via Emilia 47020 Longiano",
    "sg:city":"Longiano",
    "sg:classifiers":[
        {
            "category":"Retail",
            "subcategory":"Animal Services",
            "type":"Services"
        }
    ],
    "sg:phone":"+39 39054756162",
    "sg:postcode":"47020",
    "sg:province":"Forl\u00ec-Cesena",
    "sg:tags":[
        "breeding"
    ],
    "wof:name":"G.i.ma. Gruppo Italiano Mangimi S.p.a.",
    "wof:placetype":"venue"
},
  "geometry": {"coordinates":[12.355077,44.097637],"type":"Point"}
}