{
  "type": "Feature",
  "properties": {
    "iso:country":"IT",
    "sg:address":"20159 Milano",
    "sg:city":"Milano",
    "sg:orig_category":"Gioielleria, Oreficeria E Argenteria. Shopping",
    "sg:phone":"+39 02 6900 0223",
    "sg:postcode":"20159",
    "sg:province":"Milano",
    "wof:name":"Par Hasard Di Corinne Jaqueline Halna E C. (s.n.c.)",
    "wof:placetype":"venue"
},
  "geometry": {"coordinates":[9.181721,45.489697],"type":"Point"}
}