{
  "type": "Feature",
  "properties": {
    "iso:country":"IT",
    "sg:address":"Via Umberto I 1, 12047 Rocca De' Baldi, Cn",
    "sg:classifiers":[
        {
            "category":"Banks & Credit Unions",
            "subcategory":"Bank",
            "type":"Services"
        }
    ],
    "sg:postcode":"12047",
    "sg:province":"Cuneo",
    "wof:name":"Credito Cooperativo-cassa Rurale Artigiana Di Rocca De' Baldi (cuneo)",
    "wof:placetype":"venue"
},
  "geometry": {"coordinates":[7.74957,44.427895],"type":"Point"}
}