{
  "type": "Feature",
  "properties": {
    "iso:country":"IT",
    "sg:address":"40035 Castiglione Dei Pepoli",
    "sg:city":"Castiglione dei Pepoli",
    "sg:orig_category":"Frigotecnica, Apparecchiature E Servizi. Arredi Ed Attrezzature Per Uffici",
    "sg:phone":"+39 0534 92524",
    "sg:postcode":"40035",
    "sg:province":"Bologna",
    "wof:name":"Zanni Giovanni",
    "wof:placetype":"venue"
},
  "geometry": {"coordinates":[11.159157753,44.142578125],"type":"Point"}
}