{
  "type": "Feature",
  "properties": {
    "iso:country":"IT",
    "sg:address":"00183 Roma",
    "sg:city":"Roma",
    "sg:classifiers":[
        {
            "category":"Health Services",
            "subcategory":"Health Practitioner",
            "type":"Services"
        }
    ],
    "sg:phone":"+39 06 7720 3768",
    "sg:postcode":"00183",
    "sg:province":"Roma",
    "sg:tags":[
        "medici"
    ],
    "wof:name":"Attanasio Giuseppe",
    "wof:placetype":"venue"
},
  "geometry": {"coordinates":[12.507105,41.88311],"type":"Point"}
}