{
  "type": "Feature",
  "properties": {
    "addr:full":"00198 Roma Roma Roma 00198",
    "addr:postcode":"00198;00198",
    "iso:country":"IT",
    "sg:address":"00198 Roma",
    "sg:city":"Roma",
    "sg:classifiers":[
        {
            "category":"Health Services",
            "subcategory":"Health Practitioner",
            "type":"Services"
        }
    ],
    "sg:phone":"+39 06 854 0867",
    "sg:postcode":"00198",
    "sg:province":"Roma",
    "sg:tags":[
        "medici"
    ],
    "wof:name":"Serafini Stefano",
    "wof:placetype":"venue"
},
  "geometry": {"coordinates":[12.4968605042,41.9127426147],"type":"Point"}
}