{
  "type": "Feature",
  "properties": {
    "iso:country":"IT",
    "sg:address":"37023 Grezzana",
    "sg:city":"Grezzana",
    "sg:orig_category":"Metalli E Leghe",
    "sg:phone":"+39 045 865 0774",
    "sg:postcode":"37023",
    "sg:province":"Verona",
    "wof:name":"Alteco S.r.l.",
    "wof:placetype":"venue"
},
  "geometry": {"coordinates":[11.0001535416,45.5554962158],"type":"Point"}
}