{
  "type": "Feature",
  "properties": {
    "iso:country":"IT",
    "sg:address":"26, Via Luigi Novi 84010 Corbara",
    "sg:city":"Corbara",
    "sg:orig_category":"Miscellaneous Products",
    "sg:phone":"+39 39081930910",
    "sg:postcode":"84010",
    "sg:province":"Salerno",
    "wof:name":"Bronzo S.r.l.",
    "wof:placetype":"venue"
},
  "geometry": {"coordinates":[14.5911493301,40.725692749],"type":"Point"}
}