{
  "type": "Feature",
  "properties": {
    "iso:country":"IT",
    "sg:address":"22079 Villa Guardia",
    "sg:city":"Villa Guardia",
    "sg:orig_category":"Tessuti E Stoffe. Filati E Materie Prime Tessili",
    "sg:phone":"+39 031 563314",
    "sg:postcode":"22079",
    "sg:province":"Como",
    "wof:name":"Tessuto E Colore (s.r.l.)",
    "wof:placetype":"venue"
},
  "geometry": {"coordinates":[9.016428,45.769627],"type":"Point"}
}