{
  "type": "Feature",
  "properties": {
    "iso:country":"IT",
    "sg:address":"83, Via Fossa Lavezzola 44033 Berra",
    "sg:city":"Berra",
    "sg:classifiers":[
        {
            "category":"Food & Beverages",
            "subcategory":"Bakery",
            "type":"Retail Goods"
        }
    ],
    "sg:phone":"+39 0532 833784",
    "sg:postcode":"44033",
    "sg:province":"Ferrara",
    "sg:tags":[
        "grain",
        "cereal"
    ],
    "wof:name":"C.a.p.a. Cologna (s.r.l.)",
    "wof:placetype":"venue"
},
  "geometry": {"coordinates":[11.891789,44.968952],"type":"Point"}
}