{
  "type": "Feature",
  "properties": {
    "iso:country":"IT",
    "sg:address":"181, Viale Delle Nazioni 48100 Ravenna",
    "sg:city":"Ravenna",
    "sg:classifiers":[
        {
            "category":"Travel",
            "subcategory":"Travel Agent",
            "type":"Entertainment"
        }
    ],
    "sg:phone":"+39 0544 531743",
    "sg:postcode":"48100",
    "sg:province":"Ravenna",
    "sg:tags":[
        "business"
    ],
    "wof:name":"Park Hotel Ravenna",
    "wof:placetype":"venue"
},
  "geometry": {"coordinates":[12.282368,44.482555],"type":"Point"}
}