{
  "type": "Feature",
  "properties": {
    "iso:country":"IT",
    "sg:address":"16165 Genova",
    "sg:city":"Genova",
    "sg:classifiers":[
        {
            "category":"Health Services",
            "subcategory":"Hospital",
            "type":"Services"
        }
    ],
    "sg:phone":"+39 010 830 9103",
    "sg:postcode":"16165",
    "sg:province":"Genova",
    "sg:tags":[
        "equipment",
        "systems",
        "supply"
    ],
    "wof:name":"Behringer Snc",
    "wof:placetype":"venue"
},
  "geometry": {"coordinates":[9.000697,44.447052],"type":"Point"}
}