{
  "type": "Feature",
  "properties": {
    "addr:full":"00060 Sacrofano Sacrofano Roma 00060",
    "addr:postcode":"00060;00060",
    "iso:country":"IT",
    "sg:address":"00060 Sacrofano",
    "sg:city":"Sacrofano",
    "sg:orig_category":"Prodotti Alimentari",
    "sg:phone":"+39 06 908 6868",
    "sg:postcode":"00060",
    "sg:province":"Roma",
    "wof:name":"Meleddu Maria",
    "wof:placetype":"venue"
},
  "geometry": {"coordinates":[12.4509096146,42.1036834717],"type":"Point"}
}