{
  "type": "Feature",
  "properties": {
    "iso:country":"IT",
    "sg:address":"97019 Vittoria",
    "sg:city":"Vittoria",
    "sg:orig_category":"Prodotti Alimentari",
    "sg:phone":"+39 0932 861058",
    "sg:postcode":"97019",
    "sg:province":"Ragusa",
    "wof:name":"Nuova Linea Verde Soc.coop.r.l.",
    "wof:placetype":"venue"
},
  "geometry": {"coordinates":[14.4956235886,36.9358253479],"type":"Point"}
}