{
  "type": "Feature",
  "properties": {
    "iso:country":"IT",
    "sg:address":"Via Brescia 4 31010 Mareno Di Piave",
    "sg:city":"Mareno di Piave",
    "sg:orig_category":"Hoisiery Goods",
    "sg:phone":"+39 0438 492488",
    "sg:postcode":"31010",
    "sg:province":"Treviso",
    "wof:name":"Maglificio Barro Cunegonda",
    "wof:placetype":"venue"
},
  "geometry": {"coordinates":[12.352576,45.842392],"type":"Point"}
}