{
  "type": "Feature",
  "properties": {
    "addr:full":"20019 Settimo Milanese Settimo Milanese Milano 20019",
    "addr:postcode":"20019;20019",
    "iso:country":"IT",
    "sg:address":"20019 Settimo Milanese",
    "sg:city":"Settimo Milanese",
    "sg:orig_category":"Ospedali E Servizi Sanitari. Servizi Ausiliari Di Analisi, Controllo E Ricerca",
    "sg:phone":"+39 02 4892 0265",
    "sg:postcode":"20019",
    "sg:province":"Milano",
    "wof:name":"C.m.a. Sas Dr. Miriam Magri' & C.",
    "wof:placetype":"venue"
},
  "geometry": {"coordinates":[9.074098,45.458851],"type":"Point"}
}