{
  "type": "Feature",
  "properties": {
    "iso:country":"IT",
    "sg:address":"00185 Roma",
    "sg:city":"Roma",
    "sg:orig_category":"Alberghi",
    "sg:phone":"+39 06 4470 2024",
    "sg:postcode":"00185",
    "sg:province":"Roma",
    "sg:website":"http://www.mecenatepalace.com",
    "wof:name":"Mecenate Palace Hotel",
    "wof:placetype":"venue"
},
  "geometry": {"coordinates":[12.446297,41.869488],"type":"Point"}
}