{
  "type": "Feature",
  "properties": {
    "addr:full":"06035 Gualdo Cattaneo Gualdo Cattaneo Perugia 06035",
    "addr:postcode":"06035;06035",
    "iso:country":"IT",
    "sg:address":"06035 Gualdo Cattaneo",
    "sg:city":"Gualdo Cattaneo",
    "sg:classifiers":[
        {
            "category":"Home & Garden",
            "subcategory":"Building Materials",
            "type":"Retail Goods"
        }
    ],
    "sg:phone":"+39 0742 98367",
    "sg:postcode":"06035",
    "sg:province":"Perugia",
    "sg:tags":[
        "stone",
        "similar",
        "marble"
    ],
    "wof:name":"Burlarelli Marcello, Romano & C. Snc",
    "wof:placetype":"venue"
},
  "geometry": {"coordinates":[12.473316,42.864208],"type":"Point"}
}