{
  "type": "Feature",
  "properties": {
    "iso:country":"IT",
    "sg:address":"16040 Neirone",
    "sg:city":"Ne",
    "sg:orig_category":"Alberghi E Strutture Extra Alberghiere. Ospedali E Servizi Sanitari",
    "sg:phone":"+39 0185 936006",
    "sg:postcode":"16040",
    "sg:province":"Genova",
    "wof:name":"Casa Alpina S. Sabina",
    "wof:placetype":"venue"
},
  "geometry": {"coordinates":[9.191035,44.454494],"type":"Point"}
}