{
  "type": "Feature",
  "properties": {
    "iso:country":"IT",
    "sg:address":"70126 Bari",
    "sg:city":"Bari",
    "sg:orig_category":"Macchine, Impianti Ed Attrezzature Per Industria Alimentare E Bevande",
    "sg:phone":"+39 080 549 3297",
    "sg:postcode":"70126",
    "sg:province":"Bari",
    "wof:name":"Caracciolese Tommaso",
    "wof:placetype":"venue"
},
  "geometry": {"coordinates":[16.920811,41.105526],"type":"Point"}
}