{
  "type": "Feature",
  "properties": {
    "iso:country":"IT",
    "sg:address":"50023 Impruneta",
    "sg:city":"Impruneta",
    "sg:orig_category":"Dolciumi E Gelati",
    "sg:phone":"+39 055 237 3032",
    "sg:postcode":"50023",
    "sg:province":"Firenze",
    "wof:name":"Stefani Renzo",
    "wof:placetype":"venue"
},
  "geometry": {"coordinates":[11.218463,43.711407],"type":"Point"}
}