{
  "type": "Feature",
  "properties": {
    "iso:country":"IT",
    "sg:address":"62/64, V. Montanina 25080 Manerba Del Garda",
    "sg:city":"Manerba del Garda",
    "sg:classifiers":[
        {
            "category":"Wholesale",
            "subcategory":"Medical Equipment & Supplies",
            "type":"Manufacturing & Wholesale Goods"
        }
    ],
    "sg:phone":"+39 036 565 1888",
    "sg:postcode":"25080",
    "sg:province":"Brescia",
    "sg:tags":[
        "-",
        "health",
        "instrument"
    ],
    "sg:website":"http://www.paginegialle.it/mauricebs",
    "wof:name":"Maurice Di Maurizio Torri",
    "wof:placetype":"venue"
},
  "geometry": {"coordinates":[10.5341,45.563484],"type":"Point"}
}