{
  "type": "Feature",
  "properties": {
    "iso:country":"IT",
    "sg:address":"30020 Marcon",
    "sg:city":"Marcon",
    "sg:orig_category":"Fonderie",
    "sg:phone":"+39 041 456 9417",
    "sg:postcode":"30020",
    "sg:province":"Venezia",
    "wof:name":"I.f.i. Srl",
    "wof:placetype":"venue"
},
  "geometry": {"coordinates":[12.3079938889,45.5491638184],"type":"Point"}
}