{
  "type": "Feature",
  "properties": {
    "iso:country":"IT",
    "sg:address":"20080 Zibido San Giacomo",
    "sg:city":"Zibido San Giacomo",
    "sg:classifiers":[
        {
            "category":"Home & Garden",
            "subcategory":"Home Furnishings",
            "type":"Retail Goods"
        }
    ],
    "sg:phone":"+39 02 900231",
    "sg:postcode":"20080",
    "sg:province":"Milano",
    "sg:tags":[
        "varnish",
        "enamel",
        "paints",
        "industry",
        "wood",
        "machinery",
        "supplies"
    ],
    "wof:name":"Unitecta Italiana Spa",
    "wof:placetype":"venue"
},
  "geometry": {"coordinates":[9.116897583,45.3676834106],"type":"Point"}
}