{
  "type": "Feature",
  "properties": {
    "iso:country":"IT",
    "sg:address":"00193 Roma",
    "sg:city":"Roma",
    "sg:orig_category":"Scuole E Servizi Scolastici. Centri Di Estetica E Cosmesi E Servizi. Ricerca, Selezione E Formazione Del Personale",
    "sg:phone":"+39 06 6830 9007",
    "sg:postcode":"00193",
    "sg:province":"Roma",
    "wof:name":"Accademia Estetica Specializzata S.a.s.",
    "wof:placetype":"venue"
},
  "geometry": {"coordinates":[12.466791,41.907482],"type":"Point"}
}