{
  "type": "Feature",
  "properties": {
    "iso:country":"IT",
    "sg:address":"Ctr Gabbia Zona Industriale 98040 Giammoro",
    "sg:classifiers":[
        {
            "category":"Wholesale",
            "subcategory":"Fruits & Vegetables",
            "type":"Manufacturing & Wholesale Goods"
        }
    ],
    "sg:phone":"+39 090 938 4570",
    "sg:postcode":"98040",
    "sg:province":"Messina",
    "sg:tags":[
        "citrus",
        "concentrate"
    ],
    "wof:name":"Idag Industria Derivati Agrumari Giammoro E Gelati",
    "wof:placetype":"venue"
},
  "geometry": {"coordinates":[15.555523,38.192333],"type":"Point"}
}