{
  "type": "Feature",
  "properties": {
    "addr:full":"24124 Bergamo Bergamo Bergamo 24124",
    "addr:postcode":"24124;24124",
    "iso:country":"IT",
    "sg:address":"24124 Bergamo",
    "sg:city":"Bergamo",
    "sg:orig_category":"Scuole E Servizi Scolastici. Ricerca, Selezione E Formazione Del Personale",
    "sg:phone":"+39 035 343004",
    "sg:postcode":"24124",
    "sg:province":"Bergamo",
    "sg:website":"http://www.studioperico.it",
    "wof:name":"Perico Pierina",
    "wof:placetype":"venue"
},
  "geometry": {"coordinates":[9.693825,45.713516],"type":"Point"}
}