{
  "type": "Feature",
  "properties": {
    "iso:country":"IT",
    "sg:address":"15/17, Vl. Caproni 38068 Rovereto",
    "sg:city":"Rovereto",
    "sg:classifiers":[
        {
            "category":"Professional",
            "subcategory":"Engineering",
            "type":"Services"
        }
    ],
    "sg:phone":"+39 0464 486896",
    "sg:postcode":"38068",
    "sg:province":"Trento",
    "sg:tags":[
        "machine",
        "-",
        "mechanical"
    ],
    "sg:website":"http://www.alitech-online.it",
    "wof:name":"Alitech Srl",
    "wof:placetype":"venue"
},
  "geometry": {"coordinates":[11.014523,45.864624],"type":"Point"}
}