{
  "type": "Feature",
  "properties": {
    "iso:country":"IT",
    "sg:address":"80016 Marano Di Napoli",
    "sg:city":"Marano di Napoli",
    "sg:orig_category":"Alimentari - Vendita Al Dettaglio",
    "sg:phone":"+39 081 742 3000",
    "sg:postcode":"80016",
    "sg:province":"Napoli",
    "wof:name":"Alimentari Carputo & C. Sas",
    "wof:placetype":"venue"
},
  "geometry": {"coordinates":[14.177153,40.899773],"type":"Point"}
}