{
  "type": "Feature",
  "properties": {
    "iso:country":"IT",
    "sg:address":"56012 Fornacette",
    "sg:city":"Fornacette",
    "sg:orig_category":"Calzature, Pelletterie E Pelli",
    "sg:phone":"+39 0587 420833",
    "sg:postcode":"56012",
    "sg:province":"Pisa",
    "wof:name":"Tesi Annalisa",
    "wof:placetype":"venue"
},
  "geometry": {"coordinates":[10.587964,43.668404],"type":"Point"}
}