{
  "type": "Feature",
  "properties": {
    "iso:country":"IT",
    "sg:address":"45030 Borsea",
    "sg:orig_category":"Trasporti E Spedizioni Merci",
    "sg:phone":"+39 0425 474457",
    "sg:postcode":"45030",
    "sg:province":"Rovigo",
    "wof:name":"Bartolini Spa",
    "wof:placetype":"venue"
},
  "geometry": {"coordinates":[11.813924,45.043064],"type":"Point"}
}