{
  "type": "Feature",
  "properties": {
    "iso:country":"IT",
    "sg:address":"53, Via De Sanctis Francesco 20141 Milano",
    "sg:city":"Milano",
    "sg:classifiers":[
        {
            "category":"Shopping",
            "type":"Retail Goods"
        }
    ],
    "sg:phone":"+39 02 8950 2912",
    "sg:postcode":"20141",
    "sg:province":"Milano",
    "sg:tags":[
        "finished",
        "-",
        "metallic"
    ],
    "wof:name":"Econex S.r.l.",
    "wof:placetype":"venue"
},
  "geometry": {"coordinates":[9.2032260895,45.4824676514],"type":"Point"}
}