{
  "type": "Feature",
  "properties": {
    "addr:full":"23899 Robbiate Robbiate Lecco 23899",
    "addr:postcode":"23899;23899",
    "iso:country":"IT",
    "sg:address":"23899 Robbiate",
    "sg:city":"Robbiate",
    "sg:orig_category":"Macchine E Forniture Per Arredamento E Industria Del Legno. Macchine Utensili E Impianti",
    "sg:phone":"+39 039 951 5755",
    "sg:postcode":"23899",
    "sg:province":"Lecco",
    "wof:name":"Scamu Di Vigano' G.",
    "wof:placetype":"venue"
},
  "geometry": {"coordinates":[9.422276,45.893314],"type":"Point"}
}