{
  "type": "Feature",
  "properties": {
    "addr:full":"Piazza Puccini 8; Vizzolo Predabissi; 20077 Milano 20077",
    "addr:housenumber":"8",
    "addr:postcode":"20077;20077",
    "addr:street":"Piazza Puccini;Predabissi",
    "iso:country":"IT",
    "sg:address":"Piazza Puccini 8; Vizzolo Predabissi; 20077",
    "sg:classifiers":[
        {
            "category":"Banks & Credit Unions",
            "subcategory":"Bank",
            "type":"Services"
        }
    ],
    "sg:phone":"+39 02 9823 1114",
    "sg:postcode":"20077",
    "sg:province":"Milano",
    "wof:name":"Istituto Bancario, San Paolo Di Torino Spa",
    "wof:placetype":"venue"
},
  "geometry": {"coordinates":[9.346756,45.359631],"type":"Point"}
}