{
  "type": "Feature",
  "properties": {
    "addr:full":"20123 Milano Milano Milano 20123",
    "addr:postcode":"20123;20123",
    "iso:country":"IT",
    "sg:address":"20123 Milano",
    "sg:city":"Milano",
    "sg:orig_category":"Servizi Al Turismo. Trasporto Pubblico E Privato. Acqua, Luce, Gas E Societa' Di Esercizio Pubblico. Pubblica Amministrazione",
    "sg:phone":"+39 02 8645 0051",
    "sg:postcode":"20123",
    "sg:province":"Milano",
    "wof:name":"F.s. S.p.a.-divisione Passeggeri Business Lunga Percorrenza",
    "wof:placetype":"venue"
},
  "geometry": {"coordinates":[9.177901,45.465885],"type":"Point"}
}