{
  "type": "Feature",
  "properties": {
    "addr:full":"Via Per San Felice, 38/42 41031 Camposanto Sul Panaro Camposanto Modena 41031",
    "addr:housenumber":"38 / 42",
    "addr:postcode":"41031;41031",
    "addr:street":"Via Per San Felice",
    "iso:country":"IT",
    "sg:address":"Via Per San Felice, 38/42 41031 Camposanto Sul Panaro",
    "sg:city":"Camposanto",
    "sg:orig_category":"Lithos",
    "sg:phone":"+39 0535 87378",
    "sg:postcode":"41031",
    "sg:province":"Modena",
    "sg:website":"www.modulosei.it",
    "wof:name":"Modulo Sei",
    "wof:placetype":"venue"
},
  "geometry": {"coordinates":[11.134967,44.794521],"type":"Point"}
}