{
  "type": "Feature",
  "properties": {
    "iso:country":"IT",
    "sg:address":"00042 Lavinio-lido Di Enea",
    "sg:orig_category":"Materiali Edili",
    "sg:phone":"+39 06 987 1437",
    "sg:postcode":"00042",
    "sg:province":"Roma",
    "wof:name":"Colonia Luciano",
    "wof:placetype":"venue"
},
  "geometry": {"coordinates":[12.621242,41.496071],"type":"Point"}
}