{
  "type": "Feature",
  "properties": {
    "iso:country":"IT",
    "sg:address":"20092 Cinisello Balsamo",
    "sg:city":"Cinisello Balsamo",
    "sg:orig_category":"Impianti, Attrezzature E Forniture Sanitarie Ed Ospedaliere",
    "sg:phone":"+39 02 617 4766",
    "sg:postcode":"20092",
    "sg:province":"Milano",
    "wof:name":"Astidental Di Sabbione S.r.l.",
    "wof:placetype":"venue"
},
  "geometry": {"coordinates":[9.195832,45.549068],"type":"Point"}
}