{
  "type": "Feature",
  "properties": {
    "iso:country":"IT",
    "sg:address":"10036 Settimo Torinese",
    "sg:city":"Settimo Torinese",
    "sg:classifiers":[
        {
            "category":"Manufacturing",
            "subcategory":"Tools & Machinery",
            "type":"Manufacturing & Wholesale Goods"
        }
    ],
    "sg:phone":"+39 011 816 9711",
    "sg:postcode":"10036",
    "sg:province":"Torino",
    "sg:tags":[
        "device",
        "handling"
    ],
    "wof:name":"Spanset Italia - S.r.l.",
    "wof:placetype":"venue"
},
  "geometry": {"coordinates":[7.772878,45.138325],"type":"Point"}
}