{
  "type": "Feature",
  "properties": {
    "iso:country":"IT",
    "sg:address":"16149 Genova",
    "sg:city":"Genova",
    "sg:orig_category":"Apparecchiature E Sistemi Per Imballaggio E Confezionamento. Apparecchiature E Sistemi Per Magazzinaggio E Movimentazione",
    "sg:phone":"+39 010 645 8744",
    "sg:postcode":"16149",
    "sg:province":"Genova",
    "wof:name":"Luigi Arduini International Srl",
    "wof:placetype":"venue"
},
  "geometry": {"coordinates":[8.889291,44.412804],"type":"Point"}
}