{
  "type": "Feature",
  "properties": {
    "iso:country":"IT",
    "sg:address":"Cso Venezia 93 14100 Asti",
    "sg:city":"Asti",
    "sg:classifiers":[
        {
            "category":"Wholesale",
            "subcategory":"Fruits & Vegetables",
            "type":"Manufacturing & Wholesale Goods"
        }
    ],
    "sg:phone":"+39 0141 353807",
    "sg:postcode":"14100",
    "sg:province":"Asti",
    "sg:tags":[
        "seed"
    ],
    "sg:website":"www.olter.it",
    "wof:name":"Olter Srl",
    "wof:placetype":"venue"
},
  "geometry": {"coordinates":[8.208578,44.892044],"type":"Point"}
}