{
  "type": "Feature",
  "properties": {
    "addr:full":"233, Corso Novara 27029 Vigevano Vigevano Pavia 27029",
    "addr:postcode":"27029;27029",
    "addr:street":"Corso Novara",
    "iso:country":"IT",
    "sg:address":"233, Corso Novara 27029 Vigevano",
    "sg:city":"Vigevano",
    "sg:classifiers":[
        {
            "category":"Manufacturing",
            "subcategory":"Rubber & Plastics",
            "type":"Manufacturing & Wholesale Goods"
        }
    ],
    "sg:phone":"+39 39038120869",
    "sg:postcode":"27029",
    "sg:province":"Pavia",
    "wof:name":"Sir (s.r.l.)",
    "wof:placetype":"venue"
},
  "geometry": {"coordinates":[8.8329734802,45.3360290527],"type":"Point"}
}