{
  "type": "Feature",
  "properties": {
    "addr:full":"20122 Milano Milano Milano 20122",
    "addr:postcode":"20122;20122",
    "iso:country":"IT",
    "sg:address":"20122 Milano",
    "sg:city":"Milano",
    "sg:orig_category":"Non-classified Establishments",
    "sg:phone":"+39 02 722271",
    "sg:postcode":"20122",
    "sg:province":"Milano",
    "sg:website":"http://www.tupperware.it",
    "wof:name":"Tupperware Italia Spa",
    "wof:placetype":"venue"
},
  "geometry": {"coordinates":[9.190564,45.459599],"type":"Point"}
}