{
  "type": "Feature",
  "properties": {
    "addr:full":"20021 Baranzate Bollate Baranzate Milano 20021",
    "addr:postcode":"20021;20021",
    "iso:country":"IT",
    "sg:address":"20021 Baranzate Bollate",
    "sg:city":"Baranzate",
    "sg:orig_category":"Servizi Ausiliari Dei Mezzi Di Trasporto",
    "sg:phone":"+39 02 356 0387",
    "sg:postcode":"20021",
    "sg:province":"Milano",
    "wof:name":"Autodemolizioni Fino Snc",
    "wof:placetype":"venue"
},
  "geometry": {"coordinates":[9.106105,45.524544],"type":"Point"}
}