{
  "type": "Feature",
  "properties": {
    "iso:country":"IT",
    "sg:address":"00137 Roma",
    "sg:city":"Roma",
    "sg:classifiers":[
        {
            "category":"Home & Garden",
            "subcategory":"Furniture",
            "type":"Retail Goods"
        }
    ],
    "sg:phone":"+39 06 8680 2237",
    "sg:postcode":"00137",
    "sg:province":"Roma",
    "sg:tags":[
        "furnishing"
    ],
    "wof:name":"Fortuna Antichit\u00c0 - Centro Arredamenti Nomentano",
    "wof:placetype":"venue"
},
  "geometry": {"coordinates":[12.5781297684,41.9563522339],"type":"Point"}
}