{
  "type": "Feature",
  "properties": {
    "addr:full":"14/k, Strada Statale 351 34070 Villesse Villesse Gorizia 34070",
    "addr:housenumber":"14 / k;351",
    "addr:postcode":"34070;34070",
    "addr:street":"Strada Statale",
    "iso:country":"IT",
    "sg:address":"14/k, Strada Statale 351 34070 Villesse",
    "sg:city":"Villesse",
    "sg:classifiers":[
        {
            "category":"Shopping",
            "type":"Retail Goods"
        }
    ],
    "sg:phone":"+39 39048191000",
    "sg:postcode":"34070",
    "sg:province":"Gorizia",
    "sg:tags":[
        "finished",
        "-",
        "metallic"
    ],
    "wof:name":"Segnaletica Stradale Giuliana (s.r.l.)",
    "wof:placetype":"venue"
},
  "geometry": {"coordinates":[13.6215457916,45.9413032532],"type":"Point"}
}