{
  "type": "Feature",
  "properties": {
    "addr:full":"20066 Melzo Melzo Milano 20066",
    "addr:postcode":"20066;20066",
    "iso:country":"IT",
    "sg:address":"20066 Melzo",
    "sg:city":"Melzo",
    "sg:orig_category":"Servizi Editoriali. Professionisti - Studi E Servizi Ed Associazioni Di Interesse Aziendale",
    "sg:phone":"+39 02 9571 0601",
    "sg:postcode":"20066",
    "sg:province":"Milano",
    "wof:name":"Bellisario Michele",
    "wof:placetype":"venue"
},
  "geometry": {"coordinates":[9.424551,45.499393],"type":"Point"}
}