{
  "type": "Feature",
  "properties": {
    "addr:full":"20158 Milano Milano Milano 20158",
    "addr:postcode":"20158;20158",
    "iso:country":"IT",
    "sg:address":"20158 Milano",
    "sg:city":"Milano",
    "sg:orig_category":"Medici. Assicurazioni E Servizi Assicurativi. Avvocati, Notai E Servizi Legali. Professionisti - Studi E Servizi Ed Associazioni Di Interesse Aziendale",
    "sg:phone":"+39 02 3931 4364",
    "sg:postcode":"20158",
    "sg:province":"Milano",
    "wof:name":"Studio Associato Medicina Del Lavoro Dott. Giuseppe Vibracci & C. Associazio",
    "wof:placetype":"venue"
},
  "geometry": {"coordinates":[9.1713647842,45.4975814819],"type":"Point"}
}