{
  "type": "Feature",
  "properties": {
    "iso:country":"IT",
    "sg:address":"2/a, Via Portoncino 58036 Roccastrada",
    "sg:city":"Roccastrada",
    "sg:classifiers":[
        {
            "category":"Personal",
            "subcategory":"Shoe Repair & Shine",
            "type":"Services"
        }
    ],
    "sg:phone":"+39 0564 565546",
    "sg:postcode":"58036",
    "sg:province":"Grosseto",
    "sg:tags":[
        "leather"
    ],
    "wof:name":"Tomaificio Roccastrada Di Regoli Giacomo E C.s.a.s",
    "wof:placetype":"venue"
},
  "geometry": {"coordinates":[11.112782,42.762859],"type":"Point"}
}