{
  "type": "Feature",
  "properties": {
    "iso:country":"IT",
    "sg:address":"20010 Casorezzo",
    "sg:city":"Casorezzo",
    "sg:orig_category":"Automazione E Macchine Per Ufficio",
    "sg:phone":"+39 02 9038 0438",
    "sg:postcode":"20010",
    "sg:province":"Milano",
    "wof:name":"De Grandi Manuele",
    "wof:placetype":"venue"
},
  "geometry": {"coordinates":[9.162722,45.459152],"type":"Point"}
}