{
  "type": "Feature",
  "properties": {
    "addr:full":"80047 San Giuseppe Vesuviano San Giuseppe Vesuviano Napoli 80047",
    "addr:postcode":"80047;80047",
    "iso:country":"IT",
    "sg:address":"80047 San Giuseppe Vesuviano",
    "sg:city":"San Giuseppe Vesuviano",
    "sg:orig_category":"Materiali Semilavorati Metallici",
    "sg:phone":"+39 081 827 1196",
    "sg:postcode":"80047",
    "sg:province":"Napoli",
    "wof:name":"Annunziata Gennaro",
    "wof:placetype":"venue"
},
  "geometry": {"coordinates":[14.501448,40.826004],"type":"Point"}
}