{
  "type": "Feature",
  "properties": {
    "addr:full":"47, Via Iazzitiello; Santeramo In Colle; Bari; 70029 Santeramo in Colle Bari 70029",
    "addr:postcode":"70029;70029",
    "addr:street":"Via Iazzitiello",
    "iso:country":"IT",
    "sg:address":"47, Via Iazzitiello; Santeramo In Colle; Bari; 70029",
    "sg:city":"Santeramo in Colle",
    "sg:classifiers":[
        {
            "category":"Industrial Area",
            "type":"Public Place"
        }
    ],
    "sg:phone":"+39 39808820111",
    "sg:postcode":"70029",
    "sg:province":"Bari",
    "sg:tags":[
        "large",
        "private"
    ],
    "sg:website":"www.natuzzi.com",
    "wof:name":"Natuzzi S.p.a.",
    "wof:placetype":"venue"
},
  "geometry": {"coordinates":[16.7513027191,40.7857017517],"type":"Point"}
}