{
  "type": "Feature",
  "properties": {
    "addr:full":"16, Via S. Alfonso Maria De Liguori 84135 Salerno Salerno Salerno 84135",
    "addr:postcode":"84135;84135",
    "addr:street":"Via S. Alfonso Maria De Liguori",
    "iso:country":"IT",
    "sg:address":"16, Via S. Alfonso Maria De Liguori 84135 Salerno",
    "sg:city":"Salerno",
    "sg:classifiers":[
        {
            "category":"Manufacturing",
            "subcategory":"Printing",
            "type":"Manufacturing & Wholesale Goods"
        }
    ],
    "sg:phone":"+39 39089274777",
    "sg:postcode":"84135",
    "sg:province":"Salerno",
    "sg:tags":[
        "publishing"
    ],
    "wof:name":"Simec Srl",
    "wof:placetype":"venue"
},
  "geometry": {"coordinates":[14.765912056,40.6779556274],"type":"Point"}
}