{
  "type": "Feature",
  "properties": {
    "iso:country":"IT",
    "sg:address":"70125 Bari",
    "sg:city":"Bari",
    "sg:orig_category":"Copritermosifoni",
    "sg:phone":"+39 080 556 4193",
    "sg:postcode":"70125",
    "sg:province":"Bari",
    "wof:name":"Dimensione Casa Di Pietro Calo'",
    "wof:placetype":"venue"
},
  "geometry": {"coordinates":[16.869995,41.110085],"type":"Point"}
}