{
  "type": "Feature",
  "properties": {
    "iso:country":"IT",
    "sg:address":"65128 Pescara",
    "sg:city":"Pescara",
    "sg:orig_category":"Materiali E Componenti Elettronici",
    "sg:phone":"+39 085 431 2488",
    "sg:postcode":"65128",
    "sg:province":"Pescara",
    "wof:name":"Young Company S.n.c.",
    "wof:placetype":"venue"
},
  "geometry": {"coordinates":[14.197629,42.441456],"type":"Point"}
}