{
  "type": "Feature",
  "properties": {
    "iso:country":"IT",
    "sg:address":"25040 Monticelli Brusati",
    "sg:city":"Monticelli Brusati",
    "sg:orig_category":"Materiali E Componenti Elettrotecnici",
    "sg:phone":"+39 030 685 0777",
    "sg:postcode":"25040",
    "sg:province":"Brescia",
    "wof:name":"Archetti Enrico",
    "wof:placetype":"venue"
},
  "geometry": {"coordinates":[10.108772,45.596485],"type":"Point"}
}