{
  "type": "Feature",
  "properties": {
    "addr:full":"Corso Amatuzio 64-66; Boiano; 86021 Campobasso 86021",
    "addr:housenumber":"64-66",
    "addr:postcode":"86021;86021",
    "addr:street":"Corso Amatuzio",
    "iso:country":"IT",
    "sg:address":"Corso Amatuzio 64-66; Boiano; 86021",
    "sg:classifiers":[
        {
            "category":"Banks & Credit Unions",
            "subcategory":"Bank",
            "type":"Services"
        }
    ],
    "sg:phone":"+39 0874 778111",
    "sg:postcode":"86021",
    "sg:province":"Campobasso",
    "wof:name":"Banco Di Napoli Spa",
    "wof:placetype":"venue"
},
  "geometry": {"coordinates":[14.472718,41.484383],"type":"Point"}
}