{
  "type": "Feature",
  "properties": {
    "iso:country":"IT",
    "sg:address":"23032 Bormio",
    "sg:city":"Bormio",
    "sg:orig_category":"Scuole Di Addestramento Sportivo",
    "sg:phone":"+39 0342 901553",
    "sg:postcode":"23032",
    "sg:province":"Sondrio",
    "wof:name":"Scuola Nazionale Sci Bormio",
    "wof:placetype":"venue"
},
  "geometry": {"coordinates":[10.375435,46.463951],"type":"Point"}
}