{
  "type": "Feature",
  "properties": {
    "addr:full":"23900 Lecco Lecco Lecco 23900",
    "addr:postcode":"23900;23900",
    "iso:country":"IT",
    "sg:address":"23900 Lecco",
    "sg:city":"Lecco",
    "sg:orig_category":"Macchine, Impianti Ed Attrezzature Industria Chimica. Attrezzature E Forniture Per Officine Riparazione E Servizi Ausiliari",
    "sg:phone":"+39 0341 363199",
    "sg:postcode":"23900",
    "sg:province":"Lecco",
    "wof:name":"Saguto Natale I.e.c.i.",
    "wof:placetype":"venue"
},
  "geometry": {"coordinates":[9.415548,45.849552],"type":"Point"}
}