{
  "type": "Feature",
  "properties": {
    "iso:country":"IT",
    "sg:address":"Torre Wtc, Via De Marini, 1; Genoa; 16149",
    "sg:classifiers":[
        {
            "category":"Industrial Area",
            "type":"Public Place"
        }
    ],
    "sg:phone":"+39 391 024 011",
    "sg:postcode":"16149",
    "sg:province":"Genova",
    "sg:tags":[
        "large",
        "private"
    ],
    "sg:website":"www.erg.it",
    "wof:name":"Erg S.p.a.",
    "wof:placetype":"venue"
},
  "geometry": {"coordinates":[8.900475502,44.408706665],"type":"Point"}
}