{
  "type": "Feature",
  "properties": {
    "addr:full":"90144 Palermo Palermo Palermo 90144",
    "addr:postcode":"90144;90144",
    "iso:country":"IT",
    "sg:address":"90144 Palermo",
    "sg:city":"Palermo",
    "sg:orig_category":"Impiantistica E Prodotti Tecnologici Per Edilizia. Macchine, Strumenti Ed Apparecchi Per Attivita' Industriali",
    "sg:phone":"+39 091 227494",
    "sg:postcode":"90144",
    "sg:province":"Palermo",
    "wof:name":"Procotec S.a.s. Dell'arch.ettore Petracca & C.",
    "wof:placetype":"venue"
},
  "geometry": {"coordinates":[13.335132,38.141323],"type":"Point"}
}