{
  "type": "Feature",
  "properties": {
    "addr:full":"3, Via Maestri Del Lavoro 21018 Sesto Calende Sesto Calende Varese 21018",
    "addr:postcode":"21018;21018",
    "addr:street":"Via Maestri Del Lavoro",
    "iso:country":"IT",
    "sg:address":"3, Via Maestri Del Lavoro 21018 Sesto Calende",
    "sg:city":"Sesto Calende",
    "sg:classifiers":[
        {
            "category":"Shopping",
            "type":"Retail Goods"
        }
    ],
    "sg:phone":"+39 0331 923375",
    "sg:postcode":"21018",
    "sg:province":"Varese",
    "sg:tags":[
        "finished",
        "-",
        "metallic"
    ],
    "wof:name":"Luigi Miglioranza S.r.l.",
    "wof:placetype":"venue"
},
  "geometry": {"coordinates":[8.6515111923,45.7269248962],"type":"Point"}
}