{
  "type": "Feature",
  "properties": {
    "iso:country":"IT",
    "sg:address":"16, V. Sempione 21029 Vergiate",
    "sg:city":"Vergiate",
    "sg:classifiers":[
        {
            "category":"Shopping",
            "type":"Retail Goods"
        }
    ],
    "sg:phone":"+39 0331 948186",
    "sg:postcode":"21029",
    "sg:province":"Varese",
    "sg:tags":[
        "finished",
        "-",
        "metallic"
    ],
    "sg:website":"http://www.paginegialle.it/stesy",
    "wof:name":"Stesy Srl",
    "wof:placetype":"venue"
},
  "geometry": {"coordinates":[8.6963148117,45.7093009949],"type":"Point"}
}