{
  "type": "Feature",
  "properties": {
    "addr:full":"Via Sonnino Sidney 208 09127 Cagliari Cagliari Cagliari 09127",
    "addr:housenumber":"208",
    "addr:postcode":"09127;09127",
    "addr:street":"Via Sonnino Sidney",
    "iso:country":"IT",
    "sg:address":"Via Sonnino Sidney 208 09127 Cagliari",
    "sg:city":"Cagliari",
    "sg:classifiers":[
        {
            "category":"Manufacturing",
            "subcategory":"Electronics",
            "type":"Manufacturing & Wholesale Goods"
        }
    ],
    "sg:phone":"+39 070 656878",
    "sg:postcode":"09127",
    "sg:province":"Cagliari",
    "sg:tags":[
        "large",
        "machine",
        "industrial",
        "electrical",
        "equipment"
    ],
    "wof:name":"Samef Srl Sarda Marketing Elettronica Forniture",
    "wof:placetype":"venue"
},
  "geometry": {"coordinates":[9.119201,39.212006],"type":"Point"}
}