{
  "type": "Feature",
  "properties": {
    "iso:country":"IT",
    "sg:address":"00154 Roma",
    "sg:city":"Roma",
    "sg:orig_category":"Prodotti Alimentari",
    "sg:phone":"+39 06 513 3697",
    "sg:postcode":"00154",
    "sg:province":"Roma",
    "wof:name":"Alluvion Maurizio",
    "wof:placetype":"venue"
},
  "geometry": {"coordinates":[12.491985321,41.8644599915],"type":"Point"}
}