{
  "type": "Feature",
  "properties": {
    "addr:full":"50051 Cambiano Cambiano Firenze 50051",
    "addr:postcode":"50051;50051",
    "iso:country":"IT",
    "sg:address":"50051 Cambiano",
    "sg:city":"Cambiano",
    "sg:orig_category":"Macchine Utensili E Impianti",
    "sg:phone":"+39 0571 672225",
    "sg:postcode":"50051",
    "sg:province":"Firenze",
    "wof:name":"Mec System",
    "wof:placetype":"venue"
},
  "geometry": {"coordinates":[10.961851,43.625954],"type":"Point"}
}