{
  "type": "Feature",
  "properties": {
    "iso:country":"IT",
    "sg:address":"96100 Siracusa",
    "sg:city":"Siracusa",
    "sg:orig_category":"Legatorie",
    "sg:phone":"+39 0931 32647",
    "sg:postcode":"96100",
    "sg:province":"Siracusa",
    "wof:name":"Grafopress Di Federico Gianfranco",
    "wof:placetype":"venue"
},
  "geometry": {"coordinates":[15.293099,37.084251],"type":"Point"}
}