{
  "type": "Feature",
  "properties": {
    "addr:full":"61040 Sant'ippolito Pesaro E Urbino 61040",
    "addr:postcode":"61040;61040",
    "iso:country":"IT",
    "sg:address":"61040 Sant'ippolito",
    "sg:orig_category":"Apparecchiature Ed Attrezzature Meccaniche",
    "sg:phone":"+39 0721 749218",
    "sg:postcode":"61040",
    "sg:province":"Pesaro E Urbino",
    "wof:name":"Iron Win Srl",
    "wof:placetype":"venue"
},
  "geometry": {"coordinates":[12.877865,43.702522],"type":"Point"}
}