{
  "type": "Feature",
  "properties": {
    "iso:country":"IT",
    "sg:address":"25017 Lonato",
    "sg:city":"Lonato",
    "sg:classifiers":[
        {
            "category":"Government",
            "subcategory":"Office",
            "type":"Public Place"
        }
    ],
    "sg:phone":"+39 030 991 3397",
    "sg:postcode":"25017",
    "sg:province":"Brescia",
    "sg:tags":[
        "e",
        "lo",
        "tempo",
        "libero",
        "per",
        "spettacolo",
        "servizi",
        "culturali",
        "sport",
        "il"
    ],
    "wof:name":"Corpo Musicale Di Lonato",
    "wof:placetype":"venue"
},
  "geometry": {"coordinates":[10.197135,45.563038],"type":"Point"}
}