{
  "type": "Feature",
  "properties": {
    "iso:country":"IT",
    "sg:address":"36051 Creazzo",
    "sg:city":"Creazzo",
    "sg:orig_category":"Macchine Utensili E Impianti",
    "sg:phone":"+39 0444 520992",
    "sg:postcode":"36051",
    "sg:province":"Vicenza",
    "wof:name":"Rigoni Macchine Utensili (s.r.l.)",
    "wof:placetype":"venue"
},
  "geometry": {"coordinates":[11.488617,45.523777],"type":"Point"}
}