{
  "type": "Feature",
  "properties": {
    "iso:country":"IT",
    "sg:address":"37023 Grezzana",
    "sg:city":"Grezzana",
    "sg:orig_category":"Marmo, Pietre Ed Affini",
    "sg:phone":"+39 045 880 1033",
    "sg:postcode":"37023",
    "sg:province":"Verona",
    "sg:website":"http://www.idealmarmi.it",
    "wof:name":"Idealmarmi Srl",
    "wof:placetype":"venue"
},
  "geometry": {"coordinates":[10.992179,45.57526],"type":"Point"}
}