{
  "type": "Feature",
  "properties": {
    "addr:full":"29/31, Via Primo Maggio 25035 Ospitaletto Ospitaletto Brescia 25035",
    "addr:housenumber":"29 / 31",
    "addr:postcode":"25035;25035",
    "addr:street":"Via Primo Maggio",
    "iso:country":"IT",
    "sg:address":"29/31, Via Primo Maggio 25035 Ospitaletto",
    "sg:city":"Ospitaletto",
    "sg:classifiers":[
        {
            "category":"Manufacturing",
            "subcategory":"Rubber & Plastics",
            "type":"Manufacturing & Wholesale Goods"
        }
    ],
    "sg:phone":"+39 030 684 0777",
    "sg:postcode":"25035",
    "sg:province":"Brescia",
    "wof:name":"Flontech S.r.l.",
    "wof:placetype":"venue"
},
  "geometry": {"coordinates":[10.1132907867,45.557674408],"type":"Point"}
}