{
  "type": "Feature",
  "properties": {
    "iso:country":"IT",
    "sg:address":"10156 Torino",
    "sg:city":"Torino",
    "sg:orig_category":"Professionisti - Studi E Servizi Ed Associazioni Di Interesse Aziendale. Servizi Sociali. Associazioni Ed Organismi Di Interesse Pubblico",
    "sg:phone":"+39 011 262 9067",
    "sg:postcode":"10156",
    "sg:province":"Torino",
    "wof:name":"P.a.d.o.",
    "wof:placetype":"venue"
},
  "geometry": {"coordinates":[7.7056131363,45.1159896851],"type":"Point"}
}