{
  "type": "Feature",
  "properties": {
    "addr:full":"46, Via Pasubio 36033 Isola Vicentina Isola Vicentina Vicenza 36033",
    "addr:postcode":"36033;36033",
    "addr:street":"Via Pasubio",
    "iso:country":"IT",
    "sg:address":"46, Via Pasubio 36033 Isola Vicentina",
    "sg:city":"Isola Vicentina",
    "sg:classifiers":[
        {
            "category":"Professional",
            "subcategory":"Engineering",
            "type":"Services"
        }
    ],
    "sg:phone":"+39 0444 976111",
    "sg:postcode":"36033",
    "sg:province":"Vicenza",
    "sg:tags":[
        "machine",
        "-",
        "mechanical"
    ],
    "wof:name":"S.a.i.d. S.p.a.",
    "wof:placetype":"venue"
},
  "geometry": {"coordinates":[11.542342,45.6408],"type":"Point"}
}