{
  "type": "Feature",
  "properties": {
    "addr:full":"4/a, Zona Commerciale 38027 Male' Trento 38027",
    "addr:housenumber":"4 / a",
    "addr:postcode":"38027;38027",
    "addr:street":"Zona Commerciale;Male ' Trento",
    "iso:country":"IT",
    "sg:address":"4/a, Zona Commerciale 38027 Male'",
    "sg:classifiers":[
        {
            "category":"Professional",
            "subcategory":"Printing & Photocopies",
            "type":"Services"
        }
    ],
    "sg:phone":"+39 0463 902098",
    "sg:postcode":"38027",
    "sg:province":"Trento",
    "wof:name":"Tipolitografia Andreis S.n.c.",
    "wof:placetype":"venue"
},
  "geometry": {"coordinates":[10.9086046219,46.3481712341],"type":"Point"}
}