{
  "type": "Feature",
  "properties": {
    "iso:country":"IT",
    "sg:address":"95127 Catania",
    "sg:city":"Catania",
    "sg:orig_category":"Edilizia - Materiali",
    "sg:phone":"+39 095 377002",
    "sg:postcode":"95127",
    "sg:province":"Catania",
    "wof:name":"Bricolor Sas",
    "wof:placetype":"venue"
},
  "geometry": {"coordinates":[15.104337,37.519112],"type":"Point"}
}