{
  "type": "Feature",
  "properties": {
    "iso:country":"IT",
    "sg:address":"32, Via Vanderia 36040 Sarego",
    "sg:city":"Sarego",
    "sg:classifiers":[
        {
            "category":"Manufacturing",
            "subcategory":"Textiles",
            "type":"Manufacturing & Wholesale Goods"
        }
    ],
    "sg:phone":"+39 0444 820699",
    "sg:postcode":"36040",
    "sg:province":"Vicenza",
    "sg:tags":[
        "leather",
        "raw",
        "material",
        "-"
    ],
    "wof:name":"Rifinpell",
    "wof:placetype":"venue"
},
  "geometry": {"coordinates":[11.416471,45.432594],"type":"Point"}
}