{
  "type": "Feature",
  "properties": {
    "iso:country":"IT",
    "sg:address":"Vle Delle Industrie 9 35010 Villafranca Padovana",
    "sg:city":"Villafranca Padovana",
    "sg:classifiers":[
        {
            "category":"Manufacturing",
            "subcategory":"Motor Vehicles & Parts",
            "type":"Manufacturing & Wholesale Goods"
        }
    ],
    "sg:phone":"+39 049 907 0422",
    "sg:postcode":"35010",
    "sg:province":"Padova",
    "sg:tags":[
        "pulley",
        "belt"
    ],
    "sg:website":"www.tic-roulunds.com",
    "wof:name":"T.i.c. Roulunds (italia) - Spa",
    "wof:placetype":"venue"
},
  "geometry": {"coordinates":[11.845468,45.47472],"type":"Point"}
}