{
  "type": "Feature",
  "properties": {
    "iso:country":"IT",
    "sg:address":"17047 Vado Ligure",
    "sg:city":"Vado Ligure",
    "sg:orig_category":"Macchine, Impianti Ed Attrezzature Per Industria Alimentare E Bevande",
    "sg:phone":"+39 019 883732",
    "sg:postcode":"17047",
    "sg:province":"Savona",
    "sg:website":"http://www.salvisas.com",
    "wof:name":"Salvi Sas",
    "wof:placetype":"venue"
},
  "geometry": {"coordinates":[8.410193,44.25983],"type":"Point"}
}