{
  "type": "Feature",
  "properties": {
    "iso:country":"IT",
    "sg:address":"10015 Ivrea",
    "sg:city":"Ivrea",
    "sg:orig_category":"Banche E Servizi Finanziari",
    "sg:phone":"+39 0125 45845",
    "sg:postcode":"10015",
    "sg:province":"Torino",
    "wof:name":"Nuovi Investimenti (s.p.a.)",
    "wof:placetype":"venue"
},
  "geometry": {"coordinates":[7.679604,45.100269],"type":"Point"}
}