{
  "type": "Feature",
  "properties": {
    "iso:country":"IT",
    "sg:address":"Via Marconi 1, 10030 Vische, No",
    "sg:city":"Vische",
    "sg:classifiers":[
        {
            "category":"Banks & Credit Unions",
            "subcategory":"Bank",
            "type":"Services"
        }
    ],
    "sg:postcode":"10030",
    "sg:province":"Torino",
    "wof:name":"Credito Cooperativo Cassa Rurale Artigiano Di Vische Scarl",
    "wof:placetype":"venue"
},
  "geometry": {"coordinates":[7.951108,45.333504],"type":"Point"}
}