{
  "type": "Feature",
  "properties": {
    "iso:country":"IT",
    "sg:address":"25125 Brescia",
    "sg:city":"Brescia",
    "sg:orig_category":"Cartiere - Macchine",
    "sg:phone":"+39 030 358 3340",
    "sg:postcode":"25125",
    "sg:province":"Brescia",
    "sg:website":"http://www.petrofer.com",
    "wof:name":"Petrofer Italia Srl",
    "wof:placetype":"venue"
},
  "geometry": {"coordinates":[10.162615,45.508404],"type":"Point"}
}