{
  "type": "Feature",
  "properties": {
    "iso:country":"IT",
    "sg:address":"Via Stabbio 3 54033 Carrara",
    "sg:city":"Carrara",
    "sg:classifiers":[
        {
            "category":"Home & Garden",
            "subcategory":"Building Materials",
            "type":"Retail Goods"
        }
    ],
    "sg:phone":"+39 0585 844710",
    "sg:postcode":"54033",
    "sg:province":"Massa-Carrara",
    "sg:tags":[
        "slab",
        "marble"
    ],
    "wof:name":"Peghini Marmi Srl",
    "wof:placetype":"venue"
},
  "geometry": {"coordinates":[10.088034,44.071949],"type":"Point"}
}