{
  "type": "Feature",
  "properties": {
    "iso:country":"IT",
    "sg:address":"83100 Avellino",
    "sg:city":"Avellino",
    "sg:orig_category":"Articoli Da Regalo. Regalistica Aziendale",
    "sg:phone":"+39 0825 37097",
    "sg:postcode":"83100",
    "sg:province":"Avellino",
    "wof:name":"Stil Casa Di Aniello Iovino",
    "wof:placetype":"venue"
},
  "geometry": {"coordinates":[14.798132,40.906746],"type":"Point"}
}