{
  "type": "Feature",
  "properties": {
    "addr:full":"23848 Oggiono Oggiono Lecco 23848",
    "addr:postcode":"23848;23848",
    "iso:country":"IT",
    "sg:address":"23848 Oggiono",
    "sg:city":"Oggiono",
    "sg:orig_category":"Carni, Salumi E Pesci",
    "sg:phone":"+39 0341 576133",
    "sg:postcode":"23848",
    "sg:province":"Lecco",
    "wof:name":"Ratti Battista Sas Super Macelleria Ratti",
    "wof:placetype":"venue"
},
  "geometry": {"coordinates":[9.395772,45.85923],"type":"Point"}
}