{
  "type": "Feature",
  "properties": {
    "addr:full":"86100 Campobasso Campobasso Campobasso 86100",
    "addr:postcode":"86100;86100",
    "iso:country":"IT",
    "sg:address":"86100 Campobasso",
    "sg:city":"Campobasso",
    "sg:orig_category":"Macchine, Impianti Ed Attrezzature Per Abbigliamento E Pelletterie",
    "sg:phone":"+39 0874 92987",
    "sg:postcode":"86100",
    "sg:province":"Campobasso",
    "wof:name":"Emanuele Domenico",
    "wof:placetype":"venue"
},
  "geometry": {"coordinates":[14.670443,41.577084],"type":"Point"}
}