{
  "type": "Feature",
  "properties": {
    "addr:full":"20143 Milano Milano Milano 20143",
    "addr:postcode":"20143;20143",
    "iso:country":"IT",
    "sg:address":"20143 Milano",
    "sg:city":"Milano",
    "sg:orig_category":"Macchine Utensili E Impianti",
    "sg:phone":"+39 02 5810 4276",
    "sg:postcode":"20143",
    "sg:province":"Milano",
    "wof:name":"Nazarri Giuseppe",
    "wof:placetype":"venue"
},
  "geometry": {"coordinates":[9.163582,45.446804],"type":"Point"}
}