{
  "type": "Feature",
  "properties": {
    "iso:country":"IT",
    "sg:address":"20, V. Meucci - Seano 59015 Carmignano",
    "sg:city":"Carmignano",
    "sg:classifiers":[
        {
            "category":"Professional",
            "subcategory":"Engineering",
            "type":"Services"
        }
    ],
    "sg:phone":"+39 055 870 5177",
    "sg:postcode":"59015",
    "sg:province":"Prato",
    "sg:tags":[
        "machine",
        "-",
        "mechanical"
    ],
    "sg:website":"http://www.paginegialle.it/promecsas",
    "wof:name":"Promec Sas",
    "wof:placetype":"venue"
},
  "geometry": {"coordinates":[11.035234,43.834011],"type":"Point"}
}