{
  "type": "Feature",
  "properties": {
    "addr:full":"20090 Cusago Cusago Milano 20090",
    "addr:postcode":"20090;20090",
    "iso:country":"IT",
    "sg:address":"20090 Cusago",
    "sg:city":"Cusago",
    "sg:orig_category":"Forniture Per Attivita' Industriali",
    "sg:phone":"+39 02 9011 9649",
    "sg:postcode":"20090",
    "sg:province":"Milano",
    "wof:name":"Marchesi Srl",
    "wof:placetype":"venue"
},
  "geometry": {"coordinates":[9.0809679031,45.4607963562],"type":"Point"}
}