{
  "type": "Feature",
  "properties": {
    "iso:country":"IT",
    "sg:address":"16123 Genova",
    "sg:city":"Genova",
    "sg:orig_category":"Coperte E Copriletti",
    "sg:phone":"+39 010 247 3252",
    "sg:postcode":"16123",
    "sg:province":"Genova",
    "wof:name":"Rivara Giovanni Di Luigi Rivara & C. Snc",
    "wof:placetype":"venue"
},
  "geometry": {"coordinates":[9.295796,44.352036],"type":"Point"}
}