{
  "type": "Feature",
  "properties": {
    "addr:full":"29/d, Via Oberdan Guglielmo 25128 Brescia Brescia Brescia 25128",
    "addr:housenumber":"29 / d",
    "addr:postcode":"25128;25128",
    "addr:street":"Via Oberdan Guglielmo",
    "iso:country":"IT",
    "sg:address":"29/d, Via Oberdan Guglielmo 25128 Brescia",
    "sg:city":"Brescia",
    "sg:classifiers":[
        {
            "category":"Autos & Motor Vehicles",
            "subcategory":"Automobile Sales",
            "type":"Retail Goods"
        }
    ],
    "sg:phone":"+39 030 370 0322",
    "sg:postcode":"25128",
    "sg:province":"Brescia",
    "sg:tags":[
        "industrial"
    ],
    "wof:name":"Autobase (s.r.l.)",
    "wof:placetype":"venue"
},
  "geometry": {"coordinates":[10.222958,45.539829],"type":"Point"}
}