{
  "type": "Feature",
  "properties": {
    "iso:country":"IT",
    "sg:address":"24022 Alzano Lombardo",
    "sg:city":"Alzano Lombardo",
    "sg:orig_category":"Agenzie Immobiliari",
    "sg:phone":"+39 035 512202",
    "sg:postcode":"24022",
    "sg:province":"Bergamo",
    "sg:website":"http://www.cs.pccom.it/ediltironi",
    "wof:name":"Ediltironi Srl",
    "wof:placetype":"venue"
},
  "geometry": {"coordinates":[9.715855,45.749657],"type":"Point"}
}