{
  "type": "Feature",
  "properties": {
    "iso:country":"IT",
    "sg:address":"Via Dell'artigiano 4 40065 Pianoro",
    "sg:city":"Pianoro",
    "sg:orig_category":"Foam Products, Customized",
    "sg:phone":"+39 051 774694",
    "sg:postcode":"40065",
    "sg:province":"Bologna",
    "wof:name":"Resinplast Di Paccaloni Ing. Antonio & C. Snc",
    "wof:placetype":"venue"
},
  "geometry": {"coordinates":[11.3431091309,44.3953971863],"type":"Point"}
}