{
  "type": "Feature",
  "properties": {
    "iso:country":"IT",
    "sg:address":"74100 Taranto",
    "sg:city":"Taranto",
    "sg:orig_category":"Arredamenti E Mobili Professionali. Arredi Ed Attrezzature Per Uffici",
    "sg:phone":"+39 099 452 6618",
    "sg:postcode":"74100",
    "sg:province":"Taranto",
    "wof:name":"Boccardi Arredamenti Srl",
    "wof:placetype":"venue"
},
  "geometry": {"coordinates":[17.247841,40.471592],"type":"Point"}
}