{
  "type": "Feature",
  "properties": {
    "iso:country":"IT",
    "sg:address":"135, Via Volturno 20047 Brugherio",
    "sg:city":"Brugherio",
    "sg:classifiers":[
        {
            "category":"Shopping",
            "subcategory":"Computers & Home Electronics",
            "type":"Retail Goods"
        }
    ],
    "sg:phone":"+39 039 287 2103",
    "sg:postcode":"20047",
    "sg:province":"Milano",
    "sg:tags":[
        "electronic",
        "electrical",
        "equipment"
    ],
    "wof:name":"F.i.d.a. Fabbrica Italiana Distributori Automatici",
    "wof:placetype":"venue"
},
  "geometry": {"coordinates":[9.298677,45.542557],"type":"Point"}
}