{
  "type": "Feature",
  "properties": {
    "addr:full":"Via Papaniciaro 88900 Crotone Crotone Crotone 88900",
    "addr:postcode":"88900;88900",
    "addr:street":"Via Papaniciaro",
    "iso:country":"IT",
    "sg:address":"Via Papaniciaro 88900 Crotone",
    "sg:city":"Crotone",
    "sg:classifiers":[
        {
            "category":"Manufacturing",
            "subcategory":"Lumber",
            "type":"Manufacturing & Wholesale Goods"
        }
    ],
    "sg:phone":"+39 39096227330",
    "sg:postcode":"88900",
    "sg:province":"Crotone",
    "sg:tags":[
        "wood"
    ],
    "wof:name":"Ceraudo Vincenzo & C. S.a.s.",
    "wof:placetype":"venue"
},
  "geometry": {"coordinates":[17.127079,39.080738],"type":"Point"}
}