{
  "type": "Feature",
  "properties": {
    "addr:full":"Viale Risorgimento 11 10092 Beinasco Beinasco Torino 10092",
    "addr:housenumber":"11",
    "addr:postcode":"10092;10092",
    "addr:street":"Viale Risorgimento",
    "iso:country":"IT",
    "sg:address":"Viale Risorgimento 11 10092 Beinasco",
    "sg:city":"Beinasco",
    "sg:classifiers":[
        {
            "category":"Professional",
            "subcategory":"Printing & Photocopies",
            "type":"Services"
        }
    ],
    "sg:phone":"+39 011 349 8658",
    "sg:postcode":"10092",
    "sg:province":"Torino",
    "sg:tags":[
        "job"
    ],
    "wof:name":"A.g.i.t. Azienda Grafica Il Torchio Torchio Srl",
    "wof:placetype":"venue"
},
  "geometry": {"coordinates":[7.587389,45.0275],"type":"Point"}
}