{
  "type": "Feature",
  "properties": {
    "iso:country":"IT",
    "sg:address":"04011 Aprilia",
    "sg:city":"Aprilia",
    "sg:orig_category":"Autoclavi",
    "sg:phone":"+39 06 925 2183",
    "sg:postcode":"04011",
    "sg:province":"Latina",
    "wof:name":"Co.el. Srl",
    "wof:placetype":"venue"
},
  "geometry": {"coordinates":[12.569884,41.591694],"type":"Point"}
}