{
  "type": "Feature",
  "properties": {
    "iso:country":"IT",
    "sg:address":"20037 Paderno Dugnano",
    "sg:city":"Paderno Dugnano",
    "sg:orig_category":"Acciaierie E Fonderie",
    "sg:phone":"+39 02 9904 5093",
    "sg:postcode":"20037",
    "sg:province":"Milano",
    "wof:name":"Pastorelli Walter",
    "wof:placetype":"venue"
},
  "geometry": {"coordinates":[9.139124,45.57143],"type":"Point"}
}