{
  "type": "Feature",
  "properties": {
    "iso:country":"IT",
    "sg:address":"66050 San Salvo",
    "sg:city":"San Salvo",
    "sg:orig_category":"Servizi E Lavori Per Agricoltura E Zootecnia. Servizi E Lavori Industria Chimica. Servizi Ausiliari Di Analisi, Controllo E Ricerca",
    "sg:phone":"+39 0873 346153",
    "sg:postcode":"66050",
    "sg:province":"Chieti",
    "wof:name":"Eurovix Srl",
    "wof:placetype":"venue"
},
  "geometry": {"coordinates":[14.740611,42.049095],"type":"Point"}
}