{
  "type": "Feature",
  "properties": {
    "addr:full":"20131 Milano Milano Milano 20131",
    "addr:postcode":"20131;20131",
    "iso:country":"IT",
    "sg:address":"20131 Milano",
    "sg:city":"Milano",
    "sg:orig_category":"Servizi Per Lo Sport E Il Tempo Libero. Servizi Al Turismo",
    "sg:phone":"+39 02 2611 1950",
    "sg:postcode":"20131",
    "sg:province":"Milano",
    "wof:name":"A.s. Cristal Club",
    "wof:placetype":"venue"
},
  "geometry": {"coordinates":[9.226433,45.487846],"type":"Point"}
}