{
  "type": "Feature",
  "properties": {
    "addr:full":"77, Via Grande 36022 Cassola Cassola Vicenza 36022",
    "addr:postcode":"36022;36022",
    "addr:street":"Via Grande",
    "iso:country":"IT",
    "sg:address":"77, Via Grande 36022 Cassola",
    "sg:city":"Cassola",
    "sg:classifiers":[
        {
            "category":"Manufacturing",
            "subcategory":"Paper Products",
            "type":"Manufacturing & Wholesale Goods"
        }
    ],
    "sg:phone":"+39 0424 533472",
    "sg:postcode":"36022",
    "sg:province":"Vicenza",
    "sg:tags":[
        "cardboard"
    ],
    "wof:name":"Scatolificio Bassanese (s.n.c.)",
    "wof:placetype":"venue"
},
  "geometry": {"coordinates":[11.7882633209,45.7391204834],"type":"Point"}
}