{
  "type": "Feature",
  "properties": {
    "iso:country":"IT",
    "sg:address":"33170 Pordenone",
    "sg:city":"Pordenone",
    "sg:classifiers":[
        {
            "category":"Manufacturing",
            "subcategory":"Tobacco Products",
            "type":"Manufacturing & Wholesale Goods"
        }
    ],
    "sg:phone":"+39 0434 571556",
    "sg:postcode":"33170",
    "sg:province":"Pordenone",
    "sg:tags":[
        "activities",
        "refuse",
        "industrial",
        "supply",
        "disposal",
        "environmental",
        "chemicals",
        "protection",
        "products",
        "machinery",
        "supplies",
        "secondary"
    ],
    "sg:website":"http://www.convasscommerciale.com",
    "wof:name":"Canvass Commerciale Srl",
    "wof:placetype":"venue"
},
  "geometry": {"coordinates":[12.62553,45.967781],"type":"Point"}
}