{
  "type": "Feature",
  "properties": {
    "iso:country":"IT",
    "sg:address":"10135 Torino",
    "sg:city":"Torino",
    "sg:orig_category":"Macchine Utensili E Impianti",
    "sg:phone":"+39 011 619 9510",
    "sg:postcode":"10135",
    "sg:province":"Torino",
    "wof:name":"Canalis Sas Di Canalis V. & C.",
    "wof:placetype":"venue"
},
  "geometry": {"coordinates":[7.646148,45.022556],"type":"Point"}
}