{
  "type": "Feature",
  "properties": {
    "iso:country":"IT",
    "sg:address":"53042 Chianciano Terme",
    "sg:city":"Chianciano Terme",
    "sg:orig_category":"Alberghi",
    "sg:phone":"+39 0578 63638",
    "sg:postcode":"53042",
    "sg:province":"Siena",
    "wof:name":"Albergo Luana",
    "wof:placetype":"venue"
},
  "geometry": {"coordinates":[11.821372,43.053829],"type":"Point"}
}