{
  "type": "Feature",
  "properties": {
    "iso:country":"IT",
    "sg:address":"6, Via Martiri Della Liberta' 35010 Grantorto",
    "sg:city":"Grantorto",
    "sg:classifiers":[
        {
            "category":"Manufacturing",
            "subcategory":"Rubber & Plastics",
            "type":"Manufacturing & Wholesale Goods"
        }
    ],
    "sg:phone":"+39 049 949 0411",
    "sg:postcode":"35010",
    "sg:province":"Padova",
    "wof:name":"Geoplast Srl",
    "wof:placetype":"venue"
},
  "geometry": {"coordinates":[11.7320041656,45.6065444946],"type":"Point"}
}