{
  "type": "Feature",
  "properties": {
    "iso:country":"IT",
    "sg:address":"Via Seminario 34 23900 Lecco",
    "sg:city":"Lecco",
    "sg:orig_category":"Shrink Wrap Lines For Palletless Packaging",
    "sg:phone":"+39 0341 251100",
    "sg:postcode":"23900",
    "sg:province":"Lecco",
    "sg:website":"www.cortidomenico.it",
    "wof:name":"Corti Domenico Srl",
    "wof:placetype":"venue"
},
  "geometry": {"coordinates":[9.395229,45.863567],"type":"Point"}
}