{
  "type": "Feature",
  "properties": {
    "addr:full":"22060 Carimate Carimate Como 22060",
    "addr:postcode":"22060;22060",
    "iso:country":"IT",
    "sg:address":"22060 Carimate",
    "sg:city":"Carimate",
    "sg:orig_category":"Forniture Per Edilizia E Lavori Pubblici",
    "sg:phone":"+39 031 790594",
    "sg:postcode":"22060",
    "sg:province":"Como",
    "wof:name":"2b Di Bosaglia R.e.f. Snc Tinteggiature",
    "wof:placetype":"venue"
},
  "geometry": {"coordinates":[9.1142473221,45.7513275146],"type":"Point"}
}