{
  "type": "Feature",
  "properties": {
    "addr:full":"20030 Bovisio Masciago Bovisio Milano 20030",
    "addr:postcode":"20030;20030",
    "iso:country":"IT",
    "sg:address":"20030 Bovisio Masciago",
    "sg:city":"Bovisio",
    "sg:orig_category":"Forniture Per Edilizia E Lavori Pubblici",
    "sg:phone":"+39 036 259 5022",
    "sg:postcode":"20030",
    "sg:province":"Milano",
    "wof:name":"Corbetta Paolo",
    "wof:placetype":"venue"
},
  "geometry": {"coordinates":[9.1534490585,45.6108283997],"type":"Point"}
}