{
  "type": "Feature",
  "properties": {
    "iso:country":"IT",
    "sg:address":"27058 Voghera",
    "sg:city":"Voghera",
    "sg:orig_category":"Abbigliamento Esterno, Maglierie E Pelliccerie. Calzature, Pelletterie E Pelli. Sport - Articoli E Forniture",
    "sg:phone":"+39 0383 213445",
    "sg:postcode":"27058",
    "sg:province":"Pavia",
    "wof:name":"Pelletteria Chiaril\u00da Di Rita Crisci",
    "wof:placetype":"venue"
},
  "geometry": {"coordinates":[9.011885,44.999912],"type":"Point"}
}