{
  "type": "Feature",
  "properties": {
    "iso:country":"IT",
    "sg:address":"74100 Taranto",
    "sg:city":"Taranto",
    "sg:orig_category":"Petroli, Gas E Combustibili. Materiali Edili",
    "sg:phone":"+39 099 471 8071",
    "sg:postcode":"74100",
    "sg:province":"Taranto",
    "wof:name":"Del Prete Salvatore",
    "wof:placetype":"venue"
},
  "geometry": {"coordinates":[17.2270240784,40.4907035828],"type":"Point"}
}