{
  "type": "Feature",
  "properties": {
    "addr:full":"17, Via Xxv Aprile 21014 Laveno Mombello Laveno Varese 21014",
    "addr:postcode":"21014;21014",
    "addr:street":"Via Xxv Aprile",
    "iso:country":"IT",
    "sg:address":"17, Via Xxv Aprile 21014 Laveno Mombello",
    "sg:city":"Laveno",
    "sg:classifiers":[
        {
            "category":"Utilities",
            "subcategory":"Electric",
            "type":"Services"
        }
    ],
    "sg:phone":"+39 0332 668011",
    "sg:postcode":"21014",
    "sg:province":"Varese",
    "sg:tags":[
        "component",
        "electronic"
    ],
    "wof:name":"Meba (s.r.l.)",
    "wof:placetype":"venue"
},
  "geometry": {"coordinates":[8.826385,45.817604],"type":"Point"}
}