{
  "type": "Feature",
  "properties": {
    "iso:country":"IT",
    "sg:address":"22063 Cantu'",
    "sg:orig_category":"Abbigliamento Esterno, Maglierie E Pelliccerie",
    "sg:phone":"+39 031 715723",
    "sg:postcode":"22063",
    "sg:province":"Como",
    "wof:name":"Abbigliamento Free World Fashion",
    "wof:placetype":"venue"
},
  "geometry": {"coordinates":[9.127103,45.730709],"type":"Point"}
}