{
  "type": "Feature",
  "properties": {
    "iso:country":"IT",
    "sg:address":"10067 Vigone",
    "sg:city":"Vigone",
    "sg:orig_category":"Bruciatori Nafta, Gasolio E Kerosene - Installazione E Manutenzione",
    "sg:phone":"+39 011 980 9929",
    "sg:postcode":"10067",
    "sg:province":"Torino",
    "wof:name":"Trecca Gas",
    "wof:placetype":"venue"
},
  "geometry": {"coordinates":[8.064578,45.150867],"type":"Point"}
}