{
  "type": "Feature",
  "properties": {
    "iso:country":"IT",
    "sg:address":"78, Via S. Anna 20047 Brugherio",
    "sg:city":"Brugherio",
    "sg:classifiers":[
        {
            "category":"Manufacturing",
            "subcategory":"Metals",
            "type":"Manufacturing & Wholesale Goods"
        }
    ],
    "sg:phone":"+39 039 202 4362",
    "sg:postcode":"20047",
    "sg:province":"Milano",
    "sg:tags":[
        "metallurgy",
        "metalworking"
    ],
    "wof:name":"Lanzetta Aldo S.r.l.",
    "wof:placetype":"venue"
},
  "geometry": {"coordinates":[9.283498764,45.5145187378],"type":"Point"}
}