{
  "type": "Feature",
  "properties": {
    "addr:full":"154, Via Bonellina 51100 Pistoia Pistoia Pistoia 51100",
    "addr:housenumber":"154",
    "addr:postcode":"51100;51100",
    "addr:street":"Via Bonellina",
    "iso:country":"IT",
    "sg:address":"154, Via Bonellina 51100 Pistoia",
    "sg:city":"Pistoia",
    "sg:classifiers":[
        {
            "category":"Food & Beverages",
            "subcategory":"Groceries & Convenience Stores",
            "type":"Retail Goods"
        }
    ],
    "sg:phone":"+39 0573 380430",
    "sg:postcode":"51100",
    "sg:province":"Pistoia",
    "sg:tags":[
        "product",
        "related"
    ],
    "wof:name":"Pastificio Palandri S.r.l.",
    "wof:placetype":"venue"
},
  "geometry": {"coordinates":[10.9180297852,43.9175605774],"type":"Point"}
}