{
  "type": "Feature",
  "properties": {
    "addr:full":"22072 Cermenate Cermenate Como 22072",
    "addr:postcode":"22072;22072",
    "iso:country":"IT",
    "sg:address":"22072 Cermenate",
    "sg:city":"Cermenate",
    "sg:orig_category":"Trattamenti Termici E Superficiali Metalli, Galvanotecnica",
    "sg:phone":"+39 031 722444",
    "sg:postcode":"22072",
    "sg:province":"Como",
    "wof:name":"Lgf Di La Gala Franco & C. Srl",
    "wof:placetype":"venue"
},
  "geometry": {"coordinates":[9.080228,45.713806],"type":"Point"}
}