{
  "type": "Feature",
  "properties": {
    "iso:country":"IT",
    "sg:address":"20082 Binasco",
    "sg:city":"Binasco",
    "sg:classifiers":[
        {
            "category":"Travel",
            "subcategory":"Hotels & Motels",
            "type":"Entertainment"
        }
    ],
    "sg:phone":"+39 02 905 2606",
    "sg:postcode":"20082",
    "sg:province":"Milano",
    "sg:tags":[
        "hotels",
        "facility"
    ],
    "wof:name":"Motel Visconteo Srl",
    "wof:placetype":"venue"
},
  "geometry": {"coordinates":[9.344178,44.306465],"type":"Point"}
}