{
  "type": "Feature",
  "properties": {
    "iso:country":"IT",
    "sg:address":"Via Mameli; Pesaro; 61100",
    "sg:city":"Pesaro",
    "sg:classifiers":[
        {
            "category":"Banks & Credit Unions",
            "subcategory":"Bank",
            "type":"Services"
        }
    ],
    "sg:phone":"+39 0721 3811",
    "sg:postcode":"61100",
    "sg:province":"Pesaro E Urbino",
    "wof:name":"Banca Nazionale Del Lavoro Spa",
    "wof:placetype":"venue"
},
  "geometry": {"coordinates":[12.904784,43.912292],"type":"Point"}
}