{
  "type": "Feature",
  "properties": {
    "iso:country":"IT",
    "sg:address":"52100 Arezzo",
    "sg:city":"Arezzo",
    "sg:orig_category":"Trattamenti Termici E Superficiali Metalli, Galvanotecnica",
    "sg:phone":"+39 0575 966401",
    "sg:postcode":"52100",
    "sg:province":"Arezzo",
    "wof:name":"K.m. Preziosi (s.n.c.)",
    "wof:placetype":"venue"
},
  "geometry": {"coordinates":[11.877588,43.461899],"type":"Point"}
}