{
  "type": "Feature",
  "properties": {
    "addr:full":"50013 Campi Bisenzio Campi Bisenzio Firenze 50013",
    "addr:postcode":"50013;50013",
    "addr:street":"Bisenzio",
    "iso:country":"IT",
    "sg:address":"50013 Campi Bisenzio",
    "sg:city":"Campi Bisenzio",
    "sg:orig_category":"Materiali Semilavorati Metallici",
    "sg:phone":"+39 055 897 9516",
    "sg:postcode":"50013",
    "sg:province":"Firenze",
    "wof:name":"Centro Nastri Service Di Filie' Massimo & C. Snc",
    "wof:placetype":"venue"
},
  "geometry": {"coordinates":[11.195154,43.839851],"type":"Point"}
}