{
  "type": "Feature",
  "properties": {
    "iso:country":"IT",
    "sg:address":"24020 Torre Boldone",
    "sg:city":"Torre Boldone",
    "sg:orig_category":"Legno E Semilavorati. Articoli Per Imballaggio E Confezionamento",
    "sg:phone":"+39 035 340041",
    "sg:postcode":"24020",
    "sg:province":"Bergamo",
    "wof:name":"Arnoldi Angelo Snc Di Mauro Arnoldi Gherardi & C.",
    "wof:placetype":"venue"
},
  "geometry": {"coordinates":[9.710078,45.717865],"type":"Point"}
}