{
  "type": "Feature",
  "properties": {
    "addr:full":"20014 Nerviano Nerviano Milano 20014",
    "addr:postcode":"20014;20014",
    "iso:country":"IT",
    "sg:address":"20014 Nerviano",
    "sg:city":"Nerviano",
    "sg:orig_category":"Imprese Di Costruzioni Civili Ed Industriali",
    "sg:phone":"+39 0331 534288",
    "sg:postcode":"20014",
    "sg:province":"Milano",
    "sg:website":"http://www.sarco.it",
    "wof:name":"Sarco Srl",
    "wof:placetype":"venue"
},
  "geometry": {"coordinates":[9.035059,45.527084],"type":"Point"}
}