{
  "type": "Feature",
  "properties": {
    "iso:country":"IT",
    "sg:address":"00146 Roma",
    "sg:city":"Roma",
    "sg:orig_category":"Calzature, Pelletterie E Pelli. Servizi E Lavori Per Abbigliamento E Pelletterie",
    "sg:phone":"+39 06 557 2570",
    "sg:postcode":"00146",
    "sg:province":"Roma",
    "wof:name":"Deli Elvio",
    "wof:placetype":"venue"
},
  "geometry": {"coordinates":[12.468279,41.863522],"type":"Point"}
}