{
  "type": "Feature",
  "properties": {
    "iso:country":"IT",
    "sg:address":"00175 Roma",
    "sg:city":"Roma",
    "sg:orig_category":"Scuole E Servizi Scolastici",
    "sg:phone":"+39 06 764178",
    "sg:postcode":"00175",
    "sg:province":"Roma",
    "wof:name":"Scuola 2000 Srl",
    "wof:placetype":"venue"
},
  "geometry": {"coordinates":[12.559922,41.861591],"type":"Point"}
}