{
  "type": "Feature",
  "properties": {
    "addr:full":"84096 Montecorvino Rovella Montecorvino Rovella Salerno 84096",
    "addr:postcode":"84096;84096",
    "iso:country":"IT",
    "sg:address":"84096 Montecorvino Rovella",
    "sg:city":"Montecorvino Rovella",
    "sg:orig_category":"Materiali E Componenti Elettrotecnici",
    "sg:phone":"+39 089 981758",
    "sg:postcode":"84096",
    "sg:province":"Salerno",
    "wof:name":"C.e.m. Srl",
    "wof:placetype":"venue"
},
  "geometry": {"coordinates":[14.997303,40.706905],"type":"Point"}
}