{
  "type": "Feature",
  "properties": {
    "iso:country":"IT",
    "sg:address":"41042 Fiorano Modenese",
    "sg:city":"Fiorano Modenese",
    "sg:orig_category":"Utensili Meccanici E Materiali",
    "sg:phone":"+39 0536 843915",
    "sg:postcode":"41042",
    "sg:province":"Modena",
    "wof:name":"Metalstamp Snc Dei Fratelli Canali",
    "wof:placetype":"venue"
},
  "geometry": {"coordinates":[10.853551,44.558559],"type":"Point"}
}