{
  "type": "Feature",
  "properties": {
    "addr:full":"Contrada Specchia 74011 Castellaneta Castellaneta Taranto 74011",
    "addr:postcode":"74011;74011",
    "addr:street":"Contrada Specchia",
    "iso:country":"IT",
    "sg:address":"Contrada Specchia 74011 Castellaneta",
    "sg:city":"Castellaneta",
    "sg:classifiers":[
        {
            "category":"Food & Beverages",
            "subcategory":"Groceries & Convenience Stores",
            "type":"Retail Goods"
        }
    ],
    "sg:phone":"+39 099 849 1041",
    "sg:postcode":"74011",
    "sg:province":"Taranto",
    "sg:tags":[
        "drink"
    ],
    "wof:name":"Nuova Castelvini Soc. Coop. A R.l.",
    "wof:placetype":"venue"
},
  "geometry": {"coordinates":[17.240009,40.469238],"type":"Point"}
}