{
  "type": "Feature",
  "properties": {
    "iso:country":"IT",
    "sg:address":"Via C. Colombo 23 87060 Schiavonea",
    "sg:classifiers":[
        {
            "category":"Food & Beverages",
            "subcategory":"Meat & Fish",
            "type":"Retail Goods"
        }
    ],
    "sg:phone":"+39 0983 87741",
    "sg:postcode":"87060",
    "sg:province":"Cosenza",
    "sg:tags":[
        "fresh"
    ],
    "wof:name":"Gilca Pesca Di Giugliano E Carelli",
    "wof:placetype":"venue"
},
  "geometry": {"coordinates":[16.3393611908,39.260761261],"type":"Point"}
}