{
  "type": "Feature",
  "properties": {
    "iso:country":"IT",
    "sg:address":"00193 Roma",
    "sg:city":"Roma",
    "sg:orig_category":"Ambasciate Ed Enti Internazionali",
    "sg:phone":"+39 06 687 4431",
    "sg:postcode":"00193",
    "sg:province":"Roma",
    "wof:name":"Ambasciata Del Brasile Presso La Santa Sede",
    "wof:placetype":"venue"
},
  "geometry": {"coordinates":[12.461718,41.9025],"type":"Point"}
}