{
  "type": "Feature",
  "properties": {
    "iso:country":"IT",
    "sg:address":"1, Via Mascagni Pietro 50050 Cerreto Guidi",
    "sg:city":"Cerreto Guidi",
    "sg:classifiers":[
        {
            "category":"Shopping",
            "subcategory":"Clothing, Apparel, & Fashions",
            "type":"Retail Goods"
        }
    ],
    "sg:phone":"+39 0571 580091",
    "sg:postcode":"50050",
    "sg:province":"Firenze",
    "sg:tags":[
        "clothes"
    ],
    "wof:name":"G. Quattro Srl",
    "wof:placetype":"venue"
},
  "geometry": {"coordinates":[10.780309,43.705959],"type":"Point"}
}