{
  "type": "Feature",
  "properties": {
    "iso:country":"IT",
    "sg:address":"10023 Chieri",
    "sg:city":"Chieri",
    "sg:orig_category":"Macchine, Impianti Ed Attrezzature Industria Chimica. Macchine, Strumenti Ed Apparecchi Per Attivita' Industriali",
    "sg:phone":"+39 011 942 3562",
    "sg:postcode":"10023",
    "sg:province":"Torino",
    "wof:name":"Emanueltex",
    "wof:placetype":"venue"
},
  "geometry": {"coordinates":[7.802506,45.025883],"type":"Point"}
}