{
  "type": "Feature",
  "properties": {
    "iso:country":"IT",
    "sg:address":"40068 San Lazzaro Di Savena",
    "sg:city":"San Lazzaro",
    "sg:orig_category":"Minuterie Metalliche E Ferramenta. Forniture Per Attivita' Industriali",
    "sg:phone":"+39 051 463129",
    "sg:postcode":"40068",
    "sg:province":"Bologna",
    "sg:website":"http://www.molleguidi.it",
    "wof:name":"Mollificio Guidi Srl",
    "wof:placetype":"venue"
},
  "geometry": {"coordinates":[11.4151544571,44.4756088257],"type":"Point"}
}