{
  "type": "Feature",
  "properties": {
    "iso:country":"IT",
    "sg:address":"43013 Langhirano",
    "sg:city":"Langhirano",
    "sg:orig_category":"Salumifici E Prosciuttifici",
    "sg:phone":"+39 0521 857142",
    "sg:postcode":"43013",
    "sg:province":"Parma",
    "wof:name":"Salumificio S. Rita Spa",
    "wof:placetype":"venue"
},
  "geometry": {"coordinates":[10.242001,44.693565],"type":"Point"}
}