{
  "type": "Feature",
  "properties": {
    "iso:country":"IT",
    "sg:address":"Via Emilia 340 40064 Ozzano Dell'emilia",
    "sg:classifiers":[
        {
            "category":"Building & Trades",
            "subcategory":"Pest Control",
            "type":"Services"
        }
    ],
    "sg:phone":"+39 051 799171",
    "sg:postcode":"40064",
    "sg:province":"Bologna",
    "sg:tags":[
        "chemical",
        "industry"
    ],
    "sg:website":"www.iivela.it",
    "wof:name":"Iivela Srl Impermeabilizzant I Vernici Emulsionabili Lavorazioni",
    "wof:placetype":"venue"
},
  "geometry": {"coordinates":[11.435963,44.460243],"type":"Point"}
}