{
  "type": "Feature",
  "properties": {
    "iso:country":"IT",
    "sg:address":"10, Via E. Mattei 35030 Saccolongo",
    "sg:city":"Saccolongo",
    "sg:classifiers":[
        {
            "category":"Professional",
            "subcategory":"Engineering",
            "type":"Services"
        }
    ],
    "sg:phone":"+39 049 801 5404",
    "sg:postcode":"35030",
    "sg:province":"Padova",
    "sg:tags":[
        "machine",
        "-",
        "mechanical"
    ],
    "wof:name":"Arredacciaio (s.r.l.)",
    "wof:placetype":"venue"
},
  "geometry": {"coordinates":[11.876589,45.409569],"type":"Point"}
}