{
  "type": "Feature",
  "properties": {
    "addr:full":"00176 Roma Roma Roma 00176",
    "addr:postcode":"00176;00176",
    "iso:country":"IT",
    "sg:address":"00176 Roma",
    "sg:city":"Roma",
    "sg:orig_category":"Petroli, Gas E Combustibili",
    "sg:phone":"+39 06 274074",
    "sg:postcode":"00176",
    "sg:province":"Roma",
    "wof:name":"Fratelli Ginesi Gas Compressi Sas",
    "wof:placetype":"venue"
},
  "geometry": {"coordinates":[12.6038427353,41.8660888672],"type":"Point"}
}