{
  "type": "Feature",
  "properties": {
    "addr:full":"41051 Castelnuovo Rangone Castelnuovo Rangone Modena 41051",
    "addr:postcode":"41051;41051",
    "iso:country":"IT",
    "sg:address":"41051 Castelnuovo Rangone",
    "sg:city":"Castelnuovo Rangone",
    "sg:orig_category":"Alimentari - Vendita Al Dettaglio",
    "sg:phone":"+39 059 537774",
    "sg:postcode":"41051",
    "sg:province":"Modena",
    "wof:name":"Doppiozero Sas - Forno Di Johnny",
    "wof:placetype":"venue"
},
  "geometry": {"coordinates":[10.936544,44.549953],"type":"Point"}
}