{
  "type": "Feature",
  "properties": {
    "addr:full":"Via Papa Paolo Vi 5 21040 Venegono Inferiore Venegono Inferiore Varese 21040",
    "addr:housenumber":"5",
    "addr:postcode":"21040;21040",
    "addr:street":"Via Papa Paolo Vi;Inferiore",
    "iso:country":"IT",
    "sg:address":"Via Papa Paolo Vi 5 21040 Venegono Inferiore",
    "sg:city":"Venegono Inferiore",
    "sg:classifiers":[
        {
            "category":"Structure",
            "subcategory":"Tunnel",
            "type":"Public Place"
        }
    ],
    "sg:phone":"+39 0331 827717",
    "sg:postcode":"21040",
    "sg:province":"Varese",
    "sg:tags":[
        "extrusion",
        "system",
        "extruders"
    ],
    "sg:website":"www.macchi.it",
    "wof:name":"Macchi Spa",
    "wof:placetype":"venue"
},
  "geometry": {"coordinates":[8.899416,45.730595],"type":"Point"}
}