{
  "type": "Feature",
  "properties": {
    "iso:country":"IT",
    "sg:address":"25083 Gardone Riviera",
    "sg:city":"Gardone Riviera",
    "sg:orig_category":"Ospedali E Servizi Sanitari",
    "sg:phone":"+39 036 529 8116",
    "sg:postcode":"25083",
    "sg:province":"Brescia",
    "wof:name":"Casa Di Cura Privata Villa Gemma Spa",
    "wof:placetype":"venue"
},
  "geometry": {"coordinates":[10.569952,45.622448],"type":"Point"}
}