{
  "type": "Feature",
  "properties": {
    "iso:country":"IT",
    "sg:address":"20026 Novate Milanese",
    "sg:city":"Novate Milanese",
    "sg:orig_category":"Materiali Semilavorati Metallici",
    "sg:phone":"+39 02 354 1506",
    "sg:postcode":"20026",
    "sg:province":"Milano",
    "wof:name":"Nicro Di N. Croce & C. (s.r.l.)",
    "wof:placetype":"venue"
},
  "geometry": {"coordinates":[9.152122,45.533581],"type":"Point"}
}