{
  "type": "Feature",
  "properties": {
    "addr:full":"22077 Olgiate Comasco Olgiate Comasco Como 22077",
    "addr:postcode":"22077;22077",
    "iso:country":"IT",
    "sg:address":"22077 Olgiate Comasco",
    "sg:city":"Olgiate Comasco",
    "sg:orig_category":"Pubblica Amministrazione",
    "sg:phone":"+39 031 945209",
    "sg:postcode":"22077",
    "sg:province":"Como",
    "wof:name":"Guardia Di Finanza Comando Compagnia",
    "wof:placetype":"venue"
},
  "geometry": {"coordinates":[8.9679584503,45.7871665955],"type":"Point"}
}