{
  "type": "Feature",
  "properties": {
    "addr:full":"11, Via Novara 10098 Rivoli Rivoli Torino 10098",
    "addr:postcode":"10098;10098",
    "addr:street":"Via Novara",
    "iso:country":"IT",
    "sg:address":"11, Via Novara 10098 Rivoli",
    "sg:city":"Rivoli",
    "sg:classifiers":[
        {
            "category":"Professional",
            "subcategory":"Engineering",
            "type":"Services"
        }
    ],
    "sg:phone":"+39 011 957 4608",
    "sg:postcode":"10098",
    "sg:province":"Torino",
    "sg:tags":[
        "machine",
        "-",
        "mechanical"
    ],
    "wof:name":"Samec S.r.l.",
    "wof:placetype":"venue"
},
  "geometry": {"coordinates":[7.559805,45.059978],"type":"Point"}
}