{
  "type": "Feature",
  "properties": {
    "addr:full":"88046 Lamezia Terme Lamezia Terme Catanzaro 88046",
    "addr:postcode":"88046;88046",
    "iso:country":"IT",
    "sg:address":"88046 Lamezia Terme",
    "sg:city":"Lamezia Terme",
    "sg:classifiers":[
        {
            "category":"Banks & Credit Unions",
            "subcategory":"Investment Brokerage",
            "type":"Services"
        }
    ],
    "sg:phone":"+39 0968 442032",
    "sg:postcode":"88046",
    "sg:province":"Catanzaro",
    "sg:tags":[
        "disposal",
        "refuse",
        "work",
        "protection",
        "environmental"
    ],
    "sg:website":"http://www.ecologiaoggi.it",
    "wof:name":"Ecologia Oggi Srl",
    "wof:placetype":"venue"
},
  "geometry": {"coordinates":[16.275751,38.93362],"type":"Point"}
}