{
  "type": "Feature",
  "properties": {
    "iso:country":"IT",
    "sg:address":"31050 Ponzano Veneto",
    "sg:city":"Ponzano Veneto",
    "sg:orig_category":"Materiali Edili",
    "sg:phone":"+39 0422 440681",
    "sg:postcode":"31050",
    "sg:province":"Treviso",
    "wof:name":"Edilam Snc",
    "wof:placetype":"venue"
},
  "geometry": {"coordinates":[12.22033,45.724564],"type":"Point"}
}