{
  "type": "Feature",
  "properties": {
    "iso:country":"IT",
    "sg:address":"80131 Napoli",
    "sg:city":"Napoli",
    "sg:orig_category":"Ospedali E Servizi Sanitari",
    "sg:phone":"+39 081 546 4321",
    "sg:postcode":"80131",
    "sg:province":"Napoli",
    "wof:name":"Migliorino Concetta",
    "wof:placetype":"venue"
},
  "geometry": {"coordinates":[14.226474,40.861607],"type":"Point"}
}