{
  "type": "Feature",
  "properties": {
    "addr:full":"95024 Acireale Acireale Catania 95024",
    "addr:postcode":"95024;95024",
    "iso:country":"IT",
    "sg:address":"95024 Acireale",
    "sg:city":"Acireale",
    "sg:orig_category":"Forniture Per Uffici",
    "sg:phone":"+39 095 765 1290",
    "sg:postcode":"95024",
    "sg:province":"Catania",
    "wof:name":"Cartera Aetna Di Franco Conti & C.",
    "wof:placetype":"venue"
},
  "geometry": {"coordinates":[15.1328926086,37.6307907104],"type":"Point"}
}