{
  "type": "Feature",
  "properties": {
    "addr:full":"166, Via Trento 38023 Cles Cles Trento 38023",
    "addr:housenumber":"166",
    "addr:postcode":"38023;38023",
    "addr:street":"Via Trento",
    "iso:country":"IT",
    "sg:address":"166, Via Trento 38023 Cles",
    "sg:city":"Cles",
    "sg:classifiers":[
        {
            "category":"Wholesale",
            "subcategory":"Drugs",
            "type":"Manufacturing & Wholesale Goods"
        }
    ],
    "sg:phone":"+39 0463 421005",
    "sg:postcode":"38023",
    "sg:province":"Trento",
    "sg:tags":[
        "chemical",
        "pharmaceutical"
    ],
    "wof:name":"Cristoforetti (s.p.a.)",
    "wof:placetype":"venue"
},
  "geometry": {"coordinates":[11.039249,46.355465],"type":"Point"}
}