{
  "type": "Feature",
  "properties": {
    "iso:country":"IT",
    "sg:address":"20143 Milano",
    "sg:city":"Milano",
    "sg:orig_category":"Radiografia E Radiologia - Impianti, Apparecchi E Forniture",
    "sg:phone":"+39 02 8912 2273",
    "sg:postcode":"20143",
    "sg:province":"Milano",
    "sg:website":"http://www.eurocol.it",
    "wof:name":"Eurocolumbus Srl",
    "wof:placetype":"venue"
},
  "geometry": {"coordinates":[9.166824,45.443363],"type":"Point"}
}