{
  "type": "Feature",
  "properties": {
    "addr:full":"95128 Catania Catania Catania 95128",
    "addr:postcode":"95128;95128",
    "iso:country":"IT",
    "sg:address":"95128 Catania",
    "sg:city":"Catania",
    "sg:orig_category":"Pubblicita', Marketing E Comunicazione",
    "sg:phone":"+39 095 716 9432",
    "sg:postcode":"95128",
    "sg:province":"Catania",
    "wof:name":"Felice Ferlito",
    "wof:placetype":"venue"
},
  "geometry": {"coordinates":[15.0874013901,37.5209922791],"type":"Point"}
}