{
  "type": "Feature",
  "properties": {
    "iso:country":"IT",
    "sg:address":"40069 Zola Predosa",
    "sg:city":"Zola",
    "sg:orig_category":"Servizi Per Aziende, Manifestazioni E Supporto Agli Scambi Commerciali",
    "sg:phone":"+39 051 750247",
    "sg:postcode":"40069",
    "sg:province":"Bologna",
    "sg:website":"http://www.palazzoalbergati.it",
    "wof:name":"Palazzo Albergati",
    "wof:placetype":"venue"
},
  "geometry": {"coordinates":[11.221393,44.512066],"type":"Point"}
}