{
  "type": "Feature",
  "properties": {
    "addr:full":"V. Roma, 29/31; Iglesias; 09016 Iglesias Carbonia-Iglesias 09016",
    "addr:housenumber":"29 / 31",
    "addr:postcode":"09016;09016",
    "addr:street":"V. Roma;Iglesias",
    "iso:country":"IT",
    "sg:address":"V. Roma, 29/31; Iglesias; 09016",
    "sg:city":"Iglesias",
    "sg:classifiers":[
        {
            "category":"Banks & Credit Unions",
            "subcategory":"Bank",
            "type":"Services"
        }
    ],
    "sg:phone":"+39 0781 40634",
    "sg:postcode":"09016",
    "sg:province":"Carbonia-Iglesias",
    "wof:name":"Banca Nazionale Del Lavoro",
    "wof:placetype":"venue"
},
  "geometry": {"coordinates":[8.532166,39.311584],"type":"Point"}
}