{
  "type": "Feature",
  "properties": {
    "iso:country":"IT",
    "sg:address":"Livorno, Li",
    "sg:classifiers":[
        {
            "category":"Banks & Credit Unions",
            "subcategory":"Bank",
            "type":"Services"
        }
    ],
    "wof:name":"Centro Servizi Promozione Imprenditoriale Spa",
    "wof:placetype":"venue"
},
  "geometry": {"coordinates":[10.308011,43.551876],"type":"Point"}
}