{
  "type": "Feature",
  "properties": {
    "iso:country":"IT",
    "sg:address":"24030 Celana",
    "sg:city":"Celana",
    "sg:orig_category":"Manufacturers: Prefabbricati",
    "sg:phone":"+39 035 783786",
    "sg:postcode":"24030",
    "sg:province":"Bergamo",
    "wof:name":"Mazzoleni Maurizio",
    "wof:placetype":"venue"
},
  "geometry": {"coordinates":[9.617382,45.748882],"type":"Point"}
}