{
  "type": "Feature",
  "properties": {
    "iso:country":"IT",
    "sg:address":"51018 Pieve A Nievole",
    "sg:city":"Pieve a Nievole",
    "sg:orig_category":"Manufacturers: Prefabbricati",
    "sg:phone":"+39 0572 80484",
    "sg:postcode":"51018",
    "sg:province":"Pistoia",
    "wof:name":"Martellini Benito & C. Snc",
    "wof:placetype":"venue"
},
  "geometry": {"coordinates":[10.796077,43.881378],"type":"Point"}
}