{
  "type": "Feature",
  "properties": {
    "iso:country":"IT",
    "sg:address":"62014 Corridonia",
    "sg:city":"Corridonia",
    "sg:orig_category":"Non-classified Establishments",
    "sg:phone":"+39 0733 433926",
    "sg:postcode":"62014",
    "sg:province":"Macerata",
    "wof:name":"Anna Russia Creazioni",
    "wof:placetype":"venue"
},
  "geometry": {"coordinates":[13.500156,43.241318],"type":"Point"}
}