{
  "type": "Feature",
  "properties": {
    "iso:country":"IT",
    "sg:address":"Via Belgio 22 35127 Padova",
    "sg:city":"Padova",
    "sg:classifiers":[
        {
            "category":"Home & Garden",
            "subcategory":"Household Appliances",
            "type":"Retail Goods"
        }
    ],
    "sg:phone":"+39 049 870 0307",
    "sg:postcode":"35127",
    "sg:province":"Padova",
    "sg:tags":[
        "electric"
    ],
    "sg:website":"www.lindhaus.it",
    "wof:name":"Lindhaus S.r.l.",
    "wof:placetype":"venue"
},
  "geometry": {"coordinates":[11.948999,45.394455],"type":"Point"}
}