{
  "type": "Feature",
  "properties": {
    "addr:full":"84012 Angri Angri Salerno 84012",
    "addr:postcode":"84012;84012",
    "iso:country":"IT",
    "sg:address":"84012 Angri",
    "sg:city":"Angri",
    "sg:orig_category":"Servizi Ausiliari Dei Mezzi Di Trasporto. Servizi Ausiliari Per Il Trasporto. Acqua, Luce, Gas E Societa' Di Esercizio Pubblico",
    "sg:phone":"+39 081 940623",
    "sg:postcode":"84012",
    "sg:province":"Salerno",
    "wof:name":"Autostrade Meridionali Spa",
    "wof:placetype":"venue"
},
  "geometry": {"coordinates":[14.572762,40.734707],"type":"Point"}
}