{
  "type": "Feature",
  "properties": {
    "iso:country":"IT",
    "sg:address":"1/3, Via Nuova Valassina 22060 Arosio",
    "sg:city":"Arosio",
    "sg:classifiers":[
        {
            "category":"Shopping",
            "subcategory":"Computers & Home Electronics",
            "type":"Retail Goods"
        }
    ],
    "sg:phone":"+39 39031762733",
    "sg:postcode":"22060",
    "sg:province":"Como",
    "sg:tags":[
        "electronic",
        "electrical",
        "equipment"
    ],
    "wof:name":"Min - Tec (s.n.c.)",
    "wof:placetype":"venue"
},
  "geometry": {"coordinates":[9.085456,45.811966],"type":"Point"}
}