{
  "type": "Feature",
  "properties": {
    "iso:country":"IT",
    "sg:address":"1, Via Carlini Francesco 20146 Milano",
    "sg:city":"Milano",
    "sg:classifiers":[
        {
            "category":"Travel",
            "subcategory":"Travel Agent",
            "type":"Entertainment"
        }
    ],
    "sg:phone":"+39 39024221020",
    "sg:postcode":"20146",
    "sg:province":"Milano",
    "sg:tags":[
        "business"
    ],
    "wof:name":"Richmond Italia S.r.l.",
    "wof:placetype":"venue"
},
  "geometry": {"coordinates":[9.143507,45.453434],"type":"Point"}
}