{
  "type": "Feature",
  "properties": {
    "iso:country":"IT",
    "sg:address":"16158 Genova",
    "sg:city":"Genova",
    "sg:orig_category":"Forniture Per Attivita' Industriali",
    "sg:phone":"+39 010 613 6412",
    "sg:postcode":"16158",
    "sg:province":"Genova",
    "wof:name":"Casalino G.b.",
    "wof:placetype":"venue"
},
  "geometry": {"coordinates":[8.7475986481,44.4373207092],"type":"Point"}
}