{
  "type": "Feature",
  "properties": {
    "addr:full":"00193 Roma Roma Roma 00193",
    "addr:postcode":"00193;00193",
    "iso:country":"IT",
    "sg:address":"00193 Roma",
    "sg:city":"Roma",
    "sg:classifiers":[
        {
            "category":"Health Services",
            "subcategory":"Doctor",
            "type":"Services"
        }
    ],
    "sg:phone":"+39 06 687 3095",
    "sg:postcode":"00193",
    "sg:province":"Roma",
    "sg:tags":[
        "physician",
        "surgeon"
    ],
    "sg:website":"http://www.raprui.org",
    "wof:name":"D.u.t. Srl",
    "wof:placetype":"venue"
},
  "geometry": {"coordinates":[12.4612836838,41.9063682556],"type":"Point"}
}