{
  "type": "Feature",
  "properties": {
    "iso:country":"IT",
    "sg:address":"16128 Genova",
    "sg:city":"Genova",
    "sg:orig_category":"Lavorazioni Meccaniche E Servizi. Riparazione Dei Mezzi Di Trasporto",
    "sg:phone":"+39 010 256000",
    "sg:postcode":"16128",
    "sg:province":"Genova",
    "wof:name":"Officine Meccaniche Navali E Fonderie San Giorgio Del Porto Spa",
    "wof:placetype":"venue"
},
  "geometry": {"coordinates":[8.936954,44.401161],"type":"Point"}
}