{
  "type": "Feature",
  "properties": {
    "addr:full":"Via T. Edison 3 40017 San Giovanni In Persiceto San Giovanni in Persiceto Bologna 40017",
    "addr:housenumber":"3",
    "addr:postcode":"40017;40017",
    "addr:street":"Via T. Edison",
    "iso:country":"IT",
    "sg:address":"Via T. Edison 3 40017 San Giovanni In Persiceto",
    "sg:city":"San Giovanni in Persiceto",
    "sg:classifiers":[
        {
            "category":"Autos & Motor Vehicles",
            "subcategory":"Fuel & Gas Station",
            "type":"Retail Goods"
        }
    ],
    "sg:phone":"+39 051 821601",
    "sg:postcode":"40017",
    "sg:province":"Bologna",
    "sg:tags":[
        "machine",
        "plant",
        "different",
        "special",
        "purpose"
    ],
    "wof:name":"Co.ma.s. Snc",
    "wof:placetype":"venue"
},
  "geometry": {"coordinates":[11.346481,44.494221],"type":"Point"}
}