{
  "type": "Feature",
  "properties": {
    "addr:full":"59100 Prato Prato Prato 59100",
    "addr:postcode":"59100;59100",
    "iso:country":"IT",
    "sg:address":"59100 Prato",
    "sg:city":"Prato",
    "sg:orig_category":"Cartotecnica E Servizi. Forniture Per Uffici",
    "sg:phone":"+39 0574 730222",
    "sg:postcode":"59100",
    "sg:province":"Prato",
    "wof:name":"Innocenti Paolo - Duesse",
    "wof:placetype":"venue"
},
  "geometry": {"coordinates":[11.045377,43.843014],"type":"Point"}
}