{
  "type": "Feature",
  "properties": {
    "addr:full":"16, Via Sturzo Don Luigi 20033 Desio Desio Milano 20033",
    "addr:postcode":"20033;20033",
    "addr:street":"Via Sturzo Don Luigi",
    "iso:country":"IT",
    "sg:address":"16, Via Sturzo Don Luigi 20033 Desio",
    "sg:city":"Desio",
    "sg:classifiers":[
        {
            "category":"Professional",
            "subcategory":"Engineering",
            "type":"Services"
        }
    ],
    "sg:phone":"+39 036 262 2702",
    "sg:postcode":"20033",
    "sg:province":"Milano",
    "sg:tags":[
        "machine",
        "-",
        "mechanical"
    ],
    "wof:name":"S.v.m. Srl",
    "wof:placetype":"venue"
},
  "geometry": {"coordinates":[9.188141,45.463688],"type":"Point"}
}