{
  "type": "Feature",
  "properties": {
    "addr:full":"38035 Moena Moena Trento 38035",
    "addr:postcode":"38035;38035",
    "iso:country":"IT",
    "sg:address":"38035 Moena",
    "sg:city":"Moena",
    "sg:orig_category":"Autotrasporti",
    "sg:phone":"+39 0462 573410",
    "sg:postcode":"38035",
    "sg:province":"Trento",
    "wof:name":"Chiocchetti Luigi & C. Snc",
    "wof:placetype":"venue"
},
  "geometry": {"coordinates":[11.645689,46.363758],"type":"Point"}
}