{
  "type": "Feature",
  "properties": {
    "addr:full":"55100 Lucca Lucca Lucca 55100",
    "addr:postcode":"55100;55100",
    "iso:country":"IT",
    "sg:address":"55100 Lucca",
    "sg:city":"Lucca",
    "sg:orig_category":"Macchine, Impianti Ed Attrezzature Per Industria Alimentare E Bevande",
    "sg:phone":"+39 0583 327766",
    "sg:postcode":"55100",
    "sg:province":"Lucca",
    "wof:name":"Co.m.a.s. Srl",
    "wof:placetype":"venue"
},
  "geometry": {"coordinates":[10.475692,43.861126],"type":"Point"}
}