{
  "type": "Feature",
  "properties": {
    "iso:country":"IT",
    "sg:address":"44034 Copparo",
    "sg:city":"Copparo",
    "sg:orig_category":"Materiali Edili",
    "sg:phone":"+39 0532 860174",
    "sg:postcode":"44034",
    "sg:province":"Ferrara",
    "wof:name":"S.i.l.l.a. Sas Di A. Mattei E C.",
    "wof:placetype":"venue"
},
  "geometry": {"coordinates":[11.840269,44.890259],"type":"Point"}
}