{
  "type": "Feature",
  "properties": {
    "addr:full":"Po Box 271/272, 50100 Florence, Fi",
    "addr:housenumber":"po;/ 272",
    "addr:postcode":"50100",
    "addr:street":"Box 271",
    "iso:country":"IT",
    "sg:address":"Po Box 271/272, 50100 Florence, Fi",
    "sg:classifiers":[
        {
            "category":"Banks & Credit Unions",
            "subcategory":"Bank",
            "type":"Services"
        }
    ],
    "sg:phone":"+39 055 26121",
    "wof:name":"Cassa Di Risparmio Di Firenze Spa",
    "wof:placetype":"venue"
},
  "geometry": {"coordinates":[11.22137,43.73127],"type":"Point"}
}