{
  "type": "Feature",
  "properties": {
    "iso:country":"IT",
    "sg:address":"Via Gran Paradiso 21050 Gorla Maggiore",
    "sg:city":"Gorla Maggiore",
    "sg:classifiers":[
        {
            "category":"Manufacturing",
            "subcategory":"Metals",
            "type":"Manufacturing & Wholesale Goods"
        }
    ],
    "sg:phone":"+39 0331 617466",
    "sg:postcode":"21050",
    "sg:province":"Varese",
    "sg:tags":[
        "metallurgy",
        "metalworking"
    ],
    "wof:name":"Fior Pietro (s.r.l.)",
    "wof:placetype":"venue"
},
  "geometry": {"coordinates":[8.8986711502,45.6688537598],"type":"Point"}
}