{
  "type": "Feature",
  "properties": {
    "iso:country":"IT",
    "sg:address":"63, Via Degli Scarlatti 41100 Modena",
    "sg:city":"Modena",
    "sg:classifiers":[
        {
            "category":"Building & Trades",
            "subcategory":"Construction",
            "type":"Services"
        }
    ],
    "sg:phone":"+39 39059280556",
    "sg:postcode":"41100",
    "sg:province":"Modena",
    "sg:tags":[
        "work",
        "public"
    ],
    "wof:name":"Bowling Marketing Service (s.r.l.)",
    "wof:placetype":"venue"
},
  "geometry": {"coordinates":[10.96552,44.631897],"type":"Point"}
}