{
  "type": "Feature",
  "properties": {
    "iso:country":"IT",
    "sg:address":"Via Francesca 88; Stabbia",
    "sg:classifiers":[
        {
            "category":"Banks & Credit Unions",
            "subcategory":"Bank",
            "type":"Services"
        }
    ],
    "sg:phone":"+39 0571 586073",
    "wof:name":"Cassa Di Risparmio Di Volterra Spa",
    "wof:placetype":"venue"
},
  "geometry": {"coordinates":[10.825384,43.764942],"type":"Point"}
}