{
  "type": "Feature",
  "properties": {
    "iso:country":"IT",
    "sg:address":"25010 Isorella",
    "sg:city":"Isorella",
    "sg:classifiers":[
        {
            "category":"Retail",
            "subcategory":"Storage",
            "type":"Services"
        }
    ],
    "sg:phone":"+39 030 995 2317",
    "sg:postcode":"25010",
    "sg:province":"Brescia",
    "sg:tags":[
        "equipment",
        "handling",
        "system"
    ],
    "wof:name":"Daffi Luigi & Cristian Snc",
    "wof:placetype":"venue"
},
  "geometry": {"coordinates":[10.323462,45.309223],"type":"Point"}
}