{
  "type": "Feature",
  "properties": {
    "addr:full":"20128 Milano Milano Milano 20128",
    "addr:postcode":"20128;20128",
    "iso:country":"IT",
    "sg:address":"20128 Milano",
    "sg:city":"Milano",
    "sg:orig_category":"Materiali E Componenti Elettrotecnici",
    "sg:phone":"+39 02 256 4723",
    "sg:postcode":"20128",
    "sg:province":"Milano",
    "wof:name":"F L Di Scarioni Orlando",
    "wof:placetype":"venue"
},
  "geometry": {"coordinates":[9.23637,45.508312],"type":"Point"}
}