{
  "type": "Feature",
  "properties": {
    "iso:country":"IT",
    "sg:address":"4, Strada Battagliero 10055 Condove",
    "sg:city":"Condove",
    "sg:classifiers":[
        {
            "category":"Professional",
            "subcategory":"Engineering",
            "type":"Services"
        }
    ],
    "sg:phone":"+39 011 964 2600",
    "sg:postcode":"10055",
    "sg:province":"Torino",
    "sg:tags":[
        "machine",
        "-",
        "mechanical"
    ],
    "wof:name":"Map Engineering Srl",
    "wof:placetype":"venue"
},
  "geometry": {"coordinates":[7.686619,45.07056],"type":"Point"}
}