{
  "type": "Feature",
  "properties": {
    "iso:country":"IT",
    "sg:address":"98122 Messina",
    "sg:city":"Messina",
    "sg:orig_category":"Lavorazioni Meccaniche E Servizi",
    "sg:phone":"+39 090 678 1320",
    "sg:postcode":"98122",
    "sg:province":"Messina",
    "wof:name":"Studio Tecnico Di Ingegneria Carmelo Massimo Santisi",
    "wof:placetype":"venue"
},
  "geometry": {"coordinates":[15.551137,38.190472],"type":"Point"}
}