{
  "type": "Feature",
  "properties": {
    "addr:full":"Via Ugo Foscolo 4 20060 Basiano Basiano Milano 20060",
    "addr:housenumber":"4",
    "addr:postcode":"20060;20060",
    "addr:street":"Via Ugo Foscolo",
    "iso:country":"IT",
    "sg:address":"Via Ugo Foscolo 4 20060 Basiano",
    "sg:city":"Basiano",
    "sg:classifiers":[
        {
            "category":"Manufacturing",
            "subcategory":"Rubber & Plastics",
            "type":"Manufacturing & Wholesale Goods"
        }
    ],
    "sg:phone":"+39 02 9576 0331",
    "sg:postcode":"20060",
    "sg:province":"Milano",
    "sg:tags":[
        "joint"
    ],
    "sg:website":"www.carco.it",
    "wof:name":"Carco Spa",
    "wof:placetype":"venue"
},
  "geometry": {"coordinates":[9.188141,45.463688],"type":"Point"}
}