{
  "type": "Feature",
  "properties": {
    "iso:country":"IT",
    "sg:address":"00139 Roma",
    "sg:city":"Roma",
    "sg:orig_category":"Ristorazione E Locali Pubblici Affini. Ristoranti Ed Esercizi Affini",
    "sg:phone":"+39 06 8713 5982",
    "sg:postcode":"00139",
    "sg:province":"Roma",
    "wof:name":"Pizza Express Snc Di Moroni Roberto & C.",
    "wof:placetype":"venue"
},
  "geometry": {"coordinates":[12.532927,41.961109],"type":"Point"}
}