{
  "type": "Feature",
  "properties": {
    "addr:full":"10042 Nichelino Nichelino Torino 10042",
    "addr:postcode":"10042;10042",
    "iso:country":"IT",
    "sg:address":"10042 Nichelino",
    "sg:city":"Nichelino",
    "sg:orig_category":"Servizi E Lavori Per Edilizia E Lavori Pubblici",
    "sg:phone":"+39 011 627 2201",
    "sg:postcode":"10042",
    "sg:province":"Torino",
    "wof:name":"Jerino' Giuseppe",
    "wof:placetype":"venue"
},
  "geometry": {"coordinates":[7.623338,44.998154],"type":"Point"}
}