{
  "type": "Feature",
  "properties": {
    "addr:full":"135, Viale Regina Margherita 57025 Piombino Piombino Livorno 57025",
    "addr:postcode":"57025;57025",
    "addr:street":"Viale Regina Margherita",
    "iso:country":"IT",
    "sg:address":"135, Viale Regina Margherita 57025 Piombino",
    "sg:city":"Piombino",
    "sg:classifiers":[
        {
            "category":"Marine",
            "type":"Transportation"
        }
    ],
    "sg:phone":"+39 0565 221100",
    "sg:postcode":"57025",
    "sg:province":"Livorno",
    "sg:tags":[
        "transport",
        "sea"
    ],
    "wof:name":"Freschi Alessandro & C. (s.n.c.)",
    "wof:placetype":"venue"
},
  "geometry": {"coordinates":[10.544983,42.928211],"type":"Point"}
}