{
  "type": "Feature",
  "properties": {
    "addr:full":"50055 Lastra A Signa Lastra a Signa Firenze 50055",
    "addr:postcode":"50055;50055",
    "addr:street":"A Signa",
    "iso:country":"IT",
    "sg:address":"50055 Lastra A Signa",
    "sg:city":"Lastra a Signa",
    "sg:orig_category":"Acciaierie E Fonderie",
    "sg:phone":"+39 055 872 5653",
    "sg:postcode":"50055",
    "sg:province":"Firenze",
    "wof:name":"La Fonderia Srl",
    "wof:placetype":"venue"
},
  "geometry": {"coordinates":[11.121706,43.772266],"type":"Point"}
}