{
  "type": "Feature",
  "properties": {
    "addr:full":"Sda Degli Alberoni 2 14023 Cocconato Cocconato Asti 14023",
    "addr:housenumber":"2",
    "addr:postcode":"14023;14023",
    "addr:street":"Alberoni",
    "iso:country":"IT",
    "sg:address":"Sda Degli Alberoni 2 14023 Cocconato",
    "sg:city":"Cocconato",
    "sg:classifiers":[
        {
            "category":"Shopping",
            "subcategory":"Discount & Variety Stores",
            "type":"Retail Goods"
        }
    ],
    "sg:phone":"+39 0141 907192",
    "sg:postcode":"14023",
    "sg:province":"Asti",
    "sg:tags":[
        "shop",
        "fitting"
    ],
    "wof:name":"Conrotto Arredonegozi Di Giuseppe Conrotto & C. S.a.s.",
    "wof:placetype":"venue"
},
  "geometry": {"coordinates":[8.0534744263,45.0872077942],"type":"Point"}
}