{
  "type": "Feature",
  "properties": {
    "iso:country":"IT",
    "sg:address":"Vle Europa 83 - Asmonte 20010 Ossona",
    "sg:city":"Ossona",
    "sg:classifiers":[
        {
            "category":"Shopping",
            "subcategory":"Crafts & Fabrics",
            "type":"Retail Goods"
        }
    ],
    "sg:phone":"+39 02 9038 4004",
    "sg:postcode":"20010",
    "sg:province":"Milano",
    "sg:tags":[
        "textile",
        "shop",
        "printing"
    ],
    "sg:website":"www.matex-it.com",
    "wof:name":"Matex S.r.l.",
    "wof:placetype":"venue"
},
  "geometry": {"coordinates":[8.883531,45.49332],"type":"Point"}
}