{
  "type": "Feature",
  "properties": {
    "iso:country":"IT",
    "sg:address":"81100 Caserta",
    "sg:city":"Caserta",
    "sg:classifiers":[
        {
            "category":"Health Services",
            "subcategory":"Health Practitioner",
            "type":"Services"
        }
    ],
    "sg:phone":"+39 0823 361875",
    "sg:postcode":"81100",
    "sg:province":"Caserta",
    "sg:tags":[
        "medici"
    ],
    "wof:name":"Morra Vittoria",
    "wof:placetype":"venue"
},
  "geometry": {"coordinates":[14.3328046799,41.0851478577],"type":"Point"}
}