{
  "type": "Feature",
  "properties": {
    "addr:full":"70029 Santeramo In Colle Santeramo in Colle Bari 70029",
    "addr:postcode":"70029;70029",
    "iso:country":"IT",
    "sg:address":"70029 Santeramo In Colle",
    "sg:city":"Santeramo in Colle",
    "sg:orig_category":"Forniture Per Attivita' Commerciali Ed Artigianali. Arredi Ed Attrezzature Per Attivita' Commerciali Ed Artigianali",
    "sg:phone":"+39 080 302 1985",
    "sg:postcode":"70029",
    "sg:province":"Bari",
    "wof:name":"Gran Chic Di Lovecchio Antonella",
    "wof:placetype":"venue"
},
  "geometry": {"coordinates":[16.7500305176,40.7934761047],"type":"Point"}
}