{
  "type": "Feature",
  "properties": {
    "iso:country":"IT",
    "sg:address":"40012 Calderara Di Reno",
    "sg:city":"Calderara di Reno",
    "sg:orig_category":"Servizi E Lavori Industria Della Gomma",
    "sg:postcode":"40012",
    "sg:province":"Bologna",
    "wof:name":"Nofori Bruno Di Nofori B. E C. (s.n.c.)",
    "wof:placetype":"venue"
},
  "geometry": {"coordinates":[11.268493,44.541142],"type":"Point"}
}