{
  "type": "Feature",
  "properties": {
    "addr:full":"01100 Viterbo Viterbo Viterbo 01100",
    "addr:postcode":"01100;01100",
    "iso:country":"IT",
    "sg:address":"01100 Viterbo",
    "sg:city":"Viterbo",
    "sg:orig_category":"Servizi E Lavori Per Edilizia E Lavori Pubblici. Servizi E Lavori Per Ecologia E Smaltimento Rifiuti",
    "sg:phone":"+39 0761 328417",
    "sg:postcode":"01100",
    "sg:province":"Viterbo",
    "wof:name":"Viterspurgo & Vitermetal Snc",
    "wof:placetype":"venue"
},
  "geometry": {"coordinates":[12.081188,42.403637],"type":"Point"}
}