{
  "type": "Feature",
  "properties": {
    "iso:country":"IT",
    "sg:address":"35011 Campodarsego",
    "sg:city":"Campodarsego",
    "sg:orig_category":"Forniture Per Abbigliamento E Pelletterie. Forniture Per Attivita' Commerciali Ed Artigianali",
    "sg:phone":"+39 049 556 4449",
    "sg:postcode":"35011",
    "sg:province":"Padova",
    "wof:name":"Officina Meccanica Stampi Snc",
    "wof:placetype":"venue"
},
  "geometry": {"coordinates":[11.913769722,45.4995536804],"type":"Point"}
}