{
  "type": "Feature",
  "properties": {
    "iso:country":"IT",
    "sg:address":"35010 Cadoneghe",
    "sg:city":"Cadoneghe",
    "sg:classifiers":[
        {
            "category":"Communications",
            "subcategory":"Film & Video Production",
            "type":"Services"
        }
    ],
    "sg:phone":"+39 049 887 3440",
    "sg:postcode":"35010",
    "sg:province":"Padova",
    "sg:tags":[
        "control",
        "equipment",
        "climate",
        "conditioning"
    ],
    "wof:name":"Aersystem Snc",
    "wof:placetype":"venue"
},
  "geometry": {"coordinates":[11.901186,45.451824],"type":"Point"}
}