{
  "type": "Feature",
  "properties": {
    "addr:full":"59100 Prato Prato Prato 59100",
    "addr:postcode":"59100;59100",
    "iso:country":"IT",
    "sg:address":"59100 Prato",
    "sg:city":"Prato",
    "sg:orig_category":"Analisi Chimiche, Industriali E Merceologiche",
    "sg:phone":"+39 0574 591341",
    "sg:postcode":"59100",
    "sg:province":"Prato",
    "sg:website":"http://www.data.it/etitex",
    "wof:name":"Magazzini Generali Di Prato Soc. Coop. Per Azioni Srl",
    "wof:placetype":"venue"
},
  "geometry": {"coordinates":[11.115479,43.873775],"type":"Point"}
}