{
  "type": "Feature",
  "properties": {
    "addr:full":"Via Stanzione 121; Orta D'atella; 81030 Caserta 81030",
    "addr:housenumber":"121",
    "addr:postcode":"81030;81030",
    "addr:street":"Via Stanzione;Orta D'Atella",
    "iso:country":"IT",
    "sg:address":"Via Stanzione 121; Orta D'atella; 81030",
    "sg:classifiers":[
        {
            "category":"Banks & Credit Unions",
            "subcategory":"Bank",
            "type":"Services"
        }
    ],
    "sg:phone":"+39 081 891 7181",
    "sg:postcode":"81030",
    "sg:province":"Caserta",
    "wof:name":"Banco Di Napoli Spa",
    "wof:placetype":"venue"
},
  "geometry": {"coordinates":[14.267591,40.965233],"type":"Point"}
}