{
  "type": "Feature",
  "properties": {
    "iso:country":"IT",
    "sg:address":"35020 Maser\u00e0 Di Padova",
    "sg:orig_category":"Zanzariere",
    "sg:phone":"+39 049 886 2850",
    "sg:postcode":"35020",
    "sg:province":"Padova",
    "wof:name":"Mosquito Tecnosystem",
    "wof:placetype":"venue"
},
  "geometry": {"coordinates":[11.86419,45.320229],"type":"Point"}
}