{
  "type": "Feature",
  "properties": {
    "iso:country":"IT",
    "sg:address":"06024 Gubbio",
    "sg:city":"Gubbio",
    "sg:orig_category":"Articoli Regalo - Produzione E Ingrosso",
    "sg:phone":"+39 075 922 0622",
    "sg:postcode":"06024",
    "sg:province":"Perugia",
    "wof:name":"Comunita' Di Capodarco Dell'umbria",
    "wof:placetype":"venue"
},
  "geometry": {"coordinates":[12.575703,43.363045],"type":"Point"}
}