{
  "type": "Feature",
  "properties": {
    "addr:full":"Via Masi 4 44100 Ferrara Ferrara Ferrara 44100",
    "addr:housenumber":"4",
    "addr:postcode":"44100;44100",
    "addr:street":"Via Masi",
    "iso:country":"IT",
    "sg:address":"Via Masi 4 44100 Ferrara",
    "sg:city":"Ferrara",
    "sg:classifiers":[
        {
            "category":"Food & Beverages",
            "subcategory":"Fruits & Vegetables",
            "type":"Retail Goods"
        }
    ],
    "sg:phone":"+39 0532 722441",
    "sg:postcode":"44100",
    "sg:province":"Ferrara",
    "sg:website":"www.logiestense.it",
    "wof:name":"Logiestense",
    "wof:placetype":"venue"
},
  "geometry": {"coordinates":[11.6193552017,44.7254905701],"type":"Point"}
}