{
  "type": "Feature",
  "properties": {
    "iso:country":"IT",
    "sg:address":"28010 Cavaglio D'agogna",
    "sg:orig_category":"Apparecchiature Ed Attrezzature Meccaniche",
    "sg:phone":"+39 0322 806135",
    "sg:postcode":"28010",
    "sg:province":"Novara",
    "wof:name":"Euroflex Snc Di Claudia Testori",
    "wof:placetype":"venue"
},
  "geometry": {"coordinates":[8.488605,45.616573],"type":"Point"}
}