{
  "type": "Feature",
  "properties": {
    "iso:country":"IT",
    "sg:address":"16124 Genova",
    "sg:city":"Genova",
    "sg:orig_category":"Internet, Telematica E Audiotex - Servizi",
    "sg:phone":"+39 010 254 2058",
    "sg:postcode":"16124",
    "sg:province":"Genova",
    "sg:website":"http://www.artbook.net",
    "wof:name":"Artbook Sas",
    "wof:placetype":"venue"
},
  "geometry": {"coordinates":[8.975039,44.398674],"type":"Point"}
}