{
  "type": "Feature",
  "properties": {
    "iso:country":"IT",
    "sg:address":"00034 Colleferro",
    "sg:city":"Colleferro",
    "sg:orig_category":"Lavorazioni Meccaniche E Servizi. Riparazione Dei Mezzi Di Trasporto",
    "sg:phone":"+39 06 970 0815",
    "sg:postcode":"00034",
    "sg:province":"Roma",
    "wof:name":"Barbini Motori E Costruzioni Meccaniche Di Barbini Alessandra E C.sas",
    "wof:placetype":"venue"
},
  "geometry": {"coordinates":[12.473557,41.83572],"type":"Point"}
}