{
  "type": "Feature",
  "properties": {
    "iso:country":"IT",
    "sg:address":"10156 Torino",
    "sg:city":"Torino",
    "sg:orig_category":"Cartotecnica E Servizi. Forniture Per Uffici",
    "sg:phone":"+39 011 223 6184",
    "sg:postcode":"10156",
    "sg:province":"Torino",
    "wof:name":"Rossato Srl",
    "wof:placetype":"venue"
},
  "geometry": {"coordinates":[7.736866,45.097836],"type":"Point"}
}