{
  "type": "Feature",
  "properties": {
    "addr:full":"43, Via Moro Aldo 41043 Formigine Formigine Modena 41043",
    "addr:postcode":"41043;41043",
    "addr:street":"Via Moro Aldo",
    "iso:country":"IT",
    "sg:address":"43, Via Moro Aldo 41043 Formigine",
    "sg:city":"Formigine",
    "sg:classifiers":[
        {
            "category":"Manufacturing",
            "subcategory":"Paper Products",
            "type":"Manufacturing & Wholesale Goods"
        }
    ],
    "sg:phone":"+39 39059556097",
    "sg:postcode":"41043",
    "sg:province":"Modena",
    "sg:tags":[
        "cardboard"
    ],
    "wof:name":"Box Tosi (s.p.a.)",
    "wof:placetype":"venue"
},
  "geometry": {"coordinates":[10.9237365723,44.5455322266],"type":"Point"}
}