{
  "type": "Feature",
  "properties": {
    "iso:country":"IT",
    "sg:address":"13, Strada Pedemontana 43029 Traversetolo",
    "sg:city":"Traversetolo",
    "sg:classifiers":[
        {
            "category":"Food & Beverages",
            "subcategory":"Dairy",
            "type":"Retail Goods"
        }
    ],
    "sg:phone":"+39 0521 848347",
    "sg:postcode":"43029",
    "sg:province":"Parma",
    "sg:tags":[
        "product"
    ],
    "wof:name":"Caseificio Sociale La Traversetolese",
    "wof:placetype":"venue"
},
  "geometry": {"coordinates":[10.350777,44.664291],"type":"Point"}
}