{
  "type": "Feature",
  "properties": {
    "addr:full":"374, Via Statale 44047 Sant'agostino Ferrara 44047",
    "addr:housenumber":"374",
    "addr:postcode":"44047;44047",
    "addr:street":"Via Statale",
    "iso:country":"IT",
    "sg:address":"374, Via Statale 44047 Sant'agostino",
    "sg:classifiers":[
        {
            "category":"Manufacturing",
            "subcategory":"Motor Vehicles & Parts",
            "type":"Manufacturing & Wholesale Goods"
        }
    ],
    "sg:phone":"+39 0532 848570",
    "sg:postcode":"44047",
    "sg:province":"Ferrara",
    "sg:tags":[
        "engine"
    ],
    "wof:name":"F.i.r.a Fabbrica Italiana Radiatori Automezzi - Srl",
    "wof:placetype":"venue"
},
  "geometry": {"coordinates":[11.62044,44.837894],"type":"Point"}
}