{
  "type": "Feature",
  "properties": {
    "addr:full":"Via Altinate 107 35121 Padova Padova Padova 35121",
    "addr:housenumber":"107",
    "addr:postcode":"35121;35121",
    "addr:street":"Via Altinate",
    "iso:country":"IT",
    "sg:address":"Via Altinate 107 35121 Padova",
    "sg:city":"Padova",
    "sg:classifiers":[
        {
            "category":"Shopping",
            "subcategory":"Books",
            "type":"Retail Goods"
        }
    ],
    "sg:phone":"+39 049 655566",
    "sg:postcode":"35121",
    "sg:province":"Padova",
    "sg:website":"www.piccinonline.com",
    "wof:name":"Piccin Nuova Libraria - S.p.a.",
    "wof:placetype":"venue"
},
  "geometry": {"coordinates":[11.883014,45.407814],"type":"Point"}
}