{
  "type": "Feature",
  "properties": {
    "iso:country":"IT",
    "sg:address":"24064 Grumello Del Monte",
    "sg:city":"Grumello del Monte",
    "sg:classifiers":[
        {
            "category":"Manufacturing",
            "subcategory":"Metals",
            "type":"Manufacturing & Wholesale Goods"
        }
    ],
    "sg:phone":"+39 035 830477",
    "sg:postcode":"24064",
    "sg:province":"Bergamo",
    "sg:tags":[
        "forming",
        "working",
        "welding"
    ],
    "wof:name":"Rossi & Brevi Spa",
    "wof:placetype":"venue"
},
  "geometry": {"coordinates":[9.8727827072,45.6434020996],"type":"Point"}
}