{
  "type": "Feature",
  "properties": {
    "iso:country":"IT",
    "sg:address":"20123 Milano",
    "sg:city":"Milano",
    "sg:orig_category":"Chiese Ed Associazioni Religiose",
    "sg:phone":"+39 02 8940 7269",
    "sg:postcode":"20123",
    "sg:province":"Milano",
    "wof:name":"Comunita' Ortodossa Romena",
    "wof:placetype":"venue"
},
  "geometry": {"coordinates":[9.179931,45.457779],"type":"Point"}
}