{
  "type": "Feature",
  "properties": {
    "iso:country":"IT",
    "sg:address":"34 Via Martiri Della Liberta', 36050 Quinto Vicentino",
    "sg:city":"Quinto Vicentino",
    "sg:classifiers":[
        {
            "category":"Banks & Credit Unions",
            "subcategory":"Financial Services",
            "type":"Services"
        }
    ],
    "sg:phone":"+39 0444 250911",
    "sg:postcode":"36050",
    "sg:province":"Vicenza",
    "sg:tags":[
        "banking",
        "finance",
        "insurance"
    ],
    "wof:name":"Banca Di Credito Cooperativo Di Quinto Vicentino Scarl",
    "wof:placetype":"venue"
},
  "geometry": {"coordinates":[11.6264371872,45.5731925964],"type":"Point"}
}