{
  "type": "Feature",
  "properties": {
    "addr:full":"27029 Vigevano Vigevano Pavia 27029",
    "addr:postcode":"27029;27029",
    "iso:country":"IT",
    "sg:address":"27029 Vigevano",
    "sg:city":"Vigevano",
    "sg:orig_category":"Calzature, Pelletterie E Pelli. Shopping",
    "sg:phone":"+39 0381 69881",
    "sg:postcode":"27029",
    "sg:province":"Pavia",
    "sg:website":"http://www.moreschi.it",
    "wof:name":"Calzaturificio Moreschi Spa",
    "wof:placetype":"venue"
},
  "geometry": {"coordinates":[8.869008,45.321182],"type":"Point"}
}