{
  "type": "Feature",
  "properties": {
    "iso:country":"IT",
    "sg:address":"22060 Cabiate",
    "sg:city":"Cabiate",
    "sg:orig_category":"Articoli Per Imballaggio E Confezionamento",
    "sg:phone":"+39 031 766592",
    "sg:postcode":"22060",
    "sg:province":"Como",
    "wof:name":"Minotti Adolfo & C. (s.n.c.)",
    "wof:placetype":"venue"
},
  "geometry": {"coordinates":[9.1694,45.67382],"type":"Point"}
}