{
  "type": "Feature",
  "properties": {
    "iso:country":"IT",
    "sg:address":"41053 Maranello",
    "sg:city":"Maranello",
    "sg:orig_category":"Prodotti E Manufatti In Gomma",
    "sg:phone":"+39 0536 941248",
    "sg:postcode":"41053",
    "sg:province":"Modena",
    "wof:name":"Cavalieri Enzo",
    "wof:placetype":"venue"
},
  "geometry": {"coordinates":[10.865855217,44.5247573853],"type":"Point"}
}