{
  "type": "Feature",
  "properties": {
    "iso:country":"IT",
    "sg:address":"41013 Castelfranco Emilia",
    "sg:city":"Castelfranco Emilia",
    "sg:orig_category":"Macchine Ed Impianti Per Edilizia E Lavori Pubblici. Macchine Utensili E Impianti",
    "sg:phone":"+39 059 922105",
    "sg:postcode":"41013",
    "sg:province":"Modena",
    "sg:website":"http://www.i-sr.com",
    "wof:name":"Industrial Solutions Research Srl",
    "wof:placetype":"venue"
},
  "geometry": {"coordinates":[11.0145978928,44.6167297363],"type":"Point"}
}