{
  "type": "Feature",
  "properties": {
    "iso:country":"IT",
    "sg:address":"63023 Fermo",
    "sg:city":"Campiglione",
    "sg:orig_category":"Calzature, Pelletterie E Pelli",
    "sg:phone":"+39 0734 628360",
    "sg:postcode":"63023",
    "sg:province":"Ascoli Piceno",
    "sg:website":"http://www.sonia.it",
    "wof:name":"Calzaturificio Sonia Srl",
    "wof:placetype":"venue"
},
  "geometry": {"coordinates":[13.670963,43.178444],"type":"Point"}
}