{
  "type": "Feature",
  "properties": {
    "addr:full":"27029 Vigevano Vigevano Pavia 27029",
    "addr:postcode":"27029;27029",
    "iso:country":"IT",
    "sg:address":"27029 Vigevano",
    "sg:city":"Vigevano",
    "sg:orig_category":"Pozzi Neri",
    "sg:phone":"+39 0381 690780",
    "sg:postcode":"27029",
    "sg:province":"Pavia",
    "wof:name":"Spurghi Fratelli Piazza Snc",
    "wof:placetype":"venue"
},
  "geometry": {"coordinates":[8.8354701996,45.3154907227],"type":"Point"}
}