{
  "type": "Feature",
  "properties": {
    "iso:country":"IT",
    "sg:address":"71013 San Giovanni Rotondo",
    "sg:city":"San Giovanni Rotondo",
    "sg:orig_category":"Manufacturers: Prefabbricati",
    "sg:phone":"+39 338 814 2097",
    "sg:postcode":"71013",
    "sg:province":"Foggia",
    "wof:name":"Di Rita Matteo - Stucchi Decorativi",
    "wof:placetype":"venue"
},
  "geometry": {"coordinates":[15.758591,41.673962],"type":"Point"}
}