{
  "type": "Feature",
  "properties": {
    "iso:country":"IT",
    "sg:address":"65125 Pescara",
    "sg:city":"Pescara",
    "sg:orig_category":"Forniture Per Edilizia E Lavori Pubblici",
    "sg:phone":"+39 085 413429",
    "sg:postcode":"65125",
    "sg:province":"Pescara",
    "wof:name":"Rives S.r.l.",
    "wof:placetype":"venue"
},
  "geometry": {"coordinates":[14.1671228409,42.4770927429],"type":"Point"}
}