{
  "type": "Feature",
  "properties": {
    "iso:country":"IT",
    "sg:address":"70022 Altamura",
    "sg:city":"Altamura",
    "sg:orig_category":"Autoclavi",
    "sg:phone":"+39 080 311 8962",
    "sg:postcode":"70022",
    "sg:province":"Bari",
    "wof:name":"Cappiello Michele A. & C. Sas",
    "wof:placetype":"venue"
},
  "geometry": {"coordinates":[16.529202,40.827946],"type":"Point"}
}