{
  "type": "Feature",
  "properties": {
    "iso:country":"IT",
    "sg:address":"70032 Bitonto",
    "sg:city":"Bitonto",
    "sg:classifiers":[
        {
            "category":"Shopping",
            "subcategory":"Computers & Home Electronics",
            "type":"Retail Goods"
        }
    ],
    "sg:phone":"+39 080 374 9928",
    "sg:postcode":"70032",
    "sg:province":"Bari",
    "sg:tags":[
        "personal",
        "ed",
        "accessori"
    ],
    "wof:name":"R.a. Service Di Antonio Di Bari",
    "wof:placetype":"venue"
},
  "geometry": {"coordinates":[16.5937652588,41.0751724243],"type":"Point"}
}