{
  "type": "Feature",
  "properties": {
    "iso:country":"IT",
    "sg:address":"50018 Scandicci",
    "sg:city":"Scandicci",
    "sg:orig_category":"Macchine, Impianti Ed Attrezzature Per Abbigliamento E Pelletterie",
    "sg:phone":"+39 055 731 1219",
    "sg:postcode":"50018",
    "sg:province":"Firenze",
    "wof:name":"2c Di Coveri Srl",
    "wof:placetype":"venue"
},
  "geometry": {"coordinates":[11.150411,43.730701],"type":"Point"}
}