{
  "type": "Feature",
  "properties": {
    "addr:full":"8, Via Eridania 16151 Genova Genova Genova 16151",
    "addr:postcode":"16151;16151",
    "addr:street":"Via Eridania",
    "iso:country":"IT",
    "sg:address":"8, Via Eridania 16151 Genova",
    "sg:city":"Genova",
    "sg:classifiers":[
        {
            "category":"Manufacturing",
            "subcategory":"Metals",
            "type":"Manufacturing & Wholesale Goods"
        }
    ],
    "sg:phone":"+39 39010463463",
    "sg:postcode":"16151",
    "sg:province":"Genova",
    "sg:tags":[
        "metallurgy",
        "metalworking"
    ],
    "wof:name":"Somies (s.r.l.)",
    "wof:placetype":"venue"
},
  "geometry": {"coordinates":[8.882142067,44.4150390625],"type":"Point"}
}