{
  "type": "Feature",
  "properties": {
    "addr:full":"74, Via Bissuola 30100 Venezia VE",
    "addr:postcode":"30100",
    "addr:street":"Via Bissuola;Ve",
    "iso:country":"IT",
    "sg:address":"74, Via Bissuola 30100 Venezia",
    "sg:classifiers":[
        {
            "category":"Shopping",
            "subcategory":"Clothing, Apparel, & Fashions",
            "type":"Retail Goods"
        }
    ],
    "sg:phone":"+39 041 534 1985",
    "sg:province":"VE",
    "sg:tags":[
        "clothes"
    ],
    "wof:name":"Sirema S.r.l.",
    "wof:placetype":"venue"
},
  "geometry": {"coordinates":[12.259459,45.493137],"type":"Point"}
}