{
  "type": "Feature",
  "properties": {
    "iso:country":"IT",
    "sg:address":"06073 Corciano",
    "sg:city":"Corciano",
    "sg:orig_category":"Autofficine E Centri Assistenza",
    "sg:phone":"+39 075 517 8341",
    "sg:postcode":"06073",
    "sg:province":"Perugia",
    "wof:name":"Cdp - De Poi Srl",
    "wof:placetype":"venue"
},
  "geometry": {"coordinates":[12.30172,43.101593],"type":"Point"}
}