{
  "type": "Feature",
  "properties": {
    "iso:country":"IT",
    "sg:address":"92027 Licata",
    "sg:city":"Licata",
    "sg:orig_category":"Macchine, Impianti Ed Attrezzature Per Abbigliamento E Pelletterie. Macchine E Impianti Per Attivita' Commerciali Ed Artigianali",
    "sg:phone":"+39 0922 771514",
    "sg:postcode":"92027",
    "sg:province":"Agrigento",
    "wof:name":"Tecnoservice Siciliana",
    "wof:placetype":"venue"
},
  "geometry": {"coordinates":[13.939025,37.099674],"type":"Point"}
}