{
  "type": "Feature",
  "properties": {
    "iso:country":"IT",
    "sg:address":"20063 Cernusco Sul Naviglio",
    "sg:city":"Cernusco sul Naviglio",
    "sg:orig_category":"Arredamenti - Vendita Al Dettaglio",
    "sg:phone":"+39 02 923 8401",
    "sg:postcode":"20063",
    "sg:province":"Milano",
    "wof:name":"La Casa Di Mastrociliegia\u00ae Snc",
    "wof:placetype":"venue"
},
  "geometry": {"coordinates":[9.330445,45.52179],"type":"Point"}
}