{
  "type": "Feature",
  "properties": {
    "iso:country":"IT",
    "sg:address":"Ctr. Raganzino 97016 Pozzallo",
    "sg:city":"Pozzallo",
    "sg:classifiers":[
        {
            "category":"Autos & Motor Vehicles",
            "subcategory":"Boat Sales",
            "type":"Retail Goods"
        }
    ],
    "sg:phone":"+39 0932 954770",
    "sg:postcode":"97016",
    "sg:province":"Ragusa",
    "sg:website":"http://www.cataniaarredamenti.it",
    "wof:name":"Catania Arredamenti Srl",
    "wof:placetype":"venue"
},
  "geometry": {"coordinates":[14.728503,36.925911],"type":"Point"}
}