{
  "type": "Feature",
  "properties": {
    "iso:country":"IT",
    "sg:address":"76, Via Risorgimento 36050 Sovizzo",
    "sg:city":"Sovizzo",
    "sg:classifiers":[
        {
            "category":"Utilities",
            "subcategory":"Electric",
            "type":"Services"
        }
    ],
    "sg:phone":"+39 0444 551185",
    "sg:postcode":"36050",
    "sg:province":"Vicenza",
    "sg:tags":[
        "component",
        "electronic"
    ],
    "wof:name":"E.m.g. Elettromeccanica S.r.l.",
    "wof:placetype":"venue"
},
  "geometry": {"coordinates":[11.448546,45.524212],"type":"Point"}
}