{
  "type": "Feature",
  "properties": {
    "addr:full":"06073 Corciano Corciano Perugia 06073",
    "addr:postcode":"06073;06073",
    "iso:country":"IT",
    "sg:address":"06073 Corciano",
    "sg:city":"Corciano",
    "sg:orig_category":"Prodotti E Manufatti In Gomma. Forniture Per Attivita' Industriali",
    "sg:phone":"+39 075 506 8032",
    "sg:postcode":"06073",
    "sg:province":"Perugia",
    "sg:website":"http://www.tep.it",
    "wof:name":"T & P Srl",
    "wof:placetype":"venue"
},
  "geometry": {"coordinates":[12.2892217636,43.1093521118],"type":"Point"}
}