{
  "type": "Feature",
  "properties": {
    "iso:country":"IT",
    "sg:address":"19, Via Don G. Minzoni 23844 Sirone",
    "sg:city":"Sirone",
    "sg:classifiers":[
        {
            "category":"Manufacturing",
            "subcategory":"Glass & Minerals",
            "type":"Manufacturing & Wholesale Goods"
        }
    ],
    "sg:phone":"+39 39031850058",
    "sg:postcode":"23844",
    "sg:province":"Lecco",
    "sg:tags":[
        "building",
        "material"
    ],
    "wof:name":"Ce.si. (s.p.a.)",
    "wof:placetype":"venue"
},
  "geometry": {"coordinates":[9.375941,45.788578],"type":"Point"}
}