{
  "type": "Feature",
  "properties": {
    "iso:country":"IT",
    "sg:address":"Via Caprera 23 21052 Busto Arsizio",
    "sg:city":"Busto Arsizio",
    "sg:orig_category":"Blousons",
    "sg:phone":"+39 0331 622844",
    "sg:postcode":"21052",
    "sg:province":"Varese",
    "sg:website":"www.oxxy.it",
    "wof:name":"Oxxy Srl",
    "wof:placetype":"venue"
},
  "geometry": {"coordinates":[8.857197,45.618946],"type":"Point"}
}