{
  "type": "Feature",
  "properties": {
    "iso:country":"IT",
    "sg:address":"22, V. Cavo 43037 Lesignano De' Bagni",
    "sg:classifiers":[
        {
            "category":"Food & Beverages",
            "subcategory":"Groceries & Convenience Stores",
            "type":"Retail Goods"
        }
    ],
    "sg:phone":"+39 0521 853830",
    "sg:postcode":"43037",
    "sg:province":"Parma",
    "sg:tags":[
        "product",
        "related"
    ],
    "sg:website":"http://www.la-badia.com",
    "wof:name":"La Badia Spa",
    "wof:placetype":"venue"
},
  "geometry": {"coordinates":[10.2670841217,44.6003417969],"type":"Point"}
}