{
  "type": "Feature",
  "properties": {
    "iso:country":"IT",
    "sg:address":"07100 Sassari",
    "sg:city":"Sassari",
    "sg:classifiers":[
        {
            "category":"Health Services",
            "subcategory":"Health Practitioner",
            "type":"Services"
        }
    ],
    "sg:phone":"+39 079 397427",
    "sg:postcode":"07100",
    "sg:province":"Sassari",
    "sg:tags":[
        "medici"
    ],
    "wof:name":"Schena Giampaolo",
    "wof:placetype":"venue"
},
  "geometry": {"coordinates":[8.3745718002,40.7555809021],"type":"Point"}
}