{
  "type": "Feature",
  "properties": {
    "iso:country":"IT",
    "sg:address":"20090 Buccinasco",
    "sg:city":"Buccinasco",
    "sg:orig_category":"Macchine, Impianti Ed Attrezzature Per Abbigliamento E Pelletterie",
    "sg:phone":"+39 02 4570 8400",
    "sg:postcode":"20090",
    "sg:province":"Milano",
    "wof:name":"Co.m.i.l. Di Roberto De Angiolini & C. (s.n.c.)",
    "wof:placetype":"venue"
},
  "geometry": {"coordinates":[9.114756,45.41069],"type":"Point"}
}