{
  "type": "Feature",
  "properties": {
    "addr:full":"00162 Roma Roma Roma 00162",
    "addr:postcode":"00162;00162",
    "iso:country":"IT",
    "sg:address":"00162 Roma",
    "sg:city":"Roma",
    "sg:classifiers":[
        {
            "category":"Health Services",
            "subcategory":"Health Practitioner",
            "type":"Services"
        }
    ],
    "sg:phone":"+39 06 8530 1902",
    "sg:postcode":"00162",
    "sg:province":"Roma",
    "sg:tags":[
        "medici"
    ],
    "wof:name":"Anania Francesco",
    "wof:placetype":"venue"
},
  "geometry": {"coordinates":[12.4933357239,41.889957428],"type":"Point"}
}