{
  "type": "Feature",
  "properties": {
    "iso:country":"IT",
    "sg:address":"21100 Varese",
    "sg:city":"Varese",
    "sg:orig_category":"Non-classified Establishments",
    "sg:phone":"+39 0332 283990",
    "sg:postcode":"21100",
    "sg:province":"Varese",
    "sg:website":"http://www.arredo-design.it",
    "wof:name":"Arredo Design Srl",
    "wof:placetype":"venue"
},
  "geometry": {"coordinates":[8.830729,45.814442],"type":"Point"}
}