{
  "type": "Feature",
  "properties": {
    "addr:full":"00128 Roma Roma Roma 00128",
    "addr:postcode":"00128;00128",
    "iso:country":"IT",
    "sg:address":"00128 Roma",
    "sg:city":"Roma",
    "sg:orig_category":"Pubblica Amministrazione",
    "sg:phone":"+39 06 507751",
    "sg:postcode":"00128",
    "sg:province":"Roma",
    "wof:name":"Commissariato Coordinato - Caserma Spinaceto",
    "wof:placetype":"venue"
},
  "geometry": {"coordinates":[12.4419546127,41.7874908447],"type":"Point"}
}