{
  "type": "Feature",
  "properties": {
    "iso:country":"IT",
    "sg:address":"14, Via F.lli Cervi 25030 Roncadelle",
    "sg:city":"Roncadelle",
    "sg:classifiers":[
        {
            "category":"Manufacturing",
            "subcategory":"Wood Products",
            "type":"Manufacturing & Wholesale Goods"
        }
    ],
    "sg:phone":"+39 030 278 0193",
    "sg:postcode":"25030",
    "sg:province":"Brescia",
    "sg:tags":[
        "furniture"
    ],
    "wof:name":"A.m.a.",
    "wof:placetype":"venue"
},
  "geometry": {"coordinates":[10.159681,45.530285],"type":"Point"}
}