{
  "type": "Feature",
  "properties": {
    "addr:full":"10147 Torino Torino Torino 10147",
    "addr:postcode":"10147;10147",
    "iso:country":"IT",
    "sg:address":"10147 Torino",
    "sg:city":"Torino",
    "sg:orig_category":"Prodotti Alimentari",
    "sg:phone":"+39 011 252211",
    "sg:postcode":"10147",
    "sg:province":"Torino",
    "wof:name":"Perruquet Cipriano",
    "wof:placetype":"venue"
},
  "geometry": {"coordinates":[7.6763076782,45.095161438],"type":"Point"}
}