{
  "type": "Feature",
  "properties": {
    "addr:full":"191, Via Puccini Giacomo 50041 Calenzano Calenzano Firenze 50041",
    "addr:housenumber":"191",
    "addr:postcode":"50041;50041",
    "addr:street":"Via Puccini Giacomo",
    "iso:country":"IT",
    "sg:address":"191, Via Puccini Giacomo 50041 Calenzano",
    "sg:city":"Calenzano",
    "sg:classifiers":[
        {
            "category":"Professional",
            "subcategory":"Engineering",
            "type":"Services"
        }
    ],
    "sg:phone":"+39 055 887 9549",
    "sg:postcode":"50041",
    "sg:province":"Firenze",
    "sg:tags":[
        "machine",
        "-",
        "mechanical"
    ],
    "wof:name":"Tortelli Impianti S.r.l.",
    "wof:placetype":"venue"
},
  "geometry": {"coordinates":[11.209051,43.826786],"type":"Point"}
}