{
  "type": "Feature",
  "properties": {
    "iso:country":"IT",
    "sg:address":"21, Viale Lombardia 21052 Busto Arsizio",
    "sg:city":"Busto Arsizio",
    "sg:classifiers":[
        {
            "category":"Wholesale",
            "subcategory":"Drugs",
            "type":"Manufacturing & Wholesale Goods"
        }
    ],
    "sg:phone":"+39 0331 323122",
    "sg:postcode":"21052",
    "sg:province":"Varese",
    "sg:tags":[
        "chemical",
        "pharmaceutical"
    ],
    "wof:name":"Omeftech Srl",
    "wof:placetype":"venue"
},
  "geometry": {"coordinates":[8.862957,45.609211],"type":"Point"}
}