{
  "type": "Feature",
  "properties": {
    "addr:full":"45021 Badia Polesine Badia Polesine Rovigo 45021",
    "addr:postcode":"45021;45021",
    "iso:country":"IT",
    "sg:address":"45021 Badia Polesine",
    "sg:city":"Badia Polesine",
    "sg:orig_category":"Articoli Da Regalo. Tempo Libero - Articoli E Forniture. Regalistica Aziendale",
    "sg:phone":"+39 0425 51479",
    "sg:postcode":"45021",
    "sg:province":"Rovigo",
    "wof:name":"Tecnoprint Di Mora Geom. Alessandro",
    "wof:placetype":"venue"
},
  "geometry": {"coordinates":[11.488617,45.098663],"type":"Point"}
}