{
  "type": "Feature",
  "properties": {
    "iso:country":"IT",
    "sg:address":"37131 Verona",
    "sg:city":"Verona",
    "sg:orig_category":"Gioielleria, Oreficeria E Argenteria",
    "sg:phone":"+39 045 520805",
    "sg:postcode":"37131",
    "sg:province":"Verona",
    "wof:name":"Tonon Alessandro",
    "wof:placetype":"venue"
},
  "geometry": {"coordinates":[11.034604,45.450417],"type":"Point"}
}