{
  "type": "Feature",
  "properties": {
    "iso:country":"IT",
    "sg:address":"20, Via Camillo Cavour 13894 Gaglianico",
    "sg:city":"Gaglianico",
    "sg:classifiers":[
        {
            "category":"Manufacturing",
            "subcategory":"Metals",
            "type":"Manufacturing & Wholesale Goods"
        }
    ],
    "sg:phone":"+39 390 153 5921",
    "sg:postcode":"13894",
    "sg:province":"Biella",
    "sg:tags":[
        "metallurgy",
        "metalworking"
    ],
    "wof:name":"Mosca S.r.l.",
    "wof:placetype":"venue"
},
  "geometry": {"coordinates":[8.050406456,45.5698471069],"type":"Point"}
}