{
  "type": "Feature",
  "properties": {
    "addr:full":"20154 Milano Milano Milano 20154",
    "addr:postcode":"20154;20154",
    "iso:country":"IT",
    "sg:address":"20154 Milano",
    "sg:city":"Milano",
    "sg:orig_category":"Servizi Culturali E Per Lo Spettacolo. Musica",
    "sg:phone":"+39 02 318 0841",
    "sg:postcode":"20154",
    "sg:province":"Milano",
    "wof:name":"Best Sound S.r.l.",
    "wof:placetype":"venue"
},
  "geometry": {"coordinates":[9.171674,45.482246],"type":"Point"}
}