{
  "type": "Feature",
  "properties": {
    "iso:country":"IT",
    "sg:address":"20121 Milano",
    "sg:city":"Milano",
    "sg:orig_category":"Arredi Ed Attrezzature Per Uffici",
    "sg:phone":"+39 02 659 9369",
    "sg:postcode":"20121",
    "sg:province":"Milano",
    "wof:name":"Univec (s.r.l.)",
    "wof:placetype":"venue"
},
  "geometry": {"coordinates":[9.186193,45.476967],"type":"Point"}
}