{
  "type": "Feature",
  "properties": {
    "iso:country":"IT",
    "sg:address":"30016 Jesolo",
    "sg:orig_category":"Bagno - Accessori E Mobili",
    "sg:phone":"+39 0421 951343",
    "sg:postcode":"30016",
    "sg:province":"Venezia",
    "wof:name":"Catto Fratelli Di Catto Sergio & C. Snc",
    "wof:placetype":"venue"
},
  "geometry": {"coordinates":[12.624053,45.537151],"type":"Point"}
}