{
  "type": "Feature",
  "properties": {
    "addr:full":"13816 Miagliano Miagliano Biella 13816",
    "addr:housenumber":"13816",
    "addr:postcode":"13816",
    "addr:street":"Miagliano Miagliano",
    "iso:country":"IT",
    "sg:address":"13816 Miagliano",
    "sg:city":"Miagliano",
    "sg:orig_category":"Legno E Semilavorati",
    "sg:phone":"+39 015 471593",
    "sg:postcode":"13816",
    "sg:province":"Biella",
    "wof:name":"Recanzone Franco",
    "wof:placetype":"venue"
},
  "geometry": {"coordinates":[8.045537,45.614231],"type":"Point"}
}