{
  "type": "Feature",
  "properties": {
    "iso:country":"IT",
    "sg:address":"86170 Isernia",
    "sg:city":"Isernia",
    "sg:orig_category":"Arredamenti - Vendita Al Dettaglio",
    "sg:phone":"+39 0865 410250",
    "sg:postcode":"86170",
    "sg:province":"Isernia",
    "wof:name":"Interni Srl",
    "wof:placetype":"venue"
},
  "geometry": {"coordinates":[14.204716,41.597485],"type":"Point"}
}