{
  "type": "Feature",
  "properties": {
    "iso:country":"IT",
    "sg:address":"Corso Della Repubblica 14; Forli; 47100",
    "sg:classifiers":[
        {
            "category":"Banks & Credit Unions",
            "subcategory":"Bank",
            "type":"Services"
        }
    ],
    "sg:phone":"+39 0543 711111",
    "sg:postcode":"47100",
    "sg:province":"Forl\u00ec-Cesena",
    "wof:name":"Cassa Di Risparmio Di Forli Spa",
    "wof:placetype":"venue"
},
  "geometry": {"coordinates":[12.042065,44.221478],"type":"Point"}
}