{
  "type": "Feature",
  "properties": {
    "iso:country":"IT",
    "sg:address":"31038 Paese",
    "sg:city":"Paese",
    "sg:orig_category":"Informatica - Consulenza E Servizi. Automazione E Macchine Per Ufficio. Servizi Ausiliari Di Analisi, Controllo E Ricerca. Servizi Per Aziende, Manifestazioni E Supporto Agli Scambi Commerciali",
    "sg:phone":"+39 0422 484528",
    "sg:postcode":"31038",
    "sg:province":"Treviso",
    "sg:website":"http://www.tredservice.com",
    "wof:name":"3d Service Srl",
    "wof:placetype":"venue"
},
  "geometry": {"coordinates":[12.141704,45.676174],"type":"Point"}
}