{
  "type": "Feature",
  "properties": {
    "iso:country":"IT",
    "sg:address":"15, V. Mattiuli 80047 San Giuseppe Vesuviano",
    "sg:city":"San Giuseppe Vesuviano",
    "sg:classifiers":[
        {
            "category":"Shopping",
            "subcategory":"Crafts & Fabrics",
            "type":"Retail Goods"
        }
    ],
    "sg:phone":"+39 081 529 8148",
    "sg:postcode":"80047",
    "sg:province":"Napoli",
    "sg:website":"http://www.angelocarillo.com",
    "wof:name":"Angelo Carillo & C. Spa",
    "wof:placetype":"venue"
},
  "geometry": {"coordinates":[14.4976463318,40.8226699829],"type":"Point"}
}