{
  "type": "Feature",
  "properties": {
    "addr:full":"20129 Milano Milano Milano 20129",
    "addr:postcode":"20129;20129",
    "iso:country":"IT",
    "sg:address":"20129 Milano",
    "sg:city":"Milano",
    "sg:orig_category":"Hobbistica",
    "sg:phone":"+39 02 781919",
    "sg:postcode":"20129",
    "sg:province":"Milano",
    "wof:name":"Euronummus",
    "wof:placetype":"venue"
},
  "geometry": {"coordinates":[9.205812,45.469368],"type":"Point"}
}