{
  "type": "Feature",
  "properties": {
    "iso:country":"IT",
    "sg:address":"Contrada Pietra Di Roma, 98070 Torrenova",
    "sg:city":"Torrenova",
    "sg:classifiers":[
        {
            "category":"Farming",
            "subcategory":"Fish & Marine Products",
            "type":"Manufacturing & Wholesale Goods"
        }
    ],
    "sg:phone":"+39 0941 785391",
    "sg:postcode":"98070",
    "sg:province":"Messina",
    "sg:tags":[
        "pickled",
        "salted"
    ],
    "wof:name":"Castrovinci Srl",
    "wof:placetype":"venue"
},
  "geometry": {"coordinates":[14.6889286041,38.1003036499],"type":"Point"}
}