{
  "type": "Feature",
  "properties": {
    "addr:full":"15100 Alessandria Alessandria Alessandria 15100",
    "addr:postcode":"15100;15100",
    "iso:country":"IT",
    "sg:address":"15100 Alessandria",
    "sg:city":"Alessandria",
    "sg:orig_category":"Ricambi E Componenti Dei Mezzi Di Trasporto",
    "sg:phone":"+39 0131 445148",
    "sg:postcode":"15100",
    "sg:province":"Alessandria",
    "wof:name":"Mandirola Enzo Di Mandirola Bruno",
    "wof:placetype":"venue"
},
  "geometry": {"coordinates":[8.692655,44.92038],"type":"Point"}
}