{
  "type": "Feature",
  "properties": {
    "iso:country":"IT",
    "sg:address":"04017 San Felice Circeo",
    "sg:city":"San Felice Circeo",
    "sg:orig_category":"Manufacturers: Prefabbricati. Servizi E Lavori Per Ecologia E Smaltimento Rifiuti",
    "sg:phone":"+39 0773 540400",
    "sg:postcode":"04017",
    "sg:province":"Latina",
    "wof:name":"Egidi Leonello",
    "wof:placetype":"venue"
},
  "geometry": {"coordinates":[13.093317,41.259476],"type":"Point"}
}