{
  "type": "Feature",
  "properties": {
    "addr:full":"84085 Sant'angelo Salerno 84085",
    "addr:postcode":"84085;84085",
    "iso:country":"IT",
    "sg:address":"84085 Sant'angelo",
    "sg:orig_category":"Prodotti Chimici Secondari. Tempo Libero - Articoli E Forniture. Servizi Per Lo Sport E Il Tempo Libero. Servizi Per Aziende, Manifestazioni E Supporto Agli Scambi Commerciali",
    "sg:phone":"+39 089 893297",
    "sg:postcode":"84085",
    "sg:province":"Salerno",
    "wof:name":"Viviano (s.n.c.)",
    "wof:placetype":"venue"
},
  "geometry": {"coordinates":[14.765912056,40.6779556274],"type":"Point"}
}