{
  "type": "Feature",
  "properties": {
    "iso:country":"IT",
    "sg:address":"20144 Milano",
    "sg:city":"Milano",
    "sg:orig_category":"Cinematografia E Radiotelevisione. Pubblicita', Marketing E Comunicazione",
    "sg:phone":"+39 02 831 0551",
    "sg:postcode":"20144",
    "sg:province":"Milano",
    "sg:website":"http://www.goettsche.it",
    "wof:name":"La Nuova Agenzia Di Michael G\u00d6ttsche",
    "wof:placetype":"venue"
},
  "geometry": {"coordinates":[9.168574,45.453724],"type":"Point"}
}