{
  "type": "Feature",
  "properties": {
    "iso:country":"IT",
    "sg:address":"13, Via Giuseppe Parini 22077 Olgiate Comasco",
    "sg:city":"Olgiate Comasco",
    "sg:classifiers":[
        {
            "category":"Shopping",
            "subcategory":"Crafts & Fabrics",
            "type":"Retail Goods"
        }
    ],
    "sg:phone":"+39 39031944162",
    "sg:postcode":"22077",
    "sg:province":"Como",
    "wof:name":"A.t.a.m. Marazzi S.r.l.",
    "wof:placetype":"venue"
},
  "geometry": {"coordinates":[9.0309410095,45.8069076538],"type":"Point"}
}