{
  "type": "Feature",
  "properties": {
    "iso:country":"IT",
    "sg:address":"19123 La Spezia",
    "sg:orig_category":"Lavanderie Industriali E Noleggio Biancheria",
    "sg:phone":"+39 0187 713918",
    "sg:province":"SP",
    "wof:name":"Lavanderia Express Di Russo Agostino",
    "wof:placetype":"venue"
},
  "geometry": {"coordinates":[9.802713,44.107941],"type":"Point"}
}