{
  "type": "Feature",
  "properties": {
    "iso:country":"IT",
    "sg:address":"24, Viale Della Repubblica 47014 Meldola",
    "sg:city":"Meldola",
    "sg:classifiers":[
        {
            "category":"Building & Trades",
            "subcategory":"Construction",
            "type":"Services"
        }
    ],
    "sg:phone":"+39 0543 490174",
    "sg:postcode":"47014",
    "sg:province":"Forl\u00ec-Cesena",
    "sg:tags":[
        "work",
        "public"
    ],
    "wof:name":"C.i.a.s.-consorzio Italiano Acquisti Sportivi",
    "wof:placetype":"venue"
},
  "geometry": {"coordinates":[12.064441,44.126934],"type":"Point"}
}