{
  "type": "Feature",
  "properties": {
    "iso:country":"IT",
    "sg:address":"135, V. Iv Novembre 35047 Solesino",
    "sg:city":"Solesino",
    "sg:classifiers":[
        {
            "category":"Sports & Exercise",
            "subcategory":"Playing Field",
            "type":"Entertainment"
        }
    ],
    "sg:phone":"+39 0429 709456",
    "sg:postcode":"35047",
    "sg:province":"Padova",
    "sg:tags":[
        "game"
    ],
    "sg:website":"http://www.thomasgicattoli.com:ws_end: :mark:ws:http://www.paginegialle.it/thomassnc",
    "wof:name":"Thomas Snc",
    "wof:placetype":"venue"
},
  "geometry": {"coordinates":[11.876589,45.409569],"type":"Point"}
}