{
  "type": "Feature",
  "properties": {
    "iso:country":"IT",
    "sg:address":"05014 Castel Viscardo",
    "sg:city":"Castel Viscardo",
    "sg:orig_category":"Non-classified Establishments",
    "sg:phone":"+39 0763 361656",
    "sg:postcode":"05014",
    "sg:province":"Terni",
    "sg:website":"http://www.calandrelli.it",
    "wof:name":"Artigiano Del Cotto",
    "wof:placetype":"venue"
},
  "geometry": {"coordinates":[11.987629,42.745274],"type":"Point"}
}