{
  "type": "Feature",
  "properties": {
    "iso:country":"IT",
    "sg:address":"70021 Acquaviva Delle Fonti",
    "sg:city":"Acquaviva delle Fonti",
    "sg:classifiers":[
        {
            "category":"Manufacturing",
            "subcategory":"Leather Goods",
            "type":"Manufacturing & Wholesale Goods"
        }
    ],
    "sg:phone":"+39 080 775355",
    "sg:postcode":"70021",
    "sg:province":"Bari",
    "sg:tags":[
        "goods",
        "clothing",
        "supply"
    ],
    "wof:name":"Ricicplast Srl",
    "wof:placetype":"venue"
},
  "geometry": {"coordinates":[16.862993,40.882168],"type":"Point"}
}