{
  "type": "Feature",
  "properties": {
    "addr:full":"89029 Taurianova Taurianova Reggio Di Calabria 89029",
    "addr:postcode":"89029;89029",
    "iso:country":"IT",
    "sg:address":"89029 Taurianova",
    "sg:city":"Taurianova",
    "sg:orig_category":"Dolciumi E Gelati",
    "sg:phone":"+39 0966 643302",
    "sg:postcode":"89029",
    "sg:province":"Reggio Di Calabria",
    "wof:name":"Scarf\u00d2 Agostino",
    "wof:placetype":"venue"
},
  "geometry": {"coordinates":[16.209755,39.50251],"type":"Point"}
}