{
  "type": "Feature",
  "properties": {
    "addr:full":"6, Via L. Da Vinci 42027 Montecchio Emilia Reggio Nell'Emilia 42027",
    "addr:postcode":"42027;42027",
    "addr:street":"Via L. Da Vinci",
    "iso:country":"IT",
    "sg:address":"6, Via L. Da Vinci 42027 Montecchio Emilia",
    "sg:classifiers":[
        {
            "category":"Wholesale",
            "subcategory":"Drugs",
            "type":"Manufacturing & Wholesale Goods"
        }
    ],
    "sg:phone":"+39 0522 864860",
    "sg:postcode":"42027",
    "sg:province":"Reggio Nell'Emilia",
    "sg:tags":[
        "chemical",
        "pharmaceutical"
    ],
    "wof:name":"Damiani Colorificio",
    "wof:placetype":"venue"
},
  "geometry": {"coordinates":[10.627794,44.696228],"type":"Point"}
}