{
  "type": "Feature",
  "properties": {
    "iso:country":"IT",
    "sg:address":"27049 Stradella",
    "sg:city":"Stradella",
    "sg:orig_category":"Forniture Alberghi, Bar, Ristoranti E Comunita'",
    "sg:phone":"+39 0385 48886",
    "sg:postcode":"27049",
    "sg:province":"Pavia",
    "sg:website":"http://www.gruppocontinental.it",
    "wof:name":"Continental Snc",
    "wof:placetype":"venue"
},
  "geometry": {"coordinates":[9.3050460815,45.0781211853],"type":"Point"}
}