{
  "type": "Feature",
  "properties": {
    "iso:country":"IT",
    "sg:address":"40/a, V. Berardi 74100 Taranto",
    "sg:city":"Taranto",
    "sg:classifiers":[
        {
            "category":"Manufacturing",
            "subcategory":"Food",
            "type":"Manufacturing & Wholesale Goods"
        }
    ],
    "sg:phone":"+39 099 453 8547",
    "sg:postcode":"74100",
    "sg:province":"Taranto",
    "sg:tags":[
        "equipment",
        "processing",
        "-",
        "machinery"
    ],
    "sg:website":"http://www.paginegialle.it/distribuzioneitalia",
    "wof:name":"Distribuzione Italia Srl",
    "wof:placetype":"venue"
},
  "geometry": {"coordinates":[17.2425785065,40.4696578979],"type":"Point"}
}