{
  "type": "Feature",
  "properties": {
    "iso:country":"IT",
    "sg:address":"62100 Macerata",
    "sg:city":"Macerata",
    "sg:orig_category":"Edilizia - Materiali",
    "sg:phone":"+39 0733 292184",
    "sg:postcode":"62100",
    "sg:province":"Macerata",
    "wof:name":"Pizzichini Iolanda - Ferramenta Marcolini",
    "wof:placetype":"venue"
},
  "geometry": {"coordinates":[13.491252,43.278057],"type":"Point"}
}