{
  "type": "Feature",
  "properties": {
    "iso:country":"IT",
    "sg:address":"135/11, Str. Del Francese 10156 Torino",
    "sg:city":"Torino",
    "sg:classifiers":[
        {
            "category":"Professional",
            "subcategory":"Engineering",
            "type":"Services"
        }
    ],
    "sg:phone":"+39 011 470 2145",
    "sg:postcode":"10156",
    "sg:province":"Torino",
    "sg:tags":[
        "machine",
        "-",
        "mechanical"
    ],
    "sg:website":"http://www.iami.it:ws_end: :mark:ws:http://www.paginegialle.it/i.a.m.i.srl",
    "wof:name":"I.a.m.i. Srl",
    "wof:placetype":"venue"
},
  "geometry": {"coordinates":[7.672231,45.134182],"type":"Point"}
}