{
  "type": "Feature",
  "properties": {
    "iso:country":"IT",
    "sg:address":"192, Via Piave 21057 Olgiate Olona",
    "sg:city":"Olgiate Olona",
    "sg:classifiers":[
        {
            "category":"Shopping",
            "subcategory":"Clothing, Apparel, & Fashions",
            "type":"Retail Goods"
        }
    ],
    "sg:phone":"+39 0331 633214",
    "sg:postcode":"21057",
    "sg:province":"Varese",
    "sg:tags":[
        "clothes"
    ],
    "wof:name":"Maglificio Gi.al.va.tex. (s.r.l.)",
    "wof:placetype":"venue"
},
  "geometry": {"coordinates":[8.867393,45.622196],"type":"Point"}
}