{
  "type": "Feature",
  "properties": {
    "addr:full":"276, Viale Della Unita' D'italia 66100 Chieti Chieti Chieti 66100",
    "addr:postcode":"66100;66100",
    "addr:street":"Viale Della Unita ' D'Italia",
    "iso:country":"IT",
    "sg:address":"276, Viale Della Unita' D'italia 66100 Chieti",
    "sg:city":"Chieti",
    "sg:classifiers":[
        {
            "category":"Retail",
            "subcategory":"Animal Services",
            "type":"Services"
        }
    ],
    "sg:phone":"+39 0871 560726",
    "sg:postcode":"66100",
    "sg:province":"Chieti",
    "sg:tags":[
        "breeding"
    ],
    "wof:name":"Ponterosa Srl",
    "wof:placetype":"venue"
},
  "geometry": {"coordinates":[14.150384,42.379532],"type":"Point"}
}