{
  "type": "Feature",
  "properties": {
    "iso:country":"IT",
    "sg:address":"83029 Solofra",
    "sg:city":"Solofra",
    "sg:orig_category":"Servizi E Lavori Per Abbigliamento E Pelletterie",
    "sg:phone":"+39 0825 534616",
    "sg:postcode":"83029",
    "sg:province":"Avellino",
    "wof:name":"Seven Stars Group Spa",
    "wof:placetype":"venue"
},
  "geometry": {"coordinates":[14.832609,40.834755],"type":"Point"}
}