{
  "type": "Feature",
  "properties": {
    "addr:full":"15020 Murisengo Murisengo Alessandria 15020",
    "addr:postcode":"15020;15020",
    "iso:country":"IT",
    "sg:address":"15020 Murisengo",
    "sg:city":"Murisengo",
    "sg:classifiers":[
        {
            "category":"Health Services",
            "subcategory":"Health Practitioner",
            "type":"Services"
        }
    ],
    "sg:phone":"+39 0141 693100",
    "sg:postcode":"15020",
    "sg:province":"Alessandria",
    "sg:tags":[
        "medici"
    ],
    "wof:name":"Ferrero Paolo",
    "wof:placetype":"venue"
},
  "geometry": {"coordinates":[8.613145,44.909313],"type":"Point"}
}