{
  "type": "Feature",
  "properties": {
    "addr:full":"62027 San Severino Marche San Severino Marche Macerata 62027",
    "addr:housenumber":"62027",
    "addr:postcode":"marche san;62027",
    "iso:country":"IT",
    "sg:address":"62027 San Severino Marche",
    "sg:city":"San Severino Marche",
    "sg:orig_category":"Automobili - Commercio",
    "sg:phone":"+39 0733 638358",
    "sg:postcode":"62027",
    "sg:province":"Macerata",
    "sg:website":"http://www.autovass.it",
    "wof:name":"Autovass Srl",
    "wof:placetype":"venue"
},
  "geometry": {"coordinates":[13.189713,43.234142],"type":"Point"}
}