{
  "type": "Feature",
  "properties": {
    "iso:country":"IT",
    "sg:address":"Via Varese 28; Mozzate; 22076",
    "sg:city":"Mozzate",
    "sg:classifiers":[
        {
            "category":"Banks & Credit Unions",
            "subcategory":"Bank",
            "type":"Services"
        }
    ],
    "sg:phone":"+39 0331 830190",
    "sg:postcode":"22076",
    "sg:province":"Como",
    "wof:name":"Istituto Bancario, San Paolo Di Torino Spa",
    "wof:placetype":"venue"
},
  "geometry": {"coordinates":[8.954934,45.672626],"type":"Point"}
}