{
  "type": "Feature",
  "properties": {
    "iso:country":"IT",
    "sg:address":"Via S. Carlo 8/20, Modena, Mo",
    "sg:classifiers":[
        {
            "category":"Banks & Credit Unions",
            "subcategory":"Bank",
            "type":"Services"
        }
    ],
    "wof:name":"Em Ro Popolare Spa",
    "wof:placetype":"venue"
},
  "geometry": {"coordinates":[10.927325,44.645744],"type":"Point"}
}