{
  "type": "Feature",
  "properties": {
    "iso:country":"IT",
    "sg:address":"37050 Belfiore",
    "sg:city":"Belfiore",
    "sg:orig_category":"Forniture Industriali Per Prevenzione, Controllo E Sicurezza",
    "sg:phone":"+39 045 764 0876",
    "sg:postcode":"37050",
    "sg:province":"Verona",
    "wof:name":"Micheletti Alberto",
    "wof:placetype":"venue"
},
  "geometry": {"coordinates":[11.1555099487,45.4178657532],"type":"Point"}
}