{
  "type": "Feature",
  "properties": {
    "iso:country":"IT",
    "sg:address":"00040 Montecompatri",
    "sg:city":"Montecompatri",
    "sg:orig_category":"Istituti Di Bellezza",
    "sg:phone":"+39 06 948 5498",
    "sg:postcode":"00040",
    "sg:province":"Roma",
    "wof:name":"Miani Elisabetta",
    "wof:placetype":"venue"
},
  "geometry": {"coordinates":[12.726682,41.804913],"type":"Point"}
}