{
  "type": "Feature",
  "properties": {
    "iso:country":"IT",
    "sg:address":"Regione Bagnoli 15011 Acqui Terme",
    "sg:city":"Acqui Terme",
    "sg:classifiers":[
        {
            "category":"Professional",
            "subcategory":"Engineering",
            "type":"Services"
        }
    ],
    "sg:phone":"+39 0144 356440",
    "sg:postcode":"15011",
    "sg:province":"Alessandria",
    "sg:tags":[
        "machine",
        "-",
        "mechanical"
    ],
    "wof:name":"Automazione Industriale B.r.c. S.p.a.",
    "wof:placetype":"venue"
},
  "geometry": {"coordinates":[8.481886,44.664989],"type":"Point"}
}