{
  "type": "Feature",
  "properties": {
    "iso:country":"IT",
    "sg:address":"2, Contrada Madonna Di Loreto 01038 Soriano Nel Cimino",
    "sg:city":"Soriano nel Cimino",
    "sg:classifiers":[
        {
            "category":"Home & Garden",
            "subcategory":"Home Furnishings",
            "type":"Retail Goods"
        }
    ],
    "sg:phone":"+39 0761 748700",
    "sg:postcode":"01038",
    "sg:province":"Viterbo",
    "sg:tags":[
        "household"
    ],
    "wof:name":"Pf Di Faccenda Paolo",
    "wof:placetype":"venue"
},
  "geometry": {"coordinates":[12.104854,42.417381],"type":"Point"}
}