{
  "type": "Feature",
  "properties": {
    "iso:country":"IT",
    "sg:address":"5, Via Crevalcore 40017 San Giovanni In Persiceto",
    "sg:city":"San Giovanni in Persiceto",
    "sg:classifiers":[
        {
            "category":"Professional",
            "subcategory":"Computer Services",
            "type":"Services"
        }
    ],
    "sg:phone":"+39 39051826336",
    "sg:postcode":"40017",
    "sg:province":"Bologna",
    "sg:tags":[
        "information",
        "technology"
    ],
    "wof:name":"Optima Srl",
    "wof:placetype":"venue"
},
  "geometry": {"coordinates":[11.184105,44.645508],"type":"Point"}
}