{
  "type": "Feature",
  "properties": {
    "iso:country":"IT",
    "sg:address":"16124 Genova",
    "sg:city":"Genova",
    "sg:orig_category":"Servizi Culturali E Per Lo Spettacolo. Servizi Al Turismo. Acqua, Luce, Gas E Societa' Di Esercizio Pubblico",
    "sg:phone":"+39 010 246 2051",
    "sg:postcode":"16124",
    "sg:province":"Genova",
    "wof:name":"Biblioteca Italiana Per Ciechi Regina Margherita Onlus",
    "wof:placetype":"venue"
},
  "geometry": {"coordinates":[8.934572,44.411659],"type":"Point"}
}