{
  "type": "Feature",
  "properties": {
    "iso:country":"IT",
    "sg:address":"33098 San Martino Al Tagliamento",
    "sg:city":"San Martino al Tagliamento",
    "sg:orig_category":"Prodotti E Manufatti In Materie Plastiche. Articoli Per Imballaggio E Confezionamento",
    "sg:phone":"+39 0434 88021",
    "sg:postcode":"33098",
    "sg:province":"Pordenone",
    "wof:name":"Ge-pack S.r.l.",
    "wof:placetype":"venue"
},
  "geometry": {"coordinates":[12.8732938766,46.0126342773],"type":"Point"}
}