{
  "type": "Feature",
  "properties": {
    "iso:country":"IT",
    "sg:address":"75100 Matera",
    "sg:city":"Matera",
    "sg:orig_category":"Arredamenti E Mobili Professionali",
    "sg:phone":"+39 0835 335375",
    "sg:postcode":"75100",
    "sg:province":"Matera",
    "sg:website":"http://www.arredi.it",
    "wof:name":"Centro Studi Arredamento Srl",
    "wof:placetype":"venue"
},
  "geometry": {"coordinates":[16.593126,40.667709],"type":"Point"}
}