{
  "type": "Feature",
  "properties": {
    "iso:country":"IT",
    "sg:address":"65, V. Torino 95045 Misterbianco Lineri",
    "sg:city":"Misterbianco",
    "sg:classifiers":[
        {
            "category":"Manufacturing",
            "subcategory":"Rubber & Plastics",
            "type":"Manufacturing & Wholesale Goods"
        }
    ],
    "sg:phone":"+39 39095476520",
    "sg:postcode":"95045",
    "sg:province":"Catania",
    "sg:website":"http://www.ompstampi.it",
    "wof:name":"Omp Stampi Srl",
    "wof:placetype":"venue"
},
  "geometry": {"coordinates":[15.0360212326,37.5187911987],"type":"Point"}
}