{
  "type": "Feature",
  "properties": {
    "iso:country":"IT",
    "sg:address":"Via Bruino 42 10040 Rivalta Di Torino",
    "sg:city":"Rivalta di Torino",
    "sg:classifiers":[
        {
            "category":"Wholesale",
            "subcategory":"Machinery & Supplies",
            "type":"Manufacturing & Wholesale Goods"
        }
    ],
    "sg:phone":"+39 011 903 1461",
    "sg:postcode":"10040",
    "sg:province":"Torino",
    "sg:tags":[
        "pin",
        "clevis"
    ],
    "wof:name":"Litmat Spa",
    "wof:placetype":"venue"
},
  "geometry": {"coordinates":[7.531247,45.025658],"type":"Point"}
}