{
  "type": "Feature",
  "properties": {
    "iso:country":"IT",
    "sg:address":"1, Viale Rimembranza 36036 Torrebelvicino",
    "sg:city":"Torrebelvicino",
    "sg:classifiers":[
        {
            "category":"Shopping",
            "subcategory":"Crafts & Fabrics",
            "type":"Retail Goods"
        }
    ],
    "sg:phone":"+39 0445 661937",
    "sg:postcode":"36036",
    "sg:province":"Vicenza",
    "wof:name":"Raumer S.p.a.",
    "wof:placetype":"venue"
},
  "geometry": {"coordinates":[11.3089380264,45.7179298401],"type":"Point"}
}