{
  "type": "Feature",
  "properties": {
    "addr:full":"10127 Torino Torino Torino 10127",
    "addr:postcode":"10127;10127",
    "iso:country":"IT",
    "sg:address":"10127 Torino",
    "sg:city":"Torino",
    "sg:orig_category":"Macchine, Impianti E Forniture Per Industria Grafica, Cartaria E Cartotecnica. Automazione E Macchine Per Ufficio",
    "sg:phone":"+39 011 663 0205",
    "sg:postcode":"10127",
    "sg:province":"Torino",
    "wof:name":"Futurtecnica Snc Di Barbaro & C.",
    "wof:placetype":"venue"
},
  "geometry": {"coordinates":[7.656661,45.005062],"type":"Point"}
}