{
  "type": "Feature",
  "properties": {
    "addr:full":"Via Savena Vecchia 761 40052 San Gabriele San Gabriele Bologna 40052",
    "addr:housenumber":"761",
    "addr:postcode":"40052;40052",
    "addr:street":"Via Savena Vecchia;Gabriele San Gabriele",
    "iso:country":"IT",
    "sg:address":"Via Savena Vecchia 761 40052 San Gabriele",
    "sg:city":"San Gabriele",
    "sg:classifiers":[
        {
            "category":"Government",
            "subcategory":"Fire Station",
            "type":"Public Place"
        }
    ],
    "sg:phone":"+39 051 874802",
    "sg:postcode":"40052",
    "sg:province":"Bologna",
    "sg:tags":[
        "filter",
        "air"
    ],
    "sg:website":"www.turrini.biz",
    "wof:name":"Turrini Filtri Snc",
    "wof:placetype":"venue"
},
  "geometry": {"coordinates":[11.584319,44.666725],"type":"Point"}
}