{
  "type": "Feature",
  "properties": {
    "addr:full":"20094 Corsico Corsico Milano 20094",
    "addr:postcode":"20094;20094",
    "iso:country":"IT",
    "sg:address":"20094 Corsico",
    "sg:city":"Corsico",
    "sg:orig_category":"Motori Ed Organi Di Trasmissione",
    "sg:postcode":"20094",
    "sg:province":"Milano",
    "wof:name":"Cosil Fluidistica (s.r.l.)",
    "wof:placetype":"venue"
},
  "geometry": {"coordinates":[9.1077880859,45.4452476501],"type":"Point"}
}