{
  "type": "Feature",
  "properties": {
    "iso:country":"IT",
    "sg:address":"66038 San Vito Chietino",
    "sg:city":"San Vito Chietino",
    "sg:orig_category":"Carpenterie Metalliche",
    "sg:phone":"+39 0872 588019",
    "sg:postcode":"66038",
    "sg:province":"Chieti",
    "wof:name":"Ser.ind Srl",
    "wof:placetype":"venue"
},
  "geometry": {"coordinates":[14.407408,42.294994],"type":"Point"}
}