{
  "type": "Feature",
  "properties": {
    "iso:country":"IT",
    "sg:address":"Via Alberti 18 24020 Azzone",
    "sg:city":"Azzone",
    "sg:classifiers":[
        {
            "category":"Manufacturing",
            "subcategory":"Chemicals & Compounds",
            "type":"Manufacturing & Wholesale Goods"
        }
    ],
    "sg:phone":"+39 035 741315",
    "sg:postcode":"24020",
    "sg:province":"Bergamo",
    "sg:tags":[
        "plants",
        "used"
    ],
    "sg:website":"www.omca.it",
    "wof:name":"Omca Plants Srl",
    "wof:placetype":"venue"
},
  "geometry": {"coordinates":[9.669952,45.694904],"type":"Point"}
}