{
  "type": "Feature",
  "properties": {
    "addr:full":"Via Bongiasca 1303 21020 Comabbio Comabbio Varese 21020",
    "addr:housenumber":"1303",
    "addr:postcode":"21020;21020",
    "addr:street":"Via Bongiasca",
    "iso:country":"IT",
    "sg:address":"Via Bongiasca 1303 21020 Comabbio",
    "sg:city":"Comabbio",
    "sg:orig_category":"Hoses, Flexible",
    "sg:phone":"+39 0331 968843",
    "sg:postcode":"21020",
    "sg:province":"Varese",
    "sg:website":"www.ipl.it",
    "wof:name":"Industrie Plastiche Lombarde Spa",
    "wof:placetype":"venue"
},
  "geometry": {"coordinates":[8.679822,45.781052],"type":"Point"}
}