{
  "type": "Feature",
  "properties": {
    "addr:full":"20149 Milano Milano Milano 20149",
    "addr:postcode":"20149;20149",
    "iso:country":"IT",
    "sg:address":"20149 Milano",
    "sg:city":"Milano",
    "sg:orig_category":"Materie Plastiche - Commercio",
    "sg:phone":"+39 02 4398 1159",
    "sg:postcode":"20149",
    "sg:province":"Milano",
    "wof:name":"R.plast",
    "wof:placetype":"venue"
},
  "geometry": {"coordinates":[9.149541,45.476746],"type":"Point"}
}