{
  "type": "Feature",
  "properties": {
    "addr:full":"95025 Aci Sant'antonio Catania 95025",
    "addr:postcode":"95025;95025",
    "iso:country":"IT",
    "sg:address":"95025 Aci Sant'antonio",
    "sg:orig_category":"Pubblicita' - Cartelli, Insegne E Targhe",
    "sg:phone":"+39 095 789 2797",
    "sg:postcode":"95025",
    "sg:province":"Catania",
    "wof:name":"Meditalia",
    "wof:placetype":"venue"
},
  "geometry": {"coordinates":[15.1292829514,37.6056098938],"type":"Point"}
}