{
  "type": "Feature",
  "properties": {
    "iso:country":"IT",
    "sg:address":"38060 Villa Lagarina",
    "sg:city":"Villa Lagarina",
    "sg:orig_category":"Arredo Cucina Ed Elettrodomestici. Elettrodomestici",
    "sg:phone":"+39 0464 419410",
    "sg:postcode":"38060",
    "sg:province":"Trento",
    "wof:name":"Artecalore Di Rizzoli Alessandro",
    "wof:placetype":"venue"
},
  "geometry": {"coordinates":[11.030845,45.915943],"type":"Point"}
}