{
  "type": "Feature",
  "properties": {
    "iso:country":"IT",
    "sg:address":"20047 Brugherio",
    "sg:city":"Brugherio",
    "sg:classifiers":[
        {
            "category":"Professional",
            "subcategory":"Art Services",
            "type":"Services"
        }
    ],
    "sg:phone":"+39 039 232 1042",
    "sg:postcode":"20047",
    "sg:province":"Milano",
    "sg:tags":[
        "craft",
        "artistic"
    ],
    "wof:name":"Art 2 Scenografie Snc",
    "wof:placetype":"venue"
},
  "geometry": {"coordinates":[9.290957,45.544613],"type":"Point"}
}