{
  "type": "Feature",
  "properties": {
    "addr:full":"35037 Teolo Teolo Padova 35037",
    "addr:postcode":"35037;35037",
    "iso:country":"IT",
    "sg:address":"35037 Teolo",
    "sg:city":"Teolo",
    "sg:orig_category":"Materiali Edili",
    "sg:phone":"+39 049 990 2466",
    "sg:postcode":"35037",
    "sg:province":"Padova",
    "sg:website":"http://www.acquario-due.it",
    "wof:name":"Acquario Due Sas Di Zancanella Federico & C.",
    "wof:placetype":"venue"
},
  "geometry": {"coordinates":[11.697119,45.358231],"type":"Point"}
}