{
  "type": "Feature",
  "properties": {
    "iso:country":"IT",
    "sg:address":"70051 Barletta",
    "sg:city":"Barletta",
    "sg:classifiers":[
        {
            "category":"Health Services",
            "subcategory":"Health Practitioner",
            "type":"Services"
        }
    ],
    "sg:phone":"+39 0883 347518",
    "sg:postcode":"70051",
    "sg:province":"Bari",
    "sg:tags":[
        "medici"
    ],
    "wof:name":"Fuccilli Ruggiero",
    "wof:placetype":"venue"
},
  "geometry": {"coordinates":[16.284363,41.317898],"type":"Point"}
}