{
  "type": "Feature",
  "properties": {
    "addr:full":"95121 Catania Catania Catania 95121",
    "addr:postcode":"95121;95121",
    "iso:country":"IT",
    "sg:address":"95121 Catania",
    "sg:city":"Catania",
    "sg:orig_category":"Autodemolizioni",
    "sg:phone":"+39 095 723 1216",
    "sg:postcode":"95121",
    "sg:province":"Catania",
    "wof:name":"Ro.fe.me. Snc",
    "wof:placetype":"venue"
},
  "geometry": {"coordinates":[15.053033,37.517162],"type":"Point"}
}