{
  "type": "Feature",
  "properties": {
    "iso:country":"IT",
    "sg:address":"70, Via Boscone 22077 Olgiate Comasco",
    "sg:city":"Olgiate Comasco",
    "sg:classifiers":[
        {
            "category":"Shopping",
            "subcategory":"Crafts & Fabrics",
            "type":"Retail Goods"
        }
    ],
    "sg:phone":"+39 39031991911",
    "sg:postcode":"22077",
    "sg:province":"Como",
    "wof:name":"Stamperia Luce Spa",
    "wof:placetype":"venue"
},
  "geometry": {"coordinates":[8.9857196808,45.8009986877],"type":"Point"}
}