{
  "type": "Feature",
  "properties": {
    "iso:country":"IT",
    "sg:address":"Via G. Battista Stucchi, 62/6 20052 Monza",
    "sg:city":"Monza",
    "sg:classifiers":[
        {
            "category":"Manufacturing",
            "subcategory":"Rubber & Plastics",
            "type":"Manufacturing & Wholesale Goods"
        }
    ],
    "sg:phone":"+39 039 284 2376",
    "sg:postcode":"20052",
    "sg:province":"Milano",
    "sg:tags":[
        "machining",
        "cnc"
    ],
    "sg:website":"www.cosmaplast.it",
    "wof:name":"Co.s.ma.plast. Srl",
    "wof:placetype":"venue"
},
  "geometry": {"coordinates":[9.188141,45.463688],"type":"Point"}
}