{
  "type": "Feature",
  "properties": {
    "addr:full":"45/bis, Corso Turati Filippo 10128 Torino Torino Torino 10128",
    "addr:housenumber":"45 / bis",
    "addr:postcode":"10128;10128",
    "addr:street":"Corso Turati Filippo",
    "iso:country":"IT",
    "sg:address":"45/bis, Corso Turati Filippo 10128 Torino",
    "sg:city":"Torino",
    "sg:classifiers":[
        {
            "category":"Wholesale",
            "subcategory":"Medical Equipment & Supplies",
            "type":"Manufacturing & Wholesale Goods"
        }
    ],
    "sg:phone":"+39 011 581 8864",
    "sg:postcode":"10128",
    "sg:province":"Torino",
    "sg:tags":[
        "-",
        "health",
        "instrument"
    ],
    "wof:name":"Ortho' Officina Ortopedica Zumaglini Srl",
    "wof:placetype":"venue"
},
  "geometry": {"coordinates":[7.665637,45.051918],"type":"Point"}
}