{
  "type": "Feature",
  "properties": {
    "addr:full":"2, Via Galvani 20068 Peschiera Borromeo Peschiera Borromeo Milano 20068",
    "addr:postcode":"20068;20068",
    "addr:street":"Via Galvani",
    "iso:country":"IT",
    "sg:address":"2, Via Galvani 20068 Peschiera Borromeo",
    "sg:city":"Peschiera Borromeo",
    "sg:classifiers":[
        {
            "category":"Professional",
            "subcategory":"Printing & Photocopies",
            "type":"Services"
        }
    ],
    "sg:phone":"+39 02 5530 2615",
    "sg:postcode":"20068",
    "sg:province":"Milano",
    "wof:name":"Imaf S.p.a.",
    "wof:placetype":"venue"
},
  "geometry": {"coordinates":[9.2984857559,45.4372901917],"type":"Point"}
}