{
  "type": "Feature",
  "properties": {
    "addr:full":"00054 Fiumicino Fiumicino Roma 00054",
    "addr:postcode":"00054;roma 00054",
    "iso:country":"IT",
    "sg:address":"00054 Fiumicino",
    "sg:city":"Fiumicino",
    "sg:orig_category":"Materiali Edili",
    "sg:phone":"+39 06 652 9003",
    "sg:postcode":"00054",
    "sg:province":"Roma",
    "wof:name":"Premix Srl",
    "wof:placetype":"venue"
},
  "geometry": {"coordinates":[12.262554,41.786739],"type":"Point"}
}