{
  "type": "Feature",
  "properties": {
    "iso:country":"IT",
    "sg:address":"83, Viale Della Liberta' 33170 Pordenone",
    "sg:city":"Pordenone",
    "sg:classifiers":[
        {
            "category":"Autos & Motor Vehicles",
            "subcategory":"Automobile Sales",
            "type":"Retail Goods"
        }
    ],
    "sg:phone":"+39 0434 541183",
    "sg:postcode":"33170",
    "sg:province":"Pordenone",
    "sg:tags":[
        "motor-cars"
    ],
    "wof:name":"Muzzatti Giorgio & C. (s.n.c.)",
    "wof:placetype":"venue"
},
  "geometry": {"coordinates":[12.5964841843,45.891242981],"type":"Point"}
}