{
  "type": "Feature",
  "properties": {
    "iso:country":"IT",
    "sg:address":"39057 Appiano Sulla Strada Del Vino",
    "sg:city":"Appiano sulla strada del vino",
    "sg:orig_category":"Agricoltura, Orticoltura E Floricoltura",
    "sg:phone":"+39 0471 662484",
    "sg:postcode":"39057",
    "sg:province":"Bolzano/Bozen",
    "wof:name":"Platter Luis",
    "wof:placetype":"venue"
},
  "geometry": {"coordinates":[11.273797,46.474457],"type":"Point"}
}