{
  "type": "Feature",
  "properties": {
    "iso:country":"IT",
    "sg:address":"43036 Fidenza",
    "sg:city":"Fidenza",
    "sg:orig_category":"Imprese Di Costruzioni Civili Ed Industriali",
    "sg:phone":"+39 0524 524767",
    "sg:postcode":"43036",
    "sg:province":"Parma",
    "wof:name":"Impresa Tre Colli Spa",
    "wof:placetype":"venue"
},
  "geometry": {"coordinates":[10.064198,44.866177],"type":"Point"}
}