{
  "type": "Feature",
  "properties": {
    "iso:country":"IT",
    "sg:address":"119, Via Pontebbana 33031 Basiliano",
    "sg:city":"Basiliano",
    "sg:classifiers":[
        {
            "category":"Utilities",
            "subcategory":"Telephone",
            "type":"Services"
        }
    ],
    "sg:phone":"+39 39043284381",
    "sg:postcode":"33031",
    "sg:province":"Udine",
    "sg:tags":[
        "telecommunication"
    ],
    "wof:name":"Calzavara S.p.a.",
    "wof:placetype":"venue"
},
  "geometry": {"coordinates":[13.114558,46.006317],"type":"Point"}
}