{
  "type": "Feature",
  "properties": {
    "iso:country":"IT",
    "sg:address":"2, Via Brunacci 60010 Ostra Vetere",
    "sg:city":"Ostra",
    "sg:classifiers":[
        {
            "category":"Real Estate",
            "subcategory":"Architect",
            "type":"Services"
        }
    ],
    "sg:phone":"+39 39071965094",
    "sg:postcode":"60010",
    "sg:province":"Ancona",
    "sg:tags":[
        "textile",
        "clothing"
    ],
    "wof:name":"Confezioni Nicoletta Di Pirani E Bruni Snc",
    "wof:placetype":"venue"
},
  "geometry": {"coordinates":[13.059671,43.60799],"type":"Point"}
}