{
  "type": "Feature",
  "properties": {
    "addr:full":"03023 Ceccano Ceccano Frosinone 03023",
    "addr:postcode":"03023;03023",
    "iso:country":"IT",
    "sg:address":"03023 Ceccano",
    "sg:city":"Ceccano",
    "sg:orig_category":"Profumerie",
    "sg:phone":"+39 0775 600343",
    "sg:postcode":"03023",
    "sg:province":"Frosinone",
    "wof:name":"Di Pofi Alberto",
    "wof:placetype":"venue"
},
  "geometry": {"coordinates":[13.3356275558,41.5561904907],"type":"Point"}
}