{
  "type": "Feature",
  "properties": {
    "iso:country":"IT",
    "sg:address":"20123 Milano",
    "sg:city":"Milano",
    "sg:orig_category":"Manufacturers: Prefabbricati",
    "sg:phone":"+39 02 4800 4415",
    "sg:postcode":"20123",
    "sg:province":"Milano",
    "wof:name":"Pali Verganti (s.r.l.)",
    "wof:placetype":"venue"
},
  "geometry": {"coordinates":[9.168266,45.471615],"type":"Point"}
}