{
  "type": "Feature",
  "properties": {
    "addr:full":"01033 Civita Castellana Civita Castellana Viterbo 01033",
    "addr:postcode":"01033;01033",
    "iso:country":"IT",
    "sg:address":"01033 Civita Castellana",
    "sg:city":"Civita Castellana",
    "sg:classifiers":[
        {
            "category":"Home & Garden",
            "subcategory":"Home Furnishings",
            "type":"Retail Goods"
        }
    ],
    "sg:phone":"+39 0761 54203",
    "sg:postcode":"01033",
    "sg:province":"Viterbo",
    "sg:tags":[
        "plumbing",
        "bathroom",
        "fitting",
        "accessories",
        "accessory"
    ],
    "sg:website":"http://www.ceramicaflaminia.it",
    "wof:name":"Ceramica Flaminia Spa",
    "wof:placetype":"venue"
},
  "geometry": {"coordinates":[12.4265947342,42.2940826416],"type":"Point"}
}