{
  "type": "Feature",
  "properties": {
    "addr:full":"Via Aosta 15 10092 Beinasco Beinasco Torino 10092",
    "addr:housenumber":"15",
    "addr:postcode":"10092;10092",
    "addr:street":"Via Aosta",
    "iso:country":"IT",
    "sg:address":"Via Aosta 15 10092 Beinasco",
    "sg:city":"Beinasco",
    "sg:classifiers":[
        {
            "category":"Home & Garden",
            "subcategory":"Building Materials",
            "type":"Retail Goods"
        }
    ],
    "sg:phone":"+39 011 398 7555",
    "sg:postcode":"10092",
    "sg:province":"Torino",
    "sg:tags":[
        "installation",
        "electric"
    ],
    "sg:website":"www.egzerouno.com",
    "wof:name":"Elettrogruppo Zerouno Spa",
    "wof:placetype":"venue"
},
  "geometry": {"coordinates":[7.586957,45.028473],"type":"Point"}
}