{
  "type": "Feature",
  "properties": {
    "iso:country":"IT",
    "sg:address":"6/a, Via Colombo Cristoforo 33077 Sacile",
    "sg:city":"Sacile",
    "sg:classifiers":[
        {
            "category":"Professional",
            "subcategory":"Business Services",
            "type":"Services"
        }
    ],
    "sg:phone":"+39 0434 735349",
    "sg:postcode":"33077",
    "sg:province":"Pordenone",
    "sg:tags":[
        "advice"
    ],
    "wof:name":"C.e.a. Commerciale Europea Arredamenti Di Prosdocimo Giorgio",
    "wof:placetype":"venue"
},
  "geometry": {"coordinates":[12.655044,45.96265],"type":"Point"}
}