{
  "type": "Feature",
  "properties": {
    "iso:country":"IT",
    "sg:address":"22063 Cantu'",
    "sg:orig_category":"Forniture Per Attivita' Industriali",
    "sg:phone":"+39 031 735400",
    "sg:postcode":"22063",
    "sg:province":"Como",
    "wof:name":"Nespoli (s.r.l.)",
    "wof:placetype":"venue"
},
  "geometry": {"coordinates":[9.1314849854,45.7467498779],"type":"Point"}
}