{
  "type": "Feature",
  "properties": {
    "iso:country":"IT",
    "sg:address":"Via G. Rossa 5 20061 Carugate",
    "sg:city":"Carugate",
    "sg:orig_category":"Rotary Vane Pumps",
    "sg:phone":"+39 02 9215 0125",
    "sg:postcode":"20061",
    "sg:province":"Milano",
    "sg:website":"www.ceme.com",
    "wof:name":"Ceme Spa",
    "wof:placetype":"venue"
},
  "geometry": {"coordinates":[9.297663,45.535015],"type":"Point"}
}