{
  "type": "Feature",
  "properties": {
    "addr:full":"13, Strada Traversante S. Leonardo 43100 Parma Parma Parma 43100",
    "addr:postcode":"43100;43100",
    "addr:street":"Strada Traversante S. Leonardo",
    "iso:country":"IT",
    "sg:address":"13, Strada Traversante S. Leonardo 43100 Parma",
    "sg:city":"Parma",
    "sg:classifiers":[
        {
            "category":"Professional",
            "subcategory":"Engineering",
            "type":"Services"
        }
    ],
    "sg:phone":"+39 0521 776545",
    "sg:postcode":"43100",
    "sg:province":"Parma",
    "sg:tags":[
        "machine",
        "-",
        "mechanical"
    ],
    "wof:name":"Euram Italiana Srl",
    "wof:placetype":"venue"
},
  "geometry": {"coordinates":[10.29492,44.823208],"type":"Point"}
}