{
  "type": "Feature",
  "properties": {
    "iso:country":"IT",
    "sg:address":"Via Brodolini 12 21047 Saronno",
    "sg:city":"Saronno",
    "sg:classifiers":[
        {
            "category":"Manufacturing",
            "subcategory":"Rubber & Plastics",
            "type":"Manufacturing & Wholesale Goods"
        }
    ],
    "sg:phone":"+39 02 960 7682",
    "sg:postcode":"21047",
    "sg:province":"Varese",
    "sg:tags":[
        "device",
        "processing"
    ],
    "sg:website":"www.omc-saronno.com",
    "wof:name":"Omc Srl",
    "wof:placetype":"venue"
},
  "geometry": {"coordinates":[9.029064,45.615479],"type":"Point"}
}