{
  "type": "Feature",
  "properties": {
    "iso:country":"IT",
    "sg:address":"20090 Pieve Emanuele",
    "sg:city":"Pieve Emanuele",
    "sg:orig_category":"Scuole E Servizi Scolastici. Servizi Vari Di Interesse Pubblico",
    "sg:phone":"+39 02 9072 2474",
    "sg:postcode":"20090",
    "sg:province":"Milano",
    "wof:name":"Asilo Infantile Cesare Longhi",
    "wof:placetype":"venue"
},
  "geometry": {"coordinates":[9.212048,45.376373],"type":"Point"}
}