{
  "type": "Feature",
  "properties": {
    "iso:country":"IT",
    "sg:address":"25065 Lumezzane",
    "sg:city":"Lumezzane",
    "sg:orig_category":"Valvole E Apparecchiature Di Misura. Minuterie Metalliche E Ferramenta. Forniture Per Attivita' Industriali",
    "sg:phone":"+39 030 892 1377",
    "sg:postcode":"25065",
    "sg:province":"Brescia",
    "sg:website":"http://www.mema.it",
    "wof:name":"Mema Srl",
    "wof:placetype":"venue"
},
  "geometry": {"coordinates":[10.300862,45.534775],"type":"Point"}
}