{
  "type": "Feature",
  "properties": {
    "addr:full":"00182 Roma Roma Roma 00182",
    "addr:postcode":"00182;00182",
    "iso:country":"IT",
    "sg:address":"00182 Roma",
    "sg:city":"Roma",
    "sg:classifiers":[
        {
            "category":"Health Services",
            "subcategory":"Health Practitioner",
            "type":"Services"
        }
    ],
    "sg:phone":"+39 06 701 1412",
    "sg:postcode":"00182",
    "sg:province":"Roma",
    "sg:tags":[
        "medici"
    ],
    "wof:name":"Morganti Sandro",
    "wof:placetype":"venue"
},
  "geometry": {"coordinates":[12.5188102722,41.8862800598],"type":"Point"}
}