{
  "type": "Feature",
  "properties": {
    "addr:full":"37039 Tregnago Tregnago Verona 37039",
    "addr:postcode":"37039;37039",
    "iso:country":"IT",
    "sg:address":"37039 Tregnago",
    "sg:city":"Tregnago",
    "sg:orig_category":"Apparecchiature Ed Attrezzature Meccaniche",
    "sg:phone":"+39 045 780 8900",
    "sg:postcode":"37039",
    "sg:province":"Verona",
    "wof:name":"Mita Oleodinamica Spa",
    "wof:placetype":"venue"
},
  "geometry": {"coordinates":[11.016425,45.444351],"type":"Point"}
}