{
  "type": "Feature",
  "properties": {
    "iso:country":"IT",
    "sg:address":"38034 Cembra",
    "sg:city":"Cembra",
    "sg:orig_category":"Cartolerie",
    "sg:phone":"+39 0461 682277",
    "sg:postcode":"38034",
    "sg:province":"Trento",
    "wof:name":"Nicser Martino E Linda Snc",
    "wof:placetype":"venue"
},
  "geometry": {"coordinates":[11.223093,46.174217],"type":"Point"}
}