{
  "type": "Feature",
  "properties": {
    "iso:country":"IT",
    "sg:address":"Via Provinciale Varesina 10 21035 Cunardo",
    "sg:city":"Cunardo",
    "sg:classifiers":[
        {
            "category":"Manufacturing",
            "subcategory":"Glass & Minerals",
            "type":"Manufacturing & Wholesale Goods"
        }
    ],
    "sg:phone":"+39 0332 990000",
    "sg:postcode":"21035",
    "sg:province":"Varese",
    "sg:tags":[
        "frame"
    ],
    "wof:name":"Ilop Srl",
    "wof:placetype":"venue"
},
  "geometry": {"coordinates":[8.826385,45.817604],"type":"Point"}
}