{
  "type": "Feature",
  "properties": {
    "iso:country":"IT",
    "sg:address":"43030 Torrile",
    "sg:orig_category":"Metalli E Leghe",
    "sg:phone":"+39 0521 819352",
    "sg:postcode":"43030",
    "sg:province":"Parma",
    "wof:name":"Terenziani Giuseppe & C. Snc",
    "wof:placetype":"venue"
},
  "geometry": {"coordinates":[10.3585796356,44.8959159851],"type":"Point"}
}