{
  "type": "Feature",
  "properties": {
    "iso:country":"IT",
    "sg:address":"24126 Bergamo",
    "sg:city":"Bergamo",
    "sg:orig_category":"Ascensori - Installazione E Manutenzione",
    "sg:phone":"+39 035 320453",
    "sg:postcode":"24126",
    "sg:province":"Bergamo",
    "wof:name":"Bettinelli Lorenzo",
    "wof:placetype":"venue"
},
  "geometry": {"coordinates":[9.657347,45.671482],"type":"Point"}
}