{
  "type": "Feature",
  "properties": {
    "iso:country":"IT",
    "sg:address":"42, V. Cassia Per Siena 50026 S. Casciano Val Di Pesa",
    "sg:classifiers":[
        {
            "category":"Manufacturing",
            "subcategory":"Food",
            "type":"Manufacturing & Wholesale Goods"
        }
    ],
    "sg:phone":"+39 055 824 9117",
    "sg:postcode":"50026",
    "sg:province":"Firenze",
    "sg:tags":[
        "equipment",
        "processing",
        "-",
        "machinery"
    ],
    "sg:website":"http://www.moriluigi.it:ws_end: :mark:ws:http://www.paginegialle.it/mori-05",
    "wof:name":"Mori Luigi Sas",
    "wof:placetype":"venue"
},
  "geometry": {"coordinates":[11.1860408783,43.6234207153],"type":"Point"}
}