{
  "type": "Feature",
  "properties": {
    "iso:country":"IT",
    "sg:address":"174, Via Mantova 25018 Montichiari",
    "sg:city":"Montichiari",
    "sg:classifiers":[
        {
            "category":"Autos & Motor Vehicles",
            "subcategory":"Automobile Sales",
            "type":"Retail Goods"
        }
    ],
    "sg:phone":"+39 39030961668",
    "sg:postcode":"25018",
    "sg:province":"Brescia",
    "sg:tags":[
        "equipment",
        "transport"
    ],
    "wof:name":"Fraccaro",
    "wof:placetype":"venue"
},
  "geometry": {"coordinates":[11.115941,45.418343],"type":"Point"}
}