{
  "type": "Feature",
  "properties": {
    "iso:country":"IT",
    "sg:address":"06077 Perugia",
    "sg:classifiers":[
        {
            "category":"Bars & Pubs",
            "subcategory":"Oxygen Bar",
            "type":"Food & Drink"
        }
    ],
    "sg:phone":"+39 075 694175",
    "sg:province":"PG",
    "sg:tags":[
        "liqueurs",
        "drinks",
        "shopping",
        "wine"
    ],
    "wof:name":"Cantina Soc.coop.r.l. Perugia",
    "wof:placetype":"venue"
},
  "geometry": {"coordinates":[-72.259399,41.993801],"type":"Point"}
}