{
  "type": "Feature",
  "properties": {
    "iso:country":"IT",
    "sg:address":"Viale P Educ. 48; Castellamonte; 10081",
    "sg:city":"Castellamonte",
    "sg:classifiers":[
        {
            "category":"Banks & Credit Unions",
            "subcategory":"Bank",
            "type":"Services"
        }
    ],
    "sg:phone":"+39 0124 582378",
    "sg:postcode":"10081",
    "sg:province":"Torino",
    "wof:name":"Banca Sella Spa",
    "wof:placetype":"venue"
},
  "geometry": {"coordinates":[7.711411,45.38295],"type":"Point"}
}