{
  "type": "Feature",
  "properties": {
    "addr:full":"1, Via Renato Simoni 37014 Castelnuovo Del Garda Castelnuovo del Garda Verona 37014",
    "addr:postcode":"37014;37014",
    "addr:street":"Via Renato Simoni",
    "iso:country":"IT",
    "sg:address":"1, Via Renato Simoni 37014 Castelnuovo Del Garda",
    "sg:city":"Castelnuovo del Garda",
    "sg:orig_category":"Miscellaneous Products",
    "sg:phone":"+39 045 755 1917",
    "sg:postcode":"37014",
    "sg:province":"Verona",
    "wof:name":"Gamafood S.r.l.",
    "wof:placetype":"venue"
},
  "geometry": {"coordinates":[10.9917478561,45.4383659363],"type":"Point"}
}