{
  "type": "Feature",
  "properties": {
    "addr:full":"10144 Torino Torino Torino 10144",
    "addr:postcode":"10144;10144",
    "iso:country":"IT",
    "sg:address":"10144 Torino",
    "sg:city":"Torino",
    "sg:orig_category":"Servizi Editoriali",
    "sg:phone":"+39 011 437 9152",
    "sg:postcode":"10144",
    "sg:province":"Torino",
    "wof:name":"Interlibri S.n.c.",
    "wof:placetype":"venue"
},
  "geometry": {"coordinates":[7.919773,45.045883],"type":"Point"}
}