{
  "type": "Feature",
  "properties": {
    "addr:full":"24050 Zanica Zanica Bergamo 24050",
    "addr:postcode":"24050;24050",
    "iso:country":"IT",
    "sg:address":"24050 Zanica",
    "sg:city":"Zanica",
    "sg:orig_category":"Servizi E Lavori Per Arredamento E Industria Del Legno",
    "sg:phone":"+39 035 671066",
    "sg:postcode":"24050",
    "sg:province":"Bergamo",
    "wof:name":"Bertoli Fratelli Snc",
    "wof:placetype":"venue"
},
  "geometry": {"coordinates":[9.680886,45.639194],"type":"Point"}
}