{
  "type": "Feature",
  "properties": {
    "addr:full":"Via Enrico Fermi 33/a 42030 Fogliano Reggio Nell'Emilia 42030",
    "addr:housenumber":"33 / a",
    "addr:postcode":"42030;42030",
    "addr:street":"Via Enrico Fermi",
    "iso:country":"IT",
    "sg:address":"Via Enrico Fermi 33/a 42030 Fogliano",
    "sg:classifiers":[
        {
            "category":"Animal Shelter",
            "type":"Public Place"
        }
    ],
    "sg:phone":"+39 0522 520121",
    "sg:postcode":"42030",
    "sg:province":"Reggio Nell'Emilia",
    "sg:tags":[
        "feed",
        "system",
        "dispensing"
    ],
    "wof:name":"Alfredo Braglia Spa",
    "wof:placetype":"venue"
},
  "geometry": {"coordinates":[10.64668,44.647469],"type":"Point"}
}