{
  "type": "Feature",
  "properties": {
    "addr:full":"00040 Pomezia Pomezia Roma 00040",
    "addr:postcode":"00040;roma 00040",
    "iso:country":"IT",
    "sg:address":"00040 Pomezia",
    "sg:city":"Pomezia",
    "sg:orig_category":"Legno E Semilavorati. Macchine E Forniture Per Arredamento E Industria Del Legno. Hobbistica",
    "sg:phone":"+39 06 912 0493",
    "sg:postcode":"00040",
    "sg:province":"Roma",
    "wof:name":"Importex Srl",
    "wof:placetype":"venue"
},
  "geometry": {"coordinates":[12.508637,41.676994],"type":"Point"}
}