{
  "type": "Feature",
  "properties": {
    "addr:full":"10137 Torino Torino Torino 10137",
    "addr:postcode":"10137;10137",
    "iso:country":"IT",
    "sg:address":"10137 Torino",
    "sg:city":"Torino",
    "sg:orig_category":"Pubblica Amministrazione",
    "sg:phone":"+39 011 309 7567",
    "sg:postcode":"10137",
    "sg:province":"Torino",
    "wof:name":"Provincia Di Torino",
    "wof:placetype":"venue"
},
  "geometry": {"coordinates":[7.6318163872,45.045211792],"type":"Point"}
}