{
  "type": "Feature",
  "properties": {
    "iso:country":"IT",
    "sg:address":"50050 Cerreto Guidi",
    "sg:city":"Cerreto Guidi",
    "sg:orig_category":"Macchine, Impianti Ed Attrezzature Per Abbigliamento E Pelletterie",
    "sg:phone":"+39 0571 580301",
    "sg:postcode":"50050",
    "sg:province":"Firenze",
    "wof:name":"Versopelle Di Sorrentino Veronica",
    "wof:placetype":"venue"
},
  "geometry": {"coordinates":[10.880647,43.72282],"type":"Point"}
}