{
  "type": "Feature",
  "properties": {
    "iso:country":"IT",
    "sg:address":"50134 Firenze",
    "sg:city":"Firenze",
    "sg:orig_category":"Arredi Ed Attrezzature Per Uffici",
    "sg:phone":"+39 055 472820",
    "sg:postcode":"50134",
    "sg:province":"Firenze",
    "wof:name":"Break Time S.n.c.",
    "wof:placetype":"venue"
},
  "geometry": {"coordinates":[11.240963,43.795002],"type":"Point"}
}