{
  "type": "Feature",
  "properties": {
    "iso:country":"IT",
    "sg:address":"20143 Milano",
    "sg:city":"Milano",
    "sg:orig_category":"Scuole Private - Professionali",
    "sg:phone":"+39 02 8912 0540",
    "sg:postcode":"20143",
    "sg:province":"Milano",
    "wof:name":"Sae Italia Srl",
    "wof:placetype":"venue"
},
  "geometry": {"coordinates":[9.149614,45.444302],"type":"Point"}
}