{
  "type": "Feature",
  "properties": {
    "iso:country":"IT",
    "sg:address":"10124 Torino",
    "sg:city":"Torino",
    "sg:orig_category":"Prodotti Di Base E Forniture Per Industria Alimentare E Bevande. Forniture E Materiali Per Imballaggio E Confezionamento",
    "sg:phone":"+39 011 889115",
    "sg:postcode":"10124",
    "sg:province":"Torino",
    "wof:name":"Bocchino Clara",
    "wof:placetype":"venue"
},
  "geometry": {"coordinates":[7.5939035416,45.0305595398],"type":"Point"}
}