{
  "type": "Feature",
  "properties": {
    "addr:full":"Localita' Selvamaggio 53034 Colle Di Val D'elsa Siena 53034",
    "addr:postcode":"53034;53034",
    "addr:street":"Localita ' Selvamaggio",
    "iso:country":"IT",
    "sg:address":"Localita' Selvamaggio 53034 Colle Di Val D'elsa",
    "sg:classifiers":[
        {
            "category":"Communications",
            "subcategory":"Television Station",
            "type":"Services"
        }
    ],
    "sg:phone":"+39 0577 922685",
    "sg:postcode":"53034",
    "sg:province":"Siena",
    "sg:tags":[
        "audio-visual"
    ],
    "wof:name":"Alfa Elettronica Srl",
    "wof:placetype":"venue"
},
  "geometry": {"coordinates":[11.15863,43.415691],"type":"Point"}
}