{
  "type": "Feature",
  "properties": {
    "addr:full":"06012 Citt\u00e0 Di Castello Cerbara Perugia 06012",
    "addr:postcode":"06012;06012",
    "iso:country":"IT",
    "sg:address":"06012 Citt\u00e0 Di Castello",
    "sg:city":"Cerbara",
    "sg:orig_category":"Ferramenta - Ingrosso",
    "sg:phone":"+39 075 851 0356",
    "sg:postcode":"06012",
    "sg:province":"Perugia",
    "wof:name":"Utensil Legno Di Rumori & C. Snc",
    "wof:placetype":"venue"
},
  "geometry": {"coordinates":[12.2319049835,43.4577865601],"type":"Point"}
}