{
  "type": "Feature",
  "properties": {
    "addr:full":"Via Torino 4 10080 Salassa Salassa Torino 10080",
    "addr:housenumber":"4",
    "addr:postcode":"10080;10080",
    "addr:street":"Via Torino",
    "iso:country":"IT",
    "sg:address":"Via Torino 4 10080 Salassa",
    "sg:city":"Salassa",
    "sg:classifiers":[
        {
            "category":"Manufacturing",
            "subcategory":"Tools & Machinery",
            "type":"Manufacturing & Wholesale Goods"
        }
    ],
    "sg:phone":"+39 0124 36141",
    "sg:postcode":"10080",
    "sg:province":"Torino",
    "sg:tags":[
        "tannery"
    ],
    "sg:website":"www.vallero.com",
    "wof:name":"Vallero Co. Srl",
    "wof:placetype":"venue"
},
  "geometry": {"coordinates":[7.6874880791,45.3579406738],"type":"Point"}
}