{
  "type": "Feature",
  "properties": {
    "iso:country":"IT",
    "sg:address":"80013 Casalnuovo Di Napoli",
    "sg:city":"Casalnuovo di Napoli",
    "sg:orig_category":"Macchine E Forniture Per Ecologia E Smaltimento Rifiuti. Elettrodomestici. Forniture Alle Strutture Ricettive. Macchine, Strumenti Ed Apparecchi Per Attivita' Industriali",
    "sg:phone":"+39 081 842 1370",
    "sg:postcode":"80013",
    "sg:province":"Napoli",
    "wof:name":"Romano Angelo Sas Di Romano Angelo & Co.",
    "wof:placetype":"venue"
},
  "geometry": {"coordinates":[14.321363,40.888474],"type":"Point"}
}