{
  "type": "Feature",
  "properties": {
    "addr:full":"00185 Roma Roma Roma 00185",
    "addr:postcode":"00185;00185",
    "iso:country":"IT",
    "sg:address":"00185 Roma",
    "sg:city":"Roma",
    "sg:orig_category":"Trattamenti Termici E Superficiali Metalli, Galvanotecnica",
    "sg:phone":"+39 06 495 8294",
    "sg:postcode":"00185",
    "sg:province":"Roma",
    "wof:name":"Mastroddi",
    "wof:placetype":"venue"
},
  "geometry": {"coordinates":[12.514793,41.894749],"type":"Point"}
}