{
  "type": "Feature",
  "properties": {
    "iso:country":"IT",
    "sg:address":"09128 Cagliari",
    "sg:city":"Cagliari",
    "sg:orig_category":"Argenterie - Vendita Al Dettaglio",
    "sg:phone":"+39 070 403325",
    "sg:postcode":"09128",
    "sg:province":"Cagliari",
    "wof:name":"Barrella Alessandra Sas",
    "wof:placetype":"venue"
},
  "geometry": {"coordinates":[9.124621,39.220974],"type":"Point"}
}