{
  "type": "Feature",
  "properties": {
    "addr:full":"46/48, V. Ospiate 20017 Terrazzano Di Rho Rho Milano 20017",
    "addr:housenumber":"46 / 48",
    "addr:postcode":"20017;20017",
    "addr:street":"Ospiate",
    "iso:country":"IT",
    "sg:address":"46/48, V. Ospiate 20017 Terrazzano Di Rho",
    "sg:city":"Rho",
    "sg:classifiers":[
        {
            "category":"Shopping",
            "type":"Retail Goods"
        }
    ],
    "sg:phone":"+39 02 9393 0011",
    "sg:postcode":"20017",
    "sg:province":"Milano",
    "sg:tags":[
        "finished",
        "-",
        "metallic"
    ],
    "sg:website":"http://www.forgevienna.it",
    "wof:name":"Forgiatura Vienna Spa",
    "wof:placetype":"venue"
},
  "geometry": {"coordinates":[9.0711355209,45.5338249207],"type":"Point"}
}