{
  "type": "Feature",
  "properties": {
    "addr:full":"Localita' Castiglion Del Bosco 53024 Montalcino Montalcino Siena 53024",
    "addr:postcode":"53024;53024",
    "addr:street":"Localita ' Castiglion Del Bosco",
    "iso:country":"IT",
    "sg:address":"Localita' Castiglion Del Bosco 53024 Montalcino",
    "sg:city":"Montalcino",
    "sg:classifiers":[
        {
            "category":"Food & Beverages",
            "subcategory":"Groceries & Convenience Stores",
            "type":"Retail Goods"
        }
    ],
    "sg:phone":"+39 0577 807078",
    "sg:postcode":"53024",
    "sg:province":"Siena",
    "sg:tags":[
        "product",
        "related"
    ],
    "wof:name":"Castiglione Del Bosco Srl",
    "wof:placetype":"venue"
},
  "geometry": {"coordinates":[11.3305139542,43.3186607361],"type":"Point"}
}