{
  "type": "Feature",
  "properties": {
    "iso:country":"IT",
    "sg:address":"Piazzale Biancamano 1 20154 Milano",
    "sg:city":"Milano",
    "sg:classifiers":[
        {
            "category":"Organizations",
            "subcategory":"Professional Association",
            "type":"Services"
        }
    ],
    "sg:phone":"+39 02 345 1230",
    "sg:postcode":"20154",
    "sg:province":"Milano",
    "sg:tags":[
        "publisher",
        "literature"
    ],
    "sg:website":"www.edifis.it",
    "wof:name":"Edifis Spa",
    "wof:placetype":"venue"
},
  "geometry": {"coordinates":[9.1807556152,45.4783782959],"type":"Point"}
}