{
  "type": "Feature",
  "properties": {
    "addr:full":"00179 Roma Roma Roma 00179",
    "addr:postcode":"00179;00179",
    "iso:country":"IT",
    "sg:address":"00179 Roma",
    "sg:city":"Roma",
    "sg:orig_category":"Forniture Per Agricoltura E Zootecnia",
    "sg:phone":"+39 06 786653",
    "sg:postcode":"00179",
    "sg:province":"Roma",
    "wof:name":"Bozzolini Mario",
    "wof:placetype":"venue"
},
  "geometry": {"coordinates":[12.5307369232,41.8689346313],"type":"Point"}
}