{
  "type": "Feature",
  "properties": {
    "iso:country":"IT",
    "sg:address":"84053 Cicerale",
    "sg:city":"Cicerale",
    "sg:orig_category":"Prodotti E Manufatti In Materie Plastiche",
    "sg:phone":"+39 0974 834454",
    "sg:postcode":"84053",
    "sg:province":"Salerno",
    "wof:name":"De Santis Isidoro",
    "wof:placetype":"venue"
},
  "geometry": {"coordinates":[15.1142015457,40.3531608582],"type":"Point"}
}