{
  "type": "Feature",
  "properties": {
    "iso:country":"IT",
    "sg:address":"Piazzale Della; Lecce; 73100",
    "sg:city":"Lecce",
    "sg:classifiers":[
        {
            "category":"Banks & Credit Unions",
            "subcategory":"Bank",
            "type":"Services"
        }
    ],
    "sg:phone":"+39 0832 332132",
    "sg:postcode":"73100",
    "sg:province":"Lecce",
    "wof:name":"Istituto Bancario, San Paolo Di Torino Spa",
    "wof:placetype":"venue"
},
  "geometry": {"coordinates":[18.154802,40.356068],"type":"Point"}
}