{
  "type": "Feature",
  "properties": {
    "iso:country":"IT",
    "sg:address":"28863 Formazza",
    "sg:city":"Formazza",
    "sg:classifiers":[
        {
            "category":"Sports & Exercise",
            "subcategory":"Tennis Court",
            "type":"Entertainment"
        }
    ],
    "sg:phone":"+39 0324 634337",
    "sg:postcode":"28863",
    "sg:province":"Verbano-Cusio-Ossola",
    "sg:tags":[
        "e",
        "lo",
        "tempo",
        "libero",
        "per",
        "impianti",
        "il",
        "attrezzature"
    ],
    "wof:name":"Magic Ski Srl",
    "wof:placetype":"venue"
},
  "geometry": {"coordinates":[8.427814,46.373924],"type":"Point"}
}