{
  "type": "Feature",
  "properties": {
    "iso:country":"IT",
    "sg:address":"1, Via Socche Beniamino 42100 Reggio Emilia",
    "sg:classifiers":[
        {
            "category":"Shopping",
            "subcategory":"Clothing, Apparel, & Fashions",
            "type":"Retail Goods"
        }
    ],
    "sg:phone":"+39 0522 371338",
    "sg:postcode":"42100",
    "sg:province":"Reggio Nell'Emilia",
    "sg:tags":[
        "clothes"
    ],
    "wof:name":"Sart Moda Snc Di Cervi Enrico E C.",
    "wof:placetype":"venue"
},
  "geometry": {"coordinates":[10.553543,44.685661],"type":"Point"}
}