{
  "type": "Feature",
  "properties": {
    "addr:full":"27, Via Marconi Guglielmo 50131 Firenze Firenze Firenze 50131",
    "addr:postcode":"50131;50131",
    "addr:street":"Via Marconi Guglielmo",
    "iso:country":"IT",
    "sg:address":"27, Via Marconi Guglielmo 50131 Firenze",
    "sg:city":"Firenze",
    "sg:classifiers":[
        {
            "category":"Professional",
            "subcategory":"Business Services",
            "type":"Services"
        }
    ],
    "sg:phone":"+39 39055579657",
    "sg:postcode":"50131",
    "sg:province":"Firenze",
    "sg:tags":[
        "advice"
    ],
    "wof:name":"Traduco Snc",
    "wof:placetype":"venue"
},
  "geometry": {"coordinates":[11.256902,43.768734],"type":"Point"}
}