{
  "type": "Feature",
  "properties": {
    "iso:country":"IT",
    "sg:address":"81025 Marcianise",
    "sg:city":"Marcianise",
    "sg:orig_category":"Metalli E Leghe",
    "sg:phone":"+39 0823 821060",
    "sg:postcode":"81025",
    "sg:province":"Caserta",
    "wof:name":"Metalli Sud Srl",
    "wof:placetype":"venue"
},
  "geometry": {"coordinates":[14.3296785355,41.0266571045],"type":"Point"}
}