{
  "type": "Feature",
  "properties": {
    "iso:country":"IT",
    "sg:address":"20, Via Poggio Alla Croce 50063 Figline Valdarno",
    "sg:city":"Figline Valdarno",
    "sg:classifiers":[
        {
            "category":"Manufacturing",
            "subcategory":"Tools & Machinery",
            "type":"Manufacturing & Wholesale Goods"
        }
    ],
    "sg:phone":"+39 055 915 5082",
    "sg:postcode":"50063",
    "sg:province":"Firenze",
    "sg:tags":[
        "environment",
        "equipment",
        "-"
    ],
    "wof:name":"Societa' Toscana Ventilazione S.n.c.",
    "wof:placetype":"venue"
},
  "geometry": {"coordinates":[11.409714,43.643177],"type":"Point"}
}