{
  "type": "Feature",
  "properties": {
    "iso:country":"IT",
    "sg:address":"24064 Grumello Del Monte",
    "sg:city":"Grumello del Monte",
    "sg:orig_category":"Forniture Per Abbigliamento E Pelletterie",
    "sg:phone":"+39 035 832574",
    "sg:postcode":"24064",
    "sg:province":"Bergamo",
    "wof:name":"M.a.co. Srl",
    "wof:placetype":"venue"
},
  "geometry": {"coordinates":[9.8785619736,45.6368103027],"type":"Point"}
}