{
  "type": "Feature",
  "properties": {
    "iso:country":"IT",
    "sg:address":"22100 Como",
    "sg:city":"Como",
    "sg:orig_category":"Servizi Vari Di Interesse Pubblico",
    "sg:phone":"+39 031 308059",
    "sg:postcode":"22100",
    "sg:province":"Como",
    "wof:name":"Meeting Di Pellegrino Giovanni",
    "wof:placetype":"venue"
},
  "geometry": {"coordinates":[9.087244,45.812527],"type":"Point"}
}