{
  "type": "Feature",
  "properties": {
    "iso:country":"IT",
    "sg:address":"40017 San Giovanni In Persiceto",
    "sg:city":"San Giovanni in Persiceto",
    "sg:orig_category":"Trattamenti Termici E Superficiali Metalli, Galvanotecnica",
    "sg:phone":"+39 051 821225",
    "sg:postcode":"40017",
    "sg:province":"Bologna",
    "wof:name":"Zincatura Persicetana S.r.l.",
    "wof:placetype":"venue"
},
  "geometry": {"coordinates":[11.209474,44.6632],"type":"Point"}
}