{
  "type": "Feature",
  "properties": {
    "iso:country":"IT",
    "sg:address":"14033 Castell'alfero",
    "sg:orig_category":"Carni, Salumi E Pesci",
    "sg:phone":"+39 0141 270811",
    "sg:postcode":"14033",
    "sg:province":"Asti",
    "wof:name":"Green Lands Srl",
    "wof:placetype":"venue"
},
  "geometry": {"coordinates":[8.205997,44.981102],"type":"Point"}
}