{
  "type": "Feature",
  "properties": {
    "addr:full":"1, Via Filippo Turati 42010 Rio Saliceto Reggio Nell'Emilia 42010",
    "addr:postcode":"42010;42010",
    "addr:street":"Via Filippo Turati",
    "iso:country":"IT",
    "sg:address":"1, Via Filippo Turati 42010 Rio Saliceto",
    "sg:classifiers":[
        {
            "category":"Shopping",
            "type":"Retail Goods"
        }
    ],
    "sg:phone":"+39 0522 649188",
    "sg:postcode":"42010",
    "sg:province":"Reggio Nell'Emilia",
    "sg:tags":[
        "finished",
        "-",
        "metallic"
    ],
    "wof:name":"Masselli S.r.l.",
    "wof:placetype":"venue"
},
  "geometry": {"coordinates":[10.8164148331,44.8101844788],"type":"Point"}
}