{
  "type": "Feature",
  "properties": {
    "iso:country":"IT",
    "sg:address":"88, Localita' S. Vitale 43038 Sala Baganza",
    "sg:city":"Sala Baganza",
    "sg:classifiers":[
        {
            "category":"Food & Beverages",
            "subcategory":"Groceries & Convenience Stores",
            "type":"Retail Goods"
        }
    ],
    "sg:phone":"+39 0521 830517",
    "sg:postcode":"43038",
    "sg:province":"Parma",
    "sg:tags":[
        "product",
        "related"
    ],
    "wof:name":"Prosciutti Castoldi S.p.a",
    "wof:placetype":"venue"
},
  "geometry": {"coordinates":[10.2209815979,44.6952857971],"type":"Point"}
}