{
  "type": "Feature",
  "properties": {
    "addr:full":"Via Favetti 16 34170 Gorizia Gorizia Gorizia 34170",
    "addr:housenumber":"16",
    "addr:postcode":"34170;34170",
    "addr:street":"Via Favetti",
    "iso:country":"IT",
    "sg:address":"Via Favetti 16 34170 Gorizia",
    "sg:city":"Gorizia",
    "sg:classifiers":[
        {
            "category":"Wholesale",
            "subcategory":"Metals & Minerals",
            "type":"Manufacturing & Wholesale Goods"
        }
    ],
    "sg:phone":"+39 0481 536120",
    "sg:postcode":"34170",
    "sg:province":"Gorizia",
    "sg:tags":[
        "export"
    ],
    "wof:name":"Sic Srl",
    "wof:placetype":"venue"
},
  "geometry": {"coordinates":[13.6282787323,45.9476013184],"type":"Point"}
}