{
  "type": "Feature",
  "properties": {
    "iso:country":"IT",
    "sg:address":"09028 Sestu",
    "sg:city":"Sestu",
    "sg:orig_category":"Macchine Ed Impianti Per Edilizia E Lavori Pubblici",
    "sg:phone":"+39 070 22357",
    "sg:postcode":"09028",
    "sg:province":"Cagliari",
    "wof:name":"Fornaci Scanu (s.p.a.)",
    "wof:placetype":"venue"
},
  "geometry": {"coordinates":[9.090287,39.306751],"type":"Point"}
}