{
  "type": "Feature",
  "properties": {
    "iso:country":"IT",
    "sg:address":"41100 Modena",
    "sg:city":"Modena",
    "sg:orig_category":"Macchine, Impianti Ed Attrezzature Per Abbigliamento E Pelletterie",
    "sg:phone":"+39 059 356163",
    "sg:postcode":"41100",
    "sg:province":"Modena",
    "wof:name":"Vaccari Luciano",
    "wof:placetype":"venue"
},
  "geometry": {"coordinates":[10.91656,44.634132],"type":"Point"}
}