{
  "type": "Feature",
  "properties": {
    "iso:country":"IT",
    "sg:address":"Via Corer 56 30016 Jesolo",
    "sg:classifiers":[
        {
            "category":"Juice Bar",
            "subcategory":"None",
            "type":"Food & Drink"
        }
    ],
    "sg:phone":"+39 0421 961501",
    "sg:postcode":"30016",
    "sg:province":"Venezia",
    "sg:tags":[
        "granite",
        "slab"
    ],
    "sg:website":"www.capeletomarmi.it",
    "wof:name":"Capeleto Marmi Snc",
    "wof:placetype":"venue"
},
  "geometry": {"coordinates":[12.338784,45.434338],"type":"Point"}
}