{
  "type": "Feature",
  "properties": {
    "iso:country":"IT",
    "sg:address":"2, Via Ricasoli Bettino 20121 Milano",
    "sg:city":"Milano",
    "sg:classifiers":[
        {
            "category":"Shopping",
            "subcategory":"Stationery & Office Supplies",
            "type":"Retail Goods"
        }
    ],
    "sg:phone":"+39 390 287 7642",
    "sg:postcode":"20121",
    "sg:province":"Milano",
    "sg:tags":[
        "professional"
    ],
    "wof:name":"Trau Spa",
    "wof:placetype":"venue"
},
  "geometry": {"coordinates":[9.1795310974,45.468006134],"type":"Point"}
}