{
  "type": "Feature",
  "properties": {
    "iso:country":"IT",
    "sg:address":"29100 Piacenza",
    "sg:city":"Piacenza",
    "sg:orig_category":"Parrucche E Toupets",
    "sg:phone":"+39 0523 591479",
    "sg:postcode":"29100",
    "sg:province":"Piacenza",
    "wof:name":"C.l.a.s. Di Armando Gazzola & C. Snc",
    "wof:placetype":"venue"
},
  "geometry": {"coordinates":[9.7673749924,45.050365448],"type":"Point"}
}