{
  "type": "Feature",
  "properties": {
    "iso:country":"IT",
    "sg:address":"20123 Milano",
    "sg:city":"Milano",
    "sg:orig_category":"Agenzie Di Spettacolo E Di Animazione",
    "sg:phone":"+39 02 467521",
    "sg:postcode":"20123",
    "sg:province":"Milano",
    "sg:website":"http://www.elite.it",
    "wof:name":"Elite Model Management",
    "wof:placetype":"venue"
},
  "geometry": {"coordinates":[9.166168,45.464626],"type":"Point"}
}