{
  "type": "Feature",
  "properties": {
    "addr:full":"22063 Cantu' Como 22063",
    "addr:postcode":"22063;22063",
    "addr:street":"Cantu ' Como",
    "iso:country":"IT",
    "sg:address":"22063 Cantu'",
    "sg:orig_category":"Metalli E Leghe",
    "sg:phone":"+39 031 714306",
    "sg:postcode":"22063",
    "sg:province":"Como",
    "wof:name":"Molteni Luigi",
    "wof:placetype":"venue"
},
  "geometry": {"coordinates":[9.1296234131,45.739074707],"type":"Point"}
}