{
  "type": "Feature",
  "properties": {
    "iso:country":"IT",
    "sg:address":"10075 Mathi",
    "sg:city":"Mathi",
    "sg:orig_category":"Materiali Edili",
    "sg:phone":"+39 011 926 8187",
    "sg:postcode":"10075",
    "sg:province":"Torino",
    "wof:name":"Edil - Uno (s.r.l.)",
    "wof:placetype":"venue"
},
  "geometry": {"coordinates":[7.546268,45.296818],"type":"Point"}
}