{
  "type": "Feature",
  "properties": {
    "iso:country":"IT",
    "sg:address":"24011 Alme'",
    "sg:orig_category":"Elettrotecnica Industriale, Prodotti E Apparecchiature. Elettronica Industriale, Prodotti E Apparecchiature",
    "sg:phone":"+39 035 543160",
    "sg:postcode":"24011",
    "sg:province":"Bergamo",
    "sg:website":"http://www.emivanoncini.it",
    "wof:name":"Emi Impianti Elettrici Di Vanoncini R. & C. Sas",
    "wof:placetype":"venue"
},
  "geometry": {"coordinates":[9.616327,45.744717],"type":"Point"}
}