{
  "type": "Feature",
  "properties": {
    "iso:country":"IT",
    "sg:address":"Via P.nenni 82024 Castelpagano",
    "sg:city":"Castelpagano",
    "sg:classifiers":[
        {
            "category":"Real Estate",
            "subcategory":"Architect",
            "type":"Services"
        }
    ],
    "sg:phone":"+39 0824 935065",
    "sg:postcode":"82024",
    "sg:province":"Benevento",
    "sg:tags":[
        "textile",
        "clothing"
    ],
    "wof:name":"Confezioni Europa Srl",
    "wof:placetype":"venue"
},
  "geometry": {"coordinates":[14.781174,41.130447],"type":"Point"}
}