{
  "type": "Feature",
  "properties": {
    "iso:country":"IT",
    "sg:address":"90141 Palermo",
    "sg:city":"Palermo",
    "sg:classifiers":[
        {
            "category":"Health Services",
            "subcategory":"Health Practitioner",
            "type":"Services"
        }
    ],
    "sg:phone":"+39 091 587122",
    "sg:postcode":"90141",
    "sg:province":"Palermo",
    "sg:tags":[
        "medici"
    ],
    "sg:website":"http://www.candelaspa.it",
    "wof:name":"Casa Di Cura Candela Spa",
    "wof:placetype":"venue"
},
  "geometry": {"coordinates":[13.355134,38.122822],"type":"Point"}
}