{
  "type": "Feature",
  "properties": {
    "iso:country":"IT",
    "sg:address":"Piazza Della Liberta 8-10; Gaeta; 04024",
    "sg:city":"Gaeta",
    "sg:classifiers":[
        {
            "category":"Banks & Credit Unions",
            "subcategory":"Bank",
            "type":"Services"
        }
    ],
    "sg:phone":"+39 0771 460201",
    "sg:postcode":"04024",
    "sg:province":"Latina",
    "wof:name":"Banco Di Napoli Spa",
    "wof:placetype":"venue"
},
  "geometry": {"coordinates":[13.570771,41.214737],"type":"Point"}
}