{
  "type": "Feature",
  "properties": {
    "iso:country":"IT",
    "sg:address":"20, V. Dante - Caselle 35030 Selvazzano Dentro",
    "sg:city":"Caselle",
    "sg:classifiers":[
        {
            "category":"Wholesale",
            "subcategory":"Medical Equipment & Supplies",
            "type":"Manufacturing & Wholesale Goods"
        }
    ],
    "sg:phone":"+39 049 897 6455",
    "sg:postcode":"35030",
    "sg:province":"Padova",
    "sg:tags":[
        "-",
        "health",
        "instrument"
    ],
    "sg:website":"http://www.omsstaff.com",
    "wof:name":"O.m.s. Spa - Officine Meccaniche Specializzate",
    "wof:placetype":"venue"
},
  "geometry": {"coordinates":[11.806561,45.418049],"type":"Point"}
}