{
  "type": "Feature",
  "properties": {
    "iso:country":"IT",
    "sg:address":"Contrada San Giacomo 93014 Mussomeli",
    "sg:city":"Mussomeli",
    "sg:classifiers":[
        {
            "category":"Wholesale",
            "subcategory":"Machinery & Supplies",
            "type":"Manufacturing & Wholesale Goods"
        }
    ],
    "sg:phone":"+39 0934 993164",
    "sg:postcode":"93014",
    "sg:province":"Caltanissetta",
    "sg:tags":[
        "-",
        "agriculture",
        "equipment"
    ],
    "wof:name":"Sicil Zappa Giardina Salv. M. E C Snc",
    "wof:placetype":"venue"
},
  "geometry": {"coordinates":[14.06329,37.48991],"type":"Point"}
}