{
  "type": "Feature",
  "properties": {
    "iso:country":"IT",
    "sg:address":"65013 Citta'santangelo",
    "sg:orig_category":"Prodotti Di Base E Forniture Per Industria Alimentare E Bevande. Prodotti Chimici Di Base",
    "sg:phone":"+39 085 95116",
    "sg:postcode":"65013",
    "sg:province":"Pescara",
    "wof:name":"Real Aromi Spa",
    "wof:placetype":"venue"
},
  "geometry": {"coordinates":[14.214094162,42.4648246765],"type":"Point"}
}