{
  "type": "Feature",
  "properties": {
    "addr:full":"06073 Corciano Corciano Perugia 06073",
    "addr:postcode":"06073;06073",
    "iso:country":"IT",
    "sg:address":"06073 Corciano",
    "sg:city":"Corciano",
    "sg:orig_category":"Elettrotecnica Professionale E Di Consumo. Forniture Per Attivita' Commerciali Ed Artigianali",
    "sg:phone":"+39 075 517 3140",
    "sg:postcode":"06073",
    "sg:province":"Perugia",
    "sg:website":"http://www.bluepubblicita.it",
    "wof:name":"Blue Pubblicita' Di Pauselli & Taramelli Snc",
    "wof:placetype":"venue"
},
  "geometry": {"coordinates":[12.298871,43.099777],"type":"Point"}
}