{
  "type": "Feature",
  "properties": {
    "iso:country":"IT",
    "sg:address":"45, Via Piceno Aprutina 63100 Ascoli Piceno",
    "sg:city":"Ascoli Piceno",
    "sg:classifiers":[
        {
            "category":"Manufacturing",
            "subcategory":"Rubber & Plastics",
            "type":"Manufacturing & Wholesale Goods"
        }
    ],
    "sg:phone":"+39 39073635251",
    "sg:postcode":"63100",
    "sg:province":"Ascoli Piceno",
    "sg:tags":[
        "packaging",
        "material",
        "-"
    ],
    "wof:name":"Schmalbach-lubeca Italia Srl",
    "wof:placetype":"venue"
},
  "geometry": {"coordinates":[13.6200313568,42.8437271118],"type":"Point"}
}