{
  "type": "Feature",
  "properties": {
    "addr:full":"Via Serravalle 99 15061 Arquata Scrivia Arquata Scrivia Alessandria 15061",
    "addr:housenumber":"99",
    "addr:postcode":"15061;15061",
    "addr:street":"Via Serravalle;Scrivia",
    "iso:country":"IT",
    "sg:address":"Via Serravalle 99 15061 Arquata Scrivia",
    "sg:city":"Arquata Scrivia",
    "sg:classifiers":[
        {
            "category":"Food & Beverages",
            "subcategory":"Chocolate",
            "type":"Retail Goods"
        }
    ],
    "sg:phone":"+39 0143 635382",
    "sg:postcode":"15061",
    "sg:province":"Alessandria",
    "sg:website":"www.lasuissa.it",
    "wof:name":"La Suissa Srl",
    "wof:placetype":"venue"
},
  "geometry": {"coordinates":[8.867939,44.702629],"type":"Point"}
}