{
  "type": "Feature",
  "properties": {
    "iso:country":"IT",
    "sg:address":"10093 Collegno",
    "sg:city":"Collegno",
    "sg:orig_category":"Termotecnica E Riscaldamento, Apparecchiature E Servizi",
    "sg:phone":"+39 011 403 1292",
    "sg:postcode":"10093",
    "sg:province":"Torino",
    "wof:name":"B - F Tubi Di Benvegnu' U. E Ferraris C. (s.n.c.)",
    "wof:placetype":"venue"
},
  "geometry": {"coordinates":[7.603596,45.071712],"type":"Point"}
}