{
  "type": "Feature",
  "properties": {
    "addr:full":"Km. 46, Strada St. Paullese 26012 Castelleone Castelleone Cremona 26012",
    "addr:postcode":"26012;26012",
    "addr:street":"Km. 46 Strada St. Paullese",
    "iso:country":"IT",
    "sg:address":"Km. 46, Strada St. Paullese 26012 Castelleone",
    "sg:city":"Castelleone",
    "sg:classifiers":[
        {
            "category":"Professional",
            "subcategory":"Engineering",
            "type":"Services"
        }
    ],
    "sg:phone":"+39 39037458093",
    "sg:postcode":"26012",
    "sg:province":"Cremona",
    "sg:tags":[
        "machine",
        "-",
        "mechanical"
    ],
    "wof:name":"Benelli Annibale Di Benelli Claudio E C. Snc",
    "wof:placetype":"venue"
},
  "geometry": {"coordinates":[10.026135,45.133499],"type":"Point"}
}