{
  "type": "Feature",
  "properties": {
    "addr:full":"23, Via Nazionale Lemignano 43044 Collecchio Collecchio Parma 43044",
    "addr:postcode":"43044;43044",
    "addr:street":"Via Nazionale Lemignano",
    "iso:country":"IT",
    "sg:address":"23, Via Nazionale Lemignano 43044 Collecchio",
    "sg:city":"Collecchio",
    "sg:classifiers":[
        {
            "category":"Professional",
            "subcategory":"Printing & Photocopies",
            "type":"Services"
        }
    ],
    "sg:phone":"+39 0521 804106",
    "sg:postcode":"43044",
    "sg:province":"Parma",
    "wof:name":"Artegrafica Silva (s.r.l.)",
    "wof:placetype":"venue"
},
  "geometry": {"coordinates":[10.2678937912,44.7727203369],"type":"Point"}
}