{
  "type": "Feature",
  "properties": {
    "iso:country":"IT",
    "sg:address":"00060 Roma",
    "sg:orig_category":"Servizi E Lavori Per Ecologia E Smaltimento Rifiuti. Arte Ed Artigianato Artistico. Servizi Ausiliari Di Sorveglianza, Manutenzione E Pulizia",
    "sg:phone":"+39 06 3043 9433",
    "sg:postcode":"00060",
    "sg:province":"Roma",
    "wof:name":"Fassio Adriano",
    "wof:placetype":"venue"
},
  "geometry": {"coordinates":[12.482325,41.895466],"type":"Point"}
}