{
  "type": "Feature",
  "properties": {
    "addr:full":"40068 San Lazzaro Di Savena San Lazzaro Bologna 40068",
    "addr:housenumber":"40068",
    "addr:postcode":"40068",
    "addr:street":"San;San;Bologna",
    "iso:country":"IT",
    "sg:address":"40068 San Lazzaro Di Savena",
    "sg:city":"San Lazzaro",
    "sg:orig_category":"Prodotti Finiti Stampati. Forniture E Prodotti Informatici. Forniture Per Uffici",
    "sg:phone":"+39 051 625 6106",
    "sg:postcode":"40068",
    "sg:province":"Bologna",
    "wof:name":"C.i.a.e. Etichette",
    "wof:placetype":"venue"
},
  "geometry": {"coordinates":[11.432806015,44.4689369202],"type":"Point"}
}