{
  "type": "Feature",
  "properties": {
    "addr:full":"Via Trentino Alto Adige 5 59100 Prato Prato Prato 59100",
    "addr:housenumber":"5",
    "addr:postcode":"59100;59100",
    "addr:street":"Via Trentino Alto Adige",
    "iso:country":"IT",
    "sg:address":"Via Trentino Alto Adige 5 59100 Prato",
    "sg:city":"Prato",
    "sg:classifiers":[
        {
            "category":"Manufacturing",
            "subcategory":"Textiles",
            "type":"Manufacturing & Wholesale Goods"
        }
    ],
    "sg:phone":"+39 0574 622177",
    "sg:postcode":"59100",
    "sg:province":"Prato",
    "sg:tags":[
        "fibre",
        "natural"
    ],
    "sg:website":"www.fibreresources.it",
    "wof:name":"Fibre Resources Spa",
    "wof:placetype":"venue"
},
  "geometry": {"coordinates":[11.051266,43.860767],"type":"Point"}
}