{
  "type": "Feature",
  "properties": {
    "addr:full":"43018 Sissa Sissa Parma 43018",
    "addr:postcode":"43018;43018",
    "iso:country":"IT",
    "sg:address":"43018 Sissa",
    "sg:city":"Sissa",
    "sg:orig_category":"Apparecchi, Attrezzature E Forniture Per Centri Estetici. Forniture Per Attivita' Commerciali Ed Artigianali",
    "sg:phone":"+39 0521 944981",
    "sg:postcode":"43018",
    "sg:province":"Parma",
    "wof:name":"Kappa Cosmetics",
    "wof:placetype":"venue"
},
  "geometry": {"coordinates":[10.248907,44.967834],"type":"Point"}
}