{
  "type": "Feature",
  "properties": {
    "iso:country":"IT",
    "sg:address":"20131 Milano",
    "sg:city":"Milano",
    "sg:orig_category":"Scuole E Servizi Scolastici",
    "sg:phone":"+39 02 7063 5873",
    "sg:postcode":"20131",
    "sg:province":"Milano",
    "wof:name":"Arcadia Srl Centro Formazione Studi",
    "wof:placetype":"venue"
},
  "geometry": {"coordinates":[9.230967,45.483444],"type":"Point"}
}