{
  "type": "Feature",
  "properties": {
    "addr:full":"18, Via Melzi D'eril Francesco 20154 Milano Milano Milano 20154",
    "addr:postcode":"20154;20154",
    "addr:street":"Via Melzi D'Eril Francesco",
    "iso:country":"IT",
    "sg:address":"18, Via Melzi D'eril Francesco 20154 Milano",
    "sg:city":"Milano",
    "sg:classifiers":[
        {
            "category":"Manufacturing",
            "subcategory":"Metals",
            "type":"Manufacturing & Wholesale Goods"
        }
    ],
    "sg:phone":"+39 390 231 1653",
    "sg:postcode":"20154",
    "sg:province":"Milano",
    "sg:tags":[
        "metallurgy",
        "metalworking"
    ],
    "wof:name":"Brera Cerniere S.r.l.",
    "wof:placetype":"venue"
},
  "geometry": {"coordinates":[9.1731405258,45.4784240723],"type":"Point"}
}