{
  "type": "Feature",
  "properties": {
    "iso:country":"IT",
    "sg:address":"07010 Benetutti",
    "sg:city":"Benetutti",
    "sg:orig_category":"Alberghi E Strutture Extra Alberghiere. Ospedali E Servizi Sanitari",
    "sg:phone":"+39 079 791081",
    "sg:postcode":"07010",
    "sg:province":"Sassari",
    "wof:name":"Terme San Saturnino",
    "wof:placetype":"venue"
},
  "geometry": {"coordinates":[9.169852,40.4575],"type":"Point"}
}