{
  "type": "Feature",
  "properties": {
    "iso:country":"IT",
    "sg:address":"46100 Mantova",
    "sg:city":"Mantova",
    "sg:orig_category":"Forniture Per Uffici",
    "sg:phone":"+39 0376 327628",
    "sg:postcode":"46100",
    "sg:province":"Mantova",
    "wof:name":"Colorificio Piedimonte",
    "wof:placetype":"venue"
},
  "geometry": {"coordinates":[10.7990436554,45.1578903198],"type":"Point"}
}