{
  "type": "Feature",
  "properties": {
    "iso:country":"IT",
    "sg:address":"20098 S.giuliano Milanese",
    "sg:orig_category":"Arti Grafiche",
    "sg:phone":"+39 02 9828 1840",
    "sg:postcode":"20098",
    "sg:province":"Milano",
    "wof:name":"Sinergie Srl",
    "wof:placetype":"venue"
},
  "geometry": {"coordinates":[9.257906,45.400867],"type":"Point"}
}