{
  "type": "Feature",
  "properties": {
    "addr:full":"Strada St. 274 73014 Gallipoli Gallipoli Lecce 73014",
    "addr:housenumber":"274",
    "addr:postcode":"73014;73014",
    "addr:street":"Strada St.",
    "iso:country":"IT",
    "sg:address":"Strada St. 274 73014 Gallipoli",
    "sg:city":"Gallipoli",
    "sg:classifiers":[
        {
            "category":"Shopping",
            "type":"Retail Goods"
        }
    ],
    "sg:phone":"+39 0833 202012",
    "sg:postcode":"73014",
    "sg:province":"Lecce",
    "sg:tags":[
        "finished",
        "-",
        "metallic"
    ],
    "wof:name":"Ranger Italia Srl",
    "wof:placetype":"venue"
},
  "geometry": {"coordinates":[18.1740150452,40.3532905579],"type":"Point"}
}