{
  "type": "Feature",
  "properties": {
    "iso:country":"IT",
    "sg:address":"24040 Chignolo D'isola",
    "sg:orig_category":"Macchine Tessili",
    "sg:phone":"+39 035 904890",
    "sg:postcode":"24040",
    "sg:province":"Bergamo",
    "sg:website":"http://www.formianuova.it",
    "wof:name":"Formia Nuova Srl",
    "wof:placetype":"venue"
},
  "geometry": {"coordinates":[9.532098,45.674789],"type":"Point"}
}