{
  "type": "Feature",
  "properties": {
    "iso:country":"IT",
    "sg:address":"Via Rosa Luxemburg 24 42010 Rio Saliceto",
    "sg:classifiers":[
        {
            "category":"Ferry Terminal",
            "type":"Transportation"
        }
    ],
    "sg:phone":"+39 0522 647192",
    "sg:postcode":"42010",
    "sg:province":"Reggio Nell'Emilia",
    "sg:tags":[
        "trolley",
        "hoist",
        "electric"
    ],
    "sg:website":"www.fantozzi.com",
    "wof:name":"Fantozzi Electric Carts Srl",
    "wof:placetype":"venue"
},
  "geometry": {"coordinates":[10.810156,44.814068],"type":"Point"}
}