{
  "type": "Feature",
  "properties": {
    "iso:country":"IT",
    "sg:address":"Via Dell' Industria 26020 Cappella Cantone",
    "sg:city":"Cappella Cantone",
    "sg:classifiers":[
        {
            "category":"Professional",
            "subcategory":"Engineering",
            "type":"Services"
        }
    ],
    "sg:phone":"+39 0374 340814",
    "sg:postcode":"26020",
    "sg:province":"Cremona",
    "sg:tags":[
        "machine",
        "-",
        "mechanical"
    ],
    "wof:name":"Euro Inox Srl",
    "wof:placetype":"venue"
},
  "geometry": {"coordinates":[9.839319,45.242943],"type":"Point"}
}