{
  "type": "Feature",
  "properties": {
    "addr:full":"56, Corso Lecce 10143 Torino Torino Torino 10143",
    "addr:postcode":"10143;10143",
    "addr:street":"Corso Lecce",
    "iso:country":"IT",
    "sg:address":"56, Corso Lecce 10143 Torino",
    "sg:city":"Torino",
    "sg:classifiers":[
        {
            "category":"Home & Garden",
            "subcategory":"Home Furnishings",
            "type":"Retail Goods"
        }
    ],
    "sg:phone":"+39 011 771 0777",
    "sg:postcode":"10143",
    "sg:province":"Torino",
    "sg:tags":[
        "household"
    ],
    "wof:name":"Cappa Erasmo Successori (s.p.a.)",
    "wof:placetype":"venue"
},
  "geometry": {"coordinates":[7.646992,45.080135],"type":"Point"}
}