{
  "type": "Feature",
  "properties": {
    "addr:full":"72, V. Camollia 53100 Siena Siena Siena 53100",
    "addr:housenumber":"72",
    "addr:postcode":"53100;53100",
    "addr:street":"V. Camollia",
    "iso:country":"IT",
    "sg:address":"72, V. Camollia 53100 Siena",
    "sg:city":"Siena",
    "sg:classifiers":[
        {
            "category":"Food & Beverages",
            "subcategory":"Groceries & Convenience Stores",
            "type":"Retail Goods"
        }
    ],
    "sg:phone":"+39 0577 228811",
    "sg:postcode":"53100",
    "sg:province":"Siena",
    "sg:tags":[
        "drink"
    ],
    "sg:website":"http://www.enoteca-italiana.it",
    "wof:name":"Enoteca Italiana",
    "wof:placetype":"venue"
},
  "geometry": {"coordinates":[11.327516,43.325027],"type":"Point"}
}