{
  "type": "Feature",
  "properties": {
    "iso:country":"IT",
    "sg:address":"10124 Torino",
    "sg:city":"Torino",
    "sg:orig_category":"Forniture Per Uffici",
    "sg:phone":"+39 011 817 7642",
    "sg:postcode":"10124",
    "sg:province":"Torino",
    "wof:name":"Il Gabbiano Snc Di Pirrello & Ferrario",
    "wof:placetype":"venue"
},
  "geometry": {"coordinates":[7.6855692863,45.0710258484],"type":"Point"}
}