{
  "type": "Feature",
  "properties": {
    "addr:full":"00176 Roma Roma Roma 00176",
    "addr:postcode":"00176;00176",
    "iso:country":"IT",
    "sg:address":"00176 Roma",
    "sg:city":"Roma",
    "sg:orig_category":"Centri Di Estetica E Cosmesi E Servizi. Prodotti Cosmetici E Da Toeletta",
    "sg:phone":"+39 06 702 4489",
    "sg:postcode":"00176",
    "sg:province":"Roma",
    "wof:name":"Beautiful Wig Srl",
    "wof:placetype":"venue"
},
  "geometry": {"coordinates":[12.893683,41.888977],"type":"Point"}
}