{
  "type": "Feature",
  "properties": {
    "addr:full":"20146 Milano Milano Milano 20146",
    "addr:postcode":"20146;20146",
    "iso:country":"IT",
    "sg:address":"20146 Milano",
    "sg:city":"Milano",
    "sg:orig_category":"Servizi E Lavori Per Abbigliamento E Pelletterie",
    "sg:phone":"+39 02 418037",
    "sg:postcode":"20146",
    "sg:province":"Milano",
    "wof:name":"De Cola Vincenza",
    "wof:placetype":"venue"
},
  "geometry": {"coordinates":[9.135961,45.45459],"type":"Point"}
}