{
  "type": "Feature",
  "properties": {
    "iso:country":"IT",
    "sg:address":"24121 Bergamo",
    "sg:city":"Bergamo",
    "sg:orig_category":"Agenzie D'affari E Servizi Commerciali. Acqua, Luce, Gas E Societa' Di Esercizio Pubblico",
    "sg:phone":"+39 035 234967",
    "sg:postcode":"24121",
    "sg:province":"Bergamo",
    "wof:name":"V.g.c. (s.r.l.)",
    "wof:placetype":"venue"
},
  "geometry": {"coordinates":[9.679131,45.694668],"type":"Point"}
}