{
  "type": "Feature",
  "properties": {
    "iso:country":"IT",
    "sg:address":"41057 Spilamberto",
    "sg:city":"Spilamberto",
    "sg:orig_category":"Cancelli, Porte E Portoni Automatici E Telecomandati",
    "sg:phone":"+39 059 783379",
    "sg:postcode":"41057",
    "sg:province":"Modena",
    "wof:name":"Astolfi Federico Di Astolfi Federico & C. Sas",
    "wof:placetype":"venue"
},
  "geometry": {"coordinates":[11.019958,44.519794],"type":"Point"}
}