{
  "type": "Feature",
  "properties": {
    "iso:country":"IT",
    "sg:address":"42100 Reggio Emilia",
    "sg:orig_category":"Arredi Ed Attrezzature Per Uffici",
    "sg:phone":"+39 0522 332260",
    "sg:postcode":"42100",
    "sg:province":"Reggio Nell'Emilia",
    "sg:website":"http://www.rabittiriccardo.it",
    "wof:name":"Rabitti Riccardo",
    "wof:placetype":"venue"
},
  "geometry": {"coordinates":[10.667153,44.682949],"type":"Point"}
}