{
  "type": "Feature",
  "properties": {
    "addr:full":"28885 Piedimulera Piedimulera Verbano-Cusio-Ossola 28885",
    "addr:postcode":"28885;28885",
    "iso:country":"IT",
    "sg:address":"28885 Piedimulera",
    "sg:city":"Piedimulera",
    "sg:orig_category":"Pubblica Amministrazione",
    "sg:phone":"+39 0324 842027",
    "sg:postcode":"28885",
    "sg:province":"Verbano-Cusio-Ossola",
    "wof:name":"Corpo Forestale Dello Stato",
    "wof:placetype":"venue"
},
  "geometry": {"coordinates":[8.2592182159,46.0246772766],"type":"Point"}
}