{
  "type": "Feature",
  "properties": {
    "iso:country":"IT",
    "sg:address":"22046 Merone",
    "sg:city":"Merone",
    "sg:orig_category":"Non-classified Establishments",
    "sg:phone":"+39 031 651551",
    "sg:postcode":"22046",
    "sg:province":"Como",
    "wof:name":"Savoldelli Mario",
    "wof:placetype":"venue"
},
  "geometry": {"coordinates":[9.044816,45.787258],"type":"Point"}
}