{
  "type": "Feature",
  "properties": {
    "iso:country":"IT",
    "sg:address":"00049 Velletri",
    "sg:city":"Velletri",
    "sg:orig_category":"Telecomunicazioni E Telefonia, Impianti, Apparecchi E Servizi",
    "sg:phone":"+39 06 962 7834",
    "sg:postcode":"00049",
    "sg:province":"Roma",
    "wof:name":"Computer Des Di Alfredo Ercolani Sas",
    "wof:placetype":"venue"
},
  "geometry": {"coordinates":[12.782477,41.659153],"type":"Point"}
}