{
  "type": "Feature",
  "properties": {
    "addr:full":"00165 Roma Roma Roma 00165",
    "addr:postcode":"00165;00165",
    "iso:country":"IT",
    "sg:address":"00165 Roma",
    "sg:city":"Roma",
    "sg:classifiers":[
        {
            "category":"Health Services",
            "subcategory":"Health Practitioner",
            "type":"Services"
        }
    ],
    "sg:phone":"+39 06 663 4750",
    "sg:postcode":"00165",
    "sg:province":"Roma",
    "sg:tags":[
        "medici"
    ],
    "wof:name":"Chinni Luca",
    "wof:placetype":"venue"
},
  "geometry": {"coordinates":[12.430879,41.896091],"type":"Point"}
}