{
  "type": "Feature",
  "properties": {
    "addr:full":"21057 Olgiate Olona Olgiate Olona Varese 21057",
    "addr:postcode":"21057;21057",
    "iso:country":"IT",
    "sg:address":"21057 Olgiate Olona",
    "sg:city":"Olgiate Olona",
    "sg:orig_category":"Macchine, Impianti Ed Attrezzature Per Industria Alimentare E Bevande. Forniture Alle Strutture Ricettive. Macchine E Impianti Per Attivita' Commerciali Ed Artigianali",
    "sg:phone":"+39 0331 643332",
    "sg:postcode":"21057",
    "sg:province":"Varese",
    "wof:name":"Elangrill (s.r.l.)",
    "wof:placetype":"venue"
},
  "geometry": {"coordinates":[8.87495,45.631645],"type":"Point"}
}