{
  "type": "Feature",
  "properties": {
    "iso:country":"IT",
    "sg:address":"10050 Borgone Susa",
    "sg:city":"Borgone Susa",
    "sg:orig_category":"Utensili Meccanici E Materiali",
    "sg:phone":"+39 011 964 6597",
    "sg:postcode":"10050",
    "sg:province":"Torino",
    "wof:name":"Autoblock S.p.a.",
    "wof:placetype":"venue"
},
  "geometry": {"coordinates":[7.22759,45.127102],"type":"Point"}
}