{
  "type": "Feature",
  "properties": {
    "iso:country":"IT",
    "sg:address":"00141 Roma",
    "sg:city":"Roma",
    "sg:orig_category":"Elettronica Professionale E Di Consumo. Forniture Industriali Per Prevenzione, Controllo E Sicurezza",
    "sg:phone":"+39 06 817 7250",
    "sg:postcode":"00141",
    "sg:province":"Roma",
    "wof:name":"Tekmea",
    "wof:placetype":"venue"
},
  "geometry": {"coordinates":[12.529391,41.939072],"type":"Point"}
}