{
  "type": "Feature",
  "properties": {
    "iso:country":"IT",
    "sg:address":"28100 Novara",
    "sg:city":"Novara",
    "sg:orig_category":"Arredi Ed Attrezzature Per Uffici",
    "sg:phone":"+39 0321 33344",
    "sg:postcode":"28100",
    "sg:province":"Novara",
    "sg:website":"http://www.natalisrl.com",
    "wof:name":"Natali Srl",
    "wof:placetype":"venue"
},
  "geometry": {"coordinates":[8.619815,45.449013],"type":"Point"}
}