{
  "type": "Feature",
  "properties": {
    "addr:full":"41012 Fossoli Fossoli Modena 41012",
    "addr:postcode":"41012;41012",
    "addr:street":"Fossoli",
    "iso:country":"IT",
    "sg:address":"41012 Fossoli",
    "sg:city":"Fossoli",
    "sg:orig_category":"Dolciumi E Gelati",
    "sg:phone":"+39 059 660663",
    "sg:postcode":"41012",
    "sg:province":"Modena",
    "wof:name":"Rossi Tazio",
    "wof:placetype":"venue"
},
  "geometry": {"coordinates":[10.894009,44.819019],"type":"Point"}
}