{
  "type": "Feature",
  "properties": {
    "iso:country":"IT",
    "sg:address":"40033 Casalecchio Di Reno",
    "sg:city":"Casalecchio di Reno",
    "sg:orig_category":"Cine-foto-ottica. Articoli Medico-sanitari Ed Ortopedici",
    "sg:phone":"+39 051 613 1907",
    "sg:postcode":"40033",
    "sg:province":"Bologna",
    "wof:name":"Calzati Giorgio",
    "wof:placetype":"venue"
},
  "geometry": {"coordinates":[11.278124,44.478611],"type":"Point"}
}