{
  "type": "Feature",
  "properties": {
    "iso:country":"IT",
    "sg:address":"Via Manzoni; Zane; 36010",
    "sg:classifiers":[
        {
            "category":"Banks & Credit Unions",
            "subcategory":"Bank",
            "type":"Services"
        }
    ],
    "sg:phone":"+39 0445 380224",
    "sg:postcode":"36010",
    "sg:province":"Vicenza",
    "wof:name":"Banca Popolare Vicentina Scparl",
    "wof:placetype":"venue"
},
  "geometry": {"coordinates":[11.459937,45.715202],"type":"Point"}
}