{
  "type": "Feature",
  "properties": {
    "iso:country":"IT",
    "sg:address":"Corso Nazionale, 252; La Spezia; 19100",
    "sg:classifiers":[
        {
            "category":"Banks & Credit Unions",
            "subcategory":"Bank",
            "type":"Services"
        }
    ],
    "sg:phone":"+39 0187 517 3000",
    "wof:name":"Cassa Di Risparmio Di Genova, E Imperia",
    "wof:placetype":"venue"
},
  "geometry": {"coordinates":[9.842253,44.117634],"type":"Point"}
}