{
  "type": "Feature",
  "properties": {
    "iso:country":"IT",
    "sg:address":"Via Mazzini 1; Candelo; 13062",
    "sg:classifiers":[
        {
            "category":"Banks & Credit Unions",
            "subcategory":"Bank",
            "type":"Services"
        }
    ],
    "sg:phone":"+39 015 253 6101",
    "wof:name":"Istituto Bancario, San Paolo Do Torino Spa",
    "wof:placetype":"venue"
},
  "geometry": {"coordinates":[8.054773,45.538212],"type":"Point"}
}