{
  "type": "Feature",
  "properties": {
    "addr:full":"22070 Limido Comasco Limido Comasco Como 22070",
    "addr:housenumber":"comasco",
    "addr:postcode":"22070;22070",
    "addr:street":"Comasco",
    "iso:country":"IT",
    "sg:address":"22070 Limido Comasco",
    "sg:city":"Limido Comasco",
    "sg:orig_category":"Forniture Per Agricoltura E Zootecnia. Animali Domestici",
    "sg:phone":"+39 031 895203",
    "sg:postcode":"22070",
    "sg:province":"Como",
    "wof:name":"Aelle",
    "wof:placetype":"venue"
},
  "geometry": {"coordinates":[8.9754161835,45.6912460327],"type":"Point"}
}