{
  "type": "Feature",
  "properties": {
    "iso:country":"IT",
    "sg:address":"20124 Milano",
    "sg:city":"Milano",
    "sg:orig_category":"Scuole Di Orientamento, Formazione E Addestramento Professionale",
    "sg:phone":"+39 02 2952 5275",
    "sg:postcode":"20124",
    "sg:province":"Milano",
    "wof:name":"Istituto Il Metodo Srl",
    "wof:placetype":"venue"
},
  "geometry": {"coordinates":[9.212454,45.481895],"type":"Point"}
}