{
  "type": "Feature",
  "properties": {
    "addr:full":"71036 Lucera Lucera Foggia 71036",
    "addr:housenumber":"71036",
    "addr:postcode":"71036",
    "iso:country":"IT",
    "sg:address":"71036 Lucera",
    "sg:city":"Lucera",
    "sg:orig_category":"Bagno - Accessori E Mobili",
    "sg:phone":"+39 0881 522679",
    "sg:postcode":"71036",
    "sg:province":"Foggia",
    "wof:name":"Ce.sa.ba. Di Laboragine Luigi & C. Sas",
    "wof:placetype":"venue"
},
  "geometry": {"coordinates":[15.377068,41.6908],"type":"Point"}
}