{
  "type": "Feature",
  "properties": {
    "addr:full":"Via Modigliani 11 40033 Casalecchio Di Reno Casalecchio di Reno Bologna 40033",
    "addr:housenumber":"11",
    "addr:postcode":"40033;40033",
    "addr:street":"Via Modigliani;Di Reno",
    "iso:country":"IT",
    "sg:address":"Via Modigliani 11 40033 Casalecchio Di Reno",
    "sg:city":"Casalecchio di Reno",
    "sg:classifiers":[
        {
            "category":"Health Services",
            "subcategory":"Nursing And Care Facility",
            "type":"Services"
        }
    ],
    "sg:phone":"+39 051 571725",
    "sg:postcode":"40033",
    "sg:province":"Bologna",
    "sg:tags":[
        "person",
        "disabled",
        "equipment",
        "orthopedic",
        "appliances",
        "aid",
        "rehabilitation"
    ],
    "sg:website":"www.mto.it",
    "wof:name":"M.t.o. Spa",
    "wof:placetype":"venue"
},
  "geometry": {"coordinates":[11.272556,44.466934],"type":"Point"}
}