{
  "type": "Feature",
  "properties": {
    "iso:country":"IT",
    "sg:address":"Piazza Martiri; Casalnoceto",
    "sg:classifiers":[
        {
            "category":"Banks & Credit Unions",
            "subcategory":"Bank",
            "type":"Services"
        }
    ],
    "sg:phone":"+39 0131 809128",
    "wof:name":"Cassa Di Risparmio Di Tortona Spa",
    "wof:placetype":"venue"
},
  "geometry": {"coordinates":[8.983096,44.913548],"type":"Point"}
}