{
  "type": "Feature",
  "properties": {
    "iso:country":"IT",
    "sg:address":"20027 Rescaldina",
    "sg:city":"Rescaldina",
    "sg:orig_category":"Impiantistica E Prodotti Tecnologici Per Edilizia. Forniture Industriali Per Prevenzione, Controllo E Sicurezza",
    "sg:phone":"+39 0331 576261",
    "sg:postcode":"20027",
    "sg:province":"Milano",
    "wof:name":"Gibi Estintori S.r.l.",
    "wof:placetype":"venue"
},
  "geometry": {"coordinates":[9.096965,45.454891],"type":"Point"}
}