{
  "type": "Feature",
  "properties": {
    "addr:full":"80125 Napoli Napoli Napoli 80125",
    "addr:housenumber":"80125",
    "addr:postcode":"80125",
    "iso:country":"IT",
    "sg:address":"80125 Napoli",
    "sg:city":"Napoli",
    "sg:orig_category":"Asfalti, Bitumi Ed Affini",
    "sg:phone":"+39 081 230 1116",
    "sg:postcode":"80125",
    "sg:province":"Napoli",
    "wof:name":"Merollasfalti",
    "wof:placetype":"venue"
},
  "geometry": {"coordinates":[14.181599,40.842457],"type":"Point"}
}