{
  "type": "Feature",
  "properties": {
    "iso:country":"IT",
    "sg:address":"Sda Statale 100/14 Lotto 14 N 13 70010 Casamassima",
    "sg:city":"Casamassima",
    "sg:orig_category":"Ladies' Trousers Suits, Suits, Jackets, Skirts, And Trousers",
    "sg:phone":"+39 080 697 0193",
    "sg:postcode":"70010",
    "sg:province":"Bari",
    "wof:name":"F.lli Magrone Srl",
    "wof:placetype":"venue"
},
  "geometry": {"coordinates":[16.869291,41.126053],"type":"Point"}
}