{
  "type": "Feature",
  "properties": {
    "iso:country":"IT",
    "sg:address":"27058 Voghera",
    "sg:city":"Voghera",
    "sg:orig_category":"Abbigliamento Esterno, Maglierie E Pelliccerie. Shopping",
    "sg:phone":"+39 0383 41453",
    "sg:postcode":"27058",
    "sg:province":"Pavia",
    "sg:website":"http://www.ronchisrl.it",
    "wof:name":"Ronchi Srl",
    "wof:placetype":"venue"
},
  "geometry": {"coordinates":[9.171845,45.196484],"type":"Point"}
}