{
  "type": "Feature",
  "properties": {
    "iso:country":"IT",
    "sg:address":"13, Via Leonardo Da Vinci 35015 Galliera Veneta",
    "sg:city":"Galliera Veneta",
    "sg:classifiers":[
        {
            "category":"Real Estate",
            "subcategory":"Surveying",
            "type":"Services"
        }
    ],
    "sg:phone":"+39 049 596 8808",
    "sg:postcode":"35015",
    "sg:province":"Padova",
    "sg:tags":[
        "equipment",
        "material",
        "good",
        "-",
        "handling"
    ],
    "wof:name":"Gs Scaffalature Engineering (s.p.a.)",
    "wof:placetype":"venue"
},
  "geometry": {"coordinates":[11.857378,45.645008],"type":"Point"}
}