{
  "type": "Feature",
  "properties": {
    "iso:country":"IT",
    "sg:address":"16166 Genova",
    "sg:city":"Genova",
    "sg:orig_category":"Studi E Consulenze Tecniche E Industriali. Consulenze Tecniche, Amministrative E Perizie. Professionisti - Studi E Servizi Ed Associazioni Di Interesse Aziendale",
    "sg:phone":"+39 010 320 2205",
    "sg:postcode":"16166",
    "sg:province":"Genova",
    "wof:name":"Arnulfo Umberto Mario",
    "wof:placetype":"venue"
},
  "geometry": {"coordinates":[9.020555,44.384998],"type":"Point"}
}