{
  "type": "Feature",
  "properties": {
    "iso:country":"IT",
    "sg:address":"50012 Bagno A Ripoli",
    "sg:city":"Bagno a Ripoli",
    "sg:classifiers":[
        {
            "category":"Utilities",
            "subcategory":"Refuse",
            "type":"Services"
        }
    ],
    "sg:phone":"+39 055 651 0053",
    "sg:postcode":"50012",
    "sg:province":"Firenze",
    "sg:tags":[
        "houseware",
        "utensil",
        "linen",
        "blankets",
        "drapery",
        "kitchen"
    ],
    "wof:name":"In Florence Srl",
    "wof:placetype":"venue"
},
  "geometry": {"coordinates":[11.318523,43.753597],"type":"Point"}
}