{
  "type": "Feature",
  "properties": {
    "addr:full":"Via Argine Volano 355/d 44030 Fossalta Ferrara 44030",
    "addr:housenumber":"355 / d",
    "addr:postcode":"44030;44030",
    "addr:street":"Via Argine Volano",
    "iso:country":"IT",
    "sg:address":"Via Argine Volano 355/d 44030 Fossalta",
    "sg:classifiers":[
        {
            "category":"Wholesale",
            "subcategory":"Plants",
            "type":"Manufacturing & Wholesale Goods"
        }
    ],
    "sg:phone":"+39 0532 879600",
    "sg:postcode":"44030",
    "sg:province":"Ferrara",
    "sg:tags":[
        "packaging",
        "machinery"
    ],
    "sg:website":"www.vortexsystems.com",
    "wof:name":"Vortex Sistems Srl",
    "wof:placetype":"venue"
},
  "geometry": {"coordinates":[11.78516,44.84399],"type":"Point"}
}