{
  "type": "Feature",
  "properties": {
    "iso:country":"IT",
    "sg:address":"184, Via Fontana Domenico 80131 Napoli",
    "sg:city":"Napoli",
    "sg:classifiers":[
        {
            "category":"Professional",
            "subcategory":"Engineering",
            "type":"Services"
        }
    ],
    "sg:phone":"+39 081 545 5066",
    "sg:postcode":"80131",
    "sg:province":"Napoli",
    "sg:tags":[
        "machine",
        "-",
        "mechanical"
    ],
    "wof:name":"I.b.i. Idrobioimpianti Srl",
    "wof:placetype":"venue"
},
  "geometry": {"coordinates":[14.224703,40.858696],"type":"Point"}
}