{
  "type": "Feature",
  "properties": {
    "iso:country":"IT",
    "sg:address":"20122 Milano",
    "sg:city":"Milano",
    "sg:orig_category":"Non-classified Establishments",
    "sg:phone":"+39 02 8646 4862",
    "sg:postcode":"20122",
    "sg:province":"Milano",
    "wof:name":"P.a.m. (s.p.a.)",
    "wof:placetype":"venue"
},
  "geometry": {"coordinates":[9.193591,45.464287],"type":"Point"}
}