{
  "type": "Feature",
  "properties": {
    "addr:full":"24047 Treviglio Treviglio Bergamo 24047",
    "addr:postcode":"24047;24047",
    "iso:country":"IT",
    "sg:address":"24047 Treviglio",
    "sg:city":"Treviglio",
    "sg:orig_category":"Motocicli E Motocarri - Commercio E Riparazione",
    "sg:phone":"+39 036 330 4797",
    "sg:postcode":"24047",
    "sg:province":"Bergamo",
    "wof:name":"Centro Del Casco Snc",
    "wof:placetype":"venue"
},
  "geometry": {"coordinates":[9.6712522507,45.7236366272],"type":"Point"}
}