{
  "type": "Feature",
  "properties": {
    "iso:country":"IT",
    "sg:address":"Via Remo Pella 137 13836 Cossato",
    "sg:city":"Cossato",
    "sg:classifiers":[
        {
            "category":"Parking",
            "subcategory":"Lot",
            "type":"Transportation"
        }
    ],
    "sg:phone":"+39 015 982112",
    "sg:postcode":"13836",
    "sg:province":"Biella",
    "sg:tags":[
        "stockinette",
        "yarn"
    ],
    "sg:website":"www.fil-master.com",
    "wof:name":"Fil-master S.r.l.",
    "wof:placetype":"venue"
},
  "geometry": {"coordinates":[8.191726,45.585262],"type":"Point"}
}