{
  "type": "Feature",
  "properties": {
    "iso:country":"IT",
    "sg:address":"Via Iv Novembre, 1; Dolo; 30031",
    "sg:city":"Dolo",
    "sg:classifiers":[
        {
            "category":"Banks & Credit Unions",
            "subcategory":"Bank",
            "type":"Services"
        }
    ],
    "sg:phone":"+39 041 410148",
    "sg:postcode":"30031",
    "sg:province":"Venezia",
    "wof:name":"Banca Del Monte",
    "wof:placetype":"venue"
},
  "geometry": {"coordinates":[12.094584,45.418259],"type":"Point"}
}