{
  "type": "Feature",
  "properties": {
    "addr:full":"31027 Spresiano Spresiano Treviso 31027",
    "addr:postcode":"31027;31027",
    "iso:country":"IT",
    "sg:address":"31027 Spresiano",
    "sg:city":"Spresiano",
    "sg:orig_category":"Servizi E Lavori Per Agricoltura E Zootecnia. Servizi Ausiliari Di Analisi, Controllo E Ricerca",
    "sg:phone":"+39 0422 881968",
    "sg:postcode":"31027",
    "sg:province":"Treviso",
    "wof:name":"Istituto Sperimentale Per La Viticoltura",
    "wof:placetype":"venue"
},
  "geometry": {"coordinates":[12.251046,45.789234],"type":"Point"}
}