{
  "type": "Feature",
  "properties": {
    "iso:country":"IT",
    "sg:address":"41100 Modena",
    "sg:city":"Modena",
    "sg:orig_category":"Assicurazioni E Servizi Assicurativi",
    "sg:phone":"+39 059 219206",
    "sg:postcode":"41100",
    "sg:province":"Modena",
    "wof:name":"Lv Broker Spa",
    "wof:placetype":"venue"
},
  "geometry": {"coordinates":[10.936594,44.641979],"type":"Point"}
}