{
  "type": "Feature",
  "properties": {
    "addr:full":"Regione Prati E Pescine 18011 Arma Di Taggia Imperia 18011",
    "addr:postcode":"18011;18011",
    "addr:street":"Regione Prati E Pescine",
    "iso:country":"IT",
    "sg:address":"Regione Prati E Pescine 18011 Arma Di Taggia",
    "sg:classifiers":[
        {
            "category":"Food & Beverages",
            "subcategory":"Specialty",
            "type":"Retail Goods"
        }
    ],
    "sg:phone":"+39 0184 486044",
    "sg:postcode":"18011",
    "sg:province":"Imperia",
    "sg:tags":[
        "olive-oil"
    ],
    "sg:website":"www.casaoleariataggiasca.it",
    "wof:name":"Casa Olearia Taggiasca Srl",
    "wof:placetype":"venue"
},
  "geometry": {"coordinates":[7.860149,43.840103],"type":"Point"}
}