{
  "type": "Feature",
  "properties": {
    "iso:country":"IT",
    "sg:address":"15, Via S. Filippo 82100 Benevento",
    "sg:city":"Benevento",
    "sg:classifiers":[
        {
            "category":"Manufacturing",
            "subcategory":"Metals",
            "type":"Manufacturing & Wholesale Goods"
        }
    ],
    "sg:phone":"+39 39082454034",
    "sg:postcode":"82100",
    "sg:province":"Benevento",
    "sg:tags":[
        "metallurgy",
        "metalworking"
    ],
    "wof:name":"Maffei Alluminio Di Grimaldi M.grazia",
    "wof:placetype":"venue"
},
  "geometry": {"coordinates":[14.7811737061,41.1304473877],"type":"Point"}
}