{
  "type": "Feature",
  "properties": {
    "addr:full":"80121 Napoli Napoli Napoli 80121",
    "addr:housenumber":"80121",
    "addr:postcode":"80121",
    "iso:country":"IT",
    "sg:address":"80121 Napoli",
    "sg:city":"Napoli",
    "sg:orig_category":"Fotografia Industriale",
    "sg:phone":"+39 081 415738",
    "sg:postcode":"80121",
    "sg:province":"Napoli",
    "wof:name":"Ottaviano Claudio",
    "wof:placetype":"venue"
},
  "geometry": {"coordinates":[14.2686491013,40.9056015015],"type":"Point"}
}