{
  "type": "Feature",
  "properties": {
    "addr:full":"70124 Bari Bari Bari 70124",
    "addr:postcode":"70124;70124",
    "iso:country":"IT",
    "sg:address":"70124 Bari",
    "sg:city":"Bari",
    "sg:orig_category":"Prodotti Alimentari",
    "sg:phone":"+39 080 505 4493",
    "sg:postcode":"70124",
    "sg:province":"Bari",
    "wof:name":"Italsud Frutta Secca (s.r.l.)",
    "wof:placetype":"venue"
},
  "geometry": {"coordinates":[16.8368225098,41.087310791],"type":"Point"}
}