{
  "type": "Feature",
  "properties": {
    "addr:full":"90040 San Cipirello San Cipirello Palermo 90040",
    "addr:housenumber":"90040",
    "addr:postcode":"cipirello;90040",
    "addr:street":"San",
    "iso:country":"IT",
    "sg:address":"90040 San Cipirello",
    "sg:city":"San Cipirello",
    "sg:orig_category":"Automobili - Commercio",
    "sg:phone":"+39 091 857 6636",
    "sg:postcode":"90040",
    "sg:province":"Palermo",
    "wof:name":"Crociata F. & Figlio",
    "wof:placetype":"venue"
},
  "geometry": {"coordinates":[13.178946,37.953144],"type":"Point"}
}