{
  "type": "Feature",
  "properties": {
    "iso:country":"IT",
    "sg:address":"4, V. Indren - Zona Ind. Roccapietra 13019 Varallo",
    "sg:city":"Roccapietra",
    "sg:classifiers":[
        {
            "category":"Shopping",
            "type":"Retail Goods"
        }
    ],
    "sg:phone":"+39 0163 560000",
    "sg:postcode":"13019",
    "sg:province":"Vercelli",
    "sg:tags":[
        "finished",
        "-",
        "metallic"
    ],
    "sg:website":"http://www.ritmonio.com",
    "wof:name":"Rubinetterie Ritmonio Srl",
    "wof:placetype":"venue"
},
  "geometry": {"coordinates":[8.4263935089,45.3210601807],"type":"Point"}
}