{
  "type": "Feature",
  "properties": {
    "addr:full":"549, Via Della Magliana 00148 Roma Roma Roma 00148",
    "addr:housenumber":"549",
    "addr:postcode":"00148;00148",
    "addr:street":"Via Della Magliana",
    "iso:country":"IT",
    "sg:address":"549, Via Della Magliana 00148 Roma",
    "sg:city":"Roma",
    "sg:classifiers":[
        {
            "category":"Manufacturing",
            "subcategory":"Printing",
            "type":"Manufacturing & Wholesale Goods"
        }
    ],
    "sg:phone":"+39 39066539249",
    "sg:postcode":"00148",
    "sg:province":"Roma",
    "sg:tags":[
        "publishing"
    ],
    "wof:name":"Necnocarta 80 Snc",
    "wof:placetype":"venue"
},
  "geometry": {"coordinates":[12.4346218109,41.8337860107],"type":"Point"}
}