{
  "type": "Feature",
  "properties": {
    "addr:full":"30033 Noale Noale Venezia 30033",
    "addr:postcode":"30033;30033",
    "iso:country":"IT",
    "sg:address":"30033 Noale",
    "sg:city":"Noale",
    "sg:orig_category":"Marmo, Pietre Ed Affini",
    "sg:phone":"+39 041 580 0828",
    "sg:postcode":"30033",
    "sg:province":"Venezia",
    "wof:name":"Edilnova Sas",
    "wof:placetype":"venue"
},
  "geometry": {"coordinates":[12.073283,45.552807],"type":"Point"}
}