{
  "type": "Feature",
  "properties": {
    "addr:full":"20122 Milano Milano Milano 20122",
    "addr:postcode":"20122;20122",
    "iso:country":"IT",
    "sg:address":"20122 Milano",
    "sg:city":"Milano",
    "sg:classifiers":[
        {
            "category":"Health Services",
            "subcategory":"Health Practitioner",
            "type":"Services"
        }
    ],
    "sg:phone":"+39 02 5831 0575",
    "sg:postcode":"20122",
    "sg:province":"Milano",
    "sg:tags":[
        "medici"
    ],
    "wof:name":"Podda Mauro",
    "wof:placetype":"venue"
},
  "geometry": {"coordinates":[9.1843719482,45.4554328918],"type":"Point"}
}