{
  "type": "Feature",
  "properties": {
    "addr:full":"2, Via De Vecchi 20090 Assago Assago Milano 20090",
    "addr:postcode":"20090;20090",
    "addr:street":"Via De Vecchi;Assago",
    "iso:country":"IT",
    "sg:address":"2, Via De Vecchi 20090 Assago",
    "sg:city":"Assago",
    "sg:classifiers":[
        {
            "category":"Wholesale",
            "subcategory":"Medical Equipment & Supplies",
            "type":"Manufacturing & Wholesale Goods"
        }
    ],
    "sg:phone":"+39 39024887231",
    "sg:postcode":"20090",
    "sg:province":"Milano",
    "sg:tags":[
        "-",
        "health",
        "instrument"
    ],
    "wof:name":"Biomet Merck Srl",
    "wof:placetype":"venue"
},
  "geometry": {"coordinates":[9.126606,45.410923],"type":"Point"}
}