{
  "type": "Feature",
  "properties": {
    "iso:country":"IT",
    "sg:address":"20123 Milano",
    "sg:city":"Milano",
    "sg:orig_category":"Servizi Al Turismo. Trasporto Pubblico E Privato",
    "sg:phone":"+39 02 806601",
    "sg:postcode":"20123",
    "sg:province":"Milano",
    "wof:name":"Austrian Airlines",
    "wof:placetype":"venue"
},
  "geometry": {"coordinates":[9.190284,45.462231],"type":"Point"}
}