{
  "type": "Feature",
  "properties": {
    "iso:country":"IT",
    "sg:address":"13, Via Scaletta Ugo 10094 Giaveno",
    "sg:city":"Giaveno",
    "sg:classifiers":[
        {
            "category":"Utilities",
            "subcategory":"Electric",
            "type":"Services"
        }
    ],
    "sg:phone":"+39 011 937 8575",
    "sg:postcode":"10094",
    "sg:province":"Torino",
    "sg:tags":[
        "component",
        "electronic"
    ],
    "wof:name":"Ate-electronics Srl",
    "wof:placetype":"venue"
},
  "geometry": {"coordinates":[7.686619,45.07056],"type":"Point"}
}