{
  "type": "Feature",
  "properties": {
    "iso:country":"IT",
    "sg:address":"Via Cassia 1134/b; Roma; 00189",
    "sg:city":"Roma",
    "sg:classifiers":[
        {
            "category":"Banks & Credit Unions",
            "subcategory":"Bank",
            "type":"Services"
        }
    ],
    "sg:phone":"+39 06 303 6692",
    "sg:postcode":"00189",
    "sg:province":"Roma",
    "wof:name":"Rolo Banca 1473 Spa",
    "wof:placetype":"venue"
},
  "geometry": {"coordinates":[12.421782,41.979069],"type":"Point"}
}