{
  "type": "Feature",
  "properties": {
    "iso:country":"IT",
    "sg:address":"41100 Modena",
    "sg:city":"Modena",
    "sg:orig_category":"Macchine, Impianti Ed Attrezzature Per Agricoltura E Zootecnia",
    "sg:phone":"+39 059 468497",
    "sg:postcode":"41100",
    "sg:province":"Modena",
    "wof:name":"Libbra Palmo",
    "wof:placetype":"venue"
},
  "geometry": {"coordinates":[10.93947,44.632458],"type":"Point"}
}