{
  "type": "Feature",
  "properties": {
    "iso:country":"IT",
    "sg:address":"30035 Mirano",
    "sg:city":"Mirano",
    "sg:orig_category":"Carni, Salumi E Pesci",
    "sg:phone":"+39 041 431752",
    "sg:postcode":"30035",
    "sg:province":"Venezia",
    "wof:name":"Spolaore Fratelli",
    "wof:placetype":"venue"
},
  "geometry": {"coordinates":[12.165472,45.491039],"type":"Point"}
}