{
  "type": "Feature",
  "properties": {
    "addr:full":"6, Via Freud Sigmund 09126 Cagliari Cagliari Cagliari 09126",
    "addr:postcode":"09126;09126",
    "addr:street":"Via Freud Sigmund",
    "iso:country":"IT",
    "sg:address":"6, Via Freud Sigmund 09126 Cagliari",
    "sg:city":"Cagliari",
    "sg:classifiers":[
        {
            "category":"Manufacturing",
            "subcategory":"Tools & Machinery",
            "type":"Manufacturing & Wholesale Goods"
        }
    ],
    "sg:phone":"+39 39070343026",
    "sg:postcode":"09126",
    "sg:province":"Cagliari",
    "sg:tags":[
        "environment",
        "equipment",
        "-"
    ],
    "wof:name":"Consorzio Servizi Imprese Riunite Co.s.ir. Societa' Consortile A Responsabil",
    "wof:placetype":"venue"
},
  "geometry": {"coordinates":[9.109228,39.215458],"type":"Point"}
}