{
  "type": "Feature",
  "properties": {
    "addr:full":"80035 Nola Nola Napoli 80035",
    "addr:housenumber":"80035",
    "addr:postcode":"80035",
    "addr:street":"Nola",
    "iso:country":"IT",
    "sg:address":"80035 Nola",
    "sg:city":"Nola",
    "sg:orig_category":"Autoscuole",
    "sg:phone":"+39 081 823 7446",
    "sg:postcode":"80035",
    "sg:province":"Napoli",
    "wof:name":"Autoscuola Centrale 2",
    "wof:placetype":"venue"
},
  "geometry": {"coordinates":[14.513097,40.933453],"type":"Point"}
}