{
  "type": "Feature",
  "properties": {
    "addr:full":"95031 Adrano Adrano Catania 95031",
    "addr:postcode":"95031;95031",
    "iso:country":"IT",
    "sg:address":"95031 Adrano",
    "sg:city":"Adrano",
    "sg:orig_category":"Dolciumi E Gelati",
    "sg:phone":"+39 095 688418",
    "sg:postcode":"95031",
    "sg:province":"Catania",
    "wof:name":"Lo Cicero Antonio",
    "wof:placetype":"venue"
},
  "geometry": {"coordinates":[15.07762,37.524593],"type":"Point"}
}