{
  "type": "Feature",
  "properties": {
    "addr:full":"20141 Milano Milano Milano 20141",
    "addr:postcode":"20141;20141",
    "iso:country":"IT",
    "sg:address":"20141 Milano",
    "sg:city":"Milano",
    "sg:orig_category":"Scuole E Servizi Scolastici. Servizi Per Lo Sport E Il Tempo Libero",
    "sg:postcode":"20141",
    "sg:province":"Milano",
    "wof:name":"Il Classico Scuola Di Musica Per Pianoforte Di Kina Karaca",
    "wof:placetype":"venue"
},
  "geometry": {"coordinates":[9.178571,45.439732],"type":"Point"}
}