{
  "type": "Feature",
  "properties": {
    "addr:full":"2, Contrada Lavandaia 86022 Limosano Limosano Campobasso 86022",
    "addr:postcode":"86022;86022",
    "addr:street":"Contrada Lavandaia",
    "iso:country":"IT",
    "sg:address":"2, Contrada Lavandaia 86022 Limosano",
    "sg:city":"Limosano",
    "sg:classifiers":[
        {
            "category":"Utilities",
            "subcategory":"Electric",
            "type":"Services"
        }
    ],
    "sg:phone":"+39 0874 701249",
    "sg:postcode":"86022",
    "sg:province":"Campobasso",
    "sg:tags":[
        "component",
        "electronic"
    ],
    "wof:name":"I.mi.l.plast S.r.l.",
    "wof:placetype":"venue"
},
  "geometry": {"coordinates":[14.633149,41.658295],"type":"Point"}
}