{
  "type": "Feature",
  "properties": {
    "addr:full":"20094 Corsico Corsico Milano 20094",
    "addr:postcode":"20094;20094",
    "iso:country":"IT",
    "sg:address":"20094 Corsico",
    "sg:city":"Corsico",
    "sg:orig_category":"Serramenti Ed Infissi. Prodotti Vari In Metallo",
    "sg:phone":"+39 02 4860 1236",
    "sg:postcode":"20094",
    "sg:province":"Milano",
    "wof:name":"Elebak 2 Srl",
    "wof:placetype":"venue"
},
  "geometry": {"coordinates":[9.106134,45.447037],"type":"Point"}
}