{
  "type": "Feature",
  "properties": {
    "iso:country":"IT",
    "sg:address":"Viale Matteotti, 1; Reggio Emilia; 42100",
    "sg:classifiers":[
        {
            "category":"Banks & Credit Unions",
            "subcategory":"Bank",
            "type":"Services"
        }
    ],
    "sg:phone":"+39 0522 39044",
    "sg:postcode":"42100",
    "sg:province":"Reggio Nell'Emilia",
    "wof:name":"Banca Popolare Dell'emilia",
    "wof:placetype":"venue"
},
  "geometry": {"coordinates":[10.64089,44.694332],"type":"Point"}
}