{
  "type": "Feature",
  "properties": {
    "addr:full":"48014 Castel Bolognese Castel Bolognese Ravenna 48014",
    "addr:postcode":"48014;48014",
    "iso:country":"IT",
    "sg:address":"48014 Castel Bolognese",
    "sg:city":"Castel Bolognese",
    "sg:orig_category":"Prodotti Finiti Stampati. Forniture Per Uffici",
    "sg:phone":"+39 0546 656323",
    "sg:postcode":"48014",
    "sg:province":"Ravenna",
    "wof:name":"Modul Diagram S.r.l.",
    "wof:placetype":"venue"
},
  "geometry": {"coordinates":[11.7865657806,44.3242454529],"type":"Point"}
}