{
  "type": "Feature",
  "properties": {
    "iso:country":"IT",
    "sg:address":"72015 Fasano",
    "sg:city":"Fasano",
    "sg:orig_category":"Alberghi E Strutture Extra Alberghiere. Ospedali E Servizi Sanitari",
    "sg:phone":"+39 080 443 1022",
    "sg:postcode":"72015",
    "sg:province":"Brindisi",
    "wof:name":"Casa Del Sole",
    "wof:placetype":"venue"
},
  "geometry": {"coordinates":[17.359219,40.835384],"type":"Point"}
}