{
  "type": "Feature",
  "properties": {
    "addr:full":"34, Via Benedetti 31018 Gaiarine Gaiarine Treviso 31018",
    "addr:postcode":"31018;31018",
    "addr:street":"Via Benedetti",
    "iso:country":"IT",
    "sg:address":"34, Via Benedetti 31018 Gaiarine",
    "sg:city":"Gaiarine",
    "sg:classifiers":[
        {
            "category":"Shopping",
            "subcategory":"Computers & Home Electronics",
            "type":"Retail Goods"
        }
    ],
    "sg:phone":"+39 0434 768365",
    "sg:postcode":"31018",
    "sg:province":"Treviso",
    "sg:tags":[
        "electronic",
        "electrical",
        "equipment"
    ],
    "wof:name":"Nordelettronica S.n.c.",
    "wof:placetype":"venue"
},
  "geometry": {"coordinates":[12.504429,45.90255],"type":"Point"}
}