{
  "type": "Feature",
  "properties": {
    "iso:country":"IT",
    "sg:address":"40033 Casalecchio Di Reno",
    "sg:city":"Casalecchio di Reno",
    "sg:orig_category":"Forniture Alle Strutture Ricettive. Macchine E Impianti Per Attivita' Commerciali Ed Artigianali",
    "sg:phone":"+39 051 611 1011",
    "sg:postcode":"40033",
    "sg:province":"Bologna",
    "wof:name":"La Spaziale Spa",
    "wof:placetype":"venue"
},
  "geometry": {"coordinates":[11.2713508606,44.4610137939],"type":"Point"}
}