{
  "type": "Feature",
  "properties": {
    "iso:country":"IT",
    "sg:address":"7, Via Dell' Aeroporto Petrignano D'assisi 06081 Assisi",
    "sg:city":"Assisi",
    "sg:classifiers":[
        {
            "category":"Bars & Pubs",
            "subcategory":"Nightclub",
            "type":"Food & Drink"
        }
    ],
    "sg:phone":"+39 390 758 0351",
    "sg:postcode":"06081",
    "sg:province":"Perugia",
    "sg:tags":[
        "cake",
        "bread"
    ],
    "wof:name":"Colussi Perugia Spa",
    "wof:placetype":"venue"
},
  "geometry": {"coordinates":[12.521363,43.097134],"type":"Point"}
}