{
  "type": "Feature",
  "properties": {
    "addr:full":"Via Vallina Orticella 38 31030 Borso Del Grappa Borso del Grappa Treviso 31030",
    "addr:housenumber":"38",
    "addr:postcode":"31030;31030",
    "addr:street":"Via Vallina Orticella",
    "iso:country":"IT",
    "sg:address":"Via Vallina Orticella 38 31030 Borso Del Grappa",
    "sg:city":"Borso del Grappa",
    "sg:classifiers":[
        {
            "category":"Manufacturing",
            "subcategory":"Printing",
            "type":"Manufacturing & Wholesale Goods"
        }
    ],
    "sg:phone":"+39 0423 542249",
    "sg:postcode":"31030",
    "sg:province":"Treviso",
    "sg:tags":[
        "plastic"
    ],
    "wof:name":"Lat Srl",
    "wof:placetype":"venue"
},
  "geometry": {"coordinates":[11.8056688309,45.8143348694],"type":"Point"}
}