{
  "type": "Feature",
  "properties": {
    "iso:country":"IT",
    "sg:address":"45010 Pettorazza",
    "sg:orig_category":"Valvole E Apparecchiature Di Misura. Forniture Per Attivita' Industriali",
    "sg:phone":"+39 0426 504117",
    "sg:postcode":"45010",
    "sg:province":"Rovigo",
    "wof:name":"Effe Emme Snc Di Ferro Nazzareno & C.",
    "wof:placetype":"venue"
},
  "geometry": {"coordinates":[11.789797,45.070736],"type":"Point"}
}