{
  "type": "Feature",
  "properties": {
    "addr:full":"12018 Roccavione Roccavione Cuneo 12018",
    "addr:postcode":"12018;12018",
    "iso:country":"IT",
    "sg:address":"12018 Roccavione",
    "sg:city":"Roccavione",
    "sg:orig_category":"Dolciumi E Gelati",
    "sg:phone":"+39 0171 264245",
    "sg:postcode":"12018",
    "sg:province":"Cuneo",
    "wof:name":"Cuba Spa",
    "wof:placetype":"venue"
},
  "geometry": {"coordinates":[7.470593,44.296619],"type":"Point"}
}