{
  "type": "Feature",
  "properties": {
    "addr:full":"20040 Cornate D'adda Milano 20040",
    "addr:postcode":"20040;20040",
    "iso:country":"IT",
    "sg:address":"20040 Cornate D'adda",
    "sg:orig_category":"Prodotti Chimici Secondari. Servizi E Lavori Industria Chimica. Servizi E Lavori Per Ecologia E Smaltimento Rifiuti. Macchine E Forniture Per Ecologia E Smaltimento Rifiuti. Servizi Ausiliari Di Sorve",
    "sg:phone":"+39 039 692 7008",
    "sg:postcode":"20040",
    "sg:province":"Milano",
    "wof:name":"Bottarelli Luciano E C. (s.n.c.)",
    "wof:placetype":"venue"
},
  "geometry": {"coordinates":[9.4801969528,45.6380500793],"type":"Point"}
}