{
  "type": "Feature",
  "properties": {
    "iso:country":"IT",
    "sg:address":"10147 Torino",
    "sg:city":"Torino",
    "sg:classifiers":[
        {
            "category":"Education",
            "subcategory":"School",
            "type":"Public Place"
        }
    ],
    "sg:phone":"+39 011 226 8085",
    "sg:postcode":"10147",
    "sg:province":"Torino",
    "sg:tags":[
        "scuole",
        "informatica",
        "di"
    ],
    "sg:website":"http://www.istitutocentro.it",
    "wof:name":"Istituto Centro Snc",
    "wof:placetype":"venue"
},
  "geometry": {"coordinates":[7.665437,45.103443],"type":"Point"}
}