{
  "type": "Feature",
  "properties": {
    "iso:country":"IT",
    "sg:address":"93013 Mazzarino",
    "sg:city":"Mazzarino",
    "sg:orig_category":"Abbigliamento Intimo, Calze E Costumi Da Bagno",
    "sg:phone":"+39 0934 382003",
    "sg:postcode":"93013",
    "sg:province":"Caltanissetta",
    "wof:name":"Quattrocchi Maria",
    "wof:placetype":"venue"
},
  "geometry": {"coordinates":[14.262851,37.258701],"type":"Point"}
}