{
  "type": "Feature",
  "properties": {
    "addr:full":"50051 Castelfiorentino Castelfiorentino Firenze 50051",
    "addr:postcode":"50051;50051",
    "iso:country":"IT",
    "sg:address":"50051 Castelfiorentino",
    "sg:city":"Castelfiorentino",
    "sg:orig_category":"Arredo Cucina Ed Elettrodomestici",
    "sg:phone":"+39 0571 61114",
    "sg:postcode":"50051",
    "sg:province":"Firenze",
    "sg:website":"http://www.essepiemme.it",
    "wof:name":"Essepiemme Mobili Srl",
    "wof:placetype":"venue"
},
  "geometry": {"coordinates":[10.987962,43.591911],"type":"Point"}
}