{
  "type": "Feature",
  "properties": {
    "addr:full":"20144 Milano Milano Milano 20144",
    "addr:postcode":"20144;20144",
    "iso:country":"IT",
    "sg:address":"20144 Milano",
    "sg:city":"Milano",
    "sg:orig_category":"Assicurazioni E Servizi Assicurativi",
    "sg:phone":"+39 02 4800 6678",
    "sg:postcode":"20144",
    "sg:province":"Milano",
    "wof:name":"On Line Insurance Broker S.r.l.",
    "wof:placetype":"venue"
},
  "geometry": {"coordinates":[9.161741,45.466339],"type":"Point"}
}