{
  "type": "Feature",
  "properties": {
    "addr:full":"3, Via Ramazzini Bernardino 20129 Milano Milano Milano 20129",
    "addr:postcode":"20129;20129",
    "addr:street":"Via Ramazzini Bernardino",
    "iso:country":"IT",
    "sg:address":"3, Via Ramazzini Bernardino 20129 Milano",
    "sg:city":"Milano",
    "sg:classifiers":[
        {
            "category":"Shopping",
            "subcategory":"Computers & Home Electronics",
            "type":"Retail Goods"
        }
    ],
    "sg:phone":"+39 02 2953 3056",
    "sg:postcode":"20129",
    "sg:province":"Milano",
    "sg:tags":[
        "electronic",
        "electrical",
        "equipment"
    ],
    "wof:name":"Eurocon Srl",
    "wof:placetype":"venue"
},
  "geometry": {"coordinates":[9.211062,45.475208],"type":"Point"}
}