{
  "type": "Feature",
  "properties": {
    "iso:country":"IT",
    "sg:address":"24061 Albano Sant'alessandro",
    "sg:orig_category":"Prodotti Alimentari",
    "sg:phone":"+39 035 423 9311",
    "sg:postcode":"24061",
    "sg:province":"Bergamo",
    "sg:website":"http://www.lactis.it",
    "wof:name":"Lactis Spa",
    "wof:placetype":"venue"
},
  "geometry": {"coordinates":[9.7505903244,45.6871337891],"type":"Point"}
}