{
  "type": "Feature",
  "properties": {
    "addr:full":"1, Via Xxiv Maggio 64011 Alba Adriatica Alba Adriatica Teramo 64011",
    "addr:postcode":"64011;64011",
    "addr:street":"Via Xxiv Maggio",
    "iso:country":"IT",
    "sg:address":"1, Via Xxiv Maggio 64011 Alba Adriatica",
    "sg:city":"Alba Adriatica",
    "sg:classifiers":[
        {
            "category":"Food & Beverages",
            "subcategory":"Groceries & Convenience Stores",
            "type":"Retail Goods"
        }
    ],
    "sg:phone":"+39 0861 714307",
    "sg:postcode":"64011",
    "sg:province":"Teramo",
    "sg:tags":[
        "product",
        "related"
    ],
    "wof:name":"Alba Carni (s.r.l.)",
    "wof:placetype":"venue"
},
  "geometry": {"coordinates":[13.6985311508,42.6612701416],"type":"Point"}
}