{
  "type": "Feature",
  "properties": {
    "iso:country":"IT",
    "sg:address":"20090 Trezzano Sul Naviglio",
    "sg:city":"Trezzano sul Naviglio",
    "sg:orig_category":"Elettrotecnica Industriale, Prodotti E Apparecchiature",
    "sg:phone":"+39 02 4847 4001",
    "sg:postcode":"20090",
    "sg:province":"Milano",
    "wof:name":"Feam S.p.a. Forniture Elettriche Antideflagranti Milano",
    "wof:placetype":"venue"
},
  "geometry": {"coordinates":[9.047158,45.427357],"type":"Point"}
}