{
  "type": "Feature",
  "properties": {
    "iso:country":"IT",
    "sg:address":"17019 Varazze",
    "sg:city":"Varazze",
    "sg:orig_category":"Alberghi E Strutture Extra Alberghiere. Ospedali E Servizi Sanitari",
    "sg:phone":"+39 019 934193",
    "sg:postcode":"17019",
    "sg:province":"Savona",
    "wof:name":"Opera Bergamasca Per La Salute Dei Fanciulli",
    "wof:placetype":"venue"
},
  "geometry": {"coordinates":[8.561114,44.389042],"type":"Point"}
}