{
  "type": "Feature",
  "properties": {
    "iso:country":"IT",
    "sg:address":"23899 Robbiate",
    "sg:city":"Robbiate",
    "sg:orig_category":"Servizi E Lavori Per Agricoltura E Zootecnia",
    "sg:phone":"+39 039 510617",
    "sg:postcode":"23899",
    "sg:province":"Lecco",
    "wof:name":"Borgonovo Luigi",
    "wof:placetype":"venue"
},
  "geometry": {"coordinates":[9.460496,45.80275],"type":"Point"}
}