{
  "type": "Feature",
  "properties": {
    "addr:full":"00044 Frascati Frascati Roma 00044",
    "addr:postcode":"00044;00044",
    "iso:country":"IT",
    "sg:address":"00044 Frascati",
    "sg:city":"Frascati",
    "sg:orig_category":"Pubblica Amministrazione",
    "sg:phone":"+39 06 942 6679",
    "sg:postcode":"00044",
    "sg:province":"Roma",
    "wof:name":"Comando Tenenza Gdf Frascati",
    "wof:placetype":"venue"
},
  "geometry": {"coordinates":[12.6733007431,41.8232955933],"type":"Point"}
}