{
  "type": "Feature",
  "properties": {
    "iso:country":"IT",
    "sg:address":"41, Via Provinciale 47016 Predappio",
    "sg:city":"Predappio",
    "sg:classifiers":[
        {
            "category":"Personal",
            "subcategory":"Shoe Repair & Shine",
            "type":"Services"
        }
    ],
    "sg:phone":"+39 0543 940024",
    "sg:postcode":"47016",
    "sg:province":"Forl\u00ec-Cesena",
    "sg:tags":[
        "leather"
    ],
    "wof:name":"Tacchificio Del Rabbi (s.p.a.)",
    "wof:placetype":"venue"
},
  "geometry": {"coordinates":[11.981455,44.102139],"type":"Point"}
}