{
  "type": "Feature",
  "properties": {
    "addr:full":"70052 Bisceglie Bisceglie Bari 70052",
    "addr:postcode":"70052;70052",
    "iso:country":"IT",
    "sg:address":"70052 Bisceglie",
    "sg:city":"Bisceglie",
    "sg:orig_category":"Associazioni Ed Istituti Di Previdenza Ed Assistenza",
    "sg:phone":"+39 080 392 4773",
    "sg:postcode":"70052",
    "sg:province":"Bari",
    "wof:name":"Centro Anziani Storelli",
    "wof:placetype":"venue"
},
  "geometry": {"coordinates":[16.499325,41.238216],"type":"Point"}
}