{
  "type": "Feature",
  "properties": {
    "iso:country":"IT",
    "sg:address":"20032 Cormano",
    "sg:city":"Cormano",
    "sg:orig_category":"Forniture Per Abbigliamento E Pelletterie. Complementi Di Arredamento",
    "sg:phone":"+39 02 614 0769",
    "sg:postcode":"20032",
    "sg:province":"Milano",
    "wof:name":"Andrea Bilics E C. S.r.l.",
    "wof:placetype":"venue"
},
  "geometry": {"coordinates":[9.1812992096,45.5423278809],"type":"Point"}
}