{
  "type": "Feature",
  "properties": {
    "iso:country":"IT",
    "sg:address":"Piazza Del Popolo 8; Vittorio Veneto; 31029",
    "sg:city":"Vittorio Veneto",
    "sg:classifiers":[
        {
            "category":"Banks & Credit Unions",
            "subcategory":"Bank",
            "type":"Services"
        }
    ],
    "sg:phone":"+39 0438 53045",
    "sg:postcode":"31029",
    "sg:province":"Treviso",
    "wof:name":"Banco Ambrosiano Veneto Spa",
    "wof:placetype":"venue"
},
  "geometry": {"coordinates":[12.295274,45.989464],"type":"Point"}
}