{
  "type": "Feature",
  "properties": {
    "addr:full":"Via E. Caldara 1 20090 Trezzano Sul Naviglio Trezzano sul Naviglio Milano 20090",
    "addr:housenumber":"1",
    "addr:postcode":"20090;20090",
    "addr:street":"Via E. Caldara",
    "iso:country":"IT",
    "sg:address":"Via E. Caldara 1 20090 Trezzano Sul Naviglio",
    "sg:city":"Trezzano sul Naviglio",
    "sg:orig_category":"Stickers Stick-on Labels",
    "sg:phone":"+39 02 4840 2174",
    "sg:postcode":"20090",
    "sg:province":"Milano",
    "sg:website":"www.roladhesiv.com",
    "wof:name":"Roladhesiv Spa",
    "wof:placetype":"venue"
},
  "geometry": {"coordinates":[9.053672,45.420677],"type":"Point"}
}