{
  "type": "Feature",
  "properties": {
    "addr:full":"24040 Canonica D'adda Bergamo 24040",
    "addr:postcode":"24040;24040",
    "iso:country":"IT",
    "sg:address":"24040 Canonica D'adda",
    "sg:orig_category":"Macchine, Impianti Ed Attrezzature Industria Delle Materie Plastiche E Gomma",
    "sg:phone":"+39 02 909 5216",
    "sg:postcode":"24040",
    "sg:province":"Bergamo",
    "wof:name":"A.t.t. (s.n.c.)",
    "wof:placetype":"venue"
},
  "geometry": {"coordinates":[9.546771,45.577408],"type":"Point"}
}