{
  "type": "Feature",
  "properties": {
    "iso:country":"IT",
    "sg:address":"6/d, Via R.bacchini 40026 Imola",
    "sg:city":"Imola",
    "sg:classifiers":[
        {
            "category":"Shopping",
            "subcategory":"Computers & Home Electronics",
            "type":"Retail Goods"
        }
    ],
    "sg:phone":"+39 0542 642726",
    "sg:postcode":"40026",
    "sg:province":"Bologna",
    "sg:tags":[
        "electronic",
        "electrical",
        "equipment"
    ],
    "wof:name":"Imola Vending S.a.s.",
    "wof:placetype":"venue"
},
  "geometry": {"coordinates":[11.346481,44.494221],"type":"Point"}
}