{
  "type": "Feature",
  "properties": {
    "iso:country":"IT",
    "sg:address":"29100 Piacenza",
    "sg:city":"Piacenza",
    "sg:orig_category":"Forniture Per Edilizia E Lavori Pubblici",
    "sg:phone":"+39 0523 332630",
    "sg:postcode":"29100",
    "sg:province":"Piacenza",
    "wof:name":"M.e.r (s.n.c.)",
    "wof:placetype":"venue"
},
  "geometry": {"coordinates":[10.1211681366,45.2473983765],"type":"Point"}
}