{
  "type": "Feature",
  "properties": {
    "iso:country":"IT",
    "sg:address":"20096 Pioltello",
    "sg:city":"Pioltello",
    "sg:orig_category":"Zootecnia E Pesca, Allevamento Piccoli Animali",
    "sg:phone":"+39 02 9210 2388",
    "sg:postcode":"20096",
    "sg:province":"Milano",
    "wof:name":"Redemagni Ambrogio",
    "wof:placetype":"venue"
},
  "geometry": {"coordinates":[9.330512,45.501678],"type":"Point"}
}