{
  "type": "Feature",
  "properties": {
    "iso:country":"IT",
    "sg:address":"Via Di Bilucio 22 55015 Montecarlo",
    "sg:city":"Montecarlo",
    "sg:orig_category":"Ladies' Shoes",
    "sg:phone":"+39 0583 277316",
    "sg:postcode":"55015",
    "sg:province":"Lucca",
    "wof:name":"Clanto S.r.l.",
    "wof:placetype":"venue"
},
  "geometry": {"coordinates":[10.646501,43.830635],"type":"Point"}
}